{
  "type": "Feature",
  "properties": {
    "iso:country":"GB",
    "wof:name":"BB4 8JJ",
    "wof:placetype":"postalcode"
},
  "geometry": {"coordinates":[-2.29043179938655,53.7072673950023],"type":"Point"}
}