{
  "type": "Feature",
  "properties": {
    "date:inception_lower":"1980-01-01",
    "date:inception_upper":"1980-01-31",
    "iso:country":"GB",
    "wof:name":"NE47 9QR",
    "wof:placetype":"postalcode"
},
  "geometry": {"coordinates":[-2.270052,54.914478],"type":"Point"}
}