{
  "type": "Feature",
  "properties": {
    "iso:country": "GB",
    "wof:name": "NE47 9QR",
    "wof:placetype": "postalcode"
  },
  "geometry": {"coordinates":[-2.270052,54.914478],"type":"Point"}
}
