{
  "type": "Feature",
  "properties": {
    "iso:country":"GB",
    "wof:name":"NE47 9QR",
    "wof:placetype":"postalcode"
},
  "geometry": {"coordinates":[-2.27005169997988,54.91447800854835],"type":"Point"}
}