{
  "type": "Feature",
  "properties": {
    "iso:country": "GB",
    "wof:name": "PO32 6GD",
    "wof:placetype": "postalcode"
  },
  "geometry": {"coordinates":[-1.281306,50.746124],"type":"Point"}
}
