{
  "type": "Feature",
  "properties": {
    "iso:country":"GB",
    "wof:name":"CO5 8DG",
    "wof:placetype":"postalcode"
},
  "geometry": {"coordinates":[0.91423393080802,51.78053495235582],"type":"Point"}
}