{
  "type": "Feature",
  "properties": {
    "iso:country":"GB",
    "wof:name":"B45 0PD",
    "wof:placetype":"postalcode"
},
  "geometry": {"coordinates":[-2.00213128941979,52.40463488631499],"type":"Point"}
}