{
  "type": "Feature",
  "properties": {
    "iso:country":"GB",
    "wof:name":"SA17 5PE",
    "wof:placetype":"postalcode"
},
  "geometry": {"coordinates":[-4.26956157975109,51.77524767422467],"type":"Point"}
}