{
  "type": "Feature",
  "properties": {
    "date:inception_lower": "1980-01-01",
    "date:inception_upper": "1980-01-01",
    "iso:country": "GB",
    "wof:name": "SA17 5PE",
    "wof:placetype": "postalcode"
  },
  "geometry": {"coordinates":[-4.275083,51.774762],"type":"Point"}
}
