{
  "type": "Feature",
  "properties": {
    "date:inception_lower":"1980-01-01",
    "date:inception_upper":"1980-01-31",
    "iso:country":"GB",
    "wof:name":"SW1W 8HA",
    "wof:placetype":"postalcode"
},
  "geometry": {"coordinates":[-0.155927,51.49378],"type":"Point"}
}