{
  "type": "Feature",
  "properties": {
    "iso:country":"GB",
    "wof:name":"SW1W 8HA",
    "wof:placetype":"postalcode"
},
  "geometry": {"coordinates":[-0.15592732387491,51.49378050012178],"type":"Point"}
}