{
  "type": "Feature",
  "properties": {
    "iso:country":"GB",
    "wof:name":"BH8 8FE",
    "wof:placetype":"postalcode"
},
  "geometry": {"coordinates":[-1.85574669151307,50.73206319737268],"type":"Point"}
}