{
  "type": "Feature",
  "properties": {
    "date:inception_lower":"2008-06-01",
    "date:inception_upper":"2008-06-30",
    "iso:country":"GB",
    "wof:name":"BH8 8FE",
    "wof:placetype":"postalcode"
},
  "geometry": {"coordinates":[-1.855747,50.732063],"type":"Point"}
}