{
  "type": "Feature",
  "properties": {
    "iso:country":"GB",
    "wof:name":"TR27 6LZ",
    "wof:placetype":"postalcode"
},
  "geometry": {"coordinates":[-5.45766838597501,50.16386472160622],"type":"Point"}
}