{
  "type": "Feature",
  "properties": {
    "date:inception_lower": "1980-01-01",
    "date:inception_upper": "1980-01-01",
    "iso:country": "GB",
    "wof:name": "TR27 6LZ",
    "wof:placetype": "postalcode"
  },
  "geometry": {"coordinates":[-5.457721,50.163855],"type":"Point"}
}
