{
  "type": "Feature",
  "properties": {
    "iso:country":"GB",
    "wof:name":"SW20 9EU",
    "wof:placetype":"postalcode"
},
  "geometry": {"coordinates":[-0.2125012705327,51.40675464718894],"type":"Point"}
}