{
  "type": "Feature",
  "properties": {
    "iso:country":"GB",
    "wof:name":"GU52 0ZD",
    "wof:placetype":"postalcode"
},
  "geometry": {"coordinates":[-0.85187694557247,51.25940484191248],"type":"Point"}
}