{
  "type": "Feature",
  "properties": {
    "iso:country":"GB",
    "wof:name":"KA2 0AH",
    "wof:placetype":"postalcode"
},
  "geometry": {"coordinates":[-4.5382447774542,55.59814420605264],"type":"Point"}
}