{
  "type": "Feature",
  "properties": {
    "iso:country":"GB",
    "wof:name":"NN14 6BD",
    "wof:placetype":"postalcode"
},
  "geometry": {"coordinates":[-0.79533202129351,52.4225855703416],"type":"Point"}
}