{
  "type": "Feature",
  "properties": {
    "iso:country":"GB",
    "wof:name":"CT5 2LP",
    "wof:placetype":"postalcode"
},
  "geometry": {"coordinates":[1.06194552342895,51.36304136708031],"type":"Point"}
}