{
  "type": "Feature",
  "properties": {
    "date:inception_lower": "1980-01-01",
    "date:inception_upper": "1980-01-01",
    "iso:country": "GB",
    "wof:name": "CT5 2LP",
    "wof:placetype": "postalcode"
  },
  "geometry": {"coordinates":[1.061946,51.363041],"type":"Point"}
}
