{
  "type": "Feature",
  "properties": {
    "iso:country":"GB",
    "wof:name":"S36 1GB",
    "wof:placetype":"postalcode"
},
  "geometry": {"coordinates":[-1.60624408503101,53.4755333763442],"type":"Point"}
}