{
  "type": "Feature",
  "properties": {
    "date:inception_lower": "1991-09-01",
    "date:inception_upper": "1991-09-01",
    "iso:country": "GB",
    "wof:name": "HD4 7AW",
    "wof:placetype": "postalcode"
  },
  "geometry": {"coordinates":[-1.810464,53.619081],"type":"Point"}
}
