{
  "type": "Feature",
  "properties": {
    "iso:country":"GB",
    "wof:name":"SW15 6AD",
    "wof:placetype":"postalcode"
},
  "geometry": {"coordinates":[-0.21957997923432,51.45770617382684],"type":"Point"}
}