{
  "type": "Feature",
  "properties": {
    "iso:country": "GB",
    "wof:name": "SW15 6AD",
    "wof:placetype": "postalcode"
  },
  "geometry": {"coordinates":[-0.21958,51.457706],"type":"Point"}
}
