{
  "type": "Feature",
  "properties": {
    "iso:country":"GB",
    "wof:name":"HR1 1QL",
    "wof:placetype":"postalcode"
},
  "geometry": {"coordinates":[-2.68809695409538,52.05839368808966],"type":"Point"}
}