{
  "type": "Feature",
  "properties": {
    "iso:country":"GB",
    "wof:name":"SA20 0HW",
    "wof:placetype":"postalcode"
},
  "geometry": {"coordinates":[-3.84295344858589,52.0192821442505],"type":"Point"}
}