{
  "type": "Feature",
  "properties": {
    "iso:country": "GB",
    "wof:name": "MK5 6AZ",
    "wof:placetype": "postalcode"
  },
  "geometry": {"coordinates":[-0.779533,52.022762],"type":"Point"}
}
