{
  "type": "Feature",
  "properties": {
    "date:inception_lower": "1990-02-01",
    "date:inception_upper": "1990-02-01",
    "iso:country": "GB",
    "wof:name": "MK5 6AZ",
    "wof:placetype": "postalcode"
  },
  "geometry": {"coordinates":[-0.779533,52.022762],"type":"Point"}
}
