{
  "type": "Feature",
  "properties": {
    "date:inception_lower":"1980-01-01",
    "date:inception_upper":"1980-01-31",
    "iso:country":"GB",
    "wof:name":"NE61 4EY",
    "wof:placetype":"postalcode"
},
  "geometry": {"coordinates":[-1.866136,55.152136],"type":"Point"}
}