{
  "type": "Feature",
  "properties": {
    "iso:country":"GB",
    "wof:name":"NE61 4EY",
    "wof:placetype":"postalcode"
},
  "geometry": {"coordinates":[-1.86613646492417,55.15213624613907],"type":"Point"}
}