{
  "type": "Feature",
  "properties": {
    "iso:country": "GB",
    "wof:name": "BH12 4NB",
    "wof:placetype": "postalcode"
  },
  "geometry": {"coordinates":[-1.940973,50.749698],"type":"Point"}
}
