{
  "type": "Feature",
  "properties": {
    "iso:country":"GB",
    "wof:name":"CV8 1EA",
    "wof:placetype":"postalcode"
},
  "geometry": {"coordinates":[-1.57938920167846,52.34253867878451],"type":"Point"}
}