{
  "type": "Feature",
  "properties": {
    "iso:country":"GB",
    "wof:name":"SM4 6NP",
    "wof:placetype":"postalcode"
},
  "geometry": {"coordinates":[-0.19554879295882,51.38228673982147],"type":"Point"}
}