{
  "type": "Feature",
  "properties": {
    "iso:country":"GB",
    "wof:name":"B13 8HT",
    "wof:placetype":"postalcode"
},
  "geometry": {"coordinates":[-1.88764819383735,52.4481025842277],"type":"Point"}
}