{
  "type": "Feature",
  "properties": {
    "iso:country": "GB",
    "wof:name": "WF9 3RA",
    "wof:placetype": "postalcode"
  },
  "geometry": {"coordinates":[-1.323728,53.589323],"type":"Point"}
}
