{
  "type": "Feature",
  "properties": {
    "iso:country": "GB",
    "wof:name": "NG1 1QE",
    "wof:placetype": "postalcode"
  },
  "geometry": {"coordinates":[-1.144702,52.952266],"type":"Point"}
}
