{
  "type": "Feature",
  "properties": {
    "date:inception_lower":"1980-01-01",
    "date:inception_upper":"1980-01-31",
    "iso:country":"GB",
    "wof:name":"NG1 1QE",
    "wof:placetype":"postalcode"
},
  "geometry": {"coordinates":[-1.144702,52.952266],"type":"Point"}
}