{
  "type": "Feature",
  "properties": {
    "iso:country":"GB",
    "wof:name":"NG1 1QE",
    "wof:placetype":"postalcode"
},
  "geometry": {"coordinates":[-1.14470180757345,52.95226561434266],"type":"Point"}
}