{
  "type": "Feature",
  "properties": {
    "iso:country":"GB",
    "wof:name":"GL13 9JY",
    "wof:placetype":"postalcode"
},
  "geometry": {"coordinates":[-2.45744121578571,51.6558381215297],"type":"Point"}
}