{
  "type": "Feature",
  "properties": {
    "iso:country":"GB",
    "wof:name":"NE2 2DY",
    "wof:placetype":"postalcode"
},
  "geometry": {"coordinates":[-1.6038595075353,54.99249439048672],"type":"Point"}
}