{
  "type": "Feature",
  "properties": {
    "date:inception_lower": "1980-01-01",
    "date:inception_upper": "1980-01-01",
    "iso:country": "GB",
    "wof:name": "PO20 0AS",
    "wof:placetype": "postalcode"
  },
  "geometry": {"coordinates":[-0.7886,50.729117],"type":"Point"}
}
