{
  "type": "Feature",
  "properties": {
    "iso:country":"GB",
    "wof:name":"BN1 6TU",
    "wof:placetype":"postalcode"
},
  "geometry": {"coordinates":[-0.1540411837227,50.84712955717193],"type":"Point"}
}