{
  "type": "Feature",
  "properties": {
    "iso:country": "GB",
    "wof:name": "BH14 9JT",
    "wof:placetype": "postalcode"
  },
  "geometry": {"coordinates":[-1.93609,50.71896],"type":"Point"}
}
