{
  "type": "Feature",
  "properties": {
    "iso:country":"GB",
    "wof:name":"WS9 8QQ",
    "wof:placetype":"postalcode"
},
  "geometry": {"coordinates":[-1.91802874172998,52.60845310538276],"type":"Point"}
}