{
  "type": "Feature",
  "properties": {
    "iso:country": "GB",
    "wof:name": "WS9 8QQ",
    "wof:placetype": "postalcode"
  },
  "geometry": {"coordinates":[-1.918029,52.608453],"type":"Point"}
}
