{
  "type": "Feature",
  "properties": {
    "date:inception_lower":"1999-06-01",
    "date:inception_upper":"1999-06-30",
    "iso:country":"GB",
    "wof:name":"NP16 7AT",
    "wof:placetype":"postalcode"
},
  "geometry": {"coordinates":[-2.66102,51.638918],"type":"Point"}
}