{
  "type": "Feature",
  "properties": {
    "iso:country": "GB",
    "wof:name": "NP16 7AT",
    "wof:placetype": "postalcode"
  },
  "geometry": {"coordinates":[-2.66102,51.638918],"type":"Point"}
}
