{
  "type": "Feature",
  "properties": {
    "iso:country":"GB",
    "wof:name":"GL14 1NB",
    "wof:placetype":"postalcode"
},
  "geometry": {"coordinates":[-2.40373597704351,51.84388682250683],"type":"Point"}
}