{
  "type": "Feature",
  "properties": {
    "iso:country": "GB",
    "wof:name": "E10 6JJ",
    "wof:placetype": "postalcode"
  },
  "geometry": {"coordinates":[-0.005566,51.571426],"type":"Point"}
}
