{
  "type": "Feature",
  "properties": {
    "iso:country":"GB",
    "wof:name":"E10 6JJ",
    "wof:placetype":"postalcode"
},
  "geometry": {"coordinates":[-0.00556628761017,51.57142603422143],"type":"Point"}
}