{
  "type": "Feature",
  "properties": {
    "iso:country": "GB",
    "wof:name": "BN10 7RN",
    "wof:placetype": "postalcode"
  },
  "geometry": {"coordinates":[-0.005979,50.799042],"type":"Point"}
}
