{
  "type": "Feature",
  "properties": {
    "date:inception_lower":"1980-01-01",
    "date:inception_upper":"1980-01-31",
    "iso:country":"GB",
    "wof:name":"PO9 3LJ",
    "wof:placetype":"postalcode"
},
  "geometry": {"coordinates":[-1.008576,50.851078],"type":"Point"}
}