{
  "type": "Feature",
  "properties": {
    "iso:country":"GB",
    "wof:name":"PO9 3LJ",
    "wof:placetype":"postalcode"
},
  "geometry": {"coordinates":[-1.0085758908853,50.85107837998141],"type":"Point"}
}