{
  "type": "Feature",
  "properties": {
    "iso:country":"GB",
    "wof:name":"DD9 6EE",
    "wof:placetype":"postalcode"
},
  "geometry": {"coordinates":[-2.65975694766994,56.732508318064],"type":"Point"}
}