{
  "type": "Feature",
  "properties": {
    "iso:country": "GB",
    "wof:name": "SP6 3RB",
    "wof:placetype": "postalcode"
  },
  "geometry": {"coordinates":[-1.835234,50.912489],"type":"Point"}
}
