{
  "type": "Feature",
  "properties": {
    "date:inception_lower": "1992-08-01",
    "date:inception_upper": "1992-08-01",
    "iso:country": "GB",
    "wof:name": "SP6 3RB",
    "wof:placetype": "postalcode"
  },
  "geometry": {"coordinates":[-1.835234,50.912489],"type":"Point"}
}
