{
  "type": "Feature",
  "properties": {
    "iso:country":"GB",
    "wof:name":"NG16 1AL",
    "wof:placetype":"postalcode"
},
  "geometry": {"coordinates":[-1.2130513988243,52.98586376218829],"type":"Point"}
}