{
  "type": "Feature",
  "properties": {
    "iso:country": "GB",
    "wof:name": "IP22 1EF",
    "wof:placetype": "postalcode"
  },
  "geometry": {"coordinates":[0.996298,52.338692],"type":"Point"}
}
