{
  "type": "Feature",
  "properties": {
    "date:inception_lower": "1980-01-01",
    "date:inception_upper": "1980-01-01",
    "iso:country": "GB",
    "wof:name": "TN33 0DE",
    "wof:placetype": "postalcode"
  },
  "geometry": {"coordinates":[0.494864,50.912979],"type":"Point"}
}
