{
  "type": "Feature",
  "properties": {
    "iso:country":"GB",
    "wof:name":"TN33 0DE",
    "wof:placetype":"postalcode"
},
  "geometry": {"coordinates":[0.49448571489988,50.91337718895686],"type":"Point"}
}