{
  "type": "Feature",
  "properties": {
    "iso:country": "GB",
    "wof:name": "IV32 7EQ",
    "wof:placetype": "postalcode"
  },
  "geometry": {"coordinates":[-3.102024,57.614165],"type":"Point"}
}
