{
  "type": "Feature",
  "properties": {
    "iso:country": "GB",
    "wof:name": "RG18 4EL",
    "wof:placetype": "postalcode"
  },
  "geometry": {"coordinates":[-1.245173,51.407874],"type":"Point"}
}
