{
  "type": "Feature",
  "properties": {
    "date:inception_lower": "2016-09-01",
    "date:inception_upper": "2016-09-01",
    "iso:country": "GB",
    "wof:name": "CV37 8QN",
    "wof:placetype": "postalcode"
  },
  "geometry": {"coordinates":[-1.66224,52.133783],"type":"Point"}
}
