{
  "type": "Feature",
  "properties": {
    "iso:country":"GB",
    "wof:name":"SO23 9AT",
    "wof:placetype":"postalcode"
},
  "geometry": {"coordinates":[-1.3184553419202,51.06352383613149],"type":"Point"}
}