{
  "type": "Feature",
  "properties": {
    "iso:country": "GB",
    "wof:name": "LA5 9PY",
    "wof:placetype": "postalcode"
  },
  "geometry": {"coordinates":[-2.765556,54.14882],"type":"Point"}
}
