{
  "type": "Feature",
  "properties": {
    "iso:country":"GB",
    "wof:name":"LA5 9PY",
    "wof:placetype":"postalcode"
},
  "geometry": {"coordinates":[-2.76555603615814,54.14882047170864],"type":"Point"}
}