{
  "type": "Feature",
  "properties": {
    "date:inception_lower":"1980-01-01",
    "date:inception_upper":"1980-01-31",
    "iso:country":"GB",
    "wof:name":"PH16 5PD",
    "wof:placetype":"postalcode"
},
  "geometry": {"coordinates":[-4.129679,56.70546],"type":"Point"}
}