{
  "type": "Feature",
  "properties": {
    "iso:country":"GB",
    "wof:name":"BN11 3HB",
    "wof:placetype":"postalcode"
},
  "geometry": {"coordinates":[-0.37225316494661,50.81033060903354],"type":"Point"}
}