{
  "type": "Feature",
  "properties": {
    "iso:country":"GB",
    "wof:name":"KT10 0DR",
    "wof:placetype":"postalcode"
},
  "geometry": {"coordinates":[-0.34040260129215,51.36326863665386],"type":"Point"}
}