{
  "type": "Feature",
  "properties": {
    "iso:country": "GB",
    "wof:name": "OL10 3EQ",
    "wof:placetype": "postalcode"
  },
  "geometry": {"coordinates":[-2.225696,53.593455],"type":"Point"}
}
