{
  "type": "Feature",
  "properties": {
    "iso:country":"GB",
    "wof:name":"E12 6EU",
    "wof:placetype":"postalcode"
},
  "geometry": {"coordinates":[0.05628384280004,51.54679758898861],"type":"Point"}
}