{
  "type": "Feature",
  "properties": {
    "date:inception_lower": "1994-05-01",
    "date:inception_upper": "1994-05-01",
    "iso:country": "GB",
    "wof:name": "E12 6EU",
    "wof:placetype": "postalcode"
  },
  "geometry": {"coordinates":[0.056284,51.546798],"type":"Point"}
}
