{
  "type": "Feature",
  "properties": {
    "date:inception_lower": "1980-01-01",
    "date:inception_upper": "1980-01-01",
    "iso:country": "GB",
    "wof:name": "L26 1XA",
    "wof:placetype": "postalcode"
  },
  "geometry": {"coordinates":[-2.834248,53.360458],"type":"Point"}
}
