{
  "type": "Feature",
  "properties": {
    "iso:country":"GB",
    "wof:name":"B35 6HG",
    "wof:placetype":"postalcode"
},
  "geometry": {"coordinates":[-1.79248498615432,52.52254588055384],"type":"Point"}
}