{
  "type": "Feature",
  "properties": {
    "iso:country": "GB",
    "wof:name": "PL16 0JB",
    "wof:placetype": "postalcode"
  },
  "geometry": {"coordinates":[-4.219921,50.620772],"type":"Point"}
}
