{
  "type": "Feature",
  "properties": {
    "date:inception_lower":"1980-01-01",
    "date:inception_upper":"1980-01-31",
    "iso:country":"GB",
    "wof:name":"PL16 0JB",
    "wof:placetype":"postalcode"
},
  "geometry": {"coordinates":[-4.219921,50.620772],"type":"Point"}
}