{
  "type": "Feature",
  "properties": {
    "iso:country":"GB",
    "wof:name":"PL16 0JB",
    "wof:placetype":"postalcode"
},
  "geometry": {"coordinates":[-4.2199210557799,50.6207721656334],"type":"Point"}
}