{
  "type": "Feature",
  "properties": {
    "iso:country":"GB",
    "wof:name":"IP19 9BS",
    "wof:placetype":"postalcode"
},
  "geometry": {"coordinates":[1.55715958386851,52.32908391405829],"type":"Point"}
}