{
  "type": "Feature",
  "properties": {
    "iso:country": "GB",
    "wof:name": "CV5 8BE",
    "wof:placetype": "postalcode"
  },
  "geometry": {"coordinates":[-1.551238,52.407551],"type":"Point"}
}
