{
  "type": "Feature",
  "properties": {
    "iso:country":"GB",
    "wof:name":"CV5 8BE",
    "wof:placetype":"postalcode"
},
  "geometry": {"coordinates":[-1.55123826904047,52.40755111668952],"type":"Point"}
}