{
  "type": "Feature",
  "properties": {
    "iso:country": "GB",
    "wof:name": "SN10 2QU",
    "wof:placetype": "postalcode"
  },
  "geometry": {"coordinates":[-2.005214,51.355549],"type":"Point"}
}
