{
  "type": "Feature",
  "properties": {
    "date:inception_lower": "2019-09-01",
    "date:inception_upper": "2019-09-01",
    "iso:country": "GB",
    "wof:name": "SN10 2QU",
    "wof:placetype": "postalcode"
  },
  "geometry": {"coordinates":[-2.005214,51.355549],"type":"Point"}
}
