{
  "type": "Feature",
  "properties": {
    "iso:country":"GB",
    "wof:name":"KA8 8BH",
    "wof:placetype":"postalcode"
},
  "geometry": {"coordinates":[-4.6316105125512,55.46871399537406],"type":"Point"}
}