{
  "type": "Feature",
  "properties": {
    "date:inception_lower": "1999-12-01",
    "date:inception_upper": "1999-12-01",
    "iso:country": "GB",
    "wof:name": "RG30 2HU",
    "wof:placetype": "postalcode"
  },
  "geometry": {"coordinates":[-1.002958,51.453298],"type":"Point"}
}
