{
  "type": "Feature",
  "properties": {
    "iso:country":"GB",
    "wof:name":"DD3 6DJ",
    "wof:placetype":"postalcode"
},
  "geometry": {"coordinates":[-2.99958818019622,56.47023008095857],"type":"Point"}
}