{
  "type": "Feature",
  "properties": {
    "iso:country":"GB",
    "wof:name":"WF9 3TJ",
    "wof:placetype":"postalcode"
},
  "geometry": {"coordinates":[-1.32994534030211,53.60024250149093],"type":"Point"}
}