{
  "type": "Feature",
  "properties": {
    "iso:country": "GB",
    "wof:name": "WF9 3TJ",
    "wof:placetype": "postalcode"
  },
  "geometry": {"coordinates":[-1.329947,53.60026],"type":"Point"}
}
