{
  "type": "Feature",
  "properties": {
    "date:inception_lower": "1980-01-01",
    "date:inception_upper": "1980-01-01",
    "iso:country": "GB",
    "wof:name": "NG20 8PR",
    "wof:placetype": "postalcode"
  },
  "geometry": {"coordinates":[-1.222567,53.204806],"type":"Point"}
}
