{
  "type": "Feature",
  "properties": {
    "iso:country":"GB",
    "wof:name":"LL63 5RZ",
    "wof:placetype":"postalcode"
},
  "geometry": {"coordinates":[-4.46510950299363,53.21490616485852],"type":"Point"}
}