{
  "type": "Feature",
  "properties": {
    "iso:country":"GB",
    "wof:name":"SE6 1QQ",
    "wof:placetype":"postalcode"
},
  "geometry": {"coordinates":[0.00472474361783,51.43423797982609],"type":"Point"}
}