{
  "type": "Feature",
  "properties": {
    "date:inception_lower":"1992-08-01",
    "date:inception_upper":"1992-08-31",
    "iso:country":"GB",
    "wof:name":"DE55 6AG",
    "wof:placetype":"postalcode"
},
  "geometry": {"coordinates":[-1.415672,53.120819],"type":"Point"}
}