{
  "type": "Feature",
  "properties": {
    "iso:country":"GB",
    "wof:name":"CB8 0JB",
    "wof:placetype":"postalcode"
},
  "geometry": {"coordinates":[0.40255948850163,52.24631673755994],"type":"Point"}
}