{
  "type": "Feature",
  "properties": {
    "iso:country": "GB",
    "wof:name": "CB8 0JB",
    "wof:placetype": "postalcode"
  },
  "geometry": {"coordinates":[0.402458,52.246371],"type":"Point"}
}
