{
  "type": "Feature",
  "properties": {
    "iso:country":"GB",
    "wof:name":"PO15 6HS",
    "wof:placetype":"postalcode"
},
  "geometry": {"coordinates":[-1.20698931366214,50.86517553301219],"type":"Point"}
}