{
  "type": "Feature",
  "properties": {
    "iso:country":"GB",
    "wof:name":"NN5 7NE",
    "wof:placetype":"postalcode"
},
  "geometry": {"coordinates":[-0.91545434840753,52.25792594465796],"type":"Point"}
}