{
  "type": "Feature",
  "properties": {
    "iso:country":"GB",
    "wof:name":"RH2 8BY",
    "wof:placetype":"postalcode"
},
  "geometry": {"coordinates":[-0.20239887251187,51.21569369919234],"type":"Point"}
}