{
  "type": "Feature",
  "properties": {
    "date:inception_lower": "2000-06-01",
    "date:inception_upper": "2000-06-01",
    "iso:country": "GB",
    "wof:name": "PE28 2TS",
    "wof:placetype": "postalcode"
  },
  "geometry": {"coordinates":[-0.077996,52.406402],"type":"Point"}
}
