{
  "type": "Feature",
  "properties": {
    "iso:country":"GB",
    "wof:name":"DY7 5NN",
    "wof:placetype":"postalcode"
},
  "geometry": {"coordinates":[-2.25276295016719,52.45067196300865],"type":"Point"}
}