{
  "type": "Feature",
  "properties": {
    "iso:country": "GB",
    "wof:name": "BS39 5TY",
    "wof:placetype": "postalcode"
  },
  "geometry": {"coordinates":[-2.5996,51.33882],"type":"Point"}
}
