{
  "type": "Feature",
  "properties": {
    "iso:country":"GB",
    "wof:name":"BH21 3NS",
    "wof:placetype":"postalcode"
},
  "geometry": {"coordinates":[-2.0159168812108,50.77370586819616],"type":"Point"}
}