{
  "type": "Feature",
  "properties": {
    "iso:country": "GB",
    "wof:name": "TA10 9HG",
    "wof:placetype": "postalcode"
  },
  "geometry": {"coordinates":[-2.816125,51.032471],"type":"Point"}
}
