{
  "type": "Feature",
  "properties": {
    "iso:country":"GB",
    "wof:name":"NR31 9HP",
    "wof:placetype":"postalcode"
},
  "geometry": {"coordinates":[1.6378327845986,52.54327029783431],"type":"Point"}
}