{
  "type": "Feature",
  "properties": {
    "iso:country":"GB",
    "wof:name":"CV6 7BU",
    "wof:placetype":"postalcode"
},
  "geometry": {"coordinates":[-1.47634886846948,52.43919427781211],"type":"Point"}
}