{
  "type": "Feature",
  "properties": {
    "iso:country":"GB",
    "wof:name":"RG17 9UL",
    "wof:placetype":"postalcode"
},
  "geometry": {"coordinates":[-1.44438095794199,51.39640729886181],"type":"Point"}
}