{
  "type": "Feature",
  "properties": {
    "iso:country":"GB",
    "wof:name":"BR5 2BN",
    "wof:placetype":"postalcode"
},
  "geometry": {"coordinates":[0.10245230678762,51.38895481678048],"type":"Point"}
}