{
  "type": "Feature",
  "properties": {
    "date:inception_lower": "1980-01-01",
    "date:inception_upper": "1980-01-01",
    "iso:country": "GB",
    "wof:name": "BR5 2BN",
    "wof:placetype": "postalcode"
  },
  "geometry": {"coordinates":[0.102452,51.388955],"type":"Point"}
}
