{
  "type": "Feature",
  "properties": {
    "iso:country":"GB",
    "wof:name":"LE1 4JT",
    "wof:placetype":"postalcode"
},
  "geometry": {"coordinates":[-1.1415585498044,52.63743100956498],"type":"Point"}
}