{
  "type": "Feature",
  "properties": {
    "iso:country":"GB",
    "wof:name":"EX4 1JQ",
    "wof:placetype":"postalcode"
},
  "geometry": {"coordinates":[-3.54700153826241,50.71603071684623],"type":"Point"}
}