{
  "type": "Feature",
  "properties": {
    "iso:country": "GB",
    "wof:name": "EX4 1JQ",
    "wof:placetype": "postalcode"
  },
  "geometry": {"coordinates":[-3.547001,50.716031],"type":"Point"}
}
