{
  "type": "Feature",
  "properties": {
    "iso:country":"GB",
    "wof:name":"DE73 8DX",
    "wof:placetype":"postalcode"
},
  "geometry": {"coordinates":[-1.4265158062754,52.82309033221066],"type":"Point"}
}