{
  "type": "Feature",
  "properties": {
    "iso:country": "GB",
    "wof:name": "CT21 4DR",
    "wof:placetype": "postalcode"
  },
  "geometry": {"coordinates":[1.065439,51.073681],"type":"Point"}
}
