{
  "type": "Feature",
  "properties": {
    "iso:country":"GB",
    "wof:name":"CT21 4DR",
    "wof:placetype":"postalcode"
},
  "geometry": {"coordinates":[1.06543867690334,51.07368148163814],"type":"Point"}
}