{
  "type": "Feature",
  "properties": {
    "iso:country":"GB",
    "wof:name":"WF12 7JB",
    "wof:placetype":"postalcode"
},
  "geometry": {"coordinates":[-1.59301676175731,53.71768852483837],"type":"Point"}
}