{
  "type": "Feature",
  "properties": {
    "iso:country":"GB",
    "wof:name":"SW6 6NT",
    "wof:placetype":"postalcode"
},
  "geometry": {"coordinates":[-0.21901141560591,51.47822737399092],"type":"Point"}
}