{
  "type": "Feature",
  "properties": {
    "date:inception_lower":"1980-01-01",
    "date:inception_upper":"1980-01-31",
    "iso:country":"GB",
    "wof:name":"DT5 2HB",
    "wof:placetype":"postalcode"
},
  "geometry": {"coordinates":[-2.447567,50.541138],"type":"Point"}
}