{
  "type": "Feature",
  "properties": {
    "date:inception_lower": "1980-01-01",
    "date:inception_upper": "1980-01-01",
    "iso:country": "GB",
    "wof:name": "LE3 9GP",
    "wof:placetype": "postalcode"
  },
  "geometry": {"coordinates":[-1.157653,52.640423],"type":"Point"}
}
