{
  "type": "Feature",
  "properties": {
    "iso:country":"GB",
    "wof:name":"BD23 6AA",
    "wof:placetype":"postalcode"
},
  "geometry": {"coordinates":[-2.00215902762175,53.96812516177003],"type":"Point"}
}