{
  "type": "Feature",
  "properties": {
    "date:inception_lower": "1980-01-01",
    "date:inception_upper": "1980-01-01",
    "iso:country": "GB",
    "wof:name": "BD23 6AA",
    "wof:placetype": "postalcode"
  },
  "geometry": {"coordinates":[-2.002159,53.968125],"type":"Point"}
}
