{
  "type": "Feature",
  "properties": {
    "date:inception_lower": "2006-09-01",
    "date:inception_upper": "2006-09-01",
    "iso:country": "GB",
    "wof:name": "BD4 0QW",
    "wof:placetype": "postalcode"
  },
  "geometry": {"coordinates":[-1.699555,53.773252],"type":"Point"}
}
