{
  "type": "Feature",
  "properties": {
    "iso:country":"GB",
    "wof:name":"BD4 0QW",
    "wof:placetype":"postalcode"
},
  "geometry": {"coordinates":[-1.69955524247754,53.77325245356779],"type":"Point"}
}