{
  "type": "Feature",
  "properties": {
    "iso:country":"GB",
    "wof:name":"SO24 0QH",
    "wof:placetype":"postalcode"
},
  "geometry": {"coordinates":[-1.17230715423186,51.05172690278458],"type":"Point"}
}