{
  "type": "Feature",
  "properties": {
    "iso:country": "GB",
    "wof:name": "SO24 0QH",
    "wof:placetype": "postalcode"
  },
  "geometry": {"coordinates":[-1.172307,51.051727],"type":"Point"}
}
