{
  "type": "Feature",
  "properties": {
    "iso:country":"GB",
    "wof:name":"PE25 1JD",
    "wof:placetype":"postalcode"
},
  "geometry": {"coordinates":[0.34830835910253,53.17732981514698],"type":"Point"}
}