{
  "type": "Feature",
  "properties": {
    "iso:country": "GB",
    "wof:name": "PE25 1JD",
    "wof:placetype": "postalcode"
  },
  "geometry": {"coordinates":[0.348308,53.17733],"type":"Point"}
}
