{
  "type": "Feature",
  "properties": {
    "iso:country": "GB",
    "wof:name": "PO38 2AD",
    "wof:placetype": "postalcode"
  },
  "geometry": {"coordinates":[-1.258121,50.60229],"type":"Point"}
}
