{
  "type": "Feature",
  "properties": {
    "iso:country":"GB",
    "wof:name":"OL5 9LA",
    "wof:placetype":"postalcode"
},
  "geometry": {"coordinates":[-2.02565898706254,53.51562849790918],"type":"Point"}
}