{
  "type": "Feature",
  "properties": {
    "iso:country": "GB",
    "wof:name": "LS12 4HB",
    "wof:placetype": "postalcode"
  },
  "geometry": {"coordinates":[-1.592025,53.788907],"type":"Point"}
}
