{
  "type": "Feature",
  "properties": {
    "iso:country":"GB",
    "wof:name":"BS2 2DA",
    "wof:placetype":"postalcode"
},
  "geometry": {"coordinates":[-2.57533476405333,51.45876579349541],"type":"Point"}
}