{
  "type": "Feature",
  "properties": {
    "iso:country":"GB",
    "wof:name":"EH4 3PX",
    "wof:placetype":"postalcode"
},
  "geometry": {"coordinates":[-3.26580013461296,55.9581333170262],"type":"Point"}
}