{
  "type": "Feature",
  "properties": {
    "date:inception_lower":"1993-01-01",
    "date:inception_upper":"1993-01-31",
    "iso:country":"GB",
    "wof:name":"SA72 6UL",
    "wof:placetype":"postalcode"
},
  "geometry": {"coordinates":[-4.94209,51.697924],"type":"Point"}
}