{
  "type": "Feature",
  "properties": {
    "iso:country": "GB",
    "wof:name": "SA72 6UL",
    "wof:placetype": "postalcode"
  },
  "geometry": {"coordinates":[-4.94209,51.697924],"type":"Point"}
}
