{
  "type": "Feature",
  "properties": {
    "iso:country":"GB",
    "wof:name":"SA72 6UL",
    "wof:placetype":"postalcode"
},
  "geometry": {"coordinates":[-4.94192240566133,51.69787059304817],"type":"Point"}
}