{
  "type": "Feature",
  "properties": {
    "iso:country":"GB",
    "wof:name":"DH6 4HX",
    "wof:placetype":"postalcode"
},
  "geometry": {"coordinates":[-1.5119833654618,54.72320450995984],"type":"Point"}
}