{
  "type": "Feature",
  "properties": {
    "date:inception_lower": "1980-01-01",
    "date:inception_upper": "1980-01-01",
    "iso:country": "GB",
    "wof:name": "DH6 4HX",
    "wof:placetype": "postalcode"
  },
  "geometry": {"coordinates":[-1.511995,54.723214],"type":"Point"}
}
