{
  "type": "Feature",
  "properties": {
    "iso:country":"GB",
    "wof:name":"EX35 6HS",
    "wof:placetype":"postalcode"
},
  "geometry": {"coordinates":[-3.83446026557468,51.23014941597059],"type":"Point"}
}