{
  "type": "Feature",
  "properties": {
    "date:inception_lower": "1980-01-01",
    "date:inception_upper": "1980-01-01",
    "iso:country": "GB",
    "wof:name": "EX35 6HS",
    "wof:placetype": "postalcode"
  },
  "geometry": {"coordinates":[-3.83446,51.230149],"type":"Point"}
}
