{
  "type": "Feature",
  "properties": {
    "date:inception_lower": "1980-01-01",
    "date:inception_upper": "1980-01-01",
    "iso:country": "GB",
    "wof:name": "NR15 2HX",
    "wof:placetype": "postalcode"
  },
  "geometry": {"coordinates":[1.18362,52.455737],"type":"Point"}
}
