{
  "type": "Feature",
  "properties": {
    "date:inception_lower": "1997-06-01",
    "date:inception_upper": "1997-06-01",
    "iso:country": "GB",
    "wof:name": "S18 7TR",
    "wof:placetype": "postalcode"
  },
  "geometry": {"coordinates":[-1.485279,53.269313],"type":"Point"}
}
