{
  "type": "Feature",
  "properties": {
    "iso:country":"GB",
    "wof:name":"S18 7TR",
    "wof:placetype":"postalcode"
},
  "geometry": {"coordinates":[-1.48527934510176,53.26931346758587],"type":"Point"}
}