{
  "type": "Feature",
  "properties": {
    "iso:country":"GB",
    "wof:name":"WR6 5SD",
    "wof:placetype":"postalcode"
},
  "geometry": {"coordinates":[-2.41081892963673,52.20783320235093],"type":"Point"}
}