{
  "type": "Feature",
  "properties": {
    "date:inception_lower":"1980-01-01",
    "date:inception_upper":"1980-01-31",
    "iso:country":"GB",
    "wof:name":"WR6 5SD",
    "wof:placetype":"postalcode"
},
  "geometry": {"coordinates":[-2.410819,52.207833],"type":"Point"}
}