{
  "type": "Feature",
  "properties": {
    "date:inception_lower": "1980-01-01",
    "date:inception_upper": "1980-01-01",
    "iso:country": "GB",
    "wof:name": "UB10 0SE",
    "wof:placetype": "postalcode"
  },
  "geometry": {"coordinates":[-0.449338,51.53995],"type":"Point"}
}
