{
  "type": "Feature",
  "properties": {
    "date:inception_lower": "1980-01-01",
    "date:inception_upper": "1980-01-01",
    "iso:country": "GB",
    "wof:name": "LA13 9TN",
    "wof:placetype": "postalcode"
  },
  "geometry": {"coordinates":[-3.206905,54.109585],"type":"Point"}
}
