{
  "type": "Feature",
  "properties": {
    "iso:country":"GB",
    "wof:name":"OX1 4EW",
    "wof:placetype":"postalcode"
},
  "geometry": {"coordinates":[-1.25390245031047,51.75153109201023],"type":"Point"}
}