{
  "type": "Feature",
  "properties": {
    "iso:country":"GB",
    "wof:name":"PE9 3PH",
    "wof:placetype":"postalcode"
},
  "geometry": {"coordinates":[-0.52622028036502,52.61350258015138],"type":"Point"}
}