{
  "type": "Feature",
  "properties": {
    "iso:country": "GB",
    "wof:name": "PE9 3PH",
    "wof:placetype": "postalcode"
  },
  "geometry": {"coordinates":[-0.52622,52.613503],"type":"Point"}
}
