{
  "type": "Feature",
  "properties": {
    "date:inception_lower":"1980-01-01",
    "date:inception_upper":"1980-01-31",
    "iso:country":"GB",
    "wof:name":"PE9 3PH",
    "wof:placetype":"postalcode"
},
  "geometry": {"coordinates":[-0.52622,52.613503],"type":"Point"}
}