{
  "type": "Feature",
  "properties": {
    "date:inception_lower":"2002-09-01",
    "date:inception_upper":"2002-09-30",
    "iso:country":"GB",
    "wof:name":"PL14 6EY",
    "wof:placetype":"postalcode"
},
  "geometry": {"coordinates":[-4.474646,50.454958],"type":"Point"}
}