{
  "type": "Feature",
  "properties": {
    "iso:country":"GB",
    "wof:name":"PL14 6EY",
    "wof:placetype":"postalcode"
},
  "geometry": {"coordinates":[-4.47464601785478,50.45495821363412],"type":"Point"}
}