{
  "type": "Feature",
  "properties": {
    "date:inception_lower": "2011-11-01",
    "date:inception_upper": "2011-11-01",
    "iso:country": "GB",
    "wof:name": "MK10 7FB",
    "wof:placetype": "postalcode"
  },
  "geometry": {"coordinates":[-0.6859,52.044163],"type":"Point"}
}
