{
  "type": "Feature",
  "properties": {
    "iso:country":"GB",
    "wof:name":"BR3 5AH",
    "wof:placetype":"postalcode"
},
  "geometry": {"coordinates":[-0.0239669657015,51.41548969556986],"type":"Point"}
}