{
  "type": "Feature",
  "properties": {
    "iso:country":"GB",
    "wof:name":"CO12 3PQ",
    "wof:placetype":"postalcode"
},
  "geometry": {"coordinates":[1.27724232851722,51.936842829179],"type":"Point"}
}