{
  "type": "Feature",
  "properties": {
    "date:inception_lower": "2001-12-01",
    "date:inception_upper": "2001-12-01",
    "iso:country": "GB",
    "wof:name": "CO12 3PQ",
    "wof:placetype": "postalcode"
  },
  "geometry": {"coordinates":[1.277242,51.936843],"type":"Point"}
}
