{
  "type": "Feature",
  "properties": {
    "iso:country":"GB",
    "wof:name":"PE7 1PZ",
    "wof:placetype":"postalcode"
},
  "geometry": {"coordinates":[-0.14120684984027,52.56166568931199],"type":"Point"}
}