{
  "type": "Feature",
  "properties": {
    "iso:country":"GB",
    "wof:name":"LE3 1EG",
    "wof:placetype":"postalcode"
},
  "geometry": {"coordinates":[-1.16965209615827,52.6209367692979],"type":"Point"}
}