{
  "type": "Feature",
  "properties": {
    "date:inception_lower": "1980-01-01",
    "date:inception_upper": "1980-01-01",
    "iso:country": "GB",
    "wof:name": "NE37 2PZ",
    "wof:placetype": "postalcode"
  },
  "geometry": {"coordinates":[-1.526646,54.914388],"type":"Point"}
}
