{
  "type": "Feature",
  "properties": {
    "iso:country":"GB",
    "wof:name":"DE4 3NZ",
    "wof:placetype":"postalcode"
},
  "geometry": {"coordinates":[-1.56048665401727,53.1231304431022],"type":"Point"}
}