{
  "type": "Feature",
  "properties": {
    "date:inception_lower": "1980-01-01",
    "date:inception_upper": "1980-01-01",
    "iso:country": "GB",
    "wof:name": "DE4 3NZ",
    "wof:placetype": "postalcode"
  },
  "geometry": {"coordinates":[-1.560487,53.12313],"type":"Point"}
}
