{
  "type": "Feature",
  "properties": {
    "date:inception_lower": "1980-01-01",
    "date:inception_upper": "1980-01-01",
    "iso:country": "GB",
    "wof:name": "PL14 5JH",
    "wof:placetype": "postalcode"
  },
  "geometry": {"coordinates":[-4.454079,50.499214],"type":"Point"}
}
