{
  "type": "Feature",
  "properties": {
    "date:inception_lower": "1980-01-01",
    "date:inception_upper": "1980-01-01",
    "iso:country": "GB",
    "wof:name": "SK9 2DD",
    "wof:placetype": "postalcode"
  },
  "geometry": {"coordinates":[-2.198672,53.333743],"type":"Point"}
}
