{
  "type": "Feature",
  "properties": {
    "date:inception_lower": "2009-11-01",
    "date:inception_upper": "2009-11-01",
    "iso:country": "GB",
    "wof:name": "SA65 9HD",
    "wof:placetype": "postalcode"
  },
  "geometry": {"coordinates":[-4.97484,51.99307],"type":"Point"}
}
