{
  "type": "Feature",
  "properties": {
    "iso:country":"GB",
    "wof:name":"OX4 4YX",
    "wof:placetype":"postalcode"
},
  "geometry": {"coordinates":[-1.21852113191317,51.71238691223603],"type":"Point"}
}