{
  "type": "Feature",
  "properties": {
    "date:inception_lower": "2021-05-01",
    "date:inception_upper": "2021-05-01",
    "iso:country": "GB",
    "wof:name": "ME17 4SX",
    "wof:placetype": "postalcode"
  },
  "geometry": {"coordinates":[0.538289,51.234641],"type":"Point"}
}
