{
  "type": "Feature",
  "properties": {
    "iso:country":"GB",
    "wof:name":"LD7 1HL",
    "wof:placetype":"postalcode"
},
  "geometry": {"coordinates":[-3.05129493676033,52.34312029311423],"type":"Point"}
}