{
  "type": "Feature",
  "properties": {
    "date:inception_lower": "1980-01-01",
    "date:inception_upper": "1980-01-01",
    "iso:country": "GB",
    "wof:name": "BD2 4QX",
    "wof:placetype": "postalcode"
  },
  "geometry": {"coordinates":[-1.730231,53.807075],"type":"Point"}
}
