{
  "type": "Feature",
  "properties": {
    "iso:country": "GB",
    "wof:name": "BD2 4QX",
    "wof:placetype": "postalcode"
  },
  "geometry": {"coordinates":[-1.730231,53.807075],"type":"Point"}
}
