{
  "type": "Feature",
  "properties": {
    "date:inception_lower": "1985-10-01",
    "date:inception_upper": "1985-10-01",
    "iso:country": "GB",
    "wof:name": "NW1 5LQ",
    "wof:placetype": "postalcode"
  },
  "geometry": {"coordinates":[-0.15596,51.522962],"type":"Point"}
}
