{
  "type": "Feature",
  "properties": {
    "date:inception_lower":"1995-12-01",
    "date:inception_upper":"1995-12-31",
    "iso:country":"GB",
    "wof:name":"PO36 9EN",
    "wof:placetype":"postalcode"
},
  "geometry": {"coordinates":[-1.160529,50.659509],"type":"Point"}
}