{
  "type": "Feature",
  "properties": {
    "iso:country": "GB",
    "wof:name": "PO36 9EN",
    "wof:placetype": "postalcode"
  },
  "geometry": {"coordinates":[-1.160529,50.659509],"type":"Point"}
}
