{
  "type": "Feature",
  "properties": {
    "iso:country":"GB",
    "wof:name":"CO10 0YU",
    "wof:placetype":"postalcode"
},
  "geometry": {"coordinates":[0.76102546719519,52.02522940056504],"type":"Point"}
}