{
  "type": "Feature",
  "properties": {
    "iso:country": "GB",
    "wof:name": "CO10 0YU",
    "wof:placetype": "postalcode"
  },
  "geometry": {"coordinates":[0.761042,52.025233],"type":"Point"}
}
