{
  "type": "Feature",
  "properties": {
    "date:inception_lower": "1990-02-01",
    "date:inception_upper": "1990-02-01",
    "iso:country": "GB",
    "wof:name": "CO10 0YU",
    "wof:placetype": "postalcode"
  },
  "geometry": {"coordinates":[0.761042,52.025233],"type":"Point"}
}
