{
  "type": "Feature",
  "properties": {
    "iso:country":"GB",
    "wof:name":"LD3 8HW",
    "wof:placetype":"postalcode"
},
  "geometry": {"coordinates":[-3.53171021657249,51.96329176771115],"type":"Point"}
}