{
  "type": "Feature",
  "properties": {
    "iso:country":"GB",
    "wof:name":"DD3 7RF",
    "wof:placetype":"postalcode"
},
  "geometry": {"coordinates":[-2.97534991718395,56.47197721278481],"type":"Point"}
}