{
  "type": "Feature",
  "properties": {
    "iso:country":"GB",
    "wof:name":"LN11 9RJ",
    "wof:placetype":"postalcode"
},
  "geometry": {"coordinates":[-0.10271779236819,53.33097350152631],"type":"Point"}
}