{
  "type": "Feature",
  "properties": {
    "date:inception_lower": "1980-01-01",
    "date:inception_upper": "1980-01-01",
    "iso:country": "GB",
    "wof:name": "LN11 9RJ",
    "wof:placetype": "postalcode"
  },
  "geometry": {"coordinates":[-0.102673,53.331006],"type":"Point"}
}
