{
  "type": "Feature",
  "properties": {
    "date:inception_lower": "2023-09-01",
    "date:inception_upper": "2023-09-01",
    "iso:country": "GB",
    "wof:name": "EH9 1FD",
    "wof:placetype": "postalcode"
  },
  "geometry": {"coordinates":[-3.188875,55.938453],"type":"Point"}
}
