{
  "type": "Feature",
  "properties": {
    "iso:country": "GB",
    "wof:name": "L34 2SE",
    "wof:placetype": "postalcode"
  },
  "geometry": {"coordinates":[-2.795595,53.429477],"type":"Point"}
}
