{
  "type": "Feature",
  "properties": {
    "iso:country":"GB",
    "wof:name":"L34 2SE",
    "wof:placetype":"postalcode"
},
  "geometry": {"coordinates":[-2.79559489073484,53.42947738387576],"type":"Point"}
}