{
  "type": "Feature",
  "properties": {
    "iso:country": "GB",
    "wof:name": "HG2 0PT",
    "wof:placetype": "postalcode"
  },
  "geometry": {"coordinates":[-1.551248,53.987115],"type":"Point"}
}
