{
  "type": "Feature",
  "properties": {
    "iso:country": "GB",
    "wof:name": "E3 5EB",
    "wof:placetype": "postalcode"
  },
  "geometry": {"coordinates":[-0.032151,51.530905],"type":"Point"}
}
