{
  "type": "Feature",
  "properties": {
    "iso:country":"GB",
    "wof:name":"E3 5EB",
    "wof:placetype":"postalcode"
},
  "geometry": {"coordinates":[-0.03215099052291,51.53090468578315],"type":"Point"}
}