{
  "type": "Feature",
  "properties": {
    "date:inception_lower": "2017-07-01",
    "date:inception_upper": "2017-07-01",
    "iso:country": "GB",
    "wof:name": "G71 7WP",
    "wof:placetype": "postalcode"
  },
  "geometry": {"coordinates":[-4.106852,55.838654],"type":"Point"}
}
