{
  "type": "Feature",
  "properties": {
    "date:inception_lower":"1980-01-01",
    "date:inception_upper":"1980-01-31",
    "iso:country":"GB",
    "wof:name":"ME3 8HS",
    "wof:placetype":"postalcode"
},
  "geometry": {"coordinates":[0.49956,51.43222],"type":"Point"}
}