{
  "type": "Feature",
  "properties": {
    "date:inception_lower": "2012-07-01",
    "date:inception_upper": "2012-07-01",
    "iso:country": "GB",
    "wof:name": "GL10 2BS",
    "wof:placetype": "postalcode"
  },
  "geometry": {"coordinates":[-2.261108,51.74164],"type":"Point"}
}
