{
  "type": "Feature",
  "properties": {
    "iso:country": "GB",
    "wof:name": "GL10 2BS",
    "wof:placetype": "postalcode"
  },
  "geometry": {"coordinates":[-2.261108,51.74164],"type":"Point"}
}
