{
  "type": "Feature",
  "properties": {
    "iso:country":"GB",
    "wof:name":"SO53 2BU",
    "wof:placetype":"postalcode"
},
  "geometry": {"coordinates":[-1.36734933061782,50.98782254515029],"type":"Point"}
}