{
  "type": "Feature",
  "properties": {
    "date:inception_lower": "1980-01-01",
    "date:inception_upper": "1980-01-01",
    "iso:country": "GB",
    "wof:name": "NE30 2BZ",
    "wof:placetype": "postalcode"
  },
  "geometry": {"coordinates":[-1.446878,55.015139],"type":"Point"}
}
