{
  "type": "Feature",
  "properties": {
    "iso:country": "GB",
    "wof:name": "NE69 7AN",
    "wof:placetype": "postalcode"
  },
  "geometry": {"coordinates":[-1.719855,55.606354],"type":"Point"}
}
