{
  "type": "Feature",
  "properties": {
    "date:inception_lower": "1983-07-01",
    "date:inception_upper": "1983-07-01",
    "iso:country": "GB",
    "wof:name": "BN13 2SH",
    "wof:placetype": "postalcode"
  },
  "geometry": {"coordinates":[-0.415447,50.830423],"type":"Point"}
}
