{
  "type": "Feature",
  "properties": {
    "iso:country":"GB",
    "wof:name":"NW10 9TP",
    "wof:placetype":"postalcode"
},
  "geometry": {"coordinates":[-0.24770361697553,51.54605760389955],"type":"Point"}
}