{
  "type": "Feature",
  "properties": {
    "iso:country":"GB",
    "wof:name":"CM6 1DW",
    "wof:placetype":"postalcode"
},
  "geometry": {"coordinates":[0.35856597937307,51.87364866545681],"type":"Point"}
}