{
  "type": "Feature",
  "properties": {
    "iso:country":"GB",
    "wof:name":"FY1 6BW",
    "wof:placetype":"postalcode"
},
  "geometry": {"coordinates":[-3.04598458768561,53.80082824823913],"type":"Point"}
}