{
  "type": "Feature",
  "properties": {
    "iso:country": "GB",
    "wof:name": "PE19 5ZE",
    "wof:placetype": "postalcode"
  },
  "geometry": {"coordinates":[-0.212024,52.290135],"type":"Point"}
}
