{
  "type": "Feature",
  "properties": {
    "iso:country":"GB",
    "wof:name":"HU17 7JS",
    "wof:placetype":"postalcode"
},
  "geometry": {"coordinates":[-0.43945388565484,53.85500884038539],"type":"Point"}
}