{
  "type": "Feature",
  "properties": {
    "date:inception_lower":"1996-12-01",
    "date:inception_upper":"1996-12-31",
    "iso:country":"GB",
    "wof:name":"HU17 7JS",
    "wof:placetype":"postalcode"
},
  "geometry": {"coordinates":[-0.439454,53.855009],"type":"Point"}
}