{
  "type": "Feature",
  "properties": {
    "date:inception_lower":"1999-06-01",
    "date:inception_upper":"1999-06-30",
    "iso:country":"GB",
    "wof:name":"NP11 4EX",
    "wof:placetype":"postalcode"
},
  "geometry": {"coordinates":[-3.144235,51.665432],"type":"Point"}
}