{
  "type": "Feature",
  "properties": {
    "iso:country": "GB",
    "wof:name": "NP11 4EX",
    "wof:placetype": "postalcode"
  },
  "geometry": {"coordinates":[-3.144235,51.665432],"type":"Point"}
}
