{
  "type": "Feature",
  "properties": {
    "iso:country":"GB",
    "wof:name":"NP11 4EX",
    "wof:placetype":"postalcode"
},
  "geometry": {"coordinates":[-3.14423467100197,51.66543196190943],"type":"Point"}
}