{
  "type": "Feature",
  "properties": {
    "iso:country":"GB",
    "wof:name":"PO17 5AT",
    "wof:placetype":"postalcode"
},
  "geometry": {"coordinates":[-1.1684395357074,50.92897053707459],"type":"Point"}
}