{
  "type": "Feature",
  "properties": {
    "iso:country":"GB",
    "wof:name":"N12 8BE",
    "wof:placetype":"postalcode"
},
  "geometry": {"coordinates":[-0.18015791080275,51.61882967446778],"type":"Point"}
}