{
  "type": "Feature",
  "properties": {
    "iso:country":"GB",
    "wof:name":"E8 3PN",
    "wof:placetype":"postalcode"
},
  "geometry": {"coordinates":[-0.05732500733389,51.54071255337755],"type":"Point"}
}