{
  "type": "Feature",
  "properties": {
    "iso:country":"GB",
    "wof:name":"TW7 5PZ",
    "wof:placetype":"postalcode"
},
  "geometry": {"coordinates":[-0.33352081278666,51.48588154686809],"type":"Point"}
}