{
  "type": "Feature",
  "properties": {
    "date:inception_lower": "1980-01-01",
    "date:inception_upper": "1980-01-01",
    "iso:country": "GB",
    "wof:name": "TW7 5PZ",
    "wof:placetype": "postalcode"
  },
  "geometry": {"coordinates":[-0.333521,51.485882],"type":"Point"}
}
