{
  "type": "Feature",
  "properties": {
    "iso:country": "GB",
    "wof:name": "G81 5BE",
    "wof:placetype": "postalcode"
  },
  "geometry": {"coordinates":[-4.390776,55.930453],"type":"Point"}
}
