{
  "type": "Feature",
  "properties": {
    "iso:country":"GB",
    "wof:name":"RH13 5AZ",
    "wof:placetype":"postalcode"
},
  "geometry": {"coordinates":[-0.31229635413988,51.07099883555934],"type":"Point"}
}