{
  "type": "Feature",
  "properties": {
    "date:inception_lower": "1980-01-01",
    "date:inception_upper": "1980-01-01",
    "iso:country": "GB",
    "wof:name": "WV6 8SB",
    "wof:placetype": "postalcode"
  },
  "geometry": {"coordinates":[-2.172935,52.599796],"type":"Point"}
}
