{
  "type": "Feature",
  "properties": {
    "date:inception_lower":"2015-09-01",
    "date:inception_upper":"2015-09-30",
    "iso:country":"GB",
    "wof:name":"BD23 2UZ",
    "wof:placetype":"postalcode"
},
  "geometry": {"coordinates":[-1.996173,53.962234],"type":"Point"}
}