{
  "type": "Feature",
  "properties": {
    "iso:country":"GB",
    "wof:name":"KT6 6AE",
    "wof:placetype":"postalcode"
},
  "geometry": {"coordinates":[-0.29838429053749,51.39354620578159],"type":"Point"}
}