{
  "type": "Feature",
  "properties": {
    "iso:country": "GB",
    "wof:name": "EH21 8BF",
    "wof:placetype": "postalcode"
  },
  "geometry": {"coordinates":[-3.00262,55.939993],"type":"Point"}
}
