{
  "type": "Feature",
  "properties": {
    "date:inception_lower": "2018-06-01",
    "date:inception_upper": "2018-06-01",
    "iso:country": "GB",
    "wof:name": "EH21 8BF",
    "wof:placetype": "postalcode"
  },
  "geometry": {"coordinates":[-3.00262,55.939993],"type":"Point"}
}
