{
  "type": "Feature",
  "properties": {
    "date:inception_lower":"1980-01-01",
    "date:inception_upper":"1980-01-31",
    "iso:country":"GB",
    "wof:name":"NG23 7QB",
    "wof:placetype":"postalcode"
},
  "geometry": {"coordinates":[-0.739068,53.123424],"type":"Point"}
}