{
  "type": "Feature",
  "properties": {
    "iso:country": "GB",
    "wof:name": "NG23 7QB",
    "wof:placetype": "postalcode"
  },
  "geometry": {"coordinates":[-0.739068,53.123424],"type":"Point"}
}
