{
  "type": "Feature",
  "properties": {
    "iso:country":"GB",
    "wof:name":"TQ9 7SY",
    "wof:placetype":"postalcode"
},
  "geometry": {"coordinates":[-3.71310489733799,50.39435921373366],"type":"Point"}
}