{
  "type": "Feature",
  "properties": {
    "date:inception_lower": "1993-01-01",
    "date:inception_upper": "1993-01-01",
    "iso:country": "GB",
    "wof:name": "WR11 4XL",
    "wof:placetype": "postalcode"
  },
  "geometry": {"coordinates":[-1.946464,52.093605],"type":"Point"}
}
