{
  "type": "Feature",
  "properties": {
    "date:inception_lower": "1980-01-01",
    "date:inception_upper": "1980-01-01",
    "iso:country": "GB",
    "wof:name": "M6 5GS",
    "wof:placetype": "postalcode"
  },
  "geometry": {"coordinates":[-2.2967,53.482661],"type":"Point"}
}
