{
  "type": "Feature",
  "properties": {
    "iso:country":"GB",
    "wof:name":"E13 0AB",
    "wof:placetype":"postalcode"
},
  "geometry": {"coordinates":[0.02427724455518,51.52985451444607],"type":"Point"}
}