{
  "type": "Feature",
  "properties": {
    "iso:country":"GB",
    "wof:name":"M32 0TE",
    "wof:placetype":"postalcode"
},
  "geometry": {"coordinates":[-2.29987451865425,53.44992640699648],"type":"Point"}
}