{
  "type": "Feature",
  "properties": {
    "iso:country": "GB",
    "wof:name": "M32 0TE",
    "wof:placetype": "postalcode"
  },
  "geometry": {"coordinates":[-2.299874,53.449926],"type":"Point"}
}
