{
  "type": "Feature",
  "properties": {
    "iso:country":"GB",
    "wof:name":"CV3 1AA",
    "wof:placetype":"postalcode"
},
  "geometry": {"coordinates":[-1.48314394825147,52.40533132832647],"type":"Point"}
}