{
  "type": "Feature",
  "properties": {
    "iso:country": "GB",
    "wof:name": "KY16 9LZ",
    "wof:placetype": "postalcode"
  },
  "geometry": {"coordinates":[-2.816053,56.336689],"type":"Point"}
}
