{
  "type": "Feature",
  "properties": {
    "date:inception_lower": "1993-01-01",
    "date:inception_upper": "1993-01-01",
    "iso:country": "GB",
    "wof:name": "CF64 5TF",
    "wof:placetype": "postalcode"
  },
  "geometry": {"coordinates":[-3.22269,51.408274],"type":"Point"}
}
