{
  "type": "Feature",
  "properties": {
    "date:inception_lower":"1980-01-01",
    "date:inception_upper":"1980-01-31",
    "iso:country":"GB",
    "wof:name":"IP1 6HZ",
    "wof:placetype":"postalcode"
},
  "geometry": {"coordinates":[1.128229,52.083085],"type":"Point"}
}