{
  "type": "Feature",
  "properties": {
    "iso:country": "GB",
    "wof:name": "IP1 6HZ",
    "wof:placetype": "postalcode"
  },
  "geometry": {"coordinates":[1.128229,52.083085],"type":"Point"}
}
