{
  "type": "Feature",
  "properties": {
    "date:inception_lower":"2017-07-01",
    "date:inception_upper":"2017-07-31",
    "iso:country":"GB",
    "wof:name":"W1S 1YJ",
    "wof:placetype":"postalcode"
},
  "geometry": {"coordinates":[-0.142114,51.513672],"type":"Point"}
}