{
  "type": "Feature",
  "properties": {
    "date:inception_lower": "1980-01-01",
    "date:inception_upper": "1980-01-01",
    "iso:country": "GB",
    "wof:name": "CH3 5NF",
    "wof:placetype": "postalcode"
  },
  "geometry": {"coordinates":[-2.861273,53.193052],"type":"Point"}
}
