{
  "type": "Feature",
  "properties": {
    "iso:country": "GB",
    "wof:name": "KY8 4DD",
    "wof:placetype": "postalcode"
  },
  "geometry": {"coordinates":[-3.000851,56.201999],"type":"Point"}
}
