{
  "type": "Feature",
  "properties": {
    "iso:country":"GB",
    "wof:name":"KY8 4DD",
    "wof:placetype":"postalcode"
},
  "geometry": {"coordinates":[-3.00085103027868,56.20199925664895],"type":"Point"}
}