{
  "type": "Feature",
  "properties": {
    "iso:country": "GB",
    "wof:name": "TR10 8QZ",
    "wof:placetype": "postalcode"
  },
  "geometry": {"coordinates":[-5.116306,50.170594],"type":"Point"}
}
