{
  "type": "Feature",
  "properties": {
    "date:inception_lower":"2015-05-01",
    "date:inception_upper":"2015-05-31",
    "iso:country":"GB",
    "wof:name":"GL56 0NF",
    "wof:placetype":"postalcode"
},
  "geometry": {"coordinates":[-1.689085,51.993996],"type":"Point"}
}