{
  "type": "Feature",
  "properties": {
    "iso:country": "GB",
    "wof:name": "HA2 9EZ",
    "wof:placetype": "postalcode"
  },
  "geometry": {"coordinates":[-0.376386,51.565255],"type":"Point"}
}
