{
  "type": "Feature",
  "properties": {
    "date:inception_lower": "1980-01-01",
    "date:inception_upper": "1980-01-01",
    "iso:country": "GB",
    "wof:name": "DY5 3TQ",
    "wof:placetype": "postalcode"
  },
  "geometry": {"coordinates":[-2.140063,52.482118],"type":"Point"}
}
