{
  "type": "Feature",
  "properties": {
    "date:inception_lower":"1997-12-01",
    "date:inception_upper":"1997-12-31",
    "iso:country":"GB",
    "wof:name":"SO51 6HH",
    "wof:placetype":"postalcode"
},
  "geometry": {"coordinates":[-1.59383,50.986896],"type":"Point"}
}