{
  "type": "Feature",
  "properties": {
    "date:inception_lower": "2018-02-01",
    "date:inception_upper": "2018-02-01",
    "iso:country": "GB",
    "wof:name": "CF37 9EH",
    "wof:placetype": "postalcode"
  },
  "geometry": {"coordinates":[-3.348979,51.595929],"type":"Point"}
}
