{
  "type": "Feature",
  "properties": {
    "date:inception_lower": "1980-01-01",
    "date:inception_upper": "1980-01-01",
    "iso:country": "GB",
    "wof:name": "ME3 7BT",
    "wof:placetype": "postalcode"
  },
  "geometry": {"coordinates":[0.457153,51.41495],"type":"Point"}
}
