{
  "type": "Feature",
  "properties": {
    "iso:country": "GB",
    "wof:name": "N4 2NY",
    "wof:placetype": "postalcode"
  },
  "geometry": {"coordinates":[-0.092609,51.566318],"type":"Point"}
}
