{
  "type": "Feature",
  "properties": {
    "iso:country":"GB",
    "wof:name":"PL1 3RZ",
    "wof:placetype":"postalcode"
},
  "geometry": {"coordinates":[-4.15957088642117,50.36369146699303],"type":"Point"}
}