{
  "type": "Feature",
  "properties": {
    "iso:country": "GB",
    "wof:name": "PL21 0XJ",
    "wof:placetype": "postalcode"
  },
  "geometry": {"coordinates":[-3.87745,50.40248],"type":"Point"}
}
