{
  "type": "Feature",
  "properties": {
    "date:inception_lower": "1995-07-01",
    "date:inception_upper": "1995-07-01",
    "iso:country": "GB",
    "wof:name": "PL21 0XJ",
    "wof:placetype": "postalcode"
  },
  "geometry": {"coordinates":[-3.87753,50.402464],"type":"Point"}
}
