{
  "type": "Feature",
  "properties": {
    "iso:country":"GB",
    "wof:name":"GU9 0HU",
    "wof:placetype":"postalcode"
},
  "geometry": {"coordinates":[-0.80341045215046,51.23335450395926],"type":"Point"}
}