{
  "type": "Feature",
  "properties": {
    "iso:country":"GB",
    "wof:name":"SE5 0NS",
    "wof:placetype":"postalcode"
},
  "geometry": {"coordinates":[-0.09506745256638,51.48363522757938],"type":"Point"}
}