{
  "type": "Feature",
  "properties": {
    "iso:country":"GB",
    "wof:name":"RG41 1NL",
    "wof:placetype":"postalcode"
},
  "geometry": {"coordinates":[-0.84779986929891,51.41889380106438],"type":"Point"}
}