{
  "type": "Feature",
  "properties": {
    "iso:country":"GB",
    "wof:name":"NW10 1AQ",
    "wof:placetype":"postalcode"
},
  "geometry": {"coordinates":[-0.23999586879916,51.54958413352982],"type":"Point"}
}