{
  "type": "Feature",
  "properties": {
    "iso:country":"GB",
    "wof:name":"BN20 0AB",
    "wof:placetype":"postalcode"
},
  "geometry": {"coordinates":[0.20049131354389,50.7437036787861],"type":"Point"}
}