{
  "type": "Feature",
  "properties": {
    "date:inception_lower": "1980-01-01",
    "date:inception_upper": "1980-01-01",
    "iso:country": "GB",
    "wof:name": "CW2 7NL",
    "wof:placetype": "postalcode"
  },
  "geometry": {"coordinates":[-2.452086,53.088707],"type":"Point"}
}
