{
  "type": "Feature",
  "properties": {
    "date:inception_lower": "1980-01-01",
    "date:inception_upper": "1980-01-01",
    "iso:country": "GB",
    "wof:name": "SL1 2DA",
    "wof:placetype": "postalcode"
  },
  "geometry": {"coordinates":[-0.596255,51.504265],"type":"Point"}
}
