{
  "type": "Feature",
  "properties": {
    "iso:country":"GB",
    "wof:name":"TA20 4AS",
    "wof:placetype":"postalcode"
},
  "geometry": {"coordinates":[-2.90466212340627,50.88170649470104],"type":"Point"}
}