{
  "type": "Feature",
  "properties": {
    "date:inception_lower": "1980-01-01",
    "date:inception_upper": "1980-01-01",
    "iso:country": "GB",
    "wof:name": "TA20 4AS",
    "wof:placetype": "postalcode"
  },
  "geometry": {"coordinates":[-2.904662,50.881706],"type":"Point"}
}
