{
  "type": "Feature",
  "properties": {
    "iso:country":"GB",
    "wof:name":"TR14 0BJ",
    "wof:placetype":"postalcode"
},
  "geometry": {"coordinates":[-5.28002088786537,50.22483522036947],"type":"Point"}
}