{
  "type": "Feature",
  "properties": {
    "date:inception_lower":"1996-06-01",
    "date:inception_upper":"1996-06-30",
    "iso:country":"GB",
    "wof:name":"TR14 0BJ",
    "wof:placetype":"postalcode"
},
  "geometry": {"coordinates":[-5.28007,50.224825],"type":"Point"}
}