{
  "type": "Feature",
  "properties": {
    "iso:country": "GB",
    "wof:name": "CM5 0FN",
    "wof:placetype": "postalcode"
  },
  "geometry": {"coordinates":[0.305657,51.729337],"type":"Point"}
}
