{
  "type": "Feature",
  "properties": {
    "iso:country": "GB",
    "wof:name": "SA11 3PU",
    "wof:placetype": "postalcode"
  },
  "geometry": {"coordinates":[-3.786458,51.649935],"type":"Point"}
}
