{
  "type": "Feature",
  "properties": {
    "iso:country":"GB",
    "wof:name":"SA11 3PU",
    "wof:placetype":"postalcode"
},
  "geometry": {"coordinates":[-3.78645831872469,51.64993502363067],"type":"Point"}
}