{
  "type": "Feature",
  "properties": {
    "iso:country":"GB",
    "wof:name":"ST6 8DA",
    "wof:placetype":"postalcode"
},
  "geometry": {"coordinates":[-2.15845237223494,53.05633619093238],"type":"Point"}
}