{
  "type": "Feature",
  "properties": {
    "iso:country":"GB",
    "wof:name":"CV21 3AY",
    "wof:placetype":"postalcode"
},
  "geometry": {"coordinates":[-1.25961837942333,52.37052864831966],"type":"Point"}
}