{
  "type": "Feature",
  "properties": {
    "iso:country": "GB",
    "wof:name": "KT14 6PT",
    "wof:placetype": "postalcode"
  },
  "geometry": {"coordinates":[-0.487341,51.34525],"type":"Point"}
}
