{
  "type": "Feature",
  "properties": {
    "iso:country":"GB",
    "wof:name":"KT14 6PT",
    "wof:placetype":"postalcode"
},
  "geometry": {"coordinates":[-0.48734088951073,51.34524985566257],"type":"Point"}
}