{
  "type": "Feature",
  "properties": {
    "date:inception_lower": "2021-12-01",
    "date:inception_upper": "2021-12-01",
    "iso:country": "GB",
    "wof:name": "AB39 8BH",
    "wof:placetype": "postalcode"
  },
  "geometry": {"coordinates":[-2.17391,57.033904],"type":"Point"}
}
