{
  "type": "Feature",
  "properties": {
    "date:inception_lower":"1980-01-01",
    "date:inception_upper":"1980-01-31",
    "iso:country":"GB",
    "wof:name":"PO16 7HF",
    "wof:placetype":"postalcode"
},
  "geometry": {"coordinates":[-1.18278,50.862509],"type":"Point"}
}