{
  "type": "Feature",
  "properties": {
    "iso:country":"GB",
    "wof:name":"CF63 1RU",
    "wof:placetype":"postalcode"
},
  "geometry": {"coordinates":[-3.25946993728063,51.41824332089282],"type":"Point"}
}