{
  "type": "Feature",
  "properties": {
    "iso:country": "GB",
    "wof:name": "CF63 1RU",
    "wof:placetype": "postalcode"
  },
  "geometry": {"coordinates":[-3.25947,51.418243],"type":"Point"}
}
