{
  "type": "Feature",
  "properties": {
    "date:inception_lower": "1993-01-01",
    "date:inception_upper": "1993-01-01",
    "iso:country": "GB",
    "wof:name": "CF63 1RU",
    "wof:placetype": "postalcode"
  },
  "geometry": {"coordinates":[-3.25947,51.418243],"type":"Point"}
}
