{
  "type": "Feature",
  "properties": {
    "iso:country":"GB",
    "wof:name":"CB24 8AW",
    "wof:placetype":"postalcode"
},
  "geometry": {"coordinates":[0.12469341160598,52.29148022498267],"type":"Point"}
}