{
  "type": "Feature",
  "properties": {
    "iso:country": "GB",
    "wof:name": "CB24 8AW",
    "wof:placetype": "postalcode"
  },
  "geometry": {"coordinates":[0.124693,52.29148],"type":"Point"}
}
