{
  "type": "Feature",
  "properties": {
    "date:inception_lower": "1980-01-01",
    "date:inception_upper": "1980-01-01",
    "iso:country": "GB",
    "wof:name": "WA5 1AH",
    "wof:placetype": "postalcode"
  },
  "geometry": {"coordinates":[-2.609279,53.386978],"type":"Point"}
}
