{
  "type": "Feature",
  "properties": {
    "iso:country":"GB",
    "wof:name":"WA5 1AH",
    "wof:placetype":"postalcode"
},
  "geometry": {"coordinates":[-2.60927912933756,53.38697832096324],"type":"Point"}
}