{
  "type": "Feature",
  "properties": {
    "iso:country": "GB",
    "wof:name": "PE9 4DP",
    "wof:placetype": "postalcode"
  },
  "geometry": {"coordinates":[-0.522112,52.671881],"type":"Point"}
}
