{
  "type": "Feature",
  "properties": {
    "date:inception_lower":"2005-10-01",
    "date:inception_upper":"2005-10-31",
    "iso:country":"GB",
    "wof:name":"PE9 4DP",
    "wof:placetype":"postalcode"
},
  "geometry": {"coordinates":[-0.522112,52.671881],"type":"Point"}
}