{
  "type": "Feature",
  "properties": {
    "date:inception_lower":"2002-05-01",
    "date:inception_upper":"2002-05-31",
    "iso:country":"GB",
    "wof:name":"EX16 8HB",
    "wof:placetype":"postalcode"
},
  "geometry": {"coordinates":[-3.705204,50.915966],"type":"Point"}
}