{
  "type": "Feature",
  "properties": {
    "iso:country":"GB",
    "wof:name":"DL7 9QD",
    "wof:placetype":"postalcode"
},
  "geometry": {"coordinates":[-1.48981499964834,54.32499008786422],"type":"Point"}
}