{
  "type": "Feature",
  "properties": {
    "iso:country":"GB",
    "wof:name":"E2 0BP",
    "wof:placetype":"postalcode"
},
  "geometry": {"coordinates":[-0.05910416717206,51.52465428581743],"type":"Point"}
}