{
  "type": "Feature",
  "properties": {
    "date:inception_lower": "1980-01-01",
    "date:inception_upper": "1980-01-01",
    "iso:country": "GB",
    "wof:name": "CM18 7BA",
    "wof:placetype": "postalcode"
  },
  "geometry": {"coordinates":[0.126103,51.755855],"type":"Point"}
}
