{
  "type": "Feature",
  "properties": {
    "iso:country":"GB",
    "wof:name":"EH4 5PP",
    "wof:placetype":"postalcode"
},
  "geometry": {"coordinates":[-3.26639259669269,55.96744524495647],"type":"Point"}
}