{
  "type": "Feature",
  "properties": {
    "iso:country":"GB",
    "wof:name":"IP32 7DA",
    "wof:placetype":"postalcode"
},
  "geometry": {"coordinates":[0.73502179101883,52.24326922294593],"type":"Point"}
}