{
  "type": "Feature",
  "properties": {
    "iso:country": "GB",
    "wof:name": "IP32 7DA",
    "wof:placetype": "postalcode"
  },
  "geometry": {"coordinates":[0.735022,52.243269],"type":"Point"}
}
