{
  "type": "Feature",
  "properties": {
    "iso:country":"GB",
    "wof:name":"SR8 3RF",
    "wof:placetype":"postalcode"
},
  "geometry": {"coordinates":[-1.31915668977411,54.78597342285246],"type":"Point"}
}