{
  "type": "Feature",
  "properties": {
    "iso:country": "GB",
    "wof:name": "SR8 3RF",
    "wof:placetype": "postalcode"
  },
  "geometry": {"coordinates":[-1.319157,54.785973],"type":"Point"}
}
