{
  "type": "Feature",
  "properties": {
    "iso:country":"GB",
    "wof:name":"LN2 5QG",
    "wof:placetype":"postalcode"
},
  "geometry": {"coordinates":[-0.50791088634658,53.23379778868176],"type":"Point"}
}