{
  "type": "Feature",
  "properties": {
    "date:inception_lower":"2008-04-01",
    "date:inception_upper":"2008-04-30",
    "iso:country":"GB",
    "wof:name":"PL19 0AP",
    "wof:placetype":"postalcode"
},
  "geometry": {"coordinates":[-4.145794,50.550812],"type":"Point"}
}