{
  "type": "Feature",
  "properties": {
    "iso:country": "GB",
    "wof:name": "LE4 2WB",
    "wof:placetype": "postalcode"
  },
  "geometry": {"coordinates":[-1.149181,52.681752],"type":"Point"}
}
