{
  "type": "Feature",
  "properties": {
    "date:inception_lower":"1990-07-01",
    "date:inception_upper":"1990-07-31",
    "iso:country":"GB",
    "wof:name":"LE4 2WB",
    "wof:placetype":"postalcode"
},
  "geometry": {"coordinates":[-1.149181,52.681752],"type":"Point"}
}