{
  "type": "Feature",
  "properties": {
    "iso:country":"GB",
    "wof:name":"SA48 8DF",
    "wof:placetype":"postalcode"
},
  "geometry": {"coordinates":[-4.2050598279606,52.21250392728501],"type":"Point"}
}