{
  "type": "Feature",
  "properties": {
    "iso:country":"GB",
    "wof:name":"PR1 9RB",
    "wof:placetype":"postalcode"
},
  "geometry": {"coordinates":[-2.71070408441472,53.74684761080054],"type":"Point"}
}