{
  "type": "Feature",
  "properties": {
    "iso:country": "GB",
    "wof:name": "CO7 6XR",
    "wof:placetype": "postalcode"
  },
  "geometry": {"coordinates":[1.060966,51.970946],"type":"Point"}
}
