{
  "type": "Feature",
  "properties": {
    "iso:country":"GB",
    "wof:name":"CO7 6XR",
    "wof:placetype":"postalcode"
},
  "geometry": {"coordinates":[1.06096645623395,51.97094639442847],"type":"Point"}
}