{
  "type": "Feature",
  "properties": {
    "date:inception_lower": "1980-01-01",
    "date:inception_upper": "1980-01-01",
    "iso:country": "GB",
    "wof:name": "CO7 6XR",
    "wof:placetype": "postalcode"
  },
  "geometry": {"coordinates":[1.060966,51.970946],"type":"Point"}
}
