{
  "type": "Feature",
  "properties": {
    "iso:country":"GB",
    "wof:name":"BA1 7DP",
    "wof:placetype":"postalcode"
},
  "geometry": {"coordinates":[-2.32137993474947,51.40550906899526],"type":"Point"}
}