{
  "type": "Feature",
  "properties": {
    "date:inception_lower": "1980-01-01",
    "date:inception_upper": "1980-01-01",
    "iso:country": "GB",
    "wof:name": "BA1 7DP",
    "wof:placetype": "postalcode"
  },
  "geometry": {"coordinates":[-2.32138,51.405509],"type":"Point"}
}
