{
  "type": "Feature",
  "properties": {
    "date:inception_lower": "2006-05-01",
    "date:inception_upper": "2006-05-01",
    "iso:country": "GB",
    "wof:name": "NG20 8AG",
    "wof:placetype": "postalcode"
  },
  "geometry": {"coordinates":[-1.217436,53.196358],"type":"Point"}
}
