{
  "type": "Feature",
  "properties": {
    "iso:country":"GB",
    "wof:name":"ME4 6LH",
    "wof:placetype":"postalcode"
},
  "geometry": {"coordinates":[0.51611669809272,51.37244488800554],"type":"Point"}
}