{
  "type": "Feature",
  "properties": {
    "iso:country": "GB",
    "wof:name": "ME4 6LH",
    "wof:placetype": "postalcode"
  },
  "geometry": {"coordinates":[0.516117,51.372445],"type":"Point"}
}
