{
  "type": "Feature",
  "properties": {
    "date:inception_lower": "1980-01-01",
    "date:inception_upper": "1980-01-01",
    "iso:country": "GB",
    "wof:name": "WV13 1DR",
    "wof:placetype": "postalcode"
  },
  "geometry": {"coordinates":[-2.053112,52.590876],"type":"Point"}
}
