{
  "type": "Feature",
  "properties": {
    "iso:country":"GB",
    "wof:name":"WV13 1DR",
    "wof:placetype":"postalcode"
},
  "geometry": {"coordinates":[-2.05311197368097,52.59087626730637],"type":"Point"}
}