{
  "type": "Feature",
  "properties": {
    "date:inception_lower": "2013-10-01",
    "date:inception_upper": "2013-10-01",
    "iso:country": "GB",
    "wof:name": "FK6 5GU",
    "wof:placetype": "postalcode"
  },
  "geometry": {"coordinates":[-3.930971,56.024119],"type":"Point"}
}
