{
  "type": "Feature",
  "properties": {
    "iso:country":"GB",
    "wof:name":"PR1 8JB",
    "wof:placetype":"postalcode"
},
  "geometry": {"coordinates":[-2.71124863503526,53.75574273056226],"type":"Point"}
}