{
  "type": "Feature",
  "properties": {
    "date:inception_lower": "1999-06-01",
    "date:inception_upper": "1999-06-01",
    "iso:country": "GB",
    "wof:name": "CH45 1NQ",
    "wof:placetype": "postalcode"
  },
  "geometry": {"coordinates":[-3.037996,53.431724],"type":"Point"}
}
