{
  "type": "Feature",
  "properties": {
    "date:inception_lower": "1990-07-01",
    "date:inception_upper": "1990-07-01",
    "iso:country": "GB",
    "wof:name": "CB6 3SQ",
    "wof:placetype": "postalcode"
  },
  "geometry": {"coordinates":[0.181539,52.351579],"type":"Point"}
}
