{
  "type": "Feature",
  "properties": {
    "iso:country":"GB",
    "wof:name":"CB6 3SQ",
    "wof:placetype":"postalcode"
},
  "geometry": {"coordinates":[0.18153859557014,52.35157912475974],"type":"Point"}
}