{
  "type": "Feature",
  "properties": {
    "date:inception_lower": "1980-01-01",
    "date:inception_upper": "1980-01-01",
    "iso:country": "GB",
    "wof:name": "CV7 7DA",
    "wof:placetype": "postalcode"
  },
  "geometry": {"coordinates":[-1.617554,52.397569],"type":"Point"}
}
