{
  "type": "Feature",
  "properties": {
    "date:inception_lower":"1980-01-01",
    "date:inception_upper":"1980-01-31",
    "iso:country":"GB",
    "wof:name":"CA28 9PU",
    "wof:placetype":"postalcode"
},
  "geometry": {"coordinates":[-3.596218,54.532622],"type":"Point"}
}