{
  "type": "Feature",
  "properties": {
    "iso:country": "GB",
    "wof:name": "CA28 9PU",
    "wof:placetype": "postalcode"
  },
  "geometry": {"coordinates":[-3.596218,54.532622],"type":"Point"}
}
