{
  "type": "Feature",
  "properties": {
    "iso:country":"GB",
    "wof:name":"SK4 1QB",
    "wof:placetype":"postalcode"
},
  "geometry": {"coordinates":[-2.16743154744264,53.41986744520982],"type":"Point"}
}