{
  "type": "Feature",
  "properties": {
    "iso:country":"GB",
    "wof:name":"M26 1BW",
    "wof:placetype":"postalcode"
},
  "geometry": {"coordinates":[-2.32358065166877,53.55156877197294],"type":"Point"}
}