{
  "type": "Feature",
  "properties": {
    "date:inception_lower": "1980-01-01",
    "date:inception_upper": "1980-01-01",
    "iso:country": "GB",
    "wof:name": "ST6 8QH",
    "wof:placetype": "postalcode"
  },
  "geometry": {"coordinates":[-2.1342,53.077976],"type":"Point"}
}
