{
  "type": "Feature",
  "properties": {
    "iso:country":"GB",
    "wof:name":"ST6 8QH",
    "wof:placetype":"postalcode"
},
  "geometry": {"coordinates":[-2.13420043127986,53.07797579067862],"type":"Point"}
}