{
  "type": "Feature",
  "properties": {
    "iso:country": "GB",
    "wof:name": "CR0 8HA",
    "wof:placetype": "postalcode"
  },
  "geometry": {"coordinates":[-0.029672,51.376791],"type":"Point"}
}
