{
  "type": "Feature",
  "properties": {
    "iso:country":"GB",
    "wof:name":"CR0 8HA",
    "wof:placetype":"postalcode"
},
  "geometry": {"coordinates":[-0.02967175821417,51.37679082477475],"type":"Point"}
}