{
  "type": "Feature",
  "properties": {
    "iso:country":"GB",
    "wof:name":"M24 2BB",
    "wof:placetype":"postalcode"
},
  "geometry": {"coordinates":[-2.17264377665523,53.54365786561657],"type":"Point"}
}