{
  "type": "Feature",
  "properties": {
    "iso:country":"GB",
    "wof:name":"DN35 9QH",
    "wof:placetype":"postalcode"
},
  "geometry": {"coordinates":[-0.04687277724957,53.54256026450422],"type":"Point"}
}