{
  "type": "Feature",
  "properties": {
    "date:inception_lower":"1980-01-01",
    "date:inception_upper":"1980-01-31",
    "iso:country":"GB",
    "wof:name":"DN35 9QH",
    "wof:placetype":"postalcode"
},
  "geometry": {"coordinates":[-0.046873,53.54256],"type":"Point"}
}