{
  "type": "Feature",
  "properties": {
    "iso:country": "GB",
    "wof:name": "DN35 9QH",
    "wof:placetype": "postalcode"
  },
  "geometry": {"coordinates":[-0.046873,53.54256],"type":"Point"}
}
