{
  "type": "Feature",
  "properties": {
    "date:inception_lower": "1981-06-01",
    "date:inception_upper": "1981-06-01",
    "iso:country": "GB",
    "wof:name": "PE21 8JG",
    "wof:placetype": "postalcode"
  },
  "geometry": {"coordinates":[-0.042782,52.980468],"type":"Point"}
}
