{
  "type": "Feature",
  "properties": {
    "iso:country":"GB",
    "wof:name":"MK41 9LU",
    "wof:placetype":"postalcode"
},
  "geometry": {"coordinates":[-0.43528719648185,52.14489613778539],"type":"Point"}
}