{
  "type": "Feature",
  "properties": {
    "iso:country":"GB",
    "wof:name":"PR7 6HY",
    "wof:placetype":"postalcode"
},
  "geometry": {"coordinates":[-2.67335046634897,53.66113538017921],"type":"Point"}
}