{
  "type": "Feature",
  "properties": {
    "iso:country":"GB",
    "wof:name":"HA3 0NJ",
    "wof:placetype":"postalcode"
},
  "geometry": {"coordinates":[-0.29955639382075,51.58073038858914],"type":"Point"}
}