{
  "type": "Feature",
  "properties": {
    "iso:country": "GB",
    "wof:name": "HA3 0NJ",
    "wof:placetype": "postalcode"
  },
  "geometry": {"coordinates":[-0.299533,51.580732],"type":"Point"}
}
