{
  "type": "Feature",
  "properties": {
    "iso:country": "GB",
    "wof:name": "RM16 2QP",
    "wof:placetype": "postalcode"
  },
  "geometry": {"coordinates":[0.346467,51.497447],"type":"Point"}
}
