{
  "type": "Feature",
  "properties": {
    "date:inception_lower": "1980-01-01",
    "date:inception_upper": "1980-01-01",
    "iso:country": "GB",
    "wof:name": "DE55 1AS",
    "wof:placetype": "postalcode"
  },
  "geometry": {"coordinates":[-1.383927,53.07342],"type":"Point"}
}
