{
  "type": "Feature",
  "properties": {
    "iso:country":"GB",
    "wof:name":"DE55 1AS",
    "wof:placetype":"postalcode"
},
  "geometry": {"coordinates":[-1.38392679478913,53.07342018218476],"type":"Point"}
}