{
  "type": "Feature",
  "properties": {
    "date:inception_lower": "1993-08-01",
    "date:inception_upper": "1993-08-01",
    "iso:country": "GB",
    "wof:name": "HP10 0JJ",
    "wof:placetype": "postalcode"
  },
  "geometry": {"coordinates":[-0.686162,51.573439],"type":"Point"}
}
