{
  "type": "Feature",
  "properties": {
    "iso:country":"GB",
    "wof:name":"HP10 0JJ",
    "wof:placetype":"postalcode"
},
  "geometry": {"coordinates":[-0.68616167543203,51.57343867910085],"type":"Point"}
}