{
  "type": "Feature",
  "properties": {
    "iso:country":"GB",
    "wof:name":"BR2 9AU",
    "wof:placetype":"postalcode"
},
  "geometry": {"coordinates":[0.01020648146671,51.39391920265086],"type":"Point"}
}