{
  "type": "Feature",
  "properties": {
    "iso:country":"GB",
    "wof:name":"CH7 4TH",
    "wof:placetype":"postalcode"
},
  "geometry": {"coordinates":[-3.09019427399795,53.12588680208811],"type":"Point"}
}