{
  "type": "Feature",
  "properties": {
    "iso:country":"GB",
    "wof:name":"NW9 9LE",
    "wof:placetype":"postalcode"
},
  "geometry": {"coordinates":[-0.27787289640686,51.59116894879039],"type":"Point"}
}