{
  "type": "Feature",
  "properties": {
    "iso:country":"GB",
    "wof:name":"BD1 4AS",
    "wof:placetype":"postalcode"
},
  "geometry": {"coordinates":[-1.74939824691984,53.79619640189764],"type":"Point"}
}