{
  "type": "Feature",
  "properties": {
    "iso:country":"GB",
    "wof:name":"SK8 6DR",
    "wof:placetype":"postalcode"
},
  "geometry": {"coordinates":[-2.20295030014324,53.37742217430511],"type":"Point"}
}