{
  "type": "Feature",
  "properties": {
    "iso:country": "GB",
    "wof:name": "AB42 4QX",
    "wof:placetype": "postalcode"
  },
  "geometry": {"coordinates":[-2.171793,57.559901],"type":"Point"}
}
