{
  "type": "Feature",
  "properties": {
    "date:inception_lower":"1994-05-01",
    "date:inception_upper":"1994-05-31",
    "iso:country":"GB",
    "wof:name":"M20 3BA",
    "wof:placetype":"postalcode"
},
  "geometry": {"coordinates":[-2.229437,53.4278],"type":"Point"}
}