{
  "type": "Feature",
  "properties": {
    "iso:country":"GB",
    "wof:name":"WF14 9QF",
    "wof:placetype":"postalcode"
},
  "geometry": {"coordinates":[-1.70963261449436,53.6804032548939],"type":"Point"}
}