{
  "type": "Feature",
  "properties": {
    "iso:country":"GB",
    "wof:name":"UB3 1SG",
    "wof:placetype":"postalcode"
},
  "geometry": {"coordinates":[-0.42249170520231,51.50664320086224],"type":"Point"}
}