{
  "type": "Feature",
  "properties": {
    "iso:country": "GB",
    "wof:name": "LL51 9DQ",
    "wof:placetype": "postalcode"
  },
  "geometry": {"coordinates":[-4.269751,52.996353],"type":"Point"}
}
