{
  "type": "Feature",
  "properties": {
    "date:inception_lower":"1980-01-01",
    "date:inception_upper":"1980-01-31",
    "iso:country":"GB",
    "wof:name":"LL51 9DQ",
    "wof:placetype":"postalcode"
},
  "geometry": {"coordinates":[-4.269751,52.996353],"type":"Point"}
}