{
  "type": "Feature",
  "properties": {
    "iso:country":"GB",
    "wof:name":"RH2 0BU",
    "wof:placetype":"postalcode"
},
  "geometry": {"coordinates":[-0.19674574440465,51.24127228187604],"type":"Point"}
}