{
  "type": "Feature",
  "properties": {
    "iso:country":"GB",
    "wof:name":"GL6 7PH",
    "wof:placetype":"postalcode"
},
  "geometry": {"coordinates":[-2.1154892247416,51.7386093933077],"type":"Point"}
}