{
  "type": "Feature",
  "properties": {
    "iso:country": "GB",
    "wof:name": "GL6 7PH",
    "wof:placetype": "postalcode"
  },
  "geometry": {"coordinates":[-2.115489,51.738609],"type":"Point"}
}
