{
  "type": "Feature",
  "properties": {
    "iso:country":"GB",
    "wof:name":"BD2 3PX",
    "wof:placetype":"postalcode"
},
  "geometry": {"coordinates":[-1.71578951939661,53.80932488380402],"type":"Point"}
}