{
  "type": "Feature",
  "properties": {
    "date:inception_lower":"1980-01-01",
    "date:inception_upper":"1980-01-31",
    "iso:country":"GB",
    "wof:name":"BD2 3PX",
    "wof:placetype":"postalcode"
},
  "geometry": {"coordinates":[-1.715794,53.80934],"type":"Point"}
}