{
  "type": "Feature",
  "properties": {
    "iso:country":"GB",
    "wof:name":"CM8 1PH",
    "wof:placetype":"postalcode"
},
  "geometry": {"coordinates":[0.62928726911373,51.79288657659153],"type":"Point"}
}