{
  "type": "Feature",
  "properties": {
    "iso:country":"GB",
    "wof:name":"PO8 9EJ",
    "wof:placetype":"postalcode"
},
  "geometry": {"coordinates":[-1.00621891499775,50.89714595555821],"type":"Point"}
}