{
  "type": "Feature",
  "properties": {
    "iso:country":"GB",
    "wof:name":"ME20 6PS",
    "wof:placetype":"postalcode"
},
  "geometry": {"coordinates":[0.4423957328231,51.30289384951463],"type":"Point"}
}