{
  "type": "Feature",
  "properties": {
    "iso:country": "GB",
    "wof:name": "WF10 3SG",
    "wof:placetype": "postalcode"
  },
  "geometry": {"coordinates":[-1.311124,53.726988],"type":"Point"}
}
