{
  "type": "Feature",
  "properties": {
    "iso:country":"GB",
    "wof:name":"WF10 3SG",
    "wof:placetype":"postalcode"
},
  "geometry": {"coordinates":[-1.3111078761929,53.72705109544668],"type":"Point"}
}