{
  "type": "Feature",
  "properties": {
    "date:inception_lower":"1980-01-01",
    "date:inception_upper":"1980-01-31",
    "iso:country":"GB",
    "wof:name":"WF10 3SG",
    "wof:placetype":"postalcode"
},
  "geometry": {"coordinates":[-1.311124,53.726988],"type":"Point"}
}