{
  "type": "Feature",
  "properties": {
    "iso:country":"GB",
    "wof:name":"DA1 3RU",
    "wof:placetype":"postalcode"
},
  "geometry": {"coordinates":[0.17686876700189,51.44566369020401],"type":"Point"}
}