{
  "type": "Feature",
  "properties": {
    "iso:country": "GB",
    "wof:name": "DA1 3RU",
    "wof:placetype": "postalcode"
  },
  "geometry": {"coordinates":[0.176869,51.445664],"type":"Point"}
}
