{
  "type": "Feature",
  "properties": {
    "date:inception_lower": "1994-12-01",
    "date:inception_upper": "1994-12-01",
    "iso:country": "GB",
    "wof:name": "SO53 3NW",
    "wof:placetype": "postalcode"
  },
  "geometry": {"coordinates":[-1.393112,50.971143],"type":"Point"}
}
