{
  "type": "Feature",
  "properties": {
    "iso:country":"GB",
    "wof:name":"SO53 3NW",
    "wof:placetype":"postalcode"
},
  "geometry": {"coordinates":[-1.39311195846761,50.97114342291027],"type":"Point"}
}