{
  "type": "Feature",
  "properties": {
    "iso:country":"GB",
    "wof:name":"SO15 0LR",
    "wof:placetype":"postalcode"
},
  "geometry": {"coordinates":[-1.46924464302606,50.92034722798118],"type":"Point"}
}