{
  "type": "Feature",
  "properties": {
    "iso:country":"GB",
    "wof:name":"CT10 3PB",
    "wof:placetype":"postalcode"
},
  "geometry": {"coordinates":[1.44012102247224,51.36902580281438],"type":"Point"}
}