{
  "type": "Feature",
  "properties": {
    "date:inception_lower": "1990-02-01",
    "date:inception_upper": "1990-02-01",
    "iso:country": "GB",
    "wof:name": "CT10 3PB",
    "wof:placetype": "postalcode"
  },
  "geometry": {"coordinates":[1.440147,51.369033],"type":"Point"}
}
