{
  "type": "Feature",
  "properties": {
    "iso:country":"GB",
    "wof:name":"CF82 8FD",
    "wof:placetype":"postalcode"
},
  "geometry": {"coordinates":[-3.25247457973423,51.662726748121],"type":"Point"}
}