{
  "type": "Feature",
  "properties": {
    "iso:country": "GB",
    "wof:name": "B90 1FW",
    "wof:placetype": "postalcode"
  },
  "geometry": {"coordinates":[-1.842542,52.382528],"type":"Point"}
}
