{
  "type": "Feature",
  "properties": {
    "iso:country":"GB",
    "wof:name":"B90 1FW",
    "wof:placetype":"postalcode"
},
  "geometry": {"coordinates":[-1.84261905377113,52.38357459789648],"type":"Point"}
}