{
  "type": "Feature",
  "properties": {
    "iso:country":"GB",
    "wof:name":"NE31 2QJ",
    "wof:placetype":"postalcode"
},
  "geometry": {"coordinates":[-1.51364515464612,54.9654241750325],"type":"Point"}
}