{
  "type": "Feature",
  "properties": {
    "iso:country":"GB",
    "wof:name":"CV8 3FP",
    "wof:placetype":"postalcode"
},
  "geometry": {"coordinates":[-1.4334187654115,52.36147407896821],"type":"Point"}
}