{
  "type": "Feature",
  "properties": {
    "iso:country": "GB",
    "wof:name": "CV8 3FP",
    "wof:placetype": "postalcode"
  },
  "geometry": {"coordinates":[-1.433419,52.361474],"type":"Point"}
}
