{
  "type": "Feature",
  "properties": {
    "date:inception_lower": "1980-01-01",
    "date:inception_upper": "1980-01-01",
    "iso:country": "GB",
    "wof:name": "E14 8LP",
    "wof:placetype": "postalcode"
  },
  "geometry": {"coordinates":[-0.024108,51.500212],"type":"Point"}
}
