{
  "type": "Feature",
  "properties": {
    "date:inception_lower": "1980-01-01",
    "date:inception_upper": "1980-01-01",
    "iso:country": "GB",
    "wof:name": "ST5 6EQ",
    "wof:placetype": "postalcode"
  },
  "geometry": {"coordinates":[-2.249345,53.015244],"type":"Point"}
}
