{
  "type": "Feature",
  "properties": {
    "date:inception_lower": "2020-08-01",
    "date:inception_upper": "2020-08-01",
    "iso:country": "GB",
    "wof:name": "SA68 0AB",
    "wof:placetype": "postalcode"
  },
  "geometry": {"coordinates":[-4.708461,51.732288],"type":"Point"}
}
