{
  "type": "Feature",
  "properties": {
    "iso:country":"GB",
    "wof:name":"PE9 2XA",
    "wof:placetype":"postalcode"
},
  "geometry": {"coordinates":[-0.49576481522896,52.65613947602859],"type":"Point"}
}