{
  "type": "Feature",
  "properties": {
    "iso:country":"GB",
    "wof:name":"NN2 7ES",
    "wof:placetype":"postalcode"
},
  "geometry": {"coordinates":[-0.87904399977688,52.2580174807536],"type":"Point"}
}