{
  "type": "Feature",
  "properties": {
    "date:inception_lower": "2022-04-01",
    "date:inception_upper": "2022-04-01",
    "iso:country": "GB",
    "wof:name": "RG14 5HJ",
    "wof:placetype": "postalcode"
  },
  "geometry": {"coordinates":[-1.324264,51.398716],"type":"Point"}
}
