{
  "type": "Feature",
  "properties": {
    "date:inception_lower":"1980-01-01",
    "date:inception_upper":"1980-01-31",
    "iso:country":"GB",
    "wof:name":"NG24 3AH",
    "wof:placetype":"postalcode"
},
  "geometry": {"coordinates":[-0.789752,53.063477],"type":"Point"}
}