{
  "type": "Feature",
  "properties": {
    "iso:country": "GB",
    "wof:name": "NG24 3AH",
    "wof:placetype": "postalcode"
  },
  "geometry": {"coordinates":[-0.789752,53.063477],"type":"Point"}
}
