{
  "type": "Feature",
  "properties": {
    "iso:country": "GB",
    "wof:name": "LN3 4GH",
    "wof:placetype": "postalcode"
  },
  "geometry": {"coordinates":[-0.455483,53.245949],"type":"Point"}
}
