{
  "type": "Feature",
  "properties": {
    "iso:country": "GB",
    "wof:name": "BH18 8NN",
    "wof:placetype": "postalcode"
  },
  "geometry": {"coordinates":[-1.985275,50.756809],"type":"Point"}
}
