{
  "type": "Feature",
  "properties": {
    "date:inception_lower":"1980-01-01",
    "date:inception_upper":"1980-01-31",
    "iso:country":"GB",
    "wof:name":"TS3 0QW",
    "wof:placetype":"postalcode"
},
  "geometry": {"coordinates":[-1.176533,54.552076],"type":"Point"}
}