{
  "type": "Feature",
  "properties": {
    "iso:country": "GB",
    "wof:name": "TS3 0QW",
    "wof:placetype": "postalcode"
  },
  "geometry": {"coordinates":[-1.176533,54.552076],"type":"Point"}
}
