{
  "type": "Feature",
  "properties": {
    "iso:country":"GB",
    "wof:name":"TS3 0QW",
    "wof:placetype":"postalcode"
},
  "geometry": {"coordinates":[-1.17653335190013,54.55207588172883],"type":"Point"}
}