{
  "type": "Feature",
  "properties": {
    "iso:country": "GB",
    "wof:name": "NN16 8NA",
    "wof:placetype": "postalcode"
  },
  "geometry": {"coordinates":[-0.719628,52.402718],"type":"Point"}
}
