{
  "type": "Feature",
  "properties": {
    "iso:country":"GB",
    "wof:name":"CO2 0PT",
    "wof:placetype":"postalcode"
},
  "geometry": {"coordinates":[0.82454668540449,51.8256516214012],"type":"Point"}
}