{
  "type": "Feature",
  "properties": {
    "iso:country":"GB",
    "wof:name":"EH9 1LY",
    "wof:placetype":"postalcode"
},
  "geometry": {"coordinates":[-3.18495088521842,55.93949282172252],"type":"Point"}
}