{
  "type": "Feature",
  "properties": {
    "date:inception_lower":"2002-07-01",
    "date:inception_upper":"2002-07-31",
    "iso:country":"GB",
    "wof:name":"HG2 9QG",
    "wof:placetype":"postalcode"
},
  "geometry": {"coordinates":[-1.54121,53.976319],"type":"Point"}
}