{
  "type": "Feature",
  "properties": {
    "iso:country":"GB",
    "wof:name":"HG2 9QG",
    "wof:placetype":"postalcode"
},
  "geometry": {"coordinates":[-1.54120959441377,53.97631901714131],"type":"Point"}
}