{
  "type": "Feature",
  "properties": {
    "iso:country": "GB",
    "wof:name": "HG2 9QG",
    "wof:placetype": "postalcode"
  },
  "geometry": {"coordinates":[-1.54121,53.976319],"type":"Point"}
}
