{
  "type": "Feature",
  "properties": {
    "iso:country":"GB",
    "wof:name":"SO40 2SJ",
    "wof:placetype":"postalcode"
},
  "geometry": {"coordinates":[-1.51828728394157,50.92549657379119],"type":"Point"}
}