{
  "type": "Feature",
  "properties": {
    "date:inception_lower": "1994-12-01",
    "date:inception_upper": "1994-12-01",
    "iso:country": "GB",
    "wof:name": "SO40 2SJ",
    "wof:placetype": "postalcode"
  },
  "geometry": {"coordinates":[-1.518287,50.925497],"type":"Point"}
}
