{
  "type": "Feature",
  "properties": {
    "iso:country": "GB",
    "wof:name": "CH62 8DU",
    "wof:placetype": "postalcode"
  },
  "geometry": {"coordinates":[-2.978569,53.307684],"type":"Point"}
}
