{
  "type": "Feature",
  "properties": {
    "iso:country":"GB",
    "wof:name":"CH62 8DU",
    "wof:placetype":"postalcode"
},
  "geometry": {"coordinates":[-2.97856941634732,53.30768366426317],"type":"Point"}
}