{
  "type": "Feature",
  "properties": {
    "iso:country": "GB",
    "wof:name": "AB44 1UD",
    "wof:placetype": "postalcode"
  },
  "geometry": {"coordinates":[-2.503143,57.668586],"type":"Point"}
}
