{
  "type": "Feature",
  "properties": {
    "date:inception_lower": "1990-08-01",
    "date:inception_upper": "1990-08-01",
    "iso:country": "GB",
    "wof:name": "AB44 1UD",
    "wof:placetype": "postalcode"
  },
  "geometry": {"coordinates":[-2.503143,57.668586],"type":"Point"}
}
