{
  "type": "Feature",
  "properties": {
    "date:inception_lower": "2023-04-01",
    "date:inception_upper": "2023-04-01",
    "iso:country": "GB",
    "wof:name": "DE14 2DG",
    "wof:placetype": "postalcode"
  },
  "geometry": {"coordinates":[-1.644153,52.805001],"type":"Point"}
}
