{
  "type": "Feature",
  "properties": {
    "iso:country": "GB",
    "wof:name": "TA6 3SY",
    "wof:placetype": "postalcode"
  },
  "geometry": {"coordinates":[-3.012651,51.134148],"type":"Point"}
}
