{
  "type": "Feature",
  "properties": {
    "iso:country":"GB",
    "wof:name":"S66 3QF",
    "wof:placetype":"postalcode"
},
  "geometry": {"coordinates":[-1.26847686877433,53.42923415091857],"type":"Point"}
}