{
  "type": "Feature",
  "properties": {
    "iso:country":"GB",
    "wof:name":"DL15 8AG",
    "wof:placetype":"postalcode"
},
  "geometry": {"coordinates":[-1.73375047680384,54.6901759991967],"type":"Point"}
}