{
  "type": "Feature",
  "properties": {
    "iso:country": "GB",
    "wof:name": "NN14 4JX",
    "wof:placetype": "postalcode"
  },
  "geometry": {"coordinates":[-0.538431,52.395034],"type":"Point"}
}
