{
  "type": "Feature",
  "properties": {
    "iso:country":"GB",
    "wof:name":"NN14 4JX",
    "wof:placetype":"postalcode"
},
  "geometry": {"coordinates":[-0.53829738114333,52.39511586591221],"type":"Point"}
}