{
  "type": "Feature",
  "properties": {
    "iso:country":"GB",
    "wof:name":"NE3 9AN",
    "wof:placetype":"postalcode"
},
  "geometry": {"coordinates":[-1.63233725504598,55.00778840058346],"type":"Point"}
}