{
  "type": "Feature",
  "properties": {
    "iso:country": "GB",
    "wof:name": "E2 8GY",
    "wof:placetype": "postalcode"
  },
  "geometry": {"coordinates":[-0.070742,51.535181],"type":"Point"}
}
