{
  "type": "Feature",
  "properties": {
    "iso:country": "GB",
    "wof:name": "ST3 4UD",
    "wof:placetype": "postalcode"
  },
  "geometry": {"coordinates":[-2.128334,52.97263],"type":"Point"}
}
