{
  "type": "Feature",
  "properties": {
    "date:inception_lower": "2002-06-01",
    "date:inception_upper": "2002-06-01",
    "iso:country": "GB",
    "wof:name": "ST3 4UD",
    "wof:placetype": "postalcode"
  },
  "geometry": {"coordinates":[-2.128334,52.97263],"type":"Point"}
}
