{
  "type": "Feature",
  "properties": {
    "iso:country":"GB",
    "wof:name":"WF1 2LR",
    "wof:placetype":"postalcode"
},
  "geometry": {"coordinates":[-1.5025053406496,53.71277213390866],"type":"Point"}
}