{
  "type": "Feature",
  "properties": {
    "date:inception_lower":"1980-01-01",
    "date:inception_upper":"1980-01-31",
    "iso:country":"GB",
    "wof:name":"CW9 8JQ",
    "wof:placetype":"postalcode"
},
  "geometry": {"coordinates":[-2.515351,53.232382],"type":"Point"}
}