{
  "type": "Feature",
  "properties": {
    "iso:country": "GB",
    "wof:name": "CW9 8JQ",
    "wof:placetype": "postalcode"
  },
  "geometry": {"coordinates":[-2.515351,53.232382],"type":"Point"}
}
