{
  "type": "Feature",
  "properties": {
    "iso:country":"GB",
    "wof:name":"CW9 8JQ",
    "wof:placetype":"postalcode"
},
  "geometry": {"coordinates":[-2.51535147003917,53.23238212456347],"type":"Point"}
}