{
  "type": "Feature",
  "properties": {
    "iso:country": "GB",
    "wof:name": "SO16 6TU",
    "wof:placetype": "postalcode"
  },
  "geometry": {"coordinates":[-1.423087,50.932376],"type":"Point"}
}
