{
  "type": "Feature",
  "properties": {
    "iso:country":"GB",
    "wof:name":"NE15 6BZ",
    "wof:placetype":"postalcode"
},
  "geometry": {"coordinates":[-1.66835185562345,54.96527912679457],"type":"Point"}
}