{
  "type": "Feature",
  "properties": {
    "date:inception_lower": "2021-04-01",
    "date:inception_upper": "2021-04-01",
    "iso:country": "GB",
    "wof:name": "BS1 6ZB",
    "wof:placetype": "postalcode"
  },
  "geometry": {"coordinates":[-2.589418,51.451294],"type":"Point"}
}
