{
  "type": "Feature",
  "properties": {
    "iso:country": "GB",
    "wof:name": "SY5 7DB",
    "wof:placetype": "postalcode"
  },
  "geometry": {"coordinates":[-2.717804,52.643442],"type":"Point"}
}
