{
  "type": "Feature",
  "properties": {
    "iso:country":"GB",
    "wof:name":"SY5 7DB",
    "wof:placetype":"postalcode"
},
  "geometry": {"coordinates":[-2.71780388645755,52.64344224475808],"type":"Point"}
}