{
  "type": "Feature",
  "properties": {
    "date:inception_lower":"1980-01-01",
    "date:inception_upper":"1980-01-31",
    "iso:country":"GB",
    "wof:name":"BB11 3HB",
    "wof:placetype":"postalcode"
},
  "geometry": {"coordinates":[-2.232062,53.781384],"type":"Point"}
}