{
  "type": "Feature",
  "properties": {
    "iso:country":"GB",
    "wof:name":"CH3 5QB",
    "wof:placetype":"postalcode"
},
  "geometry": {"coordinates":[-2.85587405191666,53.18874910744852],"type":"Point"}
}