{
  "type": "Feature",
  "properties": {
    "date:inception_lower": "1980-01-01",
    "date:inception_upper": "1980-01-01",
    "iso:country": "GB",
    "wof:name": "LS25 3AL",
    "wof:placetype": "postalcode"
  },
  "geometry": {"coordinates":[-1.342493,53.833171],"type":"Point"}
}
