{
  "type": "Feature",
  "properties": {
    "iso:country":"GB",
    "wof:name":"EH19 3GS",
    "wof:placetype":"postalcode"
},
  "geometry": {"coordinates":[-3.09463750809892,55.86727696583878],"type":"Point"}
}