{
  "type": "Feature",
  "properties": {
    "date:inception_lower": "2011-12-01",
    "date:inception_upper": "2011-12-01",
    "iso:country": "GB",
    "wof:name": "EH19 3GS",
    "wof:placetype": "postalcode"
  },
  "geometry": {"coordinates":[-3.094637,55.867277],"type":"Point"}
}
