{
  "type": "Feature",
  "properties": {
    "iso:country":"GB",
    "wof:name":"CH7 6JJ",
    "wof:placetype":"postalcode"
},
  "geometry": {"coordinates":[-3.09660027938285,53.20135670588355],"type":"Point"}
}