{
  "type": "Feature",
  "properties": {
    "iso:country": "GB",
    "wof:name": "CH7 6JJ",
    "wof:placetype": "postalcode"
  },
  "geometry": {"coordinates":[-3.0966,53.201357],"type":"Point"}
}
