{
  "type": "Feature",
  "properties": {
    "iso:country":"GB",
    "wof:name":"TN1 2NQ",
    "wof:placetype":"postalcode"
},
  "geometry": {"coordinates":[0.27174410811893,51.13519427917014],"type":"Point"}
}