{
  "type": "Feature",
  "properties": {
    "iso:country": "GB",
    "wof:name": "TN1 2NQ",
    "wof:placetype": "postalcode"
  },
  "geometry": {"coordinates":[0.271744,51.135194],"type":"Point"}
}
