{
  "type": "Feature",
  "properties": {
    "iso:country": "GB",
    "wof:name": "ST15 0TN",
    "wof:placetype": "postalcode"
  },
  "geometry": {"coordinates":[-2.197987,52.892898],"type":"Point"}
}
