{
  "type": "Feature",
  "properties": {
    "iso:country":"GB",
    "wof:name":"L36 2QN",
    "wof:placetype":"postalcode"
},
  "geometry": {"coordinates":[-2.85196918534486,53.4186794170752],"type":"Point"}
}