{
  "type": "Feature",
  "properties": {
    "iso:country":"GB",
    "wof:name":"ME2 3XQ",
    "wof:placetype":"postalcode"
},
  "geometry": {"coordinates":[0.49951173819168,51.40366622078471],"type":"Point"}
}