{
  "type": "Feature",
  "properties": {
    "date:inception_lower": "1980-01-01",
    "date:inception_upper": "1980-01-01",
    "iso:country": "GB",
    "wof:name": "HX7 6PY",
    "wof:placetype": "postalcode"
  },
  "geometry": {"coordinates":[-2.042892,53.733633],"type":"Point"}
}
