{
  "type": "Feature",
  "properties": {
    "iso:country":"GB",
    "wof:name":"HX7 6PY",
    "wof:placetype":"postalcode"
},
  "geometry": {"coordinates":[-2.04289179211462,53.73363273872731],"type":"Point"}
}