{
  "type": "Feature",
  "properties": {
    "iso:country": "GB",
    "wof:name": "CF24 5HQ",
    "wof:placetype": "postalcode"
  },
  "geometry": {"coordinates":[-3.149792,51.477522],"type":"Point"}
}
