{
  "type": "Feature",
  "properties": {
    "date:inception_lower": "2014-06-01",
    "date:inception_upper": "2014-06-01",
    "iso:country": "GB",
    "wof:name": "CF24 5HQ",
    "wof:placetype": "postalcode"
  },
  "geometry": {"coordinates":[-3.149945,51.47753],"type":"Point"}
}
