{
  "type": "Feature",
  "properties": {
    "iso:country":"GB",
    "wof:name":"LU3 1PY",
    "wof:placetype":"postalcode"
},
  "geometry": {"coordinates":[-0.42773980088746,51.89900471118563],"type":"Point"}
}