{
  "type": "Feature",
  "properties": {
    "iso:country": "GB",
    "wof:name": "LU3 1PY",
    "wof:placetype": "postalcode"
  },
  "geometry": {"coordinates":[-0.42774,51.899005],"type":"Point"}
}
