{
  "type": "Feature",
  "properties": {
    "iso:country":"GB",
    "wof:name":"SO17 1NY",
    "wof:placetype":"postalcode"
},
  "geometry": {"coordinates":[-1.40196397028208,50.9294822402931],"type":"Point"}
}