{
  "type": "Feature",
  "properties": {
    "iso:country":"GB",
    "wof:name":"WF4 2DA",
    "wof:placetype":"postalcode"
},
  "geometry": {"coordinates":[-1.41852241622376,53.62474039596117],"type":"Point"}
}