{
  "type": "Feature",
  "properties": {
    "date:inception_lower": "1980-01-01",
    "date:inception_upper": "1980-01-01",
    "iso:country": "GB",
    "wof:name": "WF4 2DA",
    "wof:placetype": "postalcode"
  },
  "geometry": {"coordinates":[-1.418522,53.62474],"type":"Point"}
}
