{
  "type": "Feature",
  "properties": {
    "date:inception_lower": "1980-01-01",
    "date:inception_upper": "1980-01-01",
    "iso:country": "GB",
    "wof:name": "SP5 3JQ",
    "wof:placetype": "postalcode"
  },
  "geometry": {"coordinates":[-1.753311,50.994544],"type":"Point"}
}
