{
  "type": "Feature",
  "properties": {
    "iso:country": "GB",
    "wof:name": "SP5 3JQ",
    "wof:placetype": "postalcode"
  },
  "geometry": {"coordinates":[-1.753311,50.994544],"type":"Point"}
}
