{
  "type": "Feature",
  "properties": {
    "iso:country":"GB",
    "wof:name":"SP5 3JQ",
    "wof:placetype":"postalcode"
},
  "geometry": {"coordinates":[-1.75331128917808,50.99454366267701],"type":"Point"}
}