{
  "type": "Feature",
  "properties": {
    "date:inception_lower": "2008-04-01",
    "date:inception_upper": "2008-04-01",
    "iso:country": "GB",
    "wof:name": "NN1 1PB",
    "wof:placetype": "postalcode"
  },
  "geometry": {"coordinates":[-0.898488,52.236065],"type":"Point"}
}
