{
  "type": "Feature",
  "properties": {
    "iso:country":"GB",
    "wof:name":"SS7 2EQ",
    "wof:placetype":"postalcode"
},
  "geometry": {"coordinates":[0.62310699842387,51.55210136132725],"type":"Point"}
}