{
  "type": "Feature",
  "properties": {
    "iso:country": "GB",
    "wof:name": "GL56 0XR",
    "wof:placetype": "postalcode"
  },
  "geometry": {"coordinates":[-1.667542,51.932861],"type":"Point"}
}
