{
  "type": "Feature",
  "properties": {
    "date:inception_lower":"1990-07-01",
    "date:inception_upper":"1990-07-31",
    "iso:country":"GB",
    "wof:name":"GL56 0XR",
    "wof:placetype":"postalcode"
},
  "geometry": {"coordinates":[-1.667542,51.932861],"type":"Point"}
}