{
  "type": "Feature",
  "properties": {
    "iso:country":"GB",
    "wof:name":"IV2 7FQ",
    "wof:placetype":"postalcode"
},
  "geometry": {"coordinates":[-4.11229245520468,57.49451911586797],"type":"Point"}
}