{
  "type": "Feature",
  "properties": {
    "iso:country":"GB",
    "wof:name":"B73 5DW",
    "wof:placetype":"postalcode"
},
  "geometry": {"coordinates":[-1.84904518083375,52.54569944155965],"type":"Point"}
}