{
  "type": "Feature",
  "properties": {
    "date:inception_lower": "1980-01-01",
    "date:inception_upper": "1980-01-01",
    "iso:country": "GB",
    "wof:name": "B73 5DW",
    "wof:placetype": "postalcode"
  },
  "geometry": {"coordinates":[-1.849045,52.545699],"type":"Point"}
}
