{
  "type": "Feature",
  "properties": {
    "iso:country": "GB",
    "wof:name": "SP5 1BZ",
    "wof:placetype": "postalcode"
  },
  "geometry": {"coordinates":[-1.622103,51.128168],"type":"Point"}
}
