{
  "type": "Feature",
  "properties": {
    "iso:country":"GB",
    "wof:name":"CF5 1BU",
    "wof:placetype":"postalcode"
},
  "geometry": {"coordinates":[-3.2217931083852,51.48514700282445],"type":"Point"}
}