{
  "type": "Feature",
  "properties": {
    "iso:country":"GB",
    "wof:name":"NN3 8LQ",
    "wof:placetype":"postalcode"
},
  "geometry": {"coordinates":[-0.83101038451721,52.26664139195731],"type":"Point"}
}