{
  "type": "Feature",
  "properties": {
    "date:inception_lower": "1980-01-01",
    "date:inception_upper": "1980-01-01",
    "iso:country": "GB",
    "wof:name": "HG3 2EJ",
    "wof:placetype": "postalcode"
  },
  "geometry": {"coordinates":[-1.604185,54.022881],"type":"Point"}
}
