{
  "type": "Feature",
  "properties": {
    "iso:country":"GB",
    "wof:name":"HG3 2EJ",
    "wof:placetype":"postalcode"
},
  "geometry": {"coordinates":[-1.60401222869676,54.02279302359324],"type":"Point"}
}