{
  "type": "Feature",
  "properties": {
    "iso:country":"GB",
    "wof:name":"S6 6TG",
    "wof:placetype":"postalcode"
},
  "geometry": {"coordinates":[-1.53028018151673,53.40572343969548],"type":"Point"}
}