{
  "type": "Feature",
  "properties": {
    "iso:country":"GB",
    "wof:name":"BD20 6TW",
    "wof:placetype":"postalcode"
},
  "geometry": {"coordinates":[-1.95928423464934,53.89966766681548],"type":"Point"}
}