{
  "type": "Feature",
  "properties": {
    "date:inception_lower":"1980-01-01",
    "date:inception_upper":"1980-01-31",
    "iso:country":"GB",
    "wof:name":"BD20 6TW",
    "wof:placetype":"postalcode"
},
  "geometry": {"coordinates":[-1.959284,53.899668],"type":"Point"}
}