{
  "type": "Feature",
  "properties": {
    "iso:country":"GB",
    "wof:name":"SA19 8UR",
    "wof:placetype":"postalcode"
},
  "geometry": {"coordinates":[-3.95587654144316,52.04269204816258],"type":"Point"}
}