{
  "type": "Feature",
  "properties": {
    "iso:country": "GB",
    "wof:name": "NG10 3HF",
    "wof:placetype": "postalcode"
  },
  "geometry": {"coordinates":[-1.291006,52.889987],"type":"Point"}
}
