{
  "type": "Feature",
  "properties": {
    "iso:country":"GB",
    "wof:name":"M4 5EJ",
    "wof:placetype":"postalcode"
},
  "geometry": {"coordinates":[-2.2335712423658,53.48731381887408],"type":"Point"}
}