{
  "type": "Feature",
  "properties": {
    "date:inception_lower": "1980-01-01",
    "date:inception_upper": "1980-01-01",
    "iso:country": "GB",
    "wof:name": "DE13 9PX",
    "wof:placetype": "postalcode"
  },
  "geometry": {"coordinates":[-1.70256,52.812622],"type":"Point"}
}
