{
  "type": "Feature",
  "properties": {
    "iso:country": "GB",
    "wof:name": "SO16 6PS",
    "wof:placetype": "postalcode"
  },
  "geometry": {"coordinates":[-1.428167,50.93054],"type":"Point"}
}
