{
  "type": "Feature",
  "properties": {
    "iso:country": "GB",
    "wof:name": "L31 1ED",
    "wof:placetype": "postalcode"
  },
  "geometry": {"coordinates":[-2.913753,53.490987],"type":"Point"}
}
