{
  "type": "Feature",
  "properties": {
    "date:inception_lower": "1980-01-01",
    "date:inception_upper": "1980-01-01",
    "iso:country": "GB",
    "wof:name": "L31 1ED",
    "wof:placetype": "postalcode"
  },
  "geometry": {"coordinates":[-2.913525,53.49096],"type":"Point"}
}
