{
  "type": "Feature",
  "properties": {
    "iso:country":"GB",
    "wof:name":"L31 1ED",
    "wof:placetype":"postalcode"
},
  "geometry": {"coordinates":[-2.91375314002449,53.49098693568965],"type":"Point"}
}