{
  "type": "Feature",
  "properties": {
    "iso:country":"GB",
    "wof:name":"GL5 2RS",
    "wof:placetype":"postalcode"
},
  "geometry": {"coordinates":[-2.18701163016831,51.7236818460707],"type":"Point"}
}