{
  "type": "Feature",
  "properties": {
    "date:inception_lower":"1980-01-01",
    "date:inception_upper":"1980-01-31",
    "iso:country":"GB",
    "wof:name":"GL5 2RS",
    "wof:placetype":"postalcode"
},
  "geometry": {"coordinates":[-2.187012,51.723682],"type":"Point"}
}