{
  "type": "Feature",
  "properties": {
    "iso:country": "GB",
    "wof:name": "GL5 2RS",
    "wof:placetype": "postalcode"
  },
  "geometry": {"coordinates":[-2.187012,51.723682],"type":"Point"}
}
