{
  "type": "Feature",
  "properties": {
    "date:inception_lower": "1980-01-01",
    "date:inception_upper": "1980-01-01",
    "iso:country": "GB",
    "wof:name": "LA3 2UP",
    "wof:placetype": "postalcode"
  },
  "geometry": {"coordinates":[-2.902668,54.03581],"type":"Point"}
}
