{
  "type": "Feature",
  "properties": {
    "iso:country": "GB",
    "wof:name": "LA3 2UP",
    "wof:placetype": "postalcode"
  },
  "geometry": {"coordinates":[-2.902668,54.03581],"type":"Point"}
}
