{
  "type": "Feature",
  "properties": {
    "iso:country":"GB",
    "wof:name":"SA12 6AU",
    "wof:placetype":"postalcode"
},
  "geometry": {"coordinates":[-3.80718431868006,51.58806547727049],"type":"Point"}
}