{
  "type": "Feature",
  "properties": {
    "iso:country":"GB",
    "wof:name":"FY2 9TH",
    "wof:placetype":"postalcode"
},
  "geometry": {"coordinates":[-3.04820798786674,53.83820946902793],"type":"Point"}
}