{
  "type": "Feature",
  "properties": {
    "iso:country":"GB",
    "wof:name":"OX29 4UD",
    "wof:placetype":"postalcode"
},
  "geometry": {"coordinates":[-1.38058507781552,51.77376457477529],"type":"Point"}
}