{
  "type": "Feature",
  "properties": {
    "iso:country":"GB",
    "wof:name":"SN13 9JE",
    "wof:placetype":"postalcode"
},
  "geometry": {"coordinates":[-2.18632864112729,51.42349735107864],"type":"Point"}
}