{
  "type": "Feature",
  "properties": {
    "iso:country":"GB",
    "wof:name":"KA12 0PW",
    "wof:placetype":"postalcode"
},
  "geometry": {"coordinates":[-4.6570682190369,55.61971527165784],"type":"Point"}
}