{
  "type": "Feature",
  "properties": {
    "date:inception_lower": "1995-12-01",
    "date:inception_upper": "1995-12-01",
    "iso:country": "GB",
    "wof:name": "KA12 0PW",
    "wof:placetype": "postalcode"
  },
  "geometry": {"coordinates":[-4.657068,55.619715],"type":"Point"}
}
