{
  "type": "Feature",
  "properties": {
    "iso:country": "GB",
    "wof:name": "HX4 0FP",
    "wof:placetype": "postalcode"
  },
  "geometry": {"coordinates":[-1.920437,53.679146],"type":"Point"}
}
