{
  "type": "Feature",
  "properties": {
    "iso:country":"GB",
    "wof:name":"HX4 0FP",
    "wof:placetype":"postalcode"
},
  "geometry": {"coordinates":[-1.92043717942361,53.67914641197795],"type":"Point"}
}