{
  "type": "Feature",
  "properties": {
    "iso:country":"GB",
    "wof:name":"CT12 6RQ",
    "wof:placetype":"postalcode"
},
  "geometry": {"coordinates":[1.40913258828399,51.34846098696193],"type":"Point"}
}