{
  "type": "Feature",
  "properties": {
    "date:inception_lower": "1981-06-01",
    "date:inception_upper": "1981-06-01",
    "iso:country": "GB",
    "wof:name": "CT12 6RQ",
    "wof:placetype": "postalcode"
  },
  "geometry": {"coordinates":[1.409133,51.348461],"type":"Point"}
}
