{
  "type": "Feature",
  "properties": {
    "iso:country": "GB",
    "wof:name": "KT19 8FJ",
    "wof:placetype": "postalcode"
  },
  "geometry": {"coordinates":[-0.273445,51.349253],"type":"Point"}
}
