{
  "type": "Feature",
  "properties": {
    "iso:country":"GB",
    "wof:name":"ME4 5SN",
    "wof:placetype":"postalcode"
},
  "geometry": {"coordinates":[0.52508521908564,51.37378976718168],"type":"Point"}
}