{
  "type": "Feature",
  "properties": {
    "iso:country": "GB",
    "wof:name": "ME4 5SN",
    "wof:placetype": "postalcode"
  },
  "geometry": {"coordinates":[0.525085,51.37379],"type":"Point"}
}
