{
  "type": "Feature",
  "properties": {
    "date:inception_lower": "1980-01-01",
    "date:inception_upper": "1980-01-01",
    "iso:country": "GB",
    "wof:name": "CA26 3XX",
    "wof:placetype": "postalcode"
  },
  "geometry": {"coordinates":[-3.437276,54.54878],"type":"Point"}
}
