{
  "type": "Feature",
  "properties": {
    "iso:country": "GB",
    "wof:name": "CA26 3XX",
    "wof:placetype": "postalcode"
  },
  "geometry": {"coordinates":[-3.437276,54.54878],"type":"Point"}
}
