{
  "type": "Feature",
  "properties": {
    "iso:country":"GB",
    "wof:name":"BH19 2AN",
    "wof:placetype":"postalcode"
},
  "geometry": {"coordinates":[-1.95426026503084,50.6061457950229],"type":"Point"}
}