{
  "type": "Feature",
  "properties": {
    "iso:country":"GB",
    "wof:name":"FK2 7JS",
    "wof:placetype":"postalcode"
},
  "geometry": {"coordinates":[-3.79504534367672,56.00762481268441],"type":"Point"}
}