{
  "type": "Feature",
  "properties": {
    "date:inception_lower": "1995-07-01",
    "date:inception_upper": "1995-07-01",
    "iso:country": "GB",
    "wof:name": "SS7 4EH",
    "wof:placetype": "postalcode"
  },
  "geometry": {"coordinates":[0.551982,51.573132],"type":"Point"}
}
