{
  "type": "Feature",
  "properties": {
    "iso:country":"GB",
    "wof:name":"SS7 4EH",
    "wof:placetype":"postalcode"
},
  "geometry": {"coordinates":[0.55198181780472,51.57313223872247],"type":"Point"}
}