{
  "type": "Feature",
  "properties": {
    "date:inception_lower": "1980-01-01",
    "date:inception_upper": "1980-01-01",
    "iso:country": "GB",
    "wof:name": "CT21 5XJ",
    "wof:placetype": "postalcode"
  },
  "geometry": {"coordinates":[1.10666,51.073492],"type":"Point"}
}
