{
  "type": "Feature",
  "properties": {
    "iso:country":"GB",
    "wof:name":"CO7 7UE",
    "wof:placetype":"postalcode"
},
  "geometry": {"coordinates":[1.03837839130216,51.88307751025091],"type":"Point"}
}