{
  "type": "Feature",
  "properties": {
    "iso:country": "GB",
    "wof:name": "FK1 3DH",
    "wof:placetype": "postalcode"
  },
  "geometry": {"coordinates":[-3.81285,55.932467],"type":"Point"}
}
