{
  "type": "Feature",
  "properties": {
    "iso:country":"GB",
    "wof:name":"FK1 3DH",
    "wof:placetype":"postalcode"
},
  "geometry": {"coordinates":[-3.81285892475862,55.93247149637826],"type":"Point"}
}