{
  "type": "Feature",
  "properties": {
    "iso:country": "GB",
    "wof:name": "WV1 1HR",
    "wof:placetype": "postalcode"
  },
  "geometry": {"coordinates":[-2.129145,52.595268],"type":"Point"}
}
