{
  "type": "Feature",
  "properties": {
    "iso:country":"GB",
    "wof:name":"WV1 1HR",
    "wof:placetype":"postalcode"
},
  "geometry": {"coordinates":[-2.12914529008373,52.59526754444109],"type":"Point"}
}