{
  "type": "Feature",
  "properties": {
    "iso:country": "GB",
    "wof:name": "OX2 8NG",
    "wof:placetype": "postalcode"
  },
  "geometry": {"coordinates":[-1.265352,51.788692],"type":"Point"}
}
