{
  "type": "Feature",
  "properties": {
    "iso:country":"GB",
    "wof:name":"TQ7 1RD",
    "wof:placetype":"postalcode"
},
  "geometry": {"coordinates":[-3.77364121540568,50.28066608548136],"type":"Point"}
}