{
  "type": "Feature",
  "properties": {
    "date:inception_lower":"2004-05-01",
    "date:inception_upper":"2004-05-31",
    "iso:country":"GB",
    "wof:name":"TQ7 1RD",
    "wof:placetype":"postalcode"
},
  "geometry": {"coordinates":[-3.773641,50.280666],"type":"Point"}
}