{
  "type": "Feature",
  "properties": {
    "iso:country": "GB",
    "wof:name": "TQ7 1RD",
    "wof:placetype": "postalcode"
  },
  "geometry": {"coordinates":[-3.773641,50.280666],"type":"Point"}
}
