{
  "type": "Feature",
  "properties": {
    "iso:country":"GB",
    "wof:name":"SW1W 8QE",
    "wof:placetype":"postalcode"
},
  "geometry": {"coordinates":[-0.15132816512981,51.48959850486452],"type":"Point"}
}