{
  "type": "Feature",
  "properties": {
    "iso:country":"GB",
    "wof:name":"HA2 9QN",
    "wof:placetype":"postalcode"
},
  "geometry": {"coordinates":[-0.37904923554615,51.57192785961305],"type":"Point"}
}