{
  "type": "Feature",
  "properties": {
    "iso:country": "GB",
    "wof:name": "DE23 1DE",
    "wof:placetype": "postalcode"
  },
  "geometry": {"coordinates":[-1.503041,52.897661],"type":"Point"}
}
