{
  "type": "Feature",
  "properties": {
    "date:inception_lower": "2002-06-01",
    "date:inception_upper": "2002-06-01",
    "iso:country": "GB",
    "wof:name": "CV37 6FE",
    "wof:placetype": "postalcode"
  },
  "geometry": {"coordinates":[-1.70561,52.194104],"type":"Point"}
}
