{
  "type": "Feature",
  "properties": {
    "iso:country":"GB",
    "wof:name":"PA23 8SB",
    "wof:placetype":"postalcode"
},
  "geometry": {"coordinates":[-4.93123639950991,55.99150992576844],"type":"Point"}
}