{
  "type": "Feature",
  "properties": {
    "iso:country": "GB",
    "wof:name": "HR9 7FW",
    "wof:placetype": "postalcode"
  },
  "geometry": {"coordinates":[-2.581219,51.915872],"type":"Point"}
}
