{
  "type": "Feature",
  "properties": {
    "date:inception_lower": "2007-01-01",
    "date:inception_upper": "2007-01-01",
    "iso:country": "GB",
    "wof:name": "HR9 7FW",
    "wof:placetype": "postalcode"
  },
  "geometry": {"coordinates":[-2.581219,51.915872],"type":"Point"}
}
