{
  "type": "Feature",
  "properties": {
    "iso:country":"GB",
    "wof:name":"HR9 7FW",
    "wof:placetype":"postalcode"
},
  "geometry": {"coordinates":[-2.58121943763581,51.91587150436905],"type":"Point"}
}