{
  "type": "Feature",
  "properties": {
    "iso:country": "GB",
    "wof:name": "SP4 7EU",
    "wof:placetype": "postalcode"
  },
  "geometry": {"coordinates":[-1.783296,51.171608],"type":"Point"}
}
