{
  "type": "Feature",
  "properties": {
    "iso:country":"GB",
    "wof:name":"SP4 7EU",
    "wof:placetype":"postalcode"
},
  "geometry": {"coordinates":[-1.78330749328506,51.17161299379451],"type":"Point"}
}