{
  "type": "Feature",
  "properties": {
    "date:inception_lower": "1991-09-01",
    "date:inception_upper": "1991-09-01",
    "iso:country": "GB",
    "wof:name": "TF4 3TD",
    "wof:placetype": "postalcode"
  },
  "geometry": {"coordinates":[-2.456307,52.658169],"type":"Point"}
}
