{
  "type": "Feature",
  "properties": {
    "iso:country":"GB",
    "wof:name":"TF4 3TD",
    "wof:placetype":"postalcode"
},
  "geometry": {"coordinates":[-2.45630750859905,52.65816903691568],"type":"Point"}
}