{
  "type": "Feature",
  "properties": {
    "iso:country": "GB",
    "wof:name": "G20 6EE",
    "wof:placetype": "postalcode"
  },
  "geometry": {"coordinates":[-4.274951,55.876997],"type":"Point"}
}
