{
  "type": "Feature",
  "properties": {
    "iso:country":"GB",
    "wof:name":"G20 6EE",
    "wof:placetype":"postalcode"
},
  "geometry": {"coordinates":[-4.27495134288669,55.87699718688459],"type":"Point"}
}