{
  "type": "Feature",
  "properties": {
    "iso:country": "GB",
    "wof:name": "WF8 1TL",
    "wof:placetype": "postalcode"
  },
  "geometry": {"coordinates":[-1.311548,53.708466],"type":"Point"}
}
