{
  "type": "Feature",
  "properties": {
    "iso:country":"GB",
    "wof:name":"WF8 1TL",
    "wof:placetype":"postalcode"
},
  "geometry": {"coordinates":[-1.3115477380766,53.70846588036299],"type":"Point"}
}