{
  "type": "Feature",
  "properties": {
    "iso:country": "GB",
    "wof:name": "ST15 8BF",
    "wof:placetype": "postalcode"
  },
  "geometry": {"coordinates":[-2.138264,52.911939],"type":"Point"}
}
