{
  "type": "Feature",
  "properties": {
    "date:inception_lower":"2019-02-01",
    "date:inception_upper":"2019-02-28",
    "iso:country":"GB",
    "wof:name":"ST15 8BF",
    "wof:placetype":"postalcode"
},
  "geometry": {"coordinates":[-2.138264,52.911939],"type":"Point"}
}