{
  "type": "Feature",
  "properties": {
    "date:inception_lower": "1980-01-01",
    "date:inception_upper": "1980-01-01",
    "iso:country": "GB",
    "wof:name": "BA2 6HE",
    "wof:placetype": "postalcode"
  },
  "geometry": {"coordinates":[-2.333055,51.378237],"type":"Point"}
}
