{
  "type": "Feature",
  "properties": {
    "iso:country": "GB",
    "wof:name": "BA2 6HE",
    "wof:placetype": "postalcode"
  },
  "geometry": {"coordinates":[-2.333055,51.378237],"type":"Point"}
}
