{
  "type": "Feature",
  "properties": {
    "iso:country":"GB",
    "wof:name":"BA2 6HE",
    "wof:placetype":"postalcode"
},
  "geometry": {"coordinates":[-2.33305672016895,51.3782406928694],"type":"Point"}
}