{
  "type": "Feature",
  "properties": {
    "iso:country": "GB",
    "wof:name": "SO53 3FJ",
    "wof:placetype": "postalcode"
  },
  "geometry": {"coordinates":[-1.381742,50.970716],"type":"Point"}
}
