{
  "type": "Feature",
  "properties": {
    "date:inception_lower": "1980-01-01",
    "date:inception_upper": "1980-01-01",
    "iso:country": "GB",
    "wof:name": "ST8 6NX",
    "wof:placetype": "postalcode"
  },
  "geometry": {"coordinates":[-2.189589,53.106989],"type":"Point"}
}
