{
  "type": "Feature",
  "properties": {
    "iso:country": "GB",
    "wof:name": "SK10 2BN",
    "wof:placetype": "postalcode"
  },
  "geometry": {"coordinates":[-2.118289,53.269177],"type":"Point"}
}
