{
  "type": "Feature",
  "properties": {
    "date:inception_lower":"1991-09-01",
    "date:inception_upper":"1991-09-30",
    "iso:country":"GB",
    "wof:name":"IP19 8RS",
    "wof:placetype":"postalcode"
},
  "geometry": {"coordinates":[1.512983,52.344061],"type":"Point"}
}