{
  "type": "Feature",
  "properties": {
    "iso:country":"GB",
    "wof:name":"PE11 3BT",
    "wof:placetype":"postalcode"
},
  "geometry": {"coordinates":[-0.16916664624534,52.77106748961585],"type":"Point"}
}