{
  "type": "Feature",
  "properties": {
    "date:inception_lower": "1980-01-01",
    "date:inception_upper": "1980-01-01",
    "iso:country": "GB",
    "wof:name": "PE11 3BT",
    "wof:placetype": "postalcode"
  },
  "geometry": {"coordinates":[-0.169167,52.771067],"type":"Point"}
}
