{
  "type": "Feature",
  "properties": {
    "iso:country":"GB",
    "wof:name":"DH8 9PP",
    "wof:placetype":"postalcode"
},
  "geometry": {"coordinates":[-2.05815553350439,54.84029477572946],"type":"Point"}
}