{
  "type": "Feature",
  "properties": {
    "iso:country":"GB",
    "wof:name":"CR7 8RN",
    "wof:placetype":"postalcode"
},
  "geometry": {"coordinates":[-0.09538127093852,51.39793129738708],"type":"Point"}
}