{
  "type": "Feature",
  "properties": {
    "iso:country":"GB",
    "wof:name":"OX2 7PF",
    "wof:placetype":"postalcode"
},
  "geometry": {"coordinates":[-1.26524942687454,51.76734619855837],"type":"Point"}
}