{
  "type": "Feature",
  "properties": {
    "iso:country": "GB",
    "wof:name": "OX2 7PF",
    "wof:placetype": "postalcode"
  },
  "geometry": {"coordinates":[-1.265249,51.767346],"type":"Point"}
}
