{
  "type": "Feature",
  "properties": {
    "iso:country": "GB",
    "wof:name": "NR7 9AZ",
    "wof:placetype": "postalcode"
  },
  "geometry": {"coordinates":[1.325404,52.646309],"type":"Point"}
}
