{
  "type": "Feature",
  "properties": {
    "iso:country": "GB",
    "wof:name": "OX13 5QQ",
    "wof:placetype": "postalcode"
  },
  "geometry": {"coordinates":[-1.365055,51.685424],"type":"Point"}
}
