{
  "type": "Feature",
  "properties": {
    "iso:country":"GB",
    "wof:name":"OX13 5QQ",
    "wof:placetype":"postalcode"
},
  "geometry": {"coordinates":[-1.36505472322195,51.68542376982894],"type":"Point"}
}