{
  "type": "Feature",
  "properties": {
    "date:inception_lower": "2005-02-01",
    "date:inception_upper": "2005-02-01",
    "iso:country": "GB",
    "wof:name": "BL1 9SF",
    "wof:placetype": "postalcode"
  },
  "geometry": {"coordinates":[-2.430774,53.578232],"type":"Point"}
}
