{
  "type": "Feature",
  "properties": {
    "iso:country": "GB",
    "wof:name": "FK3 8NG",
    "wof:placetype": "postalcode"
  },
  "geometry": {"coordinates":[-3.725712,56.01061],"type":"Point"}
}
