{
  "type": "Feature",
  "properties": {
    "iso:country":"GB",
    "wof:name":"PH2 6BX",
    "wof:placetype":"postalcode"
},
  "geometry": {"coordinates":[-3.40731951018296,56.4716590680132],"type":"Point"}
}