{
  "type": "Feature",
  "properties": {
    "date:inception_lower": "1980-01-01",
    "date:inception_upper": "1980-01-01",
    "iso:country": "GB",
    "wof:name": "PH2 6BX",
    "wof:placetype": "postalcode"
  },
  "geometry": {"coordinates":[-3.407319,56.471659],"type":"Point"}
}
