{
  "type": "Feature",
  "properties": {
    "date:inception_lower": "1980-01-01",
    "date:inception_upper": "1980-01-01",
    "iso:country": "GB",
    "wof:name": "OL2 7XB",
    "wof:placetype": "postalcode"
  },
  "geometry": {"coordinates":[-2.092012,53.585299],"type":"Point"}
}
