{
  "type": "Feature",
  "properties": {
    "iso:country": "GB",
    "wof:name": "SP7 9AY",
    "wof:placetype": "postalcode"
  },
  "geometry": {"coordinates":[-2.159615,51.029044],"type":"Point"}
}
