{
  "type": "Feature",
  "properties": {
    "iso:country":"GB",
    "wof:name":"SP7 9AY",
    "wof:placetype":"postalcode"
},
  "geometry": {"coordinates":[-2.15961484694744,51.02904444389107],"type":"Point"}
}