{
  "type": "Feature",
  "properties": {
    "date:inception_lower": "2013-07-01",
    "date:inception_upper": "2013-07-01",
    "iso:country": "GB",
    "wof:name": "G33 1HE",
    "wof:placetype": "postalcode"
  },
  "geometry": {"coordinates":[-4.194317,55.878219],"type":"Point"}
}
