{
  "type": "Feature",
  "properties": {
    "iso:country": "GB",
    "wof:name": "M9 8NL",
    "wof:placetype": "postalcode"
  },
  "geometry": {"coordinates":[-2.23031,53.530662],"type":"Point"}
}
