{
  "type": "Feature",
  "properties": {
    "iso:country":"GB",
    "wof:name":"M9 8NL",
    "wof:placetype":"postalcode"
},
  "geometry": {"coordinates":[-2.23030999673677,53.53066228218708],"type":"Point"}
}