{
  "type": "Feature",
  "properties": {
    "iso:country":"GB",
    "wof:name":"GU47 9RF",
    "wof:placetype":"postalcode"
},
  "geometry": {"coordinates":[-0.78704172560143,51.34701860774736],"type":"Point"}
}