{
  "type": "Feature",
  "properties": {
    "iso:country":"GB",
    "wof:name":"M32 9BZ",
    "wof:placetype":"postalcode"
},
  "geometry": {"coordinates":[-2.31546285662472,53.44435828793026],"type":"Point"}
}