{
  "type": "Feature",
  "properties": {
    "iso:country":"GB",
    "wof:name":"NE8 4NX",
    "wof:placetype":"postalcode"
},
  "geometry": {"coordinates":[-1.60743375412794,54.94972234220378],"type":"Point"}
}