{
  "type": "Feature",
  "properties": {
    "date:inception_lower": "1983-07-01",
    "date:inception_upper": "1983-07-01",
    "iso:country": "GB",
    "wof:name": "HR9 6BX",
    "wof:placetype": "postalcode"
  },
  "geometry": {"coordinates":[-2.662623,51.850625],"type":"Point"}
}
