{
  "type": "Feature",
  "properties": {
    "iso:country": "GB",
    "wof:name": "AB45 2HL",
    "wof:placetype": "postalcode"
  },
  "geometry": {"coordinates":[-2.745284,57.580311],"type":"Point"}
}
