{
  "type": "Feature",
  "properties": {
    "iso:country":"GB",
    "wof:name":"EX39 2NG",
    "wof:placetype":"postalcode"
},
  "geometry": {"coordinates":[-4.2084694318753,51.02117163943143],"type":"Point"}
}