{
  "type": "Feature",
  "properties": {
    "iso:country": "GB",
    "wof:name": "LN2 1AX",
    "wof:placetype": "postalcode"
  },
  "geometry": {"coordinates":[-0.527951,53.243594],"type":"Point"}
}
