{
  "type": "Feature",
  "properties": {
    "iso:country":"GB",
    "wof:name":"LN2 1AX",
    "wof:placetype":"postalcode"
},
  "geometry": {"coordinates":[-0.5279514996934,53.24359395973123],"type":"Point"}
}