{
  "type": "Feature",
  "properties": {
    "iso:country": "GB",
    "wof:name": "MK2 2SA",
    "wof:placetype": "postalcode"
  },
  "geometry": {"coordinates":[-0.732346,51.99422],"type":"Point"}
}
