{
  "type": "Feature",
  "properties": {
    "iso:country":"GB",
    "wof:name":"PL11 2NA",
    "wof:placetype":"postalcode"
},
  "geometry": {"coordinates":[-4.20925010933599,50.37490940268862],"type":"Point"}
}