{
  "type": "Feature",
  "properties": {
    "date:inception_lower": "1980-01-01",
    "date:inception_upper": "1980-01-01",
    "iso:country": "GB",
    "wof:name": "PL11 2NA",
    "wof:placetype": "postalcode"
  },
  "geometry": {"coordinates":[-4.20925,50.374909],"type":"Point"}
}
