{
  "type": "Feature",
  "properties": {
    "date:inception_lower": "1984-10-01",
    "date:inception_upper": "1984-10-01",
    "iso:country": "GB",
    "wof:name": "TF3 2JZ",
    "wof:placetype": "postalcode"
  },
  "geometry": {"coordinates":[-2.435206,52.672614],"type":"Point"}
}
