{
  "type": "Feature",
  "properties": {
    "iso:country":"GB",
    "wof:name":"TF3 2JZ",
    "wof:placetype":"postalcode"
},
  "geometry": {"coordinates":[-2.43520644770869,52.67261405737681],"type":"Point"}
}