{
  "type": "Feature",
  "properties": {
    "date:inception_lower": "2000-06-01",
    "date:inception_upper": "2000-06-01",
    "iso:country": "GB",
    "wof:name": "SN8 3FA",
    "wof:placetype": "postalcode"
  },
  "geometry": {"coordinates":[-1.65093,51.28487],"type":"Point"}
}
