{
  "type": "Feature",
  "properties": {
    "iso:country": "GB",
    "wof:name": "SN8 3FA",
    "wof:placetype": "postalcode"
  },
  "geometry": {"coordinates":[-1.65093,51.28487],"type":"Point"}
}
