{
  "type": "Feature",
  "properties": {
    "iso:country":"GB",
    "wof:name":"SN8 3FA",
    "wof:placetype":"postalcode"
},
  "geometry": {"coordinates":[-1.65093039065783,51.28487914380318],"type":"Point"}
}