{
  "type": "Feature",
  "properties": {
    "iso:country": "GB",
    "wof:name": "TR1 1SZ",
    "wof:placetype": "postalcode"
  },
  "geometry": {"coordinates":[-5.017086,50.255662],"type":"Point"}
}
