{
  "type": "Feature",
  "properties": {
    "iso:country":"GB",
    "wof:name":"TR1 1SZ",
    "wof:placetype":"postalcode"
},
  "geometry": {"coordinates":[-5.0170862988646,50.25566166793491],"type":"Point"}
}