{
  "type": "Feature",
  "properties": {
    "date:inception_lower": "2003-01-01",
    "date:inception_upper": "2003-01-01",
    "iso:country": "GB",
    "wof:name": "CM23 2JP",
    "wof:placetype": "postalcode"
  },
  "geometry": {"coordinates":[0.15662,51.88113],"type":"Point"}
}
