{
  "type": "Feature",
  "properties": {
    "iso:country": "GB",
    "wof:name": "CM23 2JP",
    "wof:placetype": "postalcode"
  },
  "geometry": {"coordinates":[0.156664,51.881129],"type":"Point"}
}
