{
  "type": "Feature",
  "properties": {
    "iso:country":"GB",
    "wof:name":"RG5 4BU",
    "wof:placetype":"postalcode"
},
  "geometry": {"coordinates":[-0.89433431539161,51.44525667791839],"type":"Point"}
}