{
  "type": "Feature",
  "properties": {
    "iso:country": "GB",
    "wof:name": "RG5 4BU",
    "wof:placetype": "postalcode"
  },
  "geometry": {"coordinates":[-0.894334,51.445257],"type":"Point"}
}
