{
  "type": "Feature",
  "properties": {
    "date:inception_lower": "1987-04-01",
    "date:inception_upper": "1987-04-01",
    "iso:country": "GB",
    "wof:name": "WF14 9DT",
    "wof:placetype": "postalcode"
  },
  "geometry": {"coordinates":[-1.709483,53.684591],"type":"Point"}
}
