{
  "type": "Feature",
  "properties": {
    "iso:country": "GB",
    "wof:name": "HU15 2TQ",
    "wof:placetype": "postalcode"
  },
  "geometry": {"coordinates":[-0.732859,53.744339],"type":"Point"}
}
