{
  "type": "Feature",
  "properties": {
    "iso:country":"GB",
    "wof:name":"HU15 2TQ",
    "wof:placetype":"postalcode"
},
  "geometry": {"coordinates":[-0.73286780966106,53.74434608648117],"type":"Point"}
}