{
  "type": "Feature",
  "properties": {
    "iso:country":"GB",
    "wof:name":"TF3 1EG",
    "wof:placetype":"postalcode"
},
  "geometry": {"coordinates":[-2.44591896565534,52.65571843924955],"type":"Point"}
}