{
  "type": "Feature",
  "properties": {
    "date:inception_lower":"1980-01-01",
    "date:inception_upper":"1980-01-31",
    "iso:country":"GB",
    "wof:name":"TF3 1EG",
    "wof:placetype":"postalcode"
},
  "geometry": {"coordinates":[-2.445919,52.655718],"type":"Point"}
}