{
  "type": "Feature",
  "properties": {
    "iso:country":"GB",
    "wof:name":"HA3 7AR",
    "wof:placetype":"postalcode"
},
  "geometry": {"coordinates":[-0.33522352920454,51.59960378490347],"type":"Point"}
}