{
  "type": "Feature",
  "properties": {
    "iso:country":"GB",
    "wof:name":"DA7 4JX",
    "wof:placetype":"postalcode"
},
  "geometry": {"coordinates":[0.14415300378939,51.46185150602322],"type":"Point"}
}