{
  "type": "Feature",
  "properties": {
    "iso:country":"GB",
    "wof:name":"GU52 6QG",
    "wof:placetype":"postalcode"
},
  "geometry": {"coordinates":[-0.84956341519858,51.26367142337037],"type":"Point"}
}