{
  "type": "Feature",
  "properties": {
    "iso:country":"GB",
    "wof:name":"M16 0PG",
    "wof:placetype":"postalcode"
},
  "geometry": {"coordinates":[-2.28423533871894,53.45976214179188],"type":"Point"}
}