{
  "type": "Feature",
  "properties": {
    "iso:country": "GB",
    "wof:name": "RH15 9ET",
    "wof:placetype": "postalcode"
  },
  "geometry": {"coordinates":[-0.150851,50.955777],"type":"Point"}
}
