{
  "type": "Feature",
  "properties": {
    "date:inception_lower": "2018-01-01",
    "date:inception_upper": "2018-01-01",
    "iso:country": "GB",
    "wof:name": "RH15 9ET",
    "wof:placetype": "postalcode"
  },
  "geometry": {"coordinates":[-0.150765,50.955785],"type":"Point"}
}
