{
  "type": "Feature",
  "properties": {
    "iso:country": "GB",
    "wof:name": "DE56 1AN",
    "wof:placetype": "postalcode"
  },
  "geometry": {"coordinates":[-1.47498,53.026304],"type":"Point"}
}
