{
  "type": "Feature",
  "properties": {
    "iso:country": "GB",
    "wof:name": "LN2 3TA",
    "wof:placetype": "postalcode"
  },
  "geometry": {"coordinates":[-0.480965,53.308904],"type":"Point"}
}
