{
  "type": "Feature",
  "properties": {
    "iso:country":"GB",
    "wof:name":"BS3 4NL",
    "wof:placetype":"postalcode"
},
  "geometry": {"coordinates":[-2.59547108790532,51.43886560238741],"type":"Point"}
}