{
  "type": "Feature",
  "properties": {
    "iso:country": "GB",
    "wof:name": "BS3 4NL",
    "wof:placetype": "postalcode"
  },
  "geometry": {"coordinates":[-2.595374,51.438981],"type":"Point"}
}
