{
  "type": "Feature",
  "properties": {
    "date:inception_lower":"2002-06-01",
    "date:inception_upper":"2002-06-30",
    "iso:country":"GB",
    "wof:name":"BS3 4NL",
    "wof:placetype":"postalcode"
},
  "geometry": {"coordinates":[-2.595403,51.438945],"type":"Point"}
}