{
  "type": "Feature",
  "properties": {
    "iso:country": "GB",
    "wof:name": "PO22 9SU",
    "wof:placetype": "postalcode"
  },
  "geometry": {"coordinates":[-0.668223,50.799911],"type":"Point"}
}
