{
  "type": "Feature",
  "properties": {
    "iso:country": "GB",
    "wof:name": "EX34 9RQ",
    "wof:placetype": "postalcode"
  },
  "geometry": {"coordinates":[-4.090479,51.173361],"type":"Point"}
}
