{
  "type": "Feature",
  "properties": {
    "iso:country": "GB",
    "wof:name": "EX34 9RQ",
    "wof:placetype": "postalcode"
  },
  "geometry": {"coordinates":[-4.090392,51.173659],"type":"Point"}
}
