{
  "type": "Feature",
  "properties": {
    "iso:country":"GB",
    "wof:name":"EX34 9RQ",
    "wof:placetype":"postalcode"
},
  "geometry": {"coordinates":[-4.09045563366293,51.17336160104943],"type":"Point"}
}