{
  "type": "Feature",
  "properties": {
    "iso:country": "GB",
    "wof:name": "NP19 7NU",
    "wof:placetype": "postalcode"
  },
  "geometry": {"coordinates":[-2.965167,51.601168],"type":"Point"}
}
