{
  "type": "Feature",
  "properties": {
    "iso:country":"GB",
    "wof:name":"BL1 6HU",
    "wof:placetype":"postalcode"
},
  "geometry": {"coordinates":[-2.45467750321395,53.59465471496291],"type":"Point"}
}