{
  "type": "Feature",
  "properties": {
    "iso:country":"GB",
    "wof:name":"BR3 4NY",
    "wof:placetype":"postalcode"
},
  "geometry": {"coordinates":[-0.04789795876506,51.40569298748769],"type":"Point"}
}