{
  "type": "Feature",
  "properties": {
    "date:inception_lower": "1980-01-01",
    "date:inception_upper": "1980-01-01",
    "iso:country": "GB",
    "wof:name": "WV16 6SG",
    "wof:placetype": "postalcode"
  },
  "geometry": {"coordinates":[-2.580915,52.513668],"type":"Point"}
}
