{
  "type": "Feature",
  "properties": {
    "iso:country":"GB",
    "wof:name":"AB15 9PJ",
    "wof:placetype":"postalcode"
},
  "geometry": {"coordinates":[-2.15662446275,57.12110510610916],"type":"Point"}
}