{
  "type": "Feature",
  "properties": {
    "date:inception_lower": "1996-06-01",
    "date:inception_upper": "1996-06-01",
    "iso:country": "GB",
    "wof:name": "AB15 9PJ",
    "wof:placetype": "postalcode"
  },
  "geometry": {"coordinates":[-2.156624,57.121105],"type":"Point"}
}
