{
  "type": "Feature",
  "properties": {
    "iso:country":"GB",
    "wof:name":"SR7 7XH",
    "wof:placetype":"postalcode"
},
  "geometry": {"coordinates":[-1.34059334455792,54.84181785926006],"type":"Point"}
}