{
  "type": "Feature",
  "properties": {
    "iso:country":"GB",
    "wof:name":"BL7 0DF",
    "wof:placetype":"postalcode"
},
  "geometry": {"coordinates":[-2.39536294972421,53.64510105554734],"type":"Point"}
}