{
  "type": "Feature",
  "properties": {
    "iso:country": "GB",
    "wof:name": "BL7 0DF",
    "wof:placetype": "postalcode"
  },
  "geometry": {"coordinates":[-2.395363,53.645101],"type":"Point"}
}
