{
  "type": "Feature",
  "properties": {
    "date:inception_lower":"1980-01-01",
    "date:inception_upper":"1980-01-31",
    "iso:country":"GB",
    "wof:name":"DD10 8NJ",
    "wof:placetype":"postalcode"
},
  "geometry": {"coordinates":[-2.467329,56.714809],"type":"Point"}
}