{
  "type": "Feature",
  "properties": {
    "iso:country":"GB",
    "wof:name":"DD10 8NJ",
    "wof:placetype":"postalcode"
},
  "geometry": {"coordinates":[-2.46732913267095,56.71480918435274],"type":"Point"}
}