{
  "type": "Feature",
  "properties": {
    "iso:country": "GB",
    "wof:name": "DD10 8NJ",
    "wof:placetype": "postalcode"
  },
  "geometry": {"coordinates":[-2.467329,56.714809],"type":"Point"}
}
