{
  "type": "Feature",
  "properties": {
    "date:inception_lower": "1980-01-01",
    "date:inception_upper": "1980-01-01",
    "iso:country": "GB",
    "wof:name": "LE2 3RD",
    "wof:placetype": "postalcode"
  },
  "geometry": {"coordinates":[-1.103565,52.60421],"type":"Point"}
}
