{
  "type": "Feature",
  "properties": {
    "iso:country":"GB",
    "wof:name":"EN2 7QZ",
    "wof:placetype":"postalcode"
},
  "geometry": {"coordinates":[-0.10683805535904,51.65305514283202],"type":"Point"}
}