{
  "type": "Feature",
  "properties": {
    "date:inception_lower": "2012-08-01",
    "date:inception_upper": "2012-08-01",
    "iso:country": "GB",
    "wof:name": "GL3 4FX",
    "wof:placetype": "postalcode"
  },
  "geometry": {"coordinates":[-2.179667,51.846286],"type":"Point"}
}
