{
  "type": "Feature",
  "properties": {
    "iso:country":"GB",
    "wof:name":"SE28 8LG",
    "wof:placetype":"postalcode"
},
  "geometry": {"coordinates":[0.11658353562673,51.50631863012143],"type":"Point"}
}