{
  "type": "Feature",
  "properties": {
    "iso:country": "GB",
    "wof:name": "WF11 0BE",
    "wof:placetype": "postalcode"
  },
  "geometry": {"coordinates":[-1.271854,53.693715],"type":"Point"}
}
