{
  "type": "Feature",
  "properties": {
    "iso:country":"GB",
    "wof:name":"UB9 4BX",
    "wof:placetype":"postalcode"
},
  "geometry": {"coordinates":[-0.48792012192301,51.55509117561685],"type":"Point"}
}