{
  "type": "Feature",
  "properties": {
    "iso:country":"GB",
    "wof:name":"BA6 9PN",
    "wof:placetype":"postalcode"
},
  "geometry": {"coordinates":[-2.72764384719402,51.14307577403591],"type":"Point"}
}