{
  "type": "Feature",
  "properties": {
    "date:inception_lower": "1980-01-01",
    "date:inception_upper": "1980-01-01",
    "iso:country": "GB",
    "wof:name": "SN3 3PP",
    "wof:placetype": "postalcode"
  },
  "geometry": {"coordinates":[-1.738145,51.563415],"type":"Point"}
}
