{
  "type": "Feature",
  "properties": {
    "iso:country":"GB",
    "wof:name":"SN3 3PP",
    "wof:placetype":"postalcode"
},
  "geometry": {"coordinates":[-1.73814515714286,51.56341450522166],"type":"Point"}
}