{
  "type": "Feature",
  "properties": {
    "iso:country":"GB",
    "wof:name":"SL2 2NE",
    "wof:placetype":"postalcode"
},
  "geometry": {"coordinates":[-0.64459581476592,51.52707110882174],"type":"Point"}
}