{
  "type": "Feature",
  "properties": {
    "date:inception_lower":"1990-02-01",
    "date:inception_upper":"1990-02-28",
    "iso:country":"GB",
    "wof:name":"SL2 2NE",
    "wof:placetype":"postalcode"
},
  "geometry": {"coordinates":[-0.644596,51.527071],"type":"Point"}
}