{
  "type": "Feature",
  "properties": {
    "iso:country":"GB",
    "wof:name":"DH7 8SQ",
    "wof:placetype":"postalcode"
},
  "geometry": {"coordinates":[-1.62664243106583,54.74834269191109],"type":"Point"}
}