{
  "type": "Feature",
  "properties": {
    "iso:country": "GB",
    "wof:name": "DH7 8SQ",
    "wof:placetype": "postalcode"
  },
  "geometry": {"coordinates":[-1.626642,54.748343],"type":"Point"}
}
