{
  "type": "Feature",
  "properties": {
    "iso:country":"GB",
    "wof:name":"NG10 2FS",
    "wof:placetype":"postalcode"
},
  "geometry": {"coordinates":[-1.25728226156665,52.889079948501],"type":"Point"}
}