{
  "type": "Feature",
  "properties": {
    "iso:country": "GB",
    "wof:name": "NG10 2FS",
    "wof:placetype": "postalcode"
  },
  "geometry": {"coordinates":[-1.257282,52.88908],"type":"Point"}
}
