{
  "type": "Feature",
  "properties": {
    "iso:country": "GB",
    "wof:name": "WF9 1NP",
    "wof:placetype": "postalcode"
  },
  "geometry": {"coordinates":[-1.27223,53.61906],"type":"Point"}
}
