{
  "type": "Feature",
  "properties": {
    "date:inception_lower":"1981-06-01",
    "date:inception_upper":"1981-06-30",
    "iso:country":"GB",
    "wof:name":"WF9 1NP",
    "wof:placetype":"postalcode"
},
  "geometry": {"coordinates":[-1.27223,53.61906],"type":"Point"}
}