{
  "type": "Feature",
  "properties": {
    "iso:country":"GB",
    "wof:name":"W1U 2DB",
    "wof:placetype":"postalcode"
},
  "geometry": {"coordinates":[-0.14932017929949,51.51605876954601],"type":"Point"}
}