{
  "type": "Feature",
  "properties": {
    "iso:country":"GB",
    "wof:name":"B97 5DT",
    "wof:placetype":"postalcode"
},
  "geometry": {"coordinates":[-1.94938967095851,52.28975689142452],"type":"Point"}
}