{
  "type": "Feature",
  "properties": {
    "date:inception_lower": "1999-06-01",
    "date:inception_upper": "1999-06-01",
    "iso:country": "GB",
    "wof:name": "NP11 4NN",
    "wof:placetype": "postalcode"
  },
  "geometry": {"coordinates":[-3.155483,51.66562],"type":"Point"}
}
