{
  "type": "Feature",
  "properties": {
    "iso:country": "GB",
    "wof:name": "NP11 4NN",
    "wof:placetype": "postalcode"
  },
  "geometry": {"coordinates":[-3.155426,51.66563],"type":"Point"}
}
