{
  "type": "Feature",
  "properties": {
    "iso:country":"GB",
    "wof:name":"NP11 4NN",
    "wof:placetype":"postalcode"
},
  "geometry": {"coordinates":[-3.15547424248792,51.66561861857475],"type":"Point"}
}