{
  "type": "Feature",
  "properties": {
    "date:inception_lower": "1995-01-01",
    "date:inception_upper": "1995-01-01",
    "iso:country": "GB",
    "wof:name": "PO11 9TX",
    "wof:placetype": "postalcode"
  },
  "geometry": {"coordinates":[-0.965588,50.78806],"type":"Point"}
}
