{
  "type": "Feature",
  "properties": {
    "iso:country": "GB",
    "wof:name": "BN9 9JS",
    "wof:placetype": "postalcode"
  },
  "geometry": {"coordinates":[0.048413,50.790526],"type":"Point"}
}
