{
  "type": "Feature",
  "properties": {
    "iso:country":"GB",
    "wof:name":"NG2 9SQ",
    "wof:placetype":"postalcode"
},
  "geometry": {"coordinates":[-1.13490206296755,52.93837780772595],"type":"Point"}
}