{
  "type": "Feature",
  "properties": {
    "date:inception_lower": "2015-01-01",
    "date:inception_upper": "2015-01-01",
    "iso:country": "GB",
    "wof:name": "GL12 8JT",
    "wof:placetype": "postalcode"
  },
  "geometry": {"coordinates":[-2.363511,51.625389],"type":"Point"}
}
