{
  "type": "Feature",
  "properties": {
    "iso:country":"GB",
    "wof:name":"GL12 8JT",
    "wof:placetype":"postalcode"
},
  "geometry": {"coordinates":[-2.36351079753277,51.62538943237978],"type":"Point"}
}