{
  "type": "Feature",
  "properties": {
    "iso:country": "GB",
    "wof:name": "GL12 8JT",
    "wof:placetype": "postalcode"
  },
  "geometry": {"coordinates":[-2.363511,51.625389],"type":"Point"}
}
