{
  "type": "Feature",
  "properties": {
    "iso:country":"GB",
    "wof:name":"EX4 7JQ",
    "wof:placetype":"postalcode"
},
  "geometry": {"coordinates":[-3.50177792907998,50.73174890129022],"type":"Point"}
}