{
  "type": "Feature",
  "properties": {
    "date:inception_lower":"2012-05-01",
    "date:inception_upper":"2012-05-31",
    "iso:country":"GB",
    "wof:name":"CR2 8AT",
    "wof:placetype":"postalcode"
},
  "geometry": {"coordinates":[-0.042067,51.354013],"type":"Point"}
}