{
  "type": "Feature",
  "properties": {
    "iso:country":"GB",
    "wof:name":"SW13 8SB",
    "wof:placetype":"postalcode"
},
  "geometry": {"coordinates":[-0.22917183584318,51.48508962360317],"type":"Point"}
}