{
  "type": "Feature",
  "properties": {
    "iso:country": "GB",
    "wof:name": "SW13 8SB",
    "wof:placetype": "postalcode"
  },
  "geometry": {"coordinates":[-0.229172,51.48509],"type":"Point"}
}
