{
  "type": "Feature",
  "properties": {
    "date:inception_lower": "1980-01-01",
    "date:inception_upper": "1980-01-01",
    "iso:country": "GB",
    "wof:name": "ML8 5LT",
    "wof:placetype": "postalcode"
  },
  "geometry": {"coordinates":[-3.87767,55.752459],"type":"Point"}
}
