{
  "type": "Feature",
  "properties": {
    "iso:country":"GB",
    "wof:name":"ML8 5LT",
    "wof:placetype":"postalcode"
},
  "geometry": {"coordinates":[-3.87767018679331,55.75245854914233],"type":"Point"}
}