{
  "type": "Feature",
  "properties": {
    "iso:country":"GB",
    "wof:name":"WD18 8YS",
    "wof:placetype":"postalcode"
},
  "geometry": {"coordinates":[-0.42850910556762,51.64824181151459],"type":"Point"}
}