{
  "type": "Feature",
  "properties": {
    "date:inception_lower": "1980-01-01",
    "date:inception_upper": "1980-01-01",
    "iso:country": "GB",
    "wof:name": "NG25 0PQ",
    "wof:placetype": "postalcode"
  },
  "geometry": {"coordinates":[-0.9821,53.080362],"type":"Point"}
}
