{
  "type": "Feature",
  "properties": {
    "date:inception_lower": "1980-01-01",
    "date:inception_upper": "1980-01-01",
    "iso:country": "GB",
    "wof:name": "WV1 3DN",
    "wof:placetype": "postalcode"
  },
  "geometry": {"coordinates":[-2.118089,52.58486],"type":"Point"}
}
