{
  "type": "Feature",
  "properties": {
    "iso:country": "GB",
    "wof:name": "PH10 6BL",
    "wof:placetype": "postalcode"
  },
  "geometry": {"coordinates":[-3.340353,56.589401],"type":"Point"}
}
