{
  "type": "Feature",
  "properties": {
    "iso:country":"GB",
    "wof:name":"DL3 9JA",
    "wof:placetype":"postalcode"
},
  "geometry": {"coordinates":[-1.57390155921143,54.53323237321719],"type":"Point"}
}