{
  "type": "Feature",
  "properties": {
    "iso:country":"GB",
    "wof:name":"DD5 4PG",
    "wof:placetype":"postalcode"
},
  "geometry": {"coordinates":[-2.82677010468446,56.47930881000264],"type":"Point"}
}