{
  "type": "Feature",
  "properties": {
    "iso:country": "GB",
    "wof:name": "DD5 4PG",
    "wof:placetype": "postalcode"
  },
  "geometry": {"coordinates":[-2.82677,56.479309],"type":"Point"}
}
