{
  "type": "Feature",
  "properties": {
    "iso:country":"GB",
    "wof:name":"ST7 1DQ",
    "wof:placetype":"postalcode"
},
  "geometry": {"coordinates":[-2.25293777103178,53.08144994763551],"type":"Point"}
}