{
  "type": "Feature",
  "properties": {
    "iso:country":"GB",
    "wof:name":"N19 5BP",
    "wof:placetype":"postalcode"
},
  "geometry": {"coordinates":[-0.14091797412768,51.5631093836078],"type":"Point"}
}