{
  "type": "Feature",
  "properties": {
    "iso:country": "GB",
    "wof:name": "LL31 9JU",
    "wof:placetype": "postalcode"
  },
  "geometry": {"coordinates":[-3.780149,53.304498],"type":"Point"}
}
