{
  "type": "Feature",
  "properties": {
    "iso:country":"GB",
    "wof:name":"LL31 9JU",
    "wof:placetype":"postalcode"
},
  "geometry": {"coordinates":[-3.78014943675737,53.30449759194111],"type":"Point"}
}