{
  "type": "Feature",
  "properties": {
    "date:inception_lower": "2016-05-01",
    "date:inception_upper": "2016-05-01",
    "iso:country": "GB",
    "wof:name": "PR4 0DR",
    "wof:placetype": "postalcode"
  },
  "geometry": {"coordinates":[-2.760472,53.789055],"type":"Point"}
}
