{
  "type": "Feature",
  "properties": {
    "date:inception_lower":"1990-07-01",
    "date:inception_upper":"1990-07-31",
    "iso:country":"GB",
    "wof:name":"EX2 5EJ",
    "wof:placetype":"postalcode"
},
  "geometry": {"coordinates":[-3.505941,50.720624],"type":"Point"}
}