{
  "type": "Feature",
  "properties": {
    "iso:country":"GB",
    "wof:name":"EX2 5EJ",
    "wof:placetype":"postalcode"
},
  "geometry": {"coordinates":[-3.50594143333945,50.72062446233937],"type":"Point"}
}