{
  "type": "Feature",
  "properties": {
    "iso:country": "GB",
    "wof:name": "LL32 8PP",
    "wof:placetype": "postalcode"
  },
  "geometry": {"coordinates":[-3.834406,53.281711],"type":"Point"}
}
