{
  "type": "Feature",
  "properties": {
    "iso:country":"GB",
    "wof:name":"LL32 8PP",
    "wof:placetype":"postalcode"
},
  "geometry": {"coordinates":[-3.83456653065306,53.28167414180132],"type":"Point"}
}