{
  "type": "Feature",
  "properties": {
    "iso:country":"GB",
    "wof:name":"LS25 7DA",
    "wof:placetype":"postalcode"
},
  "geometry": {"coordinates":[-1.37744886235079,53.77316382563276],"type":"Point"}
}