{
  "type": "Feature",
  "properties": {
    "iso:country": "GB",
    "wof:name": "NG8 1AS",
    "wof:placetype": "postalcode"
  },
  "geometry": {"coordinates":[-1.189519,52.953838],"type":"Point"}
}
