{
  "type": "Feature",
  "properties": {
    "date:inception_lower": "1980-01-01",
    "date:inception_upper": "1980-01-01",
    "iso:country": "GB",
    "wof:name": "NG8 1AS",
    "wof:placetype": "postalcode"
  },
  "geometry": {"coordinates":[-1.189519,52.953838],"type":"Point"}
}
