{
  "type": "Feature",
  "properties": {
    "iso:country":"GB",
    "wof:name":"NG8 1AS",
    "wof:placetype":"postalcode"
},
  "geometry": {"coordinates":[-1.18951913187841,52.95383810625435],"type":"Point"}
}