{
  "type": "Feature",
  "properties": {
    "iso:country":"GB",
    "wof:name":"DL13 5RD",
    "wof:placetype":"postalcode"
},
  "geometry": {"coordinates":[-1.86251492817071,54.63291146263192],"type":"Point"}
}