{
  "type": "Feature",
  "properties": {
    "date:inception_lower":"1980-01-01",
    "date:inception_upper":"1980-01-31",
    "iso:country":"GB",
    "wof:name":"DL13 5RD",
    "wof:placetype":"postalcode"
},
  "geometry": {"coordinates":[-1.861475,54.631652],"type":"Point"}
}