{
  "type": "Feature",
  "properties": {
    "iso:country":"GB",
    "wof:name":"LN3 4PB",
    "wof:placetype":"postalcode"
},
  "geometry": {"coordinates":[-0.50347132574376,53.23178238398375],"type":"Point"}
}