{
  "type": "Feature",
  "properties": {
    "iso:country":"GB",
    "wof:name":"NE1 5RF",
    "wof:placetype":"postalcode"
},
  "geometry": {"coordinates":[-1.61718302446233,54.97201242213367],"type":"Point"}
}