{
  "type": "Feature",
  "properties": {
    "iso:country": "GB",
    "wof:name": "TA16 5PB",
    "wof:placetype": "postalcode"
  },
  "geometry": {"coordinates":[-2.791429,50.908734],"type":"Point"}
}
