{
  "type": "Feature",
  "properties": {
    "date:inception_lower":"1992-08-01",
    "date:inception_upper":"1992-08-31",
    "iso:country":"GB",
    "wof:name":"LE67 6NA",
    "wof:placetype":"postalcode"
},
  "geometry": {"coordinates":[-1.399266,52.695096],"type":"Point"}
}