{
  "type": "Feature",
  "properties": {
    "date:inception_lower": "1980-01-01",
    "date:inception_upper": "1980-01-01",
    "iso:country": "GB",
    "wof:name": "BS1 6RU",
    "wof:placetype": "postalcode"
  },
  "geometry": {"coordinates":[-2.586439,51.446995],"type":"Point"}
}
