{
  "type": "Feature",
  "properties": {
    "iso:country": "GB",
    "wof:name": "BS1 6RU",
    "wof:placetype": "postalcode"
  },
  "geometry": {"coordinates":[-2.586439,51.446995],"type":"Point"}
}
