{
  "type": "Feature",
  "properties": {
    "iso:country":"GB",
    "wof:name":"B63 1HR",
    "wof:placetype":"postalcode"
},
  "geometry": {"coordinates":[-2.08107152378326,52.44019853517249],"type":"Point"}
}