{
  "type": "Feature",
  "properties": {
    "date:inception_lower": "1980-01-01",
    "date:inception_upper": "1980-01-01",
    "iso:country": "GB",
    "wof:name": "B63 1HR",
    "wof:placetype": "postalcode"
  },
  "geometry": {"coordinates":[-2.080977,52.44024],"type":"Point"}
}
