{
  "type": "Feature",
  "properties": {
    "iso:country": "GB",
    "wof:name": "RG27 9TP",
    "wof:placetype": "postalcode"
  },
  "geometry": {"coordinates":[-0.961851,51.281257],"type":"Point"}
}
