{
  "type": "Feature",
  "properties": {
    "date:inception_lower": "1980-01-01",
    "date:inception_upper": "1980-01-01",
    "iso:country": "GB",
    "wof:name": "YO8 8DE",
    "wof:placetype": "postalcode"
  },
  "geometry": {"coordinates":[-1.058884,53.778691],"type":"Point"}
}
