{
  "type": "Feature",
  "properties": {
    "iso:country":"GB",
    "wof:name":"PE1 3RZ",
    "wof:placetype":"postalcode"
},
  "geometry": {"coordinates":[-0.24244601237334,52.59630748707222],"type":"Point"}
}