{
  "type": "Feature",
  "properties": {
    "iso:country":"GB",
    "wof:name":"LN9 5BH",
    "wof:placetype":"postalcode"
},
  "geometry": {"coordinates":[-0.1215909662196,53.215452422288],"type":"Point"}
}