{
  "type": "Feature",
  "properties": {
    "date:inception_lower":"1981-06-01",
    "date:inception_upper":"1981-06-30",
    "iso:country":"GB",
    "wof:name":"LN9 5BH",
    "wof:placetype":"postalcode"
},
  "geometry": {"coordinates":[-0.121591,53.215452],"type":"Point"}
}