{
  "type": "Feature",
  "properties": {
    "iso:country": "GB",
    "wof:name": "LN9 5BH",
    "wof:placetype": "postalcode"
  },
  "geometry": {"coordinates":[-0.121591,53.215452],"type":"Point"}
}
