{
  "type": "Feature",
  "properties": {
    "date:inception_lower":"2005-03-01",
    "date:inception_upper":"2005-03-31",
    "iso:country":"GB",
    "wof:name":"CW7 1RJ",
    "wof:placetype":"postalcode"
},
  "geometry": {"coordinates":[-2.546695,53.180879],"type":"Point"}
}