{
  "type": "Feature",
  "properties": {
    "iso:country": "GB",
    "wof:name": "BB4 9DF",
    "wof:placetype": "postalcode"
  },
  "geometry": {"coordinates":[-2.248436,53.696843],"type":"Point"}
}
