{
  "type": "Feature",
  "properties": {
    "date:inception_lower": "2005-07-01",
    "date:inception_upper": "2005-07-01",
    "iso:country": "GB",
    "wof:name": "E3 3NA",
    "wof:placetype": "postalcode"
  },
  "geometry": {"coordinates":[-0.011973,51.525124],"type":"Point"}
}
