{
  "type": "Feature",
  "properties": {
    "iso:country":"GB",
    "wof:name":"BA3 4SN",
    "wof:placetype":"postalcode"
},
  "geometry": {"coordinates":[-2.53782853464081,51.25674597124746],"type":"Point"}
}