{
  "type": "Feature",
  "properties": {
    "date:inception_lower": "1980-01-01",
    "date:inception_upper": "1980-01-01",
    "iso:country": "GB",
    "wof:name": "BA3 4SN",
    "wof:placetype": "postalcode"
  },
  "geometry": {"coordinates":[-2.537828,51.256746],"type":"Point"}
}
