{
  "type": "Feature",
  "properties": {
    "date:inception_lower": "2010-10-01",
    "date:inception_upper": "2010-10-01",
    "iso:country": "GB",
    "wof:name": "M90 3AH",
    "wof:placetype": "postalcode"
  },
  "geometry": {"coordinates":[-2.274143,53.366168],"type":"Point"}
}
