{
  "type": "Feature",
  "properties": {
    "iso:country":"GB",
    "wof:name":"LL18 5UA",
    "wof:placetype":"postalcode"
},
  "geometry": {"coordinates":[-3.46988935395313,53.28915541931985],"type":"Point"}
}