{
  "type": "Feature",
  "properties": {
    "iso:country":"GB",
    "wof:name":"TN24 0AQ",
    "wof:placetype":"postalcode"
},
  "geometry": {"coordinates":[0.89688115109022,51.1440567708656],"type":"Point"}
}