{
  "type": "Feature",
  "properties": {
    "date:inception_lower": "1980-01-01",
    "date:inception_upper": "1980-01-01",
    "iso:country": "GB",
    "wof:name": "TN24 0AQ",
    "wof:placetype": "postalcode"
  },
  "geometry": {"coordinates":[0.896881,51.144057],"type":"Point"}
}
