{
  "type": "Feature",
  "properties": {
    "iso:country": "GB",
    "wof:name": "G43 1AN",
    "wof:placetype": "postalcode"
  },
  "geometry": {"coordinates":[-4.335593,55.819476],"type":"Point"}
}
