{
  "type": "Feature",
  "properties": {
    "iso:country": "GB",
    "wof:name": "B28 0UB",
    "wof:placetype": "postalcode"
  },
  "geometry": {"coordinates":[-1.848324,52.412359],"type":"Point"}
}
