{
  "type": "Feature",
  "properties": {
    "iso:country":"GB",
    "wof:name":"B28 0UB",
    "wof:placetype":"postalcode"
},
  "geometry": {"coordinates":[-1.84832391028254,52.4123593251409],"type":"Point"}
}