{
  "type": "Feature",
  "properties": {
    "iso:country":"GB",
    "wof:name":"SK14 4RT",
    "wof:placetype":"postalcode"
},
  "geometry": {"coordinates":[-2.08489647420203,53.45574702501462],"type":"Point"}
}