{
  "type": "Feature",
  "properties": {
    "date:inception_lower": "1990-07-01",
    "date:inception_upper": "1990-07-01",
    "iso:country": "GB",
    "wof:name": "SK14 4RT",
    "wof:placetype": "postalcode"
  },
  "geometry": {"coordinates":[-2.084896,53.455747],"type":"Point"}
}
