{
  "type": "Feature",
  "properties": {
    "date:inception_lower": "1980-01-01",
    "date:inception_upper": "1980-01-01",
    "iso:country": "GB",
    "wof:name": "SL1 5DS",
    "wof:placetype": "postalcode"
  },
  "geometry": {"coordinates":[-0.639698,51.51439],"type":"Point"}
}
