{
  "type": "Feature",
  "properties": {
    "iso:country":"GB",
    "wof:name":"HP11 1HX",
    "wof:placetype":"postalcode"
},
  "geometry": {"coordinates":[-0.72080951136078,51.61606499509812],"type":"Point"}
}