{
  "type": "Feature",
  "properties": {
    "iso:country":"GB",
    "wof:name":"SY4 5HS",
    "wof:placetype":"postalcode"
},
  "geometry": {"coordinates":[-2.70844616290917,52.85784065603204],"type":"Point"}
}