{
  "type": "Feature",
  "properties": {
    "iso:country": "GB",
    "wof:name": "SY4 5HS",
    "wof:placetype": "postalcode"
  },
  "geometry": {"coordinates":[-2.708446,52.857841],"type":"Point"}
}
