{
  "type": "Feature",
  "properties": {
    "date:inception_lower": "1980-01-01",
    "date:inception_upper": "1980-01-01",
    "iso:country": "GB",
    "wof:name": "BH23 7EU",
    "wof:placetype": "postalcode"
  },
  "geometry": {"coordinates":[-1.771283,50.752602],"type":"Point"}
}
