{
  "type": "Feature",
  "properties": {
    "iso:country":"GB",
    "wof:name":"BD2 2DD",
    "wof:placetype":"postalcode"
},
  "geometry": {"coordinates":[-1.72178427615554,53.81906390041969],"type":"Point"}
}