{
  "type": "Feature",
  "properties": {
    "date:inception_lower":"1980-01-01",
    "date:inception_upper":"1980-01-31",
    "iso:country":"GB",
    "wof:name":"B43 6EY",
    "wof:placetype":"postalcode"
},
  "geometry": {"coordinates":[-1.92927,52.551357],"type":"Point"}
}