{
  "type": "Feature",
  "properties": {
    "iso:country": "GB",
    "wof:name": "B43 6EY",
    "wof:placetype": "postalcode"
  },
  "geometry": {"coordinates":[-1.92927,52.551357],"type":"Point"}
}
