{
  "type": "Feature",
  "properties": {
    "iso:country":"GB",
    "wof:name":"B43 6EY",
    "wof:placetype":"postalcode"
},
  "geometry": {"coordinates":[-1.929269546663,52.55135707231277],"type":"Point"}
}