{
  "type": "Feature",
  "properties": {
    "date:inception_lower": "1986-07-01",
    "date:inception_upper": "1986-07-01",
    "iso:country": "GB",
    "wof:name": "CV32 7XP",
    "wof:placetype": "postalcode"
  },
  "geometry": {"coordinates":[-1.502423,52.310423],"type":"Point"}
}
