{
  "type": "Feature",
  "properties": {
    "iso:country":"GB",
    "wof:name":"CV32 7XP",
    "wof:placetype":"postalcode"
},
  "geometry": {"coordinates":[-1.5024230294831,52.3104232197129],"type":"Point"}
}