{
  "type": "Feature",
  "properties": {
    "iso:country": "GB",
    "wof:name": "CV32 7XP",
    "wof:placetype": "postalcode"
  },
  "geometry": {"coordinates":[-1.502423,52.310423],"type":"Point"}
}
