{
  "type": "Feature",
  "properties": {
    "date:inception_lower": "1980-01-01",
    "date:inception_upper": "1980-01-01",
    "iso:country": "GB",
    "wof:name": "S17 4QN",
    "wof:placetype": "postalcode"
  },
  "geometry": {"coordinates":[-1.500563,53.31772],"type":"Point"}
}
