{
  "type": "Feature",
  "properties": {
    "iso:country": "GB",
    "wof:name": "S17 4QN",
    "wof:placetype": "postalcode"
  },
  "geometry": {"coordinates":[-1.500563,53.31772],"type":"Point"}
}
