{
  "type": "Feature",
  "properties": {
    "iso:country":"GB",
    "wof:name":"WS11 8XW",
    "wof:placetype":"postalcode"
},
  "geometry": {"coordinates":[-2.01582698909641,52.67659521946167],"type":"Point"}
}