{
  "type": "Feature",
  "properties": {
    "date:inception_lower": "2003-03-01",
    "date:inception_upper": "2003-03-01",
    "iso:country": "GB",
    "wof:name": "WS11 8XW",
    "wof:placetype": "postalcode"
  },
  "geometry": {"coordinates":[-2.019051,52.676846],"type":"Point"}
}
