{
  "type": "Feature",
  "properties": {
    "iso:country": "GB",
    "wof:name": "CV2 1UW",
    "wof:placetype": "postalcode"
  },
  "geometry": {"coordinates":[-1.466653,52.436256],"type":"Point"}
}
