{
  "type": "Feature",
  "properties": {
    "iso:country":"GB",
    "wof:name":"CF39 8AW",
    "wof:placetype":"postalcode"
},
  "geometry": {"coordinates":[-3.42503219092032,51.57263842612604],"type":"Point"}
}