{
  "type": "Feature",
  "properties": {
    "iso:country":"GB",
    "wof:name":"LE5 1AR",
    "wof:placetype":"postalcode"
},
  "geometry": {"coordinates":[-1.08236871142181,52.64409861890065],"type":"Point"}
}