{
  "type": "Feature",
  "properties": {
    "date:inception_lower": "1980-01-01",
    "date:inception_upper": "1980-01-01",
    "iso:country": "GB",
    "wof:name": "LE5 1AR",
    "wof:placetype": "postalcode"
  },
  "geometry": {"coordinates":[-1.082369,52.644099],"type":"Point"}
}
