{
  "type": "Feature",
  "properties": {
    "iso:country": "GB",
    "wof:name": "RH17 7GF",
    "wof:placetype": "postalcode"
  },
  "geometry": {"coordinates":[-0.08122,50.989045],"type":"Point"}
}
