{
  "type": "Feature",
  "properties": {
    "iso:country": "GB",
    "wof:name": "DE4 2PJ",
    "wof:placetype": "postalcode"
  },
  "geometry": {"coordinates":[-1.714457,53.12795],"type":"Point"}
}
