{
  "type": "Feature",
  "properties": {
    "iso:country":"GB",
    "wof:name":"DE4 2PJ",
    "wof:placetype":"postalcode"
},
  "geometry": {"coordinates":[-1.71445747327786,53.12794957768515],"type":"Point"}
}