{
  "type": "Feature",
  "properties": {
    "iso:country": "GB",
    "wof:name": "FK5 4NW",
    "wof:placetype": "postalcode"
  },
  "geometry": {"coordinates":[-3.840342,56.027545],"type":"Point"}
}
