{
  "type": "Feature",
  "properties": {
    "iso:country":"GB",
    "wof:name":"LU1 4LB",
    "wof:placetype":"postalcode"
},
  "geometry": {"coordinates":[-0.41701016921659,51.85606939965716],"type":"Point"}
}