{
  "type": "Feature",
  "properties": {
    "iso:country":"GB",
    "wof:name":"DL6 3LA",
    "wof:placetype":"postalcode"
},
  "geometry": {"coordinates":[-1.3244297872439,54.43890041435099],"type":"Point"}
}