{
  "type": "Feature",
  "properties": {
    "iso:country": "GB",
    "wof:name": "RH10 6JP",
    "wof:placetype": "postalcode"
  },
  "geometry": {"coordinates":[-0.171036,51.108407],"type":"Point"}
}
