{
  "type": "Feature",
  "properties": {
    "iso:country":"GB",
    "wof:name":"RH10 6JP",
    "wof:placetype":"postalcode"
},
  "geometry": {"coordinates":[-0.1710362581966,51.10840729274285],"type":"Point"}
}