{
  "type": "Feature",
  "properties": {
    "iso:country": "GB",
    "wof:name": "GU9 8NX",
    "wof:placetype": "postalcode"
  },
  "geometry": {"coordinates":[-0.799771,51.206412],"type":"Point"}
}
