{
  "type": "Feature",
  "properties": {
    "iso:country":"GB",
    "wof:name":"BD20 0PW",
    "wof:placetype":"postalcode"
},
  "geometry": {"coordinates":[-1.94381701739079,53.91488677842371],"type":"Point"}
}