{
  "type": "Feature",
  "properties": {
    "date:inception_lower": "1980-01-01",
    "date:inception_upper": "1980-01-01",
    "iso:country": "GB",
    "wof:name": "SK14 5DB",
    "wof:placetype": "postalcode"
  },
  "geometry": {"coordinates":[-2.080347,53.439059],"type":"Point"}
}
