{
  "type": "Feature",
  "properties": {
    "iso:country":"GB",
    "wof:name":"SK14 5DB",
    "wof:placetype":"postalcode"
},
  "geometry": {"coordinates":[-2.08034704058093,53.43905855934242],"type":"Point"}
}