{
  "type": "Feature",
  "properties": {
    "iso:country":"GB",
    "wof:name":"BN44 3DS",
    "wof:placetype":"postalcode"
},
  "geometry": {"coordinates":[-0.37237974704462,50.91606522546022],"type":"Point"}
}