{
  "type": "Feature",
  "properties": {
    "date:inception_lower": "1990-07-01",
    "date:inception_upper": "1990-07-01",
    "iso:country": "GB",
    "wof:name": "BN44 3DS",
    "wof:placetype": "postalcode"
  },
  "geometry": {"coordinates":[-0.372299,50.916031],"type":"Point"}
}
