{
  "type": "Feature",
  "properties": {
    "date:inception_lower": "2011-07-01",
    "date:inception_upper": "2011-07-01",
    "iso:country": "GB",
    "wof:name": "LE7 2DF",
    "wof:placetype": "postalcode"
  },
  "geometry": {"coordinates":[-1.060923,52.696558],"type":"Point"}
}
