{
  "type": "Feature",
  "properties": {
    "iso:country": "GB",
    "wof:name": "WR10 3AX",
    "wof:placetype": "postalcode"
  },
  "geometry": {"coordinates":[-2.110761,52.071752],"type":"Point"}
}
