{
  "type": "Feature",
  "properties": {
    "iso:country":"GB",
    "wof:name":"WR10 3AX",
    "wof:placetype":"postalcode"
},
  "geometry": {"coordinates":[-2.1107609723389,52.07175168352688],"type":"Point"}
}