{
  "type": "Feature",
  "properties": {
    "iso:country":"GB",
    "wof:name":"NE20 9JR",
    "wof:placetype":"postalcode"
},
  "geometry": {"coordinates":[-1.76020300474236,55.03139039583705],"type":"Point"}
}