{
  "type": "Feature",
  "properties": {
    "iso:country":"GB",
    "wof:name":"L25 9RH",
    "wof:placetype":"postalcode"
},
  "geometry": {"coordinates":[-2.84819381184793,53.36355068901328],"type":"Point"}
}