{
  "type": "Feature",
  "properties": {
    "iso:country": "GB",
    "wof:name": "S80 4DA",
    "wof:placetype": "postalcode"
  },
  "geometry": {"coordinates":[-1.220833,53.270675],"type":"Point"}
}
