{
  "type": "Feature",
  "properties": {
    "iso:country":"GB",
    "wof:name":"S80 4DA",
    "wof:placetype":"postalcode"
},
  "geometry": {"coordinates":[-1.22083318996499,53.27067490658352],"type":"Point"}
}