{
  "type": "Feature",
  "properties": {
    "iso:country":"GB",
    "wof:name":"SS0 7HT",
    "wof:placetype":"postalcode"
},
  "geometry": {"coordinates":[0.69495005984162,51.54284585077034],"type":"Point"}
}