{
  "type": "Feature",
  "properties": {
    "iso:country":"GB",
    "wof:name":"SL5 8ER",
    "wof:placetype":"postalcode"
},
  "geometry": {"coordinates":[-0.68728850798999,51.417916689605],"type":"Point"}
}