{
  "type": "Feature",
  "properties": {
    "date:inception_lower": "2018-06-01",
    "date:inception_upper": "2018-06-01",
    "iso:country": "GB",
    "wof:name": "ZE2 9FP",
    "wof:placetype": "postalcode"
  },
  "geometry": {"coordinates":[-1.207393,60.053907],"type":"Point"}
}
