{
  "type": "Feature",
  "properties": {
    "iso:country": "GB",
    "wof:name": "ZE2 9FP",
    "wof:placetype": "postalcode"
  },
  "geometry": {"coordinates":[-1.208498,60.055772],"type":"Point"}
}
