{
  "type": "Feature",
  "properties": {
    "iso:country": "GB",
    "wof:name": "HP11 2BN",
    "wof:placetype": "postalcode"
  },
  "geometry": {"coordinates":[-0.750527,51.629486],"type":"Point"}
}
