{
  "type": "Feature",
  "properties": {
    "iso:country":"GB",
    "wof:name":"W12 9NT",
    "wof:placetype":"postalcode"
},
  "geometry": {"coordinates":[-0.23522355912845,51.50069279440659],"type":"Point"}
}