{
  "type": "Feature",
  "properties": {
    "iso:country":"GB",
    "wof:name":"WF5 0HZ",
    "wof:placetype":"postalcode"
},
  "geometry": {"coordinates":[-1.55473762577174,53.67486756882388],"type":"Point"}
}