{
  "type": "Feature",
  "properties": {
    "iso:country":"GB",
    "wof:name":"DY3 3XB",
    "wof:placetype":"postalcode"
},
  "geometry": {"coordinates":[-2.12198457155527,52.53130347998066],"type":"Point"}
}