{
  "type": "Feature",
  "properties": {
    "iso:country":"GB",
    "wof:name":"BR6 8AN",
    "wof:placetype":"postalcode"
},
  "geometry": {"coordinates":[0.07776143159874,51.37187703904672],"type":"Point"}
}