{
  "type": "Feature",
  "properties": {
    "iso:country":"GB",
    "wof:name":"CF10 5BP",
    "wof:placetype":"postalcode"
},
  "geometry": {"coordinates":[-3.16557432561531,51.46510091429769],"type":"Point"}
}