{
  "type": "Feature",
  "properties": {
    "date:inception_lower": "2014-03-01",
    "date:inception_upper": "2014-03-01",
    "iso:country": "GB",
    "wof:name": "CF10 5BP",
    "wof:placetype": "postalcode"
  },
  "geometry": {"coordinates":[-3.165574,51.465101],"type":"Point"}
}
