{
  "type": "Feature",
  "properties": {
    "date:inception_lower":"1982-03-01",
    "date:inception_upper":"1982-03-31",
    "iso:country":"GB",
    "wof:name":"WN4 9LT",
    "wof:placetype":"postalcode"
},
  "geometry": {"coordinates":[-2.651281,53.487879],"type":"Point"}
}