{
  "type": "Feature",
  "properties": {
    "iso:country":"GB",
    "wof:name":"WN4 9LT",
    "wof:placetype":"postalcode"
},
  "geometry": {"coordinates":[-2.65128108414804,53.48787902062536],"type":"Point"}
}