{
  "type": "Feature",
  "properties": {
    "date:inception_lower": "1980-01-01",
    "date:inception_upper": "1980-01-01",
    "iso:country": "GB",
    "wof:name": "DD6 8BW",
    "wof:placetype": "postalcode"
  },
  "geometry": {"coordinates":[-2.938113,56.441097],"type":"Point"}
}
