{
  "type": "Feature",
  "properties": {
    "iso:country": "GB",
    "wof:name": "L15 9EW",
    "wof:placetype": "postalcode"
  },
  "geometry": {"coordinates":[-2.914078,53.389006],"type":"Point"}
}
