{
  "type": "Feature",
  "properties": {
    "iso:country":"GB",
    "wof:name":"BN21 3AJ",
    "wof:placetype":"postalcode"
},
  "geometry": {"coordinates":[0.28513476222954,50.76824783691041],"type":"Point"}
}