{
  "type": "Feature",
  "properties": {
    "iso:country":"GB",
    "wof:name":"CF14 2LW",
    "wof:placetype":"postalcode"
},
  "geometry": {"coordinates":[-3.22584919663159,51.50427546489725],"type":"Point"}
}