{
  "type": "Feature",
  "properties": {
    "iso:country":"GB",
    "wof:name":"SP11 6JH",
    "wof:placetype":"postalcode"
},
  "geometry": {"coordinates":[-1.46062258976844,51.23977350028903],"type":"Point"}
}