{
  "type": "Feature",
  "properties": {
    "iso:country": "GB",
    "wof:name": "CA3 9NY",
    "wof:placetype": "postalcode"
  },
  "geometry": {"coordinates":[-2.958509,54.904374],"type":"Point"}
}
