{
  "type": "Feature",
  "properties": {
    "iso:country":"GB",
    "wof:name":"CA3 9NY",
    "wof:placetype":"postalcode"
},
  "geometry": {"coordinates":[-2.95850925640566,54.9043736033498],"type":"Point"}
}