{
  "type": "Feature",
  "properties": {
    "date:inception_lower": "1980-01-01",
    "date:inception_upper": "1980-01-01",
    "iso:country": "GB",
    "wof:name": "IP4 4DT",
    "wof:placetype": "postalcode"
  },
  "geometry": {"coordinates":[1.180063,52.060228],"type":"Point"}
}
