{
  "type": "Feature",
  "properties": {
    "iso:country":"GB",
    "wof:name":"IP4 4DT",
    "wof:placetype":"postalcode"
},
  "geometry": {"coordinates":[1.18006316187862,52.06022840444951],"type":"Point"}
}