{
  "type": "Feature",
  "properties": {
    "iso:country": "GB",
    "wof:name": "LN9 5SH",
    "wof:placetype": "postalcode"
  },
  "geometry": {"coordinates":[-0.115563,53.210143],"type":"Point"}
}
