{
  "type": "Feature",
  "properties": {
    "date:inception_lower":"1985-04-01",
    "date:inception_upper":"1985-04-30",
    "iso:country":"GB",
    "wof:name":"LN9 5SH",
    "wof:placetype":"postalcode"
},
  "geometry": {"coordinates":[-0.115563,53.210143],"type":"Point"}
}