{
  "type": "Feature",
  "properties": {
    "iso:country": "GB",
    "wof:name": "CV4 8DX",
    "wof:placetype": "postalcode"
  },
  "geometry": {"coordinates":[-1.556369,52.393391],"type":"Point"}
}
