{
  "type": "Feature",
  "properties": {
    "iso:country":"GB",
    "wof:name":"SW16 6TZ",
    "wof:placetype":"postalcode"
},
  "geometry": {"coordinates":[-0.146170179864,51.42709960648294],"type":"Point"}
}