{
  "type": "Feature",
  "properties": {
    "iso:country":"GB",
    "wof:name":"KY10 3XL",
    "wof:placetype":"postalcode"
},
  "geometry": {"coordinates":[-2.61878401821288,56.26998091361262],"type":"Point"}
}