{
  "type": "Feature",
  "properties": {
    "iso:country": "GB",
    "wof:name": "KY10 3XL",
    "wof:placetype": "postalcode"
  },
  "geometry": {"coordinates":[-2.619556,56.270777],"type":"Point"}
}
