{
  "type": "Feature",
  "properties": {
    "iso:country":"GB",
    "wof:name":"TW18 2RN",
    "wof:placetype":"postalcode"
},
  "geometry": {"coordinates":[-0.50037566585838,51.42272441902097],"type":"Point"}
}