{
  "type": "Feature",
  "properties": {
    "date:inception_lower": "1980-01-01",
    "date:inception_upper": "1980-01-01",
    "iso:country": "GB",
    "wof:name": "TW18 2RN",
    "wof:placetype": "postalcode"
  },
  "geometry": {"coordinates":[-0.500376,51.422724],"type":"Point"}
}
