{
  "type": "Feature",
  "properties": {
    "iso:country":"GB",
    "wof:name":"HP18 0PZ",
    "wof:placetype":"postalcode"
},
  "geometry": {"coordinates":[-0.88108047630872,51.8416800354595],"type":"Point"}
}