{
  "type": "Feature",
  "properties": {
    "iso:country": "GB",
    "wof:name": "HP18 0PZ",
    "wof:placetype": "postalcode"
  },
  "geometry": {"coordinates":[-0.876875,51.841532],"type":"Point"}
}
