{
  "type": "Feature",
  "properties": {
    "iso:country":"GB",
    "wof:name":"WF9 4DQ",
    "wof:placetype":"postalcode"
},
  "geometry": {"coordinates":[-1.34649857429566,53.60569110606318],"type":"Point"}
}