{
  "type": "Feature",
  "properties": {
    "date:inception_lower": "1984-10-01",
    "date:inception_upper": "1984-10-01",
    "iso:country": "GB",
    "wof:name": "BS16 1JJ",
    "wof:placetype": "postalcode"
  },
  "geometry": {"coordinates":[-2.534876,51.492037],"type":"Point"}
}
