{
  "type": "Feature",
  "properties": {
    "iso:country": "GB",
    "wof:name": "BS16 1JJ",
    "wof:placetype": "postalcode"
  },
  "geometry": {"coordinates":[-2.534876,51.492037],"type":"Point"}
}
