{
  "type": "Feature",
  "properties": {
    "iso:country":"GB",
    "wof:name":"BS16 1JJ",
    "wof:placetype":"postalcode"
},
  "geometry": {"coordinates":[-2.53487570025452,51.49203747766866],"type":"Point"}
}