{
  "type": "Feature",
  "properties": {
    "iso:country":"GB",
    "wof:name":"B75 5PQ",
    "wof:placetype":"postalcode"
},
  "geometry": {"coordinates":[-1.80359109825824,52.59017750315256],"type":"Point"}
}