{
  "type": "Feature",
  "properties": {
    "date:inception_lower": "1996-06-01",
    "date:inception_upper": "1996-06-01",
    "iso:country": "GB",
    "wof:name": "B75 5PQ",
    "wof:placetype": "postalcode"
  },
  "geometry": {"coordinates":[-1.803591,52.590177],"type":"Point"}
}
