{
  "type": "Feature",
  "properties": {
    "iso:country":"GB",
    "wof:name":"S81 7LZ",
    "wof:placetype":"postalcode"
},
  "geometry": {"coordinates":[-1.12377715271795,53.32102307674281],"type":"Point"}
}