{
  "type": "Feature",
  "properties": {
    "iso:country":"GB",
    "wof:name":"NE26 4BZ",
    "wof:placetype":"postalcode"
},
  "geometry": {"coordinates":[-1.47220239507459,55.0778132718444],"type":"Point"}
}