{
  "type": "Feature",
  "properties": {
    "date:inception_lower": "1999-06-01",
    "date:inception_upper": "1999-06-01",
    "iso:country": "GB",
    "wof:name": "DN10 6XF",
    "wof:placetype": "postalcode"
  },
  "geometry": {"coordinates":[-1.028495,53.426625],"type":"Point"}
}
