{
  "type": "Feature",
  "properties": {
    "iso:country": "GB",
    "wof:name": "DN10 6XF",
    "wof:placetype": "postalcode"
  },
  "geometry": {"coordinates":[-1.028495,53.426625],"type":"Point"}
}
