{
  "type": "Feature",
  "properties": {
    "iso:country":"GB",
    "wof:name":"NR35 2AH",
    "wof:placetype":"postalcode"
},
  "geometry": {"coordinates":[1.39190243958964,52.45021615538909],"type":"Point"}
}