{
  "type": "Feature",
  "properties": {
    "date:inception_lower": "1995-07-01",
    "date:inception_upper": "1995-07-01",
    "iso:country": "GB",
    "wof:name": "IP30 9RB",
    "wof:placetype": "postalcode"
  },
  "geometry": {"coordinates":[0.892034,52.222222],"type":"Point"}
}
