{
  "type": "Feature",
  "properties": {
    "date:inception_lower": "1983-03-01",
    "date:inception_upper": "1983-03-01",
    "iso:country": "GB",
    "wof:name": "RG27 9NU",
    "wof:placetype": "postalcode"
  },
  "geometry": {"coordinates":[-0.96757,51.281991],"type":"Point"}
}
