{
  "type": "Feature",
  "properties": {
    "date:inception_lower": "2022-07-01",
    "date:inception_upper": "2022-07-01",
    "iso:country": "GB",
    "wof:name": "ST4 3AG",
    "wof:placetype": "postalcode"
  },
  "geometry": {"coordinates":[-2.163919,52.99922],"type":"Point"}
}
