{
  "type": "Feature",
  "properties": {
    "iso:country": "GB",
    "wof:name": "CO11 1ES",
    "wof:placetype": "postalcode"
  },
  "geometry": {"coordinates":[1.060158,51.944777],"type":"Point"}
}
