{
  "type": "Feature",
  "properties": {
    "iso:country":"GB",
    "wof:name":"CO11 1ES",
    "wof:placetype":"postalcode"
},
  "geometry": {"coordinates":[1.06015834843341,51.94477735369404],"type":"Point"}
}