{
  "type": "Feature",
  "properties": {
    "iso:country":"GB",
    "wof:name":"W1H 7TQ",
    "wof:placetype":"postalcode"
},
  "geometry": {"coordinates":[-0.16053970808206,51.51590253734595],"type":"Point"}
}