{
  "type": "Feature",
  "properties": {
    "date:inception_lower": "2000-12-01",
    "date:inception_upper": "2000-12-01",
    "iso:country": "GB",
    "wof:name": "W1H 7TQ",
    "wof:placetype": "postalcode"
  },
  "geometry": {"coordinates":[-0.16054,51.515903],"type":"Point"}
}
