{
  "type": "Feature",
  "properties": {
    "iso:country":"GB",
    "wof:name":"NE16 4HL",
    "wof:placetype":"postalcode"
},
  "geometry": {"coordinates":[-1.66474077669697,54.94500518795855],"type":"Point"}
}