{
  "type": "Feature",
  "properties": {
    "iso:country": "GB",
    "wof:name": "NE16 4HL",
    "wof:placetype": "postalcode"
  },
  "geometry": {"coordinates":[-1.664741,54.945005],"type":"Point"}
}
