{
  "type": "Feature",
  "properties": {
    "iso:country":"GB",
    "wof:name":"PR1 5AJ",
    "wof:placetype":"postalcode"
},
  "geometry": {"coordinates":[-2.68614348453286,53.76573119944435],"type":"Point"}
}