{
  "type": "Feature",
  "properties": {
    "date:inception_lower":"2004-04-01",
    "date:inception_upper":"2004-04-30",
    "iso:country":"GB",
    "wof:name":"PR1 5AJ",
    "wof:placetype":"postalcode"
},
  "geometry": {"coordinates":[-2.686141,53.765747],"type":"Point"}
}