{
  "type": "Feature",
  "properties": {
    "iso:country": "GB",
    "wof:name": "PR1 5AJ",
    "wof:placetype": "postalcode"
  },
  "geometry": {"coordinates":[-2.686141,53.765747],"type":"Point"}
}
