{
  "type": "Feature",
  "properties": {
    "iso:country":"GB",
    "wof:name":"L1 1LS",
    "wof:placetype":"postalcode"
},
  "geometry": {"coordinates":[-2.9806733986127,53.40660830083642],"type":"Point"}
}