{
  "type": "Feature",
  "properties": {
    "iso:country":"GB",
    "wof:name":"CA11 8PQ",
    "wof:placetype":"postalcode"
},
  "geometry": {"coordinates":[-2.75037346589956,54.65695880431247],"type":"Point"}
}