{
  "type": "Feature",
  "properties": {
    "iso:country":"GB",
    "wof:name":"M41 5BF",
    "wof:placetype":"postalcode"
},
  "geometry": {"coordinates":[-2.36272150778184,53.44782845369115],"type":"Point"}
}