{
  "type": "Feature",
  "properties": {
    "iso:country":"GB",
    "wof:name":"E13 8PD",
    "wof:placetype":"postalcode"
},
  "geometry": {"coordinates":[0.03013886368696,51.51836845463325],"type":"Point"}
}