{
  "type": "Feature",
  "properties": {
    "date:inception_lower": "1980-01-01",
    "date:inception_upper": "1980-01-01",
    "iso:country": "GB",
    "wof:name": "E13 8PD",
    "wof:placetype": "postalcode"
  },
  "geometry": {"coordinates":[0.030139,51.518368],"type":"Point"}
}
