{
  "type": "Feature",
  "properties": {
    "iso:country":"GB",
    "wof:name":"NE61 5LJ",
    "wof:placetype":"postalcode"
},
  "geometry": {"coordinates":[-1.55887001687213,55.2224463943251],"type":"Point"}
}