{
  "type": "Feature",
  "properties": {
    "date:inception_lower": "1980-01-01",
    "date:inception_upper": "1980-01-01",
    "iso:country": "GB",
    "wof:name": "NE61 5LJ",
    "wof:placetype": "postalcode"
  },
  "geometry": {"coordinates":[-1.55887,55.222446],"type":"Point"}
}
