{
  "type": "Feature",
  "properties": {
    "iso:country": "GB",
    "wof:name": "NE61 5LJ",
    "wof:placetype": "postalcode"
  },
  "geometry": {"coordinates":[-1.55887,55.222446],"type":"Point"}
}
