{
  "type": "Feature",
  "properties": {
    "iso:country":"GB",
    "wof:name":"L23 0TH",
    "wof:placetype":"postalcode"
},
  "geometry": {"coordinates":[-3.00877586064418,53.48677077318574],"type":"Point"}
}