{
  "type": "Feature",
  "properties": {
    "iso:country": "GB",
    "wof:name": "BN13 3SZ",
    "wof:placetype": "postalcode"
  },
  "geometry": {"coordinates":[-0.427228,50.827191],"type":"Point"}
}
