{
  "type": "Feature",
  "properties": {
    "iso:country":"GB",
    "wof:name":"SG7 6JF",
    "wof:placetype":"postalcode"
},
  "geometry": {"coordinates":[-0.19185112707225,51.98153384905724],"type":"Point"}
}