{
  "type": "Feature",
  "properties": {
    "date:inception_lower": "1980-01-01",
    "date:inception_upper": "1980-01-01",
    "iso:country": "GB",
    "wof:name": "SG7 6JF",
    "wof:placetype": "postalcode"
  },
  "geometry": {"coordinates":[-0.191839,51.981543],"type":"Point"}
}
