{
  "type": "Feature",
  "properties": {
    "date:inception_lower": "2008-06-01",
    "date:inception_upper": "2008-06-01",
    "iso:country": "GB",
    "wof:name": "DY9 9AF",
    "wof:placetype": "postalcode"
  },
  "geometry": {"coordinates":[-2.119516,52.393247],"type":"Point"}
}
