{
  "type": "Feature",
  "properties": {
    "iso:country":"GB",
    "wof:name":"DY9 9AF",
    "wof:placetype":"postalcode"
},
  "geometry": {"coordinates":[-2.11951604569696,52.39324672712019],"type":"Point"}
}