{
  "type": "Feature",
  "properties": {
    "date:inception_lower": "1980-01-01",
    "date:inception_upper": "1980-01-01",
    "iso:country": "GB",
    "wof:name": "EX3 0NZ",
    "wof:placetype": "postalcode"
  },
  "geometry": {"coordinates":[-3.435753,50.690295],"type":"Point"}
}
