{
  "type": "Feature",
  "properties": {
    "iso:country":"GB",
    "wof:name":"HU11 4NQ",
    "wof:placetype":"postalcode"
},
  "geometry": {"coordinates":[-0.14597632797873,53.8092754429634],"type":"Point"}
}