{
  "type": "Feature",
  "properties": {
    "iso:country":"GB",
    "wof:name":"BS4 1DZ",
    "wof:placetype":"postalcode"
},
  "geometry": {"coordinates":[-2.57921665771702,51.42886741174707],"type":"Point"}
}