{
  "type": "Feature",
  "properties": {
    "date:inception_lower": "1980-01-01",
    "date:inception_upper": "1980-01-01",
    "iso:country": "GB",
    "wof:name": "BS4 1DZ",
    "wof:placetype": "postalcode"
  },
  "geometry": {"coordinates":[-2.579217,51.428867],"type":"Point"}
}
