{
  "type": "Feature",
  "properties": {
    "iso:country": "GB",
    "wof:name": "G65 9JY",
    "wof:placetype": "postalcode"
  },
  "geometry": {"coordinates":[-4.062066,55.977269],"type":"Point"}
}
