{
  "type": "Feature",
  "properties": {
    "iso:country":"GB",
    "wof:name":"G65 9JY",
    "wof:placetype":"postalcode"
},
  "geometry": {"coordinates":[-4.06206594295201,55.97726878125717],"type":"Point"}
}