{
  "type": "Feature",
  "properties": {
    "date:inception_lower":"1980-01-01",
    "date:inception_upper":"1980-01-31",
    "iso:country":"GB",
    "wof:name":"DN35 7ND",
    "wof:placetype":"postalcode"
},
  "geometry": {"coordinates":[-0.056859,53.568362],"type":"Point"}
}