{
  "type": "Feature",
  "properties": {
    "iso:country":"GB",
    "wof:name":"DN35 7ND",
    "wof:placetype":"postalcode"
},
  "geometry": {"coordinates":[-0.05685937045724,53.56836199753298],"type":"Point"}
}