{
  "type": "Feature",
  "properties": {
    "iso:country":"GB",
    "wof:name":"UB6 0PH",
    "wof:placetype":"postalcode"
},
  "geometry": {"coordinates":[-0.33352955547123,51.5523796460954],"type":"Point"}
}