{
  "type": "Feature",
  "properties": {
    "iso:country": "GB",
    "wof:name": "UB6 0PH",
    "wof:placetype": "postalcode"
  },
  "geometry": {"coordinates":[-0.33353,51.55238],"type":"Point"}
}
