{
  "type": "Feature",
  "properties": {
    "date:inception_lower": "1980-01-01",
    "date:inception_upper": "1980-01-01",
    "iso:country": "GB",
    "wof:name": "NG2 4QA",
    "wof:placetype": "postalcode"
  },
  "geometry": {"coordinates":[-1.134942,52.954263],"type":"Point"}
}
