{
  "type": "Feature",
  "properties": {
    "iso:country":"GB",
    "wof:name":"NG2 4QA",
    "wof:placetype":"postalcode"
},
  "geometry": {"coordinates":[-1.13494243682588,52.95426259310312],"type":"Point"}
}