{
  "type": "Feature",
  "properties": {
    "date:inception_lower":"1980-01-01",
    "date:inception_upper":"1980-01-31",
    "iso:country":"GB",
    "wof:name":"LE3 8BJ",
    "wof:placetype":"postalcode"
},
  "geometry": {"coordinates":[-1.200569,52.650978],"type":"Point"}
}