{
  "type": "Feature",
  "properties": {
    "iso:country":"GB",
    "wof:name":"LE3 8BJ",
    "wof:placetype":"postalcode"
},
  "geometry": {"coordinates":[-1.20056863734538,52.65097801202862],"type":"Point"}
}