{
  "type": "Feature",
  "properties": {
    "iso:country":"GB",
    "wof:name":"CF81 8UW",
    "wof:placetype":"postalcode"
},
  "geometry": {"coordinates":[-3.23643144195148,51.68948516531025],"type":"Point"}
}