{
  "type": "Feature",
  "properties": {
    "iso:country":"GB",
    "wof:name":"BD20 5PJ",
    "wof:placetype":"postalcode"
},
  "geometry": {"coordinates":[-1.8854186887551,53.8808804532272],"type":"Point"}
}