{
  "type": "Feature",
  "properties": {
    "date:inception_lower":"1980-01-01",
    "date:inception_upper":"1980-01-31",
    "iso:country":"GB",
    "wof:name":"BD20 5PJ",
    "wof:placetype":"postalcode"
},
  "geometry": {"coordinates":[-1.885419,53.88088],"type":"Point"}
}