{
  "type": "Feature",
  "properties": {
    "iso:country": "GB",
    "wof:name": "LE65 1GS",
    "wof:placetype": "postalcode"
  },
  "geometry": {"coordinates":[-1.462449,52.750928],"type":"Point"}
}
