{
  "type": "Feature",
  "properties": {
    "date:inception_lower": "2014-04-01",
    "date:inception_upper": "2014-04-01",
    "iso:country": "GB",
    "wof:name": "BN1 3GY",
    "wof:placetype": "postalcode"
  },
  "geometry": {"coordinates":[-0.146844,50.828345],"type":"Point"}
}
