{
  "type": "Feature",
  "properties": {
    "iso:country":"GB",
    "wof:name":"BN1 3GY",
    "wof:placetype":"postalcode"
},
  "geometry": {"coordinates":[-0.14684447066206,50.82834510885004],"type":"Point"}
}