{
  "type": "Feature",
  "properties": {
    "iso:country":"GB",
    "wof:name":"PE22 0LS",
    "wof:placetype":"postalcode"
},
  "geometry": {"coordinates":[0.0675841330434,52.95395517319891],"type":"Point"}
}