{
  "type": "Feature",
  "properties": {
    "iso:country":"GB",
    "wof:name":"AB53 4GE",
    "wof:placetype":"postalcode"
},
  "geometry": {"coordinates":[-2.46467759779927,57.5381976435174],"type":"Point"}
}