{
  "type": "Feature",
  "properties": {
    "iso:country":"GB",
    "wof:name":"NN3 3LX",
    "wof:placetype":"postalcode"
},
  "geometry": {"coordinates":[-0.85496818873464,52.24337429627779],"type":"Point"}
}