{
  "type": "Feature",
  "properties": {
    "iso:country":"GB",
    "wof:name":"EH18 1DJ",
    "wof:placetype":"postalcode"
},
  "geometry": {"coordinates":[-3.1287250713498,55.87067105186923],"type":"Point"}
}