{
  "type": "Feature",
  "properties": {
    "iso:country": "GB",
    "wof:name": "EH18 1DJ",
    "wof:placetype": "postalcode"
  },
  "geometry": {"coordinates":[-3.128725,55.870671],"type":"Point"}
}
