{
  "type": "Feature",
  "properties": {
    "date:inception_lower":"1991-09-01",
    "date:inception_upper":"1991-09-30",
    "iso:country":"GB",
    "wof:name":"WV14 8XN",
    "wof:placetype":"postalcode"
},
  "geometry": {"coordinates":[-2.078538,52.545679],"type":"Point"}
}