{
  "type": "Feature",
  "properties": {
    "iso:country":"GB",
    "wof:name":"WV14 8XN",
    "wof:placetype":"postalcode"
},
  "geometry": {"coordinates":[-2.07853833878674,52.54567921887167],"type":"Point"}
}