{
  "type": "Feature",
  "properties": {
    "iso:country": "GB",
    "wof:name": "WV14 8XN",
    "wof:placetype": "postalcode"
  },
  "geometry": {"coordinates":[-2.078538,52.545679],"type":"Point"}
}
