{
  "type": "Feature",
  "properties": {
    "iso:country":"GB",
    "wof:name":"KA1 3ST",
    "wof:placetype":"postalcode"
},
  "geometry": {"coordinates":[-4.48506228281209,55.59032672503929],"type":"Point"}
}