{
  "type": "Feature",
  "properties": {
    "iso:country":"GB",
    "wof:name":"NW1 9EA",
    "wof:placetype":"postalcode"
},
  "geometry": {"coordinates":[-0.13857695159393,51.5412925430099],"type":"Point"}
}