{
  "type": "Feature",
  "properties": {
    "iso:country":"GB",
    "wof:name":"CW2 5QF",
    "wof:placetype":"postalcode"
},
  "geometry": {"coordinates":[-2.37018358729129,53.05152362850539],"type":"Point"}
}