{
  "type": "Feature",
  "properties": {
    "date:inception_lower": "1980-01-01",
    "date:inception_upper": "1980-01-01",
    "iso:country": "GB",
    "wof:name": "CW2 5QF",
    "wof:placetype": "postalcode"
  },
  "geometry": {"coordinates":[-2.370184,53.051524],"type":"Point"}
}
