{
  "type": "Feature",
  "properties": {
    "date:inception_lower": "1998-06-01",
    "date:inception_upper": "1998-06-01",
    "iso:country": "GB",
    "wof:name": "YO61 3LW",
    "wof:placetype": "postalcode"
  },
  "geometry": {"coordinates":[-1.275344,54.11726],"type":"Point"}
}
