{
  "type": "Feature",
  "properties": {
    "iso:country":"GB",
    "wof:name":"SM1 2LP",
    "wof:placetype":"postalcode"
},
  "geometry": {"coordinates":[-0.21403919310014,51.36357763150811],"type":"Point"}
}