{
  "type": "Feature",
  "properties": {
    "iso:country": "GB",
    "wof:name": "CM77 6DE",
    "wof:placetype": "postalcode"
  },
  "geometry": {"coordinates":[0.504577,51.877321],"type":"Point"}
}
