{
  "type": "Feature",
  "properties": {
    "iso:country":"GB",
    "wof:name":"NR19 2NJ",
    "wof:placetype":"postalcode"
},
  "geometry": {"coordinates":[0.94136035324594,52.68330725861802],"type":"Point"}
}