{
  "type": "Feature",
  "properties": {
    "date:inception_lower": "2004-11-01",
    "date:inception_upper": "2004-11-01",
    "iso:country": "GB",
    "wof:name": "NR19 2NJ",
    "wof:placetype": "postalcode"
  },
  "geometry": {"coordinates":[0.941478,52.683185],"type":"Point"}
}
