{
  "type": "Feature",
  "properties": {
    "date:inception_lower": "1994-12-01",
    "date:inception_upper": "1994-12-01",
    "iso:country": "GB",
    "wof:name": "SO40 9HJ",
    "wof:placetype": "postalcode"
  },
  "geometry": {"coordinates":[-1.484745,50.917035],"type":"Point"}
}
