{
  "type": "Feature",
  "properties": {
    "date:inception_lower": "2000-10-01",
    "date:inception_upper": "2000-10-01",
    "iso:country": "GB",
    "wof:name": "GL52 9RD",
    "wof:placetype": "postalcode"
  },
  "geometry": {"coordinates":[-2.022652,51.965964],"type":"Point"}
}
