{
  "type": "Feature",
  "properties": {
    "iso:country": "GB",
    "wof:name": "GL52 9RD",
    "wof:placetype": "postalcode"
  },
  "geometry": {"coordinates":[-2.024333,51.965316],"type":"Point"}
}
