{
  "type": "Feature",
  "properties": {
    "iso:country":"GB",
    "wof:name":"GL52 9RD",
    "wof:placetype":"postalcode"
},
  "geometry": {"coordinates":[-2.0243330560297,51.96531596251172],"type":"Point"}
}