{
  "type": "Feature",
  "properties": {
    "date:inception_lower": "2000-10-01",
    "date:inception_upper": "2000-10-01",
    "iso:country": "GB",
    "wof:name": "GL52 9RD",
    "wof:placetype": "postalcode"
  },
  "geometry": {"coordinates":[-2.024333,51.965316],"type":"Point"}
}
