{
  "type": "Feature",
  "properties": {
    "date:inception_lower": "2007-04-01",
    "date:inception_upper": "2007-04-01",
    "iso:country": "GB",
    "wof:name": "NG22 0BF",
    "wof:placetype": "postalcode"
  },
  "geometry": {"coordinates":[-0.919588,53.194399],"type":"Point"}
}
