{
  "type": "Feature",
  "properties": {
    "iso:country":"GB",
    "wof:name":"BH9 2DG",
    "wof:placetype":"postalcode"
},
  "geometry": {"coordinates":[-1.8749557007163,50.75512447470004],"type":"Point"}
}