{
  "type": "Feature",
  "properties": {
    "iso:country":"GB",
    "wof:name":"DG1 4HB",
    "wof:placetype":"postalcode"
},
  "geometry": {"coordinates":[-3.58152817604765,55.06060302526641],"type":"Point"}
}