{
  "type": "Feature",
  "properties": {
    "iso:country": "GB",
    "wof:name": "WF10 5WD",
    "wof:placetype": "postalcode"
  },
  "geometry": {"coordinates":[-1.355385,53.710103],"type":"Point"}
}
