{
  "type": "Feature",
  "properties": {
    "iso:country":"GB",
    "wof:name":"B21 8PJ",
    "wof:placetype":"postalcode"
},
  "geometry": {"coordinates":[-1.95050751656746,52.51101223466047],"type":"Point"}
}