{
  "type": "Feature",
  "properties": {
    "iso:country":"GB",
    "wof:name":"BA3 2HB",
    "wof:placetype":"postalcode"
},
  "geometry": {"coordinates":[-2.48278481972737,51.28529249166371],"type":"Point"}
}