{
  "type": "Feature",
  "properties": {
    "iso:country":"GB",
    "wof:name":"LE16 8AN",
    "wof:placetype":"postalcode"
},
  "geometry": {"coordinates":[-0.91033737704559,52.47658276863216],"type":"Point"}
}