{
  "type": "Feature",
  "properties": {
    "iso:country":"GB",
    "wof:name":"OL7 9PY",
    "wof:placetype":"postalcode"
},
  "geometry": {"coordinates":[-2.10332155935908,53.50208586592341],"type":"Point"}
}