{
  "type": "Feature",
  "properties": {
    "date:inception_lower":"2013-07-01",
    "date:inception_upper":"2013-07-31",
    "iso:country":"GB",
    "wof:name":"AB21 0FL",
    "wof:placetype":"postalcode"
},
  "geometry": {"coordinates":[-2.194315,57.269792],"type":"Point"}
}