{
  "type": "Feature",
  "properties": {
    "iso:country":"GB",
    "wof:name":"AB21 0FL",
    "wof:placetype":"postalcode"
},
  "geometry": {"coordinates":[-2.19431508909508,57.26979216279805],"type":"Point"}
}