{
  "type": "Feature",
  "properties": {
    "iso:country": "GB",
    "wof:name": "WV14 6HZ",
    "wof:placetype": "postalcode"
  },
  "geometry": {"coordinates":[-2.066846,52.575335],"type":"Point"}
}
