{
  "type": "Feature",
  "properties": {
    "date:inception_lower": "1980-01-01",
    "date:inception_upper": "1980-01-01",
    "iso:country": "GB",
    "wof:name": "WV14 6HZ",
    "wof:placetype": "postalcode"
  },
  "geometry": {"coordinates":[-2.066846,52.575335],"type":"Point"}
}
