{
  "type": "Feature",
  "properties": {
    "iso:country":"GB",
    "wof:name":"WV14 6HZ",
    "wof:placetype":"postalcode"
},
  "geometry": {"coordinates":[-2.06684570595493,52.57533490443077],"type":"Point"}
}