{
  "type": "Feature",
  "properties": {
    "iso:country": "GB",
    "wof:name": "ME20 6GZ",
    "wof:placetype": "postalcode"
  },
  "geometry": {"coordinates":[0.445276,51.312277],"type":"Point"}
}
