{
  "type": "Feature",
  "properties": {
    "iso:country":"GB",
    "wof:name":"ME20 6GZ",
    "wof:placetype":"postalcode"
},
  "geometry": {"coordinates":[0.44527623191658,51.31227693333113],"type":"Point"}
}