{
  "type": "Feature",
  "properties": {
    "date:inception_lower": "1980-01-01",
    "date:inception_upper": "1980-01-01",
    "iso:country": "GB",
    "wof:name": "DD5 2JE",
    "wof:placetype": "postalcode"
  },
  "geometry": {"coordinates":[-2.866746,56.469342],"type":"Point"}
}
