{
  "type": "Feature",
  "properties": {
    "iso:country": "GB",
    "wof:name": "DD5 2JE",
    "wof:placetype": "postalcode"
  },
  "geometry": {"coordinates":[-2.866746,56.469342],"type":"Point"}
}
