{
  "type": "Feature",
  "properties": {
    "iso:country":"GB",
    "wof:name":"PL2 3DE",
    "wof:placetype":"postalcode"
},
  "geometry": {"coordinates":[-4.15068387045988,50.39011083330637],"type":"Point"}
}