{
  "type": "Feature",
  "properties": {
    "date:inception_lower": "1980-01-01",
    "date:inception_upper": "1980-01-01",
    "iso:country": "GB",
    "wof:name": "PL2 3DE",
    "wof:placetype": "postalcode"
  },
  "geometry": {"coordinates":[-4.154791,50.387269],"type":"Point"}
}
