{
  "type": "Feature",
  "properties": {
    "iso:country": "GB",
    "wof:name": "MK3 7HZ",
    "wof:placetype": "postalcode"
  },
  "geometry": {"coordinates":[-0.75596,51.999876],"type":"Point"}
}
