{
  "type": "Feature",
  "properties": {
    "iso:country":"GB",
    "wof:name":"MK3 7HZ",
    "wof:placetype":"postalcode"
},
  "geometry": {"coordinates":[-0.75595985241493,51.99987558310719],"type":"Point"}
}