{
  "type": "Feature",
  "properties": {
    "iso:country":"GB",
    "wof:name":"RG24 9UF",
    "wof:placetype":"postalcode"
},
  "geometry": {"coordinates":[-1.11287607746991,51.27891087033183],"type":"Point"}
}