{
  "type": "Feature",
  "properties": {
    "date:inception_lower":"2009-02-01",
    "date:inception_upper":"2009-02-28",
    "iso:country":"GB",
    "wof:name":"RG24 9UF",
    "wof:placetype":"postalcode"
},
  "geometry": {"coordinates":[-1.112876,51.278911],"type":"Point"}
}