{
  "type": "Feature",
  "properties": {
    "iso:country": "GB",
    "wof:name": "OL11 2WE",
    "wof:placetype": "postalcode"
  },
  "geometry": {"coordinates":[-2.150628,53.59962],"type":"Point"}
}
