{
  "type": "Feature",
  "properties": {
    "date:inception_lower": "2018-08-01",
    "date:inception_upper": "2018-08-01",
    "iso:country": "GB",
    "wof:name": "OL11 2WE",
    "wof:placetype": "postalcode"
  },
  "geometry": {"coordinates":[-2.150778,53.599539],"type":"Point"}
}
