{
  "type": "Feature",
  "properties": {
    "iso:country": "GB",
    "wof:name": "GU9 7HS",
    "wof:placetype": "postalcode"
  },
  "geometry": {"coordinates":[-0.79947,51.21524],"type":"Point"}
}
