{
  "type": "Feature",
  "properties": {
    "iso:country":"GB",
    "wof:name":"GU9 7HS",
    "wof:placetype":"postalcode"
},
  "geometry": {"coordinates":[-0.79947014492475,51.21523961022097],"type":"Point"}
}