{
  "type": "Feature",
  "properties": {
    "iso:country":"GB",
    "wof:name":"TN3 8DN",
    "wof:placetype":"postalcode"
},
  "geometry": {"coordinates":[0.39220298074362,51.10248268350907],"type":"Point"}
}