{
  "type": "Feature",
  "properties": {
    "date:inception_lower":"2011-12-01",
    "date:inception_upper":"2011-12-31",
    "iso:country":"GB",
    "wof:name":"BN10 8FH",
    "wof:placetype":"postalcode"
},
  "geometry": {"coordinates":[0.01753,50.791973],"type":"Point"}
}