{
  "type": "Feature",
  "properties": {
    "iso:country":"GB",
    "wof:name":"BN10 8FH",
    "wof:placetype":"postalcode"
},
  "geometry": {"coordinates":[0.01752986171938,50.79197300718685],"type":"Point"}
}