{
  "type": "Feature",
  "properties": {
    "date:inception_lower": "2018-05-01",
    "date:inception_upper": "2018-05-01",
    "iso:country": "GB",
    "wof:name": "BA11 4FL",
    "wof:placetype": "postalcode"
  },
  "geometry": {"coordinates":[-2.340499,51.227521],"type":"Point"}
}
