{
  "type": "Feature",
  "properties": {
    "iso:country": "GB",
    "wof:name": "BA11 4FL",
    "wof:placetype": "postalcode"
  },
  "geometry": {"coordinates":[-2.340371,51.227602],"type":"Point"}
}
