{
  "type": "Feature",
  "properties": {
    "iso:country":"GB",
    "wof:name":"NR6 6JP",
    "wof:placetype":"postalcode"
},
  "geometry": {"coordinates":[1.29159436231048,52.65623891766531],"type":"Point"}
}