{
  "type": "Feature",
  "properties": {
    "date:inception_lower": "1981-06-01",
    "date:inception_upper": "1981-06-01",
    "iso:country": "GB",
    "wof:name": "NR6 6JP",
    "wof:placetype": "postalcode"
  },
  "geometry": {"coordinates":[1.291594,52.656239],"type":"Point"}
}
