{
  "type": "Feature",
  "properties": {
    "iso:country":"GB",
    "wof:name":"S7 1NN",
    "wof:placetype":"postalcode"
},
  "geometry": {"coordinates":[-1.48409477829587,53.36396926810402],"type":"Point"}
}