{
  "type": "Feature",
  "properties": {
    "iso:country": "GB",
    "wof:name": "NE61 4LA",
    "wof:placetype": "postalcode"
  },
  "geometry": {"coordinates":[-1.948005,55.196589],"type":"Point"}
}
