{
  "type": "Feature",
  "properties": {
    "iso:country":"GB",
    "wof:name":"NE61 4LA",
    "wof:placetype":"postalcode"
},
  "geometry": {"coordinates":[-1.94800507721822,55.19658880310103],"type":"Point"}
}