{
  "type": "Feature",
  "properties": {
    "iso:country":"GB",
    "wof:name":"SY8 1UG",
    "wof:placetype":"postalcode"
},
  "geometry": {"coordinates":[-2.70055022928827,52.36792729968014],"type":"Point"}
}