{
  "type": "Feature",
  "properties": {
    "date:inception_lower":"1991-01-01",
    "date:inception_upper":"1991-01-31",
    "iso:country":"GB",
    "wof:name":"SY8 1UG",
    "wof:placetype":"postalcode"
},
  "geometry": {"coordinates":[-2.70055,52.367927],"type":"Point"}
}