{
  "type": "Feature",
  "properties": {
    "iso:country": "GB",
    "wof:name": "SY8 1UG",
    "wof:placetype": "postalcode"
  },
  "geometry": {"coordinates":[-2.70055,52.367927],"type":"Point"}
}
