{
  "type": "Feature",
  "properties": {
    "iso:country":"GB",
    "wof:name":"NE4 7TU",
    "wof:placetype":"postalcode"
},
  "geometry": {"coordinates":[-1.65365970649439,54.96831150758214],"type":"Point"}
}