{
  "type": "Feature",
  "properties": {
    "iso:country": "GB",
    "wof:name": "NE4 7TU",
    "wof:placetype": "postalcode"
  },
  "geometry": {"coordinates":[-1.65366,54.968312],"type":"Point"}
}
