{
  "type": "Feature",
  "properties": {
    "date:inception_lower": "1980-01-01",
    "date:inception_upper": "1980-01-01",
    "iso:country": "GB",
    "wof:name": "E11 3AP",
    "wof:placetype": "postalcode"
  },
  "geometry": {"coordinates":[0.015405,51.570195],"type":"Point"}
}
