{
  "type": "Feature",
  "properties": {
    "date:inception_lower": "2006-08-01",
    "date:inception_upper": "2006-08-01",
    "iso:country": "GB",
    "wof:name": "SA15 2LZ",
    "wof:placetype": "postalcode"
  },
  "geometry": {"coordinates":[-4.175199,51.67482],"type":"Point"}
}
