{
  "type": "Feature",
  "properties": {
    "iso:country": "GB",
    "wof:name": "SW13 9LY",
    "wof:placetype": "postalcode"
  },
  "geometry": {"coordinates":[-0.244365,51.477648],"type":"Point"}
}
