{
  "type": "Feature",
  "properties": {
    "iso:country":"GB",
    "wof:name":"CA13 0XU",
    "wof:placetype":"postalcode"
},
  "geometry": {"coordinates":[-3.43109107341176,54.67186773589417],"type":"Point"}
}