{
  "type": "Feature",
  "properties": {
    "date:inception_lower": "1980-01-01",
    "date:inception_upper": "1980-01-01",
    "iso:country": "GB",
    "wof:name": "CA13 0XU",
    "wof:placetype": "postalcode"
  },
  "geometry": {"coordinates":[-3.431434,54.671915],"type":"Point"}
}
