{
  "type": "Feature",
  "properties": {
    "iso:country":"GB",
    "wof:name":"OX17 3AX",
    "wof:placetype":"postalcode"
},
  "geometry": {"coordinates":[-1.24110667513098,51.99606936144418],"type":"Point"}
}