{
  "type": "Feature",
  "properties": {
    "date:inception_lower": "1980-01-01",
    "date:inception_upper": "1980-01-01",
    "iso:country": "GB",
    "wof:name": "OX17 3AX",
    "wof:placetype": "postalcode"
  },
  "geometry": {"coordinates":[-1.241107,51.996069],"type":"Point"}
}
