{
  "type": "Feature",
  "properties": {
    "iso:country":"GB",
    "wof:name":"CH49 3PJ",
    "wof:placetype":"postalcode"
},
  "geometry": {"coordinates":[-3.11968954241891,53.37875077665582],"type":"Point"}
}