{
  "type": "Feature",
  "properties": {
    "iso:country": "GB",
    "wof:name": "CH49 3PJ",
    "wof:placetype": "postalcode"
  },
  "geometry": {"coordinates":[-3.119689,53.378751],"type":"Point"}
}
