{
  "type": "Feature",
  "properties": {
    "iso:country": "GB",
    "wof:name": "LS14 6PX",
    "wof:placetype": "postalcode"
  },
  "geometry": {"coordinates":[-1.46168,53.823707],"type":"Point"}
}
