{
  "type": "Feature",
  "properties": {
    "iso:country":"GB",
    "wof:name":"LS14 6PX",
    "wof:placetype":"postalcode"
},
  "geometry": {"coordinates":[-1.46168032621342,53.82370688720072],"type":"Point"}
}