{
  "type": "Feature",
  "properties": {
    "iso:country":"GB",
    "wof:name":"PL7 2ZJ",
    "wof:placetype":"postalcode"
},
  "geometry": {"coordinates":[-4.02124690487851,50.38805289293659],"type":"Point"}
}