{
  "type": "Feature",
  "properties": {
    "iso:country":"GB",
    "wof:name":"BD8 7BS",
    "wof:placetype":"postalcode"
},
  "geometry": {"coordinates":[-1.76328481948312,53.80773817627705],"type":"Point"}
}