{
  "type": "Feature",
  "properties": {
    "iso:country": "GB",
    "wof:name": "BD8 7BS",
    "wof:placetype": "postalcode"
  },
  "geometry": {"coordinates":[-1.763391,53.807702],"type":"Point"}
}
