{
  "type": "Feature",
  "properties": {
    "iso:country":"GB",
    "wof:name":"BD9 4RJ",
    "wof:placetype":"postalcode"
},
  "geometry": {"coordinates":[-1.77705406417359,53.80846559024454],"type":"Point"}
}