{
  "type": "Feature",
  "properties": {
    "iso:country": "GB",
    "wof:name": "BN18 0DE",
    "wof:placetype": "postalcode"
  },
  "geometry": {"coordinates":[-0.585296,50.823774],"type":"Point"}
}
