{
  "type": "Feature",
  "properties": {
    "iso:country":"GB",
    "wof:name":"BN18 0DE",
    "wof:placetype":"postalcode"
},
  "geometry": {"coordinates":[-0.58529623300471,50.82377417982017],"type":"Point"}
}