{
  "type": "Feature",
  "properties": {
    "iso:country":"GB",
    "wof:name":"EX15 3ST",
    "wof:placetype":"postalcode"
},
  "geometry": {"coordinates":[-3.22464051414479,50.93083752236596],"type":"Point"}
}