{
  "type": "Feature",
  "properties": {
    "iso:country":"GB",
    "wof:name":"SR3 1SX",
    "wof:placetype":"postalcode"
},
  "geometry": {"coordinates":[-1.40656762667821,54.8875579519685],"type":"Point"}
}