{
  "type": "Feature",
  "properties": {
    "date:inception_lower": "1984-02-01",
    "date:inception_upper": "1984-02-01",
    "iso:country": "GB",
    "wof:name": "PE3 6LZ",
    "wof:placetype": "postalcode"
  },
  "geometry": {"coordinates":[-0.28763,52.573494],"type":"Point"}
}
