{
  "type": "Feature",
  "properties": {
    "iso:country":"GB",
    "wof:name":"PE3 6LZ",
    "wof:placetype":"postalcode"
},
  "geometry": {"coordinates":[-0.28762991702871,52.57349432386649],"type":"Point"}
}