{
  "type": "Feature",
  "properties": {
    "date:inception_lower": "1980-01-01",
    "date:inception_upper": "1980-01-01",
    "iso:country": "GB",
    "wof:name": "NE2 2AA",
    "wof:placetype": "postalcode"
  },
  "geometry": {"coordinates":[-1.604243,54.983516],"type":"Point"}
}
