{
  "type": "Feature",
  "properties": {
    "iso:country":"GB",
    "wof:name":"NE2 2AA",
    "wof:placetype":"postalcode"
},
  "geometry": {"coordinates":[-1.60420085578509,54.98321270936424],"type":"Point"}
}