{
  "type": "Feature",
  "properties": {
    "iso:country": "GB",
    "wof:name": "SY7 0JR",
    "wof:placetype": "postalcode"
  },
  "geometry": {"coordinates":[-2.878261,52.375204],"type":"Point"}
}
