{
  "type": "Feature",
  "properties": {
    "iso:country": "GB",
    "wof:name": "SP1 1HZ",
    "wof:placetype": "postalcode"
  },
  "geometry": {"coordinates":[-1.789408,51.069384],"type":"Point"}
}
