{
  "type": "Feature",
  "properties": {
    "iso:country":"GB",
    "wof:name":"SP1 1HZ",
    "wof:placetype":"postalcode"
},
  "geometry": {"coordinates":[-1.78940781595051,51.06938436227298],"type":"Point"}
}