{
  "type": "Feature",
  "properties": {
    "iso:country":"GB",
    "wof:name":"G32 8FB",
    "wof:placetype":"postalcode"
},
  "geometry": {"coordinates":[-4.17593288757638,55.8348133384677],"type":"Point"}
}