{
  "type": "Feature",
  "properties": {
    "iso:country": "GB",
    "wof:name": "PE25 2NU",
    "wof:placetype": "postalcode"
  },
  "geometry": {"coordinates":[0.324995,53.152469],"type":"Point"}
}
