{
  "type": "Feature",
  "properties": {
    "date:inception_lower": "1987-04-01",
    "date:inception_upper": "1987-04-01",
    "iso:country": "GB",
    "wof:name": "WS2 8RW",
    "wof:placetype": "postalcode"
  },
  "geometry": {"coordinates":[-2.000001,52.586366],"type":"Point"}
}
