{
  "type": "Feature",
  "properties": {
    "iso:country":"GB",
    "wof:name":"SK10 1LT",
    "wof:placetype":"postalcode"
},
  "geometry": {"coordinates":[-2.11623207978833,53.26177302627487],"type":"Point"}
}