{
  "type": "Feature",
  "properties": {
    "iso:country": "GB",
    "wof:name": "SK10 1LT",
    "wof:placetype": "postalcode"
  },
  "geometry": {"coordinates":[-2.116232,53.261773],"type":"Point"}
}
