{
  "type": "Feature",
  "properties": {
    "iso:country":"GB",
    "wof:name":"LU2 7GJ",
    "wof:placetype":"postalcode"
},
  "geometry": {"coordinates":[-0.41474426355844,51.91019583155008],"type":"Point"}
}