{
  "type": "Feature",
  "properties": {
    "iso:country":"GB",
    "wof:name":"EX34 0NG",
    "wof:placetype":"postalcode"
},
  "geometry": {"coordinates":[-4.00353615670205,51.18896645168724],"type":"Point"}
}