{
  "type": "Feature",
  "properties": {
    "iso:country": "GB",
    "wof:name": "NE29 7BN",
    "wof:placetype": "postalcode"
  },
  "geometry": {"coordinates":[-1.47048,55.006536],"type":"Point"}
}
