{
  "type": "Feature",
  "properties": {
    "iso:country":"GB",
    "wof:name":"NE29 7BN",
    "wof:placetype":"postalcode"
},
  "geometry": {"coordinates":[-1.4704802843346,55.00653606685911],"type":"Point"}
}