{
  "type": "Feature",
  "properties": {
    "iso:country": "GB",
    "wof:name": "EN6 5AJ",
    "wof:placetype": "postalcode"
  },
  "geometry": {"coordinates":[-0.177693,51.693652],"type":"Point"}
}
