{
  "type": "Feature",
  "properties": {
    "iso:country":"GB",
    "wof:name":"EN6 5AJ",
    "wof:placetype":"postalcode"
},
  "geometry": {"coordinates":[-0.17769353685564,51.69365206037692],"type":"Point"}
}