{
  "type": "Feature",
  "properties": {
    "iso:country": "GB",
    "wof:name": "SS13 2HQ",
    "wof:placetype": "postalcode"
  },
  "geometry": {"coordinates":[0.532818,51.57085],"type":"Point"}
}
