{
  "type": "Feature",
  "properties": {
    "iso:country":"GB",
    "wof:name":"SS13 2HQ",
    "wof:placetype":"postalcode"
},
  "geometry": {"coordinates":[0.53281844534996,51.5708495672899],"type":"Point"}
}