{
  "type": "Feature",
  "properties": {
    "iso:country":"GB",
    "wof:name":"ML1 3EW",
    "wof:placetype":"postalcode"
},
  "geometry": {"coordinates":[-4.0010654949574,55.78811210380184],"type":"Point"}
}