{
  "type": "Feature",
  "properties": {
    "iso:country":"GB",
    "wof:name":"TS9 5LU",
    "wof:placetype":"postalcode"
},
  "geometry": {"coordinates":[-1.23345524161186,54.48552260508066],"type":"Point"}
}