{
  "type": "Feature",
  "properties": {
    "iso:country": "GB",
    "wof:name": "TS9 5LU",
    "wof:placetype": "postalcode"
  },
  "geometry": {"coordinates":[-1.233455,54.485523],"type":"Point"}
}
