{
  "type": "Feature",
  "properties": {
    "iso:country":"GB",
    "wof:name":"WF14 9QB",
    "wof:placetype":"postalcode"
},
  "geometry": {"coordinates":[-1.71057100279188,53.68044147669298],"type":"Point"}
}