{
  "type": "Feature",
  "properties": {
    "iso:country":"GB",
    "wof:name":"EN11 0JS",
    "wof:placetype":"postalcode"
},
  "geometry": {"coordinates":[-0.00445139864602,51.76630959356123],"type":"Point"}
}