{
  "type": "Feature",
  "properties": {
    "iso:country": "GB",
    "wof:name": "EN11 0JS",
    "wof:placetype": "postalcode"
  },
  "geometry": {"coordinates":[-0.004451,51.76631],"type":"Point"}
}
