{
  "type": "Feature",
  "properties": {
    "date:inception_lower": "1996-06-01",
    "date:inception_upper": "1996-06-01",
    "iso:country": "GB",
    "wof:name": "AB21 7NR",
    "wof:placetype": "postalcode"
  },
  "geometry": {"coordinates":[-2.176655,57.207378],"type":"Point"}
}
