{
  "type": "Feature",
  "properties": {
    "iso:country":"GB",
    "wof:name":"TW8 9LY",
    "wof:placetype":"postalcode"
},
  "geometry": {"coordinates":[-0.31195823409692,51.49137321965873],"type":"Point"}
}