{
  "type": "Feature",
  "properties": {
    "iso:country": "GB",
    "wof:name": "CA12 4DD",
    "wof:placetype": "postalcode"
  },
  "geometry": {"coordinates":[-3.13365,54.597933],"type":"Point"}
}
