{
  "type": "Feature",
  "properties": {
    "iso:country":"GB",
    "wof:name":"CA12 4DD",
    "wof:placetype":"postalcode"
},
  "geometry": {"coordinates":[-3.13365026998857,54.59793275163595],"type":"Point"}
}