{
  "type": "Feature",
  "properties": {
    "date:inception_lower": "1995-01-01",
    "date:inception_upper": "1995-01-01",
    "iso:country": "GB",
    "wof:name": "CA12 4DD",
    "wof:placetype": "postalcode"
  },
  "geometry": {"coordinates":[-3.133638,54.597932],"type":"Point"}
}
