{
  "type": "Feature",
  "properties": {
    "iso:country":"GB",
    "wof:name":"LL41 4PH",
    "wof:placetype":"postalcode"
},
  "geometry": {"coordinates":[-3.93038165854055,52.96642298608717],"type":"Point"}
}