{
  "type": "Feature",
  "properties": {
    "iso:country":"GB",
    "wof:name":"DL12 9TT",
    "wof:placetype":"postalcode"
},
  "geometry": {"coordinates":[-1.81234594005193,54.513409573371],"type":"Point"}
}