{
  "type": "Feature",
  "properties": {
    "iso:country": "GB",
    "wof:name": "DL12 9TT",
    "wof:placetype": "postalcode"
  },
  "geometry": {"coordinates":[-1.811645,54.513293],"type":"Point"}
}
