{
  "type": "Feature",
  "properties": {
    "date:inception_lower":"1994-05-01",
    "date:inception_upper":"1994-05-31",
    "iso:country":"GB",
    "wof:name":"M22 8DY",
    "wof:placetype":"postalcode"
},
  "geometry": {"coordinates":[-2.260271,53.392879],"type":"Point"}
}