{
  "type": "Feature",
  "properties": {
    "iso:country":"GB",
    "wof:name":"M22 8DY",
    "wof:placetype":"postalcode"
},
  "geometry": {"coordinates":[-2.26027082709975,53.39287911075262],"type":"Point"}
}