{
  "type": "Feature",
  "properties": {
    "iso:country": "GB",
    "wof:name": "M22 8DY",
    "wof:placetype": "postalcode"
  },
  "geometry": {"coordinates":[-2.260271,53.392879],"type":"Point"}
}
