{
  "type": "Feature",
  "properties": {
    "date:inception_lower": "1980-01-01",
    "date:inception_upper": "1980-01-01",
    "iso:country": "GB",
    "wof:name": "BA7 7DW",
    "wof:placetype": "postalcode"
  },
  "geometry": {"coordinates":[-2.522098,51.089979],"type":"Point"}
}
