{
  "type": "Feature",
  "properties": {
    "iso:country":"GB",
    "wof:name":"BA7 7DW",
    "wof:placetype":"postalcode"
},
  "geometry": {"coordinates":[-2.52209796560264,51.08997875906057],"type":"Point"}
}