{
  "type": "Feature",
  "properties": {
    "iso:country":"GB",
    "wof:name":"MK44 2DA",
    "wof:placetype":"postalcode"
},
  "geometry": {"coordinates":[-0.46401496703959,52.21508155748796],"type":"Point"}
}