{
  "type": "Feature",
  "properties": {
    "iso:country":"GB",
    "wof:name":"DG7 3DJ",
    "wof:placetype":"postalcode"
},
  "geometry": {"coordinates":[-3.94595631680467,55.05662520347978],"type":"Point"}
}