{
  "type": "Feature",
  "properties": {
    "date:inception_lower": "2011-11-01",
    "date:inception_upper": "2011-11-01",
    "iso:country": "GB",
    "wof:name": "LS14 6FY",
    "wof:placetype": "postalcode"
  },
  "geometry": {"coordinates":[-1.464874,53.816288],"type":"Point"}
}
