{
  "type": "Feature",
  "properties": {
    "iso:country": "GB",
    "wof:name": "LS14 6FY",
    "wof:placetype": "postalcode"
  },
  "geometry": {"coordinates":[-1.464874,53.816288],"type":"Point"}
}
