{
  "type": "Feature",
  "properties": {
    "iso:country":"GB",
    "wof:name":"LS14 6FY",
    "wof:placetype":"postalcode"
},
  "geometry": {"coordinates":[-1.46487383021256,53.81628805867116],"type":"Point"}
}