{
  "type": "Feature",
  "properties": {
    "date:inception_lower": "1980-01-01",
    "date:inception_upper": "1980-01-01",
    "iso:country": "GB",
    "wof:name": "NP44 1BH",
    "wof:placetype": "postalcode"
  },
  "geometry": {"coordinates":[-3.035155,51.664178],"type":"Point"}
}
