{
  "type": "Feature",
  "properties": {
    "iso:country":"GB",
    "wof:name":"NP44 1BH",
    "wof:placetype":"postalcode"
},
  "geometry": {"coordinates":[-3.03515509207663,51.66417839605623],"type":"Point"}
}