{
  "type": "Feature",
  "properties": {
    "iso:country":"GB",
    "wof:name":"NE61 5BL",
    "wof:placetype":"postalcode"
},
  "geometry": {"coordinates":[-1.60390170352712,55.28780211117964],"type":"Point"}
}