{
  "type": "Feature",
  "properties": {
    "iso:country": "GB",
    "wof:name": "NE61 5BL",
    "wof:placetype": "postalcode"
  },
  "geometry": {"coordinates":[-1.604291,55.288094],"type":"Point"}
}
