{
  "type": "Feature",
  "properties": {
    "date:inception_lower": "2015-12-01",
    "date:inception_upper": "2015-12-01",
    "iso:country": "GB",
    "wof:name": "NE61 5BL",
    "wof:placetype": "postalcode"
  },
  "geometry": {"coordinates":[-1.604291,55.288094],"type":"Point"}
}
