{
  "type": "Feature",
  "properties": {
    "iso:country":"GB",
    "wof:name":"EH47 7RJ",
    "wof:placetype":"postalcode"
},
  "geometry": {"coordinates":[-3.65137701755656,55.8653241289834],"type":"Point"}
}