{
  "type": "Feature",
  "properties": {
    "iso:country":"GB",
    "wof:name":"EX36 3WX",
    "wof:placetype":"postalcode"
},
  "geometry": {"coordinates":[-3.835183734831,51.01765098532824],"type":"Point"}
}