{
  "type": "Feature",
  "properties": {
    "iso:country":"GB",
    "wof:name":"CA14 4JA",
    "wof:placetype":"postalcode"
},
  "geometry": {"coordinates":[-3.5296767799429,54.63689593557363],"type":"Point"}
}