{
  "type": "Feature",
  "properties": {
    "iso:country":"GB",
    "wof:name":"NG16 5HN",
    "wof:placetype":"postalcode"
},
  "geometry": {"coordinates":[-1.32621707003485,53.06518804478755],"type":"Point"}
}