{
  "type": "Feature",
  "properties": {
    "date:inception_lower":"1992-08-01",
    "date:inception_upper":"1992-08-31",
    "iso:country":"GB",
    "wof:name":"DE23 8TU",
    "wof:placetype":"postalcode"
},
  "geometry": {"coordinates":[-1.486111,52.901248],"type":"Point"}
}