{
  "type": "Feature",
  "properties": {
    "iso:country": "GB",
    "wof:name": "NR35 1HH",
    "wof:placetype": "postalcode"
  },
  "geometry": {"coordinates":[1.440408,52.455547],"type":"Point"}
}
