{
  "type": "Feature",
  "properties": {
    "iso:country":"GB",
    "wof:name":"DN7 5BP",
    "wof:placetype":"postalcode"
},
  "geometry": {"coordinates":[-1.01240698344885,53.59983256660524],"type":"Point"}
}