{
  "type": "Feature",
  "properties": {
    "date:inception_lower": "1980-01-01",
    "date:inception_upper": "1980-01-01",
    "iso:country": "GB",
    "wof:name": "NE46 4QA",
    "wof:placetype": "postalcode"
  },
  "geometry": {"coordinates":[-2.113634,54.99231],"type":"Point"}
}
