{
  "type": "Feature",
  "properties": {
    "iso:country":"GB",
    "wof:name":"NE46 4QA",
    "wof:placetype":"postalcode"
},
  "geometry": {"coordinates":[-2.1138443477497,54.99233011367938],"type":"Point"}
}