{
  "type": "Feature",
  "properties": {
    "date:inception_lower":"2001-12-01",
    "date:inception_upper":"2001-12-31",
    "iso:country":"GB",
    "wof:name":"LL19 8YJ",
    "wof:placetype":"postalcode"
},
  "geometry": {"coordinates":[-3.425965,53.326582],"type":"Point"}
}