{
  "type": "Feature",
  "properties": {
    "iso:country":"GB",
    "wof:name":"LL19 8YJ",
    "wof:placetype":"postalcode"
},
  "geometry": {"coordinates":[-3.42596479167526,53.32658171623787],"type":"Point"}
}