{
  "type": "Feature",
  "properties": {
    "iso:country": "GB",
    "wof:name": "LL19 8YJ",
    "wof:placetype": "postalcode"
  },
  "geometry": {"coordinates":[-3.425965,53.326582],"type":"Point"}
}
