{
  "type": "Feature",
  "properties": {
    "date:inception_lower": "2014-06-01",
    "date:inception_upper": "2014-06-01",
    "iso:country": "GB",
    "wof:name": "S6 6GD",
    "wof:placetype": "postalcode"
  },
  "geometry": {"coordinates":[-1.595947,53.380903],"type":"Point"}
}
