{
  "type": "Feature",
  "properties": {
    "iso:country": "GB",
    "wof:name": "S6 6GD",
    "wof:placetype": "postalcode"
  },
  "geometry": {"coordinates":[-1.595646,53.380902],"type":"Point"}
}
