{
  "type": "Feature",
  "properties": {
    "date:inception_lower":"2016-12-01",
    "date:inception_upper":"2016-12-31",
    "iso:country":"GB",
    "wof:name":"HP5 1DU",
    "wof:placetype":"postalcode"
},
  "geometry": {"coordinates":[-0.610406,51.707342],"type":"Point"}
}