{
  "type": "Feature",
  "properties": {
    "date:inception_lower": "1980-01-01",
    "date:inception_upper": "1980-01-01",
    "iso:country": "GB",
    "wof:name": "S70 4BG",
    "wof:placetype": "postalcode"
  },
  "geometry": {"coordinates":[-1.459361,53.53601],"type":"Point"}
}
