{
  "type": "Feature",
  "properties": {
    "iso:country":"GB",
    "wof:name":"SN5 6EB",
    "wof:placetype":"postalcode"
},
  "geometry": {"coordinates":[-1.8412078992646,51.55456263463763],"type":"Point"}
}