{
  "type": "Feature",
  "properties": {
    "iso:country": "GB",
    "wof:name": "SN5 6EB",
    "wof:placetype": "postalcode"
  },
  "geometry": {"coordinates":[-1.841208,51.554563],"type":"Point"}
}
