{
  "type": "Feature",
  "properties": {
    "iso:country": "GB",
    "wof:name": "CO4 5BX",
    "wof:placetype": "postalcode"
  },
  "geometry": {"coordinates":[0.894989,51.902848],"type":"Point"}
}
