{
  "type": "Feature",
  "properties": {
    "iso:country":"GB",
    "wof:name":"CO4 5BX",
    "wof:placetype":"postalcode"
},
  "geometry": {"coordinates":[0.8949889299249,51.90284769582686],"type":"Point"}
}