{
  "type": "Feature",
  "properties": {
    "iso:country":"GB",
    "wof:name":"SW6 2NP",
    "wof:placetype":"postalcode"
},
  "geometry": {"coordinates":[-0.1900820751697,51.47053644970954],"type":"Point"}
}