{
  "type": "Feature",
  "properties": {
    "iso:country":"GB",
    "wof:name":"CO15 6HE",
    "wof:placetype":"postalcode"
},
  "geometry": {"coordinates":[1.16911131533997,51.79782416599688],"type":"Point"}
}