{
  "type": "Feature",
  "properties": {
    "iso:country":"GB",
    "wof:name":"CW5 5HU",
    "wof:placetype":"postalcode"
},
  "geometry": {"coordinates":[-2.53176873563462,53.06406197812485],"type":"Point"}
}