{
  "type": "Feature",
  "properties": {
    "iso:country":"GB",
    "wof:name":"LN5 0RJ",
    "wof:placetype":"postalcode"
},
  "geometry": {"coordinates":[-0.69168156794762,53.07414385751915],"type":"Point"}
}