{
  "type": "Feature",
  "properties": {
    "iso:country": "GB",
    "wof:name": "LN5 0RJ",
    "wof:placetype": "postalcode"
  },
  "geometry": {"coordinates":[-0.691682,53.074144],"type":"Point"}
}
