{
  "type": "Feature",
  "properties": {
    "iso:country": "GB",
    "wof:name": "SY10 7UF",
    "wof:placetype": "postalcode"
  },
  "geometry": {"coordinates":[-3.031833,52.900877],"type":"Point"}
}
