{
  "type": "Feature",
  "properties": {
    "iso:country":"GB",
    "wof:name":"SY10 7UF",
    "wof:placetype":"postalcode"
},
  "geometry": {"coordinates":[-3.03183277295948,52.90087731877797],"type":"Point"}
}