{
  "type": "Feature",
  "properties": {
    "date:inception_lower":"1981-09-01",
    "date:inception_upper":"1981-09-30",
    "iso:country":"GB",
    "wof:name":"SY10 7UF",
    "wof:placetype":"postalcode"
},
  "geometry": {"coordinates":[-3.031833,52.900877],"type":"Point"}
}