{
  "type": "Feature",
  "properties": {
    "iso:country":"GB",
    "wof:name":"NN6 9PT",
    "wof:placetype":"postalcode"
},
  "geometry": {"coordinates":[-0.82806746890119,52.34265555321145],"type":"Point"}
}