{
  "type": "Feature",
  "properties": {
    "date:inception_lower":"2006-08-01",
    "date:inception_upper":"2006-08-31",
    "iso:country":"GB",
    "wof:name":"NN6 9PT",
    "wof:placetype":"postalcode"
},
  "geometry": {"coordinates":[-0.828052,52.342669],"type":"Point"}
}