{
  "type": "Feature",
  "properties": {
    "iso:country":"GB",
    "wof:name":"BN3 7FJ",
    "wof:placetype":"postalcode"
},
  "geometry": {"coordinates":[-0.19900935022999,50.84066456528927],"type":"Point"}
}