{
  "type": "Feature",
  "properties": {
    "iso:country": "GB",
    "wof:name": "BN3 7FJ",
    "wof:placetype": "postalcode"
  },
  "geometry": {"coordinates":[-0.199009,50.840665],"type":"Point"}
}
