{
  "type": "Feature",
  "properties": {
    "iso:country":"GB",
    "wof:name":"B8 1DZ",
    "wof:placetype":"postalcode"
},
  "geometry": {"coordinates":[-1.86091905205456,52.48387235894667],"type":"Point"}
}