{
  "type": "Feature",
  "properties": {
    "iso:country":"GB",
    "wof:name":"SA62 3LS",
    "wof:placetype":"postalcode"
},
  "geometry": {"coordinates":[-5.02338072600078,51.79807142764921],"type":"Point"}
}