{
  "type": "Feature",
  "properties": {
    "iso:country": "GB",
    "wof:name": "SA62 3LS",
    "wof:placetype": "postalcode"
  },
  "geometry": {"coordinates":[-5.023381,51.798071],"type":"Point"}
}
