{
  "type": "Feature",
  "properties": {
    "date:inception_lower": "1980-01-01",
    "date:inception_upper": "1980-01-01",
    "iso:country": "GB",
    "wof:name": "PO16 9TQ",
    "wof:placetype": "postalcode"
  },
  "geometry": {"coordinates":[-1.140916,50.848],"type":"Point"}
}
