{
  "type": "Feature",
  "properties": {
    "iso:country": "GB",
    "wof:name": "BA9 9QQ",
    "wof:placetype": "postalcode"
  },
  "geometry": {"coordinates":[-2.348036,51.03394],"type":"Point"}
}
