{
  "type": "Feature",
  "properties": {
    "iso:country":"GB",
    "wof:name":"BA9 9QQ",
    "wof:placetype":"postalcode"
},
  "geometry": {"coordinates":[-2.34803649034299,51.03394018464117],"type":"Point"}
}