{
  "type": "Feature",
  "properties": {
    "iso:country":"GB",
    "wof:name":"BB1 8HL",
    "wof:placetype":"postalcode"
},
  "geometry": {"coordinates":[-2.47923294433861,53.75891764541799],"type":"Point"}
}