{
  "type": "Feature",
  "properties": {
    "iso:country": "GB",
    "wof:name": "EN9 1EX",
    "wof:placetype": "postalcode"
  },
  "geometry": {"coordinates":[-0.002341,51.687082],"type":"Point"}
}
