{
  "type": "Feature",
  "properties": {
    "iso:country":"GB",
    "wof:name":"OL16 2QY",
    "wof:placetype":"postalcode"
},
  "geometry": {"coordinates":[-2.12841847141272,53.63493564870834],"type":"Point"}
}