{
  "type": "Feature",
  "properties": {
    "date:inception_lower":"2000-06-01",
    "date:inception_upper":"2000-06-30",
    "iso:country":"GB",
    "wof:name":"OL16 2QY",
    "wof:placetype":"postalcode"
},
  "geometry": {"coordinates":[-2.128418,53.634936],"type":"Point"}
}