{
  "type": "Feature",
  "properties": {
    "date:inception_lower":"1980-01-01",
    "date:inception_upper":"1980-01-31",
    "iso:country":"GB",
    "wof:name":"SN15 1AT",
    "wof:placetype":"postalcode"
},
  "geometry": {"coordinates":[-2.117115,51.471449],"type":"Point"}
}