{
  "type": "Feature",
  "properties": {
    "iso:country":"GB",
    "wof:name":"SN15 1AT",
    "wof:placetype":"postalcode"
},
  "geometry": {"coordinates":[-2.11711542010747,51.47144910255647],"type":"Point"}
}