{
  "type": "Feature",
  "properties": {
    "iso:country": "GB",
    "wof:name": "PL6 8DL",
    "wof:placetype": "postalcode"
  },
  "geometry": {"coordinates":[-4.115932,50.420394],"type":"Point"}
}
