{
  "type": "Feature",
  "properties": {
    "date:inception_lower": "2012-09-01",
    "date:inception_upper": "2012-09-01",
    "iso:country": "GB",
    "wof:name": "PL6 8DL",
    "wof:placetype": "postalcode"
  },
  "geometry": {"coordinates":[-4.115932,50.420394],"type":"Point"}
}
