{
  "type": "Feature",
  "properties": {
    "iso:country": "GB",
    "wof:name": "BS31 2DL",
    "wof:placetype": "postalcode"
  },
  "geometry": {"coordinates":[-2.50384,51.415306],"type":"Point"}
}
