{
  "type": "Feature",
  "properties": {
    "date:inception_lower": "1980-01-01",
    "date:inception_upper": "1980-01-01",
    "iso:country": "GB",
    "wof:name": "L30 8RY",
    "wof:placetype": "postalcode"
  },
  "geometry": {"coordinates":[-2.951667,53.488597],"type":"Point"}
}
