{
  "type": "Feature",
  "properties": {
    "date:inception_lower": "1995-12-01",
    "date:inception_upper": "1995-12-01",
    "iso:country": "GB",
    "wof:name": "TF10 7RY",
    "wof:placetype": "postalcode"
  },
  "geometry": {"coordinates":[-2.368316,52.770918],"type":"Point"}
}
