{
  "type": "Feature",
  "properties": {
    "iso:country": "GB",
    "wof:name": "TF10 7RY",
    "wof:placetype": "postalcode"
  },
  "geometry": {"coordinates":[-2.368316,52.770918],"type":"Point"}
}
