{
  "type": "Feature",
  "properties": {
    "iso:country":"GB",
    "wof:name":"TF10 7RY",
    "wof:placetype":"postalcode"
},
  "geometry": {"coordinates":[-2.36831605193491,52.77091787416427],"type":"Point"}
}