{
  "type": "Feature",
  "properties": {
    "iso:country": "GB",
    "wof:name": "EH12 9FX",
    "wof:placetype": "postalcode"
  },
  "geometry": {"coordinates":[-3.308521,55.928277],"type":"Point"}
}
