{
  "type": "Feature",
  "properties": {
    "date:inception_lower":"2012-02-01",
    "date:inception_upper":"2012-02-29",
    "iso:country":"GB",
    "wof:name":"EH12 9FX",
    "wof:placetype":"postalcode"
},
  "geometry": {"coordinates":[-3.308521,55.928277],"type":"Point"}
}