{
  "type": "Feature",
  "properties": {
    "iso:country":"GB",
    "wof:name":"EH12 9FX",
    "wof:placetype":"postalcode"
},
  "geometry": {"coordinates":[-3.30852090000928,55.92827704624449],"type":"Point"}
}