{
  "type": "Feature",
  "properties": {
    "iso:country":"GB",
    "wof:name":"TQ9 7UX",
    "wof:placetype":"postalcode"
},
  "geometry": {"coordinates":[-3.66173961867432,50.40127438474892],"type":"Point"}
}