{
  "type": "Feature",
  "properties": {
    "iso:country": "GB",
    "wof:name": "PE23 5HU",
    "wof:placetype": "postalcode"
  },
  "geometry": {"coordinates":[0.089772,53.173228],"type":"Point"}
}
