{
  "type": "Feature",
  "properties": {
    "iso:country":"GB",
    "wof:name":"PE23 5HU",
    "wof:placetype":"postalcode"
},
  "geometry": {"coordinates":[0.08976963799366,53.17322846750783],"type":"Point"}
}