{
  "type": "Feature",
  "properties": {
    "iso:country":"GB",
    "wof:name":"PO7 6PX",
    "wof:placetype":"postalcode"
},
  "geometry": {"coordinates":[-1.0578801077782,50.90063168443435],"type":"Point"}
}