{
  "type": "Feature",
  "properties": {
    "iso:country": "GB",
    "wof:name": "PO7 6PX",
    "wof:placetype": "postalcode"
  },
  "geometry": {"coordinates":[-1.05788,50.900632],"type":"Point"}
}
