{
  "type": "Feature",
  "properties": {
    "iso:country":"GB",
    "wof:name":"CB8 8RR",
    "wof:placetype":"postalcode"
},
  "geometry": {"coordinates":[0.52035772887158,52.26332817691804],"type":"Point"}
}