{
  "type": "Feature",
  "properties": {
    "date:inception_lower": "1980-01-01",
    "date:inception_upper": "1980-01-01",
    "iso:country": "GB",
    "wof:name": "CB8 8RR",
    "wof:placetype": "postalcode"
  },
  "geometry": {"coordinates":[0.520402,52.263371],"type":"Point"}
}
