{
  "type": "Feature",
  "properties": {
    "iso:country":"GB",
    "wof:name":"G84 8LS",
    "wof:placetype":"postalcode"
},
  "geometry": {"coordinates":[-4.77983135819815,56.02125684942046],"type":"Point"}
}