{
  "type": "Feature",
  "properties": {
    "iso:country": "GB",
    "wof:name": "G84 8LS",
    "wof:placetype": "postalcode"
  },
  "geometry": {"coordinates":[-4.779831,56.021257],"type":"Point"}
}
