{
  "type": "Feature",
  "properties": {
    "iso:country": "GB",
    "wof:name": "PE15 8FN",
    "wof:placetype": "postalcode"
  },
  "geometry": {"coordinates":[0.07335,52.555846],"type":"Point"}
}
