{
  "type": "Feature",
  "properties": {
    "iso:country":"GB",
    "wof:name":"IP13 9PG",
    "wof:placetype":"postalcode"
},
  "geometry": {"coordinates":[1.4088808040074,52.22863197399484],"type":"Point"}
}