{
  "type": "Feature",
  "properties": {
    "iso:country":"GB",
    "wof:name":"B13 9XR",
    "wof:placetype":"postalcode"
},
  "geometry": {"coordinates":[-1.87169778615322,52.44337562514542],"type":"Point"}
}