{
  "type": "Feature",
  "properties": {
    "iso:country":"GB",
    "wof:name":"DN4 0AE",
    "wof:placetype":"postalcode"
},
  "geometry": {"coordinates":[-1.14185102035113,53.51917805394424],"type":"Point"}
}