{
  "type": "Feature",
  "properties": {
    "iso:country": "GB",
    "wof:name": "M11 4QU",
    "wof:placetype": "postalcode"
  },
  "geometry": {"coordinates":[-2.173023,53.481341],"type":"Point"}
}
