{
  "type": "Feature",
  "properties": {
    "date:inception_lower": "1983-07-01",
    "date:inception_upper": "1983-07-01",
    "iso:country": "GB",
    "wof:name": "M11 4QU",
    "wof:placetype": "postalcode"
  },
  "geometry": {"coordinates":[-2.173023,53.481341],"type":"Point"}
}
