{
  "type": "Feature",
  "properties": {
    "iso:country":"GB",
    "wof:name":"M11 4QU",
    "wof:placetype":"postalcode"
},
  "geometry": {"coordinates":[-2.17302318061998,53.48134074977992],"type":"Point"}
}