{
  "type": "Feature",
  "properties": {
    "iso:country": "GB",
    "wof:name": "SW8 2SR",
    "wof:placetype": "postalcode"
  },
  "geometry": {"coordinates":[-0.127225,51.480556],"type":"Point"}
}
