{
  "type": "Feature",
  "properties": {
    "iso:country":"GB",
    "wof:name":"PE30 2BD",
    "wof:placetype":"postalcode"
},
  "geometry": {"coordinates":[0.40344400308173,52.76087295319963],"type":"Point"}
}