{
  "type": "Feature",
  "properties": {
    "iso:country": "GB",
    "wof:name": "BB2 3TN",
    "wof:placetype": "postalcode"
  },
  "geometry": {"coordinates":[-2.468343,53.731745],"type":"Point"}
}
