{
  "type": "Feature",
  "properties": {
    "iso:country":"GB",
    "wof:name":"OX7 3DS",
    "wof:placetype":"postalcode"
},
  "geometry": {"coordinates":[-1.48603599802251,51.87475659193069],"type":"Point"}
}