{
  "type": "Feature",
  "properties": {
    "iso:country": "GB",
    "wof:name": "OX7 3DS",
    "wof:placetype": "postalcode"
  },
  "geometry": {"coordinates":[-1.486036,51.874757],"type":"Point"}
}
