{
  "type": "Feature",
  "properties": {
    "date:inception_lower":"2011-09-01",
    "date:inception_upper":"2011-09-30",
    "iso:country":"GB",
    "wof:name":"OX7 3DS",
    "wof:placetype":"postalcode"
},
  "geometry": {"coordinates":[-1.486036,51.874757],"type":"Point"}
}