{
  "type": "Feature",
  "properties": {
    "date:inception_lower":"1980-01-01",
    "date:inception_upper":"1980-01-31",
    "iso:country":"GB",
    "wof:name":"B4 7XH",
    "wof:placetype":"postalcode"
},
  "geometry": {"coordinates":[-1.878066,52.479806],"type":"Point"}
}