{
  "type": "Feature",
  "properties": {
    "date:inception_lower": "1980-01-01",
    "date:inception_upper": "1980-01-01",
    "iso:country": "GB",
    "wof:name": "B4 7XH",
    "wof:placetype": "postalcode"
  },
  "geometry": {"coordinates":[-1.878447,52.480481],"type":"Point"}
}
