{
  "type": "Feature",
  "properties": {
    "iso:country": "GB",
    "wof:name": "B4 7XH",
    "wof:placetype": "postalcode"
  },
  "geometry": {"coordinates":[-1.878066,52.479806],"type":"Point"}
}
