{
  "type": "Feature",
  "properties": {
    "iso:country":"GB",
    "wof:name":"WF17 7AX",
    "wof:placetype":"postalcode"
},
  "geometry": {"coordinates":[-1.64596611304057,53.70626185468684],"type":"Point"}
}