{
  "type": "Feature",
  "properties": {
    "date:inception_lower": "2005-05-01",
    "date:inception_upper": "2005-05-01",
    "iso:country": "GB",
    "wof:name": "ML4 3GG",
    "wof:placetype": "postalcode"
  },
  "geometry": {"coordinates":[-4.027874,55.831305],"type":"Point"}
}
