{
  "type": "Feature",
  "properties": {
    "iso:country":"GB",
    "wof:name":"PO16 0RB",
    "wof:placetype":"postalcode"
},
  "geometry": {"coordinates":[-1.1795917038709,50.84578692850413],"type":"Point"}
}