{
  "type": "Feature",
  "properties": {
    "date:inception_lower": "1990-02-01",
    "date:inception_upper": "1990-02-01",
    "iso:country": "GB",
    "wof:name": "PO16 0RB",
    "wof:placetype": "postalcode"
  },
  "geometry": {"coordinates":[-1.179592,50.845787],"type":"Point"}
}
