{
  "type": "Feature",
  "properties": {
    "iso:country":"GB",
    "wof:name":"W1T 2BH",
    "wof:placetype":"postalcode"
},
  "geometry": {"coordinates":[-0.13468072818329,51.5194868175842],"type":"Point"}
}