{
  "type": "Feature",
  "properties": {
    "iso:country": "GB",
    "wof:name": "PE11 2BA",
    "wof:placetype": "postalcode"
  },
  "geometry": {"coordinates":[-0.141384,52.794185],"type":"Point"}
}
