{
  "type": "Feature",
  "properties": {
    "iso:country":"GB",
    "wof:name":"PE11 2BA",
    "wof:placetype":"postalcode"
},
  "geometry": {"coordinates":[-0.14133306645536,52.79423539314894],"type":"Point"}
}