{
  "type": "Feature",
  "properties": {
    "date:inception_lower":"1980-01-01",
    "date:inception_upper":"1980-01-31",
    "iso:country":"GB",
    "wof:name":"ME15 9AS",
    "wof:placetype":"postalcode"
},
  "geometry": {"coordinates":[0.539863,51.248944],"type":"Point"}
}