{
  "type": "Feature",
  "properties": {
    "iso:country": "GB",
    "wof:name": "ME15 9AS",
    "wof:placetype": "postalcode"
  },
  "geometry": {"coordinates":[0.539863,51.248944],"type":"Point"}
}
