{
  "type": "Feature",
  "properties": {
    "iso:country":"GB",
    "wof:name":"LA4 4JA",
    "wof:placetype":"postalcode"
},
  "geometry": {"coordinates":[-2.87613281825814,54.06640309617749],"type":"Point"}
}