{
  "type": "Feature",
  "properties": {
    "iso:country":"GB",
    "wof:name":"OX10 9QR",
    "wof:placetype":"postalcode"
},
  "geometry": {"coordinates":[-1.14903320781318,51.5717812682029],"type":"Point"}
}