{
  "type": "Feature",
  "properties": {
    "iso:country":"GB",
    "wof:name":"TQ13 0GA",
    "wof:placetype":"postalcode"
},
  "geometry": {"coordinates":[-3.59482395340706,50.60744682522186],"type":"Point"}
}