{
  "type": "Feature",
  "properties": {
    "iso:country": "GB",
    "wof:name": "TQ13 0GA",
    "wof:placetype": "postalcode"
  },
  "geometry": {"coordinates":[-3.594824,50.607447],"type":"Point"}
}
