{
  "type": "Feature",
  "properties": {
    "iso:country": "GB",
    "wof:name": "DG8 0LB",
    "wof:placetype": "postalcode"
  },
  "geometry": {"coordinates":[-4.760181,54.858018],"type":"Point"}
}
