{
  "type": "Feature",
  "properties": {
    "iso:country":"GB",
    "wof:name":"DL16 6NT",
    "wof:placetype":"postalcode"
},
  "geometry": {"coordinates":[-1.5955927931651,54.69942777746888],"type":"Point"}
}