{
  "type": "Feature",
  "properties": {
    "date:inception_lower":"1994-12-01",
    "date:inception_upper":"1994-12-31",
    "iso:country":"GB",
    "wof:name":"HU19 2ES",
    "wof:placetype":"postalcode"
},
  "geometry": {"coordinates":[0.021858,53.729746],"type":"Point"}
}