{
  "type": "Feature",
  "properties": {
    "iso:country":"GB",
    "wof:name":"HU19 2ES",
    "wof:placetype":"postalcode"
},
  "geometry": {"coordinates":[0.02185800502079,53.7297463159293],"type":"Point"}
}