{
  "type": "Feature",
  "properties": {
    "iso:country":"GB",
    "wof:name":"BN24 6SJ",
    "wof:placetype":"postalcode"
},
  "geometry": {"coordinates":[0.36834918510189,50.82111834101337],"type":"Point"}
}