{
  "type": "Feature",
  "properties": {
    "iso:country":"GB",
    "wof:name":"PO8 9QS",
    "wof:placetype":"postalcode"
},
  "geometry": {"coordinates":[-1.01971214718289,50.90669330702506],"type":"Point"}
}