{
  "type": "Feature",
  "properties": {
    "iso:country":"GB",
    "wof:name":"IG11 8LD",
    "wof:placetype":"postalcode"
},
  "geometry": {"coordinates":[0.07272552870457,51.54265934956636],"type":"Point"}
}