{
  "type": "Feature",
  "properties": {
    "date:inception_lower":"1985-04-01",
    "date:inception_upper":"1985-04-30",
    "iso:country":"GB",
    "wof:name":"IG11 8LD",
    "wof:placetype":"postalcode"
},
  "geometry": {"coordinates":[0.072726,51.542659],"type":"Point"}
}