{
  "type": "Feature",
  "properties": {
    "iso:country":"GB",
    "wof:name":"CR2 9AT",
    "wof:placetype":"postalcode"
},
  "geometry": {"coordinates":[-0.07246481734402,51.33364481663252],"type":"Point"}
}