{
  "type": "Feature",
  "properties": {
    "iso:country":"GB",
    "wof:name":"EN3 5UZ",
    "wof:placetype":"postalcode"
},
  "geometry": {"coordinates":[-0.03952856815398,51.66645540494401],"type":"Point"}
}