{
  "type": "Feature",
  "properties": {
    "iso:country": "GB",
    "wof:name": "EN3 5UZ",
    "wof:placetype": "postalcode"
  },
  "geometry": {"coordinates":[-0.039529,51.666455],"type":"Point"}
}
