{
  "type": "Feature",
  "properties": {
    "iso:country": "GB",
    "wof:name": "CW2 6LF",
    "wof:placetype": "postalcode"
  },
  "geometry": {"coordinates":[-2.443811,53.085502],"type":"Point"}
}
