{
  "type": "Feature",
  "properties": {
    "date:inception_lower":"2000-12-01",
    "date:inception_upper":"2000-12-31",
    "iso:country":"GB",
    "wof:name":"CW2 6LF",
    "wof:placetype":"postalcode"
},
  "geometry": {"coordinates":[-2.443811,53.085502],"type":"Point"}
}