{
  "type": "Feature",
  "properties": {
    "iso:country":"GB",
    "wof:name":"CW2 6LF",
    "wof:placetype":"postalcode"
},
  "geometry": {"coordinates":[-2.44381142949585,53.08550223151801],"type":"Point"}
}