{
  "type": "Feature",
  "properties": {
    "iso:country":"GB",
    "wof:name":"NN4 6JG",
    "wof:placetype":"postalcode"
},
  "geometry": {"coordinates":[-0.89059240161082,52.20736473502249],"type":"Point"}
}