{
  "type": "Feature",
  "properties": {
    "iso:country": "GB",
    "wof:name": "NN4 6JG",
    "wof:placetype": "postalcode"
  },
  "geometry": {"coordinates":[-0.890608,52.207334],"type":"Point"}
}
