{
  "type": "Feature",
  "properties": {
    "date:inception_lower":"2001-06-01",
    "date:inception_upper":"2001-06-30",
    "iso:country":"GB",
    "wof:name":"NN4 6JG",
    "wof:placetype":"postalcode"
},
  "geometry": {"coordinates":[-0.890608,52.207334],"type":"Point"}
}