{
  "type": "Feature",
  "properties": {
    "iso:country":"GB",
    "wof:name":"NR13 4NZ",
    "wof:placetype":"postalcode"
},
  "geometry": {"coordinates":[1.48368737139262,52.62184398561935],"type":"Point"}
}