{
  "type": "Feature",
  "properties": {
    "iso:country": "GB",
    "wof:name": "NR13 4NZ",
    "wof:placetype": "postalcode"
  },
  "geometry": {"coordinates":[1.483687,52.621844],"type":"Point"}
}
