{
  "type": "Feature",
  "properties": {
    "iso:country":"GB",
    "wof:name":"SP6 3EE",
    "wof:placetype":"postalcode"
},
  "geometry": {"coordinates":[-1.86187785881936,50.9214978460504],"type":"Point"}
}