{
  "type": "Feature",
  "properties": {
    "iso:country": "GB",
    "wof:name": "SP6 3EE",
    "wof:placetype": "postalcode"
  },
  "geometry": {"coordinates":[-1.861878,50.921498],"type":"Point"}
}
