{
  "type": "Feature",
  "properties": {
    "iso:country": "GB",
    "wof:name": "S63 9NL",
    "wof:placetype": "postalcode"
  },
  "geometry": {"coordinates":[-1.301505,53.531588],"type":"Point"}
}
