{
  "type": "Feature",
  "properties": {
    "iso:country":"GB",
    "wof:name":"AL3 4QE",
    "wof:placetype":"postalcode"
},
  "geometry": {"coordinates":[-0.34430053887412,51.75283090463433],"type":"Point"}
}