{
  "type": "Feature",
  "properties": {
    "date:inception_lower":"2004-01-01",
    "date:inception_upper":"2004-01-31",
    "iso:country":"GB",
    "wof:name":"YO12 4LQ",
    "wof:placetype":"postalcode"
},
  "geometry": {"coordinates":[-0.42811,54.236698],"type":"Point"}
}