{
  "type": "Feature",
  "properties": {
    "date:inception_lower":"1980-01-01",
    "date:inception_upper":"1980-01-31",
    "iso:country":"GB",
    "wof:name":"RM14 2JB",
    "wof:placetype":"postalcode"
},
  "geometry": {"coordinates":[0.234582,51.548844],"type":"Point"}
}