{
  "type": "Feature",
  "properties": {
    "iso:country":"GB",
    "wof:name":"DD8 3RR",
    "wof:placetype":"postalcode"
},
  "geometry": {"coordinates":[-2.896003109339,56.66252991321969],"type":"Point"}
}