{
  "type": "Feature",
  "properties": {
    "iso:country": "GB",
    "wof:name": "DD8 3RR",
    "wof:placetype": "postalcode"
  },
  "geometry": {"coordinates":[-2.896003,56.66253],"type":"Point"}
}
