{
  "type": "Feature",
  "properties": {
    "iso:country":"GB",
    "wof:name":"TW9 4QJ",
    "wof:placetype":"postalcode"
},
  "geometry": {"coordinates":[-0.28270805327954,51.46705574856418],"type":"Point"}
}