{
  "type": "Feature",
  "properties": {
    "iso:country":"GB",
    "wof:name":"DY6 0LL",
    "wof:placetype":"postalcode"
},
  "geometry": {"coordinates":[-2.18305374990568,52.50558543283348],"type":"Point"}
}