{
  "type": "Feature",
  "properties": {
    "iso:country": "GB",
    "wof:name": "L39 0EG",
    "wof:placetype": "postalcode"
  },
  "geometry": {"coordinates":[-2.849073,53.53603],"type":"Point"}
}
