{
  "type": "Feature",
  "properties": {
    "iso:country":"GB",
    "wof:name":"SA10 7BB",
    "wof:placetype":"postalcode"
},
  "geometry": {"coordinates":[-3.80800503708587,51.67374931684409],"type":"Point"}
}