{
  "type": "Feature",
  "properties": {
    "date:inception_lower": "1985-05-01",
    "date:inception_upper": "1985-05-01",
    "iso:country": "GB",
    "wof:name": "ML8 5LA",
    "wof:placetype": "postalcode"
  },
  "geometry": {"coordinates":[-3.878589,55.744392],"type":"Point"}
}
