{
  "type": "Feature",
  "properties": {
    "iso:country":"GB",
    "wof:name":"DD11 1QY",
    "wof:placetype":"postalcode"
},
  "geometry": {"coordinates":[-2.59018455065702,56.55750902109227],"type":"Point"}
}