{
  "type": "Feature",
  "properties": {
    "iso:country": "GB",
    "wof:name": "TS17 8EU",
    "wof:placetype": "postalcode"
  },
  "geometry": {"coordinates":[-1.287372,54.548537],"type":"Point"}
}
