{
  "type": "Feature",
  "properties": {
    "iso:country":"GB",
    "wof:name":"W7 3QF",
    "wof:placetype":"postalcode"
},
  "geometry": {"coordinates":[-0.33042147492212,51.50921750155121],"type":"Point"}
}