{
  "type": "Feature",
  "properties": {
    "date:inception_lower": "1997-06-01",
    "date:inception_upper": "1997-06-01",
    "iso:country": "GB",
    "wof:name": "ML3 7QB",
    "wof:placetype": "postalcode"
  },
  "geometry": {"coordinates":[-4.032183,55.738088],"type":"Point"}
}
