{
  "type": "Feature",
  "properties": {
    "iso:country":"GB",
    "wof:name":"ML3 7QB",
    "wof:placetype":"postalcode"
},
  "geometry": {"coordinates":[-4.03264356330857,55.7378323092023],"type":"Point"}
}