{
  "type": "Feature",
  "properties": {
    "iso:country":"GB",
    "wof:name":"NW6 1SD",
    "wof:placetype":"postalcode"
},
  "geometry": {"coordinates":[-0.19092794974125,51.54811842119144],"type":"Point"}
}