{
  "type": "Feature",
  "properties": {
    "iso:country":"GB",
    "wof:name":"DN6 9DJ",
    "wof:placetype":"postalcode"
},
  "geometry": {"coordinates":[-1.17763673512662,53.6307528377412],"type":"Point"}
}