{
  "type": "Feature",
  "properties": {
    "iso:country": "GB",
    "wof:name": "TN22 5GG",
    "wof:placetype": "postalcode"
  },
  "geometry": {"coordinates":[0.111759,50.959844],"type":"Point"}
}
