{
  "type": "Feature",
  "properties": {
    "date:inception_lower":"2012-08-01",
    "date:inception_upper":"2012-08-31",
    "iso:country":"GB",
    "wof:name":"TN22 5GG",
    "wof:placetype":"postalcode"
},
  "geometry": {"coordinates":[0.111759,50.959844],"type":"Point"}
}