{
  "type": "Feature",
  "properties": {
    "iso:country":"GB",
    "wof:name":"TN22 5GG",
    "wof:placetype":"postalcode"
},
  "geometry": {"coordinates":[0.11175899605135,50.95984450073127],"type":"Point"}
}