{
  "type": "Feature",
  "properties": {
    "iso:country":"GB",
    "wof:name":"SG5 3PZ",
    "wof:placetype":"postalcode"
},
  "geometry": {"coordinates":[-0.33313701882655,51.96954649348054],"type":"Point"}
}