{
  "type": "Feature",
  "properties": {
    "iso:country":"GB",
    "wof:name":"SO19 6GR",
    "wof:placetype":"postalcode"
},
  "geometry": {"coordinates":[-1.32873840039778,50.90582086425454],"type":"Point"}
}