{
  "type": "Feature",
  "properties": {
    "date:inception_lower":"1994-12-01",
    "date:inception_upper":"1994-12-31",
    "iso:country":"GB",
    "wof:name":"SO19 6GR",
    "wof:placetype":"postalcode"
},
  "geometry": {"coordinates":[-1.328738,50.905821],"type":"Point"}
}