{
  "type": "Feature",
  "properties": {
    "iso:country":"GB",
    "wof:name":"DT1 1DY",
    "wof:placetype":"postalcode"
},
  "geometry": {"coordinates":[-2.42868644914408,50.71061692774136],"type":"Point"}
}