{
  "type": "Feature",
  "properties": {
    "iso:country": "GB",
    "wof:name": "LS25 3BD",
    "wof:placetype": "postalcode"
  },
  "geometry": {"coordinates":[-1.344362,53.831526],"type":"Point"}
}
