{
  "type": "Feature",
  "properties": {
    "iso:country":"GB",
    "wof:name":"LS25 3BD",
    "wof:placetype":"postalcode"
},
  "geometry": {"coordinates":[-1.34435708281022,53.83153615727215],"type":"Point"}
}