{
  "type": "Feature",
  "properties": {
    "date:inception_lower": "2016-07-01",
    "date:inception_upper": "2016-07-01",
    "iso:country": "GB",
    "wof:name": "RG6 1FL",
    "wof:placetype": "postalcode"
  },
  "geometry": {"coordinates":[-0.921067,51.450066],"type":"Point"}
}
