{
  "type": "Feature",
  "properties": {
    "iso:country":"GB",
    "wof:name":"TW5 0BB",
    "wof:placetype":"postalcode"
},
  "geometry": {"coordinates":[-0.37926513701134,51.47734152598525],"type":"Point"}
}