{
  "type": "Feature",
  "properties": {
    "date:inception_lower":"1980-01-01",
    "date:inception_upper":"1980-01-31",
    "iso:country":"GB",
    "wof:name":"NG17 2QX",
    "wof:placetype":"postalcode"
},
  "geometry": {"coordinates":[-1.301977,53.128269],"type":"Point"}
}