{
  "type": "Feature",
  "properties": {
    "iso:country":"GB",
    "wof:name":"AB41 9EE",
    "wof:placetype":"postalcode"
},
  "geometry": {"coordinates":[-2.09701677606508,57.37040427502932],"type":"Point"}
}