{
  "type": "Feature",
  "properties": {
    "date:inception_lower": "2023-04-01",
    "date:inception_upper": "2023-04-01",
    "iso:country": "GB",
    "wof:name": "DE13 9SR",
    "wof:placetype": "postalcode"
  },
  "geometry": {"coordinates":[-1.683303,52.81055],"type":"Point"}
}
