{
  "type": "Feature",
  "properties": {
    "iso:country":"GB",
    "wof:name":"BB5 6RW",
    "wof:placetype":"postalcode"
},
  "geometry": {"coordinates":[-2.35021697376108,53.74997172271814],"type":"Point"}
}