{
  "type": "Feature",
  "properties": {
    "date:inception_lower": "1990-07-01",
    "date:inception_upper": "1990-07-01",
    "iso:country": "GB",
    "wof:name": "BB5 6RW",
    "wof:placetype": "postalcode"
  },
  "geometry": {"coordinates":[-2.350217,53.749972],"type":"Point"}
}
