{
  "type": "Feature",
  "properties": {
    "iso:country":"GB",
    "wof:name":"KT12 2TP",
    "wof:placetype":"postalcode"
},
  "geometry": {"coordinates":[-0.41778800028819,51.38566027383176],"type":"Point"}
}