{
  "type": "Feature",
  "properties": {
    "date:inception_lower": "1984-10-01",
    "date:inception_upper": "1984-10-01",
    "iso:country": "GB",
    "wof:name": "KT12 2TP",
    "wof:placetype": "postalcode"
  },
  "geometry": {"coordinates":[-0.417788,51.38566],"type":"Point"}
}
