{
  "type": "Feature",
  "properties": {
    "iso:country": "GB",
    "wof:name": "LL26 0PW",
    "wof:placetype": "postalcode"
  },
  "geometry": {"coordinates":[-3.81432,53.137908],"type":"Point"}
}
