{
  "type": "Feature",
  "properties": {
    "iso:country": "GB",
    "wof:name": "YO31 1HB",
    "wof:placetype": "postalcode"
  },
  "geometry": {"coordinates":[-1.047981,53.971942],"type":"Point"}
}
