{
  "type": "Feature",
  "properties": {
    "iso:country":"GB",
    "wof:name":"DH7 8SF",
    "wof:placetype":"postalcode"
},
  "geometry": {"coordinates":[-1.62610318006083,54.74785575589173],"type":"Point"}
}