{
  "type": "Feature",
  "properties": {
    "iso:country":"GB",
    "wof:name":"GL8 8AL",
    "wof:placetype":"postalcode"
},
  "geometry": {"coordinates":[-2.16045850900847,51.63731579116001],"type":"Point"}
}