{
  "type": "Feature",
  "properties": {
    "iso:country":"GB",
    "wof:name":"NE10 9TB",
    "wof:placetype":"postalcode"
},
  "geometry": {"coordinates":[-1.5796764202355,54.94501065493279],"type":"Point"}
}