{
  "type": "Feature",
  "properties": {
    "iso:country": "GB",
    "wof:name": "NE10 9TB",
    "wof:placetype": "postalcode"
  },
  "geometry": {"coordinates":[-1.579676,54.945011],"type":"Point"}
}
