{
  "type": "Feature",
  "properties": {
    "iso:country":"GB",
    "wof:name":"M21 9QP",
    "wof:placetype":"postalcode"
},
  "geometry": {"coordinates":[-2.27838254265224,53.44916050895626],"type":"Point"}
}