{
  "type": "Feature",
  "properties": {
    "iso:country":"GB",
    "wof:name":"EN8 8UA",
    "wof:placetype":"postalcode"
},
  "geometry": {"coordinates":[-0.02849708908487,51.69704274644004],"type":"Point"}
}