{
  "type": "Feature",
  "properties": {
    "iso:country":"GB",
    "wof:name":"S73 0TJ",
    "wof:placetype":"postalcode"
},
  "geometry": {"coordinates":[-1.38096592919118,53.51295148472165],"type":"Point"}
}