{
  "type": "Feature",
  "properties": {
    "iso:country":"GB",
    "wof:name":"YO25 9YY",
    "wof:placetype":"postalcode"
},
  "geometry": {"coordinates":[-0.43673914000613,53.96652459188962],"type":"Point"}
}