{
  "type": "Feature",
  "properties": {
    "iso:country": "GB",
    "wof:name": "YO25 9YY",
    "wof:placetype": "postalcode"
  },
  "geometry": {"coordinates":[-0.436739,53.966525],"type":"Point"}
}
