{
  "type": "Feature",
  "properties": {
    "date:inception_lower":"1983-01-01",
    "date:inception_upper":"1983-01-31",
    "iso:country":"GB",
    "wof:name":"YO25 9YY",
    "wof:placetype":"postalcode"
},
  "geometry": {"coordinates":[-0.436739,53.966525],"type":"Point"}
}