{
  "type": "Feature",
  "properties": {
    "date:inception_lower": "1996-06-01",
    "date:inception_upper": "1996-06-01",
    "iso:country": "GB",
    "wof:name": "NR8 5EN",
    "wof:placetype": "postalcode"
  },
  "geometry": {"coordinates":[1.20919,52.658096],"type":"Point"}
}
