{
  "type": "Feature",
  "properties": {
    "iso:country":"GB",
    "wof:name":"NR8 5EN",
    "wof:placetype":"postalcode"
},
  "geometry": {"coordinates":[1.20919020577618,52.65809643637501],"type":"Point"}
}