{
  "type": "Feature",
  "properties": {
    "iso:country":"GB",
    "wof:name":"SS15 5SX",
    "wof:placetype":"postalcode"
},
  "geometry": {"coordinates":[0.43038958382774,51.57800761472586],"type":"Point"}
}