{
  "type": "Feature",
  "properties": {
    "date:inception_lower": "1983-03-01",
    "date:inception_upper": "1983-03-01",
    "iso:country": "GB",
    "wof:name": "SS15 5SX",
    "wof:placetype": "postalcode"
  },
  "geometry": {"coordinates":[0.43039,51.578008],"type":"Point"}
}
