{
  "type": "Feature",
  "properties": {
    "iso:country":"GB",
    "wof:name":"DH1 5NS",
    "wof:placetype":"postalcode"
},
  "geometry": {"coordinates":[-1.57153163510031,54.80054338355373],"type":"Point"}
}