{
  "type": "Feature",
  "properties": {
    "iso:country":"GB",
    "wof:name":"ST13 8XT",
    "wof:placetype":"postalcode"
},
  "geometry": {"coordinates":[-2.02725167220782,53.10974386057887],"type":"Point"}
}