{
  "type": "Feature",
  "properties": {
    "date:inception_lower": "2008-11-01",
    "date:inception_upper": "2008-11-01",
    "iso:country": "GB",
    "wof:name": "NN5 4AL",
    "wof:placetype": "postalcode"
  },
  "geometry": {"coordinates":[-0.945287,52.230595],"type":"Point"}
}
