{
  "type": "Feature",
  "properties": {
    "iso:country":"GB",
    "wof:name":"NN5 4AL",
    "wof:placetype":"postalcode"
},
  "geometry": {"coordinates":[-0.94528742779186,52.23059472580032],"type":"Point"}
}