{
  "type": "Feature",
  "properties": {
    "date:inception_lower": "1980-01-01",
    "date:inception_upper": "1980-01-01",
    "iso:country": "GB",
    "wof:name": "CO7 8LU",
    "wof:placetype": "postalcode"
  },
  "geometry": {"coordinates":[1.068256,51.852747],"type":"Point"}
}
