{
  "type": "Feature",
  "properties": {
    "iso:country":"GB",
    "wof:name":"CO7 8LU",
    "wof:placetype":"postalcode"
},
  "geometry": {"coordinates":[1.06825610858438,51.85274749139507],"type":"Point"}
}