{
  "type": "Feature",
  "properties": {
    "iso:country": "GB",
    "wof:name": "WF15 7NR",
    "wof:placetype": "postalcode"
  },
  "geometry": {"coordinates":[-1.697034,53.703984],"type":"Point"}
}
