{
  "type": "Feature",
  "properties": {
    "iso:country":"GB",
    "wof:name":"WF15 7NR",
    "wof:placetype":"postalcode"
},
  "geometry": {"coordinates":[-1.69703396648708,53.70398395353335],"type":"Point"}
}