{
  "type": "Feature",
  "properties": {
    "date:inception_lower":"1980-01-01",
    "date:inception_upper":"1980-01-31",
    "iso:country":"GB",
    "wof:name":"WF15 7NR",
    "wof:placetype":"postalcode"
},
  "geometry": {"coordinates":[-1.697034,53.703984],"type":"Point"}
}