{
  "type": "Feature",
  "properties": {
    "iso:country":"GB",
    "wof:name":"PO41 0QR",
    "wof:placetype":"postalcode"
},
  "geometry": {"coordinates":[-1.49512722988281,50.70388421508486],"type":"Point"}
}