{
  "type": "Feature",
  "properties": {
    "iso:country":"GB",
    "wof:name":"EX20 4DA",
    "wof:placetype":"postalcode"
},
  "geometry": {"coordinates":[-4.21572572365131,50.65932885675546],"type":"Point"}
}