{
  "type": "Feature",
  "properties": {
    "iso:country": "GB",
    "wof:name": "NG9 6QP",
    "wof:placetype": "postalcode"
  },
  "geometry": {"coordinates":[-1.264204,52.911291],"type":"Point"}
}
