{
  "type": "Feature",
  "properties": {
    "iso:country":"GB",
    "wof:name":"NG9 6QP",
    "wof:placetype":"postalcode"
},
  "geometry": {"coordinates":[-1.26420380778129,52.91129116041751],"type":"Point"}
}