{
  "type": "Feature",
  "properties": {
    "iso:country": "GB",
    "wof:name": "CT1 2AZ",
    "wof:placetype": "postalcode"
  },
  "geometry": {"coordinates":[1.078552,51.279667],"type":"Point"}
}
