{
  "type": "Feature",
  "properties": {
    "iso:country":"GB",
    "wof:name":"CT1 2AZ",
    "wof:placetype":"postalcode"
},
  "geometry": {"coordinates":[1.07855238457917,51.2796668400732],"type":"Point"}
}