{
  "type": "Feature",
  "properties": {
    "date:inception_lower": "2000-12-01",
    "date:inception_upper": "2000-12-01",
    "iso:country": "GB",
    "wof:name": "DY2 8AL",
    "wof:placetype": "postalcode"
  },
  "geometry": {"coordinates":[-2.073021,52.503041],"type":"Point"}
}
