{
  "type": "Feature",
  "properties": {
    "iso:country":"GB",
    "wof:name":"NR26 8NN",
    "wof:placetype":"postalcode"
},
  "geometry": {"coordinates":[1.20468850244417,52.93753976232554],"type":"Point"}
}