{
  "type": "Feature",
  "properties": {
    "iso:country":"GB",
    "wof:name":"CA6 4QU",
    "wof:placetype":"postalcode"
},
  "geometry": {"coordinates":[-2.86645919070102,54.92671379429436],"type":"Point"}
}