{
  "type": "Feature",
  "properties": {
    "date:inception_lower": "1993-01-01",
    "date:inception_upper": "1993-01-01",
    "iso:country": "GB",
    "wof:name": "CA6 4QU",
    "wof:placetype": "postalcode"
  },
  "geometry": {"coordinates":[-2.866459,54.926714],"type":"Point"}
}
