{
  "type": "Feature",
  "properties": {
    "date:inception_lower":"1980-01-01",
    "date:inception_upper":"1980-01-31",
    "iso:country":"GB",
    "wof:name":"LL21 0NT",
    "wof:placetype":"postalcode"
},
  "geometry": {"coordinates":[-3.474132,52.976858],"type":"Point"}
}