{
  "type": "Feature",
  "properties": {
    "iso:country":"GB",
    "wof:name":"LL21 0NT",
    "wof:placetype":"postalcode"
},
  "geometry": {"coordinates":[-3.47417286759209,52.97680608522358],"type":"Point"}
}