{
  "type": "Feature",
  "properties": {
    "iso:country":"GB",
    "wof:name":"NW4 1JD",
    "wof:placetype":"postalcode"
},
  "geometry": {"coordinates":[-0.23059748145804,51.59997961374614],"type":"Point"}
}