{
  "type": "Feature",
  "properties": {
    "iso:country": "GB",
    "wof:name": "EX39 3FS",
    "wof:placetype": "postalcode"
  },
  "geometry": {"coordinates":[-4.23025,51.015744],"type":"Point"}
}
