{
  "type": "Feature",
  "properties": {
    "iso:country":"GB",
    "wof:name":"BB7 4JL",
    "wof:placetype":"postalcode"
},
  "geometry": {"coordinates":[-2.2473976929822,53.91416807531337],"type":"Point"}
}