{
  "type": "Feature",
  "properties": {
    "iso:country":"GB",
    "wof:name":"BS22 7LY",
    "wof:placetype":"postalcode"
},
  "geometry": {"coordinates":[-2.91278197001321,51.36962752227856],"type":"Point"}
}