{
  "type": "Feature",
  "properties": {
    "iso:country":"GB",
    "wof:name":"YO25 9UQ",
    "wof:placetype":"postalcode"
},
  "geometry": {"coordinates":[-0.56287476111846,53.93499444164711],"type":"Point"}
}