{
  "type": "Feature",
  "properties": {
    "date:inception_lower": "1983-07-01",
    "date:inception_upper": "1983-07-01",
    "iso:country": "GB",
    "wof:name": "YO25 9UQ",
    "wof:placetype": "postalcode"
  },
  "geometry": {"coordinates":[-0.562875,53.934994],"type":"Point"}
}
