{
  "type": "Feature",
  "properties": {
    "iso:country":"GB",
    "wof:name":"PL30 3EX",
    "wof:placetype":"postalcode"
},
  "geometry": {"coordinates":[-4.78897490619622,50.56140663903207],"type":"Point"}
}