{
  "type": "Feature",
  "properties": {
    "date:inception_lower":"1996-12-01",
    "date:inception_upper":"1996-12-31",
    "iso:country":"GB",
    "wof:name":"PL30 3EX",
    "wof:placetype":"postalcode"
},
  "geometry": {"coordinates":[-4.788975,50.561407],"type":"Point"}
}