{
  "type": "Feature",
  "properties": {
    "date:inception_lower":"1999-12-01",
    "date:inception_upper":"1999-12-31",
    "iso:country":"GB",
    "wof:name":"TQ13 9FJ",
    "wof:placetype":"postalcode"
},
  "geometry": {"coordinates":[-3.677996,50.57883],"type":"Point"}
}