{
  "type": "Feature",
  "properties": {
    "iso:country":"GB",
    "wof:name":"TQ13 9FJ",
    "wof:placetype":"postalcode"
},
  "geometry": {"coordinates":[-3.6779960300906,50.57882960127726],"type":"Point"}
}