{
  "type": "Feature",
  "properties": {
    "date:inception_lower":"1980-01-01",
    "date:inception_upper":"1980-01-31",
    "iso:country":"GB",
    "wof:name":"NW6 4JD",
    "wof:placetype":"postalcode"
},
  "geometry": {"coordinates":[-0.196251,51.540809],"type":"Point"}
}