{
  "type": "Feature",
  "properties": {
    "iso:country":"GB",
    "wof:name":"NW6 4JD",
    "wof:placetype":"postalcode"
},
  "geometry": {"coordinates":[-0.19639334760698,51.54084678347435],"type":"Point"}
}