{
  "type": "Feature",
  "properties": {
    "iso:country":"GB",
    "wof:name":"CT1 1XY",
    "wof:placetype":"postalcode"
},
  "geometry": {"coordinates":[1.10482345511897,51.27005884376222],"type":"Point"}
}