{
  "type": "Feature",
  "properties": {
    "iso:country": "GB",
    "wof:name": "NR21 0DL",
    "wof:placetype": "postalcode"
  },
  "geometry": {"coordinates":[0.948871,52.913135],"type":"Point"}
}
