{
  "type": "Feature",
  "properties": {
    "iso:country":"GB",
    "wof:name":"NR21 0DL",
    "wof:placetype":"postalcode"
},
  "geometry": {"coordinates":[0.94887059773108,52.91313504794806],"type":"Point"}
}