{
  "type": "Feature",
  "properties": {
    "date:inception_lower": "2004-06-01",
    "date:inception_upper": "2004-06-01",
    "iso:country": "GB",
    "wof:name": "G68 9EU",
    "wof:placetype": "postalcode"
  },
  "geometry": {"coordinates":[-4.02136,55.94941],"type":"Point"}
}
