{
  "type": "Feature",
  "properties": {
    "iso:country":"GB",
    "wof:name":"G68 9EU",
    "wof:placetype":"postalcode"
},
  "geometry": {"coordinates":[-4.0213604194406,55.9494100912232],"type":"Point"}
}