{
  "type": "Feature",
  "properties": {
    "date:inception_lower": "2014-10-01",
    "date:inception_upper": "2014-10-01",
    "iso:country": "GB",
    "wof:name": "M9 7GG",
    "wof:placetype": "postalcode"
  },
  "geometry": {"coordinates":[-2.204574,53.524597],"type":"Point"}
}
