{
  "type": "Feature",
  "properties": {
    "date:inception_lower": "2007-04-01",
    "date:inception_upper": "2007-04-01",
    "iso:country": "GB",
    "wof:name": "TA6 9DL",
    "wof:placetype": "postalcode"
  },
  "geometry": {"coordinates":[-3.004579,51.126394],"type":"Point"}
}
