{
  "type": "Feature",
  "properties": {
    "iso:country":"GB",
    "wof:name":"NP15 1JX",
    "wof:placetype":"postalcode"
},
  "geometry": {"coordinates":[-2.9189537648668,51.73429836811605],"type":"Point"}
}