{
  "type": "Feature",
  "properties": {
    "iso:country": "GB",
    "wof:name": "NR18 0HU",
    "wof:placetype": "postalcode"
  },
  "geometry": {"coordinates":[1.122711,52.581295],"type":"Point"}
}
