{
  "type": "Feature",
  "properties": {
    "iso:country": "GB",
    "wof:name": "SG12 8PH",
    "wof:placetype": "postalcode"
  },
  "geometry": {"coordinates":[0.056526,51.805643],"type":"Point"}
}
