{
  "type": "Feature",
  "properties": {
    "iso:country":"GB",
    "wof:name":"SG12 8PH",
    "wof:placetype":"postalcode"
},
  "geometry": {"coordinates":[0.05652582614892,51.80564318326026],"type":"Point"}
}