{
  "type": "Feature",
  "properties": {
    "iso:country":"GB",
    "wof:name":"PO9 5SP",
    "wof:placetype":"postalcode"
},
  "geometry": {"coordinates":[-0.9713241058858,50.87000052124383],"type":"Point"}
}