{
  "type": "Feature",
  "properties": {
    "date:inception_lower": "1980-01-01",
    "date:inception_upper": "1980-01-01",
    "iso:country": "GB",
    "wof:name": "SK14 5DD",
    "wof:placetype": "postalcode"
  },
  "geometry": {"coordinates":[-2.08137,53.438734],"type":"Point"}
}
