{
  "type": "Feature",
  "properties": {
    "iso:country":"GB",
    "wof:name":"SK14 5DD",
    "wof:placetype":"postalcode"
},
  "geometry": {"coordinates":[-2.08137006005713,53.43873427864722],"type":"Point"}
}