{
  "type": "Feature",
  "properties": {
    "date:inception_lower": "1998-12-01",
    "date:inception_upper": "1998-12-01",
    "iso:country": "GB",
    "wof:name": "B79 0JQ",
    "wof:placetype": "postalcode"
  },
  "geometry": {"coordinates":[-1.581733,52.630434],"type":"Point"}
}
