{
  "type": "Feature",
  "properties": {
    "iso:country":"GB",
    "wof:name":"B79 0JQ",
    "wof:placetype":"postalcode"
},
  "geometry": {"coordinates":[-1.58173305331075,52.63043406734781],"type":"Point"}
}