{
  "type": "Feature",
  "properties": {
    "iso:country":"GB",
    "wof:name":"WR12 7EX",
    "wof:placetype":"postalcode"
},
  "geometry": {"coordinates":[-1.85840287098743,52.04085446353965],"type":"Point"}
}