{
  "type": "Feature",
  "properties": {
    "iso:country": "GB",
    "wof:name": "LE7 7UD",
    "wof:placetype": "postalcode"
  },
  "geometry": {"coordinates":[-1.198611,52.668793],"type":"Point"}
}
