{
  "type": "Feature",
  "properties": {
    "iso:country":"GB",
    "wof:name":"BA1 5BG",
    "wof:placetype":"postalcode"
},
  "geometry": {"coordinates":[-2.35876221821273,51.38757904807726],"type":"Point"}
}