{
  "type": "Feature",
  "properties": {
    "iso:country": "GB",
    "wof:name": "BA1 5BG",
    "wof:placetype": "postalcode"
  },
  "geometry": {"coordinates":[-2.358762,51.387579],"type":"Point"}
}
