{
  "type": "Feature",
  "properties": {
    "date:inception_lower": "1980-01-01",
    "date:inception_upper": "1980-01-01",
    "iso:country": "GB",
    "wof:name": "YO22 5DW",
    "wof:placetype": "postalcode"
  },
  "geometry": {"coordinates":[-0.662161,54.452419],"type":"Point"}
}
