{
  "type": "Feature",
  "properties": {
    "iso:country":"GB",
    "wof:name":"YO22 5DW",
    "wof:placetype":"postalcode"
},
  "geometry": {"coordinates":[-0.66216064597321,54.45241942815471],"type":"Point"}
}