{
  "type": "Feature",
  "properties": {
    "iso:country": "GB",
    "wof:name": "CO1 1RR",
    "wof:placetype": "postalcode"
  },
  "geometry": {"coordinates":[0.896603,51.894723],"type":"Point"}
}
