{
  "type": "Feature",
  "properties": {
    "iso:country":"GB",
    "wof:name":"CO1 1RR",
    "wof:placetype":"postalcode"
},
  "geometry": {"coordinates":[0.89660323315213,51.8947227148914],"type":"Point"}
}