{
  "type": "Feature",
  "properties": {
    "iso:country":"GB",
    "wof:name":"SK6 6DB",
    "wof:placetype":"postalcode"
},
  "geometry": {"coordinates":[-2.06962856905747,53.39296311730222],"type":"Point"}
}