{
  "type": "Feature",
  "properties": {
    "iso:country": "GB",
    "wof:name": "DE13 0TP",
    "wof:placetype": "postalcode"
  },
  "geometry": {"coordinates":[-1.643484,52.820218],"type":"Point"}
}
