{
  "type": "Feature",
  "properties": {
    "iso:country":"GB",
    "wof:name":"M11 1DS",
    "wof:placetype":"postalcode"
},
  "geometry": {"coordinates":[-2.16504793359923,53.47643536556873],"type":"Point"}
}