{
  "type": "Feature",
  "properties": {
    "iso:country": "GB",
    "wof:name": "M11 1DS",
    "wof:placetype": "postalcode"
  },
  "geometry": {"coordinates":[-2.165048,53.476435],"type":"Point"}
}
