{
  "type": "Feature",
  "properties": {
    "date:inception_lower": "2000-12-01",
    "date:inception_upper": "2000-12-01",
    "iso:country": "GB",
    "wof:name": "RM16 6LY",
    "wof:placetype": "postalcode"
  },
  "geometry": {"coordinates":[0.293496,51.483819],"type":"Point"}
}
