{
  "type": "Feature",
  "properties": {
    "iso:country":"GB",
    "wof:name":"ST5 3DU",
    "wof:placetype":"postalcode"
},
  "geometry": {"coordinates":[-2.22067219050791,52.99002286780523],"type":"Point"}
}