{
  "type": "Feature",
  "properties": {
    "iso:country": "GB",
    "wof:name": "L39 1QH",
    "wof:placetype": "postalcode"
  },
  "geometry": {"coordinates":[-2.882867,53.575695],"type":"Point"}
}
