{
  "type": "Feature",
  "properties": {
    "iso:country":"GB",
    "wof:name":"L39 1QH",
    "wof:placetype":"postalcode"
},
  "geometry": {"coordinates":[-2.88286699700288,53.57569463563968],"type":"Point"}
}