{
  "type": "Feature",
  "properties": {
    "iso:country":"GB",
    "wof:name":"BD16 4AR",
    "wof:placetype":"postalcode"
},
  "geometry": {"coordinates":[-1.833546814126,53.86160381303252],"type":"Point"}
}