{
  "type": "Feature",
  "properties": {
    "iso:country": "GB",
    "wof:name": "BB5 5NX",
    "wof:placetype": "postalcode"
  },
  "geometry": {"coordinates":[-2.385215,53.774653],"type":"Point"}
}
