{
  "type": "Feature",
  "properties": {
    "iso:country":"GB",
    "wof:name":"CR7 7PB",
    "wof:placetype":"postalcode"
},
  "geometry": {"coordinates":[-0.11514648665812,51.39656926408404],"type":"Point"}
}