{
  "type": "Feature",
  "properties": {
    "date:inception_lower": "1992-08-01",
    "date:inception_upper": "1992-08-01",
    "iso:country": "GB",
    "wof:name": "DE56 0RW",
    "wof:placetype": "postalcode"
  },
  "geometry": {"coordinates":[-1.476444,53.003918],"type":"Point"}
}
