{
  "type": "Feature",
  "properties": {
    "iso:country":"GB",
    "wof:name":"CT2 0BU",
    "wof:placetype":"postalcode"
},
  "geometry": {"coordinates":[1.12450599078048,51.29597021139941],"type":"Point"}
}