{
  "type": "Feature",
  "properties": {
    "iso:country": "GB",
    "wof:name": "WD23 3NL",
    "wof:placetype": "postalcode"
  },
  "geometry": {"coordinates":[-0.365698,51.647618],"type":"Point"}
}
