{
  "type": "Feature",
  "properties": {
    "iso:country":"GB",
    "wof:name":"OL1 4AD",
    "wof:placetype":"postalcode"
},
  "geometry": {"coordinates":[-2.10366161097723,53.55481132965662],"type":"Point"}
}