{
  "type": "Feature",
  "properties": {
    "date:inception_lower": "2019-12-01",
    "date:inception_upper": "2019-12-01",
    "iso:country": "GB",
    "wof:name": "SW20 0FT",
    "wof:placetype": "postalcode"
  },
  "geometry": {"coordinates":[-0.233315,51.40778],"type":"Point"}
}
