{
  "type": "Feature",
  "properties": {
    "iso:country": "GB",
    "wof:name": "SW20 0FT",
    "wof:placetype": "postalcode"
  },
  "geometry": {"coordinates":[-0.233903,51.407825],"type":"Point"}
}
