{
  "type": "Feature",
  "properties": {
    "iso:country":"GB",
    "wof:name":"PO21 2XT",
    "wof:placetype":"postalcode"
},
  "geometry": {"coordinates":[-0.69358236557162,50.78563839918093],"type":"Point"}
}