{
  "type": "Feature",
  "properties": {
    "iso:country":"GB",
    "wof:name":"SN8 2AP",
    "wof:placetype":"postalcode"
},
  "geometry": {"coordinates":[-1.72311994755853,51.41947108891139],"type":"Point"}
}