{
  "type": "Feature",
  "properties": {
    "iso:country":"GB",
    "wof:name":"HR1 1DZ",
    "wof:placetype":"postalcode"
},
  "geometry": {"coordinates":[-2.70941476268413,52.06261877954174],"type":"Point"}
}