{
  "type": "Feature",
  "properties": {
    "date:inception_lower": "1995-07-01",
    "date:inception_upper": "1995-07-01",
    "iso:country": "GB",
    "wof:name": "HR1 1DZ",
    "wof:placetype": "postalcode"
  },
  "geometry": {"coordinates":[-2.709415,52.062619],"type":"Point"}
}
