{
  "type": "Feature",
  "properties": {
    "iso:country": "GB",
    "wof:name": "DY14 8PH",
    "wof:placetype": "postalcode"
  },
  "geometry": {"coordinates":[-2.468685,52.381697],"type":"Point"}
}
