{
  "type": "Feature",
  "properties": {
    "date:inception_lower": "1999-06-01",
    "date:inception_upper": "1999-06-01",
    "iso:country": "GB",
    "wof:name": "CH41 2SH",
    "wof:placetype": "postalcode"
  },
  "geometry": {"coordinates":[-3.027995,53.387765],"type":"Point"}
}
