{
  "type": "Feature",
  "properties": {
    "iso:country":"GB",
    "wof:name":"TN17 4QZ",
    "wof:placetype":"postalcode"
},
  "geometry": {"coordinates":[0.6604941012559,51.06269397375701],"type":"Point"}
}