{
  "type": "Feature",
  "properties": {
    "date:inception_lower": "1999-06-01",
    "date:inception_upper": "1999-06-01",
    "iso:country": "GB",
    "wof:name": "TN17 4QZ",
    "wof:placetype": "postalcode"
  },
  "geometry": {"coordinates":[0.660494,51.062694],"type":"Point"}
}
