{
  "type": "Feature",
  "properties": {
    "date:inception_lower": "2021-02-01",
    "date:inception_upper": "2021-02-01",
    "iso:country": "GB",
    "wof:name": "M24 4TE",
    "wof:placetype": "postalcode"
  },
  "geometry": {"coordinates":[-2.225333,53.542687],"type":"Point"}
}
