{
  "type": "Feature",
  "properties": {
    "iso:country": "GB",
    "wof:name": "WS10 1DS",
    "wof:placetype": "postalcode"
  },
  "geometry": {"coordinates":[-2.027167,52.560371],"type":"Point"}
}
