{
  "type": "Feature",
  "properties": {
    "date:inception_lower": "1980-01-01",
    "date:inception_upper": "1980-01-01",
    "iso:country": "GB",
    "wof:name": "BN20 8XD",
    "wof:placetype": "postalcode"
  },
  "geometry": {"coordinates":[0.253705,50.786803],"type":"Point"}
}
