{
  "type": "Feature",
  "properties": {
    "date:inception_lower": "2003-07-01",
    "date:inception_upper": "2003-07-01",
    "iso:country": "GB",
    "wof:name": "PH7 3LE",
    "wof:placetype": "postalcode"
  },
  "geometry": {"coordinates":[-3.837677,56.370927],"type":"Point"}
}
