{
  "type": "Feature",
  "properties": {
    "iso:country":"GB",
    "wof:name":"PH7 3LE",
    "wof:placetype":"postalcode"
},
  "geometry": {"coordinates":[-3.83767745714795,56.37092715897644],"type":"Point"}
}