{
  "type": "Feature",
  "properties": {
    "iso:country":"GB",
    "wof:name":"TQ11 0HJ",
    "wof:placetype":"postalcode"
},
  "geometry": {"coordinates":[-3.81443900134177,50.48910242176288],"type":"Point"}
}