{
  "type": "Feature",
  "properties": {
    "iso:country": "GB",
    "wof:name": "TQ11 0HJ",
    "wof:placetype": "postalcode"
  },
  "geometry": {"coordinates":[-3.814439,50.489102],"type":"Point"}
}
