{
  "type": "Feature",
  "properties": {
    "iso:country":"GB",
    "wof:name":"NR25 6EZ",
    "wof:placetype":"postalcode"
},
  "geometry": {"coordinates":[1.09236121128696,52.9070109552561],"type":"Point"}
}