{
  "type": "Feature",
  "properties": {
    "iso:country": "GB",
    "wof:name": "NR25 6EZ",
    "wof:placetype": "postalcode"
  },
  "geometry": {"coordinates":[1.092363,52.90703],"type":"Point"}
}
