{
  "type": "Feature",
  "properties": {
    "iso:country":"GB",
    "wof:name":"SE11 5HL",
    "wof:placetype":"postalcode"
},
  "geometry": {"coordinates":[-0.12046201855649,51.48812765257487],"type":"Point"}
}