{
  "type": "Feature",
  "properties": {
    "date:inception_lower":"1980-01-01",
    "date:inception_upper":"1980-01-31",
    "iso:country":"GB",
    "wof:name":"SE11 5HL",
    "wof:placetype":"postalcode"
},
  "geometry": {"coordinates":[-0.120462,51.488128],"type":"Point"}
}