{
  "type": "Feature",
  "properties": {
    "iso:country":"GB",
    "wof:name":"LU2 7RF",
    "wof:placetype":"postalcode"
},
  "geometry": {"coordinates":[-0.41498428384992,51.8868566965489],"type":"Point"}
}