{
  "type": "Feature",
  "properties": {
    "iso:country":"GB",
    "wof:name":"WV14 0NY",
    "wof:placetype":"postalcode"
},
  "geometry": {"coordinates":[-2.07060373494238,52.56323241327733],"type":"Point"}
}