{
  "type": "Feature",
  "properties": {
    "date:inception_lower":"1980-01-01",
    "date:inception_upper":"1980-01-31",
    "iso:country":"GB",
    "wof:name":"WV14 0NY",
    "wof:placetype":"postalcode"
},
  "geometry": {"coordinates":[-2.070604,52.563232],"type":"Point"}
}