{
  "type": "Feature",
  "properties": {
    "date:inception_lower":"1980-01-01",
    "date:inception_upper":"1980-01-31",
    "iso:country":"GB",
    "wof:name":"DN18 6HP",
    "wof:placetype":"postalcode"
},
  "geometry": {"coordinates":[-0.509672,53.675755],"type":"Point"}
}