{
  "type": "Feature",
  "properties": {
    "date:inception_lower": "1996-06-01",
    "date:inception_upper": "1996-06-01",
    "iso:country": "GB",
    "wof:name": "AB16 5SF",
    "wof:placetype": "postalcode"
  },
  "geometry": {"coordinates":[-2.157497,57.159363],"type":"Point"}
}
