{
  "type": "Feature",
  "properties": {
    "iso:country":"GB",
    "wof:name":"AB16 5SF",
    "wof:placetype":"postalcode"
},
  "geometry": {"coordinates":[-2.15749726656245,57.15936274840051],"type":"Point"}
}