{
  "type": "Feature",
  "properties": {
    "date:inception_lower": "2011-11-01",
    "date:inception_upper": "2011-11-01",
    "iso:country": "GB",
    "wof:name": "M40 5BQ",
    "wof:placetype": "postalcode"
  },
  "geometry": {"coordinates":[-2.200636,53.502133],"type":"Point"}
}
