{
  "type": "Feature",
  "properties": {
    "iso:country":"GB",
    "wof:name":"BB2 3TU",
    "wof:placetype":"postalcode"
},
  "geometry": {"coordinates":[-2.47464358817436,53.72856502474463],"type":"Point"}
}