{
  "type": "Feature",
  "properties": {
    "date:inception_lower":"1980-01-01",
    "date:inception_upper":"1980-01-31",
    "iso:country":"GB",
    "wof:name":"BB2 3TU",
    "wof:placetype":"postalcode"
},
  "geometry": {"coordinates":[-2.474644,53.728565],"type":"Point"}
}