{
  "type": "Feature",
  "properties": {
    "date:inception_lower": "1980-01-01",
    "date:inception_upper": "1980-01-01",
    "iso:country": "GB",
    "wof:name": "TR11 3BQ",
    "wof:placetype": "postalcode"
  },
  "geometry": {"coordinates":[-5.070452,50.154688],"type":"Point"}
}
