{
  "type": "Feature",
  "properties": {
    "iso:country": "GB",
    "wof:name": "CF63 1EW",
    "wof:placetype": "postalcode"
  },
  "geometry": {"coordinates":[-3.256852,51.412975],"type":"Point"}
}
