{
  "type": "Feature",
  "properties": {
    "iso:country":"GB",
    "wof:name":"HD8 0RZ",
    "wof:placetype":"postalcode"
},
  "geometry": {"coordinates":[-1.70577501859731,53.61036662347097],"type":"Point"}
}