{
  "type": "Feature",
  "properties": {
    "iso:country":"GB",
    "wof:name":"YO18 8BH",
    "wof:placetype":"postalcode"
},
  "geometry": {"coordinates":[-0.78729142292639,54.24459440890953],"type":"Point"}
}