{
  "type": "Feature",
  "properties": {
    "iso:country": "GB",
    "wof:name": "WR9 8US",
    "wof:placetype": "postalcode"
  },
  "geometry": {"coordinates":[-2.151419,52.251632],"type":"Point"}
}
