{
  "type": "Feature",
  "properties": {
    "date:inception_lower":"1999-12-01",
    "date:inception_upper":"1999-12-31",
    "iso:country":"GB",
    "wof:name":"WR9 8US",
    "wof:placetype":"postalcode"
},
  "geometry": {"coordinates":[-2.151419,52.251632],"type":"Point"}
}