{
  "type": "Feature",
  "properties": {
    "iso:country":"GB",
    "wof:name":"WR9 8US",
    "wof:placetype":"postalcode"
},
  "geometry": {"coordinates":[-2.15141929654512,52.25163231786927],"type":"Point"}
}