{
  "type": "Feature",
  "properties": {
    "iso:country":"GB",
    "wof:name":"W11 2DA",
    "wof:placetype":"postalcode"
},
  "geometry": {"coordinates":[-0.2006998182979,51.515383435822],"type":"Point"}
}