{
  "type": "Feature",
  "properties": {
    "iso:country": "GB",
    "wof:name": "FY4 5FQ",
    "wof:placetype": "postalcode"
  },
  "geometry": {"coordinates":[-2.986787,53.786262],"type":"Point"}
}
