{
  "type": "Feature",
  "properties": {
    "iso:country":"GB",
    "wof:name":"FY4 5FQ",
    "wof:placetype":"postalcode"
},
  "geometry": {"coordinates":[-2.98756245772753,53.78614235106878],"type":"Point"}
}