{
  "type": "Feature",
  "properties": {
    "iso:country":"GB",
    "wof:name":"SE9 3DY",
    "wof:placetype":"postalcode"
},
  "geometry": {"coordinates":[0.05232167368007,51.43174151632729],"type":"Point"}
}