{
  "type": "Feature",
  "properties": {
    "date:inception_lower":"1983-07-01",
    "date:inception_upper":"1983-07-31",
    "iso:country":"GB",
    "wof:name":"DT2 8RW",
    "wof:placetype":"postalcode"
},
  "geometry": {"coordinates":[-2.382222,50.741075],"type":"Point"}
}