{
  "type": "Feature",
  "properties": {
    "iso:country":"GB",
    "wof:name":"DT2 8RW",
    "wof:placetype":"postalcode"
},
  "geometry": {"coordinates":[-2.38221115174679,50.74111103616347],"type":"Point"}
}