{
  "type": "Feature",
  "properties": {
    "iso:country":"GB",
    "wof:name":"RM8 3AB",
    "wof:placetype":"postalcode"
},
  "geometry": {"coordinates":[0.14290489305253,51.55499541986612],"type":"Point"}
}