{
  "type": "Feature",
  "properties": {
    "date:inception_lower": "1980-01-01",
    "date:inception_upper": "1980-01-01",
    "iso:country": "GB",
    "wof:name": "G72 9TQ",
    "wof:placetype": "postalcode"
  },
  "geometry": {"coordinates":[-4.106545,55.787563],"type":"Point"}
}
