{
  "type": "Feature",
  "properties": {
    "iso:country":"GB",
    "wof:name":"M14 6AW",
    "wof:placetype":"postalcode"
},
  "geometry": {"coordinates":[-2.22292993501695,53.43822109999049],"type":"Point"}
}