{
  "type": "Feature",
  "properties": {
    "date:inception_lower":"2003-11-01",
    "date:inception_upper":"2003-11-30",
    "iso:country":"GB",
    "wof:name":"PR26 9JT",
    "wof:placetype":"postalcode"
},
  "geometry": {"coordinates":[-2.76203,53.656163],"type":"Point"}
}