{
  "type": "Feature",
  "properties": {
    "iso:country": "GB",
    "wof:name": "PR26 9JT",
    "wof:placetype": "postalcode"
  },
  "geometry": {"coordinates":[-2.76203,53.656163],"type":"Point"}
}
