{
  "type": "Feature",
  "properties": {
    "iso:country":"GB",
    "wof:name":"PR26 9JT",
    "wof:placetype":"postalcode"
},
  "geometry": {"coordinates":[-2.7623664828116,53.65634104596835],"type":"Point"}
}