{
  "type": "Feature",
  "properties": {
    "iso:country": "GB",
    "wof:name": "EN7 6HX",
    "wof:placetype": "postalcode"
  },
  "geometry": {"coordinates":[-0.062294,51.711426],"type":"Point"}
}
