{
  "type": "Feature",
  "properties": {
    "date:inception_lower": "1995-01-01",
    "date:inception_upper": "1995-01-01",
    "iso:country": "GB",
    "wof:name": "LL14 2SJ",
    "wof:placetype": "postalcode"
  },
  "geometry": {"coordinates":[-3.064406,52.999036],"type":"Point"}
}
