{
  "type": "Feature",
  "properties": {
    "iso:country":"GB",
    "wof:name":"BA4 6PG",
    "wof:placetype":"postalcode"
},
  "geometry": {"coordinates":[-2.51623295451233,51.13898498416845],"type":"Point"}
}