{
  "type": "Feature",
  "properties": {
    "iso:country": "GB",
    "wof:name": "NE65 8XF",
    "wof:placetype": "postalcode"
  },
  "geometry": {"coordinates":[-1.759957,55.263524],"type":"Point"}
}
