{
  "type": "Feature",
  "properties": {
    "iso:country":"GB",
    "wof:name":"NE65 8XF",
    "wof:placetype":"postalcode"
},
  "geometry": {"coordinates":[-1.75995709821213,55.26352427964618],"type":"Point"}
}