{
  "type": "Feature",
  "properties": {
    "iso:country":"GB",
    "wof:name":"M45 6DE",
    "wof:placetype":"postalcode"
},
  "geometry": {"coordinates":[-2.28468560156297,53.54496243720301],"type":"Point"}
}