{
  "type": "Feature",
  "properties": {
    "date:inception_lower": "1980-01-01",
    "date:inception_upper": "1980-01-01",
    "iso:country": "GB",
    "wof:name": "DL17 8SS",
    "wof:placetype": "postalcode"
  },
  "geometry": {"coordinates":[-1.53828,54.686642],"type":"Point"}
}
