{
  "type": "Feature",
  "properties": {
    "iso:country": "GB",
    "wof:name": "NG6 8ZB",
    "wof:placetype": "postalcode"
  },
  "geometry": {"coordinates":[-1.204224,52.998383],"type":"Point"}
}
