{
  "type": "Feature",
  "properties": {
    "iso:country":"GB",
    "wof:name":"CW12 2NT",
    "wof:placetype":"postalcode"
},
  "geometry": {"coordinates":[-2.17794861214096,53.20348514047218],"type":"Point"}
}