{
  "type": "Feature",
  "properties": {
    "iso:country": "GB",
    "wof:name": "CW12 2NT",
    "wof:placetype": "postalcode"
  },
  "geometry": {"coordinates":[-2.177947,53.203503],"type":"Point"}
}
