{
  "type": "Feature",
  "properties": {
    "iso:country": "GB",
    "wof:name": "KA30 8RF",
    "wof:placetype": "postalcode"
  },
  "geometry": {"coordinates":[-4.862843,55.805365],"type":"Point"}
}
