{
  "type": "Feature",
  "properties": {
    "iso:country":"GB",
    "wof:name":"KA30 8RF",
    "wof:placetype":"postalcode"
},
  "geometry": {"coordinates":[-4.86284292752837,55.80536510404306],"type":"Point"}
}