{
  "type": "Feature",
  "properties": {
    "iso:country": "GB",
    "wof:name": "EX14 3TX",
    "wof:placetype": "postalcode"
  },
  "geometry": {"coordinates":[-3.202057,50.788311],"type":"Point"}
}
