{
  "type": "Feature",
  "properties": {
    "iso:country":"GB",
    "wof:name":"S35 1TX",
    "wof:placetype":"postalcode"
},
  "geometry": {"coordinates":[-1.45868078343396,53.45785115385279],"type":"Point"}
}