{
  "type": "Feature",
  "properties": {
    "iso:country":"GB",
    "wof:name":"TQ14 0DR",
    "wof:placetype":"postalcode"
},
  "geometry": {"coordinates":[-3.50507472225071,50.54037167629873],"type":"Point"}
}