{
  "type": "Feature",
  "properties": {
    "iso:country":"GB",
    "wof:name":"CO15 2EY",
    "wof:placetype":"postalcode"
},
  "geometry": {"coordinates":[1.11804362656875,51.77566192032745],"type":"Point"}
}