{
  "type": "Feature",
  "properties": {
    "date:inception_lower": "1980-01-01",
    "date:inception_upper": "1980-01-01",
    "iso:country": "GB",
    "wof:name": "FK13 6HA",
    "wof:placetype": "postalcode"
  },
  "geometry": {"coordinates":[-3.740995,56.156932],"type":"Point"}
}
