{
  "type": "Feature",
  "properties": {
    "iso:country":"GB",
    "wof:name":"IV2 7PZ",
    "wof:placetype":"postalcode"
},
  "geometry": {"coordinates":[-4.14171740927265,57.48462432939398],"type":"Point"}
}