{
  "type": "Feature",
  "properties": {
    "iso:country":"GB",
    "wof:name":"PL9 7LT",
    "wof:placetype":"postalcode"
},
  "geometry": {"coordinates":[-4.10850269203542,50.36183174694713],"type":"Point"}
}