{
  "type": "Feature",
  "properties": {
    "date:inception_lower": "1980-01-01",
    "date:inception_upper": "1980-01-01",
    "iso:country": "GB",
    "wof:name": "NG17 8AQ",
    "wof:placetype": "postalcode"
  },
  "geometry": {"coordinates":[-1.254785,53.099443],"type":"Point"}
}
