{
  "type": "Feature",
  "properties": {
    "iso:country":"GB",
    "wof:name":"SY11 1BJ",
    "wof:placetype":"postalcode"
},
  "geometry": {"coordinates":[-3.06039995743313,52.86343503375037],"type":"Point"}
}