{
  "type": "Feature",
  "properties": {
    "iso:country":"GB",
    "wof:name":"G63 0RF",
    "wof:placetype":"postalcode"
},
  "geometry": {"coordinates":[-4.33868400358419,56.06906076922223],"type":"Point"}
}