{
  "type": "Feature",
  "properties": {
    "iso:country": "GB",
    "wof:name": "G63 0RF",
    "wof:placetype": "postalcode"
  },
  "geometry": {"coordinates":[-4.338684,56.069061],"type":"Point"}
}
