{
  "type": "Feature",
  "properties": {
    "iso:country":"GB",
    "wof:name":"G78 3HW",
    "wof:placetype":"postalcode"
},
  "geometry": {"coordinates":[-4.42417959474791,55.78051141738001],"type":"Point"}
}