{
  "type": "Feature",
  "properties": {
    "iso:country": "GB",
    "wof:name": "G78 3HW",
    "wof:placetype": "postalcode"
  },
  "geometry": {"coordinates":[-4.42418,55.780511],"type":"Point"}
}
