{
  "type": "Feature",
  "properties": {
    "iso:country":"GB",
    "wof:name":"SG1 4EX",
    "wof:placetype":"postalcode"
},
  "geometry": {"coordinates":[-0.18721782221685,51.92206248372072],"type":"Point"}
}