{
  "type": "Feature",
  "properties": {
    "iso:country":"GB",
    "wof:name":"NG3 5NG",
    "wof:placetype":"postalcode"
},
  "geometry": {"coordinates":[-1.13370379084168,52.97602613915929],"type":"Point"}
}