{
  "type": "Feature",
  "properties": {
    "iso:country":"GB",
    "wof:name":"SE28 0JE",
    "wof:placetype":"postalcode"
},
  "geometry": {"coordinates":[0.08867913521835,51.50020025762529],"type":"Point"}
}