{
  "type": "Feature",
  "properties": {
    "iso:country": "GB",
    "wof:name": "WS1 3LT",
    "wof:placetype": "postalcode"
  },
  "geometry": {"coordinates":[-1.985332,52.579407],"type":"Point"}
}
