{
  "type": "Feature",
  "properties": {
    "iso:country":"GB",
    "wof:name":"WS1 3LT",
    "wof:placetype":"postalcode"
},
  "geometry": {"coordinates":[-1.98533214686729,52.57940744754369],"type":"Point"}
}