{
  "type": "Feature",
  "properties": {
    "iso:country": "GB",
    "wof:name": "AB12 5SP",
    "wof:placetype": "postalcode"
  },
  "geometry": {"coordinates":[-2.113536,57.118001],"type":"Point"}
}
