{
  "type": "Feature",
  "properties": {
    "iso:country":"GB",
    "wof:name":"MK42 0HG",
    "wof:placetype":"postalcode"
},
  "geometry": {"coordinates":[-0.43939998205143,52.12256227447113],"type":"Point"}
}