{
  "type": "Feature",
  "properties": {
    "iso:country":"GB",
    "wof:name":"WV3 7EP",
    "wof:placetype":"postalcode"
},
  "geometry": {"coordinates":[-2.15448928432776,52.57329302445572],"type":"Point"}
}