{
  "type": "Feature",
  "properties": {
    "date:inception_lower": "2021-06-01",
    "date:inception_upper": "2021-06-01",
    "iso:country": "GB",
    "wof:name": "PR8 5FG",
    "wof:placetype": "postalcode"
  },
  "geometry": {"coordinates":[-2.97876,53.625085],"type":"Point"}
}
