{
  "type": "Feature",
  "properties": {
    "iso:country":"GB",
    "wof:name":"OL1 4JU",
    "wof:placetype":"postalcode"
},
  "geometry": {"coordinates":[-2.07695623749997,53.56143796611114],"type":"Point"}
}