{
  "type": "Feature",
  "properties": {
    "iso:country":"GB",
    "wof:name":"N17 0NE",
    "wof:placetype":"postalcode"
},
  "geometry": {"coordinates":[-0.06107276599966,51.60145608436326],"type":"Point"}
}