{
  "type": "Feature",
  "properties": {
    "iso:country": "GB",
    "wof:name": "DL13 1QN",
    "wof:placetype": "postalcode"
  },
  "geometry": {"coordinates":[-2.184372,54.738531],"type":"Point"}
}
