{
  "type": "Feature",
  "properties": {
    "date:inception_lower": "1980-01-01",
    "date:inception_upper": "1980-01-01",
    "iso:country": "GB",
    "wof:name": "DL13 1QN",
    "wof:placetype": "postalcode"
  },
  "geometry": {"coordinates":[-2.184372,54.738531],"type":"Point"}
}
