{
  "type": "Feature",
  "properties": {
    "iso:country":"GB",
    "wof:name":"NG2 7AX",
    "wof:placetype":"postalcode"
},
  "geometry": {"coordinates":[-1.13181541154079,52.91341827084753],"type":"Point"}
}