{
  "type": "Feature",
  "properties": {
    "iso:country": "GB",
    "wof:name": "NG2 7AX",
    "wof:placetype": "postalcode"
  },
  "geometry": {"coordinates":[-1.131815,52.913418],"type":"Point"}
}
