{
  "type": "Feature",
  "properties": {
    "date:inception_lower":"1983-01-01",
    "date:inception_upper":"1983-01-31",
    "iso:country":"GB",
    "wof:name":"NG2 7AX",
    "wof:placetype":"postalcode"
},
  "geometry": {"coordinates":[-1.131815,52.913418],"type":"Point"}
}