{
  "type": "Feature",
  "properties": {
    "iso:country":"GB",
    "wof:name":"UB4 9DG",
    "wof:placetype":"postalcode"
},
  "geometry": {"coordinates":[-0.39783122421668,51.52570518733997],"type":"Point"}
}