{
  "type": "Feature",
  "properties": {
    "iso:country":"GB",
    "wof:name":"ME8 0RT",
    "wof:placetype":"postalcode"
},
  "geometry": {"coordinates":[0.58043384400268,51.36325688687473],"type":"Point"}
}