{
  "type": "Feature",
  "properties": {
    "iso:country": "GB",
    "wof:name": "CM77 8QN",
    "wof:placetype": "postalcode"
  },
  "geometry": {"coordinates":[0.522138,51.845839],"type":"Point"}
}
