{
  "type": "Feature",
  "properties": {
    "iso:country":"GB",
    "wof:name":"CM77 8QN",
    "wof:placetype":"postalcode"
},
  "geometry": {"coordinates":[0.5229314338366,51.84676591957614],"type":"Point"}
}