{
  "type": "Feature",
  "properties": {
    "date:inception_lower": "1998-12-01",
    "date:inception_upper": "1998-12-01",
    "iso:country": "GB",
    "wof:name": "DN6 8SG",
    "wof:placetype": "postalcode"
  },
  "geometry": {"coordinates":[-1.200617,53.587009],"type":"Point"}
}
