{
  "type": "Feature",
  "properties": {
    "iso:country":"GB",
    "wof:name":"DN6 8SG",
    "wof:placetype":"postalcode"
},
  "geometry": {"coordinates":[-1.2006169795471,53.58700862696337],"type":"Point"}
}