{
  "type": "Feature",
  "properties": {
    "iso:country":"GB",
    "wof:name":"S71 2BJ",
    "wof:placetype":"postalcode"
},
  "geometry": {"coordinates":[-1.45953078905639,53.57945134441184],"type":"Point"}
}