{
  "type": "Feature",
  "properties": {
    "date:inception_lower":"1980-01-01",
    "date:inception_upper":"1980-01-31",
    "iso:country":"GB",
    "wof:name":"S71 2BJ",
    "wof:placetype":"postalcode"
},
  "geometry": {"coordinates":[-1.459531,53.579451],"type":"Point"}
}