{
  "type": "Feature",
  "properties": {
    "iso:country":"GB",
    "wof:name":"W6 0BP",
    "wof:placetype":"postalcode"
},
  "geometry": {"coordinates":[-0.23134695962862,51.50071532946831],"type":"Point"}
}