{
  "type": "Feature",
  "properties": {
    "iso:country":"GB",
    "wof:name":"BB10 2LL",
    "wof:placetype":"postalcode"
},
  "geometry": {"coordinates":[-2.23477398003734,53.81867031215501],"type":"Point"}
}