{
  "type": "Feature",
  "properties": {
    "iso:country": "GB",
    "wof:name": "L22 4QS",
    "wof:placetype": "postalcode"
  },
  "geometry": {"coordinates":[-3.019782,53.479405],"type":"Point"}
}
