{
  "type": "Feature",
  "properties": {
    "iso:country":"GB",
    "wof:name":"LA14 5DG",
    "wof:placetype":"postalcode"
},
  "geometry": {"coordinates":[-3.22676816076483,54.12539150344022],"type":"Point"}
}