{
  "type": "Feature",
  "properties": {
    "iso:country": "GB",
    "wof:name": "BA4 6RD",
    "wof:placetype": "postalcode"
  },
  "geometry": {"coordinates":[-2.537713,51.127462],"type":"Point"}
}
