{
  "type": "Feature",
  "properties": {
    "iso:country":"GB",
    "wof:name":"NR19 1HX",
    "wof:placetype":"postalcode"
},
  "geometry": {"coordinates":[0.94871575597744,52.66378085038667],"type":"Point"}
}