{
  "type": "Feature",
  "properties": {
    "iso:country":"GB",
    "wof:name":"B21 9EA",
    "wof:placetype":"postalcode"
},
  "geometry": {"coordinates":[-1.9291667428855,52.50510404854622],"type":"Point"}
}