{
  "type": "Feature",
  "properties": {
    "iso:country":"GB",
    "wof:name":"CM2 9EA",
    "wof:placetype":"postalcode"
},
  "geometry": {"coordinates":[0.47173677596356,51.71686142661255],"type":"Point"}
}