{
  "type": "Feature",
  "properties": {
    "iso:country":"GB",
    "wof:name":"IV3 5EP",
    "wof:placetype":"postalcode"
},
  "geometry": {"coordinates":[-4.23648528978567,57.47270858584364],"type":"Point"}
}