{
  "type": "Feature",
  "properties": {
    "iso:country":"GB",
    "wof:name":"NR32 5DQ",
    "wof:placetype":"postalcode"
},
  "geometry": {"coordinates":[1.72224769223115,52.49932959539502],"type":"Point"}
}