{
  "type": "Feature",
  "properties": {
    "iso:country":"GB",
    "wof:name":"E16 3PY",
    "wof:placetype":"postalcode"
},
  "geometry": {"coordinates":[0.02460494634802,51.51611701940259],"type":"Point"}
}