{
  "type": "Feature",
  "properties": {
    "iso:country": "GB",
    "wof:name": "E16 3PY",
    "wof:placetype": "postalcode"
  },
  "geometry": {"coordinates":[0.024605,51.516117],"type":"Point"}
}
