{
  "type": "Feature",
  "properties": {
    "iso:country": "GB",
    "wof:name": "NP44 8SU",
    "wof:placetype": "postalcode"
  },
  "geometry": {"coordinates":[-3.010225,51.648445],"type":"Point"}
}
