{
  "type": "Feature",
  "properties": {
    "date:inception_lower": "2008-10-01",
    "date:inception_upper": "2008-10-01",
    "iso:country": "GB",
    "wof:name": "WD6 2BY",
    "wof:placetype": "postalcode"
  },
  "geometry": {"coordinates":[-0.254149,51.653027],"type":"Point"}
}
