{
  "type": "Feature",
  "properties": {
    "iso:country":"GB",
    "wof:name":"SL1 3XS",
    "wof:placetype":"postalcode"
},
  "geometry": {"coordinates":[-0.61615325342893,51.51377258591167],"type":"Point"}
}