{
  "type": "Feature",
  "properties": {
    "iso:country":"GB",
    "wof:name":"BB5 2AF",
    "wof:placetype":"postalcode"
},
  "geometry": {"coordinates":[-2.35586883834709,53.75123137140221],"type":"Point"}
}