{
  "type": "Feature",
  "properties": {
    "iso:country":"GB",
    "wof:name":"TN16 1AA",
    "wof:placetype":"postalcode"
},
  "geometry": {"coordinates":[0.0710395724589,51.26806371157753],"type":"Point"}
}