{
  "type": "Feature",
  "properties": {
    "iso:country": "GB",
    "wof:name": "TN16 1AA",
    "wof:placetype": "postalcode"
  },
  "geometry": {"coordinates":[0.071192,51.267988],"type":"Point"}
}
