{
  "type": "Feature",
  "properties": {
    "iso:country":"GB",
    "wof:name":"SG12 9DZ",
    "wof:placetype":"postalcode"
},
  "geometry": {"coordinates":[-0.03428346728372,51.8128616659404],"type":"Point"}
}