{
  "type": "Feature",
  "properties": {
    "iso:country":"GB",
    "wof:name":"TN23 7SE",
    "wof:placetype":"postalcode"
},
  "geometry": {"coordinates":[0.87108873510228,51.14018698518387],"type":"Point"}
}