{
  "type": "Feature",
  "properties": {
    "iso:country": "GB",
    "wof:name": "BD23 5DN",
    "wof:placetype": "postalcode"
  },
  "geometry": {"coordinates":[-1.992312,54.074022],"type":"Point"}
}
