{
  "type": "Feature",
  "properties": {
    "date:inception_lower":"1980-01-01",
    "date:inception_upper":"1980-01-31",
    "iso:country":"GB",
    "wof:name":"FY4 4TR",
    "wof:placetype":"postalcode"
},
  "geometry": {"coordinates":[-2.996695,53.799564],"type":"Point"}
}