{
  "type": "Feature",
  "properties": {
    "iso:country":"GB",
    "wof:name":"SR2 0LP",
    "wof:placetype":"postalcode"
},
  "geometry": {"coordinates":[-1.36418612762804,54.86743849750094],"type":"Point"}
}