{
  "type": "Feature",
  "properties": {
    "iso:country": "GB",
    "wof:name": "SS2 6YH",
    "wof:placetype": "postalcode"
  },
  "geometry": {"coordinates":[0.696703,51.567849],"type":"Point"}
}
