{
  "type": "Feature",
  "properties": {
    "iso:country":"GB",
    "wof:name":"SS2 6YH",
    "wof:placetype":"postalcode"
},
  "geometry": {"coordinates":[0.70075840198301,51.56760661675094],"type":"Point"}
}