{
  "type": "Feature",
  "properties": {
    "date:inception_lower":"1980-01-01",
    "date:inception_upper":"1980-01-31",
    "iso:country":"GB",
    "wof:name":"WN7 1UA",
    "wof:placetype":"postalcode"
},
  "geometry": {"coordinates":[-2.513925,53.510445],"type":"Point"}
}