{
  "type": "Feature",
  "properties": {
    "iso:country":"GB",
    "wof:name":"EX16 7BR",
    "wof:placetype":"postalcode"
},
  "geometry": {"coordinates":[-3.38556297020077,50.91952392878447],"type":"Point"}
}