{
  "type": "Feature",
  "properties": {
    "iso:country":"GB",
    "wof:name":"WF16 9QP",
    "wof:placetype":"postalcode"
},
  "geometry": {"coordinates":[-1.67518630647536,53.70847475908597],"type":"Point"}
}