{
  "type": "Feature",
  "properties": {
    "iso:country":"GB",
    "wof:name":"NG12 5AR",
    "wof:placetype":"postalcode"
},
  "geometry": {"coordinates":[-1.10141675036649,52.8567193990425],"type":"Point"}
}