{
  "type": "Feature",
  "properties": {
    "iso:country": "GB",
    "wof:name": "NG12 5AR",
    "wof:placetype": "postalcode"
  },
  "geometry": {"coordinates":[-1.101417,52.856719],"type":"Point"}
}
