{
  "type": "Feature",
  "properties": {
    "iso:country":"GB",
    "wof:name":"G44 3TN",
    "wof:placetype":"postalcode"
},
  "geometry": {"coordinates":[-4.27624442752877,55.80510898514145],"type":"Point"}
}