{
  "type": "Feature",
  "properties": {
    "date:inception_lower": "1980-01-01",
    "date:inception_upper": "1980-01-01",
    "iso:country": "GB",
    "wof:name": "G44 3TN",
    "wof:placetype": "postalcode"
  },
  "geometry": {"coordinates":[-4.276244,55.805109],"type":"Point"}
}
