{
  "type": "Feature",
  "properties": {
    "iso:country":"GB",
    "wof:name":"CT6 7TW",
    "wof:placetype":"postalcode"
},
  "geometry": {"coordinates":[1.11180057606334,51.35667179576062],"type":"Point"}
}