{
  "type": "Feature",
  "properties": {
    "date:inception_lower": "1992-08-01",
    "date:inception_upper": "1992-08-01",
    "iso:country": "GB",
    "wof:name": "LE7 2LF",
    "wof:placetype": "postalcode"
  },
  "geometry": {"coordinates":[-1.073837,52.696445],"type":"Point"}
}
