{
  "type": "Feature",
  "properties": {
    "iso:country": "GB",
    "wof:name": "EC1V 7JL",
    "wof:placetype": "postalcode"
  },
  "geometry": {"coordinates":[-0.10588,51.531687],"type":"Point"}
}
