{
  "type": "Feature",
  "properties": {
    "iso:country":"GB",
    "wof:name":"LA1 2HN",
    "wof:placetype":"postalcode"
},
  "geometry": {"coordinates":[-2.80084655801994,54.0655259360277],"type":"Point"}
}