{
  "type": "Feature",
  "properties": {
    "iso:country":"GB",
    "wof:name":"NW5 2JX",
    "wof:placetype":"postalcode"
},
  "geometry": {"coordinates":[-0.13957004378465,51.54735123231327],"type":"Point"}
}