{
  "type": "Feature",
  "properties": {
    "iso:country":"GB",
    "wof:name":"DN5 9JA",
    "wof:placetype":"postalcode"
},
  "geometry": {"coordinates":[-1.16000355084135,53.5401066473316],"type":"Point"}
}