{
  "type": "Feature",
  "properties": {
    "date:inception_lower": "2008-01-01",
    "date:inception_upper": "2008-01-01",
    "iso:country": "GB",
    "wof:name": "DN5 9JA",
    "wof:placetype": "postalcode"
  },
  "geometry": {"coordinates":[-1.160004,53.540107],"type":"Point"}
}
