{
  "type": "Feature",
  "properties": {
    "date:inception_lower": "2018-10-01",
    "date:inception_upper": "2018-10-01",
    "iso:country": "GB",
    "wof:name": "WA10 5QZ",
    "wof:placetype": "postalcode"
  },
  "geometry": {"coordinates":[-2.771894,53.450494],"type":"Point"}
}
