{
  "type": "Feature",
  "properties": {
    "iso:country": "GB",
    "wof:name": "ME4 3AG",
    "wof:placetype": "postalcode"
  },
  "geometry": {"coordinates":[0.536759,51.408963],"type":"Point"}
}
