{
  "type": "Feature",
  "properties": {
    "iso:country":"GB",
    "wof:name":"YO25 8TG",
    "wof:placetype":"postalcode"
},
  "geometry": {"coordinates":[-0.22319966750697,53.97807365849809],"type":"Point"}
}