{
  "type": "Feature",
  "properties": {
    "iso:country": "GB",
    "wof:name": "MK42 9DZ",
    "wof:placetype": "postalcode"
  },
  "geometry": {"coordinates":[-0.480883,52.12733],"type":"Point"}
}
