{
  "type": "Feature",
  "properties": {
    "iso:country":"GB",
    "wof:name":"BS5 6BT",
    "wof:placetype":"postalcode"
},
  "geometry": {"coordinates":[-2.56007763756221,51.46697710934725],"type":"Point"}
}