{
  "type": "Feature",
  "properties": {
    "iso:country":"GB",
    "wof:name":"CT20 2DY",
    "wof:placetype":"postalcode"
},
  "geometry": {"coordinates":[1.17482343779465,51.07663315497047],"type":"Point"}
}