{
  "type": "Feature",
  "properties": {
    "iso:country":"GB",
    "wof:name":"N16 7AE",
    "wof:placetype":"postalcode"
},
  "geometry": {"coordinates":[-0.07350724839451,51.56080795147297],"type":"Point"}
}