{
  "type": "Feature",
  "properties": {
    "iso:country":"GB",
    "wof:name":"G72 0HF",
    "wof:placetype":"postalcode"
},
  "geometry": {"coordinates":[-4.09828714276365,55.78407305053867],"type":"Point"}
}