{
  "type": "Feature",
  "properties": {
    "iso:country": "GB",
    "wof:name": "TA21 0DT",
    "wof:placetype": "postalcode"
  },
  "geometry": {"coordinates":[-3.252831,50.976356],"type":"Point"}
}
