{
  "type": "Feature",
  "properties": {
    "date:inception_lower": "1980-01-01",
    "date:inception_upper": "1980-01-01",
    "iso:country": "GB",
    "wof:name": "LN5 0NP",
    "wof:placetype": "postalcode"
  },
  "geometry": {"coordinates":[-0.557162,53.075695],"type":"Point"}
}
