{
  "type": "Feature",
  "properties": {
    "iso:country": "GB",
    "wof:name": "LN5 0NP",
    "wof:placetype": "postalcode"
  },
  "geometry": {"coordinates":[-0.557058,53.075667],"type":"Point"}
}
