{
  "type": "Feature",
  "properties": {
    "iso:country":"GB",
    "wof:name":"LN5 0NP",
    "wof:placetype":"postalcode"
},
  "geometry": {"coordinates":[-0.55706304623373,53.07564433771945],"type":"Point"}
}