{
  "type": "Feature",
  "properties": {
    "iso:country":"GB",
    "wof:name":"E15 1FF",
    "wof:placetype":"postalcode"
},
  "geometry": {"coordinates":[-0.00013573367005,51.54324967018714],"type":"Point"}
}