{
  "type": "Feature",
  "properties": {
    "date:inception_lower": "2015-09-01",
    "date:inception_upper": "2015-09-01",
    "iso:country": "GB",
    "wof:name": "E15 1FF",
    "wof:placetype": "postalcode"
  },
  "geometry": {"coordinates":[0.000005,51.543205],"type":"Point"}
}
