{
  "type": "Feature",
  "properties": {
    "iso:country":"GB",
    "wof:name":"M13 0GQ",
    "wof:placetype":"postalcode"
},
  "geometry": {"coordinates":[-2.19629927287363,53.45095965433509],"type":"Point"}
}