{
  "type": "Feature",
  "properties": {
    "iso:country":"GB",
    "wof:name":"DD8 2JX",
    "wof:placetype":"postalcode"
},
  "geometry": {"coordinates":[-2.87691935933286,56.64584749657262],"type":"Point"}
}