{
  "type": "Feature",
  "properties": {
    "date:inception_lower": "2008-10-01",
    "date:inception_upper": "2008-10-01",
    "iso:country": "GB",
    "wof:name": "DD8 2JX",
    "wof:placetype": "postalcode"
  },
  "geometry": {"coordinates":[-2.876919,56.645847],"type":"Point"}
}
