{
  "type": "Feature",
  "properties": {
    "iso:country":"GB",
    "wof:name":"BR7 6DE",
    "wof:placetype":"postalcode"
},
  "geometry": {"coordinates":[0.06049184669859,51.42179593749886],"type":"Point"}
}