{
  "type": "Feature",
  "properties": {
    "iso:country":"GB",
    "wof:name":"TS17 0EH",
    "wof:placetype":"postalcode"
},
  "geometry": {"coordinates":[-1.30409409709017,54.53341958262666],"type":"Point"}
}