{
  "type": "Feature",
  "properties": {
    "iso:country":"GB",
    "wof:name":"DG8 9PX",
    "wof:placetype":"postalcode"
},
  "geometry": {"coordinates":[-4.51364283326369,54.76423925335439],"type":"Point"}
}