{
  "type": "Feature",
  "properties": {
    "iso:country":"GB",
    "wof:name":"DE23 4RU",
    "wof:placetype":"postalcode"
},
  "geometry": {"coordinates":[-1.53743575300203,52.89798884141288],"type":"Point"}
}