{
  "type": "Feature",
  "properties": {
    "date:inception_lower": "2005-06-01",
    "date:inception_upper": "2005-06-01",
    "iso:country": "GB",
    "wof:name": "AB39 2RB",
    "wof:placetype": "postalcode"
  },
  "geometry": {"coordinates":[-2.226244,56.965679],"type":"Point"}
}
