{
  "type": "Feature",
  "properties": {
    "iso:country": "GB",
    "wof:name": "DD3 8JY",
    "wof:placetype": "postalcode"
  },
  "geometry": {"coordinates":[-2.977316,56.482159],"type":"Point"}
}
