{
  "type": "Feature",
  "properties": {
    "date:inception_lower":"1980-01-01",
    "date:inception_upper":"1980-01-31",
    "iso:country":"GB",
    "wof:name":"DD3 8JY",
    "wof:placetype":"postalcode"
},
  "geometry": {"coordinates":[-2.977316,56.482159],"type":"Point"}
}