{
  "type": "Feature",
  "properties": {
    "iso:country":"GB",
    "wof:name":"LN8 2AA",
    "wof:placetype":"postalcode"
},
  "geometry": {"coordinates":[-0.5055011639146,53.37727712304002],"type":"Point"}
}