{
  "type": "Feature",
  "properties": {
    "date:inception_lower": "1980-01-01",
    "date:inception_upper": "1980-01-01",
    "iso:country": "GB",
    "wof:name": "GL8 8YL",
    "wof:placetype": "postalcode"
  },
  "geometry": {"coordinates":[-2.219878,51.646804],"type":"Point"}
}
