{
  "type": "Feature",
  "properties": {
    "iso:country":"GB",
    "wof:name":"GL8 8YL",
    "wof:placetype":"postalcode"
},
  "geometry": {"coordinates":[-2.21987800873981,51.64680411756013],"type":"Point"}
}