{
  "type": "Feature",
  "properties": {
    "iso:country": "GB",
    "wof:name": "EX39 1HE",
    "wof:placetype": "postalcode"
  },
  "geometry": {"coordinates":[-4.237941,51.037749],"type":"Point"}
}
