{
  "type": "Feature",
  "properties": {
    "iso:country":"GB",
    "wof:name":"IP31 2QZ",
    "wof:placetype":"postalcode"
},
  "geometry": {"coordinates":[0.77633843807684,52.26186381134797],"type":"Point"}
}