{
  "type": "Feature",
  "properties": {
    "iso:country":"GB",
    "wof:name":"LL36 9ET",
    "wof:placetype":"postalcode"
},
  "geometry": {"coordinates":[-4.08807185952101,52.58442155880739],"type":"Point"}
}