{
  "type": "Feature",
  "properties": {
    "date:inception_lower":"1980-01-01",
    "date:inception_upper":"1980-01-31",
    "iso:country":"GB",
    "wof:name":"LL36 9ET",
    "wof:placetype":"postalcode"
},
  "geometry": {"coordinates":[-4.088072,52.584422],"type":"Point"}
}