{
  "type": "Feature",
  "properties": {
    "date:inception_lower": "1983-03-01",
    "date:inception_upper": "1983-03-01",
    "iso:country": "GB",
    "wof:name": "CV34 4UF",
    "wof:placetype": "postalcode"
  },
  "geometry": {"coordinates":[-1.574192,52.284533],"type":"Point"}
}
