{
  "type": "Feature",
  "properties": {
    "iso:country": "GB",
    "wof:name": "CV34 4UF",
    "wof:placetype": "postalcode"
  },
  "geometry": {"coordinates":[-1.574192,52.284533],"type":"Point"}
}
