{
  "type": "Feature",
  "properties": {
    "iso:country": "GB",
    "wof:name": "G32 0PB",
    "wof:placetype": "postalcode"
  },
  "geometry": {"coordinates":[-4.159337,55.853467],"type":"Point"}
}
