{
  "type": "Feature",
  "properties": {
    "iso:country":"GB",
    "wof:name":"G32 0PB",
    "wof:placetype":"postalcode"
},
  "geometry": {"coordinates":[-4.15933675540415,55.85346686040962],"type":"Point"}
}