{
  "type": "Feature",
  "properties": {
    "date:inception_lower":"2011-05-01",
    "date:inception_upper":"2011-05-31",
    "iso:country":"GB",
    "wof:name":"G32 0PB",
    "wof:placetype":"postalcode"
},
  "geometry": {"coordinates":[-4.159337,55.853467],"type":"Point"}
}