{
  "type": "Feature",
  "properties": {
    "iso:country": "GB",
    "wof:name": "FY5 4LN",
    "wof:placetype": "postalcode"
  },
  "geometry": {"coordinates":[-3.011384,53.884797],"type":"Point"}
}
