{
  "type": "Feature",
  "properties": {
    "iso:country":"GB",
    "wof:name":"FY5 4LN",
    "wof:placetype":"postalcode"
},
  "geometry": {"coordinates":[-3.01138422422502,53.88479730932816],"type":"Point"}
}