{
  "type": "Feature",
  "properties": {
    "date:inception_lower":"1980-01-01",
    "date:inception_upper":"1980-01-31",
    "iso:country":"GB",
    "wof:name":"FY5 4LN",
    "wof:placetype":"postalcode"
},
  "geometry": {"coordinates":[-3.011384,53.884797],"type":"Point"}
}