{
  "type": "Feature",
  "properties": {
    "iso:country":"GB",
    "wof:name":"YO7 2QD",
    "wof:placetype":"postalcode"
},
  "geometry": {"coordinates":[-1.235904493747,54.23944616437201],"type":"Point"}
}