{
  "type": "Feature",
  "properties": {
    "date:inception_lower": "1980-01-01",
    "date:inception_upper": "1980-01-01",
    "iso:country": "GB",
    "wof:name": "KY8 5SN",
    "wof:placetype": "postalcode"
  },
  "geometry": {"coordinates":[-3.048561,56.21484],"type":"Point"}
}
