{
  "type": "Feature",
  "properties": {
    "date:inception_lower": "1980-01-01",
    "date:inception_upper": "1980-01-01",
    "iso:country": "GB",
    "wof:name": "EX31 2NJ",
    "wof:placetype": "postalcode"
  },
  "geometry": {"coordinates":[-4.116341,51.073771],"type":"Point"}
}
