{
  "type": "Feature",
  "properties": {
    "iso:country":"GB",
    "wof:name":"EX31 2NJ",
    "wof:placetype":"postalcode"
},
  "geometry": {"coordinates":[-4.11634103621357,51.07377132307099],"type":"Point"}
}