{
  "type": "Feature",
  "properties": {
    "iso:country": "GB",
    "wof:name": "DH6 2SU",
    "wof:placetype": "postalcode"
  },
  "geometry": {"coordinates":[-1.396904,54.797627],"type":"Point"}
}
