{
  "type": "Feature",
  "properties": {
    "date:inception_lower": "1980-01-01",
    "date:inception_upper": "1980-01-01",
    "iso:country": "GB",
    "wof:name": "SK2 7HP",
    "wof:placetype": "postalcode"
  },
  "geometry": {"coordinates":[-2.128101,53.38549],"type":"Point"}
}
