{
  "type": "Feature",
  "properties": {
    "iso:country":"GB",
    "wof:name":"SK2 7HP",
    "wof:placetype":"postalcode"
},
  "geometry": {"coordinates":[-2.1281010947772,53.38549000787869],"type":"Point"}
}