{
  "type": "Feature",
  "properties": {
    "iso:country":"GB",
    "wof:name":"SM4 5QQ",
    "wof:placetype":"postalcode"
},
  "geometry": {"coordinates":[-0.20223222510245,51.38666097119167],"type":"Point"}
}