{
  "type": "Feature",
  "properties": {
    "iso:country":"GB",
    "wof:name":"KA8 8AQ",
    "wof:placetype":"postalcode"
},
  "geometry": {"coordinates":[-4.63458354490734,55.46726571815376],"type":"Point"}
}