{
  "type": "Feature",
  "properties": {
    "iso:country":"GB",
    "wof:name":"BS48 2SP",
    "wof:placetype":"postalcode"
},
  "geometry": {"coordinates":[-2.74069203211118,51.43069147396116],"type":"Point"}
}