{
  "type": "Feature",
  "properties": {
    "iso:country":"GB",
    "wof:name":"E4 9AB",
    "wof:placetype":"postalcode"
},
  "geometry": {"coordinates":[-0.01726056268434,51.60942889286546],"type":"Point"}
}