{
  "type": "Feature",
  "properties": {
    "iso:country":"GB",
    "wof:name":"TA9 3RZ",
    "wof:placetype":"postalcode"
},
  "geometry": {"coordinates":[-2.98893249268287,51.20803311673024],"type":"Point"}
}