{
  "type": "Feature",
  "properties": {
    "iso:country": "GB",
    "wof:name": "TA9 3RZ",
    "wof:placetype": "postalcode"
  },
  "geometry": {"coordinates":[-2.988956,51.208028],"type":"Point"}
}
