{
  "type": "Feature",
  "properties": {
    "iso:country": "GB",
    "wof:name": "S61 4RQ",
    "wof:placetype": "postalcode"
  },
  "geometry": {"coordinates":[-1.356732,53.442218],"type":"Point"}
}
