{
  "type": "Feature",
  "properties": {
    "date:inception_lower":"1995-01-01",
    "date:inception_upper":"1995-01-31",
    "iso:country":"GB",
    "wof:name":"S61 4RQ",
    "wof:placetype":"postalcode"
},
  "geometry": {"coordinates":[-1.356732,53.442218],"type":"Point"}
}