{
  "type": "Feature",
  "properties": {
    "iso:country":"GB",
    "wof:name":"CM24 8JL",
    "wof:placetype":"postalcode"
},
  "geometry": {"coordinates":[0.19264870098912,51.90393480483731],"type":"Point"}
}