{
  "type": "Feature",
  "properties": {
    "iso:country": "GB",
    "wof:name": "OX16 9QJ",
    "wof:placetype": "postalcode"
  },
  "geometry": {"coordinates":[-1.352301,52.05734],"type":"Point"}
}
