{
  "type": "Feature",
  "properties": {
    "iso:country":"GB",
    "wof:name":"TF4 2LU",
    "wof:placetype":"postalcode"
},
  "geometry": {"coordinates":[-2.48426213433684,52.6660139885157],"type":"Point"}
}