{
  "type": "Feature",
  "properties": {
    "iso:country": "GB",
    "wof:name": "TF4 2LU",
    "wof:placetype": "postalcode"
  },
  "geometry": {"coordinates":[-2.484262,52.666014],"type":"Point"}
}
