{
  "type": "Feature",
  "properties": {
    "iso:country":"GB",
    "wof:name":"CW8 4NB",
    "wof:placetype":"postalcode"
},
  "geometry": {"coordinates":[-2.55052189993112,53.276315335398],"type":"Point"}
}