{
  "type": "Feature",
  "properties": {
    "iso:country": "GB",
    "wof:name": "DD10 0HP",
    "wof:placetype": "postalcode"
  },
  "geometry": {"coordinates":[-2.350464,56.789146],"type":"Point"}
}
