{
  "type": "Feature",
  "properties": {
    "iso:country":"GB",
    "wof:name":"DD10 0HP",
    "wof:placetype":"postalcode"
},
  "geometry": {"coordinates":[-2.35046442041223,56.78914621860046],"type":"Point"}
}