{
  "type": "Feature",
  "properties": {
    "date:inception_lower": "1990-07-01",
    "date:inception_upper": "1990-07-01",
    "iso:country": "GB",
    "wof:name": "WA8 9FZ",
    "wof:placetype": "postalcode"
  },
  "geometry": {"coordinates":[-2.739255,53.382325],"type":"Point"}
}
