{
  "type": "Feature",
  "properties": {
    "iso:country":"GB",
    "wof:name":"WA8 9FZ",
    "wof:placetype":"postalcode"
},
  "geometry": {"coordinates":[-2.73925523654263,53.38232488002956],"type":"Point"}
}