{
  "type": "Feature",
  "properties": {
    "iso:country":"GB",
    "wof:name":"HG2 9AY",
    "wof:placetype":"postalcode"
},
  "geometry": {"coordinates":[-1.53920196391258,53.98416665079559],"type":"Point"}
}