{
  "type": "Feature",
  "properties": {
    "date:inception_lower": "2021-07-01",
    "date:inception_upper": "2021-07-01",
    "iso:country": "GB",
    "wof:name": "SR1 2BT",
    "wof:placetype": "postalcode"
  },
  "geometry": {"coordinates":[-1.361783,54.914937],"type":"Point"}
}
