{
  "type": "Feature",
  "properties": {
    "date:inception_lower": "2014-07-01",
    "date:inception_upper": "2014-07-01",
    "iso:country": "GB",
    "wof:name": "ME3 9XN",
    "wof:placetype": "postalcode"
  },
  "geometry": {"coordinates":[0.507423,51.386104],"type":"Point"}
}
