{
  "type": "Feature",
  "properties": {
    "date:inception_lower":"1980-01-01",
    "date:inception_upper":"1980-01-31",
    "iso:country":"GB",
    "wof:name":"LN10 6XR",
    "wof:placetype":"postalcode"
},
  "geometry": {"coordinates":[-0.252781,53.140197],"type":"Point"}
}