{
  "type": "Feature",
  "properties": {
    "iso:country":"GB",
    "wof:name":"LN10 6XR",
    "wof:placetype":"postalcode"
},
  "geometry": {"coordinates":[-0.25278149097492,53.14019659076382],"type":"Point"}
}