{
  "type": "Feature",
  "properties": {
    "iso:country":"GB",
    "wof:name":"NG3 3ET",
    "wof:placetype":"postalcode"
},
  "geometry": {"coordinates":[-1.12295528663586,52.97583048897106],"type":"Point"}
}