{
  "type": "Feature",
  "properties": {
    "iso:country": "GB",
    "wof:name": "NG3 3ET",
    "wof:placetype": "postalcode"
  },
  "geometry": {"coordinates":[-1.122955,52.97583],"type":"Point"}
}
