{
  "type": "Feature",
  "properties": {
    "iso:country":"GB",
    "wof:name":"HA4 0HX",
    "wof:placetype":"postalcode"
},
  "geometry": {"coordinates":[-0.38944919955741,51.5618379605915],"type":"Point"}
}