{
  "type": "Feature",
  "properties": {
    "iso:country": "GB",
    "wof:name": "M44 5YT",
    "wof:placetype": "postalcode"
  },
  "geometry": {"coordinates":[-2.438584,53.43241],"type":"Point"}
}
