{
  "type": "Feature",
  "properties": {
    "iso:country": "GB",
    "wof:name": "DD3 6QP",
    "wof:placetype": "postalcode"
  },
  "geometry": {"coordinates":[-2.981173,56.471168],"type":"Point"}
}
