{
  "type": "Feature",
  "properties": {
    "iso:country":"GB",
    "wof:name":"DD3 6QP",
    "wof:placetype":"postalcode"
},
  "geometry": {"coordinates":[-2.98117281122699,56.47116764238326],"type":"Point"}
}