{
  "type": "Feature",
  "properties": {
    "iso:country":"GB",
    "wof:name":"HG3 3RH",
    "wof:placetype":"postalcode"
},
  "geometry": {"coordinates":[-1.49999005544897,54.09027157985281],"type":"Point"}
}