{
  "type": "Feature",
  "properties": {
    "iso:country":"GB",
    "wof:name":"L37 2EA",
    "wof:placetype":"postalcode"
},
  "geometry": {"coordinates":[-3.07288280569668,53.55517466829324],"type":"Point"}
}