{
  "type": "Feature",
  "properties": {
    "iso:country": "GB",
    "wof:name": "WF11 0BD",
    "wof:placetype": "postalcode"
  },
  "geometry": {"coordinates":[-1.265099,53.701629],"type":"Point"}
}
