{
  "type": "Feature",
  "properties": {
    "date:inception_lower": "2015-12-01",
    "date:inception_upper": "2015-12-01",
    "iso:country": "GB",
    "wof:name": "WF11 0BD",
    "wof:placetype": "postalcode"
  },
  "geometry": {"coordinates":[-1.264632,53.701473],"type":"Point"}
}
