{
  "type": "Feature",
  "properties": {
    "date:inception_lower":"2015-12-01",
    "date:inception_upper":"2015-12-31",
    "iso:country":"GB",
    "wof:name":"WF11 0BD",
    "wof:placetype":"postalcode"
},
  "geometry": {"coordinates":[-1.265099,53.701629],"type":"Point"}
}