{
  "type": "Feature",
  "properties": {
    "iso:country":"GB",
    "wof:name":"WF11 0BD",
    "wof:placetype":"postalcode"
},
  "geometry": {"coordinates":[-1.26602967609219,53.70194889649796],"type":"Point"}
}