{
  "type": "Feature",
  "properties": {
    "date:inception_lower":"2007-01-01",
    "date:inception_upper":"2007-01-31",
    "iso:country":"GB",
    "wof:name":"WF11 8UL",
    "wof:placetype":"postalcode"
},
  "geometry": {"coordinates":[-1.274495,53.724085],"type":"Point"}
}