{
  "type": "Feature",
  "properties": {
    "iso:country":"GB",
    "wof:name":"DN21 4QP",
    "wof:placetype":"postalcode"
},
  "geometry": {"coordinates":[-0.5330843532949,53.49013903579412],"type":"Point"}
}