{
  "type": "Feature",
  "properties": {
    "iso:country": "GB",
    "wof:name": "DN21 4QP",
    "wof:placetype": "postalcode"
  },
  "geometry": {"coordinates":[-0.533084,53.490139],"type":"Point"}
}
