{
  "type": "Feature",
  "properties": {
    "date:inception_lower": "1994-05-01",
    "date:inception_upper": "1994-05-01",
    "iso:country": "GB",
    "wof:name": "DN21 4QP",
    "wof:placetype": "postalcode"
  },
  "geometry": {"coordinates":[-0.533084,53.490139],"type":"Point"}
}
