{
  "type": "Feature",
  "properties": {
    "iso:country": "GB",
    "wof:name": "B33 9JH",
    "wof:placetype": "postalcode"
  },
  "geometry": {"coordinates":[-1.797095,52.491098],"type":"Point"}
}
