{
  "type": "Feature",
  "properties": {
    "date:inception_lower": "1997-12-01",
    "date:inception_upper": "1997-12-01",
    "iso:country": "GB",
    "wof:name": "LA15 8QY",
    "wof:placetype": "postalcode"
  },
  "geometry": {"coordinates":[-3.17341,54.15358],"type":"Point"}
}
