{
  "type": "Feature",
  "properties": {
    "iso:country": "GB",
    "wof:name": "LA15 8QY",
    "wof:placetype": "postalcode"
  },
  "geometry": {"coordinates":[-3.17341,54.15358],"type":"Point"}
}
