{
  "type": "Feature",
  "properties": {
    "iso:country":"GB",
    "wof:name":"DN35 7HE",
    "wof:placetype":"postalcode"
},
  "geometry": {"coordinates":[-0.04310469676264,53.56731067086992],"type":"Point"}
}