{
  "type": "Feature",
  "properties": {
    "iso:country":"GB",
    "wof:name":"DL14 6XB",
    "wof:placetype":"postalcode"
},
  "geometry": {"coordinates":[-1.6679967611456,54.64760563411461],"type":"Point"}
}