{
  "type": "Feature",
  "properties": {
    "iso:country":"GB",
    "wof:name":"KY12 8QQ",
    "wof:placetype":"postalcode"
},
  "geometry": {"coordinates":[-3.49545622922705,56.05961558022643],"type":"Point"}
}