{
  "type": "Feature",
  "properties": {
    "iso:country":"GB",
    "wof:name":"FK9 5PP",
    "wof:placetype":"postalcode"
},
  "geometry": {"coordinates":[-3.90739672120679,56.13397667349508],"type":"Point"}
}