{
  "type": "Feature",
  "properties": {
    "iso:country": "GB",
    "wof:name": "LN8 3LZ",
    "wof:placetype": "postalcode"
  },
  "geometry": {"coordinates":[-0.407722,53.407643],"type":"Point"}
}
