{
  "type": "Feature",
  "properties": {
    "iso:country":"GB",
    "wof:name":"LN8 3LZ",
    "wof:placetype":"postalcode"
},
  "geometry": {"coordinates":[-0.41585030675556,53.4054180817114],"type":"Point"}
}