{
  "type": "Feature",
  "properties": {
    "iso:country":"GB",
    "wof:name":"B23 5UL",
    "wof:placetype":"postalcode"
},
  "geometry": {"coordinates":[-1.83467000168603,52.52937263021905],"type":"Point"}
}