{
  "type": "Feature",
  "properties": {
    "iso:country":"GB",
    "wof:name":"TS29 6NW",
    "wof:placetype":"postalcode"
},
  "geometry": {"coordinates":[-1.38632075599418,54.69010179510655],"type":"Point"}
}