{
  "type": "Feature",
  "properties": {
    "iso:country":"GB",
    "wof:name":"DE13 0TF",
    "wof:placetype":"postalcode"
},
  "geometry": {"coordinates":[-1.64739148664004,52.82148830229215],"type":"Point"}
}