{
  "type": "Feature",
  "properties": {
    "iso:country":"GB",
    "wof:name":"LL21 0DT",
    "wof:placetype":"postalcode"
},
  "geometry": {"coordinates":[-3.36985259711817,52.97994217237219],"type":"Point"}
}