{
  "type": "Feature",
  "properties": {
    "date:inception_lower": "1980-01-01",
    "date:inception_upper": "1980-01-01",
    "iso:country": "GB",
    "wof:name": "LS9 0NJ",
    "wof:placetype": "postalcode"
  },
  "geometry": {"coordinates":[-1.491065,53.799468],"type":"Point"}
}
