{
  "type": "Feature",
  "properties": {
    "iso:country":"GB",
    "wof:name":"LS9 0NJ",
    "wof:placetype":"postalcode"
},
  "geometry": {"coordinates":[-1.49106514155519,53.79946850164215],"type":"Point"}
}