{
  "type": "Feature",
  "properties": {
    "iso:country":"GB",
    "wof:name":"BS14 8DJ",
    "wof:placetype":"postalcode"
},
  "geometry": {"coordinates":[-2.55253957008382,51.41140852052393],"type":"Point"}
}