{
  "type": "Feature",
  "properties": {
    "date:inception_lower": "1990-08-01",
    "date:inception_upper": "1990-08-01",
    "iso:country": "GB",
    "wof:name": "AB51 0AQ",
    "wof:placetype": "postalcode"
  },
  "geometry": {"coordinates":[-2.3303,57.388405],"type":"Point"}
}
