{
  "type": "Feature",
  "properties": {
    "date:inception_lower": "2002-12-01",
    "date:inception_upper": "2002-12-01",
    "iso:country": "GB",
    "wof:name": "PO12 4ZN",
    "wof:placetype": "postalcode"
  },
  "geometry": {"coordinates":[-1.149617,50.804557],"type":"Point"}
}
