{
  "type": "Feature",
  "properties": {
    "iso:country":"GB",
    "wof:name":"WV3 7JU",
    "wof:placetype":"postalcode"
},
  "geometry": {"coordinates":[-2.16051976005738,52.57610779445128],"type":"Point"}
}