{
  "type": "Feature",
  "properties": {
    "iso:country":"GB",
    "wof:name":"L23 9SS",
    "wof:placetype":"postalcode"
},
  "geometry": {"coordinates":[-3.00623999041846,53.48724159778919],"type":"Point"}
}