{
  "type": "Feature",
  "properties": {
    "iso:country": "GB",
    "wof:name": "AL10 8HS",
    "wof:placetype": "postalcode"
  },
  "geometry": {"coordinates":[-0.23162,51.74169],"type":"Point"}
}
