{
  "type": "Feature",
  "properties": {
    "date:inception_lower": "1985-04-01",
    "date:inception_upper": "1985-04-01",
    "iso:country": "GB",
    "wof:name": "AL10 8HS",
    "wof:placetype": "postalcode"
  },
  "geometry": {"coordinates":[-0.231694,51.741664],"type":"Point"}
}
