{
  "type": "Feature",
  "properties": {
    "iso:country": "GB",
    "wof:name": "AL10 8HS",
    "wof:placetype": "postalcode"
  },
  "geometry": {"coordinates":[-0.231694,51.741664],"type":"Point"}
}
