{
  "type": "Feature",
  "properties": {
    "iso:country":"GB",
    "wof:name":"BD4 0EF",
    "wof:placetype":"postalcode"
},
  "geometry": {"coordinates":[-1.7073229848958,53.7820978856772],"type":"Point"}
}