{
  "type": "Feature",
  "properties": {
    "date:inception_lower": "2021-12-01",
    "date:inception_upper": "2021-12-01",
    "iso:country": "GB",
    "wof:name": "HA9 6FA",
    "wof:placetype": "postalcode"
  },
  "geometry": {"coordinates":[-0.273983,51.544624],"type":"Point"}
}
