{
  "type": "Feature",
  "properties": {
    "iso:country":"GB",
    "wof:name":"N1 6NG",
    "wof:placetype":"postalcode"
},
  "geometry": {"coordinates":[-0.08003801421245,51.52768758578205],"type":"Point"}
}