{
  "type": "Feature",
  "properties": {
    "iso:country":"GB",
    "wof:name":"YO31 8SN",
    "wof:placetype":"postalcode"
},
  "geometry": {"coordinates":[-1.07036800704589,53.97163161194503],"type":"Point"}
}