{
  "type": "Feature",
  "properties": {
    "iso:country":"GB",
    "wof:name":"AL10 0TS",
    "wof:placetype":"postalcode"
},
  "geometry": {"coordinates":[-0.217162439278,51.77027706468103],"type":"Point"}
}