{
  "type": "Feature",
  "properties": {
    "iso:country":"GB",
    "wof:name":"NE28 7AW",
    "wof:placetype":"postalcode"
},
  "geometry": {"coordinates":[-1.51077456940168,54.99986610955555],"type":"Point"}
}