{
  "type": "Feature",
  "properties": {
    "iso:country":"GB",
    "wof:name":"HA8 9NG",
    "wof:placetype":"postalcode"
},
  "geometry": {"coordinates":[-0.26528978109689,51.61413867407237],"type":"Point"}
}