{
  "type": "Feature",
  "properties": {
    "iso:country":"GB",
    "wof:name":"NP44 4RB",
    "wof:placetype":"postalcode"
},
  "geometry": {"coordinates":[-3.04329573520228,51.64971984325608],"type":"Point"}
}