{
  "type": "Feature",
  "properties": {
    "iso:country":"GB",
    "wof:name":"CF14 9EA",
    "wof:placetype":"postalcode"
},
  "geometry": {"coordinates":[-3.19527274629442,51.5394166362511],"type":"Point"}
}