{
  "type": "Feature",
  "properties": {
    "iso:country":"GB",
    "wof:name":"IG5 0TB",
    "wof:placetype":"postalcode"
},
  "geometry": {"coordinates":[0.06886226340547,51.59100928958774],"type":"Point"}
}