{
  "type": "Feature",
  "properties": {
    "iso:country": "GB",
    "wof:name": "IP14 3ED",
    "wof:placetype": "postalcode"
  },
  "geometry": {"coordinates":[0.910725,52.158466],"type":"Point"}
}
