{
  "type": "Feature",
  "properties": {
    "iso:country":"GB",
    "wof:name":"SY1 4RN",
    "wof:placetype":"postalcode"
},
  "geometry": {"coordinates":[-2.72281510977148,52.72859043117723],"type":"Point"}
}