{
  "type": "Feature",
  "properties": {
    "iso:country": "GB",
    "wof:name": "WF15 7NT",
    "wof:placetype": "postalcode"
  },
  "geometry": {"coordinates":[-1.694997,53.707089],"type":"Point"}
}
