{
  "type": "Feature",
  "properties": {
    "iso:country":"GB",
    "wof:name":"WF15 7NT",
    "wof:placetype":"postalcode"
},
  "geometry": {"coordinates":[-1.69499685350676,53.70708868316559],"type":"Point"}
}