{
  "type": "Feature",
  "properties": {
    "iso:country": "GB",
    "wof:name": "ME10 3ED",
    "wof:placetype": "postalcode"
  },
  "geometry": {"coordinates":[0.734903,51.341999],"type":"Point"}
}
