{
  "type": "Feature",
  "properties": {
    "iso:country":"GB",
    "wof:name":"ME10 3ED",
    "wof:placetype":"postalcode"
},
  "geometry": {"coordinates":[0.73491699478231,51.34202360662493],"type":"Point"}
}