{
  "type": "Feature",
  "properties": {
    "date:inception_lower":"1980-01-01",
    "date:inception_upper":"1980-01-31",
    "iso:country":"GB",
    "wof:name":"ME10 3ED",
    "wof:placetype":"postalcode"
},
  "geometry": {"coordinates":[0.734903,51.341999],"type":"Point"}
}