{
  "type": "Feature",
  "properties": {
    "iso:country":"GB",
    "wof:name":"OX11 8EG",
    "wof:placetype":"postalcode"
},
  "geometry": {"coordinates":[-1.23709541238362,51.60361406042349],"type":"Point"}
}