{
  "type": "Feature",
  "properties": {
    "iso:country":"GB",
    "wof:name":"AB32 6LX",
    "wof:placetype":"postalcode"
},
  "geometry": {"coordinates":[-2.32625093090747,57.16092360260126],"type":"Point"}
}