{
  "type": "Feature",
  "properties": {
    "date:inception_lower": "1987-04-01",
    "date:inception_upper": "1987-04-01",
    "iso:country": "GB",
    "wof:name": "LN8 3BT",
    "wof:placetype": "postalcode"
  },
  "geometry": {"coordinates":[-0.340678,53.38222],"type":"Point"}
}
