{
  "type": "Feature",
  "properties": {
    "iso:country":"GB",
    "wof:name":"LN8 3BT",
    "wof:placetype":"postalcode"
},
  "geometry": {"coordinates":[-0.34067844646065,53.38221966861455],"type":"Point"}
}