{
  "type": "Feature",
  "properties": {
    "iso:country": "GB",
    "wof:name": "TF3 3AA",
    "wof:placetype": "postalcode"
  },
  "geometry": {"coordinates":[-2.430305,52.677945],"type":"Point"}
}
