{
  "type": "Feature",
  "properties": {
    "iso:country":"GB",
    "wof:name":"AB51 0DD",
    "wof:placetype":"postalcode"
},
  "geometry": {"coordinates":[-2.31539129639779,57.3376094572575],"type":"Point"}
}