{
  "type": "Feature",
  "properties": {
    "iso:country": "GB",
    "wof:name": "TA6 3RZ",
    "wof:placetype": "postalcode"
  },
  "geometry": {"coordinates":[-3.005671,51.133291],"type":"Point"}
}
