{
  "type": "Feature",
  "properties": {
    "iso:country":"GB",
    "wof:name":"TA6 3RZ",
    "wof:placetype":"postalcode"
},
  "geometry": {"coordinates":[-3.00567151693185,51.13329056186958],"type":"Point"}
}