{
  "type": "Feature",
  "properties": {
    "date:inception_lower":"1998-06-01",
    "date:inception_upper":"1998-06-30",
    "iso:country":"GB",
    "wof:name":"TA6 3RZ",
    "wof:placetype":"postalcode"
},
  "geometry": {"coordinates":[-3.005671,51.133291],"type":"Point"}
}