{
  "type": "Feature",
  "properties": {
    "iso:country":"GB",
    "wof:name":"BL3 5AL",
    "wof:placetype":"postalcode"
},
  "geometry": {"coordinates":[-2.44036520905935,53.57247107645915],"type":"Point"}
}