{
  "type": "Feature",
  "properties": {
    "date:inception_lower": "1994-05-01",
    "date:inception_upper": "1994-05-01",
    "iso:country": "GB",
    "wof:name": "M30 7EW",
    "wof:placetype": "postalcode"
  },
  "geometry": {"coordinates":[-2.356392,53.475901],"type":"Point"}
}
