{
  "type": "Feature",
  "properties": {
    "iso:country":"GB",
    "wof:name":"NP18 3ST",
    "wof:placetype":"postalcode"
},
  "geometry": {"coordinates":[-2.97535556740028,51.61644173259275],"type":"Point"}
}