{
  "type": "Feature",
  "properties": {
    "iso:country": "GB",
    "wof:name": "NP18 3ST",
    "wof:placetype": "postalcode"
  },
  "geometry": {"coordinates":[-2.975356,51.616442],"type":"Point"}
}
