{
  "type": "Feature",
  "properties": {
    "iso:country": "GB",
    "wof:name": "RM17 6JJ",
    "wof:placetype": "postalcode"
  },
  "geometry": {"coordinates":[0.320941,51.474852],"type":"Point"}
}
