{
  "type": "Feature",
  "properties": {
    "iso:country":"GB",
    "wof:name":"G34 0NL",
    "wof:placetype":"postalcode"
},
  "geometry": {"coordinates":[-4.11555753205737,55.86989220411982],"type":"Point"}
}