{
  "type": "Feature",
  "properties": {
    "date:inception_lower": "2016-05-01",
    "date:inception_upper": "2016-05-01",
    "iso:country": "GB",
    "wof:name": "NN14 2WP",
    "wof:placetype": "postalcode"
  },
  "geometry": {"coordinates":[-0.828769,52.448875],"type":"Point"}
}
