{
  "type": "Feature",
  "properties": {
    "date:inception_lower": "2014-12-01",
    "date:inception_upper": "2014-12-01",
    "iso:country": "GB",
    "wof:name": "BB2 2TU",
    "wof:placetype": "postalcode"
  },
  "geometry": {"coordinates":[-2.510482,53.738122],"type":"Point"}
}
