{
  "type": "Feature",
  "properties": {
    "date:inception_lower": "1980-01-01",
    "date:inception_upper": "1980-01-01",
    "iso:country": "GB",
    "wof:name": "NR7 8EF",
    "wof:placetype": "postalcode"
  },
  "geometry": {"coordinates":[1.310154,52.65653],"type":"Point"}
}
