{
  "type": "Feature",
  "properties": {
    "iso:country":"GB",
    "wof:name":"NR7 8EF",
    "wof:placetype":"postalcode"
},
  "geometry": {"coordinates":[1.31016476070603,52.65655757461846],"type":"Point"}
}