{
  "type": "Feature",
  "properties": {
    "date:inception_lower":"2002-11-01",
    "date:inception_upper":"2002-11-30",
    "iso:country":"GB",
    "wof:name":"RM16 6EA",
    "wof:placetype":"postalcode"
},
  "geometry": {"coordinates":[0.299147,51.48306],"type":"Point"}
}