{
  "type": "Feature",
  "properties": {
    "iso:country":"GB",
    "wof:name":"ME8 9DX",
    "wof:placetype":"postalcode"
},
  "geometry": {"coordinates":[0.59682045237687,51.35605043806438],"type":"Point"}
}