{
  "type": "Feature",
  "properties": {
    "iso:country": "GB",
    "wof:name": "CV2 1RL",
    "wof:placetype": "postalcode"
  },
  "geometry": {"coordinates":[-1.460725,52.429613],"type":"Point"}
}
