{
  "type": "Feature",
  "properties": {
    "iso:country":"GB",
    "wof:name":"CV2 1RL",
    "wof:placetype":"postalcode"
},
  "geometry": {"coordinates":[-1.46072538566959,52.42961254828784],"type":"Point"}
}