{
  "type": "Feature",
  "properties": {
    "date:inception_lower": "1995-01-01",
    "date:inception_upper": "1995-01-01",
    "iso:country": "GB",
    "wof:name": "LL19 8PZ",
    "wof:placetype": "postalcode"
  },
  "geometry": {"coordinates":[-3.409249,53.316433],"type":"Point"}
}
