{
  "type": "Feature",
  "properties": {
    "date:inception_lower":"2016-06-01",
    "date:inception_upper":"2016-06-30",
    "iso:country":"GB",
    "wof:name":"RM14 9DB",
    "wof:placetype":"postalcode"
},
  "geometry": {"coordinates":[0.246539,51.552319],"type":"Point"}
}