{
  "type": "Feature",
  "properties": {
    "iso:country":"GB",
    "wof:name":"ST6 5XW",
    "wof:placetype":"postalcode"
},
  "geometry": {"coordinates":[-2.21791352150415,53.06335239061497],"type":"Point"}
}