{
  "type": "Feature",
  "properties": {
    "date:inception_lower": "2001-06-01",
    "date:inception_upper": "2001-06-01",
    "iso:country": "GB",
    "wof:name": "ST6 5XW",
    "wof:placetype": "postalcode"
  },
  "geometry": {"coordinates":[-2.217913,53.063352],"type":"Point"}
}
