{
  "type": "Feature",
  "properties": {
    "date:inception_lower": "1990-02-01",
    "date:inception_upper": "1990-02-01",
    "iso:country": "GB",
    "wof:name": "OX11 9BY",
    "wof:placetype": "postalcode"
  },
  "geometry": {"coordinates":[-1.226625,51.610541],"type":"Point"}
}
