{
  "type": "Feature",
  "properties": {
    "iso:country":"GB",
    "wof:name":"PE36 6EA",
    "wof:placetype":"postalcode"
},
  "geometry": {"coordinates":[0.4893660556069,52.9406693480489],"type":"Point"}
}