{
  "type": "Feature",
  "properties": {
    "iso:country": "GB",
    "wof:name": "PE36 6EA",
    "wof:placetype": "postalcode"
  },
  "geometry": {"coordinates":[0.489449,52.940666],"type":"Point"}
}
