{
  "type": "Feature",
  "properties": {
    "iso:country": "GB",
    "wof:name": "DN36 5SZ",
    "wof:placetype": "postalcode"
  },
  "geometry": {"coordinates":[0.045052,53.474901],"type":"Point"}
}
