{
  "type": "Feature",
  "properties": {
    "iso:country":"GB",
    "wof:name":"HD3 3XG",
    "wof:placetype":"postalcode"
},
  "geometry": {"coordinates":[-1.85011754318802,53.6574716770594],"type":"Point"}
}