{
  "type": "Feature",
  "properties": {
    "iso:country":"GB",
    "wof:name":"AL9 7UT",
    "wof:placetype":"postalcode"
},
  "geometry": {"coordinates":[-0.20347432494548,51.72625010819664],"type":"Point"}
}