{
  "type": "Feature",
  "properties": {
    "iso:country":"GB",
    "wof:name":"BR3 4RD",
    "wof:placetype":"postalcode"
},
  "geometry": {"coordinates":[-0.04907582859321,51.4040309570323],"type":"Point"}
}