{
  "type": "Feature",
  "properties": {
    "iso:country":"GB",
    "wof:name":"AB33 8HS",
    "wof:placetype":"postalcode"
},
  "geometry": {"coordinates":[-2.71209299258733,57.20055972654879],"type":"Point"}
}