{
  "type": "Feature",
  "properties": {
    "date:inception_lower":"1980-01-01",
    "date:inception_upper":"1980-01-31",
    "iso:country":"GB",
    "wof:name":"CT5 2AP",
    "wof:placetype":"postalcode"
},
  "geometry": {"coordinates":[1.04663,51.363895],"type":"Point"}
}