{
  "type": "Feature",
  "properties": {
    "date:inception_lower": "1980-01-01",
    "date:inception_upper": "1980-01-01",
    "iso:country": "GB",
    "wof:name": "EH4 1BQ",
    "wof:placetype": "postalcode"
  },
  "geometry": {"coordinates":[-3.223533,55.95874],"type":"Point"}
}
