{
  "type": "Feature",
  "properties": {
    "date:inception_lower": "2015-07-01",
    "date:inception_upper": "2015-07-01",
    "iso:country": "GB",
    "wof:name": "NN7 3SB",
    "wof:placetype": "postalcode"
  },
  "geometry": {"coordinates":[-0.996807,52.221106],"type":"Point"}
}
