{
  "type": "Feature",
  "properties": {
    "iso:country":"GB",
    "wof:name":"NN7 3SB",
    "wof:placetype":"postalcode"
},
  "geometry": {"coordinates":[-0.99735933126377,52.22257920493065],"type":"Point"}
}