{
  "type": "Feature",
  "properties": {
    "iso:country":"GB",
    "wof:name":"PL7 2XX",
    "wof:placetype":"postalcode"
},
  "geometry": {"coordinates":[-4.02750489634965,50.38700853179549],"type":"Point"}
}