{
  "type": "Feature",
  "properties": {
    "iso:country":"GB",
    "wof:name":"TS13 4AE",
    "wof:placetype":"postalcode"
},
  "geometry": {"coordinates":[-0.90751378288435,54.56346327375498],"type":"Point"}
}