{
  "type": "Feature",
  "properties": {
    "date:inception_lower": "1980-01-01",
    "date:inception_upper": "1980-01-01",
    "iso:country": "GB",
    "wof:name": "LU5 5NA",
    "wof:placetype": "postalcode"
  },
  "geometry": {"coordinates":[-0.516053,51.905285],"type":"Point"}
}
