{
  "type": "Feature",
  "properties": {
    "iso:country":"GB",
    "wof:name":"CW12 1SH",
    "wof:placetype":"postalcode"
},
  "geometry": {"coordinates":[-2.20641383197235,53.17351514292929],"type":"Point"}
}