{
  "type": "Feature",
  "properties": {
    "iso:country": "GB",
    "wof:name": "CW12 1SH",
    "wof:placetype": "postalcode"
  },
  "geometry": {"coordinates":[-2.206414,53.173515],"type":"Point"}
}
