{
  "type": "Feature",
  "properties": {
    "iso:country": "GB",
    "wof:name": "B30 1NX",
    "wof:placetype": "postalcode"
  },
  "geometry": {"coordinates":[-1.936606,52.422949],"type":"Point"}
}
