{
  "type": "Feature",
  "properties": {
    "iso:country":"GB",
    "wof:name":"B30 1NX",
    "wof:placetype":"postalcode"
},
  "geometry": {"coordinates":[-1.93660641903354,52.42294879034372],"type":"Point"}
}