{
  "type": "Feature",
  "properties": {
    "date:inception_lower": "1980-01-01",
    "date:inception_upper": "1980-01-01",
    "iso:country": "GB",
    "wof:name": "B30 1NX",
    "wof:placetype": "postalcode"
  },
  "geometry": {"coordinates":[-1.936606,52.422949],"type":"Point"}
}
