{
  "type": "Feature",
  "properties": {
    "date:inception_lower": "1996-06-01",
    "date:inception_upper": "1996-06-01",
    "iso:country": "GB",
    "wof:name": "GL6 8QY",
    "wof:placetype": "postalcode"
  },
  "geometry": {"coordinates":[-2.1488,51.726065],"type":"Point"}
}
