{
  "type": "Feature",
  "properties": {
    "iso:country":"GB",
    "wof:name":"GL6 8QY",
    "wof:placetype":"postalcode"
},
  "geometry": {"coordinates":[-2.14879979758853,51.72606522893611],"type":"Point"}
}