{
  "type": "Feature",
  "properties": {
    "iso:country":"GB",
    "wof:name":"EX13 5NR",
    "wof:placetype":"postalcode"
},
  "geometry": {"coordinates":[-2.99915955600655,50.78243780406058],"type":"Point"}
}