{
  "type": "Feature",
  "properties": {
    "iso:country": "GB",
    "wof:name": "EX13 5NR",
    "wof:placetype": "postalcode"
  },
  "geometry": {"coordinates":[-2.99916,50.782438],"type":"Point"}
}
