{
  "type": "Feature",
  "properties": {
    "iso:country":"GB",
    "wof:name":"AL1 2PP",
    "wof:placetype":"postalcode"
},
  "geometry": {"coordinates":[-0.346220200844,51.73914520001968],"type":"Point"}
}