{
  "type": "Feature",
  "properties": {
    "date:inception_lower":"1981-06-01",
    "date:inception_upper":"1981-06-30",
    "iso:country":"GB",
    "wof:name":"AL1 2PP",
    "wof:placetype":"postalcode"
},
  "geometry": {"coordinates":[-0.34622,51.739145],"type":"Point"}
}