{
  "type": "Feature",
  "properties": {
    "iso:country":"GB",
    "wof:name":"CV21 1QF",
    "wof:placetype":"postalcode"
},
  "geometry": {"coordinates":[-1.24083424537743,52.39098834554199],"type":"Point"}
}