{
  "type": "Feature",
  "properties": {
    "date:inception_lower":"1984-02-01",
    "date:inception_upper":"1984-02-29",
    "iso:country":"GB",
    "wof:name":"CV21 1QF",
    "wof:placetype":"postalcode"
},
  "geometry": {"coordinates":[-1.240834,52.390988],"type":"Point"}
}