{
  "type": "Feature",
  "properties": {
    "iso:country":"GB",
    "wof:name":"HU5 2PF",
    "wof:placetype":"postalcode"
},
  "geometry": {"coordinates":[-0.35633889018837,53.76516821951918],"type":"Point"}
}