{
  "type": "Feature",
  "properties": {
    "date:inception_lower": "1980-01-01",
    "date:inception_upper": "1980-01-01",
    "iso:country": "GB",
    "wof:name": "WF1 2LS",
    "wof:placetype": "postalcode"
  },
  "geometry": {"coordinates":[-1.501349,53.713154],"type":"Point"}
}
