{
  "type": "Feature",
  "properties": {
    "iso:country":"GB",
    "wof:name":"WF1 2LS",
    "wof:placetype":"postalcode"
},
  "geometry": {"coordinates":[-1.50134933429006,53.71315382298142],"type":"Point"}
}