{
  "type": "Feature",
  "properties": {
    "iso:country":"GB",
    "wof:name":"CH3 6PW",
    "wof:placetype":"postalcode"
},
  "geometry": {"coordinates":[-2.87365647777025,53.0850189085599],"type":"Point"}
}