{
  "type": "Feature",
  "properties": {
    "iso:country":"GB",
    "wof:name":"GL54 3JA",
    "wof:placetype":"postalcode"
},
  "geometry": {"coordinates":[-1.83494765424459,51.82959409032264],"type":"Point"}
}