{
  "type": "Feature",
  "properties": {
    "iso:country":"GB",
    "wof:name":"DY8 5AP",
    "wof:placetype":"postalcode"
},
  "geometry": {"coordinates":[-2.16157621751865,52.47823336875652],"type":"Point"}
}