{
  "type": "Feature",
  "properties": {
    "date:inception_lower": "1997-06-01",
    "date:inception_upper": "1997-06-01",
    "iso:country": "GB",
    "wof:name": "KT22 9AD",
    "wof:placetype": "postalcode"
  },
  "geometry": {"coordinates":[-0.333698,51.293463],"type":"Point"}
}
