{
  "type": "Feature",
  "properties": {
    "iso:country":"GB",
    "wof:name":"YO21 1LL",
    "wof:placetype":"postalcode"
},
  "geometry": {"coordinates":[-0.62721267852641,54.48273875251034],"type":"Point"}
}