{
  "type": "Feature",
  "properties": {
    "iso:country":"GB",
    "wof:name":"N21 3JA",
    "wof:placetype":"postalcode"
},
  "geometry": {"coordinates":[-0.09251679634538,51.63054923177599],"type":"Point"}
}