{
  "type": "Feature",
  "properties": {
    "date:inception_lower":"1980-01-01",
    "date:inception_upper":"1980-01-31",
    "iso:country":"GB",
    "wof:name":"WS5 4JU",
    "wof:placetype":"postalcode"
},
  "geometry": {"coordinates":[-1.965292,52.560291],"type":"Point"}
}