{
  "type": "Feature",
  "properties": {
    "iso:country":"GB",
    "wof:name":"KA3 1DN",
    "wof:placetype":"postalcode"
},
  "geometry": {"coordinates":[-4.49555014754256,55.61351923618952],"type":"Point"}
}