{
  "type": "Feature",
  "properties": {
    "iso:country": "GB",
    "wof:name": "TN23 3SS",
    "wof:placetype": "postalcode"
  },
  "geometry": {"coordinates":[0.851115,51.157324],"type":"Point"}
}
