{
  "type": "Feature",
  "properties": {
    "date:inception_lower":"1980-01-01",
    "date:inception_upper":"1980-01-31",
    "iso:country":"GB",
    "wof:name":"LE12 7DB",
    "wof:placetype":"postalcode"
},
  "geometry": {"coordinates":[-1.136413,52.726521],"type":"Point"}
}