{
  "type": "Feature",
  "properties": {
    "date:inception_lower":"2000-12-01",
    "date:inception_upper":"2000-12-31",
    "iso:country":"GB",
    "wof:name":"SY13 1EB",
    "wof:placetype":"postalcode"
},
  "geometry": {"coordinates":[-2.682073,52.966885],"type":"Point"}
}