{
  "type": "Feature",
  "properties": {
    "iso:country":"GB",
    "wof:name":"HG2 7LX",
    "wof:placetype":"postalcode"
},
  "geometry": {"coordinates":[-1.51501634215258,53.99597134065468],"type":"Point"}
}