{
  "type": "Feature",
  "properties": {
    "iso:country": "GB",
    "wof:name": "LA1 1TX",
    "wof:placetype": "postalcode"
  },
  "geometry": {"coordinates":[-2.806412,54.048385],"type":"Point"}
}
