{
  "type": "Feature",
  "properties": {
    "date:inception_lower": "1980-01-01",
    "date:inception_upper": "1980-01-01",
    "iso:country": "GB",
    "wof:name": "IV2 4UH",
    "wof:placetype": "postalcode"
  },
  "geometry": {"coordinates":[-4.214991,57.462854],"type":"Point"}
}
