{
  "type": "Feature",
  "properties": {
    "iso:country": "GB",
    "wof:name": "MK44 2JF",
    "wof:placetype": "postalcode"
  },
  "geometry": {"coordinates":[-0.426413,52.237801],"type":"Point"}
}
