{
  "type": "Feature",
  "properties": {
    "iso:country":"GB",
    "wof:name":"MK44 2JF",
    "wof:placetype":"postalcode"
},
  "geometry": {"coordinates":[-0.42641280012513,52.23780143022125],"type":"Point"}
}