{
  "type": "Feature",
  "properties": {
    "iso:country":"GB",
    "wof:name":"UB8 3LA",
    "wof:placetype":"postalcode"
},
  "geometry": {"coordinates":[-0.44027484834715,51.52599840333723],"type":"Point"}
}