{
  "type": "Feature",
  "properties": {
    "iso:country":"GB",
    "wof:name":"N21 1QP",
    "wof:placetype":"postalcode"
},
  "geometry": {"coordinates":[-0.11666009593965,51.63651428971657],"type":"Point"}
}