{
  "type": "Feature",
  "properties": {
    "iso:country": "GB",
    "wof:name": "N21 1QP",
    "wof:placetype": "postalcode"
  },
  "geometry": {"coordinates":[-0.11666,51.636514],"type":"Point"}
}
