{
  "type": "Feature",
  "properties": {
    "iso:country":"GB",
    "wof:name":"B18 4HA",
    "wof:placetype":"postalcode"
},
  "geometry": {"coordinates":[-1.94143401328764,52.48652853247538],"type":"Point"}
}