{
  "type": "Feature",
  "properties": {
    "iso:country":"GB",
    "wof:name":"PE6 0HD",
    "wof:placetype":"postalcode"
},
  "geometry": {"coordinates":[-0.16745806060891,52.677914343305],"type":"Point"}
}