{
  "type": "Feature",
  "properties": {
    "iso:country": "GB",
    "wof:name": "PE6 0HD",
    "wof:placetype": "postalcode"
  },
  "geometry": {"coordinates":[-0.167562,52.677909],"type":"Point"}
}
