{
  "type": "Feature",
  "properties": {
    "date:inception_lower": "1980-01-01",
    "date:inception_upper": "1980-01-01",
    "iso:country": "GB",
    "wof:name": "CR0 7YD",
    "wof:placetype": "postalcode"
  },
  "geometry": {"coordinates":[-0.06034,51.389326],"type":"Point"}
}
