{
  "type": "Feature",
  "properties": {
    "iso:country": "GB",
    "wof:name": "CR0 7YD",
    "wof:placetype": "postalcode"
  },
  "geometry": {"coordinates":[-0.05985,51.388958],"type":"Point"}
}
