{
  "type": "Feature",
  "properties": {
    "iso:country":"GB",
    "wof:name":"BR3 6QD",
    "wof:placetype":"postalcode"
},
  "geometry": {"coordinates":[-0.01053875411112,51.40280746854632],"type":"Point"}
}