{
  "type": "Feature",
  "properties": {
    "date:inception_lower": "2004-05-01",
    "date:inception_upper": "2004-05-01",
    "iso:country": "GB",
    "wof:name": "PE28 9WE",
    "wof:placetype": "postalcode"
  },
  "geometry": {"coordinates":[-0.18396,52.340652],"type":"Point"}
}
