{
  "type": "Feature",
  "properties": {
    "iso:country":"GB",
    "wof:name":"PE1 5EZ",
    "wof:placetype":"postalcode"
},
  "geometry": {"coordinates":[-0.22863691532325,52.57663641133806],"type":"Point"}
}