{
  "type": "Feature",
  "properties": {
    "iso:country":"GB",
    "wof:name":"IP29 4TP",
    "wof:placetype":"postalcode"
},
  "geometry": {"coordinates":[0.68171997878607,52.19044602902867],"type":"Point"}
}