{
  "type": "Feature",
  "properties": {
    "date:inception_lower": "1986-01-01",
    "date:inception_upper": "1986-01-01",
    "iso:country": "GB",
    "wof:name": "SO51 8FD",
    "wof:placetype": "postalcode"
  },
  "geometry": {"coordinates":[-1.50063,50.992011],"type":"Point"}
}
