{
  "type": "Feature",
  "properties": {
    "iso:country":"GB",
    "wof:name":"HU5 5NZ",
    "wof:placetype":"postalcode"
},
  "geometry": {"coordinates":[-0.41261003412417,53.75433067492999],"type":"Point"}
}