{
  "type": "Feature",
  "properties": {
    "iso:country":"GB",
    "wof:name":"DL17 8PW",
    "wof:placetype":"postalcode"
},
  "geometry": {"coordinates":[-1.56059780214718,54.68840518273344],"type":"Point"}
}