{
  "type": "Feature",
  "properties": {
    "date:inception_lower": "1999-12-01",
    "date:inception_upper": "1999-12-01",
    "iso:country": "GB",
    "wof:name": "CV47 8LA",
    "wof:placetype": "postalcode"
  },
  "geometry": {"coordinates":[-1.363394,52.273021],"type":"Point"}
}
