{
  "type": "Feature",
  "properties": {
    "iso:country": "GB",
    "wof:name": "ME18 6HY",
    "wof:placetype": "postalcode"
  },
  "geometry": {"coordinates":[0.432711,51.224725],"type":"Point"}
}
