{
  "type": "Feature",
  "properties": {
    "iso:country":"GB",
    "wof:name":"ME18 6HY",
    "wof:placetype":"postalcode"
},
  "geometry": {"coordinates":[0.43271138737937,51.22472544620464],"type":"Point"}
}