{
  "type": "Feature",
  "properties": {
    "date:inception_lower": "1980-01-01",
    "date:inception_upper": "1980-01-01",
    "iso:country": "GB",
    "wof:name": "CW12 3QZ",
    "wof:placetype": "postalcode"
  },
  "geometry": {"coordinates":[-2.159863,53.155186],"type":"Point"}
}
