{
  "type": "Feature",
  "properties": {
    "iso:country":"GB",
    "wof:name":"TS3 7JL",
    "wof:placetype":"postalcode"
},
  "geometry": {"coordinates":[-1.19797825086476,54.5520491370436],"type":"Point"}
}