{
  "type": "Feature",
  "properties": {
    "iso:country":"GB",
    "wof:name":"CH60 0BW",
    "wof:placetype":"postalcode"
},
  "geometry": {"coordinates":[-3.09471830711589,53.32183871892936],"type":"Point"}
}