{
  "type": "Feature",
  "properties": {
    "iso:country":"GB",
    "wof:name":"LU6 3EZ",
    "wof:placetype":"postalcode"
},
  "geometry": {"coordinates":[-0.50713693961488,51.8754915977587],"type":"Point"}
}