{
  "type": "Feature",
  "properties": {
    "iso:country":"GB",
    "wof:name":"SO22 4QN",
    "wof:placetype":"postalcode"
},
  "geometry": {"coordinates":[-1.33372350017197,51.05068093456877],"type":"Point"}
}