{
  "type": "Feature",
  "properties": {
    "iso:country":"GB",
    "wof:name":"WV1 1DN",
    "wof:placetype":"postalcode"
},
  "geometry": {"coordinates":[-2.12649192957239,52.5863974868792],"type":"Point"}
}