{
  "type": "Feature",
  "properties": {
    "date:inception_lower": "2020-04-01",
    "date:inception_upper": "2020-04-01",
    "iso:country": "GB",
    "wof:name": "PR3 2DS",
    "wof:placetype": "postalcode"
  },
  "geometry": {"coordinates":[-2.665359,53.823324],"type":"Point"}
}
