{
  "type": "Feature",
  "properties": {
    "iso:country": "GB",
    "wof:name": "OX15 5BX",
    "wof:placetype": "postalcode"
  },
  "geometry": {"coordinates":[-1.522411,51.996475],"type":"Point"}
}
