{
  "type": "Feature",
  "properties": {
    "iso:country":"GB",
    "wof:name":"MK43 9DJ",
    "wof:placetype":"postalcode"
},
  "geometry": {"coordinates":[-0.53647901115226,52.09716602767377],"type":"Point"}
}