{
  "type": "Feature",
  "properties": {
    "iso:country":"GB",
    "wof:name":"NW11 6QY",
    "wof:placetype":"postalcode"
},
  "geometry": {"coordinates":[-0.19038679567335,51.58537448123382],"type":"Point"}
}