{
  "type": "Feature",
  "properties": {
    "date:inception_lower": "2022-11-01",
    "date:inception_upper": "2022-11-01",
    "iso:country": "GB",
    "wof:name": "PE19 0AH",
    "wof:placetype": "postalcode"
  },
  "geometry": {"coordinates":[-0.232502,52.224874],"type":"Point"}
}
