{
  "type": "Feature",
  "properties": {
    "iso:country":"GB",
    "wof:name":"NW8 0BA",
    "wof:placetype":"postalcode"
},
  "geometry": {"coordinates":[-0.18622776054961,51.53792039539999],"type":"Point"}
}