{
  "type": "Feature",
  "properties": {
    "iso:country": "GB",
    "wof:name": "LE67 1FQ",
    "wof:placetype": "postalcode"
  },
  "geometry": {"coordinates":[-1.356439,52.694511],"type":"Point"}
}
