{
  "type": "Feature",
  "properties": {
    "iso:country":"GB",
    "wof:name":"BD11 1DP",
    "wof:placetype":"postalcode"
},
  "geometry": {"coordinates":[-1.65216721391404,53.75157108427538],"type":"Point"}
}