{
  "type": "Feature",
  "properties": {
    "iso:country":"GB",
    "wof:name":"BB2 1JL",
    "wof:placetype":"postalcode"
},
  "geometry": {"coordinates":[-2.48464906820472,53.74848761840657],"type":"Point"}
}