{
  "type": "Feature",
  "properties": {
    "date:inception_lower": "1995-12-01",
    "date:inception_upper": "1995-12-01",
    "iso:country": "GB",
    "wof:name": "B97 6HB",
    "wof:placetype": "postalcode"
  },
  "geometry": {"coordinates":[-1.946861,52.307961],"type":"Point"}
}
