{
  "type": "Feature",
  "properties": {
    "iso:country":"GB",
    "wof:name":"B97 6HB",
    "wof:placetype":"postalcode"
},
  "geometry": {"coordinates":[-1.94686097343246,52.30796101459654],"type":"Point"}
}