{
  "type": "Feature",
  "properties": {
    "date:inception_lower":"2005-03-01",
    "date:inception_upper":"2005-03-31",
    "iso:country":"GB",
    "wof:name":"RM12 4QD",
    "wof:placetype":"postalcode"
},
  "geometry": {"coordinates":[0.207732,51.557031],"type":"Point"}
}