{
  "type": "Feature",
  "properties": {
    "iso:country": "GB",
    "wof:name": "RM12 4QD",
    "wof:placetype": "postalcode"
  },
  "geometry": {"coordinates":[0.207732,51.557031],"type":"Point"}
}
