{
  "type": "Feature",
  "properties": {
    "iso:country":"GB",
    "wof:name":"GL51 3EE",
    "wof:placetype":"postalcode"
},
  "geometry": {"coordinates":[-2.10322926026448,51.88698107391629],"type":"Point"}
}