{
  "type": "Feature",
  "properties": {
    "iso:country":"GB",
    "wof:name":"CO9 2TU",
    "wof:placetype":"postalcode"
},
  "geometry": {"coordinates":[0.64524392550972,51.94168917317756],"type":"Point"}
}