{
  "type": "Feature",
  "properties": {
    "date:inception_lower": "1999-06-01",
    "date:inception_upper": "1999-06-01",
    "iso:country": "GB",
    "wof:name": "CO9 2TU",
    "wof:placetype": "postalcode"
  },
  "geometry": {"coordinates":[0.645244,51.941689],"type":"Point"}
}
