{
  "type": "Feature",
  "properties": {
    "iso:country": "GB",
    "wof:name": "SN10 2GH",
    "wof:placetype": "postalcode"
  },
  "geometry": {"coordinates":[-1.966824,51.369808],"type":"Point"}
}
