{
  "type": "Feature",
  "properties": {
    "iso:country": "GB",
    "wof:name": "SO16 3LT",
    "wof:placetype": "postalcode"
  },
  "geometry": {"coordinates":[-1.399801,50.949416],"type":"Point"}
}
