{
  "type": "Feature",
  "properties": {
    "date:inception_lower": "1994-12-01",
    "date:inception_upper": "1994-12-01",
    "iso:country": "GB",
    "wof:name": "SO16 3LT",
    "wof:placetype": "postalcode"
  },
  "geometry": {"coordinates":[-1.399801,50.949416],"type":"Point"}
}
