{
  "type": "Feature",
  "properties": {
    "iso:country":"GB",
    "wof:name":"PO20 2BL",
    "wof:placetype":"postalcode"
},
  "geometry": {"coordinates":[-0.74061109829301,50.83942987926825],"type":"Point"}
}