{
  "type": "Feature",
  "properties": {
    "iso:country": "GB",
    "wof:name": "PO20 2BL",
    "wof:placetype": "postalcode"
  },
  "geometry": {"coordinates":[-0.740611,50.83943],"type":"Point"}
}
