{
  "type": "Feature",
  "properties": {
    "date:inception_lower": "2002-07-01",
    "date:inception_upper": "2002-07-01",
    "iso:country": "GB",
    "wof:name": "OX4 4JW",
    "wof:placetype": "postalcode"
  },
  "geometry": {"coordinates":[-1.220517,51.722569],"type":"Point"}
}
