{
  "type": "Feature",
  "properties": {
    "iso:country":"GB",
    "wof:name":"DD11 5EW",
    "wof:placetype":"postalcode"
},
  "geometry": {"coordinates":[-2.56684435221669,56.56983594422846],"type":"Point"}
}