{
  "type": "Feature",
  "properties": {
    "iso:country": "GB",
    "wof:name": "DD11 5EW",
    "wof:placetype": "postalcode"
  },
  "geometry": {"coordinates":[-2.566844,56.569836],"type":"Point"}
}
