{
  "type": "Feature",
  "properties": {
    "iso:country":"GB",
    "wof:name":"NW7 3RH",
    "wof:placetype":"postalcode"
},
  "geometry": {"coordinates":[-0.24614887315854,51.61646201869336],"type":"Point"}
}