{
  "type": "Feature",
  "properties": {
    "date:inception_lower": "2022-10-01",
    "date:inception_upper": "2022-10-01",
    "iso:country": "GB",
    "wof:name": "SL5 9FU",
    "wof:placetype": "postalcode"
  },
  "geometry": {"coordinates":[-0.654678,51.399473],"type":"Point"}
}
