{
  "type": "Feature",
  "properties": {
    "iso:country": "GB",
    "wof:name": "TN29 0DL",
    "wof:placetype": "postalcode"
  },
  "geometry": {"coordinates":[0.93134,51.041082],"type":"Point"}
}
