{
  "type": "Feature",
  "properties": {
    "iso:country":"GB",
    "wof:name":"TN29 0DL",
    "wof:placetype":"postalcode"
},
  "geometry": {"coordinates":[0.93133973089971,51.04108223033084],"type":"Point"}
}