{
  "type": "Feature",
  "properties": {
    "iso:country": "GB",
    "wof:name": "LE67 9RP",
    "wof:placetype": "postalcode"
  },
  "geometry": {"coordinates":[-1.278517,52.675005],"type":"Point"}
}
