{
  "type": "Feature",
  "properties": {
    "date:inception_lower": "1992-10-01",
    "date:inception_upper": "1992-10-01",
    "iso:country": "GB",
    "wof:name": "G32 0RD",
    "wof:placetype": "postalcode"
  },
  "geometry": {"coordinates":[-4.137384,55.845897],"type":"Point"}
}
