{
  "type": "Feature",
  "properties": {
    "iso:country":"GB",
    "wof:name":"G32 0RD",
    "wof:placetype":"postalcode"
},
  "geometry": {"coordinates":[-4.13738376357356,55.84589660710744],"type":"Point"}
}