{
  "type": "Feature",
  "properties": {
    "iso:country":"GB",
    "wof:name":"GL5 3LW",
    "wof:placetype":"postalcode"
},
  "geometry": {"coordinates":[-2.22693782143267,51.74064961418302],"type":"Point"}
}