{
  "type": "Feature",
  "properties": {
    "iso:country": "GB",
    "wof:name": "GL5 3LW",
    "wof:placetype": "postalcode"
  },
  "geometry": {"coordinates":[-2.226938,51.74065],"type":"Point"}
}
