{
  "type": "Feature",
  "properties": {
    "date:inception_lower": "1995-12-01",
    "date:inception_upper": "1995-12-01",
    "iso:country": "GB",
    "wof:name": "GL5 3LW",
    "wof:placetype": "postalcode"
  },
  "geometry": {"coordinates":[-2.226938,51.74065],"type":"Point"}
}
