{
  "type": "Feature",
  "properties": {
    "iso:country":"GB",
    "wof:name":"MK7 7HD",
    "wof:placetype":"postalcode"
},
  "geometry": {"coordinates":[-0.69990867889547,52.01487912911229],"type":"Point"}
}