{
  "type": "Feature",
  "properties": {
    "iso:country": "GB",
    "wof:name": "MK7 7HD",
    "wof:placetype": "postalcode"
  },
  "geometry": {"coordinates":[-0.699909,52.014879],"type":"Point"}
}
