{
  "type": "Feature",
  "properties": {
    "iso:country":"GB",
    "wof:name":"CF23 5HE",
    "wof:placetype":"postalcode"
},
  "geometry": {"coordinates":[-3.16384843997162,51.49909847531499],"type":"Point"}
}