{
  "type": "Feature",
  "properties": {
    "date:inception_lower": "1999-06-01",
    "date:inception_upper": "1999-06-01",
    "iso:country": "GB",
    "wof:name": "CF24 1NJ",
    "wof:placetype": "postalcode"
  },
  "geometry": {"coordinates":[-3.15346,51.488439],"type":"Point"}
}
