{
  "type": "Feature",
  "properties": {
    "iso:country":"GB",
    "wof:name":"CF24 1NJ",
    "wof:placetype":"postalcode"
},
  "geometry": {"coordinates":[-3.15350635413987,51.48832948647582],"type":"Point"}
}