{
  "type": "Feature",
  "properties": {
    "iso:country": "GB",
    "wof:name": "SN1 2DL",
    "wof:placetype": "postalcode"
  },
  "geometry": {"coordinates":[-1.781029,51.56211],"type":"Point"}
}
