{
  "type": "Feature",
  "properties": {
    "iso:country":"GB",
    "wof:name":"SN1 2DL",
    "wof:placetype":"postalcode"
},
  "geometry": {"coordinates":[-1.78096803453164,51.56218940032051],"type":"Point"}
}