{
  "type": "Feature",
  "properties": {
    "iso:country":"GB",
    "wof:name":"TS6 8EP",
    "wof:placetype":"postalcode"
},
  "geometry": {"coordinates":[-1.13485455548985,54.56430421516491],"type":"Point"}
}