{
  "type": "Feature",
  "properties": {
    "date:inception_lower":"2007-03-01",
    "date:inception_upper":"2007-03-31",
    "iso:country":"GB",
    "wof:name":"BS40 5PY",
    "wof:placetype":"postalcode"
},
  "geometry": {"coordinates":[-2.761757,51.35579],"type":"Point"}
}