{
  "type": "Feature",
  "properties": {
    "iso:country":"GB",
    "wof:name":"BS40 5PY",
    "wof:placetype":"postalcode"
},
  "geometry": {"coordinates":[-2.76175717306564,51.35578958544168],"type":"Point"}
}