{
  "type": "Feature",
  "properties": {
    "iso:country": "GB",
    "wof:name": "BS40 5PY",
    "wof:placetype": "postalcode"
  },
  "geometry": {"coordinates":[-2.761757,51.35579],"type":"Point"}
}
