{
  "type": "Feature",
  "properties": {
    "iso:country":"GB",
    "wof:name":"E17 8EB",
    "wof:placetype":"postalcode"
},
  "geometry": {"coordinates":[-0.02719046930435,51.57492999802823],"type":"Point"}
}