{
  "type": "Feature",
  "properties": {
    "date:inception_lower": "2022-02-01",
    "date:inception_upper": "2022-02-01",
    "iso:country": "GB",
    "wof:name": "B5 6AR",
    "wof:placetype": "postalcode"
  },
  "geometry": {"coordinates":[-1.894131,52.473196],"type":"Point"}
}
