{
  "type": "Feature",
  "properties": {
    "iso:country":"GB",
    "wof:name":"DN22 7QR",
    "wof:placetype":"postalcode"
},
  "geometry": {"coordinates":[-0.95541862163423,53.33362820567839],"type":"Point"}
}