{
  "type": "Feature",
  "properties": {
    "date:inception_lower": "1980-01-01",
    "date:inception_upper": "1980-01-01",
    "iso:country": "GB",
    "wof:name": "G78 1LS",
    "wof:placetype": "postalcode"
  },
  "geometry": {"coordinates":[-4.398547,55.79757],"type":"Point"}
}
