{
  "type": "Feature",
  "properties": {
    "iso:country": "GB",
    "wof:name": "G78 1LS",
    "wof:placetype": "postalcode"
  },
  "geometry": {"coordinates":[-4.398547,55.79757],"type":"Point"}
}
