{
  "type": "Feature",
  "properties": {
    "iso:country":"GB",
    "wof:name":"CM2 6TS",
    "wof:placetype":"postalcode"
},
  "geometry": {"coordinates":[0.50149292423022,51.74105239702106],"type":"Point"}
}