{
  "type": "Feature",
  "properties": {
    "date:inception_lower": "2000-06-01",
    "date:inception_upper": "2000-06-01",
    "iso:country": "GB",
    "wof:name": "HP19 7FT",
    "wof:placetype": "postalcode"
  },
  "geometry": {"coordinates":[-0.838902,51.814414],"type":"Point"}
}
