{
  "type": "Feature",
  "properties": {
    "iso:country":"GB",
    "wof:name":"HP19 7FT",
    "wof:placetype":"postalcode"
},
  "geometry": {"coordinates":[-0.83890252016899,51.81441404457534],"type":"Point"}
}