{
  "type": "Feature",
  "properties": {
    "iso:country": "GB",
    "wof:name": "YO7 3ET",
    "wof:placetype": "postalcode"
  },
  "geometry": {"coordinates":[-1.406144,54.201974],"type":"Point"}
}
