{
  "type": "Feature",
  "properties": {
    "iso:country":"GB",
    "wof:name":"YO7 3ET",
    "wof:placetype":"postalcode"
},
  "geometry": {"coordinates":[-1.40615885823357,54.2019833635435],"type":"Point"}
}