{
  "type": "Feature",
  "properties": {
    "iso:country":"GB",
    "wof:name":"SO14 1PL",
    "wof:placetype":"postalcode"
},
  "geometry": {"coordinates":[-1.39522305706843,50.90503299030863],"type":"Point"}
}