{
  "type": "Feature",
  "properties": {
    "date:inception_lower": "2024-04-01",
    "date:inception_upper": "2024-04-01",
    "iso:country": "GB",
    "wof:name": "PO30 1BF",
    "wof:placetype": "postalcode"
  },
  "geometry": {"coordinates":[-1.290603,50.700272],"type":"Point"}
}
