{
  "type": "Feature",
  "properties": {
    "iso:country":"GB",
    "wof:name":"LA4 4HR",
    "wof:placetype":"postalcode"
},
  "geometry": {"coordinates":[-2.87732656464193,54.0664932597637],"type":"Point"}
}