{
  "type": "Feature",
  "properties": {
    "iso:country":"GB",
    "wof:name":"SL1 2AN",
    "wof:placetype":"postalcode"
},
  "geometry": {"coordinates":[-0.58528761505894,51.50388182915199],"type":"Point"}
}