{
  "type": "Feature",
  "properties": {
    "iso:country":"GB",
    "wof:name":"IP7 6EX",
    "wof:placetype":"postalcode"
},
  "geometry": {"coordinates":[0.89337951205854,52.04636947731126],"type":"Point"}
}