{
  "type": "Feature",
  "properties": {
    "iso:country":"GB",
    "wof:name":"SW3 1PP",
    "wof:placetype":"postalcode"
},
  "geometry": {"coordinates":[-0.16434105723794,51.49770733988982],"type":"Point"}
}