{
  "type": "Feature",
  "properties": {
    "iso:country":"GB",
    "wof:name":"DL1 2TP",
    "wof:placetype":"postalcode"
},
  "geometry": {"coordinates":[-1.53477069174953,54.5402598713745],"type":"Point"}
}