{
  "type": "Feature",
  "properties": {
    "iso:country": "GB",
    "wof:name": "DL1 2TP",
    "wof:placetype": "postalcode"
  },
  "geometry": {"coordinates":[-1.534771,54.54026],"type":"Point"}
}
