{
  "type": "Feature",
  "properties": {
    "date:inception_lower": "1980-01-01",
    "date:inception_upper": "1980-01-01",
    "iso:country": "GB",
    "wof:name": "DL1 2TP",
    "wof:placetype": "postalcode"
  },
  "geometry": {"coordinates":[-1.534764,54.540271],"type":"Point"}
}
