{
  "type": "Feature",
  "properties": {
    "date:inception_lower":"2013-07-01",
    "date:inception_upper":"2013-07-31",
    "iso:country":"GB",
    "wof:name":"CA28 9LF",
    "wof:placetype":"postalcode"
},
  "geometry": {"coordinates":[-3.594635,54.527708],"type":"Point"}
}