{
  "type": "Feature",
  "properties": {
    "iso:country":"GB",
    "wof:name":"M14 5AH",
    "wof:placetype":"postalcode"
},
  "geometry": {"coordinates":[-2.22315699389496,53.45280902357926],"type":"Point"}
}