{
  "type": "Feature",
  "properties": {
    "iso:country":"GB",
    "wof:name":"LN5 0TQ",
    "wof:placetype":"postalcode"
},
  "geometry": {"coordinates":[-0.52440431913748,53.10392151622344],"type":"Point"}
}