{
  "type": "Feature",
  "properties": {
    "iso:country":"GB",
    "wof:name":"HR8 1BQ",
    "wof:placetype":"postalcode"
},
  "geometry": {"coordinates":[-2.42735572383703,52.04457777025785],"type":"Point"}
}