{
  "type": "Feature",
  "properties": {
    "iso:country":"GB",
    "wof:name":"SY14 7BT",
    "wof:placetype":"postalcode"
},
  "geometry": {"coordinates":[-2.84864402640902,53.02634665585801],"type":"Point"}
}