{
  "type": "Feature",
  "properties": {
    "iso:country":"GB",
    "wof:name":"TQ12 1EP",
    "wof:placetype":"postalcode"
},
  "geometry": {"coordinates":[-3.5997443199475,50.52204819342893],"type":"Point"}
}