{
  "type": "Feature",
  "properties": {
    "iso:country": "GB",
    "wof:name": "LE65 2SN",
    "wof:placetype": "postalcode"
  },
  "geometry": {"coordinates":[-1.485616,52.773433],"type":"Point"}
}
