{
  "type": "Feature",
  "properties": {
    "iso:country":"GB",
    "wof:name":"RG9 1UH",
    "wof:placetype":"postalcode"
},
  "geometry": {"coordinates":[-0.90796733038039,51.53604918543971],"type":"Point"}
}