{
  "type": "Feature",
  "properties": {
    "iso:country":"GB",
    "wof:name":"CT9 4AL",
    "wof:placetype":"postalcode"
},
  "geometry": {"coordinates":[1.39151580495038,51.37810812078973],"type":"Point"}
}