{
  "type": "Feature",
  "properties": {
    "iso:country":"GB",
    "wof:name":"KY3 9DN",
    "wof:placetype":"postalcode"
},
  "geometry": {"coordinates":[-3.23449206891208,56.05838710558974],"type":"Point"}
}