{
  "type": "Feature",
  "properties": {
    "iso:country":"GB",
    "wof:name":"CF41 7TE",
    "wof:placetype":"postalcode"
},
  "geometry": {"coordinates":[-3.48078542016721,51.642597996062],"type":"Point"}
}