{
  "type": "Feature",
  "properties": {
    "iso:country":"GB",
    "wof:name":"LU3 1AE",
    "wof:placetype":"postalcode"
},
  "geometry": {"coordinates":[-0.42790657344405,51.8871469376093],"type":"Point"}
}