{
  "type": "Feature",
  "properties": {
    "iso:country": "GB",
    "wof:name": "GU31 5SJ",
    "wof:placetype": "postalcode"
  },
  "geometry": {"coordinates":[-0.954327,50.974644],"type":"Point"}
}
