{
  "type": "Feature",
  "properties": {
    "date:inception_lower": "2011-12-01",
    "date:inception_upper": "2011-12-01",
    "iso:country": "GB",
    "wof:name": "GU31 5SJ",
    "wof:placetype": "postalcode"
  },
  "geometry": {"coordinates":[-0.954298,50.974643],"type":"Point"}
}
