{
  "type": "Feature",
  "properties": {
    "date:inception_lower": "2004-05-01",
    "date:inception_upper": "2004-05-01",
    "iso:country": "GB",
    "wof:name": "BH19 1DL",
    "wof:placetype": "postalcode"
  },
  "geometry": {"coordinates":[-1.959351,50.611073],"type":"Point"}
}
