{
  "type": "Feature",
  "properties": {
    "iso:country": "GB",
    "wof:name": "BH19 1DL",
    "wof:placetype": "postalcode"
  },
  "geometry": {"coordinates":[-1.959351,50.611073],"type":"Point"}
}
