{
  "type": "Feature",
  "properties": {
    "iso:country":"GB",
    "wof:name":"NE36 0RG",
    "wof:placetype":"postalcode"
},
  "geometry": {"coordinates":[-1.43070097066704,54.94493490165002],"type":"Point"}
}