{
  "type": "Feature",
  "properties": {
    "iso:country": "GB",
    "wof:name": "NE36 0RG",
    "wof:placetype": "postalcode"
  },
  "geometry": {"coordinates":[-1.430701,54.944935],"type":"Point"}
}
