{
  "type": "Feature",
  "properties": {
    "iso:country":"GB",
    "wof:name":"RH6 0HJ",
    "wof:placetype":"postalcode"
},
  "geometry": {"coordinates":[-0.19622160592177,51.18542752790724],"type":"Point"}
}