{
  "type": "Feature",
  "properties": {
    "date:inception_lower": "1980-01-01",
    "date:inception_upper": "1980-01-01",
    "iso:country": "GB",
    "wof:name": "IP19 0QA",
    "wof:placetype": "postalcode"
  },
  "geometry": {"coordinates":[1.435016,52.316036],"type":"Point"}
}
