{
  "type": "Feature",
  "properties": {
    "iso:country":"GB",
    "wof:name":"IP19 0QA",
    "wof:placetype":"postalcode"
},
  "geometry": {"coordinates":[1.43501614080597,52.31603593567164],"type":"Point"}
}