{
  "type": "Feature",
  "properties": {
    "iso:country": "GB",
    "wof:name": "CT11 7QE",
    "wof:placetype": "postalcode"
  },
  "geometry": {"coordinates":[1.413928,51.338202],"type":"Point"}
}
