{
  "type": "Feature",
  "properties": {
    "iso:country": "GB",
    "wof:name": "WF4 2BQ",
    "wof:placetype": "postalcode"
  },
  "geometry": {"coordinates":[-1.414496,53.620676],"type":"Point"}
}
