{
  "type": "Feature",
  "properties": {
    "date:inception_lower":"2004-09-01",
    "date:inception_upper":"2004-09-30",
    "iso:country":"GB",
    "wof:name":"WF4 2BQ",
    "wof:placetype":"postalcode"
},
  "geometry": {"coordinates":[-1.414496,53.620676],"type":"Point"}
}