{
  "type": "Feature",
  "properties": {
    "iso:country":"GB",
    "wof:name":"WF4 2BQ",
    "wof:placetype":"postalcode"
},
  "geometry": {"coordinates":[-1.41449630746844,53.62067601799231],"type":"Point"}
}