{
  "type": "Feature",
  "properties": {
    "iso:country":"GB",
    "wof:name":"S9 1WS",
    "wof:placetype":"postalcode"
},
  "geometry": {"coordinates":[-1.38667087827915,53.40911744444799],"type":"Point"}
}