{
  "type": "Feature",
  "properties": {
    "iso:country": "GB",
    "wof:name": "S9 1WS",
    "wof:placetype": "postalcode"
  },
  "geometry": {"coordinates":[-1.386701,53.409118],"type":"Point"}
}
