{
  "type": "Feature",
  "properties": {
    "date:inception_lower": "1998-12-01",
    "date:inception_upper": "1998-12-01",
    "iso:country": "GB",
    "wof:name": "KY1 4NZ",
    "wof:placetype": "postalcode"
  },
  "geometry": {"coordinates":[-3.071304,56.157427],"type":"Point"}
}
