{
  "type": "Feature",
  "properties": {
    "iso:country":"GB",
    "wof:name":"SR2 7NJ",
    "wof:placetype":"postalcode"
},
  "geometry": {"coordinates":[-1.3982324027913,54.8987410862964],"type":"Point"}
}