{
  "type": "Feature",
  "properties": {
    "iso:country": "GB",
    "wof:name": "CV10 0TQ",
    "wof:placetype": "postalcode"
  },
  "geometry": {"coordinates":[-1.494542,52.558238],"type":"Point"}
}
