{
  "type": "Feature",
  "properties": {
    "iso:country":"GB",
    "wof:name":"OX4 3AN",
    "wof:placetype":"postalcode"
},
  "geometry": {"coordinates":[-1.23052356563982,51.74202949659312],"type":"Point"}
}