{
  "type": "Feature",
  "properties": {
    "date:inception_lower":"1980-01-01",
    "date:inception_upper":"1980-01-31",
    "iso:country":"GB",
    "wof:name":"NE15 0NW",
    "wof:placetype":"postalcode"
},
  "geometry": {"coordinates":[-1.856975,54.988795],"type":"Point"}
}