{
  "type": "Feature",
  "properties": {
    "iso:country":"GB",
    "wof:name":"NE15 0NW",
    "wof:placetype":"postalcode"
},
  "geometry": {"coordinates":[-1.85697461871883,54.9887952513199],"type":"Point"}
}