{
  "type": "Feature",
  "properties": {
    "iso:country":"GB",
    "wof:name":"NP23 4HL",
    "wof:placetype":"postalcode"
},
  "geometry": {"coordinates":[-3.18213914867145,51.79775377640522],"type":"Point"}
}