{
  "type": "Feature",
  "properties": {
    "iso:country":"GB",
    "wof:name":"DH9 7DA",
    "wof:placetype":"postalcode"
},
  "geometry": {"coordinates":[-1.70534391567672,54.86604850250485],"type":"Point"}
}