{
  "type": "Feature",
  "properties": {
    "iso:country": "GB",
    "wof:name": "DH9 7DA",
    "wof:placetype": "postalcode"
  },
  "geometry": {"coordinates":[-1.705344,54.866048],"type":"Point"}
}
