{
  "type": "Feature",
  "properties": {
    "iso:country": "GB",
    "wof:name": "NE23 7LZ",
    "wof:placetype": "postalcode"
  },
  "geometry": {"coordinates":[-1.594663,55.04737],"type":"Point"}
}
