{
  "type": "Feature",
  "properties": {
    "date:inception_lower": "2023-08-01",
    "date:inception_upper": "2023-08-01",
    "iso:country": "GB",
    "wof:name": "GL20 7GJ",
    "wof:placetype": "postalcode"
  },
  "geometry": {"coordinates":[-2.137155,51.979498],"type":"Point"}
}
