{
  "type": "Feature",
  "properties": {
    "date:inception_lower": "1980-01-01",
    "date:inception_upper": "1980-01-01",
    "iso:country": "GB",
    "wof:name": "CO6 5AB",
    "wof:placetype": "postalcode"
  },
  "geometry": {"coordinates":[0.892064,52.000675],"type":"Point"}
}
