{
  "type": "Feature",
  "properties": {
    "iso:country":"GB",
    "wof:name":"CO6 5AB",
    "wof:placetype":"postalcode"
},
  "geometry": {"coordinates":[0.89206078152737,52.00065227487439],"type":"Point"}
}