{
  "type": "Feature",
  "properties": {
    "iso:country":"GB",
    "wof:name":"LL48 6NL",
    "wof:placetype":"postalcode"
},
  "geometry": {"coordinates":[-4.0649780104296,52.93442725030901],"type":"Point"}
}