{
  "type": "Feature",
  "properties": {
    "iso:country":"GB",
    "wof:name":"TS24 0JY",
    "wof:placetype":"postalcode"
},
  "geometry": {"coordinates":[-1.18425374411745,54.69815812900289],"type":"Point"}
}