{
  "type": "Feature",
  "properties": {
    "iso:country":"GB",
    "wof:name":"W3 8AN",
    "wof:placetype":"postalcode"
},
  "geometry": {"coordinates":[-0.26785534266785,51.5037870630958],"type":"Point"}
}