{
  "type": "Feature",
  "properties": {
    "iso:country": "GB",
    "wof:name": "NE16 4AR",
    "wof:placetype": "postalcode"
  },
  "geometry": {"coordinates":[-1.685064,54.945329],"type":"Point"}
}
