{
  "type": "Feature",
  "properties": {
    "iso:country":"GB",
    "wof:name":"NE16 4AR",
    "wof:placetype":"postalcode"
},
  "geometry": {"coordinates":[-1.68506372015743,54.94532907081246],"type":"Point"}
}