{
  "type": "Feature",
  "properties": {
    "iso:country": "GB",
    "wof:name": "B27 7DY",
    "wof:placetype": "postalcode"
  },
  "geometry": {"coordinates":[-1.815942,52.442745],"type":"Point"}
}
