{
  "type": "Feature",
  "properties": {
    "iso:country":"GB",
    "wof:name":"B27 7DY",
    "wof:placetype":"postalcode"
},
  "geometry": {"coordinates":[-1.8159423122406,52.44274474430517],"type":"Point"}
}