{
  "type": "Feature",
  "properties": {
    "iso:country": "GB",
    "wof:name": "HU3 1RF",
    "wof:placetype": "postalcode"
  },
  "geometry": {"coordinates":[-0.352932,53.750649],"type":"Point"}
}
