{
  "type": "Feature",
  "properties": {
    "iso:country": "GB",
    "wof:name": "CV37 8DD",
    "wof:placetype": "postalcode"
  },
  "geometry": {"coordinates":[-1.645731,52.100168],"type":"Point"}
}
