{
  "type": "Feature",
  "properties": {
    "iso:country":"GB",
    "wof:name":"SK3 0SY",
    "wof:placetype":"postalcode"
},
  "geometry": {"coordinates":[-2.19356435760556,53.39925308804636],"type":"Point"}
}