{
  "type": "Feature",
  "properties": {
    "iso:country": "GB",
    "wof:name": "CH48 5DS",
    "wof:placetype": "postalcode"
  },
  "geometry": {"coordinates":[-3.183922,53.381304],"type":"Point"}
}
