{
  "type": "Feature",
  "properties": {
    "iso:country": "GB",
    "wof:name": "TR2 4PY",
    "wof:placetype": "postalcode"
  },
  "geometry": {"coordinates":[-4.947891,50.293223],"type":"Point"}
}
