{
  "type": "Feature",
  "properties": {
    "date:inception_lower":"1999-06-01",
    "date:inception_upper":"1999-06-30",
    "iso:country":"GB",
    "wof:name":"TR2 4PY",
    "wof:placetype":"postalcode"
},
  "geometry": {"coordinates":[-4.947891,50.293223],"type":"Point"}
}