{
  "type": "Feature",
  "properties": {
    "date:inception_lower": "1980-01-01",
    "date:inception_upper": "1980-01-01",
    "iso:country": "GB",
    "wof:name": "ST6 8LQ",
    "wof:placetype": "postalcode"
  },
  "geometry": {"coordinates":[-2.163259,53.060842],"type":"Point"}
}
