{
  "type": "Feature",
  "properties": {
    "iso:country":"GB",
    "wof:name":"PA4 9PR",
    "wof:placetype":"postalcode"
},
  "geometry": {"coordinates":[-4.43081037779253,55.89251349116314],"type":"Point"}
}