{
  "type": "Feature",
  "properties": {
    "iso:country":"GB",
    "wof:name":"TS25 1RD",
    "wof:placetype":"postalcode"
},
  "geometry": {"coordinates":[-1.21154430865148,54.67269004495637],"type":"Point"}
}