{
  "type": "Feature",
  "properties": {
    "iso:country": "GB",
    "wof:name": "DT1 2TT",
    "wof:placetype": "postalcode"
  },
  "geometry": {"coordinates":[-2.430449,50.706708],"type":"Point"}
}
