{
  "type": "Feature",
  "properties": {
    "date:inception_lower": "2002-06-01",
    "date:inception_upper": "2002-06-01",
    "iso:country": "GB",
    "wof:name": "DT1 2TT",
    "wof:placetype": "postalcode"
  },
  "geometry": {"coordinates":[-2.430449,50.706708],"type":"Point"}
}
