{
  "type": "Feature",
  "properties": {
    "iso:country": "GB",
    "wof:name": "SW1X 8BA",
    "wof:placetype": "postalcode"
  },
  "geometry": {"coordinates":[-0.149487,51.498058],"type":"Point"}
}
