{
  "type": "Feature",
  "properties": {
    "iso:country":"GB",
    "wof:name":"SW1X 8BA",
    "wof:placetype":"postalcode"
},
  "geometry": {"coordinates":[-0.1494875236631,51.49805841510314],"type":"Point"}
}