{
  "type": "Feature",
  "properties": {
    "iso:country":"GB",
    "wof:name":"DA15 9AS",
    "wof:placetype":"postalcode"
},
  "geometry": {"coordinates":[0.11595639948909,51.43552003270302],"type":"Point"}
}