{
  "type": "Feature",
  "properties": {
    "iso:country": "GB",
    "wof:name": "DA15 9AS",
    "wof:placetype": "postalcode"
  },
  "geometry": {"coordinates":[0.115956,51.43552],"type":"Point"}
}
