{
  "type": "Feature",
  "properties": {
    "iso:country":"GB",
    "wof:name":"LL40 1TH",
    "wof:placetype":"postalcode"
},
  "geometry": {"coordinates":[-3.91616764564875,52.73262381157021],"type":"Point"}
}