{
  "type": "Feature",
  "properties": {
    "iso:country":"GB",
    "wof:name":"PE1 2UY",
    "wof:placetype":"postalcode"
},
  "geometry": {"coordinates":[-0.23783915852809,52.5819614781375],"type":"Point"}
}