{
  "type": "Feature",
  "properties": {
    "iso:country": "GB",
    "wof:name": "B14 6RE",
    "wof:placetype": "postalcode"
  },
  "geometry": {"coordinates":[-1.909857,52.423408],"type":"Point"}
}
