{
  "type": "Feature",
  "properties": {
    "iso:country":"GB",
    "wof:name":"IP14 3QF",
    "wof:placetype":"postalcode"
},
  "geometry": {"coordinates":[0.98610357267784,52.2036713311202],"type":"Point"}
}