{
  "type": "Feature",
  "properties": {
    "iso:country":"GB",
    "wof:name":"SO24 0QS",
    "wof:placetype":"postalcode"
},
  "geometry": {"coordinates":[-1.18641413781231,51.08691394880925],"type":"Point"}
}