{
  "type": "Feature",
  "properties": {
    "date:inception_lower": "1980-01-01",
    "date:inception_upper": "1980-01-01",
    "iso:country": "GB",
    "wof:name": "SO24 0QS",
    "wof:placetype": "postalcode"
  },
  "geometry": {"coordinates":[-1.186399,51.086909],"type":"Point"}
}
