{
  "type": "Feature",
  "properties": {
    "iso:country": "GB",
    "wof:name": "WV3 9JS",
    "wof:placetype": "postalcode"
  },
  "geometry": {"coordinates":[-2.157759,52.587924],"type":"Point"}
}
