{
  "type": "Feature",
  "properties": {
    "date:inception_lower": "1996-12-01",
    "date:inception_upper": "1996-12-01",
    "iso:country": "GB",
    "wof:name": "G15 8JU",
    "wof:placetype": "postalcode"
  },
  "geometry": {"coordinates":[-4.377504,55.91713],"type":"Point"}
}
