{
  "type": "Feature",
  "properties": {
    "iso:country":"GB",
    "wof:name":"DT11 7QR",
    "wof:placetype":"postalcode"
},
  "geometry": {"coordinates":[-2.16065455897446,50.85963650216546],"type":"Point"}
}