{
  "type": "Feature",
  "properties": {
    "iso:country": "GB",
    "wof:name": "DT11 7QR",
    "wof:placetype": "postalcode"
  },
  "geometry": {"coordinates":[-2.160655,50.859636],"type":"Point"}
}
