{
  "type": "Feature",
  "properties": {
    "date:inception_lower": "2001-12-01",
    "date:inception_upper": "2001-12-01",
    "iso:country": "GB",
    "wof:name": "BA14 7TH",
    "wof:placetype": "postalcode"
  },
  "geometry": {"coordinates":[-2.178719,51.327325],"type":"Point"}
}
