{
  "type": "Feature",
  "properties": {
    "iso:country":"GB",
    "wof:name":"BA14 7TH",
    "wof:placetype":"postalcode"
},
  "geometry": {"coordinates":[-2.17871902649695,51.32732536761473],"type":"Point"}
}