{
  "type": "Feature",
  "properties": {
    "iso:country":"GB",
    "wof:name":"BN2 1DY",
    "wof:placetype":"postalcode"
},
  "geometry": {"coordinates":[-0.1198011532241,50.81755192010495],"type":"Point"}
}