{
  "type": "Feature",
  "properties": {
    "date:inception_lower": "1980-01-01",
    "date:inception_upper": "1980-01-01",
    "iso:country": "GB",
    "wof:name": "WF17 0PT",
    "wof:placetype": "postalcode"
  },
  "geometry": {"coordinates":[-1.617713,53.720095],"type":"Point"}
}
