{
  "type": "Feature",
  "properties": {
    "iso:country": "GB",
    "wof:name": "WF17 0PT",
    "wof:placetype": "postalcode"
  },
  "geometry": {"coordinates":[-1.618742,53.720215],"type":"Point"}
}
