{
  "type": "Feature",
  "properties": {
    "date:inception_lower": "2016-02-01",
    "date:inception_upper": "2016-02-01",
    "iso:country": "GB",
    "wof:name": "PR4 0DS",
    "wof:placetype": "postalcode"
  },
  "geometry": {"coordinates":[-2.762909,53.788653],"type":"Point"}
}
