{
  "type": "Feature",
  "properties": {
    "iso:country":"GB",
    "wof:name":"B43 7DJ",
    "wof:placetype":"postalcode"
},
  "geometry": {"coordinates":[-1.90867810201153,52.56006317588174],"type":"Point"}
}