{
  "type": "Feature",
  "properties": {
    "iso:country": "GB",
    "wof:name": "B43 7DJ",
    "wof:placetype": "postalcode"
  },
  "geometry": {"coordinates":[-1.908678,52.560063],"type":"Point"}
}
