{
  "type": "Feature",
  "properties": {
    "date:inception_lower": "1980-01-01",
    "date:inception_upper": "1980-01-01",
    "iso:country": "GB",
    "wof:name": "CB2 1HN",
    "wof:placetype": "postalcode"
  },
  "geometry": {"coordinates":[0.123421,52.197673],"type":"Point"}
}
