{
  "type": "Feature",
  "properties": {
    "iso:country":"GB",
    "wof:name":"CB2 1HN",
    "wof:placetype":"postalcode"
},
  "geometry": {"coordinates":[0.123420787707,52.19767307237457],"type":"Point"}
}