{
  "type": "Feature",
  "properties": {
    "iso:country":"GB",
    "wof:name":"DY6 8LX",
    "wof:placetype":"postalcode"
},
  "geometry": {"coordinates":[-2.15380356090424,52.48705390843597],"type":"Point"}
}