{
  "type": "Feature",
  "properties": {
    "date:inception_lower":"1993-01-01",
    "date:inception_upper":"1993-01-31",
    "iso:country":"GB",
    "wof:name":"CF64 4TN",
    "wof:placetype":"postalcode"
},
  "geometry": {"coordinates":[-3.217525,51.429261],"type":"Point"}
}