{
  "type": "Feature",
  "properties": {
    "date:inception_lower": "2024-10-01",
    "date:inception_upper": "2024-10-01",
    "iso:country": "GB",
    "wof:name": "PE38 9FH",
    "wof:placetype": "postalcode"
  },
  "geometry": {"coordinates":[0.398046,52.598207],"type":"Point"}
}
