{
  "type": "Feature",
  "properties": {
    "iso:country":"GB",
    "wof:name":"NE16 4PJ",
    "wof:placetype":"postalcode"
},
  "geometry": {"coordinates":[-1.67797140345379,54.93812147785171],"type":"Point"}
}