{
  "type": "Feature",
  "properties": {
    "date:inception_lower":"1980-01-01",
    "date:inception_upper":"1980-01-31",
    "iso:country":"GB",
    "wof:name":"NE16 4PJ",
    "wof:placetype":"postalcode"
},
  "geometry": {"coordinates":[-1.677971,54.938121],"type":"Point"}
}