{
  "type": "Feature",
  "properties": {
    "iso:country": "GB",
    "wof:name": "EX4 0AZ",
    "wof:placetype": "postalcode"
  },
  "geometry": {"coordinates":[-3.476777,50.759084],"type":"Point"}
}
