{
  "type": "Feature",
  "properties": {
    "iso:country":"GB",
    "wof:name":"EX4 0AZ",
    "wof:placetype":"postalcode"
},
  "geometry": {"coordinates":[-3.47677732203487,50.75908396855537],"type":"Point"}
}