{
  "type": "Feature",
  "properties": {
    "date:inception_lower": "1999-06-01",
    "date:inception_upper": "1999-06-01",
    "iso:country": "GB",
    "wof:name": "G11 6HT",
    "wof:placetype": "postalcode"
  },
  "geometry": {"coordinates":[-4.325469,55.870804],"type":"Point"}
}
