{
  "type": "Feature",
  "properties": {
    "iso:country":"GB",
    "wof:name":"G11 6HT",
    "wof:placetype":"postalcode"
},
  "geometry": {"coordinates":[-4.32546911107338,55.87080397463538],"type":"Point"}
}