{
  "type": "Feature",
  "properties": {
    "iso:country": "GB",
    "wof:name": "HA1 4QW",
    "wof:placetype": "postalcode"
  },
  "geometry": {"coordinates":[-0.346337,51.587192],"type":"Point"}
}
