{
  "type": "Feature",
  "properties": {
    "iso:country":"GB",
    "wof:name":"HA1 4QW",
    "wof:placetype":"postalcode"
},
  "geometry": {"coordinates":[-0.34618418081692,51.5872416211559],"type":"Point"}
}