{
  "type": "Feature",
  "properties": {
    "date:inception_lower": "1980-01-01",
    "date:inception_upper": "1980-01-01",
    "iso:country": "GB",
    "wof:name": "TF10 8LT",
    "wof:placetype": "postalcode"
  },
  "geometry": {"coordinates":[-2.419393,52.763364],"type":"Point"}
}
