{
  "type": "Feature",
  "properties": {
    "iso:country": "GB",
    "wof:name": "WS15 1PS",
    "wof:placetype": "postalcode"
  },
  "geometry": {"coordinates":[-1.910066,52.744694],"type":"Point"}
}
