{
  "type": "Feature",
  "properties": {
    "iso:country":"GB",
    "wof:name":"WS15 1PS",
    "wof:placetype":"postalcode"
},
  "geometry": {"coordinates":[-1.91032662805225,52.74298681793267],"type":"Point"}
}