{
  "type": "Feature",
  "properties": {
    "iso:country": "GB",
    "wof:name": "DN3 3QR",
    "wof:placetype": "postalcode"
  },
  "geometry": {"coordinates":[-1.047393,53.506238],"type":"Point"}
}
