{
  "type": "Feature",
  "properties": {
    "date:inception_lower": "1993-08-01",
    "date:inception_upper": "1993-08-01",
    "iso:country": "GB",
    "wof:name": "NN10 6UU",
    "wof:placetype": "postalcode"
  },
  "geometry": {"coordinates":[-0.60773,52.294969],"type":"Point"}
}
