{
  "type": "Feature",
  "properties": {
    "date:inception_lower": "2002-12-01",
    "date:inception_upper": "2002-12-01",
    "iso:country": "GB",
    "wof:name": "WF3 3TY",
    "wof:placetype": "postalcode"
  },
  "geometry": {"coordinates":[-1.507457,53.73893],"type":"Point"}
}
