{
  "type": "Feature",
  "properties": {
    "date:inception_lower":"1980-01-01",
    "date:inception_upper":"1980-01-31",
    "iso:country":"GB",
    "wof:name":"BL8 4NL",
    "wof:placetype":"postalcode"
},
  "geometry": {"coordinates":[-2.33309,53.637992],"type":"Point"}
}