{
  "type": "Feature",
  "properties": {
    "iso:country":"GB",
    "wof:name":"BL8 4NL",
    "wof:placetype":"postalcode"
},
  "geometry": {"coordinates":[-2.33308993169607,53.63799218262759],"type":"Point"}
}