{
  "type": "Feature",
  "properties": {
    "iso:country": "GB",
    "wof:name": "SG4 0UB",
    "wof:placetype": "postalcode"
  },
  "geometry": {"coordinates":[-0.263569,51.96267],"type":"Point"}
}
