{
  "type": "Feature",
  "properties": {
    "iso:country": "GB",
    "wof:name": "YO30 6HZ",
    "wof:placetype": "postalcode"
  },
  "geometry": {"coordinates":[-1.090432,53.967399],"type":"Point"}
}
