{
  "type": "Feature",
  "properties": {
    "iso:country":"GB",
    "wof:name":"PH21 1NS",
    "wof:placetype":"postalcode"
},
  "geometry": {"coordinates":[-4.01119472933013,57.07694468468468],"type":"Point"}
}