{
  "type": "Feature",
  "properties": {
    "iso:country": "GB",
    "wof:name": "TW14 0EA",
    "wof:placetype": "postalcode"
  },
  "geometry": {"coordinates":[-0.398565,51.45134],"type":"Point"}
}
