{
  "type": "Feature",
  "properties": {
    "iso:country":"GB",
    "wof:name":"TW14 0EA",
    "wof:placetype":"postalcode"
},
  "geometry": {"coordinates":[-0.39856474063886,51.45134016404815],"type":"Point"}
}