{
  "type": "Feature",
  "properties": {
    "iso:country":"GB",
    "wof:name":"RG14 7RY",
    "wof:placetype":"postalcode"
},
  "geometry": {"coordinates":[-1.30691355527156,51.39142215965678],"type":"Point"}
}