{
  "type": "Feature",
  "properties": {
    "date:inception_lower": "2011-08-01",
    "date:inception_upper": "2011-08-01",
    "iso:country": "GB",
    "wof:name": "TS3 7BF",
    "wof:placetype": "postalcode"
  },
  "geometry": {"coordinates":[-1.207882,54.564391],"type":"Point"}
}
