{
  "type": "Feature",
  "properties": {
    "date:inception_lower":"2004-06-01",
    "date:inception_upper":"2004-06-30",
    "iso:country":"GB",
    "wof:name":"DN3 3WR",
    "wof:placetype":"postalcode"
},
  "geometry": {"coordinates":[-1.125723,53.512942],"type":"Point"}
}