{
  "type": "Feature",
  "properties": {
    "date:inception_lower": "1980-01-01",
    "date:inception_upper": "1980-01-01",
    "iso:country": "GB",
    "wof:name": "UB10 9EQ",
    "wof:placetype": "postalcode"
  },
  "geometry": {"coordinates":[-0.435268,51.546326],"type":"Point"}
}
