{
  "type": "Feature",
  "properties": {
    "date:inception_lower": "2011-03-01",
    "date:inception_upper": "2011-03-01",
    "iso:country": "GB",
    "wof:name": "CA11 8RN",
    "wof:placetype": "postalcode"
  },
  "geometry": {"coordinates":[-2.749183,54.661361],"type":"Point"}
}
