{
  "type": "Feature",
  "properties": {
    "iso:country":"GB",
    "wof:name":"G4 9SP",
    "wof:placetype":"postalcode"
},
  "geometry": {"coordinates":[-4.26085724568657,55.87711317645513],"type":"Point"}
}