{
  "type": "Feature",
  "properties": {
    "iso:country":"GB",
    "wof:name":"PO16 8YD",
    "wof:placetype":"postalcode"
},
  "geometry": {"coordinates":[-1.15621271394528,50.8481022593148],"type":"Point"}
}