{
  "type": "Feature",
  "properties": {
    "iso:country": "GB",
    "wof:name": "PO16 8YD",
    "wof:placetype": "postalcode"
  },
  "geometry": {"coordinates":[-1.156213,50.848102],"type":"Point"}
}
