{
  "type": "Feature",
  "properties": {
    "date:inception_lower": "1994-12-01",
    "date:inception_upper": "1994-12-01",
    "iso:country": "GB",
    "wof:name": "PO16 8YD",
    "wof:placetype": "postalcode"
  },
  "geometry": {"coordinates":[-1.156213,50.848102],"type":"Point"}
}
