{
  "type": "Feature",
  "properties": {
    "iso:country": "GB",
    "wof:name": "HP20 2FZ",
    "wof:placetype": "postalcode"
  },
  "geometry": {"coordinates":[-0.813423,51.821254],"type":"Point"}
}
