{
  "type": "Feature",
  "properties": {
    "iso:country":"GB",
    "wof:name":"HP20 2FZ",
    "wof:placetype":"postalcode"
},
  "geometry": {"coordinates":[-0.81342285000586,51.82125399410977],"type":"Point"}
}