{
  "type": "Feature",
  "properties": {
    "iso:country": "GB",
    "wof:name": "BD23 3QJ",
    "wof:placetype": "postalcode"
  },
  "geometry": {"coordinates":[-2.116252,54.008716],"type":"Point"}
}
