{
  "type": "Feature",
  "properties": {
    "iso:country":"GB",
    "wof:name":"RG30 2DT",
    "wof:placetype":"postalcode"
},
  "geometry": {"coordinates":[-1.00333700502854,51.44712397235902],"type":"Point"}
}