{
  "type": "Feature",
  "properties": {
    "iso:country": "GB",
    "wof:name": "RG30 2DT",
    "wof:placetype": "postalcode"
  },
  "geometry": {"coordinates":[-1.003337,51.447124],"type":"Point"}
}
