{
  "type": "Feature",
  "properties": {
    "date:inception_lower": "1995-07-01",
    "date:inception_upper": "1995-07-01",
    "iso:country": "GB",
    "wof:name": "RG30 2DT",
    "wof:placetype": "postalcode"
  },
  "geometry": {"coordinates":[-1.003337,51.447124],"type":"Point"}
}
