{
  "type": "Feature",
  "properties": {
    "iso:country": "GB",
    "wof:name": "NE16 5HB",
    "wof:placetype": "postalcode"
  },
  "geometry": {"coordinates":[-1.67249,54.923154],"type":"Point"}
}
