{
  "type": "Feature",
  "properties": {
    "iso:country":"GB",
    "wof:name":"CA2 5JG",
    "wof:placetype":"postalcode"
},
  "geometry": {"coordinates":[-2.94324550538818,54.88456052459549],"type":"Point"}
}