{
  "type": "Feature",
  "properties": {
    "date:inception_lower": "2000-06-01",
    "date:inception_upper": "2000-06-01",
    "iso:country": "GB",
    "wof:name": "CA2 5JG",
    "wof:placetype": "postalcode"
  },
  "geometry": {"coordinates":[-2.943245,54.884561],"type":"Point"}
}
