{
  "type": "Feature",
  "properties": {
    "iso:country":"GB",
    "wof:name":"DH4 5EH",
    "wof:placetype":"postalcode"
},
  "geometry": {"coordinates":[-1.47797960802596,54.84176698773317],"type":"Point"}
}