{
  "type": "Feature",
  "properties": {
    "date:inception_lower": "1995-12-01",
    "date:inception_upper": "1995-12-01",
    "iso:country": "GB",
    "wof:name": "DH4 5EH",
    "wof:placetype": "postalcode"
  },
  "geometry": {"coordinates":[-1.47798,54.841767],"type":"Point"}
}
