{
  "type": "Feature",
  "properties": {
    "iso:country":"GB",
    "wof:name":"BS20 8HT",
    "wof:placetype":"postalcode"
},
  "geometry": {"coordinates":[-2.80146530256575,51.47741725197516],"type":"Point"}
}