{
  "type": "Feature",
  "properties": {
    "iso:country": "GB",
    "wof:name": "BS20 8HT",
    "wof:placetype": "postalcode"
  },
  "geometry": {"coordinates":[-2.801465,51.477417],"type":"Point"}
}
