{
  "type": "Feature",
  "properties": {
    "iso:country":"GB",
    "wof:name":"NE48 1NJ",
    "wof:placetype":"postalcode"
},
  "geometry": {"coordinates":[-2.34579130292736,55.2236596937467],"type":"Point"}
}