{
  "type": "Feature",
  "properties": {
    "iso:country":"GB",
    "wof:name":"DA11 0LY",
    "wof:placetype":"postalcode"
},
  "geometry": {"coordinates":[0.35542450096896,51.43587092256357],"type":"Point"}
}