{
  "type": "Feature",
  "properties": {
    "iso:country": "GB",
    "wof:name": "EH3 5LZ",
    "wof:placetype": "postalcode"
  },
  "geometry": {"coordinates":[-3.202999,55.968053],"type":"Point"}
}
