{
  "type": "Feature",
  "properties": {
    "iso:country":"GB",
    "wof:name":"OX29 7PT",
    "wof:placetype":"postalcode"
},
  "geometry": {"coordinates":[-1.46046945470037,51.75697605974895],"type":"Point"}
}