{
  "type": "Feature",
  "properties": {
    "date:inception_lower": "2001-06-01",
    "date:inception_upper": "2001-06-01",
    "iso:country": "GB",
    "wof:name": "OX29 7PT",
    "wof:placetype": "postalcode"
  },
  "geometry": {"coordinates":[-1.460469,51.756976],"type":"Point"}
}
