{
  "type": "Feature",
  "properties": {
    "iso:country":"GB",
    "wof:name":"DL2 2PQ",
    "wof:placetype":"postalcode"
},
  "geometry": {"coordinates":[-1.49025060920906,54.47000886682719],"type":"Point"}
}