{
  "type": "Feature",
  "properties": {
    "iso:country": "GB",
    "wof:name": "DL2 2PQ",
    "wof:placetype": "postalcode"
  },
  "geometry": {"coordinates":[-1.490251,54.470009],"type":"Point"}
}
