{
  "type": "Feature",
  "properties": {
    "iso:country": "GB",
    "wof:name": "EH11 2RB",
    "wof:placetype": "postalcode"
  },
  "geometry": {"coordinates":[-3.237747,55.937374],"type":"Point"}
}
