{
  "type": "Feature",
  "properties": {
    "iso:country":"GB",
    "wof:name":"NE61 4DT",
    "wof:placetype":"postalcode"
},
  "geometry": {"coordinates":[-1.94031315234108,55.17175730544659],"type":"Point"}
}