{
  "type": "Feature",
  "properties": {
    "iso:country":"GB",
    "wof:name":"SY23 2DR",
    "wof:placetype":"postalcode"
},
  "geometry": {"coordinates":[-4.08623271566875,52.4156302101708],"type":"Point"}
}