{
  "type": "Feature",
  "properties": {
    "iso:country": "GB",
    "wof:name": "SY23 2DR",
    "wof:placetype": "postalcode"
  },
  "geometry": {"coordinates":[-4.086233,52.41563],"type":"Point"}
}
