{
  "type": "Feature",
  "properties": {
    "iso:country": "GB",
    "wof:name": "RG14 5NF",
    "wof:placetype": "postalcode"
  },
  "geometry": {"coordinates":[-1.33698,51.397432],"type":"Point"}
}
