{
  "type": "Feature",
  "properties": {
    "iso:country":"GB",
    "wof:name":"RG14 5NF",
    "wof:placetype":"postalcode"
},
  "geometry": {"coordinates":[-1.33697970785049,51.39743170130212],"type":"Point"}
}