{
  "type": "Feature",
  "properties": {
    "date:inception_lower":"1986-07-01",
    "date:inception_upper":"1986-07-31",
    "iso:country":"GB",
    "wof:name":"RG14 5NF",
    "wof:placetype":"postalcode"
},
  "geometry": {"coordinates":[-1.33698,51.397432],"type":"Point"}
}