{
  "type": "Feature",
  "properties": {
    "iso:country": "GB",
    "wof:name": "RG26 5AD",
    "wof:placetype": "postalcode"
  },
  "geometry": {"coordinates":[-1.060686,51.332456],"type":"Point"}
}
