{
  "type": "Feature",
  "properties": {
    "iso:country":"GB",
    "wof:name":"CH49 3NF",
    "wof:placetype":"postalcode"
},
  "geometry": {"coordinates":[-3.12517613727863,53.3764519029825],"type":"Point"}
}