{
  "type": "Feature",
  "properties": {
    "iso:country":"GB",
    "wof:name":"LA23 2DB",
    "wof:placetype":"postalcode"
},
  "geometry": {"coordinates":[-2.90812280521296,54.37284329361847],"type":"Point"}
}