{
  "type": "Feature",
  "properties": {
    "date:inception_lower":"2018-05-01",
    "date:inception_upper":"2018-05-31",
    "iso:country":"GB",
    "wof:name":"PO32 6RR",
    "wof:placetype":"postalcode"
},
  "geometry": {"coordinates":[-1.285506,50.756105],"type":"Point"}
}