{
  "type": "Feature",
  "properties": {
    "iso:country":"GB",
    "wof:name":"PE4 6RR",
    "wof:placetype":"postalcode"
},
  "geometry": {"coordinates":[-0.27307602877284,52.61600746488946],"type":"Point"}
}