{
  "type": "Feature",
  "properties": {
    "iso:country": "GB",
    "wof:name": "PE4 6RR",
    "wof:placetype": "postalcode"
  },
  "geometry": {"coordinates":[-0.273076,52.616007],"type":"Point"}
}
