{
  "type": "Feature",
  "properties": {
    "iso:country": "GB",
    "wof:name": "NR6 7LE",
    "wof:placetype": "postalcode"
  },
  "geometry": {"coordinates":[1.306489,52.660366],"type":"Point"}
}
