{
  "type": "Feature",
  "properties": {
    "date:inception_lower":"1980-01-01",
    "date:inception_upper":"1980-01-31",
    "iso:country":"GB",
    "wof:name":"DD5 4EB",
    "wof:placetype":"postalcode"
},
  "geometry": {"coordinates":[-2.812339,56.484741],"type":"Point"}
}