{
  "type": "Feature",
  "properties": {
    "iso:country":"GB",
    "wof:name":"DD5 4EB",
    "wof:placetype":"postalcode"
},
  "geometry": {"coordinates":[-2.81233909740291,56.48474076529024],"type":"Point"}
}