{
  "type": "Feature",
  "properties": {
    "date:inception_lower": "1980-01-01",
    "date:inception_upper": "1980-01-01",
    "iso:country": "GB",
    "wof:name": "CW6 9RU",
    "wof:placetype": "postalcode"
  },
  "geometry": {"coordinates":[-2.660568,53.100254],"type":"Point"}
}
