{
  "type": "Feature",
  "properties": {
    "iso:country":"GB",
    "wof:name":"TW18 3HQ",
    "wof:placetype":"postalcode"
},
  "geometry": {"coordinates":[-0.51782961149142,51.42782919906163],"type":"Point"}
}