{
  "type": "Feature",
  "properties": {
    "iso:country": "GB",
    "wof:name": "IG7 6HZ",
    "wof:placetype": "postalcode"
  },
  "geometry": {"coordinates":[0.107061,51.618452],"type":"Point"}
}
