{
  "type": "Feature",
  "properties": {
    "date:inception_lower": "1980-01-01",
    "date:inception_upper": "1980-01-01",
    "iso:country": "GB",
    "wof:name": "IG7 6HZ",
    "wof:placetype": "postalcode"
  },
  "geometry": {"coordinates":[0.103466,51.617563],"type":"Point"}
}
