{
  "type": "Feature",
  "properties": {
    "iso:country":"GB",
    "wof:name":"IG7 6HZ",
    "wof:placetype":"postalcode"
},
  "geometry": {"coordinates":[0.10703363497486,51.61845026342458],"type":"Point"}
}