{
  "type": "Feature",
  "properties": {
    "iso:country":"GB",
    "wof:name":"PL30 5JE",
    "wof:placetype":"postalcode"
},
  "geometry": {"coordinates":[-4.76427851705957,50.43493244292434],"type":"Point"}
}