{
  "type": "Feature",
  "properties": {
    "iso:country":"GB",
    "wof:name":"B92 9LU",
    "wof:placetype":"postalcode"
},
  "geometry": {"coordinates":[-1.76449224455446,52.43230606401094],"type":"Point"}
}