{
  "type": "Feature",
  "properties": {
    "iso:country":"GB",
    "wof:name":"HD2 2HD",
    "wof:placetype":"postalcode"
},
  "geometry": {"coordinates":[-1.78732336087589,53.67541601537024],"type":"Point"}
}