{
  "type": "Feature",
  "properties": {
    "iso:country": "GB",
    "wof:name": "HD2 2HD",
    "wof:placetype": "postalcode"
  },
  "geometry": {"coordinates":[-1.787323,53.675416],"type":"Point"}
}
