{
  "type": "Feature",
  "properties": {
    "iso:country":"GB",
    "wof:name":"WA7 2FQ",
    "wof:placetype":"postalcode"
},
  "geometry": {"coordinates":[-2.7006782194,53.32645838886599],"type":"Point"}
}