{
  "type": "Feature",
  "properties": {
    "iso:country": "GB",
    "wof:name": "PO21 4RY",
    "wof:placetype": "postalcode"
  },
  "geometry": {"coordinates":[-0.736106,50.773247],"type":"Point"}
}
