{
  "type": "Feature",
  "properties": {
    "iso:country":"GB",
    "wof:name":"PO21 4RY",
    "wof:placetype":"postalcode"
},
  "geometry": {"coordinates":[-0.73610621205039,50.77324684017572],"type":"Point"}
}