{
  "type": "Feature",
  "properties": {
    "iso:country":"GB",
    "wof:name":"SE24 0LH",
    "wof:placetype":"postalcode"
},
  "geometry": {"coordinates":[-0.10995090272972,51.45876873595726],"type":"Point"}
}