{
  "type": "Feature",
  "properties": {
    "date:inception_lower":"2010-08-01",
    "date:inception_upper":"2010-08-31",
    "iso:country":"GB",
    "wof:name":"S20 5FG",
    "wof:placetype":"postalcode"
},
  "geometry": {"coordinates":[-1.361551,53.325471],"type":"Point"}
}