{
  "type": "Feature",
  "properties": {
    "iso:country": "GB",
    "wof:name": "S20 5FG",
    "wof:placetype": "postalcode"
  },
  "geometry": {"coordinates":[-1.361551,53.325471],"type":"Point"}
}
