{
  "type": "Feature",
  "properties": {
    "iso:country":"GB",
    "wof:name":"S20 5FG",
    "wof:placetype":"postalcode"
},
  "geometry": {"coordinates":[-1.36155140001631,53.32547121849829],"type":"Point"}
}