{
  "type": "Feature",
  "properties": {
    "date:inception_lower": "2000-10-01",
    "date:inception_upper": "2000-10-01",
    "iso:country": "GB",
    "wof:name": "W1D 6BA",
    "wof:placetype": "postalcode"
  },
  "geometry": {"coordinates":[-0.132925,51.512004],"type":"Point"}
}
