{
  "type": "Feature",
  "properties": {
    "iso:country":"GB",
    "wof:name":"W1D 6BA",
    "wof:placetype":"postalcode"
},
  "geometry": {"coordinates":[-0.13292553009333,51.51200409934426],"type":"Point"}
}