{
  "type": "Feature",
  "properties": {
    "iso:country":"GB",
    "wof:name":"AB43 8WG",
    "wof:placetype":"postalcode"
},
  "geometry": {"coordinates":[-1.93646405874389,57.67331493284176],"type":"Point"}
}