{
  "type": "Feature",
  "properties": {
    "date:inception_lower": "1980-01-01",
    "date:inception_upper": "1980-01-01",
    "iso:country": "GB",
    "wof:name": "SW18 1RQ",
    "wof:placetype": "postalcode"
  },
  "geometry": {"coordinates":[-0.200097,51.455331],"type":"Point"}
}
