{
  "type": "Feature",
  "properties": {
    "date:inception_lower":"1980-01-01",
    "date:inception_upper":"1980-01-31",
    "iso:country":"GB",
    "wof:name":"WA6 8HJ",
    "wof:placetype":"postalcode"
},
  "geometry": {"coordinates":[-2.667318,53.270721],"type":"Point"}
}