{
  "type": "Feature",
  "properties": {
    "iso:country":"GB",
    "wof:name":"WA6 8HJ",
    "wof:placetype":"postalcode"
},
  "geometry": {"coordinates":[-2.66731778975146,53.27072086796576],"type":"Point"}
}