{
  "type": "Feature",
  "properties": {
    "date:inception_lower":"2010-03-01",
    "date:inception_upper":"2010-03-31",
    "iso:country":"GB",
    "wof:name":"NP4 9AW",
    "wof:placetype":"postalcode"
},
  "geometry": {"coordinates":[-3.078035,51.773241],"type":"Point"}
}