{
  "type": "Feature",
  "properties": {
    "iso:country":"GB",
    "wof:name":"NP4 9AW",
    "wof:placetype":"postalcode"
},
  "geometry": {"coordinates":[-3.07808364173136,51.77374008959536],"type":"Point"}
}