{
  "type": "Feature",
  "properties": {
    "iso:country": "GB",
    "wof:name": "NP4 9AW",
    "wof:placetype": "postalcode"
  },
  "geometry": {"coordinates":[-3.078035,51.773241],"type":"Point"}
}
