{
  "type": "Feature",
  "properties": {
    "iso:country": "GB",
    "wof:name": "SS1 2UN",
    "wof:placetype": "postalcode"
  },
  "geometry": {"coordinates":[0.733267,51.538182],"type":"Point"}
}
