{
  "type": "Feature",
  "properties": {
    "date:inception_lower": "1980-01-01",
    "date:inception_upper": "1980-01-01",
    "iso:country": "GB",
    "wof:name": "LL29 8UB",
    "wof:placetype": "postalcode"
  },
  "geometry": {"coordinates":[-3.668067,53.280578],"type":"Point"}
}
