{
  "type": "Feature",
  "properties": {
    "iso:country":"GB",
    "wof:name":"LL29 8UB",
    "wof:placetype":"postalcode"
},
  "geometry": {"coordinates":[-3.66806692220153,53.28057816429464],"type":"Point"}
}