{
  "type": "Feature",
  "properties": {
    "iso:country": "GB",
    "wof:name": "DN20 9DJ",
    "wof:placetype": "postalcode"
  },
  "geometry": {"coordinates":[-0.537994,53.529698],"type":"Point"}
}
