{
  "type": "Feature",
  "properties": {
    "iso:country":"GB",
    "wof:name":"CR0 9EW",
    "wof:placetype":"postalcode"
},
  "geometry": {"coordinates":[-0.01892205829583,51.35651951090047],"type":"Point"}
}