{
  "type": "Feature",
  "properties": {
    "iso:country": "GB",
    "wof:name": "DT4 8AG",
    "wof:placetype": "postalcode"
  },
  "geometry": {"coordinates":[-2.456374,50.608693],"type":"Point"}
}
