{
  "type": "Feature",
  "properties": {
    "date:inception_lower": "1983-03-01",
    "date:inception_upper": "1983-03-01",
    "iso:country": "GB",
    "wof:name": "DT4 8AG",
    "wof:placetype": "postalcode"
  },
  "geometry": {"coordinates":[-2.456388,50.608702],"type":"Point"}
}
