{
  "type": "Feature",
  "properties": {
    "date:inception_lower":"1983-03-01",
    "date:inception_upper":"1983-03-31",
    "iso:country":"GB",
    "wof:name":"DT4 8AG",
    "wof:placetype":"postalcode"
},
  "geometry": {"coordinates":[-2.456374,50.608693],"type":"Point"}
}