{
  "type": "Feature",
  "properties": {
    "iso:country": "GB",
    "wof:name": "RH11 0RD",
    "wof:placetype": "postalcode"
  },
  "geometry": {"coordinates":[-0.226432,51.111113],"type":"Point"}
}
