{
  "type": "Feature",
  "properties": {
    "iso:country": "GB",
    "wof:name": "SM2 5GN",
    "wof:placetype": "postalcode"
  },
  "geometry": {"coordinates":[-0.190986,51.35585],"type":"Point"}
}
