{
  "type": "Feature",
  "properties": {
    "iso:country":"GB",
    "wof:name":"SS7 5HU",
    "wof:placetype":"postalcode"
},
  "geometry": {"coordinates":[0.55917306309732,51.55367573980058],"type":"Point"}
}