{
  "type": "Feature",
  "properties": {
    "iso:country": "GB",
    "wof:name": "SS7 5HU",
    "wof:placetype": "postalcode"
  },
  "geometry": {"coordinates":[0.559173,51.553676],"type":"Point"}
}
