{
  "type": "Feature",
  "properties": {
    "iso:country": "GB",
    "wof:name": "HR1 1UR",
    "wof:placetype": "postalcode"
  },
  "geometry": {"coordinates":[-2.682046,52.053718],"type":"Point"}
}
