{
  "type": "Feature",
  "properties": {
    "iso:country":"GB",
    "wof:name":"HR1 1UR",
    "wof:placetype":"postalcode"
},
  "geometry": {"coordinates":[-2.68204572472424,52.05371771696327],"type":"Point"}
}