{
  "type": "Feature",
  "properties": {
    "iso:country": "GB",
    "wof:name": "TN4 8NR",
    "wof:placetype": "postalcode"
  },
  "geometry": {"coordinates":[0.240973,51.135006],"type":"Point"}
}
