{
  "type": "Feature",
  "properties": {
    "iso:country":"GB",
    "wof:name":"TN4 8NR",
    "wof:placetype":"postalcode"
},
  "geometry": {"coordinates":[0.24097280226486,51.13500570803636],"type":"Point"}
}