{
  "type": "Feature",
  "properties": {
    "iso:country":"GB",
    "wof:name":"NE25 9QE",
    "wof:placetype":"postalcode"
},
  "geometry": {"coordinates":[-1.48610279389249,55.04298830306224],"type":"Point"}
}