{
  "type": "Feature",
  "properties": {
    "iso:country":"GB",
    "wof:name":"HG3 2RX",
    "wof:placetype":"postalcode"
},
  "geometry": {"coordinates":[-1.59572146652325,53.99943337509171],"type":"Point"}
}