{
  "type": "Feature",
  "properties": {
    "iso:country":"GB",
    "wof:name":"L26 6BH",
    "wof:placetype":"postalcode"
},
  "geometry": {"coordinates":[-2.82433224456554,53.36987529985618],"type":"Point"}
}