{
  "type": "Feature",
  "properties": {
    "date:inception_lower":"2005-01-01",
    "date:inception_upper":"2005-01-31",
    "iso:country":"GB",
    "wof:name":"L26 6BH",
    "wof:placetype":"postalcode"
},
  "geometry": {"coordinates":[-2.824332,53.369875],"type":"Point"}
}