{
  "type": "Feature",
  "properties": {
    "iso:country":"GB",
    "wof:name":"SE15 2RW",
    "wof:placetype":"postalcode"
},
  "geometry": {"coordinates":[-0.05965228918834,51.47987113294932],"type":"Point"}
}