{
  "type": "Feature",
  "properties": {
    "iso:country": "GB",
    "wof:name": "SE15 5JX",
    "wof:placetype": "postalcode"
  },
  "geometry": {"coordinates":[-0.075779,51.47557],"type":"Point"}
}
