{
  "type": "Feature",
  "properties": {
    "iso:country":"GB",
    "wof:name":"PA4 9LH",
    "wof:placetype":"postalcode"
},
  "geometry": {"coordinates":[-4.44022399154757,55.88628733396464],"type":"Point"}
}