{
  "type": "Feature",
  "properties": {
    "iso:country":"GB",
    "wof:name":"BL7 0DY",
    "wof:placetype":"postalcode"
},
  "geometry": {"coordinates":[-2.39742466981211,53.63753510208816],"type":"Point"}
}