{
  "type": "Feature",
  "properties": {
    "iso:country":"GB",
    "wof:name":"PA3 4JA",
    "wof:placetype":"postalcode"
},
  "geometry": {"coordinates":[-4.39233573073112,55.86093850578342],"type":"Point"}
}