{
  "type": "Feature",
  "properties": {
    "iso:country": "GB",
    "wof:name": "RH19 2LJ",
    "wof:placetype": "postalcode"
  },
  "geometry": {"coordinates":[-0.04066,51.139246],"type":"Point"}
}
