{
  "type": "Feature",
  "properties": {
    "iso:country":"GB",
    "wof:name":"RH19 2LJ",
    "wof:placetype":"postalcode"
},
  "geometry": {"coordinates":[-0.04066023582098,51.13924589168988],"type":"Point"}
}