{
  "type": "Feature",
  "properties": {
    "date:inception_lower": "1980-01-01",
    "date:inception_upper": "1980-01-01",
    "iso:country": "GB",
    "wof:name": "N14 4RD",
    "wof:placetype": "postalcode"
  },
  "geometry": {"coordinates":[-0.13255,51.645122],"type":"Point"}
}
