{
  "type": "Feature",
  "properties": {
    "iso:country":"GB",
    "wof:name":"N14 4RD",
    "wof:placetype":"postalcode"
},
  "geometry": {"coordinates":[-0.13254956216268,51.6451219820835],"type":"Point"}
}