{
  "type": "Feature",
  "properties": {
    "date:inception_lower":"2012-04-01",
    "date:inception_upper":"2012-04-30",
    "iso:country":"GB",
    "wof:name":"CT6 8BU",
    "wof:placetype":"postalcode"
},
  "geometry": {"coordinates":[1.105496,51.371766],"type":"Point"}
}