{
  "type": "Feature",
  "properties": {
    "iso:country": "GB",
    "wof:name": "SE17 2FU",
    "wof:placetype": "postalcode"
  },
  "geometry": {"coordinates":[-0.0854,51.48928],"type":"Point"}
}
