{
  "type": "Feature",
  "properties": {
    "iso:country": "GB",
    "wof:name": "EN11 0NS",
    "wof:placetype": "postalcode"
  },
  "geometry": {"coordinates":[-0.000084,51.770696],"type":"Point"}
}
