{
  "type": "Feature",
  "properties": {
    "iso:country":"GB",
    "wof:name":"EN11 0NS",
    "wof:placetype":"postalcode"
},
  "geometry": {"coordinates":[-0.00008359899229,51.77069554517837],"type":"Point"}
}