{
  "type": "Feature",
  "properties": {
    "date:inception_lower": "1980-01-01",
    "date:inception_upper": "1980-01-01",
    "iso:country": "GB",
    "wof:name": "BA1 6SW",
    "wof:placetype": "postalcode"
  },
  "geometry": {"coordinates":[-2.345386,51.399479],"type":"Point"}
}
