{
  "type": "Feature",
  "properties": {
    "iso:country":"GB",
    "wof:name":"BD1 4DQ",
    "wof:placetype":"postalcode"
},
  "geometry": {"coordinates":[-1.74743916811153,53.79884375129742],"type":"Point"}
}