{
  "type": "Feature",
  "properties": {
    "date:inception_lower": "2024-03-01",
    "date:inception_upper": "2024-03-01",
    "iso:country": "GB",
    "wof:name": "MK10 7PH",
    "wof:placetype": "postalcode"
  },
  "geometry": {"coordinates":[-0.687453,52.050897],"type":"Point"}
}
