{
  "type": "Feature",
  "properties": {
    "date:inception_lower": "1980-01-01",
    "date:inception_upper": "1980-01-01",
    "iso:country": "GB",
    "wof:name": "PL5 1PG",
    "wof:placetype": "postalcode"
  },
  "geometry": {"coordinates":[-4.188553,50.406188],"type":"Point"}
}
