{
  "type": "Feature",
  "properties": {
    "iso:country":"GB",
    "wof:name":"UB4 8PN",
    "wof:placetype":"postalcode"
},
  "geometry": {"coordinates":[-0.43414840092092,51.53775948015471],"type":"Point"}
}