{
  "type": "Feature",
  "properties": {
    "iso:country":"GB",
    "wof:name":"W1K 3EH",
    "wof:placetype":"postalcode"
},
  "geometry": {"coordinates":[-0.14829775216233,51.51035038170325],"type":"Point"}
}