{
  "type": "Feature",
  "properties": {
    "date:inception_lower":"1981-06-01",
    "date:inception_upper":"1981-06-30",
    "iso:country":"GB",
    "wof:name":"BH23 1HW",
    "wof:placetype":"postalcode"
},
  "geometry": {"coordinates":[-1.767105,50.734645],"type":"Point"}
}