{
  "type": "Feature",
  "properties": {
    "iso:country": "GB",
    "wof:name": "SN5 5RE",
    "wof:placetype": "postalcode"
  },
  "geometry": {"coordinates":[-1.829142,51.568168],"type":"Point"}
}
