{
  "type": "Feature",
  "properties": {
    "iso:country":"GB",
    "wof:name":"SN5 5RE",
    "wof:placetype":"postalcode"
},
  "geometry": {"coordinates":[-1.82914231287968,51.56816765326029],"type":"Point"}
}