{
  "type": "Feature",
  "properties": {
    "date:inception_lower": "2006-07-01",
    "date:inception_upper": "2006-07-01",
    "iso:country": "GB",
    "wof:name": "CF10 4JB",
    "wof:placetype": "postalcode"
  },
  "geometry": {"coordinates":[-3.160615,51.468999],"type":"Point"}
}
