{
  "type": "Feature",
  "properties": {
    "iso:country":"GB",
    "wof:name":"LA13 0LT",
    "wof:placetype":"postalcode"
},
  "geometry": {"coordinates":[-3.17966340288548,54.13385285810062],"type":"Point"}
}