{
  "type": "Feature",
  "properties": {
    "iso:country": "GB",
    "wof:name": "LA13 0LT",
    "wof:placetype": "postalcode"
  },
  "geometry": {"coordinates":[-3.179663,54.133853],"type":"Point"}
}
