{
  "type": "Feature",
  "properties": {
    "date:inception_lower": "2023-08-01",
    "date:inception_upper": "2023-08-01",
    "iso:country": "GB",
    "wof:name": "LN11 7EY",
    "wof:placetype": "postalcode"
  },
  "geometry": {"coordinates":[0.020403,53.369838],"type":"Point"}
}
