{
  "type": "Feature",
  "properties": {
    "iso:country":"GB",
    "wof:name":"GU4 7PT",
    "wof:placetype":"postalcode"
},
  "geometry": {"coordinates":[-0.57275825652115,51.265300387195],"type":"Point"}
}