{
  "type": "Feature",
  "properties": {
    "iso:country": "GB",
    "wof:name": "GU4 7PT",
    "wof:placetype": "postalcode"
  },
  "geometry": {"coordinates":[-0.572758,51.2653],"type":"Point"}
}
