{
  "type": "Feature",
  "properties": {
    "iso:country":"GB",
    "wof:name":"WR4 9UD",
    "wof:placetype":"postalcode"
},
  "geometry": {"coordinates":[-2.1994555649849,52.20688775508783],"type":"Point"}
}