{
  "type": "Feature",
  "properties": {
    "date:inception_lower": "1980-01-01",
    "date:inception_upper": "1980-01-01",
    "iso:country": "GB",
    "wof:name": "WR4 9UD",
    "wof:placetype": "postalcode"
  },
  "geometry": {"coordinates":[-2.199456,52.206888],"type":"Point"}
}
