{
  "type": "Feature",
  "properties": {
    "date:inception_lower": "1980-01-01",
    "date:inception_upper": "1980-01-01",
    "iso:country": "GB",
    "wof:name": "KA16 9HX",
    "wof:placetype": "postalcode"
  },
  "geometry": {"coordinates":[-4.344947,55.606201],"type":"Point"}
}
