{
  "type": "Feature",
  "properties": {
    "iso:country":"GB",
    "wof:name":"PA14 5JA",
    "wof:placetype":"postalcode"
},
  "geometry": {"coordinates":[-4.6892402096904,55.93430825853375],"type":"Point"}
}