{
  "type": "Feature",
  "properties": {
    "iso:country":"GB",
    "wof:name":"PE14 7PD",
    "wof:placetype":"postalcode"
},
  "geometry": {"coordinates":[0.22532980068948,52.72715182539542],"type":"Point"}
}