{
  "type": "Feature",
  "properties": {
    "date:inception_lower":"1980-01-01",
    "date:inception_upper":"1980-01-31",
    "iso:country":"GB",
    "wof:name":"PE14 7PD",
    "wof:placetype":"postalcode"
},
  "geometry": {"coordinates":[0.22533,52.727152],"type":"Point"}
}