{
  "type": "Feature",
  "properties": {
    "iso:country": "GB",
    "wof:name": "PE14 7PD",
    "wof:placetype": "postalcode"
  },
  "geometry": {"coordinates":[0.22533,52.727152],"type":"Point"}
}
