{
  "type": "Feature",
  "properties": {
    "date:inception_lower": "1980-04-01",
    "date:inception_upper": "1980-04-01",
    "iso:country": "GB",
    "wof:name": "ML8 5UH",
    "wof:placetype": "postalcode"
  },
  "geometry": {"coordinates":[-3.853827,55.736582],"type":"Point"}
}
