{
  "type": "Feature",
  "properties": {
    "iso:country":"GB",
    "wof:name":"ML8 5UH",
    "wof:placetype":"postalcode"
},
  "geometry": {"coordinates":[-3.8538273545187,55.73658157536289],"type":"Point"}
}