{
  "type": "Feature",
  "properties": {
    "iso:country":"GB",
    "wof:name":"CF39 9EB",
    "wof:placetype":"postalcode"
},
  "geometry": {"coordinates":[-3.42092974886961,51.6048793821164],"type":"Point"}
}