{
  "type": "Feature",
  "properties": {
    "iso:country":"GB",
    "wof:name":"PO2 7JY",
    "wof:placetype":"postalcode"
},
  "geometry": {"coordinates":[-1.06886999154839,50.81299605656486],"type":"Point"}
}