{
  "type": "Feature",
  "properties": {
    "iso:country": "GB",
    "wof:name": "RM15 4PH",
    "wof:placetype": "postalcode"
  },
  "geometry": {"coordinates":[0.251118,51.510657],"type":"Point"}
}
