{
  "type": "Feature",
  "properties": {
    "iso:country":"GB",
    "wof:name":"RM15 4PH",
    "wof:placetype":"postalcode"
},
  "geometry": {"coordinates":[0.25111762864682,51.51065679919852],"type":"Point"}
}