{
  "type": "Feature",
  "properties": {
    "iso:country":"GB",
    "wof:name":"CA14 4TB",
    "wof:placetype":"postalcode"
},
  "geometry": {"coordinates":[-3.45798896867092,54.60801325394807],"type":"Point"}
}