{
  "type": "Feature",
  "properties": {
    "iso:country": "GB",
    "wof:name": "CA14 4TB",
    "wof:placetype": "postalcode"
  },
  "geometry": {"coordinates":[-3.457989,54.608013],"type":"Point"}
}
