{
  "type": "Feature",
  "properties": {
    "iso:country":"GB",
    "wof:name":"L39 5AD",
    "wof:placetype":"postalcode"
},
  "geometry": {"coordinates":[-2.89767977553045,53.54918474760512],"type":"Point"}
}