{
  "type": "Feature",
  "properties": {
    "iso:country":"GB",
    "wof:name":"SK3 9QA",
    "wof:placetype":"postalcode"
},
  "geometry": {"coordinates":[-2.1708436914455,53.40025857127414],"type":"Point"}
}