{
  "type": "Feature",
  "properties": {
    "iso:country": "GB",
    "wof:name": "RG23 7EL",
    "wof:placetype": "postalcode"
  },
  "geometry": {"coordinates":[-1.2004,51.246136],"type":"Point"}
}
