{
  "type": "Feature",
  "properties": {
    "date:inception_lower":"1980-01-01",
    "date:inception_upper":"1980-01-31",
    "iso:country":"GB",
    "wof:name":"RG23 7EL",
    "wof:placetype":"postalcode"
},
  "geometry": {"coordinates":[-1.2004,51.246136],"type":"Point"}
}