{
  "type": "Feature",
  "properties": {
    "iso:country":"GB",
    "wof:name":"RG23 7EL",
    "wof:placetype":"postalcode"
},
  "geometry": {"coordinates":[-1.20510794805992,51.24397375642607],"type":"Point"}
}