{
  "type": "Feature",
  "properties": {
    "date:inception_lower": "2005-02-01",
    "date:inception_upper": "2005-02-01",
    "iso:country": "GB",
    "wof:name": "ST13 9TF",
    "wof:placetype": "postalcode"
  },
  "geometry": {"coordinates":[-2.024248,53.107533],"type":"Point"}
}
