{
  "type": "Feature",
  "properties": {
    "date:inception_lower":"2006-03-01",
    "date:inception_upper":"2006-03-31",
    "iso:country":"GB",
    "wof:name":"M5 3DL",
    "wof:placetype":"postalcode"
},
  "geometry": {"coordinates":[-2.281601,53.469053],"type":"Point"}
}