{
  "type": "Feature",
  "properties": {
    "iso:country":"GB",
    "wof:name":"M5 3DL",
    "wof:placetype":"postalcode"
},
  "geometry": {"coordinates":[-2.28160097266757,53.46905349608307],"type":"Point"}
}