{
  "type": "Feature",
  "properties": {
    "date:inception_lower":"2017-11-01",
    "date:inception_upper":"2017-11-30",
    "iso:country":"GB",
    "wof:name":"NG6 0DU",
    "wof:placetype":"postalcode"
},
  "geometry": {"coordinates":[-1.184422,52.989619],"type":"Point"}
}