{
  "type": "Feature",
  "properties": {
    "date:inception_lower": "2020-04-01",
    "date:inception_upper": "2020-04-01",
    "iso:country": "GB",
    "wof:name": "S42 6UQ",
    "wof:placetype": "postalcode"
  },
  "geometry": {"coordinates":[-1.418819,53.204424],"type":"Point"}
}
