{
  "type": "Feature",
  "properties": {
    "iso:country":"GB",
    "wof:name":"SE21 8LD",
    "wof:placetype":"postalcode"
},
  "geometry": {"coordinates":[-0.10296277361803,51.44399787003492],"type":"Point"}
}