{
  "type": "Feature",
  "properties": {
    "iso:country":"GB",
    "wof:name":"WS11 6DP",
    "wof:placetype":"postalcode"
},
  "geometry": {"coordinates":[-2.01472574155978,52.69999539565737],"type":"Point"}
}