{
  "type": "Feature",
  "properties": {
    "iso:country":"GB",
    "wof:name":"PO12 1QZ",
    "wof:placetype":"postalcode"
},
  "geometry": {"coordinates":[-1.13205360436294,50.79047961205342],"type":"Point"}
}