{
  "type": "Feature",
  "properties": {
    "iso:country": "GB",
    "wof:name": "DE65 6RQ",
    "wof:placetype": "postalcode"
  },
  "geometry": {"coordinates":[-1.596942,52.879948],"type":"Point"}
}
