{
  "type": "Feature",
  "properties": {
    "iso:country":"GB",
    "wof:name":"M43 6SJ",
    "wof:placetype":"postalcode"
},
  "geometry": {"coordinates":[-2.16132710650041,53.47661123492185],"type":"Point"}
}