{
  "type": "Feature",
  "properties": {
    "iso:country": "GB",
    "wof:name": "LN10 6PT",
    "wof:placetype": "postalcode"
  },
  "geometry": {"coordinates":[-0.203604,53.153903],"type":"Point"}
}
