{
  "type": "Feature",
  "properties": {
    "iso:country":"GB",
    "wof:name":"LN10 6PT",
    "wof:placetype":"postalcode"
},
  "geometry": {"coordinates":[-0.20360431123163,53.15390303717722],"type":"Point"}
}