{
  "type": "Feature",
  "properties": {
    "date:inception_lower": "1980-01-01",
    "date:inception_upper": "1980-01-01",
    "iso:country": "GB",
    "wof:name": "SK17 0AN",
    "wof:placetype": "postalcode"
  },
  "geometry": {"coordinates":[-1.810961,53.139647],"type":"Point"}
}
