{
  "type": "Feature",
  "properties": {
    "iso:country":"GB",
    "wof:name":"BD13 2NX",
    "wof:placetype":"postalcode"
},
  "geometry": {"coordinates":[-1.8574624908999,53.75889334834905],"type":"Point"}
}