{
  "type": "Feature",
  "properties": {
    "iso:country":"GB",
    "wof:name":"DE13 9AE",
    "wof:placetype":"postalcode"
},
  "geometry": {"coordinates":[-1.63830974568741,52.84653261714804],"type":"Point"}
}