{
  "type": "Feature",
  "properties": {
    "date:inception_lower":"2003-11-01",
    "date:inception_upper":"2003-11-30",
    "iso:country":"GB",
    "wof:name":"DE13 9AE",
    "wof:placetype":"postalcode"
},
  "geometry": {"coordinates":[-1.63831,52.846533],"type":"Point"}
}