{
  "type": "Feature",
  "properties": {
    "date:inception_lower": "1980-01-01",
    "date:inception_upper": "1980-01-01",
    "iso:country": "GB",
    "wof:name": "RM4 1PA",
    "wof:placetype": "postalcode"
  },
  "geometry": {"coordinates":[0.183305,51.617806],"type":"Point"}
}
