{
  "type": "Feature",
  "properties": {
    "iso:country":"GB",
    "wof:name":"EH26 9DT",
    "wof:placetype":"postalcode"
},
  "geometry": {"coordinates":[-3.224329793949,55.82407392544668],"type":"Point"}
}