{
  "type": "Feature",
  "properties": {
    "iso:country":"GB",
    "wof:name":"SN14 0YF",
    "wof:placetype":"postalcode"
},
  "geometry": {"coordinates":[-2.14731107022442,51.45061758146199],"type":"Point"}
}