{
  "type": "Feature",
  "properties": {
    "iso:country": "GB",
    "wof:name": "SN14 0YF",
    "wof:placetype": "postalcode"
  },
  "geometry": {"coordinates":[-2.147311,51.450618],"type":"Point"}
}
