{
  "type": "Feature",
  "properties": {
    "iso:country":"GB",
    "wof:name":"MK44 2PA",
    "wof:placetype":"postalcode"
},
  "geometry": {"coordinates":[-0.39725208739128,52.18336272268991],"type":"Point"}
}