{
  "type": "Feature",
  "properties": {
    "date:inception_lower": "1998-06-01",
    "date:inception_upper": "1998-06-01",
    "iso:country": "GB",
    "wof:name": "M16 7PS",
    "wof:placetype": "postalcode"
  },
  "geometry": {"coordinates":[-2.25952,53.4622],"type":"Point"}
}
