{
  "type": "Feature",
  "properties": {
    "iso:country":"GB",
    "wof:name":"M16 7PS",
    "wof:placetype":"postalcode"
},
  "geometry": {"coordinates":[-2.25952020625862,53.4622003810351],"type":"Point"}
}