{
  "type": "Feature",
  "properties": {
    "date:inception_lower": "1980-01-01",
    "date:inception_upper": "1980-01-01",
    "iso:country": "GB",
    "wof:name": "EH49 7AD",
    "wof:placetype": "postalcode"
  },
  "geometry": {"coordinates":[-3.597328,55.976486],"type":"Point"}
}
