{
  "type": "Feature",
  "properties": {
    "iso:country":"GB",
    "wof:name":"BB18 5AT",
    "wof:placetype":"postalcode"
},
  "geometry": {"coordinates":[-2.18587457797746,53.91343434053548],"type":"Point"}
}