{
  "type": "Feature",
  "properties": {
    "date:inception_lower": "2024-10-01",
    "date:inception_upper": "2024-10-01",
    "iso:country": "GB",
    "wof:name": "B77 1DZ",
    "wof:placetype": "postalcode"
  },
  "geometry": {"coordinates":[-1.68367,52.608077],"type":"Point"}
}
