{
  "type": "Feature",
  "properties": {
    "iso:country":"GB",
    "wof:name":"ST3 4UB",
    "wof:placetype":"postalcode"
},
  "geometry": {"coordinates":[-2.13095392025316,52.97240205269109],"type":"Point"}
}