{
  "type": "Feature",
  "properties": {
    "date:inception_lower": "2000-12-01",
    "date:inception_upper": "2000-12-01",
    "iso:country": "GB",
    "wof:name": "ST3 4UB",
    "wof:placetype": "postalcode"
  },
  "geometry": {"coordinates":[-2.130954,52.972402],"type":"Point"}
}
