{
  "type": "Feature",
  "properties": {
    "iso:country":"GB",
    "wof:name":"ML6 0NH",
    "wof:placetype":"postalcode"
},
  "geometry": {"coordinates":[-3.99590115464332,55.88415852019814],"type":"Point"}
}