{
  "type": "Feature",
  "properties": {
    "iso:country":"GB",
    "wof:name":"NW5 1NB",
    "wof:placetype":"postalcode"
},
  "geometry": {"coordinates":[-0.15022262824301,51.55709662239929],"type":"Point"}
}