{
  "type": "Feature",
  "properties": {
    "date:inception_lower": "1980-01-01",
    "date:inception_upper": "1980-01-01",
    "iso:country": "GB",
    "wof:name": "SY12 0NT",
    "wof:placetype": "postalcode"
  },
  "geometry": {"coordinates":[-2.844207,52.909872],"type":"Point"}
}
