{
  "type": "Feature",
  "properties": {
    "iso:country": "GB",
    "wof:name": "CO11 2RL",
    "wof:placetype": "postalcode"
  },
  "geometry": {"coordinates":[1.118793,51.906182],"type":"Point"}
}
