{
  "type": "Feature",
  "properties": {
    "date:inception_lower":"2005-05-01",
    "date:inception_upper":"2005-05-31",
    "iso:country":"GB",
    "wof:name":"NP20 3PJ",
    "wof:placetype":"postalcode"
},
  "geometry": {"coordinates":[-3.03366,51.576856],"type":"Point"}
}