{
  "type": "Feature",
  "properties": {
    "iso:country":"GB",
    "wof:name":"NP20 3PJ",
    "wof:placetype":"postalcode"
},
  "geometry": {"coordinates":[-3.03366014866617,51.57685604010153],"type":"Point"}
}