{
  "type": "Feature",
  "properties": {
    "date:inception_lower": "1980-01-01",
    "date:inception_upper": "1980-01-01",
    "iso:country": "GB",
    "wof:name": "S81 8LG",
    "wof:placetype": "postalcode"
  },
  "geometry": {"coordinates":[-1.17531,53.386678],"type":"Point"}
}
