{
  "type": "Feature",
  "properties": {
    "iso:country":"GB",
    "wof:name":"S81 8LG",
    "wof:placetype":"postalcode"
},
  "geometry": {"coordinates":[-1.17481889007326,53.38641256924254],"type":"Point"}
}