{
  "type": "Feature",
  "properties": {
    "iso:country":"GB",
    "wof:name":"DH9 0DE",
    "wof:placetype":"postalcode"
},
  "geometry": {"coordinates":[-1.69224926033444,54.87107539946496],"type":"Point"}
}