{
  "type": "Feature",
  "properties": {
    "iso:country": "GB",
    "wof:name": "DH9 0DE",
    "wof:placetype": "postalcode"
  },
  "geometry": {"coordinates":[-1.692249,54.871075],"type":"Point"}
}
