{
  "type": "Feature",
  "properties": {
    "date:inception_lower": "2015-03-01",
    "date:inception_upper": "2015-03-01",
    "iso:country": "GB",
    "wof:name": "RM10 7FL",
    "wof:placetype": "postalcode"
  },
  "geometry": {"coordinates":[0.151605,51.558426],"type":"Point"}
}
