{
  "type": "Feature",
  "properties": {
    "iso:country":"GB",
    "wof:name":"WR9 7LW",
    "wof:placetype":"postalcode"
},
  "geometry": {"coordinates":[-2.10412102838652,52.22099959730388],"type":"Point"}
}