{
  "type": "Feature",
  "properties": {
    "date:inception_lower": "2009-03-01",
    "date:inception_upper": "2009-03-01",
    "iso:country": "GB",
    "wof:name": "SE16 7BH",
    "wof:placetype": "postalcode"
  },
  "geometry": {"coordinates":[-0.05237,51.497673],"type":"Point"}
}
