{
  "type": "Feature",
  "properties": {
    "iso:country":"GB",
    "wof:name":"SE16 7BH",
    "wof:placetype":"postalcode"
},
  "geometry": {"coordinates":[-0.05236984498541,51.49767273136697],"type":"Point"}
}