{
  "type": "Feature",
  "properties": {
    "iso:country": "GB",
    "wof:name": "TF10 9DZ",
    "wof:placetype": "postalcode"
  },
  "geometry": {"coordinates":[-2.318909,52.758044],"type":"Point"}
}
