{
  "type": "Feature",
  "properties": {
    "date:inception_lower": "1980-01-01",
    "date:inception_upper": "1980-01-01",
    "iso:country": "GB",
    "wof:name": "TF10 9DZ",
    "wof:placetype": "postalcode"
  },
  "geometry": {"coordinates":[-2.318909,52.758044],"type":"Point"}
}
