{
  "type": "Feature",
  "properties": {
    "iso:country":"GB",
    "wof:name":"EC1V 7NB",
    "wof:placetype":"postalcode"
},
  "geometry": {"coordinates":[-0.10333805810354,51.52901086170842],"type":"Point"}
}