{
  "type": "Feature",
  "properties": {
    "iso:country":"GB",
    "wof:name":"GU30 7NL",
    "wof:placetype":"postalcode"
},
  "geometry": {"coordinates":[-0.80695868738561,51.03437000181075],"type":"Point"}
}