{
  "type": "Feature",
  "properties": {
    "date:inception_lower": "1983-07-01",
    "date:inception_upper": "1983-07-01",
    "iso:country": "GB",
    "wof:name": "GU30 7NL",
    "wof:placetype": "postalcode"
  },
  "geometry": {"coordinates":[-0.806959,51.03437],"type":"Point"}
}
