{
  "type": "Feature",
  "properties": {
    "date:inception_lower": "1980-01-01",
    "date:inception_upper": "1980-01-01",
    "iso:country": "GB",
    "wof:name": "BH13 6ER",
    "wof:placetype": "postalcode"
  },
  "geometry": {"coordinates":[-1.910877,50.718557],"type":"Point"}
}
