{
  "type": "Feature",
  "properties": {
    "iso:country":"GB",
    "wof:name":"BH13 6ER",
    "wof:placetype":"postalcode"
},
  "geometry": {"coordinates":[-1.9108767424053,50.71855729949282],"type":"Point"}
}