{
  "type": "Feature",
  "properties": {
    "iso:country":"GB",
    "wof:name":"G34 0DQ",
    "wof:placetype":"postalcode"
},
  "geometry": {"coordinates":[-4.09573121901716,55.87006974973627],"type":"Point"}
}