{
  "type": "Feature",
  "properties": {
    "iso:country":"GB",
    "wof:name":"SG18 8ET",
    "wof:placetype":"postalcode"
},
  "geometry": {"coordinates":[-0.25367184660209,52.08539429954881],"type":"Point"}
}