{
  "type": "Feature",
  "properties": {
    "iso:country":"GB",
    "wof:name":"LS14 5PU",
    "wof:placetype":"postalcode"
},
  "geometry": {"coordinates":[-1.43823194113944,53.81750552845671],"type":"Point"}
}