{
  "type": "Feature",
  "properties": {
    "iso:country": "GB",
    "wof:name": "DE5 3JW",
    "wof:placetype": "postalcode"
  },
  "geometry": {"coordinates":[-1.388879,53.047287],"type":"Point"}
}
