{
  "type": "Feature",
  "properties": {
    "iso:country":"GB",
    "wof:name":"HU17 0EB",
    "wof:placetype":"postalcode"
},
  "geometry": {"coordinates":[-0.42148590662664,53.84199159759493],"type":"Point"}
}