{
  "type": "Feature",
  "properties": {
    "iso:country":"GB",
    "wof:name":"E7 9JL",
    "wof:placetype":"postalcode"
},
  "geometry": {"coordinates":[0.0188096751198,51.54607259134434],"type":"Point"}
}