{
  "type": "Feature",
  "properties": {
    "iso:country":"GB",
    "wof:name":"NG2 2ED",
    "wof:placetype":"postalcode"
},
  "geometry": {"coordinates":[-1.14347416091214,52.93906015947521],"type":"Point"}
}