{
  "type": "Feature",
  "properties": {
    "iso:country":"GB",
    "wof:name":"WF10 2PH",
    "wof:placetype":"postalcode"
},
  "geometry": {"coordinates":[-1.31361068391049,53.73530767574584],"type":"Point"}
}