{
  "type": "Feature",
  "properties": {
    "iso:country": "GB",
    "wof:name": "WF10 2PH",
    "wof:placetype": "postalcode"
  },
  "geometry": {"coordinates":[-1.313611,53.735308],"type":"Point"}
}
