{
  "type": "Feature",
  "properties": {
    "iso:country":"GB",
    "wof:name":"BL0 9QJ",
    "wof:placetype":"postalcode"
},
  "geometry": {"coordinates":[-2.32410462725765,53.64174698236507],"type":"Point"}
}