{
  "type": "Feature",
  "properties": {
    "iso:country":"GB",
    "wof:name":"EC1V 0BD",
    "wof:placetype":"postalcode"
},
  "geometry": {"coordinates":[-0.100410855116,51.52521360823534],"type":"Point"}
}