{
  "type": "Feature",
  "properties": {
    "iso:country": "GB",
    "wof:name": "SE6 4RW",
    "wof:placetype": "postalcode"
  },
  "geometry": {"coordinates":[-0.027979,51.445242],"type":"Point"}
}
