{
  "type": "Feature",
  "properties": {
    "iso:country":"GB",
    "wof:name":"SE6 4RW",
    "wof:placetype":"postalcode"
},
  "geometry": {"coordinates":[-0.02771544922641,51.44500410737492],"type":"Point"}
}