{
  "type": "Feature",
  "properties": {
    "iso:country":"GB",
    "wof:name":"PE33 9JD",
    "wof:placetype":"postalcode"
},
  "geometry": {"coordinates":[0.52736030486997,52.66051825600547],"type":"Point"}
}