{
  "type": "Feature",
  "properties": {
    "iso:country": "GB",
    "wof:name": "LN7 6DW",
    "wof:placetype": "postalcode"
  },
  "geometry": {"coordinates":[-0.236136,53.520349],"type":"Point"}
}
