{
  "type": "Feature",
  "properties": {
    "iso:country":"GB",
    "wof:name":"LN7 6DW",
    "wof:placetype":"postalcode"
},
  "geometry": {"coordinates":[-0.23613621615328,53.5203489959511],"type":"Point"}
}