{
  "type": "Feature",
  "properties": {
    "iso:country":"GB",
    "wof:name":"RM2 5EE",
    "wof:placetype":"postalcode"
},
  "geometry": {"coordinates":[0.19723934246733,51.5865534383618],"type":"Point"}
}