{
  "type": "Feature",
  "properties": {
    "date:inception_lower": "1999-06-01",
    "date:inception_upper": "1999-06-01",
    "iso:country": "GB",
    "wof:name": "RM2 5EE",
    "wof:placetype": "postalcode"
  },
  "geometry": {"coordinates":[0.197239,51.586553],"type":"Point"}
}
