{
  "type": "Feature",
  "properties": {
    "iso:country": "GB",
    "wof:name": "WA13 0HZ",
    "wof:placetype": "postalcode"
  },
  "geometry": {"coordinates":[-2.473788,53.382209],"type":"Point"}
}
