{
  "type": "Feature",
  "properties": {
    "date:inception_lower": "1980-01-01",
    "date:inception_upper": "1980-01-01",
    "iso:country": "GB",
    "wof:name": "TS23 3RU",
    "wof:placetype": "postalcode"
  },
  "geometry": {"coordinates":[-1.279757,54.623678],"type":"Point"}
}
