{
  "type": "Feature",
  "properties": {
    "iso:country":"GB",
    "wof:name":"TS23 3RU",
    "wof:placetype":"postalcode"
},
  "geometry": {"coordinates":[-1.27975668987875,54.62367755615541],"type":"Point"}
}