{
  "type": "Feature",
  "properties": {
    "date:inception_lower":"1983-03-01",
    "date:inception_upper":"1983-03-31",
    "iso:country":"GB",
    "wof:name":"BD19 5NP",
    "wof:placetype":"postalcode"
},
  "geometry": {"coordinates":[-1.713464,53.718172],"type":"Point"}
}