{
  "type": "Feature",
  "properties": {
    "iso:country":"GB",
    "wof:name":"NG8 5HP",
    "wof:placetype":"postalcode"
},
  "geometry": {"coordinates":[-1.19434274889629,52.97541862801132],"type":"Point"}
}