{
  "type": "Feature",
  "properties": {
    "iso:country":"GB",
    "wof:name":"RG9 6LF",
    "wof:placetype":"postalcode"
},
  "geometry": {"coordinates":[-0.93934798449936,51.62566043777078],"type":"Point"}
}