{
  "type": "Feature",
  "properties": {
    "iso:country":"GB",
    "wof:name":"SP5 4BG",
    "wof:placetype":"postalcode"
},
  "geometry": {"coordinates":[-1.88990678479983,51.03530681250222],"type":"Point"}
}