{
  "type": "Feature",
  "properties": {
    "iso:country":"GB",
    "wof:name":"SW11 6PU",
    "wof:placetype":"postalcode"
},
  "geometry": {"coordinates":[-0.16406625833101,51.45649027384457],"type":"Point"}
}