{
  "type": "Feature",
  "properties": {
    "iso:country": "GB",
    "wof:name": "DN33 3TE",
    "wof:placetype": "postalcode"
  },
  "geometry": {"coordinates":[-0.105793,53.53922],"type":"Point"}
}
