{
  "type": "Feature",
  "properties": {
    "date:inception_lower": "2021-08-01",
    "date:inception_upper": "2021-08-01",
    "iso:country": "GB",
    "wof:name": "DN33 3TE",
    "wof:placetype": "postalcode"
  },
  "geometry": {"coordinates":[-0.106115,53.538881],"type":"Point"}
}
