{
  "type": "Feature",
  "properties": {
    "iso:country":"GB",
    "wof:name":"HU3 6EF",
    "wof:placetype":"postalcode"
},
  "geometry": {"coordinates":[-0.37514606582448,53.74056074136706],"type":"Point"}
}