{
  "type": "Feature",
  "properties": {
    "iso:country": "GB",
    "wof:name": "HU3 6EF",
    "wof:placetype": "postalcode"
  },
  "geometry": {"coordinates":[-0.375146,53.740561],"type":"Point"}
}
