{
  "type": "Feature",
  "properties": {
    "date:inception_lower": "1980-01-01",
    "date:inception_upper": "1980-01-01",
    "iso:country": "GB",
    "wof:name": "EX5 1BX",
    "wof:placetype": "postalcode"
  },
  "geometry": {"coordinates":[-3.455245,50.7117],"type":"Point"}
}
