{
  "type": "Feature",
  "properties": {
    "iso:country": "GB",
    "wof:name": "EX5 1BX",
    "wof:placetype": "postalcode"
  },
  "geometry": {"coordinates":[-3.455245,50.7117],"type":"Point"}
}
