{
  "type": "Feature",
  "properties": {
    "iso:country":"GB",
    "wof:name":"EX5 1BX",
    "wof:placetype":"postalcode"
},
  "geometry": {"coordinates":[-3.45524528427866,50.71169964074756],"type":"Point"}
}