{
  "type": "Feature",
  "properties": {
    "iso:country": "GB",
    "wof:name": "SS8 0QP",
    "wof:placetype": "postalcode"
  },
  "geometry": {"coordinates":[0.557488,51.524925],"type":"Point"}
}
