{
  "type": "Feature",
  "properties": {
    "iso:country":"GB",
    "wof:name":"SS8 0QP",
    "wof:placetype":"postalcode"
},
  "geometry": {"coordinates":[0.55748805643394,51.52492454096325],"type":"Point"}
}