{
  "type": "Feature",
  "properties": {
    "iso:country":"GB",
    "wof:name":"RM3 9HR",
    "wof:placetype":"postalcode"
},
  "geometry": {"coordinates":[0.23146436130336,51.59945982144539],"type":"Point"}
}