{
  "type": "Feature",
  "properties": {
    "iso:country": "GB",
    "wof:name": "TA2 8GA",
    "wof:placetype": "postalcode"
  },
  "geometry": {"coordinates":[-3.081795,51.033338],"type":"Point"}
}
