{
  "type": "Feature",
  "properties": {
    "iso:country":"GB",
    "wof:name":"LS26 0WN",
    "wof:placetype":"postalcode"
},
  "geometry": {"coordinates":[-1.49271837487283,53.75680004700147],"type":"Point"}
}