{
  "type": "Feature",
  "properties": {
    "date:inception_lower": "2002-06-01",
    "date:inception_upper": "2002-06-01",
    "iso:country": "GB",
    "wof:name": "LS26 0WN",
    "wof:placetype": "postalcode"
  },
  "geometry": {"coordinates":[-1.492718,53.7568],"type":"Point"}
}
