{
  "type": "Feature",
  "properties": {
    "iso:country":"GB",
    "wof:name":"WA5 1RA",
    "wof:placetype":"postalcode"
},
  "geometry": {"coordinates":[-2.65169250546499,53.39179693673616],"type":"Point"}
}