{
  "type": "Feature",
  "properties": {
    "iso:country": "GB",
    "wof:name": "WA5 1RA",
    "wof:placetype": "postalcode"
  },
  "geometry": {"coordinates":[-2.651692,53.391797],"type":"Point"}
}
