{
  "type": "Feature",
  "properties": {
    "date:inception_lower": "1980-01-01",
    "date:inception_upper": "1980-01-01",
    "iso:country": "GB",
    "wof:name": "EH17 8EL",
    "wof:placetype": "postalcode"
  },
  "geometry": {"coordinates":[-3.157792,55.900107],"type":"Point"}
}
