{
  "type": "Feature",
  "properties": {
    "iso:country": "GB",
    "wof:name": "EH32 0EH",
    "wof:placetype": "postalcode"
  },
  "geometry": {"coordinates":[-2.945162,55.970418],"type":"Point"}
}
