{
  "type": "Feature",
  "properties": {
    "iso:country":"GB",
    "wof:name":"PE9 1SU",
    "wof:placetype":"postalcode"
},
  "geometry": {"coordinates":[-0.47503803835215,52.66162851259987],"type":"Point"}
}