{
  "type": "Feature",
  "properties": {
    "date:inception_lower": "1980-01-01",
    "date:inception_upper": "1980-01-01",
    "iso:country": "GB",
    "wof:name": "PE9 1SU",
    "wof:placetype": "postalcode"
  },
  "geometry": {"coordinates":[-0.475038,52.661629],"type":"Point"}
}
