{
  "type": "Feature",
  "properties": {
    "iso:country":"GB",
    "wof:name":"LA13 9DG",
    "wof:placetype":"postalcode"
},
  "geometry": {"coordinates":[-3.20524470948288,54.11824774942041],"type":"Point"}
}