{
  "type": "Feature",
  "properties": {
    "date:inception_lower": "1993-08-01",
    "date:inception_upper": "1993-08-01",
    "iso:country": "GB",
    "wof:name": "OX33 1HU",
    "wof:placetype": "postalcode"
  },
  "geometry": {"coordinates":[-1.139461,51.749176],"type":"Point"}
}
