{
  "type": "Feature",
  "properties": {
    "iso:country":"GB",
    "wof:name":"BH6 3JZ",
    "wof:placetype":"postalcode"
},
  "geometry": {"coordinates":[-1.79405399057124,50.72869737079599],"type":"Point"}
}