{
  "type": "Feature",
  "properties": {
    "iso:country":"GB",
    "wof:name":"NG16 5HT",
    "wof:placetype":"postalcode"
},
  "geometry": {"coordinates":[-1.32882153264446,53.05411901997734],"type":"Point"}
}