{
  "type": "Feature",
  "properties": {
    "date:inception_lower": "1980-01-01",
    "date:inception_upper": "1980-01-01",
    "iso:country": "GB",
    "wof:name": "NG16 5HT",
    "wof:placetype": "postalcode"
  },
  "geometry": {"coordinates":[-1.328835,53.054102],"type":"Point"}
}
