{
  "type": "Feature",
  "properties": {
    "iso:country": "GB",
    "wof:name": "NG16 5HT",
    "wof:placetype": "postalcode"
  },
  "geometry": {"coordinates":[-1.328821,53.054119],"type":"Point"}
}
