{
  "type": "Feature",
  "properties": {
    "iso:country":"GB",
    "wof:name":"NE21 6LU",
    "wof:placetype":"postalcode"
},
  "geometry": {"coordinates":[-1.72163925140815,54.95002818236738],"type":"Point"}
}