{
  "type": "Feature",
  "properties": {
    "iso:country": "GB",
    "wof:name": "NE21 6LU",
    "wof:placetype": "postalcode"
  },
  "geometry": {"coordinates":[-1.721639,54.950028],"type":"Point"}
}
