{
  "type": "Feature",
  "properties": {
    "iso:country":"GB",
    "wof:name":"PH2 0NJ",
    "wof:placetype":"postalcode"
},
  "geometry": {"coordinates":[-3.43574548246739,56.38349474221613],"type":"Point"}
}