{
  "type": "Feature",
  "properties": {
    "iso:country": "GB",
    "wof:name": "ME19 4SP",
    "wof:placetype": "postalcode"
  },
  "geometry": {"coordinates":[0.404213,51.278636],"type":"Point"}
}
