{
  "type": "Feature",
  "properties": {
    "date:inception_lower": "2019-07-01",
    "date:inception_upper": "2019-07-01",
    "iso:country": "GB",
    "wof:name": "EX31 4FR",
    "wof:placetype": "postalcode"
  },
  "geometry": {"coordinates":[-4.144724,51.095222],"type":"Point"}
}
