{
  "type": "Feature",
  "properties": {
    "iso:country":"GB",
    "wof:name":"SW16 5TT",
    "wof:placetype":"postalcode"
},
  "geometry": {"coordinates":[-0.12481969974825,51.41066311166749],"type":"Point"}
}