{
  "type": "Feature",
  "properties": {
    "iso:country":"GB",
    "wof:name":"SL6 7QG",
    "wof:placetype":"postalcode"
},
  "geometry": {"coordinates":[-0.73417979895724,51.53933864696143],"type":"Point"}
}