{
  "type": "Feature",
  "properties": {
    "iso:country":"GB",
    "wof:name":"DN6 9LP",
    "wof:placetype":"postalcode"
},
  "geometry": {"coordinates":[-1.17199877552186,53.62057496520842],"type":"Point"}
}