{
  "type": "Feature",
  "properties": {
    "iso:country":"GB",
    "wof:name":"CA13 0PX",
    "wof:placetype":"postalcode"
},
  "geometry": {"coordinates":[-3.38615224109893,54.70423301537534],"type":"Point"}
}