{
  "type": "Feature",
  "properties": {
    "date:inception_lower": "2001-12-01",
    "date:inception_upper": "2001-12-01",
    "iso:country": "GB",
    "wof:name": "CA13 0PX",
    "wof:placetype": "postalcode"
  },
  "geometry": {"coordinates":[-3.386152,54.704233],"type":"Point"}
}
