{
  "type": "Feature",
  "properties": {
    "date:inception_lower": "2022-04-01",
    "date:inception_upper": "2022-04-01",
    "iso:country": "GB",
    "wof:name": "NG10 3TP",
    "wof:placetype": "postalcode"
  },
  "geometry": {"coordinates":[-1.264341,52.888829],"type":"Point"}
}
