{
  "type": "Feature",
  "properties": {
    "iso:country":"GB",
    "wof:name":"WS2 7ED",
    "wof:placetype":"postalcode"
},
  "geometry": {"coordinates":[-2.0148727228624,52.61150087568658],"type":"Point"}
}