{
  "type": "Feature",
  "properties": {
    "iso:country": "GB",
    "wof:name": "NE24 3JP",
    "wof:placetype": "postalcode"
  },
  "geometry": {"coordinates":[-1.50836,55.120586],"type":"Point"}
}
