{
  "type": "Feature",
  "properties": {
    "date:inception_lower": "1980-01-01",
    "date:inception_upper": "1980-01-01",
    "iso:country": "GB",
    "wof:name": "NE24 3JP",
    "wof:placetype": "postalcode"
  },
  "geometry": {"coordinates":[-1.50836,55.120586],"type":"Point"}
}
