{
  "type": "Feature",
  "properties": {
    "iso:country":"GB",
    "wof:name":"NE24 3JP",
    "wof:placetype":"postalcode"
},
  "geometry": {"coordinates":[-1.50836019188121,55.12058568631673],"type":"Point"}
}