{
  "type": "Feature",
  "properties": {
    "iso:country":"GB",
    "wof:name":"G21 2NW",
    "wof:placetype":"postalcode"
},
  "geometry": {"coordinates":[-4.23018521998019,55.86888328828132],"type":"Point"}
}