{
  "type": "Feature",
  "properties": {
    "iso:country": "GB",
    "wof:name": "DH3 1RL",
    "wof:placetype": "postalcode"
  },
  "geometry": {"coordinates":[-1.563181,54.899841],"type":"Point"}
}
