{
  "type": "Feature",
  "properties": {
    "iso:country":"GB",
    "wof:name":"DH3 1RL",
    "wof:placetype":"postalcode"
},
  "geometry": {"coordinates":[-1.56318091985109,54.89984103031162],"type":"Point"}
}