{
  "type": "Feature",
  "properties": {
    "iso:country": "GB",
    "wof:name": "WA4 3DX",
    "wof:placetype": "postalcode"
  },
  "geometry": {"coordinates":[-2.568146,53.366948],"type":"Point"}
}
