{
  "type": "Feature",
  "properties": {
    "iso:country":"GB",
    "wof:name":"WA4 3DX",
    "wof:placetype":"postalcode"
},
  "geometry": {"coordinates":[-2.56814615962728,53.3669476253104],"type":"Point"}
}