{
  "type": "Feature",
  "properties": {
    "date:inception_lower": "1989-04-01",
    "date:inception_upper": "1989-04-01",
    "iso:country": "GB",
    "wof:name": "DD8 1NX",
    "wof:placetype": "postalcode"
  },
  "geometry": {"coordinates":[-2.903886,56.636095],"type":"Point"}
}
