{
  "type": "Feature",
  "properties": {
    "iso:country": "GB",
    "wof:name": "DD8 1NX",
    "wof:placetype": "postalcode"
  },
  "geometry": {"coordinates":[-2.903886,56.636095],"type":"Point"}
}
