{
  "type": "Feature",
  "properties": {
    "iso:country":"GB",
    "wof:name":"RG30 1HP",
    "wof:placetype":"postalcode"
},
  "geometry": {"coordinates":[-1.00722807893648,51.45946680086567],"type":"Point"}
}