{
  "type": "Feature",
  "properties": {
    "date:inception_lower":"1980-01-01",
    "date:inception_upper":"1980-01-31",
    "iso:country":"GB",
    "wof:name":"N20 0BN",
    "wof:placetype":"postalcode"
},
  "geometry": {"coordinates":[-0.163588,51.626359],"type":"Point"}
}