{
  "type": "Feature",
  "properties": {
    "iso:country": "GB",
    "wof:name": "BH20 5SW",
    "wof:placetype": "postalcode"
  },
  "geometry": {"coordinates":[-2.244244,50.626276],"type":"Point"}
}
