{
  "type": "Feature",
  "properties": {
    "date:inception_lower":"1980-01-01",
    "date:inception_upper":"1980-01-31",
    "iso:country":"GB",
    "wof:name":"BH20 5SW",
    "wof:placetype":"postalcode"
},
  "geometry": {"coordinates":[-2.244244,50.626276],"type":"Point"}
}