{
  "type": "Feature",
  "properties": {
    "iso:country":"GB",
    "wof:name":"SN25 3PQ",
    "wof:placetype":"postalcode"
},
  "geometry": {"coordinates":[-1.79999929399342,51.58770484843214],"type":"Point"}
}