{
  "type": "Feature",
  "properties": {
    "date:inception_lower": "2019-11-01",
    "date:inception_upper": "2019-11-01",
    "iso:country": "GB",
    "wof:name": "EH54 7FP",
    "wof:placetype": "postalcode"
  },
  "geometry": {"coordinates":[-3.539583,55.886944],"type":"Point"}
}
