{
  "type": "Feature",
  "properties": {
    "date:inception_lower": "2019-11-01",
    "date:inception_upper": "2019-11-01",
    "iso:country": "GB",
    "wof:name": "EH54 7FP",
    "wof:placetype": "postalcode"
  },
  "geometry": {"coordinates":[-3.539448,55.88717],"type":"Point"}
}
