{
  "type": "Feature",
  "properties": {
    "iso:country":"GB",
    "wof:name":"S81 0EF",
    "wof:placetype":"postalcode"
},
  "geometry": {"coordinates":[-1.09972961172283,53.31163036674709],"type":"Point"}
}