{
  "type": "Feature",
  "properties": {
    "date:inception_lower": "2021-06-01",
    "date:inception_upper": "2021-06-01",
    "iso:country": "GB",
    "wof:name": "EX20 3FE",
    "wof:placetype": "postalcode"
  },
  "geometry": {"coordinates":[-4.075009,50.820654],"type":"Point"}
}
