{
  "type": "Feature",
  "properties": {
    "iso:country": "GB",
    "wof:name": "KW17 2DJ",
    "wof:placetype": "postalcode"
  },
  "geometry": {"coordinates":[-2.991363,59.321315],"type":"Point"}
}
