{
  "type": "Feature",
  "properties": {
    "iso:country":"GB",
    "wof:name":"KW17 2DJ",
    "wof:placetype":"postalcode"
},
  "geometry": {"coordinates":[-2.99136339120633,59.32131481608359],"type":"Point"}
}