{
  "type": "Feature",
  "properties": {
    "iso:country":"GB",
    "wof:name":"M16 7LY",
    "wof:placetype":"postalcode"
},
  "geometry": {"coordinates":[-2.2503296350795,53.45659321235529],"type":"Point"}
}