{
  "type": "Feature",
  "properties": {
    "date:inception_lower":"1992-01-01",
    "date:inception_upper":"1992-01-31",
    "iso:country":"GB",
    "wof:name":"PE2 5LY",
    "wof:placetype":"postalcode"
},
  "geometry": {"coordinates":[-0.2722,52.553059],"type":"Point"}
}