{
  "type": "Feature",
  "properties": {
    "iso:country": "GB",
    "wof:name": "PE2 5LY",
    "wof:placetype": "postalcode"
  },
  "geometry": {"coordinates":[-0.2722,52.553059],"type":"Point"}
}
