{
  "type": "Feature",
  "properties": {
    "date:inception_lower":"1986-04-01",
    "date:inception_upper":"1986-04-30",
    "iso:country":"GB",
    "wof:name":"TS18 4BP",
    "wof:placetype":"postalcode"
},
  "geometry": {"coordinates":[-1.326007,54.563443],"type":"Point"}
}