{
  "type": "Feature",
  "properties": {
    "iso:country":"GB",
    "wof:name":"TS18 4BP",
    "wof:placetype":"postalcode"
},
  "geometry": {"coordinates":[-1.32600751816971,54.56344346873173],"type":"Point"}
}