{
  "type": "Feature",
  "properties": {
    "iso:country": "GB",
    "wof:name": "TS18 4BP",
    "wof:placetype": "postalcode"
  },
  "geometry": {"coordinates":[-1.326007,54.563443],"type":"Point"}
}
