{
  "type": "Feature",
  "properties": {
    "iso:country": "GB",
    "wof:name": "SO50 6LP",
    "wof:placetype": "postalcode"
  },
  "geometry": {"coordinates":[-1.336795,50.970361],"type":"Point"}
}
