{
  "type": "Feature",
  "properties": {
    "iso:country":"GB",
    "wof:name":"SO50 6LP",
    "wof:placetype":"postalcode"
},
  "geometry": {"coordinates":[-1.33679552857018,50.97036078631728],"type":"Point"}
}