{
  "type": "Feature",
  "properties": {
    "iso:country":"GB",
    "wof:name":"PL13 2QH",
    "wof:placetype":"postalcode"
},
  "geometry": {"coordinates":[-4.54971073605744,50.35743386728845],"type":"Point"}
}