{
  "type": "Feature",
  "properties": {
    "iso:country":"GB",
    "wof:name":"EN4 8DU",
    "wof:placetype":"postalcode"
},
  "geometry": {"coordinates":[-0.16379087562616,51.63673030532104],"type":"Point"}
}