{
  "type": "Feature",
  "properties": {
    "iso:country":"GB",
    "wof:name":"UB7 9BW",
    "wof:placetype":"postalcode"
},
  "geometry": {"coordinates":[-0.45220497233973,51.50406262909605],"type":"Point"}
}