{
  "type": "Feature",
  "properties": {
    "iso:country":"GB",
    "wof:name":"CF14 7AY",
    "wof:placetype":"postalcode"
},
  "geometry": {"coordinates":[-3.22781418564007,51.5189476864799],"type":"Point"}
}