{
  "type": "Feature",
  "properties": {
    "iso:country":"GB",
    "wof:name":"WF6 1SG",
    "wof:placetype":"postalcode"
},
  "geometry": {"coordinates":[-1.40550205297031,53.69805698704771],"type":"Point"}
}