{
  "type": "Feature",
  "properties": {
    "iso:country": "GB",
    "wof:name": "SY12 0BX",
    "wof:placetype": "postalcode"
  },
  "geometry": {"coordinates":[-2.905243,52.905272],"type":"Point"}
}
