{
  "type": "Feature",
  "properties": {
    "iso:country":"GB",
    "wof:name":"DD3 9LL",
    "wof:placetype":"postalcode"
},
  "geometry": {"coordinates":[-3.02043112247959,56.49264759754016],"type":"Point"}
}