{
  "type": "Feature",
  "properties": {
    "iso:country": "GB",
    "wof:name": "DD3 9LL",
    "wof:placetype": "postalcode"
  },
  "geometry": {"coordinates":[-3.020431,56.492648],"type":"Point"}
}
