{
  "type": "Feature",
  "properties": {
    "iso:country":"GB",
    "wof:name":"B30 1LL",
    "wof:placetype":"postalcode"
},
  "geometry": {"coordinates":[-1.93763063284711,52.42660828045656],"type":"Point"}
}