{
  "type": "Feature",
  "properties": {
    "date:inception_lower": "1980-01-01",
    "date:inception_upper": "1980-01-01",
    "iso:country": "GB",
    "wof:name": "B30 1LL",
    "wof:placetype": "postalcode"
  },
  "geometry": {"coordinates":[-1.937631,52.426608],"type":"Point"}
}
