{
  "type": "Feature",
  "properties": {
    "iso:country":"GB",
    "wof:name":"G44 5SH",
    "wof:placetype":"postalcode"
},
  "geometry": {"coordinates":[-4.2463963773809,55.81772831947455],"type":"Point"}
}