{
  "type": "Feature",
  "properties": {
    "iso:country":"GB",
    "wof:name":"S60 1JE",
    "wof:placetype":"postalcode"
},
  "geometry": {"coordinates":[-1.36701060703465,53.43133380141352],"type":"Point"}
}