{
  "type": "Feature",
  "properties": {
    "iso:country": "GB",
    "wof:name": "SK16 4TA",
    "wof:placetype": "postalcode"
  },
  "geometry": {"coordinates":[-2.087094,53.477093],"type":"Point"}
}
