{
  "type": "Feature",
  "properties": {
    "date:inception_lower": "2001-12-01",
    "date:inception_upper": "2001-12-01",
    "iso:country": "GB",
    "wof:name": "TS22 5FB",
    "wof:placetype": "postalcode"
  },
  "geometry": {"coordinates":[-1.324204,54.636956],"type":"Point"}
}
