{
  "type": "Feature",
  "properties": {
    "iso:country":"GB",
    "wof:name":"TS22 5FB",
    "wof:placetype":"postalcode"
},
  "geometry": {"coordinates":[-1.3242040192428,54.63695569425591],"type":"Point"}
}