{
  "type": "Feature",
  "properties": {
    "date:inception_lower": "1990-02-01",
    "date:inception_upper": "1990-02-01",
    "iso:country": "GB",
    "wof:name": "EX12 2UN",
    "wof:placetype": "postalcode"
  },
  "geometry": {"coordinates":[-3.071943,50.718535],"type":"Point"}
}
