{
  "type": "Feature",
  "properties": {
    "iso:country": "GB",
    "wof:name": "N9 0QB",
    "wof:placetype": "postalcode"
  },
  "geometry": {"coordinates":[-0.061584,51.620304],"type":"Point"}
}
