{
  "type": "Feature",
  "properties": {
    "iso:country":"GB",
    "wof:name":"N9 0QB",
    "wof:placetype":"postalcode"
},
  "geometry": {"coordinates":[-0.06158405078296,51.62030374462839],"type":"Point"}
}