{
  "type": "Feature",
  "properties": {
    "iso:country": "GB",
    "wof:name": "HP15 7BQ",
    "wof:placetype": "postalcode"
  },
  "geometry": {"coordinates":[-0.714022,51.657231],"type":"Point"}
}
