{
  "type": "Feature",
  "properties": {
    "iso:country":"GB",
    "wof:name":"PA23 7AQ",
    "wof:placetype":"postalcode"
},
  "geometry": {"coordinates":[-4.92806060317706,55.94930967699683],"type":"Point"}
}