{
  "type": "Feature",
  "properties": {
    "iso:country":"GB",
    "wof:name":"BL0 0RD",
    "wof:placetype":"postalcode"
},
  "geometry": {"coordinates":[-2.29553863047386,53.66643966796907],"type":"Point"}
}