{
  "type": "Feature",
  "properties": {
    "iso:country":"GB",
    "wof:name":"WV11 2BZ",
    "wof:placetype":"postalcode"
},
  "geometry": {"coordinates":[-2.0573820037989,52.62768733884521],"type":"Point"}
}