{
  "type": "Feature",
  "properties": {
    "iso:country":"GB",
    "wof:name":"BN18 0JH",
    "wof:placetype":"postalcode"
},
  "geometry": {"coordinates":[-0.60796177556254,50.81642066902116],"type":"Point"}
}