{
  "type": "Feature",
  "properties": {
    "date:inception_lower": "1980-01-01",
    "date:inception_upper": "1980-01-01",
    "iso:country": "GB",
    "wof:name": "PO9 5SL",
    "wof:placetype": "postalcode"
  },
  "geometry": {"coordinates":[-0.973319,50.871034],"type":"Point"}
}
