{
  "type": "Feature",
  "properties": {
    "iso:country":"GB",
    "wof:name":"DY3 3BG",
    "wof:placetype":"postalcode"
},
  "geometry": {"coordinates":[-2.14176833406677,52.52247130000317],"type":"Point"}
}