{
  "type": "Feature",
  "properties": {
    "iso:country":"GB",
    "wof:name":"B73 6AZ",
    "wof:placetype":"postalcode"
},
  "geometry": {"coordinates":[-1.82316350404429,52.5646412511925],"type":"Point"}
}