{
  "type": "Feature",
  "properties": {
    "iso:country": "GB",
    "wof:name": "DA7 4HT",
    "wof:placetype": "postalcode"
  },
  "geometry": {"coordinates":[0.146489,51.457951],"type":"Point"}
}
