{
  "type": "Feature",
  "properties": {
    "date:inception_lower": "2021-04-01",
    "date:inception_upper": "2021-04-01",
    "iso:country": "GB",
    "wof:name": "BA11 1GP",
    "wof:placetype": "postalcode"
  },
  "geometry": {"coordinates":[-2.312027,51.22519],"type":"Point"}
}
