{
  "type": "Feature",
  "properties": {
    "iso:country": "GB",
    "wof:name": "PA16 8EP",
    "wof:placetype": "postalcode"
  },
  "geometry": {"coordinates":[-4.775211,55.955303],"type":"Point"}
}
