{
  "type": "Feature",
  "properties": {
    "iso:country": "GB",
    "wof:name": "GL16 8DN",
    "wof:placetype": "postalcode"
  },
  "geometry": {"coordinates":[-2.619037,51.794161],"type":"Point"}
}
