{
  "type": "Feature",
  "properties": {
    "iso:country":"GB",
    "wof:name":"GL16 8DN",
    "wof:placetype":"postalcode"
},
  "geometry": {"coordinates":[-2.61909196958661,51.79412843754609],"type":"Point"}
}