{
  "type": "Feature",
  "properties": {
    "date:inception_lower":"1980-01-01",
    "date:inception_upper":"1980-01-31",
    "iso:country":"GB",
    "wof:name":"L23 9XY",
    "wof:placetype":"postalcode"
},
  "geometry": {"coordinates":[-3.006922,53.498202],"type":"Point"}
}