{
  "type": "Feature",
  "properties": {
    "iso:country":"GB",
    "wof:name":"RG14 1QL",
    "wof:placetype":"postalcode"
},
  "geometry": {"coordinates":[-1.33337864965674,51.40685261830237],"type":"Point"}
}