{
  "type": "Feature",
  "properties": {
    "iso:country":"GB",
    "wof:name":"NR6 6EZ",
    "wof:placetype":"postalcode"
},
  "geometry": {"coordinates":[1.28539213129404,52.66720348998028],"type":"Point"}
}