{
  "type": "Feature",
  "properties": {
    "iso:country": "GB",
    "wof:name": "NR6 6EZ",
    "wof:placetype": "postalcode"
  },
  "geometry": {"coordinates":[1.285392,52.667203],"type":"Point"}
}
