{
  "type": "Feature",
  "properties": {
    "iso:country": "GB",
    "wof:name": "EX4 5BZ",
    "wof:placetype": "postalcode"
  },
  "geometry": {"coordinates":[-3.513581,50.740077],"type":"Point"}
}
