{
  "type": "Feature",
  "properties": {
    "iso:country":"GB",
    "wof:name":"EX4 5BZ",
    "wof:placetype":"postalcode"
},
  "geometry": {"coordinates":[-3.51358095804959,50.74007688679067],"type":"Point"}
}