{
  "type": "Feature",
  "properties": {
    "date:inception_lower": "1980-01-01",
    "date:inception_upper": "1980-01-01",
    "iso:country": "GB",
    "wof:name": "LE4 3JE",
    "wof:placetype": "postalcode"
  },
  "geometry": {"coordinates":[-1.136515,52.681175],"type":"Point"}
}
