{
  "type": "Feature",
  "properties": {
    "date:inception_lower": "2014-10-01",
    "date:inception_upper": "2014-10-01",
    "iso:country": "GB",
    "wof:name": "ML9 1HZ",
    "wof:placetype": "postalcode"
  },
  "geometry": {"coordinates":[-3.972067,55.736627],"type":"Point"}
}
