{
  "type": "Feature",
  "properties": {
    "date:inception_lower": "2018-12-01",
    "date:inception_upper": "2018-12-01",
    "iso:country": "GB",
    "wof:name": "NG22 8FG",
    "wof:placetype": "postalcode"
  },
  "geometry": {"coordinates":[-1.025585,53.10089],"type":"Point"}
}
