{
  "type": "Feature",
  "properties": {
    "iso:country": "GB",
    "wof:name": "NG22 8FG",
    "wof:placetype": "postalcode"
  },
  "geometry": {"coordinates":[-1.025585,53.10089],"type":"Point"}
}
