{
  "type": "Feature",
  "properties": {
    "date:inception_lower": "2021-04-01",
    "date:inception_upper": "2021-04-01",
    "iso:country": "GB",
    "wof:name": "AL2 3FY",
    "wof:placetype": "postalcode"
  },
  "geometry": {"coordinates":[-0.350395,51.70423],"type":"Point"}
}
