{
  "type": "Feature",
  "properties": {
    "iso:country":"GB",
    "wof:name":"LE3 8GH",
    "wof:placetype":"postalcode"
},
  "geometry": {"coordinates":[-1.20592635015765,52.65795423950256],"type":"Point"}
}