{
  "type": "Feature",
  "properties": {
    "date:inception_lower": "1980-01-01",
    "date:inception_upper": "1980-01-01",
    "iso:country": "GB",
    "wof:name": "S8 9HW",
    "wof:placetype": "postalcode"
  },
  "geometry": {"coordinates":[-1.46181,53.355485],"type":"Point"}
}
