{
  "type": "Feature",
  "properties": {
    "iso:country":"GB",
    "wof:name":"WD6 1UQ",
    "wof:placetype":"postalcode"
},
  "geometry": {"coordinates":[-0.27851073890794,51.65904241902437],"type":"Point"}
}