{
  "type": "Feature",
  "properties": {
    "iso:country":"GB",
    "wof:name":"EX39 1TR",
    "wof:placetype":"postalcode"
},
  "geometry": {"coordinates":[-4.22642107149076,51.04197474989977],"type":"Point"}
}