{
  "type": "Feature",
  "properties": {
    "date:inception_lower": "1990-07-01",
    "date:inception_upper": "1990-07-01",
    "iso:country": "GB",
    "wof:name": "EX39 1TR",
    "wof:placetype": "postalcode"
  },
  "geometry": {"coordinates":[-4.226461,51.041988],"type":"Point"}
}
