{
  "type": "Feature",
  "properties": {
    "iso:country": "GB",
    "wof:name": "DY9 9ET",
    "wof:placetype": "postalcode"
  },
  "geometry": {"coordinates":[-2.115149,52.445111],"type":"Point"}
}
