{
  "type": "Feature",
  "properties": {
    "iso:country":"GB",
    "wof:name":"DY9 9ET",
    "wof:placetype":"postalcode"
},
  "geometry": {"coordinates":[-2.11525762284791,52.44510560555765],"type":"Point"}
}