{
  "type": "Feature",
  "properties": {
    "date:inception_lower": "1980-01-01",
    "date:inception_upper": "1980-01-01",
    "iso:country": "GB",
    "wof:name": "WS5 3QN",
    "wof:placetype": "postalcode"
  },
  "geometry": {"coordinates":[-1.949444,52.5776],"type":"Point"}
}
