{
  "type": "Feature",
  "properties": {
    "iso:country":"GB",
    "wof:name":"RG41 3AX",
    "wof:placetype":"postalcode"
},
  "geometry": {"coordinates":[-0.86577169866829,51.41269373730788],"type":"Point"}
}