{
  "type": "Feature",
  "properties": {
    "iso:country": "GB",
    "wof:name": "SA1 6DR",
    "wof:placetype": "postalcode"
  },
  "geometry": {"coordinates":[-3.959623,51.619435],"type":"Point"}
}
