{
  "type": "Feature",
  "properties": {
    "iso:country":"GB",
    "wof:name":"TN23 1QT",
    "wof:placetype":"postalcode"
},
  "geometry": {"coordinates":[0.87130901278746,51.14788079057409],"type":"Point"}
}