{
  "type": "Feature",
  "properties": {
    "iso:country":"GB",
    "wof:name":"DE73 6UF",
    "wof:placetype":"postalcode"
},
  "geometry": {"coordinates":[-1.43792267621607,52.86834415217432],"type":"Point"}
}