{
  "type": "Feature",
  "properties": {
    "iso:country": "GB",
    "wof:name": "TS9 6QS",
    "wof:placetype": "postalcode"
  },
  "geometry": {"coordinates":[-1.120251,54.508356],"type":"Point"}
}
