{
  "type": "Feature",
  "properties": {
    "iso:country":"GB",
    "wof:name":"M9 8BR",
    "wof:placetype":"postalcode"
},
  "geometry": {"coordinates":[-2.2136106622909,53.51886459890104],"type":"Point"}
}