{
  "type": "Feature",
  "properties": {
    "iso:country": "GB",
    "wof:name": "M9 8BR",
    "wof:placetype": "postalcode"
  },
  "geometry": {"coordinates":[-2.213611,53.518865],"type":"Point"}
}
