{
  "type": "Feature",
  "properties": {
    "iso:country":"GB",
    "wof:name":"AB42 1UX",
    "wof:placetype":"postalcode"
},
  "geometry": {"coordinates":[-1.78089444826876,57.50745217174405],"type":"Point"}
}