{
  "type": "Feature",
  "properties": {
    "iso:country":"GB",
    "wof:name":"SA37 0JL",
    "wof:placetype":"postalcode"
},
  "geometry": {"coordinates":[-4.61469567847346,52.01491555823994],"type":"Point"}
}