{
  "type": "Feature",
  "properties": {
    "iso:country":"GB",
    "wof:name":"CM8 1RP",
    "wof:placetype":"postalcode"
},
  "geometry": {"coordinates":[0.59579767644174,51.83877667624942],"type":"Point"}
}