{
  "type": "Feature",
  "properties": {
    "date:inception_lower":"1987-04-01",
    "date:inception_upper":"1987-04-30",
    "iso:country":"GB",
    "wof:name":"PA11 3SQ",
    "wof:placetype":"postalcode"
},
  "geometry": {"coordinates":[-4.621121,55.869327],"type":"Point"}
}