{
  "type": "Feature",
  "properties": {
    "iso:country": "GB",
    "wof:name": "SK7 4FQ",
    "wof:placetype": "postalcode"
  },
  "geometry": {"coordinates":[-2.16156,53.407578],"type":"Point"}
}
