{
  "type": "Feature",
  "properties": {
    "iso:country": "GB",
    "wof:name": "BA20 1TG",
    "wof:placetype": "postalcode"
  },
  "geometry": {"coordinates":[-2.635606,50.940406],"type":"Point"}
}
