{
  "type": "Feature",
  "properties": {
    "iso:country":"GB",
    "wof:name":"BA20 1TG",
    "wof:placetype":"postalcode"
},
  "geometry": {"coordinates":[-2.63579986475892,50.94005288269923],"type":"Point"}
}