{
  "type": "Feature",
  "properties": {
    "iso:country":"GB",
    "wof:name":"KT11 2RZ",
    "wof:placetype":"postalcode"
},
  "geometry": {"coordinates":[-0.4029228189335,51.32633324812559],"type":"Point"}
}