{
  "type": "Feature",
  "properties": {
    "date:inception_lower":"1994-05-01",
    "date:inception_upper":"1994-05-31",
    "iso:country":"GB",
    "wof:name":"KT11 2RZ",
    "wof:placetype":"postalcode"
},
  "geometry": {"coordinates":[-0.402923,51.326333],"type":"Point"}
}