{
  "type": "Feature",
  "properties": {
    "iso:country":"GB",
    "wof:name":"CM1 2NL",
    "wof:placetype":"postalcode"
},
  "geometry": {"coordinates":[0.44739726435394,51.73934105659055],"type":"Point"}
}