{
  "type": "Feature",
  "properties": {
    "iso:country":"GB",
    "wof:name":"NG9 1HQ",
    "wof:placetype":"postalcode"
},
  "geometry": {"coordinates":[-1.214855613897,52.92492712943963],"type":"Point"}
}