{
  "type": "Feature",
  "properties": {
    "date:inception_lower":"1980-01-01",
    "date:inception_upper":"1980-01-31",
    "iso:country":"GB",
    "wof:name":"HR7 4QB",
    "wof:placetype":"postalcode"
},
  "geometry": {"coordinates":[-2.471927,52.226844],"type":"Point"}
}