{
  "type": "Feature",
  "properties": {
    "iso:country":"GB",
    "wof:name":"HR7 4QB",
    "wof:placetype":"postalcode"
},
  "geometry": {"coordinates":[-2.47192749943261,52.22684405686353],"type":"Point"}
}