{
  "type": "Feature",
  "properties": {
    "iso:country":"GB",
    "wof:name":"WC1B 3ND",
    "wof:placetype":"postalcode"
},
  "geometry": {"coordinates":[-0.13042658191395,51.51707204157543],"type":"Point"}
}