{
  "type": "Feature",
  "properties": {
    "date:inception_lower": "1997-12-01",
    "date:inception_upper": "1997-12-01",
    "iso:country": "GB",
    "wof:name": "BS35 1LB",
    "wof:placetype": "postalcode"
  },
  "geometry": {"coordinates":[-2.518015,51.624532],"type":"Point"}
}
