{
  "type": "Feature",
  "properties": {
    "iso:country":"GB",
    "wof:name":"BS35 1LB",
    "wof:placetype":"postalcode"
},
  "geometry": {"coordinates":[-2.51819947358445,51.62426881640135],"type":"Point"}
}