{
  "type": "Feature",
  "properties": {
    "iso:country":"GB",
    "wof:name":"WS11 1EF",
    "wof:placetype":"postalcode"
},
  "geometry": {"coordinates":[-2.02411760885317,52.69124692776742],"type":"Point"}
}