{
  "type": "Feature",
  "properties": {
    "iso:country": "GB",
    "wof:name": "WS11 1EF",
    "wof:placetype": "postalcode"
  },
  "geometry": {"coordinates":[-2.024118,52.691247],"type":"Point"}
}
