{
  "type": "Feature",
  "properties": {
    "iso:country":"GB",
    "wof:name":"BB9 8BA",
    "wof:placetype":"postalcode"
},
  "geometry": {"coordinates":[-2.19681493318734,53.84110961838877],"type":"Point"}
}