{
  "type": "Feature",
  "properties": {
    "iso:country": "GB",
    "wof:name": "CF47 8SH",
    "wof:placetype": "postalcode"
  },
  "geometry": {"coordinates":[-3.37992,51.752852],"type":"Point"}
}
