{
  "type": "Feature",
  "properties": {
    "iso:country":"GB",
    "wof:name":"TQ12 1DH",
    "wof:placetype":"postalcode"
},
  "geometry": {"coordinates":[-3.59692303371827,50.51996443700344],"type":"Point"}
}