{
  "type": "Feature",
  "properties": {
    "iso:country": "GB",
    "wof:name": "TQ12 1DH",
    "wof:placetype": "postalcode"
  },
  "geometry": {"coordinates":[-3.596923,50.519964],"type":"Point"}
}
