{
  "type": "Feature",
  "properties": {
    "iso:country":"GB",
    "wof:name":"SY12 0DU",
    "wof:placetype":"postalcode"
},
  "geometry": {"coordinates":[-2.89984452545298,52.90376665631565],"type":"Point"}
}