{
  "type": "Feature",
  "properties": {
    "date:inception_lower":"1980-01-01",
    "date:inception_upper":"1980-01-31",
    "iso:country":"GB",
    "wof:name":"SY12 0DU",
    "wof:placetype":"postalcode"
},
  "geometry": {"coordinates":[-2.899844,52.903767],"type":"Point"}
}