{
  "type": "Feature",
  "properties": {
    "iso:country":"GB",
    "wof:name":"CB21 4RT",
    "wof:placetype":"postalcode"
},
  "geometry": {"coordinates":[0.36931569278454,52.11610571164928],"type":"Point"}
}