{
  "type": "Feature",
  "properties": {
    "iso:country": "GB",
    "wof:name": "LN2 5RY",
    "wof:placetype": "postalcode"
  },
  "geometry": {"coordinates":[-0.52789,53.234068],"type":"Point"}
}
