{
  "type": "Feature",
  "properties": {
    "iso:country":"GB",
    "wof:name":"LN2 5RY",
    "wof:placetype":"postalcode"
},
  "geometry": {"coordinates":[-0.52747539210892,53.233888257221],"type":"Point"}
}