{
  "type": "Feature",
  "properties": {
    "iso:country":"GB",
    "wof:name":"WA11 9SD",
    "wof:placetype":"postalcode"
},
  "geometry": {"coordinates":[-2.67615942278665,53.47814996260427],"type":"Point"}
}