{
  "type": "Feature",
  "properties": {
    "date:inception_lower":"1980-01-01",
    "date:inception_upper":"1980-01-31",
    "iso:country":"GB",
    "wof:name":"WA11 9SD",
    "wof:placetype":"postalcode"
},
  "geometry": {"coordinates":[-2.676159,53.47815],"type":"Point"}
}