{
  "type": "Feature",
  "properties": {
    "iso:country": "GB",
    "wof:name": "CW4 7EY",
    "wof:placetype": "postalcode"
  },
  "geometry": {"coordinates":[-2.356637,53.199398],"type":"Point"}
}
