{
  "type": "Feature",
  "properties": {
    "iso:country":"GB",
    "wof:name":"CW4 7EY",
    "wof:placetype":"postalcode"
},
  "geometry": {"coordinates":[-2.35663743625745,53.19939849250083],"type":"Point"}
}