{
  "type": "Feature",
  "properties": {
    "iso:country": "GB",
    "wof:name": "BN20 8JS",
    "wof:placetype": "postalcode"
  },
  "geometry": {"coordinates":[0.259615,50.772262],"type":"Point"}
}
