{
  "type": "Feature",
  "properties": {
    "date:inception_lower": "1983-07-01",
    "date:inception_upper": "1983-07-01",
    "iso:country": "GB",
    "wof:name": "SG12 0DQ",
    "wof:placetype": "postalcode"
  },
  "geometry": {"coordinates":[-0.040566,51.818856],"type":"Point"}
}
