{
  "type": "Feature",
  "properties": {
    "iso:country": "GB",
    "wof:name": "BS10 6TJ",
    "wof:placetype": "postalcode"
  },
  "geometry": {"coordinates":[-2.60881,51.507115],"type":"Point"}
}
