{
  "type": "Feature",
  "properties": {
    "iso:country":"GB",
    "wof:name":"BS10 6TJ",
    "wof:placetype":"postalcode"
},
  "geometry": {"coordinates":[-2.60880972911517,51.50711538410614],"type":"Point"}
}