{
  "type": "Feature",
  "properties": {
    "iso:country":"GB",
    "wof:name":"NE66 4BG",
    "wof:placetype":"postalcode"
},
  "geometry": {"coordinates":[-1.93309608566928,55.41331674646562],"type":"Point"}
}