{
  "type": "Feature",
  "properties": {
    "iso:country": "GB",
    "wof:name": "SL9 0FF",
    "wof:placetype": "postalcode"
  },
  "geometry": {"coordinates":[-0.54697,51.621113],"type":"Point"}
}
