{
  "type": "Feature",
  "properties": {
    "iso:country":"GB",
    "wof:name":"PE8 5LA",
    "wof:placetype":"postalcode"
},
  "geometry": {"coordinates":[-0.46020628154308,52.48895096846695],"type":"Point"}
}