{
  "type": "Feature",
  "properties": {
    "iso:country":"GB",
    "wof:name":"SL6 4GZ",
    "wof:placetype":"postalcode"
},
  "geometry": {"coordinates":[-0.7619420586058,51.52267613997372],"type":"Point"}
}