{
  "type": "Feature",
  "properties": {
    "iso:country": "GB",
    "wof:name": "SL6 4GZ",
    "wof:placetype": "postalcode"
  },
  "geometry": {"coordinates":[-0.761942,51.522676],"type":"Point"}
}
