{
  "type": "Feature",
  "properties": {
    "date:inception_lower": "2018-12-01",
    "date:inception_upper": "2018-12-01",
    "iso:country": "GB",
    "wof:name": "SO50 9RJ",
    "wof:placetype": "postalcode"
  },
  "geometry": {"coordinates":[-1.378901,50.957329],"type":"Point"}
}
