{
  "type": "Feature",
  "properties": {
    "iso:country":"GB",
    "wof:name":"CV2 5GP",
    "wof:placetype":"postalcode"
},
  "geometry": {"coordinates":[-1.46664217173273,52.41218050224427],"type":"Point"}
}