{
  "type": "Feature",
  "properties": {
    "date:inception_lower": "1980-01-01",
    "date:inception_upper": "1980-01-01",
    "iso:country": "GB",
    "wof:name": "CV2 5GP",
    "wof:placetype": "postalcode"
  },
  "geometry": {"coordinates":[-1.466642,52.41218],"type":"Point"}
}
