{
  "type": "Feature",
  "properties": {
    "iso:country":"GB",
    "wof:name":"PR9 0NU",
    "wof:placetype":"postalcode"
},
  "geometry": {"coordinates":[-2.99969201345426,53.65527738857941],"type":"Point"}
}