{
  "type": "Feature",
  "properties": {
    "date:inception_lower": "1992-08-01",
    "date:inception_upper": "1992-08-01",
    "iso:country": "GB",
    "wof:name": "PR9 0NU",
    "wof:placetype": "postalcode"
  },
  "geometry": {"coordinates":[-2.999692,53.655277],"type":"Point"}
}
