{
  "type": "Feature",
  "properties": {
    "date:inception_lower":"1980-01-01",
    "date:inception_upper":"1980-01-31",
    "iso:country":"GB",
    "wof:name":"YO15 2HH",
    "wof:placetype":"postalcode"
},
  "geometry": {"coordinates":[-0.186719,54.088696],"type":"Point"}
}