{
  "type": "Feature",
  "properties": {
    "iso:country":"GB",
    "wof:name":"YO15 2HH",
    "wof:placetype":"postalcode"
},
  "geometry": {"coordinates":[-0.1867186705761,54.08869554658538],"type":"Point"}
}