{
  "type": "Feature",
  "properties": {
    "iso:country": "GB",
    "wof:name": "YO15 2HH",
    "wof:placetype": "postalcode"
  },
  "geometry": {"coordinates":[-0.186719,54.088696],"type":"Point"}
}
