{
  "type": "Feature",
  "properties": {
    "iso:country": "GB",
    "wof:name": "EH52 6UD",
    "wof:placetype": "postalcode"
  },
  "geometry": {"coordinates":[-3.466806,55.955958],"type":"Point"}
}
