{
  "type": "Feature",
  "properties": {
    "iso:country":"GB",
    "wof:name":"EH52 6UD",
    "wof:placetype":"postalcode"
},
  "geometry": {"coordinates":[-3.46680563811272,55.95595821819383],"type":"Point"}
}