{
  "type": "Feature",
  "properties": {
    "iso:country":"GB",
    "wof:name":"DY11 6QR",
    "wof:placetype":"postalcode"
},
  "geometry": {"coordinates":[-2.26160332683995,52.38067393701971],"type":"Point"}
}