{
  "type": "Feature",
  "properties": {
    "iso:country":"GB",
    "wof:name":"PE36 6JP",
    "wof:placetype":"postalcode"
},
  "geometry": {"coordinates":[0.50300593989415,52.95160422306726],"type":"Point"}
}