{
  "type": "Feature",
  "properties": {
    "date:inception_lower": "1980-01-01",
    "date:inception_upper": "1980-01-01",
    "iso:country": "GB",
    "wof:name": "PE36 6JP",
    "wof:placetype": "postalcode"
  },
  "geometry": {"coordinates":[0.503006,52.951604],"type":"Point"}
}
