{
  "type": "Feature",
  "properties": {
    "iso:country": "GB",
    "wof:name": "PE36 6JP",
    "wof:placetype": "postalcode"
  },
  "geometry": {"coordinates":[0.503006,52.951604],"type":"Point"}
}
