{
  "type": "Feature",
  "properties": {
    "date:inception_lower": "2023-04-01",
    "date:inception_upper": "2023-04-01",
    "iso:country": "GB",
    "wof:name": "DA10 1FZ",
    "wof:placetype": "postalcode"
  },
  "geometry": {"coordinates":[0.281493,51.439573],"type":"Point"}
}
