{
  "type": "Feature",
  "properties": {
    "iso:country": "GB",
    "wof:name": "EX16 9BG",
    "wof:placetype": "postalcode"
  },
  "geometry": {"coordinates":[-3.412738,51.013443],"type":"Point"}
}
