{
  "type": "Feature",
  "properties": {
    "iso:country":"GB",
    "wof:name":"EX16 9BG",
    "wof:placetype":"postalcode"
},
  "geometry": {"coordinates":[-3.41273812236936,51.01344327706341],"type":"Point"}
}