{
  "type": "Feature",
  "properties": {
    "date:inception_lower":"1980-01-01",
    "date:inception_upper":"1980-01-31",
    "iso:country":"GB",
    "wof:name":"EX16 9BG",
    "wof:placetype":"postalcode"
},
  "geometry": {"coordinates":[-3.412738,51.013443],"type":"Point"}
}