{
  "type": "Feature",
  "properties": {
    "date:inception_lower": "1980-01-01",
    "date:inception_upper": "1980-01-01",
    "iso:country": "GB",
    "wof:name": "BN26 6AA",
    "wof:placetype": "postalcode"
  },
  "geometry": {"coordinates":[0.244804,50.823418],"type":"Point"}
}
