{
  "type": "Feature",
  "properties": {
    "iso:country":"GB",
    "wof:name":"BA21 3SN",
    "wof:placetype":"postalcode"
},
  "geometry": {"coordinates":[-2.66633432397777,50.94839843186103],"type":"Point"}
}