{
  "type": "Feature",
  "properties": {
    "iso:country":"GB",
    "wof:name":"SA44 4HX",
    "wof:placetype":"postalcode"
},
  "geometry": {"coordinates":[-4.33670839552233,52.04317936872213],"type":"Point"}
}