{
  "type": "Feature",
  "properties": {
    "date:inception_lower":"1980-01-01",
    "date:inception_upper":"1980-01-31",
    "iso:country":"GB",
    "wof:name":"PO4 9AY",
    "wof:placetype":"postalcode"
},
  "geometry": {"coordinates":[-1.066034,50.788666],"type":"Point"}
}