{
  "type": "Feature",
  "properties": {
    "iso:country":"GB",
    "wof:name":"NG34 0EA",
    "wof:placetype":"postalcode"
},
  "geometry": {"coordinates":[-0.44652813374615,52.91230542463747],"type":"Point"}
}