{
  "type": "Feature",
  "properties": {
    "iso:country":"GB",
    "wof:name":"NG2 4QH",
    "wof:placetype":"postalcode"
},
  "geometry": {"coordinates":[-1.13318507870223,52.95207433061453],"type":"Point"}
}