{
  "type": "Feature",
  "properties": {
    "iso:country":"GB",
    "wof:name":"DD2 5PP",
    "wof:placetype":"postalcode"
},
  "geometry": {"coordinates":[-3.05229052136555,56.49357664272947],"type":"Point"}
}