{
  "type": "Feature",
  "properties": {
    "iso:country": "GB",
    "wof:name": "DD2 5PP",
    "wof:placetype": "postalcode"
  },
  "geometry": {"coordinates":[-3.05229,56.493577],"type":"Point"}
}
