{
  "type": "Feature",
  "properties": {
    "iso:country":"GB",
    "wof:name":"NW8 6HY",
    "wof:placetype":"postalcode"
},
  "geometry": {"coordinates":[-0.17319010434786,51.54121615471128],"type":"Point"}
}