{
  "type": "Feature",
  "properties": {
    "iso:country": "GB",
    "wof:name": "TW3 4LJ",
    "wof:placetype": "postalcode"
  },
  "geometry": {"coordinates":[-0.37903,51.475027],"type":"Point"}
}
