{
  "type": "Feature",
  "properties": {
    "iso:country":"GB",
    "wof:name":"WA5 1LS",
    "wof:placetype":"postalcode"
},
  "geometry": {"coordinates":[-2.61296540193155,53.38925156887631],"type":"Point"}
}