{
  "type": "Feature",
  "properties": {
    "iso:country": "GB",
    "wof:name": "HR9 5TR",
    "wof:placetype": "postalcode"
  },
  "geometry": {"coordinates":[-2.520688,51.87761],"type":"Point"}
}
