{
  "type": "Feature",
  "properties": {
    "iso:country":"GB",
    "wof:name":"HR9 5TR",
    "wof:placetype":"postalcode"
},
  "geometry": {"coordinates":[-2.52068688625202,51.87760181771003],"type":"Point"}
}