{
  "type": "Feature",
  "properties": {
    "iso:country":"GB",
    "wof:name":"CW9 8NL",
    "wof:placetype":"postalcode"
},
  "geometry": {"coordinates":[-2.50593018417964,53.22491676014174],"type":"Point"}
}