{
  "type": "Feature",
  "properties": {
    "iso:country":"GB",
    "wof:name":"RG23 7EU",
    "wof:placetype":"postalcode"
},
  "geometry": {"coordinates":[-1.19256511016738,51.27139455700122],"type":"Point"}
}