{
  "type": "Feature",
  "properties": {
    "iso:country":"GB",
    "wof:name":"EH53 0FE",
    "wof:placetype":"postalcode"
},
  "geometry": {"coordinates":[-3.46356081247998,55.88820731816194],"type":"Point"}
}