{
  "type": "Feature",
  "properties": {
    "iso:country": "GB",
    "wof:name": "EH53 0FE",
    "wof:placetype": "postalcode"
  },
  "geometry": {"coordinates":[-3.463561,55.888207],"type":"Point"}
}
