{
  "type": "Feature",
  "properties": {
    "date:inception_lower": "2016-09-01",
    "date:inception_upper": "2016-09-01",
    "iso:country": "GB",
    "wof:name": "TR3 6FT",
    "wof:placetype": "postalcode"
  },
  "geometry": {"coordinates":[-5.119638,50.263692],"type":"Point"}
}
