{
  "type": "Feature",
  "properties": {
    "iso:country": "GB",
    "wof:name": "CA8 1SU",
    "wof:placetype": "postalcode"
  },
  "geometry": {"coordinates":[-2.742794,54.938296],"type":"Point"}
}
