{
  "type": "Feature",
  "properties": {
    "iso:country":"GB",
    "wof:name":"BS22 7YR",
    "wof:placetype":"postalcode"
},
  "geometry": {"coordinates":[-2.9138395886374,51.38378152725129],"type":"Point"}
}