{
  "type": "Feature",
  "properties": {
    "date:inception_lower": "1997-12-01",
    "date:inception_upper": "1997-12-01",
    "iso:country": "GB",
    "wof:name": "BS22 7YR",
    "wof:placetype": "postalcode"
  },
  "geometry": {"coordinates":[-2.91384,51.383782],"type":"Point"}
}
