{
  "type": "Feature",
  "properties": {
    "date:inception_lower": "2017-03-01",
    "date:inception_upper": "2017-03-01",
    "iso:country": "GB",
    "wof:name": "BS23 9PJ",
    "wof:placetype": "postalcode"
  },
  "geometry": {"coordinates":[-2.957028,51.343878],"type":"Point"}
}
