{
  "type": "Feature",
  "properties": {
    "iso:country": "GB",
    "wof:name": "PE6 0TD",
    "wof:placetype": "postalcode"
  },
  "geometry": {"coordinates":[-0.082271,52.620041],"type":"Point"}
}
