{
  "type": "Feature",
  "properties": {
    "iso:country":"GB",
    "wof:name":"PE6 0TD",
    "wof:placetype":"postalcode"
},
  "geometry": {"coordinates":[-0.08531235665194,52.61942380103332],"type":"Point"}
}