{
  "type": "Feature",
  "properties": {
    "date:inception_lower": "1980-01-01",
    "date:inception_upper": "1980-01-01",
    "iso:country": "GB",
    "wof:name": "PE6 0TD",
    "wof:placetype": "postalcode"
  },
  "geometry": {"coordinates":[-0.082271,52.620041],"type":"Point"}
}
