{
  "type": "Feature",
  "properties": {
    "iso:country":"GB",
    "wof:name":"GL8 8BH",
    "wof:placetype":"postalcode"
},
  "geometry": {"coordinates":[-2.16140613996335,51.64374323785585],"type":"Point"}
}