{
  "type": "Feature",
  "properties": {
    "iso:country":"GB",
    "wof:name":"CT15 7LW",
    "wof:placetype":"postalcode"
},
  "geometry": {"coordinates":[1.24092501935996,51.18667151384525],"type":"Point"}
}