{
  "type": "Feature",
  "properties": {
    "date:inception_lower": "1980-01-01",
    "date:inception_upper": "1980-01-01",
    "iso:country": "GB",
    "wof:name": "CT15 7LW",
    "wof:placetype": "postalcode"
  },
  "geometry": {"coordinates":[1.240925,51.186672],"type":"Point"}
}
