{
  "type": "Feature",
  "properties": {
    "iso:country":"GB",
    "wof:name":"E14 3GL",
    "wof:placetype":"postalcode"
},
  "geometry": {"coordinates":[-0.00677342479998,51.49298576623057],"type":"Point"}
}