{
  "type": "Feature",
  "properties": {
    "iso:country": "GB",
    "wof:name": "G15 6AA",
    "wof:placetype": "postalcode"
  },
  "geometry": {"coordinates":[-4.355503,55.90745],"type":"Point"}
}
