{
  "type": "Feature",
  "properties": {
    "date:inception_lower":"1980-01-01",
    "date:inception_upper":"1980-01-31",
    "iso:country":"GB",
    "wof:name":"PH13 9NZ",
    "wof:placetype":"postalcode"
},
  "geometry": {"coordinates":[-3.303913,56.518045],"type":"Point"}
}