{
  "type": "Feature",
  "properties": {
    "iso:country":"GB",
    "wof:name":"PH13 9NZ",
    "wof:placetype":"postalcode"
},
  "geometry": {"coordinates":[-3.30391255641661,56.51804507684232],"type":"Point"}
}