{
  "type": "Feature",
  "properties": {
    "iso:country": "GB",
    "wof:name": "LS15 8GH",
    "wof:placetype": "postalcode"
  },
  "geometry": {"coordinates":[-1.425401,53.799827],"type":"Point"}
}
