{
  "type": "Feature",
  "properties": {
    "date:inception_lower":"1980-01-01",
    "date:inception_upper":"1980-01-31",
    "iso:country":"GB",
    "wof:name":"W3 9AE",
    "wof:placetype":"postalcode"
},
  "geometry": {"coordinates":[-0.283871,51.502431],"type":"Point"}
}