{
  "type": "Feature",
  "properties": {
    "iso:country":"GB",
    "wof:name":"WS10 9RD",
    "wof:placetype":"postalcode"
},
  "geometry": {"coordinates":[-2.00457376641572,52.56118586001907],"type":"Point"}
}