{
  "type": "Feature",
  "properties": {
    "iso:country":"GB",
    "wof:name":"GL18 1DD",
    "wof:placetype":"postalcode"
},
  "geometry": {"coordinates":[-2.40980374910293,51.93650823894724],"type":"Point"}
}