{
  "type": "Feature",
  "properties": {
    "date:inception_lower": "1980-01-01",
    "date:inception_upper": "1980-01-01",
    "iso:country": "GB",
    "wof:name": "SG14 2NP",
    "wof:placetype": "postalcode"
  },
  "geometry": {"coordinates":[-0.146205,51.786154],"type":"Point"}
}
