{
  "type": "Feature",
  "properties": {
    "iso:country":"GB",
    "wof:name":"SG14 2NP",
    "wof:placetype":"postalcode"
},
  "geometry": {"coordinates":[-0.14623194587803,51.78614797337129],"type":"Point"}
}