{
  "type": "Feature",
  "properties": {
    "iso:country": "GB",
    "wof:name": "CT17 0LN",
    "wof:placetype": "postalcode"
  },
  "geometry": {"coordinates":[1.28549,51.140101],"type":"Point"}
}
