{
  "type": "Feature",
  "properties": {
    "iso:country":"GB",
    "wof:name":"PA19 1XA",
    "wof:placetype":"postalcode"
},
  "geometry": {"coordinates":[-4.80479030751666,55.95466923930313],"type":"Point"}
}