{
  "type": "Feature",
  "properties": {
    "iso:country":"GB",
    "wof:name":"BA1 3BN",
    "wof:placetype":"postalcode"
},
  "geometry": {"coordinates":[-2.38305639104619,51.38502039795559],"type":"Point"}
}