{
  "type": "Feature",
  "properties": {
    "iso:country":"GB",
    "wof:name":"LS12 4HF",
    "wof:placetype":"postalcode"
},
  "geometry": {"coordinates":[-1.59584962367052,53.78891073928681],"type":"Point"}
}