{
  "type": "Feature",
  "properties": {
    "iso:country": "GB",
    "wof:name": "LS12 4HF",
    "wof:placetype": "postalcode"
  },
  "geometry": {"coordinates":[-1.59585,53.788911],"type":"Point"}
}
