{
  "type": "Feature",
  "properties": {
    "date:inception_lower": "1980-01-01",
    "date:inception_upper": "1980-01-01",
    "iso:country": "GB",
    "wof:name": "OL16 5PY",
    "wof:placetype": "postalcode"
  },
  "geometry": {"coordinates":[-2.141673,53.610005],"type":"Point"}
}
