{
  "type": "Feature",
  "properties": {
    "iso:country":"GB",
    "wof:name":"B32 4JL",
    "wof:placetype":"postalcode"
},
  "geometry": {"coordinates":[-2.00601521994896,52.42854828978435],"type":"Point"}
}