{
  "type": "Feature",
  "properties": {
    "date:inception_lower": "1980-01-01",
    "date:inception_upper": "1980-01-01",
    "iso:country": "GB",
    "wof:name": "B32 4JL",
    "wof:placetype": "postalcode"
  },
  "geometry": {"coordinates":[-2.006015,52.428548],"type":"Point"}
}
