{
  "type": "Feature",
  "properties": {
    "iso:country":"GB",
    "wof:name":"WS2 7JS",
    "wof:placetype":"postalcode"
},
  "geometry": {"coordinates":[-2.01329065526524,52.6054329782667],"type":"Point"}
}