{
  "type": "Feature",
  "properties": {
    "date:inception_lower":"1980-01-01",
    "date:inception_upper":"1980-01-31",
    "iso:country":"GB",
    "wof:name":"WS2 7JS",
    "wof:placetype":"postalcode"
},
  "geometry": {"coordinates":[-2.013291,52.605433],"type":"Point"}
}