{
  "type": "Feature",
  "properties": {
    "iso:country":"GB",
    "wof:name":"TW2 7EE",
    "wof:placetype":"postalcode"
},
  "geometry": {"coordinates":[-0.35780522567231,51.45738571425447],"type":"Point"}
}