{
  "type": "Feature",
  "properties": {
    "iso:country":"GB",
    "wof:name":"BH25 6TT",
    "wof:placetype":"postalcode"
},
  "geometry": {"coordinates":[-1.64715130936934,50.7520593971989],"type":"Point"}
}