{
  "type": "Feature",
  "properties": {
    "date:inception_lower": "1984-10-01",
    "date:inception_upper": "1984-10-01",
    "iso:country": "GB",
    "wof:name": "WN8 8HL",
    "wof:placetype": "postalcode"
  },
  "geometry": {"coordinates":[-2.802085,53.547869],"type":"Point"}
}
