{
  "type": "Feature",
  "properties": {
    "iso:country":"GB",
    "wof:name":"G40 1DX",
    "wof:placetype":"postalcode"
},
  "geometry": {"coordinates":[-4.23172579284349,55.8497661030291],"type":"Point"}
}