{
  "type": "Feature",
  "properties": {
    "iso:country": "GB",
    "wof:name": "G40 1DX",
    "wof:placetype": "postalcode"
  },
  "geometry": {"coordinates":[-4.231726,55.849766],"type":"Point"}
}
