{
  "type": "Feature",
  "properties": {
    "iso:country": "GB",
    "wof:name": "DN20 9FN",
    "wof:placetype": "postalcode"
  },
  "geometry": {"coordinates":[-0.503765,53.553986],"type":"Point"}
}
