{
  "type": "Feature",
  "properties": {
    "date:inception_lower": "2004-06-01",
    "date:inception_upper": "2004-06-01",
    "iso:country": "GB",
    "wof:name": "DN20 9FN",
    "wof:placetype": "postalcode"
  },
  "geometry": {"coordinates":[-0.503765,53.553986],"type":"Point"}
}
