{
  "type": "Feature",
  "properties": {
    "iso:country":"GB",
    "wof:name":"DN20 9FN",
    "wof:placetype":"postalcode"
},
  "geometry": {"coordinates":[-0.50376497368161,53.55398594665397],"type":"Point"}
}