{
  "type": "Feature",
  "properties": {
    "date:inception_lower":"1980-01-01",
    "date:inception_upper":"1980-01-31",
    "iso:country":"GB",
    "wof:name":"BS6 7AJ",
    "wof:placetype":"postalcode"
},
  "geometry": {"coordinates":[-2.596645,51.469323],"type":"Point"}
}