{
  "type": "Feature",
  "properties": {
    "iso:country":"GB",
    "wof:name":"BS6 7AJ",
    "wof:placetype":"postalcode"
},
  "geometry": {"coordinates":[-2.59664508830037,51.4693233179853],"type":"Point"}
}