{
  "type": "Feature",
  "properties": {
    "iso:country": "GB",
    "wof:name": "PO20 1AJ",
    "wof:placetype": "postalcode"
  },
  "geometry": {"coordinates":[-0.775496,50.807795],"type":"Point"}
}
