{
  "type": "Feature",
  "properties": {
    "iso:country":"GB",
    "wof:name":"PO20 1AJ",
    "wof:placetype":"postalcode"
},
  "geometry": {"coordinates":[-0.77549629436757,50.80779529780381],"type":"Point"}
}