{
  "type": "Feature",
  "properties": {
    "date:inception_lower": "1980-01-01",
    "date:inception_upper": "1980-01-01",
    "iso:country": "GB",
    "wof:name": "TW11 9RL",
    "wof:placetype": "postalcode"
  },
  "geometry": {"coordinates":[-0.308262,51.420154],"type":"Point"}
}
