{
  "type": "Feature",
  "properties": {
    "iso:country": "GB",
    "wof:name": "OX14 4EU",
    "wof:placetype": "postalcode"
  },
  "geometry": {"coordinates":[-1.29814,51.631826],"type":"Point"}
}
