{
  "type": "Feature",
  "properties": {
    "iso:country": "GB",
    "wof:name": "CM3 5FY",
    "wof:placetype": "postalcode"
  },
  "geometry": {"coordinates":[0.61685,51.638812],"type":"Point"}
}
