{
  "type": "Feature",
  "properties": {
    "iso:country":"GB",
    "wof:name":"CM3 5FY",
    "wof:placetype":"postalcode"
},
  "geometry": {"coordinates":[0.61685021469876,51.63881209851227],"type":"Point"}
}