{
  "type": "Feature",
  "properties": {
    "iso:country":"GB",
    "wof:name":"KA15 2JF",
    "wof:placetype":"postalcode"
},
  "geometry": {"coordinates":[-4.62969155960568,55.76315216876082],"type":"Point"}
}