{
  "type": "Feature",
  "properties": {
    "iso:country":"GB",
    "wof:name":"L35 3PX",
    "wof:placetype":"postalcode"
},
  "geometry": {"coordinates":[-2.79488933707452,53.40376517852065],"type":"Point"}
}