{
  "type": "Feature",
  "properties": {
    "iso:country":"GB",
    "wof:name":"CH7 4QA",
    "wof:placetype":"postalcode"
},
  "geometry": {"coordinates":[-3.1839398774033,53.09751925885399],"type":"Point"}
}