{
  "type": "Feature",
  "properties": {
    "date:inception_lower": "2022-02-01",
    "date:inception_upper": "2022-02-01",
    "iso:country": "GB",
    "wof:name": "CH7 4QA",
    "wof:placetype": "postalcode"
  },
  "geometry": {"coordinates":[-3.18397,53.097543],"type":"Point"}
}
