{
  "type": "Feature",
  "properties": {
    "iso:country":"GB",
    "wof:name":"GU5 0UH",
    "wof:placetype":"postalcode"
},
  "geometry": {"coordinates":[-0.52702828041178,51.18426884264665],"type":"Point"}
}