{
  "type": "Feature",
  "properties": {
    "iso:country":"GB",
    "wof:name":"PE27 4TB",
    "wof:placetype":"postalcode"
},
  "geometry": {"coordinates":[-0.03295716932796,52.32888321836592],"type":"Point"}
}