{
  "type": "Feature",
  "properties": {
    "iso:country": "GB",
    "wof:name": "S20 5EG",
    "wof:placetype": "postalcode"
  },
  "geometry": {"coordinates":[-1.370012,53.324923],"type":"Point"}
}
