{
  "type": "Feature",
  "properties": {
    "iso:country":"GB",
    "wof:name":"S20 5EG",
    "wof:placetype":"postalcode"
},
  "geometry": {"coordinates":[-1.3700122390576,53.32492291064276],"type":"Point"}
}