{
  "type": "Feature",
  "properties": {
    "iso:country":"GB",
    "wof:name":"BD4 0QX",
    "wof:placetype":"postalcode"
},
  "geometry": {"coordinates":[-1.70061658912272,53.77549312488724],"type":"Point"}
}