{
  "type": "Feature",
  "properties": {
    "iso:country":"GB",
    "wof:name":"M16 8NB",
    "wof:placetype":"postalcode"
},
  "geometry": {"coordinates":[-2.25626349800863,53.44664832241834],"type":"Point"}
}