{
  "type": "Feature",
  "properties": {
    "iso:country":"GB",
    "wof:name":"M7 3TA",
    "wof:placetype":"postalcode"
},
  "geometry": {"coordinates":[-2.28000825962648,53.50396840963209],"type":"Point"}
}