{
  "type": "Feature",
  "properties": {
    "date:inception_lower": "2018-03-01",
    "date:inception_upper": "2018-03-01",
    "iso:country": "GB",
    "wof:name": "TQ12 6UX",
    "wof:placetype": "postalcode"
  },
  "geometry": {"coordinates":[-3.694409,50.540187],"type":"Point"}
}
