{
  "type": "Feature",
  "properties": {
    "iso:country": "GB",
    "wof:name": "TQ12 6UX",
    "wof:placetype": "postalcode"
  },
  "geometry": {"coordinates":[-3.694409,50.540187],"type":"Point"}
}
