{
  "type": "Feature",
  "properties": {
    "iso:country":"GB",
    "wof:name":"HR1 1XF",
    "wof:placetype":"postalcode"
},
  "geometry": {"coordinates":[-2.68323828056029,52.05158898514029],"type":"Point"}
}