{
  "type": "Feature",
  "properties": {
    "date:inception_lower": "1980-01-01",
    "date:inception_upper": "1980-01-01",
    "iso:country": "GB",
    "wof:name": "ST17 9AN",
    "wof:placetype": "postalcode"
  },
  "geometry": {"coordinates":[-2.120861,52.79748],"type":"Point"}
}
