{
  "type": "Feature",
  "properties": {
    "iso:country": "GB",
    "wof:name": "ST17 9AN",
    "wof:placetype": "postalcode"
  },
  "geometry": {"coordinates":[-2.120861,52.79748],"type":"Point"}
}
