{
  "type": "Feature",
  "properties": {
    "date:inception_lower": "2017-01-01",
    "date:inception_upper": "2017-01-01",
    "iso:country": "GB",
    "wof:name": "RG14 1AW",
    "wof:placetype": "postalcode"
  },
  "geometry": {"coordinates":[-1.324971,51.404403],"type":"Point"}
}
