{
  "type": "Feature",
  "properties": {
    "date:inception_lower": "2021-11-01",
    "date:inception_upper": "2021-11-01",
    "iso:country": "GB",
    "wof:name": "GL2 9GL",
    "wof:placetype": "postalcode"
  },
  "geometry": {"coordinates":[-2.223047,51.895004],"type":"Point"}
}
