{
  "type": "Feature",
  "properties": {
    "iso:country":"GB",
    "wof:name":"SY8 1TA",
    "wof:placetype":"postalcode"
},
  "geometry": {"coordinates":[-2.70589735085259,52.37075438724617],"type":"Point"}
}