{
  "type": "Feature",
  "properties": {
    "iso:country":"GB",
    "wof:name":"BS22 7GL",
    "wof:placetype":"postalcode"
},
  "geometry": {"coordinates":[-2.90374988655494,51.36909510047843],"type":"Point"}
}