{
  "type": "Feature",
  "properties": {
    "iso:country":"GB",
    "wof:name":"SW11 2QE",
    "wof:placetype":"postalcode"
},
  "geometry": {"coordinates":[-0.16951219927424,51.46823876161647],"type":"Point"}
}