{
  "type": "Feature",
  "properties": {
    "iso:country":"GB",
    "wof:name":"TF2 9GP",
    "wof:placetype":"postalcode"
},
  "geometry": {"coordinates":[-2.41630825380075,52.69147946709924],"type":"Point"}
}