{
  "type": "Feature",
  "properties": {
    "date:inception_lower": "1980-01-01",
    "date:inception_upper": "1980-01-01",
    "iso:country": "GB",
    "wof:name": "ME7 1EB",
    "wof:placetype": "postalcode"
  },
  "geometry": {"coordinates":[0.55108,51.38749],"type":"Point"}
}
