{
  "type": "Feature",
  "properties": {
    "iso:country": "GB",
    "wof:name": "CW11 4XL",
    "wof:placetype": "postalcode"
  },
  "geometry": {"coordinates":[-2.353576,53.129357],"type":"Point"}
}
