{
  "type": "Feature",
  "properties": {
    "date:inception_lower": "1980-01-01",
    "date:inception_upper": "1980-01-01",
    "iso:country": "GB",
    "wof:name": "LE4 6QH",
    "wof:placetype": "postalcode"
  },
  "geometry": {"coordinates":[-1.115124,52.656376],"type":"Point"}
}
