{
  "type": "Feature",
  "properties": {
    "date:inception_lower": "1980-01-01",
    "date:inception_upper": "1980-01-01",
    "iso:country": "GB",
    "wof:name": "SP10 2QL",
    "wof:placetype": "postalcode"
  },
  "geometry": {"coordinates":[-1.469449,51.207128],"type":"Point"}
}
