{
  "type": "Feature",
  "properties": {
    "iso:country":"GB",
    "wof:name":"SP10 2QL",
    "wof:placetype":"postalcode"
},
  "geometry": {"coordinates":[-1.46944950896868,51.20712799784337],"type":"Point"}
}