{
  "type": "Feature",
  "properties": {
    "date:inception_lower": "2021-01-01",
    "date:inception_upper": "2021-01-01",
    "iso:country": "GB",
    "wof:name": "TA6 4YW",
    "wof:placetype": "postalcode"
  },
  "geometry": {"coordinates":[-2.986131,51.144845],"type":"Point"}
}
