{
  "type": "Feature",
  "properties": {
    "iso:country":"GB",
    "wof:name":"CH3 7LH",
    "wof:placetype":"postalcode"
},
  "geometry": {"coordinates":[-2.79028994626894,53.21221443048849],"type":"Point"}
}