{
  "type": "Feature",
  "properties": {
    "iso:country": "GB",
    "wof:name": "PR3 0LS",
    "wof:placetype": "postalcode"
  },
  "geometry": {"coordinates":[-2.789037,53.898671],"type":"Point"}
}
