{
  "type": "Feature",
  "properties": {
    "iso:country":"GB",
    "wof:name":"NG25 0RP",
    "wof:placetype":"postalcode"
},
  "geometry": {"coordinates":[-1.008354639309,53.0494081701076],"type":"Point"}
}