{
  "type": "Feature",
  "properties": {
    "iso:country": "GB",
    "wof:name": "NG25 0RP",
    "wof:placetype": "postalcode"
  },
  "geometry": {"coordinates":[-1.008355,53.049408],"type":"Point"}
}
