{
  "type": "Feature",
  "properties": {
    "date:inception_lower":"1980-01-01",
    "date:inception_upper":"1980-01-31",
    "iso:country":"GB",
    "wof:name":"W8 7JY",
    "wof:placetype":"postalcode"
},
  "geometry": {"coordinates":[-0.201761,51.506731],"type":"Point"}
}