{
  "type": "Feature",
  "properties": {
    "iso:country":"GB",
    "wof:name":"W8 7JY",
    "wof:placetype":"postalcode"
},
  "geometry": {"coordinates":[-0.20176118170211,51.50673099970955],"type":"Point"}
}