{
  "type": "Feature",
  "properties": {
    "iso:country":"GB",
    "wof:name":"EX38 8ER",
    "wof:placetype":"postalcode"
},
  "geometry": {"coordinates":[-4.14198847132634,50.9520892448443],"type":"Point"}
}