{
  "type": "Feature",
  "properties": {
    "date:inception_lower": "1980-01-01",
    "date:inception_upper": "1980-01-01",
    "iso:country": "GB",
    "wof:name": "EX38 8ER",
    "wof:placetype": "postalcode"
  },
  "geometry": {"coordinates":[-4.142084,50.952082],"type":"Point"}
}
