{
  "type": "Feature",
  "properties": {
    "iso:country":"GB",
    "wof:name":"TN34 3SH",
    "wof:placetype":"postalcode"
},
  "geometry": {"coordinates":[0.58633555142382,50.86537201611222],"type":"Point"}
}