{
  "type": "Feature",
  "properties": {
    "iso:country": "GB",
    "wof:name": "BS32 4RZ",
    "wof:placetype": "postalcode"
  },
  "geometry": {"coordinates":[-2.574156,51.540081],"type":"Point"}
}
