{
  "type": "Feature",
  "properties": {
    "iso:country": "GB",
    "wof:name": "CT7 9TB",
    "wof:placetype": "postalcode"
  },
  "geometry": {"coordinates":[1.306173,51.373201],"type":"Point"}
}
