{
  "type": "Feature",
  "properties": {
    "iso:country":"GB",
    "wof:name":"N15 6UA",
    "wof:placetype":"postalcode"
},
  "geometry": {"coordinates":[-0.06545276832967,51.57857952708667],"type":"Point"}
}