{
  "type": "Feature",
  "properties": {
    "date:inception_lower":"1980-01-01",
    "date:inception_upper":"1980-01-31",
    "iso:country":"GB",
    "wof:name":"RG4 7BT",
    "wof:placetype":"postalcode"
},
  "geometry": {"coordinates":[-0.984921,51.474886],"type":"Point"}
}