{
  "type": "Feature",
  "properties": {
    "iso:country":"GB",
    "wof:name":"RG4 7BT",
    "wof:placetype":"postalcode"
},
  "geometry": {"coordinates":[-0.98492100867617,51.47488566625093],"type":"Point"}
}