{
  "type": "Feature",
  "properties": {
    "date:inception_lower": "2007-10-01",
    "date:inception_upper": "2007-10-01",
    "iso:country": "GB",
    "wof:name": "FY4 2RF",
    "wof:placetype": "postalcode"
  },
  "geometry": {"coordinates":[-3.025899,53.776032],"type":"Point"}
}
