{
  "type": "Feature",
  "properties": {
    "date:inception_lower": "1980-01-01",
    "date:inception_upper": "1980-01-01",
    "iso:country": "GB",
    "wof:name": "GL56 9TR",
    "wof:placetype": "postalcode"
  },
  "geometry": {"coordinates":[-1.786753,52.011554],"type":"Point"}
}
