{
  "type": "Feature",
  "properties": {
    "iso:country":"GB",
    "wof:name":"GL56 9TR",
    "wof:placetype":"postalcode"
},
  "geometry": {"coordinates":[-1.78675317870511,52.01155404790163],"type":"Point"}
}