{
  "type": "Feature",
  "properties": {
    "iso:country": "GB",
    "wof:name": "CM3 4LS",
    "wof:placetype": "postalcode"
  },
  "geometry": {"coordinates":[0.586868,51.697583],"type":"Point"}
}
