{
  "type": "Feature",
  "properties": {
    "iso:country":"GB",
    "wof:name":"M18 7AZ",
    "wof:placetype":"postalcode"
},
  "geometry": {"coordinates":[-2.17762521602262,53.46119084659584],"type":"Point"}
}