{
  "type": "Feature",
  "properties": {
    "iso:country": "GB",
    "wof:name": "SA65 9HR",
    "wof:placetype": "postalcode"
  },
  "geometry": {"coordinates":[-4.974648,51.99062],"type":"Point"}
}
