{
  "type": "Feature",
  "properties": {
    "iso:country": "GB",
    "wof:name": "GL3 3UJ",
    "wof:placetype": "postalcode"
  },
  "geometry": {"coordinates":[-2.18071,51.849575],"type":"Point"}
}
