{
  "type": "Feature",
  "properties": {
    "iso:country":"GB",
    "wof:name":"SK5 7ER",
    "wof:placetype":"postalcode"
},
  "geometry": {"coordinates":[-2.16131633190416,53.42219491659603],"type":"Point"}
}