{
  "type": "Feature",
  "properties": {
    "iso:country": "GB",
    "wof:name": "SK5 7ER",
    "wof:placetype": "postalcode"
  },
  "geometry": {"coordinates":[-2.160681,53.421871],"type":"Point"}
}
