{
  "type": "Feature",
  "properties": {
    "date:inception_lower": "2014-02-01",
    "date:inception_upper": "2014-02-01",
    "iso:country": "GB",
    "wof:name": "SK5 7ER",
    "wof:placetype": "postalcode"
  },
  "geometry": {"coordinates":[-2.160666,53.421871],"type":"Point"}
}
