{
  "type": "Feature",
  "properties": {
    "iso:country": "GB",
    "wof:name": "WA9 4ZE",
    "wof:placetype": "postalcode"
  },
  "geometry": {"coordinates":[-2.684555,53.433429],"type":"Point"}
}
