{
  "type": "Feature",
  "properties": {
    "date:inception_lower":"2001-12-01",
    "date:inception_upper":"2001-12-31",
    "iso:country":"GB",
    "wof:name":"WA9 4ZE",
    "wof:placetype":"postalcode"
},
  "geometry": {"coordinates":[-2.684555,53.433429],"type":"Point"}
}