{
  "type": "Feature",
  "properties": {
    "iso:country":"GB",
    "wof:name":"WA9 4ZE",
    "wof:placetype":"postalcode"
},
  "geometry": {"coordinates":[-2.68455547390492,53.43342851247561],"type":"Point"}
}