{
  "type": "Feature",
  "properties": {
    "iso:country":"GB",
    "wof:name":"SW14 8LX",
    "wof:placetype":"postalcode"
},
  "geometry": {"coordinates":[-0.26598894004587,51.46412094600205],"type":"Point"}
}