{
  "type": "Feature",
  "properties": {
    "iso:country":"GB",
    "wof:name":"M28 2WP",
    "wof:placetype":"postalcode"
},
  "geometry": {"coordinates":[-2.37224727435424,53.50401319394613],"type":"Point"}
}