{
  "type": "Feature",
  "properties": {
    "iso:country":"GB",
    "wof:name":"UB2 4ED",
    "wof:placetype":"postalcode"
},
  "geometry": {"coordinates":[-0.37906239724126,51.49930687932918],"type":"Point"}
}