{
  "type": "Feature",
  "properties": {
    "date:inception_lower":"2009-04-01",
    "date:inception_upper":"2009-04-30",
    "iso:country":"GB",
    "wof:name":"SN25 1XH",
    "wof:placetype":"postalcode"
},
  "geometry": {"coordinates":[-1.82295,51.59863],"type":"Point"}
}