{
  "type": "Feature",
  "properties": {
    "date:inception_lower":"1985-10-01",
    "date:inception_upper":"1985-10-31",
    "iso:country":"GB",
    "wof:name":"L30 1SQ",
    "wof:placetype":"postalcode"
},
  "geometry": {"coordinates":[-2.965582,53.476808],"type":"Point"}
}