{
  "type": "Feature",
  "properties": {
    "iso:country": "GB",
    "wof:name": "L30 1SQ",
    "wof:placetype": "postalcode"
  },
  "geometry": {"coordinates":[-2.965582,53.476808],"type":"Point"}
}
