{
  "type": "Feature",
  "properties": {
    "iso:country":"GB",
    "wof:name":"TS24 7ND",
    "wof:placetype":"postalcode"
},
  "geometry": {"coordinates":[-1.20241938336501,54.68254291941102],"type":"Point"}
}