{
  "type": "Feature",
  "properties": {
    "iso:country":"GB",
    "wof:name":"S4 7BB",
    "wof:placetype":"postalcode"
},
  "geometry": {"coordinates":[-1.46223936218261,53.40143661929037],"type":"Point"}
}