{
  "type": "Feature",
  "properties": {
    "iso:country": "GB",
    "wof:name": "GL53 8PQ",
    "wof:placetype": "postalcode"
  },
  "geometry": {"coordinates":[-2.04368,51.879241],"type":"Point"}
}
