{
  "type": "Feature",
  "properties": {
    "iso:country":"GB",
    "wof:name":"EX20 2DA",
    "wof:placetype":"postalcode"
},
  "geometry": {"coordinates":[-3.9123247353513,50.7967675343985],"type":"Point"}
}