{
  "type": "Feature",
  "properties": {
    "iso:country": "GB",
    "wof:name": "EX20 2DA",
    "wof:placetype": "postalcode"
  },
  "geometry": {"coordinates":[-3.912325,50.796768],"type":"Point"}
}
