{
  "type": "Feature",
  "properties": {
    "date:inception_lower":"1980-01-01",
    "date:inception_upper":"1980-01-31",
    "iso:country":"GB",
    "wof:name":"EX20 2DA",
    "wof:placetype":"postalcode"
},
  "geometry": {"coordinates":[-3.912325,50.796768],"type":"Point"}
}