{
  "type": "Feature",
  "properties": {
    "iso:country": "GB",
    "wof:name": "G76 0LU",
    "wof:placetype": "postalcode"
  },
  "geometry": {"coordinates":[-4.282034,55.741783],"type":"Point"}
}
