{
  "type": "Feature",
  "properties": {
    "iso:country": "GB",
    "wof:name": "SE13 5AF",
    "wof:placetype": "postalcode"
  },
  "geometry": {"coordinates":[-0.01061,51.464418],"type":"Point"}
}
