{
  "type": "Feature",
  "properties": {
    "iso:country": "GB",
    "wof:name": "CW2 6UD",
    "wof:placetype": "postalcode"
  },
  "geometry": {"coordinates":[-2.452222,53.075987],"type":"Point"}
}
