{
  "type": "Feature",
  "properties": {
    "iso:country": "GB",
    "wof:name": "CF40 2SS",
    "wof:placetype": "postalcode"
  },
  "geometry": {"coordinates":[-3.454632,51.641864],"type":"Point"}
}
