{
  "type": "Feature",
  "properties": {
    "iso:country":"GB",
    "wof:name":"CF40 2SS",
    "wof:placetype":"postalcode"
},
  "geometry": {"coordinates":[-3.45463201352233,51.64186393781645],"type":"Point"}
}