{
  "type": "Feature",
  "properties": {
    "iso:country":"GB",
    "wof:name":"E6 5NA",
    "wof:placetype":"postalcode"
},
  "geometry": {"coordinates":[0.06293179331751,51.50945995108003],"type":"Point"}
}