{
  "type": "Feature",
  "properties": {
    "iso:country":"GB",
    "wof:name":"SK9 6EG",
    "wof:placetype":"postalcode"
},
  "geometry": {"coordinates":[-2.25348760808024,53.31422503151487],"type":"Point"}
}