{
  "type": "Feature",
  "properties": {
    "date:inception_lower": "1980-01-01",
    "date:inception_upper": "1980-01-01",
    "iso:country": "GB",
    "wof:name": "BL9 9TG",
    "wof:placetype": "postalcode"
  },
  "geometry": {"coordinates":[-2.293953,53.56731],"type":"Point"}
}
