{
  "type": "Feature",
  "properties": {
    "iso:country": "GB",
    "wof:name": "BL9 9TG",
    "wof:placetype": "postalcode"
  },
  "geometry": {"coordinates":[-2.293971,53.567312],"type":"Point"}
}
