{
  "type": "Feature",
  "properties": {
    "iso:country":"GB",
    "wof:name":"TR11 2RD",
    "wof:placetype":"postalcode"
},
  "geometry": {"coordinates":[-5.08051687341075,50.15095796010918],"type":"Point"}
}