{
  "type": "Feature",
  "properties": {
    "iso:country": "GB",
    "wof:name": "BN26 6FR",
    "wof:placetype": "postalcode"
  },
  "geometry": {"coordinates":[0.264555,50.822825],"type":"Point"}
}
