{
  "type": "Feature",
  "properties": {
    "iso:country": "GB",
    "wof:name": "WF2 6SU",
    "wof:placetype": "postalcode"
  },
  "geometry": {"coordinates":[-1.487188,53.649134],"type":"Point"}
}
