{
  "type": "Feature",
  "properties": {
    "iso:country":"GB",
    "wof:name":"WF2 6SU",
    "wof:placetype":"postalcode"
},
  "geometry": {"coordinates":[-1.48718793367755,53.6491337765213],"type":"Point"}
}