{
  "type": "Feature",
  "properties": {
    "iso:country":"GB",
    "wof:name":"ML4 2HL",
    "wof:placetype":"postalcode"
},
  "geometry": {"coordinates":[-4.01972311314885,55.81237742246421],"type":"Point"}
}