{
  "type": "Feature",
  "properties": {
    "iso:country": "GB",
    "wof:name": "PO38 1NZ",
    "wof:placetype": "postalcode"
  },
  "geometry": {"coordinates":[-1.198903,50.595947],"type":"Point"}
}
