{
  "type": "Feature",
  "properties": {
    "iso:country":"GB",
    "wof:name":"BS9 2JB",
    "wof:placetype":"postalcode"
},
  "geometry": {"coordinates":[-2.64345840951881,51.48842565747152],"type":"Point"}
}