{
  "type": "Feature",
  "properties": {
    "iso:country":"GB",
    "wof:name":"NE8 3JF",
    "wof:placetype":"postalcode"
},
  "geometry": {"coordinates":[-1.58658462731818,54.95943937133133],"type":"Point"}
}