{
  "type": "Feature",
  "properties": {
    "date:inception_lower": "2002-10-01",
    "date:inception_upper": "2002-10-01",
    "iso:country": "GB",
    "wof:name": "NE8 3JF",
    "wof:placetype": "postalcode"
  },
  "geometry": {"coordinates":[-1.586585,54.959439],"type":"Point"}
}
