{
  "type": "Feature",
  "properties": {
    "iso:country":"GB",
    "wof:name":"RH16 2EW",
    "wof:placetype":"postalcode"
},
  "geometry": {"coordinates":[-0.08778410486307,51.00541616253658],"type":"Point"}
}