{
  "type": "Feature",
  "properties": {
    "iso:country":"GB",
    "wof:name":"CB1 9XJ",
    "wof:placetype":"postalcode"
},
  "geometry": {"coordinates":[0.18651228202043,52.19425454803817],"type":"Point"}
}