{
  "type": "Feature",
  "properties": {
    "date:inception_lower":"1992-08-01",
    "date:inception_upper":"1992-08-31",
    "iso:country":"GB",
    "wof:name":"AL10 9ET",
    "wof:placetype":"postalcode"
},
  "geometry": {"coordinates":[-0.24047,51.746368],"type":"Point"}
}