{
  "type": "Feature",
  "properties": {
    "iso:country":"GB",
    "wof:name":"NE9 7EJ",
    "wof:placetype":"postalcode"
},
  "geometry": {"coordinates":[-1.57916862328992,54.92186908609968],"type":"Point"}
}