{
  "type": "Feature",
  "properties": {
    "iso:country":"GB",
    "wof:name":"TQ10 9FA",
    "wof:placetype":"postalcode"
},
  "geometry": {"coordinates":[-3.83599260869878,50.42138161976602],"type":"Point"}
}