{
  "type": "Feature",
  "properties": {
    "date:inception_lower": "2014-06-01",
    "date:inception_upper": "2014-06-01",
    "iso:country": "GB",
    "wof:name": "TQ10 9FA",
    "wof:placetype": "postalcode"
  },
  "geometry": {"coordinates":[-3.835993,50.421382],"type":"Point"}
}
