{
  "type": "Feature",
  "properties": {
    "iso:country":"GB",
    "wof:name":"S66 1FE",
    "wof:placetype":"postalcode"
},
  "geometry": {"coordinates":[-1.28131902703747,53.41470539930818],"type":"Point"}
}