{
  "type": "Feature",
  "properties": {
    "iso:country": "GB",
    "wof:name": "GU19 5ND",
    "wof:placetype": "postalcode"
  },
  "geometry": {"coordinates":[-0.686846,51.361558],"type":"Point"}
}
