{
  "type": "Feature",
  "properties": {
    "date:inception_lower": "1980-01-01",
    "date:inception_upper": "1980-01-01",
    "iso:country": "GB",
    "wof:name": "LN4 3PD",
    "wof:placetype": "postalcode"
  },
  "geometry": {"coordinates":[-0.385948,53.108651],"type":"Point"}
}
