{
  "type": "Feature",
  "properties": {
    "iso:country":"GB",
    "wof:name":"LN4 3PD",
    "wof:placetype":"postalcode"
},
  "geometry": {"coordinates":[-0.38594815592585,53.10865140046057],"type":"Point"}
}