{
  "type": "Feature",
  "properties": {
    "iso:country":"GB",
    "wof:name":"PE8 5RH",
    "wof:placetype":"postalcode"
},
  "geometry": {"coordinates":[-0.41150245826093,52.43692427577116],"type":"Point"}
}