{
  "type": "Feature",
  "properties": {
    "iso:country": "GB",
    "wof:name": "TF6 6RB",
    "wof:placetype": "postalcode"
  },
  "geometry": {"coordinates":[-2.591742,52.765141],"type":"Point"}
}
