{
  "type": "Feature",
  "properties": {
    "date:inception_lower":"2002-06-01",
    "date:inception_upper":"2002-06-30",
    "iso:country":"GB",
    "wof:name":"TF6 6RB",
    "wof:placetype":"postalcode"
},
  "geometry": {"coordinates":[-2.591742,52.765141],"type":"Point"}
}