{
  "type": "Feature",
  "properties": {
    "iso:country":"GB",
    "wof:name":"TF6 6RB",
    "wof:placetype":"postalcode"
},
  "geometry": {"coordinates":[-2.59174158458164,52.76514102668859],"type":"Point"}
}