{
  "type": "Feature",
  "properties": {
    "iso:country":"GB",
    "wof:name":"LN11 0YN",
    "wof:placetype":"postalcode"
},
  "geometry": {"coordinates":[-0.01018293902853,53.37407524487795],"type":"Point"}
}