{
  "type": "Feature",
  "properties": {
    "iso:country":"GB",
    "wof:name":"CT16 3EX",
    "wof:placetype":"postalcode"
},
  "geometry": {"coordinates":[1.28553345679449,51.16144516587159],"type":"Point"}
}