{
  "type": "Feature",
  "properties": {
    "iso:country":"GB",
    "wof:name":"PO6 2LH",
    "wof:placetype":"postalcode"
},
  "geometry": {"coordinates":[-1.05643145231093,50.84280603218841],"type":"Point"}
}