{
  "type": "Feature",
  "properties": {
    "date:inception_lower":"1980-01-01",
    "date:inception_upper":"1980-01-31",
    "iso:country":"GB",
    "wof:name":"KA3 1TJ",
    "wof:placetype":"postalcode"
},
  "geometry": {"coordinates":[-4.488753,55.623284],"type":"Point"}
}