{
  "type": "Feature",
  "properties": {
    "iso:country":"GB",
    "wof:name":"KA3 1TJ",
    "wof:placetype":"postalcode"
},
  "geometry": {"coordinates":[-4.48875273632454,55.62328391339944],"type":"Point"}
}