{
  "type": "Feature",
  "properties": {
    "iso:country": "GB",
    "wof:name": "IV36 3YF",
    "wof:placetype": "postalcode"
  },
  "geometry": {"coordinates":[-3.611278,57.65987],"type":"Point"}
}
