{
  "type": "Feature",
  "properties": {
    "date:inception_lower": "1988-03-01",
    "date:inception_upper": "1988-03-01",
    "iso:country": "GB",
    "wof:name": "CH5 3NW",
    "wof:placetype": "postalcode"
  },
  "geometry": {"coordinates":[-3.05173,53.180475],"type":"Point"}
}
