{
  "type": "Feature",
  "properties": {
    "iso:country":"GB",
    "wof:name":"CH5 3NW",
    "wof:placetype":"postalcode"
},
  "geometry": {"coordinates":[-3.0517303131143,53.18047464970526],"type":"Point"}
}