{
  "type": "Feature",
  "properties": {
    "date:inception_lower":"1980-01-01",
    "date:inception_upper":"1980-01-31",
    "iso:country":"GB",
    "wof:name":"WA3 4DQ",
    "wof:placetype":"postalcode"
},
  "geometry": {"coordinates":[-2.527187,53.458793],"type":"Point"}
}