{
  "type": "Feature",
  "properties": {
    "iso:country": "GB",
    "wof:name": "WA3 4DQ",
    "wof:placetype": "postalcode"
  },
  "geometry": {"coordinates":[-2.527187,53.458793],"type":"Point"}
}
