{
  "type": "Feature",
  "properties": {
    "iso:country":"GB",
    "wof:name":"WA3 4DQ",
    "wof:placetype":"postalcode"
},
  "geometry": {"coordinates":[-2.52718696563645,53.45879287161608],"type":"Point"}
}