{
  "type": "Feature",
  "properties": {
    "date:inception_lower": "1980-01-01",
    "date:inception_upper": "1980-01-01",
    "iso:country": "GB",
    "wof:name": "NG16 6FX",
    "wof:placetype": "postalcode"
  },
  "geometry": {"coordinates":[-1.315132,53.072532],"type":"Point"}
}
