{
  "type": "Feature",
  "properties": {
    "iso:country": "GB",
    "wof:name": "OL12 8AZ",
    "wof:placetype": "postalcode"
  },
  "geometry": {"coordinates":[-2.176239,53.660617],"type":"Point"}
}
