{
  "type": "Feature",
  "properties": {
    "iso:country":"GB",
    "wof:name":"OL12 8AZ",
    "wof:placetype":"postalcode"
},
  "geometry": {"coordinates":[-2.17623935364984,53.66061688579143],"type":"Point"}
}