{
  "type": "Feature",
  "properties": {
    "iso:country": "GB",
    "wof:name": "LU3 3EL",
    "wof:placetype": "postalcode"
  },
  "geometry": {"coordinates":[-0.467794,51.919189],"type":"Point"}
}
