{
  "type": "Feature",
  "properties": {
    "iso:country":"GB",
    "wof:name":"WS1 2EW",
    "wof:placetype":"postalcode"
},
  "geometry": {"coordinates":[-1.97612212150876,52.58204897162663],"type":"Point"}
}