{
  "type": "Feature",
  "properties": {
    "date:inception_lower": "2007-05-01",
    "date:inception_upper": "2007-05-01",
    "iso:country": "GB",
    "wof:name": "WS1 2EW",
    "wof:placetype": "postalcode"
  },
  "geometry": {"coordinates":[-1.976122,52.582049],"type":"Point"}
}
