{
  "type": "Feature",
  "properties": {
    "iso:country":"GB",
    "wof:name":"NE23 7HT",
    "wof:placetype":"postalcode"
},
  "geometry": {"coordinates":[-1.59467700423399,55.05534057477107],"type":"Point"}
}