{
  "type": "Feature",
  "properties": {
    "iso:country": "GB",
    "wof:name": "CV35 8BP",
    "wof:placetype": "postalcode"
  },
  "geometry": {"coordinates":[-1.608267,52.243772],"type":"Point"}
}
