{
  "type": "Feature",
  "properties": {
    "date:inception_lower": "1980-01-01",
    "date:inception_upper": "1980-01-01",
    "iso:country": "GB",
    "wof:name": "OL11 5YD",
    "wof:placetype": "postalcode"
  },
  "geometry": {"coordinates":[-2.203641,53.622293],"type":"Point"}
}
