{
  "type": "Feature",
  "properties": {
    "iso:country":"GB",
    "wof:name":"OL11 5YD",
    "wof:placetype":"postalcode"
},
  "geometry": {"coordinates":[-2.20364078857332,53.62229258453639],"type":"Point"}
}