{
  "type": "Feature",
  "properties": {
    "iso:country":"GB",
    "wof:name":"NR31 7AX",
    "wof:placetype":"postalcode"
},
  "geometry": {"coordinates":[1.72223716295654,52.5775937443392],"type":"Point"}
}