{
  "type": "Feature",
  "properties": {
    "iso:country": "GB",
    "wof:name": "BD22 8NF",
    "wof:placetype": "postalcode"
  },
  "geometry": {"coordinates":[-1.948033,53.829522],"type":"Point"}
}
