{
  "type": "Feature",
  "properties": {
    "iso:country":"GB",
    "wof:name":"BD22 8NF",
    "wof:placetype":"postalcode"
},
  "geometry": {"coordinates":[-1.94803293027251,53.82952212333676],"type":"Point"}
}