{
  "type": "Feature",
  "properties": {
    "iso:country":"GB",
    "wof:name":"TA3 6DU",
    "wof:placetype":"postalcode"
},
  "geometry": {"coordinates":[-2.95870923855787,51.01875343681385],"type":"Point"}
}