{
  "type": "Feature",
  "properties": {
    "iso:country": "GB",
    "wof:name": "TA3 6DU",
    "wof:placetype": "postalcode"
  },
  "geometry": {"coordinates":[-2.958709,51.018753],"type":"Point"}
}
