{
  "type": "Feature",
  "properties": {
    "iso:country": "GB",
    "wof:name": "M40 3RQ",
    "wof:placetype": "postalcode"
  },
  "geometry": {"coordinates":[-2.16006,53.520108],"type":"Point"}
}
