{
  "type": "Feature",
  "properties": {
    "iso:country":"GB",
    "wof:name":"M40 3RQ",
    "wof:placetype":"postalcode"
},
  "geometry": {"coordinates":[-2.16005975348003,53.52010789716187],"type":"Point"}
}