{
  "type": "Feature",
  "properties": {
    "iso:country":"GB",
    "wof:name":"BS6 7AY",
    "wof:placetype":"postalcode"
},
  "geometry": {"coordinates":[-2.59761665168974,51.46985786570771],"type":"Point"}
}