{
  "type": "Feature",
  "properties": {
    "date:inception_lower": "2005-05-01",
    "date:inception_upper": "2005-05-01",
    "iso:country": "GB",
    "wof:name": "NR33 7RT",
    "wof:placetype": "postalcode"
  },
  "geometry": {"coordinates":[1.724727,52.412818],"type":"Point"}
}
