{
  "type": "Feature",
  "properties": {
    "iso:country":"GB",
    "wof:name":"HD4 5RF",
    "wof:placetype":"postalcode"
},
  "geometry": {"coordinates":[-1.81216751138418,53.63720379193368],"type":"Point"}
}