{
  "type": "Feature",
  "properties": {
    "iso:country":"GB",
    "wof:name":"PO5 3DS",
    "wof:placetype":"postalcode"
},
  "geometry": {"coordinates":[-1.08912021233521,50.78988257565099],"type":"Point"}
}