{
  "type": "Feature",
  "properties": {
    "iso:country": "GB",
    "wof:name": "PO5 3DS",
    "wof:placetype": "postalcode"
  },
  "geometry": {"coordinates":[-1.08912,50.789883],"type":"Point"}
}
