{
  "type": "Feature",
  "properties": {
    "iso:country": "GB",
    "wof:name": "RG12 9AH",
    "wof:placetype": "postalcode"
  },
  "geometry": {"coordinates":[-0.743833,51.412233],"type":"Point"}
}
