{
  "type": "Feature",
  "properties": {
    "date:inception_lower": "2001-12-01",
    "date:inception_upper": "2001-12-01",
    "iso:country": "GB",
    "wof:name": "NN14 1GG",
    "wof:placetype": "postalcode"
  },
  "geometry": {"coordinates":[-0.820903,52.374141],"type":"Point"}
}
