{
  "type": "Feature",
  "properties": {
    "iso:country":"GB",
    "wof:name":"GU28 9EX",
    "wof:placetype":"postalcode"
},
  "geometry": {"coordinates":[-0.6780825614389,51.0300158293778],"type":"Point"}
}