{
  "type": "Feature",
  "properties": {
    "iso:country": "GB",
    "wof:name": "GU28 9EX",
    "wof:placetype": "postalcode"
  },
  "geometry": {"coordinates":[-0.678083,51.030016],"type":"Point"}
}
