{
  "type": "Feature",
  "properties": {
    "iso:country":"GB",
    "wof:name":"PL9 9RD",
    "wof:placetype":"postalcode"
},
  "geometry": {"coordinates":[-4.11090521153685,50.35450270828105],"type":"Point"}
}