{
  "type": "Feature",
  "properties": {
    "iso:country": "GB",
    "wof:name": "NR31 0PQ",
    "wof:placetype": "postalcode"
  },
  "geometry": {"coordinates":[1.72539,52.587254],"type":"Point"}
}
