{
  "type": "Feature",
  "properties": {
    "iso:country":"GB",
    "wof:name":"G53 5RS",
    "wof:placetype":"postalcode"
},
  "geometry": {"coordinates":[-4.35838438800505,55.83603308453858],"type":"Point"}
}