{
  "type": "Feature",
  "properties": {
    "iso:country":"GB",
    "wof:name":"G81 1DU",
    "wof:placetype":"postalcode"
},
  "geometry": {"coordinates":[-4.3885409128283,55.89959665077298],"type":"Point"}
}