{
  "type": "Feature",
  "properties": {
    "iso:country":"GB",
    "wof:name":"B66 4JU",
    "wof:placetype":"postalcode"
},
  "geometry": {"coordinates":[-1.96163878827667,52.48615918508945],"type":"Point"}
}