{
  "type": "Feature",
  "properties": {
    "iso:country":"GB",
    "wof:name":"UB7 9DG",
    "wof:placetype":"postalcode"
},
  "geometry": {"coordinates":[-0.46209893915649,51.50548764319819],"type":"Point"}
}