{
  "type": "Feature",
  "properties": {
    "date:inception_lower": "2023-05-01",
    "date:inception_upper": "2023-05-01",
    "iso:country": "GB",
    "wof:name": "SW4 4GY",
    "wof:placetype": "postalcode"
  },
  "geometry": {"coordinates":[-0.138875,51.463324],"type":"Point"}
}
