{
  "type": "Feature",
  "properties": {
    "iso:country":"GB",
    "wof:name":"DH3 2PT",
    "wof:placetype":"postalcode"
},
  "geometry": {"coordinates":[-1.57528201235548,54.89386301915128],"type":"Point"}
}