{
  "type": "Feature",
  "properties": {
    "iso:country": "GB",
    "wof:name": "DH3 2PT",
    "wof:placetype": "postalcode"
  },
  "geometry": {"coordinates":[-1.575282,54.893863],"type":"Point"}
}
