{
  "type": "Feature",
  "properties": {
    "iso:country":"GB",
    "wof:name":"SY10 7RL",
    "wof:placetype":"postalcode"
},
  "geometry": {"coordinates":[-3.06972343617533,52.91634600487823],"type":"Point"}
}