{
  "type": "Feature",
  "properties": {
    "iso:country":"GB",
    "wof:name":"LE7 4XT",
    "wof:placetype":"postalcode"
},
  "geometry": {"coordinates":[-1.04259460361566,52.72335430459365],"type":"Point"}
}