{
  "type": "Feature",
  "properties": {
    "date:inception_lower":"2004-05-01",
    "date:inception_upper":"2004-05-31",
    "iso:country":"GB",
    "wof:name":"LE7 4XT",
    "wof:placetype":"postalcode"
},
  "geometry": {"coordinates":[-1.042304,52.723498],"type":"Point"}
}