{
  "type": "Feature",
  "properties": {
    "iso:country":"GB",
    "wof:name":"CT9 2DH",
    "wof:placetype":"postalcode"
},
  "geometry": {"coordinates":[1.39569150665106,51.39023843036096],"type":"Point"}
}