{
  "type": "Feature",
  "properties": {
    "date:inception_lower": "1980-01-01",
    "date:inception_upper": "1980-01-01",
    "iso:country": "GB",
    "wof:name": "NG22 8RY",
    "wof:placetype": "postalcode"
  },
  "geometry": {"coordinates":[-1.026213,53.133364],"type":"Point"}
}
