{
  "type": "Feature",
  "properties": {
    "iso:country":"GB",
    "wof:name":"CM2 6HS",
    "wof:placetype":"postalcode"
},
  "geometry": {"coordinates":[0.48426244014465,51.73459230502041],"type":"Point"}
}