{
  "type": "Feature",
  "properties": {
    "iso:country":"GB",
    "wof:name":"G82 2ET",
    "wof:placetype":"postalcode"
},
  "geometry": {"coordinates":[-4.56118821416704,55.94668287348787],"type":"Point"}
}