{
  "type": "Feature",
  "properties": {
    "date:inception_lower": "1992-01-01",
    "date:inception_upper": "1992-01-01",
    "iso:country": "GB",
    "wof:name": "G82 2ET",
    "wof:placetype": "postalcode"
  },
  "geometry": {"coordinates":[-4.561188,55.946683],"type":"Point"}
}
