{
  "type": "Feature",
  "properties": {
    "iso:country": "GB",
    "wof:name": "BN24 6JA",
    "wof:placetype": "postalcode"
  },
  "geometry": {"coordinates":[0.348144,50.810325],"type":"Point"}
}
