{
  "type": "Feature",
  "properties": {
    "iso:country":"GB",
    "wof:name":"BN24 6JA",
    "wof:placetype":"postalcode"
},
  "geometry": {"coordinates":[0.34812764796394,50.81031163914169],"type":"Point"}
}