{
  "type": "Feature",
  "properties": {
    "date:inception_lower":"1980-01-01",
    "date:inception_upper":"1980-01-31",
    "iso:country":"GB",
    "wof:name":"DH2 2AW",
    "wof:placetype":"postalcode"
},
  "geometry": {"coordinates":[-1.580717,54.855384],"type":"Point"}
}