{
  "type": "Feature",
  "properties": {
    "iso:country": "GB",
    "wof:name": "TQ4 7RX",
    "wof:placetype": "postalcode"
  },
  "geometry": {"coordinates":[-3.575463,50.417279],"type":"Point"}
}
