{
  "type": "Feature",
  "properties": {
    "iso:country":"GB",
    "wof:name":"TQ4 7RX",
    "wof:placetype":"postalcode"
},
  "geometry": {"coordinates":[-3.57546328923637,50.41727899444695],"type":"Point"}
}