{
  "type": "Feature",
  "properties": {
    "iso:country":"GB",
    "wof:name":"PE25 1AH",
    "wof:placetype":"postalcode"
},
  "geometry": {"coordinates":[0.34271228134876,53.15427916754266],"type":"Point"}
}