{
  "type": "Feature",
  "properties": {
    "iso:country":"GB",
    "wof:name":"TN20 6AY",
    "wof:placetype":"postalcode"
},
  "geometry": {"coordinates":[0.2626562050934,51.0196859892834],"type":"Point"}
}