{
  "type": "Feature",
  "properties": {
    "date:inception_lower": "2019-06-01",
    "date:inception_upper": "2019-06-01",
    "iso:country": "GB",
    "wof:name": "PL13 2FF",
    "wof:placetype": "postalcode"
  },
  "geometry": {"coordinates":[-4.526687,50.371929],"type":"Point"}
}
