{
  "type": "Feature",
  "properties": {
    "iso:country":"GB",
    "wof:name":"SE1 7EH",
    "wof:placetype":"postalcode"
},
  "geometry": {"coordinates":[-0.1189050372157,51.49795853139872],"type":"Point"}
}