{
  "type": "Feature",
  "properties": {
    "date:inception_lower": "1980-01-01",
    "date:inception_upper": "1980-01-01",
    "iso:country": "GB",
    "wof:name": "SE1 7EH",
    "wof:placetype": "postalcode"
  },
  "geometry": {"coordinates":[-0.118905,51.497959],"type":"Point"}
}
