{
  "type": "Feature",
  "properties": {
    "iso:country": "GB",
    "wof:name": "GL54 2FL",
    "wof:placetype": "postalcode"
  },
  "geometry": {"coordinates":[-1.702772,51.873183],"type":"Point"}
}
