{
  "type": "Feature",
  "properties": {
    "iso:country":"GB",
    "wof:name":"SE17 2HR",
    "wof:placetype":"postalcode"
},
  "geometry": {"coordinates":[-0.08838891456281,51.48525312014833],"type":"Point"}
}