{
  "type": "Feature",
  "properties": {
    "iso:country": "GB",
    "wof:name": "AL4 8BG",
    "wof:placetype": "postalcode"
  },
  "geometry": {"coordinates":[-0.291307,51.811851],"type":"Point"}
}
