{
  "type": "Feature",
  "properties": {
    "date:inception_lower":"1981-06-01",
    "date:inception_upper":"1981-06-30",
    "iso:country":"GB",
    "wof:name":"AL4 8BG",
    "wof:placetype":"postalcode"
},
  "geometry": {"coordinates":[-0.291307,51.811851],"type":"Point"}
}