{
  "type": "Feature",
  "properties": {
    "iso:country":"GB",
    "wof:name":"AL4 8BG",
    "wof:placetype":"postalcode"
},
  "geometry": {"coordinates":[-0.29130654469202,51.81185099097527],"type":"Point"}
}