{
  "type": "Feature",
  "properties": {
    "date:inception_lower": "2008-10-01",
    "date:inception_upper": "2008-10-01",
    "iso:country": "GB",
    "wof:name": "EX35 6BJ",
    "wof:placetype": "postalcode"
  },
  "geometry": {"coordinates":[-3.836652,51.22909],"type":"Point"}
}
