{
  "type": "Feature",
  "properties": {
    "iso:country": "GB",
    "wof:name": "EX35 6BJ",
    "wof:placetype": "postalcode"
  },
  "geometry": {"coordinates":[-3.836652,51.22909],"type":"Point"}
}
