{
  "type": "Feature",
  "properties": {
    "iso:country":"GB",
    "wof:name":"EX35 6BJ",
    "wof:placetype":"postalcode"
},
  "geometry": {"coordinates":[-3.83665250446078,51.22908983239862],"type":"Point"}
}