{
  "type": "Feature",
  "properties": {
    "iso:country":"GB",
    "wof:name":"CM9 6XF",
    "wof:placetype":"postalcode"
},
  "geometry": {"coordinates":[0.67795957684717,51.72287139970175],"type":"Point"}
}