{
  "type": "Feature",
  "properties": {
    "iso:country":"GB",
    "wof:name":"CF44 8NE",
    "wof:placetype":"postalcode"
},
  "geometry": {"coordinates":[-3.45706895178833,51.72098001294526],"type":"Point"}
}