{
  "type": "Feature",
  "properties": {
    "date:inception_lower": "1980-01-01",
    "date:inception_upper": "1980-01-01",
    "iso:country": "GB",
    "wof:name": "CF44 8NE",
    "wof:placetype": "postalcode"
  },
  "geometry": {"coordinates":[-3.457069,51.72098],"type":"Point"}
}
