{
  "type": "Feature",
  "properties": {
    "date:inception_lower": "1980-01-01",
    "date:inception_upper": "1980-01-01",
    "iso:country": "GB",
    "wof:name": "E14 7LS",
    "wof:placetype": "postalcode"
  },
  "geometry": {"coordinates":[-0.03886,51.513679],"type":"Point"}
}
