{
  "type": "Feature",
  "properties": {
    "iso:country":"GB",
    "wof:name":"E14 7LS",
    "wof:placetype":"postalcode"
},
  "geometry": {"coordinates":[-0.03886017658268,51.51367928939256],"type":"Point"}
}