{
  "type": "Feature",
  "properties": {
    "iso:country":"GB",
    "wof:name":"WA4 2QP",
    "wof:placetype":"postalcode"
},
  "geometry": {"coordinates":[-2.54134232514553,53.37813735641699],"type":"Point"}
}