{
  "type": "Feature",
  "properties": {
    "iso:country":"GB",
    "wof:name":"HR5 3HG",
    "wof:placetype":"postalcode"
},
  "geometry": {"coordinates":[-3.03288182302735,52.17960781016228],"type":"Point"}
}