{
  "type": "Feature",
  "properties": {
    "date:inception_lower": "1980-01-01",
    "date:inception_upper": "1980-01-01",
    "iso:country": "GB",
    "wof:name": "HR5 3HG",
    "wof:placetype": "postalcode"
  },
  "geometry": {"coordinates":[-3.031595,52.178873],"type":"Point"}
}
