{
  "type": "Feature",
  "properties": {
    "iso:country": "GB",
    "wof:name": "YO19 5XG",
    "wof:placetype": "postalcode"
  },
  "geometry": {"coordinates":[-0.996682,53.983254],"type":"Point"}
}
