{
  "type": "Feature",
  "properties": {
    "iso:country":"GB",
    "wof:name":"UB10 9HY",
    "wof:placetype":"postalcode"
},
  "geometry": {"coordinates":[-0.44643141738553,51.54205915363569],"type":"Point"}
}