{
  "type": "Feature",
  "properties": {
    "iso:country":"GB",
    "wof:name":"GU1 3PA",
    "wof:placetype":"postalcode"
},
  "geometry": {"coordinates":[-0.55946009574274,51.23813316206911],"type":"Point"}
}