{
  "type": "Feature",
  "properties": {
    "iso:country":"GB",
    "wof:name":"LL65 1UN",
    "wof:placetype":"postalcode"
},
  "geometry": {"coordinates":[-4.63350474145036,53.31004565290837],"type":"Point"}
}