{
  "type": "Feature",
  "properties": {
    "iso:country":"GB",
    "wof:name":"SL1 6LT",
    "wof:placetype":"postalcode"
},
  "geometry": {"coordinates":[-0.64423851385098,51.52405466392134],"type":"Point"}
}