{
  "type": "Feature",
  "properties": {
    "date:inception_lower": "1980-01-01",
    "date:inception_upper": "1980-01-01",
    "iso:country": "GB",
    "wof:name": "SL1 6LT",
    "wof:placetype": "postalcode"
  },
  "geometry": {"coordinates":[-0.644238,51.524055],"type":"Point"}
}
