{
  "type": "Feature",
  "properties": {
    "iso:country":"GB",
    "wof:name":"SE16 2DN",
    "wof:placetype":"postalcode"
},
  "geometry": {"coordinates":[-0.05706045543194,51.49205820592431],"type":"Point"}
}