{
  "type": "Feature",
  "properties": {
    "iso:country":"GB",
    "wof:name":"SO41 8DF",
    "wof:placetype":"postalcode"
},
  "geometry": {"coordinates":[-1.55169851078666,50.75158787842332],"type":"Point"}
}