{
  "type": "Feature",
  "properties": {
    "iso:country":"GB",
    "wof:name":"SO41 0FQ",
    "wof:placetype":"postalcode"
},
  "geometry": {"coordinates":[-1.62624219438218,50.76101394090344],"type":"Point"}
}