{
  "type": "Feature",
  "properties": {
    "date:inception_lower": "1990-02-01",
    "date:inception_upper": "1990-02-01",
    "iso:country": "GB",
    "wof:name": "SO41 0FQ",
    "wof:placetype": "postalcode"
  },
  "geometry": {"coordinates":[-1.626242,50.761014],"type":"Point"}
}
