{
  "type": "Feature",
  "properties": {
    "iso:country":"GB",
    "wof:name":"SA44 5BB",
    "wof:placetype":"postalcode"
},
  "geometry": {"coordinates":[-4.35799463310042,52.02424853672073],"type":"Point"}
}