{
  "type": "Feature",
  "properties": {
    "iso:country": "GB",
    "wof:name": "OX2 6NB",
    "wof:placetype": "postalcode"
  },
  "geometry": {"coordinates":[-1.261951,51.76256],"type":"Point"}
}
