{
  "type": "Feature",
  "properties": {
    "iso:country": "GB",
    "wof:name": "PA13 4AH",
    "wof:placetype": "postalcode"
  },
  "geometry": {"coordinates":[-4.625926,55.89361],"type":"Point"}
}
