{
  "type": "Feature",
  "properties": {
    "date:inception_lower":"1980-01-01",
    "date:inception_upper":"1980-01-31",
    "iso:country":"GB",
    "wof:name":"G76 0DN",
    "wof:placetype":"postalcode"
},
  "geometry": {"coordinates":[-4.278609,55.750807],"type":"Point"}
}