{
  "type": "Feature",
  "properties": {
    "iso:country":"GB",
    "wof:name":"G76 0DN",
    "wof:placetype":"postalcode"
},
  "geometry": {"coordinates":[-4.2786092708348,55.75080694694964],"type":"Point"}
}