{
  "type": "Feature",
  "properties": {
    "date:inception_lower": "1980-01-01",
    "date:inception_upper": "1980-01-01",
    "iso:country": "GB",
    "wof:name": "G76 0DN",
    "wof:placetype": "postalcode"
  },
  "geometry": {"coordinates":[-4.278821,55.750574],"type":"Point"}
}
