{
  "type": "Feature",
  "properties": {
    "iso:country": "GB",
    "wof:name": "DA5 2BY",
    "wof:placetype": "postalcode"
  },
  "geometry": {"coordinates":[0.165816,51.430454],"type":"Point"}
}
