{
  "type": "Feature",
  "properties": {
    "iso:country":"GB",
    "wof:name":"SL6 9PH",
    "wof:placetype":"postalcode"
},
  "geometry": {"coordinates":[-0.74803938520159,51.55711140712877],"type":"Point"}
}