{
  "type": "Feature",
  "properties": {
    "iso:country": "GB",
    "wof:name": "TN27 9JJ",
    "wof:placetype": "postalcode"
  },
  "geometry": {"coordinates":[0.624028,51.152002],"type":"Point"}
}
