{
  "type": "Feature",
  "properties": {
    "iso:country":"GB",
    "wof:name":"CW6 9UB",
    "wof:placetype":"postalcode"
},
  "geometry": {"coordinates":[-2.71437149435126,53.13215154649944],"type":"Point"}
}