{
  "type": "Feature",
  "properties": {
    "iso:country":"GB",
    "wof:name":"SG2 9PB",
    "wof:placetype":"postalcode"
},
  "geometry": {"coordinates":[-0.16169142483155,51.88976315004842],"type":"Point"}
}