{
  "type": "Feature",
  "properties": {
    "iso:country":"GB",
    "wof:name":"NE61 5EL",
    "wof:placetype":"postalcode"
},
  "geometry": {"coordinates":[-1.60048438059199,55.27217364085607],"type":"Point"}
}