{
  "type": "Feature",
  "properties": {
    "iso:country": "GB",
    "wof:name": "NE61 5EL",
    "wof:placetype": "postalcode"
  },
  "geometry": {"coordinates":[-1.600499,55.272177],"type":"Point"}
}
