{
  "type": "Feature",
  "properties": {
    "iso:country":"GB",
    "wof:name":"LS7 2HZ",
    "wof:placetype":"postalcode"
},
  "geometry": {"coordinates":[-1.54435913791389,53.81455787932051],"type":"Point"}
}