{
  "type": "Feature",
  "properties": {
    "iso:country":"GB",
    "wof:name":"M21 9ER",
    "wof:placetype":"postalcode"
},
  "geometry": {"coordinates":[-2.28024599651877,53.43946652286363],"type":"Point"}
}