{
  "type": "Feature",
  "properties": {
    "iso:country":"GB",
    "wof:name":"NG3 1NS",
    "wof:placetype":"postalcode"
},
  "geometry": {"coordinates":[-1.14163660873342,52.96048690096984],"type":"Point"}
}