{
  "type": "Feature",
  "properties": {
    "iso:country":"GB",
    "wof:name":"E6 6HG",
    "wof:placetype":"postalcode"
},
  "geometry": {"coordinates":[0.06312163933432,51.52418673237894],"type":"Point"}
}