{
  "type": "Feature",
  "properties": {
    "iso:country": "GB",
    "wof:name": "W10 4EF",
    "wof:placetype": "postalcode"
  },
  "geometry": {"coordinates":[-0.213762,51.531113],"type":"Point"}
}
