{
  "type": "Feature",
  "properties": {
    "iso:country":"GB",
    "wof:name":"W10 4EF",
    "wof:placetype":"postalcode"
},
  "geometry": {"coordinates":[-0.21376196841344,51.5311129752717],"type":"Point"}
}