{
  "type": "Feature",
  "properties": {
    "iso:country": "GB",
    "wof:name": "PE26 1DF",
    "wof:placetype": "postalcode"
  },
  "geometry": {"coordinates":[-0.099049,52.446053],"type":"Point"}
}
