{
  "type": "Feature",
  "properties": {
    "iso:country":"GB",
    "wof:name":"PE26 1DF",
    "wof:placetype":"postalcode"
},
  "geometry": {"coordinates":[-0.09904948509868,52.44605275114108],"type":"Point"}
}