{
  "type": "Feature",
  "properties": {
    "iso:country": "GB",
    "wof:name": "BL4 7LX",
    "wof:placetype": "postalcode"
  },
  "geometry": {"coordinates":[-2.404022,53.554243],"type":"Point"}
}
