{
  "type": "Feature",
  "properties": {
    "iso:country":"GB",
    "wof:name":"NN8 3EQ",
    "wof:placetype":"postalcode"
},
  "geometry": {"coordinates":[-0.72092284180128,52.29891019010312],"type":"Point"}
}