{
  "type": "Feature",
  "properties": {
    "iso:country":"GB",
    "wof:name":"ST19 5GA",
    "wof:placetype":"postalcode"
},
  "geometry": {"coordinates":[-2.10954354759844,52.72632099927795],"type":"Point"}
}