{
  "type": "Feature",
  "properties": {
    "date:inception_lower": "2010-03-01",
    "date:inception_upper": "2010-03-01",
    "iso:country": "GB",
    "wof:name": "ST19 5GA",
    "wof:placetype": "postalcode"
  },
  "geometry": {"coordinates":[-2.109544,52.726321],"type":"Point"}
}
