{
  "type": "Feature",
  "properties": {
    "date:inception_lower":"1980-01-01",
    "date:inception_upper":"1980-01-31",
    "iso:country":"GB",
    "wof:name":"GU7 1HB",
    "wof:placetype":"postalcode"
},
  "geometry": {"coordinates":[-0.617756,51.185313],"type":"Point"}
}