{
  "type": "Feature",
  "properties": {
    "iso:country":"GB",
    "wof:name":"GU7 1HB",
    "wof:placetype":"postalcode"
},
  "geometry": {"coordinates":[-0.61775562703578,51.18531289666517],"type":"Point"}
}