{
  "type": "Feature",
  "properties": {
    "date:inception_lower": "1980-01-01",
    "date:inception_upper": "1980-01-01",
    "iso:country": "GB",
    "wof:name": "OX12 0HJ",
    "wof:placetype": "postalcode"
  },
  "geometry": {"coordinates":[-1.39778,51.636811],"type":"Point"}
}
