{
  "type": "Feature",
  "properties": {
    "iso:country":"GB",
    "wof:name":"EN6 4LJ",
    "wof:placetype":"postalcode"
},
  "geometry": {"coordinates":[-0.11581600188807,51.70566066245351],"type":"Point"}
}