{
  "type": "Feature",
  "properties": {
    "date:inception_lower": "1980-01-01",
    "date:inception_upper": "1980-01-01",
    "iso:country": "GB",
    "wof:name": "EN6 4LJ",
    "wof:placetype": "postalcode"
  },
  "geometry": {"coordinates":[-0.115762,51.705654],"type":"Point"}
}
