{
  "type": "Feature",
  "properties": {
    "iso:country":"GB",
    "wof:name":"TR16 5EJ",
    "wof:placetype":"postalcode"
},
  "geometry": {"coordinates":[-5.21097363640011,50.25153181249902],"type":"Point"}
}