{
  "type": "Feature",
  "properties": {
    "iso:country": "GB",
    "wof:name": "CO2 7QP",
    "wof:placetype": "postalcode"
  },
  "geometry": {"coordinates":[0.905094,51.879422],"type":"Point"}
}
