{
  "type": "Feature",
  "properties": {
    "date:inception_lower":"2006-04-01",
    "date:inception_upper":"2006-04-30",
    "iso:country":"GB",
    "wof:name":"CO2 7QP",
    "wof:placetype":"postalcode"
},
  "geometry": {"coordinates":[0.905094,51.879422],"type":"Point"}
}