{
  "type": "Feature",
  "properties": {
    "iso:country":"GB",
    "wof:name":"PO1 3FS",
    "wof:placetype":"postalcode"
},
  "geometry": {"coordinates":[-1.10348492638284,50.79543445868251],"type":"Point"}
}