{
  "type": "Feature",
  "properties": {
    "date:inception_lower": "2007-05-01",
    "date:inception_upper": "2007-05-01",
    "iso:country": "GB",
    "wof:name": "PO1 3FS",
    "wof:placetype": "postalcode"
  },
  "geometry": {"coordinates":[-1.103485,50.795434],"type":"Point"}
}
