{
  "type": "Feature",
  "properties": {
    "date:inception_lower": "1980-01-01",
    "date:inception_upper": "1980-01-01",
    "iso:country": "GB",
    "wof:name": "WV5 9BB",
    "wof:placetype": "postalcode"
  },
  "geometry": {"coordinates":[-2.191174,52.543501],"type":"Point"}
}
