{
  "type": "Feature",
  "properties": {
    "iso:country":"GB",
    "wof:name":"WV5 9BB",
    "wof:placetype":"postalcode"
},
  "geometry": {"coordinates":[-2.19117415223935,52.54350097512901],"type":"Point"}
}