{
  "type": "Feature",
  "properties": {
    "date:inception_lower":"2011-01-01",
    "date:inception_upper":"2011-01-31",
    "iso:country":"GB",
    "wof:name":"WD4 8RN",
    "wof:placetype":"postalcode"
},
  "geometry": {"coordinates":[-0.444611,51.69088],"type":"Point"}
}