{
  "type": "Feature",
  "properties": {
    "iso:country": "GB",
    "wof:name": "CW5 7TE",
    "wof:placetype": "postalcode"
  },
  "geometry": {"coordinates":[-2.478449,53.061357],"type":"Point"}
}
