{
  "type": "Feature",
  "properties": {
    "iso:country":"GB",
    "wof:name":"SW15 3QW",
    "wof:placetype":"postalcode"
},
  "geometry": {"coordinates":[-0.25882843649394,51.42794603270148],"type":"Point"}
}