{
  "type": "Feature",
  "properties": {
    "date:inception_lower": "1980-01-01",
    "date:inception_upper": "1980-01-01",
    "iso:country": "GB",
    "wof:name": "SW15 3QW",
    "wof:placetype": "postalcode"
  },
  "geometry": {"coordinates":[-0.258828,51.427946],"type":"Point"}
}
