{
  "type": "Feature",
  "properties": {
    "date:inception_lower": "2024-01-01",
    "date:inception_upper": "2024-01-01",
    "iso:country": "GB",
    "wof:name": "KT3 4QG",
    "wof:placetype": "postalcode"
  },
  "geometry": {"coordinates":[-0.256843,51.404662],"type":"Point"}
}
