{
  "type": "Feature",
  "properties": {
    "date:inception_lower": "1980-01-01",
    "date:inception_upper": "1980-01-01",
    "iso:country": "GB",
    "wof:name": "G64 1LJ",
    "wof:placetype": "postalcode"
  },
  "geometry": {"coordinates":[-4.198216,55.901373],"type":"Point"}
}
