{
  "type": "Feature",
  "properties": {
    "iso:country": "GB",
    "wof:name": "TQ4 7EU",
    "wof:placetype": "postalcode"
  },
  "geometry": {"coordinates":[-3.584027,50.428819],"type":"Point"}
}
