{
  "type": "Feature",
  "properties": {
    "iso:country":"GB",
    "wof:name":"NG11 6HS",
    "wof:placetype":"postalcode"
},
  "geometry": {"coordinates":[-1.15104255606374,52.88913247974554],"type":"Point"}
}