{
  "type": "Feature",
  "properties": {
    "iso:country": "GB",
    "wof:name": "NG11 6HS",
    "wof:placetype": "postalcode"
  },
  "geometry": {"coordinates":[-1.151043,52.889132],"type":"Point"}
}
