{
  "type": "Feature",
  "properties": {
    "date:inception_lower":"1980-01-01",
    "date:inception_upper":"1980-01-31",
    "iso:country":"GB",
    "wof:name":"NG11 6HS",
    "wof:placetype":"postalcode"
},
  "geometry": {"coordinates":[-1.151043,52.889132],"type":"Point"}
}