{
  "type": "Feature",
  "properties": {
    "iso:country":"GB",
    "wof:name":"HP6 6AJ",
    "wof:placetype":"postalcode"
},
  "geometry": {"coordinates":[-0.6023654409832,51.67781065340009],"type":"Point"}
}