{
  "type": "Feature",
  "properties": {
    "iso:country": "GB",
    "wof:name": "LS2 7JQ",
    "wof:placetype": "postalcode"
  },
  "geometry": {"coordinates":[-1.533267,53.802678],"type":"Point"}
}
