{
  "type": "Feature",
  "properties": {
    "date:inception_lower": "2016-02-01",
    "date:inception_upper": "2016-02-01",
    "iso:country": "GB",
    "wof:name": "NW8 7EF",
    "wof:placetype": "postalcode"
  },
  "geometry": {"coordinates":[-0.164385,51.536504],"type":"Point"}
}
