{
  "type": "Feature",
  "properties": {
    "iso:country": "GB",
    "wof:name": "TN4 9GD",
    "wof:placetype": "postalcode"
  },
  "geometry": {"coordinates":[0.260145,51.139745],"type":"Point"}
}
