{
  "type": "Feature",
  "properties": {
    "iso:country":"GB",
    "wof:name":"TN4 9GD",
    "wof:placetype":"postalcode"
},
  "geometry": {"coordinates":[0.26014463795725,51.13974496874849],"type":"Point"}
}