{
  "type": "Feature",
  "properties": {
    "iso:country":"GB",
    "wof:name":"TR17 0HJ",
    "wof:placetype":"postalcode"
},
  "geometry": {"coordinates":[-5.46374929493244,50.13544332006272],"type":"Point"}
}