{
  "type": "Feature",
  "properties": {
    "iso:country": "GB",
    "wof:name": "E11 4JR",
    "wof:placetype": "postalcode"
  },
  "geometry": {"coordinates":[0.003087,51.553905],"type":"Point"}
}
