{
  "type": "Feature",
  "properties": {
    "iso:country":"GB",
    "wof:name":"E11 4JR",
    "wof:placetype":"postalcode"
},
  "geometry": {"coordinates":[0.00308680783154,51.55390491067291],"type":"Point"}
}