{
  "type": "Feature",
  "properties": {
    "iso:country":"GB",
    "wof:name":"SA62 3HY",
    "wof:placetype":"postalcode"
},
  "geometry": {"coordinates":[-5.09537558955649,51.78392845058231],"type":"Point"}
}