{
  "type": "Feature",
  "properties": {
    "iso:country": "GB",
    "wof:name": "SA62 3HY",
    "wof:placetype": "postalcode"
  },
  "geometry": {"coordinates":[-5.095376,51.783928],"type":"Point"}
}
