{
  "type": "Feature",
  "properties": {
    "date:inception_lower":"2015-08-01",
    "date:inception_upper":"2015-08-31",
    "iso:country":"GB",
    "wof:name":"M5 3LN",
    "wof:placetype":"postalcode"
},
  "geometry": {"coordinates":[-2.28113,53.470753],"type":"Point"}
}