{
  "type": "Feature",
  "properties": {
    "iso:country":"GB",
    "wof:name":"M5 3LN",
    "wof:placetype":"postalcode"
},
  "geometry": {"coordinates":[-2.28113016147269,53.47075342882317],"type":"Point"}
}