{
  "type": "Feature",
  "properties": {
    "date:inception_lower": "1990-02-01",
    "date:inception_upper": "1990-02-01",
    "iso:country": "GB",
    "wof:name": "DE14 3TN",
    "wof:placetype": "postalcode"
  },
  "geometry": {"coordinates":[-1.633691,52.800717],"type":"Point"}
}
