{
  "type": "Feature",
  "properties": {
    "iso:country":"GB",
    "wof:name":"DE14 3TN",
    "wof:placetype":"postalcode"
},
  "geometry": {"coordinates":[-1.63369122126365,52.80071705629872],"type":"Point"}
}