{
  "type": "Feature",
  "properties": {
    "iso:country":"GB",
    "wof:name":"EN11 9QQ",
    "wof:placetype":"postalcode"
},
  "geometry": {"coordinates":[-0.00922753111951,51.77831439525173],"type":"Point"}
}