{
  "type": "Feature",
  "properties": {
    "date:inception_lower": "1980-01-01",
    "date:inception_upper": "1980-01-01",
    "iso:country": "GB",
    "wof:name": "EN11 9QQ",
    "wof:placetype": "postalcode"
  },
  "geometry": {"coordinates":[-0.009227,51.778314],"type":"Point"}
}
