{
  "type": "Feature",
  "properties": {
    "iso:country":"GB",
    "wof:name":"DE22 2TP",
    "wof:placetype":"postalcode"
},
  "geometry": {"coordinates":[-1.50624538728934,52.94399684169009],"type":"Point"}
}