{
  "type": "Feature",
  "properties": {
    "iso:country":"GB",
    "wof:name":"M46 0EP",
    "wof:placetype":"postalcode"
},
  "geometry": {"coordinates":[-2.49136790926883,53.52484940376093],"type":"Point"}
}