{
  "type": "Feature",
  "properties": {
    "iso:country":"GB",
    "wof:name":"PA20 0LX",
    "wof:placetype":"postalcode"
},
  "geometry": {"coordinates":[-5.0841292393934,55.85999831247837],"type":"Point"}
}