{
  "type": "Feature",
  "properties": {
    "date:inception_lower": "2023-04-01",
    "date:inception_upper": "2023-04-01",
    "iso:country": "GB",
    "wof:name": "SO51 6GZ",
    "wof:placetype": "postalcode"
  },
  "geometry": {"coordinates":[-1.544229,50.988136],"type":"Point"}
}
