{
  "type": "Feature",
  "properties": {
    "iso:country":"GB",
    "wof:name":"CT9 4BD",
    "wof:placetype":"postalcode"
},
  "geometry": {"coordinates":[1.38578841074805,51.37821095600988],"type":"Point"}
}