{
  "type": "Feature",
  "properties": {
    "iso:country":"GB",
    "wof:name":"N17 6YD",
    "wof:placetype":"postalcode"
},
  "geometry": {"coordinates":[-0.07565791937126,51.5922180609914],"type":"Point"}
}