{
  "type": "Feature",
  "properties": {
    "date:inception_lower":"1990-07-01",
    "date:inception_upper":"1990-07-31",
    "iso:country":"GB",
    "wof:name":"TQ14 9UE",
    "wof:placetype":"postalcode"
},
  "geometry": {"coordinates":[-3.503271,50.551988],"type":"Point"}
}