{
  "type": "Feature",
  "properties": {
    "iso:country":"GB",
    "wof:name":"NE24 3TR",
    "wof:placetype":"postalcode"
},
  "geometry": {"coordinates":[-1.51486988109907,55.11389016492556],"type":"Point"}
}