{
  "type": "Feature",
  "properties": {
    "iso:country":"GB",
    "wof:name":"B96 6NS",
    "wof:placetype":"postalcode"
},
  "geometry": {"coordinates":[-1.92151836826372,52.24860218812522],"type":"Point"}
}