{
  "type": "Feature",
  "properties": {
    "date:inception_lower": "1980-01-01",
    "date:inception_upper": "1980-01-01",
    "iso:country": "GB",
    "wof:name": "B96 6NS",
    "wof:placetype": "postalcode"
  },
  "geometry": {"coordinates":[-1.921518,52.248602],"type":"Point"}
}
