{
  "type": "Feature",
  "properties": {
    "iso:country":"GB",
    "wof:name":"CF45 3RR",
    "wof:placetype":"postalcode"
},
  "geometry": {"coordinates":[-3.38248719750211,51.68318090849009],"type":"Point"}
}