{
  "type": "Feature",
  "properties": {
    "iso:country": "GB",
    "wof:name": "CF45 3RR",
    "wof:placetype": "postalcode"
  },
  "geometry": {"coordinates":[-3.382487,51.683181],"type":"Point"}
}
