{
  "type": "Feature",
  "properties": {
    "date:inception_lower": "1983-01-01",
    "date:inception_upper": "1983-01-01",
    "iso:country": "GB",
    "wof:name": "LD8 2TU",
    "wof:placetype": "postalcode"
  },
  "geometry": {"coordinates":[-3.151478,52.241275],"type":"Point"}
}
