{
  "type": "Feature",
  "properties": {
    "iso:country":"GB",
    "wof:name":"LD8 2TU",
    "wof:placetype":"postalcode"
},
  "geometry": {"coordinates":[-3.15147842934678,52.24127452802959],"type":"Point"}
}