{
  "type": "Feature",
  "properties": {
    "date:inception_lower":"2016-01-01",
    "date:inception_upper":"2016-01-31",
    "iso:country":"GB",
    "wof:name":"S63 9GP",
    "wof:placetype":"postalcode"
},
  "geometry": {"coordinates":[-1.292592,53.531473],"type":"Point"}
}