{
  "type": "Feature",
  "properties": {
    "iso:country": "GB",
    "wof:name": "S63 9GP",
    "wof:placetype": "postalcode"
  },
  "geometry": {"coordinates":[-1.292592,53.531473],"type":"Point"}
}
