{
  "type": "Feature",
  "properties": {
    "iso:country":"GB",
    "wof:name":"S63 9GP",
    "wof:placetype":"postalcode"
},
  "geometry": {"coordinates":[-1.29293651303697,53.53151923767557],"type":"Point"}
}