{
  "type": "Feature",
  "properties": {
    "iso:country": "GB",
    "wof:name": "NE65 8XD",
    "wof:placetype": "postalcode"
  },
  "geometry": {"coordinates":[-1.767614,55.261886],"type":"Point"}
}
