{
  "type": "Feature",
  "properties": {
    "iso:country":"GB",
    "wof:name":"LS25 5NZ",
    "wof:placetype":"postalcode"
},
  "geometry": {"coordinates":[-1.25397587285145,53.77881405893672],"type":"Point"}
}