{
  "type": "Feature",
  "properties": {
    "date:inception_lower": "1980-01-01",
    "date:inception_upper": "1980-01-01",
    "iso:country": "GB",
    "wof:name": "S81 9AL",
    "wof:placetype": "postalcode"
  },
  "geometry": {"coordinates":[-1.117561,53.357454],"type":"Point"}
}
