{
  "type": "Feature",
  "properties": {
    "iso:country": "GB",
    "wof:name": "S81 9AL",
    "wof:placetype": "postalcode"
  },
  "geometry": {"coordinates":[-1.117561,53.357454],"type":"Point"}
}
