{
  "type": "Feature",
  "properties": {
    "iso:country":"GB",
    "wof:name":"S81 9AL",
    "wof:placetype":"postalcode"
},
  "geometry": {"coordinates":[-1.11756106178627,53.35745444996352],"type":"Point"}
}