{
  "type": "Feature",
  "properties": {
    "iso:country":"GB",
    "wof:name":"CA28 7RJ",
    "wof:placetype":"postalcode"
},
  "geometry": {"coordinates":[-3.58548526418311,54.54480703343544],"type":"Point"}
}