{
  "type": "Feature",
  "properties": {
    "date:inception_lower":"1999-06-01",
    "date:inception_upper":"1999-06-30",
    "iso:country":"GB",
    "wof:name":"E3 2YD",
    "wof:placetype":"postalcode"
},
  "geometry": {"coordinates":[-0.024379,51.532582],"type":"Point"}
}