{
  "type": "Feature",
  "properties": {
    "iso:country":"GB",
    "wof:name":"E3 2YD",
    "wof:placetype":"postalcode"
},
  "geometry": {"coordinates":[-0.02437926900825,51.53258156388961],"type":"Point"}
}