{
  "type": "Feature",
  "properties": {
    "date:inception_lower":"2003-08-01",
    "date:inception_upper":"2003-08-31",
    "iso:country":"GB",
    "wof:name":"KA23 9GB",
    "wof:placetype":"postalcode"
},
  "geometry": {"coordinates":[-4.847101,55.694005],"type":"Point"}
}