{
  "type": "Feature",
  "properties": {
    "iso:country":"GB",
    "wof:name":"KA23 9GB",
    "wof:placetype":"postalcode"
},
  "geometry": {"coordinates":[-4.84710084741957,55.69400517810263],"type":"Point"}
}