{
  "type": "Feature",
  "properties": {
    "iso:country": "GB",
    "wof:name": "KA23 9GB",
    "wof:placetype": "postalcode"
  },
  "geometry": {"coordinates":[-4.847101,55.694005],"type":"Point"}
}
