{
  "type": "Feature",
  "properties": {
    "iso:country":"GB",
    "wof:name":"E18 1EP",
    "wof:placetype":"postalcode"
},
  "geometry": {"coordinates":[0.03583274013724,51.59687458444346],"type":"Point"}
}