{
  "type": "Feature",
  "properties": {
    "iso:country":"GB",
    "wof:name":"TN2 4NG",
    "wof:placetype":"postalcode"
},
  "geometry": {"coordinates":[0.31303128467159,51.14470934932574],"type":"Point"}
}