{
  "type": "Feature",
  "properties": {
    "date:inception_lower": "1980-01-01",
    "date:inception_upper": "1980-01-01",
    "iso:country": "GB",
    "wof:name": "NR17 1NX",
    "wof:placetype": "postalcode"
  },
  "geometry": {"coordinates":[1.008754,52.47923],"type":"Point"}
}
