{
  "type": "Feature",
  "properties": {
    "iso:country": "GB",
    "wof:name": "NR17 1NX",
    "wof:placetype": "postalcode"
  },
  "geometry": {"coordinates":[1.008754,52.47923],"type":"Point"}
}
