{
  "type": "Feature",
  "properties": {
    "iso:country":"GB",
    "wof:name":"MK6 2BN",
    "wof:placetype":"postalcode"
},
  "geometry": {"coordinates":[-0.74507617235556,52.04005863465621],"type":"Point"}
}