{
  "type": "Feature",
  "properties": {
    "iso:country": "GB",
    "wof:name": "BD20 6PF",
    "wof:placetype": "postalcode"
  },
  "geometry": {"coordinates":[-1.949064,53.894433],"type":"Point"}
}
