{
  "type": "Feature",
  "properties": {
    "date:inception_lower":"1999-12-01",
    "date:inception_upper":"1999-12-31",
    "iso:country":"GB",
    "wof:name":"BD20 6PF",
    "wof:placetype":"postalcode"
},
  "geometry": {"coordinates":[-1.949064,53.894433],"type":"Point"}
}