{
  "type": "Feature",
  "properties": {
    "iso:country":"GB",
    "wof:name":"IP25 6EP",
    "wof:placetype":"postalcode"
},
  "geometry": {"coordinates":[0.82595362671571,52.57208139752053],"type":"Point"}
}