{
  "type": "Feature",
  "properties": {
    "date:inception_lower": "1980-01-01",
    "date:inception_upper": "1980-01-01",
    "iso:country": "GB",
    "wof:name": "FY6 8AR",
    "wof:placetype": "postalcode"
  },
  "geometry": {"coordinates":[-3.002093,53.840092],"type":"Point"}
}
