{
  "type": "Feature",
  "properties": {
    "iso:country":"GB",
    "wof:name":"FY6 8AR",
    "wof:placetype":"postalcode"
},
  "geometry": {"coordinates":[-3.00198191859787,53.84089655148595],"type":"Point"}
}