{
  "type": "Feature",
  "properties": {
    "date:inception_lower": "1980-01-01",
    "date:inception_upper": "1980-01-01",
    "iso:country": "GB",
    "wof:name": "EH3 6DS",
    "wof:placetype": "postalcode"
  },
  "geometry": {"coordinates":[-3.207246,55.955226],"type":"Point"}
}
