{
  "type": "Feature",
  "properties": {
    "iso:country":"GB",
    "wof:name":"GL11 4AT",
    "wof:placetype":"postalcode"
},
  "geometry": {"coordinates":[-2.34644477966343,51.67393997761018],"type":"Point"}
}