{
  "type": "Feature",
  "properties": {
    "iso:country":"GB",
    "wof:name":"PO12 2DJ",
    "wof:placetype":"postalcode"
},
  "geometry": {"coordinates":[-1.14346785605778,50.78151723014804],"type":"Point"}
}