{
  "type": "Feature",
  "properties": {
    "iso:country":"GB",
    "wof:name":"CW10 0HQ",
    "wof:placetype":"postalcode"
},
  "geometry": {"coordinates":[-2.44474922878332,53.15757297294289],"type":"Point"}
}