{
  "type": "Feature",
  "properties": {
    "iso:country": "GB",
    "wof:name": "HA9 6SL",
    "wof:placetype": "postalcode"
  },
  "geometry": {"coordinates":[-0.278876,51.54972],"type":"Point"}
}
