{
  "type": "Feature",
  "properties": {
    "iso:country":"GB",
    "wof:name":"B63 2TE",
    "wof:placetype":"postalcode"
},
  "geometry": {"coordinates":[-2.07602194204659,52.46356691747604],"type":"Point"}
}