{
  "type": "Feature",
  "properties": {
    "date:inception_lower":"2008-01-01",
    "date:inception_upper":"2008-01-31",
    "iso:country":"GB",
    "wof:name":"B63 2TE",
    "wof:placetype":"postalcode"
},
  "geometry": {"coordinates":[-2.076022,52.463567],"type":"Point"}
}