{
  "type": "Feature",
  "properties": {
    "iso:country": "GB",
    "wof:name": "B63 2TE",
    "wof:placetype": "postalcode"
  },
  "geometry": {"coordinates":[-2.076022,52.463567],"type":"Point"}
}
