{
  "type": "Feature",
  "properties": {
    "iso:country":"GB",
    "wof:name":"OL14 6UG",
    "wof:placetype":"postalcode"
},
  "geometry": {"coordinates":[-2.09372996448642,53.68438485353708],"type":"Point"}
}