{
  "type": "Feature",
  "properties": {
    "iso:country":"GB",
    "wof:name":"NW10 3JS",
    "wof:placetype":"postalcode"
},
  "geometry": {"coordinates":[-0.22126901468121,51.53640665756992],"type":"Point"}
}