{
  "type": "Feature",
  "properties": {
    "iso:country": "GB",
    "wof:name": "NW10 3JS",
    "wof:placetype": "postalcode"
  },
  "geometry": {"coordinates":[-0.221269,51.536407],"type":"Point"}
}
