{
  "type": "Feature",
  "properties": {
    "date:inception_lower":"1980-01-01",
    "date:inception_upper":"1980-01-31",
    "iso:country":"GB",
    "wof:name":"NW10 3JS",
    "wof:placetype":"postalcode"
},
  "geometry": {"coordinates":[-0.221269,51.536407],"type":"Point"}
}