{
  "type": "Feature",
  "properties": {
    "date:inception_lower": "2018-01-01",
    "date:inception_upper": "2018-01-01",
    "iso:country": "GB",
    "wof:name": "EX5 2FW",
    "wof:placetype": "postalcode"
  },
  "geometry": {"coordinates":[-3.427756,50.735133],"type":"Point"}
}
