{
  "type": "Feature",
  "properties": {
    "iso:country": "GB",
    "wof:name": "EX5 2FW",
    "wof:placetype": "postalcode"
  },
  "geometry": {"coordinates":[-3.427756,50.735133],"type":"Point"}
}
