{
  "type": "Feature",
  "properties": {
    "date:inception_lower": "1980-01-01",
    "date:inception_upper": "1980-01-01",
    "iso:country": "GB",
    "wof:name": "CA1 1SN",
    "wof:placetype": "postalcode"
  },
  "geometry": {"coordinates":[-2.929074,54.889891],"type":"Point"}
}
