{
  "type": "Feature",
  "properties": {
    "iso:country":"GB",
    "wof:name":"EX39 3LW",
    "wof:placetype":"postalcode"
},
  "geometry": {"coordinates":[-4.21446788584869,51.02166961819027],"type":"Point"}
}