{
  "type": "Feature",
  "properties": {
    "iso:country":"GB",
    "wof:name":"PE11 3JE",
    "wof:placetype":"postalcode"
},
  "geometry": {"coordinates":[-0.20261638823713,52.78062365537981],"type":"Point"}
}