{
  "type": "Feature",
  "properties": {
    "iso:country": "GB",
    "wof:name": "PE11 3JE",
    "wof:placetype": "postalcode"
  },
  "geometry": {"coordinates":[-0.202616,52.780624],"type":"Point"}
}
