{
  "type": "Feature",
  "properties": {
    "iso:country":"GB",
    "wof:name":"DL7 0TG",
    "wof:placetype":"postalcode"
},
  "geometry": {"coordinates":[-1.5456085822128,54.36299526106788],"type":"Point"}
}