{
  "type": "Feature",
  "properties": {
    "date:inception_lower": "1980-01-01",
    "date:inception_upper": "1980-01-01",
    "iso:country": "GB",
    "wof:name": "BD23 3EW",
    "wof:placetype": "postalcode"
  },
  "geometry": {"coordinates":[-2.04281,53.945914],"type":"Point"}
}
