{
  "type": "Feature",
  "properties": {
    "iso:country":"GB",
    "wof:name":"BD23 3EW",
    "wof:placetype":"postalcode"
},
  "geometry": {"coordinates":[-2.04280588643179,53.94589983395488],"type":"Point"}
}