{
  "type": "Feature",
  "properties": {
    "iso:country": "GB",
    "wof:name": "BD23 3EW",
    "wof:placetype": "postalcode"
  },
  "geometry": {"coordinates":[-2.042292,53.946022],"type":"Point"}
}
