{
  "type": "Feature",
  "properties": {
    "date:inception_lower": "1980-01-01",
    "date:inception_upper": "1980-01-01",
    "iso:country": "GB",
    "wof:name": "SA13 2SE",
    "wof:placetype": "postalcode"
  },
  "geometry": {"coordinates":[-3.715677,51.616752],"type":"Point"}
}
