{
  "type": "Feature",
  "properties": {
    "date:inception_lower": "1985-10-01",
    "date:inception_upper": "1985-10-01",
    "iso:country": "GB",
    "wof:name": "CV12 9JJ",
    "wof:placetype": "postalcode"
  },
  "geometry": {"coordinates":[-1.421207,52.476732],"type":"Point"}
}
