{
  "type": "Feature",
  "properties": {
    "iso:country":"GB",
    "wof:name":"CV12 9JJ",
    "wof:placetype":"postalcode"
},
  "geometry": {"coordinates":[-1.42120696228308,52.47673181413692],"type":"Point"}
}