{
  "type": "Feature",
  "properties": {
    "iso:country": "GB",
    "wof:name": "CO13 9FH",
    "wof:placetype": "postalcode"
  },
  "geometry": {"coordinates":[1.244727,51.828836],"type":"Point"}
}
