{
  "type": "Feature",
  "properties": {
    "iso:country": "GB",
    "wof:name": "KT22 9UA",
    "wof:placetype": "postalcode"
  },
  "geometry": {"coordinates":[-0.362796,51.293577],"type":"Point"}
}
