{
  "type": "Feature",
  "properties": {
    "iso:country":"GB",
    "wof:name":"BR7 6PX",
    "wof:placetype":"postalcode"
},
  "geometry": {"coordinates":[0.08951445033083,51.41509492588906],"type":"Point"}
}