{
  "type": "Feature",
  "properties": {
    "iso:country":"GB",
    "wof:name":"CW2 5LZ",
    "wof:placetype":"postalcode"
},
  "geometry": {"coordinates":[-2.40310367375496,53.06542165262387],"type":"Point"}
}