{
  "type": "Feature",
  "properties": {
    "iso:country":"GB",
    "wof:name":"TQ2 7GG",
    "wof:placetype":"postalcode"
},
  "geometry": {"coordinates":[-3.551390739785,50.49040663552042],"type":"Point"}
}