{
  "type": "Feature",
  "properties": {
    "iso:country":"GB",
    "wof:name":"EN5 5TJ",
    "wof:placetype":"postalcode"
},
  "geometry": {"coordinates":[-0.19955884619787,51.65566440799027],"type":"Point"}
}