{
  "type": "Feature",
  "properties": {
    "iso:country": "GB",
    "wof:name": "N4 2ZF",
    "wof:placetype": "postalcode"
  },
  "geometry": {"coordinates":[-0.093936,51.569166],"type":"Point"}
}
