{
  "type": "Feature",
  "properties": {
    "iso:country":"GB",
    "wof:name":"ME7 5XL",
    "wof:placetype":"postalcode"
},
  "geometry": {"coordinates":[0.54769314768122,51.38008132809406],"type":"Point"}
}