{
  "type": "Feature",
  "properties": {
    "date:inception_lower": "1980-01-01",
    "date:inception_upper": "1980-01-01",
    "iso:country": "GB",
    "wof:name": "ME7 5XL",
    "wof:placetype": "postalcode"
  },
  "geometry": {"coordinates":[0.547693,51.380081],"type":"Point"}
}
