{
  "type": "Feature",
  "properties": {
    "iso:country":"GB",
    "wof:name":"S63 9NE",
    "wof:placetype":"postalcode"
},
  "geometry": {"coordinates":[-1.30508386936079,53.53412519214665],"type":"Point"}
}