{
  "type": "Feature",
  "properties": {
    "date:inception_lower":"1980-01-01",
    "date:inception_upper":"1980-01-31",
    "iso:country":"GB",
    "wof:name":"S63 9NE",
    "wof:placetype":"postalcode"
},
  "geometry": {"coordinates":[-1.305084,53.534125],"type":"Point"}
}