{
  "type": "Feature",
  "properties": {
    "date:inception_lower": "1997-12-01",
    "date:inception_upper": "1997-12-01",
    "iso:country": "GB",
    "wof:name": "RG1 3AJ",
    "wof:placetype": "postalcode"
  },
  "geometry": {"coordinates":[-0.967427,51.454447],"type":"Point"}
}
