{
  "type": "Feature",
  "properties": {
    "iso:country":"GB",
    "wof:name":"ST17 9TF",
    "wof:placetype":"postalcode"
},
  "geometry": {"coordinates":[-2.12061107408647,52.78228812668339],"type":"Point"}
}