{
  "type": "Feature",
  "properties": {
    "date:inception_lower":"2010-12-01",
    "date:inception_upper":"2010-12-31",
    "iso:country":"GB",
    "wof:name":"ST17 9TF",
    "wof:placetype":"postalcode"
},
  "geometry": {"coordinates":[-2.120611,52.782288],"type":"Point"}
}