{
  "type": "Feature",
  "properties": {
    "iso:country": "GB",
    "wof:name": "ST17 9TF",
    "wof:placetype": "postalcode"
  },
  "geometry": {"coordinates":[-2.120611,52.782288],"type":"Point"}
}
