{
  "type": "Feature",
  "properties": {
    "date:inception_lower": "1980-01-01",
    "date:inception_upper": "1980-01-01",
    "iso:country": "GB",
    "wof:name": "L16 0JE",
    "wof:placetype": "postalcode"
  },
  "geometry": {"coordinates":[-2.886608,53.393429],"type":"Point"}
}
