{
  "type": "Feature",
  "properties": {
    "iso:country":"GB",
    "wof:name":"L16 0JE",
    "wof:placetype":"postalcode"
},
  "geometry": {"coordinates":[-2.88660833056855,53.39342919767364],"type":"Point"}
}