{
  "type": "Feature",
  "properties": {
    "iso:country": "GB",
    "wof:name": "BA14 9BZ",
    "wof:placetype": "postalcode"
  },
  "geometry": {"coordinates":[-2.226579,51.323601],"type":"Point"}
}
