{
  "type": "Feature",
  "properties": {
    "iso:country": "GB",
    "wof:name": "NE8 1AF",
    "wof:placetype": "postalcode"
  },
  "geometry": {"coordinates":[-1.614368,54.956017],"type":"Point"}
}
