{
  "type": "Feature",
  "properties": {
    "iso:country": "GB",
    "wof:name": "NE8 1AF",
    "wof:placetype": "postalcode"
  },
  "geometry": {"coordinates":[-1.683497,54.917646],"type":"Point"}
}
