{
  "type": "Feature",
  "properties": {
    "date:inception_lower": "2011-05-01",
    "date:inception_upper": "2011-05-01",
    "iso:country": "GB",
    "wof:name": "HD6 4EZ",
    "wof:placetype": "postalcode"
  },
  "geometry": {"coordinates":[-1.774144,53.722427],"type":"Point"}
}
