{
  "type": "Feature",
  "properties": {
    "iso:country":"GB",
    "wof:name":"DG9 7PA",
    "wof:placetype":"postalcode"
},
  "geometry": {"coordinates":[-5.02832422110127,54.90188730125786],"type":"Point"}
}