{
  "type": "Feature",
  "properties": {
    "iso:country": "GB",
    "wof:name": "NW6 7FA",
    "wof:placetype": "postalcode"
  },
  "geometry": {"coordinates":[-0.200992,51.544173],"type":"Point"}
}
