{
  "type": "Feature",
  "properties": {
    "date:inception_lower": "2015-02-01",
    "date:inception_upper": "2015-02-01",
    "iso:country": "GB",
    "wof:name": "NW6 7FA",
    "wof:placetype": "postalcode"
  },
  "geometry": {"coordinates":[-0.200992,51.544173],"type":"Point"}
}
