{
  "type": "Feature",
  "properties": {
    "iso:country":"GB",
    "wof:name":"NW6 7FA",
    "wof:placetype":"postalcode"
},
  "geometry": {"coordinates":[-0.2009921625419,51.54417264179693],"type":"Point"}
}