{
  "type": "Feature",
  "properties": {
    "iso:country":"GB",
    "wof:name":"NW11 6PR",
    "wof:placetype":"postalcode"
},
  "geometry": {"coordinates":[-0.18453128114701,51.57981669229551],"type":"Point"}
}