{
  "type": "Feature",
  "properties": {
    "iso:country":"GB",
    "wof:name":"LU1 1PH",
    "wof:placetype":"postalcode"
},
  "geometry": {"coordinates":[-0.43494302860115,51.88202556611899],"type":"Point"}
}