{
  "type": "Feature",
  "properties": {
    "iso:country": "GB",
    "wof:name": "LU1 1PH",
    "wof:placetype": "postalcode"
  },
  "geometry": {"coordinates":[-0.434943,51.882026],"type":"Point"}
}
