{
  "type": "Feature",
  "properties": {
    "date:inception_lower": "1980-01-01",
    "date:inception_upper": "1980-01-01",
    "iso:country": "GB",
    "wof:name": "TN9 2JL",
    "wof:placetype": "postalcode"
  },
  "geometry": {"coordinates":[0.276549,51.185777],"type":"Point"}
}
