{
  "type": "Feature",
  "properties": {
    "iso:country":"GB",
    "wof:name":"CV31 3PX",
    "wof:placetype":"postalcode"
},
  "geometry": {"coordinates":[-1.54218294080461,52.28669667008968],"type":"Point"}
}