{
  "type": "Feature",
  "properties": {
    "date:inception_lower": "1990-07-01",
    "date:inception_upper": "1990-07-01",
    "iso:country": "GB",
    "wof:name": "CR6 9BG",
    "wof:placetype": "postalcode"
  },
  "geometry": {"coordinates":[-0.073421,51.307401],"type":"Point"}
}
