{
  "type": "Feature",
  "properties": {
    "iso:country":"GB",
    "wof:name":"NW6 7YF",
    "wof:placetype":"postalcode"
},
  "geometry": {"coordinates":[-0.21291178704049,51.54398612359779],"type":"Point"}
}