{
  "type": "Feature",
  "properties": {
    "iso:country":"GB",
    "wof:name":"HD9 6HR",
    "wof:placetype":"postalcode"
},
  "geometry": {"coordinates":[-1.80168626559902,53.59851050249816],"type":"Point"}
}