{
  "type": "Feature",
  "properties": {
    "date:inception_lower": "2020-04-01",
    "date:inception_upper": "2020-04-01",
    "iso:country": "GB",
    "wof:name": "CB6 1GS",
    "wof:placetype": "postalcode"
  },
  "geometry": {"coordinates":[0.293089,52.450823],"type":"Point"}
}
