{
  "type": "Feature",
  "properties": {
    "date:inception_lower": "2013-07-01",
    "date:inception_upper": "2013-07-01",
    "iso:country": "GB",
    "wof:name": "BD20 6FA",
    "wof:placetype": "postalcode"
  },
  "geometry": {"coordinates":[-1.945331,53.897865],"type":"Point"}
}
