{
  "type": "Feature",
  "properties": {
    "iso:country":"GB",
    "wof:name":"B44 0RU",
    "wof:placetype":"postalcode"
},
  "geometry": {"coordinates":[-1.87605343854054,52.55328221768127],"type":"Point"}
}