{
  "type": "Feature",
  "properties": {
    "iso:country":"GB",
    "wof:name":"PH22 1SR",
    "wof:placetype":"postalcode"
},
  "geometry": {"coordinates":[-3.81630587588604,57.20028323372107],"type":"Point"}
}