{
  "type": "Feature",
  "properties": {
    "date:inception_lower": "1980-01-01",
    "date:inception_upper": "1980-01-01",
    "iso:country": "GB",
    "wof:name": "NE21 5SD",
    "wof:placetype": "postalcode"
  },
  "geometry": {"coordinates":[-1.701467,54.969094],"type":"Point"}
}
