{
  "type": "Feature",
  "properties": {
    "iso:country":"GB",
    "wof:name":"NE21 5SD",
    "wof:placetype":"postalcode"
},
  "geometry": {"coordinates":[-1.70146672191938,54.96909413963552],"type":"Point"}
}