{
  "type": "Feature",
  "properties": {
    "iso:country":"GB",
    "wof:name":"KT12 2BU",
    "wof:placetype":"postalcode"
},
  "geometry": {"coordinates":[-0.40918153496168,51.38808860066302],"type":"Point"}
}