{
  "type": "Feature",
  "properties": {
    "date:inception_lower": "1980-01-01",
    "date:inception_upper": "1980-01-01",
    "iso:country": "GB",
    "wof:name": "KT12 2BU",
    "wof:placetype": "postalcode"
  },
  "geometry": {"coordinates":[-0.409181,51.388089],"type":"Point"}
}
