{
  "type": "Feature",
  "properties": {
    "iso:country": "GB",
    "wof:name": "GL2 2JB",
    "wof:placetype": "postalcode"
  },
  "geometry": {"coordinates":[-2.259963,51.817686],"type":"Point"}
}
