{
  "type": "Feature",
  "properties": {
    "iso:country":"GB",
    "wof:name":"ME17 2PH",
    "wof:placetype":"postalcode"
},
  "geometry": {"coordinates":[0.7182756072612,51.2369296923689],"type":"Point"}
}