{
  "type": "Feature",
  "properties": {
    "iso:country": "GB",
    "wof:name": "G71 8RR",
    "wof:placetype": "postalcode"
  },
  "geometry": {"coordinates":[-4.064102,55.802015],"type":"Point"}
}
