{
  "type": "Feature",
  "properties": {
    "iso:country":"GB",
    "wof:name":"YO41 5LY",
    "wof:placetype":"postalcode"
},
  "geometry": {"coordinates":[-0.89521061333269,53.94861337623115],"type":"Point"}
}