{
  "type": "Feature",
  "properties": {
    "date:inception_lower": "1998-06-01",
    "date:inception_upper": "1998-06-01",
    "iso:country": "GB",
    "wof:name": "YO41 5LY",
    "wof:placetype": "postalcode"
  },
  "geometry": {"coordinates":[-0.895211,53.948613],"type":"Point"}
}
