{
  "type": "Feature",
  "properties": {
    "iso:country":"GB",
    "wof:name":"DG9 9AQ",
    "wof:placetype":"postalcode"
},
  "geometry": {"coordinates":[-5.06034067157412,54.82789124848968],"type":"Point"}
}