{
  "type": "Feature",
  "properties": {
    "iso:country":"GB",
    "wof:name":"DY14 8PU",
    "wof:placetype":"postalcode"
},
  "geometry": {"coordinates":[-2.44625149452079,52.37149906330235],"type":"Point"}
}