{
  "type": "Feature",
  "properties": {
    "iso:country":"GB",
    "wof:name":"B70 0LX",
    "wof:placetype":"postalcode"
},
  "geometry": {"coordinates":[-2.02378114479622,52.5364524323909],"type":"Point"}
}