{
  "type": "Feature",
  "properties": {
    "date:inception_lower":"1980-01-01",
    "date:inception_upper":"1980-01-31",
    "iso:country":"GB",
    "wof:name":"B70 0LX",
    "wof:placetype":"postalcode"
},
  "geometry": {"coordinates":[-2.023781,52.536452],"type":"Point"}
}