{
  "type": "Feature",
  "properties": {
    "iso:country": "GB",
    "wof:name": "AL7 2PN",
    "wof:placetype": "postalcode"
  },
  "geometry": {"coordinates":[-0.162857,51.799834],"type":"Point"}
}
