{
  "type": "Feature",
  "properties": {
    "iso:country":"GB",
    "wof:name":"SA19 6NP",
    "wof:placetype":"postalcode"
},
  "geometry": {"coordinates":[-3.98289432265548,51.89327820939379],"type":"Point"}
}