{
  "type": "Feature",
  "properties": {
    "date:inception_lower": "1980-01-01",
    "date:inception_upper": "1980-01-01",
    "iso:country": "GB",
    "wof:name": "SA19 6NP",
    "wof:placetype": "postalcode"
  },
  "geometry": {"coordinates":[-3.98227,51.894196],"type":"Point"}
}
