{
  "type": "Feature",
  "properties": {
    "date:inception_lower": "1980-01-01",
    "date:inception_upper": "1980-01-01",
    "iso:country": "GB",
    "wof:name": "GU9 7BA",
    "wof:placetype": "postalcode"
  },
  "geometry": {"coordinates":[-0.806079,51.214372],"type":"Point"}
}
