{
  "type": "Feature",
  "properties": {
    "iso:country":"GB",
    "wof:name":"GU9 7BA",
    "wof:placetype":"postalcode"
},
  "geometry": {"coordinates":[-0.80607876063534,51.21437200798669],"type":"Point"}
}