{
  "type": "Feature",
  "properties": {
    "iso:country": "GB",
    "wof:name": "BN7 1JA",
    "wof:placetype": "postalcode"
  },
  "geometry": {"coordinates":[0.0053,50.869205],"type":"Point"}
}
