{
  "type": "Feature",
  "properties": {
    "iso:country":"GB",
    "wof:name":"BN7 1JA",
    "wof:placetype":"postalcode"
},
  "geometry": {"coordinates":[0.00529987110081,50.86920518804747],"type":"Point"}
}