{
  "type": "Feature",
  "properties": {
    "iso:country": "GB",
    "wof:name": "WR9 0PZ",
    "wof:placetype": "postalcode"
  },
  "geometry": {"coordinates":[-2.205178,52.308477],"type":"Point"}
}
