{
  "type": "Feature",
  "properties": {
    "date:inception_lower": "1980-01-01",
    "date:inception_upper": "1980-01-01",
    "iso:country": "GB",
    "wof:name": "WR9 0PZ",
    "wof:placetype": "postalcode"
  },
  "geometry": {"coordinates":[-2.204912,52.309157],"type":"Point"}
}
