{
  "type": "Feature",
  "properties": {
    "iso:country":"GB",
    "wof:name":"WR9 0PZ",
    "wof:placetype":"postalcode"
},
  "geometry": {"coordinates":[-2.20517791760097,52.30847745673474],"type":"Point"}
}