{
  "type": "Feature",
  "properties": {
    "iso:country":"GB",
    "wof:name":"LN6 0DN",
    "wof:placetype":"postalcode"
},
  "geometry": {"coordinates":[-0.58252303560701,53.21027463968898],"type":"Point"}
}