{
  "type": "Feature",
  "properties": {
    "iso:country":"GB",
    "wof:name":"WA4 5LA",
    "wof:placetype":"postalcode"
},
  "geometry": {"coordinates":[-2.58580795589592,53.36063301538601],"type":"Point"}
}