{
  "type": "Feature",
  "properties": {
    "iso:country": "GB",
    "wof:name": "WA4 5LA",
    "wof:placetype": "postalcode"
  },
  "geometry": {"coordinates":[-2.585808,53.360633],"type":"Point"}
}
