{
  "type": "Feature",
  "properties": {
    "iso:country":"GB",
    "wof:name":"LS8 5HN",
    "wof:placetype":"postalcode"
},
  "geometry": {"coordinates":[-1.52789305210939,53.80665667914489],"type":"Point"}
}