{
  "type": "Feature",
  "properties": {
    "iso:country":"GB",
    "wof:name":"LL26 0ET",
    "wof:placetype":"postalcode"
},
  "geometry": {"coordinates":[-3.79779928391602,53.13859958516493],"type":"Point"}
}