{
  "type": "Feature",
  "properties": {
    "iso:country": "GB",
    "wof:name": "LL26 0ET",
    "wof:placetype": "postalcode"
  },
  "geometry": {"coordinates":[-3.797799,53.1386],"type":"Point"}
}
