{
  "type": "Feature",
  "properties": {
    "date:inception_lower": "1980-01-01",
    "date:inception_upper": "1980-01-01",
    "iso:country": "GB",
    "wof:name": "LL26 0ET",
    "wof:placetype": "postalcode"
  },
  "geometry": {"coordinates":[-3.797561,53.137819],"type":"Point"}
}
