{
  "type": "Feature",
  "properties": {
    "iso:country":"GB",
    "wof:name":"SO31 8HE",
    "wof:placetype":"postalcode"
},
  "geometry": {"coordinates":[-1.31817007637323,50.89324205760978],"type":"Point"}
}