{
  "type": "Feature",
  "properties": {
    "iso:country": "GB",
    "wof:name": "BA1 7PP",
    "wof:placetype": "postalcode"
  },
  "geometry": {"coordinates":[-2.309498,51.404435],"type":"Point"}
}
