{
  "type": "Feature",
  "properties": {
    "date:inception_lower": "2023-06-01",
    "date:inception_upper": "2023-06-01",
    "iso:country": "GB",
    "wof:name": "NE65 8FB",
    "wof:placetype": "postalcode"
  },
  "geometry": {"coordinates":[-1.797324,55.307149],"type":"Point"}
}
