{
  "type": "Feature",
  "properties": {
    "iso:country":"GB",
    "wof:name":"NR27 7BP",
    "wof:placetype":"postalcode"
},
  "geometry": {"coordinates":[1.30143383831287,52.9307609966271],"type":"Point"}
}