{
  "type": "Feature",
  "properties": {
    "iso:country":"GB",
    "wof:name":"NW4 1AD",
    "wof:placetype":"postalcode"
},
  "geometry": {"coordinates":[-0.22065948133251,51.59416423316723],"type":"Point"}
}