{
  "type": "Feature",
  "properties": {
    "iso:country":"GB",
    "wof:name":"SY20 9SB",
    "wof:placetype":"postalcode"
},
  "geometry": {"coordinates":[-3.82822707644826,52.67617466673645],"type":"Point"}
}