{
  "type": "Feature",
  "properties": {
    "date:inception_lower": "2019-04-01",
    "date:inception_upper": "2019-04-01",
    "iso:country": "GB",
    "wof:name": "BA15 1GH",
    "wof:placetype": "postalcode"
  },
  "geometry": {"coordinates":[-2.237059,51.347234],"type":"Point"}
}
