{
  "type": "Feature",
  "properties": {
    "date:inception_lower": "1996-06-01",
    "date:inception_upper": "1996-06-01",
    "iso:country": "GB",
    "wof:name": "AB56 4DR",
    "wof:placetype": "postalcode"
  },
  "geometry": {"coordinates":[-2.902525,57.683405],"type":"Point"}
}
