{
  "type": "Feature",
  "properties": {
    "iso:country": "GB",
    "wof:name": "AB56 4DR",
    "wof:placetype": "postalcode"
  },
  "geometry": {"coordinates":[-2.902525,57.683405],"type":"Point"}
}
