{
  "type": "Feature",
  "properties": {
    "iso:country":"GB",
    "wof:name":"AB56 4DR",
    "wof:placetype":"postalcode"
},
  "geometry": {"coordinates":[-2.90252468381434,57.6834049190003],"type":"Point"}
}