{
  "type": "Feature",
  "properties": {
    "iso:country": "GB",
    "wof:name": "TW17 9EL",
    "wof:placetype": "postalcode"
  },
  "geometry": {"coordinates":[-0.443518,51.393567],"type":"Point"}
}
