{
  "type": "Feature",
  "properties": {
    "iso:country": "GB",
    "wof:name": "PL3 6NU",
    "wof:placetype": "postalcode"
  },
  "geometry": {"coordinates":[-4.102879,50.39014],"type":"Point"}
}
