{
  "type": "Feature",
  "properties": {
    "iso:country":"GB",
    "wof:name":"GL1 2RX",
    "wof:placetype":"postalcode"
},
  "geometry": {"coordinates":[-2.25851510769766,51.8707472435017],"type":"Point"}
}