{
  "type": "Feature",
  "properties": {
    "iso:country":"GB",
    "wof:name":"TA19 9RW",
    "wof:placetype":"postalcode"
},
  "geometry": {"coordinates":[-2.96607668412245,50.93006226236049],"type":"Point"}
}