{
  "type": "Feature",
  "properties": {
    "date:inception_lower": "1980-01-01",
    "date:inception_upper": "1980-01-01",
    "iso:country": "GB",
    "wof:name": "TA19 9RW",
    "wof:placetype": "postalcode"
  },
  "geometry": {"coordinates":[-2.966077,50.930062],"type":"Point"}
}
