{
  "type": "Feature",
  "properties": {
    "iso:country":"GB",
    "wof:name":"DH3 1RQ",
    "wof:placetype":"postalcode"
},
  "geometry": {"coordinates":[-1.58844040319786,54.90769337848706],"type":"Point"}
}