{
  "type": "Feature",
  "properties": {
    "date:inception_lower": "1980-01-01",
    "date:inception_upper": "1980-01-01",
    "iso:country": "GB",
    "wof:name": "DH3 1RQ",
    "wof:placetype": "postalcode"
  },
  "geometry": {"coordinates":[-1.58844,54.907693],"type":"Point"}
}
