{
  "type": "Feature",
  "properties": {
    "iso:country": "GB",
    "wof:name": "RG30 9LZ",
    "wof:placetype": "postalcode"
  },
  "geometry": {"coordinates":[-0.991862,51.460183],"type":"Point"}
}
