{
  "type": "Feature",
  "properties": {
    "iso:country":"GB",
    "wof:name":"B42 2AH",
    "wof:placetype":"postalcode"
},
  "geometry": {"coordinates":[-1.90072394883389,52.53537064238436],"type":"Point"}
}