{
  "type": "Feature",
  "properties": {
    "iso:country": "GB",
    "wof:name": "B42 2AH",
    "wof:placetype": "postalcode"
  },
  "geometry": {"coordinates":[-1.900724,52.535371],"type":"Point"}
}
