{
  "type": "Feature",
  "properties": {
    "iso:country":"GB",
    "wof:name":"RG40 3RH",
    "wof:placetype":"postalcode"
},
  "geometry": {"coordinates":[-0.85808990995167,51.37586877481536],"type":"Point"}
}