{
  "type": "Feature",
  "properties": {
    "date:inception_lower": "1995-07-01",
    "date:inception_upper": "1995-07-01",
    "iso:country": "GB",
    "wof:name": "RG40 3RH",
    "wof:placetype": "postalcode"
  },
  "geometry": {"coordinates":[-0.85809,51.375869],"type":"Point"}
}
