{
  "type": "Feature",
  "properties": {
    "iso:country": "GB",
    "wof:name": "TR12 6EP",
    "wof:placetype": "postalcode"
  },
  "geometry": {"coordinates":[-5.094706,50.0678],"type":"Point"}
}
