{
  "type": "Feature",
  "properties": {
    "iso:country":"GB",
    "wof:name":"TR12 6EP",
    "wof:placetype":"postalcode"
},
  "geometry": {"coordinates":[-5.09470644212121,50.06779967279824],"type":"Point"}
}