{
  "type": "Feature",
  "properties": {
    "iso:country":"GB",
    "wof:name":"DA5 3QW",
    "wof:placetype":"postalcode"
},
  "geometry": {"coordinates":[0.14170824841795,51.43945881834144],"type":"Point"}
}