{
  "type": "Feature",
  "properties": {
    "iso:country":"GB",
    "wof:name":"DL2 3LT",
    "wof:placetype":"postalcode"
},
  "geometry": {"coordinates":[-1.80725562945218,54.58091975364374],"type":"Point"}
}