{
  "type": "Feature",
  "properties": {
    "date:inception_lower": "1990-02-01",
    "date:inception_upper": "1990-02-01",
    "iso:country": "GB",
    "wof:name": "DL2 3LT",
    "wof:placetype": "postalcode"
  },
  "geometry": {"coordinates":[-1.807256,54.58092],"type":"Point"}
}
