{
  "type": "Feature",
  "properties": {
    "iso:country": "GB",
    "wof:name": "L22 4QY",
    "wof:placetype": "postalcode"
  },
  "geometry": {"coordinates":[-3.021038,53.480267],"type":"Point"}
}
