{
  "type": "Feature",
  "properties": {
    "iso:country": "GB",
    "wof:name": "HP21 8AA",
    "wof:placetype": "postalcode"
  },
  "geometry": {"coordinates":[-0.809614,51.807773],"type":"Point"}
}
