{
  "type": "Feature",
  "properties": {
    "iso:country":"GB",
    "wof:name":"LL57 1LF",
    "wof:placetype":"postalcode"
},
  "geometry": {"coordinates":[-4.12945555212393,53.22534487921661],"type":"Point"}
}