{
  "type": "Feature",
  "properties": {
    "iso:country": "GB",
    "wof:name": "LL57 1LF",
    "wof:placetype": "postalcode"
  },
  "geometry": {"coordinates":[-4.129456,53.225345],"type":"Point"}
}
