{
  "type": "Feature",
  "properties": {
    "iso:country": "GB",
    "wof:name": "WR14 1LU",
    "wof:placetype": "postalcode"
  },
  "geometry": {"coordinates":[-2.325708,52.130486],"type":"Point"}
}
