{
  "type": "Feature",
  "properties": {
    "iso:country":"GB",
    "wof:name":"CF34 9BL",
    "wof:placetype":"postalcode"
},
  "geometry": {"coordinates":[-3.65752664695729,51.60933848976322],"type":"Point"}
}