{
  "type": "Feature",
  "properties": {
    "date:inception_lower": "1980-01-01",
    "date:inception_upper": "1980-01-01",
    "iso:country": "GB",
    "wof:name": "CF34 9BL",
    "wof:placetype": "postalcode"
  },
  "geometry": {"coordinates":[-3.657527,51.609338],"type":"Point"}
}
