{
  "type": "Feature",
  "properties": {
    "iso:country": "GB",
    "wof:name": "CF34 9BL",
    "wof:placetype": "postalcode"
  },
  "geometry": {"coordinates":[-3.657527,51.609338],"type":"Point"}
}
