{
  "type": "Feature",
  "properties": {
    "iso:country":"GB",
    "wof:name":"NG22 0TD",
    "wof:placetype":"postalcode"
},
  "geometry": {"coordinates":[-0.82175648709403,53.25870750199808],"type":"Point"}
}