{
  "type": "Feature",
  "properties": {
    "iso:country":"GB",
    "wof:name":"ST5 3QT",
    "wof:placetype":"postalcode"
},
  "geometry": {"coordinates":[-2.22752648891861,52.99883732151648],"type":"Point"}
}