{
  "type": "Feature",
  "properties": {
    "iso:country": "GB",
    "wof:name": "SG8 0SD",
    "wof:placetype": "postalcode"
  },
  "geometry": {"coordinates":[-0.093763,52.08297],"type":"Point"}
}
