{
  "type": "Feature",
  "properties": {
    "iso:country":"GB",
    "wof:name":"SG8 0SD",
    "wof:placetype":"postalcode"
},
  "geometry": {"coordinates":[-0.09376255199118,52.08297049157377],"type":"Point"}
}