{
  "type": "Feature",
  "properties": {
    "iso:country":"GB",
    "wof:name":"DY4 7TU",
    "wof:placetype":"postalcode"
},
  "geometry": {"coordinates":[-2.05214079444169,52.51916471473722],"type":"Point"}
}