{
  "type": "Feature",
  "properties": {
    "iso:country":"GB",
    "wof:name":"RH16 1LP",
    "wof:placetype":"postalcode"
},
  "geometry": {"coordinates":[-0.10878409837383,51.00111750995455],"type":"Point"}
}