{
  "type": "Feature",
  "properties": {
    "iso:country": "GB",
    "wof:name": "RH16 1LP",
    "wof:placetype": "postalcode"
  },
  "geometry": {"coordinates":[-0.108784,51.001118],"type":"Point"}
}
