{
  "type": "Feature",
  "properties": {
    "iso:country":"GB",
    "wof:name":"BS16 4SJ",
    "wof:placetype":"postalcode"
},
  "geometry": {"coordinates":[-2.50026830364734,51.47669780485817],"type":"Point"}
}