{
  "type": "Feature",
  "properties": {
    "iso:country": "GB",
    "wof:name": "SW8 4UG",
    "wof:placetype": "postalcode"
  },
  "geometry": {"coordinates":[-0.139432,51.473979],"type":"Point"}
}
