{
  "type": "Feature",
  "properties": {
    "date:inception_lower": "2010-08-01",
    "date:inception_upper": "2010-08-01",
    "iso:country": "GB",
    "wof:name": "CB2 8BJ",
    "wof:placetype": "postalcode"
  },
  "geometry": {"coordinates":[0.129591,52.189919],"type":"Point"}
}
