{
  "type": "Feature",
  "properties": {
    "iso:country":"GB",
    "wof:name":"WD6 2EP",
    "wof:placetype":"postalcode"
},
  "geometry": {"coordinates":[-0.26256322202727,51.64997724957399],"type":"Point"}
}