{
  "type": "Feature",
  "properties": {
    "iso:country": "GB",
    "wof:name": "B37 6DW",
    "wof:placetype": "postalcode"
  },
  "geometry": {"coordinates":[-1.757789,52.493326],"type":"Point"}
}
