{
  "type": "Feature",
  "properties": {
    "date:inception_lower": "1982-03-01",
    "date:inception_upper": "1982-03-01",
    "iso:country": "GB",
    "wof:name": "B37 6DW",
    "wof:placetype": "postalcode"
  },
  "geometry": {"coordinates":[-1.757789,52.493326],"type":"Point"}
}
