{
  "type": "Feature",
  "properties": {
    "iso:country":"GB",
    "wof:name":"B37 6DW",
    "wof:placetype":"postalcode"
},
  "geometry": {"coordinates":[-1.75778929495674,52.4933256825548],"type":"Point"}
}