{
  "type": "Feature",
  "properties": {
    "date:inception_lower": "2024-08-01",
    "date:inception_upper": "2024-08-01",
    "iso:country": "GB",
    "wof:name": "BS37 7NZ",
    "wof:placetype": "postalcode"
  },
  "geometry": {"coordinates":[-2.417525,51.559581],"type":"Point"}
}
