{
  "type": "Feature",
  "properties": {
    "iso:country": "GB",
    "wof:name": "SE5 0AB",
    "wof:placetype": "postalcode"
  },
  "geometry": {"coordinates":[-0.095452,51.482347],"type":"Point"}
}
