{
  "type": "Feature",
  "properties": {
    "iso:country":"GB",
    "wof:name":"SE5 0AB",
    "wof:placetype":"postalcode"
},
  "geometry": {"coordinates":[-0.09545240897174,51.48234654637783],"type":"Point"}
}