{
  "type": "Feature",
  "properties": {
    "iso:country":"GB",
    "wof:name":"S18 3AJ",
    "wof:placetype":"postalcode"
},
  "geometry": {"coordinates":[-1.45962386253861,53.31099811660043],"type":"Point"}
}