{
  "type": "Feature",
  "properties": {
    "date:inception_lower": "1997-06-01",
    "date:inception_upper": "1997-06-01",
    "iso:country": "GB",
    "wof:name": "S18 3AJ",
    "wof:placetype": "postalcode"
  },
  "geometry": {"coordinates":[-1.459624,53.310998],"type":"Point"}
}
