{
  "type": "Feature",
  "properties": {
    "iso:country":"GB",
    "wof:name":"TF6 6LQ",
    "wof:placetype":"postalcode"
},
  "geometry": {"coordinates":[-2.57013871470608,52.73603944346083],"type":"Point"}
}