{
  "type": "Feature",
  "properties": {
    "iso:country": "GB",
    "wof:name": "B64 7QG",
    "wof:placetype": "postalcode"
  },
  "geometry": {"coordinates":[-2.04827,52.47],"type":"Point"}
}
