{
  "type": "Feature",
  "properties": {
    "iso:country":"GB",
    "wof:name":"PE6 8JA",
    "wof:placetype":"postalcode"
},
  "geometry": {"coordinates":[-0.31137431425956,52.67942278962092],"type":"Point"}
}