{
  "type": "Feature",
  "properties": {
    "date:inception_lower": "1980-01-01",
    "date:inception_upper": "1980-01-01",
    "iso:country": "GB",
    "wof:name": "PE6 8JA",
    "wof:placetype": "postalcode"
  },
  "geometry": {"coordinates":[-0.311374,52.679423],"type":"Point"}
}
