{
  "type": "Feature",
  "properties": {
    "iso:country": "GB",
    "wof:name": "YO14 9LB",
    "wof:placetype": "postalcode"
  },
  "geometry": {"coordinates":[-0.285504,54.206629],"type":"Point"}
}
