{
  "type": "Feature",
  "properties": {
    "date:inception_lower": "1980-01-01",
    "date:inception_upper": "1980-01-01",
    "iso:country": "GB",
    "wof:name": "YO14 9LB",
    "wof:placetype": "postalcode"
  },
  "geometry": {"coordinates":[-0.285523,54.206558],"type":"Point"}
}
