{
  "type": "Feature",
  "properties": {
    "iso:country":"GB",
    "wof:name":"YO14 9LB",
    "wof:placetype":"postalcode"
},
  "geometry": {"coordinates":[-0.28549037181611,54.20656511560234],"type":"Point"}
}