{
  "type": "Feature",
  "properties": {
    "date:inception_lower":"1980-01-01",
    "date:inception_upper":"1980-01-31",
    "iso:country":"GB",
    "wof:name":"YO11 3EQ",
    "wof:placetype":"postalcode"
},
  "geometry": {"coordinates":[-0.400723,54.242198],"type":"Point"}
}