{
  "type": "Feature",
  "properties": {
    "iso:country": "GB",
    "wof:name": "CF42 6SX",
    "wof:placetype": "postalcode"
  },
  "geometry": {"coordinates":[-3.503878,51.663143],"type":"Point"}
}
