{
  "type": "Feature",
  "properties": {
    "iso:country":"GB",
    "wof:name":"CM8 2EY",
    "wof:placetype":"postalcode"
},
  "geometry": {"coordinates":[0.63260768377814,51.8028306989894],"type":"Point"}
}