{
  "type": "Feature",
  "properties": {
    "date:inception_lower":"2018-03-01",
    "date:inception_upper":"2018-03-31",
    "iso:country":"GB",
    "wof:name":"EH49 7EZ",
    "wof:placetype":"postalcode"
},
  "geometry": {"coordinates":[-3.60075,55.976428],"type":"Point"}
}