{
  "type": "Feature",
  "properties": {
    "iso:country":"GB",
    "wof:name":"LE17 6PP",
    "wof:placetype":"postalcode"
},
  "geometry": {"coordinates":[-1.09055239365269,52.5037721551674],"type":"Point"}
}