{
  "type": "Feature",
  "properties": {
    "iso:country": "GB",
    "wof:name": "LE17 6PP",
    "wof:placetype": "postalcode"
  },
  "geometry": {"coordinates":[-1.08616,52.505491],"type":"Point"}
}
