{
  "type": "Feature",
  "properties": {
    "iso:country": "GB",
    "wof:name": "N3 2SS",
    "wof:placetype": "postalcode"
  },
  "geometry": {"coordinates":[-0.187672,51.596294],"type":"Point"}
}
