{
  "type": "Feature",
  "properties": {
    "iso:country":"GB",
    "wof:name":"E8 2AP",
    "wof:placetype":"postalcode"
},
  "geometry": {"coordinates":[-0.06472165021028,51.55195859335794],"type":"Point"}
}