{
  "type": "Feature",
  "properties": {
    "date:inception_lower": "1980-01-01",
    "date:inception_upper": "1980-01-01",
    "iso:country": "GB",
    "wof:name": "E8 2AP",
    "wof:placetype": "postalcode"
  },
  "geometry": {"coordinates":[-0.064722,51.551959],"type":"Point"}
}
