{
  "type": "Feature",
  "properties": {
    "iso:country":"GB",
    "wof:name":"CR0 3AA",
    "wof:placetype":"postalcode"
},
  "geometry": {"coordinates":[-0.12951940562142,51.38922773833285],"type":"Point"}
}