{
  "type": "Feature",
  "properties": {
    "iso:country": "GB",
    "wof:name": "PE33 9GL",
    "wof:placetype": "postalcode"
  },
  "geometry": {"coordinates":[0.580254,52.596553],"type":"Point"}
}
