{
  "type": "Feature",
  "properties": {
    "date:inception_lower": "2009-06-01",
    "date:inception_upper": "2009-06-01",
    "iso:country": "GB",
    "wof:name": "PE33 9GL",
    "wof:placetype": "postalcode"
  },
  "geometry": {"coordinates":[0.575563,52.600414],"type":"Point"}
}
