{
  "type": "Feature",
  "properties": {
    "iso:country":"GB",
    "wof:name":"SN10 4LZ",
    "wof:placetype":"postalcode"
},
  "geometry": {"coordinates":[-2.0074896299422,51.26715400683695],"type":"Point"}
}