{
  "type": "Feature",
  "properties": {
    "iso:country":"GB",
    "wof:name":"B31 3HF",
    "wof:placetype":"postalcode"
},
  "geometry": {"coordinates":[-1.96028672705503,52.40073562617368],"type":"Point"}
}