{
  "type": "Feature",
  "properties": {
    "iso:country": "GB",
    "wof:name": "DL11 6UU",
    "wof:placetype": "postalcode"
  },
  "geometry": {"coordinates":[-1.964306,54.409248],"type":"Point"}
}
