{
  "type": "Feature",
  "properties": {
    "iso:country":"GB",
    "wof:name":"DL11 6UU",
    "wof:placetype":"postalcode"
},
  "geometry": {"coordinates":[-1.96627125409453,54.41009226446339],"type":"Point"}
}