{
  "type": "Feature",
  "properties": {
    "iso:country": "GB",
    "wof:name": "DL11 6UU",
    "wof:placetype": "postalcode"
  },
  "geometry": {"coordinates":[-1.966277,54.410102],"type":"Point"}
}
