{
  "type": "Feature",
  "properties": {
    "iso:country":"GB",
    "wof:name":"OX9 3BN",
    "wof:placetype":"postalcode"
},
  "geometry": {"coordinates":[-0.97265750106417,51.74601118556566],"type":"Point"}
}