{
  "type": "Feature",
  "properties": {
    "iso:country": "GB",
    "wof:name": "SN25 2HW",
    "wof:placetype": "postalcode"
  },
  "geometry": {"coordinates":[-1.837804,51.603327],"type":"Point"}
}
