{
  "type": "Feature",
  "properties": {
    "iso:country":"GB",
    "wof:name":"SN25 2HW",
    "wof:placetype":"postalcode"
},
  "geometry": {"coordinates":[-1.83780384932658,51.60332706982973],"type":"Point"}
}