{
  "type": "Feature",
  "properties": {
    "iso:country": "GB",
    "wof:name": "SN11 9RZ",
    "wof:placetype": "postalcode"
  },
  "geometry": {"coordinates":[-2.005276,51.449757],"type":"Point"}
}
