{
  "type": "Feature",
  "properties": {
    "iso:country":"GB",
    "wof:name":"TF2 7NR",
    "wof:placetype":"postalcode"
},
  "geometry": {"coordinates":[-2.43393292973418,52.71271279615561],"type":"Point"}
}