{
  "type": "Feature",
  "properties": {
    "iso:country":"GB",
    "wof:name":"RG25 2DR",
    "wof:placetype":"postalcode"
},
  "geometry": {"coordinates":[-1.13014089880367,51.17465998214541],"type":"Point"}
}