{
  "type": "Feature",
  "properties": {
    "date:inception_lower":"1980-01-01",
    "date:inception_upper":"1980-01-31",
    "iso:country":"GB",
    "wof:name":"RG25 2DR",
    "wof:placetype":"postalcode"
},
  "geometry": {"coordinates":[-1.130125,51.174658],"type":"Point"}
}