{
  "type": "Feature",
  "properties": {
    "iso:country":"GB",
    "wof:name":"WS7 9HH",
    "wof:placetype":"postalcode"
},
  "geometry": {"coordinates":[-1.90238210311908,52.69202752009429],"type":"Point"}
}