{
  "type": "Feature",
  "properties": {
    "iso:country":"GB",
    "wof:name":"EX33 1FE",
    "wof:placetype":"postalcode"
},
  "geometry": {"coordinates":[-4.16503554306982,51.10466199018553],"type":"Point"}
}