{
  "type": "Feature",
  "properties": {
    "date:inception_lower": "2008-10-01",
    "date:inception_upper": "2008-10-01",
    "iso:country": "GB",
    "wof:name": "EX33 1FE",
    "wof:placetype": "postalcode"
  },
  "geometry": {"coordinates":[-4.165036,51.104662],"type":"Point"}
}
