{
  "type": "Feature",
  "properties": {
    "iso:country": "GB",
    "wof:name": "EX33 1FE",
    "wof:placetype": "postalcode"
  },
  "geometry": {"coordinates":[-4.165036,51.104662],"type":"Point"}
}
