{
  "type": "Feature",
  "properties": {
    "date:inception_lower": "1980-01-01",
    "date:inception_upper": "1980-01-01",
    "iso:country": "GB",
    "wof:name": "NW10 0PY",
    "wof:placetype": "postalcode"
  },
  "geometry": {"coordinates":[-0.263555,51.549441],"type":"Point"}
}
