{
  "type": "Feature",
  "properties": {
    "iso:country":"GB",
    "wof:name":"PE31 8UN",
    "wof:placetype":"postalcode"
},
  "geometry": {"coordinates":[0.73047975299882,52.94097323965158],"type":"Point"}
}