{
  "type": "Feature",
  "properties": {
    "iso:country": "GB",
    "wof:name": "PE31 8UN",
    "wof:placetype": "postalcode"
  },
  "geometry": {"coordinates":[0.73048,52.940973],"type":"Point"}
}
