{
  "type": "Feature",
  "properties": {
    "date:inception_lower":"1997-12-01",
    "date:inception_upper":"1997-12-31",
    "iso:country":"GB",
    "wof:name":"PE31 8UN",
    "wof:placetype":"postalcode"
},
  "geometry": {"coordinates":[0.73048,52.940973],"type":"Point"}
}