{
  "type": "Feature",
  "properties": {
    "iso:country":"GB",
    "wof:name":"TA1 2AR",
    "wof:placetype":"postalcode"
},
  "geometry": {"coordinates":[-3.08411101391728,51.02047160101751],"type":"Point"}
}