{
  "type": "Feature",
  "properties": {
    "iso:country": "GB",
    "wof:name": "TA1 2AR",
    "wof:placetype": "postalcode"
  },
  "geometry": {"coordinates":[-3.083494,51.020936],"type":"Point"}
}
