{
  "type": "Feature",
  "properties": {
    "date:inception_lower": "2019-03-01",
    "date:inception_upper": "2019-03-01",
    "iso:country": "GB",
    "wof:name": "CT18 7TQ",
    "wof:placetype": "postalcode"
  },
  "geometry": {"coordinates":[1.159373,51.111355],"type":"Point"}
}
