{
  "type": "Feature",
  "properties": {
    "iso:country":"GB",
    "wof:name":"SE5 0NJ",
    "wof:placetype":"postalcode"
},
  "geometry": {"coordinates":[-0.09930754909736,51.48072748457001],"type":"Point"}
}