{
  "type": "Feature",
  "properties": {
    "iso:country":"GB",
    "wof:name":"G71 8NW",
    "wof:placetype":"postalcode"
},
  "geometry": {"coordinates":[-4.05899072791661,55.79919801316732],"type":"Point"}
}