{
  "type": "Feature",
  "properties": {
    "date:inception_lower":"1980-01-01",
    "date:inception_upper":"1980-01-31",
    "iso:country":"GB",
    "wof:name":"TA24 6AF",
    "wof:placetype":"postalcode"
},
  "geometry": {"coordinates":[-3.466247,51.199157],"type":"Point"}
}