{
  "type": "Feature",
  "properties": {
    "iso:country":"GB",
    "wof:name":"TA24 6AF",
    "wof:placetype":"postalcode"
},
  "geometry": {"coordinates":[-3.46624726775163,51.1991574110602],"type":"Point"}
}