{
  "type": "Feature",
  "properties": {
    "iso:country":"GB",
    "wof:name":"M34 6JU",
    "wof:placetype":"postalcode"
},
  "geometry": {"coordinates":[-2.11430588951722,53.44392955072993],"type":"Point"}
}