{
  "type": "Feature",
  "properties": {
    "iso:country": "GB",
    "wof:name": "M34 6JU",
    "wof:placetype": "postalcode"
  },
  "geometry": {"coordinates":[-2.114306,53.44393],"type":"Point"}
}
