{
  "type": "Feature",
  "properties": {
    "iso:country":"GB",
    "wof:name":"BS24 7FB",
    "wof:placetype":"postalcode"
},
  "geometry": {"coordinates":[-2.93064494933575,51.34727686097639],"type":"Point"}
}