{
  "type": "Feature",
  "properties": {
    "iso:country": "GB",
    "wof:name": "BS24 7FB",
    "wof:placetype": "postalcode"
  },
  "geometry": {"coordinates":[-2.930645,51.347277],"type":"Point"}
}
