{
  "type": "Feature",
  "properties": {
    "iso:country": "GB",
    "wof:name": "BA22 9JG",
    "wof:placetype": "postalcode"
  },
  "geometry": {"coordinates":[-2.65689,50.908543],"type":"Point"}
}
