{
  "type": "Feature",
  "properties": {
    "iso:country":"GB",
    "wof:name":"YO17 7AW",
    "wof:placetype":"postalcode"
},
  "geometry": {"coordinates":[-0.79849936305597,54.13447795840533],"type":"Point"}
}