{
  "type": "Feature",
  "properties": {
    "date:inception_lower": "1999-06-01",
    "date:inception_upper": "1999-06-01",
    "iso:country": "GB",
    "wof:name": "CH42 4RF",
    "wof:placetype": "postalcode"
  },
  "geometry": {"coordinates":[-3.015177,53.369805],"type":"Point"}
}
