{
  "type": "Feature",
  "properties": {
    "iso:country": "GB",
    "wof:name": "BA13 2GH",
    "wof:placetype": "postalcode"
  },
  "geometry": {"coordinates":[-2.195953,51.255993],"type":"Point"}
}
