{
  "type": "Feature",
  "properties": {
    "iso:country":"GB",
    "wof:name":"BA13 2GH",
    "wof:placetype":"postalcode"
},
  "geometry": {"coordinates":[-2.19595290819464,51.2559928160099],"type":"Point"}
}