{
  "type": "Feature",
  "properties": {
    "iso:country":"GB",
    "wof:name":"ST19 5AR",
    "wof:placetype":"postalcode"
},
  "geometry": {"coordinates":[-2.11616203968639,52.72624276991449],"type":"Point"}
}