{
  "type": "Feature",
  "properties": {
    "iso:country":"GB",
    "wof:name":"PA12 4EQ",
    "wof:placetype":"postalcode"
},
  "geometry": {"coordinates":[-4.62683255759704,55.80003011670195],"type":"Point"}
}