{
  "type": "Feature",
  "properties": {
    "date:inception_lower": "1990-09-01",
    "date:inception_upper": "1990-09-01",
    "iso:country": "GB",
    "wof:name": "PA12 4EQ",
    "wof:placetype": "postalcode"
  },
  "geometry": {"coordinates":[-4.626798,55.799986],"type":"Point"}
}
