{
  "type": "Feature",
  "properties": {
    "iso:country":"GB",
    "wof:name":"EN5 2FH",
    "wof:placetype":"postalcode"
},
  "geometry": {"coordinates":[-0.20001382408142,51.64600471613842],"type":"Point"}
}