{
  "type": "Feature",
  "properties": {
    "iso:country":"GB",
    "wof:name":"L13 9DB",
    "wof:placetype":"postalcode"
},
  "geometry": {"coordinates":[-2.93032675289172,53.43422956251855],"type":"Point"}
}