{
  "type": "Feature",
  "properties": {
    "date:inception_lower": "1986-07-01",
    "date:inception_upper": "1986-07-01",
    "iso:country": "GB",
    "wof:name": "L13 9DB",
    "wof:placetype": "postalcode"
  },
  "geometry": {"coordinates":[-2.930327,53.43423],"type":"Point"}
}
