{
  "type": "Feature",
  "properties": {
    "iso:country":"GB",
    "wof:name":"HD8 0RG",
    "wof:placetype":"postalcode"
},
  "geometry": {"coordinates":[-1.70605100448247,53.61633551145488],"type":"Point"}
}