{
  "type": "Feature",
  "properties": {
    "iso:country":"GB",
    "wof:name":"EX16 7NZ",
    "wof:placetype":"postalcode"
},
  "geometry": {"coordinates":[-3.38608120632886,51.00010262007986],"type":"Point"}
}