{
  "type": "Feature",
  "properties": {
    "iso:country": "GB",
    "wof:name": "WD6 5JZ",
    "wof:placetype": "postalcode"
  },
  "geometry": {"coordinates":[-0.276517,51.670056],"type":"Point"}
}
