{
  "type": "Feature",
  "properties": {
    "iso:country": "GB",
    "wof:name": "S41 7QP",
    "wof:placetype": "postalcode"
  },
  "geometry": {"coordinates":[-1.428065,53.243237],"type":"Point"}
}
