{
  "type": "Feature",
  "properties": {
    "date:inception_lower": "1980-01-01",
    "date:inception_upper": "1980-01-01",
    "iso:country": "GB",
    "wof:name": "S41 7QP",
    "wof:placetype": "postalcode"
  },
  "geometry": {"coordinates":[-1.428065,53.243237],"type":"Point"}
}
