{
  "type": "Feature",
  "properties": {
    "iso:country":"GB",
    "wof:name":"NG15 9AW",
    "wof:placetype":"postalcode"
},
  "geometry": {"coordinates":[-1.16957905800201,53.08401078302983],"type":"Point"}
}