{
  "type": "Feature",
  "properties": {
    "date:inception_lower": "1983-03-01",
    "date:inception_upper": "1983-03-01",
    "iso:country": "GB",
    "wof:name": "NG15 9AW",
    "wof:placetype": "postalcode"
  },
  "geometry": {"coordinates":[-1.169579,53.084011],"type":"Point"}
}
