{
  "type": "Feature",
  "properties": {
    "date:inception_lower": "2003-10-01",
    "date:inception_upper": "2003-10-01",
    "iso:country": "GB",
    "wof:name": "KY4 0JX",
    "wof:placetype": "postalcode"
  },
  "geometry": {"coordinates":[-3.37702,56.139539],"type":"Point"}
}
