{
  "type": "Feature",
  "properties": {
    "iso:country":"GB",
    "wof:name":"KY4 0JX",
    "wof:placetype":"postalcode"
},
  "geometry": {"coordinates":[-3.37585654345474,56.13936976671523],"type":"Point"}
}