{
  "type": "Feature",
  "properties": {
    "iso:country":"GB",
    "wof:name":"DE55 6AF",
    "wof:placetype":"postalcode"
},
  "geometry": {"coordinates":[-1.41359451091617,53.12104169071337],"type":"Point"}
}