{
  "type": "Feature",
  "properties": {
    "date:inception_lower": "2019-10-01",
    "date:inception_upper": "2019-10-01",
    "iso:country": "GB",
    "wof:name": "DH1 3FA",
    "wof:placetype": "postalcode"
  },
  "geometry": {"coordinates":[-1.590566,54.76044],"type":"Point"}
}
