{
  "type": "Feature",
  "properties": {
    "iso:country": "GB",
    "wof:name": "NE22 7AX",
    "wof:placetype": "postalcode"
  },
  "geometry": {"coordinates":[-1.551442,55.14487],"type":"Point"}
}
