{
  "type": "Feature",
  "properties": {
    "iso:country":"GB",
    "wof:name":"BD16 2DU",
    "wof:placetype":"postalcode"
},
  "geometry": {"coordinates":[-1.8519972988947,53.86391984896827],"type":"Point"}
}