{
  "type": "Feature",
  "properties": {
    "iso:country":"GB",
    "wof:name":"EH7 6PU",
    "wof:placetype":"postalcode"
},
  "geometry": {"coordinates":[-3.13851434084378,55.95829695241122],"type":"Point"}
}