{
  "type": "Feature",
  "properties": {
    "iso:country":"GB",
    "wof:name":"BL8 3BQ",
    "wof:placetype":"postalcode"
},
  "geometry": {"coordinates":[-2.34075953821483,53.60254780743715],"type":"Point"}
}