{
  "type": "Feature",
  "properties": {
    "iso:country": "GB",
    "wof:name": "BL8 3BQ",
    "wof:placetype": "postalcode"
  },
  "geometry": {"coordinates":[-2.340758,53.602564],"type":"Point"}
}
