{
  "type": "Feature",
  "properties": {
    "date:inception_lower": "1987-04-01",
    "date:inception_upper": "1987-04-01",
    "iso:country": "GB",
    "wof:name": "BL8 3BQ",
    "wof:placetype": "postalcode"
  },
  "geometry": {"coordinates":[-2.340833,53.602528],"type":"Point"}
}
