{
  "type": "Feature",
  "properties": {
    "iso:country": "GB",
    "wof:name": "TF10 7JF",
    "wof:placetype": "postalcode"
  },
  "geometry": {"coordinates":[-2.378351,52.779471],"type":"Point"}
}
