{
  "type": "Feature",
  "properties": {
    "iso:country":"GB",
    "wof:name":"TF10 7JF",
    "wof:placetype":"postalcode"
},
  "geometry": {"coordinates":[-2.3783507370306,52.77947130598388],"type":"Point"}
}