{
  "type": "Feature",
  "properties": {
    "iso:country": "GB",
    "wof:name": "FY4 4PN",
    "wof:placetype": "postalcode"
  },
  "geometry": {"coordinates":[-3.014179,53.79472],"type":"Point"}
}
