{
  "type": "Feature",
  "properties": {
    "iso:country":"GB",
    "wof:name":"TA24 5DQ",
    "wof:placetype":"postalcode"
},
  "geometry": {"coordinates":[-3.47113363312073,51.20247726107086],"type":"Point"}
}