{
  "type": "Feature",
  "properties": {
    "iso:country": "GB",
    "wof:name": "CB4 1AX",
    "wof:placetype": "postalcode"
  },
  "geometry": {"coordinates":[0.132782,52.217152],"type":"Point"}
}
