{
  "type": "Feature",
  "properties": {
    "iso:country":"GB",
    "wof:name":"CB4 1AX",
    "wof:placetype":"postalcode"
},
  "geometry": {"coordinates":[0.13278221751743,52.21715154459589],"type":"Point"}
}