{
  "type": "Feature",
  "properties": {
    "iso:country":"GB",
    "wof:name":"ME5 0PT",
    "wof:placetype":"postalcode"
},
  "geometry": {"coordinates":[0.51417878204044,51.34599141394583],"type":"Point"}
}