{
  "type": "Feature",
  "properties": {
    "date:inception_lower":"1997-06-01",
    "date:inception_upper":"1997-06-30",
    "iso:country":"GB",
    "wof:name":"SK6 6FT",
    "wof:placetype":"postalcode"
},
  "geometry": {"coordinates":[-2.061871,53.393893],"type":"Point"}
}