{
  "type": "Feature",
  "properties": {
    "iso:country":"GB",
    "wof:name":"SK6 6FT",
    "wof:placetype":"postalcode"
},
  "geometry": {"coordinates":[-2.06187069047129,53.39389322873431],"type":"Point"}
}