{
  "type": "Feature",
  "properties": {
    "iso:country":"GB",
    "wof:name":"E17 7DG",
    "wof:placetype":"postalcode"
},
  "geometry": {"coordinates":[-0.03518386483189,51.58333725190005],"type":"Point"}
}