{
  "type": "Feature",
  "properties": {
    "iso:country": "GB",
    "wof:name": "E17 7DG",
    "wof:placetype": "postalcode"
  },
  "geometry": {"coordinates":[-0.035184,51.583337],"type":"Point"}
}
