{
  "type": "Feature",
  "properties": {
    "iso:country": "GB",
    "wof:name": "NP10 9DN",
    "wof:placetype": "postalcode"
  },
  "geometry": {"coordinates":[-3.036344,51.580636],"type":"Point"}
}
