{
  "type": "Feature",
  "properties": {
    "iso:country":"GB",
    "wof:name":"IP21 5JN",
    "wof:placetype":"postalcode"
},
  "geometry": {"coordinates":[1.27079049002012,52.31442408222574],"type":"Point"}
}