{
  "type": "Feature",
  "properties": {
    "date:inception_lower": "1994-12-01",
    "date:inception_upper": "1994-12-01",
    "iso:country": "GB",
    "wof:name": "WA9 3QQ",
    "wof:placetype": "postalcode"
  },
  "geometry": {"coordinates":[-2.703002,53.436656],"type":"Point"}
}
