{
  "type": "Feature",
  "properties": {
    "iso:country": "GB",
    "wof:name": "CF5 3AE",
    "wof:placetype": "postalcode"
  },
  "geometry": {"coordinates":[-3.232259,51.488383],"type":"Point"}
}
