{
  "type": "Feature",
  "properties": {
    "iso:country": "GB",
    "wof:name": "HP12 3EN",
    "wof:placetype": "postalcode"
  },
  "geometry": {"coordinates":[-0.777503,51.627828],"type":"Point"}
}
