{
  "type": "Feature",
  "properties": {
    "iso:country":"GB",
    "wof:name":"ME19 5PZ",
    "wof:placetype":"postalcode"
},
  "geometry": {"coordinates":[0.42286333149483,51.30142011890356],"type":"Point"}
}