{
  "type": "Feature",
  "properties": {
    "date:inception_lower":"1982-03-01",
    "date:inception_upper":"1982-03-31",
    "iso:country":"GB",
    "wof:name":"ME19 5PZ",
    "wof:placetype":"postalcode"
},
  "geometry": {"coordinates":[0.422863,51.30142],"type":"Point"}
}