{
  "type": "Feature",
  "properties": {
    "iso:country":"GB",
    "wof:name":"DN5 8QP",
    "wof:placetype":"postalcode"
},
  "geometry": {"coordinates":[-1.17703339515226,53.53577565154455],"type":"Point"}
}