{
  "type": "Feature",
  "properties": {
    "iso:country":"GB",
    "wof:name":"RG8 0UX",
    "wof:placetype":"postalcode"
},
  "geometry": {"coordinates":[-1.06950352811561,51.53056254215084],"type":"Point"}
}