{
  "type": "Feature",
  "properties": {
    "date:inception_lower":"1980-01-01",
    "date:inception_upper":"1980-01-31",
    "iso:country":"GB",
    "wof:name":"RG8 0UX",
    "wof:placetype":"postalcode"
},
  "geometry": {"coordinates":[-1.069503,51.530563],"type":"Point"}
}