{
  "type": "Feature",
  "properties": {
    "date:inception_lower":"1980-01-01",
    "date:inception_upper":"1980-01-31",
    "iso:country":"GB",
    "wof:name":"N12 0RX",
    "wof:placetype":"postalcode"
},
  "geometry": {"coordinates":[-0.163258,51.611016],"type":"Point"}
}