{
  "type": "Feature",
  "properties": {
    "iso:country":"GB",
    "wof:name":"N12 0RX",
    "wof:placetype":"postalcode"
},
  "geometry": {"coordinates":[-0.16342849361217,51.6109975890183],"type":"Point"}
}