{
  "type": "Feature",
  "properties": {
    "iso:country":"GB",
    "wof:name":"TN23 4QS",
    "wof:placetype":"postalcode"
},
  "geometry": {"coordinates":[0.85581541612599,51.1412897162399],"type":"Point"}
}