{
  "type": "Feature",
  "properties": {
    "iso:country":"GB",
    "wof:name":"DY9 0HU",
    "wof:placetype":"postalcode"
},
  "geometry": {"coordinates":[-2.15228687633572,52.41043398575607],"type":"Point"}
}