{
  "type": "Feature",
  "properties": {
    "date:inception_lower": "1980-01-01",
    "date:inception_upper": "1980-01-01",
    "iso:country": "GB",
    "wof:name": "DY9 0HU",
    "wof:placetype": "postalcode"
  },
  "geometry": {"coordinates":[-2.152287,52.410434],"type":"Point"}
}
