{
  "type": "Feature",
  "properties": {
    "iso:country": "GB",
    "wof:name": "DY9 0HU",
    "wof:placetype": "postalcode"
  },
  "geometry": {"coordinates":[-2.152287,52.410434],"type":"Point"}
}
