{
  "type": "Feature",
  "properties": {
    "iso:country": "GB",
    "wof:name": "RH11 7ED",
    "wof:placetype": "postalcode"
  },
  "geometry": {"coordinates":[-0.193523,51.119737],"type":"Point"}
}
