{
  "type": "Feature",
  "properties": {
    "iso:country": "GB",
    "wof:name": "BN13 3UH",
    "wof:placetype": "postalcode"
  },
  "geometry": {"coordinates":[-0.464044,50.840695],"type":"Point"}
}
