{
  "type": "Feature",
  "properties": {
    "iso:country": "GB",
    "wof:name": "SG12 0SL",
    "wof:placetype": "postalcode"
  },
  "geometry": {"coordinates":[-0.02841,51.834075],"type":"Point"}
}
