{
  "type": "Feature",
  "properties": {
    "iso:country":"GB",
    "wof:name":"SG12 0SL",
    "wof:placetype":"postalcode"
},
  "geometry": {"coordinates":[-0.02841030911784,51.83407488324337],"type":"Point"}
}