{
  "type": "Feature",
  "properties": {
    "iso:country":"GB",
    "wof:name":"B90 4EZ",
    "wof:placetype":"postalcode"
},
  "geometry": {"coordinates":[-1.8135619560613,52.37919916746296],"type":"Point"}
}