{
  "type": "Feature",
  "properties": {
    "date:inception_lower": "1987-04-01",
    "date:inception_upper": "1987-04-01",
    "iso:country": "GB",
    "wof:name": "TS24 7JB",
    "wof:placetype": "postalcode"
  },
  "geometry": {"coordinates":[-1.206416,54.68203],"type":"Point"}
}
