{
  "type": "Feature",
  "properties": {
    "iso:country":"GB",
    "wof:name":"M22 4QT",
    "wof:placetype":"postalcode"
},
  "geometry": {"coordinates":[-2.25234002942017,53.38930071364876],"type":"Point"}
}