{
  "type": "Feature",
  "properties": {
    "iso:country": "GB",
    "wof:name": "M22 4QT",
    "wof:placetype": "postalcode"
  },
  "geometry": {"coordinates":[-2.25234,53.389301],"type":"Point"}
}
