{
  "type": "Feature",
  "properties": {
    "iso:country":"GB",
    "wof:name":"SA70 8PG",
    "wof:placetype":"postalcode"
},
  "geometry": {"coordinates":[-4.83810268695335,51.6908753357643],"type":"Point"}
}