{
  "type": "Feature",
  "properties": {
    "iso:country": "GB",
    "wof:name": "N10 1BW",
    "wof:placetype": "postalcode"
  },
  "geometry": {"coordinates":[-0.143558,51.592502],"type":"Point"}
}
