{
  "type": "Feature",
  "properties": {
    "iso:country":"GB",
    "wof:name":"LE9 7EE",
    "wof:placetype":"postalcode"
},
  "geometry": {"coordinates":[-1.30814306726221,52.58115568989206],"type":"Point"}
}