{
  "type": "Feature",
  "properties": {
    "iso:country":"GB",
    "wof:name":"ST13 6EB",
    "wof:placetype":"postalcode"
},
  "geometry": {"coordinates":[-2.02194731024071,53.10728198247633],"type":"Point"}
}