{
  "type": "Feature",
  "properties": {
    "iso:country": "GB",
    "wof:name": "EX33 2BS",
    "wof:placetype": "postalcode"
  },
  "geometry": {"coordinates":[-4.158174,51.105185],"type":"Point"}
}
