{
  "type": "Feature",
  "properties": {
    "date:inception_lower":"2006-02-01",
    "date:inception_upper":"2006-02-28",
    "iso:country":"GB",
    "wof:name":"BA4 5WW",
    "wof:placetype":"postalcode"
},
  "geometry": {"coordinates":[-2.557092,51.188317],"type":"Point"}
}