{
  "type": "Feature",
  "properties": {
    "iso:country":"GB",
    "wof:name":"BA4 5WW",
    "wof:placetype":"postalcode"
},
  "geometry": {"coordinates":[-2.55709236205956,51.18831676479387],"type":"Point"}
}