{
  "type": "Feature",
  "properties": {
    "iso:country":"GB",
    "wof:name":"TN2 5PG",
    "wof:placetype":"postalcode"
},
  "geometry": {"coordinates":[0.2499975506757,51.11805049208763],"type":"Point"}
}