{
  "type": "Feature",
  "properties": {
    "date:inception_lower": "1980-01-01",
    "date:inception_upper": "1980-01-01",
    "iso:country": "GB",
    "wof:name": "TN2 5PG",
    "wof:placetype": "postalcode"
  },
  "geometry": {"coordinates":[0.249998,51.11805],"type":"Point"}
}
