{
  "type": "Feature",
  "properties": {
    "iso:country":"GB",
    "wof:name":"L21 9LU",
    "wof:placetype":"postalcode"
},
  "geometry": {"coordinates":[-3.00583793864992,53.47216171067283],"type":"Point"}
}