{
  "type": "Feature",
  "properties": {
    "date:inception_lower":"1980-01-01",
    "date:inception_upper":"1980-01-31",
    "iso:country":"GB",
    "wof:name":"L21 9LU",
    "wof:placetype":"postalcode"
},
  "geometry": {"coordinates":[-3.005838,53.472162],"type":"Point"}
}