{
  "type": "Feature",
  "properties": {
    "iso:country": "GB",
    "wof:name": "NN17 1JA",
    "wof:placetype": "postalcode"
  },
  "geometry": {"coordinates":[-0.701433,52.495701],"type":"Point"}
}
