{
  "type": "Feature",
  "properties": {
    "iso:country": "GB",
    "wof:name": "CW7 1SX",
    "wof:placetype": "postalcode"
  },
  "geometry": {"coordinates":[-2.530872,53.175486],"type":"Point"}
}
