{
  "type": "Feature",
  "properties": {
    "iso:country":"GB",
    "wof:name":"DN10 6AF",
    "wof:placetype":"postalcode"
},
  "geometry": {"coordinates":[-1.0218078749149,53.41110945131708],"type":"Point"}
}