{
  "type": "Feature",
  "properties": {
    "date:inception_lower": "1980-01-01",
    "date:inception_upper": "1980-01-01",
    "iso:country": "GB",
    "wof:name": "GU3 3HW",
    "wof:placetype": "postalcode"
  },
  "geometry": {"coordinates":[-0.60006,51.260711],"type":"Point"}
}
