{
  "type": "Feature",
  "properties": {
    "iso:country":"GB",
    "wof:name":"GU3 3HW",
    "wof:placetype":"postalcode"
},
  "geometry": {"coordinates":[-0.60005984758682,51.26071117674763],"type":"Point"}
}