{
  "type": "Feature",
  "properties": {
    "iso:country":"GB",
    "wof:name":"SL4 1TB",
    "wof:placetype":"postalcode"
},
  "geometry": {"coordinates":[-0.61509019011493,51.4818112691069],"type":"Point"}
}