{
  "type": "Feature",
  "properties": {
    "iso:country":"GB",
    "wof:name":"TN6 3AW",
    "wof:placetype":"postalcode"
},
  "geometry": {"coordinates":[0.16872051537537,51.04265647617125],"type":"Point"}
}