{
  "type": "Feature",
  "properties": {
    "iso:country": "GB",
    "wof:name": "TN6 3AW",
    "wof:placetype": "postalcode"
  },
  "geometry": {"coordinates":[0.168748,51.042645],"type":"Point"}
}
