{
  "type": "Feature",
  "properties": {
    "iso:country": "GB",
    "wof:name": "NR5 8TE",
    "wof:placetype": "postalcode"
  },
  "geometry": {"coordinates":[1.237691,52.6399],"type":"Point"}
}
