{
  "type": "Feature",
  "properties": {
    "iso:country":"GB",
    "wof:name":"NR5 8TE",
    "wof:placetype":"postalcode"
},
  "geometry": {"coordinates":[1.23769098159096,52.63990013433165],"type":"Point"}
}