{
  "type": "Feature",
  "properties": {
    "iso:country":"GB",
    "wof:name":"BB12 0QZ",
    "wof:placetype":"postalcode"
},
  "geometry": {"coordinates":[-2.25249565916153,53.79272196471818],"type":"Point"}
}