{
  "type": "Feature",
  "properties": {
    "date:inception_lower": "1980-01-01",
    "date:inception_upper": "1980-01-01",
    "iso:country": "GB",
    "wof:name": "BB12 0QZ",
    "wof:placetype": "postalcode"
  },
  "geometry": {"coordinates":[-2.252496,53.792736],"type":"Point"}
}
