{
  "type": "Feature",
  "properties": {
    "date:inception_lower": "2023-07-01",
    "date:inception_upper": "2023-07-01",
    "iso:country": "GB",
    "wof:name": "CV23 1DN",
    "wof:placetype": "postalcode"
  },
  "geometry": {"coordinates":[-1.203012,52.37051],"type":"Point"}
}
