{
  "type": "Feature",
  "properties": {
    "iso:country":"GB",
    "wof:name":"YO42 2EY",
    "wof:placetype":"postalcode"
},
  "geometry": {"coordinates":[-0.78962536731177,53.9345899608762],"type":"Point"}
}