{
  "type": "Feature",
  "properties": {
    "iso:country":"GB",
    "wof:name":"RH4 1HD",
    "wof:placetype":"postalcode"
},
  "geometry": {"coordinates":[-0.33682635810755,51.23584679077184],"type":"Point"}
}