{
  "type": "Feature",
  "properties": {
    "iso:country": "GB",
    "wof:name": "RH4 1HD",
    "wof:placetype": "postalcode"
  },
  "geometry": {"coordinates":[-0.336826,51.235847],"type":"Point"}
}
