{
  "type": "Feature",
  "properties": {
    "iso:country":"GB",
    "wof:name":"KY9 1HY",
    "wof:placetype":"postalcode"
},
  "geometry": {"coordinates":[-2.86300836591033,56.25660515777133],"type":"Point"}
}