{
  "type": "Feature",
  "properties": {
    "date:inception_lower": "1996-06-01",
    "date:inception_upper": "1996-06-01",
    "iso:country": "GB",
    "wof:name": "BS4 2DQ",
    "wof:placetype": "postalcode"
  },
  "geometry": {"coordinates":[-2.579034,51.434884],"type":"Point"}
}
