{
  "type": "Feature",
  "properties": {
    "date:inception_lower":"2013-08-01",
    "date:inception_upper":"2013-08-31",
    "iso:country":"GB",
    "wof:name":"LL14 5DH",
    "wof:placetype":"postalcode"
},
  "geometry": {"coordinates":[-3.055161,52.932766],"type":"Point"}
}