{
  "type": "Feature",
  "properties": {
    "iso:country":"GB",
    "wof:name":"LL14 5DH",
    "wof:placetype":"postalcode"
},
  "geometry": {"coordinates":[-3.05516111730006,52.93276558927319],"type":"Point"}
}