{
  "type": "Feature",
  "properties": {
    "iso:country": "GB",
    "wof:name": "LL14 5DH",
    "wof:placetype": "postalcode"
  },
  "geometry": {"coordinates":[-3.055161,52.932766],"type":"Point"}
}
