{
  "type": "Feature",
  "properties": {
    "iso:country":"GB",
    "wof:name":"LE11 5DH",
    "wof:placetype":"postalcode"
},
  "geometry": {"coordinates":[-1.21884264193192,52.77512343738162],"type":"Point"}
}