{
  "type": "Feature",
  "properties": {
    "iso:country":"GB",
    "wof:name":"OL11 3TW",
    "wof:placetype":"postalcode"
},
  "geometry": {"coordinates":[-2.16108820025961,53.60813810844945],"type":"Point"}
}