{
  "type": "Feature",
  "properties": {
    "iso:country": "GB",
    "wof:name": "ME10 4QZ",
    "wof:placetype": "postalcode"
  },
  "geometry": {"coordinates":[0.733324,51.329739],"type":"Point"}
}
