{
  "type": "Feature",
  "properties": {
    "date:inception_lower": "2023-01-01",
    "date:inception_upper": "2023-01-01",
    "iso:country": "GB",
    "wof:name": "W3 6GF",
    "wof:placetype": "postalcode"
  },
  "geometry": {"coordinates":[-0.265965,51.516926],"type":"Point"}
}
