{
  "type": "Feature",
  "properties": {
    "iso:country":"GB",
    "wof:name":"L14 9QD",
    "wof:placetype":"postalcode"
},
  "geometry": {"coordinates":[-2.87229857087498,53.4260832315932],"type":"Point"}
}