{
  "type": "Feature",
  "properties": {
    "iso:country":"GB",
    "wof:name":"LA3 2WD",
    "wof:placetype":"postalcode"
},
  "geometry": {"coordinates":[-2.89248129989527,54.03713508133178],"type":"Point"}
}