{
  "type": "Feature",
  "properties": {
    "date:inception_lower": "1980-01-01",
    "date:inception_upper": "1980-01-01",
    "iso:country": "GB",
    "wof:name": "SL8 5DH",
    "wof:placetype": "postalcode"
  },
  "geometry": {"coordinates":[-0.709829,51.573386],"type":"Point"}
}
