{
  "type": "Feature",
  "properties": {
    "iso:country":"GB",
    "wof:name":"SL8 5DH",
    "wof:placetype":"postalcode"
},
  "geometry": {"coordinates":[-0.70982868092553,51.5733864947759],"type":"Point"}
}