{
  "type": "Feature",
  "properties": {
    "iso:country":"GB",
    "wof:name":"WA13 9PS",
    "wof:placetype":"postalcode"
},
  "geometry": {"coordinates":[-2.47031867270046,53.38527881913441],"type":"Point"}
}