{
  "type": "Feature",
  "properties": {
    "iso:country":"GB",
    "wof:name":"ME7 1NG",
    "wof:placetype":"postalcode"
},
  "geometry": {"coordinates":[0.54561752684243,51.39317616726359],"type":"Point"}
}