{
  "type": "Feature",
  "properties": {
    "iso:country":"GB",
    "wof:name":"NP7 8PP",
    "wof:placetype":"postalcode"
},
  "geometry": {"coordinates":[-2.86483460747393,51.8704769036102],"type":"Point"}
}