{
  "type": "Feature",
  "properties": {
    "iso:country": "GB",
    "wof:name": "TN15 0SB",
    "wof:placetype": "postalcode"
  },
  "geometry": {"coordinates":[0.229122,51.246228],"type":"Point"}
}
