{
  "type": "Feature",
  "properties": {
    "date:inception_lower":"1980-01-01",
    "date:inception_upper":"1980-01-31",
    "iso:country":"GB",
    "wof:name":"TN15 0SB",
    "wof:placetype":"postalcode"
},
  "geometry": {"coordinates":[0.229122,51.246228],"type":"Point"}
}