{
  "type": "Feature",
  "properties": {
    "iso:country": "GB",
    "wof:name": "CO11 2HP",
    "wof:placetype": "postalcode"
  },
  "geometry": {"coordinates":[1.061784,51.94237],"type":"Point"}
}
