{
  "type": "Feature",
  "properties": {
    "iso:country":"GB",
    "wof:name":"CO11 2HP",
    "wof:placetype":"postalcode"
},
  "geometry": {"coordinates":[1.0617843169549,51.94236966162659],"type":"Point"}
}