{
  "type": "Feature",
  "properties": {
    "date:inception_lower": "1982-03-01",
    "date:inception_upper": "1982-03-01",
    "iso:country": "GB",
    "wof:name": "CO11 2HP",
    "wof:placetype": "postalcode"
  },
  "geometry": {"coordinates":[1.061784,51.94237],"type":"Point"}
}
