{
  "type": "Feature",
  "properties": {
    "iso:country":"GB",
    "wof:name":"RH7 6RH",
    "wof:placetype":"postalcode"
},
  "geometry": {"coordinates":[0.00938968622409,51.15739013880707],"type":"Point"}
}