{
  "type": "Feature",
  "properties": {
    "iso:country": "GB",
    "wof:name": "RH7 6RH",
    "wof:placetype": "postalcode"
  },
  "geometry": {"coordinates":[0.00939,51.15739],"type":"Point"}
}
