{
  "type": "Feature",
  "properties": {
    "iso:country": "GB",
    "wof:name": "YO21 3NN",
    "wof:placetype": "postalcode"
  },
  "geometry": {"coordinates":[-0.638391,54.484977],"type":"Point"}
}
