{
  "type": "Feature",
  "properties": {
    "date:inception_lower": "1990-02-01",
    "date:inception_upper": "1990-02-01",
    "iso:country": "GB",
    "wof:name": "YO21 3NN",
    "wof:placetype": "postalcode"
  },
  "geometry": {"coordinates":[-0.638391,54.484977],"type":"Point"}
}
