{
  "type": "Feature",
  "properties": {
    "iso:country":"GB",
    "wof:name":"YO21 3NN",
    "wof:placetype":"postalcode"
},
  "geometry": {"coordinates":[-0.63839095997244,54.48497728805317],"type":"Point"}
}