{
  "type": "Feature",
  "properties": {
    "date:inception_lower": "1980-01-01",
    "date:inception_upper": "1980-01-01",
    "iso:country": "GB",
    "wof:name": "G5 0TY",
    "wof:placetype": "postalcode"
  },
  "geometry": {"coordinates":[-4.248976,55.841408],"type":"Point"}
}
