{
  "type": "Feature",
  "properties": {
    "iso:country":"GB",
    "wof:name":"G5 0TY",
    "wof:placetype":"postalcode"
},
  "geometry": {"coordinates":[-4.24897630839686,55.84140810101863],"type":"Point"}
}