{
  "type": "Feature",
  "properties": {
    "iso:country":"GB",
    "wof:name":"AL1 5FX",
    "wof:placetype":"postalcode"
},
  "geometry": {"coordinates":[-0.30571361138881,51.74601357038538],"type":"Point"}
}