{
  "type": "Feature",
  "properties": {
    "iso:country": "GB",
    "wof:name": "AL1 5FX",
    "wof:placetype": "postalcode"
  },
  "geometry": {"coordinates":[-0.305706,51.745974],"type":"Point"}
}
