{
  "type": "Feature",
  "properties": {
    "iso:country":"GB",
    "wof:name":"OX33 1DA",
    "wof:placetype":"postalcode"
},
  "geometry": {"coordinates":[-1.12017624348528,51.81501996167157],"type":"Point"}
}