{
  "type": "Feature",
  "properties": {
    "iso:country": "GB",
    "wof:name": "OX33 1DA",
    "wof:placetype": "postalcode"
  },
  "geometry": {"coordinates":[-1.120176,51.81502],"type":"Point"}
}
