{
  "type": "Feature",
  "properties": {
    "iso:country": "GB",
    "wof:name": "SR6 7UX",
    "wof:placetype": "postalcode"
  },
  "geometry": {"coordinates":[-1.393114,54.95498],"type":"Point"}
}
