{
  "type": "Feature",
  "properties": {
    "iso:country":"GB",
    "wof:name":"SR6 7UX",
    "wof:placetype":"postalcode"
},
  "geometry": {"coordinates":[-1.39311423135744,54.95497970468291],"type":"Point"}
}