{
  "type": "Feature",
  "properties": {
    "iso:country":"GB",
    "wof:name":"SE6 3JX",
    "wof:placetype":"postalcode"
},
  "geometry": {"coordinates":[-0.02574003673397,51.43641875601745],"type":"Point"}
}