{
  "type": "Feature",
  "properties": {
    "date:inception_lower": "1980-01-01",
    "date:inception_upper": "1980-01-01",
    "iso:country": "GB",
    "wof:name": "WR6 5TD",
    "wof:placetype": "postalcode"
  },
  "geometry": {"coordinates":[-2.473623,52.186896],"type":"Point"}
}
