{
  "type": "Feature",
  "properties": {
    "iso:country": "GB",
    "wof:name": "WR6 5TD",
    "wof:placetype": "postalcode"
  },
  "geometry": {"coordinates":[-2.473611,52.186902],"type":"Point"}
}
