{
  "type": "Feature",
  "properties": {
    "iso:country":"GB",
    "wof:name":"WR6 5TD",
    "wof:placetype":"postalcode"
},
  "geometry": {"coordinates":[-2.47361059545173,52.18690172193049],"type":"Point"}
}