{
  "type": "Feature",
  "properties": {
    "iso:country":"GB",
    "wof:name":"DT6 6JH",
    "wof:placetype":"postalcode"
},
  "geometry": {"coordinates":[-2.8171621966352,50.73249736380893],"type":"Point"}
}