{
  "type": "Feature",
  "properties": {
    "iso:country": "GB",
    "wof:name": "DT6 6JH",
    "wof:placetype": "postalcode"
  },
  "geometry": {"coordinates":[-2.817206,50.732486],"type":"Point"}
}
