{
  "type": "Feature",
  "properties": {
    "iso:country":"GB",
    "wof:name":"HA0 4SE",
    "wof:placetype":"postalcode"
},
  "geometry": {"coordinates":[-0.29934791605901,51.54725817232666],"type":"Point"}
}