{
  "type": "Feature",
  "properties": {
    "date:inception_lower": "2019-04-01",
    "date:inception_upper": "2019-04-01",
    "iso:country": "GB",
    "wof:name": "ML1 5UX",
    "wof:placetype": "postalcode"
  },
  "geometry": {"coordinates":[-3.951244,55.818737],"type":"Point"}
}
