{
  "type": "Feature",
  "properties": {
    "iso:country":"GB",
    "wof:name":"DN8 5JY",
    "wof:placetype":"postalcode"
},
  "geometry": {"coordinates":[-0.9541695038037,53.6107804676131],"type":"Point"}
}