{
  "type": "Feature",
  "properties": {
    "iso:country": "GB",
    "wof:name": "DN8 5JY",
    "wof:placetype": "postalcode"
  },
  "geometry": {"coordinates":[-0.954169,53.61078],"type":"Point"}
}
