{
  "type": "Feature",
  "properties": {
    "iso:country": "GB",
    "wof:name": "WD23 4GS",
    "wof:placetype": "postalcode"
  },
  "geometry": {"coordinates":[-0.33578,51.641245],"type":"Point"}
}
