{
  "type": "Feature",
  "properties": {
    "iso:country":"GB",
    "wof:name":"WD23 4GS",
    "wof:placetype":"postalcode"
},
  "geometry": {"coordinates":[-0.33578007057714,51.64124529994279],"type":"Point"}
}