{
  "type": "Feature",
  "properties": {
    "iso:country": "GB",
    "wof:name": "SG6 4DF",
    "wof:placetype": "postalcode"
  },
  "geometry": {"coordinates":[-0.234926,51.982979],"type":"Point"}
}
