{
  "type": "Feature",
  "properties": {
    "iso:country":"GB",
    "wof:name":"SG6 4DF",
    "wof:placetype":"postalcode"
},
  "geometry": {"coordinates":[-0.23492641269999,51.98297864591496],"type":"Point"}
}