{
  "type": "Feature",
  "properties": {
    "date:inception_lower":"1992-08-01",
    "date:inception_upper":"1992-08-31",
    "iso:country":"GB",
    "wof:name":"AL3 8JH",
    "wof:placetype":"postalcode"
},
  "geometry": {"coordinates":[-0.4573,51.835581],"type":"Point"}
}