{
  "type": "Feature",
  "properties": {
    "iso:country":"GB",
    "wof:name":"AL3 8JH",
    "wof:placetype":"postalcode"
},
  "geometry": {"coordinates":[-0.45673245935983,51.83546669978742],"type":"Point"}
}