{
  "type": "Feature",
  "properties": {
    "iso:country":"GB",
    "wof:name":"DT2 0QL",
    "wof:placetype":"postalcode"
},
  "geometry": {"coordinates":[-2.5837276535047,50.75613913853915],"type":"Point"}
}