{
  "type": "Feature",
  "properties": {
    "iso:country": "GB",
    "wof:name": "CO5 9QH",
    "wof:placetype": "postalcode"
  },
  "geometry": {"coordinates":[0.717553,51.850271],"type":"Point"}
}
