{
  "type": "Feature",
  "properties": {
    "iso:country":"GB",
    "wof:name":"CO5 9QH",
    "wof:placetype":"postalcode"
},
  "geometry": {"coordinates":[0.71755321973909,51.85027060969072],"type":"Point"}
}