{
  "type": "Feature",
  "properties": {
    "iso:country":"GB",
    "wof:name":"WD3 5NS",
    "wof:placetype":"postalcode"
},
  "geometry": {"coordinates":[-0.52577373043087,51.65041126415638],"type":"Point"}
}