{
  "type": "Feature",
  "properties": {
    "iso:country":"GB",
    "wof:name":"PO9 5QX",
    "wof:placetype":"postalcode"
},
  "geometry": {"coordinates":[-0.96541735105919,50.8691209939394],"type":"Point"}
}