{
  "type": "Feature",
  "properties": {
    "iso:country":"GB",
    "wof:name":"MK2 3QQ",
    "wof:placetype":"postalcode"
},
  "geometry": {"coordinates":[-0.72834687447178,51.98115769601249],"type":"Point"}
}