{
  "type": "Feature",
  "properties": {
    "iso:country":"GB",
    "wof:name":"NW10 9DS",
    "wof:placetype":"postalcode"
},
  "geometry": {"coordinates":[-0.25333677069327,51.54583586204976],"type":"Point"}
}