{
  "type": "Feature",
  "properties": {
    "date:inception_lower":"1980-01-01",
    "date:inception_upper":"1980-01-31",
    "iso:country":"GB",
    "wof:name":"WF8 2DB",
    "wof:placetype":"postalcode"
},
  "geometry": {"coordinates":[-1.294249,53.685679],"type":"Point"}
}