{
  "type": "Feature",
  "properties": {
    "date:inception_lower": "1980-01-01",
    "date:inception_upper": "1980-01-01",
    "iso:country": "GB",
    "wof:name": "DY9 0LL",
    "wof:placetype": "postalcode"
  },
  "geometry": {"coordinates":[-2.14809,52.417092],"type":"Point"}
}
