{
  "type": "Feature",
  "properties": {
    "iso:country":"GB",
    "wof:name":"NP12 0HT",
    "wof:placetype":"postalcode"
},
  "geometry": {"coordinates":[-3.1836748225241,51.68854512287646],"type":"Point"}
}