{
  "type": "Feature",
  "properties": {
    "iso:country":"GB",
    "wof:name":"WN2 5XT",
    "wof:placetype":"postalcode"
},
  "geometry": {"coordinates":[-2.59038611099479,53.50467147173338],"type":"Point"}
}