{
  "type": "Feature",
  "properties": {
    "date:inception_lower": "1980-01-01",
    "date:inception_upper": "1980-01-01",
    "iso:country": "GB",
    "wof:name": "HP5 2DA",
    "wof:placetype": "postalcode"
  },
  "geometry": {"coordinates":[-0.616857,51.721502],"type":"Point"}
}
