{
  "type": "Feature",
  "properties": {
    "iso:country": "GB",
    "wof:name": "PE27 5NN",
    "wof:placetype": "postalcode"
  },
  "geometry": {"coordinates":[-0.069851,52.330948],"type":"Point"}
}
