{
  "type": "Feature",
  "properties": {
    "iso:country":"GB",
    "wof:name":"PL18 9RD",
    "wof:placetype":"postalcode"
},
  "geometry": {"coordinates":[-4.21243913698283,50.49833248611991],"type":"Point"}
}