{
  "type": "Feature",
  "properties": {
    "date:inception_lower":"1980-01-01",
    "date:inception_upper":"1980-01-31",
    "iso:country":"GB",
    "wof:name":"PL18 9RD",
    "wof:placetype":"postalcode"
},
  "geometry": {"coordinates":[-4.212555,50.498346],"type":"Point"}
}