{
  "type": "Feature",
  "properties": {
    "iso:country":"GB",
    "wof:name":"SP4 6DP",
    "wof:placetype":"postalcode"
},
  "geometry": {"coordinates":[-1.763882488094,51.09599730124368],"type":"Point"}
}