{
  "type": "Feature",
  "properties": {
    "iso:country": "GB",
    "wof:name": "SP4 6DP",
    "wof:placetype": "postalcode"
  },
  "geometry": {"coordinates":[-1.763882,51.095997],"type":"Point"}
}
