{
  "type": "Feature",
  "properties": {
    "iso:country": "GB",
    "wof:name": "DH6 2TF",
    "wof:placetype": "postalcode"
  },
  "geometry": {"coordinates":[-1.408077,54.799425],"type":"Point"}
}
