{
  "type": "Feature",
  "properties": {
    "iso:country":"GB",
    "wof:name":"DH6 2TF",
    "wof:placetype":"postalcode"
},
  "geometry": {"coordinates":[-1.40807666790629,54.79942524511097],"type":"Point"}
}