{
  "type": "Feature",
  "properties": {
    "date:inception_lower":"2004-09-01",
    "date:inception_upper":"2004-09-30",
    "iso:country":"GB",
    "wof:name":"DH6 2TF",
    "wof:placetype":"postalcode"
},
  "geometry": {"coordinates":[-1.408077,54.799425],"type":"Point"}
}