{
  "type": "Feature",
  "properties": {
    "date:inception_lower": "2021-11-01",
    "date:inception_upper": "2021-11-01",
    "iso:country": "GB",
    "wof:name": "WS3 1FR",
    "wof:placetype": "postalcode"
  },
  "geometry": {"coordinates":[-1.979494,52.618222],"type":"Point"}
}
