{
  "type": "Feature",
  "properties": {
    "iso:country": "GB",
    "wof:name": "GU9 8DY",
    "wof:placetype": "postalcode"
  },
  "geometry": {"coordinates":[-0.785965,51.209372],"type":"Point"}
}
