{
  "type": "Feature",
  "properties": {
    "iso:country": "GB",
    "wof:name": "WA9 1DY",
    "wof:placetype": "postalcode"
  },
  "geometry": {"coordinates":[-2.71913,53.45665],"type":"Point"}
}
