{
  "type": "Feature",
  "properties": {
    "iso:country": "GB",
    "wof:name": "DT3 6EW",
    "wof:placetype": "postalcode"
  },
  "geometry": {"coordinates":[-2.392522,50.648793],"type":"Point"}
}
