{
  "type": "Feature",
  "properties": {
    "iso:country":"GB",
    "wof:name":"DT3 6EW",
    "wof:placetype":"postalcode"
},
  "geometry": {"coordinates":[-2.39252197699332,50.64879314478864],"type":"Point"}
}