{
  "type": "Feature",
  "properties": {
    "iso:country":"GB",
    "wof:name":"NR32 2QB",
    "wof:placetype":"postalcode"
},
  "geometry": {"coordinates":[1.72769654321583,52.47978290988453],"type":"Point"}
}