{
  "type": "Feature",
  "properties": {
    "date:inception_lower": "2022-09-01",
    "date:inception_upper": "2022-09-01",
    "iso:country": "GB",
    "wof:name": "IV31 6GP",
    "wof:placetype": "postalcode"
  },
  "geometry": {"coordinates":[-3.30004,57.708128],"type":"Point"}
}
