{
  "type": "Feature",
  "properties": {
    "iso:country": "GB",
    "wof:name": "KT10 0ND",
    "wof:placetype": "postalcode"
  },
  "geometry": {"coordinates":[-0.339495,51.356592],"type":"Point"}
}
