{
  "type": "Feature",
  "properties": {
    "iso:country":"GB",
    "wof:name":"KT10 0ND",
    "wof:placetype":"postalcode"
},
  "geometry": {"coordinates":[-0.33949487960115,51.35659232631313],"type":"Point"}
}