{
  "type": "Feature",
  "properties": {
    "iso:country": "GB",
    "wof:name": "L11 2SJ",
    "wof:placetype": "postalcode"
  },
  "geometry": {"coordinates":[-2.911563,53.447875],"type":"Point"}
}
