{
  "type": "Feature",
  "properties": {
    "iso:country":"GB",
    "wof:name":"L11 2SJ",
    "wof:placetype":"postalcode"
},
  "geometry": {"coordinates":[-2.91156255026896,53.44787548963201],"type":"Point"}
}