{
  "type": "Feature",
  "properties": {
    "iso:country":"GB",
    "wof:name":"CH8 7HU",
    "wof:placetype":"postalcode"
},
  "geometry": {"coordinates":[-3.20601688377354,53.27786842274794],"type":"Point"}
}