{
  "type": "Feature",
  "properties": {
    "date:inception_lower": "1980-01-01",
    "date:inception_upper": "1980-01-01",
    "iso:country": "GB",
    "wof:name": "CH8 7HU",
    "wof:placetype": "postalcode"
  },
  "geometry": {"coordinates":[-3.206017,53.277868],"type":"Point"}
}
