{
  "type": "Feature",
  "properties": {
    "date:inception_lower": "1980-01-01",
    "date:inception_upper": "1980-01-01",
    "iso:country": "GB",
    "wof:name": "CW9 5NP",
    "wof:placetype": "postalcode"
  },
  "geometry": {"coordinates":[-2.5073,53.262233],"type":"Point"}
}
