{
  "type": "Feature",
  "properties": {
    "iso:country":"GB",
    "wof:name":"CW9 5NP",
    "wof:placetype":"postalcode"
},
  "geometry": {"coordinates":[-2.50730018701321,53.26223282172475],"type":"Point"}
}