{
  "type": "Feature",
  "properties": {
    "iso:country":"GB",
    "wof:name":"NG7 6LH",
    "wof:placetype":"postalcode"
},
  "geometry": {"coordinates":[-1.16043731866342,52.96827118932922],"type":"Point"}
}