{
  "type": "Feature",
  "properties": {
    "date:inception_lower":"1980-01-01",
    "date:inception_upper":"1980-01-31",
    "iso:country":"GB",
    "wof:name":"NG7 6LH",
    "wof:placetype":"postalcode"
},
  "geometry": {"coordinates":[-1.160405,52.968246],"type":"Point"}
}