{
  "type": "Feature",
  "properties": {
    "iso:country": "GB",
    "wof:name": "BS32 4AU",
    "wof:placetype": "postalcode"
  },
  "geometry": {"coordinates":[-2.561113,51.546619],"type":"Point"}
}
