{
  "type": "Feature",
  "properties": {
    "date:inception_lower": "1980-01-01",
    "date:inception_upper": "1980-01-01",
    "iso:country": "GB",
    "wof:name": "ME1 2XS",
    "wof:placetype": "postalcode"
  },
  "geometry": {"coordinates":[0.501266,51.362555],"type":"Point"}
}
