{
  "type": "Feature",
  "properties": {
    "iso:country":"GB",
    "wof:name":"ME1 2XS",
    "wof:placetype":"postalcode"
},
  "geometry": {"coordinates":[0.50126593835702,51.36255531634617],"type":"Point"}
}