{
  "type": "Feature",
  "properties": {
    "iso:country":"GB",
    "wof:name":"DY1 3JU",
    "wof:placetype":"postalcode"
},
  "geometry": {"coordinates":[-2.09494008598052,52.52031570387083],"type":"Point"}
}