{
  "type": "Feature",
  "properties": {
    "iso:country":"GB",
    "wof:name":"TS3 0SG",
    "wof:placetype":"postalcode"
},
  "geometry": {"coordinates":[-1.180811098645,54.55386638755121],"type":"Point"}
}