{
  "type": "Feature",
  "properties": {
    "iso:country":"GB",
    "wof:name":"UB10 8HH",
    "wof:placetype":"postalcode"
},
  "geometry": {"coordinates":[-0.4590773655341,51.56599207280456],"type":"Point"}
}