{
  "type": "Feature",
  "properties": {
    "iso:country":"GB",
    "wof:name":"HU10 6SQ",
    "wof:placetype":"postalcode"
},
  "geometry": {"coordinates":[-0.42993008018854,53.74583043639552],"type":"Point"}
}