{
  "type": "Feature",
  "properties": {
    "iso:country":"GB",
    "wof:name":"LE4 7RF",
    "wof:placetype":"postalcode"
},
  "geometry": {"coordinates":[-1.11751606821555,52.65945069501829],"type":"Point"}
}