{
  "type": "Feature",
  "properties": {
    "iso:country":"GB",
    "wof:name":"NW1 5SW",
    "wof:placetype":"postalcode"
},
  "geometry": {"coordinates":[-0.15754023276581,51.52308541173096],"type":"Point"}
}