{
  "type": "Feature",
  "properties": {
    "iso:country": "GB",
    "wof:name": "EH16 5GS",
    "wof:placetype": "postalcode"
  },
  "geometry": {"coordinates":[-3.161844,55.928072],"type":"Point"}
}
