{
  "type": "Feature",
  "properties": {
    "iso:country":"GB",
    "wof:name":"IP26 5HY",
    "wof:placetype":"postalcode"
},
  "geometry": {"coordinates":[0.66463351346517,52.51998098043708],"type":"Point"}
}