{
  "type": "Feature",
  "properties": {
    "date:inception_lower":"2006-09-01",
    "date:inception_upper":"2006-09-30",
    "iso:country":"GB",
    "wof:name":"IP26 5HY",
    "wof:placetype":"postalcode"
},
  "geometry": {"coordinates":[0.664634,52.519981],"type":"Point"}
}