{
  "type": "Feature",
  "properties": {
    "iso:country": "GB",
    "wof:name": "IP26 5HY",
    "wof:placetype": "postalcode"
  },
  "geometry": {"coordinates":[0.664634,52.519981],"type":"Point"}
}
