{
  "type": "Feature",
  "properties": {
    "date:inception_lower": "2006-09-01",
    "date:inception_upper": "2006-09-01",
    "iso:country": "GB",
    "wof:name": "IP26 5HY",
    "wof:placetype": "postalcode"
  },
  "geometry": {"coordinates":[0.664449,52.519753],"type":"Point"}
}
