{
  "type": "Feature",
  "properties": {
    "iso:country":"GB",
    "wof:name":"IP16 4HB",
    "wof:placetype":"postalcode"
},
  "geometry": {"coordinates":[1.57500443450012,52.20975197086363],"type":"Point"}
}