{
  "type": "Feature",
  "properties": {
    "iso:country":"GB",
    "wof:name":"SE13 6TH",
    "wof:placetype":"postalcode"
},
  "geometry": {"coordinates":[-0.0037798627921,51.45003954171248],"type":"Point"}
}