{
  "type": "Feature",
  "properties": {
    "iso:country":"GB",
    "wof:name":"CT5 2AZ",
    "wof:placetype":"postalcode"
},
  "geometry": {"coordinates":[1.05429369524104,51.3635650521192],"type":"Point"}
}