{
  "type": "Feature",
  "properties": {
    "iso:country": "GB",
    "wof:name": "OX12 9LP",
    "wof:placetype": "postalcode"
  },
  "geometry": {"coordinates":[-1.461696,51.563291],"type":"Point"}
}
