{
  "type": "Feature",
  "properties": {
    "date:inception_lower": "1981-09-01",
    "date:inception_upper": "1981-09-01",
    "iso:country": "GB",
    "wof:name": "HR2 7JB",
    "wof:placetype": "postalcode"
  },
  "geometry": {"coordinates":[-2.734917,52.035346],"type":"Point"}
}
