{
  "type": "Feature",
  "properties": {
    "iso:country":"GB",
    "wof:name":"WC2H 9DX",
    "wof:placetype":"postalcode"
},
  "geometry": {"coordinates":[-0.12627116790702,51.51542304920676],"type":"Point"}
}