{
  "type": "Feature",
  "properties": {
    "iso:country": "GB",
    "wof:name": "WC2H 9DX",
    "wof:placetype": "postalcode"
  },
  "geometry": {"coordinates":[-0.126411,51.515247],"type":"Point"}
}
