{
  "type": "Feature",
  "properties": {
    "iso:country": "GB",
    "wof:name": "ME13 7BL",
    "wof:placetype": "postalcode"
  },
  "geometry": {"coordinates":[0.897656,51.320066],"type":"Point"}
}
