{
  "type": "Feature",
  "properties": {
    "iso:country":"GB",
    "wof:name":"ME13 7BL",
    "wof:placetype":"postalcode"
},
  "geometry": {"coordinates":[0.89765639014678,51.32006607124627],"type":"Point"}
}