{
  "type": "Feature",
  "properties": {
    "iso:country": "GB",
    "wof:name": "TR27 4JE",
    "wof:placetype": "postalcode"
  },
  "geometry": {"coordinates":[-5.423079,50.178016],"type":"Point"}
}
