{
  "type": "Feature",
  "properties": {
    "iso:country":"GB",
    "wof:name":"TR27 4JE",
    "wof:placetype":"postalcode"
},
  "geometry": {"coordinates":[-5.42307929830098,50.1780162444072],"type":"Point"}
}