{
  "type": "Feature",
  "properties": {
    "iso:country":"GB",
    "wof:name":"SK5 8JX",
    "wof:placetype":"postalcode"
},
  "geometry": {"coordinates":[-2.13549830796503,53.43278856618029],"type":"Point"}
}