{
  "type": "Feature",
  "properties": {
    "iso:country":"GB",
    "wof:name":"BH9 3LS",
    "wof:placetype":"postalcode"
},
  "geometry": {"coordinates":[-1.86544063425078,50.76104903395392],"type":"Point"}
}