{
  "type": "Feature",
  "properties": {
    "date:inception_lower":"1980-01-01",
    "date:inception_upper":"1980-01-31",
    "iso:country":"GB",
    "wof:name":"AL1 1HA",
    "wof:placetype":"postalcode"
},
  "geometry": {"coordinates":[-0.340406,51.749206],"type":"Point"}
}