{
  "type": "Feature",
  "properties": {
    "iso:country":"GB",
    "wof:name":"AL1 1HA",
    "wof:placetype":"postalcode"
},
  "geometry": {"coordinates":[-0.34040577707706,51.74920616874335],"type":"Point"}
}