{
  "type": "Feature",
  "properties": {
    "iso:country": "GB",
    "wof:name": "SY11 1EX",
    "wof:placetype": "postalcode"
  },
  "geometry": {"coordinates":[-3.047695,52.866928],"type":"Point"}
}
