{
  "type": "Feature",
  "properties": {
    "iso:country": "GB",
    "wof:name": "BD4 8QA",
    "wof:placetype": "postalcode"
  },
  "geometry": {"coordinates":[-1.718825,53.786853],"type":"Point"}
}
