{
  "type": "Feature",
  "properties": {
    "iso:country":"GB",
    "wof:name":"ME1 3GP",
    "wof:placetype":"postalcode"
},
  "geometry": {"coordinates":[0.46002898659984,51.35010043624972],"type":"Point"}
}