{
  "type": "Feature",
  "properties": {
    "date:inception_lower": "2001-12-01",
    "date:inception_upper": "2001-12-01",
    "iso:country": "GB",
    "wof:name": "ME1 3GP",
    "wof:placetype": "postalcode"
  },
  "geometry": {"coordinates":[0.460029,51.3501],"type":"Point"}
}
