{
  "type": "Feature",
  "properties": {
    "iso:country": "GB",
    "wof:name": "ME1 3GP",
    "wof:placetype": "postalcode"
  },
  "geometry": {"coordinates":[0.460029,51.3501],"type":"Point"}
}
