{
  "type": "Feature",
  "properties": {
    "iso:country":"GB",
    "wof:name":"B66 3TA",
    "wof:placetype":"postalcode"
},
  "geometry": {"coordinates":[-1.95220970148553,52.4901922592748],"type":"Point"}
}