{
  "type": "Feature",
  "properties": {
    "iso:country": "GB",
    "wof:name": "NP25 4SD",
    "wof:placetype": "postalcode"
  },
  "geometry": {"coordinates":[-2.722854,51.746116],"type":"Point"}
}
