{
  "type": "Feature",
  "properties": {
    "iso:country":"GB",
    "wof:name":"NP25 4SD",
    "wof:placetype":"postalcode"
},
  "geometry": {"coordinates":[-2.72285417755676,51.74611643248493],"type":"Point"}
}