{
  "type": "Feature",
  "properties": {
    "date:inception_lower": "2014-11-01",
    "date:inception_upper": "2014-11-01",
    "iso:country": "GB",
    "wof:name": "NP25 4SD",
    "wof:placetype": "postalcode"
  },
  "geometry": {"coordinates":[-2.722854,51.746116],"type":"Point"}
}
