{
  "type": "Feature",
  "properties": {
    "date:inception_lower": "1996-06-01",
    "date:inception_upper": "1996-06-01",
    "iso:country": "GB",
    "wof:name": "AB11 8ED",
    "wof:placetype": "postalcode"
  },
  "geometry": {"coordinates":[-2.08903,57.134969],"type":"Point"}
}
