{
  "type": "Feature",
  "properties": {
    "iso:country":"GB",
    "wof:name":"PO8 0DG",
    "wof:placetype":"postalcode"
},
  "geometry": {"coordinates":[-0.99352336774687,50.91153339913768],"type":"Point"}
}