{
  "type": "Feature",
  "properties": {
    "date:inception_lower":"1980-01-01",
    "date:inception_upper":"1980-01-31",
    "iso:country":"GB",
    "wof:name":"PO8 0DG",
    "wof:placetype":"postalcode"
},
  "geometry": {"coordinates":[-0.993523,50.911533],"type":"Point"}
}