{
  "type": "Feature",
  "properties": {
    "iso:country":"GB",
    "wof:name":"CF62 4PT",
    "wof:placetype":"postalcode"
},
  "geometry": {"coordinates":[-3.41754580729485,51.40046745514541],"type":"Point"}
}