{
  "type": "Feature",
  "properties": {
    "date:inception_lower": "1980-01-01",
    "date:inception_upper": "1980-01-01",
    "iso:country": "GB",
    "wof:name": "N3 1XN",
    "wof:placetype": "postalcode"
  },
  "geometry": {"coordinates":[-0.19239,51.602629],"type":"Point"}
}
