{
  "type": "Feature",
  "properties": {
    "iso:country":"GB",
    "wof:name":"N3 1XN",
    "wof:placetype":"postalcode"
},
  "geometry": {"coordinates":[-0.19240135387327,51.60262584969859],"type":"Point"}
}