{
  "type": "Feature",
  "properties": {
    "iso:country":"GB",
    "wof:name":"TN21 9HX",
    "wof:placetype":"postalcode"
},
  "geometry": {"coordinates":[0.31604475178544,50.96363371954512],"type":"Point"}
}