{
  "type": "Feature",
  "properties": {
    "iso:country": "GB",
    "wof:name": "TN21 9HX",
    "wof:placetype": "postalcode"
  },
  "geometry": {"coordinates":[0.316554,50.963836],"type":"Point"}
}
