{
  "type": "Feature",
  "properties": {
    "date:inception_lower": "1980-01-01",
    "date:inception_upper": "1980-01-01",
    "iso:country": "GB",
    "wof:name": "TN21 9HX",
    "wof:placetype": "postalcode"
  },
  "geometry": {"coordinates":[0.316554,50.963836],"type":"Point"}
}
