{
  "type": "Feature",
  "properties": {
    "iso:country":"GB",
    "wof:name":"EH16 6XJ",
    "wof:placetype":"postalcode"
},
  "geometry": {"coordinates":[-3.16285075913452,55.91789569780599],"type":"Point"}
}