{
  "type": "Feature",
  "properties": {
    "iso:country": "GB",
    "wof:name": "WS3 2DJ",
    "wof:placetype": "postalcode"
  },
  "geometry": {"coordinates":[-2.005829,52.613091],"type":"Point"}
}
