{
  "type": "Feature",
  "properties": {
    "date:inception_lower": "1980-01-01",
    "date:inception_upper": "1980-01-01",
    "iso:country": "GB",
    "wof:name": "WS3 2DJ",
    "wof:placetype": "postalcode"
  },
  "geometry": {"coordinates":[-2.005829,52.613019],"type":"Point"}
}
