{
  "type": "Feature",
  "properties": {
    "iso:country":"GB",
    "wof:name":"WS3 2DJ",
    "wof:placetype":"postalcode"
},
  "geometry": {"coordinates":[-2.00583482259811,52.61307489296115],"type":"Point"}
}