{
  "type": "Feature",
  "properties": {
    "date:inception_lower": "1980-01-01",
    "date:inception_upper": "1980-01-01",
    "iso:country": "GB",
    "wof:name": "LE4 0JP",
    "wof:placetype": "postalcode"
  },
  "geometry": {"coordinates":[-1.143269,52.654678],"type":"Point"}
}
