{
  "type": "Feature",
  "properties": {
    "iso:country":"GB",
    "wof:name":"LE4 0JP",
    "wof:placetype":"postalcode"
},
  "geometry": {"coordinates":[-1.14348477338638,52.65457083407026],"type":"Point"}
}