{
  "type": "Feature",
  "properties": {
    "date:inception_lower":"1980-01-01",
    "date:inception_upper":"1980-01-31",
    "iso:country":"GB",
    "wof:name":"LE4 0JP",
    "wof:placetype":"postalcode"
},
  "geometry": {"coordinates":[-1.143223,52.654731],"type":"Point"}
}