{
  "type": "Feature",
  "properties": {
    "iso:country":"GB",
    "wof:name":"LS28 7RT",
    "wof:placetype":"postalcode"
},
  "geometry": {"coordinates":[-1.66679355851487,53.79476417205832],"type":"Point"}
}