{
  "type": "Feature",
  "properties": {
    "iso:country": "GB",
    "wof:name": "YO19 5PX",
    "wof:placetype": "postalcode"
  },
  "geometry": {"coordinates":[-0.982757,53.96491],"type":"Point"}
}
