{
  "type": "Feature",
  "properties": {
    "iso:country":"GB",
    "wof:name":"S5 8GL",
    "wof:placetype":"postalcode"
},
  "geometry": {"coordinates":[-1.49123326310773,53.42195883198141],"type":"Point"}
}