{
  "type": "Feature",
  "properties": {
    "date:inception_lower": "1980-01-01",
    "date:inception_upper": "1980-01-01",
    "iso:country": "GB",
    "wof:name": "LL12 9PY",
    "wof:placetype": "postalcode"
  },
  "geometry": {"coordinates":[-3.034835,53.118237],"type":"Point"}
}
