{
  "type": "Feature",
  "properties": {
    "iso:country": "GB",
    "wof:name": "PE3 7EB",
    "wof:placetype": "postalcode"
  },
  "geometry": {"coordinates":[-0.27075,52.588426],"type":"Point"}
}
