{
  "type": "Feature",
  "properties": {
    "iso:country":"GB",
    "wof:name":"PE3 7EB",
    "wof:placetype":"postalcode"
},
  "geometry": {"coordinates":[-0.27075051304308,52.58842559993761],"type":"Point"}
}