{
  "type": "Feature",
  "properties": {
    "iso:country":"GB",
    "wof:name":"NR12 7ET",
    "wof:placetype":"postalcode"
},
  "geometry": {"coordinates":[1.35149677941664,52.72966481906825],"type":"Point"}
}