{
  "type": "Feature",
  "properties": {
    "iso:country": "GB",
    "wof:name": "NR12 7ET",
    "wof:placetype": "postalcode"
  },
  "geometry": {"coordinates":[1.351497,52.729665],"type":"Point"}
}
