{
  "type": "Feature",
  "properties": {
    "date:inception_lower":"1980-01-01",
    "date:inception_upper":"1980-01-31",
    "iso:country":"GB",
    "wof:name":"NR12 7ET",
    "wof:placetype":"postalcode"
},
  "geometry": {"coordinates":[1.351497,52.729665],"type":"Point"}
}