{
  "type": "Feature",
  "properties": {
    "iso:country": "GB",
    "wof:name": "S20 7LS",
    "wof:placetype": "postalcode"
  },
  "geometry": {"coordinates":[-1.348502,53.335513],"type":"Point"}
}
