{
  "type": "Feature",
  "properties": {
    "iso:country":"GB",
    "wof:name":"S20 7LS",
    "wof:placetype":"postalcode"
},
  "geometry": {"coordinates":[-1.34850162467765,53.33551313695226],"type":"Point"}
}