{
  "type": "Feature",
  "properties": {
    "iso:country":"GB",
    "wof:name":"AB24 5BA",
    "wof:placetype":"postalcode"
},
  "geometry": {"coordinates":[-2.09354589523499,57.15021926479619],"type":"Point"}
}