{
  "type": "Feature",
  "properties": {
    "iso:country":"GB",
    "wof:name":"WR13 6DW",
    "wof:placetype":"postalcode"
},
  "geometry": {"coordinates":[-2.34566118872508,52.06358241258118],"type":"Point"}
}