{
  "type": "Feature",
  "properties": {
    "iso:country":"GB",
    "wof:name":"GU22 8SS",
    "wof:placetype":"postalcode"
},
  "geometry": {"coordinates":[-0.51267611160239,51.32330911931314],"type":"Point"}
}