{
  "type": "Feature",
  "properties": {
    "date:inception_lower": "1990-02-01",
    "date:inception_upper": "1990-02-01",
    "iso:country": "GB",
    "wof:name": "OX11 7QB",
    "wof:placetype": "postalcode"
  },
  "geometry": {"coordinates":[-1.226676,51.610919],"type":"Point"}
}
