{
  "type": "Feature",
  "properties": {
    "iso:country":"GB",
    "wof:name":"OX11 7QB",
    "wof:placetype":"postalcode"
},
  "geometry": {"coordinates":[-1.22667619419629,51.61091892753163],"type":"Point"}
}