{
  "type": "Feature",
  "properties": {
    "iso:country": "GB",
    "wof:name": "CM7 4JA",
    "wof:placetype": "postalcode"
  },
  "geometry": {"coordinates":[0.462042,51.977392],"type":"Point"}
}
