{
  "type": "Feature",
  "properties": {
    "iso:country":"GB",
    "wof:name":"BD20 9HU",
    "wof:placetype":"postalcode"
},
  "geometry": {"coordinates":[-1.96216863333568,53.94154262776544],"type":"Point"}
}