{
  "type": "Feature",
  "properties": {
    "iso:country":"GB",
    "wof:name":"W1J 7UR",
    "wof:placetype":"postalcode"
},
  "geometry": {"coordinates":[-0.14714924673398,51.50669027883522],"type":"Point"}
}