{
  "type": "Feature",
  "properties": {
    "iso:country":"GB",
    "wof:name":"PE6 0LS",
    "wof:placetype":"postalcode"
},
  "geometry": {"coordinates":[-0.13175933869385,52.67246591855359],"type":"Point"}
}