{
  "type": "Feature",
  "properties": {
    "iso:country":"GB",
    "wof:name":"TW8 9QU",
    "wof:placetype":"postalcode"
},
  "geometry": {"coordinates":[-0.29835609068932,51.49650911495104],"type":"Point"}
}