{
  "type": "Feature",
  "properties": {
    "iso:country": "GB",
    "wof:name": "TD9 8ND",
    "wof:placetype": "postalcode"
  },
  "geometry": {"coordinates":[-2.684692,55.459922],"type":"Point"}
}
