{
  "type": "Feature",
  "properties": {
    "iso:country":"GB",
    "wof:name":"TD9 8ND",
    "wof:placetype":"postalcode"
},
  "geometry": {"coordinates":[-2.68469218081154,55.45992233774729],"type":"Point"}
}