{
  "type": "Feature",
  "properties": {
    "iso:country":"GB",
    "wof:name":"CF62 9TP",
    "wof:placetype":"postalcode"
},
  "geometry": {"coordinates":[-3.27223903526697,51.4202634783537],"type":"Point"}
}