{
  "type": "Feature",
  "properties": {
    "iso:country":"GB",
    "wof:name":"S11 7LD",
    "wof:placetype":"postalcode"
},
  "geometry": {"coordinates":[-1.52134902454464,53.36247046541392],"type":"Point"}
}