{
  "type": "Feature",
  "properties": {
    "iso:country": "GB",
    "wof:name": "BS48 3LH",
    "wof:placetype": "postalcode"
  },
  "geometry": {"coordinates":[-2.748967,51.41948],"type":"Point"}
}
