{
  "type": "Feature",
  "properties": {
    "iso:country":"GB",
    "wof:name":"BS48 3LH",
    "wof:placetype":"postalcode"
},
  "geometry": {"coordinates":[-2.74896682043711,51.41948011831298],"type":"Point"}
}