{
  "type": "Feature",
  "properties": {
    "date:inception_lower": "1980-01-01",
    "date:inception_upper": "1980-01-01",
    "iso:country": "GB",
    "wof:name": "HR6 9JP",
    "wof:placetype": "postalcode"
  },
  "geometry": {"coordinates":[-2.927516,52.181329],"type":"Point"}
}
