{
  "type": "Feature",
  "properties": {
    "date:inception_lower": "1980-01-01",
    "date:inception_upper": "1980-01-01",
    "iso:country": "GB",
    "wof:name": "FK7 0LX",
    "wof:placetype": "postalcode"
  },
  "geometry": {"coordinates":[-3.925858,56.090701],"type":"Point"}
}
