{
  "type": "Feature",
  "properties": {
    "iso:country":"GB",
    "wof:name":"S10 5EA",
    "wof:placetype":"postalcode"
},
  "geometry": {"coordinates":[-1.50709868729662,53.37984158390252],"type":"Point"}
}