{
  "type": "Feature",
  "properties": {
    "iso:country": "GB",
    "wof:name": "S10 5EA",
    "wof:placetype": "postalcode"
  },
  "geometry": {"coordinates":[-1.507099,53.379842],"type":"Point"}
}
