{
  "type": "Feature",
  "properties": {
    "iso:country":"GB",
    "wof:name":"LL53 7TR",
    "wof:placetype":"postalcode"
},
  "geometry": {"coordinates":[-4.47898112436012,52.8531354066436],"type":"Point"}
}