{
  "type": "Feature",
  "properties": {
    "iso:country": "GB",
    "wof:name": "LL53 7TR",
    "wof:placetype": "postalcode"
  },
  "geometry": {"coordinates":[-4.478981,52.853135],"type":"Point"}
}
