{
  "type": "Feature",
  "properties": {
    "iso:country": "GB",
    "wof:name": "NR35 1RH",
    "wof:placetype": "postalcode"
  },
  "geometry": {"coordinates":[1.44196,52.447464],"type":"Point"}
}
