{
  "type": "Feature",
  "properties": {
    "iso:country":"GB",
    "wof:name":"PA5 0ES",
    "wof:placetype":"postalcode"
},
  "geometry": {"coordinates":[-4.51911112301969,55.82480079969348],"type":"Point"}
}