{
  "type": "Feature",
  "properties": {
    "date:inception_lower": "1980-01-01",
    "date:inception_upper": "1980-01-01",
    "iso:country": "GB",
    "wof:name": "PA5 0ES",
    "wof:placetype": "postalcode"
  },
  "geometry": {"coordinates":[-4.519111,55.824801],"type":"Point"}
}
