{
  "type": "Feature",
  "properties": {
    "iso:country":"GB",
    "wof:name":"DA15 9NY",
    "wof:placetype":"postalcode"
},
  "geometry": {"coordinates":[0.10810558624547,51.44969044118437],"type":"Point"}
}