{
  "type": "Feature",
  "properties": {
    "iso:country": "GB",
    "wof:name": "CM8 2XH",
    "wof:placetype": "postalcode"
  },
  "geometry": {"coordinates":[0.619009,51.81023],"type":"Point"}
}
