{
  "type": "Feature",
  "properties": {
    "iso:country":"GB",
    "wof:name":"CM8 2XH",
    "wof:placetype":"postalcode"
},
  "geometry": {"coordinates":[0.61900936764758,51.81023014667459],"type":"Point"}
}