{
  "type": "Feature",
  "properties": {
    "iso:country":"GB",
    "wof:name":"PL14 5BD",
    "wof:placetype":"postalcode"
},
  "geometry": {"coordinates":[-4.41187851204867,50.53157909882486],"type":"Point"}
}