{
  "type": "Feature",
  "properties": {
    "iso:country":"GB",
    "wof:name":"IP7 5HX",
    "wof:placetype":"postalcode"
},
  "geometry": {"coordinates":[0.96578153309048,52.0412765667725],"type":"Point"}
}