{
  "type": "Feature",
  "properties": {
    "iso:country":"GB",
    "wof:name":"TA2 7QX",
    "wof:placetype":"postalcode"
},
  "geometry": {"coordinates":[-3.09324559164108,51.03906395846981],"type":"Point"}
}