{
  "type": "Feature",
  "properties": {
    "iso:country": "GB",
    "wof:name": "TA2 7QX",
    "wof:placetype": "postalcode"
  },
  "geometry": {"coordinates":[-3.093382,51.039067],"type":"Point"}
}
