{
  "type": "Feature",
  "properties": {
    "iso:country":"GB",
    "wof:name":"L40 9WB",
    "wof:placetype":"postalcode"
},
  "geometry": {"coordinates":[-2.87940505969467,53.57116291872987],"type":"Point"}
}