{
  "type": "Feature",
  "properties": {
    "iso:country":"GB",
    "wof:name":"PR7 4PP",
    "wof:placetype":"postalcode"
},
  "geometry": {"coordinates":[-2.65074690479359,53.6241294767992],"type":"Point"}
}