{
  "type": "Feature",
  "properties": {
    "iso:country":"GB",
    "wof:name":"NR17 2RA",
    "wof:placetype":"postalcode"
},
  "geometry": {"coordinates":[1.02192253385429,52.52080735564004],"type":"Point"}
}