{
  "type": "Feature",
  "properties": {
    "date:inception_lower": "1992-01-01",
    "date:inception_upper": "1992-01-01",
    "iso:country": "GB",
    "wof:name": "NR17 2RA",
    "wof:placetype": "postalcode"
  },
  "geometry": {"coordinates":[1.021923,52.520807],"type":"Point"}
}
