{
  "type": "Feature",
  "properties": {
    "iso:country":"GB",
    "wof:name":"DG10 9HH",
    "wof:placetype":"postalcode"
},
  "geometry": {"coordinates":[-3.44672804766266,55.33262249170183],"type":"Point"}
}