{
  "type": "Feature",
  "properties": {
    "iso:country":"GB",
    "wof:name":"WD3 5RQ",
    "wof:placetype":"postalcode"
},
  "geometry": {"coordinates":[-0.52803871741502,51.65902694389217],"type":"Point"}
}