{
  "type": "Feature",
  "properties": {
    "iso:country":"GB",
    "wof:name":"UB7 0AX",
    "wof:placetype":"postalcode"
},
  "geometry": {"coordinates":[-0.48180335938426,51.48749021716202],"type":"Point"}
}