{
  "type": "Feature",
  "properties": {
    "iso:country": "GB",
    "wof:name": "UB7 0AX",
    "wof:placetype": "postalcode"
  },
  "geometry": {"coordinates":[-0.481803,51.48749],"type":"Point"}
}
