{
  "type": "Feature",
  "properties": {
    "date:inception_lower":"1980-01-01",
    "date:inception_upper":"1980-01-31",
    "iso:country":"GB",
    "wof:name":"UB7 0AX",
    "wof:placetype":"postalcode"
},
  "geometry": {"coordinates":[-0.481803,51.48749],"type":"Point"}
}