{
  "type": "Feature",
  "properties": {
    "iso:country": "GB",
    "wof:name": "SP9 7QU",
    "wof:placetype": "postalcode"
  },
  "geometry": {"coordinates":[-1.658491,51.241731],"type":"Point"}
}
