{
  "type": "Feature",
  "properties": {
    "iso:country":"GB",
    "wof:name":"SS8 0AU",
    "wof:placetype":"postalcode"
},
  "geometry": {"coordinates":[0.58910478740203,51.51348345324858],"type":"Point"}
}