{
  "type": "Feature",
  "properties": {
    "date:inception_lower": "2011-06-01",
    "date:inception_upper": "2011-06-01",
    "iso:country": "GB",
    "wof:name": "BH12 5BD",
    "wof:placetype": "postalcode"
  },
  "geometry": {"coordinates":[-1.895553,50.742915],"type":"Point"}
}
