{
  "type": "Feature",
  "properties": {
    "iso:country":"GB",
    "wof:name":"KA21 5PE",
    "wof:placetype":"postalcode"
},
  "geometry": {"coordinates":[-4.77508047511855,55.63846721710388],"type":"Point"}
}