{
  "type": "Feature",
  "properties": {
    "date:inception_lower":"2003-06-01",
    "date:inception_upper":"2003-06-30",
    "iso:country":"GB",
    "wof:name":"KA21 5PE",
    "wof:placetype":"postalcode"
},
  "geometry": {"coordinates":[-4.77508,55.638467],"type":"Point"}
}