{
  "type": "Feature",
  "properties": {
    "iso:country": "GB",
    "wof:name": "RM3 8PW",
    "wof:placetype": "postalcode"
  },
  "geometry": {"coordinates":[0.226108,51.597709],"type":"Point"}
}
