{
  "type": "Feature",
  "properties": {
    "iso:country":"GB",
    "wof:name":"RM3 8PW",
    "wof:placetype":"postalcode"
},
  "geometry": {"coordinates":[0.22610809754997,51.597709021729],"type":"Point"}
}