{
  "type": "Feature",
  "properties": {
    "date:inception_lower":"2001-06-01",
    "date:inception_upper":"2001-06-30",
    "iso:country":"GB",
    "wof:name":"RM3 8PW",
    "wof:placetype":"postalcode"
},
  "geometry": {"coordinates":[0.226108,51.597709],"type":"Point"}
}