{
  "type": "Feature",
  "properties": {
    "iso:country":"GB",
    "wof:name":"TW13 4AG",
    "wof:placetype":"postalcode"
},
  "geometry": {"coordinates":[-0.40975057063703,51.4458632311714],"type":"Point"}
}