{
  "type": "Feature",
  "properties": {
    "iso:country":"GB",
    "wof:name":"TN11 8LE",
    "wof:placetype":"postalcode"
},
  "geometry": {"coordinates":[0.17213405195279,51.20053540104661],"type":"Point"}
}