{
  "type": "Feature",
  "properties": {
    "iso:country": "GB",
    "wof:name": "CW10 9GP",
    "wof:placetype": "postalcode"
  },
  "geometry": {"coordinates":[-2.438855,53.19551],"type":"Point"}
}
