{
  "type": "Feature",
  "properties": {
    "iso:country": "GB",
    "wof:name": "SW16 2LZ",
    "wof:placetype": "postalcode"
  },
  "geometry": {"coordinates":[-0.117619,51.431222],"type":"Point"}
}
