{
  "type": "Feature",
  "properties": {
    "date:inception_lower":"2005-09-01",
    "date:inception_upper":"2005-09-30",
    "iso:country":"GB",
    "wof:name":"SW16 2LZ",
    "wof:placetype":"postalcode"
},
  "geometry": {"coordinates":[-0.117619,51.431222],"type":"Point"}
}