{
  "type": "Feature",
  "properties": {
    "date:inception_lower": "1996-06-01",
    "date:inception_upper": "1996-06-01",
    "iso:country": "GB",
    "wof:name": "AB16 5DR",
    "wof:placetype": "postalcode"
  },
  "geometry": {"coordinates":[-2.136777,57.162271],"type":"Point"}
}
