{
  "type": "Feature",
  "properties": {
    "iso:country":"GB",
    "wof:name":"NR20 4HT",
    "wof:placetype":"postalcode"
},
  "geometry": {"coordinates":[0.88477957341271,52.74102852232556],"type":"Point"}
}