{
  "type": "Feature",
  "properties": {
    "date:inception_lower":"2016-11-01",
    "date:inception_upper":"2016-11-30",
    "iso:country":"GB",
    "wof:name":"PE8 5BB",
    "wof:placetype":"postalcode"
},
  "geometry": {"coordinates":[-0.482298,52.493246],"type":"Point"}
}