{
  "type": "Feature",
  "properties": {
    "iso:country": "GB",
    "wof:name": "PE19 6GY",
    "wof:placetype": "postalcode"
  },
  "geometry": {"coordinates":[-0.245332,52.23051],"type":"Point"}
}
