{
  "type": "Feature",
  "properties": {
    "date:inception_lower": "1980-01-01",
    "date:inception_upper": "1980-01-01",
    "iso:country": "GB",
    "wof:name": "LD8 2EG",
    "wof:placetype": "postalcode"
  },
  "geometry": {"coordinates":[-3.036225,52.293232],"type":"Point"}
}
