{
  "type": "Feature",
  "properties": {
    "iso:country":"GB",
    "wof:name":"LD8 2EG",
    "wof:placetype":"postalcode"
},
  "geometry": {"coordinates":[-3.03581377178575,52.29309863963196],"type":"Point"}
}