{
  "type": "Feature",
  "properties": {
    "date:inception_lower": "1998-06-01",
    "date:inception_upper": "1998-06-01",
    "iso:country": "GB",
    "wof:name": "YO23 3GB",
    "wof:placetype": "postalcode"
  },
  "geometry": {"coordinates":[-1.19929,53.957351],"type":"Point"}
}
