{
  "type": "Feature",
  "properties": {
    "iso:country": "GB",
    "wof:name": "YO23 3GB",
    "wof:placetype": "postalcode"
  },
  "geometry": {"coordinates":[-1.199267,53.957325],"type":"Point"}
}
