{
  "type": "Feature",
  "properties": {
    "iso:country":"GB",
    "wof:name":"YO23 3GB",
    "wof:placetype":"postalcode"
},
  "geometry": {"coordinates":[-1.19926724881153,53.95732481114603],"type":"Point"}
}