{
  "type": "Feature",
  "properties": {
    "iso:country":"GB",
    "wof:name":"BB18 6EX",
    "wof:placetype":"postalcode"
},
  "geometry": {"coordinates":[-2.17693393658921,53.91959551347941],"type":"Point"}
}