{
  "type": "Feature",
  "properties": {
    "iso:country":"GB",
    "wof:name":"NR14 6JE",
    "wof:placetype":"postalcode"
},
  "geometry": {"coordinates":[1.48104754235576,52.53291558410736],"type":"Point"}
}