{
  "type": "Feature",
  "properties": {
    "date:inception_lower":"1999-06-01",
    "date:inception_upper":"1999-06-30",
    "iso:country":"GB",
    "wof:name":"NR14 6JE",
    "wof:placetype":"postalcode"
},
  "geometry": {"coordinates":[1.481048,52.532916],"type":"Point"}
}