{
  "type": "Feature",
  "properties": {
    "iso:country": "GB",
    "wof:name": "SA43 2RB",
    "wof:placetype": "postalcode"
  },
  "geometry": {"coordinates":[-4.545974,52.075396],"type":"Point"}
}
