{
  "type": "Feature",
  "properties": {
    "iso:country":"GB",
    "wof:name":"SA43 2RB",
    "wof:placetype":"postalcode"
},
  "geometry": {"coordinates":[-4.54597422910959,52.07539649138806],"type":"Point"}
}