{
  "type": "Feature",
  "properties": {
    "date:inception_lower":"1992-01-01",
    "date:inception_upper":"1992-01-31",
    "iso:country":"GB",
    "wof:name":"DE11 7DS",
    "wof:placetype":"postalcode"
},
  "geometry": {"coordinates":[-1.529049,52.765037],"type":"Point"}
}