{
  "type": "Feature",
  "properties": {
    "iso:country": "GB",
    "wof:name": "WN7 2DH",
    "wof:placetype": "postalcode"
  },
  "geometry": {"coordinates":[-2.506602,53.493173],"type":"Point"}
}
