{
  "type": "Feature",
  "properties": {
    "date:inception_lower": "1997-12-01",
    "date:inception_upper": "1997-12-01",
    "iso:country": "GB",
    "wof:name": "WN7 2DH",
    "wof:placetype": "postalcode"
  },
  "geometry": {"coordinates":[-2.506602,53.493173],"type":"Point"}
}
