{
  "type": "Feature",
  "properties": {
    "iso:country":"GB",
    "wof:name":"DN15 7BD",
    "wof:placetype":"postalcode"
},
  "geometry": {"coordinates":[-0.65456401968932,53.58702310606787],"type":"Point"}
}