{
  "type": "Feature",
  "properties": {
    "iso:country":"GB",
    "wof:name":"LS15 7PZ",
    "wof:placetype":"postalcode"
},
  "geometry": {"coordinates":[-1.45683191893087,53.8097895205712],"type":"Point"}
}