{
  "type": "Feature",
  "properties": {
    "iso:country":"GB",
    "wof:name":"LE3 9FR",
    "wof:placetype":"postalcode"
},
  "geometry": {"coordinates":[-1.15918341137978,52.6407487920419],"type":"Point"}
}