{
  "type": "Feature",
  "properties": {
    "iso:country":"GB",
    "wof:name":"LE1 2PP",
    "wof:placetype":"postalcode"
},
  "geometry": {"coordinates":[-1.12125119390162,52.64054555238216],"type":"Point"}
}