{
  "type": "Feature",
  "properties": {
    "iso:country": "GB",
    "wof:name": "LE1 2PP",
    "wof:placetype": "postalcode"
  },
  "geometry": {"coordinates":[-1.121251,52.640546],"type":"Point"}
}
