{
  "type": "Feature",
  "properties": {
    "iso:country":"GB",
    "wof:name":"E2 6FT",
    "wof:placetype":"postalcode"
},
  "geometry": {"coordinates":[-0.0625377814881,51.53138354447433],"type":"Point"}
}