{
  "type": "Feature",
  "properties": {
    "iso:country": "GB",
    "wof:name": "TQ7 1DU",
    "wof:placetype": "postalcode"
  },
  "geometry": {"coordinates":[-3.771108,50.285768],"type":"Point"}
}
