{
  "type": "Feature",
  "properties": {
    "iso:country":"GB",
    "wof:name":"CF81 9AB",
    "wof:placetype":"postalcode"
},
  "geometry": {"coordinates":[-3.2165574458127,51.6831468018787],"type":"Point"}
}