{
  "type": "Feature",
  "properties": {
    "date:inception_lower":"2002-06-01",
    "date:inception_upper":"2002-06-30",
    "iso:country":"GB",
    "wof:name":"CF81 9AB",
    "wof:placetype":"postalcode"
},
  "geometry": {"coordinates":[-3.216557,51.683147],"type":"Point"}
}