{
  "type": "Feature",
  "properties": {
    "iso:country": "GB",
    "wof:name": "CF81 9AB",
    "wof:placetype": "postalcode"
  },
  "geometry": {"coordinates":[-3.216557,51.683147],"type":"Point"}
}
