{
  "type": "Feature",
  "properties": {
    "iso:country":"GB",
    "wof:name":"BS9 3QL",
    "wof:placetype":"postalcode"
},
  "geometry": {"coordinates":[-2.62620994776918,51.48991275656493],"type":"Point"}
}