{
  "type": "Feature",
  "properties": {
    "date:inception_lower": "1987-10-01",
    "date:inception_upper": "1987-10-01",
    "iso:country": "GB",
    "wof:name": "CH1 5TX",
    "wof:placetype": "postalcode"
  },
  "geometry": {"coordinates":[-2.918174,53.210228],"type":"Point"}
}
