{
  "type": "Feature",
  "properties": {
    "iso:country": "GB",
    "wof:name": "CH1 5TX",
    "wof:placetype": "postalcode"
  },
  "geometry": {"coordinates":[-2.918174,53.210228],"type":"Point"}
}
