{
  "type": "Feature",
  "properties": {
    "iso:country":"GB",
    "wof:name":"BD13 4NS",
    "wof:placetype":"postalcode"
},
  "geometry": {"coordinates":[-1.90042364937473,53.80122511090327],"type":"Point"}
}