{
  "type": "Feature",
  "properties": {
    "date:inception_lower": "2005-06-01",
    "date:inception_upper": "2005-06-01",
    "iso:country": "GB",
    "wof:name": "BD13 4NS",
    "wof:placetype": "postalcode"
  },
  "geometry": {"coordinates":[-1.900424,53.801225],"type":"Point"}
}
