{
  "type": "Feature",
  "properties": {
    "iso:country": "GB",
    "wof:name": "EX39 4QQ",
    "wof:placetype": "postalcode"
  },
  "geometry": {"coordinates":[-4.152184,51.007909],"type":"Point"}
}
