{
  "type": "Feature",
  "properties": {
    "iso:country": "GB",
    "wof:name": "CH2 3LN",
    "wof:placetype": "postalcode"
  },
  "geometry": {"coordinates":[-2.859951,53.203972],"type":"Point"}
}
