{
  "type": "Feature",
  "properties": {
    "date:inception_lower": "2021-06-01",
    "date:inception_upper": "2021-06-01",
    "iso:country": "GB",
    "wof:name": "EX1 3FH",
    "wof:placetype": "postalcode"
  },
  "geometry": {"coordinates":[-3.46323,50.736141],"type":"Point"}
}
