{
  "type": "Feature",
  "properties": {
    "date:inception_lower": "1980-01-01",
    "date:inception_upper": "1980-01-01",
    "iso:country": "GB",
    "wof:name": "HA9 6LS",
    "wof:placetype": "postalcode"
  },
  "geometry": {"coordinates":[-0.281084,51.552738],"type":"Point"}
}
