{
  "type": "Feature",
  "properties": {
    "iso:country":"GB",
    "wof:name":"HA9 6LS",
    "wof:placetype":"postalcode"
},
  "geometry": {"coordinates":[-0.28108438740414,51.55273810568298],"type":"Point"}
}