{
  "type": "Feature",
  "properties": {
    "iso:country":"GB",
    "wof:name":"WF10 3DP",
    "wof:placetype":"postalcode"
},
  "geometry": {"coordinates":[-1.32390806835603,53.72749248641943],"type":"Point"}
}