{
  "type": "Feature",
  "properties": {
    "iso:country": "GB",
    "wof:name": "BB2 3JG",
    "wof:placetype": "postalcode"
  },
  "geometry": {"coordinates":[-2.470756,53.737548],"type":"Point"}
}
