{
  "type": "Feature",
  "properties": {
    "iso:country": "GB",
    "wof:name": "G69 8AQ",
    "wof:placetype": "postalcode"
  },
  "geometry": {"coordinates":[-4.082743,55.888696],"type":"Point"}
}
