{
  "type": "Feature",
  "properties": {
    "iso:country":"GB",
    "wof:name":"SE3 8RN",
    "wof:placetype":"postalcode"
},
  "geometry": {"coordinates":[0.02866443025436,51.47512094324306],"type":"Point"}
}