{
  "type": "Feature",
  "properties": {
    "iso:country":"GB",
    "wof:name":"DD8 3NF",
    "wof:placetype":"postalcode"
},
  "geometry": {"coordinates":[-2.85736946268459,56.65744744882038],"type":"Point"}
}