{
  "type": "Feature",
  "properties": {
    "iso:country":"GB",
    "wof:name":"S36 7JG",
    "wof:placetype":"postalcode"
},
  "geometry": {"coordinates":[-1.62295405154506,53.54000744979088],"type":"Point"}
}