{
  "type": "Feature",
  "properties": {
    "iso:country":"GB",
    "wof:name":"IG7 4PQ",
    "wof:placetype":"postalcode"
},
  "geometry": {"coordinates":[0.10516521385202,51.61022851610182],"type":"Point"}
}