{
  "type": "Feature",
  "properties": {
    "iso:country": "GB",
    "wof:name": "LN5 0JJ",
    "wof:placetype": "postalcode"
  },
  "geometry": {"coordinates":[-0.526297,53.103518],"type":"Point"}
}
