{
  "type": "Feature",
  "properties": {
    "iso:country":"GB",
    "wof:name":"LN5 0JJ",
    "wof:placetype":"postalcode"
},
  "geometry": {"coordinates":[-0.52632547599734,53.10321713827533],"type":"Point"}
}