{
  "type": "Feature",
  "properties": {
    "iso:country": "GB",
    "wof:name": "AL8 6JU",
    "wof:placetype": "postalcode"
  },
  "geometry": {"coordinates":[-0.214039,51.797251],"type":"Point"}
}
