{
  "type": "Feature",
  "properties": {
    "iso:country":"GB",
    "wof:name":"AL8 6JU",
    "wof:placetype":"postalcode"
},
  "geometry": {"coordinates":[-0.21403938621939,51.79725075692907],"type":"Point"}
}