{
  "type": "Feature",
  "properties": {
    "date:inception_lower": "1980-01-01",
    "date:inception_upper": "1980-01-01",
    "iso:country": "GB",
    "wof:name": "TN25 5JB",
    "wof:placetype": "postalcode"
  },
  "geometry": {"coordinates":[0.988463,51.174302],"type":"Point"}
}
