{
  "type": "Feature",
  "properties": {
    "date:inception_lower": "2000-12-01",
    "date:inception_upper": "2000-12-01",
    "iso:country": "GB",
    "wof:name": "MK44 3JQ",
    "wof:placetype": "postalcode"
  },
  "geometry": {"coordinates":[-0.348819,52.154983],"type":"Point"}
}
