{
  "type": "Feature",
  "properties": {
    "iso:country":"GB",
    "wof:name":"MK44 3JQ",
    "wof:placetype":"postalcode"
},
  "geometry": {"coordinates":[-0.34881860975502,52.15498345620416],"type":"Point"}
}