{
  "type": "Feature",
  "properties": {
    "iso:country": "GB",
    "wof:name": "CV31 2JP",
    "wof:placetype": "postalcode"
  },
  "geometry": {"coordinates":[-1.524028,52.267005],"type":"Point"}
}
