{
  "type": "Feature",
  "properties": {
    "date:inception_lower": "1994-12-01",
    "date:inception_upper": "1994-12-01",
    "iso:country": "GB",
    "wof:name": "SS16 6EA",
    "wof:placetype": "postalcode"
  },
  "geometry": {"coordinates":[0.402231,51.5649],"type":"Point"}
}
