{
  "type": "Feature",
  "properties": {
    "iso:country":"GB",
    "wof:name":"SS16 6EA",
    "wof:placetype":"postalcode"
},
  "geometry": {"coordinates":[0.40223093080943,51.56490000569889],"type":"Point"}
}