{
  "type": "Feature",
  "properties": {
    "date:inception_lower": "2002-12-01",
    "date:inception_upper": "2002-12-01",
    "iso:country": "GB",
    "wof:name": "PE21 7TH",
    "wof:placetype": "postalcode"
  },
  "geometry": {"coordinates":[-0.057402,52.974989],"type":"Point"}
}
