{
  "type": "Feature",
  "properties": {
    "iso:country":"GB",
    "wof:name":"PE21 7TH",
    "wof:placetype":"postalcode"
},
  "geometry": {"coordinates":[-0.05740253224355,52.97498937838555],"type":"Point"}
}