{
  "type": "Feature",
  "properties": {
    "iso:country":"GB",
    "wof:name":"TR4 8HS",
    "wof:placetype":"postalcode"
},
  "geometry": {"coordinates":[-5.16573579803526,50.27938400962369],"type":"Point"}
}