{
  "type": "Feature",
  "properties": {
    "iso:country": "GB",
    "wof:name": "TR4 8HS",
    "wof:placetype": "postalcode"
  },
  "geometry": {"coordinates":[-5.165736,50.279384],"type":"Point"}
}
