{
  "type": "Feature",
  "properties": {
    "date:inception_lower": "1987-04-01",
    "date:inception_upper": "1987-04-01",
    "iso:country": "GB",
    "wof:name": "EX20 1SS",
    "wof:placetype": "postalcode"
  },
  "geometry": {"coordinates":[-4.002191,50.738941],"type":"Point"}
}
