{
  "type": "Feature",
  "properties": {
    "iso:country": "GB",
    "wof:name": "EX20 1SS",
    "wof:placetype": "postalcode"
  },
  "geometry": {"coordinates":[-4.002191,50.738941],"type":"Point"}
}
