{
  "type": "Feature",
  "properties": {
    "iso:country": "GB",
    "wof:name": "GL50 2PH",
    "wof:placetype": "postalcode"
  },
  "geometry": {"coordinates":[-2.090209,51.896826],"type":"Point"}
}
