{
  "type": "Feature",
  "properties": {
    "date:inception_lower": "1980-01-01",
    "date:inception_upper": "1980-01-01",
    "iso:country": "GB",
    "wof:name": "GL50 2PH",
    "wof:placetype": "postalcode"
  },
  "geometry": {"coordinates":[-2.090209,51.896826],"type":"Point"}
}
