{
  "type": "Feature",
  "properties": {
    "date:inception_lower": "2015-06-01",
    "date:inception_upper": "2015-06-01",
    "iso:country": "GB",
    "wof:name": "NE13 6LP",
    "wof:placetype": "postalcode"
  },
  "geometry": {"coordinates":[-1.61758,55.043697],"type":"Point"}
}
