{
  "type": "Feature",
  "properties": {
    "iso:country": "GB",
    "wof:name": "TQ13 7PX",
    "wof:placetype": "postalcode"
  },
  "geometry": {"coordinates":[-3.824133,50.525178],"type":"Point"}
}
