{
  "type": "Feature",
  "properties": {
    "iso:country":"GB",
    "wof:name":"TQ13 7PX",
    "wof:placetype":"postalcode"
},
  "geometry": {"coordinates":[-3.82413264606865,50.52517816080712],"type":"Point"}
}