{
  "type": "Feature",
  "properties": {
    "iso:country": "GB",
    "wof:name": "PO9 4BG",
    "wof:placetype": "postalcode"
  },
  "geometry": {"coordinates":[-1.005453,50.86767],"type":"Point"}
}
