{
  "type": "Feature",
  "properties": {
    "iso:country":"GB",
    "wof:name":"PO9 4BG",
    "wof:placetype":"postalcode"
},
  "geometry": {"coordinates":[-1.00545295904742,50.86767037666171],"type":"Point"}
}