{
  "type": "Feature",
  "properties": {
    "iso:country": "GB",
    "wof:name": "EH10 5XH",
    "wof:placetype": "postalcode"
  },
  "geometry": {"coordinates":[-3.230314,55.918044],"type":"Point"}
}
