{
  "type": "Feature",
  "properties": {
    "date:inception_lower": "1980-01-01",
    "date:inception_upper": "1980-01-01",
    "iso:country": "GB",
    "wof:name": "SY5 8NW",
    "wof:placetype": "postalcode"
  },
  "geometry": {"coordinates":[-2.779768,52.687137],"type":"Point"}
}
