{
  "type": "Feature",
  "properties": {
    "iso:country":"GB",
    "wof:name":"SY5 8NW",
    "wof:placetype":"postalcode"
},
  "geometry": {"coordinates":[-2.77976762622399,52.68713699015673],"type":"Point"}
}