{
  "type": "Feature",
  "properties": {
    "iso:country":"GB",
    "wof:name":"SY18 6DA",
    "wof:placetype":"postalcode"
},
  "geometry": {"coordinates":[-3.53738372370687,52.44726708497888],"type":"Point"}
}