{
  "type": "Feature",
  "properties": {
    "iso:country":"GB",
    "wof:name":"PL21 0NE",
    "wof:placetype":"postalcode"
},
  "geometry": {"coordinates":[-3.86248797556884,50.38623429880192],"type":"Point"}
}