{
  "type": "Feature",
  "properties": {
    "iso:country": "GB",
    "wof:name": "CV23 0PL",
    "wof:placetype": "postalcode"
  },
  "geometry": {"coordinates":[-1.343582,52.438703],"type":"Point"}
}
