{
  "type": "Feature",
  "properties": {
    "date:inception_lower": "1980-01-01",
    "date:inception_upper": "1980-01-01",
    "iso:country": "GB",
    "wof:name": "CV23 0PL",
    "wof:placetype": "postalcode"
  },
  "geometry": {"coordinates":[-1.343582,52.438703],"type":"Point"}
}
