{
  "type": "Feature",
  "properties": {
    "iso:country":"GB",
    "wof:name":"CV23 0PL",
    "wof:placetype":"postalcode"
},
  "geometry": {"coordinates":[-1.34306904815877,52.43925755469147],"type":"Point"}
}