{
  "type": "Feature",
  "properties": {
    "iso:country":"GB",
    "wof:name":"LE12 7RU",
    "wof:placetype":"postalcode"
},
  "geometry": {"coordinates":[-1.10800730462088,52.73144269897449],"type":"Point"}
}