{
  "type": "Feature",
  "properties": {
    "date:inception_lower":"1980-01-01",
    "date:inception_upper":"1980-01-31",
    "iso:country":"GB",
    "wof:name":"BS2 8HA",
    "wof:placetype":"postalcode"
},
  "geometry": {"coordinates":[-2.595929,51.460812],"type":"Point"}
}