{
  "type": "Feature",
  "properties": {
    "iso:country": "GB",
    "wof:name": "BB11 5HX",
    "wof:placetype": "postalcode"
  },
  "geometry": {"coordinates":[-2.263998,53.777606],"type":"Point"}
}
