{
  "type": "Feature",
  "properties": {
    "iso:country":"GB",
    "wof:name":"BB11 5HX",
    "wof:placetype":"postalcode"
},
  "geometry": {"coordinates":[-2.26399812120797,53.77760631310534],"type":"Point"}
}