{
  "type": "Feature",
  "properties": {
    "date:inception_lower":"1980-01-01",
    "date:inception_upper":"1980-01-31",
    "iso:country":"GB",
    "wof:name":"DD11 2BU",
    "wof:placetype":"postalcode"
},
  "geometry": {"coordinates":[-2.602537,56.557791],"type":"Point"}
}