{
  "type": "Feature",
  "properties": {
    "iso:country":"GB",
    "wof:name":"B14 4EH",
    "wof:placetype":"postalcode"
},
  "geometry": {"coordinates":[-1.86636731758872,52.41571636772524],"type":"Point"}
}