{
  "type": "Feature",
  "properties": {
    "date:inception_lower": "1980-01-01",
    "date:inception_upper": "1980-01-01",
    "iso:country": "GB",
    "wof:name": "B14 4EH",
    "wof:placetype": "postalcode"
  },
  "geometry": {"coordinates":[-1.866367,52.415716],"type":"Point"}
}
