{
  "type": "Feature",
  "properties": {
    "iso:country": "GB",
    "wof:name": "B14 4EH",
    "wof:placetype": "postalcode"
  },
  "geometry": {"coordinates":[-1.866367,52.415716],"type":"Point"}
}
