{
  "type": "Feature",
  "properties": {
    "date:inception_lower": "2019-05-01",
    "date:inception_upper": "2019-05-01",
    "iso:country": "GB",
    "wof:name": "SE15 5FA",
    "wof:placetype": "postalcode"
  },
  "geometry": {"coordinates":[-0.076414,51.474501],"type":"Point"}
}
