{
  "type": "Feature",
  "properties": {
    "iso:country": "GB",
    "wof:name": "TR8 4HU",
    "wof:placetype": "postalcode"
  },
  "geometry": {"coordinates":[-4.983529,50.419177],"type":"Point"}
}
