{
  "type": "Feature",
  "properties": {
    "iso:country":"GB",
    "wof:name":"TR8 4HU",
    "wof:placetype":"postalcode"
},
  "geometry": {"coordinates":[-4.9835294274563,50.41917676544271],"type":"Point"}
}