{
  "type": "Feature",
  "properties": {
    "iso:country":"GB",
    "wof:name":"ME3 8UG",
    "wof:placetype":"postalcode"
},
  "geometry": {"coordinates":[0.50178948269151,51.43432136826527],"type":"Point"}
}