{
  "type": "Feature",
  "properties": {
    "date:inception_lower": "1980-01-01",
    "date:inception_upper": "1980-01-01",
    "iso:country": "GB",
    "wof:name": "ME3 8UG",
    "wof:placetype": "postalcode"
  },
  "geometry": {"coordinates":[0.50179,51.434321],"type":"Point"}
}
