{
  "type": "Feature",
  "properties": {
    "iso:country": "GB",
    "wof:name": "DE55 6FP",
    "wof:placetype": "postalcode"
  },
  "geometry": {"coordinates":[-1.434218,53.142294],"type":"Point"}
}
