{
  "type": "Feature",
  "properties": {
    "iso:country":"GB",
    "wof:name":"DE55 6FP",
    "wof:placetype":"postalcode"
},
  "geometry": {"coordinates":[-1.43357608702306,53.14123798181377],"type":"Point"}
}