{
  "type": "Feature",
  "properties": {
    "iso:country":"GB",
    "wof:name":"SW20 9LP",
    "wof:placetype":"postalcode"
},
  "geometry": {"coordinates":[-0.23506339526213,51.4025823490589],"type":"Point"}
}