{
  "type": "Feature",
  "properties": {
    "iso:country":"GB",
    "wof:name":"SM1 4EW",
    "wof:placetype":"postalcode"
},
  "geometry": {"coordinates":[-0.18925352221597,51.36956394892746],"type":"Point"}
}