{
  "type": "Feature",
  "properties": {
    "date:inception_lower": "1985-04-01",
    "date:inception_upper": "1985-04-01",
    "iso:country": "GB",
    "wof:name": "BN25 4DD",
    "wof:placetype": "postalcode"
  },
  "geometry": {"coordinates":[0.126238,50.771416],"type":"Point"}
}
