{
  "type": "Feature",
  "properties": {
    "date:inception_lower": "1980-01-01",
    "date:inception_upper": "1980-01-01",
    "iso:country": "GB",
    "wof:name": "M29 8AN",
    "wof:placetype": "postalcode"
  },
  "geometry": {"coordinates":[-2.467893,53.514912],"type":"Point"}
}
