{
  "type": "Feature",
  "properties": {
    "iso:country":"GB",
    "wof:name":"LS28 9EL",
    "wof:placetype":"postalcode"
},
  "geometry": {"coordinates":[-1.64821320824866,53.79103505284276],"type":"Point"}
}