{
  "type": "Feature",
  "properties": {
    "iso:country": "GB",
    "wof:name": "LS28 9EL",
    "wof:placetype": "postalcode"
  },
  "geometry": {"coordinates":[-1.648213,53.791035],"type":"Point"}
}
