{
  "type": "Feature",
  "properties": {
    "iso:country":"GB",
    "wof:name":"TN27 9EX",
    "wof:placetype":"postalcode"
},
  "geometry": {"coordinates":[0.7272081653839,51.17768450072293],"type":"Point"}
}