{
  "type": "Feature",
  "properties": {
    "iso:country": "GB",
    "wof:name": "NR17 1GY",
    "wof:placetype": "postalcode"
  },
  "geometry": {"coordinates":[1.034637,52.501331],"type":"Point"}
}
