{
  "type": "Feature",
  "properties": {
    "iso:country":"GB",
    "wof:name":"HG5 8HP",
    "wof:placetype":"postalcode"
},
  "geometry": {"coordinates":[-1.45668530897536,53.99949682757469],"type":"Point"}
}