{
  "type": "Feature",
  "properties": {
    "date:inception_lower": "1980-01-01",
    "date:inception_upper": "1980-01-01",
    "iso:country": "GB",
    "wof:name": "HG5 8HP",
    "wof:placetype": "postalcode"
  },
  "geometry": {"coordinates":[-1.456685,53.999497],"type":"Point"}
}
