{
  "type": "Feature",
  "properties": {
    "date:inception_lower": "1980-01-01",
    "date:inception_upper": "1980-01-01",
    "iso:country": "GB",
    "wof:name": "ME14 2JG",
    "wof:placetype": "postalcode"
  },
  "geometry": {"coordinates":[0.531797,51.291748],"type":"Point"}
}
