{
  "type": "Feature",
  "properties": {
    "iso:country":"GB",
    "wof:name":"ME14 2JG",
    "wof:placetype":"postalcode"
},
  "geometry": {"coordinates":[0.53109477249243,51.29149414216195],"type":"Point"}
}