{
  "type": "Feature",
  "properties": {
    "iso:country": "GB",
    "wof:name": "WN6 7RX",
    "wof:placetype": "postalcode"
  },
  "geometry": {"coordinates":[-2.655134,53.556908],"type":"Point"}
}
