{
  "type": "Feature",
  "properties": {
    "iso:country":"GB",
    "wof:name":"WN6 7RX",
    "wof:placetype":"postalcode"
},
  "geometry": {"coordinates":[-2.65513384735775,53.55690794684499],"type":"Point"}
}