{
  "type": "Feature",
  "properties": {
    "iso:country":"GB",
    "wof:name":"BN7 2XS",
    "wof:placetype":"postalcode"
},
  "geometry": {"coordinates":[0.0131831764815,50.87008572612477],"type":"Point"}
}