{
  "type": "Feature",
  "properties": {
    "date:inception_lower": "2022-08-01",
    "date:inception_upper": "2022-08-01",
    "iso:country": "GB",
    "wof:name": "NN2 7GA",
    "wof:placetype": "postalcode"
  },
  "geometry": {"coordinates":[-0.879989,52.273443],"type":"Point"}
}
