{
  "type": "Feature",
  "properties": {
    "date:inception_lower": "1980-01-01",
    "date:inception_upper": "1980-01-01",
    "iso:country": "GB",
    "wof:name": "LL76 8TJ",
    "wof:placetype": "postalcode"
  },
  "geometry": {"coordinates":[-4.237691,53.301005],"type":"Point"}
}
