{
  "type": "Feature",
  "properties": {
    "iso:country": "GB",
    "wof:name": "B5 7RN",
    "wof:placetype": "postalcode"
  },
  "geometry": {"coordinates":[-1.90716,52.45408],"type":"Point"}
}
