{
  "type": "Feature",
  "properties": {
    "iso:country":"GB",
    "wof:name":"B5 7RN",
    "wof:placetype":"postalcode"
},
  "geometry": {"coordinates":[-1.90716043195354,52.45407983870103],"type":"Point"}
}