{
  "type": "Feature",
  "properties": {
    "date:inception_lower": "1984-10-01",
    "date:inception_upper": "1984-10-01",
    "iso:country": "GB",
    "wof:name": "ST3 7TY",
    "wof:placetype": "postalcode"
  },
  "geometry": {"coordinates":[-2.095998,52.969531],"type":"Point"}
}
