{
  "type": "Feature",
  "properties": {
    "iso:country": "GB",
    "wof:name": "KA26 0ET",
    "wof:placetype": "postalcode"
  },
  "geometry": {"coordinates":[-4.846385,55.234896],"type":"Point"}
}
