{
  "type": "Feature",
  "properties": {
    "iso:country":"GB",
    "wof:name":"SP5 5RW",
    "wof:placetype":"postalcode"
},
  "geometry": {"coordinates":[-2.03763540374881,50.95642734738914],"type":"Point"}
}