{
  "type": "Feature",
  "properties": {
    "iso:country": "GB",
    "wof:name": "PL1 4TH",
    "wof:placetype": "postalcode"
  },
  "geometry": {"coordinates":[-4.175524,50.372114],"type":"Point"}
}
