{
  "type": "Feature",
  "properties": {
    "iso:country":"GB",
    "wof:name":"DL14 0DF",
    "wof:placetype":"postalcode"
},
  "geometry": {"coordinates":[-1.7426102209774,54.65797790777916],"type":"Point"}
}