{
  "type": "Feature",
  "properties": {
    "iso:country":"GB",
    "wof:name":"IP22 2BE",
    "wof:placetype":"postalcode"
},
  "geometry": {"coordinates":[1.07774983517918,52.40154605889599],"type":"Point"}
}