{
  "type": "Feature",
  "properties": {
    "iso:country":"GB",
    "wof:name":"HP13 7RQ",
    "wof:placetype":"postalcode"
},
  "geometry": {"coordinates":[-0.72721275350074,51.627257414016],"type":"Point"}
}