{
  "type": "Feature",
  "properties": {
    "date:inception_lower":"1980-01-01",
    "date:inception_upper":"1980-01-31",
    "iso:country":"GB",
    "wof:name":"E11 3BH",
    "wof:placetype":"postalcode"
},
  "geometry": {"coordinates":[0.01531,51.568039],"type":"Point"}
}