{
  "type": "Feature",
  "properties": {
    "iso:country":"GB",
    "wof:name":"SA43 2SW",
    "wof:placetype":"postalcode"
},
  "geometry": {"coordinates":[-4.62483192657513,52.05309879706222],"type":"Point"}
}