{
  "type": "Feature",
  "properties": {
    "iso:country": "GB",
    "wof:name": "SA43 2SW",
    "wof:placetype": "postalcode"
  },
  "geometry": {"coordinates":[-4.62503,52.052875],"type":"Point"}
}
