{
  "type": "Feature",
  "properties": {
    "iso:country":"GB",
    "wof:name":"DH2 2BF",
    "wof:placetype":"postalcode"
},
  "geometry": {"coordinates":[-1.61850567622315,54.86528578384893],"type":"Point"}
}