{
  "type": "Feature",
  "properties": {
    "iso:country": "GB",
    "wof:name": "RH11 0JL",
    "wof:placetype": "postalcode"
  },
  "geometry": {"coordinates":[-0.216463,51.116969],"type":"Point"}
}
