{
  "type": "Feature",
  "properties": {
    "iso:country":"GB",
    "wof:name":"RH11 0JL",
    "wof:placetype":"postalcode"
},
  "geometry": {"coordinates":[-0.21646336552919,51.11696896849151],"type":"Point"}
}