{
  "type": "Feature",
  "properties": {
    "date:inception_lower": "1993-08-01",
    "date:inception_upper": "1993-08-01",
    "iso:country": "GB",
    "wof:name": "B76 1YB",
    "wof:placetype": "postalcode"
  },
  "geometry": {"coordinates":[-1.782758,52.531455],"type":"Point"}
}
