{
  "type": "Feature",
  "properties": {
    "iso:country":"GB",
    "wof:name":"B76 1YB",
    "wof:placetype":"postalcode"
},
  "geometry": {"coordinates":[-1.78275799301409,52.53145542254048],"type":"Point"}
}