{
  "type": "Feature",
  "properties": {
    "iso:country":"GB",
    "wof:name":"TN8 5DT",
    "wof:placetype":"postalcode"
},
  "geometry": {"coordinates":[0.06382799165773,51.19665972418382],"type":"Point"}
}