{
  "type": "Feature",
  "properties": {
    "iso:country":"GB",
    "wof:name":"TQ3 2AB",
    "wof:placetype":"postalcode"
},
  "geometry": {"coordinates":[-3.56608160609419,50.43968322895831],"type":"Point"}
}