{
  "type": "Feature",
  "properties": {
    "date:inception_lower":"1980-01-01",
    "date:inception_upper":"1980-01-31",
    "iso:country":"GB",
    "wof:name":"TQ3 2AB",
    "wof:placetype":"postalcode"
},
  "geometry": {"coordinates":[-3.566082,50.439683],"type":"Point"}
}