{
  "type": "Feature",
  "properties": {
    "iso:country":"GB",
    "wof:name":"FK6 5HJ",
    "wof:placetype":"postalcode"
},
  "geometry": {"coordinates":[-3.94574437444636,56.02527071496451],"type":"Point"}
}