{
  "type": "Feature",
  "properties": {
    "date:inception_lower": "1980-01-01",
    "date:inception_upper": "1980-01-01",
    "iso:country": "GB",
    "wof:name": "PE14 0RW",
    "wof:placetype": "postalcode"
  },
  "geometry": {"coordinates":[0.145558,52.638332],"type":"Point"}
}
