{
  "type": "Feature",
  "properties": {
    "iso:country":"GB",
    "wof:name":"PE14 0RW",
    "wof:placetype":"postalcode"
},
  "geometry": {"coordinates":[0.1455583999357,52.638331563296],"type":"Point"}
}