{
  "type": "Feature",
  "properties": {
    "iso:country":"GB",
    "wof:name":"CW2 8JG",
    "wof:placetype":"postalcode"
},
  "geometry": {"coordinates":[-2.47305009815582,53.07921402018628],"type":"Point"}
}