{
  "type": "Feature",
  "properties": {
    "iso:country": "GB",
    "wof:name": "PO7 5DA",
    "wof:placetype": "postalcode"
  },
  "geometry": {"coordinates":[-1.043867,50.855752],"type":"Point"}
}
