{
  "type": "Feature",
  "properties": {
    "iso:country":"GB",
    "wof:name":"PO7 5DA",
    "wof:placetype":"postalcode"
},
  "geometry": {"coordinates":[-1.04386689917648,50.85575223024222],"type":"Point"}
}