{
  "type": "Feature",
  "properties": {
    "iso:country":"GB",
    "wof:name":"NG19 9AW",
    "wof:placetype":"postalcode"
},
  "geometry": {"coordinates":[-1.18831002168042,53.15891238554715],"type":"Point"}
}