{
  "type": "Feature",
  "properties": {
    "iso:country": "GB",
    "wof:name": "B50 4AX",
    "wof:placetype": "postalcode"
  },
  "geometry": {"coordinates":[-1.867747,52.169951],"type":"Point"}
}
