{
  "type": "Feature",
  "properties": {
    "date:inception_lower": "1980-01-01",
    "date:inception_upper": "1980-01-01",
    "iso:country": "GB",
    "wof:name": "LE7 9FB",
    "wof:placetype": "postalcode"
  },
  "geometry": {"coordinates":[-0.9368,52.619247],"type":"Point"}
}
