{
  "type": "Feature",
  "properties": {
    "date:inception_lower": "1996-06-01",
    "date:inception_upper": "1996-06-01",
    "iso:country": "GB",
    "wof:name": "GU29 9RT",
    "wof:placetype": "postalcode"
  },
  "geometry": {"coordinates":[-0.733287,50.992309],"type":"Point"}
}
