{
  "type": "Feature",
  "properties": {
    "iso:country": "GB",
    "wof:name": "GU29 9RT",
    "wof:placetype": "postalcode"
  },
  "geometry": {"coordinates":[-0.733287,50.992309],"type":"Point"}
}
