{
  "type": "Feature",
  "properties": {
    "iso:country":"GB",
    "wof:name":"GU29 9RT",
    "wof:placetype":"postalcode"
},
  "geometry": {"coordinates":[-0.73328654107594,50.99230940983953],"type":"Point"}
}