{
  "type": "Feature",
  "properties": {
    "iso:country":"GB",
    "wof:name":"W1U 5AF",
    "wof:placetype":"postalcode"
},
  "geometry": {"coordinates":[-0.15579769484896,51.52125953267284],"type":"Point"}
}