{
  "type": "Feature",
  "properties": {
    "date:inception_lower": "2000-12-01",
    "date:inception_upper": "2000-12-01",
    "iso:country": "GB",
    "wof:name": "W1U 5AF",
    "wof:placetype": "postalcode"
  },
  "geometry": {"coordinates":[-0.155798,51.52126],"type":"Point"}
}
