{
  "type": "Feature",
  "properties": {
    "iso:country":"GB",
    "wof:name":"BH15 4AF",
    "wof:placetype":"postalcode"
},
  "geometry": {"coordinates":[-1.99443837876316,50.71106416452825],"type":"Point"}
}