{
  "type": "Feature",
  "properties": {
    "iso:country": "GB",
    "wof:name": "BH15 4AF",
    "wof:placetype": "postalcode"
  },
  "geometry": {"coordinates":[-1.994438,50.711064],"type":"Point"}
}
