{
  "type": "Feature",
  "properties": {
    "iso:country":"GB",
    "wof:name":"SA2 0RA",
    "wof:placetype":"postalcode"
},
  "geometry": {"coordinates":[-3.96478961827694,51.62107038448529],"type":"Point"}
}