{
  "type": "Feature",
  "properties": {
    "date:inception_lower": "1980-01-01",
    "date:inception_upper": "1980-01-01",
    "iso:country": "GB",
    "wof:name": "SA2 0RA",
    "wof:placetype": "postalcode"
  },
  "geometry": {"coordinates":[-3.96479,51.62107],"type":"Point"}
}
