{
  "type": "Feature",
  "properties": {
    "iso:country": "GB",
    "wof:name": "AL3 8DY",
    "wof:placetype": "postalcode"
  },
  "geometry": {"coordinates":[-0.441578,51.814487],"type":"Point"}
}
