{
  "type": "Feature",
  "properties": {
    "iso:country":"GB",
    "wof:name":"AL3 8DY",
    "wof:placetype":"postalcode"
},
  "geometry": {"coordinates":[-0.44157808079141,51.81448696726429],"type":"Point"}
}