{
  "type": "Feature",
  "properties": {
    "iso:country":"GB",
    "wof:name":"PA18 6BH",
    "wof:placetype":"postalcode"
},
  "geometry": {"coordinates":[-4.89088009223596,55.88615922633588],"type":"Point"}
}