{
  "type": "Feature",
  "properties": {
    "iso:country":"GB",
    "wof:name":"SN10 4BJ",
    "wof:placetype":"postalcode"
},
  "geometry": {"coordinates":[-1.97479822594802,51.28863303517802],"type":"Point"}
}