{
  "type": "Feature",
  "properties": {
    "iso:country": "GB",
    "wof:name": "EH30 9JJ",
    "wof:placetype": "postalcode"
  },
  "geometry": {"coordinates":[-3.387759,55.985862],"type":"Point"}
}
