{
  "type": "Feature",
  "properties": {
    "date:inception_lower": "1980-01-01",
    "date:inception_upper": "1980-01-01",
    "iso:country": "GB",
    "wof:name": "EH30 9JJ",
    "wof:placetype": "postalcode"
  },
  "geometry": {"coordinates":[-3.387759,55.985862],"type":"Point"}
}
