{
  "type": "Feature",
  "properties": {
    "iso:country":"GB",
    "wof:name":"EH30 9JJ",
    "wof:placetype":"postalcode"
},
  "geometry": {"coordinates":[-3.38775858512139,55.98586181228107],"type":"Point"}
}