{
  "type": "Feature",
  "properties": {
    "iso:country": "GB",
    "wof:name": "PE7 8PF",
    "wof:placetype": "postalcode"
  },
  "geometry": {"coordinates":[-0.261825,52.537506],"type":"Point"}
}
