{
  "type": "Feature",
  "properties": {
    "iso:country":"GB",
    "wof:name":"DA8 1GX",
    "wof:placetype":"postalcode"
},
  "geometry": {"coordinates":[0.17752376063493,51.48271154050938],"type":"Point"}
}