{
  "type": "Feature",
  "properties": {
    "iso:country":"GB",
    "wof:name":"S3 7NS",
    "wof:placetype":"postalcode"
},
  "geometry": {"coordinates":[-1.48802958200391,53.38422875124828],"type":"Point"}
}