{
  "type": "Feature",
  "properties": {
    "iso:country":"GB",
    "wof:name":"NR16 1PB",
    "wof:placetype":"postalcode"
},
  "geometry": {"coordinates":[1.13020580034983,52.44358817416445],"type":"Point"}
}