{
  "type": "Feature",
  "properties": {
    "iso:country":"GB",
    "wof:name":"SS17 0GZ",
    "wof:placetype":"postalcode"
},
  "geometry": {"coordinates":[0.42444437304738,51.51727358134242],"type":"Point"}
}