{
  "type": "Feature",
  "properties": {
    "date:inception_lower": "2001-06-01",
    "date:inception_upper": "2001-06-01",
    "iso:country": "GB",
    "wof:name": "SS17 0GZ",
    "wof:placetype": "postalcode"
  },
  "geometry": {"coordinates":[0.424444,51.517274],"type":"Point"}
}
