{
  "type": "Feature",
  "properties": {
    "iso:country":"GB",
    "wof:name":"SE2 9RU",
    "wof:placetype":"postalcode"
},
  "geometry": {"coordinates":[0.12555759543436,51.49230731986346],"type":"Point"}
}