{
  "type": "Feature",
  "properties": {
    "iso:country": "GB",
    "wof:name": "SS2 5SA",
    "wof:placetype": "postalcode"
  },
  "geometry": {"coordinates":[0.712171,51.54065],"type":"Point"}
}
