{
  "type": "Feature",
  "properties": {
    "iso:country":"GB",
    "wof:name":"SS2 5SA",
    "wof:placetype":"postalcode"
},
  "geometry": {"coordinates":[0.71209706836561,51.54062481525065],"type":"Point"}
}