{
  "type": "Feature",
  "properties": {
    "iso:country": "GB",
    "wof:name": "NR6 6PU",
    "wof:placetype": "postalcode"
  },
  "geometry": {"coordinates":[1.259195,52.669816],"type":"Point"}
}
