{
  "type": "Feature",
  "properties": {
    "iso:country":"GB",
    "wof:name":"NR6 6PU",
    "wof:placetype":"postalcode"
},
  "geometry": {"coordinates":[1.25919542535097,52.66981608550075],"type":"Point"}
}