{
  "type": "Feature",
  "properties": {
    "iso:country":"GB",
    "wof:name":"E14 8HG",
    "wof:placetype":"postalcode"
},
  "geometry": {"coordinates":[-0.02939922092902,51.51082291537214],"type":"Point"}
}