{
  "type": "Feature",
  "properties": {
    "date:inception_lower": "1980-01-01",
    "date:inception_upper": "1980-01-01",
    "iso:country": "GB",
    "wof:name": "E14 8HG",
    "wof:placetype": "postalcode"
  },
  "geometry": {"coordinates":[-0.029399,51.510823],"type":"Point"}
}
