{
  "type": "Feature",
  "properties": {
    "date:inception_lower":"2001-06-01",
    "date:inception_upper":"2001-06-30",
    "iso:country":"GB",
    "wof:name":"PR25 1JD",
    "wof:placetype":"postalcode"
},
  "geometry": {"coordinates":[-2.712363,53.689834],"type":"Point"}
}