{
  "type": "Feature",
  "properties": {
    "iso:country":"GB",
    "wof:name":"PR25 1JD",
    "wof:placetype":"postalcode"
},
  "geometry": {"coordinates":[-2.71236298648583,53.68983406813998],"type":"Point"}
}