{
  "type": "Feature",
  "properties": {
    "iso:country":"GB",
    "wof:name":"LE3 2JU",
    "wof:placetype":"postalcode"
},
  "geometry": {"coordinates":[-1.17555760741018,52.60930898810898],"type":"Point"}
}