{
  "type": "Feature",
  "properties": {
    "iso:country": "GB",
    "wof:name": "LE3 2JU",
    "wof:placetype": "postalcode"
  },
  "geometry": {"coordinates":[-1.175558,52.609309],"type":"Point"}
}
