{
  "type": "Feature",
  "properties": {
    "iso:country":"GB",
    "wof:name":"WA4 2DN",
    "wof:placetype":"postalcode"
},
  "geometry": {"coordinates":[-2.56357974219253,53.37621868024422],"type":"Point"}
}