{
  "type": "Feature",
  "properties": {
    "iso:country":"GB",
    "wof:name":"IP9 2XS",
    "wof:placetype":"postalcode"
},
  "geometry": {"coordinates":[1.05226466662486,52.00058213923126],"type":"Point"}
}