{
  "type": "Feature",
  "properties": {
    "iso:country":"GB",
    "wof:name":"CF5 4QF",
    "wof:placetype":"postalcode"
},
  "geometry": {"coordinates":[-3.25644696064388,51.47684083562623],"type":"Point"}
}