{
  "type": "Feature",
  "properties": {
    "date:inception_lower":"1980-01-01",
    "date:inception_upper":"1980-01-31",
    "iso:country":"GB",
    "wof:name":"CF5 4QF",
    "wof:placetype":"postalcode"
},
  "geometry": {"coordinates":[-3.256447,51.476841],"type":"Point"}
}