{
  "type": "Feature",
  "properties": {
    "date:inception_lower": "1980-01-01",
    "date:inception_upper": "1980-01-01",
    "iso:country": "GB",
    "wof:name": "BA4 5NY",
    "wof:placetype": "postalcode"
  },
  "geometry": {"coordinates":[-2.543448,51.188822],"type":"Point"}
}
