{
  "type": "Feature",
  "properties": {
    "iso:country":"GB",
    "wof:name":"BA4 5NY",
    "wof:placetype":"postalcode"
},
  "geometry": {"coordinates":[-2.54344760279762,51.18882157570518],"type":"Point"}
}