{
  "type": "Feature",
  "properties": {
    "iso:country": "GB",
    "wof:name": "PE11 3LY",
    "wof:placetype": "postalcode"
  },
  "geometry": {"coordinates":[-0.160655,52.822093],"type":"Point"}
}
