{
  "type": "Feature",
  "properties": {
    "iso:country":"GB",
    "wof:name":"PE11 3LY",
    "wof:placetype":"postalcode"
},
  "geometry": {"coordinates":[-0.1606554481326,52.82209299833585],"type":"Point"}
}