{
  "type": "Feature",
  "properties": {
    "date:inception_lower":"2008-06-01",
    "date:inception_upper":"2008-06-30",
    "iso:country":"GB",
    "wof:name":"PE11 3LY",
    "wof:placetype":"postalcode"
},
  "geometry": {"coordinates":[-0.160655,52.822093],"type":"Point"}
}