{
  "type": "Feature",
  "properties": {
    "iso:country":"GB",
    "wof:name":"N14 4QX",
    "wof:placetype":"postalcode"
},
  "geometry": {"coordinates":[-0.13140458597904,51.64344018394385],"type":"Point"}
}