{
  "type": "Feature",
  "properties": {
    "iso:country":"GB",
    "wof:name":"IP29 4EU",
    "wof:placetype":"postalcode"
},
  "geometry": {"coordinates":[0.68858685980887,52.13498340401457],"type":"Point"}
}