{
  "type": "Feature",
  "properties": {
    "date:inception_lower": "1980-01-01",
    "date:inception_upper": "1980-01-01",
    "iso:country": "GB",
    "wof:name": "IP29 4EU",
    "wof:placetype": "postalcode"
  },
  "geometry": {"coordinates":[0.688702,52.134969],"type":"Point"}
}
