{
  "type": "Feature",
  "properties": {
    "iso:country": "GB",
    "wof:name": "ML1 1EH",
    "wof:placetype": "postalcode"
  },
  "geometry": {"coordinates":[-3.988394,55.792982],"type":"Point"}
}
