{
  "type": "Feature",
  "properties": {
    "date:inception_lower": "2002-06-01",
    "date:inception_upper": "2002-06-01",
    "iso:country": "GB",
    "wof:name": "ML1 1EH",
    "wof:placetype": "postalcode"
  },
  "geometry": {"coordinates":[-3.988394,55.792982],"type":"Point"}
}
