{
  "type": "Feature",
  "properties": {
    "iso:country":"GB",
    "wof:name":"PL4 7LJ",
    "wof:placetype":"postalcode"
},
  "geometry": {"coordinates":[-4.12663829505717,50.38095618270267],"type":"Point"}
}