{
  "type": "Feature",
  "properties": {
    "iso:country": "GB",
    "wof:name": "PL4 7LJ",
    "wof:placetype": "postalcode"
  },
  "geometry": {"coordinates":[-4.126638,50.380956],"type":"Point"}
}
