{
  "type": "Feature",
  "properties": {
    "iso:country": "GB",
    "wof:name": "DE7 8WH",
    "wof:placetype": "postalcode"
  },
  "geometry": {"coordinates":[-1.307539,52.993104],"type":"Point"}
}
