{
  "type": "Feature",
  "properties": {
    "iso:country":"GB",
    "wof:name":"TS4 2PZ",
    "wof:placetype":"postalcode"
},
  "geometry": {"coordinates":[-1.21782393283259,54.55802961750182],"type":"Point"}
}