{
  "type": "Feature",
  "properties": {
    "iso:country":"GB",
    "wof:name":"ME15 8ER",
    "wof:placetype":"postalcode"
},
  "geometry": {"coordinates":[0.55496554388512,51.25407411217594],"type":"Point"}
}