{
  "type": "Feature",
  "properties": {
    "iso:country":"GB",
    "wof:name":"SO45 4LR",
    "wof:placetype":"postalcode"
},
  "geometry": {"coordinates":[-1.40317712168628,50.85351077696119],"type":"Point"}
}