{
  "type": "Feature",
  "properties": {
    "iso:country":"GB",
    "wof:name":"CH61 6UY",
    "wof:placetype":"postalcode"
},
  "geometry": {"coordinates":[-3.10272910275024,53.33731613665667],"type":"Point"}
}