{
  "type": "Feature",
  "properties": {
    "iso:country":"GB",
    "wof:name":"BL9 5HE",
    "wof:placetype":"postalcode"
},
  "geometry": {"coordinates":[-2.29524623783527,53.60948196287016],"type":"Point"}
}