{
  "type": "Feature",
  "properties": {
    "iso:country": "GB",
    "wof:name": "BL9 5HE",
    "wof:placetype": "postalcode"
  },
  "geometry": {"coordinates":[-2.295246,53.609482],"type":"Point"}
}
