{
  "type": "Feature",
  "properties": {
    "iso:country":"GB",
    "wof:name":"EH12 9AX",
    "wof:placetype":"postalcode"
},
  "geometry": {"coordinates":[-3.28369689809921,55.93118904553607],"type":"Point"}
}