{
  "type": "Feature",
  "properties": {
    "iso:country":"GB",
    "wof:name":"IG10 4RD",
    "wof:placetype":"postalcode"
},
  "geometry": {"coordinates":[0.04276402224898,51.642886094994],"type":"Point"}
}