{
  "type": "Feature",
  "properties": {
    "iso:country": "GB",
    "wof:name": "LL14 1PH",
    "wof:placetype": "postalcode"
  },
  "geometry": {"coordinates":[-3.044113,53.010237],"type":"Point"}
}
