{
  "type": "Feature",
  "properties": {
    "iso:country": "GB",
    "wof:name": "G75 8TR",
    "wof:placetype": "postalcode"
  },
  "geometry": {"coordinates":[-4.216228,55.755409],"type":"Point"}
}
