{
  "type": "Feature",
  "properties": {
    "iso:country":"GB",
    "wof:name":"G75 8TR",
    "wof:placetype":"postalcode"
},
  "geometry": {"coordinates":[-4.216227584253,55.75540858728511],"type":"Point"}
}