{
  "type": "Feature",
  "properties": {
    "date:inception_lower": "1996-12-01",
    "date:inception_upper": "1996-12-01",
    "iso:country": "GB",
    "wof:name": "TW1 2TH",
    "wof:placetype": "postalcode"
  },
  "geometry": {"coordinates":[-0.306982,51.454595],"type":"Point"}
}
