{
  "type": "Feature",
  "properties": {
    "iso:country":"GB",
    "wof:name":"TW1 2TH",
    "wof:placetype":"postalcode"
},
  "geometry": {"coordinates":[-0.30698219253148,51.45459458996661],"type":"Point"}
}