{
  "type": "Feature",
  "properties": {
    "iso:country":"GB",
    "wof:name":"NE23 6NH",
    "wof:placetype":"postalcode"
},
  "geometry": {"coordinates":[-1.58821200660566,55.07059533438614],"type":"Point"}
}