{
  "type": "Feature",
  "properties": {
    "date:inception_lower": "1980-01-01",
    "date:inception_upper": "1980-01-01",
    "iso:country": "GB",
    "wof:name": "NE23 6NH",
    "wof:placetype": "postalcode"
  },
  "geometry": {"coordinates":[-1.588212,55.070595],"type":"Point"}
}
