{
  "type": "Feature",
  "properties": {
    "iso:country":"GB",
    "wof:name":"TN23 4TW",
    "wof:placetype":"postalcode"
},
  "geometry": {"coordinates":[0.86114810798203,51.14636705198287],"type":"Point"}
}