{
  "type": "Feature",
  "properties": {
    "date:inception_lower": "2008-03-01",
    "date:inception_upper": "2008-03-01",
    "iso:country": "GB",
    "wof:name": "TN23 4TW",
    "wof:placetype": "postalcode"
  },
  "geometry": {"coordinates":[0.861179,51.146366],"type":"Point"}
}
