{
  "type": "Feature",
  "properties": {
    "iso:country": "GB",
    "wof:name": "TN23 4TW",
    "wof:placetype": "postalcode"
  },
  "geometry": {"coordinates":[0.861179,51.146366],"type":"Point"}
}
