{
  "type": "Feature",
  "properties": {
    "date:inception_lower": "2020-01-01",
    "date:inception_upper": "2020-01-01",
    "iso:country": "GB",
    "wof:name": "TN21 9BL",
    "wof:placetype": "postalcode"
  },
  "geometry": {"coordinates":[0.251357,50.931204],"type":"Point"}
}
