{
  "type": "Feature",
  "properties": {
    "iso:country":"GB",
    "wof:name":"S70 4RF",
    "wof:placetype":"postalcode"
},
  "geometry": {"coordinates":[-1.45204187589476,53.5325066219423],"type":"Point"}
}