{
  "type": "Feature",
  "properties": {
    "iso:country":"GB",
    "wof:name":"B28 9PW",
    "wof:placetype":"postalcode"
},
  "geometry": {"coordinates":[-1.83056372041882,52.42790603173561],"type":"Point"}
}