{
  "type": "Feature",
  "properties": {
    "iso:country":"GB",
    "wof:name":"SA1 4EZ",
    "wof:placetype":"postalcode"
},
  "geometry": {"coordinates":[-3.95220473717471,51.62001246941257],"type":"Point"}
}