{
  "type": "Feature",
  "properties": {
    "iso:country":"GB",
    "wof:name":"SY2 5AA",
    "wof:placetype":"postalcode"
},
  "geometry": {"coordinates":[-2.74064948114838,52.70794766347117],"type":"Point"}
}