{
  "type": "Feature",
  "properties": {
    "iso:country":"GB",
    "wof:name":"NW8 7PB",
    "wof:placetype":"postalcode"
},
  "geometry": {"coordinates":[-0.17044008317535,51.53175821527976],"type":"Point"}
}