{
  "type": "Feature",
  "properties": {
    "iso:country":"GB",
    "wof:name":"HS2 0PB",
    "wof:placetype":"postalcode"
},
  "geometry": {"coordinates":[-6.27652747440257,58.20811583060213],"type":"Point"}
}