{
  "type": "Feature",
  "properties": {
    "iso:country": "GB",
    "wof:name": "SA15 9DQ",
    "wof:placetype": "postalcode"
  },
  "geometry": {"coordinates":[-4.16677,51.680659],"type":"Point"}
}
