{
  "type": "Feature",
  "properties": {
    "date:inception_lower": "1980-01-01",
    "date:inception_upper": "1980-01-01",
    "iso:country": "GB",
    "wof:name": "WA15 8NJ",
    "wof:placetype": "postalcode"
  },
  "geometry": {"coordinates":[-2.316666,53.373327],"type":"Point"}
}
