{
  "type": "Feature",
  "properties": {
    "date:inception_lower":"1980-01-01",
    "date:inception_upper":"1980-01-31",
    "iso:country":"GB",
    "wof:name":"DY8 1JZ",
    "wof:placetype":"postalcode"
},
  "geometry": {"coordinates":[-2.135085,52.455114],"type":"Point"}
}