{
  "type": "Feature",
  "properties": {
    "iso:country":"GB",
    "wof:name":"B35 6HJ",
    "wof:placetype":"postalcode"
},
  "geometry": {"coordinates":[-1.79042919516391,52.52405256747438],"type":"Point"}
}