{
  "type": "Feature",
  "properties": {
    "iso:country":"GB",
    "wof:name":"DY13 0AQ",
    "wof:placetype":"postalcode"
},
  "geometry": {"coordinates":[-2.28598819199498,52.33031736117178],"type":"Point"}
}