{
  "type": "Feature",
  "properties": {
    "iso:country": "GB",
    "wof:name": "YO26 6QD",
    "wof:placetype": "postalcode"
  },
  "geometry": {"coordinates":[-1.142754,53.972016],"type":"Point"}
}
