{
  "type": "Feature",
  "properties": {
    "iso:country":"GB",
    "wof:name":"YO26 6QD",
    "wof:placetype":"postalcode"
},
  "geometry": {"coordinates":[-1.14291934534955,53.97170347283115],"type":"Point"}
}