{
  "type": "Feature",
  "properties": {
    "iso:country":"GB",
    "wof:name":"DL13 5PR",
    "wof:placetype":"postalcode"
},
  "geometry": {"coordinates":[-1.84119079612528,54.62708899292244],"type":"Point"}
}