{
  "type": "Feature",
  "properties": {
    "iso:country": "GB",
    "wof:name": "DL13 5PR",
    "wof:placetype": "postalcode"
  },
  "geometry": {"coordinates":[-1.841091,54.627079],"type":"Point"}
}
