{
  "type": "Feature",
  "properties": {
    "date:inception_lower": "1980-01-01",
    "date:inception_upper": "1980-01-01",
    "iso:country": "GB",
    "wof:name": "DL13 5PR",
    "wof:placetype": "postalcode"
  },
  "geometry": {"coordinates":[-1.841199,54.627097],"type":"Point"}
}
