{
  "type": "Feature",
  "properties": {
    "date:inception_lower": "1980-01-01",
    "date:inception_upper": "1980-01-01",
    "iso:country": "GB",
    "wof:name": "EH11 3EF",
    "wof:placetype": "postalcode"
  },
  "geometry": {"coordinates":[-3.262138,55.932728],"type":"Point"}
}
