{
  "type": "Feature",
  "properties": {
    "date:inception_lower": "1990-02-01",
    "date:inception_upper": "1990-02-01",
    "iso:country": "GB",
    "wof:name": "WN8 6UU",
    "wof:placetype": "postalcode"
  },
  "geometry": {"coordinates":[-2.76432,53.561024],"type":"Point"}
}
