{
  "type": "Feature",
  "properties": {
    "iso:country":"GB",
    "wof:name":"NG21 0NN",
    "wof:placetype":"postalcode"
},
  "geometry": {"coordinates":[-1.12423704825715,53.08695798265832],"type":"Point"}
}