{
  "type": "Feature",
  "properties": {
    "iso:country":"GB",
    "wof:name":"PH1 3FB",
    "wof:placetype":"postalcode"
},
  "geometry": {"coordinates":[-3.5058547133823,56.41703169105581],"type":"Point"}
}