{
  "type": "Feature",
  "properties": {
    "date:inception_lower": "1993-02-01",
    "date:inception_upper": "1993-02-01",
    "iso:country": "GB",
    "wof:name": "PH1 3FB",
    "wof:placetype": "postalcode"
  },
  "geometry": {"coordinates":[-3.505855,56.417032],"type":"Point"}
}
