{
  "type": "Feature",
  "properties": {
    "iso:country":"GB",
    "wof:name":"EX10 9JA",
    "wof:placetype":"postalcode"
},
  "geometry": {"coordinates":[-3.23729175214472,50.69346112931247],"type":"Point"}
}