{
  "type": "Feature",
  "properties": {
    "iso:country":"GB",
    "wof:name":"EN4 8QL",
    "wof:placetype":"postalcode"
},
  "geometry": {"coordinates":[-0.15247382107747,51.64353080626277],"type":"Point"}
}