{
  "type": "Feature",
  "properties": {
    "date:inception_lower":"1980-01-01",
    "date:inception_upper":"1980-01-31",
    "iso:country":"GB",
    "wof:name":"LL48 6DH",
    "wof:placetype":"postalcode"
},
  "geometry": {"coordinates":[-4.065153,52.934667],"type":"Point"}
}