{
  "type": "Feature",
  "properties": {
    "date:inception_lower": "1980-01-01",
    "date:inception_upper": "1980-01-01",
    "iso:country": "GB",
    "wof:name": "CT14 0NB",
    "wof:placetype": "postalcode"
  },
  "geometry": {"coordinates":[1.346611,51.235379],"type":"Point"}
}
