{
  "type": "Feature",
  "properties": {
    "iso:country": "GB",
    "wof:name": "CT14 0NB",
    "wof:placetype": "postalcode"
  },
  "geometry": {"coordinates":[1.34664,51.235387],"type":"Point"}
}
