{
  "type": "Feature",
  "properties": {
    "iso:country":"GB",
    "wof:name":"CT14 0NB",
    "wof:placetype":"postalcode"
},
  "geometry": {"coordinates":[1.3466408039291,51.23538797846625],"type":"Point"}
}