{
  "type": "Feature",
  "properties": {
    "iso:country":"GB",
    "wof:name":"NR2 4TW",
    "wof:placetype":"postalcode"
},
  "geometry": {"coordinates":[1.28093525146677,52.63932105096552],"type":"Point"}
}