{
  "type": "Feature",
  "properties": {
    "iso:country": "GB",
    "wof:name": "NR2 4TW",
    "wof:placetype": "postalcode"
  },
  "geometry": {"coordinates":[1.280935,52.639321],"type":"Point"}
}
