{
  "type": "Feature",
  "properties": {
    "iso:country":"GB",
    "wof:name":"S80 1PZ",
    "wof:placetype":"postalcode"
},
  "geometry": {"coordinates":[-1.12329219068799,53.31098780864706],"type":"Point"}
}