{
  "type": "Feature",
  "properties": {
    "date:inception_lower": "2020-09-01",
    "date:inception_upper": "2020-09-01",
    "iso:country": "GB",
    "wof:name": "EN4 0FL",
    "wof:placetype": "postalcode"
  },
  "geometry": {"coordinates":[-0.137267,51.659525],"type":"Point"}
}
