{
  "type": "Feature",
  "properties": {
    "date:inception_lower":"1980-01-01",
    "date:inception_upper":"1980-01-31",
    "iso:country":"GB",
    "wof:name":"SN9 6JP",
    "wof:placetype":"postalcode"
},
  "geometry": {"coordinates":[-1.803888,51.318366],"type":"Point"}
}