{
  "type": "Feature",
  "properties": {
    "iso:country":"GB",
    "wof:name":"SN9 6JP",
    "wof:placetype":"postalcode"
},
  "geometry": {"coordinates":[-1.80389747225179,51.31837858959267],"type":"Point"}
}