{
  "type": "Feature",
  "properties": {
    "iso:country": "GB",
    "wof:name": "CB1 9ND",
    "wof:placetype": "postalcode"
  },
  "geometry": {"coordinates":[0.182213,52.190126],"type":"Point"}
}
