{
  "type": "Feature",
  "properties": {
    "iso:country":"GB",
    "wof:name":"CB1 9ND",
    "wof:placetype":"postalcode"
},
  "geometry": {"coordinates":[0.18221304831728,52.19012589698931],"type":"Point"}
}