{
  "type": "Feature",
  "properties": {
    "iso:country":"GB",
    "wof:name":"L24 2UZ",
    "wof:placetype":"postalcode"
},
  "geometry": {"coordinates":[-2.83538756204108,53.34573514556546],"type":"Point"}
}