{
  "type": "Feature",
  "properties": {
    "date:inception_lower":"1986-04-01",
    "date:inception_upper":"1986-04-30",
    "iso:country":"GB",
    "wof:name":"LA4 4XB",
    "wof:placetype":"postalcode"
},
  "geometry": {"coordinates":[-2.864927,54.061002],"type":"Point"}
}