{
  "type": "Feature",
  "properties": {
    "iso:country":"GB",
    "wof:name":"SA16 0HE",
    "wof:placetype":"postalcode"
},
  "geometry": {"coordinates":[-4.25990930427943,51.67951719255357],"type":"Point"}
}