{
  "type": "Feature",
  "properties": {
    "iso:country":"GB",
    "wof:name":"NG9 3BA",
    "wof:placetype":"postalcode"
},
  "geometry": {"coordinates":[-1.23588197773888,52.93799103928325],"type":"Point"}
}