{
  "type": "Feature",
  "properties": {
    "date:inception_lower": "2007-04-01",
    "date:inception_upper": "2007-04-01",
    "iso:country": "GB",
    "wof:name": "IP1 5NS",
    "wof:placetype": "postalcode"
  },
  "geometry": {"coordinates":[1.116574,52.068347],"type":"Point"}
}
