{
  "type": "Feature",
  "properties": {
    "iso:country": "GB",
    "wof:name": "S42 5BX",
    "wof:placetype": "postalcode"
  },
  "geometry": {"coordinates":[-1.361452,53.193154],"type":"Point"}
}
