{
  "type": "Feature",
  "properties": {
    "date:inception_lower": "2004-06-01",
    "date:inception_upper": "2004-06-01",
    "iso:country": "GB",
    "wof:name": "S42 5BX",
    "wof:placetype": "postalcode"
  },
  "geometry": {"coordinates":[-1.361159,53.192713],"type":"Point"}
}
