{
  "type": "Feature",
  "properties": {
    "iso:country":"GB",
    "wof:name":"NG5 5QR",
    "wof:placetype":"postalcode"
},
  "geometry": {"coordinates":[-1.1556253761676,53.00813229620258],"type":"Point"}
}