{
  "type": "Feature",
  "properties": {
    "iso:country":"GB",
    "wof:name":"GU34 3RR",
    "wof:placetype":"postalcode"
},
  "geometry": {"coordinates":[-0.98423611604269,51.09751726851133],"type":"Point"}
}