{
  "type": "Feature",
  "properties": {
    "date:inception_lower": "1994-12-01",
    "date:inception_upper": "1994-12-01",
    "iso:country": "GB",
    "wof:name": "SO40 2TN",
    "wof:placetype": "postalcode"
  },
  "geometry": {"coordinates":[-1.511494,50.927438],"type":"Point"}
}
