{
  "type": "Feature",
  "properties": {
    "iso:country": "GB",
    "wof:name": "BA2 7LS",
    "wof:placetype": "postalcode"
  },
  "geometry": {"coordinates":[-2.327045,51.30288],"type":"Point"}
}
