{
  "type": "Feature",
  "properties": {
    "iso:country":"GB",
    "wof:name":"SK6 3DS",
    "wof:placetype":"postalcode"
},
  "geometry": {"coordinates":[-2.09921235561257,53.40820471095675],"type":"Point"}
}