{
  "type": "Feature",
  "properties": {
    "iso:country": "GB",
    "wof:name": "SK6 3DS",
    "wof:placetype": "postalcode"
  },
  "geometry": {"coordinates":[-2.099212,53.408205],"type":"Point"}
}
