{
  "type": "Feature",
  "properties": {
    "iso:country":"GB",
    "wof:name":"GL7 5BY",
    "wof:placetype":"postalcode"
},
  "geometry": {"coordinates":[-1.79491588925197,51.73900941457493],"type":"Point"}
}