{
  "type": "Feature",
  "properties": {
    "iso:country":"GB",
    "wof:name":"BR1 1BY",
    "wof:placetype":"postalcode"
},
  "geometry": {"coordinates":[0.01089664281874,51.4080171244457],"type":"Point"}
}