{
  "type": "Feature",
  "properties": {
    "iso:country": "GB",
    "wof:name": "TW16 7PJ",
    "wof:placetype": "postalcode"
  },
  "geometry": {"coordinates":[-0.423289,51.425885],"type":"Point"}
}
