{
  "type": "Feature",
  "properties": {
    "iso:country":"GB",
    "wof:name":"IP14 6RU",
    "wof:placetype":"postalcode"
},
  "geometry": {"coordinates":[1.18152262462993,52.22276260329638],"type":"Point"}
}