{
  "type": "Feature",
  "properties": {
    "iso:country":"GB",
    "wof:name":"FK3 8NE",
    "wof:placetype":"postalcode"
},
  "geometry": {"coordinates":[-3.72619181306287,56.01022559096173],"type":"Point"}
}