{
  "type": "Feature",
  "properties": {
    "date:inception_lower": "1980-01-01",
    "date:inception_upper": "1980-01-01",
    "iso:country": "GB",
    "wof:name": "FK3 8NE",
    "wof:placetype": "postalcode"
  },
  "geometry": {"coordinates":[-3.726192,56.010226],"type":"Point"}
}
