{
  "type": "Feature",
  "properties": {
    "iso:country":"GB",
    "wof:name":"KA20 3HD",
    "wof:placetype":"postalcode"
},
  "geometry": {"coordinates":[-4.75604119773411,55.6391393869378],"type":"Point"}
}