{
  "type": "Feature",
  "properties": {
    "iso:country": "GB",
    "wof:name": "NE15 9DA",
    "wof:placetype": "postalcode"
  },
  "geometry": {"coordinates":[-1.755763,54.997106],"type":"Point"}
}
