{
  "type": "Feature",
  "properties": {
    "iso:country":"GB",
    "wof:name":"BH2 5LT",
    "wof:placetype":"postalcode"
},
  "geometry": {"coordinates":[-1.88455516300727,50.71959540531404],"type":"Point"}
}