{
  "type": "Feature",
  "properties": {
    "iso:country": "GB",
    "wof:name": "TA23 0PB",
    "wof:placetype": "postalcode"
  },
  "geometry": {"coordinates":[-3.363054,51.16249],"type":"Point"}
}
