{
  "type": "Feature",
  "properties": {
    "iso:country":"GB",
    "wof:name":"WV12 4BA",
    "wof:placetype":"postalcode"
},
  "geometry": {"coordinates":[-2.03110784486337,52.59769839539481],"type":"Point"}
}