{
  "type": "Feature",
  "properties": {
    "date:inception_lower": "2012-08-01",
    "date:inception_upper": "2012-08-01",
    "iso:country": "GB",
    "wof:name": "LE1 7AE",
    "wof:placetype": "postalcode"
  },
  "geometry": {"coordinates":[-1.120833,52.626033],"type":"Point"}
}
