{
  "type": "Feature",
  "properties": {
    "iso:country":"GB",
    "wof:name":"LE1 7AE",
    "wof:placetype":"postalcode"
},
  "geometry": {"coordinates":[-1.12083271072049,52.62603258740484],"type":"Point"}
}