{
  "type": "Feature",
  "properties": {
    "date:inception_lower": "1980-01-01",
    "date:inception_upper": "1980-01-01",
    "iso:country": "GB",
    "wof:name": "NR16 1EH",
    "wof:placetype": "postalcode"
  },
  "geometry": {"coordinates":[1.17978,52.527541],"type":"Point"}
}
