{
  "type": "Feature",
  "properties": {
    "iso:country":"GB",
    "wof:name":"ST8 6DE",
    "wof:placetype":"postalcode"
},
  "geometry": {"coordinates":[-2.17235746647159,53.12345596270051],"type":"Point"}
}