{
  "type": "Feature",
  "properties": {
    "iso:country": "GB",
    "wof:name": "B7 5LE",
    "wof:placetype": "postalcode"
  },
  "geometry": {"coordinates":[-1.863112,52.503374],"type":"Point"}
}
