{
  "type": "Feature",
  "properties": {
    "iso:country":"GB",
    "wof:name":"B7 5LE",
    "wof:placetype":"postalcode"
},
  "geometry": {"coordinates":[-1.86311161361064,52.50337409857219],"type":"Point"}
}