{
  "type": "Feature",
  "properties": {
    "iso:country":"GB",
    "wof:name":"G53 7DN",
    "wof:placetype":"postalcode"
},
  "geometry": {"coordinates":[-4.36020480919719,55.82337936855058],"type":"Point"}
}