{
  "type": "Feature",
  "properties": {
    "iso:country": "GB",
    "wof:name": "BD13 5AL",
    "wof:placetype": "postalcode"
  },
  "geometry": {"coordinates":[-1.892853,53.828695],"type":"Point"}
}
