{
  "type": "Feature",
  "properties": {
    "iso:country":"GB",
    "wof:name":"BD13 5AL",
    "wof:placetype":"postalcode"
},
  "geometry": {"coordinates":[-1.89285340339074,53.82869471821821],"type":"Point"}
}