{
  "type": "Feature",
  "properties": {
    "date:inception_lower": "1980-01-01",
    "date:inception_upper": "1980-01-01",
    "iso:country": "GB",
    "wof:name": "BD13 5AL",
    "wof:placetype": "postalcode"
  },
  "geometry": {"coordinates":[-1.892853,53.828695],"type":"Point"}
}
