{
  "type": "Feature",
  "properties": {
    "iso:country":"GB",
    "wof:name":"DD6 9DX",
    "wof:placetype":"postalcode"
},
  "geometry": {"coordinates":[-2.87316702616983,56.4430535175483],"type":"Point"}
}