{
  "type": "Feature",
  "properties": {
    "iso:country":"GB",
    "wof:name":"DN11 8SG",
    "wof:placetype":"postalcode"
},
  "geometry": {"coordinates":[-1.07094828138815,53.40946128091034],"type":"Point"}
}