{
  "type": "Feature",
  "properties": {
    "iso:country": "GB",
    "wof:name": "DN11 8SG",
    "wof:placetype": "postalcode"
  },
  "geometry": {"coordinates":[-1.070822,53.409093],"type":"Point"}
}
