{
  "type": "Feature",
  "properties": {
    "date:inception_lower": "1980-01-01",
    "date:inception_upper": "1980-01-01",
    "iso:country": "GB",
    "wof:name": "N9 7AB",
    "wof:placetype": "postalcode"
  },
  "geometry": {"coordinates":[-0.060614,51.627547],"type":"Point"}
}
