{
  "type": "Feature",
  "properties": {
    "date:inception_lower": "1980-01-01",
    "date:inception_upper": "1980-01-01",
    "iso:country": "GB",
    "wof:name": "B23 5JD",
    "wof:placetype": "postalcode"
  },
  "geometry": {"coordinates":[-1.868066,52.536346],"type":"Point"}
}
