{
  "type": "Feature",
  "properties": {
    "iso:country":"GB",
    "wof:name":"DT2 9RB",
    "wof:placetype":"postalcode"
},
  "geometry": {"coordinates":[-2.45808199836893,50.74042384964288],"type":"Point"}
}