{
  "type": "Feature",
  "properties": {
    "iso:country":"GB",
    "wof:name":"DL9 4RP",
    "wof:placetype":"postalcode"
},
  "geometry": {"coordinates":[-1.67896274521377,54.38022921256664],"type":"Point"}
}