{
  "type": "Feature",
  "properties": {
    "iso:country": "GB",
    "wof:name": "S66 2DD",
    "wof:placetype": "postalcode"
  },
  "geometry": {"coordinates":[-1.289005,53.424747],"type":"Point"}
}
