{
  "type": "Feature",
  "properties": {
    "iso:country":"GB",
    "wof:name":"S66 2DD",
    "wof:placetype":"postalcode"
},
  "geometry": {"coordinates":[-1.28900523262851,53.42474685249967],"type":"Point"}
}