{
  "type": "Feature",
  "properties": {
    "date:inception_lower": "1997-06-01",
    "date:inception_upper": "1997-06-01",
    "iso:country": "GB",
    "wof:name": "S66 2DD",
    "wof:placetype": "postalcode"
  },
  "geometry": {"coordinates":[-1.289005,53.424747],"type":"Point"}
}
