{
  "type": "Feature",
  "properties": {
    "iso:country":"GB",
    "wof:name":"LL18 3SF",
    "wof:placetype":"postalcode"
},
  "geometry": {"coordinates":[-3.48026605798708,53.32198275116211],"type":"Point"}
}