{
  "type": "Feature",
  "properties": {
    "date:inception_lower": "2008-03-01",
    "date:inception_upper": "2008-03-01",
    "iso:country": "GB",
    "wof:name": "L3 5NP",
    "wof:placetype": "postalcode"
  },
  "geometry": {"coordinates":[-2.971214,53.409346],"type":"Point"}
}
