{
  "type": "Feature",
  "properties": {
    "iso:country": "GB",
    "wof:name": "L3 5NP",
    "wof:placetype": "postalcode"
  },
  "geometry": {"coordinates":[-2.971214,53.409346],"type":"Point"}
}
