{
  "type": "Feature",
  "properties": {
    "iso:country":"GB",
    "wof:name":"HU6 9EB",
    "wof:placetype":"postalcode"
},
  "geometry": {"coordinates":[-0.38122233606551,53.79036158073406],"type":"Point"}
}