{
  "type": "Feature",
  "properties": {
    "iso:country": "GB",
    "wof:name": "PL19 8DF",
    "wof:placetype": "postalcode"
  },
  "geometry": {"coordinates":[-4.154081,50.543713],"type":"Point"}
}
