{
  "type": "Feature",
  "properties": {
    "date:inception_lower": "2000-06-01",
    "date:inception_upper": "2000-06-01",
    "iso:country": "GB",
    "wof:name": "PL19 8DF",
    "wof:placetype": "postalcode"
  },
  "geometry": {"coordinates":[-4.154041,50.543759],"type":"Point"}
}
