{
  "type": "Feature",
  "properties": {
    "iso:country":"GB",
    "wof:name":"BN3 3EL",
    "wof:placetype":"postalcode"
},
  "geometry": {"coordinates":[-0.16252662269827,50.83326973279017],"type":"Point"}
}