{
  "type": "Feature",
  "properties": {
    "iso:country": "GB",
    "wof:name": "PH1 2HJ",
    "wof:placetype": "postalcode"
  },
  "geometry": {"coordinates":[-3.471331,56.402872],"type":"Point"}
}
