{
  "type": "Feature",
  "properties": {
    "iso:country": "GB",
    "wof:name": "WA6 7BW",
    "wof:placetype": "postalcode"
  },
  "geometry": {"coordinates":[-2.732026,53.294782],"type":"Point"}
}
