{
  "type": "Feature",
  "properties": {
    "iso:country":"GB",
    "wof:name":"UB6 9PB",
    "wof:placetype":"postalcode"
},
  "geometry": {"coordinates":[-0.35125311120332,51.53612028228802],"type":"Point"}
}