{
  "type": "Feature",
  "properties": {
    "iso:country": "GB",
    "wof:name": "UB6 9PB",
    "wof:placetype": "postalcode"
  },
  "geometry": {"coordinates":[-0.351253,51.53612],"type":"Point"}
}
