{
  "type": "Feature",
  "properties": {
    "date:inception_lower":"1980-01-01",
    "date:inception_upper":"1980-01-31",
    "iso:country":"GB",
    "wof:name":"UB6 9PB",
    "wof:placetype":"postalcode"
},
  "geometry": {"coordinates":[-0.351253,51.53612],"type":"Point"}
}