{
  "type": "Feature",
  "properties": {
    "iso:country":"GB",
    "wof:name":"SO23 8UT",
    "wof:placetype":"postalcode"
},
  "geometry": {"coordinates":[-1.32037116288966,51.06425436802247],"type":"Point"}
}