{
  "type": "Feature",
  "properties": {
    "date:inception_lower":"1980-01-01",
    "date:inception_upper":"1980-01-31",
    "iso:country":"GB",
    "wof:name":"SO23 8UT",
    "wof:placetype":"postalcode"
},
  "geometry": {"coordinates":[-1.320229,51.064365],"type":"Point"}
}