{
  "type": "Feature",
  "properties": {
    "iso:country":"GB",
    "wof:name":"RG12 0UD",
    "wof:placetype":"postalcode"
},
  "geometry": {"coordinates":[-0.7326853766703,51.39830994140044],"type":"Point"}
}