{
  "type": "Feature",
  "properties": {
    "date:inception_lower":"2005-01-01",
    "date:inception_upper":"2005-01-31",
    "iso:country":"GB",
    "wof:name":"CO11 1AL",
    "wof:placetype":"postalcode"
},
  "geometry": {"coordinates":[1.08122,51.944183],"type":"Point"}
}