{
  "type": "Feature",
  "properties": {
    "iso:country":"GB",
    "wof:name":"CO11 1AL",
    "wof:placetype":"postalcode"
},
  "geometry": {"coordinates":[1.08121972258238,51.94418262751446],"type":"Point"}
}