{
  "type": "Feature",
  "properties": {
    "iso:country":"GB",
    "wof:name":"NE62 5XT",
    "wof:placetype":"postalcode"
},
  "geometry": {"coordinates":[-1.59460870360438,55.16590491991575],"type":"Point"}
}