{
  "type": "Feature",
  "properties": {
    "iso:country":"GB",
    "wof:name":"PL19 9PN",
    "wof:placetype":"postalcode"
},
  "geometry": {"coordinates":[-4.11321498289739,50.58905682235224],"type":"Point"}
}