{
  "type": "Feature",
  "properties": {
    "iso:country":"GB",
    "wof:name":"M26 3NH",
    "wof:placetype":"postalcode"
},
  "geometry": {"coordinates":[-2.35316132452391,53.56755622089436],"type":"Point"}
}