{
  "type": "Feature",
  "properties": {
    "date:inception_lower": "1980-01-01",
    "date:inception_upper": "1980-01-01",
    "iso:country": "GB",
    "wof:name": "ST7 2RW",
    "wof:placetype": "postalcode"
  },
  "geometry": {"coordinates":[-2.29221,53.091742],"type":"Point"}
}
