{
  "type": "Feature",
  "properties": {
    "iso:country":"GB",
    "wof:name":"ST7 2RW",
    "wof:placetype":"postalcode"
},
  "geometry": {"coordinates":[-2.2922098852158,53.09174229005193],"type":"Point"}
}