{
  "type": "Feature",
  "properties": {
    "iso:country":"GB",
    "wof:name":"G40 2RS",
    "wof:placetype":"postalcode"
},
  "geometry": {"coordinates":[-4.22942532945533,55.85367240966753],"type":"Point"}
}