{
  "type": "Feature",
  "properties": {
    "iso:country":"GB",
    "wof:name":"SS7 3YG",
    "wof:placetype":"postalcode"
},
  "geometry": {"coordinates":[0.59823540774901,51.56093798579387],"type":"Point"}
}