{
  "type": "Feature",
  "properties": {
    "date:inception_lower":"2003-01-01",
    "date:inception_upper":"2003-01-31",
    "iso:country":"GB",
    "wof:name":"IP19 9BN",
    "wof:placetype":"postalcode"
},
  "geometry": {"coordinates":[1.554183,52.327483],"type":"Point"}
}