{
  "type": "Feature",
  "properties": {
    "iso:country": "GB",
    "wof:name": "IP19 9BN",
    "wof:placetype": "postalcode"
  },
  "geometry": {"coordinates":[1.554183,52.327483],"type":"Point"}
}
