{
  "type": "Feature",
  "properties": {
    "iso:country": "GB",
    "wof:name": "PL30 3EG",
    "wof:placetype": "postalcode"
  },
  "geometry": {"coordinates":[-4.784981,50.53727],"type":"Point"}
}
