{
  "type": "Feature",
  "properties": {
    "iso:country":"GB",
    "wof:name":"PL30 3EG",
    "wof:placetype":"postalcode"
},
  "geometry": {"coordinates":[-4.78498135633448,50.53726981710474],"type":"Point"}
}