{
  "type": "Feature",
  "properties": {
    "date:inception_lower": "1980-01-01",
    "date:inception_upper": "1980-01-01",
    "iso:country": "GB",
    "wof:name": "HX6 2EW",
    "wof:placetype": "postalcode"
  },
  "geometry": {"coordinates":[-1.91342,53.712317],"type":"Point"}
}
