{
  "type": "Feature",
  "properties": {
    "date:inception_lower":"1997-12-01",
    "date:inception_upper":"1997-12-31",
    "iso:country":"GB",
    "wof:name":"BS37 6LN",
    "wof:placetype":"postalcode"
},
  "geometry": {"coordinates":[-2.380969,51.533199],"type":"Point"}
}