{
  "type": "Feature",
  "properties": {
    "iso:country":"GB",
    "wof:name":"BS37 6LN",
    "wof:placetype":"postalcode"
},
  "geometry": {"coordinates":[-2.38096938146793,51.53319930784656],"type":"Point"}
}