{
  "type": "Feature",
  "properties": {
    "iso:country": "GB",
    "wof:name": "BS37 6LN",
    "wof:placetype": "postalcode"
  },
  "geometry": {"coordinates":[-2.380969,51.533199],"type":"Point"}
}
