{
  "type": "Feature",
  "properties": {
    "iso:country":"GB",
    "wof:name":"ME16 9EY",
    "wof:placetype":"postalcode"
},
  "geometry": {"coordinates":[0.46996561713704,51.26136742667612],"type":"Point"}
}