{
  "type": "Feature",
  "properties": {
    "iso:country":"GB",
    "wof:name":"LE15 7QE",
    "wof:placetype":"postalcode"
},
  "geometry": {"coordinates":[-0.68621546941187,52.73851582294116],"type":"Point"}
}