{
  "type": "Feature",
  "properties": {
    "date:inception_lower":"1995-01-01",
    "date:inception_upper":"1995-01-31",
    "iso:country":"GB",
    "wof:name":"LE15 7QE",
    "wof:placetype":"postalcode"
},
  "geometry": {"coordinates":[-0.686206,52.738536],"type":"Point"}
}