{
  "type": "Feature",
  "properties": {
    "iso:country": "GB",
    "wof:name": "WF9 3DW",
    "wof:placetype": "postalcode"
  },
  "geometry": {"coordinates":[-1.329813,53.588539],"type":"Point"}
}
