{
  "type": "Feature",
  "properties": {
    "date:inception_lower":"1980-01-01",
    "date:inception_upper":"1980-01-31",
    "iso:country":"GB",
    "wof:name":"WF9 3DW",
    "wof:placetype":"postalcode"
},
  "geometry": {"coordinates":[-1.329813,53.588539],"type":"Point"}
}