{
  "type": "Feature",
  "properties": {
    "iso:country":"GB",
    "wof:name":"WF9 3DW",
    "wof:placetype":"postalcode"
},
  "geometry": {"coordinates":[-1.32981317393735,53.58853880814196],"type":"Point"}
}