{
  "type": "Feature",
  "properties": {
    "iso:country":"GB",
    "wof:name":"OX26 2HN",
    "wof:placetype":"postalcode"
},
  "geometry": {"coordinates":[-1.15676664450534,51.90413837257142],"type":"Point"}
}