{
  "type": "Feature",
  "properties": {
    "iso:country":"GB",
    "wof:name":"KT10 9UA",
    "wof:placetype":"postalcode"
},
  "geometry": {"coordinates":[-0.36042977675622,51.37243518689913],"type":"Point"}
}