{
  "type": "Feature",
  "properties": {
    "iso:country": "GB",
    "wof:name": "KT10 9UA",
    "wof:placetype": "postalcode"
  },
  "geometry": {"coordinates":[-0.36043,51.372435],"type":"Point"}
}
