{
  "type": "Feature",
  "properties": {
    "iso:country":"GB",
    "wof:name":"LS25 5HA",
    "wof:placetype":"postalcode"
},
  "geometry": {"coordinates":[-1.25068138805949,53.75673640303376],"type":"Point"}
}