{
  "type": "Feature",
  "properties": {
    "date:inception_lower":"1980-01-01",
    "date:inception_upper":"1980-01-31",
    "iso:country":"GB",
    "wof:name":"LS25 5HA",
    "wof:placetype":"postalcode"
},
  "geometry": {"coordinates":[-1.250681,53.756736],"type":"Point"}
}