{
  "type": "Feature",
  "properties": {
    "date:inception_lower":"1980-01-01",
    "date:inception_upper":"1980-01-31",
    "iso:country":"GB",
    "wof:name":"CT2 9HF",
    "wof:placetype":"postalcode"
},
  "geometry": {"coordinates":[1.047307,51.313297],"type":"Point"}
}