{
  "type": "Feature",
  "properties": {
    "iso:country": "GB",
    "wof:name": "CT2 9HF",
    "wof:placetype": "postalcode"
  },
  "geometry": {"coordinates":[1.047307,51.313297],"type":"Point"}
}
