{
  "type": "Feature",
  "properties": {
    "iso:country":"GB",
    "wof:name":"KA19 7AW",
    "wof:placetype":"postalcode"
},
  "geometry": {"coordinates":[-4.68429379099928,55.35215884314646],"type":"Point"}
}