{
  "type": "Feature",
  "properties": {
    "iso:country":"GB",
    "wof:name":"HD9 4DP",
    "wof:placetype":"postalcode"
},
  "geometry": {"coordinates":[-1.83920741004995,53.58986606824654],"type":"Point"}
}