{
  "type": "Feature",
  "properties": {
    "iso:country": "GB",
    "wof:name": "HD9 4DP",
    "wof:placetype": "postalcode"
  },
  "geometry": {"coordinates":[-1.839207,53.589866],"type":"Point"}
}
