{
  "type": "Feature",
  "properties": {
    "iso:country":"GB",
    "wof:name":"DH3 2DY",
    "wof:placetype":"postalcode"
},
  "geometry": {"coordinates":[-1.57226418806727,54.88290699885122],"type":"Point"}
}