{
  "type": "Feature",
  "properties": {
    "iso:country":"GB",
    "wof:name":"SY11 3BP",
    "wof:placetype":"postalcode"
},
  "geometry": {"coordinates":[-2.99792096944981,52.92415370197199],"type":"Point"}
}