{
  "type": "Feature",
  "properties": {
    "iso:country": "GB",
    "wof:name": "SY11 3BP",
    "wof:placetype": "postalcode"
  },
  "geometry": {"coordinates":[-2.997905,52.924169],"type":"Point"}
}
