{
  "type": "Feature",
  "properties": {
    "iso:country":"GB",
    "wof:name":"TN29 0RE",
    "wof:placetype":"postalcode"
},
  "geometry": {"coordinates":[0.98261703946245,51.01266474495785],"type":"Point"}
}