{
  "type": "Feature",
  "properties": {
    "iso:country": "GB",
    "wof:name": "EH7 4FA",
    "wof:placetype": "postalcode"
  },
  "geometry": {"coordinates":[-3.18596,55.961456],"type":"Point"}
}
