{
  "type": "Feature",
  "properties": {
    "iso:country":"GB",
    "wof:name":"WR1 3JD",
    "wof:placetype":"postalcode"
},
  "geometry": {"coordinates":[-2.22966674539104,52.20262525597497],"type":"Point"}
}