{
  "type": "Feature",
  "properties": {
    "iso:country":"GB",
    "wof:name":"SE16 5EP",
    "wof:placetype":"postalcode"
},
  "geometry": {"coordinates":[-0.03516788465515,51.50570397169833],"type":"Point"}
}