{
  "type": "Feature",
  "properties": {
    "iso:country":"GB",
    "wof:name":"IP12 2QJ",
    "wof:placetype":"postalcode"
},
  "geometry": {"coordinates":[1.53737865385678,52.09590791380428],"type":"Point"}
}