{
  "type": "Feature",
  "properties": {
    "iso:country": "GB",
    "wof:name": "IP12 2QJ",
    "wof:placetype": "postalcode"
  },
  "geometry": {"coordinates":[1.537379,52.095908],"type":"Point"}
}
