{
  "type": "Feature",
  "properties": {
    "date:inception_lower":"2003-07-01",
    "date:inception_upper":"2003-07-31",
    "iso:country":"GB",
    "wof:name":"IP12 2QJ",
    "wof:placetype":"postalcode"
},
  "geometry": {"coordinates":[1.537379,52.095908],"type":"Point"}
}