{
  "type": "Feature",
  "properties": {
    "iso:country": "GB",
    "wof:name": "TA24 8JW",
    "wof:placetype": "postalcode"
  },
  "geometry": {"coordinates":[-3.674946,51.211282],"type":"Point"}
}
