{
  "type": "Feature",
  "properties": {
    "iso:country":"GB",
    "wof:name":"TA24 8JW",
    "wof:placetype":"postalcode"
},
  "geometry": {"coordinates":[-3.67535808807165,51.21121421051521],"type":"Point"}
}