{
  "type": "Feature",
  "properties": {
    "iso:country":"GB",
    "wof:name":"NG22 9LL",
    "wof:placetype":"postalcode"
},
  "geometry": {"coordinates":[-0.96824575247081,53.21018371760784],"type":"Point"}
}