{
  "type": "Feature",
  "properties": {
    "iso:country":"GB",
    "wof:name":"TS12 2UB",
    "wof:placetype":"postalcode"
},
  "geometry": {"coordinates":[-0.93214442825549,54.54949211423467],"type":"Point"}
}