{
  "type": "Feature",
  "properties": {
    "iso:country": "GB",
    "wof:name": "TS12 2UB",
    "wof:placetype": "postalcode"
  },
  "geometry": {"coordinates":[-0.932144,54.549492],"type":"Point"}
}
