{
  "type": "Feature",
  "properties": {
    "date:inception_lower": "1980-01-01",
    "date:inception_upper": "1980-01-01",
    "iso:country": "GB",
    "wof:name": "TS12 2UB",
    "wof:placetype": "postalcode"
  },
  "geometry": {"coordinates":[-0.932144,54.549492],"type":"Point"}
}
