{
  "type": "Feature",
  "properties": {
    "iso:country":"GB",
    "wof:name":"NE29 6TG",
    "wof:placetype":"postalcode"
},
  "geometry": {"coordinates":[-1.44892930834657,55.00354683767966],"type":"Point"}
}