{
  "type": "Feature",
  "properties": {
    "date:inception_lower":"1996-06-01",
    "date:inception_upper":"1996-06-30",
    "iso:country":"GB",
    "wof:name":"NE29 6TG",
    "wof:placetype":"postalcode"
},
  "geometry": {"coordinates":[-1.448736,55.003796],"type":"Point"}
}