{
  "type": "Feature",
  "properties": {
    "iso:country":"GB",
    "wof:name":"SS6 9ST",
    "wof:placetype":"postalcode"
},
  "geometry": {"coordinates":[0.59077776381506,51.59624028134458],"type":"Point"}
}