{
  "type": "Feature",
  "properties": {
    "date:inception_lower":"2011-10-01",
    "date:inception_upper":"2011-10-31",
    "iso:country":"GB",
    "wof:name":"MK45 2GE",
    "wof:placetype":"postalcode"
},
  "geometry": {"coordinates":[-0.502992,52.020274],"type":"Point"}
}