{
  "type": "Feature",
  "properties": {
    "date:inception_lower": "2014-05-01",
    "date:inception_upper": "2014-05-01",
    "iso:country": "GB",
    "wof:name": "CT4 5BQ",
    "wof:placetype": "postalcode"
  },
  "geometry": {"coordinates":[1.025362,51.207429],"type":"Point"}
}
