{
  "type": "Feature",
  "properties": {
    "iso:country": "GB",
    "wof:name": "CT4 5BQ",
    "wof:placetype": "postalcode"
  },
  "geometry": {"coordinates":[1.026912,51.207047],"type":"Point"}
}
