{
  "type": "Feature",
  "properties": {
    "date:inception_lower": "2018-08-01",
    "date:inception_upper": "2018-08-01",
    "iso:country": "GB",
    "wof:name": "TN12 0FJ",
    "wof:placetype": "postalcode"
  },
  "geometry": {"coordinates":[0.558576,51.168274],"type":"Point"}
}
