{
  "type": "Feature",
  "properties": {
    "iso:country":"GB",
    "wof:name":"CR4 2BP",
    "wof:placetype":"postalcode"
},
  "geometry": {"coordinates":[-0.15865359717694,51.41750343406819],"type":"Point"}
}