{
  "type": "Feature",
  "properties": {
    "date:inception_lower": "1980-01-01",
    "date:inception_upper": "1980-01-01",
    "iso:country": "GB",
    "wof:name": "CR4 2BP",
    "wof:placetype": "postalcode"
  },
  "geometry": {"coordinates":[-0.158654,51.417503],"type":"Point"}
}
