{
  "type": "Feature",
  "properties": {
    "iso:country":"GB",
    "wof:name":"PE15 9PS",
    "wof:placetype":"postalcode"
},
  "geometry": {"coordinates":[0.08504409286873,52.53901481270434],"type":"Point"}
}