{
  "type": "Feature",
  "properties": {
    "iso:country":"GB",
    "wof:name":"LN6 9DH",
    "wof:placetype":"postalcode"
},
  "geometry": {"coordinates":[-0.69012713435202,53.19168399410874],"type":"Point"}
}