{
  "type": "Feature",
  "properties": {
    "iso:country": "GB",
    "wof:name": "LN6 9DH",
    "wof:placetype": "postalcode"
  },
  "geometry": {"coordinates":[-0.690127,53.191684],"type":"Point"}
}
