{
  "type": "Feature",
  "properties": {
    "iso:country":"GB",
    "wof:name":"HD9 7EU",
    "wof:placetype":"postalcode"
},
  "geometry": {"coordinates":[-1.75585398457497,53.57017564215385],"type":"Point"}
}