{
  "type": "Feature",
  "properties": {
    "date:inception_lower": "2001-06-01",
    "date:inception_upper": "2001-06-01",
    "iso:country": "GB",
    "wof:name": "HD9 7EU",
    "wof:placetype": "postalcode"
  },
  "geometry": {"coordinates":[-1.75581,53.570146],"type":"Point"}
}
