{
  "type": "Feature",
  "properties": {
    "date:inception_lower":"1980-01-01",
    "date:inception_upper":"1980-01-31",
    "iso:country":"GB",
    "wof:name":"RH1 2EH",
    "wof:placetype":"postalcode"
},
  "geometry": {"coordinates":[-0.162706,51.248441],"type":"Point"}
}