{
  "type": "Feature",
  "properties": {
    "iso:country":"GB",
    "wof:name":"W3 7DX",
    "wof:placetype":"postalcode"
},
  "geometry": {"coordinates":[-0.25148636284409,51.52111529314614],"type":"Point"}
}