{
  "type": "Feature",
  "properties": {
    "iso:country": "GB",
    "wof:name": "W3 7DX",
    "wof:placetype": "postalcode"
  },
  "geometry": {"coordinates":[-0.251486,51.521115],"type":"Point"}
}
