{
  "type": "Feature",
  "properties": {
    "iso:country":"GB",
    "wof:name":"W1G 8GN",
    "wof:placetype":"postalcode"
},
  "geometry": {"coordinates":[-0.14815425856788,51.51886400982102],"type":"Point"}
}