{
  "type": "Feature",
  "properties": {
    "date:inception_lower":"2012-09-01",
    "date:inception_upper":"2012-09-30",
    "iso:country":"GB",
    "wof:name":"PL12 4FW",
    "wof:placetype":"postalcode"
},
  "geometry": {"coordinates":[-4.226051,50.409307],"type":"Point"}
}