{
  "type": "Feature",
  "properties": {
    "iso:country":"GB",
    "wof:name":"PL12 4FW",
    "wof:placetype":"postalcode"
},
  "geometry": {"coordinates":[-4.22605090761744,50.40930746060727],"type":"Point"}
}