{
  "type": "Feature",
  "properties": {
    "iso:country":"GB",
    "wof:name":"KA30 8RT",
    "wof:placetype":"postalcode"
},
  "geometry": {"coordinates":[-4.88166968405511,55.81174779719777],"type":"Point"}
}