{
  "type": "Feature",
  "properties": {
    "date:inception_lower": "1992-01-01",
    "date:inception_upper": "1992-01-01",
    "iso:country": "GB",
    "wof:name": "KA30 8RT",
    "wof:placetype": "postalcode"
  },
  "geometry": {"coordinates":[-4.88167,55.811748],"type":"Point"}
}
