{
  "type": "Feature",
  "properties": {
    "date:inception_lower": "2018-11-01",
    "date:inception_upper": "2018-11-01",
    "iso:country": "GB",
    "wof:name": "E3 4YG",
    "wof:placetype": "postalcode"
  },
  "geometry": {"coordinates":[-0.027538,51.517583],"type":"Point"}
}
