{
  "type": "Feature",
  "properties": {
    "iso:country":"GB",
    "wof:name":"NE46 4PB",
    "wof:placetype":"postalcode"
},
  "geometry": {"coordinates":[-2.10087497788741,54.98105494548663],"type":"Point"}
}