{
  "type": "Feature",
  "properties": {
    "date:inception_lower":"1980-01-01",
    "date:inception_upper":"1980-01-31",
    "iso:country":"GB",
    "wof:name":"NE46 4PB",
    "wof:placetype":"postalcode"
},
  "geometry": {"coordinates":[-2.100875,54.981055],"type":"Point"}
}