{
  "type": "Feature",
  "properties": {
    "iso:country":"GB",
    "wof:name":"TQ14 8XQ",
    "wof:placetype":"postalcode"
},
  "geometry": {"coordinates":[-3.49559730472239,50.55885860396828],"type":"Point"}
}