{
  "type": "Feature",
  "properties": {
    "iso:country":"GB",
    "wof:name":"IP32 7PG",
    "wof:placetype":"postalcode"
},
  "geometry": {"coordinates":[0.75115976632815,52.24482747507871],"type":"Point"}
}