{
  "type": "Feature",
  "properties": {
    "date:inception_lower": "2002-08-01",
    "date:inception_upper": "2002-08-01",
    "iso:country": "GB",
    "wof:name": "IP32 7PG",
    "wof:placetype": "postalcode"
  },
  "geometry": {"coordinates":[0.75116,52.244827],"type":"Point"}
}
