{
  "type": "Feature",
  "properties": {
    "iso:country": "GB",
    "wof:name": "SS8 0LY",
    "wof:placetype": "postalcode"
  },
  "geometry": {"coordinates":[0.56378,51.518357],"type":"Point"}
}
