{
  "type": "Feature",
  "properties": {
    "iso:country":"GB",
    "wof:name":"SS8 0LY",
    "wof:placetype":"postalcode"
},
  "geometry": {"coordinates":[0.56377981388439,51.5183568223351],"type":"Point"}
}