{
  "type": "Feature",
  "properties": {
    "date:inception_lower": "1980-01-01",
    "date:inception_upper": "1980-01-01",
    "iso:country": "GB",
    "wof:name": "BB6 8BA",
    "wof:placetype": "postalcode"
  },
  "geometry": {"coordinates":[-2.45909,53.825625],"type":"Point"}
}
