{
  "type": "Feature",
  "properties": {
    "iso:country":"GB",
    "wof:name":"BB6 8BA",
    "wof:placetype":"postalcode"
},
  "geometry": {"coordinates":[-2.45909023902423,53.82562493950503],"type":"Point"}
}