{
  "type": "Feature",
  "properties": {
    "iso:country":"GB",
    "wof:name":"PE30 3NP",
    "wof:placetype":"postalcode"
},
  "geometry": {"coordinates":[0.43636134438899,52.77489361362166],"type":"Point"}
}