{
  "type": "Feature",
  "properties": {
    "iso:country":"GB",
    "wof:name":"YO7 3DN",
    "wof:placetype":"postalcode"
},
  "geometry": {"coordinates":[-1.39822338199169,54.13509459238416],"type":"Point"}
}