{
  "type": "Feature",
  "properties": {
    "iso:country":"GB",
    "wof:name":"KT12 3PG",
    "wof:placetype":"postalcode"
},
  "geometry": {"coordinates":[-0.38849388860351,51.37966778331575],"type":"Point"}
}