{
  "type": "Feature",
  "properties": {
    "iso:country":"GB",
    "wof:name":"PL12 4SW",
    "wof:placetype":"postalcode"
},
  "geometry": {"coordinates":[-4.2359243149847,50.40885717899294],"type":"Point"}
}