{
  "type": "Feature",
  "properties": {
    "iso:country":"GB",
    "wof:name":"TW16 6HQ",
    "wof:placetype":"postalcode"
},
  "geometry": {"coordinates":[-0.41467329000388,51.40925015420591],"type":"Point"}
}