{
  "type": "Feature",
  "properties": {
    "date:inception_lower": "1985-10-01",
    "date:inception_upper": "1985-10-01",
    "iso:country": "GB",
    "wof:name": "CV1 5PZ",
    "wof:placetype": "postalcode"
  },
  "geometry": {"coordinates":[-1.497959,52.409414],"type":"Point"}
}
