{
  "type": "Feature",
  "properties": {
    "iso:country":"GB",
    "wof:name":"CV1 5PZ",
    "wof:placetype":"postalcode"
},
  "geometry": {"coordinates":[-1.4979586955659,52.40941373110407],"type":"Point"}
}