{
  "type": "Feature",
  "properties": {
    "date:inception_lower":"2002-07-01",
    "date:inception_upper":"2002-07-31",
    "iso:country":"GB",
    "wof:name":"ST1 1DE",
    "wof:placetype":"postalcode"
},
  "geometry": {"coordinates":[-2.175736,53.025236],"type":"Point"}
}