{
  "type": "Feature",
  "properties": {
    "iso:country":"GB",
    "wof:name":"GL13 9TG",
    "wof:placetype":"postalcode"
},
  "geometry": {"coordinates":[-2.4694083120016,51.69477699144596],"type":"Point"}
}