{
  "type": "Feature",
  "properties": {
    "iso:country":"GB",
    "wof:name":"LE11 3UQ",
    "wof:placetype":"postalcode"
},
  "geometry": {"coordinates":[-1.23606709766906,52.76416020777298],"type":"Point"}
}