{
  "type": "Feature",
  "properties": {
    "iso:country": "GB",
    "wof:name": "LE11 3UQ",
    "wof:placetype": "postalcode"
  },
  "geometry": {"coordinates":[-1.234845,52.764172],"type":"Point"}
}
