{
  "type": "Feature",
  "properties": {
    "iso:country":"GB",
    "wof:name":"WN7 5AH",
    "wof:placetype":"postalcode"
},
  "geometry": {"coordinates":[-2.53184108311911,53.49856454911186],"type":"Point"}
}