{
  "type": "Feature",
  "properties": {
    "iso:country": "GB",
    "wof:name": "WN7 5AH",
    "wof:placetype": "postalcode"
  },
  "geometry": {"coordinates":[-2.531841,53.498565],"type":"Point"}
}
