{
  "type": "Feature",
  "properties": {
    "date:inception_lower": "2020-01-01",
    "date:inception_upper": "2020-01-01",
    "iso:country": "GB",
    "wof:name": "RH20 1FX",
    "wof:placetype": "postalcode"
  },
  "geometry": {"coordinates":[-0.503875,50.964896],"type":"Point"}
}
