{
  "type": "Feature",
  "properties": {
    "iso:country": "GB",
    "wof:name": "RH20 1FX",
    "wof:placetype": "postalcode"
  },
  "geometry": {"coordinates":[-0.504674,50.964843],"type":"Point"}
}
