{
  "type": "Feature",
  "properties": {
    "iso:country":"GB",
    "wof:name":"RG5 4WP",
    "wof:placetype":"postalcode"
},
  "geometry": {"coordinates":[-0.87659832139285,51.45497022766786],"type":"Point"}
}