{
  "type": "Feature",
  "properties": {
    "date:inception_lower":"2014-09-01",
    "date:inception_upper":"2014-09-30",
    "iso:country":"GB",
    "wof:name":"RG5 4WP",
    "wof:placetype":"postalcode"
},
  "geometry": {"coordinates":[-0.876598,51.45497],"type":"Point"}
}