{
  "type": "Feature",
  "properties": {
    "date:inception_lower":"1990-07-01",
    "date:inception_upper":"1990-07-31",
    "iso:country":"GB",
    "wof:name":"RM6 4EF",
    "wof:placetype":"postalcode"
},
  "geometry": {"coordinates":[0.128715,51.569013],"type":"Point"}
}