{
  "type": "Feature",
  "properties": {
    "date:inception_lower":"2014-12-01",
    "date:inception_upper":"2014-12-31",
    "iso:country":"GB",
    "wof:name":"PR3 3BF",
    "wof:placetype":"postalcode"
},
  "geometry": {"coordinates":[-2.606447,53.81907],"type":"Point"}
}