{
  "type": "Feature",
  "properties": {
    "date:inception_lower": "2014-12-01",
    "date:inception_upper": "2014-12-01",
    "iso:country": "GB",
    "wof:name": "PR3 3BF",
    "wof:placetype": "postalcode"
  },
  "geometry": {"coordinates":[-2.6064,53.818927],"type":"Point"}
}
