{
  "type": "Feature",
  "properties": {
    "iso:country":"GB",
    "wof:name":"SW17 7AE",
    "wof:placetype":"postalcode"
},
  "geometry": {"coordinates":[-0.16035075332912,51.43791631626784],"type":"Point"}
}