{
  "type": "Feature",
  "properties": {
    "date:inception_lower":"1980-01-01",
    "date:inception_upper":"1980-01-31",
    "iso:country":"GB",
    "wof:name":"OL9 8LX",
    "wof:placetype":"postalcode"
},
  "geometry": {"coordinates":[-2.148968,53.53134],"type":"Point"}
}