{
  "type": "Feature",
  "properties": {
    "iso:country":"GB",
    "wof:name":"OL9 8LX",
    "wof:placetype":"postalcode"
},
  "geometry": {"coordinates":[-2.14896851035134,53.53133974683116],"type":"Point"}
}