{
  "type": "Feature",
  "properties": {
    "iso:country": "GB",
    "wof:name": "OL9 8LX",
    "wof:placetype": "postalcode"
  },
  "geometry": {"coordinates":[-2.148968,53.53134],"type":"Point"}
}
