{
  "type": "Feature",
  "properties": {
    "iso:country":"GB",
    "wof:name":"S6 2PQ",
    "wof:placetype":"postalcode"
},
  "geometry": {"coordinates":[-1.50219544481675,53.39811319599927],"type":"Point"}
}