{
  "type": "Feature",
  "properties": {
    "iso:country":"GB",
    "wof:name":"BS48 2QQ",
    "wof:placetype":"postalcode"
},
  "geometry": {"coordinates":[-2.7633345820013,51.42730914077352],"type":"Point"}
}