{
  "type": "Feature",
  "properties": {
    "iso:country":"GB",
    "wof:name":"WR9 8FB",
    "wof:placetype":"postalcode"
},
  "geometry": {"coordinates":[-2.15613433822481,52.25530320418266],"type":"Point"}
}