{
  "type": "Feature",
  "properties": {
    "iso:country": "GB",
    "wof:name": "WR9 8FB",
    "wof:placetype": "postalcode"
  },
  "geometry": {"coordinates":[-2.156134,52.255303],"type":"Point"}
}
