{
  "type": "Feature",
  "properties": {
    "date:inception_lower": "2012-10-01",
    "date:inception_upper": "2012-10-01",
    "iso:country": "GB",
    "wof:name": "WR9 8FB",
    "wof:placetype": "postalcode"
  },
  "geometry": {"coordinates":[-2.156134,52.255303],"type":"Point"}
}
