{
  "type": "Feature",
  "properties": {
    "iso:country":"GB",
    "wof:name":"SK1 3QZ",
    "wof:placetype":"postalcode"
},
  "geometry": {"coordinates":[-2.15401361832518,53.40012869507659],"type":"Point"}
}