{
  "type": "Feature",
  "properties": {
    "iso:country": "GB",
    "wof:name": "SK1 3QZ",
    "wof:placetype": "postalcode"
  },
  "geometry": {"coordinates":[-2.154014,53.400129],"type":"Point"}
}
