{
  "type": "Feature",
  "properties": {
    "iso:country":"GB",
    "wof:name":"NR1 4NQ",
    "wof:placetype":"postalcode"
},
  "geometry": {"coordinates":[1.3230178991667,52.6390285606907],"type":"Point"}
}