{
  "type": "Feature",
  "properties": {
    "date:inception_lower": "1980-01-01",
    "date:inception_upper": "1980-01-01",
    "iso:country": "GB",
    "wof:name": "NR1 4NQ",
    "wof:placetype": "postalcode"
  },
  "geometry": {"coordinates":[1.323018,52.639029],"type":"Point"}
}
