{
  "type": "Feature",
  "properties": {
    "iso:country":"GB",
    "wof:name":"OL14 7TB",
    "wof:placetype":"postalcode"
},
  "geometry": {"coordinates":[-2.10393609630248,53.6909916708155],"type":"Point"}
}