{
  "type": "Feature",
  "properties": {
    "iso:country":"GB",
    "wof:name":"SO45 5TR",
    "wof:placetype":"postalcode"
},
  "geometry": {"coordinates":[-1.42246383885456,50.86660199583244],"type":"Point"}
}