{
  "type": "Feature",
  "properties": {
    "iso:country": "GB",
    "wof:name": "TS12 3AT",
    "wof:placetype": "postalcode"
  },
  "geometry": {"coordinates":[-0.980686,54.543431],"type":"Point"}
}
