{
  "type": "Feature",
  "properties": {
    "iso:country":"GB",
    "wof:name":"TS12 3AT",
    "wof:placetype":"postalcode"
},
  "geometry": {"coordinates":[-0.98068633679713,54.54343089840263],"type":"Point"}
}