{
  "type": "Feature",
  "properties": {
    "date:inception_lower":"1980-01-01",
    "date:inception_upper":"1980-01-31",
    "iso:country":"GB",
    "wof:name":"TS12 3AT",
    "wof:placetype":"postalcode"
},
  "geometry": {"coordinates":[-0.980686,54.543431],"type":"Point"}
}