{
  "type": "Feature",
  "properties": {
    "iso:country":"GB",
    "wof:name":"CV13 6DD",
    "wof:placetype":"postalcode"
},
  "geometry": {"coordinates":[-1.44808869529182,52.60281874072549],"type":"Point"}
}