{
  "type": "Feature",
  "properties": {
    "iso:country":"GB",
    "wof:name":"B49 6JF",
    "wof:placetype":"postalcode"
},
  "geometry": {"coordinates":[-1.85149472152166,52.25574526322548],"type":"Point"}
}