{
  "type": "Feature",
  "properties": {
    "iso:country":"GB",
    "wof:name":"PE9 4LD",
    "wof:placetype":"postalcode"
},
  "geometry": {"coordinates":[-0.45245224980357,52.70116372724227],"type":"Point"}
}