{
  "type": "Feature",
  "properties": {
    "iso:country":"GB",
    "wof:name":"RG4 7DD",
    "wof:placetype":"postalcode"
},
  "geometry": {"coordinates":[-0.98349530821399,51.46971201367857],"type":"Point"}
}