{
  "type": "Feature",
  "properties": {
    "date:inception_lower": "1980-01-01",
    "date:inception_upper": "1980-01-01",
    "iso:country": "GB",
    "wof:name": "M15 5AH",
    "wof:placetype": "postalcode"
  },
  "geometry": {"coordinates":[-2.257545,53.469243],"type":"Point"}
}
