{
  "type": "Feature",
  "properties": {
    "date:inception_lower": "2015-08-01",
    "date:inception_upper": "2015-08-01",
    "iso:country": "GB",
    "wof:name": "RH16 9LY",
    "wof:placetype": "postalcode"
  },
  "geometry": {"coordinates":[-0.103822,51.006415],"type":"Point"}
}
