{
  "type": "Feature",
  "properties": {
    "iso:country":"GB",
    "wof:name":"BH9 2EA",
    "wof:placetype":"postalcode"
},
  "geometry": {"coordinates":[-1.87906169235049,50.74057871676309],"type":"Point"}
}