{
  "type": "Feature",
  "properties": {
    "date:inception_lower": "1980-01-01",
    "date:inception_upper": "1980-01-01",
    "iso:country": "GB",
    "wof:name": "OX7 6HX",
    "wof:placetype": "postalcode"
  },
  "geometry": {"coordinates":[-1.634444,51.830165],"type":"Point"}
}
