{
  "type": "Feature",
  "properties": {
    "iso:country":"GB",
    "wof:name":"OX7 6HX",
    "wof:placetype":"postalcode"
},
  "geometry": {"coordinates":[-1.63483454479118,51.83021344011388],"type":"Point"}
}