{
  "type": "Feature",
  "properties": {
    "iso:country": "GB",
    "wof:name": "OX7 6HX",
    "wof:placetype": "postalcode"
  },
  "geometry": {"coordinates":[-1.634835,51.830213],"type":"Point"}
}
