{
  "type": "Feature",
  "properties": {
    "iso:country":"GB",
    "wof:name":"PL5 4AB",
    "wof:placetype":"postalcode"
},
  "geometry": {"coordinates":[-4.14620183421743,50.41889459749352],"type":"Point"}
}