{
  "type": "Feature",
  "properties": {
    "iso:country":"GB",
    "wof:name":"ML5 3AE",
    "wof:placetype":"postalcode"
},
  "geometry": {"coordinates":[-4.02729880589637,55.86228331661478],"type":"Point"}
}