{
  "type": "Feature",
  "properties": {
    "iso:country":"GB",
    "wof:name":"LL11 6BW",
    "wof:placetype":"postalcode"
},
  "geometry": {"coordinates":[-3.04527833379329,53.07877161280508],"type":"Point"}
}