{
  "type": "Feature",
  "properties": {
    "iso:country": "GB",
    "wof:name": "LL11 6BW",
    "wof:placetype": "postalcode"
  },
  "geometry": {"coordinates":[-3.045278,53.078772],"type":"Point"}
}
