{
  "type": "Feature",
  "properties": {
    "date:inception_lower": "1982-03-01",
    "date:inception_upper": "1982-03-01",
    "iso:country": "GB",
    "wof:name": "B45 0NB",
    "wof:placetype": "postalcode"
  },
  "geometry": {"coordinates":[-2.02765,52.406358],"type":"Point"}
}
