{
  "type": "Feature",
  "properties": {
    "iso:country":"GB",
    "wof:name":"B45 0NB",
    "wof:placetype":"postalcode"
},
  "geometry": {"coordinates":[-2.02764983283599,52.40635770927055],"type":"Point"}
}