{
  "type": "Feature",
  "properties": {
    "iso:country":"GB",
    "wof:name":"DN8 5PS",
    "wof:placetype":"postalcode"
},
  "geometry": {"coordinates":[-0.95070315421744,53.60549175088134],"type":"Point"}
}