{
  "type": "Feature",
  "properties": {
    "date:inception_lower": "1980-01-01",
    "date:inception_upper": "1980-01-01",
    "iso:country": "GB",
    "wof:name": "DN8 5PS",
    "wof:placetype": "postalcode"
  },
  "geometry": {"coordinates":[-0.950824,53.605475],"type":"Point"}
}
