{
  "type": "Feature",
  "properties": {
    "date:inception_lower": "2012-11-01",
    "date:inception_upper": "2012-11-01",
    "iso:country": "GB",
    "wof:name": "PL6 7HA",
    "wof:placetype": "postalcode"
  },
  "geometry": {"coordinates":[-4.111409,50.42885],"type":"Point"}
}
