{
  "type": "Feature",
  "properties": {
    "iso:country":"GB",
    "wof:name":"PL6 7HA",
    "wof:placetype":"postalcode"
},
  "geometry": {"coordinates":[-4.1114086684983,50.42884960590064],"type":"Point"}
}