{
  "type": "Feature",
  "properties": {
    "iso:country": "GB",
    "wof:name": "SG4 8QP",
    "wof:placetype": "postalcode"
  },
  "geometry": {"coordinates":[-0.303201,51.850508],"type":"Point"}
}
