{
  "type": "Feature",
  "properties": {
    "iso:country": "GB",
    "wof:name": "CB6 3TA",
    "wof:placetype": "postalcode"
  },
  "geometry": {"coordinates":[0.147084,52.358118],"type":"Point"}
}
