{
  "type": "Feature",
  "properties": {
    "iso:country":"GB",
    "wof:name":"CB6 3TA",
    "wof:placetype":"postalcode"
},
  "geometry": {"coordinates":[0.14708373947715,52.35811794919378],"type":"Point"}
}