{
  "type": "Feature",
  "properties": {
    "iso:country":"GB",
    "wof:name":"HA5 3TD",
    "wof:placetype":"postalcode"
},
  "geometry": {"coordinates":[-0.39458115499616,51.60168050854154],"type":"Point"}
}