{
  "type": "Feature",
  "properties": {
    "date:inception_lower": "1981-12-01",
    "date:inception_upper": "1981-12-01",
    "iso:country": "GB",
    "wof:name": "DN15 7UH",
    "wof:placetype": "postalcode"
  },
  "geometry": {"coordinates":[-0.69096,53.587418],"type":"Point"}
}
