{
  "type": "Feature",
  "properties": {
    "iso:country": "GB",
    "wof:name": "DN15 7UH",
    "wof:placetype": "postalcode"
  },
  "geometry": {"coordinates":[-0.69096,53.587418],"type":"Point"}
}
