{
  "type": "Feature",
  "properties": {
    "date:inception_lower": "1996-06-01",
    "date:inception_upper": "1996-06-01",
    "iso:country": "GB",
    "wof:name": "AB51 3JA",
    "wof:placetype": "postalcode"
  },
  "geometry": {"coordinates":[-2.371453,57.27313],"type":"Point"}
}
