{
  "type": "Feature",
  "properties": {
    "iso:country":"GB",
    "wof:name":"DH6 5PS",
    "wof:placetype":"postalcode"
},
  "geometry": {"coordinates":[-1.52029556963568,54.73980007501339],"type":"Point"}
}