{
  "type": "Feature",
  "properties": {
    "iso:country": "GB",
    "wof:name": "DH6 5PS",
    "wof:placetype": "postalcode"
  },
  "geometry": {"coordinates":[-1.520296,54.7398],"type":"Point"}
}
