{
  "type": "Feature",
  "properties": {
    "date:inception_lower":"1997-06-01",
    "date:inception_upper":"1997-06-30",
    "iso:country":"GB",
    "wof:name":"DH6 5PS",
    "wof:placetype":"postalcode"
},
  "geometry": {"coordinates":[-1.520296,54.7398],"type":"Point"}
}