{
  "type": "Feature",
  "properties": {
    "iso:country": "GB",
    "wof:name": "MK46 4BL",
    "wof:placetype": "postalcode"
  },
  "geometry": {"coordinates":[-0.701003,52.159471],"type":"Point"}
}
