{
  "type": "Feature",
  "properties": {
    "iso:country":"GB",
    "wof:name":"MK46 4BL",
    "wof:placetype":"postalcode"
},
  "geometry": {"coordinates":[-0.70109487462244,52.1594604835387],"type":"Point"}
}