{
  "type": "Feature",
  "properties": {
    "iso:country":"GB",
    "wof:name":"KA8 9NL",
    "wof:placetype":"postalcode"
},
  "geometry": {"coordinates":[-4.60799126629344,55.46974116899229],"type":"Point"}
}