{
  "type": "Feature",
  "properties": {
    "iso:country": "GB",
    "wof:name": "KA8 9NL",
    "wof:placetype": "postalcode"
  },
  "geometry": {"coordinates":[-4.607991,55.469741],"type":"Point"}
}
