{
  "type": "Feature",
  "properties": {
    "date:inception_lower": "1980-01-01",
    "date:inception_upper": "1980-01-01",
    "iso:country": "GB",
    "wof:name": "NG5 4DN",
    "wof:placetype": "postalcode"
  },
  "geometry": {"coordinates":[-1.142429,52.981375],"type":"Point"}
}
