{
  "type": "Feature",
  "properties": {
    "iso:country":"GB",
    "wof:name":"NG5 4DN",
    "wof:placetype":"postalcode"
},
  "geometry": {"coordinates":[-1.1424292296502,52.98137519184473],"type":"Point"}
}