{
  "type": "Feature",
  "properties": {
    "iso:country":"GB",
    "wof:name":"CH5 4EH",
    "wof:placetype":"postalcode"
},
  "geometry": {"coordinates":[-3.05104425883496,53.21727386206761],"type":"Point"}
}