{
  "type": "Feature",
  "properties": {
    "date:inception_lower":"1980-01-01",
    "date:inception_upper":"1980-01-31",
    "iso:country":"GB",
    "wof:name":"CH5 4EH",
    "wof:placetype":"postalcode"
},
  "geometry": {"coordinates":[-3.051044,53.217274],"type":"Point"}
}