{
  "type": "Feature",
  "properties": {
    "iso:country":"GB",
    "wof:name":"EH8 7LB",
    "wof:placetype":"postalcode"
},
  "geometry": {"coordinates":[-3.14224715316227,55.95016654971454],"type":"Point"}
}