{
  "type": "Feature",
  "properties": {
    "iso:country": "GB",
    "wof:name": "CB2 1EG",
    "wof:placetype": "postalcode"
  },
  "geometry": {"coordinates":[0.125752,52.198683],"type":"Point"}
}
