{
  "type": "Feature",
  "properties": {
    "iso:country":"GB",
    "wof:name":"CB2 1EG",
    "wof:placetype":"postalcode"
},
  "geometry": {"coordinates":[0.12575175745668,52.19868314715224],"type":"Point"}
}