{
  "type": "Feature",
  "properties": {
    "iso:country":"GB",
    "wof:name":"CF5 2LT",
    "wof:placetype":"postalcode"
},
  "geometry": {"coordinates":[-3.22263197326972,51.49604547696964],"type":"Point"}
}