{
  "type": "Feature",
  "properties": {
    "iso:country":"GB",
    "wof:name":"WV5 7DU",
    "wof:placetype":"postalcode"
},
  "geometry": {"coordinates":[-2.30650003177216,52.53748679987589],"type":"Point"}
}