{
  "type": "Feature",
  "properties": {
    "date:inception_lower": "1980-01-01",
    "date:inception_upper": "1980-01-01",
    "iso:country": "GB",
    "wof:name": "WV5 7DU",
    "wof:placetype": "postalcode"
  },
  "geometry": {"coordinates":[-2.306437,52.537439],"type":"Point"}
}
