{
  "type": "Feature",
  "properties": {
    "iso:country":"GB",
    "wof:name":"PO31 8LT",
    "wof:placetype":"postalcode"
},
  "geometry": {"coordinates":[-1.32603442139161,50.73921669406015],"type":"Point"}
}