{
  "type": "Feature",
  "properties": {
    "iso:country":"GB",
    "wof:name":"BD19 4AN",
    "wof:placetype":"postalcode"
},
  "geometry": {"coordinates":[-1.69157597253001,53.73572503823753],"type":"Point"}
}