{
  "type": "Feature",
  "properties": {
    "iso:country": "GB",
    "wof:name": "CW10 0JL",
    "wof:placetype": "postalcode"
  },
  "geometry": {"coordinates":[-2.440922,53.185417],"type":"Point"}
}
