{
  "type": "Feature",
  "properties": {
    "iso:country":"GB",
    "wof:name":"CM14 5JR",
    "wof:placetype":"postalcode"
},
  "geometry": {"coordinates":[0.29744926548418,51.61248530553297],"type":"Point"}
}