{
  "type": "Feature",
  "properties": {
    "date:inception_lower": "1980-01-01",
    "date:inception_upper": "1980-01-01",
    "iso:country": "GB",
    "wof:name": "NP7 0HT",
    "wof:placetype": "postalcode"
  },
  "geometry": {"coordinates":[-3.118979,51.816576],"type":"Point"}
}
