{
  "type": "Feature",
  "properties": {
    "iso:country":"GB",
    "wof:name":"NP7 0HT",
    "wof:placetype":"postalcode"
},
  "geometry": {"coordinates":[-3.11911101369377,51.81630854746946],"type":"Point"}
}