{
  "type": "Feature",
  "properties": {
    "iso:country":"GB",
    "wof:name":"LS24 9HG",
    "wof:placetype":"postalcode"
},
  "geometry": {"coordinates":[-1.27184392062926,53.87920440067047],"type":"Point"}
}