{
  "type": "Feature",
  "properties": {
    "iso:country": "GB",
    "wof:name": "LS24 9HG",
    "wof:placetype": "postalcode"
  },
  "geometry": {"coordinates":[-1.271844,53.879204],"type":"Point"}
}
