{
  "type": "Feature",
  "properties": {
    "iso:country": "GB",
    "wof:name": "SY14 8JJ",
    "wof:placetype": "postalcode"
  },
  "geometry": {"coordinates":[-2.750416,53.040013],"type":"Point"}
}
