{
  "type": "Feature",
  "properties": {
    "iso:country":"GB",
    "wof:name":"DH1 2HR",
    "wof:placetype":"postalcode"
},
  "geometry": {"coordinates":[-1.53985043343259,54.78229258905711],"type":"Point"}
}