{
  "type": "Feature",
  "properties": {
    "iso:country": "GB",
    "wof:name": "DH1 2HR",
    "wof:placetype": "postalcode"
  },
  "geometry": {"coordinates":[-1.53985,54.782293],"type":"Point"}
}
