{
  "type": "Feature",
  "properties": {
    "iso:country": "GB",
    "wof:name": "IP25 6LG",
    "wof:placetype": "postalcode"
  },
  "geometry": {"coordinates":[0.806748,52.571801],"type":"Point"}
}
