{
  "type": "Feature",
  "properties": {
    "date:inception_lower": "1980-01-01",
    "date:inception_upper": "1980-01-01",
    "iso:country": "GB",
    "wof:name": "IP25 6LG",
    "wof:placetype": "postalcode"
  },
  "geometry": {"coordinates":[0.806748,52.571801],"type":"Point"}
}
