{
  "type": "Feature",
  "properties": {
    "iso:country":"GB",
    "wof:name":"BS2 0LA",
    "wof:placetype":"postalcode"
},
  "geometry": {"coordinates":[-2.57875169312243,51.45466676914823],"type":"Point"}
}