{
  "type": "Feature",
  "properties": {
    "iso:country":"GB",
    "wof:name":"LE67 1FD",
    "wof:placetype":"postalcode"
},
  "geometry": {"coordinates":[-1.3614089778818,52.69461917010138],"type":"Point"}
}