{
  "type": "Feature",
  "properties": {
    "iso:country":"GB",
    "wof:name":"SW6 5JD",
    "wof:placetype":"postalcode"
},
  "geometry": {"coordinates":[-0.20958681087906,51.47213981867498],"type":"Point"}
}