{
  "type": "Feature",
  "properties": {
    "iso:country": "GB",
    "wof:name": "SW6 5JD",
    "wof:placetype": "postalcode"
  },
  "geometry": {"coordinates":[-0.209431,51.47221],"type":"Point"}
}
