{
  "type": "Feature",
  "properties": {
    "iso:country": "GB",
    "wof:name": "CW11 3TA",
    "wof:placetype": "postalcode"
  },
  "geometry": {"coordinates":[-2.384237,53.133692],"type":"Point"}
}
