{
  "type": "Feature",
  "properties": {
    "iso:country":"GB",
    "wof:name":"GL6 8JE",
    "wof:placetype":"postalcode"
},
  "geometry": {"coordinates":[-2.1176443059341,51.72086778319677],"type":"Point"}
}