{
  "type": "Feature",
  "properties": {
    "iso:country": "GB",
    "wof:name": "S75 3SL",
    "wof:placetype": "postalcode"
  },
  "geometry": {"coordinates":[-1.532616,53.542493],"type":"Point"}
}
