{
  "type": "Feature",
  "properties": {
    "iso:country":"GB",
    "wof:name":"S75 3SL",
    "wof:placetype":"postalcode"
},
  "geometry": {"coordinates":[-1.53261635153183,53.54249310566812],"type":"Point"}
}