{
  "type": "Feature",
  "properties": {
    "date:inception_lower":"1995-12-01",
    "date:inception_upper":"1995-12-31",
    "iso:country":"GB",
    "wof:name":"BS9 1UB",
    "wof:placetype":"postalcode"
},
  "geometry": {"coordinates":[-2.625355,51.479028],"type":"Point"}
}