{
  "type": "Feature",
  "properties": {
    "iso:country":"GB",
    "wof:name":"BS9 1UB",
    "wof:placetype":"postalcode"
},
  "geometry": {"coordinates":[-2.62535523138504,51.47902848214729],"type":"Point"}
}