{
  "type": "Feature",
  "properties": {
    "iso:country":"GB",
    "wof:name":"L33 1SX",
    "wof:placetype":"postalcode"
},
  "geometry": {"coordinates":[-2.89302583303469,53.49588070891581],"type":"Point"}
}