{
  "type": "Feature",
  "properties": {
    "iso:country": "GB",
    "wof:name": "L33 1SX",
    "wof:placetype": "postalcode"
  },
  "geometry": {"coordinates":[-2.893026,53.495881],"type":"Point"}
}
