{
  "type": "Feature",
  "properties": {
    "iso:country":"GB",
    "wof:name":"CM24 8TA",
    "wof:placetype":"postalcode"
},
  "geometry": {"coordinates":[0.19774100756423,51.91176210819009],"type":"Point"}
}