{
  "type": "Feature",
  "properties": {
    "date:inception_lower": "1980-01-01",
    "date:inception_upper": "1980-01-01",
    "iso:country": "GB",
    "wof:name": "CM24 8TA",
    "wof:placetype": "postalcode"
  },
  "geometry": {"coordinates":[0.198809,51.911355],"type":"Point"}
}
