{
  "type": "Feature",
  "properties": {
    "iso:country":"GB",
    "wof:name":"PR6 0SJ",
    "wof:placetype":"postalcode"
},
  "geometry": {"coordinates":[-2.62040984898966,53.65352074583601],"type":"Point"}
}