{
  "type": "Feature",
  "properties": {
    "date:inception_lower": "1997-12-01",
    "date:inception_upper": "1997-12-01",
    "iso:country": "GB",
    "wof:name": "WA4 3DP",
    "wof:placetype": "postalcode"
  },
  "geometry": {"coordinates":[-2.569067,53.361604],"type":"Point"}
}
