{
  "type": "Feature",
  "properties": {
    "iso:country":"GB",
    "wof:name":"WA4 3DP",
    "wof:placetype":"postalcode"
},
  "geometry": {"coordinates":[-2.56906678897428,53.36160392730996],"type":"Point"}
}