{
  "type": "Feature",
  "properties": {
    "date:inception_lower": "2023-08-01",
    "date:inception_upper": "2023-08-01",
    "iso:country": "GB",
    "wof:name": "TQ6 9FA",
    "wof:placetype": "postalcode"
  },
  "geometry": {"coordinates":[-3.601614,50.347788],"type":"Point"}
}
