{
  "type": "Feature",
  "properties": {
    "iso:country":"GB",
    "wof:name":"G41 5HH",
    "wof:placetype":"postalcode"
},
  "geometry": {"coordinates":[-4.28598095584641,55.84432980572821],"type":"Point"}
}