{
  "type": "Feature",
  "properties": {
    "iso:country":"GB",
    "wof:name":"PR9 9RL",
    "wof:placetype":"postalcode"
},
  "geometry": {"coordinates":[-2.97349166491155,53.66213587338198],"type":"Point"}
}