{
  "type": "Feature",
  "properties": {
    "iso:country":"GB",
    "wof:name":"CH61 8RY",
    "wof:placetype":"postalcode"
},
  "geometry": {"coordinates":[-3.10058193683198,53.35016343599463],"type":"Point"}
}