{
  "type": "Feature",
  "properties": {
    "date:inception_lower": "1980-01-01",
    "date:inception_upper": "1980-01-01",
    "iso:country": "GB",
    "wof:name": "SE18 6UB",
    "wof:placetype": "postalcode"
  },
  "geometry": {"coordinates":[0.06877,51.483413],"type":"Point"}
}
