{
  "type": "Feature",
  "properties": {
    "iso:country":"GB",
    "wof:name":"SE18 6UB",
    "wof:placetype":"postalcode"
},
  "geometry": {"coordinates":[0.06877026768554,51.48341292485342],"type":"Point"}
}