{
  "type": "Feature",
  "properties": {
    "iso:country": "GB",
    "wof:name": "SE18 6UB",
    "wof:placetype": "postalcode"
  },
  "geometry": {"coordinates":[0.06877,51.483413],"type":"Point"}
}
