{
  "type": "Feature",
  "properties": {
    "iso:country":"GB",
    "wof:name":"L6 1HA",
    "wof:placetype":"postalcode"
},
  "geometry": {"coordinates":[-2.96792928467453,53.41310342693276],"type":"Point"}
}