{
  "type": "Feature",
  "properties": {
    "date:inception_lower": "2001-12-01",
    "date:inception_upper": "2001-12-01",
    "iso:country": "GB",
    "wof:name": "L6 1HA",
    "wof:placetype": "postalcode"
  },
  "geometry": {"coordinates":[-2.967929,53.413103],"type":"Point"}
}
