{
  "type": "Feature",
  "properties": {
    "iso:country":"GB",
    "wof:name":"SP10 3QS",
    "wof:placetype":"postalcode"
},
  "geometry": {"coordinates":[-1.48591522610468,51.20678782134674],"type":"Point"}
}