{
  "type": "Feature",
  "properties": {
    "date:inception_lower": "1980-01-01",
    "date:inception_upper": "1980-01-01",
    "iso:country": "GB",
    "wof:name": "B33 0RL",
    "wof:placetype": "postalcode"
  },
  "geometry": {"coordinates":[-1.771774,52.469098],"type":"Point"}
}
