{
  "type": "Feature",
  "properties": {
    "date:inception_lower":"1980-01-01",
    "date:inception_upper":"1980-01-31",
    "iso:country":"GB",
    "wof:name":"DN14 0DJ",
    "wof:placetype":"postalcode"
},
  "geometry": {"coordinates":[-1.060287,53.668927],"type":"Point"}
}