{
  "type": "Feature",
  "properties": {
    "iso:country": "GB",
    "wof:name": "WA11 7RX",
    "wof:placetype": "postalcode"
  },
  "geometry": {"coordinates":[-2.751374,53.488188],"type":"Point"}
}
