{
  "type": "Feature",
  "properties": {
    "iso:country":"GB",
    "wof:name":"PO10 8EN",
    "wof:placetype":"postalcode"
},
  "geometry": {"coordinates":[-0.93247921435218,50.82413927751097],"type":"Point"}
}