{
  "type": "Feature",
  "properties": {
    "iso:country":"GB",
    "wof:name":"RH20 4ES",
    "wof:placetype":"postalcode"
},
  "geometry": {"coordinates":[-0.4528458483734,50.91727611935963],"type":"Point"}
}