{
  "type": "Feature",
  "properties": {
    "iso:country":"GB",
    "wof:name":"L23 5TP",
    "wof:placetype":"postalcode"
},
  "geometry": {"coordinates":[-3.02224814172982,53.49047652547046],"type":"Point"}
}