{
  "type": "Feature",
  "properties": {
    "iso:country":"GB",
    "wof:name":"LS8 1BG",
    "wof:placetype":"postalcode"
},
  "geometry": {"coordinates":[-1.51507854098485,53.8433665507138],"type":"Point"}
}