{
  "type": "Feature",
  "properties": {
    "iso:country":"GB",
    "wof:name":"WS7 0DA",
    "wof:placetype":"postalcode"
},
  "geometry": {"coordinates":[-1.91856356895608,52.67856422332902],"type":"Point"}
}