{
  "type": "Feature",
  "properties": {
    "iso:country":"GB",
    "wof:name":"BB18 5AQ",
    "wof:placetype":"postalcode"
},
  "geometry": {"coordinates":[-2.18809016023315,53.9152464204696],"type":"Point"}
}