{
  "type": "Feature",
  "properties": {
    "date:inception_lower":"1985-04-01",
    "date:inception_upper":"1985-04-30",
    "iso:country":"GB",
    "wof:name":"SL8 5XW",
    "wof:placetype":"postalcode"
},
  "geometry": {"coordinates":[-0.701709,51.576264],"type":"Point"}
}