{
  "type": "Feature",
  "properties": {
    "date:inception_lower": "1980-01-01",
    "date:inception_upper": "1980-01-01",
    "iso:country": "GB",
    "wof:name": "IP33 2LX",
    "wof:placetype": "postalcode"
  },
  "geometry": {"coordinates":[0.70648,52.237183],"type":"Point"}
}
