{
  "type": "Feature",
  "properties": {
    "iso:country":"GB",
    "wof:name":"NR8 6NS",
    "wof:placetype":"postalcode"
},
  "geometry": {"coordinates":[1.20119724461673,52.67904254477918],"type":"Point"}
}