{
  "type": "Feature",
  "properties": {
    "iso:country": "GB",
    "wof:name": "SO52 9FB",
    "wof:placetype": "postalcode"
  },
  "geometry": {"coordinates":[-1.441043,50.974134],"type":"Point"}
}
