{
  "type": "Feature",
  "properties": {
    "date:inception_lower":"1986-01-01",
    "date:inception_upper":"1986-01-31",
    "iso:country":"GB",
    "wof:name":"SO52 9FB",
    "wof:placetype":"postalcode"
},
  "geometry": {"coordinates":[-1.441043,50.974134],"type":"Point"}
}