{
  "type": "Feature",
  "properties": {
    "iso:country": "GB",
    "wof:name": "IP22 4AJ",
    "wof:placetype": "postalcode"
  },
  "geometry": {"coordinates":[1.108805,52.37565],"type":"Point"}
}
