{
  "type": "Feature",
  "properties": {
    "iso:country":"GB",
    "wof:name":"IP22 4AJ",
    "wof:placetype":"postalcode"
},
  "geometry": {"coordinates":[1.10880533870046,52.37565002700766],"type":"Point"}
}