{
  "type": "Feature",
  "properties": {
    "iso:country":"GB",
    "wof:name":"BA11 1NH",
    "wof:placetype":"postalcode"
},
  "geometry": {"coordinates":[-2.31853286560547,51.22532159272127],"type":"Point"}
}