{
  "type": "Feature",
  "properties": {
    "iso:country": "GB",
    "wof:name": "BA11 1NH",
    "wof:placetype": "postalcode"
  },
  "geometry": {"coordinates":[-2.318533,51.225322],"type":"Point"}
}
