{
  "type": "Feature",
  "properties": {
    "date:inception_lower": "1987-04-01",
    "date:inception_upper": "1987-04-01",
    "iso:country": "GB",
    "wof:name": "NG24 1LW",
    "wof:placetype": "postalcode"
  },
  "geometry": {"coordinates":[-0.800088,53.076599],"type":"Point"}
}
