{
  "type": "Feature",
  "properties": {
    "date:inception_lower": "1981-06-01",
    "date:inception_upper": "1981-06-01",
    "iso:country": "GB",
    "wof:name": "HR1 1YE",
    "wof:placetype": "postalcode"
  },
  "geometry": {"coordinates":[-2.677045,52.048999],"type":"Point"}
}
