{
  "type": "Feature",
  "properties": {
    "iso:country":"GB",
    "wof:name":"PL4 9ER",
    "wof:placetype":"postalcode"
},
  "geometry": {"coordinates":[-4.11716673612002,50.3770546177438],"type":"Point"}
}