{
  "type": "Feature",
  "properties": {
    "date:inception_lower": "1980-01-01",
    "date:inception_upper": "1980-01-01",
    "iso:country": "GB",
    "wof:name": "L7 7DX",
    "wof:placetype": "postalcode"
  },
  "geometry": {"coordinates":[-2.968471,53.400559],"type":"Point"}
}
