{
  "type": "Feature",
  "properties": {
    "iso:country":"GB",
    "wof:name":"B63 3EG",
    "wof:placetype":"postalcode"
},
  "geometry": {"coordinates":[-2.04582963078319,52.44523394911347],"type":"Point"}
}