{
  "type": "Feature",
  "properties": {
    "iso:country":"GB",
    "wof:name":"RG21 7AX",
    "wof:placetype":"postalcode"
},
  "geometry": {"coordinates":[-1.0847597594444,51.26740948524156],"type":"Point"}
}