{
  "type": "Feature",
  "properties": {
    "iso:country":"GB",
    "wof:name":"DA1 1NQ",
    "wof:placetype":"postalcode"
},
  "geometry": {"coordinates":[0.21774207891317,51.43292765826396],"type":"Point"}
}