{
  "type": "Feature",
  "properties": {
    "date:inception_lower": "2002-07-01",
    "date:inception_upper": "2002-07-01",
    "iso:country": "GB",
    "wof:name": "DA1 1NQ",
    "wof:placetype": "postalcode"
  },
  "geometry": {"coordinates":[0.217742,51.432928],"type":"Point"}
}
