{
  "type": "Feature",
  "properties": {
    "iso:country": "GB",
    "wof:name": "G73 3PT",
    "wof:placetype": "postalcode"
  },
  "geometry": {"coordinates":[-4.205067,55.823339],"type":"Point"}
}
