{
  "type": "Feature",
  "properties": {
    "iso:country":"GB",
    "wof:name":"BH2 5AZ",
    "wof:placetype":"postalcode"
},
  "geometry": {"coordinates":[-1.87843916013746,50.7182313092367],"type":"Point"}
}