{
  "type": "Feature",
  "properties": {
    "iso:country": "GB",
    "wof:name": "AB23 8AX",
    "wof:placetype": "postalcode"
  },
  "geometry": {"coordinates":[-2.083307,57.194946],"type":"Point"}
}
