{
  "type": "Feature",
  "properties": {
    "iso:country":"GB",
    "wof:name":"AB23 8AX",
    "wof:placetype":"postalcode"
},
  "geometry": {"coordinates":[-2.08330047071138,57.19496172701668],"type":"Point"}
}