{
  "type": "Feature",
  "properties": {
    "date:inception_lower": "1990-08-01",
    "date:inception_upper": "1990-08-01",
    "iso:country": "GB",
    "wof:name": "AB23 8AX",
    "wof:placetype": "postalcode"
  },
  "geometry": {"coordinates":[-2.083307,57.194946],"type":"Point"}
}
