{
  "type": "Feature",
  "properties": {
    "date:inception_lower": "1983-07-01",
    "date:inception_upper": "1983-07-01",
    "iso:country": "GB",
    "wof:name": "SM7 3HJ",
    "wof:placetype": "postalcode"
  },
  "geometry": {"coordinates":[-0.18039,51.32387],"type":"Point"}
}
