{
  "type": "Feature",
  "properties": {
    "iso:country": "GB",
    "wof:name": "NE26 1AJ",
    "wof:placetype": "postalcode"
  },
  "geometry": {"coordinates":[-1.445385,55.044005],"type":"Point"}
}
