{
  "type": "Feature",
  "properties": {
    "iso:country":"GB",
    "wof:name":"NE26 1AJ",
    "wof:placetype":"postalcode"
},
  "geometry": {"coordinates":[-1.44538521113864,55.04400487009148],"type":"Point"}
}