{
  "type": "Feature",
  "properties": {
    "date:inception_lower": "1980-01-01",
    "date:inception_upper": "1980-01-01",
    "iso:country": "GB",
    "wof:name": "DN16 3NH",
    "wof:placetype": "postalcode"
  },
  "geometry": {"coordinates":[-0.639053,53.560657],"type":"Point"}
}
