{
  "type": "Feature",
  "properties": {
    "iso:country":"GB",
    "wof:name":"W1D 5QJ",
    "wof:placetype":"postalcode"
},
  "geometry": {"coordinates":[-0.12998268401519,51.51207411836317],"type":"Point"}
}