{
  "type": "Feature",
  "properties": {
    "date:inception_lower": "2007-09-01",
    "date:inception_upper": "2007-09-01",
    "iso:country": "GB",
    "wof:name": "DT11 7FE",
    "wof:placetype": "postalcode"
  },
  "geometry": {"coordinates":[-2.166011,50.856951],"type":"Point"}
}
