{
  "type": "Feature",
  "properties": {
    "iso:country":"GB",
    "wof:name":"DT11 7FE",
    "wof:placetype":"postalcode"
},
  "geometry": {"coordinates":[-2.16602956071538,50.85687727375273],"type":"Point"}
}