{
  "type": "Feature",
  "properties": {
    "iso:country": "GB",
    "wof:name": "DT11 7FE",
    "wof:placetype": "postalcode"
  },
  "geometry": {"coordinates":[-2.166011,50.856951],"type":"Point"}
}
