{
  "type": "Feature",
  "properties": {
    "iso:country":"GB",
    "wof:name":"NG10 1ED",
    "wof:placetype":"postalcode"
},
  "geometry": {"coordinates":[-1.26781624472732,52.89635492557183],"type":"Point"}
}