{
  "type": "Feature",
  "properties": {
    "date:inception_lower": "1980-01-01",
    "date:inception_upper": "1980-01-01",
    "iso:country": "GB",
    "wof:name": "NG10 1ED",
    "wof:placetype": "postalcode"
  },
  "geometry": {"coordinates":[-1.267365,52.896353],"type":"Point"}
}
