{
  "type": "Feature",
  "properties": {
    "iso:country":"GB",
    "wof:name":"S70 3LH",
    "wof:placetype":"postalcode"
},
  "geometry": {"coordinates":[-1.45901506061848,53.5452929864816],"type":"Point"}
}