{
  "type": "Feature",
  "properties": {
    "iso:country":"GB",
    "wof:name":"SW19 7HA",
    "wof:placetype":"postalcode"
},
  "geometry": {"coordinates":[-0.20519926362212,51.42652561170888],"type":"Point"}
}