{
  "type": "Feature",
  "properties": {
    "iso:country": "GB",
    "wof:name": "DE1 2LJ",
    "wof:placetype": "postalcode"
  },
  "geometry": {"coordinates":[-1.469064,52.917911],"type":"Point"}
}
