{
  "type": "Feature",
  "properties": {
    "iso:country":"GB",
    "wof:name":"NG9 7GW",
    "wof:placetype":"postalcode"
},
  "geometry": {"coordinates":[-1.26666768669267,52.92477264351578],"type":"Point"}
}