{
  "type": "Feature",
  "properties": {
    "iso:country": "GB",
    "wof:name": "NG9 7GW",
    "wof:placetype": "postalcode"
  },
  "geometry": {"coordinates":[-1.266668,52.924773],"type":"Point"}
}
