{
  "type": "Feature",
  "properties": {
    "date:inception_lower": "1994-05-01",
    "date:inception_upper": "1994-05-01",
    "iso:country": "GB",
    "wof:name": "NG9 7GW",
    "wof:placetype": "postalcode"
  },
  "geometry": {"coordinates":[-1.266668,52.924773],"type":"Point"}
}
