{
  "type": "Feature",
  "properties": {
    "iso:country":"GB",
    "wof:name":"BS23 1TA",
    "wof:placetype":"postalcode"
},
  "geometry": {"coordinates":[-2.9797180997941,51.34638205486718],"type":"Point"}
}