{
  "type": "Feature",
  "properties": {
    "date:inception_lower": "1980-01-01",
    "date:inception_upper": "1980-01-01",
    "iso:country": "GB",
    "wof:name": "SS8 8JY",
    "wof:placetype": "postalcode"
  },
  "geometry": {"coordinates":[0.607581,51.521258],"type":"Point"}
}
