{
  "type": "Feature",
  "properties": {
    "iso:country":"GB",
    "wof:name":"HU2 8QP",
    "wof:placetype":"postalcode"
},
  "geometry": {"coordinates":[-0.34776485898718,53.74705409376508],"type":"Point"}
}