{
  "type": "Feature",
  "properties": {
    "iso:country":"GB",
    "wof:name":"ST11 9QA",
    "wof:placetype":"postalcode"
},
  "geometry": {"coordinates":[-2.05906710128534,52.96623013763528],"type":"Point"}
}