{
  "type": "Feature",
  "properties": {
    "iso:country": "GB",
    "wof:name": "BS16 6TL",
    "wof:placetype": "postalcode"
  },
  "geometry": {"coordinates":[-2.490704,51.497849],"type":"Point"}
}
