{
  "type": "Feature",
  "properties": {
    "iso:country": "GB",
    "wof:name": "S18 8ZE",
    "wof:placetype": "postalcode"
  },
  "geometry": {"coordinates":[-1.496051,53.30322],"type":"Point"}
}
