{
  "type": "Feature",
  "properties": {
    "date:inception_lower":"1997-06-01",
    "date:inception_upper":"1997-06-30",
    "iso:country":"GB",
    "wof:name":"S18 8ZE",
    "wof:placetype":"postalcode"
},
  "geometry": {"coordinates":[-1.496051,53.30322],"type":"Point"}
}