{
  "type": "Feature",
  "properties": {
    "iso:country":"GB",
    "wof:name":"MK40 3BD",
    "wof:placetype":"postalcode"
},
  "geometry": {"coordinates":[-0.44820575580152,52.14239640603976],"type":"Point"}
}