{
  "type": "Feature",
  "properties": {
    "iso:country":"GB",
    "wof:name":"SA5 7EX",
    "wof:placetype":"postalcode"
},
  "geometry": {"coordinates":[-3.95398613937801,51.64667242782853],"type":"Point"}
}