{
  "type": "Feature",
  "properties": {
    "iso:country":"GB",
    "wof:name":"HP5 3BU",
    "wof:placetype":"postalcode"
},
  "geometry": {"coordinates":[-0.60095725746687,51.71364411804341],"type":"Point"}
}