{
  "type": "Feature",
  "properties": {
    "iso:country": "GB",
    "wof:name": "LE14 4EF",
    "wof:placetype": "postalcode"
  },
  "geometry": {"coordinates":[-0.861516,52.841294],"type":"Point"}
}
