{
  "type": "Feature",
  "properties": {
    "date:inception_lower": "1980-01-01",
    "date:inception_upper": "1980-01-01",
    "iso:country": "GB",
    "wof:name": "LE14 4EF",
    "wof:placetype": "postalcode"
  },
  "geometry": {"coordinates":[-0.861516,52.841294],"type":"Point"}
}
