{
  "type": "Feature",
  "properties": {
    "iso:country":"GB",
    "wof:name":"LE14 4EF",
    "wof:placetype":"postalcode"
},
  "geometry": {"coordinates":[-0.86151649651188,52.84129407873336],"type":"Point"}
}