{
  "type": "Feature",
  "properties": {
    "iso:country": "GB",
    "wof:name": "WS12 2SZ",
    "wof:placetype": "postalcode"
  },
  "geometry": {"coordinates":[-1.983653,52.691455],"type":"Point"}
}
