{
  "type": "Feature",
  "properties": {
    "iso:country": "GB",
    "wof:name": "EX16 8JN",
    "wof:placetype": "postalcode"
  },
  "geometry": {"coordinates":[-3.537777,50.910828],"type":"Point"}
}
