{
  "type": "Feature",
  "properties": {
    "iso:country":"GB",
    "wof:name":"SK8 6NJ",
    "wof:placetype":"postalcode"
},
  "geometry": {"coordinates":[-2.1952793385179,53.35997908629821],"type":"Point"}
}