{
  "type": "Feature",
  "properties": {
    "iso:country":"GB",
    "wof:name":"SA67 8TW",
    "wof:placetype":"postalcode"
},
  "geometry": {"coordinates":[-4.70661368598097,51.78229630655881],"type":"Point"}
}