{
  "type": "Feature",
  "properties": {
    "iso:country": "GB",
    "wof:name": "SA67 8TW",
    "wof:placetype": "postalcode"
  },
  "geometry": {"coordinates":[-4.706614,51.782296],"type":"Point"}
}
