{
  "type": "Feature",
  "properties": {
    "date:inception_lower": "1980-01-01",
    "date:inception_upper": "1980-01-01",
    "iso:country": "GB",
    "wof:name": "SA67 8TW",
    "wof:placetype": "postalcode"
  },
  "geometry": {"coordinates":[-4.706614,51.782296],"type":"Point"}
}
