{
  "type": "Feature",
  "properties": {
    "iso:country":"GB",
    "wof:name":"EH54 6PZ",
    "wof:placetype":"postalcode"
},
  "geometry": {"coordinates":[-3.50743646620912,55.88740821547547],"type":"Point"}
}