{
  "type": "Feature",
  "properties": {
    "date:inception_lower": "1987-03-01",
    "date:inception_upper": "1987-03-01",
    "iso:country": "GB",
    "wof:name": "EH54 6PZ",
    "wof:placetype": "postalcode"
  },
  "geometry": {"coordinates":[-3.507436,55.887408],"type":"Point"}
}
