{
  "type": "Feature",
  "properties": {
    "iso:country":"GB",
    "wof:name":"G84 7BP",
    "wof:placetype":"postalcode"
},
  "geometry": {"coordinates":[-4.71459960198251,56.00079687243726],"type":"Point"}
}