{
  "type": "Feature",
  "properties": {
    "iso:country": "GB",
    "wof:name": "SA4 6PY",
    "wof:placetype": "postalcode"
  },
  "geometry": {"coordinates":[-4.053423,51.672978],"type":"Point"}
}
