{
  "type": "Feature",
  "properties": {
    "iso:country":"GB",
    "wof:name":"LE7 7EP",
    "wof:placetype":"postalcode"
},
  "geometry": {"coordinates":[-1.18853245175409,52.67753334376159],"type":"Point"}
}