{
  "type": "Feature",
  "properties": {
    "iso:country":"GB",
    "wof:name":"HP27 0JA",
    "wof:placetype":"postalcode"
},
  "geometry": {"coordinates":[-0.82440864211278,51.72297047754556],"type":"Point"}
}