{
  "type": "Feature",
  "properties": {
    "iso:country":"GB",
    "wof:name":"LE65 2QP",
    "wof:placetype":"postalcode"
},
  "geometry": {"coordinates":[-1.48033543029694,52.7525360402372],"type":"Point"}
}