{
  "type": "Feature",
  "properties": {
    "iso:country":"GB",
    "wof:name":"GU33 6AS",
    "wof:placetype":"postalcode"
},
  "geometry": {"coordinates":[-0.88481864711675,51.07815894249845],"type":"Point"}
}