{
  "type": "Feature",
  "properties": {
    "date:inception_lower": "2015-11-01",
    "date:inception_upper": "2015-11-01",
    "iso:country": "GB",
    "wof:name": "KT20 5FA",
    "wof:placetype": "postalcode"
  },
  "geometry": {"coordinates":[-0.229296,51.302066],"type":"Point"}
}
