{
  "type": "Feature",
  "properties": {
    "iso:country":"GB",
    "wof:name":"RH10 1LB",
    "wof:placetype":"postalcode"
},
  "geometry": {"coordinates":[-0.17385386461146,51.11593353409886],"type":"Point"}
}