{
  "type": "Feature",
  "properties": {
    "date:inception_lower": "1990-07-01",
    "date:inception_upper": "1990-07-01",
    "iso:country": "GB",
    "wof:name": "RH10 1LB",
    "wof:placetype": "postalcode"
  },
  "geometry": {"coordinates":[-0.173854,51.115934],"type":"Point"}
}
