{
  "type": "Feature",
  "properties": {
    "iso:country": "GB",
    "wof:name": "PO30 3EE",
    "wof:placetype": "postalcode"
  },
  "geometry": {"coordinates":[-1.303116,50.671859],"type":"Point"}
}
