{
  "type": "Feature",
  "properties": {
    "iso:country":"GB",
    "wof:name":"PO30 3EE",
    "wof:placetype":"postalcode"
},
  "geometry": {"coordinates":[-1.30312544960758,50.67186972053597],"type":"Point"}
}