{
  "type": "Feature",
  "properties": {
    "date:inception_lower": "1980-01-01",
    "date:inception_upper": "1980-01-01",
    "iso:country": "GB",
    "wof:name": "PO30 3EE",
    "wof:placetype": "postalcode"
  },
  "geometry": {"coordinates":[-1.303116,50.671859],"type":"Point"}
}
