{
  "type": "Feature",
  "properties": {
    "date:inception_lower": "2019-12-01",
    "date:inception_upper": "2019-12-01",
    "iso:country": "GB",
    "wof:name": "SO32 2TG",
    "wof:placetype": "postalcode"
  },
  "geometry": {"coordinates":[-1.271275,50.930009],"type":"Point"}
}
