{
  "type": "Feature",
  "properties": {
    "iso:country": "GB",
    "wof:name": "SO32 2TG",
    "wof:placetype": "postalcode"
  },
  "geometry": {"coordinates":[-1.276661,50.925861],"type":"Point"}
}
