{
  "type": "Feature",
  "properties": {
    "iso:country":"GB",
    "wof:name":"AL3 7PG",
    "wof:placetype":"postalcode"
},
  "geometry": {"coordinates":[-0.39350600799656,51.80045127220564],"type":"Point"}
}