{
  "type": "Feature",
  "properties": {
    "iso:country": "GB",
    "wof:name": "SE2 0LD",
    "wof:placetype": "postalcode"
  },
  "geometry": {"coordinates":[0.117253,51.485947],"type":"Point"}
}
