{
  "type": "Feature",
  "properties": {
    "iso:country":"GB",
    "wof:name":"SE2 0LD",
    "wof:placetype":"postalcode"
},
  "geometry": {"coordinates":[0.11725317210966,51.48594674017712],"type":"Point"}
}