{
  "type": "Feature",
  "properties": {
    "iso:country":"GB",
    "wof:name":"CF39 8SD",
    "wof:placetype":"postalcode"
},
  "geometry": {"coordinates":[-3.47735493878312,51.59529853580183],"type":"Point"}
}