{
  "type": "Feature",
  "properties": {
    "date:inception_lower":"1980-01-01",
    "date:inception_upper":"1980-01-31",
    "iso:country":"GB",
    "wof:name":"TA7 9PF",
    "wof:placetype":"postalcode"
},
  "geometry": {"coordinates":[-2.811727,51.129711],"type":"Point"}
}