{
  "type": "Feature",
  "properties": {
    "date:inception_lower": "2009-06-01",
    "date:inception_upper": "2009-06-01",
    "iso:country": "GB",
    "wof:name": "KT19 8HJ",
    "wof:placetype": "postalcode"
  },
  "geometry": {"coordinates":[-0.28425,51.346128],"type":"Point"}
}
