{
  "type": "Feature",
  "properties": {
    "iso:country":"GB",
    "wof:name":"KT19 8HJ",
    "wof:placetype":"postalcode"
},
  "geometry": {"coordinates":[-0.28428851201379,51.34612978374652],"type":"Point"}
}