{
  "type": "Feature",
  "properties": {
    "iso:country": "GB",
    "wof:name": "PR7 7JF",
    "wof:placetype": "postalcode"
  },
  "geometry": {"coordinates":[-2.660572,53.675478],"type":"Point"}
}
