{
  "type": "Feature",
  "properties": {
    "iso:country": "GB",
    "wof:name": "LL57 2NS",
    "wof:placetype": "postalcode"
  },
  "geometry": {"coordinates":[-4.169606,53.206082],"type":"Point"}
}
