{
  "type": "Feature",
  "properties": {
    "date:inception_lower":"1980-01-01",
    "date:inception_upper":"1980-01-31",
    "iso:country":"GB",
    "wof:name":"LL57 2NS",
    "wof:placetype":"postalcode"
},
  "geometry": {"coordinates":[-4.169606,53.206082],"type":"Point"}
}