{
  "type": "Feature",
  "properties": {
    "date:inception_lower": "2021-04-01",
    "date:inception_upper": "2021-04-01",
    "iso:country": "GB",
    "wof:name": "NN14 4GH",
    "wof:placetype": "postalcode"
  },
  "geometry": {"coordinates":[-0.527728,52.39162],"type":"Point"}
}
