{
  "type": "Feature",
  "properties": {
    "iso:country":"GB",
    "wof:name":"UB3 2JL",
    "wof:placetype":"postalcode"
},
  "geometry": {"coordinates":[-0.41380034970306,51.51874641328671],"type":"Point"}
}