{
  "type": "Feature",
  "properties": {
    "iso:country":"GB",
    "wof:name":"G83 0DX",
    "wof:placetype":"postalcode"
},
  "geometry": {"coordinates":[-4.58336166680105,55.9890661467023],"type":"Point"}
}