{
  "type": "Feature",
  "properties": {
    "iso:country": "GB",
    "wof:name": "HD9 5AJ",
    "wof:placetype": "postalcode"
  },
  "geometry": {"coordinates":[-1.857162,53.596774],"type":"Point"}
}
