{
  "type": "Feature",
  "properties": {
    "iso:country": "GB",
    "wof:name": "IP14 5RJ",
    "wof:placetype": "postalcode"
  },
  "geometry": {"coordinates":[1.071156,52.225634],"type":"Point"}
}
