{
  "type": "Feature",
  "properties": {
    "iso:country":"GB",
    "wof:name":"IP14 5RJ",
    "wof:placetype":"postalcode"
},
  "geometry": {"coordinates":[1.07115642422115,52.22563449241721],"type":"Point"}
}