{
  "type": "Feature",
  "properties": {
    "iso:country":"GB",
    "wof:name":"EH6 8LB",
    "wof:placetype":"postalcode"
},
  "geometry": {"coordinates":[-3.16552018301103,55.96364237570354],"type":"Point"}
}