{
  "type": "Feature",
  "properties": {
    "date:inception_lower": "2017-07-01",
    "date:inception_upper": "2017-07-01",
    "iso:country": "GB",
    "wof:name": "PR7 7LL",
    "wof:placetype": "postalcode"
  },
  "geometry": {"coordinates":[-2.659953,53.674637],"type":"Point"}
}
