{
  "type": "Feature",
  "properties": {
    "iso:country":"GB",
    "wof:name":"NG9 3ND",
    "wof:placetype":"postalcode"
},
  "geometry": {"coordinates":[-1.24744738857126,52.95062309131176],"type":"Point"}
}