{
  "type": "Feature",
  "properties": {
    "iso:country":"GB",
    "wof:name":"E17 8SB",
    "wof:placetype":"postalcode"
},
  "geometry": {"coordinates":[-0.03391443914744,51.57562736746503],"type":"Point"}
}