{
  "type": "Feature",
  "properties": {
    "iso:country":"GB",
    "wof:name":"BD23 5EQ",
    "wof:placetype":"postalcode"
},
  "geometry": {"coordinates":[-1.97903557945294,54.08904267740139],"type":"Point"}
}