{
  "type": "Feature",
  "properties": {
    "iso:country": "GB",
    "wof:name": "BD23 5EQ",
    "wof:placetype": "postalcode"
  },
  "geometry": {"coordinates":[-1.9793,54.089074],"type":"Point"}
}
