{
  "type": "Feature",
  "properties": {
    "iso:country": "GB",
    "wof:name": "BD23 5EQ",
    "wof:placetype": "postalcode"
  },
  "geometry": {"coordinates":[-1.97904,54.089056],"type":"Point"}
}
