{
  "type": "Feature",
  "properties": {
    "iso:country":"GB",
    "wof:name":"YO23 2RD",
    "wof:placetype":"postalcode"
},
  "geometry": {"coordinates":[-1.09514382923465,53.9222514588643],"type":"Point"}
}