{
  "type": "Feature",
  "properties": {
    "iso:country":"GB",
    "wof:name":"M20 2UN",
    "wof:placetype":"postalcode"
},
  "geometry": {"coordinates":[-2.24214277714208,53.42055714121057],"type":"Point"}
}