{
  "type": "Feature",
  "properties": {
    "date:inception_lower": "2017-01-01",
    "date:inception_upper": "2017-01-01",
    "iso:country": "GB",
    "wof:name": "GL7 4GH",
    "wof:placetype": "postalcode"
  },
  "geometry": {"coordinates":[-1.76342,51.708457],"type":"Point"}
}
