{
  "type": "Feature",
  "properties": {
    "iso:country": "GB",
    "wof:name": "TS18 4QJ",
    "wof:placetype": "postalcode"
  },
  "geometry": {"coordinates":[-1.340296,54.568294],"type":"Point"}
}
