{
  "type": "Feature",
  "properties": {
    "date:inception_lower": "2004-11-01",
    "date:inception_upper": "2004-11-01",
    "iso:country": "GB",
    "wof:name": "TS18 4QJ",
    "wof:placetype": "postalcode"
  },
  "geometry": {"coordinates":[-1.340296,54.568294],"type":"Point"}
}
