{
  "type": "Feature",
  "properties": {
    "iso:country":"GB",
    "wof:name":"TS18 4QJ",
    "wof:placetype":"postalcode"
},
  "geometry": {"coordinates":[-1.34029632389514,54.56829427522158],"type":"Point"}
}