{
  "type": "Feature",
  "properties": {
    "date:inception_lower": "1980-01-01",
    "date:inception_upper": "1980-01-01",
    "iso:country": "GB",
    "wof:name": "FY5 2JZ",
    "wof:placetype": "postalcode"
  },
  "geometry": {"coordinates":[-3.02708,53.887684],"type":"Point"}
}
