{
  "type": "Feature",
  "properties": {
    "date:inception_lower":"1980-01-01",
    "date:inception_upper":"1980-01-31",
    "iso:country":"GB",
    "wof:name":"BL9 0LA",
    "wof:placetype":"postalcode"
},
  "geometry": {"coordinates":[-2.297859,53.594168],"type":"Point"}
}