{
  "type": "Feature",
  "properties": {
    "iso:country":"GB",
    "wof:name":"BL9 0LA",
    "wof:placetype":"postalcode"
},
  "geometry": {"coordinates":[-2.2978589373507,53.59416843022575],"type":"Point"}
}