{
  "type": "Feature",
  "properties": {
    "iso:country": "GB",
    "wof:name": "BL9 0LA",
    "wof:placetype": "postalcode"
  },
  "geometry": {"coordinates":[-2.297859,53.594168],"type":"Point"}
}
