{
  "type": "Feature",
  "properties": {
    "iso:country":"GB",
    "wof:name":"L26 1UH",
    "wof:placetype":"postalcode"
},
  "geometry": {"coordinates":[-2.84175171628801,53.35692654754138],"type":"Point"}
}