{
  "type": "Feature",
  "properties": {
    "iso:country": "GB",
    "wof:name": "L26 1UH",
    "wof:placetype": "postalcode"
  },
  "geometry": {"coordinates":[-2.841752,53.356927],"type":"Point"}
}
