{
  "type": "Feature",
  "properties": {
    "iso:country": "GB",
    "wof:name": "LA10 5PS",
    "wof:placetype": "postalcode"
  },
  "geometry": {"coordinates":[-2.345131,54.334983],"type":"Point"}
}
