{
  "type": "Feature",
  "properties": {
    "iso:country":"GB",
    "wof:name":"LA10 5PS",
    "wof:placetype":"postalcode"
},
  "geometry": {"coordinates":[-2.3451310401877,54.3349828195937],"type":"Point"}
}