{
  "type": "Feature",
  "properties": {
    "iso:country": "GB",
    "wof:name": "BN18 0HZ",
    "wof:placetype": "postalcode"
  },
  "geometry": {"coordinates":[-0.613925,50.823569],"type":"Point"}
}
