{
  "type": "Feature",
  "properties": {
    "iso:country":"GB",
    "wof:name":"BN18 0HZ",
    "wof:placetype":"postalcode"
},
  "geometry": {"coordinates":[-0.6139252870945,50.82356918856793],"type":"Point"}
}