{
  "type": "Feature",
  "properties": {
    "date:inception_lower":"1990-07-01",
    "date:inception_upper":"1990-07-31",
    "iso:country":"GB",
    "wof:name":"BN18 0HZ",
    "wof:placetype":"postalcode"
},
  "geometry": {"coordinates":[-0.613925,50.823569],"type":"Point"}
}