{
  "type": "Feature",
  "properties": {
    "iso:country":"GB",
    "wof:name":"LS27 7PY",
    "wof:placetype":"postalcode"
},
  "geometry": {"coordinates":[-1.59329724964253,53.75931342554538],"type":"Point"}
}