{
  "type": "Feature",
  "properties": {
    "iso:country": "GB",
    "wof:name": "BS16 6SY",
    "wof:placetype": "postalcode"
  },
  "geometry": {"coordinates":[-2.49688,51.502797],"type":"Point"}
}
