{
  "type": "Feature",
  "properties": {
    "iso:country":"GB",
    "wof:name":"DN2 5EJ",
    "wof:placetype":"postalcode"
},
  "geometry": {"coordinates":[-1.11131250596387,53.52766506231064],"type":"Point"}
}