{
  "type": "Feature",
  "properties": {
    "date:inception_lower": "2007-10-01",
    "date:inception_upper": "2007-10-01",
    "iso:country": "GB",
    "wof:name": "CA7 9PD",
    "wof:placetype": "postalcode"
  },
  "geometry": {"coordinates":[-3.164159,54.823824],"type":"Point"}
}
