{
  "type": "Feature",
  "properties": {
    "iso:country":"GB",
    "wof:name":"CA7 9PD",
    "wof:placetype":"postalcode"
},
  "geometry": {"coordinates":[-3.16415919681021,54.82382400711372],"type":"Point"}
}