{
  "type": "Feature",
  "properties": {
    "iso:country": "GB",
    "wof:name": "CA7 9PD",
    "wof:placetype": "postalcode"
  },
  "geometry": {"coordinates":[-3.164159,54.823824],"type":"Point"}
}
