{
  "type": "Feature",
  "properties": {
    "iso:country":"GB",
    "wof:name":"AL10 9BB",
    "wof:placetype":"postalcode"
},
  "geometry": {"coordinates":[-0.26285629664091,51.78813594427778],"type":"Point"}
}