{
  "type": "Feature",
  "properties": {
    "iso:country":"GB",
    "wof:name":"B43 5JN",
    "wof:placetype":"postalcode"
},
  "geometry": {"coordinates":[-1.94333542980308,52.54272535638115],"type":"Point"}
}