{
  "type": "Feature",
  "properties": {
    "iso:country":"GB",
    "wof:name":"SY3 9EA",
    "wof:placetype":"postalcode"
},
  "geometry": {"coordinates":[-2.77462388509455,52.68823152802997],"type":"Point"}
}