{
  "type": "Feature",
  "properties": {
    "iso:country": "GB",
    "wof:name": "SY3 9EA",
    "wof:placetype": "postalcode"
  },
  "geometry": {"coordinates":[-2.774624,52.688232],"type":"Point"}
}
