{
  "type": "Feature",
  "properties": {
    "iso:country": "GB",
    "wof:name": "IV25 3LD",
    "wof:placetype": "postalcode"
  },
  "geometry": {"coordinates":[-4.019508,57.881237],"type":"Point"}
}
