{
  "type": "Feature",
  "properties": {
    "iso:country":"GB",
    "wof:name":"IV25 3LD",
    "wof:placetype":"postalcode"
},
  "geometry": {"coordinates":[-4.01950805990247,57.8812368066781],"type":"Point"}
}