{
  "type": "Feature",
  "properties": {
    "iso:country":"GB",
    "wof:name":"SS7 4DS",
    "wof:placetype":"postalcode"
},
  "geometry": {"coordinates":[0.55328288810781,51.57136820475316],"type":"Point"}
}