{
  "type": "Feature",
  "properties": {
    "iso:country": "GB",
    "wof:name": "CM9 8UT",
    "wof:placetype": "postalcode"
  },
  "geometry": {"coordinates":[0.687722,51.771464],"type":"Point"}
}
