{
  "type": "Feature",
  "properties": {
    "date:inception_lower": "1986-07-01",
    "date:inception_upper": "1986-07-01",
    "iso:country": "GB",
    "wof:name": "CM9 8UT",
    "wof:placetype": "postalcode"
  },
  "geometry": {"coordinates":[0.687722,51.771464],"type":"Point"}
}
