{
  "type": "Feature",
  "properties": {
    "iso:country":"GB",
    "wof:name":"CM9 8UT",
    "wof:placetype":"postalcode"
},
  "geometry": {"coordinates":[0.68772187294963,51.77146449470504],"type":"Point"}
}