{
  "type": "Feature",
  "properties": {
    "date:inception_lower": "2012-02-01",
    "date:inception_upper": "2012-02-01",
    "iso:country": "GB",
    "wof:name": "L27 4YE",
    "wof:placetype": "postalcode"
  },
  "geometry": {"coordinates":[-2.831814,53.384367],"type":"Point"}
}
