{
  "type": "Feature",
  "properties": {
    "iso:country": "GB",
    "wof:name": "CB1 3US",
    "wof:placetype": "postalcode"
  },
  "geometry": {"coordinates":[0.147307,52.204147],"type":"Point"}
}
