{
  "type": "Feature",
  "properties": {
    "date:inception_lower": "2003-02-01",
    "date:inception_upper": "2003-02-01",
    "iso:country": "GB",
    "wof:name": "CB1 3US",
    "wof:placetype": "postalcode"
  },
  "geometry": {"coordinates":[0.147307,52.204147],"type":"Point"}
}
