{
  "type": "Feature",
  "properties": {
    "iso:country": "GB",
    "wof:name": "NE13 7FF",
    "wof:placetype": "postalcode"
  },
  "geometry": {"coordinates":[-1.680866,55.055235],"type":"Point"}
}
