{
  "type": "Feature",
  "properties": {
    "iso:country":"GB",
    "wof:name":"CO10 9DA",
    "wof:placetype":"postalcode"
},
  "geometry": {"coordinates":[0.72659339788327,52.09183413673015],"type":"Point"}
}