{
  "type": "Feature",
  "properties": {
    "iso:country": "GB",
    "wof:name": "CO10 9DA",
    "wof:placetype": "postalcode"
  },
  "geometry": {"coordinates":[0.726593,52.091834],"type":"Point"}
}
