{
  "type": "Feature",
  "properties": {
    "iso:country": "GB",
    "wof:name": "CO10 9DA",
    "wof:placetype": "postalcode"
  },
  "geometry": {"coordinates":[0.726626,52.091884],"type":"Point"}
}
