{
  "type": "Feature",
  "properties": {
    "iso:country":"GB",
    "wof:name":"B75 6PA",
    "wof:placetype":"postalcode"
},
  "geometry": {"coordinates":[-1.8234824970243,52.57338883371312],"type":"Point"}
}