{
  "type": "Feature",
  "properties": {
    "iso:country":"GB",
    "wof:name":"CW7 3QY",
    "wof:placetype":"postalcode"
},
  "geometry": {"coordinates":[-2.4914555602927,53.19828920237493],"type":"Point"}
}