{
  "type": "Feature",
  "properties": {
    "date:inception_lower": "1981-06-01",
    "date:inception_upper": "1981-06-01",
    "iso:country": "GB",
    "wof:name": "CW7 3QY",
    "wof:placetype": "postalcode"
  },
  "geometry": {"coordinates":[-2.488975,53.198881],"type":"Point"}
}
