{
  "type": "Feature",
  "properties": {
    "date:inception_lower": "2023-06-01",
    "date:inception_upper": "2023-06-01",
    "iso:country": "GB",
    "wof:name": "CF48 2AN",
    "wof:placetype": "postalcode"
  },
  "geometry": {"coordinates":[-3.401151,51.771434],"type":"Point"}
}
