{
  "type": "Feature",
  "properties": {
    "date:inception_lower": "1990-02-01",
    "date:inception_upper": "1990-02-01",
    "iso:country": "GB",
    "wof:name": "HP16 0HR",
    "wof:placetype": "postalcode"
  },
  "geometry": {"coordinates":[-0.703076,51.689378],"type":"Point"}
}
