{
  "type": "Feature",
  "properties": {
    "iso:country":"GB",
    "wof:name":"CW7 1JA",
    "wof:placetype":"postalcode"
},
  "geometry": {"coordinates":[-2.53623387147241,53.18552940780834],"type":"Point"}
}