{
  "type": "Feature",
  "properties": {
    "date:inception_lower": "1981-06-01",
    "date:inception_upper": "1981-06-01",
    "iso:country": "GB",
    "wof:name": "LL42 1EP",
    "wof:placetype": "postalcode"
  },
  "geometry": {"coordinates":[-4.060023,52.726165],"type":"Point"}
}
