{
  "type": "Feature",
  "properties": {
    "iso:country":"GB",
    "wof:name":"LL42 1EP",
    "wof:placetype":"postalcode"
},
  "geometry": {"coordinates":[-4.06002277885316,52.72616511976825],"type":"Point"}
}