{
  "type": "Feature",
  "properties": {
    "iso:country": "GB",
    "wof:name": "CV37 7QB",
    "wof:placetype": "postalcode"
  },
  "geometry": {"coordinates":[-1.667573,52.20254],"type":"Point"}
}
