{
  "type": "Feature",
  "properties": {
    "date:inception_lower": "1980-01-01",
    "date:inception_upper": "1980-01-01",
    "iso:country": "GB",
    "wof:name": "CV37 7QB",
    "wof:placetype": "postalcode"
  },
  "geometry": {"coordinates":[-1.667573,52.20254],"type":"Point"}
}
