{
  "type": "Feature",
  "properties": {
    "iso:country":"GB",
    "wof:name":"CV37 7QB",
    "wof:placetype":"postalcode"
},
  "geometry": {"coordinates":[-1.66717263774266,52.20267734725918],"type":"Point"}
}