{
  "type": "Feature",
  "properties": {
    "date:inception_lower": "2024-09-01",
    "date:inception_upper": "2024-09-01",
    "iso:country": "GB",
    "wof:name": "WD18 8AU",
    "wof:placetype": "postalcode"
  },
  "geometry": {"coordinates":[-0.422237,51.650069],"type":"Point"}
}
