{
  "type": "Feature",
  "properties": {
    "iso:country": "GB",
    "wof:name": "PE21 9RY",
    "wof:placetype": "postalcode"
  },
  "geometry": {"coordinates":[0.027123,52.981847],"type":"Point"}
}
