{
  "type": "Feature",
  "properties": {
    "iso:country":"GB",
    "wof:name":"PE21 9RY",
    "wof:placetype":"postalcode"
},
  "geometry": {"coordinates":[0.02700121863344,52.9819502959383],"type":"Point"}
}