{
  "type": "Feature",
  "properties": {
    "date:inception_lower": "2004-10-01",
    "date:inception_upper": "2004-10-01",
    "iso:country": "GB",
    "wof:name": "TN24 9RN",
    "wof:placetype": "postalcode"
  },
  "geometry": {"coordinates":[0.872798,51.17069],"type":"Point"}
}
