{
  "type": "Feature",
  "properties": {
    "iso:country":"GB",
    "wof:name":"ME4 5AY",
    "wof:placetype":"postalcode"
},
  "geometry": {"coordinates":[0.54324744992165,51.3691068188587],"type":"Point"}
}