{
  "type": "Feature",
  "properties": {
    "date:inception_lower":"2015-01-01",
    "date:inception_upper":"2015-01-31",
    "iso:country":"GB",
    "wof:name":"ME4 5AY",
    "wof:placetype":"postalcode"
},
  "geometry": {"coordinates":[0.543247,51.369107],"type":"Point"}
}