{
  "type": "Feature",
  "properties": {
    "iso:country": "GB",
    "wof:name": "ME4 5AY",
    "wof:placetype": "postalcode"
  },
  "geometry": {"coordinates":[0.543247,51.369107],"type":"Point"}
}
