{
  "type": "Feature",
  "properties": {
    "iso:country":"GB",
    "wof:name":"SO16 0XU",
    "wof:placetype":"postalcode"
},
  "geometry": {"coordinates":[-1.47104286967577,50.93616406919563],"type":"Point"}
}