{
  "type": "Feature",
  "properties": {
    "date:inception_lower": "1994-12-01",
    "date:inception_upper": "1994-12-01",
    "iso:country": "GB",
    "wof:name": "SO16 0XU",
    "wof:placetype": "postalcode"
  },
  "geometry": {"coordinates":[-1.471043,50.936164],"type":"Point"}
}
