{
  "type": "Feature",
  "properties": {
    "iso:country":"GB",
    "wof:name":"SA43 2AL",
    "wof:placetype":"postalcode"
},
  "geometry": {"coordinates":[-4.55740941759192,52.1117672108775],"type":"Point"}
}