{
  "type": "Feature",
  "properties": {
    "iso:country":"GB",
    "wof:name":"ST4 7PU",
    "wof:placetype":"postalcode"
},
  "geometry": {"coordinates":[-2.19838025308597,53.01467456059593],"type":"Point"}
}