{
  "type": "Feature",
  "properties": {
    "date:inception_lower": "1980-01-01",
    "date:inception_upper": "1980-01-01",
    "iso:country": "GB",
    "wof:name": "EX5 5AP",
    "wof:placetype": "postalcode"
  },
  "geometry": {"coordinates":[-3.586606,50.780529],"type":"Point"}
}
