{
  "type": "Feature",
  "properties": {
    "iso:country":"GB",
    "wof:name":"PO9 4DQ",
    "wof:placetype":"postalcode"
},
  "geometry": {"coordinates":[-0.9997680489227,50.86969013370628],"type":"Point"}
}