{
  "type": "Feature",
  "properties": {
    "iso:country":"GB",
    "wof:name":"IV16 9XJ",
    "wof:placetype":"postalcode"
},
  "geometry": {"coordinates":[-4.30427953279717,57.67579945594173],"type":"Point"}
}