{
  "type": "Feature",
  "properties": {
    "iso:country":"GB",
    "wof:name":"M22 1EN",
    "wof:placetype":"postalcode"
},
  "geometry": {"coordinates":[-2.27574234679512,53.37399523116034],"type":"Point"}
}