{
  "type": "Feature",
  "properties": {
    "iso:country": "GB",
    "wof:name": "M22 1EN",
    "wof:placetype": "postalcode"
  },
  "geometry": {"coordinates":[-2.275742,53.373995],"type":"Point"}
}
