{
  "type": "Feature",
  "properties": {
    "date:inception_lower": "2007-07-01",
    "date:inception_upper": "2007-07-01",
    "iso:country": "GB",
    "wof:name": "PE25 1JQ",
    "wof:placetype": "postalcode"
  },
  "geometry": {"coordinates":[0.334972,53.198218],"type":"Point"}
}
