{
  "type": "Feature",
  "properties": {
    "iso:country": "GB",
    "wof:name": "PE25 1JQ",
    "wof:placetype": "postalcode"
  },
  "geometry": {"coordinates":[0.335064,53.198261],"type":"Point"}
}
