{
  "type": "Feature",
  "properties": {
    "iso:country":"GB",
    "wof:name":"SO50 4JE",
    "wof:placetype":"postalcode"
},
  "geometry": {"coordinates":[-1.34844612902718,50.97947267661367],"type":"Point"}
}