{
  "type": "Feature",
  "properties": {
    "iso:country":"GB",
    "wof:name":"SY2 5QG",
    "wof:placetype":"postalcode"
},
  "geometry": {"coordinates":[-2.72635292544982,52.71247709774838],"type":"Point"}
}