{
  "type": "Feature",
  "properties": {
    "iso:country": "GB",
    "wof:name": "SY2 5QG",
    "wof:placetype": "postalcode"
  },
  "geometry": {"coordinates":[-2.726353,52.712477],"type":"Point"}
}
