{
  "type": "Feature",
  "properties": {
    "date:inception_lower": "1980-01-01",
    "date:inception_upper": "1980-01-01",
    "iso:country": "GB",
    "wof:name": "SA62 5XA",
    "wof:placetype": "postalcode"
  },
  "geometry": {"coordinates":[-5.03732,51.964153],"type":"Point"}
}
