{
  "type": "Feature",
  "properties": {
    "iso:country":"GB",
    "wof:name":"SM6 9HD",
    "wof:placetype":"postalcode"
},
  "geometry": {"coordinates":[-0.13232377330874,51.35458758622607],"type":"Point"}
}