{
  "type": "Feature",
  "properties": {
    "iso:country": "GB",
    "wof:name": "CW1 5QN",
    "wof:placetype": "postalcode"
  },
  "geometry": {"coordinates":[-2.406953,53.101716],"type":"Point"}
}
