{
  "type": "Feature",
  "properties": {
    "iso:country":"GB",
    "wof:name":"CW1 5QN",
    "wof:placetype":"postalcode"
},
  "geometry": {"coordinates":[-2.40695297152447,53.10171551833089],"type":"Point"}
}