{
  "type": "Feature",
  "properties": {
    "iso:country":"GB",
    "wof:name":"DA17 6EF",
    "wof:placetype":"postalcode"
},
  "geometry": {"coordinates":[0.15151525812144,51.4901252352923],"type":"Point"}
}