{
  "type": "Feature",
  "properties": {
    "iso:country": "GB",
    "wof:name": "G32 6TP",
    "wof:placetype": "postalcode"
  },
  "geometry": {"coordinates":[-4.171168,55.857042],"type":"Point"}
}
