{
  "type": "Feature",
  "properties": {
    "date:inception_lower": "1980-01-01",
    "date:inception_upper": "1980-01-01",
    "iso:country": "GB",
    "wof:name": "SN7 8EA",
    "wof:placetype": "postalcode"
  },
  "geometry": {"coordinates":[-1.597087,51.685603],"type":"Point"}
}
