{
  "type": "Feature",
  "properties": {
    "iso:country":"GB",
    "wof:name":"SN7 8EA",
    "wof:placetype":"postalcode"
},
  "geometry": {"coordinates":[-1.59708726691579,51.68560301613087],"type":"Point"}
}