{
  "type": "Feature",
  "properties": {
    "date:inception_lower":"2002-08-01",
    "date:inception_upper":"2002-08-31",
    "iso:country":"GB",
    "wof:name":"SN6 7AB",
    "wof:placetype":"postalcode"
},
  "geometry": {"coordinates":[-1.709611,51.631495],"type":"Point"}
}