{
  "type": "Feature",
  "properties": {
    "iso:country": "GB",
    "wof:name": "SN6 7AB",
    "wof:placetype": "postalcode"
  },
  "geometry": {"coordinates":[-1.709596,51.63154],"type":"Point"}
}
