{
  "type": "Feature",
  "properties": {
    "iso:country":"GB",
    "wof:name":"SN6 7AB",
    "wof:placetype":"postalcode"
},
  "geometry": {"coordinates":[-1.70960914820318,51.63153775054104],"type":"Point"}
}