{
  "type": "Feature",
  "properties": {
    "iso:country":"GB",
    "wof:name":"NR35 2HT",
    "wof:placetype":"postalcode"
},
  "geometry": {"coordinates":[1.45705472084669,52.50124957699659],"type":"Point"}
}