{
  "type": "Feature",
  "properties": {
    "iso:country": "GB",
    "wof:name": "NR35 2HT",
    "wof:placetype": "postalcode"
  },
  "geometry": {"coordinates":[1.457055,52.50125],"type":"Point"}
}
