{
  "type": "Feature",
  "properties": {
    "iso:country":"GB",
    "wof:name":"CF23 9FB",
    "wof:placetype":"postalcode"
},
  "geometry": {"coordinates":[-3.15008384989053,51.49541274354745],"type":"Point"}
}