{
  "type": "Feature",
  "properties": {
    "iso:country": "GB",
    "wof:name": "TN12 8DQ",
    "wof:placetype": "postalcode"
  },
  "geometry": {"coordinates":[0.43572,51.146319],"type":"Point"}
}
