{
  "type": "Feature",
  "properties": {
    "date:inception_lower": "1980-01-01",
    "date:inception_upper": "1980-01-01",
    "iso:country": "GB",
    "wof:name": "TN12 8DQ",
    "wof:placetype": "postalcode"
  },
  "geometry": {"coordinates":[0.43572,51.146319],"type":"Point"}
}
