{
  "type": "Feature",
  "properties": {
    "iso:country":"GB",
    "wof:name":"TN12 8DQ",
    "wof:placetype":"postalcode"
},
  "geometry": {"coordinates":[0.43572041105155,51.14631884255105],"type":"Point"}
}