{
  "type": "Feature",
  "properties": {
    "iso:country":"GB",
    "wof:name":"TW16 5AF",
    "wof:placetype":"postalcode"
},
  "geometry": {"coordinates":[-0.40372079398602,51.41491056723419],"type":"Point"}
}