{
  "type": "Feature",
  "properties": {
    "date:inception_lower":"1992-01-01",
    "date:inception_upper":"1992-01-31",
    "iso:country":"GB",
    "wof:name":"TW16 5AF",
    "wof:placetype":"postalcode"
},
  "geometry": {"coordinates":[-0.403721,51.414911],"type":"Point"}
}