{
  "type": "Feature",
  "properties": {
    "iso:country": "GB",
    "wof:name": "TW16 5AF",
    "wof:placetype": "postalcode"
  },
  "geometry": {"coordinates":[-0.403721,51.414911],"type":"Point"}
}
