{
  "type": "Feature",
  "properties": {
    "date:inception_lower": "2000-12-01",
    "date:inception_upper": "2000-12-01",
    "iso:country": "GB",
    "wof:name": "WD24 7TG",
    "wof:placetype": "postalcode"
  },
  "geometry": {"coordinates":[-0.383144,51.67159],"type":"Point"}
}
