{
  "type": "Feature",
  "properties": {
    "date:inception_lower": "1996-12-01",
    "date:inception_upper": "1996-12-01",
    "iso:country": "GB",
    "wof:name": "SK22 4JF",
    "wof:placetype": "postalcode"
  },
  "geometry": {"coordinates":[-1.987938,53.369046],"type":"Point"}
}
