{
  "type": "Feature",
  "properties": {
    "iso:country":"GB",
    "wof:name":"TN37 6BJ",
    "wof:placetype":"postalcode"
},
  "geometry": {"coordinates":[0.56153845784111,50.8537768719772],"type":"Point"}
}