{
  "type": "Feature",
  "properties": {
    "date:inception_lower": "1980-01-01",
    "date:inception_upper": "1980-01-01",
    "iso:country": "GB",
    "wof:name": "RG8 8PU",
    "wof:placetype": "postalcode"
  },
  "geometry": {"coordinates":[-1.123791,51.475602],"type":"Point"}
}
