{
  "type": "Feature",
  "properties": {
    "iso:country":"GB",
    "wof:name":"CF72 8QD",
    "wof:placetype":"postalcode"
},
  "geometry": {"coordinates":[-3.36886568087181,51.53789685013612],"type":"Point"}
}