{
  "type": "Feature",
  "properties": {
    "iso:country": "GB",
    "wof:name": "TS22 5GZ",
    "wof:placetype": "postalcode"
  },
  "geometry": {"coordinates":[-1.302302,54.623971],"type":"Point"}
}
