{
  "type": "Feature",
  "properties": {
    "iso:country":"GB",
    "wof:name":"TS22 5GZ",
    "wof:placetype":"postalcode"
},
  "geometry": {"coordinates":[-1.30230218751766,54.62397126680378],"type":"Point"}
}