{
  "type": "Feature",
  "properties": {
    "iso:country": "GB",
    "wof:name": "DL8 5JH",
    "wof:placetype": "postalcode"
  },
  "geometry": {"coordinates":[-1.819004,54.338011],"type":"Point"}
}
