{
  "type": "Feature",
  "properties": {
    "iso:country":"GB",
    "wof:name":"DL8 5JH",
    "wof:placetype":"postalcode"
},
  "geometry": {"coordinates":[-1.81900425884606,54.33801093864241],"type":"Point"}
}