{
  "type": "Feature",
  "properties": {
    "date:inception_lower": "2006-07-01",
    "date:inception_upper": "2006-07-01",
    "iso:country": "GB",
    "wof:name": "NN11 8AS",
    "wof:placetype": "postalcode"
  },
  "geometry": {"coordinates":[-1.168592,52.280747],"type":"Point"}
}
