{
  "type": "Feature",
  "properties": {
    "iso:country":"GB",
    "wof:name":"NN11 8AS",
    "wof:placetype":"postalcode"
},
  "geometry": {"coordinates":[-1.16859180666917,52.28074746187166],"type":"Point"}
}