{
  "type": "Feature",
  "properties": {
    "iso:country": "GB",
    "wof:name": "SY4 2DA",
    "wof:placetype": "postalcode"
  },
  "geometry": {"coordinates":[-2.831476,52.816427],"type":"Point"}
}
