{
  "type": "Feature",
  "properties": {
    "date:inception_lower": "1980-01-01",
    "date:inception_upper": "1980-01-01",
    "iso:country": "GB",
    "wof:name": "BS14 9EZ",
    "wof:placetype": "postalcode"
  },
  "geometry": {"coordinates":[-2.558583,51.420075],"type":"Point"}
}
