{
  "type": "Feature",
  "properties": {
    "iso:country":"GB",
    "wof:name":"SP1 2LA",
    "wof:placetype":"postalcode"
},
  "geometry": {"coordinates":[-1.77714480286754,51.06411923362793],"type":"Point"}
}