{
  "type": "Feature",
  "properties": {
    "iso:country":"GB",
    "wof:name":"GU15 3PH",
    "wof:placetype":"postalcode"
},
  "geometry": {"coordinates":[-0.7500321081693,51.33512861556735],"type":"Point"}
}