{
  "type": "Feature",
  "properties": {
    "date:inception_lower": "1980-01-01",
    "date:inception_upper": "1980-01-01",
    "iso:country": "GB",
    "wof:name": "WF5 9LJ",
    "wof:placetype": "postalcode"
  },
  "geometry": {"coordinates":[-1.578172,53.685352],"type":"Point"}
}
