{
  "type": "Feature",
  "properties": {
    "iso:country":"GB",
    "wof:name":"WF5 9LJ",
    "wof:placetype":"postalcode"
},
  "geometry": {"coordinates":[-1.57817192322868,53.68535169964766],"type":"Point"}
}