{
  "type": "Feature",
  "properties": {
    "iso:country": "GB",
    "wof:name": "KA7 3LN",
    "wof:placetype": "postalcode"
  },
  "geometry": {"coordinates":[-4.597885,55.459961],"type":"Point"}
}
