{
  "type": "Feature",
  "properties": {
    "iso:country": "GB",
    "wof:name": "TN27 0RT",
    "wof:placetype": "postalcode"
  },
  "geometry": {"coordinates":[0.746871,51.156996],"type":"Point"}
}
