{
  "type": "Feature",
  "properties": {
    "iso:country":"GB",
    "wof:name":"TN27 0RT",
    "wof:placetype":"postalcode"
},
  "geometry": {"coordinates":[0.7468555175956,51.15700565536827],"type":"Point"}
}