{
  "type": "Feature",
  "properties": {
    "date:inception_lower":"1980-01-01",
    "date:inception_upper":"1980-01-31",
    "iso:country":"GB",
    "wof:name":"UB3 4EX",
    "wof:placetype":"postalcode"
},
  "geometry": {"coordinates":[-0.425678,51.496552],"type":"Point"}
}