{
  "type": "Feature",
  "properties": {
    "iso:country":"GB",
    "wof:name":"UB3 4EX",
    "wof:placetype":"postalcode"
},
  "geometry": {"coordinates":[-0.42567814049652,51.49655177763794],"type":"Point"}
}