{
  "type": "Feature",
  "properties": {
    "iso:country": "GB",
    "wof:name": "EH19 2PE",
    "wof:placetype": "postalcode"
  },
  "geometry": {"coordinates":[-3.122631,55.871041],"type":"Point"}
}
