{
  "type": "Feature",
  "properties": {
    "iso:country":"GB",
    "wof:name":"DD8 2QB",
    "wof:placetype":"postalcode"
},
  "geometry": {"coordinates":[-2.76504763679209,56.62868021865759],"type":"Point"}
}