{
  "type": "Feature",
  "properties": {
    "iso:country":"GB",
    "wof:name":"S10 3RA",
    "wof:placetype":"postalcode"
},
  "geometry": {"coordinates":[-1.54348349250114,53.36948740342163],"type":"Point"}
}