{
  "type": "Feature",
  "properties": {
    "iso:country": "GB",
    "wof:name": "SN11 0AA",
    "wof:placetype": "postalcode"
  },
  "geometry": {"coordinates":[-2.001591,51.434022],"type":"Point"}
}
