{
  "type": "Feature",
  "properties": {
    "iso:country": "GB",
    "wof:name": "DL13 1EF",
    "wof:placetype": "postalcode"
  },
  "geometry": {"coordinates":[-2.208403,54.746776],"type":"Point"}
}
