{
  "type": "Feature",
  "properties": {
    "iso:country":"GB",
    "wof:name":"DL13 1EF",
    "wof:placetype":"postalcode"
},
  "geometry": {"coordinates":[-2.20831752148303,54.74674217069857],"type":"Point"}
}