{
  "type": "Feature",
  "properties": {
    "iso:country": "GB",
    "wof:name": "IP3 9UU",
    "wof:placetype": "postalcode"
  },
  "geometry": {"coordinates":[1.193842,52.026964],"type":"Point"}
}
