{
  "type": "Feature",
  "properties": {
    "iso:country":"GB",
    "wof:name":"NE22 5PY",
    "wof:placetype":"postalcode"
},
  "geometry": {"coordinates":[-1.57583522450346,55.13775082044738],"type":"Point"}
}