{
  "type": "Feature",
  "properties": {
    "iso:country":"GB",
    "wof:name":"CR0 8BX",
    "wof:placetype":"postalcode"
},
  "geometry": {"coordinates":[-0.03230733985989,51.37598080348726],"type":"Point"}
}