{
  "type": "Feature",
  "properties": {
    "iso:country": "GB",
    "wof:name": "SY13 4BB",
    "wof:placetype": "postalcode"
  },
  "geometry": {"coordinates":[-2.555142,52.965739],"type":"Point"}
}
