{
  "type": "Feature",
  "properties": {
    "iso:country":"GB",
    "wof:name":"SY13 4BB",
    "wof:placetype":"postalcode"
},
  "geometry": {"coordinates":[-2.55514216251612,52.96573854416363],"type":"Point"}
}