{
  "type": "Feature",
  "properties": {
    "date:inception_lower": "1980-01-01",
    "date:inception_upper": "1980-01-01",
    "iso:country": "GB",
    "wof:name": "BN13 2RL",
    "wof:placetype": "postalcode"
  },
  "geometry": {"coordinates":[-0.415205,50.83381],"type":"Point"}
}
