{
  "type": "Feature",
  "properties": {
    "date:inception_lower": "1985-04-01",
    "date:inception_upper": "1985-04-01",
    "iso:country": "GB",
    "wof:name": "FY8 3LE",
    "wof:placetype": "postalcode"
  },
  "geometry": {"coordinates":[-3.023174,53.769458],"type":"Point"}
}
