{
  "type": "Feature",
  "properties": {
    "iso:country":"GB",
    "wof:name":"IV2 4BP",
    "wof:placetype":"postalcode"
},
  "geometry": {"coordinates":[-4.22790607421991,57.45452127069794],"type":"Point"}
}