{
  "type": "Feature",
  "properties": {
    "date:inception_lower": "1980-01-01",
    "date:inception_upper": "1980-01-01",
    "iso:country": "GB",
    "wof:name": "LE5 4WE",
    "wof:placetype": "postalcode"
  },
  "geometry": {"coordinates":[-1.086627,52.626574],"type":"Point"}
}
