{
  "type": "Feature",
  "properties": {
    "iso:country":"GB",
    "wof:name":"LE5 4WE",
    "wof:placetype":"postalcode"
},
  "geometry": {"coordinates":[-1.08647356224521,52.62654584840081],"type":"Point"}
}