{
  "type": "Feature",
  "properties": {
    "iso:country":"GB",
    "wof:name":"G33 2AP",
    "wof:placetype":"postalcode"
},
  "geometry": {"coordinates":[-4.19049923407834,55.87033325259738],"type":"Point"}
}