{
  "type": "Feature",
  "properties": {
    "iso:country":"GB",
    "wof:name":"YO31 1JF",
    "wof:placetype":"postalcode"
},
  "geometry": {"coordinates":[-1.04884229547288,53.97360235488361],"type":"Point"}
}