{
  "type": "Feature",
  "properties": {
    "iso:country": "GB",
    "wof:name": "GU33 6AZ",
    "wof:placetype": "postalcode"
  },
  "geometry": {"coordinates":[-0.883462,51.079247],"type":"Point"}
}
