{
  "type": "Feature",
  "properties": {
    "iso:country":"GB",
    "wof:name":"AL2 1RN",
    "wof:placetype":"postalcode"
},
  "geometry": {"coordinates":[-0.29615846566396,51.72237926909826],"type":"Point"}
}