{
  "type": "Feature",
  "properties": {
    "iso:country":"GB",
    "wof:name":"SL1 3JA",
    "wof:placetype":"postalcode"
},
  "geometry": {"coordinates":[-0.60092038723881,51.52129808380406],"type":"Point"}
}