{
  "type": "Feature",
  "properties": {
    "date:inception_lower":"1980-01-01",
    "date:inception_upper":"1980-01-31",
    "iso:country":"GB",
    "wof:name":"SL1 3JA",
    "wof:placetype":"postalcode"
},
  "geometry": {"coordinates":[-0.60092,51.521298],"type":"Point"}
}