{
  "type": "Feature",
  "properties": {
    "iso:country": "GB",
    "wof:name": "TD9 0PW",
    "wof:placetype": "postalcode"
  },
  "geometry": {"coordinates":[-2.887878,55.358792],"type":"Point"}
}
