{
  "type": "Feature",
  "properties": {
    "iso:country":"GB",
    "wof:name":"TD9 0PW",
    "wof:placetype":"postalcode"
},
  "geometry": {"coordinates":[-2.88787836321413,55.35879199498793],"type":"Point"}
}