{
  "type": "Feature",
  "properties": {
    "iso:country":"GB",
    "wof:name":"BB10 4QW",
    "wof:placetype":"postalcode"
},
  "geometry": {"coordinates":[-2.22735224932736,53.78890748679662],"type":"Point"}
}