{
  "type": "Feature",
  "properties": {
    "iso:country":"GB",
    "wof:name":"LL30 1LE",
    "wof:placetype":"postalcode"
},
  "geometry": {"coordinates":[-3.82646596600235,53.31365914150622],"type":"Point"}
}