{
  "type": "Feature",
  "properties": {
    "iso:country": "GB",
    "wof:name": "LL30 1LE",
    "wof:placetype": "postalcode"
  },
  "geometry": {"coordinates":[-3.826466,53.313659],"type":"Point"}
}
