{
  "type": "Feature",
  "properties": {
    "iso:country": "GB",
    "wof:name": "HU15 1UE",
    "wof:placetype": "postalcode"
  },
  "geometry": {"coordinates":[-0.563749,53.725171],"type":"Point"}
}
