{
  "type": "Feature",
  "properties": {
    "iso:country":"GB",
    "wof:name":"HU15 1UE",
    "wof:placetype":"postalcode"
},
  "geometry": {"coordinates":[-0.56374880726019,53.72517125983487],"type":"Point"}
}