{
  "type": "Feature",
  "properties": {
    "iso:country":"GB",
    "wof:name":"WF9 1PH",
    "wof:placetype":"postalcode"
},
  "geometry": {"coordinates":[-1.27351360629562,53.61825877278897],"type":"Point"}
}