{
  "type": "Feature",
  "properties": {
    "iso:country": "GB",
    "wof:name": "WF9 1PH",
    "wof:placetype": "postalcode"
  },
  "geometry": {"coordinates":[-1.273514,53.618259],"type":"Point"}
}
