{
  "type": "Feature",
  "properties": {
    "iso:country":"GB",
    "wof:name":"NE5 3AL",
    "wof:placetype":"postalcode"
},
  "geometry": {"coordinates":[-1.65234942139291,54.98982083458235],"type":"Point"}
}