{
  "type": "Feature",
  "properties": {
    "iso:country":"GB",
    "wof:name":"DD8 1BB",
    "wof:placetype":"postalcode"
},
  "geometry": {"coordinates":[-2.8891428868201,56.64417057407319],"type":"Point"}
}