{
  "type": "Feature",
  "properties": {
    "date:inception_lower": "2017-03-01",
    "date:inception_upper": "2017-03-01",
    "iso:country": "GB",
    "wof:name": "SR5 2HH",
    "wof:placetype": "postalcode"
  },
  "geometry": {"coordinates":[-1.40136,54.921141],"type":"Point"}
}
