{
  "type": "Feature",
  "properties": {
    "date:inception_lower":"1980-01-01",
    "date:inception_upper":"1980-01-31",
    "iso:country":"GB",
    "wof:name":"SL0 9AF",
    "wof:placetype":"postalcode"
},
  "geometry": {"coordinates":[-0.504519,51.505759],"type":"Point"}
}