{
  "type": "Feature",
  "properties": {
    "iso:country": "GB",
    "wof:name": "BA12 6FL",
    "wof:placetype": "postalcode"
  },
  "geometry": {"coordinates":[-2.262345,51.083435],"type":"Point"}
}
