{
  "type": "Feature",
  "properties": {
    "date:inception_lower": "2019-10-01",
    "date:inception_upper": "2019-10-01",
    "iso:country": "GB",
    "wof:name": "BA12 6FL",
    "wof:placetype": "postalcode"
  },
  "geometry": {"coordinates":[-2.26203,51.083202],"type":"Point"}
}
