{
  "type": "Feature",
  "properties": {
    "iso:country": "GB",
    "wof:name": "DY8 4TQ",
    "wof:placetype": "postalcode"
  },
  "geometry": {"coordinates":[-2.164444,52.469572],"type":"Point"}
}
