{
  "type": "Feature",
  "properties": {
    "iso:country":"GB",
    "wof:name":"DY8 4TQ",
    "wof:placetype":"postalcode"
},
  "geometry": {"coordinates":[-2.16444441154818,52.46957206305955],"type":"Point"}
}