{
  "type": "Feature",
  "properties": {
    "date:inception_lower": "1980-01-01",
    "date:inception_upper": "1980-01-01",
    "iso:country": "GB",
    "wof:name": "DY8 4TQ",
    "wof:placetype": "postalcode"
  },
  "geometry": {"coordinates":[-2.164444,52.469572],"type":"Point"}
}
