{
  "type": "Feature",
  "properties": {
    "iso:country":"GB",
    "wof:name":"WA13 0QJ",
    "wof:placetype":"postalcode"
},
  "geometry": {"coordinates":[-2.48318729093916,53.38120047861513],"type":"Point"}
}