{
  "type": "Feature",
  "properties": {
    "date:inception_lower": "1981-07-01",
    "date:inception_upper": "1981-07-01",
    "iso:country": "GB",
    "wof:name": "KA7 1UW",
    "wof:placetype": "postalcode"
  },
  "geometry": {"coordinates":[-4.62684,55.457176],"type":"Point"}
}
