{
  "type": "Feature",
  "properties": {
    "iso:country": "GB",
    "wof:name": "BA2 1RD",
    "wof:placetype": "postalcode"
  },
  "geometry": {"coordinates":[-2.406395,51.375491],"type":"Point"}
}
