{
  "type": "Feature",
  "properties": {
    "iso:country":"GB",
    "wof:name":"BH20 4PT",
    "wof:placetype":"postalcode"
},
  "geometry": {"coordinates":[-2.11557550302134,50.68276063260318],"type":"Point"}
}