{
  "type": "Feature",
  "properties": {
    "iso:country": "GB",
    "wof:name": "BH20 4PT",
    "wof:placetype": "postalcode"
  },
  "geometry": {"coordinates":[-2.115575,50.682761],"type":"Point"}
}
