{
  "type": "Feature",
  "properties": {
    "iso:country":"GB",
    "wof:name":"CH60 8PT",
    "wof:placetype":"postalcode"
},
  "geometry": {"coordinates":[-3.09768212756784,53.32091256458224],"type":"Point"}
}