{
  "type": "Feature",
  "properties": {
    "iso:country": "GB",
    "wof:name": "PE20 3JP",
    "wof:placetype": "postalcode"
  },
  "geometry": {"coordinates":[-0.153202,52.939498],"type":"Point"}
}
