{
  "type": "Feature",
  "properties": {
    "iso:country":"GB",
    "wof:name":"WA11 0HA",
    "wof:placetype":"postalcode"
},
  "geometry": {"coordinates":[-2.68254107036595,53.46832505235516],"type":"Point"}
}