{
  "type": "Feature",
  "properties": {
    "iso:country": "GB",
    "wof:name": "ST19 5HR",
    "wof:placetype": "postalcode"
  },
  "geometry": {"coordinates":[-2.107173,52.719833],"type":"Point"}
}
