{
  "type": "Feature",
  "properties": {
    "iso:country":"GB",
    "wof:name":"B31 2PB",
    "wof:placetype":"postalcode"
},
  "geometry": {"coordinates":[-1.97599701739544,52.4036256391445],"type":"Point"}
}