{
  "type": "Feature",
  "properties": {
    "date:inception_lower":"2004-01-01",
    "date:inception_upper":"2004-01-31",
    "iso:country":"GB",
    "wof:name":"B31 2PB",
    "wof:placetype":"postalcode"
},
  "geometry": {"coordinates":[-1.975997,52.403626],"type":"Point"}
}