{
  "type": "Feature",
  "properties": {
    "iso:country": "GB",
    "wof:name": "DL14 9JX",
    "wof:placetype": "postalcode"
  },
  "geometry": {"coordinates":[-1.7255,54.629911],"type":"Point"}
}
