{
  "type": "Feature",
  "properties": {
    "iso:country":"GB",
    "wof:name":"DL14 9JX",
    "wof:placetype":"postalcode"
},
  "geometry": {"coordinates":[-1.72550041647128,54.62991081073748],"type":"Point"}
}