{
  "type": "Feature",
  "properties": {
    "iso:country":"GB",
    "wof:name":"DG7 2PQ",
    "wof:placetype":"postalcode"
},
  "geometry": {"coordinates":[-4.01763824780233,54.95483666822857],"type":"Point"}
}