{
  "type": "Feature",
  "properties": {
    "iso:country":"GB",
    "wof:name":"NP23 5LH",
    "wof:placetype":"postalcode"
},
  "geometry": {"coordinates":[-3.20750496159921,51.78699389813681],"type":"Point"}
}