{
  "type": "Feature",
  "properties": {
    "date:inception_lower":"1999-06-01",
    "date:inception_upper":"1999-06-30",
    "iso:country":"GB",
    "wof:name":"NP23 5LH",
    "wof:placetype":"postalcode"
},
  "geometry": {"coordinates":[-3.207499,51.787044],"type":"Point"}
}