{
  "type": "Feature",
  "properties": {
    "iso:country":"GB",
    "wof:name":"LL54 5HY",
    "wof:placetype":"postalcode"
},
  "geometry": {"coordinates":[-4.4235663229051,52.9951225907019],"type":"Point"}
}