{
  "type": "Feature",
  "properties": {
    "date:inception_lower": "1987-04-01",
    "date:inception_upper": "1987-04-01",
    "iso:country": "GB",
    "wof:name": "NE61 2TG",
    "wof:placetype": "postalcode"
  },
  "geometry": {"coordinates":[-1.678054,55.154328],"type":"Point"}
}
