{
  "type": "Feature",
  "properties": {
    "iso:country": "GB",
    "wof:name": "SY13 2NB",
    "wof:placetype": "postalcode"
  },
  "geometry": {"coordinates":[-2.715213,52.912591],"type":"Point"}
}
