{
  "type": "Feature",
  "properties": {
    "iso:country":"GB",
    "wof:name":"SY13 2NB",
    "wof:placetype":"postalcode"
},
  "geometry": {"coordinates":[-2.71521347177426,52.91259125326836],"type":"Point"}
}