{
  "type": "Feature",
  "properties": {
    "iso:country":"GB",
    "wof:name":"SG8 0ES",
    "wof:placetype":"postalcode"
},
  "geometry": {"coordinates":[-0.13090895348251,52.11016292321197],"type":"Point"}
}