{
  "type": "Feature",
  "properties": {
    "iso:country":"GB",
    "wof:name":"KA21 6GL",
    "wof:placetype":"postalcode"
},
  "geometry": {"coordinates":[-4.7867792876413,55.65146970986363],"type":"Point"}
}