{
  "type": "Feature",
  "properties": {
    "date:inception_lower":"1997-12-01",
    "date:inception_upper":"1997-12-31",
    "iso:country":"GB",
    "wof:name":"BS48 2AR",
    "wof:placetype":"postalcode"
},
  "geometry": {"coordinates":[-2.770834,51.433617],"type":"Point"}
}