{
  "type": "Feature",
  "properties": {
    "iso:country": "GB",
    "wof:name": "SW10 0AU",
    "wof:placetype": "postalcode"
  },
  "geometry": {"coordinates":[-0.178888,51.485265],"type":"Point"}
}
