{
  "type": "Feature",
  "properties": {
    "iso:country":"GB",
    "wof:name":"SW10 0AU",
    "wof:placetype":"postalcode"
},
  "geometry": {"coordinates":[-0.17892493386518,51.48531824032942],"type":"Point"}
}