{
  "type": "Feature",
  "properties": {
    "iso:country":"GB",
    "wof:name":"TN27 9TD",
    "wof:placetype":"postalcode"
},
  "geometry": {"coordinates":[0.63098493548207,51.16895253760157],"type":"Point"}
}