{
  "type": "Feature",
  "properties": {
    "date:inception_lower":"1980-01-01",
    "date:inception_upper":"1980-01-31",
    "iso:country":"GB",
    "wof:name":"TN5 6DA",
    "wof:placetype":"postalcode"
},
  "geometry": {"coordinates":[0.331767,51.063925],"type":"Point"}
}