{
  "type": "Feature",
  "properties": {
    "iso:country":"GB",
    "wof:name":"LL24 0HE",
    "wof:placetype":"postalcode"
},
  "geometry": {"coordinates":[-3.78823979443409,53.09741560341498],"type":"Point"}
}