{
  "type": "Feature",
  "properties": {
    "date:inception_lower": "1980-01-01",
    "date:inception_upper": "1980-01-01",
    "iso:country": "GB",
    "wof:name": "LL24 0HE",
    "wof:placetype": "postalcode"
  },
  "geometry": {"coordinates":[-3.78824,53.097416],"type":"Point"}
}
