{
  "type": "Feature",
  "properties": {
    "iso:country":"GB",
    "wof:name":"NP23 6EF",
    "wof:placetype":"postalcode"
},
  "geometry": {"coordinates":[-3.20528238018037,51.77867260485747],"type":"Point"}
}