{
  "type": "Feature",
  "properties": {
    "iso:country":"GB",
    "wof:name":"SA6 7JF",
    "wof:placetype":"postalcode"
},
  "geometry": {"coordinates":[-3.94341709183945,51.66721569687578],"type":"Point"}
}