{
  "type": "Feature",
  "properties": {
    "iso:country": "GB",
    "wof:name": "OX11 6FH",
    "wof:placetype": "postalcode"
  },
  "geometry": {"coordinates":[-1.265047,51.600864],"type":"Point"}
}
