{
  "type": "Feature",
  "properties": {
    "iso:country":"GB",
    "wof:name":"SO40 3GA",
    "wof:placetype":"postalcode"
},
  "geometry": {"coordinates":[-1.50597601059013,50.91915046832207],"type":"Point"}
}