{
  "type": "Feature",
  "properties": {
    "iso:country":"GB",
    "wof:name":"SR8 4AN",
    "wof:placetype":"postalcode"
},
  "geometry": {"coordinates":[-1.32893597563277,54.77103808068825],"type":"Point"}
}