{
  "type": "Feature",
  "properties": {
    "iso:country":"GB",
    "wof:name":"NG7 2NF",
    "wof:placetype":"postalcode"
},
  "geometry": {"coordinates":[-1.17573128870894,52.94545500359843],"type":"Point"}
}