{
  "type": "Feature",
  "properties": {
    "date:inception_lower": "2022-10-01",
    "date:inception_upper": "2022-10-01",
    "iso:country": "GB",
    "wof:name": "B31 5FG",
    "wof:placetype": "postalcode"
  },
  "geometry": {"coordinates":[-1.989261,52.409216],"type":"Point"}
}
