{
  "type": "Feature",
  "properties": {
    "iso:country":"GB",
    "wof:name":"FY6 7JE",
    "wof:placetype":"postalcode"
},
  "geometry": {"coordinates":[-2.98584236973793,53.84804115096146],"type":"Point"}
}