{
  "type": "Feature",
  "properties": {
    "iso:country":"GB",
    "wof:name":"SE5 0YW",
    "wof:placetype":"postalcode"
},
  "geometry": {"coordinates":[-0.09546688875634,51.48096192082668],"type":"Point"}
}