{
  "type": "Feature",
  "properties": {
    "date:inception_lower":"1980-01-01",
    "date:inception_upper":"1980-01-31",
    "iso:country":"GB",
    "wof:name":"UB2 5AL",
    "wof:placetype":"postalcode"
},
  "geometry": {"coordinates":[-0.383213,51.502737],"type":"Point"}
}