{
  "type": "Feature",
  "properties": {
    "iso:country": "GB",
    "wof:name": "UB2 5AL",
    "wof:placetype": "postalcode"
  },
  "geometry": {"coordinates":[-0.383213,51.502737],"type":"Point"}
}
