{
  "type": "Feature",
  "properties": {
    "iso:country":"GB",
    "wof:name":"BD23 4HT",
    "wof:placetype":"postalcode"
},
  "geometry": {"coordinates":[-2.22188925724781,54.00432897894985],"type":"Point"}
}