{
  "type": "Feature",
  "properties": {
    "iso:country":"GB",
    "wof:name":"LE9 2WU",
    "wof:placetype":"postalcode"
},
  "geometry": {"coordinates":[-1.23365306109929,52.63559900109961],"type":"Point"}
}