{
  "type": "Feature",
  "properties": {
    "iso:country":"GB",
    "wof:name":"IP30 0TL",
    "wof:placetype":"postalcode"
},
  "geometry": {"coordinates":[0.74793774914875,52.20833734250602],"type":"Point"}
}