{
  "type": "Feature",
  "properties": {
    "iso:country":"GB",
    "wof:name":"FY6 9AY",
    "wof:placetype":"postalcode"
},
  "geometry": {"coordinates":[-2.95335310713728,53.87720992017733],"type":"Point"}
}