{
  "type": "Feature",
  "properties": {
    "date:inception_lower": "1980-01-01",
    "date:inception_upper": "1980-01-01",
    "iso:country": "GB",
    "wof:name": "FY6 9AY",
    "wof:placetype": "postalcode"
  },
  "geometry": {"coordinates":[-2.953353,53.87721],"type":"Point"}
}
