{
  "type": "Feature",
  "properties": {
    "iso:country": "GB",
    "wof:name": "OX12 8PX",
    "wof:placetype": "postalcode"
  },
  "geometry": {"coordinates":[-1.373904,51.603758],"type":"Point"}
}
