{
  "type": "Feature",
  "properties": {
    "date:inception_lower":"1980-01-01",
    "date:inception_upper":"1980-01-31",
    "iso:country":"GB",
    "wof:name":"OX12 8PX",
    "wof:placetype":"postalcode"
},
  "geometry": {"coordinates":[-1.373904,51.603758],"type":"Point"}
}