{
  "type": "Feature",
  "properties": {
    "iso:country":"GB",
    "wof:name":"OX12 8PX",
    "wof:placetype":"postalcode"
},
  "geometry": {"coordinates":[-1.37390448513562,51.60375773778019],"type":"Point"}
}