{
  "type": "Feature",
  "properties": {
    "iso:country": "GB",
    "wof:name": "OX11 0NA",
    "wof:placetype": "postalcode"
  },
  "geometry": {"coordinates":[-1.268891,51.584664],"type":"Point"}
}
