{
  "type": "Feature",
  "properties": {
    "date:inception_lower": "2020-08-01",
    "date:inception_upper": "2020-08-01",
    "iso:country": "GB",
    "wof:name": "BS30 5AD",
    "wof:placetype": "postalcode"
  },
  "geometry": {"coordinates":[-2.404539,51.453471],"type":"Point"}
}
