{
  "type": "Feature",
  "properties": {
    "iso:country":"GB",
    "wof:name":"TW15 2JR",
    "wof:placetype":"postalcode"
},
  "geometry": {"coordinates":[-0.45782930170139,51.43558889265785],"type":"Point"}
}