{
  "type": "Feature",
  "properties": {
    "date:inception_lower": "1980-01-01",
    "date:inception_upper": "1980-01-01",
    "iso:country": "GB",
    "wof:name": "SN11 8SL",
    "wof:placetype": "postalcode"
  },
  "geometry": {"coordinates":[-1.963414,51.467708],"type":"Point"}
}
