{
  "type": "Feature",
  "properties": {
    "iso:country": "GB",
    "wof:name": "SN11 8SL",
    "wof:placetype": "postalcode"
  },
  "geometry": {"coordinates":[-1.963414,51.467708],"type":"Point"}
}
