{
  "type": "Feature",
  "properties": {
    "iso:country":"GB",
    "wof:name":"SN11 8SL",
    "wof:placetype":"postalcode"
},
  "geometry": {"coordinates":[-1.96341428647073,51.46770780469704],"type":"Point"}
}