{
  "type": "Feature",
  "properties": {
    "date:inception_lower":"1980-01-01",
    "date:inception_upper":"1980-01-31",
    "iso:country":"GB",
    "wof:name":"B64 6PN",
    "wof:placetype":"postalcode"
},
  "geometry": {"coordinates":[-2.055013,52.470995],"type":"Point"}
}