{
  "type": "Feature",
  "properties": {
    "iso:country":"GB",
    "wof:name":"BN2 9QQ",
    "wof:placetype":"postalcode"
},
  "geometry": {"coordinates":[-0.13250596243599,50.82647966292673],"type":"Point"}
}