{
  "type": "Feature",
  "properties": {
    "date:inception_lower":"1980-01-01",
    "date:inception_upper":"1980-01-31",
    "iso:country":"GB",
    "wof:name":"EH42 1AU",
    "wof:placetype":"postalcode"
},
  "geometry": {"coordinates":[-2.528196,56.003207],"type":"Point"}
}