{
  "type": "Feature",
  "properties": {
    "iso:country":"GB",
    "wof:name":"EH42 1AU",
    "wof:placetype":"postalcode"
},
  "geometry": {"coordinates":[-2.52819559822767,56.00320706118337],"type":"Point"}
}