{
  "type": "Feature",
  "properties": {
    "iso:country":"GB",
    "wof:name":"FY1 5HP",
    "wof:placetype":"postalcode"
},
  "geometry": {"coordinates":[-3.04188631250146,53.80700300584154],"type":"Point"}
}