{
  "type": "Feature",
  "properties": {
    "iso:country": "GB",
    "wof:name": "FY1 5HP",
    "wof:placetype": "postalcode"
  },
  "geometry": {"coordinates":[-3.041886,53.807003],"type":"Point"}
}
