{
  "type": "Feature",
  "properties": {
    "iso:country": "GB",
    "wof:name": "HU17 7SD",
    "wof:placetype": "postalcode"
  },
  "geometry": {"coordinates":[-0.497377,53.864476],"type":"Point"}
}
