{
  "type": "Feature",
  "properties": {
    "iso:country":"GB",
    "wof:name":"HU17 7SD",
    "wof:placetype":"postalcode"
},
  "geometry": {"coordinates":[-0.4973766482657,53.86447622107666],"type":"Point"}
}