{
  "type": "Feature",
  "properties": {
    "date:inception_lower":"1997-06-01",
    "date:inception_upper":"1997-06-30",
    "iso:country":"GB",
    "wof:name":"DN33 3RB",
    "wof:placetype":"postalcode"
},
  "geometry": {"coordinates":[-0.101657,53.542607],"type":"Point"}
}