{
  "type": "Feature",
  "properties": {
    "iso:country":"GB",
    "wof:name":"DN33 3RB",
    "wof:placetype":"postalcode"
},
  "geometry": {"coordinates":[-0.10165732598061,53.54260654960933],"type":"Point"}
}