{
  "type": "Feature",
  "properties": {
    "iso:country":"GB",
    "wof:name":"LU3 2DN",
    "wof:placetype":"postalcode"
},
  "geometry": {"coordinates":[-0.42787678696479,51.91506561322103],"type":"Point"}
}