{
  "type": "Feature",
  "properties": {
    "iso:country": "GB",
    "wof:name": "BN23 6RR",
    "wof:placetype": "postalcode"
  },
  "geometry": {"coordinates":[0.32497,50.785898],"type":"Point"}
}
