{
  "type": "Feature",
  "properties": {
    "iso:country":"GB",
    "wof:name":"BN23 6RR",
    "wof:placetype":"postalcode"
},
  "geometry": {"coordinates":[0.32496948102872,50.78589811187688],"type":"Point"}
}