{
  "type": "Feature",
  "properties": {
    "date:inception_lower":"1999-06-01",
    "date:inception_upper":"1999-06-30",
    "iso:country":"GB",
    "wof:name":"BN23 6RR",
    "wof:placetype":"postalcode"
},
  "geometry": {"coordinates":[0.32497,50.785898],"type":"Point"}
}