{
  "type": "Feature",
  "properties": {
    "iso:country":"GB",
    "wof:name":"LE10 0RP",
    "wof:placetype":"postalcode"
},
  "geometry": {"coordinates":[-1.39968291965635,52.53181450807512],"type":"Point"}
}