{
  "type": "Feature",
  "properties": {
    "iso:country": "GB",
    "wof:name": "LE10 0RP",
    "wof:placetype": "postalcode"
  },
  "geometry": {"coordinates":[-1.399683,52.531815],"type":"Point"}
}
