{
  "type": "Feature",
  "properties": {
    "date:inception_lower": "1980-01-01",
    "date:inception_upper": "1980-01-01",
    "iso:country": "GB",
    "wof:name": "SP10 5EU",
    "wof:placetype": "postalcode"
  },
  "geometry": {"coordinates":[-1.465814,51.218244],"type":"Point"}
}
