{
  "type": "Feature",
  "properties": {
    "date:inception_lower": "1993-08-01",
    "date:inception_upper": "1993-08-01",
    "iso:country": "GB",
    "wof:name": "TW1 1AH",
    "wof:placetype": "postalcode"
  },
  "geometry": {"coordinates":[-0.338236,51.457587],"type":"Point"}
}
