{
  "type": "Feature",
  "properties": {
    "iso:country":"GB",
    "wof:name":"TW1 1AH",
    "wof:placetype":"postalcode"
},
  "geometry": {"coordinates":[-0.33823639344694,51.45758658730757],"type":"Point"}
}