{
  "type": "Feature",
  "properties": {
    "iso:country":"GB",
    "wof:name":"S72 7AF",
    "wof:placetype":"postalcode"
},
  "geometry": {"coordinates":[-1.3802917440956,53.58293235145741],"type":"Point"}
}