{
  "type": "Feature",
  "properties": {
    "date:inception_lower": "2003-08-01",
    "date:inception_upper": "2003-08-01",
    "iso:country": "GB",
    "wof:name": "W2 6DL",
    "wof:placetype": "postalcode"
  },
  "geometry": {"coordinates":[-0.179567,51.519464],"type":"Point"}
}
