{
  "type": "Feature",
  "properties": {
    "iso:country":"GB",
    "wof:name":"NG17 2GQ",
    "wof:placetype":"postalcode"
},
  "geometry": {"coordinates":[-1.27899649386802,53.12885168225655],"type":"Point"}
}