{
  "type": "Feature",
  "properties": {
    "date:inception_lower": "1993-01-01",
    "date:inception_upper": "1993-01-01",
    "iso:country": "GB",
    "wof:name": "YO8 9QR",
    "wof:placetype": "postalcode"
  },
  "geometry": {"coordinates":[-1.077686,53.778028],"type":"Point"}
}
