{
  "type": "Feature",
  "properties": {
    "iso:country":"GB",
    "wof:name":"YO8 9QR",
    "wof:placetype":"postalcode"
},
  "geometry": {"coordinates":[-1.07768598438824,53.77802838469686],"type":"Point"}
}