{
  "type": "Feature",
  "properties": {
    "iso:country":"GB",
    "wof:name":"PH1 4QF",
    "wof:placetype":"postalcode"
},
  "geometry": {"coordinates":[-3.43420784374128,56.48643725406708],"type":"Point"}
}