{
  "type": "Feature",
  "properties": {
    "iso:country":"GB",
    "wof:name":"LL57 4LS",
    "wof:placetype":"postalcode"
},
  "geometry": {"coordinates":[-4.1427140996784,53.21844509685806],"type":"Point"}
}