{
  "type": "Feature",
  "properties": {
    "date:inception_lower":"1980-01-01",
    "date:inception_upper":"1980-01-31",
    "iso:country":"GB",
    "wof:name":"LL57 4LS",
    "wof:placetype":"postalcode"
},
  "geometry": {"coordinates":[-4.142714,53.218445],"type":"Point"}
}