{
  "type": "Feature",
  "properties": {
    "iso:country": "GB",
    "wof:name": "WS15 3AB",
    "wof:placetype": "postalcode"
  },
  "geometry": {"coordinates":[-1.879575,52.800878],"type":"Point"}
}
