{
  "type": "Feature",
  "properties": {
    "iso:country":"GB",
    "wof:name":"WS15 3AB",
    "wof:placetype":"postalcode"
},
  "geometry": {"coordinates":[-1.87956459959922,52.80085213199128],"type":"Point"}
}