{
  "type": "Feature",
  "properties": {
    "date:inception_lower":"1980-01-01",
    "date:inception_upper":"1980-01-31",
    "iso:country":"GB",
    "wof:name":"WS15 3AB",
    "wof:placetype":"postalcode"
},
  "geometry": {"coordinates":[-1.879575,52.800878],"type":"Point"}
}