{
  "type": "Feature",
  "properties": {
    "date:inception_lower": "1980-01-01",
    "date:inception_upper": "1980-01-01",
    "iso:country": "GB",
    "wof:name": "LS15 7EP",
    "wof:placetype": "postalcode"
  },
  "geometry": {"coordinates":[-1.46071,53.802257],"type":"Point"}
}
