{
  "type": "Feature",
  "properties": {
    "iso:country": "GB",
    "wof:name": "CB2 9AY",
    "wof:placetype": "postalcode"
  },
  "geometry": {"coordinates":[0.105269,52.169044],"type":"Point"}
}
