{
  "type": "Feature",
  "properties": {
    "iso:country":"GB",
    "wof:name":"CB2 9AY",
    "wof:placetype":"postalcode"
},
  "geometry": {"coordinates":[0.10526922535647,52.16904443835973],"type":"Point"}
}