{
  "type": "Feature",
  "properties": {
    "date:inception_lower":"2012-12-01",
    "date:inception_upper":"2012-12-31",
    "iso:country":"GB",
    "wof:name":"CB2 9AY",
    "wof:placetype":"postalcode"
},
  "geometry": {"coordinates":[0.105269,52.169044],"type":"Point"}
}