{
  "type": "Feature",
  "properties": {
    "date:inception_lower":"2003-08-01",
    "date:inception_upper":"2003-08-31",
    "iso:country":"GB",
    "wof:name":"LS29 7QX",
    "wof:placetype":"postalcode"
},
  "geometry": {"coordinates":[-1.74886,53.914341],"type":"Point"}
}