{
  "type": "Feature",
  "properties": {
    "iso:country":"GB",
    "wof:name":"LS29 7QX",
    "wof:placetype":"postalcode"
},
  "geometry": {"coordinates":[-1.7488596359887,53.91434115289217],"type":"Point"}
}