{
  "type": "Feature",
  "properties": {
    "date:inception_lower":"1980-01-01",
    "date:inception_upper":"1980-01-31",
    "iso:country":"GB",
    "wof:name":"CF37 1BH",
    "wof:placetype":"postalcode"
},
  "geometry": {"coordinates":[-3.328444,51.596209],"type":"Point"}
}