{
  "type": "Feature",
  "properties": {
    "iso:country":"GB",
    "wof:name":"HR8 1QB",
    "wof:placetype":"postalcode"
},
  "geometry": {"coordinates":[-2.43741095304515,52.09475363762705],"type":"Point"}
}