{
  "type": "Feature",
  "properties": {
    "date:inception_lower": "2007-10-01",
    "date:inception_upper": "2007-10-01",
    "iso:country": "GB",
    "wof:name": "PO33 2DF",
    "wof:placetype": "postalcode"
  },
  "geometry": {"coordinates":[-1.167698,50.72377],"type":"Point"}
}
