{
  "type": "Feature",
  "properties": {
    "date:inception_lower": "2009-08-01",
    "date:inception_upper": "2009-08-01",
    "iso:country": "GB",
    "wof:name": "PE15 8RB",
    "wof:placetype": "postalcode"
  },
  "geometry": {"coordinates":[0.076555,52.554431],"type":"Point"}
}
