{
  "type": "Feature",
  "properties": {
    "iso:country":"GB",
    "wof:name":"PE15 8RB",
    "wof:placetype":"postalcode"
},
  "geometry": {"coordinates":[0.0765552984554,52.55443144451764],"type":"Point"}
}