{
  "type": "Feature",
  "properties": {
    "date:inception_lower": "1980-01-01",
    "date:inception_upper": "1980-01-01",
    "iso:country": "GB",
    "wof:name": "SY23 2BT",
    "wof:placetype": "postalcode"
  },
  "geometry": {"coordinates":[-4.084753,52.416149],"type":"Point"}
}
