{
  "type": "Feature",
  "properties": {
    "iso:country":"GB",
    "wof:name":"SY23 2BT",
    "wof:placetype":"postalcode"
},
  "geometry": {"coordinates":[-4.08448991134877,52.41609255927973],"type":"Point"}
}