{
  "type": "Feature",
  "properties": {
    "iso:country":"GB",
    "wof:name":"IP1 4NE",
    "wof:placetype":"postalcode"
},
  "geometry": {"coordinates":[1.14876210751,52.07054914712537],"type":"Point"}
}