{
  "type": "Feature",
  "properties": {
    "iso:country":"GB",
    "wof:name":"HR2 9AA",
    "wof:placetype":"postalcode"
},
  "geometry": {"coordinates":[-2.77141105551925,52.03059945875138],"type":"Point"}
}