{
  "type": "Feature",
  "properties": {
    "date:inception_lower": "1980-01-01",
    "date:inception_upper": "1980-01-01",
    "iso:country": "GB",
    "wof:name": "HR2 9AA",
    "wof:placetype": "postalcode"
  },
  "geometry": {"coordinates":[-2.771411,52.030599],"type":"Point"}
}
