{
  "type": "Feature",
  "properties": {
    "iso:country":"GB",
    "wof:name":"S73 0XW",
    "wof:placetype":"postalcode"
},
  "geometry": {"coordinates":[-1.37432477963728,53.51130797891712],"type":"Point"}
}