{
  "type": "Feature",
  "properties": {
    "iso:country": "GB",
    "wof:name": "S73 0XW",
    "wof:placetype": "postalcode"
  },
  "geometry": {"coordinates":[-1.374325,53.511308],"type":"Point"}
}
