{
  "type": "Feature",
  "properties": {
    "date:inception_lower": "2021-04-01",
    "date:inception_upper": "2021-04-01",
    "iso:country": "GB",
    "wof:name": "KA3 6GS",
    "wof:placetype": "postalcode"
  },
  "geometry": {"coordinates":[-4.485967,55.638789],"type":"Point"}
}
