{
  "type": "Feature",
  "properties": {
    "iso:country":"GB",
    "wof:name":"E16 1NZ",
    "wof:placetype":"postalcode"
},
  "geometry": {"coordinates":[0.02033886143462,51.51253955066488],"type":"Point"}
}