{
  "type": "Feature",
  "properties": {
    "iso:country":"GB",
    "wof:name":"CB9 8LR",
    "wof:placetype":"postalcode"
},
  "geometry": {"coordinates":[0.4279579881148,52.0770357954537],"type":"Point"}
}