{
  "type": "Feature",
  "properties": {
    "iso:country":"GB",
    "wof:name":"B33 9NL",
    "wof:placetype":"postalcode"
},
  "geometry": {"coordinates":[-1.78832141646801,52.49030061664209],"type":"Point"}
}