{
  "type": "Feature",
  "properties": {
    "iso:country":"GB",
    "wof:name":"RH6 9AR",
    "wof:placetype":"postalcode"
},
  "geometry": {"coordinates":[-0.12484614105677,51.17590575370964],"type":"Point"}
}