{
  "type": "Feature",
  "properties": {
    "iso:country":"GB",
    "wof:name":"CM13 1DF",
    "wof:placetype":"postalcode"
},
  "geometry": {"coordinates":[0.35222232293557,51.63677851466919],"type":"Point"}
}