{
  "type": "Feature",
  "properties": {
    "iso:country":"GB",
    "wof:name":"EN5 2ET",
    "wof:placetype":"postalcode"
},
  "geometry": {"coordinates":[-0.20003799940227,51.64721904101232],"type":"Point"}
}