{
  "type": "Feature",
  "properties": {
    "iso:country":"GB",
    "wof:name":"DN9 1EQ",
    "wof:placetype":"postalcode"
},
  "geometry": {"coordinates":[-0.85704925809564,53.52747396876341],"type":"Point"}
}