{
  "type": "Feature",
  "properties": {
    "iso:country": "GB",
    "wof:name": "DN9 1EQ",
    "wof:placetype": "postalcode"
  },
  "geometry": {"coordinates":[-0.857049,53.527474],"type":"Point"}
}
