{
  "type": "Feature",
  "properties": {
    "iso:country":"GB",
    "wof:name":"DA4 9DJ",
    "wof:placetype":"postalcode"
},
  "geometry": {"coordinates":[0.24571992414968,51.39114338132785],"type":"Point"}
}