{
  "type": "Feature",
  "properties": {
    "iso:country":"GB",
    "wof:name":"IV18 0DY",
    "wof:placetype":"postalcode"
},
  "geometry": {"coordinates":[-4.17156831773623,57.68760880229156],"type":"Point"}
}