{
  "type": "Feature",
  "properties": {
    "iso:country":"GB",
    "wof:name":"B26 3UT",
    "wof:placetype":"postalcode"
},
  "geometry": {"coordinates":[-1.77456763713857,52.45822594906527],"type":"Point"}
}