{
  "type": "Feature",
  "properties": {
    "iso:country":"GB",
    "wof:name":"CF23 5HH",
    "wof:placetype":"postalcode"
},
  "geometry": {"coordinates":[-3.17636097330617,51.50219270829336],"type":"Point"}
}