{
  "type": "Feature",
  "properties": {
    "iso:country": "GB",
    "wof:name": "SS8 0BG",
    "wof:placetype": "postalcode"
  },
  "geometry": {"coordinates":[0.592676,51.513935],"type":"Point"}
}
