{
  "type": "Feature",
  "properties": {
    "date:inception_lower":"1995-07-01",
    "date:inception_upper":"1995-07-31",
    "iso:country":"GB",
    "wof:name":"RG18 9PL",
    "wof:placetype":"postalcode"
},
  "geometry": {"coordinates":[-1.265605,51.423002],"type":"Point"}
}