{
  "type": "Feature",
  "properties": {
    "iso:country": "GB",
    "wof:name": "E13 0LW",
    "wof:placetype": "postalcode"
  },
  "geometry": {"coordinates":[0.021219,51.53274],"type":"Point"}
}
