{
  "type": "Feature",
  "properties": {
    "iso:country":"GB",
    "wof:name":"E13 0LW",
    "wof:placetype":"postalcode"
},
  "geometry": {"coordinates":[0.02121876393724,51.53273995036545],"type":"Point"}
}