{
  "type": "Feature",
  "properties": {
    "date:inception_lower":"1985-04-01",
    "date:inception_upper":"1985-04-30",
    "iso:country":"GB",
    "wof:name":"TS20 1ST",
    "wof:placetype":"postalcode"
},
  "geometry": {"coordinates":[-1.334041,54.5915],"type":"Point"}
}