{
  "type": "Feature",
  "properties": {
    "iso:country":"GB",
    "wof:name":"TS20 1ST",
    "wof:placetype":"postalcode"
},
  "geometry": {"coordinates":[-1.33404071920971,54.59150035336501],"type":"Point"}
}