{
  "type": "Feature",
  "properties": {
    "iso:country": "GB",
    "wof:name": "TS20 1ST",
    "wof:placetype": "postalcode"
  },
  "geometry": {"coordinates":[-1.334041,54.5915],"type":"Point"}
}
