{
  "type": "Feature",
  "properties": {
    "iso:country":"GB",
    "wof:name":"NG3 7GX",
    "wof:placetype":"postalcode"
},
  "geometry": {"coordinates":[-1.10725917573256,52.95917298713627],"type":"Point"}
}