{
  "type": "Feature",
  "properties": {
    "date:inception_lower": "1980-01-01",
    "date:inception_upper": "1980-01-01",
    "iso:country": "GB",
    "wof:name": "NG3 7GX",
    "wof:placetype": "postalcode"
  },
  "geometry": {"coordinates":[-1.107259,52.959173],"type":"Point"}
}
