{
  "type": "Feature",
  "properties": {
    "iso:country": "GB",
    "wof:name": "NG3 7GX",
    "wof:placetype": "postalcode"
  },
  "geometry": {"coordinates":[-1.107259,52.959173],"type":"Point"}
}
