{
  "type": "Feature",
  "properties": {
    "iso:country":"GB",
    "wof:name":"LE9 8DJ",
    "wof:placetype":"postalcode"
},
  "geometry": {"coordinates":[-1.35610563039888,52.56313149709489],"type":"Point"}
}