{
  "type": "Feature",
  "properties": {
    "iso:country": "GB",
    "wof:name": "BR8 7AW",
    "wof:placetype": "postalcode"
  },
  "geometry": {"coordinates":[0.167412,51.40002],"type":"Point"}
}
