{
  "type": "Feature",
  "properties": {
    "iso:country": "GB",
    "wof:name": "DL10 4TE",
    "wof:placetype": "postalcode"
  },
  "geometry": {"coordinates":[-1.745627,54.41108],"type":"Point"}
}
