{
  "type": "Feature",
  "properties": {
    "iso:country":"GB",
    "wof:name":"CW11 2UU",
    "wof:placetype":"postalcode"
},
  "geometry": {"coordinates":[-2.28247321519842,53.13942559519438],"type":"Point"}
}