{
  "type": "Feature",
  "properties": {
    "iso:country": "GB",
    "wof:name": "CW11 2UU",
    "wof:placetype": "postalcode"
  },
  "geometry": {"coordinates":[-2.282473,53.139443],"type":"Point"}
}
