{
  "type": "Feature",
  "properties": {
    "iso:country":"GB",
    "wof:name":"ME1 3NQ",
    "wof:placetype":"postalcode"
},
  "geometry": {"coordinates":[0.49098960194815,51.37226253430612],"type":"Point"}
}