{
  "type": "Feature",
  "properties": {
    "iso:country":"GB",
    "wof:name":"FY4 2PA",
    "wof:placetype":"postalcode"
},
  "geometry": {"coordinates":[-3.04376518705488,53.78360781313772],"type":"Point"}
}