{
  "type": "Feature",
  "properties": {
    "iso:country":"GB",
    "wof:name":"PH11 8DX",
    "wof:placetype":"postalcode"
},
  "geometry": {"coordinates":[-3.23429351649958,56.62322998751527],"type":"Point"}
}