{
  "type": "Feature",
  "properties": {
    "iso:country": "GB",
    "wof:name": "PH11 8DX",
    "wof:placetype": "postalcode"
  },
  "geometry": {"coordinates":[-3.234293,56.62323],"type":"Point"}
}
