{
  "type": "Feature",
  "properties": {
    "iso:country": "GB",
    "wof:name": "WN7 4SF",
    "wof:placetype": "postalcode"
  },
  "geometry": {"coordinates":[-2.533738,53.498349],"type":"Point"}
}
