{
  "type": "Feature",
  "properties": {
    "iso:country": "GB",
    "wof:name": "DE4 2PE",
    "wof:placetype": "postalcode"
  },
  "geometry": {"coordinates":[-1.640853,53.131571],"type":"Point"}
}
