{
  "type": "Feature",
  "properties": {
    "date:inception_lower": "1980-01-01",
    "date:inception_upper": "1980-01-01",
    "iso:country": "GB",
    "wof:name": "DE4 2PE",
    "wof:placetype": "postalcode"
  },
  "geometry": {"coordinates":[-1.644484,53.129784],"type":"Point"}
}
