{
  "type": "Feature",
  "properties": {
    "date:inception_lower":"2002-06-01",
    "date:inception_upper":"2002-06-30",
    "iso:country":"GB",
    "wof:name":"TD13 5XS",
    "wof:placetype":"postalcode"
},
  "geometry": {"coordinates":[-2.362168,55.932737],"type":"Point"}
}