{
  "type": "Feature",
  "properties": {
    "iso:country": "GB",
    "wof:name": "TD13 5XS",
    "wof:placetype": "postalcode"
  },
  "geometry": {"coordinates":[-2.362168,55.932737],"type":"Point"}
}
