{
  "type": "Feature",
  "properties": {
    "iso:country":"GB",
    "wof:name":"LL11 6DY",
    "wof:placetype":"postalcode"
},
  "geometry": {"coordinates":[-3.0390484513701,53.0754731173726],"type":"Point"}
}