{
  "type": "Feature",
  "properties": {
    "iso:country":"GB",
    "wof:name":"SO53 3TF",
    "wof:placetype":"postalcode"
},
  "geometry": {"coordinates":[-1.38665667881275,50.96709012236028],"type":"Point"}
}