{
  "type": "Feature",
  "properties": {
    "iso:country":"GB",
    "wof:name":"DN14 5JY",
    "wof:placetype":"postalcode"
},
  "geometry": {"coordinates":[-0.85456308418731,53.70777365544959],"type":"Point"}
}