{
  "type": "Feature",
  "properties": {
    "date:inception_lower": "1994-05-01",
    "date:inception_upper": "1994-05-01",
    "iso:country": "GB",
    "wof:name": "M40 3PN",
    "wof:placetype": "postalcode"
  },
  "geometry": {"coordinates":[-2.165108,53.51522],"type":"Point"}
}
