{
  "type": "Feature",
  "properties": {
    "iso:country":"GB",
    "wof:name":"SO31 1ZT",
    "wof:placetype":"postalcode"
},
  "geometry": {"coordinates":[-1.26501046498749,50.87497942545405],"type":"Point"}
}