{
  "type": "Feature",
  "properties": {
    "date:inception_lower":"1980-01-01",
    "date:inception_upper":"1980-01-31",
    "iso:country":"GB",
    "wof:name":"BN20 7XN",
    "wof:placetype":"postalcode"
},
  "geometry": {"coordinates":[0.267218,50.751711],"type":"Point"}
}