{
  "type": "Feature",
  "properties": {
    "iso:country": "GB",
    "wof:name": "TR16 6PL",
    "wof:placetype": "postalcode"
  },
  "geometry": {"coordinates":[-5.227883,50.173526],"type":"Point"}
}
