{
  "type": "Feature",
  "properties": {
    "date:inception_lower": "1980-01-01",
    "date:inception_upper": "1980-01-01",
    "iso:country": "GB",
    "wof:name": "WV3 7JD",
    "wof:placetype": "postalcode"
  },
  "geometry": {"coordinates":[-2.156275,52.575095],"type":"Point"}
}
