{
  "type": "Feature",
  "properties": {
    "iso:country": "GB",
    "wof:name": "TR13 9NR",
    "wof:placetype": "postalcode"
  },
  "geometry": {"coordinates":[-5.335744,50.12759],"type":"Point"}
}
