{
  "type": "Feature",
  "properties": {
    "date:inception_lower": "1980-01-01",
    "date:inception_upper": "1980-01-01",
    "iso:country": "GB",
    "wof:name": "TR13 9NR",
    "wof:placetype": "postalcode"
  },
  "geometry": {"coordinates":[-5.335744,50.12759],"type":"Point"}
}
