{
  "type": "Feature",
  "properties": {
    "iso:country":"GB",
    "wof:name":"RG6 6HS",
    "wof:placetype":"postalcode"
},
  "geometry": {"coordinates":[-0.94939833721443,51.44482778758295],"type":"Point"}
}