{
  "type": "Feature",
  "properties": {
    "date:inception_lower": "1980-01-01",
    "date:inception_upper": "1980-01-01",
    "iso:country": "GB",
    "wof:name": "TA6 4SG",
    "wof:placetype": "postalcode"
  },
  "geometry": {"coordinates":[-3.003822,51.180052],"type":"Point"}
}
