{
  "type": "Feature",
  "properties": {
    "iso:country":"GB",
    "wof:name":"TA6 4SG",
    "wof:placetype":"postalcode"
},
  "geometry": {"coordinates":[-3.00401505278025,51.18011864745348],"type":"Point"}
}