{
  "type": "Feature",
  "properties": {
    "date:inception_lower":"1993-08-01",
    "date:inception_upper":"1993-08-31",
    "iso:country":"GB",
    "wof:name":"NE16 5ED",
    "wof:placetype":"postalcode"
},
  "geometry": {"coordinates":[-1.682047,54.916044],"type":"Point"}
}