{
  "type": "Feature",
  "properties": {
    "iso:country":"GB",
    "wof:name":"NE16 5ED",
    "wof:placetype":"postalcode"
},
  "geometry": {"coordinates":[-1.6820474928098,54.91604384843274],"type":"Point"}
}