{
  "type": "Feature",
  "properties": {
    "iso:country": "GB",
    "wof:name": "NE16 5ED",
    "wof:placetype": "postalcode"
  },
  "geometry": {"coordinates":[-1.682047,54.916044],"type":"Point"}
}
