{
  "type": "Feature",
  "properties": {
    "iso:country":"GB",
    "wof:name":"SK9 3BP",
    "wof:placetype":"postalcode"
},
  "geometry": {"coordinates":[-2.21202305268601,53.34286306196714],"type":"Point"}
}