{
  "type": "Feature",
  "properties": {
    "date:inception_lower": "1980-01-01",
    "date:inception_upper": "1980-01-01",
    "iso:country": "GB",
    "wof:name": "SK9 3BP",
    "wof:placetype": "postalcode"
  },
  "geometry": {"coordinates":[-2.212023,53.342863],"type":"Point"}
}
