{
  "type": "Feature",
  "properties": {
    "date:inception_lower": "1980-01-01",
    "date:inception_upper": "1980-01-01",
    "iso:country": "GB",
    "wof:name": "OL1 3EJ",
    "wof:placetype": "postalcode"
  },
  "geometry": {"coordinates":[-2.113202,53.549464],"type":"Point"}
}
