{
  "type": "Feature",
  "properties": {
    "iso:country":"GB",
    "wof:name":"OL1 3EJ",
    "wof:placetype":"postalcode"
},
  "geometry": {"coordinates":[-2.11320218704955,53.54946359096984],"type":"Point"}
}