{
  "type": "Feature",
  "properties": {
    "iso:country":"GB",
    "wof:name":"G53 7DH",
    "wof:placetype":"postalcode"
},
  "geometry": {"coordinates":[-4.362476059906,55.82397387496504],"type":"Point"}
}