{
  "type": "Feature",
  "properties": {
    "date:inception_lower":"2004-07-01",
    "date:inception_upper":"2004-07-31",
    "iso:country":"GB",
    "wof:name":"N15 5HR",
    "wof:placetype":"postalcode"
},
  "geometry": {"coordinates":[-0.080891,51.581441],"type":"Point"}
}