{
  "type": "Feature",
  "properties": {
    "iso:country": "GB",
    "wof:name": "MK17 0QS",
    "wof:placetype": "postalcode"
  },
  "geometry": {"coordinates":[-0.876541,51.973206],"type":"Point"}
}
