{
  "type": "Feature",
  "properties": {
    "iso:country":"GB",
    "wof:name":"MK17 0QS",
    "wof:placetype":"postalcode"
},
  "geometry": {"coordinates":[-0.87654124349816,51.97320569349281],"type":"Point"}
}