{
  "type": "Feature",
  "properties": {
    "iso:country":"GB",
    "wof:name":"TN21 8QB",
    "wof:placetype":"postalcode"
},
  "geometry": {"coordinates":[0.25866384848021,50.98330286538733],"type":"Point"}
}