{
  "type": "Feature",
  "properties": {
    "date:inception_lower": "1980-01-01",
    "date:inception_upper": "1980-01-01",
    "iso:country": "GB",
    "wof:name": "TN21 8QB",
    "wof:placetype": "postalcode"
  },
  "geometry": {"coordinates":[0.258694,50.983326],"type":"Point"}
}
