{
  "type": "Feature",
  "properties": {
    "iso:country":"GB",
    "wof:name":"AL6 0GD",
    "wof:placetype":"postalcode"
},
  "geometry": {"coordinates":[-0.19460048590403,51.84203985181884],"type":"Point"}
}