{
  "type": "Feature",
  "properties": {
    "iso:country": "GB",
    "wof:name": "AL6 0GD",
    "wof:placetype": "postalcode"
  },
  "geometry": {"coordinates":[-0.1946,51.84204],"type":"Point"}
}
