{
  "type": "Feature",
  "properties": {
    "iso:country":"GB",
    "wof:name":"M17 1NW",
    "wof:placetype":"postalcode"
},
  "geometry": {"coordinates":[-2.31047929081216,53.46702240145475],"type":"Point"}
}