{
  "type": "Feature",
  "properties": {
    "iso:country":"GB",
    "wof:name":"ML5 3NG",
    "wof:placetype":"postalcode"
},
  "geometry": {"coordinates":[-4.02181284903221,55.86373062552425],"type":"Point"}
}