{
  "type": "Feature",
  "properties": {
    "date:inception_lower":"2007-07-01",
    "date:inception_upper":"2007-07-31",
    "iso:country":"GB",
    "wof:name":"W12 0EA",
    "wof:placetype":"postalcode"
},
  "geometry": {"coordinates":[-0.229931,51.516422],"type":"Point"}
}