{
  "type": "Feature",
  "properties": {
    "iso:country":"GB",
    "wof:name":"W12 0EA",
    "wof:placetype":"postalcode"
},
  "geometry": {"coordinates":[-0.22993151234786,51.51642170599222],"type":"Point"}
}