{
  "type": "Feature",
  "properties": {
    "date:inception_lower":"2016-10-01",
    "date:inception_upper":"2016-10-31",
    "iso:country":"GB",
    "wof:name":"SL4 6PE",
    "wof:placetype":"postalcode"
},
  "geometry": {"coordinates":[-0.619761,51.49443],"type":"Point"}
}