{
  "type": "Feature",
  "properties": {
    "date:inception_lower": "2024-07-01",
    "date:inception_upper": "2024-07-01",
    "iso:country": "GB",
    "wof:name": "NR4 7XT",
    "wof:placetype": "postalcode"
  },
  "geometry": {"coordinates":[1.225734,52.611166],"type":"Point"}
}
