{
  "type": "Feature",
  "properties": {
    "iso:country":"GB",
    "wof:name":"G73 2AX",
    "wof:placetype":"postalcode"
},
  "geometry": {"coordinates":[-4.2151586279825,55.82000275148332],"type":"Point"}
}