{
  "type": "Feature",
  "properties": {
    "iso:country": "GB",
    "wof:name": "ST6 4JA",
    "wof:placetype": "postalcode"
  },
  "geometry": {"coordinates":[-2.205267,53.049244],"type":"Point"}
}
