{
  "type": "Feature",
  "properties": {
    "iso:country":"GB",
    "wof:name":"ST6 4JA",
    "wof:placetype":"postalcode"
},
  "geometry": {"coordinates":[-2.20526690581027,53.04924404907797],"type":"Point"}
}