{
  "type": "Feature",
  "properties": {
    "iso:country": "GB",
    "wof:name": "NN1 4NA",
    "wof:placetype": "postalcode"
  },
  "geometry": {"coordinates":[-0.873934,52.243431],"type":"Point"}
}
