{
  "type": "Feature",
  "properties": {
    "date:inception_lower":"1980-01-01",
    "date:inception_upper":"1980-01-31",
    "iso:country":"GB",
    "wof:name":"IP28 6PL",
    "wof:placetype":"postalcode"
},
  "geometry": {"coordinates":[0.604005,52.322428],"type":"Point"}
}