{
  "type": "Feature",
  "properties": {
    "date:inception_lower": "1982-03-01",
    "date:inception_upper": "1982-03-01",
    "iso:country": "GB",
    "wof:name": "ME15 8TQ",
    "wof:placetype": "postalcode"
  },
  "geometry": {"coordinates":[0.558873,51.260428],"type":"Point"}
}
