{
  "type": "Feature",
  "properties": {
    "iso:country": "GB",
    "wof:name": "ME15 8TQ",
    "wof:placetype": "postalcode"
  },
  "geometry": {"coordinates":[0.558873,51.260428],"type":"Point"}
}
