{
  "type": "Feature",
  "properties": {
    "iso:country": "GB",
    "wof:name": "M21 0YB",
    "wof:placetype": "postalcode"
  },
  "geometry": {"coordinates":[-2.257698,53.44234],"type":"Point"}
}
