{
  "type": "Feature",
  "properties": {
    "iso:country":"GB",
    "wof:name":"AB21 9QU",
    "wof:placetype":"postalcode"
},
  "geometry": {"coordinates":[-2.19110747345784,57.17879113865149],"type":"Point"}
}