{
  "type": "Feature",
  "properties": {
    "iso:country": "GB",
    "wof:name": "SL2 5QU",
    "wof:placetype": "postalcode"
  },
  "geometry": {"coordinates":[-0.581192,51.519766],"type":"Point"}
}
