{
  "type": "Feature",
  "properties": {
    "iso:country":"GB",
    "wof:name":"SL2 5QU",
    "wof:placetype":"postalcode"
},
  "geometry": {"coordinates":[-0.581192180446,51.51976630236474],"type":"Point"}
}