{
  "type": "Feature",
  "properties": {
    "date:inception_lower": "2011-05-01",
    "date:inception_upper": "2011-05-01",
    "iso:country": "GB",
    "wof:name": "CF10 5BX",
    "wof:placetype": "postalcode"
  },
  "geometry": {"coordinates":[-3.16528,51.464493],"type":"Point"}
}
