{
  "type": "Feature",
  "properties": {
    "date:inception_lower":"2011-05-01",
    "date:inception_upper":"2011-05-31",
    "iso:country":"GB",
    "wof:name":"CF10 5BX",
    "wof:placetype":"postalcode"
},
  "geometry": {"coordinates":[-3.165386,51.464491],"type":"Point"}
}