{
  "type": "Feature",
  "properties": {
    "iso:country":"GB",
    "wof:name":"CF10 5BX",
    "wof:placetype":"postalcode"
},
  "geometry": {"coordinates":[-3.16538604293432,51.46449133483644],"type":"Point"}
}