{
  "type": "Feature",
  "properties": {
    "iso:country":"GB",
    "wof:name":"RG17 0GY",
    "wof:placetype":"postalcode"
},
  "geometry": {"coordinates":[-1.51789603893307,51.40933893807325],"type":"Point"}
}