{
  "type": "Feature",
  "properties": {
    "iso:country":"GB",
    "wof:name":"KT3 6RS",
    "wof:placetype":"postalcode"
},
  "geometry": {"coordinates":[-0.24760627079623,51.38963246417612],"type":"Point"}
}