{
  "type": "Feature",
  "properties": {
    "iso:country":"GB",
    "wof:name":"IV1 1RN",
    "wof:placetype":"postalcode"
},
  "geometry": {"coordinates":[-4.22979503480998,57.48006035693403],"type":"Point"}
}