{
  "type": "Feature",
  "properties": {
    "date:inception_lower": "1980-01-01",
    "date:inception_upper": "1980-01-01",
    "iso:country": "GB",
    "wof:name": "KT10 9DQ",
    "wof:placetype": "postalcode"
  },
  "geometry": {"coordinates":[-0.350232,51.363947],"type":"Point"}
}
