{
  "type": "Feature",
  "properties": {
    "iso:country":"GB",
    "wof:name":"BN9 0EW",
    "wof:placetype":"postalcode"
},
  "geometry": {"coordinates":[0.05771124109397,50.79094721160067],"type":"Point"}
}