{
  "type": "Feature",
  "properties": {
    "iso:country":"GB",
    "wof:name":"CF38 2RY",
    "wof:placetype":"postalcode"
},
  "geometry": {"coordinates":[-3.34821029501035,51.55179487339856],"type":"Point"}
}