{
  "type": "Feature",
  "properties": {
    "iso:country": "GB",
    "wof:name": "CF38 2RY",
    "wof:placetype": "postalcode"
  },
  "geometry": {"coordinates":[-3.34821,51.551795],"type":"Point"}
}
