{
  "type": "Feature",
  "properties": {
    "date:inception_lower": "2012-10-01",
    "date:inception_upper": "2012-10-01",
    "iso:country": "GB",
    "wof:name": "PE28 0DA",
    "wof:placetype": "postalcode"
  },
  "geometry": {"coordinates":[-0.293926,52.336393],"type":"Point"}
}
