{
  "type": "Feature",
  "properties": {
    "iso:country": "GB",
    "wof:name": "PE28 0DA",
    "wof:placetype": "postalcode"
  },
  "geometry": {"coordinates":[-0.293926,52.336393],"type":"Point"}
}
