{
  "type": "Feature",
  "properties": {
    "iso:country":"GB",
    "wof:name":"BS1 3ED",
    "wof:placetype":"postalcode"
},
  "geometry": {"coordinates":[-2.58971489006562,51.45774120814693],"type":"Point"}
}