{
  "type": "Feature",
  "properties": {
    "iso:country":"GB",
    "wof:name":"BL6 5DH",
    "wof:placetype":"postalcode"
},
  "geometry": {"coordinates":[-2.58659214677425,53.59343331529657],"type":"Point"}
}