{
  "type": "Feature",
  "properties": {
    "iso:country":"GB",
    "wof:name":"OX3 7LL",
    "wof:placetype":"postalcode"
},
  "geometry": {"coordinates":[-1.21128677587503,51.75301524288098],"type":"Point"}
}