{
  "type": "Feature",
  "properties": {
    "iso:country":"GB",
    "wof:name":"B74 3UD",
    "wof:placetype":"postalcode"
},
  "geometry": {"coordinates":[-1.85940882082551,52.60206037885955],"type":"Point"}
}