{
  "type": "Feature",
  "properties": {
    "iso:country":"GB",
    "wof:name":"W12 9RL",
    "wof:placetype":"postalcode"
},
  "geometry": {"coordinates":[-0.24526441675595,51.49998018145388],"type":"Point"}
}