{
  "type": "Feature",
  "properties": {
    "date:inception_lower": "1997-06-01",
    "date:inception_upper": "1997-06-01",
    "iso:country": "GB",
    "wof:name": "KY1 3NE",
    "wof:placetype": "postalcode"
  },
  "geometry": {"coordinates":[-3.148742,56.134047],"type":"Point"}
}
