{
  "type": "Feature",
  "properties": {
    "date:inception_lower": "1987-04-01",
    "date:inception_upper": "1987-04-01",
    "iso:country": "GB",
    "wof:name": "PE10 9DQ",
    "wof:placetype": "postalcode"
  },
  "geometry": {"coordinates":[-0.37796,52.775482],"type":"Point"}
}
