{
  "type": "Feature",
  "properties": {
    "iso:country":"GB",
    "wof:name":"CF46 6DL",
    "wof:placetype":"postalcode"
},
  "geometry": {"coordinates":[-3.29031619569875,51.66031183093622],"type":"Point"}
}