{
  "type": "Feature",
  "properties": {
    "iso:country":"GB",
    "wof:name":"NE26 2BQ",
    "wof:placetype":"postalcode"
},
  "geometry": {"coordinates":[-1.43621852379258,55.04149156817778],"type":"Point"}
}