{
  "type": "Feature",
  "properties": {
    "date:inception_lower": "1981-09-01",
    "date:inception_upper": "1981-09-01",
    "iso:country": "GB",
    "wof:name": "WN2 3SQ",
    "wof:placetype": "postalcode"
  },
  "geometry": {"coordinates":[-2.573312,53.522058],"type":"Point"}
}
