{
  "type": "Feature",
  "properties": {
    "date:inception_lower": "2007-05-01",
    "date:inception_upper": "2007-05-01",
    "iso:country": "GB",
    "wof:name": "RH12 2RD",
    "wof:placetype": "postalcode"
  },
  "geometry": {"coordinates":[-0.332447,51.076725],"type":"Point"}
}
