{
  "type": "Feature",
  "properties": {
    "iso:country":"GB",
    "wof:name":"BR4 0EF",
    "wof:placetype":"postalcode"
},
  "geometry": {"coordinates":[-0.00033732594275,51.38584419798964],"type":"Point"}
}