{
  "type": "Feature",
  "properties": {
    "iso:country":"GB",
    "wof:name":"RG42 6EX",
    "wof:placetype":"postalcode"
},
  "geometry": {"coordinates":[-0.75036948759191,51.4525240636678],"type":"Point"}
}