{
  "type": "Feature",
  "properties": {
    "date:inception_lower":"2007-07-01",
    "date:inception_upper":"2007-07-31",
    "iso:country":"GB",
    "wof:name":"PO6 3SY",
    "wof:placetype":"postalcode"
},
  "geometry": {"coordinates":[-1.084437,50.850934],"type":"Point"}
}