{
  "type": "Feature",
  "properties": {
    "iso:country":"GB",
    "wof:name":"NE66 3AS",
    "wof:placetype":"postalcode"
},
  "geometry": {"coordinates":[-1.62674770927707,55.40361893034144],"type":"Point"}
}