{
  "type": "Feature",
  "properties": {
    "iso:country": "GB",
    "wof:name": "NE66 3AS",
    "wof:placetype": "postalcode"
  },
  "geometry": {"coordinates":[-1.626748,55.403619],"type":"Point"}
}
