{
  "type": "Feature",
  "properties": {
    "iso:country": "GB",
    "wof:name": "EX20 3HP",
    "wof:placetype": "postalcode"
  },
  "geometry": {"coordinates":[-4.105739,50.859773],"type":"Point"}
}
