{
  "type": "Feature",
  "properties": {
    "date:inception_lower": "1980-01-01",
    "date:inception_upper": "1980-01-01",
    "iso:country": "GB",
    "wof:name": "EX20 3HP",
    "wof:placetype": "postalcode"
  },
  "geometry": {"coordinates":[-4.105739,50.859773],"type":"Point"}
}
