{
  "type": "Feature",
  "properties": {
    "iso:country":"GB",
    "wof:name":"EX20 3HP",
    "wof:placetype":"postalcode"
},
  "geometry": {"coordinates":[-4.10573887530844,50.85977273105679],"type":"Point"}
}