{
  "type": "Feature",
  "properties": {
    "iso:country":"GB",
    "wof:name":"SL6 3TA",
    "wof:placetype":"postalcode"
},
  "geometry": {"coordinates":[-0.74109397491032,51.47318738723426],"type":"Point"}
}