{
  "type": "Feature",
  "properties": {
    "iso:country":"GB",
    "wof:name":"TF13 6DD",
    "wof:placetype":"postalcode"
},
  "geometry": {"coordinates":[-2.57950179679046,52.58988283294141],"type":"Point"}
}