{
  "type": "Feature",
  "properties": {
    "iso:country":"GB",
    "wof:name":"BN3 2LL",
    "wof:placetype":"postalcode"
},
  "geometry": {"coordinates":[-0.16674286008006,50.82606037533013],"type":"Point"}
}