{
  "type": "Feature",
  "properties": {
    "date:inception_lower": "2005-07-01",
    "date:inception_upper": "2005-07-01",
    "iso:country": "GB",
    "wof:name": "IP12 2GN",
    "wof:placetype": "postalcode"
  },
  "geometry": {"coordinates":[1.417333,52.128523],"type":"Point"}
}
