{
  "type": "Feature",
  "properties": {
    "iso:country":"GB",
    "wof:name":"BL7 9ER",
    "wof:placetype":"postalcode"
},
  "geometry": {"coordinates":[-2.43637563054094,53.62201143108414],"type":"Point"}
}