{
  "type": "Feature",
  "properties": {
    "iso:country": "GB",
    "wof:name": "BL7 9ER",
    "wof:placetype": "postalcode"
  },
  "geometry": {"coordinates":[-2.43657,53.621991],"type":"Point"}
}
