{
  "type": "Feature",
  "properties": {
    "iso:country": "GB",
    "wof:name": "BL7 9ER",
    "wof:placetype": "postalcode"
  },
  "geometry": {"coordinates":[-2.436374,53.622027],"type":"Point"}
}
