{
  "type": "Feature",
  "properties": {
    "iso:country": "GB",
    "wof:name": "LE67 6DF",
    "wof:placetype": "postalcode"
  },
  "geometry": {"coordinates":[-1.400912,52.69701],"type":"Point"}
}
