{
  "type": "Feature",
  "properties": {
    "iso:country":"GB",
    "wof:name":"S26 3YB",
    "wof:placetype":"postalcode"
},
  "geometry": {"coordinates":[-1.31078865309976,53.38236674338266],"type":"Point"}
}