{
  "type": "Feature",
  "properties": {
    "date:inception_lower": "1997-06-01",
    "date:inception_upper": "1997-06-01",
    "iso:country": "GB",
    "wof:name": "S26 3YB",
    "wof:placetype": "postalcode"
  },
  "geometry": {"coordinates":[-1.3107,53.382286],"type":"Point"}
}
