{
  "type": "Feature",
  "properties": {
    "date:inception_lower":"2010-04-01",
    "date:inception_upper":"2010-04-30",
    "iso:country":"GB",
    "wof:name":"IP24 2DY",
    "wof:placetype":"postalcode"
},
  "geometry": {"coordinates":[0.754334,52.416912],"type":"Point"}
}