{
  "type": "Feature",
  "properties": {
    "iso:country":"GB",
    "wof:name":"IP24 2DY",
    "wof:placetype":"postalcode"
},
  "geometry": {"coordinates":[0.75433356501527,52.41691180514009],"type":"Point"}
}