{
  "type": "Feature",
  "properties": {
    "date:inception_lower": "2022-03-01",
    "date:inception_upper": "2022-03-01",
    "iso:country": "GB",
    "wof:name": "BR1 3FR",
    "wof:placetype": "postalcode"
  },
  "geometry": {"coordinates":[0.026907,51.410835],"type":"Point"}
}
