{
  "type": "Feature",
  "properties": {
    "date:inception_lower": "2016-07-01",
    "date:inception_upper": "2016-07-01",
    "iso:country": "GB",
    "wof:name": "SW8 2ET",
    "wof:placetype": "postalcode"
  },
  "geometry": {"coordinates":[-0.12823,51.480644],"type":"Point"}
}
