{
  "type": "Feature",
  "properties": {
    "iso:country":"GB",
    "wof:name":"HP15 6LJ",
    "wof:placetype":"postalcode"
},
  "geometry": {"coordinates":[-0.73252771551454,51.6656736700851],"type":"Point"}
}