{
  "type": "Feature",
  "properties": {
    "iso:country": "GB",
    "wof:name": "HP15 6LJ",
    "wof:placetype": "postalcode"
  },
  "geometry": {"coordinates":[-0.733159,51.66564],"type":"Point"}
}
