{
  "type": "Feature",
  "properties": {
    "date:inception_lower": "1980-01-01",
    "date:inception_upper": "1980-01-01",
    "iso:country": "GB",
    "wof:name": "HP15 6LJ",
    "wof:placetype": "postalcode"
  },
  "geometry": {"coordinates":[-0.733159,51.66564],"type":"Point"}
}
