{
  "type": "Feature",
  "properties": {
    "date:inception_lower": "2005-09-01",
    "date:inception_upper": "2005-09-01",
    "iso:country": "GB",
    "wof:name": "CM1 3WR",
    "wof:placetype": "postalcode"
  },
  "geometry": {"coordinates":[0.405373,51.711477],"type":"Point"}
}
