{
  "type": "Feature",
  "properties": {
    "iso:country":"GB",
    "wof:name":"CM1 3WR",
    "wof:placetype":"postalcode"
},
  "geometry": {"coordinates":[0.40537340290303,51.71147653482556],"type":"Point"}
}