{
  "type": "Feature",
  "properties": {
    "date:inception_lower": "1990-07-01",
    "date:inception_upper": "1990-07-01",
    "iso:country": "GB",
    "wof:name": "DA11 7ET",
    "wof:placetype": "postalcode"
  },
  "geometry": {"coordinates":[0.351614,51.430587],"type":"Point"}
}
