{
  "type": "Feature",
  "properties": {
    "iso:country":"GB",
    "wof:name":"DA11 7ET",
    "wof:placetype":"postalcode"
},
  "geometry": {"coordinates":[0.35161349602054,51.43058748521814],"type":"Point"}
}