{
  "type": "Feature",
  "properties": {
    "iso:country":"GB",
    "wof:name":"M6 5NR",
    "wof:placetype":"postalcode"
},
  "geometry": {"coordinates":[-2.29737048454036,53.48804385851842],"type":"Point"}
}