{
  "type": "Feature",
  "properties": {
    "iso:country":"GB",
    "wof:name":"WF2 9DX",
    "wof:placetype":"postalcode"
},
  "geometry": {"coordinates":[-1.54364790107832,53.6799041968676],"type":"Point"}
}