{
  "type": "Feature",
  "properties": {
    "iso:country":"GB",
    "wof:name":"BS15 3QH",
    "wof:placetype":"postalcode"
},
  "geometry": {"coordinates":[-2.51270955092458,51.44978613359524],"type":"Point"}
}