{
  "type": "Feature",
  "properties": {
    "iso:country":"GB",
    "wof:name":"SM1 3QE",
    "wof:placetype":"postalcode"
},
  "geometry": {"coordinates":[-0.17674626120707,51.36904623205248],"type":"Point"}
}