{
  "type": "Feature",
  "properties": {
    "iso:country":"GB",
    "wof:name":"SA73 3HW",
    "wof:placetype":"postalcode"
},
  "geometry": {"coordinates":[-5.05754367909683,51.71556612898866],"type":"Point"}
}