{
  "type": "Feature",
  "properties": {
    "iso:country":"GB",
    "wof:name":"G51 3DG",
    "wof:placetype":"postalcode"
},
  "geometry": {"coordinates":[-4.31787492371064,55.86327188310733],"type":"Point"}
}