{
  "type": "Feature",
  "properties": {
    "date:inception_lower": "1980-01-01",
    "date:inception_upper": "1980-01-01",
    "iso:country": "GB",
    "wof:name": "LE16 9UA",
    "wof:placetype": "postalcode"
  },
  "geometry": {"coordinates":[-0.999128,52.437288],"type":"Point"}
}
