{
  "type": "Feature",
  "properties": {
    "iso:country": "GB",
    "wof:name": "LE16 9UA",
    "wof:placetype": "postalcode"
  },
  "geometry": {"coordinates":[-0.999128,52.437288],"type":"Point"}
}
