{
  "type": "Feature",
  "properties": {
    "iso:country": "GB",
    "wof:name": "E2 7DX",
    "wof:placetype": "postalcode"
  },
  "geometry": {"coordinates":[-0.067503,51.530917],"type":"Point"}
}
