{
  "type": "Feature",
  "properties": {
    "iso:country":"GB",
    "wof:name":"E2 7DX",
    "wof:placetype":"postalcode"
},
  "geometry": {"coordinates":[-0.06750288639995,51.53091690088472],"type":"Point"}
}