{
  "type": "Feature",
  "properties": {
    "date:inception_lower":"2011-12-01",
    "date:inception_upper":"2011-12-31",
    "iso:country":"GB",
    "wof:name":"E2 7DX",
    "wof:placetype":"postalcode"
},
  "geometry": {"coordinates":[-0.067503,51.530917],"type":"Point"}
}