{
  "type": "Feature",
  "properties": {
    "iso:country":"GB",
    "wof:name":"DN20 8JL",
    "wof:placetype":"postalcode"
},
  "geometry": {"coordinates":[-0.49185077287558,53.55238904293992],"type":"Point"}
}