{
  "type": "Feature",
  "properties": {
    "date:inception_lower": "1980-01-01",
    "date:inception_upper": "1980-01-01",
    "iso:country": "GB",
    "wof:name": "ME12 4NZ",
    "wof:placetype": "postalcode"
  },
  "geometry": {"coordinates":[0.902582,51.407988],"type":"Point"}
}
