{
  "type": "Feature",
  "properties": {
    "iso:country": "GB",
    "wof:name": "IP13 6JL",
    "wof:placetype": "postalcode"
  },
  "geometry": {"coordinates":[1.272705,52.115882],"type":"Point"}
}
