{
  "type": "Feature",
  "properties": {
    "iso:country":"GB",
    "wof:name":"SG8 8AY",
    "wof:placetype":"postalcode"
},
  "geometry": {"coordinates":[-0.01780043432804,52.00803750153672],"type":"Point"}
}