{
  "type": "Feature",
  "properties": {
    "date:inception_lower": "1980-01-01",
    "date:inception_upper": "1980-01-01",
    "iso:country": "GB",
    "wof:name": "SG8 8AY",
    "wof:placetype": "postalcode"
  },
  "geometry": {"coordinates":[-0.017771,52.008047],"type":"Point"}
}
