{
  "type": "Feature",
  "properties": {
    "iso:country":"GB",
    "wof:name":"CH7 1TT",
    "wof:placetype":"postalcode"
},
  "geometry": {"coordinates":[-3.15681718135947,53.16535991796385],"type":"Point"}
}