{
  "type": "Feature",
  "properties": {
    "date:inception_lower":"2014-08-01",
    "date:inception_upper":"2014-08-31",
    "iso:country":"GB",
    "wof:name":"SG19 3DJ",
    "wof:placetype":"postalcode"
},
  "geometry": {"coordinates":[-0.183638,52.150892],"type":"Point"}
}