{
  "type": "Feature",
  "properties": {
    "iso:country": "GB",
    "wof:name": "SG19 3DJ",
    "wof:placetype": "postalcode"
  },
  "geometry": {"coordinates":[-0.183638,52.150892],"type":"Point"}
}
