{
  "type": "Feature",
  "properties": {
    "iso:country":"GB",
    "wof:name":"HS1 2JX",
    "wof:placetype":"postalcode"
},
  "geometry": {"coordinates":[-6.38566032356373,58.21381432397136],"type":"Point"}
}