{
  "type": "Feature",
  "properties": {
    "iso:country": "GB",
    "wof:name": "HS1 2JX",
    "wof:placetype": "postalcode"
  },
  "geometry": {"coordinates":[-6.38566,58.213814],"type":"Point"}
}
