{
  "type": "Feature",
  "properties": {
    "date:inception_lower": "2016-07-01",
    "date:inception_upper": "2016-07-01",
    "iso:country": "GB",
    "wof:name": "LA6 1FP",
    "wof:placetype": "postalcode"
  },
  "geometry": {"coordinates":[-2.72981,54.21165],"type":"Point"}
}
