{
  "type": "Feature",
  "properties": {
    "iso:country": "GB",
    "wof:name": "NN8 2FH",
    "wof:placetype": "postalcode"
  },
  "geometry": {"coordinates":[-0.746077,52.289434],"type":"Point"}
}
