{
  "type": "Feature",
  "properties": {
    "date:inception_lower":"2015-02-01",
    "date:inception_upper":"2015-02-28",
    "iso:country":"GB",
    "wof:name":"NN8 2FH",
    "wof:placetype":"postalcode"
},
  "geometry": {"coordinates":[-0.746077,52.289434],"type":"Point"}
}