{
  "type": "Feature",
  "properties": {
    "date:inception_lower": "2001-12-01",
    "date:inception_upper": "2001-12-01",
    "iso:country": "GB",
    "wof:name": "LA2 0RT",
    "wof:placetype": "postalcode"
  },
  "geometry": {"coordinates":[-2.793143,54.002305],"type":"Point"}
}
