{
  "type": "Feature",
  "properties": {
    "iso:country":"GB",
    "wof:name":"LA2 0RT",
    "wof:placetype":"postalcode"
},
  "geometry": {"coordinates":[-2.79336412823346,54.00243577420115],"type":"Point"}
}