{
  "type": "Feature",
  "properties": {
    "iso:country": "GB",
    "wof:name": "PR5 4QR",
    "wof:placetype": "postalcode"
  },
  "geometry": {"coordinates":[-2.675762,53.739005],"type":"Point"}
}
