{
  "type": "Feature",
  "properties": {
    "date:inception_lower": "1993-08-01",
    "date:inception_upper": "1993-08-01",
    "iso:country": "GB",
    "wof:name": "OL11 1SU",
    "wof:placetype": "postalcode"
  },
  "geometry": {"coordinates":[-2.157547,53.602975],"type":"Point"}
}
