{
  "type": "Feature",
  "properties": {
    "iso:country": "GB",
    "wof:name": "OL11 1SU",
    "wof:placetype": "postalcode"
  },
  "geometry": {"coordinates":[-2.157547,53.602975],"type":"Point"}
}
