{
  "type": "Feature",
  "properties": {
    "iso:country":"GB",
    "wof:name":"CR6 9LS",
    "wof:placetype":"postalcode"
},
  "geometry": {"coordinates":[-0.05644731384422,51.30334390464039],"type":"Point"}
}