{
  "type": "Feature",
  "properties": {
    "iso:country": "GB",
    "wof:name": "CR6 9LS",
    "wof:placetype": "postalcode"
  },
  "geometry": {"coordinates":[-0.056447,51.303344],"type":"Point"}
}
