{
  "type": "Feature",
  "properties": {
    "iso:country":"GB",
    "wof:name":"TA7 8PJ",
    "wof:placetype":"postalcode"
},
  "geometry": {"coordinates":[-2.9552302887713,51.15455765931959],"type":"Point"}
}