{
  "type": "Feature",
  "properties": {
    "iso:country":"GB",
    "wof:name":"NP19 9JG",
    "wof:placetype":"postalcode"
},
  "geometry": {"coordinates":[-2.92471310963689,51.59351853226458],"type":"Point"}
}