{
  "type": "Feature",
  "properties": {
    "iso:country":"GB",
    "wof:name":"M11 3UH",
    "wof:placetype":"postalcode"
},
  "geometry": {"coordinates":[-2.19898248107659,53.48053627473336],"type":"Point"}
}