{
  "type": "Feature",
  "properties": {
    "iso:country":"GB",
    "wof:name":"WF2 9QG",
    "wof:placetype":"postalcode"
},
  "geometry": {"coordinates":[-1.51421640743215,53.68257485946069],"type":"Point"}
}