{
  "type": "Feature",
  "properties": {
    "iso:country": "GB",
    "wof:name": "M27 5EG",
    "wof:placetype": "postalcode"
  },
  "geometry": {"coordinates":[-2.323159,53.506187],"type":"Point"}
}
