{
  "type": "Feature",
  "properties": {
    "iso:country":"GB",
    "wof:name":"M27 5EG",
    "wof:placetype":"postalcode"
},
  "geometry": {"coordinates":[-2.32315926435555,53.50618746243272],"type":"Point"}
}