{
  "type": "Feature",
  "properties": {
    "iso:country":"GB",
    "wof:name":"WF5 9HE",
    "wof:placetype":"postalcode"
},
  "geometry": {"coordinates":[-1.5792966192731,53.68188620756457],"type":"Point"}
}