{
  "type": "Feature",
  "properties": {
    "iso:country":"GB",
    "wof:name":"TN33 9AH",
    "wof:placetype":"postalcode"
},
  "geometry": {"coordinates":[0.49386971439766,50.88588630822988],"type":"Point"}
}