{
  "type": "Feature",
  "properties": {
    "iso:country": "GB",
    "wof:name": "TN33 9AH",
    "wof:placetype": "postalcode"
  },
  "geometry": {"coordinates":[0.49387,50.885886],"type":"Point"}
}
