{
  "type": "Feature",
  "properties": {
    "iso:country": "GB",
    "wof:name": "TS25 1JX",
    "wof:placetype": "postalcode"
  },
  "geometry": {"coordinates":[-1.218701,54.664946],"type":"Point"}
}
