{
  "type": "Feature",
  "properties": {
    "iso:country":"GB",
    "wof:name":"SK7 4NJ",
    "wof:placetype":"postalcode"
},
  "geometry": {"coordinates":[-2.10541679481373,53.38062244981007],"type":"Point"}
}