{
  "type": "Feature",
  "properties": {
    "iso:country":"GB",
    "wof:name":"OL2 6AE",
    "wof:placetype":"postalcode"
},
  "geometry": {"coordinates":[-2.11769990366157,53.55492414549098],"type":"Point"}
}