{
  "type": "Feature",
  "properties": {
    "iso:country": "GB",
    "wof:name": "OL2 6AE",
    "wof:placetype": "postalcode"
  },
  "geometry": {"coordinates":[-2.117773,53.554949],"type":"Point"}
}
