{
  "type": "Feature",
  "properties": {
    "iso:country": "GB",
    "wof:name": "YO19 6LN",
    "wof:placetype": "postalcode"
  },
  "geometry": {"coordinates":[-1.04916,53.877513],"type":"Point"}
}
