{
  "type": "Feature",
  "properties": {
    "iso:country":"GB",
    "wof:name":"YO19 6LN",
    "wof:placetype":"postalcode"
},
  "geometry": {"coordinates":[-1.04929138005264,53.87744178969626],"type":"Point"}
}