{
  "type": "Feature",
  "properties": {
    "date:inception_lower":"1980-01-01",
    "date:inception_upper":"1980-01-31",
    "iso:country":"GB",
    "wof:name":"SW12 9NZ",
    "wof:placetype":"postalcode"
},
  "geometry": {"coordinates":[-0.145088,51.452756],"type":"Point"}
}