{
  "type": "Feature",
  "properties": {
    "iso:country":"GB",
    "wof:name":"SW12 9NZ",
    "wof:placetype":"postalcode"
},
  "geometry": {"coordinates":[-0.14508784213782,51.45275636324673],"type":"Point"}
}