{
  "type": "Feature",
  "properties": {
    "date:inception_lower": "1980-01-01",
    "date:inception_upper": "1980-01-01",
    "iso:country": "GB",
    "wof:name": "GL7 7DE",
    "wof:placetype": "postalcode"
  },
  "geometry": {"coordinates":[-1.968016,51.772924],"type":"Point"}
}
