{
  "type": "Feature",
  "properties": {
    "iso:country":"GB",
    "wof:name":"GL7 7DE",
    "wof:placetype":"postalcode"
},
  "geometry": {"coordinates":[-1.96802493040675,51.77291809231524],"type":"Point"}
}