{
  "type": "Feature",
  "properties": {
    "iso:country":"GB",
    "wof:name":"SA73 1QS",
    "wof:placetype":"postalcode"
},
  "geometry": {"coordinates":[-4.96282253505066,51.7131562322779],"type":"Point"}
}