{
  "type": "Feature",
  "properties": {
    "iso:country": "GB",
    "wof:name": "SA73 1QS",
    "wof:placetype": "postalcode"
  },
  "geometry": {"coordinates":[-4.962822,51.713156],"type":"Point"}
}
