{
  "type": "Feature",
  "properties": {
    "iso:country":"GB",
    "wof:name":"NR20 4AU",
    "wof:placetype":"postalcode"
},
  "geometry": {"coordinates":[0.94827780447789,52.6825327687142],"type":"Point"}
}