{
  "type": "Feature",
  "properties": {
    "iso:country":"GB",
    "wof:name":"CV4 7EA",
    "wof:placetype":"postalcode"
},
  "geometry": {"coordinates":[-1.55194752257217,52.38250722577624],"type":"Point"}
}