{
  "type": "Feature",
  "properties": {
    "iso:country":"GB",
    "wof:name":"TN17 4LY",
    "wof:placetype":"postalcode"
},
  "geometry": {"coordinates":[0.63091030052286,51.05371324778102],"type":"Point"}
}