{
  "type": "Feature",
  "properties": {
    "iso:country": "GB",
    "wof:name": "CT3 1UP",
    "wof:placetype": "postalcode"
  },
  "geometry": {"coordinates":[1.173077,51.272145],"type":"Point"}
}
