{
  "type": "Feature",
  "properties": {
    "date:inception_lower":"2008-03-01",
    "date:inception_upper":"2008-03-31",
    "iso:country":"GB",
    "wof:name":"G33 3UJ",
    "wof:placetype":"postalcode"
},
  "geometry": {"coordinates":[-4.164445,55.876942],"type":"Point"}
}