{
  "type": "Feature",
  "properties": {
    "date:inception_lower": "2020-02-01",
    "date:inception_upper": "2020-02-01",
    "iso:country": "GB",
    "wof:name": "FY6 6ES",
    "wof:placetype": "postalcode"
  },
  "geometry": {"coordinates":[-2.973461,53.843986],"type":"Point"}
}
