{
  "type": "Feature",
  "properties": {
    "iso:country":"GB",
    "wof:name":"NG2 6UB",
    "wof:placetype":"postalcode"
},
  "geometry": {"coordinates":[-1.12555294429482,52.9201504966054],"type":"Point"}
}