{
  "type": "Feature",
  "properties": {
    "date:inception_lower": "2002-05-01",
    "date:inception_upper": "2002-05-01",
    "iso:country": "GB",
    "wof:name": "TA20 2EU",
    "wof:placetype": "postalcode"
  },
  "geometry": {"coordinates":[-2.971354,50.871611],"type":"Point"}
}
