{
  "type": "Feature",
  "properties": {
    "iso:country": "GB",
    "wof:name": "CV47 1GG",
    "wof:placetype": "postalcode"
  },
  "geometry": {"coordinates":[-1.383432,52.249465],"type":"Point"}
}
