{
  "type": "Feature",
  "properties": {
    "date:inception_lower": "1980-01-01",
    "date:inception_upper": "1980-01-01",
    "iso:country": "GB",
    "wof:name": "CR0 2BY",
    "wof:placetype": "postalcode"
  },
  "geometry": {"coordinates":[-0.095629,51.38236],"type":"Point"}
}
