{
  "type": "Feature",
  "properties": {
    "iso:country": "GB",
    "wof:name": "CR0 2BY",
    "wof:placetype": "postalcode"
  },
  "geometry": {"coordinates":[-0.095715,51.382362],"type":"Point"}
}
