{
  "type": "Feature",
  "properties": {
    "iso:country":"GB",
    "wof:name":"M33 3HY",
    "wof:placetype":"postalcode"
},
  "geometry": {"coordinates":[-2.304631140916,53.41816683248884],"type":"Point"}
}