{
  "type": "Feature",
  "properties": {
    "date:inception_lower": "1990-08-01",
    "date:inception_upper": "1990-08-01",
    "iso:country": "GB",
    "wof:name": "AB45 2RQ",
    "wof:placetype": "postalcode"
  },
  "geometry": {"coordinates":[-2.686616,57.682005],"type":"Point"}
}
