{
  "type": "Feature",
  "properties": {
    "iso:country":"GB",
    "wof:name":"AB45 2RQ",
    "wof:placetype":"postalcode"
},
  "geometry": {"coordinates":[-2.68653069650378,57.68201260714923],"type":"Point"}
}