{
  "type": "Feature",
  "properties": {
    "date:inception_lower": "1980-01-01",
    "date:inception_upper": "1980-01-01",
    "iso:country": "GB",
    "wof:name": "YO13 0EN",
    "wof:placetype": "postalcode"
  },
  "geometry": {"coordinates":[-0.480287,54.382182],"type":"Point"}
}
