{
  "type": "Feature",
  "properties": {
    "iso:country":"GB",
    "wof:name":"YO13 0EN",
    "wof:placetype":"postalcode"
},
  "geometry": {"coordinates":[-0.4803155079514,54.38217605021963],"type":"Point"}
}