{
  "type": "Feature",
  "properties": {
    "iso:country": "GB",
    "wof:name": "YO13 0EN",
    "wof:placetype": "postalcode"
  },
  "geometry": {"coordinates":[-0.479826,54.382572],"type":"Point"}
}
