{
  "type": "Feature",
  "properties": {
    "iso:country": "GB",
    "wof:name": "PO17 6JY",
    "wof:placetype": "postalcode"
  },
  "geometry": {"coordinates":[-1.154091,50.920603],"type":"Point"}
}
