{
  "type": "Feature",
  "properties": {
    "date:inception_lower": "1980-01-01",
    "date:inception_upper": "1980-01-01",
    "iso:country": "GB",
    "wof:name": "KA10 6DQ",
    "wof:placetype": "postalcode"
  },
  "geometry": {"coordinates":[-4.684478,55.547665],"type":"Point"}
}
