{
  "type": "Feature",
  "properties": {
    "iso:country":"GB",
    "wof:name":"KA10 6DQ",
    "wof:placetype":"postalcode"
},
  "geometry": {"coordinates":[-4.68420553925382,55.54777951181008],"type":"Point"}
}