{
  "type": "Feature",
  "properties": {
    "iso:country": "GB",
    "wof:name": "KA10 6DQ",
    "wof:placetype": "postalcode"
  },
  "geometry": {"coordinates":[-4.684478,55.547665],"type":"Point"}
}
