{
  "type": "Feature",
  "properties": {
    "date:inception_lower": "1980-01-01",
    "date:inception_upper": "1980-01-01",
    "iso:country": "GB",
    "wof:name": "HD6 3PU",
    "wof:placetype": "postalcode"
  },
  "geometry": {"coordinates":[-1.801667,53.686631],"type":"Point"}
}
