{
  "type": "Feature",
  "properties": {
    "iso:country": "GB",
    "wof:name": "TF6 5HP",
    "wof:placetype": "postalcode"
  },
  "geometry": {"coordinates":[-2.589401,52.681827],"type":"Point"}
}
