{
  "type": "Feature",
  "properties": {
    "iso:country":"GB",
    "wof:name":"RH5 4NP",
    "wof:placetype":"postalcode"
},
  "geometry": {"coordinates":[-0.32598892618913,51.19223942155304],"type":"Point"}
}