{
  "type": "Feature",
  "properties": {
    "iso:country":"GB",
    "wof:name":"GU24 8HQ",
    "wof:placetype":"postalcode"
},
  "geometry": {"coordinates":[-0.58354266202488,51.35552575336799],"type":"Point"}
}