{
  "type": "Feature",
  "properties": {
    "iso:country":"GB",
    "wof:name":"KY12 9TA",
    "wof:placetype":"postalcode"
},
  "geometry": {"coordinates":[-3.57477753014924,56.12732529061967],"type":"Point"}
}