{
  "type": "Feature",
  "properties": {
    "iso:country": "GB",
    "wof:name": "HD6 2LG",
    "wof:placetype": "postalcode"
  },
  "geometry": {"coordinates":[-1.787217,53.717498],"type":"Point"}
}
