{
  "type": "Feature",
  "properties": {
    "iso:country": "GB",
    "wof:name": "WD4 8NF",
    "wof:placetype": "postalcode"
  },
  "geometry": {"coordinates":[-0.447144,51.713268],"type":"Point"}
}
