{
  "type": "Feature",
  "properties": {
    "iso:country":"GB",
    "wof:name":"WD4 8NF",
    "wof:placetype":"postalcode"
},
  "geometry": {"coordinates":[-0.44714390076486,51.71326767030467],"type":"Point"}
}