{
  "type": "Feature",
  "properties": {
    "date:inception_lower": "1980-01-01",
    "date:inception_upper": "1980-01-01",
    "iso:country": "GB",
    "wof:name": "SY23 1RB",
    "wof:placetype": "postalcode"
  },
  "geometry": {"coordinates":[-4.073871,52.403835],"type":"Point"}
}
