{
  "type": "Feature",
  "properties": {
    "iso:country":"GB",
    "wof:name":"HU9 5TH",
    "wof:placetype":"postalcode"
},
  "geometry": {"coordinates":[-0.27415616011853,53.75546442979498],"type":"Point"}
}