{
  "type": "Feature",
  "properties": {
    "date:inception_lower": "1980-01-01",
    "date:inception_upper": "1980-01-01",
    "iso:country": "GB",
    "wof:name": "AL1 4PN",
    "wof:placetype": "postalcode"
  },
  "geometry": {"coordinates":[-0.319328,51.755039],"type":"Point"}
}
