{
  "type": "Feature",
  "properties": {
    "iso:country":"GB",
    "wof:name":"AL1 4PN",
    "wof:placetype":"postalcode"
},
  "geometry": {"coordinates":[-0.31932838633525,51.75503917840081],"type":"Point"}
}