{
  "type": "Feature",
  "properties": {
    "date:inception_lower": "1994-05-01",
    "date:inception_upper": "1994-05-01",
    "iso:country": "GB",
    "wof:name": "LE8 4AW",
    "wof:placetype": "postalcode"
  },
  "geometry": {"coordinates":[-1.170484,52.565942],"type":"Point"}
}
