{
  "type": "Feature",
  "properties": {
    "iso:country":"GB",
    "wof:name":"LE8 4AW",
    "wof:placetype":"postalcode"
},
  "geometry": {"coordinates":[-1.17048424559695,52.56594159290828],"type":"Point"}
}