{
  "type": "Feature",
  "properties": {
    "date:inception_lower": "1988-03-01",
    "date:inception_upper": "1988-03-01",
    "iso:country": "GB",
    "wof:name": "SE22 9QS",
    "wof:placetype": "postalcode"
  },
  "geometry": {"coordinates":[-0.067274,51.4614],"type":"Point"}
}
