{
  "type": "Feature",
  "properties": {
    "iso:country":"GB",
    "wof:name":"HU2 9JJ",
    "wof:placetype":"postalcode"
},
  "geometry": {"coordinates":[-0.34219668688842,53.75135492332242],"type":"Point"}
}