{
  "type": "Feature",
  "properties": {
    "iso:country":"GB",
    "wof:name":"NP24 6JS",
    "wof:placetype":"postalcode"
},
  "geometry": {"coordinates":[-3.22826294653657,51.70945138092875],"type":"Point"}
}