{
  "type": "Feature",
  "properties": {
    "date:inception_lower":"1999-06-01",
    "date:inception_upper":"1999-06-30",
    "iso:country":"GB",
    "wof:name":"NP24 6JS",
    "wof:placetype":"postalcode"
},
  "geometry": {"coordinates":[-3.228245,51.709491],"type":"Point"}
}