{
  "type": "Feature",
  "properties": {
    "iso:country": "GB",
    "wof:name": "NP24 6JS",
    "wof:placetype": "postalcode"
  },
  "geometry": {"coordinates":[-3.228245,51.709491],"type":"Point"}
}
