{
  "type": "Feature",
  "properties": {
    "iso:country":"GB",
    "wof:name":"S61 2AS",
    "wof:placetype":"postalcode"
},
  "geometry": {"coordinates":[-1.40299758832318,53.43886272552956],"type":"Point"}
}