{
  "type": "Feature",
  "properties": {
    "iso:country":"GB",
    "wof:name":"SP4 9LD",
    "wof:placetype":"postalcode"
},
  "geometry": {"coordinates":[-1.72994021542142,51.19374824446392],"type":"Point"}
}