{
  "type": "Feature",
  "properties": {
    "iso:country":"GB",
    "wof:name":"G3 8AD",
    "wof:placetype":"postalcode"
},
  "geometry": {"coordinates":[-4.29113454757648,55.8672959446839],"type":"Point"}
}