{
  "type": "Feature",
  "properties": {
    "iso:country":"GB",
    "wof:name":"NE39 1QZ",
    "wof:placetype":"postalcode"
},
  "geometry": {"coordinates":[-1.74300858725145,54.92871480163561],"type":"Point"}
}