{
  "type": "Feature",
  "properties": {
    "iso:country":"GB",
    "wof:name":"EX5 4JT",
    "wof:placetype":"postalcode"
},
  "geometry": {"coordinates":[-3.47313619337504,50.82189326919295],"type":"Point"}
}