{
  "type": "Feature",
  "properties": {
    "iso:country":"GB",
    "wof:name":"B33 0AD",
    "wof:placetype":"postalcode"
},
  "geometry": {"coordinates":[-1.77672512377502,52.48269179865289],"type":"Point"}
}