{
  "type": "Feature",
  "properties": {
    "iso:country":"GB",
    "wof:name":"YO12 4PD",
    "wof:placetype":"postalcode"
},
  "geometry": {"coordinates":[-0.50209661053836,54.19905320031168],"type":"Point"}
}