{
  "type": "Feature",
  "properties": {
    "iso:country": "GB",
    "wof:name": "YO12 4PD",
    "wof:placetype": "postalcode"
  },
  "geometry": {"coordinates":[-0.502068,54.198972],"type":"Point"}
}
