{
  "type": "Feature",
  "properties": {
    "iso:country":"GB",
    "wof:name":"FY4 5DJ",
    "wof:placetype":"postalcode"
},
  "geometry": {"coordinates":[-3.0181897713283,53.77915380645779],"type":"Point"}
}