{
  "type": "Feature",
  "properties": {
    "iso:country": "GB",
    "wof:name": "AB25 2JQ",
    "wof:placetype": "postalcode"
  },
  "geometry": {"coordinates":[-2.120612,57.148211],"type":"Point"}
}
