{
  "type": "Feature",
  "properties": {
    "iso:country":"GB",
    "wof:name":"BH23 7EY",
    "wof:placetype":"postalcode"
},
  "geometry": {"coordinates":[-1.77002703097593,50.7542545958896],"type":"Point"}
}