{
  "type": "Feature",
  "properties": {
    "iso:country": "GB",
    "wof:name": "L6 9AB",
    "wof:placetype": "postalcode"
  },
  "geometry": {"coordinates":[-2.953604,53.412302],"type":"Point"}
}
