{
  "type": "Feature",
  "properties": {
    "iso:country":"GB",
    "wof:name":"PE1 5LG",
    "wof:placetype":"postalcode"
},
  "geometry": {"coordinates":[-0.22261235391541,52.58437723116006],"type":"Point"}
}