{
  "type": "Feature",
  "properties": {
    "date:inception_lower": "1980-01-01",
    "date:inception_upper": "1980-01-01",
    "iso:country": "GB",
    "wof:name": "LS24 8HQ",
    "wof:placetype": "postalcode"
  },
  "geometry": {"coordinates":[-1.262115,53.911142],"type":"Point"}
}
