{
  "type": "Feature",
  "properties": {
    "iso:country":"GB",
    "wof:name":"LS24 8HQ",
    "wof:placetype":"postalcode"
},
  "geometry": {"coordinates":[-1.26289235396645,53.91075171752245],"type":"Point"}
}