{
  "type": "Feature",
  "properties": {
    "iso:country": "GB",
    "wof:name": "LS24 8HQ",
    "wof:placetype": "postalcode"
  },
  "geometry": {"coordinates":[-1.262892,53.910752],"type":"Point"}
}
