{
  "type": "Feature",
  "properties": {
    "date:inception_lower": "2000-12-01",
    "date:inception_upper": "2000-12-01",
    "iso:country": "GB",
    "wof:name": "KT13 8SY",
    "wof:placetype": "postalcode"
  },
  "geometry": {"coordinates":[-0.459783,51.37345],"type":"Point"}
}
