{
  "type": "Feature",
  "properties": {
    "iso:country":"GB",
    "wof:name":"PL30 3DE",
    "wof:placetype":"postalcode"
},
  "geometry": {"coordinates":[-4.74628345182649,50.53173131105365],"type":"Point"}
}