{
  "type": "Feature",
  "properties": {
    "iso:country":"GB",
    "wof:name":"TR13 9EN",
    "wof:placetype":"postalcode"
},
  "geometry": {"coordinates":[-5.31419200481577,50.08155295996763],"type":"Point"}
}