{
  "type": "Feature",
  "properties": {
    "date:inception_lower": "1994-05-01",
    "date:inception_upper": "1994-05-01",
    "iso:country": "GB",
    "wof:name": "TA20 1YX",
    "wof:placetype": "postalcode"
  },
  "geometry": {"coordinates":[-2.962022,50.872849],"type":"Point"}
}
