{
  "type": "Feature",
  "properties": {
    "iso:country":"GB",
    "wof:name":"W11 1AN",
    "wof:placetype":"postalcode"
},
  "geometry": {"coordinates":[-0.20635964699289,51.51842863020057],"type":"Point"}
}