{
  "type": "Feature",
  "properties": {
    "iso:country": "GB",
    "wof:name": "NR14 6BX",
    "wof:placetype": "postalcode"
  },
  "geometry": {"coordinates":[1.509029,52.554385],"type":"Point"}
}
