{
  "type": "Feature",
  "properties": {
    "iso:country":"GB",
    "wof:name":"NR14 6BX",
    "wof:placetype":"postalcode"
},
  "geometry": {"coordinates":[1.50902899113997,52.55438521246381],"type":"Point"}
}