{
  "type": "Feature",
  "properties": {
    "iso:country":"GB",
    "wof:name":"WA3 2LF",
    "wof:placetype":"postalcode"
},
  "geometry": {"coordinates":[-2.57093511372188,53.47538242142869],"type":"Point"}
}