{
  "type": "Feature",
  "properties": {
    "iso:country":"GB",
    "wof:name":"BB5 0JG",
    "wof:placetype":"postalcode"
},
  "geometry": {"coordinates":[-2.37817079871223,53.74552750667916],"type":"Point"}
}