{
  "type": "Feature",
  "properties": {
    "iso:country":"GB",
    "wof:name":"GU17 0DT",
    "wof:placetype":"postalcode"
},
  "geometry": {"coordinates":[-0.80102703159078,51.33656981939239],"type":"Point"}
}