{
  "type": "Feature",
  "properties": {
    "iso:country":"GB",
    "wof:name":"M8 5YD",
    "wof:placetype":"postalcode"
},
  "geometry": {"coordinates":[-2.22517046341437,53.51167960572313],"type":"Point"}
}