{
  "type": "Feature",
  "properties": {
    "iso:country": "GB",
    "wof:name": "M8 5YD",
    "wof:placetype": "postalcode"
  },
  "geometry": {"coordinates":[-2.22517,53.51168],"type":"Point"}
}
