{
  "type": "Feature",
  "properties": {
    "iso:country":"GB",
    "wof:name":"OL16 3NJ",
    "wof:placetype":"postalcode"
},
  "geometry": {"coordinates":[-2.1096763397966,53.6099311084167],"type":"Point"}
}