{
  "type": "Feature",
  "properties": {
    "iso:country":"GB",
    "wof:name":"LA5 9BQ",
    "wof:placetype":"postalcode"
},
  "geometry": {"coordinates":[-2.76883621137064,54.12919740212012],"type":"Point"}
}