{
  "type": "Feature",
  "properties": {
    "iso:country": "GB",
    "wof:name": "LA5 9BQ",
    "wof:placetype": "postalcode"
  },
  "geometry": {"coordinates":[-2.768836,54.129197],"type":"Point"}
}
