{
  "type": "Feature",
  "properties": {
    "date:inception_lower":"2007-10-01",
    "date:inception_upper":"2007-10-31",
    "iso:country":"GB",
    "wof:name":"LA5 9BQ",
    "wof:placetype":"postalcode"
},
  "geometry": {"coordinates":[-2.768836,54.129197],"type":"Point"}
}