{
  "type": "Feature",
  "properties": {
    "iso:country":"GB",
    "wof:name":"LE16 7PL",
    "wof:placetype":"postalcode"
},
  "geometry": {"coordinates":[-0.91830315283175,52.48677900974219],"type":"Point"}
}