{
  "type": "Feature",
  "properties": {
    "iso:country":"GB",
    "wof:name":"DE73 8AU",
    "wof:placetype":"postalcode"
},
  "geometry": {"coordinates":[-1.40147265803688,52.803144733491],"type":"Point"}
}