{
  "type": "Feature",
  "properties": {
    "iso:country":"GB",
    "wof:name":"DL14 8RX",
    "wof:placetype":"postalcode"
},
  "geometry": {"coordinates":[-1.64325662461492,54.64666364167208],"type":"Point"}
}