{
  "type": "Feature",
  "properties": {
    "iso:country": "GB",
    "wof:name": "S9 1SB",
    "wof:placetype": "postalcode"
  },
  "geometry": {"coordinates":[-1.395476,53.416182],"type":"Point"}
}
