{
  "type": "Feature",
  "properties": {
    "date:inception_lower": "1995-12-01",
    "date:inception_upper": "1995-12-01",
    "iso:country": "GB",
    "wof:name": "PE25 1RH",
    "wof:placetype": "postalcode"
  },
  "geometry": {"coordinates":[0.347939,53.192208],"type":"Point"}
}
