{
  "type": "Feature",
  "properties": {
    "iso:country":"GB",
    "wof:name":"HR9 7RE",
    "wof:placetype":"postalcode"
},
  "geometry": {"coordinates":[-2.60690205924776,51.89911755141448],"type":"Point"}
}