{
  "type": "Feature",
  "properties": {
    "iso:country": "GB",
    "wof:name": "HR9 7RE",
    "wof:placetype": "postalcode"
  },
  "geometry": {"coordinates":[-2.606902,51.899118],"type":"Point"}
}
