{
  "type": "Feature",
  "properties": {
    "iso:country":"GB",
    "wof:name":"SE12 9JN",
    "wof:placetype":"postalcode"
},
  "geometry": {"coordinates":[0.02023601217834,51.44470904278193],"type":"Point"}
}