{
  "type": "Feature",
  "properties": {
    "iso:country": "GB",
    "wof:name": "ME9 7AD",
    "wof:placetype": "postalcode"
  },
  "geometry": {"coordinates":[0.652598,51.375207],"type":"Point"}
}
