{
  "type": "Feature",
  "properties": {
    "iso:country":"GB",
    "wof:name":"LE4 3DY",
    "wof:placetype":"postalcode"
},
  "geometry": {"coordinates":[-1.12820105295646,52.67973914471785],"type":"Point"}
}