{
  "type": "Feature",
  "properties": {
    "iso:country":"GB",
    "wof:name":"NE39 1EH",
    "wof:placetype":"postalcode"
},
  "geometry": {"coordinates":[-1.76187109385519,54.91872446951855],"type":"Point"}
}