{
  "type": "Feature",
  "properties": {
    "date:inception_lower": "1994-05-01",
    "date:inception_upper": "1994-05-01",
    "iso:country": "GB",
    "wof:name": "NE39 1EH",
    "wof:placetype": "postalcode"
  },
  "geometry": {"coordinates":[-1.76196,54.918813],"type":"Point"}
}
