{
  "type": "Feature",
  "properties": {
    "iso:country":"GB",
    "wof:name":"LL59 5BP",
    "wof:placetype":"postalcode"
},
  "geometry": {"coordinates":[-4.16573710772217,53.22794539895687],"type":"Point"}
}