{
  "type": "Feature",
  "properties": {
    "iso:country":"GB",
    "wof:name":"ME3 7LE",
    "wof:placetype":"postalcode"
},
  "geometry": {"coordinates":[0.46598902929728,51.43134799022472],"type":"Point"}
}