{
  "type": "Feature",
  "properties": {
    "iso:country":"GB",
    "wof:name":"AL7 4NZ",
    "wof:placetype":"postalcode"
},
  "geometry": {"coordinates":[-0.1946022772152,51.78681984094496],"type":"Point"}
}