{
  "type": "Feature",
  "properties": {
    "iso:country": "GB",
    "wof:name": "SW1V 1SB",
    "wof:placetype": "postalcode"
  },
  "geometry": {"coordinates":[-0.142649,51.491215],"type":"Point"}
}
