{
  "type": "Feature",
  "properties": {
    "iso:country": "GB",
    "wof:name": "BR7 5LS",
    "wof:placetype": "postalcode"
  },
  "geometry": {"coordinates":[0.047831,51.411739],"type":"Point"}
}
