{
  "type": "Feature",
  "properties": {
    "iso:country":"GB",
    "wof:name":"BR7 5LS",
    "wof:placetype":"postalcode"
},
  "geometry": {"coordinates":[0.04783062365963,51.41173902534094],"type":"Point"}
}