{
  "type": "Feature",
  "properties": {
    "iso:country":"GB",
    "wof:name":"HA6 2YF",
    "wof:placetype":"postalcode"
},
  "geometry": {"coordinates":[-0.42611197932552,51.61101863717166],"type":"Point"}
}