{
  "type": "Feature",
  "properties": {
    "iso:country": "GB",
    "wof:name": "BN17 6BF",
    "wof:placetype": "postalcode"
  },
  "geometry": {"coordinates":[-0.531673,50.808759],"type":"Point"}
}
