{
  "type": "Feature",
  "properties": {
    "date:inception_lower":"1992-01-01",
    "date:inception_upper":"1992-01-31",
    "iso:country":"GB",
    "wof:name":"BN17 6BF",
    "wof:placetype":"postalcode"
},
  "geometry": {"coordinates":[-0.531673,50.808759],"type":"Point"}
}