{
  "type": "Feature",
  "properties": {
    "iso:country":"GB",
    "wof:name":"DD5 4LL",
    "wof:placetype":"postalcode"
},
  "geometry": {"coordinates":[-2.82933750325115,56.47940848200772],"type":"Point"}
}