{
  "type": "Feature",
  "properties": {
    "iso:country":"GB",
    "wof:name":"PR4 2TP",
    "wof:placetype":"postalcode"
},
  "geometry": {"coordinates":[-2.87753325220846,53.78017618986886],"type":"Point"}
}