{
  "type": "Feature",
  "properties": {
    "iso:country": "GB",
    "wof:name": "PR4 2TP",
    "wof:placetype": "postalcode"
  },
  "geometry": {"coordinates":[-2.87756,53.780182],"type":"Point"}
}
