{
  "type": "Feature",
  "properties": {
    "iso:country":"GB",
    "wof:name":"CF5 6TA",
    "wof:placetype":"postalcode"
},
  "geometry": {"coordinates":[-3.30747985369724,51.45822677751927],"type":"Point"}
}