{
  "type": "Feature",
  "properties": {
    "iso:country": "GB",
    "wof:name": "CF5 6TA",
    "wof:placetype": "postalcode"
  },
  "geometry": {"coordinates":[-3.30748,51.458227],"type":"Point"}
}
