{
  "type": "Feature",
  "properties": {
    "iso:country": "GB",
    "wof:name": "KT19 8NF",
    "wof:placetype": "postalcode"
  },
  "geometry": {"coordinates":[-0.287021,51.338444],"type":"Point"}
}
