{
  "type": "Feature",
  "properties": {
    "iso:country":"GB",
    "wof:name":"KT19 8NF",
    "wof:placetype":"postalcode"
},
  "geometry": {"coordinates":[-0.28739722136223,51.3382348224122],"type":"Point"}
}