{
  "type": "Feature",
  "properties": {
    "iso:country":"GB",
    "wof:name":"B68 0QA",
    "wof:placetype":"postalcode"
},
  "geometry": {"coordinates":[-2.00855167512966,52.46292592719858],"type":"Point"}
}