{
  "type": "Feature",
  "properties": {
    "date:inception_lower": "1980-01-01",
    "date:inception_upper": "1980-01-01",
    "iso:country": "GB",
    "wof:name": "DH1 1ED",
    "wof:placetype": "postalcode"
  },
  "geometry": {"coordinates":[-1.544738,54.783183],"type":"Point"}
}
