{
  "type": "Feature",
  "properties": {
    "iso:country":"GB",
    "wof:name":"DH1 1ED",
    "wof:placetype":"postalcode"
},
  "geometry": {"coordinates":[-1.54473816090009,54.78318271320417],"type":"Point"}
}