{
  "type": "Feature",
  "properties": {
    "iso:country": "GB",
    "wof:name": "LN10 5DY",
    "wof:placetype": "postalcode"
  },
  "geometry": {"coordinates":[-0.248699,53.205555],"type":"Point"}
}
