{
  "type": "Feature",
  "properties": {
    "date:inception_lower": "1990-02-01",
    "date:inception_upper": "1990-02-01",
    "iso:country": "GB",
    "wof:name": "MK13 0DR",
    "wof:placetype": "postalcode"
  },
  "geometry": {"coordinates":[-0.791144,52.063467],"type":"Point"}
}
