{
  "type": "Feature",
  "properties": {
    "iso:country":"GB",
    "wof:name":"MK13 0DR",
    "wof:placetype":"postalcode"
},
  "geometry": {"coordinates":[-0.79114418279066,52.06346749437259],"type":"Point"}
}