{
  "type": "Feature",
  "properties": {
    "date:inception_lower": "2017-05-01",
    "date:inception_upper": "2017-05-01",
    "iso:country": "GB",
    "wof:name": "B64 6LA",
    "wof:placetype": "postalcode"
  },
  "geometry": {"coordinates":[-2.068365,52.47495],"type":"Point"}
}
