{
  "type": "Feature",
  "properties": {
    "iso:country":"GB",
    "wof:name":"G72 0QR",
    "wof:placetype":"postalcode"
},
  "geometry": {"coordinates":[-4.09980977341743,55.78984379131646],"type":"Point"}
}