{
  "type": "Feature",
  "properties": {
    "iso:country":"GB",
    "wof:name":"NE6 5EX",
    "wof:placetype":"postalcode"
},
  "geometry": {"coordinates":[-1.57669169168469,54.98097243582958],"type":"Point"}
}