{
  "type": "Feature",
  "properties": {
    "iso:country": "GB",
    "wof:name": "NE6 5EX",
    "wof:placetype": "postalcode"
  },
  "geometry": {"coordinates":[-1.576692,54.980972],"type":"Point"}
}
