{
  "type": "Feature",
  "properties": {
    "date:inception_lower":"1982-03-01",
    "date:inception_upper":"1982-03-31",
    "iso:country":"GB",
    "wof:name":"NE6 5EX",
    "wof:placetype":"postalcode"
},
  "geometry": {"coordinates":[-1.576692,54.980972],"type":"Point"}
}