{
  "type": "Feature",
  "properties": {
    "date:inception_lower": "1980-01-01",
    "date:inception_upper": "1980-01-01",
    "iso:country": "GB",
    "wof:name": "NN6 0BD",
    "wof:placetype": "postalcode"
  },
  "geometry": {"coordinates":[-0.802964,52.282355],"type":"Point"}
}
