{
  "type": "Feature",
  "properties": {
    "iso:country":"GB",
    "wof:name":"NN6 0BD",
    "wof:placetype":"postalcode"
},
  "geometry": {"coordinates":[-0.80300842402311,52.28234645790221],"type":"Point"}
}