{
  "type": "Feature",
  "properties": {
    "iso:country": "GB",
    "wof:name": "NR35 2TA",
    "wof:placetype": "postalcode"
  },
  "geometry": {"coordinates":[1.423239,52.452811],"type":"Point"}
}
