{
  "type": "Feature",
  "properties": {
    "iso:country": "GB",
    "wof:name": "KT12 5ER",
    "wof:placetype": "postalcode"
  },
  "geometry": {"coordinates":[-0.409437,51.365386],"type":"Point"}
}
