{
  "type": "Feature",
  "properties": {
    "iso:country":"GB",
    "wof:name":"S18 1WQ",
    "wof:placetype":"postalcode"
},
  "geometry": {"coordinates":[-1.47074995152234,53.29240516770741],"type":"Point"}
}