{
  "type": "Feature",
  "properties": {
    "date:inception_lower": "2006-10-01",
    "date:inception_upper": "2006-10-01",
    "iso:country": "GB",
    "wof:name": "S18 1WQ",
    "wof:placetype": "postalcode"
  },
  "geometry": {"coordinates":[-1.470749,53.292423],"type":"Point"}
}
