{
  "type": "Feature",
  "properties": {
    "iso:country":"GB",
    "wof:name":"SL9 7JZ",
    "wof:placetype":"postalcode"
},
  "geometry": {"coordinates":[-0.55758964694362,51.57793567873691],"type":"Point"}
}