{
  "type": "Feature",
  "properties": {
    "iso:country":"GB",
    "wof:name":"RG41 4DH",
    "wof:placetype":"postalcode"
},
  "geometry": {"coordinates":[-0.86599394001588,51.39789505782904],"type":"Point"}
}