{
  "type": "Feature",
  "properties": {
    "date:inception_lower": "1995-07-01",
    "date:inception_upper": "1995-07-01",
    "iso:country": "GB",
    "wof:name": "RG41 4DH",
    "wof:placetype": "postalcode"
  },
  "geometry": {"coordinates":[-0.865994,51.397895],"type":"Point"}
}
