{
  "type": "Feature",
  "properties": {
    "iso:country":"GB",
    "wof:name":"LN6 3NP",
    "wof:placetype":"postalcode"
},
  "geometry": {"coordinates":[-0.60409258210428,53.20962128810342],"type":"Point"}
}