{
  "type": "Feature",
  "properties": {
    "date:inception_lower": "1987-04-01",
    "date:inception_upper": "1987-04-01",
    "iso:country": "GB",
    "wof:name": "LN6 3NP",
    "wof:placetype": "postalcode"
  },
  "geometry": {"coordinates":[-0.604093,53.209621],"type":"Point"}
}
