{
  "type": "Feature",
  "properties": {
    "date:inception_lower": "2021-02-01",
    "date:inception_upper": "2021-02-01",
    "iso:country": "GB",
    "wof:name": "ME5 0FR",
    "wof:placetype": "postalcode"
  },
  "geometry": {"coordinates":[0.5364,51.36609],"type":"Point"}
}
