{
  "type": "Feature",
  "properties": {
    "iso:country":"GB",
    "wof:name":"DG9 7QF",
    "wof:placetype":"postalcode"
},
  "geometry": {"coordinates":[-5.03090652340934,54.89929650992116],"type":"Point"}
}