{
  "type": "Feature",
  "properties": {
    "date:inception_lower": "1980-01-01",
    "date:inception_upper": "1980-01-01",
    "iso:country": "GB",
    "wof:name": "DG9 7QF",
    "wof:placetype": "postalcode"
  },
  "geometry": {"coordinates":[-5.030906,54.899297],"type":"Point"}
}
