{
  "type": "Feature",
  "properties": {
    "iso:country": "GB",
    "wof:name": "RH6 9PZ",
    "wof:placetype": "postalcode"
  },
  "geometry": {"coordinates":[-0.15599,51.170573],"type":"Point"}
}
