{
  "type": "Feature",
  "properties": {
    "iso:country":"GB",
    "wof:name":"G21 2PS",
    "wof:placetype":"postalcode"
},
  "geometry": {"coordinates":[-4.23104176484466,55.87099776961137],"type":"Point"}
}