{
  "type": "Feature",
  "properties": {
    "iso:country":"GB",
    "wof:name":"WF17 0BZ",
    "wof:placetype":"postalcode"
},
  "geometry": {"coordinates":[-1.65382206237021,53.72734397404322],"type":"Point"}
}