{
  "type": "Feature",
  "properties": {
    "iso:country":"GB",
    "wof:name":"SK17 7SY",
    "wof:placetype":"postalcode"
},
  "geometry": {"coordinates":[-1.89713920947962,53.25393859230949],"type":"Point"}
}