{
  "type": "Feature",
  "properties": {
    "iso:country":"GB",
    "wof:name":"SE3 9HZ",
    "wof:placetype":"postalcode"
},
  "geometry": {"coordinates":[0.00827101424512,51.46194694978746],"type":"Point"}
}