{
  "type": "Feature",
  "properties": {
    "iso:country": "GB",
    "wof:name": "KY16 9UE",
    "wof:placetype": "postalcode"
  },
  "geometry": {"coordinates":[-2.824013,56.336277],"type":"Point"}
}
