{
  "type": "Feature",
  "properties": {
    "iso:country":"GB",
    "wof:name":"TQ3 2BH",
    "wof:placetype":"postalcode"
},
  "geometry": {"coordinates":[-3.56275406193285,50.43913439423245],"type":"Point"}
}