{
  "type": "Feature",
  "properties": {
    "iso:country": "GB",
    "wof:name": "GU32 2DF",
    "wof:placetype": "postalcode"
  },
  "geometry": {"coordinates":[-0.940747,51.022575],"type":"Point"}
}
