{
  "type": "Feature",
  "properties": {
    "iso:country":"GB",
    "wof:name":"GU32 2DF",
    "wof:placetype":"postalcode"
},
  "geometry": {"coordinates":[-0.94074725617248,51.02257491530055],"type":"Point"}
}