{
  "type": "Feature",
  "properties": {
    "iso:country":"GB",
    "wof:name":"RG2 7JR",
    "wof:placetype":"postalcode"
},
  "geometry": {"coordinates":[-0.95417597276822,51.43283934518679],"type":"Point"}
}