{
  "type": "Feature",
  "properties": {
    "iso:country":"GB",
    "wof:name":"BB10 4JQ",
    "wof:placetype":"postalcode"
},
  "geometry": {"coordinates":[-2.20320641989836,53.78329743963661],"type":"Point"}
}