{
  "type": "Feature",
  "properties": {
    "iso:country":"GB",
    "wof:name":"PE30 4JL",
    "wof:placetype":"postalcode"
},
  "geometry": {"coordinates":[0.41323245156622,52.742214251973],"type":"Point"}
}