{
  "type": "Feature",
  "properties": {
    "iso:country":"GB",
    "wof:name":"E14 7HN",
    "wof:placetype":"postalcode"
},
  "geometry": {"coordinates":[-0.02916595752447,51.51255457526183],"type":"Point"}
}