{
  "type": "Feature",
  "properties": {
    "iso:country": "GB",
    "wof:name": "DN16 2RG",
    "wof:placetype": "postalcode"
  },
  "geometry": {"coordinates":[-0.622134,53.564202],"type":"Point"}
}
