{
  "type": "Feature",
  "properties": {
    "iso:country":"GB",
    "wof:name":"BN17 6QG",
    "wof:placetype":"postalcode"
},
  "geometry": {"coordinates":[-0.52847087957449,50.80405992515722],"type":"Point"}
}