{
  "type": "Feature",
  "properties": {
    "iso:country":"GB",
    "wof:name":"PA3 1SA",
    "wof:placetype":"postalcode"
},
  "geometry": {"coordinates":[-4.44252251629464,55.85465827855022],"type":"Point"}
}