{
  "type": "Feature",
  "properties": {
    "iso:country": "GB",
    "wof:name": "GL14 3BH",
    "wof:placetype": "postalcode"
  },
  "geometry": {"coordinates":[-2.494777,51.819893],"type":"Point"}
}
