{
  "type": "Feature",
  "properties": {
    "iso:country":"GB",
    "wof:name":"GL14 3BH",
    "wof:placetype":"postalcode"
},
  "geometry": {"coordinates":[-2.49477699193239,51.81989251759161],"type":"Point"}
}