{
  "type": "Feature",
  "properties": {
    "iso:country":"GB",
    "wof:name":"DY13 8AS",
    "wof:placetype":"postalcode"
},
  "geometry": {"coordinates":[-2.27416936786053,52.34832580286525],"type":"Point"}
}