{
  "type": "Feature",
  "properties": {
    "iso:country":"GB",
    "wof:name":"SN3 2DD",
    "wof:placetype":"postalcode"
},
  "geometry": {"coordinates":[-1.75417174519946,51.55019581738949],"type":"Point"}
}