{
  "type": "Feature",
  "properties": {
    "iso:country":"GB",
    "wof:name":"RG14 6QU",
    "wof:placetype":"postalcode"
},
  "geometry": {"coordinates":[-1.34780626208688,51.38206256191172],"type":"Point"}
}