{
  "type": "Feature",
  "properties": {
    "iso:country":"GB",
    "wof:name":"WS5 4NP",
    "wof:placetype":"postalcode"
},
  "geometry": {"coordinates":[-1.97849160528464,52.56516654808848],"type":"Point"}
}