{
  "type": "Feature",
  "properties": {
    "iso:country": "GB",
    "wof:name": "WS5 4NP",
    "wof:placetype": "postalcode"
  },
  "geometry": {"coordinates":[-1.978492,52.565167],"type":"Point"}
}
