{
  "type": "Feature",
  "properties": {
    "iso:country":"GB",
    "wof:name":"N2 8JL",
    "wof:placetype":"postalcode"
},
  "geometry": {"coordinates":[-0.17335658164059,51.59358145813876],"type":"Point"}
}