{
  "type": "Feature",
  "properties": {
    "date:inception_lower": "1980-01-01",
    "date:inception_upper": "1980-01-01",
    "iso:country": "GB",
    "wof:name": "N2 8JL",
    "wof:placetype": "postalcode"
  },
  "geometry": {"coordinates":[-0.173357,51.593581],"type":"Point"}
}
