{
  "type": "Feature",
  "properties": {
    "iso:country":"GB",
    "wof:name":"M25 1AG",
    "wof:placetype":"postalcode"
},
  "geometry": {"coordinates":[-2.28043713631264,53.53008772617151],"type":"Point"}
}