{
  "type": "Feature",
  "properties": {
    "iso:country": "GB",
    "wof:name": "SY8 1SJ",
    "wof:placetype": "postalcode"
  },
  "geometry": {"coordinates":[-2.705512,52.368671],"type":"Point"}
}
