{
  "type": "Feature",
  "properties": {
    "iso:country":"GB",
    "wof:name":"SY8 1SJ",
    "wof:placetype":"postalcode"
},
  "geometry": {"coordinates":[-2.70551163020157,52.36867094172597],"type":"Point"}
}