{
  "type": "Feature",
  "properties": {
    "iso:country": "GB",
    "wof:name": "LS29 0TQ",
    "wof:placetype": "postalcode"
  },
  "geometry": {"coordinates":[-1.896736,53.942897],"type":"Point"}
}
