{
  "type": "Feature",
  "properties": {
    "date:inception_lower": "1991-01-01",
    "date:inception_upper": "1991-01-01",
    "iso:country": "GB",
    "wof:name": "LS29 0TQ",
    "wof:placetype": "postalcode"
  },
  "geometry": {"coordinates":[-1.896736,53.942897],"type":"Point"}
}
