{
  "type": "Feature",
  "properties": {
    "iso:country": "GB",
    "wof:name": "MK44 1EY",
    "wof:placetype": "postalcode"
  },
  "geometry": {"coordinates":[-0.558297,52.245312],"type":"Point"}
}
