{
  "type": "Feature",
  "properties": {
    "iso:country":"GB",
    "wof:name":"MK44 1EY",
    "wof:placetype":"postalcode"
},
  "geometry": {"coordinates":[-0.558297356736,52.24531201527938],"type":"Point"}
}