{
  "type": "Feature",
  "properties": {
    "iso:country":"GB",
    "wof:name":"S33 7ZQ",
    "wof:placetype":"postalcode"
},
  "geometry": {"coordinates":[-1.81503705454373,53.36410415932769],"type":"Point"}
}