{
  "type": "Feature",
  "properties": {
    "iso:country":"GB",
    "wof:name":"PO20 2HG",
    "wof:placetype":"postalcode"
},
  "geometry": {"coordinates":[-0.7158816146311,50.84833319433854],"type":"Point"}
}