{
  "type": "Feature",
  "properties": {
    "date:inception_lower": "2002-06-01",
    "date:inception_upper": "2002-06-01",
    "iso:country": "GB",
    "wof:name": "PO20 2HG",
    "wof:placetype": "postalcode"
  },
  "geometry": {"coordinates":[-0.715882,50.848333],"type":"Point"}
}
