{
  "type": "Feature",
  "properties": {
    "iso:country":"GB",
    "wof:name":"IP32 6JL",
    "wof:placetype":"postalcode"
},
  "geometry": {"coordinates":[0.7001419931506,52.26306544916743],"type":"Point"}
}