{
  "type": "Feature",
  "properties": {
    "iso:country":"GB",
    "wof:name":"HA4 6JP",
    "wof:placetype":"postalcode"
},
  "geometry": {"coordinates":[-0.41789677636105,51.56814176666611],"type":"Point"}
}