{
  "type": "Feature",
  "properties": {
    "iso:country": "GB",
    "wof:name": "SA10 7BT",
    "wof:placetype": "postalcode"
  },
  "geometry": {"coordinates":[-3.821443,51.663335],"type":"Point"}
}
