{
  "type": "Feature",
  "properties": {
    "iso:country": "GB",
    "wof:name": "SY16 4LB",
    "wof:placetype": "postalcode"
  },
  "geometry": {"coordinates":[-3.374983,52.504488],"type":"Point"}
}
