{
  "type": "Feature",
  "properties": {
    "iso:country":"GB",
    "wof:name":"SY16 4LB",
    "wof:placetype":"postalcode"
},
  "geometry": {"coordinates":[-3.3749835098713,52.50448766302019],"type":"Point"}
}