{
  "type": "Feature",
  "properties": {
    "iso:country":"GB",
    "wof:name":"SA62 6JU",
    "wof:placetype":"postalcode"
},
  "geometry": {"coordinates":[-5.09092391598574,51.85067365939035],"type":"Point"}
}