{
  "type": "Feature",
  "properties": {
    "iso:country": "GB",
    "wof:name": "EX39 5HR",
    "wof:placetype": "postalcode"
  },
  "geometry": {"coordinates":[-4.218799,50.992102],"type":"Point"}
}
