{
  "type": "Feature",
  "properties": {
    "iso:country":"GB",
    "wof:name":"EX39 5HR",
    "wof:placetype":"postalcode"
},
  "geometry": {"coordinates":[-4.2187981263483,50.99200739473213],"type":"Point"}
}