{
  "type": "Feature",
  "properties": {
    "date:inception_lower":"1980-01-01",
    "date:inception_upper":"1980-01-31",
    "iso:country":"GB",
    "wof:name":"EX39 5HR",
    "wof:placetype":"postalcode"
},
  "geometry": {"coordinates":[-4.218799,50.992102],"type":"Point"}
}