{
  "type": "Feature",
  "properties": {
    "date:inception_lower": "2010-02-01",
    "date:inception_upper": "2010-02-01",
    "iso:country": "GB",
    "wof:name": "EX32 0FD",
    "wof:placetype": "postalcode"
  },
  "geometry": {"coordinates":[-4.008727,51.06421],"type":"Point"}
}
