{
  "type": "Feature",
  "properties": {
    "iso:country":"GB",
    "wof:name":"EX32 0FD",
    "wof:placetype":"postalcode"
},
  "geometry": {"coordinates":[-4.00905830833557,51.06413588445147],"type":"Point"}
}