{
  "type": "Feature",
  "properties": {
    "iso:country":"GB",
    "wof:name":"LE12 7JW",
    "wof:placetype":"postalcode"
},
  "geometry": {"coordinates":[-1.1413050717658,52.72430773274031],"type":"Point"}
}