{
  "type": "Feature",
  "properties": {
    "iso:country":"GB",
    "wof:name":"DL5 5LR",
    "wof:placetype":"postalcode"
},
  "geometry": {"coordinates":[-1.57491959178684,54.61522316667342],"type":"Point"}
}