{
  "type": "Feature",
  "properties": {
    "iso:country":"GB",
    "wof:name":"KY13 9HR",
    "wof:placetype":"postalcode"
},
  "geometry": {"coordinates":[-3.32835411080269,56.21131415050787],"type":"Point"}
}