{
  "type": "Feature",
  "properties": {
    "iso:country":"GB",
    "wof:name":"TS25 1QJ",
    "wof:placetype":"postalcode"
},
  "geometry": {"coordinates":[-1.21323068374102,54.67288972836697],"type":"Point"}
}