{
  "type": "Feature",
  "properties": {
    "iso:country":"GB",
    "wof:name":"PO32 6FT",
    "wof:placetype":"postalcode"
},
  "geometry": {"coordinates":[-1.28515600977692,50.75831679881899],"type":"Point"}
}