{
  "type": "Feature",
  "properties": {
    "iso:country":"GB",
    "wof:name":"WN5 8PX",
    "wof:placetype":"postalcode"
},
  "geometry": {"coordinates":[-2.70275595326471,53.54296597360239],"type":"Point"}
}