{
  "type": "Feature",
  "properties": {
    "date:inception_lower":"1980-01-01",
    "date:inception_upper":"1980-01-31",
    "iso:country":"GB",
    "wof:name":"WN5 8PX",
    "wof:placetype":"postalcode"
},
  "geometry": {"coordinates":[-2.702756,53.542966],"type":"Point"}
}