{
  "type": "Feature",
  "properties": {
    "date:inception_lower": "2003-03-01",
    "date:inception_upper": "2003-03-01",
    "iso:country": "GB",
    "wof:name": "WS7 4XZ",
    "wof:placetype": "postalcode"
  },
  "geometry": {"coordinates":[-1.93255,52.672532],"type":"Point"}
}
