{
  "type": "Feature",
  "properties": {
    "iso:country":"GB",
    "wof:name":"WS7 4XZ",
    "wof:placetype":"postalcode"
},
  "geometry": {"coordinates":[-1.93255010927349,52.67253192371744],"type":"Point"}
}