{
  "type": "Feature",
  "properties": {
    "iso:country": "GB",
    "wof:name": "SK14 2PP",
    "wof:placetype": "postalcode"
  },
  "geometry": {"coordinates":[-2.06229,53.454429],"type":"Point"}
}
