{
  "type": "Feature",
  "properties": {
    "date:inception_lower":"1980-01-01",
    "date:inception_upper":"1980-01-31",
    "iso:country":"GB",
    "wof:name":"OX2 6BT",
    "wof:placetype":"postalcode"
},
  "geometry": {"coordinates":[-1.269287,51.758722],"type":"Point"}
}