{
  "type": "Feature",
  "properties": {
    "date:inception_lower": "2006-07-01",
    "date:inception_upper": "2006-07-01",
    "iso:country": "GB",
    "wof:name": "NE34 8BX",
    "wof:placetype": "postalcode"
  },
  "geometry": {"coordinates":[-1.412263,54.969623],"type":"Point"}
}
