{
  "type": "Feature",
  "properties": {
    "date:inception_lower": "2024-04-01",
    "date:inception_upper": "2024-04-01",
    "iso:country": "GB",
    "wof:name": "BL2 6GH",
    "wof:placetype": "postalcode"
  },
  "geometry": {"coordinates":[-2.391679,53.579182],"type":"Point"}
}
