{
  "type": "Feature",
  "properties": {
    "date:inception_lower": "1980-01-01",
    "date:inception_upper": "1980-01-01",
    "iso:country": "GB",
    "wof:name": "ST13 6QB",
    "wof:placetype": "postalcode"
  },
  "geometry": {"coordinates":[-2.006563,53.115823],"type":"Point"}
}
