{
  "type": "Feature",
  "properties": {
    "iso:country":"GB",
    "wof:name":"ST13 6QB",
    "wof:placetype":"postalcode"
},
  "geometry": {"coordinates":[-2.00656310124423,53.11582340360851],"type":"Point"}
}