{
  "type": "Feature",
  "properties": {
    "iso:country": "GB",
    "wof:name": "OL5 0RJ",
    "wof:placetype": "postalcode"
  },
  "geometry": {"coordinates":[-2.039153,53.528469],"type":"Point"}
}
