{
  "type": "Feature",
  "properties": {
    "iso:country":"GB",
    "wof:name":"MK18 4LD",
    "wof:placetype":"postalcode"
},
  "geometry": {"coordinates":[-1.0676423823703,51.95783535456258],"type":"Point"}
}