{
  "type": "Feature",
  "properties": {
    "date:inception_lower": "1990-02-01",
    "date:inception_upper": "1990-02-01",
    "iso:country": "GB",
    "wof:name": "BB5 5JG",
    "wof:placetype": "postalcode"
  },
  "geometry": {"coordinates":[-2.387456,53.770862],"type":"Point"}
}
