{
  "type": "Feature",
  "properties": {
    "iso:country": "GB",
    "wof:name": "BB5 5JG",
    "wof:placetype": "postalcode"
  },
  "geometry": {"coordinates":[-2.387456,53.770862],"type":"Point"}
}
