{
  "type": "Feature",
  "properties": {
    "date:inception_lower": "2017-08-01",
    "date:inception_upper": "2017-08-01",
    "iso:country": "GB",
    "wof:name": "E16 2PN",
    "wof:placetype": "postalcode"
  },
  "geometry": {"coordinates":[0.030533,51.499739],"type":"Point"}
}
