{
  "type": "Feature",
  "properties": {
    "iso:country": "GB",
    "wof:name": "E16 2PN",
    "wof:placetype": "postalcode"
  },
  "geometry": {"coordinates":[0.030533,51.499739],"type":"Point"}
}
