{
  "type": "Feature",
  "properties": {
    "date:inception_lower": "2022-05-01",
    "date:inception_upper": "2022-05-01",
    "iso:country": "GB",
    "wof:name": "BL3 4FU",
    "wof:placetype": "postalcode"
  },
  "geometry": {"coordinates":[-2.461863,53.56242],"type":"Point"}
}
