{
  "type": "Feature",
  "properties": {
    "date:inception_lower": "1980-01-01",
    "date:inception_upper": "1980-01-01",
    "iso:country": "GB",
    "wof:name": "TN14 7DG",
    "wof:placetype": "postalcode"
  },
  "geometry": {"coordinates":[0.136766,51.331633],"type":"Point"}
}
