{
  "type": "Feature",
  "properties": {
    "iso:country":"GB",
    "wof:name":"TN14 7DG",
    "wof:placetype":"postalcode"
},
  "geometry": {"coordinates":[0.13676548497986,51.33163282141731],"type":"Point"}
}