{
  "type": "Feature",
  "properties": {
    "iso:country": "GB",
    "wof:name": "SE28 8PH",
    "wof:placetype": "postalcode"
  },
  "geometry": {"coordinates":[0.12813,51.509491],"type":"Point"}
}
