{
  "type": "Feature",
  "properties": {
    "iso:country":"GB",
    "wof:name":"SE28 8PH",
    "wof:placetype":"postalcode"
},
  "geometry": {"coordinates":[0.12812996606188,51.50949096660354],"type":"Point"}
}