{
  "type": "Feature",
  "properties": {
    "iso:country":"GB",
    "wof:name":"BB1 4BN",
    "wof:placetype":"postalcode"
},
  "geometry": {"coordinates":[-2.42660838390362,53.76566889537108],"type":"Point"}
}