{
  "type": "Feature",
  "properties": {
    "iso:country": "GB",
    "wof:name": "HR8 1EY",
    "wof:placetype": "postalcode"
  },
  "geometry": {"coordinates":[-2.421572,52.037334],"type":"Point"}
}
