{
  "type": "Feature",
  "properties": {
    "iso:country":"GB",
    "wof:name":"NP12 1DY",
    "wof:placetype":"postalcode"
},
  "geometry": {"coordinates":[-3.19961958987379,51.66401597480306],"type":"Point"}
}