{
  "type": "Feature",
  "properties": {
    "iso:country":"GB",
    "wof:name":"SN16 9PP",
    "wof:placetype":"postalcode"
},
  "geometry": {"coordinates":[-1.9882537656243,51.61411085332044],"type":"Point"}
}