{
  "type": "Feature",
  "properties": {
    "iso:country": "GB",
    "wof:name": "SN16 9PP",
    "wof:placetype": "postalcode"
  },
  "geometry": {"coordinates":[-1.988254,51.614111],"type":"Point"}
}
