{
  "type": "Feature",
  "properties": {
    "iso:country": "GB",
    "wof:name": "CA15 7PB",
    "wof:placetype": "postalcode"
  },
  "geometry": {"coordinates":[-3.48775,54.711126],"type":"Point"}
}
