{
  "type": "Feature",
  "properties": {
    "date:inception_lower":"1990-07-01",
    "date:inception_upper":"1990-07-31",
    "iso:country":"GB",
    "wof:name":"MK7 8DN",
    "wof:placetype":"postalcode"
},
  "geometry": {"coordinates":[-0.683715,52.015518],"type":"Point"}
}