{
  "type": "Feature",
  "properties": {
    "iso:country": "GB",
    "wof:name": "MK7 8DN",
    "wof:placetype": "postalcode"
  },
  "geometry": {"coordinates":[-0.683715,52.015518],"type":"Point"}
}
