{
  "type": "Feature",
  "properties": {
    "date:inception_lower": "1980-01-01",
    "date:inception_upper": "1980-01-01",
    "iso:country": "GB",
    "wof:name": "BB2 2AH",
    "wof:placetype": "postalcode"
  },
  "geometry": {"coordinates":[-2.482101,53.744453],"type":"Point"}
}
