{
  "type": "Feature",
  "properties": {
    "iso:country":"GB",
    "wof:name":"BB2 2AH",
    "wof:placetype":"postalcode"
},
  "geometry": {"coordinates":[-2.48210078342679,53.7444532425749],"type":"Point"}
}