{
  "type": "Feature",
  "properties": {
    "date:inception_lower": "1980-01-01",
    "date:inception_upper": "1980-01-01",
    "iso:country": "GB",
    "wof:name": "PO14 4BP",
    "wof:placetype": "postalcode"
  },
  "geometry": {"coordinates":[-1.241964,50.849113],"type":"Point"}
}
