{
  "type": "Feature",
  "properties": {
    "iso:country": "GB",
    "wof:name": "PO14 4BP",
    "wof:placetype": "postalcode"
  },
  "geometry": {"coordinates":[-1.241964,50.849113],"type":"Point"}
}
