{
  "type": "Feature",
  "properties": {
    "iso:country":"GB",
    "wof:name":"B90 4BG",
    "wof:placetype":"postalcode"
},
  "geometry": {"coordinates":[-1.81061139215446,52.39242793185544],"type":"Point"}
}