{
  "type": "Feature",
  "properties": {
    "iso:country":"GB",
    "wof:name":"HP9 2BS",
    "wof:placetype":"postalcode"
},
  "geometry": {"coordinates":[-0.63896510332337,51.61337340929853],"type":"Point"}
}