{
  "type": "Feature",
  "properties": {
    "iso:country": "GB",
    "wof:name": "HP9 2BS",
    "wof:placetype": "postalcode"
  },
  "geometry": {"coordinates":[-0.638931,51.613385],"type":"Point"}
}
