{
  "type": "Feature",
  "properties": {
    "date:inception_lower": "1994-12-01",
    "date:inception_upper": "1994-12-01",
    "iso:country": "GB",
    "wof:name": "SO14 0PA",
    "wof:placetype": "postalcode"
  },
  "geometry": {"coordinates":[-1.395934,50.907276],"type":"Point"}
}
