{
  "type": "Feature",
  "properties": {
    "iso:country": "GB",
    "wof:name": "TW16 6EL",
    "wof:placetype": "postalcode"
  },
  "geometry": {"coordinates":[-0.41406,51.405357],"type":"Point"}
}
