{
  "type": "Feature",
  "properties": {
    "iso:country":"GB",
    "wof:name":"BS4 1QY",
    "wof:placetype":"postalcode"
},
  "geometry": {"coordinates":[-2.59825955051925,51.42545380069479],"type":"Point"}
}