{
  "type": "Feature",
  "properties": {
    "iso:country":"GB",
    "wof:name":"TN30 6ST",
    "wof:placetype":"postalcode"
},
  "geometry": {"coordinates":[0.68781224675758,51.09764966433614],"type":"Point"}
}