{
  "type": "Feature",
  "properties": {
    "iso:country": "GB",
    "wof:name": "TN30 6ST",
    "wof:placetype": "postalcode"
  },
  "geometry": {"coordinates":[0.687812,51.09765],"type":"Point"}
}
