{
  "type": "Feature",
  "properties": {
    "iso:country":"GB",
    "wof:name":"HA7 4JB",
    "wof:placetype":"postalcode"
},
  "geometry": {"coordinates":[-0.30687862771994,51.61515949810167],"type":"Point"}
}