{
  "type": "Feature",
  "properties": {
    "iso:country": "GB",
    "wof:name": "DL14 7AX",
    "wof:placetype": "postalcode"
  },
  "geometry": {"coordinates":[-1.675521,54.66347],"type":"Point"}
}
