{
  "type": "Feature",
  "properties": {
    "iso:country": "GB",
    "wof:name": "DL14 7AX",
    "wof:placetype": "postalcode"
  },
  "geometry": {"coordinates":[-1.676099,54.663471],"type":"Point"}
}
