{
  "type": "Feature",
  "properties": {
    "iso:country":"GB",
    "wof:name":"KT4 8LY",
    "wof:placetype":"postalcode"
},
  "geometry": {"coordinates":[-0.23046330095945,51.37648845433691],"type":"Point"}
}