{
  "type": "Feature",
  "properties": {
    "date:inception_lower":"1980-01-01",
    "date:inception_upper":"1980-01-31",
    "iso:country":"GB",
    "wof:name":"KT4 8LY",
    "wof:placetype":"postalcode"
},
  "geometry": {"coordinates":[-0.230463,51.376488],"type":"Point"}
}