{
  "type": "Feature",
  "properties": {
    "date:inception_lower": "2018-12-01",
    "date:inception_upper": "2018-12-01",
    "iso:country": "GB",
    "wof:name": "OX25 2BH",
    "wof:placetype": "postalcode"
  },
  "geometry": {"coordinates":[-1.149431,51.882856],"type":"Point"}
}
