{
  "type": "Feature",
  "properties": {
    "iso:country": "GB",
    "wof:name": "NP7 5DU",
    "wof:placetype": "postalcode"
  },
  "geometry": {"coordinates":[-3.024032,51.823469],"type":"Point"}
}
