{
  "type": "Feature",
  "properties": {
    "date:inception_lower":"1992-08-01",
    "date:inception_upper":"1992-08-31",
    "iso:country":"GB",
    "wof:name":"SS12 9NJ",
    "wof:placetype":"postalcode"
},
  "geometry": {"coordinates":[0.530532,51.601638],"type":"Point"}
}