{
  "type": "Feature",
  "properties": {
    "date:inception_lower":"1996-12-01",
    "date:inception_upper":"1996-12-31",
    "iso:country":"GB",
    "wof:name":"SK23 0TS",
    "wof:placetype":"postalcode"
},
  "geometry": {"coordinates":[-1.920354,53.319736],"type":"Point"}
}