{
  "type": "Feature",
  "properties": {
    "iso:country": "GB",
    "wof:name": "SK23 0TS",
    "wof:placetype": "postalcode"
  },
  "geometry": {"coordinates":[-1.920354,53.319736],"type":"Point"}
}
