{
  "type": "Feature",
  "properties": {
    "iso:country":"GB",
    "wof:name":"SK23 0TS",
    "wof:placetype":"postalcode"
},
  "geometry": {"coordinates":[-1.92035441760041,53.31973584152772],"type":"Point"}
}