{
  "type": "Feature",
  "properties": {
    "iso:country": "GB",
    "wof:name": "NW10 6LP",
    "wof:placetype": "postalcode"
  },
  "geometry": {"coordinates":[-0.252676,51.526196],"type":"Point"}
}
