{
  "type": "Feature",
  "properties": {
    "iso:country":"GB",
    "wof:name":"HG5 9NL",
    "wof:placetype":"postalcode"
},
  "geometry": {"coordinates":[-1.48468321623698,54.03124790837494],"type":"Point"}
}