{
  "type": "Feature",
  "properties": {
    "iso:country": "GB",
    "wof:name": "HG5 9NL",
    "wof:placetype": "postalcode"
  },
  "geometry": {"coordinates":[-1.484683,54.031248],"type":"Point"}
}
