{
  "type": "Feature",
  "properties": {
    "iso:country":"GB",
    "wof:name":"LL17 0DP",
    "wof:placetype":"postalcode"
},
  "geometry": {"coordinates":[-3.44578018592953,53.25981162864519],"type":"Point"}
}