{
  "type": "Feature",
  "properties": {
    "iso:country":"GB",
    "wof:name":"FK7 0HN",
    "wof:placetype":"postalcode"
},
  "geometry": {"coordinates":[-3.92833180631912,56.08862053902392],"type":"Point"}
}