{
  "type": "Feature",
  "properties": {
    "iso:country": "GB",
    "wof:name": "FK7 0HN",
    "wof:placetype": "postalcode"
  },
  "geometry": {"coordinates":[-3.928332,56.088621],"type":"Point"}
}
