{
  "type": "Feature",
  "properties": {
    "iso:country":"GB",
    "wof:name":"BB12 6BD",
    "wof:placetype":"postalcode"
},
  "geometry": {"coordinates":[-2.28735149791479,53.79533983557076],"type":"Point"}
}