{
  "type": "Feature",
  "properties": {
    "iso:country": "GB",
    "wof:name": "BB12 6BD",
    "wof:placetype": "postalcode"
  },
  "geometry": {"coordinates":[-2.287351,53.79534],"type":"Point"}
}
