{
  "type": "Feature",
  "properties": {
    "iso:country":"GB",
    "wof:name":"CT21 6HT",
    "wof:placetype":"postalcode"
},
  "geometry": {"coordinates":[1.07656213469374,51.06681378834705],"type":"Point"}
}