{
  "type": "Feature",
  "properties": {
    "iso:country": "GB",
    "wof:name": "CT21 6HT",
    "wof:placetype": "postalcode"
  },
  "geometry": {"coordinates":[1.076562,51.066814],"type":"Point"}
}
