{
  "type": "Feature",
  "properties": {
    "iso:country":"GB",
    "wof:name":"HP1 1BH",
    "wof:placetype":"postalcode"
},
  "geometry": {"coordinates":[-0.47307175041624,51.75013234659812],"type":"Point"}
}