{
  "type": "Feature",
  "properties": {
    "iso:country":"GB",
    "wof:name":"RM10 9RA",
    "wof:placetype":"postalcode"
},
  "geometry": {"coordinates":[0.1496224550872,51.53959371948118],"type":"Point"}
}