{
  "type": "Feature",
  "properties": {
    "date:inception_lower": "1980-01-01",
    "date:inception_upper": "1980-01-01",
    "iso:country": "GB",
    "wof:name": "RM10 9RA",
    "wof:placetype": "postalcode"
  },
  "geometry": {"coordinates":[0.149622,51.539594],"type":"Point"}
}
