{
  "type": "Feature",
  "properties": {
    "iso:country":"GB",
    "wof:name":"M16 0TW",
    "wof:placetype":"postalcode"
},
  "geometry": {"coordinates":[-2.28280236249874,53.45943297058144],"type":"Point"}
}