{
  "type": "Feature",
  "properties": {
    "date:inception_lower": "2000-06-01",
    "date:inception_upper": "2000-06-01",
    "iso:country": "GB",
    "wof:name": "M16 0TW",
    "wof:placetype": "postalcode"
  },
  "geometry": {"coordinates":[-2.282802,53.459433],"type":"Point"}
}
