{
  "type": "Feature",
  "properties": {
    "iso:country":"GB",
    "wof:name":"S35 8QW",
    "wof:placetype":"postalcode"
},
  "geometry": {"coordinates":[-1.50380845480375,53.43658224414472],"type":"Point"}
}