{
  "type": "Feature",
  "properties": {
    "iso:country": "GB",
    "wof:name": "KW15 1LU",
    "wof:placetype": "postalcode"
  },
  "geometry": {"coordinates":[-2.983193,58.978006],"type":"Point"}
}
