{
  "type": "Feature",
  "properties": {
    "date:inception_lower": "2020-01-01",
    "date:inception_upper": "2020-01-01",
    "iso:country": "GB",
    "wof:name": "KW15 1LU",
    "wof:placetype": "postalcode"
  },
  "geometry": {"coordinates":[-2.983662,58.978012],"type":"Point"}
}
