{
  "type": "Feature",
  "properties": {
    "iso:country":"GB",
    "wof:name":"SW16 4EB",
    "wof:placetype":"postalcode"
},
  "geometry": {"coordinates":[-0.1205977844687,51.40771782443204],"type":"Point"}
}