{
  "type": "Feature",
  "properties": {
    "iso:country":"GB",
    "wof:name":"LE2 2RN",
    "wof:placetype":"postalcode"
},
  "geometry": {"coordinates":[-1.09206424834187,52.61339143561978],"type":"Point"}
}