{
  "type": "Feature",
  "properties": {
    "iso:country":"GB",
    "wof:name":"TQ12 4NQ",
    "wof:placetype":"postalcode"
},
  "geometry": {"coordinates":[-3.58626850819128,50.51564029830694],"type":"Point"}
}