{
  "type": "Feature",
  "properties": {
    "date:inception_lower": "1980-01-01",
    "date:inception_upper": "1980-01-01",
    "iso:country": "GB",
    "wof:name": "TF9 2SE",
    "wof:placetype": "postalcode"
  },
  "geometry": {"coordinates":[-2.405145,52.858326],"type":"Point"}
}
