{
  "type": "Feature",
  "properties": {
    "iso:country":"GB",
    "wof:name":"BB7 9EP",
    "wof:placetype":"postalcode"
},
  "geometry": {"coordinates":[-2.33536799851735,53.83327915381459],"type":"Point"}
}