{
  "type": "Feature",
  "properties": {
    "iso:country":"GB",
    "wof:name":"SE14 5PN",
    "wof:placetype":"postalcode"
},
  "geometry": {"coordinates":[-0.04201298172202,51.47341791968904],"type":"Point"}
}