{
  "type": "Feature",
  "properties": {
    "iso:country": "GB",
    "wof:name": "SE14 5PN",
    "wof:placetype": "postalcode"
  },
  "geometry": {"coordinates":[-0.042013,51.473418],"type":"Point"}
}
