{
  "type": "Feature",
  "properties": {
    "iso:country":"GB",
    "wof:name":"WA16 6RH",
    "wof:placetype":"postalcode"
},
  "geometry": {"coordinates":[-2.40883715611968,53.34714165446064],"type":"Point"}
}