{
  "type": "Feature",
  "properties": {
    "date:inception_lower":"1980-01-01",
    "date:inception_upper":"1980-01-31",
    "iso:country":"GB",
    "wof:name":"CA23 3AJ",
    "wof:placetype":"postalcode"
},
  "geometry": {"coordinates":[-3.442557,54.528899],"type":"Point"}
}