{
  "type": "Feature",
  "properties": {
    "iso:country":"GB",
    "wof:name":"CA23 3AJ",
    "wof:placetype":"postalcode"
},
  "geometry": {"coordinates":[-3.44255754574024,54.52889941993786],"type":"Point"}
}