{
  "type": "Feature",
  "properties": {
    "iso:country":"GB",
    "wof:name":"TS9 6DG",
    "wof:placetype":"postalcode"
},
  "geometry": {"coordinates":[-1.13200247926653,54.49393205531437],"type":"Point"}
}