{
  "type": "Feature",
  "properties": {
    "iso:country":"GB",
    "wof:name":"TN40 2BJ",
    "wof:placetype":"postalcode"
},
  "geometry": {"coordinates":[0.47230412566668,50.8502427747696],"type":"Point"}
}