{
  "type": "Feature",
  "properties": {
    "date:inception_lower": "1980-01-01",
    "date:inception_upper": "1980-01-01",
    "iso:country": "GB",
    "wof:name": "TN40 2BJ",
    "wof:placetype": "postalcode"
  },
  "geometry": {"coordinates":[0.472304,50.850243],"type":"Point"}
}
