{
  "type": "Feature",
  "properties": {
    "iso:country":"GB",
    "wof:name":"SK11 6RJ",
    "wof:placetype":"postalcode"
},
  "geometry": {"coordinates":[-2.13150619848535,53.25626498251252],"type":"Point"}
}