{
  "type": "Feature",
  "properties": {
    "date:inception_lower": "1980-01-01",
    "date:inception_upper": "1980-01-01",
    "iso:country": "GB",
    "wof:name": "SK11 6RJ",
    "wof:placetype": "postalcode"
  },
  "geometry": {"coordinates":[-2.131506,53.256265],"type":"Point"}
}
