{
  "type": "Feature",
  "properties": {
    "date:inception_lower":"1980-01-01",
    "date:inception_upper":"1980-01-31",
    "iso:country":"GB",
    "wof:name":"HA3 8TX",
    "wof:placetype":"postalcode"
},
  "geometry": {"coordinates":[-0.307407,51.587741],"type":"Point"}
}