{
  "type": "Feature",
  "properties": {
    "iso:country": "GB",
    "wof:name": "HA3 8TX",
    "wof:placetype": "postalcode"
  },
  "geometry": {"coordinates":[-0.307407,51.587741],"type":"Point"}
}
