{
  "type": "Feature",
  "properties": {
    "iso:country":"GB",
    "wof:name":"ME18 5BB",
    "wof:placetype":"postalcode"
},
  "geometry": {"coordinates":[0.44061473403792,51.26634516835422],"type":"Point"}
}