{
  "type": "Feature",
  "properties": {
    "iso:country": "GB",
    "wof:name": "EX19 8HP",
    "wof:placetype": "postalcode"
  },
  "geometry": {"coordinates":[-3.948205,50.854209],"type":"Point"}
}
