{
  "type": "Feature",
  "properties": {
    "iso:country":"GB",
    "wof:name":"MK17 0NQ",
    "wof:placetype":"postalcode"
},
  "geometry": {"coordinates":[-0.8371872521367,52.00089414487822],"type":"Point"}
}