{
  "type": "Feature",
  "properties": {
    "date:inception_lower": "1980-01-01",
    "date:inception_upper": "1980-01-01",
    "iso:country": "GB",
    "wof:name": "MK17 0NQ",
    "wof:placetype": "postalcode"
  },
  "geometry": {"coordinates":[-0.837187,52.000894],"type":"Point"}
}
