{
  "type": "Feature",
  "properties": {
    "iso:country": "GB",
    "wof:name": "EX8 2EH",
    "wof:placetype": "postalcode"
  },
  "geometry": {"coordinates":[-3.395952,50.619057],"type":"Point"}
}
