{
  "type": "Feature",
  "properties": {
    "iso:country":"GB",
    "wof:name":"PH16 5DR",
    "wof:placetype":"postalcode"
},
  "geometry": {"coordinates":[-3.7352203238367,56.69809273497221],"type":"Point"}
}