{
  "type": "Feature",
  "properties": {
    "date:inception_lower": "1980-01-01",
    "date:inception_upper": "1980-01-01",
    "iso:country": "GB",
    "wof:name": "G81 6HQ",
    "wof:placetype": "postalcode"
  },
  "geometry": {"coordinates":[-4.41775,55.926044],"type":"Point"}
}
