{
  "type": "Feature",
  "properties": {
    "date:inception_lower":"1980-01-01",
    "date:inception_upper":"1980-01-31",
    "iso:country":"GB",
    "wof:name":"UB9 6EU",
    "wof:placetype":"postalcode"
},
  "geometry": {"coordinates":[-0.473993,51.604667],"type":"Point"}
}