{
  "type": "Feature",
  "properties": {
    "iso:country":"GB",
    "wof:name":"UB9 6EU",
    "wof:placetype":"postalcode"
},
  "geometry": {"coordinates":[-0.47389110448953,51.60445583602237],"type":"Point"}
}