{
  "type": "Feature",
  "properties": {
    "iso:country":"GB",
    "wof:name":"GU10 3AN",
    "wof:placetype":"postalcode"
},
  "geometry": {"coordinates":[-0.80323578986137,51.17822069558706],"type":"Point"}
}