{
  "type": "Feature",
  "properties": {
    "date:inception_lower": "1980-01-01",
    "date:inception_upper": "1980-01-01",
    "iso:country": "GB",
    "wof:name": "GU10 3AN",
    "wof:placetype": "postalcode"
  },
  "geometry": {"coordinates":[-0.803218,51.178218],"type":"Point"}
}
