{
  "type": "Feature",
  "properties": {
    "date:inception_lower":"1980-01-01",
    "date:inception_upper":"1980-01-31",
    "iso:country":"GB",
    "wof:name":"NG6 8NG",
    "wof:placetype":"postalcode"
},
  "geometry": {"coordinates":[-1.202413,52.999584],"type":"Point"}
}