{
  "type": "Feature",
  "properties": {
    "iso:country":"GB",
    "wof:name":"NG6 8NG",
    "wof:placetype":"postalcode"
},
  "geometry": {"coordinates":[-1.20236283722692,53.00005875961008],"type":"Point"}
}