{
  "type": "Feature",
  "properties": {
    "iso:country":"GB",
    "wof:name":"KT4 8QG",
    "wof:placetype":"postalcode"
},
  "geometry": {"coordinates":[-0.22360876034793,51.38021557687304],"type":"Point"}
}