{
  "type": "Feature",
  "properties": {
    "iso:country":"GB",
    "wof:name":"M28 2LX",
    "wof:placetype":"postalcode"
},
  "geometry": {"coordinates":[-2.35594552612081,53.51433666859725],"type":"Point"}
}