{
  "type": "Feature",
  "properties": {
    "date:inception_lower": "1996-06-01",
    "date:inception_upper": "1996-06-01",
    "iso:country": "GB",
    "wof:name": "AB15 7TT",
    "wof:placetype": "postalcode"
  },
  "geometry": {"coordinates":[-2.148161,57.127332],"type":"Point"}
}
