{
  "type": "Feature",
  "properties": {
    "iso:country": "GB",
    "wof:name": "TR19 6EW",
    "wof:placetype": "postalcode"
  },
  "geometry": {"coordinates":[-5.624533,50.07395],"type":"Point"}
}
