{
  "type": "Feature",
  "properties": {
    "iso:country":"GB",
    "wof:name":"L12 1LH",
    "wof:placetype":"postalcode"
},
  "geometry": {"coordinates":[-2.91093758293085,53.42289130437641],"type":"Point"}
}