{
  "type": "Feature",
  "properties": {
    "iso:country":"GB",
    "wof:name":"RH19 2RJ",
    "wof:placetype":"postalcode"
},
  "geometry": {"coordinates":[-0.05254413839469,51.14083834519592],"type":"Point"}
}