{
  "type": "Feature",
  "properties": {
    "date:inception_lower": "2005-09-01",
    "date:inception_upper": "2005-09-01",
    "iso:country": "GB",
    "wof:name": "RH19 2RJ",
    "wof:placetype": "postalcode"
  },
  "geometry": {"coordinates":[-0.052544,51.140838],"type":"Point"}
}
