{
  "type": "Feature",
  "properties": {
    "iso:country":"GB",
    "wof:name":"ME2 3NA",
    "wof:placetype":"postalcode"
},
  "geometry": {"coordinates":[0.48979699233848,51.40561783370237],"type":"Point"}
}