{
  "type": "Feature",
  "properties": {
    "iso:country":"GB",
    "wof:name":"E4 7QP",
    "wof:placetype":"postalcode"
},
  "geometry": {"coordinates":[0.00912187743027,51.65379900651309],"type":"Point"}
}