{
  "type": "Feature",
  "properties": {
    "iso:country": "GB",
    "wof:name": "E4 7QP",
    "wof:placetype": "postalcode"
  },
  "geometry": {"coordinates":[0.009122,51.653799],"type":"Point"}
}
