{
  "type": "Feature",
  "properties": {
    "date:inception_lower":"1997-06-01",
    "date:inception_upper":"1997-06-30",
    "iso:country":"GB",
    "wof:name":"E4 7QP",
    "wof:placetype":"postalcode"
},
  "geometry": {"coordinates":[0.009122,51.653799],"type":"Point"}
}