{
  "type": "Feature",
  "properties": {
    "iso:country":"GB",
    "wof:name":"DL3 7TD",
    "wof:placetype":"postalcode"
},
  "geometry": {"coordinates":[-1.56506277525194,54.52444765452981],"type":"Point"}
}