{
  "type": "Feature",
  "properties": {
    "date:inception_lower": "1980-01-01",
    "date:inception_upper": "1980-01-01",
    "iso:country": "GB",
    "wof:name": "EC1R 4RL",
    "wof:placetype": "postalcode"
  },
  "geometry": {"coordinates":[-0.110091,51.52608],"type":"Point"}
}
