{
  "type": "Feature",
  "properties": {
    "date:inception_lower": "1995-01-01",
    "date:inception_upper": "1995-01-01",
    "iso:country": "GB",
    "wof:name": "EX1 3QG",
    "wof:placetype": "postalcode"
  },
  "geometry": {"coordinates":[-3.469613,50.73724],"type":"Point"}
}
