{
  "type": "Feature",
  "properties": {
    "iso:country":"GB",
    "wof:name":"EX1 3QG",
    "wof:placetype":"postalcode"
},
  "geometry": {"coordinates":[-3.46961349380955,50.73724004093754],"type":"Point"}
}