{
  "type": "Feature",
  "properties": {
    "date:inception_lower": "1980-01-01",
    "date:inception_upper": "1980-01-01",
    "iso:country": "GB",
    "wof:name": "TN29 9RS",
    "wof:placetype": "postalcode"
  },
  "geometry": {"coordinates":[0.834171,51.006],"type":"Point"}
}
