{
  "type": "Feature",
  "properties": {
    "date:inception_lower": "1995-07-01",
    "date:inception_upper": "1995-07-01",
    "iso:country": "GB",
    "wof:name": "CH3 5XZ",
    "wof:placetype": "postalcode"
  },
  "geometry": {"coordinates":[-2.863051,53.183178],"type":"Point"}
}
