{
  "type": "Feature",
  "properties": {
    "iso:country":"GB",
    "wof:name":"CH3 5XZ",
    "wof:placetype":"postalcode"
},
  "geometry": {"coordinates":[-2.86305069739776,53.18317797109457],"type":"Point"}
}