{
  "type": "Feature",
  "properties": {
    "iso:country":"GB",
    "wof:name":"TA24 7RZ",
    "wof:placetype":"postalcode"
},
  "geometry": {"coordinates":[-3.66664930954257,51.11748084494921],"type":"Point"}
}