{
  "type": "Feature",
  "properties": {
    "date:inception_lower": "2009-11-01",
    "date:inception_upper": "2009-11-01",
    "iso:country": "GB",
    "wof:name": "TD9 9RA",
    "wof:placetype": "postalcode"
  },
  "geometry": {"coordinates":[-2.766634,55.428624],"type":"Point"}
}
