{
  "type": "Feature",
  "properties": {
    "iso:country": "GB",
    "wof:name": "KY11 8WD",
    "wof:placetype": "postalcode"
  },
  "geometry": {"coordinates":[-3.40138,56.072621],"type":"Point"}
}
