{
  "type": "Feature",
  "properties": {
    "iso:country":"GB",
    "wof:name":"NG1 4EX",
    "wof:placetype":"postalcode"
},
  "geometry": {"coordinates":[-1.15191850632482,52.9592302381018],"type":"Point"}
}