{
  "type": "Feature",
  "properties": {
    "date:inception_lower": "1981-06-01",
    "date:inception_upper": "1981-06-01",
    "iso:country": "GB",
    "wof:name": "NG1 4EX",
    "wof:placetype": "postalcode"
  },
  "geometry": {"coordinates":[-1.151918,52.95923],"type":"Point"}
}
