{
  "type": "Feature",
  "properties": {
    "iso:country":"GB",
    "wof:name":"BH21 5ND",
    "wof:placetype":"postalcode"
},
  "geometry": {"coordinates":[-1.95267299918362,50.90755962410496],"type":"Point"}
}