{
  "type": "Feature",
  "properties": {
    "date:inception_lower": "1980-01-01",
    "date:inception_upper": "1980-01-01",
    "iso:country": "GB",
    "wof:name": "SG5 4DG",
    "wof:placetype": "postalcode"
  },
  "geometry": {"coordinates":[-0.225832,52.020005],"type":"Point"}
}
