{
  "type": "Feature",
  "properties": {
    "iso:country": "GB",
    "wof:name": "CA12 5EZ",
    "wof:placetype": "postalcode"
  },
  "geometry": {"coordinates":[-3.139597,54.600707],"type":"Point"}
}
