{
  "type": "Feature",
  "properties": {
    "iso:country":"GB",
    "wof:name":"CA12 5EZ",
    "wof:placetype":"postalcode"
},
  "geometry": {"coordinates":[-3.13959426688157,54.60070793637534],"type":"Point"}
}