{
  "type": "Feature",
  "properties": {
    "date:inception_lower": "1980-01-01",
    "date:inception_upper": "1980-01-01",
    "iso:country": "GB",
    "wof:name": "DN40 1PY",
    "wof:placetype": "postalcode"
  },
  "geometry": {"coordinates":[-0.222453,53.612919],"type":"Point"}
}
