{
  "type": "Feature",
  "properties": {
    "iso:country":"GB",
    "wof:name":"DN40 1PY",
    "wof:placetype":"postalcode"
},
  "geometry": {"coordinates":[-0.22245354528858,53.61291875703764],"type":"Point"}
}