{
  "type": "Feature",
  "properties": {
    "date:inception_lower":"1991-01-01",
    "date:inception_upper":"1991-01-31",
    "iso:country":"GB",
    "wof:name":"TW1 4AG",
    "wof:placetype":"postalcode"
},
  "geometry": {"coordinates":[-0.330167,51.445197],"type":"Point"}
}