{
  "type": "Feature",
  "properties": {
    "iso:country":"GB",
    "wof:name":"TW1 4AG",
    "wof:placetype":"postalcode"
},
  "geometry": {"coordinates":[-0.33016712808126,51.44519733117767],"type":"Point"}
}