{
  "type": "Feature",
  "properties": {
    "iso:country": "GB",
    "wof:name": "LE12 9JN",
    "wof:placetype": "postalcode"
  },
  "geometry": {"coordinates":[-1.282008,52.769679],"type":"Point"}
}
