{
  "type": "Feature",
  "properties": {
    "iso:country":"GB",
    "wof:name":"LE12 9JN",
    "wof:placetype":"postalcode"
},
  "geometry": {"coordinates":[-1.28200755268497,52.76967904910327],"type":"Point"}
}