{
  "type": "Feature",
  "properties": {
    "date:inception_lower": "1984-10-01",
    "date:inception_upper": "1984-10-01",
    "iso:country": "GB",
    "wof:name": "LE12 9JN",
    "wof:placetype": "postalcode"
  },
  "geometry": {"coordinates":[-1.282008,52.769679],"type":"Point"}
}
