{
  "type": "Feature",
  "properties": {
    "iso:country":"GB",
    "wof:name":"DY1 3DB",
    "wof:placetype":"postalcode"
},
  "geometry": {"coordinates":[-2.10671427363305,52.5198471627554],"type":"Point"}
}