{
  "type": "Feature",
  "properties": {
    "iso:country": "GB",
    "wof:name": "DY1 3DB",
    "wof:placetype": "postalcode"
  },
  "geometry": {"coordinates":[-2.106812,52.519907],"type":"Point"}
}
