{
  "type": "Feature",
  "properties": {
    "date:inception_lower": "1997-06-01",
    "date:inception_upper": "1997-06-01",
    "iso:country": "GB",
    "wof:name": "DY1 3DB",
    "wof:placetype": "postalcode"
  },
  "geometry": {"coordinates":[-2.106812,52.519907],"type":"Point"}
}
