{
  "type": "Feature",
  "properties": {
    "iso:country": "GB",
    "wof:name": "YO32 4DS",
    "wof:placetype": "postalcode"
  },
  "geometry": {"coordinates":[-1.074802,53.995817],"type":"Point"}
}
