{
  "type": "Feature",
  "properties": {
    "iso:country": "GB",
    "wof:name": "ME20 7TQ",
    "wof:placetype": "postalcode"
  },
  "geometry": {"coordinates":[0.467063,51.291736],"type":"Point"}
}
