{
  "type": "Feature",
  "properties": {
    "date:inception_lower":"1986-07-01",
    "date:inception_upper":"1986-07-31",
    "iso:country":"GB",
    "wof:name":"ME20 7TQ",
    "wof:placetype":"postalcode"
},
  "geometry": {"coordinates":[0.467063,51.291736],"type":"Point"}
}