{
  "type": "Feature",
  "properties": {
    "iso:country":"GB",
    "wof:name":"ME20 7TQ",
    "wof:placetype":"postalcode"
},
  "geometry": {"coordinates":[0.46702371061049,51.2918099194162],"type":"Point"}
}