{
  "type": "Feature",
  "properties": {
    "iso:country":"GB",
    "wof:name":"M20 5WW",
    "wof:placetype":"postalcode"
},
  "geometry": {"coordinates":[-2.2218059390752,53.4045251432364],"type":"Point"}
}