{
  "type": "Feature",
  "properties": {
    "date:inception_lower": "1994-05-01",
    "date:inception_upper": "1994-05-01",
    "iso:country": "GB",
    "wof:name": "M20 5WW",
    "wof:placetype": "postalcode"
  },
  "geometry": {"coordinates":[-2.221806,53.404525],"type":"Point"}
}
