{
  "type": "Feature",
  "properties": {
    "iso:country": "GB",
    "wof:name": "IP12 4PZ",
    "wof:placetype": "postalcode"
  },
  "geometry": {"coordinates":[1.323511,52.051185],"type":"Point"}
}
