{
  "type": "Feature",
  "properties": {
    "iso:country":"GB",
    "wof:name":"IP12 4PZ",
    "wof:placetype":"postalcode"
},
  "geometry": {"coordinates":[1.32351068963569,52.0511849358254],"type":"Point"}
}