{
  "type": "Feature",
  "properties": {
    "date:inception_lower": "2014-07-01",
    "date:inception_upper": "2014-07-01",
    "iso:country": "GB",
    "wof:name": "E3 5GT",
    "wof:placetype": "postalcode"
  },
  "geometry": {"coordinates":[-0.029651,51.532364],"type":"Point"}
}
