{
  "type": "Feature",
  "properties": {
    "iso:country":"GB",
    "wof:name":"CB4 1GE",
    "wof:placetype":"postalcode"
},
  "geometry": {"coordinates":[0.13952151912724,52.21817150484698],"type":"Point"}
}