{
  "type": "Feature",
  "properties": {
    "iso:country":"GB",
    "wof:name":"PE25 3TH",
    "wof:placetype":"postalcode"
},
  "geometry": {"coordinates":[0.32308322912206,53.13451494037454],"type":"Point"}
}