{
  "type": "Feature",
  "properties": {
    "date:inception_lower": "2020-07-01",
    "date:inception_upper": "2020-07-01",
    "iso:country": "GB",
    "wof:name": "N11 2DW",
    "wof:placetype": "postalcode"
  },
  "geometry": {"coordinates":[-0.125103,51.608839],"type":"Point"}
}
