{
  "type": "Feature",
  "properties": {
    "iso:country":"GB",
    "wof:name":"BS16 6TN",
    "wof:placetype":"postalcode"
},
  "geometry": {"coordinates":[-2.49246029757189,51.49772615723764],"type":"Point"}
}