{
  "type": "Feature",
  "properties": {
    "iso:country":"GB",
    "wof:name":"HA7 4TD",
    "wof:placetype":"postalcode"
},
  "geometry": {"coordinates":[-0.30561243119391,51.61657997878798],"type":"Point"}
}