{
  "type": "Feature",
  "properties": {
    "date:inception_lower":"1980-01-01",
    "date:inception_upper":"1980-01-31",
    "iso:country":"GB",
    "wof:name":"NE37 2HU",
    "wof:placetype":"postalcode"
},
  "geometry": {"coordinates":[-1.525712,54.911554],"type":"Point"}
}