{
  "type": "Feature",
  "properties": {
    "iso:country":"GB",
    "wof:name":"NE37 2HU",
    "wof:placetype":"postalcode"
},
  "geometry": {"coordinates":[-1.52571233185081,54.91155370680966],"type":"Point"}
}