{
  "type": "Feature",
  "properties": {
    "iso:country": "GB",
    "wof:name": "NE37 2HU",
    "wof:placetype": "postalcode"
  },
  "geometry": {"coordinates":[-1.525712,54.911554],"type":"Point"}
}
