{
  "type": "Feature",
  "properties": {
    "iso:country": "GB",
    "wof:name": "PE14 7JQ",
    "wof:placetype": "postalcode"
  },
  "geometry": {"coordinates":[0.218206,52.725714],"type":"Point"}
}
