{
  "type": "Feature",
  "properties": {
    "iso:country":"GB",
    "wof:name":"LE12 6RB",
    "wof:placetype":"postalcode"
},
  "geometry": {"coordinates":[-1.13766400123186,52.81353193544201],"type":"Point"}
}