{
  "type": "Feature",
  "properties": {
    "date:inception_lower": "2016-03-01",
    "date:inception_upper": "2016-03-01",
    "iso:country": "GB",
    "wof:name": "LE12 6RB",
    "wof:placetype": "postalcode"
  },
  "geometry": {"coordinates":[-1.192728,52.826705],"type":"Point"}
}
