{
  "type": "Feature",
  "properties": {
    "date:inception_lower":"2013-10-01",
    "date:inception_upper":"2013-10-31",
    "iso:country":"GB",
    "wof:name":"G31 4QD",
    "wof:placetype":"postalcode"
},
  "geometry": {"coordinates":[-4.199021,55.843754],"type":"Point"}
}