{
  "type": "Feature",
  "properties": {
    "iso:country":"GB",
    "wof:name":"EN2 6TS",
    "wof:placetype":"postalcode"
},
  "geometry": {"coordinates":[-0.08198321531734,51.64938754726035],"type":"Point"}
}