{
  "type": "Feature",
  "properties": {
    "iso:country":"GB",
    "wof:name":"CA7 5EU",
    "wof:placetype":"postalcode"
},
  "geometry": {"coordinates":[-3.25391623922305,54.88281083987565],"type":"Point"}
}