{
  "type": "Feature",
  "properties": {
    "date:inception_lower": "2000-06-01",
    "date:inception_upper": "2000-06-01",
    "iso:country": "GB",
    "wof:name": "CA7 5EU",
    "wof:placetype": "postalcode"
  },
  "geometry": {"coordinates":[-3.253934,54.882826],"type":"Point"}
}
