{
  "type": "Feature",
  "properties": {
    "iso:country":"GB",
    "wof:name":"BD4 9AT",
    "wof:placetype":"postalcode"
},
  "geometry": {"coordinates":[-1.71225966813385,53.7725645450462],"type":"Point"}
}