{
  "type": "Feature",
  "properties": {
    "date:inception_lower": "1980-01-01",
    "date:inception_upper": "1980-01-01",
    "iso:country": "GB",
    "wof:name": "BD22 7HH",
    "wof:placetype": "postalcode"
  },
  "geometry": {"coordinates":[-1.946948,53.846599],"type":"Point"}
}
