{
  "type": "Feature",
  "properties": {
    "iso:country":"GB",
    "wof:name":"TS6 9QN",
    "wof:placetype":"postalcode"
},
  "geometry": {"coordinates":[-1.15122827758301,54.56302713331284],"type":"Point"}
}