{
  "type": "Feature",
  "properties": {
    "date:inception_lower":"1980-01-01",
    "date:inception_upper":"1980-01-31",
    "iso:country":"GB",
    "wof:name":"TS6 9QN",
    "wof:placetype":"postalcode"
},
  "geometry": {"coordinates":[-1.151228,54.563027],"type":"Point"}
}