{
  "type": "Feature",
  "properties": {
    "iso:country":"GB",
    "wof:name":"FY2 9BN",
    "wof:placetype":"postalcode"
},
  "geometry": {"coordinates":[-3.04810769282711,53.85731055990407],"type":"Point"}
}