{
  "type": "Feature",
  "properties": {
    "date:inception_lower":"1991-01-01",
    "date:inception_upper":"1991-01-31",
    "iso:country":"GB",
    "wof:name":"FY2 9BN",
    "wof:placetype":"postalcode"
},
  "geometry": {"coordinates":[-3.048108,53.857311],"type":"Point"}
}