{
  "type": "Feature",
  "properties": {
    "iso:country":"GB",
    "wof:name":"CV1 3GW",
    "wof:placetype":"postalcode"
},
  "geometry": {"coordinates":[-1.52493560881333,52.4079428747342],"type":"Point"}
}