{
  "type": "Feature",
  "properties": {
    "iso:country":"GB",
    "wof:name":"G72 8QJ",
    "wof:placetype":"postalcode"
},
  "geometry": {"coordinates":[-4.1790702855767,55.80811033410909],"type":"Point"}
}