{
  "type": "Feature",
  "properties": {
    "date:inception_lower": "2022-10-01",
    "date:inception_upper": "2022-10-01",
    "iso:country": "GB",
    "wof:name": "G72 8QJ",
    "wof:placetype": "postalcode"
  },
  "geometry": {"coordinates":[-4.178707,55.807843],"type":"Point"}
}
