{
  "type": "Feature",
  "properties": {
    "iso:country": "GB",
    "wof:name": "SO31 7NT",
    "wof:placetype": "postalcode"
  },
  "geometry": {"coordinates":[-1.27938,50.86684],"type":"Point"}
}
