{
  "type": "Feature",
  "properties": {
    "date:inception_lower": "2014-09-01",
    "date:inception_upper": "2014-09-01",
    "iso:country": "GB",
    "wof:name": "SO31 7NT",
    "wof:placetype": "postalcode"
  },
  "geometry": {"coordinates":[-1.27938,50.86684],"type":"Point"}
}
