{
  "type": "Feature",
  "properties": {
    "iso:country":"GB",
    "wof:name":"E6 1NP",
    "wof:placetype":"postalcode"
},
  "geometry": {"coordinates":[0.05070240656673,51.53397278067973],"type":"Point"}
}