{
  "type": "Feature",
  "properties": {
    "iso:country":"GB",
    "wof:name":"PR2 3GG",
    "wof:placetype":"postalcode"
},
  "geometry": {"coordinates":[-2.73666076243537,53.78303024163829],"type":"Point"}
}