{
  "type": "Feature",
  "properties": {
    "iso:country": "GB",
    "wof:name": "SG18 9FA",
    "wof:placetype": "postalcode"
  },
  "geometry": {"coordinates":[-0.267864,52.044667],"type":"Point"}
}
