{
  "type": "Feature",
  "properties": {
    "date:inception_lower":"2015-11-01",
    "date:inception_upper":"2015-11-30",
    "iso:country":"GB",
    "wof:name":"SG18 9FA",
    "wof:placetype":"postalcode"
},
  "geometry": {"coordinates":[-0.332265,52.076084],"type":"Point"}
}