{
  "type": "Feature",
  "properties": {
    "iso:country":"GB",
    "wof:name":"SG18 9FA",
    "wof:placetype":"postalcode"
},
  "geometry": {"coordinates":[-0.33226518100076,52.0760843682389],"type":"Point"}
}