{
  "type": "Feature",
  "properties": {
    "iso:country": "GB",
    "wof:name": "SG18 9FA",
    "wof:placetype": "postalcode"
  },
  "geometry": {"coordinates":[-0.332265,52.076084],"type":"Point"}
}
