{
  "type": "Feature",
  "properties": {
    "date:inception_lower": "2016-02-01",
    "date:inception_upper": "2016-02-01",
    "iso:country": "GB",
    "wof:name": "RH16 4XE",
    "wof:placetype": "postalcode"
  },
  "geometry": {"coordinates":[-0.110163,50.98546],"type":"Point"}
}
