{
  "type": "Feature",
  "properties": {
    "iso:country":"GB",
    "wof:name":"WD17 2DS",
    "wof:placetype":"postalcode"
},
  "geometry": {"coordinates":[-0.39568958570398,51.65543227535504],"type":"Point"}
}