{
  "type": "Feature",
  "properties": {
    "iso:country": "GB",
    "wof:name": "ML1 2PS",
    "wof:placetype": "postalcode"
  },
  "geometry": {"coordinates":[-3.982805,55.780302],"type":"Point"}
}
