{
  "type": "Feature",
  "properties": {
    "iso:country":"GB",
    "wof:name":"WR11 8SG",
    "wof:placetype":"postalcode"
},
  "geometry": {"coordinates":[-1.90213283397934,52.16499520452295],"type":"Point"}
}