{
  "type": "Feature",
  "properties": {
    "iso:country":"GB",
    "wof:name":"FY2 9HR",
    "wof:placetype":"postalcode"
},
  "geometry": {"coordinates":[-3.05151645155467,53.8495507668084],"type":"Point"}
}