{
  "type": "Feature",
  "properties": {
    "iso:country": "GB",
    "wof:name": "CM9 6FP",
    "wof:placetype": "postalcode"
  },
  "geometry": {"coordinates":[0.690765,51.720284],"type":"Point"}
}
