{
  "type": "Feature",
  "properties": {
    "date:inception_lower": "1995-01-01",
    "date:inception_upper": "1995-01-01",
    "iso:country": "GB",
    "wof:name": "NG2 6RU",
    "wof:placetype": "postalcode"
  },
  "geometry": {"coordinates":[-1.09998,52.921137],"type":"Point"}
}
