{
  "type": "Feature",
  "properties": {
    "iso:country":"GB",
    "wof:name":"NG2 6RU",
    "wof:placetype":"postalcode"
},
  "geometry": {"coordinates":[-1.09997990875212,52.92113722578733],"type":"Point"}
}