{
  "type": "Feature",
  "properties": {
    "iso:country": "GB",
    "wof:name": "CH8 8PH",
    "wof:placetype": "postalcode"
  },
  "geometry": {"coordinates":[-3.261617,53.273346],"type":"Point"}
}
