{
  "type": "Feature",
  "properties": {
    "date:inception_lower":"1980-01-01",
    "date:inception_upper":"1980-01-31",
    "iso:country":"GB",
    "wof:name":"CH8 8PH",
    "wof:placetype":"postalcode"
},
  "geometry": {"coordinates":[-3.261617,53.273346],"type":"Point"}
}