{
  "type": "Feature",
  "properties": {
    "iso:country":"GB",
    "wof:name":"LN1 3JB",
    "wof:placetype":"postalcode"
},
  "geometry": {"coordinates":[-0.54647812288339,53.23950627125708],"type":"Point"}
}