{
  "type": "Feature",
  "properties": {
    "date:inception_lower": "1980-01-01",
    "date:inception_upper": "1980-01-01",
    "iso:country": "GB",
    "wof:name": "WF12 8PF",
    "wof:placetype": "postalcode"
  },
  "geometry": {"coordinates":[-1.598679,53.686303],"type":"Point"}
}
