{
  "type": "Feature",
  "properties": {
    "iso:country":"GB",
    "wof:name":"WD3 8LD",
    "wof:placetype":"postalcode"
},
  "geometry": {"coordinates":[-0.49635921804939,51.64338430092484],"type":"Point"}
}