{
  "type": "Feature",
  "properties": {
    "iso:country":"GB",
    "wof:name":"DH8 7UF",
    "wof:placetype":"postalcode"
},
  "geometry": {"coordinates":[-1.83081979099815,54.84576290591028],"type":"Point"}
}