{
  "type": "Feature",
  "properties": {
    "date:inception_lower": "2002-05-01",
    "date:inception_upper": "2002-05-01",
    "iso:country": "GB",
    "wof:name": "DH8 7UF",
    "wof:placetype": "postalcode"
  },
  "geometry": {"coordinates":[-1.83082,54.845763],"type":"Point"}
}
