{
  "type": "Feature",
  "properties": {
    "iso:country": "GB",
    "wof:name": "TS15 0HL",
    "wof:placetype": "postalcode"
  },
  "geometry": {"coordinates":[-1.286559,54.446187],"type":"Point"}
}
