{
  "type": "Feature",
  "properties": {
    "iso:country":"GB",
    "wof:name":"WF6 1SW",
    "wof:placetype":"postalcode"
},
  "geometry": {"coordinates":[-1.40779600728678,53.6975650019183],"type":"Point"}
}