{
  "type": "Feature",
  "properties": {
    "date:inception_lower": "1980-01-01",
    "date:inception_upper": "1980-01-01",
    "iso:country": "GB",
    "wof:name": "WF6 1SW",
    "wof:placetype": "postalcode"
  },
  "geometry": {"coordinates":[-1.407796,53.697565],"type":"Point"}
}
