{
  "type": "Feature",
  "properties": {
    "iso:country":"GB",
    "wof:name":"PA16 0XX",
    "wof:placetype":"postalcode"
},
  "geometry": {"coordinates":[-4.80899059549206,55.93745885313121],"type":"Point"}
}