{
  "type": "Feature",
  "properties": {
    "date:inception_lower":"1980-01-01",
    "date:inception_upper":"1980-01-31",
    "iso:country":"GB",
    "wof:name":"PA16 0XX",
    "wof:placetype":"postalcode"
},
  "geometry": {"coordinates":[-4.808991,55.937459],"type":"Point"}
}