{
  "type": "Feature",
  "properties": {
    "iso:country": "GB",
    "wof:name": "PA16 0XX",
    "wof:placetype": "postalcode"
  },
  "geometry": {"coordinates":[-4.808991,55.937459],"type":"Point"}
}
