{
  "type": "Feature",
  "properties": {
    "iso:country":"GB",
    "wof:name":"W4 3BD",
    "wof:placetype":"postalcode"
},
  "geometry": {"coordinates":[-0.28069780296276,51.48874293910793],"type":"Point"}
}