{
  "type": "Feature",
  "properties": {
    "iso:country":"GB",
    "wof:name":"BS16 3JX",
    "wof:placetype":"postalcode"
},
  "geometry": {"coordinates":[-2.53100428235917,51.4749620921876],"type":"Point"}
}