{
  "type": "Feature",
  "properties": {
    "iso:country":"GB",
    "wof:name":"G84 9QD",
    "wof:placetype":"postalcode"
},
  "geometry": {"coordinates":[-4.73095680928141,56.00982842867366],"type":"Point"}
}