{
  "type": "Feature",
  "properties": {
    "iso:country": "GB",
    "wof:name": "SY6 6QG",
    "wof:placetype": "postalcode"
  },
  "geometry": {"coordinates":[-2.82005,52.502866],"type":"Point"}
}
