{
  "type": "Feature",
  "properties": {
    "iso:country":"GB",
    "wof:name":"SY6 6QG",
    "wof:placetype":"postalcode"
},
  "geometry": {"coordinates":[-2.82004990741722,52.50286628581544],"type":"Point"}
}