{
  "type": "Feature",
  "properties": {
    "iso:country":"GB",
    "wof:name":"SP10 3SA",
    "wof:placetype":"postalcode"
},
  "geometry": {"coordinates":[-1.51685895762145,51.21542600785182],"type":"Point"}
}