{
  "type": "Feature",
  "properties": {
    "iso:country": "GB",
    "wof:name": "SP10 3SA",
    "wof:placetype": "postalcode"
  },
  "geometry": {"coordinates":[-1.516802,51.215399],"type":"Point"}
}
