{
  "type": "Feature",
  "properties": {
    "iso:country": "GB",
    "wof:name": "PL3 5PW",
    "wof:placetype": "postalcode"
  },
  "geometry": {"coordinates":[-4.13512,50.393483],"type":"Point"}
}
