{
  "type": "Feature",
  "properties": {
    "date:inception_lower": "1982-03-01",
    "date:inception_upper": "1982-03-01",
    "iso:country": "GB",
    "wof:name": "CT20 2TJ",
    "wof:placetype": "postalcode"
  },
  "geometry": {"coordinates":[1.164387,51.077276],"type":"Point"}
}
