{
  "type": "Feature",
  "properties": {
    "iso:country":"GB",
    "wof:name":"CV36 4JE",
    "wof:placetype":"postalcode"
},
  "geometry": {"coordinates":[-1.67687503475508,52.08329234637072],"type":"Point"}
}