{
  "type": "Feature",
  "properties": {
    "date:inception_lower": "1980-01-01",
    "date:inception_upper": "1980-01-01",
    "iso:country": "GB",
    "wof:name": "CV36 4JE",
    "wof:placetype": "postalcode"
  },
  "geometry": {"coordinates":[-1.676875,52.083292],"type":"Point"}
}
