{
  "type": "Feature",
  "properties": {
    "iso:country":"GB",
    "wof:name":"SG9 9JD",
    "wof:placetype":"postalcode"
},
  "geometry": {"coordinates":[-0.01457914296433,51.94219755676284],"type":"Point"}
}