{
  "type": "Feature",
  "properties": {
    "iso:country":"GB",
    "wof:name":"TR20 8XW",
    "wof:placetype":"postalcode"
},
  "geometry": {"coordinates":[-5.56245700652385,50.15295685413908],"type":"Point"}
}