{
  "type": "Feature",
  "properties": {
    "date:inception_lower": "2019-11-01",
    "date:inception_upper": "2019-11-01",
    "iso:country": "GB",
    "wof:name": "BA5 2LG",
    "wof:placetype": "postalcode"
  },
  "geometry": {"coordinates":[-2.668358,51.214732],"type":"Point"}
}
