{
  "type": "Feature",
  "properties": {
    "iso:country":"GB",
    "wof:name":"M35 0RJ",
    "wof:placetype":"postalcode"
},
  "geometry": {"coordinates":[-2.14815114880884,53.50467221994865],"type":"Point"}
}