{
  "type": "Feature",
  "properties": {
    "iso:country":"GB",
    "wof:name":"IP33 2EW",
    "wof:placetype":"postalcode"
},
  "geometry": {"coordinates":[0.69068800698286,52.23667173735164],"type":"Point"}
}