{
  "type": "Feature",
  "properties": {
    "iso:country":"GB",
    "wof:name":"GL2 9HE",
    "wof:placetype":"postalcode"
},
  "geometry": {"coordinates":[-2.22611100784687,51.87936439539502],"type":"Point"}
}