{
  "type": "Feature",
  "properties": {
    "date:inception_lower": "1980-01-01",
    "date:inception_upper": "1980-01-01",
    "iso:country": "GB",
    "wof:name": "GL2 9HE",
    "wof:placetype": "postalcode"
  },
  "geometry": {"coordinates":[-2.226111,51.879364],"type":"Point"}
}
