{
  "type": "Feature",
  "properties": {
    "iso:country": "GB",
    "wof:name": "BB12 8NQ",
    "wof:placetype": "postalcode"
  },
  "geometry": {"coordinates":[-2.313239,53.808164],"type":"Point"}
}
