{
  "type": "Feature",
  "properties": {
    "iso:country":"GB",
    "wof:name":"DL12 9LY",
    "wof:placetype":"postalcode"
},
  "geometry": {"coordinates":[-2.01989108476661,54.51129736620685],"type":"Point"}
}