{
  "type": "Feature",
  "properties": {
    "iso:country":"GB",
    "wof:name":"SG7 6HS",
    "wof:placetype":"postalcode"
},
  "geometry": {"coordinates":[-0.19394260667686,51.9838408686085],"type":"Point"}
}