{
  "type": "Feature",
  "properties": {
    "date:inception_lower": "1999-12-01",
    "date:inception_upper": "1999-12-01",
    "iso:country": "GB",
    "wof:name": "NG20 8HX",
    "wof:placetype": "postalcode"
  },
  "geometry": {"coordinates":[-1.223871,53.21303],"type":"Point"}
}
