{
  "type": "Feature",
  "properties": {
    "date:inception_lower": "1980-01-01",
    "date:inception_upper": "1980-01-01",
    "iso:country": "GB",
    "wof:name": "CF43 3EH",
    "wof:placetype": "postalcode"
  },
  "geometry": {"coordinates":[-3.428036,51.635303],"type":"Point"}
}
