{
  "type": "Feature",
  "properties": {
    "iso:country": "GB",
    "wof:name": "BH16 5QZ",
    "wof:placetype": "postalcode"
  },
  "geometry": {"coordinates":[-2.026604,50.738867],"type":"Point"}
}
