{
  "type": "Feature",
  "properties": {
    "iso:country": "GB",
    "wof:name": "OX4 2BY",
    "wof:placetype": "postalcode"
  },
  "geometry": {"coordinates":[-1.22658,51.742264],"type":"Point"}
}
