{
  "type": "Feature",
  "properties": {
    "date:inception_lower":"1980-01-01",
    "date:inception_upper":"1980-01-31",
    "iso:country":"GB",
    "wof:name":"OX4 2BY",
    "wof:placetype":"postalcode"
},
  "geometry": {"coordinates":[-1.22658,51.742264],"type":"Point"}
}