{
  "type": "Feature",
  "properties": {
    "iso:country":"GB",
    "wof:name":"OX4 2BY",
    "wof:placetype":"postalcode"
},
  "geometry": {"coordinates":[-1.2265800987151,51.7422643682923],"type":"Point"}
}