{
  "type": "Feature",
  "properties": {
    "iso:country": "GB",
    "wof:name": "FK1 2HD",
    "wof:placetype": "postalcode"
  },
  "geometry": {"coordinates":[-3.771721,55.970426],"type":"Point"}
}
