{
  "type": "Feature",
  "properties": {
    "iso:country": "GB",
    "wof:name": "TN1 2RZ",
    "wof:placetype": "postalcode"
  },
  "geometry": {"coordinates":[0.268115,51.137855],"type":"Point"}
}
