{
  "type": "Feature",
  "properties": {
    "date:inception_lower": "2022-10-01",
    "date:inception_upper": "2022-10-01",
    "iso:country": "GB",
    "wof:name": "PE11 4FY",
    "wof:placetype": "postalcode"
  },
  "geometry": {"coordinates":[-0.194272,52.903457],"type":"Point"}
}
