{
  "type": "Feature",
  "properties": {
    "iso:country":"GB",
    "wof:name":"DA17 6FE",
    "wof:placetype":"postalcode"
},
  "geometry": {"coordinates":[0.16084323393126,51.49089795276072],"type":"Point"}
}