{
  "type": "Feature",
  "properties": {
    "iso:country": "GB",
    "wof:name": "DA17 6FE",
    "wof:placetype": "postalcode"
  },
  "geometry": {"coordinates":[0.160843,51.490898],"type":"Point"}
}
