{
  "type": "Feature",
  "properties": {
    "iso:country": "GB",
    "wof:name": "PE14 7AR",
    "wof:placetype": "postalcode"
  },
  "geometry": {"coordinates":[0.185433,52.687498],"type":"Point"}
}
