{
  "type": "Feature",
  "properties": {
    "iso:country": "GB",
    "wof:name": "GL5 5JG",
    "wof:placetype": "postalcode"
  },
  "geometry": {"coordinates":[-2.217616,51.708479],"type":"Point"}
}
