{
  "type": "Feature",
  "properties": {
    "iso:country":"GB",
    "wof:name":"GL5 5JG",
    "wof:placetype":"postalcode"
},
  "geometry": {"coordinates":[-2.21761565203342,51.70847901017115],"type":"Point"}
}