{
  "type": "Feature",
  "properties": {
    "iso:country":"GB",
    "wof:name":"PO14 4RZ",
    "wof:placetype":"postalcode"
},
  "geometry": {"coordinates":[-1.26070400639914,50.85430523413864],"type":"Point"}
}