{
  "type": "Feature",
  "properties": {
    "iso:country":"GB",
    "wof:name":"N19 3DF",
    "wof:placetype":"postalcode"
},
  "geometry": {"coordinates":[-0.12855720035639,51.56582644130649],"type":"Point"}
}