{
  "type": "Feature",
  "properties": {
    "iso:country":"GB",
    "wof:name":"PH6 2HQ",
    "wof:placetype":"postalcode"
},
  "geometry": {"coordinates":[-3.98679872162984,56.37135802925735],"type":"Point"}
}