{
  "type": "Feature",
  "properties": {
    "iso:country": "GB",
    "wof:name": "PE11 4LL",
    "wof:placetype": "postalcode"
  },
  "geometry": {"coordinates":[-0.172213,52.871684],"type":"Point"}
}
