{
  "type": "Feature",
  "properties": {
    "iso:country":"GB",
    "wof:name":"LE67 4LB",
    "wof:placetype":"postalcode"
},
  "geometry": {"coordinates":[-1.35054144852149,52.71902130678701],"type":"Point"}
}