{
  "type": "Feature",
  "properties": {
    "date:inception_lower": "1980-01-01",
    "date:inception_upper": "1980-01-01",
    "iso:country": "GB",
    "wof:name": "KW15 1ET",
    "wof:placetype": "postalcode"
  },
  "geometry": {"coordinates":[-2.956932,58.975301],"type":"Point"}
}
