{
  "type": "Feature",
  "properties": {
    "date:inception_lower": "1995-07-01",
    "date:inception_upper": "1995-07-01",
    "iso:country": "GB",
    "wof:name": "RM16 5UR",
    "wof:placetype": "postalcode"
  },
  "geometry": {"coordinates":[0.303864,51.495774],"type":"Point"}
}
