{
  "type": "Feature",
  "properties": {
    "iso:country":"GB",
    "wof:name":"N11 3AW",
    "wof:placetype":"postalcode"
},
  "geometry": {"coordinates":[-0.14889462260066,51.61110201165775],"type":"Point"}
}