{
  "type": "Feature",
  "properties": {
    "date:inception_lower": "2000-06-01",
    "date:inception_upper": "2000-06-01",
    "iso:country": "GB",
    "wof:name": "N11 3AW",
    "wof:placetype": "postalcode"
  },
  "geometry": {"coordinates":[-0.148895,51.611102],"type":"Point"}
}
