{
  "type": "Feature",
  "properties": {
    "iso:country":"GB",
    "wof:name":"CV1 2BH",
    "wof:placetype":"postalcode"
},
  "geometry": {"coordinates":[-1.49543560882475,52.40506974040542],"type":"Point"}
}