{
  "type": "Feature",
  "properties": {
    "iso:country":"GB",
    "wof:name":"IP2 0EH",
    "wof:placetype":"postalcode"
},
  "geometry": {"coordinates":[1.14022704882844,52.05250145933542],"type":"Point"}
}