{
  "type": "Feature",
  "properties": {
    "date:inception_lower":"2008-11-01",
    "date:inception_upper":"2008-11-30",
    "iso:country":"GB",
    "wof:name":"IP2 0EH",
    "wof:placetype":"postalcode"
},
  "geometry": {"coordinates":[1.140227,52.052501],"type":"Point"}
}