{
  "type": "Feature",
  "properties": {
    "iso:country": "GB",
    "wof:name": "IP2 0EH",
    "wof:placetype": "postalcode"
  },
  "geometry": {"coordinates":[1.140227,52.052501],"type":"Point"}
}
