{
  "type": "Feature",
  "properties": {
    "iso:country": "GB",
    "wof:name": "TQ12 2AN",
    "wof:placetype": "postalcode"
  },
  "geometry": {"coordinates":[-3.607158,50.531368],"type":"Point"}
}
