{
  "type": "Feature",
  "properties": {
    "date:inception_lower": "1980-01-01",
    "date:inception_upper": "1980-01-01",
    "iso:country": "GB",
    "wof:name": "TQ12 2AN",
    "wof:placetype": "postalcode"
  },
  "geometry": {"coordinates":[-3.607157,50.531323],"type":"Point"}
}
