{
  "type": "Feature",
  "properties": {
    "iso:country":"GB",
    "wof:name":"TQ12 2AN",
    "wof:placetype":"postalcode"
},
  "geometry": {"coordinates":[-3.60714180062799,50.53133564790956],"type":"Point"}
}