{
  "type": "Feature",
  "properties": {
    "date:inception_lower": "1980-01-01",
    "date:inception_upper": "1980-01-01",
    "iso:country": "GB",
    "wof:name": "IP24 2QQ",
    "wof:placetype": "postalcode"
  },
  "geometry": {"coordinates":[0.786935,52.378584],"type":"Point"}
}
