{
  "type": "Feature",
  "properties": {
    "iso:country":"GB",
    "wof:name":"IP24 2QQ",
    "wof:placetype":"postalcode"
},
  "geometry": {"coordinates":[0.78693477767035,52.37858448920707],"type":"Point"}
}