{
  "type": "Feature",
  "properties": {
    "iso:country":"GB",
    "wof:name":"CA7 5AP",
    "wof:placetype":"postalcode"
},
  "geometry": {"coordinates":[-3.2460865986543,54.9159906297812],"type":"Point"}
}