{
  "type": "Feature",
  "properties": {
    "iso:country":"GB",
    "wof:name":"NR35 2DT",
    "wof:placetype":"postalcode"
},
  "geometry": {"coordinates":[1.43685972865311,52.47873256922995],"type":"Point"}
}