{
  "type": "Feature",
  "properties": {
    "iso:country": "GB",
    "wof:name": "NR35 2DT",
    "wof:placetype": "postalcode"
  },
  "geometry": {"coordinates":[1.436859,52.479668],"type":"Point"}
}
