{
  "type": "Feature",
  "properties": {
    "date:inception_lower": "2006-03-01",
    "date:inception_upper": "2006-03-01",
    "iso:country": "GB",
    "wof:name": "W4 5RR",
    "wof:placetype": "postalcode"
  },
  "geometry": {"coordinates":[-0.272765,51.492844],"type":"Point"}
}
