{
  "type": "Feature",
  "properties": {
    "iso:country": "GB",
    "wof:name": "PR3 0PB",
    "wof:placetype": "postalcode"
  },
  "geometry": {"coordinates":[-2.769974,53.862731],"type":"Point"}
}
