{
  "type": "Feature",
  "properties": {
    "iso:country":"GB",
    "wof:name":"PR3 0PB",
    "wof:placetype":"postalcode"
},
  "geometry": {"coordinates":[-2.76997696413587,53.86271664270969],"type":"Point"}
}