{
  "type": "Feature",
  "properties": {
    "iso:country":"GB",
    "wof:name":"CO4 9UN",
    "wof:placetype":"postalcode"
},
  "geometry": {"coordinates":[0.91253738458918,51.91025684964817],"type":"Point"}
}