{
  "type": "Feature",
  "properties": {
    "iso:country": "GB",
    "wof:name": "CO4 9UN",
    "wof:placetype": "postalcode"
  },
  "geometry": {"coordinates":[0.912537,51.910257],"type":"Point"}
}
