{
  "type": "Feature",
  "properties": {
    "iso:country": "GB",
    "wof:name": "SO19 2FN",
    "wof:placetype": "postalcode"
  },
  "geometry": {"coordinates":[-1.366237,50.899897],"type":"Point"}
}
