{
  "type": "Feature",
  "properties": {
    "iso:country":"GB",
    "wof:name":"DD1 9AX",
    "wof:placetype":"postalcode"
},
  "geometry": {"coordinates":[-2.99141183326709,56.4616884825584],"type":"Point"}
}