{
  "type": "Feature",
  "properties": {
    "date:inception_lower": "1980-01-01",
    "date:inception_upper": "1980-01-01",
    "iso:country": "GB",
    "wof:name": "BH19 1AP",
    "wof:placetype": "postalcode"
  },
  "geometry": {"coordinates":[-1.964713,50.612381],"type":"Point"}
}
