{
  "type": "Feature",
  "properties": {
    "iso:country":"GB",
    "wof:name":"SN15 4TR",
    "wof:placetype":"postalcode"
},
  "geometry": {"coordinates":[-1.96899952051546,51.51115623466529],"type":"Point"}
}