{
  "type": "Feature",
  "properties": {
    "date:inception_lower":"1996-12-01",
    "date:inception_upper":"1996-12-31",
    "iso:country":"GB",
    "wof:name":"SN15 4TR",
    "wof:placetype":"postalcode"
},
  "geometry": {"coordinates":[-1.968999,51.511156],"type":"Point"}
}