{
  "type": "Feature",
  "properties": {
    "date:inception_lower": "1998-06-01",
    "date:inception_upper": "1998-06-01",
    "iso:country": "GB",
    "wof:name": "EN9 1DZ",
    "wof:placetype": "postalcode"
  },
  "geometry": {"coordinates":[-0.005584,51.687304],"type":"Point"}
}
