{
  "type": "Feature",
  "properties": {
    "iso:country":"GB",
    "wof:name":"YO32 3DN",
    "wof:placetype":"postalcode"
},
  "geometry": {"coordinates":[-1.07436523223766,54.01552400533895],"type":"Point"}
}