{
  "type": "Feature",
  "properties": {
    "iso:country": "GB",
    "wof:name": "M8 4QU",
    "wof:placetype": "postalcode"
  },
  "geometry": {"coordinates":[-2.232575,53.520016],"type":"Point"}
}
