{
  "type": "Feature",
  "properties": {
    "date:inception_lower": "1980-01-01",
    "date:inception_upper": "1980-01-01",
    "iso:country": "GB",
    "wof:name": "FK6 6PD",
    "wof:placetype": "postalcode"
  },
  "geometry": {"coordinates":[-3.919344,56.023923],"type":"Point"}
}
