{
  "type": "Feature",
  "properties": {
    "iso:country": "GB",
    "wof:name": "FK6 6PD",
    "wof:placetype": "postalcode"
  },
  "geometry": {"coordinates":[-3.919344,56.023923],"type":"Point"}
}
