{
  "type": "Feature",
  "properties": {
    "iso:country":"GB",
    "wof:name":"FK6 6PD",
    "wof:placetype":"postalcode"
},
  "geometry": {"coordinates":[-3.91934382233327,56.02392310273002],"type":"Point"}
}