{
  "type": "Feature",
  "properties": {
    "date:inception_lower":"1998-12-01",
    "date:inception_upper":"1998-12-31",
    "iso:country":"GB",
    "wof:name":"TS28 5PR",
    "wof:placetype":"postalcode"
},
  "geometry": {"coordinates":[-1.374543,54.73671],"type":"Point"}
}