{
  "type": "Feature",
  "properties": {
    "iso:country":"GB",
    "wof:name":"TS28 5PR",
    "wof:placetype":"postalcode"
},
  "geometry": {"coordinates":[-1.37454320878316,54.73670985101698],"type":"Point"}
}