{
  "type": "Feature",
  "properties": {
    "iso:country":"GB",
    "wof:name":"FY8 2RA",
    "wof:placetype":"postalcode"
},
  "geometry": {"coordinates":[-3.04213558128157,53.76378450653728],"type":"Point"}
}