{
  "type": "Feature",
  "properties": {
    "iso:country":"GB",
    "wof:name":"DE22 3WZ",
    "wof:placetype":"postalcode"
},
  "geometry": {"coordinates":[-1.4934904459909,52.919914627064],"type":"Point"}
}