{
  "type": "Feature",
  "properties": {
    "iso:country":"GB",
    "wof:name":"NE63 0LU",
    "wof:placetype":"postalcode"
},
  "geometry": {"coordinates":[-1.56281724527976,55.17350513016034],"type":"Point"}
}