{
  "type": "Feature",
  "properties": {
    "iso:country":"GB",
    "wof:name":"EX4 4EQ",
    "wof:placetype":"postalcode"
},
  "geometry": {"coordinates":[-3.52771689948961,50.72675329601819],"type":"Point"}
}