{
  "type": "Feature",
  "properties": {
    "date:inception_lower": "1995-07-01",
    "date:inception_upper": "1995-07-01",
    "iso:country": "GB",
    "wof:name": "KT14 6YX",
    "wof:placetype": "postalcode"
  },
  "geometry": {"coordinates":[-0.47877,51.346074],"type":"Point"}
}
