{
  "type": "Feature",
  "properties": {
    "date:inception_lower": "1980-01-01",
    "date:inception_upper": "1980-01-01",
    "iso:country": "GB",
    "wof:name": "OX2 9HW",
    "wof:placetype": "postalcode"
  },
  "geometry": {"coordinates":[-1.298006,51.746381],"type":"Point"}
}
