{
  "type": "Feature",
  "properties": {
    "iso:country":"GB",
    "wof:name":"DT5 1HA",
    "wof:placetype":"postalcode"
},
  "geometry": {"coordinates":[-2.4445886247529,50.56500803195166],"type":"Point"}
}