{
  "type": "Feature",
  "properties": {
    "iso:country": "GB",
    "wof:name": "LL53 8SW",
    "wof:placetype": "postalcode"
  },
  "geometry": {"coordinates":[-4.580374,52.87741],"type":"Point"}
}
