{
  "type": "Feature",
  "properties": {
    "date:inception_lower": "1980-01-01",
    "date:inception_upper": "1980-01-01",
    "iso:country": "GB",
    "wof:name": "LL53 8SW",
    "wof:placetype": "postalcode"
  },
  "geometry": {"coordinates":[-4.580374,52.87741],"type":"Point"}
}
