{
  "type": "Feature",
  "properties": {
    "date:inception_lower":"1996-06-01",
    "date:inception_upper":"1996-06-30",
    "iso:country":"GB",
    "wof:name":"L39 4YA",
    "wof:placetype":"postalcode"
},
  "geometry": {"coordinates":[-2.890235,53.563362],"type":"Point"}
}