{
  "type": "Feature",
  "properties": {
    "iso:country":"GB",
    "wof:name":"L39 4YA",
    "wof:placetype":"postalcode"
},
  "geometry": {"coordinates":[-2.89023464712118,53.56336156608364],"type":"Point"}
}