{
  "type": "Feature",
  "properties": {
    "date:inception_lower": "1980-01-01",
    "date:inception_upper": "1980-01-01",
    "iso:country": "GB",
    "wof:name": "DN7 5AJ",
    "wof:placetype": "postalcode"
  },
  "geometry": {"coordinates":[-1.029696,53.600623],"type":"Point"}
}
