{
  "type": "Feature",
  "properties": {
    "iso:country":"GB",
    "wof:name":"LU1 5PG",
    "wof:placetype":"postalcode"
},
  "geometry": {"coordinates":[-0.4330679352828,51.87118362073532],"type":"Point"}
}