{
  "type": "Feature",
  "properties": {
    "iso:country":"GB",
    "wof:name":"M27 5FQ",
    "wof:placetype":"postalcode"
},
  "geometry": {"coordinates":[-2.32270859195061,53.50640440330618],"type":"Point"}
}