{
  "type": "Feature",
  "properties": {
    "iso:country":"GB",
    "wof:name":"MK45 2BT",
    "wof:placetype":"postalcode"
},
  "geometry": {"coordinates":[-0.46710908492363,52.03099807523616],"type":"Point"}
}