{
  "type": "Feature",
  "properties": {
    "iso:country":"GB",
    "wof:name":"YO7 1JZ",
    "wof:placetype":"postalcode"
},
  "geometry": {"coordinates":[-1.33259605838973,54.23878881923775],"type":"Point"}
}