{
  "type": "Feature",
  "properties": {
    "iso:country": "GB",
    "wof:name": "YO7 1JZ",
    "wof:placetype": "postalcode"
  },
  "geometry": {"coordinates":[-1.332596,54.238789],"type":"Point"}
}
