{
  "type": "Feature",
  "properties": {
    "iso:country": "GB",
    "wof:name": "EH49 6QX",
    "wof:placetype": "postalcode"
  },
  "geometry": {"coordinates":[-3.567053,55.974457],"type":"Point"}
}
