{
  "type": "Feature",
  "properties": {
    "date:inception_lower": "1980-01-01",
    "date:inception_upper": "1980-01-01",
    "iso:country": "GB",
    "wof:name": "EH49 6QX",
    "wof:placetype": "postalcode"
  },
  "geometry": {"coordinates":[-3.567053,55.974457],"type":"Point"}
}
