{
  "type": "Feature",
  "properties": {
    "iso:country":"GB",
    "wof:name":"YO26 6LS",
    "wof:placetype":"postalcode"
},
  "geometry": {"coordinates":[-1.14627081881428,53.98077823273801],"type":"Point"}
}