{
  "type": "Feature",
  "properties": {
    "iso:country": "GB",
    "wof:name": "YO26 6LS",
    "wof:placetype": "postalcode"
  },
  "geometry": {"coordinates":[-1.146248,53.980813],"type":"Point"}
}
