{
  "type": "Feature",
  "properties": {
    "date:inception_lower": "1980-01-01",
    "date:inception_upper": "1980-01-01",
    "iso:country": "GB",
    "wof:name": "N20 0AP",
    "wof:placetype": "postalcode"
  },
  "geometry": {"coordinates":[-0.155375,51.630163],"type":"Point"}
}
