{
  "type": "Feature",
  "properties": {
    "iso:country":"GB",
    "wof:name":"N20 0AP",
    "wof:placetype":"postalcode"
},
  "geometry": {"coordinates":[-0.15538604298708,51.63017803910416],"type":"Point"}
}