{
  "type": "Feature",
  "properties": {
    "date:inception_lower":"1980-01-01",
    "date:inception_upper":"1980-01-31",
    "iso:country":"GB",
    "wof:name":"MK6 3DQ",
    "wof:placetype":"postalcode"
},
  "geometry": {"coordinates":[-0.732211,52.030975],"type":"Point"}
}