{
  "type": "Feature",
  "properties": {
    "date:inception_lower": "1980-01-01",
    "date:inception_upper": "1980-01-01",
    "iso:country": "GB",
    "wof:name": "MK6 3DQ",
    "wof:placetype": "postalcode"
  },
  "geometry": {"coordinates":[-0.732163,52.030922],"type":"Point"}
}
