{
  "type": "Feature",
  "properties": {
    "iso:country": "GB",
    "wof:name": "MK6 3DQ",
    "wof:placetype": "postalcode"
  },
  "geometry": {"coordinates":[-0.732211,52.030975],"type":"Point"}
}
