{
  "type": "Feature",
  "properties": {
    "iso:country":"GB",
    "wof:name":"MK6 3DQ",
    "wof:placetype":"postalcode"
},
  "geometry": {"coordinates":[-0.73221115397994,52.0309747194683],"type":"Point"}
}