{
  "type": "Feature",
  "properties": {
    "iso:country": "GB",
    "wof:name": "LS26 0PQ",
    "wof:placetype": "postalcode"
  },
  "geometry": {"coordinates":[-1.486144,53.754858],"type":"Point"}
}
