{
  "type": "Feature",
  "properties": {
    "date:inception_lower": "1980-01-01",
    "date:inception_upper": "1980-01-01",
    "iso:country": "GB",
    "wof:name": "CF45 4ES",
    "wof:placetype": "postalcode"
  },
  "geometry": {"coordinates":[-3.391334,51.691969],"type":"Point"}
}
