{
  "type": "Feature",
  "properties": {
    "iso:country": "GB",
    "wof:name": "CF45 4ES",
    "wof:placetype": "postalcode"
  },
  "geometry": {"coordinates":[-3.391334,51.691969],"type":"Point"}
}
