{
  "type": "Feature",
  "properties": {
    "iso:country":"GB",
    "wof:name":"WA16 0PW",
    "wof:placetype":"postalcode"
},
  "geometry": {"coordinates":[-2.42190096155411,53.31472773688592],"type":"Point"}
}