{
  "type": "Feature",
  "properties": {
    "date:inception_lower": "2020-09-01",
    "date:inception_upper": "2020-09-01",
    "iso:country": "GB",
    "wof:name": "NR14 8UD",
    "wof:placetype": "postalcode"
  },
  "geometry": {"coordinates":[1.315066,52.609634],"type":"Point"}
}
