{
  "type": "Feature",
  "properties": {
    "date:inception_lower": "1992-08-01",
    "date:inception_upper": "1992-08-01",
    "iso:country": "GB",
    "wof:name": "CR3 5AX",
    "wof:placetype": "postalcode"
  },
  "geometry": {"coordinates":[-0.100157,51.288486],"type":"Point"}
}
