{
  "type": "Feature",
  "properties": {
    "date:inception_lower":"1980-01-01",
    "date:inception_upper":"1980-01-31",
    "iso:country":"GB",
    "wof:name":"G73 1DB",
    "wof:placetype":"postalcode"
},
  "geometry": {"coordinates":[-4.231485,55.836361],"type":"Point"}
}