{
  "type": "Feature",
  "properties": {
    "iso:country":"GB",
    "wof:name":"G73 1DB",
    "wof:placetype":"postalcode"
},
  "geometry": {"coordinates":[-4.23148456683724,55.83636124192755],"type":"Point"}
}