{
  "type": "Feature",
  "properties": {
    "iso:country":"GB",
    "wof:name":"LS24 8EH",
    "wof:placetype":"postalcode"
},
  "geometry": {"coordinates":[-1.1866838489371,53.90614336124802],"type":"Point"}
}