{
  "type": "Feature",
  "properties": {
    "iso:country": "GB",
    "wof:name": "LS24 8EH",
    "wof:placetype": "postalcode"
  },
  "geometry": {"coordinates":[-1.194943,53.903646],"type":"Point"}
}
