{
  "type": "Feature",
  "properties": {
    "date:inception_lower": "1980-01-01",
    "date:inception_upper": "1980-01-01",
    "iso:country": "GB",
    "wof:name": "LS24 8EH",
    "wof:placetype": "postalcode"
  },
  "geometry": {"coordinates":[-1.193147,53.902834],"type":"Point"}
}
