{
  "type": "Feature",
  "properties": {
    "date:inception_lower": "1980-01-01",
    "date:inception_upper": "1980-01-01",
    "iso:country": "GB",
    "wof:name": "NG13 8RL",
    "wof:placetype": "postalcode"
  },
  "geometry": {"coordinates":[-0.965403,52.95227],"type":"Point"}
}
