{
  "type": "Feature",
  "properties": {
    "iso:country":"GB",
    "wof:name":"W1U 8AQ",
    "wof:placetype":"postalcode"
},
  "geometry": {"coordinates":[-0.1569333805693,51.51705091755633],"type":"Point"}
}