{
  "type": "Feature",
  "properties": {
    "date:inception_lower":"1995-01-01",
    "date:inception_upper":"1995-01-31",
    "iso:country":"GB",
    "wof:name":"BN2 5XA",
    "wof:placetype":"postalcode"
},
  "geometry": {"coordinates":[-0.097471,50.81263],"type":"Point"}
}