{
  "type": "Feature",
  "properties": {
    "iso:country":"GB",
    "wof:name":"BN2 5XA",
    "wof:placetype":"postalcode"
},
  "geometry": {"coordinates":[-0.09747096021938,50.81263016430892],"type":"Point"}
}