{
  "type": "Feature",
  "properties": {
    "iso:country":"GB",
    "wof:name":"WR11 8SY",
    "wof:placetype":"postalcode"
},
  "geometry": {"coordinates":[-1.87616554076099,52.12359668635451],"type":"Point"}
}