{
  "type": "Feature",
  "properties": {
    "iso:country": "GB",
    "wof:name": "WR11 8SY",
    "wof:placetype": "postalcode"
  },
  "geometry": {"coordinates":[-1.876165,52.123597],"type":"Point"}
}
