{
  "type": "Feature",
  "properties": {
    "iso:country":"GB",
    "wof:name":"S26 5PW",
    "wof:placetype":"postalcode"
},
  "geometry": {"coordinates":[-1.27811717958783,53.3425150671526],"type":"Point"}
}