{
  "type": "Feature",
  "properties": {
    "iso:country": "GB",
    "wof:name": "S26 5PW",
    "wof:placetype": "postalcode"
  },
  "geometry": {"coordinates":[-1.278117,53.342515],"type":"Point"}
}
