{
  "type": "Feature",
  "properties": {
    "iso:country":"GB",
    "wof:name":"CV2 5GY",
    "wof:placetype":"postalcode"
},
  "geometry": {"coordinates":[-1.46490990315671,52.41440223896531],"type":"Point"}
}