{
  "type": "Feature",
  "properties": {
    "date:inception_lower": "1980-01-01",
    "date:inception_upper": "1980-01-01",
    "iso:country": "GB",
    "wof:name": "CA12 5LZ",
    "wof:placetype": "postalcode"
  },
  "geometry": {"coordinates":[-3.137691,54.602973],"type":"Point"}
}
