{
  "type": "Feature",
  "properties": {
    "iso:country":"GB",
    "wof:name":"ME3 9HG",
    "wof:placetype":"postalcode"
},
  "geometry": {"coordinates":[0.54295943552386,51.41989083653969],"type":"Point"}
}