{
  "type": "Feature",
  "properties": {
    "date:inception_lower":"1980-01-01",
    "date:inception_upper":"1980-01-31",
    "iso:country":"GB",
    "wof:name":"ME3 9HG",
    "wof:placetype":"postalcode"
},
  "geometry": {"coordinates":[0.542859,51.419893],"type":"Point"}
}