{
  "type": "Feature",
  "properties": {
    "iso:country":"GB",
    "wof:name":"HU7 6EL",
    "wof:placetype":"postalcode"
},
  "geometry": {"coordinates":[-0.32996344496603,53.7794829443702],"type":"Point"}
}