{
  "type": "Feature",
  "properties": {
    "date:inception_lower":"1990-02-01",
    "date:inception_upper":"1990-02-28",
    "iso:country":"GB",
    "wof:name":"HU7 6EL",
    "wof:placetype":"postalcode"
},
  "geometry": {"coordinates":[-0.329963,53.779483],"type":"Point"}
}