{
  "type": "Feature",
  "properties": {
    "iso:country": "GB",
    "wof:name": "HU7 6EL",
    "wof:placetype": "postalcode"
  },
  "geometry": {"coordinates":[-0.329963,53.779483],"type":"Point"}
}
