{
  "type": "Feature",
  "properties": {
    "date:inception_lower":"1980-01-01",
    "date:inception_upper":"1980-01-31",
    "iso:country":"GB",
    "wof:name":"PO17 5BY",
    "wof:placetype":"postalcode"
},
  "geometry": {"coordinates":[-1.18497,50.896615],"type":"Point"}
}