{
  "type": "Feature",
  "properties": {
    "iso:country":"GB",
    "wof:name":"UB2 5SP",
    "wof:placetype":"postalcode"
},
  "geometry": {"coordinates":[-0.3853291981723,51.49157004539796],"type":"Point"}
}