{
  "type": "Feature",
  "properties": {
    "date:inception_lower": "2022-07-01",
    "date:inception_upper": "2022-07-01",
    "iso:country": "GB",
    "wof:name": "BN18 0XZ",
    "wof:placetype": "postalcode"
  },
  "geometry": {"coordinates":[-0.650938,50.852898],"type":"Point"}
}
