{
  "type": "Feature",
  "properties": {
    "iso:country":"GB",
    "wof:name":"WD3 4PA",
    "wof:placetype":"postalcode"
},
  "geometry": {"coordinates":[-0.51193489903511,51.6942700412082],"type":"Point"}
}