{
  "type": "Feature",
  "properties": {
    "iso:country":"GB",
    "wof:name":"SR4 9LR",
    "wof:placetype":"postalcode"
},
  "geometry": {"coordinates":[-1.45136228509897,54.88928709957865],"type":"Point"}
}