{
  "type": "Feature",
  "properties": {
    "iso:country": "GB",
    "wof:name": "PL31 2NG",
    "wof:placetype": "postalcode"
  },
  "geometry": {"coordinates":[-4.729487,50.473246],"type":"Point"}
}
