{
  "type": "Feature",
  "properties": {
    "date:inception_lower": "2017-01-01",
    "date:inception_upper": "2017-01-01",
    "iso:country": "GB",
    "wof:name": "CV37 0SS",
    "wof:placetype": "postalcode"
  },
  "geometry": {"coordinates":[-1.721854,52.20847],"type":"Point"}
}
