{
  "type": "Feature",
  "properties": {
    "iso:country": "GB",
    "wof:name": "CV37 0SS",
    "wof:placetype": "postalcode"
  },
  "geometry": {"coordinates":[-1.721854,52.20847],"type":"Point"}
}
