{
  "type": "Feature",
  "properties": {
    "date:inception_lower": "1980-01-01",
    "date:inception_upper": "1980-01-01",
    "iso:country": "GB",
    "wof:name": "CF48 1EJ",
    "wof:placetype": "postalcode"
  },
  "geometry": {"coordinates":[-3.366466,51.7242],"type":"Point"}
}
