{
  "type": "Feature",
  "properties": {
    "iso:country": "GB",
    "wof:name": "CF48 1EJ",
    "wof:placetype": "postalcode"
  },
  "geometry": {"coordinates":[-3.366466,51.7242],"type":"Point"}
}
