{
  "type": "Feature",
  "properties": {
    "iso:country":"GB",
    "wof:name":"CF48 1EJ",
    "wof:placetype":"postalcode"
},
  "geometry": {"coordinates":[-3.36646583256214,51.7241999212299],"type":"Point"}
}