{
  "type": "Feature",
  "properties": {
    "iso:country":"GB",
    "wof:name":"EC4A 2HR",
    "wof:placetype":"postalcode"
},
  "geometry": {"coordinates":[-0.10993565068043,51.51417176770779],"type":"Point"}
}