{
  "type": "Feature",
  "properties": {
    "date:inception_lower": "1980-01-01",
    "date:inception_upper": "1980-01-01",
    "iso:country": "GB",
    "wof:name": "EC4A 2HR",
    "wof:placetype": "postalcode"
  },
  "geometry": {"coordinates":[-0.109979,51.514255],"type":"Point"}
}
