{
  "type": "Feature",
  "properties": {
    "date:inception_lower":"1987-04-01",
    "date:inception_upper":"1987-04-30",
    "iso:country":"GB",
    "wof:name":"CM3 5ZX",
    "wof:placetype":"postalcode"
},
  "geometry": {"coordinates":[0.608687,51.639866],"type":"Point"}
}