{
  "type": "Feature",
  "properties": {
    "iso:country":"GB",
    "wof:name":"CM3 5ZX",
    "wof:placetype":"postalcode"
},
  "geometry": {"coordinates":[0.60868666763826,51.6398661924993],"type":"Point"}
}