{
  "type": "Feature",
  "properties": {
    "iso:country":"GB",
    "wof:name":"BS23 2AD",
    "wof:placetype":"postalcode"
},
  "geometry": {"coordinates":[-2.98956445538924,51.35155059221582],"type":"Point"}
}