{
  "type": "Feature",
  "properties": {
    "iso:country":"GB",
    "wof:name":"TR12 7NH",
    "wof:placetype":"postalcode"
},
  "geometry": {"coordinates":[-5.20440986976353,49.96865950041985],"type":"Point"}
}