{
  "type": "Feature",
  "properties": {
    "iso:country":"GB",
    "wof:name":"NP7 0PN",
    "wof:placetype":"postalcode"
},
  "geometry": {"coordinates":[-3.1229810660388,51.80391747406863],"type":"Point"}
}