{
  "type": "Feature",
  "properties": {
    "date:inception_lower": "1980-01-01",
    "date:inception_upper": "1980-01-01",
    "iso:country": "GB",
    "wof:name": "NP7 0PN",
    "wof:placetype": "postalcode"
  },
  "geometry": {"coordinates":[-3.122981,51.803917],"type":"Point"}
}
