{
  "type": "Feature",
  "properties": {
    "iso:country": "GB",
    "wof:name": "NP7 0PN",
    "wof:placetype": "postalcode"
  },
  "geometry": {"coordinates":[-3.122981,51.803917],"type":"Point"}
}
