{
  "type": "Feature",
  "properties": {
    "date:inception_lower":"1980-01-01",
    "date:inception_upper":"1980-01-31",
    "iso:country":"GB",
    "wof:name":"PL11 2PD",
    "wof:placetype":"postalcode"
},
  "geometry": {"coordinates":[-4.224943,50.37363],"type":"Point"}
}