{
  "type": "Feature",
  "properties": {
    "iso:country": "GB",
    "wof:name": "PL11 2PD",
    "wof:placetype": "postalcode"
  },
  "geometry": {"coordinates":[-4.224943,50.37363],"type":"Point"}
}
