{
  "type": "Feature",
  "properties": {
    "iso:country":"GB",
    "wof:name":"PL11 2PD",
    "wof:placetype":"postalcode"
},
  "geometry": {"coordinates":[-4.22494259578508,50.37362971748784],"type":"Point"}
}