{
  "type": "Feature",
  "properties": {
    "date:inception_lower": "2021-08-01",
    "date:inception_upper": "2021-08-01",
    "iso:country": "GB",
    "wof:name": "CO3 8DT",
    "wof:placetype": "postalcode"
  },
  "geometry": {"coordinates":[0.821647,51.888841],"type":"Point"}
}
