{
  "type": "Feature",
  "properties": {
    "iso:country": "GB",
    "wof:name": "MK41 7DE",
    "wof:placetype": "postalcode"
  },
  "geometry": {"coordinates":[-0.460271,52.15908],"type":"Point"}
}
