{
  "type": "Feature",
  "properties": {
    "iso:country": "GB",
    "wof:name": "CV2 3JU",
    "wof:placetype": "postalcode"
  },
  "geometry": {"coordinates":[-1.468878,52.425541],"type":"Point"}
}
