{
  "type": "Feature",
  "properties": {
    "iso:country":"GB",
    "wof:name":"CV2 3JU",
    "wof:placetype":"postalcode"
},
  "geometry": {"coordinates":[-1.46887811537873,52.42554093460915],"type":"Point"}
}