{
  "type": "Feature",
  "properties": {
    "iso:country":"GB",
    "wof:name":"HA1 4EX",
    "wof:placetype":"postalcode"
},
  "geometry": {"coordinates":[-0.35176184583074,51.58189779783853],"type":"Point"}
}