{
  "type": "Feature",
  "properties": {
    "iso:country": "GB",
    "wof:name": "HA1 4EX",
    "wof:placetype": "postalcode"
  },
  "geometry": {"coordinates":[-0.351762,51.581898],"type":"Point"}
}
