{
  "type": "Feature",
  "properties": {
    "iso:country": "GB",
    "wof:name": "DG1 1AG",
    "wof:placetype": "postalcode"
  },
  "geometry": {"coordinates":[-3.598957,55.1866],"type":"Point"}
}
