{
  "type": "Feature",
  "properties": {
    "iso:country":"GB",
    "wof:name":"DN22 7UJ",
    "wof:placetype":"postalcode"
},
  "geometry": {"coordinates":[-0.94373974180737,53.30669291055056],"type":"Point"}
}