{
  "type": "Feature",
  "properties": {
    "iso:country":"GB",
    "wof:name":"GL12 8DF",
    "wof:placetype":"postalcode"
},
  "geometry": {"coordinates":[-2.46037272480925,51.63557824048593],"type":"Point"}
}