{
  "type": "Feature",
  "properties": {
    "iso:country":"GB",
    "wof:name":"WA3 2AY",
    "wof:placetype":"postalcode"
},
  "geometry": {"coordinates":[-2.56950614411731,53.46880960456824],"type":"Point"}
}