{
  "type": "Feature",
  "properties": {
    "date:inception_lower":"2001-06-01",
    "date:inception_upper":"2001-06-30",
    "iso:country":"GB",
    "wof:name":"ME13 0ET",
    "wof:placetype":"postalcode"
},
  "geometry": {"coordinates":[0.86237,51.266735],"type":"Point"}
}