{
  "type": "Feature",
  "properties": {
    "iso:country": "GB",
    "wof:name": "ME13 0ET",
    "wof:placetype": "postalcode"
  },
  "geometry": {"coordinates":[0.86237,51.266735],"type":"Point"}
}
