{
  "type": "Feature",
  "properties": {
    "iso:country": "GB",
    "wof:name": "SK6 2JY",
    "wof:placetype": "postalcode"
  },
  "geometry": {"coordinates":[-2.111212,53.41792],"type":"Point"}
}
