{
  "type": "Feature",
  "properties": {
    "iso:country":"GB",
    "wof:name":"SK6 2JY",
    "wof:placetype":"postalcode"
},
  "geometry": {"coordinates":[-2.11121170620369,53.41791971568498],"type":"Point"}
}