{
  "type": "Feature",
  "properties": {
    "date:inception_lower":"1980-01-01",
    "date:inception_upper":"1980-01-31",
    "iso:country":"GB",
    "wof:name":"SK6 2JY",
    "wof:placetype":"postalcode"
},
  "geometry": {"coordinates":[-2.111212,53.41792],"type":"Point"}
}