{
  "type": "Feature",
  "properties": {
    "iso:country":"GB",
    "wof:name":"IP12 4LL",
    "wof:placetype":"postalcode"
},
  "geometry": {"coordinates":[1.30093990443076,52.09761853212643],"type":"Point"}
}