{
  "type": "Feature",
  "properties": {
    "iso:country":"GB",
    "wof:name":"SW9 6BU",
    "wof:placetype":"postalcode"
},
  "geometry": {"coordinates":[-0.11141707280206,51.48043755302617],"type":"Point"}
}