{
  "type": "Feature",
  "properties": {
    "iso:country":"GB",
    "wof:name":"SG3 6QZ",
    "wof:placetype":"postalcode"
},
  "geometry": {"coordinates":[-0.16654967045576,51.86358238914257],"type":"Point"}
}