{
  "type": "Feature",
  "properties": {
    "date:inception_lower": "1980-01-01",
    "date:inception_upper": "1980-01-01",
    "iso:country": "GB",
    "wof:name": "ME17 2PB",
    "wof:placetype": "postalcode"
  },
  "geometry": {"coordinates":[0.680996,51.22411],"type":"Point"}
}
