{
  "type": "Feature",
  "properties": {
    "iso:country": "GB",
    "wof:name": "ME17 2PB",
    "wof:placetype": "postalcode"
  },
  "geometry": {"coordinates":[0.680996,51.22411],"type":"Point"}
}
