{
  "type": "Feature",
  "properties": {
    "iso:country":"GB",
    "wof:name":"SO52 9DQ",
    "wof:placetype":"postalcode"
},
  "geometry": {"coordinates":[-1.44485010440516,50.98098650654899],"type":"Point"}
}