{
  "type": "Feature",
  "properties": {
    "iso:country":"GB",
    "wof:name":"WF9 3DE",
    "wof:placetype":"postalcode"
},
  "geometry": {"coordinates":[-1.31217361531638,53.5975170850347],"type":"Point"}
}