{
  "type": "Feature",
  "properties": {
    "iso:country": "GB",
    "wof:name": "WF9 3DE",
    "wof:placetype": "postalcode"
  },
  "geometry": {"coordinates":[-1.312174,53.597517],"type":"Point"}
}
