{
  "type": "Feature",
  "properties": {
    "iso:country":"GB",
    "wof:name":"PE11 4TR",
    "wof:placetype":"postalcode"
},
  "geometry": {"coordinates":[-0.20525841100136,52.90154220370309],"type":"Point"}
}