{
  "type": "Feature",
  "properties": {
    "date:inception_lower": "1980-01-01",
    "date:inception_upper": "1980-01-01",
    "iso:country": "GB",
    "wof:name": "LL49 9YR",
    "wof:placetype": "postalcode"
  },
  "geometry": {"coordinates":[-4.163224,52.913042],"type":"Point"}
}
