{
  "type": "Feature",
  "properties": {
    "iso:country":"GB",
    "wof:name":"LL49 9YR",
    "wof:placetype":"postalcode"
},
  "geometry": {"coordinates":[-4.16322449547154,52.91304208003226],"type":"Point"}
}