{
  "type": "Feature",
  "properties": {
    "iso:country":"GB",
    "wof:name":"SG11 2JL",
    "wof:placetype":"postalcode"
},
  "geometry": {"coordinates":[0.09486395643967,51.90443052854123],"type":"Point"}
}