{
  "type": "Feature",
  "properties": {
    "iso:country":"GB",
    "wof:name":"GL7 5DX",
    "wof:placetype":"postalcode"
},
  "geometry": {"coordinates":[-1.91443445021039,51.72454637264995],"type":"Point"}
}