{
  "type": "Feature",
  "properties": {
    "iso:country": "GB",
    "wof:name": "GL7 5DX",
    "wof:placetype": "postalcode"
  },
  "geometry": {"coordinates":[-1.914434,51.724546],"type":"Point"}
}
