{
  "type": "Feature",
  "properties": {
    "iso:country":"GB",
    "wof:name":"CM3 5GU",
    "wof:placetype":"postalcode"
},
  "geometry": {"coordinates":[0.6242295715397,51.64445707192082],"type":"Point"}
}