{
  "type": "Feature",
  "properties": {
    "iso:country":"GB",
    "wof:name":"KT22 9DA",
    "wof:placetype":"postalcode"
},
  "geometry": {"coordinates":[-0.33847582730052,51.28865705854641],"type":"Point"}
}