{
  "type": "Feature",
  "properties": {
    "iso:country":"GB",
    "wof:name":"SE6 4PH",
    "wof:placetype":"postalcode"
},
  "geometry": {"coordinates":[-0.02860359179483,51.44108922293857],"type":"Point"}
}