{
  "type": "Feature",
  "properties": {
    "iso:country":"GB",
    "wof:name":"ST2 0NN",
    "wof:placetype":"postalcode"
},
  "geometry": {"coordinates":[-2.12660611592581,53.01826955563456],"type":"Point"}
}