{
  "type": "Feature",
  "properties": {
    "iso:country":"GB",
    "wof:name":"CT9 5DJ",
    "wof:placetype":"postalcode"
},
  "geometry": {"coordinates":[1.36499475415527,51.38454040383947],"type":"Point"}
}