{
  "type": "Feature",
  "properties": {
    "iso:country": "GB",
    "wof:name": "CT9 5DJ",
    "wof:placetype": "postalcode"
  },
  "geometry": {"coordinates":[1.364995,51.38454],"type":"Point"}
}
