{
  "type": "Feature",
  "properties": {
    "iso:country": "GB",
    "wof:name": "BN15 9JF",
    "wof:placetype": "postalcode"
  },
  "geometry": {"coordinates":[-0.332328,50.827789],"type":"Point"}
}
