{
  "type": "Feature",
  "properties": {
    "iso:country":"GB",
    "wof:name":"RG8 8ND",
    "wof:placetype":"postalcode"
},
  "geometry": {"coordinates":[-1.12490029420498,51.48717222455083],"type":"Point"}
}