{
  "type": "Feature",
  "properties": {
    "iso:country":"GB",
    "wof:name":"NE2 1YF",
    "wof:placetype":"postalcode"
},
  "geometry": {"coordinates":[-1.60206144398544,54.97991676480845],"type":"Point"}
}