{
  "type": "Feature",
  "properties": {
    "date:inception_lower":"1980-01-01",
    "date:inception_upper":"1980-01-31",
    "iso:country":"GB",
    "wof:name":"NE2 1YF",
    "wof:placetype":"postalcode"
},
  "geometry": {"coordinates":[-1.602061,54.979917],"type":"Point"}
}