{
  "type": "Feature",
  "properties": {
    "date:inception_lower": "1980-01-01",
    "date:inception_upper": "1980-01-01",
    "iso:country": "GB",
    "wof:name": "S5 6HA",
    "wof:placetype": "postalcode"
  },
  "geometry": {"coordinates":[-1.445068,53.41956],"type":"Point"}
}
