{
  "type": "Feature",
  "properties": {
    "iso:country": "GB",
    "wof:name": "CF64 1SB",
    "wof:placetype": "postalcode"
  },
  "geometry": {"coordinates":[-3.185315,51.446353],"type":"Point"}
}
