{
  "type": "Feature",
  "properties": {
    "iso:country":"GB",
    "wof:name":"CF64 1SB",
    "wof:placetype":"postalcode"
},
  "geometry": {"coordinates":[-3.18531464195055,51.44635255657128],"type":"Point"}
}