{
  "type": "Feature",
  "properties": {
    "date:inception_lower":"1997-06-01",
    "date:inception_upper":"1997-06-30",
    "iso:country":"GB",
    "wof:name":"CF64 1SB",
    "wof:placetype":"postalcode"
},
  "geometry": {"coordinates":[-3.185315,51.446353],"type":"Point"}
}