{
  "type": "Feature",
  "properties": {
    "iso:country": "GB",
    "wof:name": "M3 4BA",
    "wof:placetype": "postalcode"
  },
  "geometry": {"coordinates":[-2.262702,53.475279],"type":"Point"}
}
