{
  "type": "Feature",
  "properties": {
    "iso:country":"GB",
    "wof:name":"SR5 4JF",
    "wof:placetype":"postalcode"
},
  "geometry": {"coordinates":[-1.45338082973295,54.92904316229249],"type":"Point"}
}