{
  "type": "Feature",
  "properties": {
    "iso:country":"GB",
    "wof:name":"M40 2TB",
    "wof:placetype":"postalcode"
},
  "geometry": {"coordinates":[-2.1841696221469,53.49772796267808],"type":"Point"}
}