{
  "type": "Feature",
  "properties": {
    "iso:country": "GB",
    "wof:name": "M40 2TB",
    "wof:placetype": "postalcode"
  },
  "geometry": {"coordinates":[-2.18417,53.497728],"type":"Point"}
}
