{
  "type": "Feature",
  "properties": {
    "iso:country":"GB",
    "wof:name":"NE63 8JQ",
    "wof:placetype":"postalcode"
},
  "geometry": {"coordinates":[-1.5734317124372,55.17339892275933],"type":"Point"}
}