{
  "type": "Feature",
  "properties": {
    "iso:country": "GB",
    "wof:name": "PA37 1RZ",
    "wof:placetype": "postalcode"
  },
  "geometry": {"coordinates":[-5.385731,56.507551],"type":"Point"}
}
