{
  "type": "Feature",
  "properties": {
    "date:inception_lower":"1980-01-01",
    "date:inception_upper":"1980-01-31",
    "iso:country":"GB",
    "wof:name":"PA37 1RZ",
    "wof:placetype":"postalcode"
},
  "geometry": {"coordinates":[-5.385731,56.507551],"type":"Point"}
}