{
  "type": "Feature",
  "properties": {
    "iso:country":"GB",
    "wof:name":"PA37 1RZ",
    "wof:placetype":"postalcode"
},
  "geometry": {"coordinates":[-5.38573086049819,56.50755148772093],"type":"Point"}
}