{
  "type": "Feature",
  "properties": {
    "iso:country": "GB",
    "wof:name": "G72 9AY",
    "wof:placetype": "postalcode"
  },
  "geometry": {"coordinates":[-4.11005,55.783877],"type":"Point"}
}
