{
  "type": "Feature",
  "properties": {
    "iso:country":"GB",
    "wof:name":"BA11 4HG",
    "wof:placetype":"postalcode"
},
  "geometry": {"coordinates":[-2.33689234913509,51.22544099168236],"type":"Point"}
}