{
  "type": "Feature",
  "properties": {
    "iso:country": "GB",
    "wof:name": "DE56 0NZ",
    "wof:placetype": "postalcode"
  },
  "geometry": {"coordinates":[-1.430032,53.006707],"type":"Point"}
}
