{
  "type": "Feature",
  "properties": {
    "iso:country":"GB",
    "wof:name":"RM15 5RD",
    "wof:placetype":"postalcode"
},
  "geometry": {"coordinates":[0.28435151066626,51.50373693655198],"type":"Point"}
}