{
  "type": "Feature",
  "properties": {
    "iso:country": "GB",
    "wof:name": "M23 1PG",
    "wof:placetype": "postalcode"
  },
  "geometry": {"coordinates":[-2.274567,53.392254],"type":"Point"}
}
