{
  "type": "Feature",
  "properties": {
    "iso:country":"GB",
    "wof:name":"M23 1PG",
    "wof:placetype":"postalcode"
},
  "geometry": {"coordinates":[-2.27456726036784,53.39225381351704],"type":"Point"}
}