{
  "type": "Feature",
  "properties": {
    "date:inception_lower": "2016-11-01",
    "date:inception_upper": "2016-11-01",
    "iso:country": "GB",
    "wof:name": "EC3A 5AF",
    "wof:placetype": "postalcode"
  },
  "geometry": {"coordinates":[-0.078458,51.514256],"type":"Point"}
}
