{
  "type": "Feature",
  "properties": {
    "iso:country": "GB",
    "wof:name": "ST5 1AR",
    "wof:placetype": "postalcode"
  },
  "geometry": {"coordinates":[-2.222717,53.011242],"type":"Point"}
}
