{
  "type": "Feature",
  "properties": {
    "iso:country":"GB",
    "wof:name":"SN10 5UB",
    "wof:placetype":"postalcode"
},
  "geometry": {"coordinates":[-2.06404015981366,51.28165838289384],"type":"Point"}
}