{
  "type": "Feature",
  "properties": {
    "iso:country": "GB",
    "wof:name": "SN10 5UB",
    "wof:placetype": "postalcode"
  },
  "geometry": {"coordinates":[-2.062568,51.268644],"type":"Point"}
}
