{
  "type": "Feature",
  "properties": {
    "iso:country":"GB",
    "wof:name":"DL10 6TE",
    "wof:placetype":"postalcode"
},
  "geometry": {"coordinates":[-1.61477703370531,54.39340550245508],"type":"Point"}
}