{
  "type": "Feature",
  "properties": {
    "iso:country":"GB",
    "wof:name":"CH2 3LF",
    "wof:placetype":"postalcode"
},
  "geometry": {"coordinates":[-2.86133053968822,53.202624981307],"type":"Point"}
}