{
  "type": "Feature",
  "properties": {
    "date:inception_lower": "1980-01-01",
    "date:inception_upper": "1980-01-01",
    "iso:country": "GB",
    "wof:name": "CH2 3LF",
    "wof:placetype": "postalcode"
  },
  "geometry": {"coordinates":[-2.86133,53.202625],"type":"Point"}
}
