{
  "type": "Feature",
  "properties": {
    "iso:country":"GB",
    "wof:name":"CF42 5SE",
    "wof:placetype":"postalcode"
},
  "geometry": {"coordinates":[-3.55262550047465,51.68775364521498],"type":"Point"}
}