{
  "type": "Feature",
  "properties": {
    "date:inception_lower": "1980-01-01",
    "date:inception_upper": "1980-01-01",
    "iso:country": "GB",
    "wof:name": "BN20 8DD",
    "wof:placetype": "postalcode"
  },
  "geometry": {"coordinates":[0.256442,50.765857],"type":"Point"}
}
