{
  "type": "Feature",
  "properties": {
    "iso:country":"GB",
    "wof:name":"CT5 3HL",
    "wof:placetype":"postalcode"
},
  "geometry": {"coordinates":[1.05457924059062,51.35663184525639],"type":"Point"}
}