{
  "type": "Feature",
  "properties": {
    "iso:country":"GB",
    "wof:name":"DN14 6AL",
    "wof:placetype":"postalcode"
},
  "geometry": {"coordinates":[-0.88226575310338,53.7068937133442],"type":"Point"}
}