{
  "type": "Feature",
  "properties": {
    "iso:country":"GB",
    "wof:name":"E15 1HB",
    "wof:placetype":"postalcode"
},
  "geometry": {"coordinates":[0.00752294845854,51.547525250056],"type":"Point"}
}