{
  "type": "Feature",
  "properties": {
    "date:inception_lower": "2019-12-01",
    "date:inception_upper": "2019-12-01",
    "iso:country": "GB",
    "wof:name": "G43 2AY",
    "wof:placetype": "postalcode"
  },
  "geometry": {"coordinates":[-4.266134,55.821936],"type":"Point"}
}
