{
  "type": "Feature",
  "properties": {
    "iso:country":"GB",
    "wof:name":"WA9 3ST",
    "wof:placetype":"postalcode"
},
  "geometry": {"coordinates":[-2.71298733234554,53.4342598746024],"type":"Point"}
}