{
  "type": "Feature",
  "properties": {
    "iso:country": "GB",
    "wof:name": "WA9 3ST",
    "wof:placetype": "postalcode"
  },
  "geometry": {"coordinates":[-2.712987,53.43426],"type":"Point"}
}
