{
  "type": "Feature",
  "properties": {
    "iso:country":"GB",
    "wof:name":"E1 4PJ",
    "wof:placetype":"postalcode"
},
  "geometry": {"coordinates":[-0.03690071947102,51.52338551714212],"type":"Point"}
}