{
  "type": "Feature",
  "properties": {
    "date:inception_lower": "1983-03-01",
    "date:inception_upper": "1983-03-01",
    "iso:country": "GB",
    "wof:name": "E1 4PJ",
    "wof:placetype": "postalcode"
  },
  "geometry": {"coordinates":[-0.036901,51.523386],"type":"Point"}
}
