{
  "type": "Feature",
  "properties": {
    "iso:country": "GB",
    "wof:name": "CO12 4AJ",
    "wof:placetype": "postalcode"
  },
  "geometry": {"coordinates":[1.270616,51.935165],"type":"Point"}
}
