{
  "type": "Feature",
  "properties": {
    "iso:country":"GB",
    "wof:name":"GU16 7HF",
    "wof:placetype":"postalcode"
},
  "geometry": {"coordinates":[-0.74797114581856,51.314343612519],"type":"Point"}
}