{
  "type": "Feature",
  "properties": {
    "date:inception_lower": "2000-10-01",
    "date:inception_upper": "2000-10-01",
    "iso:country": "GB",
    "wof:name": "GU16 7HF",
    "wof:placetype": "postalcode"
  },
  "geometry": {"coordinates":[-0.747971,51.314344],"type":"Point"}
}
