{
  "type": "Feature",
  "properties": {
    "iso:country":"GB",
    "wof:name":"HA2 7QE",
    "wof:placetype":"postalcode"
},
  "geometry": {"coordinates":[-0.3675600790759,51.58408788148253],"type":"Point"}
}