{
  "type": "Feature",
  "properties": {
    "iso:country": "GB",
    "wof:name": "ML1 3HW",
    "wof:placetype": "postalcode"
  },
  "geometry": {"coordinates":[-4.01324,55.788821],"type":"Point"}
}
