{
  "type": "Feature",
  "properties": {
    "iso:country":"GB",
    "wof:name":"EN7 6TW",
    "wof:placetype":"postalcode"
},
  "geometry": {"coordinates":[-0.06431664662064,51.71761044710757],"type":"Point"}
}