{
  "type": "Feature",
  "properties": {
    "date:inception_lower":"1987-04-01",
    "date:inception_upper":"1987-04-30",
    "iso:country":"GB",
    "wof:name":"EN7 6TW",
    "wof:placetype":"postalcode"
},
  "geometry": {"coordinates":[-0.064317,51.71761],"type":"Point"}
}