{
  "type": "Feature",
  "properties": {
    "iso:country":"GB",
    "wof:name":"TS25 3BX",
    "wof:placetype":"postalcode"
},
  "geometry": {"coordinates":[-1.22222726375243,54.65976397278278],"type":"Point"}
}