{
  "type": "Feature",
  "properties": {
    "iso:country": "GB",
    "wof:name": "YO8 6LN",
    "wof:placetype": "postalcode"
  },
  "geometry": {"coordinates":[-0.917518,53.816086],"type":"Point"}
}
