{
  "type": "Feature",
  "properties": {
    "iso:country":"GB",
    "wof:name":"YO8 6LN",
    "wof:placetype":"postalcode"
},
  "geometry": {"coordinates":[-0.91751795450568,53.81608596256842],"type":"Point"}
}