{
  "type": "Feature",
  "properties": {
    "iso:country":"GB",
    "wof:name":"TW15 1EL",
    "wof:placetype":"postalcode"
},
  "geometry": {"coordinates":[-0.44450304641138,51.43104256910233],"type":"Point"}
}