{
  "type": "Feature",
  "properties": {
    "date:inception_lower": "2020-06-01",
    "date:inception_upper": "2020-06-01",
    "iso:country": "GB",
    "wof:name": "HG3 2PA",
    "wof:placetype": "postalcode"
  },
  "geometry": {"coordinates":[-1.693977,54.031744],"type":"Point"}
}
