{
  "type": "Feature",
  "properties": {
    "iso:country": "GB",
    "wof:name": "CF32 7RA",
    "wof:placetype": "postalcode"
  },
  "geometry": {"coordinates":[-3.540612,51.624509],"type":"Point"}
}
