{
  "type": "Feature",
  "properties": {
    "iso:country":"GB",
    "wof:name":"CF32 7RA",
    "wof:placetype":"postalcode"
},
  "geometry": {"coordinates":[-3.54061238586445,51.62450948586488],"type":"Point"}
}