{
  "type": "Feature",
  "properties": {
    "iso:country":"GB",
    "wof:name":"NW10 5XJ",
    "wof:placetype":"postalcode"
},
  "geometry": {"coordinates":[-0.23187792438029,51.53203487269833],"type":"Point"}
}