{
  "type": "Feature",
  "properties": {
    "iso:country":"GB",
    "wof:name":"LD1 6LB",
    "wof:placetype":"postalcode"
},
  "geometry": {"coordinates":[-3.44082450520456,52.21284060971563],"type":"Point"}
}