{
  "type": "Feature",
  "properties": {
    "date:inception_lower": "1980-01-01",
    "date:inception_upper": "1980-01-01",
    "iso:country": "GB",
    "wof:name": "HP8 4SJ",
    "wof:placetype": "postalcode"
  },
  "geometry": {"coordinates":[-0.556148,51.65233],"type":"Point"}
}
