{
  "type": "Feature",
  "properties": {
    "iso:country":"GB",
    "wof:name":"L35 6NN",
    "wof:placetype":"postalcode"
},
  "geometry": {"coordinates":[-2.7506469392579,53.40687406105927],"type":"Point"}
}