{
  "type": "Feature",
  "properties": {
    "date:inception_lower": "2000-10-01",
    "date:inception_upper": "2000-10-01",
    "iso:country": "GB",
    "wof:name": "WD23 3BX",
    "wof:placetype": "postalcode"
  },
  "geometry": {"coordinates":[-0.359043,51.64258],"type":"Point"}
}
