{
  "type": "Feature",
  "properties": {
    "iso:country":"GB",
    "wof:name":"B24 0GA",
    "wof:placetype":"postalcode"
},
  "geometry": {"coordinates":[-1.81615999627077,52.5212904205197],"type":"Point"}
}