{
  "type": "Feature",
  "properties": {
    "date:inception_lower": "1980-01-01",
    "date:inception_upper": "1980-01-01",
    "iso:country": "GB",
    "wof:name": "SK11 6EG",
    "wof:placetype": "postalcode"
  },
  "geometry": {"coordinates":[-2.129809,53.25997],"type":"Point"}
}
