{
  "type": "Feature",
  "properties": {
    "iso:country":"GB",
    "wof:name":"ML11 0BD",
    "wof:placetype":"postalcode"
},
  "geometry": {"coordinates":[-3.87643666448385,55.63046244112917],"type":"Point"}
}