{
  "type": "Feature",
  "properties": {
    "iso:country":"GB",
    "wof:name":"DE4 5GW",
    "wof:placetype":"postalcode"
},
  "geometry": {"coordinates":[-1.47919763637875,53.10446505589898],"type":"Point"}
}