{
  "type": "Feature",
  "properties": {
    "iso:country":"GB",
    "wof:name":"BN27 4BP",
    "wof:placetype":"postalcode"
},
  "geometry": {"coordinates":[0.21817551868643,50.88888044351446],"type":"Point"}
}