{
  "type": "Feature",
  "properties": {
    "date:inception_lower": "2000-12-01",
    "date:inception_upper": "2000-12-01",
    "iso:country": "GB",
    "wof:name": "SW2 2YN",
    "wof:placetype": "postalcode"
  },
  "geometry": {"coordinates":[-0.112721,51.44885],"type":"Point"}
}
