{
  "type": "Feature",
  "properties": {
    "iso:country":"GB",
    "wof:name":"HP9 2TH",
    "wof:placetype":"postalcode"
},
  "geometry": {"coordinates":[-0.65186487501374,51.62207348408965],"type":"Point"}
}