{
  "type": "Feature",
  "properties": {
    "iso:country":"GB",
    "wof:name":"M14 5TE",
    "wof:placetype":"postalcode"
},
  "geometry": {"coordinates":[-2.22574438925563,53.45798152946843],"type":"Point"}
}