{
  "type": "Feature",
  "properties": {
    "iso:country": "GB",
    "wof:name": "DY3 2PU",
    "wof:placetype": "postalcode"
  },
  "geometry": {"coordinates":[-2.127098,52.512389],"type":"Point"}
}
