{
  "type": "Feature",
  "properties": {
    "date:inception_lower": "2009-11-01",
    "date:inception_upper": "2009-11-01",
    "iso:country": "GB",
    "wof:name": "BN21 2YH",
    "wof:placetype": "postalcode"
  },
  "geometry": {"coordinates":[0.271113,50.784738],"type":"Point"}
}
