{
  "type": "Feature",
  "properties": {
    "iso:country":"GB",
    "wof:name":"PO22 7LG",
    "wof:placetype":"postalcode"
},
  "geometry": {"coordinates":[-0.64225174304817,50.7887394273452],"type":"Point"}
}