{
  "type": "Feature",
  "properties": {
    "iso:country": "GB",
    "wof:name": "NW9 8RD",
    "wof:placetype": "postalcode"
  },
  "geometry": {"coordinates":[-0.265373,51.575959],"type":"Point"}
}
