{
  "type": "Feature",
  "properties": {
    "iso:country":"GB",
    "wof:name":"NW9 8RD",
    "wof:placetype":"postalcode"
},
  "geometry": {"coordinates":[-0.26537278059456,51.57595879142441],"type":"Point"}
}