{
  "type": "Feature",
  "properties": {
    "iso:country":"GB",
    "wof:name":"NW11 8PR",
    "wof:placetype":"postalcode"
},
  "geometry": {"coordinates":[-0.20743321056884,51.57109546982105],"type":"Point"}
}