{
  "type": "Feature",
  "properties": {
    "date:inception_lower": "1996-06-01",
    "date:inception_upper": "1996-06-01",
    "iso:country": "GB",
    "wof:name": "LE11 4QX",
    "wof:placetype": "postalcode"
  },
  "geometry": {"coordinates":[-1.24422,52.778632],"type":"Point"}
}
