{
  "type": "Feature",
  "properties": {
    "iso:country":"GB",
    "wof:name":"LE11 4QX",
    "wof:placetype":"postalcode"
},
  "geometry": {"coordinates":[-1.24421959897252,52.77863191987529],"type":"Point"}
}