{
  "type": "Feature",
  "properties": {
    "date:inception_lower":"1980-01-01",
    "date:inception_upper":"1980-01-31",
    "iso:country":"GB",
    "wof:name":"RH13 8NR",
    "wof:placetype":"postalcode"
},
  "geometry": {"coordinates":[-0.359444,50.95874],"type":"Point"}
}