{
  "type": "Feature",
  "properties": {
    "iso:country": "GB",
    "wof:name": "S72 8HE",
    "wof:placetype": "postalcode"
  },
  "geometry": {"coordinates":[-1.417695,53.576046],"type":"Point"}
}
