{
  "type": "Feature",
  "properties": {
    "iso:country":"GB",
    "wof:name":"L31 5JQ",
    "wof:placetype":"postalcode"
},
  "geometry": {"coordinates":[-2.94055666704004,53.50072951723308],"type":"Point"}
}