{
  "type": "Feature",
  "properties": {
    "iso:country":"GB",
    "wof:name":"BA1 3DW",
    "wof:placetype":"postalcode"
},
  "geometry": {"coordinates":[-2.38452840184977,51.38405346334928],"type":"Point"}
}