{
  "type": "Feature",
  "properties": {
    "iso:country":"GB",
    "wof:name":"EH12 6AU",
    "wof:placetype":"postalcode"
},
  "geometry": {"coordinates":[-3.23653976979744,55.94719853463022],"type":"Point"}
}