{
  "type": "Feature",
  "properties": {
    "iso:country": "GB",
    "wof:name": "B30 2HG",
    "wof:placetype": "postalcode"
  },
  "geometry": {"coordinates":[-1.929119,52.424257],"type":"Point"}
}
