{
  "type": "Feature",
  "properties": {
    "iso:country":"GB",
    "wof:name":"EX10 9NU",
    "wof:placetype":"postalcode"
},
  "geometry": {"coordinates":[-3.22879568854273,50.7015459025429],"type":"Point"}
}