{
  "type": "Feature",
  "properties": {
    "iso:country": "GB",
    "wof:name": "EX10 9NU",
    "wof:placetype": "postalcode"
  },
  "geometry": {"coordinates":[-3.228796,50.701546],"type":"Point"}
}
