{
  "type": "Feature",
  "properties": {
    "iso:country": "GB",
    "wof:name": "E8 1AY",
    "wof:placetype": "postalcode"
  },
  "geometry": {"coordinates":[-0.060687,51.550498],"type":"Point"}
}
