{
  "type": "Feature",
  "properties": {
    "iso:country":"GB",
    "wof:name":"M29 8PA",
    "wof:placetype":"postalcode"
},
  "geometry": {"coordinates":[-2.44004775910251,53.51427224168295],"type":"Point"}
}