{
  "type": "Feature",
  "properties": {
    "iso:country": "GB",
    "wof:name": "YO12 7BL",
    "wof:placetype": "postalcode"
  },
  "geometry": {"coordinates":[-0.410993,54.280822],"type":"Point"}
}
