{
  "type": "Feature",
  "properties": {
    "date:inception_lower":"1980-01-01",
    "date:inception_upper":"1980-01-31",
    "iso:country":"GB",
    "wof:name":"L26 0TP",
    "wof:placetype":"postalcode"
},
  "geometry": {"coordinates":[-2.827154,53.366566],"type":"Point"}
}