{
  "type": "Feature",
  "properties": {
    "iso:country":"GB",
    "wof:name":"L26 0TP",
    "wof:placetype":"postalcode"
},
  "geometry": {"coordinates":[-2.82715379469137,53.36656584729549],"type":"Point"}
}