{
  "type": "Feature",
  "properties": {
    "date:inception_lower": "2020-11-01",
    "date:inception_upper": "2020-11-01",
    "iso:country": "GB",
    "wof:name": "BS3 1FW",
    "wof:placetype": "postalcode"
  },
  "geometry": {"coordinates":[-2.596183,51.442565],"type":"Point"}
}
