{
  "type": "Feature",
  "properties": {
    "iso:country":"GB",
    "wof:name":"G13 1HS",
    "wof:placetype":"postalcode"
},
  "geometry": {"coordinates":[-4.32375851339988,55.89006075576472],"type":"Point"}
}