{
  "type": "Feature",
  "properties": {
    "date:inception_lower":"1980-01-01",
    "date:inception_upper":"1980-01-31",
    "iso:country":"GB",
    "wof:name":"G13 1HS",
    "wof:placetype":"postalcode"
},
  "geometry": {"coordinates":[-4.323758,55.890061],"type":"Point"}
}