{
  "type": "Feature",
  "properties": {
    "iso:country": "GB",
    "wof:name": "CO10 5NF",
    "wof:placetype": "postalcode"
  },
  "geometry": {"coordinates":[0.80406,51.997443],"type":"Point"}
}
