{
  "type": "Feature",
  "properties": {
    "iso:country": "GB",
    "wof:name": "NR34 0EX",
    "wof:placetype": "postalcode"
  },
  "geometry": {"coordinates":[1.565901,52.504015],"type":"Point"}
}
