{
  "type": "Feature",
  "properties": {
    "iso:country":"GB",
    "wof:name":"NR34 0EX",
    "wof:placetype":"postalcode"
},
  "geometry": {"coordinates":[1.5659004853334,52.50401525167874],"type":"Point"}
}