{
  "type": "Feature",
  "properties": {
    "date:inception_lower":"1980-01-01",
    "date:inception_upper":"1980-01-31",
    "iso:country":"GB",
    "wof:name":"NR34 0EX",
    "wof:placetype":"postalcode"
},
  "geometry": {"coordinates":[1.565901,52.504015],"type":"Point"}
}