{
  "type": "Feature",
  "properties": {
    "iso:country": "GB",
    "wof:name": "LU1 1UG",
    "wof:placetype": "postalcode"
  },
  "geometry": {"coordinates":[-0.452358,51.884],"type":"Point"}
}
