{
  "type": "Feature",
  "properties": {
    "date:inception_lower":"1980-01-01",
    "date:inception_upper":"1980-01-31",
    "iso:country":"GB",
    "wof:name":"HR5 3EF",
    "wof:placetype":"postalcode"
},
  "geometry": {"coordinates":[-3.057591,52.207017],"type":"Point"}
}