{
  "type": "Feature",
  "properties": {
    "date:inception_lower": "1993-01-01",
    "date:inception_upper": "1993-01-01",
    "iso:country": "GB",
    "wof:name": "CW3 9JB",
    "wof:placetype": "postalcode"
  },
  "geometry": {"coordinates":[-2.33509,53.004587],"type":"Point"}
}
