{
  "type": "Feature",
  "properties": {
    "date:inception_lower": "2015-02-01",
    "date:inception_upper": "2015-02-01",
    "iso:country": "GB",
    "wof:name": "PA10 2BH",
    "wof:placetype": "postalcode"
  },
  "geometry": {"coordinates":[-4.531641,55.8299],"type":"Point"}
}
