{
  "type": "Feature",
  "properties": {
    "iso:country":"GB",
    "wof:name":"PA10 2BH",
    "wof:placetype":"postalcode"
},
  "geometry": {"coordinates":[-4.53164135016189,55.82990034555687],"type":"Point"}
}