{
  "type": "Feature",
  "properties": {
    "date:inception_lower": "2021-03-01",
    "date:inception_upper": "2021-03-01",
    "iso:country": "GB",
    "wof:name": "CF62 3FZ",
    "wof:placetype": "postalcode"
  },
  "geometry": {"coordinates":[-3.387914,51.389509],"type":"Point"}
}
