{
  "type": "Feature",
  "properties": {
    "iso:country":"GB",
    "wof:name":"S44 6SW",
    "wof:placetype":"postalcode"
},
  "geometry": {"coordinates":[-1.30348318129358,53.23379201895924],"type":"Point"}
}