{
  "type": "Feature",
  "properties": {
    "iso:country": "GB",
    "wof:name": "S44 6SW",
    "wof:placetype": "postalcode"
  },
  "geometry": {"coordinates":[-1.303483,53.233792],"type":"Point"}
}
