{
  "type": "Feature",
  "properties": {
    "iso:country":"GB",
    "wof:name":"GL2 7BL",
    "wof:placetype":"postalcode"
},
  "geometry": {"coordinates":[-2.37943504951203,51.7314625541594],"type":"Point"}
}