{
  "type": "Feature",
  "properties": {
    "date:inception_lower": "1980-01-01",
    "date:inception_upper": "1980-01-01",
    "iso:country": "GB",
    "wof:name": "GL2 7BL",
    "wof:placetype": "postalcode"
  },
  "geometry": {"coordinates":[-2.379435,51.731463],"type":"Point"}
}
