{
  "type": "Feature",
  "properties": {
    "iso:country":"GB",
    "wof:name":"CB24 8SJ",
    "wof:placetype":"postalcode"
},
  "geometry": {"coordinates":[0.12854279786681,52.29438717793869],"type":"Point"}
}