{
  "type": "Feature",
  "properties": {
    "date:inception_lower":"2006-09-01",
    "date:inception_upper":"2006-09-30",
    "iso:country":"GB",
    "wof:name":"CB24 8SJ",
    "wof:placetype":"postalcode"
},
  "geometry": {"coordinates":[0.128726,52.294597],"type":"Point"}
}