{
  "type": "Feature",
  "properties": {
    "iso:country":"GB",
    "wof:name":"B68 8RT",
    "wof:placetype":"postalcode"
},
  "geometry": {"coordinates":[-2.00521391043534,52.48960834065273],"type":"Point"}
}