{
  "type": "Feature",
  "properties": {
    "date:inception_lower": "2001-12-01",
    "date:inception_upper": "2001-12-01",
    "iso:country": "GB",
    "wof:name": "B68 8RT",
    "wof:placetype": "postalcode"
  },
  "geometry": {"coordinates":[-2.005214,52.489608],"type":"Point"}
}
