{
  "type": "Feature",
  "properties": {
    "iso:country":"GB",
    "wof:name":"AL2 3AR",
    "wof:placetype":"postalcode"
},
  "geometry": {"coordinates":[-0.36321275620673,51.72942900228065],"type":"Point"}
}