{
  "type": "Feature",
  "properties": {
    "date:inception_lower": "2000-06-01",
    "date:inception_upper": "2000-06-01",
    "iso:country": "GB",
    "wof:name": "PE28 3NS",
    "wof:placetype": "postalcode"
  },
  "geometry": {"coordinates":[0.007969,52.355114],"type":"Point"}
}
