{
  "type": "Feature",
  "properties": {
    "iso:country": "GB",
    "wof:name": "PE28 3NS",
    "wof:placetype": "postalcode"
  },
  "geometry": {"coordinates":[0.007944,52.355098],"type":"Point"}
}
