{
  "type": "Feature",
  "properties": {
    "iso:country":"GB",
    "wof:name":"B38 9AE",
    "wof:placetype":"postalcode"
},
  "geometry": {"coordinates":[-1.92722723084494,52.40339901670102],"type":"Point"}
}