{
  "type": "Feature",
  "properties": {
    "date:inception_lower":"1980-01-01",
    "date:inception_upper":"1980-01-31",
    "iso:country":"GB",
    "wof:name":"B38 9AE",
    "wof:placetype":"postalcode"
},
  "geometry": {"coordinates":[-1.927227,52.403399],"type":"Point"}
}