{
  "type": "Feature",
  "properties": {
    "date:inception_lower": "1997-06-01",
    "date:inception_upper": "1997-06-01",
    "iso:country": "GB",
    "wof:name": "DH1 3YD",
    "wof:placetype": "postalcode"
  },
  "geometry": {"coordinates":[-1.576646,54.76608],"type":"Point"}
}
