{
  "type": "Feature",
  "properties": {
    "iso:country": "GB",
    "wof:name": "DH1 3YD",
    "wof:placetype": "postalcode"
  },
  "geometry": {"coordinates":[-1.577508,54.765391],"type":"Point"}
}
