{
  "type": "Feature",
  "properties": {
    "date:inception_lower": "2021-08-01",
    "date:inception_upper": "2021-08-01",
    "iso:country": "GB",
    "wof:name": "NE12 7BG",
    "wof:placetype": "postalcode"
  },
  "geometry": {"coordinates":[-1.587077,55.037701],"type":"Point"}
}
