{
  "type": "Feature",
  "properties": {
    "iso:country":"GB",
    "wof:name":"KW16 3JX",
    "wof:placetype":"postalcode"
},
  "geometry": {"coordinates":[-3.22984287680534,58.98492283832223],"type":"Point"}
}