{
  "type": "Feature",
  "properties": {
    "iso:country":"GB",
    "wof:name":"LS10 2AG",
    "wof:placetype":"postalcode"
},
  "geometry": {"coordinates":[-1.53163943824665,53.77841291805121],"type":"Point"}
}