{
  "type": "Feature",
  "properties": {
    "date:inception_lower":"1986-07-01",
    "date:inception_upper":"1986-07-31",
    "iso:country":"GB",
    "wof:name":"MK5 8DG",
    "wof:placetype":"postalcode"
},
  "geometry": {"coordinates":[-0.791588,52.030807],"type":"Point"}
}