{
  "type": "Feature",
  "properties": {
    "iso:country":"GB",
    "wof:name":"MK5 8DG",
    "wof:placetype":"postalcode"
},
  "geometry": {"coordinates":[-0.79158772085742,52.03080735339669],"type":"Point"}
}