{
  "type": "Feature",
  "properties": {
    "iso:country":"GB",
    "wof:name":"NG7 3FW",
    "wof:placetype":"postalcode"
},
  "geometry": {"coordinates":[-1.17725291354319,52.95546185966119],"type":"Point"}
}