{
  "type": "Feature",
  "properties": {
    "iso:country": "GB",
    "wof:name": "NG7 3FW",
    "wof:placetype": "postalcode"
  },
  "geometry": {"coordinates":[-1.177253,52.955462],"type":"Point"}
}
