{
  "type": "Feature",
  "properties": {
    "iso:country": "GB",
    "wof:name": "TN32 5EF",
    "wof:placetype": "postalcode"
  },
  "geometry": {"coordinates":[0.466242,50.98378],"type":"Point"}
}
