{
  "type": "Feature",
  "properties": {
    "iso:country": "GB",
    "wof:name": "G74 4AH",
    "wof:placetype": "postalcode"
  },
  "geometry": {"coordinates":[-4.177465,55.772216],"type":"Point"}
}
