{
  "type": "Feature",
  "properties": {
    "iso:country":"GB",
    "wof:name":"G74 4AH",
    "wof:placetype":"postalcode"
},
  "geometry": {"coordinates":[-4.17746489623433,55.77221626036159],"type":"Point"}
}