{
  "type": "Feature",
  "properties": {
    "iso:country": "GB",
    "wof:name": "LL11 3PE",
    "wof:placetype": "postalcode"
  },
  "geometry": {"coordinates":[-3.067972,53.055961],"type":"Point"}
}
