{
  "type": "Feature",
  "properties": {
    "iso:country":"GB",
    "wof:name":"LE10 0XH",
    "wof:placetype":"postalcode"
},
  "geometry": {"coordinates":[-1.38924379716281,52.5394026330891],"type":"Point"}
}