{
  "type": "Feature",
  "properties": {
    "iso:country": "GB",
    "wof:name": "RG45 7EB",
    "wof:placetype": "postalcode"
  },
  "geometry": {"coordinates":[-0.795058,51.369294],"type":"Point"}
}
