{
  "type": "Feature",
  "properties": {
    "date:inception_lower": "1995-07-01",
    "date:inception_upper": "1995-07-01",
    "iso:country": "GB",
    "wof:name": "RG45 7EB",
    "wof:placetype": "postalcode"
  },
  "geometry": {"coordinates":[-0.795058,51.369294],"type":"Point"}
}
