{
  "type": "Feature",
  "properties": {
    "iso:country":"GB",
    "wof:name":"DG1 3NX",
    "wof:placetype":"postalcode"
},
  "geometry": {"coordinates":[-3.58116051064101,55.10328806519225],"type":"Point"}
}