{
  "type": "Feature",
  "properties": {
    "iso:country": "GB",
    "wof:name": "CT20 3LE",
    "wof:placetype": "postalcode"
  },
  "geometry": {"coordinates":[1.134663,51.086218],"type":"Point"}
}
