{
  "type": "Feature",
  "properties": {
    "iso:country":"GB",
    "wof:name":"N12 7DE",
    "wof:placetype":"postalcode"
},
  "geometry": {"coordinates":[-0.18713319751741,51.62105079079279],"type":"Point"}
}