{
  "type": "Feature",
  "properties": {
    "iso:country": "GB",
    "wof:name": "BD6 2EG",
    "wof:placetype": "postalcode"
  },
  "geometry": {"coordinates":[-1.797323,53.758699],"type":"Point"}
}
