{
  "type": "Feature",
  "properties": {
    "date:inception_lower":"1986-07-01",
    "date:inception_upper":"1986-07-31",
    "iso:country":"GB",
    "wof:name":"BD6 2EG",
    "wof:placetype":"postalcode"
},
  "geometry": {"coordinates":[-1.797323,53.758699],"type":"Point"}
}