{
  "type": "Feature",
  "properties": {
    "iso:country": "GB",
    "wof:name": "DA12 3JW",
    "wof:placetype": "postalcode"
  },
  "geometry": {"coordinates":[0.437415,51.419184],"type":"Point"}
}
