{
  "type": "Feature",
  "properties": {
    "iso:country":"GB",
    "wof:name":"CF82 7FA",
    "wof:placetype":"postalcode"
},
  "geometry": {"coordinates":[-3.24283004020723,51.63733771262682],"type":"Point"}
}