{
  "type": "Feature",
  "properties": {
    "iso:country":"GB",
    "wof:name":"M8 8WQ",
    "wof:placetype":"postalcode"
},
  "geometry": {"coordinates":[-2.23201391021831,53.50293875423555],"type":"Point"}
}