{
  "type": "Feature",
  "properties": {
    "iso:country":"GB",
    "wof:name":"SP2 7TS",
    "wof:placetype":"postalcode"
},
  "geometry": {"coordinates":[-1.80206821769429,51.07583583197558],"type":"Point"}
}