{
  "type": "Feature",
  "properties": {
    "iso:country":"GB",
    "wof:name":"SA43 1PF",
    "wof:placetype":"postalcode"
},
  "geometry": {"coordinates":[-4.65874267342931,52.09132246732681],"type":"Point"}
}