{
  "type": "Feature",
  "properties": {
    "iso:country":"GB",
    "wof:name":"BS22 8QG",
    "wof:placetype":"postalcode"
},
  "geometry": {"coordinates":[-2.93996142780133,51.34997198038322],"type":"Point"}
}