{
  "type": "Feature",
  "properties": {
    "iso:country":"GB",
    "wof:name":"DD2 2TQ",
    "wof:placetype":"postalcode"
},
  "geometry": {"coordinates":[-3.02311883971084,56.47665099182384],"type":"Point"}
}