{
  "type": "Feature",
  "properties": {
    "date:inception_lower":"1980-01-01",
    "date:inception_upper":"1980-01-31",
    "iso:country":"GB",
    "wof:name":"DD2 2TQ",
    "wof:placetype":"postalcode"
},
  "geometry": {"coordinates":[-3.023119,56.476651],"type":"Point"}
}