{
  "type": "Feature",
  "properties": {
    "iso:country":"GB",
    "wof:name":"EX4 6SR",
    "wof:placetype":"postalcode"
},
  "geometry": {"coordinates":[-3.51818390100539,50.72989959725722],"type":"Point"}
}