{
  "type": "Feature",
  "properties": {
    "iso:country":"GB",
    "wof:name":"SR8 2PQ",
    "wof:placetype":"postalcode"
},
  "geometry": {"coordinates":[-1.35394117067521,54.7625914730511],"type":"Point"}
}