{
  "type": "Feature",
  "properties": {
    "iso:country": "GB",
    "wof:name": "SR8 2PQ",
    "wof:placetype": "postalcode"
  },
  "geometry": {"coordinates":[-1.353941,54.762591],"type":"Point"}
}
