{
  "type": "Feature",
  "properties": {
    "date:inception_lower": "1980-01-01",
    "date:inception_upper": "1980-01-01",
    "iso:country": "GB",
    "wof:name": "E17 4PN",
    "wof:placetype": "postalcode"
  },
  "geometry": {"coordinates":[-0.018476,51.593517],"type":"Point"}
}
