{
  "type": "Feature",
  "properties": {
    "iso:country":"GB",
    "wof:name":"E17 4PN",
    "wof:placetype":"postalcode"
},
  "geometry": {"coordinates":[-0.01854558207256,51.59351582804325],"type":"Point"}
}