{
  "type": "Feature",
  "properties": {
    "iso:country":"GB",
    "wof:name":"BS25 1UQ",
    "wof:placetype":"postalcode"
},
  "geometry": {"coordinates":[-2.80945011897606,51.3182791199259],"type":"Point"}
}