{
  "type": "Feature",
  "properties": {
    "iso:country": "GB",
    "wof:name": "CW7 1NU",
    "wof:placetype": "postalcode"
  },
  "geometry": {"coordinates":[-2.545151,53.184203],"type":"Point"}
}
