{
  "type": "Feature",
  "properties": {
    "iso:country":"GB",
    "wof:name":"CW7 1NU",
    "wof:placetype":"postalcode"
},
  "geometry": {"coordinates":[-2.54515103466298,53.18420349354471],"type":"Point"}
}