{
  "type": "Feature",
  "properties": {
    "iso:country": "GB",
    "wof:name": "CF42 5PQ",
    "wof:placetype": "postalcode"
  },
  "geometry": {"coordinates":[-3.537009,51.675173],"type":"Point"}
}
