{
  "type": "Feature",
  "properties": {
    "date:inception_lower":"2008-07-01",
    "date:inception_upper":"2008-07-31",
    "iso:country":"GB",
    "wof:name":"CF42 5PQ",
    "wof:placetype":"postalcode"
},
  "geometry": {"coordinates":[-3.537009,51.675173],"type":"Point"}
}