{
  "type": "Feature",
  "properties": {
    "date:inception_lower": "2022-05-01",
    "date:inception_upper": "2022-05-01",
    "iso:country": "GB",
    "wof:name": "CF42 5PQ",
    "wof:placetype": "postalcode"
  },
  "geometry": {"coordinates":[-3.537122,51.675184],"type":"Point"}
}
