{
  "type": "Feature",
  "properties": {
    "iso:country":"GB",
    "wof:name":"CF42 5PQ",
    "wof:placetype":"postalcode"
},
  "geometry": {"coordinates":[-3.53700908113562,51.67517255152606],"type":"Point"}
}