{
  "type": "Feature",
  "properties": {
    "iso:country": "GB",
    "wof:name": "GU46 6FN",
    "wof:placetype": "postalcode"
  },
  "geometry": {"coordinates":[-0.849883,51.335252],"type":"Point"}
}
