{
  "type": "Feature",
  "properties": {
    "iso:country":"GB",
    "wof:name":"GU46 6FN",
    "wof:placetype":"postalcode"
},
  "geometry": {"coordinates":[-0.84988315686633,51.33525221070344],"type":"Point"}
}