{
  "type": "Feature",
  "properties": {
    "date:inception_lower": "1990-02-01",
    "date:inception_upper": "1990-02-01",
    "iso:country": "GB",
    "wof:name": "YO17 9ER",
    "wof:placetype": "postalcode"
  },
  "geometry": {"coordinates":[-0.78127,54.134187],"type":"Point"}
}
