{
  "type": "Feature",
  "properties": {
    "iso:country":"GB",
    "wof:name":"LU2 0TL",
    "wof:placetype":"postalcode"
},
  "geometry": {"coordinates":[-0.39968779664803,51.89245829760139],"type":"Point"}
}