{
  "type": "Feature",
  "properties": {
    "date:inception_lower":"1981-06-01",
    "date:inception_upper":"1981-06-30",
    "iso:country":"GB",
    "wof:name":"LU2 0TL",
    "wof:placetype":"postalcode"
},
  "geometry": {"coordinates":[-0.399708,51.89244],"type":"Point"}
}