{
  "type": "Feature",
  "properties": {
    "iso:country": "GB",
    "wof:name": "RG4 6TJ",
    "wof:placetype": "postalcode"
  },
  "geometry": {"coordinates":[-0.903389,51.473722],"type":"Point"}
}
