{
  "type": "Feature",
  "properties": {
    "iso:country":"GB",
    "wof:name":"RG4 6TJ",
    "wof:placetype":"postalcode"
},
  "geometry": {"coordinates":[-0.9034081815661,51.47373828121295],"type":"Point"}
}