{
  "type": "Feature",
  "properties": {
    "date:inception_lower": "1980-01-01",
    "date:inception_upper": "1980-01-01",
    "iso:country": "GB",
    "wof:name": "RH10 1QX",
    "wof:placetype": "postalcode"
  },
  "geometry": {"coordinates":[-0.17229,51.122258],"type":"Point"}
}
