{
  "type": "Feature",
  "properties": {
    "iso:country":"GB",
    "wof:name":"RH10 1QX",
    "wof:placetype":"postalcode"
},
  "geometry": {"coordinates":[-0.17228980215206,51.12225816596754],"type":"Point"}
}