{
  "type": "Feature",
  "properties": {
    "date:inception_lower": "1980-01-01",
    "date:inception_upper": "1980-01-01",
    "iso:country": "GB",
    "wof:name": "WN5 7HR",
    "wof:placetype": "postalcode"
  },
  "geometry": {"coordinates":[-2.704362,53.502436],"type":"Point"}
}
