{
  "type": "Feature",
  "properties": {
    "iso:country": "GB",
    "wof:name": "DN9 1BN",
    "wof:placetype": "postalcode"
  },
  "geometry": {"coordinates":[-0.823381,53.523543],"type":"Point"}
}
