{
  "type": "Feature",
  "properties": {
    "iso:country":"GB",
    "wof:name":"B67 5AA",
    "wof:placetype":"postalcode"
},
  "geometry": {"coordinates":[-1.97146532802062,52.47961725466183],"type":"Point"}
}