{
  "type": "Feature",
  "properties": {
    "date:inception_lower":"1980-01-01",
    "date:inception_upper":"1980-01-31",
    "iso:country":"GB",
    "wof:name":"WD3 5RA",
    "wof:placetype":"postalcode"
},
  "geometry": {"coordinates":[-0.521449,51.655392],"type":"Point"}
}