{
  "type": "Feature",
  "properties": {
    "iso:country": "GB",
    "wof:name": "RG40 1EW",
    "wof:placetype": "postalcode"
  },
  "geometry": {"coordinates":[-0.827285,51.412998],"type":"Point"}
}
