{
  "type": "Feature",
  "properties": {
    "date:inception_lower":"2007-08-01",
    "date:inception_upper":"2007-08-31",
    "iso:country":"GB",
    "wof:name":"DG12 6TX",
    "wof:placetype":"postalcode"
},
  "geometry": {"coordinates":[-3.243866,54.994676],"type":"Point"}
}