{
  "type": "Feature",
  "properties": {
    "date:inception_lower":"1980-01-01",
    "date:inception_upper":"1980-01-31",
    "iso:country":"GB",
    "wof:name":"CT5 3JW",
    "wof:placetype":"postalcode"
},
  "geometry": {"coordinates":[1.062017,51.353775],"type":"Point"}
}