{
  "type": "Feature",
  "properties": {
    "iso:country":"GB",
    "wof:name":"CT5 3JW",
    "wof:placetype":"postalcode"
},
  "geometry": {"coordinates":[1.06201678750838,51.35377516304744],"type":"Point"}
}