{
  "type": "Feature",
  "properties": {
    "iso:country":"GB",
    "wof:name":"EH20 9AW",
    "wof:placetype":"postalcode"
},
  "geometry": {"coordinates":[-3.15819620911036,55.87609404645518],"type":"Point"}
}