{
  "type": "Feature",
  "properties": {
    "iso:country": "GB",
    "wof:name": "EH20 9AW",
    "wof:placetype": "postalcode"
  },
  "geometry": {"coordinates":[-3.158196,55.876094],"type":"Point"}
}
