{
  "type": "Feature",
  "properties": {
    "iso:country":"GB",
    "wof:name":"W1G 8QD",
    "wof:placetype":"postalcode"
},
  "geometry": {"coordinates":[-0.14751225208439,51.51870099969747],"type":"Point"}
}