{
  "type": "Feature",
  "properties": {
    "iso:country":"GB",
    "wof:name":"TR12 7BB",
    "wof:placetype":"postalcode"
},
  "geometry": {"coordinates":[-5.21390395468818,50.05223248508991],"type":"Point"}
}