{
  "type": "Feature",
  "properties": {
    "date:inception_lower":"1980-01-01",
    "date:inception_upper":"1980-01-31",
    "iso:country":"GB",
    "wof:name":"GU33 6LN",
    "wof:placetype":"postalcode"
},
  "geometry": {"coordinates":[-0.928852,51.040667],"type":"Point"}
}