{
  "type": "Feature",
  "properties": {
    "iso:country": "GB",
    "wof:name": "GU33 6LN",
    "wof:placetype": "postalcode"
  },
  "geometry": {"coordinates":[-0.928852,51.040667],"type":"Point"}
}
