{
  "type": "Feature",
  "properties": {
    "iso:country":"GB",
    "wof:name":"GU33 6LN",
    "wof:placetype":"postalcode"
},
  "geometry": {"coordinates":[-0.92885249425054,51.0406673570621],"type":"Point"}
}