{
  "type": "Feature",
  "properties": {
    "date:inception_lower": "1980-01-01",
    "date:inception_upper": "1980-01-01",
    "iso:country": "GB",
    "wof:name": "RH8 9NG",
    "wof:placetype": "postalcode"
  },
  "geometry": {"coordinates":[-0.033412,51.249847],"type":"Point"}
}
