{
  "type": "Feature",
  "properties": {
    "iso:country":"GB",
    "wof:name":"RH8 9NG",
    "wof:placetype":"postalcode"
},
  "geometry": {"coordinates":[-0.03341196981679,51.24984686620679],"type":"Point"}
}