{
  "type": "Feature",
  "properties": {
    "iso:country":"GB",
    "wof:name":"PA5 0PF",
    "wof:placetype":"postalcode"
},
  "geometry": {"coordinates":[-4.5357247317699,55.82197850007305],"type":"Point"}
}