{
  "type": "Feature",
  "properties": {
    "iso:country": "GB",
    "wof:name": "B73 5LB",
    "wof:placetype": "postalcode"
  },
  "geometry": {"coordinates":[-1.825122,52.546988],"type":"Point"}
}
