{
  "type": "Feature",
  "properties": {
    "iso:country":"GB",
    "wof:name":"SY1 4QX",
    "wof:placetype":"postalcode"
},
  "geometry": {"coordinates":[-2.71560998444089,52.72988372005971],"type":"Point"}
}