{
  "type": "Feature",
  "properties": {
    "date:inception_lower": "1980-01-01",
    "date:inception_upper": "1980-01-01",
    "iso:country": "GB",
    "wof:name": "MK19 6EN",
    "wof:placetype": "postalcode"
  },
  "geometry": {"coordinates":[-0.830767,52.025764],"type":"Point"}
}
