{
  "type": "Feature",
  "properties": {
    "iso:country":"GB",
    "wof:name":"MK19 6EN",
    "wof:placetype":"postalcode"
},
  "geometry": {"coordinates":[-0.83078549815884,52.02575418328357],"type":"Point"}
}