{
  "type": "Feature",
  "properties": {
    "iso:country": "GB",
    "wof:name": "NR6 5HD",
    "wof:placetype": "postalcode"
  },
  "geometry": {"coordinates":[1.269439,52.655045],"type":"Point"}
}
