{
  "type": "Feature",
  "properties": {
    "iso:country":"GB",
    "wof:name":"NR6 5HD",
    "wof:placetype":"postalcode"
},
  "geometry": {"coordinates":[1.26943907360422,52.6550450920589],"type":"Point"}
}