{
  "type": "Feature",
  "properties": {
    "iso:country":"GB",
    "wof:name":"B97 6AD",
    "wof:placetype":"postalcode"
},
  "geometry": {"coordinates":[-1.94343693674741,52.3131917393935],"type":"Point"}
}