{
  "type": "Feature",
  "properties": {
    "iso:country":"GB",
    "wof:name":"RM6 5RX",
    "wof:placetype":"postalcode"
},
  "geometry": {"coordinates":[0.11856776670428,51.58415129451569],"type":"Point"}
}