{
  "type": "Feature",
  "properties": {
    "date:inception_lower": "1998-12-01",
    "date:inception_upper": "1998-12-01",
    "iso:country": "GB",
    "wof:name": "CF64 1SH",
    "wof:placetype": "postalcode"
  },
  "geometry": {"coordinates":[-3.180562,51.444512],"type":"Point"}
}
