{
  "type": "Feature",
  "properties": {
    "iso:country": "GB",
    "wof:name": "CF64 1SH",
    "wof:placetype": "postalcode"
  },
  "geometry": {"coordinates":[-3.180562,51.444512],"type":"Point"}
}
