{
  "type": "Feature",
  "properties": {
    "date:inception_lower": "1984-10-01",
    "date:inception_upper": "1984-10-01",
    "iso:country": "GB",
    "wof:name": "WF6 2RT",
    "wof:placetype": "postalcode"
  },
  "geometry": {"coordinates":[-1.405492,53.698767],"type":"Point"}
}
