{
  "type": "Feature",
  "properties": {
    "date:inception_lower":"1986-04-01",
    "date:inception_upper":"1986-04-30",
    "iso:country":"GB",
    "wof:name":"CF5 2TE",
    "wof:placetype":"postalcode"
},
  "geometry": {"coordinates":[-3.235679,51.503858],"type":"Point"}
}