{
  "type": "Feature",
  "properties": {
    "iso:country":"GB",
    "wof:name":"LL29 9BY",
    "wof:placetype":"postalcode"
},
  "geometry": {"coordinates":[-3.70121361883509,53.28882092248354],"type":"Point"}
}