{
  "type": "Feature",
  "properties": {
    "date:inception_lower": "1993-08-01",
    "date:inception_upper": "1993-08-01",
    "iso:country": "GB",
    "wof:name": "LL29 9BY",
    "wof:placetype": "postalcode"
  },
  "geometry": {"coordinates":[-3.701214,53.288821],"type":"Point"}
}
