{
  "type": "Feature",
  "properties": {
    "date:inception_lower": "1980-01-01",
    "date:inception_upper": "1980-01-01",
    "iso:country": "GB",
    "wof:name": "SY21 8JX",
    "wof:placetype": "postalcode"
  },
  "geometry": {"coordinates":[-3.043057,52.61997],"type":"Point"}
}
