{
  "type": "Feature",
  "properties": {
    "iso:country":"GB",
    "wof:name":"SY21 8JX",
    "wof:placetype":"postalcode"
},
  "geometry": {"coordinates":[-3.04305700867276,52.61996990178859],"type":"Point"}
}