{
  "type": "Feature",
  "properties": {
    "iso:country":"GB",
    "wof:name":"UB10 8ER",
    "wof:placetype":"postalcode"
},
  "geometry": {"coordinates":[-0.46211243127964,51.56156281240698],"type":"Point"}
}