{
  "type": "Feature",
  "properties": {
    "iso:country":"GB",
    "wof:name":"M9 7GJ",
    "wof:placetype":"postalcode"
},
  "geometry": {"coordinates":[-2.20421159563255,53.5244897968801],"type":"Point"}
}