{
  "type": "Feature",
  "properties": {
    "date:inception_lower":"1997-12-01",
    "date:inception_upper":"1997-12-31",
    "iso:country":"GB",
    "wof:name":"KT2 5US",
    "wof:placetype":"postalcode"
},
  "geometry": {"coordinates":[-0.305342,51.41531],"type":"Point"}
}