{
  "type": "Feature",
  "properties": {
    "iso:country":"GB",
    "wof:name":"CB22 7NU",
    "wof:placetype":"postalcode"
},
  "geometry": {"coordinates":[0.06537490667717,52.13996865768586],"type":"Point"}
}