{
  "type": "Feature",
  "properties": {
    "iso:country": "GB",
    "wof:name": "SP4 8LE",
    "wof:placetype": "postalcode"
  },
  "geometry": {"coordinates":[-1.783171,51.219018],"type":"Point"}
}
