{
  "type": "Feature",
  "properties": {
    "iso:country":"GB",
    "wof:name":"FY1 3ND",
    "wof:placetype":"postalcode"
},
  "geometry": {"coordinates":[-3.04391216133413,53.82008145861951],"type":"Point"}
}