{
  "type": "Feature",
  "properties": {
    "date:inception_lower": "1980-01-01",
    "date:inception_upper": "1980-01-01",
    "iso:country": "GB",
    "wof:name": "KY11 1JL",
    "wof:placetype": "postalcode"
  },
  "geometry": {"coordinates":[-3.397214,56.012011],"type":"Point"}
}
