{
  "type": "Feature",
  "properties": {
    "iso:country":"GB",
    "wof:name":"TW20 8NU",
    "wof:placetype":"postalcode"
},
  "geometry": {"coordinates":[-0.54105622684725,51.42254538669242],"type":"Point"}
}