{
  "type": "Feature",
  "properties": {
    "iso:country":"GB",
    "wof:name":"PL7 1TB",
    "wof:placetype":"postalcode"
},
  "geometry": {"coordinates":[-4.05472587341998,50.38504659588337],"type":"Point"}
}