{
  "type": "Feature",
  "properties": {
    "iso:country": "GB",
    "wof:name": "PL7 1TB",
    "wof:placetype": "postalcode"
  },
  "geometry": {"coordinates":[-4.054726,50.385047],"type":"Point"}
}
