{
  "type": "Feature",
  "properties": {
    "date:inception_lower":"1990-07-01",
    "date:inception_upper":"1990-07-31",
    "iso:country":"GB",
    "wof:name":"BN41 1PW",
    "wof:placetype":"postalcode"
},
  "geometry": {"coordinates":[-0.220737,50.832922],"type":"Point"}
}