{
  "type": "Feature",
  "properties": {
    "iso:country":"GB",
    "wof:name":"BN41 1PW",
    "wof:placetype":"postalcode"
},
  "geometry": {"coordinates":[-0.22073703015168,50.83292187021141],"type":"Point"}
}