{
  "type": "Feature",
  "properties": {
    "iso:country": "GB",
    "wof:name": "GL51 0AJ",
    "wof:placetype": "postalcode"
  },
  "geometry": {"coordinates":[-2.104377,51.911795],"type":"Point"}
}
