{
  "type": "Feature",
  "properties": {
    "iso:country":"GB",
    "wof:name":"WV2 1EP",
    "wof:placetype":"postalcode"
},
  "geometry": {"coordinates":[-2.11997259626413,52.57724367110262],"type":"Point"}
}