{
  "type": "Feature",
  "properties": {
    "iso:country": "GB",
    "wof:name": "ZE1 0RB",
    "wof:placetype": "postalcode"
  },
  "geometry": {"coordinates":[-1.153403,60.151439],"type":"Point"}
}
