{
  "type": "Feature",
  "properties": {
    "iso:country": "GB",
    "wof:name": "TQ13 0FB",
    "wof:placetype": "postalcode"
  },
  "geometry": {"coordinates":[-3.610186,50.6004],"type":"Point"}
}
