{
  "type": "Feature",
  "properties": {
    "iso:country":"GB",
    "wof:name":"TQ13 0FB",
    "wof:placetype":"postalcode"
},
  "geometry": {"coordinates":[-3.61018612463876,50.60040034506665],"type":"Point"}
}