{
  "type": "Feature",
  "properties": {
    "date:inception_lower":"2011-05-01",
    "date:inception_upper":"2011-05-31",
    "iso:country":"GB",
    "wof:name":"TQ13 0FB",
    "wof:placetype":"postalcode"
},
  "geometry": {"coordinates":[-3.610186,50.6004],"type":"Point"}
}