{
  "type": "Feature",
  "properties": {
    "iso:country":"GB",
    "wof:name":"N18 1NP",
    "wof:placetype":"postalcode"
},
  "geometry": {"coordinates":[-0.07891373440921,51.61941061886142],"type":"Point"}
}