{
  "type": "Feature",
  "properties": {
    "date:inception_lower": "1980-01-01",
    "date:inception_upper": "1980-01-01",
    "iso:country": "GB",
    "wof:name": "GU26 6JJ",
    "wof:placetype": "postalcode"
  },
  "geometry": {"coordinates":[-0.776927,51.114354],"type":"Point"}
}
