{
  "type": "Feature",
  "properties": {
    "iso:country":"GB",
    "wof:name":"BD3 9NJ",
    "wof:placetype":"postalcode"
},
  "geometry": {"coordinates":[-1.73048404614056,53.79358486482693],"type":"Point"}
}