{
  "type": "Feature",
  "properties": {
    "date:inception_lower": "1995-01-01",
    "date:inception_upper": "1995-01-01",
    "iso:country": "GB",
    "wof:name": "BD3 9NJ",
    "wof:placetype": "postalcode"
  },
  "geometry": {"coordinates":[-1.730484,53.793585],"type":"Point"}
}
