{
  "type": "Feature",
  "properties": {
    "iso:country":"GB",
    "wof:name":"IP19 0AP",
    "wof:placetype":"postalcode"
},
  "geometry": {"coordinates":[1.40908360463735,52.38050284831043],"type":"Point"}
}