{
  "type": "Feature",
  "properties": {
    "iso:country": "GB",
    "wof:name": "IP19 0AP",
    "wof:placetype": "postalcode"
  },
  "geometry": {"coordinates":[1.409084,52.380503],"type":"Point"}
}
