{
  "type": "Feature",
  "properties": {
    "date:inception_lower":"2002-07-01",
    "date:inception_upper":"2002-07-31",
    "iso:country":"GB",
    "wof:name":"IP19 0AP",
    "wof:placetype":"postalcode"
},
  "geometry": {"coordinates":[1.409084,52.380503],"type":"Point"}
}