{
  "type": "Feature",
  "properties": {
    "date:inception_lower":"1980-01-01",
    "date:inception_upper":"1980-01-31",
    "iso:country":"GB",
    "wof:name":"OX13 6HA",
    "wof:placetype":"postalcode"
},
  "geometry": {"coordinates":[-1.302827,51.687184],"type":"Point"}
}