{
  "type": "Feature",
  "properties": {
    "date:inception_lower":"1980-01-01",
    "date:inception_upper":"1980-01-31",
    "iso:country":"GB",
    "wof:name":"TW2 7HJ",
    "wof:placetype":"postalcode"
},
  "geometry": {"coordinates":[-0.359833,51.453826],"type":"Point"}
}