{
  "type": "Feature",
  "properties": {
    "iso:country": "GB",
    "wof:name": "TW2 7HJ",
    "wof:placetype": "postalcode"
  },
  "geometry": {"coordinates":[-0.359833,51.453826],"type":"Point"}
}
