{
  "type": "Feature",
  "properties": {
    "iso:country":"GB",
    "wof:name":"TW2 7HJ",
    "wof:placetype":"postalcode"
},
  "geometry": {"coordinates":[-0.35983282366296,51.45382614753871],"type":"Point"}
}