{
  "type": "Feature",
  "properties": {
    "iso:country":"GB",
    "wof:name":"E15 4HG",
    "wof:placetype":"postalcode"
},
  "geometry": {"coordinates":[0.01086892961581,51.5406515190915],"type":"Point"}
}