{
  "type": "Feature",
  "properties": {
    "iso:country": "GB",
    "wof:name": "CT14 6JA",
    "wof:placetype": "postalcode"
  },
  "geometry": {"coordinates":[1.404127,51.224904],"type":"Point"}
}
