{
  "type": "Feature",
  "properties": {
    "iso:country":"GB",
    "wof:name":"NG20 8FB",
    "wof:placetype":"postalcode"
},
  "geometry": {"coordinates":[-1.22851075451785,53.19813832650217],"type":"Point"}
}