{
  "type": "Feature",
  "properties": {
    "date:inception_lower": "2000-12-01",
    "date:inception_upper": "2000-12-01",
    "iso:country": "GB",
    "wof:name": "NG20 8FB",
    "wof:placetype": "postalcode"
  },
  "geometry": {"coordinates":[-1.228511,53.198138],"type":"Point"}
}
