{
  "type": "Feature",
  "properties": {
    "iso:country": "GB",
    "wof:name": "M5 4DY",
    "wof:placetype": "postalcode"
  },
  "geometry": {"coordinates":[-2.275161,53.479603],"type":"Point"}
}
