{
  "type": "Feature",
  "properties": {
    "iso:country": "GB",
    "wof:name": "CM24 8GS",
    "wof:placetype": "postalcode"
  },
  "geometry": {"coordinates":[0.197025,51.895364],"type":"Point"}
}
