{
  "type": "Feature",
  "properties": {
    "iso:country": "GB",
    "wof:name": "L39 3LR",
    "wof:placetype": "postalcode"
  },
  "geometry": {"coordinates":[-2.907596,53.557667],"type":"Point"}
}
