{
  "type": "Feature",
  "properties": {
    "date:inception_lower":"1999-06-01",
    "date:inception_upper":"1999-06-30",
    "iso:country":"GB",
    "wof:name":"NP20 3HW",
    "wof:placetype":"postalcode"
},
  "geometry": {"coordinates":[-3.01992,51.578055],"type":"Point"}
}