{
  "type": "Feature",
  "properties": {
    "iso:country": "GB",
    "wof:name": "NP20 3HW",
    "wof:placetype": "postalcode"
  },
  "geometry": {"coordinates":[-3.01992,51.578055],"type":"Point"}
}
