{
  "type": "Feature",
  "properties": {
    "iso:country":"GB",
    "wof:name":"TS3 7HT",
    "wof:placetype":"postalcode"
},
  "geometry": {"coordinates":[-1.20281756113567,54.55442674331253],"type":"Point"}
}