{
  "type": "Feature",
  "properties": {
    "iso:country": "GB",
    "wof:name": "TS3 7HT",
    "wof:placetype": "postalcode"
  },
  "geometry": {"coordinates":[-1.202818,54.554427],"type":"Point"}
}
