{
  "type": "Feature",
  "properties": {
    "iso:country":"GB",
    "wof:name":"LA22 9DR",
    "wof:placetype":"postalcode"
},
  "geometry": {"coordinates":[-2.96372808327092,54.43209777920754],"type":"Point"}
}