{
  "type": "Feature",
  "properties": {
    "date:inception_lower": "1980-01-01",
    "date:inception_upper": "1980-01-01",
    "iso:country": "GB",
    "wof:name": "LA22 9DR",
    "wof:placetype": "postalcode"
  },
  "geometry": {"coordinates":[-2.963885,54.432077],"type":"Point"}
}
