{
  "type": "Feature",
  "properties": {
    "iso:country":"GB",
    "wof:name":"CW9 8GL",
    "wof:placetype":"postalcode"
},
  "geometry": {"coordinates":[-2.52234369232192,53.24189789600929],"type":"Point"}
}