{
  "type": "Feature",
  "properties": {
    "iso:country":"GB",
    "wof:name":"SW9 6JZ",
    "wof:placetype":"postalcode"
},
  "geometry": {"coordinates":[-0.11118319886979,51.47564073599873],"type":"Point"}
}