{
  "type": "Feature",
  "properties": {
    "iso:country":"GB",
    "wof:name":"PL4 9QD",
    "wof:placetype":"postalcode"
},
  "geometry": {"coordinates":[-4.11775566612078,50.37196208337178],"type":"Point"}
}