{
  "type": "Feature",
  "properties": {
    "iso:country": "GB",
    "wof:name": "UB8 1GQ",
    "wof:placetype": "postalcode"
  },
  "geometry": {"coordinates":[-0.466603,51.549437],"type":"Point"}
}
