{
  "type": "Feature",
  "properties": {
    "iso:country":"GB",
    "wof:name":"HG4 2TX",
    "wof:placetype":"postalcode"
},
  "geometry": {"coordinates":[-1.5491281161601,54.13813566800575],"type":"Point"}
}