{
  "type": "Feature",
  "properties": {
    "date:inception_lower": "2009-10-01",
    "date:inception_upper": "2009-10-01",
    "iso:country": "GB",
    "wof:name": "LS9 8FR",
    "wof:placetype": "postalcode"
  },
  "geometry": {"coordinates":[-1.528027,53.794739],"type":"Point"}
}
