{
  "type": "Feature",
  "properties": {
    "iso:country":"GB",
    "wof:name":"LS9 8FR",
    "wof:placetype":"postalcode"
},
  "geometry": {"coordinates":[-1.5280268219405,53.79473906062216],"type":"Point"}
}