{
  "type": "Feature",
  "properties": {
    "date:inception_lower":"1980-01-01",
    "date:inception_upper":"1980-01-31",
    "iso:country":"GB",
    "wof:name":"SR8 4AR",
    "wof:placetype":"postalcode"
},
  "geometry": {"coordinates":[-1.320183,54.765535],"type":"Point"}
}