{
  "type": "Feature",
  "properties": {
    "iso:country": "GB",
    "wof:name": "TN1 1SX",
    "wof:placetype": "postalcode"
  },
  "geometry": {"coordinates":[0.267867,51.129298],"type":"Point"}
}
