{
  "type": "Feature",
  "properties": {
    "iso:country":"GB",
    "wof:name":"TN1 1SX",
    "wof:placetype":"postalcode"
},
  "geometry": {"coordinates":[0.26786718849722,51.12929784779626],"type":"Point"}
}