{
  "type": "Feature",
  "properties": {
    "iso:country":"GB",
    "wof:name":"BN3 6GF",
    "wof:placetype":"postalcode"
},
  "geometry": {"coordinates":[-0.16415885069354,50.83655104607291],"type":"Point"}
}