{
  "type": "Feature",
  "properties": {
    "iso:country": "GB",
    "wof:name": "BN3 6GF",
    "wof:placetype": "postalcode"
  },
  "geometry": {"coordinates":[-0.164159,50.836551],"type":"Point"}
}
