{
  "type": "Feature",
  "properties": {
    "date:inception_lower":"1980-01-01",
    "date:inception_upper":"1980-01-31",
    "iso:country":"GB",
    "wof:name":"BN3 6GF",
    "wof:placetype":"postalcode"
},
  "geometry": {"coordinates":[-0.164159,50.836551],"type":"Point"}
}