{
  "type": "Feature",
  "properties": {
    "iso:country": "GB",
    "wof:name": "NE15 9ER",
    "wof:placetype": "postalcode"
  },
  "geometry": {"coordinates":[-1.755319,54.998455],"type":"Point"}
}
