{
  "type": "Feature",
  "properties": {
    "iso:country":"GB",
    "wof:name":"SL5 8QF",
    "wof:placetype":"postalcode"
},
  "geometry": {"coordinates":[-0.68112929169236,51.42905172351135],"type":"Point"}
}