{
  "type": "Feature",
  "properties": {
    "date:inception_lower":"2009-06-01",
    "date:inception_upper":"2009-06-30",
    "iso:country":"GB",
    "wof:name":"FK10 2QB",
    "wof:placetype":"postalcode"
},
  "geometry": {"coordinates":[-3.848902,56.136358],"type":"Point"}
}