{
  "type": "Feature",
  "properties": {
    "iso:country": "GB",
    "wof:name": "WA15 6XF",
    "wof:placetype": "postalcode"
  },
  "geometry": {"coordinates":[-2.317961,53.401872],"type":"Point"}
}
