{
  "type": "Feature",
  "properties": {
    "iso:country":"GB",
    "wof:name":"TW14 9DH",
    "wof:placetype":"postalcode"
},
  "geometry": {"coordinates":[-0.40475078351785,51.450174565077],"type":"Point"}
}