{
  "type": "Feature",
  "properties": {
    "iso:country":"GB",
    "wof:name":"HX3 8SR",
    "wof:placetype":"postalcode"
},
  "geometry": {"coordinates":[-1.80204556173889,53.72857896128724],"type":"Point"}
}