{
  "type": "Feature",
  "properties": {
    "iso:country":"GB",
    "wof:name":"GU32 3BZ",
    "wof:placetype":"postalcode"
},
  "geometry": {"coordinates":[-0.94392810940046,51.00808076448268],"type":"Point"}
}