{
  "type": "Feature",
  "properties": {
    "iso:country":"GB",
    "wof:name":"GL7 9SE",
    "wof:placetype":"postalcode"
},
  "geometry": {"coordinates":[-1.96609921505993,51.71193099106807],"type":"Point"}
}