{
  "type": "Feature",
  "properties": {
    "iso:country":"GB",
    "wof:name":"B34 6EH",
    "wof:placetype":"postalcode"
},
  "geometry": {"coordinates":[-1.80353271636527,52.4941205767734],"type":"Point"}
}