{
  "type": "Feature",
  "properties": {
    "iso:country": "GB",
    "wof:name": "PO30 2DH",
    "wof:placetype": "postalcode"
  },
  "geometry": {"coordinates":[-1.277274,50.70209],"type":"Point"}
}
