{
  "type": "Feature",
  "properties": {
    "date:inception_lower": "1980-01-01",
    "date:inception_upper": "1980-01-01",
    "iso:country": "GB",
    "wof:name": "PO30 2DH",
    "wof:placetype": "postalcode"
  },
  "geometry": {"coordinates":[-1.277274,50.70209],"type":"Point"}
}
