{
  "type": "Feature",
  "properties": {
    "iso:country": "GB",
    "wof:name": "ME14 2JE",
    "wof:placetype": "postalcode"
  },
  "geometry": {"coordinates":[0.529624,51.292129],"type":"Point"}
}
