{
  "type": "Feature",
  "properties": {
    "iso:country":"GB",
    "wof:name":"NR20 4HH",
    "wof:placetype":"postalcode"
},
  "geometry": {"coordinates":[0.88366890404904,52.72825008411127],"type":"Point"}
}