{
  "type": "Feature",
  "properties": {
    "date:inception_lower":"1988-03-01",
    "date:inception_upper":"1988-03-31",
    "iso:country":"GB",
    "wof:name":"SK10 3NR",
    "wof:placetype":"postalcode"
},
  "geometry": {"coordinates":[-2.147543,53.264354],"type":"Point"}
}