{
  "type": "Feature",
  "properties": {
    "iso:country": "GB",
    "wof:name": "SK10 3NR",
    "wof:placetype": "postalcode"
  },
  "geometry": {"coordinates":[-2.147543,53.264354],"type":"Point"}
}
