{
  "type": "Feature",
  "properties": {
    "date:inception_lower": "1995-07-01",
    "date:inception_upper": "1995-07-01",
    "iso:country": "GB",
    "wof:name": "RG29 1RW",
    "wof:placetype": "postalcode"
  },
  "geometry": {"coordinates":[-0.968272,51.221192],"type":"Point"}
}
