{
  "type": "Feature",
  "properties": {
    "iso:country": "GB",
    "wof:name": "RG29 1RW",
    "wof:placetype": "postalcode"
  },
  "geometry": {"coordinates":[-0.968272,51.221192],"type":"Point"}
}
