{
  "type": "Feature",
  "properties": {
    "iso:country": "GB",
    "wof:name": "GL3 4GZ",
    "wof:placetype": "postalcode"
  },
  "geometry": {"coordinates":[-2.184926,51.841501],"type":"Point"}
}
