{
  "type": "Feature",
  "properties": {
    "iso:country": "GB",
    "wof:name": "L9 9DE",
    "wof:placetype": "postalcode"
  },
  "geometry": {"coordinates":[-2.944702,53.466791],"type":"Point"}
}
