{
  "type": "Feature",
  "properties": {
    "iso:country":"GB",
    "wof:name":"EH48 4QJ",
    "wof:placetype":"postalcode"
},
  "geometry": {"coordinates":[-3.65856211649982,55.93150986853111],"type":"Point"}
}