{
  "type": "Feature",
  "properties": {
    "date:inception_lower": "1989-04-01",
    "date:inception_upper": "1989-04-01",
    "iso:country": "GB",
    "wof:name": "EH48 4QJ",
    "wof:placetype": "postalcode"
  },
  "geometry": {"coordinates":[-3.658562,55.93151],"type":"Point"}
}
