{
  "type": "Feature",
  "properties": {
    "iso:country":"GB",
    "wof:name":"G42 8HT",
    "wof:placetype":"postalcode"
},
  "geometry": {"coordinates":[-4.25563900574121,55.8351026851355],"type":"Point"}
}