{
  "type": "Feature",
  "properties": {
    "iso:country":"GB",
    "wof:name":"GL20 7RN",
    "wof:placetype":"postalcode"
},
  "geometry": {"coordinates":[-2.14306343884857,51.98557735102863],"type":"Point"}
}