{
  "type": "Feature",
  "properties": {
    "iso:country":"GB",
    "wof:name":"KA25 6JB",
    "wof:placetype":"postalcode"
},
  "geometry": {"coordinates":[-4.68962468207226,55.74425450458429],"type":"Point"}
}