{
  "type": "Feature",
  "properties": {
    "iso:country": "GB",
    "wof:name": "PL1 3AD",
    "wof:placetype": "postalcode"
  },
  "geometry": {"coordinates":[-4.147913,50.369228],"type":"Point"}
}
