{
  "type": "Feature",
  "properties": {
    "iso:country":"GB",
    "wof:name":"N22 6TN",
    "wof:placetype":"postalcode"
},
  "geometry": {"coordinates":[-0.11155909024091,51.59440187801764],"type":"Point"}
}