{
  "type": "Feature",
  "properties": {
    "iso:country":"GB",
    "wof:name":"EX1 1GG",
    "wof:placetype":"postalcode"
},
  "geometry": {"coordinates":[-3.52788771685006,50.72372930980664],"type":"Point"}
}