{
  "type": "Feature",
  "properties": {
    "iso:country": "GB",
    "wof:name": "EX1 1GG",
    "wof:placetype": "postalcode"
  },
  "geometry": {"coordinates":[-3.527902,50.723719],"type":"Point"}
}
