{
  "type": "Feature",
  "properties": {
    "date:inception_lower": "2013-03-01",
    "date:inception_upper": "2013-03-01",
    "iso:country": "GB",
    "wof:name": "CB6 2ND",
    "wof:placetype": "postalcode"
  },
  "geometry": {"coordinates":[0.11088,52.386725],"type":"Point"}
}
