{
  "type": "Feature",
  "properties": {
    "iso:country": "GB",
    "wof:name": "CH49 6LG",
    "wof:placetype": "postalcode"
  },
  "geometry": {"coordinates":[-3.092949,53.389435],"type":"Point"}
}
