{
  "type": "Feature",
  "properties": {
    "iso:country":"GB",
    "wof:name":"SY20 9JR",
    "wof:placetype":"postalcode"
},
  "geometry": {"coordinates":[-3.87100118926718,52.59608959146469],"type":"Point"}
}