{
  "type": "Feature",
  "properties": {
    "iso:country": "GB",
    "wof:name": "SY20 9JR",
    "wof:placetype": "postalcode"
  },
  "geometry": {"coordinates":[-3.871001,52.59609],"type":"Point"}
}
