{
  "type": "Feature",
  "properties": {
    "date:inception_lower": "2000-12-01",
    "date:inception_upper": "2000-12-01",
    "iso:country": "GB",
    "wof:name": "M14 7DH",
    "wof:placetype": "postalcode"
  },
  "geometry": {"coordinates":[-2.225469,53.442971],"type":"Point"}
}
