{
  "type": "Feature",
  "properties": {
    "iso:country":"GB",
    "wof:name":"M14 7DH",
    "wof:placetype":"postalcode"
},
  "geometry": {"coordinates":[-2.22546900714442,53.44297125398794],"type":"Point"}
}