{
  "type": "Feature",
  "properties": {
    "date:inception_lower":"2008-01-01",
    "date:inception_upper":"2008-01-31",
    "iso:country":"GB",
    "wof:name":"HD6 2WB",
    "wof:placetype":"postalcode"
},
  "geometry": {"coordinates":[-1.775121,53.698358],"type":"Point"}
}