{
  "type": "Feature",
  "properties": {
    "iso:country": "GB",
    "wof:name": "NE19 1ND",
    "wof:placetype": "postalcode"
  },
  "geometry": {"coordinates":[-2.139502,55.219685],"type":"Point"}
}
