{
  "type": "Feature",
  "properties": {
    "iso:country":"GB",
    "wof:name":"EN1 4QE",
    "wof:placetype":"postalcode"
},
  "geometry": {"coordinates":[-0.0498130185843,51.67346087135078],"type":"Point"}
}