{
  "type": "Feature",
  "properties": {
    "iso:country":"GB",
    "wof:name":"YO30 4UL",
    "wof:placetype":"postalcode"
},
  "geometry": {"coordinates":[-1.1035163228274,53.98703722370991],"type":"Point"}
}