{
  "type": "Feature",
  "properties": {
    "date:inception_lower": "1998-06-01",
    "date:inception_upper": "1998-06-01",
    "iso:country": "GB",
    "wof:name": "YO30 4UL",
    "wof:placetype": "postalcode"
  },
  "geometry": {"coordinates":[-1.103516,53.987037],"type":"Point"}
}
