{
  "type": "Feature",
  "properties": {
    "iso:country":"GB",
    "wof:name":"OL2 8DP",
    "wof:placetype":"postalcode"
},
  "geometry": {"coordinates":[-2.08505603051617,53.58783108684096],"type":"Point"}
}