{
  "type": "Feature",
  "properties": {
    "date:inception_lower": "1980-01-01",
    "date:inception_upper": "1980-01-01",
    "iso:country": "GB",
    "wof:name": "OL2 8DP",
    "wof:placetype": "postalcode"
  },
  "geometry": {"coordinates":[-2.085056,53.587831],"type":"Point"}
}
