{
  "type": "Feature",
  "properties": {
    "iso:country": "GB",
    "wof:name": "NN17 3HJ",
    "wof:placetype": "postalcode"
  },
  "geometry": {"coordinates":[-0.644045,52.496136],"type":"Point"}
}
