{
  "type": "Feature",
  "properties": {
    "iso:country":"GB",
    "wof:name":"HP27 0QA",
    "wof:placetype":"postalcode"
},
  "geometry": {"coordinates":[-0.79485589388065,51.69152423855542],"type":"Point"}
}