{
  "type": "Feature",
  "properties": {
    "iso:country": "GB",
    "wof:name": "IV31 6JZ",
    "wof:placetype": "postalcode"
  },
  "geometry": {"coordinates":[-3.289705,57.719011],"type":"Point"}
}
