{
  "type": "Feature",
  "properties": {
    "iso:country":"GB",
    "wof:name":"EH17 8JD",
    "wof:placetype":"postalcode"
},
  "geometry": {"coordinates":[-3.14793965447366,55.90387448873141],"type":"Point"}
}