{
  "type": "Feature",
  "properties": {
    "iso:country":"GB",
    "wof:name":"CM4 9ED",
    "wof:placetype":"postalcode"
},
  "geometry": {"coordinates":[0.38784280678416,51.6718964680728],"type":"Point"}
}