{
  "type": "Feature",
  "properties": {
    "iso:country":"GB",
    "wof:name":"RG24 8LP",
    "wof:placetype":"postalcode"
},
  "geometry": {"coordinates":[-1.05084130666699,51.29060878884616],"type":"Point"}
}