{
  "type": "Feature",
  "properties": {
    "iso:country": "GB",
    "wof:name": "OX18 1AR",
    "wof:placetype": "postalcode"
  },
  "geometry": {"coordinates":[-1.587385,51.769574],"type":"Point"}
}
