{
  "type": "Feature",
  "properties": {
    "date:inception_lower":"1980-01-01",
    "date:inception_upper":"1980-01-31",
    "iso:country":"GB",
    "wof:name":"CT14 8HE",
    "wof:placetype":"postalcode"
},
  "geometry": {"coordinates":[1.378129,51.186232],"type":"Point"}
}