{
  "type": "Feature",
  "properties": {
    "iso:country": "GB",
    "wof:name": "RH12 2BJ",
    "wof:placetype": "postalcode"
  },
  "geometry": {"coordinates":[-0.331458,51.068036],"type":"Point"}
}
