{
  "type": "Feature",
  "properties": {
    "iso:country": "GB",
    "wof:name": "NR14 6BF",
    "wof:placetype": "postalcode"
  },
  "geometry": {"coordinates":[1.454263,52.545106],"type":"Point"}
}
