{
  "type": "Feature",
  "properties": {
    "iso:country":"GB",
    "wof:name":"NR14 6BF",
    "wof:placetype":"postalcode"
},
  "geometry": {"coordinates":[1.45426271580801,52.54510564786033],"type":"Point"}
}