{
  "type": "Feature",
  "properties": {
    "iso:country":"GB",
    "wof:name":"SN25 3EA",
    "wof:placetype":"postalcode"
},
  "geometry": {"coordinates":[-1.80442072204018,51.58325258195358],"type":"Point"}
}