{
  "type": "Feature",
  "properties": {
    "iso:country":"GB",
    "wof:name":"WF10 3UA",
    "wof:placetype":"postalcode"
},
  "geometry": {"coordinates":[-1.32541508260516,53.72992780234768],"type":"Point"}
}