{
  "type": "Feature",
  "properties": {
    "iso:country":"GB",
    "wof:name":"LE2 5RF",
    "wof:placetype":"postalcode"
},
  "geometry": {"coordinates":[-1.07177698042567,52.59425619577425],"type":"Point"}
}