{
  "type": "Feature",
  "properties": {
    "date:inception_lower": "2009-02-01",
    "date:inception_upper": "2009-02-01",
    "iso:country": "GB",
    "wof:name": "SO23 9BN",
    "wof:placetype": "postalcode"
  },
  "geometry": {"coordinates":[-1.307439,51.051068],"type":"Point"}
}
