{
  "type": "Feature",
  "properties": {
    "iso:country":"GB",
    "wof:name":"SO23 9BN",
    "wof:placetype":"postalcode"
},
  "geometry": {"coordinates":[-1.30743879339857,51.0510677400515],"type":"Point"}
}