{
  "type": "Feature",
  "properties": {
    "date:inception_lower": "1980-01-01",
    "date:inception_upper": "1980-01-01",
    "iso:country": "GB",
    "wof:name": "CO11 1BE",
    "wof:placetype": "postalcode"
  },
  "geometry": {"coordinates":[1.064348,51.944969],"type":"Point"}
}
