{
  "type": "Feature",
  "properties": {
    "iso:country":"GB",
    "wof:name":"CO11 1BE",
    "wof:placetype":"postalcode"
},
  "geometry": {"coordinates":[1.06491509998381,51.94495931197665],"type":"Point"}
}