{
  "type": "Feature",
  "properties": {
    "iso:country":"GB",
    "wof:name":"IP18 6QB",
    "wof:placetype":"postalcode"
},
  "geometry": {"coordinates":[1.66812723878918,52.33943968890419],"type":"Point"}
}