{
  "type": "Feature",
  "properties": {
    "iso:country": "GB",
    "wof:name": "IP18 6QB",
    "wof:placetype": "postalcode"
  },
  "geometry": {"coordinates":[1.668156,52.339464],"type":"Point"}
}
