{
  "type": "Feature",
  "properties": {
    "iso:country":"GB",
    "wof:name":"TW7 6JT",
    "wof:placetype":"postalcode"
},
  "geometry": {"coordinates":[-0.33997007114833,51.47169318099468],"type":"Point"}
}