{
  "type": "Feature",
  "properties": {
    "iso:country":"GB",
    "wof:name":"NR32 3AN",
    "wof:placetype":"postalcode"
},
  "geometry": {"coordinates":[1.71643558460528,52.49158806782024],"type":"Point"}
}