{
  "type": "Feature",
  "properties": {
    "iso:country": "GB",
    "wof:name": "NR32 3AN",
    "wof:placetype": "postalcode"
  },
  "geometry": {"coordinates":[1.716436,52.491588],"type":"Point"}
}
