{
  "type": "Feature",
  "properties": {
    "iso:country":"GB",
    "wof:name":"IV15 9AD",
    "wof:placetype":"postalcode"
},
  "geometry": {"coordinates":[-4.43107675800943,57.60889896072848],"type":"Point"}
}