{
  "type": "Feature",
  "properties": {
    "iso:country":"GB",
    "wof:name":"S40 4JX",
    "wof:placetype":"postalcode"
},
  "geometry": {"coordinates":[-1.45106185384755,53.24831570511968],"type":"Point"}
}