{
  "type": "Feature",
  "properties": {
    "date:inception_lower": "1980-01-01",
    "date:inception_upper": "1980-01-01",
    "iso:country": "GB",
    "wof:name": "PA2 6SA",
    "wof:placetype": "postalcode"
  },
  "geometry": {"coordinates":[-4.41185,55.831311],"type":"Point"}
}
