{
  "type": "Feature",
  "properties": {
    "iso:country": "GB",
    "wof:name": "PA2 6SA",
    "wof:placetype": "postalcode"
  },
  "geometry": {"coordinates":[-4.41185,55.831311],"type":"Point"}
}
