{
  "type": "Feature",
  "properties": {
    "iso:country":"GB",
    "wof:name":"CT14 9UW",
    "wof:placetype":"postalcode"
},
  "geometry": {"coordinates":[1.38594294613586,51.22288645199333],"type":"Point"}
}