{
  "type": "Feature",
  "properties": {
    "iso:country": "GB",
    "wof:name": "SA5 7LP",
    "wof:placetype": "postalcode"
  },
  "geometry": {"coordinates":[-3.966186,51.677403],"type":"Point"}
}
