{
  "type": "Feature",
  "properties": {
    "iso:country":"GB",
    "wof:name":"SA5 7LP",
    "wof:placetype":"postalcode"
},
  "geometry": {"coordinates":[-3.96618621752917,51.67740266627895],"type":"Point"}
}