{
  "type": "Feature",
  "properties": {
    "iso:country":"GB",
    "wof:name":"SW3 1RE",
    "wof:placetype":"postalcode"
},
  "geometry": {"coordinates":[-0.16342536342676,51.49754912326523],"type":"Point"}
}