{
  "type": "Feature",
  "properties": {
    "date:inception_lower": "1980-01-01",
    "date:inception_upper": "1980-01-01",
    "iso:country": "GB",
    "wof:name": "SW3 1RE",
    "wof:placetype": "postalcode"
  },
  "geometry": {"coordinates":[-0.163425,51.497549],"type":"Point"}
}
