{
  "type": "Feature",
  "properties": {
    "iso:country": "GB",
    "wof:name": "GL1 1UN",
    "wof:placetype": "postalcode"
  },
  "geometry": {"coordinates":[-2.248217,51.860779],"type":"Point"}
}
