{
  "type": "Feature",
  "properties": {
    "iso:country":"GB",
    "wof:name":"CF15 8DE",
    "wof:placetype":"postalcode"
},
  "geometry": {"coordinates":[-3.26184349664175,51.52000720203201],"type":"Point"}
}