{
  "type": "Feature",
  "properties": {
    "iso:country": "GB",
    "wof:name": "BN43 5BY",
    "wof:placetype": "postalcode"
  },
  "geometry": {"coordinates":[-0.262201,50.830336],"type":"Point"}
}
