{
  "type": "Feature",
  "properties": {
    "iso:country":"GB",
    "wof:name":"BN43 5BY",
    "wof:placetype":"postalcode"
},
  "geometry": {"coordinates":[-0.26220108803403,50.83033618883427],"type":"Point"}
}