{
  "type": "Feature",
  "properties": {
    "iso:country":"GB",
    "wof:name":"ZE2 9QT",
    "wof:placetype":"postalcode"
},
  "geometry": {"coordinates":[-1.21063786094409,60.47055589424361],"type":"Point"}
}