{
  "type": "Feature",
  "properties": {
    "iso:country":"GB",
    "wof:name":"DL3 6DY",
    "wof:placetype":"postalcode"
},
  "geometry": {"coordinates":[-1.56759435806764,54.53636441853721],"type":"Point"}
}