{
  "type": "Feature",
  "properties": {
    "iso:country": "GB",
    "wof:name": "M33 5FR",
    "wof:placetype": "postalcode"
  },
  "geometry": {"coordinates":[-2.347361,53.429086],"type":"Point"}
}
