{
  "type": "Feature",
  "properties": {
    "iso:country": "GB",
    "wof:name": "GU9 0NJ",
    "wof:placetype": "postalcode"
  },
  "geometry": {"coordinates":[-0.786563,51.229656],"type":"Point"}
}
