{
  "type": "Feature",
  "properties": {
    "iso:country":"GB",
    "wof:name":"GU21 4ZA",
    "wof:placetype":"postalcode"
},
  "geometry": {"coordinates":[-0.58972130662403,51.32875826508258],"type":"Point"}
}