{
  "type": "Feature",
  "properties": {
    "date:inception_lower":"2012-05-01",
    "date:inception_upper":"2012-05-31",
    "iso:country":"GB",
    "wof:name":"GU21 4ZA",
    "wof:placetype":"postalcode"
},
  "geometry": {"coordinates":[-0.589721,51.328758],"type":"Point"}
}