{
  "type": "Feature",
  "properties": {
    "iso:country":"GB",
    "wof:name":"EX4 1EB",
    "wof:placetype":"postalcode"
},
  "geometry": {"coordinates":[-3.54236795635847,50.71943764261227],"type":"Point"}
}