{
  "type": "Feature",
  "properties": {
    "iso:country": "GB",
    "wof:name": "EX4 1EB",
    "wof:placetype": "postalcode"
  },
  "geometry": {"coordinates":[-3.542368,50.719438],"type":"Point"}
}
