{
  "type": "Feature",
  "properties": {
    "iso:country":"GB",
    "wof:name":"NR15 2YQ",
    "wof:placetype":"postalcode"
},
  "geometry": {"coordinates":[1.22433831552783,52.50435428271609],"type":"Point"}
}