{
  "type": "Feature",
  "properties": {
    "iso:country":"GB",
    "wof:name":"LE16 8EW",
    "wof:placetype":"postalcode"
},
  "geometry": {"coordinates":[-0.91068652003341,52.47735016563657],"type":"Point"}
}