{
  "type": "Feature",
  "properties": {
    "iso:country": "GB",
    "wof:name": "LE16 8EW",
    "wof:placetype": "postalcode"
  },
  "geometry": {"coordinates":[-0.910686,52.47735],"type":"Point"}
}
