{
  "type": "Feature",
  "properties": {
    "iso:country": "GB",
    "wof:name": "BA5 3HE",
    "wof:placetype": "postalcode"
  },
  "geometry": {"coordinates":[-2.565552,51.221173],"type":"Point"}
}
