{
  "type": "Feature",
  "properties": {
    "iso:country":"GB",
    "wof:name":"BA5 3HE",
    "wof:placetype":"postalcode"
},
  "geometry": {"coordinates":[-2.56581507599696,51.21937826967109],"type":"Point"}
}