{
  "type": "Feature",
  "properties": {
    "date:inception_lower": "1980-01-01",
    "date:inception_upper": "1980-01-01",
    "iso:country": "GB",
    "wof:name": "BA5 3HE",
    "wof:placetype": "postalcode"
  },
  "geometry": {"coordinates":[-2.565552,51.221173],"type":"Point"}
}
