{
  "type": "Feature",
  "properties": {
    "iso:country":"GB",
    "wof:name":"EN2 8PB",
    "wof:placetype":"postalcode"
},
  "geometry": {"coordinates":[-0.09831830981615,51.65628061560747],"type":"Point"}
}