{
  "type": "Feature",
  "properties": {
    "date:inception_lower":"1986-07-01",
    "date:inception_upper":"1986-07-31",
    "iso:country":"GB",
    "wof:name":"HA3 0NW",
    "wof:placetype":"postalcode"
},
  "geometry": {"coordinates":[-0.303631,51.581761],"type":"Point"}
}