{
  "type": "Feature",
  "properties": {
    "iso:country":"GB",
    "wof:name":"HA3 0NW",
    "wof:placetype":"postalcode"
},
  "geometry": {"coordinates":[-0.30363146887519,51.5817605221246],"type":"Point"}
}