{
  "type": "Feature",
  "properties": {
    "iso:country": "GB",
    "wof:name": "DY14 0EX",
    "wof:placetype": "postalcode"
  },
  "geometry": {"coordinates":[-2.534002,52.404623],"type":"Point"}
}
