{
  "type": "Feature",
  "properties": {
    "date:inception_lower":"2002-06-01",
    "date:inception_upper":"2002-06-30",
    "iso:country":"GB",
    "wof:name":"DH6 1RE",
    "wof:placetype":"postalcode"
},
  "geometry": {"coordinates":[-1.490266,54.787271],"type":"Point"}
}