{
  "type": "Feature",
  "properties": {
    "date:inception_lower":"1980-01-01",
    "date:inception_upper":"1980-01-31",
    "iso:country":"GB",
    "wof:name":"WA15 0HP",
    "wof:placetype":"postalcode"
},
  "geometry": {"coordinates":[-2.314701,53.367822],"type":"Point"}
}