{
  "type": "Feature",
  "properties": {
    "iso:country":"GB",
    "wof:name":"WA15 0HP",
    "wof:placetype":"postalcode"
},
  "geometry": {"coordinates":[-2.31470133883241,53.36782248119903],"type":"Point"}
}