{
  "type": "Feature",
  "properties": {
    "iso:country": "GB",
    "wof:name": "LU3 3XH",
    "wof:placetype": "postalcode"
  },
  "geometry": {"coordinates":[-0.437685,51.915664],"type":"Point"}
}
