{
  "type": "Feature",
  "properties": {
    "iso:country": "GB",
    "wof:name": "RM17 6LH",
    "wof:placetype": "postalcode"
  },
  "geometry": {"coordinates":[0.333552,51.473649],"type":"Point"}
}
