{
  "type": "Feature",
  "properties": {
    "iso:country": "GB",
    "wof:name": "EH24 9BL",
    "wof:placetype": "postalcode"
  },
  "geometry": {"coordinates":[-3.1398,55.854305],"type":"Point"}
}
