{
  "type": "Feature",
  "properties": {
    "iso:country":"GB",
    "wof:name":"EH24 9BL",
    "wof:placetype":"postalcode"
},
  "geometry": {"coordinates":[-3.13980008429353,55.85430515189313],"type":"Point"}
}