{
  "type": "Feature",
  "properties": {
    "date:inception_lower": "1980-01-01",
    "date:inception_upper": "1980-01-01",
    "iso:country": "GB",
    "wof:name": "SG13 7HG",
    "wof:placetype": "postalcode"
  },
  "geometry": {"coordinates":[-0.058509,51.799749],"type":"Point"}
}
