{
  "type": "Feature",
  "properties": {
    "iso:country":"GB",
    "wof:name":"PR7 1XN",
    "wof:placetype":"postalcode"
},
  "geometry": {"coordinates":[-2.64725495417463,53.66071306629833],"type":"Point"}
}