{
  "type": "Feature",
  "properties": {
    "iso:country":"GB",
    "wof:name":"NN3 7TJ",
    "wof:placetype":"postalcode"
},
  "geometry": {"coordinates":[-0.84372534305868,52.28710359585188],"type":"Point"}
}