{
  "type": "Feature",
  "properties": {
    "iso:country": "GB",
    "wof:name": "NN3 7TJ",
    "wof:placetype": "postalcode"
  },
  "geometry": {"coordinates":[-0.843696,52.2871],"type":"Point"}
}
