{
  "type": "Feature",
  "properties": {
    "iso:country":"GB",
    "wof:name":"BD18 1AN",
    "wof:placetype":"postalcode"
},
  "geometry": {"coordinates":[-1.76047557201922,53.82373115987727],"type":"Point"}
}