{
  "type": "Feature",
  "properties": {
    "iso:country":"GB",
    "wof:name":"CV2 3JW",
    "wof:placetype":"postalcode"
},
  "geometry": {"coordinates":[-1.46702654640762,52.42542472640049],"type":"Point"}
}