{
  "type": "Feature",
  "properties": {
    "iso:country":"GB",
    "wof:name":"NE48 2ET",
    "wof:placetype":"postalcode"
},
  "geometry": {"coordinates":[-2.21293480742638,55.13390733807356],"type":"Point"}
}