{
  "type": "Feature",
  "properties": {
    "iso:country":"GB",
    "wof:name":"RG17 7TT",
    "wof:placetype":"postalcode"
},
  "geometry": {"coordinates":[-1.55028179820151,51.48483524462096],"type":"Point"}
}