{
  "type": "Feature",
  "properties": {
    "iso:country":"GB",
    "wof:name":"BS16 6ET",
    "wof:placetype":"postalcode"
},
  "geometry": {"coordinates":[-2.50602023922301,51.49031332253776],"type":"Point"}
}