{
  "type": "Feature",
  "properties": {
    "iso:country":"GB",
    "wof:name":"GU8 5NL",
    "wof:placetype":"postalcode"
},
  "geometry": {"coordinates":[-0.65145552929431,51.15333313691993],"type":"Point"}
}