{
  "type": "Feature",
  "properties": {
    "date:inception_lower":"1980-01-01",
    "date:inception_upper":"1980-01-31",
    "iso:country":"GB",
    "wof:name":"CV36 5NA",
    "wof:placetype":"postalcode"
},
  "geometry": {"coordinates":[-1.618042,52.017485],"type":"Point"}
}