{
  "type": "Feature",
  "properties": {
    "iso:country":"GB",
    "wof:name":"CV36 5NA",
    "wof:placetype":"postalcode"
},
  "geometry": {"coordinates":[-1.61804157631398,52.01748467998846],"type":"Point"}
}