{
  "type": "Feature",
  "properties": {
    "date:inception_lower":"1980-01-01",
    "date:inception_upper":"1980-01-31",
    "iso:country":"GB",
    "wof:name":"HD6 3QD",
    "wof:placetype":"postalcode"
},
  "geometry": {"coordinates":[-1.811962,53.683457],"type":"Point"}
}