{
  "type": "Feature",
  "properties": {
    "date:inception_lower": "1984-02-01",
    "date:inception_upper": "1984-02-01",
    "iso:country": "GB",
    "wof:name": "CV36 4PP",
    "wof:placetype": "postalcode"
  },
  "geometry": {"coordinates":[-1.623971,52.062826],"type":"Point"}
}
