{
  "type": "Feature",
  "properties": {
    "iso:country":"GB",
    "wof:name":"NW2 7LU",
    "wof:placetype":"postalcode"
},
  "geometry": {"coordinates":[-0.23424031730074,51.56598960645817],"type":"Point"}
}