{
  "type": "Feature",
  "properties": {
    "iso:country": "GB",
    "wof:name": "OX10 6FF",
    "wof:placetype": "postalcode"
  },
  "geometry": {"coordinates":[-1.113608,51.623512],"type":"Point"}
}
