{
  "type": "Feature",
  "properties": {
    "iso:country":"GB",
    "wof:name":"SS0 0RE",
    "wof:placetype":"postalcode"
},
  "geometry": {"coordinates":[0.69691946938194,51.55224389871773],"type":"Point"}
}