{
  "type": "Feature",
  "properties": {
    "iso:country":"GB",
    "wof:name":"LS17 8HR",
    "wof:placetype":"postalcode"
},
  "geometry": {"coordinates":[-1.47871258548768,53.8528582707924],"type":"Point"}
}