{
  "type": "Feature",
  "properties": {
    "date:inception_lower": "1980-01-01",
    "date:inception_upper": "1980-01-01",
    "iso:country": "GB",
    "wof:name": "LS17 8HR",
    "wof:placetype": "postalcode"
  },
  "geometry": {"coordinates":[-1.478713,53.852858],"type":"Point"}
}
