{
  "type": "Feature",
  "properties": {
    "iso:country":"GB",
    "wof:name":"AB42 3NB",
    "wof:placetype":"postalcode"
},
  "geometry": {"coordinates":[-1.78092355424307,57.47190829493223],"type":"Point"}
}