{
  "type": "Feature",
  "properties": {
    "iso:country": "GB",
    "wof:name": "CV13 0JT",
    "wof:placetype": "postalcode"
  },
  "geometry": {"coordinates":[-1.404817,52.624598],"type":"Point"}
}
