{
  "type": "Feature",
  "properties": {
    "iso:country":"GB",
    "wof:name":"DL13 2EU",
    "wof:placetype":"postalcode"
},
  "geometry": {"coordinates":[-2.02788204340541,54.78897507451732],"type":"Point"}
}