{
  "type": "Feature",
  "properties": {
    "iso:country":"GB",
    "wof:name":"SW4 7LB",
    "wof:placetype":"postalcode"
},
  "geometry": {"coordinates":[-0.13300175434604,51.45971361700624],"type":"Point"}
}