{
  "type": "Feature",
  "properties": {
    "iso:country":"GB",
    "wof:name":"DY5 1HH",
    "wof:placetype":"postalcode"
},
  "geometry": {"coordinates":[-2.12099906026045,52.48925865316779],"type":"Point"}
}