{
  "type": "Feature",
  "properties": {
    "date:inception_lower": "1980-01-01",
    "date:inception_upper": "1980-01-01",
    "iso:country": "GB",
    "wof:name": "DY5 1HH",
    "wof:placetype": "postalcode"
  },
  "geometry": {"coordinates":[-2.121008,52.489273],"type":"Point"}
}
