{
  "type": "Feature",
  "properties": {
    "date:inception_lower":"1981-06-01",
    "date:inception_upper":"1981-06-30",
    "iso:country":"GB",
    "wof:name":"BA5 2FB",
    "wof:placetype":"postalcode"
},
  "geometry": {"coordinates":[-2.661445,51.210136],"type":"Point"}
}