{
  "type": "Feature",
  "properties": {
    "date:inception_lower":"1980-01-01",
    "date:inception_upper":"1980-01-31",
    "iso:country":"GB",
    "wof:name":"SY4 2JJ",
    "wof:placetype":"postalcode"
},
  "geometry": {"coordinates":[-2.830486,52.800334],"type":"Point"}
}