{
  "type": "Feature",
  "properties": {
    "iso:country":"GB",
    "wof:name":"SY4 2JJ",
    "wof:placetype":"postalcode"
},
  "geometry": {"coordinates":[-2.8304864492987,52.8003336622803],"type":"Point"}
}