{
  "type": "Feature",
  "properties": {
    "iso:country": "GB",
    "wof:name": "SY4 2JJ",
    "wof:placetype": "postalcode"
  },
  "geometry": {"coordinates":[-2.830486,52.800334],"type":"Point"}
}
