{
  "type": "Feature",
  "properties": {
    "date:inception_lower": "1980-01-01",
    "date:inception_upper": "1980-01-01",
    "iso:country": "GB",
    "wof:name": "ST17 0DP",
    "wof:placetype": "postalcode"
  },
  "geometry": {"coordinates":[-2.078853,52.786054],"type":"Point"}
}
