{
  "type": "Feature",
  "properties": {
    "iso:country":"GB",
    "wof:name":"ST17 0DP",
    "wof:placetype":"postalcode"
},
  "geometry": {"coordinates":[-2.07885327786175,52.78605395649816],"type":"Point"}
}