{
  "type": "Feature",
  "properties": {
    "iso:country": "GB",
    "wof:name": "CA3 8AQ",
    "wof:placetype": "postalcode"
  },
  "geometry": {"coordinates":[-2.936889,54.893435],"type":"Point"}
}
