{
  "type": "Feature",
  "properties": {
    "iso:country":"GB",
    "wof:name":"CA3 8AQ",
    "wof:placetype":"postalcode"
},
  "geometry": {"coordinates":[-2.93688884712578,54.89343469061915],"type":"Point"}
}