{
  "type": "Feature",
  "properties": {
    "date:inception_lower":"1996-12-01",
    "date:inception_upper":"1996-12-31",
    "iso:country":"GB",
    "wof:name":"PA16 9LZ",
    "wof:placetype":"postalcode"
},
  "geometry": {"coordinates":[-4.801322,55.943252],"type":"Point"}
}