{
  "type": "Feature",
  "properties": {
    "iso:country":"GB",
    "wof:name":"G41 3PF",
    "wof:placetype":"postalcode"
},
  "geometry": {"coordinates":[-4.28551532190187,55.82714526261378],"type":"Point"}
}