{
  "type": "Feature",
  "properties": {
    "iso:country": "GB",
    "wof:name": "G41 3PF",
    "wof:placetype": "postalcode"
  },
  "geometry": {"coordinates":[-4.285515,55.827145],"type":"Point"}
}
