{
  "type": "Feature",
  "properties": {
    "iso:country":"GB",
    "wof:name":"N7 9PQ",
    "wof:placetype":"postalcode"
},
  "geometry": {"coordinates":[-0.12583212120524,51.54402117935806],"type":"Point"}
}