{
  "type": "Feature",
  "properties": {
    "iso:country":"GB",
    "wof:name":"LE16 9UD",
    "wof:placetype":"postalcode"
},
  "geometry": {"coordinates":[-1.00182695635118,52.43829989283017],"type":"Point"}
}