{
  "type": "Feature",
  "properties": {
    "iso:country": "GB",
    "wof:name": "CW3 0JR",
    "wof:placetype": "postalcode"
  },
  "geometry": {"coordinates":[-2.506105,52.990525],"type":"Point"}
}
