{
  "type": "Feature",
  "properties": {
    "iso:country":"GB",
    "wof:name":"PE34 3LP",
    "wof:placetype":"postalcode"
},
  "geometry": {"coordinates":[0.38401102788041,52.74267056913481],"type":"Point"}
}