{
  "type": "Feature",
  "properties": {
    "iso:country":"GB",
    "wof:name":"UB9 6NX",
    "wof:placetype":"postalcode"
},
  "geometry": {"coordinates":[-0.47305833844881,51.60216103137299],"type":"Point"}
}