{
  "type": "Feature",
  "properties": {
    "date:inception_lower": "2004-05-01",
    "date:inception_upper": "2004-05-01",
    "iso:country": "GB",
    "wof:name": "UB9 6NX",
    "wof:placetype": "postalcode"
  },
  "geometry": {"coordinates":[-0.473058,51.602161],"type":"Point"}
}
