{
  "type": "Feature",
  "properties": {
    "iso:country":"GB",
    "wof:name":"SY7 0EA",
    "wof:placetype":"postalcode"
},
  "geometry": {"coordinates":[-2.93097574714839,52.28468460624403],"type":"Point"}
}