{
  "type": "Feature",
  "properties": {
    "iso:country":"GB",
    "wof:name":"PR4 1RH",
    "wof:placetype":"postalcode"
},
  "geometry": {"coordinates":[-2.86627642340388,53.7516213094035],"type":"Point"}
}