{
  "type": "Feature",
  "properties": {
    "iso:country": "GB",
    "wof:name": "PR4 1RH",
    "wof:placetype": "postalcode"
  },
  "geometry": {"coordinates":[-2.866276,53.751621],"type":"Point"}
}
