{
  "type": "Feature",
  "properties": {
    "iso:country": "GB",
    "wof:name": "SE3 7DX",
    "wof:placetype": "postalcode"
  },
  "geometry": {"coordinates":[0.020193,51.481877],"type":"Point"}
}
