{
  "type": "Feature",
  "properties": {
    "date:inception_lower": "1980-01-01",
    "date:inception_upper": "1980-01-01",
    "iso:country": "GB",
    "wof:name": "M13 0LX",
    "wof:placetype": "postalcode"
  },
  "geometry": {"coordinates":[-2.208072,53.45973],"type":"Point"}
}
