{
  "type": "Feature",
  "properties": {
    "date:inception_lower": "1995-07-01",
    "date:inception_upper": "1995-07-01",
    "iso:country": "GB",
    "wof:name": "CF72 8ER",
    "wof:placetype": "postalcode"
  },
  "geometry": {"coordinates":[-3.376194,51.540401],"type":"Point"}
}
