{
  "type": "Feature",
  "properties": {
    "date:inception_lower":"1980-01-01",
    "date:inception_upper":"1980-01-31",
    "iso:country":"GB",
    "wof:name":"OX15 4NY",
    "wof:placetype":"postalcode"
},
  "geometry": {"coordinates":[-1.370621,52.024029],"type":"Point"}
}