{
  "type": "Feature",
  "properties": {
    "iso:country":"GB",
    "wof:name":"EN9 1XD",
    "wof:placetype":"postalcode"
},
  "geometry": {"coordinates":[0.0051904667537,51.68558264592109],"type":"Point"}
}