{
  "type": "Feature",
  "properties": {
    "date:inception_lower": "1998-06-01",
    "date:inception_upper": "1998-06-01",
    "iso:country": "GB",
    "wof:name": "YO30 6ER",
    "wof:placetype": "postalcode"
  },
  "geometry": {"coordinates":[-1.085284,53.972456],"type":"Point"}
}
