{
  "type": "Feature",
  "properties": {
    "iso:country": "GB",
    "wof:name": "SK9 3BJ",
    "wof:placetype": "postalcode"
  },
  "geometry": {"coordinates":[-2.21028,53.342937],"type":"Point"}
}
