{
  "type": "Feature",
  "properties": {
    "iso:country":"GB",
    "wof:name":"SW16 5BS",
    "wof:placetype":"postalcode"
},
  "geometry": {"coordinates":[-0.13857850698073,51.41957834757939],"type":"Point"}
}