{
  "type": "Feature",
  "properties": {
    "iso:country": "GB",
    "wof:name": "BS34 6LD",
    "wof:placetype": "postalcode"
  },
  "geometry": {"coordinates":[-2.555505,51.52413],"type":"Point"}
}
