{
  "type": "Feature",
  "properties": {
    "iso:country":"GB",
    "wof:name":"BS34 6LD",
    "wof:placetype":"postalcode"
},
  "geometry": {"coordinates":[-2.55553240699529,51.52414912942647],"type":"Point"}
}