{
  "type": "Feature",
  "properties": {
    "iso:country": "GB",
    "wof:name": "CH2 3AP",
    "wof:placetype": "postalcode"
  },
  "geometry": {"coordinates":[-2.873703,53.196977],"type":"Point"}
}
