{
  "type": "Feature",
  "properties": {
    "iso:country":"GB",
    "wof:name":"S44 5PJ",
    "wof:placetype":"postalcode"
},
  "geometry": {"coordinates":[-1.3042229871604,53.18998381128517],"type":"Point"}
}