{
  "type": "Feature",
  "properties": {
    "date:inception_lower": "1980-01-01",
    "date:inception_upper": "1980-01-01",
    "iso:country": "GB",
    "wof:name": "S44 5PJ",
    "wof:placetype": "postalcode"
  },
  "geometry": {"coordinates":[-1.304223,53.189984],"type":"Point"}
}
