{
  "type": "Feature",
  "properties": {
    "iso:country":"GB",
    "wof:name":"KA21 6AP",
    "wof:placetype":"postalcode"
},
  "geometry": {"coordinates":[-4.78338249866832,55.64572195731917],"type":"Point"}
}