{
  "type": "Feature",
  "properties": {
    "iso:country":"GB",
    "wof:name":"TR16 5DH",
    "wof:placetype":"postalcode"
},
  "geometry": {"coordinates":[-5.2075678774669,50.26640631848892],"type":"Point"}
}