{
  "type": "Feature",
  "properties": {
    "iso:country":"GB",
    "wof:name":"BN20 7XW",
    "wof:placetype":"postalcode"
},
  "geometry": {"coordinates":[0.26404737070991,50.75242504657967],"type":"Point"}
}