{
  "type": "Feature",
  "properties": {
    "iso:country":"GB",
    "wof:name":"PO3 6GN",
    "wof:placetype":"postalcode"
},
  "geometry": {"coordinates":[-1.06462159836461,50.80041715937087],"type":"Point"}
}