{
  "type": "Feature",
  "properties": {
    "iso:country":"GB",
    "wof:name":"HU12 8PQ",
    "wof:placetype":"postalcode"
},
  "geometry": {"coordinates":[-0.2310425591938,53.71802456997217],"type":"Point"}
}