{
  "type": "Feature",
  "properties": {
    "date:inception_lower": "1990-07-01",
    "date:inception_upper": "1990-07-01",
    "iso:country": "GB",
    "wof:name": "HU12 8PQ",
    "wof:placetype": "postalcode"
  },
  "geometry": {"coordinates":[-0.231043,53.718025],"type":"Point"}
}
