{
  "type": "Feature",
  "properties": {
    "iso:country": "GB",
    "wof:name": "HU12 8PQ",
    "wof:placetype": "postalcode"
  },
  "geometry": {"coordinates":[-0.231043,53.718025],"type":"Point"}
}
