{
  "type": "Feature",
  "properties": {
    "date:inception_lower":"2009-08-01",
    "date:inception_upper":"2009-08-31",
    "iso:country":"GB",
    "wof:name":"CM22 7FE",
    "wof:placetype":"postalcode"
},
  "geometry": {"coordinates":[0.204835,51.816137],"type":"Point"}
}