{
  "type": "Feature",
  "properties": {
    "iso:country":"GB",
    "wof:name":"CO6 2DQ",
    "wof:placetype":"postalcode"
},
  "geometry": {"coordinates":[0.75893021801714,51.92199112640288],"type":"Point"}
}