{
  "type": "Feature",
  "properties": {
    "date:inception_lower": "1980-01-01",
    "date:inception_upper": "1980-01-01",
    "iso:country": "GB",
    "wof:name": "CO6 2DQ",
    "wof:placetype": "postalcode"
  },
  "geometry": {"coordinates":[0.75893,51.921991],"type":"Point"}
}
