{
  "type": "Feature",
  "properties": {
    "iso:country":"GB",
    "wof:name":"IP32 7PN",
    "wof:placetype":"postalcode"
},
  "geometry": {"coordinates":[0.75610777221756,52.24476594566051],"type":"Point"}
}