{
  "type": "Feature",
  "properties": {
    "date:inception_lower":"2007-05-01",
    "date:inception_upper":"2007-05-31",
    "iso:country":"GB",
    "wof:name":"IP32 7PN",
    "wof:placetype":"postalcode"
},
  "geometry": {"coordinates":[0.756108,52.244766],"type":"Point"}
}