{
  "type": "Feature",
  "properties": {
    "iso:country":"GB",
    "wof:name":"PO16 7UY",
    "wof:placetype":"postalcode"
},
  "geometry": {"coordinates":[-1.19854896386466,50.8684721479563],"type":"Point"}
}