{
  "type": "Feature",
  "properties": {
    "iso:country": "GB",
    "wof:name": "KA7 4EL",
    "wof:placetype": "postalcode"
  },
  "geometry": {"coordinates":[-4.660233,55.436984],"type":"Point"}
}
