{
  "type": "Feature",
  "properties": {
    "date:inception_lower": "1980-01-01",
    "date:inception_upper": "1980-01-01",
    "iso:country": "GB",
    "wof:name": "S12 3AT",
    "wof:placetype": "postalcode"
  },
  "geometry": {"coordinates":[-1.39885,53.341172],"type":"Point"}
}
