{
  "type": "Feature",
  "properties": {
    "iso:country": "GB",
    "wof:name": "S12 3AT",
    "wof:placetype": "postalcode"
  },
  "geometry": {"coordinates":[-1.39885,53.341172],"type":"Point"}
}
