{
  "type": "Feature",
  "properties": {
    "iso:country":"GB",
    "wof:name":"S12 3AT",
    "wof:placetype":"postalcode"
},
  "geometry": {"coordinates":[-1.39883573323582,53.3411345390971],"type":"Point"}
}