{
  "type": "Feature",
  "properties": {
    "iso:country":"GB",
    "wof:name":"RG9 2LF",
    "wof:placetype":"postalcode"
},
  "geometry": {"coordinates":[-0.91095601722825,51.54312650599886],"type":"Point"}
}