{
  "type": "Feature",
  "properties": {
    "date:inception_lower": "1980-01-01",
    "date:inception_upper": "1980-01-01",
    "iso:country": "GB",
    "wof:name": "RG9 2LF",
    "wof:placetype": "postalcode"
  },
  "geometry": {"coordinates":[-0.910956,51.543127],"type":"Point"}
}
