{
  "type": "Feature",
  "properties": {
    "date:inception_lower":"1980-01-01",
    "date:inception_upper":"1980-01-31",
    "iso:country":"GB",
    "wof:name":"NE38 7JJ",
    "wof:placetype":"postalcode"
},
  "geometry": {"coordinates":[-1.522458,54.904451],"type":"Point"}
}