{
  "type": "Feature",
  "properties": {
    "iso:country":"GB",
    "wof:name":"WR9 8PF",
    "wof:placetype":"postalcode"
},
  "geometry": {"coordinates":[-2.16685699164978,52.25897454028227],"type":"Point"}
}