{
  "type": "Feature",
  "properties": {
    "iso:country":"GB",
    "wof:name":"BR3 5LE",
    "wof:placetype":"postalcode"
},
  "geometry": {"coordinates":[-0.02254366233292,51.40714736136265],"type":"Point"}
}