{
  "type": "Feature",
  "properties": {
    "iso:country":"GB",
    "wof:name":"PE10 0QL",
    "wof:placetype":"postalcode"
},
  "geometry": {"coordinates":[-0.37133789281413,52.75589945696558],"type":"Point"}
}