{
  "type": "Feature",
  "properties": {
    "date:inception_lower":"1980-01-01",
    "date:inception_upper":"1980-01-31",
    "iso:country":"GB",
    "wof:name":"TA8 1BY",
    "wof:placetype":"postalcode"
},
  "geometry": {"coordinates":[-2.998823,51.231787],"type":"Point"}
}