{
  "type": "Feature",
  "properties": {
    "date:inception_lower": "1993-08-01",
    "date:inception_upper": "1993-08-01",
    "iso:country": "GB",
    "wof:name": "CF48 2SD",
    "wof:placetype": "postalcode"
  },
  "geometry": {"coordinates":[-3.398303,51.756659],"type":"Point"}
}
