{
  "type": "Feature",
  "properties": {
    "date:inception_lower": "1984-02-01",
    "date:inception_upper": "1984-02-01",
    "iso:country": "GB",
    "wof:name": "UB3 4BN",
    "wof:placetype": "postalcode"
  },
  "geometry": {"coordinates":[-0.428917,51.498313],"type":"Point"}
}
