{
  "type": "Feature",
  "properties": {
    "iso:country":"GB",
    "wof:name":"UB3 4BN",
    "wof:placetype":"postalcode"
},
  "geometry": {"coordinates":[-0.42891663564168,51.49831271743123],"type":"Point"}
}