{
  "type": "Feature",
  "properties": {
    "date:inception_lower": "2017-03-01",
    "date:inception_upper": "2017-03-01",
    "iso:country": "GB",
    "wof:name": "CM8 3FR",
    "wof:placetype": "postalcode"
  },
  "geometry": {"coordinates":[0.701507,51.795979],"type":"Point"}
}
