{
  "type": "Feature",
  "properties": {
    "iso:country": "GB",
    "wof:name": "CM8 3FR",
    "wof:placetype": "postalcode"
  },
  "geometry": {"coordinates":[0.701507,51.795979],"type":"Point"}
}
