{
  "type": "Feature",
  "properties": {
    "iso:country":"GB",
    "wof:name":"LS29 9BD",
    "wof:placetype":"postalcode"
},
  "geometry": {"coordinates":[-1.83315263716587,53.92636052280237],"type":"Point"}
}