{
  "type": "Feature",
  "properties": {
    "iso:country": "GB",
    "wof:name": "TF1 6FQ",
    "wof:placetype": "postalcode"
  },
  "geometry": {"coordinates":[-2.501392,52.713094],"type":"Point"}
}
