{
  "type": "Feature",
  "properties": {
    "iso:country":"GB",
    "wof:name":"L23 7TA",
    "wof:placetype":"postalcode"
},
  "geometry": {"coordinates":[-3.03301940801331,53.48962882548005],"type":"Point"}
}