{
  "type": "Feature",
  "properties": {
    "iso:country":"GB",
    "wof:name":"BA6 9HN",
    "wof:placetype":"postalcode"
},
  "geometry": {"coordinates":[-2.71920070019674,51.14892795882945],"type":"Point"}
}