{
  "type": "Feature",
  "properties": {
    "iso:country": "GB",
    "wof:name": "BA6 9HN",
    "wof:placetype": "postalcode"
  },
  "geometry": {"coordinates":[-2.719134,51.14894],"type":"Point"}
}
