{
  "type": "Feature",
  "properties": {
    "iso:country": "GB",
    "wof:name": "NG9 5FU",
    "wof:placetype": "postalcode"
  },
  "geometry": {"coordinates":[-1.243701,52.918759],"type":"Point"}
}
