{
  "type": "Feature",
  "properties": {
    "iso:country":"GB",
    "wof:name":"PH7 3DH",
    "wof:placetype":"postalcode"
},
  "geometry": {"coordinates":[-3.83472605559932,56.37858195165371],"type":"Point"}
}