{
  "type": "Feature",
  "properties": {
    "iso:country":"GB",
    "wof:name":"LE2 3PE",
    "wof:placetype":"postalcode"
},
  "geometry": {"coordinates":[-1.10860313426494,52.60334027724998],"type":"Point"}
}