{
  "type": "Feature",
  "properties": {
    "iso:country":"GB",
    "wof:name":"CB3 0WB",
    "wof:placetype":"postalcode"
},
  "geometry": {"coordinates":[0.10192791442489,52.21014307024245],"type":"Point"}
}