{
  "type": "Feature",
  "properties": {
    "iso:country": "GB",
    "wof:name": "BA2 8BT",
    "wof:placetype": "postalcode"
  },
  "geometry": {"coordinates":[-2.405002,51.342964],"type":"Point"}
}
