{
  "type": "Feature",
  "properties": {
    "iso:country": "GB",
    "wof:name": "NN13 5LJ",
    "wof:placetype": "postalcode"
  },
  "geometry": {"coordinates":[-1.176221,52.015649],"type":"Point"}
}
