{
  "type": "Feature",
  "properties": {
    "date:inception_lower":"2003-03-01",
    "date:inception_upper":"2003-03-31",
    "iso:country":"GB",
    "wof:name":"B69 4TU",
    "wof:placetype":"postalcode"
},
  "geometry": {"coordinates":[-2.016686,52.488214],"type":"Point"}
}