{
  "type": "Feature",
  "properties": {
    "iso:country":"GB",
    "wof:name":"NN9 5HA",
    "wof:placetype":"postalcode"
},
  "geometry": {"coordinates":[-0.64257061272435,52.33910590992542],"type":"Point"}
}