{
  "type": "Feature",
  "properties": {
    "iso:country":"GB",
    "wof:name":"NE10 8QR",
    "wof:placetype":"postalcode"
},
  "geometry": {"coordinates":[-1.55239781724463,54.93572033146999],"type":"Point"}
}