{
  "type": "Feature",
  "properties": {
    "iso:country":"GB",
    "wof:name":"SE1 3DF",
    "wof:placetype":"postalcode"
},
  "geometry": {"coordinates":[-0.08415059278634,51.4990865095284],"type":"Point"}
}