{
  "type": "Feature",
  "properties": {
    "date:inception_lower": "2017-01-01",
    "date:inception_upper": "2017-01-01",
    "iso:country": "GB",
    "wof:name": "CH5 3FA",
    "wof:placetype": "postalcode"
  },
  "geometry": {"coordinates":[-3.077278,53.191445],"type":"Point"}
}
