{
  "type": "Feature",
  "properties": {
    "iso:country":"GB",
    "wof:name":"BS9 4UN",
    "wof:placetype":"postalcode"
},
  "geometry": {"coordinates":[-2.60771742892731,51.49324704746731],"type":"Point"}
}