{
  "type": "Feature",
  "properties": {
    "iso:country":"GB",
    "wof:name":"ML5 2RS",
    "wof:placetype":"postalcode"
},
  "geometry": {"coordinates":[-4.05983084974886,55.89570481709225],"type":"Point"}
}