{
  "type": "Feature",
  "properties": {
    "iso:country":"GB",
    "wof:name":"DY13 9GL",
    "wof:placetype":"postalcode"
},
  "geometry": {"coordinates":[-2.26509463553551,52.34304231841208],"type":"Point"}
}