{
  "type": "Feature",
  "properties": {
    "date:inception_lower": "2005-03-01",
    "date:inception_upper": "2005-03-01",
    "iso:country": "GB",
    "wof:name": "DY13 9GL",
    "wof:placetype": "postalcode"
  },
  "geometry": {"coordinates":[-2.265095,52.343042],"type":"Point"}
}
