{
  "type": "Feature",
  "properties": {
    "iso:country": "GB",
    "wof:name": "DY13 9GL",
    "wof:placetype": "postalcode"
  },
  "geometry": {"coordinates":[-2.265095,52.343042],"type":"Point"}
}
