{
  "type": "Feature",
  "properties": {
    "iso:country":"GB",
    "wof:name":"BD3 9AR",
    "wof:placetype":"postalcode"
},
  "geometry": {"coordinates":[-1.7378074361624,53.7974119896603],"type":"Point"}
}