{
  "type": "Feature",
  "properties": {
    "iso:country":"GB",
    "wof:name":"LE2 6NH",
    "wof:placetype":"postalcode"
},
  "geometry": {"coordinates":[-1.13689525101872,52.60105052385702],"type":"Point"}
}