{
  "type": "Feature",
  "properties": {
    "iso:country":"GB",
    "wof:name":"WA2 7NS",
    "wof:placetype":"postalcode"
},
  "geometry": {"coordinates":[-2.59571057982581,53.39404003884372],"type":"Point"}
}