{
  "type": "Feature",
  "properties": {
    "iso:country":"GB",
    "wof:name":"S80 3EZ",
    "wof:placetype":"postalcode"
},
  "geometry": {"coordinates":[-1.14027405164187,53.31139901258507],"type":"Point"}
}