{
  "type": "Feature",
  "properties": {
    "iso:country": "GB",
    "wof:name": "TF7 5AQ",
    "wof:placetype": "postalcode"
  },
  "geometry": {"coordinates":[-2.448251,52.636543],"type":"Point"}
}
