{
  "type": "Feature",
  "properties": {
    "iso:country":"GB",
    "wof:name":"TF7 5AQ",
    "wof:placetype":"postalcode"
},
  "geometry": {"coordinates":[-2.44825067615307,52.63654343469879],"type":"Point"}
}