{
  "type": "Feature",
  "properties": {
    "date:inception_lower": "1980-01-01",
    "date:inception_upper": "1980-01-01",
    "iso:country": "GB",
    "wof:name": "TF7 5AQ",
    "wof:placetype": "postalcode"
  },
  "geometry": {"coordinates":[-2.448251,52.636543],"type":"Point"}
}
