{
  "type": "Feature",
  "properties": {
    "date:inception_lower": "2009-05-01",
    "date:inception_upper": "2009-05-01",
    "iso:country": "GB",
    "wof:name": "LS18 4GN",
    "wof:placetype": "postalcode"
  },
  "geometry": {"coordinates":[-1.638269,53.839394],"type":"Point"}
}
