{
  "type": "Feature",
  "properties": {
    "iso:country": "GB",
    "wof:name": "LS18 4GN",
    "wof:placetype": "postalcode"
  },
  "geometry": {"coordinates":[-1.63828,53.839343],"type":"Point"}
}
