{
  "type": "Feature",
  "properties": {
    "iso:country":"GB",
    "wof:name":"HU8 9EE",
    "wof:placetype":"postalcode"
},
  "geometry": {"coordinates":[-0.27401326155087,53.77152613023232],"type":"Point"}
}