{
  "type": "Feature",
  "properties": {
    "date:inception_lower":"1980-01-01",
    "date:inception_upper":"1980-01-31",
    "iso:country":"GB",
    "wof:name":"HU8 9EE",
    "wof:placetype":"postalcode"
},
  "geometry": {"coordinates":[-0.274013,53.771526],"type":"Point"}
}