{
  "type": "Feature",
  "properties": {
    "iso:country": "GB",
    "wof:name": "CM9 8PD",
    "wof:placetype": "postalcode"
  },
  "geometry": {"coordinates":[0.694735,51.74927],"type":"Point"}
}
