{
  "type": "Feature",
  "properties": {
    "iso:country":"GB",
    "wof:name":"CM9 8PD",
    "wof:placetype":"postalcode"
},
  "geometry": {"coordinates":[0.69473480140874,51.74927007033678],"type":"Point"}
}