{
  "type": "Feature",
  "properties": {
    "iso:country":"GB",
    "wof:name":"YO1 6EJ",
    "wof:placetype":"postalcode"
},
  "geometry": {"coordinates":[-1.08783910006319,53.95557798437019],"type":"Point"}
}