{
  "type": "Feature",
  "properties": {
    "date:inception_lower": "2005-02-01",
    "date:inception_upper": "2005-02-01",
    "iso:country": "GB",
    "wof:name": "S40 9TL",
    "wof:placetype": "postalcode"
  },
  "geometry": {"coordinates":[-1.432586,53.237883],"type":"Point"}
}
