{
  "type": "Feature",
  "properties": {
    "iso:country": "GB",
    "wof:name": "PH10 7LY",
    "wof:placetype": "postalcode"
  },
  "geometry": {"coordinates":[-3.507365,56.722254],"type":"Point"}
}
