{
  "type": "Feature",
  "properties": {
    "iso:country":"GB",
    "wof:name":"PH10 7LY",
    "wof:placetype":"postalcode"
},
  "geometry": {"coordinates":[-3.50736459197705,56.72225401775388],"type":"Point"}
}