{
  "type": "Feature",
  "properties": {
    "iso:country":"GB",
    "wof:name":"LL60 6BB",
    "wof:placetype":"postalcode"
},
  "geometry": {"coordinates":[-4.22888687179367,53.22676259258729],"type":"Point"}
}