{
  "type": "Feature",
  "properties": {
    "iso:country": "GB",
    "wof:name": "RG27 9QU",
    "wof:placetype": "postalcode"
  },
  "geometry": {"coordinates":[-0.948852,51.287787],"type":"Point"}
}
