{
  "type": "Feature",
  "properties": {
    "iso:country":"GB",
    "wof:name":"IP14 3AS",
    "wof:placetype":"postalcode"
},
  "geometry": {"coordinates":[0.93574576632412,52.17051831201967],"type":"Point"}
}