{
  "type": "Feature",
  "properties": {
    "iso:country":"GB",
    "wof:name":"TF7 5FG",
    "wof:placetype":"postalcode"
},
  "geometry": {"coordinates":[-2.46649559712469,52.63752477511517],"type":"Point"}
}