{
  "type": "Feature",
  "properties": {
    "iso:country": "GB",
    "wof:name": "TF7 5FG",
    "wof:placetype": "postalcode"
  },
  "geometry": {"coordinates":[-2.466496,52.637525],"type":"Point"}
}
