{
  "type": "Feature",
  "properties": {
    "date:inception_lower":"2013-03-01",
    "date:inception_upper":"2013-03-31",
    "iso:country":"GB",
    "wof:name":"TF7 5FG",
    "wof:placetype":"postalcode"
},
  "geometry": {"coordinates":[-2.466496,52.637525],"type":"Point"}
}