{
  "type": "Feature",
  "properties": {
    "iso:country":"GB",
    "wof:name":"SE9 5BB",
    "wof:placetype":"postalcode"
},
  "geometry": {"coordinates":[0.05919914785304,51.4474303058918],"type":"Point"}
}