{
  "type": "Feature",
  "properties": {
    "iso:country":"GB",
    "wof:name":"TS12 1PZ",
    "wof:placetype":"postalcode"
},
  "geometry": {"coordinates":[-0.98085651763905,54.58125975678237],"type":"Point"}
}