{
  "type": "Feature",
  "properties": {
    "iso:country":"GB",
    "wof:name":"NP13 1LL",
    "wof:placetype":"postalcode"
},
  "geometry": {"coordinates":[-3.13381893051964,51.74625017449073],"type":"Point"}
}