{
  "type": "Feature",
  "properties": {
    "date:inception_lower": "1980-01-01",
    "date:inception_upper": "1980-01-01",
    "iso:country": "GB",
    "wof:name": "CB5 8HT",
    "wof:placetype": "postalcode"
  },
  "geometry": {"coordinates":[0.138775,52.210277],"type":"Point"}
}
