{
  "type": "Feature",
  "properties": {
    "date:inception_lower": "2022-04-01",
    "date:inception_upper": "2022-04-01",
    "iso:country": "GB",
    "wof:name": "SA7 0AT",
    "wof:placetype": "postalcode"
  },
  "geometry": {"coordinates":[-3.905024,51.670611],"type":"Point"}
}
