{
  "type": "Feature",
  "properties": {
    "iso:country": "GB",
    "wof:name": "L8 3SA",
    "wof:placetype": "postalcode"
  },
  "geometry": {"coordinates":[-2.950335,53.388534],"type":"Point"}
}
