{
  "type": "Feature",
  "properties": {
    "iso:country":"GB",
    "wof:name":"L8 3SA",
    "wof:placetype":"postalcode"
},
  "geometry": {"coordinates":[-2.95033553582469,53.38853425136593],"type":"Point"}
}