{
  "type": "Feature",
  "properties": {
    "iso:country":"GB",
    "wof:name":"TS5 8NH",
    "wof:placetype":"postalcode"
},
  "geometry": {"coordinates":[-1.2582278650104,54.5402019804797],"type":"Point"}
}