{
  "type": "Feature",
  "properties": {
    "iso:country":"GB",
    "wof:name":"DN33 2HB",
    "wof:placetype":"postalcode"
},
  "geometry": {"coordinates":[-0.08846974391583,53.53750599409256],"type":"Point"}
}