{
  "type": "Feature",
  "properties": {
    "iso:country": "GB",
    "wof:name": "IP18 6RH",
    "wof:placetype": "postalcode"
  },
  "geometry": {"coordinates":[1.674323,52.336414],"type":"Point"}
}
