{
  "type": "Feature",
  "properties": {
    "iso:country":"GB",
    "wof:name":"DE5 3EQ",
    "wof:placetype":"postalcode"
},
  "geometry": {"coordinates":[-1.40353741847497,53.04763112948563],"type":"Point"}
}