{
  "type": "Feature",
  "properties": {
    "iso:country": "GB",
    "wof:name": "MK45 3LE",
    "wof:placetype": "postalcode"
  },
  "geometry": {"coordinates":[-0.475839,52.061053],"type":"Point"}
}
