{
  "type": "Feature",
  "properties": {
    "iso:country":"GB",
    "wof:name":"MK45 3LE",
    "wof:placetype":"postalcode"
},
  "geometry": {"coordinates":[-0.47583926162837,52.06105267508133],"type":"Point"}
}