{
  "type": "Feature",
  "properties": {
    "iso:country":"GB",
    "wof:name":"LS7 4SX",
    "wof:placetype":"postalcode"
},
  "geometry": {"coordinates":[-1.52971109211965,53.82467580871446],"type":"Point"}
}