{
  "type": "Feature",
  "properties": {
    "iso:country":"GB",
    "wof:name":"BN5 9PH",
    "wof:placetype":"postalcode"
},
  "geometry": {"coordinates":[-0.27812088516661,50.93288835521662],"type":"Point"}
}