{
  "type": "Feature",
  "properties": {
    "iso:country": "GB",
    "wof:name": "BN5 9PH",
    "wof:placetype": "postalcode"
  },
  "geometry": {"coordinates":[-0.278121,50.932888],"type":"Point"}
}
