{
  "type": "Feature",
  "properties": {
    "iso:country":"GB",
    "wof:name":"GU25 4HL",
    "wof:placetype":"postalcode"
},
  "geometry": {"coordinates":[-0.56543398437327,51.39684973034878],"type":"Point"}
}