{
  "type": "Feature",
  "properties": {
    "iso:country": "GB",
    "wof:name": "FY3 7SY",
    "wof:placetype": "postalcode"
  },
  "geometry": {"coordinates":[-3.006898,53.8298],"type":"Point"}
}
