{
  "type": "Feature",
  "properties": {
    "iso:country":"GB",
    "wof:name":"FY3 7SY",
    "wof:placetype":"postalcode"
},
  "geometry": {"coordinates":[-3.00689813578828,53.82979975088065],"type":"Point"}
}