{
  "type": "Feature",
  "properties": {
    "date:inception_lower":"1980-01-01",
    "date:inception_upper":"1980-01-31",
    "iso:country":"GB",
    "wof:name":"FY3 7SY",
    "wof:placetype":"postalcode"
},
  "geometry": {"coordinates":[-3.006898,53.8298],"type":"Point"}
}