{
  "type": "Feature",
  "properties": {
    "iso:country":"GB",
    "wof:name":"L30 8RF",
    "wof:placetype":"postalcode"
},
  "geometry": {"coordinates":[-2.95369750427584,53.48571298196792],"type":"Point"}
}