{
  "type": "Feature",
  "properties": {
    "date:inception_lower": "1980-01-01",
    "date:inception_upper": "1980-01-01",
    "iso:country": "GB",
    "wof:name": "NE47 8HS",
    "wof:placetype": "postalcode"
  },
  "geometry": {"coordinates":[-2.36707,54.903323],"type":"Point"}
}
