{
  "type": "Feature",
  "properties": {
    "iso:country":"GB",
    "wof:name":"NE47 8HS",
    "wof:placetype":"postalcode"
},
  "geometry": {"coordinates":[-2.36707038388983,54.90332306887208],"type":"Point"}
}