{
  "type": "Feature",
  "properties": {
    "date:inception_lower": "2008-04-01",
    "date:inception_upper": "2008-04-01",
    "iso:country": "GB",
    "wof:name": "S2 4QY",
    "wof:placetype": "postalcode"
  },
  "geometry": {"coordinates":[-1.476653,53.371577],"type":"Point"}
}
