{
  "type": "Feature",
  "properties": {
    "iso:country": "GB",
    "wof:name": "S2 4QY",
    "wof:placetype": "postalcode"
  },
  "geometry": {"coordinates":[-1.476653,53.371577],"type":"Point"}
}
