{
  "type": "Feature",
  "properties": {
    "iso:country":"GB",
    "wof:name":"DY14 0HQ",
    "wof:placetype":"postalcode"
},
  "geometry": {"coordinates":[-2.55863841409851,52.38725738836087],"type":"Point"}
}