{
  "type": "Feature",
  "properties": {
    "iso:country": "GB",
    "wof:name": "DY14 0HQ",
    "wof:placetype": "postalcode"
  },
  "geometry": {"coordinates":[-2.558638,52.387257],"type":"Point"}
}
