{
  "type": "Feature",
  "properties": {
    "iso:country":"GB",
    "wof:name":"DE55 6GS",
    "wof:placetype":"postalcode"
},
  "geometry": {"coordinates":[-1.38942156266554,53.13658825391031],"type":"Point"}
}