{
  "type": "Feature",
  "properties": {
    "date:inception_lower": "2018-12-01",
    "date:inception_upper": "2018-12-01",
    "iso:country": "GB",
    "wof:name": "CA16 6DQ",
    "wof:placetype": "postalcode"
  },
  "geometry": {"coordinates":[-2.560013,54.599313],"type":"Point"}
}
