{
  "type": "Feature",
  "properties": {
    "iso:country":"GB",
    "wof:name":"TR19 7PS",
    "wof:placetype":"postalcode"
},
  "geometry": {"coordinates":[-5.67567799219062,50.13412935925133],"type":"Point"}
}