{
  "type": "Feature",
  "properties": {
    "iso:country":"GB",
    "wof:name":"NR11 8BA",
    "wof:placetype":"postalcode"
},
  "geometry": {"coordinates":[1.4332873431551,52.87906624452548],"type":"Point"}
}