{
  "type": "Feature",
  "properties": {
    "iso:country": "GB",
    "wof:name": "NR11 8BA",
    "wof:placetype": "postalcode"
  },
  "geometry": {"coordinates":[1.433287,52.879066],"type":"Point"}
}
