{
  "type": "Feature",
  "properties": {
    "iso:country":"GB",
    "wof:name":"TA2 7JH",
    "wof:placetype":"postalcode"
},
  "geometry": {"coordinates":[-3.0987881172109,51.03760913009241],"type":"Point"}
}