{
  "type": "Feature",
  "properties": {
    "iso:country":"GB",
    "wof:name":"LL16 3NP",
    "wof:placetype":"postalcode"
},
  "geometry": {"coordinates":[-3.42301290002767,53.18001513734531],"type":"Point"}
}