{
  "type": "Feature",
  "properties": {
    "iso:country":"GB",
    "wof:name":"E1 8AT",
    "wof:placetype":"postalcode"
},
  "geometry": {"coordinates":[-0.07356208801667,51.51101708263748],"type":"Point"}
}