{
  "type": "Feature",
  "properties": {
    "date:inception_lower": "1999-12-01",
    "date:inception_upper": "1999-12-01",
    "iso:country": "GB",
    "wof:name": "PO37 7QH",
    "wof:placetype": "postalcode"
  },
  "geometry": {"coordinates":[-1.180378,50.627815],"type":"Point"}
}
