{
  "type": "Feature",
  "properties": {
    "iso:country": "GB",
    "wof:name": "PO37 7QH",
    "wof:placetype": "postalcode"
  },
  "geometry": {"coordinates":[-1.180378,50.627815],"type":"Point"}
}
