{
  "type": "Feature",
  "properties": {
    "date:inception_lower": "2017-07-01",
    "date:inception_upper": "2017-07-01",
    "iso:country": "GB",
    "wof:name": "ME17 1GR",
    "wof:placetype": "postalcode"
  },
  "geometry": {"coordinates":[0.679285,51.241229],"type":"Point"}
}
