{
  "type": "Feature",
  "properties": {
    "iso:country":"GB",
    "wof:name":"PH2 0HB",
    "wof:placetype":"postalcode"
},
  "geometry": {"coordinates":[-3.44585921744259,56.38924454561418],"type":"Point"}
}