{
  "type": "Feature",
  "properties": {
    "iso:country":"GB",
    "wof:name":"PH41 4QA",
    "wof:placetype":"postalcode"
},
  "geometry": {"coordinates":[-5.82955891776239,57.0059435273547],"type":"Point"}
}