{
  "type": "Feature",
  "properties": {
    "date:inception_lower": "2024-08-01",
    "date:inception_upper": "2024-08-01",
    "iso:country": "GB",
    "wof:name": "LU4 9LW",
    "wof:placetype": "postalcode"
  },
  "geometry": {"coordinates":[-0.463664,51.901403],"type":"Point"}
}
