{
  "type": "Feature",
  "properties": {
    "date:inception_lower": "2021-05-01",
    "date:inception_upper": "2021-05-01",
    "iso:country": "GB",
    "wof:name": "ME17 2FS",
    "wof:placetype": "postalcode"
  },
  "geometry": {"coordinates":[0.709539,51.232564],"type":"Point"}
}
