{
  "type": "Feature",
  "properties": {
    "iso:country":"GB",
    "wof:name":"HR1 2NG",
    "wof:placetype":"postalcode"
},
  "geometry": {"coordinates":[-2.71496116979233,52.05370236629382],"type":"Point"}
}