{
  "type": "Feature",
  "properties": {
    "iso:country": "GB",
    "wof:name": "HR1 2NG",
    "wof:placetype": "postalcode"
  },
  "geometry": {"coordinates":[-2.714961,52.053702],"type":"Point"}
}
