{
  "type": "Feature",
  "properties": {
    "date:inception_lower": "2008-11-01",
    "date:inception_upper": "2008-11-01",
    "iso:country": "GB",
    "wof:name": "RG27 0AY",
    "wof:placetype": "postalcode"
  },
  "geometry": {"coordinates":[-1.052312,51.300656],"type":"Point"}
}
