{
  "type": "Feature",
  "properties": {
    "iso:country": "GB",
    "wof:name": "RG27 0AY",
    "wof:placetype": "postalcode"
  },
  "geometry": {"coordinates":[-1.052312,51.300656],"type":"Point"}
}
