{
  "type": "Feature",
  "properties": {
    "iso:country":"GB",
    "wof:name":"RG27 0AY",
    "wof:placetype":"postalcode"
},
  "geometry": {"coordinates":[-1.05231241262462,51.30065582457215],"type":"Point"}
}