{
  "type": "Feature",
  "properties": {
    "iso:country":"GB",
    "wof:name":"WA4 4QB",
    "wof:placetype":"postalcode"
},
  "geometry": {"coordinates":[-2.56133657674559,53.32223378711036],"type":"Point"}
}