{
  "type": "Feature",
  "properties": {
    "iso:country":"GB",
    "wof:name":"BL9 0JF",
    "wof:placetype":"postalcode"
},
  "geometry": {"coordinates":[-2.30483429313452,53.59349470306633],"type":"Point"}
}