{
  "type": "Feature",
  "properties": {
    "date:inception_lower":"1995-12-01",
    "date:inception_upper":"1995-12-31",
    "iso:country":"GB",
    "wof:name":"NN18 8LT",
    "wof:placetype":"postalcode"
},
  "geometry": {"coordinates":[-0.727774,52.461877],"type":"Point"}
}