{
  "type": "Feature",
  "properties": {
    "iso:country": "GB",
    "wof:name": "NN18 8LT",
    "wof:placetype": "postalcode"
  },
  "geometry": {"coordinates":[-0.727774,52.461877],"type":"Point"}
}
