{
  "type": "Feature",
  "properties": {
    "iso:country":"GB",
    "wof:name":"ME18 6JS",
    "wof:placetype":"postalcode"
},
  "geometry": {"coordinates":[0.42774990739839,51.22216640226829],"type":"Point"}
}