{
  "type": "Feature",
  "properties": {
    "iso:country":"GB",
    "wof:name":"CH65 2DY",
    "wof:placetype":"postalcode"
},
  "geometry": {"coordinates":[-2.90001359956698,53.28534441770237],"type":"Point"}
}