{
  "type": "Feature",
  "properties": {
    "date:inception_lower":"1999-06-01",
    "date:inception_upper":"1999-06-30",
    "iso:country":"GB",
    "wof:name":"CH65 2DY",
    "wof:placetype":"postalcode"
},
  "geometry": {"coordinates":[-2.900014,53.285344],"type":"Point"}
}