{
  "type": "Feature",
  "properties": {
    "iso:country":"GB",
    "wof:name":"WA11 9BN",
    "wof:placetype":"postalcode"
},
  "geometry": {"coordinates":[-2.70915898855689,53.46196781800218],"type":"Point"}
}