{
  "type": "Feature",
  "properties": {
    "iso:country":"GB",
    "wof:name":"CB10 2QF",
    "wof:placetype":"postalcode"
},
  "geometry": {"coordinates":[0.39038339342629,51.98176372119085],"type":"Point"}
}