{
  "type": "Feature",
  "properties": {
    "iso:country": "GB",
    "wof:name": "CB10 2QF",
    "wof:placetype": "postalcode"
  },
  "geometry": {"coordinates":[0.390413,51.981773],"type":"Point"}
}
