{
  "type": "Feature",
  "properties": {
    "date:inception_lower": "1980-01-01",
    "date:inception_upper": "1980-01-01",
    "iso:country": "GB",
    "wof:name": "DD11 2AZ",
    "wof:placetype": "postalcode"
  },
  "geometry": {"coordinates":[-2.592109,56.558856],"type":"Point"}
}
