{
  "type": "Feature",
  "properties": {
    "date:inception_lower":"1980-01-01",
    "date:inception_upper":"1980-01-31",
    "iso:country":"GB",
    "wof:name":"SA18 1JG",
    "wof:placetype":"postalcode"
},
  "geometry": {"coordinates":[-3.905072,51.802656],"type":"Point"}
}