{
  "type": "Feature",
  "properties": {
    "iso:country":"GB",
    "wof:name":"SA18 1JG",
    "wof:placetype":"postalcode"
},
  "geometry": {"coordinates":[-3.90507238017724,51.80265606909649],"type":"Point"}
}