{
  "type": "Feature",
  "properties": {
    "iso:country": "GB",
    "wof:name": "WA6 7NN",
    "wof:placetype": "postalcode"
  },
  "geometry": {"coordinates":[-2.725752,53.298155],"type":"Point"}
}
