{
  "type": "Feature",
  "properties": {
    "date:inception_lower": "2017-01-01",
    "date:inception_upper": "2017-01-01",
    "iso:country": "GB",
    "wof:name": "B18 4ED",
    "wof:placetype": "postalcode"
  },
  "geometry": {"coordinates":[-1.941266,52.486894],"type":"Point"}
}
