{
  "type": "Feature",
  "properties": {
    "date:inception_lower":"2002-06-01",
    "date:inception_upper":"2002-06-30",
    "iso:country":"GB",
    "wof:name":"PO19 7LY",
    "wof:placetype":"postalcode"
},
  "geometry": {"coordinates":[-0.771479,50.840298],"type":"Point"}
}