{
  "type": "Feature",
  "properties": {
    "iso:country":"GB",
    "wof:name":"MK43 0LW",
    "wof:placetype":"postalcode"
},
  "geometry": {"coordinates":[-0.54638448465279,52.07357859958559],"type":"Point"}
}