{
  "type": "Feature",
  "properties": {
    "date:inception_lower": "1980-01-01",
    "date:inception_upper": "1980-01-01",
    "iso:country": "GB",
    "wof:name": "MK43 0LW",
    "wof:placetype": "postalcode"
  },
  "geometry": {"coordinates":[-0.546384,52.073579],"type":"Point"}
}
