{
  "type": "Feature",
  "properties": {
    "iso:country":"GB",
    "wof:name":"DE65 5NR",
    "wof:placetype":"postalcode"
},
  "geometry": {"coordinates":[-1.63740266052892,52.86809549550838],"type":"Point"}
}