{
  "type": "Feature",
  "properties": {
    "date:inception_lower": "1980-01-01",
    "date:inception_upper": "1980-01-01",
    "iso:country": "GB",
    "wof:name": "E16 2NL",
    "wof:placetype": "postalcode"
  },
  "geometry": {"coordinates":[0.065815,51.500274],"type":"Point"}
}
