{
  "type": "Feature",
  "properties": {
    "iso:country":"GB",
    "wof:name":"E16 2NL",
    "wof:placetype":"postalcode"
},
  "geometry": {"coordinates":[0.06588875844496,51.50028023951934],"type":"Point"}
}