{
  "type": "Feature",
  "properties": {
    "iso:country":"GB",
    "wof:name":"M22 5AT",
    "wof:placetype":"postalcode"
},
  "geometry": {"coordinates":[-2.24436863130967,53.38102981991462],"type":"Point"}
}