{
  "type": "Feature",
  "properties": {
    "iso:country":"GB",
    "wof:name":"PL1 3HR",
    "wof:placetype":"postalcode"
},
  "geometry": {"coordinates":[-4.1597773334607,50.36978583863966],"type":"Point"}
}