{
  "type": "Feature",
  "properties": {
    "iso:country":"GB",
    "wof:name":"M7 4GF",
    "wof:placetype":"postalcode"
},
  "geometry": {"coordinates":[-2.25184388261216,53.51136567170747],"type":"Point"}
}