{
  "type": "Feature",
  "properties": {
    "iso:country": "GB",
    "wof:name": "WN7 2YZ",
    "wof:placetype": "postalcode"
  },
  "geometry": {"coordinates":[-2.479749,53.504448],"type":"Point"}
}
