{
  "type": "Feature",
  "properties": {
    "iso:country": "GB",
    "wof:name": "PE11 4JL",
    "wof:placetype": "postalcode"
  },
  "geometry": {"coordinates":[-0.236592,52.847178],"type":"Point"}
}
