{
  "type": "Feature",
  "properties": {
    "date:inception_lower": "1980-01-01",
    "date:inception_upper": "1980-01-01",
    "iso:country": "GB",
    "wof:name": "PE11 4JL",
    "wof:placetype": "postalcode"
  },
  "geometry": {"coordinates":[-0.236592,52.847178],"type":"Point"}
}
