{
  "type": "Feature",
  "properties": {
    "iso:country":"GB",
    "wof:name":"PE11 4JL",
    "wof:placetype":"postalcode"
},
  "geometry": {"coordinates":[-0.23659247041951,52.84717840896357],"type":"Point"}
}