{
  "type": "Feature",
  "properties": {
    "iso:country":"GB",
    "wof:name":"RH20 4JJ",
    "wof:placetype":"postalcode"
},
  "geometry": {"coordinates":[-0.46931495423782,50.9183025560324],"type":"Point"}
}