{
  "type": "Feature",
  "properties": {
    "iso:country":"GB",
    "wof:name":"BS16 9PT",
    "wof:placetype":"postalcode"
},
  "geometry": {"coordinates":[-2.4455308067872,51.49072967129862],"type":"Point"}
}