{
  "type": "Feature",
  "properties": {
    "iso:country":"GB",
    "wof:name":"SG6 3NW",
    "wof:placetype":"postalcode"
},
  "geometry": {"coordinates":[-0.23032643062287,51.96372118338872],"type":"Point"}
}