{
  "type": "Feature",
  "properties": {
    "iso:country":"GB",
    "wof:name":"TD5 8EZ",
    "wof:placetype":"postalcode"
},
  "geometry": {"coordinates":[-2.42751510432749,55.59315956369908],"type":"Point"}
}