{
  "type": "Feature",
  "properties": {
    "iso:country": "GB",
    "wof:name": "PE32 1UL",
    "wof:placetype": "postalcode"
  },
  "geometry": {"coordinates":[0.61372,52.701546],"type":"Point"}
}
