{
  "type": "Feature",
  "properties": {
    "date:inception_lower":"1991-09-01",
    "date:inception_upper":"1991-09-30",
    "iso:country":"GB",
    "wof:name":"PE32 1UL",
    "wof:placetype":"postalcode"
},
  "geometry": {"coordinates":[0.61372,52.701546],"type":"Point"}
}