{
  "type": "Feature",
  "properties": {
    "iso:country":"GB",
    "wof:name":"PE32 1UL",
    "wof:placetype":"postalcode"
},
  "geometry": {"coordinates":[0.61372019484803,52.70154558674395],"type":"Point"}
}