{
  "type": "Feature",
  "properties": {
    "iso:country":"GB",
    "wof:name":"ML11 9YR",
    "wof:placetype":"postalcode"
},
  "geometry": {"coordinates":[-3.92225905774558,55.67669197217211],"type":"Point"}
}