{
  "type": "Feature",
  "properties": {
    "iso:country":"GB",
    "wof:name":"RH15 8NB",
    "wof:placetype":"postalcode"
},
  "geometry": {"coordinates":[-0.13869133067123,50.96287296026639],"type":"Point"}
}