{
  "type": "Feature",
  "properties": {
    "date:inception_lower":"1980-01-01",
    "date:inception_upper":"1980-01-31",
    "iso:country":"GB",
    "wof:name":"EN5 5TY",
    "wof:placetype":"postalcode"
},
  "geometry": {"coordinates":[-0.200899,51.653683],"type":"Point"}
}