{
  "type": "Feature",
  "properties": {
    "iso:country": "GB",
    "wof:name": "L9 6AT",
    "wof:placetype": "postalcode"
  },
  "geometry": {"coordinates":[-2.939909,53.450298],"type":"Point"}
}
