{
  "type": "Feature",
  "properties": {
    "date:inception_lower": "1990-07-01",
    "date:inception_upper": "1990-07-01",
    "iso:country": "GB",
    "wof:name": "TS12 1JJ",
    "wof:placetype": "postalcode"
  },
  "geometry": {"coordinates":[-0.97905,54.580472],"type":"Point"}
}
