{
  "type": "Feature",
  "properties": {
    "iso:country":"GB",
    "wof:name":"TS12 1JJ",
    "wof:placetype":"postalcode"
},
  "geometry": {"coordinates":[-0.97905048383013,54.58047163578877],"type":"Point"}
}