{
  "type": "Feature",
  "properties": {
    "iso:country": "GB",
    "wof:name": "BA14 9RR",
    "wof:placetype": "postalcode"
  },
  "geometry": {"coordinates":[-2.212952,51.294061],"type":"Point"}
}
