{
  "type": "Feature",
  "properties": {
    "iso:country":"GB",
    "wof:name":"BA14 9RR",
    "wof:placetype":"postalcode"
},
  "geometry": {"coordinates":[-2.2129522088003,51.29406145144794],"type":"Point"}
}