{
  "type": "Feature",
  "properties": {
    "iso:country":"GB",
    "wof:name":"NE6 4QQ",
    "wof:placetype":"postalcode"
},
  "geometry": {"coordinates":[-1.5564409706452,54.98529460999266],"type":"Point"}
}