{
  "type": "Feature",
  "properties": {
    "iso:country": "GB",
    "wof:name": "NE6 4QQ",
    "wof:placetype": "postalcode"
  },
  "geometry": {"coordinates":[-1.556441,54.985295],"type":"Point"}
}
