{
  "type": "Feature",
  "properties": {
    "iso:country":"GB",
    "wof:name":"SE1 3RR",
    "wof:placetype":"postalcode"
},
  "geometry": {"coordinates":[-0.08538992539001,51.5035490877085],"type":"Point"}
}