{
  "type": "Feature",
  "properties": {
    "iso:country": "GB",
    "wof:name": "PA28 6TB",
    "wof:placetype": "postalcode"
  },
  "geometry": {"coordinates":[-5.602775,55.431052],"type":"Point"}
}
