{
  "type": "Feature",
  "properties": {
    "iso:country": "GB",
    "wof:name": "LE17 4UB",
    "wof:placetype": "postalcode"
  },
  "geometry": {"coordinates":[-1.222171,52.456433],"type":"Point"}
}
