{
  "type": "Feature",
  "properties": {
    "iso:country":"GB",
    "wof:name":"DG8 6RX",
    "wof:placetype":"postalcode"
},
  "geometry": {"coordinates":[-4.64378157159635,55.01907543078435],"type":"Point"}
}