{
  "type": "Feature",
  "properties": {
    "date:inception_lower": "1980-01-01",
    "date:inception_upper": "1980-01-01",
    "iso:country": "GB",
    "wof:name": "RH15 9DP",
    "wof:placetype": "postalcode"
  },
  "geometry": {"coordinates":[-0.129102,50.953771],"type":"Point"}
}
