{
  "type": "Feature",
  "properties": {
    "iso:country":"GB",
    "wof:name":"RH15 9DP",
    "wof:placetype":"postalcode"
},
  "geometry": {"coordinates":[-0.12910249244797,50.95377141761786],"type":"Point"}
}