{
  "type": "Feature",
  "properties": {
    "iso:country":"GB",
    "wof:name":"NW7 3SX",
    "wof:placetype":"postalcode"
},
  "geometry": {"coordinates":[-0.25936497015186,51.61647887619445],"type":"Point"}
}