{
  "type": "Feature",
  "properties": {
    "date:inception_lower": "1993-01-01",
    "date:inception_upper": "1993-01-01",
    "iso:country": "GB",
    "wof:name": "NW7 3SX",
    "wof:placetype": "postalcode"
  },
  "geometry": {"coordinates":[-0.259299,51.616463],"type":"Point"}
}
