{
  "type": "Feature",
  "properties": {
    "iso:country":"GB",
    "wof:name":"PE13 5PQ",
    "wof:placetype":"postalcode"
},
  "geometry": {"coordinates":[0.14169311545472,52.7325045046839],"type":"Point"}
}