{
  "type": "Feature",
  "properties": {
    "date:inception_lower": "1980-01-01",
    "date:inception_upper": "1980-01-01",
    "iso:country": "GB",
    "wof:name": "PE13 5PQ",
    "wof:placetype": "postalcode"
  },
  "geometry": {"coordinates":[0.141693,52.732504],"type":"Point"}
}
