{
  "type": "Feature",
  "properties": {
    "iso:country":"GB",
    "wof:name":"OL2 5PN",
    "wof:placetype":"postalcode"
},
  "geometry": {"coordinates":[-2.12430760237111,53.56392374483632],"type":"Point"}
}