{
  "type": "Feature",
  "properties": {
    "date:inception_lower": "2024-02-01",
    "date:inception_upper": "2024-02-01",
    "iso:country": "GB",
    "wof:name": "LU7 3SD",
    "wof:placetype": "postalcode"
  },
  "geometry": {"coordinates":[-0.643276,51.93135],"type":"Point"}
}
