{
  "type": "Feature",
  "properties": {
    "iso:country":"GB",
    "wof:name":"SW4 9JR",
    "wof:placetype":"postalcode"
},
  "geometry": {"coordinates":[-0.14309287839955,51.45580923720662],"type":"Point"}
}