{
  "type": "Feature",
  "properties": {
    "iso:country":"GB",
    "wof:name":"CB1 3AY",
    "wof:placetype":"postalcode"
},
  "geometry": {"coordinates":[0.14792846672768,52.20216596988914],"type":"Point"}
}