{
  "type": "Feature",
  "properties": {
    "iso:country": "GB",
    "wof:name": "TN14 7DY",
    "wof:placetype": "postalcode"
  },
  "geometry": {"coordinates":[0.137621,51.343857],"type":"Point"}
}
