{
  "type": "Feature",
  "properties": {
    "iso:country":"GB",
    "wof:name":"TN14 7DY",
    "wof:placetype":"postalcode"
},
  "geometry": {"coordinates":[0.13762123651669,51.34385678881635],"type":"Point"}
}