{
  "type": "Feature",
  "properties": {
    "iso:country":"GB",
    "wof:name":"LE16 7HJ",
    "wof:placetype":"postalcode"
},
  "geometry": {"coordinates":[-0.90674462780069,52.48728413745113],"type":"Point"}
}