{
  "type": "Feature",
  "properties": {
    "date:inception_lower":"1983-03-01",
    "date:inception_upper":"1983-03-31",
    "iso:country":"GB",
    "wof:name":"LE16 7HJ",
    "wof:placetype":"postalcode"
},
  "geometry": {"coordinates":[-0.906745,52.487284],"type":"Point"}
}