{
  "type": "Feature",
  "properties": {
    "iso:country": "GB",
    "wof:name": "SA9 2PS",
    "wof:placetype": "postalcode"
  },
  "geometry": {"coordinates":[-3.78389,51.775091],"type":"Point"}
}
