{
  "type": "Feature",
  "properties": {
    "iso:country":"GB",
    "wof:name":"SA9 2PS",
    "wof:placetype":"postalcode"
},
  "geometry": {"coordinates":[-3.78388955284201,51.77509079224057],"type":"Point"}
}