{
  "type": "Feature",
  "properties": {
    "iso:country": "GB",
    "wof:name": "GU10 4ET",
    "wof:placetype": "postalcode"
  },
  "geometry": {"coordinates":[-0.82662,51.172142],"type":"Point"}
}
