{
  "type": "Feature",
  "properties": {
    "iso:country": "GB",
    "wof:name": "GU10 4ET",
    "wof:placetype": "postalcode"
  },
  "geometry": {"coordinates":[-0.82578,51.173105],"type":"Point"}
}
