{
  "type": "Feature",
  "properties": {
    "iso:country": "GB",
    "wof:name": "YO51 9EP",
    "wof:placetype": "postalcode"
  },
  "geometry": {"coordinates":[-1.382965,54.09282],"type":"Point"}
}
