{
  "type": "Feature",
  "properties": {
    "date:inception_lower": "2018-01-01",
    "date:inception_upper": "2018-01-01",
    "iso:country": "GB",
    "wof:name": "BD20 8DN",
    "wof:placetype": "postalcode"
  },
  "geometry": {"coordinates":[-1.966928,53.898875],"type":"Point"}
}
