{
  "type": "Feature",
  "properties": {
    "date:inception_lower": "1980-01-01",
    "date:inception_upper": "1980-01-01",
    "iso:country": "GB",
    "wof:name": "BB5 2BH",
    "wof:placetype": "postalcode"
  },
  "geometry": {"coordinates":[-2.3594,53.749222],"type":"Point"}
}
