{
  "type": "Feature",
  "properties": {
    "iso:country":"GB",
    "wof:name":"BB5 2BH",
    "wof:placetype":"postalcode"
},
  "geometry": {"coordinates":[-2.35932365209482,53.74912683477481],"type":"Point"}
}