{
  "type": "Feature",
  "properties": {
    "date:inception_lower": "1980-01-01",
    "date:inception_upper": "1980-01-01",
    "iso:country": "GB",
    "wof:name": "CT1 2PY",
    "wof:placetype": "postalcode"
  },
  "geometry": {"coordinates":[1.076237,51.276549],"type":"Point"}
}
