{
  "type": "Feature",
  "properties": {
    "iso:country":"GB",
    "wof:name":"CT1 2PY",
    "wof:placetype":"postalcode"
},
  "geometry": {"coordinates":[1.07604988772002,51.27655756488925],"type":"Point"}
}