{
  "type": "Feature",
  "properties": {
    "iso:country":"GB",
    "wof:name":"M25 0BR",
    "wof:placetype":"postalcode"
},
  "geometry": {"coordinates":[-2.25922530562334,53.52496731213845],"type":"Point"}
}