{
  "type": "Feature",
  "properties": {
    "iso:country":"GB",
    "wof:name":"CV9 1DX",
    "wof:placetype":"postalcode"
},
  "geometry": {"coordinates":[-1.54240105513177,52.57532486720326],"type":"Point"}
}