{
  "type": "Feature",
  "properties": {
    "date:inception_lower":"2002-06-01",
    "date:inception_upper":"2002-06-30",
    "iso:country":"GB",
    "wof:name":"BS27 3XQ",
    "wof:placetype":"postalcode"
},
  "geometry": {"coordinates":[-2.777555,51.271],"type":"Point"}
}