{
  "type": "Feature",
  "properties": {
    "iso:country": "GB",
    "wof:name": "CH7 2NH",
    "wof:placetype": "postalcode"
  },
  "geometry": {"coordinates":[-3.089707,53.168043],"type":"Point"}
}
