{
  "type": "Feature",
  "properties": {
    "iso:country": "GB",
    "wof:name": "OX3 7JU",
    "wof:placetype": "postalcode"
  },
  "geometry": {"coordinates":[-1.214213,51.749654],"type":"Point"}
}
