{
  "type": "Feature",
  "properties": {
    "iso:country":"GB",
    "wof:name":"LU2 8UT",
    "wof:placetype":"postalcode"
},
  "geometry": {"coordinates":[-0.365075498551,51.89233318308062],"type":"Point"}
}