{
  "type": "Feature",
  "properties": {
    "date:inception_lower": "1990-07-01",
    "date:inception_upper": "1990-07-01",
    "iso:country": "GB",
    "wof:name": "LU2 8UT",
    "wof:placetype": "postalcode"
  },
  "geometry": {"coordinates":[-0.365075,51.892333],"type":"Point"}
}
