{
  "type": "Feature",
  "properties": {
    "iso:country": "GB",
    "wof:name": "SA16 0AR",
    "wof:placetype": "postalcode"
  },
  "geometry": {"coordinates":[-4.258032,51.684805],"type":"Point"}
}
