{
  "type": "Feature",
  "properties": {
    "iso:country":"GB",
    "wof:name":"SA16 0AR",
    "wof:placetype":"postalcode"
},
  "geometry": {"coordinates":[-4.25806002668197,51.68479557431701],"type":"Point"}
}