{
  "type": "Feature",
  "properties": {
    "iso:country":"GB",
    "wof:name":"IP11 2GJ",
    "wof:placetype":"postalcode"
},
  "geometry": {"coordinates":[1.33460184826432,51.94838038820712],"type":"Point"}
}