{
  "type": "Feature",
  "properties": {
    "iso:country": "GB",
    "wof:name": "IP11 2GJ",
    "wof:placetype": "postalcode"
  },
  "geometry": {"coordinates":[1.334602,51.94838],"type":"Point"}
}
