{
  "type": "Feature",
  "properties": {
    "date:inception_lower": "1980-01-01",
    "date:inception_upper": "1980-01-01",
    "iso:country": "GB",
    "wof:name": "WV2 3JQ",
    "wof:placetype": "postalcode"
  },
  "geometry": {"coordinates":[-2.130667,52.57102],"type":"Point"}
}
