{
  "type": "Feature",
  "properties": {
    "iso:country":"GB",
    "wof:name":"WV2 3JQ",
    "wof:placetype":"postalcode"
},
  "geometry": {"coordinates":[-2.13066739575084,52.57102036423418],"type":"Point"}
}