{
  "type": "Feature",
  "properties": {
    "date:inception_lower":"1980-01-01",
    "date:inception_upper":"1980-01-31",
    "iso:country":"GB",
    "wof:name":"RH11 7NH",
    "wof:placetype":"postalcode"
},
  "geometry": {"coordinates":[-0.200733,51.129813],"type":"Point"}
}