{
  "type": "Feature",
  "properties": {
    "iso:country": "GB",
    "wof:name": "RH11 7NH",
    "wof:placetype": "postalcode"
  },
  "geometry": {"coordinates":[-0.200733,51.129813],"type":"Point"}
}
