{
  "type": "Feature",
  "properties": {
    "iso:country":"GB",
    "wof:name":"RH11 7NH",
    "wof:placetype":"postalcode"
},
  "geometry": {"coordinates":[-0.20073318261361,51.12981275413527],"type":"Point"}
}