{
  "type": "Feature",
  "properties": {
    "date:inception_lower": "1980-01-01",
    "date:inception_upper": "1980-01-01",
    "iso:country": "GB",
    "wof:name": "CV22 6AE",
    "wof:placetype": "postalcode"
  },
  "geometry": {"coordinates":[-1.265078,52.368153],"type":"Point"}
}
