{
  "type": "Feature",
  "properties": {
    "iso:country":"GB",
    "wof:name":"PE26 2NX",
    "wof:placetype":"postalcode"
},
  "geometry": {"coordinates":[-0.10713748046755,52.42317380084494],"type":"Point"}
}