{
  "type": "Feature",
  "properties": {
    "iso:country": "GB",
    "wof:name": "PE26 2NX",
    "wof:placetype": "postalcode"
  },
  "geometry": {"coordinates":[-0.106634,52.422077],"type":"Point"}
}
