{
  "type": "Feature",
  "properties": {
    "date:inception_lower": "2000-06-01",
    "date:inception_upper": "2000-06-01",
    "iso:country": "GB",
    "wof:name": "PE26 2NX",
    "wof:placetype": "postalcode"
  },
  "geometry": {"coordinates":[-0.107115,52.423191],"type":"Point"}
}
