{
  "type": "Feature",
  "properties": {
    "iso:country":"GB",
    "wof:name":"HU13 0RZ",
    "wof:placetype":"postalcode"
},
  "geometry": {"coordinates":[-0.43822702327183,53.72410443471907],"type":"Point"}
}