{
  "type": "Feature",
  "properties": {
    "iso:country": "GB",
    "wof:name": "HU13 0RZ",
    "wof:placetype": "postalcode"
  },
  "geometry": {"coordinates":[-0.438227,53.724104],"type":"Point"}
}
