{
  "type": "Feature",
  "properties": {
    "iso:country": "GB",
    "wof:name": "PO30 1ND",
    "wof:placetype": "postalcode"
  },
  "geometry": {"coordinates":[-1.29967,50.691993],"type":"Point"}
}
