{
  "type": "Feature",
  "properties": {
    "iso:country":"GB",
    "wof:name":"ML5 1RW",
    "wof:placetype":"postalcode"
},
  "geometry": {"coordinates":[-4.05253197583979,55.86410267811675],"type":"Point"}
}