{
  "type": "Feature",
  "properties": {
    "iso:country": "GB",
    "wof:name": "LL29 7DP",
    "wof:placetype": "postalcode"
  },
  "geometry": {"coordinates":[-3.729776,53.293957],"type":"Point"}
}
