{
  "type": "Feature",
  "properties": {
    "iso:country":"GB",
    "wof:name":"LL29 7DP",
    "wof:placetype":"postalcode"
},
  "geometry": {"coordinates":[-3.73015639399697,53.29408602022588],"type":"Point"}
}