{
  "type": "Feature",
  "properties": {
    "iso:country": "GB",
    "wof:name": "WA7 6GJ",
    "wof:placetype": "postalcode"
  },
  "geometry": {"coordinates":[-2.668994,53.332921],"type":"Point"}
}
