{
  "type": "Feature",
  "properties": {
    "iso:country":"GB",
    "wof:name":"L17 7DL",
    "wof:placetype":"postalcode"
},
  "geometry": {"coordinates":[-2.95214121998664,53.37916237538023],"type":"Point"}
}