{
  "type": "Feature",
  "properties": {
    "iso:country":"GB",
    "wof:name":"PE19 1BJ",
    "wof:placetype":"postalcode"
},
  "geometry": {"coordinates":[-0.26766833309591,52.22811556174413],"type":"Point"}
}