{
  "type": "Feature",
  "properties": {
    "date:inception_lower": "1986-04-01",
    "date:inception_upper": "1986-04-01",
    "iso:country": "GB",
    "wof:name": "PE19 1BJ",
    "wof:placetype": "postalcode"
  },
  "geometry": {"coordinates":[-0.267668,52.228116],"type":"Point"}
}
