{
  "type": "Feature",
  "properties": {
    "iso:country": "GB",
    "wof:name": "TA21 8PY",
    "wof:placetype": "postalcode"
  },
  "geometry": {"coordinates":[-3.22374,50.974048],"type":"Point"}
}
