{
  "type": "Feature",
  "properties": {
    "date:inception_lower":"1998-06-01",
    "date:inception_upper":"1998-06-30",
    "iso:country":"GB",
    "wof:name":"YO30 5PU",
    "wof:placetype":"postalcode"
},
  "geometry": {"coordinates":[-1.104566,53.979351],"type":"Point"}
}