{
  "type": "Feature",
  "properties": {
    "iso:country":"GB",
    "wof:name":"YO30 5PU",
    "wof:placetype":"postalcode"
},
  "geometry": {"coordinates":[-1.10456570344713,53.97935130521391],"type":"Point"}
}