{
  "type": "Feature",
  "properties": {
    "iso:country": "GB",
    "wof:name": "RM15 6NU",
    "wof:placetype": "postalcode"
  },
  "geometry": {"coordinates":[0.296618,51.522149],"type":"Point"}
}
