{
  "type": "Feature",
  "properties": {
    "iso:country":"GB",
    "wof:name":"DN11 8NL",
    "wof:placetype":"postalcode"
},
  "geometry": {"coordinates":[-1.08100659456256,53.41950774308567],"type":"Point"}
}