{
  "type": "Feature",
  "properties": {
    "iso:country": "GB",
    "wof:name": "RG2 0LJ",
    "wof:placetype": "postalcode"
  },
  "geometry": {"coordinates":[-0.971209,51.436038],"type":"Point"}
}
