{
  "type": "Feature",
  "properties": {
    "iso:country":"GB",
    "wof:name":"RG2 0LJ",
    "wof:placetype":"postalcode"
},
  "geometry": {"coordinates":[-0.97120854451134,51.43603827672887],"type":"Point"}
}