{
  "type": "Feature",
  "properties": {
    "iso:country": "GB",
    "wof:name": "PL17 7BT",
    "wof:placetype": "postalcode"
  },
  "geometry": {"coordinates":[-4.313712,50.506643],"type":"Point"}
}
