{
  "type": "Feature",
  "properties": {
    "date:inception_lower": "1980-01-01",
    "date:inception_upper": "1980-01-01",
    "iso:country": "GB",
    "wof:name": "ME17 4HD",
    "wof:placetype": "postalcode"
  },
  "geometry": {"coordinates":[0.49996,51.23508],"type":"Point"}
}
