{
  "type": "Feature",
  "properties": {
    "iso:country":"GB",
    "wof:name":"ME17 4HD",
    "wof:placetype":"postalcode"
},
  "geometry": {"coordinates":[0.4999601258811,51.23508042107901],"type":"Point"}
}