{
  "type": "Feature",
  "properties": {
    "iso:country":"GB",
    "wof:name":"KY3 0RZ",
    "wof:placetype":"postalcode"
},
  "geometry": {"coordinates":[-3.34145348179594,56.05304739518093],"type":"Point"}
}