{
  "type": "Feature",
  "properties": {
    "iso:country": "GB",
    "wof:name": "KY3 0RZ",
    "wof:placetype": "postalcode"
  },
  "geometry": {"coordinates":[-3.341453,56.053047],"type":"Point"}
}
