{
  "type": "Feature",
  "properties": {
    "iso:country":"GB",
    "wof:name":"B65 8DP",
    "wof:placetype":"postalcode"
},
  "geometry": {"coordinates":[-2.04654483521834,52.48148128396096],"type":"Point"}
}