{
  "type": "Feature",
  "properties": {
    "iso:country":"GB",
    "wof:name":"RH19 1QW",
    "wof:placetype":"postalcode"
},
  "geometry": {"coordinates":[-0.03351212600127,51.13723734020889],"type":"Point"}
}