{
  "type": "Feature",
  "properties": {
    "iso:country":"GB",
    "wof:name":"B45 0JJ",
    "wof:placetype":"postalcode"
},
  "geometry": {"coordinates":[-2.00273402013933,52.40569570110424],"type":"Point"}
}