{
  "type": "Feature",
  "properties": {
    "iso:country": "GB",
    "wof:name": "KY1 2QF",
    "wof:placetype": "postalcode"
  },
  "geometry": {"coordinates":[-3.142677,56.122231],"type":"Point"}
}
