{
  "type": "Feature",
  "properties": {
    "date:inception_lower":"1980-01-01",
    "date:inception_upper":"1980-01-31",
    "iso:country":"GB",
    "wof:name":"NE15 6UX",
    "wof:placetype":"postalcode"
},
  "geometry": {"coordinates":[-1.684941,54.96704],"type":"Point"}
}