{
  "type": "Feature",
  "properties": {
    "iso:country":"GB",
    "wof:name":"NE15 6UX",
    "wof:placetype":"postalcode"
},
  "geometry": {"coordinates":[-1.68494089797109,54.96703957029531],"type":"Point"}
}