{
  "type": "Feature",
  "properties": {
    "iso:country":"GB",
    "wof:name":"M40 3SB",
    "wof:placetype":"postalcode"
},
  "geometry": {"coordinates":[-2.15980302376461,53.51601852444048],"type":"Point"}
}