{
  "type": "Feature",
  "properties": {
    "iso:country": "GB",
    "wof:name": "NN17 1JZ",
    "wof:placetype": "postalcode"
  },
  "geometry": {"coordinates":[-0.697737,52.499149],"type":"Point"}
}
