{
  "type": "Feature",
  "properties": {
    "iso:country":"GB",
    "wof:name":"NN17 1JZ",
    "wof:placetype":"postalcode"
},
  "geometry": {"coordinates":[-0.69773695981095,52.49914884824275],"type":"Point"}
}