{
  "type": "Feature",
  "properties": {
    "iso:country":"GB",
    "wof:name":"LN11 9AN",
    "wof:placetype":"postalcode"
},
  "geometry": {"coordinates":[0.00489572202077,53.36672065218031],"type":"Point"}
}