{
  "type": "Feature",
  "properties": {
    "iso:country":"GB",
    "wof:name":"IV14 9DL",
    "wof:placetype":"postalcode"
},
  "geometry": {"coordinates":[-4.53629907265065,57.58774365685614],"type":"Point"}
}