{
  "type": "Feature",
  "properties": {
    "date:inception_lower": "1980-01-01",
    "date:inception_upper": "1980-01-01",
    "iso:country": "GB",
    "wof:name": "IV14 9DL",
    "wof:placetype": "postalcode"
  },
  "geometry": {"coordinates":[-4.536299,57.587744],"type":"Point"}
}
