{
  "type": "Feature",
  "properties": {
    "iso:country":"GB",
    "wof:name":"DA7 6NR",
    "wof:placetype":"postalcode"
},
  "geometry": {"coordinates":[0.17611887949734,51.46378947254424],"type":"Point"}
}