{
  "type": "Feature",
  "properties": {
    "iso:country":"GB",
    "wof:name":"SL6 0DH",
    "wof:placetype":"postalcode"
},
  "geometry": {"coordinates":[-0.68270872955018,51.51564480629069],"type":"Point"}
}