{
  "type": "Feature",
  "properties": {
    "iso:country": "GB",
    "wof:name": "SL6 0DH",
    "wof:placetype": "postalcode"
  },
  "geometry": {"coordinates":[-0.682709,51.515645],"type":"Point"}
}
