{
  "type": "Feature",
  "properties": {
    "iso:country":"GB",
    "wof:name":"CV31 2AN",
    "wof:placetype":"postalcode"
},
  "geometry": {"coordinates":[-1.52902566856321,52.28045961253676],"type":"Point"}
}