{
  "type": "Feature",
  "properties": {
    "iso:country":"GB",
    "wof:name":"N12 7JD",
    "wof:placetype":"postalcode"
},
  "geometry": {"coordinates":[-0.18997702461068,51.61638270449747],"type":"Point"}
}