{
  "type": "Feature",
  "properties": {
    "iso:country":"GB",
    "wof:name":"TA6 6NS",
    "wof:placetype":"postalcode"
},
  "geometry": {"coordinates":[-3.01806327472267,51.08911173931774],"type":"Point"}
}