{
  "type": "Feature",
  "properties": {
    "iso:country":"GB",
    "wof:name":"SK9 3UL",
    "wof:placetype":"postalcode"
},
  "geometry": {"coordinates":[-2.2146028881111,53.34215732940787],"type":"Point"}
}