{
  "type": "Feature",
  "properties": {
    "iso:country": "GB",
    "wof:name": "SK9 3UL",
    "wof:placetype": "postalcode"
  },
  "geometry": {"coordinates":[-2.214603,53.342157],"type":"Point"}
}
