{
  "type": "Feature",
  "properties": {
    "date:inception_lower": "2019-08-01",
    "date:inception_upper": "2019-08-01",
    "iso:country": "GB",
    "wof:name": "WF7 5FJ",
    "wof:placetype": "postalcode"
  },
  "geometry": {"coordinates":[-1.348563,53.676009],"type":"Point"}
}
