{
  "type": "Feature",
  "properties": {
    "iso:country": "GB",
    "wof:name": "WF7 5FJ",
    "wof:placetype": "postalcode"
  },
  "geometry": {"coordinates":[-1.348257,53.676215],"type":"Point"}
}
