{
  "type": "Feature",
  "properties": {
    "iso:country":"GB",
    "wof:name":"SK9 5HD",
    "wof:placetype":"postalcode"
},
  "geometry": {"coordinates":[-2.24229682096322,53.32594260834829],"type":"Point"}
}