{
  "type": "Feature",
  "properties": {
    "date:inception_lower": "1980-01-01",
    "date:inception_upper": "1980-01-01",
    "iso:country": "GB",
    "wof:name": "SK9 5HD",
    "wof:placetype": "postalcode"
  },
  "geometry": {"coordinates":[-2.242297,53.325943],"type":"Point"}
}
