{
  "type": "Feature",
  "properties": {
    "iso:country":"GB",
    "wof:name":"DN5 8EQ",
    "wof:placetype":"postalcode"
},
  "geometry": {"coordinates":[-1.16269108241547,53.52472795390229],"type":"Point"}
}