{
  "type": "Feature",
  "properties": {
    "date:inception_lower": "1997-12-01",
    "date:inception_upper": "1997-12-01",
    "iso:country": "GB",
    "wof:name": "CA14 5XH",
    "wof:placetype": "postalcode"
  },
  "geometry": {"coordinates":[-3.540763,54.593676],"type":"Point"}
}
