{
  "type": "Feature",
  "properties": {
    "date:inception_lower": "1980-01-01",
    "date:inception_upper": "1980-01-01",
    "iso:country": "GB",
    "wof:name": "NR13 3AS",
    "wof:placetype": "postalcode"
  },
  "geometry": {"coordinates":[1.566902,52.64856],"type":"Point"}
}
