{
  "type": "Feature",
  "properties": {
    "iso:country":"GB",
    "wof:name":"TR18 3BW",
    "wof:placetype":"postalcode"
},
  "geometry": {"coordinates":[-5.52926620071292,50.13236161532856],"type":"Point"}
}