{
  "type": "Feature",
  "properties": {
    "date:inception_lower": "1980-01-01",
    "date:inception_upper": "1980-01-01",
    "iso:country": "GB",
    "wof:name": "TR18 3BW",
    "wof:placetype": "postalcode"
  },
  "geometry": {"coordinates":[-5.529266,50.132362],"type":"Point"}
}
