{
  "type": "Feature",
  "properties": {
    "iso:country": "GB",
    "wof:name": "NP12 1EN",
    "wof:placetype": "postalcode"
  },
  "geometry": {"coordinates":[-3.208891,51.674477],"type":"Point"}
}
