{
  "type": "Feature",
  "properties": {
    "iso:country":"GB",
    "wof:name":"MK42 0EL",
    "wof:placetype":"postalcode"
},
  "geometry": {"coordinates":[-0.45766255830566,52.1275409711442],"type":"Point"}
}