{
  "type": "Feature",
  "properties": {
    "iso:country":"GB",
    "wof:name":"KY7 4PN",
    "wof:placetype":"postalcode"
},
  "geometry": {"coordinates":[-3.16127687706227,56.18534887984097],"type":"Point"}
}