{
  "type": "Feature",
  "properties": {
    "iso:country": "GB",
    "wof:name": "DY5 2LW",
    "wof:placetype": "postalcode"
  },
  "geometry": {"coordinates":[-2.118764,52.465677],"type":"Point"}
}
