{
  "type": "Feature",
  "properties": {
    "date:inception_lower": "1980-01-01",
    "date:inception_upper": "1980-01-01",
    "iso:country": "GB",
    "wof:name": "DY5 2LW",
    "wof:placetype": "postalcode"
  },
  "geometry": {"coordinates":[-2.118764,52.465677],"type":"Point"}
}
