{
  "type": "Feature",
  "properties": {
    "iso:country":"GB",
    "wof:name":"DY5 2LW",
    "wof:placetype":"postalcode"
},
  "geometry": {"coordinates":[-2.1185643748784,52.46565347068298],"type":"Point"}
}