{
  "type": "Feature",
  "properties": {
    "iso:country":"GB",
    "wof:name":"SG7 5RR",
    "wof:placetype":"postalcode"
},
  "geometry": {"coordinates":[-0.11177848959079,52.03198930287661],"type":"Point"}
}