{
  "type": "Feature",
  "properties": {
    "iso:country": "GB",
    "wof:name": "EX34 0NW",
    "wof:placetype": "postalcode"
  },
  "geometry": {"coordinates":[-4.023974,51.19669],"type":"Point"}
}
