{
  "type": "Feature",
  "properties": {
    "iso:country": "GB",
    "wof:name": "EX34 0NW",
    "wof:placetype": "postalcode"
  },
  "geometry": {"coordinates":[-4.023923,51.196664],"type":"Point"}
}
