{
  "type": "Feature",
  "properties": {
    "date:inception_lower": "1980-01-01",
    "date:inception_upper": "1980-01-01",
    "iso:country": "GB",
    "wof:name": "EX34 0NW",
    "wof:placetype": "postalcode"
  },
  "geometry": {"coordinates":[-4.023944,51.196664],"type":"Point"}
}
