{
  "type": "Feature",
  "properties": {
    "iso:country":"GB",
    "wof:name":"EX34 0NW",
    "wof:placetype":"postalcode"
},
  "geometry": {"coordinates":[-4.02390979975219,51.19701522341231],"type":"Point"}
}