{
  "type": "Feature",
  "properties": {
    "iso:country": "GB",
    "wof:name": "OX2 0BB",
    "wof:placetype": "postalcode"
  },
  "geometry": {"coordinates":[-1.273196,51.749845],"type":"Point"}
}
