{
  "type": "Feature",
  "properties": {
    "iso:country":"GB",
    "wof:name":"OX2 0BB",
    "wof:placetype":"postalcode"
},
  "geometry": {"coordinates":[-1.27319630530521,51.74984469448557],"type":"Point"}
}