{
  "type": "Feature",
  "properties": {
    "iso:country":"GB",
    "wof:name":"NE3 3GH",
    "wof:placetype":"postalcode"
},
  "geometry": {"coordinates":[-1.6640416517407,55.00078988130939],"type":"Point"}
}