{
  "type": "Feature",
  "properties": {
    "iso:country": "GB",
    "wof:name": "NE3 3GH",
    "wof:placetype": "postalcode"
  },
  "geometry": {"coordinates":[-1.664042,55.00079],"type":"Point"}
}
