{
  "type": "Feature",
  "properties": {
    "iso:country": "GB",
    "wof:name": "IP27 0PH",
    "wof:placetype": "postalcode"
  },
  "geometry": {"coordinates":[0.623256,52.454182],"type":"Point"}
}
