{
  "type": "Feature",
  "properties": {
    "iso:country":"GB",
    "wof:name":"NR21 0HW",
    "wof:placetype":"postalcode"
},
  "geometry": {"coordinates":[0.89262580228591,52.87431353582317],"type":"Point"}
}