{
  "type": "Feature",
  "properties": {
    "date:inception_lower": "2005-03-01",
    "date:inception_upper": "2005-03-01",
    "iso:country": "GB",
    "wof:name": "KY7 9SG",
    "wof:placetype": "postalcode"
  },
  "geometry": {"coordinates":[-3.176264,56.197571],"type":"Point"}
}
