{
  "type": "Feature",
  "properties": {
    "iso:country":"GB",
    "wof:name":"SW19 6DX",
    "wof:placetype":"postalcode"
},
  "geometry": {"coordinates":[-0.22048541218265,51.44515739339122],"type":"Point"}
}