{
  "type": "Feature",
  "properties": {
    "iso:country": "GB",
    "wof:name": "E9 5AA",
    "wof:placetype": "postalcode"
  },
  "geometry": {"coordinates":[-0.022437,51.541822],"type":"Point"}
}
