{
  "type": "Feature",
  "properties": {
    "iso:country":"GB",
    "wof:name":"SO22 4QS",
    "wof:placetype":"postalcode"
},
  "geometry": {"coordinates":[-1.34416048534942,51.04707108905224],"type":"Point"}
}