{
  "type": "Feature",
  "properties": {
    "iso:country": "GB",
    "wof:name": "SO22 4QS",
    "wof:placetype": "postalcode"
  },
  "geometry": {"coordinates":[-1.34416,51.047071],"type":"Point"}
}
