{
  "type": "Feature",
  "properties": {
    "date:inception_lower":"1990-02-01",
    "date:inception_upper":"1990-02-28",
    "iso:country":"GB",
    "wof:name":"SO22 4QS",
    "wof:placetype":"postalcode"
},
  "geometry": {"coordinates":[-1.34416,51.047071],"type":"Point"}
}