{
  "type": "Feature",
  "properties": {
    "iso:country":"GB",
    "wof:name":"SW5 9RE",
    "wof:placetype":"postalcode"
},
  "geometry": {"coordinates":[-0.19318825136949,51.49249905765534],"type":"Point"}
}