{
  "type": "Feature",
  "properties": {
    "date:inception_lower": "2019-12-01",
    "date:inception_upper": "2019-12-01",
    "iso:country": "GB",
    "wof:name": "SO30 2BL",
    "wof:placetype": "postalcode"
  },
  "geometry": {"coordinates":[-1.245188,50.905599],"type":"Point"}
}
