{
  "type": "Feature",
  "properties": {
    "iso:country":"GB",
    "wof:name":"SY7 8NQ",
    "wof:placetype":"postalcode"
},
  "geometry": {"coordinates":[-3.0750917502948,52.45865856228608],"type":"Point"}
}