{
  "type": "Feature",
  "properties": {
    "date:inception_lower": "1980-01-01",
    "date:inception_upper": "1980-01-01",
    "iso:country": "GB",
    "wof:name": "SY7 8NQ",
    "wof:placetype": "postalcode"
  },
  "geometry": {"coordinates":[-3.075858,52.459934],"type":"Point"}
}
