{
  "type": "Feature",
  "properties": {
    "iso:country": "GB",
    "wof:name": "SY7 8NQ",
    "wof:placetype": "postalcode"
  },
  "geometry": {"coordinates":[-3.075091,52.458673],"type":"Point"}
}
