{
  "type": "Feature",
  "properties": {
    "iso:country":"GB",
    "wof:name":"TN6 2NU",
    "wof:placetype":"postalcode"
},
  "geometry": {"coordinates":[0.1680046952869,51.04840762025366],"type":"Point"}
}