{
  "type": "Feature",
  "properties": {
    "date:inception_lower": "1980-01-01",
    "date:inception_upper": "1980-01-01",
    "iso:country": "GB",
    "wof:name": "TN6 2NU",
    "wof:placetype": "postalcode"
  },
  "geometry": {"coordinates":[0.167934,51.048416],"type":"Point"}
}
