{
  "type": "Feature",
  "properties": {
    "iso:country": "GB",
    "wof:name": "TN6 2NU",
    "wof:placetype": "postalcode"
  },
  "geometry": {"coordinates":[0.168033,51.048405],"type":"Point"}
}
