{
  "type": "Feature",
  "properties": {
    "iso:country":"GB",
    "wof:name":"NE2 2ND",
    "wof:placetype":"postalcode"
},
  "geometry": {"coordinates":[-1.60023858658378,54.99040673268341],"type":"Point"}
}