{
  "type": "Feature",
  "properties": {
    "iso:country": "GB",
    "wof:name": "NE2 2ND",
    "wof:placetype": "postalcode"
  },
  "geometry": {"coordinates":[-1.600239,54.990407],"type":"Point"}
}
