{
  "type": "Feature",
  "properties": {
    "date:inception_lower": "2021-09-01",
    "date:inception_upper": "2021-09-01",
    "iso:country": "GB",
    "wof:name": "NW4 3AJ",
    "wof:placetype": "postalcode"
  },
  "geometry": {"coordinates":[-0.220683,51.575563],"type":"Point"}
}
