{
  "type": "Feature",
  "properties": {
    "date:inception_lower":"1985-10-01",
    "date:inception_upper":"1985-10-31",
    "iso:country":"GB",
    "wof:name":"SK9 6DF",
    "wof:placetype":"postalcode"
},
  "geometry": {"coordinates":[-2.247435,53.323964],"type":"Point"}
}