{
  "type": "Feature",
  "properties": {
    "iso:country":"GB",
    "wof:name":"SK9 6DF",
    "wof:placetype":"postalcode"
},
  "geometry": {"coordinates":[-2.24743507061501,53.32396352831415],"type":"Point"}
}