{
  "type": "Feature",
  "properties": {
    "iso:country":"GB",
    "wof:name":"SO23 0AF",
    "wof:placetype":"postalcode"
},
  "geometry": {"coordinates":[-1.30475864026462,51.06332630542457],"type":"Point"}
}