{
  "type": "Feature",
  "properties": {
    "date:inception_lower": "2012-10-01",
    "date:inception_upper": "2012-10-01",
    "iso:country": "GB",
    "wof:name": "SO23 0AF",
    "wof:placetype": "postalcode"
  },
  "geometry": {"coordinates":[-1.304759,51.063326],"type":"Point"}
}
