{
  "type": "Feature",
  "properties": {
    "iso:country":"GB",
    "wof:name":"TW3 2DW",
    "wof:placetype":"postalcode"
},
  "geometry": {"coordinates":[-0.35931841931289,51.46295517630266],"type":"Point"}
}