{
  "type": "Feature",
  "properties": {
    "iso:country":"GB",
    "wof:name":"SW4 6JY",
    "wof:placetype":"postalcode"
},
  "geometry": {"coordinates":[-0.13656523322031,51.46870893453988],"type":"Point"}
}