{
  "type": "Feature",
  "properties": {
    "iso:country": "GB",
    "wof:name": "ST13 8AW",
    "wof:placetype": "postalcode"
  },
  "geometry": {"coordinates":[-2.032627,53.106093],"type":"Point"}
}
