{
  "type": "Feature",
  "properties": {
    "iso:country":"GB",
    "wof:name":"LE18 4WG",
    "wof:placetype":"postalcode"
},
  "geometry": {"coordinates":[-1.13260065520148,52.58823530776995],"type":"Point"}
}