{
  "type": "Feature",
  "properties": {
    "iso:country":"GB",
    "wof:name":"UB5 4BZ",
    "wof:placetype":"postalcode"
},
  "geometry": {"coordinates":[-0.37122817105037,51.55375426694692],"type":"Point"}
}