{
  "type": "Feature",
  "properties": {
    "date:inception_lower": "1990-02-01",
    "date:inception_upper": "1990-02-01",
    "iso:country": "GB",
    "wof:name": "WA1 1NF",
    "wof:placetype": "postalcode"
  },
  "geometry": {"coordinates":[-2.601717,53.386017],"type":"Point"}
}
