{
  "type": "Feature",
  "properties": {
    "iso:country":"GB",
    "wof:name":"WA1 1NF",
    "wof:placetype":"postalcode"
},
  "geometry": {"coordinates":[-2.60171756921744,53.38600096022174],"type":"Point"}
}