{
  "type": "Feature",
  "properties": {
    "iso:country": "GB",
    "wof:name": "BL0 0NU",
    "wof:placetype": "postalcode"
  },
  "geometry": {"coordinates":[-2.319513,53.664562],"type":"Point"}
}
