{
  "type": "Feature",
  "properties": {
    "date:inception_lower": "1980-01-01",
    "date:inception_upper": "1980-01-01",
    "iso:country": "GB",
    "wof:name": "EH10 4NH",
    "wof:placetype": "postalcode"
  },
  "geometry": {"coordinates":[-3.2117,55.936842],"type":"Point"}
}
