{
  "type": "Feature",
  "properties": {
    "iso:country":"GB",
    "wof:name":"KY8 5HS",
    "wof:placetype":"postalcode"
},
  "geometry": {"coordinates":[-3.04278117322793,56.21527390648789],"type":"Point"}
}