{
  "type": "Feature",
  "properties": {
    "iso:country":"GB",
    "wof:name":"DN21 3SQ",
    "wof:placetype":"postalcode"
},
  "geometry": {"coordinates":[-0.66808186117753,53.49577363792049],"type":"Point"}
}