{
  "type": "Feature",
  "properties": {
    "date:inception_lower": "2018-01-01",
    "date:inception_upper": "2018-01-01",
    "iso:country": "GB",
    "wof:name": "B29 6UL",
    "wof:placetype": "postalcode"
  },
  "geometry": {"coordinates":[-1.934552,52.436115],"type":"Point"}
}
