{
  "type": "Feature",
  "properties": {
    "iso:country":"GB",
    "wof:name":"WA7 1EL",
    "wof:placetype":"postalcode"
},
  "geometry": {"coordinates":[-2.74058092824799,53.34263097905589],"type":"Point"}
}