{
  "type": "Feature",
  "properties": {
    "iso:country":"GB",
    "wof:name":"DD9 7BG",
    "wof:placetype":"postalcode"
},
  "geometry": {"coordinates":[-2.64995498316868,56.72993654652984],"type":"Point"}
}