{
  "type": "Feature",
  "properties": {
    "iso:country": "GB",
    "wof:name": "WF13 4BD",
    "wof:placetype": "postalcode"
  },
  "geometry": {"coordinates":[-1.658238,53.707987],"type":"Point"}
}
