{
  "type": "Feature",
  "properties": {
    "date:inception_lower":"1980-01-01",
    "date:inception_upper":"1980-01-31",
    "iso:country":"GB",
    "wof:name":"WF13 4BD",
    "wof:placetype":"postalcode"
},
  "geometry": {"coordinates":[-1.658238,53.707987],"type":"Point"}
}