{
  "type": "Feature",
  "properties": {
    "iso:country":"GB",
    "wof:name":"M25 3BS",
    "wof:placetype":"postalcode"
},
  "geometry": {"coordinates":[-2.28276376972972,53.53512472782567],"type":"Point"}
}