{
  "type": "Feature",
  "properties": {
    "date:inception_lower": "2023-04-01",
    "date:inception_upper": "2023-04-01",
    "iso:country": "GB",
    "wof:name": "DN21 2FF",
    "wof:placetype": "postalcode"
  },
  "geometry": {"coordinates":[-0.785131,53.403196],"type":"Point"}
}
