{
  "type": "Feature",
  "properties": {
    "date:inception_lower":"2000-12-01",
    "date:inception_upper":"2000-12-31",
    "iso:country":"GB",
    "wof:name":"TQ13 7FB",
    "wof:placetype":"postalcode"
},
  "geometry": {"coordinates":[-3.747301,50.521087],"type":"Point"}
}