{
  "type": "Feature",
  "properties": {
    "iso:country": "GB",
    "wof:name": "TQ13 7FB",
    "wof:placetype": "postalcode"
  },
  "geometry": {"coordinates":[-3.747301,50.521087],"type":"Point"}
}
