{
  "type": "Feature",
  "properties": {
    "iso:country":"GB",
    "wof:name":"TQ13 7FB",
    "wof:placetype":"postalcode"
},
  "geometry": {"coordinates":[-3.74730135107623,50.52108664070614],"type":"Point"}
}