{
  "type": "Feature",
  "properties": {
    "iso:country": "GB",
    "wof:name": "CV8 1JY",
    "wof:placetype": "postalcode"
  },
  "geometry": {"coordinates":[-1.580318,52.340555],"type":"Point"}
}
