{
  "type": "Feature",
  "properties": {
    "iso:country":"GB",
    "wof:name":"CV8 1JY",
    "wof:placetype":"postalcode"
},
  "geometry": {"coordinates":[-1.58031803657655,52.34055513837968],"type":"Point"}
}