{
  "type": "Feature",
  "properties": {
    "iso:country":"GB",
    "wof:name":"S44 6AD",
    "wof:placetype":"postalcode"
},
  "geometry": {"coordinates":[-1.31140678844243,53.24230566244035],"type":"Point"}
}