{
  "type": "Feature",
  "properties": {
    "date:inception_lower":"1990-02-01",
    "date:inception_upper":"1990-02-28",
    "iso:country":"GB",
    "wof:name":"ME15 6FZ",
    "wof:placetype":"postalcode"
},
  "geometry": {"coordinates":[0.514859,51.262381],"type":"Point"}
}