{
  "type": "Feature",
  "properties": {
    "iso:country":"GB",
    "wof:name":"ME15 6FZ",
    "wof:placetype":"postalcode"
},
  "geometry": {"coordinates":[0.51485884812298,51.2623808172573],"type":"Point"}
}