{
  "type": "Feature",
  "properties": {
    "iso:country": "GB",
    "wof:name": "ME15 6FZ",
    "wof:placetype": "postalcode"
  },
  "geometry": {"coordinates":[0.514859,51.262381],"type":"Point"}
}
