{
  "type": "Feature",
  "properties": {
    "date:inception_lower": "1980-01-01",
    "date:inception_upper": "1980-01-01",
    "iso:country": "GB",
    "wof:name": "SR3 4ED",
    "wof:placetype": "postalcode"
  },
  "geometry": {"coordinates":[-1.427413,54.890641],"type":"Point"}
}
