{
  "type": "Feature",
  "properties": {
    "iso:country":"GB",
    "wof:name":"SR3 4ED",
    "wof:placetype":"postalcode"
},
  "geometry": {"coordinates":[-1.42741308387979,54.89064144251376],"type":"Point"}
}