{
  "type": "Feature",
  "properties": {
    "iso:country":"GB",
    "wof:name":"HR2 0JX",
    "wof:placetype":"postalcode"
},
  "geometry": {"coordinates":[-2.9863793354942,52.00982662174861],"type":"Point"}
}