{
  "type": "Feature",
  "properties": {
    "date:inception_lower": "1980-01-01",
    "date:inception_upper": "1980-01-01",
    "iso:country": "GB",
    "wof:name": "HR2 0JX",
    "wof:placetype": "postalcode"
  },
  "geometry": {"coordinates":[-2.98637,52.009816],"type":"Point"}
}
