{
  "type": "Feature",
  "properties": {
    "iso:country":"GB",
    "wof:name":"CF11 8AD",
    "wof:placetype":"postalcode"
},
  "geometry": {"coordinates":[-3.2017999067881,51.47572328459574],"type":"Point"}
}