{
  "type": "Feature",
  "properties": {
    "date:inception_lower": "1999-06-01",
    "date:inception_upper": "1999-06-01",
    "iso:country": "GB",
    "wof:name": "CF11 8AD",
    "wof:placetype": "postalcode"
  },
  "geometry": {"coordinates":[-3.2018,51.475723],"type":"Point"}
}
