{
  "type": "Feature",
  "properties": {
    "iso:country": "GB",
    "wof:name": "W11 2QL",
    "wof:placetype": "postalcode"
  },
  "geometry": {"coordinates":[-0.196744,51.515179],"type":"Point"}
}
