{
  "type": "Feature",
  "properties": {
    "iso:country":"GB",
    "wof:name":"W11 2QL",
    "wof:placetype":"postalcode"
},
  "geometry": {"coordinates":[-0.19674443267531,51.51517881390561],"type":"Point"}
}