{
  "type": "Feature",
  "properties": {
    "iso:country":"GB",
    "wof:name":"NG31 8FT",
    "wof:placetype":"postalcode"
},
  "geometry": {"coordinates":[-0.64023106189518,52.92225874708026],"type":"Point"}
}