{
  "type": "Feature",
  "properties": {
    "iso:country": "GB",
    "wof:name": "NG31 8FT",
    "wof:placetype": "postalcode"
  },
  "geometry": {"coordinates":[-0.640231,52.922259],"type":"Point"}
}
