{
  "type": "Feature",
  "properties": {
    "iso:country":"GB",
    "wof:name":"NW1 8PR",
    "wof:placetype":"postalcode"
},
  "geometry": {"coordinates":[-0.14213176475109,51.54500882529959],"type":"Point"}
}