{
  "type": "Feature",
  "properties": {
    "date:inception_lower": "2020-06-01",
    "date:inception_upper": "2020-06-01",
    "iso:country": "GB",
    "wof:name": "B38 8RJ",
    "wof:placetype": "postalcode"
  },
  "geometry": {"coordinates":[-1.937116,52.40039],"type":"Point"}
}
