{
  "type": "Feature",
  "properties": {
    "iso:country": "GB",
    "wof:name": "NE65 7XJ",
    "wof:placetype": "postalcode"
  },
  "geometry": {"coordinates":[-1.888695,55.306562],"type":"Point"}
}
