{
  "type": "Feature",
  "properties": {
    "iso:country": "GB",
    "wof:name": "CO7 8HT",
    "wof:placetype": "postalcode"
  },
  "geometry": {"coordinates":[1.035146,51.851718],"type":"Point"}
}
