{
  "type": "Feature",
  "properties": {
    "iso:country":"GB",
    "wof:name":"CO7 8HT",
    "wof:placetype":"postalcode"
},
  "geometry": {"coordinates":[1.03514612079662,51.85171835470506],"type":"Point"}
}