{
  "type": "Feature",
  "properties": {
    "iso:country": "GB",
    "wof:name": "DL15 0SR",
    "wof:placetype": "postalcode"
  },
  "geometry": {"coordinates":[-1.688942,54.719537],"type":"Point"}
}
