{
  "type": "Feature",
  "properties": {
    "iso:country":"GB",
    "wof:name":"DL15 0SR",
    "wof:placetype":"postalcode"
},
  "geometry": {"coordinates":[-1.68894177486179,54.71953656446669],"type":"Point"}
}