{
  "type": "Feature",
  "properties": {
    "date:inception_lower": "2019-09-01",
    "date:inception_upper": "2019-09-01",
    "iso:country": "GB",
    "wof:name": "GU16 9AF",
    "wof:placetype": "postalcode"
  },
  "geometry": {"coordinates":[-0.702947,51.324329],"type":"Point"}
}
