{
  "type": "Feature",
  "properties": {
    "iso:country":"GB",
    "wof:name":"S42 7AL",
    "wof:placetype":"postalcode"
},
  "geometry": {"coordinates":[-1.48936844459271,53.25582077260762],"type":"Point"}
}