{
  "type": "Feature",
  "properties": {
    "iso:country":"GB",
    "wof:name":"LE11 1SB",
    "wof:placetype":"postalcode"
},
  "geometry": {"coordinates":[-1.19885678998711,52.76884122629104],"type":"Point"}
}