{
  "type": "Feature",
  "properties": {
    "iso:country": "GB",
    "wof:name": "BS39 6HJ",
    "wof:placetype": "postalcode"
  },
  "geometry": {"coordinates":[-2.504826,51.319476],"type":"Point"}
}
