{
  "type": "Feature",
  "properties": {
    "iso:country":"GB",
    "wof:name":"BS39 6HJ",
    "wof:placetype":"postalcode"
},
  "geometry": {"coordinates":[-2.50482609935544,51.31947640387877],"type":"Point"}
}