{
  "type": "Feature",
  "properties": {
    "iso:country": "GB",
    "wof:name": "BN17 7FH",
    "wof:placetype": "postalcode"
  },
  "geometry": {"coordinates":[-0.557966,50.821902],"type":"Point"}
}
