{
  "type": "Feature",
  "properties": {
    "iso:country":"GB",
    "wof:name":"BN17 7FH",
    "wof:placetype":"postalcode"
},
  "geometry": {"coordinates":[-0.55796607401668,50.82190180866646],"type":"Point"}
}