{
  "type": "Feature",
  "properties": {
    "iso:country": "GB",
    "wof:name": "BH14 8FS",
    "wof:placetype": "postalcode"
  },
  "geometry": {"coordinates":[-1.928024,50.707838],"type":"Point"}
}
