{
  "type": "Feature",
  "properties": {
    "iso:country":"GB",
    "wof:name":"CV6 6AH",
    "wof:placetype":"postalcode"
},
  "geometry": {"coordinates":[-1.49267633207063,52.45340683320035],"type":"Point"}
}