{
  "type": "Feature",
  "properties": {
    "iso:country":"GB",
    "wof:name":"BH23 2LG",
    "wof:placetype":"postalcode"
},
  "geometry": {"coordinates":[-1.79335517991541,50.74908248150132],"type":"Point"}
}