{
  "type": "Feature",
  "properties": {
    "iso:country":"GB",
    "wof:name":"B67 5QU",
    "wof:placetype":"postalcode"
},
  "geometry": {"coordinates":[-1.97479339755453,52.478817896694],"type":"Point"}
}