{
  "type": "Feature",
  "properties": {
    "iso:country":"GB",
    "wof:name":"W3 7EB",
    "wof:placetype":"postalcode"
},
  "geometry": {"coordinates":[-0.25785349614948,51.51517614937231],"type":"Point"}
}