{
  "type": "Feature",
  "properties": {
    "iso:country":"GB",
    "wof:name":"SW2 4XH",
    "wof:placetype":"postalcode"
},
  "geometry": {"coordinates":[-0.13527450872373,51.44138690111243],"type":"Point"}
}