{
  "type": "Feature",
  "properties": {
    "date:inception_lower": "2018-12-01",
    "date:inception_upper": "2018-12-01",
    "iso:country": "GB",
    "wof:name": "L32 1BL",
    "wof:placetype": "postalcode"
  },
  "geometry": {"coordinates":[-2.880639,53.4918],"type":"Point"}
}
