{
  "type": "Feature",
  "properties": {
    "iso:country": "GB",
    "wof:name": "L32 1BL",
    "wof:placetype": "postalcode"
  },
  "geometry": {"coordinates":[-2.880459,53.491855],"type":"Point"}
}
