{
  "type": "Feature",
  "properties": {
    "date:inception_lower":"1980-01-01",
    "date:inception_upper":"1980-01-31",
    "iso:country":"GB",
    "wof:name":"NE23 6TX",
    "wof:placetype":"postalcode"
},
  "geometry": {"coordinates":[-1.594164,55.079718],"type":"Point"}
}