{
  "type": "Feature",
  "properties": {
    "iso:country":"GB",
    "wof:name":"NE23 6TX",
    "wof:placetype":"postalcode"
},
  "geometry": {"coordinates":[-1.59416444340766,55.07971824243141],"type":"Point"}
}