{
  "type": "Feature",
  "properties": {
    "iso:country":"GB",
    "wof:name":"ST17 4EJ",
    "wof:placetype":"postalcode"
},
  "geometry": {"coordinates":[-2.10857828333946,52.78463704345087],"type":"Point"}
}