{
  "type": "Feature",
  "properties": {
    "iso:country":"GB",
    "wof:name":"TN2 4HN",
    "wof:placetype":"postalcode"
},
  "geometry": {"coordinates":[0.32735167721437,51.14345386142297],"type":"Point"}
}