{
  "type": "Feature",
  "properties": {
    "iso:country":"GB",
    "wof:name":"YO21 2QW",
    "wof:placetype":"postalcode"
},
  "geometry": {"coordinates":[-0.79562024927296,54.44366708437435],"type":"Point"}
}