{
  "type": "Feature",
  "properties": {
    "date:inception_lower": "1980-01-01",
    "date:inception_upper": "1980-01-01",
    "iso:country": "GB",
    "wof:name": "YO21 2QW",
    "wof:placetype": "postalcode"
  },
  "geometry": {"coordinates":[-0.797018,54.443884],"type":"Point"}
}
