{
  "type": "Feature",
  "properties": {
    "iso:country":"GB",
    "wof:name":"DY2 7TJ",
    "wof:placetype":"postalcode"
},
  "geometry": {"coordinates":[-2.06127132119905,52.50394040079639],"type":"Point"}
}