{
  "type": "Feature",
  "properties": {
    "iso:country":"GB",
    "wof:name":"PE24 5QX",
    "wof:placetype":"postalcode"
},
  "geometry": {"coordinates":[0.33741175648,53.23148997300049],"type":"Point"}
}