{
  "type": "Feature",
  "properties": {
    "iso:country":"GB",
    "wof:name":"AB21 7NJ",
    "wof:placetype":"postalcode"
},
  "geometry": {"coordinates":[-2.17594907591222,57.20851997718687],"type":"Point"}
}