{
  "type": "Feature",
  "properties": {
    "date:inception_lower": "1980-01-01",
    "date:inception_upper": "1980-01-01",
    "iso:country": "GB",
    "wof:name": "ME7 3NH",
    "wof:placetype": "postalcode"
  },
  "geometry": {"coordinates":[0.562214,51.327682],"type":"Point"}
}
