{
  "type": "Feature",
  "properties": {
    "iso:country":"GB",
    "wof:name":"ME7 3NH",
    "wof:placetype":"postalcode"
},
  "geometry": {"coordinates":[0.56221420295972,51.32768225761381],"type":"Point"}
}