{
  "type": "Feature",
  "properties": {
    "iso:country": "GB",
    "wof:name": "ME7 3NH",
    "wof:placetype": "postalcode"
  },
  "geometry": {"coordinates":[0.562214,51.327682],"type":"Point"}
}
