{
  "type": "Feature",
  "properties": {
    "iso:country": "GB",
    "wof:name": "NG5 8NH",
    "wof:placetype": "postalcode"
  },
  "geometry": {"coordinates":[-1.145782,52.983442],"type":"Point"}
}
