{
  "type": "Feature",
  "properties": {
    "iso:country": "GB",
    "wof:name": "DT11 9PU",
    "wof:placetype": "postalcode"
  },
  "geometry": {"coordinates":[-2.159502,50.850789],"type":"Point"}
}
