{
  "type": "Feature",
  "properties": {
    "iso:country":"GB",
    "wof:name":"NR12 9QE",
    "wof:placetype":"postalcode"
},
  "geometry": {"coordinates":[1.52968346194763,52.76617736987343],"type":"Point"}
}