{
  "type": "Feature",
  "properties": {
    "iso:country":"GB",
    "wof:name":"M28 3AY",
    "wof:placetype":"postalcode"
},
  "geometry": {"coordinates":[-2.39940295160364,53.52512923872002],"type":"Point"}
}