{
  "type": "Feature",
  "properties": {
    "date:inception_lower": "1980-01-01",
    "date:inception_upper": "1980-01-01",
    "iso:country": "GB",
    "wof:name": "PL30 4JR",
    "wof:placetype": "postalcode"
  },
  "geometry": {"coordinates":[-4.681897,50.529383],"type":"Point"}
}
