{
  "type": "Feature",
  "properties": {
    "iso:country":"GB",
    "wof:name":"PL30 4JR",
    "wof:placetype":"postalcode"
},
  "geometry": {"coordinates":[-4.68189712845084,50.52938348603451],"type":"Point"}
}