{
  "type": "Feature",
  "properties": {
    "iso:country":"GB",
    "wof:name":"TS21 3EN",
    "wof:placetype":"postalcode"
},
  "geometry": {"coordinates":[-1.42088267860646,54.65858437033278],"type":"Point"}
}