{
  "type": "Feature",
  "properties": {
    "date:inception_lower": "1986-04-01",
    "date:inception_upper": "1986-04-01",
    "iso:country": "GB",
    "wof:name": "DE13 0GW",
    "wof:placetype": "postalcode"
  },
  "geometry": {"coordinates":[-1.62656,52.834981],"type":"Point"}
}
