{
  "type": "Feature",
  "properties": {
    "iso:country":"GB",
    "wof:name":"DE13 0GW",
    "wof:placetype":"postalcode"
},
  "geometry": {"coordinates":[-1.62656018267505,52.83498077452032],"type":"Point"}
}