{
  "type": "Feature",
  "properties": {
    "iso:country": "GB",
    "wof:name": "EH48 4PR",
    "wof:placetype": "postalcode"
  },
  "geometry": {"coordinates":[-3.644243,55.902375],"type":"Point"}
}
