{
  "type": "Feature",
  "properties": {
    "date:inception_lower": "2013-07-01",
    "date:inception_upper": "2013-07-01",
    "iso:country": "GB",
    "wof:name": "EH48 4PR",
    "wof:placetype": "postalcode"
  },
  "geometry": {"coordinates":[-3.644243,55.902375],"type":"Point"}
}
