{
  "type": "Feature",
  "properties": {
    "iso:country": "GB",
    "wof:name": "DN34 4PB",
    "wof:placetype": "postalcode"
  },
  "geometry": {"coordinates":[-0.096994,53.562112],"type":"Point"}
}
