{
  "type": "Feature",
  "properties": {
    "iso:country":"GB",
    "wof:name":"CB6 2HN",
    "wof:placetype":"postalcode"
},
  "geometry": {"coordinates":[0.21282079295753,52.38488749722277],"type":"Point"}
}