{
  "type": "Feature",
  "properties": {
    "iso:country": "GB",
    "wof:name": "HA7 1NA",
    "wof:placetype": "postalcode"
  },
  "geometry": {"coordinates":[-0.299117,51.599077],"type":"Point"}
}
