{
  "type": "Feature",
  "properties": {
    "iso:country":"GB",
    "wof:name":"HA7 1NA",
    "wof:placetype":"postalcode"
},
  "geometry": {"coordinates":[-0.29911666843145,51.59907714742737],"type":"Point"}
}