{
  "type": "Feature",
  "properties": {
    "date:inception_lower": "1980-01-01",
    "date:inception_upper": "1980-01-01",
    "iso:country": "GB",
    "wof:name": "M4 6JW",
    "wof:placetype": "postalcode"
  },
  "geometry": {"coordinates":[-2.224876,53.485108],"type":"Point"}
}
