{
  "type": "Feature",
  "properties": {
    "iso:country":"GB",
    "wof:name":"M4 6JW",
    "wof:placetype":"postalcode"
},
  "geometry": {"coordinates":[-2.22397516834812,53.48520194516487],"type":"Point"}
}