{
  "type": "Feature",
  "properties": {
    "iso:country": "GB",
    "wof:name": "M4 6JW",
    "wof:placetype": "postalcode"
  },
  "geometry": {"coordinates":[-2.224879,53.485092],"type":"Point"}
}
