{
  "type": "Feature",
  "properties": {
    "date:inception_lower": "2001-06-01",
    "date:inception_upper": "2001-06-01",
    "iso:country": "GB",
    "wof:name": "S73 0BT",
    "wof:placetype": "postalcode"
  },
  "geometry": {"coordinates":[-1.390714,53.525136],"type":"Point"}
}
