{
  "type": "Feature",
  "properties": {
    "date:inception_lower": "1980-01-01",
    "date:inception_upper": "1980-01-01",
    "iso:country": "GB",
    "wof:name": "S71 5QB",
    "wof:placetype": "postalcode"
  },
  "geometry": {"coordinates":[-1.439484,53.555809],"type":"Point"}
}
