{
  "type": "Feature",
  "properties": {
    "iso:country":"GB",
    "wof:name":"S71 5QB",
    "wof:placetype":"postalcode"
},
  "geometry": {"coordinates":[-1.43948371502046,53.55580946383686],"type":"Point"}
}