{
  "type": "Feature",
  "properties": {
    "iso:country":"GB",
    "wof:name":"DN15 9LP",
    "wof:placetype":"postalcode"
},
  "geometry": {"coordinates":[-0.63401064860139,53.70522852998923],"type":"Point"}
}