{
  "type": "Feature",
  "properties": {
    "iso:country": "GB",
    "wof:name": "DN15 9LP",
    "wof:placetype": "postalcode"
  },
  "geometry": {"coordinates":[-0.634011,53.705229],"type":"Point"}
}
