{
  "type": "Feature",
  "properties": {
    "iso:country":"GB",
    "wof:name":"PE38 9GP",
    "wof:placetype":"postalcode"
},
  "geometry": {"coordinates":[0.36897827454882,52.60226089362429],"type":"Point"}
}