{
  "type": "Feature",
  "properties": {
    "iso:country": "GB",
    "wof:name": "IP17 2AZ",
    "wof:placetype": "postalcode"
  },
  "geometry": {"coordinates":[1.438682,52.22836],"type":"Point"}
}
