{
  "type": "Feature",
  "properties": {
    "date:inception_lower": "1980-01-01",
    "date:inception_upper": "1980-01-01",
    "iso:country": "GB",
    "wof:name": "LD1 6AA",
    "wof:placetype": "postalcode"
  },
  "geometry": {"coordinates":[-3.382675,52.239763],"type":"Point"}
}
