{
  "type": "Feature",
  "properties": {
    "iso:country": "GB",
    "wof:name": "SE15 6GP",
    "wof:placetype": "postalcode"
  },
  "geometry": {"coordinates":[-0.08089,51.48067],"type":"Point"}
}
