{
  "type": "Feature",
  "properties": {
    "iso:country":"GB",
    "wof:name":"HD3 3JU",
    "wof:placetype":"postalcode"
},
  "geometry": {"coordinates":[-1.82605655429742,53.66170858031425],"type":"Point"}
}