{
  "type": "Feature",
  "properties": {
    "iso:country":"GB",
    "wof:name":"DH8 8TD",
    "wof:placetype":"postalcode"
},
  "geometry": {"coordinates":[-1.84877669740466,54.85781033969685],"type":"Point"}
}