{
  "type": "Feature",
  "properties": {
    "date:inception_lower": "1980-01-01",
    "date:inception_upper": "1980-01-01",
    "iso:country": "GB",
    "wof:name": "BB11 3QZ",
    "wof:placetype": "postalcode"
  },
  "geometry": {"coordinates":[-2.217421,53.758726],"type":"Point"}
}
