{
  "type": "Feature",
  "properties": {
    "date:inception_lower": "2007-07-01",
    "date:inception_upper": "2007-07-01",
    "iso:country": "GB",
    "wof:name": "NR31 9GR",
    "wof:placetype": "postalcode"
  },
  "geometry": {"coordinates":[1.665538,52.575092],"type":"Point"}
}
