{
  "type": "Feature",
  "properties": {
    "iso:country":"GB",
    "wof:name":"HD2 2AY",
    "wof:placetype":"postalcode"
},
  "geometry": {"coordinates":[-1.79503192898001,53.65596105830351],"type":"Point"}
}