{
  "type": "Feature",
  "properties": {
    "iso:country": "GB",
    "wof:name": "RG20 8BX",
    "wof:placetype": "postalcode"
  },
  "geometry": {"coordinates":[-1.37457,51.426591],"type":"Point"}
}
