{
  "type": "Feature",
  "properties": {
    "iso:country":"GB",
    "wof:name":"RG20 8BX",
    "wof:placetype":"postalcode"
},
  "geometry": {"coordinates":[-1.37500462367598,51.42657591055629],"type":"Point"}
}