{
  "type": "Feature",
  "properties": {
    "iso:country":"GB",
    "wof:name":"DN33 3LP",
    "wof:placetype":"postalcode"
},
  "geometry": {"coordinates":[-0.10193312875625,53.53273114523671],"type":"Point"}
}