{
  "type": "Feature",
  "properties": {
    "date:inception_lower": "1980-01-01",
    "date:inception_upper": "1980-01-01",
    "iso:country": "GB",
    "wof:name": "NE10 9TE",
    "wof:placetype": "postalcode"
  },
  "geometry": {"coordinates":[-1.578759,54.946113],"type":"Point"}
}
