{
  "type": "Feature",
  "properties": {
    "iso:country":"GB",
    "wof:name":"NE10 9TE",
    "wof:placetype":"postalcode"
},
  "geometry": {"coordinates":[-1.57875946476705,54.94611280065055],"type":"Point"}
}