{
  "type": "Feature",
  "properties": {
    "iso:country":"GB",
    "wof:name":"DL15 0XJ",
    "wof:placetype":"postalcode"
},
  "geometry": {"coordinates":[-1.708079452974,54.68760067920616],"type":"Point"}
}