{
  "type": "Feature",
  "properties": {
    "iso:country": "GB",
    "wof:name": "DL15 0XJ",
    "wof:placetype": "postalcode"
  },
  "geometry": {"coordinates":[-1.708079,54.687601],"type":"Point"}
}
