{
  "type": "Feature",
  "properties": {
    "date:inception_lower":"1981-06-01",
    "date:inception_upper":"1981-06-30",
    "iso:country":"GB",
    "wof:name":"DL15 0XJ",
    "wof:placetype":"postalcode"
},
  "geometry": {"coordinates":[-1.708079,54.687601],"type":"Point"}
}