{
  "type": "Feature",
  "properties": {
    "iso:country": "GB",
    "wof:name": "CT5 3ET",
    "wof:placetype": "postalcode"
  },
  "geometry": {"coordinates":[1.049447,51.356546],"type":"Point"}
}
