{
  "type": "Feature",
  "properties": {
    "date:inception_lower": "1981-06-01",
    "date:inception_upper": "1981-06-01",
    "iso:country": "GB",
    "wof:name": "CT5 3ET",
    "wof:placetype": "postalcode"
  },
  "geometry": {"coordinates":[1.049447,51.356546],"type":"Point"}
}
