{
  "type": "Feature",
  "properties": {
    "iso:country":"GB",
    "wof:name":"CF37 4BD",
    "wof:placetype":"postalcode"
},
  "geometry": {"coordinates":[-3.32166232328623,51.59525807201724],"type":"Point"}
}