{
  "type": "Feature",
  "properties": {
    "iso:country": "GB",
    "wof:name": "W1D 2DZ",
    "wof:placetype": "postalcode"
  },
  "geometry": {"coordinates":[-0.13215,51.516164],"type":"Point"}
}
