{
  "type": "Feature",
  "properties": {
    "iso:country":"GB",
    "wof:name":"W1D 2DZ",
    "wof:placetype":"postalcode"
},
  "geometry": {"coordinates":[-0.13215007048677,51.51616427930715],"type":"Point"}
}