{
  "type": "Feature",
  "properties": {
    "iso:country":"GB",
    "wof:name":"LS25 4AR",
    "wof:placetype":"postalcode"
},
  "geometry": {"coordinates":[-1.33253430873182,53.79530281300983],"type":"Point"}
}