{
  "type": "Feature",
  "properties": {
    "date:inception_lower": "1980-01-01",
    "date:inception_upper": "1980-01-01",
    "iso:country": "GB",
    "wof:name": "LS25 4AR",
    "wof:placetype": "postalcode"
  },
  "geometry": {"coordinates":[-1.332534,53.795303],"type":"Point"}
}
