{
  "type": "Feature",
  "properties": {
    "iso:country":"GB",
    "wof:name":"NE64 6HE",
    "wof:placetype":"postalcode"
},
  "geometry": {"coordinates":[-1.51402967811179,55.18828225685709],"type":"Point"}
}