{
  "type": "Feature",
  "properties": {
    "iso:country":"GB",
    "wof:name":"DE5 9QX",
    "wof:placetype":"postalcode"
},
  "geometry": {"coordinates":[-1.36898663343246,53.05089584969205],"type":"Point"}
}