{
  "type": "Feature",
  "properties": {
    "date:inception_lower": "1980-01-01",
    "date:inception_upper": "1980-01-01",
    "iso:country": "GB",
    "wof:name": "DE5 9QX",
    "wof:placetype": "postalcode"
  },
  "geometry": {"coordinates":[-1.368879,53.050941],"type":"Point"}
}
