{
  "type": "Feature",
  "properties": {
    "iso:country": "GB",
    "wof:name": "TR19 7DQ",
    "wof:placetype": "postalcode"
  },
  "geometry": {"coordinates":[-5.678009,50.12292],"type":"Point"}
}
