{
  "type": "Feature",
  "properties": {
    "iso:country":"GB",
    "wof:name":"WF3 3LJ",
    "wof:placetype":"postalcode"
},
  "geometry": {"coordinates":[-1.49643451338869,53.73140623445859],"type":"Point"}
}