{
  "type": "Feature",
  "properties": {
    "iso:country":"GB",
    "wof:name":"DN22 8DP",
    "wof:placetype":"postalcode"
},
  "geometry": {"coordinates":[-1.01628762639305,53.2498097143714],"type":"Point"}
}