{
  "type": "Feature",
  "properties": {
    "date:inception_lower": "1980-01-01",
    "date:inception_upper": "1980-01-01",
    "iso:country": "GB",
    "wof:name": "DN22 8DP",
    "wof:placetype": "postalcode"
  },
  "geometry": {"coordinates":[-1.017205,53.249612],"type":"Point"}
}
