{
  "type": "Feature",
  "properties": {
    "iso:country": "GB",
    "wof:name": "DN22 8DP",
    "wof:placetype": "postalcode"
  },
  "geometry": {"coordinates":[-1.017205,53.249612],"type":"Point"}
}
