{
  "type": "Feature",
  "properties": {
    "iso:country": "GB",
    "wof:name": "DN22 8DP",
    "wof:placetype": "postalcode"
  },
  "geometry": {"coordinates":[-1.016286,53.24983],"type":"Point"}
}
