{
  "type": "Feature",
  "properties": {
    "date:inception_lower":"1980-01-01",
    "date:inception_upper":"1980-01-31",
    "iso:country":"GB",
    "wof:name":"SK12 2NF",
    "wof:placetype":"postalcode"
},
  "geometry": {"coordinates":[-2.060288,53.359225],"type":"Point"}
}