{
  "type": "Feature",
  "properties": {
    "iso:country":"GB",
    "wof:name":"SK12 2NF",
    "wof:placetype":"postalcode"
},
  "geometry": {"coordinates":[-2.05997185084917,53.3590274456778],"type":"Point"}
}