{
  "type": "Feature",
  "properties": {
    "date:inception_lower": "2019-10-01",
    "date:inception_upper": "2019-10-01",
    "iso:country": "GB",
    "wof:name": "NN1 1RT",
    "wof:placetype": "postalcode"
  },
  "geometry": {"coordinates":[-0.898334,52.236951],"type":"Point"}
}
