{
  "type": "Feature",
  "properties": {
    "iso:country":"GB",
    "wof:name":"NR8 6RT",
    "wof:placetype":"postalcode"
},
  "geometry": {"coordinates":[1.2261060267699,52.67389688149108],"type":"Point"}
}