{
  "type": "Feature",
  "properties": {
    "iso:country": "GB",
    "wof:name": "BB5 5QZ",
    "wof:placetype": "postalcode"
  },
  "geometry": {"coordinates":[-2.383888,53.777225],"type":"Point"}
}
