{
  "type": "Feature",
  "properties": {
    "iso:country":"GB",
    "wof:name":"BB5 5QZ",
    "wof:placetype":"postalcode"
},
  "geometry": {"coordinates":[-2.38388867380981,53.77726417233432],"type":"Point"}
}