{
  "type": "Feature",
  "properties": {
    "iso:country":"GB",
    "wof:name":"CW9 7LY",
    "wof:placetype":"postalcode"
},
  "geometry": {"coordinates":[-2.48794301022745,53.26590919067789],"type":"Point"}
}