{
  "type": "Feature",
  "properties": {
    "date:inception_lower": "1980-01-01",
    "date:inception_upper": "1980-01-01",
    "iso:country": "GB",
    "wof:name": "CW9 7LY",
    "wof:placetype": "postalcode"
  },
  "geometry": {"coordinates":[-2.487863,53.26562],"type":"Point"}
}
