{
  "type": "Feature",
  "properties": {
    "date:inception_lower":"1990-02-01",
    "date:inception_upper":"1990-02-28",
    "iso:country":"GB",
    "wof:name":"CV6 5TF",
    "wof:placetype":"postalcode"
},
  "geometry": {"coordinates":[-1.501163,52.432919],"type":"Point"}
}