{
  "type": "Feature",
  "properties": {
    "iso:country":"GB",
    "wof:name":"CV6 5TF",
    "wof:placetype":"postalcode"
},
  "geometry": {"coordinates":[-1.50116300308862,52.43291850827305],"type":"Point"}
}