{
  "type": "Feature",
  "properties": {
    "date:inception_lower": "2000-10-01",
    "date:inception_upper": "2000-10-01",
    "iso:country": "GB",
    "wof:name": "OX25 2RY",
    "wof:placetype": "postalcode"
  },
  "geometry": {"coordinates":[-1.121021,51.87301],"type":"Point"}
}
