{
  "type": "Feature",
  "properties": {
    "iso:country":"GB",
    "wof:name":"OX25 2RY",
    "wof:placetype":"postalcode"
},
  "geometry": {"coordinates":[-1.12102074074948,51.87301041227878],"type":"Point"}
}