{
  "type": "Feature",
  "properties": {
    "iso:country":"GB",
    "wof:name":"HX2 7TX",
    "wof:placetype":"postalcode"
},
  "geometry": {"coordinates":[-1.92713773055997,53.75305066100558],"type":"Point"}
}