{
  "type": "Feature",
  "properties": {
    "iso:country": "GB",
    "wof:name": "SA62 4FG",
    "wof:placetype": "postalcode"
  },
  "geometry": {"coordinates":[-4.948726,51.825669],"type":"Point"}
}
