{
  "type": "Feature",
  "properties": {
    "date:inception_lower": "2016-05-01",
    "date:inception_upper": "2016-05-01",
    "iso:country": "GB",
    "wof:name": "SA62 4FG",
    "wof:placetype": "postalcode"
  },
  "geometry": {"coordinates":[-4.948726,51.825669],"type":"Point"}
}
