{
  "type": "Feature",
  "properties": {
    "iso:country":"GB",
    "wof:name":"SW3 2AG",
    "wof:placetype":"postalcode"
},
  "geometry": {"coordinates":[-0.16809462629196,51.49787394292344],"type":"Point"}
}