{
  "type": "Feature",
  "properties": {
    "iso:country":"GB",
    "wof:name":"WV5 8AG",
    "wof:placetype":"postalcode"
},
  "geometry": {"coordinates":[-2.2027068936112,52.53751248411825],"type":"Point"}
}