{
  "type": "Feature",
  "properties": {
    "date:inception_lower": "2002-06-01",
    "date:inception_upper": "2002-06-01",
    "iso:country": "GB",
    "wof:name": "WV5 8AG",
    "wof:placetype": "postalcode"
  },
  "geometry": {"coordinates":[-2.202707,52.537512],"type":"Point"}
}
