{
  "type": "Feature",
  "properties": {
    "iso:country":"GB",
    "wof:name":"GU17 0ES",
    "wof:placetype":"postalcode"
},
  "geometry": {"coordinates":[-0.79509052017035,51.33850517100478],"type":"Point"}
}