{
  "type": "Feature",
  "properties": {
    "iso:country":"GB",
    "wof:name":"BS9 1HD",
    "wof:placetype":"postalcode"
},
  "geometry": {"coordinates":[-2.63226301545703,51.4797736990593],"type":"Point"}
}