{
  "type": "Feature",
  "properties": {
    "iso:country": "GB",
    "wof:name": "CH1 4NL",
    "wof:placetype": "postalcode"
  },
  "geometry": {"coordinates":[-2.917203,53.193468],"type":"Point"}
}
