{
  "type": "Feature",
  "properties": {
    "iso:country":"GB",
    "wof:name":"PO15 5PG",
    "wof:placetype":"postalcode"
},
  "geometry": {"coordinates":[-1.21914751827737,50.85699326061489],"type":"Point"}
}