{
  "type": "Feature",
  "properties": {
    "date:inception_lower": "1980-01-01",
    "date:inception_upper": "1980-01-01",
    "iso:country": "GB",
    "wof:name": "PO15 5PG",
    "wof:placetype": "postalcode"
  },
  "geometry": {"coordinates":[-1.219147,50.856993],"type":"Point"}
}
