{
  "type": "Feature",
  "properties": {
    "iso:country": "GB",
    "wof:name": "IV2 4NS",
    "wof:placetype": "postalcode"
  },
  "geometry": {"coordinates":[-4.221395,57.460416],"type":"Point"}
}
