{
  "type": "Feature",
  "properties": {
    "iso:country":"GB",
    "wof:name":"IV2 4NS",
    "wof:placetype":"postalcode"
},
  "geometry": {"coordinates":[-4.22161511091589,57.46018531320035],"type":"Point"}
}