{
  "type": "Feature",
  "properties": {
    "date:inception_lower": "1980-01-01",
    "date:inception_upper": "1980-01-01",
    "iso:country": "GB",
    "wof:name": "IV2 4NS",
    "wof:placetype": "postalcode"
  },
  "geometry": {"coordinates":[-4.221395,57.460425],"type":"Point"}
}
