{
  "type": "Feature",
  "properties": {
    "iso:country":"GB",
    "wof:name":"DN3 2EP",
    "wof:placetype":"postalcode"
},
  "geometry": {"coordinates":[-1.05162106049643,53.53973690665443],"type":"Point"}
}