{
  "type": "Feature",
  "properties": {
    "iso:country":"GB",
    "wof:name":"DN14 0SF",
    "wof:placetype":"postalcode"
},
  "geometry": {"coordinates":[-1.18855905091374,53.72115185374865],"type":"Point"}
}