{
  "type": "Feature",
  "properties": {
    "iso:country": "GB",
    "wof:name": "DN14 0SF",
    "wof:placetype": "postalcode"
  },
  "geometry": {"coordinates":[-1.188559,53.721152],"type":"Point"}
}
