{
  "type": "Feature",
  "properties": {
    "date:inception_lower":"1998-06-01",
    "date:inception_upper":"1998-06-30",
    "iso:country":"GB",
    "wof:name":"ST8 6UH",
    "wof:placetype":"postalcode"
},
  "geometry": {"coordinates":[-2.164585,53.111332],"type":"Point"}
}