{
  "type": "Feature",
  "properties": {
    "iso:country": "GB",
    "wof:name": "ST8 6UH",
    "wof:placetype": "postalcode"
  },
  "geometry": {"coordinates":[-2.164585,53.111332],"type":"Point"}
}
