{
  "type": "Feature",
  "properties": {
    "date:inception_lower":"1980-01-01",
    "date:inception_upper":"1980-01-31",
    "iso:country":"GB",
    "wof:name":"NR16 2NA",
    "wof:placetype":"postalcode"
},
  "geometry": {"coordinates":[0.926293,52.441286],"type":"Point"}
}