{
  "type": "Feature",
  "properties": {
    "iso:country":"GB",
    "wof:name":"NR16 2NA",
    "wof:placetype":"postalcode"
},
  "geometry": {"coordinates":[0.92629306118581,52.4412861394534],"type":"Point"}
}