{
  "type": "Feature",
  "properties": {
    "iso:country":"GB",
    "wof:name":"EX16 6UR",
    "wof:placetype":"postalcode"
},
  "geometry": {"coordinates":[-3.47968206229092,50.91570682632923],"type":"Point"}
}