{
  "type": "Feature",
  "properties": {
    "iso:country": "GB",
    "wof:name": "EX16 6UR",
    "wof:placetype": "postalcode"
  },
  "geometry": {"coordinates":[-3.479682,50.915707],"type":"Point"}
}
