{
  "type": "Feature",
  "properties": {
    "iso:country":"GB",
    "wof:name":"OX16 0JR",
    "wof:placetype":"postalcode"
},
  "geometry": {"coordinates":[-1.36374747829732,52.05751915502003],"type":"Point"}
}