{
  "type": "Feature",
  "properties": {
    "date:inception_lower": "1980-01-01",
    "date:inception_upper": "1980-01-01",
    "iso:country": "GB",
    "wof:name": "OX16 0JR",
    "wof:placetype": "postalcode"
  },
  "geometry": {"coordinates":[-1.363747,52.057519],"type":"Point"}
}
