{
  "type": "Feature",
  "properties": {
    "iso:country": "GB",
    "wof:name": "NN17 4DR",
    "wof:placetype": "postalcode"
  },
  "geometry": {"coordinates":[-0.692283,52.512232],"type":"Point"}
}
