{
  "type": "Feature",
  "properties": {
    "iso:country":"GB",
    "wof:name":"ST1 3RG",
    "wof:placetype":"postalcode"
},
  "geometry": {"coordinates":[-2.16453026901865,53.02258279227433],"type":"Point"}
}