{
  "type": "Feature",
  "properties": {
    "date:inception_lower": "2018-08-01",
    "date:inception_upper": "2018-08-01",
    "iso:country": "GB",
    "wof:name": "TN21 0FW",
    "wof:placetype": "postalcode"
  },
  "geometry": {"coordinates":[0.224841,50.967841],"type":"Point"}
}
