{
  "type": "Feature",
  "properties": {
    "date:inception_lower": "1994-05-01",
    "date:inception_upper": "1994-05-01",
    "iso:country": "GB",
    "wof:name": "M46 0NF",
    "wof:placetype": "postalcode"
  },
  "geometry": {"coordinates":[-2.499273,53.524924],"type":"Point"}
}
