{
  "type": "Feature",
  "properties": {
    "iso:country":"GB",
    "wof:name":"M46 0NF",
    "wof:placetype":"postalcode"
},
  "geometry": {"coordinates":[-2.4992728632681,53.52492450214338],"type":"Point"}
}