{
  "type": "Feature",
  "properties": {
    "date:inception_lower":"1980-01-01",
    "date:inception_upper":"1980-01-31",
    "iso:country":"GB",
    "wof:name":"RH15 0NS",
    "wof:placetype":"postalcode"
},
  "geometry": {"coordinates":[-0.111834,50.964609],"type":"Point"}
}