{
  "type": "Feature",
  "properties": {
    "iso:country": "GB",
    "wof:name": "TF11 8JU",
    "wof:placetype": "postalcode"
  },
  "geometry": {"coordinates":[-2.293074,52.695148],"type":"Point"}
}
