{
  "type": "Feature",
  "properties": {
    "iso:country":"GB",
    "wof:name":"TF11 8JU",
    "wof:placetype":"postalcode"
},
  "geometry": {"coordinates":[-2.29307390335474,52.69514763770407],"type":"Point"}
}