{
  "type": "Feature",
  "properties": {
    "iso:country": "GB",
    "wof:name": "GL50 4BW",
    "wof:placetype": "postalcode"
  },
  "geometry": {"coordinates":[-2.081857,51.907298],"type":"Point"}
}
