{
  "type": "Feature",
  "properties": {
    "date:inception_lower": "1987-04-01",
    "date:inception_upper": "1987-04-01",
    "iso:country": "GB",
    "wof:name": "BN13 3QJ",
    "wof:placetype": "postalcode"
  },
  "geometry": {"coordinates":[-0.412019,50.845664],"type":"Point"}
}
