{
  "type": "Feature",
  "properties": {
    "iso:country":"GB",
    "wof:name":"BN13 3QJ",
    "wof:placetype":"postalcode"
},
  "geometry": {"coordinates":[-0.41201899234177,50.84566434319616],"type":"Point"}
}