{
  "type": "Feature",
  "properties": {
    "iso:country":"GB",
    "wof:name":"BA21 3TA",
    "wof:placetype":"postalcode"
},
  "geometry": {"coordinates":[-2.66627181038835,50.94999944306873],"type":"Point"}
}