{
  "type": "Feature",
  "properties": {
    "iso:country":"GB",
    "wof:name":"IV3 8SF",
    "wof:placetype":"postalcode"
},
  "geometry": {"coordinates":[-4.25592526377721,57.48070968743409],"type":"Point"}
}