{
  "type": "Feature",
  "properties": {
    "iso:country":"GB",
    "wof:name":"NW6 4EN",
    "wof:placetype":"postalcode"
},
  "geometry": {"coordinates":[-0.17939004473508,51.54304807092481],"type":"Point"}
}