{
  "type": "Feature",
  "properties": {
    "iso:country": "GB",
    "wof:name": "PA23 7DL",
    "wof:placetype": "postalcode"
  },
  "geometry": {"coordinates":[-4.925395,55.947746],"type":"Point"}
}
