{
  "type": "Feature",
  "properties": {
    "iso:country":"GB",
    "wof:name":"SG18 8LL",
    "wof:placetype":"postalcode"
},
  "geometry": {"coordinates":[-0.25973135617603,52.0857087089359],"type":"Point"}
}