{
  "type": "Feature",
  "properties": {
    "iso:country": "GB",
    "wof:name": "M16 8FS",
    "wof:placetype": "postalcode"
  },
  "geometry": {"coordinates":[-2.254554,53.452907],"type":"Point"}
}
