{
  "type": "Feature",
  "properties": {
    "iso:country":"GB",
    "wof:name":"M16 8FS",
    "wof:placetype":"postalcode"
},
  "geometry": {"coordinates":[-2.25515617086036,53.45280782245739],"type":"Point"}
}