{
  "type": "Feature",
  "properties": {
    "date:inception_lower": "1990-09-01",
    "date:inception_upper": "1990-09-01",
    "iso:country": "GB",
    "wof:name": "G82 2JX",
    "wof:placetype": "postalcode"
  },
  "geometry": {"coordinates":[-4.553408,55.948211],"type":"Point"}
}
