{
  "type": "Feature",
  "properties": {
    "date:inception_lower": "1980-01-01",
    "date:inception_upper": "1980-01-01",
    "iso:country": "GB",
    "wof:name": "NN18 8BL",
    "wof:placetype": "postalcode"
  },
  "geometry": {"coordinates":[-0.696282,52.482096],"type":"Point"}
}
