{
  "type": "Feature",
  "properties": {
    "iso:country": "GB",
    "wof:name": "NN18 8BL",
    "wof:placetype": "postalcode"
  },
  "geometry": {"coordinates":[-0.696282,52.482096],"type":"Point"}
}
