{
  "type": "Feature",
  "properties": {
    "date:inception_lower": "1999-06-01",
    "date:inception_upper": "1999-06-01",
    "iso:country": "GB",
    "wof:name": "CH45 0JN",
    "wof:placetype": "postalcode"
  },
  "geometry": {"coordinates":[-3.057459,53.431751],"type":"Point"}
}
