{
  "type": "Feature",
  "properties": {
    "iso:country":"GB",
    "wof:name":"CH45 0JN",
    "wof:placetype":"postalcode"
},
  "geometry": {"coordinates":[-3.05745875047753,53.4317511791944],"type":"Point"}
}