{
  "type": "Feature",
  "properties": {
    "iso:country": "GB",
    "wof:name": "YO16 4HL",
    "wof:placetype": "postalcode"
  },
  "geometry": {"coordinates":[-0.205816,54.087993],"type":"Point"}
}
