{
  "type": "Feature",
  "properties": {
    "iso:country":"GB",
    "wof:name":"B29 5HU",
    "wof:placetype":"postalcode"
},
  "geometry": {"coordinates":[-1.96562030807628,52.44102169372005],"type":"Point"}
}