{
  "type": "Feature",
  "properties": {
    "iso:country": "GB",
    "wof:name": "B29 5HU",
    "wof:placetype": "postalcode"
  },
  "geometry": {"coordinates":[-1.96562,52.441022],"type":"Point"}
}
