{
  "type": "Feature",
  "properties": {
    "iso:country":"GB",
    "wof:name":"DL1 1LX",
    "wof:placetype":"postalcode"
},
  "geometry": {"coordinates":[-1.55307813341991,54.52684844164514],"type":"Point"}
}