{
  "type": "Feature",
  "properties": {
    "iso:country":"GB",
    "wof:name":"WV14 0UN",
    "wof:placetype":"postalcode"
},
  "geometry": {"coordinates":[-2.09054673643641,52.56243668251025],"type":"Point"}
}