{
  "type": "Feature",
  "properties": {
    "date:inception_lower": "1996-12-01",
    "date:inception_upper": "1996-12-01",
    "iso:country": "GB",
    "wof:name": "WV14 0UN",
    "wof:placetype": "postalcode"
  },
  "geometry": {"coordinates":[-2.090547,52.562437],"type":"Point"}
}
