{
  "type": "Feature",
  "properties": {
    "iso:country": "GB",
    "wof:name": "CF39 8HJ",
    "wof:placetype": "postalcode"
  },
  "geometry": {"coordinates":[-3.410041,51.564313],"type":"Point"}
}
