{
  "type": "Feature",
  "properties": {
    "date:inception_lower": "1980-01-01",
    "date:inception_upper": "1980-01-01",
    "iso:country": "GB",
    "wof:name": "CF39 8HJ",
    "wof:placetype": "postalcode"
  },
  "geometry": {"coordinates":[-3.410041,51.564313],"type":"Point"}
}
