{
  "type": "Feature",
  "properties": {
    "iso:country":"GB",
    "wof:name":"NG1 1NL",
    "wof:placetype":"postalcode"
},
  "geometry": {"coordinates":[-1.14448120777262,52.95363942209448],"type":"Point"}
}