{
  "type": "Feature",
  "properties": {
    "date:inception_lower": "2023-10-01",
    "date:inception_upper": "2023-10-01",
    "iso:country": "GB",
    "wof:name": "DA2 8DF",
    "wof:placetype": "postalcode"
  },
  "geometry": {"coordinates":[0.257183,51.437409],"type":"Point"}
}
