{
  "type": "Feature",
  "properties": {
    "iso:country":"GB",
    "wof:name":"DY5 3NQ",
    "wof:placetype":"postalcode"
},
  "geometry": {"coordinates":[-2.14129753890619,52.47686592463572],"type":"Point"}
}