{
  "type": "Feature",
  "properties": {
    "date:inception_lower": "2016-02-01",
    "date:inception_upper": "2016-02-01",
    "iso:country": "GB",
    "wof:name": "WA1 9UZ",
    "wof:placetype": "postalcode"
  },
  "geometry": {"coordinates":[-2.606686,53.389634],"type":"Point"}
}
