{
  "type": "Feature",
  "properties": {
    "iso:country": "GB",
    "wof:name": "TR14 7UR",
    "wof:placetype": "postalcode"
  },
  "geometry": {"coordinates":[-5.286506,50.212993],"type":"Point"}
}
