{
  "type": "Feature",
  "properties": {
    "iso:country":"GB",
    "wof:name":"TR14 7UR",
    "wof:placetype":"postalcode"
},
  "geometry": {"coordinates":[-5.28647004145441,50.21299380902704],"type":"Point"}
}