{
  "type": "Feature",
  "properties": {
    "date:inception_lower": "1984-02-01",
    "date:inception_upper": "1984-02-01",
    "iso:country": "GB",
    "wof:name": "TS11 8LF",
    "wof:placetype": "postalcode"
  },
  "geometry": {"coordinates":[-1.038841,54.582821],"type":"Point"}
}
