{
  "type": "Feature",
  "properties": {
    "iso:country":"GB",
    "wof:name":"CH7 4TR",
    "wof:placetype":"postalcode"
},
  "geometry": {"coordinates":[-3.09076553504759,53.12660971212771],"type":"Point"}
}