{
  "type": "Feature",
  "properties": {
    "iso:country": "GB",
    "wof:name": "GL18 1AR",
    "wof:placetype": "postalcode"
  },
  "geometry": {"coordinates":[-2.405303,51.930994],"type":"Point"}
}
