{
  "type": "Feature",
  "properties": {
    "iso:country":"GB",
    "wof:name":"NE25 8PH",
    "wof:placetype":"postalcode"
},
  "geometry": {"coordinates":[-1.44547021555881,55.03898195087873],"type":"Point"}
}