{
  "type": "Feature",
  "properties": {
    "date:inception_lower": "1980-01-01",
    "date:inception_upper": "1980-01-01",
    "iso:country": "GB",
    "wof:name": "NE25 8PH",
    "wof:placetype": "postalcode"
  },
  "geometry": {"coordinates":[-1.44547,55.038982],"type":"Point"}
}
