{
  "type": "Feature",
  "properties": {
    "iso:country":"GB",
    "wof:name":"WS3 3WG",
    "wof:placetype":"postalcode"
},
  "geometry": {"coordinates":[-2.00276356100436,52.62217263566192],"type":"Point"}
}