{
  "type": "Feature",
  "properties": {
    "iso:country":"GB",
    "wof:name":"WF12 8RE",
    "wof:placetype":"postalcode"
},
  "geometry": {"coordinates":[-1.59951038887146,53.6912851950589],"type":"Point"}
}