{
  "type": "Feature",
  "properties": {
    "date:inception_lower": "1980-01-01",
    "date:inception_upper": "1980-01-01",
    "iso:country": "GB",
    "wof:name": "WF12 8RE",
    "wof:placetype": "postalcode"
  },
  "geometry": {"coordinates":[-1.59951,53.691285],"type":"Point"}
}
