{
  "type": "Feature",
  "properties": {
    "iso:country":"GB",
    "wof:name":"NN10 9UJ",
    "wof:placetype":"postalcode"
},
  "geometry": {"coordinates":[-0.60402489159893,52.29342369042687],"type":"Point"}
}