{
  "type": "Feature",
  "properties": {
    "date:inception_lower": "1980-01-01",
    "date:inception_upper": "1980-01-01",
    "iso:country": "GB",
    "wof:name": "NN10 9UJ",
    "wof:placetype": "postalcode"
  },
  "geometry": {"coordinates":[-0.603657,52.293424],"type":"Point"}
}
