{
  "type": "Feature",
  "properties": {
    "iso:country":"GB",
    "wof:name":"PO6 1BP",
    "wof:placetype":"postalcode"
},
  "geometry": {"coordinates":[-1.02325199536515,50.8510042644284],"type":"Point"}
}