{
  "type": "Feature",
  "properties": {
    "iso:country": "GB",
    "wof:name": "PO6 1BP",
    "wof:placetype": "postalcode"
  },
  "geometry": {"coordinates":[-1.023252,50.851004],"type":"Point"}
}
