{
  "type": "Feature",
  "properties": {
    "date:inception_lower": "1980-01-01",
    "date:inception_upper": "1980-01-01",
    "iso:country": "GB",
    "wof:name": "KT16 8QB",
    "wof:placetype": "postalcode"
  },
  "geometry": {"coordinates":[-0.50051,51.406765],"type":"Point"}
}
