{
  "type": "Feature",
  "properties": {
    "iso:country":"GB",
    "wof:name":"NN29 7AG",
    "wof:placetype":"postalcode"
},
  "geometry": {"coordinates":[-0.64576068744351,52.28895562484599],"type":"Point"}
}