{
  "type": "Feature",
  "properties": {
    "iso:country":"GB",
    "wof:name":"NR11 6HQ",
    "wof:placetype":"postalcode"
},
  "geometry": {"coordinates":[1.25489903443635,52.79711946113172],"type":"Point"}
}