{
  "type": "Feature",
  "properties": {
    "iso:country": "GB",
    "wof:name": "SA44 6SH",
    "wof:placetype": "postalcode"
  },
  "geometry": {"coordinates":[-4.466127,52.158928],"type":"Point"}
}
