{
  "type": "Feature",
  "properties": {
    "iso:country":"GB",
    "wof:name":"CM9 4AZ",
    "wof:placetype":"postalcode"
},
  "geometry": {"coordinates":[0.69298413192934,51.74541607748968],"type":"Point"}
}