{
  "type": "Feature",
  "properties": {
    "iso:country": "GB",
    "wof:name": "KA7 4GX",
    "wof:placetype": "postalcode"
  },
  "geometry": {"coordinates":[-4.70658,55.422753],"type":"Point"}
}
