{
  "type": "Feature",
  "properties": {
    "date:inception_lower": "2009-08-01",
    "date:inception_upper": "2009-08-01",
    "iso:country": "GB",
    "wof:name": "KA7 4GX",
    "wof:placetype": "postalcode"
  },
  "geometry": {"coordinates":[-4.70658,55.422753],"type":"Point"}
}
