{
  "type": "Feature",
  "properties": {
    "iso:country":"GB",
    "wof:name":"KA7 4GX",
    "wof:placetype":"postalcode"
},
  "geometry": {"coordinates":[-4.70657976740044,55.42275309437703],"type":"Point"}
}