{
  "type": "Feature",
  "properties": {
    "date:inception_lower": "2022-04-01",
    "date:inception_upper": "2022-04-01",
    "iso:country": "GB",
    "wof:name": "S42 5WQ",
    "wof:placetype": "postalcode"
  },
  "geometry": {"coordinates":[-1.366608,53.187555],"type":"Point"}
}
