{
  "type": "Feature",
  "properties": {
    "iso:country":"GB",
    "wof:name":"CM11 2HU",
    "wof:placetype":"postalcode"
},
  "geometry": {"coordinates":[0.43175675987308,51.62252237294075],"type":"Point"}
}