{
  "type": "Feature",
  "properties": {
    "date:inception_lower": "2022-07-01",
    "date:inception_upper": "2022-07-01",
    "iso:country": "GB",
    "wof:name": "BB12 8FF",
    "wof:placetype": "postalcode"
  },
  "geometry": {"coordinates":[-2.323565,53.80016],"type":"Point"}
}
