{
  "type": "Feature",
  "properties": {
    "iso:country":"GB",
    "wof:name":"RG12 8UE",
    "wof:placetype":"postalcode"
},
  "geometry": {"coordinates":[-0.77327782544914,51.40269832226554],"type":"Point"}
}