{
  "type": "Feature",
  "properties": {
    "iso:country":"GB",
    "wof:name":"EX7 9QY",
    "wof:placetype":"postalcode"
},
  "geometry": {"coordinates":[-3.47987341094147,50.57925890099806],"type":"Point"}
}