{
  "type": "Feature",
  "properties": {
    "iso:country": "GB",
    "wof:name": "NP23 4SJ",
    "wof:placetype": "postalcode"
  },
  "geometry": {"coordinates":[-3.169119,51.802874],"type":"Point"}
}
