{
  "type": "Feature",
  "properties": {
    "iso:country":"GB",
    "wof:name":"NP23 4SJ",
    "wof:placetype":"postalcode"
},
  "geometry": {"coordinates":[-3.16911871088715,51.80287424421988],"type":"Point"}
}