{
  "type": "Feature",
  "properties": {
    "iso:country":"GB",
    "wof:name":"GU17 0BU",
    "wof:placetype":"postalcode"
},
  "geometry": {"coordinates":[-0.79538288285601,51.33447070210819],"type":"Point"}
}