{
  "type": "Feature",
  "properties": {
    "date:inception_lower": "1993-08-01",
    "date:inception_upper": "1993-08-01",
    "iso:country": "GB",
    "wof:name": "LL59 5UH",
    "wof:placetype": "postalcode"
  },
  "geometry": {"coordinates":[-4.152478,53.24587],"type":"Point"}
}
