{
  "type": "Feature",
  "properties": {
    "iso:country":"GB",
    "wof:name":"B31 3TR",
    "wof:placetype":"postalcode"
},
  "geometry": {"coordinates":[-1.96256088811312,52.40547413315642],"type":"Point"}
}