{
  "type": "Feature",
  "properties": {
    "iso:country": "GB",
    "wof:name": "NG20 9LW",
    "wof:placetype": "postalcode"
  },
  "geometry": {"coordinates":[-1.144107,53.242795],"type":"Point"}
}
