{
  "type": "Feature",
  "properties": {
    "iso:country": "GB",
    "wof:name": "CV21 4DR",
    "wof:placetype": "postalcode"
  },
  "geometry": {"coordinates":[-1.202975,52.357025],"type":"Point"}
}
