{
  "type": "Feature",
  "properties": {
    "iso:country":"GB",
    "wof:name":"AL7 4EZ",
    "wof:placetype":"postalcode"
},
  "geometry": {"coordinates":[-0.19787606835245,51.78471197659135],"type":"Point"}
}