{
  "type": "Feature",
  "properties": {
    "iso:country": "GB",
    "wof:name": "DT11 0QF",
    "wof:placetype": "postalcode"
  },
  "geometry": {"coordinates":[-2.225653,50.873674],"type":"Point"}
}
