{
  "type": "Feature",
  "properties": {
    "iso:country":"GB",
    "wof:name":"DT11 0QF",
    "wof:placetype":"postalcode"
},
  "geometry": {"coordinates":[-2.22565277397304,50.87367392671582],"type":"Point"}
}