{
  "type": "Feature",
  "properties": {
    "iso:country":"GB",
    "wof:name":"SE8 4JF",
    "wof:placetype":"postalcode"
},
  "geometry": {"coordinates":[-0.02108482713955,51.46955040268297],"type":"Point"}
}