{
  "type": "Feature",
  "properties": {
    "iso:country": "GB",
    "wof:name": "SE8 4JF",
    "wof:placetype": "postalcode"
  },
  "geometry": {"coordinates":[-0.021085,51.46955],"type":"Point"}
}
