{
  "type": "Feature",
  "properties": {
    "iso:country": "GB",
    "wof:name": "SA39 9HQ",
    "wof:placetype": "postalcode"
  },
  "geometry": {"coordinates":[-4.264062,51.997703],"type":"Point"}
}
