{
  "type": "Feature",
  "properties": {
    "iso:country":"GB",
    "wof:name":"DY3 1QU",
    "wof:placetype":"postalcode"
},
  "geometry": {"coordinates":[-2.12466052871927,52.54963103295302],"type":"Point"}
}