{
  "type": "Feature",
  "properties": {
    "date:inception_lower": "2014-10-01",
    "date:inception_upper": "2014-10-01",
    "iso:country": "GB",
    "wof:name": "G5 9QL",
    "wof:placetype": "postalcode"
  },
  "geometry": {"coordinates":[-4.25623,55.849683],"type":"Point"}
}
