{
  "type": "Feature",
  "properties": {
    "iso:country":"GB",
    "wof:name":"NN7 3PX",
    "wof:placetype":"postalcode"
},
  "geometry": {"coordinates":[-1.01118290385726,52.21053139172575],"type":"Point"}
}