{
  "type": "Feature",
  "properties": {
    "date:inception_lower": "2023-03-01",
    "date:inception_upper": "2023-03-01",
    "iso:country": "GB",
    "wof:name": "BH31 7BU",
    "wof:placetype": "postalcode"
  },
  "geometry": {"coordinates":[-1.885161,50.88604],"type":"Point"}
}
