{
  "type": "Feature",
  "properties": {
    "date:inception_lower":"2013-03-01",
    "date:inception_upper":"2013-03-31",
    "iso:country":"GB",
    "wof:name":"N1 9FJ",
    "wof:placetype":"postalcode"
},
  "geometry": {"coordinates":[-0.122138,51.531121],"type":"Point"}
}