{
  "type": "Feature",
  "properties": {
    "iso:country":"GB",
    "wof:name":"BB7 4TG",
    "wof:placetype":"postalcode"
},
  "geometry": {"coordinates":[-2.38960549171311,53.89790906125157],"type":"Point"}
}