{
  "type": "Feature",
  "properties": {
    "iso:country":"GB",
    "wof:name":"PR8 2NL",
    "wof:placetype":"postalcode"
},
  "geometry": {"coordinates":[-3.02630437569222,53.62648634161388],"type":"Point"}
}