{
  "type": "Feature",
  "properties": {
    "iso:country": "GB",
    "wof:name": "BA2 6FF",
    "wof:placetype": "postalcode"
  },
  "geometry": {"coordinates":[-2.343912,51.389041],"type":"Point"}
}
