{
  "type": "Feature",
  "properties": {
    "date:inception_lower": "1980-01-01",
    "date:inception_upper": "1980-01-01",
    "iso:country": "GB",
    "wof:name": "WF11 9NN",
    "wof:placetype": "postalcode"
  },
  "geometry": {"coordinates":[-1.25802,53.720703],"type":"Point"}
}
