{
  "type": "Feature",
  "properties": {
    "iso:country": "GB",
    "wof:name": "WF11 9NN",
    "wof:placetype": "postalcode"
  },
  "geometry": {"coordinates":[-1.25802,53.720703],"type":"Point"}
}
