{
  "type": "Feature",
  "properties": {
    "iso:country":"GB",
    "wof:name":"WF11 9NN",
    "wof:placetype":"postalcode"
},
  "geometry": {"coordinates":[-1.25802005177444,53.72070312032331],"type":"Point"}
}