{
  "type": "Feature",
  "properties": {
    "iso:country":"GB",
    "wof:name":"M40 1JE",
    "wof:placetype":"postalcode"
},
  "geometry": {"coordinates":[-2.18005900816016,53.49883082145745],"type":"Point"}
}