{
  "type": "Feature",
  "properties": {
    "iso:country":"GB",
    "wof:name":"NN7 2FB",
    "wof:placetype":"postalcode"
},
  "geometry": {"coordinates":[-0.85263169949952,52.14649328791383],"type":"Point"}
}