{
  "type": "Feature",
  "properties": {
    "iso:country": "GB",
    "wof:name": "NN7 2FB",
    "wof:placetype": "postalcode"
  },
  "geometry": {"coordinates":[-0.852632,52.146493],"type":"Point"}
}
