{
  "type": "Feature",
  "properties": {
    "date:inception_lower": "2008-05-01",
    "date:inception_upper": "2008-05-01",
    "iso:country": "GB",
    "wof:name": "NN7 2FB",
    "wof:placetype": "postalcode"
  },
  "geometry": {"coordinates":[-0.852632,52.146493],"type":"Point"}
}
