{
  "type": "Feature",
  "properties": {
    "iso:country": "GB",
    "wof:name": "BR4 0RQ",
    "wof:placetype": "postalcode"
  },
  "geometry": {"coordinates":[-0.020581,51.381674],"type":"Point"}
}
