{
  "type": "Feature",
  "properties": {
    "iso:country":"GB",
    "wof:name":"BR4 0RQ",
    "wof:placetype":"postalcode"
},
  "geometry": {"coordinates":[-0.02058087346387,51.38167356248479],"type":"Point"}
}