{
  "type": "Feature",
  "properties": {
    "date:inception_lower": "2017-01-01",
    "date:inception_upper": "2017-01-01",
    "iso:country": "GB",
    "wof:name": "DD11 4WH",
    "wof:placetype": "postalcode"
  },
  "geometry": {"coordinates":[-2.664255,56.635996],"type":"Point"}
}
