{
  "type": "Feature",
  "properties": {
    "iso:country": "GB",
    "wof:name": "TF7 5DR",
    "wof:placetype": "postalcode"
  },
  "geometry": {"coordinates":[-2.453921,52.63049],"type":"Point"}
}
