{
  "type": "Feature",
  "properties": {
    "iso:country":"GB",
    "wof:name":"TF7 5DR",
    "wof:placetype":"postalcode"
},
  "geometry": {"coordinates":[-2.45392135155892,52.63048968026298],"type":"Point"}
}