{
  "type": "Feature",
  "properties": {
    "iso:country": "GB",
    "wof:name": "OX7 5PJ",
    "wof:placetype": "postalcode"
  },
  "geometry": {"coordinates":[-1.547484,51.940903],"type":"Point"}
}
