{
  "type": "Feature",
  "properties": {
    "iso:country":"GB",
    "wof:name":"CT9 3UL",
    "wof:placetype":"postalcode"
},
  "geometry": {"coordinates":[1.41575322971407,51.37989502910576],"type":"Point"}
}