{
  "type": "Feature",
  "properties": {
    "iso:country": "GB",
    "wof:name": "LL16 3PP",
    "wof:placetype": "postalcode"
  },
  "geometry": {"coordinates":[-3.42377,53.183908],"type":"Point"}
}
