{
  "type": "Feature",
  "properties": {
    "iso:country":"GB",
    "wof:name":"BN22 7LD",
    "wof:placetype":"postalcode"
},
  "geometry": {"coordinates":[0.30705228816611,50.77758373555663],"type":"Point"}
}