{
  "type": "Feature",
  "properties": {
    "date:inception_lower": "2018-06-01",
    "date:inception_upper": "2018-06-01",
    "iso:country": "GB",
    "wof:name": "NP44 7AG",
    "wof:placetype": "postalcode"
  },
  "geometry": {"coordinates":[-3.04234,51.63735],"type":"Point"}
}
