{
  "type": "Feature",
  "properties": {
    "iso:country": "GB",
    "wof:name": "NP44 7AG",
    "wof:placetype": "postalcode"
  },
  "geometry": {"coordinates":[-3.04234,51.63735],"type":"Point"}
}
