{
  "type": "Feature",
  "properties": {
    "iso:country":"GB",
    "wof:name":"DG14 0XS",
    "wof:placetype":"postalcode"
},
  "geometry": {"coordinates":[-3.08124435219246,55.08782234050706],"type":"Point"}
}