{
  "type": "Feature",
  "properties": {
    "date:inception_lower":"1980-01-01",
    "date:inception_upper":"1980-01-31",
    "iso:country":"GB",
    "wof:name":"LN11 0SJ",
    "wof:placetype":"postalcode"
},
  "geometry": {"coordinates":[-0.094093,53.386637],"type":"Point"}
}