{
  "type": "Feature",
  "properties": {
    "iso:country":"GB",
    "wof:name":"LN11 0SJ",
    "wof:placetype":"postalcode"
},
  "geometry": {"coordinates":[-0.09409305265349,53.38663724534156],"type":"Point"}
}