{
  "type": "Feature",
  "properties": {
    "iso:country":"GB",
    "wof:name":"EN1 4UQ",
    "wof:placetype":"postalcode"
},
  "geometry": {"coordinates":[-0.06374801982686,51.66481596475533],"type":"Point"}
}