{
  "type": "Feature",
  "properties": {
    "iso:country":"GB",
    "wof:name":"BH9 3QE",
    "wof:placetype":"postalcode"
},
  "geometry": {"coordinates":[-1.85671343850964,50.75891640185584],"type":"Point"}
}