{
  "type": "Feature",
  "properties": {
    "iso:country": "GB",
    "wof:name": "GU6 8GW",
    "wof:placetype": "postalcode"
  },
  "geometry": {"coordinates":[-0.504624,51.138802],"type":"Point"}
}
