{
  "type": "Feature",
  "properties": {
    "iso:country": "GB",
    "wof:name": "G41 5DA",
    "wof:placetype": "postalcode"
  },
  "geometry": {"coordinates":[-4.303356,55.847484],"type":"Point"}
}
