{
  "type": "Feature",
  "properties": {
    "iso:country":"GB",
    "wof:name":"G41 5DA",
    "wof:placetype":"postalcode"
},
  "geometry": {"coordinates":[-4.30335563068546,55.84748381114135],"type":"Point"}
}