{
  "type": "Feature",
  "properties": {
    "date:inception_lower": "1980-01-01",
    "date:inception_upper": "1980-01-01",
    "iso:country": "GB",
    "wof:name": "G41 5DA",
    "wof:placetype": "postalcode"
  },
  "geometry": {"coordinates":[-4.303356,55.847484],"type":"Point"}
}
