{
  "type": "Feature",
  "properties": {
    "date:inception_lower": "1987-10-01",
    "date:inception_upper": "1987-10-01",
    "iso:country": "GB",
    "wof:name": "SA10 8DU",
    "wof:placetype": "postalcode"
  },
  "geometry": {"coordinates":[-3.803615,51.673547],"type":"Point"}
}
