{
  "type": "Feature",
  "properties": {
    "iso:country": "GB",
    "wof:name": "WN5 8RF",
    "wof:placetype": "postalcode"
  },
  "geometry": {"coordinates":[-2.703876,53.533144],"type":"Point"}
}
