{
  "type": "Feature",
  "properties": {
    "date:inception_lower": "2013-03-01",
    "date:inception_upper": "2013-03-01",
    "iso:country": "GB",
    "wof:name": "ML6 1AS",
    "wof:placetype": "postalcode"
  },
  "geometry": {"coordinates":[-3.979692,55.866653],"type":"Point"}
}
