{
  "type": "Feature",
  "properties": {
    "iso:country":"GB",
    "wof:name":"NG9 6EW",
    "wof:placetype":"postalcode"
},
  "geometry": {"coordinates":[-1.25904379221542,52.90519118484982],"type":"Point"}
}