{
  "type": "Feature",
  "properties": {
    "iso:country":"GB",
    "wof:name":"BS28 4AR",
    "wof:placetype":"postalcode"
},
  "geometry": {"coordinates":[-2.81897556398185,51.22543326768209],"type":"Point"}
}