{
  "type": "Feature",
  "properties": {
    "date:inception_lower": "1980-01-01",
    "date:inception_upper": "1980-01-01",
    "iso:country": "GB",
    "wof:name": "BS28 4AR",
    "wof:placetype": "postalcode"
  },
  "geometry": {"coordinates":[-2.818957,51.225608],"type":"Point"}
}
