{
  "type": "Feature",
  "properties": {
    "iso:country":"GB",
    "wof:name":"AB24 3LP",
    "wof:placetype":"postalcode"
},
  "geometry": {"coordinates":[-2.10862164660979,57.16233414249122],"type":"Point"}
}