{
  "type": "Feature",
  "properties": {
    "iso:country": "GB",
    "wof:name": "WD6 2JR",
    "wof:placetype": "postalcode"
  },
  "geometry": {"coordinates":[-0.257846,51.647839],"type":"Point"}
}
