{
  "type": "Feature",
  "properties": {
    "date:inception_lower": "1980-01-01",
    "date:inception_upper": "1980-01-01",
    "iso:country": "GB",
    "wof:name": "WD6 2JR",
    "wof:placetype": "postalcode"
  },
  "geometry": {"coordinates":[-0.257846,51.647839],"type":"Point"}
}
