{
  "type": "Feature",
  "properties": {
    "iso:country":"GB",
    "wof:name":"DN18 5HB",
    "wof:placetype":"postalcode"
},
  "geometry": {"coordinates":[-0.43686285962785,53.68608974888264],"type":"Point"}
}