{
  "type": "Feature",
  "properties": {
    "date:inception_lower": "1988-03-01",
    "date:inception_upper": "1988-03-01",
    "iso:country": "GB",
    "wof:name": "TA23 0EU",
    "wof:placetype": "postalcode"
  },
  "geometry": {"coordinates":[-3.325403,51.175656],"type":"Point"}
}
