{
  "type": "Feature",
  "properties": {
    "iso:country": "GB",
    "wof:name": "TA23 0EU",
    "wof:placetype": "postalcode"
  },
  "geometry": {"coordinates":[-3.325126,51.17548],"type":"Point"}
}
