{
  "type": "Feature",
  "properties": {
    "date:inception_lower": "1980-01-01",
    "date:inception_upper": "1980-01-01",
    "iso:country": "GB",
    "wof:name": "NR12 0DH",
    "wof:placetype": "postalcode"
  },
  "geometry": {"coordinates":[1.55329,52.797771],"type":"Point"}
}
