{
  "type": "Feature",
  "properties": {
    "iso:country":"GB",
    "wof:name":"NR12 0DH",
    "wof:placetype":"postalcode"
},
  "geometry": {"coordinates":[1.55326285106083,52.79768068569801],"type":"Point"}
}