{
  "type": "Feature",
  "properties": {
    "iso:country":"GB",
    "wof:name":"BD22 0PS",
    "wof:placetype":"postalcode"
},
  "geometry": {"coordinates":[-1.94772768585035,53.86742388131372],"type":"Point"}
}