{
  "type": "Feature",
  "properties": {
    "date:inception_lower":"1980-01-01",
    "date:inception_upper":"1980-01-31",
    "iso:country":"GB",
    "wof:name":"BD22 0PS",
    "wof:placetype":"postalcode"
},
  "geometry": {"coordinates":[-1.947728,53.867424],"type":"Point"}
}