{
  "type": "Feature",
  "properties": {
    "iso:country": "GB",
    "wof:name": "BD22 0PS",
    "wof:placetype": "postalcode"
  },
  "geometry": {"coordinates":[-1.947728,53.867424],"type":"Point"}
}
