{
  "type": "Feature",
  "properties": {
    "date:inception_lower":"2004-03-01",
    "date:inception_upper":"2004-03-31",
    "iso:country":"GB",
    "wof:name":"G15 7JJ",
    "wof:placetype":"postalcode"
},
  "geometry": {"coordinates":[-4.360044,55.916881],"type":"Point"}
}