{
  "type": "Feature",
  "properties": {
    "iso:country": "GB",
    "wof:name": "G15 7JJ",
    "wof:placetype": "postalcode"
  },
  "geometry": {"coordinates":[-4.360044,55.916881],"type":"Point"}
}
