{
  "type": "Feature",
  "properties": {
    "date:inception_lower": "1980-01-01",
    "date:inception_upper": "1980-01-01",
    "iso:country": "GB",
    "wof:name": "SO20 8DT",
    "wof:placetype": "postalcode"
  },
  "geometry": {"coordinates":[-1.59124,51.135824],"type":"Point"}
}
