{
  "type": "Feature",
  "properties": {
    "iso:country": "GB",
    "wof:name": "OX3 7HS",
    "wof:placetype": "postalcode"
  },
  "geometry": {"coordinates":[-1.206024,51.749141],"type":"Point"}
}
