{
  "type": "Feature",
  "properties": {
    "iso:country":"GB",
    "wof:name":"OX3 7HS",
    "wof:placetype":"postalcode"
},
  "geometry": {"coordinates":[-1.20602354337199,51.74914054447758],"type":"Point"}
}