{
  "type": "Feature",
  "properties": {
    "iso:country":"GB",
    "wof:name":"EX33 1BW",
    "wof:placetype":"postalcode"
},
  "geometry": {"coordinates":[-4.17049002526807,51.11192643170003],"type":"Point"}
}