{
  "type": "Feature",
  "properties": {
    "iso:country": "GB",
    "wof:name": "EX33 1BW",
    "wof:placetype": "postalcode"
  },
  "geometry": {"coordinates":[-4.17049,51.111926],"type":"Point"}
}
