{
  "type": "Feature",
  "properties": {
    "iso:country": "GB",
    "wof:name": "DT5 1ET",
    "wof:placetype": "postalcode"
  },
  "geometry": {"coordinates":[-2.44045,50.564808],"type":"Point"}
}
