{
  "type": "Feature",
  "properties": {
    "iso:country":"GB",
    "wof:name":"DT5 1ET",
    "wof:placetype":"postalcode"
},
  "geometry": {"coordinates":[-2.44044982020547,50.56480793534859],"type":"Point"}
}