{
  "type": "Feature",
  "properties": {
    "iso:country":"GB",
    "wof:name":"ME15 7RH",
    "wof:placetype":"postalcode"
},
  "geometry": {"coordinates":[0.53222245819849,51.26741157867077],"type":"Point"}
}