{
  "type": "Feature",
  "properties": {
    "iso:country": "GB",
    "wof:name": "N22 5LN",
    "wof:placetype": "postalcode"
  },
  "geometry": {"coordinates":[-0.098855,51.600258],"type":"Point"}
}
