{
  "type": "Feature",
  "properties": {
    "iso:country":"GB",
    "wof:name":"ML11 7ET",
    "wof:placetype":"postalcode"
},
  "geometry": {"coordinates":[-3.77679742010836,55.67344733508251],"type":"Point"}
}