{
  "type": "Feature",
  "properties": {
    "date:inception_lower":"1993-01-01",
    "date:inception_upper":"1993-01-31",
    "iso:country":"GB",
    "wof:name":"L21 4LP",
    "wof:placetype":"postalcode"
},
  "geometry": {"coordinates":[-3.014227,53.463192],"type":"Point"}
}