{
  "type": "Feature",
  "properties": {
    "iso:country":"GB",
    "wof:name":"DG4 6DT",
    "wof:placetype":"postalcode"
},
  "geometry": {"coordinates":[-3.92151400738655,55.36709480506679],"type":"Point"}
}