{
  "type": "Feature",
  "properties": {
    "date:inception_lower":"1992-01-01",
    "date:inception_upper":"1992-01-31",
    "iso:country":"GB",
    "wof:name":"PE33 0NN",
    "wof:placetype":"postalcode"
},
  "geometry": {"coordinates":[0.411926,52.70943],"type":"Point"}
}