{
  "type": "Feature",
  "properties": {
    "date:inception_lower": "1980-01-01",
    "date:inception_upper": "1980-01-01",
    "iso:country": "GB",
    "wof:name": "IP12 1PQ",
    "wof:placetype": "postalcode"
  },
  "geometry": {"coordinates":[1.325464,52.104932],"type":"Point"}
}
