{
  "type": "Feature",
  "properties": {
    "iso:country":"GB",
    "wof:name":"FY4 5HW",
    "wof:placetype":"postalcode"
},
  "geometry": {"coordinates":[-3.01158338643401,53.78651731078075],"type":"Point"}
}