{
  "type": "Feature",
  "properties": {
    "date:inception_lower": "2016-09-01",
    "date:inception_upper": "2016-09-01",
    "iso:country": "GB",
    "wof:name": "M12 5GS",
    "wof:placetype": "postalcode"
  },
  "geometry": {"coordinates":[-2.198606,53.467951],"type":"Point"}
}
