{
  "type": "Feature",
  "properties": {
    "date:inception_lower": "1992-05-01",
    "date:inception_upper": "1992-05-01",
    "iso:country": "GB",
    "wof:name": "EH52 6XL",
    "wof:placetype": "postalcode"
  },
  "geometry": {"coordinates":[-3.483182,55.937287],"type":"Point"}
}
