{
  "type": "Feature",
  "properties": {
    "iso:country":"GB",
    "wof:name":"CF39 8SB",
    "wof:placetype":"postalcode"
},
  "geometry": {"coordinates":[-3.46791872458248,51.59950830952304],"type":"Point"}
}