{
  "type": "Feature",
  "properties": {
    "iso:country":"GB",
    "wof:name":"DN15 5SB",
    "wof:placetype":"postalcode"
},
  "geometry": {"coordinates":[-0.65555575438797,53.58147904731694],"type":"Point"}
}