{
  "type": "Feature",
  "properties": {
    "iso:country": "GB",
    "wof:name": "WA12 8TA",
    "wof:placetype": "postalcode"
  },
  "geometry": {"coordinates":[-2.62623,53.440686],"type":"Point"}
}
