{
  "type": "Feature",
  "properties": {
    "date:inception_lower": "2019-08-01",
    "date:inception_upper": "2019-08-01",
    "iso:country": "GB",
    "wof:name": "NE28 9FQ",
    "wof:placetype": "postalcode"
  },
  "geometry": {"coordinates":[-1.544247,55.014597],"type":"Point"}
}
