{
  "type": "Feature",
  "properties": {
    "iso:country":"GB",
    "wof:name":"OL4 4JG",
    "wof:placetype":"postalcode"
},
  "geometry": {"coordinates":[-2.02751404304921,53.538889968513],"type":"Point"}
}