{
  "type": "Feature",
  "properties": {
    "iso:country": "GB",
    "wof:name": "OL4 4JG",
    "wof:placetype": "postalcode"
  },
  "geometry": {"coordinates":[-2.027514,53.53889],"type":"Point"}
}
