{
  "type": "Feature",
  "properties": {
    "iso:country":"GB",
    "wof:name":"L37 8RP",
    "wof:placetype":"postalcode"
},
  "geometry": {"coordinates":[-3.05543448135258,53.55404456077857],"type":"Point"}
}