{
  "type": "Feature",
  "properties": {
    "date:inception_lower":"2003-10-01",
    "date:inception_upper":"2003-10-31",
    "iso:country":"GB",
    "wof:name":"L37 8RP",
    "wof:placetype":"postalcode"
},
  "geometry": {"coordinates":[-3.055434,53.554045],"type":"Point"}
}