{
  "type": "Feature",
  "properties": {
    "iso:country": "GB",
    "wof:name": "GU47 0XE",
    "wof:placetype": "postalcode"
  },
  "geometry": {"coordinates":[-0.782959,51.344476],"type":"Point"}
}
