{
  "type": "Feature",
  "properties": {
    "iso:country":"GB",
    "wof:name":"BH15 2HT",
    "wof:placetype":"postalcode"
},
  "geometry": {"coordinates":[-1.97759439384519,50.71996493436416],"type":"Point"}
}