{
  "type": "Feature",
  "properties": {
    "iso:country":"GB",
    "wof:name":"SM5 2NH",
    "wof:placetype":"postalcode"
},
  "geometry": {"coordinates":[-0.15941326536259,51.37387404664079],"type":"Point"}
}