{
  "type": "Feature",
  "properties": {
    "date:inception_lower": "1990-08-01",
    "date:inception_upper": "1990-08-01",
    "iso:country": "GB",
    "wof:name": "AB37 9AA",
    "wof:placetype": "postalcode"
  },
  "geometry": {"coordinates":[-3.36399,57.406545],"type":"Point"}
}
