{
  "type": "Feature",
  "properties": {
    "date:inception_lower":"1994-05-01",
    "date:inception_upper":"1994-05-31",
    "iso:country":"GB",
    "wof:name":"TR27 6LA",
    "wof:placetype":"postalcode"
},
  "geometry": {"coordinates":[-5.436852,50.170628],"type":"Point"}
}