{
  "type": "Feature",
  "properties": {
    "date:inception_lower": "2023-04-01",
    "date:inception_upper": "2023-04-01",
    "iso:country": "GB",
    "wof:name": "S9 5HG",
    "wof:placetype": "postalcode"
  },
  "geometry": {"coordinates":[-1.409132,53.390552],"type":"Point"}
}
