{
  "type": "Feature",
  "properties": {
    "iso:country":"GB",
    "wof:name":"HA8 8AB",
    "wof:placetype":"postalcode"
},
  "geometry": {"coordinates":[-0.28901901558692,51.6191808471315],"type":"Point"}
}