{
  "type": "Feature",
  "properties": {
    "date:inception_lower": "1983-07-01",
    "date:inception_upper": "1983-07-01",
    "iso:country": "GB",
    "wof:name": "DE13 0HR",
    "wof:placetype": "postalcode"
  },
  "geometry": {"coordinates":[-1.630903,52.828702],"type":"Point"}
}
