{
  "type": "Feature",
  "properties": {
    "date:inception_lower": "1980-01-01",
    "date:inception_upper": "1980-01-01",
    "iso:country": "GB",
    "wof:name": "DN4 6LJ",
    "wof:placetype": "postalcode"
  },
  "geometry": {"coordinates":[-1.080836,53.511803],"type":"Point"}
}
