{
  "type": "Feature",
  "properties": {
    "iso:country": "GB",
    "wof:name": "DN4 6LJ",
    "wof:placetype": "postalcode"
  },
  "geometry": {"coordinates":[-1.080836,53.511803],"type":"Point"}
}
