{
  "type": "Feature",
  "properties": {
    "iso:country":"GB",
    "wof:name":"DN4 6LJ",
    "wof:placetype":"postalcode"
},
  "geometry": {"coordinates":[-1.08083616112669,53.51180335871008],"type":"Point"}
}