{
  "type": "Feature",
  "properties": {
    "iso:country":"GB",
    "wof:name":"MK6 2LW",
    "wof:placetype":"postalcode"
},
  "geometry": {"coordinates":[-0.75845194406362,52.0287905386734],"type":"Point"}
}