{
  "type": "Feature",
  "properties": {
    "date:inception_lower":"1992-01-01",
    "date:inception_upper":"1992-01-31",
    "iso:country":"GB",
    "wof:name":"MK6 2LW",
    "wof:placetype":"postalcode"
},
  "geometry": {"coordinates":[-0.758452,52.028791],"type":"Point"}
}