{
  "type": "Feature",
  "properties": {
    "date:inception_lower": "1986-07-01",
    "date:inception_upper": "1986-07-01",
    "iso:country": "GB",
    "wof:name": "WR14 1NP",
    "wof:placetype": "postalcode"
  },
  "geometry": {"coordinates":[-2.31676,52.1288],"type":"Point"}
}
