{
  "type": "Feature",
  "properties": {
    "iso:country":"GB",
    "wof:name":"WR14 1NP",
    "wof:placetype":"postalcode"
},
  "geometry": {"coordinates":[-2.31675986462243,52.1288004421256],"type":"Point"}
}