{
  "type": "Feature",
  "properties": {
    "iso:country":"GB",
    "wof:name":"RG40 3RU",
    "wof:placetype":"postalcode"
},
  "geometry": {"coordinates":[-0.85584196896747,51.36690874642446],"type":"Point"}
}