{
  "type": "Feature",
  "properties": {
    "iso:country": "GB",
    "wof:name": "RG40 3RU",
    "wof:placetype": "postalcode"
  },
  "geometry": {"coordinates":[-0.855842,51.366909],"type":"Point"}
}
