{
  "type": "Feature",
  "properties": {
    "iso:country":"GB",
    "wof:name":"TW7 6HJ",
    "wof:placetype":"postalcode"
},
  "geometry": {"coordinates":[-0.34531299742418,51.46649019070113],"type":"Point"}
}