{
  "type": "Feature",
  "properties": {
    "iso:country":"GB",
    "wof:name":"CF83 2BT",
    "wof:placetype":"postalcode"
},
  "geometry": {"coordinates":[-3.24560829362703,51.58841998982316],"type":"Point"}
}