{
  "type": "Feature",
  "properties": {
    "date:inception_lower": "1980-01-01",
    "date:inception_upper": "1980-01-01",
    "iso:country": "GB",
    "wof:name": "WF17 6DH",
    "wof:placetype": "postalcode"
  },
  "geometry": {"coordinates":[-1.611639,53.702938],"type":"Point"}
}
