{
  "type": "Feature",
  "properties": {
    "iso:country":"GB",
    "wof:name":"NP4 0TF",
    "wof:placetype":"postalcode"
},
  "geometry": {"coordinates":[-2.96391689093395,51.70637936964317],"type":"Point"}
}