{
  "type": "Feature",
  "properties": {
    "date:inception_lower":"1980-01-01",
    "date:inception_upper":"1980-01-31",
    "iso:country":"GB",
    "wof:name":"NP4 0TF",
    "wof:placetype":"postalcode"
},
  "geometry": {"coordinates":[-2.962221,51.706648],"type":"Point"}
}