{
  "type": "Feature",
  "properties": {
    "iso:country":"GB",
    "wof:name":"TD11 3PZ",
    "wof:placetype":"postalcode"
},
  "geometry": {"coordinates":[-2.26170368466788,55.80034736413288],"type":"Point"}
}