{
  "type": "Feature",
  "properties": {
    "iso:country":"GB",
    "wof:name":"EX1 1AN",
    "wof:placetype":"postalcode"
},
  "geometry": {"coordinates":[-3.53146131099865,50.72035488787046],"type":"Point"}
}