{
  "type": "Feature",
  "properties": {
    "date:inception_lower": "2012-12-01",
    "date:inception_upper": "2012-12-01",
    "iso:country": "GB",
    "wof:name": "EX1 1AN",
    "wof:placetype": "postalcode"
  },
  "geometry": {"coordinates":[-3.531461,50.720355],"type":"Point"}
}
