{
  "type": "Feature",
  "properties": {
    "iso:country":"GB",
    "wof:name":"B46 1PF",
    "wof:placetype":"postalcode"
},
  "geometry": {"coordinates":[-1.73074811296503,52.51737833417388],"type":"Point"}
}