{
  "type": "Feature",
  "properties": {
    "date:inception_lower":"1980-01-01",
    "date:inception_upper":"1980-01-31",
    "iso:country":"GB",
    "wof:name":"B46 1PF",
    "wof:placetype":"postalcode"
},
  "geometry": {"coordinates":[-1.730748,52.517378],"type":"Point"}
}