{
  "type": "Feature",
  "properties": {
    "date:inception_lower": "1980-01-01",
    "date:inception_upper": "1980-01-01",
    "iso:country": "GB",
    "wof:name": "NP7 0DG",
    "wof:placetype": "postalcode"
  },
  "geometry": {"coordinates":[-3.096755,51.827651],"type":"Point"}
}
