{
  "type": "Feature",
  "properties": {
    "iso:country":"GB",
    "wof:name":"NP7 0DG",
    "wof:placetype":"postalcode"
},
  "geometry": {"coordinates":[-3.09675488447138,51.82765052207213],"type":"Point"}
}