{
  "type": "Feature",
  "properties": {
    "date:inception_lower": "2001-12-01",
    "date:inception_upper": "2001-12-01",
    "iso:country": "GB",
    "wof:name": "CW3 0JS",
    "wof:placetype": "postalcode"
  },
  "geometry": {"coordinates":[-2.506584,52.990685],"type":"Point"}
}
