{
  "type": "Feature",
  "properties": {
    "iso:country":"GB",
    "wof:name":"CW3 0JS",
    "wof:placetype":"postalcode"
},
  "geometry": {"coordinates":[-2.5065839127055,52.99068504598647],"type":"Point"}
}