{
  "type": "Feature",
  "properties": {
    "iso:country":"GB",
    "wof:name":"SW20 0AP",
    "wof:placetype":"postalcode"
},
  "geometry": {"coordinates":[-0.25012706533842,51.41547872506663],"type":"Point"}
}