{
  "type": "Feature",
  "properties": {
    "iso:country":"GB",
    "wof:name":"BN1 5NH",
    "wof:placetype":"postalcode"
},
  "geometry": {"coordinates":[-0.15595323849999,50.84295087146494],"type":"Point"}
}