{
  "type": "Feature",
  "properties": {
    "iso:country": "GB",
    "wof:name": "CT14 8JR",
    "wof:placetype": "postalcode"
  },
  "geometry": {"coordinates":[1.358582,51.189817],"type":"Point"}
}
