{
  "type": "Feature",
  "properties": {
    "date:inception_lower": "1998-06-01",
    "date:inception_upper": "1998-06-01",
    "iso:country": "GB",
    "wof:name": "CT14 8JR",
    "wof:placetype": "postalcode"
  },
  "geometry": {"coordinates":[1.358653,51.189815],"type":"Point"}
}
