{
  "type": "Feature",
  "properties": {
    "iso:country":"GB",
    "wof:name":"CT14 8JR",
    "wof:placetype":"postalcode"
},
  "geometry": {"coordinates":[1.35855133358166,51.18980946505877],"type":"Point"}
}