{
  "type": "Feature",
  "properties": {
    "date:inception_lower": "2023-04-01",
    "date:inception_upper": "2023-04-01",
    "iso:country": "GB",
    "wof:name": "HU12 8FU",
    "wof:placetype": "postalcode"
  },
  "geometry": {"coordinates":[-0.199595,53.760448],"type":"Point"}
}
