{
  "type": "Feature",
  "properties": {
    "iso:country":"GB",
    "wof:name":"SS1 3QE",
    "wof:placetype":"postalcode"
},
  "geometry": {"coordinates":[0.7616919913544,51.54102317756477],"type":"Point"}
}