{
  "type": "Feature",
  "properties": {
    "iso:country":"GB",
    "wof:name":"RM3 9UB",
    "wof:placetype":"postalcode"
},
  "geometry": {"coordinates":[0.23887712456,51.60689961874106],"type":"Point"}
}