{
  "type": "Feature",
  "properties": {
    "iso:country":"GB",
    "wof:name":"RG30 2SB",
    "wof:placetype":"postalcode"
},
  "geometry": {"coordinates":[-0.99613586021293,51.44871704962368],"type":"Point"}
}