{
  "type": "Feature",
  "properties": {
    "iso:country":"GB",
    "wof:name":"S63 9GZ",
    "wof:placetype":"postalcode"
},
  "geometry": {"coordinates":[-1.30407815992834,53.53012842924459],"type":"Point"}
}