{
  "type": "Feature",
  "properties": {
    "iso:country":"GB",
    "wof:name":"SA1 9HX",
    "wof:placetype":"postalcode"
},
  "geometry": {"coordinates":[-3.92358605669921,51.64798385927068],"type":"Point"}
}