{
  "type": "Feature",
  "properties": {
    "iso:country":"GB",
    "wof:name":"CA10 1QX",
    "wof:placetype":"postalcode"
},
  "geometry": {"coordinates":[-2.60274754981883,54.66127943222547],"type":"Point"}
}