{
  "type": "Feature",
  "properties": {
    "iso:country": "GB",
    "wof:name": "CA10 1QX",
    "wof:placetype": "postalcode"
  },
  "geometry": {"coordinates":[-2.602747,54.661279],"type":"Point"}
}
