{
  "type": "Feature",
  "properties": {
    "iso:country":"GB",
    "wof:name":"WD3 3SB",
    "wof:placetype":"postalcode"
},
  "geometry": {"coordinates":[-0.43530745316473,51.65397956436978],"type":"Point"}
}