{
  "type": "Feature",
  "properties": {
    "iso:country": "GB",
    "wof:name": "LS23 6ST",
    "wof:placetype": "postalcode"
  },
  "geometry": {"coordinates":[-1.351374,53.894634],"type":"Point"}
}
