{
  "type": "Feature",
  "properties": {
    "date:inception_lower":"1990-07-01",
    "date:inception_upper":"1990-07-31",
    "iso:country":"GB",
    "wof:name":"LS23 6ST",
    "wof:placetype":"postalcode"
},
  "geometry": {"coordinates":[-1.351374,53.894634],"type":"Point"}
}