{
  "type": "Feature",
  "properties": {
    "iso:country":"GB",
    "wof:name":"LS23 6ST",
    "wof:placetype":"postalcode"
},
  "geometry": {"coordinates":[-1.35137436863042,53.89463431404432],"type":"Point"}
}