{
  "type": "Feature",
  "properties": {
    "date:inception_lower": "1980-01-01",
    "date:inception_upper": "1980-01-01",
    "iso:country": "GB",
    "wof:name": "SK14 5RX",
    "wof:placetype": "postalcode"
  },
  "geometry": {"coordinates":[-2.07435,53.436087],"type":"Point"}
}
