{
  "type": "Feature",
  "properties": {
    "iso:country": "GB",
    "wof:name": "EX34 9SB",
    "wof:placetype": "postalcode"
  },
  "geometry": {"coordinates":[-4.066249,51.204063],"type":"Point"}
}
