{
  "type": "Feature",
  "properties": {
    "iso:country": "GB",
    "wof:name": "S65 1NB",
    "wof:placetype": "postalcode"
  },
  "geometry": {"coordinates":[-1.338829,53.438525],"type":"Point"}
}
