{
  "type": "Feature",
  "properties": {
    "iso:country":"GB",
    "wof:name":"CT6 6AQ",
    "wof:placetype":"postalcode"
},
  "geometry": {"coordinates":[1.13368491062949,51.36474083003631],"type":"Point"}
}