{
  "type": "Feature",
  "properties": {
    "iso:country":"GB",
    "wof:name":"B43 7PT",
    "wof:placetype":"postalcode"
},
  "geometry": {"coordinates":[-1.91465448369265,52.55888995216993],"type":"Point"}
}