{
  "type": "Feature",
  "properties": {
    "iso:country":"GB",
    "wof:name":"SN13 0DL",
    "wof:placetype":"postalcode"
},
  "geometry": {"coordinates":[-2.18788540841003,51.43835794643581],"type":"Point"}
}