{
  "type": "Feature",
  "properties": {
    "date:inception_lower": "1980-01-01",
    "date:inception_upper": "1980-01-01",
    "iso:country": "GB",
    "wof:name": "SN13 0DL",
    "wof:placetype": "postalcode"
  },
  "geometry": {"coordinates":[-2.187924,51.438356],"type":"Point"}
}
