{
  "type": "Feature",
  "properties": {
    "iso:country": "GB",
    "wof:name": "SN3 5HE",
    "wof:placetype": "postalcode"
  },
  "geometry": {"coordinates":[-1.725271,51.554888],"type":"Point"}
}
