{
  "type": "Feature",
  "properties": {
    "iso:country":"GB",
    "wof:name":"IP17 1RX",
    "wof:placetype":"postalcode"
},
  "geometry": {"coordinates":[1.49870496066854,52.19296379139909],"type":"Point"}
}