{
  "type": "Feature",
  "properties": {
    "iso:country":"GB",
    "wof:name":"DE23 8UU",
    "wof:placetype":"postalcode"
},
  "geometry": {"coordinates":[-1.47587463555905,52.89823672763286],"type":"Point"}
}