{
  "type": "Feature",
  "properties": {
    "iso:country": "GB",
    "wof:name": "DE23 8UU",
    "wof:placetype": "postalcode"
  },
  "geometry": {"coordinates":[-1.475875,52.898237],"type":"Point"}
}
