{
  "type": "Feature",
  "properties": {
    "iso:country": "GB",
    "wof:name": "G2 7DA",
    "wof:placetype": "postalcode"
  },
  "geometry": {"coordinates":[-4.262881,55.860759],"type":"Point"}
}
