{
  "type": "Feature",
  "properties": {
    "iso:country":"GB",
    "wof:name":"HP15 6UH",
    "wof:placetype":"postalcode"
},
  "geometry": {"coordinates":[-0.70230148004416,51.66790628057264],"type":"Point"}
}