{
  "type": "Feature",
  "properties": {
    "iso:country":"GB",
    "wof:name":"PE1 5DL",
    "wof:placetype":"postalcode"
},
  "geometry": {"coordinates":[-0.23487041295115,52.57209018411023],"type":"Point"}
}