{
  "type": "Feature",
  "properties": {
    "iso:country": "GB",
    "wof:name": "BS28 4XN",
    "wof:placetype": "postalcode"
  },
  "geometry": {"coordinates":[-2.804155,51.214835],"type":"Point"}
}
