{
  "type": "Feature",
  "properties": {
    "date:inception_lower":"1980-01-01",
    "date:inception_upper":"1980-01-31",
    "iso:country":"GB",
    "wof:name":"NE13 8DH",
    "wof:placetype":"postalcode"
},
  "geometry": {"coordinates":[-1.677089,55.030495],"type":"Point"}
}