{
  "type": "Feature",
  "properties": {
    "iso:country":"GB",
    "wof:name":"NE13 8DH",
    "wof:placetype":"postalcode"
},
  "geometry": {"coordinates":[-1.67707536277355,55.03048852143802],"type":"Point"}
}