{
  "type": "Feature",
  "properties": {
    "iso:country": "GB",
    "wof:name": "NE13 8DH",
    "wof:placetype": "postalcode"
  },
  "geometry": {"coordinates":[-1.677089,55.030495],"type":"Point"}
}
