{
  "type": "Feature",
  "properties": {
    "iso:country":"GB",
    "wof:name":"WS12 4GG",
    "wof:placetype":"postalcode"
},
  "geometry": {"coordinates":[-2.00374705998943,52.71579101937768],"type":"Point"}
}