{
  "type": "Feature",
  "properties": {
    "iso:country":"GB",
    "wof:name":"PE12 8EZ",
    "wof:placetype":"postalcode"
},
  "geometry": {"coordinates":[0.01701151731586,52.86142772640139],"type":"Point"}
}