{
  "type": "Feature",
  "properties": {
    "iso:country": "GB",
    "wof:name": "L5 9RF",
    "wof:placetype": "postalcode"
  },
  "geometry": {"coordinates":[-2.992439,53.422224],"type":"Point"}
}
