{
  "type": "Feature",
  "properties": {
    "iso:country": "GB",
    "wof:name": "SK8 4PQ",
    "wof:placetype": "postalcode"
  },
  "geometry": {"coordinates":[-2.229794,53.390722],"type":"Point"}
}
