{
  "type": "Feature",
  "properties": {
    "iso:country": "GB",
    "wof:name": "EN2 8DP",
    "wof:placetype": "postalcode"
  },
  "geometry": {"coordinates":[-0.094006,51.655347],"type":"Point"}
}
