{
  "type": "Feature",
  "properties": {
    "iso:country":"GB",
    "wof:name":"SP7 9EN",
    "wof:placetype":"postalcode"
},
  "geometry": {"coordinates":[-2.11067479493741,51.02272567973326],"type":"Point"}
}