{
  "type": "Feature",
  "properties": {
    "date:inception_lower": "1980-01-01",
    "date:inception_upper": "1980-01-01",
    "iso:country": "GB",
    "wof:name": "SY11 2QY",
    "wof:placetype": "postalcode"
  },
  "geometry": {"coordinates":[-3.045999,52.853863],"type":"Point"}
}
