{
  "type": "Feature",
  "properties": {
    "date:inception_lower": "2004-08-01",
    "date:inception_upper": "2004-08-01",
    "iso:country": "GB",
    "wof:name": "S74 8DP",
    "wof:placetype": "postalcode"
  },
  "geometry": {"coordinates":[-1.43062,53.501989],"type":"Point"}
}
