{
  "type": "Feature",
  "properties": {
    "iso:country":"GB",
    "wof:name":"S74 8DP",
    "wof:placetype":"postalcode"
},
  "geometry": {"coordinates":[-1.43062026897613,53.50198947586246],"type":"Point"}
}