{
  "type": "Feature",
  "properties": {
    "iso:country":"GB",
    "wof:name":"LS14 5LX",
    "wof:placetype":"postalcode"
},
  "geometry": {"coordinates":[-1.44231535763084,53.81997831120123],"type":"Point"}
}