{
  "type": "Feature",
  "properties": {
    "iso:country":"GB",
    "wof:name":"HD4 5JJ",
    "wof:placetype":"postalcode"
},
  "geometry": {"coordinates":[-1.81131801266173,53.62759405137442],"type":"Point"}
}