{
  "type": "Feature",
  "properties": {
    "iso:country": "GB",
    "wof:name": "HD4 5JJ",
    "wof:placetype": "postalcode"
  },
  "geometry": {"coordinates":[-1.811318,53.627594],"type":"Point"}
}
