{
  "type": "Feature",
  "properties": {
    "date:inception_lower":"1980-01-01",
    "date:inception_upper":"1980-01-31",
    "iso:country":"GB",
    "wof:name":"SE14 5TE",
    "wof:placetype":"postalcode"
},
  "geometry": {"coordinates":[-0.047876,51.473363],"type":"Point"}
}