{
  "type": "Feature",
  "properties": {
    "iso:country":"GB",
    "wof:name":"SE14 5TE",
    "wof:placetype":"postalcode"
},
  "geometry": {"coordinates":[-0.04787599246331,51.47336280958379],"type":"Point"}
}