{
  "type": "Feature",
  "properties": {
    "iso:country":"GB",
    "wof:name":"B92 9DP",
    "wof:placetype":"postalcode"
},
  "geometry": {"coordinates":[-1.76790714284972,52.44862972483835],"type":"Point"}
}