{
  "type": "Feature",
  "properties": {
    "iso:country": "GB",
    "wof:name": "PO19 7BT",
    "wof:placetype": "postalcode"
  },
  "geometry": {"coordinates":[-0.767877,50.837185],"type":"Point"}
}
