{
  "type": "Feature",
  "properties": {
    "iso:country":"GB",
    "wof:name":"ST4 3AP",
    "wof:placetype":"postalcode"
},
  "geometry": {"coordinates":[-2.16203447308293,52.99711094640553],"type":"Point"}
}