{
  "type": "Feature",
  "properties": {
    "iso:country":"GB",
    "wof:name":"DL13 5DQ",
    "wof:placetype":"postalcode"
},
  "geometry": {"coordinates":[-1.80488927429768,54.61317847889163],"type":"Point"}
}