{
  "type": "Feature",
  "properties": {
    "iso:country": "GB",
    "wof:name": "DL13 5DQ",
    "wof:placetype": "postalcode"
  },
  "geometry": {"coordinates":[-1.804898,54.613187],"type":"Point"}
}
