{
  "type": "Feature",
  "properties": {
    "iso:country":"GB",
    "wof:name":"LL24 0LL",
    "wof:placetype":"postalcode"
},
  "geometry": {"coordinates":[-3.65394741944131,53.04318800223341],"type":"Point"}
}