{
  "type": "Feature",
  "properties": {
    "date:inception_lower": "1980-01-01",
    "date:inception_upper": "1980-01-01",
    "iso:country": "GB",
    "wof:name": "LL24 0LL",
    "wof:placetype": "postalcode"
  },
  "geometry": {"coordinates":[-3.653947,53.043188],"type":"Point"}
}
