{
  "type": "Feature",
  "properties": {
    "iso:country": "GB",
    "wof:name": "LL24 0LL",
    "wof:placetype": "postalcode"
  },
  "geometry": {"coordinates":[-3.653947,53.043188],"type":"Point"}
}
