{
  "type": "Feature",
  "properties": {
    "iso:country":"GB",
    "wof:name":"SK16 5LL",
    "wof:placetype":"postalcode"
},
  "geometry": {"coordinates":[-2.08537098440228,53.4820109526706],"type":"Point"}
}