{
  "type": "Feature",
  "properties": {
    "iso:country":"GB",
    "wof:name":"CH63 3EN",
    "wof:placetype":"postalcode"
},
  "geometry": {"coordinates":[-3.007012868751,53.34161432128288],"type":"Point"}
}