{
  "type": "Feature",
  "properties": {
    "iso:country":"GB",
    "wof:name":"HA5 5EY",
    "wof:placetype":"postalcode"
},
  "geometry": {"coordinates":[-0.37212694916961,51.57988902756313],"type":"Point"}
}