{
  "type": "Feature",
  "properties": {
    "date:inception_lower": "1980-01-01",
    "date:inception_upper": "1980-01-01",
    "iso:country": "GB",
    "wof:name": "HA5 5EY",
    "wof:placetype": "postalcode"
  },
  "geometry": {"coordinates":[-0.372022,51.5798],"type":"Point"}
}
