{
  "type": "Feature",
  "properties": {
    "iso:country":"GB",
    "wof:name":"SG5 3TE",
    "wof:placetype":"postalcode"
},
  "geometry": {"coordinates":[-0.27755271950563,51.97113833189277],"type":"Point"}
}