{
  "type": "Feature",
  "properties": {
    "iso:country": "GB",
    "wof:name": "SG5 3TE",
    "wof:placetype": "postalcode"
  },
  "geometry": {"coordinates":[-0.277553,51.971138],"type":"Point"}
}
