{
  "type": "Feature",
  "properties": {
    "iso:country": "GB",
    "wof:name": "HP19 0UD",
    "wof:placetype": "postalcode"
  },
  "geometry": {"coordinates":[-0.801874,51.831072],"type":"Point"}
}
