{
  "type": "Feature",
  "properties": {
    "date:inception_lower": "2000-06-01",
    "date:inception_upper": "2000-06-01",
    "iso:country": "GB",
    "wof:name": "HP19 0UD",
    "wof:placetype": "postalcode"
  },
  "geometry": {"coordinates":[-0.801874,51.831072],"type":"Point"}
}
