{
  "type": "Feature",
  "properties": {
    "iso:country":"GB",
    "wof:name":"OX16 4QJ",
    "wof:placetype":"postalcode"
},
  "geometry": {"coordinates":[-1.32645888951799,52.06298519671738],"type":"Point"}
}