{
  "type": "Feature",
  "properties": {
    "date:inception_lower":"1980-01-01",
    "date:inception_upper":"1980-01-31",
    "iso:country":"GB",
    "wof:name":"LE17 6DX",
    "wof:placetype":"postalcode"
},
  "geometry": {"coordinates":[-1.10296,52.433374],"type":"Point"}
}