{
  "type": "Feature",
  "properties": {
    "iso:country":"GB",
    "wof:name":"LE17 6DX",
    "wof:placetype":"postalcode"
},
  "geometry": {"coordinates":[-1.10296011347192,52.43337422309973],"type":"Point"}
}