{
  "type": "Feature",
  "properties": {
    "date:inception_lower": "2018-10-01",
    "date:inception_upper": "2018-10-01",
    "iso:country": "GB",
    "wof:name": "CM22 6YE",
    "wof:placetype": "postalcode"
  },
  "geometry": {"coordinates":[0.224385,51.914291],"type":"Point"}
}
