{
  "type": "Feature",
  "properties": {
    "date:inception_lower": "1980-01-01",
    "date:inception_upper": "1980-01-01",
    "iso:country": "GB",
    "wof:name": "CF48 2TW",
    "wof:placetype": "postalcode"
  },
  "geometry": {"coordinates":[-3.382978,51.775637],"type":"Point"}
}
