{
  "type": "Feature",
  "properties": {
    "iso:country":"GB",
    "wof:name":"CF48 2TW",
    "wof:placetype":"postalcode"
},
  "geometry": {"coordinates":[-3.38297795665306,51.77563696344237],"type":"Point"}
}