{
  "type": "Feature",
  "properties": {
    "date:inception_lower": "2015-09-01",
    "date:inception_upper": "2015-09-01",
    "iso:country": "GB",
    "wof:name": "M35 9RG",
    "wof:placetype": "postalcode"
  },
  "geometry": {"coordinates":[-2.152475,53.508386],"type":"Point"}
}
