{
  "type": "Feature",
  "properties": {
    "iso:country":"GB",
    "wof:name":"M35 9RG",
    "wof:placetype":"postalcode"
},
  "geometry": {"coordinates":[-2.15208492249742,53.50852329724029],"type":"Point"}
}