{
  "type": "Feature",
  "properties": {
    "iso:country":"GB",
    "wof:name":"DE7 6ND",
    "wof:placetype":"postalcode"
},
  "geometry": {"coordinates":[-1.35788087815627,52.97097548767866],"type":"Point"}
}