{
  "type": "Feature",
  "properties": {
    "iso:country": "GB",
    "wof:name": "KY11 2BA",
    "wof:placetype": "postalcode"
  },
  "geometry": {"coordinates":[-3.436836,56.028952],"type":"Point"}
}
