{
  "type": "Feature",
  "properties": {
    "iso:country":"GB",
    "wof:name":"KY11 2BA",
    "wof:placetype":"postalcode"
},
  "geometry": {"coordinates":[-3.43683654058826,56.02895212565399],"type":"Point"}
}