{
  "type": "Feature",
  "properties": {
    "iso:country": "GB",
    "wof:name": "BD10 8DH",
    "wof:placetype": "postalcode"
  },
  "geometry": {"coordinates":[-1.729809,53.827801],"type":"Point"}
}
