{
  "type": "Feature",
  "properties": {
    "iso:country":"GB",
    "wof:name":"BD10 8DH",
    "wof:placetype":"postalcode"
},
  "geometry": {"coordinates":[-1.72980891311512,53.82780053351301],"type":"Point"}
}