{
  "type": "Feature",
  "properties": {
    "iso:country": "GB",
    "wof:name": "DE11 7HR",
    "wof:placetype": "postalcode"
  },
  "geometry": {"coordinates":[-1.518711,52.781914],"type":"Point"}
}
