{
  "type": "Feature",
  "properties": {
    "iso:country":"GB",
    "wof:name":"CH6 6BD",
    "wof:placetype":"postalcode"
},
  "geometry": {"coordinates":[-3.16884271588644,53.26487162085299],"type":"Point"}
}