{
  "type": "Feature",
  "properties": {
    "date:inception_lower":"2003-07-01",
    "date:inception_upper":"2003-07-31",
    "iso:country":"GB",
    "wof:name":"CH6 6BD",
    "wof:placetype":"postalcode"
},
  "geometry": {"coordinates":[-3.168843,53.264872],"type":"Point"}
}