{
  "type": "Feature",
  "properties": {
    "iso:country":"GB",
    "wof:name":"LE9 6SW",
    "wof:placetype":"postalcode"
},
  "geometry": {"coordinates":[-1.21129546281722,52.52623251661007],"type":"Point"}
}