{
  "type": "Feature",
  "properties": {
    "iso:country":"GB",
    "wof:name":"KA2 0BT",
    "wof:placetype":"postalcode"
},
  "geometry": {"coordinates":[-4.55966786812043,55.59802220227599],"type":"Point"}
}