{
  "type": "Feature",
  "properties": {
    "iso:country":"GB",
    "wof:name":"CH64 2UP",
    "wof:placetype":"postalcode"
},
  "geometry": {"coordinates":[-3.00204715445231,53.28804527008744],"type":"Point"}
}