{
  "type": "Feature",
  "properties": {
    "date:inception_lower":"1980-01-01",
    "date:inception_upper":"1980-01-31",
    "iso:country":"GB",
    "wof:name":"CB4 2HP",
    "wof:placetype":"postalcode"
},
  "geometry": {"coordinates":[0.122041,52.227686],"type":"Point"}
}