{
  "type": "Feature",
  "properties": {
    "iso:country":"GB",
    "wof:name":"CB4 2HP",
    "wof:placetype":"postalcode"
},
  "geometry": {"coordinates":[0.12204128294391,52.22768587868971],"type":"Point"}
}