{
  "type": "Feature",
  "properties": {
    "iso:country":"GB",
    "wof:name":"ST16 1WE",
    "wof:placetype":"postalcode"
},
  "geometry": {"coordinates":[-2.12529669320206,52.83399963856799],"type":"Point"}
}