{
  "type": "Feature",
  "properties": {
    "date:inception_lower": "2014-11-01",
    "date:inception_upper": "2014-11-01",
    "iso:country": "GB",
    "wof:name": "ST16 1WE",
    "wof:placetype": "postalcode"
  },
  "geometry": {"coordinates":[-2.125297,52.834],"type":"Point"}
}
