{
  "type": "Feature",
  "properties": {
    "iso:country":"GB",
    "wof:name":"CM7 9AX",
    "wof:placetype":"postalcode"
},
  "geometry": {"coordinates":[0.55824259973427,51.88692116950461],"type":"Point"}
}