{
  "type": "Feature",
  "properties": {
    "iso:country": "GB",
    "wof:name": "CM7 9AX",
    "wof:placetype": "postalcode"
  },
  "geometry": {"coordinates":[0.558243,51.886921],"type":"Point"}
}
