{
  "type": "Feature",
  "properties": {
    "date:inception_lower":"1997-06-01",
    "date:inception_upper":"1997-06-30",
    "iso:country":"GB",
    "wof:name":"CM7 9AX",
    "wof:placetype":"postalcode"
},
  "geometry": {"coordinates":[0.558243,51.886921],"type":"Point"}
}