{
  "type": "Feature",
  "properties": {
    "iso:country":"GB",
    "wof:name":"PR7 7HS",
    "wof:placetype":"postalcode"
},
  "geometry": {"coordinates":[-2.65822116063861,53.68077812243601],"type":"Point"}
}