{
  "type": "Feature",
  "properties": {
    "date:inception_lower": "2011-10-01",
    "date:inception_upper": "2011-10-01",
    "iso:country": "GB",
    "wof:name": "PR7 7HS",
    "wof:placetype": "postalcode"
  },
  "geometry": {"coordinates":[-2.658221,53.680778],"type":"Point"}
}
