{
  "type": "Feature",
  "properties": {
    "iso:country": "GB",
    "wof:name": "PR7 7HS",
    "wof:placetype": "postalcode"
  },
  "geometry": {"coordinates":[-2.658221,53.680778],"type":"Point"}
}
