{
  "type": "Feature",
  "properties": {
    "iso:country":"GB",
    "wof:name":"RG9 6BX",
    "wof:placetype":"postalcode"
},
  "geometry": {"coordinates":[-0.95182799213989,51.56112244512902],"type":"Point"}
}