{
  "type": "Feature",
  "properties": {
    "iso:country":"GB",
    "wof:name":"RH12 3JG",
    "wof:placetype":"postalcode"
},
  "geometry": {"coordinates":[-0.45305078115376,51.08210099012686],"type":"Point"}
}