{
  "type": "Feature",
  "properties": {
    "iso:country": "GB",
    "wof:name": "ST18 0UY",
    "wof:placetype": "postalcode"
  },
  "geometry": {"coordinates":[-1.989577,52.794953],"type":"Point"}
}
