{
  "type": "Feature",
  "properties": {
    "iso:country":"GB",
    "wof:name":"ST18 0UY",
    "wof:placetype":"postalcode"
},
  "geometry": {"coordinates":[-1.98957664453266,52.79495251629341],"type":"Point"}
}