{
  "type": "Feature",
  "properties": {
    "date:inception_lower": "1980-01-01",
    "date:inception_upper": "1980-01-01",
    "iso:country": "GB",
    "wof:name": "ST18 0UY",
    "wof:placetype": "postalcode"
  },
  "geometry": {"coordinates":[-1.989577,52.794953],"type":"Point"}
}
