{
  "type": "Feature",
  "properties": {
    "date:inception_lower": "1980-01-01",
    "date:inception_upper": "1980-01-01",
    "iso:country": "GB",
    "wof:name": "BB1 1LP",
    "wof:placetype": "postalcode"
  },
  "geometry": {"coordinates":[-2.470563,53.745937],"type":"Point"}
}
