{
  "type": "Feature",
  "properties": {
    "iso:country": "GB",
    "wof:name": "BB1 1LP",
    "wof:placetype": "postalcode"
  },
  "geometry": {"coordinates":[-2.470563,53.745937],"type":"Point"}
}
