{
  "type": "Feature",
  "properties": {
    "iso:country":"GB",
    "wof:name":"BB1 1LP",
    "wof:placetype":"postalcode"
},
  "geometry": {"coordinates":[-2.47056344825008,53.7459372179888],"type":"Point"}
}