{
  "type": "Feature",
  "properties": {
    "iso:country":"GB",
    "wof:name":"TQ12 1EG",
    "wof:placetype":"postalcode"
},
  "geometry": {"coordinates":[-3.60928800525939,50.52308579983512],"type":"Point"}
}