{
  "type": "Feature",
  "properties": {
    "iso:country":"GB",
    "wof:name":"GU11 2EF",
    "wof:placetype":"postalcode"
},
  "geometry": {"coordinates":[-0.73791501249359,51.27136060919073],"type":"Point"}
}