{
  "type": "Feature",
  "properties": {
    "date:inception_lower":"1981-06-01",
    "date:inception_upper":"1981-06-30",
    "iso:country":"GB",
    "wof:name":"NE28 8QP",
    "wof:placetype":"postalcode"
},
  "geometry": {"coordinates":[-1.537099,54.993086],"type":"Point"}
}