{
  "type": "Feature",
  "properties": {
    "iso:country": "GB",
    "wof:name": "NE28 8QP",
    "wof:placetype": "postalcode"
  },
  "geometry": {"coordinates":[-1.537099,54.993086],"type":"Point"}
}
