{
  "type": "Feature",
  "properties": {
    "iso:country":"GB",
    "wof:name":"NE28 8QP",
    "wof:placetype":"postalcode"
},
  "geometry": {"coordinates":[-1.53709930739834,54.99308557742796],"type":"Point"}
}