{
  "type": "Feature",
  "properties": {
    "iso:country":"GB",
    "wof:name":"SA70 8JD",
    "wof:placetype":"postalcode"
},
  "geometry": {"coordinates":[-4.71307130574322,51.67965798123867],"type":"Point"}
}