{
  "type": "Feature",
  "properties": {
    "date:inception_lower":"1980-01-01",
    "date:inception_upper":"1980-01-31",
    "iso:country":"GB",
    "wof:name":"N16 8JS",
    "wof:placetype":"postalcode"
},
  "geometry": {"coordinates":[-0.076977,51.547646],"type":"Point"}
}