{
  "type": "Feature",
  "properties": {
    "iso:country":"GB",
    "wof:name":"N16 8JS",
    "wof:placetype":"postalcode"
},
  "geometry": {"coordinates":[-0.07697675472976,51.54764585625711],"type":"Point"}
}