{
  "type": "Feature",
  "properties": {
    "iso:country": "GB",
    "wof:name": "CM9 8LN",
    "wof:placetype": "postalcode"
  },
  "geometry": {"coordinates":[0.755484,51.768959],"type":"Point"}
}
