{
  "type": "Feature",
  "properties": {
    "iso:country":"GB",
    "wof:name":"CA6 6NH",
    "wof:placetype":"postalcode"
},
  "geometry": {"coordinates":[-2.7707953682533,55.05503767101077],"type":"Point"}
}