{
  "type": "Feature",
  "properties": {
    "date:inception_lower":"1980-01-01",
    "date:inception_upper":"1980-01-31",
    "iso:country":"GB",
    "wof:name":"CA6 6NH",
    "wof:placetype":"postalcode"
},
  "geometry": {"coordinates":[-2.7708,55.055042],"type":"Point"}
}