{
  "type": "Feature",
  "properties": {
    "iso:country": "GB",
    "wof:name": "IP10 0FN",
    "wof:placetype": "postalcode"
  },
  "geometry": {"coordinates":[1.238485,52.032982],"type":"Point"}
}
