{
  "type": "Feature",
  "properties": {
    "iso:country":"GB",
    "wof:name":"CM17 0ED",
    "wof:placetype":"postalcode"
},
  "geometry": {"coordinates":[0.13699499945879,51.7846133863152],"type":"Point"}
}