{
  "type": "Feature",
  "properties": {
    "iso:country":"GB",
    "wof:name":"RG9 5EJ",
    "wof:placetype":"postalcode"
},
  "geometry": {"coordinates":[-0.9850249787143,51.52469203434394],"type":"Point"}
}