{
  "type": "Feature",
  "properties": {
    "date:inception_lower":"1980-01-01",
    "date:inception_upper":"1980-01-31",
    "iso:country":"GB",
    "wof:name":"RG9 5EJ",
    "wof:placetype":"postalcode"
},
  "geometry": {"coordinates":[-0.985004,51.524695],"type":"Point"}
}