{
  "type": "Feature",
  "properties": {
    "iso:country": "GB",
    "wof:name": "CF14 0NB",
    "wof:placetype": "postalcode"
  },
  "geometry": {"coordinates":[-3.179207,51.521452],"type":"Point"}
}
