{
  "type": "Feature",
  "properties": {
    "iso:country":"GB",
    "wof:name":"CF14 0NB",
    "wof:placetype":"postalcode"
},
  "geometry": {"coordinates":[-3.17920669243267,51.52145169312265],"type":"Point"}
}