{
  "type": "Feature",
  "properties": {
    "iso:country":"GB",
    "wof:name":"SE14 5LU",
    "wof:placetype":"postalcode"
},
  "geometry": {"coordinates":[-0.04791738427667,51.46902003782618],"type":"Point"}
}