{
  "type": "Feature",
  "properties": {
    "date:inception_lower":"2009-02-01",
    "date:inception_upper":"2009-02-28",
    "iso:country":"GB",
    "wof:name":"KY10 3WJ",
    "wof:placetype":"postalcode"
},
  "geometry": {"coordinates":[-2.624126,56.264492],"type":"Point"}
}