{
  "type": "Feature",
  "properties": {
    "iso:country":"GB",
    "wof:name":"BH20 4BE",
    "wof:placetype":"postalcode"
},
  "geometry": {"coordinates":[-2.11599462647738,50.69198675178399],"type":"Point"}
}