{
  "type": "Feature",
  "properties": {
    "date:inception_lower": "2003-02-01",
    "date:inception_upper": "2003-02-01",
    "iso:country": "GB",
    "wof:name": "CF33 6RX",
    "wof:placetype": "postalcode"
  },
  "geometry": {"coordinates":[-3.686979,51.527242],"type":"Point"}
}
