{
  "type": "Feature",
  "properties": {
    "iso:country": "GB",
    "wof:name": "S41 7QW",
    "wof:placetype": "postalcode"
  },
  "geometry": {"coordinates":[-1.428484,53.243248],"type":"Point"}
}
