{
  "type": "Feature",
  "properties": {
    "iso:country":"GB",
    "wof:name":"TA6 3PA",
    "wof:placetype":"postalcode"
},
  "geometry": {"coordinates":[-2.99944046453795,51.12470236725736],"type":"Point"}
}