{
  "type": "Feature",
  "properties": {
    "iso:country":"GB",
    "wof:name":"OL3 5SQ",
    "wof:placetype":"postalcode"
},
  "geometry": {"coordinates":[-2.04037675562369,53.59339137669115],"type":"Point"}
}