{
  "type": "Feature",
  "properties": {
    "date:inception_lower":"1980-01-01",
    "date:inception_upper":"1980-01-31",
    "iso:country":"GB",
    "wof:name":"BN11 4DD",
    "wof:placetype":"postalcode"
},
  "geometry": {"coordinates":[-0.38226,50.811153],"type":"Point"}
}