{
  "type": "Feature",
  "properties": {
    "iso:country":"GB",
    "wof:name":"LU5 5XR",
    "wof:placetype":"postalcode"
},
  "geometry": {"coordinates":[-0.51240315472563,51.89771356346545],"type":"Point"}
}