{
  "type": "Feature",
  "properties": {
    "date:inception_lower": "2000-12-01",
    "date:inception_upper": "2000-12-01",
    "iso:country": "GB",
    "wof:name": "LU5 5XR",
    "wof:placetype": "postalcode"
  },
  "geometry": {"coordinates":[-0.512403,51.897714],"type":"Point"}
}
