{
  "type": "Feature",
  "properties": {
    "iso:country": "GB",
    "wof:name": "NE34 7EF",
    "wof:placetype": "postalcode"
  },
  "geometry": {"coordinates":[-1.394778,54.978326],"type":"Point"}
}
