{
  "type": "Feature",
  "properties": {
    "date:inception_lower": "1980-01-01",
    "date:inception_upper": "1980-01-01",
    "iso:country": "GB",
    "wof:name": "NR10 3PL",
    "wof:placetype": "postalcode"
  },
  "geometry": {"coordinates":[1.315091,52.683329],"type":"Point"}
}
