{
  "type": "Feature",
  "properties": {
    "iso:country":"GB",
    "wof:name":"NR10 3PL",
    "wof:placetype":"postalcode"
},
  "geometry": {"coordinates":[1.31509111732757,52.68332873007638],"type":"Point"}
}