{
  "type": "Feature",
  "properties": {
    "date:inception_lower":"1994-05-01",
    "date:inception_upper":"1994-05-31",
    "iso:country":"GB",
    "wof:name":"M7 4QE",
    "wof:placetype":"postalcode"
},
  "geometry": {"coordinates":[-2.247981,53.510888],"type":"Point"}
}