{
  "type": "Feature",
  "properties": {
    "iso:country":"GB",
    "wof:name":"M7 4QE",
    "wof:placetype":"postalcode"
},
  "geometry": {"coordinates":[-2.24798082012638,53.5108883809425],"type":"Point"}
}