{
  "type": "Feature",
  "properties": {
    "date:inception_lower": "1980-07-01",
    "date:inception_upper": "1980-07-01",
    "iso:country": "GB",
    "wof:name": "DG5 4BN",
    "wof:placetype": "postalcode"
  },
  "geometry": {"coordinates":[-3.826114,54.935196],"type":"Point"}
}
