{
  "type": "Feature",
  "properties": {
    "iso:country":"GB",
    "wof:name":"DG5 4BN",
    "wof:placetype":"postalcode"
},
  "geometry": {"coordinates":[-3.82667382761849,54.93540513448975],"type":"Point"}
}