{
  "type": "Feature",
  "properties": {
    "iso:country": "GB",
    "wof:name": "HD8 0SR",
    "wof:placetype": "postalcode"
  },
  "geometry": {"coordinates":[-1.697618,53.605421],"type":"Point"}
}
