{
  "type": "Feature",
  "properties": {
    "iso:country":"GB",
    "wof:name":"HD8 0SR",
    "wof:placetype":"postalcode"
},
  "geometry": {"coordinates":[-1.69761828440174,53.60542073462901],"type":"Point"}
}