{
  "type": "Feature",
  "properties": {
    "date:inception_lower": "2001-06-01",
    "date:inception_upper": "2001-06-01",
    "iso:country": "GB",
    "wof:name": "ML2 0FF",
    "wof:placetype": "postalcode"
  },
  "geometry": {"coordinates":[-3.945269,55.76628],"type":"Point"}
}
