{
  "type": "Feature",
  "properties": {
    "iso:country":"GB",
    "wof:name":"ML2 0FF",
    "wof:placetype":"postalcode"
},
  "geometry": {"coordinates":[-3.94526945729599,55.76628002935222],"type":"Point"}
}