{
  "type": "Feature",
  "properties": {
    "iso:country": "GB",
    "wof:name": "ML2 0FF",
    "wof:placetype": "postalcode"
  },
  "geometry": {"coordinates":[-3.945269,55.76628],"type":"Point"}
}
