{
  "type": "Feature",
  "properties": {
    "date:inception_lower":"2008-12-01",
    "date:inception_upper":"2008-12-31",
    "iso:country":"GB",
    "wof:name":"SM6 9EQ",
    "wof:placetype":"postalcode"
},
  "geometry": {"coordinates":[-0.134273,51.35478],"type":"Point"}
}