{
  "type": "Feature",
  "properties": {
    "date:inception_lower": "1980-01-01",
    "date:inception_upper": "1980-01-01",
    "iso:country": "GB",
    "wof:name": "LA2 9DB",
    "wof:placetype": "postalcode"
  },
  "geometry": {"coordinates":[-2.771452,53.968415],"type":"Point"}
}
