{
  "type": "Feature",
  "properties": {
    "iso:country":"GB",
    "wof:name":"SK11 9AE",
    "wof:placetype":"postalcode"
},
  "geometry": {"coordinates":[-2.28280286551999,53.25316132343892],"type":"Point"}
}