{
  "type": "Feature",
  "properties": {
    "date:inception_lower":"1980-01-01",
    "date:inception_upper":"1980-01-31",
    "iso:country":"GB",
    "wof:name":"SK11 9AE",
    "wof:placetype":"postalcode"
},
  "geometry": {"coordinates":[-2.282803,53.253161],"type":"Point"}
}