{
  "type": "Feature",
  "properties": {
    "iso:country":"GB",
    "wof:name":"BL8 2UG",
    "wof:placetype":"postalcode"
},
  "geometry": {"coordinates":[-2.32939598888312,53.59289924867966],"type":"Point"}
}