{
  "type": "Feature",
  "properties": {
    "date:inception_lower":"2001-06-01",
    "date:inception_upper":"2001-06-30",
    "iso:country":"GB",
    "wof:name":"BA3 3PW",
    "wof:placetype":"postalcode"
},
  "geometry": {"coordinates":[-2.443311,51.291347],"type":"Point"}
}