{
  "type": "Feature",
  "properties": {
    "iso:country":"GB",
    "wof:name":"BA3 3PW",
    "wof:placetype":"postalcode"
},
  "geometry": {"coordinates":[-2.44331057318583,51.29134733259183],"type":"Point"}
}