{
  "type": "Feature",
  "properties": {
    "iso:country":"GB",
    "wof:name":"S26 1HS",
    "wof:placetype":"postalcode"
},
  "geometry": {"coordinates":[-1.25618885737857,53.35024570027731],"type":"Point"}
}