{
  "type": "Feature",
  "properties": {
    "iso:country": "GB",
    "wof:name": "S26 1HS",
    "wof:placetype": "postalcode"
  },
  "geometry": {"coordinates":[-1.256189,53.350246],"type":"Point"}
}
