{
  "type": "Feature",
  "properties": {
    "iso:country": "GB",
    "wof:name": "DN21 1ZN",
    "wof:placetype": "postalcode"
  },
  "geometry": {"coordinates":[-0.756024,53.406357],"type":"Point"}
}
