{
  "type": "Feature",
  "properties": {
    "iso:country": "GB",
    "wof:name": "LL65 3BA",
    "wof:placetype": "postalcode"
  },
  "geometry": {"coordinates":[-4.568815,53.290283],"type":"Point"}
}
