{
  "type": "Feature",
  "properties": {
    "iso:country":"GB",
    "wof:name":"LL65 3BA",
    "wof:placetype":"postalcode"
},
  "geometry": {"coordinates":[-4.56881461473359,53.29028273723182],"type":"Point"}
}