{
  "type": "Feature",
  "properties": {
    "date:inception_lower": "1980-01-01",
    "date:inception_upper": "1980-01-01",
    "iso:country": "GB",
    "wof:name": "DE7 8HF",
    "wof:placetype": "postalcode"
  },
  "geometry": {"coordinates":[-1.308735,52.973271],"type":"Point"}
}
