{
  "type": "Feature",
  "properties": {
    "date:inception_lower": "2007-08-01",
    "date:inception_upper": "2007-08-01",
    "iso:country": "GB",
    "wof:name": "PE1 5WS",
    "wof:placetype": "postalcode"
  },
  "geometry": {"coordinates":[-0.206254,52.580471],"type":"Point"}
}
