{
  "type": "Feature",
  "properties": {
    "iso:country":"GB",
    "wof:name":"PE1 5WS",
    "wof:placetype":"postalcode"
},
  "geometry": {"coordinates":[-0.20625436133585,52.58047124997875],"type":"Point"}
}