{
  "type": "Feature",
  "properties": {
    "iso:country": "GB",
    "wof:name": "WF1 4FW",
    "wof:placetype": "postalcode"
  },
  "geometry": {"coordinates":[-1.478495,53.695465],"type":"Point"}
}
