{
  "type": "Feature",
  "properties": {
    "date:inception_lower": "1983-01-01",
    "date:inception_upper": "1983-01-01",
    "iso:country": "GB",
    "wof:name": "PO7 8EQ",
    "wof:placetype": "postalcode"
  },
  "geometry": {"coordinates":[-1.01688,50.871634],"type":"Point"}
}
