{
  "type": "Feature",
  "properties": {
    "iso:country":"GB",
    "wof:name":"CR2 6BN",
    "wof:placetype":"postalcode"
},
  "geometry": {"coordinates":[-0.1031071752445,51.35224760460576],"type":"Point"}
}