{
  "type": "Feature",
  "properties": {
    "date:inception_lower": "1980-01-01",
    "date:inception_upper": "1980-01-01",
    "iso:country": "GB",
    "wof:name": "CR2 6BN",
    "wof:placetype": "postalcode"
  },
  "geometry": {"coordinates":[-0.103107,51.352248],"type":"Point"}
}
