{
  "type": "Feature",
  "properties": {
    "iso:country":"GB",
    "wof:name":"LS29 8DA",
    "wof:placetype":"postalcode"
},
  "geometry": {"coordinates":[-1.82291044496458,53.92482694650413],"type":"Point"}
}