{
  "type": "Feature",
  "properties": {
    "iso:country": "GB",
    "wof:name": "SK12 1NE",
    "wof:placetype": "postalcode"
  },
  "geometry": {"coordinates":[-2.12218,53.339124],"type":"Point"}
}
