{
  "type": "Feature",
  "properties": {
    "iso:country": "GB",
    "wof:name": "NG6 8JA",
    "wof:placetype": "postalcode"
  },
  "geometry": {"coordinates":[-1.202587,53.00246],"type":"Point"}
}
