{
  "type": "Feature",
  "properties": {
    "iso:country": "GB",
    "wof:name": "TS5 5AX",
    "wof:placetype": "postalcode"
  },
  "geometry": {"coordinates":[-1.258714,54.559446],"type":"Point"}
}
