{
  "type": "Feature",
  "properties": {
    "iso:country":"GB",
    "wof:name":"M5 5NE",
    "wof:placetype":"postalcode"
},
  "geometry": {"coordinates":[-2.30079272279336,53.48607580326114],"type":"Point"}
}