{
  "type": "Feature",
  "properties": {
    "iso:country": "GB",
    "wof:name": "GU12 4FG",
    "wof:placetype": "postalcode"
  },
  "geometry": {"coordinates":[-0.737492,51.252778],"type":"Point"}
}
