{
  "type": "Feature",
  "properties": {
    "date:inception_lower":"1980-01-01",
    "date:inception_upper":"1980-01-31",
    "iso:country":"GB",
    "wof:name":"NW10 8DX",
    "wof:placetype":"postalcode"
},
  "geometry": {"coordinates":[-0.261046,51.542237],"type":"Point"}
}