{
  "type": "Feature",
  "properties": {
    "iso:country":"GB",
    "wof:name":"NW10 8DX",
    "wof:placetype":"postalcode"
},
  "geometry": {"coordinates":[-0.26104560854565,51.54223654006809],"type":"Point"}
}