{
  "type": "Feature",
  "properties": {
    "date:inception_lower": "1980-01-01",
    "date:inception_upper": "1980-01-01",
    "iso:country": "GB",
    "wof:name": "LE12 7AB",
    "wof:placetype": "postalcode"
  },
  "geometry": {"coordinates":[-1.140285,52.727673],"type":"Point"}
}
