{
  "type": "Feature",
  "properties": {
    "iso:country": "GB",
    "wof:name": "LE12 7AB",
    "wof:placetype": "postalcode"
  },
  "geometry": {"coordinates":[-1.140535,52.72772],"type":"Point"}
}
