{
  "type": "Feature",
  "properties": {
    "date:inception_lower": "2017-11-01",
    "date:inception_upper": "2017-11-01",
    "iso:country": "GB",
    "wof:name": "GL7 5FD",
    "wof:placetype": "postalcode"
  },
  "geometry": {"coordinates":[-1.896971,51.734581],"type":"Point"}
}
