{
  "type": "Feature",
  "properties": {
    "date:inception_lower": "1980-01-01",
    "date:inception_upper": "1980-01-01",
    "iso:country": "GB",
    "wof:name": "FK3 9BZ",
    "wof:placetype": "postalcode"
  },
  "geometry": {"coordinates":[-3.710013,56.01436],"type":"Point"}
}
