{
  "type": "Feature",
  "properties": {
    "date:inception_lower": "1999-06-01",
    "date:inception_upper": "1999-06-01",
    "iso:country": "GB",
    "wof:name": "TR12 7DA",
    "wof:placetype": "postalcode"
  },
  "geometry": {"coordinates":[-5.238375,50.024777],"type":"Point"}
}
