{
  "type": "Feature",
  "properties": {
    "date:inception_lower": "1983-02-01",
    "date:inception_upper": "1983-02-01",
    "iso:country": "GB",
    "wof:name": "G51 4DX",
    "wof:placetype": "postalcode"
  },
  "geometry": {"coordinates":[-4.330989,55.853528],"type":"Point"}
}
