{
  "type": "Feature",
  "properties": {
    "iso:country": "GB",
    "wof:name": "IV28 3UB",
    "wof:placetype": "postalcode"
  },
  "geometry": {"coordinates":[-4.232513,58.009791],"type":"Point"}
}
