{
  "type": "Feature",
  "properties": {
    "iso:country":"GB",
    "wof:name":"IV28 3UB",
    "wof:placetype":"postalcode"
},
  "geometry": {"coordinates":[-4.23438180617433,58.00637084401973],"type":"Point"}
}