{
  "type": "Feature",
  "properties": {
    "date:inception_lower": "2021-03-01",
    "date:inception_upper": "2021-03-01",
    "iso:country": "GB",
    "wof:name": "B97 6RX",
    "wof:placetype": "postalcode"
  },
  "geometry": {"coordinates":[-1.944724,52.321244],"type":"Point"}
}
