{
  "type": "Feature",
  "properties": {
    "iso:country": "GB",
    "wof:name": "BN1 7BF",
    "wof:placetype": "postalcode"
  },
  "geometry": {"coordinates":[-0.126743,50.842027],"type":"Point"}
}
