{
  "type": "Feature",
  "properties": {
    "iso:country":"GB",
    "wof:name":"BN1 7BF",
    "wof:placetype":"postalcode"
},
  "geometry": {"coordinates":[-0.12674341793362,50.84202690775797],"type":"Point"}
}