{
  "type": "Feature",
  "properties": {
    "date:inception_lower": "2018-12-01",
    "date:inception_upper": "2018-12-01",
    "iso:country": "GB",
    "wof:name": "GL15 4BQ",
    "wof:placetype": "postalcode"
  },
  "geometry": {"coordinates":[-2.513935,51.733761],"type":"Point"}
}
