{
  "type": "Feature",
  "properties": {
    "iso:country":"GB",
    "wof:name":"SN15 3JR",
    "wof:placetype":"postalcode"
},
  "geometry": {"coordinates":[-2.1116649621672,51.45627673991084],"type":"Point"}
}