{
  "type": "Feature",
  "properties": {
    "iso:country":"GB",
    "wof:name":"TS13 4AU",
    "wof:placetype":"postalcode"
},
  "geometry": {"coordinates":[-0.89916436393489,54.56798015025277],"type":"Point"}
}