{
  "type": "Feature",
  "properties": {
    "iso:country":"GB",
    "wof:name":"IP7 7BZ",
    "wof:placetype":"postalcode"
},
  "geometry": {"coordinates":[0.96749487069176,52.10846897729085],"type":"Point"}
}