{
  "type": "Feature",
  "properties": {
    "iso:country":"GB",
    "wof:name":"PL4 8AQ",
    "wof:placetype":"postalcode"
},
  "geometry": {"coordinates":[-4.13794583446368,50.3737241874957],"type":"Point"}
}