{
  "type": "Feature",
  "properties": {
    "iso:country":"GB",
    "wof:name":"WN8 6EE",
    "wof:placetype":"postalcode"
},
  "geometry": {"coordinates":[-2.76888109345833,53.54699034337011],"type":"Point"}
}