{
  "type": "Feature",
  "properties": {
    "iso:country":"GB",
    "wof:name":"SW6 6JX",
    "wof:placetype":"postalcode"
},
  "geometry": {"coordinates":[-0.22157861744962,51.47886883288102],"type":"Point"}
}