{
  "type": "Feature",
  "properties": {
    "iso:country":"GB",
    "wof:name":"B65 0JQ",
    "wof:placetype":"postalcode"
},
  "geometry": {"coordinates":[-2.03835189497596,52.47455298135537],"type":"Point"}
}