{
  "type": "Feature",
  "properties": {
    "iso:country":"GB",
    "wof:name":"LS18 4QT",
    "wof:placetype":"postalcode"
},
  "geometry": {"coordinates":[-1.63969736568648,53.83536549776938],"type":"Point"}
}