{
  "type": "Feature",
  "properties": {
    "iso:country":"GB",
    "wof:name":"RG7 5SH",
    "wof:placetype":"postalcode"
},
  "geometry": {"coordinates":[-1.17848573777522,51.39445901714291],"type":"Point"}
}