{
  "type": "Feature",
  "properties": {
    "iso:country":"GB",
    "wof:name":"SS7 2HF",
    "wof:placetype":"postalcode"
},
  "geometry": {"coordinates":[0.62084874187498,51.5527184392698],"type":"Point"}
}