{
  "type": "Feature",
  "properties": {
    "iso:country": "GB",
    "wof:name": "SO41 0NH",
    "wof:placetype": "postalcode"
  },
  "geometry": {"coordinates":[-1.604499,50.724945],"type":"Point"}
}
