{
  "type": "Feature",
  "properties": {
    "iso:country":"GB",
    "wof:name":"SO41 0NH",
    "wof:placetype":"postalcode"
},
  "geometry": {"coordinates":[-1.60449896711519,50.7249445963123],"type":"Point"}
}