{
  "type": "Feature",
  "properties": {
    "date:inception_lower":"1999-06-01",
    "date:inception_upper":"1999-06-30",
    "iso:country":"GB",
    "wof:name":"E14 9PP",
    "wof:placetype":"postalcode"
},
  "geometry": {"coordinates":[-0.008013,51.511136],"type":"Point"}
}