{
  "type": "Feature",
  "properties": {
    "iso:country":"GB",
    "wof:name":"DT11 9HS",
    "wof:placetype":"postalcode"
},
  "geometry": {"coordinates":[-2.14795868213475,50.85257624472619],"type":"Point"}
}