{
  "type": "Feature",
  "properties": {
    "date:inception_lower": "1980-01-01",
    "date:inception_upper": "1980-01-01",
    "iso:country": "GB",
    "wof:name": "DT11 9HS",
    "wof:placetype": "postalcode"
  },
  "geometry": {"coordinates":[-2.147157,50.852219],"type":"Point"}
}
