{
  "type": "Feature",
  "properties": {
    "date:inception_lower": "2018-10-01",
    "date:inception_upper": "2018-10-01",
    "iso:country": "GB",
    "wof:name": "SO52 9AG",
    "wof:placetype": "postalcode"
  },
  "geometry": {"coordinates":[-1.40053,50.9937],"type":"Point"}
}
