{
  "type": "Feature",
  "properties": {
    "iso:country": "GB",
    "wof:name": "GL13 9BW",
    "wof:placetype": "postalcode"
  },
  "geometry": {"coordinates":[-2.461123,51.689541],"type":"Point"}
}
