{
  "type": "Feature",
  "properties": {
    "iso:country": "GB",
    "wof:name": "SY8 4EQ",
    "wof:placetype": "postalcode"
  },
  "geometry": {"coordinates":[-2.742186,52.326632],"type":"Point"}
}
