{
  "type": "Feature",
  "properties": {
    "iso:country":"GB",
    "wof:name":"SY8 4EQ",
    "wof:placetype":"postalcode"
},
  "geometry": {"coordinates":[-2.74218631102411,52.32663211717011],"type":"Point"}
}