{
  "type": "Feature",
  "properties": {
    "iso:country":"GB",
    "wof:name":"NR32 2JF",
    "wof:placetype":"postalcode"
},
  "geometry": {"coordinates":[1.73980914202227,52.47669268415017],"type":"Point"}
}