{
  "type": "Feature",
  "properties": {
    "date:inception_lower":"1980-01-01",
    "date:inception_upper":"1980-01-31",
    "iso:country":"GB",
    "wof:name":"TS12 1EG",
    "wof:placetype":"postalcode"
},
  "geometry": {"coordinates":[-0.976065,54.584791],"type":"Point"}
}