{
  "type": "Feature",
  "properties": {
    "iso:country":"GB",
    "wof:name":"TS12 1EG",
    "wof:placetype":"postalcode"
},
  "geometry": {"coordinates":[-0.97604790252746,54.58483205202727],"type":"Point"}
}