{
  "type": "Feature",
  "properties": {
    "iso:country": "GB",
    "wof:name": "TS12 1EG",
    "wof:placetype": "postalcode"
  },
  "geometry": {"coordinates":[-0.976065,54.584791],"type":"Point"}
}
