{
  "type": "Feature",
  "properties": {
    "date:inception_lower": "1980-01-01",
    "date:inception_upper": "1980-01-01",
    "iso:country": "GB",
    "wof:name": "IP13 7BH",
    "wof:placetype": "postalcode"
  },
  "geometry": {"coordinates":[1.2566,52.195089],"type":"Point"}
}
