{
  "type": "Feature",
  "properties": {
    "iso:country":"GB",
    "wof:name":"IP13 7BH",
    "wof:placetype":"postalcode"
},
  "geometry": {"coordinates":[1.25653994315788,52.19465914356554],"type":"Point"}
}