{
  "type": "Feature",
  "properties": {
    "date:inception_lower": "1980-01-01",
    "date:inception_upper": "1980-01-01",
    "iso:country": "GB",
    "wof:name": "IP13 7BH",
    "wof:placetype": "postalcode"
  },
  "geometry": {"coordinates":[1.25657,52.194676],"type":"Point"}
}
