{
  "type": "Feature",
  "properties": {
    "date:inception_lower": "2001-12-01",
    "date:inception_upper": "2001-12-01",
    "iso:country": "GB",
    "wof:name": "SP10 3XU",
    "wof:placetype": "postalcode"
  },
  "geometry": {"coordinates":[-1.504939,51.2041],"type":"Point"}
}
