{
  "type": "Feature",
  "properties": {
    "iso:country": "GB",
    "wof:name": "SL1 6NG",
    "wof:placetype": "postalcode"
  },
  "geometry": {"coordinates":[-0.645643,51.528207],"type":"Point"}
}
