{
  "type": "Feature",
  "properties": {
    "date:inception_lower":"2003-02-01",
    "date:inception_upper":"2003-02-28",
    "iso:country":"GB",
    "wof:name":"EX16 8PP",
    "wof:placetype":"postalcode"
},
  "geometry": {"coordinates":[-3.655498,50.913175],"type":"Point"}
}