{
  "type": "Feature",
  "properties": {
    "iso:country": "GB",
    "wof:name": "EX16 8PP",
    "wof:placetype": "postalcode"
  },
  "geometry": {"coordinates":[-3.655498,50.913175],"type":"Point"}
}
