{
  "type": "Feature",
  "properties": {
    "date:inception_lower": "1980-01-01",
    "date:inception_upper": "1980-01-01",
    "iso:country": "GB",
    "wof:name": "FY3 8NP",
    "wof:placetype": "postalcode"
  },
  "geometry": {"coordinates":[-3.015051,53.82201],"type":"Point"}
}
