{
  "type": "Feature",
  "properties": {
    "iso:country":"GB",
    "wof:name":"FY3 8NP",
    "wof:placetype":"postalcode"
},
  "geometry": {"coordinates":[-3.01505125947182,53.8220100406554],"type":"Point"}
}