{
  "type": "Feature",
  "properties": {
    "iso:country": "GB",
    "wof:name": "FY3 8NP",
    "wof:placetype": "postalcode"
  },
  "geometry": {"coordinates":[-3.015051,53.82201],"type":"Point"}
}
