{
  "type": "Feature",
  "properties": {
    "iso:country":"GB",
    "wof:name":"M29 8FD",
    "wof:placetype":"postalcode"
},
  "geometry": {"coordinates":[-2.46247920288627,53.51491559292604],"type":"Point"}
}