{
  "type": "Feature",
  "properties": {
    "date:inception_lower": "1980-01-01",
    "date:inception_upper": "1980-01-01",
    "iso:country": "GB",
    "wof:name": "SA72 6RH",
    "wof:placetype": "postalcode"
  },
  "geometry": {"coordinates":[-4.947925,51.682008],"type":"Point"}
}
