{
  "type": "Feature",
  "properties": {
    "iso:country":"GB",
    "wof:name":"CF44 7EL",
    "wof:placetype":"postalcode"
},
  "geometry": {"coordinates":[-3.44265566174431,51.71116802921909],"type":"Point"}
}