{
  "type": "Feature",
  "properties": {
    "date:inception_lower":"1980-01-01",
    "date:inception_upper":"1980-01-31",
    "iso:country":"GB",
    "wof:name":"CF44 7EL",
    "wof:placetype":"postalcode"
},
  "geometry": {"coordinates":[-3.442656,51.711168],"type":"Point"}
}