{
  "type": "Feature",
  "properties": {
    "iso:country":"GB",
    "wof:name":"NP44 5SU",
    "wof:placetype":"postalcode"
},
  "geometry": {"coordinates":[-3.04916358524336,51.66596926199141],"type":"Point"}
}