{
  "type": "Feature",
  "properties": {
    "iso:country":"GB",
    "wof:name":"NG19 8NR",
    "wof:placetype":"postalcode"
},
  "geometry": {"coordinates":[-1.1942024394282,53.17329908348016],"type":"Point"}
}