{
  "type": "Feature",
  "properties": {
    "iso:country":"GB",
    "wof:name":"DD8 5QG",
    "wof:placetype":"postalcode"
},
  "geometry": {"coordinates":[-2.95789501980152,56.66489909421989],"type":"Point"}
}