{
  "type": "Feature",
  "properties": {
    "date:inception_lower": "1980-01-01",
    "date:inception_upper": "1980-01-01",
    "iso:country": "GB",
    "wof:name": "GU15 2JZ",
    "wof:placetype": "postalcode"
  },
  "geometry": {"coordinates":[-0.738097,51.328005],"type":"Point"}
}
