{
  "type": "Feature",
  "properties": {
    "iso:country":"GB",
    "wof:name":"GU15 2JZ",
    "wof:placetype":"postalcode"
},
  "geometry": {"coordinates":[-0.73809753826161,51.32800473711086],"type":"Point"}
}