{
  "type": "Feature",
  "properties": {
    "iso:country":"GB",
    "wof:name":"TW7 7NF",
    "wof:placetype":"postalcode"
},
  "geometry": {"coordinates":[-0.34951382795387,51.4581955015333],"type":"Point"}
}