{
  "type": "Feature",
  "properties": {
    "date:inception_lower": "2020-10-01",
    "date:inception_upper": "2020-10-01",
    "iso:country": "GB",
    "wof:name": "WV5 5AX",
    "wof:placetype": "postalcode"
  },
  "geometry": {"coordinates":[-2.212489,52.527792],"type":"Point"}
}
