{
  "type": "Feature",
  "properties": {
    "iso:country":"GB",
    "wof:name":"BN16 1HT",
    "wof:placetype":"postalcode"
},
  "geometry": {"coordinates":[-0.4848284300014,50.81377148179086],"type":"Point"}
}