{
  "type": "Feature",
  "properties": {
    "iso:country":"GB",
    "wof:name":"BD4 8LA",
    "wof:placetype":"postalcode"
},
  "geometry": {"coordinates":[-1.71097954917888,53.78885674088068],"type":"Point"}
}