{
  "type": "Feature",
  "properties": {
    "iso:country": "GB",
    "wof:name": "BD4 8LA",
    "wof:placetype": "postalcode"
  },
  "geometry": {"coordinates":[-1.71098,53.788857],"type":"Point"}
}
