{
  "type": "Feature",
  "properties": {
    "date:inception_lower":"1980-01-01",
    "date:inception_upper":"1980-01-31",
    "iso:country":"GB",
    "wof:name":"BD4 8LA",
    "wof:placetype":"postalcode"
},
  "geometry": {"coordinates":[-1.71098,53.788857],"type":"Point"}
}