{
  "type": "Feature",
  "properties": {
    "iso:country": "GB",
    "wof:name": "SN11 8GN",
    "wof:placetype": "postalcode"
  },
  "geometry": {"coordinates":[-1.99295,51.449935],"type":"Point"}
}
