{
  "type": "Feature",
  "properties": {
    "iso:country": "GB",
    "wof:name": "EX38 7BY",
    "wof:placetype": "postalcode"
  },
  "geometry": {"coordinates":[-4.127563,50.958661],"type":"Point"}
}
