{
  "type": "Feature",
  "properties": {
    "date:inception_lower": "2017-05-01",
    "date:inception_upper": "2017-05-01",
    "iso:country": "GB",
    "wof:name": "EX38 7BY",
    "wof:placetype": "postalcode"
  },
  "geometry": {"coordinates":[-4.12745,50.959005],"type":"Point"}
}
