{
  "type": "Feature",
  "properties": {
    "date:inception_lower": "2017-05-01",
    "date:inception_upper": "2017-05-01",
    "iso:country": "GB",
    "wof:name": "EX38 7BY",
    "wof:placetype": "postalcode"
  },
  "geometry": {"coordinates":[-4.127295,50.958711],"type":"Point"}
}
