{
  "type": "Feature",
  "properties": {
    "date:inception_lower": "1980-01-01",
    "date:inception_upper": "1980-01-01",
    "iso:country": "GB",
    "wof:name": "SY7 8JG",
    "wof:placetype": "postalcode"
  },
  "geometry": {"coordinates":[-3.02854,52.418926],"type":"Point"}
}
