{
  "type": "Feature",
  "properties": {
    "date:inception_lower": "1980-01-01",
    "date:inception_upper": "1980-01-01",
    "iso:country": "GB",
    "wof:name": "KA30 8PB",
    "wof:placetype": "postalcode"
  },
  "geometry": {"coordinates":[-4.866834,55.799303],"type":"Point"}
}
