{
  "type": "Feature",
  "properties": {
    "iso:country":"GB",
    "wof:name":"KA30 8PB",
    "wof:placetype":"postalcode"
},
  "geometry": {"coordinates":[-4.86683415998683,55.79930328232949],"type":"Point"}
}