{
  "type": "Feature",
  "properties": {
    "iso:country":"GB",
    "wof:name":"TQ13 8QT",
    "wof:placetype":"postalcode"
},
  "geometry": {"coordinates":[-3.75920401119813,50.64604568746672],"type":"Point"}
}