{
  "type": "Feature",
  "properties": {
    "iso:country":"GB",
    "wof:name":"WS6 6BZ",
    "wof:placetype":"postalcode"
},
  "geometry": {"coordinates":[-2.01503760452387,52.66082744371183],"type":"Point"}
}