{
  "type": "Feature",
  "properties": {
    "date:inception_lower": "1980-01-01",
    "date:inception_upper": "1980-01-01",
    "iso:country": "GB",
    "wof:name": "WS6 6BZ",
    "wof:placetype": "postalcode"
  },
  "geometry": {"coordinates":[-2.015038,52.660827],"type":"Point"}
}
