{
  "type": "Feature",
  "properties": {
    "iso:country":"GB",
    "wof:name":"YO42 1NW",
    "wof:placetype":"postalcode"
},
  "geometry": {"coordinates":[-0.78434691384264,53.91704527177383],"type":"Point"}
}