{
  "type": "Feature",
  "properties": {
    "iso:country":"GB",
    "wof:name":"SG19 2QB",
    "wof:placetype":"postalcode"
},
  "geometry": {"coordinates":[-0.2244855481609,52.12681410555706],"type":"Point"}
}