{
  "type": "Feature",
  "properties": {
    "iso:country":"GB",
    "wof:name":"TW12 3BJ",
    "wof:placetype":"postalcode"
},
  "geometry": {"coordinates":[-0.37483074975914,51.42340701858306],"type":"Point"}
}