{
  "type": "Feature",
  "properties": {
    "date:inception_lower": "1980-01-01",
    "date:inception_upper": "1980-01-01",
    "iso:country": "GB",
    "wof:name": "TW12 3BJ",
    "wof:placetype": "postalcode"
  },
  "geometry": {"coordinates":[-0.374831,51.423407],"type":"Point"}
}
