{
  "type": "Feature",
  "properties": {
    "iso:country":"GB",
    "wof:name":"WD17 2QR",
    "wof:placetype":"postalcode"
},
  "geometry": {"coordinates":[-0.39217800015605,51.65825271088153],"type":"Point"}
}