{
  "type": "Feature",
  "properties": {
    "iso:country":"GB",
    "wof:name":"AB24 4HR",
    "wof:placetype":"postalcode"
},
  "geometry": {"coordinates":[-2.12766766881711,57.16710410945512],"type":"Point"}
}