{
  "type": "Feature",
  "properties": {
    "iso:country":"GB",
    "wof:name":"AL10 8SU",
    "wof:placetype":"postalcode"
},
  "geometry": {"coordinates":[-0.2289079120369,51.74717416816245],"type":"Point"}
}