{
  "type": "Feature",
  "properties": {
    "date:inception_lower": "1980-01-01",
    "date:inception_upper": "1980-01-01",
    "iso:country": "GB",
    "wof:name": "SA19 8EX",
    "wof:placetype": "postalcode"
  },
  "geometry": {"coordinates":[-3.957765,52.087881],"type":"Point"}
}
