{
  "type": "Feature",
  "properties": {
    "iso:country":"GB",
    "wof:name":"SA19 8EX",
    "wof:placetype":"postalcode"
},
  "geometry": {"coordinates":[-3.95776501776535,52.08788079644176],"type":"Point"}
}