{
  "type": "Feature",
  "properties": {
    "iso:country":"GB",
    "wof:name":"SM6 7DU",
    "wof:placetype":"postalcode"
},
  "geometry": {"coordinates":[-0.15114437840056,51.37333917599044],"type":"Point"}
}