{
  "type": "Feature",
  "properties": {
    "date:inception_lower":"1980-01-01",
    "date:inception_upper":"1980-01-31",
    "iso:country":"GB",
    "wof:name":"ME8 7PH",
    "wof:placetype":"postalcode"
},
  "geometry": {"coordinates":[0.609767,51.364208],"type":"Point"}
}