{
  "type": "Feature",
  "properties": {
    "iso:country":"GB",
    "wof:name":"UB10 8LJ",
    "wof:placetype":"postalcode"
},
  "geometry": {"coordinates":[-0.44312484600149,51.5645765821447],"type":"Point"}
}