{
  "type": "Feature",
  "properties": {
    "date:inception_lower": "1992-01-01",
    "date:inception_upper": "1992-01-01",
    "iso:country": "GB",
    "wof:name": "CO6 1TW",
    "wof:placetype": "postalcode"
  },
  "geometry": {"coordinates":[0.693701,51.878582],"type":"Point"}
}
