{
  "type": "Feature",
  "properties": {
    "date:inception_lower":"2015-06-01",
    "date:inception_upper":"2015-06-30",
    "iso:country":"GB",
    "wof:name":"SA12 6EJ",
    "wof:placetype":"postalcode"
},
  "geometry": {"coordinates":[-3.797686,51.595028],"type":"Point"}
}