{
  "type": "Feature",
  "properties": {
    "iso:country": "GB",
    "wof:name": "SA12 6EJ",
    "wof:placetype": "postalcode"
  },
  "geometry": {"coordinates":[-3.797686,51.595028],"type":"Point"}
}
