{
  "type": "Feature",
  "properties": {
    "date:inception_lower": "1983-03-01",
    "date:inception_upper": "1983-03-01",
    "iso:country": "GB",
    "wof:name": "PE14 7BQ",
    "wof:placetype": "postalcode"
  },
  "geometry": {"coordinates":[0.192591,52.660247],"type":"Point"}
}
