{
  "type": "Feature",
  "properties": {
    "iso:country":"GB",
    "wof:name":"EX34 8NZ",
    "wof:placetype":"postalcode"
},
  "geometry": {"coordinates":[-4.14599808029625,51.17779635848261],"type":"Point"}
}