{
  "type": "Feature",
  "properties": {
    "date:inception_lower": "1995-01-01",
    "date:inception_upper": "1995-01-01",
    "iso:country": "GB",
    "wof:name": "SE18 1BL",
    "wof:placetype": "postalcode"
  },
  "geometry": {"coordinates":[0.092505,51.484665],"type":"Point"}
}
