{
  "type": "Feature",
  "properties": {
    "iso:country":"GB",
    "wof:name":"SE18 1BL",
    "wof:placetype":"postalcode"
},
  "geometry": {"coordinates":[0.09247780388568,51.48467388017765],"type":"Point"}
}