{
  "type": "Feature",
  "properties": {
    "iso:country": "GB",
    "wof:name": "BB3 1JY",
    "wof:placetype": "postalcode"
  },
  "geometry": {"coordinates":[-2.48332,53.698744],"type":"Point"}
}
