{
  "type": "Feature",
  "properties": {
    "iso:country":"GB",
    "wof:name":"BB3 1JY",
    "wof:placetype":"postalcode"
},
  "geometry": {"coordinates":[-2.48331981715335,53.69874350607452],"type":"Point"}
}