{
  "type": "Feature",
  "properties": {
    "date:inception_lower": "1980-01-01",
    "date:inception_upper": "1980-01-01",
    "iso:country": "GB",
    "wof:name": "KT3 6LD",
    "wof:placetype": "postalcode"
  },
  "geometry": {"coordinates":[-0.236808,51.397582],"type":"Point"}
}
