{
  "type": "Feature",
  "properties": {
    "iso:country":"GB",
    "wof:name":"ST6 2JF",
    "wof:placetype":"postalcode"
},
  "geometry": {"coordinates":[-2.18518571858888,53.03478659290104],"type":"Point"}
}