{
  "type": "Feature",
  "properties": {
    "iso:country":"GB",
    "wof:name":"SG6 3LN",
    "wof:placetype":"postalcode"
},
  "geometry": {"coordinates":[-0.23176921373828,51.96737553634237],"type":"Point"}
}