{
  "type": "Feature",
  "properties": {
    "iso:country":"GB",
    "wof:name":"PL30 5HB",
    "wof:placetype":"postalcode"
},
  "geometry": {"coordinates":[-4.76817977116201,50.44796344689479],"type":"Point"}
}