{
  "type": "Feature",
  "properties": {
    "iso:country":"GB",
    "wof:name":"DN3 1PD",
    "wof:placetype":"postalcode"
},
  "geometry": {"coordinates":[-1.06605850588878,53.56389521270348],"type":"Point"}
}