{
  "type": "Feature",
  "properties": {
    "iso:country":"GB",
    "wof:name":"CF31 5FW",
    "wof:placetype":"postalcode"
},
  "geometry": {"coordinates":[-3.60792742498869,51.50123217868246],"type":"Point"}
}