{
  "type": "Feature",
  "properties": {
    "iso:country": "GB",
    "wof:name": "CF31 5FW",
    "wof:placetype": "postalcode"
  },
  "geometry": {"coordinates":[-3.607927,51.501232],"type":"Point"}
}
