{
  "type": "Feature",
  "properties": {
    "iso:country":"GB",
    "wof:name":"GU47 0YG",
    "wof:placetype":"postalcode"
},
  "geometry": {"coordinates":[-0.7822704165307,51.35801145762354],"type":"Point"}
}