{
  "type": "Feature",
  "properties": {
    "date:inception_lower":"1980-01-01",
    "date:inception_upper":"1980-01-31",
    "iso:country":"GB",
    "wof:name":"WR4 9BA",
    "wof:placetype":"postalcode"
},
  "geometry": {"coordinates":[-2.189737,52.199729],"type":"Point"}
}