{
  "type": "Feature",
  "properties": {
    "iso:country": "GB",
    "wof:name": "WR4 9BA",
    "wof:placetype": "postalcode"
  },
  "geometry": {"coordinates":[-2.189737,52.199729],"type":"Point"}
}
