{
  "type": "Feature",
  "properties": {
    "date:inception_lower": "1997-12-01",
    "date:inception_upper": "1997-12-01",
    "iso:country": "GB",
    "wof:name": "GU34 1TS",
    "wof:placetype": "postalcode"
  },
  "geometry": {"coordinates":[-0.972343,51.150189],"type":"Point"}
}
