{
  "type": "Feature",
  "properties": {
    "iso:country":"GB",
    "wof:name":"GU34 1TS",
    "wof:placetype":"postalcode"
},
  "geometry": {"coordinates":[-0.97234307450678,51.15018946730194],"type":"Point"}
}