{
  "type": "Feature",
  "properties": {
    "iso:country":"GB",
    "wof:name":"NN2 6BW",
    "wof:placetype":"postalcode"
},
  "geometry": {"coordinates":[-0.90383954499053,52.24708378404561],"type":"Point"}
}