{
  "type": "Feature",
  "properties": {
    "date:inception_lower": "1992-08-01",
    "date:inception_upper": "1992-08-01",
    "iso:country": "GB",
    "wof:name": "NN15 6XG",
    "wof:placetype": "postalcode"
  },
  "geometry": {"coordinates":[-0.715021,52.377632],"type":"Point"}
}
