{
  "type": "Feature",
  "properties": {
    "iso:country": "GB",
    "wof:name": "DL10 6TG",
    "wof:placetype": "postalcode"
  },
  "geometry": {"coordinates":[-1.615197,54.394593],"type":"Point"}
}
