{
  "type": "Feature",
  "properties": {
    "iso:country":"GB",
    "wof:name":"CR8 3PN",
    "wof:placetype":"postalcode"
},
  "geometry": {"coordinates":[-0.13878774548786,51.34605744674267],"type":"Point"}
}