{
  "type": "Feature",
  "properties": {
    "iso:country": "GB",
    "wof:name": "CR8 3PN",
    "wof:placetype": "postalcode"
  },
  "geometry": {"coordinates":[-0.138788,51.346057],"type":"Point"}
}
