{
  "type": "Feature",
  "properties": {
    "date:inception_lower": "1980-01-01",
    "date:inception_upper": "1980-01-01",
    "iso:country": "GB",
    "wof:name": "B6 7HH",
    "wof:placetype": "postalcode"
  },
  "geometry": {"coordinates":[-1.882074,52.524449],"type":"Point"}
}
