{
  "type": "Feature",
  "properties": {
    "date:inception_lower":"1981-09-01",
    "date:inception_upper":"1981-09-30",
    "iso:country":"GB",
    "wof:name":"SY2 5YU",
    "wof:placetype":"postalcode"
},
  "geometry": {"coordinates":[-2.719352,52.705319],"type":"Point"}
}