{
  "type": "Feature",
  "properties": {
    "iso:country": "GB",
    "wof:name": "SY2 5YU",
    "wof:placetype": "postalcode"
  },
  "geometry": {"coordinates":[-2.719352,52.705319],"type":"Point"}
}
