{
  "type": "Feature",
  "properties": {
    "iso:country":"GB",
    "wof:name":"SY2 5YU",
    "wof:placetype":"postalcode"
},
  "geometry": {"coordinates":[-2.71935196052668,52.70531896599739],"type":"Point"}
}