{
  "type": "Feature",
  "properties": {
    "iso:country": "GB",
    "wof:name": "PE12 0QG",
    "wof:placetype": "postalcode"
  },
  "geometry": {"coordinates":[-0.020519,52.681235],"type":"Point"}
}
