{
  "type": "Feature",
  "properties": {
    "iso:country":"GB",
    "wof:name":"PE12 0QG",
    "wof:placetype":"postalcode"
},
  "geometry": {"coordinates":[-0.02047590303771,52.68122379145042],"type":"Point"}
}