{
  "type": "Feature",
  "properties": {
    "iso:country": "GB",
    "wof:name": "WA16 0JG",
    "wof:placetype": "postalcode"
  },
  "geometry": {"coordinates":[-2.453373,53.303089],"type":"Point"}
}
