{
  "type": "Feature",
  "properties": {
    "iso:country":"GB",
    "wof:name":"WA16 0JG",
    "wof:placetype":"postalcode"
},
  "geometry": {"coordinates":[-2.45337337825297,53.3030886092084],"type":"Point"}
}