{
  "type": "Feature",
  "properties": {
    "iso:country":"GB",
    "wof:name":"SG6 2BJ",
    "wof:placetype":"postalcode"
},
  "geometry": {"coordinates":[-0.21631676493926,51.97122473770943],"type":"Point"}
}