{
  "type": "Feature",
  "properties": {
    "iso:country":"GB",
    "wof:name":"CF35 6JR",
    "wof:placetype":"postalcode"
},
  "geometry": {"coordinates":[-3.51891474787373,51.52760606483149],"type":"Point"}
}