{
  "type": "Feature",
  "properties": {
    "iso:country": "GB",
    "wof:name": "CF35 6JR",
    "wof:placetype": "postalcode"
  },
  "geometry": {"coordinates":[-3.518915,51.527606],"type":"Point"}
}
