{
  "type": "Feature",
  "properties": {
    "iso:country":"GB",
    "wof:name":"NW10 5LR",
    "wof:placetype":"postalcode"
},
  "geometry": {"coordinates":[-0.21755109399105,51.52933616105146],"type":"Point"}
}