{
  "type": "Feature",
  "properties": {
    "iso:country": "GB",
    "wof:name": "CF32 7EH",
    "wof:placetype": "postalcode"
  },
  "geometry": {"coordinates":[-3.543347,51.605076],"type":"Point"}
}
