{
  "type": "Feature",
  "properties": {
    "date:inception_lower": "2023-07-01",
    "date:inception_upper": "2023-07-01",
    "iso:country": "GB",
    "wof:name": "TN19 7YQ",
    "wof:placetype": "postalcode"
  },
  "geometry": {"coordinates":[0.435649,51.008236],"type":"Point"}
}
