{
  "type": "Feature",
  "properties": {
    "iso:country": "GB",
    "wof:name": "ME5 7HX",
    "wof:placetype": "postalcode"
  },
  "geometry": {"coordinates":[0.5563,51.370496],"type":"Point"}
}
