{
  "type": "Feature",
  "properties": {
    "iso:country": "GB",
    "wof:name": "CT3 3ND",
    "wof:placetype": "postalcode"
  },
  "geometry": {"coordinates":[1.2033,51.231681],"type":"Point"}
}
