{
  "type": "Feature",
  "properties": {
    "iso:country":"GB",
    "wof:name":"EX32 0EH",
    "wof:placetype":"postalcode"
},
  "geometry": {"coordinates":[-4.00871468792537,51.06180353568647],"type":"Point"}
}