{
  "type": "Feature",
  "properties": {
    "date:inception_lower":"1985-10-01",
    "date:inception_upper":"1985-10-31",
    "iso:country":"GB",
    "wof:name":"EX32 0EH",
    "wof:placetype":"postalcode"
},
  "geometry": {"coordinates":[-4.008715,51.061804],"type":"Point"}
}