{
  "type": "Feature",
  "properties": {
    "date:inception_lower": "1991-09-01",
    "date:inception_upper": "1991-09-01",
    "iso:country": "GB",
    "wof:name": "CA13 0LF",
    "wof:placetype": "postalcode"
  },
  "geometry": {"coordinates":[-3.436027,54.671117],"type":"Point"}
}
