{
  "type": "Feature",
  "properties": {
    "iso:country": "GB",
    "wof:name": "CA13 0LF",
    "wof:placetype": "postalcode"
  },
  "geometry": {"coordinates":[-3.436027,54.671117],"type":"Point"}
}
