{
  "type": "Feature",
  "properties": {
    "iso:country":"GB",
    "wof:name":"WD25 0JU",
    "wof:placetype":"postalcode"
},
  "geometry": {"coordinates":[-0.39090555630352,51.70273669914688],"type":"Point"}
}