{
  "type": "Feature",
  "properties": {
    "date:inception_lower": "1992-08-01",
    "date:inception_upper": "1992-08-01",
    "iso:country": "GB",
    "wof:name": "MK7 7HR",
    "wof:placetype": "postalcode"
  },
  "geometry": {"coordinates":[-0.698908,52.014724],"type":"Point"}
}
