{
  "type": "Feature",
  "properties": {
    "iso:country":"GB",
    "wof:name":"MK7 7HR",
    "wof:placetype":"postalcode"
},
  "geometry": {"coordinates":[-0.69890771549216,52.01472421985677],"type":"Point"}
}