{
  "type": "Feature",
  "properties": {
    "iso:country":"GB",
    "wof:name":"DE56 1UY",
    "wof:placetype":"postalcode"
},
  "geometry": {"coordinates":[-1.48255849308351,53.01723977968013],"type":"Point"}
}