{
  "type": "Feature",
  "properties": {
    "date:inception_lower": "1992-08-01",
    "date:inception_upper": "1992-08-01",
    "iso:country": "GB",
    "wof:name": "DE56 1UY",
    "wof:placetype": "postalcode"
  },
  "geometry": {"coordinates":[-1.482558,53.01724],"type":"Point"}
}
