{
  "type": "Feature",
  "properties": {
    "iso:country":"GB",
    "wof:name":"SP3 4LL",
    "wof:placetype":"postalcode"
},
  "geometry": {"coordinates":[-1.89930741476491,51.13317639468939],"type":"Point"}
}