{
  "type": "Feature",
  "properties": {
    "iso:country":"GB",
    "wof:name":"DL14 9RB",
    "wof:placetype":"postalcode"
},
  "geometry": {"coordinates":[-1.76286164121241,54.62203638458602],"type":"Point"}
}