{
  "type": "Feature",
  "properties": {
    "iso:country":"GB",
    "wof:name":"BS6 5QB",
    "wof:placetype":"postalcode"
},
  "geometry": {"coordinates":[-2.58758291749959,51.46656371095096],"type":"Point"}
}