{
  "type": "Feature",
  "properties": {
    "iso:country": "GB",
    "wof:name": "BS6 5QB",
    "wof:placetype": "postalcode"
  },
  "geometry": {"coordinates":[-2.587583,51.466564],"type":"Point"}
}
