{
  "type": "Feature",
  "properties": {
    "iso:country":"GB",
    "wof:name":"N1 0JF",
    "wof:placetype":"postalcode"
},
  "geometry": {"coordinates":[-0.11193355057484,51.53556118976807],"type":"Point"}
}