{
  "type": "Feature",
  "properties": {
    "iso:country": "GB",
    "wof:name": "L33 1TD",
    "wof:placetype": "postalcode"
  },
  "geometry": {"coordinates":[-2.875567,53.496495],"type":"Point"}
}
