{
  "type": "Feature",
  "properties": {
    "iso:country":"GB",
    "wof:name":"L33 1TD",
    "wof:placetype":"postalcode"
},
  "geometry": {"coordinates":[-2.87556752334345,53.49649529864511],"type":"Point"}
}