{
  "type": "Feature",
  "properties": {
    "date:inception_lower":"1996-12-01",
    "date:inception_upper":"1996-12-31",
    "iso:country":"GB",
    "wof:name":"L33 1TD",
    "wof:placetype":"postalcode"
},
  "geometry": {"coordinates":[-2.875567,53.496495],"type":"Point"}
}