{
  "type": "Feature",
  "properties": {
    "iso:country": "GB",
    "wof:name": "OL1 2PT",
    "wof:placetype": "postalcode"
  },
  "geometry": {"coordinates":[-2.133166,53.552966],"type":"Point"}
}
