{
  "type": "Feature",
  "properties": {
    "iso:country":"GB",
    "wof:name":"OL1 2PT",
    "wof:placetype":"postalcode"
},
  "geometry": {"coordinates":[-2.13316575432795,53.55296641376495],"type":"Point"}
}