{
  "type": "Feature",
  "properties": {
    "date:inception_lower": "1980-01-01",
    "date:inception_upper": "1980-01-01",
    "iso:country": "GB",
    "wof:name": "OL1 2PT",
    "wof:placetype": "postalcode"
  },
  "geometry": {"coordinates":[-2.133166,53.552966],"type":"Point"}
}
