{
  "type": "Feature",
  "properties": {
    "iso:country":"GB",
    "wof:name":"GU15 3TU",
    "wof:placetype":"postalcode"
},
  "geometry": {"coordinates":[-0.7283925048311,51.3431415703823],"type":"Point"}
}