{
  "type": "Feature",
  "properties": {
    "iso:country": "GB",
    "wof:name": "GU15 3TU",
    "wof:placetype": "postalcode"
  },
  "geometry": {"coordinates":[-0.728964,51.343147],"type":"Point"}
}
