{
  "type": "Feature",
  "properties": {
    "date:inception_lower": "2004-02-01",
    "date:inception_upper": "2004-02-01",
    "iso:country": "GB",
    "wof:name": "SE12 9DQ",
    "wof:placetype": "postalcode"
  },
  "geometry": {"coordinates":[0.025734,51.444389],"type":"Point"}
}
