{
  "type": "Feature",
  "properties": {
    "date:inception_lower": "1986-01-01",
    "date:inception_upper": "1986-01-01",
    "iso:country": "GB",
    "wof:name": "SO51 0NX",
    "wof:placetype": "postalcode"
  },
  "geometry": {"coordinates":[-1.519288,51.033025],"type":"Point"}
}
