{
  "type": "Feature",
  "properties": {
    "iso:country":"GB",
    "wof:name":"TD8 6HL",
    "wof:placetype":"postalcode"
},
  "geometry": {"coordinates":[-2.5477827030639,55.48214136828321],"type":"Point"}
}