{
  "type": "Feature",
  "properties": {
    "iso:country":"GB",
    "wof:name":"KT2 7JS",
    "wof:placetype":"postalcode"
},
  "geometry": {"coordinates":[-0.27298104305728,51.42609613227621],"type":"Point"}
}