{
  "type": "Feature",
  "properties": {
    "iso:country":"GB",
    "wof:name":"RH16 3EE",
    "wof:placetype":"postalcode"
},
  "geometry": {"coordinates":[-0.10237855028483,51.00371160627923],"type":"Point"}
}