{
  "type": "Feature",
  "properties": {
    "iso:country":"GB",
    "wof:name":"N3 3RT",
    "wof:placetype":"postalcode"
},
  "geometry": {"coordinates":[-0.20040885584183,51.59658915220771],"type":"Point"}
}