{
  "type": "Feature",
  "properties": {
    "iso:country":"GB",
    "wof:name":"DE4 2FL",
    "wof:placetype":"postalcode"
},
  "geometry": {"coordinates":[-1.57494873618856,53.16432563740712],"type":"Point"}
}