{
  "type": "Feature",
  "properties": {
    "iso:country": "GB",
    "wof:name": "NG21 9PN",
    "wof:placetype": "postalcode"
  },
  "geometry": {"coordinates":[-1.070254,53.191122],"type":"Point"}
}
