{
  "type": "Feature",
  "properties": {
    "iso:country": "GB",
    "wof:name": "BD7 4HB",
    "wof:placetype": "postalcode"
  },
  "geometry": {"coordinates":[-1.787108,53.77832],"type":"Point"}
}
