{
  "type": "Feature",
  "properties": {
    "iso:country":"GB",
    "wof:name":"BD7 4HB",
    "wof:placetype":"postalcode"
},
  "geometry": {"coordinates":[-1.7871075855678,53.77832017043622],"type":"Point"}
}