{
  "type": "Feature",
  "properties": {
    "iso:country": "GB",
    "wof:name": "CV34 5FE",
    "wof:placetype": "postalcode"
  },
  "geometry": {"coordinates":[-1.590028,52.296807],"type":"Point"}
}
