{
  "type": "Feature",
  "properties": {
    "date:inception_lower": "1980-02-01",
    "date:inception_upper": "1980-02-01",
    "iso:country": "GB",
    "wof:name": "KY6 2SF",
    "wof:placetype": "postalcode"
  },
  "geometry": {"coordinates":[-3.198717,56.175379],"type":"Point"}
}
