{
  "type": "Feature",
  "properties": {
    "iso:country": "GB",
    "wof:name": "YO1 7BP",
    "wof:placetype": "postalcode"
  },
  "geometry": {"coordinates":[-1.078514,53.960351],"type":"Point"}
}
