{
  "type": "Feature",
  "properties": {
    "iso:country":"GB",
    "wof:name":"YO1 7BP",
    "wof:placetype":"postalcode"
},
  "geometry": {"coordinates":[-1.07851393443358,53.96035141033068],"type":"Point"}
}