{
  "type": "Feature",
  "properties": {
    "iso:country":"GB",
    "wof:name":"SY14 7BY",
    "wof:placetype":"postalcode"
},
  "geometry": {"coordinates":[-2.82655651786398,53.00498162628673],"type":"Point"}
}