{
  "type": "Feature",
  "properties": {
    "date:inception_lower": "2011-05-01",
    "date:inception_upper": "2011-05-01",
    "iso:country": "GB",
    "wof:name": "SY14 7BY",
    "wof:placetype": "postalcode"
  },
  "geometry": {"coordinates":[-2.826004,53.004965],"type":"Point"}
}
