{
  "type": "Feature",
  "properties": {
    "iso:country": "GB",
    "wof:name": "SY14 7BY",
    "wof:placetype": "postalcode"
  },
  "geometry": {"coordinates":[-2.826556,53.004997],"type":"Point"}
}
