{
  "type": "Feature",
  "properties": {
    "date:inception_lower":"2005-02-01",
    "date:inception_upper":"2005-02-28",
    "iso:country":"GB",
    "wof:name":"OX14 9TJ",
    "wof:placetype":"postalcode"
},
  "geometry": {"coordinates":[-1.279902,51.670592],"type":"Point"}
}