{
  "type": "Feature",
  "properties": {
    "date:inception_lower": "2005-01-01",
    "date:inception_upper": "2005-01-01",
    "iso:country": "GB",
    "wof:name": "SW1P 4DF",
    "wof:placetype": "postalcode"
  },
  "geometry": {"coordinates":[-0.12981,51.495867],"type":"Point"}
}
