{
  "type": "Feature",
  "properties": {
    "iso:country":"GB",
    "wof:name":"SW1P 4DF",
    "wof:placetype":"postalcode"
},
  "geometry": {"coordinates":[-0.129810494656,51.4958668307909],"type":"Point"}
}