{
  "type": "Feature",
  "properties": {
    "iso:country":"GB",
    "wof:name":"NR16 1JE",
    "wof:placetype":"postalcode"
},
  "geometry": {"coordinates":[1.20211800986988,52.48679118489415],"type":"Point"}
}