{
  "type": "Feature",
  "properties": {
    "iso:country":"GB",
    "wof:name":"TW5 0LQ",
    "wof:placetype":"postalcode"
},
  "geometry": {"coordinates":[-0.37367367913922,51.48515036197318],"type":"Point"}
}