{
  "type": "Feature",
  "properties": {
    "iso:country": "GB",
    "wof:name": "NE37 3EA",
    "wof:placetype": "postalcode"
  },
  "geometry": {"coordinates":[-1.507813,54.914808],"type":"Point"}
}
