{
  "type": "Feature",
  "properties": {
    "iso:country":"GB",
    "wof:name":"WA13 9AH",
    "wof:placetype":"postalcode"
},
  "geometry": {"coordinates":[-2.48183952201997,53.3843249987248],"type":"Point"}
}