{
  "type": "Feature",
  "properties": {
    "date:inception_lower":"1981-06-01",
    "date:inception_upper":"1981-06-30",
    "iso:country":"GB",
    "wof:name":"LS21 2RZ",
    "wof:placetype":"postalcode"
},
  "geometry": {"coordinates":[-1.605951,53.91438],"type":"Point"}
}