{
  "type": "Feature",
  "properties": {
    "iso:country":"GB",
    "wof:name":"LS21 2RZ",
    "wof:placetype":"postalcode"
},
  "geometry": {"coordinates":[-1.60592101355961,53.91437091713904],"type":"Point"}
}