{
  "type": "Feature",
  "properties": {
    "iso:country": "GB",
    "wof:name": "LS21 2RZ",
    "wof:placetype": "postalcode"
  },
  "geometry": {"coordinates":[-1.605951,53.91438],"type":"Point"}
}
