{
  "type": "Feature",
  "properties": {
    "iso:country": "GB",
    "wof:name": "NR12 7DE",
    "wof:placetype": "postalcode"
  },
  "geometry": {"coordinates":[1.33192,52.686201],"type":"Point"}
}
