{
  "type": "Feature",
  "properties": {
    "date:inception_lower":"2009-02-01",
    "date:inception_upper":"2009-02-28",
    "iso:country":"GB",
    "wof:name":"SA73 2RS",
    "wof:placetype":"postalcode"
},
  "geometry": {"coordinates":[-5.030093,51.727718],"type":"Point"}
}