{
  "type": "Feature",
  "properties": {
    "date:inception_lower": "2020-06-01",
    "date:inception_upper": "2020-06-01",
    "iso:country": "GB",
    "wof:name": "CA11 9FY",
    "wof:placetype": "postalcode"
  },
  "geometry": {"coordinates":[-2.769067,54.66332],"type":"Point"}
}
