{
  "type": "Feature",
  "properties": {
    "date:inception_lower": "1998-12-01",
    "date:inception_upper": "1998-12-01",
    "iso:country": "GB",
    "wof:name": "NG12 4GP",
    "wof:placetype": "postalcode"
  },
  "geometry": {"coordinates":[-1.104363,52.916298],"type":"Point"}
}
