{
  "type": "Feature",
  "properties": {
    "iso:country": "GB",
    "wof:name": "NG12 4GP",
    "wof:placetype": "postalcode"
  },
  "geometry": {"coordinates":[-1.104363,52.916298],"type":"Point"}
}
