{
  "type": "Feature",
  "properties": {
    "iso:country":"GB",
    "wof:name":"WN8 6SD",
    "wof:placetype":"postalcode"
},
  "geometry": {"coordinates":[-2.78027440806972,53.56250270410423],"type":"Point"}
}