{
  "type": "Feature",
  "properties": {
    "iso:country": "GB",
    "wof:name": "WN8 6SD",
    "wof:placetype": "postalcode"
  },
  "geometry": {"coordinates":[-2.780274,53.562503],"type":"Point"}
}
