{
  "type": "Feature",
  "properties": {
    "iso:country":"GB",
    "wof:name":"EH49 7BQ",
    "wof:placetype":"postalcode"
},
  "geometry": {"coordinates":[-3.61512347972643,55.97587633636933],"type":"Point"}
}