{
  "type": "Feature",
  "properties": {
    "date:inception_lower":"1995-12-01",
    "date:inception_upper":"1995-12-31",
    "iso:country":"GB",
    "wof:name":"FK1 4EE",
    "wof:placetype":"postalcode"
},
  "geometry": {"coordinates":[-3.812152,56.003007],"type":"Point"}
}