{
  "type": "Feature",
  "properties": {
    "iso:country":"GB",
    "wof:name":"FK1 4EE",
    "wof:placetype":"postalcode"
},
  "geometry": {"coordinates":[-3.81215185094512,56.00300718678867],"type":"Point"}
}