{
  "type": "Feature",
  "properties": {
    "iso:country":"GB",
    "wof:name":"HR9 5PR",
    "wof:placetype":"postalcode"
},
  "geometry": {"coordinates":[-2.58710107729268,51.90421701068397],"type":"Point"}
}