{
  "type": "Feature",
  "properties": {
    "iso:country":"GB",
    "wof:name":"RM16 6QR",
    "wof:placetype":"postalcode"
},
  "geometry": {"coordinates":[0.31800497399982,51.49136742762163],"type":"Point"}
}