{
  "type": "Feature",
  "properties": {
    "iso:country":"GB",
    "wof:name":"PE9 3TG",
    "wof:placetype":"postalcode"
},
  "geometry": {"coordinates":[-0.55535096605726,52.62998135599938],"type":"Point"}
}