{
  "type": "Feature",
  "properties": {
    "iso:country": "GB",
    "wof:name": "BN22 0UX",
    "wof:placetype": "postalcode"
  },
  "geometry": {"coordinates":[0.267912,50.808886],"type":"Point"}
}
