{
  "type": "Feature",
  "properties": {
    "iso:country":"GB",
    "wof:name":"CO4 5XH",
    "wof:placetype":"postalcode"
},
  "geometry": {"coordinates":[0.90370775762214,51.90728244293948],"type":"Point"}
}