{
  "type": "Feature",
  "properties": {
    "date:inception_lower": "1994-12-01",
    "date:inception_upper": "1994-12-01",
    "iso:country": "GB",
    "wof:name": "BA21 5HZ",
    "wof:placetype": "postalcode"
  },
  "geometry": {"coordinates":[-2.604323,50.952558],"type":"Point"}
}
