{
  "type": "Feature",
  "properties": {
    "iso:country":"GB",
    "wof:name":"BA21 5HZ",
    "wof:placetype":"postalcode"
},
  "geometry": {"coordinates":[-2.60432296080902,50.95255768441682],"type":"Point"}
}