{
  "type": "Feature",
  "properties": {
    "date:inception_lower":"1992-08-01",
    "date:inception_upper":"1992-08-31",
    "iso:country":"GB",
    "wof:name":"SW11 4BL",
    "wof:placetype":"postalcode"
},
  "geometry": {"coordinates":[-0.151932,51.476443],"type":"Point"}
}