{
  "type": "Feature",
  "properties": {
    "iso:country":"GB",
    "wof:name":"SS7 1FN",
    "wof:placetype":"postalcode"
},
  "geometry": {"coordinates":[0.5913674258497,51.56296955634166],"type":"Point"}
}