{
  "type": "Feature",
  "properties": {
    "iso:country":"GB",
    "wof:name":"E16 1AY",
    "wof:placetype":"postalcode"
},
  "geometry": {"coordinates":[0.02287769835596,51.50771166746026],"type":"Point"}
}