{
  "type": "Feature",
  "properties": {
    "iso:country":"GB",
    "wof:name":"RG9 4JP",
    "wof:placetype":"postalcode"
},
  "geometry": {"coordinates":[-0.95421324635941,51.50867687825598],"type":"Point"}
}