{
  "type": "Feature",
  "properties": {
    "date:inception_lower": "1980-01-01",
    "date:inception_upper": "1980-01-01",
    "iso:country": "GB",
    "wof:name": "RG9 4JP",
    "wof:placetype": "postalcode"
  },
  "geometry": {"coordinates":[-0.954193,51.508679],"type":"Point"}
}
