{
  "type": "Feature",
  "properties": {
    "iso:country":"GB",
    "wof:name":"WV8 1ND",
    "wof:placetype":"postalcode"
},
  "geometry": {"coordinates":[-2.18345727591777,52.63053452673687],"type":"Point"}
}