{
  "type": "Feature",
  "properties": {
    "date:inception_lower":"1980-01-01",
    "date:inception_upper":"1980-01-31",
    "iso:country":"GB",
    "wof:name":"WR15 8TH",
    "wof:placetype":"postalcode"
},
  "geometry": {"coordinates":[-2.625455,52.302423],"type":"Point"}
}