{
  "type": "Feature",
  "properties": {
    "iso:country":"GB",
    "wof:name":"WR15 8TH",
    "wof:placetype":"postalcode"
},
  "geometry": {"coordinates":[-2.62545544295133,52.30242275456092],"type":"Point"}
}