{
  "type": "Feature",
  "properties": {
    "iso:country": "GB",
    "wof:name": "NE34 8EW",
    "wof:placetype": "postalcode"
  },
  "geometry": {"coordinates":[-1.407309,54.966606],"type":"Point"}
}
