{
  "type": "Feature",
  "properties": {
    "date:inception_lower": "2011-07-01",
    "date:inception_upper": "2011-07-01",
    "iso:country": "GB",
    "wof:name": "NE34 8EW",
    "wof:placetype": "postalcode"
  },
  "geometry": {"coordinates":[-1.407309,54.966606],"type":"Point"}
}
