{
  "type": "Feature",
  "properties": {
    "date:inception_lower": "2000-06-01",
    "date:inception_upper": "2000-06-01",
    "iso:country": "GB",
    "wof:name": "SG1 6BB",
    "wof:placetype": "postalcode"
  },
  "geometry": {"coordinates":[-0.170415,51.9302],"type":"Point"}
}
