{
  "type": "Feature",
  "properties": {
    "iso:country": "GB",
    "wof:name": "DL1 2LG",
    "wof:placetype": "postalcode"
  },
  "geometry": {"coordinates":[-1.532102,54.535219],"type":"Point"}
}
