{
  "type": "Feature",
  "properties": {
    "date:inception_lower":"1996-06-01",
    "date:inception_upper":"1996-06-30",
    "iso:country":"GB",
    "wof:name":"CF42 5AB",
    "wof:placetype":"postalcode"
},
  "geometry": {"coordinates":[-3.528622,51.670151],"type":"Point"}
}