{
  "type": "Feature",
  "properties": {
    "iso:country": "GB",
    "wof:name": "CF42 5AB",
    "wof:placetype": "postalcode"
  },
  "geometry": {"coordinates":[-3.528622,51.670151],"type":"Point"}
}
