{
  "type": "Feature",
  "properties": {
    "iso:country": "GB",
    "wof:name": "IP28 8EP",
    "wof:placetype": "postalcode"
  },
  "geometry": {"coordinates":[0.470776,52.376088],"type":"Point"}
}
