{
  "type": "Feature",
  "properties": {
    "iso:country":"GB",
    "wof:name":"IP28 8EP",
    "wof:placetype":"postalcode"
},
  "geometry": {"coordinates":[0.4707057866841,52.37607158691371],"type":"Point"}
}