{
  "type": "Feature",
  "properties": {
    "iso:country": "GB",
    "wof:name": "DN22 9AW",
    "wof:placetype": "postalcode"
  },
  "geometry": {"coordinates":[-0.892691,53.392229],"type":"Point"}
}
