{
  "type": "Feature",
  "properties": {
    "iso:country":"GB",
    "wof:name":"NG6 0EU",
    "wof:placetype":"postalcode"
},
  "geometry": {"coordinates":[-1.1791030002438,52.99139651875482],"type":"Point"}
}