{
  "type": "Feature",
  "properties": {
    "iso:country":"GB",
    "wof:name":"BS5 0NL",
    "wof:placetype":"postalcode"
},
  "geometry": {"coordinates":[-2.56726042651843,51.46807551002382],"type":"Point"}
}