{
  "type": "Feature",
  "properties": {
    "iso:country": "GB",
    "wof:name": "SS2 4SE",
    "wof:placetype": "postalcode"
  },
  "geometry": {"coordinates":[0.747864,51.548498],"type":"Point"}
}
