{
  "type": "Feature",
  "properties": {
    "iso:country":"GB",
    "wof:name":"BS24 7AG",
    "wof:placetype":"postalcode"
},
  "geometry": {"coordinates":[-2.89661987360756,51.33281348652202],"type":"Point"}
}