{
  "type": "Feature",
  "properties": {
    "iso:country":"GB",
    "wof:name":"SG9 0AA",
    "wof:placetype":"postalcode"
},
  "geometry": {"coordinates":[0.00197979931595,51.94778892165877],"type":"Point"}
}