{
  "type": "Feature",
  "properties": {
    "iso:country": "GB",
    "wof:name": "SG9 0AA",
    "wof:placetype": "postalcode"
  },
  "geometry": {"coordinates":[0.00198,51.947789],"type":"Point"}
}
