{
  "type": "Feature",
  "properties": {
    "iso:country":"GB",
    "wof:name":"GL20 7NP",
    "wof:placetype":"postalcode"
},
  "geometry": {"coordinates":[-2.06457703042906,52.03575176124978],"type":"Point"}
}