{
  "type": "Feature",
  "properties": {
    "iso:country": "GB",
    "wof:name": "DH8 8AH",
    "wof:placetype": "postalcode"
  },
  "geometry": {"coordinates":[-1.854731,54.8437],"type":"Point"}
}
