{
  "type": "Feature",
  "properties": {
    "date:inception_lower": "1980-01-01",
    "date:inception_upper": "1980-01-01",
    "iso:country": "GB",
    "wof:name": "DH8 8AH",
    "wof:placetype": "postalcode"
  },
  "geometry": {"coordinates":[-1.854731,54.8437],"type":"Point"}
}
