{
  "type": "Feature",
  "properties": {
    "iso:country":"GB",
    "wof:name":"DH8 8AH",
    "wof:placetype":"postalcode"
},
  "geometry": {"coordinates":[-1.8547310718602,54.84369998214318],"type":"Point"}
}