{
  "type": "Feature",
  "properties": {
    "iso:country": "GB",
    "wof:name": "NN8 4HU",
    "wof:placetype": "postalcode"
  },
  "geometry": {"coordinates":[-0.6956,52.301695],"type":"Point"}
}
