{
  "type": "Feature",
  "properties": {
    "date:inception_lower":"2018-01-01",
    "date:inception_upper":"2018-01-31",
    "iso:country":"GB",
    "wof:name":"NN8 4HU",
    "wof:placetype":"postalcode"
},
  "geometry": {"coordinates":[-0.6956,52.301695],"type":"Point"}
}