{
  "type": "Feature",
  "properties": {
    "date:inception_lower": "2018-01-01",
    "date:inception_upper": "2018-01-01",
    "iso:country": "GB",
    "wof:name": "NN8 4HU",
    "wof:placetype": "postalcode"
  },
  "geometry": {"coordinates":[-0.695585,52.301731],"type":"Point"}
}
