{
  "type": "Feature",
  "properties": {
    "iso:country":"GB",
    "wof:name":"NE24 4QH",
    "wof:placetype":"postalcode"
},
  "geometry": {"coordinates":[-1.53282298956462,55.11496672228705],"type":"Point"}
}