{
  "type": "Feature",
  "properties": {
    "iso:country":"GB",
    "wof:name":"M35 0SF",
    "wof:placetype":"postalcode"
},
  "geometry": {"coordinates":[-2.15638519139955,53.50115623398618],"type":"Point"}
}