{
  "type": "Feature",
  "properties": {
    "date:inception_lower":"1980-01-01",
    "date:inception_upper":"1980-01-31",
    "iso:country":"GB",
    "wof:name":"M35 0SF",
    "wof:placetype":"postalcode"
},
  "geometry": {"coordinates":[-2.156384,53.501172],"type":"Point"}
}