{
  "type": "Feature",
  "properties": {
    "date:inception_lower":"1980-01-01",
    "date:inception_upper":"1980-01-31",
    "iso:country":"GB",
    "wof:name":"WA14 3HW",
    "wof:placetype":"postalcode"
},
  "geometry": {"coordinates":[-2.347772,53.372459],"type":"Point"}
}