{
  "type": "Feature",
  "properties": {
    "iso:country":"GB",
    "wof:name":"WA14 3HW",
    "wof:placetype":"postalcode"
},
  "geometry": {"coordinates":[-2.34777174345955,53.37245867397372],"type":"Point"}
}