{
  "type": "Feature",
  "properties": {
    "iso:country":"GB",
    "wof:name":"EH19 2PT",
    "wof:placetype":"postalcode"
},
  "geometry": {"coordinates":[-3.12126892890291,55.86869950420451],"type":"Point"}
}