{
  "type": "Feature",
  "properties": {
    "iso:country":"GB",
    "wof:name":"SY23 3RB",
    "wof:placetype":"postalcode"
},
  "geometry": {"coordinates":[-4.06069106765371,52.40714074478648],"type":"Point"}
}