{
  "type": "Feature",
  "properties": {
    "iso:country": "GB",
    "wof:name": "WF3 4EA",
    "wof:placetype": "postalcode"
  },
  "geometry": {"coordinates":[-1.477335,53.7168],"type":"Point"}
}
