{
  "type": "Feature",
  "properties": {
    "date:inception_lower": "2001-12-01",
    "date:inception_upper": "2001-12-01",
    "iso:country": "GB",
    "wof:name": "BS8 2RB",
    "wof:placetype": "postalcode"
  },
  "geometry": {"coordinates":[-2.613173,51.467224],"type":"Point"}
}
