{
  "type": "Feature",
  "properties": {
    "iso:country":"GB",
    "wof:name":"TW9 1XP",
    "wof:placetype":"postalcode"
},
  "geometry": {"coordinates":[-0.28998902731008,51.46292673570188],"type":"Point"}
}