{
  "type": "Feature",
  "properties": {
    "date:inception_lower": "1991-09-01",
    "date:inception_upper": "1991-09-01",
    "iso:country": "GB",
    "wof:name": "NP44 7NZ",
    "wof:placetype": "postalcode"
  },
  "geometry": {"coordinates":[-3.03022,51.640394],"type":"Point"}
}
