{
  "type": "Feature",
  "properties": {
    "iso:country": "GB",
    "wof:name": "NP44 7NZ",
    "wof:placetype": "postalcode"
  },
  "geometry": {"coordinates":[-3.03022,51.640394],"type":"Point"}
}
