{
  "type": "Feature",
  "properties": {
    "iso:country":"GB",
    "wof:name":"NP44 7NZ",
    "wof:placetype":"postalcode"
},
  "geometry": {"coordinates":[-3.03022012848134,51.64039415943219],"type":"Point"}
}