{
  "type": "Feature",
  "properties": {
    "iso:country":"GB",
    "wof:name":"CW4 7JT",
    "wof:placetype":"postalcode"
},
  "geometry": {"coordinates":[-2.36904408721197,53.20078093569921],"type":"Point"}
}