{
  "type": "Feature",
  "properties": {
    "iso:country":"GB",
    "wof:name":"DG1 1PA",
    "wof:placetype":"postalcode"
},
  "geometry": {"coordinates":[-3.60022874027067,55.07799160590484],"type":"Point"}
}