{
  "type": "Feature",
  "properties": {
    "iso:country": "GB",
    "wof:name": "DG1 1PA",
    "wof:placetype": "postalcode"
  },
  "geometry": {"coordinates":[-3.600229,55.077992],"type":"Point"}
}
