{
  "type": "Feature",
  "properties": {
    "date:inception_lower": "1999-12-01",
    "date:inception_upper": "1999-12-01",
    "iso:country": "GB",
    "wof:name": "DG1 1PA",
    "wof:placetype": "postalcode"
  },
  "geometry": {"coordinates":[-3.600229,55.077992],"type":"Point"}
}
