{
  "type": "Feature",
  "properties": {
    "iso:country":"GB",
    "wof:name":"L33 1SA",
    "wof:placetype":"postalcode"
},
  "geometry": {"coordinates":[-2.87666434678892,53.49778163200322],"type":"Point"}
}