{
  "type": "Feature",
  "properties": {
    "iso:country": "GB",
    "wof:name": "L33 1SA",
    "wof:placetype": "postalcode"
  },
  "geometry": {"coordinates":[-2.876664,53.497782],"type":"Point"}
}
