{
  "type": "Feature",
  "properties": {
    "iso:country":"GB",
    "wof:name":"CT5 2HX",
    "wof:placetype":"postalcode"
},
  "geometry": {"coordinates":[1.05333871165674,51.36173709951125],"type":"Point"}
}