{
  "type": "Feature",
  "properties": {
    "date:inception_lower": "1988-03-01",
    "date:inception_upper": "1988-03-01",
    "iso:country": "GB",
    "wof:name": "WS3 3UF",
    "wof:placetype": "postalcode"
  },
  "geometry": {"coordinates":[-2.017079,52.626388],"type":"Point"}
}
