{
  "type": "Feature",
  "properties": {
    "date:inception_lower":"2016-05-01",
    "date:inception_upper":"2016-05-31",
    "iso:country":"GB",
    "wof:name":"SN15 1JJ",
    "wof:placetype":"postalcode"
},
  "geometry": {"coordinates":[-2.144161,51.464891],"type":"Point"}
}