{
  "type": "Feature",
  "properties": {
    "iso:country": "GB",
    "wof:name": "SK8 2HB",
    "wof:placetype": "postalcode"
  },
  "geometry": {"coordinates":[-2.196451,53.39577],"type":"Point"}
}
