{
  "type": "Feature",
  "properties": {
    "iso:country":"GB",
    "wof:name":"SK8 2HB",
    "wof:placetype":"postalcode"
},
  "geometry": {"coordinates":[-2.19645091982079,53.39576978891886],"type":"Point"}
}