{
  "type": "Feature",
  "properties": {
    "iso:country":"GB",
    "wof:name":"RG7 2NR",
    "wof:placetype":"postalcode"
},
  "geometry": {"coordinates":[-1.10365936782109,51.35833881901761],"type":"Point"}
}