{
  "type": "Feature",
  "properties": {
    "iso:country": "GB",
    "wof:name": "RG7 2NR",
    "wof:placetype": "postalcode"
  },
  "geometry": {"coordinates":[-1.103659,51.358339],"type":"Point"}
}
