{
  "type": "Feature",
  "properties": {
    "iso:country": "GB",
    "wof:name": "NE65 7EF",
    "wof:placetype": "postalcode"
  },
  "geometry": {"coordinates":[-1.954339,55.313768],"type":"Point"}
}
