{
  "type": "Feature",
  "properties": {
    "iso:country":"GB",
    "wof:name":"KT22 9JB",
    "wof:placetype":"postalcode"
},
  "geometry": {"coordinates":[-0.35484657332943,51.29406795385741],"type":"Point"}
}