{
  "type": "Feature",
  "properties": {
    "iso:country":"GB",
    "wof:name":"WF14 8HN",
    "wof:placetype":"postalcode"
},
  "geometry": {"coordinates":[-1.70402797379955,53.66570286425907],"type":"Point"}
}