{
  "type": "Feature",
  "properties": {
    "date:inception_lower": "1980-01-01",
    "date:inception_upper": "1980-01-01",
    "iso:country": "GB",
    "wof:name": "IP14 2AA",
    "wof:placetype": "postalcode"
  },
  "geometry": {"coordinates":[1.001187,52.181839],"type":"Point"}
}
