{
  "type": "Feature",
  "properties": {
    "iso:country": "GB",
    "wof:name": "EH48 3DR",
    "wof:placetype": "postalcode"
  },
  "geometry": {"coordinates":[-3.698916,55.91593],"type":"Point"}
}
