{
  "type": "Feature",
  "properties": {
    "iso:country":"GB",
    "wof:name":"EH48 3DR",
    "wof:placetype":"postalcode"
},
  "geometry": {"coordinates":[-3.69930886001245,55.91521944716052],"type":"Point"}
}