{
  "type": "Feature",
  "properties": {
    "iso:country":"GB",
    "wof:name":"PL14 3RA",
    "wof:placetype":"postalcode"
},
  "geometry": {"coordinates":[-4.41212895254528,50.44184431585188],"type":"Point"}
}