{
  "type": "Feature",
  "properties": {
    "iso:country": "GB",
    "wof:name": "WF15 7JQ",
    "wof:placetype": "postalcode"
  },
  "geometry": {"coordinates":[-1.684617,53.705747],"type":"Point"}
}
