{
  "type": "Feature",
  "properties": {
    "iso:country":"GB",
    "wof:name":"WF15 7JQ",
    "wof:placetype":"postalcode"
},
  "geometry": {"coordinates":[-1.68485647737809,53.70581311161724],"type":"Point"}
}