{
  "type": "Feature",
  "properties": {
    "iso:country":"GB",
    "wof:name":"W10 6PZ",
    "wof:placetype":"postalcode"
},
  "geometry": {"coordinates":[-0.22004496598414,51.51751304808632],"type":"Point"}
}