{
  "type": "Feature",
  "properties": {
    "iso:country":"GB",
    "wof:name":"TA7 8NL",
    "wof:placetype":"postalcode"
},
  "geometry": {"coordinates":[-2.87446223789611,51.19339736804619],"type":"Point"}
}