{
  "type": "Feature",
  "properties": {
    "iso:country":"GB",
    "wof:name":"BS13 0RW",
    "wof:placetype":"postalcode"
},
  "geometry": {"coordinates":[-2.59265092021981,51.40438777108645],"type":"Point"}
}