{
  "type": "Feature",
  "properties": {
    "iso:country":"GB",
    "wof:name":"DE1 1EH",
    "wof:placetype":"postalcode"
},
  "geometry": {"coordinates":[-1.48294374007148,52.92380657355405],"type":"Point"}
}