{
  "type": "Feature",
  "properties": {
    "iso:country": "GB",
    "wof:name": "CO4 9AU",
    "wof:placetype": "postalcode"
  },
  "geometry": {"coordinates":[0.934664,51.917067],"type":"Point"}
}
