{
  "type": "Feature",
  "properties": {
    "date:inception_lower": "1980-01-01",
    "date:inception_upper": "1980-01-01",
    "iso:country": "GB",
    "wof:name": "KT22 0HN",
    "wof:placetype": "postalcode"
  },
  "geometry": {"coordinates":[-0.356287,51.32683],"type":"Point"}
}
