{
  "type": "Feature",
  "properties": {
    "iso:country": "GB",
    "wof:name": "SM2 5BF",
    "wof:placetype": "postalcode"
  },
  "geometry": {"coordinates":[-0.199646,51.348187],"type":"Point"}
}
