{
  "type": "Feature",
  "properties": {
    "date:inception_lower":"1995-07-01",
    "date:inception_upper":"1995-07-31",
    "iso:country":"GB",
    "wof:name":"SM2 5BF",
    "wof:placetype":"postalcode"
},
  "geometry": {"coordinates":[-0.199646,51.348187],"type":"Point"}
}