{
  "type": "Feature",
  "properties": {
    "iso:country":"GB",
    "wof:name":"BL3 4PR",
    "wof:placetype":"postalcode"
},
  "geometry": {"coordinates":[-2.48112171192351,53.57369823424438],"type":"Point"}
}