{
  "type": "Feature",
  "properties": {
    "iso:country":"GB",
    "wof:name":"NR16 1BD",
    "wof:placetype":"postalcode"
},
  "geometry": {"coordinates":[1.17653244284377,52.54852923352282],"type":"Point"}
}