{
  "type": "Feature",
  "properties": {
    "iso:country": "GB",
    "wof:name": "SK17 6UT",
    "wof:placetype": "postalcode"
  },
  "geometry": {"coordinates":[-1.931851,53.254826],"type":"Point"}
}
