{
  "type": "Feature",
  "properties": {
    "iso:country":"GB",
    "wof:name":"IV41 8PJ",
    "wof:placetype":"postalcode"
},
  "geometry": {"coordinates":[-5.73587669732645,57.27292155140584],"type":"Point"}
}