{
  "type": "Feature",
  "properties": {
    "date:inception_lower": "1980-01-01",
    "date:inception_upper": "1980-01-01",
    "iso:country": "GB",
    "wof:name": "HR2 8RT",
    "wof:placetype": "postalcode"
  },
  "geometry": {"coordinates":[-2.808904,51.930349],"type":"Point"}
}
