{
  "type": "Feature",
  "properties": {
    "iso:country": "GB",
    "wof:name": "HR2 8RT",
    "wof:placetype": "postalcode"
  },
  "geometry": {"coordinates":[-2.808358,51.929276],"type":"Point"}
}
