{
  "type": "Feature",
  "properties": {
    "date:inception_lower": "2017-08-01",
    "date:inception_upper": "2017-08-01",
    "iso:country": "GB",
    "wof:name": "RM1 2EW",
    "wof:placetype": "postalcode"
  },
  "geometry": {"coordinates":[0.194273,51.573563],"type":"Point"}
}
