{
  "type": "Feature",
  "properties": {
    "iso:country":"GB",
    "wof:name":"DL8 3RZ",
    "wof:placetype":"postalcode"
},
  "geometry": {"coordinates":[-2.19744549321588,54.29944725976917],"type":"Point"}
}