{
  "type": "Feature",
  "properties": {
    "iso:country": "GB",
    "wof:name": "FK1 9FY",
    "wof:placetype": "postalcode"
  },
  "geometry": {"coordinates":[-3.78477,56.001991],"type":"Point"}
}
