{
  "type": "Feature",
  "properties": {
    "iso:country":"GB",
    "wof:name":"SS7 3YL",
    "wof:placetype":"postalcode"
},
  "geometry": {"coordinates":[0.59823307829056,51.56190933140029],"type":"Point"}
}