{
  "type": "Feature",
  "properties": {
    "iso:country": "GB",
    "wof:name": "CF48 4SF",
    "wof:placetype": "postalcode"
  },
  "geometry": {"coordinates":[-3.339084,51.691758],"type":"Point"}
}
