{
  "type": "Feature",
  "properties": {
    "date:inception_lower": "1980-01-01",
    "date:inception_upper": "1980-01-01",
    "iso:country": "GB",
    "wof:name": "CF48 4SF",
    "wof:placetype": "postalcode"
  },
  "geometry": {"coordinates":[-3.339084,51.691758],"type":"Point"}
}
