{
  "type": "Feature",
  "properties": {
    "iso:country": "GB",
    "wof:name": "BD5 5FZ",
    "wof:placetype": "postalcode"
  },
  "geometry": {"coordinates":[-1.756194,53.781916],"type":"Point"}
}
