{
  "type": "Feature",
  "properties": {
    "date:inception_lower": "1980-01-01",
    "date:inception_upper": "1980-01-01",
    "iso:country": "GB",
    "wof:name": "WV4 6SX",
    "wof:placetype": "postalcode"
  },
  "geometry": {"coordinates":[-2.111393,52.557573],"type":"Point"}
}
