{
  "type": "Feature",
  "properties": {
    "iso:country":"GB",
    "wof:name":"S73 0DQ",
    "wof:placetype":"postalcode"
},
  "geometry": {"coordinates":[-1.39830133436042,53.52086895394416],"type":"Point"}
}