{
  "type": "Feature",
  "properties": {
    "iso:country": "GB",
    "wof:name": "S73 0DQ",
    "wof:placetype": "postalcode"
  },
  "geometry": {"coordinates":[-1.398287,53.520888],"type":"Point"}
}
