{
  "type": "Feature",
  "properties": {
    "date:inception_lower": "1980-01-01",
    "date:inception_upper": "1980-01-01",
    "iso:country": "GB",
    "wof:name": "DT5 1BT",
    "wof:placetype": "postalcode"
  },
  "geometry": {"coordinates":[-2.435733,50.546676],"type":"Point"}
}
