{
  "type": "Feature",
  "properties": {
    "iso:country":"GB",
    "wof:name":"LN1 2PN",
    "wof:placetype":"postalcode"
},
  "geometry": {"coordinates":[-0.74272604435805,53.29388482465977],"type":"Point"}
}