{
  "type": "Feature",
  "properties": {
    "date:inception_lower": "2001-12-01",
    "date:inception_upper": "2001-12-01",
    "iso:country": "GB",
    "wof:name": "LN1 2PN",
    "wof:placetype": "postalcode"
  },
  "geometry": {"coordinates":[-0.742726,53.293885],"type":"Point"}
}
