{
  "type": "Feature",
  "properties": {
    "date:inception_lower": "2018-12-01",
    "date:inception_upper": "2018-12-01",
    "iso:country": "GB",
    "wof:name": "CV10 9RF",
    "wof:placetype": "postalcode"
  },
  "geometry": {"coordinates":[-1.530038,52.527341],"type":"Point"}
}
