{
  "type": "Feature",
  "properties": {
    "iso:country":"GB",
    "wof:name":"SA37 0LJ",
    "wof:placetype":"postalcode"
},
  "geometry": {"coordinates":[-4.54104590368049,52.01688802268177],"type":"Point"}
}