{
  "type": "Feature",
  "properties": {
    "iso:country": "GB",
    "wof:name": "YO23 1AG",
    "wof:placetype": "postalcode"
  },
  "geometry": {"coordinates":[-1.08847,53.952491],"type":"Point"}
}
