{
  "type": "Feature",
  "properties": {
    "iso:country":"GB",
    "wof:name":"CW1 4PY",
    "wof:placetype":"postalcode"
},
  "geometry": {"coordinates":[-2.45269756503664,53.11846768497295],"type":"Point"}
}