{
  "type": "Feature",
  "properties": {
    "iso:country": "GB",
    "wof:name": "RH11 0BB",
    "wof:placetype": "postalcode"
  },
  "geometry": {"coordinates":[-0.203495,51.124936],"type":"Point"}
}
