{
  "type": "Feature",
  "properties": {
    "date:inception_lower": "1980-01-01",
    "date:inception_upper": "1980-01-01",
    "iso:country": "GB",
    "wof:name": "OX4 2JE",
    "wof:placetype": "postalcode"
  },
  "geometry": {"coordinates":[-1.204497,51.73541],"type":"Point"}
}
