{
  "type": "Feature",
  "properties": {
    "iso:country": "GB",
    "wof:name": "OX4 2JE",
    "wof:placetype": "postalcode"
  },
  "geometry": {"coordinates":[-1.204497,51.73541],"type":"Point"}
}
