{
  "type": "Feature",
  "properties": {
    "iso:country":"GB",
    "wof:name":"IP31 3EQ",
    "wof:placetype":"postalcode"
},
  "geometry": {"coordinates":[0.91559173580034,52.28179731232999],"type":"Point"}
}