{
  "type": "Feature",
  "properties": {
    "date:inception_lower": "1987-04-01",
    "date:inception_upper": "1987-04-01",
    "iso:country": "GB",
    "wof:name": "DE13 0FN",
    "wof:placetype": "postalcode"
  },
  "geometry": {"coordinates":[-1.640806,52.833739],"type":"Point"}
}
