{
  "type": "Feature",
  "properties": {
    "iso:country": "GB",
    "wof:name": "DE13 0FN",
    "wof:placetype": "postalcode"
  },
  "geometry": {"coordinates":[-1.640806,52.833739],"type":"Point"}
}
