{
  "type": "Feature",
  "properties": {
    "iso:country":"GB",
    "wof:name":"DE13 0FN",
    "wof:placetype":"postalcode"
},
  "geometry": {"coordinates":[-1.64080575021833,52.83373920426703],"type":"Point"}
}