{
  "type": "Feature",
  "properties": {
    "iso:country":"GB",
    "wof:name":"HD4 5EB",
    "wof:placetype":"postalcode"
},
  "geometry": {"coordinates":[-1.80950590613997,53.63715465128504],"type":"Point"}
}