{
  "type": "Feature",
  "properties": {
    "date:inception_lower": "1980-01-01",
    "date:inception_upper": "1980-01-01",
    "iso:country": "GB",
    "wof:name": "DG12 5JP",
    "wof:placetype": "postalcode"
  },
  "geometry": {"coordinates":[-3.254093,54.98979],"type":"Point"}
}
