{
  "type": "Feature",
  "properties": {
    "iso:country":"GB",
    "wof:name":"LE5 1PH",
    "wof:placetype":"postalcode"
},
  "geometry": {"coordinates":[-1.06129723922455,52.66046624071293],"type":"Point"}
}