{
  "type": "Feature",
  "properties": {
    "iso:country": "GB",
    "wof:name": "PO1 2BD",
    "wof:placetype": "postalcode"
  },
  "geometry": {"coordinates":[-1.089239,50.796187],"type":"Point"}
}
