{
  "type": "Feature",
  "properties": {
    "iso:country": "GB",
    "wof:name": "LE6 0GL",
    "wof:placetype": "postalcode"
  },
  "geometry": {"coordinates":[-1.225017,52.661865],"type":"Point"}
}
