{
  "type": "Feature",
  "properties": {
    "iso:country":"GB",
    "wof:name":"LE6 0GL",
    "wof:placetype":"postalcode"
},
  "geometry": {"coordinates":[-1.2250175025419,52.66186532589087],"type":"Point"}
}