{
  "type": "Feature",
  "properties": {
    "iso:country":"GB",
    "wof:name":"TW10 5DN",
    "wof:placetype":"postalcode"
},
  "geometry": {"coordinates":[-0.28124175366993,51.46584726459165],"type":"Point"}
}