{
  "type": "Feature",
  "properties": {
    "iso:country": "GB",
    "wof:name": "BH22 9UE",
    "wof:placetype": "postalcode"
  },
  "geometry": {"coordinates":[-1.89691,50.815639],"type":"Point"}
}
