{
  "type": "Feature",
  "properties": {
    "iso:country":"GB",
    "wof:name":"B33 8PL",
    "wof:placetype":"postalcode"
},
  "geometry": {"coordinates":[-1.8077909778245,52.47683087299148],"type":"Point"}
}