{
  "type": "Feature",
  "properties": {
    "iso:country":"GB",
    "wof:name":"W1K 2SP",
    "wof:placetype":"postalcode"
},
  "geometry": {"coordinates":[-0.15205562826303,51.5093665206684],"type":"Point"}
}