{
  "type": "Feature",
  "properties": {
    "iso:country":"GB",
    "wof:name":"HP7 0HF",
    "wof:placetype":"postalcode"
},
  "geometry": {"coordinates":[-0.61960119081862,51.66512021235245],"type":"Point"}
}