{
  "type": "Feature",
  "properties": {
    "date:inception_lower": "2006-07-01",
    "date:inception_upper": "2006-07-01",
    "iso:country": "GB",
    "wof:name": "HP7 0HF",
    "wof:placetype": "postalcode"
  },
  "geometry": {"coordinates":[-0.619601,51.66512],"type":"Point"}
}
