{
  "type": "Feature",
  "properties": {
    "iso:country":"GB",
    "wof:name":"RG41 5JJ",
    "wof:placetype":"postalcode"
},
  "geometry": {"coordinates":[-0.87189625262981,51.43668944654708],"type":"Point"}
}