{
  "type": "Feature",
  "properties": {
    "iso:country": "GB",
    "wof:name": "RG41 5JJ",
    "wof:placetype": "postalcode"
  },
  "geometry": {"coordinates":[-0.871896,51.436689],"type":"Point"}
}
