{
  "type": "Feature",
  "properties": {
    "iso:country": "GB",
    "wof:name": "PA2 6QU",
    "wof:placetype": "postalcode"
  },
  "geometry": {"coordinates":[-4.414413,55.831944],"type":"Point"}
}
