{
  "type": "Feature",
  "properties": {
    "iso:country":"GB",
    "wof:name":"PA2 6QU",
    "wof:placetype":"postalcode"
},
  "geometry": {"coordinates":[-4.41441271472921,55.83194374975132],"type":"Point"}
}