{
  "type": "Feature",
  "properties": {
    "iso:country":"GB",
    "wof:name":"RG26 5JF",
    "wof:placetype":"postalcode"
},
  "geometry": {"coordinates":[-1.16783918167715,51.35142977156215],"type":"Point"}
}