{
  "type": "Feature",
  "properties": {
    "iso:country":"GB",
    "wof:name":"G61 1EP",
    "wof:placetype":"postalcode"
},
  "geometry": {"coordinates":[-4.34450542164385,55.91265755187383],"type":"Point"}
}