{
  "type": "Feature",
  "properties": {
    "iso:country":"GB",
    "wof:name":"EX13 7QJ",
    "wof:placetype":"postalcode"
},
  "geometry": {"coordinates":[-3.08545368827061,50.77109081532179],"type":"Point"}
}