{
  "type": "Feature",
  "properties": {
    "iso:country": "GB",
    "wof:name": "EX13 7QJ",
    "wof:placetype": "postalcode"
  },
  "geometry": {"coordinates":[-3.085454,50.771091],"type":"Point"}
}
