{
  "type": "Feature",
  "properties": {
    "iso:country": "GB",
    "wof:name": "BS1 5DZ",
    "wof:placetype": "postalcode"
  },
  "geometry": {"coordinates":[-2.606615,51.450208],"type":"Point"}
}
