{
  "type": "Feature",
  "properties": {
    "iso:country": "GB",
    "wof:name": "BS1 5DZ",
    "wof:placetype": "postalcode"
  },
  "geometry": {"coordinates":[-2.606858,51.45009],"type":"Point"}
}
