{
  "type": "Feature",
  "properties": {
    "iso:country": "GB",
    "wof:name": "IV36 1LW",
    "wof:placetype": "postalcode"
  },
  "geometry": {"coordinates":[-3.620484,57.606217],"type":"Point"}
}
