{
  "type": "Feature",
  "properties": {
    "iso:country":"GB",
    "wof:name":"TR14 8UJ",
    "wof:placetype":"postalcode"
},
  "geometry": {"coordinates":[-5.29368255268962,50.21227656460251],"type":"Point"}
}