{
  "type": "Feature",
  "properties": {
    "date:inception_lower": "2010-04-01",
    "date:inception_upper": "2010-04-01",
    "iso:country": "GB",
    "wof:name": "LS11 6AD",
    "wof:placetype": "postalcode"
  },
  "geometry": {"coordinates":[-1.551593,53.781428],"type":"Point"}
}
