{
  "type": "Feature",
  "properties": {
    "iso:country": "GB",
    "wof:name": "LS11 6AD",
    "wof:placetype": "postalcode"
  },
  "geometry": {"coordinates":[-1.551593,53.781428],"type":"Point"}
}
