{
  "type": "Feature",
  "properties": {
    "iso:country": "GB",
    "wof:name": "S66 9DE",
    "wof:placetype": "postalcode"
  },
  "geometry": {"coordinates":[-1.252931,53.393066],"type":"Point"}
}
