{
  "type": "Feature",
  "properties": {
    "iso:country":"GB",
    "wof:name":"S66 9DE",
    "wof:placetype":"postalcode"
},
  "geometry": {"coordinates":[-1.25293147009155,53.39306607332756],"type":"Point"}
}