{
  "type": "Feature",
  "properties": {
    "date:inception_lower": "1980-01-01",
    "date:inception_upper": "1980-01-01",
    "iso:country": "GB",
    "wof:name": "CW8 2RQ",
    "wof:placetype": "postalcode"
  },
  "geometry": {"coordinates":[-2.623366,53.266428],"type":"Point"}
}
