{
  "type": "Feature",
  "properties": {
    "iso:country":"GB",
    "wof:name":"CW8 2RQ",
    "wof:placetype":"postalcode"
},
  "geometry": {"coordinates":[-2.62336609081715,53.26642841403832],"type":"Point"}
}