{
  "type": "Feature",
  "properties": {
    "iso:country": "GB",
    "wof:name": "CW8 2RQ",
    "wof:placetype": "postalcode"
  },
  "geometry": {"coordinates":[-2.623366,53.266428],"type":"Point"}
}
