{
  "type": "Feature",
  "properties": {
    "iso:country":"GB",
    "wof:name":"LL15 1TB",
    "wof:placetype":"postalcode"
},
  "geometry": {"coordinates":[-3.290436822775,53.14175563782202],"type":"Point"}
}