{
  "type": "Feature",
  "properties": {
    "iso:country": "GB",
    "wof:name": "LL15 1TB",
    "wof:placetype": "postalcode"
  },
  "geometry": {"coordinates":[-3.290452,53.141771],"type":"Point"}
}
