{
  "type": "Feature",
  "properties": {
    "iso:country":"GB",
    "wof:name":"EX15 1NA",
    "wof:placetype":"postalcode"
},
  "geometry": {"coordinates":[-3.42690597555429,50.87484341677945],"type":"Point"}
}