{
  "type": "Feature",
  "properties": {
    "iso:country": "GB",
    "wof:name": "EX15 1NA",
    "wof:placetype": "postalcode"
  },
  "geometry": {"coordinates":[-3.426906,50.874843],"type":"Point"}
}
