{
  "type": "Feature",
  "properties": {
    "iso:country": "GB",
    "wof:name": "WA6 8PA",
    "wof:placetype": "postalcode"
  },
  "geometry": {"coordinates":[-2.632771,53.248464],"type":"Point"}
}
