{
  "type": "Feature",
  "properties": {
    "date:inception_lower":"1980-01-01",
    "date:inception_upper":"1980-01-31",
    "iso:country":"GB",
    "wof:name":"WA6 8PA",
    "wof:placetype":"postalcode"
},
  "geometry": {"coordinates":[-2.632771,53.248464],"type":"Point"}
}