{
  "type": "Feature",
  "properties": {
    "iso:country": "GB",
    "wof:name": "OL1 2SX",
    "wof:placetype": "postalcode"
  },
  "geometry": {"coordinates":[-2.146446,53.561022],"type":"Point"}
}
