{
  "type": "Feature",
  "properties": {
    "date:inception_lower": "1980-01-01",
    "date:inception_upper": "1980-01-01",
    "iso:country": "GB",
    "wof:name": "OL1 2SX",
    "wof:placetype": "postalcode"
  },
  "geometry": {"coordinates":[-2.146413,53.560913],"type":"Point"}
}
