{
  "type": "Feature",
  "properties": {
    "iso:country":"GB",
    "wof:name":"OL1 2SX",
    "wof:placetype":"postalcode"
},
  "geometry": {"coordinates":[-2.14644610775464,53.56102238037342],"type":"Point"}
}