{
  "type": "Feature",
  "properties": {
    "iso:country":"GB",
    "wof:name":"CF44 7PA",
    "wof:placetype":"postalcode"
},
  "geometry": {"coordinates":[-3.44721398602104,51.71158852031635],"type":"Point"}
}