{
  "type": "Feature",
  "properties": {
    "iso:country":"GB",
    "wof:name":"M7 4TZ",
    "wof:placetype":"postalcode"
},
  "geometry": {"coordinates":[-2.25484781400791,53.50184954979423],"type":"Point"}
}