{
  "type": "Feature",
  "properties": {
    "date:inception_lower": "1994-05-01",
    "date:inception_upper": "1994-05-01",
    "iso:country": "GB",
    "wof:name": "M7 4TZ",
    "wof:placetype": "postalcode"
  },
  "geometry": {"coordinates":[-2.254848,53.50185],"type":"Point"}
}
