{
  "type": "Feature",
  "properties": {
    "iso:country":"GB",
    "wof:name":"LN4 2HB",
    "wof:placetype":"postalcode"
},
  "geometry": {"coordinates":[-0.40477319010792,53.15381888567787],"type":"Point"}
}