{
  "type": "Feature",
  "properties": {
    "date:inception_lower":"1980-01-01",
    "date:inception_upper":"1980-01-31",
    "iso:country":"GB",
    "wof:name":"LN4 2HB",
    "wof:placetype":"postalcode"
},
  "geometry": {"coordinates":[-0.404773,53.153819],"type":"Point"}
}