{
  "type": "Feature",
  "properties": {
    "iso:country":"GB",
    "wof:name":"LS27 9BP",
    "wof:placetype":"postalcode"
},
  "geometry": {"coordinates":[-1.60112271552363,53.74502167493803],"type":"Point"}
}