{
  "type": "Feature",
  "properties": {
    "iso:country":"GB",
    "wof:name":"SA11 1EH",
    "wof:placetype":"postalcode"
},
  "geometry": {"coordinates":[-3.8056160983859,51.66132284525326],"type":"Point"}
}