{
  "type": "Feature",
  "properties": {
    "iso:country":"GB",
    "wof:name":"B10 9RD",
    "wof:placetype":"postalcode"
},
  "geometry": {"coordinates":[-1.85026594758785,52.46845056963028],"type":"Point"}
}