{
  "type": "Feature",
  "properties": {
    "iso:country": "GB",
    "wof:name": "CO1 2AX",
    "wof:placetype": "postalcode"
  },
  "geometry": {"coordinates":[0.915391,51.877989],"type":"Point"}
}
