{
  "type": "Feature",
  "properties": {
    "iso:country":"GB",
    "wof:name":"CO1 2AX",
    "wof:placetype":"postalcode"
},
  "geometry": {"coordinates":[0.91539097001662,51.87798896806922],"type":"Point"}
}