{
  "type": "Feature",
  "properties": {
    "iso:country":"GB",
    "wof:name":"AB23 8ND",
    "wof:placetype":"postalcode"
},
  "geometry": {"coordinates":[-2.09964976291915,57.19504859569207],"type":"Point"}
}