{
  "type": "Feature",
  "properties": {
    "iso:country":"GB",
    "wof:name":"SO14 6TA",
    "wof:placetype":"postalcode"
},
  "geometry": {"coordinates":[-1.40149070793188,50.91978595146426],"type":"Point"}
}