{
  "type": "Feature",
  "properties": {
    "date:inception_lower": "1994-12-01",
    "date:inception_upper": "1994-12-01",
    "iso:country": "GB",
    "wof:name": "SO14 6TA",
    "wof:placetype": "postalcode"
  },
  "geometry": {"coordinates":[-1.401491,50.919786],"type":"Point"}
}
