{
  "type": "Feature",
  "properties": {
    "iso:country":"GB",
    "wof:name":"TN23 5UF",
    "wof:placetype":"postalcode"
},
  "geometry": {"coordinates":[0.84384728628462,51.13034755222407],"type":"Point"}
}