{
  "type": "Feature",
  "properties": {
    "date:inception_lower": "1980-01-01",
    "date:inception_upper": "1980-01-01",
    "iso:country": "GB",
    "wof:name": "LL57 3SF",
    "wof:placetype": "postalcode"
  },
  "geometry": {"coordinates":[-4.057399,53.183232],"type":"Point"}
}
