{
  "type": "Feature",
  "properties": {
    "iso:country":"GB",
    "wof:name":"LL57 3SF",
    "wof:placetype":"postalcode"
},
  "geometry": {"coordinates":[-4.05739893057534,53.18323202309341],"type":"Point"}
}