{
  "type": "Feature",
  "properties": {
    "iso:country":"GB",
    "wof:name":"E3 4HG",
    "wof:placetype":"postalcode"
},
  "geometry": {"coordinates":[-0.03245137635049,51.52092792021957],"type":"Point"}
}