{
  "type": "Feature",
  "properties": {
    "iso:country":"GB",
    "wof:name":"CT11 8NF",
    "wof:placetype":"postalcode"
},
  "geometry": {"coordinates":[1.41917606861478,51.33481007232924],"type":"Point"}
}