{
  "type": "Feature",
  "properties": {
    "iso:country":"GB",
    "wof:name":"WV4 6QX",
    "wof:placetype":"postalcode"
},
  "geometry": {"coordinates":[-2.11716823262759,52.55492473450366],"type":"Point"}
}