{
  "type": "Feature",
  "properties": {
    "iso:country": "GB",
    "wof:name": "WV4 6QX",
    "wof:placetype": "postalcode"
  },
  "geometry": {"coordinates":[-2.117168,52.554925],"type":"Point"}
}
