{
  "type": "Feature",
  "properties": {
    "iso:country":"GB",
    "wof:name":"M38 9PT",
    "wof:placetype":"postalcode"
},
  "geometry": {"coordinates":[-2.41589783287449,53.53362995361857],"type":"Point"}
}