{
  "type": "Feature",
  "properties": {
    "iso:country":"GB",
    "wof:name":"SO50 8NH",
    "wof:placetype":"postalcode"
},
  "geometry": {"coordinates":[-1.31683521195316,50.96601036952687],"type":"Point"}
}