{
  "type": "Feature",
  "properties": {
    "date:inception_lower":"1993-08-01",
    "date:inception_upper":"1993-08-31",
    "iso:country":"GB",
    "wof:name":"L3 7HT",
    "wof:placetype":"postalcode"
},
  "geometry": {"coordinates":[-2.995857,53.412622],"type":"Point"}
}