{
  "type": "Feature",
  "properties": {
    "iso:country":"GB",
    "wof:name":"E11 2RE",
    "wof:placetype":"postalcode"
},
  "geometry": {"coordinates":[0.02171009064171,51.57603106832345],"type":"Point"}
}