{
  "type": "Feature",
  "properties": {
    "date:inception_lower":"1980-01-01",
    "date:inception_upper":"1980-01-31",
    "iso:country":"GB",
    "wof:name":"SY8 3NB",
    "wof:placetype":"postalcode"
},
  "geometry": {"coordinates":[-2.597625,52.376894],"type":"Point"}
}