{
  "type": "Feature",
  "properties": {
    "iso:country":"GB",
    "wof:name":"RH20 3DQ",
    "wof:placetype":"postalcode"
},
  "geometry": {"coordinates":[-0.39388340371553,50.93071596601707],"type":"Point"}
}