{
  "type": "Feature",
  "properties": {
    "iso:country": "GB",
    "wof:name": "RH20 3DQ",
    "wof:placetype": "postalcode"
  },
  "geometry": {"coordinates":[-0.393859,50.93071],"type":"Point"}
}
