{
  "type": "Feature",
  "properties": {
    "iso:country":"GB",
    "wof:name":"PA9 1BF",
    "wof:placetype":"postalcode"
},
  "geometry": {"coordinates":[-4.56058044270181,55.80735170650479],"type":"Point"}
}