{
  "type": "Feature",
  "properties": {
    "date:inception_lower": "2001-12-01",
    "date:inception_upper": "2001-12-01",
    "iso:country": "GB",
    "wof:name": "PA9 1BF",
    "wof:placetype": "postalcode"
  },
  "geometry": {"coordinates":[-4.56058,55.807352],"type":"Point"}
}
