{
  "type": "Feature",
  "properties": {
    "iso:country":"GB",
    "wof:name":"BH21 2RX",
    "wof:placetype":"postalcode"
},
  "geometry": {"coordinates":[-1.96361440832592,50.8100583187808],"type":"Point"}
}