{
  "type": "Feature",
  "properties": {
    "iso:country":"GB",
    "wof:name":"CO15 2EZ",
    "wof:placetype":"postalcode"
},
  "geometry": {"coordinates":[1.11712560096091,51.77622593457453],"type":"Point"}
}