{
  "type": "Feature",
  "properties": {
    "iso:country":"GB",
    "wof:name":"GL52 9PZ",
    "wof:placetype":"postalcode"
},
  "geometry": {"coordinates":[-2.04291122949119,51.94144912350089],"type":"Point"}
}