{
  "type": "Feature",
  "properties": {
    "date:inception_lower": "2000-10-01",
    "date:inception_upper": "2000-10-01",
    "iso:country": "GB",
    "wof:name": "GL52 9PZ",
    "wof:placetype": "postalcode"
  },
  "geometry": {"coordinates":[-2.042911,51.941449],"type":"Point"}
}
