{
  "type": "Feature",
  "properties": {
    "date:inception_lower": "1980-01-01",
    "date:inception_upper": "1980-01-01",
    "iso:country": "GB",
    "wof:name": "W7 3ST",
    "wof:placetype": "postalcode"
  },
  "geometry": {"coordinates":[-0.336304,51.508924],"type":"Point"}
}
