{
  "type": "Feature",
  "properties": {
    "iso:country":"GB",
    "wof:name":"B43 5NA",
    "wof:placetype":"postalcode"
},
  "geometry": {"coordinates":[-1.9430854116959,52.54222180465521],"type":"Point"}
}