{
  "type": "Feature",
  "properties": {
    "iso:country":"GB",
    "wof:name":"DD4 0SF",
    "wof:placetype":"postalcode"
},
  "geometry": {"coordinates":[-2.90856984086223,56.4890062885932],"type":"Point"}
}