{
  "type": "Feature",
  "properties": {
    "iso:country":"GB",
    "wof:name":"BD11 2BJ",
    "wof:placetype":"postalcode"
},
  "geometry": {"coordinates":[-1.6935568223933,53.75935975003969],"type":"Point"}
}