{
  "type": "Feature",
  "properties": {
    "iso:country": "GB",
    "wof:name": "HU8 0RP",
    "wof:placetype": "postalcode"
  },
  "geometry": {"coordinates":[-0.28365,53.773741],"type":"Point"}
}
