{
  "type": "Feature",
  "properties": {
    "iso:country":"GB",
    "wof:name":"TS23 3BD",
    "wof:placetype":"postalcode"
},
  "geometry": {"coordinates":[-1.28116020307256,54.61258700233071],"type":"Point"}
}