{
  "type": "Feature",
  "properties": {
    "iso:country":"GB",
    "wof:name":"BS39 7AB",
    "wof:placetype":"postalcode"
},
  "geometry": {"coordinates":[-2.50450689845738,51.30869657954185],"type":"Point"}
}