{
  "type": "Feature",
  "properties": {
    "iso:country": "GB",
    "wof:name": "BS39 7AB",
    "wof:placetype": "postalcode"
  },
  "geometry": {"coordinates":[-2.504138,51.308873],"type":"Point"}
}
