{
  "type": "Feature",
  "properties": {
    "date:inception_lower": "1980-01-01",
    "date:inception_upper": "1980-01-01",
    "iso:country": "GB",
    "wof:name": "B37 7PN",
    "wof:placetype": "postalcode"
  },
  "geometry": {"coordinates":[-1.739129,52.475702],"type":"Point"}
}
