{
  "type": "Feature",
  "properties": {
    "iso:country":"GB",
    "wof:name":"B37 7PN",
    "wof:placetype":"postalcode"
},
  "geometry": {"coordinates":[-1.73912924835217,52.47570166693492],"type":"Point"}
}