{
  "type": "Feature",
  "properties": {
    "iso:country": "GB",
    "wof:name": "TS14 7DH",
    "wof:placetype": "postalcode"
  },
  "geometry": {"coordinates":[-1.057751,54.53039],"type":"Point"}
}
