{
  "type": "Feature",
  "properties": {
    "iso:country":"GB",
    "wof:name":"TS14 7DH",
    "wof:placetype":"postalcode"
},
  "geometry": {"coordinates":[-1.05773569945799,54.53037683289992],"type":"Point"}
}