{
  "type": "Feature",
  "properties": {
    "date:inception_lower": "1980-01-01",
    "date:inception_upper": "1980-01-01",
    "iso:country": "GB",
    "wof:name": "BS14 8QF",
    "wof:placetype": "postalcode"
  },
  "geometry": {"coordinates":[-2.544968,51.414348],"type":"Point"}
}
