{
  "type": "Feature",
  "properties": {
    "iso:country":"GB",
    "wof:name":"BS14 8QF",
    "wof:placetype":"postalcode"
},
  "geometry": {"coordinates":[-2.54496834284482,51.41434829919919],"type":"Point"}
}