{
  "type": "Feature",
  "properties": {
    "date:inception_lower": "1981-09-01",
    "date:inception_upper": "1981-09-01",
    "iso:country": "GB",
    "wof:name": "TS7 8SR",
    "wof:placetype": "postalcode"
  },
  "geometry": {"coordinates":[-1.208127,54.536541],"type":"Point"}
}
