{
  "type": "Feature",
  "properties": {
    "iso:country": "GB",
    "wof:name": "TS7 8SR",
    "wof:placetype": "postalcode"
  },
  "geometry": {"coordinates":[-1.208127,54.536541],"type":"Point"}
}
