{
  "type": "Feature",
  "properties": {
    "iso:country":"GB",
    "wof:name":"TS7 8SR",
    "wof:placetype":"postalcode"
},
  "geometry": {"coordinates":[-1.20812714146679,54.53654129750602],"type":"Point"}
}