{
  "type": "Feature",
  "properties": {
    "iso:country":"GB",
    "wof:name":"BD6 3RN",
    "wof:placetype":"postalcode"
},
  "geometry": {"coordinates":[-1.81874778683337,53.77104687979311],"type":"Point"}
}