{
  "type": "Feature",
  "properties": {
    "iso:country": "GB",
    "wof:name": "NE27 0GG",
    "wof:placetype": "postalcode"
  },
  "geometry": {"coordinates":[-1.529626,55.039919],"type":"Point"}
}
