{
  "type": "Feature",
  "properties": {
    "iso:country":"GB",
    "wof:name":"NW9 7ED",
    "wof:placetype":"postalcode"
},
  "geometry": {"coordinates":[-0.23952512097281,51.57783995055878],"type":"Point"}
}