{
  "type": "Feature",
  "properties": {
    "iso:country":"GB",
    "wof:name":"S35 7BA",
    "wof:placetype":"postalcode"
},
  "geometry": {"coordinates":[-1.57206001190457,53.50979690614208],"type":"Point"}
}