{
  "type": "Feature",
  "properties": {
    "iso:country": "GB",
    "wof:name": "S35 7BA",
    "wof:placetype": "postalcode"
  },
  "geometry": {"coordinates":[-1.57206,53.509797],"type":"Point"}
}
