{
  "type": "Feature",
  "properties": {
    "iso:country":"GB",
    "wof:name":"BN16 3SW",
    "wof:placetype":"postalcode"
},
  "geometry": {"coordinates":[-0.51409896691908,50.82002044144048],"type":"Point"}
}