{
  "type": "Feature",
  "properties": {
    "date:inception_lower": "1995-07-01",
    "date:inception_upper": "1995-07-01",
    "iso:country": "GB",
    "wof:name": "BN16 3SW",
    "wof:placetype": "postalcode"
  },
  "geometry": {"coordinates":[-0.514099,50.82002],"type":"Point"}
}
