{
  "type": "Feature",
  "properties": {
    "date:inception_lower": "1980-01-01",
    "date:inception_upper": "1980-01-01",
    "iso:country": "GB",
    "wof:name": "M35 9FD",
    "wof:placetype": "postalcode"
  },
  "geometry": {"coordinates":[-2.148162,53.516375],"type":"Point"}
}
