{
  "type": "Feature",
  "properties": {
    "iso:country":"GB",
    "wof:name":"DE4 3HZ",
    "wof:placetype":"postalcode"
},
  "geometry": {"coordinates":[-1.55859780592569,53.14414881393791],"type":"Point"}
}