{
  "type": "Feature",
  "properties": {
    "iso:country":"GB",
    "wof:name":"DT11 7JD",
    "wof:placetype":"postalcode"
},
  "geometry": {"coordinates":[-2.15977548593671,50.86016826605289],"type":"Point"}
}