{
  "type": "Feature",
  "properties": {
    "iso:country": "GB",
    "wof:name": "SK15 2LF",
    "wof:placetype": "postalcode"
  },
  "geometry": {"coordinates":[-2.049462,53.481834],"type":"Point"}
}
