{
  "type": "Feature",
  "properties": {
    "iso:country":"GB",
    "wof:name":"NR30 1TH",
    "wof:placetype":"postalcode"
},
  "geometry": {"coordinates":[1.63334984341251,52.6310418296305],"type":"Point"}
}