{
  "type": "Feature",
  "properties": {
    "iso:country": "GB",
    "wof:name": "NR30 1TH",
    "wof:placetype": "postalcode"
  },
  "geometry": {"coordinates":[1.63335,52.631042],"type":"Point"}
}
