{
  "type": "Feature",
  "properties": {
    "date:inception_lower": "1980-01-01",
    "date:inception_upper": "1980-01-01",
    "iso:country": "GB",
    "wof:name": "WF15 6HU",
    "wof:placetype": "postalcode"
  },
  "geometry": {"coordinates":[-1.684374,53.70989],"type":"Point"}
}
