{
  "type": "Feature",
  "properties": {
    "iso:country":"GB",
    "wof:name":"GL51 8DD",
    "wof:placetype":"postalcode"
},
  "geometry": {"coordinates":[-2.10494875753471,51.90157171482598],"type":"Point"}
}