{
  "type": "Feature",
  "properties": {
    "date:inception_lower":"1980-01-01",
    "date:inception_upper":"1980-01-31",
    "iso:country":"GB",
    "wof:name":"KA26 0LH",
    "wof:placetype":"postalcode"
},
  "geometry": {"coordinates":[-4.952918,55.114763],"type":"Point"}
}