{
  "type": "Feature",
  "properties": {
    "iso:country": "GB",
    "wof:name": "KA26 0LH",
    "wof:placetype": "postalcode"
  },
  "geometry": {"coordinates":[-4.952918,55.114763],"type":"Point"}
}
