{
  "type": "Feature",
  "properties": {
    "iso:country":"GB",
    "wof:name":"KA26 0LH",
    "wof:placetype":"postalcode"
},
  "geometry": {"coordinates":[-4.952918472815,55.1147634336662],"type":"Point"}
}