{
  "type": "Feature",
  "properties": {
    "iso:country":"GB",
    "wof:name":"SE4 2LR",
    "wof:placetype":"postalcode"
},
  "geometry": {"coordinates":[-0.04482707472378,51.46081217762474],"type":"Point"}
}