{
  "type": "Feature",
  "properties": {
    "iso:country": "GB",
    "wof:name": "SN4 9NN",
    "wof:placetype": "postalcode"
  },
  "geometry": {"coordinates":[-1.851456,51.451658],"type":"Point"}
}
