{
  "type": "Feature",
  "properties": {
    "date:inception_lower": "1980-01-01",
    "date:inception_upper": "1980-01-01",
    "iso:country": "GB",
    "wof:name": "SN4 9NN",
    "wof:placetype": "postalcode"
  },
  "geometry": {"coordinates":[-1.851456,51.451658],"type":"Point"}
}
