{
  "type": "Feature",
  "properties": {
    "iso:country":"GB",
    "wof:name":"SN4 9NN",
    "wof:placetype":"postalcode"
},
  "geometry": {"coordinates":[-1.85146550873054,51.45165972660737],"type":"Point"}
}