{
  "type": "Feature",
  "properties": {
    "date:inception_lower": "1980-01-01",
    "date:inception_upper": "1980-01-01",
    "iso:country": "GB",
    "wof:name": "SN4 9NN",
    "wof:placetype": "postalcode"
  },
  "geometry": {"coordinates":[-1.851269,51.451685],"type":"Point"}
}
