{
  "type": "Feature",
  "properties": {
    "iso:country":"GB",
    "wof:name":"SA32 8QE",
    "wof:placetype":"postalcode"
},
  "geometry": {"coordinates":[-4.0549740230643,51.88069280902288],"type":"Point"}
}