{
  "type": "Feature",
  "properties": {
    "iso:country": "GB",
    "wof:name": "CV7 7LZ",
    "wof:placetype": "postalcode"
  },
  "geometry": {"coordinates":[-1.649206,52.439102],"type":"Point"}
}
