{
  "type": "Feature",
  "properties": {
    "iso:country":"GB",
    "wof:name":"CV7 7LZ",
    "wof:placetype":"postalcode"
},
  "geometry": {"coordinates":[-1.64911083922941,52.43911343012138],"type":"Point"}
}