{
  "type": "Feature",
  "properties": {
    "date:inception_lower": "2018-07-01",
    "date:inception_upper": "2018-07-01",
    "iso:country": "GB",
    "wof:name": "IG11 7QG",
    "wof:placetype": "postalcode"
  },
  "geometry": {"coordinates":[0.08404,51.533405],"type":"Point"}
}
