{
  "type": "Feature",
  "properties": {
    "iso:country":"GB",
    "wof:name":"DY5 2HE",
    "wof:placetype":"postalcode"
},
  "geometry": {"coordinates":[-2.1089225989735,52.46540205303574],"type":"Point"}
}