{
  "type": "Feature",
  "properties": {
    "date:inception_lower": "1998-06-01",
    "date:inception_upper": "1998-06-01",
    "iso:country": "GB",
    "wof:name": "OL6 9RB",
    "wof:placetype": "postalcode"
  },
  "geometry": {"coordinates":[-2.073672,53.496391],"type":"Point"}
}
