{
  "type": "Feature",
  "properties": {
    "iso:country": "GB",
    "wof:name": "OL6 9RB",
    "wof:placetype": "postalcode"
  },
  "geometry": {"coordinates":[-2.073672,53.496391],"type":"Point"}
}
