{
  "type": "Feature",
  "properties": {
    "iso:country":"GB",
    "wof:name":"W1J 5AW",
    "wof:placetype":"postalcode"
},
  "geometry": {"coordinates":[-0.14672084649519,51.50943521714014],"type":"Point"}
}