{
  "type": "Feature",
  "properties": {
    "iso:country": "GB",
    "wof:name": "PR6 8NL",
    "wof:placetype": "postalcode"
  },
  "geometry": {"coordinates":[-2.601676,53.718107],"type":"Point"}
}
