{
  "type": "Feature",
  "properties": {
    "iso:country":"GB",
    "wof:name":"PR6 8NL",
    "wof:placetype":"postalcode"
},
  "geometry": {"coordinates":[-2.60167625334643,53.71810723925068],"type":"Point"}
}