{
  "type": "Feature",
  "properties": {
    "date:inception_lower":"2001-06-01",
    "date:inception_upper":"2001-06-30",
    "iso:country":"GB",
    "wof:name":"LU7 4AD",
    "wof:placetype":"postalcode"
},
  "geometry": {"coordinates":[-0.655888,51.908746],"type":"Point"}
}