{
  "type": "Feature",
  "properties": {
    "iso:country":"GB",
    "wof:name":"LU7 4AD",
    "wof:placetype":"postalcode"
},
  "geometry": {"coordinates":[-0.65588839132651,51.90874583012339],"type":"Point"}
}