{
  "type": "Feature",
  "properties": {
    "date:inception_lower":"1992-08-01",
    "date:inception_upper":"1992-08-31",
    "iso:country":"GB",
    "wof:name":"DE55 7NL",
    "wof:placetype":"postalcode"
},
  "geometry": {"coordinates":[-1.435923,53.094398],"type":"Point"}
}