{
  "type": "Feature",
  "properties": {
    "iso:country":"GB",
    "wof:name":"DE55 7NL",
    "wof:placetype":"postalcode"
},
  "geometry": {"coordinates":[-1.43592337441897,53.09439789549409],"type":"Point"}
}