{
  "type": "Feature",
  "properties": {
    "iso:country": "GB",
    "wof:name": "DE55 7NL",
    "wof:placetype": "postalcode"
  },
  "geometry": {"coordinates":[-1.435923,53.094398],"type":"Point"}
}
