{
  "type": "Feature",
  "properties": {
    "iso:country": "GB",
    "wof:name": "L11 2XY",
    "wof:placetype": "postalcode"
  },
  "geometry": {"coordinates":[-2.920013,53.444548],"type":"Point"}
}
