{
  "type": "Feature",
  "properties": {
    "iso:country":"GB",
    "wof:name":"L11 2XY",
    "wof:placetype":"postalcode"
},
  "geometry": {"coordinates":[-2.92001300545068,53.44454774967609],"type":"Point"}
}