{
  "type": "Feature",
  "properties": {
    "iso:country": "GB",
    "wof:name": "EX32 0AQ",
    "wof:placetype": "postalcode"
  },
  "geometry": {"coordinates":[-4.048666,51.056433],"type":"Point"}
}
