{
  "type": "Feature",
  "properties": {
    "iso:country":"GB",
    "wof:name":"WD25 7LY",
    "wof:placetype":"postalcode"
},
  "geometry": {"coordinates":[-0.40884660774445,51.68964597114984],"type":"Point"}
}