{
  "type": "Feature",
  "properties": {
    "iso:country":"GB",
    "wof:name":"PO16 7PQ",
    "wof:placetype":"postalcode"
},
  "geometry": {"coordinates":[-1.19632330208755,50.8607141986273],"type":"Point"}
}