{
  "type": "Feature",
  "properties": {
    "iso:country":"GB",
    "wof:name":"CB1 2AL",
    "wof:placetype":"postalcode"
},
  "geometry": {"coordinates":[0.13427844940712,52.20194612633235],"type":"Point"}
}