{
  "type": "Feature",
  "properties": {
    "iso:country":"GB",
    "wof:name":"S10 4JL",
    "wof:placetype":"postalcode"
},
  "geometry": {"coordinates":[-1.56149866408516,53.37141555523204],"type":"Point"}
}