{
  "type": "Feature",
  "properties": {
    "iso:country":"GB",
    "wof:name":"OX7 6FE",
    "wof:placetype":"postalcode"
},
  "geometry": {"coordinates":[-1.6432328250041,51.90233754564787],"type":"Point"}
}