{
  "type": "Feature",
  "properties": {
    "iso:country": "GB",
    "wof:name": "OX7 6FE",
    "wof:placetype": "postalcode"
  },
  "geometry": {"coordinates":[-1.64322,51.902346],"type":"Point"}
}
