{
  "type": "Feature",
  "properties": {
    "date:inception_lower": "2001-12-01",
    "date:inception_upper": "2001-12-01",
    "iso:country": "GB",
    "wof:name": "OX7 6FE",
    "wof:placetype": "postalcode"
  },
  "geometry": {"coordinates":[-1.643308,51.902193],"type":"Point"}
}
