{
  "type": "Feature",
  "properties": {
    "iso:country":"GB",
    "wof:name":"SN8 4AT",
    "wof:placetype":"postalcode"
},
  "geometry": {"coordinates":[-1.72685665977926,51.41502899806244],"type":"Point"}
}