{
  "type": "Feature",
  "properties": {
    "iso:country":"GB",
    "wof:name":"S10 1UY",
    "wof:placetype":"postalcode"
},
  "geometry": {"coordinates":[-1.51027515219663,53.3833782112396],"type":"Point"}
}