{
  "type": "Feature",
  "properties": {
    "date:inception_lower": "2019-08-01",
    "date:inception_upper": "2019-08-01",
    "iso:country": "GB",
    "wof:name": "ME17 4FX",
    "wof:placetype": "postalcode"
  },
  "geometry": {"coordinates":[0.494725,51.237323],"type":"Point"}
}
