{
  "type": "Feature",
  "properties": {
    "iso:country":"GB",
    "wof:name":"NN16 8JA",
    "wof:placetype":"postalcode"
},
  "geometry": {"coordinates":[-0.72795222766156,52.4005272582078],"type":"Point"}
}