{
  "type": "Feature",
  "properties": {
    "iso:country": "GB",
    "wof:name": "NN16 8JA",
    "wof:placetype": "postalcode"
  },
  "geometry": {"coordinates":[-0.727952,52.400527],"type":"Point"}
}
