{
  "type": "Feature",
  "properties": {
    "date:inception_lower": "1986-07-01",
    "date:inception_upper": "1986-07-01",
    "iso:country": "GB",
    "wof:name": "CO5 7LD",
    "wof:placetype": "postalcode"
  },
  "geometry": {"coordinates":[0.915414,51.833883],"type":"Point"}
}
