{
  "type": "Feature",
  "properties": {
    "iso:country":"GB",
    "wof:name":"KA13 6UB",
    "wof:placetype":"postalcode"
},
  "geometry": {"coordinates":[-4.71462837768349,55.65892191731758],"type":"Point"}
}