{
  "type": "Feature",
  "properties": {
    "date:inception_lower": "1980-01-01",
    "date:inception_upper": "1980-01-01",
    "iso:country": "GB",
    "wof:name": "SN1 3AF",
    "wof:placetype": "postalcode"
  },
  "geometry": {"coordinates":[-1.772547,51.558613],"type":"Point"}
}
