{
  "type": "Feature",
  "properties": {
    "iso:country": "GB",
    "wof:name": "NR12 9DX",
    "wof:placetype": "postalcode"
  },
  "geometry": {"coordinates":[1.517604,52.774093],"type":"Point"}
}
