{
  "type": "Feature",
  "properties": {
    "iso:country":"GB",
    "wof:name":"NR12 9DX",
    "wof:placetype":"postalcode"
},
  "geometry": {"coordinates":[1.51758484918998,52.7740921257265],"type":"Point"}
}