{
  "type": "Feature",
  "properties": {
    "iso:country": "GB",
    "wof:name": "LL55 1PS",
    "wof:placetype": "postalcode"
  },
  "geometry": {"coordinates":[-4.259674,53.143062],"type":"Point"}
}
