{
  "type": "Feature",
  "properties": {
    "iso:country": "GB",
    "wof:name": "PE24 4ST",
    "wof:placetype": "postalcode"
  },
  "geometry": {"coordinates":[0.328052,53.106411],"type":"Point"}
}
