{
  "type": "Feature",
  "properties": {
    "iso:country":"GB",
    "wof:name":"PE24 4ST",
    "wof:placetype":"postalcode"
},
  "geometry": {"coordinates":[0.32805215426115,53.1064107312262],"type":"Point"}
}