{
  "type": "Feature",
  "properties": {
    "iso:country":"GB",
    "wof:name":"RH11 9AW",
    "wof:placetype":"postalcode"
},
  "geometry": {"coordinates":[-0.20587628987843,51.08227383640234],"type":"Point"}
}