{
  "type": "Feature",
  "properties": {
    "date:inception_lower": "1980-01-01",
    "date:inception_upper": "1980-01-01",
    "iso:country": "GB",
    "wof:name": "RH11 9AW",
    "wof:placetype": "postalcode"
  },
  "geometry": {"coordinates":[-0.205876,51.082274],"type":"Point"}
}
