{
  "type": "Feature",
  "properties": {
    "iso:country":"GB",
    "wof:name":"W1U 2NE",
    "wof:placetype":"postalcode"
},
  "geometry": {"coordinates":[-0.15047595837018,51.51634677497602],"type":"Point"}
}