{
  "type": "Feature",
  "properties": {
    "iso:country":"GB",
    "wof:name":"KT2 5UR",
    "wof:placetype":"postalcode"
},
  "geometry": {"coordinates":[-0.30603200411827,51.41570656596986],"type":"Point"}
}