{
  "type": "Feature",
  "properties": {
    "iso:country": "GB",
    "wof:name": "NG24 4DX",
    "wof:placetype": "postalcode"
  },
  "geometry": {"coordinates":[-0.805477,53.065236],"type":"Point"}
}
