{
  "type": "Feature",
  "properties": {
    "iso:country":"GB",
    "wof:name":"NG24 4DX",
    "wof:placetype":"postalcode"
},
  "geometry": {"coordinates":[-0.80547739870706,53.06523607724883],"type":"Point"}
}