{
  "type": "Feature",
  "properties": {
    "iso:country":"GB",
    "wof:name":"CW9 8QJ",
    "wof:placetype":"postalcode"
},
  "geometry": {"coordinates":[-2.51538857322144,53.22050759684228],"type":"Point"}
}