{
  "type": "Feature",
  "properties": {
    "iso:country": "GB",
    "wof:name": "LL20 8BY",
    "wof:placetype": "postalcode"
  },
  "geometry": {"coordinates":[-3.209167,52.992096],"type":"Point"}
}
