{
  "type": "Feature",
  "properties": {
    "iso:country":"GB",
    "wof:name":"BA14 6JD",
    "wof:placetype":"postalcode"
},
  "geometry": {"coordinates":[-2.15826009683786,51.3376863397699],"type":"Point"}
}