{
  "type": "Feature",
  "properties": {
    "date:inception_lower": "1980-01-01",
    "date:inception_upper": "1980-01-01",
    "iso:country": "GB",
    "wof:name": "BA14 6JD",
    "wof:placetype": "postalcode"
  },
  "geometry": {"coordinates":[-2.158529,51.337872],"type":"Point"}
}
