{
  "type": "Feature",
  "properties": {
    "date:inception_lower":"1980-01-01",
    "date:inception_upper":"1980-01-31",
    "iso:country":"GB",
    "wof:name":"SW20 8NW",
    "wof:placetype":"postalcode"
},
  "geometry": {"coordinates":[-0.229102,51.41287],"type":"Point"}
}