{
  "type": "Feature",
  "properties": {
    "iso:country":"GB",
    "wof:name":"SW20 8NW",
    "wof:placetype":"postalcode"
},
  "geometry": {"coordinates":[-0.22910208559496,51.41286982426051],"type":"Point"}
}