{
  "type": "Feature",
  "properties": {
    "iso:country": "GB",
    "wof:name": "DL13 2SE",
    "wof:placetype": "postalcode"
  },
  "geometry": {"coordinates":[-1.953863,54.726584],"type":"Point"}
}
