{
  "type": "Feature",
  "properties": {
    "iso:country":"GB",
    "wof:name":"BN3 2FA",
    "wof:placetype":"postalcode"
},
  "geometry": {"coordinates":[-0.16298509709012,50.8270175249878],"type":"Point"}
}