{
  "type": "Feature",
  "properties": {
    "iso:country":"GB",
    "wof:name":"E17 9NB",
    "wof:placetype":"postalcode"
},
  "geometry": {"coordinates":[-0.00867255958193,51.58157745576521],"type":"Point"}
}