{
  "type": "Feature",
  "properties": {
    "iso:country": "GB",
    "wof:name": "E17 9NB",
    "wof:placetype": "postalcode"
  },
  "geometry": {"coordinates":[-0.008673,51.581577],"type":"Point"}
}
