{
  "type": "Feature",
  "properties": {
    "iso:country":"GB",
    "wof:name":"CH49 3PF",
    "wof:placetype":"postalcode"
},
  "geometry": {"coordinates":[-3.12758046650635,53.37642022118676],"type":"Point"}
}