{
  "type": "Feature",
  "properties": {
    "iso:country":"GB",
    "wof:name":"TS6 9LX",
    "wof:placetype":"postalcode"
},
  "geometry": {"coordinates":[-1.14326654669106,54.56141626723616],"type":"Point"}
}