{
  "type": "Feature",
  "properties": {
    "iso:country":"GB",
    "wof:name":"EX23 8QP",
    "wof:placetype":"postalcode"
},
  "geometry": {"coordinates":[-4.53628044062422,50.82252249364679],"type":"Point"}
}