{
  "type": "Feature",
  "properties": {
    "date:inception_lower": "1980-01-01",
    "date:inception_upper": "1980-01-01",
    "iso:country": "GB",
    "wof:name": "EX23 8QP",
    "wof:placetype": "postalcode"
  },
  "geometry": {"coordinates":[-4.53628,50.822522],"type":"Point"}
}
