{
  "type": "Feature",
  "properties": {
    "iso:country":"GB",
    "wof:name":"B69 1BS",
    "wof:placetype":"postalcode"
},
  "geometry": {"coordinates":[-2.03326967352607,52.48992735370975],"type":"Point"}
}