{
  "type": "Feature",
  "properties": {
    "date:inception_lower": "1980-01-01",
    "date:inception_upper": "1980-01-01",
    "iso:country": "GB",
    "wof:name": "B69 1BS",
    "wof:placetype": "postalcode"
  },
  "geometry": {"coordinates":[-2.03327,52.489927],"type":"Point"}
}
