{
  "type": "Feature",
  "properties": {
    "date:inception_lower": "1980-01-01",
    "date:inception_upper": "1980-01-01",
    "iso:country": "GB",
    "wof:name": "WN5 9TZ",
    "wof:placetype": "postalcode"
  },
  "geometry": {"coordinates":[-2.682501,53.539027],"type":"Point"}
}
