{
  "type": "Feature",
  "properties": {
    "iso:country": "GB",
    "wof:name": "DN14 7HR",
    "wof:placetype": "postalcode"
  },
  "geometry": {"coordinates":[-0.955868,53.748493],"type":"Point"}
}
