{
  "type": "Feature",
  "properties": {
    "iso:country": "GB",
    "wof:name": "M27 0DD",
    "wof:placetype": "postalcode"
  },
  "geometry": {"coordinates":[-2.349928,53.497861],"type":"Point"}
}
