{
  "type": "Feature",
  "properties": {
    "iso:country":"GB",
    "wof:name":"M27 0DD",
    "wof:placetype":"postalcode"
},
  "geometry": {"coordinates":[-2.34992838930143,53.49786064738312],"type":"Point"}
}