{
  "type": "Feature",
  "properties": {
    "date:inception_lower": "1994-05-01",
    "date:inception_upper": "1994-05-01",
    "iso:country": "GB",
    "wof:name": "M27 0DD",
    "wof:placetype": "postalcode"
  },
  "geometry": {"coordinates":[-2.349928,53.497861],"type":"Point"}
}
