{
  "type": "Feature",
  "properties": {
    "iso:country": "GB",
    "wof:name": "PE22 9AS",
    "wof:placetype": "postalcode"
  },
  "geometry": {"coordinates":[0.137511,53.03983],"type":"Point"}
}
