{
  "type": "Feature",
  "properties": {
    "iso:country":"GB",
    "wof:name":"PE22 9AS",
    "wof:placetype":"postalcode"
},
  "geometry": {"coordinates":[0.13769847097195,53.03982721593201],"type":"Point"}
}