{
  "type": "Feature",
  "properties": {
    "iso:country":"GB",
    "wof:name":"CM1 1DX",
    "wof:placetype":"postalcode"
},
  "geometry": {"coordinates":[0.47331328193771,51.73380713625559],"type":"Point"}
}