{
  "type": "Feature",
  "properties": {
    "date:inception_lower": "1980-01-01",
    "date:inception_upper": "1980-01-01",
    "iso:country": "GB",
    "wof:name": "CM1 1DX",
    "wof:placetype": "postalcode"
  },
  "geometry": {"coordinates":[0.473313,51.733807],"type":"Point"}
}
