{
  "type": "Feature",
  "properties": {
    "iso:country":"GB",
    "wof:name":"CO9 3RY",
    "wof:placetype":"postalcode"
},
  "geometry": {"coordinates":[0.58610084987292,51.97112483797927],"type":"Point"}
}