{
  "type": "Feature",
  "properties": {
    "iso:country": "GB",
    "wof:name": "CO9 3RY",
    "wof:placetype": "postalcode"
  },
  "geometry": {"coordinates":[0.586101,51.971125],"type":"Point"}
}
