{
  "type": "Feature",
  "properties": {
    "date:inception_lower": "1980-01-01",
    "date:inception_upper": "1980-01-01",
    "iso:country": "GB",
    "wof:name": "SA3 4DP",
    "wof:placetype": "postalcode"
  },
  "geometry": {"coordinates":[-3.996088,51.573844],"type":"Point"}
}
