{
  "type": "Feature",
  "properties": {
    "iso:country":"GB",
    "wof:name":"SA3 4DP",
    "wof:placetype":"postalcode"
},
  "geometry": {"coordinates":[-3.99608842926206,51.5738438530271],"type":"Point"}
}