{
  "type": "Feature",
  "properties": {
    "iso:country":"GB",
    "wof:name":"WN2 2DA",
    "wof:placetype":"postalcode"
},
  "geometry": {"coordinates":[-2.60987637233923,53.54006026416769],"type":"Point"}
}