{
  "type": "Feature",
  "properties": {
    "date:inception_lower":"2009-08-01",
    "date:inception_upper":"2009-08-31",
    "iso:country":"GB",
    "wof:name":"SA44 5JJ",
    "wof:placetype":"postalcode"
},
  "geometry": {"coordinates":[-4.397936,52.058567],"type":"Point"}
}