{
  "type": "Feature",
  "properties": {
    "iso:country":"GB",
    "wof:name":"SA44 5JJ",
    "wof:placetype":"postalcode"
},
  "geometry": {"coordinates":[-4.39793592257537,52.05856674907641],"type":"Point"}
}