{
  "type": "Feature",
  "properties": {
    "iso:country": "GB",
    "wof:name": "SA44 5JJ",
    "wof:placetype": "postalcode"
  },
  "geometry": {"coordinates":[-4.397936,52.058567],"type":"Point"}
}
