{
  "type": "Feature",
  "properties": {
    "date:inception_lower": "1980-01-01",
    "date:inception_upper": "1980-01-01",
    "iso:country": "GB",
    "wof:name": "ST14 7QR",
    "wof:placetype": "postalcode"
  },
  "geometry": {"coordinates":[-1.870854,52.897605],"type":"Point"}
}
