{
  "type": "Feature",
  "properties": {
    "iso:country": "GB",
    "wof:name": "SS99 2PP",
    "wof:placetype": "postalcode"
  },
  "geometry": {"coordinates":[0.723185,51.539846],"type":"Point"}
}
