{
  "type": "Feature",
  "properties": {
    "date:inception_lower":"1980-01-01",
    "date:inception_upper":"1980-01-31",
    "iso:country":"GB",
    "wof:name":"NE8 2QF",
    "wof:placetype":"postalcode"
},
  "geometry": {"coordinates":[-1.62189,54.956553],"type":"Point"}
}