{
  "type": "Feature",
  "properties": {
    "iso:country": "GB",
    "wof:name": "NE8 2QF",
    "wof:placetype": "postalcode"
  },
  "geometry": {"coordinates":[-1.62189,54.956553],"type":"Point"}
}
