{
  "type": "Feature",
  "properties": {
    "iso:country":"GB",
    "wof:name":"LL14 3YY",
    "wof:placetype":"postalcode"
},
  "geometry": {"coordinates":[-3.06448502336285,52.96833541376363],"type":"Point"}
}