{
  "type": "Feature",
  "properties": {
    "date:inception_lower": "1980-01-01",
    "date:inception_upper": "1980-01-01",
    "iso:country": "GB",
    "wof:name": "GL4 0TD",
    "wof:placetype": "postalcode"
  },
  "geometry": {"coordinates":[-2.256623,51.82416],"type":"Point"}
}
