{
  "type": "Feature",
  "properties": {
    "iso:country": "GB",
    "wof:name": "GL4 0TD",
    "wof:placetype": "postalcode"
  },
  "geometry": {"coordinates":[-2.256623,51.82416],"type":"Point"}
}
