{
  "type": "Feature",
  "properties": {
    "iso:country":"GB",
    "wof:name":"KT13 8TG",
    "wof:placetype":"postalcode"
},
  "geometry": {"coordinates":[-0.46060736307621,51.36831780664431],"type":"Point"}
}