{
  "type": "Feature",
  "properties": {
    "iso:country":"GB",
    "wof:name":"CM5 9PZ",
    "wof:placetype":"postalcode"
},
  "geometry": {"coordinates":[0.19879624142981,51.67136214735019],"type":"Point"}
}