{
  "type": "Feature",
  "properties": {
    "iso:country": "GB",
    "wof:name": "CM5 9PZ",
    "wof:placetype": "postalcode"
  },
  "geometry": {"coordinates":[0.195679,51.673043],"type":"Point"}
}
