{
  "type": "Feature",
  "properties": {
    "iso:country": "GB",
    "wof:name": "OX14 4NR",
    "wof:placetype": "postalcode"
  },
  "geometry": {"coordinates":[-1.268418,51.64631],"type":"Point"}
}
