{
  "type": "Feature",
  "properties": {
    "iso:country": "GB",
    "wof:name": "OX14 4NR",
    "wof:placetype": "postalcode"
  },
  "geometry": {"coordinates":[-1.268649,51.646321],"type":"Point"}
}
