{
  "type": "Feature",
  "properties": {
    "date:inception_lower": "1980-01-01",
    "date:inception_upper": "1980-01-01",
    "iso:country": "GB",
    "wof:name": "NE3 3HD",
    "wof:placetype": "postalcode"
  },
  "geometry": {"coordinates":[-1.630352,55.01106],"type":"Point"}
}
