{
  "type": "Feature",
  "properties": {
    "iso:country":"GB",
    "wof:name":"SW6 1LB",
    "wof:placetype":"postalcode"
},
  "geometry": {"coordinates":[-0.19786809983668,51.48414511656308],"type":"Point"}
}