{
  "type": "Feature",
  "properties": {
    "date:inception_lower":"1980-01-01",
    "date:inception_upper":"1980-01-31",
    "iso:country":"GB",
    "wof:name":"SW6 1LB",
    "wof:placetype":"postalcode"
},
  "geometry": {"coordinates":[-0.197868,51.484145],"type":"Point"}
}