{
  "type": "Feature",
  "properties": {
    "iso:country":"GB",
    "wof:name":"GU19 5NG",
    "wof:placetype":"postalcode"
},
  "geometry": {"coordinates":[-0.68699441648441,51.36089414594463],"type":"Point"}
}