{
  "type": "Feature",
  "properties": {
    "iso:country":"GB",
    "wof:name":"SE16 4UJ",
    "wof:placetype":"postalcode"
},
  "geometry": {"coordinates":[-0.06856220521636,51.50077321111144],"type":"Point"}
}