{
  "type": "Feature",
  "properties": {
    "iso:country":"GB",
    "wof:name":"TN21 0LE",
    "wof:placetype":"postalcode"
},
  "geometry": {"coordinates":[0.241560008612,50.91659317278523],"type":"Point"}
}