{
  "type": "Feature",
  "properties": {
    "iso:country": "GB",
    "wof:name": "TN21 0LE",
    "wof:placetype": "postalcode"
  },
  "geometry": {"coordinates":[0.241588,50.916588],"type":"Point"}
}
