{
  "type": "Feature",
  "properties": {
    "iso:country": "GB",
    "wof:name": "MK42 9QA",
    "wof:placetype": "postalcode"
  },
  "geometry": {"coordinates":[-0.47374,52.120036],"type":"Point"}
}
