{
  "type": "Feature",
  "properties": {
    "iso:country":"GB",
    "wof:name":"CW1 4AE",
    "wof:placetype":"postalcode"
},
  "geometry": {"coordinates":[-2.43235902752207,53.09879433672705],"type":"Point"}
}