{
  "type": "Feature",
  "properties": {
    "date:inception_lower": "2011-08-01",
    "date:inception_upper": "2011-08-01",
    "iso:country": "GB",
    "wof:name": "EH33 2AQ",
    "wof:placetype": "postalcode"
  },
  "geometry": {"coordinates":[-2.938004,55.94012],"type":"Point"}
}
