{
  "type": "Feature",
  "properties": {
    "iso:country":"GB",
    "wof:name":"EH33 2AQ",
    "wof:placetype":"postalcode"
},
  "geometry": {"coordinates":[-2.93800412677998,55.94012025553489],"type":"Point"}
}