{
  "type": "Feature",
  "properties": {
    "iso:country": "GB",
    "wof:name": "EH33 2AQ",
    "wof:placetype": "postalcode"
  },
  "geometry": {"coordinates":[-2.938004,55.94012],"type":"Point"}
}
