{
  "type": "Feature",
  "properties": {
    "date:inception_lower":"2005-11-01",
    "date:inception_upper":"2005-11-30",
    "iso:country":"GB",
    "wof:name":"B68 9LF",
    "wof:placetype":"postalcode"
},
  "geometry": {"coordinates":[-2.003549,52.478793],"type":"Point"}
}