{
  "type": "Feature",
  "properties": {
    "iso:country":"GB",
    "wof:name":"BD23 1DR",
    "wof:placetype":"postalcode"
},
  "geometry": {"coordinates":[-2.02221531988826,53.9603037807893],"type":"Point"}
}