{
  "type": "Feature",
  "properties": {
    "iso:country": "GB",
    "wof:name": "GU34 2FB",
    "wof:placetype": "postalcode"
  },
  "geometry": {"coordinates":[-0.9693,51.159731],"type":"Point"}
}
