{
  "type": "Feature",
  "properties": {
    "iso:country": "GB",
    "wof:name": "FK8 2AX",
    "wof:placetype": "postalcode"
  },
  "geometry": {"coordinates":[-3.942757,56.106746],"type":"Point"}
}
