{
  "type": "Feature",
  "properties": {
    "iso:country":"GB",
    "wof:name":"FK8 2AX",
    "wof:placetype":"postalcode"
},
  "geometry": {"coordinates":[-3.94279245368619,56.10669923137935],"type":"Point"}
}