{
  "type": "Feature",
  "properties": {
    "iso:country": "GB",
    "wof:name": "FK8 2AX",
    "wof:placetype": "postalcode"
  },
  "geometry": {"coordinates":[-3.942773,56.106755],"type":"Point"}
}
