{
  "type": "Feature",
  "properties": {
    "iso:country":"GB",
    "wof:name":"FY2 0QY",
    "wof:placetype":"postalcode"
},
  "geometry": {"coordinates":[-3.02806775802302,53.84424417455761],"type":"Point"}
}