{
  "type": "Feature",
  "properties": {
    "date:inception_lower":"1980-01-01",
    "date:inception_upper":"1980-01-31",
    "iso:country":"GB",
    "wof:name":"FY2 0QY",
    "wof:placetype":"postalcode"
},
  "geometry": {"coordinates":[-3.028068,53.844244],"type":"Point"}
}