{
  "type": "Feature",
  "properties": {
    "iso:country":"GB",
    "wof:name":"WR14 4LU",
    "wof:placetype":"postalcode"
},
  "geometry": {"coordinates":[-2.33601535801941,52.12130294125534],"type":"Point"}
}