{
  "type": "Feature",
  "properties": {
    "iso:country":"GB",
    "wof:name":"EC2M 7LS",
    "wof:placetype":"postalcode"
},
  "geometry": {"coordinates":[-0.08580494380626,51.51874431827586],"type":"Point"}
}