{
  "type": "Feature",
  "properties": {
    "date:inception_lower": "1990-02-01",
    "date:inception_upper": "1990-02-01",
    "iso:country": "GB",
    "wof:name": "SL7 1XT",
    "wof:placetype": "postalcode"
  },
  "geometry": {"coordinates":[-0.76697,51.57347],"type":"Point"}
}
