{
  "type": "Feature",
  "properties": {
    "iso:country":"GB",
    "wof:name":"SL7 1XT",
    "wof:placetype":"postalcode"
},
  "geometry": {"coordinates":[-0.76696974115053,51.57347014520112],"type":"Point"}
}