{
  "type": "Feature",
  "properties": {
    "iso:country": "GB",
    "wof:name": "SL7 1XT",
    "wof:placetype": "postalcode"
  },
  "geometry": {"coordinates":[-0.76697,51.57347],"type":"Point"}
}
