{
  "type": "Feature",
  "properties": {
    "iso:country":"GB",
    "wof:name":"KT10 0HF",
    "wof:placetype":"postalcode"
},
  "geometry": {"coordinates":[-0.34320730868353,51.35958543764341],"type":"Point"}
}