{
  "type": "Feature",
  "properties": {
    "iso:country": "GB",
    "wof:name": "SY21 8AD",
    "wof:placetype": "postalcode"
  },
  "geometry": {"coordinates":[-3.18868,52.604258],"type":"Point"}
}
