{
  "type": "Feature",
  "properties": {
    "date:inception_lower": "1980-01-01",
    "date:inception_upper": "1980-01-01",
    "iso:country": "GB",
    "wof:name": "EN8 9PG",
    "wof:placetype": "postalcode"
  },
  "geometry": {"coordinates":[-0.046801,51.706152],"type":"Point"}
}
