{
  "type": "Feature",
  "properties": {
    "iso:country": "GB",
    "wof:name": "HR5 3NT",
    "wof:placetype": "postalcode"
  },
  "geometry": {"coordinates":[-3.143208,52.19071],"type":"Point"}
}
