{
  "type": "Feature",
  "properties": {
    "iso:country":"GB",
    "wof:name":"HR5 3NT",
    "wof:placetype":"postalcode"
},
  "geometry": {"coordinates":[-3.14320773555899,52.19070972284555],"type":"Point"}
}