{
  "type": "Feature",
  "properties": {
    "iso:country":"GB",
    "wof:name":"ST17 4LL",
    "wof:placetype":"postalcode"
},
  "geometry": {"coordinates":[-2.1065854546578,52.80032550541056],"type":"Point"}
}