{
  "type": "Feature",
  "properties": {
    "iso:country": "GB",
    "wof:name": "CW5 5TG",
    "wof:placetype": "postalcode"
  },
  "geometry": {"coordinates":[-2.523718,53.063433],"type":"Point"}
}
