{
  "type": "Feature",
  "properties": {
    "iso:country":"GB",
    "wof:name":"CW5 5TG",
    "wof:placetype":"postalcode"
},
  "geometry": {"coordinates":[-2.52371778412408,53.06343250357838],"type":"Point"}
}