{
  "type": "Feature",
  "properties": {
    "date:inception_lower": "2009-05-01",
    "date:inception_upper": "2009-05-01",
    "iso:country": "GB",
    "wof:name": "WN2 3AS",
    "wof:placetype": "postalcode"
  },
  "geometry": {"coordinates":[-2.577936,53.535913],"type":"Point"}
}
