{
  "type": "Feature",
  "properties": {
    "iso:country":"GB",
    "wof:name":"WN2 3AS",
    "wof:placetype":"postalcode"
},
  "geometry": {"coordinates":[-2.57793558202329,53.5359134748354],"type":"Point"}
}