{
  "type": "Feature",
  "properties": {
    "date:inception_lower":"1986-07-01",
    "date:inception_upper":"1986-07-31",
    "iso:country":"GB",
    "wof:name":"BA14 8DS",
    "wof:placetype":"postalcode"
},
  "geometry": {"coordinates":[-2.202547,51.321658],"type":"Point"}
}