{
  "type": "Feature",
  "properties": {
    "iso:country":"GB",
    "wof:name":"WA12 9HQ",
    "wof:placetype":"postalcode"
},
  "geometry": {"coordinates":[-2.65445456704361,53.45613185621937],"type":"Point"}
}