{
  "type": "Feature",
  "properties": {
    "date:inception_lower": "1993-01-01",
    "date:inception_upper": "1993-01-01",
    "iso:country": "GB",
    "wof:name": "WA12 9HQ",
    "wof:placetype": "postalcode"
  },
  "geometry": {"coordinates":[-2.654455,53.456132],"type":"Point"}
}
