{
  "type": "Feature",
  "properties": {
    "iso:country": "GB",
    "wof:name": "LA23 1NT",
    "wof:placetype": "postalcode"
  },
  "geometry": {"coordinates":[-2.913055,54.403633],"type":"Point"}
}
