{
  "type": "Feature",
  "properties": {
    "iso:country": "GB",
    "wof:name": "L30 1PR",
    "wof:placetype": "postalcode"
  },
  "geometry": {"coordinates":[-2.963608,53.47482],"type":"Point"}
}
