{
  "type": "Feature",
  "properties": {
    "date:inception_lower": "1987-04-01",
    "date:inception_upper": "1987-04-01",
    "iso:country": "GB",
    "wof:name": "TF3 5AS",
    "wof:placetype": "postalcode"
  },
  "geometry": {"coordinates":[-2.47078,52.686925],"type":"Point"}
}
