{
  "type": "Feature",
  "properties": {
    "iso:country":"GB",
    "wof:name":"KT22 8RW",
    "wof:placetype":"postalcode"
},
  "geometry": {"coordinates":[-0.31811879628232,51.29669358124033],"type":"Point"}
}