{
  "type": "Feature",
  "properties": {
    "iso:country": "GB",
    "wof:name": "G41 1PZ",
    "wof:placetype": "postalcode"
  },
  "geometry": {"coordinates":[-4.258069,55.846436],"type":"Point"}
}
