{
  "type": "Feature",
  "properties": {
    "iso:country":"GB",
    "wof:name":"G41 1PZ",
    "wof:placetype":"postalcode"
},
  "geometry": {"coordinates":[-4.25806886459479,55.84643624908752],"type":"Point"}
}