{
  "type": "Feature",
  "properties": {
    "date:inception_lower":"2008-07-01",
    "date:inception_upper":"2008-07-31",
    "iso:country":"GB",
    "wof:name":"S63 7BU",
    "wof:placetype":"postalcode"
},
  "geometry": {"coordinates":[-1.333951,53.511728],"type":"Point"}
}