{
  "type": "Feature",
  "properties": {
    "iso:country": "GB",
    "wof:name": "S63 7BU",
    "wof:placetype": "postalcode"
  },
  "geometry": {"coordinates":[-1.333951,53.511728],"type":"Point"}
}
