{
  "type": "Feature",
  "properties": {
    "iso:country":"GB",
    "wof:name":"S63 7BU",
    "wof:placetype":"postalcode"
},
  "geometry": {"coordinates":[-1.33395061480539,53.51172814077923],"type":"Point"}
}