{
  "type": "Feature",
  "properties": {
    "iso:country":"GB",
    "wof:name":"PE27 6AE",
    "wof:placetype":"postalcode"
},
  "geometry": {"coordinates":[-0.09555408010032,52.33426089697799],"type":"Point"}
}