{
  "type": "Feature",
  "properties": {
    "iso:country": "GB",
    "wof:name": "PE27 6AE",
    "wof:placetype": "postalcode"
  },
  "geometry": {"coordinates":[-0.095554,52.334261],"type":"Point"}
}
