{
  "type": "Feature",
  "properties": {
    "date:inception_lower":"2013-01-01",
    "date:inception_upper":"2013-01-31",
    "iso:country":"GB",
    "wof:name":"PE27 6AE",
    "wof:placetype":"postalcode"
},
  "geometry": {"coordinates":[-0.095554,52.334261],"type":"Point"}
}