{
  "type": "Feature",
  "properties": {
    "iso:country":"GB",
    "wof:name":"SA5 8PR",
    "wof:placetype":"postalcode"
},
  "geometry": {"coordinates":[-3.95706263754863,51.64158540593102],"type":"Point"}
}