{
  "type": "Feature",
  "properties": {
    "date:inception_lower":"1980-01-01",
    "date:inception_upper":"1980-01-31",
    "iso:country":"GB",
    "wof:name":"SA5 8PR",
    "wof:placetype":"postalcode"
},
  "geometry": {"coordinates":[-3.957009,51.6416],"type":"Point"}
}