{
  "type": "Feature",
  "properties": {
    "iso:country": "GB",
    "wof:name": "SA9 1EL",
    "wof:placetype": "postalcode"
  },
  "geometry": {"coordinates":[-3.769089,51.7684],"type":"Point"}
}
