{
  "type": "Feature",
  "properties": {
    "date:inception_lower": "1980-01-01",
    "date:inception_upper": "1980-01-01",
    "iso:country": "GB",
    "wof:name": "IP23 7EE",
    "wof:placetype": "postalcode"
  },
  "geometry": {"coordinates":[1.094699,52.271417],"type":"Point"}
}
