{
  "type": "Feature",
  "properties": {
    "iso:country":"GB",
    "wof:name":"IP23 7EE",
    "wof:placetype":"postalcode"
},
  "geometry": {"coordinates":[1.09468326314976,52.27139043737211],"type":"Point"}
}