{
  "type": "Feature",
  "properties": {
    "iso:country":"GB",
    "wof:name":"CB7 5NR",
    "wof:placetype":"postalcode"
},
  "geometry": {"coordinates":[0.40224389577985,52.31067168939928],"type":"Point"}
}