{
  "type": "Feature",
  "properties": {
    "iso:country": "GB",
    "wof:name": "CB7 5NR",
    "wof:placetype": "postalcode"
  },
  "geometry": {"coordinates":[0.402244,52.310672],"type":"Point"}
}
