{
  "type": "Feature",
  "properties": {
    "iso:country":"GB",
    "wof:name":"SO41 6DE",
    "wof:placetype":"postalcode"
},
  "geometry": {"coordinates":[-1.60470463579225,50.76786731950415],"type":"Point"}
}