{
  "type": "Feature",
  "properties": {
    "iso:country": "GB",
    "wof:name": "SO41 6DE",
    "wof:placetype": "postalcode"
  },
  "geometry": {"coordinates":[-1.604705,50.767867],"type":"Point"}
}
