{
  "type": "Feature",
  "properties": {
    "date:inception_lower":"1986-01-01",
    "date:inception_upper":"1986-01-31",
    "iso:country":"GB",
    "wof:name":"SO41 6DE",
    "wof:placetype":"postalcode"
},
  "geometry": {"coordinates":[-1.604705,50.767867],"type":"Point"}
}