{
  "type": "Feature",
  "properties": {
    "iso:country": "GB",
    "wof:name": "LS26 0TF",
    "wof:placetype": "postalcode"
  },
  "geometry": {"coordinates":[-1.47437,53.744353],"type":"Point"}
}
