{
  "type": "Feature",
  "properties": {
    "iso:country":"GB",
    "wof:name":"LS26 0TF",
    "wof:placetype":"postalcode"
},
  "geometry": {"coordinates":[-1.47436982345023,53.74435335675913],"type":"Point"}
}