{
  "type": "Feature",
  "properties": {
    "iso:country":"GB",
    "wof:name":"PE24 5RS",
    "wof:placetype":"postalcode"
},
  "geometry": {"coordinates":[0.32667940525246,53.22534345395316],"type":"Point"}
}