{
  "type": "Feature",
  "properties": {
    "iso:country":"GB",
    "wof:name":"CM7 4TR",
    "wof:placetype":"postalcode"
},
  "geometry": {"coordinates":[0.41284581461681,51.95125200849501],"type":"Point"}
}