{
  "type": "Feature",
  "properties": {
    "iso:country":"GB",
    "wof:name":"PE24 4PE",
    "wof:placetype":"postalcode"
},
  "geometry": {"coordinates":[0.24549121343864,53.12074638573751],"type":"Point"}
}