{
  "type": "Feature",
  "properties": {
    "iso:country": "GB",
    "wof:name": "PE24 4PE",
    "wof:placetype": "postalcode"
  },
  "geometry": {"coordinates":[0.24544,53.120586],"type":"Point"}
}
