{
  "type": "Feature",
  "properties": {
    "date:inception_lower": "1980-01-01",
    "date:inception_upper": "1980-01-01",
    "iso:country": "GB",
    "wof:name": "CH1 1NW",
    "wof:placetype": "postalcode"
  },
  "geometry": {"coordinates":[-2.891058,53.189399],"type":"Point"}
}
