{
  "type": "Feature",
  "properties": {
    "iso:country":"GB",
    "wof:name":"CW11 3AZ",
    "wof:placetype":"postalcode"
},
  "geometry": {"coordinates":[-2.38217155994777,53.13334025729363],"type":"Point"}
}