{
  "type": "Feature",
  "properties": {
    "date:inception_lower":"2013-12-01",
    "date:inception_upper":"2013-12-31",
    "iso:country":"GB",
    "wof:name":"CW11 3AZ",
    "wof:placetype":"postalcode"
},
  "geometry": {"coordinates":[-2.382617,53.133005],"type":"Point"}
}