{
  "type": "Feature",
  "properties": {
    "date:inception_lower": "2013-12-01",
    "date:inception_upper": "2013-12-01",
    "iso:country": "GB",
    "wof:name": "CW11 3AZ",
    "wof:placetype": "postalcode"
  },
  "geometry": {"coordinates":[-2.38269,53.132888],"type":"Point"}
}
