{
  "type": "Feature",
  "properties": {
    "iso:country": "GB",
    "wof:name": "CW11 3AZ",
    "wof:placetype": "postalcode"
  },
  "geometry": {"coordinates":[-2.382617,53.133005],"type":"Point"}
}
