{
  "type": "Feature",
  "properties": {
    "iso:country": "GB",
    "wof:name": "LL65 2DZ",
    "wof:placetype": "postalcode"
  },
  "geometry": {"coordinates":[-4.596005,53.261101],"type":"Point"}
}
