{
  "type": "Feature",
  "properties": {
    "iso:country":"GB",
    "wof:name":"LL65 2DZ",
    "wof:placetype":"postalcode"
},
  "geometry": {"coordinates":[-4.59600529298134,53.26110101623091],"type":"Point"}
}