{
  "type": "Feature",
  "properties": {
    "iso:country":"GB",
    "wof:name":"IP31 1ST",
    "wof:placetype":"postalcode"
},
  "geometry": {"coordinates":[0.71190483953353,52.2692075748211],"type":"Point"}
}