{
  "type": "Feature",
  "properties": {
    "date:inception_lower":"1980-01-01",
    "date:inception_upper":"1980-01-31",
    "iso:country":"GB",
    "wof:name":"IP31 1ST",
    "wof:placetype":"postalcode"
},
  "geometry": {"coordinates":[0.711905,52.269208],"type":"Point"}
}