{
  "type": "Feature",
  "properties": {
    "iso:country":"GB",
    "wof:name":"YO43 3QY",
    "wof:placetype":"postalcode"
},
  "geometry": {"coordinates":[-0.66522263680519,53.86436585565836],"type":"Point"}
}