{
  "type": "Feature",
  "properties": {
    "iso:country": "GB",
    "wof:name": "YO43 3QY",
    "wof:placetype": "postalcode"
  },
  "geometry": {"coordinates":[-0.665223,53.864366],"type":"Point"}
}
