{
  "type": "Feature",
  "properties": {
    "iso:country":"GB",
    "wof:name":"CO10 5LA",
    "wof:placetype":"postalcode"
},
  "geometry": {"coordinates":[0.81438324705004,52.02941602143716],"type":"Point"}
}