{
  "type": "Feature",
  "properties": {
    "iso:country": "GB",
    "wof:name": "CO10 5LA",
    "wof:placetype": "postalcode"
  },
  "geometry": {"coordinates":[0.814445,52.029437],"type":"Point"}
}
