{
  "type": "Feature",
  "properties": {
    "date:inception_lower": "1994-05-01",
    "date:inception_upper": "1994-05-01",
    "iso:country": "GB",
    "wof:name": "DE6 5LE",
    "wof:placetype": "postalcode"
  },
  "geometry": {"coordinates":[-1.790643,52.86005],"type":"Point"}
}
