{
  "type": "Feature",
  "properties": {
    "date:inception_lower":"1980-01-01",
    "date:inception_upper":"1980-01-31",
    "iso:country":"GB",
    "wof:name":"BS3 5HS",
    "wof:placetype":"postalcode"
},
  "geometry": {"coordinates":[-2.59072,51.435257],"type":"Point"}
}