{
  "type": "Feature",
  "properties": {
    "iso:country":"GB",
    "wof:name":"BS3 5HS",
    "wof:placetype":"postalcode"
},
  "geometry": {"coordinates":[-2.59071994152863,51.4352570152713],"type":"Point"}
}