{
  "type": "Feature",
  "properties": {
    "date:inception_lower":"1995-07-01",
    "date:inception_upper":"1995-07-31",
    "iso:country":"GB",
    "wof:name":"RG18 3BF",
    "wof:placetype":"postalcode"
},
  "geometry": {"coordinates":[-1.263308,51.410201],"type":"Point"}
}