{
  "type": "Feature",
  "properties": {
    "iso:country":"GB",
    "wof:name":"RG18 3BF",
    "wof:placetype":"postalcode"
},
  "geometry": {"coordinates":[-1.26330836599789,51.41020084957827],"type":"Point"}
}