{
  "type": "Feature",
  "properties": {
    "iso:country":"GB",
    "wof:name":"BS16 2TW",
    "wof:placetype":"postalcode"
},
  "geometry": {"coordinates":[-2.51272243231279,51.48944798525991],"type":"Point"}
}