{
  "type": "Feature",
  "properties": {
    "iso:country":"GB",
    "wof:name":"SN4 8DD",
    "wof:placetype":"postalcode"
},
  "geometry": {"coordinates":[-1.89484783805494,51.54230462813172],"type":"Point"}
}