{
  "type": "Feature",
  "properties": {
    "iso:country":"GB",
    "wof:name":"GL54 5SB",
    "wof:placetype":"postalcode"
},
  "geometry": {"coordinates":[-1.89152322748945,51.97002491906715],"type":"Point"}
}