{
  "type": "Feature",
  "properties": {
    "iso:country": "GB",
    "wof:name": "GL54 5SB",
    "wof:placetype": "postalcode"
  },
  "geometry": {"coordinates":[-1.891523,51.970025],"type":"Point"}
}
