{
  "type": "Feature",
  "properties": {
    "date:inception_lower": "2003-03-01",
    "date:inception_upper": "2003-03-01",
    "iso:country": "GB",
    "wof:name": "WS11 4PD",
    "wof:placetype": "postalcode"
  },
  "geometry": {"coordinates":[-2.030194,52.706977],"type":"Point"}
}
