{
  "type": "Feature",
  "properties": {
    "date:inception_lower": "1980-01-01",
    "date:inception_upper": "1980-01-01",
    "iso:country": "GB",
    "wof:name": "BH16 5LG",
    "wof:placetype": "postalcode"
  },
  "geometry": {"coordinates":[-2.035375,50.736769],"type":"Point"}
}
