{
  "type": "Feature",
  "properties": {
    "iso:country":"GB",
    "wof:name":"BH16 5LG",
    "wof:placetype":"postalcode"
},
  "geometry": {"coordinates":[-2.03537474424607,50.73676886811559],"type":"Point"}
}