{
  "type": "Feature",
  "properties": {
    "date:inception_lower": "1980-01-01",
    "date:inception_upper": "1980-01-01",
    "iso:country": "GB",
    "wof:name": "SG7 6QA",
    "wof:placetype": "postalcode"
  },
  "geometry": {"coordinates":[-0.189049,51.989988],"type":"Point"}
}
