{
  "type": "Feature",
  "properties": {
    "iso:country":"GB",
    "wof:name":"SG7 6QA",
    "wof:placetype":"postalcode"
},
  "geometry": {"coordinates":[-0.18904917505093,51.98998803986351],"type":"Point"}
}