{
  "type": "Feature",
  "properties": {
    "iso:country":"GB",
    "wof:name":"CB3 0GU",
    "wof:placetype":"postalcode"
},
  "geometry": {"coordinates":[0.09481180603683,52.22253452268198],"type":"Point"}
}