{
  "type": "Feature",
  "properties": {
    "iso:country": "GB",
    "wof:name": "CB3 0GU",
    "wof:placetype": "postalcode"
  },
  "geometry": {"coordinates":[0.094812,52.222535],"type":"Point"}
}
