{
  "type": "Feature",
  "properties": {
    "iso:country": "GB",
    "wof:name": "BA12 9EH",
    "wof:placetype": "postalcode"
  },
  "geometry": {"coordinates":[-2.161596,51.20234],"type":"Point"}
}
