{
  "type": "Feature",
  "properties": {
    "iso:country":"GB",
    "wof:name":"ME10 2EA",
    "wof:placetype":"postalcode"
},
  "geometry": {"coordinates":[0.73979601290493,51.36121953462877],"type":"Point"}
}