{
  "type": "Feature",
  "properties": {
    "iso:country": "GB",
    "wof:name": "GL56 9RH",
    "wof:placetype": "postalcode"
  },
  "geometry": {"coordinates":[-1.744116,52.004834],"type":"Point"}
}
