{
  "type": "Feature",
  "properties": {
    "date:inception_lower": "1980-01-01",
    "date:inception_upper": "1980-01-01",
    "iso:country": "GB",
    "wof:name": "GL56 9RH",
    "wof:placetype": "postalcode"
  },
  "geometry": {"coordinates":[-1.744149,52.004872],"type":"Point"}
}
