{
  "type": "Feature",
  "properties": {
    "iso:country":"GB",
    "wof:name":"DL14 9NG",
    "wof:placetype":"postalcode"
},
  "geometry": {"coordinates":[-1.73484818595872,54.62879030084279],"type":"Point"}
}