{
  "type": "Feature",
  "properties": {
    "iso:country":"GB",
    "wof:name":"NE32 5ND",
    "wof:placetype":"postalcode"
},
  "geometry": {"coordinates":[-1.49538052693639,54.96964526413865],"type":"Point"}
}