{
  "type": "Feature",
  "properties": {
    "date:inception_lower": "1980-01-01",
    "date:inception_upper": "1980-01-01",
    "iso:country": "GB",
    "wof:name": "NE32 5ND",
    "wof:placetype": "postalcode"
  },
  "geometry": {"coordinates":[-1.49538,54.969645],"type":"Point"}
}
