{
  "type": "Feature",
  "properties": {
    "iso:country": "GB",
    "wof:name": "PR4 0DT",
    "wof:placetype": "postalcode"
  },
  "geometry": {"coordinates":[-2.763719,53.788126],"type":"Point"}
}
