{
  "type": "Feature",
  "properties": {
    "date:inception_lower": "1980-01-01",
    "date:inception_upper": "1980-01-01",
    "iso:country": "GB",
    "wof:name": "TN22 3DP",
    "wof:placetype": "postalcode"
  },
  "geometry": {"coordinates":[0.085395,51.005553],"type":"Point"}
}
