{
  "type": "Feature",
  "properties": {
    "iso:country": "GB",
    "wof:name": "TN22 3DP",
    "wof:placetype": "postalcode"
  },
  "geometry": {"coordinates":[0.085395,51.005553],"type":"Point"}
}
