{
  "type": "Feature",
  "properties": {
    "iso:country":"GB",
    "wof:name":"IP7 7NH",
    "wof:placetype":"postalcode"
},
  "geometry": {"coordinates":[0.89510469019833,52.12150265815961],"type":"Point"}
}