{
  "type": "Feature",
  "properties": {
    "iso:country":"GB",
    "wof:name":"TW7 6PB",
    "wof:placetype":"postalcode"
},
  "geometry": {"coordinates":[-0.33539302011912,51.47283326986533],"type":"Point"}
}