{
  "type": "Feature",
  "properties": {
    "iso:country":"GB",
    "wof:name":"NG1 2GR",
    "wof:placetype":"postalcode"
},
  "geometry": {"coordinates":[-1.14703408956713,52.95249811811411],"type":"Point"}
}