{
  "type": "Feature",
  "properties": {
    "date:inception_lower": "1980-01-01",
    "date:inception_upper": "1980-01-01",
    "iso:country": "GB",
    "wof:name": "ST18 0AU",
    "wof:placetype": "postalcode"
  },
  "geometry": {"coordinates":[-2.083507,52.838873],"type":"Point"}
}
