{
  "type": "Feature",
  "properties": {
    "date:inception_lower": "1980-01-01",
    "date:inception_upper": "1980-01-01",
    "iso:country": "GB",
    "wof:name": "SA44 4UL",
    "wof:placetype": "postalcode"
  },
  "geometry": {"coordinates":[-4.281242,52.09198],"type":"Point"}
}
