{
  "type": "Feature",
  "properties": {
    "date:inception_lower": "1980-01-01",
    "date:inception_upper": "1980-01-01",
    "iso:country": "GB",
    "wof:name": "PR3 1DH",
    "wof:placetype": "postalcode"
  },
  "geometry": {"coordinates":[-2.722957,53.95235],"type":"Point"}
}
