{
  "type": "Feature",
  "properties": {
    "iso:country":"GB",
    "wof:name":"BN10 8EZ",
    "wof:placetype":"postalcode"
},
  "geometry": {"coordinates":[0.0086215651217,50.80427719884365],"type":"Point"}
}