{
  "type": "Feature",
  "properties": {
    "iso:country":"GB",
    "wof:name":"SE1 7QN",
    "wof:placetype":"postalcode"
},
  "geometry": {"coordinates":[-0.10707313971193,51.49873934312649],"type":"Point"}
}