{
  "type": "Feature",
  "properties": {
    "iso:country": "GB",
    "wof:name": "SE1 7QN",
    "wof:placetype": "postalcode"
  },
  "geometry": {"coordinates":[-0.107073,51.498739],"type":"Point"}
}
