{
  "type": "Feature",
  "properties": {
    "iso:country": "GB",
    "wof:name": "IP1 3AD",
    "wof:placetype": "postalcode"
  },
  "geometry": {"coordinates":[1.155025,52.057745],"type":"Point"}
}
