{
  "type": "Feature",
  "properties": {
    "iso:country": "GB",
    "wof:name": "LS18 4EP",
    "wof:placetype": "postalcode"
  },
  "geometry": {"coordinates":[-1.64186,53.831166],"type":"Point"}
}
