{
  "type": "Feature",
  "properties": {
    "iso:country":"GB",
    "wof:name":"LS18 4EP",
    "wof:placetype":"postalcode"
},
  "geometry": {"coordinates":[-1.64186052381315,53.83116560650375],"type":"Point"}
}