{
  "type": "Feature",
  "properties": {
    "iso:country":"GB",
    "wof:name":"OL1 4LT",
    "wof:placetype":"postalcode"
},
  "geometry": {"coordinates":[-2.09379287071283,53.55622167554159],"type":"Point"}
}