{
  "type": "Feature",
  "properties": {
    "date:inception_lower": "1980-01-01",
    "date:inception_upper": "1980-01-01",
    "iso:country": "GB",
    "wof:name": "OL1 4LT",
    "wof:placetype": "postalcode"
  },
  "geometry": {"coordinates":[-2.093793,53.556222],"type":"Point"}
}
