{
  "type": "Feature",
  "properties": {
    "iso:country":"GB",
    "wof:name":"WD19 6XL",
    "wof:placetype":"postalcode"
},
  "geometry": {"coordinates":[-0.38592523716094,51.61774760127656],"type":"Point"}
}