{
  "type": "Feature",
  "properties": {
    "date:inception_lower": "2000-10-01",
    "date:inception_upper": "2000-10-01",
    "iso:country": "GB",
    "wof:name": "WD19 6XL",
    "wof:placetype": "postalcode"
  },
  "geometry": {"coordinates":[-0.385925,51.617748],"type":"Point"}
}
