{
  "type": "Feature",
  "properties": {
    "iso:country": "GB",
    "wof:name": "WD19 6XL",
    "wof:placetype": "postalcode"
  },
  "geometry": {"coordinates":[-0.385925,51.617748],"type":"Point"}
}
