{
  "type": "Feature",
  "properties": {
    "iso:country":"GB",
    "wof:name":"CT6 5AG",
    "wof:placetype":"postalcode"
},
  "geometry": {"coordinates":[1.12899331755908,51.37073981096049],"type":"Point"}
}