{
  "type": "Feature",
  "properties": {
    "date:inception_lower": "2009-01-01",
    "date:inception_upper": "2009-01-01",
    "iso:country": "GB",
    "wof:name": "CT6 5AG",
    "wof:placetype": "postalcode"
  },
  "geometry": {"coordinates":[1.128993,51.37074],"type":"Point"}
}
