{
  "type": "Feature",
  "properties": {
    "iso:country":"GB",
    "wof:name":"LE13 1DT",
    "wof:placetype":"postalcode"
},
  "geometry": {"coordinates":[-0.87610070565288,52.75709844739357],"type":"Point"}
}