{
  "type": "Feature",
  "properties": {
    "date:inception_lower": "2018-04-01",
    "date:inception_upper": "2018-04-01",
    "iso:country": "GB",
    "wof:name": "DE15 0TS",
    "wof:placetype": "postalcode"
  },
  "geometry": {"coordinates":[-1.607026,52.816345],"type":"Point"}
}
