{
  "type": "Feature",
  "properties": {
    "iso:country": "GB",
    "wof:name": "TN16 2NG",
    "wof:placetype": "postalcode"
  },
  "geometry": {"coordinates":[0.034091,51.306231],"type":"Point"}
}
