{
  "type": "Feature",
  "properties": {
    "iso:country":"GB",
    "wof:name":"W8 9ZY",
    "wof:placetype":"postalcode"
},
  "geometry": {"coordinates":[-0.19858635419466,51.49844519008422],"type":"Point"}
}