{
  "type": "Feature",
  "properties": {
    "iso:country":"GB",
    "wof:name":"EN2 9BS",
    "wof:placetype":"postalcode"
},
  "geometry": {"coordinates":[-0.0967950530157,51.67917742450631],"type":"Point"}
}