{
  "type": "Feature",
  "properties": {
    "iso:country":"GB",
    "wof:name":"KA21 5QY",
    "wof:placetype":"postalcode"
},
  "geometry": {"coordinates":[-4.78003115152333,55.63992814290471],"type":"Point"}
}