{
  "type": "Feature",
  "properties": {
    "iso:country":"GB",
    "wof:name":"SW1V 1TH",
    "wof:placetype":"postalcode"
},
  "geometry": {"coordinates":[-0.13896078900942,51.49369232453996],"type":"Point"}
}