{
  "type": "Feature",
  "properties": {
    "iso:country":"GB",
    "wof:name":"DE56 1TZ",
    "wof:placetype":"postalcode"
},
  "geometry": {"coordinates":[-1.48315327457915,53.0211077358648],"type":"Point"}
}