{
  "type": "Feature",
  "properties": {
    "iso:country":"GB",
    "wof:name":"SO51 7NA",
    "wof:placetype":"postalcode"
},
  "geometry": {"coordinates":[-1.48218911929997,50.99355832119601],"type":"Point"}
}