{
  "type": "Feature",
  "properties": {
    "date:inception_lower": "1993-01-01",
    "date:inception_upper": "1993-01-01",
    "iso:country": "GB",
    "wof:name": "SO51 7NA",
    "wof:placetype": "postalcode"
  },
  "geometry": {"coordinates":[-1.482179,50.993551],"type":"Point"}
}
