{
  "type": "Feature",
  "properties": {
    "iso:country":"GB",
    "wof:name":"CF44 9QD",
    "wof:placetype":"postalcode"
},
  "geometry": {"coordinates":[-3.51660214893491,51.73877664843617],"type":"Point"}
}