{
  "type": "Feature",
  "properties": {
    "date:inception_lower": "2005-06-01",
    "date:inception_upper": "2005-06-01",
    "iso:country": "GB",
    "wof:name": "CF44 9QD",
    "wof:placetype": "postalcode"
  },
  "geometry": {"coordinates":[-3.516602,51.738777],"type":"Point"}
}
