{
  "type": "Feature",
  "properties": {
    "iso:country":"GB",
    "wof:name":"KT6 7UH",
    "wof:placetype":"postalcode"
},
  "geometry": {"coordinates":[-0.30004404556658,51.38095380489298],"type":"Point"}
}