{
  "type": "Feature",
  "properties": {
    "iso:country":"GB",
    "wof:name":"GL14 2YQ",
    "wof:placetype":"postalcode"
},
  "geometry": {"coordinates":[-2.51198871297912,51.82674192066204],"type":"Point"}
}