{
  "type": "Feature",
  "properties": {
    "iso:country":"GB",
    "wof:name":"WN1 3NX",
    "wof:placetype":"postalcode"
},
  "geometry": {"coordinates":[-2.62266313402631,53.55279395451825],"type":"Point"}
}