{
  "type": "Feature",
  "properties": {
    "iso:country":"GB",
    "wof:name":"KA20 3AW",
    "wof:placetype":"postalcode"
},
  "geometry": {"coordinates":[-4.74970270226948,55.64098960874218],"type":"Point"}
}