{
  "type": "Feature",
  "properties": {
    "iso:country":"GB",
    "wof:name":"TA4 2JX",
    "wof:placetype":"postalcode"
},
  "geometry": {"coordinates":[-3.31205330288562,51.04183847097171],"type":"Point"}
}