{
  "type": "Feature",
  "properties": {
    "iso:country": "GB",
    "wof:name": "TA4 2JX",
    "wof:placetype": "postalcode"
  },
  "geometry": {"coordinates":[-3.312065,51.041834],"type":"Point"}
}
