{
  "type": "Feature",
  "properties": {
    "iso:country":"GB",
    "wof:name":"LS19 7BB",
    "wof:placetype":"postalcode"
},
  "geometry": {"coordinates":[-1.67127843090368,53.87548827312789],"type":"Point"}
}