{
  "type": "Feature",
  "properties": {
    "iso:country":"GB",
    "wof:name":"B90 2JT",
    "wof:placetype":"postalcode"
},
  "geometry": {"coordinates":[-1.84063047824444,52.40952634043893],"type":"Point"}
}