{
  "type": "Feature",
  "properties": {
    "date:inception_lower":"1994-05-01",
    "date:inception_upper":"1994-05-31",
    "iso:country":"GB",
    "wof:name":"B77 4PR",
    "wof:placetype":"postalcode"
},
  "geometry": {"coordinates":[-1.641409,52.617576],"type":"Point"}
}