{
  "type": "Feature",
  "properties": {
    "iso:country":"GB",
    "wof:name":"B77 4PR",
    "wof:placetype":"postalcode"
},
  "geometry": {"coordinates":[-1.6414093840606,52.61757640557063],"type":"Point"}
}