{
  "type": "Feature",
  "properties": {
    "iso:country": "GB",
    "wof:name": "B77 4PR",
    "wof:placetype": "postalcode"
  },
  "geometry": {"coordinates":[-1.641409,52.617576],"type":"Point"}
}
