{
  "type": "Feature",
  "properties": {
    "iso:country":"GB",
    "wof:name":"W12 0SA",
    "wof:placetype":"postalcode"
},
  "geometry": {"coordinates":[-0.23803005128116,51.51384591927017],"type":"Point"}
}