{
  "type": "Feature",
  "properties": {
    "iso:country": "GB",
    "wof:name": "W12 0SA",
    "wof:placetype": "postalcode"
  },
  "geometry": {"coordinates":[-0.23803,51.513846],"type":"Point"}
}
