{
  "type": "Feature",
  "properties": {
    "iso:country":"GB",
    "wof:name":"W1U 3LR",
    "wof:placetype":"postalcode"
},
  "geometry": {"coordinates":[-0.15201876602183,51.51597542312047],"type":"Point"}
}