{
  "type": "Feature",
  "properties": {
    "iso:country": "GB",
    "wof:name": "TQ9 7JZ",
    "wof:placetype": "postalcode"
  },
  "geometry": {"coordinates":[-3.754627,50.382624],"type":"Point"}
}
