{
  "type": "Feature",
  "properties": {
    "date:inception_lower": "1980-01-01",
    "date:inception_upper": "1980-01-01",
    "iso:country": "GB",
    "wof:name": "TQ9 7JZ",
    "wof:placetype": "postalcode"
  },
  "geometry": {"coordinates":[-3.754663,50.382608],"type":"Point"}
}
