{
  "type": "Feature",
  "properties": {
    "date:inception_lower":"1980-01-01",
    "date:inception_upper":"1980-01-31",
    "iso:country":"GB",
    "wof:name":"TQ9 7JZ",
    "wof:placetype":"postalcode"
},
  "geometry": {"coordinates":[-3.754627,50.382624],"type":"Point"}
}