{
  "type": "Feature",
  "properties": {
    "date:inception_lower":"1980-01-01",
    "date:inception_upper":"1980-01-31",
    "iso:country":"GB",
    "wof:name":"ME10 2LS",
    "wof:placetype":"postalcode"
},
  "geometry": {"coordinates":[0.725632,51.346971],"type":"Point"}
}