{
  "type": "Feature",
  "properties": {
    "iso:country":"GB",
    "wof:name":"ME10 2LS",
    "wof:placetype":"postalcode"
},
  "geometry": {"coordinates":[0.72563241513618,51.34697094180071],"type":"Point"}
}