{
  "type": "Feature",
  "properties": {
    "date:inception_lower": "1980-01-01",
    "date:inception_upper": "1980-01-01",
    "iso:country": "GB",
    "wof:name": "S41 9LE",
    "wof:placetype": "postalcode"
  },
  "geometry": {"coordinates":[-1.42117,53.27115],"type":"Point"}
}
