{
  "type": "Feature",
  "properties": {
    "iso:country": "GB",
    "wof:name": "S41 9LE",
    "wof:placetype": "postalcode"
  },
  "geometry": {"coordinates":[-1.42117,53.27115],"type":"Point"}
}
