{
  "type": "Feature",
  "properties": {
    "iso:country":"GB",
    "wof:name":"SE19 3SW",
    "wof:placetype":"postalcode"
},
  "geometry": {"coordinates":[-0.0869242514608,51.41800914887992],"type":"Point"}
}