{
  "type": "Feature",
  "properties": {
    "date:inception_lower": "1994-05-01",
    "date:inception_upper": "1994-05-01",
    "iso:country": "GB",
    "wof:name": "HP14 3SY",
    "wof:placetype": "postalcode"
  },
  "geometry": {"coordinates":[-0.901351,51.661673],"type":"Point"}
}
