{
  "type": "Feature",
  "properties": {
    "iso:country":"GB",
    "wof:name":"HP14 3SY",
    "wof:placetype":"postalcode"
},
  "geometry": {"coordinates":[-0.90135057256375,51.66167322320655],"type":"Point"}
}