{
  "type": "Feature",
  "properties": {
    "iso:country": "GB",
    "wof:name": "TA2 8AA",
    "wof:placetype": "postalcode"
  },
  "geometry": {"coordinates":[-3.103659,51.042734],"type":"Point"}
}
