{
  "type": "Feature",
  "properties": {
    "iso:country":"GB",
    "wof:name":"CO7 8JL",
    "wof:placetype":"postalcode"
},
  "geometry": {"coordinates":[1.02362906544772,51.83395542845211],"type":"Point"}
}