{
  "type": "Feature",
  "properties": {
    "iso:country": "GB",
    "wof:name": "SL2 1QQ",
    "wof:placetype": "postalcode"
  },
  "geometry": {"coordinates":[-0.623425,51.53596],"type":"Point"}
}
