{
  "type": "Feature",
  "properties": {
    "iso:country":"GB",
    "wof:name":"SL2 1QQ",
    "wof:placetype":"postalcode"
},
  "geometry": {"coordinates":[-0.62342509481536,51.53596049747679],"type":"Point"}
}