{
  "type": "Feature",
  "properties": {
    "iso:country":"GB",
    "wof:name":"CM7 3LB",
    "wof:placetype":"postalcode"
},
  "geometry": {"coordinates":[0.58274235410202,51.8785078214493],"type":"Point"}
}