{
  "type": "Feature",
  "properties": {
    "iso:country":"GB",
    "wof:name":"CV5 7LJ",
    "wof:placetype":"postalcode"
},
  "geometry": {"coordinates":[-1.57609903664791,52.41491581906563],"type":"Point"}
}