{
  "type": "Feature",
  "properties": {
    "iso:country":"GB",
    "wof:name":"DE24 9GG",
    "wof:placetype":"postalcode"
},
  "geometry": {"coordinates":[-1.48076424961529,52.89086888196866],"type":"Point"}
}