{
  "type": "Feature",
  "properties": {
    "date:inception_lower": "1992-08-01",
    "date:inception_upper": "1992-08-01",
    "iso:country": "GB",
    "wof:name": "DE24 9GG",
    "wof:placetype": "postalcode"
  },
  "geometry": {"coordinates":[-1.48107,52.891059],"type":"Point"}
}
