{
  "type": "Feature",
  "properties": {
    "date:inception_lower":"1992-08-01",
    "date:inception_upper":"1992-08-31",
    "iso:country":"GB",
    "wof:name":"DE24 9GG",
    "wof:placetype":"postalcode"
},
  "geometry": {"coordinates":[-1.480764,52.890869],"type":"Point"}
}