{
  "type": "Feature",
  "properties": {
    "iso:country": "GB",
    "wof:name": "OX3 9TS",
    "wof:placetype": "postalcode"
  },
  "geometry": {"coordinates":[-1.227236,51.803967],"type":"Point"}
}
