{
  "type": "Feature",
  "properties": {
    "date:inception_lower": "1980-01-01",
    "date:inception_upper": "1980-01-01",
    "iso:country": "GB",
    "wof:name": "OX3 9TS",
    "wof:placetype": "postalcode"
  },
  "geometry": {"coordinates":[-1.227236,51.803967],"type":"Point"}
}
