{
  "type": "Feature",
  "properties": {
    "iso:country":"GB",
    "wof:name":"OX3 9TS",
    "wof:placetype":"postalcode"
},
  "geometry": {"coordinates":[-1.22723636995074,51.80396652654667],"type":"Point"}
}