{
  "type": "Feature",
  "properties": {
    "iso:country":"GB",
    "wof:name":"GU35 0PP",
    "wof:placetype":"postalcode"
},
  "geometry": {"coordinates":[-0.84502283955183,51.11870632168052],"type":"Point"}
}