{
  "type": "Feature",
  "properties": {
    "date:inception_lower": "1980-01-01",
    "date:inception_upper": "1980-01-01",
    "iso:country": "GB",
    "wof:name": "GU35 0PP",
    "wof:placetype": "postalcode"
  },
  "geometry": {"coordinates":[-0.844989,51.118792],"type":"Point"}
}
