{
  "type": "Feature",
  "properties": {
    "date:inception_lower":"1980-01-01",
    "date:inception_upper":"1980-01-31",
    "iso:country":"GB",
    "wof:name":"EX7 9HQ",
    "wof:placetype":"postalcode"
},
  "geometry": {"coordinates":[-3.469669,50.581762],"type":"Point"}
}