{
  "type": "Feature",
  "properties": {
    "iso:country": "GB",
    "wof:name": "WF9 3SD",
    "wof:placetype": "postalcode"
  },
  "geometry": {"coordinates":[-1.316468,53.598279],"type":"Point"}
}
