{
  "type": "Feature",
  "properties": {
    "date:inception_lower":"1981-09-01",
    "date:inception_upper":"1981-09-30",
    "iso:country":"GB",
    "wof:name":"WF9 3SD",
    "wof:placetype":"postalcode"
},
  "geometry": {"coordinates":[-1.316468,53.598279],"type":"Point"}
}