{
  "type": "Feature",
  "properties": {
    "iso:country":"GB",
    "wof:name":"SA14 8YW",
    "wof:placetype":"postalcode"
},
  "geometry": {"coordinates":[-4.0891783576855,51.69721137262125],"type":"Point"}
}