{
  "type": "Feature",
  "properties": {
    "iso:country": "GB",
    "wof:name": "EX5 4DL",
    "wof:placetype": "postalcode"
  },
  "geometry": {"coordinates":[-3.480577,50.818786],"type":"Point"}
}
