{
  "type": "Feature",
  "properties": {
    "iso:country":"GB",
    "wof:name":"EX5 4DL",
    "wof:placetype":"postalcode"
},
  "geometry": {"coordinates":[-3.48057674284597,50.81878636420016],"type":"Point"}
}