{
  "type": "Feature",
  "properties": {
    "iso:country":"GB",
    "wof:name":"CO15 4AP",
    "wof:placetype":"postalcode"
},
  "geometry": {"coordinates":[1.158590670113,51.80274850278531],"type":"Point"}
}