{
  "type": "Feature",
  "properties": {
    "iso:country":"GB",
    "wof:name":"WA8 9HS",
    "wof:placetype":"postalcode"
},
  "geometry": {"coordinates":[-2.73090509660698,53.38458755468822],"type":"Point"}
}