{
  "type": "Feature",
  "properties": {
    "date:inception_lower": "2017-03-01",
    "date:inception_upper": "2017-03-01",
    "iso:country": "GB",
    "wof:name": "WA8 8WQ",
    "wof:placetype": "postalcode"
  },
  "geometry": {"coordinates":[-2.781873,53.355067],"type":"Point"}
}
