{
  "type": "Feature",
  "properties": {
    "date:inception_lower":"2002-12-01",
    "date:inception_upper":"2002-12-31",
    "iso:country":"GB",
    "wof:name":"BA11 1DU",
    "wof:placetype":"postalcode"
},
  "geometry": {"coordinates":[-2.324876,51.231284],"type":"Point"}
}