{
  "type": "Feature",
  "properties": {
    "iso:country":"GB",
    "wof:name":"NE4 8HG",
    "wof:placetype":"postalcode"
},
  "geometry": {"coordinates":[-1.65648066517056,54.96721419214403],"type":"Point"}
}