{
  "type": "Feature",
  "properties": {
    "iso:country":"GB",
    "wof:name":"BS25 5SE",
    "wof:placetype":"postalcode"
},
  "geometry": {"coordinates":[-2.79619891626002,51.33446552149077],"type":"Point"}
}