{
  "type": "Feature",
  "properties": {
    "date:inception_lower": "1997-12-01",
    "date:inception_upper": "1997-12-01",
    "iso:country": "GB",
    "wof:name": "BS25 5SE",
    "wof:placetype": "postalcode"
  },
  "geometry": {"coordinates":[-2.799162,51.334523],"type":"Point"}
}
