{
  "type": "Feature",
  "properties": {
    "iso:country":"GB",
    "wof:name":"E14 0DA",
    "wof:placetype":"postalcode"
},
  "geometry": {"coordinates":[-0.01905980529743,51.50930882533038],"type":"Point"}
}