{
  "type": "Feature",
  "properties": {
    "iso:country":"GB",
    "wof:name":"AB51 5NF",
    "wof:placetype":"postalcode"
},
  "geometry": {"coordinates":[-2.43571731566618,57.23291356305244],"type":"Point"}
}