{
  "type": "Feature",
  "properties": {
    "date:inception_lower": "1997-12-01",
    "date:inception_upper": "1997-12-01",
    "iso:country": "GB",
    "wof:name": "RH15 8UW",
    "wof:placetype": "postalcode"
  },
  "geometry": {"coordinates":[-0.154713,50.964296],"type":"Point"}
}
