{
  "type": "Feature",
  "properties": {
    "iso:country":"GB",
    "wof:name":"E17 7BT",
    "wof:placetype":"postalcode"
},
  "geometry": {"coordinates":[-0.02237376901724,51.58581983533119],"type":"Point"}
}