{
  "type": "Feature",
  "properties": {
    "iso:country": "GB",
    "wof:name": "RH14 9ZF",
    "wof:placetype": "postalcode"
  },
  "geometry": {"coordinates":[-0.443491,51.027536],"type":"Point"}
}
