{
  "type": "Feature",
  "properties": {
    "iso:country":"GB",
    "wof:name":"B47 5DE",
    "wof:placetype":"postalcode"
},
  "geometry": {"coordinates":[-1.89273545124922,52.38884484680451],"type":"Point"}
}