{
  "type": "Feature",
  "properties": {
    "date:inception_lower": "1980-01-01",
    "date:inception_upper": "1980-01-01",
    "iso:country": "GB",
    "wof:name": "B47 5DE",
    "wof:placetype": "postalcode"
  },
  "geometry": {"coordinates":[-1.893021,52.389327],"type":"Point"}
}
