{
  "type": "Feature",
  "properties": {
    "iso:country": "GB",
    "wof:name": "PL24 2PB",
    "wof:placetype": "postalcode"
  },
  "geometry": {"coordinates":[-4.701635,50.352787],"type":"Point"}
}
