{
  "type": "Feature",
  "properties": {
    "iso:country":"GB",
    "wof:name":"CR0 7UP",
    "wof:placetype":"postalcode"
},
  "geometry": {"coordinates":[-0.05005481050192,51.39149334440139],"type":"Point"}
}