{
  "type": "Feature",
  "properties": {
    "iso:country": "GB",
    "wof:name": "CR0 7UP",
    "wof:placetype": "postalcode"
  },
  "geometry": {"coordinates":[-0.050055,51.391493],"type":"Point"}
}
