{
  "type": "Feature",
  "properties": {
    "iso:country":"GB",
    "wof:name":"HG3 2WA",
    "wof:placetype":"postalcode"
},
  "geometry": {"coordinates":[-1.64167930814988,54.02853737087047],"type":"Point"}
}