{
  "type": "Feature",
  "properties": {
    "iso:country": "GB",
    "wof:name": "HG3 2WA",
    "wof:placetype": "postalcode"
  },
  "geometry": {"coordinates":[-1.641679,54.028537],"type":"Point"}
}
