{
  "type": "Feature",
  "properties": {
    "date:inception_lower": "2022-03-01",
    "date:inception_upper": "2022-03-01",
    "iso:country": "GB",
    "wof:name": "HA7 4GD",
    "wof:placetype": "postalcode"
  },
  "geometry": {"coordinates":[-0.313683,51.617212],"type":"Point"}
}
