{
  "type": "Feature",
  "properties": {
    "iso:country":"GB",
    "wof:name":"W1U 4ED",
    "wof:placetype":"postalcode"
},
  "geometry": {"coordinates":[-0.15345637882257,51.51856092308012],"type":"Point"}
}