{
  "type": "Feature",
  "properties": {
    "date:inception_lower":"1980-01-01",
    "date:inception_upper":"1980-01-31",
    "iso:country":"GB",
    "wof:name":"SY25 6DF",
    "wof:placetype":"postalcode"
},
  "geometry": {"coordinates":[-3.851856,52.333709],"type":"Point"}
}