{
  "type": "Feature",
  "properties": {
    "iso:country":"GB",
    "wof:name":"L32 7RL",
    "wof:placetype":"postalcode"
},
  "geometry": {"coordinates":[-2.8897585640799,53.46870513131113],"type":"Point"}
}