{
  "type": "Feature",
  "properties": {
    "date:inception_lower": "1980-01-01",
    "date:inception_upper": "1980-01-01",
    "iso:country": "GB",
    "wof:name": "DG14 0RP",
    "wof:placetype": "postalcode"
  },
  "geometry": {"coordinates":[-2.896414,55.096072],"type":"Point"}
}
