{
  "type": "Feature",
  "properties": {
    "iso:country":"GB",
    "wof:name":"DG14 0RP",
    "wof:placetype":"postalcode"
},
  "geometry": {"coordinates":[-2.89641422185802,55.09607202268686],"type":"Point"}
}