{
  "type": "Feature",
  "properties": {
    "iso:country": "GB",
    "wof:name": "FK8 3SP",
    "wof:placetype": "postalcode"
  },
  "geometry": {"coordinates":[-4.38106,56.179793],"type":"Point"}
}
