{
  "type": "Feature",
  "properties": {
    "iso:country":"GB",
    "wof:name":"FK8 3SP",
    "wof:placetype":"postalcode"
},
  "geometry": {"coordinates":[-4.38105963668257,56.17979320503952],"type":"Point"}
}