{
  "type": "Feature",
  "properties": {
    "iso:country":"GB",
    "wof:name":"S21 4JF",
    "wof:placetype":"postalcode"
},
  "geometry": {"coordinates":[-1.37262117188214,53.30467580716432],"type":"Point"}
}