{
  "type": "Feature",
  "properties": {
    "date:inception_lower":"2003-03-01",
    "date:inception_upper":"2003-03-31",
    "iso:country":"GB",
    "wof:name":"S21 4JF",
    "wof:placetype":"postalcode"
},
  "geometry": {"coordinates":[-1.372621,53.304676],"type":"Point"}
}