{
  "type": "Feature",
  "properties": {
    "iso:country":"GB",
    "wof:name":"TA24 8LL",
    "wof:placetype":"postalcode"
},
  "geometry": {"coordinates":[-3.59347694356276,51.20494828624942],"type":"Point"}
}