{
  "type": "Feature",
  "properties": {
    "iso:country": "GB",
    "wof:name": "DA1 5XA",
    "wof:placetype": "postalcode"
  },
  "geometry": {"coordinates":[0.217609,51.453067],"type":"Point"}
}
