{
  "type": "Feature",
  "properties": {
    "iso:country": "GB",
    "wof:name": "NE29 7BE",
    "wof:placetype": "postalcode"
  },
  "geometry": {"coordinates":[-1.472368,55.003255],"type":"Point"}
}
