{
  "type": "Feature",
  "properties": {
    "iso:country": "GB",
    "wof:name": "CR0 4LE",
    "wof:placetype": "postalcode"
  },
  "geometry": {"coordinates":[-0.107509,51.371932],"type":"Point"}
}
