{
  "type": "Feature",
  "properties": {
    "date:inception_lower": "2012-02-01",
    "date:inception_upper": "2012-02-01",
    "iso:country": "GB",
    "wof:name": "DH1 9JL",
    "wof:placetype": "postalcode"
  },
  "geometry": {"coordinates":[-1.53502,54.792717],"type":"Point"}
}
