{
  "type": "Feature",
  "properties": {
    "iso:country":"GB",
    "wof:name":"TW2 5JD",
    "wof:placetype":"postalcode"
},
  "geometry": {"coordinates":[-0.36933348273517,51.43803320858622],"type":"Point"}
}