{
  "type": "Feature",
  "properties": {
    "date:inception_lower": "2018-01-01",
    "date:inception_upper": "2018-01-01",
    "iso:country": "GB",
    "wof:name": "HU7 3FL",
    "wof:placetype": "postalcode"
  },
  "geometry": {"coordinates":[-0.3536,53.805889],"type":"Point"}
}
