{
  "type": "Feature",
  "properties": {
    "iso:country":"GB",
    "wof:name":"BN26 6FS",
    "wof:placetype":"postalcode"
},
  "geometry": {"coordinates":[0.26084987969178,50.82343149719996],"type":"Point"}
}