{
  "type": "Feature",
  "properties": {
    "date:inception_lower": "2014-02-01",
    "date:inception_upper": "2014-02-01",
    "iso:country": "GB",
    "wof:name": "BN26 6FS",
    "wof:placetype": "postalcode"
  },
  "geometry": {"coordinates":[0.26085,50.823431],"type":"Point"}
}
