{
  "type": "Feature",
  "properties": {
    "iso:country":"GB",
    "wof:name":"EH41 3RJ",
    "wof:placetype":"postalcode"
},
  "geometry": {"coordinates":[-2.79917746558768,55.95443302793957],"type":"Point"}
}