{
  "type": "Feature",
  "properties": {
    "iso:country":"GB",
    "wof:name":"CV1 4HT",
    "wof:placetype":"postalcode"
},
  "geometry": {"coordinates":[-1.50404520100809,52.41986797141729],"type":"Point"}
}