{
  "type": "Feature",
  "properties": {
    "iso:country": "GB",
    "wof:name": "NP16 7EG",
    "wof:placetype": "postalcode"
  },
  "geometry": {"coordinates":[-2.666319,51.64555],"type":"Point"}
}
