{
  "type": "Feature",
  "properties": {
    "iso:country":"GB",
    "wof:name":"NP16 7EG",
    "wof:placetype":"postalcode"
},
  "geometry": {"coordinates":[-2.66631927659302,51.64555026817178],"type":"Point"}
}