{
  "type": "Feature",
  "properties": {
    "iso:country":"GB",
    "wof:name":"SW5 0QF",
    "wof:placetype":"postalcode"
},
  "geometry": {"coordinates":[-0.18994857967182,51.49391487292635],"type":"Point"}
}