{
  "type": "Feature",
  "properties": {
    "iso:country":"GB",
    "wof:name":"BD22 7QA",
    "wof:placetype":"postalcode"
},
  "geometry": {"coordinates":[-1.95987049531857,53.84333205163478],"type":"Point"}
}