{
  "type": "Feature",
  "properties": {
    "iso:country":"GB",
    "wof:name":"SY4 4HL",
    "wof:placetype":"postalcode"
},
  "geometry": {"coordinates":[-2.65815331916407,52.79571546296214],"type":"Point"}
}