{
  "type": "Feature",
  "properties": {
    "date:inception_lower": "1992-08-01",
    "date:inception_upper": "1992-08-01",
    "iso:country": "GB",
    "wof:name": "SY4 4HL",
    "wof:placetype": "postalcode"
  },
  "geometry": {"coordinates":[-2.658153,52.795715],"type":"Point"}
}
