{
  "type": "Feature",
  "properties": {
    "iso:country": "GB",
    "wof:name": "DL5 4RX",
    "wof:placetype": "postalcode"
  },
  "geometry": {"coordinates":[-1.571748,54.632682],"type":"Point"}
}
