{
  "type": "Feature",
  "properties": {
    "date:inception_lower": "1980-01-01",
    "date:inception_upper": "1980-01-01",
    "iso:country": "GB",
    "wof:name": "RH12 2JX",
    "wof:placetype": "postalcode"
  },
  "geometry": {"coordinates":[-0.335937,51.066982],"type":"Point"}
}
