{
  "type": "Feature",
  "properties": {
    "iso:country":"GB",
    "wof:name":"RH12 2JX",
    "wof:placetype":"postalcode"
},
  "geometry": {"coordinates":[-0.33597751615939,51.06699477583413],"type":"Point"}
}