{
  "type": "Feature",
  "properties": {
    "date:inception_lower":"2015-11-01",
    "date:inception_upper":"2015-11-30",
    "iso:country":"GB",
    "wof:name":"DE5 9TU",
    "wof:placetype":"postalcode"
},
  "geometry": {"coordinates":[-1.38727,53.042749],"type":"Point"}
}