{
  "type": "Feature",
  "properties": {
    "iso:country":"GB",
    "wof:name":"DE5 9TU",
    "wof:placetype":"postalcode"
},
  "geometry": {"coordinates":[-1.38736642464735,53.04243411788013],"type":"Point"}
}