{
  "type": "Feature",
  "properties": {
    "date:inception_lower": "2015-11-01",
    "date:inception_upper": "2015-11-01",
    "iso:country": "GB",
    "wof:name": "DE5 9TU",
    "wof:placetype": "postalcode"
  },
  "geometry": {"coordinates":[-1.387478,53.042822],"type":"Point"}
}
