{
  "type": "Feature",
  "properties": {
    "iso:country": "GB",
    "wof:name": "DE5 9TU",
    "wof:placetype": "postalcode"
  },
  "geometry": {"coordinates":[-1.38727,53.042749],"type":"Point"}
}
