{
  "type": "Feature",
  "properties": {
    "iso:country":"GB",
    "wof:name":"DG9 7AU",
    "wof:placetype":"postalcode"
},
  "geometry": {"coordinates":[-5.02630011867139,54.89757735806818],"type":"Point"}
}