{
  "type": "Feature",
  "properties": {
    "iso:country":"GB",
    "wof:name":"N20 0SL",
    "wof:placetype":"postalcode"
},
  "geometry": {"coordinates":[-0.15617082110586,51.62258285381212],"type":"Point"}
}