{
  "type": "Feature",
  "properties": {
    "date:inception_lower": "1980-01-01",
    "date:inception_upper": "1980-01-01",
    "iso:country": "GB",
    "wof:name": "DE5 8NF",
    "wof:placetype": "postalcode"
  },
  "geometry": {"coordinates":[-1.427593,53.034562],"type":"Point"}
}
