{
  "type": "Feature",
  "properties": {
    "iso:country":"GB",
    "wof:name":"BA14 6LR",
    "wof:placetype":"postalcode"
},
  "geometry": {"coordinates":[-2.12135675099965,51.32290310242028],"type":"Point"}
}