{
  "type": "Feature",
  "properties": {
    "iso:country": "GB",
    "wof:name": "L12 5ES",
    "wof:placetype": "postalcode"
  },
  "geometry": {"coordinates":[-2.91164,53.436747],"type":"Point"}
}
