{
  "type": "Feature",
  "properties": {
    "date:inception_lower": "1984-10-01",
    "date:inception_upper": "1984-10-01",
    "iso:country": "GB",
    "wof:name": "WF9 3EU",
    "wof:placetype": "postalcode"
  },
  "geometry": {"coordinates":[-1.335518,53.58698],"type":"Point"}
}
