{
  "type": "Feature",
  "properties": {
    "iso:country": "GB",
    "wof:name": "WF9 3EU",
    "wof:placetype": "postalcode"
  },
  "geometry": {"coordinates":[-1.335518,53.58698],"type":"Point"}
}
