{
  "type": "Feature",
  "properties": {
    "iso:country":"GB",
    "wof:name":"WF9 3EU",
    "wof:placetype":"postalcode"
},
  "geometry": {"coordinates":[-1.33551782073699,53.58697965631131],"type":"Point"}
}