{
  "type": "Feature",
  "properties": {
    "iso:country": "GB",
    "wof:name": "SA44 5LZ",
    "wof:placetype": "postalcode"
  },
  "geometry": {"coordinates":[-4.393935,52.062317],"type":"Point"}
}
