{
  "type": "Feature",
  "properties": {
    "iso:country":"GB",
    "wof:name":"SA44 5LZ",
    "wof:placetype":"postalcode"
},
  "geometry": {"coordinates":[-4.39393512623447,52.06231708096147],"type":"Point"}
}