{
  "type": "Feature",
  "properties": {
    "iso:country":"GB",
    "wof:name":"BS20 6PL",
    "wof:placetype":"postalcode"
},
  "geometry": {"coordinates":[-2.76823454070775,51.48187480622799],"type":"Point"}
}