{
  "type": "Feature",
  "properties": {
    "date:inception_lower": "1980-01-01",
    "date:inception_upper": "1980-01-01",
    "iso:country": "GB",
    "wof:name": "LN12 2LD",
    "wof:placetype": "postalcode"
  },
  "geometry": {"coordinates":[0.27766,53.32046],"type":"Point"}
}
