{
  "type": "Feature",
  "properties": {
    "iso:country": "GB",
    "wof:name": "DN14 6HS",
    "wof:placetype": "postalcode"
  },
  "geometry": {"coordinates":[-0.868132,53.709846],"type":"Point"}
}
