{
  "type": "Feature",
  "properties": {
    "iso:country": "GB",
    "wof:name": "RG5 3EW",
    "wof:placetype": "postalcode"
  },
  "geometry": {"coordinates":[-0.895347,51.449205],"type":"Point"}
}
