{
  "type": "Feature",
  "properties": {
    "iso:country":"GB",
    "wof:name":"LN11 9RL",
    "wof:placetype":"postalcode"
},
  "geometry": {"coordinates":[-0.07350092928944,53.3374636175472],"type":"Point"}
}