{
  "type": "Feature",
  "properties": {
    "iso:country": "GB",
    "wof:name": "LN11 9RL",
    "wof:placetype": "postalcode"
  },
  "geometry": {"coordinates":[-0.073501,53.337464],"type":"Point"}
}
