{
  "type": "Feature",
  "properties": {
    "iso:country":"GB",
    "wof:name":"OX5 2SS",
    "wof:placetype":"postalcode"
},
  "geometry": {"coordinates":[-1.24366789897523,51.82393480232533],"type":"Point"}
}