{
  "type": "Feature",
  "properties": {
    "iso:country": "GB",
    "wof:name": "OX5 2SS",
    "wof:placetype": "postalcode"
  },
  "geometry": {"coordinates":[-1.243668,51.823935],"type":"Point"}
}
