{
  "type": "Feature",
  "properties": {
    "iso:country":"GB",
    "wof:name":"PH11 8PF",
    "wof:placetype":"postalcode"
},
  "geometry": {"coordinates":[-3.26092312520892,56.71793873822508],"type":"Point"}
}