{
  "type": "Feature",
  "properties": {
    "iso:country":"GB",
    "wof:name":"SA9 2FA",
    "wof:placetype":"postalcode"
},
  "geometry": {"coordinates":[-3.81534292644745,51.79672063560034],"type":"Point"}
}