{
  "type": "Feature",
  "properties": {
    "iso:country":"GB",
    "wof:name":"SY10 0JN",
    "wof:placetype":"postalcode"
},
  "geometry": {"coordinates":[-3.30218981105916,52.82538353495244],"type":"Point"}
}