{
  "type": "Feature",
  "properties": {
    "date:inception_lower": "1980-01-01",
    "date:inception_upper": "1980-01-01",
    "iso:country": "GB",
    "wof:name": "TN11 8JR",
    "wof:placetype": "postalcode"
  },
  "geometry": {"coordinates":[0.170462,51.198777],"type":"Point"}
}
