{
  "type": "Feature",
  "properties": {
    "iso:country":"GB",
    "wof:name":"PA1 3JR",
    "wof:placetype":"postalcode"
},
  "geometry": {"coordinates":[-4.3871474244824,55.84618251098646],"type":"Point"}
}