{
  "type": "Feature",
  "properties": {
    "iso:country":"GB",
    "wof:name":"LS24 8JT",
    "wof:placetype":"postalcode"
},
  "geometry": {"coordinates":[-1.24361782656179,53.89064249846658],"type":"Point"}
}