{
  "type": "Feature",
  "properties": {
    "iso:country":"GB",
    "wof:name":"SG1 5HF",
    "wof:placetype":"postalcode"
},
  "geometry": {"coordinates":[-0.1849494172721,51.91015821885417],"type":"Point"}
}