{
  "type": "Feature",
  "properties": {
    "iso:country":"GB",
    "wof:name":"S35 4LG",
    "wof:placetype":"postalcode"
},
  "geometry": {"coordinates":[-1.48020161489826,53.48132590795309],"type":"Point"}
}