{
  "type": "Feature",
  "properties": {
    "iso:country":"GB",
    "wof:name":"HG5 8AN",
    "wof:placetype":"postalcode"
},
  "geometry": {"coordinates":[-1.46566442603531,54.00713171950289],"type":"Point"}
}