{
  "type": "Feature",
  "properties": {
    "date:inception_lower":"2001-12-01",
    "date:inception_upper":"2001-12-31",
    "iso:country":"GB",
    "wof:name":"LS25 6PE",
    "wof:placetype":"postalcode"
},
  "geometry": {"coordinates":[-1.250232,53.79816],"type":"Point"}
}