{
  "type": "Feature",
  "properties": {
    "date:inception_lower":"1998-06-01",
    "date:inception_upper":"1998-06-30",
    "iso:country":"GB",
    "wof:name":"YO19 6EZ",
    "wof:placetype":"postalcode"
},
  "geometry": {"coordinates":[-1.016975,53.892039],"type":"Point"}
}