{
  "type": "Feature",
  "properties": {
    "iso:country":"GB",
    "wof:name":"YO19 6EZ",
    "wof:placetype":"postalcode"
},
  "geometry": {"coordinates":[-1.01697510401627,53.89203908537022],"type":"Point"}
}