{
  "type": "Feature",
  "properties": {
    "date:inception_lower": "1986-04-01",
    "date:inception_upper": "1986-04-01",
    "iso:country": "GB",
    "wof:name": "NG4 1NR",
    "wof:placetype": "postalcode"
  },
  "geometry": {"coordinates":[-1.111031,52.97487],"type":"Point"}
}
