{
  "type": "Feature",
  "properties": {
    "iso:country":"GB",
    "wof:name":"NG4 1NR",
    "wof:placetype":"postalcode"
},
  "geometry": {"coordinates":[-1.11103116421312,52.97486996609834],"type":"Point"}
}