{
  "type": "Feature",
  "properties": {
    "date:inception_lower":"1993-02-01",
    "date:inception_upper":"1993-02-28",
    "iso:country":"GB",
    "wof:name":"KY12 0NH",
    "wof:placetype":"postalcode"
},
  "geometry": {"coordinates":[-3.462519,56.076212],"type":"Point"}
}