{
  "type": "Feature",
  "properties": {
    "date:inception_lower": "1980-01-01",
    "date:inception_upper": "1980-01-01",
    "iso:country": "GB",
    "wof:name": "TQ9 6HN",
    "wof:placetype": "postalcode"
  },
  "geometry": {"coordinates":[-3.707488,50.443989],"type":"Point"}
}
