{
  "type": "Feature",
  "properties": {
    "iso:country":"GB",
    "wof:name":"SO16 9GD",
    "wof:placetype":"postalcode"
},
  "geometry": {"coordinates":[-1.4566204222469,50.92935356765607],"type":"Point"}
}