{
  "type": "Feature",
  "properties": {
    "iso:country":"GB",
    "wof:name":"GU52 6BH",
    "wof:placetype":"postalcode"
},
  "geometry": {"coordinates":[-0.82794588679797,51.26719779704696],"type":"Point"}
}