{
  "type": "Feature",
  "properties": {
    "date:inception_lower": "1996-06-01",
    "date:inception_upper": "1996-06-01",
    "iso:country": "GB",
    "wof:name": "L4 4NS",
    "wof:placetype": "postalcode"
  },
  "geometry": {"coordinates":[-2.972619,53.436625],"type":"Point"}
}
