{
  "type": "Feature",
  "properties": {
    "iso:country":"GB",
    "wof:name":"PA1 1RL",
    "wof:placetype":"postalcode"
},
  "geometry": {"coordinates":[-4.41251370046049,55.84433932827672],"type":"Point"}
}