{
  "type": "Feature",
  "properties": {
    "date:inception_lower":"2014-05-01",
    "date:inception_upper":"2014-05-31",
    "iso:country":"GB",
    "wof:name":"CH62 5AF",
    "wof:placetype":"postalcode"
},
  "geometry": {"coordinates":[-2.996339,53.359224],"type":"Point"}
}