{
  "type": "Feature",
  "properties": {
    "iso:country": "GB",
    "wof:name": "CH62 5AF",
    "wof:placetype": "postalcode"
  },
  "geometry": {"coordinates":[-2.996339,53.359224],"type":"Point"}
}
