{
  "type": "Feature",
  "properties": {
    "iso:country":"GB",
    "wof:name":"DD2 4SD",
    "wof:placetype":"postalcode"
},
  "geometry": {"coordinates":[-3.0482900034592,56.47220027857005],"type":"Point"}
}