{
  "type": "Feature",
  "properties": {
    "iso:country":"GB",
    "wof:name":"WR8 9JR",
    "wof:placetype":"postalcode"
},
  "geometry": {"coordinates":[-2.19057655085125,52.09150967531272],"type":"Point"}
}