{
  "type": "Feature",
  "properties": {
    "iso:country": "GB",
    "wof:name": "WR8 9JR",
    "wof:placetype": "postalcode"
  },
  "geometry": {"coordinates":[-2.190453,52.091539],"type":"Point"}
}
