{
  "type": "Feature",
  "properties": {
    "date:inception_lower":"1980-01-01",
    "date:inception_upper":"1980-01-31",
    "iso:country":"GB",
    "wof:name":"WR8 9JR",
    "wof:placetype":"postalcode"
},
  "geometry": {"coordinates":[-2.190453,52.091539],"type":"Point"}
}