{
  "type": "Feature",
  "properties": {
    "iso:country":"GB",
    "wof:name":"PA1 1JN",
    "wof:placetype":"postalcode"
},
  "geometry": {"coordinates":[-4.41734550598839,55.84240193114215],"type":"Point"}
}