{
  "type": "Feature",
  "properties": {
    "iso:country":"GB",
    "wof:name":"ME8 6NU",
    "wof:placetype":"postalcode"
},
  "geometry": {"coordinates":[0.57804722628463,51.37703378783052],"type":"Point"}
}