{
  "type": "Feature",
  "properties": {
    "iso:country":"GB",
    "wof:name":"TA1 5NY",
    "wof:placetype":"postalcode"
},
  "geometry": {"coordinates":[-3.12542461890643,51.00790493750615],"type":"Point"}
}