{
  "type": "Feature",
  "properties": {
    "iso:country": "GB",
    "wof:name": "CF10 5UY",
    "wof:placetype": "postalcode"
  },
  "geometry": {"coordinates":[-3.175374,51.462369],"type":"Point"}
}
