{
  "type": "Feature",
  "properties": {
    "iso:country":"GB",
    "wof:name":"CF10 5UY",
    "wof:placetype":"postalcode"
},
  "geometry": {"coordinates":[-3.17437317646313,51.46241442500817],"type":"Point"}
}