{
  "type": "Feature",
  "properties": {
    "date:inception_lower":"2007-09-01",
    "date:inception_upper":"2007-09-30",
    "iso:country":"GB",
    "wof:name":"CF10 5UY",
    "wof:placetype":"postalcode"
},
  "geometry": {"coordinates":[-3.175374,51.462369],"type":"Point"}
}