{
  "type": "Feature",
  "properties": {
    "iso:country":"GB",
    "wof:name":"YO8 6QH",
    "wof:placetype":"postalcode"
},
  "geometry": {"coordinates":[-0.97031971650317,53.77560860860203],"type":"Point"}
}