{
  "type": "Feature",
  "properties": {
    "date:inception_lower": "1998-06-01",
    "date:inception_upper": "1998-06-01",
    "iso:country": "GB",
    "wof:name": "YO8 6QH",
    "wof:placetype": "postalcode"
  },
  "geometry": {"coordinates":[-0.97032,53.775609],"type":"Point"}
}
