{
  "type": "Feature",
  "properties": {
    "date:inception_lower":"1980-01-01",
    "date:inception_upper":"1980-01-31",
    "iso:country":"GB",
    "wof:name":"S74 8DB",
    "wof:placetype":"postalcode"
},
  "geometry": {"coordinates":[-1.427522,53.499215],"type":"Point"}
}