{
  "type": "Feature",
  "properties": {
    "iso:country": "GB",
    "wof:name": "G61 2ES",
    "wof:placetype": "postalcode"
  },
  "geometry": {"coordinates":[-4.311449,55.915952],"type":"Point"}
}
