{
  "type": "Feature",
  "properties": {
    "iso:country":"GB",
    "wof:name":"G61 2ES",
    "wof:placetype":"postalcode"
},
  "geometry": {"coordinates":[-4.31144879099392,55.91595200045784],"type":"Point"}
}