{
  "type": "Feature",
  "properties": {
    "iso:country":"GB",
    "wof:name":"RM7 8NX",
    "wof:placetype":"postalcode"
},
  "geometry": {"coordinates":[0.1590369145557,51.59527512645776],"type":"Point"}
}