{
  "type": "Feature",
  "properties": {
    "iso:country":"GB",
    "wof:name":"M41 6QP",
    "wof:placetype":"postalcode"
},
  "geometry": {"coordinates":[-2.39025884205585,53.44438888837772],"type":"Point"}
}