{
  "type": "Feature",
  "properties": {
    "date:inception_lower": "2019-08-01",
    "date:inception_upper": "2019-08-01",
    "iso:country": "GB",
    "wof:name": "HA9 7FP",
    "wof:placetype": "postalcode"
  },
  "geometry": {"coordinates":[-0.299812,51.567077],"type":"Point"}
}
