{
  "type": "Feature",
  "properties": {
    "iso:country":"GB",
    "wof:name":"CF14 6LU",
    "wof:placetype":"postalcode"
},
  "geometry": {"coordinates":[-3.20669460428963,51.52422033208313],"type":"Point"}
}