{
  "type": "Feature",
  "properties": {
    "iso:country":"GB",
    "wof:name":"W10 5BJ",
    "wof:placetype":"postalcode"
},
  "geometry": {"coordinates":[-0.20754949269517,51.52556881445292],"type":"Point"}
}