{
  "type": "Feature",
  "properties": {
    "iso:country":"GB",
    "wof:name":"TW11 8LT",
    "wof:placetype":"postalcode"
},
  "geometry": {"coordinates":[-0.33797764264205,51.43062373359461],"type":"Point"}
}