{
  "type": "Feature",
  "properties": {
    "iso:country":"GB",
    "wof:name":"BS2 8BE",
    "wof:placetype":"postalcode"
},
  "geometry": {"coordinates":[-2.59940866084204,51.45719749243175],"type":"Point"}
}