{
  "type": "Feature",
  "properties": {
    "date:inception_lower": "2005-05-01",
    "date:inception_upper": "2005-05-01",
    "iso:country": "GB",
    "wof:name": "BB5 0DQ",
    "wof:placetype": "postalcode"
  },
  "geometry": {"coordinates":[-2.388775,53.751012],"type":"Point"}
}
