{
  "type": "Feature",
  "properties": {
    "iso:country":"GB",
    "wof:name":"BB5 0DQ",
    "wof:placetype":"postalcode"
},
  "geometry": {"coordinates":[-2.38877488560363,53.75101224677859],"type":"Point"}
}