{
  "type": "Feature",
  "properties": {
    "iso:country": "GB",
    "wof:name": "YO60 7NH",
    "wof:placetype": "postalcode"
  },
  "geometry": {"coordinates":[-0.849051,54.078076],"type":"Point"}
}
