{
  "type": "Feature",
  "properties": {
    "iso:country":"GB",
    "wof:name":"YO60 7NH",
    "wof:placetype":"postalcode"
},
  "geometry": {"coordinates":[-0.84916295572963,54.07805150341002],"type":"Point"}
}