{
  "type": "Feature",
  "properties": {
    "date:inception_lower": "1998-06-01",
    "date:inception_upper": "1998-06-01",
    "iso:country": "GB",
    "wof:name": "YO60 7NH",
    "wof:placetype": "postalcode"
  },
  "geometry": {"coordinates":[-0.849051,54.078076],"type":"Point"}
}
