{
  "type": "Feature",
  "properties": {
    "iso:country":"GB",
    "wof:name":"TS17 0XG",
    "wof:placetype":"postalcode"
},
  "geometry": {"coordinates":[-1.31057140804096,54.51677664975499],"type":"Point"}
}