{
  "type": "Feature",
  "properties": {
    "date:inception_lower": "1980-01-01",
    "date:inception_upper": "1980-01-01",
    "iso:country": "GB",
    "wof:name": "TS5 7PW",
    "wof:placetype": "postalcode"
  },
  "geometry": {"coordinates":[-1.243224,54.549159],"type":"Point"}
}
