{
  "type": "Feature",
  "properties": {
    "iso:country":"GB",
    "wof:name":"TS5 7PW",
    "wof:placetype":"postalcode"
},
  "geometry": {"coordinates":[-1.24322401787398,54.54915908094694],"type":"Point"}
}