{
  "type": "Feature",
  "properties": {
    "date:inception_lower":"2000-12-01",
    "date:inception_upper":"2000-12-31",
    "iso:country":"GB",
    "wof:name":"PE11 1GF",
    "wof:placetype":"postalcode"
},
  "geometry": {"coordinates":[-0.154303,52.799098],"type":"Point"}
}