{
  "type": "Feature",
  "properties": {
    "iso:country":"GB",
    "wof:name":"M2 5HD",
    "wof:placetype":"postalcode"
},
  "geometry": {"coordinates":[-2.24618371635669,53.47922583494024],"type":"Point"}
}