{
  "type": "Feature",
  "properties": {
    "date:inception_lower": "2005-06-01",
    "date:inception_upper": "2005-06-01",
    "iso:country": "GB",
    "wof:name": "KT8 1TL",
    "wof:placetype": "postalcode"
  },
  "geometry": {"coordinates":[-0.369328,51.408295],"type":"Point"}
}
