{
  "type": "Feature",
  "properties": {
    "iso:country":"GB",
    "wof:name":"DY5 4UL",
    "wof:placetype":"postalcode"
},
  "geometry": {"coordinates":[-2.12955841664395,52.51023207682584],"type":"Point"}
}