{
  "type": "Feature",
  "properties": {
    "date:inception_lower": "1980-01-01",
    "date:inception_upper": "1980-01-01",
    "iso:country": "GB",
    "wof:name": "M22 4FZ",
    "wof:placetype": "postalcode"
  },
  "geometry": {"coordinates":[-2.258647,53.407775],"type":"Point"}
}
