{
  "type": "Feature",
  "properties": {
    "iso:country":"GB",
    "wof:name":"NP16 5BL",
    "wof:placetype":"postalcode"
},
  "geometry": {"coordinates":[-2.68431538436231,51.63901789594309],"type":"Point"}
}