{
  "type": "Feature",
  "properties": {
    "iso:country":"GB",
    "wof:name":"CO14 8NT",
    "wof:placetype":"postalcode"
},
  "geometry": {"coordinates":[1.26128126610874,51.84417718821219],"type":"Point"}
}