{
  "type": "Feature",
  "properties": {
    "iso:country": "GB",
    "wof:name": "CO14 8NT",
    "wof:placetype": "postalcode"
  },
  "geometry": {"coordinates":[1.261281,51.844177],"type":"Point"}
}
