{
  "type": "Feature",
  "properties": {
    "iso:country": "GB",
    "wof:name": "YO13 9ED",
    "wof:placetype": "postalcode"
  },
  "geometry": {"coordinates":[-0.554432,54.233317],"type":"Point"}
}
