{
  "type": "Feature",
  "properties": {
    "date:inception_lower": "1980-01-01",
    "date:inception_upper": "1980-01-01",
    "iso:country": "GB",
    "wof:name": "YO13 9ED",
    "wof:placetype": "postalcode"
  },
  "geometry": {"coordinates":[-0.554477,54.233372],"type":"Point"}
}
