{
  "type": "Feature",
  "properties": {
    "iso:country":"GB",
    "wof:name":"FK8 2JY",
    "wof:placetype":"postalcode"
},
  "geometry": {"coordinates":[-3.94781159358411,56.11150878882509],"type":"Point"}
}