{
  "type": "Feature",
  "properties": {
    "date:inception_lower":"1986-05-01",
    "date:inception_upper":"1986-05-31",
    "iso:country":"GB",
    "wof:name":"FK8 2JY",
    "wof:placetype":"postalcode"
},
  "geometry": {"coordinates":[-3.947812,56.111509],"type":"Point"}
}