{
  "type": "Feature",
  "properties": {
    "iso:country": "GB",
    "wof:name": "FK8 2JY",
    "wof:placetype": "postalcode"
  },
  "geometry": {"coordinates":[-3.947812,56.111509],"type":"Point"}
}
