{
  "type": "Feature",
  "properties": {
    "iso:country":"GB",
    "wof:name":"DN12 2JU",
    "wof:placetype":"postalcode"
},
  "geometry": {"coordinates":[-1.24738836565861,53.47625791165758],"type":"Point"}
}