{
  "type": "Feature",
  "properties": {
    "iso:country": "GB",
    "wof:name": "UB3 5AN",
    "wof:placetype": "postalcode"
  },
  "geometry": {"coordinates":[-0.438275,51.481461],"type":"Point"}
}
