{
  "type": "Feature",
  "properties": {
    "iso:country":"GB",
    "wof:name":"UB3 5AN",
    "wof:placetype":"postalcode"
},
  "geometry": {"coordinates":[-0.43510619556022,51.48122030461968],"type":"Point"}
}