{
  "type": "Feature",
  "properties": {
    "iso:country":"GB",
    "wof:name":"L33 7BJ",
    "wof:placetype":"postalcode"
},
  "geometry": {"coordinates":[-2.85117646247015,53.48140869986017],"type":"Point"}
}