{
  "type": "Feature",
  "properties": {
    "date:inception_lower": "1984-02-01",
    "date:inception_upper": "1984-02-01",
    "iso:country": "GB",
    "wof:name": "L33 7BJ",
    "wof:placetype": "postalcode"
  },
  "geometry": {"coordinates":[-2.85232,53.481362],"type":"Point"}
}
