{
  "type": "Feature",
  "properties": {
    "date:inception_lower": "2021-03-01",
    "date:inception_upper": "2021-03-01",
    "iso:country": "GB",
    "wof:name": "GU3 2BY",
    "wof:placetype": "postalcode"
  },
  "geometry": {"coordinates":[-0.649837,51.271779],"type":"Point"}
}
