{
  "type": "Feature",
  "properties": {
    "iso:country":"GB",
    "wof:name":"ST3 7HS",
    "wof:placetype":"postalcode"
},
  "geometry": {"coordinates":[-2.11779010852762,52.97777342074392],"type":"Point"}
}