{
  "type": "Feature",
  "properties": {
    "iso:country":"GB",
    "wof:name":"DA2 6AY",
    "wof:placetype":"postalcode"
},
  "geometry": {"coordinates":[0.24274928019414,51.44412477837511],"type":"Point"}
}