{
  "type": "Feature",
  "properties": {
    "date:inception_lower": "1980-01-01",
    "date:inception_upper": "1980-01-01",
    "iso:country": "GB",
    "wof:name": "DA2 6AY",
    "wof:placetype": "postalcode"
  },
  "geometry": {"coordinates":[0.242776,51.444098],"type":"Point"}
}
