{
  "type": "Feature",
  "properties": {
    "date:inception_lower": "1994-05-01",
    "date:inception_upper": "1994-05-01",
    "iso:country": "GB",
    "wof:name": "GU7 3SG",
    "wof:placetype": "postalcode"
  },
  "geometry": {"coordinates":[-0.603944,51.203431],"type":"Point"}
}
