{
  "type": "Feature",
  "properties": {
    "iso:country":"GB",
    "wof:name":"GU7 3SG",
    "wof:placetype":"postalcode"
},
  "geometry": {"coordinates":[-0.60394403945809,51.20343068343249],"type":"Point"}
}