{
  "type": "Feature",
  "properties": {
    "iso:country":"GB",
    "wof:name":"SR7 9NJ",
    "wof:placetype":"postalcode"
},
  "geometry": {"coordinates":[-1.38360663067671,54.8148952607481],"type":"Point"}
}