{
  "type": "Feature",
  "properties": {
    "iso:country":"GB",
    "wof:name":"MK43 8QN",
    "wof:placetype":"postalcode"
},
  "geometry": {"coordinates":[-0.53868431589343,52.14358810595292],"type":"Point"}
}