{
  "type": "Feature",
  "properties": {
    "iso:country":"GB",
    "wof:name":"DG11 1NW",
    "wof:placetype":"postalcode"
},
  "geometry": {"coordinates":[-3.43852743087255,55.12607680090223],"type":"Point"}
}