{
  "type": "Feature",
  "properties": {
    "iso:country": "GB",
    "wof:name": "SO45 4PT",
    "wof:placetype": "postalcode"
  },
  "geometry": {"coordinates":[-1.416164,50.852579],"type":"Point"}
}
