{
  "type": "Feature",
  "properties": {
    "iso:country":"GB",
    "wof:name":"SO45 4PT",
    "wof:placetype":"postalcode"
},
  "geometry": {"coordinates":[-1.41622940352148,50.85263254483481],"type":"Point"}
}