{
  "type": "Feature",
  "properties": {
    "iso:country": "GB",
    "wof:name": "BS28 4ES",
    "wof:placetype": "postalcode"
  },
  "geometry": {"coordinates":[-2.839977,51.240413],"type":"Point"}
}
