{
  "type": "Feature",
  "properties": {
    "iso:country": "GB",
    "wof:name": "SG19 3RJ",
    "wof:placetype": "postalcode"
  },
  "geometry": {"coordinates":[-0.140406,52.187938],"type":"Point"}
}
