{
  "type": "Feature",
  "properties": {
    "date:inception_lower": "2011-08-01",
    "date:inception_upper": "2011-08-01",
    "iso:country": "GB",
    "wof:name": "NG10 2GG",
    "wof:placetype": "postalcode"
  },
  "geometry": {"coordinates":[-1.261734,52.89914],"type":"Point"}
}
