{
  "type": "Feature",
  "properties": {
    "iso:country": "GB",
    "wof:name": "NG10 2GG",
    "wof:placetype": "postalcode"
  },
  "geometry": {"coordinates":[-1.261734,52.89914],"type":"Point"}
}
