{
  "type": "Feature",
  "properties": {
    "iso:country": "GB",
    "wof:name": "RG7 4SA",
    "wof:placetype": "postalcode"
  },
  "geometry": {"coordinates":[-1.063485,51.435671],"type":"Point"}
}
