{
  "type": "Feature",
  "properties": {
    "iso:country":"GB",
    "wof:name":"RG7 4SA",
    "wof:placetype":"postalcode"
},
  "geometry": {"coordinates":[-1.0649314805301,51.435582237067],"type":"Point"}
}