{
  "type": "Feature",
  "properties": {
    "iso:country": "GB",
    "wof:name": "CW1 5RY",
    "wof:placetype": "postalcode"
  },
  "geometry": {"coordinates":[-2.394563,53.104022],"type":"Point"}
}
