{
  "type": "Feature",
  "properties": {
    "iso:country":"GB",
    "wof:name":"CW1 5RY",
    "wof:placetype":"postalcode"
},
  "geometry": {"coordinates":[-2.39456260218461,53.10402250345007],"type":"Point"}
}