{
  "type": "Feature",
  "properties": {
    "iso:country":"GB",
    "wof:name":"TN14 5RH",
    "wof:placetype":"postalcode"
},
  "geometry": {"coordinates":[0.19582751460161,51.30555712561696],"type":"Point"}
}