{
  "type": "Feature",
  "properties": {
    "iso:country": "GB",
    "wof:name": "TN14 5RH",
    "wof:placetype": "postalcode"
  },
  "geometry": {"coordinates":[0.195828,51.305557],"type":"Point"}
}
