{
  "type": "Feature",
  "properties": {
    "date:inception_lower": "2022-08-01",
    "date:inception_upper": "2022-08-01",
    "iso:country": "GB",
    "wof:name": "M5 4JA",
    "wof:placetype": "postalcode"
  },
  "geometry": {"coordinates":[-2.289058,53.482491],"type":"Point"}
}
