{
  "type": "Feature",
  "properties": {
    "iso:country": "GB",
    "wof:name": "KT23 3BB",
    "wof:placetype": "postalcode"
  },
  "geometry": {"coordinates":[-0.389321,51.285618],"type":"Point"}
}
