{
  "type": "Feature",
  "properties": {
    "date:inception_lower": "1980-01-01",
    "date:inception_upper": "1980-01-01",
    "iso:country": "GB",
    "wof:name": "KT23 3BB",
    "wof:placetype": "postalcode"
  },
  "geometry": {"coordinates":[-0.389321,51.285618],"type":"Point"}
}
