{
  "type": "Feature",
  "properties": {
    "date:inception_lower": "1980-01-01",
    "date:inception_upper": "1980-01-01",
    "iso:country": "GB",
    "wof:name": "MK42 9XX",
    "wof:placetype": "postalcode"
  },
  "geometry": {"coordinates":[-0.470388,52.114933],"type":"Point"}
}
