{
  "type": "Feature",
  "properties": {
    "iso:country": "GB",
    "wof:name": "MK42 9XX",
    "wof:placetype": "postalcode"
  },
  "geometry": {"coordinates":[-0.470646,52.115098],"type":"Point"}
}
