{
  "type": "Feature",
  "properties": {
    "iso:country":"GB",
    "wof:name":"WA3 3GX",
    "wof:placetype":"postalcode"
},
  "geometry": {"coordinates":[-2.60165930361138,53.47774842576771],"type":"Point"}
}