{
  "type": "Feature",
  "properties": {
    "date:inception_lower": "1998-06-01",
    "date:inception_upper": "1998-06-01",
    "iso:country": "GB",
    "wof:name": "YO31 1ET",
    "wof:placetype": "postalcode"
  },
  "geometry": {"coordinates":[-1.049793,53.969323],"type":"Point"}
}
