{
  "type": "Feature",
  "properties": {
    "iso:country": "GB",
    "wof:name": "YO31 1ET",
    "wof:placetype": "postalcode"
  },
  "geometry": {"coordinates":[-1.049793,53.969323],"type":"Point"}
}
