{
  "type": "Feature",
  "properties": {
    "iso:country":"GB",
    "wof:name":"CB4 2EE",
    "wof:placetype":"postalcode"
},
  "geometry": {"coordinates":[0.12389252691671,52.21953289843518],"type":"Point"}
}