{
  "type": "Feature",
  "properties": {
    "iso:country": "GB",
    "wof:name": "CB4 2EE",
    "wof:placetype": "postalcode"
  },
  "geometry": {"coordinates":[0.123893,52.219533],"type":"Point"}
}
