{
  "type": "Feature",
  "properties": {
    "iso:country":"GB",
    "wof:name":"UB6 7PE",
    "wof:placetype":"postalcode"
},
  "geometry": {"coordinates":[-0.32670189022397,51.53875812048015],"type":"Point"}
}