{
  "type": "Feature",
  "properties": {
    "date:inception_lower": "1980-01-01",
    "date:inception_upper": "1980-01-01",
    "iso:country": "GB",
    "wof:name": "UB6 7PE",
    "wof:placetype": "postalcode"
  },
  "geometry": {"coordinates":[-0.326702,51.538758],"type":"Point"}
}
