{
  "type": "Feature",
  "properties": {
    "iso:country":"GB",
    "wof:name":"EH3 5PS",
    "wof:placetype":"postalcode"
},
  "geometry": {"coordinates":[-3.21140028853825,55.97081056680764],"type":"Point"}
}