{
  "type": "Feature",
  "properties": {
    "date:inception_lower":"1980-01-01",
    "date:inception_upper":"1980-01-31",
    "iso:country":"GB",
    "wof:name":"EH3 5PS",
    "wof:placetype":"postalcode"
},
  "geometry": {"coordinates":[-3.2114,55.970811],"type":"Point"}
}