{
  "type": "Feature",
  "properties": {
    "iso:country": "GB",
    "wof:name": "PL30 4DL",
    "wof:placetype": "postalcode"
  },
  "geometry": {"coordinates":[-4.633116,50.487601],"type":"Point"}
}
