{
  "type": "Feature",
  "properties": {
    "iso:country":"GB",
    "wof:name":"IP33 3TR",
    "wof:placetype":"postalcode"
},
  "geometry": {"coordinates":[0.66966024527732,52.24823751858567],"type":"Point"}
}