{
  "type": "Feature",
  "properties": {
    "iso:country":"GB",
    "wof:name":"PL28 8NU",
    "wof:placetype":"postalcode"
},
  "geometry": {"coordinates":[-4.99134128138182,50.52759518385253],"type":"Point"}
}