{
  "type": "Feature",
  "properties": {
    "iso:country":"GB",
    "wof:name":"LD1 5HG",
    "wof:placetype":"postalcode"
},
  "geometry": {"coordinates":[-3.37842383893676,52.23822150649546],"type":"Point"}
}