{
  "type": "Feature",
  "properties": {
    "iso:country":"GB",
    "wof:name":"EC2Y 8DH",
    "wof:placetype":"postalcode"
},
  "geometry": {"coordinates":[-0.09662379094578,51.5209616916253],"type":"Point"}
}