{
  "type": "Feature",
  "properties": {
    "iso:country":"GB",
    "wof:name":"LS8 5PR",
    "wof:placetype":"postalcode"
},
  "geometry": {"coordinates":[-1.51851272386976,53.81425923831184],"type":"Point"}
}