{
  "type": "Feature",
  "properties": {
    "iso:country":"GB",
    "wof:name":"M14 5XF",
    "wof:placetype":"postalcode"
},
  "geometry": {"coordinates":[-2.22836706306814,53.4527811906225],"type":"Point"}
}