{
  "type": "Feature",
  "properties": {
    "iso:country": "GB",
    "wof:name": "EN8 9JP",
    "wof:placetype": "postalcode"
  },
  "geometry": {"coordinates":[-0.030005,51.707634],"type":"Point"}
}
