{
  "type": "Feature",
  "properties": {
    "iso:country":"GB",
    "wof:name":"EN8 9JP",
    "wof:placetype":"postalcode"
},
  "geometry": {"coordinates":[-0.03000507270261,51.70763409308778],"type":"Point"}
}