{
  "type": "Feature",
  "properties": {
    "iso:country":"GB",
    "wof:name":"RG5 4AG",
    "wof:placetype":"postalcode"
},
  "geometry": {"coordinates":[-0.89968557306965,51.44532499684532],"type":"Point"}
}