{
  "type": "Feature",
  "properties": {
    "date:inception_lower": "1980-01-01",
    "date:inception_upper": "1980-01-01",
    "iso:country": "GB",
    "wof:name": "LN3 4HL",
    "wof:placetype": "postalcode"
  },
  "geometry": {"coordinates":[-0.425559,53.23477],"type":"Point"}
}
