{
  "type": "Feature",
  "properties": {
    "iso:country": "GB",
    "wof:name": "LN3 4HL",
    "wof:placetype": "postalcode"
  },
  "geometry": {"coordinates":[-0.425559,53.23477],"type":"Point"}
}
