{
  "type": "Feature",
  "properties": {
    "iso:country":"GB",
    "wof:name":"PH15 2EW",
    "wof:placetype":"postalcode"
},
  "geometry": {"coordinates":[-3.88709413505237,56.59755404145345],"type":"Point"}
}