{
  "type": "Feature",
  "properties": {
    "date:inception_lower": "1980-01-01",
    "date:inception_upper": "1980-01-01",
    "iso:country": "GB",
    "wof:name": "PH15 2EW",
    "wof:placetype": "postalcode"
  },
  "geometry": {"coordinates":[-3.887078,56.597563],"type":"Point"}
}
