{
  "type": "Feature",
  "properties": {
    "iso:country":"GB",
    "wof:name":"TN4 8FE",
    "wof:placetype":"postalcode"
},
  "geometry": {"coordinates":[0.23479557870705,51.13614920297907],"type":"Point"}
}