{
  "type": "Feature",
  "properties": {
    "iso:country": "GB",
    "wof:name": "SK3 0XN",
    "wof:placetype": "postalcode"
  },
  "geometry": {"coordinates":[-2.186093,53.393475],"type":"Point"}
}
