{
  "type": "Feature",
  "properties": {
    "iso:country":"GB",
    "wof:name":"WV7 3PU",
    "wof:placetype":"postalcode"
},
  "geometry": {"coordinates":[-2.27435757467022,52.63871917679023],"type":"Point"}
}