{
  "type": "Feature",
  "properties": {
    "date:inception_lower":"2014-02-01",
    "date:inception_upper":"2014-02-28",
    "iso:country":"GB",
    "wof:name":"TA20 1FL",
    "wof:placetype":"postalcode"
},
  "geometry": {"coordinates":[-2.972065,50.87192],"type":"Point"}
}