{
  "type": "Feature",
  "properties": {
    "iso:country": "GB",
    "wof:name": "TA20 1FL",
    "wof:placetype": "postalcode"
  },
  "geometry": {"coordinates":[-2.972065,50.87192],"type":"Point"}
}
