{
  "type": "Feature",
  "properties": {
    "iso:country": "GB",
    "wof:name": "BA6 9AE",
    "wof:placetype": "postalcode"
  },
  "geometry": {"coordinates":[-2.724764,51.147239],"type":"Point"}
}
