{
  "type": "Feature",
  "properties": {
    "date:inception_lower":"2003-05-01",
    "date:inception_upper":"2003-05-31",
    "iso:country":"GB",
    "wof:name":"BA6 9AE",
    "wof:placetype":"postalcode"
},
  "geometry": {"coordinates":[-2.724764,51.147239],"type":"Point"}
}