{
  "type": "Feature",
  "properties": {
    "iso:country":"GB",
    "wof:name":"BA6 9AE",
    "wof:placetype":"postalcode"
},
  "geometry": {"coordinates":[-2.72476429576922,51.14723904732598],"type":"Point"}
}