{
  "type": "Feature",
  "properties": {
    "iso:country": "GB",
    "wof:name": "GL20 5TX",
    "wof:placetype": "postalcode"
  },
  "geometry": {"coordinates":[-2.161207,51.983315],"type":"Point"}
}
