{
  "type": "Feature",
  "properties": {
    "iso:country":"GB",
    "wof:name":"AB25 3TY",
    "wof:placetype":"postalcode"
},
  "geometry": {"coordinates":[-2.10703066926942,57.15531080774365],"type":"Point"}
}