{
  "type": "Feature",
  "properties": {
    "iso:country":"GB",
    "wof:name":"LU1 2LT",
    "wof:placetype":"postalcode"
},
  "geometry": {"coordinates":[-0.41428108384926,51.88247726244224],"type":"Point"}
}