{
  "type": "Feature",
  "properties": {
    "iso:country": "GB",
    "wof:name": "LU1 2LT",
    "wof:placetype": "postalcode"
  },
  "geometry": {"coordinates":[-0.458618,51.905267],"type":"Point"}
}
