{
  "type": "Feature",
  "properties": {
    "date:inception_lower": "1980-01-01",
    "date:inception_upper": "1980-01-01",
    "iso:country": "GB",
    "wof:name": "NG6 9EF",
    "wof:placetype": "postalcode"
  },
  "geometry": {"coordinates":[-1.181695,52.993788],"type":"Point"}
}
