{
  "type": "Feature",
  "properties": {
    "iso:country":"GB",
    "wof:name":"NG6 9EF",
    "wof:placetype":"postalcode"
},
  "geometry": {"coordinates":[-1.18169473595385,52.99378758689138],"type":"Point"}
}