{
  "type": "Feature",
  "properties": {
    "iso:country":"GB",
    "wof:name":"HA0 3QN",
    "wof:placetype":"postalcode"
},
  "geometry": {"coordinates":[-0.30769793462897,51.56048963001708],"type":"Point"}
}