{
  "type": "Feature",
  "properties": {
    "iso:country":"GB",
    "wof:name":"BS30 6DL",
    "wof:placetype":"postalcode"
},
  "geometry": {"coordinates":[-2.49848092304681,51.44218665894334],"type":"Point"}
}