{
  "type": "Feature",
  "properties": {
    "iso:country": "GB",
    "wof:name": "BS30 6DL",
    "wof:placetype": "postalcode"
  },
  "geometry": {"coordinates":[-2.49811,51.442366],"type":"Point"}
}
