{
  "type": "Feature",
  "properties": {
    "iso:country":"GB",
    "wof:name":"CM9 8TB",
    "wof:placetype":"postalcode"
},
  "geometry": {"coordinates":[0.84836127118203,51.75911770893027],"type":"Point"}
}