{
  "type": "Feature",
  "properties": {
    "iso:country":"GB",
    "wof:name":"NW6 1AA",
    "wof:placetype":"postalcode"
},
  "geometry": {"coordinates":[-0.1932813164975,51.55242607282169],"type":"Point"}
}