{
  "type": "Feature",
  "properties": {
    "date:inception_lower": "1980-01-01",
    "date:inception_upper": "1980-01-01",
    "iso:country": "GB",
    "wof:name": "MK44 1QX",
    "wof:placetype": "postalcode"
  },
  "geometry": {"coordinates":[-0.504548,52.211866],"type":"Point"}
}
