{
  "type": "Feature",
  "properties": {
    "date:inception_lower":"1998-12-01",
    "date:inception_upper":"1998-12-31",
    "iso:country":"GB",
    "wof:name":"EX15 1UX",
    "wof:placetype":"postalcode"
},
  "geometry": {"coordinates":[-3.403584,50.854101],"type":"Point"}
}