{
  "type": "Feature",
  "properties": {
    "iso:country":"GB",
    "wof:name":"EX15 1UX",
    "wof:placetype":"postalcode"
},
  "geometry": {"coordinates":[-3.40358392421052,50.85410066370095],"type":"Point"}
}