{
  "type": "Feature",
  "properties": {
    "date:inception_lower": "2016-11-01",
    "date:inception_upper": "2016-11-01",
    "iso:country": "GB",
    "wof:name": "AB23 8AN",
    "wof:placetype": "postalcode"
  },
  "geometry": {"coordinates":[-2.076944,57.198687],"type":"Point"}
}
