{
  "type": "Feature",
  "properties": {
    "iso:country":"GB",
    "wof:name":"S81 7LN",
    "wof:placetype":"postalcode"
},
  "geometry": {"coordinates":[-1.11874683697103,53.31889160464414],"type":"Point"}
}