{
  "type": "Feature",
  "properties": {
    "iso:country": "GB",
    "wof:name": "S81 7LN",
    "wof:placetype": "postalcode"
  },
  "geometry": {"coordinates":[-1.118747,53.318892],"type":"Point"}
}
