{
  "type": "Feature",
  "properties": {
    "date:inception_lower": "1980-01-01",
    "date:inception_upper": "1980-01-01",
    "iso:country": "GB",
    "wof:name": "RM11 1AJ",
    "wof:placetype": "postalcode"
  },
  "geometry": {"coordinates":[0.192245,51.568265],"type":"Point"}
}
