{
  "type": "Feature",
  "properties": {
    "iso:country":"GB",
    "wof:name":"TA20 3HA",
    "wof:placetype":"postalcode"
},
  "geometry": {"coordinates":[-3.06314215004147,50.9102530644976],"type":"Point"}
}