{
  "type": "Feature",
  "properties": {
    "iso:country":"GB",
    "wof:name":"HG4 1RN",
    "wof:placetype":"postalcode"
},
  "geometry": {"coordinates":[-1.52249641174111,54.1260796086558],"type":"Point"}
}