{
  "type": "Feature",
  "properties": {
    "iso:country":"GB",
    "wof:name":"FK1 3DG",
    "wof:placetype":"postalcode"
},
  "geometry": {"coordinates":[-3.79850535979395,55.93329302364734],"type":"Point"}
}