{
  "type": "Feature",
  "properties": {
    "iso:country":"GB",
    "wof:name":"SA1 4QF",
    "wof:placetype":"postalcode"
},
  "geometry": {"coordinates":[-3.96254053925964,51.61883291913175],"type":"Point"}
}