{
  "type": "Feature",
  "properties": {
    "iso:country": "GB",
    "wof:name": "SA1 4QF",
    "wof:placetype": "postalcode"
  },
  "geometry": {"coordinates":[-3.96254,51.618833],"type":"Point"}
}
