{
  "type": "Feature",
  "properties": {
    "date:inception_lower": "1980-01-01",
    "date:inception_upper": "1980-01-01",
    "iso:country": "GB",
    "wof:name": "SA1 4QF",
    "wof:placetype": "postalcode"
  },
  "geometry": {"coordinates":[-3.96254,51.618833],"type":"Point"}
}
