{
  "type": "Feature",
  "properties": {
    "date:inception_lower": "1995-12-01",
    "date:inception_upper": "1995-12-01",
    "iso:country": "GB",
    "wof:name": "AL7 3NZ",
    "wof:placetype": "postalcode"
  },
  "geometry": {"coordinates":[-0.195704,51.796375],"type":"Point"}
}
