{
  "type": "Feature",
  "properties": {
    "iso:country":"GB",
    "wof:name":"AL7 3NZ",
    "wof:placetype":"postalcode"
},
  "geometry": {"coordinates":[-0.19572984284559,51.79635074863773],"type":"Point"}
}