{
  "type": "Feature",
  "properties": {
    "iso:country": "GB",
    "wof:name": "TF1 2BN",
    "wof:placetype": "postalcode"
  },
  "geometry": {"coordinates":[-2.529153,52.696468],"type":"Point"}
}
