{
  "type": "Feature",
  "properties": {
    "iso:country":"GB",
    "wof:name":"TF1 2BN",
    "wof:placetype":"postalcode"
},
  "geometry": {"coordinates":[-2.52915296279742,52.69646803750869],"type":"Point"}
}