{
  "type": "Feature",
  "properties": {
    "iso:country":"GB",
    "wof:name":"CT11 7BJ",
    "wof:placetype":"postalcode"
},
  "geometry": {"coordinates":[1.41735537862564,51.34970536811139],"type":"Point"}
}