{
  "type": "Feature",
  "properties": {
    "iso:country": "GB",
    "wof:name": "CT11 7BJ",
    "wof:placetype": "postalcode"
  },
  "geometry": {"coordinates":[1.417355,51.349705],"type":"Point"}
}
