{
  "type": "Feature",
  "properties": {
    "iso:country": "GB",
    "wof:name": "TA3 7SU",
    "wof:placetype": "postalcode"
  },
  "geometry": {"coordinates":[-3.149888,50.953279],"type":"Point"}
}
