{
  "type": "Feature",
  "properties": {
    "iso:country":"GB",
    "wof:name":"AL7 2NJ",
    "wof:placetype":"postalcode"
},
  "geometry": {"coordinates":[-0.1673623967591,51.80031810466905],"type":"Point"}
}