{
  "type": "Feature",
  "properties": {
    "date:inception_lower": "1987-04-01",
    "date:inception_upper": "1987-04-01",
    "iso:country": "GB",
    "wof:name": "AL7 2NJ",
    "wof:placetype": "postalcode"
  },
  "geometry": {"coordinates":[-0.167308,51.800315],"type":"Point"}
}
