{
  "type": "Feature",
  "properties": {
    "date:inception_lower": "1980-01-01",
    "date:inception_upper": "1980-01-01",
    "iso:country": "GB",
    "wof:name": "HR1 3AN",
    "wof:placetype": "postalcode"
  },
  "geometry": {"coordinates":[-2.693208,52.08227],"type":"Point"}
}
