{
  "type": "Feature",
  "properties": {
    "date:inception_lower": "1980-01-01",
    "date:inception_upper": "1980-01-01",
    "iso:country": "GB",
    "wof:name": "HR1 3AN",
    "wof:placetype": "postalcode"
  },
  "geometry": {"coordinates":[-2.692487,52.082841],"type":"Point"}
}
