{
  "type": "Feature",
  "properties": {
    "iso:country":"GB",
    "wof:name":"HR1 3AN",
    "wof:placetype":"postalcode"
},
  "geometry": {"coordinates":[-2.69248602621204,52.08283178877302],"type":"Point"}
}