{
  "type": "Feature",
  "properties": {
    "iso:country":"GB",
    "wof:name":"CF3 5SE",
    "wof:placetype":"postalcode"
},
  "geometry": {"coordinates":[-3.12193268460636,51.52284982388355],"type":"Point"}
}