{
  "type": "Feature",
  "properties": {
    "date:inception_lower":"1980-01-01",
    "date:inception_upper":"1980-01-31",
    "iso:country":"GB",
    "wof:name":"SW2 2HY",
    "wof:placetype":"postalcode"
},
  "geometry": {"coordinates":[-0.113592,51.451813],"type":"Point"}
}