{
  "type": "Feature",
  "properties": {
    "date:inception_lower":"1985-10-01",
    "date:inception_upper":"1985-10-31",
    "iso:country":"GB",
    "wof:name":"PL20 7NJ",
    "wof:placetype":"postalcode"
},
  "geometry": {"coordinates":[-4.129017,50.496768],"type":"Point"}
}