{
  "type": "Feature",
  "properties": {
    "date:inception_lower": "1980-01-01",
    "date:inception_upper": "1980-01-01",
    "iso:country": "GB",
    "wof:name": "DT11 0TA",
    "wof:placetype": "postalcode"
  },
  "geometry": {"coordinates":[-2.243897,50.886406],"type":"Point"}
}
