{
  "type": "Feature",
  "properties": {
    "iso:country":"GB",
    "wof:name":"DT11 0TA",
    "wof:placetype":"postalcode"
},
  "geometry": {"coordinates":[-2.24389675386728,50.88640645587643],"type":"Point"}
}