{
  "type": "Feature",
  "properties": {
    "iso:country": "GB",
    "wof:name": "PE13 2TG",
    "wof:placetype": "postalcode"
  },
  "geometry": {"coordinates":[0.165155,52.660148],"type":"Point"}
}
