{
  "type": "Feature",
  "properties": {
    "iso:country":"GB",
    "wof:name":"PE13 2TG",
    "wof:placetype":"postalcode"
},
  "geometry": {"coordinates":[0.16515532241465,52.66014774736909],"type":"Point"}
}