{
  "type": "Feature",
  "properties": {
    "iso:country":"GB",
    "wof:name":"NN13 7DT",
    "wof:placetype":"postalcode"
},
  "geometry": {"coordinates":[-1.14812760352823,52.02880809195256],"type":"Point"}
}