{
  "type": "Feature",
  "properties": {
    "date:inception_lower": "1980-01-01",
    "date:inception_upper": "1980-01-01",
    "iso:country": "GB",
    "wof:name": "TN12 7BH",
    "wof:placetype": "postalcode"
  },
  "geometry": {"coordinates":[0.410337,51.15091],"type":"Point"}
}
