{
  "type": "Feature",
  "properties": {
    "iso:country":"GB",
    "wof:name":"TQ8 8EF",
    "wof:placetype":"postalcode"
},
  "geometry": {"coordinates":[-3.77554137760131,50.23893108981298],"type":"Point"}
}