{
  "type": "Feature",
  "properties": {
    "iso:country": "GB",
    "wof:name": "SS0 9LA",
    "wof:placetype": "postalcode"
  },
  "geometry": {"coordinates":[0.691462,51.543861],"type":"Point"}
}
