{
  "type": "Feature",
  "properties": {
    "iso:country": "GB",
    "wof:name": "DY10 3PB",
    "wof:placetype": "postalcode"
  },
  "geometry": {"coordinates":[-2.182399,52.429333],"type":"Point"}
}
