{
  "type": "Feature",
  "properties": {
    "iso:country":"GB",
    "wof:name":"DY10 3PB",
    "wof:placetype":"postalcode"
},
  "geometry": {"coordinates":[-2.18257486828163,52.42918924807172],"type":"Point"}
}