{
  "type": "Feature",
  "properties": {
    "date:inception_lower": "1980-01-01",
    "date:inception_upper": "1980-01-01",
    "iso:country": "GB",
    "wof:name": "DY10 3PB",
    "wof:placetype": "postalcode"
  },
  "geometry": {"coordinates":[-2.182399,52.429333],"type":"Point"}
}
