{
  "type": "Feature",
  "properties": {
    "iso:country": "GB",
    "wof:name": "KT23 3EX",
    "wof:placetype": "postalcode"
  },
  "geometry": {"coordinates":[-0.382307,51.279305],"type":"Point"}
}
