{
  "type": "Feature",
  "properties": {
    "iso:country":"GB",
    "wof:name":"RM1 1NT",
    "wof:placetype":"postalcode"
},
  "geometry": {"coordinates":[0.18218107069885,51.57748191207446],"type":"Point"}
}