{
  "type": "Feature",
  "properties": {
    "iso:country": "GB",
    "wof:name": "UB1 3JL",
    "wof:placetype": "postalcode"
  },
  "geometry": {"coordinates":[-0.36164,51.516294],"type":"Point"}
}
