{
  "type": "Feature",
  "properties": {
    "iso:country":"GB",
    "wof:name":"SO50 7PW",
    "wof:placetype":"postalcode"
},
  "geometry": {"coordinates":[-1.29794873450601,50.94922643723562],"type":"Point"}
}