{
  "type": "Feature",
  "properties": {
    "iso:country": "GB",
    "wof:name": "SO50 7PW",
    "wof:placetype": "postalcode"
  },
  "geometry": {"coordinates":[-1.297923,50.949218],"type":"Point"}
}
