{
  "type": "Feature",
  "properties": {
    "iso:country": "GB",
    "wof:name": "SG8 8AU",
    "wof:placetype": "postalcode"
  },
  "geometry": {"coordinates":[-0.01829,52.008847],"type":"Point"}
}
