{
  "type": "Feature",
  "properties": {
    "iso:country":"GB",
    "wof:name":"SG8 8AU",
    "wof:placetype":"postalcode"
},
  "geometry": {"coordinates":[-0.01844545535585,52.00893856150576],"type":"Point"}
}