{
  "type": "Feature",
  "properties": {
    "date:inception_lower":"1980-01-01",
    "date:inception_upper":"1980-01-31",
    "iso:country":"GB",
    "wof:name":"SW19 2RQ",
    "wof:placetype":"postalcode"
},
  "geometry": {"coordinates":[-0.182624,51.411808],"type":"Point"}
}