{
  "type": "Feature",
  "properties": {
    "iso:country": "GB",
    "wof:name": "SW19 2RQ",
    "wof:placetype": "postalcode"
  },
  "geometry": {"coordinates":[-0.182624,51.411808],"type":"Point"}
}
