{
  "type": "Feature",
  "properties": {
    "iso:country":"GB",
    "wof:name":"SW19 2RQ",
    "wof:placetype":"postalcode"
},
  "geometry": {"coordinates":[-0.1826238982255,51.41180758479172],"type":"Point"}
}