{
  "type": "Feature",
  "properties": {
    "date:inception_lower": "2000-06-01",
    "date:inception_upper": "2000-06-01",
    "iso:country": "GB",
    "wof:name": "SN5 3ND",
    "wof:placetype": "postalcode"
  },
  "geometry": {"coordinates":[-1.854077,51.568374],"type":"Point"}
}
