{
  "type": "Feature",
  "properties": {
    "iso:country":"GB",
    "wof:name":"SN5 3ND",
    "wof:placetype":"postalcode"
},
  "geometry": {"coordinates":[-1.85408715377744,51.56837209594725],"type":"Point"}
}