{
  "type": "Feature",
  "properties": {
    "iso:country":"GB",
    "wof:name":"W10 6JX",
    "wof:placetype":"postalcode"
},
  "geometry": {"coordinates":[-0.21583424211079,51.51830335502112],"type":"Point"}
}