{
  "type": "Feature",
  "properties": {
    "iso:country":"GB",
    "wof:name":"LS1 3AX",
    "wof:placetype":"postalcode"
},
  "geometry": {"coordinates":[-1.55061815373271,53.80020063827006],"type":"Point"}
}