{
  "type": "Feature",
  "properties": {
    "iso:country":"GB",
    "wof:name":"NW10 1LT",
    "wof:placetype":"postalcode"
},
  "geometry": {"coordinates":[-0.24218651448649,51.55374445796944],"type":"Point"}
}