{
  "type": "Feature",
  "properties": {
    "iso:country": "GB",
    "wof:name": "NW10 1LT",
    "wof:placetype": "postalcode"
  },
  "geometry": {"coordinates":[-0.242186,51.553744],"type":"Point"}
}
