{
  "type": "Feature",
  "properties": {
    "date:inception_lower":"1990-02-01",
    "date:inception_upper":"1990-02-28",
    "iso:country":"GB",
    "wof:name":"TS10 2QD",
    "wof:placetype":"postalcode"
},
  "geometry": {"coordinates":[-1.052095,54.59842],"type":"Point"}
}