{
  "type": "Feature",
  "properties": {
    "iso:country": "GB",
    "wof:name": "TS10 2QD",
    "wof:placetype": "postalcode"
  },
  "geometry": {"coordinates":[-1.052095,54.59842],"type":"Point"}
}
