{
  "type": "Feature",
  "properties": {
    "iso:country":"GB",
    "wof:name":"B35 6HY",
    "wof:placetype":"postalcode"
},
  "geometry": {"coordinates":[-1.78696159909578,52.5248734562382],"type":"Point"}
}