{
  "type": "Feature",
  "properties": {
    "date:inception_lower": "1980-01-01",
    "date:inception_upper": "1980-01-01",
    "iso:country": "GB",
    "wof:name": "KT18 6LP",
    "wof:placetype": "postalcode"
  },
  "geometry": {"coordinates":[-0.273079,51.276821],"type":"Point"}
}
