{
  "type": "Feature",
  "properties": {
    "iso:country":"GB",
    "wof:name":"ME14 4BB",
    "wof:placetype":"postalcode"
},
  "geometry": {"coordinates":[0.56302521185712,51.27039242495055],"type":"Point"}
}