{
  "type": "Feature",
  "properties": {
    "iso:country":"GB",
    "wof:name":"W9 2DU",
    "wof:placetype":"postalcode"
},
  "geometry": {"coordinates":[-0.1940398963568,51.52379692072951],"type":"Point"}
}