{
  "type": "Feature",
  "properties": {
    "iso:country":"GB",
    "wof:name":"NG3 6GJ",
    "wof:placetype":"postalcode"
},
  "geometry": {"coordinates":[-1.12639933138052,52.98080904514616],"type":"Point"}
}