{
  "type": "Feature",
  "properties": {
    "iso:country":"GB",
    "wof:name":"BH12 1EG",
    "wof:placetype":"postalcode"
},
  "geometry": {"coordinates":[-1.90541855941466,50.7278874022745],"type":"Point"}
}