{
  "type": "Feature",
  "properties": {
    "iso:country":"GB",
    "wof:name":"B67 5AJ",
    "wof:placetype":"postalcode"
},
  "geometry": {"coordinates":[-1.9729679476038,52.4783410298889],"type":"Point"}
}