{
  "type": "Feature",
  "properties": {
    "iso:country":"GB",
    "wof:name":"LL11 5YG",
    "wof:placetype":"postalcode"
},
  "geometry": {"coordinates":[-3.09283453200919,53.07738240577422],"type":"Point"}
}