{
  "type": "Feature",
  "properties": {
    "iso:country": "GB",
    "wof:name": "LL11 5YG",
    "wof:placetype": "postalcode"
  },
  "geometry": {"coordinates":[-3.092834,53.077382],"type":"Point"}
}
