{
  "type": "Feature",
  "properties": {
    "iso:country":"GB",
    "wof:name":"FY6 8AU",
    "wof:placetype":"postalcode"
},
  "geometry": {"coordinates":[-2.99394012157251,53.84273415329697],"type":"Point"}
}