{
  "type": "Feature",
  "properties": {
    "iso:country": "GB",
    "wof:name": "BA10 0LA",
    "wof:placetype": "postalcode"
  },
  "geometry": {"coordinates":[-2.392963,51.110261],"type":"Point"}
}
