{
  "type": "Feature",
  "properties": {
    "iso:country":"GB",
    "wof:name":"B45 9SA",
    "wof:placetype":"postalcode"
},
  "geometry": {"coordinates":[-2.01954683173949,52.39845706721832],"type":"Point"}
}