{
  "type": "Feature",
  "properties": {
    "iso:country":"GB",
    "wof:name":"PL30 5JX",
    "wof:placetype":"postalcode"
},
  "geometry": {"coordinates":[-4.75576562609561,50.45275585156379],"type":"Point"}
}