{
  "type": "Feature",
  "properties": {
    "iso:country": "GB",
    "wof:name": "PL30 5JX",
    "wof:placetype": "postalcode"
  },
  "geometry": {"coordinates":[-4.755766,50.452756],"type":"Point"}
}
