{
  "type": "Feature",
  "properties": {
    "date:inception_lower": "1995-07-01",
    "date:inception_upper": "1995-07-01",
    "iso:country": "GB",
    "wof:name": "CF82 7GL",
    "wof:placetype": "postalcode"
  },
  "geometry": {"coordinates":[-3.248757,51.654782],"type":"Point"}
}
