{
  "type": "Feature",
  "properties": {
    "iso:country":"GB",
    "wof:name":"CF82 7GL",
    "wof:placetype":"postalcode"
},
  "geometry": {"coordinates":[-3.24875715630678,51.65478170562761],"type":"Point"}
}