{
  "type": "Feature",
  "properties": {
    "date:inception_lower": "2022-04-01",
    "date:inception_upper": "2022-04-01",
    "iso:country": "GB",
    "wof:name": "DN4 7FY",
    "wof:placetype": "postalcode"
  },
  "geometry": {"coordinates":[-1.07569,53.49262],"type":"Point"}
}
