{
  "type": "Feature",
  "properties": {
    "date:inception_lower": "1980-01-01",
    "date:inception_upper": "1980-01-01",
    "iso:country": "GB",
    "wof:name": "DA11 0PR",
    "wof:placetype": "postalcode"
  },
  "geometry": {"coordinates":[0.365607,51.438562],"type":"Point"}
}
