{
  "type": "Feature",
  "properties": {
    "iso:country":"GB",
    "wof:name":"TN4 9HT",
    "wof:placetype":"postalcode"
},
  "geometry": {"coordinates":[0.2737657379219,51.14695447707611],"type":"Point"}
}