{
  "type": "Feature",
  "properties": {
    "date:inception_lower": "1980-01-01",
    "date:inception_upper": "1980-01-01",
    "iso:country": "GB",
    "wof:name": "TN4 9HT",
    "wof:placetype": "postalcode"
  },
  "geometry": {"coordinates":[0.273766,51.146954],"type":"Point"}
}
