{
  "type": "Feature",
  "properties": {
    "iso:country": "GB",
    "wof:name": "HD4 5UJ",
    "wof:placetype": "postalcode"
  },
  "geometry": {"coordinates":[-1.837677,53.634572],"type":"Point"}
}
