{
  "type": "Feature",
  "properties": {
    "iso:country":"GB",
    "wof:name":"HD4 5UJ",
    "wof:placetype":"postalcode"
},
  "geometry": {"coordinates":[-1.83767667998002,53.63457154158223],"type":"Point"}
}