{
  "type": "Feature",
  "properties": {
    "iso:country":"GB",
    "wof:name":"PL26 6XB",
    "wof:placetype":"postalcode"
},
  "geometry": {"coordinates":[-4.78784843091885,50.26955032234417],"type":"Point"}
}