{
  "type": "Feature",
  "properties": {
    "iso:country":"GB",
    "wof:name":"DA16 1JB",
    "wof:placetype":"postalcode"
},
  "geometry": {"coordinates":[0.12239552103457,51.46113233426328],"type":"Point"}
}