{
  "type": "Feature",
  "properties": {
    "iso:country": "GB",
    "wof:name": "PO7 3BH",
    "wof:placetype": "postalcode"
  },
  "geometry": {"coordinates":[-1.039976,50.881853],"type":"Point"}
}
