{
  "type": "Feature",
  "properties": {
    "iso:country":"GB",
    "wof:name":"YO24 1EJ",
    "wof:placetype":"postalcode"
},
  "geometry": {"coordinates":[-1.09724181278403,53.95205376209224],"type":"Point"}
}