{
  "type": "Feature",
  "properties": {
    "iso:country":"GB",
    "wof:name":"MK46 5NT",
    "wof:placetype":"postalcode"
},
  "geometry": {"coordinates":[-0.75994893023245,52.14690403686905],"type":"Point"}
}