{
  "type": "Feature",
  "properties": {
    "date:inception_lower": "1986-07-01",
    "date:inception_upper": "1986-07-01",
    "iso:country": "GB",
    "wof:name": "MK46 5NT",
    "wof:placetype": "postalcode"
  },
  "geometry": {"coordinates":[-0.759949,52.146904],"type":"Point"}
}
