{
  "type": "Feature",
  "properties": {
    "iso:country":"GB",
    "wof:name":"SL1 2JP",
    "wof:placetype":"postalcode"
},
  "geometry": {"coordinates":[-0.5975753989946,51.5044340235837],"type":"Point"}
}