{
  "type": "Feature",
  "properties": {
    "iso:country":"GB",
    "wof:name":"IP1 3PH",
    "wof:placetype":"postalcode"
},
  "geometry": {"coordinates":[1.14561907181274,52.06362689765572],"type":"Point"}
}