{
  "type": "Feature",
  "properties": {
    "iso:country":"GB",
    "wof:name":"PO13 0UD",
    "wof:placetype":"postalcode"
},
  "geometry": {"coordinates":[-1.1718295131085,50.83092118051934],"type":"Point"}
}