{
  "type": "Feature",
  "properties": {
    "iso:country":"GB",
    "wof:name":"S63 7TA",
    "wof:placetype":"postalcode"
},
  "geometry": {"coordinates":[-1.34739657524951,53.49241391501035],"type":"Point"}
}