{
  "type": "Feature",
  "properties": {
    "iso:country": "GB",
    "wof:name": "BS16 5NU",
    "wof:placetype": "postalcode"
  },
  "geometry": {"coordinates":[-2.505455,51.480929],"type":"Point"}
}
