{
  "type": "Feature",
  "properties": {
    "iso:country":"GB",
    "wof:name":"BS16 5NU",
    "wof:placetype":"postalcode"
},
  "geometry": {"coordinates":[-2.50545551111683,51.48092856580397],"type":"Point"}
}