{
  "type": "Feature",
  "properties": {
    "date:inception_lower":"1980-01-01",
    "date:inception_upper":"1980-01-31",
    "iso:country":"GB",
    "wof:name":"BS16 5NU",
    "wof:placetype":"postalcode"
},
  "geometry": {"coordinates":[-2.505455,51.480929],"type":"Point"}
}