{
  "type": "Feature",
  "properties": {
    "iso:country": "GB",
    "wof:name": "NG16 5AL",
    "wof:placetype": "postalcode"
  },
  "geometry": {"coordinates":[-1.320619,53.033065],"type":"Point"}
}
