{
  "type": "Feature",
  "properties": {
    "iso:country":"GB",
    "wof:name":"NG16 5AL",
    "wof:placetype":"postalcode"
},
  "geometry": {"coordinates":[-1.32061865794867,53.03306455234618],"type":"Point"}
}