{
  "type": "Feature",
  "properties": {
    "iso:country": "GB",
    "wof:name": "WA7 3BU",
    "wof:placetype": "postalcode"
  },
  "geometry": {"coordinates":[-2.657973,53.304679],"type":"Point"}
}
