{
  "type": "Feature",
  "properties": {
    "iso:country":"GB",
    "wof:name":"WA7 3BU",
    "wof:placetype":"postalcode"
},
  "geometry": {"coordinates":[-2.65797303757503,53.30467893201276],"type":"Point"}
}