{
  "type": "Feature",
  "properties": {
    "iso:country":"GB",
    "wof:name":"RG30 3SG",
    "wof:placetype":"postalcode"
},
  "geometry": {"coordinates":[-1.05770382476295,51.40648068925185],"type":"Point"}
}