{
  "type": "Feature",
  "properties": {
    "date:inception_lower": "2005-07-01",
    "date:inception_upper": "2005-07-01",
    "iso:country": "GB",
    "wof:name": "CM9 8WS",
    "wof:placetype": "postalcode"
  },
  "geometry": {"coordinates":[0.689273,51.770979],"type":"Point"}
}
