{
  "type": "Feature",
  "properties": {
    "iso:country":"GB",
    "wof:name":"HR8 2QE",
    "wof:placetype":"postalcode"
},
  "geometry": {"coordinates":[-2.48983667499378,52.03948848832443],"type":"Point"}
}