{
  "type": "Feature",
  "properties": {
    "date:inception_lower":"1980-01-01",
    "date:inception_upper":"1980-01-31",
    "iso:country":"GB",
    "wof:name":"EH21 7RN",
    "wof:placetype":"postalcode"
},
  "geometry": {"coordinates":[-3.048506,55.944423],"type":"Point"}
}