{
  "type": "Feature",
  "properties": {
    "iso:country":"GB",
    "wof:name":"TR2 4FE",
    "wof:placetype":"postalcode"
},
  "geometry": {"coordinates":[-4.92813158528534,50.31672453477747],"type":"Point"}
}