{
  "type": "Feature",
  "properties": {
    "iso:country":"GB",
    "wof:name":"PE25 1EZ",
    "wof:placetype":"postalcode"
},
  "geometry": {"coordinates":[0.34414736678644,53.16441977704038],"type":"Point"}
}