{
  "type": "Feature",
  "properties": {
    "iso:country": "GB",
    "wof:name": "PE25 1EZ",
    "wof:placetype": "postalcode"
  },
  "geometry": {"coordinates":[0.344147,53.164411],"type":"Point"}
}
