{
  "type": "Feature",
  "properties": {
    "date:inception_lower":"1990-02-01",
    "date:inception_upper":"1990-02-28",
    "iso:country":"GB",
    "wof:name":"MK8 0EA",
    "wof:placetype":"postalcode"
},
  "geometry": {"coordinates":[-0.80736,52.028055],"type":"Point"}
}