{
  "type": "Feature",
  "properties": {
    "date:inception_lower": "2000-12-01",
    "date:inception_upper": "2000-12-01",
    "iso:country": "GB",
    "wof:name": "WD23 1SE",
    "wof:placetype": "postalcode"
  },
  "geometry": {"coordinates":[-0.34488,51.636626],"type":"Point"}
}
