{
  "type": "Feature",
  "properties": {
    "iso:country":"GB",
    "wof:name":"S41 9RW",
    "wof:placetype":"postalcode"
},
  "geometry": {"coordinates":[-1.47305501668369,53.25989370007155],"type":"Point"}
}