{
  "type": "Feature",
  "properties": {
    "iso:country": "GB",
    "wof:name": "CV2 1AH",
    "wof:placetype": "postalcode"
  },
  "geometry": {"coordinates":[-1.455646,52.430057],"type":"Point"}
}
