{
  "type": "Feature",
  "properties": {
    "iso:country":"GB",
    "wof:name":"CV2 1AH",
    "wof:placetype":"postalcode"
},
  "geometry": {"coordinates":[-1.45564583829182,52.43005677402776],"type":"Point"}
}