{
  "type": "Feature",
  "properties": {
    "iso:country":"GB",
    "wof:name":"PO2 7RA",
    "wof:placetype":"postalcode"
},
  "geometry": {"coordinates":[-1.06536664557684,50.80930799466721],"type":"Point"}
}