{
  "type": "Feature",
  "properties": {
    "date:inception_lower":"1980-01-01",
    "date:inception_upper":"1980-01-31",
    "iso:country":"GB",
    "wof:name":"PO2 7RA",
    "wof:placetype":"postalcode"
},
  "geometry": {"coordinates":[-1.065367,50.809308],"type":"Point"}
}