{
  "type": "Feature",
  "properties": {
    "date:inception_lower":"1999-06-01",
    "date:inception_upper":"1999-06-30",
    "iso:country":"GB",
    "wof:name":"CH41 4DT",
    "wof:placetype":"postalcode"
},
  "geometry": {"coordinates":[-3.032713,53.389504],"type":"Point"}
}