{
  "type": "Feature",
  "properties": {
    "date:inception_lower": "2023-12-01",
    "date:inception_upper": "2023-12-01",
    "iso:country": "GB",
    "wof:name": "BA12 8GR",
    "wof:placetype": "postalcode"
  },
  "geometry": {"coordinates":[-2.209867,51.203577],"type":"Point"}
}
