{
  "type": "Feature",
  "properties": {
    "iso:country":"GB",
    "wof:name":"BN25 2UF",
    "wof:placetype":"postalcode"
},
  "geometry": {"coordinates":[0.08655833002421,50.79001195955664],"type":"Point"}
}