{
  "type": "Feature",
  "properties": {
    "iso:country": "GB",
    "wof:name": "BN25 2UF",
    "wof:placetype": "postalcode"
  },
  "geometry": {"coordinates":[0.086558,50.790012],"type":"Point"}
}
