{
  "type": "Feature",
  "properties": {
    "iso:country":"GB",
    "wof:name":"CR0 6RZ",
    "wof:placetype":"postalcode"
},
  "geometry": {"coordinates":[-0.08008674635907,51.38073036816965],"type":"Point"}
}