{
  "type": "Feature",
  "properties": {
    "iso:country": "GB",
    "wof:name": "PE9 1EJ",
    "wof:placetype": "postalcode"
  },
  "geometry": {"coordinates":[-0.478413,52.654408],"type":"Point"}
}
