{
  "type": "Feature",
  "properties": {
    "iso:country":"GB",
    "wof:name":"PE9 1EJ",
    "wof:placetype":"postalcode"
},
  "geometry": {"coordinates":[-0.47832132057123,52.65437041147764],"type":"Point"}
}