{
  "type": "Feature",
  "properties": {
    "iso:country":"GB",
    "wof:name":"SL2 2DY",
    "wof:placetype":"postalcode"
},
  "geometry": {"coordinates":[-0.63352170660271,51.53487359045617],"type":"Point"}
}