{
  "type": "Feature",
  "properties": {
    "iso:country":"GB",
    "wof:name":"FK3 9HY",
    "wof:placetype":"postalcode"
},
  "geometry": {"coordinates":[-3.71819742209042,56.0176699742232],"type":"Point"}
}