{
  "type": "Feature",
  "properties": {
    "iso:country":"GB",
    "wof:name":"PE34 4PG",
    "wof:placetype":"postalcode"
},
  "geometry": {"coordinates":[0.29550250235527,52.75621401499135],"type":"Point"}
}