{
  "type": "Feature",
  "properties": {
    "iso:country":"GB",
    "wof:name":"HX6 3RH",
    "wof:placetype":"postalcode"
},
  "geometry": {"coordinates":[-1.89921983984992,53.7014030511965],"type":"Point"}
}