{
  "type": "Feature",
  "properties": {
    "iso:country": "GB",
    "wof:name": "NR25 6FS",
    "wof:placetype": "postalcode"
  },
  "geometry": {"coordinates":[1.109908,52.910043],"type":"Point"}
}
