{
  "type": "Feature",
  "properties": {
    "iso:country": "GB",
    "wof:name": "AL3 6XZ",
    "wof:placetype": "postalcode"
  },
  "geometry": {"coordinates":[-0.322995,51.772371],"type":"Point"}
}
