{
  "type": "Feature",
  "properties": {
    "iso:country":"GB",
    "wof:name":"AL3 6XZ",
    "wof:placetype":"postalcode"
},
  "geometry": {"coordinates":[-0.32301259058947,51.77252720206719],"type":"Point"}
}