{
  "type": "Feature",
  "properties": {
    "iso:country":"GB",
    "wof:name":"CF45 4YU",
    "wof:placetype":"postalcode"
},
  "geometry": {"coordinates":[-3.34449546648612,51.65953307221664],"type":"Point"}
}