{
  "type": "Feature",
  "properties": {
    "date:inception_lower": "1980-01-01",
    "date:inception_upper": "1980-01-01",
    "iso:country": "GB",
    "wof:name": "CF45 4YU",
    "wof:placetype": "postalcode"
  },
  "geometry": {"coordinates":[-3.344495,51.659533],"type":"Point"}
}
