{
  "type": "Feature",
  "properties": {
    "iso:country":"GB",
    "wof:name":"ST5 1QQ",
    "wof:placetype":"postalcode"
},
  "geometry": {"coordinates":[-2.2271553728006,53.01044305903959],"type":"Point"}
}