{
  "type": "Feature",
  "properties": {
    "iso:country": "GB",
    "wof:name": "PL5 2TJ",
    "wof:placetype": "postalcode"
  },
  "geometry": {"coordinates":[-4.177164,50.419012],"type":"Point"}
}
