{
  "type": "Feature",
  "properties": {
    "iso:country":"GB",
    "wof:name":"PL5 2TJ",
    "wof:placetype":"postalcode"
},
  "geometry": {"coordinates":[-4.17716375154044,50.41901159757694],"type":"Point"}
}