{
  "type": "Feature",
  "properties": {
    "iso:country": "GB",
    "wof:name": "IP12 2EH",
    "wof:placetype": "postalcode"
  },
  "geometry": {"coordinates":[1.483298,52.156731],"type":"Point"}
}
