{
  "type": "Feature",
  "properties": {
    "iso:country":"GB",
    "wof:name":"PL9 8DU",
    "wof:placetype":"postalcode"
},
  "geometry": {"coordinates":[-4.06142236544909,50.35942923544352],"type":"Point"}
}