{
  "type": "Feature",
  "properties": {
    "date:inception_lower": "2016-10-01",
    "date:inception_upper": "2016-10-01",
    "iso:country": "GB",
    "wof:name": "HU15 2GH",
    "wof:placetype": "postalcode"
  },
  "geometry": {"coordinates":[-0.741464,53.753212],"type":"Point"}
}
