{
  "type": "Feature",
  "properties": {
    "iso:country": "GB",
    "wof:name": "WV5 9HW",
    "wof:placetype": "postalcode"
  },
  "geometry": {"coordinates":[-2.189997,52.533866],"type":"Point"}
}
