{
  "type": "Feature",
  "properties": {
    "date:inception_lower":"1980-01-01",
    "date:inception_upper":"1980-01-31",
    "iso:country":"GB",
    "wof:name":"WV5 9HW",
    "wof:placetype":"postalcode"
},
  "geometry": {"coordinates":[-2.189997,52.533866],"type":"Point"}
}