{
  "type": "Feature",
  "properties": {
    "iso:country":"GB",
    "wof:name":"WV5 9HW",
    "wof:placetype":"postalcode"
},
  "geometry": {"coordinates":[-2.1899971031819,52.53386572025941],"type":"Point"}
}