{
  "type": "Feature",
  "properties": {
    "date:inception_lower": "1985-04-01",
    "date:inception_upper": "1985-04-01",
    "iso:country": "GB",
    "wof:name": "MK4 1AT",
    "wof:placetype": "postalcode"
  },
  "geometry": {"coordinates":[-0.755201,52.01304],"type":"Point"}
}
