{
  "type": "Feature",
  "properties": {
    "iso:country":"GB",
    "wof:name":"MK4 1AT",
    "wof:placetype":"postalcode"
},
  "geometry": {"coordinates":[-0.75520140585931,52.01303967273125],"type":"Point"}
}