{
  "type": "Feature",
  "properties": {
    "iso:country": "GB",
    "wof:name": "BA11 2PT",
    "wof:placetype": "postalcode"
  },
  "geometry": {"coordinates":[-2.256101,51.257054],"type":"Point"}
}
