{
  "type": "Feature",
  "properties": {
    "iso:country":"GB",
    "wof:name":"BA11 2PT",
    "wof:placetype":"postalcode"
},
  "geometry": {"coordinates":[-2.25610093957,51.25705448594001],"type":"Point"}
}