{
  "type": "Feature",
  "properties": {
    "iso:country":"GB",
    "wof:name":"NN10 8BT",
    "wof:placetype":"postalcode"
},
  "geometry": {"coordinates":[-0.59246150649233,52.30618841624929],"type":"Point"}
}