{
  "type": "Feature",
  "properties": {
    "iso:country": "GB",
    "wof:name": "NN10 8BT",
    "wof:placetype": "postalcode"
  },
  "geometry": {"coordinates":[-0.592461,52.306188],"type":"Point"}
}
