{
  "type": "Feature",
  "properties": {
    "iso:country":"GB",
    "wof:name":"SP5 1PF",
    "wof:placetype":"postalcode"
},
  "geometry": {"coordinates":[-1.64765352392912,51.09057057894707],"type":"Point"}
}