{
  "type": "Feature",
  "properties": {
    "iso:country": "GB",
    "wof:name": "SP5 1PF",
    "wof:placetype": "postalcode"
  },
  "geometry": {"coordinates":[-1.647486,51.090546],"type":"Point"}
}
