{
  "type": "Feature",
  "properties": {
    "iso:country":"GB",
    "wof:name":"NE6 5SD",
    "wof:placetype":"postalcode"
},
  "geometry": {"coordinates":[-1.57792791231919,54.98973833129661],"type":"Point"}
}