{
  "type": "Feature",
  "properties": {
    "iso:country":"GB",
    "wof:name":"WF11 8NT",
    "wof:placetype":"postalcode"
},
  "geometry": {"coordinates":[-1.2682278249762,53.71058212996778],"type":"Point"}
}