{
  "type": "Feature",
  "properties": {
    "iso:country":"GB",
    "wof:name":"TW4 7LE",
    "wof:placetype":"postalcode"
},
  "geometry": {"coordinates":[-0.39359223030699,51.47327631850533],"type":"Point"}
}