{
  "type": "Feature",
  "properties": {
    "iso:country":"GB",
    "wof:name":"TW4 5NA",
    "wof:placetype":"postalcode"
},
  "geometry": {"coordinates":[-0.37179063182985,51.45107030850647],"type":"Point"}
}