{
  "type": "Feature",
  "properties": {
    "iso:country":"GB",
    "wof:name":"SY21 7EW",
    "wof:placetype":"postalcode"
},
  "geometry": {"coordinates":[-3.14210317102348,52.66201124525242],"type":"Point"}
}