{
  "type": "Feature",
  "properties": {
    "iso:country":"GB",
    "wof:name":"YO32 5SF",
    "wof:placetype":"postalcode"
},
  "geometry": {"coordinates":[-1.04069720563235,54.02287298124401],"type":"Point"}
}