{
  "type": "Feature",
  "properties": {
    "date:inception_lower": "2023-11-01",
    "date:inception_upper": "2023-11-01",
    "iso:country": "GB",
    "wof:name": "OX14 3XF",
    "wof:placetype": "postalcode"
  },
  "geometry": {"coordinates":[-1.247221,51.68698],"type":"Point"}
}
