{
  "type": "Feature",
  "properties": {
    "date:inception_lower": "1980-01-01",
    "date:inception_upper": "1980-01-01",
    "iso:country": "GB",
    "wof:name": "HU5 5HJ",
    "wof:placetype": "postalcode"
  },
  "geometry": {"coordinates":[-0.410148,53.752437],"type":"Point"}
}
