{
  "type": "Feature",
  "properties": {
    "iso:country":"GB",
    "wof:name":"HU5 5HJ",
    "wof:placetype":"postalcode"
},
  "geometry": {"coordinates":[-0.4101485150114,53.75243731594989],"type":"Point"}
}