{
  "type": "Feature",
  "properties": {
    "iso:country":"GB",
    "wof:name":"S70 3ED",
    "wof:placetype":"postalcode"
},
  "geometry": {"coordinates":[-1.44606033439571,53.53999343993382],"type":"Point"}
}