{
  "type": "Feature",
  "properties": {
    "iso:country":"GB",
    "wof:name":"G62 6ER",
    "wof:placetype":"postalcode"
},
  "geometry": {"coordinates":[-4.27449660837241,55.93179307058943],"type":"Point"}
}