{
  "type": "Feature",
  "properties": {
    "iso:country":"GB",
    "wof:name":"SG4 8PW",
    "wof:placetype":"postalcode"
},
  "geometry": {"coordinates":[-0.29768069161832,51.85134588695179],"type":"Point"}
}