{
  "type": "Feature",
  "properties": {
    "date:inception_lower": "2003-02-01",
    "date:inception_upper": "2003-02-01",
    "iso:country": "GB",
    "wof:name": "SG4 8PW",
    "wof:placetype": "postalcode"
  },
  "geometry": {"coordinates":[-0.297657,51.851335],"type":"Point"}
}
