{
  "type": "Feature",
  "properties": {
    "iso:country":"GB",
    "wof:name":"SK3 8PG",
    "wof:placetype":"postalcode"
},
  "geometry": {"coordinates":[-2.16570998737885,53.3912143226787],"type":"Point"}
}