{
  "type": "Feature",
  "properties": {
    "iso:country": "GB",
    "wof:name": "EX4 3SJ",
    "wof:placetype": "postalcode"
  },
  "geometry": {"coordinates":[-3.534479,50.726422],"type":"Point"}
}
