{
  "type": "Feature",
  "properties": {
    "iso:country":"GB",
    "wof:name":"RH12 3AG",
    "wof:placetype":"postalcode"
},
  "geometry": {"coordinates":[-0.48075416629801,51.10501812235011],"type":"Point"}
}