{
  "type": "Feature",
  "properties": {
    "date:inception_lower": "1998-06-01",
    "date:inception_upper": "1998-06-01",
    "iso:country": "GB",
    "wof:name": "GL4 6SU",
    "wof:placetype": "postalcode"
  },
  "geometry": {"coordinates":[-2.235241,51.841701],"type":"Point"}
}
