{
  "type": "Feature",
  "properties": {
    "iso:country":"GB",
    "wof:name":"GL4 6SU",
    "wof:placetype":"postalcode"
},
  "geometry": {"coordinates":[-2.23524068215049,51.8417014701461],"type":"Point"}
}