{
  "type": "Feature",
  "properties": {
    "iso:country":"GB",
    "wof:name":"HG4 2AA",
    "wof:placetype":"postalcode"
},
  "geometry": {"coordinates":[-1.52598058192032,54.13587182479985],"type":"Point"}
}