{
  "type": "Feature",
  "properties": {
    "date:inception_lower": "2012-05-01",
    "date:inception_upper": "2012-05-01",
    "iso:country": "GB",
    "wof:name": "HG4 2AA",
    "wof:placetype": "postalcode"
  },
  "geometry": {"coordinates":[-1.525971,54.135949],"type":"Point"}
}
