{
  "type": "Feature",
  "properties": {
    "iso:country":"GB",
    "wof:name":"TN33 9AY",
    "wof:placetype":"postalcode"
},
  "geometry": {"coordinates":[0.50300646797207,50.87622880275323],"type":"Point"}
}