{
  "type": "Feature",
  "properties": {
    "date:inception_lower":"1980-01-01",
    "date:inception_upper":"1980-01-31",
    "iso:country":"GB",
    "wof:name":"GU15 2AT",
    "wof:placetype":"postalcode"
},
  "geometry": {"coordinates":[-0.720971,51.344122],"type":"Point"}
}