{
  "type": "Feature",
  "properties": {
    "iso:country":"GB",
    "wof:name":"GU15 2AT",
    "wof:placetype":"postalcode"
},
  "geometry": {"coordinates":[-0.72097100417911,51.34412186218904],"type":"Point"}
}