{
  "type": "Feature",
  "properties": {
    "iso:country":"GB",
    "wof:name":"HP23 4BW",
    "wof:placetype":"postalcode"
},
  "geometry": {"coordinates":[-0.67029356311808,51.82111669506774],"type":"Point"}
}