{
  "type": "Feature",
  "properties": {
    "iso:country": "GB",
    "wof:name": "HP23 4BW",
    "wof:placetype": "postalcode"
  },
  "geometry": {"coordinates":[-0.67024,51.821106],"type":"Point"}
}
