{
  "type": "Feature",
  "properties": {
    "iso:country":"GB",
    "wof:name":"UB7 8BX",
    "wof:placetype":"postalcode"
},
  "geometry": {"coordinates":[-0.46181165773106,51.51829772200224],"type":"Point"}
}