{
  "type": "Feature",
  "properties": {
    "date:inception_lower": "2020-02-01",
    "date:inception_upper": "2020-02-01",
    "iso:country": "GB",
    "wof:name": "PR4 3WL",
    "wof:placetype": "postalcode"
  },
  "geometry": {"coordinates":[-2.916374,53.797328],"type":"Point"}
}
