{
  "type": "Feature",
  "properties": {
    "date:inception_lower": "2008-06-01",
    "date:inception_upper": "2008-06-01",
    "iso:country": "GB",
    "wof:name": "SE15 4BE",
    "wof:placetype": "postalcode"
  },
  "geometry": {"coordinates":[-0.066685,51.466813],"type":"Point"}
}
