{
  "type": "Feature",
  "properties": {
    "iso:country":"GB",
    "wof:name":"PR4 0HN",
    "wof:placetype":"postalcode"
},
  "geometry": {"coordinates":[-2.80099309923604,53.81318654817336],"type":"Point"}
}