{
  "type": "Feature",
  "properties": {
    "iso:country": "GB",
    "wof:name": "PR4 0HN",
    "wof:placetype": "postalcode"
  },
  "geometry": {"coordinates":[-2.800993,53.813187],"type":"Point"}
}
