{
  "type": "Feature",
  "properties": {
    "iso:country":"GB",
    "wof:name":"NG13 8SJ",
    "wof:placetype":"postalcode"
},
  "geometry": {"coordinates":[-0.97188434716929,52.95009661361695],"type":"Point"}
}