{
  "type": "Feature",
  "properties": {
    "iso:country": "GB",
    "wof:name": "NG13 8SJ",
    "wof:placetype": "postalcode"
  },
  "geometry": {"coordinates":[-0.971884,52.950097],"type":"Point"}
}
