{
  "type": "Feature",
  "properties": {
    "date:inception_lower": "1980-01-01",
    "date:inception_upper": "1980-01-01",
    "iso:country": "GB",
    "wof:name": "TA4 4HP",
    "wof:placetype": "postalcode"
  },
  "geometry": {"coordinates":[-3.341474,51.14027],"type":"Point"}
}
