{
  "type": "Feature",
  "properties": {
    "iso:country":"GB",
    "wof:name":"TA4 4HP",
    "wof:placetype":"postalcode"
},
  "geometry": {"coordinates":[-3.34147354840973,51.14027025543463],"type":"Point"}
}