{
  "type": "Feature",
  "properties": {
    "iso:country":"GB",
    "wof:name":"SO20 6BW",
    "wof:placetype":"postalcode"
},
  "geometry": {"coordinates":[-1.42198520575639,51.16107980477312],"type":"Point"}
}