{
  "type": "Feature",
  "properties": {
    "iso:country": "GB",
    "wof:name": "SO20 6BW",
    "wof:placetype": "postalcode"
  },
  "geometry": {"coordinates":[-1.421985,51.16108],"type":"Point"}
}
