{
  "type": "Feature",
  "properties": {
    "iso:country": "GB",
    "wof:name": "N4 3EJ",
    "wof:placetype": "postalcode"
  },
  "geometry": {"coordinates":[-0.110031,51.569372],"type":"Point"}
}
