{
  "type": "Feature",
  "properties": {
    "iso:country": "GB",
    "wof:name": "TA6 4WS",
    "wof:placetype": "postalcode"
  },
  "geometry": {"coordinates":[-2.981945,51.14497],"type":"Point"}
}
