{
  "type": "Feature",
  "properties": {
    "iso:country": "GB",
    "wof:name": "LL14 1RL",
    "wof:placetype": "postalcode"
  },
  "geometry": {"coordinates":[-3.053865,53.012884],"type":"Point"}
}
