{
  "type": "Feature",
  "properties": {
    "date:inception_lower": "2018-07-01",
    "date:inception_upper": "2018-07-01",
    "iso:country": "GB",
    "wof:name": "RG7 1ZG",
    "wof:placetype": "postalcode"
  },
  "geometry": {"coordinates":[-0.979071,51.388253],"type":"Point"}
}
