{
  "type": "Feature",
  "properties": {
    "iso:country": "GB",
    "wof:name": "NP11 7JN",
    "wof:placetype": "postalcode"
  },
  "geometry": {"coordinates":[-3.18525,51.625893],"type":"Point"}
}
