{
  "type": "Feature",
  "properties": {
    "iso:country":"GB",
    "wof:name":"CW1 4RB",
    "wof:placetype":"postalcode"
},
  "geometry": {"coordinates":[-2.47781535955824,53.12665739438193],"type":"Point"}
}