{
  "type": "Feature",
  "properties": {
    "iso:country":"GB",
    "wof:name":"NE37 2NT",
    "wof:placetype":"postalcode"
},
  "geometry": {"coordinates":[-1.52224302759102,54.9186932893686],"type":"Point"}
}