{
  "type": "Feature",
  "properties": {
    "date:inception_lower":"1980-01-01",
    "date:inception_upper":"1980-01-31",
    "iso:country":"GB",
    "wof:name":"NE37 2NT",
    "wof:placetype":"postalcode"
},
  "geometry": {"coordinates":[-1.522243,54.918693],"type":"Point"}
}