{
  "type": "Feature",
  "properties": {
    "iso:country": "GB",
    "wof:name": "OX7 6HS",
    "wof:placetype": "postalcode"
  },
  "geometry": {"coordinates":[-1.665314,51.864703],"type":"Point"}
}
