{
  "type": "Feature",
  "properties": {
    "iso:country":"GB",
    "wof:name":"OX7 6HS",
    "wof:placetype":"postalcode"
},
  "geometry": {"coordinates":[-1.66531403364054,51.86470347599057],"type":"Point"}
}