{
  "type": "Feature",
  "properties": {
    "iso:country": "GB",
    "wof:name": "IP9 1QA",
    "wof:placetype": "postalcode"
  },
  "geometry": {"coordinates":[1.267455,51.957325],"type":"Point"}
}
