{
  "type": "Feature",
  "properties": {
    "iso:country":"GB",
    "wof:name":"IP9 1QA",
    "wof:placetype":"postalcode"
},
  "geometry": {"coordinates":[1.26745461360716,51.95732530246259],"type":"Point"}
}