{
  "type": "Feature",
  "properties": {
    "iso:country":"GB",
    "wof:name":"HP10 9EX",
    "wof:placetype":"postalcode"
},
  "geometry": {"coordinates":[-0.71832855786176,51.60568837297248],"type":"Point"}
}