{
  "type": "Feature",
  "properties": {
    "iso:country": "GB",
    "wof:name": "HP10 9EX",
    "wof:placetype": "postalcode"
  },
  "geometry": {"coordinates":[-0.718329,51.605688],"type":"Point"}
}
