{
  "type": "Feature",
  "properties": {
    "date:inception_lower": "1980-01-01",
    "date:inception_upper": "1980-01-01",
    "iso:country": "GB",
    "wof:name": "PR8 4DT",
    "wof:placetype": "postalcode"
  },
  "geometry": {"coordinates":[-3.005251,53.632651],"type":"Point"}
}
