{
  "type": "Feature",
  "properties": {
    "iso:country":"GB",
    "wof:name":"HA4 7JQ",
    "wof:placetype":"postalcode"
},
  "geometry": {"coordinates":[-0.43125003671618,51.57675562897303],"type":"Point"}
}