{
  "type": "Feature",
  "properties": {
    "iso:country":"GB",
    "wof:name":"S75 5LY",
    "wof:placetype":"postalcode"
},
  "geometry": {"coordinates":[-1.54305907404587,53.58172284030176],"type":"Point"}
}