{
  "type": "Feature",
  "properties": {
    "date:inception_lower": "2017-10-01",
    "date:inception_upper": "2017-10-01",
    "iso:country": "GB",
    "wof:name": "SS12 9FZ",
    "wof:placetype": "postalcode"
  },
  "geometry": {"coordinates":[0.524524,51.609722],"type":"Point"}
}
