{
  "type": "Feature",
  "properties": {
    "iso:country":"GB",
    "wof:name":"SO15 1JH",
    "wof:placetype":"postalcode"
},
  "geometry": {"coordinates":[-1.42086651596511,50.90836426830642],"type":"Point"}
}