{
  "type": "Feature",
  "properties": {
    "iso:country": "GB",
    "wof:name": "SO15 1JH",
    "wof:placetype": "postalcode"
  },
  "geometry": {"coordinates":[-1.420866,50.908364],"type":"Point"}
}
