{
  "type": "Feature",
  "properties": {
    "date:inception_lower": "2023-04-01",
    "date:inception_upper": "2023-04-01",
    "iso:country": "GB",
    "wof:name": "DD5 9BP",
    "wof:placetype": "postalcode"
  },
  "geometry": {"coordinates":[-2.88734,56.484479],"type":"Point"}
}
