{
  "type": "Feature",
  "properties": {
    "iso:country":"GB",
    "wof:name":"PO2 0RJ",
    "wof:placetype":"postalcode"
},
  "geometry": {"coordinates":[-1.07041241456762,50.81967198725523],"type":"Point"}
}