{
  "type": "Feature",
  "properties": {
    "iso:country":"GB",
    "wof:name":"SY4 3RE",
    "wof:placetype":"postalcode"
},
  "geometry": {"coordinates":[-2.79500486916208,52.81971577815327],"type":"Point"}
}