{
  "type": "Feature",
  "properties": {
    "iso:country": "GB",
    "wof:name": "SY4 3RE",
    "wof:placetype": "postalcode"
  },
  "geometry": {"coordinates":[-2.795005,52.819716],"type":"Point"}
}
