{
  "type": "Feature",
  "properties": {
    "date:inception_lower":"1980-01-01",
    "date:inception_upper":"1980-01-31",
    "iso:country":"GB",
    "wof:name":"SP2 8HZ",
    "wof:placetype":"postalcode"
},
  "geometry": {"coordinates":[-1.814565,51.059787],"type":"Point"}
}