{
  "type": "Feature",
  "properties": {
    "iso:country":"GB",
    "wof:name":"SP2 8HZ",
    "wof:placetype":"postalcode"
},
  "geometry": {"coordinates":[-1.81456497430704,51.05978733621656],"type":"Point"}
}