{
  "type": "Feature",
  "properties": {
    "date:inception_lower": "1999-06-01",
    "date:inception_upper": "1999-06-01",
    "iso:country": "GB",
    "wof:name": "DE11 9JA",
    "wof:placetype": "postalcode"
  },
  "geometry": {"coordinates":[-1.588127,52.7598],"type":"Point"}
}
