{
  "type": "Feature",
  "properties": {
    "iso:country": "GB",
    "wof:name": "DE11 9JA",
    "wof:placetype": "postalcode"
  },
  "geometry": {"coordinates":[-1.588127,52.7598],"type":"Point"}
}
