{
  "type": "Feature",
  "properties": {
    "iso:country": "GB",
    "wof:name": "NP26 3DJ",
    "wof:placetype": "postalcode"
  },
  "geometry": {"coordinates":[-2.845106,51.58431],"type":"Point"}
}
