{
  "type": "Feature",
  "properties": {
    "date:inception_lower":"2002-06-01",
    "date:inception_upper":"2002-06-30",
    "iso:country":"GB",
    "wof:name":"NP26 3DJ",
    "wof:placetype":"postalcode"
},
  "geometry": {"coordinates":[-2.845106,51.58431],"type":"Point"}
}