{
  "type": "Feature",
  "properties": {
    "iso:country":"GB",
    "wof:name":"NP26 3DJ",
    "wof:placetype":"postalcode"
},
  "geometry": {"coordinates":[-2.84268365949104,51.5855313602504],"type":"Point"}
}