{
  "type": "Feature",
  "properties": {
    "date:inception_lower": "1980-01-01",
    "date:inception_upper": "1980-01-01",
    "iso:country": "GB",
    "wof:name": "PL30 3JB",
    "wof:placetype": "postalcode"
  },
  "geometry": {"coordinates":[-4.734372,50.592925],"type":"Point"}
}
