{
  "type": "Feature",
  "properties": {
    "iso:country":"GB",
    "wof:name":"DN32 0DG",
    "wof:placetype":"postalcode"
},
  "geometry": {"coordinates":[-0.08372586736087,53.55265879690251],"type":"Point"}
}