{
  "type": "Feature",
  "properties": {
    "iso:country": "GB",
    "wof:name": "DN32 0DG",
    "wof:placetype": "postalcode"
  },
  "geometry": {"coordinates":[-0.083726,53.552659],"type":"Point"}
}
