{
  "type": "Feature",
  "properties": {
    "iso:country":"GB",
    "wof:name":"PL31 1QW",
    "wof:placetype":"postalcode"
},
  "geometry": {"coordinates":[-4.73972006463611,50.46594391631282],"type":"Point"}
}