{
  "type": "Feature",
  "properties": {
    "iso:country":"GB",
    "wof:name":"LS8 1HJ",
    "wof:placetype":"postalcode"
},
  "geometry": {"coordinates":[-1.51777768943974,53.83596233195014],"type":"Point"}
}