{
  "type": "Feature",
  "properties": {
    "iso:country":"GB",
    "wof:name":"TD4 6EA",
    "wof:placetype":"postalcode"
},
  "geometry": {"coordinates":[-2.67908909907536,55.63975475036647],"type":"Point"}
}