{
  "type": "Feature",
  "properties": {
    "iso:country":"GB",
    "wof:name":"CW1 4PE",
    "wof:placetype":"postalcode"
},
  "geometry": {"coordinates":[-2.43456494656928,53.12353320176518],"type":"Point"}
}