{
  "type": "Feature",
  "properties": {
    "date:inception_lower":"1980-01-01",
    "date:inception_upper":"1980-01-31",
    "iso:country":"GB",
    "wof:name":"CW1 4PE",
    "wof:placetype":"postalcode"
},
  "geometry": {"coordinates":[-2.434565,53.123533],"type":"Point"}
}