{
  "type": "Feature",
  "properties": {
    "iso:country": "GB",
    "wof:name": "NE27 0AN",
    "wof:placetype": "postalcode"
  },
  "geometry": {"coordinates":[-1.53096,55.043608],"type":"Point"}
}
