{
  "type": "Feature",
  "properties": {
    "date:inception_lower": "1980-01-01",
    "date:inception_upper": "1980-01-01",
    "iso:country": "GB",
    "wof:name": "LD1 5UB",
    "wof:placetype": "postalcode"
  },
  "geometry": {"coordinates":[-3.293829,52.264713],"type":"Point"}
}
