{
  "type": "Feature",
  "properties": {
    "iso:country":"GB",
    "wof:name":"LD1 5UB",
    "wof:placetype":"postalcode"
},
  "geometry": {"coordinates":[-3.29382920113163,52.26471342042074],"type":"Point"}
}