{
  "type": "Feature",
  "properties": {
    "iso:country":"GB",
    "wof:name":"WV14 9AA",
    "wof:placetype":"postalcode"
},
  "geometry": {"coordinates":[-2.09907990614813,52.54580760180879],"type":"Point"}
}