{
  "type": "Feature",
  "properties": {
    "iso:country": "GB",
    "wof:name": "WV14 9AA",
    "wof:placetype": "postalcode"
  },
  "geometry": {"coordinates":[-2.09908,52.545808],"type":"Point"}
}
