{
  "type": "Feature",
  "properties": {
    "date:inception_lower":"1980-01-01",
    "date:inception_upper":"1980-01-31",
    "iso:country":"GB",
    "wof:name":"WV14 9AA",
    "wof:placetype":"postalcode"
},
  "geometry": {"coordinates":[-2.09908,52.545808],"type":"Point"}
}