{
  "type": "Feature",
  "properties": {
    "iso:country":"GB",
    "wof:name":"CR8 4LJ",
    "wof:placetype":"postalcode"
},
  "geometry": {"coordinates":[-0.13019556558163,51.33348361590244],"type":"Point"}
}