{
  "type": "Feature",
  "properties": {
    "iso:country":"GB",
    "wof:name":"KA3 7TL",
    "wof:placetype":"postalcode"
},
  "geometry": {"coordinates":[-4.46860291558056,55.62441935735785],"type":"Point"}
}