{
  "type": "Feature",
  "properties": {
    "iso:country":"GB",
    "wof:name":"TA20 3DS",
    "wof:placetype":"postalcode"
},
  "geometry": {"coordinates":[-3.04482477873536,50.89323343329519],"type":"Point"}
}