{
  "type": "Feature",
  "properties": {
    "date:inception_lower": "1985-04-01",
    "date:inception_upper": "1985-04-01",
    "iso:country": "GB",
    "wof:name": "IP21 4EG",
    "wof:placetype": "postalcode"
  },
  "geometry": {"coordinates":[1.154421,52.363531],"type":"Point"}
}
