{
  "type": "Feature",
  "properties": {
    "iso:country":"GB",
    "wof:name":"LU7 3BX",
    "wof:placetype":"postalcode"
},
  "geometry": {"coordinates":[-0.65424202867538,51.9273482293971],"type":"Point"}
}