{
  "type": "Feature",
  "properties": {
    "iso:country": "GB",
    "wof:name": "LU7 3BX",
    "wof:placetype": "postalcode"
  },
  "geometry": {"coordinates":[-0.654242,51.927348],"type":"Point"}
}
