{
  "type": "Feature",
  "properties": {
    "date:inception_lower":"2010-12-01",
    "date:inception_upper":"2010-12-31",
    "iso:country":"GB",
    "wof:name":"LU7 3BX",
    "wof:placetype":"postalcode"
},
  "geometry": {"coordinates":[-0.654242,51.927348],"type":"Point"}
}