{
  "type": "Feature",
  "properties": {
    "date:inception_lower": "2003-03-01",
    "date:inception_upper": "2003-03-01",
    "iso:country": "GB",
    "wof:name": "NN29 7SW",
    "wof:placetype": "postalcode"
  },
  "geometry": {"coordinates":[-0.671642,52.257449],"type":"Point"}
}
