{
  "type": "Feature",
  "properties": {
    "date:inception_lower": "1980-01-01",
    "date:inception_upper": "1980-01-01",
    "iso:country": "GB",
    "wof:name": "TS18 3QD",
    "wof:placetype": "postalcode"
  },
  "geometry": {"coordinates":[-1.329367,54.553783],"type":"Point"}
}
