{
  "type": "Feature",
  "properties": {
    "iso:country":"GB",
    "wof:name":"TS18 3QD",
    "wof:placetype":"postalcode"
},
  "geometry": {"coordinates":[-1.32936726655605,54.55378311466522],"type":"Point"}
}