{
  "type": "Feature",
  "properties": {
    "iso:country":"GB",
    "wof:name":"OX7 3RA",
    "wof:placetype":"postalcode"
},
  "geometry": {"coordinates":[-1.52516649146972,51.89700267034228],"type":"Point"}
}