{
  "type": "Feature",
  "properties": {
    "date:inception_lower": "1996-12-01",
    "date:inception_upper": "1996-12-01",
    "iso:country": "GB",
    "wof:name": "OX7 3RA",
    "wof:placetype": "postalcode"
  },
  "geometry": {"coordinates":[-1.525166,51.897003],"type":"Point"}
}
