{
  "type": "Feature",
  "properties": {
    "iso:country":"GB",
    "wof:name":"NW2 5AB",
    "wof:placetype":"postalcode"
},
  "geometry": {"coordinates":[-0.22410729852116,51.54831958872953],"type":"Point"}
}