{
  "type": "Feature",
  "properties": {
    "iso:country": "GB",
    "wof:name": "NW2 5AB",
    "wof:placetype": "postalcode"
  },
  "geometry": {"coordinates":[-0.224166,51.548293],"type":"Point"}
}
