{
  "type": "Feature",
  "properties": {
    "date:inception_lower": "1991-09-01",
    "date:inception_upper": "1991-09-01",
    "iso:country": "GB",
    "wof:name": "PE1 4RS",
    "wof:placetype": "postalcode"
  },
  "geometry": {"coordinates":[-0.215913,52.591226],"type":"Point"}
}
