{
  "type": "Feature",
  "properties": {
    "iso:country": "GB",
    "wof:name": "KY5 8JS",
    "wof:placetype": "postalcode"
  },
  "geometry": {"coordinates":[-3.326959,56.163455],"type":"Point"}
}
