{
  "type": "Feature",
  "properties": {
    "iso:country":"GB",
    "wof:name":"DN14 7JS",
    "wof:placetype":"postalcode"
},
  "geometry": {"coordinates":[-0.90898438589941,53.75688255484826],"type":"Point"}
}