{
  "type": "Feature",
  "properties": {
    "date:inception_lower": "1980-01-01",
    "date:inception_upper": "1980-01-01",
    "iso:country": "GB",
    "wof:name": "B79 0BN",
    "wof:placetype": "postalcode"
  },
  "geometry": {"coordinates":[-1.621751,52.694602],"type":"Point"}
}
