{
  "type": "Feature",
  "properties": {
    "iso:country": "GB",
    "wof:name": "B79 0BN",
    "wof:placetype": "postalcode"
  },
  "geometry": {"coordinates":[-1.621751,52.694602],"type":"Point"}
}
