{
  "type": "Feature",
  "properties": {
    "iso:country": "GB",
    "wof:name": "TN34 3EN",
    "wof:placetype": "postalcode"
  },
  "geometry": {"coordinates":[0.591095,50.856875],"type":"Point"}
}
