{
  "type": "Feature",
  "properties": {
    "date:inception_lower": "1980-01-01",
    "date:inception_upper": "1980-01-01",
    "iso:country": "GB",
    "wof:name": "TN34 3EN",
    "wof:placetype": "postalcode"
  },
  "geometry": {"coordinates":[0.591095,50.856875],"type":"Point"}
}
