{
  "type": "Feature",
  "properties": {
    "iso:country":"GB",
    "wof:name":"TN34 3EN",
    "wof:placetype":"postalcode"
},
  "geometry": {"coordinates":[0.59109455542564,50.85687471312044],"type":"Point"}
}