{
  "type": "Feature",
  "properties": {
    "iso:country":"GB",
    "wof:name":"WR5 3NA",
    "wof:placetype":"postalcode"
},
  "geometry": {"coordinates":[-2.21710684444405,52.13851120388643],"type":"Point"}
}