{
  "type": "Feature",
  "properties": {
    "iso:country":"GB",
    "wof:name":"WC1N 1JN",
    "wof:placetype":"postalcode"
},
  "geometry": {"coordinates":[-0.1260474889481,51.52508642773033],"type":"Point"}
}