{
  "type": "Feature",
  "properties": {
    "date:inception_lower": "1980-01-01",
    "date:inception_upper": "1980-01-01",
    "iso:country": "GB",
    "wof:name": "OX3 9JQ",
    "wof:placetype": "postalcode"
  },
  "geometry": {"coordinates":[-1.204886,51.7628],"type":"Point"}
}
