{
  "type": "Feature",
  "properties": {
    "iso:country":"GB",
    "wof:name":"TA22 9DF",
    "wof:placetype":"postalcode"
},
  "geometry": {"coordinates":[-3.55131739656516,51.0428453020077],"type":"Point"}
}