{
  "type": "Feature",
  "properties": {
    "iso:country":"GB",
    "wof:name":"CR8 5DL",
    "wof:placetype":"postalcode"
},
  "geometry": {"coordinates":[-0.09432266402209,51.32063020495345],"type":"Point"}
}