{
  "type": "Feature",
  "properties": {
    "iso:country":"GB",
    "wof:name":"NE5 3UY",
    "wof:placetype":"postalcode"
},
  "geometry": {"coordinates":[-1.65983606025805,54.99898995019022],"type":"Point"}
}