{
  "type": "Feature",
  "properties": {
    "iso:country":"GB",
    "wof:name":"SR2 0RW",
    "wof:placetype":"postalcode"
},
  "geometry": {"coordinates":[-1.36877422547709,54.87096716498005],"type":"Point"}
}