{
  "type": "Feature",
  "properties": {
    "iso:country":"GB",
    "wof:name":"M34 7SD",
    "wof:placetype":"postalcode"
},
  "geometry": {"coordinates":[-2.09177590725054,53.44751746285281],"type":"Point"}
}