{
  "type": "Feature",
  "properties": {
    "iso:country":"GB",
    "wof:name":"B32 4BT",
    "wof:placetype":"postalcode"
},
  "geometry": {"coordinates":[-1.99930881710742,52.43209951909108],"type":"Point"}
}