{
  "type": "Feature",
  "properties": {
    "iso:country": "GB",
    "wof:name": "B32 4BT",
    "wof:placetype": "postalcode"
  },
  "geometry": {"coordinates":[-1.999309,52.4321],"type":"Point"}
}
