{
  "type": "Feature",
  "properties": {
    "date:inception_lower": "2021-02-01",
    "date:inception_upper": "2021-02-01",
    "iso:country": "GB",
    "wof:name": "E15 1GW",
    "wof:placetype": "postalcode"
  },
  "geometry": {"coordinates":[-0.003012,51.546421],"type":"Point"}
}
