{
  "type": "Feature",
  "properties": {
    "iso:country":"GB",
    "wof:name":"SK14 1AG",
    "wof:placetype":"postalcode"
},
  "geometry": {"coordinates":[-2.0796158755894,53.45052836565932],"type":"Point"}
}