{
  "type": "Feature",
  "properties": {
    "date:inception_lower": "2022-02-01",
    "date:inception_upper": "2022-02-01",
    "iso:country": "GB",
    "wof:name": "SN12 6WT",
    "wof:placetype": "postalcode"
  },
  "geometry": {"coordinates":[-2.119217,51.368419],"type":"Point"}
}
