{
  "type": "Feature",
  "properties": {
    "iso:country": "GB",
    "wof:name": "DL1 5LP",
    "wof:placetype": "postalcode"
  },
  "geometry": {"coordinates":[-1.548931,54.522593],"type":"Point"}
}
