{
  "type": "Feature",
  "properties": {
    "date:inception_lower": "1981-06-01",
    "date:inception_upper": "1981-06-01",
    "iso:country": "GB",
    "wof:name": "DL1 5LP",
    "wof:placetype": "postalcode"
  },
  "geometry": {"coordinates":[-1.548931,54.522593],"type":"Point"}
}
