{
  "type": "Feature",
  "properties": {
    "date:inception_lower":"1980-01-01",
    "date:inception_upper":"1980-01-31",
    "iso:country":"GB",
    "wof:name":"WS15 3LE",
    "wof:placetype":"postalcode"
},
  "geometry": {"coordinates":[-1.920573,52.785937],"type":"Point"}
}