{
  "type": "Feature",
  "properties": {
    "iso:country": "GB",
    "wof:name": "WS15 3LE",
    "wof:placetype": "postalcode"
  },
  "geometry": {"coordinates":[-1.920573,52.785937],"type":"Point"}
}
