{
  "type": "Feature",
  "properties": {
    "date:inception_lower": "1992-01-01",
    "date:inception_upper": "1992-01-01",
    "iso:country": "GB",
    "wof:name": "TQ14 8FA",
    "wof:placetype": "postalcode"
  },
  "geometry": {"coordinates":[-3.491245,50.556954],"type":"Point"}
}
