{
  "type": "Feature",
  "properties": {
    "iso:country": "GB",
    "wof:name": "PL9 8DN",
    "wof:placetype": "postalcode"
  },
  "geometry": {"coordinates":[-4.061531,50.360956],"type":"Point"}
}
