{
  "type": "Feature",
  "properties": {
    "iso:country":"GB",
    "wof:name":"TS26 0EA",
    "wof:placetype":"postalcode"
},
  "geometry": {"coordinates":[-1.24272212527875,54.68636019293604],"type":"Point"}
}