{
  "type": "Feature",
  "properties": {
    "iso:country":"GB",
    "wof:name":"LL14 5BS",
    "wof:placetype":"postalcode"
},
  "geometry": {"coordinates":[-3.05984208891347,52.93071023007279],"type":"Point"}
}