{
  "type": "Feature",
  "properties": {
    "iso:country": "GB",
    "wof:name": "LL14 5BS",
    "wof:placetype": "postalcode"
  },
  "geometry": {"coordinates":[-3.059842,52.93071],"type":"Point"}
}
