{
  "type": "Feature",
  "properties": {
    "iso:country":"GB",
    "wof:name":"PE19 1HS",
    "wof:placetype":"postalcode"
},
  "geometry": {"coordinates":[-0.26699262911664,52.23080305131396],"type":"Point"}
}