{
  "type": "Feature",
  "properties": {
    "date:inception_lower": "2000-06-01",
    "date:inception_upper": "2000-06-01",
    "iso:country": "GB",
    "wof:name": "GU2 9QN",
    "wof:placetype": "postalcode"
  },
  "geometry": {"coordinates":[-0.58464,51.26111],"type":"Point"}
}
