{
  "type": "Feature",
  "properties": {
    "iso:country":"GB",
    "wof:name":"GU2 9QN",
    "wof:placetype":"postalcode"
},
  "geometry": {"coordinates":[-0.58464051302563,51.26111028841565],"type":"Point"}
}