{
  "type": "Feature",
  "properties": {
    "iso:country":"GB",
    "wof:name":"PE9 2SQ",
    "wof:placetype":"postalcode"
},
  "geometry": {"coordinates":[-0.50410882327488,52.65294557972581],"type":"Point"}
}