{
  "type": "Feature",
  "properties": {
    "iso:country": "GB",
    "wof:name": "BS37 8RJ",
    "wof:placetype": "postalcode"
  },
  "geometry": {"coordinates":[-2.41567,51.515924],"type":"Point"}
}
