{
  "type": "Feature",
  "properties": {
    "iso:country":"GB",
    "wof:name":"BS37 8RJ",
    "wof:placetype":"postalcode"
},
  "geometry": {"coordinates":[-2.41567158017916,51.51592567776019],"type":"Point"}
}