{
  "type": "Feature",
  "properties": {
    "iso:country":"GB",
    "wof:name":"N21 3AX",
    "wof:placetype":"postalcode"
},
  "geometry": {"coordinates":[-0.09047197363265,51.62487775055646],"type":"Point"}
}