{
  "type": "Feature",
  "properties": {
    "iso:country": "GB",
    "wof:name": "NP4 7NZ",
    "wof:placetype": "postalcode"
  },
  "geometry": {"coordinates":[-3.066461,51.73168],"type":"Point"}
}
