{
  "type": "Feature",
  "properties": {
    "iso:country":"GB",
    "wof:name":"DN12 4LY",
    "wof:placetype":"postalcode"
},
  "geometry": {"coordinates":[-1.25391262184863,53.49085143434739],"type":"Point"}
}