{
  "type": "Feature",
  "properties": {
    "iso:country":"GB",
    "wof:name":"HR5 3DJ",
    "wof:placetype":"postalcode"
},
  "geometry": {"coordinates":[-3.02848942198843,52.20348069440904],"type":"Point"}
}