{
  "type": "Feature",
  "properties": {
    "iso:country":"GB",
    "wof:name":"GL9 1JE",
    "wof:placetype":"postalcode"
},
  "geometry": {"coordinates":[-2.33622754809063,51.5029359914104],"type":"Point"}
}