{
  "type": "Feature",
  "properties": {
    "iso:country": "GB",
    "wof:name": "GL9 1JE",
    "wof:placetype": "postalcode"
  },
  "geometry": {"coordinates":[-2.336228,51.502936],"type":"Point"}
}
