{
  "type": "Feature",
  "properties": {
    "date:inception_lower": "2022-08-01",
    "date:inception_upper": "2022-08-01",
    "iso:country": "GB",
    "wof:name": "TF4 3XH",
    "wof:placetype": "postalcode"
  },
  "geometry": {"coordinates":[-2.478419,52.659203],"type":"Point"}
}
