{
  "type": "Feature",
  "properties": {
    "iso:country": "GB",
    "wof:name": "TA10 0QR",
    "wof:placetype": "postalcode"
  },
  "geometry": {"coordinates":[-2.863228,51.055128],"type":"Point"}
}
