{
  "type": "Feature",
  "properties": {
    "date:inception_lower":"1980-01-01",
    "date:inception_upper":"1980-01-31",
    "iso:country":"GB",
    "wof:name":"TA10 0QR",
    "wof:placetype":"postalcode"
},
  "geometry": {"coordinates":[-2.863228,51.055128],"type":"Point"}
}