{
  "type": "Feature",
  "properties": {
    "iso:country":"GB",
    "wof:name":"TA10 0QR",
    "wof:placetype":"postalcode"
},
  "geometry": {"coordinates":[-2.86331135956145,51.05607847622268],"type":"Point"}
}