{
  "type": "Feature",
  "properties": {
    "iso:country":"GB",
    "wof:name":"CH62 9DN",
    "wof:placetype":"postalcode"
},
  "geometry": {"coordinates":[-2.96824475558157,53.30904438545073],"type":"Point"}
}