{
  "type": "Feature",
  "properties": {
    "iso:country":"GB",
    "wof:name":"CF23 5HU",
    "wof:placetype":"postalcode"
},
  "geometry": {"coordinates":[-3.16245751642853,51.49822207671848],"type":"Point"}
}