{
  "type": "Feature",
  "properties": {
    "date:inception_lower":"2005-11-01",
    "date:inception_upper":"2005-11-30",
    "iso:country":"GB",
    "wof:name":"CF23 5HU",
    "wof:placetype":"postalcode"
},
  "geometry": {"coordinates":[-3.162457,51.498222],"type":"Point"}
}