{
  "type": "Feature",
  "properties": {
    "date:inception_lower": "1980-01-01",
    "date:inception_upper": "1980-01-01",
    "iso:country": "GB",
    "wof:name": "SA11 5HE",
    "wof:placetype": "postalcode"
  },
  "geometry": {"coordinates":[-3.634486,51.742173],"type":"Point"}
}
