{
  "type": "Feature",
  "properties": {
    "date:inception_lower": "1980-01-01",
    "date:inception_upper": "1980-01-01",
    "iso:country": "GB",
    "wof:name": "TF3 1XJ",
    "wof:placetype": "postalcode"
  },
  "geometry": {"coordinates":[-2.431127,52.654847],"type":"Point"}
}
