{
  "type": "Feature",
  "properties": {
    "iso:country": "GB",
    "wof:name": "M3 7AB",
    "wof:placetype": "postalcode"
  },
  "geometry": {"coordinates":[-2.252112,53.487896],"type":"Point"}
}
