{
  "type": "Feature",
  "properties": {
    "iso:country":"GB",
    "wof:name":"M3 7AB",
    "wof:placetype":"postalcode"
},
  "geometry": {"coordinates":[-2.25211161012283,53.48789631250168],"type":"Point"}
}