{
  "type": "Feature",
  "properties": {
    "iso:country":"GB",
    "wof:name":"BD9 4LT",
    "wof:placetype":"postalcode"
},
  "geometry": {"coordinates":[-1.77170611772182,53.82013988004358],"type":"Point"}
}