{
  "type": "Feature",
  "properties": {
    "date:inception_lower":"1980-01-01",
    "date:inception_upper":"1980-01-31",
    "iso:country":"GB",
    "wof:name":"BD9 4LT",
    "wof:placetype":"postalcode"
},
  "geometry": {"coordinates":[-1.771706,53.82014],"type":"Point"}
}