{
  "type": "Feature",
  "properties": {
    "iso:country":"GB",
    "wof:name":"TR1 3NX",
    "wof:placetype":"postalcode"
},
  "geometry": {"coordinates":[-5.07605910899108,50.26349683510602],"type":"Point"}
}