{
  "type": "Feature",
  "properties": {
    "date:inception_lower": "2000-12-01",
    "date:inception_upper": "2000-12-01",
    "iso:country": "GB",
    "wof:name": "PA72 6JD",
    "wof:placetype": "postalcode"
  },
  "geometry": {"coordinates":[-5.945002,56.517311],"type":"Point"}
}
