{
  "type": "Feature",
  "properties": {
    "iso:country": "GB",
    "wof:name": "PA72 6JD",
    "wof:placetype": "postalcode"
  },
  "geometry": {"coordinates":[-5.945002,56.517311],"type":"Point"}
}
