{
  "type": "Feature",
  "properties": {
    "iso:country":"GB",
    "wof:name":"B90 1QS",
    "wof:placetype":"postalcode"
},
  "geometry": {"coordinates":[-1.85939522945595,52.37960409414321],"type":"Point"}
}