{
  "type": "Feature",
  "properties": {
    "date:inception_lower": "2004-06-01",
    "date:inception_upper": "2004-06-01",
    "iso:country": "GB",
    "wof:name": "SK4 1LW",
    "wof:placetype": "postalcode"
  },
  "geometry": {"coordinates":[-2.165957,53.412533],"type":"Point"}
}
