{
  "type": "Feature",
  "properties": {
    "iso:country":"GB",
    "wof:name":"SK4 1LW",
    "wof:placetype":"postalcode"
},
  "geometry": {"coordinates":[-2.16595839195745,53.41251687606542],"type":"Point"}
}