{
  "type": "Feature",
  "properties": {
    "iso:country":"GB",
    "wof:name":"CH4 8NY",
    "wof:placetype":"postalcode"
},
  "geometry": {"coordinates":[-2.9175051189313,53.17473455564756],"type":"Point"}
}