{
  "type": "Feature",
  "properties": {
    "date:inception_lower": "1980-01-01",
    "date:inception_upper": "1980-01-01",
    "iso:country": "GB",
    "wof:name": "CH4 8NY",
    "wof:placetype": "postalcode"
  },
  "geometry": {"coordinates":[-2.917505,53.174735],"type":"Point"}
}
