{
  "type": "Feature",
  "properties": {
    "iso:country":"GB",
    "wof:name":"SY2 5HG",
    "wof:placetype":"postalcode"
},
  "geometry": {"coordinates":[-2.73646459656142,52.70905251678119],"type":"Point"}
}