{
  "type": "Feature",
  "properties": {
    "iso:country": "GB",
    "wof:name": "AB51 5AB",
    "wof:placetype": "postalcode"
  },
  "geometry": {"coordinates":[-2.483368,57.363935],"type":"Point"}
}
