{
  "type": "Feature",
  "properties": {
    "iso:country":"GB",
    "wof:name":"AB51 5AB",
    "wof:placetype":"postalcode"
},
  "geometry": {"coordinates":[-2.48336777475075,57.36393479421282],"type":"Point"}
}