{
  "type": "Feature",
  "properties": {
    "iso:country":"GB",
    "wof:name":"CH61 8RN",
    "wof:placetype":"postalcode"
},
  "geometry": {"coordinates":[-3.09802355340763,53.34940495657843],"type":"Point"}
}