{
  "type": "Feature",
  "properties": {
    "iso:country":"GB",
    "wof:name":"PL7 4QS",
    "wof:placetype":"postalcode"
},
  "geometry": {"coordinates":[-4.07713756117756,50.39604411082788],"type":"Point"}
}