{
  "type": "Feature",
  "properties": {
    "iso:country": "GB",
    "wof:name": "PL7 4QS",
    "wof:placetype": "postalcode"
  },
  "geometry": {"coordinates":[-4.077138,50.396044],"type":"Point"}
}
