{
  "type": "Feature",
  "properties": {
    "iso:country":"GB",
    "wof:name":"PH1 1NX",
    "wof:placetype":"postalcode"
},
  "geometry": {"coordinates":[-3.45296532519942,56.39634066142264],"type":"Point"}
}