{
  "type": "Feature",
  "properties": {
    "iso:country":"GB",
    "wof:name":"SS5 5NU",
    "wof:placetype":"postalcode"
},
  "geometry": {"coordinates":[0.66139167115619,51.61331223885579],"type":"Point"}
}