{
  "type": "Feature",
  "properties": {
    "iso:country":"GB",
    "wof:name":"BD20 0PX",
    "wof:placetype":"postalcode"
},
  "geometry": {"coordinates":[-1.94118321639139,53.91490349868886],"type":"Point"}
}