{
  "type": "Feature",
  "properties": {
    "iso:country":"GB",
    "wof:name":"SY2 5UP",
    "wof:placetype":"postalcode"
},
  "geometry": {"coordinates":[-2.71468803333844,52.71516403339878],"type":"Point"}
}