{
  "type": "Feature",
  "properties": {
    "iso:country":"GB",
    "wof:name":"BS9 1DT",
    "wof:placetype":"postalcode"
},
  "geometry": {"coordinates":[-2.64762711418476,51.48074184625486],"type":"Point"}
}