{
  "type": "Feature",
  "properties": {
    "iso:country": "GB",
    "wof:name": "TS18 2TA",
    "wof:placetype": "postalcode"
  },
  "geometry": {"coordinates":[-1.285265,54.572632],"type":"Point"}
}
