{
  "type": "Feature",
  "properties": {
    "iso:country":"GB",
    "wof:name":"TS18 2TA",
    "wof:placetype":"postalcode"
},
  "geometry": {"coordinates":[-1.28523561482417,54.57261901188199],"type":"Point"}
}