{
  "type": "Feature",
  "properties": {
    "date:inception_lower":"2001-12-01",
    "date:inception_upper":"2001-12-31",
    "iso:country":"GB",
    "wof:name":"TS18 2TA",
    "wof:placetype":"postalcode"
},
  "geometry": {"coordinates":[-1.285265,54.572632],"type":"Point"}
}