{
  "type": "Feature",
  "properties": {
    "iso:country":"GB",
    "wof:name":"DT1 2AS",
    "wof:placetype":"postalcode"
},
  "geometry": {"coordinates":[-2.43394075828747,50.70906871253984],"type":"Point"}
}