{
  "type": "Feature",
  "properties": {
    "date:inception_lower":"1980-01-01",
    "date:inception_upper":"1980-01-31",
    "iso:country":"GB",
    "wof:name":"PL30 3PT",
    "wof:placetype":"postalcode"
},
  "geometry": {"coordinates":[-4.736086,50.532799],"type":"Point"}
}