{
  "type": "Feature",
  "properties": {
    "iso:country":"GB",
    "wof:name":"PL30 3PT",
    "wof:placetype":"postalcode"
},
  "geometry": {"coordinates":[-4.73608560827627,50.53279911349111],"type":"Point"}
}