{
  "type": "Feature",
  "properties": {
    "iso:country":"GB",
    "wof:name":"W10 5RU",
    "wof:placetype":"postalcode"
},
  "geometry": {"coordinates":[-0.21004838711151,51.52139852211463],"type":"Point"}
}