{
  "type": "Feature",
  "properties": {
    "iso:country": "GB",
    "wof:name": "W10 5RU",
    "wof:placetype": "postalcode"
  },
  "geometry": {"coordinates":[-0.210081,51.521419],"type":"Point"}
}
