{
  "type": "Feature",
  "properties": {
    "date:inception_lower": "2008-09-01",
    "date:inception_upper": "2008-09-01",
    "iso:country": "GB",
    "wof:name": "BS35 2FH",
    "wof:placetype": "postalcode"
  },
  "geometry": {"coordinates":[-2.52216,51.606835],"type":"Point"}
}
