{
  "type": "Feature",
  "properties": {
    "iso:country":"GB",
    "wof:name":"BS35 2FH",
    "wof:placetype":"postalcode"
},
  "geometry": {"coordinates":[-2.52215961459058,51.60683497821778],"type":"Point"}
}