{
  "type": "Feature",
  "properties": {
    "iso:country": "GB",
    "wof:name": "GU10 1AZ",
    "wof:placetype": "postalcode"
  },
  "geometry": {"coordinates":[-0.733472,51.233752],"type":"Point"}
}
