{
  "type": "Feature",
  "properties": {
    "iso:country":"GB",
    "wof:name":"WR3 7UQ",
    "wof:placetype":"postalcode"
},
  "geometry": {"coordinates":[-2.19507780951651,52.22972163594729],"type":"Point"}
}