{
  "type": "Feature",
  "properties": {
    "iso:country":"GB",
    "wof:name":"BH23 7HQ",
    "wof:placetype":"postalcode"
},
  "geometry": {"coordinates":[-1.76999396744982,50.75232111447377],"type":"Point"}
}