{
  "type": "Feature",
  "properties": {
    "date:inception_lower":"1980-01-01",
    "date:inception_upper":"1980-01-31",
    "iso:country":"GB",
    "wof:name":"GU12 4JR",
    "wof:placetype":"postalcode"
},
  "geometry": {"coordinates":[-0.752948,51.241856],"type":"Point"}
}