{
  "type": "Feature",
  "properties": {
    "iso:country": "GB",
    "wof:name": "TA10 9PD",
    "wof:placetype": "postalcode"
  },
  "geometry": {"coordinates":[-2.828967,51.037409],"type":"Point"}
}
