{
  "type": "Feature",
  "properties": {
    "iso:country":"GB",
    "wof:name":"NE4 6RG",
    "wof:placetype":"postalcode"
},
  "geometry": {"coordinates":[-1.63403035761318,54.96775982469686],"type":"Point"}
}