{
  "type": "Feature",
  "properties": {
    "iso:country": "GB",
    "wof:name": "NE4 6RG",
    "wof:placetype": "postalcode"
  },
  "geometry": {"coordinates":[-1.63403,54.96776],"type":"Point"}
}
