{
  "type": "Feature",
  "properties": {
    "iso:country":"GB",
    "wof:name":"BS35 4EQ",
    "wof:placetype":"postalcode"
},
  "geometry": {"coordinates":[-2.5729422873664,51.58020819086921],"type":"Point"}
}