{
  "type": "Feature",
  "properties": {
    "iso:country":"GB",
    "wof:name":"WC1E 6JF",
    "wof:placetype":"postalcode"
},
  "geometry": {"coordinates":[-0.13566492357444,51.52327032290187],"type":"Point"}
}