{
  "type": "Feature",
  "properties": {
    "iso:country":"GB",
    "wof:name":"B1 2SG",
    "wof:placetype":"postalcode"
},
  "geometry": {"coordinates":[-1.90797133523533,52.47456864582083],"type":"Point"}
}