{
  "type": "Feature",
  "properties": {
    "iso:country": "GB",
    "wof:name": "B1 2SG",
    "wof:placetype": "postalcode"
  },
  "geometry": {"coordinates":[-1.907971,52.474569],"type":"Point"}
}
