{
  "type": "Feature",
  "properties": {
    "date:inception_lower": "2000-12-01",
    "date:inception_upper": "2000-12-01",
    "iso:country": "GB",
    "wof:name": "OX25 5QL",
    "wof:placetype": "postalcode"
  },
  "geometry": {"coordinates":[-1.309962,51.934833],"type":"Point"}
}
