{
  "type": "Feature",
  "properties": {
    "date:inception_lower":"2001-06-01",
    "date:inception_upper":"2001-06-30",
    "iso:country":"GB",
    "wof:name":"HP18 0BL",
    "wof:placetype":"postalcode"
},
  "geometry": {"coordinates":[-0.960201,51.791407],"type":"Point"}
}