{
  "type": "Feature",
  "properties": {
    "iso:country": "GB",
    "wof:name": "HP18 0BL",
    "wof:placetype": "postalcode"
  },
  "geometry": {"coordinates":[-0.960201,51.791407],"type":"Point"}
}
