{
  "type": "Feature",
  "properties": {
    "iso:country":"GB",
    "wof:name":"SY25 6BW",
    "wof:placetype":"postalcode"
},
  "geometry": {"coordinates":[-3.84851802520832,52.2954170742211],"type":"Point"}
}