{
  "type": "Feature",
  "properties": {
    "iso:country":"GB",
    "wof:name":"CW6 9QY",
    "wof:placetype":"postalcode"
},
  "geometry": {"coordinates":[-2.65215519248058,53.11375734192695],"type":"Point"}
}