{
  "type": "Feature",
  "properties": {
    "iso:country": "GB",
    "wof:name": "FY3 9JG",
    "wof:placetype": "postalcode"
  },
  "geometry": {"coordinates":[-3.029486,53.808494],"type":"Point"}
}
