{
  "type": "Feature",
  "properties": {
    "date:inception_lower":"2002-08-01",
    "date:inception_upper":"2002-08-31",
    "iso:country":"GB",
    "wof:name":"M26 3ST",
    "wof:placetype":"postalcode"
},
  "geometry": {"coordinates":[-2.336827,53.5623],"type":"Point"}
}