{
  "type": "Feature",
  "properties": {
    "iso:country":"GB",
    "wof:name":"M26 3ST",
    "wof:placetype":"postalcode"
},
  "geometry": {"coordinates":[-2.33682748353919,53.56230023332287],"type":"Point"}
}