{
  "type": "Feature",
  "properties": {
    "iso:country": "GB",
    "wof:name": "M26 3ST",
    "wof:placetype": "postalcode"
  },
  "geometry": {"coordinates":[-2.336827,53.5623],"type":"Point"}
}
