{
  "type": "Feature",
  "properties": {
    "iso:country": "GB",
    "wof:name": "TS28 5AR",
    "wof:placetype": "postalcode"
  },
  "geometry": {"coordinates":[-1.381939,54.728309],"type":"Point"}
}
