{
  "type": "Feature",
  "properties": {
    "iso:country":"GB",
    "wof:name":"DE22 4NN",
    "wof:placetype":"postalcode"
},
  "geometry": {"coordinates":[-1.52659988172566,52.92381762374777],"type":"Point"}
}