{
  "type": "Feature",
  "properties": {
    "iso:country": "GB",
    "wof:name": "OX10 9RF",
    "wof:placetype": "postalcode"
  },
  "geometry": {"coordinates":[-1.13881,51.599679],"type":"Point"}
}
