{
  "type": "Feature",
  "properties": {
    "iso:country":"GB",
    "wof:name":"RM11 1LY",
    "wof:placetype":"postalcode"
},
  "geometry": {"coordinates":[0.1996775748546,51.56649866766536],"type":"Point"}
}