{
  "type": "Feature",
  "properties": {
    "iso:country": "GB",
    "wof:name": "AB32 6FY",
    "wof:placetype": "postalcode"
  },
  "geometry": {"coordinates":[-2.27838,57.155245],"type":"Point"}
}
