{
  "type": "Feature",
  "properties": {
    "iso:country":"GB",
    "wof:name":"B69 1UQ",
    "wof:placetype":"postalcode"
},
  "geometry": {"coordinates":[-2.06033456225637,52.50837291430303],"type":"Point"}
}