{
  "type": "Feature",
  "properties": {
    "date:inception_lower": "1980-01-01",
    "date:inception_upper": "1980-01-01",
    "iso:country": "GB",
    "wof:name": "B69 1UQ",
    "wof:placetype": "postalcode"
  },
  "geometry": {"coordinates":[-2.060335,52.508373],"type":"Point"}
}
