{
  "type": "Feature",
  "properties": {
    "iso:country":"GB",
    "wof:name":"LU2 9JQ",
    "wof:placetype":"postalcode"
},
  "geometry": {"coordinates":[-0.38090738602632,51.88691427182678],"type":"Point"}
}