{
  "type": "Feature",
  "properties": {
    "iso:country":"GB",
    "wof:name":"PE9 2SX",
    "wof:placetype":"postalcode"
},
  "geometry": {"coordinates":[-0.50101001340566,52.654075188498],"type":"Point"}
}