{
  "type": "Feature",
  "properties": {
    "date:inception_lower": "2023-07-01",
    "date:inception_upper": "2023-07-01",
    "iso:country": "GB",
    "wof:name": "PA7 5RZ",
    "wof:placetype": "postalcode"
  },
  "geometry": {"coordinates":[-4.506636,55.895165],"type":"Point"}
}
