{
  "type": "Feature",
  "properties": {
    "iso:country": "GB",
    "wof:name": "DD10 8RX",
    "wof:placetype": "postalcode"
  },
  "geometry": {"coordinates":[-2.459247,56.717867],"type":"Point"}
}
