{
  "type": "Feature",
  "properties": {
    "iso:country":"GB",
    "wof:name":"SA19 7NS",
    "wof:placetype":"postalcode"
},
  "geometry": {"coordinates":[-4.00928655700031,51.93753927092779],"type":"Point"}
}