{
  "type": "Feature",
  "properties": {
    "iso:country": "GB",
    "wof:name": "SA19 7NS",
    "wof:placetype": "postalcode"
  },
  "geometry": {"coordinates":[-4.009287,51.937539],"type":"Point"}
}
