{
  "type": "Feature",
  "properties": {
    "iso:country": "GB",
    "wof:name": "PA4 8FL",
    "wof:placetype": "postalcode"
  },
  "geometry": {"coordinates":[-4.373239,55.872978],"type":"Point"}
}
