{
  "type": "Feature",
  "properties": {
    "iso:country":"GB",
    "wof:name":"SM5 3PD",
    "wof:placetype":"postalcode"
},
  "geometry": {"coordinates":[-0.16385010963152,51.3646092656947],"type":"Point"}
}