{
  "type": "Feature",
  "properties": {
    "iso:country": "GB",
    "wof:name": "HP23 6JE",
    "wof:placetype": "postalcode"
  },
  "geometry": {"coordinates":[-0.630795,51.762531],"type":"Point"}
}
