{
  "type": "Feature",
  "properties": {
    "iso:country":"GB",
    "wof:name":"HP23 6JE",
    "wof:placetype":"postalcode"
},
  "geometry": {"coordinates":[-0.63090373621058,51.76259693671029],"type":"Point"}
}