{
  "type": "Feature",
  "properties": {
    "iso:country":"GB",
    "wof:name":"GL18 1AJ",
    "wof:placetype":"postalcode"
},
  "geometry": {"coordinates":[-2.40655218252692,51.93081032981713],"type":"Point"}
}