{
  "type": "Feature",
  "properties": {
    "iso:country": "GB",
    "wof:name": "SL3 9DY",
    "wof:placetype": "postalcode"
  },
  "geometry": {"coordinates":[-0.573763,51.477953],"type":"Point"}
}
