{
  "type": "Feature",
  "properties": {
    "date:inception_lower":"1982-03-01",
    "date:inception_upper":"1982-03-31",
    "iso:country":"GB",
    "wof:name":"SL3 9DY",
    "wof:placetype":"postalcode"
},
  "geometry": {"coordinates":[-0.573763,51.477953],"type":"Point"}
}