{
  "type": "Feature",
  "properties": {
    "iso:country":"GB",
    "wof:name":"SL3 9DY",
    "wof:placetype":"postalcode"
},
  "geometry": {"coordinates":[-0.57376333634457,51.4779529298586],"type":"Point"}
}