{
  "type": "Feature",
  "properties": {
    "iso:country":"GB",
    "wof:name":"SE28 0JG",
    "wof:placetype":"postalcode"
},
  "geometry": {"coordinates":[0.09613367900008,51.50000429128485],"type":"Point"}
}