{
  "type": "Feature",
  "properties": {
    "date:inception_lower": "2002-06-01",
    "date:inception_upper": "2002-06-01",
    "iso:country": "GB",
    "wof:name": "SE28 0JG",
    "wof:placetype": "postalcode"
  },
  "geometry": {"coordinates":[0.096134,51.500004],"type":"Point"}
}
