{
  "type": "Feature",
  "properties": {
    "date:inception_lower": "1980-01-01",
    "date:inception_upper": "1980-01-01",
    "iso:country": "GB",
    "wof:name": "BR4 9DU",
    "wof:placetype": "postalcode"
  },
  "geometry": {"coordinates":[0.009129,51.365394],"type":"Point"}
}
