{
  "type": "Feature",
  "properties": {
    "iso:country": "GB",
    "wof:name": "G53 5JX",
    "wof:placetype": "postalcode"
  },
  "geometry": {"coordinates":[-4.347603,55.827279],"type":"Point"}
}
