{
  "type": "Feature",
  "properties": {
    "iso:country": "GB",
    "wof:name": "EN5 2QB",
    "wof:placetype": "postalcode"
  },
  "geometry": {"coordinates":[-0.211969,51.642294],"type":"Point"}
}
