{
  "type": "Feature",
  "properties": {
    "iso:country":"GB",
    "wof:name":"YO25 4PB",
    "wof:placetype":"postalcode"
},
  "geometry": {"coordinates":[-0.38908219616126,54.01478495039243],"type":"Point"}
}