{
  "type": "Feature",
  "properties": {
    "iso:country": "GB",
    "wof:name": "LE17 6HJ",
    "wof:placetype": "postalcode"
  },
  "geometry": {"coordinates":[-1.097819,52.443126],"type":"Point"}
}
