{
  "type": "Feature",
  "properties": {
    "iso:country":"GB",
    "wof:name":"LE17 6HJ",
    "wof:placetype":"postalcode"
},
  "geometry": {"coordinates":[-1.09781878945504,52.4431255664861],"type":"Point"}
}