{
  "type": "Feature",
  "properties": {
    "iso:country": "GB",
    "wof:name": "BL3 3QQ",
    "wof:placetype": "postalcode"
  },
  "geometry": {"coordinates":[-2.453824,53.557302],"type":"Point"}
}
