{
  "type": "Feature",
  "properties": {
    "iso:country":"GB",
    "wof:name":"CB4 1LP",
    "wof:placetype":"postalcode"
},
  "geometry": {"coordinates":[0.14582528406613,52.22442331011839],"type":"Point"}
}