{
  "type": "Feature",
  "properties": {
    "date:inception_lower": "1980-01-01",
    "date:inception_upper": "1980-01-01",
    "iso:country": "GB",
    "wof:name": "W14 8LN",
    "wof:placetype": "postalcode"
  },
  "geometry": {"coordinates":[-0.204141,51.498971],"type":"Point"}
}
