{
  "type": "Feature",
  "properties": {
    "iso:country":"GB",
    "wof:name":"W14 8LN",
    "wof:placetype":"postalcode"
},
  "geometry": {"coordinates":[-0.20414129328234,51.49897101414653],"type":"Point"}
}