{
  "type": "Feature",
  "properties": {
    "iso:country":"GB",
    "wof:name":"PE32 2NJ",
    "wof:placetype":"postalcode"
},
  "geometry": {"coordinates":[0.8275616823076,52.70746247285123],"type":"Point"}
}