{
  "type": "Feature",
  "properties": {
    "iso:country": "GB",
    "wof:name": "NG2 7HT",
    "wof:placetype": "postalcode"
  },
  "geometry": {"coordinates":[-1.13911,52.92051],"type":"Point"}
}
