{
  "type": "Feature",
  "properties": {
    "iso:country":"GB",
    "wof:name":"NG2 7HT",
    "wof:placetype":"postalcode"
},
  "geometry": {"coordinates":[-1.13911037613651,52.92051016923272],"type":"Point"}
}