{
  "type": "Feature",
  "properties": {
    "iso:country": "GB",
    "wof:name": "NE12 9TZ",
    "wof:placetype": "postalcode"
  },
  "geometry": {"coordinates":[-1.56293,55.00791],"type":"Point"}
}
