{
  "type": "Feature",
  "properties": {
    "date:inception_lower": "2015-01-01",
    "date:inception_upper": "2015-01-01",
    "iso:country": "GB",
    "wof:name": "NE12 9TZ",
    "wof:placetype": "postalcode"
  },
  "geometry": {"coordinates":[-1.56293,55.00791],"type":"Point"}
}
