{
  "type": "Feature",
  "properties": {
    "iso:country":"GB",
    "wof:name":"DN3 3PD",
    "wof:placetype":"postalcode"
},
  "geometry": {"coordinates":[-1.03171631105095,53.51134379654282],"type":"Point"}
}