{
  "type": "Feature",
  "properties": {
    "iso:country": "GB",
    "wof:name": "DN3 3PD",
    "wof:placetype": "postalcode"
  },
  "geometry": {"coordinates":[-1.031716,53.511344],"type":"Point"}
}
