{
  "type": "Feature",
  "properties": {
    "iso:country": "GB",
    "wof:name": "HX7 8AD",
    "wof:placetype": "postalcode"
  },
  "geometry": {"coordinates":[-2.011077,53.740207],"type":"Point"}
}
