{
  "type": "Feature",
  "properties": {
    "date:inception_lower":"2000-12-01",
    "date:inception_upper":"2000-12-31",
    "iso:country":"GB",
    "wof:name":"PO37 6SD",
    "wof:placetype":"postalcode"
},
  "geometry": {"coordinates":[-1.179937,50.622317],"type":"Point"}
}