{
  "type": "Feature",
  "properties": {
    "iso:country":"GB",
    "wof:name":"PO37 6SD",
    "wof:placetype":"postalcode"
},
  "geometry": {"coordinates":[-1.1799367464517,50.62231749215967],"type":"Point"}
}