{
  "type": "Feature",
  "properties": {
    "iso:country": "GB",
    "wof:name": "HR3 5PE",
    "wof:placetype": "postalcode"
  },
  "geometry": {"coordinates":[-3.194273,52.043021],"type":"Point"}
}
