{
  "type": "Feature",
  "properties": {
    "iso:country":"GB",
    "wof:name":"HR3 5PE",
    "wof:placetype":"postalcode"
},
  "geometry": {"coordinates":[-3.19427303573624,52.04302119536119],"type":"Point"}
}