{
  "type": "Feature",
  "properties": {
    "date:inception_lower": "1980-01-01",
    "date:inception_upper": "1980-01-01",
    "iso:country": "GB",
    "wof:name": "WR8 0AB",
    "wof:placetype": "postalcode"
  },
  "geometry": {"coordinates":[-2.237634,52.09698],"type":"Point"}
}
