{
  "type": "Feature",
  "properties": {
    "iso:country":"GB",
    "wof:name":"WR8 0AB",
    "wof:placetype":"postalcode"
},
  "geometry": {"coordinates":[-2.23763364783454,52.09698028168134],"type":"Point"}
}