{
  "type": "Feature",
  "properties": {
    "iso:country": "GB",
    "wof:name": "OX4 7TY",
    "wof:placetype": "postalcode"
  },
  "geometry": {"coordinates":[-1.192988,51.715712],"type":"Point"}
}
