{
  "type": "Feature",
  "properties": {
    "iso:country":"GB",
    "wof:name":"HG4 4HY",
    "wof:placetype":"postalcode"
},
  "geometry": {"coordinates":[-1.65666298099952,54.22021282237728],"type":"Point"}
}