{
  "type": "Feature",
  "properties": {
    "iso:country":"GB",
    "wof:name":"GL11 5LR",
    "wof:placetype":"postalcode"
},
  "geometry": {"coordinates":[-2.36749687702389,51.70384367568855],"type":"Point"}
}