{
  "type": "Feature",
  "properties": {
    "iso:country": "GB",
    "wof:name": "GL11 5LR",
    "wof:placetype": "postalcode"
  },
  "geometry": {"coordinates":[-2.367497,51.703844],"type":"Point"}
}
