{
  "type": "Feature",
  "properties": {
    "date:inception_lower":"1980-01-01",
    "date:inception_upper":"1980-01-31",
    "iso:country":"GB",
    "wof:name":"GL11 5LR",
    "wof:placetype":"postalcode"
},
  "geometry": {"coordinates":[-2.367497,51.703844],"type":"Point"}
}