{
  "type": "Feature",
  "properties": {
    "iso:country":"GB",
    "wof:name":"PE30 3BG",
    "wof:placetype":"postalcode"
},
  "geometry": {"coordinates":[0.42749243767893,52.7655263256125],"type":"Point"}
}