{
  "type": "Feature",
  "properties": {
    "iso:country":"GB",
    "wof:name":"CM4 9QT",
    "wof:placetype":"postalcode"
},
  "geometry": {"coordinates":[0.44536579953875,51.67084738958339],"type":"Point"}
}