{
  "type": "Feature",
  "properties": {
    "iso:country": "GB",
    "wof:name": "CM4 9QT",
    "wof:placetype": "postalcode"
  },
  "geometry": {"coordinates":[0.445366,51.670847],"type":"Point"}
}
