{
  "type": "Feature",
  "properties": {
    "date:inception_lower": "1980-01-01",
    "date:inception_upper": "1980-01-01",
    "iso:country": "GB",
    "wof:name": "GL56 9AG",
    "wof:placetype": "postalcode"
  },
  "geometry": {"coordinates":[-1.748245,51.990674],"type":"Point"}
}
