{
  "type": "Feature",
  "properties": {
    "iso:country":"GB",
    "wof:name":"SO53 2DQ",
    "wof:placetype":"postalcode"
},
  "geometry": {"coordinates":[-1.37393745559424,50.98844252522098],"type":"Point"}
}