{
  "type": "Feature",
  "properties": {
    "date:inception_lower": "2008-12-01",
    "date:inception_upper": "2008-12-01",
    "iso:country": "GB",
    "wof:name": "TF2 8DW",
    "wof:placetype": "postalcode"
  },
  "geometry": {"coordinates":[-2.440238,52.727289],"type":"Point"}
}
