{
  "type": "Feature",
  "properties": {
    "iso:country": "GB",
    "wof:name": "TF2 8DW",
    "wof:placetype": "postalcode"
  },
  "geometry": {"coordinates":[-2.440238,52.727289],"type":"Point"}
}
