{
  "type": "Feature",
  "properties": {
    "iso:country":"GB",
    "wof:name":"G81 4JH",
    "wof:placetype":"postalcode"
},
  "geometry": {"coordinates":[-4.4357750561221,55.91226046264914],"type":"Point"}
}