{
  "type": "Feature",
  "properties": {
    "iso:country": "GB",
    "wof:name": "G81 4JH",
    "wof:placetype": "postalcode"
  },
  "geometry": {"coordinates":[-4.435722,55.912156],"type":"Point"}
}
