{
  "type": "Feature",
  "properties": {
    "date:inception_lower": "1980-01-01",
    "date:inception_upper": "1980-01-01",
    "iso:country": "GB",
    "wof:name": "DT7 3TJ",
    "wof:placetype": "postalcode"
  },
  "geometry": {"coordinates":[-2.950668,50.733095],"type":"Point"}
}
