{
  "type": "Feature",
  "properties": {
    "iso:country":"GB",
    "wof:name":"DT7 3TJ",
    "wof:placetype":"postalcode"
},
  "geometry": {"coordinates":[-2.95066782575785,50.73309472502177],"type":"Point"}
}