{
  "type": "Feature",
  "properties": {
    "iso:country":"GB",
    "wof:name":"SY3 6AL",
    "wof:placetype":"postalcode"
},
  "geometry": {"coordinates":[-2.77611938145646,52.69580917824999],"type":"Point"}
}