{
  "type": "Feature",
  "properties": {
    "iso:country": "GB",
    "wof:name": "SY3 6AL",
    "wof:placetype": "postalcode"
  },
  "geometry": {"coordinates":[-2.776103,52.695815],"type":"Point"}
}
