{
  "type": "Feature",
  "properties": {
    "iso:country": "GB",
    "wof:name": "SO40 4SL",
    "wof:placetype": "postalcode"
  },
  "geometry": {"coordinates":[-1.444963,50.892565],"type":"Point"}
}
