{
  "type": "Feature",
  "properties": {
    "iso:country":"GB",
    "wof:name":"GU31 5NG",
    "wof:placetype":"postalcode"
},
  "geometry": {"coordinates":[-0.85691898094606,50.96647152082266],"type":"Point"}
}