{
  "type": "Feature",
  "properties": {
    "iso:country":"GB",
    "wof:name":"WA12 8SH",
    "wof:placetype":"postalcode"
},
  "geometry": {"coordinates":[-2.63004980773775,53.44340035095177],"type":"Point"}
}