{
  "type": "Feature",
  "properties": {
    "date:inception_lower":"1980-01-01",
    "date:inception_upper":"1980-01-31",
    "iso:country":"GB",
    "wof:name":"WA12 8SH",
    "wof:placetype":"postalcode"
},
  "geometry": {"coordinates":[-2.63005,53.4434],"type":"Point"}
}