{
  "type": "Feature",
  "properties": {
    "iso:country": "GB",
    "wof:name": "WA12 8SH",
    "wof:placetype": "postalcode"
  },
  "geometry": {"coordinates":[-2.63005,53.4434],"type":"Point"}
}
