{
  "type": "Feature",
  "properties": {
    "iso:country":"GB",
    "wof:name":"NG5 8LF",
    "wof:placetype":"postalcode"
},
  "geometry": {"coordinates":[-1.12442343869667,53.01371390407056],"type":"Point"}
}