{
  "type": "Feature",
  "properties": {
    "iso:country":"GB",
    "wof:name":"RH2 8EQ",
    "wof:placetype":"postalcode"
},
  "geometry": {"coordinates":[-0.20203257376677,51.2199506818613],"type":"Point"}
}