{
  "type": "Feature",
  "properties": {
    "date:inception_lower": "1980-01-01",
    "date:inception_upper": "1980-01-01",
    "iso:country": "GB",
    "wof:name": "RH2 8EQ",
    "wof:placetype": "postalcode"
  },
  "geometry": {"coordinates":[-0.202033,51.219951],"type":"Point"}
}
