{
  "type": "Feature",
  "properties": {
    "iso:country":"GB",
    "wof:name":"SK14 5NT",
    "wof:placetype":"postalcode"
},
  "geometry": {"coordinates":[-2.06367489501736,53.44384153690913],"type":"Point"}
}