{
  "type": "Feature",
  "properties": {
    "iso:country": "GB",
    "wof:name": "SY2 5LZ",
    "wof:placetype": "postalcode"
  },
  "geometry": {"coordinates":[-2.727547,52.708649],"type":"Point"}
}
