{
  "type": "Feature",
  "properties": {
    "iso:country":"GB",
    "wof:name":"IP12 2LH",
    "wof:placetype":"postalcode"
},
  "geometry": {"coordinates":[1.5332471157434,52.09444887549906],"type":"Point"}
}