{
  "type": "Feature",
  "properties": {
    "iso:country":"GB",
    "wof:name":"WF12 9PB",
    "wof:placetype":"postalcode"
},
  "geometry": {"coordinates":[-1.63425855024102,53.67974757027813],"type":"Point"}
}