{
  "type": "Feature",
  "properties": {
    "iso:country": "GB",
    "wof:name": "W10 6DE",
    "wof:placetype": "postalcode"
  },
  "geometry": {"coordinates":[-0.219513,51.521902],"type":"Point"}
}
