{
  "type": "Feature",
  "properties": {
    "iso:country":"GB",
    "wof:name":"W10 6DE",
    "wof:placetype":"postalcode"
},
  "geometry": {"coordinates":[-0.21951346618338,51.52190226948218],"type":"Point"}
}