{
  "type": "Feature",
  "properties": {
    "date:inception_lower": "2002-05-01",
    "date:inception_upper": "2002-05-01",
    "iso:country": "GB",
    "wof:name": "HP23 4BU",
    "wof:placetype": "postalcode"
  },
  "geometry": {"coordinates":[-0.672005,51.790529],"type":"Point"}
}
