{
  "type": "Feature",
  "properties": {
    "iso:country":"GB",
    "wof:name":"SP11 9JN",
    "wof:placetype":"postalcode"
},
  "geometry": {"coordinates":[-1.6420255504051,51.24062128060103],"type":"Point"}
}