{
  "type": "Feature",
  "properties": {
    "iso:country":"GB",
    "wof:name":"MK6 2XR",
    "wof:placetype":"postalcode"
},
  "geometry": {"coordinates":[-0.76082898453482,52.03296947334685],"type":"Point"}
}