{
  "type": "Feature",
  "properties": {
    "iso:country":"GB",
    "wof:name":"SR5 2JD",
    "wof:placetype":"postalcode"
},
  "geometry": {"coordinates":[-1.40208330107239,54.92089372307242],"type":"Point"}
}