{
  "type": "Feature",
  "properties": {
    "iso:country": "GB",
    "wof:name": "BN11 2LT",
    "wof:placetype": "postalcode"
  },
  "geometry": {"coordinates":[-0.355224,50.815083],"type":"Point"}
}
