{
  "type": "Feature",
  "properties": {
    "date:inception_lower": "1980-01-01",
    "date:inception_upper": "1980-01-01",
    "iso:country": "GB",
    "wof:name": "HU11 4DH",
    "wof:placetype": "postalcode"
  },
  "geometry": {"coordinates":[-0.227142,53.78047],"type":"Point"}
}
