{
  "type": "Feature",
  "properties": {
    "iso:country": "GB",
    "wof:name": "HU11 4DH",
    "wof:placetype": "postalcode"
  },
  "geometry": {"coordinates":[-0.227142,53.78047],"type":"Point"}
}
