{
  "type": "Feature",
  "properties": {
    "iso:country":"GB",
    "wof:name":"NE6 2DA",
    "wof:placetype":"postalcode"
},
  "geometry": {"coordinates":[-1.571493718007,54.97168041189825],"type":"Point"}
}