{
  "type": "Feature",
  "properties": {
    "iso:country":"GB",
    "wof:name":"NG1 3HL",
    "wof:placetype":"postalcode"
},
  "geometry": {"coordinates":[-1.15034116568024,52.96147533999375],"type":"Point"}
}