{
  "type": "Feature",
  "properties": {
    "date:inception_lower": "1994-12-01",
    "date:inception_upper": "1994-12-01",
    "iso:country": "GB",
    "wof:name": "GL11 5SZ",
    "wof:placetype": "postalcode"
  },
  "geometry": {"coordinates":[-2.35898,51.693692],"type":"Point"}
}
