{
  "type": "Feature",
  "properties": {
    "iso:country": "GB",
    "wof:name": "GL11 5SZ",
    "wof:placetype": "postalcode"
  },
  "geometry": {"coordinates":[-2.35898,51.693692],"type":"Point"}
}
