{
  "type": "Feature",
  "properties": {
    "iso:country":"GB",
    "wof:name":"TS3 7LX",
    "wof:placetype":"postalcode"
},
  "geometry": {"coordinates":[-1.20654635476515,54.55429846501629],"type":"Point"}
}