{
  "type": "Feature",
  "properties": {
    "iso:country":"GB",
    "wof:name":"G82 3EZ",
    "wof:placetype":"postalcode"
},
  "geometry": {"coordinates":[-4.550700776317,55.95648183078967],"type":"Point"}
}