{
  "type": "Feature",
  "properties": {
    "iso:country":"GB",
    "wof:name":"PO38 2LN",
    "wof:placetype":"postalcode"
},
  "geometry": {"coordinates":[-1.35412852632194,50.61292713935076],"type":"Point"}
}