{
  "type": "Feature",
  "properties": {
    "date:inception_lower": "1980-01-01",
    "date:inception_upper": "1980-01-01",
    "iso:country": "GB",
    "wof:name": "NG17 5GE",
    "wof:placetype": "postalcode"
  },
  "geometry": {"coordinates":[-1.245873,53.122318],"type":"Point"}
}
