{
  "type": "Feature",
  "properties": {
    "date:inception_lower": "1980-01-01",
    "date:inception_upper": "1980-01-01",
    "iso:country": "GB",
    "wof:name": "E17 4JE",
    "wof:placetype": "postalcode"
  },
  "geometry": {"coordinates":[-0.006802,51.592375],"type":"Point"}
}
