{
  "type": "Feature",
  "properties": {
    "iso:country":"GB",
    "wof:name":"E17 4JE",
    "wof:placetype":"postalcode"
},
  "geometry": {"coordinates":[-0.00673301334491,51.59225467189998],"type":"Point"}
}