{
  "type": "Feature",
  "properties": {
    "iso:country":"GB",
    "wof:name":"LN13 0HH",
    "wof:placetype":"postalcode"
},
  "geometry": {"coordinates":[0.14937485523532,53.22243431524825],"type":"Point"}
}