{
  "type": "Feature",
  "properties": {
    "iso:country": "GB",
    "wof:name": "LN13 0HH",
    "wof:placetype": "postalcode"
  },
  "geometry": {"coordinates":[0.149375,53.222434],"type":"Point"}
}
