{
  "type": "Feature",
  "properties": {
    "iso:country": "GB",
    "wof:name": "EH12 5YS",
    "wof:placetype": "postalcode"
  },
  "geometry": {"coordinates":[-3.260892,55.942648],"type":"Point"}
}
