{
  "type": "Feature",
  "properties": {
    "iso:country":"GB",
    "wof:name":"GU8 6AZ",
    "wof:placetype":"postalcode"
},
  "geometry": {"coordinates":[-0.65217904610739,51.19425733778426],"type":"Point"}
}