{
  "type": "Feature",
  "properties": {
    "date:inception_lower":"1980-01-01",
    "date:inception_upper":"1980-01-31",
    "iso:country":"GB",
    "wof:name":"GU8 6AZ",
    "wof:placetype":"postalcode"
},
  "geometry": {"coordinates":[-0.652179,51.194257],"type":"Point"}
}