{
  "type": "Feature",
  "properties": {
    "iso:country": "GB",
    "wof:name": "TQ4 6AR",
    "wof:placetype": "postalcode"
  },
  "geometry": {"coordinates":[-3.561608,50.433843],"type":"Point"}
}
