{
  "type": "Feature",
  "properties": {
    "iso:country":"GB",
    "wof:name":"SK13 6JS",
    "wof:placetype":"postalcode"
},
  "geometry": {"coordinates":[-1.9553297364968,53.43680341161406],"type":"Point"}
}