{
  "type": "Feature",
  "properties": {
    "iso:country":"GB",
    "wof:name":"BL5 3BB",
    "wof:placetype":"postalcode"
},
  "geometry": {"coordinates":[-2.52409913503841,53.54916794514583],"type":"Point"}
}