{
  "type": "Feature",
  "properties": {
    "iso:country": "GB",
    "wof:name": "BL5 3BB",
    "wof:placetype": "postalcode"
  },
  "geometry": {"coordinates":[-2.524099,53.549168],"type":"Point"}
}
