{
  "type": "Feature",
  "properties": {
    "iso:country":"GB",
    "wof:name":"B90 1FH",
    "wof:placetype":"postalcode"
},
  "geometry": {"coordinates":[-1.83706450860087,52.38383678806682],"type":"Point"}
}