{
  "type": "Feature",
  "properties": {
    "iso:country": "GB",
    "wof:name": "PE28 4BP",
    "wof:placetype": "postalcode"
  },
  "geometry": {"coordinates":[-0.229945,52.372278],"type":"Point"}
}
