{
  "type": "Feature",
  "properties": {
    "date:inception_lower": "1995-07-01",
    "date:inception_upper": "1995-07-01",
    "iso:country": "GB",
    "wof:name": "RG14 3BB",
    "wof:placetype": "postalcode"
  },
  "geometry": {"coordinates":[-1.334577,51.427307],"type":"Point"}
}
