{
  "type": "Feature",
  "properties": {
    "date:inception_lower": "2004-01-01",
    "date:inception_upper": "2004-01-01",
    "iso:country": "GB",
    "wof:name": "WR10 2DE",
    "wof:placetype": "postalcode"
  },
  "geometry": {"coordinates":[-2.034691,52.126839],"type":"Point"}
}
