{
  "type": "Feature",
  "properties": {
    "iso:country": "GB",
    "wof:name": "WR10 2DE",
    "wof:placetype": "postalcode"
  },
  "geometry": {"coordinates":[-2.034691,52.126839],"type":"Point"}
}
