{
  "type": "Feature",
  "properties": {
    "iso:country":"GB",
    "wof:name":"WR10 2DE",
    "wof:placetype":"postalcode"
},
  "geometry": {"coordinates":[-2.03469090769762,52.12683888379914],"type":"Point"}
}