{
  "type": "Feature",
  "properties": {
    "iso:country":"GB",
    "wof:name":"PE4 7UT",
    "wof:placetype":"postalcode"
},
  "geometry": {"coordinates":[-0.25568298005762,52.60615038632199],"type":"Point"}
}