{
  "type": "Feature",
  "properties": {
    "date:inception_lower":"1980-01-01",
    "date:inception_upper":"1980-01-31",
    "iso:country":"GB",
    "wof:name":"IG3 8PG",
    "wof:placetype":"postalcode"
},
  "geometry": {"coordinates":[0.102075,51.569962],"type":"Point"}
}