{
  "type": "Feature",
  "properties": {
    "date:inception_lower": "2015-08-01",
    "date:inception_upper": "2015-08-01",
    "iso:country": "GB",
    "wof:name": "MK3 5GW",
    "wof:placetype": "postalcode"
  },
  "geometry": {"coordinates":[-0.735809,51.976257],"type":"Point"}
}
