{
  "type": "Feature",
  "properties": {
    "iso:country":"GB",
    "wof:name":"MK3 5GW",
    "wof:placetype":"postalcode"
},
  "geometry": {"coordinates":[-0.73580892406064,51.97625686901337],"type":"Point"}
}