{
  "type": "Feature",
  "properties": {
    "iso:country":"GB",
    "wof:name":"TW9 1PE",
    "wof:placetype":"postalcode"
},
  "geometry": {"coordinates":[-0.31037705898889,51.46088428929752],"type":"Point"}
}