{
  "type": "Feature",
  "properties": {
    "iso:country":"GB",
    "wof:name":"WA6 7PS",
    "wof:placetype":"postalcode"
},
  "geometry": {"coordinates":[-2.71601697385449,53.30100963908643],"type":"Point"}
}