{
  "type": "Feature",
  "properties": {
    "iso:country": "GB",
    "wof:name": "BB12 8AG",
    "wof:placetype": "postalcode"
  },
  "geometry": {"coordinates":[-2.269415,53.794159],"type":"Point"}
}
