{
  "type": "Feature",
  "properties": {
    "iso:country":"GB",
    "wof:name":"BB12 8AG",
    "wof:placetype":"postalcode"
},
  "geometry": {"coordinates":[-2.2694153113552,53.79415914190622],"type":"Point"}
}