{
  "type": "Feature",
  "properties": {
    "iso:country": "GB",
    "wof:name": "KT20 6NX",
    "wof:placetype": "postalcode"
  },
  "geometry": {"coordinates":[-0.21567,51.292371],"type":"Point"}
}
