{
  "type": "Feature",
  "properties": {
    "iso:country":"GB",
    "wof:name":"KT20 6NX",
    "wof:placetype":"postalcode"
},
  "geometry": {"coordinates":[-0.21567041063189,51.29237146352339],"type":"Point"}
}