{
  "type": "Feature",
  "properties": {
    "iso:country":"GB",
    "wof:name":"NG9 3QN",
    "wof:placetype":"postalcode"
},
  "geometry": {"coordinates":[-1.27256478636985,52.94745332568115],"type":"Point"}
}