{
  "type": "Feature",
  "properties": {
    "iso:country": "GB",
    "wof:name": "NG9 3QN",
    "wof:placetype": "postalcode"
  },
  "geometry": {"coordinates":[-1.272565,52.947453],"type":"Point"}
}
