{
  "type": "Feature",
  "properties": {
    "iso:country":"GB",
    "wof:name":"WS15 4EX",
    "wof:placetype":"postalcode"
},
  "geometry": {"coordinates":[-1.86141171223704,52.7394968577137],"type":"Point"}
}