{
  "type": "Feature",
  "properties": {
    "date:inception_lower": "1980-01-01",
    "date:inception_upper": "1980-01-01",
    "iso:country": "GB",
    "wof:name": "WS15 4EX",
    "wof:placetype": "postalcode"
  },
  "geometry": {"coordinates":[-1.861412,52.739497],"type":"Point"}
}
