{
  "type": "Feature",
  "properties": {
    "iso:country": "GB",
    "wof:name": "PL2 2PN",
    "wof:placetype": "postalcode"
  },
  "geometry": {"coordinates":[-4.16553,50.392336],"type":"Point"}
}
