{
  "type": "Feature",
  "properties": {
    "iso:country":"GB",
    "wof:name":"PL2 2PN",
    "wof:placetype":"postalcode"
},
  "geometry": {"coordinates":[-4.16552959735498,50.39233570028414],"type":"Point"}
}