{
  "type": "Feature",
  "properties": {
    "iso:country":"GB",
    "wof:name":"WR1 1PG",
    "wof:placetype":"postalcode"
},
  "geometry": {"coordinates":[-2.21804799120011,52.19949169069289],"type":"Point"}
}