{
  "type": "Feature",
  "properties": {
    "iso:country": "GB",
    "wof:name": "DG1 3GY",
    "wof:placetype": "postalcode"
  },
  "geometry": {"coordinates":[-3.595453,55.080099],"type":"Point"}
}
