{
  "type": "Feature",
  "properties": {
    "iso:country": "GB",
    "wof:name": "GL11 5GN",
    "wof:placetype": "postalcode"
  },
  "geometry": {"coordinates":[-2.341245,51.678586],"type":"Point"}
}
