{
  "type": "Feature",
  "properties": {
    "date:inception_lower": "2003-09-01",
    "date:inception_upper": "2003-09-01",
    "iso:country": "GB",
    "wof:name": "GL11 5GN",
    "wof:placetype": "postalcode"
  },
  "geometry": {"coordinates":[-2.341245,51.678586],"type":"Point"}
}
