{
  "type": "Feature",
  "properties": {
    "date:inception_lower": "1999-12-01",
    "date:inception_upper": "1999-12-01",
    "iso:country": "GB",
    "wof:name": "TQ12 6PW",
    "wof:placetype": "postalcode"
  },
  "geometry": {"coordinates":[-3.649882,50.560057],"type":"Point"}
}
