{
  "type": "Feature",
  "properties": {
    "iso:country":"GB",
    "wof:name":"BD21 2HT",
    "wof:placetype":"postalcode"
},
  "geometry": {"coordinates":[-1.91805254010624,53.87074184690352],"type":"Point"}
}