{
  "type": "Feature",
  "properties": {
    "iso:country":"GB",
    "wof:name":"B90 3JA",
    "wof:placetype":"postalcode"
},
  "geometry": {"coordinates":[-1.82593310372245,52.41243641377864],"type":"Point"}
}