{
  "type": "Feature",
  "properties": {
    "date:inception_lower": "1980-01-01",
    "date:inception_upper": "1980-01-01",
    "iso:country": "GB",
    "wof:name": "GL6 7AQ",
    "wof:placetype": "postalcode"
  },
  "geometry": {"coordinates":[-2.142227,51.749019],"type":"Point"}
}
