{
  "type": "Feature",
  "properties": {
    "date:inception_lower": "2022-08-01",
    "date:inception_upper": "2022-08-01",
    "iso:country": "GB",
    "wof:name": "SO30 2DT",
    "wof:placetype": "postalcode"
  },
  "geometry": {"coordinates":[-1.24438,50.903642],"type":"Point"}
}
