{
  "type": "Feature",
  "properties": {
    "iso:country":"GB",
    "wof:name":"NE6 1DE",
    "wof:placetype":"postalcode"
},
  "geometry": {"coordinates":[-1.58572982043718,54.97422788664829],"type":"Point"}
}