{
  "type": "Feature",
  "properties": {
    "iso:country":"GB",
    "wof:name":"ME8 8BH",
    "wof:placetype":"postalcode"
},
  "geometry": {"coordinates":[0.61295516461677,51.36444240837475],"type":"Point"}
}