{
  "type": "Feature",
  "properties": {
    "date:inception_lower":"1980-01-01",
    "date:inception_upper":"1980-01-31",
    "iso:country":"GB",
    "wof:name":"OX1 3ND",
    "wof:placetype":"postalcode"
},
  "geometry": {"coordinates":[-1.26103,51.758625],"type":"Point"}
}