{
  "type": "Feature",
  "properties": {
    "iso:country":"GB",
    "wof:name":"SY5 6NU",
    "wof:placetype":"postalcode"
},
  "geometry": {"coordinates":[-2.61848222566521,52.58962267230739],"type":"Point"}
}