{
  "type": "Feature",
  "properties": {
    "iso:country": "GB",
    "wof:name": "G75 9DE",
    "wof:placetype": "postalcode"
  },
  "geometry": {"coordinates":[-4.200833,55.741287],"type":"Point"}
}
