{
  "type": "Feature",
  "properties": {
    "date:inception_lower":"1996-12-01",
    "date:inception_upper":"1996-12-31",
    "iso:country":"GB",
    "wof:name":"G75 9DE",
    "wof:placetype":"postalcode"
},
  "geometry": {"coordinates":[-4.200833,55.741287],"type":"Point"}
}