{
  "type": "Feature",
  "properties": {
    "iso:country": "GB",
    "wof:name": "BS23 3NT",
    "wof:placetype": "postalcode"
  },
  "geometry": {"coordinates":[-2.968514,51.339746],"type":"Point"}
}
