{
  "type": "Feature",
  "properties": {
    "iso:country":"GB",
    "wof:name":"BS23 3NT",
    "wof:placetype":"postalcode"
},
  "geometry": {"coordinates":[-2.96873455277575,51.33960354617181],"type":"Point"}
}