{
  "type": "Feature",
  "properties": {
    "iso:country": "GB",
    "wof:name": "L15 8HF",
    "wof:placetype": "postalcode"
  },
  "geometry": {"coordinates":[-2.917893,53.39862],"type":"Point"}
}
