{
  "type": "Feature",
  "properties": {
    "iso:country":"GB",
    "wof:name":"CR3 6FE",
    "wof:placetype":"postalcode"
},
  "geometry": {"coordinates":[-0.07769854104689,51.27885638476034],"type":"Point"}
}