{
  "type": "Feature",
  "properties": {
    "date:inception_lower": "2012-02-01",
    "date:inception_upper": "2012-02-01",
    "iso:country": "GB",
    "wof:name": "CR3 6FE",
    "wof:placetype": "postalcode"
  },
  "geometry": {"coordinates":[-0.077699,51.278856],"type":"Point"}
}
