{
  "type": "Feature",
  "properties": {
    "iso:country":"GB",
    "wof:name":"EX32 7LU",
    "wof:placetype":"postalcode"
},
  "geometry": {"coordinates":[-4.00256040723409,51.08883504331065],"type":"Point"}
}