{
  "type": "Feature",
  "properties": {
    "date:inception_lower": "1997-12-01",
    "date:inception_upper": "1997-12-01",
    "iso:country": "GB",
    "wof:name": "WA8 7ST",
    "wof:placetype": "postalcode"
  },
  "geometry": {"coordinates":[-2.733194,53.361167],"type":"Point"}
}
