{
  "type": "Feature",
  "properties": {
    "iso:country": "GB",
    "wof:name": "PE12 0SP",
    "wof:placetype": "postalcode"
  },
  "geometry": {"coordinates":[-0.059679,52.706941],"type":"Point"}
}
