{
  "type": "Feature",
  "properties": {
    "iso:country":"GB",
    "wof:name":"PE12 0SP",
    "wof:placetype":"postalcode"
},
  "geometry": {"coordinates":[-0.05969379888008,52.70693924236753],"type":"Point"}
}