{
  "type": "Feature",
  "properties": {
    "date:inception_lower": "1980-01-01",
    "date:inception_upper": "1980-01-01",
    "iso:country": "GB",
    "wof:name": "LN3 5UN",
    "wof:placetype": "postalcode"
  },
  "geometry": {"coordinates":[-0.353989,53.214642],"type":"Point"}
}
