{
  "type": "Feature",
  "properties": {
    "iso:country":"GB",
    "wof:name":"LN3 5UN",
    "wof:placetype":"postalcode"
},
  "geometry": {"coordinates":[-0.34660406168144,53.21395032468025],"type":"Point"}
}