{
  "type": "Feature",
  "properties": {
    "iso:country": "GB",
    "wof:name": "LN3 5UN",
    "wof:placetype": "postalcode"
  },
  "geometry": {"coordinates":[-0.348625,53.215862],"type":"Point"}
}
