{
  "type": "Feature",
  "properties": {
    "iso:country": "GB",
    "wof:name": "MK17 7AX",
    "wof:placetype": "postalcode"
  },
  "geometry": {"coordinates":[-0.650065,52.035243],"type":"Point"}
}
