{
  "type": "Feature",
  "properties": {
    "iso:country":"GB",
    "wof:name":"SW1W 9JA",
    "wof:placetype":"postalcode"
},
  "geometry": {"coordinates":[-0.15339931330487,51.49359683974505],"type":"Point"}
}