{
  "type": "Feature",
  "properties": {
    "date:inception_lower": "2000-06-01",
    "date:inception_upper": "2000-06-01",
    "iso:country": "GB",
    "wof:name": "PE28 2PD",
    "wof:placetype": "postalcode"
  },
  "geometry": {"coordinates":[-0.189302,52.385933],"type":"Point"}
}
