{
  "type": "Feature",
  "properties": {
    "iso:country":"GB",
    "wof:name":"PE28 2PD",
    "wof:placetype":"postalcode"
},
  "geometry": {"coordinates":[-0.18930221887173,52.38593334896481],"type":"Point"}
}