{
  "type": "Feature",
  "properties": {
    "date:inception_lower": "2012-07-01",
    "date:inception_upper": "2012-07-01",
    "iso:country": "GB",
    "wof:name": "CT50 1AN",
    "wof:placetype": "postalcode"
  },
  "geometry": {"coordinates":[1.141477,51.080971],"type":"Point"}
}
