{
  "type": "Feature",
  "properties": {
    "date:inception_lower": "2020-10-01",
    "date:inception_upper": "2020-10-01",
    "iso:country": "GB",
    "wof:name": "SY12 0FT",
    "wof:placetype": "postalcode"
  },
  "geometry": {"coordinates":[-2.841005,52.855165],"type":"Point"}
}
