{
  "type": "Feature",
  "properties": {
    "iso:country":"GB",
    "wof:name":"WA12 0BU",
    "wof:placetype":"postalcode"
},
  "geometry": {"coordinates":[-2.60611465090204,53.45522743119194],"type":"Point"}
}