{
  "type": "Feature",
  "properties": {
    "iso:country": "GB",
    "wof:name": "DY1 1AH",
    "wof:placetype": "postalcode"
  },
  "geometry": {"coordinates":[-2.086165,52.512238],"type":"Point"}
}
