{
  "type": "Feature",
  "properties": {
    "iso:country":"GB",
    "wof:name":"CA7 8DJ",
    "wof:placetype":"postalcode"
},
  "geometry": {"coordinates":[-3.08441807028282,54.76627306067618],"type":"Point"}
}