{
  "type": "Feature",
  "properties": {
    "iso:country": "GB",
    "wof:name": "CA7 8DJ",
    "wof:placetype": "postalcode"
  },
  "geometry": {"coordinates":[-3.079224,54.76718],"type":"Point"}
}
