{
  "type": "Feature",
  "properties": {
    "iso:country":"GB",
    "wof:name":"SA72 6AT",
    "wof:placetype":"postalcode"
},
  "geometry": {"coordinates":[-4.94344664303388,51.69080813768733],"type":"Point"}
}