{
  "type": "Feature",
  "properties": {
    "iso:country": "GB",
    "wof:name": "SA72 6AT",
    "wof:placetype": "postalcode"
  },
  "geometry": {"coordinates":[-4.943447,51.690808],"type":"Point"}
}
