{
  "type": "Feature",
  "properties": {
    "iso:country": "GB",
    "wof:name": "OX9 3BS",
    "wof:placetype": "postalcode"
  },
  "geometry": {"coordinates":[-0.975298,51.747095],"type":"Point"}
}
