{
  "type": "Feature",
  "properties": {
    "iso:country":"GB",
    "wof:name":"OX9 3BS",
    "wof:placetype":"postalcode"
},
  "geometry": {"coordinates":[-0.9752981837849,51.74709522003207],"type":"Point"}
}