{
  "type": "Feature",
  "properties": {
    "iso:country": "GB",
    "wof:name": "CM23 1FH",
    "wof:placetype": "postalcode"
  },
  "geometry": {"coordinates":[0.171423,51.887989],"type":"Point"}
}
