{
  "type": "Feature",
  "properties": {
    "iso:country":"GB",
    "wof:name":"W12 0HR",
    "wof:placetype":"postalcode"
},
  "geometry": {"coordinates":[-0.22989227122058,51.51892100114996],"type":"Point"}
}