{
  "type": "Feature",
  "properties": {
    "iso:country":"GB",
    "wof:name":"EX1 2PR",
    "wof:placetype":"postalcode"
},
  "geometry": {"coordinates":[-3.50920587489338,50.72654478415784],"type":"Point"}
}