{
  "type": "Feature",
  "properties": {
    "date:inception_lower": "2003-06-01",
    "date:inception_upper": "2003-06-01",
    "iso:country": "GB",
    "wof:name": "NG7 5HA",
    "wof:placetype": "postalcode"
  },
  "geometry": {"coordinates":[-1.176704,52.969473],"type":"Point"}
}
