{
  "type": "Feature",
  "properties": {
    "iso:country":"GB",
    "wof:name":"NG7 5HA",
    "wof:placetype":"postalcode"
},
  "geometry": {"coordinates":[-1.17670404871519,52.96947265196793],"type":"Point"}
}