{
  "type": "Feature",
  "properties": {
    "iso:country":"GB",
    "wof:name":"SE18 6DT",
    "wof:placetype":"postalcode"
},
  "geometry": {"coordinates":[0.06385991092226,51.49364332539197],"type":"Point"}
}