{
  "type": "Feature",
  "properties": {
    "date:inception_lower": "1996-06-01",
    "date:inception_upper": "1996-06-01",
    "iso:country": "GB",
    "wof:name": "SE18 6DT",
    "wof:placetype": "postalcode"
  },
  "geometry": {"coordinates":[0.063743,51.493655],"type":"Point"}
}
