{
  "type": "Feature",
  "properties": {
    "iso:country":"GB",
    "wof:name":"BR3 4XP",
    "wof:placetype":"postalcode"
},
  "geometry": {"coordinates":[-0.04328195588088,51.40570592684544],"type":"Point"}
}