{
  "type": "Feature",
  "properties": {
    "iso:country": "GB",
    "wof:name": "BR3 4XP",
    "wof:placetype": "postalcode"
  },
  "geometry": {"coordinates":[-0.043282,51.405706],"type":"Point"}
}
