{
  "type": "Feature",
  "properties": {
    "date:inception_lower": "1980-01-01",
    "date:inception_upper": "1980-01-01",
    "iso:country": "GB",
    "wof:name": "NP7 8HW",
    "wof:placetype": "postalcode"
  },
  "geometry": {"coordinates":[-2.968342,51.880819],"type":"Point"}
}
