{
  "type": "Feature",
  "properties": {
    "iso:country":"GB",
    "wof:name":"NP7 8HW",
    "wof:placetype":"postalcode"
},
  "geometry": {"coordinates":[-2.96834166800814,51.88081938279139],"type":"Point"}
}