{
  "type": "Feature",
  "properties": {
    "iso:country":"GB",
    "wof:name":"PO32 6QR",
    "wof:placetype":"postalcode"
},
  "geometry": {"coordinates":[-1.28150021973627,50.75540766814304],"type":"Point"}
}