{
  "type": "Feature",
  "properties": {
    "date:inception_lower": "2015-06-01",
    "date:inception_upper": "2015-06-01",
    "iso:country": "GB",
    "wof:name": "SK8 1BA",
    "wof:placetype": "postalcode"
  },
  "geometry": {"coordinates":[-2.225133,53.390919],"type":"Point"}
}
