{
  "type": "Feature",
  "properties": {
    "iso:country":"GB",
    "wof:name":"SK8 1BA",
    "wof:placetype":"postalcode"
},
  "geometry": {"coordinates":[-2.22513338675572,53.39091918717603],"type":"Point"}
}