{
  "type": "Feature",
  "properties": {
    "iso:country":"GB",
    "wof:name":"SW16 5LL",
    "wof:placetype":"postalcode"
},
  "geometry": {"coordinates":[-0.1328661150674,51.4182285104249],"type":"Point"}
}