{
  "type": "Feature",
  "properties": {
    "date:inception_lower": "1980-01-01",
    "date:inception_upper": "1980-01-01",
    "iso:country": "GB",
    "wof:name": "DN35 8RW",
    "wof:placetype": "postalcode"
  },
  "geometry": {"coordinates":[-0.026668,53.553808],"type":"Point"}
}
