{
  "type": "Feature",
  "properties": {
    "iso:country":"GB",
    "wof:name":"M20 4WS",
    "wof:placetype":"postalcode"
},
  "geometry": {"coordinates":[-2.21967452932422,53.43455083266726],"type":"Point"}
}