{
  "type": "Feature",
  "properties": {
    "date:inception_lower": "2020-08-01",
    "date:inception_upper": "2020-08-01",
    "iso:country": "GB",
    "wof:name": "YO12 5AP",
    "wof:placetype": "postalcode"
  },
  "geometry": {"coordinates":[-0.442738,54.284668],"type":"Point"}
}
