{
  "type": "Feature",
  "properties": {
    "date:inception_lower": "2019-04-01",
    "date:inception_upper": "2019-04-01",
    "iso:country": "GB",
    "wof:name": "TA7 9DH",
    "wof:placetype": "postalcode"
  },
  "geometry": {"coordinates":[-2.896396,51.146305],"type":"Point"}
}
