{
  "type": "Feature",
  "properties": {
    "iso:country": "GB",
    "wof:name": "BS5 9LA",
    "wof:placetype": "postalcode"
  },
  "geometry": {"coordinates":[-2.557847,51.458814],"type":"Point"}
}
