{
  "type": "Feature",
  "properties": {
    "iso:country":"GB",
    "wof:name":"SE27 0JJ",
    "wof:placetype":"postalcode"
},
  "geometry": {"coordinates":[-0.10550699124193,51.43050507613427],"type":"Point"}
}