{
  "type": "Feature",
  "properties": {
    "iso:country":"GB",
    "wof:name":"NG31 9HB",
    "wof:placetype":"postalcode"
},
  "geometry": {"coordinates":[-0.59099416236726,52.91541906069924],"type":"Point"}
}