{
  "type": "Feature",
  "properties": {
    "date:inception_lower":"1995-12-01",
    "date:inception_upper":"1995-12-31",
    "iso:country":"GB",
    "wof:name":"PL6 7ND",
    "wof:placetype":"postalcode"
},
  "geometry": {"coordinates":[-4.097908,50.426036],"type":"Point"}
}