{
  "type": "Feature",
  "properties": {
    "iso:country":"GB",
    "wof:name":"PL6 7ND",
    "wof:placetype":"postalcode"
},
  "geometry": {"coordinates":[-4.09790788212776,50.42603588785712],"type":"Point"}
}