{
  "type": "Feature",
  "properties": {
    "iso:country": "GB",
    "wof:name": "PL6 7ND",
    "wof:placetype": "postalcode"
  },
  "geometry": {"coordinates":[-4.097908,50.426036],"type":"Point"}
}
