{
  "type": "Feature",
  "properties": {
    "iso:country": "GB",
    "wof:name": "CO6 2EG",
    "wof:placetype": "postalcode"
  },
  "geometry": {"coordinates":[0.74709,51.908179],"type":"Point"}
}
