{
  "type": "Feature",
  "properties": {
    "iso:country":"GB",
    "wof:name":"CO6 2EG",
    "wof:placetype":"postalcode"
},
  "geometry": {"coordinates":[0.74580185714917,51.90802593757387],"type":"Point"}
}