{
  "type": "Feature",
  "properties": {
    "date:inception_lower":"2012-03-01",
    "date:inception_upper":"2012-03-31",
    "iso:country":"GB",
    "wof:name":"RM16 3AY",
    "wof:placetype":"postalcode"
},
  "geometry": {"coordinates":[0.398582,51.511161],"type":"Point"}
}