{
  "type": "Feature",
  "properties": {
    "iso:country":"GB",
    "wof:name":"RM16 3AY",
    "wof:placetype":"postalcode"
},
  "geometry": {"coordinates":[0.39855185375967,51.51116008445541],"type":"Point"}
}