{
  "type": "Feature",
  "properties": {
    "iso:country": "GB",
    "wof:name": "RM16 3AY",
    "wof:placetype": "postalcode"
  },
  "geometry": {"coordinates":[0.399918,51.511629],"type":"Point"}
}
