{
  "type": "Feature",
  "properties": {
    "iso:country": "GB",
    "wof:name": "RM16 3AY",
    "wof:placetype": "postalcode"
  },
  "geometry": {"coordinates":[0.398582,51.511161],"type":"Point"}
}
