{
  "type": "Feature",
  "properties": {
    "date:inception_lower":"1980-01-01",
    "date:inception_upper":"1980-01-31",
    "iso:country":"GB",
    "wof:name":"BD22 0LE",
    "wof:placetype":"postalcode"
},
  "geometry": {"coordinates":[-2.043992,53.900682],"type":"Point"}
}