{
  "type": "Feature",
  "properties": {
    "iso:country": "GB",
    "wof:name": "BD22 0LE",
    "wof:placetype": "postalcode"
  },
  "geometry": {"coordinates":[-2.043992,53.900682],"type":"Point"}
}
