{
  "type": "Feature",
  "properties": {
    "iso:country":"GB",
    "wof:name":"BD22 0LE",
    "wof:placetype":"postalcode"
},
  "geometry": {"coordinates":[-2.04399210680019,53.9006819474771],"type":"Point"}
}