{
  "type": "Feature",
  "properties": {
    "iso:country":"GB",
    "wof:name":"G69 7TQ",
    "wof:placetype":"postalcode"
},
  "geometry": {"coordinates":[-4.07134923062071,55.85943756289206],"type":"Point"}
}