{
  "type": "Feature",
  "properties": {
    "date:inception_lower": "2003-10-01",
    "date:inception_upper": "2003-10-01",
    "iso:country": "GB",
    "wof:name": "G69 7TQ",
    "wof:placetype": "postalcode"
  },
  "geometry": {"coordinates":[-4.071349,55.859438],"type":"Point"}
}
