{
  "type": "Feature",
  "properties": {
    "iso:country": "GB",
    "wof:name": "G69 7TQ",
    "wof:placetype": "postalcode"
  },
  "geometry": {"coordinates":[-4.071349,55.859438],"type":"Point"}
}
