{
  "type": "Feature",
  "properties": {
    "iso:country": "GB",
    "wof:name": "SS0 8EE",
    "wof:placetype": "postalcode"
  },
  "geometry": {"coordinates":[0.685935,51.536227],"type":"Point"}
}
