{
  "type": "Feature",
  "properties": {
    "date:inception_lower":"1986-07-01",
    "date:inception_upper":"1986-07-31",
    "iso:country":"GB",
    "wof:name":"SS0 8EE",
    "wof:placetype":"postalcode"
},
  "geometry": {"coordinates":[0.685935,51.536227],"type":"Point"}
}