{
  "type": "Feature",
  "properties": {
    "iso:country":"GB",
    "wof:name":"HA2 9UH",
    "wof:placetype":"postalcode"
},
  "geometry": {"coordinates":[-0.36785334554706,51.57026200030385],"type":"Point"}
}