{
  "type": "Feature",
  "properties": {
    "iso:country": "GB",
    "wof:name": "HA2 9UH",
    "wof:placetype": "postalcode"
  },
  "geometry": {"coordinates":[-0.367853,51.570262],"type":"Point"}
}
