{
  "type": "Feature",
  "properties": {
    "iso:country":"GB",
    "wof:name":"KA19 7SE",
    "wof:placetype":"postalcode"
},
  "geometry": {"coordinates":[-4.6804654317561,55.30298245212703],"type":"Point"}
}