{
  "type": "Feature",
  "properties": {
    "iso:country":"GB",
    "wof:name":"BN2 4TS",
    "wof:placetype":"postalcode"
},
  "geometry": {"coordinates":[-0.11106409043899,50.84690039820612],"type":"Point"}
}