{
  "type": "Feature",
  "properties": {
    "iso:country": "GB",
    "wof:name": "EX17 5EY",
    "wof:placetype": "postalcode"
  },
  "geometry": {"coordinates":[-3.751704,50.767149],"type":"Point"}
}
