{
  "type": "Feature",
  "properties": {
    "date:inception_lower":"1999-06-01",
    "date:inception_upper":"1999-06-30",
    "iso:country":"GB",
    "wof:name":"OX4 4HJ",
    "wof:placetype":"postalcode"
},
  "geometry": {"coordinates":[-1.22374,51.727941],"type":"Point"}
}