{
  "type": "Feature",
  "properties": {
    "iso:country":"GB",
    "wof:name":"OX4 4HJ",
    "wof:placetype":"postalcode"
},
  "geometry": {"coordinates":[-1.22374051007635,51.72794050775427],"type":"Point"}
}