{
  "type": "Feature",
  "properties": {
    "iso:country":"GB",
    "wof:name":"SA48 7DL",
    "wof:placetype":"postalcode"
},
  "geometry": {"coordinates":[-4.079884905693,52.11333985704035],"type":"Point"}
}