{
  "type": "Feature",
  "properties": {
    "iso:country":"GB",
    "wof:name":"G69 9LY",
    "wof:placetype":"postalcode"
},
  "geometry": {"coordinates":[-4.10272753467915,55.90250160882918],"type":"Point"}
}