{
  "type": "Feature",
  "properties": {
    "date:inception_lower": "2020-12-01",
    "date:inception_upper": "2020-12-01",
    "iso:country": "GB",
    "wof:name": "BS49 4FX",
    "wof:placetype": "postalcode"
  },
  "geometry": {"coordinates":[-2.839659,51.399108],"type":"Point"}
}
