{
  "type": "Feature",
  "properties": {
    "iso:country": "GB",
    "wof:name": "SE14 6TU",
    "wof:placetype": "postalcode"
  },
  "geometry": {"coordinates":[-0.029426,51.473783],"type":"Point"}
}
