{
  "type": "Feature",
  "properties": {
    "iso:country":"GB",
    "wof:name":"SE14 6TU",
    "wof:placetype":"postalcode"
},
  "geometry": {"coordinates":[-0.02942635572202,51.47378257939727],"type":"Point"}
}