{
  "type": "Feature",
  "properties": {
    "iso:country":"GB",
    "wof:name":"BS22 7FH",
    "wof:placetype":"postalcode"
},
  "geometry": {"coordinates":[-2.91221110087522,51.37270720379799],"type":"Point"}
}