{
  "type": "Feature",
  "properties": {
    "iso:country":"GB",
    "wof:name":"PE22 9RQ",
    "wof:placetype":"postalcode"
},
  "geometry": {"coordinates":[0.07514109435384,53.05761298523011],"type":"Point"}
}