{
  "type": "Feature",
  "properties": {
    "iso:country": "GB",
    "wof:name": "PE22 9RQ",
    "wof:placetype": "postalcode"
  },
  "geometry": {"coordinates":[0.075141,53.057613],"type":"Point"}
}
