{
  "type": "Feature",
  "properties": {
    "iso:country": "GB",
    "wof:name": "LS27 0DE",
    "wof:placetype": "postalcode"
  },
  "geometry": {"coordinates":[-1.603604,53.73757],"type":"Point"}
}
