{
  "type": "Feature",
  "properties": {
    "iso:country":"GB",
    "wof:name":"HA3 7FD",
    "wof:placetype":"postalcode"
},
  "geometry": {"coordinates":[-0.33382946361655,51.59429660430764],"type":"Point"}
}