{
  "type": "Feature",
  "properties": {
    "iso:country":"GB",
    "wof:name":"SE18 7DE",
    "wof:placetype":"postalcode"
},
  "geometry": {"coordinates":[0.07707959755252,51.48814011901139],"type":"Point"}
}