{
  "type": "Feature",
  "properties": {
    "date:inception_lower": "1996-06-01",
    "date:inception_upper": "1996-06-01",
    "iso:country": "GB",
    "wof:name": "TW19 5DY",
    "wof:placetype": "postalcode"
  },
  "geometry": {"coordinates":[-0.559886,51.457686],"type":"Point"}
}
