{
  "type": "Feature",
  "properties": {
    "iso:country": "GB",
    "wof:name": "MK18 3LG",
    "wof:placetype": "postalcode"
  },
  "geometry": {"coordinates":[-0.844554,51.909633],"type":"Point"}
}
