{
  "type": "Feature",
  "properties": {
    "iso:country":"GB",
    "wof:name":"CO12 5JG",
    "wof:placetype":"postalcode"
},
  "geometry": {"coordinates":[1.22342513824565,51.91625825833874],"type":"Point"}
}