{
  "type": "Feature",
  "properties": {
    "date:inception_lower": "2017-10-01",
    "date:inception_upper": "2017-10-01",
    "iso:country": "GB",
    "wof:name": "BR8 8FF",
    "wof:placetype": "postalcode"
  },
  "geometry": {"coordinates":[0.177658,51.392707],"type":"Point"}
}
