{
  "type": "Feature",
  "properties": {
    "iso:country": "GB",
    "wof:name": "BR8 8FF",
    "wof:placetype": "postalcode"
  },
  "geometry": {"coordinates":[0.177658,51.392707],"type":"Point"}
}
