{
  "type": "Feature",
  "properties": {
    "iso:country":"GB",
    "wof:name":"SW18 5BL",
    "wof:placetype":"postalcode"
},
  "geometry": {"coordinates":[-0.20478458508964,51.44334430968038],"type":"Point"}
}