{
  "type": "Feature",
  "properties": {
    "iso:country":"GB",
    "wof:name":"E1 5DN",
    "wof:placetype":"postalcode"
},
  "geometry": {"coordinates":[-0.06066708997866,51.52247695373704],"type":"Point"}
}