{
  "type": "Feature",
  "properties": {
    "iso:country": "GB",
    "wof:name": "BH7 6HN",
    "wof:placetype": "postalcode"
  },
  "geometry": {"coordinates":[-1.834277,50.728941],"type":"Point"}
}
