{
  "type": "Feature",
  "properties": {
    "iso:country":"GB",
    "wof:name":"BH7 6HN",
    "wof:placetype":"postalcode"
},
  "geometry": {"coordinates":[-1.83427698644983,50.72894123483182],"type":"Point"}
}