{
  "type": "Feature",
  "properties": {
    "iso:country":"GB",
    "wof:name":"KY8 2AD",
    "wof:placetype":"postalcode"
},
  "geometry": {"coordinates":[-3.02275269446984,56.19036423992538],"type":"Point"}
}