{
  "type": "Feature",
  "properties": {
    "iso:country":"GB",
    "wof:name":"WF9 2LX",
    "wof:placetype":"postalcode"
},
  "geometry": {"coordinates":[-1.30019076628378,53.58657159310941],"type":"Point"}
}