{
  "type": "Feature",
  "properties": {
    "date:inception_lower": "1980-01-01",
    "date:inception_upper": "1980-01-01",
    "iso:country": "GB",
    "wof:name": "WF9 2LX",
    "wof:placetype": "postalcode"
  },
  "geometry": {"coordinates":[-1.300191,53.586572],"type":"Point"}
}
