{
  "type": "Feature",
  "properties": {
    "iso:country": "GB",
    "wof:name": "WF9 2LX",
    "wof:placetype": "postalcode"
  },
  "geometry": {"coordinates":[-1.300191,53.586572],"type":"Point"}
}
