{
  "type": "Feature",
  "properties": {
    "iso:country":"GB",
    "wof:name":"NE30 4DY",
    "wof:placetype":"postalcode"
},
  "geometry": {"coordinates":[-1.42480609982399,55.01776838309659],"type":"Point"}
}