{
  "type": "Feature",
  "properties": {
    "iso:country":"GB",
    "wof:name":"SO41 9PA",
    "wof:placetype":"postalcode"
},
  "geometry": {"coordinates":[-1.5498412399276,50.76049246483859],"type":"Point"}
}