{
  "type": "Feature",
  "properties": {
    "iso:country": "GB",
    "wof:name": "SO41 9PA",
    "wof:placetype": "postalcode"
  },
  "geometry": {"coordinates":[-1.549841,50.760492],"type":"Point"}
}
