{
  "type": "Feature",
  "properties": {
    "date:inception_lower": "2010-08-01",
    "date:inception_upper": "2010-08-01",
    "iso:country": "GB",
    "wof:name": "SO41 9PA",
    "wof:placetype": "postalcode"
  },
  "geometry": {"coordinates":[-1.549841,50.760492],"type":"Point"}
}
