{
  "type": "Feature",
  "properties": {
    "date:inception_lower": "2020-08-01",
    "date:inception_upper": "2020-08-01",
    "iso:country": "GB",
    "wof:name": "HD2 2FY",
    "wof:placetype": "postalcode"
  },
  "geometry": {"coordinates":[-1.81853,53.666853],"type":"Point"}
}
