{
  "type": "Feature",
  "properties": {
    "iso:country": "GB",
    "wof:name": "LA3 2LH",
    "wof:placetype": "postalcode"
  },
  "geometry": {"coordinates":[-2.888646,54.041307],"type":"Point"}
}
