{
  "type": "Feature",
  "properties": {
    "iso:country":"GB",
    "wof:name":"LA3 2LH",
    "wof:placetype":"postalcode"
},
  "geometry": {"coordinates":[-2.88864608587876,54.04130692694274],"type":"Point"}
}