{
  "type": "Feature",
  "properties": {
    "iso:country":"GB",
    "wof:name":"M13 9AR",
    "wof:placetype":"postalcode"
},
  "geometry": {"coordinates":[-2.21349544205513,53.46299267831322],"type":"Point"}
}