{
  "type": "Feature",
  "properties": {
    "iso:country": "GB",
    "wof:name": "M13 9AR",
    "wof:placetype": "postalcode"
  },
  "geometry": {"coordinates":[-2.213495,53.462993],"type":"Point"}
}
