{
  "type": "Feature",
  "properties": {
    "date:inception_lower": "2000-12-01",
    "date:inception_upper": "2000-12-01",
    "iso:country": "GB",
    "wof:name": "TF9 3TT",
    "wof:placetype": "postalcode"
  },
  "geometry": {"coordinates":[-2.492383,52.910557],"type":"Point"}
}
