{
  "type": "Feature",
  "properties": {
    "iso:country":"GB",
    "wof:name":"EH39 4LF",
    "wof:placetype":"postalcode"
},
  "geometry": {"coordinates":[-2.71476860511215,56.05813457837119],"type":"Point"}
}