{
  "type": "Feature",
  "properties": {
    "iso:country": "GB",
    "wof:name": "BD18 1AF",
    "wof:placetype": "postalcode"
  },
  "geometry": {"coordinates":[-1.761723,53.826678],"type":"Point"}
}
