{
  "type": "Feature",
  "properties": {
    "iso:country":"GB",
    "wof:name":"BD18 1AF",
    "wof:placetype":"postalcode"
},
  "geometry": {"coordinates":[-1.76171981421547,53.82666370249676],"type":"Point"}
}