{
  "type": "Feature",
  "properties": {
    "date:inception_lower": "1980-01-01",
    "date:inception_upper": "1980-01-01",
    "iso:country": "GB",
    "wof:name": "BD18 1AF",
    "wof:placetype": "postalcode"
  },
  "geometry": {"coordinates":[-1.761967,53.826652],"type":"Point"}
}
