{
  "type": "Feature",
  "properties": {
    "iso:country":"GB",
    "wof:name":"EX10 8SD",
    "wof:placetype":"postalcode"
},
  "geometry": {"coordinates":[-3.25062365075037,50.68261697864288],"type":"Point"}
}