{
  "type": "Feature",
  "properties": {
    "iso:country": "GB",
    "wof:name": "MK18 3DS",
    "wof:placetype": "postalcode"
  },
  "geometry": {"coordinates":[-0.882418,51.943905],"type":"Point"}
}
