{
  "type": "Feature",
  "properties": {
    "iso:country":"GB",
    "wof:name":"SN16 9HZ",
    "wof:placetype":"postalcode"
},
  "geometry": {"coordinates":[-2.09147495429297,51.58665207337594],"type":"Point"}
}