{
  "type": "Feature",
  "properties": {
    "iso:country":"GB",
    "wof:name":"PO18 8LL",
    "wof:placetype":"postalcode"
},
  "geometry": {"coordinates":[-0.85787394326408,50.83213807492317],"type":"Point"}
}