{
  "type": "Feature",
  "properties": {
    "date:inception_lower":"1980-01-01",
    "date:inception_upper":"1980-01-31",
    "iso:country":"GB",
    "wof:name":"GU21 5TH",
    "wof:placetype":"postalcode"
},
  "geometry": {"coordinates":[-0.537975,51.331523],"type":"Point"}
}