{
  "type": "Feature",
  "properties": {
    "iso:country":"GB",
    "wof:name":"LN6 7JY",
    "wof:placetype":"postalcode"
},
  "geometry": {"coordinates":[-0.57811638869948,53.20225733230811],"type":"Point"}
}