{
  "type": "Feature",
  "properties": {
    "iso:country":"GB",
    "wof:name":"TW14 9NS",
    "wof:placetype":"postalcode"
},
  "geometry": {"coordinates":[-0.41835084996273,51.45309248381272],"type":"Point"}
}