{
  "type": "Feature",
  "properties": {
    "date:inception_lower": "1980-01-01",
    "date:inception_upper": "1980-01-01",
    "iso:country": "GB",
    "wof:name": "WD3 4LR",
    "wof:placetype": "postalcode"
  },
  "geometry": {"coordinates":[-0.468385,51.671307],"type":"Point"}
}
