{
  "type": "Feature",
  "properties": {
    "date:inception_lower":"1985-10-01",
    "date:inception_upper":"1985-10-31",
    "iso:country":"GB",
    "wof:name":"TS26 0PY",
    "wof:placetype":"postalcode"
},
  "geometry": {"coordinates":[-1.252207,54.692719],"type":"Point"}
}