{
  "type": "Feature",
  "properties": {
    "iso:country":"GB",
    "wof:name":"TS26 0PY",
    "wof:placetype":"postalcode"
},
  "geometry": {"coordinates":[-1.25220713507339,54.69271886618111],"type":"Point"}
}