{
  "type": "Feature",
  "properties": {
    "iso:country":"GB",
    "wof:name":"RM6 5LU",
    "wof:placetype":"postalcode"
},
  "geometry": {"coordinates":[0.13141123476366,51.58499783716799],"type":"Point"}
}