{
  "type": "Feature",
  "properties": {
    "date:inception_lower":"2015-08-01",
    "date:inception_upper":"2015-08-31",
    "iso:country":"GB",
    "wof:name":"CA28 7UN",
    "wof:placetype":"postalcode"
},
  "geometry": {"coordinates":[-3.587504,54.550218],"type":"Point"}
}