{
  "type": "Feature",
  "properties": {
    "date:inception_lower": "2022-08-01",
    "date:inception_upper": "2022-08-01",
    "iso:country": "GB",
    "wof:name": "HG3 2FJ",
    "wof:placetype": "postalcode"
  },
  "geometry": {"coordinates":[-1.6015,54.017965],"type":"Point"}
}
