{
  "type": "Feature",
  "properties": {
    "iso:country":"GB",
    "wof:name":"SP11 6JX",
    "wof:placetype":"postalcode"
},
  "geometry": {"coordinates":[-1.47425605737575,51.24136412893209],"type":"Point"}
}