{
  "type": "Feature",
  "properties": {
    "iso:country": "GB",
    "wof:name": "SL6 9ES",
    "wof:placetype": "postalcode"
  },
  "geometry": {"coordinates":[-0.730255,51.558983],"type":"Point"}
}
