{
  "type": "Feature",
  "properties": {
    "date:inception_lower":"2013-07-01",
    "date:inception_upper":"2013-07-31",
    "iso:country":"GB",
    "wof:name":"CW11 2XP",
    "wof:placetype":"postalcode"
},
  "geometry": {"coordinates":[-2.276957,53.153353],"type":"Point"}
}