{
  "type": "Feature",
  "properties": {
    "iso:country":"GB",
    "wof:name":"CW11 2XP",
    "wof:placetype":"postalcode"
},
  "geometry": {"coordinates":[-2.27695715015031,53.15335349091806],"type":"Point"}
}