{
  "type": "Feature",
  "properties": {
    "iso:country":"GB",
    "wof:name":"ME4 6UP",
    "wof:placetype":"postalcode"
},
  "geometry": {"coordinates":[0.51255575493429,51.37432904275658],"type":"Point"}
}