{
  "type": "Feature",
  "properties": {
    "date:inception_lower": "1980-01-01",
    "date:inception_upper": "1980-01-01",
    "iso:country": "GB",
    "wof:name": "ME4 6UP",
    "wof:placetype": "postalcode"
  },
  "geometry": {"coordinates":[0.512556,51.374329],"type":"Point"}
}
