{
  "type": "Feature",
  "properties": {
    "iso:country":"GB",
    "wof:name":"W1W 6SA",
    "wof:placetype":"postalcode"
},
  "geometry": {"coordinates":[-0.14184993469809,51.52076963396096],"type":"Point"}
}