{
  "type": "Feature",
  "properties": {
    "iso:country": "GB",
    "wof:name": "W1W 6SA",
    "wof:placetype": "postalcode"
  },
  "geometry": {"coordinates":[-0.14185,51.52077],"type":"Point"}
}
