{
  "type": "Feature",
  "properties": {
    "iso:country": "GB",
    "wof:name": "BB8 9NT",
    "wof:placetype": "postalcode"
  },
  "geometry": {"coordinates":[-2.184,53.854108],"type":"Point"}
}
