{
  "type": "Feature",
  "properties": {
    "iso:country":"GB",
    "wof:name":"BB8 9NT",
    "wof:placetype":"postalcode"
},
  "geometry": {"coordinates":[-2.18399981371957,53.85410850116872],"type":"Point"}
}