{
  "type": "Feature",
  "properties": {
    "iso:country":"GB",
    "wof:name":"ME16 0NN",
    "wof:placetype":"postalcode"
},
  "geometry": {"coordinates":[0.49390755546813,51.28658147137494],"type":"Point"}
}