{
  "type": "Feature",
  "properties": {
    "iso:country":"GB",
    "wof:name":"W5 4UU",
    "wof:placetype":"postalcode"
},
  "geometry": {"coordinates":[-0.31348397057484,51.49608917491832],"type":"Point"}
}