{
  "type": "Feature",
  "properties": {
    "iso:country":"GB",
    "wof:name":"DT7 3TW",
    "wof:placetype":"postalcode"
},
  "geometry": {"coordinates":[-2.95070020035048,50.73399375051227],"type":"Point"}
}