{
  "type": "Feature",
  "properties": {
    "iso:country":"GB",
    "wof:name":"BH1 4HP",
    "wof:placetype":"postalcode"
},
  "geometry": {"coordinates":[-1.84397954460962,50.72978192335652],"type":"Point"}
}