{
  "type": "Feature",
  "properties": {
    "iso:country": "GB",
    "wof:name": "BS21 6PW",
    "wof:placetype": "postalcode"
  },
  "geometry": {"coordinates":[-2.85704,51.431742],"type":"Point"}
}
