{
  "type": "Feature",
  "properties": {
    "iso:country":"GB",
    "wof:name":"GU32 3JS",
    "wof:placetype":"postalcode"
},
  "geometry": {"coordinates":[-0.93637411786131,51.00182538226132],"type":"Point"}
}