{
  "type": "Feature",
  "properties": {
    "iso:country": "GB",
    "wof:name": "RG9 6TL",
    "wof:placetype": "postalcode"
  },
  "geometry": {"coordinates":[-0.868388,51.561705],"type":"Point"}
}
