{
  "type": "Feature",
  "properties": {
    "date:inception_lower": "2009-06-01",
    "date:inception_upper": "2009-06-01",
    "iso:country": "GB",
    "wof:name": "NG12 3RH",
    "wof:placetype": "postalcode"
  },
  "geometry": {"coordinates":[-1.040165,52.905971],"type":"Point"}
}
