{
  "type": "Feature",
  "properties": {
    "date:inception_lower": "1998-06-01",
    "date:inception_upper": "1998-06-01",
    "iso:country": "GB",
    "wof:name": "YO26 6PY",
    "wof:placetype": "postalcode"
  },
  "geometry": {"coordinates":[-1.150485,53.977167],"type":"Point"}
}
