{
  "type": "Feature",
  "properties": {
    "iso:country":"GB",
    "wof:name":"YO26 6PY",
    "wof:placetype":"postalcode"
},
  "geometry": {"coordinates":[-1.15046176683824,53.97714981326074],"type":"Point"}
}