{
  "type": "Feature",
  "properties": {
    "date:inception_lower": "1980-01-01",
    "date:inception_upper": "1980-01-01",
    "iso:country": "GB",
    "wof:name": "BS5 0BY",
    "wof:placetype": "postalcode"
  },
  "geometry": {"coordinates":[-2.573114,51.458326],"type":"Point"}
}
