{
  "type": "Feature",
  "properties": {
    "iso:country":"GB",
    "wof:name":"BS5 0BY",
    "wof:placetype":"postalcode"
},
  "geometry": {"coordinates":[-2.57302645307592,51.45833651221574],"type":"Point"}
}