{
  "type": "Feature",
  "properties": {
    "iso:country": "GB",
    "wof:name": "SP4 6NS",
    "wof:placetype": "postalcode"
  },
  "geometry": {"coordinates":[-1.82596,51.126176],"type":"Point"}
}
