{
  "type": "Feature",
  "properties": {
    "iso:country":"GB",
    "wof:name":"SP4 6NS",
    "wof:placetype":"postalcode"
},
  "geometry": {"coordinates":[-1.82595995004975,51.12617553342584],"type":"Point"}
}