{
  "type": "Feature",
  "properties": {
    "iso:country":"GB",
    "wof:name":"EX34 0LG",
    "wof:placetype":"postalcode"
},
  "geometry": {"coordinates":[-4.02531264123493,51.19930217340883],"type":"Point"}
}