{
  "type": "Feature",
  "properties": {
    "iso:country": "GB",
    "wof:name": "EX34 0LG",
    "wof:placetype": "postalcode"
  },
  "geometry": {"coordinates":[-4.025364,51.199346],"type":"Point"}
}
