{
  "type": "Feature",
  "properties": {
    "iso:country": "GB",
    "wof:name": "IP29 5HT",
    "wof:placetype": "postalcode"
  },
  "geometry": {"coordinates":[0.585534,52.205921],"type":"Point"}
}
