{
  "type": "Feature",
  "properties": {
    "iso:country": "GB",
    "wof:name": "SM6 8EX",
    "wof:placetype": "postalcode"
  },
  "geometry": {"coordinates":[-0.143372,51.364089],"type":"Point"}
}
