{
  "type": "Feature",
  "properties": {
    "iso:country":"GB",
    "wof:name":"SM6 8EX",
    "wof:placetype":"postalcode"
},
  "geometry": {"coordinates":[-0.14337191954875,51.36408866599792],"type":"Point"}
}