{
  "type": "Feature",
  "properties": {
    "iso:country":"GB",
    "wof:name":"W1B 5AH",
    "wof:placetype":"postalcode"
},
  "geometry": {"coordinates":[-0.13999245603322,51.5136451099922],"type":"Point"}
}