{
  "type": "Feature",
  "properties": {
    "iso:country":"GB",
    "wof:name":"B21 9BN",
    "wof:placetype":"postalcode"
},
  "geometry": {"coordinates":[-1.92778667535985,52.50217250250486],"type":"Point"}
}