{
  "type": "Feature",
  "properties": {
    "iso:country":"GB",
    "wof:name":"CB4 1PD",
    "wof:placetype":"postalcode"
},
  "geometry": {"coordinates":[0.14871174326654,52.22052223884867],"type":"Point"}
}