{
  "type": "Feature",
  "properties": {
    "iso:country":"GB",
    "wof:name":"PL21 0JW",
    "wof:placetype":"postalcode"
},
  "geometry": {"coordinates":[-3.90769095358868,50.39124866573177],"type":"Point"}
}