{
  "type": "Feature",
  "properties": {
    "iso:country":"GB",
    "wof:name":"SP2 9NQ",
    "wof:placetype":"postalcode"
},
  "geometry": {"coordinates":[-1.8211492931882,51.07299804718601],"type":"Point"}
}