{
  "type": "Feature",
  "properties": {
    "iso:country": "GB",
    "wof:name": "N4 4AT",
    "wof:placetype": "postalcode"
  },
  "geometry": {"coordinates":[-0.118236,51.571959],"type":"Point"}
}
