{
  "type": "Feature",
  "properties": {
    "iso:country": "GB",
    "wof:name": "DA14 5LB",
    "wof:placetype": "postalcode"
  },
  "geometry": {"coordinates":[0.129152,51.420712],"type":"Point"}
}
