{
  "type": "Feature",
  "properties": {
    "date:inception_lower":"1980-01-01",
    "date:inception_upper":"1980-01-31",
    "iso:country":"GB",
    "wof:name":"DA14 5LB",
    "wof:placetype":"postalcode"
},
  "geometry": {"coordinates":[0.129152,51.420712],"type":"Point"}
}