{
  "type": "Feature",
  "properties": {
    "date:inception_lower": "1980-01-01",
    "date:inception_upper": "1980-01-01",
    "iso:country": "GB",
    "wof:name": "BS25 1RQ",
    "wof:placetype": "postalcode"
  },
  "geometry": {"coordinates":[-2.795996,51.305324],"type":"Point"}
}
