{
  "type": "Feature",
  "properties": {
    "iso:country": "GB",
    "wof:name": "BS25 1RQ",
    "wof:placetype": "postalcode"
  },
  "geometry": {"coordinates":[-2.795996,51.305324],"type":"Point"}
}
