{
  "type": "Feature",
  "properties": {
    "iso:country": "GB",
    "wof:name": "SE10 8DZ",
    "wof:placetype": "postalcode"
  },
  "geometry": {"coordinates":[-0.019946,51.47356],"type":"Point"}
}
