{
  "type": "Feature",
  "properties": {
    "date:inception_lower":"1997-12-01",
    "date:inception_upper":"1997-12-31",
    "iso:country":"GB",
    "wof:name":"SE10 8DZ",
    "wof:placetype":"postalcode"
},
  "geometry": {"coordinates":[-0.019946,51.47356],"type":"Point"}
}