{
  "type": "Feature",
  "properties": {
    "iso:country":"GB",
    "wof:name":"SE10 8DZ",
    "wof:placetype":"postalcode"
},
  "geometry": {"coordinates":[-0.01994652614637,51.47355991583341],"type":"Point"}
}