{
  "type": "Feature",
  "properties": {
    "iso:country": "GB",
    "wof:name": "UB4 0QL",
    "wof:placetype": "postalcode"
  },
  "geometry": {"coordinates":[-0.411389,51.524074],"type":"Point"}
}
