{
  "type": "Feature",
  "properties": {
    "iso:country": "GB",
    "wof:name": "KA12 2ZZ",
    "wof:placetype": "postalcode"
  },
  "geometry": {"coordinates":[-4.668317,55.615786],"type":"Point"}
}
