{
  "type": "Feature",
  "properties": {
    "iso:country":"GB",
    "wof:name":"KA12 2ZZ",
    "wof:placetype":"postalcode"
},
  "geometry": {"coordinates":[-4.66831706589175,55.61578552429801],"type":"Point"}
}