{
  "type": "Feature",
  "properties": {
    "date:inception_lower":"2016-03-01",
    "date:inception_upper":"2016-03-31",
    "iso:country":"GB",
    "wof:name":"KA12 2ZZ",
    "wof:placetype":"postalcode"
},
  "geometry": {"coordinates":[-4.668317,55.615786],"type":"Point"}
}