{
  "type": "Feature",
  "properties": {
    "date:inception_lower": "2021-06-01",
    "date:inception_upper": "2021-06-01",
    "iso:country": "GB",
    "wof:name": "KA12 2ZZ",
    "wof:placetype": "postalcode"
  },
  "geometry": {"coordinates":[-4.668296,55.615784],"type":"Point"}
}
