{
  "type": "Feature",
  "properties": {
    "iso:country": "GB",
    "wof:name": "SA44 5DG",
    "wof:placetype": "postalcode"
  },
  "geometry": {"coordinates":[-4.34951,52.022017],"type":"Point"}
}
