{
  "type": "Feature",
  "properties": {
    "iso:country":"GB",
    "wof:name":"G65 9BW",
    "wof:placetype":"postalcode"
},
  "geometry": {"coordinates":[-4.0733313117297,55.97692696782259],"type":"Point"}
}