{
  "type": "Feature",
  "properties": {
    "iso:country": "GB",
    "wof:name": "L16 5EY",
    "wof:placetype": "postalcode"
  },
  "geometry": {"coordinates":[-2.880774,53.394944],"type":"Point"}
}
