{
  "type": "Feature",
  "properties": {
    "date:inception_lower": "1980-01-01",
    "date:inception_upper": "1980-01-01",
    "iso:country": "GB",
    "wof:name": "L16 5EY",
    "wof:placetype": "postalcode"
  },
  "geometry": {"coordinates":[-2.880774,53.394944],"type":"Point"}
}
