{
  "type": "Feature",
  "properties": {
    "iso:country":"GB",
    "wof:name":"NE32 3JA",
    "wof:placetype":"postalcode"
},
  "geometry": {"coordinates":[-1.49271779100763,54.9813793008813],"type":"Point"}
}