{
  "type": "Feature",
  "properties": {
    "iso:country": "GB",
    "wof:name": "NE32 3JA",
    "wof:placetype": "postalcode"
  },
  "geometry": {"coordinates":[-1.492718,54.981379],"type":"Point"}
}
