{
  "type": "Feature",
  "properties": {
    "iso:country": "GB",
    "wof:name": "NW9 0FL",
    "wof:placetype": "postalcode"
  },
  "geometry": {"coordinates":[-0.258752,51.592581],"type":"Point"}
}
