{
  "type": "Feature",
  "properties": {
    "iso:country": "GB",
    "wof:name": "HD2 2BZ",
    "wof:placetype": "postalcode"
  },
  "geometry": {"coordinates":[-1.805338,53.661991],"type":"Point"}
}
