{
  "type": "Feature",
  "properties": {
    "iso:country":"GB",
    "wof:name":"CF10 5NE",
    "wof:placetype":"postalcode"
},
  "geometry": {"coordinates":[-3.17709047900349,51.46899624622595],"type":"Point"}
}