{
  "type": "Feature",
  "properties": {
    "iso:country":"GB",
    "wof:name":"RG7 6AF",
    "wof:placetype":"postalcode"
},
  "geometry": {"coordinates":[-1.13561496343192,51.4384354563818],"type":"Point"}
}