{
  "type": "Feature",
  "properties": {
    "date:inception_lower":"1980-01-01",
    "date:inception_upper":"1980-01-31",
    "iso:country":"GB",
    "wof:name":"RG7 6AF",
    "wof:placetype":"postalcode"
},
  "geometry": {"coordinates":[-1.135522,51.438481],"type":"Point"}
}