{
  "type": "Feature",
  "properties": {
    "iso:country":"GB",
    "wof:name":"NG21 9NB",
    "wof:placetype":"postalcode"
},
  "geometry": {"coordinates":[-1.07336089544402,53.19704207893137],"type":"Point"}
}