{
  "type": "Feature",
  "properties": {
    "date:inception_lower": "1980-01-01",
    "date:inception_upper": "1980-01-01",
    "iso:country": "GB",
    "wof:name": "NG21 9NB",
    "wof:placetype": "postalcode"
  },
  "geometry": {"coordinates":[-1.073361,53.197042],"type":"Point"}
}
