{
  "type": "Feature",
  "properties": {
    "iso:country": "GB",
    "wof:name": "YO8 5NE",
    "wof:placetype": "postalcode"
  },
  "geometry": {"coordinates":[-1.040736,53.801917],"type":"Point"}
}
