{
  "type": "Feature",
  "properties": {
    "iso:country":"GB",
    "wof:name":"YO8 5NE",
    "wof:placetype":"postalcode"
},
  "geometry": {"coordinates":[-1.040735980641,53.80191718428366],"type":"Point"}
}