{
  "type": "Feature",
  "properties": {
    "iso:country":"GB",
    "wof:name":"ME14 5JA",
    "wof:placetype":"postalcode"
},
  "geometry": {"coordinates":[0.5377280029322,51.28458723681445],"type":"Point"}
}