{
  "type": "Feature",
  "properties": {
    "date:inception_lower":"1980-01-01",
    "date:inception_upper":"1980-01-31",
    "iso:country":"GB",
    "wof:name":"ME14 5JA",
    "wof:placetype":"postalcode"
},
  "geometry": {"coordinates":[0.537728,51.284587],"type":"Point"}
}