{
  "type": "Feature",
  "properties": {
    "iso:country":"GB",
    "wof:name":"RG20 0BE",
    "wof:placetype":"postalcode"
},
  "geometry": {"coordinates":[-1.41019259484063,51.36456236144309],"type":"Point"}
}