{
  "type": "Feature",
  "properties": {
    "iso:country":"GB",
    "wof:name":"CM5 0QL",
    "wof:placetype":"postalcode"
},
  "geometry": {"coordinates":[0.33781295227151,51.73139296763307],"type":"Point"}
}