{
  "type": "Feature",
  "properties": {
    "date:inception_lower": "1980-01-01",
    "date:inception_upper": "1980-01-01",
    "iso:country": "GB",
    "wof:name": "CM5 0QL",
    "wof:placetype": "postalcode"
  },
  "geometry": {"coordinates":[0.341365,51.730681],"type":"Point"}
}
