{
  "type": "Feature",
  "properties": {
    "date:inception_lower": "1990-08-01",
    "date:inception_upper": "1990-08-01",
    "iso:country": "GB",
    "wof:name": "AB34 4YT",
    "wof:placetype": "postalcode"
  },
  "geometry": {"coordinates":[-2.889365,57.110214],"type":"Point"}
}
