{
  "type": "Feature",
  "properties": {
    "iso:country":"GB",
    "wof:name":"AB34 4YT",
    "wof:placetype":"postalcode"
},
  "geometry": {"coordinates":[-2.8893652262136,57.11021439621207],"type":"Point"}
}