{
  "type": "Feature",
  "properties": {
    "date:inception_lower": "1980-01-01",
    "date:inception_upper": "1980-01-01",
    "iso:country": "GB",
    "wof:name": "SW1X 8BJ",
    "wof:placetype": "postalcode"
  },
  "geometry": {"coordinates":[-0.15114,51.498876],"type":"Point"}
}
