{
  "type": "Feature",
  "properties": {
    "iso:country":"GB",
    "wof:name":"SW1X 8BJ",
    "wof:placetype":"postalcode"
},
  "geometry": {"coordinates":[-0.15114009086859,51.49887582117755],"type":"Point"}
}