{
  "type": "Feature",
  "properties": {
    "iso:country":"GB",
    "wof:name":"SP5 4AD",
    "wof:placetype":"postalcode"
},
  "geometry": {"coordinates":[-1.90296399069868,51.0315416344194],"type":"Point"}
}