{
  "type": "Feature",
  "properties": {
    "iso:country":"GB",
    "wof:name":"ME1 3QX",
    "wof:placetype":"postalcode"
},
  "geometry": {"coordinates":[0.49957465519587,51.35392163485087],"type":"Point"}
}