{
  "type": "Feature",
  "properties": {
    "date:inception_lower": "1985-10-01",
    "date:inception_upper": "1985-10-01",
    "iso:country": "GB",
    "wof:name": "ME1 3QX",
    "wof:placetype": "postalcode"
  },
  "geometry": {"coordinates":[0.499575,51.353922],"type":"Point"}
}
