{
  "type": "Feature",
  "properties": {
    "iso:country":"GB",
    "wof:name":"CV10 0SY",
    "wof:placetype":"postalcode"
},
  "geometry": {"coordinates":[-1.52364478938588,52.54273441428509],"type":"Point"}
}