{
  "type": "Feature",
  "properties": {
    "iso:country":"GB",
    "wof:name":"NE4 9AL",
    "wof:placetype":"postalcode"
},
  "geometry": {"coordinates":[-1.6466072008007,54.97989248541158],"type":"Point"}
}