{
  "type": "Feature",
  "properties": {
    "iso:country":"GB",
    "wof:name":"CF15 8DL",
    "wof:placetype":"postalcode"
},
  "geometry": {"coordinates":[-3.26477665799288,51.51922927578549],"type":"Point"}
}