{
  "type": "Feature",
  "properties": {
    "iso:country": "GB",
    "wof:name": "CV6 5DH",
    "wof:placetype": "postalcode"
  },
  "geometry": {"coordinates":[-1.495747,52.422881],"type":"Point"}
}
