{
  "type": "Feature",
  "properties": {
    "date:inception_lower": "1980-01-01",
    "date:inception_upper": "1980-01-01",
    "iso:country": "GB",
    "wof:name": "CV6 5DH",
    "wof:placetype": "postalcode"
  },
  "geometry": {"coordinates":[-1.495739,52.422898],"type":"Point"}
}
