{
  "type": "Feature",
  "properties": {
    "iso:country":"GB",
    "wof:name":"OX28 1HS",
    "wof:placetype":"postalcode"
},
  "geometry": {"coordinates":[-1.48629339973642,51.79344280579615],"type":"Point"}
}