{
  "type": "Feature",
  "properties": {
    "iso:country": "GB",
    "wof:name": "DT10 1QT",
    "wof:placetype": "postalcode"
  },
  "geometry": {"coordinates":[-2.298065,50.929417],"type":"Point"}
}
