{
  "type": "Feature",
  "properties": {
    "date:inception_lower":"1998-12-01",
    "date:inception_upper":"1998-12-31",
    "iso:country":"GB",
    "wof:name":"DT10 1QT",
    "wof:placetype":"postalcode"
},
  "geometry": {"coordinates":[-2.298065,50.929417],"type":"Point"}
}