{
  "type": "Feature",
  "properties": {
    "iso:country":"GB",
    "wof:name":"DT10 1QT",
    "wof:placetype":"postalcode"
},
  "geometry": {"coordinates":[-2.2980648411441,50.92941716174555],"type":"Point"}
}