{
  "type": "Feature",
  "properties": {
    "iso:country":"GB",
    "wof:name":"DL7 0DT",
    "wof:placetype":"postalcode"
},
  "geometry": {"coordinates":[-1.51054871816478,54.42793431762716],"type":"Point"}
}