{
  "type": "Feature",
  "properties": {
    "iso:country":"GB",
    "wof:name":"RG18 9JD",
    "wof:placetype":"postalcode"
},
  "geometry": {"coordinates":[-1.26983194520329,51.42761371741331],"type":"Point"}
}