{
  "type": "Feature",
  "properties": {
    "date:inception_lower":"1980-01-01",
    "date:inception_upper":"1980-01-31",
    "iso:country":"GB",
    "wof:name":"BD20 8QN",
    "wof:placetype":"postalcode"
},
  "geometry": {"coordinates":[-2.002064,53.899045],"type":"Point"}
}