{
  "type": "Feature",
  "properties": {
    "iso:country": "GB",
    "wof:name": "BD20 8QN",
    "wof:placetype": "postalcode"
  },
  "geometry": {"coordinates":[-2.002064,53.899045],"type":"Point"}
}
