{
  "type": "Feature",
  "properties": {
    "date:inception_lower": "2021-01-01",
    "date:inception_upper": "2021-01-01",
    "iso:country": "GB",
    "wof:name": "CV7 8RZ",
    "wof:placetype": "postalcode"
  },
  "geometry": {"coordinates":[-1.593165,52.49753],"type":"Point"}
}
