{
  "type": "Feature",
  "properties": {
    "iso:country": "GB",
    "wof:name": "TA8 1QP",
    "wof:placetype": "postalcode"
  },
  "geometry": {"coordinates":[-2.992426,51.234683],"type":"Point"}
}
