{
  "type": "Feature",
  "properties": {
    "date:inception_lower":"1991-01-01",
    "date:inception_upper":"1991-01-31",
    "iso:country":"GB",
    "wof:name":"TA8 1QP",
    "wof:placetype":"postalcode"
},
  "geometry": {"coordinates":[-2.992426,51.234683],"type":"Point"}
}