{
  "type": "Feature",
  "properties": {
    "iso:country":"GB",
    "wof:name":"M20 1EA",
    "wof:placetype":"postalcode"
},
  "geometry": {"coordinates":[-2.2431677937732,53.43404685350964],"type":"Point"}
}