{
  "type": "Feature",
  "properties": {
    "date:inception_lower": "2007-09-01",
    "date:inception_upper": "2007-09-01",
    "iso:country": "GB",
    "wof:name": "SP8 5FB",
    "wof:placetype": "postalcode"
  },
  "geometry": {"coordinates":[-2.255321,51.029057],"type":"Point"}
}
