{
  "type": "Feature",
  "properties": {
    "iso:country": "GB",
    "wof:name": "SP8 5FB",
    "wof:placetype": "postalcode"
  },
  "geometry": {"coordinates":[-2.25527,51.029252],"type":"Point"}
}
