{
  "type": "Feature",
  "properties": {
    "iso:country":"GB",
    "wof:name":"SP8 5FB",
    "wof:placetype":"postalcode"
},
  "geometry": {"coordinates":[-2.25527001171474,51.0292521066564],"type":"Point"}
}