{
  "type": "Feature",
  "properties": {
    "iso:country":"GB",
    "wof:name":"CO3 9ES",
    "wof:placetype":"postalcode"
},
  "geometry": {"coordinates":[0.8515632626027,51.88062439915073],"type":"Point"}
}