{
  "type": "Feature",
  "properties": {
    "date:inception_lower":"2002-06-01",
    "date:inception_upper":"2002-06-30",
    "iso:country":"GB",
    "wof:name":"CO3 9ES",
    "wof:placetype":"postalcode"
},
  "geometry": {"coordinates":[0.851563,51.880624],"type":"Point"}
}