{
  "type": "Feature",
  "properties": {
    "iso:country":"GB",
    "wof:name":"RG21 3NU",
    "wof:placetype":"postalcode"
},
  "geometry": {"coordinates":[-1.0990239154356,51.25043515386265],"type":"Point"}
}