{
  "type": "Feature",
  "properties": {
    "date:inception_lower": "1980-01-01",
    "date:inception_upper": "1980-01-01",
    "iso:country": "GB",
    "wof:name": "DN19 7DP",
    "wof:placetype": "postalcode"
  },
  "geometry": {"coordinates":[-0.380456,53.673816],"type":"Point"}
}
