{
  "type": "Feature",
  "properties": {
    "iso:country":"GB",
    "wof:name":"DN19 7DP",
    "wof:placetype":"postalcode"
},
  "geometry": {"coordinates":[-0.38045579643605,53.67381615727714],"type":"Point"}
}