{
  "type": "Feature",
  "properties": {
    "iso:country": "GB",
    "wof:name": "AB33 8UJ",
    "wof:placetype": "postalcode"
  },
  "geometry": {"coordinates":[-2.696048,57.231839],"type":"Point"}
}
