{
  "type": "Feature",
  "properties": {
    "date:inception_lower":"2000-12-01",
    "date:inception_upper":"2000-12-31",
    "iso:country":"GB",
    "wof:name":"AB33 8UJ",
    "wof:placetype":"postalcode"
},
  "geometry": {"coordinates":[-2.696048,57.231839],"type":"Point"}
}