{
  "type": "Feature",
  "properties": {
    "date:inception_lower":"1980-01-01",
    "date:inception_upper":"1980-01-31",
    "iso:country":"GB",
    "wof:name":"TQ14 8JE",
    "wof:placetype":"postalcode"
},
  "geometry": {"coordinates":[-3.495596,50.54857],"type":"Point"}
}