{
  "type": "Feature",
  "properties": {
    "iso:country":"GB",
    "wof:name":"TQ14 8JE",
    "wof:placetype":"postalcode"
},
  "geometry": {"coordinates":[-3.49559632903472,50.54857003279528],"type":"Point"}
}