{
  "type": "Feature",
  "properties": {
    "iso:country": "GB",
    "wof:name": "OL15 9DW",
    "wof:placetype": "postalcode"
  },
  "geometry": {"coordinates":[-2.093568,53.645655],"type":"Point"}
}
