{
  "type": "Feature",
  "properties": {
    "date:inception_lower":"2009-07-01",
    "date:inception_upper":"2009-07-31",
    "iso:country":"GB",
    "wof:name":"HP2 4FL",
    "wof:placetype":"postalcode"
},
  "geometry": {"coordinates":[-0.418027,51.759511],"type":"Point"}
}