{
  "type": "Feature",
  "properties": {
    "iso:country": "GB",
    "wof:name": "HP2 4FL",
    "wof:placetype": "postalcode"
  },
  "geometry": {"coordinates":[-0.418027,51.759511],"type":"Point"}
}
