{
  "type": "Feature",
  "properties": {
    "iso:country":"GB",
    "wof:name":"HP2 4FL",
    "wof:placetype":"postalcode"
},
  "geometry": {"coordinates":[-0.41802731639236,51.75951122598234],"type":"Point"}
}