{
  "type": "Feature",
  "properties": {
    "iso:country":"GB",
    "wof:name":"B49 5JL",
    "wof:placetype":"postalcode"
},
  "geometry": {"coordinates":[-1.90996627918449,52.23901927636967],"type":"Point"}
}