{
  "type": "Feature",
  "properties": {
    "iso:country":"GB",
    "wof:name":"TN34 1YE",
    "wof:placetype":"postalcode"
},
  "geometry": {"coordinates":[0.57336577064791,50.86290659015162],"type":"Point"}
}