{
  "type": "Feature",
  "properties": {
    "iso:country":"GB",
    "wof:name":"TF3 1QS",
    "wof:placetype":"postalcode"
},
  "geometry": {"coordinates":[-2.44049812653803,52.6605842021108],"type":"Point"}
}