{
  "type": "Feature",
  "properties": {
    "date:inception_lower": "1992-01-01",
    "date:inception_upper": "1992-01-01",
    "iso:country": "GB",
    "wof:name": "TF3 1QS",
    "wof:placetype": "postalcode"
  },
  "geometry": {"coordinates":[-2.440498,52.660584],"type":"Point"}
}
