{
  "type": "Feature",
  "properties": {
    "iso:country":"GB",
    "wof:name":"SP5 2SQ",
    "wof:placetype":"postalcode"
},
  "geometry": {"coordinates":[-1.65117464631235,51.01150378764856],"type":"Point"}
}