{
  "type": "Feature",
  "properties": {
    "iso:country":"GB",
    "wof:name":"DN38 6EP",
    "wof:placetype":"postalcode"
},
  "geometry": {"coordinates":[-0.40036891732752,53.55329500122604],"type":"Point"}
}