{
  "type": "Feature",
  "properties": {
    "iso:country": "GB",
    "wof:name": "DN38 6EP",
    "wof:placetype": "postalcode"
  },
  "geometry": {"coordinates":[-0.400524,53.553282],"type":"Point"}
}
