{
  "type": "Feature",
  "properties": {
    "iso:country":"GB",
    "wof:name":"M41 6HE",
    "wof:placetype":"postalcode"
},
  "geometry": {"coordinates":[-2.36933942319085,53.44354759512385],"type":"Point"}
}