{
  "type": "Feature",
  "properties": {
    "date:inception_lower": "1996-06-01",
    "date:inception_upper": "1996-06-01",
    "iso:country": "GB",
    "wof:name": "AB16 5UL",
    "wof:placetype": "postalcode"
  },
  "geometry": {"coordinates":[-2.148802,57.155358],"type":"Point"}
}
