{
  "type": "Feature",
  "properties": {
    "iso:country":"GB",
    "wof:name":"HA1 4HN",
    "wof:placetype":"postalcode"
},
  "geometry": {"coordinates":[-0.35886347817293,51.58429031919145],"type":"Point"}
}