{
  "type": "Feature",
  "properties": {
    "iso:country": "GB",
    "wof:name": "HA1 4HN",
    "wof:placetype": "postalcode"
  },
  "geometry": {"coordinates":[-0.358841,51.584292],"type":"Point"}
}
