{
  "type": "Feature",
  "properties": {
    "iso:country": "GB",
    "wof:name": "CH5 3RD",
    "wof:placetype": "postalcode"
  },
  "geometry": {"coordinates":[-3.048326,53.19184],"type":"Point"}
}
