{
  "type": "Feature",
  "properties": {
    "iso:country":"GB",
    "wof:name":"CV6 7BX",
    "wof:placetype":"postalcode"
},
  "geometry": {"coordinates":[-1.47472358713619,52.43731712948418],"type":"Point"}
}