{
  "type": "Feature",
  "properties": {
    "iso:country":"GB",
    "wof:name":"IP30 0RL",
    "wof:placetype":"postalcode"
},
  "geometry": {"coordinates":[0.89153085199974,52.19261932903388],"type":"Point"}
}