{
  "type": "Feature",
  "properties": {
    "iso:country":"GB",
    "wof:name":"L31 7BQ",
    "wof:placetype":"postalcode"
},
  "geometry": {"coordinates":[-2.94493145068216,53.50491972037815],"type":"Point"}
}