{
  "type": "Feature",
  "properties": {
    "iso:country": "GB",
    "wof:name": "CA4 8QP",
    "wof:placetype": "postalcode"
  },
  "geometry": {"coordinates":[-2.816681,54.905886],"type":"Point"}
}
