{
  "type": "Feature",
  "properties": {
    "date:inception_lower": "1992-01-01",
    "date:inception_upper": "1992-01-01",
    "iso:country": "GB",
    "wof:name": "CT12 5LE",
    "wof:placetype": "postalcode"
  },
  "geometry": {"coordinates":[1.364396,51.33037],"type":"Point"}
}
