{
  "type": "Feature",
  "properties": {
    "iso:country":"GB",
    "wof:name":"CT12 5LE",
    "wof:placetype":"postalcode"
},
  "geometry": {"coordinates":[1.36437559251742,51.33045271216201],"type":"Point"}
}