{
  "type": "Feature",
  "properties": {
    "iso:country":"GB",
    "wof:name":"HA5 4RN",
    "wof:placetype":"postalcode"
},
  "geometry": {"coordinates":[-0.38756320446131,51.60698857916221],"type":"Point"}
}