{
  "type": "Feature",
  "properties": {
    "iso:country": "GB",
    "wof:name": "LE18 4SE",
    "wof:placetype": "postalcode"
  },
  "geometry": {"coordinates":[-1.129183,52.580452],"type":"Point"}
}
