{
  "type": "Feature",
  "properties": {
    "iso:country":"GB",
    "wof:name":"LE18 4SE",
    "wof:placetype":"postalcode"
},
  "geometry": {"coordinates":[-1.12918277892547,52.58045180351129],"type":"Point"}
}