{
  "type": "Feature",
  "properties": {
    "date:inception_lower": "1980-01-01",
    "date:inception_upper": "1980-01-01",
    "iso:country": "GB",
    "wof:name": "TA17 8SA",
    "wof:placetype": "postalcode"
  },
  "geometry": {"coordinates":[-2.828754,50.909734],"type":"Point"}
}
