{
  "type": "Feature",
  "properties": {
    "iso:country":"GB",
    "wof:name":"B76 9RA",
    "wof:placetype":"postalcode"
},
  "geometry": {"coordinates":[-1.77051574350408,52.52995800614516],"type":"Point"}
}