{
  "type": "Feature",
  "properties": {
    "iso:country":"GB",
    "wof:name":"PH1 2BW",
    "wof:placetype":"postalcode"
},
  "geometry": {"coordinates":[-3.45226066623821,56.40378867029137],"type":"Point"}
}