{
  "type": "Feature",
  "properties": {
    "iso:country":"GB",
    "wof:name":"PE9 1QD",
    "wof:placetype":"postalcode"
},
  "geometry": {"coordinates":[-0.47602386164655,52.65411612554843],"type":"Point"}
}