{
  "type": "Feature",
  "properties": {
    "iso:country":"GB",
    "wof:name":"EH6 7PS",
    "wof:placetype":"postalcode"
},
  "geometry": {"coordinates":[-3.15190277029826,55.96739154350382],"type":"Point"}
}