{
  "type": "Feature",
  "properties": {
    "iso:country":"GB",
    "wof:name":"TN8 6LE",
    "wof:placetype":"postalcode"
},
  "geometry": {"coordinates":[0.04755084176549,51.21144271598592],"type":"Point"}
}