{
  "type": "Feature",
  "properties": {
    "iso:country":"GB",
    "wof:name":"DY6 9TP",
    "wof:placetype":"postalcode"
},
  "geometry": {"coordinates":[-2.17233741765998,52.48908702425352],"type":"Point"}
}