{
  "type": "Feature",
  "properties": {
    "iso:country":"GB",
    "wof:name":"NG32 2DD",
    "wof:placetype":"postalcode"
},
  "geometry": {"coordinates":[-0.57594309881492,52.95304266121916],"type":"Point"}
}