{
  "type": "Feature",
  "properties": {
    "date:inception_lower":"1980-01-01",
    "date:inception_upper":"1980-01-31",
    "iso:country":"GB",
    "wof:name":"NG32 2DD",
    "wof:placetype":"postalcode"
},
  "geometry": {"coordinates":[-0.575684,52.953071],"type":"Point"}
}