{
  "type": "Feature",
  "properties": {
    "iso:country":"GB",
    "wof:name":"NE24 2HE",
    "wof:placetype":"postalcode"
},
  "geometry": {"coordinates":[-1.50866243484951,55.12278849606006],"type":"Point"}
}