{
  "type": "Feature",
  "properties": {
    "iso:country":"GB",
    "wof:name":"TN2 3TP",
    "wof:placetype":"postalcode"
},
  "geometry": {"coordinates":[0.287929580591,51.14770344239969],"type":"Point"}
}