{
  "type": "Feature",
  "properties": {
    "iso:country": "GB",
    "wof:name": "TN2 3TP",
    "wof:placetype": "postalcode"
  },
  "geometry": {"coordinates":[0.28793,51.147703],"type":"Point"}
}
