{
  "type": "Feature",
  "properties": {
    "iso:country":"GB",
    "wof:name":"N16 9JS",
    "wof:placetype":"postalcode"
},
  "geometry": {"coordinates":[-0.0823020160644,51.55751688646923],"type":"Point"}
}