{
  "type": "Feature",
  "properties": {
    "iso:country":"GB",
    "wof:name":"TD9 8PQ",
    "wof:placetype":"postalcode"
},
  "geometry": {"coordinates":[-2.7804050954137,55.43701066677131],"type":"Point"}
}