{
  "type": "Feature",
  "properties": {
    "iso:country": "GB",
    "wof:name": "TD9 8PQ",
    "wof:placetype": "postalcode"
  },
  "geometry": {"coordinates":[-2.780405,55.437011],"type":"Point"}
}
