{
  "type": "Feature",
  "properties": {
    "iso:country": "GB",
    "wof:name": "G73 4AF",
    "wof:placetype": "postalcode"
  },
  "geometry": {"coordinates":[-4.205546,55.804726],"type":"Point"}
}
