{
  "type": "Feature",
  "properties": {
    "iso:country":"GB",
    "wof:name":"W9 2AE",
    "wof:placetype":"postalcode"
},
  "geometry": {"coordinates":[-0.19795826577045,51.52532294743739],"type":"Point"}
}