{
  "type": "Feature",
  "properties": {
    "iso:country":"GB",
    "wof:name":"OX15 6BB",
    "wof:placetype":"postalcode"
},
  "geometry": {"coordinates":[-1.39227646306066,52.08864263126021],"type":"Point"}
}