{
  "type": "Feature",
  "properties": {
    "date:inception_lower":"2002-06-01",
    "date:inception_upper":"2002-06-30",
    "iso:country":"GB",
    "wof:name":"CM77 6RY",
    "wof:placetype":"postalcode"
},
  "geometry": {"coordinates":[0.500115,51.874682],"type":"Point"}
}