{
  "type": "Feature",
  "properties": {
    "iso:country":"GB",
    "wof:name":"CM77 6RY",
    "wof:placetype":"postalcode"
},
  "geometry": {"coordinates":[0.50011475947055,51.87468173545209],"type":"Point"}
}