{
  "type": "Feature",
  "properties": {
    "date:inception_lower": "1980-01-01",
    "date:inception_upper": "1980-01-01",
    "iso:country": "GB",
    "wof:name": "OL10 3JS",
    "wof:placetype": "postalcode"
  },
  "geometry": {"coordinates":[-2.244504,53.593022],"type":"Point"}
}
