{
  "type": "Feature",
  "properties": {
    "iso:country":"GB",
    "wof:name":"OL10 3JS",
    "wof:placetype":"postalcode"
},
  "geometry": {"coordinates":[-2.24450361078869,53.59302211191246],"type":"Point"}
}