{
  "type": "Feature",
  "properties": {
    "iso:country":"GB",
    "wof:name":"S40 4AU",
    "wof:placetype":"postalcode"
},
  "geometry": {"coordinates":[-1.44494701815988,53.24138392267249],"type":"Point"}
}