{
  "type": "Feature",
  "properties": {
    "iso:country":"GB",
    "wof:name":"LE11 4LL",
    "wof:placetype":"postalcode"
},
  "geometry": {"coordinates":[-1.23329182672754,52.7770425708805],"type":"Point"}
}