{
  "type": "Feature",
  "properties": {
    "date:inception_lower":"1980-01-01",
    "date:inception_upper":"1980-01-31",
    "iso:country":"GB",
    "wof:name":"SK17 0DD",
    "wof:placetype":"postalcode"
},
  "geometry": {"coordinates":[-1.835679,53.185204],"type":"Point"}
}