{
  "type": "Feature",
  "properties": {
    "iso:country":"GB",
    "wof:name":"SK17 0DD",
    "wof:placetype":"postalcode"
},
  "geometry": {"coordinates":[-1.83567946644008,53.18520410969662],"type":"Point"}
}