{
  "type": "Feature",
  "properties": {
    "date:inception_lower": "1992-08-01",
    "date:inception_upper": "1992-08-01",
    "iso:country": "GB",
    "wof:name": "LE67 9PQ",
    "wof:placetype": "postalcode"
  },
  "geometry": {"coordinates":[-1.258277,52.68502],"type":"Point"}
}
