{
  "type": "Feature",
  "properties": {
    "iso:country":"GB",
    "wof:name":"OL4 1SE",
    "wof:placetype":"postalcode"
},
  "geometry": {"coordinates":[-2.10299800890408,53.53643973613983],"type":"Point"}
}