{
  "type": "Feature",
  "properties": {
    "iso:country":"GB",
    "wof:name":"WV10 7HR",
    "wof:placetype":"postalcode"
},
  "geometry": {"coordinates":[-2.08204510764318,52.64659613329462],"type":"Point"}
}