{
  "type": "Feature",
  "properties": {
    "date:inception_lower": "1980-01-01",
    "date:inception_upper": "1980-01-01",
    "iso:country": "GB",
    "wof:name": "WV10 7HR",
    "wof:placetype": "postalcode"
  },
  "geometry": {"coordinates":[-2.082045,52.646596],"type":"Point"}
}
