{
  "type": "Feature",
  "properties": {
    "iso:country":"GB",
    "wof:name":"CT21 6AZ",
    "wof:placetype":"postalcode"
},
  "geometry": {"coordinates":[1.08491282863343,51.06916605514742],"type":"Point"}
}