{
  "type": "Feature",
  "properties": {
    "date:inception_lower": "2009-05-01",
    "date:inception_upper": "2009-05-01",
    "iso:country": "GB",
    "wof:name": "CT21 6AZ",
    "wof:placetype": "postalcode"
  },
  "geometry": {"coordinates":[1.084913,51.069166],"type":"Point"}
}
