{
  "type": "Feature",
  "properties": {
    "iso:country": "GB",
    "wof:name": "AB39 3GZ",
    "wof:placetype": "postalcode"
  },
  "geometry": {"coordinates":[-2.1516,57.035439],"type":"Point"}
}
