{
  "type": "Feature",
  "properties": {
    "date:inception_lower": "2019-10-01",
    "date:inception_upper": "2019-10-01",
    "iso:country": "GB",
    "wof:name": "CH2 1HJ",
    "wof:placetype": "postalcode"
  },
  "geometry": {"coordinates":[-2.9023,53.211542],"type":"Point"}
}
