{
  "type": "Feature",
  "properties": {
    "iso:country": "GB",
    "wof:name": "CH2 1HJ",
    "wof:placetype": "postalcode"
  },
  "geometry": {"coordinates":[-2.9023,53.211542],"type":"Point"}
}
