{
  "type": "Feature",
  "properties": {
    "iso:country":"GB",
    "wof:name":"BD3 9BZ",
    "wof:placetype":"postalcode"
},
  "geometry": {"coordinates":[-1.73510933262764,53.79674095583247],"type":"Point"}
}