{
  "type": "Feature",
  "properties": {
    "date:inception_lower": "1996-06-01",
    "date:inception_upper": "1996-06-01",
    "iso:country": "GB",
    "wof:name": "PO15 7HN",
    "wof:placetype": "postalcode"
  },
  "geometry": {"coordinates":[-1.259162,50.887091],"type":"Point"}
}
