{
  "type": "Feature",
  "properties": {
    "iso:country":"GB",
    "wof:name":"TN14 6LA",
    "wof:placetype":"postalcode"
},
  "geometry": {"coordinates":[0.12215428071669,51.23245241122624],"type":"Point"}
}