{
  "type": "Feature",
  "properties": {
    "iso:country":"GB",
    "wof:name":"LU1 4BQ",
    "wof:placetype":"postalcode"
},
  "geometry": {"coordinates":[-0.42954190436295,51.86190213563945],"type":"Point"}
}