{
  "type": "Feature",
  "properties": {
    "date:inception_lower":"1981-06-01",
    "date:inception_upper":"1981-06-30",
    "iso:country":"GB",
    "wof:name":"LU1 4BQ",
    "wof:placetype":"postalcode"
},
  "geometry": {"coordinates":[-0.429997,51.862726],"type":"Point"}
}