{
  "type": "Feature",
  "properties": {
    "iso:country": "GB",
    "wof:name": "LU1 4BQ",
    "wof:placetype": "postalcode"
  },
  "geometry": {"coordinates":[-0.429997,51.862726],"type":"Point"}
}
