{
  "type": "Feature",
  "properties": {
    "iso:country":"GB",
    "wof:name":"SE12 8LR",
    "wof:placetype":"postalcode"
},
  "geometry": {"coordinates":[0.0044712844979,51.45342390021603],"type":"Point"}
}