{
  "type": "Feature",
  "properties": {
    "date:inception_lower": "1980-01-01",
    "date:inception_upper": "1980-01-01",
    "iso:country": "GB",
    "wof:name": "SE12 8LR",
    "wof:placetype": "postalcode"
  },
  "geometry": {"coordinates":[0.004471,51.453424],"type":"Point"}
}
