{
  "type": "Feature",
  "properties": {
    "date:inception_lower": "1980-01-01",
    "date:inception_upper": "1980-01-01",
    "iso:country": "GB",
    "wof:name": "RG25 2PW",
    "wof:placetype": "postalcode"
  },
  "geometry": {"coordinates":[-1.04977,51.19166],"type":"Point"}
}
