{
  "type": "Feature",
  "properties": {
    "iso:country":"GB",
    "wof:name":"NG16 4BN",
    "wof:placetype":"postalcode"
},
  "geometry": {"coordinates":[-1.33679824524617,53.01750546564442],"type":"Point"}
}