{
  "type": "Feature",
  "properties": {
    "iso:country": "GB",
    "wof:name": "NG16 4BN",
    "wof:placetype": "postalcode"
  },
  "geometry": {"coordinates":[-1.336798,53.017505],"type":"Point"}
}
