{
  "type": "Feature",
  "properties": {
    "iso:country":"GB",
    "wof:name":"NR31 9EF",
    "wof:placetype":"postalcode"
},
  "geometry": {"coordinates":[1.69227438737288,52.59017207548719],"type":"Point"}
}