{
  "type": "Feature",
  "properties": {
    "iso:country":"GB",
    "wof:name":"WA7 5EA",
    "wof:placetype":"postalcode"
},
  "geometry": {"coordinates":[-2.71970652957678,53.33658340200898],"type":"Point"}
}