{
  "type": "Feature",
  "properties": {
    "iso:country": "GB",
    "wof:name": "RH16 3QR",
    "wof:placetype": "postalcode"
  },
  "geometry": {"coordinates":[-0.089849,51.002338],"type":"Point"}
}
