{
  "type": "Feature",
  "properties": {
    "iso:country":"GB",
    "wof:name":"DN14 7JW",
    "wof:placetype":"postalcode"
},
  "geometry": {"coordinates":[-0.87015095889476,53.74685120594913],"type":"Point"}
}