{
  "type": "Feature",
  "properties": {
    "iso:country": "GB",
    "wof:name": "DN14 7JW",
    "wof:placetype": "postalcode"
  },
  "geometry": {"coordinates":[-0.871787,53.747084],"type":"Point"}
}
