{
  "type": "Feature",
  "properties": {
    "iso:country":"GB",
    "wof:name":"DH9 6JQ",
    "wof:placetype":"postalcode"
},
  "geometry": {"coordinates":[-1.69663103354384,54.8644274944369],"type":"Point"}
}