{
  "type": "Feature",
  "properties": {
    "iso:country": "GB",
    "wof:name": "HU14 3RA",
    "wof:placetype": "postalcode"
  },
  "geometry": {"coordinates":[-0.505774,53.753775],"type":"Point"}
}
