{
  "type": "Feature",
  "properties": {
    "iso:country": "GB",
    "wof:name": "IP12 1AY",
    "wof:placetype": "postalcode"
  },
  "geometry": {"coordinates":[1.323481,52.098109],"type":"Point"}
}
