{
  "type": "Feature",
  "properties": {
    "date:inception_lower": "1999-12-01",
    "date:inception_upper": "1999-12-01",
    "iso:country": "GB",
    "wof:name": "PE32 1XL",
    "wof:placetype": "postalcode"
  },
  "geometry": {"coordinates":[0.583017,52.686968],"type":"Point"}
}
