{
  "type": "Feature",
  "properties": {
    "iso:country":"GB",
    "wof:name":"PE32 1XL",
    "wof:placetype":"postalcode"
},
  "geometry": {"coordinates":[0.58301720232585,52.68696830452559],"type":"Point"}
}