{
  "type": "Feature",
  "properties": {
    "iso:country":"GB",
    "wof:name":"SK14 4BD",
    "wof:placetype":"postalcode"
},
  "geometry": {"coordinates":[-2.07433201788432,53.45989777278462],"type":"Point"}
}