{
  "type": "Feature",
  "properties": {
    "date:inception_lower":"1980-01-01",
    "date:inception_upper":"1980-01-31",
    "iso:country":"GB",
    "wof:name":"GL15 6TG",
    "wof:placetype":"postalcode"
},
  "geometry": {"coordinates":[-2.638277,51.737601],"type":"Point"}
}