{
  "type": "Feature",
  "properties": {
    "iso:country":"GB",
    "wof:name":"SN14 8EA",
    "wof:placetype":"postalcode"
},
  "geometry": {"coordinates":[-2.26243425304596,51.44026468741295],"type":"Point"}
}