{
  "type": "Feature",
  "properties": {
    "iso:country": "GB",
    "wof:name": "SY9 5HN",
    "wof:placetype": "postalcode"
  },
  "geometry": {"coordinates":[-3.006427,52.491364],"type":"Point"}
}
