{
  "type": "Feature",
  "properties": {
    "iso:country":"GB",
    "wof:name":"HX1 5QN",
    "wof:placetype":"postalcode"
},
  "geometry": {"coordinates":[-1.87036524314782,53.72594880312283],"type":"Point"}
}