{
  "type": "Feature",
  "properties": {
    "iso:country": "GB",
    "wof:name": "HX1 5QN",
    "wof:placetype": "postalcode"
  },
  "geometry": {"coordinates":[-1.870367,53.725964],"type":"Point"}
}
