{
  "type": "Feature",
  "properties": {
    "date:inception_lower": "2023-02-01",
    "date:inception_upper": "2023-02-01",
    "iso:country": "GB",
    "wof:name": "TA5 2SX",
    "wof:placetype": "postalcode"
  },
  "geometry": {"coordinates":[-3.057019,51.145846],"type":"Point"}
}
