{
  "type": "Feature",
  "properties": {
    "iso:country": "GB",
    "wof:name": "NE5 2ST",
    "wof:placetype": "postalcode"
  },
  "geometry": {"coordinates":[-1.68099,54.988569],"type":"Point"}
}
