{
  "type": "Feature",
  "properties": {
    "iso:country":"GB",
    "wof:name":"NE5 2ST",
    "wof:placetype":"postalcode"
},
  "geometry": {"coordinates":[-1.68099048695282,54.98856928563652],"type":"Point"}
}