{
  "type": "Feature",
  "properties": {
    "iso:country": "GB",
    "wof:name": "TS17 6PY",
    "wof:placetype": "postalcode"
  },
  "geometry": {"coordinates":[-1.293902,54.563422],"type":"Point"}
}
