{
  "type": "Feature",
  "properties": {
    "date:inception_lower": "1980-01-01",
    "date:inception_upper": "1980-01-01",
    "iso:country": "GB",
    "wof:name": "EX15 1PD",
    "wof:placetype": "postalcode"
  },
  "geometry": {"coordinates":[-3.413439,50.845043],"type":"Point"}
}
