{
  "type": "Feature",
  "properties": {
    "iso:country":"GB",
    "wof:name":"EX15 1PD",
    "wof:placetype":"postalcode"
},
  "geometry": {"coordinates":[-3.41309128508446,50.84526266585039],"type":"Point"}
}