{
  "type": "Feature",
  "properties": {
    "iso:country": "GB",
    "wof:name": "GL16 8DP",
    "wof:placetype": "postalcode"
  },
  "geometry": {"coordinates":[-2.616023,51.794486],"type":"Point"}
}
