{
  "type": "Feature",
  "properties": {
    "date:inception_lower": "1998-06-01",
    "date:inception_upper": "1998-06-01",
    "iso:country": "GB",
    "wof:name": "GL16 8DP",
    "wof:placetype": "postalcode"
  },
  "geometry": {"coordinates":[-2.61611,51.794356],"type":"Point"}
}
