{
  "type": "Feature",
  "properties": {
    "iso:country":"GB",
    "wof:name":"TS27 4RY",
    "wof:placetype":"postalcode"
},
  "geometry": {"coordinates":[-1.34306619211234,54.71915411290002],"type":"Point"}
}