{
  "type": "Feature",
  "properties": {
    "iso:country":"GB",
    "wof:name":"NE30 2RP",
    "wof:placetype":"postalcode"
},
  "geometry": {"coordinates":[-1.43219098750504,55.01865674297036],"type":"Point"}
}