{
  "type": "Feature",
  "properties": {
    "iso:country":"GB",
    "wof:name":"MK16 8QW",
    "wof:placetype":"postalcode"
},
  "geometry": {"coordinates":[-0.73473532445149,52.08613549695327],"type":"Point"}
}