{
  "type": "Feature",
  "properties": {
    "iso:country": "GB",
    "wof:name": "LS23 6TF",
    "wof:placetype": "postalcode"
  },
  "geometry": {"coordinates":[-1.352691,53.882292],"type":"Point"}
}
