{
  "type": "Feature",
  "properties": {
    "iso:country":"GB",
    "wof:name":"LS23 6TF",
    "wof:placetype":"postalcode"
},
  "geometry": {"coordinates":[-1.35269108397688,53.88229191508772],"type":"Point"}
}