{
  "type": "Feature",
  "properties": {
    "iso:country":"GB",
    "wof:name":"CF62 7HZ",
    "wof:placetype":"postalcode"
},
  "geometry": {"coordinates":[-3.2856685383836,51.40221362942121],"type":"Point"}
}