{
  "type": "Feature",
  "properties": {
    "iso:country":"GB",
    "wof:name":"IP5 2HT",
    "wof:placetype":"postalcode"
},
  "geometry": {"coordinates":[1.24054623747198,52.06388589699466],"type":"Point"}
}