{
  "type": "Feature",
  "properties": {
    "date:inception_lower": "2012-10-01",
    "date:inception_upper": "2012-10-01",
    "iso:country": "GB",
    "wof:name": "IP5 2HT",
    "wof:placetype": "postalcode"
  },
  "geometry": {"coordinates":[1.240546,52.063886],"type":"Point"}
}
