{
  "type": "Feature",
  "properties": {
    "iso:country": "GB",
    "wof:name": "IP5 2HT",
    "wof:placetype": "postalcode"
  },
  "geometry": {"coordinates":[1.240546,52.063886],"type":"Point"}
}
