{
  "type": "Feature",
  "properties": {
    "date:inception_lower": "1992-10-01",
    "date:inception_upper": "1992-10-01",
    "iso:country": "GB",
    "wof:name": "EH32 9SQ",
    "wof:placetype": "postalcode"
  },
  "geometry": {"coordinates":[-2.985261,55.959546],"type":"Point"}
}
