{
  "type": "Feature",
  "properties": {
    "iso:country": "GB",
    "wof:name": "EH32 9SQ",
    "wof:placetype": "postalcode"
  },
  "geometry": {"coordinates":[-2.985261,55.959546],"type":"Point"}
}
