{
  "type": "Feature",
  "properties": {
    "iso:country":"GB",
    "wof:name":"EH32 9SQ",
    "wof:placetype":"postalcode"
},
  "geometry": {"coordinates":[-2.98526128359838,55.95954583257576],"type":"Point"}
}