{
  "type": "Feature",
  "properties": {
    "iso:country": "GB",
    "wof:name": "HP21 9UQ",
    "wof:placetype": "postalcode"
  },
  "geometry": {"coordinates":[-0.786921,51.80372],"type":"Point"}
}
