{
  "type": "Feature",
  "properties": {
    "iso:country":"GB",
    "wof:name":"HD1 5RB",
    "wof:placetype":"postalcode"
},
  "geometry": {"coordinates":[-1.79861139408149,53.65415151007927],"type":"Point"}
}