{
  "type": "Feature",
  "properties": {
    "date:inception_lower": "2019-04-01",
    "date:inception_upper": "2019-04-01",
    "iso:country": "GB",
    "wof:name": "S42 5FX",
    "wof:placetype": "postalcode"
  },
  "geometry": {"coordinates":[-1.355964,53.188775],"type":"Point"}
}
