{
  "type": "Feature",
  "properties": {
    "date:inception_lower": "1980-01-01",
    "date:inception_upper": "1980-01-01",
    "iso:country": "GB",
    "wof:name": "AL9 7RW",
    "wof:placetype": "postalcode"
  },
  "geometry": {"coordinates":[-0.189596,51.721501],"type":"Point"}
}
