{
  "type": "Feature",
  "properties": {
    "iso:country":"GB",
    "wof:name":"CF72 9RT",
    "wof:placetype":"postalcode"
},
  "geometry": {"coordinates":[-3.45563806737012,51.5342263722308],"type":"Point"}
}