{
  "type": "Feature",
  "properties": {
    "iso:country":"GB",
    "wof:name":"SE21 7BQ",
    "wof:placetype":"postalcode"
},
  "geometry": {"coordinates":[-0.08276414096607,51.44661883773212],"type":"Point"}
}