{
  "type": "Feature",
  "properties": {
    "iso:country": "GB",
    "wof:name": "CV31 2HZ",
    "wof:placetype": "postalcode"
  },
  "geometry": {"coordinates":[-1.524274,52.267302],"type":"Point"}
}
