{
  "type": "Feature",
  "properties": {
    "iso:country": "GB",
    "wof:name": "EH21 8RE",
    "wof:placetype": "postalcode"
  },
  "geometry": {"coordinates":[-3.061764,55.926276],"type":"Point"}
}
