{
  "type": "Feature",
  "properties": {
    "iso:country":"GB",
    "wof:name":"EH21 8RE",
    "wof:placetype":"postalcode"
},
  "geometry": {"coordinates":[-3.06176375462882,55.92627560932264],"type":"Point"}
}