{
  "type": "Feature",
  "properties": {
    "iso:country": "GB",
    "wof:name": "DY1 3QU",
    "wof:placetype": "postalcode"
  },
  "geometry": {"coordinates":[-2.10039,52.527905],"type":"Point"}
}
