{
  "type": "Feature",
  "properties": {
    "iso:country":"GB",
    "wof:name":"LE3 0LP",
    "wof:placetype":"postalcode"
},
  "geometry": {"coordinates":[-1.15358674613604,52.63133241217978],"type":"Point"}
}