{
  "type": "Feature",
  "properties": {
    "date:inception_lower":"1980-01-01",
    "date:inception_upper":"1980-01-31",
    "iso:country":"GB",
    "wof:name":"LE3 0LP",
    "wof:placetype":"postalcode"
},
  "geometry": {"coordinates":[-1.153587,52.631332],"type":"Point"}
}