{
  "type": "Feature",
  "properties": {
    "iso:country":"GB",
    "wof:name":"BN14 0HU",
    "wof:placetype":"postalcode"
},
  "geometry": {"coordinates":[-0.39690601518076,50.85599771471431],"type":"Point"}
}