{
  "type": "Feature",
  "properties": {
    "iso:country":"GB",
    "wof:name":"WA8 6RF",
    "wof:placetype":"postalcode"
},
  "geometry": {"coordinates":[-2.72048128535722,53.37540147110118],"type":"Point"}
}