{
  "type": "Feature",
  "properties": {
    "iso:country":"GB",
    "wof:name":"TW1 4BZ",
    "wof:placetype":"postalcode"
},
  "geometry": {"coordinates":[-0.33133537864353,51.44551970695801],"type":"Point"}
}