{
  "type": "Feature",
  "properties": {
    "iso:country": "GB",
    "wof:name": "TN14 5RS",
    "wof:placetype": "postalcode"
  },
  "geometry": {"coordinates":[0.198899,51.318477],"type":"Point"}
}
