{
  "type": "Feature",
  "properties": {
    "date:inception_lower": "1980-01-01",
    "date:inception_upper": "1980-01-01",
    "iso:country": "GB",
    "wof:name": "TN14 5RS",
    "wof:placetype": "postalcode"
  },
  "geometry": {"coordinates":[0.198899,51.318477],"type":"Point"}
}
