{
  "type": "Feature",
  "properties": {
    "iso:country":"GB",
    "wof:name":"DH9 9HW",
    "wof:placetype":"postalcode"
},
  "geometry": {"coordinates":[-1.7545152712541,54.88152441559895],"type":"Point"}
}