{
  "type": "Feature",
  "properties": {
    "iso:country": "GB",
    "wof:name": "DH9 9HW",
    "wof:placetype": "postalcode"
  },
  "geometry": {"coordinates":[-1.754515,54.881524],"type":"Point"}
}
