{
  "type": "Feature",
  "properties": {
    "date:inception_lower": "1980-01-01",
    "date:inception_upper": "1980-01-01",
    "iso:country": "GB",
    "wof:name": "IG2 7HB",
    "wof:placetype": "postalcode"
  },
  "geometry": {"coordinates":[0.091661,51.574086],"type":"Point"}
}
