{
  "type": "Feature",
  "properties": {
    "iso:country":"GB",
    "wof:name":"BH2 6JJ",
    "wof:placetype":"postalcode"
},
  "geometry": {"coordinates":[-1.88324379714834,50.72287642820525],"type":"Point"}
}