{
  "type": "Feature",
  "properties": {
    "date:inception_lower": "1980-01-01",
    "date:inception_upper": "1980-01-01",
    "iso:country": "GB",
    "wof:name": "TQ12 3NX",
    "wof:placetype": "postalcode"
  },
  "geometry": {"coordinates":[-3.60026,50.556478],"type":"Point"}
}
