{
  "type": "Feature",
  "properties": {
    "iso:country": "GB",
    "wof:name": "TQ12 3NX",
    "wof:placetype": "postalcode"
  },
  "geometry": {"coordinates":[-3.60026,50.556478],"type":"Point"}
}
