{
  "type": "Feature",
  "properties": {
    "iso:country": "GB",
    "wof:name": "CF11 7LZ",
    "wof:placetype": "postalcode"
  },
  "geometry": {"coordinates":[-3.185016,51.468737],"type":"Point"}
}
