{
  "type": "Feature",
  "properties": {
    "iso:country":"GB",
    "wof:name":"CF11 7LZ",
    "wof:placetype":"postalcode"
},
  "geometry": {"coordinates":[-3.18501653536919,51.46873655341835],"type":"Point"}
}