{
  "type": "Feature",
  "properties": {
    "iso:country":"GB",
    "wof:name":"SE10 9BL",
    "wof:placetype":"postalcode"
},
  "geometry": {"coordinates":[-0.00984366604657,51.48169812372233],"type":"Point"}
}