{
  "type": "Feature",
  "properties": {
    "iso:country": "GB",
    "wof:name": "BR7 5EY",
    "wof:placetype": "postalcode"
  },
  "geometry": {"coordinates":[0.06561,51.413774],"type":"Point"}
}
