{
  "type": "Feature",
  "properties": {
    "iso:country": "GB",
    "wof:name": "DN6 7FQ",
    "wof:placetype": "postalcode"
  },
  "geometry": {"coordinates":[-1.205293,53.564974],"type":"Point"}
}
