{
  "type": "Feature",
  "properties": {
    "iso:country":"GB",
    "wof:name":"SP2 0PP",
    "wof:placetype":"postalcode"
},
  "geometry": {"coordinates":[-1.88055761696223,51.12170292859282],"type":"Point"}
}