{
  "type": "Feature",
  "properties": {
    "date:inception_lower": "1980-01-01",
    "date:inception_upper": "1980-01-01",
    "iso:country": "GB",
    "wof:name": "SK14 4AB",
    "wof:placetype": "postalcode"
  },
  "geometry": {"coordinates":[-2.07088,53.457974],"type":"Point"}
}
