{
  "type": "Feature",
  "properties": {
    "iso:country":"GB",
    "wof:name":"CV10 7HD",
    "wof:placetype":"postalcode"
},
  "geometry": {"coordinates":[-1.49576772577624,52.51515465458725],"type":"Point"}
}