{
  "type": "Feature",
  "properties": {
    "iso:country": "GB",
    "wof:name": "CV10 7HD",
    "wof:placetype": "postalcode"
  },
  "geometry": {"coordinates":[-1.495768,52.515155],"type":"Point"}
}
