{
  "type": "Feature",
  "properties": {
    "iso:country":"GB",
    "wof:name":"BA21 3JL",
    "wof:placetype":"postalcode"
},
  "geometry": {"coordinates":[-2.65380909160604,50.94750705918364],"type":"Point"}
}