{
  "type": "Feature",
  "properties": {
    "iso:country":"GB",
    "wof:name":"HP11 1JT",
    "wof:placetype":"postalcode"
},
  "geometry": {"coordinates":[-0.70247265874566,51.60620658172033],"type":"Point"}
}