{
  "type": "Feature",
  "properties": {
    "iso:country": "GB",
    "wof:name": "HP11 1JT",
    "wof:placetype": "postalcode"
  },
  "geometry": {"coordinates":[-0.702453,51.60621],"type":"Point"}
}
