{
  "type": "Feature",
  "properties": {
    "date:inception_lower": "1980-01-01",
    "date:inception_upper": "1980-01-01",
    "iso:country": "GB",
    "wof:name": "N10 2RS",
    "wof:placetype": "postalcode"
  },
  "geometry": {"coordinates":[-0.144078,51.606665],"type":"Point"}
}
