{
  "type": "Feature",
  "properties": {
    "iso:country": "GB",
    "wof:name": "HP6 6DF",
    "wof:placetype": "postalcode"
  },
  "geometry": {"coordinates":[-0.599868,51.687492],"type":"Point"}
}
