{
  "type": "Feature",
  "properties": {
    "iso:country":"GB",
    "wof:name":"HP6 6DF",
    "wof:placetype":"postalcode"
},
  "geometry": {"coordinates":[-0.59986841407091,51.6874920622431],"type":"Point"}
}