{
  "type": "Feature",
  "properties": {
    "date:inception_lower": "2017-04-01",
    "date:inception_upper": "2017-04-01",
    "iso:country": "GB",
    "wof:name": "B32 3AJ",
    "wof:placetype": "postalcode"
  },
  "geometry": {"coordinates":[-1.971805,52.444859],"type":"Point"}
}
