{
  "type": "Feature",
  "properties": {
    "date:inception_lower": "1980-01-01",
    "date:inception_upper": "1980-01-01",
    "iso:country": "GB",
    "wof:name": "NE5 4HS",
    "wof:placetype": "postalcode"
  },
  "geometry": {"coordinates":[-1.689978,55.008659],"type":"Point"}
}
