{
  "type": "Feature",
  "properties": {
    "iso:country": "GB",
    "wof:name": "NE5 4HS",
    "wof:placetype": "postalcode"
  },
  "geometry": {"coordinates":[-1.689978,55.008659],"type":"Point"}
}
