{
  "type": "Feature",
  "properties": {
    "iso:country":"GB",
    "wof:name":"NE5 4HS",
    "wof:placetype":"postalcode"
},
  "geometry": {"coordinates":[-1.68997806191857,55.00865868855799],"type":"Point"}
}