{
  "type": "Feature",
  "properties": {
    "iso:country": "GB",
    "wof:name": "SL7 2HL",
    "wof:placetype": "postalcode"
  },
  "geometry": {"coordinates":[-0.831511,51.570273],"type":"Point"}
}
