{
  "type": "Feature",
  "properties": {
    "iso:country":"GB",
    "wof:name":"SL7 2HL",
    "wof:placetype":"postalcode"
},
  "geometry": {"coordinates":[-0.83151089316759,51.57027290773917],"type":"Point"}
}