{
  "type": "Feature",
  "properties": {
    "iso:country": "GB",
    "wof:name": "TQ3 1DA",
    "wof:placetype": "postalcode"
  },
  "geometry": {"coordinates":[-3.576397,50.45048],"type":"Point"}
}
