{
  "type": "Feature",
  "properties": {
    "iso:country":"GB",
    "wof:name":"TQ3 1DA",
    "wof:placetype":"postalcode"
},
  "geometry": {"coordinates":[-3.57639696418946,50.45048027985681],"type":"Point"}
}