{
  "type": "Feature",
  "properties": {
    "date:inception_lower":"1980-01-01",
    "date:inception_upper":"1980-01-31",
    "iso:country":"GB",
    "wof:name":"FK17 8AD",
    "wof:placetype":"postalcode"
},
  "geometry": {"coordinates":[-4.216842,56.241389],"type":"Point"}
}