{
  "type": "Feature",
  "properties": {
    "iso:country": "GB",
    "wof:name": "FK17 8AD",
    "wof:placetype": "postalcode"
  },
  "geometry": {"coordinates":[-4.216842,56.241389],"type":"Point"}
}
