{
  "type": "Feature",
  "properties": {
    "iso:country":"GB",
    "wof:name":"DE5 3GB",
    "wof:placetype":"postalcode"
},
  "geometry": {"coordinates":[-1.4138501310791,53.05055891188541],"type":"Point"}
}