{
  "type": "Feature",
  "properties": {
    "date:inception_lower":"2001-06-01",
    "date:inception_upper":"2001-06-30",
    "iso:country":"GB",
    "wof:name":"HD7 5XZ",
    "wof:placetype":"postalcode"
},
  "geometry": {"coordinates":[-1.87238,53.625814],"type":"Point"}
}