{
  "type": "Feature",
  "properties": {
    "date:inception_lower": "2014-03-01",
    "date:inception_upper": "2014-03-01",
    "iso:country": "GB",
    "wof:name": "E20 1BY",
    "wof:placetype": "postalcode"
  },
  "geometry": {"coordinates":[-0.004532,51.546274],"type":"Point"}
}
