{
  "type": "Feature",
  "properties": {
    "iso:country":"GB",
    "wof:name":"E20 1BY",
    "wof:placetype":"postalcode"
},
  "geometry": {"coordinates":[-0.00453185278555,51.54627411264775],"type":"Point"}
}