{
  "type": "Feature",
  "properties": {
    "iso:country":"GB",
    "wof:name":"SW12 0BW",
    "wof:placetype":"postalcode"
},
  "geometry": {"coordinates":[-0.14408384841704,51.4487657487357],"type":"Point"}
}