{
  "type": "Feature",
  "properties": {
    "iso:country":"GB",
    "wof:name":"PO15 5LN",
    "wof:placetype":"postalcode"
},
  "geometry": {"coordinates":[-1.24339584868031,50.86424809158048],"type":"Point"}
}