{
  "type": "Feature",
  "properties": {
    "iso:country": "GB",
    "wof:name": "PO15 5LN",
    "wof:placetype": "postalcode"
  },
  "geometry": {"coordinates":[-1.243396,50.864248],"type":"Point"}
}
