{
  "type": "Feature",
  "properties": {
    "date:inception_lower": "1998-12-01",
    "date:inception_upper": "1998-12-01",
    "iso:country": "GB",
    "wof:name": "PO15 5LN",
    "wof:placetype": "postalcode"
  },
  "geometry": {"coordinates":[-1.243396,50.864248],"type":"Point"}
}
