{
  "type": "Feature",
  "properties": {
    "date:inception_lower":"1990-02-01",
    "date:inception_upper":"1990-02-28",
    "iso:country":"GB",
    "wof:name":"TR11 2UQ",
    "wof:placetype":"postalcode"
},
  "geometry": {"coordinates":[-5.07513,50.157335],"type":"Point"}
}