{
  "type": "Feature",
  "properties": {
    "iso:country":"GB",
    "wof:name":"SW2 2QS",
    "wof:placetype":"postalcode"
},
  "geometry": {"coordinates":[-0.10829239076836,51.44561274914248],"type":"Point"}
}