{
  "type": "Feature",
  "properties": {
    "iso:country": "GB",
    "wof:name": "PE1 5YX",
    "wof:placetype": "postalcode"
  },
  "geometry": {"coordinates":[-0.213691,52.574003],"type":"Point"}
}
