{
  "type": "Feature",
  "properties": {
    "iso:country":"GB",
    "wof:name":"PE1 5YX",
    "wof:placetype":"postalcode"
},
  "geometry": {"coordinates":[-0.21370599669592,52.57398454302717],"type":"Point"}
}