{
  "type": "Feature",
  "properties": {
    "date:inception_lower":"2015-06-01",
    "date:inception_upper":"2015-06-30",
    "iso:country":"GB",
    "wof:name":"PL2 2EZ",
    "wof:placetype":"postalcode"
},
  "geometry": {"coordinates":[-4.161574,50.39786],"type":"Point"}
}