{
  "type": "Feature",
  "properties": {
    "date:inception_lower": "1980-01-01",
    "date:inception_upper": "1980-01-01",
    "iso:country": "GB",
    "wof:name": "LL22 9AF",
    "wof:placetype": "postalcode"
  },
  "geometry": {"coordinates":[-3.562225,53.297277],"type":"Point"}
}
