{
  "type": "Feature",
  "properties": {
    "iso:country": "GB",
    "wof:name": "CA2 7TA",
    "wof:placetype": "postalcode"
  },
  "geometry": {"coordinates":[-2.979079,54.887602],"type":"Point"}
}
