{
  "type": "Feature",
  "properties": {
    "date:inception_lower":"2002-06-01",
    "date:inception_upper":"2002-06-30",
    "iso:country":"GB",
    "wof:name":"TW17 9WL",
    "wof:placetype":"postalcode"
},
  "geometry": {"coordinates":[-0.448975,51.394566],"type":"Point"}
}