{
  "type": "Feature",
  "properties": {
    "iso:country": "GB",
    "wof:name": "LL32 8LG",
    "wof:placetype": "postalcode"
  },
  "geometry": {"coordinates":[-3.82983,53.275787],"type":"Point"}
}
