{
  "type": "Feature",
  "properties": {
    "date:inception_lower": "1987-04-01",
    "date:inception_upper": "1987-04-01",
    "iso:country": "GB",
    "wof:name": "PE23 5HZ",
    "wof:placetype": "postalcode"
  },
  "geometry": {"coordinates":[0.09055,53.172343],"type":"Point"}
}
