{
  "type": "Feature",
  "properties": {
    "iso:country": "GB",
    "wof:name": "PE23 5HZ",
    "wof:placetype": "postalcode"
  },
  "geometry": {"coordinates":[0.09055,53.172343],"type":"Point"}
}
