{
  "type": "Feature",
  "properties": {
    "iso:country":"GB",
    "wof:name":"SA33 5DZ",
    "wof:placetype":"postalcode"
},
  "geometry": {"coordinates":[-4.40974152675049,51.84374256040557],"type":"Point"}
}