{
  "type": "Feature",
  "properties": {
    "iso:country": "GB",
    "wof:name": "SA33 5DZ",
    "wof:placetype": "postalcode"
  },
  "geometry": {"coordinates":[-4.409741,51.843743],"type":"Point"}
}
