{
  "type": "Feature",
  "properties": {
    "iso:country":"GB",
    "wof:name":"NE66 4RZ",
    "wof:placetype":"postalcode"
},
  "geometry": {"coordinates":[-1.86193638011515,55.39153917176916],"type":"Point"}
}