{
  "type": "Feature",
  "properties": {
    "date:inception_lower":"1980-01-01",
    "date:inception_upper":"1980-01-31",
    "iso:country":"GB",
    "wof:name":"NE66 4RZ",
    "wof:placetype":"postalcode"
},
  "geometry": {"coordinates":[-1.861936,55.391539],"type":"Point"}
}