{
  "type": "Feature",
  "properties": {
    "iso:country":"GB",
    "wof:name":"TQ14 9NG",
    "wof:placetype":"postalcode"
},
  "geometry": {"coordinates":[-3.50819339458495,50.56115133659232],"type":"Point"}
}