{
  "type": "Feature",
  "properties": {
    "date:inception_lower": "1980-01-01",
    "date:inception_upper": "1980-01-01",
    "iso:country": "GB",
    "wof:name": "TQ14 9NG",
    "wof:placetype": "postalcode"
  },
  "geometry": {"coordinates":[-3.508193,50.561151],"type":"Point"}
}
