{
  "type": "Feature",
  "properties": {
    "iso:country":"GB",
    "wof:name":"NE2 1PT",
    "wof:placetype":"postalcode"
},
  "geometry": {"coordinates":[-1.59269344707079,54.98388466305926],"type":"Point"}
}