{
  "type": "Feature",
  "properties": {
    "iso:country": "GB",
    "wof:name": "CV11 5HT",
    "wof:placetype": "postalcode"
  },
  "geometry": {"coordinates":[-1.478809,52.526139],"type":"Point"}
}
