{
  "type": "Feature",
  "properties": {
    "iso:country":"GB",
    "wof:name":"CV11 5HT",
    "wof:placetype":"postalcode"
},
  "geometry": {"coordinates":[-1.47880930568097,52.526138917382],"type":"Point"}
}