{
  "type": "Feature",
  "properties": {
    "iso:country":"GB",
    "wof:name":"B65 0PY",
    "wof:placetype":"postalcode"
},
  "geometry": {"coordinates":[-2.0251975150764,52.48726834231127],"type":"Point"}
}