{
  "type": "Feature",
  "properties": {
    "iso:country":"GB",
    "wof:name":"TD10 6YQ",
    "wof:placetype":"postalcode"
},
  "geometry": {"coordinates":[-2.4525760652823,55.70800944938],"type":"Point"}
}