{
  "type": "Feature",
  "properties": {
    "date:inception_lower": "1980-01-01",
    "date:inception_upper": "1980-01-01",
    "iso:country": "GB",
    "wof:name": "TD10 6YQ",
    "wof:placetype": "postalcode"
  },
  "geometry": {"coordinates":[-2.453121,55.707807],"type":"Point"}
}
