{
  "type": "Feature",
  "properties": {
    "iso:country": "GB",
    "wof:name": "CA28 7BH",
    "wof:placetype": "postalcode"
  },
  "geometry": {"coordinates":[-3.586221,54.542649],"type":"Point"}
}
