{
  "type": "Feature",
  "properties": {
    "iso:country": "GB",
    "wof:name": "CO12 4PY",
    "wof:placetype": "postalcode"
  },
  "geometry": {"coordinates":[1.253621,51.943813],"type":"Point"}
}
