{
  "type": "Feature",
  "properties": {
    "date:inception_lower": "2005-02-01",
    "date:inception_upper": "2005-02-01",
    "iso:country": "GB",
    "wof:name": "CO12 4PY",
    "wof:placetype": "postalcode"
  },
  "geometry": {"coordinates":[1.253621,51.943813],"type":"Point"}
}
