{
  "type": "Feature",
  "properties": {
    "iso:country":"GB",
    "wof:name":"CO12 4PY",
    "wof:placetype":"postalcode"
},
  "geometry": {"coordinates":[1.25362094664333,51.94381261103666],"type":"Point"}
}