{
  "type": "Feature",
  "properties": {
    "iso:country": "GB",
    "wof:name": "LN12 1JS",
    "wof:placetype": "postalcode"
  },
  "geometry": {"coordinates":[0.248911,53.345118],"type":"Point"}
}
