{
  "type": "Feature",
  "properties": {
    "iso:country":"GB",
    "wof:name":"NE3 4QX",
    "wof:placetype":"postalcode"
},
  "geometry": {"coordinates":[-1.64890937930411,54.99898589374956],"type":"Point"}
}