{
  "type": "Feature",
  "properties": {
    "iso:country":"GB",
    "wof:name":"TQ2 7HR",
    "wof:placetype":"postalcode"
},
  "geometry": {"coordinates":[-3.56552727218415,50.48347205234069],"type":"Point"}
}