{
  "type": "Feature",
  "properties": {
    "iso:country":"GB",
    "wof:name":"KY15 7UZ",
    "wof:placetype":"postalcode"
},
  "geometry": {"coordinates":[-3.18260370513793,56.29352445636516],"type":"Point"}
}