{
  "type": "Feature",
  "properties": {
    "iso:country": "GB",
    "wof:name": "N10 2LR",
    "wof:placetype": "postalcode"
  },
  "geometry": {"coordinates":[-0.146457,51.600381],"type":"Point"}
}
