{
  "type": "Feature",
  "properties": {
    "date:inception_lower":"1999-06-01",
    "date:inception_upper":"1999-06-30",
    "iso:country":"GB",
    "wof:name":"CH63 7RZ",
    "wof:placetype":"postalcode"
},
  "geometry": {"coordinates":[-3.001305,53.349932],"type":"Point"}
}