{
  "type": "Feature",
  "properties": {
    "iso:country":"GB",
    "wof:name":"MK45 5AL",
    "wof:placetype":"postalcode"
},
  "geometry": {"coordinates":[-0.50842835193083,51.99573359191086],"type":"Point"}
}