{
  "type": "Feature",
  "properties": {
    "iso:country":"GB",
    "wof:name":"M22 0HB",
    "wof:placetype":"postalcode"
},
  "geometry": {"coordinates":[-2.25907635999102,53.36953828608966],"type":"Point"}
}