{
  "type": "Feature",
  "properties": {
    "iso:country": "GB",
    "wof:name": "M22 0HB",
    "wof:placetype": "postalcode"
  },
  "geometry": {"coordinates":[-2.259076,53.369538],"type":"Point"}
}
