{
  "type": "Feature",
  "properties": {
    "date:inception_lower": "1980-01-01",
    "date:inception_upper": "1980-01-01",
    "iso:country": "GB",
    "wof:name": "RG10 9LB",
    "wof:placetype": "postalcode"
  },
  "geometry": {"coordinates":[-0.861952,51.478875],"type":"Point"}
}
