{
  "type": "Feature",
  "properties": {
    "iso:country":"GB",
    "wof:name":"BS15 1RN",
    "wof:placetype":"postalcode"
},
  "geometry": {"coordinates":[-2.50959714569221,51.46492359533862],"type":"Point"}
}