{
  "type": "Feature",
  "properties": {
    "iso:country": "GB",
    "wof:name": "GU35 8HR",
    "wof:placetype": "postalcode"
  },
  "geometry": {"coordinates":[-0.80599,51.119744],"type":"Point"}
}
