{
  "type": "Feature",
  "properties": {
    "date:inception_lower": "1980-01-01",
    "date:inception_upper": "1980-01-01",
    "iso:country": "GB",
    "wof:name": "GU35 8HR",
    "wof:placetype": "postalcode"
  },
  "geometry": {"coordinates":[-0.805532,51.119627],"type":"Point"}
}
