{
  "type": "Feature",
  "properties": {
    "iso:country":"GB",
    "wof:name":"WN5 8UP",
    "wof:placetype":"postalcode"
},
  "geometry": {"coordinates":[-2.71382955828058,53.53382192782028],"type":"Point"}
}