{
  "type": "Feature",
  "properties": {
    "iso:country":"GB",
    "wof:name":"S7 1DJ",
    "wof:placetype":"postalcode"
},
  "geometry": {"coordinates":[-1.47883694901338,53.3638295859613],"type":"Point"}
}