{
  "type": "Feature",
  "properties": {
    "iso:country": "GB",
    "wof:name": "HS8 5TS",
    "wof:placetype": "postalcode"
  },
  "geometry": {"coordinates":[-7.333311,57.103485],"type":"Point"}
}
