{
  "type": "Feature",
  "properties": {
    "iso:country":"GB",
    "wof:name":"HS8 5TS",
    "wof:placetype":"postalcode"
},
  "geometry": {"coordinates":[-7.33455185507659,57.10366403350366],"type":"Point"}
}