{
  "type": "Feature",
  "properties": {
    "date:inception_lower": "1980-01-01",
    "date:inception_upper": "1980-01-01",
    "iso:country": "GB",
    "wof:name": "SK10 4BS",
    "wof:placetype": "postalcode"
  },
  "geometry": {"coordinates":[-2.14815,53.284541],"type":"Point"}
}
