{
  "type": "Feature",
  "properties": {
    "iso:country":"GB",
    "wof:name":"HP4 3AR",
    "wof:placetype":"postalcode"
},
  "geometry": {"coordinates":[-0.5899836130654,51.7579051336488],"type":"Point"}
}