{
  "type": "Feature",
  "properties": {
    "date:inception_lower":"2004-01-01",
    "date:inception_upper":"2004-01-31",
    "iso:country":"GB",
    "wof:name":"HP4 3AR",
    "wof:placetype":"postalcode"
},
  "geometry": {"coordinates":[-0.589984,51.757905],"type":"Point"}
}