{
  "type": "Feature",
  "properties": {
    "iso:country": "GB",
    "wof:name": "HP4 3AR",
    "wof:placetype": "postalcode"
  },
  "geometry": {"coordinates":[-0.589984,51.757905],"type":"Point"}
}
