{
  "type": "Feature",
  "properties": {
    "date:inception_lower": "1995-07-01",
    "date:inception_upper": "1995-07-01",
    "iso:country": "GB",
    "wof:name": "DH1 1NU",
    "wof:placetype": "postalcode"
  },
  "geometry": {"coordinates":[-1.566305,54.781617],"type":"Point"}
}
