{
  "type": "Feature",
  "properties": {
    "iso:country":"GB",
    "wof:name":"CR4 3HT",
    "wof:placetype":"postalcode"
},
  "geometry": {"coordinates":[-0.16594446022197,51.41177255731112],"type":"Point"}
}