{
  "type": "Feature",
  "properties": {
    "iso:country":"GB",
    "wof:name":"E17 3RU",
    "wof:placetype":"postalcode"
},
  "geometry": {"coordinates":[-0.01741990794067,51.58554740422338],"type":"Point"}
}