{
  "type": "Feature",
  "properties": {
    "iso:country":"GB",
    "wof:name":"KT4 7AE",
    "wof:placetype":"postalcode"
},
  "geometry": {"coordinates":[-0.24464518297564,51.37611726852425],"type":"Point"}
}