{
  "type": "Feature",
  "properties": {
    "iso:country": "GB",
    "wof:name": "OX39 4JG",
    "wof:placetype": "postalcode"
  },
  "geometry": {"coordinates":[-0.908985,51.699581],"type":"Point"}
}
