{
  "type": "Feature",
  "properties": {
    "iso:country":"GB",
    "wof:name":"OX39 4JG",
    "wof:placetype":"postalcode"
},
  "geometry": {"coordinates":[-0.90898473049419,51.69958085807077],"type":"Point"}
}