{
  "type": "Feature",
  "properties": {
    "iso:country":"GB",
    "wof:name":"AL3 4PZ",
    "wof:placetype":"postalcode"
},
  "geometry": {"coordinates":[-0.3439638899901,51.75332071887553],"type":"Point"}
}