{
  "type": "Feature",
  "properties": {
    "date:inception_lower": "1980-01-01",
    "date:inception_upper": "1980-01-01",
    "iso:country": "GB",
    "wof:name": "LS8 2ET",
    "wof:placetype": "postalcode"
  },
  "geometry": {"coordinates":[-1.504718,53.84292],"type":"Point"}
}
