{
  "type": "Feature",
  "properties": {
    "iso:country":"GB",
    "wof:name":"WA11 7EU",
    "wof:placetype":"postalcode"
},
  "geometry": {"coordinates":[-2.72507300274393,53.47572380159746],"type":"Point"}
}