{
  "type": "Feature",
  "properties": {
    "iso:country":"GB",
    "wof:name":"BB2 5HH",
    "wof:placetype":"postalcode"
},
  "geometry": {"coordinates":[-2.52753681421345,53.72820892011878],"type":"Point"}
}