{
  "type": "Feature",
  "properties": {
    "iso:country":"GB",
    "wof:name":"PR7 1LH",
    "wof:placetype":"postalcode"
},
  "geometry": {"coordinates":[-2.63782341122591,53.65244049744631],"type":"Point"}
}