{
  "type": "Feature",
  "properties": {
    "iso:country": "GB",
    "wof:name": "NE28 6DD",
    "wof:placetype": "postalcode"
  },
  "geometry": {"coordinates":[-1.535187,54.985404],"type":"Point"}
}
