{
  "type": "Feature",
  "properties": {
    "date:inception_lower":"1997-06-01",
    "date:inception_upper":"1997-06-30",
    "iso:country":"GB",
    "wof:name":"NE28 6DD",
    "wof:placetype":"postalcode"
},
  "geometry": {"coordinates":[-1.535187,54.985404],"type":"Point"}
}