{
  "type": "Feature",
  "properties": {
    "date:inception_lower":"1980-01-01",
    "date:inception_upper":"1980-01-31",
    "iso:country":"GB",
    "wof:name":"OL2 5UP",
    "wof:placetype":"postalcode"
},
  "geometry": {"coordinates":[-2.13615,53.579712],"type":"Point"}
}