{
  "type": "Feature",
  "properties": {
    "iso:country":"GB",
    "wof:name":"OL2 5UP",
    "wof:placetype":"postalcode"
},
  "geometry": {"coordinates":[-2.13614982498883,53.57971226574008],"type":"Point"}
}