{
  "type": "Feature",
  "properties": {
    "iso:country":"GB",
    "wof:name":"EX20 3SA",
    "wof:placetype":"postalcode"
},
  "geometry": {"coordinates":[-3.98464301252087,50.79785244792276],"type":"Point"}
}