{
  "type": "Feature",
  "properties": {
    "iso:country":"GB",
    "wof:name":"S43 1DY",
    "wof:placetype":"postalcode"
},
  "geometry": {"coordinates":[-1.38736969050606,53.25871137556863],"type":"Point"}
}