{
  "type": "Feature",
  "properties": {
    "date:inception_lower":"1980-01-01",
    "date:inception_upper":"1980-01-31",
    "iso:country":"GB",
    "wof:name":"FK2 7QH",
    "wof:placetype":"postalcode"
},
  "geometry": {"coordinates":[-3.789102,56.01854],"type":"Point"}
}