{
  "type": "Feature",
  "properties": {
    "iso:country":"GB",
    "wof:name":"NG10 4JU",
    "wof:placetype":"postalcode"
},
  "geometry": {"coordinates":[-1.29602201358521,52.90053468412995],"type":"Point"}
}