{
  "type": "Feature",
  "properties": {
    "iso:country": "GB",
    "wof:name": "NG10 4JU",
    "wof:placetype": "postalcode"
  },
  "geometry": {"coordinates":[-1.296022,52.900535],"type":"Point"}
}
