{
  "type": "Feature",
  "properties": {
    "iso:country": "GB",
    "wof:name": "EH23 4FH",
    "wof:placetype": "postalcode"
  },
  "geometry": {"coordinates":[-3.052028,55.851061],"type":"Point"}
}
