{
  "type": "Feature",
  "properties": {
    "iso:country":"GB",
    "wof:name":"LE3 2HD",
    "wof:placetype":"postalcode"
},
  "geometry": {"coordinates":[-1.17065618192744,52.60922983362441],"type":"Point"}
}