{
  "type": "Feature",
  "properties": {
    "iso:country": "GB",
    "wof:name": "NR21 8NS",
    "wof:placetype": "postalcode"
  },
  "geometry": {"coordinates":[0.871614,52.829835],"type":"Point"}
}
