{
  "type": "Feature",
  "properties": {
    "iso:country":"GB",
    "wof:name":"NR21 8NS",
    "wof:placetype":"postalcode"
},
  "geometry": {"coordinates":[0.87161420447951,52.8298346069726],"type":"Point"}
}