{
  "type": "Feature",
  "properties": {
    "date:inception_lower": "1983-07-01",
    "date:inception_upper": "1983-07-01",
    "iso:country": "GB",
    "wof:name": "NR21 8NS",
    "wof:placetype": "postalcode"
  },
  "geometry": {"coordinates":[0.871614,52.829835],"type":"Point"}
}
