{
  "type": "Feature",
  "properties": {
    "iso:country":"GB",
    "wof:name":"AL3 4HD",
    "wof:placetype":"postalcode"
},
  "geometry": {"coordinates":[-0.34493062750933,51.75065473561132],"type":"Point"}
}