{
  "type": "Feature",
  "properties": {
    "iso:country":"GB",
    "wof:name":"SP4 7ES",
    "wof:placetype":"postalcode"
},
  "geometry": {"coordinates":[-1.78241704189231,51.17238465381165],"type":"Point"}
}