{
  "type": "Feature",
  "properties": {
    "iso:country": "GB",
    "wof:name": "SP4 7ES",
    "wof:placetype": "postalcode"
  },
  "geometry": {"coordinates":[-1.782377,51.172353],"type":"Point"}
}
