{
  "type": "Feature",
  "properties": {
    "iso:country": "GB",
    "wof:name": "ME12 4RL",
    "wof:placetype": "postalcode"
  },
  "geometry": {"coordinates":[0.944106,51.380545],"type":"Point"}
}
