{
  "type": "Feature",
  "properties": {
    "iso:country":"GB",
    "wof:name":"ME12 4RL",
    "wof:placetype":"postalcode"
},
  "geometry": {"coordinates":[0.94410600230944,51.38054479379439],"type":"Point"}
}