{
  "type": "Feature",
  "properties": {
    "date:inception_lower": "1980-01-01",
    "date:inception_upper": "1980-01-01",
    "iso:country": "GB",
    "wof:name": "S70 1RY",
    "wof:placetype": "postalcode"
  },
  "geometry": {"coordinates":[-1.479425,53.55102],"type":"Point"}
}
