{
  "type": "Feature",
  "properties": {
    "iso:country":"GB",
    "wof:name":"SE15 3EQ",
    "wof:placetype":"postalcode"
},
  "geometry": {"coordinates":[-0.05016175170746,51.45487592485603],"type":"Point"}
}