{
  "type": "Feature",
  "properties": {
    "iso:country":"GB",
    "wof:name":"TQ7 3DS",
    "wof:placetype":"postalcode"
},
  "geometry": {"coordinates":[-3.81105313958547,50.22643849978513],"type":"Point"}
}