{
  "type": "Feature",
  "properties": {
    "date:inception_lower": "1980-01-01",
    "date:inception_upper": "1980-01-01",
    "iso:country": "GB",
    "wof:name": "CB9 7QP",
    "wof:placetype": "postalcode"
  },
  "geometry": {"coordinates":[0.50933,52.090155],"type":"Point"}
}
