{
  "type": "Feature",
  "properties": {
    "iso:country":"GB",
    "wof:name":"TR20 8EJ",
    "wof:placetype":"postalcode"
},
  "geometry": {"coordinates":[-5.48407220000361,50.14679102233552],"type":"Point"}
}