{
  "type": "Feature",
  "properties": {
    "iso:country":"GB",
    "wof:name":"CV2 2TA",
    "wof:placetype":"postalcode"
},
  "geometry": {"coordinates":[-1.42905811598553,52.43091138380825],"type":"Point"}
}