{
  "type": "Feature",
  "properties": {
    "date:inception_lower": "1992-08-01",
    "date:inception_upper": "1992-08-01",
    "iso:country": "GB",
    "wof:name": "CV2 2TA",
    "wof:placetype": "postalcode"
  },
  "geometry": {"coordinates":[-1.428117,52.430269],"type":"Point"}
}
