{
  "type": "Feature",
  "properties": {
    "date:inception_lower":"2014-06-01",
    "date:inception_upper":"2014-06-30",
    "iso:country":"GB",
    "wof:name":"OX15 4GB",
    "wof:placetype":"postalcode"
},
  "geometry": {"coordinates":[-1.408307,52.008717],"type":"Point"}
}