{
  "type": "Feature",
  "properties": {
    "iso:country": "GB",
    "wof:name": "OX15 4GB",
    "wof:placetype": "postalcode"
  },
  "geometry": {"coordinates":[-1.408307,52.008717],"type":"Point"}
}
