{
  "type": "Feature",
  "properties": {
    "iso:country":"GB",
    "wof:name":"OX15 4GB",
    "wof:placetype":"postalcode"
},
  "geometry": {"coordinates":[-1.40839509075338,52.00868007190568],"type":"Point"}
}