{
  "type": "Feature",
  "properties": {
    "date:inception_lower": "1980-01-01",
    "date:inception_upper": "1980-01-01",
    "iso:country": "GB",
    "wof:name": "OX10 0RS",
    "wof:placetype": "postalcode"
  },
  "geometry": {"coordinates":[-1.160467,51.612182],"type":"Point"}
}
