{
  "type": "Feature",
  "properties": {
    "iso:country": "GB",
    "wof:name": "OX10 0RS",
    "wof:placetype": "postalcode"
  },
  "geometry": {"coordinates":[-1.160467,51.612182],"type":"Point"}
}
