{
  "type": "Feature",
  "properties": {
    "iso:country":"GB",
    "wof:name":"ME18 6JP",
    "wof:placetype":"postalcode"
},
  "geometry": {"coordinates":[0.42892251205391,51.22784401966854],"type":"Point"}
}