{
  "type": "Feature",
  "properties": {
    "iso:country":"GB",
    "wof:name":"LE2 3AE",
    "wof:placetype":"postalcode"
},
  "geometry": {"coordinates":[-1.11780554157622,52.61640874889694],"type":"Point"}
}