{
  "type": "Feature",
  "properties": {
    "iso:country":"GB",
    "wof:name":"BD17 5SD",
    "wof:placetype":"postalcode"
},
  "geometry": {"coordinates":[-1.80187414474342,53.84248347496615],"type":"Point"}
}