{
  "type": "Feature",
  "properties": {
    "iso:country": "GB",
    "wof:name": "CB10 1BG",
    "wof:placetype": "postalcode"
  },
  "geometry": {"coordinates":[0.238453,52.025387],"type":"Point"}
}
