{
  "type": "Feature",
  "properties": {
    "iso:country":"GB",
    "wof:name":"KT19 8AA",
    "wof:placetype":"postalcode"
},
  "geometry": {"coordinates":[-0.28314952310727,51.34279483090744],"type":"Point"}
}