{
  "type": "Feature",
  "properties": {
    "iso:country": "GB",
    "wof:name": "SM7 1EB",
    "wof:placetype": "postalcode"
  },
  "geometry": {"coordinates":[-0.22272,51.32041],"type":"Point"}
}
