{
  "type": "Feature",
  "properties": {
    "date:inception_lower": "1980-01-01",
    "date:inception_upper": "1980-01-01",
    "iso:country": "GB",
    "wof:name": "SM7 1EB",
    "wof:placetype": "postalcode"
  },
  "geometry": {"coordinates":[-0.22272,51.32041],"type":"Point"}
}
