{
  "type": "Feature",
  "properties": {
    "iso:country":"GB",
    "wof:name":"PE9 1UR",
    "wof:placetype":"postalcode"
},
  "geometry": {"coordinates":[-0.46701482276683,52.66146207011929],"type":"Point"}
}