{
  "type": "Feature",
  "properties": {
    "date:inception_lower":"1980-01-01",
    "date:inception_upper":"1980-01-31",
    "iso:country":"GB",
    "wof:name":"PE9 1UR",
    "wof:placetype":"postalcode"
},
  "geometry": {"coordinates":[-0.467015,52.661462],"type":"Point"}
}