{
  "type": "Feature",
  "properties": {
    "iso:country":"GB",
    "wof:name":"NE29 8PD",
    "wof:placetype":"postalcode"
},
  "geometry": {"coordinates":[-1.46968747334919,55.02041639626498],"type":"Point"}
}