{
  "type": "Feature",
  "properties": {
    "iso:country": "GB",
    "wof:name": "HP13 7UH",
    "wof:placetype": "postalcode"
  },
  "geometry": {"coordinates":[-0.720321,51.625213],"type":"Point"}
}
