{
  "type": "Feature",
  "properties": {
    "iso:country":"GB",
    "wof:name":"HP13 7UH",
    "wof:placetype":"postalcode"
},
  "geometry": {"coordinates":[-0.72032113522329,51.62521331470901],"type":"Point"}
}