{
  "type": "Feature",
  "properties": {
    "date:inception_lower": "1980-01-01",
    "date:inception_upper": "1980-01-01",
    "iso:country": "GB",
    "wof:name": "SW19 3DJ",
    "wof:placetype": "postalcode"
  },
  "geometry": {"coordinates":[-0.193181,51.405919],"type":"Point"}
}
