{
  "type": "Feature",
  "properties": {
    "iso:country":"GB",
    "wof:name":"NE26 3DU",
    "wof:placetype":"postalcode"
},
  "geometry": {"coordinates":[-1.46399582799647,55.05196910437848],"type":"Point"}
}