{
  "type": "Feature",
  "properties": {
    "iso:country": "GB",
    "wof:name": "PE1 5LY",
    "wof:placetype": "postalcode"
  },
  "geometry": {"coordinates":[-0.218466,52.587974],"type":"Point"}
}
