{
  "type": "Feature",
  "properties": {
    "iso:country":"GB",
    "wof:name":"PE1 5LY",
    "wof:placetype":"postalcode"
},
  "geometry": {"coordinates":[-0.21846627966857,52.58797423424262],"type":"Point"}
}