{
  "type": "Feature",
  "properties": {
    "iso:country":"GB",
    "wof:name":"TA9 4EB",
    "wof:placetype":"postalcode"
},
  "geometry": {"coordinates":[-2.95201666302368,51.24982913820119],"type":"Point"}
}