{
  "type": "Feature",
  "properties": {
    "iso:country":"GB",
    "wof:name":"HA3 9JP",
    "wof:placetype":"postalcode"
},
  "geometry": {"coordinates":[-0.29795555848734,51.58880918551003],"type":"Point"}
}