{
  "type": "Feature",
  "properties": {
    "iso:country":"GB",
    "wof:name":"SS5 5NL",
    "wof:placetype":"postalcode"
},
  "geometry": {"coordinates":[0.65593396074563,51.61954248141292],"type":"Point"}
}