{
  "type": "Feature",
  "properties": {
    "iso:country":"GB",
    "wof:name":"GL6 7EY",
    "wof:placetype":"postalcode"
},
  "geometry": {"coordinates":[-2.15375165069798,51.78155178979351],"type":"Point"}
}