{
  "type": "Feature",
  "properties": {
    "iso:country":"GB",
    "wof:name":"DE1 1WG",
    "wof:placetype":"postalcode"
},
  "geometry": {"coordinates":[-1.4661393479782,52.91503955683449],"type":"Point"}
}