{
  "type": "Feature",
  "properties": {
    "date:inception_lower": "2016-05-01",
    "date:inception_upper": "2016-05-01",
    "iso:country": "GB",
    "wof:name": "W5 2JU",
    "wof:placetype": "postalcode"
  },
  "geometry": {"coordinates":[-0.306702,51.51404],"type":"Point"}
}
