{
  "type": "Feature",
  "properties": {
    "iso:country":"GB",
    "wof:name":"ST5 2JB",
    "wof:placetype":"postalcode"
},
  "geometry": {"coordinates":[-2.23880091035565,53.00064898462151],"type":"Point"}
}