{
  "type": "Feature",
  "properties": {
    "iso:country":"GB",
    "wof:name":"SO18 2GB",
    "wof:placetype":"postalcode"
},
  "geometry": {"coordinates":[-1.36304116438479,50.93300837677499],"type":"Point"}
}