{
  "type": "Feature",
  "properties": {
    "iso:country":"GB",
    "wof:name":"BB10 3DA",
    "wof:placetype":"postalcode"
},
  "geometry": {"coordinates":[-2.23030819869828,53.80204226777864],"type":"Point"}
}