{
  "type": "Feature",
  "properties": {
    "date:inception_lower":"1980-01-01",
    "date:inception_upper":"1980-01-31",
    "iso:country":"GB",
    "wof:name":"BB10 3DA",
    "wof:placetype":"postalcode"
},
  "geometry": {"coordinates":[-2.230308,53.802042],"type":"Point"}
}