{
  "type": "Feature",
  "properties": {
    "iso:country":"GB",
    "wof:name":"L31 3HA",
    "wof:placetype":"postalcode"
},
  "geometry": {"coordinates":[-2.93093909621084,53.50833739628487],"type":"Point"}
}