{
  "type": "Feature",
  "properties": {
    "iso:country":"GB",
    "wof:name":"DN14 7JX",
    "wof:placetype":"postalcode"
},
  "geometry": {"coordinates":[-0.90229186084705,53.77330637609032],"type":"Point"}
}