{
  "type": "Feature",
  "properties": {
    "date:inception_lower": "1988-03-01",
    "date:inception_upper": "1988-03-01",
    "iso:country": "GB",
    "wof:name": "NR13 5RN",
    "wof:placetype": "postalcode"
  },
  "geometry": {"coordinates":[1.426676,52.627016],"type":"Point"}
}
