{
  "type": "Feature",
  "properties": {
    "iso:country":"GB",
    "wof:name":"NR13 5RN",
    "wof:placetype":"postalcode"
},
  "geometry": {"coordinates":[1.42667644487548,52.62701614664487],"type":"Point"}
}