{
  "type": "Feature",
  "properties": {
    "iso:country": "GB",
    "wof:name": "WA14 2AT",
    "wof:placetype": "postalcode"
  },
  "geometry": {"coordinates":[-2.365265,53.386267],"type":"Point"}
}
