{
  "type": "Feature",
  "properties": {
    "iso:country":"GB",
    "wof:name":"WA14 2AT",
    "wof:placetype":"postalcode"
},
  "geometry": {"coordinates":[-2.3652648008465,53.38626687724161],"type":"Point"}
}