{
  "type": "Feature",
  "properties": {
    "iso:country":"GB",
    "wof:name":"SL0 0HS",
    "wof:placetype":"postalcode"
},
  "geometry": {"coordinates":[-0.52109337373767,51.52806113670071],"type":"Point"}
}