{
  "type": "Feature",
  "properties": {
    "iso:country": "GB",
    "wof:name": "WF13 9DA",
    "wof:placetype": "postalcode"
  },
  "geometry": {"coordinates":[-1.634178,53.687744],"type":"Point"}
}
