{
  "type": "Feature",
  "properties": {
    "iso:country":"GB",
    "wof:name":"BN16 3TW",
    "wof:placetype":"postalcode"
},
  "geometry": {"coordinates":[-0.51425470765973,50.82227070497841],"type":"Point"}
}