{
  "type": "Feature",
  "properties": {
    "date:inception_lower": "2000-06-01",
    "date:inception_upper": "2000-06-01",
    "iso:country": "GB",
    "wof:name": "BN16 3TW",
    "wof:placetype": "postalcode"
  },
  "geometry": {"coordinates":[-0.514255,50.822271],"type":"Point"}
}
