{
  "type": "Feature",
  "properties": {
    "iso:country": "GB",
    "wof:name": "BN16 3TW",
    "wof:placetype": "postalcode"
  },
  "geometry": {"coordinates":[-0.514255,50.822271],"type":"Point"}
}
