{
  "type": "Feature",
  "properties": {
    "iso:country": "GB",
    "wof:name": "BH23 3AG",
    "wof:placetype": "postalcode"
  },
  "geometry": {"coordinates":[-1.758875,50.742353],"type":"Point"}
}
