{
  "type": "Feature",
  "properties": {
    "iso:country":"GB",
    "wof:name":"BH23 3AG",
    "wof:placetype":"postalcode"
},
  "geometry": {"coordinates":[-1.7588748583609,50.74235281631373],"type":"Point"}
}