{
  "type": "Feature",
  "properties": {
    "iso:country":"GB",
    "wof:name":"ML2 8JL",
    "wof:placetype":"postalcode"
},
  "geometry": {"coordinates":[-3.90574779561084,55.77434949428277],"type":"Point"}
}