{
  "type": "Feature",
  "properties": {
    "date:inception_lower": "1980-01-01",
    "date:inception_upper": "1980-01-01",
    "iso:country": "GB",
    "wof:name": "BN1 9PY",
    "wof:placetype": "postalcode"
  },
  "geometry": {"coordinates":[-0.094018,50.85979],"type":"Point"}
}
