{
  "type": "Feature",
  "properties": {
    "iso:country":"GB",
    "wof:name":"BN1 9PY",
    "wof:placetype":"postalcode"
},
  "geometry": {"coordinates":[-0.09401756744485,50.85978962876761],"type":"Point"}
}