{
  "type": "Feature",
  "properties": {
    "iso:country":"GB",
    "wof:name":"DL8 3EP",
    "wof:placetype":"postalcode"
},
  "geometry": {"coordinates":[-2.13136542643628,54.30670026440329],"type":"Point"}
}