{
  "type": "Feature",
  "properties": {
    "iso:country": "GB",
    "wof:name": "EX16 6FQ",
    "wof:placetype": "postalcode"
  },
  "geometry": {"coordinates":[-3.479284,50.917027],"type":"Point"}
}
