{
  "type": "Feature",
  "properties": {
    "iso:country":"GB",
    "wof:name":"BA5 2AW",
    "wof:placetype":"postalcode"
},
  "geometry": {"coordinates":[-2.65120717055278,51.20794581897827],"type":"Point"}
}