{
  "type": "Feature",
  "properties": {
    "iso:country": "GB",
    "wof:name": "BA5 2AW",
    "wof:placetype": "postalcode"
  },
  "geometry": {"coordinates":[-2.651207,51.207946],"type":"Point"}
}
