{
  "type": "Feature",
  "properties": {
    "iso:country":"GB",
    "wof:name":"HA7 4UB",
    "wof:placetype":"postalcode"
},
  "geometry": {"coordinates":[-0.30569762220241,51.61584384949057],"type":"Point"}
}