{
  "type": "Feature",
  "properties": {
    "iso:country":"GB",
    "wof:name":"PL24 2SA",
    "wof:placetype":"postalcode"
},
  "geometry": {"coordinates":[-4.71401409419392,50.38247917249821],"type":"Point"}
}