{
  "type": "Feature",
  "properties": {
    "date:inception_lower": "1980-01-01",
    "date:inception_upper": "1980-01-01",
    "iso:country": "GB",
    "wof:name": "NE31 1ED",
    "wof:placetype": "postalcode"
  },
  "geometry": {"coordinates":[-1.525957,54.979671],"type":"Point"}
}
