{
  "type": "Feature",
  "properties": {
    "iso:country": "GB",
    "wof:name": "BN12 5BG",
    "wof:placetype": "postalcode"
  },
  "geometry": {"coordinates":[-0.439456,50.812634],"type":"Point"}
}
