{
  "type": "Feature",
  "properties": {
    "iso:country":"GB",
    "wof:name":"BN12 5BG",
    "wof:placetype":"postalcode"
},
  "geometry": {"coordinates":[-0.4394563748805,50.81263383613686],"type":"Point"}
}