{
  "type": "Feature",
  "properties": {
    "iso:country": "GB",
    "wof:name": "WF12 7EU",
    "wof:placetype": "postalcode"
  },
  "geometry": {"coordinates":[-1.610782,53.702306],"type":"Point"}
}
