{
  "type": "Feature",
  "properties": {
    "date:inception_lower": "1980-01-01",
    "date:inception_upper": "1980-01-01",
    "iso:country": "GB",
    "wof:name": "B63 4LA",
    "wof:placetype": "postalcode"
  },
  "geometry": {"coordinates":[-2.067258,52.443827],"type":"Point"}
}
