{
  "type": "Feature",
  "properties": {
    "iso:country":"GB",
    "wof:name":"B63 4LA",
    "wof:placetype":"postalcode"
},
  "geometry": {"coordinates":[-2.06726357873601,52.44381222189565],"type":"Point"}
}