{
  "type": "Feature",
  "properties": {
    "iso:country": "GB",
    "wof:name": "B63 4LA",
    "wof:placetype": "postalcode"
  },
  "geometry": {"coordinates":[-2.067258,52.443827],"type":"Point"}
}
