{
  "type": "Feature",
  "properties": {
    "iso:country":"GB",
    "wof:name":"TQ13 8SP",
    "wof:placetype":"postalcode"
},
  "geometry": {"coordinates":[-3.75542314542297,50.66414388097957],"type":"Point"}
}