{
  "type": "Feature",
  "properties": {
    "date:inception_lower": "1980-01-01",
    "date:inception_upper": "1980-01-01",
    "iso:country": "GB",
    "wof:name": "TQ13 8SP",
    "wof:placetype": "postalcode"
  },
  "geometry": {"coordinates":[-3.754081,50.663346],"type":"Point"}
}
