{
  "type": "Feature",
  "properties": {
    "iso:country": "GB",
    "wof:name": "DG8 9HR",
    "wof:placetype": "postalcode"
  },
  "geometry": {"coordinates":[-4.4406,54.868873],"type":"Point"}
}
