{
  "type": "Feature",
  "properties": {
    "iso:country":"GB",
    "wof:name":"PR1 3TB",
    "wof:placetype":"postalcode"
},
  "geometry": {"coordinates":[-2.69568746089847,53.75391060625036],"type":"Point"}
}