{
  "type": "Feature",
  "properties": {
    "iso:country": "GB",
    "wof:name": "PR1 3TB",
    "wof:placetype": "postalcode"
  },
  "geometry": {"coordinates":[-2.695687,53.753911],"type":"Point"}
}
