{
  "type": "Feature",
  "properties": {
    "iso:country":"GB",
    "wof:name":"BB4 6NL",
    "wof:placetype":"postalcode"
},
  "geometry": {"coordinates":[-2.32296639459241,53.70255514958921],"type":"Point"}
}