{
  "type": "Feature",
  "properties": {
    "iso:country":"GB",
    "wof:name":"BA12 7PQ",
    "wof:placetype":"postalcode"
},
  "geometry": {"coordinates":[-2.2731864131878,51.209394733218],"type":"Point"}
}