{
  "type": "Feature",
  "properties": {
    "iso:country": "GB",
    "wof:name": "TS10 4GQ",
    "wof:placetype": "postalcode"
  },
  "geometry": {"coordinates":[-1.078022,54.601828],"type":"Point"}
}
