{
  "type": "Feature",
  "properties": {
    "date:inception_lower":"2008-11-01",
    "date:inception_upper":"2008-11-30",
    "iso:country":"GB",
    "wof:name":"TS10 4GQ",
    "wof:placetype":"postalcode"
},
  "geometry": {"coordinates":[-1.078022,54.601828],"type":"Point"}
}