{
  "type": "Feature",
  "properties": {
    "iso:country":"GB",
    "wof:name":"TS10 4GQ",
    "wof:placetype":"postalcode"
},
  "geometry": {"coordinates":[-1.07802203468488,54.60182843333362],"type":"Point"}
}