{
  "type": "Feature",
  "properties": {
    "iso:country":"GB",
    "wof:name":"PO31 8NT",
    "wof:placetype":"postalcode"
},
  "geometry": {"coordinates":[-1.33271126965483,50.75403915913691],"type":"Point"}
}