{
  "type": "Feature",
  "properties": {
    "date:inception_lower": "1980-01-01",
    "date:inception_upper": "1980-01-01",
    "iso:country": "GB",
    "wof:name": "PO31 8NT",
    "wof:placetype": "postalcode"
  },
  "geometry": {"coordinates":[-1.332711,50.754039],"type":"Point"}
}
