{
  "type": "Feature",
  "properties": {
    "iso:country":"GB",
    "wof:name":"G12 8TA",
    "wof:placetype":"postalcode"
},
  "geometry": {"coordinates":[-4.29575094803327,55.87293494427433],"type":"Point"}
}