{
  "type": "Feature",
  "properties": {
    "date:inception_lower":"1996-12-01",
    "date:inception_upper":"1996-12-31",
    "iso:country":"GB",
    "wof:name":"G12 8TA",
    "wof:placetype":"postalcode"
},
  "geometry": {"coordinates":[-4.295751,55.872935],"type":"Point"}
}