{
  "type": "Feature",
  "properties": {
    "date:inception_lower": "1996-12-01",
    "date:inception_upper": "1996-12-01",
    "iso:country": "GB",
    "wof:name": "G12 8TA",
    "wof:placetype": "postalcode"
  },
  "geometry": {"coordinates":[-4.294994,55.873078],"type":"Point"}
}
