{
  "type": "Feature",
  "properties": {
    "iso:country":"GB",
    "wof:name":"N14 4SS",
    "wof:placetype":"postalcode"
},
  "geometry": {"coordinates":[-0.12319926837068,51.64473909612028],"type":"Point"}
}