{
  "type": "Feature",
  "properties": {
    "iso:country":"GB",
    "wof:name":"EX9 7DH",
    "wof:placetype":"postalcode"
},
  "geometry": {"coordinates":[-3.32090415621687,50.65237969607722],"type":"Point"}
}