{
  "type": "Feature",
  "properties": {
    "iso:country": "GB",
    "wof:name": "EX9 7DH",
    "wof:placetype": "postalcode"
  },
  "geometry": {"coordinates":[-3.320904,50.65238],"type":"Point"}
}
