{
  "type": "Feature",
  "properties": {
    "iso:country":"GB",
    "wof:name":"CW5 5BG",
    "wof:placetype":"postalcode"
},
  "geometry": {"coordinates":[-2.52104192598141,53.06551176545563],"type":"Point"}
}