{
  "type": "Feature",
  "properties": {
    "iso:country":"GB",
    "wof:name":"SW11 2EE",
    "wof:placetype":"postalcode"
},
  "geometry": {"coordinates":[-0.17282181715528,51.46612318477349],"type":"Point"}
}