{
  "type": "Feature",
  "properties": {
    "date:inception_lower": "1980-01-01",
    "date:inception_upper": "1980-01-01",
    "iso:country": "GB",
    "wof:name": "SW11 2EE",
    "wof:placetype": "postalcode"
  },
  "geometry": {"coordinates":[-0.172822,51.466123],"type":"Point"}
}
