{
  "type": "Feature",
  "properties": {
    "iso:country": "GB",
    "wof:name": "DN21 3AY",
    "wof:placetype": "postalcode"
  },
  "geometry": {"coordinates":[-0.784153,53.415255],"type":"Point"}
}
