{
  "type": "Feature",
  "properties": {
    "date:inception_lower":"1995-01-01",
    "date:inception_upper":"1995-01-31",
    "iso:country":"GB",
    "wof:name":"NG2 7EZ",
    "wof:placetype":"postalcode"
},
  "geometry": {"coordinates":[-1.148844,52.921713],"type":"Point"}
}