{
  "type": "Feature",
  "properties": {
    "iso:country":"GB",
    "wof:name":"NG2 7EZ",
    "wof:placetype":"postalcode"
},
  "geometry": {"coordinates":[-1.14884383562755,52.92171295728473],"type":"Point"}
}