{
  "type": "Feature",
  "properties": {
    "iso:country":"GB",
    "wof:name":"PO21 3NH",
    "wof:placetype":"postalcode"
},
  "geometry": {"coordinates":[-0.72827596551243,50.78062594762905],"type":"Point"}
}