{
  "type": "Feature",
  "properties": {
    "iso:country":"GB",
    "wof:name":"PE2 6YY",
    "wof:placetype":"postalcode"
},
  "geometry": {"coordinates":[-0.31157500831916,52.55673761102798],"type":"Point"}
}