{
  "type": "Feature",
  "properties": {
    "iso:country": "GB",
    "wof:name": "RH10 6AT",
    "wof:placetype": "postalcode"
  },
  "geometry": {"coordinates":[-0.190518,51.109592],"type":"Point"}
}
