{
  "type": "Feature",
  "properties": {
    "iso:country":"GB",
    "wof:name":"AB54 7PQ",
    "wof:placetype":"postalcode"
},
  "geometry": {"coordinates":[-2.65272638209136,57.57579303444127],"type":"Point"}
}