{
  "type": "Feature",
  "properties": {
    "date:inception_lower": "1980-01-01",
    "date:inception_upper": "1980-01-01",
    "iso:country": "GB",
    "wof:name": "BN14 9LY",
    "wof:placetype": "postalcode"
  },
  "geometry": {"coordinates":[-0.372731,50.832128],"type":"Point"}
}
