{
  "type": "Feature",
  "properties": {
    "date:inception_lower": "2001-12-01",
    "date:inception_upper": "2001-12-01",
    "iso:country": "GB",
    "wof:name": "CF14 0UN",
    "wof:placetype": "postalcode"
  },
  "geometry": {"coordinates":[-3.17889,51.542281],"type":"Point"}
}
