{
  "type": "Feature",
  "properties": {
    "iso:country":"GB",
    "wof:name":"CF14 0UN",
    "wof:placetype":"postalcode"
},
  "geometry": {"coordinates":[-3.17887992139497,51.54228008733887],"type":"Point"}
}