{
  "type": "Feature",
  "properties": {
    "iso:country":"GB",
    "wof:name":"WR6 6PB",
    "wof:placetype":"postalcode"
},
  "geometry": {"coordinates":[-2.36214904796457,52.23876682031045],"type":"Point"}
}