{
  "type": "Feature",
  "properties": {
    "iso:country":"GB",
    "wof:name":"NN17 1LT",
    "wof:placetype":"postalcode"
},
  "geometry": {"coordinates":[-0.69978025903968,52.49929718295036],"type":"Point"}
}