{
  "type": "Feature",
  "properties": {
    "iso:country":"GB",
    "wof:name":"NG16 2FB",
    "wof:placetype":"postalcode"
},
  "geometry": {"coordinates":[-1.27952347308747,53.02038161908995],"type":"Point"}
}