{
  "type": "Feature",
  "properties": {
    "iso:country": "GB",
    "wof:name": "NG16 2FB",
    "wof:placetype": "postalcode"
  },
  "geometry": {"coordinates":[-1.279523,53.020382],"type":"Point"}
}
