{
  "type": "Feature",
  "properties": {
    "iso:country": "GB",
    "wof:name": "DN8 5FE",
    "wof:placetype": "postalcode"
  },
  "geometry": {"coordinates":[-0.972219,53.61217],"type":"Point"}
}
