{
  "type": "Feature",
  "properties": {
    "iso:country":"GB",
    "wof:name":"N22 8PZ",
    "wof:placetype":"postalcode"
},
  "geometry": {"coordinates":[-0.11425485477964,51.60356353526917],"type":"Point"}
}