{
  "type": "Feature",
  "properties": {
    "iso:country": "GB",
    "wof:name": "DG8 0HG",
    "wof:placetype": "postalcode"
  },
  "geometry": {"coordinates":[-4.608914,54.913655],"type":"Point"}
}
