{
  "type": "Feature",
  "properties": {
    "iso:country":"GB",
    "wof:name":"W6 7BT",
    "wof:placetype":"postalcode"
},
  "geometry": {"coordinates":[-0.21588285361709,51.4938177020255],"type":"Point"}
}