{
  "type": "Feature",
  "properties": {
    "iso:country": "GB",
    "wof:name": "LE9 6WF",
    "wof:placetype": "postalcode"
  },
  "geometry": {"coordinates":[-1.220393,52.521915],"type":"Point"}
}
