{
  "type": "Feature",
  "properties": {
    "iso:country":"GB",
    "wof:name":"LE9 6WF",
    "wof:placetype":"postalcode"
},
  "geometry": {"coordinates":[-1.22039271424166,52.52191458528991],"type":"Point"}
}