{
  "type": "Feature",
  "properties": {
    "date:inception_lower":"1992-01-01",
    "date:inception_upper":"1992-01-31",
    "iso:country":"GB",
    "wof:name":"LE9 6WF",
    "wof:placetype":"postalcode"
},
  "geometry": {"coordinates":[-1.220393,52.521915],"type":"Point"}
}