{
  "type": "Feature",
  "properties": {
    "iso:country":"GB",
    "wof:name":"LN6 7DH",
    "wof:placetype":"postalcode"
},
  "geometry": {"coordinates":[-0.55608481450533,53.22922203460715],"type":"Point"}
}