{
  "type": "Feature",
  "properties": {
    "iso:country":"GB",
    "wof:name":"NP4 7HX",
    "wof:placetype":"postalcode"
},
  "geometry": {"coordinates":[-3.07129212231561,51.73053537985984],"type":"Point"}
}