{
  "type": "Feature",
  "properties": {
    "iso:country":"GB",
    "wof:name":"BN13 3RP",
    "wof:placetype":"postalcode"
},
  "geometry": {"coordinates":[-0.42985080256229,50.82943913996067],"type":"Point"}
}