{
  "type": "Feature",
  "properties": {
    "date:inception_lower":"1980-01-01",
    "date:inception_upper":"1980-01-31",
    "iso:country":"GB",
    "wof:name":"LL11 2BU",
    "wof:placetype":"postalcode"
},
  "geometry": {"coordinates":[-3.005062,53.05829],"type":"Point"}
}