{
  "type": "Feature",
  "properties": {
    "iso:country": "GB",
    "wof:name": "LL11 2BU",
    "wof:placetype": "postalcode"
  },
  "geometry": {"coordinates":[-3.005062,53.05829],"type":"Point"}
}
