{
  "type": "Feature",
  "properties": {
    "date:inception_lower": "2024-01-01",
    "date:inception_upper": "2024-01-01",
    "iso:country": "GB",
    "wof:name": "S60 8DT",
    "wof:placetype": "postalcode"
  },
  "geometry": {"coordinates":[-1.369562,53.387087],"type":"Point"}
}
