{
  "type": "Feature",
  "properties": {
    "iso:country":"GB",
    "wof:name":"DN21 5HA",
    "wof:placetype":"postalcode"
},
  "geometry": {"coordinates":[-0.73830618071044,53.36086230086882],"type":"Point"}
}