{
  "type": "Feature",
  "properties": {
    "iso:country":"GB",
    "wof:name":"NR17 2AG",
    "wof:placetype":"postalcode"
},
  "geometry": {"coordinates":[1.01509746823674,52.51845448868962],"type":"Point"}
}