{
  "type": "Feature",
  "properties": {
    "iso:country":"GB",
    "wof:name":"RG12 7JR",
    "wof:placetype":"postalcode"
},
  "geometry": {"coordinates":[-0.75465739385907,51.40122509332428],"type":"Point"}
}