{
  "type": "Feature",
  "properties": {
    "date:inception_lower": "2016-10-01",
    "date:inception_upper": "2016-10-01",
    "iso:country": "GB",
    "wof:name": "HP12 3FU",
    "wof:placetype": "postalcode"
  },
  "geometry": {"coordinates":[-0.771677,51.621872],"type":"Point"}
}
