{
  "type": "Feature",
  "properties": {
    "date:inception_lower":"1980-01-01",
    "date:inception_upper":"1980-01-31",
    "iso:country":"GB",
    "wof:name":"SW13 0DU",
    "wof:placetype":"postalcode"
},
  "geometry": {"coordinates":[-0.240115,51.472458],"type":"Point"}
}