{
  "type": "Feature",
  "properties": {
    "iso:country":"GB",
    "wof:name":"SW13 0DU",
    "wof:placetype":"postalcode"
},
  "geometry": {"coordinates":[-0.24011467070173,51.47245811215875],"type":"Point"}
}