{
  "type": "Feature",
  "properties": {
    "iso:country":"GB",
    "wof:name":"AB45 3XL",
    "wof:placetype":"postalcode"
},
  "geometry": {"coordinates":[-2.53526401859284,57.58595683891967],"type":"Point"}
}