{
  "type": "Feature",
  "properties": {
    "iso:country":"GB",
    "wof:name":"B12 0TA",
    "wof:placetype":"postalcode"
},
  "geometry": {"coordinates":[-1.88825940841647,52.46825873190538],"type":"Point"}
}