{
  "type": "Feature",
  "properties": {
    "date:inception_lower": "2008-06-01",
    "date:inception_upper": "2008-06-01",
    "iso:country": "GB",
    "wof:name": "CF14 5BD",
    "wof:placetype": "postalcode"
  },
  "geometry": {"coordinates":[-3.19659,51.527534],"type":"Point"}
}
