{
  "type": "Feature",
  "properties": {
    "iso:country": "GB",
    "wof:name": "SL6 3RQ",
    "wof:placetype": "postalcode"
  },
  "geometry": {"coordinates":[-0.793988,51.514917],"type":"Point"}
}
