{
  "type": "Feature",
  "properties": {
    "iso:country":"GB",
    "wof:name":"SL6 3RQ",
    "wof:placetype":"postalcode"
},
  "geometry": {"coordinates":[-0.79398760549543,51.51491721294283],"type":"Point"}
}