{
  "type": "Feature",
  "properties": {
    "iso:country":"GB",
    "wof:name":"LS8 4AL",
    "wof:placetype":"postalcode"
},
  "geometry": {"coordinates":[-1.51229556305253,53.82519053246076],"type":"Point"}
}