{
  "type": "Feature",
  "properties": {
    "iso:country":"GB",
    "wof:name":"M14 5DQ",
    "wof:placetype":"postalcode"
},
  "geometry": {"coordinates":[-2.20981261457498,53.45533203208658],"type":"Point"}
}