{
  "type": "Feature",
  "properties": {
    "iso:country":"GB",
    "wof:name":"B98 7XQ",
    "wof:placetype":"postalcode"
},
  "geometry": {"coordinates":[-1.93321613049335,52.28164866824184],"type":"Point"}
}