{
  "type": "Feature",
  "properties": {
    "iso:country":"GB",
    "wof:name":"LN9 6NG",
    "wof:placetype":"postalcode"
},
  "geometry": {"coordinates":[-0.10459948734522,53.20136536293709],"type":"Point"}
}