{
  "type": "Feature",
  "properties": {
    "iso:country":"GB",
    "wof:name":"KY16 0BP",
    "wof:placetype":"postalcode"
},
  "geometry": {"coordinates":[-2.90934694441339,56.38636193700001],"type":"Point"}
}