{
  "type": "Feature",
  "properties": {
    "date:inception_lower": "1980-01-01",
    "date:inception_upper": "1980-01-01",
    "iso:country": "GB",
    "wof:name": "KY16 0BP",
    "wof:placetype": "postalcode"
  },
  "geometry": {"coordinates":[-2.909204,56.386345],"type":"Point"}
}
