{
  "type": "Feature",
  "properties": {
    "iso:country": "GB",
    "wof:name": "KY16 0BP",
    "wof:placetype": "postalcode"
  },
  "geometry": {"coordinates":[-2.909347,56.386362],"type":"Point"}
}
