{
  "type": "Feature",
  "properties": {
    "date:inception_lower": "1980-01-01",
    "date:inception_upper": "1980-01-01",
    "iso:country": "GB",
    "wof:name": "GU29 9HL",
    "wof:placetype": "postalcode"
  },
  "geometry": {"coordinates":[-0.747103,50.984014],"type":"Point"}
}
