{
  "type": "Feature",
  "properties": {
    "iso:country":"GB",
    "wof:name":"RG19 8BH",
    "wof:placetype":"postalcode"
},
  "geometry": {"coordinates":[-1.20369102967015,51.35086960016917],"type":"Point"}
}