{
  "type": "Feature",
  "properties": {
    "date:inception_lower":"1995-07-01",
    "date:inception_upper":"1995-07-31",
    "iso:country":"GB",
    "wof:name":"RG19 8BH",
    "wof:placetype":"postalcode"
},
  "geometry": {"coordinates":[-1.203691,51.35087],"type":"Point"}
}