{
  "type": "Feature",
  "properties": {
    "date:inception_lower":"1986-07-01",
    "date:inception_upper":"1986-07-31",
    "iso:country":"GB",
    "wof:name":"WF7 7PP",
    "wof:placetype":"postalcode"
},
  "geometry": {"coordinates":[-1.316388,53.651885],"type":"Point"}
}