{
  "type": "Feature",
  "properties": {
    "iso:country":"GB",
    "wof:name":"CO6 1LG",
    "wof:placetype":"postalcode"
},
  "geometry": {"coordinates":[0.80352899220066,51.88051132364189],"type":"Point"}
}