{
  "type": "Feature",
  "properties": {
    "date:inception_lower": "1980-01-01",
    "date:inception_upper": "1980-01-01",
    "iso:country": "GB",
    "wof:name": "CO6 1LG",
    "wof:placetype": "postalcode"
  },
  "geometry": {"coordinates":[0.803698,51.880681],"type":"Point"}
}
