{
  "type": "Feature",
  "properties": {
    "date:inception_lower":"1992-05-01",
    "date:inception_upper":"1992-05-31",
    "iso:country":"GB",
    "wof:name":"EH1 1NS",
    "wof:placetype":"postalcode"
},
  "geometry": {"coordinates":[-3.186376,55.94842],"type":"Point"}
}