{
  "type": "Feature",
  "properties": {
    "iso:country": "GB",
    "wof:name": "EH1 1NS",
    "wof:placetype": "postalcode"
  },
  "geometry": {"coordinates":[-3.186376,55.94842],"type":"Point"}
}
