{
  "type": "Feature",
  "properties": {
    "iso:country": "GB",
    "wof:name": "NN2 7JN",
    "wof:placetype": "postalcode"
  },
  "geometry": {"coordinates":[-0.891963,52.258155],"type":"Point"}
}
