{
  "type": "Feature",
  "properties": {
    "iso:country":"GB",
    "wof:name":"NN2 7JN",
    "wof:placetype":"postalcode"
},
  "geometry": {"coordinates":[-0.89218726286451,52.25797069087869],"type":"Point"}
}