{
  "type": "Feature",
  "properties": {
    "iso:country": "GB",
    "wof:name": "MK11 1JR",
    "wof:placetype": "postalcode"
  },
  "geometry": {"coordinates":[-0.853275,52.054819],"type":"Point"}
}
