{
  "type": "Feature",
  "properties": {
    "iso:country":"GB",
    "wof:name":"MK11 1JR",
    "wof:placetype":"postalcode"
},
  "geometry": {"coordinates":[-0.85327493445109,52.05481852948792],"type":"Point"}
}