{
  "type": "Feature",
  "properties": {
    "iso:country":"GB",
    "wof:name":"OL12 7LE",
    "wof:placetype":"postalcode"
},
  "geometry": {"coordinates":[-2.18489597103204,53.62973833606629],"type":"Point"}
}