{
  "type": "Feature",
  "properties": {
    "iso:country":"GB",
    "wof:name":"KA3 4DT",
    "wof:placetype":"postalcode"
},
  "geometry": {"coordinates":[-4.51487574097191,55.73168904690482],"type":"Point"}
}