{
  "type": "Feature",
  "properties": {
    "iso:country":"GB",
    "wof:name":"SA15 3HR",
    "wof:placetype":"postalcode"
},
  "geometry": {"coordinates":[-4.16350024344963,51.68717862596584],"type":"Point"}
}