{
  "type": "Feature",
  "properties": {
    "date:inception_lower": "2001-06-01",
    "date:inception_upper": "2001-06-01",
    "iso:country": "GB",
    "wof:name": "L3 5TP",
    "wof:placetype": "postalcode"
  },
  "geometry": {"coordinates":[-2.973191,53.404377],"type":"Point"}
}
