{
  "type": "Feature",
  "properties": {
    "iso:country":"GB",
    "wof:name":"L3 5TP",
    "wof:placetype":"postalcode"
},
  "geometry": {"coordinates":[-2.9731913666223,53.40437735411817],"type":"Point"}
}