{
  "type": "Feature",
  "properties": {
    "date:inception_lower": "2019-05-01",
    "date:inception_upper": "2019-05-01",
    "iso:country": "GB",
    "wof:name": "CW4 7FX",
    "wof:placetype": "postalcode"
  },
  "geometry": {"coordinates":[-2.353592,53.191514],"type":"Point"}
}
