{
  "type": "Feature",
  "properties": {
    "date:inception_lower":"1996-06-01",
    "date:inception_upper":"1996-06-30",
    "iso:country":"GB",
    "wof:name":"PE24 4NL",
    "wof:placetype":"postalcode"
},
  "geometry": {"coordinates":[0.199071,53.123321],"type":"Point"}
}