{
  "type": "Feature",
  "properties": {
    "iso:country":"GB",
    "wof:name":"PE24 4NL",
    "wof:placetype":"postalcode"
},
  "geometry": {"coordinates":[0.19906687136245,53.12329447265574],"type":"Point"}
}