{
  "type": "Feature",
  "properties": {
    "iso:country": "GB",
    "wof:name": "PE24 4NL",
    "wof:placetype": "postalcode"
  },
  "geometry": {"coordinates":[0.199216,53.123526],"type":"Point"}
}
