{
  "type": "Feature",
  "properties": {
    "iso:country":"GB",
    "wof:name":"CM2 9QA",
    "wof:placetype":"postalcode"
},
  "geometry": {"coordinates":[0.4679940884491,51.72230898698178],"type":"Point"}
}