{
  "type": "Feature",
  "properties": {
    "iso:country":"GB",
    "wof:name":"GU16 6DF",
    "wof:placetype":"postalcode"
},
  "geometry": {"coordinates":[-0.72499361810091,51.28812611759782],"type":"Point"}
}