{
  "type": "Feature",
  "properties": {
    "date:inception_lower": "1988-03-01",
    "date:inception_upper": "1988-03-01",
    "iso:country": "GB",
    "wof:name": "B46 1NA",
    "wof:placetype": "postalcode"
  },
  "geometry": {"coordinates":[-1.743273,52.520202],"type":"Point"}
}
