{
  "type": "Feature",
  "properties": {
    "iso:country":"GB",
    "wof:name":"B46 1NA",
    "wof:placetype":"postalcode"
},
  "geometry": {"coordinates":[-1.74327254416122,52.52020200105064],"type":"Point"}
}