{
  "type": "Feature",
  "properties": {
    "iso:country":"GB",
    "wof:name":"DY2 9EB",
    "wof:placetype":"postalcode"
},
  "geometry": {"coordinates":[-2.08385689895533,52.49688738719848],"type":"Point"}
}