{
  "type": "Feature",
  "properties": {
    "date:inception_lower": "1980-01-01",
    "date:inception_upper": "1980-01-01",
    "iso:country": "GB",
    "wof:name": "PR2 6AX",
    "wof:placetype": "postalcode"
  },
  "geometry": {"coordinates":[-2.662014,53.777722],"type":"Point"}
}
