{
  "type": "Feature",
  "properties": {
    "iso:country":"GB",
    "wof:name":"PR2 6AX",
    "wof:placetype":"postalcode"
},
  "geometry": {"coordinates":[-2.66201396667491,53.77772232734682],"type":"Point"}
}