{
  "type": "Feature",
  "properties": {
    "iso:country": "GB",
    "wof:name": "LL22 7NU",
    "wof:placetype": "postalcode"
  },
  "geometry": {"coordinates":[-3.576836,53.287816],"type":"Point"}
}
