{
  "type": "Feature",
  "properties": {
    "iso:country":"GB",
    "wof:name":"SM5 1AH",
    "wof:placetype":"postalcode"
},
  "geometry": {"coordinates":[-0.183465361727,51.38513054206927],"type":"Point"}
}