{
  "type": "Feature",
  "properties": {
    "date:inception_lower": "1998-12-01",
    "date:inception_upper": "1998-12-01",
    "iso:country": "GB",
    "wof:name": "TQ4 7NG",
    "wof:placetype": "postalcode"
  },
  "geometry": {"coordinates":[-3.590588,50.412864],"type":"Point"}
}
