{
  "type": "Feature",
  "properties": {
    "iso:country": "GB",
    "wof:name": "TQ4 7NG",
    "wof:placetype": "postalcode"
  },
  "geometry": {"coordinates":[-3.590588,50.412864],"type":"Point"}
}
