{
  "type": "Feature",
  "properties": {
    "iso:country": "GB",
    "wof:name": "MK18 3LE",
    "wof:placetype": "postalcode"
  },
  "geometry": {"coordinates":[-0.860281,51.92492],"type":"Point"}
}
