{
  "type": "Feature",
  "properties": {
    "iso:country":"GB",
    "wof:name":"MK18 3LE",
    "wof:placetype":"postalcode"
},
  "geometry": {"coordinates":[-0.86028150288945,51.92491960045299],"type":"Point"}
}