{
  "type": "Feature",
  "properties": {
    "iso:country":"GB",
    "wof:name":"EH45 9EX",
    "wof:placetype":"postalcode"
},
  "geometry": {"coordinates":[-3.19139323480453,55.64771909555968],"type":"Point"}
}