{
  "type": "Feature",
  "properties": {
    "iso:country": "GB",
    "wof:name": "PR6 7RN",
    "wof:placetype": "postalcode"
  },
  "geometry": {"coordinates":[-2.635137,53.70118],"type":"Point"}
}
