{
  "type": "Feature",
  "properties": {
    "iso:country":"GB",
    "wof:name":"PR6 7RN",
    "wof:placetype":"postalcode"
},
  "geometry": {"coordinates":[-2.63513716500019,53.70118036994988],"type":"Point"}
}