{
  "type": "Feature",
  "properties": {
    "iso:country":"GB",
    "wof:name":"CO7 7UZ",
    "wof:placetype":"postalcode"
},
  "geometry": {"coordinates":[1.02399333664998,51.90410720088725],"type":"Point"}
}