{
  "type": "Feature",
  "properties": {
    "iso:country": "GB",
    "wof:name": "CO7 7UZ",
    "wof:placetype": "postalcode"
  },
  "geometry": {"coordinates":[1.023993,51.904107],"type":"Point"}
}
