{
  "type": "Feature",
  "properties": {
    "date:inception_lower":"1980-01-01",
    "date:inception_upper":"1980-01-31",
    "iso:country":"GB",
    "wof:name":"B80 7DS",
    "wof:placetype":"postalcode"
},
  "geometry": {"coordinates":[-1.866568,52.29541],"type":"Point"}
}