{
  "type": "Feature",
  "properties": {
    "iso:country":"GB",
    "wof:name":"YO21 3TQ",
    "wof:placetype":"postalcode"
},
  "geometry": {"coordinates":[-0.67708908832028,54.50270822145205],"type":"Point"}
}