{
  "type": "Feature",
  "properties": {
    "iso:country": "GB",
    "wof:name": "ST6 1AJ",
    "wof:placetype": "postalcode"
  },
  "geometry": {"coordinates":[-2.193002,53.048554],"type":"Point"}
}
