{
  "type": "Feature",
  "properties": {
    "iso:country": "GB",
    "wof:name": "BN6 8YJ",
    "wof:placetype": "postalcode"
  },
  "geometry": {"coordinates":[-0.138706,50.928995],"type":"Point"}
}
