{
  "type": "Feature",
  "properties": {
    "iso:country":"GB",
    "wof:name":"BL8 3DB",
    "wof:placetype":"postalcode"
},
  "geometry": {"coordinates":[-2.34045529236767,53.60417555558284],"type":"Point"}
}