{
  "type": "Feature",
  "properties": {
    "iso:country":"GB",
    "wof:name":"TN22 1BZ",
    "wof:placetype":"postalcode"
},
  "geometry": {"coordinates":[0.09371602635251,50.97567425021121],"type":"Point"}
}