{
  "type": "Feature",
  "properties": {
    "iso:country": "GB",
    "wof:name": "TN22 1BZ",
    "wof:placetype": "postalcode"
  },
  "geometry": {"coordinates":[0.093594,50.975547],"type":"Point"}
}
