{
  "type": "Feature",
  "properties": {
    "date:inception_lower": "1980-01-01",
    "date:inception_upper": "1980-01-01",
    "iso:country": "GB",
    "wof:name": "TN22 1BZ",
    "wof:placetype": "postalcode"
  },
  "geometry": {"coordinates":[0.093594,50.975547],"type":"Point"}
}
