{
  "type": "Feature",
  "properties": {
    "iso:country": "GB",
    "wof:name": "HR3 6QU",
    "wof:placetype": "postalcode"
  },
  "geometry": {"coordinates":[-2.956362,52.169365],"type":"Point"}
}
