{
  "type": "Feature",
  "properties": {
    "iso:country":"GB",
    "wof:name":"HR3 6QU",
    "wof:placetype":"postalcode"
},
  "geometry": {"coordinates":[-2.95636217038321,52.16936531134644],"type":"Point"}
}