{
  "type": "Feature",
  "properties": {
    "iso:country": "GB",
    "wof:name": "CM14 4PJ",
    "wof:placetype": "postalcode"
  },
  "geometry": {"coordinates":[0.279296,51.611391],"type":"Point"}
}
