{
  "type": "Feature",
  "properties": {
    "iso:country":"GB",
    "wof:name":"EX39 4HP",
    "wof:placetype":"postalcode"
},
  "geometry": {"coordinates":[-4.17913585355878,51.04818164564747],"type":"Point"}
}