{
  "type": "Feature",
  "properties": {
    "iso:country":"GB",
    "wof:name":"BR7 5AX",
    "wof:placetype":"postalcode"
},
  "geometry": {"coordinates":[0.06792611853609,51.41697070269682],"type":"Point"}
}