{
  "type": "Feature",
  "properties": {
    "date:inception_lower": "1994-12-01",
    "date:inception_upper": "1994-12-01",
    "iso:country": "GB",
    "wof:name": "BR7 5AX",
    "wof:placetype": "postalcode"
  },
  "geometry": {"coordinates":[0.067926,51.416971],"type":"Point"}
}
