{
  "type": "Feature",
  "properties": {
    "iso:country": "GB",
    "wof:name": "SL6 3EA",
    "wof:placetype": "postalcode"
  },
  "geometry": {"coordinates":[-0.740341,51.507322],"type":"Point"}
}
