{
  "type": "Feature",
  "properties": {
    "iso:country":"GB",
    "wof:name":"SL6 3EA",
    "wof:placetype":"postalcode"
},
  "geometry": {"coordinates":[-0.74034089976596,51.50732179069711],"type":"Point"}
}