{
  "type": "Feature",
  "properties": {
    "iso:country":"GB",
    "wof:name":"W11 1NY",
    "wof:placetype":"postalcode"
},
  "geometry": {"coordinates":[-0.20956815980092,51.51489866427654],"type":"Point"}
}