{
  "type": "Feature",
  "properties": {
    "iso:country":"GB",
    "wof:name":"KT4 8JU",
    "wof:placetype":"postalcode"
},
  "geometry": {"coordinates":[-0.23819931338848,51.3782147100984],"type":"Point"}
}