{
  "type": "Feature",
  "properties": {
    "iso:country":"GB",
    "wof:name":"RG7 3XF",
    "wof:placetype":"postalcode"
},
  "geometry": {"coordinates":[-1.0724381766695,51.38028793061229],"type":"Point"}
}