{
  "type": "Feature",
  "properties": {
    "iso:country":"GB",
    "wof:name":"LE9 7FL",
    "wof:placetype":"postalcode"
},
  "geometry": {"coordinates":[-1.31775092908052,52.57258103293731],"type":"Point"}
}