{
  "type": "Feature",
  "properties": {
    "iso:country": "GB",
    "wof:name": "LE9 7FL",
    "wof:placetype": "postalcode"
  },
  "geometry": {"coordinates":[-1.317751,52.572581],"type":"Point"}
}
