{
  "type": "Feature",
  "properties": {
    "iso:country":"GB",
    "wof:name":"PL14 4HS",
    "wof:placetype":"postalcode"
},
  "geometry": {"coordinates":[-4.47099457743173,50.45383056811428],"type":"Point"}
}