{
  "type": "Feature",
  "properties": {
    "iso:country": "GB",
    "wof:name": "PO7 5NY",
    "wof:placetype": "postalcode"
  },
  "geometry": {"coordinates":[-1.034081,50.866598],"type":"Point"}
}
