{
  "type": "Feature",
  "properties": {
    "iso:country":"GB",
    "wof:name":"TN12 9NH",
    "wof:placetype":"postalcode"
},
  "geometry": {"coordinates":[0.48120015853883,51.16516679886757],"type":"Point"}
}