{
  "type": "Feature",
  "properties": {
    "iso:country":"GB",
    "wof:name":"B45 9QR",
    "wof:placetype":"postalcode"
},
  "geometry": {"coordinates":[-2.01797012744377,52.38843337010782],"type":"Point"}
}