{
  "type": "Feature",
  "properties": {
    "date:inception_lower":"1980-01-01",
    "date:inception_upper":"1980-01-31",
    "iso:country":"GB",
    "wof:name":"B45 9QR",
    "wof:placetype":"postalcode"
},
  "geometry": {"coordinates":[-2.01797,52.388433],"type":"Point"}
}