{
  "type": "Feature",
  "properties": {
    "iso:country":"GB",
    "wof:name":"TD1 2JR",
    "wof:placetype":"postalcode"
},
  "geometry": {"coordinates":[-2.81770249899433,55.62393011790155],"type":"Point"}
}