{
  "type": "Feature",
  "properties": {
    "iso:country":"GB",
    "wof:name":"NN9 6AF",
    "wof:placetype":"postalcode"
},
  "geometry": {"coordinates":[-0.55266236785588,52.31492317905592],"type":"Point"}
}