{
  "type": "Feature",
  "properties": {
    "iso:country":"GB",
    "wof:name":"B68 0TF",
    "wof:placetype":"postalcode"
},
  "geometry": {"coordinates":[-2.00028005877414,52.47309391747853],"type":"Point"}
}