{
  "type": "Feature",
  "properties": {
    "iso:country": "GB",
    "wof:name": "B68 0TF",
    "wof:placetype": "postalcode"
  },
  "geometry": {"coordinates":[-2.00028,52.473094],"type":"Point"}
}
