{
  "type": "Feature",
  "properties": {
    "date:inception_lower": "1980-01-01",
    "date:inception_upper": "1980-01-01",
    "iso:country": "GB",
    "wof:name": "B68 0TF",
    "wof:placetype": "postalcode"
  },
  "geometry": {"coordinates":[-2.00028,52.473094],"type":"Point"}
}
