{
  "type": "Feature",
  "properties": {
    "iso:country":"GB",
    "wof:name":"LL57 1DD",
    "wof:placetype":"postalcode"
},
  "geometry": {"coordinates":[-4.11749042126558,53.23121322119375],"type":"Point"}
}