{
  "type": "Feature",
  "properties": {
    "date:inception_lower": "2022-05-01",
    "date:inception_upper": "2022-05-01",
    "iso:country": "GB",
    "wof:name": "S71 4GQ",
    "wof:placetype": "postalcode"
  },
  "geometry": {"coordinates":[-1.4379,53.599268],"type":"Point"}
}
