{
  "type": "Feature",
  "properties": {
    "iso:country":"GB",
    "wof:name":"NP23 4EX",
    "wof:placetype":"postalcode"
},
  "geometry": {"coordinates":[-3.17878297575864,51.79862368470814],"type":"Point"}
}