{
  "type": "Feature",
  "properties": {
    "iso:country": "GB",
    "wof:name": "SS4 3EX",
    "wof:placetype": "postalcode"
  },
  "geometry": {"coordinates":[0.689279,51.604652],"type":"Point"}
}
