{
  "type": "Feature",
  "properties": {
    "iso:country":"GB",
    "wof:name":"SS4 3EX",
    "wof:placetype":"postalcode"
},
  "geometry": {"coordinates":[0.68924932695784,51.60462783600033],"type":"Point"}
}