{
  "type": "Feature",
  "properties": {
    "date:inception_lower":"2006-04-01",
    "date:inception_upper":"2006-04-30",
    "iso:country":"GB",
    "wof:name":"N8 9HB",
    "wof:placetype":"postalcode"
},
  "geometry": {"coordinates":[-0.118823,51.580817],"type":"Point"}
}