{
  "type": "Feature",
  "properties": {
    "iso:country":"GB",
    "wof:name":"N8 9HB",
    "wof:placetype":"postalcode"
},
  "geometry": {"coordinates":[-0.11874231793235,51.5805879650803],"type":"Point"}
}