{
  "type": "Feature",
  "properties": {
    "iso:country":"GB",
    "wof:name":"TN17 1LU",
    "wof:placetype":"postalcode"
},
  "geometry": {"coordinates":[0.48086742658101,51.12830827638546],"type":"Point"}
}