{
  "type": "Feature",
  "properties": {
    "iso:country":"GB",
    "wof:name":"SO22 5HE",
    "wof:placetype":"postalcode"
},
  "geometry": {"coordinates":[-1.33662944483301,51.06697346866643],"type":"Point"}
}