{
  "type": "Feature",
  "properties": {
    "iso:country": "GB",
    "wof:name": "SO22 5HE",
    "wof:placetype": "postalcode"
  },
  "geometry": {"coordinates":[-1.336629,51.066973],"type":"Point"}
}
