{
  "type": "Feature",
  "properties": {
    "date:inception_lower": "2024-02-01",
    "date:inception_upper": "2024-02-01",
    "iso:country": "GB",
    "wof:name": "TA6 4YN",
    "wof:placetype": "postalcode"
  },
  "geometry": {"coordinates":[-2.985865,51.149155],"type":"Point"}
}
