{
  "type": "Feature",
  "properties": {
    "iso:country":"GB",
    "wof:name":"B30 1DG",
    "wof:placetype":"postalcode"
},
  "geometry": {"coordinates":[-1.93629383680427,52.41533404871588],"type":"Point"}
}