{
  "type": "Feature",
  "properties": {
    "date:inception_lower":"1980-01-01",
    "date:inception_upper":"1980-01-31",
    "iso:country":"GB",
    "wof:name":"BH3 7HR",
    "wof:placetype":"postalcode"
},
  "geometry": {"coordinates":[-1.88335,50.737247],"type":"Point"}
}