{
  "type": "Feature",
  "properties": {
    "iso:country":"GB",
    "wof:name":"BH3 7HR",
    "wof:placetype":"postalcode"
},
  "geometry": {"coordinates":[-1.88334986272854,50.73724680368745],"type":"Point"}
}