{
  "type": "Feature",
  "properties": {
    "iso:country": "GB",
    "wof:name": "BH3 7HR",
    "wof:placetype": "postalcode"
  },
  "geometry": {"coordinates":[-1.88335,50.737247],"type":"Point"}
}
