{
  "type": "Feature",
  "properties": {
    "iso:country":"GB",
    "wof:name":"GL8 8LU",
    "wof:placetype":"postalcode"
},
  "geometry": {"coordinates":[-2.16979429546414,51.68015483571715],"type":"Point"}
}