{
  "type": "Feature",
  "properties": {
    "iso:country":"GB",
    "wof:name":"OX16 1DW",
    "wof:placetype":"postalcode"
},
  "geometry": {"coordinates":[-1.3531503059621,52.06820542214707],"type":"Point"}
}