{
  "type": "Feature",
  "properties": {
    "iso:country":"GB",
    "wof:name":"RM13 9YZ",
    "wof:placetype":"postalcode"
},
  "geometry": {"coordinates":[0.19065153764968,51.52010241820555],"type":"Point"}
}