{
  "type": "Feature",
  "properties": {
    "date:inception_lower": "1990-07-01",
    "date:inception_upper": "1990-07-01",
    "iso:country": "GB",
    "wof:name": "RM13 9YZ",
    "wof:placetype": "postalcode"
  },
  "geometry": {"coordinates":[0.189577,51.520538],"type":"Point"}
}
