{
  "type": "Feature",
  "properties": {
    "iso:country":"GB",
    "wof:name":"WS7 2EA",
    "wof:placetype":"postalcode"
},
  "geometry": {"coordinates":[-1.91964853257552,52.68378794950865],"type":"Point"}
}