{
  "type": "Feature",
  "properties": {
    "date:inception_lower": "2021-01-01",
    "date:inception_upper": "2021-01-01",
    "iso:country": "GB",
    "wof:name": "ME15 8YU",
    "wof:placetype": "postalcode"
  },
  "geometry": {"coordinates":[0.567343,51.244683],"type":"Point"}
}
