{
  "type": "Feature",
  "properties": {
    "iso:country":"GB",
    "wof:name":"OX13 5BQ",
    "wof:placetype":"postalcode"
},
  "geometry": {"coordinates":[-1.42790986115286,51.68049562647534],"type":"Point"}
}