{
  "type": "Feature",
  "properties": {
    "iso:country":"GB",
    "wof:name":"M43 7JL",
    "wof:placetype":"postalcode"
},
  "geometry": {"coordinates":[-2.13325038270257,53.48391754868294],"type":"Point"}
}