{
  "type": "Feature",
  "properties": {
    "date:inception_lower": "2003-11-01",
    "date:inception_upper": "2003-11-01",
    "iso:country": "GB",
    "wof:name": "BR3 5RT",
    "wof:placetype": "postalcode"
  },
  "geometry": {"coordinates":[-0.015584,51.406148],"type":"Point"}
}
