{
  "type": "Feature",
  "properties": {
    "iso:country":"GB",
    "wof:name":"SS0 9AD",
    "wof:placetype":"postalcode"
},
  "geometry": {"coordinates":[0.70060020671715,51.54813903731281],"type":"Point"}
}