{
  "type": "Feature",
  "properties": {
    "iso:country":"GB",
    "wof:name":"CF35 6RW",
    "wof:placetype":"postalcode"
},
  "geometry": {"coordinates":[-3.49448763278126,51.52961039941905],"type":"Point"}
}