{
  "type": "Feature",
  "properties": {
    "iso:country": "GB",
    "wof:name": "CF35 6RW",
    "wof:placetype": "postalcode"
  },
  "geometry": {"coordinates":[-3.494488,51.52961],"type":"Point"}
}
