{
  "type": "Feature",
  "properties": {
    "iso:country":"GB",
    "wof:name":"EN6 1LX",
    "wof:placetype":"postalcode"
},
  "geometry": {"coordinates":[-0.18070884570102,51.70830213306994],"type":"Point"}
}