{
  "type": "Feature",
  "properties": {
    "iso:country":"GB",
    "wof:name":"SS9 5BP",
    "wof:placetype":"postalcode"
},
  "geometry": {"coordinates":[0.63788930436624,51.57495511232135],"type":"Point"}
}