{
  "type": "Feature",
  "properties": {
    "date:inception_lower": "1980-01-01",
    "date:inception_upper": "1980-01-01",
    "iso:country": "GB",
    "wof:name": "PL1 2NG",
    "wof:placetype": "postalcode"
  },
  "geometry": {"coordinates":[-4.137901,50.367096],"type":"Point"}
}
