{
  "type": "Feature",
  "properties": {
    "iso:country": "GB",
    "wof:name": "PL1 2NG",
    "wof:placetype": "postalcode"
  },
  "geometry": {"coordinates":[-4.137901,50.367096],"type":"Point"}
}
