{
  "type": "Feature",
  "properties": {
    "date:inception_lower": "1990-07-01",
    "date:inception_upper": "1990-07-01",
    "iso:country": "GB",
    "wof:name": "SA5 7HD",
    "wof:placetype": "postalcode"
  },
  "geometry": {"coordinates":[-3.952977,51.658173],"type":"Point"}
}
