{
  "type": "Feature",
  "properties": {
    "iso:country":"GB",
    "wof:name":"AB31 5TZ",
    "wof:placetype":"postalcode"
},
  "geometry": {"coordinates":[-2.48871670522397,57.05688236736646],"type":"Point"}
}