{
  "type": "Feature",
  "properties": {
    "date:inception_lower": "2023-09-01",
    "date:inception_upper": "2023-09-01",
    "iso:country": "GB",
    "wof:name": "CO16 8EF",
    "wof:placetype": "postalcode"
  },
  "geometry": {"coordinates":[1.121972,51.802687],"type":"Point"}
}
