{
  "type": "Feature",
  "properties": {
    "iso:country":"GB",
    "wof:name":"NN5 5BQ",
    "wof:placetype":"postalcode"
},
  "geometry": {"coordinates":[-0.91799816079247,52.24128949414402],"type":"Point"}
}