{
  "type": "Feature",
  "properties": {
    "iso:country":"GB",
    "wof:name":"PL12 4JS",
    "wof:placetype":"postalcode"
},
  "geometry": {"coordinates":[-4.23593726761706,50.41092564978581],"type":"Point"}
}