{
  "type": "Feature",
  "properties": {
    "iso:country":"GB",
    "wof:name":"CF45 4DZ",
    "wof:placetype":"postalcode"
},
  "geometry": {"coordinates":[-3.39333144208989,51.69716085215941],"type":"Point"}
}