{
  "type": "Feature",
  "properties": {
    "iso:country": "GB",
    "wof:name": "CF45 4DZ",
    "wof:placetype": "postalcode"
  },
  "geometry": {"coordinates":[-3.393331,51.697161],"type":"Point"}
}
