{
  "type": "Feature",
  "properties": {
    "date:inception_lower": "1994-12-01",
    "date:inception_upper": "1994-12-01",
    "iso:country": "GB",
    "wof:name": "CF45 4DZ",
    "wof:placetype": "postalcode"
  },
  "geometry": {"coordinates":[-3.393331,51.697161],"type":"Point"}
}
