{
  "type": "Feature",
  "properties": {
    "iso:country":"GB",
    "wof:name":"CV2 2HW",
    "wof:placetype":"postalcode"
},
  "geometry": {"coordinates":[-1.44698304996271,52.43240797723425],"type":"Point"}
}