{
  "type": "Feature",
  "properties": {
    "date:inception_lower":"1980-01-01",
    "date:inception_upper":"1980-01-31",
    "iso:country":"GB",
    "wof:name":"WF12 8QL",
    "wof:placetype":"postalcode"
},
  "geometry": {"coordinates":[-1.599992,53.689966],"type":"Point"}
}