{
  "type": "Feature",
  "properties": {
    "iso:country": "GB",
    "wof:name": "WF12 8QL",
    "wof:placetype": "postalcode"
  },
  "geometry": {"coordinates":[-1.599992,53.689966],"type":"Point"}
}
