{
  "type": "Feature",
  "properties": {
    "date:inception_lower":"1990-02-01",
    "date:inception_upper":"1990-02-28",
    "iso:country":"GB",
    "wof:name":"BN25 3HQ",
    "wof:placetype":"postalcode"
},
  "geometry": {"coordinates":[0.116653,50.782787],"type":"Point"}
}