{
  "type": "Feature",
  "properties": {
    "iso:country": "GB",
    "wof:name": "BN25 3HQ",
    "wof:placetype": "postalcode"
  },
  "geometry": {"coordinates":[0.116653,50.782787],"type":"Point"}
}
