{
  "type": "Feature",
  "properties": {
    "iso:country":"GB",
    "wof:name":"ME7 3PP",
    "wof:placetype":"postalcode"
},
  "geometry": {"coordinates":[0.55841684034298,51.36157250103847],"type":"Point"}
}