{
  "type": "Feature",
  "properties": {
    "iso:country": "GB",
    "wof:name": "ME7 3PP",
    "wof:placetype": "postalcode"
  },
  "geometry": {"coordinates":[0.558671,51.361748],"type":"Point"}
}
