{
  "type": "Feature",
  "properties": {
    "date:inception_lower": "1980-01-01",
    "date:inception_upper": "1980-01-01",
    "iso:country": "GB",
    "wof:name": "SK13 0EL",
    "wof:placetype": "postalcode"
  },
  "geometry": {"coordinates":[-1.987991,53.448002],"type":"Point"}
}
