{
  "type": "Feature",
  "properties": {
    "iso:country": "GB",
    "wof:name": "RH17 5AB",
    "wof:placetype": "postalcode"
  },
  "geometry": {"coordinates":[-0.151765,51.004485],"type":"Point"}
}
