{
  "type": "Feature",
  "properties": {
    "date:inception_lower": "2014-10-01",
    "date:inception_upper": "2014-10-01",
    "iso:country": "GB",
    "wof:name": "M14 4AY",
    "wof:placetype": "postalcode"
  },
  "geometry": {"coordinates":[-2.235049,53.457487],"type":"Point"}
}
