{
  "type": "Feature",
  "properties": {
    "iso:country": "GB",
    "wof:name": "KA6 7BS",
    "wof:placetype": "postalcode"
  },
  "geometry": {"coordinates":[-4.463078,55.439973],"type":"Point"}
}
