{
  "type": "Feature",
  "properties": {
    "date:inception_lower": "2005-10-01",
    "date:inception_upper": "2005-10-01",
    "iso:country": "GB",
    "wof:name": "KA6 7BS",
    "wof:placetype": "postalcode"
  },
  "geometry": {"coordinates":[-4.463078,55.439973],"type":"Point"}
}
