{
  "type": "Feature",
  "properties": {
    "date:inception_lower": "2020-07-01",
    "date:inception_upper": "2020-07-01",
    "iso:country": "GB",
    "wof:name": "BB9 9EL",
    "wof:placetype": "postalcode"
  },
  "geometry": {"coordinates":[-2.211617,53.834735],"type":"Point"}
}
