{
  "type": "Feature",
  "properties": {
    "iso:country":"GB",
    "wof:name":"TS8 9JE",
    "wof:placetype":"postalcode"
},
  "geometry": {"coordinates":[-1.24181904480476,54.52153291854502],"type":"Point"}
}