{
  "type": "Feature",
  "properties": {
    "iso:country":"GB",
    "wof:name":"WD4 8BD",
    "wof:placetype":"postalcode"
},
  "geometry": {"coordinates":[-0.46245811127031,51.72437620666112],"type":"Point"}
}