{
  "type": "Feature",
  "properties": {
    "iso:country":"GB",
    "wof:name":"PL30 4AZ",
    "wof:placetype":"postalcode"
},
  "geometry": {"coordinates":[-4.66729820517881,50.44942178844088],"type":"Point"}
}