{
  "type": "Feature",
  "properties": {
    "date:inception_lower": "1997-12-01",
    "date:inception_upper": "1997-12-01",
    "iso:country": "GB",
    "wof:name": "WR2 4ZF",
    "wof:placetype": "postalcode"
  },
  "geometry": {"coordinates":[-2.237843,52.18283],"type":"Point"}
}
