{
  "type": "Feature",
  "properties": {
    "iso:country":"GB",
    "wof:name":"WR2 4ZF",
    "wof:placetype":"postalcode"
},
  "geometry": {"coordinates":[-2.23784283667645,52.18283012507882],"type":"Point"}
}