{
  "type": "Feature",
  "properties": {
    "iso:country":"GB",
    "wof:name":"LE2 8HE",
    "wof:placetype":"postalcode"
},
  "geometry": {"coordinates":[-1.14557504840467,52.60495217942683],"type":"Point"}
}