{
  "type": "Feature",
  "properties": {
    "date:inception_lower": "1980-01-01",
    "date:inception_upper": "1980-01-01",
    "iso:country": "GB",
    "wof:name": "LE2 8HE",
    "wof:placetype": "postalcode"
  },
  "geometry": {"coordinates":[-1.145575,52.604952],"type":"Point"}
}
