{
  "type": "Feature",
  "properties": {
    "iso:country":"GB",
    "wof:name":"PL16 0AX",
    "wof:placetype":"postalcode"
},
  "geometry": {"coordinates":[-4.24024537733058,50.64919116532954],"type":"Point"}
}