{
  "type": "Feature",
  "properties": {
    "iso:country":"GB",
    "wof:name":"WA3 6XU",
    "wof:placetype":"postalcode"
},
  "geometry": {"coordinates":[-2.52939211759261,53.42782636998123],"type":"Point"}
}