{
  "type": "Feature",
  "properties": {
    "iso:country":"GB",
    "wof:name":"CO7 0GB",
    "wof:placetype":"postalcode"
},
  "geometry": {"coordinates":[1.02189126613798,51.80562431756771],"type":"Point"}
}