{
  "type": "Feature",
  "properties": {
    "date:inception_lower":"1994-05-01",
    "date:inception_upper":"1994-05-31",
    "iso:country":"GB",
    "wof:name":"M8 4QP",
    "wof:placetype":"postalcode"
},
  "geometry": {"coordinates":[-2.239801,53.520316],"type":"Point"}
}