{
  "type": "Feature",
  "properties": {
    "iso:country":"GB",
    "wof:name":"M8 4QP",
    "wof:placetype":"postalcode"
},
  "geometry": {"coordinates":[-2.23980095419465,53.52031594544955],"type":"Point"}
}