{
  "type": "Feature",
  "properties": {
    "iso:country":"GB",
    "wof:name":"CV6 4HP",
    "wof:placetype":"postalcode"
},
  "geometry": {"coordinates":[-1.51313757103145,52.44744244867545],"type":"Point"}
}