{
  "type": "Feature",
  "properties": {
    "date:inception_lower": "1980-01-01",
    "date:inception_upper": "1980-01-01",
    "iso:country": "GB",
    "wof:name": "CV6 4HP",
    "wof:placetype": "postalcode"
  },
  "geometry": {"coordinates":[-1.513138,52.447442],"type":"Point"}
}
