{
  "type": "Feature",
  "properties": {
    "iso:country":"GB",
    "wof:name":"EN2 8BT",
    "wof:placetype":"postalcode"
},
  "geometry": {"coordinates":[-0.09558741919202,51.66141595613135],"type":"Point"}
}