{
  "type": "Feature",
  "properties": {
    "iso:country":"GB",
    "wof:name":"LE2 5UN",
    "wof:placetype":"postalcode"
},
  "geometry": {"coordinates":[-1.06453780409542,52.58688131181751],"type":"Point"}
}