{
  "type": "Feature",
  "properties": {
    "date:inception_lower": "1995-07-01",
    "date:inception_upper": "1995-07-01",
    "iso:country": "GB",
    "wof:name": "SN8 3TU",
    "wof:placetype": "postalcode"
  },
  "geometry": {"coordinates":[-1.634959,51.344356],"type":"Point"}
}
