{
  "type": "Feature",
  "properties": {
    "iso:country":"GB",
    "wof:name":"UB6 9SZ",
    "wof:placetype":"postalcode"
},
  "geometry": {"coordinates":[-0.36041446973585,51.53717487142147],"type":"Point"}
}