{
  "type": "Feature",
  "properties": {
    "iso:country": "GB",
    "wof:name": "UB6 9SZ",
    "wof:placetype": "postalcode"
  },
  "geometry": {"coordinates":[-0.360414,51.537175],"type":"Point"}
}
