{
  "type": "Feature",
  "properties": {
    "iso:country":"GB",
    "wof:name":"M25 1BZ",
    "wof:placetype":"postalcode"
},
  "geometry": {"coordinates":[-2.28005148851553,53.53336939274082],"type":"Point"}
}