{
  "type": "Feature",
  "properties": {
    "date:inception_lower":"1995-07-01",
    "date:inception_upper":"1995-07-31",
    "iso:country":"GB",
    "wof:name":"M25 1BZ",
    "wof:placetype":"postalcode"
},
  "geometry": {"coordinates":[-2.280051,53.533369],"type":"Point"}
}