{
  "type": "Feature",
  "properties": {
    "date:inception_lower": "1980-01-01",
    "date:inception_upper": "1980-01-01",
    "iso:country": "GB",
    "wof:name": "WA11 9RG",
    "wof:placetype": "postalcode"
  },
  "geometry": {"coordinates":[-2.703853,53.46173],"type":"Point"}
}
