{
  "type": "Feature",
  "properties": {
    "iso:country":"GB",
    "wof:name":"SS0 9TZ",
    "wof:placetype":"postalcode"
},
  "geometry": {"coordinates":[0.68019470930917,51.5509365160398],"type":"Point"}
}