{
  "type": "Feature",
  "properties": {
    "date:inception_lower":"1980-01-01",
    "date:inception_upper":"1980-01-31",
    "iso:country":"GB",
    "wof:name":"GU35 8PJ",
    "wof:placetype":"postalcode"
},
  "geometry": {"coordinates":[-0.828922,51.12315],"type":"Point"}
}