{
  "type": "Feature",
  "properties": {
    "iso:country": "GB",
    "wof:name": "GU35 8PJ",
    "wof:placetype": "postalcode"
  },
  "geometry": {"coordinates":[-0.828922,51.12315],"type":"Point"}
}
