{
  "type": "Feature",
  "properties": {
    "iso:country":"GB",
    "wof:name":"SR4 7QS",
    "wof:placetype":"postalcode"
},
  "geometry": {"coordinates":[-1.41447847616643,54.89673555942819],"type":"Point"}
}