{
  "type": "Feature",
  "properties": {
    "iso:country": "GB",
    "wof:name": "PE30 3ER",
    "wof:placetype": "postalcode"
  },
  "geometry": {"coordinates":[0.435639,52.769918],"type":"Point"}
}
