{
  "type": "Feature",
  "properties": {
    "iso:country":"GB",
    "wof:name":"PE30 3ER",
    "wof:placetype":"postalcode"
},
  "geometry": {"coordinates":[0.43563869215644,52.76991807282613],"type":"Point"}
}