{
  "type": "Feature",
  "properties": {
    "iso:country": "GB",
    "wof:name": "N6 6BS",
    "wof:placetype": "postalcode"
  },
  "geometry": {"coordinates":[-0.148242,51.570347],"type":"Point"}
}
