{
  "type": "Feature",
  "properties": {
    "date:inception_lower":"1980-01-01",
    "date:inception_upper":"1980-01-31",
    "iso:country":"GB",
    "wof:name":"EX6 7SJ",
    "wof:placetype":"postalcode"
},
  "geometry": {"coordinates":[-3.608482,50.708642],"type":"Point"}
}