{
  "type": "Feature",
  "properties": {
    "iso:country":"GB",
    "wof:name":"EX6 7SJ",
    "wof:placetype":"postalcode"
},
  "geometry": {"coordinates":[-3.60848201152398,50.70864225930794],"type":"Point"}
}