{
  "type": "Feature",
  "properties": {
    "date:inception_lower": "2003-01-01",
    "date:inception_upper": "2003-01-01",
    "iso:country": "GB",
    "wof:name": "SO32 2YL",
    "wof:placetype": "postalcode"
  },
  "geometry": {"coordinates":[-1.180261,50.943739],"type":"Point"}
}
