{
  "type": "Feature",
  "properties": {
    "iso:country": "GB",
    "wof:name": "BL2 1NP",
    "wof:placetype": "postalcode"
  },
  "geometry": {"coordinates":[-2.422186,53.572975],"type":"Point"}
}
