{
  "type": "Feature",
  "properties": {
    "iso:country": "GB",
    "wof:name": "KT24 5RQ",
    "wof:placetype": "postalcode"
  },
  "geometry": {"coordinates":[-0.423848,51.25768],"type":"Point"}
}
