{
  "type": "Feature",
  "properties": {
    "iso:country": "GB",
    "wof:name": "FK8 3PF",
    "wof:placetype": "postalcode"
  },
  "geometry": {"coordinates":[-4.145192,56.173546],"type":"Point"}
}
