{
  "type": "Feature",
  "properties": {
    "iso:country":"GB",
    "wof:name":"TA7 8QW",
    "wof:placetype":"postalcode"
},
  "geometry": {"coordinates":[-2.96916970037721,51.14150306717222],"type":"Point"}
}