{
  "type": "Feature",
  "properties": {
    "date:inception_lower":"1980-01-01",
    "date:inception_upper":"1980-01-31",
    "iso:country":"GB",
    "wof:name":"HR3 6BE",
    "wof:placetype":"postalcode"
},
  "geometry": {"coordinates":[-3.000218,52.067819],"type":"Point"}
}