{
  "type": "Feature",
  "properties": {
    "date:inception_lower": "1980-01-01",
    "date:inception_upper": "1980-01-01",
    "iso:country": "GB",
    "wof:name": "HR3 6BE",
    "wof:placetype": "postalcode"
  },
  "geometry": {"coordinates":[-2.99974,52.06775],"type":"Point"}
}
