{
  "type": "Feature",
  "properties": {
    "iso:country":"GB",
    "wof:name":"HR3 6BE",
    "wof:placetype":"postalcode"
},
  "geometry": {"coordinates":[-3.00021786119598,52.06781851700264],"type":"Point"}
}