{
  "type": "Feature",
  "properties": {
    "date:inception_lower": "2023-11-01",
    "date:inception_upper": "2023-11-01",
    "iso:country": "GB",
    "wof:name": "CW1 5BP",
    "wof:placetype": "postalcode"
  },
  "geometry": {"coordinates":[-2.41933,53.110453],"type":"Point"}
}
