{
  "type": "Feature",
  "properties": {
    "date:inception_lower": "2023-05-01",
    "date:inception_upper": "2023-05-01",
    "iso:country": "GB",
    "wof:name": "CW1 5BP",
    "wof:placetype": "postalcode"
  },
  "geometry": {"coordinates":[-2.419226,53.110472],"type":"Point"}
}
