{
  "type": "Feature",
  "properties": {
    "iso:country": "GB",
    "wof:name": "TN23 8AQ",
    "wof:placetype": "postalcode"
  },
  "geometry": {"coordinates":[0.823999,51.136989],"type":"Point"}
}
