{
  "type": "Feature",
  "properties": {
    "iso:country":"GB",
    "wof:name":"S21 3WN",
    "wof:placetype":"postalcode"
},
  "geometry": {"coordinates":[-1.32715255399466,53.29792015696975],"type":"Point"}
}