{
  "type": "Feature",
  "properties": {
    "iso:country":"GB",
    "wof:name":"WS9 8NY",
    "wof:placetype":"postalcode"
},
  "geometry": {"coordinates":[-1.9152855838279,52.606617269423],"type":"Point"}
}