{
  "type": "Feature",
  "properties": {
    "iso:country": "GB",
    "wof:name": "PE21 7FD",
    "wof:placetype": "postalcode"
  },
  "geometry": {"coordinates":[-0.05145,52.979357],"type":"Point"}
}
