{
  "type": "Feature",
  "properties": {
    "iso:country":"GB",
    "wof:name":"FK9 5EY",
    "wof:placetype":"postalcode"
},
  "geometry": {"coordinates":[-3.92765279664169,56.13549540527625],"type":"Point"}
}