{
  "type": "Feature",
  "properties": {
    "date:inception_lower": "1994-05-01",
    "date:inception_upper": "1994-05-01",
    "iso:country": "GB",
    "wof:name": "M9 0NP",
    "wof:placetype": "postalcode"
  },
  "geometry": {"coordinates":[-2.229669,53.534852],"type":"Point"}
}
