{
  "type": "Feature",
  "properties": {
    "iso:country":"GB",
    "wof:name":"CV9 2BH",
    "wof:placetype":"postalcode"
},
  "geometry": {"coordinates":[-1.60514153348436,52.58711150339215],"type":"Point"}
}