{
  "type": "Feature",
  "properties": {
    "iso:country":"GB",
    "wof:name":"BA21 3LQ",
    "wof:placetype":"postalcode"
},
  "geometry": {"coordinates":[-2.65674635463073,50.95391117062612],"type":"Point"}
}