{
  "type": "Feature",
  "properties": {
    "iso:country":"GB",
    "wof:name":"NE49 9EG",
    "wof:placetype":"postalcode"
},
  "geometry": {"coordinates":[-2.45834821564036,54.97335798250806],"type":"Point"}
}