{
  "type": "Feature",
  "properties": {
    "iso:country":"GB",
    "wof:name":"RM14 3AB",
    "wof:placetype":"postalcode"
},
  "geometry": {"coordinates":[0.24922848230815,51.55128734764072],"type":"Point"}
}