{
  "type": "Feature",
  "properties": {
    "iso:country": "GB",
    "wof:name": "RM14 3AB",
    "wof:placetype": "postalcode"
  },
  "geometry": {"coordinates":[0.249227,51.55128],"type":"Point"}
}
