{
  "type": "Feature",
  "properties": {
    "date:inception_lower": "1980-01-01",
    "date:inception_upper": "1980-01-01",
    "iso:country": "GB",
    "wof:name": "L30 2RQ",
    "wof:placetype": "postalcode"
  },
  "geometry": {"coordinates":[-2.983535,53.488878],"type":"Point"}
}
