{
  "type": "Feature",
  "properties": {
    "iso:country": "GB",
    "wof:name": "TA4 4EX",
    "wof:placetype": "postalcode"
  },
  "geometry": {"coordinates":[-3.272756,51.135595],"type":"Point"}
}
