{
  "type": "Feature",
  "properties": {
    "date:inception_lower": "1980-01-01",
    "date:inception_upper": "1980-01-01",
    "iso:country": "GB",
    "wof:name": "MK42 7DA",
    "wof:placetype": "postalcode"
  },
  "geometry": {"coordinates":[-0.512096,52.113309],"type":"Point"}
}
