{
  "type": "Feature",
  "properties": {
    "date:inception_lower": "2021-02-01",
    "date:inception_upper": "2021-02-01",
    "iso:country": "GB",
    "wof:name": "NG24 4FR",
    "wof:placetype": "postalcode"
  },
  "geometry": {"coordinates":[-0.806958,53.056354],"type":"Point"}
}
