{
  "type": "Feature",
  "properties": {
    "iso:country":"GB",
    "wof:name":"NG5 7FE",
    "wof:placetype":"postalcode"
},
  "geometry": {"coordinates":[-1.11873969363134,53.00443078817774],"type":"Point"}
}