{
  "type": "Feature",
  "properties": {
    "iso:country":"GB",
    "wof:name":"SW16 1JJ",
    "wof:placetype":"postalcode"
},
  "geometry": {"coordinates":[-0.13001098127452,51.43497224467097],"type":"Point"}
}