{
  "type": "Feature",
  "properties": {
    "iso:country": "GB",
    "wof:name": "SW16 1JJ",
    "wof:placetype": "postalcode"
  },
  "geometry": {"coordinates":[-0.130011,51.434972],"type":"Point"}
}
