{
  "type": "Feature",
  "properties": {
    "iso:country":"GB",
    "wof:name":"EX13 5HA",
    "wof:placetype":"postalcode"
},
  "geometry": {"coordinates":[-2.98350146642723,50.78929755679571],"type":"Point"}
}