{
  "type": "Feature",
  "properties": {
    "date:inception_lower": "1980-01-01",
    "date:inception_upper": "1980-01-01",
    "iso:country": "GB",
    "wof:name": "GL5 1SY",
    "wof:placetype": "postalcode"
  },
  "geometry": {"coordinates":[-2.209374,51.751738],"type":"Point"}
}
