{
  "type": "Feature",
  "properties": {
    "iso:country":"GB",
    "wof:name":"GU46 7PN",
    "wof:placetype":"postalcode"
},
  "geometry": {"coordinates":[-0.84249467571953,51.34704903007285],"type":"Point"}
}