{
  "type": "Feature",
  "properties": {
    "date:inception_lower":"1996-06-01",
    "date:inception_upper":"1996-06-30",
    "iso:country":"GB",
    "wof:name":"GU46 7PN",
    "wof:placetype":"postalcode"
},
  "geometry": {"coordinates":[-0.842495,51.347049],"type":"Point"}
}