{
  "type": "Feature",
  "properties": {
    "iso:country": "GB",
    "wof:name": "GU46 7PN",
    "wof:placetype": "postalcode"
  },
  "geometry": {"coordinates":[-0.842495,51.347049],"type":"Point"}
}
