{
  "type": "Feature",
  "properties": {
    "iso:country": "GB",
    "wof:name": "CV35 8RB",
    "wof:placetype": "postalcode"
  },
  "geometry": {"coordinates":[-1.657311,52.273472],"type":"Point"}
}
