{
  "type": "Feature",
  "properties": {
    "iso:country":"GB",
    "wof:name":"CV35 8RB",
    "wof:placetype":"postalcode"
},
  "geometry": {"coordinates":[-1.66880815820427,52.27400251239978],"type":"Point"}
}