{
  "type": "Feature",
  "properties": {
    "iso:country":"GB",
    "wof:name":"BR6 0XA",
    "wof:placetype":"postalcode"
},
  "geometry": {"coordinates":[0.09523646720816,51.38045083970422],"type":"Point"}
}