{
  "type": "Feature",
  "properties": {
    "iso:country":"GB",
    "wof:name":"DH4 6LY",
    "wof:placetype":"postalcode"
},
  "geometry": {"coordinates":[-1.50018790188546,54.83768165621784],"type":"Point"}
}