{
  "type": "Feature",
  "properties": {
    "iso:country": "GB",
    "wof:name": "B67 5LT",
    "wof:placetype": "postalcode"
  },
  "geometry": {"coordinates":[-1.98036,52.476356],"type":"Point"}
}
