{
  "type": "Feature",
  "properties": {
    "date:inception_lower":"1980-01-01",
    "date:inception_upper":"1980-01-31",
    "iso:country":"GB",
    "wof:name":"SO21 3PG",
    "wof:placetype":"postalcode"
},
  "geometry": {"coordinates":[-1.304767,51.150362],"type":"Point"}
}