{
  "type": "Feature",
  "properties": {
    "iso:country": "GB",
    "wof:name": "SO21 3PG",
    "wof:placetype": "postalcode"
  },
  "geometry": {"coordinates":[-1.304767,51.150362],"type":"Point"}
}
