{
  "type": "Feature",
  "properties": {
    "iso:country":"GB",
    "wof:name":"LE11 1NP",
    "wof:placetype":"postalcode"
},
  "geometry": {"coordinates":[-1.20810310723961,52.77714687498496],"type":"Point"}
}