{
  "type": "Feature",
  "properties": {
    "iso:country":"GB",
    "wof:name":"YO18 7RW",
    "wof:placetype":"postalcode"
},
  "geometry": {"coordinates":[-0.72110942487431,54.23642350288771],"type":"Point"}
}