{
  "type": "Feature",
  "properties": {
    "iso:country":"GB",
    "wof:name":"IV19 1HT",
    "wof:placetype":"postalcode"
},
  "geometry": {"coordinates":[-4.05853331901336,57.81476234413886],"type":"Point"}
}