{
  "type": "Feature",
  "properties": {
    "iso:country":"GB",
    "wof:name":"ME3 8TP",
    "wof:placetype":"postalcode"
},
  "geometry": {"coordinates":[0.49916533061031,51.43448528816759],"type":"Point"}
}