{
  "type": "Feature",
  "properties": {
    "date:inception_lower": "1980-01-01",
    "date:inception_upper": "1980-01-01",
    "iso:country": "GB",
    "wof:name": "SL6 5BB",
    "wof:placetype": "postalcode"
  },
  "geometry": {"coordinates":[-0.747194,51.522241],"type":"Point"}
}
