{
  "type": "Feature",
  "properties": {
    "iso:country":"GB",
    "wof:name":"SW4 0BD",
    "wof:placetype":"postalcode"
},
  "geometry": {"coordinates":[-0.13781831695739,51.46268583300027],"type":"Point"}
}