{
  "type": "Feature",
  "properties": {
    "iso:country":"GB",
    "wof:name":"UB3 5AW",
    "wof:placetype":"postalcode"
},
  "geometry": {"coordinates":[-0.44143229049145,51.48152935530884],"type":"Point"}
}