{
  "type": "Feature",
  "properties": {
    "date:inception_lower": "1980-01-01",
    "date:inception_upper": "1980-01-01",
    "iso:country": "GB",
    "wof:name": "IP2 0PN",
    "wof:placetype": "postalcode"
  },
  "geometry": {"coordinates":[1.129847,52.049468],"type":"Point"}
}
