{
  "type": "Feature",
  "properties": {
    "date:inception_lower": "1983-01-01",
    "date:inception_upper": "1983-01-01",
    "iso:country": "GB",
    "wof:name": "BB4 4RX",
    "wof:placetype": "postalcode"
  },
  "geometry": {"coordinates":[-2.324008,53.694193],"type":"Point"}
}
