{
  "type": "Feature",
  "properties": {
    "date:inception_lower":"1980-01-01",
    "date:inception_upper":"1980-01-31",
    "iso:country":"GB",
    "wof:name":"HU11 4HF",
    "wof:placetype":"postalcode"
},
  "geometry": {"coordinates":[-0.23507,53.780712],"type":"Point"}
}