{
  "type": "Feature",
  "properties": {
    "iso:country": "GB",
    "wof:name": "HU11 4HF",
    "wof:placetype": "postalcode"
  },
  "geometry": {"coordinates":[-0.23507,53.780712],"type":"Point"}
}
