{
  "type": "Feature",
  "properties": {
    "iso:country":"GB",
    "wof:name":"HU11 4HF",
    "wof:placetype":"postalcode"
},
  "geometry": {"coordinates":[-0.23506984155749,53.7807124705965],"type":"Point"}
}