{
  "type": "Feature",
  "properties": {
    "iso:country":"GB",
    "wof:name":"EC1R 1XJ",
    "wof:placetype":"postalcode"
},
  "geometry": {"coordinates":[-0.10838687425683,51.529290223232],"type":"Point"}
}