{
  "type": "Feature",
  "properties": {
    "iso:country":"GB",
    "wof:name":"OL2 5AT",
    "wof:placetype":"postalcode"
},
  "geometry": {"coordinates":[-2.12068901884609,53.55505598520416],"type":"Point"}
}