{
  "type": "Feature",
  "properties": {
    "iso:country": "GB",
    "wof:name": "OL2 5AT",
    "wof:placetype": "postalcode"
  },
  "geometry": {"coordinates":[-2.120689,53.555056],"type":"Point"}
}
