{
  "type": "Feature",
  "properties": {
    "iso:country": "GB",
    "wof:name": "PL14 3QY",
    "wof:placetype": "postalcode"
  },
  "geometry": {"coordinates":[-4.409099,50.439596],"type":"Point"}
}
