{
  "type": "Feature",
  "properties": {
    "iso:country": "GB",
    "wof:name": "PO13 8EY",
    "wof:placetype": "postalcode"
  },
  "geometry": {"coordinates":[-1.169916,50.80107],"type":"Point"}
}
