{
  "type": "Feature",
  "properties": {
    "date:inception_lower": "1996-12-01",
    "date:inception_upper": "1996-12-01",
    "iso:country": "GB",
    "wof:name": "MK7 8HX",
    "wof:placetype": "postalcode"
  },
  "geometry": {"coordinates":[-0.689877,52.011109],"type":"Point"}
}
