{
  "type": "Feature",
  "properties": {
    "iso:country":"GB",
    "wof:name":"MK7 8HX",
    "wof:placetype":"postalcode"
},
  "geometry": {"coordinates":[-0.69147788645762,52.01166583611891],"type":"Point"}
}