{
  "type": "Feature",
  "properties": {
    "date:inception_lower": "1980-01-01",
    "date:inception_upper": "1980-01-01",
    "iso:country": "GB",
    "wof:name": "SE25 6UW",
    "wof:placetype": "postalcode"
  },
  "geometry": {"coordinates":[-0.083288,51.402123],"type":"Point"}
}
