{
  "type": "Feature",
  "properties": {
    "iso:country":"GB",
    "wof:name":"HD6 1PY",
    "wof:placetype":"postalcode"
},
  "geometry": {"coordinates":[-1.77225478916636,53.69910805352415],"type":"Point"}
}