{
  "type": "Feature",
  "properties": {
    "iso:country":"GB",
    "wof:name":"AB39 2PF",
    "wof:placetype":"postalcode"
},
  "geometry": {"coordinates":[-2.20741018633522,56.96509222351224],"type":"Point"}
}