{
  "type": "Feature",
  "properties": {
    "date:inception_lower": "1996-06-01",
    "date:inception_upper": "1996-06-01",
    "iso:country": "GB",
    "wof:name": "AB39 2PF",
    "wof:placetype": "postalcode"
  },
  "geometry": {"coordinates":[-2.207417,56.965078],"type":"Point"}
}
