{
  "type": "Feature",
  "properties": {
    "iso:country":"GB",
    "wof:name":"GL2 8HR",
    "wof:placetype":"postalcode"
},
  "geometry": {"coordinates":[-2.2893941914951,51.90018340444912],"type":"Point"}
}