{
  "type": "Feature",
  "properties": {
    "date:inception_lower":"2000-12-01",
    "date:inception_upper":"2000-12-31",
    "iso:country":"GB",
    "wof:name":"S10 3FH",
    "wof:placetype":"postalcode"
},
  "geometry": {"coordinates":[-1.520578,53.373613],"type":"Point"}
}