{
  "type": "Feature",
  "properties": {
    "iso:country":"GB",
    "wof:name":"YO42 1TW",
    "wof:placetype":"postalcode"
},
  "geometry": {"coordinates":[-0.77539165743544,53.94106114421133],"type":"Point"}
}