{
  "type": "Feature",
  "properties": {
    "iso:country":"GB",
    "wof:name":"AB43 8UL",
    "wof:placetype":"postalcode"
},
  "geometry": {"coordinates":[-1.99978514779173,57.63747349306971],"type":"Point"}
}