{
  "type": "Feature",
  "properties": {
    "date:inception_lower": "2021-04-01",
    "date:inception_upper": "2021-04-01",
    "iso:country": "GB",
    "wof:name": "DT9 6FD",
    "wof:placetype": "postalcode"
  },
  "geometry": {"coordinates":[-2.533031,50.947881],"type":"Point"}
}
