{
  "type": "Feature",
  "properties": {
    "date:inception_lower":"1980-01-01",
    "date:inception_upper":"1980-01-31",
    "iso:country":"GB",
    "wof:name":"M1 6DF",
    "wof:placetype":"postalcode"
},
  "geometry": {"coordinates":[-2.240176,53.477252],"type":"Point"}
}