{
  "type": "Feature",
  "properties": {
    "iso:country":"GB",
    "wof:name":"OX2 6NA",
    "wof:placetype":"postalcode"
},
  "geometry": {"coordinates":[-1.26228738882887,51.76414475993689],"type":"Point"}
}