{
  "type": "Feature",
  "properties": {
    "date:inception_lower": "1980-01-01",
    "date:inception_upper": "1980-01-01",
    "iso:country": "GB",
    "wof:name": "OX2 6NA",
    "wof:placetype": "postalcode"
  },
  "geometry": {"coordinates":[-1.262269,51.76415],"type":"Point"}
}
