{
  "type": "Feature",
  "properties": {
    "iso:country":"GB",
    "wof:name":"PL2 2RS",
    "wof:placetype":"postalcode"
},
  "geometry": {"coordinates":[-4.16375539495129,50.39508503385424],"type":"Point"}
}