{
  "type": "Feature",
  "properties": {
    "iso:country":"GB",
    "wof:name":"N12 8QA",
    "wof:placetype":"postalcode"
},
  "geometry": {"coordinates":[-0.17777121832096,51.61890955143758],"type":"Point"}
}