{
  "type": "Feature",
  "properties": {
    "iso:country": "GB",
    "wof:name": "N12 8QA",
    "wof:placetype": "postalcode"
  },
  "geometry": {"coordinates":[-0.177746,51.618912],"type":"Point"}
}
