{
  "type": "Feature",
  "properties": {
    "iso:country":"GB",
    "wof:name":"BS40 6PN",
    "wof:placetype":"postalcode"
},
  "geometry": {"coordinates":[-2.68044211206006,51.32170760017223],"type":"Point"}
}