{
  "type": "Feature",
  "properties": {
    "date:inception_lower": "1997-12-01",
    "date:inception_upper": "1997-12-01",
    "iso:country": "GB",
    "wof:name": "BS40 6PN",
    "wof:placetype": "postalcode"
  },
  "geometry": {"coordinates":[-2.680442,51.321708],"type":"Point"}
}
