{
  "type": "Feature",
  "properties": {
    "iso:country": "GB",
    "wof:name": "BS48 3QR",
    "wof:placetype": "postalcode"
  },
  "geometry": {"coordinates":[-2.689163,51.42473],"type":"Point"}
}
