{
  "type": "Feature",
  "properties": {
    "iso:country":"GB",
    "wof:name":"BS48 3QR",
    "wof:placetype":"postalcode"
},
  "geometry": {"coordinates":[-2.6891629903671,51.42472962498776],"type":"Point"}
}