{
  "type": "Feature",
  "properties": {
    "iso:country":"GB",
    "wof:name":"KT23 4LB",
    "wof:placetype":"postalcode"
},
  "geometry": {"coordinates":[-0.37690231589314,51.27505070751679],"type":"Point"}
}