{
  "type": "Feature",
  "properties": {
    "iso:country": "GB",
    "wof:name": "DT3 6RB",
    "wof:placetype": "postalcode"
  },
  "geometry": {"coordinates":[-2.452921,50.644707],"type":"Point"}
}
