{
  "type": "Feature",
  "properties": {
    "iso:country":"GB",
    "wof:name":"DT3 6RB",
    "wof:placetype":"postalcode"
},
  "geometry": {"coordinates":[-2.45292140477369,50.64470699885834],"type":"Point"}
}