{
  "type": "Feature",
  "properties": {
    "iso:country": "GB",
    "wof:name": "BA3 2TR",
    "wof:placetype": "postalcode"
  },
  "geometry": {"coordinates":[-2.477893,51.293324],"type":"Point"}
}
