{
  "type": "Feature",
  "properties": {
    "date:inception_lower": "1980-01-01",
    "date:inception_upper": "1980-01-01",
    "iso:country": "GB",
    "wof:name": "BA3 2TR",
    "wof:placetype": "postalcode"
  },
  "geometry": {"coordinates":[-2.477893,51.293302],"type":"Point"}
}
