{
  "type": "Feature",
  "properties": {
    "iso:country":"GB",
    "wof:name":"BA3 2TR",
    "wof:placetype":"postalcode"
},
  "geometry": {"coordinates":[-2.47789259808054,51.29332431586334],"type":"Point"}
}