{
  "type": "Feature",
  "properties": {
    "iso:country":"GB",
    "wof:name":"SW6 3SS",
    "wof:placetype":"postalcode"
},
  "geometry": {"coordinates":[-0.19515115939039,51.47306954146966],"type":"Point"}
}