{
  "type": "Feature",
  "properties": {
    "iso:country":"GB",
    "wof:name":"SE5 0LF",
    "wof:placetype":"postalcode"
},
  "geometry": {"coordinates":[-0.09831261897923,51.47729416367513],"type":"Point"}
}