{
  "type": "Feature",
  "properties": {
    "iso:country": "GB",
    "wof:name": "TS15 0AY",
    "wof:placetype": "postalcode"
  },
  "geometry": {"coordinates":[-1.31988,54.468643],"type":"Point"}
}
