{
  "type": "Feature",
  "properties": {
    "iso:country":"GB",
    "wof:name":"TS15 0AY",
    "wof:placetype":"postalcode"
},
  "geometry": {"coordinates":[-1.31986692407488,54.46863135817279],"type":"Point"}
}