{
  "type": "Feature",
  "properties": {
    "date:inception_lower": "2011-05-01",
    "date:inception_upper": "2011-05-01",
    "iso:country": "GB",
    "wof:name": "LE67 1GJ",
    "wof:placetype": "postalcode"
  },
  "geometry": {"coordinates":[-1.359832,52.696193],"type":"Point"}
}
