{
  "type": "Feature",
  "properties": {
    "iso:country": "GB",
    "wof:name": "BS27 3NR",
    "wof:placetype": "postalcode"
  },
  "geometry": {"coordinates":[-2.773145,51.273825],"type":"Point"}
}
