{
  "type": "Feature",
  "properties": {
    "iso:country":"GB",
    "wof:name":"CA1 3HU",
    "wof:placetype":"postalcode"
},
  "geometry": {"coordinates":[-2.8963890074497,54.876207274786],"type":"Point"}
}