{
  "type": "Feature",
  "properties": {
    "iso:country":"GB",
    "wof:name":"HG2 8HP",
    "wof:placetype":"postalcode"
},
  "geometry": {"coordinates":[-1.52566017010123,53.96940998888138],"type":"Point"}
}