{
  "type": "Feature",
  "properties": {
    "iso:country":"GB",
    "wof:name":"NG31 9LD",
    "wof:placetype":"postalcode"
},
  "geometry": {"coordinates":[-0.6265595821401,52.9161950908835],"type":"Point"}
}