{
  "type": "Feature",
  "properties": {
    "iso:country":"GB",
    "wof:name":"GU2 8DW",
    "wof:placetype":"postalcode"
},
  "geometry": {"coordinates":[-0.60446853047833,51.24338146074556],"type":"Point"}
}