{
  "type": "Feature",
  "properties": {
    "iso:country":"GB",
    "wof:name":"CV35 8AY",
    "wof:placetype":"postalcode"
},
  "geometry": {"coordinates":[-1.62817299958784,52.21198296287734],"type":"Point"}
}