{
  "type": "Feature",
  "properties": {
    "iso:country": "GB",
    "wof:name": "CV35 8AY",
    "wof:placetype": "postalcode"
  },
  "geometry": {"coordinates":[-1.628173,52.211983],"type":"Point"}
}
