{
  "type": "Feature",
  "properties": {
    "iso:country":"GB",
    "wof:name":"SK12 2DJ",
    "wof:placetype":"postalcode"
},
  "geometry": {"coordinates":[-2.02895522615379,53.35265714484589],"type":"Point"}
}