{
  "type": "Feature",
  "properties": {
    "iso:country":"GB",
    "wof:name":"SK5 7BA",
    "wof:placetype":"postalcode"
},
  "geometry": {"coordinates":[-2.16328943337625,53.43444359009876],"type":"Point"}
}