{
  "type": "Feature",
  "properties": {
    "iso:country":"GB",
    "wof:name":"LE17 4DY",
    "wof:placetype":"postalcode"
},
  "geometry": {"coordinates":[-1.19730417285504,52.45843354806293],"type":"Point"}
}