{
  "type": "Feature",
  "properties": {
    "date:inception_lower": "2008-03-01",
    "date:inception_upper": "2008-03-01",
    "iso:country": "GB",
    "wof:name": "DN17 1BU",
    "wof:placetype": "postalcode"
  },
  "geometry": {"coordinates":[-0.667373,53.583733],"type":"Point"}
}
