{
  "type": "Feature",
  "properties": {
    "iso:country":"GB",
    "wof:name":"LL11 5BB",
    "wof:placetype":"postalcode"
},
  "geometry": {"coordinates":[-3.05705239928761,53.07554823744602],"type":"Point"}
}