{
  "type": "Feature",
  "properties": {
    "iso:country": "GB",
    "wof:name": "WA6 0PW",
    "wof:placetype": "postalcode"
  },
  "geometry": {"coordinates":[-2.765345,53.276206],"type":"Point"}
}
