{
  "type": "Feature",
  "properties": {
    "iso:country":"GB",
    "wof:name":"WA6 0PW",
    "wof:placetype":"postalcode"
},
  "geometry": {"coordinates":[-2.76528624816852,53.27621769611856],"type":"Point"}
}