{
  "type": "Feature",
  "properties": {
    "iso:country": "GB",
    "wof:name": "LN7 6AR",
    "wof:placetype": "postalcode"
  },
  "geometry": {"coordinates":[-0.3326,53.486274],"type":"Point"}
}
