{
  "type": "Feature",
  "properties": {
    "iso:country": "GB",
    "wof:name": "LN7 6AR",
    "wof:placetype": "postalcode"
  },
  "geometry": {"coordinates":[-0.332298,53.486279],"type":"Point"}
}
