{
  "type": "Feature",
  "properties": {
    "iso:country": "GB",
    "wof:name": "HS2 9LN",
    "wof:placetype": "postalcode"
  },
  "geometry": {"coordinates":[-6.792842,58.193744],"type":"Point"}
}
