{
  "type": "Feature",
  "properties": {
    "date:inception_lower": "1980-01-01",
    "date:inception_upper": "1980-01-01",
    "iso:country": "GB",
    "wof:name": "BH15 4LY",
    "wof:placetype": "postalcode"
  },
  "geometry": {"coordinates":[-2.023759,50.717015],"type":"Point"}
}
