{
  "type": "Feature",
  "properties": {
    "iso:country":"GB",
    "wof:name":"BH15 4LY",
    "wof:placetype":"postalcode"
},
  "geometry": {"coordinates":[-2.02375880485587,50.71701496414172],"type":"Point"}
}