{
  "type": "Feature",
  "properties": {
    "iso:country":"GB",
    "wof:name":"AL2 3RZ",
    "wof:placetype":"postalcode"
},
  "geometry": {"coordinates":[-0.3748520559233,51.70729946742404],"type":"Point"}
}