{
  "type": "Feature",
  "properties": {
    "iso:country": "GB",
    "wof:name": "AL2 3RZ",
    "wof:placetype": "postalcode"
  },
  "geometry": {"coordinates":[-0.374852,51.707299],"type":"Point"}
}
