{
  "type": "Feature",
  "properties": {
    "date:inception_lower": "1999-06-01",
    "date:inception_upper": "1999-06-01",
    "iso:country": "GB",
    "wof:name": "E3 5BQ",
    "wof:placetype": "postalcode"
  },
  "geometry": {"coordinates":[-0.035181,51.530857],"type":"Point"}
}
