{
  "type": "Feature",
  "properties": {
    "iso:country":"GB",
    "wof:name":"E3 5BQ",
    "wof:placetype":"postalcode"
},
  "geometry": {"coordinates":[-0.03518080464818,51.53085655690747],"type":"Point"}
}