{
  "type": "Feature",
  "properties": {
    "date:inception_lower":"1996-06-01",
    "date:inception_upper":"1996-06-30",
    "iso:country":"GB",
    "wof:name":"HP2 7YJ",
    "wof:placetype":"postalcode"
},
  "geometry": {"coordinates":[-0.434788,51.762982],"type":"Point"}
}