{
  "type": "Feature",
  "properties": {
    "date:inception_lower":"1983-07-01",
    "date:inception_upper":"1983-07-31",
    "iso:country":"GB",
    "wof:name":"DL14 0SF",
    "wof:placetype":"postalcode"
},
  "geometry": {"coordinates":[-1.696017,54.647284],"type":"Point"}
}