{
  "type": "Feature",
  "properties": {
    "iso:country":"GB",
    "wof:name":"FY3 7RN",
    "wof:placetype":"postalcode"
},
  "geometry": {"coordinates":[-3.01336296809993,53.82632973405137],"type":"Point"}
}