{
  "type": "Feature",
  "properties": {
    "iso:country":"GB",
    "wof:name":"NR19 2PR",
    "wof:placetype":"postalcode"
},
  "geometry": {"coordinates":[0.92184774887548,52.67917689488099],"type":"Point"}
}