{
  "type": "Feature",
  "properties": {
    "date:inception_lower": "1980-01-01",
    "date:inception_upper": "1980-01-01",
    "iso:country": "GB",
    "wof:name": "NR19 2PR",
    "wof:placetype": "postalcode"
  },
  "geometry": {"coordinates":[0.921848,52.679177],"type":"Point"}
}
