{
  "type": "Feature",
  "properties": {
    "iso:country":"GB",
    "wof:name":"PL4 6PD",
    "wof:placetype":"postalcode"
},
  "geometry": {"coordinates":[-4.1398481573353,50.38099261514161],"type":"Point"}
}