{
  "type": "Feature",
  "properties": {
    "iso:country":"GB",
    "wof:name":"TW2 5LN",
    "wof:placetype":"postalcode"
},
  "geometry": {"coordinates":[-0.35175556685698,51.43751760659838],"type":"Point"}
}