{
  "type": "Feature",
  "properties": {
    "iso:country":"GB",
    "wof:name":"NG19 6BE",
    "wof:placetype":"postalcode"
},
  "geometry": {"coordinates":[-1.21475017732091,53.14998355410823],"type":"Point"}
}