{
  "type": "Feature",
  "properties": {
    "date:inception_lower": "1980-01-01",
    "date:inception_upper": "1980-01-01",
    "iso:country": "GB",
    "wof:name": "EH14 5TA",
    "wof:placetype": "postalcode"
  },
  "geometry": {"coordinates":[-3.334756,55.893418],"type":"Point"}
}
