{
  "type": "Feature",
  "properties": {
    "iso:country":"GB",
    "wof:name":"NR27 9QR",
    "wof:placetype":"postalcode"
},
  "geometry": {"coordinates":[1.24372816767196,52.9392674852925],"type":"Point"}
}