{
  "type": "Feature",
  "properties": {
    "iso:country":"GB",
    "wof:name":"SK11 7RS",
    "wof:placetype":"postalcode"
},
  "geometry": {"coordinates":[-2.12687179911343,53.24524076937271],"type":"Point"}
}