{
  "type": "Feature",
  "properties": {
    "iso:country":"GB",
    "wof:name":"SO21 2NN",
    "wof:placetype":"postalcode"
},
  "geometry": {"coordinates":[-1.38031647535966,51.07965837670817],"type":"Point"}
}