{
  "type": "Feature",
  "properties": {
    "date:inception_lower": "1980-01-01",
    "date:inception_upper": "1980-01-01",
    "iso:country": "GB",
    "wof:name": "SO21 2NN",
    "wof:placetype": "postalcode"
  },
  "geometry": {"coordinates":[-1.380316,51.079658],"type":"Point"}
}
