{
  "type": "Feature",
  "properties": {
    "date:inception_lower": "1980-01-01",
    "date:inception_upper": "1980-01-01",
    "iso:country": "GB",
    "wof:name": "LS25 5EY",
    "wof:placetype": "postalcode"
  },
  "geometry": {"coordinates":[-1.23216,53.760179],"type":"Point"}
}
