{
  "type": "Feature",
  "properties": {
    "iso:country":"GB",
    "wof:name":"G84 9DL",
    "wof:placetype":"postalcode"
},
  "geometry": {"coordinates":[-4.72078038117436,56.01455672636705],"type":"Point"}
}