{
  "type": "Feature",
  "properties": {
    "iso:country":"GB",
    "wof:name":"CW8 1LQ",
    "wof:placetype":"postalcode"
},
  "geometry": {"coordinates":[-2.54633140238546,53.24876571666007],"type":"Point"}
}