{
  "type": "Feature",
  "properties": {
    "iso:country":"GB",
    "wof:name":"NN11 4PN",
    "wof:placetype":"postalcode"
},
  "geometry": {"coordinates":[-1.16295702921451,52.25693673101133],"type":"Point"}
}