{
  "type": "Feature",
  "properties": {
    "iso:country": "GB",
    "wof:name": "NN11 4PL",
    "wof:placetype": "postalcode"
  },
  "geometry": {"coordinates":[-1.144584,52.262352],"type":"Point"}
}
