{
  "type": "Feature",
  "properties": {
    "iso:country":"GB",
    "wof:name":"NN11 4PL",
    "wof:placetype":"postalcode"
},
  "geometry": {"coordinates":[-1.14458366808933,52.26235224554306],"type":"Point"}
}