{
  "type": "Feature",
  "properties": {
    "iso:country":"GB",
    "wof:name":"PE28 9AX",
    "wof:placetype":"postalcode"
},
  "geometry": {"coordinates":[-0.12511134115469,52.32462737576319],"type":"Point"}
}