{
  "type": "Feature",
  "properties": {
    "iso:country": "GB",
    "wof:name": "PE28 9AX",
    "wof:placetype": "postalcode"
  },
  "geometry": {"coordinates":[-0.125111,52.324627],"type":"Point"}
}
