{
  "type": "Feature",
  "properties": {
    "iso:country":"GB",
    "wof:name":"TR1 2PN",
    "wof:placetype":"postalcode"
},
  "geometry": {"coordinates":[-5.05212907566289,50.26191537663667],"type":"Point"}
}