{
  "type": "Feature",
  "properties": {
    "iso:country": "GB",
    "wof:name": "W9 2AN",
    "wof:placetype": "postalcode"
  },
  "geometry": {"coordinates":[-0.196133,51.523712],"type":"Point"}
}
