{
  "type": "Feature",
  "properties": {
    "iso:country":"GB",
    "wof:name":"LL53 8NA",
    "wof:placetype":"postalcode"
},
  "geometry": {"coordinates":[-4.61862504164471,52.89778376466511],"type":"Point"}
}