{
  "type": "Feature",
  "properties": {
    "iso:country": "GB",
    "wof:name": "LL53 8NA",
    "wof:placetype": "postalcode"
  },
  "geometry": {"coordinates":[-4.618625,52.897784],"type":"Point"}
}
