{
  "type": "Feature",
  "properties": {
    "date:inception_lower": "2017-04-01",
    "date:inception_upper": "2017-04-01",
    "iso:country": "GB",
    "wof:name": "GL12 8EF",
    "wof:placetype": "postalcode"
  },
  "geometry": {"coordinates":[-2.394869,51.628563],"type":"Point"}
}
