{
  "type": "Feature",
  "properties": {
    "iso:country": "GB",
    "wof:name": "CA28 9RB",
    "wof:placetype": "postalcode"
  },
  "geometry": {"coordinates":[-3.587307,54.525621],"type":"Point"}
}
