{
  "type": "Feature",
  "properties": {
    "date:inception_lower": "1994-05-01",
    "date:inception_upper": "1994-05-01",
    "iso:country": "GB",
    "wof:name": "TS17 6DA",
    "wof:placetype": "postalcode"
  },
  "geometry": {"coordinates":[-1.306539,54.559553],"type":"Point"}
}
