{
  "type": "Feature",
  "properties": {
    "iso:country":"GB",
    "wof:name":"TS17 6DA",
    "wof:placetype":"postalcode"
},
  "geometry": {"coordinates":[-1.30644879093936,54.55952249355145],"type":"Point"}
}