{
  "type": "Feature",
  "properties": {
    "iso:country":"GB",
    "wof:name":"CB4 3XP",
    "wof:placetype":"postalcode"
},
  "geometry": {"coordinates":[0.11734984139032,52.23125899842354],"type":"Point"}
}