{
  "type": "Feature",
  "properties": {
    "date:inception_lower":"1997-06-01",
    "date:inception_upper":"1997-06-30",
    "iso:country":"GB",
    "wof:name":"CB4 3XP",
    "wof:placetype":"postalcode"
},
  "geometry": {"coordinates":[0.11735,52.231259],"type":"Point"}
}