{
  "type": "Feature",
  "properties": {
    "iso:country": "GB",
    "wof:name": "AB51 7QS",
    "wof:placetype": "postalcode"
  },
  "geometry": {"coordinates":[-2.546207,57.185684],"type":"Point"}
}
