{
  "type": "Feature",
  "properties": {
    "iso:country":"GB",
    "wof:name":"AB51 7QS",
    "wof:placetype":"postalcode"
},
  "geometry": {"coordinates":[-2.54595445050454,57.18569876469787],"type":"Point"}
}