{
  "type": "Feature",
  "properties": {
    "date:inception_lower": "2019-06-01",
    "date:inception_upper": "2019-06-01",
    "iso:country": "GB",
    "wof:name": "B78 1ER",
    "wof:placetype": "postalcode"
  },
  "geometry": {"coordinates":[-1.621971,52.618441],"type":"Point"}
}
