{
  "type": "Feature",
  "properties": {
    "iso:country": "GB",
    "wof:name": "B78 1ER",
    "wof:placetype": "postalcode"
  },
  "geometry": {"coordinates":[-1.622015,52.618441],"type":"Point"}
}
