{
  "type": "Feature",
  "properties": {
    "iso:country":"GB",
    "wof:name":"YO31 0QF",
    "wof:placetype":"postalcode"
},
  "geometry": {"coordinates":[-1.04764343591168,53.96065002494105],"type":"Point"}
}