{
  "type": "Feature",
  "properties": {
    "iso:country":"GB",
    "wof:name":"DE73 7FY",
    "wof:placetype":"postalcode"
},
  "geometry": {"coordinates":[-1.48799225842625,52.86145080304311],"type":"Point"}
}