{
  "type": "Feature",
  "properties": {
    "iso:country": "GB",
    "wof:name": "EX5 2PU",
    "wof:placetype": "postalcode"
  },
  "geometry": {"coordinates":[-3.353787,50.754902],"type":"Point"}
}
