{
  "type": "Feature",
  "properties": {
    "iso:country":"GB",
    "wof:name":"EX5 2PU",
    "wof:placetype":"postalcode"
},
  "geometry": {"coordinates":[-3.35378716901461,50.75490231319336],"type":"Point"}
}