{
  "type": "Feature",
  "properties": {
    "iso:country":"GB",
    "wof:name":"LA15 8PE",
    "wof:placetype":"postalcode"
},
  "geometry": {"coordinates":[-3.18324630470825,54.14678742699398],"type":"Point"}
}