{
  "type": "Feature",
  "properties": {
    "iso:country": "GB",
    "wof:name": "BS13 0BY",
    "wof:placetype": "postalcode"
  },
  "geometry": {"coordinates":[-2.607259,51.403477],"type":"Point"}
}
