{
  "type": "Feature",
  "properties": {
    "iso:country": "GB",
    "wof:name": "DE55 7PT",
    "wof:placetype": "postalcode"
  },
  "geometry": {"coordinates":[-1.396824,53.090279],"type":"Point"}
}
