{
  "type": "Feature",
  "properties": {
    "iso:country":"GB",
    "wof:name":"OX4 1BJ",
    "wof:placetype":"postalcode"
},
  "geometry": {"coordinates":[-1.23813607089875,51.75184358900141],"type":"Point"}
}