{
  "type": "Feature",
  "properties": {
    "iso:country":"GB",
    "wof:name":"CT16 2GZ",
    "wof:placetype":"postalcode"
},
  "geometry": {"coordinates":[1.29089147577892,51.15311781377329],"type":"Point"}
}