{
  "type": "Feature",
  "properties": {
    "date:inception_lower":"2005-06-01",
    "date:inception_upper":"2005-06-30",
    "iso:country":"GB",
    "wof:name":"CT16 2GZ",
    "wof:placetype":"postalcode"
},
  "geometry": {"coordinates":[1.291082,51.152949],"type":"Point"}
}