{
  "type": "Feature",
  "properties": {
    "iso:country": "GB",
    "wof:name": "TA16 5PS",
    "wof:placetype": "postalcode"
  },
  "geometry": {"coordinates":[-2.793096,50.912248],"type":"Point"}
}
