{
  "type": "Feature",
  "properties": {
    "iso:country": "GB",
    "wof:name": "NG34 7SL",
    "wof:placetype": "postalcode"
  },
  "geometry": {"coordinates":[-0.43247,52.993949],"type":"Point"}
}
