{
  "type": "Feature",
  "properties": {
    "date:inception_lower":"1980-01-01",
    "date:inception_upper":"1980-01-31",
    "iso:country":"GB",
    "wof:name":"N17 7QT",
    "wof:placetype":"postalcode"
},
  "geometry": {"coordinates":[-0.083831,51.598017],"type":"Point"}
}