{
  "type": "Feature",
  "properties": {
    "iso:country": "GB",
    "wof:name": "B77 4PX",
    "wof:placetype": "postalcode"
  },
  "geometry": {"coordinates":[-1.647416,52.609781],"type":"Point"}
}
