{
  "type": "Feature",
  "properties": {
    "iso:country":"GB",
    "wof:name":"HU16 5PN",
    "wof:placetype":"postalcode"
},
  "geometry": {"coordinates":[-0.42339284810808,53.78312099982231],"type":"Point"}
}