{
  "type": "Feature",
  "properties": {
    "iso:country":"GB",
    "wof:name":"SL6 7NB",
    "wof:placetype":"postalcode"
},
  "geometry": {"coordinates":[-0.73296647317786,51.53058542086041],"type":"Point"}
}