{
  "type": "Feature",
  "properties": {
    "iso:country":"GB",
    "wof:name":"B70 7LJ",
    "wof:placetype":"postalcode"
},
  "geometry": {"coordinates":[-1.99559512884205,52.50930532740056],"type":"Point"}
}