{
  "type": "Feature",
  "properties": {
    "date:inception_lower": "1980-01-01",
    "date:inception_upper": "1980-01-01",
    "iso:country": "GB",
    "wof:name": "BH21 7NF",
    "wof:placetype": "postalcode"
  },
  "geometry": {"coordinates":[-1.919815,50.801988],"type":"Point"}
}
