{
  "type": "Feature",
  "properties": {
    "date:inception_lower": "1980-01-01",
    "date:inception_upper": "1980-01-01",
    "iso:country": "GB",
    "wof:name": "TQ7 4AL",
    "wof:placetype": "postalcode"
  },
  "geometry": {"coordinates":[-3.856436,50.311285],"type":"Point"}
}
