{
  "type": "Feature",
  "properties": {
    "iso:country":"GB",
    "wof:name":"TQ7 4AL",
    "wof:placetype":"postalcode"
},
  "geometry": {"coordinates":[-3.85631985160556,50.31110611110361],"type":"Point"}
}