{
  "type": "Feature",
  "properties": {
    "date:inception_lower": "1980-01-01",
    "date:inception_upper": "1980-01-01",
    "iso:country": "GB",
    "wof:name": "CA13 9XN",
    "wof:placetype": "postalcode"
  },
  "geometry": {"coordinates":[-3.305311,54.660228],"type":"Point"}
}
