{
  "type": "Feature",
  "properties": {
    "iso:country": "GB",
    "wof:name": "CA13 9XN",
    "wof:placetype": "postalcode"
  },
  "geometry": {"coordinates":[-3.305311,54.66021],"type":"Point"}
}
