{
  "type": "Feature",
  "properties": {
    "iso:country": "GB",
    "wof:name": "B49 6DN",
    "wof:placetype": "postalcode"
  },
  "geometry": {"coordinates":[-1.832608,52.186305],"type":"Point"}
}
