{
  "type": "Feature",
  "properties": {
    "date:inception_lower": "1996-06-01",
    "date:inception_upper": "1996-06-01",
    "iso:country": "GB",
    "wof:name": "B49 6DN",
    "wof:placetype": "postalcode"
  },
  "geometry": {"coordinates":[-1.832608,52.186305],"type":"Point"}
}
