{
  "type": "Feature",
  "properties": {
    "iso:country": "GB",
    "wof:name": "DN18 5EQ",
    "wof:placetype": "postalcode"
  },
  "geometry": {"coordinates":[-0.443343,53.678318],"type":"Point"}
}
