{
  "type": "Feature",
  "properties": {
    "iso:country": "GB",
    "wof:name": "SP11 0AL",
    "wof:placetype": "postalcode"
  },
  "geometry": {"coordinates":[-1.45003,51.277577],"type":"Point"}
}
