{
  "type": "Feature",
  "properties": {
    "date:inception_lower": "1980-01-01",
    "date:inception_upper": "1980-01-01",
    "iso:country": "GB",
    "wof:name": "SP11 0AL",
    "wof:placetype": "postalcode"
  },
  "geometry": {"coordinates":[-1.45003,51.277577],"type":"Point"}
}
