{
  "type": "Feature",
  "properties": {
    "iso:country":"GB",
    "wof:name":"SP11 0AL",
    "wof:placetype":"postalcode"
},
  "geometry": {"coordinates":[-1.45004420152152,51.27758030882323],"type":"Point"}
}