{
  "type": "Feature",
  "properties": {
    "iso:country":"GB",
    "wof:name":"ML4 3LJ",
    "wof:placetype":"postalcode"
},
  "geometry": {"coordinates":[-4.04147925088194,55.82522902733899],"type":"Point"}
}