{
  "type": "Feature",
  "properties": {
    "date:inception_lower": "1990-09-01",
    "date:inception_upper": "1990-09-01",
    "iso:country": "GB",
    "wof:name": "ML4 3LJ",
    "wof:placetype": "postalcode"
  },
  "geometry": {"coordinates":[-4.041468,55.825225],"type":"Point"}
}
