{
  "type": "Feature",
  "properties": {
    "iso:country":"GB",
    "wof:name":"IP18 6EW",
    "wof:placetype":"postalcode"
},
  "geometry": {"coordinates":[1.67993325129671,52.32547186041025],"type":"Point"}
}