{
  "type": "Feature",
  "properties": {
    "iso:country":"GB",
    "wof:name":"HA3 9JS",
    "wof:placetype":"postalcode"
},
  "geometry": {"coordinates":[-0.29804948598968,51.58938605009889],"type":"Point"}
}