{
  "type": "Feature",
  "properties": {
    "iso:country":"GB",
    "wof:name":"BL1 4BE",
    "wof:placetype":"postalcode"
},
  "geometry": {"coordinates":[-2.44541164704417,53.58278001814018],"type":"Point"}
}