{
  "type": "Feature",
  "properties": {
    "iso:country": "GB",
    "wof:name": "DY2 0NW",
    "wof:placetype": "postalcode"
  },
  "geometry": {"coordinates":[-2.091632,52.491395],"type":"Point"}
}
