{
  "type": "Feature",
  "properties": {
    "iso:country":"GB",
    "wof:name":"DY2 0NW",
    "wof:placetype":"postalcode"
},
  "geometry": {"coordinates":[-2.09140225331651,52.49159569874576],"type":"Point"}
}