{
  "type": "Feature",
  "properties": {
    "date:inception_lower": "1980-01-01",
    "date:inception_upper": "1980-01-01",
    "iso:country": "GB",
    "wof:name": "DY2 0NW",
    "wof:placetype": "postalcode"
  },
  "geometry": {"coordinates":[-2.091485,52.491602],"type":"Point"}
}
