{
  "type": "Feature",
  "properties": {
    "iso:country":"GB",
    "wof:name":"WV16 6RA",
    "wof:placetype":"postalcode"
},
  "geometry": {"coordinates":[-2.57926848708967,52.50053258901242],"type":"Point"}
}