{
  "type": "Feature",
  "properties": {
    "date:inception_lower": "1998-06-01",
    "date:inception_upper": "1998-06-01",
    "iso:country": "GB",
    "wof:name": "WV16 6RA",
    "wof:placetype": "postalcode"
  },
  "geometry": {"coordinates":[-2.579268,52.500533],"type":"Point"}
}
