{
  "type": "Feature",
  "properties": {
    "iso:country":"GB",
    "wof:name":"BD14 6ND",
    "wof:placetype":"postalcode"
},
  "geometry": {"coordinates":[-1.817757276804,53.77906267939741],"type":"Point"}
}