{
  "type": "Feature",
  "properties": {
    "iso:country":"GB",
    "wof:name":"TS6 0AU",
    "wof:placetype":"postalcode"
},
  "geometry": {"coordinates":[-1.16809615647682,54.56857245436137],"type":"Point"}
}