{
  "type": "Feature",
  "properties": {
    "date:inception_lower": "1997-06-01",
    "date:inception_upper": "1997-06-01",
    "iso:country": "GB",
    "wof:name": "CR3 5FD",
    "wof:placetype": "postalcode"
  },
  "geometry": {"coordinates":[-0.099801,51.287041],"type":"Point"}
}
