{
  "type": "Feature",
  "properties": {
    "iso:country":"GB",
    "wof:name":"M9 4JJ",
    "wof:placetype":"postalcode"
},
  "geometry": {"coordinates":[-2.20433240285902,53.51199572183327],"type":"Point"}
}