{
  "type": "Feature",
  "properties": {
    "date:inception_lower": "2018-06-01",
    "date:inception_upper": "2018-06-01",
    "iso:country": "GB",
    "wof:name": "ST10 1FR",
    "wof:placetype": "postalcode"
  },
  "geometry": {"coordinates":[-1.982183,52.993543],"type":"Point"}
}
