{
  "type": "Feature",
  "properties": {
    "iso:country":"GB",
    "wof:name":"KT6 4TU",
    "wof:placetype":"postalcode"
},
  "geometry": {"coordinates":[-0.29902737125379,51.39674787940784],"type":"Point"}
}