{
  "type": "Feature",
  "properties": {
    "iso:country": "GB",
    "wof:name": "KT6 4TU",
    "wof:placetype": "postalcode"
  },
  "geometry": {"coordinates":[-0.299027,51.396748],"type":"Point"}
}
