{
  "type": "Feature",
  "properties": {
    "date:inception_lower":"1980-01-01",
    "date:inception_upper":"1980-01-31",
    "iso:country":"GB",
    "wof:name":"KT6 4TU",
    "wof:placetype":"postalcode"
},
  "geometry": {"coordinates":[-0.299027,51.396748],"type":"Point"}
}