{
  "type": "Feature",
  "properties": {
    "date:inception_lower": "1980-01-01",
    "date:inception_upper": "1980-01-01",
    "iso:country": "GB",
    "wof:name": "BS3 4HS",
    "wof:placetype": "postalcode"
  },
  "geometry": {"coordinates":[-2.592909,51.444319],"type":"Point"}
}
