{
  "type": "Feature",
  "properties": {
    "iso:country":"GB",
    "wof:name":"BS3 4HS",
    "wof:placetype":"postalcode"
},
  "geometry": {"coordinates":[-2.59290888738285,51.44431854889183],"type":"Point"}
}