{
  "type": "Feature",
  "properties": {
    "iso:country": "GB",
    "wof:name": "DH7 9SW",
    "wof:placetype": "postalcode"
  },
  "geometry": {"coordinates":[-1.66643,54.799188],"type":"Point"}
}
