{
  "type": "Feature",
  "properties": {
    "iso:country":"GB",
    "wof:name":"DH7 9SW",
    "wof:placetype":"postalcode"
},
  "geometry": {"coordinates":[-1.66642993574773,54.79918758499112],"type":"Point"}
}