{
  "type": "Feature",
  "properties": {
    "iso:country": "GB",
    "wof:name": "SG4 0JP",
    "wof:placetype": "postalcode"
  },
  "geometry": {"coordinates":[-0.254397,51.958218],"type":"Point"}
}
