{
  "type": "Feature",
  "properties": {
    "date:inception_lower": "1980-01-01",
    "date:inception_upper": "1980-01-01",
    "iso:country": "GB",
    "wof:name": "FK6 6HE",
    "wof:placetype": "postalcode"
  },
  "geometry": {"coordinates":[-3.90724,56.023314],"type":"Point"}
}
