{
  "type": "Feature",
  "properties": {
    "iso:country": "GB",
    "wof:name": "ME9 8WH",
    "wof:placetype": "postalcode"
  },
  "geometry": {"coordinates":[0.732587,51.374771],"type":"Point"}
}
