{
  "type": "Feature",
  "properties": {
    "date:inception_lower": "2021-03-01",
    "date:inception_upper": "2021-03-01",
    "iso:country": "GB",
    "wof:name": "YO25 6BG",
    "wof:placetype": "postalcode"
  },
  "geometry": {"coordinates":[-0.432597,54.002868],"type":"Point"}
}
