{
  "type": "Feature",
  "properties": {
    "iso:country":"GB",
    "wof:name":"BS27 3AS",
    "wof:placetype":"postalcode"
},
  "geometry": {"coordinates":[-2.7838433898366,51.27744102878593],"type":"Point"}
}