{
  "type": "Feature",
  "properties": {
    "iso:country":"GB",
    "wof:name":"AB43 6NA",
    "wof:placetype":"postalcode"
},
  "geometry": {"coordinates":[-2.19857908466214,57.64487132855484],"type":"Point"}
}