{
  "type": "Feature",
  "properties": {
    "iso:country": "GB",
    "wof:name": "AB43 6NA",
    "wof:placetype": "postalcode"
  },
  "geometry": {"coordinates":[-2.198579,57.644871],"type":"Point"}
}
