{
  "type": "Feature",
  "properties": {
    "iso:country":"GB",
    "wof:name":"RG29 1AJ",
    "wof:placetype":"postalcode"
},
  "geometry": {"coordinates":[-0.93519711287265,51.25579503105319],"type":"Point"}
}