{
  "type": "Feature",
  "properties": {
    "iso:country": "GB",
    "wof:name": "PO8 0FU",
    "wof:placetype": "postalcode"
  },
  "geometry": {"coordinates":[-0.994536,50.941784],"type":"Point"}
}
