{
  "type": "Feature",
  "properties": {
    "iso:country":"GB",
    "wof:name":"CO16 8RS",
    "wof:placetype":"postalcode"
},
  "geometry": {"coordinates":[1.07944941654526,51.79760022886434],"type":"Point"}
}