{
  "type": "Feature",
  "properties": {
    "iso:country":"GB",
    "wof:name":"HP4 1SE",
    "wof:placetype":"postalcode"
},
  "geometry": {"coordinates":[-0.58314717032624,51.77264124601629],"type":"Point"}
}