{
  "type": "Feature",
  "properties": {
    "iso:country":"GB",
    "wof:name":"DL9 3AL",
    "wof:placetype":"postalcode"
},
  "geometry": {"coordinates":[-1.73254020919973,54.38500599627699],"type":"Point"}
}