{
  "type": "Feature",
  "properties": {
    "iso:country":"GB",
    "wof:name":"E8 2PQ",
    "wof:placetype":"postalcode"
},
  "geometry": {"coordinates":[-0.07568035039137,51.54863176289275],"type":"Point"}
}