{
  "type": "Feature",
  "properties": {
    "date:inception_lower":"1995-07-01",
    "date:inception_upper":"1995-07-31",
    "iso:country":"GB",
    "wof:name":"WN4 8SP",
    "wof:placetype":"postalcode"
},
  "geometry": {"coordinates":[-2.621069,53.490287],"type":"Point"}
}