{
  "type": "Feature",
  "properties": {
    "iso:country": "GB",
    "wof:name": "WN4 8SP",
    "wof:placetype": "postalcode"
  },
  "geometry": {"coordinates":[-2.621069,53.490287],"type":"Point"}
}
