{
  "type": "Feature",
  "properties": {
    "iso:country":"GB",
    "wof:name":"SK12 1ZF",
    "wof:placetype":"postalcode"
},
  "geometry": {"coordinates":[-2.12855147540818,53.34042957307533],"type":"Point"}
}