{
  "type": "Feature",
  "properties": {
    "date:inception_lower": "2002-06-01",
    "date:inception_upper": "2002-06-01",
    "iso:country": "GB",
    "wof:name": "SK12 1ZF",
    "wof:placetype": "postalcode"
  },
  "geometry": {"coordinates":[-2.128551,53.34043],"type":"Point"}
}
