{
  "type": "Feature",
  "properties": {
    "date:inception_lower":"1998-06-01",
    "date:inception_upper":"1998-06-30",
    "iso:country":"GB",
    "wof:name":"YO10 3JA",
    "wof:placetype":"postalcode"
},
  "geometry": {"coordinates":[-1.026976,53.95839],"type":"Point"}
}