{
  "type": "Feature",
  "properties": {
    "iso:country":"GB",
    "wof:name":"TQ5 9NJ",
    "wof:placetype":"postalcode"
},
  "geometry": {"coordinates":[-3.51902045116848,50.38831450306615],"type":"Point"}
}