{
  "type": "Feature",
  "properties": {
    "iso:country":"GB",
    "wof:name":"NR9 3PN",
    "wof:placetype":"postalcode"
},
  "geometry": {"coordinates":[1.18727467664414,52.60306429812474],"type":"Point"}
}