{
  "type": "Feature",
  "properties": {
    "date:inception_lower": "1990-02-01",
    "date:inception_upper": "1990-02-01",
    "iso:country": "GB",
    "wof:name": "NR9 3PN",
    "wof:placetype": "postalcode"
  },
  "geometry": {"coordinates":[1.187275,52.603064],"type":"Point"}
}
