{
  "type": "Feature",
  "properties": {
    "iso:country":"GB",
    "wof:name":"DL6 2QQ",
    "wof:placetype":"postalcode"
},
  "geometry": {"coordinates":[-1.43106361463817,54.35745018397252],"type":"Point"}
}