{
  "type": "Feature",
  "properties": {
    "date:inception_lower": "1980-01-01",
    "date:inception_upper": "1980-01-01",
    "iso:country": "GB",
    "wof:name": "SE26 5HZ",
    "wof:placetype": "postalcode"
  },
  "geometry": {"coordinates":[-0.05268,51.42276],"type":"Point"}
}
