{
  "type": "Feature",
  "properties": {
    "iso:country":"GB",
    "wof:name":"SE26 5HZ",
    "wof:placetype":"postalcode"
},
  "geometry": {"coordinates":[-0.05267973274619,51.42275984367523],"type":"Point"}
}