{
  "type": "Feature",
  "properties": {
    "iso:country": "GB",
    "wof:name": "SE26 5HZ",
    "wof:placetype": "postalcode"
  },
  "geometry": {"coordinates":[-0.05268,51.42276],"type":"Point"}
}
