{
  "type": "Feature",
  "properties": {
    "iso:country":"GB",
    "wof:name":"NW2 5AN",
    "wof:placetype":"postalcode"
},
  "geometry": {"coordinates":[-0.22684325720856,51.54843290800122],"type":"Point"}
}