{
  "type": "Feature",
  "properties": {
    "date:inception_lower":"2007-02-01",
    "date:inception_upper":"2007-02-28",
    "iso:country":"GB",
    "wof:name":"SR5 2TD",
    "wof:placetype":"postalcode"
},
  "geometry": {"coordinates":[-1.409987,54.91599],"type":"Point"}
}