{
  "type": "Feature",
  "properties": {
    "iso:country":"GB",
    "wof:name":"M31 4QJ",
    "wof:placetype":"postalcode"
},
  "geometry": {"coordinates":[-2.4121907694924,53.42687735769732],"type":"Point"}
}