{
  "type": "Feature",
  "properties": {
    "date:inception_lower": "1994-12-01",
    "date:inception_upper": "1994-12-01",
    "iso:country": "GB",
    "wof:name": "M31 4QJ",
    "wof:placetype": "postalcode"
  },
  "geometry": {"coordinates":[-2.412191,53.426877],"type":"Point"}
}
