{
  "type": "Feature",
  "properties": {
    "iso:country": "GB",
    "wof:name": "CA22 2SL",
    "wof:placetype": "postalcode"
  },
  "geometry": {"coordinates":[-3.525717,54.46437],"type":"Point"}
}
