{
  "type": "Feature",
  "properties": {
    "iso:country":"GB",
    "wof:name":"CA22 2SL",
    "wof:placetype":"postalcode"
},
  "geometry": {"coordinates":[-3.52571690606061,54.4643698936922],"type":"Point"}
}