{
  "type": "Feature",
  "properties": {
    "iso:country":"GB",
    "wof:name":"CT16 3NF",
    "wof:placetype":"postalcode"
},
  "geometry": {"coordinates":[1.28685085383047,51.14738468418579],"type":"Point"}
}