{
  "type": "Feature",
  "properties": {
    "date:inception_lower": "2001-06-01",
    "date:inception_upper": "2001-06-01",
    "iso:country": "GB",
    "wof:name": "CT16 3NF",
    "wof:placetype": "postalcode"
  },
  "geometry": {"coordinates":[1.287464,51.148122],"type":"Point"}
}
