{
  "type": "Feature",
  "properties": {
    "iso:country": "GB",
    "wof:name": "NN11 7HG",
    "wof:placetype": "postalcode"
  },
  "geometry": {"coordinates":[-1.207637,52.292497],"type":"Point"}
}
