{
  "type": "Feature",
  "properties": {
    "date:inception_lower":"2014-04-01",
    "date:inception_upper":"2014-04-30",
    "iso:country":"GB",
    "wof:name":"L39 2BU",
    "wof:placetype":"postalcode"
},
  "geometry": {"coordinates":[-2.877135,53.568007],"type":"Point"}
}