{
  "type": "Feature",
  "properties": {
    "iso:country":"GB",
    "wof:name":"L39 2BU",
    "wof:placetype":"postalcode"
},
  "geometry": {"coordinates":[-2.87713498496018,53.56800661091577],"type":"Point"}
}