{
  "type": "Feature",
  "properties": {
    "iso:country": "GB",
    "wof:name": "L39 2BU",
    "wof:placetype": "postalcode"
  },
  "geometry": {"coordinates":[-2.877135,53.568007],"type":"Point"}
}
