{
  "type": "Feature",
  "properties": {
    "iso:country": "GB",
    "wof:name": "NN3 7UG",
    "wof:placetype": "postalcode"
  },
  "geometry": {"coordinates":[-0.849357,52.288711],"type":"Point"}
}
