{
  "type": "Feature",
  "properties": {
    "iso:country":"GB",
    "wof:name":"NN3 7UG",
    "wof:placetype":"postalcode"
},
  "geometry": {"coordinates":[-0.84937248530559,52.2886961535471],"type":"Point"}
}