{
  "type": "Feature",
  "properties": {
    "iso:country":"GB",
    "wof:name":"CH5 2JF",
    "wof:placetype":"postalcode"
},
  "geometry": {"coordinates":[-3.00860204893739,53.21666988090194],"type":"Point"}
}