{
  "type": "Feature",
  "properties": {
    "iso:country":"GB",
    "wof:name":"M27 0LB",
    "wof:placetype":"postalcode"
},
  "geometry": {"coordinates":[-2.35534543019687,53.50930492966389],"type":"Point"}
}