{
  "type": "Feature",
  "properties": {
    "iso:country":"GB",
    "wof:name":"BD2 1AG",
    "wof:placetype":"postalcode"
},
  "geometry": {"coordinates":[-1.76969510438928,53.82400085503183],"type":"Point"}
}