{
  "type": "Feature",
  "properties": {
    "iso:country":"GB",
    "wof:name":"CH64 4BU",
    "wof:placetype":"postalcode"
},
  "geometry": {"coordinates":[-3.05510450436247,53.28372221292819],"type":"Point"}
}