{
  "type": "Feature",
  "properties": {
    "iso:country": "GB",
    "wof:name": "LL11 2TP",
    "wof:placetype": "postalcode"
  },
  "geometry": {"coordinates":[-2.992096,53.062857],"type":"Point"}
}
