{
  "type": "Feature",
  "properties": {
    "iso:country":"GB",
    "wof:name":"LL11 2TP",
    "wof:placetype":"postalcode"
},
  "geometry": {"coordinates":[-2.99209634149474,53.06285722640811],"type":"Point"}
}