{
  "type": "Feature",
  "properties": {
    "date:inception_lower": "2009-07-01",
    "date:inception_upper": "2009-07-01",
    "iso:country": "GB",
    "wof:name": "LL11 2TP",
    "wof:placetype": "postalcode"
  },
  "geometry": {"coordinates":[-2.992096,53.062857],"type":"Point"}
}
