{
  "type": "Feature",
  "properties": {
    "iso:country": "GB",
    "wof:name": "B14 4ES",
    "wof:placetype": "postalcode"
  },
  "geometry": {"coordinates":[-1.862217,52.415016],"type":"Point"}
}
