{
  "type": "Feature",
  "properties": {
    "date:inception_lower": "1980-01-01",
    "date:inception_upper": "1980-01-01",
    "iso:country": "GB",
    "wof:name": "B14 4ES",
    "wof:placetype": "postalcode"
  },
  "geometry": {"coordinates":[-1.862217,52.415016],"type":"Point"}
}
