{
  "type": "Feature",
  "properties": {
    "iso:country":"GB",
    "wof:name":"AB51 5EX",
    "wof:placetype":"postalcode"
},
  "geometry": {"coordinates":[-2.41762782415573,57.28848962589364],"type":"Point"}
}