{
  "type": "Feature",
  "properties": {
    "iso:country": "GB",
    "wof:name": "SN16 0LR",
    "wof:placetype": "postalcode"
  },
  "geometry": {"coordinates":[-2.211412,51.572938],"type":"Point"}
}
