{
  "type": "Feature",
  "properties": {
    "date:inception_lower": "2015-04-01",
    "date:inception_upper": "2015-04-01",
    "iso:country": "GB",
    "wof:name": "PE6 9AX",
    "wof:placetype": "postalcode"
  },
  "geometry": {"coordinates":[-0.351879,52.70923],"type":"Point"}
}
