{
  "type": "Feature",
  "properties": {
    "iso:country": "GB",
    "wof:name": "TN4 8LA",
    "wof:placetype": "postalcode"
  },
  "geometry": {"coordinates":[0.242615,51.119622],"type":"Point"}
}
