{
  "type": "Feature",
  "properties": {
    "iso:country":"GB",
    "wof:name":"CO2 9ND",
    "wof:placetype":"postalcode"
},
  "geometry": {"coordinates":[0.87946068951198,51.86715569509511],"type":"Point"}
}