{
  "type": "Feature",
  "properties": {
    "iso:country":"GB",
    "wof:name":"G15 7SP",
    "wof:placetype":"postalcode"
},
  "geometry": {"coordinates":[-4.36168503583125,55.91175393684323],"type":"Point"}
}