{
  "type": "Feature",
  "properties": {
    "date:inception_lower":"2003-08-01",
    "date:inception_upper":"2003-08-31",
    "iso:country":"GB",
    "wof:name":"G15 7SP",
    "wof:placetype":"postalcode"
},
  "geometry": {"coordinates":[-4.36167,55.911748],"type":"Point"}
}