{
  "type": "Feature",
  "properties": {
    "date:inception_lower": "2003-08-01",
    "date:inception_upper": "2003-08-01",
    "iso:country": "GB",
    "wof:name": "G15 7SP",
    "wof:placetype": "postalcode"
  },
  "geometry": {"coordinates":[-4.360162,55.913009],"type":"Point"}
}
