{
  "type": "Feature",
  "properties": {
    "iso:country": "GB",
    "wof:name": "PE22 0PH",
    "wof:placetype": "postalcode"
  },
  "geometry": {"coordinates":[0.027362,52.994423],"type":"Point"}
}
