{
  "type": "Feature",
  "properties": {
    "iso:country":"GB",
    "wof:name":"SA3 3BU",
    "wof:placetype":"postalcode"
},
  "geometry": {"coordinates":[-4.03990835477314,51.57075194420806],"type":"Point"}
}