{
  "type": "Feature",
  "properties": {
    "date:inception_lower": "1982-03-01",
    "date:inception_upper": "1982-03-01",
    "iso:country": "GB",
    "wof:name": "ME5 9HS",
    "wof:placetype": "postalcode"
  },
  "geometry": {"coordinates":[0.517512,51.332133],"type":"Point"}
}
