{
  "type": "Feature",
  "properties": {
    "iso:country": "GB",
    "wof:name": "BS25 1LU",
    "wof:placetype": "postalcode"
  },
  "geometry": {"coordinates":[-2.819851,51.312979],"type":"Point"}
}
