{
  "type": "Feature",
  "properties": {
    "iso:country":"GB",
    "wof:name":"BS25 1LU",
    "wof:placetype":"postalcode"
},
  "geometry": {"coordinates":[-2.81984514084591,51.31298247013071],"type":"Point"}
}