{
  "type": "Feature",
  "properties": {
    "date:inception_lower": "2018-06-01",
    "date:inception_upper": "2018-06-01",
    "iso:country": "GB",
    "wof:name": "S60 8BN",
    "wof:placetype": "postalcode"
  },
  "geometry": {"coordinates":[-1.37655,53.382153],"type":"Point"}
}
