{
  "type": "Feature",
  "properties": {
    "iso:country":"GB",
    "wof:name":"N8 9JD",
    "wof:placetype":"postalcode"
},
  "geometry": {"coordinates":[-0.12139432029642,51.57787876302532],"type":"Point"}
}