{
  "type": "Feature",
  "properties": {
    "iso:country": "GB",
    "wof:name": "TF8 7QS",
    "wof:placetype": "postalcode"
  },
  "geometry": {"coordinates":[-2.481127,52.629645],"type":"Point"}
}
