{
  "type": "Feature",
  "properties": {
    "iso:country":"GB",
    "wof:name":"TF8 7QS",
    "wof:placetype":"postalcode"
},
  "geometry": {"coordinates":[-2.48112706086286,52.62964510441449],"type":"Point"}
}