{
  "type": "Feature",
  "properties": {
    "iso:country":"GB",
    "wof:name":"GL15 5DD",
    "wof:placetype":"postalcode"
},
  "geometry": {"coordinates":[-2.53562087731015,51.72474913171529],"type":"Point"}
}