{
  "type": "Feature",
  "properties": {
    "iso:country": "GB",
    "wof:name": "M18 8BL",
    "wof:placetype": "postalcode"
  },
  "geometry": {"coordinates":[-2.184974,53.46446],"type":"Point"}
}
