{
  "type": "Feature",
  "properties": {
    "iso:country":"GB",
    "wof:name":"NG10 3QH",
    "wof:placetype":"postalcode"
},
  "geometry": {"coordinates":[-1.29371291979684,52.89442609836362],"type":"Point"}
}