{
  "type": "Feature",
  "properties": {
    "date:inception_lower": "2005-08-01",
    "date:inception_upper": "2005-08-01",
    "iso:country": "GB",
    "wof:name": "NG10 3QH",
    "wof:placetype": "postalcode"
  },
  "geometry": {"coordinates":[-1.293713,52.894426],"type":"Point"}
}
