{
  "type": "Feature",
  "properties": {
    "iso:country":"GB",
    "wof:name":"DD3 0NN",
    "wof:placetype":"postalcode"
},
  "geometry": {"coordinates":[-2.98708990874735,56.4927553899017],"type":"Point"}
}