{
  "type": "Feature",
  "properties": {
    "date:inception_lower": "1980-01-01",
    "date:inception_upper": "1980-01-01",
    "iso:country": "GB",
    "wof:name": "DY13 0RR",
    "wof:placetype": "postalcode"
  },
  "geometry": {"coordinates":[-2.295964,52.305758],"type":"Point"}
}
