{
  "type": "Feature",
  "properties": {
    "iso:country": "GB",
    "wof:name": "TS15 9ZF",
    "wof:placetype": "postalcode"
  },
  "geometry": {"coordinates":[-1.358346,54.491249],"type":"Point"}
}
