{
  "type": "Feature",
  "properties": {
    "iso:country":"GB",
    "wof:name":"KT1 1BS",
    "wof:placetype":"postalcode"
},
  "geometry": {"coordinates":[-0.30418798553669,51.40918733663079],"type":"Point"}
}