{
  "type": "Feature",
  "properties": {
    "iso:country": "GB",
    "wof:name": "BB7 9BU",
    "wof:placetype": "postalcode"
  },
  "geometry": {"coordinates":[-2.3877,53.833517],"type":"Point"}
}
