{
  "type": "Feature",
  "properties": {
    "iso:country": "GB",
    "wof:name": "W1S 1DZ",
    "wof:placetype": "postalcode"
  },
  "geometry": {"coordinates":[-0.144856,51.512418],"type":"Point"}
}
