{
  "type": "Feature",
  "properties": {
    "date:inception_lower":"2000-12-01",
    "date:inception_upper":"2000-12-31",
    "iso:country":"GB",
    "wof:name":"W1S 1DZ",
    "wof:placetype":"postalcode"
},
  "geometry": {"coordinates":[-0.144856,51.512418],"type":"Point"}
}