{
  "type": "Feature",
  "properties": {
    "iso:country":"GB",
    "wof:name":"W1S 1DZ",
    "wof:placetype":"postalcode"
},
  "geometry": {"coordinates":[-0.14485596154152,51.51241822346728],"type":"Point"}
}