{
  "type": "Feature",
  "properties": {
    "iso:country":"GB",
    "wof:name":"MK43 7PY",
    "wof:placetype":"postalcode"
},
  "geometry": {"coordinates":[-0.5489858398404,52.1908289039766],"type":"Point"}
}