{
  "type": "Feature",
  "properties": {
    "iso:country":"GB",
    "wof:name":"GL51 7AP",
    "wof:placetype":"postalcode"
},
  "geometry": {"coordinates":[-2.10547141127243,51.89513379521063],"type":"Point"}
}