{
  "type": "Feature",
  "properties": {
    "iso:country": "GB",
    "wof:name": "SP7 9LP",
    "wof:placetype": "postalcode"
  },
  "geometry": {"coordinates":[-2.165109,51.006116],"type":"Point"}
}
