{
  "type": "Feature",
  "properties": {
    "iso:country":"GB",
    "wof:name":"SP7 9LP",
    "wof:placetype":"postalcode"
},
  "geometry": {"coordinates":[-2.16510880492924,51.00611563619808],"type":"Point"}
}