{
  "type": "Feature",
  "properties": {
    "date:inception_lower":"1993-01-01",
    "date:inception_upper":"1993-01-31",
    "iso:country":"GB",
    "wof:name":"SP7 9LP",
    "wof:placetype":"postalcode"
},
  "geometry": {"coordinates":[-2.165109,51.006116],"type":"Point"}
}