{
  "type": "Feature",
  "properties": {
    "date:inception_lower": "1980-01-01",
    "date:inception_upper": "1980-01-01",
    "iso:country": "GB",
    "wof:name": "SA15 2RW",
    "wof:placetype": "postalcode"
  },
  "geometry": {"coordinates":[-4.161323,51.674881],"type":"Point"}
}
