{
  "type": "Feature",
  "properties": {
    "iso:country":"GB",
    "wof:name":"SA15 2RW",
    "wof:placetype":"postalcode"
},
  "geometry": {"coordinates":[-4.16136579436392,51.67487101560818],"type":"Point"}
}