{
  "type": "Feature",
  "properties": {
    "iso:country": "GB",
    "wof:name": "LN6 7RN",
    "wof:placetype": "postalcode"
  },
  "geometry": {"coordinates":[-0.567573,53.209102],"type":"Point"}
}
