{
  "type": "Feature",
  "properties": {
    "iso:country":"GB",
    "wof:name":"KA1 1TA",
    "wof:placetype":"postalcode"
},
  "geometry": {"coordinates":[-4.50282067240382,55.59951994122948],"type":"Point"}
}