{
  "type": "Feature",
  "properties": {
    "iso:country":"GB",
    "wof:name":"UB1 3AT",
    "wof:placetype":"postalcode"
},
  "geometry": {"coordinates":[-0.36480137428651,51.51011546887069],"type":"Point"}
}