{
  "type": "Feature",
  "properties": {
    "date:inception_lower":"1980-01-01",
    "date:inception_upper":"1980-01-31",
    "iso:country":"GB",
    "wof:name":"LD2 3EQ",
    "wof:placetype":"postalcode"
},
  "geometry": {"coordinates":[-3.321503,52.078687],"type":"Point"}
}