{
  "type": "Feature",
  "properties": {
    "iso:country":"GB",
    "wof:name":"LD2 3EQ",
    "wof:placetype":"postalcode"
},
  "geometry": {"coordinates":[-3.32145140254258,52.07871585396079],"type":"Point"}
}