{
  "type": "Feature",
  "properties": {
    "date:inception_lower":"2009-05-01",
    "date:inception_upper":"2009-05-31",
    "iso:country":"GB",
    "wof:name":"G61 1FE",
    "wof:placetype":"postalcode"
},
  "geometry": {"coordinates":[-4.346227,55.911232],"type":"Point"}
}