{
  "type": "Feature",
  "properties": {
    "iso:country": "GB",
    "wof:name": "G61 1FE",
    "wof:placetype": "postalcode"
  },
  "geometry": {"coordinates":[-4.346227,55.911232],"type":"Point"}
}
