{
  "type": "Feature",
  "properties": {
    "iso:country": "GB",
    "wof:name": "G61 1FE",
    "wof:placetype": "postalcode"
  },
  "geometry": {"coordinates":[-4.346133,55.911236],"type":"Point"}
}
