{
  "type": "Feature",
  "properties": {
    "iso:country":"GB",
    "wof:name":"BN3 2GT",
    "wof:placetype":"postalcode"
},
  "geometry": {"coordinates":[-0.16607046101768,50.82437702888402],"type":"Point"}
}