{
  "type": "Feature",
  "properties": {
    "iso:country": "GB",
    "wof:name": "BN3 2GT",
    "wof:placetype": "postalcode"
  },
  "geometry": {"coordinates":[-0.16607,50.824377],"type":"Point"}
}
