{
  "type": "Feature",
  "properties": {
    "date:inception_lower": "1993-01-01",
    "date:inception_upper": "1993-01-01",
    "iso:country": "GB",
    "wof:name": "LE11 2LE",
    "wof:placetype": "postalcode"
  },
  "geometry": {"coordinates":[-1.200615,52.757796],"type":"Point"}
}
