{
  "type": "Feature",
  "properties": {
    "iso:country":"GB",
    "wof:name":"LE11 2LE",
    "wof:placetype":"postalcode"
},
  "geometry": {"coordinates":[-1.20061530178129,52.75779568167415],"type":"Point"}
}