{
  "type": "Feature",
  "properties": {
    "iso:country": "GB",
    "wof:name": "LE11 2LE",
    "wof:placetype": "postalcode"
  },
  "geometry": {"coordinates":[-1.200615,52.757796],"type":"Point"}
}
