{
  "type": "Feature",
  "properties": {
    "iso:country":"GB",
    "wof:name":"HX2 9TG",
    "wof:placetype":"postalcode"
},
  "geometry": {"coordinates":[-1.87527275049373,53.75774471960388],"type":"Point"}
}