{
  "type": "Feature",
  "properties": {
    "date:inception_lower": "2017-03-01",
    "date:inception_upper": "2017-03-01",
    "iso:country": "GB",
    "wof:name": "CB8 7FY",
    "wof:placetype": "postalcode"
  },
  "geometry": {"coordinates":[0.498912,52.274232],"type":"Point"}
}
