{
  "type": "Feature",
  "properties": {
    "date:inception_lower": "1980-01-01",
    "date:inception_upper": "1980-01-01",
    "iso:country": "GB",
    "wof:name": "HA3 6PE",
    "wof:placetype": "postalcode"
  },
  "geometry": {"coordinates":[-0.35929,51.606111],"type":"Point"}
}
