{
  "type": "Feature",
  "properties": {
    "iso:country":"GB",
    "wof:name":"HA3 6PE",
    "wof:placetype":"postalcode"
},
  "geometry": {"coordinates":[-0.35928985520171,51.60611124756012],"type":"Point"}
}