{
  "type": "Feature",
  "properties": {
    "iso:country": "GB",
    "wof:name": "PE7 3GH",
    "wof:placetype": "postalcode"
  },
  "geometry": {"coordinates":[-0.328188,52.548513],"type":"Point"}
}
