{
  "type": "Feature",
  "properties": {
    "date:inception_lower": "2016-07-01",
    "date:inception_upper": "2016-07-01",
    "iso:country": "GB",
    "wof:name": "PE7 3GH",
    "wof:placetype": "postalcode"
  },
  "geometry": {"coordinates":[-0.195508,52.542367],"type":"Point"}
}
