{
  "type": "Feature",
  "properties": {
    "date:inception_lower":"2016-07-01",
    "date:inception_upper":"2016-07-31",
    "iso:country":"GB",
    "wof:name":"PE7 3GH",
    "wof:placetype":"postalcode"
},
  "geometry": {"coordinates":[-0.328188,52.548513],"type":"Point"}
}