{
  "type": "Feature",
  "properties": {
    "iso:country":"GB",
    "wof:name":"WA3 3AZ",
    "wof:placetype":"postalcode"
},
  "geometry": {"coordinates":[-2.59700450775569,53.47567743965485],"type":"Point"}
}