{
  "type": "Feature",
  "properties": {
    "date:inception_lower": "1980-01-01",
    "date:inception_upper": "1980-01-01",
    "iso:country": "GB",
    "wof:name": "RM9 6PD",
    "wof:placetype": "postalcode"
  },
  "geometry": {"coordinates":[0.147024,51.538024],"type":"Point"}
}
