{
  "type": "Feature",
  "properties": {
    "iso:country":"GB",
    "wof:name":"RM9 6PD",
    "wof:placetype":"postalcode"
},
  "geometry": {"coordinates":[0.14739944760323,51.538015728652],"type":"Point"}
}