{
  "type": "Feature",
  "properties": {
    "iso:country":"GB",
    "wof:name":"PA16 8SX",
    "wof:placetype":"postalcode"
},
  "geometry": {"coordinates":[-4.77631878654572,55.95264479526736],"type":"Point"}
}