{
  "type": "Feature",
  "properties": {
    "iso:country":"GB",
    "wof:name":"LL44 2HF",
    "wof:placetype":"postalcode"
},
  "geometry": {"coordinates":[-4.09912840123113,52.78827317795088],"type":"Point"}
}