{
  "type": "Feature",
  "properties": {
    "iso:country":"GB",
    "wof:name":"DL12 9PF",
    "wof:placetype":"postalcode"
},
  "geometry": {"coordinates":[-1.98564337728061,54.57355004206996],"type":"Point"}
}