{
  "type": "Feature",
  "properties": {
    "date:inception_lower": "1980-01-01",
    "date:inception_upper": "1980-01-01",
    "iso:country": "GB",
    "wof:name": "DL12 9PF",
    "wof:placetype": "postalcode"
  },
  "geometry": {"coordinates":[-1.985643,54.57355],"type":"Point"}
}
