{
  "type": "Feature",
  "properties": {
    "iso:country":"GB",
    "wof:name":"FK1 3AW",
    "wof:placetype":"postalcode"
},
  "geometry": {"coordinates":[-3.79847664425533,55.94372667153808],"type":"Point"}
}