{
  "type": "Feature",
  "properties": {
    "iso:country": "GB",
    "wof:name": "SO41 5QY",
    "wof:placetype": "postalcode"
  },
  "geometry": {"coordinates":[-1.519382,50.783626],"type":"Point"}
}
