{
  "type": "Feature",
  "properties": {
    "iso:country":"GB",
    "wof:name":"SO41 5QY",
    "wof:placetype":"postalcode"
},
  "geometry": {"coordinates":[-1.51902190455487,50.78366048359688],"type":"Point"}
}