{
  "type": "Feature",
  "properties": {
    "date:inception_lower": "2021-01-01",
    "date:inception_upper": "2021-01-01",
    "iso:country": "GB",
    "wof:name": "NN11 4RU",
    "wof:placetype": "postalcode"
  },
  "geometry": {"coordinates":[-1.168878,52.248148],"type":"Point"}
}
