{
  "type": "Feature",
  "properties": {
    "date:inception_lower": "2010-05-01",
    "date:inception_upper": "2010-05-01",
    "iso:country": "GB",
    "wof:name": "PE13 2GA",
    "wof:placetype": "postalcode"
  },
  "geometry": {"coordinates":[0.158938,52.656423],"type":"Point"}
}
