{
  "type": "Feature",
  "properties": {
    "iso:country": "GB",
    "wof:name": "PE13 2GA",
    "wof:placetype": "postalcode"
  },
  "geometry": {"coordinates":[0.159054,52.656376],"type":"Point"}
}
