{
  "type": "Feature",
  "properties": {
    "iso:country":"GB",
    "wof:name":"PE13 2GA",
    "wof:placetype":"postalcode"
},
  "geometry": {"coordinates":[0.15892280237829,52.65640418409866],"type":"Point"}
}