{
  "type": "Feature",
  "properties": {
    "iso:country":"GB",
    "wof:name":"S18 2XY",
    "wof:placetype":"postalcode"
},
  "geometry": {"coordinates":[-1.45065044783792,53.29916382314668],"type":"Point"}
}