{
  "type": "Feature",
  "properties": {
    "date:inception_lower":"1990-02-01",
    "date:inception_upper":"1990-02-28",
    "iso:country":"GB",
    "wof:name":"DN14 7JB",
    "wof:placetype":"postalcode"
},
  "geometry": {"coordinates":[-0.865134,53.747882],"type":"Point"}
}