{
  "type": "Feature",
  "properties": {
    "iso:country":"GB",
    "wof:name":"BS10 7TT",
    "wof:placetype":"postalcode"
},
  "geometry": {"coordinates":[-2.61730079614297,51.52129563486028],"type":"Point"}
}