{
  "type": "Feature",
  "properties": {
    "iso:country": "GB",
    "wof:name": "BS10 7TT",
    "wof:placetype": "postalcode"
  },
  "geometry": {"coordinates":[-2.617301,51.521296],"type":"Point"}
}
