{
  "type": "Feature",
  "properties": {
    "iso:country":"GB",
    "wof:name":"B90 4RB",
    "wof:placetype":"postalcode"
},
  "geometry": {"coordinates":[-1.8123046730967,52.40204104198288],"type":"Point"}
}