{
  "type": "Feature",
  "properties": {
    "date:inception_lower": "1997-06-01",
    "date:inception_upper": "1997-06-01",
    "iso:country": "GB",
    "wof:name": "NW4 2AT",
    "wof:placetype": "postalcode"
  },
  "geometry": {"coordinates":[-0.217848,51.587129],"type":"Point"}
}
