{
  "type": "Feature",
  "properties": {
    "date:inception_lower":"1980-01-01",
    "date:inception_upper":"1980-01-31",
    "iso:country":"GB",
    "wof:name":"SA73 2HT",
    "wof:placetype":"postalcode"
},
  "geometry": {"coordinates":[-5.031646,51.71296],"type":"Point"}
}