{
  "type": "Feature",
  "properties": {
    "iso:country":"GB",
    "wof:name":"SA73 2HT",
    "wof:placetype":"postalcode"
},
  "geometry": {"coordinates":[-5.03162298071724,51.71292858804519],"type":"Point"}
}