{
  "type": "Feature",
  "properties": {
    "date:inception_lower": "2024-09-01",
    "date:inception_upper": "2024-09-01",
    "iso:country": "GB",
    "wof:name": "HU17 0WT",
    "wof:placetype": "postalcode"
  },
  "geometry": {"coordinates":[-0.422543,53.835121],"type":"Point"}
}
