{
  "type": "Feature",
  "properties": {
    "iso:country": "GB",
    "wof:name": "SK6 3BP",
    "wof:placetype": "postalcode"
  },
  "geometry": {"coordinates":[-2.092079,53.413693],"type":"Point"}
}
