{
  "type": "Feature",
  "properties": {
    "iso:country":"GB",
    "wof:name":"SK6 3BP",
    "wof:placetype":"postalcode"
},
  "geometry": {"coordinates":[-2.09207898303625,53.41369345129397],"type":"Point"}
}