{
  "type": "Feature",
  "properties": {
    "iso:country": "GB",
    "wof:name": "YO32 9NB",
    "wof:placetype": "postalcode"
  },
  "geometry": {"coordinates":[-1.059486,53.985047],"type":"Point"}
}
