{
  "type": "Feature",
  "properties": {
    "iso:country":"GB",
    "wof:name":"YO32 9NB",
    "wof:placetype":"postalcode"
},
  "geometry": {"coordinates":[-1.05948562099907,53.98504700881234],"type":"Point"}
}