{
  "type": "Feature",
  "properties": {
    "iso:country": "GB",
    "wof:name": "PO30 5BP",
    "wof:placetype": "postalcode"
  },
  "geometry": {"coordinates":[-1.294994,50.712154],"type":"Point"}
}
