{
  "type": "Feature",
  "properties": {
    "iso:country":"GB",
    "wof:name":"PO30 5BP",
    "wof:placetype":"postalcode"
},
  "geometry": {"coordinates":[-1.29499356709292,50.71215375952129],"type":"Point"}
}