{
  "type": "Feature",
  "properties": {
    "date:inception_lower": "2015-09-01",
    "date:inception_upper": "2015-09-01",
    "iso:country": "GB",
    "wof:name": "PO30 5BP",
    "wof:placetype": "postalcode"
  },
  "geometry": {"coordinates":[-1.294994,50.712154],"type":"Point"}
}
