{
  "type": "Feature",
  "properties": {
    "iso:country":"GB",
    "wof:name":"GL4 6SH",
    "wof:placetype":"postalcode"
},
  "geometry": {"coordinates":[-2.23153979857066,51.84461289860647],"type":"Point"}
}