{
  "type": "Feature",
  "properties": {
    "iso:country": "GB",
    "wof:name": "GL4 6SH",
    "wof:placetype": "postalcode"
  },
  "geometry": {"coordinates":[-2.23154,51.844613],"type":"Point"}
}
