{
  "type": "Feature",
  "properties": {
    "iso:country": "GB",
    "wof:name": "TN11 9BN",
    "wof:placetype": "postalcode"
  },
  "geometry": {"coordinates":[0.258277,51.207196],"type":"Point"}
}
