{
  "type": "Feature",
  "properties": {
    "iso:country":"GB",
    "wof:name":"SM1 2LN",
    "wof:placetype":"postalcode"
},
  "geometry": {"coordinates":[-0.21359319029146,51.36544129879506],"type":"Point"}
}