{
  "type": "Feature",
  "properties": {
    "iso:country": "GB",
    "wof:name": "NR31 6DD",
    "wof:placetype": "postalcode"
  },
  "geometry": {"coordinates":[1.725277,52.564528],"type":"Point"}
}
