{
  "type": "Feature",
  "properties": {
    "iso:country":"GB",
    "wof:name":"HR4 0DF",
    "wof:placetype":"postalcode"
},
  "geometry": {"coordinates":[-2.73185896403162,52.05964940063068],"type":"Point"}
}