{
  "type": "Feature",
  "properties": {
    "date:inception_lower": "1994-12-01",
    "date:inception_upper": "1994-12-01",
    "iso:country": "GB",
    "wof:name": "HR4 0DF",
    "wof:placetype": "postalcode"
  },
  "geometry": {"coordinates":[-2.731859,52.059649],"type":"Point"}
}
