{
  "type": "Feature",
  "properties": {
    "iso:country":"GB",
    "wof:name":"WF6 1JF",
    "wof:placetype":"postalcode"
},
  "geometry": {"coordinates":[-1.41360495350205,53.68935133640655],"type":"Point"}
}