{
  "type": "Feature",
  "properties": {
    "date:inception_lower": "1980-01-01",
    "date:inception_upper": "1980-01-01",
    "iso:country": "GB",
    "wof:name": "WF6 1JF",
    "wof:placetype": "postalcode"
  },
  "geometry": {"coordinates":[-1.413605,53.689351],"type":"Point"}
}
