{
  "type": "Feature",
  "properties": {
    "date:inception_lower": "1980-01-01",
    "date:inception_upper": "1980-01-01",
    "iso:country": "GB",
    "wof:name": "N18 1SX",
    "wof:placetype": "postalcode"
  },
  "geometry": {"coordinates":[-0.075268,51.60939],"type":"Point"}
}
