{
  "type": "Feature",
  "properties": {
    "date:inception_lower":"1995-07-01",
    "date:inception_upper":"1995-07-31",
    "iso:country":"GB",
    "wof:name":"L75 1AE",
    "wof:placetype":"postalcode"
},
  "geometry": {"coordinates":[-2.991574,53.404424],"type":"Point"}
}