{
  "type": "Feature",
  "properties": {
    "iso:country":"GB",
    "wof:name":"SW20 9DN",
    "wof:placetype":"postalcode"
},
  "geometry": {"coordinates":[-0.2310510836295,51.4052196195317],"type":"Point"}
}