{
  "type": "Feature",
  "properties": {
    "iso:country": "GB",
    "wof:name": "HR8 2TG",
    "wof:placetype": "postalcode"
  },
  "geometry": {"coordinates":[-2.51534,52.086725],"type":"Point"}
}
