{
  "type": "Feature",
  "properties": {
    "date:inception_lower": "1980-01-01",
    "date:inception_upper": "1980-01-01",
    "iso:country": "GB",
    "wof:name": "HR8 2TG",
    "wof:placetype": "postalcode"
  },
  "geometry": {"coordinates":[-2.51534,52.086725],"type":"Point"}
}
