{
  "type": "Feature",
  "properties": {
    "iso:country":"GB",
    "wof:name":"HR8 2TG",
    "wof:placetype":"postalcode"
},
  "geometry": {"coordinates":[-2.51533968504596,52.08672460789204],"type":"Point"}
}