{
  "type": "Feature",
  "properties": {
    "iso:country":"GB",
    "wof:name":"DE6 1FB",
    "wof:placetype":"postalcode"
},
  "geometry": {"coordinates":[-1.73393151740282,53.0186874336108],"type":"Point"}
}