{
  "type": "Feature",
  "properties": {
    "date:inception_lower": "2006-11-01",
    "date:inception_upper": "2006-11-01",
    "iso:country": "GB",
    "wof:name": "FK5 4GE",
    "wof:placetype": "postalcode"
  },
  "geometry": {"coordinates":[-3.83559,56.02243],"type":"Point"}
}
