{
  "type": "Feature",
  "properties": {
    "date:inception_lower": "1980-01-01",
    "date:inception_upper": "1980-01-01",
    "iso:country": "GB",
    "wof:name": "PL19 8RH",
    "wof:placetype": "postalcode"
  },
  "geometry": {"coordinates":[-4.192554,50.570689],"type":"Point"}
}
