{
  "type": "Feature",
  "properties": {
    "iso:country":"GB",
    "wof:name":"PL19 8RH",
    "wof:placetype":"postalcode"
},
  "geometry": {"coordinates":[-4.19252587183742,50.57069917786345],"type":"Point"}
}