{
  "type": "Feature",
  "properties": {
    "iso:country":"GB",
    "wof:name":"UB2 4HE",
    "wof:placetype":"postalcode"
},
  "geometry": {"coordinates":[-0.37082793933828,51.49589262077176],"type":"Point"}
}