{
  "type": "Feature",
  "properties": {
    "iso:country": "GB",
    "wof:name": "CA2 6DE",
    "wof:placetype": "postalcode"
  },
  "geometry": {"coordinates":[-2.953791,54.884901],"type":"Point"}
}
