{
  "type": "Feature",
  "properties": {
    "iso:country":"GB",
    "wof:name":"CA2 6DE",
    "wof:placetype":"postalcode"
},
  "geometry": {"coordinates":[-2.9528726956438,54.88495268563272],"type":"Point"}
}