{
  "type": "Feature",
  "properties": {
    "iso:country":"GB",
    "wof:name":"IP13 7RT",
    "wof:placetype":"postalcode"
},
  "geometry": {"coordinates":[1.26493501145971,52.22032068344861],"type":"Point"}
}