{
  "type": "Feature",
  "properties": {
    "iso:country": "GB",
    "wof:name": "IP13 7RT",
    "wof:placetype": "postalcode"
  },
  "geometry": {"coordinates":[1.264935,52.220321],"type":"Point"}
}
