{
  "type": "Feature",
  "properties": {
    "iso:country":"GB",
    "wof:name":"NP10 8RA",
    "wof:placetype":"postalcode"
},
  "geometry": {"coordinates":[-3.06039839805072,51.57923401907788],"type":"Point"}
}