{
  "type": "Feature",
  "properties": {
    "iso:country": "GB",
    "wof:name": "GL4 0AE",
    "wof:placetype": "postalcode"
  },
  "geometry": {"coordinates":[-2.244734,51.836485],"type":"Point"}
}
