{
  "type": "Feature",
  "properties": {
    "iso:country":"GB",
    "wof:name":"GL4 0AE",
    "wof:placetype":"postalcode"
},
  "geometry": {"coordinates":[-2.2447342008205,51.83648530603776],"type":"Point"}
}