{
  "type": "Feature",
  "properties": {
    "date:inception_lower":"1980-01-01",
    "date:inception_upper":"1980-01-31",
    "iso:country":"GB",
    "wof:name":"GL4 0AE",
    "wof:placetype":"postalcode"
},
  "geometry": {"coordinates":[-2.244734,51.836485],"type":"Point"}
}