{
  "type": "Feature",
  "properties": {
    "iso:country":"GB",
    "wof:name":"L32 0SN",
    "wof:placetype":"postalcode"
},
  "geometry": {"coordinates":[-2.90115889139606,53.4855994485524],"type":"Point"}
}