{
  "type": "Feature",
  "properties": {
    "iso:country":"GB",
    "wof:name":"CF14 6AH",
    "wof:placetype":"postalcode"
},
  "geometry": {"coordinates":[-3.20824605060725,51.51966345985603],"type":"Point"}
}