{
  "type": "Feature",
  "properties": {
    "iso:country":"GB",
    "wof:name":"E10 5ET",
    "wof:placetype":"postalcode"
},
  "geometry": {"coordinates":[-0.01555518368436,51.56672141668098],"type":"Point"}
}