{
  "type": "Feature",
  "properties": {
    "iso:country": "GB",
    "wof:name": "LE9 6XL",
    "wof:placetype": "postalcode"
  },
  "geometry": {"coordinates":[-1.218968,52.522454],"type":"Point"}
}
