{
  "type": "Feature",
  "properties": {
    "date:inception_lower":"1991-01-01",
    "date:inception_upper":"1991-01-31",
    "iso:country":"GB",
    "wof:name":"LE9 6XL",
    "wof:placetype":"postalcode"
},
  "geometry": {"coordinates":[-1.218968,52.522454],"type":"Point"}
}