{
  "type": "Feature",
  "properties": {
    "iso:country":"GB",
    "wof:name":"LE9 6XL",
    "wof:placetype":"postalcode"
},
  "geometry": {"coordinates":[-1.21896826537748,52.52245359377592],"type":"Point"}
}