{
  "type": "Feature",
  "properties": {
    "iso:country":"GB",
    "wof:name":"PA16 0AU",
    "wof:placetype":"postalcode"
},
  "geometry": {"coordinates":[-4.8718148206195,55.90822436923259],"type":"Point"}
}