{
  "type": "Feature",
  "properties": {
    "iso:country": "GB",
    "wof:name": "NG5 6DU",
    "wof:placetype": "postalcode"
  },
  "geometry": {"coordinates":[-1.14806,52.995727],"type":"Point"}
}
