{
  "type": "Feature",
  "properties": {
    "iso:country":"GB",
    "wof:name":"NG5 6DU",
    "wof:placetype":"postalcode"
},
  "geometry": {"coordinates":[-1.14806005300529,52.99572687346583],"type":"Point"}
}