{
  "type": "Feature",
  "properties": {
    "iso:country":"GB",
    "wof:name":"WS3 1AS",
    "wof:placetype":"postalcode"
},
  "geometry": {"coordinates":[-1.98678567977582,52.60467790546787],"type":"Point"}
}