{
  "type": "Feature",
  "properties": {
    "iso:country": "GB",
    "wof:name": "TN31 7SR",
    "wof:placetype": "postalcode"
  },
  "geometry": {"coordinates":[0.789112,50.93701],"type":"Point"}
}
