{
  "type": "Feature",
  "properties": {
    "date:inception_lower":"2008-07-01",
    "date:inception_upper":"2008-07-31",
    "iso:country":"GB",
    "wof:name":"TN31 7SR",
    "wof:placetype":"postalcode"
},
  "geometry": {"coordinates":[0.789112,50.93701],"type":"Point"}
}