{
  "type": "Feature",
  "properties": {
    "iso:country": "GB",
    "wof:name": "SN5 6DL",
    "wof:placetype": "postalcode"
  },
  "geometry": {"coordinates":[-1.839502,51.555549],"type":"Point"}
}
