{
  "type": "Feature",
  "properties": {
    "iso:country":"GB",
    "wof:name":"SN5 6DL",
    "wof:placetype":"postalcode"
},
  "geometry": {"coordinates":[-1.83950247160615,51.55554937099264],"type":"Point"}
}