{
  "type": "Feature",
  "properties": {
    "iso:country":"GB",
    "wof:name":"DE6 5AF",
    "wof:placetype":"postalcode"
},
  "geometry": {"coordinates":[-1.75688643658129,52.91536928554788],"type":"Point"}
}