{
  "type": "Feature",
  "properties": {
    "date:inception_lower":"1998-12-01",
    "date:inception_upper":"1998-12-31",
    "iso:country":"GB",
    "wof:name":"DE6 5AF",
    "wof:placetype":"postalcode"
},
  "geometry": {"coordinates":[-1.756883,52.915387],"type":"Point"}
}