{
  "type": "Feature",
  "properties": {
    "iso:country":"GB",
    "wof:name":"BB18 5EW",
    "wof:placetype":"postalcode"
},
  "geometry": {"coordinates":[-2.18936525717065,53.92114040331502],"type":"Point"}
}