{
  "type": "Feature",
  "properties": {
    "iso:country":"GB",
    "wof:name":"LE11 2BH",
    "wof:placetype":"postalcode"
},
  "geometry": {"coordinates":[-1.21126450994656,52.76299110307161],"type":"Point"}
}