{
  "type": "Feature",
  "properties": {
    "iso:country": "GB",
    "wof:name": "S40 3HF",
    "wof:placetype": "postalcode"
  },
  "geometry": {"coordinates":[-1.456828,53.222544],"type":"Point"}
}
