{
  "type": "Feature",
  "properties": {
    "iso:country":"GB",
    "wof:name":"S40 3HF",
    "wof:placetype":"postalcode"
},
  "geometry": {"coordinates":[-1.45682819825111,53.22254390170838],"type":"Point"}
}