{
  "type": "Feature",
  "properties": {
    "iso:country":"GB",
    "wof:name":"RM3 0RS",
    "wof:placetype":"postalcode"
},
  "geometry": {"coordinates":[0.23274827061275,51.59707926958896],"type":"Point"}
}