{
  "type": "Feature",
  "properties": {
    "date:inception_lower": "1980-01-01",
    "date:inception_upper": "1980-01-01",
    "iso:country": "GB",
    "wof:name": "RM3 0RS",
    "wof:placetype": "postalcode"
  },
  "geometry": {"coordinates":[0.233212,51.597181],"type":"Point"}
}
