{
  "type": "Feature",
  "properties": {
    "iso:country":"GB",
    "wof:name":"NE28 9LQ",
    "wof:placetype":"postalcode"
},
  "geometry": {"coordinates":[-1.5384644005833,55.00352380404635],"type":"Point"}
}