{
  "type": "Feature",
  "properties": {
    "date:inception_lower": "1980-01-01",
    "date:inception_upper": "1980-01-01",
    "iso:country": "GB",
    "wof:name": "NE28 9LQ",
    "wof:placetype": "postalcode"
  },
  "geometry": {"coordinates":[-1.538464,55.003524],"type":"Point"}
}
