{
  "type": "Feature",
  "properties": {
    "date:inception_lower": "2009-03-01",
    "date:inception_upper": "2009-03-01",
    "iso:country": "GB",
    "wof:name": "BS23 2SE",
    "wof:placetype": "postalcode"
  },
  "geometry": {"coordinates":[-2.96163,51.351343],"type":"Point"}
}
