{
  "type": "Feature",
  "properties": {
    "date:inception_lower": "1980-01-01",
    "date:inception_upper": "1980-01-01",
    "iso:country": "GB",
    "wof:name": "DY3 3UG",
    "wof:placetype": "postalcode"
  },
  "geometry": {"coordinates":[-2.125021,52.536487],"type":"Point"}
}
