{
  "type": "Feature",
  "properties": {
    "iso:country":"GB",
    "wof:name":"DY3 3UG",
    "wof:placetype":"postalcode"
},
  "geometry": {"coordinates":[-2.1250212829926,52.53648746624314],"type":"Point"}
}