{
  "type": "Feature",
  "properties": {
    "iso:country":"GB",
    "wof:name":"SE8 5JZ",
    "wof:placetype":"postalcode"
},
  "geometry": {"coordinates":[-0.03765701513826,51.48231079213509],"type":"Point"}
}