{
  "type": "Feature",
  "properties": {
    "iso:country":"GB",
    "wof:name":"L12 0JE",
    "wof:placetype":"postalcode"
},
  "geometry": {"coordinates":[-2.87750186984487,53.44927217809744],"type":"Point"}
}