{
  "type": "Feature",
  "properties": {
    "date:inception_lower": "1996-06-01",
    "date:inception_upper": "1996-06-01",
    "iso:country": "GB",
    "wof:name": "AB41 9ED",
    "wof:placetype": "postalcode"
  },
  "geometry": {"coordinates":[-2.086404,57.368301],"type":"Point"}
}
