{
  "type": "Feature",
  "properties": {
    "date:inception_lower": "2017-06-01",
    "date:inception_upper": "2017-06-01",
    "iso:country": "GB",
    "wof:name": "PE31 7UU",
    "wof:placetype": "postalcode"
  },
  "geometry": {"coordinates":[0.488638,52.910174],"type":"Point"}
}
