{
  "type": "Feature",
  "properties": {
    "date:inception_lower": "2018-03-01",
    "date:inception_upper": "2018-03-01",
    "iso:country": "GB",
    "wof:name": "TR13 0JF",
    "wof:placetype": "postalcode"
  },
  "geometry": {"coordinates":[-5.244773,50.15455],"type":"Point"}
}
