{
  "type": "Feature",
  "properties": {
    "iso:country":"GB",
    "wof:name":"TR13 0JF",
    "wof:placetype":"postalcode"
},
  "geometry": {"coordinates":[-5.24490342064411,50.1545372720882],"type":"Point"}
}