{
  "type": "Feature",
  "properties": {
    "iso:country": "GB",
    "wof:name": "TR13 0JF",
    "wof:placetype": "postalcode"
  },
  "geometry": {"coordinates":[-5.244966,50.154499],"type":"Point"}
}
