{
  "type": "Feature",
  "properties": {
    "iso:country":"GB",
    "wof:name":"CV37 9DR",
    "wof:placetype":"postalcode"
},
  "geometry": {"coordinates":[-1.72930010675649,52.19567071239894],"type":"Point"}
}