{
  "type": "Feature",
  "properties": {
    "iso:country": "GB",
    "wof:name": "CV37 9DR",
    "wof:placetype": "postalcode"
  },
  "geometry": {"coordinates":[-1.729686,52.195703],"type":"Point"}
}
