{
  "type": "Feature",
  "properties": {
    "iso:country":"GB",
    "wof:name":"BA12 8AJ",
    "wof:placetype":"postalcode"
},
  "geometry": {"coordinates":[-2.19697093159457,51.17906530125045],"type":"Point"}
}