{
  "type": "Feature",
  "properties": {
    "iso:country":"GB",
    "wof:name":"CH42 8ND",
    "wof:placetype":"postalcode"
},
  "geometry": {"coordinates":[-3.03753323960326,53.36944356150777],"type":"Point"}
}