{
  "type": "Feature",
  "properties": {
    "iso:country":"GB",
    "wof:name":"YO42 2LG",
    "wof:placetype":"postalcode"
},
  "geometry": {"coordinates":[-0.76831905883133,53.93653060540051],"type":"Point"}
}