{
  "type": "Feature",
  "properties": {
    "iso:country":"GB",
    "wof:name":"NN15 6DJ",
    "wof:placetype":"postalcode"
},
  "geometry": {"coordinates":[-0.7282583376316,52.39090156504874],"type":"Point"}
}