{
  "type": "Feature",
  "properties": {
    "date:inception_lower":"1992-10-01",
    "date:inception_upper":"1992-10-31",
    "iso:country":"GB",
    "wof:name":"FK13 6RR",
    "wof:placetype":"postalcode"
},
  "geometry": {"coordinates":[-3.728522,56.158859],"type":"Point"}
}