{
  "type": "Feature",
  "properties": {
    "iso:country":"GB",
    "wof:name":"TW7 6RG",
    "wof:placetype":"postalcode"
},
  "geometry": {"coordinates":[-0.32351476106721,51.46927392309392],"type":"Point"}
}