{
  "type": "Feature",
  "properties": {
    "date:inception_lower": "2021-12-01",
    "date:inception_upper": "2021-12-01",
    "iso:country": "GB",
    "wof:name": "DN11 8SW",
    "wof:placetype": "postalcode"
  },
  "geometry": {"coordinates":[-1.066256,53.425229],"type":"Point"}
}
