{
  "type": "Feature",
  "properties": {
    "iso:country":"GB",
    "wof:name":"LL34 6NY",
    "wof:placetype":"postalcode"
},
  "geometry": {"coordinates":[-3.93729704607212,53.2662488745937],"type":"Point"}
}