{
  "type": "Feature",
  "properties": {
    "iso:country":"GB",
    "wof:name":"FK7 8EH",
    "wof:placetype":"postalcode"
},
  "geometry": {"coordinates":[-3.91597325025193,56.08413106754892],"type":"Point"}
}