{
  "type": "Feature",
  "properties": {
    "iso:country":"GB",
    "wof:name":"PR1 6QQ",
    "wof:placetype":"postalcode"
},
  "geometry": {"coordinates":[-2.68794651236458,53.766520812265],"type":"Point"}
}