{
  "type": "Feature",
  "properties": {
    "iso:country":"GB",
    "wof:name":"KA20 3LA",
    "wof:placetype":"postalcode"
},
  "geometry": {"coordinates":[-4.75123639271195,55.63294603089625],"type":"Point"}
}