{
  "type": "Feature",
  "properties": {
    "date:inception_lower": "1980-01-01",
    "date:inception_upper": "1980-01-01",
    "iso:country": "GB",
    "wof:name": "SS5 4LA",
    "wof:placetype": "postalcode"
  },
  "geometry": {"coordinates":[0.675114,51.592909],"type":"Point"}
}
