{
  "type": "Feature",
  "properties": {
    "iso:country": "GB",
    "wof:name": "SS5 4LA",
    "wof:placetype": "postalcode"
  },
  "geometry": {"coordinates":[0.675114,51.592909],"type":"Point"}
}
