{
  "type": "Feature",
  "properties": {
    "iso:country":"GB",
    "wof:name":"HU12 0PD",
    "wof:placetype":"postalcode"
},
  "geometry": {"coordinates":[-0.00771665794259,53.68554489403917],"type":"Point"}
}