{
  "type": "Feature",
  "properties": {
    "iso:country":"GB",
    "wof:name":"NN7 2DD",
    "wof:placetype":"postalcode"
},
  "geometry": {"coordinates":[-0.82437929157879,52.18376113646013],"type":"Point"}
}