{
  "type": "Feature",
  "properties": {
    "date:inception_lower":"1990-02-01",
    "date:inception_upper":"1990-02-28",
    "iso:country":"GB",
    "wof:name":"HA0 2PR",
    "wof:placetype":"postalcode"
},
  "geometry": {"coordinates":[-0.323149,51.5593],"type":"Point"}
}