{
  "type": "Feature",
  "properties": {
    "iso:country":"GB",
    "wof:name":"HA0 2PR",
    "wof:placetype":"postalcode"
},
  "geometry": {"coordinates":[-0.3231493843895,51.55929966860879],"type":"Point"}
}