{
  "type": "Feature",
  "properties": {
    "iso:country": "GB",
    "wof:name": "HA0 2PR",
    "wof:placetype": "postalcode"
  },
  "geometry": {"coordinates":[-0.323149,51.5593],"type":"Point"}
}
