{
  "type": "Feature",
  "properties": {
    "date:inception_lower":"1983-01-01",
    "date:inception_upper":"1983-01-31",
    "iso:country":"GB",
    "wof:name":"SL2 1TW",
    "wof:placetype":"postalcode"
},
  "geometry": {"coordinates":[-0.629745,51.529093],"type":"Point"}
}