{
  "type": "Feature",
  "properties": {
    "iso:country":"GB",
    "wof:name":"SL2 1TW",
    "wof:placetype":"postalcode"
},
  "geometry": {"coordinates":[-0.6297447159652,51.52909265116243],"type":"Point"}
}