{
  "type": "Feature",
  "properties": {
    "iso:country": "GB",
    "wof:name": "NG19 8RF",
    "wof:placetype": "postalcode"
  },
  "geometry": {"coordinates":[-1.194688,53.176125],"type":"Point"}
}
