{
  "type": "Feature",
  "properties": {
    "iso:country":"GB",
    "wof:name":"NG19 8RF",
    "wof:placetype":"postalcode"
},
  "geometry": {"coordinates":[-1.19468812691835,53.17612495916548],"type":"Point"}
}