{
  "type": "Feature",
  "properties": {
    "iso:country":"GB",
    "wof:name":"CT16 3PT",
    "wof:placetype":"postalcode"
},
  "geometry": {"coordinates":[1.30289538528631,51.15357072290912],"type":"Point"}
}