{
  "type": "Feature",
  "properties": {
    "iso:country": "GB",
    "wof:name": "CT16 3PT",
    "wof:placetype": "postalcode"
  },
  "geometry": {"coordinates":[1.302927,51.153578],"type":"Point"}
}
