{
  "type": "Feature",
  "properties": {
    "iso:country": "GB",
    "wof:name": "PE22 8AS",
    "wof:placetype": "postalcode"
  },
  "geometry": {"coordinates":[-0.007178,53.097841],"type":"Point"}
}
