{
  "type": "Feature",
  "properties": {
    "date:inception_lower": "2008-01-01",
    "date:inception_upper": "2008-01-01",
    "iso:country": "GB",
    "wof:name": "PE22 8AS",
    "wof:placetype": "postalcode"
  },
  "geometry": {"coordinates":[-0.007178,53.097841],"type":"Point"}
}
