{
  "type": "Feature",
  "properties": {
    "iso:country":"GB",
    "wof:name":"PE22 8AS",
    "wof:placetype":"postalcode"
},
  "geometry": {"coordinates":[-0.0071828062377,53.0978148542717],"type":"Point"}
}