{
  "type": "Feature",
  "properties": {
    "iso:country":"GB",
    "wof:name":"IP16 4NE",
    "wof:placetype":"postalcode"
},
  "geometry": {"coordinates":[1.61406500762741,52.18086570854703],"type":"Point"}
}