{
  "type": "Feature",
  "properties": {
    "iso:country":"GB",
    "wof:name":"HP15 6TN",
    "wof:placetype":"postalcode"
},
  "geometry": {"coordinates":[-0.69066371437207,51.66530440755056],"type":"Point"}
}