{
  "type": "Feature",
  "properties": {
    "iso:country": "GB",
    "wof:name": "HP15 6TN",
    "wof:placetype": "postalcode"
  },
  "geometry": {"coordinates":[-0.690664,51.665304],"type":"Point"}
}
