{
  "type": "Feature",
  "properties": {
    "date:inception_lower": "1980-01-01",
    "date:inception_upper": "1980-01-01",
    "iso:country": "GB",
    "wof:name": "NG31 6LR",
    "wof:placetype": "postalcode"
  },
  "geometry": {"coordinates":[-0.643592,52.912759],"type":"Point"}
}
