{
  "type": "Feature",
  "properties": {
    "iso:country": "GB",
    "wof:name": "NG31 6LR",
    "wof:placetype": "postalcode"
  },
  "geometry": {"coordinates":[-0.643592,52.912759],"type":"Point"}
}
