{
  "type": "Feature",
  "properties": {
    "iso:country":"GB",
    "wof:name":"TW13 5QX",
    "wof:placetype":"postalcode"
},
  "geometry": {"coordinates":[-0.3725462018411,51.44074858552106],"type":"Point"}
}