{
  "type": "Feature",
  "properties": {
    "iso:country": "GB",
    "wof:name": "W1T 2QR",
    "wof:placetype": "postalcode"
  },
  "geometry": {"coordinates":[-0.135556,51.519591],"type":"Point"}
}
