{
  "type": "Feature",
  "properties": {
    "iso:country":"GB",
    "wof:name":"W1T 2QR",
    "wof:placetype":"postalcode"
},
  "geometry": {"coordinates":[-0.13555574256507,51.51959065463443],"type":"Point"}
}