{
  "type": "Feature",
  "properties": {
    "date:inception_lower": "2019-10-01",
    "date:inception_upper": "2019-10-01",
    "iso:country": "GB",
    "wof:name": "BH11 9FU",
    "wof:placetype": "postalcode"
  },
  "geometry": {"coordinates":[-1.940181,50.771461],"type":"Point"}
}
