{
  "type": "Feature",
  "properties": {
    "iso:country":"GB",
    "wof:name":"WV4 4NT",
    "wof:placetype":"postalcode"
},
  "geometry": {"coordinates":[-2.1774189289171,52.56595210653472],"type":"Point"}
}