{
  "type": "Feature",
  "properties": {
    "iso:country": "GB",
    "wof:name": "B35 6JA",
    "wof:placetype": "postalcode"
  },
  "geometry": {"coordinates":[-1.784821,52.525661],"type":"Point"}
}
