{
  "type": "Feature",
  "properties": {
    "iso:country":"GB",
    "wof:name":"B35 6JA",
    "wof:placetype":"postalcode"
},
  "geometry": {"coordinates":[-1.78482058373037,52.52566069983985],"type":"Point"}
}