{
  "type": "Feature",
  "properties": {
    "date:inception_lower": "1980-01-01",
    "date:inception_upper": "1980-01-01",
    "iso:country": "GB",
    "wof:name": "L35 2UU",
    "wof:placetype": "postalcode"
  },
  "geometry": {"coordinates":[-2.798169,53.416651],"type":"Point"}
}
