{
  "type": "Feature",
  "properties": {
    "iso:country":"GB",
    "wof:name":"NG5 1DE",
    "wof:placetype":"postalcode"
},
  "geometry": {"coordinates":[-1.16176586919055,52.97810605101986],"type":"Point"}
}