{
  "type": "Feature",
  "properties": {
    "date:inception_lower": "1980-01-01",
    "date:inception_upper": "1980-01-01",
    "iso:country": "GB",
    "wof:name": "B71 1PP",
    "wof:placetype": "postalcode"
  },
  "geometry": {"coordinates":[-1.991009,52.528328],"type":"Point"}
}
