{
  "type": "Feature",
  "properties": {
    "date:inception_lower":"1990-02-01",
    "date:inception_upper":"1990-02-28",
    "iso:country":"GB",
    "wof:name":"DL7 8YU",
    "wof:placetype":"postalcode"
},
  "geometry": {"coordinates":[-1.435827,54.328722],"type":"Point"}
}