{
  "type": "Feature",
  "properties": {
    "iso:country":"GB",
    "wof:name":"DL7 8YU",
    "wof:placetype":"postalcode"
},
  "geometry": {"coordinates":[-1.43582703032898,54.3287222409104],"type":"Point"}
}