{
  "type": "Feature",
  "properties": {
    "iso:country": "GB",
    "wof:name": "DL7 8YU",
    "wof:placetype": "postalcode"
  },
  "geometry": {"coordinates":[-1.435827,54.328722],"type":"Point"}
}
