{
  "type": "Feature",
  "properties": {
    "iso:country": "GB",
    "wof:name": "PH7 3GZ",
    "wof:placetype": "postalcode"
  },
  "geometry": {"coordinates":[-3.837074,56.37285],"type":"Point"}
}
