{
  "type": "Feature",
  "properties": {
    "iso:country":"GB",
    "wof:name":"OL2 5TA",
    "wof:placetype":"postalcode"
},
  "geometry": {"coordinates":[-2.13076207001881,53.57129625193328],"type":"Point"}
}