{
  "type": "Feature",
  "properties": {
    "iso:country":"GB",
    "wof:name":"NG2 1AB",
    "wof:placetype":"postalcode"
},
  "geometry": {"coordinates":[-1.15360498063564,52.94680977193273],"type":"Point"}
}