{
  "type": "Feature",
  "properties": {
    "iso:country": "GB",
    "wof:name": "NG2 1AB",
    "wof:placetype": "postalcode"
  },
  "geometry": {"coordinates":[-1.153605,52.94681],"type":"Point"}
}
