{
  "type": "Feature",
  "properties": {
    "iso:country":"GB",
    "wof:name":"OL13 0EP",
    "wof:placetype":"postalcode"
},
  "geometry": {"coordinates":[-2.21479200674497,53.69238991048147],"type":"Point"}
}