{
  "type": "Feature",
  "properties": {
    "iso:country":"GB",
    "wof:name":"KA12 0JS",
    "wof:placetype":"postalcode"
},
  "geometry": {"coordinates":[-4.64835494326883,55.61534655467325],"type":"Point"}
}