{
  "type": "Feature",
  "properties": {
    "date:inception_lower":"1980-01-01",
    "date:inception_upper":"1980-01-31",
    "iso:country":"GB",
    "wof:name":"KA12 0JS",
    "wof:placetype":"postalcode"
},
  "geometry": {"coordinates":[-4.648355,55.615347],"type":"Point"}
}