{
  "type": "Feature",
  "properties": {
    "iso:country":"GB",
    "wof:name":"NR5 9DT",
    "wof:placetype":"postalcode"
},
  "geometry": {"coordinates":[1.22369443302186,52.64095661764861],"type":"Point"}
}