{
  "type": "Feature",
  "properties": {
    "iso:country":"GB",
    "wof:name":"AL10 9QZ",
    "wof:placetype":"postalcode"
},
  "geometry": {"coordinates":[-0.2399997908082,51.7644347017011],"type":"Point"}
}