{
  "type": "Feature",
  "properties": {
    "iso:country":"GB",
    "wof:name":"RH8 0DX",
    "wof:placetype":"postalcode"
},
  "geometry": {"coordinates":[0.01452987742524,51.2569363353747],"type":"Point"}
}