{
  "type": "Feature",
  "properties": {
    "iso:country":"GB",
    "wof:name":"NN5 6YD",
    "wof:placetype":"postalcode"
},
  "geometry": {"coordinates":[-0.96241928330735,52.25254895669959],"type":"Point"}
}