{
  "type": "Feature",
  "properties": {
    "iso:country": "GB",
    "wof:name": "KT1 4BY",
    "wof:placetype": "postalcode"
  },
  "geometry": {"coordinates":[-0.310858,51.411568],"type":"Point"}
}
