{
  "type": "Feature",
  "properties": {
    "iso:country":"GB",
    "wof:name":"KT1 4BY",
    "wof:placetype":"postalcode"
},
  "geometry": {"coordinates":[-0.31085838734868,51.41156775116141],"type":"Point"}
}