{
  "type": "Feature",
  "properties": {
    "iso:country":"GB",
    "wof:name":"TQ13 8PL",
    "wof:placetype":"postalcode"
},
  "geometry": {"coordinates":[-3.77508851096203,50.66030242073361],"type":"Point"}
}