{
  "type": "Feature",
  "properties": {
    "iso:country":"GB",
    "wof:name":"SM4 4JN",
    "wof:placetype":"postalcode"
},
  "geometry": {"coordinates":[-0.2193860761355,51.39275010532097],"type":"Point"}
}