{
  "type": "Feature",
  "properties": {
    "iso:country": "GB",
    "wof:name": "KT13 8BP",
    "wof:placetype": "postalcode"
  },
  "geometry": {"coordinates":[-0.457381,51.379696],"type":"Point"}
}
