{
  "type": "Feature",
  "properties": {
    "iso:country":"GB",
    "wof:name":"KT13 8BP",
    "wof:placetype":"postalcode"
},
  "geometry": {"coordinates":[-0.45738055239623,51.37969568233902],"type":"Point"}
}