{
  "type": "Feature",
  "properties": {
    "iso:country":"GB",
    "wof:name":"TW16 6SW",
    "wof:placetype":"postalcode"
},
  "geometry": {"coordinates":[-0.41522143824303,51.41834884038376],"type":"Point"}
}