{
  "type": "Feature",
  "properties": {
    "iso:country": "GB",
    "wof:name": "DN6 7NS",
    "wof:placetype": "postalcode"
  },
  "geometry": {"coordinates":[-1.204728,53.566767],"type":"Point"}
}
