{
  "type": "Feature",
  "properties": {
    "iso:country": "GB",
    "wof:name": "GL7 3NX",
    "wof:placetype": "postalcode"
  },
  "geometry": {"coordinates":[-1.708505,51.729359],"type":"Point"}
}
