{
  "type": "Feature",
  "properties": {
    "iso:country":"GB",
    "wof:name":"GL7 3NX",
    "wof:placetype":"postalcode"
},
  "geometry": {"coordinates":[-1.70850552330915,51.72935940737167],"type":"Point"}
}