{
  "type": "Feature",
  "properties": {
    "iso:country": "GB",
    "wof:name": "BH8 9JZ",
    "wof:placetype": "postalcode"
  },
  "geometry": {"coordinates":[-1.837057,50.748459],"type":"Point"}
}
