{
  "type": "Feature",
  "properties": {
    "iso:country": "GB",
    "wof:name": "BL2 4EW",
    "wof:placetype": "postalcode"
  },
  "geometry": {"coordinates":[-2.377894,53.599704],"type":"Point"}
}
