{
  "type": "Feature",
  "properties": {
    "iso:country":"GB",
    "wof:name":"NN3 8RS",
    "wof:placetype":"postalcode"
},
  "geometry": {"coordinates":[-0.84148578545763,52.28022173229456],"type":"Point"}
}