{
  "type": "Feature",
  "properties": {
    "iso:country":"GB",
    "wof:name":"CW10 0HJ",
    "wof:placetype":"postalcode"
},
  "geometry": {"coordinates":[-2.437541223633,53.16201328167504],"type":"Point"}
}