{
  "type": "Feature",
  "properties": {
    "iso:country":"GB",
    "wof:name":"MK6 5HQ",
    "wof:placetype":"postalcode"
},
  "geometry": {"coordinates":[-0.74229181702872,52.02185779670344],"type":"Point"}
}