{
  "type": "Feature",
  "properties": {
    "iso:country":"GB",
    "wof:name":"IV63 6XH",
    "wof:placetype":"postalcode"
},
  "geometry": {"coordinates":[-4.50399525005558,57.27991888666967],"type":"Point"}
}