{
  "type": "Feature",
  "properties": {
    "iso:country": "GB",
    "wof:name": "IV63 6XH",
    "wof:placetype": "postalcode"
  },
  "geometry": {"coordinates":[-4.503828,57.279941],"type":"Point"}
}
