{
  "type": "Feature",
  "properties": {
    "iso:country":"GB",
    "wof:name":"BN20 7HB",
    "wof:placetype":"postalcode"
},
  "geometry": {"coordinates":[0.27581272377587,50.75910337531541],"type":"Point"}
}