{
  "type": "Feature",
  "properties": {
    "iso:country":"GB",
    "wof:name":"PO38 2RE",
    "wof:placetype":"postalcode"
},
  "geometry": {"coordinates":[-1.26784130878965,50.60114881898529],"type":"Point"}
}