{
  "type": "Feature",
  "properties": {
    "iso:country": "GB",
    "wof:name": "PO38 2RE",
    "wof:placetype": "postalcode"
  },
  "geometry": {"coordinates":[-1.267841,50.601149],"type":"Point"}
}
