{
  "type": "Feature",
  "properties": {
    "iso:country":"GB",
    "wof:name":"OX4 7YB",
    "wof:placetype":"postalcode"
},
  "geometry": {"coordinates":[-1.19060435982791,51.71788051387529],"type":"Point"}
}