{
  "type": "Feature",
  "properties": {
    "iso:country":"GB",
    "wof:name":"DE5 3HE",
    "wof:placetype":"postalcode"
},
  "geometry": {"coordinates":[-1.41240694223509,53.04698307573364],"type":"Point"}
}