{
  "type": "Feature",
  "properties": {
    "iso:country": "GB",
    "wof:name": "EH41 3PZ",
    "wof:placetype": "postalcode"
  },
  "geometry": {"coordinates":[-2.775092,55.960122],"type":"Point"}
}
