{
  "type": "Feature",
  "properties": {
    "iso:country":"GB",
    "wof:name":"EH41 3PZ",
    "wof:placetype":"postalcode"
},
  "geometry": {"coordinates":[-2.77509226354563,55.96012169502562],"type":"Point"}
}