{
  "type": "Feature",
  "properties": {
    "date:inception_lower": "2002-06-01",
    "date:inception_upper": "2002-06-01",
    "iso:country": "GB",
    "wof:name": "WS9 8ZE",
    "wof:placetype": "postalcode"
  },
  "geometry": {"coordinates":[-1.923207,52.602631],"type":"Point"}
}
