{
  "type": "Feature",
  "properties": {
    "iso:country":"GB",
    "wof:name":"WS9 8ZE",
    "wof:placetype":"postalcode"
},
  "geometry": {"coordinates":[-1.92320739129871,52.60263119445018],"type":"Point"}
}