{
  "type": "Feature",
  "properties": {
    "iso:country":"GB",
    "wof:name":"TN12 6PE",
    "wof:placetype":"postalcode"
},
  "geometry": {"coordinates":[0.41990276319233,51.1842319318257],"type":"Point"}
}