{
  "type": "Feature",
  "properties": {
    "date:inception_lower": "1991-01-01",
    "date:inception_upper": "1991-01-01",
    "iso:country": "GB",
    "wof:name": "TN12 6PE",
    "wof:placetype": "postalcode"
  },
  "geometry": {"coordinates":[0.418184,51.181991],"type":"Point"}
}
