{
  "type": "Feature",
  "properties": {
    "iso:country": "GB",
    "wof:name": "TN12 6PE",
    "wof:placetype": "postalcode"
  },
  "geometry": {"coordinates":[0.419706,51.18428],"type":"Point"}
}
