{
  "type": "Feature",
  "properties": {
    "iso:country": "GB",
    "wof:name": "PL28 8RZ",
    "wof:placetype": "postalcode"
  },
  "geometry": {"coordinates":[-4.970573,50.537761],"type":"Point"}
}
