{
  "type": "Feature",
  "properties": {
    "iso:country":"GB",
    "wof:name":"PL28 8RZ",
    "wof:placetype":"postalcode"
},
  "geometry": {"coordinates":[-4.97057286827227,50.53776133253511],"type":"Point"}
}