{
  "type": "Feature",
  "properties": {
    "date:inception_lower": "1980-01-01",
    "date:inception_upper": "1980-01-01",
    "iso:country": "GB",
    "wof:name": "PO20 0QX",
    "wof:placetype": "postalcode"
  },
  "geometry": {"coordinates":[-0.787811,50.734973],"type":"Point"}
}
