{
  "type": "Feature",
  "properties": {
    "iso:country":"GB",
    "wof:name":"PO20 0QX",
    "wof:placetype":"postalcode"
},
  "geometry": {"coordinates":[-0.78781142591013,50.73497273754463],"type":"Point"}
}