{
  "type": "Feature",
  "properties": {
    "date:inception_lower": "1980-01-01",
    "date:inception_upper": "1980-01-01",
    "iso:country": "GB",
    "wof:name": "HA9 0QZ",
    "wof:placetype": "postalcode"
  },
  "geometry": {"coordinates":[-0.285926,51.557854],"type":"Point"}
}
