{
  "type": "Feature",
  "properties": {
    "iso:country":"GB",
    "wof:name":"SR6 8EF",
    "wof:placetype":"postalcode"
},
  "geometry": {"coordinates":[-1.37090209338701,54.93145723742509],"type":"Point"}
}