{
  "type": "Feature",
  "properties": {
    "iso:country": "GB",
    "wof:name": "SR6 8EF",
    "wof:placetype": "postalcode"
  },
  "geometry": {"coordinates":[-1.371181,54.931458],"type":"Point"}
}
