{
  "type": "Feature",
  "properties": {
    "iso:country": "GB",
    "wof:name": "NR12 9FX",
    "wof:placetype": "postalcode"
  },
  "geometry": {"coordinates":[1.490914,52.802845],"type":"Point"}
}
