{
  "type": "Feature",
  "properties": {
    "date:inception_lower":"1985-04-01",
    "date:inception_upper":"1985-04-30",
    "iso:country":"GB",
    "wof:name":"TS19 0XJ",
    "wof:placetype":"postalcode"
},
  "geometry": {"coordinates":[-1.348874,54.575521],"type":"Point"}
}