{
  "type": "Feature",
  "properties": {
    "iso:country": "GB",
    "wof:name": "S12 2JF",
    "wof:placetype": "postalcode"
  },
  "geometry": {"coordinates":[-1.420479,53.351057],"type":"Point"}
}
