{
  "type": "Feature",
  "properties": {
    "date:inception_lower": "1980-01-01",
    "date:inception_upper": "1980-01-01",
    "iso:country": "GB",
    "wof:name": "S12 2JF",
    "wof:placetype": "postalcode"
  },
  "geometry": {"coordinates":[-1.420479,53.351057],"type":"Point"}
}
