{
  "type": "Feature",
  "properties": {
    "iso:country":"GB",
    "wof:name":"S12 2JF",
    "wof:placetype":"postalcode"
},
  "geometry": {"coordinates":[-1.42047918055944,53.35105729592263],"type":"Point"}
}