{
  "type": "Feature",
  "properties": {
    "iso:country": "GB",
    "wof:name": "DG12 6LX",
    "wof:placetype": "postalcode"
  },
  "geometry": {"coordinates":[-3.242153,54.992794],"type":"Point"}
}
