{
  "type": "Feature",
  "properties": {
    "date:inception_lower": "2001-12-01",
    "date:inception_upper": "2001-12-01",
    "iso:country": "GB",
    "wof:name": "DG12 6LX",
    "wof:placetype": "postalcode"
  },
  "geometry": {"coordinates":[-3.242617,54.992636],"type":"Point"}
}
