{
  "type": "Feature",
  "properties": {
    "iso:country":"GB",
    "wof:name":"DG12 6LX",
    "wof:placetype":"postalcode"
},
  "geometry": {"coordinates":[-3.2426150026567,54.99263086819634],"type":"Point"}
}