{
  "type": "Feature",
  "properties": {
    "iso:country":"GB",
    "wof:name":"NG4 3AL",
    "wof:placetype":"postalcode"
},
  "geometry": {"coordinates":[-1.08315035019676,52.96583954536146],"type":"Point"}
}