{
  "type": "Feature",
  "properties": {
    "date:inception_lower": "1980-01-01",
    "date:inception_upper": "1980-01-01",
    "iso:country": "GB",
    "wof:name": "NG4 3AL",
    "wof:placetype": "postalcode"
  },
  "geometry": {"coordinates":[-1.08315,52.96584],"type":"Point"}
}
