{
  "type": "Feature",
  "properties": {
    "iso:country":"GB",
    "wof:name":"HG1 2BL",
    "wof:placetype":"postalcode"
},
  "geometry": {"coordinates":[-1.55242342889316,54.00407950034057],"type":"Point"}
}