{
  "type": "Feature",
  "properties": {
    "iso:country": "GB",
    "wof:name": "HG1 2BL",
    "wof:placetype": "postalcode"
  },
  "geometry": {"coordinates":[-1.552423,54.004079],"type":"Point"}
}
