{
  "type": "Feature",
  "properties": {
    "iso:country": "GB",
    "wof:name": "ST19 5AN",
    "wof:placetype": "postalcode"
  },
  "geometry": {"coordinates":[-2.117015,52.724219],"type":"Point"}
}
