{
  "type": "Feature",
  "properties": {
    "iso:country":"GB",
    "wof:name":"NG17 7FU",
    "wof:placetype":"postalcode"
},
  "geometry": {"coordinates":[-1.24369927081628,53.09202871183088],"type":"Point"}
}