{
  "type": "Feature",
  "properties": {
    "iso:country": "GB",
    "wof:name": "WN1 9SN",
    "wof:placetype": "postalcode"
  },
  "geometry": {"coordinates":[-2.62996,53.545098],"type":"Point"}
}
