{
  "type": "Feature",
  "properties": {
    "iso:country":"GB",
    "wof:name":"NG4 3HN",
    "wof:placetype":"postalcode"
},
  "geometry": {"coordinates":[-1.08069136239779,52.97366841588102],"type":"Point"}
}