{
  "type": "Feature",
  "properties": {
    "iso:country": "GB",
    "wof:name": "NG4 3HN",
    "wof:placetype": "postalcode"
  },
  "geometry": {"coordinates":[-1.080691,52.973668],"type":"Point"}
}
