{
  "type": "Feature",
  "properties": {
    "iso:country":"GB",
    "wof:name":"SW8 4RA",
    "wof:placetype":"postalcode"
},
  "geometry": {"coordinates":[-0.13066366327682,51.47677125418203],"type":"Point"}
}