{
  "type": "Feature",
  "properties": {
    "iso:country":"GB",
    "wof:name":"TN39 4HE",
    "wof:placetype":"postalcode"
},
  "geometry": {"coordinates":[0.45829524681975,50.85024203106128],"type":"Point"}
}