{
  "type": "Feature",
  "properties": {
    "iso:country":"GB",
    "wof:name":"LA5 8JT",
    "wof:placetype":"postalcode"
},
  "geometry": {"coordinates":[-2.79535353718351,54.10668153453864],"type":"Point"}
}