{
  "type": "Feature",
  "properties": {
    "iso:country":"GB",
    "wof:name":"NW2 3SL",
    "wof:placetype":"postalcode"
},
  "geometry": {"coordinates":[-0.20251048315988,51.55248689553444],"type":"Point"}
}