{
  "type": "Feature",
  "properties": {
    "iso:country": "GB",
    "wof:name": "PE3 6SS",
    "wof:placetype": "postalcode"
  },
  "geometry": {"coordinates":[-0.28733,52.569462],"type":"Point"}
}
