{
  "type": "Feature",
  "properties": {
    "iso:country":"GB",
    "wof:name":"PE3 6SS",
    "wof:placetype":"postalcode"
},
  "geometry": {"coordinates":[-0.28732956991885,52.56946207288163],"type":"Point"}
}