{
  "type": "Feature",
  "properties": {
    "iso:country":"GB",
    "wof:name":"WS11 1JX",
    "wof:placetype":"postalcode"
},
  "geometry": {"coordinates":[-2.02484385078801,52.69348519493352],"type":"Point"}
}