{
  "type": "Feature",
  "properties": {
    "iso:country": "GB",
    "wof:name": "WS11 1JX",
    "wof:placetype": "postalcode"
  },
  "geometry": {"coordinates":[-2.024844,52.693485],"type":"Point"}
}
