{
  "type": "Feature",
  "properties": {
    "iso:country": "GB",
    "wof:name": "BL1 7EA",
    "wof:placetype": "postalcode"
  },
  "geometry": {"coordinates":[-2.436964,53.607295],"type":"Point"}
}
