{
  "type": "Feature",
  "properties": {
    "iso:country":"GB",
    "wof:name":"BL1 7EA",
    "wof:placetype":"postalcode"
},
  "geometry": {"coordinates":[-2.43696437817747,53.60729541974604],"type":"Point"}
}