{
  "type": "Feature",
  "properties": {
    "iso:country":"GB",
    "wof:name":"PL10 1HB",
    "wof:placetype":"postalcode"
},
  "geometry": {"coordinates":[-4.19767467925446,50.35481934194151],"type":"Point"}
}