{
  "type": "Feature",
  "properties": {
    "iso:country":"GB",
    "wof:name":"SM3 9SJ",
    "wof:placetype":"postalcode"
},
  "geometry": {"coordinates":[-0.21252458285418,51.36964254211652],"type":"Point"}
}