{
  "type": "Feature",
  "properties": {
    "date:inception_lower": "1980-01-01",
    "date:inception_upper": "1980-01-01",
    "iso:country": "GB",
    "wof:name": "SM3 9SJ",
    "wof:placetype": "postalcode"
  },
  "geometry": {"coordinates":[-0.212398,51.369658],"type":"Point"}
}
