{
  "type": "Feature",
  "properties": {
    "iso:country": "GB",
    "wof:name": "SM3 9SJ",
    "wof:placetype": "postalcode"
  },
  "geometry": {"coordinates":[-0.212398,51.369658],"type":"Point"}
}
