{
  "type": "Feature",
  "properties": {
    "iso:country":"GB",
    "wof:name":"MK42 0BG",
    "wof:placetype":"postalcode"
},
  "geometry": {"coordinates":[-0.45120313156707,52.12971312824042],"type":"Point"}
}