{
  "type": "Feature",
  "properties": {
    "iso:country": "GB",
    "wof:name": "TN12 9TA",
    "wof:placetype": "postalcode"
  },
  "geometry": {"coordinates":[0.475978,51.201981],"type":"Point"}
}
