{
  "type": "Feature",
  "properties": {
    "date:inception_lower":"1980-01-01",
    "date:inception_upper":"1980-01-31",
    "iso:country":"GB",
    "wof:name":"TN12 9TA",
    "wof:placetype":"postalcode"
},
  "geometry": {"coordinates":[0.475978,51.201981],"type":"Point"}
}