{
  "type": "Feature",
  "properties": {
    "date:inception_lower": "1980-01-01",
    "date:inception_upper": "1980-01-01",
    "iso:country": "GB",
    "wof:name": "TN12 9TA",
    "wof:placetype": "postalcode"
  },
  "geometry": {"coordinates":[0.476307,51.202225],"type":"Point"}
}
