{
  "type": "Feature",
  "properties": {
    "iso:country": "GB",
    "wof:name": "KT24 5GA",
    "wof:placetype": "postalcode"
  },
  "geometry": {"coordinates":[-0.397187,51.270177],"type":"Point"}
}
