{
  "type": "Feature",
  "properties": {
    "date:inception_lower": "2003-02-01",
    "date:inception_upper": "2003-02-01",
    "iso:country": "GB",
    "wof:name": "KT24 5GA",
    "wof:placetype": "postalcode"
  },
  "geometry": {"coordinates":[-0.397187,51.270177],"type":"Point"}
}
