{
  "type": "Feature",
  "properties": {
    "date:inception_lower": "1980-01-01",
    "date:inception_upper": "1980-01-01",
    "iso:country": "GB",
    "wof:name": "HP11 1RJ",
    "wof:placetype": "postalcode"
  },
  "geometry": {"coordinates":[-0.716789,51.618278],"type":"Point"}
}
