{
  "type": "Feature",
  "properties": {
    "iso:country":"GB",
    "wof:name":"TA20 3QH",
    "wof:placetype":"postalcode"
},
  "geometry": {"coordinates":[-3.08326999927164,50.92193835216597],"type":"Point"}
}