{
  "type": "Feature",
  "properties": {
    "date:inception_lower": "2018-12-01",
    "date:inception_upper": "2018-12-01",
    "iso:country": "GB",
    "wof:name": "TN18 5AF",
    "wof:placetype": "postalcode"
  },
  "geometry": {"coordinates":[0.517573,51.04654],"type":"Point"}
}
