{
  "type": "Feature",
  "properties": {
    "iso:country":"GB",
    "wof:name":"YO43 4BB",
    "wof:placetype":"postalcode"
},
  "geometry": {"coordinates":[-0.74081155258812,53.80930979720073],"type":"Point"}
}