{
  "type": "Feature",
  "properties": {
    "date:inception_lower":"1998-06-01",
    "date:inception_upper":"1998-06-30",
    "iso:country":"GB",
    "wof:name":"YO43 4BB",
    "wof:placetype":"postalcode"
},
  "geometry": {"coordinates":[-0.740812,53.80931],"type":"Point"}
}