{
  "type": "Feature",
  "properties": {
    "iso:country":"GB",
    "wof:name":"B13 8NS",
    "wof:placetype":"postalcode"
},
  "geometry": {"coordinates":[-1.90379799595849,52.44390046975668],"type":"Point"}
}