{
  "type": "Feature",
  "properties": {
    "date:inception_lower":"2005-09-01",
    "date:inception_upper":"2005-09-30",
    "iso:country":"GB",
    "wof:name":"BB3 1BR",
    "wof:placetype":"postalcode"
},
  "geometry": {"coordinates":[-2.468072,53.695011],"type":"Point"}
}