{
  "type": "Feature",
  "properties": {
    "iso:country": "GB",
    "wof:name": "BB3 1BR",
    "wof:placetype": "postalcode"
  },
  "geometry": {"coordinates":[-2.468072,53.695011],"type":"Point"}
}
