{
  "type": "Feature",
  "properties": {
    "iso:country": "GB",
    "wof:name": "BL4 0LR",
    "wof:placetype": "postalcode"
  },
  "geometry": {"coordinates":[-2.453946,53.550354],"type":"Point"}
}
