{
  "type": "Feature",
  "properties": {
    "date:inception_lower":"1995-07-01",
    "date:inception_upper":"1995-07-31",
    "iso:country":"GB",
    "wof:name":"LL14 1DP",
    "wof:placetype":"postalcode"
},
  "geometry": {"coordinates":[-3.056881,53.012479],"type":"Point"}
}