{
  "type": "Feature",
  "properties": {
    "iso:country": "GB",
    "wof:name": "LL14 1DP",
    "wof:placetype": "postalcode"
  },
  "geometry": {"coordinates":[-3.056881,53.012479],"type":"Point"}
}
