{
  "type": "Feature",
  "properties": {
    "iso:country":"GB",
    "wof:name":"LL14 1DP",
    "wof:placetype":"postalcode"
},
  "geometry": {"coordinates":[-3.05688145624727,53.01247928241074],"type":"Point"}
}