{
  "type": "Feature",
  "properties": {
    "iso:country":"GB",
    "wof:name":"TN21 8QN",
    "wof:placetype":"postalcode"
},
  "geometry": {"coordinates":[0.25563047358513,50.960697328088],"type":"Point"}
}