{
  "type": "Feature",
  "properties": {
    "date:inception_lower":"1980-01-01",
    "date:inception_upper":"1980-01-31",
    "iso:country":"GB",
    "wof:name":"LA12 7BJ",
    "wof:placetype":"postalcode"
},
  "geometry": {"coordinates":[-3.097283,54.197233],"type":"Point"}
}