{
  "type": "Feature",
  "properties": {
    "iso:country": "GB",
    "wof:name": "LA12 7BJ",
    "wof:placetype": "postalcode"
  },
  "geometry": {"coordinates":[-3.097283,54.197233],"type":"Point"}
}
