{
  "type": "Feature",
  "properties": {
    "iso:country":"GB",
    "wof:name":"CF31 1NU",
    "wof:placetype":"postalcode"
},
  "geometry": {"coordinates":[-3.5742175715401,51.51765977751184],"type":"Point"}
}