{
  "type": "Feature",
  "properties": {
    "iso:country": "GB",
    "wof:name": "CF31 1NU",
    "wof:placetype": "postalcode"
  },
  "geometry": {"coordinates":[-3.574234,51.51767],"type":"Point"}
}
