{
  "type": "Feature",
  "properties": {
    "iso:country": "GB",
    "wof:name": "PE15 8FA",
    "wof:placetype": "postalcode"
  },
  "geometry": {"coordinates":[0.067588,52.55761],"type":"Point"}
}
