{
  "type": "Feature",
  "properties": {
    "iso:country":"GB",
    "wof:name":"PE15 8FA",
    "wof:placetype":"postalcode"
},
  "geometry": {"coordinates":[0.06758829713435,52.55760951877004],"type":"Point"}
}