{
  "type": "Feature",
  "properties": {
    "iso:country": "GB",
    "wof:name": "BH9 3LW",
    "wof:placetype": "postalcode"
  },
  "geometry": {"coordinates":[-1.858081,50.756661],"type":"Point"}
}
