{
  "type": "Feature",
  "properties": {
    "date:inception_lower": "1980-01-01",
    "date:inception_upper": "1980-01-01",
    "iso:country": "GB",
    "wof:name": "KY5 8HS",
    "wof:placetype": "postalcode"
  },
  "geometry": {"coordinates":[-3.320182,56.157447],"type":"Point"}
}
