{
  "type": "Feature",
  "properties": {
    "iso:country":"GB",
    "wof:name":"NN3 6TE",
    "wof:placetype":"postalcode"
},
  "geometry": {"coordinates":[-0.87132360040763,52.27645583214505],"type":"Point"}
}