{
  "type": "Feature",
  "properties": {
    "iso:country": "GB",
    "wof:name": "OX10 8DS",
    "wof:placetype": "postalcode"
  },
  "geometry": {"coordinates":[-1.11452,51.599912],"type":"Point"}
}
