{
  "type": "Feature",
  "properties": {
    "iso:country":"GB",
    "wof:name":"OX10 8DS",
    "wof:placetype":"postalcode"
},
  "geometry": {"coordinates":[-1.11452032681462,51.59991242454807],"type":"Point"}
}