{
  "type": "Feature",
  "properties": {
    "iso:country":"GB",
    "wof:name":"HG1 4BB",
    "wof:placetype":"postalcode"
},
  "geometry": {"coordinates":[-1.52154465070822,54.00265741066288],"type":"Point"}
}