{
  "type": "Feature",
  "properties": {
    "iso:country":"GB",
    "wof:name":"BL9 7QT",
    "wof:placetype":"postalcode"
},
  "geometry": {"coordinates":[-2.27465465316121,53.59457453322505],"type":"Point"}
}