{
  "type": "Feature",
  "properties": {
    "iso:country": "GB",
    "wof:name": "BL9 7QT",
    "wof:placetype": "postalcode"
  },
  "geometry": {"coordinates":[-2.274655,53.594575],"type":"Point"}
}
