{
  "type": "Feature",
  "properties": {
    "date:inception_lower": "2014-03-01",
    "date:inception_upper": "2014-03-01",
    "iso:country": "GB",
    "wof:name": "YO31 9JR",
    "wof:placetype": "postalcode"
  },
  "geometry": {"coordinates":[-1.069784,53.986197],"type":"Point"}
}
