{
  "type": "Feature",
  "properties": {
    "iso:country": "GB",
    "wof:name": "WA7 5YG",
    "wof:placetype": "postalcode"
  },
  "geometry": {"coordinates":[-2.721507,53.326721],"type":"Point"}
}
