{
  "type": "Feature",
  "properties": {
    "iso:country":"GB",
    "wof:name":"WA7 5YG",
    "wof:placetype":"postalcode"
},
  "geometry": {"coordinates":[-2.72150735387978,53.32672072767084],"type":"Point"}
}