{
  "type": "Feature",
  "properties": {
    "iso:country":"GB",
    "wof:name":"CB7 5NE",
    "wof:placetype":"postalcode"
},
  "geometry": {"coordinates":[0.39204498517881,52.30763256691473],"type":"Point"}
}