{
  "type": "Feature",
  "properties": {
    "iso:country":"GB",
    "wof:name":"E17 4JG",
    "wof:placetype":"postalcode"
},
  "geometry": {"coordinates":[-0.00802904719526,51.59233063264546],"type":"Point"}
}