{
  "type": "Feature",
  "properties": {
    "date:inception_lower": "2000-06-01",
    "date:inception_upper": "2000-06-01",
    "iso:country": "GB",
    "wof:name": "SN2 8BQ",
    "wof:placetype": "postalcode"
  },
  "geometry": {"coordinates":[-1.772459,51.570481],"type":"Point"}
}
