{
  "type": "Feature",
  "properties": {
    "iso:country":"GB",
    "wof:name":"SN2 8BQ",
    "wof:placetype":"postalcode"
},
  "geometry": {"coordinates":[-1.77245874055582,51.57048126262637],"type":"Point"}
}