{
  "type": "Feature",
  "properties": {
    "iso:country":"GB",
    "wof:name":"E13 8ND",
    "wof:placetype":"postalcode"
},
  "geometry": {"coordinates":[0.02819370348207,51.51806038573766],"type":"Point"}
}