{
  "type": "Feature",
  "properties": {
    "iso:country":"GB",
    "wof:name":"DD8 1JS",
    "wof:placetype":"postalcode"
},
  "geometry": {"coordinates":[-2.89943107610497,56.63658587331095],"type":"Point"}
}