{
  "type": "Feature",
  "properties": {
    "iso:country": "GB",
    "wof:name": "PR7 6QR",
    "wof:placetype": "postalcode"
  },
  "geometry": {"coordinates":[-2.669106,53.67047],"type":"Point"}
}
