{
  "type": "Feature",
  "properties": {
    "date:inception_lower": "2018-11-01",
    "date:inception_upper": "2018-11-01",
    "iso:country": "GB",
    "wof:name": "PR7 6QR",
    "wof:placetype": "postalcode"
  },
  "geometry": {"coordinates":[-2.669106,53.67047],"type":"Point"}
}
