{
  "type": "Feature",
  "properties": {
    "iso:country":"GB",
    "wof:name":"TR7 1LN",
    "wof:placetype":"postalcode"
},
  "geometry": {"coordinates":[-5.08690045526194,50.41440847875206],"type":"Point"}
}