{
  "type": "Feature",
  "properties": {
    "iso:country":"GB",
    "wof:name":"BN25 3HB",
    "wof:placetype":"postalcode"
},
  "geometry": {"coordinates":[0.11452705581845,50.77969596794651],"type":"Point"}
}