{
  "type": "Feature",
  "properties": {
    "date:inception_lower": "1980-01-01",
    "date:inception_upper": "1980-01-01",
    "iso:country": "GB",
    "wof:name": "KT12 3ND",
    "wof:placetype": "postalcode"
  },
  "geometry": {"coordinates":[-0.405538,51.38169],"type":"Point"}
}
