{
  "type": "Feature",
  "properties": {
    "iso:country": "GB",
    "wof:name": "LL71 8BG",
    "wof:placetype": "postalcode"
  },
  "geometry": {"coordinates":[-4.30595,53.339722],"type":"Point"}
}
