{
  "type": "Feature",
  "properties": {
    "iso:country":"GB",
    "wof:name":"LL71 8BG",
    "wof:placetype":"postalcode"
},
  "geometry": {"coordinates":[-4.30594974147476,53.33972173510738],"type":"Point"}
}