{
  "type": "Feature",
  "properties": {
    "iso:country":"GB",
    "wof:name":"WV9 5JE",
    "wof:placetype":"postalcode"
},
  "geometry": {"coordinates":[-2.13822989932732,52.65786182466089],"type":"Point"}
}