{
  "type": "Feature",
  "properties": {
    "iso:country": "GB",
    "wof:name": "WV9 5JE",
    "wof:placetype": "postalcode"
  },
  "geometry": {"coordinates":[-2.13823,52.657862],"type":"Point"}
}
