{
  "type": "Feature",
  "properties": {
    "date:inception_lower": "1980-01-01",
    "date:inception_upper": "1980-01-01",
    "iso:country": "GB",
    "wof:name": "SG5 3AH",
    "wof:placetype": "postalcode"
  },
  "geometry": {"coordinates":[-0.338941,51.929614],"type":"Point"}
}
