{
  "type": "Feature",
  "properties": {
    "date:inception_lower":"2005-06-01",
    "date:inception_upper":"2005-06-30",
    "iso:country":"GB",
    "wof:name":"TN2 3UQ",
    "wof:placetype":"postalcode"
},
  "geometry": {"coordinates":[0.285785,51.136414],"type":"Point"}
}