{
  "type": "Feature",
  "properties": {
    "iso:country":"GB",
    "wof:name":"TN2 3UQ",
    "wof:placetype":"postalcode"
},
  "geometry": {"coordinates":[0.28578458519347,51.13641354226218],"type":"Point"}
}