{
  "type": "Feature",
  "properties": {
    "iso:country":"GB",
    "wof:name":"B23 6TD",
    "wof:placetype":"postalcode"
},
  "geometry": {"coordinates":[-1.84036343257424,52.52431912165179],"type":"Point"}
}