{
  "type": "Feature",
  "properties": {
    "iso:country":"GB",
    "wof:name":"NE33 4TS",
    "wof:placetype":"postalcode"
},
  "geometry": {"coordinates":[-1.42775769386953,54.9840027680253],"type":"Point"}
}