{
  "type": "Feature",
  "properties": {
    "iso:country":"GB",
    "wof:name":"CM6 3HA",
    "wof:placetype":"postalcode"
},
  "geometry": {"coordinates":[0.4302199078875,51.85695608816257],"type":"Point"}
}