{
  "type": "Feature",
  "properties": {
    "iso:country":"GB",
    "wof:name":"BS37 6EN",
    "wof:placetype":"postalcode"
},
  "geometry": {"coordinates":[-2.39469600538894,51.53508706755904],"type":"Point"}
}