{
  "type": "Feature",
  "properties": {
    "iso:country": "GB",
    "wof:name": "BS37 6EN",
    "wof:placetype": "postalcode"
  },
  "geometry": {"coordinates":[-2.394696,51.535087],"type":"Point"}
}
