{
  "type": "Feature",
  "properties": {
    "date:inception_lower":"1980-01-01",
    "date:inception_upper":"1980-01-31",
    "iso:country":"GB",
    "wof:name":"BB2 2ED",
    "wof:placetype":"postalcode"
},
  "geometry": {"coordinates":[-2.48496,53.746686],"type":"Point"}
}