{
  "type": "Feature",
  "properties": {
    "iso:country": "GB",
    "wof:name": "BB2 2ED",
    "wof:placetype": "postalcode"
  },
  "geometry": {"coordinates":[-2.48496,53.746686],"type":"Point"}
}
