{
  "type": "Feature",
  "properties": {
    "iso:country":"GB",
    "wof:name":"BA12 0LR",
    "wof:placetype":"postalcode"
},
  "geometry": {"coordinates":[-2.01467559037346,51.19415722875688],"type":"Point"}
}