{
  "type": "Feature",
  "properties": {
    "date:inception_lower":"2005-08-01",
    "date:inception_upper":"2005-08-31",
    "iso:country":"GB",
    "wof:name":"HG3 3TJ",
    "wof:placetype":"postalcode"
},
  "geometry": {"coordinates":[-1.499218,54.069336],"type":"Point"}
}