{
  "type": "Feature",
  "properties": {
    "iso:country":"GB",
    "wof:name":"HG3 3TJ",
    "wof:placetype":"postalcode"
},
  "geometry": {"coordinates":[-1.4992176730392,54.06933616290053],"type":"Point"}
}