{
  "type": "Feature",
  "properties": {
    "iso:country":"GB",
    "wof:name":"HP5 1AJ",
    "wof:placetype":"postalcode"
},
  "geometry": {"coordinates":[-0.60739675060415,51.70899094855596],"type":"Point"}
}