{
  "type": "Feature",
  "properties": {
    "iso:country": "GB",
    "wof:name": "HP5 1AJ",
    "wof:placetype": "postalcode"
  },
  "geometry": {"coordinates":[-0.607397,51.708991],"type":"Point"}
}
