{
  "type": "Feature",
  "properties": {
    "iso:country":"GB",
    "wof:name":"CA7 8EY",
    "wof:placetype":"postalcode"
},
  "geometry": {"coordinates":[-3.05657975654923,54.73998907774141],"type":"Point"}
}