{
  "type": "Feature",
  "properties": {
    "date:inception_lower": "1980-01-01",
    "date:inception_upper": "1980-01-01",
    "iso:country": "GB",
    "wof:name": "CA7 8EY",
    "wof:placetype": "postalcode"
  },
  "geometry": {"coordinates":[-3.05658,54.739989],"type":"Point"}
}
