{
  "type": "Feature",
  "properties": {
    "iso:country":"GB",
    "wof:name":"S3 7GL",
    "wof:placetype":"postalcode"
},
  "geometry": {"coordinates":[-1.47904917376787,53.38586181949352],"type":"Point"}
}