{
  "type": "Feature",
  "properties": {
    "date:inception_lower": "2011-12-01",
    "date:inception_upper": "2011-12-01",
    "iso:country": "GB",
    "wof:name": "S3 7GL",
    "wof:placetype": "postalcode"
  },
  "geometry": {"coordinates":[-1.479137,53.386051],"type":"Point"}
}
