{
  "type": "Feature",
  "properties": {
    "iso:country":"GB",
    "wof:name":"B62 9BQ",
    "wof:placetype":"postalcode"
},
  "geometry": {"coordinates":[-2.01505736451395,52.46337476267688],"type":"Point"}
}