{
  "type": "Feature",
  "properties": {
    "iso:country":"GB",
    "wof:name":"TS9 6LH",
    "wof:placetype":"postalcode"
},
  "geometry": {"coordinates":[-1.10840335733939,54.46520777715913],"type":"Point"}
}