{
  "type": "Feature",
  "properties": {
    "iso:country": "GB",
    "wof:name": "TS9 6LH",
    "wof:placetype": "postalcode"
  },
  "geometry": {"coordinates":[-1.108403,54.465208],"type":"Point"}
}
