{
  "type": "Feature",
  "properties": {
    "iso:country":"GB",
    "wof:name":"SS17 0LA",
    "wof:placetype":"postalcode"
},
  "geometry": {"coordinates":[0.42297250530207,51.51126953406138],"type":"Point"}
}