{
  "type": "Feature",
  "properties": {
    "iso:country":"GB",
    "wof:name":"CR0 7TF",
    "wof:placetype":"postalcode"
},
  "geometry": {"coordinates":[-0.05273241011826,51.39275189988646],"type":"Point"}
}