{
  "type": "Feature",
  "properties": {
    "iso:country":"GB",
    "wof:name":"ST8 7HA",
    "wof:placetype":"postalcode"
},
  "geometry": {"coordinates":[-2.16698860979608,53.12234899063458],"type":"Point"}
}