{
  "type": "Feature",
  "properties": {
    "iso:country":"GB",
    "wof:name":"TQ2 5RZ",
    "wof:placetype":"postalcode"
},
  "geometry": {"coordinates":[-3.53815353492669,50.46959116743707],"type":"Point"}
}