{
  "type": "Feature",
  "properties": {
    "date:inception_lower": "1980-01-01",
    "date:inception_upper": "1980-01-01",
    "iso:country": "GB",
    "wof:name": "TQ2 5RZ",
    "wof:placetype": "postalcode"
  },
  "geometry": {"coordinates":[-3.538153,50.469591],"type":"Point"}
}
