{
  "type": "Feature",
  "properties": {
    "iso:country": "GB",
    "wof:name": "UB9 5FL",
    "wof:placetype": "postalcode"
  },
  "geometry": {"coordinates":[-0.49791,51.587495],"type":"Point"}
}
