{
  "type": "Feature",
  "properties": {
    "date:inception_lower": "2019-08-01",
    "date:inception_upper": "2019-08-01",
    "iso:country": "GB",
    "wof:name": "UB9 5FL",
    "wof:placetype": "postalcode"
  },
  "geometry": {"coordinates":[-0.497883,51.587422],"type":"Point"}
}
