{
  "type": "Feature",
  "properties": {
    "iso:country":"GB",
    "wof:name":"SM5 3QN",
    "wof:placetype":"postalcode"
},
  "geometry": {"coordinates":[-0.1708714696498,51.36144576981387],"type":"Point"}
}