{
  "type": "Feature",
  "properties": {
    "iso:country":"GB",
    "wof:name":"LS26 8JS",
    "wof:placetype":"postalcode"
},
  "geometry": {"coordinates":[-1.4536973843372,53.74713717271847],"type":"Point"}
}