{
  "type": "Feature",
  "properties": {
    "iso:country":"GB",
    "wof:name":"DG2 8NW",
    "wof:placetype":"postalcode"
},
  "geometry": {"coordinates":[-3.72518780068873,55.04597026856072],"type":"Point"}
}