{
  "type": "Feature",
  "properties": {
    "date:inception_lower":"2006-09-01",
    "date:inception_upper":"2006-09-30",
    "iso:country":"GB",
    "wof:name":"CB24 6AF",
    "wof:placetype":"postalcode"
},
  "geometry": {"coordinates":[0.174535,52.236945],"type":"Point"}
}