{
  "type": "Feature",
  "properties": {
    "iso:country":"GB",
    "wof:name":"CB24 6AF",
    "wof:placetype":"postalcode"
},
  "geometry": {"coordinates":[0.17453522335662,52.23694502807083],"type":"Point"}
}