{
  "type": "Feature",
  "properties": {
    "iso:country":"GB",
    "wof:name":"GL7 3JS",
    "wof:placetype":"postalcode"
},
  "geometry": {"coordinates":[-1.67882168470809,51.69281391104058],"type":"Point"}
}