{
  "type": "Feature",
  "properties": {
    "date:inception_lower":"2015-02-01",
    "date:inception_upper":"2015-02-28",
    "iso:country":"GB",
    "wof:name":"GL7 3JS",
    "wof:placetype":"postalcode"
},
  "geometry": {"coordinates":[-1.677708,51.692896],"type":"Point"}
}