{
  "type": "Feature",
  "properties": {
    "iso:country": "GB",
    "wof:name": "GL7 3JS",
    "wof:placetype": "postalcode"
  },
  "geometry": {"coordinates":[-1.677708,51.692896],"type":"Point"}
}
