{
  "type": "Feature",
  "properties": {
    "date:inception_lower": "1992-08-01",
    "date:inception_upper": "1992-08-01",
    "iso:country": "GB",
    "wof:name": "DE55 6EX",
    "wof:placetype": "postalcode"
  },
  "geometry": {"coordinates":[-1.409259,53.149436],"type":"Point"}
}
