{
  "type": "Feature",
  "properties": {
    "iso:country": "GB",
    "wof:name": "DE55 6EX",
    "wof:placetype": "postalcode"
  },
  "geometry": {"coordinates":[-1.412536,53.150324],"type":"Point"}
}
