{
  "type": "Feature",
  "properties": {
    "date:inception_lower": "1980-01-01",
    "date:inception_upper": "1980-01-01",
    "iso:country": "GB",
    "wof:name": "SW4 0QY",
    "wof:placetype": "postalcode"
  },
  "geometry": {"coordinates":[-0.145139,51.463557],"type":"Point"}
}
