{
  "type": "Feature",
  "properties": {
    "iso:country":"GB",
    "wof:name":"SW4 0QY",
    "wof:placetype":"postalcode"
},
  "geometry": {"coordinates":[-0.14513938520918,51.46355726431861],"type":"Point"}
}