{
  "type": "Feature",
  "properties": {
    "iso:country":"GB",
    "wof:name":"FY5 4HS",
    "wof:placetype":"postalcode"
},
  "geometry": {"coordinates":[-3.0091742711456,53.88273962782913],"type":"Point"}
}