{
  "type": "Feature",
  "properties": {
    "date:inception_lower": "2004-11-01",
    "date:inception_upper": "2004-11-01",
    "iso:country": "GB",
    "wof:name": "IV8 8NU",
    "wof:placetype": "postalcode"
  },
  "geometry": {"coordinates":[-4.262112,57.548088],"type":"Point"}
}
