{
  "type": "Feature",
  "properties": {
    "iso:country":"GB",
    "wof:name":"IV8 8NU",
    "wof:placetype":"postalcode"
},
  "geometry": {"coordinates":[-4.26211249592649,57.54808848623264],"type":"Point"}
}