{
  "type": "Feature",
  "properties": {
    "iso:country":"GB",
    "wof:name":"SG14 3JN",
    "wof:placetype":"postalcode"
},
  "geometry": {"coordinates":[-0.07319364710463,51.80638393270375],"type":"Point"}
}