{
  "type": "Feature",
  "properties": {
    "iso:country":"GB",
    "wof:name":"CH49 9DB",
    "wof:placetype":"postalcode"
},
  "geometry": {"coordinates":[-3.0895817539311,53.38006319077799],"type":"Point"}
}