{
  "type": "Feature",
  "properties": {
    "date:inception_lower": "1999-06-01",
    "date:inception_upper": "1999-06-01",
    "iso:country": "GB",
    "wof:name": "CH49 9DB",
    "wof:placetype": "postalcode"
  },
  "geometry": {"coordinates":[-3.089582,53.380063],"type":"Point"}
}
