{
  "type": "Feature",
  "properties": {
    "iso:country":"GB",
    "wof:name":"EH13 0BT",
    "wof:placetype":"postalcode"
},
  "geometry": {"coordinates":[-3.24574542679384,55.90474778659372],"type":"Point"}
}