{
  "type": "Feature",
  "properties": {
    "iso:country":"GB",
    "wof:name":"IP14 4JS",
    "wof:placetype":"postalcode"
},
  "geometry": {"coordinates":[0.99975735515673,52.22490901195237],"type":"Point"}
}