{
  "type": "Feature",
  "properties": {
    "iso:country":"GB",
    "wof:name":"LD3 9LP",
    "wof:placetype":"postalcode"
},
  "geometry": {"coordinates":[-3.4252321474188,51.9732069122761],"type":"Point"}
}