{
  "type": "Feature",
  "properties": {
    "iso:country": "GB",
    "wof:name": "LD3 9LP",
    "wof:placetype": "postalcode"
  },
  "geometry": {"coordinates":[-3.425232,51.973207],"type":"Point"}
}
