{
  "type": "Feature",
  "properties": {
    "iso:country":"GB",
    "wof:name":"HG3 2WS",
    "wof:placetype":"postalcode"
},
  "geometry": {"coordinates":[-1.5792643071938,54.00215414236281],"type":"Point"}
}