{
  "type": "Feature",
  "properties": {
    "date:inception_lower":"1980-01-01",
    "date:inception_upper":"1980-01-31",
    "iso:country":"GB",
    "wof:name":"WN3 6RY",
    "wof:placetype":"postalcode"
},
  "geometry": {"coordinates":[-2.656538,53.52473],"type":"Point"}
}