{
  "type": "Feature",
  "properties": {
    "iso:country": "GB",
    "wof:name": "CB11 3QU",
    "wof:placetype": "postalcode"
  },
  "geometry": {"coordinates":[0.208287,51.982344],"type":"Point"}
}
