{
  "type": "Feature",
  "properties": {
    "iso:country": "GB",
    "wof:name": "LL13 9FZ",
    "wof:placetype": "postalcode"
  },
  "geometry": {"coordinates":[-2.933108,53.035286],"type":"Point"}
}
