{
  "type": "Feature",
  "properties": {
    "iso:country":"GB",
    "wof:name":"LL13 9FZ",
    "wof:placetype":"postalcode"
},
  "geometry": {"coordinates":[-2.93310776575247,53.03526961514523],"type":"Point"}
}