{
  "type": "Feature",
  "properties": {
    "iso:country":"GB",
    "wof:name":"GL7 1YE",
    "wof:placetype":"postalcode"
},
  "geometry": {"coordinates":[-1.96312041407403,51.70856741428154],"type":"Point"}
}