{
  "type": "Feature",
  "properties": {
    "iso:country": "GB",
    "wof:name": "GL7 1YE",
    "wof:placetype": "postalcode"
  },
  "geometry": {"coordinates":[-1.963112,51.708572],"type":"Point"}
}
