{
  "type": "Feature",
  "properties": {
    "date:inception_lower":"1980-01-01",
    "date:inception_upper":"1980-01-31",
    "iso:country":"GB",
    "wof:name":"GL7 1YE",
    "wof:placetype":"postalcode"
},
  "geometry": {"coordinates":[-1.963112,51.708572],"type":"Point"}
}