{
  "type": "Feature",
  "properties": {
    "iso:country": "GB",
    "wof:name": "G32 9HH",
    "wof:placetype": "postalcode"
  },
  "geometry": {"coordinates":[-4.15367,55.846628],"type":"Point"}
}
