{
  "type": "Feature",
  "properties": {
    "date:inception_lower":"1980-01-01",
    "date:inception_upper":"1980-01-31",
    "iso:country":"GB",
    "wof:name":"SG5 4NG",
    "wof:placetype":"postalcode"
},
  "geometry": {"coordinates":[-0.224755,52.014072],"type":"Point"}
}