{
  "type": "Feature",
  "properties": {
    "iso:country":"GB",
    "wof:name":"SG5 4NG",
    "wof:placetype":"postalcode"
},
  "geometry": {"coordinates":[-0.22475553656649,52.01407204403134],"type":"Point"}
}