{
  "type": "Feature",
  "properties": {
    "iso:country": "GB",
    "wof:name": "SG5 4NG",
    "wof:placetype": "postalcode"
  },
  "geometry": {"coordinates":[-0.224755,52.014072],"type":"Point"}
}
