{
  "type": "Feature",
  "properties": {
    "iso:country": "GB",
    "wof:name": "E4 9AH",
    "wof:placetype": "postalcode"
  },
  "geometry": {"coordinates":[-0.016543,51.606721],"type":"Point"}
}
