{
  "type": "Feature",
  "properties": {
    "iso:country":"GB",
    "wof:name":"E4 9AH",
    "wof:placetype":"postalcode"
},
  "geometry": {"coordinates":[-0.01656595224855,51.60680932512511],"type":"Point"}
}