{
  "type": "Feature",
  "properties": {
    "iso:country": "GB",
    "wof:name": "LS6 3DY",
    "wof:placetype": "postalcode"
  },
  "geometry": {"coordinates":[-1.589102,53.81773],"type":"Point"}
}
