{
  "type": "Feature",
  "properties": {
    "iso:country":"GB",
    "wof:name":"LS6 3DY",
    "wof:placetype":"postalcode"
},
  "geometry": {"coordinates":[-1.58910204141443,53.81773036908178],"type":"Point"}
}