{
  "type": "Feature",
  "properties": {
    "iso:country":"GB",
    "wof:name":"BB11 3RR",
    "wof:placetype":"postalcode"
},
  "geometry": {"coordinates":[-2.24037780311853,53.77075324781933],"type":"Point"}
}