{
  "type": "Feature",
  "properties": {
    "iso:country": "GB",
    "wof:name": "BB11 3RR",
    "wof:placetype": "postalcode"
  },
  "geometry": {"coordinates":[-2.240378,53.770767],"type":"Point"}
}
