{
  "type": "Feature",
  "properties": {
    "date:inception_lower":"1980-01-01",
    "date:inception_upper":"1980-01-31",
    "iso:country":"GB",
    "wof:name":"SO24 0BG",
    "wof:placetype":"postalcode"
},
  "geometry": {"coordinates":[-1.105678,51.082961],"type":"Point"}
}