{
  "type": "Feature",
  "properties": {
    "iso:country":"GB",
    "wof:name":"SO24 0BG",
    "wof:placetype":"postalcode"
},
  "geometry": {"coordinates":[-1.10567803808108,51.08296126676554],"type":"Point"}
}