{
  "type": "Feature",
  "properties": {
    "iso:country": "GB",
    "wof:name": "SO24 0BG",
    "wof:placetype": "postalcode"
  },
  "geometry": {"coordinates":[-1.105678,51.082961],"type":"Point"}
}
