{
  "type": "Feature",
  "properties": {
    "date:inception_lower": "1991-09-01",
    "date:inception_upper": "1991-09-01",
    "iso:country": "GB",
    "wof:name": "KT8 1RP",
    "wof:placetype": "postalcode"
  },
  "geometry": {"coordinates":[-0.366944,51.40739],"type":"Point"}
}
