{
  "type": "Feature",
  "properties": {
    "date:inception_lower": "1994-12-01",
    "date:inception_upper": "1994-12-01",
    "iso:country": "GB",
    "wof:name": "SO31 7GJ",
    "wof:placetype": "postalcode"
  },
  "geometry": {"coordinates":[-1.268891,50.873313],"type":"Point"}
}
