{
  "type": "Feature",
  "properties": {
    "iso:country":"GB",
    "wof:name":"SO31 7GJ",
    "wof:placetype":"postalcode"
},
  "geometry": {"coordinates":[-1.26925839404294,50.87327051860503],"type":"Point"}
}