{
  "type": "Feature",
  "properties": {
    "iso:country": "GB",
    "wof:name": "RG4 9JJ",
    "wof:placetype": "postalcode"
  },
  "geometry": {"coordinates":[-0.969645,51.504893],"type":"Point"}
}
