{
  "type": "Feature",
  "properties": {
    "date:inception_lower": "2013-07-01",
    "date:inception_upper": "2013-07-01",
    "iso:country": "GB",
    "wof:name": "RG4 9JJ",
    "wof:placetype": "postalcode"
  },
  "geometry": {"coordinates":[-0.969645,51.504893],"type":"Point"}
}
