{
  "type": "Feature",
  "properties": {
    "iso:country":"GB",
    "wof:name":"B32 4JX",
    "wof:placetype":"postalcode"
},
  "geometry": {"coordinates":[-2.01260395892924,52.42863765675513],"type":"Point"}
}