{
  "type": "Feature",
  "properties": {
    "date:inception_lower":"1981-06-01",
    "date:inception_upper":"1981-06-30",
    "iso:country":"GB",
    "wof:name":"B32 4JX",
    "wof:placetype":"postalcode"
},
  "geometry": {"coordinates":[-2.012604,52.428638],"type":"Point"}
}