{
  "type": "Feature",
  "properties": {
    "date:inception_lower": "1993-08-01",
    "date:inception_upper": "1993-08-01",
    "iso:country": "GB",
    "wof:name": "SK8 1JS",
    "wof:placetype": "postalcode"
  },
  "geometry": {"coordinates":[-2.21463,53.386417],"type":"Point"}
}
