{
  "type": "Feature",
  "properties": {
    "iso:country":"GB",
    "wof:name":"DN4 6BU",
    "wof:placetype":"postalcode"
},
  "geometry": {"coordinates":[-1.07393723980242,53.50660857546119],"type":"Point"}
}