{
  "type": "Feature",
  "properties": {
    "iso:country": "GB",
    "wof:name": "UB10 0YE",
    "wof:placetype": "postalcode"
  },
  "geometry": {"coordinates":[-0.470843,51.541941],"type":"Point"}
}
