{
  "type": "Feature",
  "properties": {
    "iso:country":"GB",
    "wof:name":"HA6 2TY",
    "wof:placetype":"postalcode"
},
  "geometry": {"coordinates":[-0.44134236005779,51.60445980841138],"type":"Point"}
}