{
  "type": "Feature",
  "properties": {
    "iso:country":"GB",
    "wof:name":"BR3 3AB",
    "wof:placetype":"postalcode"
},
  "geometry": {"coordinates":[-0.01280556431467,51.39761211698701],"type":"Point"}
}