{
  "type": "Feature",
  "properties": {
    "date:inception_lower": "1980-01-01",
    "date:inception_upper": "1980-01-01",
    "iso:country": "GB",
    "wof:name": "BR3 3AB",
    "wof:placetype": "postalcode"
  },
  "geometry": {"coordinates":[-0.012806,51.397612],"type":"Point"}
}
