{
  "type": "Feature",
  "properties": {
    "iso:country": "GB",
    "wof:name": "PE14 7AH",
    "wof:placetype": "postalcode"
  },
  "geometry": {"coordinates":[0.182779,52.684416],"type":"Point"}
}
