{
  "type": "Feature",
  "properties": {
    "iso:country":"GB",
    "wof:name":"PE14 7AH",
    "wof:placetype":"postalcode"
},
  "geometry": {"coordinates":[0.1827788005813,52.68441581297451],"type":"Point"}
}