{
  "type": "Feature",
  "properties": {
    "iso:country": "GB",
    "wof:name": "CO10 1UN",
    "wof:placetype": "postalcode"
  },
  "geometry": {"coordinates":[0.731197,52.041474],"type":"Point"}
}
