{
  "type": "Feature",
  "properties": {
    "iso:country":"GB",
    "wof:name":"SE9 4SY",
    "wof:placetype":"postalcode"
},
  "geometry": {"coordinates":[0.0536117223429,51.42938977018582],"type":"Point"}
}