{
  "type": "Feature",
  "properties": {
    "iso:country": "GB",
    "wof:name": "SE9 4SY",
    "wof:placetype": "postalcode"
  },
  "geometry": {"coordinates":[0.053612,51.42939],"type":"Point"}
}
