{
  "type": "Feature",
  "properties": {
    "iso:country":"GB",
    "wof:name":"TA8 1JQ",
    "wof:placetype":"postalcode"
},
  "geometry": {"coordinates":[-2.98237776375081,51.22963361126534],"type":"Point"}
}