{
  "type": "Feature",
  "properties": {
    "date:inception_lower": "1995-01-01",
    "date:inception_upper": "1995-01-01",
    "iso:country": "GB",
    "wof:name": "TA8 1JQ",
    "wof:placetype": "postalcode"
  },
  "geometry": {"coordinates":[-2.982358,51.229638],"type":"Point"}
}
