{
  "type": "Feature",
  "properties": {
    "iso:country":"GB",
    "wof:name":"SL5 7RW",
    "wof:placetype":"postalcode"
},
  "geometry": {"coordinates":[-0.64256287729673,51.41937658572514],"type":"Point"}
}