{
  "type": "Feature",
  "properties": {
    "date:inception_lower": "1980-01-01",
    "date:inception_upper": "1980-01-01",
    "iso:country": "GB",
    "wof:name": "SL5 7RW",
    "wof:placetype": "postalcode"
  },
  "geometry": {"coordinates":[-0.642563,51.419377],"type":"Point"}
}
