{
  "type": "Feature",
  "properties": {
    "iso:country":"GB",
    "wof:name":"GU14 7SD",
    "wof:placetype":"postalcode"
},
  "geometry": {"coordinates":[-0.75574704624605,51.29103768449168],"type":"Point"}
}