{
  "type": "Feature",
  "properties": {
    "date:inception_lower": "2022-07-01",
    "date:inception_upper": "2022-07-01",
    "iso:country": "GB",
    "wof:name": "CA12 5FH",
    "wof:placetype": "postalcode"
  },
  "geometry": {"coordinates":[-3.164545,54.603192],"type":"Point"}
}
