{
  "type": "Feature",
  "properties": {
    "iso:country":"GB",
    "wof:name":"PE9 4HH",
    "wof:placetype":"postalcode"
},
  "geometry": {"coordinates":[-0.46768749329015,52.68619467072995],"type":"Point"}
}