{
  "type": "Feature",
  "properties": {
    "iso:country": "GB",
    "wof:name": "PE9 4HH",
    "wof:placetype": "postalcode"
  },
  "geometry": {"coordinates":[-0.467687,52.686195],"type":"Point"}
}
