{
  "type": "Feature",
  "properties": {
    "date:inception_lower": "1980-01-01",
    "date:inception_upper": "1980-01-01",
    "iso:country": "GB",
    "wof:name": "KT22 0TA",
    "wof:placetype": "postalcode"
  },
  "geometry": {"coordinates":[-0.36288,51.336365],"type":"Point"}
}
