{
  "type": "Feature",
  "properties": {
    "date:inception_lower": "1981-06-01",
    "date:inception_upper": "1981-06-01",
    "iso:country": "GB",
    "wof:name": "PO12 3DT",
    "wof:placetype": "postalcode"
  },
  "geometry": {"coordinates":[-1.153885,50.811836],"type":"Point"}
}
