{
  "type": "Feature",
  "properties": {
    "iso:country": "GB",
    "wof:name": "DN15 7US",
    "wof:placetype": "postalcode"
  },
  "geometry": {"coordinates":[-0.688411,53.587785],"type":"Point"}
}
