{
  "type": "Feature",
  "properties": {
    "iso:country":"GB",
    "wof:name":"DN15 7US",
    "wof:placetype":"postalcode"
},
  "geometry": {"coordinates":[-0.68841090270062,53.58778541887867],"type":"Point"}
}