{
  "type": "Feature",
  "properties": {
    "date:inception_lower": "1980-01-01",
    "date:inception_upper": "1980-01-01",
    "iso:country": "GB",
    "wof:name": "CR4 3AU",
    "wof:placetype": "postalcode"
  },
  "geometry": {"coordinates":[-0.170558,51.403913],"type":"Point"}
}
