{
  "type": "Feature",
  "properties": {
    "iso:country":"GB",
    "wof:name":"PO6 1HG",
    "wof:placetype":"postalcode"
},
  "geometry": {"coordinates":[-1.04865085614263,50.84895685111383],"type":"Point"}
}