{
  "type": "Feature",
  "properties": {
    "iso:country":"GB",
    "wof:name":"TR7 1FG",
    "wof:placetype":"postalcode"
},
  "geometry": {"coordinates":[-5.08420739958046,50.41434503802065],"type":"Point"}
}