{
  "type": "Feature",
  "properties": {
    "date:inception_lower":"2008-12-01",
    "date:inception_upper":"2008-12-31",
    "iso:country":"GB",
    "wof:name":"TR7 1FG",
    "wof:placetype":"postalcode"
},
  "geometry": {"coordinates":[-5.084207,50.414345],"type":"Point"}
}