{
  "type": "Feature",
  "properties": {
    "iso:country":"GB",
    "wof:name":"NE24 5TZ",
    "wof:placetype":"postalcode"
},
  "geometry": {"coordinates":[-1.51980922754866,55.12817961936769],"type":"Point"}
}