{
  "type": "Feature",
  "properties": {
    "iso:country": "GB",
    "wof:name": "NE24 5TZ",
    "wof:placetype": "postalcode"
  },
  "geometry": {"coordinates":[-1.519809,55.12818],"type":"Point"}
}
