{
  "type": "Feature",
  "properties": {
    "iso:country":"GB",
    "wof:name":"KA26 9JR",
    "wof:placetype":"postalcode"
},
  "geometry": {"coordinates":[-4.81833938877406,55.29514806657141],"type":"Point"}
}