{
  "type": "Feature",
  "properties": {
    "date:inception_lower": "1980-01-01",
    "date:inception_upper": "1980-01-01",
    "iso:country": "GB",
    "wof:name": "KA26 9JR",
    "wof:placetype": "postalcode"
  },
  "geometry": {"coordinates":[-4.818339,55.295148],"type":"Point"}
}
