{
  "type": "Feature",
  "properties": {
    "iso:country":"GB",
    "wof:name":"EX6 8QR",
    "wof:placetype":"postalcode"
},
  "geometry": {"coordinates":[-3.45153965531505,50.62562585920104],"type":"Point"}
}