{
  "type": "Feature",
  "properties": {
    "iso:country": "GB",
    "wof:name": "EX6 8QR",
    "wof:placetype": "postalcode"
  },
  "geometry": {"coordinates":[-3.45154,50.625626],"type":"Point"}
}
