{
  "type": "Feature",
  "properties": {
    "iso:country":"GB",
    "wof:name":"ME3 9JG",
    "wof:placetype":"postalcode"
},
  "geometry": {"coordinates":[0.56097987227798,51.42755655330069],"type":"Point"}
}