{
  "type": "Feature",
  "properties": {
    "date:inception_lower": "2007-09-01",
    "date:inception_upper": "2007-09-01",
    "iso:country": "GB",
    "wof:name": "ME3 9JG",
    "wof:placetype": "postalcode"
  },
  "geometry": {"coordinates":[0.56098,51.427557],"type":"Point"}
}
