{
  "type": "Feature",
  "properties": {
    "iso:country":"GB",
    "wof:name":"WA2 0XS",
    "wof:placetype":"postalcode"
},
  "geometry": {"coordinates":[-2.54440229107333,53.41648711274278],"type":"Point"}
}