{
  "type": "Feature",
  "properties": {
    "iso:country":"GB",
    "wof:name":"NE61 5HU",
    "wof:placetype":"postalcode"
},
  "geometry": {"coordinates":[-1.5566788953606,55.22582614827065],"type":"Point"}
}