{
  "type": "Feature",
  "properties": {
    "iso:country": "GB",
    "wof:name": "M40 7WA",
    "wof:placetype": "postalcode"
  },
  "geometry": {"coordinates":[-2.215773,53.490869],"type":"Point"}
}
