{
  "type": "Feature",
  "properties": {
    "iso:country":"GB",
    "wof:name":"M40 7WA",
    "wof:placetype":"postalcode"
},
  "geometry": {"coordinates":[-2.21539732305828,53.49053888813929],"type":"Point"}
}