{
  "type": "Feature",
  "properties": {
    "iso:country":"GB",
    "wof:name":"CW5 8NA",
    "wof:placetype":"postalcode"
},
  "geometry": {"coordinates":[-2.57788455269702,53.07778907693895],"type":"Point"}
}