{
  "type": "Feature",
  "properties": {
    "iso:country": "GB",
    "wof:name": "CW5 8NA",
    "wof:placetype": "postalcode"
  },
  "geometry": {"coordinates":[-2.577945,53.077796],"type":"Point"}
}
