{
  "type": "Feature",
  "properties": {
    "iso:country": "GB",
    "wof:name": "EH22 4ND",
    "wof:placetype": "postalcode"
  },
  "geometry": {"coordinates":[-3.068181,55.869244],"type":"Point"}
}
