{
  "type": "Feature",
  "properties": {
    "iso:country": "GB",
    "wof:name": "HU12 0AU",
    "wof:placetype": "postalcode"
  },
  "geometry": {"coordinates":[0.028978,53.68542],"type":"Point"}
}
