{
  "type": "Feature",
  "properties": {
    "date:inception_lower": "2018-02-01",
    "date:inception_upper": "2018-02-01",
    "iso:country": "GB",
    "wof:name": "HU12 0AU",
    "wof:placetype": "postalcode"
  },
  "geometry": {"coordinates":[0.028978,53.68542],"type":"Point"}
}
