{
  "type": "Feature",
  "properties": {
    "iso:country":"GB",
    "wof:name":"TN4 8PY",
    "wof:placetype":"postalcode"
},
  "geometry": {"coordinates":[0.23983267656079,51.13596287803139],"type":"Point"}
}