{
  "type": "Feature",
  "properties": {
    "iso:country": "GB",
    "wof:name": "TN4 8PY",
    "wof:placetype": "postalcode"
  },
  "geometry": {"coordinates":[0.239902,51.135942],"type":"Point"}
}
