{
  "type": "Feature",
  "properties": {
    "date:inception_lower": "1980-01-01",
    "date:inception_upper": "1980-01-01",
    "iso:country": "GB",
    "wof:name": "TN4 8PY",
    "wof:placetype": "postalcode"
  },
  "geometry": {"coordinates":[0.239902,51.135942],"type":"Point"}
}
