{
  "type": "Feature",
  "properties": {
    "iso:country":"GB",
    "wof:name":"B15 1UJ",
    "wof:placetype":"postalcode"
},
  "geometry": {"coordinates":[-1.91057599561064,52.47515498533895],"type":"Point"}
}