{
  "type": "Feature",
  "properties": {
    "date:inception_lower": "2016-01-01",
    "date:inception_upper": "2016-01-01",
    "iso:country": "GB",
    "wof:name": "CB6 2FA",
    "wof:placetype": "postalcode"
  },
  "geometry": {"coordinates":[0.203649,52.384671],"type":"Point"}
}
