{
  "type": "Feature",
  "properties": {
    "iso:country": "GB",
    "wof:name": "NG18 2TA",
    "wof:placetype": "postalcode"
  },
  "geometry": {"coordinates":[-1.192886,53.139779],"type":"Point"}
}
