{
  "type": "Feature",
  "properties": {
    "date:inception_lower": "1980-01-01",
    "date:inception_upper": "1980-01-01",
    "iso:country": "GB",
    "wof:name": "IP13 0NQ",
    "wof:placetype": "postalcode"
  },
  "geometry": {"coordinates":[1.363556,52.141942],"type":"Point"}
}
