{
  "type": "Feature",
  "properties": {
    "iso:country":"GB",
    "wof:name":"IP13 0NQ",
    "wof:placetype":"postalcode"
},
  "geometry": {"coordinates":[1.36332851325218,52.14222814902589],"type":"Point"}
}