{
  "type": "Feature",
  "properties": {
    "iso:country":"GB",
    "wof:name":"S2 1QX",
    "wof:placetype":"postalcode"
},
  "geometry": {"coordinates":[-1.42013949143151,53.37166684436203],"type":"Point"}
}