{
  "type": "Feature",
  "properties": {
    "date:inception_lower": "1980-01-01",
    "date:inception_upper": "1980-01-01",
    "iso:country": "GB",
    "wof:name": "S2 1QX",
    "wof:placetype": "postalcode"
  },
  "geometry": {"coordinates":[-1.419985,53.371945],"type":"Point"}
}
