{
  "type": "Feature",
  "properties": {
    "iso:country":"GB",
    "wof:name":"BH10 7JD",
    "wof:placetype":"postalcode"
},
  "geometry": {"coordinates":[-1.8974647465505,50.76946261692476],"type":"Point"}
}