{
  "type": "Feature",
  "properties": {
    "date:inception_lower": "1980-01-01",
    "date:inception_upper": "1980-01-01",
    "iso:country": "GB",
    "wof:name": "LL17 0RU",
    "wof:placetype": "postalcode"
  },
  "geometry": {"coordinates":[-3.436376,53.252976],"type":"Point"}
}
