{
  "type": "Feature",
  "properties": {
    "iso:country": "GB",
    "wof:name": "DL6 3AL",
    "wof:placetype": "postalcode"
  },
  "geometry": {"coordinates":[-1.292687,54.37872],"type":"Point"}
}
