{
  "type": "Feature",
  "properties": {
    "iso:country":"GB",
    "wof:name":"DL6 3AL",
    "wof:placetype":"postalcode"
},
  "geometry": {"coordinates":[-1.29271839938433,54.37867514930613],"type":"Point"}
}