{
  "type": "Feature",
  "properties": {
    "iso:country":"GB",
    "wof:name":"W4 5DQ",
    "wof:placetype":"postalcode"
},
  "geometry": {"coordinates":[-0.26510285737789,51.49848583494025],"type":"Point"}
}