{
  "type": "Feature",
  "properties": {
    "date:inception_lower": "1994-12-01",
    "date:inception_upper": "1994-12-01",
    "iso:country": "GB",
    "wof:name": "W4 5DQ",
    "wof:placetype": "postalcode"
  },
  "geometry": {"coordinates":[-0.265103,51.498486],"type":"Point"}
}
