{
  "type": "Feature",
  "properties": {
    "iso:country": "GB",
    "wof:name": "FK5 4TH",
    "wof:placetype": "postalcode"
  },
  "geometry": {"coordinates":[-3.798908,56.033099],"type":"Point"}
}
