{
  "type": "Feature",
  "properties": {
    "date:inception_lower": "1980-01-01",
    "date:inception_upper": "1980-01-01",
    "iso:country": "GB",
    "wof:name": "WS15 2RG",
    "wof:placetype": "postalcode"
  },
  "geometry": {"coordinates":[-1.956876,52.76466],"type":"Point"}
}
