{
  "type": "Feature",
  "properties": {
    "date:inception_lower":"1980-01-01",
    "date:inception_upper":"1980-01-31",
    "iso:country":"GB",
    "wof:name":"OL13 9NR",
    "wof:placetype":"postalcode"
},
  "geometry": {"coordinates":[-2.198274,53.699744],"type":"Point"}
}