{
  "type": "Feature",
  "properties": {
    "iso:country":"GB",
    "wof:name":"LL54 6LP",
    "wof:placetype":"postalcode"
},
  "geometry": {"coordinates":[-4.28375361154967,53.05408608713679],"type":"Point"}
}