{
  "type": "Feature",
  "properties": {
    "date:inception_lower":"1980-01-01",
    "date:inception_upper":"1980-01-31",
    "iso:country":"GB",
    "wof:name":"LL54 6LP",
    "wof:placetype":"postalcode"
},
  "geometry": {"coordinates":[-4.283754,53.054086],"type":"Point"}
}