{
  "type": "Feature",
  "properties": {
    "iso:country":"GB",
    "wof:name":"TS26 8PG",
    "wof:placetype":"postalcode"
},
  "geometry": {"coordinates":[-1.21920786885098,54.68707377025777],"type":"Point"}
}