{
  "type": "Feature",
  "properties": {
    "iso:country": "GB",
    "wof:name": "TS26 8PG",
    "wof:placetype": "postalcode"
  },
  "geometry": {"coordinates":[-1.219208,54.687074],"type":"Point"}
}
