{
  "type": "Feature",
  "properties": {
    "date:inception_lower": "2007-08-01",
    "date:inception_upper": "2007-08-01",
    "iso:country": "GB",
    "wof:name": "TS26 8PG",
    "wof:placetype": "postalcode"
  },
  "geometry": {"coordinates":[-1.219207,54.687084],"type":"Point"}
}
