{
  "type": "Feature",
  "properties": {
    "date:inception_lower": "1980-01-01",
    "date:inception_upper": "1980-01-01",
    "iso:country": "GB",
    "wof:name": "BB5 2DU",
    "wof:placetype": "postalcode"
  },
  "geometry": {"coordinates":[-2.320759,53.723051],"type":"Point"}
}
