{
  "type": "Feature",
  "properties": {
    "iso:country":"GB",
    "wof:name":"BB5 2DU",
    "wof:placetype":"postalcode"
},
  "geometry": {"coordinates":[-2.32083545549767,53.72308975898819],"type":"Point"}
}