{
  "type": "Feature",
  "properties": {
    "iso:country":"GB",
    "wof:name":"KA5 6JL",
    "wof:placetype":"postalcode"
},
  "geometry": {"coordinates":[-4.34287080457779,55.54421487262523],"type":"Point"}
}