{
  "type": "Feature",
  "properties": {
    "date:inception_lower": "1980-01-01",
    "date:inception_upper": "1980-01-01",
    "iso:country": "GB",
    "wof:name": "KA5 6JL",
    "wof:placetype": "postalcode"
  },
  "geometry": {"coordinates":[-4.342969,55.544267],"type":"Point"}
}
