{
  "type": "Feature",
  "properties": {
    "date:inception_lower": "1980-01-01",
    "date:inception_upper": "1980-01-01",
    "iso:country": "GB",
    "wof:name": "TR13 8HR",
    "wof:placetype": "postalcode"
  },
  "geometry": {"coordinates":[-5.279563,50.101681],"type":"Point"}
}
