{
  "type": "Feature",
  "properties": {
    "iso:country":"GB",
    "wof:name":"BS16 4LP",
    "wof:placetype":"postalcode"
},
  "geometry": {"coordinates":[-2.51515961024487,51.47950161646131],"type":"Point"}
}