{
  "type": "Feature",
  "properties": {
    "iso:country":"GB",
    "wof:name":"CV6 7GL",
    "wof:placetype":"postalcode"
},
  "geometry": {"coordinates":[-1.48786975875077,52.43390457267949],"type":"Point"}
}