{
  "type": "Feature",
  "properties": {
    "iso:country":"GB",
    "wof:name":"WF8 2DA",
    "wof:placetype":"postalcode"
},
  "geometry": {"coordinates":[-1.2930490564523,53.68499757298328],"type":"Point"}
}