{
  "type": "Feature",
  "properties": {
    "iso:country":"GB",
    "wof:name":"HA7 3EP",
    "wof:placetype":"postalcode"
},
  "geometry": {"coordinates":[-0.3218168126633,51.62447405459785],"type":"Point"}
}