{
  "type": "Feature",
  "properties": {
    "iso:country":"GB",
    "wof:name":"LE9 9QN",
    "wof:placetype":"postalcode"
},
  "geometry": {"coordinates":[-1.29878175781641,52.62861249782432],"type":"Point"}
}