{
  "type": "Feature",
  "properties": {
    "date:inception_lower": "2015-10-01",
    "date:inception_upper": "2015-10-01",
    "iso:country": "GB",
    "wof:name": "LE9 9QN",
    "wof:placetype": "postalcode"
  },
  "geometry": {"coordinates":[-1.298782,52.628612],"type":"Point"}
}
