{
  "type": "Feature",
  "properties": {
    "date:inception_lower": "1980-01-01",
    "date:inception_upper": "1980-01-01",
    "iso:country": "GB",
    "wof:name": "L35 8PJ",
    "wof:placetype": "postalcode"
  },
  "geometry": {"coordinates":[-2.76823,53.420973],"type":"Point"}
}
