{
  "type": "Feature",
  "properties": {
    "date:inception_lower": "2000-06-01",
    "date:inception_upper": "2000-06-01",
    "iso:country": "GB",
    "wof:name": "RG5 4SZ",
    "wof:placetype": "postalcode"
  },
  "geometry": {"coordinates":[-0.894868,51.45295],"type":"Point"}
}
