{
  "type": "Feature",
  "properties": {
    "iso:country":"GB",
    "wof:name":"RG5 4SZ",
    "wof:placetype":"postalcode"
},
  "geometry": {"coordinates":[-0.89486810848635,51.45294979615283],"type":"Point"}
}