{
  "type": "Feature",
  "properties": {
    "iso:country":"GB",
    "wof:name":"YO24 3JF",
    "wof:placetype":"postalcode"
},
  "geometry": {"coordinates":[-1.13224132890236,53.94484253012005],"type":"Point"}
}