{
  "type": "Feature",
  "properties": {
    "date:inception_lower":"1995-07-01",
    "date:inception_upper":"1995-07-31",
    "iso:country":"GB",
    "wof:name":"CF81 9AZ",
    "wof:placetype":"postalcode"
},
  "geometry": {"coordinates":[-3.226706,51.695225],"type":"Point"}
}