{
  "type": "Feature",
  "properties": {
    "iso:country":"GB",
    "wof:name":"CF81 9AZ",
    "wof:placetype":"postalcode"
},
  "geometry": {"coordinates":[-3.22670569123304,51.69522491583375],"type":"Point"}
}