{
  "type": "Feature",
  "properties": {
    "iso:country":"GB",
    "wof:name":"WF8 4JQ",
    "wof:placetype":"postalcode"
},
  "geometry": {"coordinates":[-1.32057941225988,53.68479730445463],"type":"Point"}
}