{
  "type": "Feature",
  "properties": {
    "date:inception_lower": "1995-12-01",
    "date:inception_upper": "1995-12-01",
    "iso:country": "GB",
    "wof:name": "DD2 2JR",
    "wof:placetype": "postalcode"
  },
  "geometry": {"coordinates":[-3.023076,56.46419],"type":"Point"}
}
