{
  "type": "Feature",
  "properties": {
    "iso:country":"GB",
    "wof:name":"SM3 8AW",
    "wof:placetype":"postalcode"
},
  "geometry": {"coordinates":[-0.22075136882331,51.35717809480013],"type":"Point"}
}