{
  "type": "Feature",
  "properties": {
    "iso:country":"GB",
    "wof:name":"TS17 9NT",
    "wof:placetype":"postalcode"
},
  "geometry": {"coordinates":[-1.28689572172368,54.52267874572418],"type":"Point"}
}