{
  "type": "Feature",
  "properties": {
    "date:inception_lower":"1998-12-01",
    "date:inception_upper":"1998-12-31",
    "iso:country":"GB",
    "wof:name":"TS17 9NT",
    "wof:placetype":"postalcode"
},
  "geometry": {"coordinates":[-1.286909,54.52269],"type":"Point"}
}