{
  "type": "Feature",
  "properties": {
    "iso:country": "GB",
    "wof:name": "CB8 0UP",
    "wof:placetype": "postalcode"
  },
  "geometry": {"coordinates":[0.303832,52.174415],"type":"Point"}
}
