{
  "type": "Feature",
  "properties": {
    "iso:country":"GB",
    "wof:name":"CB8 0UP",
    "wof:placetype":"postalcode"
},
  "geometry": {"coordinates":[0.3038323211228,52.17441473771309],"type":"Point"}
}