{
  "type": "Feature",
  "properties": {
    "iso:country":"GB",
    "wof:name":"TS4 3JG",
    "wof:placetype":"postalcode"
},
  "geometry": {"coordinates":[-1.22949412956928,54.54678074063767],"type":"Point"}
}