{
  "type": "Feature",
  "properties": {
    "iso:country":"GB",
    "wof:name":"W4 1PB",
    "wof:placetype":"postalcode"
},
  "geometry": {"coordinates":[-0.26047004528452,51.49264409187046],"type":"Point"}
}