{
  "type": "Feature",
  "properties": {
    "iso:country":"GB",
    "wof:name":"BB2 1JG",
    "wof:placetype":"postalcode"
},
  "geometry": {"coordinates":[-2.48383518031064,53.74760108365928],"type":"Point"}
}