{
  "type": "Feature",
  "properties": {
    "iso:country":"GB",
    "wof:name":"TS25 4NN",
    "wof:placetype":"postalcode"
},
  "geometry": {"coordinates":[-1.24200089884539,54.67011636900774],"type":"Point"}
}