{
  "type": "Feature",
  "properties": {
    "iso:country": "GB",
    "wof:name": "TS25 4NN",
    "wof:placetype": "postalcode"
  },
  "geometry": {"coordinates":[-1.242001,54.670116],"type":"Point"}
}
