{
  "type": "Feature",
  "properties": {
    "iso:country":"GB",
    "wof:name":"OL11 5PX",
    "wof:placetype":"postalcode"
},
  "geometry": {"coordinates":[-2.20443360784039,53.6142916947715],"type":"Point"}
}