{
  "type": "Feature",
  "properties": {
    "iso:country":"GB",
    "wof:name":"N12 8RB",
    "wof:placetype":"postalcode"
},
  "geometry": {"coordinates":[-0.17783952805492,51.62333483051789],"type":"Point"}
}