{
  "type": "Feature",
  "properties": {
    "iso:country": "GB",
    "wof:name": "HP11 2TZ",
    "wof:placetype": "postalcode"
  },
  "geometry": {"coordinates":[-0.763717,51.622099],"type":"Point"}
}
