{
  "type": "Feature",
  "properties": {
    "iso:country": "GB",
    "wof:name": "BA12 7LA",
    "wof:placetype": "postalcode"
  },
  "geometry": {"coordinates":[-2.249349,51.17188],"type":"Point"}
}
