{
  "type": "Feature",
  "properties": {
    "iso:country": "GB",
    "wof:name": "PO5 1PU",
    "wof:placetype": "postalcode"
  },
  "geometry": {"coordinates":[-1.082011,50.790699],"type":"Point"}
}
