{
  "type": "Feature",
  "properties": {
    "iso:country":"GB",
    "wof:name":"PO5 1PU",
    "wof:placetype":"postalcode"
},
  "geometry": {"coordinates":[-1.08201064773847,50.7906991595895],"type":"Point"}
}