{
  "type": "Feature",
  "properties": {
    "date:inception_lower": "1990-02-01",
    "date:inception_upper": "1990-02-01",
    "iso:country": "GB",
    "wof:name": "PO5 1PU",
    "wof:placetype": "postalcode"
  },
  "geometry": {"coordinates":[-1.082011,50.790699],"type":"Point"}
}
