{
  "type": "Feature",
  "properties": {
    "date:inception_lower": "1999-12-01",
    "date:inception_upper": "1999-12-01",
    "iso:country": "GB",
    "wof:name": "CO5 9EF",
    "wof:placetype": "postalcode"
  },
  "geometry": {"coordinates":[0.702784,51.837904],"type":"Point"}
}
