{
  "type": "Feature",
  "properties": {
    "iso:country":"GB",
    "wof:name":"CO5 9EF",
    "wof:placetype":"postalcode"
},
  "geometry": {"coordinates":[0.70278420305302,51.83790353251713],"type":"Point"}
}