{
  "type": "Feature",
  "properties": {
    "iso:country": "GB",
    "wof:name": "S43 3RX",
    "wof:placetype": "postalcode"
  },
  "geometry": {"coordinates":[-1.368809,53.260657],"type":"Point"}
}
