{
  "type": "Feature",
  "properties": {
    "date:inception_lower": "2022-02-01",
    "date:inception_upper": "2022-02-01",
    "iso:country": "GB",
    "wof:name": "BS2 0ND",
    "wof:placetype": "postalcode"
  },
  "geometry": {"coordinates":[-2.585785,51.455305],"type":"Point"}
}
