{
  "type": "Feature",
  "properties": {
    "date:inception_lower": "2015-04-01",
    "date:inception_upper": "2015-04-01",
    "iso:country": "GB",
    "wof:name": "LE2 0GY",
    "wof:placetype": "postalcode"
  },
  "geometry": {"coordinates":[-1.1249,52.631708],"type":"Point"}
}
