{
  "type": "Feature",
  "properties": {
    "iso:country":"GB",
    "wof:name":"LE2 0GY",
    "wof:placetype":"postalcode"
},
  "geometry": {"coordinates":[-1.12490042612175,52.63170841762581],"type":"Point"}
}