{
  "type": "Feature",
  "properties": {
    "date:inception_lower": "1980-01-01",
    "date:inception_upper": "1980-01-01",
    "iso:country": "GB",
    "wof:name": "NE66 2BH",
    "wof:placetype": "postalcode"
  },
  "geometry": {"coordinates":[-1.809582,55.396195],"type":"Point"}
}
