{
  "type": "Feature",
  "properties": {
    "iso:country":"GB",
    "wof:name":"NE66 2BH",
    "wof:placetype":"postalcode"
},
  "geometry": {"coordinates":[-1.80958231229175,55.39619539508481],"type":"Point"}
}