{
  "type": "Feature",
  "properties": {
    "iso:country":"GB",
    "wof:name":"NG5 3DA",
    "wof:placetype":"postalcode"
},
  "geometry": {"coordinates":[-1.14467505477643,52.98531077165961],"type":"Point"}
}