{
  "type": "Feature",
  "properties": {
    "iso:country":"GB",
    "wof:name":"WV8 1YQ",
    "wof:placetype":"postalcode"
},
  "geometry": {"coordinates":[-2.1564349266975,52.61409513533898],"type":"Point"}
}