{
  "type": "Feature",
  "properties": {
    "iso:country": "GB",
    "wof:name": "WV8 1YQ",
    "wof:placetype": "postalcode"
  },
  "geometry": {"coordinates":[-2.156435,52.614095],"type":"Point"}
}
