{
  "type": "Feature",
  "properties": {
    "iso:country": "GB",
    "wof:name": "CF36 5SU",
    "wof:placetype": "postalcode"
  },
  "geometry": {"coordinates":[-3.679781,51.489911],"type":"Point"}
}
