{
  "type": "Feature",
  "properties": {
    "iso:country":"GB",
    "wof:name":"CF36 5SU",
    "wof:placetype":"postalcode"
},
  "geometry": {"coordinates":[-3.67978095124276,51.4899105741702],"type":"Point"}
}