{
  "type": "Feature",
  "properties": {
    "iso:country":"GB",
    "wof:name":"WV13 2QE",
    "wof:placetype":"postalcode"
},
  "geometry": {"coordinates":[-2.04446706223925,52.58145854124029],"type":"Point"}
}