{
  "type": "Feature",
  "properties": {
    "iso:country": "GB",
    "wof:name": "WV13 2QE",
    "wof:placetype": "postalcode"
  },
  "geometry": {"coordinates":[-2.044462,52.581474],"type":"Point"}
}
