{
  "type": "Feature",
  "properties": {
    "date:inception_lower":"2018-07-01",
    "date:inception_upper":"2018-07-31",
    "iso:country":"GB",
    "wof:name":"WV13 2QE",
    "wof:placetype":"postalcode"
},
  "geometry": {"coordinates":[-2.044462,52.581474],"type":"Point"}
}