{
  "type": "Feature",
  "properties": {
    "iso:country":"GB",
    "wof:name":"IP27 0PY",
    "wof:placetype":"postalcode"
},
  "geometry": {"coordinates":[0.61388882199957,52.46353514440195],"type":"Point"}
}