{
  "type": "Feature",
  "properties": {
    "iso:country": "GB",
    "wof:name": "IP27 0PY",
    "wof:placetype": "postalcode"
  },
  "geometry": {"coordinates":[0.613889,52.463535],"type":"Point"}
}
