{
  "type": "Feature",
  "properties": {
    "iso:country":"GB",
    "wof:name":"SW12 9QH",
    "wof:placetype":"postalcode"
},
  "geometry": {"coordinates":[-0.14681511915999,51.44422273608019],"type":"Point"}
}