{
  "type": "Feature",
  "properties": {
    "date:inception_lower": "2003-03-01",
    "date:inception_upper": "2003-03-01",
    "iso:country": "GB",
    "wof:name": "G69 7TL",
    "wof:placetype": "postalcode"
  },
  "geometry": {"coordinates":[-4.071874,55.858197],"type":"Point"}
}
