{
  "type": "Feature",
  "properties": {
    "iso:country":"GB",
    "wof:name":"EH48 2JT",
    "wof:placetype":"postalcode"
},
  "geometry": {"coordinates":[-3.69906435248786,55.89060938386249],"type":"Point"}
}