{
  "type": "Feature",
  "properties": {
    "iso:country": "GB",
    "wof:name": "EH48 2JT",
    "wof:placetype": "postalcode"
  },
  "geometry": {"coordinates":[-3.699064,55.890609],"type":"Point"}
}
