{
  "type": "Feature",
  "properties": {
    "iso:country":"GB",
    "wof:name":"SP1 3GW",
    "wof:placetype":"postalcode"
},
  "geometry": {"coordinates":[-1.78413987537073,51.09121663947309],"type":"Point"}
}