{
  "type": "Feature",
  "properties": {
    "iso:country":"GB",
    "wof:name":"OL3 6AT",
    "wof:placetype":"postalcode"
},
  "geometry": {"coordinates":[-2.00605901498221,53.54848358521424],"type":"Point"}
}