{
  "type": "Feature",
  "properties": {
    "iso:country": "GB",
    "wof:name": "NR4 7TN",
    "wof:placetype": "postalcode"
  },
  "geometry": {"coordinates":[1.227335,52.627565],"type":"Point"}
}
