{
  "type": "Feature",
  "properties": {
    "iso:country":"GB",
    "wof:name":"NR4 7TN",
    "wof:placetype":"postalcode"
},
  "geometry": {"coordinates":[1.2273354142093,52.62756505547182],"type":"Point"}
}