{
  "type": "Feature",
  "properties": {
    "date:inception_lower": "1980-01-01",
    "date:inception_upper": "1980-01-01",
    "iso:country": "GB",
    "wof:name": "NR4 7TN",
    "wof:placetype": "postalcode"
  },
  "geometry": {"coordinates":[1.228017,52.627535],"type":"Point"}
}
