{
  "type": "Feature",
  "properties": {
    "iso:country": "GB",
    "wof:name": "SP8 5DH",
    "wof:placetype": "postalcode"
  },
  "geometry": {"coordinates":[-2.325568,51.075621],"type":"Point"}
}
