{
  "type": "Feature",
  "properties": {
    "iso:country":"GB",
    "wof:name":"CV13 6NU",
    "wof:placetype":"postalcode"
},
  "geometry": {"coordinates":[-1.45502808239445,52.64687411546951],"type":"Point"}
}