{
  "type": "Feature",
  "properties": {
    "iso:country": "GB",
    "wof:name": "CV13 6NU",
    "wof:placetype": "postalcode"
  },
  "geometry": {"coordinates":[-1.455028,52.646874],"type":"Point"}
}
