{
  "type": "Feature",
  "properties": {
    "date:inception_lower": "1980-01-01",
    "date:inception_upper": "1980-01-01",
    "iso:country": "GB",
    "wof:name": "NR25 6AJ",
    "wof:placetype": "postalcode"
  },
  "geometry": {"coordinates":[1.11582,52.912819],"type":"Point"}
}
