{
  "type": "Feature",
  "properties": {
    "iso:country":"GB",
    "wof:name":"GU32 1HB",
    "wof:placetype":"postalcode"
},
  "geometry": {"coordinates":[-1.02905158276712,50.98142779751295],"type":"Point"}
}