{
  "type": "Feature",
  "properties": {
    "date:inception_lower":"1980-01-01",
    "date:inception_upper":"1980-01-31",
    "iso:country":"GB",
    "wof:name":"GU32 1HB",
    "wof:placetype":"postalcode"
},
  "geometry": {"coordinates":[-1.028923,50.981357],"type":"Point"}
}