{
  "type": "Feature",
  "properties": {
    "iso:country": "GB",
    "wof:name": "SO45 5DW",
    "wof:placetype": "postalcode"
  },
  "geometry": {"coordinates":[-1.406311,50.864003],"type":"Point"}
}
