{
  "type": "Feature",
  "properties": {
    "iso:country":"GB",
    "wof:name":"SO45 5DW",
    "wof:placetype":"postalcode"
},
  "geometry": {"coordinates":[-1.40631140251984,50.86400308026413],"type":"Point"}
}