{
  "type": "Feature",
  "properties": {
    "iso:country":"GB",
    "wof:name":"GL56 0GS",
    "wof:placetype":"postalcode"
},
  "geometry": {"coordinates":[-1.68873433516204,51.99367829217007],"type":"Point"}
}