{
  "type": "Feature",
  "properties": {
    "date:inception_lower": "2013-07-01",
    "date:inception_upper": "2013-07-01",
    "iso:country": "GB",
    "wof:name": "GL56 0GS",
    "wof:placetype": "postalcode"
  },
  "geometry": {"coordinates":[-1.688734,51.993678],"type":"Point"}
}
