{
  "type": "Feature",
  "properties": {
    "iso:country": "GB",
    "wof:name": "CB21 4SZ",
    "wof:placetype": "postalcode"
  },
  "geometry": {"coordinates":[0.38169,52.065987],"type":"Point"}
}
