{
  "type": "Feature",
  "properties": {
    "date:inception_lower":"2006-09-01",
    "date:inception_upper":"2006-09-30",
    "iso:country":"GB",
    "wof:name":"CB21 4SZ",
    "wof:placetype":"postalcode"
},
  "geometry": {"coordinates":[0.381673,52.065952],"type":"Point"}
}