{
  "type": "Feature",
  "properties": {
    "iso:country":"GB",
    "wof:name":"CB21 4SZ",
    "wof:placetype":"postalcode"
},
  "geometry": {"coordinates":[0.38165985878302,52.06597579219586],"type":"Point"}
}