{
  "type": "Feature",
  "properties": {
    "iso:country": "GB",
    "wof:name": "CB21 4SZ",
    "wof:placetype": "postalcode"
  },
  "geometry": {"coordinates":[0.381673,52.065952],"type":"Point"}
}
