{
  "type": "Feature",
  "properties": {
    "iso:country":"GB",
    "wof:name":"HP13 5PA",
    "wof:placetype":"postalcode"
},
  "geometry": {"coordinates":[-0.75060933641861,51.63701295047017],"type":"Point"}
}