{
  "type": "Feature",
  "properties": {
    "date:inception_lower": "1980-01-01",
    "date:inception_upper": "1980-01-01",
    "iso:country": "GB",
    "wof:name": "HP13 5PA",
    "wof:placetype": "postalcode"
  },
  "geometry": {"coordinates":[-0.750609,51.637013],"type":"Point"}
}
