{
  "type": "Feature",
  "properties": {
    "iso:country": "GB",
    "wof:name": "EH54 8PJ",
    "wof:placetype": "postalcode"
  },
  "geometry": {"coordinates":[-3.541067,55.904074],"type":"Point"}
}
