{
  "type": "Feature",
  "properties": {
    "iso:country":"GB",
    "wof:name":"EH54 8PJ",
    "wof:placetype":"postalcode"
},
  "geometry": {"coordinates":[-3.5410666570484,55.90407420100108],"type":"Point"}
}