{
  "type": "Feature",
  "properties": {
    "iso:country": "GB",
    "wof:name": "PE29 1GD",
    "wof:placetype": "postalcode"
  },
  "geometry": {"coordinates":[-0.171658,52.344931],"type":"Point"}
}
