{
  "type": "Feature",
  "properties": {
    "iso:country":"GB",
    "wof:name":"PE29 1GD",
    "wof:placetype":"postalcode"
},
  "geometry": {"coordinates":[-0.17165776740151,52.3449311536932],"type":"Point"}
}