{
  "type": "Feature",
  "properties": {
    "iso:country":"GB",
    "wof:name":"YO21 1EZ",
    "wof:placetype":"postalcode"
},
  "geometry": {"coordinates":[-0.61695836317121,54.48471602818552],"type":"Point"}
}