{
  "type": "Feature",
  "properties": {
    "iso:country":"GB",
    "wof:name":"BL0 0BY",
    "wof:placetype":"postalcode"
},
  "geometry": {"coordinates":[-2.30697882189716,53.6454233990121],"type":"Point"}
}