{
  "type": "Feature",
  "properties": {
    "date:inception_lower": "1980-01-01",
    "date:inception_upper": "1980-01-01",
    "iso:country": "GB",
    "wof:name": "CV37 0JA",
    "wof:placetype": "postalcode"
  },
  "geometry": {"coordinates":[-1.730969,52.226961],"type":"Point"}
}
