{
  "type": "Feature",
  "properties": {
    "iso:country":"GB",
    "wof:name":"CV37 0JA",
    "wof:placetype":"postalcode"
},
  "geometry": {"coordinates":[-1.73146739287674,52.22691727790019],"type":"Point"}
}