{
  "type": "Feature",
  "properties": {
    "iso:country":"GB",
    "wof:name":"CM2 8PY",
    "wof:placetype":"postalcode"
},
  "geometry": {"coordinates":[0.46801511810727,51.70142663971079],"type":"Point"}
}