{
  "type": "Feature",
  "properties": {
    "iso:country":"GB",
    "wof:name":"CT17 0PZ",
    "wof:placetype":"postalcode"
},
  "geometry": {"coordinates":[1.2706211859647,51.14458382798806],"type":"Point"}
}