{
  "type": "Feature",
  "properties": {
    "iso:country": "GB",
    "wof:name": "SO53 4NT",
    "wof:placetype": "postalcode"
  },
  "geometry": {"coordinates":[-1.404629,50.987083],"type":"Point"}
}
