{
  "type": "Feature",
  "properties": {
    "iso:country":"GB",
    "wof:name":"SO53 4NT",
    "wof:placetype":"postalcode"
},
  "geometry": {"coordinates":[-1.40462948256689,50.98708319178477],"type":"Point"}
}