{
  "type": "Feature",
  "properties": {
    "iso:country":"GB",
    "wof:name":"LL55 1DG",
    "wof:placetype":"postalcode"
},
  "geometry": {"coordinates":[-4.26026117322257,53.14286217701876],"type":"Point"}
}