{
  "type": "Feature",
  "properties": {
    "date:inception_lower":"1980-01-01",
    "date:inception_upper":"1980-01-31",
    "iso:country":"GB",
    "wof:name":"LL55 1DG",
    "wof:placetype":"postalcode"
},
  "geometry": {"coordinates":[-4.258006,53.142527],"type":"Point"}
}