{
  "type": "Feature",
  "properties": {
    "iso:country":"GB",
    "wof:name":"EH2 3DN",
    "wof:placetype":"postalcode"
},
  "geometry": {"coordinates":[-3.20286977057136,55.95201564907093],"type":"Point"}
}