{
  "type": "Feature",
  "properties": {
    "iso:country":"GB",
    "wof:name":"FK4 1PJ",
    "wof:placetype":"postalcode"
},
  "geometry": {"coordinates":[-3.88592766985824,56.00699594334305],"type":"Point"}
}