{
  "type": "Feature",
  "properties": {
    "iso:country":"GB",
    "wof:name":"B43 5JX",
    "wof:placetype":"postalcode"
},
  "geometry": {"coordinates":[-1.94575304787681,52.54319395632203],"type":"Point"}
}