{
  "type": "Feature",
  "properties": {
    "iso:country": "GB",
    "wof:name": "B43 5JX",
    "wof:placetype": "postalcode"
  },
  "geometry": {"coordinates":[-1.945753,52.543194],"type":"Point"}
}
