{
  "type": "Feature",
  "properties": {
    "iso:country":"GB",
    "wof:name":"ST3 6HE",
    "wof:placetype":"postalcode"
},
  "geometry": {"coordinates":[-2.09343516832705,52.97532307830318],"type":"Point"}
}