{
  "type": "Feature",
  "properties": {
    "iso:country": "GB",
    "wof:name": "SO19 9EF",
    "wof:placetype": "postalcode"
  },
  "geometry": {"coordinates":[-1.380912,50.893897],"type":"Point"}
}
