{
  "type": "Feature",
  "properties": {
    "iso:country":"GB",
    "wof:name":"BA14 7XA",
    "wof:placetype":"postalcode"
},
  "geometry": {"coordinates":[-2.18374361967658,51.31691412915635],"type":"Point"}
}