{
  "type": "Feature",
  "properties": {
    "date:inception_lower": "2014-08-01",
    "date:inception_upper": "2014-08-01",
    "iso:country": "GB",
    "wof:name": "BA14 7XA",
    "wof:placetype": "postalcode"
  },
  "geometry": {"coordinates":[-2.183744,51.316914],"type":"Point"}
}
