{
  "type": "Feature",
  "properties": {
    "iso:country": "GB",
    "wof:name": "BA14 7XA",
    "wof:placetype": "postalcode"
  },
  "geometry": {"coordinates":[-2.183744,51.316914],"type":"Point"}
}
