{
  "type": "Feature",
  "properties": {
    "iso:country": "GB",
    "wof:name": "CT1 1XE",
    "wof:placetype": "postalcode"
  },
  "geometry": {"coordinates":[1.090015,51.285058],"type":"Point"}
}
