{
  "type": "Feature",
  "properties": {
    "iso:country":"GB",
    "wof:name":"CT1 1XE",
    "wof:placetype":"postalcode"
},
  "geometry": {"coordinates":[1.0900148606847,51.28505825351402],"type":"Point"}
}