{
  "type": "Feature",
  "properties": {
    "iso:country":"GB",
    "wof:name":"IP11 7HL",
    "wof:placetype":"postalcode"
},
  "geometry": {"coordinates":[1.35685222745316,51.96409042824657],"type":"Point"}
}