{
  "type": "Feature",
  "properties": {
    "iso:country":"GB",
    "wof:name":"TN31 6HQ",
    "wof:placetype":"postalcode"
},
  "geometry": {"coordinates":[0.60681498293385,50.99005325509946],"type":"Point"}
}