{
  "type": "Feature",
  "properties": {
    "date:inception_lower":"1994-05-01",
    "date:inception_upper":"1994-05-31",
    "iso:country":"GB",
    "wof:name":"TN31 6HQ",
    "wof:placetype":"postalcode"
},
  "geometry": {"coordinates":[0.607329,50.990291],"type":"Point"}
}