{
  "type": "Feature",
  "properties": {
    "iso:country": "GB",
    "wof:name": "TN31 6HQ",
    "wof:placetype": "postalcode"
  },
  "geometry": {"coordinates":[0.607329,50.990291],"type":"Point"}
}
