{
  "type": "Feature",
  "properties": {
    "iso:country":"GB",
    "wof:name":"B38 9HU",
    "wof:placetype":"postalcode"
},
  "geometry": {"coordinates":[-1.92302845976797,52.40050156160017],"type":"Point"}
}