{
  "type": "Feature",
  "properties": {
    "iso:country": "GB",
    "wof:name": "SK23 9TS",
    "wof:placetype": "postalcode"
  },
  "geometry": {"coordinates":[-1.919062,53.32022],"type":"Point"}
}
