{
  "type": "Feature",
  "properties": {
    "iso:country":"GB",
    "wof:name":"SK23 9TS",
    "wof:placetype":"postalcode"
},
  "geometry": {"coordinates":[-1.91906251295032,53.32022036375312],"type":"Point"}
}