{
  "type": "Feature",
  "properties": {
    "date:inception_lower": "2002-08-01",
    "date:inception_upper": "2002-08-01",
    "iso:country": "GB",
    "wof:name": "SK23 9TS",
    "wof:placetype": "postalcode"
  },
  "geometry": {"coordinates":[-1.919076,53.320245],"type":"Point"}
}
