{
  "type": "Feature",
  "properties": {
    "iso:country": "GB",
    "wof:name": "SL6 8LP",
    "wof:placetype": "postalcode"
  },
  "geometry": {"coordinates":[-0.714159,51.524743],"type":"Point"}
}
