{
  "type": "Feature",
  "properties": {
    "date:inception_lower":"2012-02-01",
    "date:inception_upper":"2012-02-29",
    "iso:country":"GB",
    "wof:name":"NE67 5DD",
    "wof:placetype":"postalcode"
},
  "geometry": {"coordinates":[-1.635507,55.555096],"type":"Point"}
}