{
  "type": "Feature",
  "properties": {
    "iso:country":"GB",
    "wof:name":"NE67 5DD",
    "wof:placetype":"postalcode"
},
  "geometry": {"coordinates":[-1.63550714529824,55.555096072604],"type":"Point"}
}