{
  "type": "Feature",
  "properties": {
    "iso:country":"GB",
    "wof:name":"SE26 5RY",
    "wof:placetype":"postalcode"
},
  "geometry": {"coordinates":[-0.04192873761207,51.42492782081141],"type":"Point"}
}