{
  "type": "Feature",
  "properties": {
    "iso:country": "GB",
    "wof:name": "YO14 9PQ",
    "wof:placetype": "postalcode"
  },
  "geometry": {"coordinates":[-0.325599,54.221421],"type":"Point"}
}
