{
  "type": "Feature",
  "properties": {
    "iso:country":"GB",
    "wof:name":"CH2 2LX",
    "wof:placetype":"postalcode"
},
  "geometry": {"coordinates":[-2.86563280729347,53.20735804055467],"type":"Point"}
}