{
  "type": "Feature",
  "properties": {
    "iso:country":"GB",
    "wof:name":"TQ13 7BG",
    "wof:placetype":"postalcode"
},
  "geometry": {"coordinates":[-3.75203547250541,50.51864111025],"type":"Point"}
}