{
  "type": "Feature",
  "properties": {
    "iso:country": "GB",
    "wof:name": "G41 2QE",
    "wof:placetype": "postalcode"
  },
  "geometry": {"coordinates":[-4.269068,55.837534],"type":"Point"}
}
