{
  "type": "Feature",
  "properties": {
    "date:inception_lower":"2000-12-01",
    "date:inception_upper":"2000-12-31",
    "iso:country":"GB",
    "wof:name":"SE12 0AP",
    "wof:placetype":"postalcode"
},
  "geometry": {"coordinates":[0.020035,51.441512],"type":"Point"}
}