{
  "type": "Feature",
  "properties": {
    "iso:country": "GB",
    "wof:name": "TN8 6QT",
    "wof:placetype": "postalcode"
  },
  "geometry": {"coordinates":[0.047468,51.221849],"type":"Point"}
}
