{
  "type": "Feature",
  "properties": {
    "iso:country":"GB",
    "wof:name":"BN2 5DE",
    "wof:placetype":"postalcode"
},
  "geometry": {"coordinates":[-0.11589814647047,50.82069962613868],"type":"Point"}
}