{
  "type": "Feature",
  "properties": {
    "date:inception_lower": "2002-06-01",
    "date:inception_upper": "2002-06-01",
    "iso:country": "GB",
    "wof:name": "AB38 7BH",
    "wof:placetype": "postalcode"
  },
  "geometry": {"coordinates":[-3.19568,57.532105],"type":"Point"}
}
