{
  "type": "Feature",
  "properties": {
    "iso:country": "GB",
    "wof:name": "AB38 7BH",
    "wof:placetype": "postalcode"
  },
  "geometry": {"coordinates":[-3.19568,57.532105],"type":"Point"}
}
