{
  "type": "Feature",
  "properties": {
    "date:inception_lower": "2023-09-01",
    "date:inception_upper": "2023-09-01",
    "iso:country": "GB",
    "wof:name": "G60 5AX",
    "wof:placetype": "postalcode"
  },
  "geometry": {"coordinates":[-4.451225,55.917439],"type":"Point"}
}
