{
  "type": "Feature",
  "properties": {
    "iso:country":"GB",
    "wof:name":"IP14 3HY",
    "wof:placetype":"postalcode"
},
  "geometry": {"coordinates":[0.9444148704844,52.20276809969865],"type":"Point"}
}