{
  "type": "Feature",
  "properties": {
    "date:inception_lower": "2021-03-01",
    "date:inception_upper": "2021-03-01",
    "iso:country": "GB",
    "wof:name": "PL4 6AR",
    "wof:placetype": "postalcode"
  },
  "geometry": {"coordinates":[-4.139057,50.380571],"type":"Point"}
}
