{
  "type": "Feature",
  "properties": {
    "date:inception_lower": "1980-01-01",
    "date:inception_upper": "1980-01-01",
    "iso:country": "GB",
    "wof:name": "IP3 8AB",
    "wof:placetype": "postalcode"
  },
  "geometry": {"coordinates":[1.167955,52.051396],"type":"Point"}
}
