{
  "type": "Feature",
  "properties": {
    "iso:country":"GB",
    "wof:name":"HA8 8PB",
    "wof:placetype":"postalcode"
},
  "geometry": {"coordinates":[-0.27142050659185,51.62118908213836],"type":"Point"}
}