{
  "type": "Feature",
  "properties": {
    "iso:country":"GB",
    "wof:name":"L32 6RH",
    "wof:placetype":"postalcode"
},
  "geometry": {"coordinates":[-2.87386440254911,53.47231908403014],"type":"Point"}
}