{
  "type": "Feature",
  "properties": {
    "iso:country":"GB",
    "wof:name":"CR0 9BG",
    "wof:placetype":"postalcode"
},
  "geometry": {"coordinates":[-0.04228423576857,51.34656154154906],"type":"Point"}
}