{
  "type": "Feature",
  "properties": {
    "date:inception_lower": "2011-03-01",
    "date:inception_upper": "2011-03-01",
    "iso:country": "GB",
    "wof:name": "CR0 9BG",
    "wof:placetype": "postalcode"
  },
  "geometry": {"coordinates":[-0.042284,51.346562],"type":"Point"}
}
