{
  "type": "Feature",
  "properties": {
    "iso:country": "GB",
    "wof:name": "DN36 5JP",
    "wof:placetype": "postalcode"
  },
  "geometry": {"coordinates":[-0.03718,53.479966],"type":"Point"}
}
