{
  "type": "Feature",
  "properties": {
    "iso:country":"GB",
    "wof:name":"DN36 5JP",
    "wof:placetype":"postalcode"
},
  "geometry": {"coordinates":[-0.03718041180398,53.47996648961193],"type":"Point"}
}