{
  "type": "Feature",
  "properties": {
    "iso:country":"GB",
    "wof:name":"SE16 4BS",
    "wof:placetype":"postalcode"
},
  "geometry": {"coordinates":[-0.06953473665297,51.49787561916885],"type":"Point"}
}