{
  "type": "Feature",
  "properties": {
    "iso:country":"GB",
    "wof:name":"M28 1UN",
    "wof:placetype":"postalcode"
},
  "geometry": {"coordinates":[-2.42571910693848,53.49899881484803],"type":"Point"}
}