{
  "type": "Feature",
  "properties": {
    "date:inception_lower": "2004-02-01",
    "date:inception_upper": "2004-02-01",
    "iso:country": "GB",
    "wof:name": "NW9 5AW",
    "wof:placetype": "postalcode"
  },
  "geometry": {"coordinates":[-0.2509,51.600338],"type":"Point"}
}
