{
  "type": "Feature",
  "properties": {
    "iso:country":"GB",
    "wof:name":"NW9 5AW",
    "wof:placetype":"postalcode"
},
  "geometry": {"coordinates":[-0.25089983227989,51.60033785773751],"type":"Point"}
}