{
  "type": "Feature",
  "properties": {
    "iso:country":"GB",
    "wof:name":"ML5 4QN",
    "wof:placetype":"postalcode"
},
  "geometry": {"coordinates":[-4.00544344701194,55.85588336073889],"type":"Point"}
}