{
  "type": "Feature",
  "properties": {
    "iso:country":"GB",
    "wof:name":"OL15 0AR",
    "wof:placetype":"postalcode"
},
  "geometry": {"coordinates":[-2.07132684041613,53.62505142872422],"type":"Point"}
}