{
  "type": "Feature",
  "properties": {
    "iso:country": "GB",
    "wof:name": "PL3 4NQ",
    "wof:placetype": "postalcode"
  },
  "geometry": {"coordinates":[-4.141871,50.391857],"type":"Point"}
}
