{
  "type": "Feature",
  "properties": {
    "iso:country":"GB",
    "wof:name":"PL8 1LR",
    "wof:placetype":"postalcode"
},
  "geometry": {"coordinates":[-3.94820399174333,50.33549649283835],"type":"Point"}
}