{
  "type": "Feature",
  "properties": {
    "iso:country": "GB",
    "wof:name": "PL8 1LR",
    "wof:placetype": "postalcode"
  },
  "geometry": {"coordinates":[-3.948204,50.335496],"type":"Point"}
}
