{
  "type": "Feature",
  "properties": {
    "iso:country":"GB",
    "wof:name":"NR12 9DG",
    "wof:placetype":"postalcode"
},
  "geometry": {"coordinates":[1.51752363576124,52.77186341760959],"type":"Point"}
}