{
  "type": "Feature",
  "properties": {
    "iso:country": "GB",
    "wof:name": "SN14 6HB",
    "wof:placetype": "postalcode"
  },
  "geometry": {"coordinates":[-2.147421,51.533726],"type":"Point"}
}
