{
  "type": "Feature",
  "properties": {
    "iso:country":"GB",
    "wof:name":"SN14 6HB",
    "wof:placetype":"postalcode"
},
  "geometry": {"coordinates":[-2.14742106304248,51.53372571614782],"type":"Point"}
}