{
  "type": "Feature",
  "properties": {
    "iso:country": "GB",
    "wof:name": "B94 5SB",
    "wof:placetype": "postalcode"
  },
  "geometry": {"coordinates":[-1.842968,52.359805],"type":"Point"}
}
