{
  "type": "Feature",
  "properties": {
    "iso:country":"GB",
    "wof:name":"B94 5SB",
    "wof:placetype":"postalcode"
},
  "geometry": {"coordinates":[-1.84296768567529,52.35980515143945],"type":"Point"}
}