{
  "type": "Feature",
  "properties": {
    "iso:country": "GB",
    "wof:name": "SN14 7DE",
    "wof:placetype": "postalcode"
  },
  "geometry": {"coordinates":[-2.19873,51.460783],"type":"Point"}
}
