{
  "type": "Feature",
  "properties": {
    "iso:country":"GB",
    "wof:name":"SN14 7DE",
    "wof:placetype":"postalcode"
},
  "geometry": {"coordinates":[-2.19872978641211,51.46078295965786],"type":"Point"}
}