{
  "type": "Feature",
  "properties": {
    "iso:country":"GB",
    "wof:name":"W5 1DL",
    "wof:placetype":"postalcode"
},
  "geometry": {"coordinates":[-0.29299614031511,51.53007156459634],"type":"Point"}
}