{
  "type": "Feature",
  "properties": {
    "iso:country":"GB",
    "wof:name":"E17 3DS",
    "wof:placetype":"postalcode"
},
  "geometry": {"coordinates":[-0.01060358508074,51.58858843734021],"type":"Point"}
}