{
  "type": "Feature",
  "properties": {
    "iso:country": "GB",
    "wof:name": "DL9 3LL",
    "wof:placetype": "postalcode"
  },
  "geometry": {"coordinates":[-1.731434,54.372763],"type":"Point"}
}
