{
  "type": "Feature",
  "properties": {
    "iso:country":"GB",
    "wof:name":"NW4 1PD",
    "wof:placetype":"postalcode"
},
  "geometry": {"coordinates":[-0.218473397504,51.59653201716054],"type":"Point"}
}