{
  "type": "Feature",
  "properties": {
    "date:inception_lower": "1980-01-01",
    "date:inception_upper": "1980-01-01",
    "iso:country": "GB",
    "wof:name": "NW4 1PD",
    "wof:placetype": "postalcode"
  },
  "geometry": {"coordinates":[-0.218688,51.596674],"type":"Point"}
}
