{
  "type": "Feature",
  "properties": {
    "iso:country": "GB",
    "wof:name": "DE4 3JD",
    "wof:placetype": "postalcode"
  },
  "geometry": {"coordinates":[-1.559525,53.145581],"type":"Point"}
}
