{
  "type": "Feature",
  "properties": {
    "iso:country":"GB",
    "wof:name":"UB10 9BB",
    "wof:placetype":"postalcode"
},
  "geometry": {"coordinates":[-0.4459742671944,51.544049355446],"type":"Point"}
}