{
  "type": "Feature",
  "properties": {
    "date:inception_lower": "2021-02-01",
    "date:inception_upper": "2021-02-01",
    "iso:country": "GB",
    "wof:name": "SK17 8FR",
    "wof:placetype": "postalcode"
  },
  "geometry": {"coordinates":[-1.872315,53.284762],"type":"Point"}
}
