{
  "type": "Feature",
  "properties": {
    "date:inception_lower":"1980-01-01",
    "date:inception_upper":"1980-01-31",
    "iso:country":"GB",
    "wof:name":"SG10 6HT",
    "wof:placetype":"postalcode"
},
  "geometry": {"coordinates":[0.06994,51.862842],"type":"Point"}
}