{
  "type": "Feature",
  "properties": {
    "iso:country": "GB",
    "wof:name": "SG10 6HT",
    "wof:placetype": "postalcode"
  },
  "geometry": {"coordinates":[0.06994,51.862842],"type":"Point"}
}
