{
  "type": "Feature",
  "properties": {
    "iso:country":"GB",
    "wof:name":"SG10 6HT",
    "wof:placetype":"postalcode"
},
  "geometry": {"coordinates":[0.06993954869326,51.86284179320896],"type":"Point"}
}