{
  "type": "Feature",
  "properties": {
    "iso:country": "GB",
    "wof:name": "HP4 3HN",
    "wof:placetype": "postalcode"
  },
  "geometry": {"coordinates":[-0.590514,51.770364],"type":"Point"}
}
