{
  "type": "Feature",
  "properties": {
    "iso:country":"GB",
    "wof:name":"SS9 5TR",
    "wof:placetype":"postalcode"
},
  "geometry": {"coordinates":[0.66535120265804,51.56673476374478],"type":"Point"}
}