{
  "type": "Feature",
  "properties": {
    "iso:country": "GB",
    "wof:name": "L1 5EN",
    "wof:placetype": "postalcode"
  },
  "geometry": {"coordinates":[-2.978494,53.400153],"type":"Point"}
}
