{
  "type": "Feature",
  "properties": {
    "date:inception_lower":"2019-04-01",
    "date:inception_upper":"2019-04-30",
    "iso:country":"GB",
    "wof:name":"L1 5EN",
    "wof:placetype":"postalcode"
},
  "geometry": {"coordinates":[-2.978494,53.400153],"type":"Point"}
}