{
  "type": "Feature",
  "properties": {
    "iso:country":"GB",
    "wof:name":"MK17 8SG",
    "wof:placetype":"postalcode"
},
  "geometry": {"coordinates":[-0.65391135908743,52.01807597204923],"type":"Point"}
}