{
  "type": "Feature",
  "properties": {
    "iso:country":"GB",
    "wof:name":"DE7 6AR",
    "wof:placetype":"postalcode"
},
  "geometry": {"coordinates":[-1.41732131198359,53.00109910619508],"type":"Point"}
}