{
  "type": "Feature",
  "properties": {
    "date:inception_lower": "2002-06-01",
    "date:inception_upper": "2002-06-01",
    "iso:country": "GB",
    "wof:name": "DE7 6AR",
    "wof:placetype": "postalcode"
  },
  "geometry": {"coordinates":[-1.417318,53.001118],"type":"Point"}
}
