{
  "type": "Feature",
  "properties": {
    "iso:country":"GB",
    "wof:name":"EN2 8QU",
    "wof:placetype":"postalcode"
},
  "geometry": {"coordinates":[-0.09782655624929,51.65766646629426],"type":"Point"}
}