{
  "type": "Feature",
  "properties": {
    "date:inception_lower": "1980-01-01",
    "date:inception_upper": "1980-01-01",
    "iso:country": "GB",
    "wof:name": "ST1 2BA",
    "wof:placetype": "postalcode"
  },
  "geometry": {"coordinates":[-2.169775,53.025659],"type":"Point"}
}
