{
  "type": "Feature",
  "properties": {
    "iso:country":"GB",
    "wof:name":"SA19 7NY",
    "wof:placetype":"postalcode"
},
  "geometry": {"coordinates":[-4.00800601395834,51.93492644087247],"type":"Point"}
}