{
  "type": "Feature",
  "properties": {
    "date:inception_lower": "2021-04-01",
    "date:inception_upper": "2021-04-01",
    "iso:country": "GB",
    "wof:name": "CA13 0DD",
    "wof:placetype": "postalcode"
  },
  "geometry": {"coordinates":[-3.38314,54.707357],"type":"Point"}
}
