{
  "type": "Feature",
  "properties": {
    "iso:country":"GB",
    "wof:name":"LE67 8LJ",
    "wof:placetype":"postalcode"
},
  "geometry": {"coordinates":[-1.36870656838241,52.75698401402725],"type":"Point"}
}