{
  "type": "Feature",
  "properties": {
    "date:inception_lower":"1992-08-01",
    "date:inception_upper":"1992-08-31",
    "iso:country":"GB",
    "wof:name":"LE67 8LJ",
    "wof:placetype":"postalcode"
},
  "geometry": {"coordinates":[-1.368707,52.756984],"type":"Point"}
}