{
  "type": "Feature",
  "properties": {
    "date:inception_lower": "2023-10-01",
    "date:inception_upper": "2023-10-01",
    "iso:country": "GB",
    "wof:name": "CH4 7GE",
    "wof:placetype": "postalcode"
  },
  "geometry": {"coordinates":[-2.908963,53.16339],"type":"Point"}
}
