{
  "type": "Feature",
  "properties": {
    "iso:country": "GB",
    "wof:name": "LE13 0LQ",
    "wof:placetype": "postalcode"
  },
  "geometry": {"coordinates":[-0.899758,52.770079],"type":"Point"}
}
