{
  "type": "Feature",
  "properties": {
    "iso:country":"GB",
    "wof:name":"LE13 0LQ",
    "wof:placetype":"postalcode"
},
  "geometry": {"coordinates":[-0.89972133696748,52.77001368056764],"type":"Point"}
}