{
  "type": "Feature",
  "properties": {
    "iso:country":"GB",
    "wof:name":"BS11 9ET",
    "wof:placetype":"postalcode"
},
  "geometry": {"coordinates":[-2.69766890574668,51.5024841984835],"type":"Point"}
}