{
  "type": "Feature",
  "properties": {
    "iso:country": "GB",
    "wof:name": "BS11 9ET",
    "wof:placetype": "postalcode"
  },
  "geometry": {"coordinates":[-2.697669,51.502484],"type":"Point"}
}
