{
  "type": "Feature",
  "properties": {
    "iso:country": "GB",
    "wof:name": "N17 0SQ",
    "wof:placetype": "postalcode"
  },
  "geometry": {"coordinates":[-0.054131,51.608537],"type":"Point"}
}
