{
  "type": "Feature",
  "properties": {
    "iso:country":"GB",
    "wof:name":"N17 0SQ",
    "wof:placetype":"postalcode"
},
  "geometry": {"coordinates":[-0.05415652487327,51.60853561107525],"type":"Point"}
}