{
  "type": "Feature",
  "properties": {
    "iso:country":"GB",
    "wof:name":"N2 9PT",
    "wof:placetype":"postalcode"
},
  "geometry": {"coordinates":[-0.1617926012403,51.5889227105075],"type":"Point"}
}