{
  "type": "Feature",
  "properties": {
    "date:inception_lower": "1980-01-01",
    "date:inception_upper": "1980-01-01",
    "iso:country": "GB",
    "wof:name": "N2 9PT",
    "wof:placetype": "postalcode"
  },
  "geometry": {"coordinates":[-0.161793,51.588923],"type":"Point"}
}
