{
  "type": "Feature",
  "properties": {
    "iso:country":"GB",
    "wof:name":"PO1 3EL",
    "wof:placetype":"postalcode"
},
  "geometry": {"coordinates":[-1.10445517762471,50.7981217549249],"type":"Point"}
}