{
  "type": "Feature",
  "properties": {
    "date:inception_lower": "1980-01-01",
    "date:inception_upper": "1980-01-01",
    "iso:country": "GB",
    "wof:name": "PO1 3EL",
    "wof:placetype": "postalcode"
  },
  "geometry": {"coordinates":[-1.104455,50.798122],"type":"Point"}
}
