{
  "type": "Feature",
  "properties": {
    "iso:country":"GB",
    "wof:name":"SK13 6WE",
    "wof:placetype":"postalcode"
},
  "geometry": {"coordinates":[-1.94931643798433,53.44293118023117],"type":"Point"}
}