{
  "type": "Feature",
  "properties": {
    "iso:country": "GB",
    "wof:name": "HP12 4HJ",
    "wof:placetype": "postalcode"
  },
  "geometry": {"coordinates":[-0.79538,51.631765],"type":"Point"}
}
