{
  "type": "Feature",
  "properties": {
    "iso:country": "GB",
    "wof:name": "OX27 9AJ",
    "wof:placetype": "postalcode"
  },
  "geometry": {"coordinates":[-1.097447,51.941119],"type":"Point"}
}
