{
  "type": "Feature",
  "properties": {
    "date:inception_lower":"2000-10-01",
    "date:inception_upper":"2000-10-31",
    "iso:country":"GB",
    "wof:name":"OX27 9AJ",
    "wof:placetype":"postalcode"
},
  "geometry": {"coordinates":[-1.097447,51.941119],"type":"Point"}
}