{
  "type": "Feature",
  "properties": {
    "iso:country":"GB",
    "wof:name":"G84 7BF",
    "wof:placetype":"postalcode"
},
  "geometry": {"coordinates":[-4.71591521013875,55.9982870688353],"type":"Point"}
}