{
  "type": "Feature",
  "properties": {
    "iso:country": "GB",
    "wof:name": "N15 4DL",
    "wof:placetype": "postalcode"
  },
  "geometry": {"coordinates":[-0.068663,51.585242],"type":"Point"}
}
