{
  "type": "Feature",
  "properties": {
    "iso:country": "GB",
    "wof:name": "PE8 5QN",
    "wof:placetype": "postalcode"
  },
  "geometry": {"coordinates":[-0.374992,52.457997],"type":"Point"}
}
