{
  "type": "Feature",
  "properties": {
    "date:inception_lower": "1994-05-01",
    "date:inception_upper": "1994-05-01",
    "iso:country": "GB",
    "wof:name": "PE8 5QN",
    "wof:placetype": "postalcode"
  },
  "geometry": {"coordinates":[-0.374992,52.457997],"type":"Point"}
}
