{
  "type": "Feature",
  "properties": {
    "date:inception_lower": "1998-12-01",
    "date:inception_upper": "1998-12-01",
    "iso:country": "GB",
    "wof:name": "IV1 3YD",
    "wof:placetype": "postalcode"
  },
  "geometry": {"coordinates":[-4.241759,57.501611],"type":"Point"}
}
