{
  "type": "Feature",
  "properties": {
    "iso:country": "GB",
    "wof:name": "IV1 3YD",
    "wof:placetype": "postalcode"
  },
  "geometry": {"coordinates":[-4.241759,57.501611],"type":"Point"}
}
