{
  "type": "Feature",
  "properties": {
    "iso:country":"GB",
    "wof:name":"IV1 3YD",
    "wof:placetype":"postalcode"
},
  "geometry": {"coordinates":[-4.24175887852937,57.50161087290745],"type":"Point"}
}