{
  "type": "Feature",
  "properties": {
    "date:inception_lower": "2018-11-01",
    "date:inception_upper": "2018-11-01",
    "iso:country": "GB",
    "wof:name": "DE15 9NQ",
    "wof:placetype": "postalcode"
  },
  "geometry": {"coordinates":[-1.633,52.781782],"type":"Point"}
}
