{
  "type": "Feature",
  "properties": {
    "iso:country": "GB",
    "wof:name": "DE15 9NQ",
    "wof:placetype": "postalcode"
  },
  "geometry": {"coordinates":[-1.632851,52.781872],"type":"Point"}
}
