{
  "type": "Feature",
  "properties": {
    "iso:country":"GB",
    "wof:name":"IG3 8EZ",
    "wof:placetype":"postalcode"
},
  "geometry": {"coordinates":[0.09599693260248,51.57140928774794],"type":"Point"}
}