{
  "type": "Feature",
  "properties": {
    "iso:country":"GB",
    "wof:name":"NG31 8PS",
    "wof:placetype":"postalcode"
},
  "geometry": {"coordinates":[-0.66001343121161,52.93530313062432],"type":"Point"}
}