{
  "type": "Feature",
  "properties": {
    "date:inception_lower": "2000-06-01",
    "date:inception_upper": "2000-06-01",
    "iso:country": "GB",
    "wof:name": "NG31 8PS",
    "wof:placetype": "postalcode"
  },
  "geometry": {"coordinates":[-0.660013,52.935303],"type":"Point"}
}
