{
  "type": "Feature",
  "properties": {
    "date:inception_lower": "1980-01-01",
    "date:inception_upper": "1980-01-01",
    "iso:country": "GB",
    "wof:name": "WN5 8AH",
    "wof:placetype": "postalcode"
  },
  "geometry": {"coordinates":[-2.679843,53.53606],"type":"Point"}
}
