{
  "type": "Feature",
  "properties": {
    "iso:country":"GB",
    "wof:name":"WN5 8AH",
    "wof:placetype":"postalcode"
},
  "geometry": {"coordinates":[-2.67984321932919,53.53606045013689],"type":"Point"}
}