{
  "type": "Feature",
  "properties": {
    "iso:country":"GB",
    "wof:name":"BL6 6JW",
    "wof:placetype":"postalcode"
},
  "geometry": {"coordinates":[-2.53627877932838,53.58016892981407],"type":"Point"}
}