{
  "type": "Feature",
  "properties": {
    "date:inception_lower":"1996-12-01",
    "date:inception_upper":"1996-12-31",
    "iso:country":"GB",
    "wof:name":"BL6 6JW",
    "wof:placetype":"postalcode"
},
  "geometry": {"coordinates":[-2.536279,53.580169],"type":"Point"}
}