{
  "type": "Feature",
  "properties": {
    "iso:country":"GB",
    "wof:name":"M24 1LQ",
    "wof:placetype":"postalcode"
},
  "geometry": {"coordinates":[-2.19484407461605,53.54080136568851],"type":"Point"}
}