{
  "type": "Feature",
  "properties": {
    "date:inception_lower": "1980-01-01",
    "date:inception_upper": "1980-01-01",
    "iso:country": "GB",
    "wof:name": "ST20 0ND",
    "wof:placetype": "postalcode"
  },
  "geometry": {"coordinates":[-2.322231,52.83272],"type":"Point"}
}
