{
  "type": "Feature",
  "properties": {
    "iso:country":"GB",
    "wof:name":"CA4 8RT",
    "wof:placetype":"postalcode"
},
  "geometry": {"coordinates":[-2.81932901273544,54.90420578361742],"type":"Point"}
}