{
  "type": "Feature",
  "properties": {
    "date:inception_lower": "1991-09-01",
    "date:inception_upper": "1991-09-01",
    "iso:country": "GB",
    "wof:name": "CA4 8RT",
    "wof:placetype": "postalcode"
  },
  "geometry": {"coordinates":[-2.819329,54.904206],"type":"Point"}
}
