{
  "type": "Feature",
  "properties": {
    "iso:country": "GB",
    "wof:name": "NE12 6EN",
    "wof:placetype": "postalcode"
  },
  "geometry": {"coordinates":[-1.574255,55.029533],"type":"Point"}
}
