{
  "type": "Feature",
  "properties": {
    "iso:country": "GB",
    "wof:name": "DE11 9AF",
    "wof:placetype": "postalcode"
  },
  "geometry": {"coordinates":[-1.556465,52.768037],"type":"Point"}
}
