{
  "type": "Feature",
  "properties": {
    "iso:country":"GB",
    "wof:name":"YO16 6XL",
    "wof:placetype":"postalcode"
},
  "geometry": {"coordinates":[-0.18586197757711,54.10167160765039],"type":"Point"}
}