{
  "type": "Feature",
  "properties": {
    "date:inception_lower": "1980-01-01",
    "date:inception_upper": "1980-01-01",
    "iso:country": "GB",
    "wof:name": "WV6 0AU",
    "wof:placetype": "postalcode"
  },
  "geometry": {"coordinates":[-2.14452,52.592733],"type":"Point"}
}
