{
  "type": "Feature",
  "properties": {
    "iso:country":"GB",
    "wof:name":"M3 4JL",
    "wof:placetype":"postalcode"
},
  "geometry": {"coordinates":[-2.25487332721493,53.47596276466651],"type":"Point"}
}