{
  "type": "Feature",
  "properties": {
    "iso:country": "GB",
    "wof:name": "M3 4JL",
    "wof:placetype": "postalcode"
  },
  "geometry": {"coordinates":[-2.254873,53.475963],"type":"Point"}
}
