{
  "type": "Feature",
  "properties": {
    "date:inception_lower": "2004-06-01",
    "date:inception_upper": "2004-06-01",
    "iso:country": "GB",
    "wof:name": "M3 4JL",
    "wof:placetype": "postalcode"
  },
  "geometry": {"coordinates":[-2.254873,53.475963],"type":"Point"}
}
