{
  "type": "Feature",
  "properties": {
    "date:inception_lower": "1980-01-01",
    "date:inception_upper": "1980-01-01",
    "iso:country": "GB",
    "wof:name": "MK18 1QR",
    "wof:placetype": "postalcode"
  },
  "geometry": {"coordinates":[-0.975377,52.013991],"type":"Point"}
}
