{
  "type": "Feature",
  "properties": {
    "iso:country":"GB",
    "wof:name":"MK18 1QR",
    "wof:placetype":"postalcode"
},
  "geometry": {"coordinates":[-0.97537698174464,52.0139912170653],"type":"Point"}
}