{
  "type": "Feature",
  "properties": {
    "iso:country":"GB",
    "wof:name":"G22 5NY",
    "wof:placetype":"postalcode"
},
  "geometry": {"coordinates":[-4.26301283433974,55.88036295587831],"type":"Point"}
}