{
  "type": "Feature",
  "properties": {
    "iso:country":"GB",
    "wof:name":"DH1 1AF",
    "wof:placetype":"postalcode"
},
  "geometry": {"coordinates":[-1.52970014178955,54.79009897246687],"type":"Point"}
}