{
  "type": "Feature",
  "properties": {
    "date:inception_lower":"1980-01-01",
    "date:inception_upper":"1980-01-31",
    "iso:country":"GB",
    "wof:name":"NE15 8LB",
    "wof:placetype":"postalcode"
},
  "geometry": {"coordinates":[-1.738915,54.982226],"type":"Point"}
}