{
  "type": "Feature",
  "properties": {
    "date:inception_lower": "1980-01-01",
    "date:inception_upper": "1980-01-01",
    "iso:country": "GB",
    "wof:name": "ST18 0HS",
    "wof:placetype": "postalcode"
  },
  "geometry": {"coordinates":[-2.05279,52.841109],"type":"Point"}
}
