{
  "type": "Feature",
  "properties": {
    "iso:country":"GB",
    "wof:name":"HA3 8LZ",
    "wof:placetype":"postalcode"
},
  "geometry": {"coordinates":[-0.3203473422611,51.59110105564376],"type":"Point"}
}