{
  "type": "Feature",
  "properties": {
    "iso:country":"GB",
    "wof:name":"RH4 1PN",
    "wof:placetype":"postalcode"
},
  "geometry": {"coordinates":[-0.31824381682881,51.24025745192352],"type":"Point"}
}