{
  "type": "Feature",
  "properties": {
    "date:inception_lower":"2005-06-01",
    "date:inception_upper":"2005-06-30",
    "iso:country":"GB",
    "wof:name":"EX13 5JT",
    "wof:placetype":"postalcode"
},
  "geometry": {"coordinates":[-2.994897,50.785442],"type":"Point"}
}