{
  "type": "Feature",
  "properties": {
    "date:inception_lower": "1980-01-01",
    "date:inception_upper": "1980-01-01",
    "iso:country": "GB",
    "wof:name": "G20 7JZ",
    "wof:placetype": "postalcode"
  },
  "geometry": {"coordinates":[-4.265884,55.875852],"type":"Point"}
}
