{
  "type": "Feature",
  "properties": {
    "iso:country":"GB",
    "wof:name":"RG7 2AY",
    "wof:placetype":"postalcode"
},
  "geometry": {"coordinates":[-1.00614149510541,51.37024901750405],"type":"Point"}
}