{
  "type": "Feature",
  "properties": {
    "date:inception_lower": "2024-04-01",
    "date:inception_upper": "2024-04-01",
    "iso:country": "GB",
    "wof:name": "EX5 7JH",
    "wof:placetype": "postalcode"
  },
  "geometry": {"coordinates":[-3.389402,50.75406],"type":"Point"}
}
