{
  "type": "Feature",
  "properties": {
    "iso:country":"GB",
    "wof:name":"TF2 6NS",
    "wof:placetype":"postalcode"
},
  "geometry": {"coordinates":[-2.45193113458321,52.69824404725211],"type":"Point"}
}