{
  "type": "Feature",
  "properties": {
    "iso:country": "GB",
    "wof:name": "TF2 6NS",
    "wof:placetype": "postalcode"
  },
  "geometry": {"coordinates":[-2.451931,52.698244],"type":"Point"}
}
