{
  "type": "Feature",
  "properties": {
    "iso:country":"GB",
    "wof:name":"WF9 2BG",
    "wof:placetype":"postalcode"
},
  "geometry": {"coordinates":[-1.30058174238845,53.5958319967659],"type":"Point"}
}