{
  "type": "Feature",
  "properties": {
    "iso:country":"GB",
    "wof:name":"CV6 1NB",
    "wof:placetype":"postalcode"
},
  "geometry": {"coordinates":[-1.52195495805132,52.41850327179634],"type":"Point"}
}