{
  "type": "Feature",
  "properties": {
    "iso:country":"GB",
    "wof:name":"TA20 4AU",
    "wof:placetype":"postalcode"
},
  "geometry": {"coordinates":[-2.93334802617224,50.88952901091911],"type":"Point"}
}