{
  "type": "Feature",
  "properties": {
    "iso:country":"GB",
    "wof:name":"G11 5AN",
    "wof:placetype":"postalcode"
},
  "geometry": {"coordinates":[-4.31105085770497,55.87538071494566],"type":"Point"}
}