{
  "type": "Feature",
  "properties": {
    "date:inception_lower": "2001-06-01",
    "date:inception_upper": "2001-06-01",
    "iso:country": "GB",
    "wof:name": "GU51 5RX",
    "wof:placetype": "postalcode"
  },
  "geometry": {"coordinates":[-0.856429,51.267622],"type":"Point"}
}
