{
  "type": "Feature",
  "properties": {
    "iso:country":"GB",
    "wof:name":"GU51 5RX",
    "wof:placetype":"postalcode"
},
  "geometry": {"coordinates":[-0.85611692744386,51.26757530470451],"type":"Point"}
}