{
  "type": "Feature",
  "properties": {
    "date:inception_lower":"2001-12-01",
    "date:inception_upper":"2001-12-31",
    "iso:country":"GB",
    "wof:name":"GU51 1DP",
    "wof:placetype":"postalcode"
},
  "geometry": {"coordinates":[-0.85639,51.291794],"type":"Point"}
}