{
  "type": "Feature",
  "properties": {
    "iso:country":"GB",
    "wof:name":"GU51 1DP",
    "wof:placetype":"postalcode"
},
  "geometry": {"coordinates":[-0.8563901673408,51.29179394546368],"type":"Point"}
}