{
  "type": "Feature",
  "properties": {
    "iso:country":"GB",
    "wof:name":"SN15 2QL",
    "wof:placetype":"postalcode"
},
  "geometry": {"coordinates":[-2.09707188582177,51.42281418404709],"type":"Point"}
}