{
  "type": "Feature",
  "properties": {
    "iso:country":"GB",
    "wof:name":"SL9 7PU",
    "wof:placetype":"postalcode"
},
  "geometry": {"coordinates":[-0.56924661861958,51.59046928833165],"type":"Point"}
}