{
  "type": "Feature",
  "properties": {
    "iso:country":"GB",
    "wof:name":"EH48 2BP",
    "wof:placetype":"postalcode"
},
  "geometry": {"coordinates":[-3.66109961326508,55.89878385691522],"type":"Point"}
}