{
  "type": "Feature",
  "properties": {
    "iso:country":"GB",
    "wof:name":"EX5 4BR",
    "wof:placetype":"postalcode"
},
  "geometry": {"coordinates":[-3.50131138016624,50.83761372058972],"type":"Point"}
}