{
  "type": "Feature",
  "properties": {
    "iso:country":"GB",
    "wof:name":"CH4 8QW",
    "wof:placetype":"postalcode"
},
  "geometry": {"coordinates":[-2.93348874579959,53.17426874777609],"type":"Point"}
}