{
  "type": "Feature",
  "properties": {
    "iso:country":"GB",
    "wof:name":"LL34 6EB",
    "wof:placetype":"postalcode"
},
  "geometry": {"coordinates":[-3.92626961761496,53.26478240313084],"type":"Point"}
}