{
  "type": "Feature",
  "properties": {
    "iso:country":"GB",
    "wof:name":"CW8 1RD",
    "wof:placetype":"postalcode"
},
  "geometry": {"coordinates":[-2.55057242519494,53.24174383705276],"type":"Point"}
}