{
  "type": "Feature",
  "properties": {
    "iso:country": "GB",
    "wof:name": "CW8 1RD",
    "wof:placetype": "postalcode"
  },
  "geometry": {"coordinates":[-2.5506,53.241741],"type":"Point"}
}
