{
  "type": "Feature",
  "properties": {
    "iso:country":"GB",
    "wof:name":"ME4 4PJ",
    "wof:placetype":"postalcode"
},
  "geometry": {"coordinates":[0.53134687755894,51.37971627276076],"type":"Point"}
}