{
  "type": "Feature",
  "properties": {
    "iso:country":"GB",
    "wof:name":"CV37 7DH",
    "wof:placetype":"postalcode"
},
  "geometry": {"coordinates":[-1.69635212658491,52.18295005403675],"type":"Point"}
}