{
  "type": "Feature",
  "properties": {
    "date:inception_lower":"2012-10-01",
    "date:inception_upper":"2012-10-31",
    "iso:country":"GB",
    "wof:name":"CV37 7DH",
    "wof:placetype":"postalcode"
},
  "geometry": {"coordinates":[-1.696352,52.18295],"type":"Point"}
}