{
  "type": "Feature",
  "properties": {
    "date:inception_lower": "1980-01-01",
    "date:inception_upper": "1980-01-01",
    "iso:country": "GB",
    "wof:name": "BR2 9QQ",
    "wof:placetype": "postalcode"
  },
  "geometry": {"coordinates":[0.036798,51.39168],"type":"Point"}
}
