{
  "type": "Feature",
  "properties": {
    "iso:country":"GB",
    "wof:name":"BR2 9QQ",
    "wof:placetype":"postalcode"
},
  "geometry": {"coordinates":[0.03677224983825,51.39167981305931],"type":"Point"}
}