{
  "type": "Feature",
  "properties": {
    "iso:country":"GB",
    "wof:name":"OX10 6SP",
    "wof:placetype":"postalcode"
},
  "geometry": {"coordinates":[-1.10958305490441,51.61981832757998],"type":"Point"}
}