{
  "type": "Feature",
  "properties": {
    "date:inception_lower": "2014-11-01",
    "date:inception_upper": "2014-11-01",
    "iso:country": "GB",
    "wof:name": "NN5 6FA",
    "wof:placetype": "postalcode"
  },
  "geometry": {"coordinates":[-0.939262,52.241399],"type":"Point"}
}
