{
  "type": "Feature",
  "properties": {
    "iso:country":"GB",
    "wof:name":"PO22 0JW",
    "wof:placetype":"postalcode"
},
  "geometry": {"coordinates":[-0.6398777951829,50.83338019153157],"type":"Point"}
}