{
  "type": "Feature",
  "properties": {
    "iso:country":"GB",
    "wof:name":"NR7 9QN",
    "wof:placetype":"postalcode"
},
  "geometry": {"coordinates":[1.34148452007787,52.64369809893862],"type":"Point"}
}