{
  "type": "Feature",
  "properties": {
    "iso:country":"GB",
    "wof:name":"AB22 8AJ",
    "wof:placetype":"postalcode"
},
  "geometry": {"coordinates":[-2.1278698717502,57.17775771955159],"type":"Point"}
}