{
  "type": "Feature",
  "properties": {
    "date:inception_lower":"1980-01-01",
    "date:inception_upper":"1980-01-31",
    "iso:country":"GB",
    "wof:name":"CM5 0DU",
    "wof:placetype":"postalcode"
},
  "geometry": {"coordinates":[0.211248,51.757107],"type":"Point"}
}