{
  "type": "Feature",
  "properties": {
    "iso:country": "GB",
    "wof:name": "CM5 0DU",
    "wof:placetype": "postalcode"
  },
  "geometry": {"coordinates":[0.211383,51.757543],"type":"Point"}
}
