{
  "type": "Feature",
  "properties": {
    "iso:country":"GB",
    "wof:name":"CM5 0DU",
    "wof:placetype":"postalcode"
},
  "geometry": {"coordinates":[0.21124813337614,51.75710737055697],"type":"Point"}
}