{
  "type": "Feature",
  "properties": {
    "iso:country":"GB",
    "wof:name":"W12 8TT",
    "wof:placetype":"postalcode"
},
  "geometry": {"coordinates":[-0.2244986841232,51.50342648433587],"type":"Point"}
}