{
  "type": "Feature",
  "properties": {
    "iso:country": "GB",
    "wof:name": "W12 8TT",
    "wof:placetype": "postalcode"
  },
  "geometry": {"coordinates":[-0.224499,51.503426],"type":"Point"}
}
