{
  "type": "Feature",
  "properties": {
    "date:inception_lower":"1990-02-01",
    "date:inception_upper":"1990-02-28",
    "iso:country":"GB",
    "wof:name":"W12 8TT",
    "wof:placetype":"postalcode"
},
  "geometry": {"coordinates":[-0.224499,51.503426],"type":"Point"}
}