{
  "type": "Feature",
  "properties": {
    "iso:country":"GB",
    "wof:name":"DY2 9PP",
    "wof:placetype":"postalcode"
},
  "geometry": {"coordinates":[-2.08110129051979,52.48828594053882],"type":"Point"}
}