{
  "type": "Feature",
  "properties": {
    "iso:country":"GB",
    "wof:name":"OX4 3XS",
    "wof:placetype":"postalcode"
},
  "geometry": {"coordinates":[-1.21822593868936,51.73203097191117],"type":"Point"}
}