{
  "type": "Feature",
  "properties": {
    "iso:country": "GB",
    "wof:name": "OX4 3XS",
    "wof:placetype": "postalcode"
  },
  "geometry": {"coordinates":[-1.218226,51.732031],"type":"Point"}
}
