{
  "type": "Feature",
  "properties": {
    "iso:country":"GB",
    "wof:name":"CF14 1NW",
    "wof:placetype":"postalcode"
},
  "geometry": {"coordinates":[-3.22058909055065,51.50800802813566],"type":"Point"}
}