{
  "type": "Feature",
  "properties": {
    "iso:country":"GB",
    "wof:name":"NR13 5LA",
    "wof:placetype":"postalcode"
},
  "geometry": {"coordinates":[1.4402828130949,52.6209102163243],"type":"Point"}
}