{
  "type": "Feature",
  "properties": {
    "iso:country": "GB",
    "wof:name": "PO30 5DT",
    "wof:placetype": "postalcode"
  },
  "geometry": {"coordinates":[-1.304601,50.696501],"type":"Point"}
}
