{
  "type": "Feature",
  "properties": {
    "date:inception_lower":"1980-01-01",
    "date:inception_upper":"1980-01-31",
    "iso:country":"GB",
    "wof:name":"PO30 5DT",
    "wof:placetype":"postalcode"
},
  "geometry": {"coordinates":[-1.304601,50.696501],"type":"Point"}
}