{
  "type": "Feature",
  "properties": {
    "iso:country":"GB",
    "wof:name":"PA4 0YW",
    "wof:placetype":"postalcode"
},
  "geometry": {"coordinates":[-4.37773392430014,55.8675579881279],"type":"Point"}
}