{
  "type": "Feature",
  "properties": {
    "iso:country":"GB",
    "wof:name":"E2 6QD",
    "wof:placetype":"postalcode"
},
  "geometry": {"coordinates":[-0.06058370769616,51.5298674778095],"type":"Point"}
}