{
  "type": "Feature",
  "properties": {
    "date:inception_lower":"2001-12-01",
    "date:inception_upper":"2001-12-31",
    "iso:country":"GB",
    "wof:name":"E2 6QD",
    "wof:placetype":"postalcode"
},
  "geometry": {"coordinates":[-0.060584,51.529867],"type":"Point"}
}