{
  "type": "Feature",
  "properties": {
    "iso:country": "GB",
    "wof:name": "HP21 8DH",
    "wof:placetype": "postalcode"
  },
  "geometry": {"coordinates":[-0.811516,51.804644],"type":"Point"}
}
