{
  "type": "Feature",
  "properties": {
    "date:inception_lower":"1980-01-01",
    "date:inception_upper":"1980-01-31",
    "iso:country":"GB",
    "wof:name":"HP21 8DH",
    "wof:placetype":"postalcode"
},
  "geometry": {"coordinates":[-0.811516,51.804644],"type":"Point"}
}