{
  "type": "Feature",
  "properties": {
    "iso:country": "GB",
    "wof:name": "DE11 0RX",
    "wof:placetype": "postalcode"
  },
  "geometry": {"coordinates":[-1.577042,52.778217],"type":"Point"}
}
