{
  "type": "Feature",
  "properties": {
    "iso:country":"GB",
    "wof:name":"PR7 4HW",
    "wof:placetype":"postalcode"
},
  "geometry": {"coordinates":[-2.60528095886666,53.60818903752875],"type":"Point"}
}