{
  "type": "Feature",
  "properties": {
    "iso:country":"GB",
    "wof:name":"PE1 3DU",
    "wof:placetype":"postalcode"
},
  "geometry": {"coordinates":[-0.24909277026514,52.59253986463879],"type":"Point"}
}