{
  "type": "Feature",
  "properties": {
    "iso:country": "GB",
    "wof:name": "NR14 8SX",
    "wof:placetype": "postalcode"
  },
  "geometry": {"coordinates":[1.31664,52.612775],"type":"Point"}
}
