{
  "type": "Feature",
  "properties": {
    "date:inception_lower": "1981-06-01",
    "date:inception_upper": "1981-06-01",
    "iso:country": "GB",
    "wof:name": "L37 1XT",
    "wof:placetype": "postalcode"
  },
  "geometry": {"coordinates":[-3.07472,53.562142],"type":"Point"}
}
