{
  "type": "Feature",
  "properties": {
    "iso:country":"GB",
    "wof:name":"L19 0PL",
    "wof:placetype":"postalcode"
},
  "geometry": {"coordinates":[-2.91336252330584,53.35698413353811],"type":"Point"}
}