{
  "type": "Feature",
  "properties": {
    "iso:country": "GB",
    "wof:name": "L19 0PL",
    "wof:placetype": "postalcode"
  },
  "geometry": {"coordinates":[-2.913362,53.356984],"type":"Point"}
}
