{
  "type": "Feature",
  "properties": {
    "iso:country":"GB",
    "wof:name":"LL32 8TB",
    "wof:placetype":"postalcode"
},
  "geometry": {"coordinates":[-3.82770011487619,53.22129436486544],"type":"Point"}
}