{
  "type": "Feature",
  "properties": {
    "date:inception_lower": "1980-01-01",
    "date:inception_upper": "1980-01-01",
    "iso:country": "GB",
    "wof:name": "LL32 8TB",
    "wof:placetype": "postalcode"
  },
  "geometry": {"coordinates":[-3.8277,53.221294],"type":"Point"}
}
