{
  "type": "Feature",
  "properties": {
    "iso:country":"GB",
    "wof:name":"WN2 1HG",
    "wof:placetype":"postalcode"
},
  "geometry": {"coordinates":[-2.59871760265073,53.55448925067527],"type":"Point"}
}