{
  "type": "Feature",
  "properties": {
    "iso:country": "GB",
    "wof:name": "PE10 0FW",
    "wof:placetype": "postalcode"
  },
  "geometry": {"coordinates":[-0.365737,52.757459],"type":"Point"}
}
