{
  "type": "Feature",
  "properties": {
    "date:inception_lower": "2006-05-01",
    "date:inception_upper": "2006-05-01",
    "iso:country": "GB",
    "wof:name": "PE10 0FW",
    "wof:placetype": "postalcode"
  },
  "geometry": {"coordinates":[-0.365741,52.757497],"type":"Point"}
}
