{
  "type": "Feature",
  "properties": {
    "iso:country": "GB",
    "wof:name": "G74 4FQ",
    "wof:placetype": "postalcode"
  },
  "geometry": {"coordinates":[-4.170485,55.778537],"type":"Point"}
}
