{
  "type": "Feature",
  "properties": {
    "iso:country": "GB",
    "wof:name": "PO13 0UH",
    "wof:placetype": "postalcode"
  },
  "geometry": {"coordinates":[-1.174694,50.830348],"type":"Point"}
}
