{
  "type": "Feature",
  "properties": {
    "iso:country":"GB",
    "wof:name":"PO13 0UH",
    "wof:placetype":"postalcode"
},
  "geometry": {"coordinates":[-1.1746937224652,50.83034795001326],"type":"Point"}
}