{
  "type": "Feature",
  "properties": {
    "iso:country": "GB",
    "wof:name": "ML8 5LR",
    "wof:placetype": "postalcode"
  },
  "geometry": {"coordinates":[-3.876836,55.755662],"type":"Point"}
}
