{
  "type": "Feature",
  "properties": {
    "date:inception_lower":"1980-01-01",
    "date:inception_upper":"1980-01-31",
    "iso:country":"GB",
    "wof:name":"TR23 0PR",
    "wof:placetype":"postalcode"
},
  "geometry": {"coordinates":[-6.352647,49.953605],"type":"Point"}
}