{
  "type": "Feature",
  "properties": {
    "iso:country": "GB",
    "wof:name": "TR23 0PR",
    "wof:placetype": "postalcode"
  },
  "geometry": {"coordinates":[-6.352647,49.953605],"type":"Point"}
}
