{
  "type": "Feature",
  "properties": {
    "iso:country":"GB",
    "wof:name":"TR23 0PR",
    "wof:placetype":"postalcode"
},
  "geometry": {"coordinates":[-6.35264664773038,49.95360524311833],"type":"Point"}
}