{
  "type": "Feature",
  "properties": {
    "iso:country":"GB",
    "wof:name":"N1 0PU",
    "wof:placetype":"postalcode"
},
  "geometry": {"coordinates":[-0.10613565123781,51.53385806923006],"type":"Point"}
}