{
  "type": "Feature",
  "properties": {
    "date:inception_lower": "1995-07-01",
    "date:inception_upper": "1995-07-01",
    "iso:country": "GB",
    "wof:name": "HS7 5PQ",
    "wof:placetype": "postalcode"
  },
  "geometry": {"coordinates":[-7.334553,57.411848],"type":"Point"}
}
