{
  "type": "Feature",
  "properties": {
    "iso:country":"GB",
    "wof:name":"HS7 5PQ",
    "wof:placetype":"postalcode"
},
  "geometry": {"coordinates":[-7.33457034213074,57.41188214832985],"type":"Point"}
}