{
  "type": "Feature",
  "properties": {
    "date:inception_lower": "1980-01-01",
    "date:inception_upper": "1980-01-01",
    "iso:country": "GB",
    "wof:name": "G53 6HA",
    "wof:placetype": "postalcode"
  },
  "geometry": {"coordinates":[-4.345628,55.819138],"type":"Point"}
}
