{
  "type": "Feature",
  "properties": {
    "iso:country":"GB",
    "wof:name":"G53 6HA",
    "wof:placetype":"postalcode"
},
  "geometry": {"coordinates":[-4.34562821462156,55.81913752064757],"type":"Point"}
}