{
  "type": "Feature",
  "properties": {
    "iso:country":"GB",
    "wof:name":"EC2A 3HS",
    "wof:placetype":"postalcode"
},
  "geometry": {"coordinates":[-0.08135693553727,51.52477759280647],"type":"Point"}
}