{
  "type": "Feature",
  "properties": {
    "iso:country":"GB",
    "wof:name":"WF17 0LX",
    "wof:placetype":"postalcode"
},
  "geometry": {"coordinates":[-1.62757052748054,53.71711772923767],"type":"Point"}
}