{
  "type": "Feature",
  "properties": {
    "iso:country":"GB",
    "wof:name":"DN37 8JR",
    "wof:placetype":"postalcode"
},
  "geometry": {"coordinates":[-0.28711954197862,53.56226233495849],"type":"Point"}
}