{
  "type": "Feature",
  "properties": {
    "date:inception_lower": "2004-09-01",
    "date:inception_upper": "2004-09-01",
    "iso:country": "GB",
    "wof:name": "DN37 8JR",
    "wof:placetype": "postalcode"
  },
  "geometry": {"coordinates":[-0.287119,53.562262],"type":"Point"}
}
