{
  "type": "Feature",
  "properties": {
    "iso:country": "GB",
    "wof:name": "SK4 2ND",
    "wof:placetype": "postalcode"
  },
  "geometry": {"coordinates":[-2.178545,53.414728],"type":"Point"}
}
