{
  "type": "Feature",
  "properties": {
    "iso:country":"GB",
    "wof:name":"NG12 2BS",
    "wof:placetype":"postalcode"
},
  "geometry": {"coordinates":[-1.0488818346983,52.94519100663413],"type":"Point"}
}