{
  "type": "Feature",
  "properties": {
    "iso:country": "GB",
    "wof:name": "SO20 6BP",
    "wof:placetype": "postalcode"
  },
  "geometry": {"coordinates":[-1.412914,51.161421],"type":"Point"}
}
