{
  "type": "Feature",
  "properties": {
    "iso:country":"GB",
    "wof:name":"SO20 6BP",
    "wof:placetype":"postalcode"
},
  "geometry": {"coordinates":[-1.41291435752289,51.16142131327351],"type":"Point"}
}