{
  "type": "Feature",
  "properties": {
    "iso:country":"GB",
    "wof:name":"NG34 9SG",
    "wof:placetype":"postalcode"
},
  "geometry": {"coordinates":[-0.38648629902067,53.03197360912291],"type":"Point"}
}