{
  "type": "Feature",
  "properties": {
    "date:inception_lower": "1980-01-01",
    "date:inception_upper": "1980-01-01",
    "iso:country": "GB",
    "wof:name": "TA4 2RT",
    "wof:placetype": "postalcode"
  },
  "geometry": {"coordinates":[-3.299275,51.07311],"type":"Point"}
}
