{
  "type": "Feature",
  "properties": {
    "iso:country":"GB",
    "wof:name":"TA4 2RT",
    "wof:placetype":"postalcode"
},
  "geometry": {"coordinates":[-3.2961233313989,51.07363436138458],"type":"Point"}
}