{
  "type": "Feature",
  "properties": {
    "date:inception_lower": "1980-01-01",
    "date:inception_upper": "1980-01-01",
    "iso:country": "GB",
    "wof:name": "OL6 9DE",
    "wof:placetype": "postalcode"
  },
  "geometry": {"coordinates":[-2.059827,53.501963],"type":"Point"}
}
