{
  "type": "Feature",
  "properties": {
    "iso:country":"GB",
    "wof:name":"OL6 9DE",
    "wof:placetype":"postalcode"
},
  "geometry": {"coordinates":[-2.05982752321364,53.5019628378714],"type":"Point"}
}