{
  "type": "Feature",
  "properties": {
    "iso:country": "GB",
    "wof:name": "GU28 0RH",
    "wof:placetype": "postalcode"
  },
  "geometry": {"coordinates":[-0.67417,50.988968],"type":"Point"}
}
