{
  "type": "Feature",
  "properties": {
    "iso:country": "GB",
    "wof:name": "L20 9PF",
    "wof:placetype": "postalcode"
  },
  "geometry": {"coordinates":[-2.978045,53.446792],"type":"Point"}
}
