{
  "type": "Feature",
  "properties": {
    "iso:country":"GB",
    "wof:name":"L20 9PF",
    "wof:placetype":"postalcode"
},
  "geometry": {"coordinates":[-2.978045534834,53.44679224329938],"type":"Point"}
}