{
  "type": "Feature",
  "properties": {
    "date:inception_lower": "2002-09-01",
    "date:inception_upper": "2002-09-01",
    "iso:country": "GB",
    "wof:name": "CM2 6GA",
    "wof:placetype": "postalcode"
  },
  "geometry": {"coordinates":[0.51401,51.74369],"type":"Point"}
}
