{
  "type": "Feature",
  "properties": {
    "iso:country": "GB",
    "wof:name": "CM2 6GA",
    "wof:placetype": "postalcode"
  },
  "geometry": {"coordinates":[0.51401,51.74369],"type":"Point"}
}
