{
  "type": "Feature",
  "properties": {
    "iso:country":"GB",
    "wof:name":"LL12 8AB",
    "wof:placetype":"postalcode"
},
  "geometry": {"coordinates":[-2.98519713568025,53.06656427796098],"type":"Point"}
}