{
  "type": "Feature",
  "properties": {
    "iso:country": "GB",
    "wof:name": "CH4 9BA",
    "wof:placetype": "postalcode"
  },
  "geometry": {"coordinates":[-3.00303,53.144182],"type":"Point"}
}
