{
  "type": "Feature",
  "properties": {
    "iso:country":"GB",
    "wof:name":"CH4 9BA",
    "wof:placetype":"postalcode"
},
  "geometry": {"coordinates":[-3.00303022044291,53.14418244238846],"type":"Point"}
}