{
  "type": "Feature",
  "properties": {
    "date:inception_lower": "2016-08-01",
    "date:inception_upper": "2016-08-01",
    "iso:country": "GB",
    "wof:name": "LL13 9QE",
    "wof:placetype": "postalcode"
  },
  "geometry": {"coordinates":[-2.926991,53.035181],"type":"Point"}
}
