{
  "type": "Feature",
  "properties": {
    "date:inception_lower":"1980-01-01",
    "date:inception_upper":"1980-01-31",
    "iso:country":"GB",
    "wof:name":"WA9 4RG",
    "wof:placetype":"postalcode"
},
  "geometry": {"coordinates":[-2.717843,53.417817],"type":"Point"}
}