{
  "type": "Feature",
  "properties": {
    "date:inception_lower": "2016-12-01",
    "date:inception_upper": "2016-12-01",
    "iso:country": "GB",
    "wof:name": "AB12 3HA",
    "wof:placetype": "postalcode"
  },
  "geometry": {"coordinates":[-2.086303,57.12388],"type":"Point"}
}
