{
  "type": "Feature",
  "properties": {
    "iso:country": "GB",
    "wof:name": "ST1 6TL",
    "wof:placetype": "postalcode"
  },
  "geometry": {"coordinates":[-2.153799,53.03173],"type":"Point"}
}
