{
  "type": "Feature",
  "properties": {
    "iso:country":"GB",
    "wof:name":"ST1 6TL",
    "wof:placetype":"postalcode"
},
  "geometry": {"coordinates":[-2.15379915143191,53.0317301336441],"type":"Point"}
}