{
  "type": "Feature",
  "properties": {
    "date:inception_lower": "1987-10-01",
    "date:inception_upper": "1987-10-01",
    "iso:country": "GB",
    "wof:name": "ST1 6TL",
    "wof:placetype": "postalcode"
  },
  "geometry": {"coordinates":[-2.153799,53.03173],"type":"Point"}
}
