{
  "type": "Feature",
  "properties": {
    "iso:country":"GB",
    "wof:name":"RG14 1UH",
    "wof:placetype":"postalcode"
},
  "geometry": {"coordinates":[-1.33482190484652,51.41241770820076],"type":"Point"}
}