{
  "type": "Feature",
  "properties": {
    "iso:country":"GB",
    "wof:name":"BL1 4RP",
    "wof:placetype":"postalcode"
},
  "geometry": {"coordinates":[-2.45064307839533,53.57759210682483],"type":"Point"}
}