{
  "type": "Feature",
  "properties": {
    "iso:country":"GB",
    "wof:name":"L25 8QL",
    "wof:placetype":"postalcode"
},
  "geometry": {"coordinates":[-2.85866150200265,53.36995681643306],"type":"Point"}
}