{
  "type": "Feature",
  "properties": {
    "iso:country": "GB",
    "wof:name": "L25 8QL",
    "wof:placetype": "postalcode"
  },
  "geometry": {"coordinates":[-2.858661,53.369957],"type":"Point"}
}
