{
  "type": "Feature",
  "properties": {
    "iso:country":"GB",
    "wof:name":"PR26 9HW",
    "wof:placetype":"postalcode"
},
  "geometry": {"coordinates":[-2.77501981156849,53.66890647160017],"type":"Point"}
}