{
  "type": "Feature",
  "properties": {
    "iso:country":"GB",
    "wof:name":"WA3 2RG",
    "wof:placetype":"postalcode"
},
  "geometry": {"coordinates":[-2.58184384715336,53.47321746788027],"type":"Point"}
}