{
  "type": "Feature",
  "properties": {
    "iso:country": "GB",
    "wof:name": "HU16 4AU",
    "wof:placetype": "postalcode"
  },
  "geometry": {"coordinates":[-0.418528,53.780918],"type":"Point"}
}
