{
  "type": "Feature",
  "properties": {
    "iso:country": "GB",
    "wof:name": "NE61 5RG",
    "wof:placetype": "postalcode"
  },
  "geometry": {"coordinates":[-1.609149,55.239138],"type":"Point"}
}
