{
  "type": "Feature",
  "properties": {
    "iso:country":"GB",
    "wof:name":"NE61 5RG",
    "wof:placetype":"postalcode"
},
  "geometry": {"coordinates":[-1.60913568066686,55.23901688608905],"type":"Point"}
}