{
  "type": "Feature",
  "properties": {
    "iso:country":"GB",
    "wof:name":"TR13 9QX",
    "wof:placetype":"postalcode"
},
  "geometry": {"coordinates":[-5.3431491556244,50.12936491527097],"type":"Point"}
}