{
  "type": "Feature",
  "properties": {
    "date:inception_lower":"1980-01-01",
    "date:inception_upper":"1980-01-31",
    "iso:country":"GB",
    "wof:name":"TR13 9QX",
    "wof:placetype":"postalcode"
},
  "geometry": {"coordinates":[-5.343149,50.129365],"type":"Point"}
}