{
  "type": "Feature",
  "properties": {
    "iso:country":"GB",
    "wof:name":"TS4 2RY",
    "wof:placetype":"postalcode"
},
  "geometry": {"coordinates":[-1.23174073813494,54.55885569072581],"type":"Point"}
}