{
  "type": "Feature",
  "properties": {
    "iso:country":"GB",
    "wof:name":"BN11 1TP",
    "wof:placetype":"postalcode"
},
  "geometry": {"coordinates":[-0.37261355030173,50.81139684108116],"type":"Point"}
}