{
  "type": "Feature",
  "properties": {
    "date:inception_lower":"2004-10-01",
    "date:inception_upper":"2004-10-31",
    "iso:country":"GB",
    "wof:name":"BN11 1TP",
    "wof:placetype":"postalcode"
},
  "geometry": {"coordinates":[-0.372614,50.811397],"type":"Point"}
}