{
  "type": "Feature",
  "properties": {
    "iso:country": "GB",
    "wof:name": "BN11 1TP",
    "wof:placetype": "postalcode"
  },
  "geometry": {"coordinates":[-0.372614,50.811397],"type":"Point"}
}
