{
  "type": "Feature",
  "properties": {
    "iso:country": "GB",
    "wof:name": "PE27 3DP",
    "wof:placetype": "postalcode"
  },
  "geometry": {"coordinates":[-0.076612,52.344933],"type":"Point"}
}
