{
  "type": "Feature",
  "properties": {
    "iso:country": "GB",
    "wof:name": "SY1 1SS",
    "wof:placetype": "postalcode"
  },
  "geometry": {"coordinates":[-2.753732,52.707883],"type":"Point"}
}
