{
  "type": "Feature",
  "properties": {
    "iso:country":"GB",
    "wof:name":"SY1 1SS",
    "wof:placetype":"postalcode"
},
  "geometry": {"coordinates":[-2.75373249062176,52.70788316808825],"type":"Point"}
}