{
  "type": "Feature",
  "properties": {
    "iso:country":"GB",
    "wof:name":"NE65 0BH",
    "wof:placetype":"postalcode"
},
  "geometry": {"coordinates":[-1.58031082090832,55.33301169486596],"type":"Point"}
}