{
  "type": "Feature",
  "properties": {
    "iso:country":"GB",
    "wof:name":"WD19 7SW",
    "wof:placetype":"postalcode"
},
  "geometry": {"coordinates":[-0.39393596758375,51.62528492088253],"type":"Point"}
}