{
  "type": "Feature",
  "properties": {
    "iso:country":"GB",
    "wof:name":"EX39 1TS",
    "wof:placetype":"postalcode"
},
  "geometry": {"coordinates":[-4.21858689331663,51.04461503528451],"type":"Point"}
}