{
  "type": "Feature",
  "properties": {
    "date:inception_lower": "1991-01-01",
    "date:inception_upper": "1991-01-01",
    "iso:country": "GB",
    "wof:name": "EX39 1TS",
    "wof:placetype": "postalcode"
  },
  "geometry": {"coordinates":[-4.218587,51.044615],"type":"Point"}
}
