{
  "type": "Feature",
  "properties": {
    "iso:country":"GB",
    "wof:name":"NW3 3LP",
    "wof:placetype":"postalcode"
},
  "geometry": {"coordinates":[-0.15991128957622,51.54472250978608],"type":"Point"}
}