{
  "type": "Feature",
  "properties": {
    "iso:country":"GB",
    "wof:name":"UB8 2XB",
    "wof:placetype":"postalcode"
},
  "geometry": {"coordinates":[-0.48912462681912,51.54050352751367],"type":"Point"}
}