{
  "type": "Feature",
  "properties": {
    "iso:country":"GB",
    "wof:name":"GU1 4PD",
    "wof:placetype":"postalcode"
},
  "geometry": {"coordinates":[-0.57445411425277,51.24291187924567],"type":"Point"}
}