{
  "type": "Feature",
  "properties": {
    "date:inception_lower": "1998-06-01",
    "date:inception_upper": "1998-06-01",
    "iso:country": "GB",
    "wof:name": "YO61 4BQ",
    "wof:placetype": "postalcode"
  },
  "geometry": {"coordinates":[-1.149726,54.206226],"type":"Point"}
}
