{
  "type": "Feature",
  "properties": {
    "iso:country":"GB",
    "wof:name":"YO61 4BQ",
    "wof:placetype":"postalcode"
},
  "geometry": {"coordinates":[-1.14972560642636,54.20622617621781],"type":"Point"}
}