{
  "type": "Feature",
  "properties": {
    "iso:country":"GB",
    "wof:name":"SN10 3AS",
    "wof:placetype":"postalcode"
},
  "geometry": {"coordinates":[-1.9829347071648,51.35145978492508],"type":"Point"}
}