{
  "type": "Feature",
  "properties": {
    "date:inception_lower":"1986-07-01",
    "date:inception_upper":"1986-07-31",
    "iso:country":"GB",
    "wof:name":"NG2 7QL",
    "wof:placetype":"postalcode"
},
  "geometry": {"coordinates":[-1.149568,52.912827],"type":"Point"}
}