{
  "type": "Feature",
  "properties": {
    "iso:country":"GB",
    "wof:name":"NG2 7QL",
    "wof:placetype":"postalcode"
},
  "geometry": {"coordinates":[-1.1495682144138,52.91282746835706],"type":"Point"}
}