{
  "type": "Feature",
  "properties": {
    "date:inception_lower": "1985-04-01",
    "date:inception_upper": "1985-04-01",
    "iso:country": "GB",
    "wof:name": "SA33 4DU",
    "wof:placetype": "postalcode"
  },
  "geometry": {"coordinates":[-4.492326,51.832218],"type":"Point"}
}
