{
  "type": "Feature",
  "properties": {
    "iso:country": "GB",
    "wof:name": "SA33 4DU",
    "wof:placetype": "postalcode"
  },
  "geometry": {"coordinates":[-4.492326,51.832218],"type":"Point"}
}
