{
  "type": "Feature",
  "properties": {
    "iso:country":"GB",
    "wof:name":"DA12 5BL",
    "wof:placetype":"postalcode"
},
  "geometry": {"coordinates":[0.37029436568021,51.41848385764033],"type":"Point"}
}