{
  "type": "Feature",
  "properties": {
    "date:inception_lower": "2015-10-01",
    "date:inception_upper": "2015-10-01",
    "iso:country": "GB",
    "wof:name": "PH2 6GG",
    "wof:placetype": "postalcode"
  },
  "geometry": {"coordinates":[-3.396177,56.41889],"type":"Point"}
}
