{
  "type": "Feature",
  "properties": {
    "iso:country": "GB",
    "wof:name": "PH2 6GG",
    "wof:placetype": "postalcode"
  },
  "geometry": {"coordinates":[-3.396177,56.41889],"type":"Point"}
}
