{
  "type": "Feature",
  "properties": {
    "iso:country": "GB",
    "wof:name": "DL8 2QS",
    "wof:placetype": "postalcode"
  },
  "geometry": {"coordinates":[-1.574815,54.219263],"type":"Point"}
}
