{
  "type": "Feature",
  "properties": {
    "iso:country":"GB",
    "wof:name":"DL8 2QS",
    "wof:placetype":"postalcode"
},
  "geometry": {"coordinates":[-1.57480743139897,54.21925098441006],"type":"Point"}
}