{
  "type": "Feature",
  "properties": {
    "date:inception_lower": "1980-01-01",
    "date:inception_upper": "1980-01-01",
    "iso:country": "GB",
    "wof:name": "DL8 2QS",
    "wof:placetype": "postalcode"
  },
  "geometry": {"coordinates":[-1.574784,54.219317],"type":"Point"}
}
