{
  "type": "Feature",
  "properties": {
    "date:inception_lower": "1980-01-01",
    "date:inception_upper": "1980-01-01",
    "iso:country": "GB",
    "wof:name": "S45 9HR",
    "wof:placetype": "postalcode"
  },
  "geometry": {"coordinates":[-1.405714,53.163737],"type":"Point"}
}
