{
  "type": "Feature",
  "properties": {
    "iso:country":"GB",
    "wof:name":"S45 9HR",
    "wof:placetype":"postalcode"
},
  "geometry": {"coordinates":[-1.40571384745613,53.16373673336755],"type":"Point"}
}