{
  "type": "Feature",
  "properties": {
    "date:inception_lower": "2023-04-01",
    "date:inception_upper": "2023-04-01",
    "iso:country": "GB",
    "wof:name": "SO30 2DH",
    "wof:placetype": "postalcode"
  },
  "geometry": {"coordinates":[-1.24235,50.90344],"type":"Point"}
}
