{
  "type": "Feature",
  "properties": {
    "iso:country":"GB",
    "wof:name":"HA0 2RN",
    "wof:placetype":"postalcode"
},
  "geometry": {"coordinates":[-0.32486070353535,51.55669837639387],"type":"Point"}
}