{
  "type": "Feature",
  "properties": {
    "iso:country":"GB",
    "wof:name":"TQ11 0BG",
    "wof:placetype":"postalcode"
},
  "geometry": {"coordinates":[-3.78368135755955,50.48284158600937],"type":"Point"}
}