{
  "type": "Feature",
  "properties": {
    "iso:country": "GB",
    "wof:name": "TQ11 0BG",
    "wof:placetype": "postalcode"
  },
  "geometry": {"coordinates":[-3.783681,50.482842],"type":"Point"}
}
