{
  "type": "Feature",
  "properties": {
    "date:inception_lower": "2006-03-01",
    "date:inception_upper": "2006-03-01",
    "iso:country": "GB",
    "wof:name": "CF72 9GT",
    "wof:placetype": "postalcode"
  },
  "geometry": {"coordinates":[-3.458233,51.539643],"type":"Point"}
}
