{
  "type": "Feature",
  "properties": {
    "date:inception_lower":"2012-12-01",
    "date:inception_upper":"2012-12-31",
    "iso:country":"GB",
    "wof:name":"SY12 0FJ",
    "wof:placetype":"postalcode"
},
  "geometry": {"coordinates":[-2.898649,52.902829],"type":"Point"}
}