{
  "type": "Feature",
  "properties": {
    "iso:country":"GB",
    "wof:name":"SY12 0FJ",
    "wof:placetype":"postalcode"
},
  "geometry": {"coordinates":[-2.89719679715002,52.90298661322607],"type":"Point"}
}