{
  "type": "Feature",
  "properties": {
    "iso:country":"GB",
    "wof:name":"NE8 2XY",
    "wof:placetype":"postalcode"
},
  "geometry": {"coordinates":[-1.62177081959022,54.95257147600358],"type":"Point"}
}