{
  "type": "Feature",
  "properties": {
    "iso:country": "GB",
    "wof:name": "NE8 2XY",
    "wof:placetype": "postalcode"
  },
  "geometry": {"coordinates":[-1.621771,54.952571],"type":"Point"}
}
