{
  "type": "Feature",
  "properties": {
    "date:inception_lower":"1980-01-01",
    "date:inception_upper":"1980-01-31",
    "iso:country":"GB",
    "wof:name":"LE15 6PW",
    "wof:placetype":"postalcode"
},
  "geometry": {"coordinates":[-0.745842,52.672139],"type":"Point"}
}