{
  "type": "Feature",
  "properties": {
    "iso:country":"GB",
    "wof:name":"LE15 6PW",
    "wof:placetype":"postalcode"
},
  "geometry": {"coordinates":[-0.74584226744925,52.67213944493233],"type":"Point"}
}