{
  "type": "Feature",
  "properties": {
    "date:inception_lower": "2010-04-01",
    "date:inception_upper": "2010-04-01",
    "iso:country": "GB",
    "wof:name": "AL7 1GE",
    "wof:placetype": "postalcode"
  },
  "geometry": {"coordinates":[-0.186323,51.807779],"type":"Point"}
}
