{
  "type": "Feature",
  "properties": {
    "iso:country":"GB",
    "wof:name":"NW5 1AA",
    "wof:placetype":"postalcode"
},
  "geometry": {"coordinates":[-0.14129145706579,51.5521804881766],"type":"Point"}
}