{
  "type": "Feature",
  "properties": {
    "iso:country":"GB",
    "wof:name":"BN15 0DA",
    "wof:placetype":"postalcode"
},
  "geometry": {"coordinates":[-0.3409028432032,50.8346384587316],"type":"Point"}
}