{
  "type": "Feature",
  "properties": {
    "iso:country": "GB",
    "wof:name": "WD23 1FN",
    "wof:placetype": "postalcode"
  },
  "geometry": {"coordinates":[-0.35181,51.638378],"type":"Point"}
}
