{
  "type": "Feature",
  "properties": {
    "iso:country":"GB",
    "wof:name":"WD23 1FN",
    "wof:placetype":"postalcode"
},
  "geometry": {"coordinates":[-0.35181040410624,51.63837811858691],"type":"Point"}
}