{
  "type": "Feature",
  "properties": {
    "date:inception_lower": "2011-09-01",
    "date:inception_upper": "2011-09-01",
    "iso:country": "GB",
    "wof:name": "WD23 1FN",
    "wof:placetype": "postalcode"
  },
  "geometry": {"coordinates":[-0.35181,51.638378],"type":"Point"}
}
