{
  "type": "Feature",
  "properties": {
    "iso:country": "GB",
    "wof:name": "MK6 2RR",
    "wof:placetype": "postalcode"
  },
  "geometry": {"coordinates":[-0.746578,52.03744],"type":"Point"}
}
