{
  "type": "Feature",
  "properties": {
    "iso:country":"GB",
    "wof:name":"MK6 2RR",
    "wof:placetype":"postalcode"
},
  "geometry": {"coordinates":[-0.74657823896792,52.03744021169148],"type":"Point"}
}