{
  "type": "Feature",
  "properties": {
    "iso:country":"GB",
    "wof:name":"SY1 4LD",
    "wof:placetype":"postalcode"
},
  "geometry": {"coordinates":[-2.72587075367417,52.72979436968202],"type":"Point"}
}