{
  "type": "Feature",
  "properties": {
    "date:inception_lower": "2020-09-01",
    "date:inception_upper": "2020-09-01",
    "iso:country": "GB",
    "wof:name": "M25 9AD",
    "wof:placetype": "postalcode"
  },
  "geometry": {"coordinates":[-2.283067,53.515276],"type":"Point"}
}
