{
  "type": "Feature",
  "properties": {
    "iso:country":"GB",
    "wof:name":"LL19 7UG",
    "wof:placetype":"postalcode"
},
  "geometry": {"coordinates":[-3.41998742821853,53.33648748618791],"type":"Point"}
}