{
  "type": "Feature",
  "properties": {
    "iso:country": "GB",
    "wof:name": "DA12 4TL",
    "wof:placetype": "postalcode"
  },
  "geometry": {"coordinates":[0.402287,51.431997],"type":"Point"}
}
