{
  "type": "Feature",
  "properties": {
    "date:inception_lower": "1980-01-01",
    "date:inception_upper": "1980-01-01",
    "iso:country": "GB",
    "wof:name": "HP6 6NH",
    "wof:placetype": "postalcode"
  },
  "geometry": {"coordinates":[-0.596671,51.675819],"type":"Point"}
}
