{
  "type": "Feature",
  "properties": {
    "iso:country":"GB",
    "wof:name":"HP6 6NH",
    "wof:placetype":"postalcode"
},
  "geometry": {"coordinates":[-0.5966705428403,51.67581851214305],"type":"Point"}
}