{
  "type": "Feature",
  "properties": {
    "date:inception_lower": "2024-03-01",
    "date:inception_upper": "2024-03-01",
    "iso:country": "GB",
    "wof:name": "PE11 7AF",
    "wof:placetype": "postalcode"
  },
  "geometry": {"coordinates":[-0.170962,52.763321],"type":"Point"}
}
