{
  "type": "Feature",
  "properties": {
    "iso:country": "GB",
    "wof:name": "SP6 2DL",
    "wof:placetype": "postalcode"
  },
  "geometry": {"coordinates":[-1.761561,50.970679],"type":"Point"}
}
