{
  "type": "Feature",
  "properties": {
    "iso:country":"GB",
    "wof:name":"SP6 2DL",
    "wof:placetype":"postalcode"
},
  "geometry": {"coordinates":[-1.7616154834335,50.97007490292867],"type":"Point"}
}