{
  "type": "Feature",
  "properties": {
    "iso:country": "GB",
    "wof:name": "L39 9ER",
    "wof:placetype": "postalcode"
  },
  "geometry": {"coordinates":[-2.884854,53.528373],"type":"Point"}
}
