{
  "type": "Feature",
  "properties": {
    "date:inception_lower":"1980-01-01",
    "date:inception_upper":"1980-01-31",
    "iso:country":"GB",
    "wof:name":"TA20 2ND",
    "wof:placetype":"postalcode"
},
  "geometry": {"coordinates":[-2.938993,50.859844],"type":"Point"}
}