{
  "type": "Feature",
  "properties": {
    "iso:country":"GB",
    "wof:name":"TA20 2ND",
    "wof:placetype":"postalcode"
},
  "geometry": {"coordinates":[-2.93899257583806,50.85984387006491],"type":"Point"}
}