{
  "type": "Feature",
  "properties": {
    "iso:country": "GB",
    "wof:name": "CM3 1NP",
    "wof:placetype": "postalcode"
  },
  "geometry": {"coordinates":[0.508864,51.831149],"type":"Point"}
}
