{
  "type": "Feature",
  "properties": {
    "iso:country":"GB",
    "wof:name":"CM3 1NP",
    "wof:placetype":"postalcode"
},
  "geometry": {"coordinates":[0.50886428233795,51.83114935654989],"type":"Point"}
}