{
  "type": "Feature",
  "properties": {
    "date:inception_lower": "1980-01-01",
    "date:inception_upper": "1980-01-01",
    "iso:country": "GB",
    "wof:name": "KT23 3LW",
    "wof:placetype": "postalcode"
  },
  "geometry": {"coordinates":[-0.374877,51.288152],"type":"Point"}
}
