{
  "type": "Feature",
  "properties": {
    "iso:country":"GB",
    "wof:name":"DA1 5SR",
    "wof:placetype":"postalcode"
},
  "geometry": {"coordinates":[0.22838983304538,51.44831965283061],"type":"Point"}
}