{
  "type": "Feature",
  "properties": {
    "date:inception_lower": "1983-01-01",
    "date:inception_upper": "1983-01-01",
    "iso:country": "GB",
    "wof:name": "GL2 9PH",
    "wof:placetype": "postalcode"
  },
  "geometry": {"coordinates":[-2.221042,51.900996],"type":"Point"}
}
