{
  "type": "Feature",
  "properties": {
    "iso:country":"GB",
    "wof:name":"GL2 9PH",
    "wof:placetype":"postalcode"
},
  "geometry": {"coordinates":[-2.22057953098596,51.90080017024946],"type":"Point"}
}