{
  "type": "Feature",
  "properties": {
    "iso:country": "GB",
    "wof:name": "GL2 9PH",
    "wof:placetype": "postalcode"
  },
  "geometry": {"coordinates":[-2.220579,51.9008],"type":"Point"}
}
