{
  "type": "Feature",
  "properties": {
    "date:inception_lower": "2007-07-01",
    "date:inception_upper": "2007-07-01",
    "iso:country": "GB",
    "wof:name": "TA18 8RD",
    "wof:placetype": "postalcode"
  },
  "geometry": {"coordinates":[-2.767798,50.872076],"type":"Point"}
}
