{
  "type": "Feature",
  "properties": {
    "date:inception_lower": "1997-06-01",
    "date:inception_upper": "1997-06-01",
    "iso:country": "GB",
    "wof:name": "DN41 8HE",
    "wof:placetype": "postalcode"
  },
  "geometry": {"coordinates":[-0.242304,53.575034],"type":"Point"}
}
