{
  "type": "Feature",
  "properties": {
    "iso:country":"GB",
    "wof:name":"DN41 8HE",
    "wof:placetype":"postalcode"
},
  "geometry": {"coordinates":[-0.24230381087774,53.57503351452223],"type":"Point"}
}