{
  "type": "Feature",
  "properties": {
    "iso:country": "GB",
    "wof:name": "N19 4BY",
    "wof:placetype": "postalcode"
  },
  "geometry": {"coordinates":[-0.125292,51.561728],"type":"Point"}
}
