{
  "type": "Feature",
  "properties": {
    "iso:country":"GB",
    "wof:name":"N22 7AS",
    "wof:placetype":"postalcode"
},
  "geometry": {"coordinates":[-0.12103922526956,51.60118144061166],"type":"Point"}
}