{
  "type": "Feature",
  "properties": {
    "iso:country": "GB",
    "wof:name": "N22 7AS",
    "wof:placetype": "postalcode"
  },
  "geometry": {"coordinates":[-0.121039,51.601181],"type":"Point"}
}
