{
  "type": "Feature",
  "properties": {
    "date:inception_lower": "1980-01-01",
    "date:inception_upper": "1980-01-01",
    "iso:country": "GB",
    "wof:name": "WS15 3DW",
    "wof:placetype": "postalcode"
  },
  "geometry": {"coordinates":[-1.873677,52.816083],"type":"Point"}
}
