{
  "type": "Feature",
  "properties": {
    "iso:country":"GB",
    "wof:name":"WS15 3DW",
    "wof:placetype":"postalcode"
},
  "geometry": {"coordinates":[-1.87367665171413,52.81608316219405],"type":"Point"}
}