{
  "type": "Feature",
  "properties": {
    "iso:country":"GB",
    "wof:name":"BA2 1QX",
    "wof:placetype":"postalcode"
},
  "geometry": {"coordinates":[-2.40581508033945,51.3765005411592],"type":"Point"}
}