{
  "type": "Feature",
  "properties": {
    "date:inception_lower": "1980-01-01",
    "date:inception_upper": "1980-01-01",
    "iso:country": "GB",
    "wof:name": "PR1 1TU",
    "wof:placetype": "postalcode"
  },
  "geometry": {"coordinates":[-2.69588,53.763725],"type":"Point"}
}
