{
  "type": "Feature",
  "properties": {
    "iso:country": "GB",
    "wof:name": "KA29 0DH",
    "wof:placetype": "postalcode"
  },
  "geometry": {"coordinates":[-4.853563,55.753655],"type":"Point"}
}
