{
  "type": "Feature",
  "properties": {
    "iso:country":"GB",
    "wof:name":"M41 9ND",
    "wof:placetype":"postalcode"
},
  "geometry": {"coordinates":[-2.33490743091848,53.44728052313044],"type":"Point"}
}