{
  "type": "Feature",
  "properties": {
    "iso:country": "GB",
    "wof:name": "G32 8LH",
    "wof:placetype": "postalcode"
  },
  "geometry": {"coordinates":[-4.174186,55.841854],"type":"Point"}
}
