{
  "type": "Feature",
  "properties": {
    "date:inception_lower": "1981-04-01",
    "date:inception_upper": "1981-04-01",
    "iso:country": "GB",
    "wof:name": "G32 8LH",
    "wof:placetype": "postalcode"
  },
  "geometry": {"coordinates":[-4.174125,55.841851],"type":"Point"}
}
