{
  "type": "Feature",
  "properties": {
    "iso:country":"GB",
    "wof:name":"BD2 2NJ",
    "wof:placetype":"postalcode"
},
  "geometry": {"coordinates":[-1.73540429319287,53.82225844319379],"type":"Point"}
}