{
  "type": "Feature",
  "properties": {
    "iso:country":"GB",
    "wof:name":"LS9 6RP",
    "wof:placetype":"postalcode"
},
  "geometry": {"coordinates":[-1.49411769412079,53.80696845738558],"type":"Point"}
}