{
  "type": "Feature",
  "properties": {
    "iso:country":"GB",
    "wof:name":"BB4 5JB",
    "wof:placetype":"postalcode"
},
  "geometry": {"coordinates":[-2.32606417977403,53.71138208957453],"type":"Point"}
}