{
  "type": "Feature",
  "properties": {
    "iso:country": "GB",
    "wof:name": "WF1 2FP",
    "wof:placetype": "postalcode"
  },
  "geometry": {"coordinates":[-1.5106,53.700662],"type":"Point"}
}
