{
  "type": "Feature",
  "properties": {
    "date:inception_lower": "2016-05-01",
    "date:inception_upper": "2016-05-01",
    "iso:country": "GB",
    "wof:name": "WF1 2FP",
    "wof:placetype": "postalcode"
  },
  "geometry": {"coordinates":[-1.5106,53.700662],"type":"Point"}
}
