{
  "type": "Feature",
  "properties": {
    "iso:country":"GB",
    "wof:name":"LE19 4LE",
    "wof:placetype":"postalcode"
},
  "geometry": {"coordinates":[-1.20884465705322,52.58633272110321],"type":"Point"}
}