{
  "type": "Feature",
  "properties": {
    "iso:country":"GB",
    "wof:name":"LL11 4FB",
    "wof:placetype":"postalcode"
},
  "geometry": {"coordinates":[-3.01406201710534,53.06855110170093],"type":"Point"}
}