{
  "type": "Feature",
  "properties": {
    "iso:country": "GB",
    "wof:name": "LL11 4FB",
    "wof:placetype": "postalcode"
  },
  "geometry": {"coordinates":[-3.014062,53.068551],"type":"Point"}
}
