{
  "type": "Feature",
  "properties": {
    "iso:country":"GB",
    "wof:name":"BS16 3TQ",
    "wof:placetype":"postalcode"
},
  "geometry": {"coordinates":[-2.52573007296711,51.48083938694726],"type":"Point"}
}