{
  "type": "Feature",
  "properties": {
    "iso:country": "GB",
    "wof:name": "LS10 4LX",
    "wof:placetype": "postalcode"
  },
  "geometry": {"coordinates":[-1.548705,53.74782],"type":"Point"}
}
