{
  "type": "Feature",
  "properties": {
    "date:inception_lower":"1980-01-01",
    "date:inception_upper":"1980-01-31",
    "iso:country":"GB",
    "wof:name":"KA11 3BA",
    "wof:placetype":"postalcode"
},
  "geometry": {"coordinates":[-4.592241,55.615072],"type":"Point"}
}