{
  "type": "Feature",
  "properties": {
    "iso:country":"GB",
    "wof:name":"KA11 3BA",
    "wof:placetype":"postalcode"
},
  "geometry": {"coordinates":[-4.59224114707667,55.61507198229124],"type":"Point"}
}