{
  "type": "Feature",
  "properties": {
    "iso:country": "GB",
    "wof:name": "KA11 3BA",
    "wof:placetype": "postalcode"
  },
  "geometry": {"coordinates":[-4.592241,55.615072],"type":"Point"}
}
