{
  "type": "Feature",
  "properties": {
    "date:inception_lower": "1980-01-01",
    "date:inception_upper": "1980-01-01",
    "iso:country": "GB",
    "wof:name": "M12 5DL",
    "wof:placetype": "postalcode"
  },
  "geometry": {"coordinates":[-2.190875,53.470249],"type":"Point"}
}
