{
  "type": "Feature",
  "properties": {
    "iso:country":"GB",
    "wof:name":"DN16 2AS",
    "wof:placetype":"postalcode"
},
  "geometry": {"coordinates":[-0.65112354156948,53.56981534455191],"type":"Point"}
}