{
  "type": "Feature",
  "properties": {
    "iso:country": "GB",
    "wof:name": "DN16 2AS",
    "wof:placetype": "postalcode"
  },
  "geometry": {"coordinates":[-0.651123,53.569815],"type":"Point"}
}
