{
  "type": "Feature",
  "properties": {
    "date:inception_lower": "2018-07-01",
    "date:inception_upper": "2018-07-01",
    "iso:country": "GB",
    "wof:name": "DE6 1TW",
    "wof:placetype": "postalcode"
  },
  "geometry": {"coordinates":[-1.730454,53.006724],"type":"Point"}
}
