{
  "type": "Feature",
  "properties": {
    "date:inception_lower":"1998-12-01",
    "date:inception_upper":"1998-12-31",
    "iso:country":"GB",
    "wof:name":"B70 0EN",
    "wof:placetype":"postalcode"
},
  "geometry": {"coordinates":[-2.029644,52.529664],"type":"Point"}
}