{
  "type": "Feature",
  "properties": {
    "iso:country":"GB",
    "wof:name":"B70 0EN",
    "wof:placetype":"postalcode"
},
  "geometry": {"coordinates":[-2.02964423664698,52.52966373916121],"type":"Point"}
}