{
  "type": "Feature",
  "properties": {
    "iso:country":"GB",
    "wof:name":"TS13 4DT",
    "wof:placetype":"postalcode"
},
  "geometry": {"coordinates":[-0.91104079008131,54.56343214838886],"type":"Point"}
}