{
  "type": "Feature",
  "properties": {
    "date:inception_lower": "1980-01-01",
    "date:inception_upper": "1980-01-01",
    "iso:country": "GB",
    "wof:name": "TS13 4DT",
    "wof:placetype": "postalcode"
  },
  "geometry": {"coordinates":[-0.911041,54.563432],"type":"Point"}
}
