{
  "type": "Feature",
  "properties": {
    "iso:country":"GB",
    "wof:name":"BD14 6NJ",
    "wof:placetype":"postalcode"
},
  "geometry": {"coordinates":[-1.80452024423742,53.78329318170254],"type":"Point"}
}