{
  "type": "Feature",
  "properties": {
    "iso:country":"GB",
    "wof:name":"DA6 7NA",
    "wof:placetype":"postalcode"
},
  "geometry": {"coordinates":[0.14991153373906,51.45358044545237],"type":"Point"}
}