{
  "type": "Feature",
  "properties": {
    "date:inception_lower": "1980-01-01",
    "date:inception_upper": "1980-01-01",
    "iso:country": "GB",
    "wof:name": "TN2 3BJ",
    "wof:placetype": "postalcode"
  },
  "geometry": {"coordinates":[0.282153,51.150029],"type":"Point"}
}
