{
  "type": "Feature",
  "properties": {
    "iso:country":"GB",
    "wof:name":"TN2 3BJ",
    "wof:placetype":"postalcode"
},
  "geometry": {"coordinates":[0.28215327333676,51.15002873471275],"type":"Point"}
}