{
  "type": "Feature",
  "properties": {
    "iso:country": "GB",
    "wof:name": "BS14 9YE",
    "wof:placetype": "postalcode"
  },
  "geometry": {"coordinates":[-2.567704,51.411048],"type":"Point"}
}
