{
  "type": "Feature",
  "properties": {
    "date:inception_lower": "1994-12-01",
    "date:inception_upper": "1994-12-01",
    "iso:country": "GB",
    "wof:name": "PR4 2HG",
    "wof:placetype": "postalcode"
  },
  "geometry": {"coordinates":[-2.879902,53.782415],"type":"Point"}
}
