{
  "type": "Feature",
  "properties": {
    "iso:country": "GB",
    "wof:name": "PR4 2HG",
    "wof:placetype": "postalcode"
  },
  "geometry": {"coordinates":[-2.879902,53.782415],"type":"Point"}
}
