{
  "type": "Feature",
  "properties": {
    "iso:country":"GB",
    "wof:name":"PR4 2HG",
    "wof:placetype":"postalcode"
},
  "geometry": {"coordinates":[-2.87990201090865,53.78241488799592],"type":"Point"}
}