{
  "type": "Feature",
  "properties": {
    "date:inception_lower": "1990-02-01",
    "date:inception_upper": "1990-02-01",
    "iso:country": "GB",
    "wof:name": "DN8 4LD",
    "wof:placetype": "postalcode"
  },
  "geometry": {"coordinates":[-0.952967,53.619066],"type":"Point"}
}
