{
  "type": "Feature",
  "properties": {
    "iso:country":"GB",
    "wof:name":"DN8 4LD",
    "wof:placetype":"postalcode"
},
  "geometry": {"coordinates":[-0.95296693667817,53.61906650158148],"type":"Point"}
}