{
  "type": "Feature",
  "properties": {
    "iso:country":"GB",
    "wof:name":"RH14 9ER",
    "wof:placetype":"postalcode"
},
  "geometry": {"coordinates":[-0.45442826764364,51.01931320842216],"type":"Point"}
}