{
  "type": "Feature",
  "properties": {
    "iso:country":"GB",
    "wof:name":"LS12 6JS",
    "wof:placetype":"postalcode"
},
  "geometry": {"coordinates":[-1.61948996787245,53.77467907079681],"type":"Point"}
}