{
  "type": "Feature",
  "properties": {
    "iso:country": "GB",
    "wof:name": "PE37 7BP",
    "wof:placetype": "postalcode"
  },
  "geometry": {"coordinates":[0.681902,52.648433],"type":"Point"}
}
