{
  "type": "Feature",
  "properties": {
    "iso:country":"GB",
    "wof:name":"SN5 5SP",
    "wof:placetype":"postalcode"
},
  "geometry": {"coordinates":[-1.8345111923895,51.56369763169786],"type":"Point"}
}