{
  "type": "Feature",
  "properties": {
    "iso:country":"GB",
    "wof:name":"PE9 1SN",
    "wof:placetype":"postalcode"
},
  "geometry": {"coordinates":[-0.47288480537474,52.66316513727057],"type":"Point"}
}