{
  "type": "Feature",
  "properties": {
    "iso:country":"GB",
    "wof:name":"KT10 9BZ",
    "wof:placetype":"postalcode"
},
  "geometry": {"coordinates":[-0.34777950053238,51.3702341724293],"type":"Point"}
}