{
  "type": "Feature",
  "properties": {
    "date:inception_lower": "1990-02-01",
    "date:inception_upper": "1990-02-01",
    "iso:country": "GB",
    "wof:name": "MK13 7HT",
    "wof:placetype": "postalcode"
  },
  "geometry": {"coordinates":[-0.786988,52.059649],"type":"Point"}
}
