{
  "type": "Feature",
  "properties": {
    "iso:country":"GB",
    "wof:name":"ME4 5ST",
    "wof:placetype":"postalcode"
},
  "geometry": {"coordinates":[0.5264580771693,51.37523510711826],"type":"Point"}
}