{
  "type": "Feature",
  "properties": {
    "iso:country": "GB",
    "wof:name": "SK11 8WD",
    "wof:placetype": "postalcode"
  },
  "geometry": {"coordinates":[-2.153542,53.261712],"type":"Point"}
}
