{
  "type": "Feature",
  "properties": {
    "iso:country":"GB",
    "wof:name":"DE6 3EY",
    "wof:placetype":"postalcode"
},
  "geometry": {"coordinates":[-1.62183323414655,53.0219258355064],"type":"Point"}
}