{
  "type": "Feature",
  "properties": {
    "iso:country":"GB",
    "wof:name":"L37 0AA",
    "wof:placetype":"postalcode"
},
  "geometry": {"coordinates":[-3.04283977825313,53.56241573570058],"type":"Point"}
}