{
  "type": "Feature",
  "properties": {
    "iso:country": "GB",
    "wof:name": "L37 0AA",
    "wof:placetype": "postalcode"
  },
  "geometry": {"coordinates":[-3.040307,53.561474],"type":"Point"}
}
