{
  "type": "Feature",
  "properties": {
    "iso:country": "GB",
    "wof:name": "L37 0AA",
    "wof:placetype": "postalcode"
  },
  "geometry": {"coordinates":[-3.042793,53.562477],"type":"Point"}
}
