{
  "type": "Feature",
  "properties": {
    "date:inception_lower": "2008-09-01",
    "date:inception_upper": "2008-09-01",
    "iso:country": "GB",
    "wof:name": "WV16 5AR",
    "wof:placetype": "postalcode"
  },
  "geometry": {"coordinates":[-2.438627,52.534167],"type":"Point"}
}
