{
  "type": "Feature",
  "properties": {
    "iso:country": "GB",
    "wof:name": "WV16 5AR",
    "wof:placetype": "postalcode"
  },
  "geometry": {"coordinates":[-2.438627,52.534167],"type":"Point"}
}
