{
  "type": "Feature",
  "properties": {
    "iso:country":"GB",
    "wof:name":"SN5 8LN",
    "wof:placetype":"postalcode"
},
  "geometry": {"coordinates":[-1.83248554776292,51.55352550945604],"type":"Point"}
}