{
  "type": "Feature",
  "properties": {
    "iso:country": "GB",
    "wof:name": "FK14 7PW",
    "wof:placetype": "postalcode"
  },
  "geometry": {"coordinates":[-3.580997,56.166738],"type":"Point"}
}
