{
  "type": "Feature",
  "properties": {
    "iso:country":"GB",
    "wof:name":"FK14 7PW",
    "wof:placetype":"postalcode"
},
  "geometry": {"coordinates":[-3.58099666619418,56.16673824327398],"type":"Point"}
}