{
  "type": "Feature",
  "properties": {
    "date:inception_lower":"2002-06-01",
    "date:inception_upper":"2002-06-30",
    "iso:country":"GB",
    "wof:name":"FK14 7PW",
    "wof:placetype":"postalcode"
},
  "geometry": {"coordinates":[-3.580997,56.166738],"type":"Point"}
}