{
  "type": "Feature",
  "properties": {
    "date:inception_lower": "2017-01-01",
    "date:inception_upper": "2017-01-01",
    "iso:country": "GB",
    "wof:name": "LS3 1FD",
    "wof:placetype": "postalcode"
  },
  "geometry": {"coordinates":[-1.563421,53.804605],"type":"Point"}
}
