{
  "type": "Feature",
  "properties": {
    "iso:country":"GB",
    "wof:name":"LL32 8JX",
    "wof:placetype":"postalcode"
},
  "geometry": {"coordinates":[-3.83753312677307,53.18191004031319],"type":"Point"}
}