{
  "type": "Feature",
  "properties": {
    "iso:country": "GB",
    "wof:name": "LL32 8JX",
    "wof:placetype": "postalcode"
  },
  "geometry": {"coordinates":[-3.837533,53.18191],"type":"Point"}
}
