{
  "type": "Feature",
  "properties": {
    "iso:country":"GB",
    "wof:name":"SO40 2UU",
    "wof:placetype":"postalcode"
},
  "geometry": {"coordinates":[-1.51245143676282,50.92435730709298],"type":"Point"}
}