{
  "type": "Feature",
  "properties": {
    "date:inception_lower": "2013-03-01",
    "date:inception_upper": "2013-03-01",
    "iso:country": "GB",
    "wof:name": "SE10 8FS",
    "wof:placetype": "postalcode"
  },
  "geometry": {"coordinates":[-0.019623,51.47404],"type":"Point"}
}
