{
  "type": "Feature",
  "properties": {
    "iso:country":"GB",
    "wof:name":"SE10 8FS",
    "wof:placetype":"postalcode"
},
  "geometry": {"coordinates":[-0.01962333633824,51.47404006322765],"type":"Point"}
}