{
  "type": "Feature",
  "properties": {
    "iso:country":"GB",
    "wof:name":"SA15 5LR",
    "wof:placetype":"postalcode"
},
  "geometry": {"coordinates":[-4.1297778494779,51.77437543739635],"type":"Point"}
}