{
  "type": "Feature",
  "properties": {
    "date:inception_lower": "1980-01-01",
    "date:inception_upper": "1980-01-01",
    "iso:country": "GB",
    "wof:name": "SA15 5LR",
    "wof:placetype": "postalcode"
  },
  "geometry": {"coordinates":[-4.12957,51.774126],"type":"Point"}
}
