{
  "type": "Feature",
  "properties": {
    "iso:country": "GB",
    "wof:name": "BA2 6SW",
    "wof:placetype": "postalcode"
  },
  "geometry": {"coordinates":[-2.329818,51.393464],"type":"Point"}
}
