{
  "type": "Feature",
  "properties": {
    "iso:country":"GB",
    "wof:name":"BA2 6SW",
    "wof:placetype":"postalcode"
},
  "geometry": {"coordinates":[-2.32981848681135,51.39346376958483],"type":"Point"}
}