{
  "type": "Feature",
  "properties": {
    "date:inception_lower": "2002-12-01",
    "date:inception_upper": "2002-12-01",
    "iso:country": "GB",
    "wof:name": "NG19 7AY",
    "wof:placetype": "postalcode"
  },
  "geometry": {"coordinates":[-1.198447,53.150262],"type":"Point"}
}
