{
  "type": "Feature",
  "properties": {
    "iso:country":"GB",
    "wof:name":"BN9 0JL",
    "wof:placetype":"postalcode"
},
  "geometry": {"coordinates":[0.05734866655954,50.80595511643023],"type":"Point"}
}