{
  "type": "Feature",
  "properties": {
    "date:inception_lower": "1980-01-01",
    "date:inception_upper": "1980-01-01",
    "iso:country": "GB",
    "wof:name": "RG4 7HS",
    "wof:placetype": "postalcode"
  },
  "geometry": {"coordinates":[-0.993273,51.481137],"type":"Point"}
}
