{
  "type": "Feature",
  "properties": {
    "iso:country":"GB",
    "wof:name":"LE14 4JH",
    "wof:placetype":"postalcode"
},
  "geometry": {"coordinates":[-0.92196668696935,52.86311019750838],"type":"Point"}
}