{
  "type": "Feature",
  "properties": {
    "date:inception_lower": "2004-07-01",
    "date:inception_upper": "2004-07-01",
    "iso:country": "GB",
    "wof:name": "LE14 4JH",
    "wof:placetype": "postalcode"
  },
  "geometry": {"coordinates":[-0.922067,52.86368],"type":"Point"}
}
