{
  "type": "Feature",
  "properties": {
    "iso:country":"GB",
    "wof:name":"PH8 0DA",
    "wof:placetype":"postalcode"
},
  "geometry": {"coordinates":[-3.83958765348494,56.50754640385377],"type":"Point"}
}