{
  "type": "Feature",
  "properties": {
    "date:inception_lower": "1990-07-01",
    "date:inception_upper": "1990-07-01",
    "iso:country": "GB",
    "wof:name": "SG16 6LX",
    "wof:placetype": "postalcode"
  },
  "geometry": {"coordinates":[-0.287003,52.030226],"type":"Point"}
}
