{
  "type": "Feature",
  "properties": {
    "iso:country": "GB",
    "wof:name": "SG16 6LX",
    "wof:placetype": "postalcode"
  },
  "geometry": {"coordinates":[-0.287003,52.030226],"type":"Point"}
}
