{
  "type": "Feature",
  "properties": {
    "date:inception_lower": "2016-02-01",
    "date:inception_upper": "2016-02-01",
    "iso:country": "GB",
    "wof:name": "TR12 7FB",
    "wof:placetype": "postalcode"
  },
  "geometry": {"coordinates":[-5.199129,49.968742],"type":"Point"}
}
