{
  "type": "Feature",
  "properties": {
    "iso:country":"GB",
    "wof:name":"S65 1DR",
    "wof:placetype":"postalcode"
},
  "geometry": {"coordinates":[-1.3498639547435,53.42958782802378],"type":"Point"}
}