{
  "type": "Feature",
  "properties": {
    "iso:country":"GB",
    "wof:name":"AB16 5TA",
    "wof:placetype":"postalcode"
},
  "geometry": {"coordinates":[-2.15604807859921,57.16461063445073],"type":"Point"}
}