{
  "type": "Feature",
  "properties": {
    "iso:country":"GB",
    "wof:name":"CM20 1DT",
    "wof:placetype":"postalcode"
},
  "geometry": {"coordinates":[0.08938654129996,51.77093753520679],"type":"Point"}
}