{
  "type": "Feature",
  "properties": {
    "date:inception_lower":"1994-12-01",
    "date:inception_upper":"1994-12-31",
    "iso:country":"GB",
    "wof:name":"DN18 6JW",
    "wof:placetype":"postalcode"
},
  "geometry": {"coordinates":[-0.427567,53.679127],"type":"Point"}
}