{
  "type": "Feature",
  "properties": {
    "date:inception_lower": "1990-02-01",
    "date:inception_upper": "1990-02-01",
    "iso:country": "GB",
    "wof:name": "TW16 7NJ",
    "wof:placetype": "postalcode"
  },
  "geometry": {"coordinates":[-0.426658,51.421183],"type":"Point"}
}
