{
  "type": "Feature",
  "properties": {
    "iso:country": "GB",
    "wof:name": "CT4 5QR",
    "wof:placetype": "postalcode"
  },
  "geometry": {"coordinates":[1.051202,51.233135],"type":"Point"}
}
