{
  "type": "Feature",
  "properties": {
    "iso:country":"GB",
    "wof:name":"CT4 5QR",
    "wof:placetype":"postalcode"
},
  "geometry": {"coordinates":[1.05120212679525,51.23313472479259],"type":"Point"}
}