{
  "type": "Feature",
  "properties": {
    "iso:country": "GB",
    "wof:name": "B23 5DZ",
    "wof:placetype": "postalcode"
  },
  "geometry": {"coordinates":[-1.833009,52.534078],"type":"Point"}
}
