{
  "type": "Feature",
  "properties": {
    "date:inception_lower": "2014-07-01",
    "date:inception_upper": "2014-07-01",
    "iso:country": "GB",
    "wof:name": "B23 5DZ",
    "wof:placetype": "postalcode"
  },
  "geometry": {"coordinates":[-1.832994,52.534105],"type":"Point"}
}
