{
  "type": "Feature",
  "properties": {
    "iso:country": "GB",
    "wof:name": "OL7 9AN",
    "wof:placetype": "postalcode"
  },
  "geometry": {"coordinates":[-2.100407,53.493558],"type":"Point"}
}
