{
  "type": "Feature",
  "properties": {
    "date:inception_lower": "1995-07-01",
    "date:inception_upper": "1995-07-01",
    "iso:country": "GB",
    "wof:name": "RG30 2RA",
    "wof:placetype": "postalcode"
  },
  "geometry": {"coordinates":[-1.006213,51.458183],"type":"Point"}
}
