{
  "type": "Feature",
  "properties": {
    "iso:country": "GB",
    "wof:name": "KA1 4SF",
    "wof:placetype": "postalcode"
  },
  "geometry": {"coordinates":[-4.498468,55.586495],"type":"Point"}
}
