{
  "type": "Feature",
  "properties": {
    "iso:country":"GB",
    "wof:name":"NE24 1DR",
    "wof:placetype":"postalcode"
},
  "geometry": {"coordinates":[-1.51311298031777,55.12687704341312],"type":"Point"}
}