{
  "type": "Feature",
  "properties": {
    "date:inception_lower": "1997-06-01",
    "date:inception_upper": "1997-06-01",
    "iso:country": "GB",
    "wof:name": "NE24 1DR",
    "wof:placetype": "postalcode"
  },
  "geometry": {"coordinates":[-1.513113,55.126877],"type":"Point"}
}
