{
  "type": "Feature",
  "properties": {
    "iso:country":"GB",
    "wof:name":"SM2 6PZ",
    "wof:placetype":"postalcode"
},
  "geometry": {"coordinates":[-0.20057094766167,51.35572777773205],"type":"Point"}
}