{
  "type": "Feature",
  "properties": {
    "iso:country": "GB",
    "wof:name": "G73 3QJ",
    "wof:placetype": "postalcode"
  },
  "geometry": {"coordinates":[-4.210337,55.81831],"type":"Point"}
}
