{
  "type": "Feature",
  "properties": {
    "iso:country":"GB",
    "wof:name":"G73 3QJ",
    "wof:placetype":"postalcode"
},
  "geometry": {"coordinates":[-4.21033735017772,55.81831001887851],"type":"Point"}
}