{
  "type": "Feature",
  "properties": {
    "iso:country": "GB",
    "wof:name": "N1 6RR",
    "wof:placetype": "postalcode"
  },
  "geometry": {"coordinates":[-0.079254,51.531928],"type":"Point"}
}
