{
  "type": "Feature",
  "properties": {
    "date:inception_lower":"1980-01-01",
    "date:inception_upper":"1980-01-31",
    "iso:country":"GB",
    "wof:name":"N1 6RR",
    "wof:placetype":"postalcode"
},
  "geometry": {"coordinates":[-0.079254,51.531928],"type":"Point"}
}