{
  "type": "Feature",
  "properties": {
    "iso:country":"GB",
    "wof:name":"N1 6RR",
    "wof:placetype":"postalcode"
},
  "geometry": {"coordinates":[-0.07925403369086,51.53192822950685],"type":"Point"}
}