{
  "type": "Feature",
  "properties": {
    "iso:country": "GB",
    "wof:name": "M22 1EL",
    "wof:placetype": "postalcode"
  },
  "geometry": {"coordinates":[-2.276088,53.374048],"type":"Point"}
}
