{
  "type": "Feature",
  "properties": {
    "iso:country":"GB",
    "wof:name":"M22 1EL",
    "wof:placetype":"postalcode"
},
  "geometry": {"coordinates":[-2.2760883954109,53.37404836236142],"type":"Point"}
}