{
  "type": "Feature",
  "properties": {
    "date:inception_lower": "1980-01-01",
    "date:inception_upper": "1980-01-01",
    "iso:country": "GB",
    "wof:name": "CV37 7QU",
    "wof:placetype": "postalcode"
  },
  "geometry": {"coordinates":[-1.65725,52.206695],"type":"Point"}
}
