{
  "type": "Feature",
  "properties": {
    "iso:country":"GB",
    "wof:name":"CV37 7QU",
    "wof:placetype":"postalcode"
},
  "geometry": {"coordinates":[-1.65725029627133,52.20669465722261],"type":"Point"}
}