{
  "type": "Feature",
  "properties": {
    "iso:country":"GB",
    "wof:name":"WF10 4HL",
    "wof:placetype":"postalcode"
},
  "geometry": {"coordinates":[-1.34796656855343,53.7212980320272],"type":"Point"}
}