{
  "type": "Feature",
  "properties": {
    "iso:country": "GB",
    "wof:name": "NE7 7NJ",
    "wof:placetype": "postalcode"
  },
  "geometry": {"coordinates":[-1.585141,55.007134],"type":"Point"}
}
