{
  "type": "Feature",
  "properties": {
    "iso:country":"GB",
    "wof:name":"NE7 7NJ",
    "wof:placetype":"postalcode"
},
  "geometry": {"coordinates":[-1.58514081235852,55.00713352163541],"type":"Point"}
}