{
  "type": "Feature",
  "properties": {
    "iso:country":"GB",
    "wof:name":"LE3 2LB",
    "wof:placetype":"postalcode"
},
  "geometry": {"coordinates":[-1.1735626181014,52.60545635743966],"type":"Point"}
}