{
  "type": "Feature",
  "properties": {
    "iso:country":"GB",
    "wof:name":"NG20 0TH",
    "wof:placetype":"postalcode"
},
  "geometry": {"coordinates":[-1.15709934839226,53.21453629008438],"type":"Point"}
}