{
  "type": "Feature",
  "properties": {
    "iso:country":"GB",
    "wof:name":"SW6 7DL",
    "wof:placetype":"postalcode"
},
  "geometry": {"coordinates":[-0.20888291903511,51.47981764016598],"type":"Point"}
}