{
  "type": "Feature",
  "properties": {
    "iso:country":"GB",
    "wof:name":"DY14 9TA",
    "wof:placetype":"postalcode"
},
  "geometry": {"coordinates":[-2.38992727365494,52.36368817224543],"type":"Point"}
}