{
  "type": "Feature",
  "properties": {
    "iso:country":"GB",
    "wof:name":"EX32 7NA",
    "wof:placetype":"postalcode"
},
  "geometry": {"coordinates":[-3.99988793644825,51.08282834995919],"type":"Point"}
}