{
  "type": "Feature",
  "properties": {
    "iso:country": "GB",
    "wof:name": "EX32 7NA",
    "wof:placetype": "postalcode"
  },
  "geometry": {"coordinates":[-3.999888,51.082828],"type":"Point"}
}
