{
  "type": "Feature",
  "properties": {
    "date:inception_lower":"2012-09-01",
    "date:inception_upper":"2012-09-30",
    "iso:country":"GB",
    "wof:name":"CT20 9GX",
    "wof:placetype":"postalcode"
},
  "geometry": {"coordinates":[1.177144,51.078612],"type":"Point"}
}