{
  "type": "Feature",
  "properties": {
    "date:inception_lower": "2020-09-01",
    "date:inception_upper": "2020-09-01",
    "iso:country": "GB",
    "wof:name": "PL31 2SZ",
    "wof:placetype": "postalcode"
  },
  "geometry": {"coordinates":[-4.749674,50.472122],"type":"Point"}
}
