{
  "type": "Feature",
  "properties": {
    "iso:country":"GB",
    "wof:name":"GU15 1JP",
    "wof:placetype":"postalcode"
},
  "geometry": {"coordinates":[-0.72333886809301,51.33124387903728],"type":"Point"}
}