{
  "type": "Feature",
  "properties": {
    "iso:country":"GB",
    "wof:name":"BN27 4RB",
    "wof:placetype":"postalcode"
},
  "geometry": {"coordinates":[0.34387776686298,50.91022127519367],"type":"Point"}
}