{
  "type": "Feature",
  "properties": {
    "iso:country": "GB",
    "wof:name": "HX6 2AY",
    "wof:placetype": "postalcode"
  },
  "geometry": {"coordinates":[-1.894911,53.710298],"type":"Point"}
}
