{
  "type": "Feature",
  "properties": {
    "iso:country":"GB",
    "wof:name":"BH12 3NG",
    "wof:placetype":"postalcode"
},
  "geometry": {"coordinates":[-1.94142953740024,50.74271286785799],"type":"Point"}
}