{
  "type": "Feature",
  "properties": {
    "iso:country":"GB",
    "wof:name":"ML11 9RT",
    "wof:placetype":"postalcode"
},
  "geometry": {"coordinates":[-3.9245159395489,55.67148008560044],"type":"Point"}
}