{
  "type": "Feature",
  "properties": {
    "iso:country":"GB",
    "wof:name":"PE3 9NJ",
    "wof:placetype":"postalcode"
},
  "geometry": {"coordinates":[-0.28317691381506,52.57793426304934],"type":"Point"}
}