{
  "type": "Feature",
  "properties": {
    "iso:country":"GB",
    "wof:name":"GU10 3BD",
    "wof:placetype":"postalcode"
},
  "geometry": {"coordinates":[-0.80058417077738,51.17455162966808],"type":"Point"}
}