{
  "type": "Feature",
  "properties": {
    "iso:country":"GB",
    "wof:name":"L40 4LD",
    "wof:placetype":"postalcode"
},
  "geometry": {"coordinates":[-2.83835812952278,53.60155140626809],"type":"Point"}
}