{
  "type": "Feature",
  "properties": {
    "iso:country":"GB",
    "wof:name":"OX3 8HA",
    "wof:placetype":"postalcode"
},
  "geometry": {"coordinates":[-1.19062028238364,51.75834149438239],"type":"Point"}
}