{
  "type": "Feature",
  "properties": {
    "iso:country": "GB",
    "wof:name": "SG2 0QH",
    "wof:placetype": "postalcode"
  },
  "geometry": {"coordinates":[-0.169196,51.903197],"type":"Point"}
}
