{
  "type": "Feature",
  "properties": {
    "iso:country":"GB",
    "wof:name":"SG2 0QH",
    "wof:placetype":"postalcode"
},
  "geometry": {"coordinates":[-0.16919624870194,51.90319723068546],"type":"Point"}
}