{
  "type": "Feature",
  "properties": {
    "date:inception_lower": "1980-01-01",
    "date:inception_upper": "1980-01-01",
    "iso:country": "GB",
    "wof:name": "TS6 8BE",
    "wof:placetype": "postalcode"
  },
  "geometry": {"coordinates":[-1.13847,54.565957],"type":"Point"}
}
