{
  "type": "Feature",
  "properties": {
    "iso:country": "GB",
    "wof:name": "TS6 8BE",
    "wof:placetype": "postalcode"
  },
  "geometry": {"coordinates":[-1.13847,54.565957],"type":"Point"}
}
