{
  "type": "Feature",
  "properties": {
    "iso:country":"GB",
    "wof:name":"SY3 9PE",
    "wof:placetype":"postalcode"
},
  "geometry": {"coordinates":[-2.75983869720144,52.68620564644295],"type":"Point"}
}