{
  "type": "Feature",
  "properties": {
    "iso:country": "GB",
    "wof:name": "SY3 9PE",
    "wof:placetype": "postalcode"
  },
  "geometry": {"coordinates":[-2.759839,52.686206],"type":"Point"}
}
