{
  "type": "Feature",
  "properties": {
    "iso:country":"GB",
    "wof:name":"BR1 2QH",
    "wof:placetype":"postalcode"
},
  "geometry": {"coordinates":[0.03760567007734,51.40202511681831],"type":"Point"}
}