{
  "type": "Feature",
  "properties": {
    "iso:country":"GB",
    "wof:name":"MK6 4HF",
    "wof:placetype":"postalcode"
},
  "geometry": {"coordinates":[-0.73113990956086,52.02350050565733],"type":"Point"}
}