{
  "type": "Feature",
  "properties": {
    "iso:country": "GB",
    "wof:name": "MK6 4HF",
    "wof:placetype": "postalcode"
  },
  "geometry": {"coordinates":[-0.73114,52.023501],"type":"Point"}
}
