{
  "type": "Feature",
  "properties": {
    "iso:country": "GB",
    "wof:name": "BA12 8AR",
    "wof:placetype": "postalcode"
  },
  "geometry": {"coordinates":[-2.197257,51.1825],"type":"Point"}
}
