{
  "type": "Feature",
  "properties": {
    "iso:country":"GB",
    "wof:name":"SE27 9RY",
    "wof:placetype":"postalcode"
},
  "geometry": {"coordinates":[-0.09254642975035,51.43047472348446],"type":"Point"}
}