{
  "type": "Feature",
  "properties": {
    "date:inception_lower": "1980-01-01",
    "date:inception_upper": "1980-01-01",
    "iso:country": "GB",
    "wof:name": "WF6 2JB",
    "wof:placetype": "postalcode"
  },
  "geometry": {"coordinates":[-1.437856,53.687697],"type":"Point"}
}
