{
  "type": "Feature",
  "properties": {
    "iso:country": "GB",
    "wof:name": "WF6 2JB",
    "wof:placetype": "postalcode"
  },
  "geometry": {"coordinates":[-1.437856,53.687697],"type":"Point"}
}
