{
  "type": "Feature",
  "properties": {
    "iso:country":"GB",
    "wof:name":"WF6 2JB",
    "wof:placetype":"postalcode"
},
  "geometry": {"coordinates":[-1.43785561461685,53.68769685888189],"type":"Point"}
}