{
  "type": "Feature",
  "properties": {
    "iso:country":"GB",
    "wof:name":"DD3 9NF",
    "wof:placetype":"postalcode"
},
  "geometry": {"coordinates":[-3.01705922748997,56.4947057599171],"type":"Point"}
}