{
  "type": "Feature",
  "properties": {
    "date:inception_lower": "2023-03-01",
    "date:inception_upper": "2023-03-01",
    "iso:country": "GB",
    "wof:name": "KT15 9FJ",
    "wof:placetype": "postalcode"
  },
  "geometry": {"coordinates":[-0.489139,51.371215],"type":"Point"}
}
