{
  "type": "Feature",
  "properties": {
    "date:inception_lower": "2016-03-01",
    "date:inception_upper": "2016-03-01",
    "iso:country": "GB",
    "wof:name": "CH63 7AA",
    "wof:placetype": "postalcode"
  },
  "geometry": {"coordinates":[-2.998881,53.348433],"type":"Point"}
}
