{
  "type": "Feature",
  "properties": {
    "iso:country":"GB",
    "wof:name":"LL54 6AW",
    "wof:placetype":"postalcode"
},
  "geometry": {"coordinates":[-4.25274989493498,53.05474942544924],"type":"Point"}
}