{
  "type": "Feature",
  "properties": {
    "date:inception_lower": "1980-01-01",
    "date:inception_upper": "1980-01-01",
    "iso:country": "GB",
    "wof:name": "LL54 6AW",
    "wof:placetype": "postalcode"
  },
  "geometry": {"coordinates":[-4.25275,53.054749],"type":"Point"}
}
