{
  "type": "Feature",
  "properties": {
    "iso:country":"GB",
    "wof:name":"DN17 2XF",
    "wof:placetype":"postalcode"
},
  "geometry": {"coordinates":[-0.68440688191435,53.56542181105814],"type":"Point"}
}