{
  "type": "Feature",
  "properties": {
    "iso:country":"GB",
    "wof:name":"LL14 5AG",
    "wof:placetype":"postalcode"
},
  "geometry": {"coordinates":[-3.0977587803469,52.94283462628934],"type":"Point"}
}