{
  "type": "Feature",
  "properties": {
    "iso:country":"GB",
    "wof:name":"E12 6DU",
    "wof:placetype":"postalcode"
},
  "geometry": {"coordinates":[0.05345161064325,51.55116369220941],"type":"Point"}
}