{
  "type": "Feature",
  "properties": {
    "iso:country":"GB",
    "wof:name":"BH24 1TJ",
    "wof:placetype":"postalcode"
},
  "geometry": {"coordinates":[-1.77021717341526,50.85444102287449],"type":"Point"}
}