{
  "type": "Feature",
  "properties": {
    "date:inception_lower": "2019-04-01",
    "date:inception_upper": "2019-04-01",
    "iso:country": "GB",
    "wof:name": "AL5 5FH",
    "wof:placetype": "postalcode"
  },
  "geometry": {"coordinates":[-0.329746,51.823075],"type":"Point"}
}
