{
  "type": "Feature",
  "properties": {
    "iso:country":"GB",
    "wof:name":"WR4 9HU",
    "wof:placetype":"postalcode"
},
  "geometry": {"coordinates":[-2.18391229112757,52.20632866008368],"type":"Point"}
}