{
  "type": "Feature",
  "properties": {
    "iso:country":"GB",
    "wof:name":"SM4 6BL",
    "wof:placetype":"postalcode"
},
  "geometry": {"coordinates":[-0.18334539933836,51.3870710912821],"type":"Point"}
}