{
  "type": "Feature",
  "properties": {
    "iso:country":"GB",
    "wof:name":"RG1 6AP",
    "wof:placetype":"postalcode"
},
  "geometry": {"coordinates":[-0.97938103292563,51.45019995288203],"type":"Point"}
}