{
  "type": "Feature",
  "properties": {
    "date:inception_lower": "1999-06-01",
    "date:inception_upper": "1999-06-01",
    "iso:country": "GB",
    "wof:name": "CH41 4DB",
    "wof:placetype": "postalcode"
  },
  "geometry": {"coordinates":[-3.033982,53.389124],"type":"Point"}
}
