{
  "type": "Feature",
  "properties": {
    "date:inception_lower": "1980-01-01",
    "date:inception_upper": "1980-01-01",
    "iso:country": "GB",
    "wof:name": "LL57 3NG",
    "wof:placetype": "postalcode"
  },
  "geometry": {"coordinates":[-4.063077,53.181785],"type":"Point"}
}
