{
  "type": "Feature",
  "properties": {
    "iso:country":"GB",
    "wof:name":"LL57 3NG",
    "wof:placetype":"postalcode"
},
  "geometry": {"coordinates":[-4.06307661419714,53.18178520995666],"type":"Point"}
}