{
  "type": "Feature",
  "properties": {
    "iso:country": "GB",
    "wof:name": "LL57 3NG",
    "wof:placetype": "postalcode"
  },
  "geometry": {"coordinates":[-4.063077,53.181785],"type":"Point"}
}
