{
  "type": "Feature",
  "properties": {
    "date:inception_lower": "2013-03-01",
    "date:inception_upper": "2013-03-01",
    "iso:country": "GB",
    "wof:name": "KA12 8TD",
    "wof:placetype": "postalcode"
  },
  "geometry": {"coordinates":[-4.685033,55.629422],"type":"Point"}
}
