{
  "type": "Feature",
  "properties": {
    "iso:country":"GB",
    "wof:name":"KA12 8TD",
    "wof:placetype":"postalcode"
},
  "geometry": {"coordinates":[-4.68580692475745,55.62999236703194],"type":"Point"}
}