{
  "type": "Feature",
  "properties": {
    "iso:country": "GB",
    "wof:name": "KA12 8TD",
    "wof:placetype": "postalcode"
  },
  "geometry": {"coordinates":[-4.685593,55.629482],"type":"Point"}
}
