{
  "type": "Feature",
  "properties": {
    "date:inception_lower":"2013-03-01",
    "date:inception_upper":"2013-03-31",
    "iso:country":"GB",
    "wof:name":"KA12 8TD",
    "wof:placetype":"postalcode"
},
  "geometry": {"coordinates":[-4.685593,55.629482],"type":"Point"}
}