{
  "type": "Feature",
  "properties": {
    "iso:country": "GB",
    "wof:name": "SK11 7ET",
    "wof:placetype": "postalcode"
  },
  "geometry": {"coordinates":[-2.110181,53.257869],"type":"Point"}
}
