{
  "type": "Feature",
  "properties": {
    "iso:country": "GB",
    "wof:name": "TD15 2GY",
    "wof:placetype": "postalcode"
  },
  "geometry": {"coordinates":[-1.988933,55.735499],"type":"Point"}
}
