{
  "type": "Feature",
  "properties": {
    "iso:country":"GB",
    "wof:name":"TD15 2GY",
    "wof:placetype":"postalcode"
},
  "geometry": {"coordinates":[-1.98890628804119,55.73543957955336],"type":"Point"}
}