{
  "type": "Feature",
  "properties": {
    "date:inception_lower": "2009-11-01",
    "date:inception_upper": "2009-11-01",
    "iso:country": "GB",
    "wof:name": "TD15 2GY",
    "wof:placetype": "postalcode"
  },
  "geometry": {"coordinates":[-1.988933,55.735499],"type":"Point"}
}
