{
  "type": "Feature",
  "properties": {
    "iso:country":"GB",
    "wof:name":"B64 7DU",
    "wof:placetype":"postalcode"
},
  "geometry": {"coordinates":[-2.07450760140043,52.46455678258379],"type":"Point"}
}