{
  "type": "Feature",
  "properties": {
    "iso:country":"GB",
    "wof:name":"KT6 4DP",
    "wof:placetype":"postalcode"
},
  "geometry": {"coordinates":[-0.30821223821159,51.39715960600928],"type":"Point"}
}