{
  "type": "Feature",
  "properties": {
    "date:inception_lower": "2020-04-01",
    "date:inception_upper": "2020-04-01",
    "iso:country": "GB",
    "wof:name": "CH49 4AA",
    "wof:placetype": "postalcode"
  },
  "geometry": {"coordinates":[-3.094205,53.393333],"type":"Point"}
}
