{
  "type": "Feature",
  "properties": {
    "iso:country":"GB",
    "wof:name":"CO7 8DQ",
    "wof:placetype":"postalcode"
},
  "geometry": {"coordinates":[0.99914953283218,51.85748096633571],"type":"Point"}
}