{
  "type": "Feature",
  "properties": {
    "date:inception_lower": "1980-01-01",
    "date:inception_upper": "1980-01-01",
    "iso:country": "GB",
    "wof:name": "TS25 3NF",
    "wof:placetype": "postalcode"
  },
  "geometry": {"coordinates":[-1.24717,54.658879],"type":"Point"}
}
