{
  "type": "Feature",
  "properties": {
    "iso:country":"GB",
    "wof:name":"TS25 3NF",
    "wof:placetype":"postalcode"
},
  "geometry": {"coordinates":[-1.2471704895765,54.65887900281508],"type":"Point"}
}