{
  "type": "Feature",
  "properties": {
    "iso:country":"GB",
    "wof:name":"TW14 9SJ",
    "wof:placetype":"postalcode"
},
  "geometry": {"coordinates":[-0.42431232645842,51.45593338602401],"type":"Point"}
}