{
  "type": "Feature",
  "properties": {
    "iso:country": "GB",
    "wof:name": "RG42 6DJ",
    "wof:placetype": "postalcode"
  },
  "geometry": {"coordinates":[-0.751741,51.4338],"type":"Point"}
}
