{
  "type": "Feature",
  "properties": {
    "iso:country":"GB",
    "wof:name":"TW5 0UQ",
    "wof:placetype":"postalcode"
},
  "geometry": {"coordinates":[-0.37020285186233,51.48837537413382],"type":"Point"}
}