{
  "type": "Feature",
  "properties": {
    "iso:country": "GB",
    "wof:name": "TW5 0UQ",
    "wof:placetype": "postalcode"
  },
  "geometry": {"coordinates":[-0.370203,51.488375],"type":"Point"}
}
