{
  "type": "Feature",
  "properties": {
    "iso:country":"GB",
    "wof:name":"BN25 3EN",
    "wof:placetype":"postalcode"
},
  "geometry": {"coordinates":[0.11402300743306,50.78361740864518],"type":"Point"}
}