{
  "type": "Feature",
  "properties": {
    "iso:country":"GB",
    "wof:name":"S11 9NE",
    "wof:placetype":"postalcode"
},
  "geometry": {"coordinates":[-1.52166243888232,53.34386507590055],"type":"Point"}
}