{
  "type": "Feature",
  "properties": {
    "date:inception_lower": "1998-06-01",
    "date:inception_upper": "1998-06-01",
    "iso:country": "GB",
    "wof:name": "L34 1PP",
    "wof:placetype": "postalcode"
  },
  "geometry": {"coordinates":[-2.827429,53.4234],"type":"Point"}
}
