{
  "type": "Feature",
  "properties": {
    "iso:country":"GB",
    "wof:name":"L34 1PP",
    "wof:placetype":"postalcode"
},
  "geometry": {"coordinates":[-2.82742924081905,53.4234003392511],"type":"Point"}
}