{
  "type": "Feature",
  "properties": {
    "iso:country":"GB",
    "wof:name":"MK42 7GJ",
    "wof:placetype":"postalcode"
},
  "geometry": {"coordinates":[-0.51646302423527,52.11039377295916],"type":"Point"}
}