{
  "type": "Feature",
  "properties": {
    "date:inception_lower": "2015-09-01",
    "date:inception_upper": "2015-09-01",
    "iso:country": "GB",
    "wof:name": "MK42 7GJ",
    "wof:placetype": "postalcode"
  },
  "geometry": {"coordinates":[-0.516463,52.110394],"type":"Point"}
}
