{
  "type": "Feature",
  "properties": {
    "iso:country":"GB",
    "wof:name":"BA1 2LZ",
    "wof:placetype":"postalcode"
},
  "geometry": {"coordinates":[-2.37190191430379,51.38638712183574],"type":"Point"}
}