{
  "type": "Feature",
  "properties": {
    "iso:country":"GB",
    "wof:name":"KA11 4DQ",
    "wof:placetype":"postalcode"
},
  "geometry": {"coordinates":[-4.61403303980717,55.61128338749958],"type":"Point"}
}