{
  "type": "Feature",
  "properties": {
    "date:inception_lower": "2004-07-01",
    "date:inception_upper": "2004-07-01",
    "iso:country": "GB",
    "wof:name": "KA11 4DQ",
    "wof:placetype": "postalcode"
  },
  "geometry": {"coordinates":[-4.614033,55.611283],"type":"Point"}
}
