{
  "type": "Feature",
  "properties": {
    "iso:country":"GB",
    "wof:name":"SE20 7LJ",
    "wof:placetype":"postalcode"
},
  "geometry": {"coordinates":[-0.05133808915457,51.41845700043149],"type":"Point"}
}