{
  "type": "Feature",
  "properties": {
    "iso:country": "GB",
    "wof:name": "L11 8LE",
    "wof:placetype": "postalcode"
  },
  "geometry": {"coordinates":[-2.928952,53.436074],"type":"Point"}
}
