{
  "type": "Feature",
  "properties": {
    "date:inception_lower":"1997-12-01",
    "date:inception_upper":"1997-12-31",
    "iso:country":"GB",
    "wof:name":"BS48 4PD",
    "wof:placetype":"postalcode"
},
  "geometry": {"coordinates":[-2.751721,51.426944],"type":"Point"}
}