{
  "type": "Feature",
  "properties": {
    "date:inception_lower": "1980-01-01",
    "date:inception_upper": "1980-01-01",
    "iso:country": "GB",
    "wof:name": "PO18 8RU",
    "wof:placetype": "postalcode"
  },
  "geometry": {"coordinates":[-0.894754,50.842853],"type":"Point"}
}
