{
  "type": "Feature",
  "properties": {
    "iso:country":"GB",
    "wof:name":"PO18 8RU",
    "wof:placetype":"postalcode"
},
  "geometry": {"coordinates":[-0.89475429232075,50.84285290041603],"type":"Point"}
}