{
  "type": "Feature",
  "properties": {
    "date:inception_lower": "2013-03-01",
    "date:inception_upper": "2013-03-01",
    "iso:country": "GB",
    "wof:name": "BS30 6AH",
    "wof:placetype": "postalcode"
  },
  "geometry": {"coordinates":[-2.445939,51.427812],"type":"Point"}
}
