{
  "type": "Feature",
  "properties": {
    "iso:country":"GB",
    "wof:name":"M33 7UB",
    "wof:placetype":"postalcode"
},
  "geometry": {"coordinates":[-2.32886700763418,53.41964853923057],"type":"Point"}
}