{
  "type": "Feature",
  "properties": {
    "iso:country":"GB",
    "wof:name":"SL9 0BT",
    "wof:placetype":"postalcode"
},
  "geometry": {"coordinates":[-0.55046567843062,51.60860945574954],"type":"Point"}
}