{
  "type": "Feature",
  "properties": {
    "iso:country": "GB",
    "wof:name": "CV37 9TH",
    "wof:placetype": "postalcode"
  },
  "geometry": {"coordinates":[-1.783606,52.183753],"type":"Point"}
}
