{
  "type": "Feature",
  "properties": {
    "date:inception_lower":"2013-11-01",
    "date:inception_upper":"2013-11-30",
    "iso:country":"GB",
    "wof:name":"SN12 7GR",
    "wof:placetype":"postalcode"
},
  "geometry": {"coordinates":[-2.135101,51.372142],"type":"Point"}
}