{
  "type": "Feature",
  "properties": {
    "iso:country":"GB",
    "wof:name":"NW6 1XN",
    "wof:placetype":"postalcode"
},
  "geometry": {"coordinates":[-0.19172545347538,51.54983027889268],"type":"Point"}
}