{
  "type": "Feature",
  "properties": {
    "iso:country":"GB",
    "wof:name":"B15 3UP",
    "wof:placetype":"postalcode"
},
  "geometry": {"coordinates":[-1.9524652133725,52.47165506989061],"type":"Point"}
}