{
  "type": "Feature",
  "properties": {
    "iso:country":"GB",
    "wof:name":"S20 5BF",
    "wof:placetype":"postalcode"
},
  "geometry": {"coordinates":[-1.36707315076944,53.3226511663806],"type":"Point"}
}