{
  "type": "Feature",
  "properties": {
    "date:inception_lower": "1980-01-01",
    "date:inception_upper": "1980-01-01",
    "iso:country": "GB",
    "wof:name": "CV11 4EJ",
    "wof:placetype": "postalcode"
  },
  "geometry": {"coordinates":[-1.46735,52.52304],"type":"Point"}
}
