{
  "type": "Feature",
  "properties": {
    "iso:country": "GB",
    "wof:name": "CV11 4EJ",
    "wof:placetype": "postalcode"
  },
  "geometry": {"coordinates":[-1.46735,52.52304],"type":"Point"}
}
