{
  "type": "Feature",
  "properties": {
    "iso:country":"GB",
    "wof:name":"NW3 4LT",
    "wof:placetype":"postalcode"
},
  "geometry": {"coordinates":[-0.16491479534897,51.54940500499929],"type":"Point"}
}