{
  "type": "Feature",
  "properties": {
    "iso:country":"GB",
    "wof:name":"AL3 8LJ",
    "wof:placetype":"postalcode"
},
  "geometry": {"coordinates":[-0.45842971753524,51.83634316909114],"type":"Point"}
}