{
  "type": "Feature",
  "properties": {
    "date:inception_lower":"1980-01-01",
    "date:inception_upper":"1980-01-31",
    "iso:country":"GB",
    "wof:name":"AL3 8LJ",
    "wof:placetype":"postalcode"
},
  "geometry": {"coordinates":[-0.458765,51.836455],"type":"Point"}
}