{
  "type": "Feature",
  "properties": {
    "iso:country": "GB",
    "wof:name": "DN7 5PT",
    "wof:placetype": "postalcode"
  },
  "geometry": {"coordinates":[-1.030547,53.59317],"type":"Point"}
}
