{
  "type": "Feature",
  "properties": {
    "date:inception_lower": "2019-06-01",
    "date:inception_upper": "2019-06-01",
    "iso:country": "GB",
    "wof:name": "DN7 5PT",
    "wof:placetype": "postalcode"
  },
  "geometry": {"coordinates":[-1.030846,53.593298],"type":"Point"}
}
