{
  "type": "Feature",
  "properties": {
    "iso:country":"GB",
    "wof:name":"BD18 1NA",
    "wof:placetype":"postalcode"
},
  "geometry": {"coordinates":[-1.75241992583126,53.82962888605186],"type":"Point"}
}