{
  "type": "Feature",
  "properties": {
    "iso:country": "GB",
    "wof:name": "BD18 1NA",
    "wof:placetype": "postalcode"
  },
  "geometry": {"coordinates":[-1.75242,53.829629],"type":"Point"}
}
