{
  "type": "Feature",
  "properties": {
    "iso:country":"GB",
    "wof:name":"GU5 0NH",
    "wof:placetype":"postalcode"
},
  "geometry": {"coordinates":[-0.57221712868341,51.16936181234308],"type":"Point"}
}