{
  "type": "Feature",
  "properties": {
    "iso:country": "GB",
    "wof:name": "BN6 8RR",
    "wof:placetype": "postalcode"
  },
  "geometry": {"coordinates":[-0.080723,50.908775],"type":"Point"}
}
