{
  "type": "Feature",
  "properties": {
    "date:inception_lower": "2023-09-01",
    "date:inception_upper": "2023-09-01",
    "iso:country": "GB",
    "wof:name": "B5 7QW",
    "wof:placetype": "postalcode"
  },
  "geometry": {"coordinates":[-1.906151,52.455559],"type":"Point"}
}
