{
  "type": "Feature",
  "properties": {
    "iso:country":"GB",
    "wof:name":"DE1 3HS",
    "wof:placetype":"postalcode"
},
  "geometry": {"coordinates":[-1.48481353105233,52.92919033717111],"type":"Point"}
}