{
  "type": "Feature",
  "properties": {
    "iso:country": "GB",
    "wof:name": "DE1 3HS",
    "wof:placetype": "postalcode"
  },
  "geometry": {"coordinates":[-1.48478,52.929181],"type":"Point"}
}
