{
  "type": "Feature",
  "properties": {
    "date:inception_lower": "1994-12-01",
    "date:inception_upper": "1994-12-01",
    "iso:country": "GB",
    "wof:name": "LL18 2UQ",
    "wof:placetype": "postalcode"
  },
  "geometry": {"coordinates":[-3.466473,53.291884],"type":"Point"}
}
