{
  "type": "Feature",
  "properties": {
    "iso:country": "GB",
    "wof:name": "LL18 2UQ",
    "wof:placetype": "postalcode"
  },
  "geometry": {"coordinates":[-3.466473,53.291884],"type":"Point"}
}
