{
  "type": "Feature",
  "properties": {
    "iso:country":"GB",
    "wof:name":"LL18 2UQ",
    "wof:placetype":"postalcode"
},
  "geometry": {"coordinates":[-3.46649104797344,53.29199302030399],"type":"Point"}
}