{
  "type": "Feature",
  "properties": {
    "iso:country":"GB",
    "wof:name":"WA10 6RE",
    "wof:placetype":"postalcode"
},
  "geometry": {"coordinates":[-2.75336639195115,53.45944100983754],"type":"Point"}
}