{
  "type": "Feature",
  "properties": {
    "date:inception_lower":"2013-11-01",
    "date:inception_upper":"2013-11-30",
    "iso:country":"GB",
    "wof:name":"SN15 3GR",
    "wof:placetype":"postalcode"
},
  "geometry": {"coordinates":[-2.103697,51.452229],"type":"Point"}
}