{
  "type": "Feature",
  "properties": {
    "iso:country": "GB",
    "wof:name": "SN15 3GR",
    "wof:placetype": "postalcode"
  },
  "geometry": {"coordinates":[-2.103697,51.452229],"type":"Point"}
}
