{
  "type": "Feature",
  "properties": {
    "iso:country":"GB",
    "wof:name":"LE1 7QR",
    "wof:placetype":"postalcode"
},
  "geometry": {"coordinates":[-1.12066680402853,52.62620216670935],"type":"Point"}
}