{
  "type": "Feature",
  "properties": {
    "iso:country":"GB",
    "wof:name":"KY4 0EH",
    "wof:placetype":"postalcode"
},
  "geometry": {"coordinates":[-3.38496078223347,56.13342747327928],"type":"Point"}
}