{
  "type": "Feature",
  "properties": {
    "iso:country":"GB",
    "wof:name":"BL2 3JJ",
    "wof:placetype":"postalcode"
},
  "geometry": {"coordinates":[-2.39323044369153,53.60125425646554],"type":"Point"}
}