{
  "type": "Feature",
  "properties": {
    "iso:country":"GB",
    "wof:name":"SN10 2EH",
    "wof:placetype":"postalcode"
},
  "geometry": {"coordinates":[-1.96673936318946,51.36838767743764],"type":"Point"}
}