{
  "type": "Feature",
  "properties": {
    "iso:country": "GB",
    "wof:name": "W7 3AR",
    "wof:placetype": "postalcode"
  },
  "geometry": {"coordinates":[-0.346622,51.52147],"type":"Point"}
}
