{
  "type": "Feature",
  "properties": {
    "iso:country":"GB",
    "wof:name":"W7 3AR",
    "wof:placetype":"postalcode"
},
  "geometry": {"coordinates":[-0.34662194886234,51.52146965950102],"type":"Point"}
}