{
  "type": "Feature",
  "properties": {
    "iso:country":"GB",
    "wof:name":"OX13 5DL",
    "wof:placetype":"postalcode"
},
  "geometry": {"coordinates":[-1.42427394009171,51.679794533364],"type":"Point"}
}