{
  "type": "Feature",
  "properties": {
    "iso:country": "GB",
    "wof:name": "SN9 6BQ",
    "wof:placetype": "postalcode"
  },
  "geometry": {"coordinates":[-1.778658,51.294335],"type":"Point"}
}
