{
  "type": "Feature",
  "properties": {
    "iso:country":"GB",
    "wof:name":"NP4 8RH",
    "wof:placetype":"postalcode"
},
  "geometry": {"coordinates":[-3.0110529130796,51.73429716309264],"type":"Point"}
}