{
  "type": "Feature",
  "properties": {
    "date:inception_lower":"1980-01-01",
    "date:inception_upper":"1980-01-31",
    "iso:country":"GB",
    "wof:name":"L6 4BA",
    "wof:placetype":"postalcode"
},
  "geometry": {"coordinates":[-2.945471,53.422136],"type":"Point"}
}