{
  "type": "Feature",
  "properties": {
    "iso:country":"GB",
    "wof:name":"SS17 7RA",
    "wof:placetype":"postalcode"
},
  "geometry": {"coordinates":[0.44450054491908,51.52410576261691],"type":"Point"}
}