{
  "type": "Feature",
  "properties": {
    "iso:country": "GB",
    "wof:name": "BS21 6QZ",
    "wof:placetype": "postalcode"
  },
  "geometry": {"coordinates":[-2.815434,51.441983],"type":"Point"}
}
