{
  "type": "Feature",
  "properties": {
    "iso:country":"GB",
    "wof:name":"BS21 6QZ",
    "wof:placetype":"postalcode"
},
  "geometry": {"coordinates":[-2.81543434649115,51.44198342499985],"type":"Point"}
}