{
  "type": "Feature",
  "properties": {
    "iso:country": "GB",
    "wof:name": "DE13 0YG",
    "wof:placetype": "postalcode"
  },
  "geometry": {"coordinates":[-1.641407,52.834604],"type":"Point"}
}
