{
  "type": "Feature",
  "properties": {
    "iso:country":"GB",
    "wof:name":"NW4 3RX",
    "wof:placetype":"postalcode"
},
  "geometry": {"coordinates":[-0.23179139391875,51.57964803576014],"type":"Point"}
}