{
  "type": "Feature",
  "properties": {
    "iso:country": "GB",
    "wof:name": "TS6 6XN",
    "wof:placetype": "postalcode"
  },
  "geometry": {"coordinates":[-1.173579,54.571279],"type":"Point"}
}
