{
  "type": "Feature",
  "properties": {
    "iso:country":"GB",
    "wof:name":"WA9 3TX",
    "wof:placetype":"postalcode"
},
  "geometry": {"coordinates":[-2.72156620482142,53.43420834201364],"type":"Point"}
}