{
  "type": "Feature",
  "properties": {
    "iso:country":"GB",
    "wof:name":"CA2 5UR",
    "wof:placetype":"postalcode"
},
  "geometry": {"coordinates":[-2.94878030828559,54.89256054234889],"type":"Point"}
}