{
  "type": "Feature",
  "properties": {
    "iso:country":"GB",
    "wof:name":"TA24 8AR",
    "wof:placetype":"postalcode"
},
  "geometry": {"coordinates":[-3.49179208649665,51.20301596524318],"type":"Point"}
}