{
  "type": "Feature",
  "properties": {
    "iso:country":"GB",
    "wof:name":"S65 4AE",
    "wof:placetype":"postalcode"
},
  "geometry": {"coordinates":[-1.30567304638212,53.44915029364615],"type":"Point"}
}