{
  "type": "Feature",
  "properties": {
    "date:inception_lower":"1980-01-01",
    "date:inception_upper":"1980-01-31",
    "iso:country":"GB",
    "wof:name":"S65 4AE",
    "wof:placetype":"postalcode"
},
  "geometry": {"coordinates":[-1.305673,53.44915],"type":"Point"}
}