{
  "type": "Feature",
  "properties": {
    "iso:country": "GB",
    "wof:name": "WA14 4UA",
    "wof:placetype": "postalcode"
  },
  "geometry": {"coordinates":[-2.360097,53.393932],"type":"Point"}
}
