{
  "type": "Feature",
  "properties": {
    "iso:country":"GB",
    "wof:name":"WA14 4UA",
    "wof:placetype":"postalcode"
},
  "geometry": {"coordinates":[-2.36009735125336,53.39393190368032],"type":"Point"}
}