{
  "type": "Feature",
  "properties": {
    "iso:country": "GB",
    "wof:name": "ST13 7BZ",
    "wof:placetype": "postalcode"
  },
  "geometry": {"coordinates":[-2.047712,53.051596],"type":"Point"}
}
