{
  "type": "Feature",
  "properties": {
    "iso:country":"GB",
    "wof:name":"PA2 9LW",
    "wof:placetype":"postalcode"
},
  "geometry": {"coordinates":[-4.44511810821775,55.82984495245317],"type":"Point"}
}