{
  "type": "Feature",
  "properties": {
    "iso:country":"GB",
    "wof:name":"FY7 7NX",
    "wof:placetype":"postalcode"
},
  "geometry": {"coordinates":[-3.02825415517426,53.90948847676372],"type":"Point"}
}