{
  "type": "Feature",
  "properties": {
    "iso:country":"GB",
    "wof:name":"LS25 4AF",
    "wof:placetype":"postalcode"
},
  "geometry": {"coordinates":[-1.32798428474392,53.79123274604766],"type":"Point"}
}