{
  "type": "Feature",
  "properties": {
    "iso:country": "GB",
    "wof:name": "ML4 2UY",
    "wof:placetype": "postalcode"
  },
  "geometry": {"coordinates":[-4.035907,55.80812],"type":"Point"}
}
