{
  "type": "Feature",
  "properties": {
    "iso:country":"GB",
    "wof:name":"ML4 2UY",
    "wof:placetype":"postalcode"
},
  "geometry": {"coordinates":[-4.03590755301072,55.80812021891288],"type":"Point"}
}