{
  "type": "Feature",
  "properties": {
    "iso:country":"GB",
    "wof:name":"EX23 0HE",
    "wof:placetype":"postalcode"
},
  "geometry": {"coordinates":[-4.51421809387639,50.80356369910609],"type":"Point"}
}