{
  "type": "Feature",
  "properties": {
    "date:inception_lower": "1980-01-01",
    "date:inception_upper": "1980-01-01",
    "iso:country": "GB",
    "wof:name": "EX23 0HE",
    "wof:placetype": "postalcode"
  },
  "geometry": {"coordinates":[-4.51425,50.803558],"type":"Point"}
}
