{
  "type": "Feature",
  "properties": {
    "iso:country": "GB",
    "wof:name": "EX23 0HE",
    "wof:placetype": "postalcode"
  },
  "geometry": {"coordinates":[-4.514508,50.803597],"type":"Point"}
}
