{
  "type": "Feature",
  "properties": {
    "iso:country":"GB",
    "wof:name":"MK43 9JY",
    "wof:placetype":"postalcode"
},
  "geometry": {"coordinates":[-0.52473188446319,52.10011261511809],"type":"Point"}
}