{
  "type": "Feature",
  "properties": {
    "iso:country": "GB",
    "wof:name": "MK43 9JY",
    "wof:placetype": "postalcode"
  },
  "geometry": {"coordinates":[-0.524732,52.100113],"type":"Point"}
}
