{
  "type": "Feature",
  "properties": {
    "date:inception_lower": "2018-09-01",
    "date:inception_upper": "2018-09-01",
    "iso:country": "GB",
    "wof:name": "E16 2TG",
    "wof:placetype": "postalcode"
  },
  "geometry": {"coordinates":[0.026687,51.499751],"type":"Point"}
}
