{
  "type": "Feature",
  "properties": {
    "iso:country":"GB",
    "wof:name":"B37 5JY",
    "wof:placetype":"postalcode"
},
  "geometry": {"coordinates":[-1.75787590713348,52.47485146682989],"type":"Point"}
}