{
  "type": "Feature",
  "properties": {
    "iso:country": "GB",
    "wof:name": "B37 5JY",
    "wof:placetype": "postalcode"
  },
  "geometry": {"coordinates":[-1.757876,52.474851],"type":"Point"}
}
