{
  "type": "Feature",
  "properties": {
    "iso:country": "GB",
    "wof:name": "WD24 5LN",
    "wof:placetype": "postalcode"
  },
  "geometry": {"coordinates":[-0.415762,51.682609],"type":"Point"}
}
