{
  "type": "Feature",
  "properties": {
    "iso:country":"GB",
    "wof:name":"WD24 5LN",
    "wof:placetype":"postalcode"
},
  "geometry": {"coordinates":[-0.41576180984476,51.68260880089714],"type":"Point"}
}