{
  "type": "Feature",
  "properties": {
    "date:inception_lower": "1995-12-01",
    "date:inception_upper": "1995-12-01",
    "iso:country": "GB",
    "wof:name": "CO11 1QB",
    "wof:placetype": "postalcode"
  },
  "geometry": {"coordinates":[1.057381,51.958277],"type":"Point"}
}
