{
  "type": "Feature",
  "properties": {
    "iso:country":"GB",
    "wof:name":"EH19 2AY",
    "wof:placetype":"postalcode"
},
  "geometry": {"coordinates":[-3.11212675310107,55.8753598449188],"type":"Point"}
}