{
  "type": "Feature",
  "properties": {
    "iso:country":"GB",
    "wof:name":"NN8 3TX",
    "wof:placetype":"postalcode"
},
  "geometry": {"coordinates":[-0.71649221789139,52.30455330483353],"type":"Point"}
}