{
  "type": "Feature",
  "properties": {
    "iso:country":"GB",
    "wof:name":"HP4 3EP",
    "wof:placetype":"postalcode"
},
  "geometry": {"coordinates":[-0.57112185837944,51.76193944648681],"type":"Point"}
}