{
  "type": "Feature",
  "properties": {
    "iso:country":"GB",
    "wof:name":"EX31 3LX",
    "wof:placetype":"postalcode"
},
  "geometry": {"coordinates":[-4.07167083176307,51.00210306078122],"type":"Point"}
}