{
  "type": "Feature",
  "properties": {
    "iso:country":"GB",
    "wof:name":"BD6 1AA",
    "wof:placetype":"postalcode"
},
  "geometry": {"coordinates":[-1.75535709925507,53.76611685135964],"type":"Point"}
}