{
  "type": "Feature",
  "properties": {
    "date:inception_lower": "2014-12-01",
    "date:inception_upper": "2014-12-01",
    "iso:country": "GB",
    "wof:name": "BD6 1AA",
    "wof:placetype": "postalcode"
  },
  "geometry": {"coordinates":[-1.755357,53.766117],"type":"Point"}
}
