{
  "type": "Feature",
  "properties": {
    "iso:country":"GB",
    "wof:name":"SO15 2LW",
    "wof:placetype":"postalcode"
},
  "geometry": {"coordinates":[-1.4104683847447,50.91634252789428],"type":"Point"}
}