{
  "type": "Feature",
  "properties": {
    "date:inception_lower": "1994-12-01",
    "date:inception_upper": "1994-12-01",
    "iso:country": "GB",
    "wof:name": "SO15 2LW",
    "wof:placetype": "postalcode"
  },
  "geometry": {"coordinates":[-1.41046,50.916334],"type":"Point"}
}
