{
  "type": "Feature",
  "properties": {
    "iso:country":"GB",
    "wof:name":"UB10 0NS",
    "wof:placetype":"postalcode"
},
  "geometry": {"coordinates":[-0.44462616088958,51.52860095669346],"type":"Point"}
}