{
  "type": "Feature",
  "properties": {
    "iso:country": "GB",
    "wof:name": "UB10 0NS",
    "wof:placetype": "postalcode"
  },
  "geometry": {"coordinates":[-0.444626,51.528601],"type":"Point"}
}
