{
  "type": "Feature",
  "properties": {
    "date:inception_lower":"2007-02-01",
    "date:inception_upper":"2007-02-28",
    "iso:country":"GB",
    "wof:name":"M24 5SU",
    "wof:placetype":"postalcode"
},
  "geometry": {"coordinates":[-2.213473,53.563348],"type":"Point"}
}