{
  "type": "Feature",
  "properties": {
    "iso:country":"GB",
    "wof:name":"M24 5SU",
    "wof:placetype":"postalcode"
},
  "geometry": {"coordinates":[-2.21347264124106,53.56334824682365],"type":"Point"}
}