{
  "type": "Feature",
  "properties": {
    "iso:country":"GB",
    "wof:name":"HU8 0EU",
    "wof:placetype":"postalcode"
},
  "geometry": {"coordinates":[-0.3126737000445,53.7689662506926],"type":"Point"}
}