{
  "type": "Feature",
  "properties": {
    "iso:country":"GB",
    "wof:name":"BD18 4ER",
    "wof:placetype":"postalcode"
},
  "geometry": {"coordinates":[-1.80314730601749,53.83024402989798],"type":"Point"}
}