{
  "type": "Feature",
  "properties": {
    "iso:country":"GB",
    "wof:name":"SS6 7NW",
    "wof:placetype":"postalcode"
},
  "geometry": {"coordinates":[0.61584473672444,51.57713055812489],"type":"Point"}
}