{
  "type": "Feature",
  "properties": {
    "iso:country":"GB",
    "wof:name":"LN8 5LJ",
    "wof:placetype":"postalcode"
},
  "geometry": {"coordinates":[-0.15987755714671,53.303352530043],"type":"Point"}
}