{
  "type": "Feature",
  "properties": {
    "iso:country": "GB",
    "wof:name": "LN8 5LJ",
    "wof:placetype": "postalcode"
  },
  "geometry": {"coordinates":[-0.159878,53.303353],"type":"Point"}
}
