{
  "type": "Feature",
  "properties": {
    "iso:country":"GB",
    "wof:name":"IP2 8JW",
    "wof:placetype":"postalcode"
},
  "geometry": {"coordinates":[1.15486742847609,52.04682166035619],"type":"Point"}
}