{
  "type": "Feature",
  "properties": {
    "date:inception_lower": "1980-01-01",
    "date:inception_upper": "1980-01-01",
    "iso:country": "GB",
    "wof:name": "PO20 7EA",
    "wof:placetype": "postalcode"
  },
  "geometry": {"coordinates":[-0.80254,50.818634],"type":"Point"}
}
