{
  "type": "Feature",
  "properties": {
    "iso:country": "GB",
    "wof:name": "PO20 7EA",
    "wof:placetype": "postalcode"
  },
  "geometry": {"coordinates":[-0.80254,50.818634],"type":"Point"}
}
