{
  "type": "Feature",
  "properties": {
    "iso:country":"GB",
    "wof:name":"SY5 7LP",
    "wof:placetype":"postalcode"
},
  "geometry": {"coordinates":[-2.75738788142111,52.62749035547566],"type":"Point"}
}