{
  "type": "Feature",
  "properties": {
    "date:inception_lower": "1980-01-01",
    "date:inception_upper": "1980-01-01",
    "iso:country": "GB",
    "wof:name": "SY5 7LP",
    "wof:placetype": "postalcode"
  },
  "geometry": {"coordinates":[-2.757388,52.62749],"type":"Point"}
}
