{
  "type": "Feature",
  "properties": {
    "date:inception_lower":"1980-01-01",
    "date:inception_upper":"1980-01-31",
    "iso:country":"GB",
    "wof:name":"NE47 6AB",
    "wof:placetype":"postalcode"
},
  "geometry": {"coordinates":[-2.244512,54.97288],"type":"Point"}
}