{
  "type": "Feature",
  "properties": {
    "iso:country": "GB",
    "wof:name": "PL11 3BH",
    "wof:placetype": "postalcode"
  },
  "geometry": {"coordinates":[-4.299034,50.368113],"type":"Point"}
}
