{
  "type": "Feature",
  "properties": {
    "iso:country":"GB",
    "wof:name":"PL11 3BH",
    "wof:placetype":"postalcode"
},
  "geometry": {"coordinates":[-4.2990339249797,50.36811345117404],"type":"Point"}
}