{
  "type": "Feature",
  "properties": {
    "date:inception_lower":"1980-01-01",
    "date:inception_upper":"1980-01-31",
    "iso:country":"GB",
    "wof:name":"PL11 3BH",
    "wof:placetype":"postalcode"
},
  "geometry": {"coordinates":[-4.299034,50.368113],"type":"Point"}
}