{
  "type": "Feature",
  "properties": {
    "date:inception_lower": "1980-01-01",
    "date:inception_upper": "1980-01-01",
    "iso:country": "GB",
    "wof:name": "EX22 6TY",
    "wof:placetype": "postalcode"
  },
  "geometry": {"coordinates":[-4.457575,50.755492],"type":"Point"}
}
