{
  "type": "Feature",
  "properties": {
    "iso:country":"GB",
    "wof:name":"EX22 6TY",
    "wof:placetype":"postalcode"
},
  "geometry": {"coordinates":[-4.45757520299348,50.75549207656934],"type":"Point"}
}