{
  "type": "Feature",
  "properties": {
    "iso:country":"GB",
    "wof:name":"DT6 6QP",
    "wof:placetype":"postalcode"
},
  "geometry": {"coordinates":[-2.89735712541307,50.73885907102748],"type":"Point"}
}