{
  "type": "Feature",
  "properties": {
    "date:inception_lower":"2003-05-01",
    "date:inception_upper":"2003-05-31",
    "iso:country":"GB",
    "wof:name":"CB1 2NX",
    "wof:placetype":"postalcode"
},
  "geometry": {"coordinates":[0.143069,52.20336],"type":"Point"}
}