{
  "type": "Feature",
  "properties": {
    "date:inception_lower": "1980-01-01",
    "date:inception_upper": "1980-01-01",
    "iso:country": "GB",
    "wof:name": "HA1 4ET",
    "wof:placetype": "postalcode"
  },
  "geometry": {"coordinates":[-0.346928,51.581074],"type":"Point"}
}
