{
  "type": "Feature",
  "properties": {
    "iso:country":"GB",
    "wof:name":"YO12 5JP",
    "wof:placetype":"postalcode"
},
  "geometry": {"coordinates":[-0.42467087935278,54.28225968774355],"type":"Point"}
}