{
  "type": "Feature",
  "properties": {
    "iso:country": "GB",
    "wof:name": "ME9 8XA",
    "wof:placetype": "postalcode"
  },
  "geometry": {"coordinates":[0.722152,51.37523],"type":"Point"}
}
