{
  "type": "Feature",
  "properties": {
    "date:inception_lower":"2013-11-01",
    "date:inception_upper":"2013-11-30",
    "iso:country":"GB",
    "wof:name":"ME9 8XA",
    "wof:placetype":"postalcode"
},
  "geometry": {"coordinates":[0.722152,51.37523],"type":"Point"}
}