{
  "type": "Feature",
  "properties": {
    "iso:country":"GB",
    "wof:name":"ME9 8XA",
    "wof:placetype":"postalcode"
},
  "geometry": {"coordinates":[0.72215224232525,51.37522982378057],"type":"Point"}
}