{
  "type": "Feature",
  "properties": {
    "date:inception_lower":"1991-01-01",
    "date:inception_upper":"1991-01-31",
    "iso:country":"GB",
    "wof:name":"LL19 7HJ",
    "wof:placetype":"postalcode"
},
  "geometry": {"coordinates":[-3.399338,53.338835],"type":"Point"}
}