{
  "type": "Feature",
  "properties": {
    "date:inception_lower": "1980-01-01",
    "date:inception_upper": "1980-01-01",
    "iso:country": "GB",
    "wof:name": "NN9 5HW",
    "wof:placetype": "postalcode"
  },
  "geometry": {"coordinates":[-0.628717,52.364117],"type":"Point"}
}
