{
  "type": "Feature",
  "properties": {
    "iso:country":"GB",
    "wof:name":"NN9 5HW",
    "wof:placetype":"postalcode"
},
  "geometry": {"coordinates":[-0.62442515952218,52.36947379313423],"type":"Point"}
}