{
  "type": "Feature",
  "properties": {
    "date:inception_lower": "1980-01-01",
    "date:inception_upper": "1980-01-01",
    "iso:country": "GB",
    "wof:name": "SY13 2LR",
    "wof:placetype": "postalcode"
  },
  "geometry": {"coordinates":[-2.788002,52.910755],"type":"Point"}
}
