{
  "type": "Feature",
  "properties": {
    "iso:country":"GB",
    "wof:name":"SY13 2LR",
    "wof:placetype":"postalcode"
},
  "geometry": {"coordinates":[-2.788002054225,52.91075521631788],"type":"Point"}
}