{
  "type": "Feature",
  "properties": {
    "date:inception_lower":"1980-01-01",
    "date:inception_upper":"1980-01-31",
    "iso:country":"GB",
    "wof:name":"MK3 7JZ",
    "wof:placetype":"postalcode"
},
  "geometry": {"coordinates":[-0.749461,52.005157],"type":"Point"}
}