{
  "type": "Feature",
  "properties": {
    "iso:country": "GB",
    "wof:name": "BS7 8DN",
    "wof:placetype": "postalcode"
  },
  "geometry": {"coordinates":[-2.595601,51.473168],"type":"Point"}
}
