{
  "type": "Feature",
  "properties": {
    "iso:country":"GB",
    "wof:name":"DT2 0PW",
    "wof:placetype":"postalcode"
},
  "geometry": {"coordinates":[-2.65593484130181,50.81932449929284],"type":"Point"}
}