{
  "type": "Feature",
  "properties": {
    "iso:country": "GB",
    "wof:name": "SO51 8AB",
    "wof:placetype": "postalcode"
  },
  "geometry": {"coordinates":[-1.491669,50.989239],"type":"Point"}
}
