{
  "type": "Feature",
  "properties": {
    "iso:country": "GB",
    "wof:name": "EX4 6PG",
    "wof:placetype": "postalcode"
  },
  "geometry": {"coordinates":[-3.525104,50.729169],"type":"Point"}
}
