{
  "type": "Feature",
  "properties": {
    "iso:country": "GB",
    "wof:name": "LE67 4DR",
    "wof:placetype": "postalcode"
  },
  "geometry": {"coordinates":[-1.357685,52.721883],"type":"Point"}
}
