{
  "type": "Feature",
  "properties": {
    "date:inception_lower": "2000-12-01",
    "date:inception_upper": "2000-12-01",
    "iso:country": "GB",
    "wof:name": "LE67 4DR",
    "wof:placetype": "postalcode"
  },
  "geometry": {"coordinates":[-1.357685,52.721883],"type":"Point"}
}
