{
  "type": "Feature",
  "properties": {
    "date:inception_lower": "2022-08-01",
    "date:inception_upper": "2022-08-01",
    "iso:country": "GB",
    "wof:name": "CW7 3SR",
    "wof:placetype": "postalcode"
  },
  "geometry": {"coordinates":[-2.507316,53.206732],"type":"Point"}
}
