{
  "type": "Feature",
  "properties": {
    "iso:country":"GB",
    "wof:name":"SA16 0HY",
    "wof:placetype":"postalcode"
},
  "geometry": {"coordinates":[-4.26285621683512,51.68494603650004],"type":"Point"}
}