{
  "type": "Feature",
  "properties": {
    "iso:country": "GB",
    "wof:name": "SA16 0HY",
    "wof:placetype": "postalcode"
  },
  "geometry": {"coordinates":[-4.262856,51.684946],"type":"Point"}
}
