{
  "type": "Feature",
  "properties": {
    "iso:country":"GB",
    "wof:name":"N1 3DU",
    "wof:placetype":"postalcode"
},
  "geometry": {"coordinates":[-0.08693740161982,51.53780901165921],"type":"Point"}
}