{
  "type": "Feature",
  "properties": {
    "iso:country":"GB",
    "wof:name":"LA12 7LY",
    "wof:placetype":"postalcode"
},
  "geometry": {"coordinates":[-3.08273802413212,54.19847013206328],"type":"Point"}
}