{
  "type": "Feature",
  "properties": {
    "iso:country":"GB",
    "wof:name":"NR2 4BH",
    "wof:placetype":"postalcode"
},
  "geometry": {"coordinates":[1.2818265226218,52.63247020031132],"type":"Point"}
}