{
  "type": "Feature",
  "properties": {
    "iso:country": "GB",
    "wof:name": "BA21 5LU",
    "wof:placetype": "postalcode"
  },
  "geometry": {"coordinates":[-2.620371,50.949607],"type":"Point"}
}
