{
  "type": "Feature",
  "properties": {
    "iso:country":"GB",
    "wof:name":"BA21 5LU",
    "wof:placetype":"postalcode"
},
  "geometry": {"coordinates":[-2.62058658628606,50.94977463692263],"type":"Point"}
}