{
  "type": "Feature",
  "properties": {
    "iso:country":"GB",
    "wof:name":"SL6 2SX",
    "wof:placetype":"postalcode"
},
  "geometry": {"coordinates":[-0.73341380670925,51.51290313659966],"type":"Point"}
}