{
  "type": "Feature",
  "properties": {
    "iso:country":"GB",
    "wof:name":"CH43 9TU",
    "wof:placetype":"postalcode"
},
  "geometry": {"coordinates":[-3.06189981247739,53.38105879420578],"type":"Point"}
}