{
  "type": "Feature",
  "properties": {
    "iso:country": "GB",
    "wof:name": "DA14 5EB",
    "wof:placetype": "postalcode"
  },
  "geometry": {"coordinates":[0.136157,51.427861],"type":"Point"}
}
