{
  "type": "Feature",
  "properties": {
    "date:inception_lower":"2018-09-01",
    "date:inception_upper":"2018-09-30",
    "iso:country":"GB",
    "wof:name":"DA14 5EB",
    "wof:placetype":"postalcode"
},
  "geometry": {"coordinates":[0.136157,51.427861],"type":"Point"}
}