{
  "type": "Feature",
  "properties": {
    "iso:country":"GB",
    "wof:name":"KY10 3AH",
    "wof:placetype":"postalcode"
},
  "geometry": {"coordinates":[-2.68423240935535,56.22601632925851],"type":"Point"}
}