{
  "type": "Feature",
  "properties": {
    "iso:country": "GB",
    "wof:name": "BD4 8EP",
    "wof:placetype": "postalcode"
  },
  "geometry": {"coordinates":[-1.702829,53.788864],"type":"Point"}
}
