{
  "type": "Feature",
  "properties": {
    "iso:country":"GB",
    "wof:name":"BD4 8EP",
    "wof:placetype":"postalcode"
},
  "geometry": {"coordinates":[-1.70282862372328,53.78886380134772],"type":"Point"}
}