{
  "type": "Feature",
  "properties": {
    "date:inception_lower": "1980-01-01",
    "date:inception_upper": "1980-01-01",
    "iso:country": "GB",
    "wof:name": "BD4 8EP",
    "wof:placetype": "postalcode"
  },
  "geometry": {"coordinates":[-1.702829,53.788864],"type":"Point"}
}
