{
  "type": "Feature",
  "properties": {
    "iso:country": "GB",
    "wof:name": "KT17 2JW",
    "wof:placetype": "postalcode"
  },
  "geometry": {"coordinates":[-0.242871,51.36655],"type":"Point"}
}
