{
  "type": "Feature",
  "properties": {
    "iso:country":"GB",
    "wof:name":"KT17 2JW",
    "wof:placetype":"postalcode"
},
  "geometry": {"coordinates":[-0.24287056145101,51.36654952825376],"type":"Point"}
}