{
  "type": "Feature",
  "properties": {
    "iso:country":"GB",
    "wof:name":"B7 5EA",
    "wof:placetype":"postalcode"
},
  "geometry": {"coordinates":[-1.87653307276581,52.49786002436469],"type":"Point"}
}