{
  "type": "Feature",
  "properties": {
    "iso:country":"GB",
    "wof:name":"DN17 4FB",
    "wof:placetype":"postalcode"
},
  "geometry": {"coordinates":[-0.83846786586562,53.6083383658153],"type":"Point"}
}