{
  "type": "Feature",
  "properties": {
    "iso:country": "GB",
    "wof:name": "SY4 5HX",
    "wof:placetype": "postalcode"
  },
  "geometry": {"coordinates":[-2.713246,52.855268],"type":"Point"}
}
