{
  "type": "Feature",
  "properties": {
    "iso:country":"GB",
    "wof:name":"SY4 5HX",
    "wof:placetype":"postalcode"
},
  "geometry": {"coordinates":[-2.71324570561132,52.85526786499204],"type":"Point"}
}