{
  "type": "Feature",
  "properties": {
    "iso:country":"GB",
    "wof:name":"NG17 7RE",
    "wof:placetype":"postalcode"
},
  "geometry": {"coordinates":[-1.23780596033392,53.1061132195193],"type":"Point"}
}