{
  "type": "Feature",
  "properties": {
    "iso:country":"GB",
    "wof:name":"KT12 1HY",
    "wof:placetype":"postalcode"
},
  "geometry": {"coordinates":[-0.41739498907909,51.38372160137317],"type":"Point"}
}