{
  "type": "Feature",
  "properties": {
    "iso:country": "GB",
    "wof:name": "KT12 1HY",
    "wof:placetype": "postalcode"
  },
  "geometry": {"coordinates":[-0.417285,51.3838],"type":"Point"}
}
