{
  "type": "Feature",
  "properties": {
    "iso:country":"GB",
    "wof:name":"WV1 1DG",
    "wof:placetype":"postalcode"
},
  "geometry": {"coordinates":[-2.12674268842822,52.58634327943432],"type":"Point"}
}