{
  "type": "Feature",
  "properties": {
    "date:inception_lower": "1980-01-01",
    "date:inception_upper": "1980-01-01",
    "iso:country": "GB",
    "wof:name": "WV1 1DG",
    "wof:placetype": "postalcode"
  },
  "geometry": {"coordinates":[-2.126869,52.586385],"type":"Point"}
}
