{
  "type": "Feature",
  "properties": {
    "iso:country": "GB",
    "wof:name": "WV1 1DG",
    "wof:placetype": "postalcode"
  },
  "geometry": {"coordinates":[-2.126766,52.586412],"type":"Point"}
}
