{
  "type": "Feature",
  "properties": {
    "iso:country": "GB",
    "wof:name": "LD7 1HE",
    "wof:placetype": "postalcode"
  },
  "geometry": {"coordinates":[-3.056542,52.342156],"type":"Point"}
}
