{
  "type": "Feature",
  "properties": {
    "iso:country":"GB",
    "wof:name":"LD7 1HE",
    "wof:placetype":"postalcode"
},
  "geometry": {"coordinates":[-3.05654179279847,52.34215644273299],"type":"Point"}
}