{
  "type": "Feature",
  "properties": {
    "iso:country":"GB",
    "wof:name":"S66 3RB",
    "wof:placetype":"postalcode"
},
  "geometry": {"coordinates":[-1.27809452792116,53.43276228846728],"type":"Point"}
}