{
  "type": "Feature",
  "properties": {
    "iso:country":"GB",
    "wof:name":"PE15 8LH",
    "wof:placetype":"postalcode"
},
  "geometry": {"coordinates":[0.09153564767463,52.55272905697998],"type":"Point"}
}