{
  "type": "Feature",
  "properties": {
    "iso:country": "GB",
    "wof:name": "PE15 8LH",
    "wof:placetype": "postalcode"
  },
  "geometry": {"coordinates":[0.091536,52.552729],"type":"Point"}
}
