{
  "type": "Feature",
  "properties": {
    "iso:country": "GB",
    "wof:name": "SR7 9BS",
    "wof:placetype": "postalcode"
  },
  "geometry": {"coordinates":[-1.38528,54.815398],"type":"Point"}
}
