{
  "type": "Feature",
  "properties": {
    "iso:country":"GB",
    "wof:name":"TN21 8DB",
    "wof:placetype":"postalcode"
},
  "geometry": {"coordinates":[0.25092925990413,50.96920617651016],"type":"Point"}
}