{
  "type": "Feature",
  "properties": {
    "date:inception_lower": "1981-06-01",
    "date:inception_upper": "1981-06-01",
    "iso:country": "GB",
    "wof:name": "TN21 8DB",
    "wof:placetype": "postalcode"
  },
  "geometry": {"coordinates":[0.251251,50.969088],"type":"Point"}
}
