{
  "type": "Feature",
  "properties": {
    "date:inception_lower": "1995-07-01",
    "date:inception_upper": "1995-07-01",
    "iso:country": "GB",
    "wof:name": "MK43 0UR",
    "wof:placetype": "postalcode"
  },
  "geometry": {"coordinates":[-0.553133,52.062072],"type":"Point"}
}
