{
  "type": "Feature",
  "properties": {
    "iso:country":"GB",
    "wof:name":"YO24 1DE",
    "wof:placetype":"postalcode"
},
  "geometry": {"coordinates":[-1.09356874528934,53.9506779019523],"type":"Point"}
}