{
  "type": "Feature",
  "properties": {
    "iso:country":"GB",
    "wof:name":"G72 8UU",
    "wof:placetype":"postalcode"
},
  "geometry": {"coordinates":[-4.14240756156434,55.80916819116495],"type":"Point"}
}