{
  "type": "Feature",
  "properties": {
    "iso:country":"GB",
    "wof:name":"EH7 5UH",
    "wof:placetype":"postalcode"
},
  "geometry": {"coordinates":[-3.16121998185888,55.95859722553377],"type":"Point"}
}