{
  "type": "Feature",
  "properties": {
    "date:inception_lower":"1980-01-01",
    "date:inception_upper":"1980-01-31",
    "iso:country":"GB",
    "wof:name":"EH7 5UH",
    "wof:placetype":"postalcode"
},
  "geometry": {"coordinates":[-3.16122,55.958597],"type":"Point"}
}