{
  "type": "Feature",
  "properties": {
    "iso:country": "GB",
    "wof:name": "NP4 0QW",
    "wof:placetype": "postalcode"
  },
  "geometry": {"coordinates":[-3.00504,51.693698],"type":"Point"}
}
