{
  "type": "Feature",
  "properties": {
    "iso:country": "GB",
    "wof:name": "YO61 2RT",
    "wof:placetype": "postalcode"
  },
  "geometry": {"coordinates":[-1.386474,54.134223],"type":"Point"}
}
