{
  "type": "Feature",
  "properties": {
    "date:inception_lower":"1998-06-01",
    "date:inception_upper":"1998-06-30",
    "iso:country":"GB",
    "wof:name":"YO61 2RT",
    "wof:placetype":"postalcode"
},
  "geometry": {"coordinates":[-1.386474,54.134223],"type":"Point"}
}