{
  "type": "Feature",
  "properties": {
    "iso:country":"GB",
    "wof:name":"CF83 8DT",
    "wof:placetype":"postalcode"
},
  "geometry": {"coordinates":[-3.18350440097395,51.59099602482519],"type":"Point"}
}