{
  "type": "Feature",
  "properties": {
    "date:inception_lower": "2008-05-01",
    "date:inception_upper": "2008-05-01",
    "iso:country": "GB",
    "wof:name": "G66 7BD",
    "wof:placetype": "postalcode"
  },
  "geometry": {"coordinates":[-4.221456,55.97848],"type":"Point"}
}
