{
  "type": "Feature",
  "properties": {
    "iso:country":"GB",
    "wof:name":"G66 7BD",
    "wof:placetype":"postalcode"
},
  "geometry": {"coordinates":[-4.22145584878509,55.97847959100216],"type":"Point"}
}