{
  "type": "Feature",
  "properties": {
    "iso:country":"GB",
    "wof:name":"DE4 5BS",
    "wof:placetype":"postalcode"
},
  "geometry": {"coordinates":[-1.47918223304772,53.08099437967996],"type":"Point"}
}