{
  "type": "Feature",
  "properties": {
    "iso:country": "GB",
    "wof:name": "DE4 5BS",
    "wof:placetype": "postalcode"
  },
  "geometry": {"coordinates":[-1.479182,53.080994],"type":"Point"}
}
