{
  "type": "Feature",
  "properties": {
    "iso:country":"GB",
    "wof:name":"SS6 7XN",
    "wof:placetype":"postalcode"
},
  "geometry": {"coordinates":[0.61212449497049,51.57694365473879],"type":"Point"}
}