{
  "type": "Feature",
  "properties": {
    "iso:country":"GB",
    "wof:name":"BR2 9QN",
    "wof:placetype":"postalcode"
},
  "geometry": {"coordinates":[0.03474862727026,51.39272217693678],"type":"Point"}
}