{
  "type": "Feature",
  "properties": {
    "iso:country":"GB",
    "wof:name":"PE15 8JG",
    "wof:placetype":"postalcode"
},
  "geometry": {"coordinates":[0.08440398964199,52.56036267326811],"type":"Point"}
}