{
  "type": "Feature",
  "properties": {
    "date:inception_lower": "1980-01-01",
    "date:inception_upper": "1980-01-01",
    "iso:country": "GB",
    "wof:name": "PE15 8JG",
    "wof:placetype": "postalcode"
  },
  "geometry": {"coordinates":[0.084404,52.560363],"type":"Point"}
}
