{
  "type": "Feature",
  "properties": {
    "iso:country": "GB",
    "wof:name": "LN2 2DT",
    "wof:placetype": "postalcode"
  },
  "geometry": {"coordinates":[-0.530965,53.249681],"type":"Point"}
}
