{
  "type": "Feature",
  "properties": {
    "iso:country":"GB",
    "wof:name":"LN2 2DT",
    "wof:placetype":"postalcode"
},
  "geometry": {"coordinates":[-0.53096507432863,53.2496811514709],"type":"Point"}
}