{
  "type": "Feature",
  "properties": {
    "iso:country":"GB",
    "wof:name":"BH23 2JW",
    "wof:placetype":"postalcode"
},
  "geometry": {"coordinates":[-1.79282049427623,50.74497189719779],"type":"Point"}
}