{
  "type": "Feature",
  "properties": {
    "iso:country": "GB",
    "wof:name": "LN3 4HE",
    "wof:placetype": "postalcode"
  },
  "geometry": {"coordinates":[-0.431849,53.235267],"type":"Point"}
}
