{
  "type": "Feature",
  "properties": {
    "date:inception_lower": "1985-04-01",
    "date:inception_upper": "1985-04-01",
    "iso:country": "GB",
    "wof:name": "SK11 8EN",
    "wof:placetype": "postalcode"
  },
  "geometry": {"coordinates":[-2.13446,53.256594],"type":"Point"}
}
