{
  "type": "Feature",
  "properties": {
    "iso:country":"GB",
    "wof:name":"SK11 8EN",
    "wof:placetype":"postalcode"
},
  "geometry": {"coordinates":[-2.13446012509431,53.25659426635053],"type":"Point"}
}