{
  "type": "Feature",
  "properties": {
    "iso:country":"GB",
    "wof:name":"ME16 0EE",
    "wof:placetype":"postalcode"
},
  "geometry": {"coordinates":[0.50250758846228,51.28041711688112],"type":"Point"}
}