{
  "type": "Feature",
  "properties": {
    "iso:country":"GB",
    "wof:name":"NP4 8TR",
    "wof:placetype":"postalcode"
},
  "geometry": {"coordinates":[-3.04167533719114,51.72589237853128],"type":"Point"}
}