{
  "type": "Feature",
  "properties": {
    "iso:country":"GB",
    "wof:name":"LN4 4FE",
    "wof:placetype":"postalcode"
},
  "geometry": {"coordinates":[-0.16801569460668,53.10280867199542],"type":"Point"}
}