{
  "type": "Feature",
  "properties": {
    "date:inception_lower": "1980-01-01",
    "date:inception_upper": "1980-01-01",
    "iso:country": "GB",
    "wof:name": "BH18 8EA",
    "wof:placetype": "postalcode"
  },
  "geometry": {"coordinates":[-1.991314,50.759903],"type":"Point"}
}
