{
  "type": "Feature",
  "properties": {
    "iso:country": "GB",
    "wof:name": "CW12 2FS",
    "wof:placetype": "postalcode"
  },
  "geometry": {"coordinates":[-2.203294,53.1689],"type":"Point"}
}
