{
  "type": "Feature",
  "properties": {
    "date:inception_lower":"2015-01-01",
    "date:inception_upper":"2015-01-31",
    "iso:country":"GB",
    "wof:name":"CW12 2FS",
    "wof:placetype":"postalcode"
},
  "geometry": {"coordinates":[-2.203294,53.1689],"type":"Point"}
}