{
  "type": "Feature",
  "properties": {
    "iso:country": "GB",
    "wof:name": "RG10 0SD",
    "wof:placetype": "postalcode"
  },
  "geometry": {"coordinates":[-0.853409,51.453928],"type":"Point"}
}
