{
  "type": "Feature",
  "properties": {
    "iso:country":"GB",
    "wof:name":"RG10 0SD",
    "wof:placetype":"postalcode"
},
  "geometry": {"coordinates":[-0.85340917022463,51.45392752429174],"type":"Point"}
}