{
  "type": "Feature",
  "properties": {
    "iso:country":"GB",
    "wof:name":"G14 9YF",
    "wof:placetype":"postalcode"
},
  "geometry": {"coordinates":[-4.35490236895066,55.88091245373701],"type":"Point"}
}