{
  "type": "Feature",
  "properties": {
    "date:inception_lower":"1999-12-01",
    "date:inception_upper":"1999-12-31",
    "iso:country":"GB",
    "wof:name":"SE16 5UN",
    "wof:placetype":"postalcode"
},
  "geometry": {"coordinates":[-0.033822,51.499153],"type":"Point"}
}