{
  "type": "Feature",
  "properties": {
    "iso:country":"GB",
    "wof:name":"HU15 2EN",
    "wof:placetype":"postalcode"
},
  "geometry": {"coordinates":[-0.61562252872556,53.76464041925552],"type":"Point"}
}