{
  "type": "Feature",
  "properties": {
    "iso:country":"GB",
    "wof:name":"CM20 3EL",
    "wof:placetype":"postalcode"
},
  "geometry": {"coordinates":[0.12124385253241,51.77213838131505],"type":"Point"}
}