{
  "type": "Feature",
  "properties": {
    "iso:country":"GB",
    "wof:name":"DE14 3JW",
    "wof:placetype":"postalcode"
},
  "geometry": {"coordinates":[-1.6671952176898,52.79321053300936],"type":"Point"}
}