{
  "type": "Feature",
  "properties": {
    "date:inception_lower": "1980-01-01",
    "date:inception_upper": "1980-01-01",
    "iso:country": "GB",
    "wof:name": "AL2 2TX",
    "wof:placetype": "postalcode"
  },
  "geometry": {"coordinates":[-0.35172,51.721487],"type":"Point"}
}
