{
  "type": "Feature",
  "properties": {
    "iso:country":"GB",
    "wof:name":"WN7 3HH",
    "wof:placetype":"postalcode"
},
  "geometry": {"coordinates":[-2.51714245176791,53.48983830068428],"type":"Point"}
}