{
  "type": "Feature",
  "properties": {
    "iso:country": "GB",
    "wof:name": "WN7 3HH",
    "wof:placetype": "postalcode"
  },
  "geometry": {"coordinates":[-2.517142,53.489838],"type":"Point"}
}
