{
  "type": "Feature",
  "properties": {
    "iso:country":"GB",
    "wof:name":"IP1 6TH",
    "wof:placetype":"postalcode"
},
  "geometry": {"coordinates":[1.13521463679749,52.08964480818597],"type":"Point"}
}