{
  "type": "Feature",
  "properties": {
    "iso:country": "GB",
    "wof:name": "IP1 6TH",
    "wof:placetype": "postalcode"
  },
  "geometry": {"coordinates":[1.135215,52.089645],"type":"Point"}
}
