{
  "type": "Feature",
  "properties": {
    "iso:country": "GB",
    "wof:name": "WV6 8LW",
    "wof:placetype": "postalcode"
  },
  "geometry": {"coordinates":[-2.171174,52.595025],"type":"Point"}
}
