{
  "type": "Feature",
  "properties": {
    "iso:country":"GB",
    "wof:name":"TN40 2BL",
    "wof:placetype":"postalcode"
},
  "geometry": {"coordinates":[0.47215995450959,50.85074050909935],"type":"Point"}
}