{
  "type": "Feature",
  "properties": {
    "iso:country":"GB",
    "wof:name":"TN8 6EX",
    "wof:placetype":"postalcode"
},
  "geometry": {"coordinates":[0.06325902248934,51.20667016836566],"type":"Point"}
}