{
  "type": "Feature",
  "properties": {
    "iso:country": "GB",
    "wof:name": "TN8 6EX",
    "wof:placetype": "postalcode"
  },
  "geometry": {"coordinates":[0.063259,51.20667],"type":"Point"}
}
