{
  "type": "Feature",
  "properties": {
    "date:inception_lower": "1990-07-01",
    "date:inception_upper": "1990-07-01",
    "iso:country": "GB",
    "wof:name": "NG18 3LW",
    "wof:placetype": "postalcode"
  },
  "geometry": {"coordinates":[-1.164395,53.136625],"type":"Point"}
}
