{
  "type": "Feature",
  "properties": {
    "iso:country": "GB",
    "wof:name": "TN20 6BP",
    "wof:placetype": "postalcode"
  },
  "geometry": {"coordinates":[0.252393,51.018865],"type":"Point"}
}
