{
  "type": "Feature",
  "properties": {
    "iso:country":"GB",
    "wof:name":"TN20 6BP",
    "wof:placetype":"postalcode"
},
  "geometry": {"coordinates":[0.2523638573054,51.01885962432373],"type":"Point"}
}