{
  "type": "Feature",
  "properties": {
    "date:inception_lower":"1980-01-01",
    "date:inception_upper":"1980-01-31",
    "iso:country":"GB",
    "wof:name":"NG34 9PA",
    "wof:placetype":"postalcode"
},
  "geometry": {"coordinates":[-0.369952,53.014056],"type":"Point"}
}