{
  "type": "Feature",
  "properties": {
    "iso:country": "GB",
    "wof:name": "NG34 9PA",
    "wof:placetype": "postalcode"
  },
  "geometry": {"coordinates":[-0.369952,53.014056],"type":"Point"}
}
