{
  "type": "Feature",
  "properties": {
    "iso:country":"GB",
    "wof:name":"NG34 9PA",
    "wof:placetype":"postalcode"
},
  "geometry": {"coordinates":[-0.36995224252132,53.01405559361129],"type":"Point"}
}