{
  "type": "Feature",
  "properties": {
    "date:inception_lower": "2001-12-01",
    "date:inception_upper": "2001-12-01",
    "iso:country": "GB",
    "wof:name": "LU1 1YB",
    "wof:placetype": "postalcode"
  },
  "geometry": {"coordinates":[-0.437715,51.883375],"type":"Point"}
}
