{
  "type": "Feature",
  "properties": {
    "date:inception_lower": "1981-06-01",
    "date:inception_upper": "1981-06-01",
    "iso:country": "GB",
    "wof:name": "DL14 0SH",
    "wof:placetype": "postalcode"
  },
  "geometry": {"coordinates":[-1.701582,54.649239],"type":"Point"}
}
