{
  "type": "Feature",
  "properties": {
    "iso:country":"GB",
    "wof:name":"DL14 0SH",
    "wof:placetype":"postalcode"
},
  "geometry": {"coordinates":[-1.70158182538574,54.64923866864554],"type":"Point"}
}