{
  "type": "Feature",
  "properties": {
    "iso:country": "GB",
    "wof:name": "DL14 0SH",
    "wof:placetype": "postalcode"
  },
  "geometry": {"coordinates":[-1.701582,54.649239],"type":"Point"}
}
