{
  "type": "Feature",
  "properties": {
    "iso:country": "GB",
    "wof:name": "PO4 9FZ",
    "wof:placetype": "postalcode"
  },
  "geometry": {"coordinates":[-1.047372,50.788956],"type":"Point"}
}
