{
  "type": "Feature",
  "properties": {
    "iso:country":"GB",
    "wof:name":"ST6 4GW",
    "wof:placetype":"postalcode"
},
  "geometry": {"coordinates":[-2.19850160624994,53.04756559161067],"type":"Point"}
}