{
  "type": "Feature",
  "properties": {
    "date:inception_lower": "2009-06-01",
    "date:inception_upper": "2009-06-01",
    "iso:country": "GB",
    "wof:name": "ST6 4GW",
    "wof:placetype": "postalcode"
  },
  "geometry": {"coordinates":[-2.198502,53.047566],"type":"Point"}
}
