{
  "type": "Feature",
  "properties": {
    "date:inception_lower": "2017-06-01",
    "date:inception_upper": "2017-06-01",
    "iso:country": "GB",
    "wof:name": "DE22 3XS",
    "wof:placetype": "postalcode"
  },
  "geometry": {"coordinates":[-1.511447,52.917787],"type":"Point"}
}
