{
  "type": "Feature",
  "properties": {
    "date:inception_lower":"1980-01-01",
    "date:inception_upper":"1980-01-31",
    "iso:country":"GB",
    "wof:name":"EX12 3JH",
    "wof:placetype":"postalcode"
},
  "geometry": {"coordinates":[-3.093081,50.698785],"type":"Point"}
}