{
  "type": "Feature",
  "properties": {
    "date:inception_lower": "1980-01-01",
    "date:inception_upper": "1980-01-01",
    "iso:country": "GB",
    "wof:name": "PA32 8UA",
    "wof:placetype": "postalcode"
  },
  "geometry": {"coordinates":[-5.073538,56.229614],"type":"Point"}
}
