{
  "type": "Feature",
  "properties": {
    "iso:country": "GB",
    "wof:name": "SW19 8BH",
    "wof:placetype": "postalcode"
  },
  "geometry": {"coordinates":[-0.198764,51.439106],"type":"Point"}
}
