{
  "type": "Feature",
  "properties": {
    "iso:country":"GB",
    "wof:name":"BN13 2AA",
    "wof:placetype":"postalcode"
},
  "geometry": {"coordinates":[-0.3937453771198,50.83633111991585],"type":"Point"}
}