{
  "type": "Feature",
  "properties": {
    "iso:country":"GB",
    "wof:name":"NR31 0PU",
    "wof:placetype":"postalcode"
},
  "geometry": {"coordinates":[1.72423274191867,52.5877130040283],"type":"Point"}
}