{
  "type": "Feature",
  "properties": {
    "iso:country":"GB",
    "wof:name":"RG14 6TA",
    "wof:placetype":"postalcode"
},
  "geometry": {"coordinates":[-1.34905351422234,51.37821202212955],"type":"Point"}
}