{
  "type": "Feature",
  "properties": {
    "iso:country": "GB",
    "wof:name": "EX2 5HN",
    "wof:placetype": "postalcode"
  },
  "geometry": {"coordinates":[-3.499264,50.718696],"type":"Point"}
}
