{
  "type": "Feature",
  "properties": {
    "iso:country": "GB",
    "wof:name": "W11 3JS",
    "wof:placetype": "postalcode"
  },
  "geometry": {"coordinates":[-0.196534,51.508827],"type":"Point"}
}
