{
  "type": "Feature",
  "properties": {
    "iso:country":"GB",
    "wof:name":"W11 3JS",
    "wof:placetype":"postalcode"
},
  "geometry": {"coordinates":[-0.19653409922408,51.5088269138251],"type":"Point"}
}