{
  "type": "Feature",
  "properties": {
    "date:inception_lower":"2004-06-01",
    "date:inception_upper":"2004-06-30",
    "iso:country":"GB",
    "wof:name":"W11 3JS",
    "wof:placetype":"postalcode"
},
  "geometry": {"coordinates":[-0.196534,51.508827],"type":"Point"}
}