{
  "type": "Feature",
  "properties": {
    "iso:country":"GB",
    "wof:name":"EX17 1BU",
    "wof:placetype":"postalcode"
},
  "geometry": {"coordinates":[-3.61310469771609,50.80074196753389],"type":"Point"}
}