{
  "type": "Feature",
  "properties": {
    "iso:country":"GB",
    "wof:name":"BN22 8DB",
    "wof:placetype":"postalcode"
},
  "geometry": {"coordinates":[0.29531328685408,50.77366017477886],"type":"Point"}
}