{
  "type": "Feature",
  "properties": {
    "iso:country":"GB",
    "wof:name":"CW5 6BS",
    "wof:placetype":"postalcode"
},
  "geometry": {"coordinates":[-2.5836804685891,53.11669277194866],"type":"Point"}
}