{
  "type": "Feature",
  "properties": {
    "iso:country": "GB",
    "wof:name": "CW5 6BS",
    "wof:placetype": "postalcode"
  },
  "geometry": {"coordinates":[-2.586765,53.117162],"type":"Point"}
}
