{
  "type": "Feature",
  "properties": {
    "iso:country": "GB",
    "wof:name": "NG34 0BZ",
    "wof:placetype": "postalcode"
  },
  "geometry": {"coordinates":[-0.337959,52.967178],"type":"Point"}
}
