{
  "type": "Feature",
  "properties": {
    "date:inception_lower":"1980-01-01",
    "date:inception_upper":"1980-01-31",
    "iso:country":"GB",
    "wof:name":"NG34 0BZ",
    "wof:placetype":"postalcode"
},
  "geometry": {"coordinates":[-0.337959,52.967178],"type":"Point"}
}