{
  "type": "Feature",
  "properties": {
    "iso:country":"GB",
    "wof:name":"YO22 4HJ",
    "wof:placetype":"postalcode"
},
  "geometry": {"coordinates":[-0.60532428145674,54.47277241344178],"type":"Point"}
}