{
  "type": "Feature",
  "properties": {
    "iso:country": "GB",
    "wof:name": "SO23 7RG",
    "wof:placetype": "postalcode"
  },
  "geometry": {"coordinates":[-1.316049,51.067053],"type":"Point"}
}
