{
  "type": "Feature",
  "properties": {
    "iso:country":"GB",
    "wof:name":"SO23 7RG",
    "wof:placetype":"postalcode"
},
  "geometry": {"coordinates":[-1.31604873040588,51.06705273912055],"type":"Point"}
}