{
  "type": "Feature",
  "properties": {
    "iso:country":"GB",
    "wof:name":"CB8 7NB",
    "wof:placetype":"postalcode"
},
  "geometry": {"coordinates":[0.39659838772177,52.28764045903793],"type":"Point"}
}