{
  "type": "Feature",
  "properties": {
    "date:inception_lower": "1992-01-01",
    "date:inception_upper": "1992-01-01",
    "iso:country": "GB",
    "wof:name": "DG7 2EA",
    "wof:placetype": "postalcode"
  },
  "geometry": {"coordinates":[-4.190561,54.884438],"type":"Point"}
}
