{
  "type": "Feature",
  "properties": {
    "iso:country":"GB",
    "wof:name":"DG7 2EA",
    "wof:placetype":"postalcode"
},
  "geometry": {"coordinates":[-4.19056073354938,54.88443809396154],"type":"Point"}
}