{
  "type": "Feature",
  "properties": {
    "iso:country":"GB",
    "wof:name":"DL5 6LG",
    "wof:placetype":"postalcode"
},
  "geometry": {"coordinates":[-1.56181776728945,54.59809253431578],"type":"Point"}
}