{
  "type": "Feature",
  "properties": {
    "iso:country": "GB",
    "wof:name": "BD5 0HR",
    "wof:placetype": "postalcode"
  },
  "geometry": {"coordinates":[-1.768359,53.785323],"type":"Point"}
}
