{
  "type": "Feature",
  "properties": {
    "iso:country":"GB",
    "wof:name":"PA2 8PY",
    "wof:placetype":"postalcode"
},
  "geometry": {"coordinates":[-4.44269515393238,55.82049172320789],"type":"Point"}
}