{
  "type": "Feature",
  "properties": {
    "date:inception_lower": "1990-09-01",
    "date:inception_upper": "1990-09-01",
    "iso:country": "GB",
    "wof:name": "PA2 8PY",
    "wof:placetype": "postalcode"
  },
  "geometry": {"coordinates":[-4.442695,55.820492],"type":"Point"}
}
