{
  "type": "Feature",
  "properties": {
    "iso:country": "GB",
    "wof:name": "PA2 8PY",
    "wof:placetype": "postalcode"
  },
  "geometry": {"coordinates":[-4.442695,55.820492],"type":"Point"}
}
