{
  "type": "Feature",
  "properties": {
    "iso:country": "GB",
    "wof:name": "PH2 6GE",
    "wof:placetype": "postalcode"
  },
  "geometry": {"coordinates":[-3.396921,56.419241],"type":"Point"}
}
