{
  "type": "Feature",
  "properties": {
    "date:inception_lower": "1980-01-01",
    "date:inception_upper": "1980-01-01",
    "iso:country": "GB",
    "wof:name": "CB4 2NG",
    "wof:placetype": "postalcode"
  },
  "geometry": {"coordinates":[0.13936,52.22883],"type":"Point"}
}
