{
  "type": "Feature",
  "properties": {
    "iso:country":"GB",
    "wof:name":"ME17 1EE",
    "wof:placetype":"postalcode"
},
  "geometry": {"coordinates":[0.65047770460075,51.20674578553959],"type":"Point"}
}