{
  "type": "Feature",
  "properties": {
    "date:inception_lower":"2016-10-01",
    "date:inception_upper":"2016-10-31",
    "iso:country":"GB",
    "wof:name":"G4 0HZ",
    "wof:placetype":"postalcode"
},
  "geometry": {"coordinates":[-4.25469,55.869141],"type":"Point"}
}