{
  "type": "Feature",
  "properties": {
    "iso:country": "GB",
    "wof:name": "G4 0HZ",
    "wof:placetype": "postalcode"
  },
  "geometry": {"coordinates":[-4.25469,55.869141],"type":"Point"}
}
