{
  "type": "Feature",
  "properties": {
    "iso:country": "GB",
    "wof:name": "TS13 4JQ",
    "wof:placetype": "postalcode"
  },
  "geometry": {"coordinates":[-0.890051,54.566967],"type":"Point"}
}
