{
  "type": "Feature",
  "properties": {
    "iso:country":"GB",
    "wof:name":"TS13 4JQ",
    "wof:placetype":"postalcode"
},
  "geometry": {"coordinates":[-0.89003554430783,54.56695310491765],"type":"Point"}
}