{
  "type": "Feature",
  "properties": {
    "date:inception_lower": "1991-01-01",
    "date:inception_upper": "1991-01-01",
    "iso:country": "GB",
    "wof:name": "DE7 9HL",
    "wof:placetype": "postalcode"
  },
  "geometry": {"coordinates":[-1.325162,52.984629],"type":"Point"}
}
