{
  "type": "Feature",
  "properties": {
    "iso:country":"GB",
    "wof:name":"DE7 9HL",
    "wof:placetype":"postalcode"
},
  "geometry": {"coordinates":[-1.32516193680094,52.98462896761631],"type":"Point"}
}