{
  "type": "Feature",
  "properties": {
    "date:inception_lower": "1980-01-01",
    "date:inception_upper": "1980-01-01",
    "iso:country": "GB",
    "wof:name": "SA2 9JE",
    "wof:placetype": "postalcode"
  },
  "geometry": {"coordinates":[-3.993789,51.622106],"type":"Point"}
}
