{
  "type": "Feature",
  "properties": {
    "iso:country":"GB",
    "wof:name":"SA2 9JE",
    "wof:placetype":"postalcode"
},
  "geometry": {"coordinates":[-3.9937710156791,51.62210132619663],"type":"Point"}
}