{
  "type": "Feature",
  "properties": {
    "iso:country": "GB",
    "wof:name": "ME13 0EL",
    "wof:placetype": "postalcode"
  },
  "geometry": {"coordinates":[0.856621,51.296071],"type":"Point"}
}
