{
  "type": "Feature",
  "properties": {
    "date:inception_lower": "1993-08-01",
    "date:inception_upper": "1993-08-01",
    "iso:country": "GB",
    "wof:name": "ME13 0EL",
    "wof:placetype": "postalcode"
  },
  "geometry": {"coordinates":[0.856621,51.296071],"type":"Point"}
}
