{
  "type": "Feature",
  "properties": {
    "date:inception_lower": "1993-08-01",
    "date:inception_upper": "1993-08-01",
    "iso:country": "GB",
    "wof:name": "S43 4US",
    "wof:placetype": "postalcode"
  },
  "geometry": {"coordinates":[-1.288762,53.28496],"type":"Point"}
}
