{
  "type": "Feature",
  "properties": {
    "iso:country":"GB",
    "wof:name":"S43 4US",
    "wof:placetype":"postalcode"
},
  "geometry": {"coordinates":[-1.28876201188607,53.28496020859396],"type":"Point"}
}