{
  "type": "Feature",
  "properties": {
    "date:inception_lower": "2006-07-01",
    "date:inception_upper": "2006-07-01",
    "iso:country": "GB",
    "wof:name": "B80 7FG",
    "wof:placetype": "postalcode"
  },
  "geometry": {"coordinates":[-1.846693,52.271778],"type":"Point"}
}
