{
  "type": "Feature",
  "properties": {
    "iso:country": "GB",
    "wof:name": "B80 7FG",
    "wof:placetype": "postalcode"
  },
  "geometry": {"coordinates":[-1.846693,52.271778],"type":"Point"}
}
