{
  "type": "Feature",
  "properties": {
    "iso:country":"GB",
    "wof:name":"B80 7FG",
    "wof:placetype":"postalcode"
},
  "geometry": {"coordinates":[-1.84664877553078,52.27185868189527],"type":"Point"}
}