{
  "type": "Feature",
  "properties": {
    "iso:country":"GB",
    "wof:name":"NP10 8NE",
    "wof:placetype":"postalcode"
},
  "geometry": {"coordinates":[-3.04245706766709,51.57848663129069],"type":"Point"}
}