{
  "type": "Feature",
  "properties": {
    "iso:country": "GB",
    "wof:name": "NP10 8NE",
    "wof:placetype": "postalcode"
  },
  "geometry": {"coordinates":[-3.042457,51.578487],"type":"Point"}
}
