{
  "type": "Feature",
  "properties": {
    "iso:country":"GB",
    "wof:name":"M43 6LU",
    "wof:placetype":"postalcode"
},
  "geometry": {"coordinates":[-2.16726802909836,53.48160063188229],"type":"Point"}
}