{
  "type": "Feature",
  "properties": {
    "iso:country": "GB",
    "wof:name": "M43 6LU",
    "wof:placetype": "postalcode"
  },
  "geometry": {"coordinates":[-2.167268,53.481601],"type":"Point"}
}
