{
  "type": "Feature",
  "properties": {
    "iso:country": "GB",
    "wof:name": "GU12 5RA",
    "wof:placetype": "postalcode"
  },
  "geometry": {"coordinates":[-0.715901,51.278764],"type":"Point"}
}
