{
  "type": "Feature",
  "properties": {
    "iso:country": "GB",
    "wof:name": "NE65 0SG",
    "wof:placetype": "postalcode"
  },
  "geometry": {"coordinates":[-1.573474,55.334075],"type":"Point"}
}
