{
  "type": "Feature",
  "properties": {
    "iso:country": "GB",
    "wof:name": "NN4 8LE",
    "wof:placetype": "postalcode"
  },
  "geometry": {"coordinates":[-0.91414,52.220539],"type":"Point"}
}
