{
  "type": "Feature",
  "properties": {
    "iso:country":"GB",
    "wof:name":"NN4 8LE",
    "wof:placetype":"postalcode"
},
  "geometry": {"coordinates":[-0.9141400813477,52.22053940838187],"type":"Point"}
}