{
  "type": "Feature",
  "properties": {
    "date:inception_lower": "1995-07-01",
    "date:inception_upper": "1995-07-01",
    "iso:country": "GB",
    "wof:name": "NN4 8LE",
    "wof:placetype": "postalcode"
  },
  "geometry": {"coordinates":[-0.91414,52.220539],"type":"Point"}
}
