{
  "type": "Feature",
  "properties": {
    "date:inception_lower": "1999-06-01",
    "date:inception_upper": "1999-06-01",
    "iso:country": "GB",
    "wof:name": "NP20 4HX",
    "wof:placetype": "postalcode"
  },
  "geometry": {"coordinates":[-3.011715,51.583539],"type":"Point"}
}
