{
  "type": "Feature",
  "properties": {
    "iso:country":"GB",
    "wof:name":"NP20 4HX",
    "wof:placetype":"postalcode"
},
  "geometry": {"coordinates":[-3.01171479259033,51.583539297513],"type":"Point"}
}