{
  "type": "Feature",
  "properties": {
    "iso:country": "GB",
    "wof:name": "CM18 6QH",
    "wof:placetype": "postalcode"
  },
  "geometry": {"coordinates":[0.106366,51.757107],"type":"Point"}
}
