{
  "type": "Feature",
  "properties": {
    "date:inception_lower": "1995-01-01",
    "date:inception_upper": "1995-01-01",
    "iso:country": "GB",
    "wof:name": "CM18 6QH",
    "wof:placetype": "postalcode"
  },
  "geometry": {"coordinates":[0.106322,51.75709],"type":"Point"}
}
