{
  "type": "Feature",
  "properties": {
    "iso:country": "GB",
    "wof:name": "CO4 3UJ",
    "wof:placetype": "postalcode"
  },
  "geometry": {"coordinates":[0.934472,51.88426],"type":"Point"}
}
