{
  "type": "Feature",
  "properties": {
    "iso:country": "GB",
    "wof:name": "BH6 3DZ",
    "wof:placetype": "postalcode"
  },
  "geometry": {"coordinates":[-1.800489,50.721353],"type":"Point"}
}
