{
  "type": "Feature",
  "properties": {
    "iso:country": "GB",
    "wof:name": "DY10 1UE",
    "wof:placetype": "postalcode"
  },
  "geometry": {"coordinates":[-2.236369,52.384341],"type":"Point"}
}
