{
  "type": "Feature",
  "properties": {
    "iso:country":"GB",
    "wof:name":"DY10 1UE",
    "wof:placetype":"postalcode"
},
  "geometry": {"coordinates":[-2.23636897755526,52.38434117733814],"type":"Point"}
}