{
  "type": "Feature",
  "properties": {
    "date:inception_lower": "1980-01-01",
    "date:inception_upper": "1980-01-01",
    "iso:country": "GB",
    "wof:name": "TF5 0BB",
    "wof:placetype": "postalcode"
  },
  "geometry": {"coordinates":[-2.543652,52.710633],"type":"Point"}
}
