{
  "type": "Feature",
  "properties": {
    "iso:country":"GB",
    "wof:name":"TF5 0BB",
    "wof:placetype":"postalcode"
},
  "geometry": {"coordinates":[-2.54365253748481,52.71063313628822],"type":"Point"}
}