{
  "type": "Feature",
  "properties": {
    "iso:country":"GB",
    "wof:name":"PL9 8ND",
    "wof:placetype":"postalcode"
},
  "geometry": {"coordinates":[-4.07133940741118,50.35986455994758],"type":"Point"}
}