{
  "type": "Feature",
  "properties": {
    "date:inception_lower": "1980-01-01",
    "date:inception_upper": "1980-01-01",
    "iso:country": "GB",
    "wof:name": "HD8 8NR",
    "wof:placetype": "postalcode"
  },
  "geometry": {"coordinates":[-1.690174,53.57557],"type":"Point"}
}
