{
  "type": "Feature",
  "properties": {
    "iso:country":"GB",
    "wof:name":"PO1 5RL",
    "wof:placetype":"postalcode"
},
  "geometry": {"coordinates":[-1.07016339949733,50.8086178986259],"type":"Point"}
}