{
  "type": "Feature",
  "properties": {
    "iso:country": "GB",
    "wof:name": "CH42 3SZ",
    "wof:placetype": "postalcode"
  },
  "geometry": {"coordinates":[-3.013847,53.377045],"type":"Point"}
}
