{
  "type": "Feature",
  "properties": {
    "iso:country":"GB",
    "wof:name":"CH42 3SZ",
    "wof:placetype":"postalcode"
},
  "geometry": {"coordinates":[-3.01384666510737,53.37704510104415],"type":"Point"}
}