{
  "type": "Feature",
  "properties": {
    "iso:country":"GB",
    "wof:name":"SP1 2RA",
    "wof:placetype":"postalcode"
},
  "geometry": {"coordinates":[-1.78535736067862,51.06877453103648],"type":"Point"}
}