{
  "type": "Feature",
  "properties": {
    "iso:country":"GB",
    "wof:name":"BB3 2UQ",
    "wof:placetype":"postalcode"
},
  "geometry": {"coordinates":[-2.4684175929555,53.69343677889386],"type":"Point"}
}