{
  "type": "Feature",
  "properties": {
    "date:inception_lower":"2008-01-01",
    "date:inception_upper":"2008-01-31",
    "iso:country":"GB",
    "wof:name":"BB3 2UQ",
    "wof:placetype":"postalcode"
},
  "geometry": {"coordinates":[-2.468418,53.693437],"type":"Point"}
}