{
  "type": "Feature",
  "properties": {
    "iso:country":"GB",
    "wof:name":"OL8 2TN",
    "wof:placetype":"postalcode"
},
  "geometry": {"coordinates":[-2.10509643162193,53.51260074134652],"type":"Point"}
}