{
  "type": "Feature",
  "properties": {
    "iso:country":"GB",
    "wof:name":"EN3 6TG",
    "wof:placetype":"postalcode"
},
  "geometry": {"coordinates":[-0.03820637739584,51.68099203323442],"type":"Point"}
}