{
  "type": "Feature",
  "properties": {
    "iso:country":"GB",
    "wof:name":"M1 5QB",
    "wof:placetype":"postalcode"
},
  "geometry": {"coordinates":[-2.24395189732609,53.47366655650846],"type":"Point"}
}