{
  "type": "Feature",
  "properties": {
    "iso:country": "GB",
    "wof:name": "SP6 3JW",
    "wof:placetype": "postalcode"
  },
  "geometry": {"coordinates":[-1.873362,50.956995],"type":"Point"}
}
