{
  "type": "Feature",
  "properties": {
    "iso:country":"GB",
    "wof:name":"SP6 3JW",
    "wof:placetype":"postalcode"
},
  "geometry": {"coordinates":[-1.87336228221969,50.95699459556154],"type":"Point"}
}