{
  "type": "Feature",
  "properties": {
    "iso:country":"GB",
    "wof:name":"EX7 9JQ",
    "wof:placetype":"postalcode"
},
  "geometry": {"coordinates":[-3.46564405537383,50.58224483880959],"type":"Point"}
}