{
  "type": "Feature",
  "properties": {
    "iso:country": "GB",
    "wof:name": "NE28 7AG",
    "wof:placetype": "postalcode"
  },
  "geometry": {"coordinates":[-1.511936,54.999493],"type":"Point"}
}
