{
  "type": "Feature",
  "properties": {
    "date:inception_lower":"2010-03-01",
    "date:inception_upper":"2010-03-31",
    "iso:country":"GB",
    "wof:name":"NE28 7AG",
    "wof:placetype":"postalcode"
},
  "geometry": {"coordinates":[-1.511936,54.999493],"type":"Point"}
}