{
  "type": "Feature",
  "properties": {
    "iso:country":"GB",
    "wof:name":"NE28 7AG",
    "wof:placetype":"postalcode"
},
  "geometry": {"coordinates":[-1.51193588672784,54.99949334780104],"type":"Point"}
}