{
  "type": "Feature",
  "properties": {
    "iso:country":"GB",
    "wof:name":"DL14 9SS",
    "wof:placetype":"postalcode"
},
  "geometry": {"coordinates":[-1.69012772063881,54.64128364310235],"type":"Point"}
}