{
  "type": "Feature",
  "properties": {
    "date:inception_lower": "1980-01-01",
    "date:inception_upper": "1980-01-01",
    "iso:country": "GB",
    "wof:name": "G82 2PU",
    "wof:placetype": "postalcode"
  },
  "geometry": {"coordinates":[-4.540447,55.941567],"type":"Point"}
}
