{
  "type": "Feature",
  "properties": {
    "iso:country": "GB",
    "wof:name": "EX4 3DR",
    "wof:placetype": "postalcode"
  },
  "geometry": {"coordinates":[-3.534634,50.721195],"type":"Point"}
}
