{
  "type": "Feature",
  "properties": {
    "date:inception_lower":"2003-02-01",
    "date:inception_upper":"2003-02-28",
    "iso:country":"GB",
    "wof:name":"EX4 3DR",
    "wof:placetype":"postalcode"
},
  "geometry": {"coordinates":[-3.534634,50.721195],"type":"Point"}
}