{
  "type": "Feature",
  "properties": {
    "iso:country":"GB",
    "wof:name":"DL5 5PT",
    "wof:placetype":"postalcode"
},
  "geometry": {"coordinates":[-1.5638828889303,54.62066589667165],"type":"Point"}
}