{
  "type": "Feature",
  "properties": {
    "iso:country": "GB",
    "wof:name": "CV12 8JT",
    "wof:placetype": "postalcode"
  },
  "geometry": {"coordinates":[-1.46874,52.47744],"type":"Point"}
}
