{
  "type": "Feature",
  "properties": {
    "date:inception_lower":"1997-12-01",
    "date:inception_upper":"1997-12-31",
    "iso:country":"GB",
    "wof:name":"CV12 8JT",
    "wof:placetype":"postalcode"
},
  "geometry": {"coordinates":[-1.46874,52.47744],"type":"Point"}
}