{
  "type": "Feature",
  "properties": {
    "date:inception_lower": "1980-01-01",
    "date:inception_upper": "1980-01-01",
    "iso:country": "GB",
    "wof:name": "CT17 0JL",
    "wof:placetype": "postalcode"
  },
  "geometry": {"coordinates":[1.293242,51.136321],"type":"Point"}
}
