{
  "type": "Feature",
  "properties": {
    "iso:country": "GB",
    "wof:name": "HU12 9PU",
    "wof:placetype": "postalcode"
  },
  "geometry": {"coordinates":[-0.164697,53.717935],"type":"Point"}
}
