{
  "type": "Feature",
  "properties": {
    "date:inception_lower": "2020-12-01",
    "date:inception_upper": "2020-12-01",
    "iso:country": "GB",
    "wof:name": "NR13 5PT",
    "wof:placetype": "postalcode"
  },
  "geometry": {"coordinates":[1.445539,52.618886],"type":"Point"}
}
