{
  "type": "Feature",
  "properties": {
    "iso:country":"GB",
    "wof:name":"NR13 5PT",
    "wof:placetype":"postalcode"
},
  "geometry": {"coordinates":[1.43430117755312,52.61246771003516],"type":"Point"}
}