{
  "type": "Feature",
  "properties": {
    "iso:country": "GB",
    "wof:name": "CM6 1SE",
    "wof:placetype": "postalcode"
  },
  "geometry": {"coordinates":[0.313704,51.796366],"type":"Point"}
}
