{
  "type": "Feature",
  "properties": {
    "iso:country":"GB",
    "wof:name":"CM6 1SE",
    "wof:placetype":"postalcode"
},
  "geometry": {"coordinates":[0.31370366285796,51.79636640262584],"type":"Point"}
}