{
  "type": "Feature",
  "properties": {
    "iso:country":"GB",
    "wof:name":"HU6 8QU",
    "wof:placetype":"postalcode"
},
  "geometry": {"coordinates":[-0.38564925161412,53.77153525763242],"type":"Point"}
}