{
  "type": "Feature",
  "properties": {
    "iso:country":"GB",
    "wof:name":"HA6 3BT",
    "wof:placetype":"postalcode"
},
  "geometry": {"coordinates":[-0.42574542132908,51.6237015140685],"type":"Point"}
}