{
  "type": "Feature",
  "properties": {
    "iso:country":"GB",
    "wof:name":"WS2 9PW",
    "wof:placetype":"postalcode"
},
  "geometry": {"coordinates":[-1.99554367230597,52.58551232426449],"type":"Point"}
}