{
  "type": "Feature",
  "properties": {
    "date:inception_lower": "1980-01-01",
    "date:inception_upper": "1980-01-01",
    "iso:country": "GB",
    "wof:name": "WS2 9PW",
    "wof:placetype": "postalcode"
  },
  "geometry": {"coordinates":[-1.995544,52.585512],"type":"Point"}
}
