{
  "type": "Feature",
  "properties": {
    "iso:country":"GB",
    "wof:name":"CH1 2JB",
    "wof:placetype":"postalcode"
},
  "geometry": {"coordinates":[-2.89285222086268,53.19362844664694],"type":"Point"}
}