{
  "type": "Feature",
  "properties": {
    "date:inception_lower": "1997-06-01",
    "date:inception_upper": "1997-06-01",
    "iso:country": "GB",
    "wof:name": "CH1 2JB",
    "wof:placetype": "postalcode"
  },
  "geometry": {"coordinates":[-2.892852,53.193628],"type":"Point"}
}
