{
  "type": "Feature",
  "properties": {
    "iso:country":"GB",
    "wof:name":"SL6 3ED",
    "wof:placetype":"postalcode"
},
  "geometry": {"coordinates":[-0.74100384975329,51.50836298019703],"type":"Point"}
}