{
  "type": "Feature",
  "properties": {
    "date:inception_lower": "1998-12-01",
    "date:inception_upper": "1998-12-01",
    "iso:country": "GB",
    "wof:name": "EC4V 5EF",
    "wof:placetype": "postalcode"
  },
  "geometry": {"coordinates":[-0.101726,51.513356],"type":"Point"}
}
