{
  "type": "Feature",
  "properties": {
    "iso:country": "GB",
    "wof:name": "EC4V 5EF",
    "wof:placetype": "postalcode"
  },
  "geometry": {"coordinates":[-0.101726,51.513356],"type":"Point"}
}
