{
  "type": "Feature",
  "properties": {
    "iso:country":"GB",
    "wof:name":"SP3 6EX",
    "wof:placetype":"postalcode"
},
  "geometry": {"coordinates":[-2.17074044344765,51.06861222478007],"type":"Point"}
}