{
  "type": "Feature",
  "properties": {
    "date:inception_lower":"1995-12-01",
    "date:inception_upper":"1995-12-31",
    "iso:country":"GB",
    "wof:name":"SP3 6EX",
    "wof:placetype":"postalcode"
},
  "geometry": {"coordinates":[-2.17074,51.068612],"type":"Point"}
}