{
  "type": "Feature",
  "properties": {
    "iso:country":"GB",
    "wof:name":"DH4 7EF",
    "wof:placetype":"postalcode"
},
  "geometry": {"coordinates":[-1.48765692190409,54.87436622356842],"type":"Point"}
}