{
  "type": "Feature",
  "properties": {
    "iso:country":"GB",
    "wof:name":"LE67 5EW",
    "wof:placetype":"postalcode"
},
  "geometry": {"coordinates":[-1.35606687673501,52.73890973668254],"type":"Point"}
}