{
  "type": "Feature",
  "properties": {
    "iso:country":"GB",
    "wof:name":"FY7 7JA",
    "wof:placetype":"postalcode"
},
  "geometry": {"coordinates":[-3.03246740384735,53.92353685748168],"type":"Point"}
}