{
  "type": "Feature",
  "properties": {
    "iso:country": "GB",
    "wof:name": "FY7 7JA",
    "wof:placetype": "postalcode"
  },
  "geometry": {"coordinates":[-3.032467,53.923537],"type":"Point"}
}
