{
  "type": "Feature",
  "properties": {
    "iso:country":"GB",
    "wof:name":"BN2 9PP",
    "wof:placetype":"postalcode"
},
  "geometry": {"coordinates":[-0.13340903926377,50.82769024599577],"type":"Point"}
}