{
  "type": "Feature",
  "properties": {
    "iso:country": "GB",
    "wof:name": "BN2 9PP",
    "wof:placetype": "postalcode"
  },
  "geometry": {"coordinates":[-0.133057,50.827616],"type":"Point"}
}
