{
  "type": "Feature",
  "properties": {
    "date:inception_lower": "2021-05-01",
    "date:inception_upper": "2021-05-01",
    "iso:country": "GB",
    "wof:name": "WD23 2PU",
    "wof:placetype": "postalcode"
  },
  "geometry": {"coordinates":[-0.373796,51.656953],"type":"Point"}
}
