{
  "type": "Feature",
  "properties": {
    "date:inception_lower": "1980-01-01",
    "date:inception_upper": "1980-01-01",
    "iso:country": "GB",
    "wof:name": "E11 2LR",
    "wof:placetype": "postalcode"
  },
  "geometry": {"coordinates":[0.035624,51.571204],"type":"Point"}
}
