{
  "type": "Feature",
  "properties": {
    "iso:country":"GB",
    "wof:name":"E11 2LR",
    "wof:placetype":"postalcode"
},
  "geometry": {"coordinates":[0.03562357172245,51.5712042757429],"type":"Point"}
}