{
  "type": "Feature",
  "properties": {
    "iso:country":"GB",
    "wof:name":"RG12 8BQ",
    "wof:placetype":"postalcode"
},
  "geometry": {"coordinates":[-0.78569488506257,51.40773727789551],"type":"Point"}
}