{
  "type": "Feature",
  "properties": {
    "date:inception_lower":"2009-01-01",
    "date:inception_upper":"2009-01-31",
    "iso:country":"GB",
    "wof:name":"RG12 8BQ",
    "wof:placetype":"postalcode"
},
  "geometry": {"coordinates":[-0.785695,51.407737],"type":"Point"}
}