{
  "type": "Feature",
  "properties": {
    "iso:country":"GB",
    "wof:name":"EN4 8TY",
    "wof:placetype":"postalcode"
},
  "geometry": {"coordinates":[-0.15814199415281,51.64061642672357],"type":"Point"}
}