{
  "type": "Feature",
  "properties": {
    "iso:country":"GB",
    "wof:name":"KW15 1ZN",
    "wof:placetype":"postalcode"
},
  "geometry": {"coordinates":[-2.97669663532208,58.98531971834996],"type":"Point"}
}