{
  "type": "Feature",
  "properties": {
    "date:inception_lower":"2014-12-01",
    "date:inception_upper":"2014-12-31",
    "iso:country":"GB",
    "wof:name":"KW15 1ZN",
    "wof:placetype":"postalcode"
},
  "geometry": {"coordinates":[-2.976433,58.985655],"type":"Point"}
}