{
  "type": "Feature",
  "properties": {
    "iso:country":"GB",
    "wof:name":"BS23 4PT",
    "wof:placetype":"postalcode"
},
  "geometry": {"coordinates":[-2.96759892961836,51.32930810340757],"type":"Point"}
}