{
  "type": "Feature",
  "properties": {
    "date:inception_lower":"2015-02-01",
    "date:inception_upper":"2015-02-28",
    "iso:country":"GB",
    "wof:name":"WR7 4FB",
    "wof:placetype":"postalcode"
},
  "geometry": {"coordinates":[-2.027647,52.192255],"type":"Point"}
}