{
  "type": "Feature",
  "properties": {
    "iso:country": "GB",
    "wof:name": "WR7 4FB",
    "wof:placetype": "postalcode"
  },
  "geometry": {"coordinates":[-2.027647,52.192255],"type":"Point"}
}
