{
  "type": "Feature",
  "properties": {
    "iso:country":"GB",
    "wof:name":"WR7 4FB",
    "wof:placetype":"postalcode"
},
  "geometry": {"coordinates":[-2.02764719916453,52.19225526857164],"type":"Point"}
}