{
  "type": "Feature",
  "properties": {
    "date:inception_lower": "1994-05-01",
    "date:inception_upper": "1994-05-01",
    "iso:country": "GB",
    "wof:name": "NE17 7LW",
    "wof:placetype": "postalcode"
  },
  "geometry": {"coordinates":[-1.817184,54.906446],"type":"Point"}
}
