{
  "type": "Feature",
  "properties": {
    "date:inception_lower":"1980-01-01",
    "date:inception_upper":"1980-01-31",
    "iso:country":"GB",
    "wof:name":"CA28 9EA",
    "wof:placetype":"postalcode"
},
  "geometry": {"coordinates":[-3.592694,54.539373],"type":"Point"}
}