{
  "type": "Feature",
  "properties": {
    "iso:country":"GB",
    "wof:name":"LL59 5RA",
    "wof:placetype":"postalcode"
},
  "geometry": {"coordinates":[-4.15473520662551,53.24663857702443],"type":"Point"}
}