{
  "type": "Feature",
  "properties": {
    "iso:country":"GB",
    "wof:name":"NN15 6LX",
    "wof:placetype":"postalcode"
},
  "geometry": {"coordinates":[-0.71379518613602,52.38341769700261],"type":"Point"}
}