{
  "type": "Feature",
  "properties": {
    "date:inception_lower":"1980-01-01",
    "date:inception_upper":"1980-01-31",
    "iso:country":"GB",
    "wof:name":"BH25 7DZ",
    "wof:placetype":"postalcode"
},
  "geometry": {"coordinates":[-1.663413,50.735867],"type":"Point"}
}