{
  "type": "Feature",
  "properties": {
    "iso:country":"GB",
    "wof:name":"BH25 7DZ",
    "wof:placetype":"postalcode"
},
  "geometry": {"coordinates":[-1.66341311308766,50.73586667362311],"type":"Point"}
}