{
  "type": "Feature",
  "properties": {
    "iso:country":"GB",
    "wof:name":"M13 0XD",
    "wof:placetype":"postalcode"
},
  "geometry": {"coordinates":[-2.20857524808757,53.44868271460007],"type":"Point"}
}