{
  "type": "Feature",
  "properties": {
    "date:inception_lower": "1994-05-01",
    "date:inception_upper": "1994-05-01",
    "iso:country": "GB",
    "wof:name": "M13 0XD",
    "wof:placetype": "postalcode"
  },
  "geometry": {"coordinates":[-2.208575,53.448683],"type":"Point"}
}
