{
  "type": "Feature",
  "properties": {
    "iso:country":"GB",
    "wof:name":"LE67 6QP",
    "wof:placetype":"postalcode"
},
  "geometry": {"coordinates":[-1.40289324464178,52.69172481438292],"type":"Point"}
}