{
  "type": "Feature",
  "properties": {
    "date:inception_lower":"2015-04-01",
    "date:inception_upper":"2015-04-30",
    "iso:country":"GB",
    "wof:name":"LE67 6QP",
    "wof:placetype":"postalcode"
},
  "geometry": {"coordinates":[-1.402893,52.691725],"type":"Point"}
}