{
  "type": "Feature",
  "properties": {
    "iso:country": "GB",
    "wof:name": "BN20 0HY",
    "wof:placetype": "postalcode"
  },
  "geometry": {"coordinates":[0.208572,50.764804],"type":"Point"}
}
