{
  "type": "Feature",
  "properties": {
    "iso:country": "GB",
    "wof:name": "CF23 6HH",
    "wof:placetype": "postalcode"
  },
  "geometry": {"coordinates":[-3.16691,51.510119],"type":"Point"}
}
