{
  "type": "Feature",
  "properties": {
    "iso:country":"GB",
    "wof:name":"TQ3 2TJ",
    "wof:placetype":"postalcode"
},
  "geometry": {"coordinates":[-3.56494420597705,50.44576031239701],"type":"Point"}
}