{
  "type": "Feature",
  "properties": {
    "date:inception_lower": "1980-01-01",
    "date:inception_upper": "1980-01-01",
    "iso:country": "GB",
    "wof:name": "TQ3 2TJ",
    "wof:placetype": "postalcode"
  },
  "geometry": {"coordinates":[-3.564944,50.44576],"type":"Point"}
}
