{
  "type": "Feature",
  "properties": {
    "iso:country":"GB",
    "wof:name":"OX9 3LD",
    "wof:placetype":"postalcode"
},
  "geometry": {"coordinates":[-0.9606869985069,51.74627461433348],"type":"Point"}
}