{
  "type": "Feature",
  "properties": {
    "iso:country":"GB",
    "wof:name":"NR35 1LH",
    "wof:placetype":"postalcode"
},
  "geometry": {"coordinates":[1.45553025441082,52.44970351579219],"type":"Point"}
}