{
  "type": "Feature",
  "properties": {
    "iso:country":"GB",
    "wof:name":"KY10 3EF",
    "wof:placetype":"postalcode"
},
  "geometry": {"coordinates":[-2.70886016815668,56.22165486190124],"type":"Point"}
}