{
  "type": "Feature",
  "properties": {
    "iso:country":"GB",
    "wof:name":"KA24 5JD",
    "wof:placetype":"postalcode"
},
  "geometry": {"coordinates":[-4.72059193990064,55.71366658099954],"type":"Point"}
}