{
  "type": "Feature",
  "properties": {
    "iso:country":"GB",
    "wof:name":"GL56 0UD",
    "wof:placetype":"postalcode"
},
  "geometry": {"coordinates":[-1.70470733096584,51.93883969657053],"type":"Point"}
}