{
  "type": "Feature",
  "properties": {
    "date:inception_lower": "2009-01-01",
    "date:inception_upper": "2009-01-01",
    "iso:country": "GB",
    "wof:name": "M34 7UG",
    "wof:placetype": "postalcode"
  },
  "geometry": {"coordinates":[-2.104824,53.445599],"type":"Point"}
}
