{
  "type": "Feature",
  "properties": {
    "iso:country":"GB",
    "wof:name":"M34 7UG",
    "wof:placetype":"postalcode"
},
  "geometry": {"coordinates":[-2.10476530407351,53.44573601759282],"type":"Point"}
}