{
  "type": "Feature",
  "properties": {
    "iso:country": "GB",
    "wof:name": "TA3 6LU",
    "wof:placetype": "postalcode"
  },
  "geometry": {"coordinates":[-2.971996,51.022151],"type":"Point"}
}
