{
  "type": "Feature",
  "properties": {
    "iso:country": "GB",
    "wof:name": "LD3 9PY",
    "wof:placetype": "postalcode"
  },
  "geometry": {"coordinates":[-3.411973,51.99277],"type":"Point"}
}
