{
  "type": "Feature",
  "properties": {
    "iso:country":"GB",
    "wof:name":"LD3 9PY",
    "wof:placetype":"postalcode"
},
  "geometry": {"coordinates":[-3.41197313541285,51.9927700752664],"type":"Point"}
}