{
  "type": "Feature",
  "properties": {
    "date:inception_lower":"1980-01-01",
    "date:inception_upper":"1980-01-31",
    "iso:country":"GB",
    "wof:name":"LD3 9PY",
    "wof:placetype":"postalcode"
},
  "geometry": {"coordinates":[-3.411973,51.99277],"type":"Point"}
}