{
  "type": "Feature",
  "properties": {
    "iso:country":"GB",
    "wof:name":"SL0 9DE",
    "wof:placetype":"postalcode"
},
  "geometry": {"coordinates":[-0.5087016407756,51.50227672381238],"type":"Point"}
}