{
  "type": "Feature",
  "properties": {
    "iso:country": "GB",
    "wof:name": "SK10 2LJ",
    "wof:placetype": "postalcode"
  },
  "geometry": {"coordinates":[-2.130643,53.273111],"type":"Point"}
}
