{
  "type": "Feature",
  "properties": {
    "iso:country":"GB",
    "wof:name":"IP22 1QH",
    "wof:placetype":"postalcode"
},
  "geometry": {"coordinates":[1.03061117731117,52.34663752282273],"type":"Point"}
}