{
  "type": "Feature",
  "properties": {
    "iso:country":"GB",
    "wof:name":"N15 4NQ",
    "wof:placetype":"postalcode"
},
  "geometry": {"coordinates":[-0.06970492428265,51.58347851998523],"type":"Point"}
}