{
  "type": "Feature",
  "properties": {
    "iso:country": "GB",
    "wof:name": "N15 4NQ",
    "wof:placetype": "postalcode"
  },
  "geometry": {"coordinates":[-0.069705,51.583479],"type":"Point"}
}
