{
  "type": "Feature",
  "properties": {
    "iso:country":"GB",
    "wof:name":"SW4 0QW",
    "wof:placetype":"postalcode"
},
  "geometry": {"coordinates":[-0.14291177773425,51.4631083420372],"type":"Point"}
}