{
  "type": "Feature",
  "properties": {
    "date:inception_lower":"1980-01-01",
    "date:inception_upper":"1980-01-31",
    "iso:country":"GB",
    "wof:name":"PE7 3RD",
    "wof:placetype":"postalcode"
},
  "geometry": {"coordinates":[-0.287549,52.487657],"type":"Point"}
}