{
  "type": "Feature",
  "properties": {
    "iso:country":"GB",
    "wof:name":"PE7 3RD",
    "wof:placetype":"postalcode"
},
  "geometry": {"coordinates":[-0.28754878959911,52.48765683238464],"type":"Point"}
}