{
  "type": "Feature",
  "properties": {
    "iso:country": "GB",
    "wof:name": "PE12 9BY",
    "wof:placetype": "postalcode"
  },
  "geometry": {"coordinates":[0.110748,52.78824],"type":"Point"}
}
