{
  "type": "Feature",
  "properties": {
    "iso:country":"GB",
    "wof:name":"PE12 9BY",
    "wof:placetype":"postalcode"
},
  "geometry": {"coordinates":[0.11071877704636,52.78822071599378],"type":"Point"}
}