{
  "type": "Feature",
  "properties": {
    "iso:country":"GB",
    "wof:name":"PO9 1NE",
    "wof:placetype":"postalcode"
},
  "geometry": {"coordinates":[-0.98912913597575,50.85366337434263],"type":"Point"}
}