{
  "type": "Feature",
  "properties": {
    "date:inception_lower": "1980-01-01",
    "date:inception_upper": "1980-01-01",
    "iso:country": "GB",
    "wof:name": "PO9 1NE",
    "wof:placetype": "postalcode"
  },
  "geometry": {"coordinates":[-0.989129,50.853663],"type":"Point"}
}
