{
  "type": "Feature",
  "properties": {
    "date:inception_lower": "2010-08-01",
    "date:inception_upper": "2010-08-01",
    "iso:country": "GB",
    "wof:name": "NP44 7DJ",
    "wof:placetype": "postalcode"
  },
  "geometry": {"coordinates":[-3.038921,51.642359],"type":"Point"}
}
