{
  "type": "Feature",
  "properties": {
    "iso:country":"GB",
    "wof:name":"TS13 5JT",
    "wof:placetype":"postalcode"
},
  "geometry": {"coordinates":[-0.77857275476862,54.54077748748232],"type":"Point"}
}