{
  "type": "Feature",
  "properties": {
    "date:inception_lower": "1980-01-01",
    "date:inception_upper": "1980-01-01",
    "iso:country": "GB",
    "wof:name": "TS13 5JT",
    "wof:placetype": "postalcode"
  },
  "geometry": {"coordinates":[-0.778573,54.540777],"type":"Point"}
}
