{
  "type": "Feature",
  "properties": {
    "date:inception_lower": "2009-03-01",
    "date:inception_upper": "2009-03-01",
    "iso:country": "GB",
    "wof:name": "CW11 2WL",
    "wof:placetype": "postalcode"
  },
  "geometry": {"coordinates":[-2.298616,53.143449],"type":"Point"}
}
