{
  "type": "Feature",
  "properties": {
    "iso:country":"GB",
    "wof:name":"CW11 2WL",
    "wof:placetype":"postalcode"
},
  "geometry": {"coordinates":[-2.2986157766774,53.14344919635981],"type":"Point"}
}