{
  "type": "Feature",
  "properties": {
    "iso:country":"GB",
    "wof:name":"PO30 4JT",
    "wof:placetype":"postalcode"
},
  "geometry": {"coordinates":[-1.39503427323367,50.68762563752525],"type":"Point"}
}