{
  "type": "Feature",
  "properties": {
    "iso:country":"GB",
    "wof:name":"NG17 7HY",
    "wof:placetype":"postalcode"
},
  "geometry": {"coordinates":[-1.2330956875702,53.09967365580435],"type":"Point"}
}