{
  "type": "Feature",
  "properties": {
    "iso:country": "GB",
    "wof:name": "NG17 7HY",
    "wof:placetype": "postalcode"
  },
  "geometry": {"coordinates":[-1.233096,53.099674],"type":"Point"}
}
