{
  "type": "Feature",
  "properties": {
    "iso:country": "GB",
    "wof:name": "SO41 0LJ",
    "wof:placetype": "postalcode"
  },
  "geometry": {"coordinates":[-1.628602,50.734241],"type":"Point"}
}
