{
  "type": "Feature",
  "properties": {
    "iso:country":"GB",
    "wof:name":"ML3 7YH",
    "wof:placetype":"postalcode"
},
  "geometry": {"coordinates":[-4.03935699661297,55.75506618024652],"type":"Point"}
}