{
  "type": "Feature",
  "properties": {
    "iso:country":"GB",
    "wof:name":"AB53 4RE",
    "wof:placetype":"postalcode"
},
  "geometry": {"coordinates":[-2.4625994204752,57.53632792088735],"type":"Point"}
}