{
  "type": "Feature",
  "properties": {
    "iso:country":"GB",
    "wof:name":"N11 2AG",
    "wof:placetype":"postalcode"
},
  "geometry": {"coordinates":[-0.13174512814254,51.6070175440019],"type":"Point"}
}