{
  "type": "Feature",
  "properties": {
    "iso:country":"GB",
    "wof:name":"ML5 5BY",
    "wof:placetype":"postalcode"
},
  "geometry": {"coordinates":[-4.03733101797172,55.84665097634708],"type":"Point"}
}