{
  "type": "Feature",
  "properties": {
    "iso:country":"GB",
    "wof:name":"LE4 6DP",
    "wof:placetype":"postalcode"
},
  "geometry": {"coordinates":[-1.12109878362179,52.64520123531299],"type":"Point"}
}