{
  "type": "Feature",
  "properties": {
    "iso:country":"GB",
    "wof:name":"WD3 7EH",
    "wof:placetype":"postalcode"
},
  "geometry": {"coordinates":[-0.48593756789717,51.63821489652166],"type":"Point"}
}