{
  "type": "Feature",
  "properties": {
    "date:inception_lower":"2000-10-01",
    "date:inception_upper":"2000-10-31",
    "iso:country":"GB",
    "wof:name":"WD3 7EH",
    "wof:placetype":"postalcode"
},
  "geometry": {"coordinates":[-0.485938,51.638215],"type":"Point"}
}