{
  "type": "Feature",
  "properties": {
    "iso:country":"GB",
    "wof:name":"GL3 4FH",
    "wof:placetype":"postalcode"
},
  "geometry": {"coordinates":[-2.18189220052568,51.84382812942025],"type":"Point"}
}