{
  "type": "Feature",
  "properties": {
    "iso:country":"GB",
    "wof:name":"RG17 0ED",
    "wof:placetype":"postalcode"
},
  "geometry": {"coordinates":[-1.50989296987104,51.41287545978857],"type":"Point"}
}