{
  "type": "Feature",
  "properties": {
    "iso:country":"GB",
    "wof:name":"EX36 4PS",
    "wof:placetype":"postalcode"
},
  "geometry": {"coordinates":[-3.7426587803742,50.98437272471984],"type":"Point"}
}