{
  "type": "Feature",
  "properties": {
    "iso:country":"GB",
    "wof:name":"TN13 3HZ",
    "wof:placetype":"postalcode"
},
  "geometry": {"coordinates":[0.17977938789231,51.28207901389123],"type":"Point"}
}