{
  "type": "Feature",
  "properties": {
    "iso:country":"GB",
    "wof:name":"HA3 8EW",
    "wof:placetype":"postalcode"
},
  "geometry": {"coordinates":[-0.31333170966809,51.58563209890436],"type":"Point"}
}