{
  "type": "Feature",
  "properties": {
    "date:inception_lower": "1980-01-01",
    "date:inception_upper": "1980-01-01",
    "iso:country": "GB",
    "wof:name": "LL55 1UD",
    "wof:placetype": "postalcode"
  },
  "geometry": {"coordinates":[-4.225859,53.1469],"type":"Point"}
}
