{
  "type": "Feature",
  "properties": {
    "iso:country": "GB",
    "wof:name": "DD8 2TP",
    "wof:placetype": "postalcode"
  },
  "geometry": {"coordinates":[-2.708395,56.642833],"type":"Point"}
}
