{
  "type": "Feature",
  "properties": {
    "date:inception_lower": "1980-01-01",
    "date:inception_upper": "1980-01-01",
    "iso:country": "GB",
    "wof:name": "DD8 2TP",
    "wof:placetype": "postalcode"
  },
  "geometry": {"coordinates":[-2.708395,56.642833],"type":"Point"}
}
