{
  "type": "Feature",
  "properties": {
    "iso:country": "GB",
    "wof:name": "YO41 1EB",
    "wof:placetype": "postalcode"
  },
  "geometry": {"coordinates":[-0.925852,53.973537],"type":"Point"}
}
