{
  "type": "Feature",
  "properties": {
    "iso:country":"GB",
    "wof:name":"WA2 7PT",
    "wof:placetype":"postalcode"
},
  "geometry": {"coordinates":[-2.58764557821959,53.40024626762721],"type":"Point"}
}