{
  "type": "Feature",
  "properties": {
    "iso:country": "GB",
    "wof:name": "WA2 7PT",
    "wof:placetype": "postalcode"
  },
  "geometry": {"coordinates":[-2.587762,53.400037],"type":"Point"}
}
