{
  "type": "Feature",
  "properties": {
    "iso:country":"GB",
    "wof:name":"W2 5HU",
    "wof:placetype":"postalcode"
},
  "geometry": {"coordinates":[-0.18869345558419,51.51685325206007],"type":"Point"}
}