{
  "type": "Feature",
  "properties": {
    "date:inception_lower": "2019-07-01",
    "date:inception_upper": "2019-07-01",
    "iso:country": "GB",
    "wof:name": "HR4 9EB",
    "wof:placetype": "postalcode"
  },
  "geometry": {"coordinates":[-2.716457,52.060499],"type":"Point"}
}
