{
  "type": "Feature",
  "properties": {
    "iso:country":"GB",
    "wof:name":"M18 7DH",
    "wof:placetype":"postalcode"
},
  "geometry": {"coordinates":[-2.18787217809711,53.45896398655094],"type":"Point"}
}