{
  "type": "Feature",
  "properties": {
    "date:inception_lower": "1980-01-01",
    "date:inception_upper": "1980-01-01",
    "iso:country": "GB",
    "wof:name": "BA14 6BE",
    "wof:placetype": "postalcode"
  },
  "geometry": {"coordinates":[-2.168272,51.296472],"type":"Point"}
}
