{
  "type": "Feature",
  "properties": {
    "iso:country":"GB",
    "wof:name":"BA14 6BE",
    "wof:placetype":"postalcode"
},
  "geometry": {"coordinates":[-2.16827251649462,51.29647214249162],"type":"Point"}
}