{
  "type": "Feature",
  "properties": {
    "date:inception_lower": "2011-08-01",
    "date:inception_upper": "2011-08-01",
    "iso:country": "GB",
    "wof:name": "NG17 2TE",
    "wof:placetype": "postalcode"
  },
  "geometry": {"coordinates":[-1.29384,53.121354],"type":"Point"}
}
