{
  "type": "Feature",
  "properties": {
    "date:inception_lower": "1980-01-01",
    "date:inception_upper": "1980-01-01",
    "iso:country": "GB",
    "wof:name": "EX38 7BJ",
    "wof:placetype": "postalcode"
  },
  "geometry": {"coordinates":[-4.136969,50.954726],"type":"Point"}
}
