{
  "type": "Feature",
  "properties": {
    "iso:country":"GB",
    "wof:name":"EX38 7BJ",
    "wof:placetype":"postalcode"
},
  "geometry": {"coordinates":[-4.13696950306595,50.95472642238317],"type":"Point"}
}