{
  "type": "Feature",
  "properties": {
    "date:inception_lower":"2005-07-01",
    "date:inception_upper":"2005-07-31",
    "iso:country":"GB",
    "wof:name":"SN4 0TP",
    "wof:placetype":"postalcode"
},
  "geometry": {"coordinates":[-1.768287,51.511984],"type":"Point"}
}