{
  "type": "Feature",
  "properties": {
    "iso:country": "GB",
    "wof:name": "SN4 0TP",
    "wof:placetype": "postalcode"
  },
  "geometry": {"coordinates":[-1.768286,51.512128],"type":"Point"}
}
