{
  "type": "Feature",
  "properties": {
    "iso:country":"GB",
    "wof:name":"S75 1JL",
    "wof:placetype":"postalcode"
},
  "geometry": {"coordinates":[-1.50394319024373,53.56457009185321],"type":"Point"}
}