{
  "type": "Feature",
  "properties": {
    "date:inception_lower": "2011-05-01",
    "date:inception_upper": "2011-05-01",
    "iso:country": "GB",
    "wof:name": "AL3 7FD",
    "wof:placetype": "postalcode"
  },
  "geometry": {"coordinates":[-0.395276,51.799199],"type":"Point"}
}
