{
  "type": "Feature",
  "properties": {
    "iso:country": "GB",
    "wof:name": "AL3 7FD",
    "wof:placetype": "postalcode"
  },
  "geometry": {"coordinates":[-0.395276,51.799199],"type":"Point"}
}
