{
  "type": "Feature",
  "properties": {
    "iso:country": "GB",
    "wof:name": "M18 8GL",
    "wof:placetype": "postalcode"
  },
  "geometry": {"coordinates":[-2.163431,53.467296],"type":"Point"}
}
