{
  "type": "Feature",
  "properties": {
    "date:inception_lower": "1980-01-01",
    "date:inception_upper": "1980-01-01",
    "iso:country": "GB",
    "wof:name": "WS10 8NL",
    "wof:placetype": "postalcode"
  },
  "geometry": {"coordinates":[-2.045107,52.572711],"type":"Point"}
}
