{
  "type": "Feature",
  "properties": {
    "date:inception_lower": "1980-01-01",
    "date:inception_upper": "1980-01-01",
    "iso:country": "GB",
    "wof:name": "NE9 7XD",
    "wof:placetype": "postalcode"
  },
  "geometry": {"coordinates":[-1.567562,54.920256],"type":"Point"}
}
