{
  "type": "Feature",
  "properties": {
    "iso:country":"GB",
    "wof:name":"SA19 6PL",
    "wof:placetype":"postalcode"
},
  "geometry": {"coordinates":[-3.99233852801106,51.86496414209311],"type":"Point"}
}