{
  "type": "Feature",
  "properties": {
    "iso:country":"GB",
    "wof:name":"S43 4ES",
    "wof:placetype":"postalcode"
},
  "geometry": {"coordinates":[-1.28732356850512,53.29118094927126],"type":"Point"}
}