{
  "type": "Feature",
  "properties": {
    "date:inception_lower": "2020-05-01",
    "date:inception_upper": "2020-05-01",
    "iso:country": "GB",
    "wof:name": "L22 0AD",
    "wof:placetype": "postalcode"
  },
  "geometry": {"coordinates":[-3.022878,53.478523],"type":"Point"}
}
