{
  "type": "Feature",
  "properties": {
    "iso:country": "GB",
    "wof:name": "BS15 3FT",
    "wof:placetype": "postalcode"
  },
  "geometry": {"coordinates":[-2.506541,51.448921],"type":"Point"}
}
