{
  "type": "Feature",
  "properties": {
    "iso:country":"GB",
    "wof:name":"OX33 1XT",
    "wof:placetype":"postalcode"
},
  "geometry": {"coordinates":[-1.1385888092539,51.74707435326897],"type":"Point"}
}