{
  "type": "Feature",
  "properties": {
    "iso:country":"GB",
    "wof:name":"ST1 6LN",
    "wof:placetype":"postalcode"
},
  "geometry": {"coordinates":[-2.16404248859953,53.03545590180196],"type":"Point"}
}