{
  "type": "Feature",
  "properties": {
    "iso:country": "GB",
    "wof:name": "ST1 6LN",
    "wof:placetype": "postalcode"
  },
  "geometry": {"coordinates":[-2.164042,53.035456],"type":"Point"}
}
