{
  "type": "Feature",
  "properties": {
    "iso:country": "GB",
    "wof:name": "LA22 9HX",
    "wof:placetype": "postalcode"
  },
  "geometry": {"coordinates":[-3.038519,54.433033],"type":"Point"}
}
