{
  "type": "Feature",
  "properties": {
    "iso:country":"GB",
    "wof:name":"CA8 1TA",
    "wof:placetype":"postalcode"
},
  "geometry": {"coordinates":[-2.75508192657444,54.92539001840468],"type":"Point"}
}