{
  "type": "Feature",
  "properties": {
    "iso:country": "GB",
    "wof:name": "CA8 1TA",
    "wof:placetype": "postalcode"
  },
  "geometry": {"coordinates":[-2.756098,54.925238],"type":"Point"}
}
