{
  "type": "Feature",
  "properties": {
    "iso:country":"GB",
    "wof:name":"AB42 1NS",
    "wof:placetype":"postalcode"
},
  "geometry": {"coordinates":[-1.78892847274884,57.51497522676861],"type":"Point"}
}