{
  "type": "Feature",
  "properties": {
    "iso:country":"GB",
    "wof:name":"TF1 6DR",
    "wof:placetype":"postalcode"
},
  "geometry": {"coordinates":[-2.50563567331815,52.71140373855611],"type":"Point"}
}