{
  "type": "Feature",
  "properties": {
    "iso:country": "GB",
    "wof:name": "NN11 4PH",
    "wof:placetype": "postalcode"
  },
  "geometry": {"coordinates":[-1.15201,52.250168],"type":"Point"}
}
