{
  "type": "Feature",
  "properties": {
    "iso:country":"GB",
    "wof:name":"BH20 5EU",
    "wof:placetype":"postalcode"
},
  "geometry": {"coordinates":[-2.05326356289028,50.62948776069625],"type":"Point"}
}