{
  "type": "Feature",
  "properties": {
    "iso:country": "GB",
    "wof:name": "BD20 7EU",
    "wof:placetype": "postalcode"
  },
  "geometry": {"coordinates":[-1.989799,53.895063],"type":"Point"}
}
