{
  "type": "Feature",
  "properties": {
    "iso:country":"GB",
    "wof:name":"BD4 8DZ",
    "wof:placetype":"postalcode"
},
  "geometry": {"coordinates":[-1.71217647902943,53.79139423325248],"type":"Point"}
}