{
  "type": "Feature",
  "properties": {
    "date:inception_lower":"2012-10-01",
    "date:inception_upper":"2012-10-31",
    "iso:country":"GB",
    "wof:name":"BD4 8DZ",
    "wof:placetype":"postalcode"
},
  "geometry": {"coordinates":[-1.712176,53.791394],"type":"Point"}
}