{
  "type": "Feature",
  "properties": {
    "iso:country":"GB",
    "wof:name":"BA4 5PH",
    "wof:placetype":"postalcode"
},
  "geometry": {"coordinates":[-2.53469107633186,51.18763902254291],"type":"Point"}
}