{
  "type": "Feature",
  "properties": {
    "iso:country": "GB",
    "wof:name": "RG14 7JB",
    "wof:placetype": "postalcode"
  },
  "geometry": {"coordinates":[-1.317074,51.395312],"type":"Point"}
}
