{
  "type": "Feature",
  "properties": {
    "iso:country":"GB",
    "wof:name":"RG14 7JB",
    "wof:placetype":"postalcode"
},
  "geometry": {"coordinates":[-1.31707433547619,51.39531228191181],"type":"Point"}
}