{
  "type": "Feature",
  "properties": {
    "iso:country":"GB",
    "wof:name":"PL15 9HZ",
    "wof:placetype":"postalcode"
},
  "geometry": {"coordinates":[-4.36020242123603,50.62903125803972],"type":"Point"}
}