{
  "type": "Feature",
  "properties": {
    "iso:country":"GB",
    "wof:name":"DD10 8SS",
    "wof:placetype":"postalcode"
},
  "geometry": {"coordinates":[-2.46606895995268,56.71858708067234],"type":"Point"}
}