{
  "type": "Feature",
  "properties": {
    "iso:country": "GB",
    "wof:name": "KT5 8BX",
    "wof:placetype": "postalcode"
  },
  "geometry": {"coordinates":[-0.30077,51.398985],"type":"Point"}
}
