{
  "type": "Feature",
  "properties": {
    "iso:country":"GB",
    "wof:name":"KT5 8BX",
    "wof:placetype":"postalcode"
},
  "geometry": {"coordinates":[-0.30077010053712,51.3989853158341],"type":"Point"}
}