{
  "type": "Feature",
  "properties": {
    "iso:country":"GB",
    "wof:name":"BA2 8LZ",
    "wof:placetype":"postalcode"
},
  "geometry": {"coordinates":[-2.4024691677717,51.30461398699487],"type":"Point"}
}