{
  "type": "Feature",
  "properties": {
    "iso:country":"GB",
    "wof:name":"IG10 4EF",
    "wof:placetype":"postalcode"
},
  "geometry": {"coordinates":[0.04226680937962,51.64372205983858],"type":"Point"}
}