{
  "type": "Feature",
  "properties": {
    "iso:country":"GB",
    "wof:name":"SG13 7NR",
    "wof:placetype":"postalcode"
},
  "geometry": {"coordinates":[-0.06472493229935,51.79718070229477],"type":"Point"}
}