{
  "type": "Feature",
  "properties": {
    "iso:country": "GB",
    "wof:name": "SG13 7NR",
    "wof:placetype": "postalcode"
  },
  "geometry": {"coordinates":[-0.064725,51.797181],"type":"Point"}
}
