{
  "type": "Feature",
  "properties": {
    "iso:country": "GB",
    "wof:name": "L19 9BZ",
    "wof:placetype": "postalcode"
  },
  "geometry": {"coordinates":[-2.90906,53.365197],"type":"Point"}
}
