{
  "type": "Feature",
  "properties": {
    "iso:country": "GB",
    "wof:name": "GU2 8AA",
    "wof:placetype": "postalcode"
  },
  "geometry": {"coordinates":[-0.59749,51.248604],"type":"Point"}
}
