{
  "type": "Feature",
  "properties": {
    "iso:country":"GB",
    "wof:name":"CB2 9BZ",
    "wof:placetype":"postalcode"
},
  "geometry": {"coordinates":[0.12176432613795,52.17794760308471],"type":"Point"}
}