{
  "type": "Feature",
  "properties": {
    "iso:country":"GB",
    "wof:name":"DE13 8RA",
    "wof:placetype":"postalcode"
},
  "geometry": {"coordinates":[-1.82804712010506,52.80967937486962],"type":"Point"}
}