{
  "type": "Feature",
  "properties": {
    "iso:country": "GB",
    "wof:name": "SM6 9GG",
    "wof:placetype": "postalcode"
  },
  "geometry": {"coordinates":[-0.125629,51.354625],"type":"Point"}
}
