{
  "type": "Feature",
  "properties": {
    "iso:country":"GB",
    "wof:name":"SM6 9GG",
    "wof:placetype":"postalcode"
},
  "geometry": {"coordinates":[-0.12562948910226,51.35462454303413],"type":"Point"}
}