{
  "type": "Feature",
  "properties": {
    "iso:country":"GB",
    "wof:name":"DT7 3XP",
    "wof:placetype":"postalcode"
},
  "geometry": {"coordinates":[-3.00971557406216,50.70876690055584],"type":"Point"}
}