{
  "type": "Feature",
  "properties": {
    "date:inception_lower": "1980-01-01",
    "date:inception_upper": "1980-01-01",
    "iso:country": "GB",
    "wof:name": "DT7 3XP",
    "wof:placetype": "postalcode"
  },
  "geometry": {"coordinates":[-3.009716,50.708767],"type":"Point"}
}
