{
  "type": "Feature",
  "properties": {
    "date:inception_lower": "1980-01-01",
    "date:inception_upper": "1980-01-01",
    "iso:country": "GB",
    "wof:name": "BS5 7JF",
    "wof:placetype": "postalcode"
  },
  "geometry": {"coordinates":[-2.543335,51.46087],"type":"Point"}
}
