{
  "type": "Feature",
  "properties": {
    "iso:country": "GB",
    "wof:name": "SL2 5LY",
    "wof:placetype": "postalcode"
  },
  "geometry": {"coordinates":[-0.572565,51.522199],"type":"Point"}
}
