{
  "type": "Feature",
  "properties": {
    "date:inception_lower": "1980-01-01",
    "date:inception_upper": "1980-01-01",
    "iso:country": "GB",
    "wof:name": "BL8 3NA",
    "wof:placetype": "postalcode"
  },
  "geometry": {"coordinates":[-2.338375,53.614338],"type":"Point"}
}
