{
  "type": "Feature",
  "properties": {
    "iso:country":"GB",
    "wof:name":"LL57 3YD",
    "wof:placetype":"postalcode"
},
  "geometry": {"coordinates":[-4.08396375022025,53.21190841141629],"type":"Point"}
}