{
  "type": "Feature",
  "properties": {
    "iso:country": "GB",
    "wof:name": "LL57 3YD",
    "wof:placetype": "postalcode"
  },
  "geometry": {"coordinates":[-4.083964,53.211908],"type":"Point"}
}
