{
  "type": "Feature",
  "properties": {
    "iso:country":"GB",
    "wof:name":"AL3 4NH",
    "wof:placetype":"postalcode"
},
  "geometry": {"coordinates":[-0.36095934864441,51.74048467411983],"type":"Point"}
}