{
  "type": "Feature",
  "properties": {
    "date:inception_lower":"2011-07-01",
    "date:inception_upper":"2011-07-31",
    "iso:country":"GB",
    "wof:name":"YO8 8SA",
    "wof:placetype":"postalcode"
},
  "geometry": {"coordinates":[-1.061002,53.768111],"type":"Point"}
}