{
  "type": "Feature",
  "properties": {
    "iso:country": "GB",
    "wof:name": "YO8 8SA",
    "wof:placetype": "postalcode"
  },
  "geometry": {"coordinates":[-1.061002,53.768111],"type":"Point"}
}
