{
  "type": "Feature",
  "properties": {
    "date:inception_lower": "2001-12-01",
    "date:inception_upper": "2001-12-01",
    "iso:country": "GB",
    "wof:name": "PO12 4LZ",
    "wof:placetype": "postalcode"
  },
  "geometry": {"coordinates":[-1.131455,50.810556],"type":"Point"}
}
