{
  "type": "Feature",
  "properties": {
    "iso:country": "GB",
    "wof:name": "PO12 4LZ",
    "wof:placetype": "postalcode"
  },
  "geometry": {"coordinates":[-1.131455,50.810556],"type":"Point"}
}
