{
  "type": "Feature",
  "properties": {
    "iso:country":"GB",
    "wof:name":"G52 2AS",
    "wof:placetype":"postalcode"
},
  "geometry": {"coordinates":[-4.35975336156207,55.85018944733462],"type":"Point"}
}