{
  "type": "Feature",
  "properties": {
    "iso:country":"GB",
    "wof:name":"YO8 4LR",
    "wof:placetype":"postalcode"
},
  "geometry": {"coordinates":[-1.07418306245935,53.78825707987205],"type":"Point"}
}