{
  "type": "Feature",
  "properties": {
    "iso:country":"GB",
    "wof:name":"ST5 6AX",
    "wof:placetype":"postalcode"
},
  "geometry": {"coordinates":[-2.26581430909656,53.02706471714844],"type":"Point"}
}