{
  "type": "Feature",
  "properties": {
    "date:inception_lower": "2011-05-01",
    "date:inception_upper": "2011-05-01",
    "iso:country": "GB",
    "wof:name": "ST5 6AX",
    "wof:placetype": "postalcode"
  },
  "geometry": {"coordinates":[-2.265814,53.027065],"type":"Point"}
}
