{
  "type": "Feature",
  "properties": {
    "iso:country":"GB",
    "wof:name":"TQ4 6BE",
    "wof:placetype":"postalcode"
},
  "geometry": {"coordinates":[-3.56092801390065,50.43628091643164],"type":"Point"}
}