{
  "type": "Feature",
  "properties": {
    "iso:country":"GB",
    "wof:name":"TR20 9SR",
    "wof:placetype":"postalcode"
},
  "geometry": {"coordinates":[-5.38375774251832,50.10967277476246],"type":"Point"}
}