{
  "type": "Feature",
  "properties": {
    "date:inception_lower":"1990-02-01",
    "date:inception_upper":"1990-02-28",
    "iso:country":"GB",
    "wof:name":"TR20 9SR",
    "wof:placetype":"postalcode"
},
  "geometry": {"coordinates":[-5.383758,50.109673],"type":"Point"}
}