{
  "type": "Feature",
  "properties": {
    "iso:country":"GB",
    "wof:name":"ML5 2TG",
    "wof:placetype":"postalcode"
},
  "geometry": {"coordinates":[-4.04007217555971,55.89559354261623],"type":"Point"}
}