{
  "type": "Feature",
  "properties": {
    "date:inception_lower": "2010-03-01",
    "date:inception_upper": "2010-03-01",
    "iso:country": "GB",
    "wof:name": "ML5 2TG",
    "wof:placetype": "postalcode"
  },
  "geometry": {"coordinates":[-4.040072,55.895594],"type":"Point"}
}
