{
  "type": "Feature",
  "properties": {
    "iso:country": "GB",
    "wof:name": "ML5 2TG",
    "wof:placetype": "postalcode"
  },
  "geometry": {"coordinates":[-4.040072,55.895594],"type":"Point"}
}
