{
  "type": "Feature",
  "properties": {
    "iso:country":"GB",
    "wof:name":"B90 2LD",
    "wof:placetype":"postalcode"
},
  "geometry": {"coordinates":[-1.84337079174133,52.40783087188044],"type":"Point"}
}