{
  "type": "Feature",
  "properties": {
    "iso:country": "GB",
    "wof:name": "B90 2LD",
    "wof:placetype": "postalcode"
  },
  "geometry": {"coordinates":[-1.843371,52.407831],"type":"Point"}
}
