{
  "type": "Feature",
  "properties": {
    "date:inception_lower": "1980-01-01",
    "date:inception_upper": "1980-01-01",
    "iso:country": "GB",
    "wof:name": "EN11 8UA",
    "wof:placetype": "postalcode"
  },
  "geometry": {"coordinates":[-0.011122,51.764612],"type":"Point"}
}
