{
  "type": "Feature",
  "properties": {
    "date:inception_lower":"1991-09-01",
    "date:inception_upper":"1991-09-30",
    "iso:country":"GB",
    "wof:name":"DL9 3RG",
    "wof:placetype":"postalcode"
},
  "geometry": {"coordinates":[-1.709062,54.354036],"type":"Point"}
}