{
  "type": "Feature",
  "properties": {
    "iso:country": "GB",
    "wof:name": "DL9 3RG",
    "wof:placetype": "postalcode"
  },
  "geometry": {"coordinates":[-1.709062,54.354036],"type":"Point"}
}
