{
  "type": "Feature",
  "properties": {
    "iso:country":"GB",
    "wof:name":"B61 0JX",
    "wof:placetype":"postalcode"
},
  "geometry": {"coordinates":[-2.06314630574845,52.36325442760615],"type":"Point"}
}