{
  "type": "Feature",
  "properties": {
    "date:inception_lower": "1995-12-01",
    "date:inception_upper": "1995-12-01",
    "iso:country": "GB",
    "wof:name": "B61 0JX",
    "wof:placetype": "postalcode"
  },
  "geometry": {"coordinates":[-2.063146,52.363254],"type":"Point"}
}
