{
  "type": "Feature",
  "properties": {
    "iso:country":"GB",
    "wof:name":"YO26 5LR",
    "wof:placetype":"postalcode"
},
  "geometry": {"coordinates":[-1.13069959405409,53.95451150889449],"type":"Point"}
}