{
  "type": "Feature",
  "properties": {
    "iso:country": "GB",
    "wof:name": "YO26 5LR",
    "wof:placetype": "postalcode"
  },
  "geometry": {"coordinates":[-1.1307,53.954512],"type":"Point"}
}
