{
  "type": "Feature",
  "properties": {
    "date:inception_lower": "1998-06-01",
    "date:inception_upper": "1998-06-01",
    "iso:country": "GB",
    "wof:name": "YO26 5LR",
    "wof:placetype": "postalcode"
  },
  "geometry": {"coordinates":[-1.1307,53.954512],"type":"Point"}
}
