{
  "type": "Feature",
  "properties": {
    "date:inception_lower": "1980-01-01",
    "date:inception_upper": "1980-01-01",
    "iso:country": "GB",
    "wof:name": "SY20 9TJ",
    "wof:placetype": "postalcode"
  },
  "geometry": {"coordinates":[-3.841916,52.655056],"type":"Point"}
}
