{
  "type": "Feature",
  "properties": {
    "iso:country": "GB",
    "wof:name": "SY20 9TJ",
    "wof:placetype": "postalcode"
  },
  "geometry": {"coordinates":[-3.841814,52.655085],"type":"Point"}
}
