{
  "type": "Feature",
  "properties": {
    "iso:country":"GB",
    "wof:name":"SY20 9TJ",
    "wof:placetype":"postalcode"
},
  "geometry": {"coordinates":[-3.84190800672712,52.65504094870716],"type":"Point"}
}