{
  "type": "Feature",
  "properties": {
    "iso:country":"GB",
    "wof:name":"LL57 1TG",
    "wof:placetype":"postalcode"
},
  "geometry": {"coordinates":[-4.11399507148645,53.22383112197667],"type":"Point"}
}