{
  "type": "Feature",
  "properties": {
    "iso:country": "GB",
    "wof:name": "L33 9TZ",
    "wof:placetype": "postalcode"
  },
  "geometry": {"coordinates":[-2.872409,53.49106],"type":"Point"}
}
