{
  "type": "Feature",
  "properties": {
    "date:inception_lower": "1980-01-01",
    "date:inception_upper": "1980-01-01",
    "iso:country": "GB",
    "wof:name": "L33 9TZ",
    "wof:placetype": "postalcode"
  },
  "geometry": {"coordinates":[-2.87297,53.4912],"type":"Point"}
}
