{
  "type": "Feature",
  "properties": {
    "iso:country":"GB",
    "wof:name":"L33 9TZ",
    "wof:placetype":"postalcode"
},
  "geometry": {"coordinates":[-2.87322750240306,53.49119110017467],"type":"Point"}
}