{
  "type": "Feature",
  "properties": {
    "date:inception_lower": "2018-12-01",
    "date:inception_upper": "2018-12-01",
    "iso:country": "GB",
    "wof:name": "CA14 3FB",
    "wof:placetype": "postalcode"
  },
  "geometry": {"coordinates":[-3.567099,54.630134],"type":"Point"}
}
