{
  "type": "Feature",
  "properties": {
    "iso:country":"GB",
    "wof:name":"G42 8BY",
    "wof:placetype":"postalcode"
},
  "geometry": {"coordinates":[-4.25840655335119,55.83187930072945],"type":"Point"}
}