{
  "type": "Feature",
  "properties": {
    "iso:country": "GB",
    "wof:name": "DD1 3BH",
    "wof:placetype": "postalcode"
  },
  "geometry": {"coordinates":[-2.961016,56.459771],"type":"Point"}
}
