{
  "type": "Feature",
  "properties": {
    "iso:country":"GB",
    "wof:name":"YO7 3BJ",
    "wof:placetype":"postalcode"
},
  "geometry": {"coordinates":[-1.30698748012071,54.1774122198277],"type":"Point"}
}