{
  "type": "Feature",
  "properties": {
    "iso:country": "GB",
    "wof:name": "ST3 6EY",
    "wof:placetype": "postalcode"
  },
  "geometry": {"coordinates":[-2.101914,52.990427],"type":"Point"}
}
