{
  "type": "Feature",
  "properties": {
    "iso:country":"GB",
    "wof:name":"SK8 6JU",
    "wof:placetype":"postalcode"
},
  "geometry": {"coordinates":[-2.19283683500021,53.37475136693265],"type":"Point"}
}