{
  "type": "Feature",
  "properties": {
    "date:inception_lower": "2000-06-01",
    "date:inception_upper": "2000-06-01",
    "iso:country": "GB",
    "wof:name": "SA4 6PB",
    "wof:placetype": "postalcode"
  },
  "geometry": {"coordinates":[-4.051677,51.662505],"type":"Point"}
}
