{
  "type": "Feature",
  "properties": {
    "iso:country": "GB",
    "wof:name": "SA4 6PB",
    "wof:placetype": "postalcode"
  },
  "geometry": {"coordinates":[-4.051677,51.662505],"type":"Point"}
}
