{
  "type": "Feature",
  "properties": {
    "iso:country": "GB",
    "wof:name": "WS12 2RS",
    "wof:placetype": "postalcode"
  },
  "geometry": {"coordinates":[-1.978703,52.700487],"type":"Point"}
}
