{
  "type": "Feature",
  "properties": {
    "date:inception_lower": "1980-01-01",
    "date:inception_upper": "1980-01-01",
    "iso:country": "GB",
    "wof:name": "LL34 6PE",
    "wof:placetype": "postalcode"
  },
  "geometry": {"coordinates":[-3.935217,53.266337],"type":"Point"}
}
