{
  "type": "Feature",
  "properties": {
    "iso:country":"GB",
    "wof:name":"N22 7RS",
    "wof:placetype":"postalcode"
},
  "geometry": {"coordinates":[-0.12427207495899,51.59911993393393],"type":"Point"}
}