{
  "type": "Feature",
  "properties": {
    "iso:country":"GB",
    "wof:name":"L31 1JQ",
    "wof:placetype":"postalcode"
},
  "geometry": {"coordinates":[-2.91605809724278,53.48464120066098],"type":"Point"}
}