{
  "type": "Feature",
  "properties": {
    "date:inception_lower": "1990-08-01",
    "date:inception_upper": "1990-08-01",
    "iso:country": "GB",
    "wof:name": "AB41 9LJ",
    "wof:placetype": "postalcode"
  },
  "geometry": {"coordinates":[-2.075641,57.363029],"type":"Point"}
}
