{
  "type": "Feature",
  "properties": {
    "iso:country":"GB",
    "wof:name":"G81 1SW",
    "wof:placetype":"postalcode"
},
  "geometry": {"coordinates":[-4.40199090709176,55.89902030832024],"type":"Point"}
}