{
  "type": "Feature",
  "properties": {
    "date:inception_lower": "1997-12-01",
    "date:inception_upper": "1997-12-01",
    "iso:country": "GB",
    "wof:name": "G81 1SW",
    "wof:placetype": "postalcode"
  },
  "geometry": {"coordinates":[-4.401991,55.89902],"type":"Point"}
}
