{
  "type": "Feature",
  "properties": {
    "iso:country": "GB",
    "wof:name": "TD9 9PZ",
    "wof:placetype": "postalcode"
  },
  "geometry": {"coordinates":[-2.780294,55.427397],"type":"Point"}
}
