{
  "type": "Feature",
  "properties": {
    "iso:country": "GB",
    "wof:name": "CF39 9PY",
    "wof:placetype": "postalcode"
  },
  "geometry": {"coordinates":[-3.407738,51.61162],"type":"Point"}
}
