{
  "type": "Feature",
  "properties": {
    "iso:country":"GB",
    "wof:name":"TS25 1BJ",
    "wof:placetype":"postalcode"
},
  "geometry": {"coordinates":[-1.19182804410745,54.65977176190444],"type":"Point"}
}