{
  "type": "Feature",
  "properties": {
    "iso:country":"GB",
    "wof:name":"L3 6DE",
    "wof:placetype":"postalcode"
},
  "geometry": {"coordinates":[-2.98497426965472,53.41826747988782],"type":"Point"}
}