{
  "type": "Feature",
  "properties": {
    "date:inception_lower": "1980-01-01",
    "date:inception_upper": "1980-01-01",
    "iso:country": "GB",
    "wof:name": "HG4 1BP",
    "wof:placetype": "postalcode"
  },
  "geometry": {"coordinates":[-1.523004,54.13648],"type":"Point"}
}
