{
  "type": "Feature",
  "properties": {
    "iso:country":"GB",
    "wof:name":"B71 4DA",
    "wof:placetype":"postalcode"
},
  "geometry": {"coordinates":[-1.98465654224215,52.52695161206435],"type":"Point"}
}