{
  "type": "Feature",
  "properties": {
    "date:inception_lower":"2015-07-01",
    "date:inception_upper":"2015-07-31",
    "iso:country":"GB",
    "wof:name":"CH8 9AB",
    "wof:placetype":"postalcode"
},
  "geometry": {"coordinates":[-3.304437,53.327245],"type":"Point"}
}