{
  "type": "Feature",
  "properties": {
    "date:inception_lower": "2015-07-01",
    "date:inception_upper": "2015-07-01",
    "iso:country": "GB",
    "wof:name": "CH8 9AB",
    "wof:placetype": "postalcode"
  },
  "geometry": {"coordinates":[-3.304955,53.32749],"type":"Point"}
}
