{
  "type": "Feature",
  "properties": {
    "iso:country": "GB",
    "wof:name": "CH8 9AB",
    "wof:placetype": "postalcode"
  },
  "geometry": {"coordinates":[-3.30471,53.327348],"type":"Point"}
}
