{
  "type": "Feature",
  "properties": {
    "date:inception_lower":"2007-01-01",
    "date:inception_upper":"2007-01-31",
    "iso:country":"GB",
    "wof:name":"DN1 3AN",
    "wof:placetype":"postalcode"
},
  "geometry": {"coordinates":[-1.133239,53.518451],"type":"Point"}
}