{
  "type": "Feature",
  "properties": {
    "iso:country":"GB",
    "wof:name":"DN1 3AN",
    "wof:placetype":"postalcode"
},
  "geometry": {"coordinates":[-1.13323871416369,53.51845078449896],"type":"Point"}
}