{
  "type": "Feature",
  "properties": {
    "iso:country":"GB",
    "wof:name":"WS15 2YJ",
    "wof:placetype":"postalcode"
},
  "geometry": {"coordinates":[-1.94294064686038,52.76829448784351],"type":"Point"}
}