{
  "type": "Feature",
  "properties": {
    "iso:country":"GB",
    "wof:name":"BN1 1RU",
    "wof:placetype":"postalcode"
},
  "geometry": {"coordinates":[-0.14171477006298,50.82378477380373],"type":"Point"}
}