{
  "type": "Feature",
  "properties": {
    "date:inception_lower":"1997-12-01",
    "date:inception_upper":"1997-12-31",
    "iso:country":"GB",
    "wof:name":"BS32 0EW",
    "wof:placetype":"postalcode"
},
  "geometry": {"coordinates":[-2.551128,51.541253],"type":"Point"}
}