{
  "type": "Feature",
  "properties": {
    "date:inception_lower": "1980-01-01",
    "date:inception_upper": "1980-01-01",
    "iso:country": "GB",
    "wof:name": "MK41 0PU",
    "wof:placetype": "postalcode"
  },
  "geometry": {"coordinates":[-0.426459,52.152385],"type":"Point"}
}
