{
  "type": "Feature",
  "properties": {
    "iso:country":"GB",
    "wof:name":"W2 2SW",
    "wof:placetype":"postalcode"
},
  "geometry": {"coordinates":[-0.17291031390706,51.51399165184196],"type":"Point"}
}