{
  "type": "Feature",
  "properties": {
    "date:inception_lower": "1980-01-01",
    "date:inception_upper": "1980-01-01",
    "iso:country": "GB",
    "wof:name": "WS12 4DR",
    "wof:placetype": "postalcode"
  },
  "geometry": {"coordinates":[-1.993913,52.719826],"type":"Point"}
}
