{
  "type": "Feature",
  "properties": {
    "date:inception_lower": "2019-11-01",
    "date:inception_upper": "2019-11-01",
    "iso:country": "GB",
    "wof:name": "SO21 1GJ",
    "wof:placetype": "postalcode"
  },
  "geometry": {"coordinates":[-1.293388,51.053873],"type":"Point"}
}
