{
  "type": "Feature",
  "properties": {
    "iso:country": "GB",
    "wof:name": "OL2 5BP",
    "wof:placetype": "postalcode"
  },
  "geometry": {"coordinates":[-2.131187,53.557409],"type":"Point"}
}
