{
  "type": "Feature",
  "properties": {
    "iso:country":"GB",
    "wof:name":"OL2 5BP",
    "wof:placetype":"postalcode"
},
  "geometry": {"coordinates":[-2.13118712114735,53.55740883904145],"type":"Point"}
}