{
  "type": "Feature",
  "properties": {
    "date:inception_lower": "1980-01-01",
    "date:inception_upper": "1980-01-01",
    "iso:country": "GB",
    "wof:name": "OL2 5BP",
    "wof:placetype": "postalcode"
  },
  "geometry": {"coordinates":[-2.131187,53.557409],"type":"Point"}
}
