{
  "type": "Feature",
  "properties": {
    "iso:country": "GB",
    "wof:name": "LE16 9GW",
    "wof:placetype": "postalcode"
  },
  "geometry": {"coordinates":[-0.939929,52.468751],"type":"Point"}
}
