{
  "type": "Feature",
  "properties": {
    "iso:country": "GB",
    "wof:name": "M5 4RZ",
    "wof:placetype": "postalcode"
  },
  "geometry": {"coordinates":[-2.266268,53.481725],"type":"Point"}
}
