{
  "type": "Feature",
  "properties": {
    "date:inception_lower":"2009-07-01",
    "date:inception_upper":"2009-07-31",
    "iso:country":"GB",
    "wof:name":"B95 5LZ",
    "wof:placetype":"postalcode"
},
  "geometry": {"coordinates":[-1.788042,52.29175],"type":"Point"}
}