{
  "type": "Feature",
  "properties": {
    "iso:country":"GB",
    "wof:name":"B95 5LZ",
    "wof:placetype":"postalcode"
},
  "geometry": {"coordinates":[-1.78805109289942,52.2917355824893],"type":"Point"}
}