{
  "type": "Feature",
  "properties": {
    "date:inception_lower": "1980-01-01",
    "date:inception_upper": "1980-01-01",
    "iso:country": "GB",
    "wof:name": "SA3 5TX",
    "wof:placetype": "postalcode"
  },
  "geometry": {"coordinates":[-4.005788,51.582946],"type":"Point"}
}
