{
  "type": "Feature",
  "properties": {
    "iso:country": "GB",
    "wof:name": "CA22 2BE",
    "wof:placetype": "postalcode"
  },
  "geometry": {"coordinates":[-3.532147,54.481599],"type":"Point"}
}
