{
  "type": "Feature",
  "properties": {
    "iso:country":"GB",
    "wof:name":"TN4 8DF",
    "wof:placetype":"postalcode"
},
  "geometry": {"coordinates":[0.23933150728574,51.12205954885439],"type":"Point"}
}