{
  "type": "Feature",
  "properties": {
    "date:inception_lower":"2013-07-01",
    "date:inception_upper":"2013-07-31",
    "iso:country":"GB",
    "wof:name":"TN4 8DF",
    "wof:placetype":"postalcode"
},
  "geometry": {"coordinates":[0.239332,51.12206],"type":"Point"}
}