{
  "type": "Feature",
  "properties": {
    "date:inception_lower": "1990-02-01",
    "date:inception_upper": "1990-02-01",
    "iso:country": "GB",
    "wof:name": "WR9 8AE",
    "wof:placetype": "postalcode"
  },
  "geometry": {"coordinates":[-2.15816,52.256451],"type":"Point"}
}
