{
  "type": "Feature",
  "properties": {
    "iso:country":"GB",
    "wof:name":"WR9 8AE",
    "wof:placetype":"postalcode"
},
  "geometry": {"coordinates":[-2.15816007270295,52.25645126308759],"type":"Point"}
}