{
  "type": "Feature",
  "properties": {
    "iso:country":"GB",
    "wof:name":"CO6 1EG",
    "wof:placetype":"postalcode"
},
  "geometry": {"coordinates":[0.78478206073765,51.88354686716993],"type":"Point"}
}