{
  "type": "Feature",
  "properties": {
    "iso:country":"GB",
    "wof:name":"CR8 2FA",
    "wof:placetype":"postalcode"
},
  "geometry": {"coordinates":[-0.12477915947004,51.34379265390016],"type":"Point"}
}