{
  "type": "Feature",
  "properties": {
    "date:inception_lower": "1995-07-01",
    "date:inception_upper": "1995-07-01",
    "iso:country": "GB",
    "wof:name": "CR8 2FA",
    "wof:placetype": "postalcode"
  },
  "geometry": {"coordinates":[-0.124779,51.343793],"type":"Point"}
}
