{
  "type": "Feature",
  "properties": {
    "iso:country": "GB",
    "wof:name": "CR8 2FA",
    "wof:placetype": "postalcode"
  },
  "geometry": {"coordinates":[-0.124779,51.343793],"type":"Point"}
}
