{
  "type": "Feature",
  "properties": {
    "date:inception_lower":"1999-06-01",
    "date:inception_upper":"1999-06-30",
    "iso:country":"GB",
    "wof:name":"CF23 9UW",
    "wof:placetype":"postalcode"
},
  "geometry": {"coordinates":[-3.147169,51.516428],"type":"Point"}
}