{
  "type": "Feature",
  "properties": {
    "iso:country":"GB",
    "wof:name":"RG1 3JB",
    "wof:placetype":"postalcode"
},
  "geometry": {"coordinates":[-0.95126530491701,51.45378242463613],"type":"Point"}
}