{
  "type": "Feature",
  "properties": {
    "date:inception_lower": "2002-11-01",
    "date:inception_upper": "2002-11-01",
    "iso:country": "GB",
    "wof:name": "RG1 3JB",
    "wof:placetype": "postalcode"
  },
  "geometry": {"coordinates":[-0.951265,51.453782],"type":"Point"}
}
