{
  "type": "Feature",
  "properties": {
    "iso:country":"GB",
    "wof:name":"S62 7FD",
    "wof:placetype":"postalcode"
},
  "geometry": {"coordinates":[-1.35476855572665,53.47344303892351],"type":"Point"}
}