{
  "type": "Feature",
  "properties": {
    "date:inception_lower":"1997-12-01",
    "date:inception_upper":"1997-12-31",
    "iso:country":"GB",
    "wof:name":"S62 7FD",
    "wof:placetype":"postalcode"
},
  "geometry": {"coordinates":[-1.354769,53.473443],"type":"Point"}
}