{
  "type": "Feature",
  "properties": {
    "iso:country": "GB",
    "wof:name": "NP19 7DT",
    "wof:placetype": "postalcode"
  },
  "geometry": {"coordinates":[-2.982413,51.597447],"type":"Point"}
}
