{
  "type": "Feature",
  "properties": {
    "iso:country":"GB",
    "wof:name":"NW9 6RR",
    "wof:placetype":"postalcode"
},
  "geometry": {"coordinates":[-0.25075830387577,51.58748579323125],"type":"Point"}
}