{
  "type": "Feature",
  "properties": {
    "iso:country": "GB",
    "wof:name": "NW9 6RR",
    "wof:placetype": "postalcode"
  },
  "geometry": {"coordinates":[-0.250894,51.587437],"type":"Point"}
}
