{
  "type": "Feature",
  "properties": {
    "iso:country":"GB",
    "wof:name":"PL11 2WW",
    "wof:placetype":"postalcode"
},
  "geometry": {"coordinates":[-4.22387340577317,50.37572789848404],"type":"Point"}
}