{
  "type": "Feature",
  "properties": {
    "date:inception_lower": "2007-06-01",
    "date:inception_upper": "2007-06-01",
    "iso:country": "GB",
    "wof:name": "PL11 2WW",
    "wof:placetype": "postalcode"
  },
  "geometry": {"coordinates":[-4.223873,50.375728],"type":"Point"}
}
