{
  "type": "Feature",
  "properties": {
    "iso:country":"GB",
    "wof:name":"SN8 3LJ",
    "wof:placetype":"postalcode"
},
  "geometry": {"coordinates":[-1.62686467710129,51.38461352647781],"type":"Point"}
}