{
  "type": "Feature",
  "properties": {
    "iso:country": "GB",
    "wof:name": "SY12 0DX",
    "wof:placetype": "postalcode"
  },
  "geometry": {"coordinates":[-2.899785,52.904486],"type":"Point"}
}
