{
  "type": "Feature",
  "properties": {
    "date:inception_lower": "1980-01-01",
    "date:inception_upper": "1980-01-01",
    "iso:country": "GB",
    "wof:name": "SY12 0DX",
    "wof:placetype": "postalcode"
  },
  "geometry": {"coordinates":[-2.899785,52.904486],"type":"Point"}
}
