{
  "type": "Feature",
  "properties": {
    "date:inception_lower": "2002-12-01",
    "date:inception_upper": "2002-12-01",
    "iso:country": "GB",
    "wof:name": "G45 0JA",
    "wof:placetype": "postalcode"
  },
  "geometry": {"coordinates":[-4.218592,55.803197],"type":"Point"}
}
