{
  "type": "Feature",
  "properties": {
    "iso:country":"GB",
    "wof:name":"HA7 4TZ",
    "wof:placetype":"postalcode"
},
  "geometry": {"coordinates":[-0.30285996583336,51.61485868179913],"type":"Point"}
}