{
  "type": "Feature",
  "properties": {
    "iso:country":"GB",
    "wof:name":"PE33 9PT",
    "wof:placetype":"postalcode"
},
  "geometry": {"coordinates":[0.5594122461581,52.57021475384142],"type":"Point"}
}