{
  "type": "Feature",
  "properties": {
    "date:inception_lower": "2011-06-01",
    "date:inception_upper": "2011-06-01",
    "iso:country": "GB",
    "wof:name": "S2 4RD",
    "wof:placetype": "postalcode"
  },
  "geometry": {"coordinates":[-1.472746,53.370284],"type":"Point"}
}
