{
  "type": "Feature",
  "properties": {
    "iso:country":"GB",
    "wof:name":"S2 4RD",
    "wof:placetype":"postalcode"
},
  "geometry": {"coordinates":[-1.47252981496204,53.37078612765599],"type":"Point"}
}