{
  "type": "Feature",
  "properties": {
    "iso:country":"GB",
    "wof:name":"WF8 2LA",
    "wof:placetype":"postalcode"
},
  "geometry": {"coordinates":[-1.28221047766508,53.70086943302228],"type":"Point"}
}