{
  "type": "Feature",
  "properties": {
    "iso:country": "GB",
    "wof:name": "WF8 2LA",
    "wof:placetype": "postalcode"
  },
  "geometry": {"coordinates":[-1.28221,53.700869],"type":"Point"}
}
