{
  "type": "Feature",
  "properties": {
    "date:inception_lower": "2003-03-01",
    "date:inception_upper": "2003-03-01",
    "iso:country": "GB",
    "wof:name": "SW1X 7GG",
    "wof:placetype": "postalcode"
  },
  "geometry": {"coordinates":[-0.147755,51.498508],"type":"Point"}
}
