{
  "type": "Feature",
  "properties": {
    "iso:country":"GB",
    "wof:name":"SW1X 7GG",
    "wof:placetype":"postalcode"
},
  "geometry": {"coordinates":[-0.14778109654618,51.49857102751448],"type":"Point"}
}