{
  "type": "Feature",
  "properties": {
    "iso:country":"GB",
    "wof:name":"EH11 2EN",
    "wof:placetype":"postalcode"
},
  "geometry": {"coordinates":[-3.22476681357091,55.94151149327977],"type":"Point"}
}