{
  "type": "Feature",
  "properties": {
    "iso:country":"GB",
    "wof:name":"L7 0EJ",
    "wof:placetype":"postalcode"
},
  "geometry": {"coordinates":[-2.94562904470567,53.40955175157739],"type":"Point"}
}