{
  "type": "Feature",
  "properties": {
    "iso:country": "GB",
    "wof:name": "L7 0EJ",
    "wof:placetype": "postalcode"
  },
  "geometry": {"coordinates":[-2.945629,53.409552],"type":"Point"}
}
