{
  "type": "Feature",
  "properties": {
    "date:inception_lower": "2017-05-01",
    "date:inception_upper": "2017-05-01",
    "iso:country": "GB",
    "wof:name": "TR16 4FF",
    "wof:placetype": "postalcode"
  },
  "geometry": {"coordinates":[-5.21165,50.247717],"type":"Point"}
}
