{
  "type": "Feature",
  "properties": {
    "iso:country": "GB",
    "wof:name": "PA15 2WE",
    "wof:placetype": "postalcode"
  },
  "geometry": {"coordinates":[-4.708615,55.939106],"type":"Point"}
}
