{
  "type": "Feature",
  "properties": {
    "date:inception_lower": "2009-01-01",
    "date:inception_upper": "2009-01-01",
    "iso:country": "GB",
    "wof:name": "PA15 2WE",
    "wof:placetype": "postalcode"
  },
  "geometry": {"coordinates":[-4.708615,55.939106],"type":"Point"}
}
