{
  "type": "Feature",
  "properties": {
    "iso:country":"GB",
    "wof:name":"LL12 9LU",
    "wof:placetype":"postalcode"
},
  "geometry": {"coordinates":[-3.04433517934908,53.11257117889377],"type":"Point"}
}