{
  "type": "Feature",
  "properties": {
    "date:inception_lower": "1980-01-01",
    "date:inception_upper": "1980-01-01",
    "iso:country": "GB",
    "wof:name": "EX39 2HJ",
    "wof:placetype": "postalcode"
  },
  "geometry": {"coordinates":[-4.204911,51.018375],"type":"Point"}
}
