{
  "type": "Feature",
  "properties": {
    "iso:country": "GB",
    "wof:name": "S20 5JX",
    "wof:placetype": "postalcode"
  },
  "geometry": {"coordinates":[-1.373566,53.331396],"type":"Point"}
}
