{
  "type": "Feature",
  "properties": {
    "iso:country":"GB",
    "wof:name":"S20 5JX",
    "wof:placetype":"postalcode"
},
  "geometry": {"coordinates":[-1.37356577451903,53.33139558479655],"type":"Point"}
}