{
  "type": "Feature",
  "properties": {
    "iso:country":"GB",
    "wof:name":"BN7 2NR",
    "wof:placetype":"postalcode"
},
  "geometry": {"coordinates":[0.01208972010191,50.8737379829152],"type":"Point"}
}