{
  "type": "Feature",
  "properties": {
    "date:inception_lower":"1980-01-01",
    "date:inception_upper":"1980-01-31",
    "iso:country":"GB",
    "wof:name":"BN7 2NR",
    "wof:placetype":"postalcode"
},
  "geometry": {"coordinates":[0.01209,50.873738],"type":"Point"}
}