{
  "type": "Feature",
  "properties": {
    "iso:country": "GB",
    "wof:name": "TN9 1NE",
    "wof:placetype": "postalcode"
  },
  "geometry": {"coordinates":[0.278577,51.204257],"type":"Point"}
}
