{
  "type": "Feature",
  "properties": {
    "date:inception_lower":"1980-01-01",
    "date:inception_upper":"1980-01-31",
    "iso:country":"GB",
    "wof:name":"TN9 1NE",
    "wof:placetype":"postalcode"
},
  "geometry": {"coordinates":[0.278577,51.204257],"type":"Point"}
}