{
  "type": "Feature",
  "properties": {
    "iso:country":"GB",
    "wof:name":"TN9 1NE",
    "wof:placetype":"postalcode"
},
  "geometry": {"coordinates":[0.27857697062534,51.20425721152201],"type":"Point"}
}