{
  "type": "Feature",
  "properties": {
    "iso:country": "GB",
    "wof:name": "SN25 2DY",
    "wof:placetype": "postalcode"
  },
  "geometry": {"coordinates":[-1.812265,51.60952],"type":"Point"}
}
