{
  "type": "Feature",
  "properties": {
    "date:inception_lower":"2000-06-01",
    "date:inception_upper":"2000-06-30",
    "iso:country":"GB",
    "wof:name":"SN25 2DY",
    "wof:placetype":"postalcode"
},
  "geometry": {"coordinates":[-1.812265,51.60952],"type":"Point"}
}