{
  "type": "Feature",
  "properties": {
    "iso:country":"GB",
    "wof:name":"M34 5LE",
    "wof:placetype":"postalcode"
},
  "geometry": {"coordinates":[-2.12121679602609,53.47050164717716],"type":"Point"}
}