{
  "type": "Feature",
  "properties": {
    "iso:country":"GB",
    "wof:name":"S75 1DB",
    "wof:placetype":"postalcode"
},
  "geometry": {"coordinates":[-1.48278109601111,53.56163118273032],"type":"Point"}
}