{
  "type": "Feature",
  "properties": {
    "iso:country":"GB",
    "wof:name":"B62 9QJ",
    "wof:placetype":"postalcode"
},
  "geometry": {"coordinates":[-2.02059614598272,52.47311904959307],"type":"Point"}
}