{
  "type": "Feature",
  "properties": {
    "iso:country":"GB",
    "wof:name":"NR34 9DR",
    "wof:placetype":"postalcode"
},
  "geometry": {"coordinates":[1.56863404853411,52.46027364730571],"type":"Point"}
}