{
  "type": "Feature",
  "properties": {
    "iso:country":"GB",
    "wof:name":"SK13 1PP",
    "wof:placetype":"postalcode"
},
  "geometry": {"coordinates":[-1.9790563783271,53.46055744804296],"type":"Point"}
}