{
  "type": "Feature",
  "properties": {
    "iso:country": "GB",
    "wof:name": "SK13 1PP",
    "wof:placetype": "postalcode"
  },
  "geometry": {"coordinates":[-1.979056,53.460557],"type":"Point"}
}
