{
  "type": "Feature",
  "properties": {
    "date:inception_lower": "2019-06-01",
    "date:inception_upper": "2019-06-01",
    "iso:country": "GB",
    "wof:name": "PE15 0WJ",
    "wof:placetype": "postalcode"
  },
  "geometry": {"coordinates":[0.059125,52.49016],"type":"Point"}
}
