{
  "type": "Feature",
  "properties": {
    "iso:country":"GB",
    "wof:name":"B69 4TE",
    "wof:placetype":"postalcode"
},
  "geometry": {"coordinates":[-2.01586088847117,52.48724301320284],"type":"Point"}
}