{
  "type": "Feature",
  "properties": {
    "iso:country":"GB",
    "wof:name":"KY16 9PN",
    "wof:placetype":"postalcode"
},
  "geometry": {"coordinates":[-2.78934382752996,56.34063549882504],"type":"Point"}
}