{
  "type": "Feature",
  "properties": {
    "date:inception_lower": "2002-06-01",
    "date:inception_upper": "2002-06-01",
    "iso:country": "GB",
    "wof:name": "CT1 1GZ",
    "wof:placetype": "postalcode"
  },
  "geometry": {"coordinates":[1.084457,51.282381],"type":"Point"}
}
