{
  "type": "Feature",
  "properties": {
    "iso:country": "GB",
    "wof:name": "EC2A 4HU",
    "wof:placetype": "postalcode"
  },
  "geometry": {"coordinates":[-0.082252,51.523362],"type":"Point"}
}
