{
  "type": "Feature",
  "properties": {
    "iso:country":"GB",
    "wof:name":"EC2A 4HU",
    "wof:placetype":"postalcode"
},
  "geometry": {"coordinates":[-0.08225251083479,51.52336242155049],"type":"Point"}
}