{
  "type": "Feature",
  "properties": {
    "date:inception_lower": "1998-12-01",
    "date:inception_upper": "1998-12-01",
    "iso:country": "GB",
    "wof:name": "CO10 2AG",
    "wof:placetype": "postalcode"
  },
  "geometry": {"coordinates":[0.727416,52.036359],"type":"Point"}
}
