{
  "type": "Feature",
  "properties": {
    "iso:country":"GB",
    "wof:name":"SA20 0UF",
    "wof:placetype":"postalcode"
},
  "geometry": {"coordinates":[-3.80735897992856,52.0542271440776],"type":"Point"}
}