{
  "type": "Feature",
  "properties": {
    "iso:country": "GB",
    "wof:name": "TS26 0LN",
    "wof:placetype": "postalcode"
  },
  "geometry": {"coordinates":[-1.244318,54.69063],"type":"Point"}
}
