{
  "type": "Feature",
  "properties": {
    "iso:country": "GB",
    "wof:name": "DE73 6UD",
    "wof:placetype": "postalcode"
  },
  "geometry": {"coordinates":[-1.437574,52.864306],"type":"Point"}
}
