{
  "type": "Feature",
  "properties": {
    "iso:country":"GB",
    "wof:name":"DE73 6UD",
    "wof:placetype":"postalcode"
},
  "geometry": {"coordinates":[-1.4375737763291,52.86430622243617],"type":"Point"}
}