{
  "type": "Feature",
  "properties": {
    "iso:country":"GB",
    "wof:name":"NW8 7AF",
    "wof:placetype":"postalcode"
},
  "geometry": {"coordinates":[-0.16748114589571,51.53291701789822],"type":"Point"}
}