{
  "type": "Feature",
  "properties": {
    "date:inception_lower": "2021-06-01",
    "date:inception_upper": "2021-06-01",
    "iso:country": "GB",
    "wof:name": "DA11 7FP",
    "wof:placetype": "postalcode"
  },
  "geometry": {"coordinates":[0.358638,51.42059],"type":"Point"}
}
