{
  "type": "Feature",
  "properties": {
    "date:inception_lower": "1980-01-01",
    "date:inception_upper": "1980-01-01",
    "iso:country": "GB",
    "wof:name": "SG8 7HF",
    "wof:placetype": "postalcode"
  },
  "geometry": {"coordinates":[-0.014755,52.0482],"type":"Point"}
}
