{
  "type": "Feature",
  "properties": {
    "iso:country": "GB",
    "wof:name": "SG8 7HF",
    "wof:placetype": "postalcode"
  },
  "geometry": {"coordinates":[-0.014755,52.0482],"type":"Point"}
}
