{
  "type": "Feature",
  "properties": {
    "iso:country":"GB",
    "wof:name":"LL18 5AB",
    "wof:placetype":"postalcode"
},
  "geometry": {"coordinates":[-3.46638110711855,53.29009757520589],"type":"Point"}
}