{
  "type": "Feature",
  "properties": {
    "iso:country":"GB",
    "wof:name":"PL13 2JD",
    "wof:placetype":"postalcode"
},
  "geometry": {"coordinates":[-4.50538320233692,50.34816178404157],"type":"Point"}
}