{
  "type": "Feature",
  "properties": {
    "iso:country": "GB",
    "wof:name": "PL13 2JD",
    "wof:placetype": "postalcode"
  },
  "geometry": {"coordinates":[-4.505244,50.34799],"type":"Point"}
}
