{
  "type": "Feature",
  "properties": {
    "iso:country":"GB",
    "wof:name":"SO31 7BS",
    "wof:placetype":"postalcode"
},
  "geometry": {"coordinates":[-1.28898332795961,50.86591046738682],"type":"Point"}
}