{
  "type": "Feature",
  "properties": {
    "iso:country":"GB",
    "wof:name":"SE25 5QE",
    "wof:placetype":"postalcode"
},
  "geometry": {"coordinates":[-0.08873601421381,51.39146523497512],"type":"Point"}
}