{
  "type": "Feature",
  "properties": {
    "iso:country": "GB",
    "wof:name": "SA4 3XP",
    "wof:placetype": "postalcode"
  },
  "geometry": {"coordinates":[-4.100657,51.64089],"type":"Point"}
}
