{
  "type": "Feature",
  "properties": {
    "iso:country":"GB",
    "wof:name":"SA4 3XP",
    "wof:placetype":"postalcode"
},
  "geometry": {"coordinates":[-4.10053466211281,51.6408859996029],"type":"Point"}
}