{
  "type": "Feature",
  "properties": {
    "date:inception_lower": "2019-01-01",
    "date:inception_upper": "2019-01-01",
    "iso:country": "GB",
    "wof:name": "E15 2ZG",
    "wof:placetype": "postalcode"
  },
  "geometry": {"coordinates":[-0.013046,51.531628],"type":"Point"}
}
