{
  "type": "Feature",
  "properties": {
    "date:inception_lower": "1992-08-01",
    "date:inception_upper": "1992-08-01",
    "iso:country": "GB",
    "wof:name": "DE21 4EQ",
    "wof:placetype": "postalcode"
  },
  "geometry": {"coordinates":[-1.453437,52.936511],"type":"Point"}
}
