{
  "type": "Feature",
  "properties": {
    "iso:country": "GB",
    "wof:name": "RH14 9PX",
    "wof:placetype": "postalcode"
  },
  "geometry": {"coordinates":[-0.449719,51.022857],"type":"Point"}
}
