{
  "type": "Feature",
  "properties": {
    "iso:country":"GB",
    "wof:name":"RH5 5HF",
    "wof:placetype":"postalcode"
},
  "geometry": {"coordinates":[-0.31314955954665,51.13544526075722],"type":"Point"}
}