{
  "type": "Feature",
  "properties": {
    "iso:country":"GB",
    "wof:name":"CW9 8WT",
    "wof:placetype":"postalcode"
},
  "geometry": {"coordinates":[-2.52228433729979,53.24440605945436],"type":"Point"}
}