{
  "type": "Feature",
  "properties": {
    "date:inception_lower": "1999-06-01",
    "date:inception_upper": "1999-06-01",
    "iso:country": "GB",
    "wof:name": "CW9 8WT",
    "wof:placetype": "postalcode"
  },
  "geometry": {"coordinates":[-2.522284,53.244406],"type":"Point"}
}
