{
  "type": "Feature",
  "properties": {
    "iso:country":"GB",
    "wof:name":"CM6 1WZ",
    "wof:placetype":"postalcode"
},
  "geometry": {"coordinates":[0.35019858340664,51.87505714922717],"type":"Point"}
}