{
  "type": "Feature",
  "properties": {
    "date:inception_lower": "1980-01-01",
    "date:inception_upper": "1980-01-01",
    "iso:country": "GB",
    "wof:name": "ME12 2EE",
    "wof:placetype": "postalcode"
  },
  "geometry": {"coordinates":[0.792789,51.423204],"type":"Point"}
}
