{
  "type": "Feature",
  "properties": {
    "iso:country":"GB",
    "wof:name":"ME12 2EE",
    "wof:placetype":"postalcode"
},
  "geometry": {"coordinates":[0.79278865589332,51.42320428671965],"type":"Point"}
}