{
  "type": "Feature",
  "properties": {
    "iso:country": "GB",
    "wof:name": "ME12 2EE",
    "wof:placetype": "postalcode"
  },
  "geometry": {"coordinates":[0.792789,51.423204],"type":"Point"}
}
