{
  "type": "Feature",
  "properties": {
    "iso:country":"GB",
    "wof:name":"DT7 3TP",
    "wof:placetype":"postalcode"
},
  "geometry": {"coordinates":[-2.94953750274107,50.73325681708533],"type":"Point"}
}