{
  "type": "Feature",
  "properties": {
    "iso:country":"GB",
    "wof:name":"HX2 7NW",
    "wof:placetype":"postalcode"
},
  "geometry": {"coordinates":[-1.90041355945028,53.7154973785061],"type":"Point"}
}