{
  "type": "Feature",
  "properties": {
    "iso:country": "GB",
    "wof:name": "TF11 8DU",
    "wof:placetype": "postalcode"
  },
  "geometry": {"coordinates":[-2.367664,52.667446],"type":"Point"}
}
