{
  "type": "Feature",
  "properties": {
    "iso:country":"GB",
    "wof:name":"DT2 7SB",
    "wof:placetype":"postalcode"
},
  "geometry": {"coordinates":[-2.32132150578319,50.78363216316254],"type":"Point"}
}