{
  "type": "Feature",
  "properties": {
    "iso:country": "GB",
    "wof:name": "S17 3LW",
    "wof:placetype": "postalcode"
  },
  "geometry": {"coordinates":[-1.520057,53.323517],"type":"Point"}
}
