{
  "type": "Feature",
  "properties": {
    "date:inception_lower": "1980-01-01",
    "date:inception_upper": "1980-01-01",
    "iso:country": "GB",
    "wof:name": "SS7 3TL",
    "wof:placetype": "postalcode"
  },
  "geometry": {"coordinates":[0.596376,51.57464],"type":"Point"}
}
