{
  "type": "Feature",
  "properties": {
    "iso:country": "GB",
    "wof:name": "SS7 3TL",
    "wof:placetype": "postalcode"
  },
  "geometry": {"coordinates":[0.596376,51.57464],"type":"Point"}
}
