{
  "type": "Feature",
  "properties": {
    "iso:country": "GB",
    "wof:name": "PR4 0FX",
    "wof:placetype": "postalcode"
  },
  "geometry": {"coordinates":[-2.768109,53.795774],"type":"Point"}
}
