{
  "type": "Feature",
  "properties": {
    "date:inception_lower":"1980-01-01",
    "date:inception_upper":"1980-01-31",
    "iso:country":"GB",
    "wof:name":"CB9 8EN",
    "wof:placetype":"postalcode"
},
  "geometry": {"coordinates":[0.446407,52.075737],"type":"Point"}
}