{
  "type": "Feature",
  "properties": {
    "iso:country":"GB",
    "wof:name":"BD8 0DG",
    "wof:placetype":"postalcode"
},
  "geometry": {"coordinates":[-1.80989667190347,53.80259001349361],"type":"Point"}
}