{
  "type": "Feature",
  "properties": {
    "iso:country":"GB",
    "wof:name":"B91 2BL",
    "wof:placetype":"postalcode"
},
  "geometry": {"coordinates":[-1.77848301378809,52.41990880699171],"type":"Point"}
}