{
  "type": "Feature",
  "properties": {
    "date:inception_lower": "1980-01-01",
    "date:inception_upper": "1980-01-01",
    "iso:country": "GB",
    "wof:name": "G64 1TH",
    "wof:placetype": "postalcode"
  },
  "geometry": {"coordinates":[-4.215802,55.901462],"type":"Point"}
}
