{
  "type": "Feature",
  "properties": {
    "iso:country":"GB",
    "wof:name":"TF3 3BH",
    "wof:placetype":"postalcode"
},
  "geometry": {"coordinates":[-2.42228059433094,52.67717368182446],"type":"Point"}
}