{
  "type": "Feature",
  "properties": {
    "iso:country":"GB",
    "wof:name":"HU13 0NR",
    "wof:placetype":"postalcode"
},
  "geometry": {"coordinates":[-0.44935087988384,53.72825801737611],"type":"Point"}
}