{
  "type": "Feature",
  "properties": {
    "iso:country":"GB",
    "wof:name":"ML11 8DB",
    "wof:placetype":"postalcode"
},
  "geometry": {"coordinates":[-3.6887114294668,55.76668606401288],"type":"Point"}
}