{
  "type": "Feature",
  "properties": {
    "iso:country":"GB",
    "wof:name":"WA11 8JA",
    "wof:placetype":"postalcode"
},
  "geometry": {"coordinates":[-2.79021760705815,53.50789456727261],"type":"Point"}
}