{
  "type": "Feature",
  "properties": {
    "date:inception_lower": "2018-12-01",
    "date:inception_upper": "2018-12-01",
    "iso:country": "GB",
    "wof:name": "RM14 3BN",
    "wof:placetype": "postalcode"
  },
  "geometry": {"coordinates":[0.349489,51.547795],"type":"Point"}
}
