{
  "type": "Feature",
  "properties": {
    "iso:country":"GB",
    "wof:name":"ME2 2YN",
    "wof:placetype":"postalcode"
},
  "geometry": {"coordinates":[0.47618717815825,51.39298267212558],"type":"Point"}
}