{
  "type": "Feature",
  "properties": {
    "date:inception_lower": "1980-01-01",
    "date:inception_upper": "1980-01-01",
    "iso:country": "GB",
    "wof:name": "NN7 3AP",
    "wof:placetype": "postalcode"
  },
  "geometry": {"coordinates":[-0.929085,52.195646],"type":"Point"}
}
