{
  "type": "Feature",
  "properties": {
    "iso:country":"GB",
    "wof:name":"NN7 3AP",
    "wof:placetype":"postalcode"
},
  "geometry": {"coordinates":[-0.92908468361031,52.19564564476201],"type":"Point"}
}