{
  "type": "Feature",
  "properties": {
    "date:inception_lower":"1986-07-01",
    "date:inception_upper":"1986-07-31",
    "iso:country":"GB",
    "wof:name":"PL14 3TB",
    "wof:placetype":"postalcode"
},
  "geometry": {"coordinates":[-4.465255,50.456696],"type":"Point"}
}