{
  "type": "Feature",
  "properties": {
    "date:inception_lower": "1986-04-01",
    "date:inception_upper": "1986-04-01",
    "iso:country": "GB",
    "wof:name": "B16 0ED",
    "wof:placetype": "postalcode"
  },
  "geometry": {"coordinates":[-1.93453,52.484997],"type":"Point"}
}
