{
  "type": "Feature",
  "properties": {
    "iso:country":"GB",
    "wof:name":"B16 0ED",
    "wof:placetype":"postalcode"
},
  "geometry": {"coordinates":[-1.93452965289834,52.48499663745655],"type":"Point"}
}