{
  "type": "Feature",
  "properties": {
    "iso:country":"GB",
    "wof:name":"CO15 4EF",
    "wof:placetype":"postalcode"
},
  "geometry": {"coordinates":[1.15015293044041,51.80990056580607],"type":"Point"}
}