{
  "type": "Feature",
  "properties": {
    "iso:country": "GB",
    "wof:name": "MK43 0EX",
    "wof:placetype": "postalcode"
  },
  "geometry": {"coordinates":[-0.595786,52.074636],"type":"Point"}
}
