{
  "type": "Feature",
  "properties": {
    "iso:country":"GB",
    "wof:name":"MK43 0EX",
    "wof:placetype":"postalcode"
},
  "geometry": {"coordinates":[-0.59578607619637,52.07463601822682],"type":"Point"}
}