{
  "type": "Feature",
  "properties": {
    "iso:country":"GB",
    "wof:name":"BD15 7EE",
    "wof:placetype":"postalcode"
},
  "geometry": {"coordinates":[-1.82953463359743,53.8049204059046],"type":"Point"}
}