{
  "type": "Feature",
  "properties": {
    "date:inception_lower": "2005-06-01",
    "date:inception_upper": "2005-06-01",
    "iso:country": "GB",
    "wof:name": "RH2 9BB",
    "wof:placetype": "postalcode"
  },
  "geometry": {"coordinates":[-0.217244,51.239131],"type":"Point"}
}
