{
  "type": "Feature",
  "properties": {
    "iso:country":"GB",
    "wof:name":"RH2 9BB",
    "wof:placetype":"postalcode"
},
  "geometry": {"coordinates":[-0.21724406450827,51.23913128160548],"type":"Point"}
}