{
  "type": "Feature",
  "properties": {
    "date:inception_lower": "1980-01-01",
    "date:inception_upper": "1980-01-01",
    "iso:country": "GB",
    "wof:name": "CV23 0QW",
    "wof:placetype": "postalcode"
  },
  "geometry": {"coordinates":[-1.266396,52.440371],"type":"Point"}
}
