{
  "type": "Feature",
  "properties": {
    "iso:country":"GB",
    "wof:name":"CV23 0QW",
    "wof:placetype":"postalcode"
},
  "geometry": {"coordinates":[-1.26279281747128,52.44098717764133],"type":"Point"}
}