{
  "type": "Feature",
  "properties": {
    "iso:country": "GB",
    "wof:name": "CV23 0QW",
    "wof:placetype": "postalcode"
  },
  "geometry": {"coordinates":[-1.262781,52.441004],"type":"Point"}
}
