{
  "type": "Feature",
  "properties": {
    "iso:country": "GB",
    "wof:name": "CO10 7FR",
    "wof:placetype": "postalcode"
  },
  "geometry": {"coordinates":[0.71531,52.034148],"type":"Point"}
}
