{
  "type": "Feature",
  "properties": {
    "iso:country": "GB",
    "wof:name": "LL57 2TZ",
    "wof:placetype": "postalcode"
  },
  "geometry": {"coordinates":[-4.138078,53.221603],"type":"Point"}
}
