{
  "type": "Feature",
  "properties": {
    "iso:country": "GB",
    "wof:name": "TQ1 3HJ",
    "wof:placetype": "postalcode"
  },
  "geometry": {"coordinates":[-3.528954,50.475351],"type":"Point"}
}
