{
  "type": "Feature",
  "properties": {
    "iso:country": "GB",
    "wof:name": "SO19 9DN",
    "wof:placetype": "postalcode"
  },
  "geometry": {"coordinates":[-1.371182,50.894204],"type":"Point"}
}
