{
  "type": "Feature",
  "properties": {
    "date:inception_lower":"2005-09-01",
    "date:inception_upper":"2005-09-30",
    "iso:country":"GB",
    "wof:name":"TR9 6HB",
    "wof:placetype":"postalcode"
},
  "geometry": {"coordinates":[-4.918269,50.399892],"type":"Point"}
}