{
  "type": "Feature",
  "properties": {
    "date:inception_lower": "1980-01-01",
    "date:inception_upper": "1980-01-01",
    "iso:country": "GB",
    "wof:name": "EN8 7EU",
    "wof:placetype": "postalcode"
  },
  "geometry": {"coordinates":[-0.026484,51.693097],"type":"Point"}
}
