{
  "type": "Feature",
  "properties": {
    "iso:country":"GB",
    "wof:name":"EN8 7EU",
    "wof:placetype":"postalcode"
},
  "geometry": {"coordinates":[-0.02648368284544,51.69309724433488],"type":"Point"}
}