{
  "type": "Feature",
  "properties": {
    "date:inception_lower": "1980-01-01",
    "date:inception_upper": "1980-01-01",
    "iso:country": "GB",
    "wof:name": "L37 1NL",
    "wof:placetype": "postalcode"
  },
  "geometry": {"coordinates":[-3.078375,53.561004],"type":"Point"}
}
