{
  "type": "Feature",
  "properties": {
    "iso:country": "GB",
    "wof:name": "L37 1NL",
    "wof:placetype": "postalcode"
  },
  "geometry": {"coordinates":[-3.078375,53.561004],"type":"Point"}
}
