{
  "type": "Feature",
  "properties": {
    "date:inception_lower":"1980-01-01",
    "date:inception_upper":"1980-01-31",
    "iso:country":"GB",
    "wof:name":"IG11 7LP",
    "wof:placetype":"postalcode"
},
  "geometry": {"coordinates":[0.077945,51.53281],"type":"Point"}
}