{
  "type": "Feature",
  "properties": {
    "iso:country": "GB",
    "wof:name": "IG11 7LP",
    "wof:placetype": "postalcode"
  },
  "geometry": {"coordinates":[0.077945,51.53281],"type":"Point"}
}
