{
  "type": "Feature",
  "properties": {
    "iso:country":"GB",
    "wof:name":"N14 4QN",
    "wof:placetype":"postalcode"
},
  "geometry": {"coordinates":[-0.138487744654,51.63953312298048],"type":"Point"}
}