{
  "type": "Feature",
  "properties": {
    "date:inception_lower": "1991-09-01",
    "date:inception_upper": "1991-09-01",
    "iso:country": "GB",
    "wof:name": "RG7 3XT",
    "wof:placetype": "postalcode"
  },
  "geometry": {"coordinates":[-1.057834,51.400826],"type":"Point"}
}
