{
  "type": "Feature",
  "properties": {
    "date:inception_lower": "2003-04-01",
    "date:inception_upper": "2003-04-01",
    "iso:country": "GB",
    "wof:name": "EX2 8BS",
    "wof:placetype": "postalcode"
  },
  "geometry": {"coordinates":[-3.535692,50.716738],"type":"Point"}
}
