{
  "type": "Feature",
  "properties": {
    "iso:country":"GB",
    "wof:name":"EX2 8BS",
    "wof:placetype":"postalcode"
},
  "geometry": {"coordinates":[-3.53569225864929,50.71673786651034],"type":"Point"}
}