{
  "type": "Feature",
  "properties": {
    "iso:country":"GB",
    "wof:name":"TN29 9HR",
    "wof:placetype":"postalcode"
},
  "geometry": {"coordinates":[0.91068514419499,50.95031214162633],"type":"Point"}
}