{
  "type": "Feature",
  "properties": {
    "iso:country":"GB",
    "wof:name":"NE38 8QD",
    "wof:placetype":"postalcode"
},
  "geometry": {"coordinates":[-1.50152164513569,54.89370878091988],"type":"Point"}
}