{
  "type": "Feature",
  "properties": {
    "iso:country":"GB",
    "wof:name":"KA7 2UU",
    "wof:placetype":"postalcode"
},
  "geometry": {"coordinates":[-4.63721672760865,55.45504703745451],"type":"Point"}
}