{
  "type": "Feature",
  "properties": {
    "date:inception_lower": "1980-01-01",
    "date:inception_upper": "1980-01-01",
    "iso:country": "GB",
    "wof:name": "B23 5SF",
    "wof:placetype": "postalcode"
  },
  "geometry": {"coordinates":[-1.839685,52.532481],"type":"Point"}
}
