{
  "type": "Feature",
  "properties": {
    "iso:country":"GB",
    "wof:name":"B23 5SF",
    "wof:placetype":"postalcode"
},
  "geometry": {"coordinates":[-1.83968525311143,52.53248102930289],"type":"Point"}
}