{
  "type": "Feature",
  "properties": {
    "iso:country":"GB",
    "wof:name":"CA5 6HF",
    "wof:placetype":"postalcode"
},
  "geometry": {"coordinates":[-3.07186853791648,54.9017277915591],"type":"Point"}
}