{
  "type": "Feature",
  "properties": {
    "date:inception_lower": "1980-01-01",
    "date:inception_upper": "1980-01-01",
    "iso:country": "GB",
    "wof:name": "CA5 6HF",
    "wof:placetype": "postalcode"
  },
  "geometry": {"coordinates":[-3.071823,54.901672],"type":"Point"}
}
