{
  "type": "Feature",
  "properties": {
    "date:inception_lower":"2015-10-01",
    "date:inception_upper":"2015-10-31",
    "iso:country":"GB",
    "wof:name":"GL1 2JN",
    "wof:placetype":"postalcode"
},
  "geometry": {"coordinates":[-2.252052,51.865547],"type":"Point"}
}