{
  "type": "Feature",
  "properties": {
    "iso:country":"GB",
    "wof:name":"GL1 2JN",
    "wof:placetype":"postalcode"
},
  "geometry": {"coordinates":[-2.25205172317294,51.86554654882846],"type":"Point"}
}