{
  "type": "Feature",
  "properties": {
    "iso:country": "GB",
    "wof:name": "S61 3BS",
    "wof:placetype": "postalcode"
  },
  "geometry": {"coordinates":[-1.407052,53.448249],"type":"Point"}
}
