{
  "type": "Feature",
  "properties": {
    "iso:country":"GB",
    "wof:name":"WA11 9LA",
    "wof:placetype":"postalcode"
},
  "geometry": {"coordinates":[-2.72115091924164,53.46212073454044],"type":"Point"}
}