{
  "type": "Feature",
  "properties": {
    "iso:country":"GB",
    "wof:name":"DE22 2XX",
    "wof:placetype":"postalcode"
},
  "geometry": {"coordinates":[-1.48977893210182,52.94465546552536],"type":"Point"}
}