{
  "type": "Feature",
  "properties": {
    "date:inception_lower": "2016-03-01",
    "date:inception_upper": "2016-03-01",
    "iso:country": "GB",
    "wof:name": "CW8 4ZT",
    "wof:placetype": "postalcode"
  },
  "geometry": {"coordinates":[-2.538777,53.26194],"type":"Point"}
}
