{
  "type": "Feature",
  "properties": {
    "date:inception_lower": "1986-04-01",
    "date:inception_upper": "1986-04-01",
    "iso:country": "GB",
    "wof:name": "HU15 1HQ",
    "wof:placetype": "postalcode"
  },
  "geometry": {"coordinates":[-0.568547,53.738748],"type":"Point"}
}
