{
  "type": "Feature",
  "properties": {
    "iso:country":"GB",
    "wof:name":"HU15 1HQ",
    "wof:placetype":"postalcode"
},
  "geometry": {"coordinates":[-0.56854712499528,53.73874796977027],"type":"Point"}
}