{
  "type": "Feature",
  "properties": {
    "iso:country":"GB",
    "wof:name":"BS23 2NJ",
    "wof:placetype":"postalcode"
},
  "geometry": {"coordinates":[-2.97641793740884,51.3539179206776],"type":"Point"}
}