{
  "type": "Feature",
  "properties": {
    "iso:country":"GB",
    "wof:name":"G51 2DH",
    "wof:placetype":"postalcode"
},
  "geometry": {"coordinates":[-4.30427364627212,55.86002226212899],"type":"Point"}
}