{
  "type": "Feature",
  "properties": {
    "iso:country":"GB",
    "wof:name":"SR3 1NT",
    "wof:placetype":"postalcode"
},
  "geometry": {"coordinates":[-1.40153193146421,54.88443292378696],"type":"Point"}
}