{
  "type": "Feature",
  "properties": {
    "date:inception_lower": "2010-12-01",
    "date:inception_upper": "2010-12-01",
    "iso:country": "GB",
    "wof:name": "KY16 9ZW",
    "wof:placetype": "postalcode"
  },
  "geometry": {"coordinates":[-2.923078,56.352065],"type":"Point"}
}
