{
  "type": "Feature",
  "properties": {
    "iso:country": "GB",
    "wof:name": "KY16 9ZW",
    "wof:placetype": "postalcode"
  },
  "geometry": {"coordinates":[-2.923078,56.352065],"type":"Point"}
}
