{
  "type": "Feature",
  "properties": {
    "iso:country":"GB",
    "wof:name":"KY16 9ZW",
    "wof:placetype":"postalcode"
},
  "geometry": {"coordinates":[-2.92307766158698,56.35206512487693],"type":"Point"}
}