{
  "type": "Feature",
  "properties": {
    "iso:country":"GB",
    "wof:name":"B62 8AN",
    "wof:placetype":"postalcode"
},
  "geometry": {"coordinates":[-2.04266502394605,52.45890893187939],"type":"Point"}
}