{
  "type": "Feature",
  "properties": {
    "iso:country":"GB",
    "wof:name":"TS14 8JH",
    "wof:placetype":"postalcode"
},
  "geometry": {"coordinates":[-1.08316629267245,54.52714808035557],"type":"Point"}
}