{
  "type": "Feature",
  "properties": {
    "iso:country": "GB",
    "wof:name": "TS14 8JH",
    "wof:placetype": "postalcode"
  },
  "geometry": {"coordinates":[-1.083166,54.527148],"type":"Point"}
}
