{
  "type": "Feature",
  "properties": {
    "date:inception_lower": "2020-07-01",
    "date:inception_upper": "2020-07-01",
    "iso:country": "GB",
    "wof:name": "PE12 8JW",
    "wof:placetype": "postalcode"
  },
  "geometry": {"coordinates":[0.043049,52.81809],"type":"Point"}
}
