{
  "type": "Feature",
  "properties": {
    "iso:country":"GB",
    "wof:name":"NG24 3FJ",
    "wof:placetype":"postalcode"
},
  "geometry": {"coordinates":[-0.78777927700278,53.0577395611366],"type":"Point"}
}