{
  "type": "Feature",
  "properties": {
    "date:inception_lower": "1980-01-01",
    "date:inception_upper": "1980-01-01",
    "iso:country": "GB",
    "wof:name": "BR2 7JD",
    "wof:placetype": "postalcode"
  },
  "geometry": {"coordinates":[0.006946,51.3792],"type":"Point"}
}
