{
  "type": "Feature",
  "properties": {
    "iso:country":"GB",
    "wof:name":"BR2 7JD",
    "wof:placetype":"postalcode"
},
  "geometry": {"coordinates":[0.00694613310852,51.3791998353307],"type":"Point"}
}