{
  "type": "Feature",
  "properties": {
    "iso:country":"GB",
    "wof:name":"LA11 7ED",
    "wof:placetype":"postalcode"
},
  "geometry": {"coordinates":[-2.92074577104644,54.1855449364107],"type":"Point"}
}