{
  "type": "Feature",
  "properties": {
    "iso:country":"GB",
    "wof:name":"L23 9AB",
    "wof:placetype":"postalcode"
},
  "geometry": {"coordinates":[-3.01462436493789,53.48744035861663],"type":"Point"}
}