{
  "type": "Feature",
  "properties": {
    "iso:country": "GB",
    "wof:name": "L23 9AB",
    "wof:placetype": "postalcode"
  },
  "geometry": {"coordinates":[-3.014624,53.48744],"type":"Point"}
}
