{
  "type": "Feature",
  "properties": {
    "iso:country": "GB",
    "wof:name": "L23 9AB",
    "wof:placetype": "postalcode"
  },
  "geometry": {"coordinates":[-3.015439,53.487548],"type":"Point"}
}
