{
  "type": "Feature",
  "properties": {
    "iso:country":"GB",
    "wof:name":"EX1 3TE",
    "wof:placetype":"postalcode"
},
  "geometry": {"coordinates":[-3.46641121104481,50.74088665253431],"type":"Point"}
}