{
  "type": "Feature",
  "properties": {
    "iso:country":"GB",
    "wof:name":"L17 5AR",
    "wof:placetype":"postalcode"
},
  "geometry": {"coordinates":[-2.93803701806186,53.36944016395786],"type":"Point"}
}