{
  "type": "Feature",
  "properties": {
    "iso:country":"GB",
    "wof:name":"CF81 8NX",
    "wof:placetype":"postalcode"
},
  "geometry": {"coordinates":[-3.22964301245623,51.68775810811989],"type":"Point"}
}