{
  "type": "Feature",
  "properties": {
    "iso:country": "GB",
    "wof:name": "TF11 8QZ",
    "wof:placetype": "postalcode"
  },
  "geometry": {"coordinates":[-2.368914,52.706703],"type":"Point"}
}
