{
  "type": "Feature",
  "properties": {
    "iso:country":"GB",
    "wof:name":"TF11 8QZ",
    "wof:placetype":"postalcode"
},
  "geometry": {"coordinates":[-2.36891439277912,52.70670321501309],"type":"Point"}
}