{
  "type": "Feature",
  "properties": {
    "date:inception_lower":"1980-01-01",
    "date:inception_upper":"1980-01-31",
    "iso:country":"GB",
    "wof:name":"TF11 8QZ",
    "wof:placetype":"postalcode"
},
  "geometry": {"coordinates":[-2.368914,52.706703],"type":"Point"}
}