{
  "type": "Feature",
  "properties": {
    "iso:country": "GB",
    "wof:name": "FK6 6NY",
    "wof:placetype": "postalcode"
  },
  "geometry": {"coordinates":[-3.915807,56.023142],"type":"Point"}
}
