{
  "type": "Feature",
  "properties": {
    "iso:country":"GB",
    "wof:name":"DH5 9DT",
    "wof:placetype":"postalcode"
},
  "geometry": {"coordinates":[-1.44638713311324,54.82457965703315],"type":"Point"}
}