{
  "type": "Feature",
  "properties": {
    "iso:country":"GB",
    "wof:name":"DN8 4EQ",
    "wof:placetype":"postalcode"
},
  "geometry": {"coordinates":[-0.95730644347076,53.62088413201311],"type":"Point"}
}