{
  "type": "Feature",
  "properties": {
    "iso:country":"GB",
    "wof:name":"MK16 9PE",
    "wof:placetype":"postalcode"
},
  "geometry": {"coordinates":[-0.69960721702636,52.11267263492539],"type":"Point"}
}