{
  "type": "Feature",
  "properties": {
    "iso:country": "GB",
    "wof:name": "MK16 9PE",
    "wof:placetype": "postalcode"
  },
  "geometry": {"coordinates":[-0.699607,52.112673],"type":"Point"}
}
