{
  "type": "Feature",
  "properties": {
    "date:inception_lower": "2020-04-01",
    "date:inception_upper": "2020-04-01",
    "iso:country": "GB",
    "wof:name": "SY23 5BL",
    "wof:placetype": "postalcode"
  },
  "geometry": {"coordinates":[-4.176751,52.28194],"type":"Point"}
}
