{
  "type": "Feature",
  "properties": {
    "iso:country":"GB",
    "wof:name":"PE21 7EE",
    "wof:placetype":"postalcode"
},
  "geometry": {"coordinates":[-0.0385077282437,52.95282276875238],"type":"Point"}
}