{
  "type": "Feature",
  "properties": {
    "iso:country": "GB",
    "wof:name": "N14 5HY",
    "wof:placetype": "postalcode"
  },
  "geometry": {"coordinates":[-0.13425,51.63399],"type":"Point"}
}
