{
  "type": "Feature",
  "properties": {
    "iso:country":"GB",
    "wof:name":"N14 5HY",
    "wof:placetype":"postalcode"
},
  "geometry": {"coordinates":[-0.1342495832232,51.63398951461006],"type":"Point"}
}