{
  "type": "Feature",
  "properties": {
    "iso:country":"GB",
    "wof:name":"CH7 6XE",
    "wof:placetype":"postalcode"
},
  "geometry": {"coordinates":[-3.11383329087071,53.17081278371616],"type":"Point"}
}