{
  "type": "Feature",
  "properties": {
    "iso:country":"GB",
    "wof:name":"LE5 5TW",
    "wof:placetype":"postalcode"
},
  "geometry": {"coordinates":[-1.09444603583662,52.61678092886235],"type":"Point"}
}