{
  "type": "Feature",
  "properties": {
    "date:inception_lower": "2020-08-01",
    "date:inception_upper": "2020-08-01",
    "iso:country": "GB",
    "wof:name": "DA6 7BE",
    "wof:placetype": "postalcode"
  },
  "geometry": {"coordinates":[0.151304,51.455381],"type":"Point"}
}
