{
  "type": "Feature",
  "properties": {
    "iso:country":"GB",
    "wof:name":"EN2 0TZ",
    "wof:placetype":"postalcode"
},
  "geometry": {"coordinates":[-0.09365412173999,51.66544913146905],"type":"Point"}
}