{
  "type": "Feature",
  "properties": {
    "iso:country": "GB",
    "wof:name": "CR2 8RL",
    "wof:placetype": "postalcode"
  },
  "geometry": {"coordinates":[-0.056634,51.337979],"type":"Point"}
}
