{
  "type": "Feature",
  "properties": {
    "date:inception_lower": "1980-01-01",
    "date:inception_upper": "1980-01-01",
    "iso:country": "GB",
    "wof:name": "CR2 8RL",
    "wof:placetype": "postalcode"
  },
  "geometry": {"coordinates":[-0.056634,51.337979],"type":"Point"}
}
