{
  "type": "Feature",
  "properties": {
    "iso:country":"GB",
    "wof:name":"CR2 8RL",
    "wof:placetype":"postalcode"
},
  "geometry": {"coordinates":[-0.05663378860606,51.33797853560683],"type":"Point"}
}