{
  "type": "Feature",
  "properties": {
    "date:inception_lower": "1980-01-01",
    "date:inception_upper": "1980-01-01",
    "iso:country": "GB",
    "wof:name": "NN17 3AD",
    "wof:placetype": "postalcode"
  },
  "geometry": {"coordinates":[-0.65166,52.564992],"type":"Point"}
}
