{
  "type": "Feature",
  "properties": {
    "iso:country":"GB",
    "wof:name":"NN17 3AD",
    "wof:placetype":"postalcode"
},
  "geometry": {"coordinates":[-0.65165991937707,52.56499187910448],"type":"Point"}
}