{
  "type": "Feature",
  "properties": {
    "iso:country":"GB",
    "wof:name":"NW3 1LB",
    "wof:placetype":"postalcode"
},
  "geometry": {"coordinates":[-0.17331624502348,51.55859147134633],"type":"Point"}
}