{
  "type": "Feature",
  "properties": {
    "iso:country":"GB",
    "wof:name":"SS6 9HQ",
    "wof:placetype":"postalcode"
},
  "geometry": {"coordinates":[0.60105874910795,51.59143514998524],"type":"Point"}
}