{
  "type": "Feature",
  "properties": {
    "iso:country":"GB",
    "wof:name":"HU6 7DU",
    "wof:placetype":"postalcode"
},
  "geometry": {"coordinates":[-0.34813208232007,53.78098412648287],"type":"Point"}
}