{
  "type": "Feature",
  "properties": {
    "date:inception_lower": "1980-01-01",
    "date:inception_upper": "1980-01-01",
    "iso:country": "GB",
    "wof:name": "HU6 7DU",
    "wof:placetype": "postalcode"
  },
  "geometry": {"coordinates":[-0.348132,53.780984],"type":"Point"}
}
