{
  "type": "Feature",
  "properties": {
    "iso:country":"GB",
    "wof:name":"DN15 8NL",
    "wof:placetype":"postalcode"
},
  "geometry": {"coordinates":[-0.67583754027294,53.60675748261944],"type":"Point"}
}