{
  "type": "Feature",
  "properties": {
    "iso:country":"GB",
    "wof:name":"B44 9NB",
    "wof:placetype":"postalcode"
},
  "geometry": {"coordinates":[-1.88600064476981,52.556420658027],"type":"Point"}
}