{
  "type": "Feature",
  "properties": {
    "iso:country":"GB",
    "wof:name":"BR2 6HY",
    "wof:placetype":"postalcode"
},
  "geometry": {"coordinates":[0.03794192714262,51.36138935379047],"type":"Point"}
}