{
  "type": "Feature",
  "properties": {
    "date:inception_lower":"1981-06-01",
    "date:inception_upper":"1981-06-30",
    "iso:country":"GB",
    "wof:name":"BR2 6HY",
    "wof:placetype":"postalcode"
},
  "geometry": {"coordinates":[0.037942,51.361389],"type":"Point"}
}