{
  "type": "Feature",
  "properties": {
    "date:inception_lower": "1980-01-01",
    "date:inception_upper": "1980-01-01",
    "iso:country": "GB",
    "wof:name": "GL5 3LY",
    "wof:placetype": "postalcode"
  },
  "geometry": {"coordinates":[-2.227951,51.740531],"type":"Point"}
}
