{
  "type": "Feature",
  "properties": {
    "iso:country": "GB",
    "wof:name": "GL5 3LY",
    "wof:placetype": "postalcode"
  },
  "geometry": {"coordinates":[-2.227951,51.740531],"type":"Point"}
}
