{
  "type": "Feature",
  "properties": {
    "iso:country":"GB",
    "wof:name":"AB52 6NT",
    "wof:placetype":"postalcode"
},
  "geometry": {"coordinates":[-2.66898084622032,57.31131603889101],"type":"Point"}
}