{
  "type": "Feature",
  "properties": {
    "iso:country":"GB",
    "wof:name":"BD16 4DQ",
    "wof:placetype":"postalcode"
},
  "geometry": {"coordinates":[-1.83364116952148,53.85697518853487],"type":"Point"}
}