{
  "type": "Feature",
  "properties": {
    "date:inception_lower": "1980-01-01",
    "date:inception_upper": "1980-01-01",
    "iso:country": "GB",
    "wof:name": "BD16 4DQ",
    "wof:placetype": "postalcode"
  },
  "geometry": {"coordinates":[-1.833037,53.856701],"type":"Point"}
}
