{
  "type": "Feature",
  "properties": {
    "iso:country":"GB",
    "wof:name":"DL16 6UU",
    "wof:placetype":"postalcode"
},
  "geometry": {"coordinates":[-1.5957819236728,54.70694126440799],"type":"Point"}
}