{
  "type": "Feature",
  "properties": {
    "date:inception_lower":"1980-01-01",
    "date:inception_upper":"1980-01-31",
    "iso:country":"GB",
    "wof:name":"DL16 6UU",
    "wof:placetype":"postalcode"
},
  "geometry": {"coordinates":[-1.595782,54.706941],"type":"Point"}
}