{
  "type": "Feature",
  "properties": {
    "iso:country": "GB",
    "wof:name": "YO30 5RW",
    "wof:placetype": "postalcode"
  },
  "geometry": {"coordinates":[-1.111529,53.978145],"type":"Point"}
}
