{
  "type": "Feature",
  "properties": {
    "date:inception_lower":"1980-01-01",
    "date:inception_upper":"1980-01-31",
    "iso:country":"GB",
    "wof:name":"GU33 7QG",
    "wof:placetype":"postalcode"
},
  "geometry": {"coordinates":[-0.881172,51.030446],"type":"Point"}
}