{
  "type": "Feature",
  "properties": {
    "iso:country":"GB",
    "wof:name":"LU3 1RU",
    "wof:placetype":"postalcode"
},
  "geometry": {"coordinates":[-0.44113704869105,51.89659334027925],"type":"Point"}
}