{
  "type": "Feature",
  "properties": {
    "iso:country": "GB",
    "wof:name": "LU3 1RU",
    "wof:placetype": "postalcode"
  },
  "geometry": {"coordinates":[-0.441137,51.896593],"type":"Point"}
}
