{
  "type": "Feature",
  "properties": {
    "date:inception_lower":"2015-09-01",
    "date:inception_upper":"2015-09-30",
    "iso:country":"GB",
    "wof:name":"E14 7JU",
    "wof:placetype":"postalcode"
},
  "geometry": {"coordinates":[-0.038555,51.511057],"type":"Point"}
}