{
  "type": "Feature",
  "properties": {
    "iso:country": "GB",
    "wof:name": "E14 7JU",
    "wof:placetype": "postalcode"
  },
  "geometry": {"coordinates":[-0.038555,51.511057],"type":"Point"}
}
