{
  "type": "Feature",
  "properties": {
    "iso:country":"GB",
    "wof:name":"E14 7JU",
    "wof:placetype":"postalcode"
},
  "geometry": {"coordinates":[-0.03855484834146,51.5110573288032],"type":"Point"}
}