{
  "type": "Feature",
  "properties": {
    "iso:country": "GB",
    "wof:name": "LS17 9EY",
    "wof:placetype": "postalcode"
  },
  "geometry": {"coordinates":[-1.454104,53.897024],"type":"Point"}
}
