{
  "type": "Feature",
  "properties": {
    "iso:country":"GB",
    "wof:name":"LS17 9EY",
    "wof:placetype":"postalcode"
},
  "geometry": {"coordinates":[-1.45410388783806,53.89702360951328],"type":"Point"}
}