{
  "type": "Feature",
  "properties": {
    "date:inception_lower": "1980-01-01",
    "date:inception_upper": "1980-01-01",
    "iso:country": "GB",
    "wof:name": "ST15 8DH",
    "wof:placetype": "postalcode"
  },
  "geometry": {"coordinates":[-2.14656,52.9066],"type":"Point"}
}
