{
  "type": "Feature",
  "properties": {
    "iso:country":"GB",
    "wof:name":"HU9 3JU",
    "wof:placetype":"postalcode"
},
  "geometry": {"coordinates":[-0.29118771928297,53.76337625259075],"type":"Point"}
}