{
  "type": "Feature",
  "properties": {
    "iso:country": "GB",
    "wof:name": "SA9 1GB",
    "wof:placetype": "postalcode"
  },
  "geometry": {"coordinates":[-3.674506,51.817667],"type":"Point"}
}
