{
  "type": "Feature",
  "properties": {
    "iso:country":"GB",
    "wof:name":"SA9 1GB",
    "wof:placetype":"postalcode"
},
  "geometry": {"coordinates":[-3.67450635770831,51.8176674280823],"type":"Point"}
}