{
  "type": "Feature",
  "properties": {
    "iso:country":"GB",
    "wof:name":"KT12 2JA",
    "wof:placetype":"postalcode"
},
  "geometry": {"coordinates":[-0.41580221932953,51.39447296436506],"type":"Point"}
}