{
  "type": "Feature",
  "properties": {
    "iso:country":"GB",
    "wof:name":"HD9 6PX",
    "wof:placetype":"postalcode"
},
  "geometry": {"coordinates":[-1.78840526582458,53.60439307918909],"type":"Point"}
}