{
  "type": "Feature",
  "properties": {
    "date:inception_lower":"1991-09-01",
    "date:inception_upper":"1991-09-30",
    "iso:country":"GB",
    "wof:name":"GU22 9JB",
    "wof:placetype":"postalcode"
},
  "geometry": {"coordinates":[-0.538545,51.301864],"type":"Point"}
}