{
  "type": "Feature",
  "properties": {
    "iso:country":"GB",
    "wof:name":"GU22 9JB",
    "wof:placetype":"postalcode"
},
  "geometry": {"coordinates":[-0.53854492423666,51.30186417533088],"type":"Point"}
}