{
  "type": "Feature",
  "properties": {
    "iso:country": "GB",
    "wof:name": "RG30 2NW",
    "wof:placetype": "postalcode"
  },
  "geometry": {"coordinates":[-1.008521,51.452941],"type":"Point"}
}
