{
  "type": "Feature",
  "properties": {
    "iso:country": "GB",
    "wof:name": "OX49 5HT",
    "wof:placetype": "postalcode"
  },
  "geometry": {"coordinates":[-0.967577,51.639615],"type":"Point"}
}
