{
  "type": "Feature",
  "properties": {
    "iso:country": "GB",
    "wof:name": "CH5 4GZ",
    "wof:placetype": "postalcode"
  },
  "geometry": {"coordinates":[-3.07149,53.216795],"type":"Point"}
}
