{
  "type": "Feature",
  "properties": {
    "date:inception_lower": "1991-09-01",
    "date:inception_upper": "1991-09-01",
    "iso:country": "GB",
    "wof:name": "CH5 4GZ",
    "wof:placetype": "postalcode"
  },
  "geometry": {"coordinates":[-3.07149,53.216795],"type":"Point"}
}
