{
  "type": "Feature",
  "properties": {
    "iso:country":"GB",
    "wof:name":"CH5 4GZ",
    "wof:placetype":"postalcode"
},
  "geometry": {"coordinates":[-3.07149006827212,53.2167950931561],"type":"Point"}
}