{
  "type": "Feature",
  "properties": {
    "date:inception_lower": "2016-05-01",
    "date:inception_upper": "2016-05-01",
    "iso:country": "GB",
    "wof:name": "HP22 4FH",
    "wof:placetype": "postalcode"
  },
  "geometry": {"coordinates":[-0.742748,51.864199],"type":"Point"}
}
