{
  "type": "Feature",
  "properties": {
    "iso:country": "GB",
    "wof:name": "WV10 7TS",
    "wof:placetype": "postalcode"
  },
  "geometry": {"coordinates":[-2.095022,52.64682],"type":"Point"}
}
