{
  "type": "Feature",
  "properties": {
    "date:inception_lower":"1985-04-01",
    "date:inception_upper":"1985-04-30",
    "iso:country":"GB",
    "wof:name":"WV10 7TS",
    "wof:placetype":"postalcode"
},
  "geometry": {"coordinates":[-2.095022,52.64682],"type":"Point"}
}