{
  "type": "Feature",
  "properties": {
    "iso:country":"GB",
    "wof:name":"TS9 6PG",
    "wof:placetype":"postalcode"
},
  "geometry": {"coordinates":[-1.14357607649709,54.4860788338451],"type":"Point"}
}