{
  "type": "Feature",
  "properties": {
    "date:inception_lower": "1980-01-01",
    "date:inception_upper": "1980-01-01",
    "iso:country": "GB",
    "wof:name": "TS9 6PG",
    "wof:placetype": "postalcode"
  },
  "geometry": {"coordinates":[-1.143591,54.486079],"type":"Point"}
}
