{
  "type": "Feature",
  "properties": {
    "iso:country":"GB",
    "wof:name":"IP11 0YE",
    "wof:placetype":"postalcode"
},
  "geometry": {"coordinates":[1.31115270154258,51.98962536302612],"type":"Point"}
}