{
  "type": "Feature",
  "properties": {
    "iso:country":"GB",
    "wof:name":"NE28 8SG",
    "wof:placetype":"postalcode"
},
  "geometry": {"coordinates":[-1.53881126627381,54.99508702554101],"type":"Point"}
}