{
  "type": "Feature",
  "properties": {
    "iso:country":"GB",
    "wof:name":"ST5 5AY",
    "wof:placetype":"postalcode"
},
  "geometry": {"coordinates":[-2.27940609355766,53.00309537554838],"type":"Point"}
}