{
  "type": "Feature",
  "properties": {
    "date:inception_lower": "1991-09-01",
    "date:inception_upper": "1991-09-01",
    "iso:country": "GB",
    "wof:name": "ST5 5AY",
    "wof:placetype": "postalcode"
  },
  "geometry": {"coordinates":[-2.279406,53.003095],"type":"Point"}
}
