{
  "type": "Feature",
  "properties": {
    "iso:country":"GB",
    "wof:name":"SG9 0NP",
    "wof:placetype":"postalcode"
},
  "geometry": {"coordinates":[0.03740322396413,51.95111968258012],"type":"Point"}
}