{
  "type": "Feature",
  "properties": {
    "iso:country":"GB",
    "wof:name":"TN13 1BH",
    "wof:placetype":"postalcode"
},
  "geometry": {"coordinates":[0.18756344141073,51.27447841403733],"type":"Point"}
}