{
  "type": "Feature",
  "properties": {
    "iso:country":"GB",
    "wof:name":"G44 4EJ",
    "wof:placetype":"postalcode"
},
  "geometry": {"coordinates":[-4.26269317203361,55.81742945176513],"type":"Point"}
}