{
  "type": "Feature",
  "properties": {
    "iso:country": "GB",
    "wof:name": "SR7 7WR",
    "wof:placetype": "postalcode"
  },
  "geometry": {"coordinates":[-1.337994,54.843673],"type":"Point"}
}
