{
  "type": "Feature",
  "properties": {
    "date:inception_lower":"2003-09-01",
    "date:inception_upper":"2003-09-30",
    "iso:country":"GB",
    "wof:name":"SR7 7WR",
    "wof:placetype":"postalcode"
},
  "geometry": {"coordinates":[-1.337994,54.843673],"type":"Point"}
}