{
  "type": "Feature",
  "properties": {
    "iso:country":"GB",
    "wof:name":"SR7 7WR",
    "wof:placetype":"postalcode"
},
  "geometry": {"coordinates":[-1.33799371491288,54.84367293041114],"type":"Point"}
}