{
  "type": "Feature",
  "properties": {
    "date:inception_lower": "1997-06-01",
    "date:inception_upper": "1997-06-01",
    "iso:country": "GB",
    "wof:name": "S36 9FB",
    "wof:placetype": "postalcode"
  },
  "geometry": {"coordinates":[-1.642449,53.51507],"type":"Point"}
}
