{
  "type": "Feature",
  "properties": {
    "iso:country":"GB",
    "wof:name":"S36 9FB",
    "wof:placetype":"postalcode"
},
  "geometry": {"coordinates":[-1.643125426483,53.51524329886175],"type":"Point"}
}