{
  "type": "Feature",
  "properties": {
    "iso:country": "GB",
    "wof:name": "SA1 8AT",
    "wof:placetype": "postalcode"
  },
  "geometry": {"coordinates":[-3.933191,51.622324],"type":"Point"}
}
