{
  "type": "Feature",
  "properties": {
    "iso:country":"GB",
    "wof:name":"G43 2YN",
    "wof:placetype":"postalcode"
},
  "geometry": {"coordinates":[-4.29152885793111,55.81889956493531],"type":"Point"}
}