{
  "type": "Feature",
  "properties": {
    "iso:country":"GB",
    "wof:name":"LS16 8ED",
    "wof:placetype":"postalcode"
},
  "geometry": {"coordinates":[-1.57475489742444,53.8531109901357],"type":"Point"}
}