{
  "type": "Feature",
  "properties": {
    "date:inception_lower": "2007-07-01",
    "date:inception_upper": "2007-07-01",
    "iso:country": "GB",
    "wof:name": "LS16 8ED",
    "wof:placetype": "postalcode"
  },
  "geometry": {"coordinates":[-1.57467,53.85301],"type":"Point"}
}
