{
  "type": "Feature",
  "properties": {
    "iso:country":"GB",
    "wof:name":"CR0 6QU",
    "wof:placetype":"postalcode"
},
  "geometry": {"coordinates":[-0.07586394308665,51.38033735256977],"type":"Point"}
}