{
  "type": "Feature",
  "properties": {
    "iso:country": "GB",
    "wof:name": "DN40 3PN",
    "wof:placetype": "postalcode"
  },
  "geometry": {"coordinates":[-0.291638,53.658406],"type":"Point"}
}
