{
  "type": "Feature",
  "properties": {
    "iso:country": "GB",
    "wof:name": "PR5 0AY",
    "wof:placetype": "postalcode"
  },
  "geometry": {"coordinates":[-2.623809,53.730002],"type":"Point"}
}
