{
  "type": "Feature",
  "properties": {
    "iso:country":"GB",
    "wof:name":"PR5 0AY",
    "wof:placetype":"postalcode"
},
  "geometry": {"coordinates":[-2.6238094192916,53.73000227824991],"type":"Point"}
}