{
  "type": "Feature",
  "properties": {
    "iso:country":"GB",
    "wof:name":"SR7 8LU",
    "wof:placetype":"postalcode"
},
  "geometry": {"coordinates":[-1.35559381310839,54.83366664709634],"type":"Point"}
}