{
  "type": "Feature",
  "properties": {
    "iso:country":"GB",
    "wof:name":"E14 6AE",
    "wof:placetype":"postalcode"
},
  "geometry": {"coordinates":[-0.01676900141381,51.51228264893593],"type":"Point"}
}