{
  "type": "Feature",
  "properties": {
    "iso:country":"GB",
    "wof:name":"DN35 0HQ",
    "wof:placetype":"postalcode"
},
  "geometry": {"coordinates":[-0.01518887331534,53.54425901759127],"type":"Point"}
}