{
  "type": "Feature",
  "properties": {
    "iso:country": "GB",
    "wof:name": "DN35 0HQ",
    "wof:placetype": "postalcode"
  },
  "geometry": {"coordinates":[-0.015189,53.544259],"type":"Point"}
}
