{
  "type": "Feature",
  "properties": {
    "iso:country": "GB",
    "wof:name": "ME10 9JX",
    "wof:placetype": "postalcode"
  },
  "geometry": {"coordinates":[0.734379,51.339214],"type":"Point"}
}
