{
  "type": "Feature",
  "properties": {
    "iso:country":"GB",
    "wof:name":"SW12 0DD",
    "wof:placetype":"postalcode"
},
  "geometry": {"coordinates":[-0.14270919599726,51.45072234764701],"type":"Point"}
}