{
  "type": "Feature",
  "properties": {
    "date:inception_lower": "1980-01-01",
    "date:inception_upper": "1980-01-01",
    "iso:country": "GB",
    "wof:name": "B71 3AR",
    "wof:placetype": "postalcode"
  },
  "geometry": {"coordinates":[-1.982188,52.544284],"type":"Point"}
}
