{
  "type": "Feature",
  "properties": {
    "iso:country":"GB",
    "wof:name":"B71 3AR",
    "wof:placetype":"postalcode"
},
  "geometry": {"coordinates":[-1.98218808842223,52.54428374675869],"type":"Point"}
}