{
  "type": "Feature",
  "properties": {
    "iso:country":"GB",
    "wof:name":"PE27 6DH",
    "wof:placetype":"postalcode"
},
  "geometry": {"coordinates":[-0.07903851656579,52.3278972694654],"type":"Point"}
}