{
  "type": "Feature",
  "properties": {
    "iso:country":"GB",
    "wof:name":"CH60 9HG",
    "wof:placetype":"postalcode"
},
  "geometry": {"coordinates":[-3.1209258497186,53.33480936109817],"type":"Point"}
}