{
  "type": "Feature",
  "properties": {
    "iso:country": "GB",
    "wof:name": "NG34 7EX",
    "wof:placetype": "postalcode"
  },
  "geometry": {"coordinates":[-0.400223,52.99565],"type":"Point"}
}
