{
  "type": "Feature",
  "properties": {
    "iso:country":"GB",
    "wof:name":"WF1 2JP",
    "wof:placetype":"postalcode"
},
  "geometry": {"coordinates":[-1.50469200105889,53.70203131090423],"type":"Point"}
}