{
  "type": "Feature",
  "properties": {
    "date:inception_lower": "1980-01-01",
    "date:inception_upper": "1980-01-01",
    "iso:country": "GB",
    "wof:name": "FK16 6HU",
    "wof:placetype": "postalcode"
  },
  "geometry": {"coordinates":[-4.059578,56.190683],"type":"Point"}
}
