{
  "type": "Feature",
  "properties": {
    "iso:country":"GB",
    "wof:name":"SS0 0HW",
    "wof:placetype":"postalcode"
},
  "geometry": {"coordinates":[0.67266261142947,51.56172984263106],"type":"Point"}
}