{
  "type": "Feature",
  "properties": {
    "date:inception_lower": "1980-01-01",
    "date:inception_upper": "1980-01-01",
    "iso:country": "GB",
    "wof:name": "SS0 0HW",
    "wof:placetype": "postalcode"
  },
  "geometry": {"coordinates":[0.672663,51.56173],"type":"Point"}
}
