{
  "type": "Feature",
  "properties": {
    "iso:country":"GB",
    "wof:name":"CA1 3NZ",
    "wof:placetype":"postalcode"
},
  "geometry": {"coordinates":[-2.90298565430377,54.8770930216022],"type":"Point"}
}