{
  "type": "Feature",
  "properties": {
    "date:inception_lower": "2010-04-01",
    "date:inception_upper": "2010-04-01",
    "iso:country": "GB",
    "wof:name": "CA1 3NZ",
    "wof:placetype": "postalcode"
  },
  "geometry": {"coordinates":[-2.903068,54.877099],"type":"Point"}
}
