{
  "type": "Feature",
  "properties": {
    "iso:country":"GB",
    "wof:name":"AB53 5UA",
    "wof:placetype":"postalcode"
},
  "geometry": {"coordinates":[-2.32915343078737,57.59603986541051],"type":"Point"}
}