{
  "type": "Feature",
  "properties": {
    "iso:country": "GB",
    "wof:name": "AB53 5UA",
    "wof:placetype": "postalcode"
  },
  "geometry": {"coordinates":[-2.329153,57.59604],"type":"Point"}
}
