{
  "type": "Feature",
  "properties": {
    "iso:country":"GB",
    "wof:name":"KW15 1WU",
    "wof:placetype":"postalcode"
},
  "geometry": {"coordinates":[-2.95358294365257,58.96929928942083],"type":"Point"}
}