{
  "type": "Feature",
  "properties": {
    "date:inception_lower": "2007-07-01",
    "date:inception_upper": "2007-07-01",
    "iso:country": "GB",
    "wof:name": "KW15 1WU",
    "wof:placetype": "postalcode"
  },
  "geometry": {"coordinates":[-2.953793,58.969138],"type":"Point"}
}
