{
  "type": "Feature",
  "properties": {
    "iso:country": "GB",
    "wof:name": "NE66 3LW",
    "wof:placetype": "postalcode"
  },
  "geometry": {"coordinates":[-1.598348,55.452699],"type":"Point"}
}
