{
  "type": "Feature",
  "properties": {
    "iso:country":"GB",
    "wof:name":"NE66 3LW",
    "wof:placetype":"postalcode"
},
  "geometry": {"coordinates":[-1.59833118794295,55.45269816908691],"type":"Point"}
}