{
  "type": "Feature",
  "properties": {
    "iso:country":"GB",
    "wof:name":"SN12 7ER",
    "wof:placetype":"postalcode"
},
  "geometry": {"coordinates":[-2.12600663441188,51.38047202169427],"type":"Point"}
}