{
  "type": "Feature",
  "properties": {
    "iso:country": "GB",
    "wof:name": "SN12 7ER",
    "wof:placetype": "postalcode"
  },
  "geometry": {"coordinates":[-2.126007,51.380472],"type":"Point"}
}
