{
  "type": "Feature",
  "properties": {
    "iso:country":"GB",
    "wof:name":"RM5 2AJ",
    "wof:placetype":"postalcode"
},
  "geometry": {"coordinates":[0.16011224891618,51.59785424751906],"type":"Point"}
}