{
  "type": "Feature",
  "properties": {
    "date:inception_lower": "1980-01-01",
    "date:inception_upper": "1980-01-01",
    "iso:country": "GB",
    "wof:name": "NG7 2JQ",
    "wof:placetype": "postalcode"
  },
  "geometry": {"coordinates":[-1.185131,52.938475],"type":"Point"}
}
