{
  "type": "Feature",
  "properties": {
    "iso:country":"GB",
    "wof:name":"S26 3NT",
    "wof:placetype":"postalcode"
},
  "geometry": {"coordinates":[-1.31706497689358,53.37063648987834],"type":"Point"}
}