{
  "type": "Feature",
  "properties": {
    "iso:country":"GB",
    "wof:name":"MK40 3HD",
    "wof:placetype":"postalcode"
},
  "geometry": {"coordinates":[-0.46505985371711,52.13716824735305],"type":"Point"}
}