{
  "type": "Feature",
  "properties": {
    "date:inception_lower": "1980-01-01",
    "date:inception_upper": "1980-01-01",
    "iso:country": "GB",
    "wof:name": "MK40 3HD",
    "wof:placetype": "postalcode"
  },
  "geometry": {"coordinates":[-0.464983,52.137072],"type":"Point"}
}
