{
  "type": "Feature",
  "properties": {
    "date:inception_lower": "2024-03-01",
    "date:inception_upper": "2024-03-01",
    "iso:country": "GB",
    "wof:name": "L35 3AA",
    "wof:placetype": "postalcode"
  },
  "geometry": {"coordinates":[-2.78984,53.399194],"type":"Point"}
}
