{
  "type": "Feature",
  "properties": {
    "date:inception_lower":"1992-05-01",
    "date:inception_upper":"1992-05-31",
    "iso:country":"GB",
    "wof:name":"ML5 5BL",
    "wof:placetype":"postalcode"
},
  "geometry": {"coordinates":[-4.041191,55.847153],"type":"Point"}
}