{
  "type": "Feature",
  "properties": {
    "iso:country":"GB",
    "wof:name":"ML5 5BL",
    "wof:placetype":"postalcode"
},
  "geometry": {"coordinates":[-4.0411911061555,55.84715315844984],"type":"Point"}
}