{
  "type": "Feature",
  "properties": {
    "iso:country": "GB",
    "wof:name": "SE16 3UH",
    "wof:placetype": "postalcode"
  },
  "geometry": {"coordinates":[-0.06829,51.4946],"type":"Point"}
}
