{
  "type": "Feature",
  "properties": {
    "iso:country":"GB",
    "wof:name":"SA14 8TD",
    "wof:placetype":"postalcode"
},
  "geometry": {"coordinates":[-4.13028076953638,51.68560982988148],"type":"Point"}
}