{
  "type": "Feature",
  "properties": {
    "date:inception_lower": "1983-01-01",
    "date:inception_upper": "1983-01-01",
    "iso:country": "GB",
    "wof:name": "SA14 8TD",
    "wof:placetype": "postalcode"
  },
  "geometry": {"coordinates":[-4.130281,51.68561],"type":"Point"}
}
