{
  "type": "Feature",
  "properties": {
    "iso:country":"GB",
    "wof:name":"LE67 9XQ",
    "wof:placetype":"postalcode"
},
  "geometry": {"coordinates":[-1.28249715086639,52.68572658204687],"type":"Point"}
}