{
  "type": "Feature",
  "properties": {
    "date:inception_lower":"2000-10-01",
    "date:inception_upper":"2000-10-31",
    "iso:country":"GB",
    "wof:name":"OX25 2RR",
    "wof:placetype":"postalcode"
},
  "geometry": {"coordinates":[-1.126914,51.871742],"type":"Point"}
}