{
  "type": "Feature",
  "properties": {
    "iso:country":"GB",
    "wof:name":"WN7 3AR",
    "wof:placetype":"postalcode"
},
  "geometry": {"coordinates":[-2.50234914004338,53.4878879931831],"type":"Point"}
}