{
  "type": "Feature",
  "properties": {
    "iso:country": "GB",
    "wof:name": "TN10 3HJ",
    "wof:placetype": "postalcode"
  },
  "geometry": {"coordinates":[0.274295,51.214971],"type":"Point"}
}
