{
  "type": "Feature",
  "properties": {
    "iso:country": "GB",
    "wof:name": "PR5 6GE",
    "wof:placetype": "postalcode"
  },
  "geometry": {"coordinates":[-2.659722,53.736084],"type":"Point"}
}
