{
  "type": "Feature",
  "properties": {
    "iso:country":"GB",
    "wof:name":"BB11 2NH",
    "wof:placetype":"postalcode"
},
  "geometry": {"coordinates":[-2.25403429308981,53.77605495591809],"type":"Point"}
}