{
  "type": "Feature",
  "properties": {
    "iso:country":"GB",
    "wof:name":"DE23 1GY",
    "wof:placetype":"postalcode"
},
  "geometry": {"coordinates":[-1.49842564014163,52.89180771537124],"type":"Point"}
}