{
  "type": "Feature",
  "properties": {
    "date:inception_lower": "2018-05-01",
    "date:inception_upper": "2018-05-01",
    "iso:country": "GB",
    "wof:name": "M15 4SG",
    "wof:placetype": "postalcode"
  },
  "geometry": {"coordinates":[-2.261772,53.466104],"type":"Point"}
}
