{
  "type": "Feature",
  "properties": {
    "iso:country": "GB",
    "wof:name": "M15 4SG",
    "wof:placetype": "postalcode"
  },
  "geometry": {"coordinates":[-2.261772,53.466104],"type":"Point"}
}
