{
  "type": "Feature",
  "properties": {
    "iso:country": "GB",
    "wof:name": "TN21 0EE",
    "wof:placetype": "postalcode"
  },
  "geometry": {"coordinates":[0.242614,50.931112],"type":"Point"}
}
