{
  "type": "Feature",
  "properties": {
    "iso:country":"GB",
    "wof:name":"LN5 7TH",
    "wof:placetype":"postalcode"
},
  "geometry": {"coordinates":[-0.54029626786603,53.22168518972541],"type":"Point"}
}