{
  "type": "Feature",
  "properties": {
    "iso:country":"GB",
    "wof:name":"CO10 9AA",
    "wof:placetype":"postalcode"
},
  "geometry": {"coordinates":[0.72262373389638,52.08251022352674],"type":"Point"}
}