{
  "type": "Feature",
  "properties": {
    "iso:country": "GB",
    "wof:name": "DA2 6LL",
    "wof:placetype": "postalcode"
  },
  "geometry": {"coordinates":[0.250708,51.437398],"type":"Point"}
}
