{
  "type": "Feature",
  "properties": {
    "iso:country": "GB",
    "wof:name": "BS27 3FL",
    "wof:placetype": "postalcode"
  },
  "geometry": {"coordinates":[-2.784727,51.281019],"type":"Point"}
}
