{
  "type": "Feature",
  "properties": {
    "iso:country": "GB",
    "wof:name": "BS27 3FL",
    "wof:placetype": "postalcode"
  },
  "geometry": {"coordinates":[-2.784736,51.281014],"type":"Point"}
}
