{
  "type": "Feature",
  "properties": {
    "date:inception_lower": "2012-05-01",
    "date:inception_upper": "2012-05-01",
    "iso:country": "GB",
    "wof:name": "BS27 3FL",
    "wof:placetype": "postalcode"
  },
  "geometry": {"coordinates":[-2.784727,51.281019],"type":"Point"}
}
