{
  "type": "Feature",
  "properties": {
    "iso:country":"GB",
    "wof:name":"CM17 9BW",
    "wof:placetype":"postalcode"
},
  "geometry": {"coordinates":[0.13437379755733,51.75795328285625],"type":"Point"}
}