{
  "type": "Feature",
  "properties": {
    "iso:country":"GB",
    "wof:name":"BB1 1NG",
    "wof:placetype":"postalcode"
},
  "geometry": {"coordinates":[-2.4640695327827,53.74831743802766],"type":"Point"}
}