{
  "type": "Feature",
  "properties": {
    "iso:country":"GB",
    "wof:name":"SY15 6EP",
    "wof:placetype":"postalcode"
},
  "geometry": {"coordinates":[-3.09083886900303,52.57878685081696],"type":"Point"}
}