{
  "type": "Feature",
  "properties": {
    "iso:country":"GB",
    "wof:name":"AB32 6PB",
    "wof:placetype":"postalcode"
},
  "geometry": {"coordinates":[-2.28110899839482,57.15984716574555],"type":"Point"}
}