{
  "type": "Feature",
  "properties": {
    "iso:country":"GB",
    "wof:name":"PL26 8EQ",
    "wof:placetype":"postalcode"
},
  "geometry": {"coordinates":[-4.88190459526428,50.37950774476909],"type":"Point"}
}