{
  "type": "Feature",
  "properties": {
    "iso:country":"GB",
    "wof:name":"B42 2AY",
    "wof:placetype":"postalcode"
},
  "geometry": {"coordinates":[-1.90920502650822,52.53339066921864],"type":"Point"}
}