{
  "type": "Feature",
  "properties": {
    "iso:country":"GB",
    "wof:name":"BR2 9JZ",
    "wof:placetype":"postalcode"
},
  "geometry": {"coordinates":[0.02609210367919,51.39915820368454],"type":"Point"}
}