{
  "type": "Feature",
  "properties": {
    "iso:country": "GB",
    "wof:name": "BR2 9JZ",
    "wof:placetype": "postalcode"
  },
  "geometry": {"coordinates":[0.026092,51.399158],"type":"Point"}
}
