{
  "type": "Feature",
  "properties": {
    "date:inception_lower": "1985-04-01",
    "date:inception_upper": "1985-04-01",
    "iso:country": "GB",
    "wof:name": "CM12 0SP",
    "wof:placetype": "postalcode"
  },
  "geometry": {"coordinates":[0.425332,51.64864],"type":"Point"}
}
