{
  "type": "Feature",
  "properties": {
    "date:inception_lower": "1994-12-01",
    "date:inception_upper": "1994-12-01",
    "iso:country": "GB",
    "wof:name": "HX1 4JN",
    "wof:placetype": "postalcode"
  },
  "geometry": {"coordinates":[-1.885782,53.724625],"type":"Point"}
}
