{
  "type": "Feature",
  "properties": {
    "iso:country": "GB",
    "wof:name": "HX1 4JN",
    "wof:placetype": "postalcode"
  },
  "geometry": {"coordinates":[-1.885782,53.724625],"type":"Point"}
}
