{
  "type": "Feature",
  "properties": {
    "iso:country":"GB",
    "wof:name":"HX1 4JN",
    "wof:placetype":"postalcode"
},
  "geometry": {"coordinates":[-1.88578229637158,53.72462523252999],"type":"Point"}
}