{
  "type": "Feature",
  "properties": {
    "iso:country":"GB",
    "wof:name":"M35 0AJ",
    "wof:placetype":"postalcode"
},
  "geometry": {"coordinates":[-2.16077650829415,53.5102556554569],"type":"Point"}
}