{
  "type": "Feature",
  "properties": {
    "iso:country":"GB",
    "wof:name":"DT6 6DD",
    "wof:placetype":"postalcode"
},
  "geometry": {"coordinates":[-2.94115649813468,50.77250668135046],"type":"Point"}
}