{
  "type": "Feature",
  "properties": {
    "date:inception_lower":"1993-01-01",
    "date:inception_upper":"1993-01-31",
    "iso:country":"GB",
    "wof:name":"CF62 6QH",
    "wof:placetype":"postalcode"
},
  "geometry": {"coordinates":[-3.299355,51.393097],"type":"Point"}
}