{
  "type": "Feature",
  "properties": {
    "date:inception_lower": "1980-01-01",
    "date:inception_upper": "1980-01-01",
    "iso:country": "GB",
    "wof:name": "SN14 8PD",
    "wof:placetype": "postalcode"
  },
  "geometry": {"coordinates":[-2.295972,51.458168],"type":"Point"}
}
