{
  "type": "Feature",
  "properties": {
    "iso:country":"GB",
    "wof:name":"SN14 8PD",
    "wof:placetype":"postalcode"
},
  "geometry": {"coordinates":[-2.29597199785068,51.45816788203803],"type":"Point"}
}