{
  "type": "Feature",
  "properties": {
    "iso:country": "GB",
    "wof:name": "RH13 9EZ",
    "wof:placetype": "postalcode"
  },
  "geometry": {"coordinates":[-0.352543,51.026509],"type":"Point"}
}
