{
  "type": "Feature",
  "properties": {
    "iso:country":"GB",
    "wof:name":"RH13 9EZ",
    "wof:placetype":"postalcode"
},
  "geometry": {"coordinates":[-0.35254334586396,51.02650940716185],"type":"Point"}
}