{
  "type": "Feature",
  "properties": {
    "iso:country":"GB",
    "wof:name":"AB15 9FD",
    "wof:placetype":"postalcode"
},
  "geometry": {"coordinates":[-2.20561923879132,57.1173422095785],"type":"Point"}
}