{
  "type": "Feature",
  "properties": {
    "iso:country":"GB",
    "wof:name":"DL13 2NB",
    "wof:placetype":"postalcode"
},
  "geometry": {"coordinates":[-2.00823311397393,54.74899710978239],"type":"Point"}
}