{
  "type": "Feature",
  "properties": {
    "date:inception_lower":"1980-01-01",
    "date:inception_upper":"1980-01-31",
    "iso:country":"GB",
    "wof:name":"DL13 2NB",
    "wof:placetype":"postalcode"
},
  "geometry": {"coordinates":[-2.008233,54.748997],"type":"Point"}
}