{
  "type": "Feature",
  "properties": {
    "date:inception_lower":"2001-12-01",
    "date:inception_upper":"2001-12-31",
    "iso:country":"GB",
    "wof:name":"NE3 4TZ",
    "wof:placetype":"postalcode"
},
  "geometry": {"coordinates":[-1.621085,55.003962],"type":"Point"}
}