{
  "type": "Feature",
  "properties": {
    "iso:country":"GB",
    "wof:name":"G20 6UG",
    "wof:placetype":"postalcode"
},
  "geometry": {"coordinates":[-4.27112008969828,55.87408412464087],"type":"Point"}
}