{
  "type": "Feature",
  "properties": {
    "date:inception_lower":"1981-12-01",
    "date:inception_upper":"1981-12-31",
    "iso:country":"GB",
    "wof:name":"G20 6UG",
    "wof:placetype":"postalcode"
},
  "geometry": {"coordinates":[-4.27112,55.874084],"type":"Point"}
}