{
  "type": "Feature",
  "properties": {
    "iso:country":"GB",
    "wof:name":"ME5 9RT",
    "wof:placetype":"postalcode"
},
  "geometry": {"coordinates":[0.50879546391281,51.33892999160607],"type":"Point"}
}