{
  "type": "Feature",
  "properties": {
    "iso:country":"GB",
    "wof:name":"DA16 3QZ",
    "wof:placetype":"postalcode"
},
  "geometry": {"coordinates":[0.08837055260622,51.4663387742202],"type":"Point"}
}