{
  "type": "Feature",
  "properties": {
    "date:inception_lower": "1980-01-01",
    "date:inception_upper": "1980-01-01",
    "iso:country": "GB",
    "wof:name": "PH20 1AH",
    "wof:placetype": "postalcode"
  },
  "geometry": {"coordinates":[-4.28709,57.020415],"type":"Point"}
}
