{
  "type": "Feature",
  "properties": {
    "iso:country":"GB",
    "wof:name":"PH20 1AH",
    "wof:placetype":"postalcode"
},
  "geometry": {"coordinates":[-4.28709038678678,57.02041520432461],"type":"Point"}
}