{
  "type": "Feature",
  "properties": {
    "iso:country": "GB",
    "wof:name": "PE19 6XT",
    "wof:placetype": "postalcode"
  },
  "geometry": {"coordinates":[-0.201801,52.194186],"type":"Point"}
}
