{
  "type": "Feature",
  "properties": {
    "iso:country":"GB",
    "wof:name":"WD25 9TF",
    "wof:placetype":"postalcode"
},
  "geometry": {"coordinates":[-0.38179476522899,51.68227167405666],"type":"Point"}
}