{
  "type": "Feature",
  "properties": {
    "iso:country":"GB",
    "wof:name":"CB11 4NE",
    "wof:placetype":"postalcode"
},
  "geometry": {"coordinates":[0.12874984541156,52.03587324795133],"type":"Point"}
}