{
  "type": "Feature",
  "properties": {
    "date:inception_lower": "1980-01-01",
    "date:inception_upper": "1980-01-01",
    "iso:country": "GB",
    "wof:name": "CB11 4NE",
    "wof:placetype": "postalcode"
  },
  "geometry": {"coordinates":[0.12875,52.035873],"type":"Point"}
}
