{
  "type": "Feature",
  "properties": {
    "iso:country": "GB",
    "wof:name": "DN14 0PR",
    "wof:placetype": "postalcode"
  },
  "geometry": {"coordinates":[-1.143798,53.705947],"type":"Point"}
}
