{
  "type": "Feature",
  "properties": {
    "iso:country":"GB",
    "wof:name":"ME16 9NB",
    "wof:placetype":"postalcode"
},
  "geometry": {"coordinates":[0.48430118659076,51.25501121671442],"type":"Point"}
}