{
  "type": "Feature",
  "properties": {
    "date:inception_lower": "1980-01-01",
    "date:inception_upper": "1980-01-01",
    "iso:country": "GB",
    "wof:name": "GL50 3PE",
    "wof:placetype": "postalcode"
  },
  "geometry": {"coordinates":[-2.077826,51.900316],"type":"Point"}
}
