{
  "type": "Feature",
  "properties": {
    "iso:country": "GB",
    "wof:name": "FK2 7NW",
    "wof:placetype": "postalcode"
  },
  "geometry": {"coordinates":[-3.785787,56.013816],"type":"Point"}
}
