{
  "type": "Feature",
  "properties": {
    "iso:country":"GB",
    "wof:name":"FK2 7NW",
    "wof:placetype":"postalcode"
},
  "geometry": {"coordinates":[-3.78578753716711,56.01381602230208],"type":"Point"}
}