{
  "type": "Feature",
  "properties": {
    "iso:country":"GB",
    "wof:name":"GU14 7HR",
    "wof:placetype":"postalcode"
},
  "geometry": {"coordinates":[-0.75471069925043,51.28640465244445],"type":"Point"}
}