{
  "type": "Feature",
  "properties": {
    "iso:country":"GB",
    "wof:name":"NN16 8YJ",
    "wof:placetype":"postalcode"
},
  "geometry": {"coordinates":[-0.71706207312984,52.40402383313128],"type":"Point"}
}