{
  "type": "Feature",
  "properties": {
    "date:inception_lower": "1982-04-01",
    "date:inception_upper": "1982-04-01",
    "iso:country": "GB",
    "wof:name": "G72 0QD",
    "wof:placetype": "postalcode"
  },
  "geometry": {"coordinates":[-4.088953,55.792568],"type":"Point"}
}
