{
  "type": "Feature",
  "properties": {
    "iso:country": "GB",
    "wof:name": "HA4 8AH",
    "wof:placetype": "postalcode"
  },
  "geometry": {"coordinates":[-0.419634,51.579216],"type":"Point"}
}
