{
  "type": "Feature",
  "properties": {
    "iso:country":"GB",
    "wof:name":"HA4 8AH",
    "wof:placetype":"postalcode"
},
  "geometry": {"coordinates":[-0.41963380084404,51.57921649241465],"type":"Point"}
}