{
  "type": "Feature",
  "properties": {
    "iso:country": "GB",
    "wof:name": "KY5 8JH",
    "wof:placetype": "postalcode"
  },
  "geometry": {"coordinates":[-3.326469,56.159983],"type":"Point"}
}
