{
  "type": "Feature",
  "properties": {
    "date:inception_lower": "1980-01-01",
    "date:inception_upper": "1980-01-01",
    "iso:country": "GB",
    "wof:name": "KY5 8JH",
    "wof:placetype": "postalcode"
  },
  "geometry": {"coordinates":[-3.326469,56.159983],"type":"Point"}
}
