{
  "type": "Feature",
  "properties": {
    "date:inception_lower":"1980-01-01",
    "date:inception_upper":"1980-01-31",
    "iso:country":"GB",
    "wof:name":"TS20 2PH",
    "wof:placetype":"postalcode"
},
  "geometry": {"coordinates":[-1.311235,54.582008],"type":"Point"}
}