{
  "type": "Feature",
  "properties": {
    "iso:country": "GB",
    "wof:name": "TS20 2PH",
    "wof:placetype": "postalcode"
  },
  "geometry": {"coordinates":[-1.311235,54.582008],"type":"Point"}
}
