{
  "type": "Feature",
  "properties": {
    "iso:country":"GB",
    "wof:name":"TS20 2PH",
    "wof:placetype":"postalcode"
},
  "geometry": {"coordinates":[-1.31123479175266,54.5820083498245],"type":"Point"}
}