{
  "type": "Feature",
  "properties": {
    "iso:country": "GB",
    "wof:name": "CA10 1DA",
    "wof:placetype": "postalcode"
  },
  "geometry": {"coordinates":[-2.534712,54.657608],"type":"Point"}
}
