{
  "type": "Feature",
  "properties": {
    "date:inception_lower": "2004-10-01",
    "date:inception_upper": "2004-10-01",
    "iso:country": "GB",
    "wof:name": "LA12 8RD",
    "wof:placetype": "postalcode"
  },
  "geometry": {"coordinates":[-2.9917,54.252255],"type":"Point"}
}
