{
  "type": "Feature",
  "properties": {
    "iso:country":"GB",
    "wof:name":"LA12 8RD",
    "wof:placetype":"postalcode"
},
  "geometry": {"coordinates":[-2.99169956975012,54.25222784849881],"type":"Point"}
}