{
  "type": "Feature",
  "properties": {
    "iso:country": "GB",
    "wof:name": "BL2 3QQ",
    "wof:placetype": "postalcode"
  },
  "geometry": {"coordinates":[-2.384462,53.599126],"type":"Point"}
}
