{
  "type": "Feature",
  "properties": {
    "date:inception_lower":"1980-01-01",
    "date:inception_upper":"1980-01-31",
    "iso:country":"GB",
    "wof:name":"BL2 3QQ",
    "wof:placetype":"postalcode"
},
  "geometry": {"coordinates":[-2.384462,53.599126],"type":"Point"}
}