{
  "type": "Feature",
  "properties": {
    "iso:country": "GB",
    "wof:name": "RM17 6BP",
    "wof:placetype": "postalcode"
  },
  "geometry": {"coordinates":[0.326626,51.47366],"type":"Point"}
}
