{
  "type": "Feature",
  "properties": {
    "iso:country":"GB",
    "wof:name":"KA11 4HE",
    "wof:placetype":"postalcode"
},
  "geometry": {"coordinates":[-4.62681982361466,55.60705499621109],"type":"Point"}
}