{
  "type": "Feature",
  "properties": {
    "iso:country": "GB",
    "wof:name": "KA11 4HE",
    "wof:placetype": "postalcode"
  },
  "geometry": {"coordinates":[-4.62682,55.607055],"type":"Point"}
}
