{
  "type": "Feature",
  "properties": {
    "iso:country":"GB",
    "wof:name":"OL4 5NZ",
    "wof:placetype":"postalcode"
},
  "geometry": {"coordinates":[-2.07526617430465,53.5279754552413],"type":"Point"}
}