{
  "type": "Feature",
  "properties": {
    "iso:country": "GB",
    "wof:name": "B60 1BD",
    "wof:placetype": "postalcode"
  },
  "geometry": {"coordinates":[-2.01101,52.348842],"type":"Point"}
}
