{
  "type": "Feature",
  "properties": {
    "date:inception_lower":"1990-07-01",
    "date:inception_upper":"1990-07-31",
    "iso:country":"GB",
    "wof:name":"B60 1BD",
    "wof:placetype":"postalcode"
},
  "geometry": {"coordinates":[-2.01101,52.348842],"type":"Point"}
}