{
  "type": "Feature",
  "properties": {
    "iso:country":"GB",
    "wof:name":"SE23 3HH",
    "wof:placetype":"postalcode"
},
  "geometry": {"coordinates":[-0.05373141569495,51.43761530442344],"type":"Point"}
}