{
  "type": "Feature",
  "properties": {
    "date:inception_lower":"1980-01-01",
    "date:inception_upper":"1980-01-31",
    "iso:country":"GB",
    "wof:name":"HX3 9JS",
    "wof:placetype":"postalcode"
},
  "geometry": {"coordinates":[-1.848064,53.706796],"type":"Point"}
}