{
  "type": "Feature",
  "properties": {
    "date:inception_lower": "2002-07-01",
    "date:inception_upper": "2002-07-01",
    "iso:country": "GB",
    "wof:name": "CV34 6NR",
    "wof:placetype": "postalcode"
  },
  "geometry": {"coordinates":[-1.612475,52.271835],"type":"Point"}
}
