{
  "type": "Feature",
  "properties": {
    "date:inception_lower": "1998-06-01",
    "date:inception_upper": "1998-06-01",
    "iso:country": "GB",
    "wof:name": "YO17 6SH",
    "wof:placetype": "postalcode"
  },
  "geometry": {"coordinates":[-0.837928,54.150297],"type":"Point"}
}
