{
  "type": "Feature",
  "properties": {
    "iso:country":"GB",
    "wof:name":"YO17 6SH",
    "wof:placetype":"postalcode"
},
  "geometry": {"coordinates":[-0.83792759512031,54.15029736836569],"type":"Point"}
}