{
  "type": "Feature",
  "properties": {
    "iso:country":"GB",
    "wof:name":"CT1 2BE",
    "wof:placetype":"postalcode"
},
  "geometry": {"coordinates":[1.07755943274988,51.2802596261127],"type":"Point"}
}