{
  "type": "Feature",
  "properties": {
    "iso:country": "GB",
    "wof:name": "PL23 1HY",
    "wof:placetype": "postalcode"
  },
  "geometry": {"coordinates":[-4.636537,50.334439],"type":"Point"}
}
