{
  "type": "Feature",
  "properties": {
    "iso:country":"GB",
    "wof:name":"SY5 0EE",
    "wof:placetype":"postalcode"
},
  "geometry": {"coordinates":[-2.98913443852398,52.60528420776294],"type":"Point"}
}