{
  "type": "Feature",
  "properties": {
    "iso:country": "GB",
    "wof:name": "SY5 0EE",
    "wof:placetype": "postalcode"
  },
  "geometry": {"coordinates":[-2.989029,52.605336],"type":"Point"}
}
