{
  "type": "Feature",
  "properties": {
    "date:inception_lower": "1980-01-01",
    "date:inception_upper": "1980-01-01",
    "iso:country": "GB",
    "wof:name": "SY5 0EE",
    "wof:placetype": "postalcode"
  },
  "geometry": {"coordinates":[-2.990255,52.603402],"type":"Point"}
}
