{
  "type": "Feature",
  "properties": {
    "iso:country": "GB",
    "wof:name": "SY5 0EE",
    "wof:placetype": "postalcode"
  },
  "geometry": {"coordinates":[-2.988034,52.60574],"type":"Point"}
}
