{
  "type": "Feature",
  "properties": {
    "date:inception_lower":"1980-01-01",
    "date:inception_upper":"1980-01-31",
    "iso:country":"GB",
    "wof:name":"SY5 0EE",
    "wof:placetype":"postalcode"
},
  "geometry": {"coordinates":[-2.988034,52.60574],"type":"Point"}
}