{
  "type": "Feature",
  "properties": {
    "iso:country":"GB",
    "wof:name":"GL54 5AU",
    "wof:placetype":"postalcode"
},
  "geometry": {"coordinates":[-1.91218318862992,51.96026914533871],"type":"Point"}
}