{
  "type": "Feature",
  "properties": {
    "iso:country": "GB",
    "wof:name": "GL54 5AU",
    "wof:placetype": "postalcode"
  },
  "geometry": {"coordinates":[-1.912183,51.960269],"type":"Point"}
}
