{
  "type": "Feature",
  "properties": {
    "iso:country":"GB",
    "wof:name":"W12 8BU",
    "wof:placetype":"postalcode"
},
  "geometry": {"coordinates":[-0.23537267836301,51.50503837471189],"type":"Point"}
}