{
  "type": "Feature",
  "properties": {
    "iso:country": "GB",
    "wof:name": "HA0 2PP",
    "wof:placetype": "postalcode"
  },
  "geometry": {"coordinates":[-0.322808,51.562298],"type":"Point"}
}
