{
  "type": "Feature",
  "properties": {
    "iso:country":"GB",
    "wof:name":"HA0 2PP",
    "wof:placetype":"postalcode"
},
  "geometry": {"coordinates":[-0.32280825305406,51.56229820173772],"type":"Point"}
}