{
  "type": "Feature",
  "properties": {
    "iso:country": "GB",
    "wof:name": "YO10 3TU",
    "wof:placetype": "postalcode"
  },
  "geometry": {"coordinates":[-1.043133,53.959958],"type":"Point"}
}
