{
  "type": "Feature",
  "properties": {
    "iso:country": "GB",
    "wof:name": "CH48 0RQ",
    "wof:placetype": "postalcode"
  },
  "geometry": {"coordinates":[-3.182071,53.369304],"type":"Point"}
}
