{
  "type": "Feature",
  "properties": {
    "date:inception_lower": "2009-12-01",
    "date:inception_upper": "2009-12-01",
    "iso:country": "GB",
    "wof:name": "CV22 7TY",
    "wof:placetype": "postalcode"
  },
  "geometry": {"coordinates":[-1.312029,52.361952],"type":"Point"}
}
