{
  "type": "Feature",
  "properties": {
    "iso:country":"GB",
    "wof:name":"B63 4BP",
    "wof:placetype":"postalcode"
},
  "geometry": {"coordinates":[-2.06412373889025,52.44966646947586],"type":"Point"}
}