{
  "type": "Feature",
  "properties": {
    "iso:country":"GB",
    "wof:name":"SL3 0JB",
    "wof:placetype":"postalcode"
},
  "geometry": {"coordinates":[-0.51863949688547,51.47794400068091],"type":"Point"}
}