{
  "type": "Feature",
  "properties": {
    "iso:country": "GB",
    "wof:name": "SL3 0JB",
    "wof:placetype": "postalcode"
  },
  "geometry": {"coordinates":[-0.518639,51.477944],"type":"Point"}
}
