{
  "type": "Feature",
  "properties": {
    "date:inception_lower": "2021-10-01",
    "date:inception_upper": "2021-10-01",
    "iso:country": "GB",
    "wof:name": "DD2 5FW",
    "wof:placetype": "postalcode"
  },
  "geometry": {"coordinates":[-3.07163,56.474876],"type":"Point"}
}
