{
  "type": "Feature",
  "properties": {
    "iso:country": "GB",
    "wof:name": "BS41 8LS",
    "wof:placetype": "postalcode"
  },
  "geometry": {"coordinates":[-2.641128,51.395168],"type":"Point"}
}
