{
  "type": "Feature",
  "properties": {
    "date:inception_lower": "1997-12-01",
    "date:inception_upper": "1997-12-01",
    "iso:country": "GB",
    "wof:name": "BS41 8LS",
    "wof:placetype": "postalcode"
  },
  "geometry": {"coordinates":[-2.641128,51.395168],"type":"Point"}
}
