{
  "type": "Feature",
  "properties": {
    "iso:country":"GB",
    "wof:name":"SA16 0BW",
    "wof:placetype":"postalcode"
},
  "geometry": {"coordinates":[-4.25066549863007,51.68796812613731],"type":"Point"}
}