{
  "type": "Feature",
  "properties": {
    "date:inception_lower": "1980-01-01",
    "date:inception_upper": "1980-01-01",
    "iso:country": "GB",
    "wof:name": "EX39 5HG",
    "wof:placetype": "postalcode"
  },
  "geometry": {"coordinates":[-4.203022,50.992594],"type":"Point"}
}
