{
  "type": "Feature",
  "properties": {
    "iso:country": "GB",
    "wof:name": "EX39 5HG",
    "wof:placetype": "postalcode"
  },
  "geometry": {"coordinates":[-4.203022,50.992594],"type":"Point"}
}
