{
  "type": "Feature",
  "properties": {
    "iso:country":"GB",
    "wof:name":"SY13 3LR",
    "wof:placetype":"postalcode"
},
  "geometry": {"coordinates":[-2.70089001105571,52.91056411840939],"type":"Point"}
}