{
  "type": "Feature",
  "properties": {
    "date:inception_lower": "1980-01-01",
    "date:inception_upper": "1980-01-01",
    "iso:country": "GB",
    "wof:name": "SY13 3LR",
    "wof:placetype": "postalcode"
  },
  "geometry": {"coordinates":[-2.700901,52.910507],"type":"Point"}
}
