{
  "type": "Feature",
  "properties": {
    "date:inception_lower":"1983-03-01",
    "date:inception_upper":"1983-03-31",
    "iso:country":"GB",
    "wof:name":"BR6 0DU",
    "wof:placetype":"postalcode"
},
  "geometry": {"coordinates":[0.087314,51.386672],"type":"Point"}
}