{
  "type": "Feature",
  "properties": {
    "iso:country": "GB",
    "wof:name": "RG12 1PU",
    "wof:placetype": "postalcode"
  },
  "geometry": {"coordinates":[-0.760338,51.415952],"type":"Point"}
}
