{
  "type": "Feature",
  "properties": {
    "date:inception_lower": "1990-02-01",
    "date:inception_upper": "1990-02-01",
    "iso:country": "GB",
    "wof:name": "MK15 9LH",
    "wof:placetype": "postalcode"
  },
  "geometry": {"coordinates":[-0.717384,52.064154],"type":"Point"}
}
