{
  "type": "Feature",
  "properties": {
    "iso:country":"GB",
    "wof:name":"DN32 8JA",
    "wof:placetype":"postalcode"
},
  "geometry": {"coordinates":[-0.05430079209029,53.55797310410401],"type":"Point"}
}