{
  "type": "Feature",
  "properties": {
    "iso:country": "GB",
    "wof:name": "DN32 8JA",
    "wof:placetype": "postalcode"
  },
  "geometry": {"coordinates":[-0.054301,53.557973],"type":"Point"}
}
