{
  "type": "Feature",
  "properties": {
    "iso:country":"GB",
    "wof:name":"HA7 1JH",
    "wof:placetype":"postalcode"
},
  "geometry": {"coordinates":[-0.29562617312709,51.59743489434224],"type":"Point"}
}