{
  "type": "Feature",
  "properties": {
    "iso:country": "GB",
    "wof:name": "TS18 3EP",
    "wof:placetype": "postalcode"
  },
  "geometry": {"coordinates":[-1.31833,54.559195],"type":"Point"}
}
