{
  "type": "Feature",
  "properties": {
    "iso:country":"GB",
    "wof:name":"TS18 3EP",
    "wof:placetype":"postalcode"
},
  "geometry": {"coordinates":[-1.31833034113561,54.55919455768076],"type":"Point"}
}