{
  "type": "Feature",
  "properties": {
    "iso:country":"GB",
    "wof:name":"KA5 5RE",
    "wof:placetype":"postalcode"
},
  "geometry": {"coordinates":[-4.48264472283097,55.51357906771666],"type":"Point"}
}