{
  "type": "Feature",
  "properties": {
    "date:inception_lower": "1980-01-01",
    "date:inception_upper": "1980-01-01",
    "iso:country": "GB",
    "wof:name": "SY23 1PN",
    "wof:placetype": "postalcode"
  },
  "geometry": {"coordinates":[-4.083439,52.411352],"type":"Point"}
}
