{
  "type": "Feature",
  "properties": {
    "iso:country":"GB",
    "wof:name":"SY23 1PN",
    "wof:placetype":"postalcode"
},
  "geometry": {"coordinates":[-4.08357663092191,52.41169380023272],"type":"Point"}
}