{
  "type": "Feature",
  "properties": {
    "iso:country":"GB",
    "wof:name":"CO7 7LW",
    "wof:placetype":"postalcode"
},
  "geometry": {"coordinates":[0.99058828234299,51.93812134276781],"type":"Point"}
}