{
  "type": "Feature",
  "properties": {
    "iso:country": "GB",
    "wof:name": "CO7 7LW",
    "wof:placetype": "postalcode"
  },
  "geometry": {"coordinates":[0.990588,51.938121],"type":"Point"}
}
