{
  "type": "Feature",
  "properties": {
    "date:inception_lower": "1980-01-01",
    "date:inception_upper": "1980-01-01",
    "iso:country": "GB",
    "wof:name": "CO7 7LW",
    "wof:placetype": "postalcode"
  },
  "geometry": {"coordinates":[0.990588,51.938121],"type":"Point"}
}
