{
  "type": "Feature",
  "properties": {
    "iso:country":"GB",
    "wof:name":"SE24 9AG",
    "wof:placetype":"postalcode"
},
  "geometry": {"coordinates":[-0.10488665947888,51.44549479011557],"type":"Point"}
}