{
  "type": "Feature",
  "properties": {
    "date:inception_lower": "1990-07-01",
    "date:inception_upper": "1990-07-01",
    "iso:country": "GB",
    "wof:name": "SK14 3SJ",
    "wof:placetype": "postalcode"
  },
  "geometry": {"coordinates":[-2.057802,53.454244],"type":"Point"}
}
