{
  "type": "Feature",
  "properties": {
    "iso:country":"GB",
    "wof:name":"SK14 3SJ",
    "wof:placetype":"postalcode"
},
  "geometry": {"coordinates":[-2.05780248412451,53.45424421123106],"type":"Point"}
}