{
  "type": "Feature",
  "properties": {
    "iso:country":"GB",
    "wof:name":"EX20 3EQ",
    "wof:placetype":"postalcode"
},
  "geometry": {"coordinates":[-4.09531351799556,50.88775983938503],"type":"Point"}
}