{
  "type": "Feature",
  "properties": {
    "iso:country": "GB",
    "wof:name": "EX20 3EQ",
    "wof:placetype": "postalcode"
  },
  "geometry": {"coordinates":[-4.095723,50.887153],"type":"Point"}
}
