{
  "type": "Feature",
  "properties": {
    "date:inception_lower": "2021-07-01",
    "date:inception_upper": "2021-07-01",
    "iso:country": "GB",
    "wof:name": "EH21 8GH",
    "wof:placetype": "postalcode"
  },
  "geometry": {"coordinates":[-3.003037,55.941257],"type":"Point"}
}
