{
  "type": "Feature",
  "properties": {
    "iso:country":"GB",
    "wof:name":"WN6 7DA",
    "wof:placetype":"postalcode"
},
  "geometry": {"coordinates":[-2.64114888938623,53.54750089961878],"type":"Point"}
}