{
  "type": "Feature",
  "properties": {
    "iso:country":"GB",
    "wof:name":"CB24 8RA",
    "wof:placetype":"postalcode"
},
  "geometry": {"coordinates":[0.1316441082175,52.28964649643833],"type":"Point"}
}