{
  "type": "Feature",
  "properties": {
    "date:inception_lower": "2006-09-01",
    "date:inception_upper": "2006-09-01",
    "iso:country": "GB",
    "wof:name": "CB24 8RA",
    "wof:placetype": "postalcode"
  },
  "geometry": {"coordinates":[0.131672,52.289661],"type":"Point"}
}
