{
  "type": "Feature",
  "properties": {
    "iso:country":"GB",
    "wof:name":"DY10 1NR",
    "wof:placetype":"postalcode"
},
  "geometry": {"coordinates":[-2.24593386157821,52.37381217740545],"type":"Point"}
}