{
  "type": "Feature",
  "properties": {
    "iso:country": "GB",
    "wof:name": "CM18 7SR",
    "wof:placetype": "postalcode"
  },
  "geometry": {"coordinates":[0.100618,51.746853],"type":"Point"}
}
