{
  "type": "Feature",
  "properties": {
    "iso:country":"GB",
    "wof:name":"CM18 7SR",
    "wof:placetype":"postalcode"
},
  "geometry": {"coordinates":[0.10061766986167,51.7468533265573],"type":"Point"}
}