{
  "type": "Feature",
  "properties": {
    "iso:country": "GB",
    "wof:name": "EH55 8HD",
    "wof:placetype": "postalcode"
  },
  "geometry": {"coordinates":[-3.620745,55.842736],"type":"Point"}
}
