{
  "type": "Feature",
  "properties": {
    "iso:country":"GB",
    "wof:name":"EH55 8HD",
    "wof:placetype":"postalcode"
},
  "geometry": {"coordinates":[-3.62074476978662,55.84273569551695],"type":"Point"}
}