{
  "type": "Feature",
  "properties": {
    "date:inception_lower": "2000-12-01",
    "date:inception_upper": "2000-12-01",
    "iso:country": "GB",
    "wof:name": "EH55 8HD",
    "wof:placetype": "postalcode"
  },
  "geometry": {"coordinates":[-3.620745,55.842736],"type":"Point"}
}
