{
  "type": "Feature",
  "properties": {
    "iso:country":"GB",
    "wof:name":"KY2 5AT",
    "wof:placetype":"postalcode"
},
  "geometry": {"coordinates":[-3.1609437869383,56.12040732547673],"type":"Point"}
}