{
  "type": "Feature",
  "properties": {
    "date:inception_lower": "2001-12-01",
    "date:inception_upper": "2001-12-01",
    "iso:country": "GB",
    "wof:name": "SP1 3ZA",
    "wof:placetype": "postalcode"
  },
  "geometry": {"coordinates":[-1.776549,51.090033],"type":"Point"}
}
