{
  "type": "Feature",
  "properties": {
    "iso:country":"GB",
    "wof:name":"SP1 3ZA",
    "wof:placetype":"postalcode"
},
  "geometry": {"coordinates":[-1.77654924545848,51.09003342205964],"type":"Point"}
}