{
  "type": "Feature",
  "properties": {
    "iso:country": "GB",
    "wof:name": "M7 2XG",
    "wof:placetype": "postalcode"
  },
  "geometry": {"coordinates":[-2.257628,53.497907],"type":"Point"}
}
