{
  "type": "Feature",
  "properties": {
    "date:inception_lower":"2009-02-01",
    "date:inception_upper":"2009-02-28",
    "iso:country":"GB",
    "wof:name":"DE15 0PW",
    "wof:placetype":"postalcode"
},
  "geometry": {"coordinates":[-1.592607,52.800538],"type":"Point"}
}