{
  "type": "Feature",
  "properties": {
    "iso:country":"GB",
    "wof:name":"DE15 0PW",
    "wof:placetype":"postalcode"
},
  "geometry": {"coordinates":[-1.59260749148365,52.80053828463465],"type":"Point"}
}