{
  "type": "Feature",
  "properties": {
    "iso:country":"GB",
    "wof:name":"SO20 8ER",
    "wof:placetype":"postalcode"
},
  "geometry": {"coordinates":[-1.56371809347008,51.12910668423185],"type":"Point"}
}