{
  "type": "Feature",
  "properties": {
    "iso:country":"GB",
    "wof:name":"GU35 9JQ",
    "wof:placetype":"postalcode"
},
  "geometry": {"coordinates":[-0.90194749451952,51.11742015320895],"type":"Point"}
}