{
  "type": "Feature",
  "properties": {
    "iso:country":"GB",
    "wof:name":"ZE2 9LB",
    "wof:placetype":"postalcode"
},
  "geometry": {"coordinates":[-1.32097307104385,60.10007291017947],"type":"Point"}
}