{
  "type": "Feature",
  "properties": {
    "date:inception_lower": "1980-01-01",
    "date:inception_upper": "1980-01-01",
    "iso:country": "GB",
    "wof:name": "ZE2 9LB",
    "wof:placetype": "postalcode"
  },
  "geometry": {"coordinates":[-1.321885,60.101612],"type":"Point"}
}
