{
  "type": "Feature",
  "properties": {
    "iso:country":"GB",
    "wof:name":"WV12 4HW",
    "wof:placetype":"postalcode"
},
  "geometry": {"coordinates":[-2.04418730679164,52.59668735381799],"type":"Point"}
}