{
  "type": "Feature",
  "properties": {
    "date:inception_lower": "1980-01-01",
    "date:inception_upper": "1980-01-01",
    "iso:country": "GB",
    "wof:name": "NG34 7QJ",
    "wof:placetype": "postalcode"
  },
  "geometry": {"coordinates":[-0.419052,52.998927],"type":"Point"}
}
