{
  "type": "Feature",
  "properties": {
    "date:inception_lower": "1980-01-01",
    "date:inception_upper": "1980-01-01",
    "iso:country": "GB",
    "wof:name": "TD14 5RH",
    "wof:placetype": "postalcode"
  },
  "geometry": {"coordinates":[-2.120895,55.839292],"type":"Point"}
}
