{
  "type": "Feature",
  "properties": {
    "date:inception_lower":"1999-12-01",
    "date:inception_upper":"1999-12-31",
    "iso:country":"GB",
    "wof:name":"PO21 1FJ",
    "wof:placetype":"postalcode"
},
  "geometry": {"coordinates":[-0.671944,50.784279],"type":"Point"}
}