{
  "type": "Feature",
  "properties": {
    "iso:country":"GB",
    "wof:name":"PO21 1FJ",
    "wof:placetype":"postalcode"
},
  "geometry": {"coordinates":[-0.67194428185142,50.78427893661503],"type":"Point"}
}