{
  "type": "Feature",
  "properties": {
    "iso:country": "GB",
    "wof:name": "PO21 1FJ",
    "wof:placetype": "postalcode"
  },
  "geometry": {"coordinates":[-0.671944,50.784279],"type":"Point"}
}
