{
  "type": "Feature",
  "properties": {
    "date:inception_lower": "1980-01-01",
    "date:inception_upper": "1980-01-01",
    "iso:country": "GB",
    "wof:name": "NE26 2AG",
    "wof:placetype": "postalcode"
  },
  "geometry": {"coordinates":[-1.441594,55.04202],"type":"Point"}
}
