{
  "type": "Feature",
  "properties": {
    "iso:country":"GB",
    "wof:name":"NE26 2AG",
    "wof:placetype":"postalcode"
},
  "geometry": {"coordinates":[-1.4415943118536,55.0420195632841],"type":"Point"}
}