{
  "type": "Feature",
  "properties": {
    "iso:country":"GB",
    "wof:name":"BN3 4PB",
    "wof:placetype":"postalcode"
},
  "geometry": {"coordinates":[-0.20070038248758,50.83030329489817],"type":"Point"}
}