{
  "type": "Feature",
  "properties": {
    "iso:country":"GB",
    "wof:name":"S64 5UA",
    "wof:placetype":"postalcode"
},
  "geometry": {"coordinates":[-1.30863032585044,53.47567497204282],"type":"Point"}
}