{
  "type": "Feature",
  "properties": {
    "iso:country": "GB",
    "wof:name": "S64 5UA",
    "wof:placetype": "postalcode"
  },
  "geometry": {"coordinates":[-1.30863,53.475675],"type":"Point"}
}
