{
  "type": "Feature",
  "properties": {
    "iso:country":"GB",
    "wof:name":"SS8 8EH",
    "wof:placetype":"postalcode"
},
  "geometry": {"coordinates":[0.59754729209588,51.52911630069629],"type":"Point"}
}