{
  "type": "Feature",
  "properties": {
    "date:inception_lower": "1980-01-01",
    "date:inception_upper": "1980-01-01",
    "iso:country": "GB",
    "wof:name": "SS8 8EH",
    "wof:placetype": "postalcode"
  },
  "geometry": {"coordinates":[0.597547,51.529116],"type":"Point"}
}
