{
  "type": "Feature",
  "properties": {
    "iso:country":"GB",
    "wof:name":"G65 0TA",
    "wof:placetype":"postalcode"
},
  "geometry": {"coordinates":[-4.05673645794643,55.96956622834416],"type":"Point"}
}