{
  "type": "Feature",
  "properties": {
    "iso:country":"GB",
    "wof:name":"DE7 9JF",
    "wof:placetype":"postalcode"
},
  "geometry": {"coordinates":[-1.32371161960459,52.98593317647885],"type":"Point"}
}