{
  "type": "Feature",
  "properties": {
    "date:inception_lower": "1980-01-01",
    "date:inception_upper": "1980-01-01",
    "iso:country": "GB",
    "wof:name": "ME12 1LF",
    "wof:placetype": "postalcode"
  },
  "geometry": {"coordinates":[0.747546,51.428226],"type":"Point"}
}
