{
  "type": "Feature",
  "properties": {
    "iso:country": "GB",
    "wof:name": "WA4 6LN",
    "wof:placetype": "postalcode"
  },
  "geometry": {"coordinates":[-2.585013,53.366324],"type":"Point"}
}
