{
  "type": "Feature",
  "properties": {
    "iso:country":"GB",
    "wof:name":"WA4 6LN",
    "wof:placetype":"postalcode"
},
  "geometry": {"coordinates":[-2.58499906565915,53.36629989487249],"type":"Point"}
}