{
  "type": "Feature",
  "properties": {
    "iso:country": "GB",
    "wof:name": "WA4 6LN",
    "wof:placetype": "postalcode"
  },
  "geometry": {"coordinates":[-2.584999,53.3663],"type":"Point"}
}
