{
  "type": "Feature",
  "properties": {
    "iso:country": "GB",
    "wof:name": "OX26 1TW",
    "wof:placetype": "postalcode"
  },
  "geometry": {"coordinates":[-1.211162,51.888125],"type":"Point"}
}
