{
  "type": "Feature",
  "properties": {
    "iso:country":"GB",
    "wof:name":"OX26 1TW",
    "wof:placetype":"postalcode"
},
  "geometry": {"coordinates":[-1.21116241338319,51.88812471491764],"type":"Point"}
}