{
  "type": "Feature",
  "properties": {
    "iso:country": "GB",
    "wof:name": "PE9 3NX",
    "wof:placetype": "postalcode"
  },
  "geometry": {"coordinates":[-0.511882,52.623429],"type":"Point"}
}
