{
  "type": "Feature",
  "properties": {
    "iso:country":"GB",
    "wof:name":"CB4 1QJ",
    "wof:placetype":"postalcode"
},
  "geometry": {"coordinates":[0.14471806183203,52.21967772298746],"type":"Point"}
}