{
  "type": "Feature",
  "properties": {
    "iso:country":"GB",
    "wof:name":"BS34 8SW",
    "wof:placetype":"postalcode"
},
  "geometry": {"coordinates":[-2.54780519248735,51.51202893609513],"type":"Point"}
}