{
  "type": "Feature",
  "properties": {
    "iso:country":"GB",
    "wof:name":"SE25 6NZ",
    "wof:placetype":"postalcode"
},
  "geometry": {"coordinates":[-0.08971710852157,51.39655313371207],"type":"Point"}
}