{
  "type": "Feature",
  "properties": {
    "iso:country":"GB",
    "wof:name":"EH6 6DJ",
    "wof:placetype":"postalcode"
},
  "geometry": {"coordinates":[-3.17222175391768,55.97388508813553],"type":"Point"}
}