{
  "type": "Feature",
  "properties": {
    "iso:country": "GB",
    "wof:name": "DD10 8HP",
    "wof:placetype": "postalcode"
  },
  "geometry": {"coordinates":[-2.465167,56.706417],"type":"Point"}
}
