{
  "type": "Feature",
  "properties": {
    "iso:country":"GB",
    "wof:name":"W9 2EQ",
    "wof:placetype":"postalcode"
},
  "geometry": {"coordinates":[-0.19276018574,51.52589942528123],"type":"Point"}
}