{
  "type": "Feature",
  "properties": {
    "date:inception_lower": "1980-01-01",
    "date:inception_upper": "1980-01-01",
    "iso:country": "GB",
    "wof:name": "W9 2EQ",
    "wof:placetype": "postalcode"
  },
  "geometry": {"coordinates":[-0.19276,51.525899],"type":"Point"}
}
