{
  "type": "Feature",
  "properties": {
    "date:inception_lower": "1980-01-01",
    "date:inception_upper": "1980-01-01",
    "iso:country": "GB",
    "wof:name": "CM9 6BZ",
    "wof:placetype": "postalcode"
  },
  "geometry": {"coordinates":[0.681501,51.720812],"type":"Point"}
}
