{
  "type": "Feature",
  "properties": {
    "iso:country":"GB",
    "wof:name":"CM9 6BZ",
    "wof:placetype":"postalcode"
},
  "geometry": {"coordinates":[0.68150125746251,51.72081203913962],"type":"Point"}
}