{
  "type": "Feature",
  "properties": {
    "iso:country": "GB",
    "wof:name": "CM9 6BZ",
    "wof:placetype": "postalcode"
  },
  "geometry": {"coordinates":[0.681501,51.720812],"type":"Point"}
}
