{
  "type": "Feature",
  "properties": {
    "iso:country":"GB",
    "wof:name":"PO21 5RS",
    "wof:placetype":"postalcode"
},
  "geometry": {"coordinates":[-0.70140912065249,50.79090576812114],"type":"Point"}
}