{
  "type": "Feature",
  "properties": {
    "iso:country":"GB",
    "wof:name":"NP7 9UB",
    "wof:placetype":"postalcode"
},
  "geometry": {"coordinates":[-2.91418150006269,51.81134617248117],"type":"Point"}
}