{
  "type": "Feature",
  "properties": {
    "date:inception_lower":"1980-01-01",
    "date:inception_upper":"1980-01-31",
    "iso:country":"GB",
    "wof:name":"NP7 9UB",
    "wof:placetype":"postalcode"
},
  "geometry": {"coordinates":[-2.914181,51.811346],"type":"Point"}
}