{
  "type": "Feature",
  "properties": {
    "iso:country": "GB",
    "wof:name": "NP7 9UB",
    "wof:placetype": "postalcode"
  },
  "geometry": {"coordinates":[-2.914181,51.811346],"type":"Point"}
}
