{
  "type": "Feature",
  "properties": {
    "iso:country":"GB",
    "wof:name":"HP10 0PG",
    "wof:placetype":"postalcode"
},
  "geometry": {"coordinates":[-0.6939708096844,51.58191524891151],"type":"Point"}
}