{
  "type": "Feature",
  "properties": {
    "iso:country": "GB",
    "wof:name": "HP10 0PG",
    "wof:placetype": "postalcode"
  },
  "geometry": {"coordinates":[-0.693971,51.581915],"type":"Point"}
}
