{
  "type": "Feature",
  "properties": {
    "iso:country": "GB",
    "wof:name": "CM6 3NT",
    "wof:placetype": "postalcode"
  },
  "geometry": {"coordinates":[0.462158,51.851409],"type":"Point"}
}
