{
  "type": "Feature",
  "properties": {
    "date:inception_lower": "1980-01-01",
    "date:inception_upper": "1980-01-01",
    "iso:country": "GB",
    "wof:name": "SE9 5BH",
    "wof:placetype": "postalcode"
  },
  "geometry": {"coordinates":[0.06072,51.448932],"type":"Point"}
}
