{
  "type": "Feature",
  "properties": {
    "iso:country":"GB",
    "wof:name":"SE9 5BH",
    "wof:placetype":"postalcode"
},
  "geometry": {"coordinates":[0.06072033937627,51.4489323543911],"type":"Point"}
}