{
  "type": "Feature",
  "properties": {
    "date:inception_lower":"1983-01-01",
    "date:inception_upper":"1983-01-31",
    "iso:country":"GB",
    "wof:name":"LS14 2EN",
    "wof:placetype":"postalcode"
},
  "geometry": {"coordinates":[-1.452932,53.835217],"type":"Point"}
}