{
  "type": "Feature",
  "properties": {
    "iso:country":"GB",
    "wof:name":"LS14 2EN",
    "wof:placetype":"postalcode"
},
  "geometry": {"coordinates":[-1.45293218239325,53.83521695227915],"type":"Point"}
}