{
  "type": "Feature",
  "properties": {
    "date:inception_lower": "2021-10-01",
    "date:inception_upper": "2021-10-01",
    "iso:country": "GB",
    "wof:name": "CT1 3ZR",
    "wof:placetype": "postalcode"
  },
  "geometry": {"coordinates":[1.05835,51.265262],"type":"Point"}
}
