{
  "type": "Feature",
  "properties": {
    "iso:country":"GB",
    "wof:name":"BS3 3BX",
    "wof:placetype":"postalcode"
},
  "geometry": {"coordinates":[-2.60311793649619,51.43941994612381],"type":"Point"}
}