{
  "type": "Feature",
  "properties": {
    "iso:country":"GB",
    "wof:name":"G31 2SN",
    "wof:placetype":"postalcode"
},
  "geometry": {"coordinates":[-4.21240078282359,55.85942614941631],"type":"Point"}
}