{
  "type": "Feature",
  "properties": {
    "iso:country":"GB",
    "wof:name":"S75 1DD",
    "wof:placetype":"postalcode"
},
  "geometry": {"coordinates":[-1.48487814850929,53.56423787953477],"type":"Point"}
}