{
  "type": "Feature",
  "properties": {
    "date:inception_lower": "1980-01-01",
    "date:inception_upper": "1980-01-01",
    "iso:country": "GB",
    "wof:name": "W5 2SY",
    "wof:placetype": "postalcode"
  },
  "geometry": {"coordinates":[-0.311671,51.513752],"type":"Point"}
}
