{
  "type": "Feature",
  "properties": {
    "iso:country":"GB",
    "wof:name":"W5 2SY",
    "wof:placetype":"postalcode"
},
  "geometry": {"coordinates":[-0.31169321933052,51.51375132574232],"type":"Point"}
}