{
  "type": "Feature",
  "properties": {
    "iso:country":"GB",
    "wof:name":"HU2 8AW",
    "wof:placetype":"postalcode"
},
  "geometry": {"coordinates":[-0.33481589547803,53.7500660392717],"type":"Point"}
}