{
  "type": "Feature",
  "properties": {
    "date:inception_lower": "1980-01-01",
    "date:inception_upper": "1980-01-01",
    "iso:country": "GB",
    "wof:name": "HU2 8AW",
    "wof:placetype": "postalcode"
  },
  "geometry": {"coordinates":[-0.334816,53.750066],"type":"Point"}
}
