{
  "type": "Feature",
  "properties": {
    "iso:country":"GB",
    "wof:name":"WS7 9DT",
    "wof:placetype":"postalcode"
},
  "geometry": {"coordinates":[-1.88931722317122,52.68053629270619],"type":"Point"}
}