{
  "type": "Feature",
  "properties": {
    "date:inception_lower": "1995-07-01",
    "date:inception_upper": "1995-07-01",
    "iso:country": "GB",
    "wof:name": "NW9 5JA",
    "wof:placetype": "postalcode"
  },
  "geometry": {"coordinates":[-0.245049,51.595925],"type":"Point"}
}
