{
  "type": "Feature",
  "properties": {
    "iso:country": "GB",
    "wof:name": "NW9 5JA",
    "wof:placetype": "postalcode"
  },
  "geometry": {"coordinates":[-0.245049,51.595925],"type":"Point"}
}
