{
  "type": "Feature",
  "properties": {
    "iso:country":"GB",
    "wof:name":"NW9 5JA",
    "wof:placetype":"postalcode"
},
  "geometry": {"coordinates":[-0.24504870274882,51.59592523933789],"type":"Point"}
}