{
  "type": "Feature",
  "properties": {
    "iso:country":"GB",
    "wof:name":"M27 8RD",
    "wof:placetype":"postalcode"
},
  "geometry": {"coordinates":[-2.32767916320504,53.5213835685316],"type":"Point"}
}