{
  "type": "Feature",
  "properties": {
    "iso:country": "GB",
    "wof:name": "IP24 2LQ",
    "wof:placetype": "postalcode"
  },
  "geometry": {"coordinates":[0.752748,52.41837],"type":"Point"}
}
