{
  "type": "Feature",
  "properties": {
    "iso:country": "GB",
    "wof:name": "HD9 3EP",
    "wof:placetype": "postalcode"
  },
  "geometry": {"coordinates":[-1.790054,53.579606],"type":"Point"}
}
