{
  "type": "Feature",
  "properties": {
    "date:inception_lower": "1980-01-01",
    "date:inception_upper": "1980-01-01",
    "iso:country": "GB",
    "wof:name": "BS4 2HF",
    "wof:placetype": "postalcode"
  },
  "geometry": {"coordinates":[-2.575327,51.43644],"type":"Point"}
}
