{
  "type": "Feature",
  "properties": {
    "date:inception_lower": "2019-09-01",
    "date:inception_upper": "2019-09-01",
    "iso:country": "GB",
    "wof:name": "EH26 0FU",
    "wof:placetype": "postalcode"
  },
  "geometry": {"coordinates":[-3.224722,55.845677],"type":"Point"}
}
