{
  "type": "Feature",
  "properties": {
    "iso:country": "GB",
    "wof:name": "EH26 0FU",
    "wof:placetype": "postalcode"
  },
  "geometry": {"coordinates":[-3.22459,55.845552],"type":"Point"}
}
