{
  "type": "Feature",
  "properties": {
    "iso:country": "GB",
    "wof:name": "SS8 9BT",
    "wof:placetype": "postalcode"
  },
  "geometry": {"coordinates":[0.587338,51.523788],"type":"Point"}
}
