{
  "type": "Feature",
  "properties": {
    "iso:country":"GB",
    "wof:name":"SS8 9BT",
    "wof:placetype":"postalcode"
},
  "geometry": {"coordinates":[0.58731046127996,51.52378464450734],"type":"Point"}
}