{
  "type": "Feature",
  "properties": {
    "iso:country": "GB",
    "wof:name": "DA12 4PT",
    "wof:placetype": "postalcode"
  },
  "geometry": {"coordinates":[0.399847,51.415373],"type":"Point"}
}
