{
  "type": "Feature",
  "properties": {
    "iso:country":"GB",
    "wof:name":"DA12 4PT",
    "wof:placetype":"postalcode"
},
  "geometry": {"coordinates":[0.39984724319904,51.41537313560904],"type":"Point"}
}