{
  "type": "Feature",
  "properties": {
    "iso:country":"GB",
    "wof:name":"SN10 4SA",
    "wof:placetype":"postalcode"
},
  "geometry": {"coordinates":[-1.93782254214018,51.31543278379801],"type":"Point"}
}