{
  "type": "Feature",
  "properties": {
    "iso:country":"GB",
    "wof:name":"SN10 3DP",
    "wof:placetype":"postalcode"
},
  "geometry": {"coordinates":[-1.97947383200832,51.35198075572767],"type":"Point"}
}