{
  "type": "Feature",
  "properties": {
    "iso:country": "GB",
    "wof:name": "CV34 6FQ",
    "wof:placetype": "postalcode"
  },
  "geometry": {"coordinates":[-1.542103,52.269153],"type":"Point"}
}
