{
  "type": "Feature",
  "properties": {
    "date:inception_lower": "2001-12-01",
    "date:inception_upper": "2001-12-01",
    "iso:country": "GB",
    "wof:name": "RH10 1SS",
    "wof:placetype": "postalcode"
  },
  "geometry": {"coordinates":[-0.180087,51.113666],"type":"Point"}
}
