{
  "type": "Feature",
  "properties": {
    "iso:country": "GB",
    "wof:name": "DH9 7DR",
    "wof:placetype": "postalcode"
  },
  "geometry": {"coordinates":[-1.709004,54.859713],"type":"Point"}
}
