{
  "type": "Feature",
  "properties": {
    "iso:country":"GB",
    "wof:name":"HP5 2DS",
    "wof:placetype":"postalcode"
},
  "geometry": {"coordinates":[-0.61756912303972,51.71999107004843],"type":"Point"}
}