{
  "type": "Feature",
  "properties": {
    "iso:country": "GB",
    "wof:name": "HP5 2DS",
    "wof:placetype": "postalcode"
  },
  "geometry": {"coordinates":[-0.617569,51.719991],"type":"Point"}
}
