{
  "type": "Feature",
  "properties": {
    "iso:country":"GB",
    "wof:name":"CM3 6DG",
    "wof:placetype":"postalcode"
},
  "geometry": {"coordinates":[0.75297182146464,51.64805517388966],"type":"Point"}
}