{
  "type": "Feature",
  "properties": {
    "iso:country":"GB",
    "wof:name":"RG19 4JR",
    "wof:placetype":"postalcode"
},
  "geometry": {"coordinates":[-1.25308661838757,51.40306864377442],"type":"Point"}
}