{
  "type": "Feature",
  "properties": {
    "iso:country":"GB",
    "wof:name":"SW11 6LT",
    "wof:placetype":"postalcode"
},
  "geometry": {"coordinates":[-0.16008218692663,51.45712923450132],"type":"Point"}
}