{
  "type": "Feature",
  "properties": {
    "date:inception_lower": "1980-01-01",
    "date:inception_upper": "1980-01-01",
    "iso:country": "GB",
    "wof:name": "SW11 6LT",
    "wof:placetype": "postalcode"
  },
  "geometry": {"coordinates":[-0.160082,51.457129],"type":"Point"}
}
