{
  "type": "Feature",
  "properties": {
    "iso:country":"GB",
    "wof:name":"B95 5AN",
    "wof:placetype":"postalcode"
},
  "geometry": {"coordinates":[-1.77913607137197,52.29483888813522],"type":"Point"}
}