{
  "type": "Feature",
  "properties": {
    "iso:country": "GB",
    "wof:name": "B95 5AN",
    "wof:placetype": "postalcode"
  },
  "geometry": {"coordinates":[-1.779112,52.29489],"type":"Point"}
}
