{
  "type": "Feature",
  "properties": {
    "iso:country":"GB",
    "wof:name":"SY10 9DA",
    "wof:placetype":"postalcode"
},
  "geometry": {"coordinates":[-3.09660807031213,52.83371830059247],"type":"Point"}
}