{
  "type": "Feature",
  "properties": {
    "date:inception_lower":"1990-07-01",
    "date:inception_upper":"1990-07-31",
    "iso:country":"GB",
    "wof:name":"SY10 9DA",
    "wof:placetype":"postalcode"
},
  "geometry": {"coordinates":[-3.096608,52.833718],"type":"Point"}
}