{
  "type": "Feature",
  "properties": {
    "iso:country":"GB",
    "wof:name":"EX8 2BJ",
    "wof:placetype":"postalcode"
},
  "geometry": {"coordinates":[-3.40674643970999,50.61650761153369],"type":"Point"}
}