{
  "type": "Feature",
  "properties": {
    "date:inception_lower": "1980-01-01",
    "date:inception_upper": "1980-01-01",
    "iso:country": "GB",
    "wof:name": "EX8 2BJ",
    "wof:placetype": "postalcode"
  },
  "geometry": {"coordinates":[-3.406857,50.616431],"type":"Point"}
}
