{
  "type": "Feature",
  "properties": {
    "iso:country":"GB",
    "wof:name":"WV2 2NE",
    "wof:placetype":"postalcode"
},
  "geometry": {"coordinates":[-2.10171761205706,52.57045550598146],"type":"Point"}
}