{
  "type": "Feature",
  "properties": {
    "iso:country": "GB",
    "wof:name": "PE14 0BY",
    "wof:placetype": "postalcode"
  },
  "geometry": {"coordinates":[0.167368,52.640605],"type":"Point"}
}
