{
  "type": "Feature",
  "properties": {
    "date:inception_lower": "2022-02-01",
    "date:inception_upper": "2022-02-01",
    "iso:country": "GB",
    "wof:name": "YO42 2TZ",
    "wof:placetype": "postalcode"
  },
  "geometry": {"coordinates":[-0.778322,53.920283],"type":"Point"}
}
