{
  "type": "Feature",
  "properties": {
    "iso:country":"GB",
    "wof:name":"KT16 0RE",
    "wof:placetype":"postalcode"
},
  "geometry": {"coordinates":[-0.53277185566017,51.3564835870427],"type":"Point"}
}