{
  "type": "Feature",
  "properties": {
    "iso:country":"GB",
    "wof:name":"ST6 4NJ",
    "wof:placetype":"postalcode"
},
  "geometry": {"coordinates":[-2.21314969804637,53.04148155573199],"type":"Point"}
}