{
  "type": "Feature",
  "properties": {
    "date:inception_lower": "2022-11-01",
    "date:inception_upper": "2022-11-01",
    "iso:country": "GB",
    "wof:name": "BS2 9AW",
    "wof:placetype": "postalcode"
  },
  "geometry": {"coordinates":[-2.584346,51.459862],"type":"Point"}
}
