{
  "type": "Feature",
  "properties": {
    "iso:country": "GB",
    "wof:name": "OL12 0BF",
    "wof:placetype": "postalcode"
  },
  "geometry": {"coordinates":[-2.156704,53.62417],"type":"Point"}
}
