{
  "type": "Feature",
  "properties": {
    "date:inception_lower":"2014-05-01",
    "date:inception_upper":"2014-05-31",
    "iso:country":"GB",
    "wof:name":"OL12 0BF",
    "wof:placetype":"postalcode"
},
  "geometry": {"coordinates":[-2.156704,53.62417],"type":"Point"}
}