{
  "type": "Feature",
  "properties": {
    "iso:country":"GB",
    "wof:name":"OX3 7PS",
    "wof:placetype":"postalcode"
},
  "geometry": {"coordinates":[-1.22164212751064,51.75654588571432],"type":"Point"}
}