{
  "type": "Feature",
  "properties": {
    "iso:country":"GB",
    "wof:name":"SW16 5SY",
    "wof:placetype":"postalcode"
},
  "geometry": {"coordinates":[-0.14327970290142,51.41288146415568],"type":"Point"}
}