{
  "type": "Feature",
  "properties": {
    "iso:country":"GB",
    "wof:name":"BN22 0ES",
    "wof:placetype":"postalcode"
},
  "geometry": {"coordinates":[0.26076025109032,50.79864595003153],"type":"Point"}
}