{
  "type": "Feature",
  "properties": {
    "iso:country":"GB",
    "wof:name":"RG18 9UJ",
    "wof:placetype":"postalcode"
},
  "geometry": {"coordinates":[-1.24705465033012,51.45085717020705],"type":"Point"}
}