{
  "type": "Feature",
  "properties": {
    "date:inception_lower":"1995-07-01",
    "date:inception_upper":"1995-07-31",
    "iso:country":"GB",
    "wof:name":"RG18 9UJ",
    "wof:placetype":"postalcode"
},
  "geometry": {"coordinates":[-1.247055,51.450857],"type":"Point"}
}