{
  "type": "Feature",
  "properties": {
    "iso:country": "GB",
    "wof:name": "NE66 3FD",
    "wof:placetype": "postalcode"
  },
  "geometry": {"coordinates":[-1.621305,55.429608],"type":"Point"}
}
