{
  "type": "Feature",
  "properties": {
    "iso:country":"GB",
    "wof:name":"S42 6AZ",
    "wof:placetype":"postalcode"
},
  "geometry": {"coordinates":[-1.45333993611792,53.18357875145118],"type":"Point"}
}