{
  "type": "Feature",
  "properties": {
    "iso:country": "GB",
    "wof:name": "S42 6AZ",
    "wof:placetype": "postalcode"
  },
  "geometry": {"coordinates":[-1.45334,53.183579],"type":"Point"}
}
