{
  "type": "Feature",
  "properties": {
    "iso:country": "GB",
    "wof:name": "CW11 1PA",
    "wof:placetype": "postalcode"
  },
  "geometry": {"coordinates":[-2.382443,53.158886],"type":"Point"}
}
