{
  "type": "Feature",
  "properties": {
    "date:inception_lower": "1995-12-01",
    "date:inception_upper": "1995-12-01",
    "iso:country": "GB",
    "wof:name": "CW11 1PA",
    "wof:placetype": "postalcode"
  },
  "geometry": {"coordinates":[-2.382443,53.158886],"type":"Point"}
}
