{
  "type": "Feature",
  "properties": {
    "iso:country":"GB",
    "wof:name":"CW11 1PA",
    "wof:placetype":"postalcode"
},
  "geometry": {"coordinates":[-2.3824434277572,53.15888611690835],"type":"Point"}
}