{
  "type": "Feature",
  "properties": {
    "iso:country":"GB",
    "wof:name":"WA3 2LJ",
    "wof:placetype":"postalcode"
},
  "geometry": {"coordinates":[-2.57023100351389,53.47455883602544],"type":"Point"}
}