{
  "type": "Feature",
  "properties": {
    "iso:country":"GB",
    "wof:name":"CV3 4DL",
    "wof:placetype":"postalcode"
},
  "geometry": {"coordinates":[-1.47135121311424,52.38104166692245],"type":"Point"}
}