{
  "type": "Feature",
  "properties": {
    "iso:country": "GB",
    "wof:name": "CV3 4DL",
    "wof:placetype": "postalcode"
  },
  "geometry": {"coordinates":[-1.471351,52.381042],"type":"Point"}
}
