{
  "type": "Feature",
  "properties": {
    "date:inception_lower": "1996-06-01",
    "date:inception_upper": "1996-06-01",
    "iso:country": "GB",
    "wof:name": "CW2 8UU",
    "wof:placetype": "postalcode"
  },
  "geometry": {"coordinates":[-2.476648,53.088683],"type":"Point"}
}
