{
  "type": "Feature",
  "properties": {
    "iso:country": "GB",
    "wof:name": "CW2 8UU",
    "wof:placetype": "postalcode"
  },
  "geometry": {"coordinates":[-2.476648,53.088683],"type":"Point"}
}
