{
  "type": "Feature",
  "properties": {
    "iso:country":"GB",
    "wof:name":"LE67 3HS",
    "wof:placetype":"postalcode"
},
  "geometry": {"coordinates":[-1.39319950163997,52.71433877627118],"type":"Point"}
}