{
  "type": "Feature",
  "properties": {
    "date:inception_lower": "1980-01-01",
    "date:inception_upper": "1980-01-01",
    "iso:country": "GB",
    "wof:name": "TQ7 4LD",
    "wof:placetype": "postalcode"
  },
  "geometry": {"coordinates":[-3.835766,50.314976],"type":"Point"}
}
