{
  "type": "Feature",
  "properties": {
    "date:inception_lower":"1980-01-01",
    "date:inception_upper":"1980-01-31",
    "iso:country":"GB",
    "wof:name":"SK7 1QN",
    "wof:placetype":"postalcode"
},
  "geometry": {"coordinates":[-2.152961,53.341488],"type":"Point"}
}