{
  "type": "Feature",
  "properties": {
    "iso:country":"GB",
    "wof:name":"SK7 1QN",
    "wof:placetype":"postalcode"
},
  "geometry": {"coordinates":[-2.15296081621655,53.34148835665095],"type":"Point"}
}