{
  "type": "Feature",
  "properties": {
    "iso:country": "GB",
    "wof:name": "DA12 1LY",
    "wof:placetype": "postalcode"
  },
  "geometry": {"coordinates":[0.378278,51.436776],"type":"Point"}
}
