{
  "type": "Feature",
  "properties": {
    "iso:country":"GB",
    "wof:name":"DA12 1LY",
    "wof:placetype":"postalcode"
},
  "geometry": {"coordinates":[0.378277627907,51.43677632504093],"type":"Point"}
}