{
  "type": "Feature",
  "properties": {
    "date:inception_lower": "1980-01-01",
    "date:inception_upper": "1980-01-01",
    "iso:country": "GB",
    "wof:name": "TA3 6PZ",
    "wof:placetype": "postalcode"
  },
  "geometry": {"coordinates":[-2.902771,51.005836],"type":"Point"}
}
