{
  "type": "Feature",
  "properties": {
    "date:inception_lower":"2017-08-01",
    "date:inception_upper":"2017-08-31",
    "iso:country":"GB",
    "wof:name":"RG24 4ES",
    "wof:placetype":"postalcode"
},
  "geometry": {"coordinates":[-1.083746,51.261943],"type":"Point"}
}