{
  "type": "Feature",
  "properties": {
    "iso:country": "GB",
    "wof:name": "RG24 4ES",
    "wof:placetype": "postalcode"
  },
  "geometry": {"coordinates":[-1.083746,51.261943],"type":"Point"}
}
