{
  "type": "Feature",
  "properties": {
    "iso:country": "GB",
    "wof:name": "ME2 3ER",
    "wof:placetype": "postalcode"
  },
  "geometry": {"coordinates":[0.486426,51.39755],"type":"Point"}
}
