{
  "type": "Feature",
  "properties": {
    "iso:country":"GB",
    "wof:name":"G81 1UF",
    "wof:placetype":"postalcode"
},
  "geometry": {"coordinates":[-4.41820628567071,55.90355616569821],"type":"Point"}
}