{
  "type": "Feature",
  "properties": {
    "date:inception_lower":"1992-08-01",
    "date:inception_upper":"1992-08-31",
    "iso:country":"GB",
    "wof:name":"DE22 4BG",
    "wof:placetype":"postalcode"
},
  "geometry": {"coordinates":[-1.518172,52.928323],"type":"Point"}
}