{
  "type": "Feature",
  "properties": {
    "date:inception_lower": "2022-06-01",
    "date:inception_upper": "2022-06-01",
    "iso:country": "GB",
    "wof:name": "CW2 8GU",
    "wof:placetype": "postalcode"
  },
  "geometry": {"coordinates":[-2.476163,53.08276],"type":"Point"}
}
