{
  "type": "Feature",
  "properties": {
    "date:inception_lower": "1980-01-01",
    "date:inception_upper": "1980-01-01",
    "iso:country": "GB",
    "wof:name": "BD4 6LD",
    "wof:placetype": "postalcode"
  },
  "geometry": {"coordinates":[-1.72495,53.76473],"type":"Point"}
}
