{
  "type": "Feature",
  "properties": {
    "iso:country":"GB",
    "wof:name":"DT9 6NU",
    "wof:placetype":"postalcode"
},
  "geometry": {"coordinates":[-2.56556845395352,50.87253910772466],"type":"Point"}
}