{
  "type": "Feature",
  "properties": {
    "date:inception_lower": "1980-01-01",
    "date:inception_upper": "1980-01-01",
    "iso:country": "GB",
    "wof:name": "LA14 2BA",
    "wof:placetype": "postalcode"
  },
  "geometry": {"coordinates":[-3.21461,54.110082],"type":"Point"}
}
