{
  "type": "Feature",
  "properties": {
    "date:inception_lower":"1987-04-01",
    "date:inception_upper":"1987-04-30",
    "iso:country":"GB",
    "wof:name":"PO34 5LH",
    "wof:placetype":"postalcode"
},
  "geometry": {"coordinates":[-1.109804,50.712333],"type":"Point"}
}