{
  "type": "Feature",
  "properties": {
    "iso:country":"GB",
    "wof:name":"PO34 5LH",
    "wof:placetype":"postalcode"
},
  "geometry": {"coordinates":[-1.10978672998464,50.71235294928807],"type":"Point"}
}