{
  "type": "Feature",
  "properties": {
    "iso:country":"GB",
    "wof:name":"CM3 1EB",
    "wof:placetype":"postalcode"
},
  "geometry": {"coordinates":[0.42954208656764,51.78585447674333],"type":"Point"}
}