{
  "type": "Feature",
  "properties": {
    "iso:country":"GB",
    "wof:name":"KA1 2RS",
    "wof:placetype":"postalcode"
},
  "geometry": {"coordinates":[-4.53164228363712,55.60284690419586],"type":"Point"}
}