{
  "type": "Feature",
  "properties": {
    "iso:country": "GB",
    "wof:name": "OX4 9ZY",
    "wof:placetype": "postalcode"
  },
  "geometry": {"coordinates":[-1.213389,51.722617],"type":"Point"}
}
