{
  "type": "Feature",
  "properties": {
    "date:inception_lower": "1990-02-01",
    "date:inception_upper": "1990-02-01",
    "iso:country": "GB",
    "wof:name": "LE15 9SS",
    "wof:placetype": "postalcode"
  },
  "geometry": {"coordinates":[-0.730028,52.59265],"type":"Point"}
}
