{
  "type": "Feature",
  "properties": {
    "iso:country":"GB",
    "wof:name":"LE15 9SS",
    "wof:placetype":"postalcode"
},
  "geometry": {"coordinates":[-0.7300285070967,52.59264962538983],"type":"Point"}
}