{
  "type": "Feature",
  "properties": {
    "iso:country": "GB",
    "wof:name": "LE15 9SS",
    "wof:placetype": "postalcode"
  },
  "geometry": {"coordinates":[-0.730028,52.59265],"type":"Point"}
}
