{
  "type": "Feature",
  "properties": {
    "iso:country": "GB",
    "wof:name": "MK44 2AB",
    "wof:placetype": "postalcode"
  },
  "geometry": {"coordinates":[-0.444535,52.281604],"type":"Point"}
}
