{
  "type": "Feature",
  "properties": {
    "iso:country":"GB",
    "wof:name":"MK44 2AB",
    "wof:placetype":"postalcode"
},
  "geometry": {"coordinates":[-0.44453481052883,52.28160360859914],"type":"Point"}
}