{
  "type": "Feature",
  "properties": {
    "iso:country": "GB",
    "wof:name": "CH7 3FH",
    "wof:placetype": "postalcode"
  },
  "geometry": {"coordinates":[-3.066917,53.17622],"type":"Point"}
}
