{
  "type": "Feature",
  "properties": {
    "iso:country":"GB",
    "wof:name":"OX3 0LY",
    "wof:placetype":"postalcode"
},
  "geometry": {"coordinates":[-1.23134675992129,51.76777685535667],"type":"Point"}
}