{
  "type": "Feature",
  "properties": {
    "date:inception_lower":"1980-01-01",
    "date:inception_upper":"1980-01-31",
    "iso:country":"GB",
    "wof:name":"OX3 0LY",
    "wof:placetype":"postalcode"
},
  "geometry": {"coordinates":[-1.231347,51.767777],"type":"Point"}
}