{
  "type": "Feature",
  "properties": {
    "iso:country":"GB",
    "wof:name":"NR25 6SP",
    "wof:placetype":"postalcode"
},
  "geometry": {"coordinates":[1.09033833195249,52.89844846507845],"type":"Point"}
}