{
  "type": "Feature",
  "properties": {
    "iso:country":"GB",
    "wof:name":"NG22 0TZ",
    "wof:placetype":"postalcode"
},
  "geometry": {"coordinates":[-0.78120504548943,53.26136529187852],"type":"Point"}
}