{
  "type": "Feature",
  "properties": {
    "iso:country":"GB",
    "wof:name":"PL9 9QP",
    "wof:placetype":"postalcode"
},
  "geometry": {"coordinates":[-4.10648969504781,50.35225327068147],"type":"Point"}
}