{
  "type": "Feature",
  "properties": {
    "iso:country": "GB",
    "wof:name": "NE3 4UB",
    "wof:placetype": "postalcode"
  },
  "geometry": {"coordinates":[-1.655282,54.999606],"type":"Point"}
}
