{
  "type": "Feature",
  "properties": {
    "date:inception_lower": "2024-02-01",
    "date:inception_upper": "2024-02-01",
    "iso:country": "GB",
    "wof:name": "EX1 4BZ",
    "wof:placetype": "postalcode"
  },
  "geometry": {"coordinates":[-3.463314,50.741545],"type":"Point"}
}
