{
  "type": "Feature",
  "properties": {
    "iso:country": "GB",
    "wof:name": "LU2 0JF",
    "wof:placetype": "postalcode"
  },
  "geometry": {"coordinates":[-0.40062,51.883398],"type":"Point"}
}
