{
  "type": "Feature",
  "properties": {
    "iso:country":"GB",
    "wof:name":"LU2 0JF",
    "wof:placetype":"postalcode"
},
  "geometry": {"coordinates":[-0.40061980289958,51.88339834615405],"type":"Point"}
}