{
  "type": "Feature",
  "properties": {
    "iso:country": "GB",
    "wof:name": "GU32 1HQ",
    "wof:placetype": "postalcode"
  },
  "geometry": {"coordinates":[-1.04888,50.984999],"type":"Point"}
}
