{
  "type": "Feature",
  "properties": {
    "iso:country":"GB",
    "wof:name":"GU32 1HQ",
    "wof:placetype":"postalcode"
},
  "geometry": {"coordinates":[-1.04887958733989,50.9849990434308],"type":"Point"}
}