{
  "type": "Feature",
  "properties": {
    "iso:country":"GB",
    "wof:name":"GL4 0PJ",
    "wof:placetype":"postalcode"
},
  "geometry": {"coordinates":[-2.25633505212949,51.82965440644285],"type":"Point"}
}