{
  "type": "Feature",
  "properties": {
    "iso:country":"GB",
    "wof:name":"NP25 5EH",
    "wof:placetype":"postalcode"
},
  "geometry": {"coordinates":[-2.72717917401042,51.80524290113745],"type":"Point"}
}