{
  "type": "Feature",
  "properties": {
    "date:inception_lower": "2011-09-01",
    "date:inception_upper": "2011-09-01",
    "iso:country": "GB",
    "wof:name": "DY13 9FF",
    "wof:placetype": "postalcode"
  },
  "geometry": {"coordinates":[-2.278196,52.337384],"type":"Point"}
}
