{
  "type": "Feature",
  "properties": {
    "iso:country":"GB",
    "wof:name":"DY13 9FF",
    "wof:placetype":"postalcode"
},
  "geometry": {"coordinates":[-2.27819644266704,52.33738430528606],"type":"Point"}
}