{
  "type": "Feature",
  "properties": {
    "iso:country": "GB",
    "wof:name": "DY13 9FF",
    "wof:placetype": "postalcode"
  },
  "geometry": {"coordinates":[-2.278196,52.337384],"type":"Point"}
}
