{
  "type": "Feature",
  "properties": {
    "iso:country":"GB",
    "wof:name":"CR2 7RE",
    "wof:placetype":"postalcode"
},
  "geometry": {"coordinates":[-0.06305103025039,51.35161005518722],"type":"Point"}
}