{
  "type": "Feature",
  "properties": {
    "iso:country":"GB",
    "wof:name":"SS5 4QU",
    "wof:placetype":"postalcode"
},
  "geometry": {"coordinates":[0.65362057013102,51.60094231254291],"type":"Point"}
}