{
  "type": "Feature",
  "properties": {
    "date:inception_lower": "1980-01-01",
    "date:inception_upper": "1980-01-01",
    "iso:country": "GB",
    "wof:name": "SS5 4QU",
    "wof:placetype": "postalcode"
  },
  "geometry": {"coordinates":[0.653621,51.600942],"type":"Point"}
}
