{
  "type": "Feature",
  "properties": {
    "date:inception_lower":"2015-09-01",
    "date:inception_upper":"2015-09-30",
    "iso:country":"GB",
    "wof:name":"NN6 9TR",
    "wof:placetype":"postalcode"
},
  "geometry": {"coordinates":[-0.812985,52.329186],"type":"Point"}
}