{
  "type": "Feature",
  "properties": {
    "iso:country": "GB",
    "wof:name": "NN6 9TR",
    "wof:placetype": "postalcode"
  },
  "geometry": {"coordinates":[-0.812985,52.329186],"type":"Point"}
}
