{
  "type": "Feature",
  "properties": {
    "iso:country": "GB",
    "wof:name": "WF11 8NZ",
    "wof:placetype": "postalcode"
  },
  "geometry": {"coordinates":[-1.268334,53.712309],"type":"Point"}
}
