{
  "type": "Feature",
  "properties": {
    "iso:country":"GB",
    "wof:name":"WF11 8NZ",
    "wof:placetype":"postalcode"
},
  "geometry": {"coordinates":[-1.26833423673927,53.71230853403814],"type":"Point"}
}