{
  "type": "Feature",
  "properties": {
    "date:inception_lower": "1995-07-01",
    "date:inception_upper": "1995-07-01",
    "iso:country": "GB",
    "wof:name": "RG18 9EX",
    "wof:placetype": "postalcode"
  },
  "geometry": {"coordinates":[-1.274107,51.422866],"type":"Point"}
}
