{
  "type": "Feature",
  "properties": {
    "date:inception_lower": "1998-12-01",
    "date:inception_upper": "1998-12-01",
    "iso:country": "GB",
    "wof:name": "EC4V 4AY",
    "wof:placetype": "postalcode"
  },
  "geometry": {"coordinates":[-0.09444,51.511873],"type":"Point"}
}
