{
  "type": "Feature",
  "properties": {
    "iso:country":"GB",
    "wof:name":"EC4V 4AY",
    "wof:placetype":"postalcode"
},
  "geometry": {"coordinates":[-0.09482219170599,51.51197585746656],"type":"Point"}
}