{
  "type": "Feature",
  "properties": {
    "iso:country": "GB",
    "wof:name": "PA2 6FF",
    "wof:placetype": "postalcode"
  },
  "geometry": {"coordinates":[-4.420221,55.834175],"type":"Point"}
}
