{
  "type": "Feature",
  "properties": {
    "iso:country":"GB",
    "wof:name":"BS32 4HU",
    "wof:placetype":"postalcode"
},
  "geometry": {"coordinates":[-2.54950396979542,51.56215758984717],"type":"Point"}
}