{
  "type": "Feature",
  "properties": {
    "date:inception_lower": "1994-05-01",
    "date:inception_upper": "1994-05-01",
    "iso:country": "GB",
    "wof:name": "M44 6HA",
    "wof:placetype": "postalcode"
  },
  "geometry": {"coordinates":[-2.414376,53.455058],"type":"Point"}
}
