{
  "type": "Feature",
  "properties": {
    "iso:country":"GB",
    "wof:name":"M44 6HA",
    "wof:placetype":"postalcode"
},
  "geometry": {"coordinates":[-2.41437630673409,53.45505792446512],"type":"Point"}
}