{
  "type": "Feature",
  "properties": {
    "iso:country":"GB",
    "wof:name":"LL54 7HU",
    "wof:placetype":"postalcode"
},
  "geometry": {"coordinates":[-4.23356291102797,53.08883642966794],"type":"Point"}
}