{
  "type": "Feature",
  "properties": {
    "iso:country": "GB",
    "wof:name": "OL10 1EJ",
    "wof:placetype": "postalcode"
  },
  "geometry": {"coordinates":[-2.223397,53.59292],"type":"Point"}
}
