{
  "type": "Feature",
  "properties": {
    "iso:country": "GB",
    "wof:name": "RG41 5JR",
    "wof:placetype": "postalcode"
  },
  "geometry": {"coordinates":[-0.868545,51.434904],"type":"Point"}
}
