{
  "type": "Feature",
  "properties": {
    "iso:country":"GB",
    "wof:name":"BR3 1AJ",
    "wof:placetype":"postalcode"
},
  "geometry": {"coordinates":[-0.02880261173014,51.40604778215717],"type":"Point"}
}