{
  "type": "Feature",
  "properties": {
    "iso:country":"GB",
    "wof:name":"HA9 8QE",
    "wof:placetype":"postalcode"
},
  "geometry": {"coordinates":[-0.302383922713,51.56798435241849],"type":"Point"}
}