{
  "type": "Feature",
  "properties": {
    "iso:country": "GB",
    "wof:name": "CV3 2TG",
    "wof:placetype": "postalcode"
  },
  "geometry": {"coordinates":[-1.44586,52.401108],"type":"Point"}
}
