{
  "type": "Feature",
  "properties": {
    "iso:country":"GB",
    "wof:name":"CV3 2TG",
    "wof:placetype":"postalcode"
},
  "geometry": {"coordinates":[-1.44586038975929,52.40110797167756],"type":"Point"}
}