{
  "type": "Feature",
  "properties": {
    "date:inception_lower": "1980-01-01",
    "date:inception_upper": "1980-01-01",
    "iso:country": "GB",
    "wof:name": "NE9 6BX",
    "wof:placetype": "postalcode"
  },
  "geometry": {"coordinates":[-1.600587,54.936409],"type":"Point"}
}
