{
  "type": "Feature",
  "properties": {
    "date:inception_lower": "1980-01-01",
    "date:inception_upper": "1980-01-01",
    "iso:country": "GB",
    "wof:name": "LL31 9BA",
    "wof:placetype": "postalcode"
  },
  "geometry": {"coordinates":[-3.80087,53.28297],"type":"Point"}
}
