{
  "type": "Feature",
  "properties": {
    "iso:country": "GB",
    "wof:name": "NE28 6JB",
    "wof:placetype": "postalcode"
  },
  "geometry": {"coordinates":[-1.528089,54.991074],"type":"Point"}
}
