{
  "type": "Feature",
  "properties": {
    "iso:country":"GB",
    "wof:name":"NE28 6JB",
    "wof:placetype":"postalcode"
},
  "geometry": {"coordinates":[-1.5280889246777,54.99107400118513],"type":"Point"}
}