{
  "type": "Feature",
  "properties": {
    "date:inception_lower":"1980-01-01",
    "date:inception_upper":"1980-01-31",
    "iso:country":"GB",
    "wof:name":"NE28 6JB",
    "wof:placetype":"postalcode"
},
  "geometry": {"coordinates":[-1.528089,54.991074],"type":"Point"}
}