{
  "type": "Feature",
  "properties": {
    "iso:country":"GB",
    "wof:name":"ME9 7TP",
    "wof:placetype":"postalcode"
},
  "geometry": {"coordinates":[0.63588394592318,51.34366555835899],"type":"Point"}
}