{
  "type": "Feature",
  "properties": {
    "iso:country":"GB",
    "wof:name":"DD8 2RU",
    "wof:placetype":"postalcode"
},
  "geometry": {"coordinates":[-2.85806870851788,56.63222416688145],"type":"Point"}
}