{
  "type": "Feature",
  "properties": {
    "iso:country": "GB",
    "wof:name": "WS1 3DF",
    "wof:placetype": "postalcode"
  },
  "geometry": {"coordinates":[-1.978085,52.580998],"type":"Point"}
}
