{
  "type": "Feature",
  "properties": {
    "iso:country":"GB",
    "wof:name":"DY3 2HB",
    "wof:placetype":"postalcode"
},
  "geometry": {"coordinates":[-2.12839317212707,52.51989750259645],"type":"Point"}
}