{
  "type": "Feature",
  "properties": {
    "iso:country":"GB",
    "wof:name":"SW19 5HR",
    "wof:placetype":"postalcode"
},
  "geometry": {"coordinates":[-0.21737709141852,51.43296126807388],"type":"Point"}
}