{
  "type": "Feature",
  "properties": {
    "date:inception_lower": "1987-04-01",
    "date:inception_upper": "1987-04-01",
    "iso:country": "GB",
    "wof:name": "DH3 3QW",
    "wof:placetype": "postalcode"
  },
  "geometry": {"coordinates":[-1.571376,54.856466],"type":"Point"}
}
