{
  "type": "Feature",
  "properties": {
    "iso:country":"GB",
    "wof:name":"E7 9PQ",
    "wof:placetype":"postalcode"
},
  "geometry": {"coordinates":[0.02766214726904,51.54048834368975],"type":"Point"}
}