{
  "type": "Feature",
  "properties": {
    "date:inception_lower": "1980-01-01",
    "date:inception_upper": "1980-01-01",
    "iso:country": "GB",
    "wof:name": "NG33 5AU",
    "wof:placetype": "postalcode"
  },
  "geometry": {"coordinates":[-0.604837,52.828669],"type":"Point"}
}
