{
  "type": "Feature",
  "properties": {
    "iso:country":"GB",
    "wof:name":"NG33 5AU",
    "wof:placetype":"postalcode"
},
  "geometry": {"coordinates":[-0.60557320573003,52.828656988744],"type":"Point"}
}