{
  "type": "Feature",
  "properties": {
    "iso:country": "GB",
    "wof:name": "NG33 5AU",
    "wof:placetype": "postalcode"
  },
  "geometry": {"coordinates":[-0.605573,52.828657],"type":"Point"}
}
