{
  "type": "Feature",
  "properties": {
    "iso:country": "GB",
    "wof:name": "NG21 0AG",
    "wof:placetype": "postalcode"
  },
  "geometry": {"coordinates":[-1.119554,53.114494],"type":"Point"}
}
