{
  "type": "Feature",
  "properties": {
    "iso:country":"GB",
    "wof:name":"CT3 4JP",
    "wof:placetype":"postalcode"
},
  "geometry": {"coordinates":[1.15218425923082,51.33033419152164],"type":"Point"}
}