{
  "type": "Feature",
  "properties": {
    "iso:country": "GB",
    "wof:name": "CT3 4JP",
    "wof:placetype": "postalcode"
  },
  "geometry": {"coordinates":[1.152184,51.330334],"type":"Point"}
}
