{
  "type": "Feature",
  "properties": {
    "iso:country":"GB",
    "wof:name":"LS29 0JU",
    "wof:placetype":"postalcode"
},
  "geometry": {"coordinates":[-1.91370947894627,53.95648226995168],"type":"Point"}
}