{
  "type": "Feature",
  "properties": {
    "iso:country":"GB",
    "wof:name":"LE3 3TQ",
    "wof:placetype":"postalcode"
},
  "geometry": {"coordinates":[-1.19129041589212,52.6162498000435],"type":"Point"}
}