{
  "type": "Feature",
  "properties": {
    "date:inception_lower": "1995-12-01",
    "date:inception_upper": "1995-12-01",
    "iso:country": "GB",
    "wof:name": "LE3 3TQ",
    "wof:placetype": "postalcode"
  },
  "geometry": {"coordinates":[-1.19129,52.61625],"type":"Point"}
}
