{
  "type": "Feature",
  "properties": {
    "iso:country": "GB",
    "wof:name": "RH10 3PQ",
    "wof:placetype": "postalcode"
  },
  "geometry": {"coordinates":[-0.15539,51.130383],"type":"Point"}
}
