{
  "type": "Feature",
  "properties": {
    "iso:country":"GB",
    "wof:name":"RH10 3PQ",
    "wof:placetype":"postalcode"
},
  "geometry": {"coordinates":[-0.15538985273783,51.13038326963543],"type":"Point"}
}