{
  "type": "Feature",
  "properties": {
    "iso:country":"GB",
    "wof:name":"RG42 1YD",
    "wof:placetype":"postalcode"
},
  "geometry": {"coordinates":[-0.76225978419261,51.41995516202904],"type":"Point"}
}