{
  "type": "Feature",
  "properties": {
    "iso:country": "GB",
    "wof:name": "CF40 2ET",
    "wof:placetype": "postalcode"
  },
  "geometry": {"coordinates":[-3.455145,51.627312],"type":"Point"}
}
