{
  "type": "Feature",
  "properties": {
    "iso:country":"GB",
    "wof:name":"L31 2JX",
    "wof:placetype":"postalcode"
},
  "geometry": {"coordinates":[-2.94434047148779,53.52716252959887],"type":"Point"}
}