{
  "type": "Feature",
  "properties": {
    "iso:country":"GB",
    "wof:name":"ME2 3SU",
    "wof:placetype":"postalcode"
},
  "geometry": {"coordinates":[0.4765802598753,51.40025907945137],"type":"Point"}
}