{
  "type": "Feature",
  "properties": {
    "iso:country":"GB",
    "wof:name":"DT1 3QY",
    "wof:placetype":"postalcode"
},
  "geometry": {"coordinates":[-2.47078544274579,50.71270262455641],"type":"Point"}
}