{
  "type": "Feature",
  "properties": {
    "iso:country":"GB",
    "wof:name":"E17 7FD",
    "wof:placetype":"postalcode"
},
  "geometry": {"coordinates":[-0.02046627947757,51.58487043451959],"type":"Point"}
}