{
  "type": "Feature",
  "properties": {
    "date:inception_lower": "2015-02-01",
    "date:inception_upper": "2015-02-01",
    "iso:country": "GB",
    "wof:name": "E17 7FD",
    "wof:placetype": "postalcode"
  },
  "geometry": {"coordinates":[-0.020466,51.58487],"type":"Point"}
}
