{
  "type": "Feature",
  "properties": {
    "iso:country":"GB",
    "wof:name":"LE12 9DF",
    "wof:placetype":"postalcode"
},
  "geometry": {"coordinates":[-1.28728863283092,52.76668134999347],"type":"Point"}
}