{
  "type": "Feature",
  "properties": {
    "iso:country": "GB",
    "wof:name": "OL13 8QS",
    "wof:placetype": "postalcode"
  },
  "geometry": {"coordinates":[-2.195456,53.725634],"type":"Point"}
}
