{
  "type": "Feature",
  "properties": {
    "iso:country":"GB",
    "wof:name":"OL13 8QS",
    "wof:placetype":"postalcode"
},
  "geometry": {"coordinates":[-2.19545616948605,53.72563410981313],"type":"Point"}
}