{
  "type": "Feature",
  "properties": {
    "date:inception_lower": "1980-01-01",
    "date:inception_upper": "1980-01-01",
    "iso:country": "GB",
    "wof:name": "NG34 0QN",
    "wof:placetype": "postalcode"
  },
  "geometry": {"coordinates":[-0.336804,52.891724],"type":"Point"}
}
