{
  "type": "Feature",
  "properties": {
    "iso:country":"GB",
    "wof:name":"HP10 9UW",
    "wof:placetype":"postalcode"
},
  "geometry": {"coordinates":[-0.70161501418482,51.60792353048225],"type":"Point"}
}