{
  "type": "Feature",
  "properties": {
    "iso:country":"GB",
    "wof:name":"NN14 4EY",
    "wof:placetype":"postalcode"
},
  "geometry": {"coordinates":[-0.57804104623671,52.38130521446762],"type":"Point"}
}