{
  "type": "Feature",
  "properties": {
    "iso:country": "GB",
    "wof:name": "NN7 2BP",
    "wof:placetype": "postalcode"
  },
  "geometry": {"coordinates":[-0.816532,52.187324],"type":"Point"}
}
