{
  "type": "Feature",
  "properties": {
    "iso:country":"GB",
    "wof:name":"NN7 2BP",
    "wof:placetype":"postalcode"
},
  "geometry": {"coordinates":[-0.81653249912988,52.18732400828977],"type":"Point"}
}