{
  "type": "Feature",
  "properties": {
    "iso:country":"GB",
    "wof:name":"EX12 2RZ",
    "wof:placetype":"postalcode"
},
  "geometry": {"coordinates":[-3.07368594159324,50.70802426971822],"type":"Point"}
}