{
  "type": "Feature",
  "properties": {
    "iso:country": "GB",
    "wof:name": "EX12 2RZ",
    "wof:placetype": "postalcode"
  },
  "geometry": {"coordinates":[-3.073686,50.708024],"type":"Point"}
}
