{
  "type": "Feature",
  "properties": {
    "date:inception_lower":"1980-01-01",
    "date:inception_upper":"1980-01-31",
    "iso:country":"GB",
    "wof:name":"EX12 2RZ",
    "wof:placetype":"postalcode"
},
  "geometry": {"coordinates":[-3.073686,50.708024],"type":"Point"}
}