{
  "type": "Feature",
  "properties": {
    "date:inception_lower": "1980-01-01",
    "date:inception_upper": "1980-01-01",
    "iso:country": "GB",
    "wof:name": "GL2 0RG",
    "wof:placetype": "postalcode"
  },
  "geometry": {"coordinates":[-2.217499,51.870821],"type":"Point"}
}
