{
  "type": "Feature",
  "properties": {
    "iso:country":"GB",
    "wof:name":"OL16 3QF",
    "wof:placetype":"postalcode"
},
  "geometry": {"coordinates":[-2.09723040421371,53.60036940733244],"type":"Point"}
}