{
  "type": "Feature",
  "properties": {
    "iso:country":"GB",
    "wof:name":"ST6 4DE",
    "wof:placetype":"postalcode"
},
  "geometry": {"coordinates":[-2.20828546929224,53.04415096022304],"type":"Point"}
}