{
  "type": "Feature",
  "properties": {
    "iso:country":"GB",
    "wof:name":"NP22 4NH",
    "wof:placetype":"postalcode"
},
  "geometry": {"coordinates":[-3.23053491366201,51.76433918136859],"type":"Point"}
}