{
  "type": "Feature",
  "properties": {
    "iso:country": "GB",
    "wof:name": "NP22 4NH",
    "wof:placetype": "postalcode"
  },
  "geometry": {"coordinates":[-3.230535,51.764339],"type":"Point"}
}
