{
  "type": "Feature",
  "properties": {
    "iso:country":"GB",
    "wof:name":"M33 3GP",
    "wof:placetype":"postalcode"
},
  "geometry": {"coordinates":[-2.31764388454116,53.41181393750126],"type":"Point"}
}