{
  "type": "Feature",
  "properties": {
    "iso:country":"GB",
    "wof:name":"M25 2SJ",
    "wof:placetype":"postalcode"
},
  "geometry": {"coordinates":[-2.25114418399719,53.54855209539745],"type":"Point"}
}