{
  "type": "Feature",
  "properties": {
    "iso:country": "GB",
    "wof:name": "M25 2SJ",
    "wof:placetype": "postalcode"
  },
  "geometry": {"coordinates":[-2.251144,53.548552],"type":"Point"}
}
