{
  "type": "Feature",
  "properties": {
    "date:inception_lower":"1994-05-01",
    "date:inception_upper":"1994-05-31",
    "iso:country":"GB",
    "wof:name":"M25 2SJ",
    "wof:placetype":"postalcode"
},
  "geometry": {"coordinates":[-2.251144,53.548552],"type":"Point"}
}