{
  "type": "Feature",
  "properties": {
    "iso:country":"GB",
    "wof:name":"LL52 0EJ",
    "wof:placetype":"postalcode"
},
  "geometry": {"coordinates":[-4.2395623588525,52.91634719288206],"type":"Point"}
}