{
  "type": "Feature",
  "properties": {
    "date:inception_lower":"2004-05-01",
    "date:inception_upper":"2004-05-31",
    "iso:country":"GB",
    "wof:name":"LL52 0EJ",
    "wof:placetype":"postalcode"
},
  "geometry": {"coordinates":[-4.239562,52.916347],"type":"Point"}
}