{
  "type": "Feature",
  "properties": {
    "iso:country":"GB",
    "wof:name":"NE26 3PF",
    "wof:placetype":"postalcode"
},
  "geometry": {"coordinates":[-1.45701579994199,55.04378768800822],"type":"Point"}
}