{
  "type": "Feature",
  "properties": {
    "date:inception_lower": "1980-01-01",
    "date:inception_upper": "1980-01-01",
    "iso:country": "GB",
    "wof:name": "DD1 1PS",
    "wof:placetype": "postalcode"
  },
  "geometry": {"coordinates":[-2.976711,56.460987],"type":"Point"}
}
