{
  "type": "Feature",
  "properties": {
    "iso:country":"GB",
    "wof:name":"B6 7AN",
    "wof:placetype":"postalcode"
},
  "geometry": {"coordinates":[-1.87774361692947,52.51817849818408],"type":"Point"}
}