{
  "type": "Feature",
  "properties": {
    "iso:country":"GB",
    "wof:name":"EN5 5DH",
    "wof:placetype":"postalcode"
},
  "geometry": {"coordinates":[-0.17578967645001,51.65174562258584],"type":"Point"}
}