{
  "type": "Feature",
  "properties": {
    "date:inception_lower": "2019-04-01",
    "date:inception_upper": "2019-04-01",
    "iso:country": "GB",
    "wof:name": "G42 7BD",
    "wof:placetype": "postalcode"
  },
  "geometry": {"coordinates":[-4.253779,55.837702],"type":"Point"}
}
