{
  "type": "Feature",
  "properties": {
    "iso:country":"GB",
    "wof:name":"N20 8DH",
    "wof:placetype":"postalcode"
},
  "geometry": {"coordinates":[-0.18710225182153,51.62726399207975],"type":"Point"}
}