{
  "type": "Feature",
  "properties": {
    "iso:country": "GB",
    "wof:name": "WF15 7LH",
    "wof:placetype": "postalcode"
  },
  "geometry": {"coordinates":[-1.705821,53.697586],"type":"Point"}
}
