{
  "type": "Feature",
  "properties": {
    "iso:country":"GB",
    "wof:name":"WF15 7LH",
    "wof:placetype":"postalcode"
},
  "geometry": {"coordinates":[-1.70581891625424,53.69758829736232],"type":"Point"}
}