{
  "type": "Feature",
  "properties": {
    "date:inception_lower":"2018-11-01",
    "date:inception_upper":"2018-11-30",
    "iso:country":"GB",
    "wof:name":"NN2 6NB",
    "wof:placetype":"postalcode"
},
  "geometry": {"coordinates":[-0.899281,52.253746],"type":"Point"}
}