{
  "type": "Feature",
  "properties": {
    "iso:country": "GB",
    "wof:name": "NN2 6NB",
    "wof:placetype": "postalcode"
  },
  "geometry": {"coordinates":[-0.899281,52.253746],"type":"Point"}
}
