{
  "type": "Feature",
  "properties": {
    "iso:country":"GB",
    "wof:name":"L33 7SE",
    "wof:placetype":"postalcode"
},
  "geometry": {"coordinates":[-2.86302711879654,53.48098211144416],"type":"Point"}
}