{
  "type": "Feature",
  "properties": {
    "iso:country":"GB",
    "wof:name":"LL65 3PN",
    "wof:placetype":"postalcode"
},
  "geometry": {"coordinates":[-4.47863163490924,53.27031687844259],"type":"Point"}
}