{
  "type": "Feature",
  "properties": {
    "date:inception_lower": "1980-01-01",
    "date:inception_upper": "1980-01-01",
    "iso:country": "GB",
    "wof:name": "G20 8AU",
    "wof:placetype": "postalcode"
  },
  "geometry": {"coordinates":[-4.298696,55.892464],"type":"Point"}
}
