{
  "type": "Feature",
  "properties": {
    "iso:country":"GB",
    "wof:name":"CV6 4BT",
    "wof:placetype":"postalcode"
},
  "geometry": {"coordinates":[-1.50590340076187,52.43780204839742],"type":"Point"}
}