{
  "type": "Feature",
  "properties": {
    "iso:country": "GB",
    "wof:name": "WA5 9RX",
    "wof:placetype": "postalcode"
  },
  "geometry": {"coordinates":[-2.619146,53.41002],"type":"Point"}
}
