{
  "type": "Feature",
  "properties": {
    "iso:country":"GB",
    "wof:name":"WA5 9RX",
    "wof:placetype":"postalcode"
},
  "geometry": {"coordinates":[-2.61914608396881,53.41001953677731],"type":"Point"}
}