{
  "type": "Feature",
  "properties": {
    "iso:country":"GB",
    "wof:name":"CH5 4QA",
    "wof:placetype":"postalcode"
},
  "geometry": {"coordinates":[-3.05690885979388,53.21884903845645],"type":"Point"}
}