{
  "type": "Feature",
  "properties": {
    "iso:country":"GB",
    "wof:name":"WR8 9LA",
    "wof:placetype":"postalcode"
},
  "geometry": {"coordinates":[-2.14028075253814,52.04556649722536],"type":"Point"}
}