{
  "type": "Feature",
  "properties": {
    "iso:country": "GB",
    "wof:name": "WR8 9LA",
    "wof:placetype": "postalcode"
  },
  "geometry": {"coordinates":[-2.140229,52.045568],"type":"Point"}
}
