{
  "type": "Feature",
  "properties": {
    "date:inception_lower":"1980-01-01",
    "date:inception_upper":"1980-01-31",
    "iso:country":"GB",
    "wof:name":"WR8 9LA",
    "wof:placetype":"postalcode"
},
  "geometry": {"coordinates":[-2.140229,52.045568],"type":"Point"}
}