{
  "type": "Feature",
  "properties": {
    "date:inception_lower": "1980-01-01",
    "date:inception_upper": "1980-01-01",
    "iso:country": "GB",
    "wof:name": "WR8 9LA",
    "wof:placetype": "postalcode"
  },
  "geometry": {"coordinates":[-2.140507,52.045612],"type":"Point"}
}
