{
  "type": "Feature",
  "properties": {
    "iso:country":"GB",
    "wof:name":"BH12 5BJ",
    "wof:placetype":"postalcode"
},
  "geometry": {"coordinates":[-1.91098054364404,50.74609288589311],"type":"Point"}
}