{
  "type": "Feature",
  "properties": {
    "iso:country":"GB",
    "wof:name":"BR1 3RP",
    "wof:placetype":"postalcode"
},
  "geometry": {"coordinates":[0.01126121086175,51.41370332665579],"type":"Point"}
}