{
  "type": "Feature",
  "properties": {
    "iso:country":"GB",
    "wof:name":"LA5 9JS",
    "wof:placetype":"postalcode"
},
  "geometry": {"coordinates":[-2.77020282836097,54.12532394661322],"type":"Point"}
}