{
  "type": "Feature",
  "properties": {
    "iso:country":"GB",
    "wof:name":"RH10 1BP",
    "wof:placetype":"postalcode"
},
  "geometry": {"coordinates":[-0.19039906096204,51.11593897123783],"type":"Point"}
}