{
  "type": "Feature",
  "properties": {
    "iso:country":"GB",
    "wof:name":"E4 8EH",
    "wof:placetype":"postalcode"
},
  "geometry": {"coordinates":[-0.02432479587142,51.61803693830886],"type":"Point"}
}