{
  "type": "Feature",
  "properties": {
    "iso:country":"GB",
    "wof:name":"HU15 1QB",
    "wof:placetype":"postalcode"
},
  "geometry": {"coordinates":[-0.55872647958421,53.74704387611292],"type":"Point"}
}