{
  "type": "Feature",
  "properties": {
    "iso:country": "GB",
    "wof:name": "GL19 4NX",
    "wof:placetype": "postalcode"
  },
  "geometry": {"coordinates":[-2.2725,51.971134],"type":"Point"}
}
