{
  "type": "Feature",
  "properties": {
    "iso:country":"GB",
    "wof:name":"HR9 5AQ",
    "wof:placetype":"postalcode"
},
  "geometry": {"coordinates":[-2.58277517866668,51.91138632186089],"type":"Point"}
}