{
  "type": "Feature",
  "properties": {
    "date:inception_lower": "1994-05-01",
    "date:inception_upper": "1994-05-01",
    "iso:country": "GB",
    "wof:name": "M29 8LD",
    "wof:placetype": "postalcode"
  },
  "geometry": {"coordinates":[-2.472006,53.514519],"type":"Point"}
}
