{
  "type": "Feature",
  "properties": {
    "date:inception_lower": "2016-06-01",
    "date:inception_upper": "2016-06-01",
    "iso:country": "GB",
    "wof:name": "CV37 9LF",
    "wof:placetype": "postalcode"
  },
  "geometry": {"coordinates":[-1.733784,52.199448],"type":"Point"}
}
