{
  "type": "Feature",
  "properties": {
    "date:inception_lower": "2003-06-01",
    "date:inception_upper": "2003-06-01",
    "iso:country": "GB",
    "wof:name": "NN9 5TL",
    "wof:placetype": "postalcode"
  },
  "geometry": {"coordinates":[-0.61336,52.328814],"type":"Point"}
}
