{
  "type": "Feature",
  "properties": {
    "iso:country":"GB",
    "wof:name":"S75 5PU",
    "wof:placetype":"postalcode"
},
  "geometry": {"coordinates":[-1.51875668895578,53.58567237959425],"type":"Point"}
}