{
  "type": "Feature",
  "properties": {
    "date:inception_lower": "1980-01-01",
    "date:inception_upper": "1980-01-01",
    "iso:country": "GB",
    "wof:name": "B28 0LN",
    "wof:placetype": "postalcode"
  },
  "geometry": {"coordinates":[-1.839492,52.421775],"type":"Point"}
}
