{
  "type": "Feature",
  "properties": {
    "iso:country":"GB",
    "wof:name":"B28 0LN",
    "wof:placetype":"postalcode"
},
  "geometry": {"coordinates":[-1.83949829531683,52.42176029033071],"type":"Point"}
}