{
  "type": "Feature",
  "properties": {
    "iso:country":"GB",
    "wof:name":"TN6 2AR",
    "wof:placetype":"postalcode"
},
  "geometry": {"coordinates":[0.17296226061364,51.05434117771191],"type":"Point"}
}