{
  "type": "Feature",
  "properties": {
    "iso:country":"GB",
    "wof:name":"PH33 7AB",
    "wof:placetype":"postalcode"
},
  "geometry": {"coordinates":[-5.27193480042358,56.71704929647615],"type":"Point"}
}