{
  "type": "Feature",
  "properties": {
    "iso:country": "GB",
    "wof:name": "LS26 8QN",
    "wof:placetype": "postalcode"
  },
  "geometry": {"coordinates":[-1.419531,53.770418],"type":"Point"}
}
