{
  "type": "Feature",
  "properties": {
    "iso:country":"GB",
    "wof:name":"LS26 8QN",
    "wof:placetype":"postalcode"
},
  "geometry": {"coordinates":[-1.41953130538167,53.77041776028568],"type":"Point"}
}