{
  "type": "Feature",
  "properties": {
    "date:inception_lower": "1983-07-01",
    "date:inception_upper": "1983-07-01",
    "iso:country": "GB",
    "wof:name": "KT9 2DD",
    "wof:placetype": "postalcode"
  },
  "geometry": {"coordinates":[-0.304446,51.356062],"type":"Point"}
}
