{
  "type": "Feature",
  "properties": {
    "iso:country":"GB",
    "wof:name":"KT9 2DD",
    "wof:placetype":"postalcode"
},
  "geometry": {"coordinates":[-0.30449700076959,51.35610901406448],"type":"Point"}
}