{
  "type": "Feature",
  "properties": {
    "iso:country":"GB",
    "wof:name":"BR6 9BZ",
    "wof:placetype":"postalcode"
},
  "geometry": {"coordinates":[0.11044180853287,51.3661038552342],"type":"Point"}
}