{
  "type": "Feature",
  "properties": {
    "iso:country":"GB",
    "wof:name":"WV6 9BW",
    "wof:placetype":"postalcode"
},
  "geometry": {"coordinates":[-2.19432973902582,52.60684713287102],"type":"Point"}
}