{
  "type": "Feature",
  "properties": {
    "iso:country":"GB",
    "wof:name":"WN4 8XY",
    "wof:placetype":"postalcode"
},
  "geometry": {"coordinates":[-2.6226642573485,53.49015289575735],"type":"Point"}
}