{
  "type": "Feature",
  "properties": {
    "date:inception_lower": "1996-12-01",
    "date:inception_upper": "1996-12-01",
    "iso:country": "GB",
    "wof:name": "WN4 8XY",
    "wof:placetype": "postalcode"
  },
  "geometry": {"coordinates":[-2.622664,53.490153],"type":"Point"}
}
