{
  "type": "Feature",
  "properties": {
    "iso:country": "GB",
    "wof:name": "KA17 0JF",
    "wof:placetype": "postalcode"
  },
  "geometry": {"coordinates":[-4.274541,55.613199],"type":"Point"}
}
