{
  "type": "Feature",
  "properties": {
    "iso:country":"GB",
    "wof:name":"KA17 0JF",
    "wof:placetype":"postalcode"
},
  "geometry": {"coordinates":[-4.27454057475548,55.6131994336235],"type":"Point"}
}