{
  "type": "Feature",
  "properties": {
    "date:inception_lower": "2006-07-01",
    "date:inception_upper": "2006-07-01",
    "iso:country": "GB",
    "wof:name": "KA17 0JF",
    "wof:placetype": "postalcode"
  },
  "geometry": {"coordinates":[-4.274541,55.613199],"type":"Point"}
}
