{
  "type": "Feature",
  "properties": {
    "iso:country":"GB",
    "wof:name":"G71 6NF",
    "wof:placetype":"postalcode"
},
  "geometry": {"coordinates":[-4.06584402376459,55.82345604952668],"type":"Point"}
}