{
  "type": "Feature",
  "properties": {
    "date:inception_lower": "1993-01-01",
    "date:inception_upper": "1993-01-01",
    "iso:country": "GB",
    "wof:name": "MK7 6EA",
    "wof:placetype": "postalcode"
  },
  "geometry": {"coordinates":[-0.69437,52.030957],"type":"Point"}
}
