{
  "type": "Feature",
  "properties": {
    "iso:country":"GB",
    "wof:name":"MK7 6EA",
    "wof:placetype":"postalcode"
},
  "geometry": {"coordinates":[-0.69436964509342,52.03095712222763],"type":"Point"}
}