{
  "type": "Feature",
  "properties": {
    "iso:country":"GB",
    "wof:name":"GL4 5WD",
    "wof:placetype":"postalcode"
},
  "geometry": {"coordinates":[-2.19091059137971,51.84481181417242],"type":"Point"}
}