{
  "type": "Feature",
  "properties": {
    "iso:country":"GB",
    "wof:name":"SK14 5BD",
    "wof:placetype":"postalcode"
},
  "geometry": {"coordinates":[-2.07713264214897,53.44294371580519],"type":"Point"}
}