{
  "type": "Feature",
  "properties": {
    "iso:country": "GB",
    "wof:name": "HU11 5AD",
    "wof:placetype": "postalcode"
  },
  "geometry": {"coordinates":[-0.258116,53.836612],"type":"Point"}
}
