{
  "type": "Feature",
  "properties": {
    "iso:country":"GB",
    "wof:name":"MK43 9BT",
    "wof:placetype":"postalcode"
},
  "geometry": {"coordinates":[-0.52406327971762,52.11196371951752],"type":"Point"}
}