{
  "type": "Feature",
  "properties": {
    "date:inception_lower": "2018-02-01",
    "date:inception_upper": "2018-02-01",
    "iso:country": "GB",
    "wof:name": "NE28 9FH",
    "wof:placetype": "postalcode"
  },
  "geometry": {"coordinates":[-1.545546,55.011771],"type":"Point"}
}
