{
  "type": "Feature",
  "properties": {
    "iso:country":"GB",
    "wof:name":"BD18 3EY",
    "wof:placetype":"postalcode"
},
  "geometry": {"coordinates":[-1.79260757512149,53.83548423030891],"type":"Point"}
}