{
  "type": "Feature",
  "properties": {
    "date:inception_lower": "2004-09-01",
    "date:inception_upper": "2004-09-01",
    "iso:country": "GB",
    "wof:name": "B31 3BU",
    "wof:placetype": "postalcode"
  },
  "geometry": {"coordinates":[-1.947626,52.405756],"type":"Point"}
}
