{
  "type": "Feature",
  "properties": {
    "date:inception_lower": "2022-02-01",
    "date:inception_upper": "2022-02-01",
    "iso:country": "GB",
    "wof:name": "CM77 8PR",
    "wof:placetype": "postalcode"
  },
  "geometry": {"coordinates":[0.596288,51.853372],"type":"Point"}
}
