{
  "type": "Feature",
  "properties": {
    "iso:country": "GB",
    "wof:name": "BL2 6ET",
    "wof:placetype": "postalcode"
  },
  "geometry": {"coordinates":[-2.391197,53.57746],"type":"Point"}
}
