{
  "type": "Feature",
  "properties": {
    "iso:country": "GB",
    "wof:name": "RG23 8EB",
    "wof:placetype": "postalcode"
  },
  "geometry": {"coordinates":[-1.122294,51.268443],"type":"Point"}
}
