{
  "type": "Feature",
  "properties": {
    "iso:country":"GB",
    "wof:name":"RG23 8EB",
    "wof:placetype":"postalcode"
},
  "geometry": {"coordinates":[-1.12229435264281,51.26844315898204],"type":"Point"}
}