{
  "type": "Feature",
  "properties": {
    "date:inception_lower":"1980-01-01",
    "date:inception_upper":"1980-01-31",
    "iso:country":"GB",
    "wof:name":"RG23 8EB",
    "wof:placetype":"postalcode"
},
  "geometry": {"coordinates":[-1.122294,51.268443],"type":"Point"}
}