{
  "type": "Feature",
  "properties": {
    "date:inception_lower": "2020-04-01",
    "date:inception_upper": "2020-04-01",
    "iso:country": "GB",
    "wof:name": "TN12 0FS",
    "wof:placetype": "postalcode"
  },
  "geometry": {"coordinates":[0.557863,51.167813],"type":"Point"}
}
