{
  "type": "Feature",
  "properties": {
    "date:inception_lower": "1980-01-01",
    "date:inception_upper": "1980-01-01",
    "iso:country": "GB",
    "wof:name": "DY6 0AB",
    "wof:placetype": "postalcode"
  },
  "geometry": {"coordinates":[-2.200285,52.491272],"type":"Point"}
}
