{
  "type": "Feature",
  "properties": {
    "iso:country":"GB",
    "wof:name":"DY6 0AB",
    "wof:placetype":"postalcode"
},
  "geometry": {"coordinates":[-2.20028476758053,52.4912724665183],"type":"Point"}
}