{
  "type": "Feature",
  "properties": {
    "iso:country": "GB",
    "wof:name": "DY6 0AB",
    "wof:placetype": "postalcode"
  },
  "geometry": {"coordinates":[-2.200285,52.491272],"type":"Point"}
}
