{
  "type": "Feature",
  "properties": {
    "iso:country":"GB",
    "wof:name":"PE2 5PF",
    "wof:placetype":"postalcode"
},
  "geometry": {"coordinates":[-0.26751284818378,52.54960955268215],"type":"Point"}
}