{
  "type": "Feature",
  "properties": {
    "iso:country":"GB",
    "wof:name":"KT9 1NQ",
    "wof:placetype":"postalcode"
},
  "geometry": {"coordinates":[-0.3108051926517,51.36773756456584],"type":"Point"}
}