{
  "type": "Feature",
  "properties": {
    "date:inception_lower": "1980-01-01",
    "date:inception_upper": "1980-01-01",
    "iso:country": "GB",
    "wof:name": "TN8 7LX",
    "wof:placetype": "postalcode"
  },
  "geometry": {"coordinates":[0.114864,51.176224],"type":"Point"}
}
