{
  "type": "Feature",
  "properties": {
    "iso:country":"GB",
    "wof:name":"TN8 7LX",
    "wof:placetype":"postalcode"
},
  "geometry": {"coordinates":[0.11486414449372,51.17622381635386],"type":"Point"}
}