{
  "type": "Feature",
  "properties": {
    "iso:country":"GB",
    "wof:name":"M9 5GE",
    "wof:placetype":"postalcode"
},
  "geometry": {"coordinates":[-2.21433882629625,53.50477846211311],"type":"Point"}
}