{
  "type": "Feature",
  "properties": {
    "iso:country": "GB",
    "wof:name": "SA61 1ED",
    "wof:placetype": "postalcode"
  },
  "geometry": {"coordinates":[-4.984215,51.793668],"type":"Point"}
}
