{
  "type": "Feature",
  "properties": {
    "iso:country":"GB",
    "wof:name":"SA61 1ED",
    "wof:placetype":"postalcode"
},
  "geometry": {"coordinates":[-4.98421466117501,51.79366757372046],"type":"Point"}
}