{
  "type": "Feature",
  "properties": {
    "date:inception_lower":"2004-09-01",
    "date:inception_upper":"2004-09-30",
    "iso:country":"GB",
    "wof:name":"SA61 1ED",
    "wof:placetype":"postalcode"
},
  "geometry": {"coordinates":[-4.984215,51.793668],"type":"Point"}
}