{
  "type": "Feature",
  "properties": {
    "iso:country":"GB",
    "wof:name":"WA14 4AS",
    "wof:placetype":"postalcode"
},
  "geometry": {"coordinates":[-2.36318869343179,53.38788217965713],"type":"Point"}
}