{
  "type": "Feature",
  "properties": {
    "iso:country":"GB",
    "wof:name":"IP19 8TP",
    "wof:placetype":"postalcode"
},
  "geometry": {"coordinates":[1.49737392681273,52.34073775953778],"type":"Point"}
}