{
  "type": "Feature",
  "properties": {
    "date:inception_lower": "2022-08-01",
    "date:inception_upper": "2022-08-01",
    "iso:country": "GB",
    "wof:name": "CT1 3ZW",
    "wof:placetype": "postalcode"
  },
  "geometry": {"coordinates":[1.059271,51.264446],"type":"Point"}
}
