{
  "type": "Feature",
  "properties": {
    "iso:country":"GB",
    "wof:name":"NE62 5JZ",
    "wof:placetype":"postalcode"
},
  "geometry": {"coordinates":[-1.58881268857388,55.16321668591563],"type":"Point"}
}