{
  "type": "Feature",
  "properties": {
    "iso:country": "GB",
    "wof:name": "TA6 5LP",
    "wof:placetype": "postalcode"
  },
  "geometry": {"coordinates":[-2.989924,51.120728],"type":"Point"}
}
