{
  "type": "Feature",
  "properties": {
    "date:inception_lower":"1980-01-01",
    "date:inception_upper":"1980-01-31",
    "iso:country":"GB",
    "wof:name":"TA6 5LP",
    "wof:placetype":"postalcode"
},
  "geometry": {"coordinates":[-2.989924,51.120728],"type":"Point"}
}