{
  "type": "Feature",
  "properties": {
    "date:inception_lower": "1980-01-01",
    "date:inception_upper": "1980-01-01",
    "iso:country": "GB",
    "wof:name": "TA6 5LP",
    "wof:placetype": "postalcode"
  },
  "geometry": {"coordinates":[-2.989493,51.118892],"type":"Point"}
}
