{
  "type": "Feature",
  "properties": {
    "iso:country":"GB",
    "wof:name":"CF14 5JT",
    "wof:placetype":"postalcode"
},
  "geometry": {"coordinates":[-3.19662146799755,51.53421458774484],"type":"Point"}
}