{
  "type": "Feature",
  "properties": {
    "iso:country":"GB",
    "wof:name":"CF3 0BS",
    "wof:placetype":"postalcode"
},
  "geometry": {"coordinates":[-3.1068515986541,51.5262481573259],"type":"Point"}
}