{
  "type": "Feature",
  "properties": {
    "iso:country":"GB",
    "wof:name":"PL2 3AJ",
    "wof:placetype":"postalcode"
},
  "geometry": {"coordinates":[-4.16403158978364,50.38354010330284],"type":"Point"}
}