{
  "type": "Feature",
  "properties": {
    "date:inception_lower": "1980-01-01",
    "date:inception_upper": "1980-01-01",
    "iso:country": "GB",
    "wof:name": "PL2 3AJ",
    "wof:placetype": "postalcode"
  },
  "geometry": {"coordinates":[-4.164032,50.38354],"type":"Point"}
}
