{
  "type": "Feature",
  "properties": {
    "iso:country":"GB",
    "wof:name":"FY2 0AN",
    "wof:placetype":"postalcode"
},
  "geometry": {"coordinates":[-3.04133618119354,53.85279447228775],"type":"Point"}
}