{
  "type": "Feature",
  "properties": {
    "iso:country":"GB",
    "wof:name":"E6 5PE",
    "wof:placetype":"postalcode"
},
  "geometry": {"coordinates":[0.05858286402805,51.50921263220634],"type":"Point"}
}