{
  "type": "Feature",
  "properties": {
    "iso:country": "GB",
    "wof:name": "E6 5PE",
    "wof:placetype": "postalcode"
  },
  "geometry": {"coordinates":[0.058583,51.509213],"type":"Point"}
}
