{
  "type": "Feature",
  "properties": {
    "iso:country":"GB",
    "wof:name":"W10 6EA",
    "wof:placetype":"postalcode"
},
  "geometry": {"coordinates":[-0.21611221955466,51.52151787414814],"type":"Point"}
}