{
  "type": "Feature",
  "properties": {
    "iso:country": "GB",
    "wof:name": "WN3 6EQ",
    "wof:placetype": "postalcode"
  },
  "geometry": {"coordinates":[-2.669015,53.522998],"type":"Point"}
}
