{
  "type": "Feature",
  "properties": {
    "iso:country":"GB",
    "wof:name":"WN3 6EQ",
    "wof:placetype":"postalcode"
},
  "geometry": {"coordinates":[-2.66901513257637,53.52299827362712],"type":"Point"}
}