{
  "type": "Feature",
  "properties": {
    "iso:country":"GB",
    "wof:name":"MK18 4HJ",
    "wof:placetype":"postalcode"
},
  "geometry": {"coordinates":[-1.0097470928399,51.98112618787327],"type":"Point"}
}