{
  "type": "Feature",
  "properties": {
    "iso:country": "GB",
    "wof:name": "MK18 4HJ",
    "wof:placetype": "postalcode"
  },
  "geometry": {"coordinates":[-1.009747,51.981126],"type":"Point"}
}
