{
  "type": "Feature",
  "properties": {
    "iso:country":"GB",
    "wof:name":"LN4 3AL",
    "wof:placetype":"postalcode"
},
  "geometry": {"coordinates":[-0.30912523029929,53.16013181532826],"type":"Point"}
}