{
  "type": "Feature",
  "properties": {
    "date:inception_lower":"1980-01-01",
    "date:inception_upper":"1980-01-31",
    "iso:country":"GB",
    "wof:name":"LN4 3AL",
    "wof:placetype":"postalcode"
},
  "geometry": {"coordinates":[-0.309125,53.160132],"type":"Point"}
}