{
  "type": "Feature",
  "properties": {
    "iso:country": "GB",
    "wof:name": "LN4 3AL",
    "wof:placetype": "postalcode"
  },
  "geometry": {"coordinates":[-0.309125,53.160132],"type":"Point"}
}
