{
  "type": "Feature",
  "properties": {
    "date:inception_lower":"2018-11-01",
    "date:inception_upper":"2018-11-30",
    "iso:country":"GB",
    "wof:name":"EX38 8HT",
    "wof:placetype":"postalcode"
},
  "geometry": {"coordinates":[-4.142875,50.952238],"type":"Point"}
}