{
  "type": "Feature",
  "properties": {
    "date:inception_lower": "1980-01-01",
    "date:inception_upper": "1980-01-01",
    "iso:country": "GB",
    "wof:name": "BD12 8QB",
    "wof:placetype": "postalcode"
  },
  "geometry": {"coordinates":[-1.769505,53.733923],"type":"Point"}
}
