{
  "type": "Feature",
  "properties": {
    "iso:country":"GB",
    "wof:name":"BD12 8QB",
    "wof:placetype":"postalcode"
},
  "geometry": {"coordinates":[-1.76950504647835,53.73392269884389],"type":"Point"}
}