{
  "type": "Feature",
  "properties": {
    "iso:country":"GB",
    "wof:name":"G73 5RD",
    "wof:placetype":"postalcode"
},
  "geometry": {"coordinates":[-4.19517088269587,55.80155965204522],"type":"Point"}
}