{
  "type": "Feature",
  "properties": {
    "iso:country":"GB",
    "wof:name":"HX2 7RD",
    "wof:placetype":"postalcode"
},
  "geometry": {"coordinates":[-1.91366865524635,53.72436987542697],"type":"Point"}
}