{
  "type": "Feature",
  "properties": {
    "iso:country": "GB",
    "wof:name": "TA1 1QL",
    "wof:placetype": "postalcode"
  },
  "geometry": {"coordinates":[-3.098268,51.019215],"type":"Point"}
}
