{
  "type": "Feature",
  "properties": {
    "date:inception_lower":"1980-01-01",
    "date:inception_upper":"1980-01-31",
    "iso:country":"GB",
    "wof:name":"LU6 2BY",
    "wof:placetype":"postalcode"
},
  "geometry": {"coordinates":[-0.580299,51.887933],"type":"Point"}
}