{
  "type": "Feature",
  "properties": {
    "iso:country": "GB",
    "wof:name": "LU6 2BY",
    "wof:placetype": "postalcode"
  },
  "geometry": {"coordinates":[-0.580299,51.887933],"type":"Point"}
}
