{
  "type": "Feature",
  "properties": {
    "iso:country":"GB",
    "wof:name":"LU6 2BY",
    "wof:placetype":"postalcode"
},
  "geometry": {"coordinates":[-0.58032603730721,51.88787058362785],"type":"Point"}
}