{
  "type": "Feature",
  "properties": {
    "iso:country": "GB",
    "wof:name": "SE25 4AY",
    "wof:placetype": "postalcode"
  },
  "geometry": {"coordinates":[-0.083394,51.40716],"type":"Point"}
}
