{
  "type": "Feature",
  "properties": {
    "date:inception_lower": "1980-01-01",
    "date:inception_upper": "1980-01-01",
    "iso:country": "GB",
    "wof:name": "SE25 4AY",
    "wof:placetype": "postalcode"
  },
  "geometry": {"coordinates":[-0.083394,51.40716],"type":"Point"}
}
