{
  "type": "Feature",
  "properties": {
    "date:inception_lower":"1980-01-01",
    "date:inception_upper":"1980-01-31",
    "iso:country":"GB",
    "wof:name":"LS10 4DY",
    "wof:placetype":"postalcode"
},
  "geometry": {"coordinates":[-1.542771,53.74271],"type":"Point"}
}