{
  "type": "Feature",
  "properties": {
    "iso:country":"GB",
    "wof:name":"WA14 1LX",
    "wof:placetype":"postalcode"
},
  "geometry": {"coordinates":[-2.3446316452801,53.3986516537276],"type":"Point"}
}