{
  "type": "Feature",
  "properties": {
    "iso:country":"GB",
    "wof:name":"WV12 5BX",
    "wof:placetype":"postalcode"
},
  "geometry": {"coordinates":[-2.02648305462296,52.61568804854093],"type":"Point"}
}