{
  "type": "Feature",
  "properties": {
    "iso:country":"GB",
    "wof:name":"WA8 6RY",
    "wof:placetype":"postalcode"
},
  "geometry": {"coordinates":[-2.72076564172232,53.373548061129],"type":"Point"}
}