{
  "type": "Feature",
  "properties": {
    "iso:country": "GB",
    "wof:name": "WA8 6RY",
    "wof:placetype": "postalcode"
  },
  "geometry": {"coordinates":[-2.720766,53.373548],"type":"Point"}
}
