{
  "type": "Feature",
  "properties": {
    "iso:country":"GB",
    "wof:name":"GU22 8TW",
    "wof:placetype":"postalcode"
},
  "geometry": {"coordinates":[-0.50339056797478,51.3241889974169],"type":"Point"}
}