{
  "type": "Feature",
  "properties": {
    "iso:country": "GB",
    "wof:name": "CV9 2JZ",
    "wof:placetype": "postalcode"
  },
  "geometry": {"coordinates":[-1.644983,52.559971],"type":"Point"}
}
