{
  "type": "Feature",
  "properties": {
    "date:inception_lower":"1980-01-01",
    "date:inception_upper":"1980-01-31",
    "iso:country":"GB",
    "wof:name":"CV9 2JZ",
    "wof:placetype":"postalcode"
},
  "geometry": {"coordinates":[-1.644983,52.559971],"type":"Point"}
}