{
  "type": "Feature",
  "properties": {
    "iso:country":"GB",
    "wof:name":"CV9 2JZ",
    "wof:placetype":"postalcode"
},
  "geometry": {"coordinates":[-1.64503569253573,52.5599624668135],"type":"Point"}
}