{
  "type": "Feature",
  "properties": {
    "iso:country":"GB",
    "wof:name":"SS17 7PX",
    "wof:placetype":"postalcode"
},
  "geometry": {"coordinates":[0.45420023326156,51.52378624849172],"type":"Point"}
}