{
  "type": "Feature",
  "properties": {
    "date:inception_lower": "2023-12-01",
    "date:inception_upper": "2023-12-01",
    "iso:country": "GB",
    "wof:name": "TA6 6ND",
    "wof:placetype": "postalcode"
  },
  "geometry": {"coordinates":[-3.01312,51.086019],"type":"Point"}
}
