{
  "type": "Feature",
  "properties": {
    "iso:country":"GB",
    "wof:name":"RH11 9RE",
    "wof:placetype":"postalcode"
},
  "geometry": {"coordinates":[-0.19793668339956,51.09075804187211],"type":"Point"}
}