{
  "type": "Feature",
  "properties": {
    "iso:country": "GB",
    "wof:name": "RH11 9RE",
    "wof:placetype": "postalcode"
  },
  "geometry": {"coordinates":[-0.197937,51.090758],"type":"Point"}
}
