{
  "type": "Feature",
  "properties": {
    "date:inception_lower":"1985-10-01",
    "date:inception_upper":"1985-10-31",
    "iso:country":"GB",
    "wof:name":"RH11 9RE",
    "wof:placetype":"postalcode"
},
  "geometry": {"coordinates":[-0.197937,51.090758],"type":"Point"}
}