{
  "type": "Feature",
  "properties": {
    "date:inception_lower":"1980-01-01",
    "date:inception_upper":"1980-01-31",
    "iso:country":"GB",
    "wof:name":"NE65 9PR",
    "wof:placetype":"postalcode"
},
  "geometry": {"coordinates":[-1.7113,55.298652],"type":"Point"}
}