{
  "type": "Feature",
  "properties": {
    "date:inception_lower": "2021-12-01",
    "date:inception_upper": "2021-12-01",
    "iso:country": "GB",
    "wof:name": "SA73 9AP",
    "wof:placetype": "postalcode"
  },
  "geometry": {"coordinates":[-4.979156,51.792569],"type":"Point"}
}
