{
  "type": "Feature",
  "properties": {
    "iso:country":"GB",
    "wof:name":"W4 3EP",
    "wof:placetype":"postalcode"
},
  "geometry": {"coordinates":[-0.2606749306012,51.48726067950282],"type":"Point"}
}