{
  "type": "Feature",
  "properties": {
    "iso:country": "GB",
    "wof:name": "W4 3EP",
    "wof:placetype": "postalcode"
  },
  "geometry": {"coordinates":[-0.260675,51.487261],"type":"Point"}
}
