{
  "type": "Feature",
  "properties": {
    "iso:country":"GB",
    "wof:name":"HR4 7RH",
    "wof:placetype":"postalcode"
},
  "geometry": {"coordinates":[-2.762702303505,52.08927615988779],"type":"Point"}
}