{
  "type": "Feature",
  "properties": {
    "iso:country": "GB",
    "wof:name": "HR4 7RH",
    "wof:placetype": "postalcode"
  },
  "geometry": {"coordinates":[-2.762702,52.089276],"type":"Point"}
}
