{
  "type": "Feature",
  "properties": {
    "iso:country":"GB",
    "wof:name":"SN13 0LY",
    "wof:placetype":"postalcode"
},
  "geometry": {"coordinates":[-2.22063805997746,51.42815830530282],"type":"Point"}
}