{
  "type": "Feature",
  "properties": {
    "iso:country": "GB",
    "wof:name": "SN14 0YQ",
    "wof:placetype": "postalcode"
  },
  "geometry": {"coordinates":[-2.145775,51.451672],"type":"Point"}
}
