{
  "type": "Feature",
  "properties": {
    "iso:country":"GB",
    "wof:name":"DL12 0SL",
    "wof:placetype":"postalcode"
},
  "geometry": {"coordinates":[-2.0817102883294,54.62323783722265],"type":"Point"}
}