{
  "type": "Feature",
  "properties": {
    "iso:country": "GB",
    "wof:name": "GL17 0QJ",
    "wof:placetype": "postalcode"
  },
  "geometry": {"coordinates":[-2.463497,51.870675],"type":"Point"}
}
