{
  "type": "Feature",
  "properties": {
    "iso:country":"GB",
    "wof:name":"L25 8TF",
    "wof:placetype":"postalcode"
},
  "geometry": {"coordinates":[-2.85501062721686,53.36927290853026],"type":"Point"}
}