{
  "type": "Feature",
  "properties": {
    "iso:country":"GB",
    "wof:name":"TW4 6DJ",
    "wof:placetype":"postalcode"
},
  "geometry": {"coordinates":[-0.39951905608924,51.46602864252994],"type":"Point"}
}