{
  "type": "Feature",
  "properties": {
    "date:inception_lower": "1980-01-01",
    "date:inception_upper": "1980-01-01",
    "iso:country": "GB",
    "wof:name": "TW4 6DJ",
    "wof:placetype": "postalcode"
  },
  "geometry": {"coordinates":[-0.399519,51.466029],"type":"Point"}
}
