{
  "type": "Feature",
  "properties": {
    "iso:country": "GB",
    "wof:name": "NR28 9TW",
    "wof:placetype": "postalcode"
  },
  "geometry": {"coordinates":[1.453441,52.843623],"type":"Point"}
}
