{
  "type": "Feature",
  "properties": {
    "iso:country": "GB",
    "wof:name": "EX5 1JF",
    "wof:placetype": "postalcode"
  },
  "geometry": {"coordinates":[-3.397469,50.678781],"type":"Point"}
}
