{
  "type": "Feature",
  "properties": {
    "iso:country":"GB",
    "wof:name":"EX5 1JF",
    "wof:placetype":"postalcode"
},
  "geometry": {"coordinates":[-3.39746860837851,50.67878102752515],"type":"Point"}
}