{
  "type": "Feature",
  "properties": {
    "iso:country":"GB",
    "wof:name":"RH13 5LS",
    "wof:placetype":"postalcode"
},
  "geometry": {"coordinates":[-0.31188789180051,51.06339389486244],"type":"Point"}
}