{
  "type": "Feature",
  "properties": {
    "iso:country":"GB",
    "wof:name":"PA16 7JU",
    "wof:placetype":"postalcode"
},
  "geometry": {"coordinates":[-4.78989854031964,55.94298959874997],"type":"Point"}
}