{
  "type": "Feature",
  "properties": {
    "iso:country":"GB",
    "wof:name":"BN1 3DL",
    "wof:placetype":"postalcode"
},
  "geometry": {"coordinates":[-0.14975729833356,50.82650271592711],"type":"Point"}
}