{
  "type": "Feature",
  "properties": {
    "iso:country":"GB",
    "wof:name":"ML3 8RN",
    "wof:placetype":"postalcode"
},
  "geometry": {"coordinates":[-4.07248721342976,55.74962265426117],"type":"Point"}
}