{
  "type": "Feature",
  "properties": {
    "iso:country":"GB",
    "wof:name":"TA20 2EE",
    "wof:placetype":"postalcode"
},
  "geometry": {"coordinates":[-2.96571154281111,50.86637930268248],"type":"Point"}
}