{
  "type": "Feature",
  "properties": {
    "date:inception_lower":"2000-06-01",
    "date:inception_upper":"2000-06-30",
    "iso:country":"GB",
    "wof:name":"S66 8SR",
    "wof:placetype":"postalcode"
},
  "geometry": {"coordinates":[-1.225972,53.43187],"type":"Point"}
}