{
  "type": "Feature",
  "properties": {
    "iso:country": "GB",
    "wof:name": "S66 8SR",
    "wof:placetype": "postalcode"
  },
  "geometry": {"coordinates":[-1.225972,53.43187],"type":"Point"}
}
