{
  "type": "Feature",
  "properties": {
    "iso:country":"GB",
    "wof:name":"TF1 5GE",
    "wof:placetype":"postalcode"
},
  "geometry": {"coordinates":[-2.47972151476608,52.69964506830951],"type":"Point"}
}