{
  "type": "Feature",
  "properties": {
    "iso:country":"GB",
    "wof:name":"HX7 8DB",
    "wof:placetype":"postalcode"
},
  "geometry": {"coordinates":[-2.01036395515588,53.74344599391114],"type":"Point"}
}