{
  "type": "Feature",
  "properties": {
    "iso:country":"GB",
    "wof:name":"CW12 1EE",
    "wof:placetype":"postalcode"
},
  "geometry": {"coordinates":[-2.2070572925702,53.16423745521105],"type":"Point"}
}