{
  "type": "Feature",
  "properties": {
    "iso:country": "GB",
    "wof:name": "PH1 1NQ",
    "wof:placetype": "postalcode"
  },
  "geometry": {"coordinates":[-3.462048,56.394059],"type":"Point"}
}
