{
  "type": "Feature",
  "properties": {
    "date:inception_lower":"2008-02-01",
    "date:inception_upper":"2008-02-29",
    "iso:country":"GB",
    "wof:name":"M6 5BR",
    "wof:placetype":"postalcode"
},
  "geometry": {"coordinates":[-2.287327,53.491592],"type":"Point"}
}