{
  "type": "Feature",
  "properties": {
    "iso:country":"GB",
    "wof:name":"PA3 1RB",
    "wof:placetype":"postalcode"
},
  "geometry": {"coordinates":[-4.43993006809429,55.85357725973754],"type":"Point"}
}