{
  "type": "Feature",
  "properties": {
    "iso:country": "GB",
    "wof:name": "WV6 0JG",
    "wof:placetype": "postalcode"
  },
  "geometry": {"coordinates":[-2.153968,52.597027],"type":"Point"}
}
