{
  "type": "Feature",
  "properties": {
    "iso:country":"GB",
    "wof:name":"WV6 0JG",
    "wof:placetype":"postalcode"
},
  "geometry": {"coordinates":[-2.15396760208284,52.59702679165993],"type":"Point"}
}