{
  "type": "Feature",
  "properties": {
    "iso:country":"GB",
    "wof:name":"NR21 9AD",
    "wof:placetype":"postalcode"
},
  "geometry": {"coordinates":[0.75512869193614,52.90724108740324],"type":"Point"}
}