{
  "type": "Feature",
  "properties": {
    "iso:country": "GB",
    "wof:name": "NR21 9AD",
    "wof:placetype": "postalcode"
  },
  "geometry": {"coordinates":[0.755129,52.907241],"type":"Point"}
}
