{
  "type": "Feature",
  "properties": {
    "iso:country":"GB",
    "wof:name":"LS25 2BJ",
    "wof:placetype":"postalcode"
},
  "geometry": {"coordinates":[-1.37290436692028,53.78590331806783],"type":"Point"}
}