{
  "type": "Feature",
  "properties": {
    "date:inception_lower":"1980-01-01",
    "date:inception_upper":"1980-01-31",
    "iso:country":"GB",
    "wof:name":"TN15 7RE",
    "wof:placetype":"postalcode"
},
  "geometry": {"coordinates":[0.322856,51.307449],"type":"Point"}
}