{
  "type": "Feature",
  "properties": {
    "iso:country": "GB",
    "wof:name": "TN15 7RE",
    "wof:placetype": "postalcode"
  },
  "geometry": {"coordinates":[0.322856,51.307449],"type":"Point"}
}
