{
  "type": "Feature",
  "properties": {
    "iso:country":"GB",
    "wof:name":"TN15 7RE",
    "wof:placetype":"postalcode"
},
  "geometry": {"coordinates":[0.32136761869955,51.30467295634698],"type":"Point"}
}