{
  "type": "Feature",
  "properties": {
    "iso:country": "GB",
    "wof:name": "S45 0JZ",
    "wof:placetype": "postalcode"
  },
  "geometry": {"coordinates":[-1.469552,53.140425],"type":"Point"}
}
