{
  "type": "Feature",
  "properties": {
    "iso:country":"GB",
    "wof:name":"S45 0JZ",
    "wof:placetype":"postalcode"
},
  "geometry": {"coordinates":[-1.46920968758106,53.14049416284338],"type":"Point"}
}