{
  "type": "Feature",
  "properties": {
    "iso:country":"GB",
    "wof:name":"SG1 2HN",
    "wof:placetype":"postalcode"
},
  "geometry": {"coordinates":[-0.22049357710384,51.91427980433498],"type":"Point"}
}