{
  "type": "Feature",
  "properties": {
    "iso:country":"GB",
    "wof:name":"SA12 6JG",
    "wof:placetype":"postalcode"
},
  "geometry": {"coordinates":[-3.80885474117002,51.59123201851428],"type":"Point"}
}