{
  "type": "Feature",
  "properties": {
    "iso:country":"GB",
    "wof:name":"CV5 7GA",
    "wof:placetype":"postalcode"
},
  "geometry": {"coordinates":[-1.58372711935447,52.4136213553517],"type":"Point"}
}