{
  "type": "Feature",
  "properties": {
    "iso:country": "GB",
    "wof:name": "MK43 7JJ",
    "wof:placetype": "postalcode"
  },
  "geometry": {"coordinates":[-0.56708,52.200904],"type":"Point"}
}
