{
  "type": "Feature",
  "properties": {
    "date:inception_lower": "1993-08-01",
    "date:inception_upper": "1993-08-01",
    "iso:country": "GB",
    "wof:name": "OX12 8PH",
    "wof:placetype": "postalcode"
  },
  "geometry": {"coordinates":[-1.375041,51.535662],"type":"Point"}
}
