{
  "type": "Feature",
  "properties": {
    "iso:country":"GB",
    "wof:name":"OX12 8PH",
    "wof:placetype":"postalcode"
},
  "geometry": {"coordinates":[-1.37504064359157,51.53566234152774],"type":"Point"}
}