{
  "type": "Feature",
  "properties": {
    "iso:country":"GB",
    "wof:name":"NE42 5BH",
    "wof:placetype":"postalcode"
},
  "geometry": {"coordinates":[-1.84706033871197,54.95748426093899],"type":"Point"}
}