{
  "type": "Feature",
  "properties": {
    "date:inception_lower": "2001-06-01",
    "date:inception_upper": "2001-06-01",
    "iso:country": "GB",
    "wof:name": "PL8 1BA",
    "wof:placetype": "postalcode"
  },
  "geometry": {"coordinates":[-4.035878,50.316113],"type":"Point"}
}
