{
  "type": "Feature",
  "properties": {
    "date:inception_lower": "2005-07-01",
    "date:inception_upper": "2005-07-01",
    "iso:country": "GB",
    "wof:name": "M15 5LP",
    "wof:placetype": "postalcode"
  },
  "geometry": {"coordinates":[-2.257009,53.462961],"type":"Point"}
}
