{
  "type": "Feature",
  "properties": {
    "date:inception_lower":"1980-01-01",
    "date:inception_upper":"1980-01-31",
    "iso:country":"GB",
    "wof:name":"AL3 4JU",
    "wof:placetype":"postalcode"
},
  "geometry": {"coordinates":[-0.359576,51.743891],"type":"Point"}
}