{
  "type": "Feature",
  "properties": {
    "iso:country":"GB",
    "wof:name":"AL3 4JU",
    "wof:placetype":"postalcode"
},
  "geometry": {"coordinates":[-0.35957587430324,51.74389130269116],"type":"Point"}
}