{
  "type": "Feature",
  "properties": {
    "iso:country":"GB",
    "wof:name":"SA2 8HZ",
    "wof:placetype":"postalcode"
},
  "geometry": {"coordinates":[-3.99971678688186,51.61867292594309],"type":"Point"}
}