{
  "type": "Feature",
  "properties": {
    "iso:country":"GB",
    "wof:name":"TS9 6QQ",
    "wof:placetype":"postalcode"
},
  "geometry": {"coordinates":[-1.13971919815425,54.49774385761006],"type":"Point"}
}