{
  "type": "Feature",
  "properties": {
    "iso:country": "GB",
    "wof:name": "NN6 7WU",
    "wof:placetype": "postalcode"
  },
  "geometry": {"coordinates":[-1.085972,52.295959],"type":"Point"}
}
