{
  "type": "Feature",
  "properties": {
    "date:inception_lower":"2018-07-01",
    "date:inception_upper":"2018-07-31",
    "iso:country":"GB",
    "wof:name":"NN6 7WU",
    "wof:placetype":"postalcode"
},
  "geometry": {"coordinates":[-1.085972,52.295959],"type":"Point"}
}