{
  "type": "Feature",
  "properties": {
    "date:inception_lower": "2018-07-01",
    "date:inception_upper": "2018-07-01",
    "iso:country": "GB",
    "wof:name": "NN6 7WU",
    "wof:placetype": "postalcode"
  },
  "geometry": {"coordinates":[-1.084028,52.294937],"type":"Point"}
}
