{
  "type": "Feature",
  "properties": {
    "iso:country": "GB",
    "wof:name": "OL15 0EX",
    "wof:placetype": "postalcode"
  },
  "geometry": {"coordinates":[-2.108813,53.632609],"type":"Point"}
}
