{
  "type": "Feature",
  "properties": {
    "iso:country":"GB",
    "wof:name":"OL15 0EX",
    "wof:placetype":"postalcode"
},
  "geometry": {"coordinates":[-2.10881281998671,53.63260919459437],"type":"Point"}
}