{
  "type": "Feature",
  "properties": {
    "date:inception_lower":"2011-02-01",
    "date:inception_upper":"2011-02-28",
    "iso:country":"GB",
    "wof:name":"OL15 0EX",
    "wof:placetype":"postalcode"
},
  "geometry": {"coordinates":[-2.108813,53.632609],"type":"Point"}
}