{
  "type": "Feature",
  "properties": {
    "iso:country": "GB",
    "wof:name": "DN32 0NQ",
    "wof:placetype": "postalcode"
  },
  "geometry": {"coordinates":[-0.079454,53.558973],"type":"Point"}
}
