{
  "type": "Feature",
  "properties": {
    "iso:country":"GB",
    "wof:name":"DN32 0NQ",
    "wof:placetype":"postalcode"
},
  "geometry": {"coordinates":[-0.07945446094284,53.55897303302172],"type":"Point"}
}