{
  "type": "Feature",
  "properties": {
    "iso:country":"GB",
    "wof:name":"B66 4HB",
    "wof:placetype":"postalcode"
},
  "geometry": {"coordinates":[-1.97018592069799,52.47726157238659],"type":"Point"}
}