{
  "type": "Feature",
  "properties": {
    "iso:country": "GB",
    "wof:name": "B66 4HB",
    "wof:placetype": "postalcode"
  },
  "geometry": {"coordinates":[-1.970186,52.477262],"type":"Point"}
}
