{
  "type": "Feature",
  "properties": {
    "iso:country":"GB",
    "wof:name":"N16 5UG",
    "wof:placetype":"postalcode"
},
  "geometry": {"coordinates":[-0.08801009371088,51.56725899718247],"type":"Point"}
}