{
  "type": "Feature",
  "properties": {
    "iso:country":"GB",
    "wof:name":"SA6 8JN",
    "wof:placetype":"postalcode"
},
  "geometry": {"coordinates":[-3.93229185845516,51.65011595139786],"type":"Point"}
}