{
  "type": "Feature",
  "properties": {
    "date:inception_lower": "2008-01-01",
    "date:inception_upper": "2008-01-01",
    "iso:country": "GB",
    "wof:name": "LN5 7RH",
    "wof:placetype": "postalcode"
  },
  "geometry": {"coordinates":[-0.540735,53.22245],"type":"Point"}
}
