{
  "type": "Feature",
  "properties": {
    "iso:country":"GB",
    "wof:name":"LN5 7RH",
    "wof:placetype":"postalcode"
},
  "geometry": {"coordinates":[-0.540688308578,53.22249006930299],"type":"Point"}
}