{
  "type": "Feature",
  "properties": {
    "date:inception_lower": "2017-01-01",
    "date:inception_upper": "2017-01-01",
    "iso:country": "GB",
    "wof:name": "DH4 6NZ",
    "wof:placetype": "postalcode"
  },
  "geometry": {"coordinates":[-1.486881,54.85426],"type":"Point"}
}
