{
  "type": "Feature",
  "properties": {
    "date:inception_lower": "2018-12-01",
    "date:inception_upper": "2018-12-01",
    "iso:country": "GB",
    "wof:name": "OX25 5BB",
    "wof:placetype": "postalcode"
  },
  "geometry": {"coordinates":[-1.254254,51.926015],"type":"Point"}
}
