{
  "type": "Feature",
  "properties": {
    "iso:country": "GB",
    "wof:name": "LE17 5HY",
    "wof:placetype": "postalcode"
  },
  "geometry": {"coordinates":[-1.222735,52.489646],"type":"Point"}
}
