{
  "type": "Feature",
  "properties": {
    "iso:country":"GB",
    "wof:name":"L6 9DP",
    "wof:placetype":"postalcode"
},
  "geometry": {"coordinates":[-2.9529232681805,53.41686464611627],"type":"Point"}
}