{
  "type": "Feature",
  "properties": {
    "iso:country": "GB",
    "wof:name": "WA16 0PL",
    "wof:placetype": "postalcode"
  },
  "geometry": {"coordinates":[-2.413135,53.316233],"type":"Point"}
}
