{
  "type": "Feature",
  "properties": {
    "iso:country":"GB",
    "wof:name":"WA16 0PL",
    "wof:placetype":"postalcode"
},
  "geometry": {"coordinates":[-2.41313472469581,53.31623258971263],"type":"Point"}
}