{
  "type": "Feature",
  "properties": {
    "iso:country":"GB",
    "wof:name":"SY3 0HW",
    "wof:placetype":"postalcode"
},
  "geometry": {"coordinates":[-2.77002053469071,52.6687625033478],"type":"Point"}
}