{
  "type": "Feature",
  "properties": {
    "date:inception_lower":"1990-07-01",
    "date:inception_upper":"1990-07-31",
    "iso:country":"GB",
    "wof:name":"SY3 0HW",
    "wof:placetype":"postalcode"
},
  "geometry": {"coordinates":[-2.77002,52.668763],"type":"Point"}
}