{
  "type": "Feature",
  "properties": {
    "iso:country":"GB",
    "wof:name":"G61 4HY",
    "wof:placetype":"postalcode"
},
  "geometry": {"coordinates":[-4.35107383995962,55.92414426575165],"type":"Point"}
}