{
  "type": "Feature",
  "properties": {
    "iso:country":"GB",
    "wof:name":"HP12 3EA",
    "wof:placetype":"postalcode"
},
  "geometry": {"coordinates":[-0.77187993088277,51.63381146444544],"type":"Point"}
}