{
  "type": "Feature",
  "properties": {
    "iso:country":"GB",
    "wof:name":"DA14 6AP",
    "wof:placetype":"postalcode"
},
  "geometry": {"coordinates":[0.09924676953383,51.42348224558496],"type":"Point"}
}