{
  "type": "Feature",
  "properties": {
    "iso:country": "GB",
    "wof:name": "AL10 0NF",
    "wof:placetype": "postalcode"
  },
  "geometry": {"coordinates":[-0.226526,51.76485],"type":"Point"}
}
