{
  "type": "Feature",
  "properties": {
    "date:inception_lower":"1980-01-01",
    "date:inception_upper":"1980-01-31",
    "iso:country":"GB",
    "wof:name":"TW1 3SX",
    "wof:placetype":"postalcode"
},
  "geometry": {"coordinates":[-0.328698,51.447388],"type":"Point"}
}