{
  "type": "Feature",
  "properties": {
    "iso:country":"GB",
    "wof:name":"TW1 3SX",
    "wof:placetype":"postalcode"
},
  "geometry": {"coordinates":[-0.32850730341168,51.44690921008248],"type":"Point"}
}