{
  "type": "Feature",
  "properties": {
    "iso:country":"GB",
    "wof:name":"NR21 9RH",
    "wof:placetype":"postalcode"
},
  "geometry": {"coordinates":[0.84885900731625,52.84012203219268],"type":"Point"}
}