{
  "type": "Feature",
  "properties": {
    "iso:country":"GB",
    "wof:name":"LS5 3BW",
    "wof:placetype":"postalcode"
},
  "geometry": {"coordinates":[-1.60669217902552,53.81597371855791],"type":"Point"}
}