{
  "type": "Feature",
  "properties": {
    "iso:country": "GB",
    "wof:name": "PO3 5GD",
    "wof:placetype": "postalcode"
  },
  "geometry": {"coordinates":[-1.067918,50.833024],"type":"Point"}
}
