{
  "type": "Feature",
  "properties": {
    "iso:country":"GB",
    "wof:name":"PO3 5GD",
    "wof:placetype":"postalcode"
},
  "geometry": {"coordinates":[-1.06791783934745,50.83302430299335],"type":"Point"}
}