{
  "type": "Feature",
  "properties": {
    "iso:country":"GB",
    "wof:name":"BH13 7QE",
    "wof:placetype":"postalcode"
},
  "geometry": {"coordinates":[-1.94202267889957,50.68675171310451],"type":"Point"}
}