{
  "type": "Feature",
  "properties": {
    "date:inception_lower": "1993-01-01",
    "date:inception_upper": "1993-01-01",
    "iso:country": "GB",
    "wof:name": "DN39 6RY",
    "wof:placetype": "postalcode"
  },
  "geometry": {"coordinates":[-0.329144,53.616928],"type":"Point"}
}
