{
  "type": "Feature",
  "properties": {
    "iso:country":"GB",
    "wof:name":"SL1 8AN",
    "wof:placetype":"postalcode"
},
  "geometry": {"coordinates":[-0.6580077452046,51.53767394832403],"type":"Point"}
}