{
  "type": "Feature",
  "properties": {
    "date:inception_lower":"1980-01-01",
    "date:inception_upper":"1980-01-31",
    "iso:country":"GB",
    "wof:name":"SL1 8AN",
    "wof:placetype":"postalcode"
},
  "geometry": {"coordinates":[-0.658008,51.537674],"type":"Point"}
}