{
  "type": "Feature",
  "properties": {
    "date:inception_lower": "1996-06-01",
    "date:inception_upper": "1996-06-01",
    "iso:country": "GB",
    "wof:name": "AB24 5NG",
    "wof:placetype": "postalcode"
  },
  "geometry": {"coordinates":[-2.086434,57.155273],"type":"Point"}
}
