{
  "type": "Feature",
  "properties": {
    "iso:country":"GB",
    "wof:name":"AB24 5NG",
    "wof:placetype":"postalcode"
},
  "geometry": {"coordinates":[-2.08643429725862,57.1552728284592],"type":"Point"}
}