{
  "type": "Feature",
  "properties": {
    "iso:country":"GB",
    "wof:name":"BN9 0HE",
    "wof:placetype":"postalcode"
},
  "geometry": {"coordinates":[0.05225915273752,50.80317578919205],"type":"Point"}
}