{
  "type": "Feature",
  "properties": {
    "iso:country":"GB",
    "wof:name":"NR8 6HG",
    "wof:placetype":"postalcode"
},
  "geometry": {"coordinates":[1.21960860693728,52.68633172883523],"type":"Point"}
}