{
  "type": "Feature",
  "properties": {
    "date:inception_lower": "2005-03-01",
    "date:inception_upper": "2005-03-01",
    "iso:country": "GB",
    "wof:name": "NR8 6HG",
    "wof:placetype": "postalcode"
  },
  "geometry": {"coordinates":[1.219609,52.686332],"type":"Point"}
}
