{
  "type": "Feature",
  "properties": {
    "iso:country":"GB",
    "wof:name":"GU10 2EH",
    "wof:placetype":"postalcode"
},
  "geometry": {"coordinates":[-0.75552386903081,51.1601607574331],"type":"Point"}
}