{
  "type": "Feature",
  "properties": {
    "iso:country":"GB",
    "wof:name":"AB10 7EP",
    "wof:placetype":"postalcode"
},
  "geometry": {"coordinates":[-2.14765731204583,57.12118786636906],"type":"Point"}
}