{
  "type": "Feature",
  "properties": {
    "iso:country": "GB",
    "wof:name": "FK1 4RE",
    "wof:placetype": "postalcode"
  },
  "geometry": {"coordinates":[-3.825255,55.997916],"type":"Point"}
}
