{
  "type": "Feature",
  "properties": {
    "date:inception_lower": "1980-01-01",
    "date:inception_upper": "1980-01-01",
    "iso:country": "GB",
    "wof:name": "FK1 4RE",
    "wof:placetype": "postalcode"
  },
  "geometry": {"coordinates":[-3.825255,55.997916],"type":"Point"}
}
