{
  "type": "Feature",
  "properties": {
    "iso:country": "GB",
    "wof:name": "DA1 4RB",
    "wof:placetype": "postalcode"
  },
  "geometry": {"coordinates":[0.180678,51.462491],"type":"Point"}
}
