{
  "type": "Feature",
  "properties": {
    "date:inception_lower": "1980-01-01",
    "date:inception_upper": "1980-01-01",
    "iso:country": "GB",
    "wof:name": "DA1 4RB",
    "wof:placetype": "postalcode"
  },
  "geometry": {"coordinates":[0.180678,51.462491],"type":"Point"}
}
