{
  "type": "Feature",
  "properties": {
    "iso:country":"GB",
    "wof:name":"IP3 8RU",
    "wof:placetype":"postalcode"
},
  "geometry": {"coordinates":[1.20748959266797,52.04244978010742],"type":"Point"}
}