{
  "type": "Feature",
  "properties": {
    "iso:country": "GB",
    "wof:name": "CO16 0AU",
    "wof:placetype": "postalcode"
  },
  "geometry": {"coordinates":[1.172075,51.885204],"type":"Point"}
}
