{
  "type": "Feature",
  "properties": {
    "iso:country":"GB",
    "wof:name":"PE10 9TR",
    "wof:placetype":"postalcode"
},
  "geometry": {"coordinates":[-0.38117150679794,52.77763818472649],"type":"Point"}
}