{
  "type": "Feature",
  "properties": {
    "date:inception_lower": "1980-01-01",
    "date:inception_upper": "1980-01-01",
    "iso:country": "GB",
    "wof:name": "RM3 7JD",
    "wof:placetype": "postalcode"
  },
  "geometry": {"coordinates":[0.211422,51.598043],"type":"Point"}
}
