{
  "type": "Feature",
  "properties": {
    "iso:country":"GB",
    "wof:name":"RM3 7JD",
    "wof:placetype":"postalcode"
},
  "geometry": {"coordinates":[0.21138150706233,51.59804141532982],"type":"Point"}
}