{
  "type": "Feature",
  "properties": {
    "iso:country": "GB",
    "wof:name": "CV11 4GG",
    "wof:placetype": "postalcode"
  },
  "geometry": {"coordinates":[-1.447298,52.50246],"type":"Point"}
}
