{
  "type": "Feature",
  "properties": {
    "iso:country":"GB",
    "wof:name":"CV11 4GG",
    "wof:placetype":"postalcode"
},
  "geometry": {"coordinates":[-1.4472980912213,52.50246018620449],"type":"Point"}
}