{
  "type": "Feature",
  "properties": {
    "iso:country":"GB",
    "wof:name":"SR4 0HE",
    "wof:placetype":"postalcode"
},
  "geometry": {"coordinates":[-1.44022381256639,54.90332707597653],"type":"Point"}
}