{
  "type": "Feature",
  "properties": {
    "date:inception_lower": "1980-01-01",
    "date:inception_upper": "1980-01-01",
    "iso:country": "GB",
    "wof:name": "NN1 1JA",
    "wof:placetype": "postalcode"
  },
  "geometry": {"coordinates":[-0.893541,52.23714],"type":"Point"}
}
