{
  "type": "Feature",
  "properties": {
    "iso:country":"GB",
    "wof:name":"TQ9 6QU",
    "wof:placetype":"postalcode"
},
  "geometry": {"coordinates":[-3.62545049168776,50.4050160650732],"type":"Point"}
}