{
  "type": "Feature",
  "properties": {
    "iso:country":"GB",
    "wof:name":"TR16 5QW",
    "wof:placetype":"postalcode"
},
  "geometry": {"coordinates":[-5.18015829011847,50.23060986362319],"type":"Point"}
}