{
  "type": "Feature",
  "properties": {
    "date:inception_lower":"1980-01-01",
    "date:inception_upper":"1980-01-31",
    "iso:country":"GB",
    "wof:name":"TR16 5QW",
    "wof:placetype":"postalcode"
},
  "geometry": {"coordinates":[-5.180191,50.230582],"type":"Point"}
}