{
  "type": "Feature",
  "properties": {
    "iso:country": "GB",
    "wof:name": "DH5 8HJ",
    "wof:placetype": "postalcode"
  },
  "geometry": {"coordinates":[-1.460029,54.83689],"type":"Point"}
}
