{
  "type": "Feature",
  "properties": {
    "iso:country": "GB",
    "wof:name": "CB9 7YX",
    "wof:placetype": "postalcode"
  },
  "geometry": {"coordinates":[0.467927,52.069803],"type":"Point"}
}
