{
  "type": "Feature",
  "properties": {
    "iso:country":"GB",
    "wof:name":"RG14 6AW",
    "wof:placetype":"postalcode"
},
  "geometry": {"coordinates":[-1.33755966865163,51.39409903772302],"type":"Point"}
}