{
  "type": "Feature",
  "properties": {
    "iso:country":"GB",
    "wof:name":"DL6 1JH",
    "wof:placetype":"postalcode"
},
  "geometry": {"coordinates":[-1.42834406671311,54.34052330061139],"type":"Point"}
}