{
  "type": "Feature",
  "properties": {
    "date:inception_lower": "1985-10-01",
    "date:inception_upper": "1985-10-01",
    "iso:country": "GB",
    "wof:name": "L39 3QG",
    "wof:placetype": "postalcode"
  },
  "geometry": {"coordinates":[-2.885707,53.568597],"type":"Point"}
}
