{
  "type": "Feature",
  "properties": {
    "iso:country":"GB",
    "wof:name":"WA8 7DP",
    "wof:placetype":"postalcode"
},
  "geometry": {"coordinates":[-2.73893851317116,53.37271780788662],"type":"Point"}
}