{
  "type": "Feature",
  "properties": {
    "iso:country": "GB",
    "wof:name": "WA8 7DP",
    "wof:placetype": "postalcode"
  },
  "geometry": {"coordinates":[-2.738938,53.372718],"type":"Point"}
}
