{
  "type": "Feature",
  "properties": {
    "iso:country":"GB",
    "wof:name":"TR1 2DF",
    "wof:placetype":"postalcode"
},
  "geometry": {"coordinates":[-5.05980961287385,50.25914045498669],"type":"Point"}
}