{
  "type": "Feature",
  "properties": {
    "iso:country":"GB",
    "wof:name":"DA5 3HW",
    "wof:placetype":"postalcode"
},
  "geometry": {"coordinates":[0.12636426733962,51.43656369642046],"type":"Point"}
}