{
  "type": "Feature",
  "properties": {
    "iso:country":"GB",
    "wof:name":"BN21 2QS",
    "wof:placetype":"postalcode"
},
  "geometry": {"coordinates":[0.26537930244402,50.78499341411876],"type":"Point"}
}