{
  "type": "Feature",
  "properties": {
    "date:inception_lower":"1980-01-01",
    "date:inception_upper":"1980-01-31",
    "iso:country":"GB",
    "wof:name":"BD10 8UQ",
    "wof:placetype":"postalcode"
},
  "geometry": {"coordinates":[-1.737818,53.837058],"type":"Point"}
}