{
  "type": "Feature",
  "properties": {
    "iso:country": "GB",
    "wof:name": "DD2 3FN",
    "wof:placetype": "postalcode"
  },
  "geometry": {"coordinates":[-3.00333,56.471161],"type":"Point"}
}
