{
  "type": "Feature",
  "properties": {
    "date:inception_lower": "1995-12-01",
    "date:inception_upper": "1995-12-01",
    "iso:country": "GB",
    "wof:name": "DD2 3FN",
    "wof:placetype": "postalcode"
  },
  "geometry": {"coordinates":[-3.00333,56.471161],"type":"Point"}
}
