{
  "type": "Feature",
  "properties": {
    "iso:country":"GB",
    "wof:name":"M26 1AD",
    "wof:placetype":"postalcode"
},
  "geometry": {"coordinates":[-2.32928228823634,53.55691925376203],"type":"Point"}
}