{
  "type": "Feature",
  "properties": {
    "iso:country": "GB",
    "wof:name": "M26 1AD",
    "wof:placetype": "postalcode"
  },
  "geometry": {"coordinates":[-2.326127,53.559101],"type":"Point"}
}
