{
  "type": "Feature",
  "properties": {
    "iso:country":"GB",
    "wof:name":"PE8 6XG",
    "wof:placetype":"postalcode"
},
  "geometry": {"coordinates":[-0.51691795150244,52.56356969413568],"type":"Point"}
}