{
  "type": "Feature",
  "properties": {
    "iso:country":"GB",
    "wof:name":"WS9 9BU",
    "wof:placetype":"postalcode"
},
  "geometry": {"coordinates":[-1.92476692365094,52.62319176515432],"type":"Point"}
}