{
  "type": "Feature",
  "properties": {
    "iso:country": "GB",
    "wof:name": "SL6 0ER",
    "wof:placetype": "postalcode"
  },
  "geometry": {"coordinates":[-0.694307,51.531393],"type":"Point"}
}
