{
  "type": "Feature",
  "properties": {
    "date:inception_lower": "1995-01-01",
    "date:inception_upper": "1995-01-01",
    "iso:country": "GB",
    "wof:name": "SL6 0ER",
    "wof:placetype": "postalcode"
  },
  "geometry": {"coordinates":[-0.694307,51.531393],"type":"Point"}
}
