{
  "type": "Feature",
  "properties": {
    "iso:country":"GB",
    "wof:name":"SL6 0ER",
    "wof:placetype":"postalcode"
},
  "geometry": {"coordinates":[-0.69430680935696,51.53139348059581],"type":"Point"}
}