{
  "type": "Feature",
  "properties": {
    "iso:country":"GB",
    "wof:name":"YO1 8AA",
    "wof:placetype":"postalcode"
},
  "geometry": {"coordinates":[-1.08566425452683,53.96025322652675],"type":"Point"}
}