{
  "type": "Feature",
  "properties": {
    "iso:country": "GB",
    "wof:name": "EH12 5TA",
    "wof:placetype": "postalcode"
  },
  "geometry": {"coordinates":[-3.255591,55.942612],"type":"Point"}
}
