{
  "type": "Feature",
  "properties": {
    "iso:country": "GB",
    "wof:name": "NR31 6JL",
    "wof:placetype": "postalcode"
  },
  "geometry": {"coordinates":[1.720777,52.56019],"type":"Point"}
}
