{
  "type": "Feature",
  "properties": {
    "date:inception_lower": "1980-01-01",
    "date:inception_upper": "1980-01-01",
    "iso:country": "GB",
    "wof:name": "NR31 6JL",
    "wof:placetype": "postalcode"
  },
  "geometry": {"coordinates":[1.720777,52.56019],"type":"Point"}
}
