{
  "type": "Feature",
  "properties": {
    "iso:country":"GB",
    "wof:name":"NR31 6JL",
    "wof:placetype":"postalcode"
},
  "geometry": {"coordinates":[1.72077674867946,52.5601898329863],"type":"Point"}
}