{
  "type": "Feature",
  "properties": {
    "iso:country": "GB",
    "wof:name": "CT13 9FP",
    "wof:placetype": "postalcode"
  },
  "geometry": {"coordinates":[1.347657,51.290975],"type":"Point"}
}
