{
  "type": "Feature",
  "properties": {
    "date:inception_lower": "1985-04-01",
    "date:inception_upper": "1985-04-01",
    "iso:country": "GB",
    "wof:name": "WS10 8SU",
    "wof:placetype": "postalcode"
  },
  "geometry": {"coordinates":[-2.05374,52.561255],"type":"Point"}
}
