{
  "type": "Feature",
  "properties": {
    "iso:country":"GB",
    "wof:name":"CF63 3NZ",
    "wof:placetype":"postalcode"
},
  "geometry": {"coordinates":[-3.25568592185214,51.40873434777598],"type":"Point"}
}