{
  "type": "Feature",
  "properties": {
    "iso:country":"GB",
    "wof:name":"GL4 0PQ",
    "wof:placetype":"postalcode"
},
  "geometry": {"coordinates":[-2.25808788736764,51.83166454808853],"type":"Point"}
}