{
  "type": "Feature",
  "properties": {
    "iso:country": "GB",
    "wof:name": "GL4 0PQ",
    "wof:placetype": "postalcode"
  },
  "geometry": {"coordinates":[-2.258088,51.831665],"type":"Point"}
}
