{
  "type": "Feature",
  "properties": {
    "iso:country":"GB",
    "wof:name":"BS1 6TS",
    "wof:placetype":"postalcode"
},
  "geometry": {"coordinates":[-2.61180617199484,51.44682899964483],"type":"Point"}
}