{
  "type": "Feature",
  "properties": {
    "date:inception_lower":"1986-07-01",
    "date:inception_upper":"1986-07-31",
    "iso:country":"GB",
    "wof:name":"BS1 6TS",
    "wof:placetype":"postalcode"
},
  "geometry": {"coordinates":[-2.611806,51.446829],"type":"Point"}
}