{
  "type": "Feature",
  "properties": {
    "iso:country":"GB",
    "wof:name":"B26 2UL",
    "wof:placetype":"postalcode"
},
  "geometry": {"coordinates":[-1.78870379774676,52.45963647343168],"type":"Point"}
}