{
  "type": "Feature",
  "properties": {
    "iso:country": "GB",
    "wof:name": "FY6 7DN",
    "wof:placetype": "postalcode"
  },
  "geometry": {"coordinates":[-2.998736,53.844375],"type":"Point"}
}
