{
  "type": "Feature",
  "properties": {
    "date:inception_lower":"1980-01-01",
    "date:inception_upper":"1980-01-31",
    "iso:country":"GB",
    "wof:name":"FY6 7DN",
    "wof:placetype":"postalcode"
},
  "geometry": {"coordinates":[-2.998736,53.844375],"type":"Point"}
}