{
  "type": "Feature",
  "properties": {
    "iso:country":"GB",
    "wof:name":"FY6 7DN",
    "wof:placetype":"postalcode"
},
  "geometry": {"coordinates":[-2.99873636765568,53.84437512688272],"type":"Point"}
}