{
  "type": "Feature",
  "properties": {
    "iso:country":"GB",
    "wof:name":"B62 8LZ",
    "wof:placetype":"postalcode"
},
  "geometry": {"coordinates":[-2.03559271340472,52.46702924289388],"type":"Point"}
}