{
  "type": "Feature",
  "properties": {
    "date:inception_lower": "1980-01-01",
    "date:inception_upper": "1980-01-01",
    "iso:country": "GB",
    "wof:name": "B62 8LZ",
    "wof:placetype": "postalcode"
  },
  "geometry": {"coordinates":[-2.035601,52.467035],"type":"Point"}
}
