{
  "type": "Feature",
  "properties": {
    "iso:country":"GB",
    "wof:name":"GU34 2EW",
    "wof:placetype":"postalcode"
},
  "geometry": {"coordinates":[-0.98393416446506,51.15233196115823],"type":"Point"}
}