{
  "type": "Feature",
  "properties": {
    "date:inception_lower":"1990-07-01",
    "date:inception_upper":"1990-07-31",
    "iso:country":"GB",
    "wof:name":"DL1 2FD",
    "wof:placetype":"postalcode"
},
  "geometry": {"coordinates":[-1.535441,54.543257],"type":"Point"}
}