{
  "type": "Feature",
  "properties": {
    "iso:country": "GB",
    "wof:name": "HP14 3QL",
    "wof:placetype": "postalcode"
  },
  "geometry": {"coordinates":[-0.89718,51.657201],"type":"Point"}
}
