{
  "type": "Feature",
  "properties": {
    "iso:country":"GB",
    "wof:name":"HP14 3QL",
    "wof:placetype":"postalcode"
},
  "geometry": {"coordinates":[-0.89717955362848,51.65720128101223],"type":"Point"}
}