{
  "type": "Feature",
  "properties": {
    "iso:country": "GB",
    "wof:name": "EH3 5JF",
    "wof:placetype": "postalcode"
  },
  "geometry": {"coordinates":[-3.21034,55.961485],"type":"Point"}
}
