{
  "type": "Feature",
  "properties": {
    "iso:country": "GB",
    "wof:name": "E2 9AN",
    "wof:placetype": "postalcode"
  },
  "geometry": {"coordinates":[-0.054484,51.530558],"type":"Point"}
}
