{
  "type": "Feature",
  "properties": {
    "iso:country":"GB",
    "wof:name":"HG4 3NX",
    "wof:placetype":"postalcode"
},
  "geometry": {"coordinates":[-1.64962449133599,54.15118713818587],"type":"Point"}
}