{
  "type": "Feature",
  "properties": {
    "iso:country": "GB",
    "wof:name": "HG4 3NX",
    "wof:placetype": "postalcode"
  },
  "geometry": {"coordinates":[-1.649624,54.151187],"type":"Point"}
}
