{
  "type": "Feature",
  "properties": {
    "iso:country":"GB",
    "wof:name":"GU12 4DZ",
    "wof:placetype":"postalcode"
},
  "geometry": {"coordinates":[-0.74236435729998,51.24122130755512],"type":"Point"}
}