{
  "type": "Feature",
  "properties": {
    "iso:country": "GB",
    "wof:name": "SL6 0EX",
    "wof:placetype": "postalcode"
  },
  "geometry": {"coordinates":[-0.687102,51.532284],"type":"Point"}
}
