{
  "type": "Feature",
  "properties": {
    "date:inception_lower":"1980-01-01",
    "date:inception_upper":"1980-01-31",
    "iso:country":"GB",
    "wof:name":"TS18 3ST",
    "wof:placetype":"postalcode"
},
  "geometry": {"coordinates":[-1.314719,54.558761],"type":"Point"}
}