{
  "type": "Feature",
  "properties": {
    "iso:country": "GB",
    "wof:name": "PL6 6GA",
    "wof:placetype": "postalcode"
  },
  "geometry": {"coordinates":[-4.140071,50.427144],"type":"Point"}
}
