{
  "type": "Feature",
  "properties": {
    "iso:country":"GB",
    "wof:name":"PO36 0JQ",
    "wof:placetype":"postalcode"
},
  "geometry": {"coordinates":[-1.16078904903202,50.68384594004863],"type":"Point"}
}