{
  "type": "Feature",
  "properties": {
    "iso:country":"GB",
    "wof:name":"KA22 8GA",
    "wof:placetype":"postalcode"
},
  "geometry": {"coordinates":[-4.81627436368738,55.6402515792369],"type":"Point"}
}