{
  "type": "Feature",
  "properties": {
    "date:inception_lower":"2008-09-01",
    "date:inception_upper":"2008-09-30",
    "iso:country":"GB",
    "wof:name":"KA22 8GA",
    "wof:placetype":"postalcode"
},
  "geometry": {"coordinates":[-4.816274,55.640252],"type":"Point"}
}