{
  "type": "Feature",
  "properties": {
    "date:inception_lower":"1998-06-01",
    "date:inception_upper":"1998-06-30",
    "iso:country":"GB",
    "wof:name":"B61 0TR",
    "wof:placetype":"postalcode"
},
  "geometry": {"coordinates":[-2.047815,52.363091],"type":"Point"}
}