{
  "type": "Feature",
  "properties": {
    "iso:country":"GB",
    "wof:name":"B61 0TR",
    "wof:placetype":"postalcode"
},
  "geometry": {"coordinates":[-2.04781471581819,52.36309084635479],"type":"Point"}
}