{
  "type": "Feature",
  "properties": {
    "date:inception_lower": "1980-01-01",
    "date:inception_upper": "1980-01-01",
    "iso:country": "GB",
    "wof:name": "TN22 5UQ",
    "wof:placetype": "postalcode"
  },
  "geometry": {"coordinates":[0.085299,50.926738],"type":"Point"}
}
