{
  "type": "Feature",
  "properties": {
    "iso:country":"GB",
    "wof:name":"TN22 5UQ",
    "wof:placetype":"postalcode"
},
  "geometry": {"coordinates":[0.08529928862407,50.92673812626965],"type":"Point"}
}