{
  "type": "Feature",
  "properties": {
    "iso:country":"GB",
    "wof:name":"ST3 3LR",
    "wof:placetype":"postalcode"
},
  "geometry": {"coordinates":[-2.15519841360323,52.96468703720387],"type":"Point"}
}