{
  "type": "Feature",
  "properties": {
    "iso:country":"GB",
    "wof:name":"NE26 2AU",
    "wof:placetype":"postalcode"
},
  "geometry": {"coordinates":[-1.44072229418489,55.04283330976661],"type":"Point"}
}