{
  "type": "Feature",
  "properties": {
    "iso:country":"GB",
    "wof:name":"EH10 6TL",
    "wof:placetype":"postalcode"
},
  "geometry": {"coordinates":[-3.20179036049659,55.90838353731122],"type":"Point"}
}