{
  "type": "Feature",
  "properties": {
    "iso:country":"GB",
    "wof:name":"PE31 8RH",
    "wof:placetype":"postalcode"
},
  "geometry": {"coordinates":[0.71836868803369,52.82157532508814],"type":"Point"}
}