{
  "type": "Feature",
  "properties": {
    "iso:country": "GB",
    "wof:name": "PE31 8RH",
    "wof:placetype": "postalcode"
  },
  "geometry": {"coordinates":[0.718369,52.821575],"type":"Point"}
}
