{
  "type": "Feature",
  "properties": {
    "date:inception_lower": "1980-01-01",
    "date:inception_upper": "1980-01-01",
    "iso:country": "GB",
    "wof:name": "B12 8QA",
    "wof:placetype": "postalcode"
  },
  "geometry": {"coordinates":[-1.881293,52.453131],"type":"Point"}
}
