{
  "type": "Feature",
  "properties": {
    "iso:country":"GB",
    "wof:name":"WN8 6QG",
    "wof:placetype":"postalcode"
},
  "geometry": {"coordinates":[-2.76576259909482,53.55649329191145],"type":"Point"}
}