{
  "type": "Feature",
  "properties": {
    "iso:country":"GB",
    "wof:name":"MK7 7FA",
    "wof:placetype":"postalcode"
},
  "geometry": {"coordinates":[-0.70501130377536,52.01782150698634],"type":"Point"}
}