{
  "type": "Feature",
  "properties": {
    "iso:country": "GB",
    "wof:name": "PH10 6DD",
    "wof:placetype": "postalcode"
  },
  "geometry": {"coordinates":[-3.334331,56.58853],"type":"Point"}
}
