{
  "type": "Feature",
  "properties": {
    "date:inception_lower":"1999-12-01",
    "date:inception_upper":"1999-12-31",
    "iso:country":"GB",
    "wof:name":"PH10 6DD",
    "wof:placetype":"postalcode"
},
  "geometry": {"coordinates":[-3.334331,56.58853],"type":"Point"}
}