{
  "type": "Feature",
  "properties": {
    "iso:country": "GB",
    "wof:name": "B98 9LL",
    "wof:placetype": "postalcode"
  },
  "geometry": {"coordinates":[-1.904303,52.319091],"type":"Point"}
}
