{
  "type": "Feature",
  "properties": {
    "date:inception_lower":"1980-01-01",
    "date:inception_upper":"1980-01-31",
    "iso:country":"GB",
    "wof:name":"B98 9LL",
    "wof:placetype":"postalcode"
},
  "geometry": {"coordinates":[-1.904303,52.319091],"type":"Point"}
}