{
  "type": "Feature",
  "properties": {
    "date:inception_lower":"1980-01-01",
    "date:inception_upper":"1980-01-31",
    "iso:country":"GB",
    "wof:name":"CV4 8GD",
    "wof:placetype":"postalcode"
},
  "geometry": {"coordinates":[-1.557163,52.389899],"type":"Point"}
}