{
  "type": "Feature",
  "properties": {
    "iso:country":"GB",
    "wof:name":"CV4 8GD",
    "wof:placetype":"postalcode"
},
  "geometry": {"coordinates":[-1.55707403195625,52.38994342462326],"type":"Point"}
}