{
  "type": "Feature",
  "properties": {
    "iso:country":"GB",
    "wof:name":"NE71 6JE",
    "wof:placetype":"postalcode"
},
  "geometry": {"coordinates":[-2.11467153629391,55.60219013389484],"type":"Point"}
}