{
  "type": "Feature",
  "properties": {
    "iso:country": "GB",
    "wof:name": "WF9 2NU",
    "wof:placetype": "postalcode"
  },
  "geometry": {"coordinates":[-1.299161,53.597702],"type":"Point"}
}
