{
  "type": "Feature",
  "properties": {
    "iso:country":"GB",
    "wof:name":"TN15 8QZ",
    "wof:placetype":"postalcode"
},
  "geometry": {"coordinates":[0.34800835694023,51.29197354919555],"type":"Point"}
}