{
  "type": "Feature",
  "properties": {
    "iso:country": "GB",
    "wof:name": "TN15 8QZ",
    "wof:placetype": "postalcode"
  },
  "geometry": {"coordinates":[0.348008,51.291974],"type":"Point"}
}
