{
  "type": "Feature",
  "properties": {
    "date:inception_lower": "1980-01-01",
    "date:inception_upper": "1980-01-01",
    "iso:country": "GB",
    "wof:name": "BB5 5QB",
    "wof:placetype": "postalcode"
  },
  "geometry": {"coordinates":[-2.38616,53.778353],"type":"Point"}
}
