{
  "type": "Feature",
  "properties": {
    "iso:country":"GB",
    "wof:name":"RH1 3JB",
    "wof:placetype":"postalcode"
},
  "geometry": {"coordinates":[-0.14394760915156,51.26130131906896],"type":"Point"}
}