{
  "type": "Feature",
  "properties": {
    "iso:country": "GB",
    "wof:name": "ML3 6TT",
    "wof:placetype": "postalcode"
  },
  "geometry": {"coordinates":[-4.050435,55.76634],"type":"Point"}
}
