{
  "type": "Feature",
  "properties": {
    "iso:country": "GB",
    "wof:name": "DN14 0ED",
    "wof:placetype": "postalcode"
  },
  "geometry": {"coordinates":[-1.103812,53.654923],"type":"Point"}
}
