{
  "type": "Feature",
  "properties": {
    "date:inception_lower": "1980-01-01",
    "date:inception_upper": "1980-01-01",
    "iso:country": "GB",
    "wof:name": "DN14 0ED",
    "wof:placetype": "postalcode"
  },
  "geometry": {"coordinates":[-1.103812,53.654923],"type":"Point"}
}
