{
  "type": "Feature",
  "properties": {
    "iso:country":"GB",
    "wof:name":"SS6 9JE",
    "wof:placetype":"postalcode"
},
  "geometry": {"coordinates":[0.60173520151527,51.59291306015388],"type":"Point"}
}