{
  "type": "Feature",
  "properties": {
    "iso:country":"GB",
    "wof:name":"N7 9AU",
    "wof:placetype":"postalcode"
},
  "geometry": {"coordinates":[-0.12411189088578,51.54166463217848],"type":"Point"}
}