{
  "type": "Feature",
  "properties": {
    "date:inception_lower": "1990-02-01",
    "date:inception_upper": "1990-02-01",
    "iso:country": "GB",
    "wof:name": "N7 9AU",
    "wof:placetype": "postalcode"
  },
  "geometry": {"coordinates":[-0.124112,51.541665],"type":"Point"}
}
