{
  "type": "Feature",
  "properties": {
    "iso:country":"GB",
    "wof:name":"RH15 8LN",
    "wof:placetype":"postalcode"
},
  "geometry": {"coordinates":[-0.13942712460654,50.95693113769207],"type":"Point"}
}