{
  "type": "Feature",
  "properties": {
    "iso:country":"GB",
    "wof:name":"SO31 8DU",
    "wof:placetype":"postalcode"
},
  "geometry": {"coordinates":[-1.32308636878774,50.88659819551285],"type":"Point"}
}