{
  "type": "Feature",
  "properties": {
    "iso:country": "GB",
    "wof:name": "SO31 8DU",
    "wof:placetype": "postalcode"
  },
  "geometry": {"coordinates":[-1.32256,50.886586],"type":"Point"}
}
