{
  "type": "Feature",
  "properties": {
    "iso:country": "GB",
    "wof:name": "GU7 3RF",
    "wof:placetype": "postalcode"
  },
  "geometry": {"coordinates":[-0.612306,51.201929],"type":"Point"}
}
