{
  "type": "Feature",
  "properties": {
    "iso:country":"GB",
    "wof:name":"LL20 8BB",
    "wof:placetype":"postalcode"
},
  "geometry": {"coordinates":[-3.16045799868197,52.96408382217744],"type":"Point"}
}