{
  "type": "Feature",
  "properties": {
    "iso:country": "GB",
    "wof:name": "LL20 8BB",
    "wof:placetype": "postalcode"
  },
  "geometry": {"coordinates":[-3.160458,52.964084],"type":"Point"}
}
