{
  "type": "Feature",
  "properties": {
    "iso:country": "GB",
    "wof:name": "CF38 1UQ",
    "wof:placetype": "postalcode"
  },
  "geometry": {"coordinates":[-3.327605,51.566858],"type":"Point"}
}
