{
  "type": "Feature",
  "properties": {
    "date:inception_lower": "1994-12-01",
    "date:inception_upper": "1994-12-01",
    "iso:country": "GB",
    "wof:name": "CF38 1UQ",
    "wof:placetype": "postalcode"
  },
  "geometry": {"coordinates":[-3.327605,51.566858],"type":"Point"}
}
