{
  "type": "Feature",
  "properties": {
    "iso:country":"GB",
    "wof:name":"CT14 7AS",
    "wof:placetype":"postalcode"
},
  "geometry": {"coordinates":[1.40224099206309,51.22147779017054],"type":"Point"}
}