{
  "type": "Feature",
  "properties": {
    "iso:country": "GB",
    "wof:name": "NR3 2QR",
    "wof:placetype": "postalcode"
  },
  "geometry": {"coordinates":[1.276526,52.648958],"type":"Point"}
}
