{
  "type": "Feature",
  "properties": {
    "iso:country":"GB",
    "wof:name":"S43 4ER",
    "wof:placetype":"postalcode"
},
  "geometry": {"coordinates":[-1.28530961406022,53.28960483042341],"type":"Point"}
}