{
  "type": "Feature",
  "properties": {
    "iso:country": "GB",
    "wof:name": "S43 4ER",
    "wof:placetype": "postalcode"
  },
  "geometry": {"coordinates":[-1.28531,53.289605],"type":"Point"}
}
