{
  "type": "Feature",
  "properties": {
    "iso:country":"GB",
    "wof:name":"LS9 0AF",
    "wof:placetype":"postalcode"
},
  "geometry": {"coordinates":[-1.51765688878001,53.79089587546058],"type":"Point"}
}