{
  "type": "Feature",
  "properties": {
    "iso:country":"GB",
    "wof:name":"DH8 6TX",
    "wof:placetype":"postalcode"
},
  "geometry": {"coordinates":[-1.82887480604705,54.863813829949],"type":"Point"}
}