{
  "type": "Feature",
  "properties": {
    "iso:country":"GB",
    "wof:name":"RM7 9DR",
    "wof:placetype":"postalcode"
},
  "geometry": {"coordinates":[0.16821996372212,51.57193137875942],"type":"Point"}
}