{
  "type": "Feature",
  "properties": {
    "iso:country": "GB",
    "wof:name": "RM7 9DR",
    "wof:placetype": "postalcode"
  },
  "geometry": {"coordinates":[0.16816,51.571917],"type":"Point"}
}
