{
  "type": "Feature",
  "properties": {
    "date:inception_lower": "1998-12-01",
    "date:inception_upper": "1998-12-01",
    "iso:country": "GB",
    "wof:name": "WF2 0FD",
    "wof:placetype": "postalcode"
  },
  "geometry": {"coordinates":[-1.528092,53.690091],"type":"Point"}
}
