{
  "type": "Feature",
  "properties": {
    "iso:country":"GB",
    "wof:name":"LS25 7HB",
    "wof:placetype":"postalcode"
},
  "geometry": {"coordinates":[-1.36879881850334,53.76920876881071],"type":"Point"}
}