{
  "type": "Feature",
  "properties": {
    "date:inception_lower": "2007-04-01",
    "date:inception_upper": "2007-04-01",
    "iso:country": "GB",
    "wof:name": "NE63 9JS",
    "wof:placetype": "postalcode"
  },
  "geometry": {"coordinates":[-1.546577,55.182351],"type":"Point"}
}
