{
  "type": "Feature",
  "properties": {
    "iso:country":"GB",
    "wof:name":"SP2 8LF",
    "wof:placetype":"postalcode"
},
  "geometry": {"coordinates":[-1.80534183121442,51.06104924796013],"type":"Point"}
}