{
  "type": "Feature",
  "properties": {
    "date:inception_lower": "1996-06-01",
    "date:inception_upper": "1996-06-01",
    "iso:country": "GB",
    "wof:name": "TS26 0SB",
    "wof:placetype": "postalcode"
  },
  "geometry": {"coordinates":[-1.235438,54.700064],"type":"Point"}
}
