{
  "type": "Feature",
  "properties": {
    "iso:country":"GB",
    "wof:name":"TS26 0SB",
    "wof:placetype":"postalcode"
},
  "geometry": {"coordinates":[-1.23543771274345,54.70006439192663],"type":"Point"}
}