{
  "type": "Feature",
  "properties": {
    "iso:country": "GB",
    "wof:name": "LL60 6BN",
    "wof:placetype": "postalcode"
  },
  "geometry": {"coordinates":[-4.273866,53.223134],"type":"Point"}
}
