{
  "type": "Feature",
  "properties": {
    "iso:country":"GB",
    "wof:name":"FK12 5DD",
    "wof:placetype":"postalcode"
},
  "geometry": {"coordinates":[-3.8125376287316,56.15152639156182],"type":"Point"}
}