{
  "type": "Feature",
  "properties": {
    "iso:country":"GB",
    "wof:name":"TN6 1EB",
    "wof:placetype":"postalcode"
},
  "geometry": {"coordinates":[0.16245073614094,51.05659569265808],"type":"Point"}
}