{
  "type": "Feature",
  "properties": {
    "iso:country":"GB",
    "wof:name":"CT6 5NB",
    "wof:placetype":"postalcode"
},
  "geometry": {"coordinates":[1.1214840293476,51.37167783022296],"type":"Point"}
}