{
  "type": "Feature",
  "properties": {
    "iso:country": "GB",
    "wof:name": "CT6 5NB",
    "wof:placetype": "postalcode"
  },
  "geometry": {"coordinates":[1.121484,51.371678],"type":"Point"}
}
