{
  "type": "Feature",
  "properties": {
    "iso:country":"GB",
    "wof:name":"M20 3JJ",
    "wof:placetype":"postalcode"
},
  "geometry": {"coordinates":[-2.23181588709506,53.43076166836104],"type":"Point"}
}