{
  "type": "Feature",
  "properties": {
    "iso:country":"GB",
    "wof:name":"BH23 1NG",
    "wof:placetype":"postalcode"
},
  "geometry": {"coordinates":[-1.79094017855424,50.73434822324867],"type":"Point"}
}