{
  "type": "Feature",
  "properties": {
    "iso:country":"GB",
    "wof:name":"LA11 6EJ",
    "wof:placetype":"postalcode"
},
  "geometry": {"coordinates":[-2.90243514006607,54.19757429103218],"type":"Point"}
}