{
  "type": "Feature",
  "properties": {
    "iso:country":"GB",
    "wof:name":"W12 0TY",
    "wof:placetype":"postalcode"
},
  "geometry": {"coordinates":[-0.23187058582004,51.51957131375084],"type":"Point"}
}