{
  "type": "Feature",
  "properties": {
    "iso:country": "GB",
    "wof:name": "SO53 2FL",
    "wof:placetype": "postalcode"
  },
  "geometry": {"coordinates":[-1.385001,50.989231],"type":"Point"}
}
