{
  "type": "Feature",
  "properties": {
    "date:inception_lower": "1980-01-01",
    "date:inception_upper": "1980-01-01",
    "iso:country": "GB",
    "wof:name": "IP25 6BX",
    "wof:placetype": "postalcode"
  },
  "geometry": {"coordinates":[0.829064,52.56743],"type":"Point"}
}
