{
  "type": "Feature",
  "properties": {
    "date:inception_lower":"1981-06-01",
    "date:inception_upper":"1981-06-30",
    "iso:country":"GB",
    "wof:name":"TS11 8HW",
    "wof:placetype":"postalcode"
},
  "geometry": {"coordinates":[-1.045126,54.57605],"type":"Point"}
}