{
  "type": "Feature",
  "properties": {
    "iso:country": "GB",
    "wof:name": "TS11 8HW",
    "wof:placetype": "postalcode"
  },
  "geometry": {"coordinates":[-1.045126,54.57605],"type":"Point"}
}
