{
  "type": "Feature",
  "properties": {
    "iso:country":"GB",
    "wof:name":"TS11 8HW",
    "wof:placetype":"postalcode"
},
  "geometry": {"coordinates":[-1.04512632520485,54.57604992365354],"type":"Point"}
}