{
  "type": "Feature",
  "properties": {
    "iso:country":"GB",
    "wof:name":"ST5 2TP",
    "wof:placetype":"postalcode"
},
  "geometry": {"coordinates":[-2.23575945538521,53.00852958019283],"type":"Point"}
}