{
  "type": "Feature",
  "properties": {
    "iso:country": "GB",
    "wof:name": "ST5 2TP",
    "wof:placetype": "postalcode"
  },
  "geometry": {"coordinates":[-2.235759,53.00853],"type":"Point"}
}
