{
  "type": "Feature",
  "properties": {
    "date:inception_lower":"1980-01-01",
    "date:inception_upper":"1980-01-31",
    "iso:country":"GB",
    "wof:name":"SR5 1JN",
    "wof:placetype":"postalcode"
},
  "geometry": {"coordinates":[-1.387187,54.922698],"type":"Point"}
}