{
  "type": "Feature",
  "properties": {
    "iso:country":"GB",
    "wof:name":"BD17 5RN",
    "wof:placetype":"postalcode"
},
  "geometry": {"coordinates":[-1.79411323576568,53.84141884167129],"type":"Point"}
}