{
  "type": "Feature",
  "properties": {
    "iso:country":"GB",
    "wof:name":"SO20 8BY",
    "wof:placetype":"postalcode"
},
  "geometry": {"coordinates":[-1.57253823683529,51.10400628930954],"type":"Point"}
}