{
  "type": "Feature",
  "properties": {
    "iso:country":"GB",
    "wof:name":"HA6 3ER",
    "wof:placetype":"postalcode"
},
  "geometry": {"coordinates":[-0.40634736625084,51.61617422383252],"type":"Point"}
}