{
  "type": "Feature",
  "properties": {
    "iso:country": "GB",
    "wof:name": "HA6 3ER",
    "wof:placetype": "postalcode"
  },
  "geometry": {"coordinates":[-0.406256,51.61651],"type":"Point"}
}
