{
  "type": "Feature",
  "properties": {
    "iso:country":"GB",
    "wof:name":"SY6 6RG",
    "wof:placetype":"postalcode"
},
  "geometry": {"coordinates":[-2.82562114620694,52.5100736015459],"type":"Point"}
}