{
  "type": "Feature",
  "properties": {
    "date:inception_lower": "1980-01-01",
    "date:inception_upper": "1980-01-01",
    "iso:country": "GB",
    "wof:name": "SY6 6RG",
    "wof:placetype": "postalcode"
  },
  "geometry": {"coordinates":[-2.825621,52.510074],"type":"Point"}
}
