{
  "type": "Feature",
  "properties": {
    "iso:country":"GB",
    "wof:name":"CF37 2HW",
    "wof:placetype":"postalcode"
},
  "geometry": {"coordinates":[-3.34672469326234,51.60499906369381],"type":"Point"}
}