{
  "type": "Feature",
  "properties": {
    "iso:country": "GB",
    "wof:name": "CF37 2HW",
    "wof:placetype": "postalcode"
  },
  "geometry": {"coordinates":[-3.346725,51.604999],"type":"Point"}
}
