{
  "type": "Feature",
  "properties": {
    "date:inception_lower":"1980-01-01",
    "date:inception_upper":"1980-01-31",
    "iso:country":"GB",
    "wof:name":"CF37 2HW",
    "wof:placetype":"postalcode"
},
  "geometry": {"coordinates":[-3.346725,51.604999],"type":"Point"}
}