{
  "type": "Feature",
  "properties": {
    "iso:country": "GB",
    "wof:name": "DG5 4LQ",
    "wof:placetype": "postalcode"
  },
  "geometry": {"coordinates":[-3.834146,54.93736],"type":"Point"}
}
