{
  "type": "Feature",
  "properties": {
    "iso:country":"GB",
    "wof:name":"NE10 9AR",
    "wof:placetype":"postalcode"
},
  "geometry": {"coordinates":[-1.55527610453558,54.9407901964459],"type":"Point"}
}