{
  "type": "Feature",
  "properties": {
    "date:inception_lower": "1993-01-01",
    "date:inception_upper": "1993-01-01",
    "iso:country": "GB",
    "wof:name": "CF62 9HA",
    "wof:placetype": "postalcode"
  },
  "geometry": {"coordinates":[-3.261861,51.422048],"type":"Point"}
}
