{
  "type": "Feature",
  "properties": {
    "iso:country": "GB",
    "wof:name": "SW1H 0AA",
    "wof:placetype": "postalcode"
  },
  "geometry": {"coordinates":[-0.13534,51.499462],"type":"Point"}
}
