{
  "type": "Feature",
  "properties": {
    "iso:country":"GB",
    "wof:name":"SW1H 0AA",
    "wof:placetype":"postalcode"
},
  "geometry": {"coordinates":[-0.1353399609522,51.49946197000764],"type":"Point"}
}