{
  "type": "Feature",
  "properties": {
    "iso:country":"GB",
    "wof:name":"ME10 1NF",
    "wof:placetype":"postalcode"
},
  "geometry": {"coordinates":[0.72643281867071,51.34206859861398],"type":"Point"}
}