{
  "type": "Feature",
  "properties": {
    "iso:country": "GB",
    "wof:name": "NP18 1LU",
    "wof:placetype": "postalcode"
  },
  "geometry": {"coordinates":[-2.921093,51.629342],"type":"Point"}
}
