{
  "type": "Feature",
  "properties": {
    "iso:country":"GB",
    "wof:name":"CM4 9ND",
    "wof:placetype":"postalcode"
},
  "geometry": {"coordinates":[0.45060310126642,51.66498260800075],"type":"Point"}
}