{
  "type": "Feature",
  "properties": {
    "iso:country":"GB",
    "wof:name":"BS48 2AJ",
    "wof:placetype":"postalcode"
},
  "geometry": {"coordinates":[-2.77048781878015,51.43185711186624],"type":"Point"}
}