{
  "type": "Feature",
  "properties": {
    "date:inception_lower":"1984-10-01",
    "date:inception_upper":"1984-10-31",
    "iso:country":"GB",
    "wof:name":"PL19 0JQ",
    "wof:placetype":"postalcode"
},
  "geometry": {"coordinates":[-4.145738,50.551757],"type":"Point"}
}