{
  "type": "Feature",
  "properties": {
    "iso:country":"GB",
    "wof:name":"KT9 1BY",
    "wof:placetype":"postalcode"
},
  "geometry": {"coordinates":[-0.29768738223085,51.36739482463956],"type":"Point"}
}