{
  "type": "Feature",
  "properties": {
    "iso:country":"GB",
    "wof:name":"DN22 7TE",
    "wof:placetype":"postalcode"
},
  "geometry": {"coordinates":[-0.94913736626619,53.31301498154011],"type":"Point"}
}