{
  "type": "Feature",
  "properties": {
    "iso:country":"GB",
    "wof:name":"W13 9HX",
    "wof:placetype":"postalcode"
},
  "geometry": {"coordinates":[-0.32092959621454,51.50634834443862],"type":"Point"}
}