{
  "type": "Feature",
  "properties": {
    "iso:country": "GB",
    "wof:name": "SN8 4NH",
    "wof:placetype": "postalcode"
  },
  "geometry": {"coordinates":[-1.717968,51.366192],"type":"Point"}
}
