{
  "type": "Feature",
  "properties": {
    "date:inception_lower":"1980-01-01",
    "date:inception_upper":"1980-01-31",
    "iso:country":"GB",
    "wof:name":"SN8 4NH",
    "wof:placetype":"postalcode"
},
  "geometry": {"coordinates":[-1.717968,51.366192],"type":"Point"}
}