{
  "type": "Feature",
  "properties": {
    "iso:country":"GB",
    "wof:name":"LE14 4BN",
    "wof:placetype":"postalcode"
},
  "geometry": {"coordinates":[-0.89565265345387,52.87158856420539],"type":"Point"}
}