{
  "type": "Feature",
  "properties": {
    "date:inception_lower":"1980-01-01",
    "date:inception_upper":"1980-01-31",
    "iso:country":"GB",
    "wof:name":"PA29 6YB",
    "wof:placetype":"postalcode"
},
  "geometry": {"coordinates":[-5.595621,55.797161],"type":"Point"}
}