{
  "type": "Feature",
  "properties": {
    "iso:country":"GB",
    "wof:name":"IP21 5UD",
    "wof:placetype":"postalcode"
},
  "geometry": {"coordinates":[1.29822909608933,52.3865202905077],"type":"Point"}
}