{
  "type": "Feature",
  "properties": {
    "iso:country": "GB",
    "wof:name": "IP21 5UD",
    "wof:placetype": "postalcode"
  },
  "geometry": {"coordinates":[1.298258,52.386541],"type":"Point"}
}
