{
  "type": "Feature",
  "properties": {
    "iso:country":"GB",
    "wof:name":"NW4 1LD",
    "wof:placetype":"postalcode"
},
  "geometry": {"coordinates":[-0.21113604443224,51.59954075018634],"type":"Point"}
}