{
  "type": "Feature",
  "properties": {
    "iso:country":"GB",
    "wof:name":"SP9 7JA",
    "wof:placetype":"postalcode"
},
  "geometry": {"coordinates":[-1.67336136141533,51.24368916172426],"type":"Point"}
}