{
  "type": "Feature",
  "properties": {
    "iso:country": "GB",
    "wof:name": "DY12 1AB",
    "wof:placetype": "postalcode"
  },
  "geometry": {"coordinates":[-2.314541,52.377326],"type":"Point"}
}
