{
  "type": "Feature",
  "properties": {
    "iso:country":"GB",
    "wof:name":"HD9 1PR",
    "wof:placetype":"postalcode"
},
  "geometry": {"coordinates":[-1.76242465537656,53.56170387479241],"type":"Point"}
}