{
  "type": "Feature",
  "properties": {
    "iso:country": "GB",
    "wof:name": "HD9 1PR",
    "wof:placetype": "postalcode"
  },
  "geometry": {"coordinates":[-1.762425,53.561704],"type":"Point"}
}
