{
  "type": "Feature",
  "properties": {
    "date:inception_lower":"2010-11-01",
    "date:inception_upper":"2010-11-30",
    "iso:country":"GB",
    "wof:name":"S73 0NH",
    "wof:placetype":"postalcode"
},
  "geometry": {"coordinates":[-1.411575,53.515353],"type":"Point"}
}