{
  "type": "Feature",
  "properties": {
    "iso:country": "GB",
    "wof:name": "S73 0NH",
    "wof:placetype": "postalcode"
  },
  "geometry": {"coordinates":[-1.411575,53.515353],"type":"Point"}
}
