{
  "type": "Feature",
  "properties": {
    "iso:country":"GB",
    "wof:name":"S73 0NH",
    "wof:placetype":"postalcode"
},
  "geometry": {"coordinates":[-1.41157514771452,53.51535311815996],"type":"Point"}
}