{
  "type": "Feature",
  "properties": {
    "iso:country": "GB",
    "wof:name": "EX1 2RD",
    "wof:placetype": "postalcode"
  },
  "geometry": {"coordinates":[-3.50672,50.723267],"type":"Point"}
}
