{
  "type": "Feature",
  "properties": {
    "iso:country":"GB",
    "wof:name":"SS1 2YA",
    "wof:placetype":"postalcode"
},
  "geometry": {"coordinates":[0.74014788619414,51.53076310503197],"type":"Point"}
}