{
  "type": "Feature",
  "properties": {
    "iso:country": "GB",
    "wof:name": "HU8 9PZ",
    "wof:placetype": "postalcode"
  },
  "geometry": {"coordinates":[-0.266723,53.781096],"type":"Point"}
}
