{
  "type": "Feature",
  "properties": {
    "iso:country":"GB",
    "wof:name":"HU8 9PZ",
    "wof:placetype":"postalcode"
},
  "geometry": {"coordinates":[-0.26714245276478,53.78102750268618],"type":"Point"}
}