{
  "type": "Feature",
  "properties": {
    "iso:country":"GB",
    "wof:name":"SE5 0YP",
    "wof:placetype":"postalcode"
},
  "geometry": {"coordinates":[-0.10108665942219,51.47915562779935],"type":"Point"}
}