{
  "type": "Feature",
  "properties": {
    "date:inception_lower":"1980-01-01",
    "date:inception_upper":"1980-01-31",
    "iso:country":"GB",
    "wof:name":"NN9 5PZ",
    "wof:placetype":"postalcode"
},
  "geometry": {"coordinates":[-0.609763,52.328385],"type":"Point"}
}