{
  "type": "Feature",
  "properties": {
    "iso:country":"GB",
    "wof:name":"NN9 5PZ",
    "wof:placetype":"postalcode"
},
  "geometry": {"coordinates":[-0.60976313747803,52.32838498659117],"type":"Point"}
}