{
  "type": "Feature",
  "properties": {
    "iso:country": "GB",
    "wof:name": "BB18 6DW",
    "wof:placetype": "postalcode"
  },
  "geometry": {"coordinates":[-2.186492,53.918781],"type":"Point"}
}
