{
  "type": "Feature",
  "properties": {
    "date:inception_lower": "1997-12-01",
    "date:inception_upper": "1997-12-01",
    "iso:country": "GB",
    "wof:name": "BB18 6DW",
    "wof:placetype": "postalcode"
  },
  "geometry": {"coordinates":[-2.186492,53.918781],"type":"Point"}
}
