{
  "type": "Feature",
  "properties": {
    "iso:country":"GB",
    "wof:name":"TS4 3LA",
    "wof:placetype":"postalcode"
},
  "geometry": {"coordinates":[-1.23470091179834,54.55189148280851],"type":"Point"}
}