{
  "type": "Feature",
  "properties": {
    "iso:country":"GB",
    "wof:name":"WV11 1LG",
    "wof:placetype":"postalcode"
},
  "geometry": {"coordinates":[-2.08718540443109,52.60796355840343],"type":"Point"}
}