{
  "type": "Feature",
  "properties": {
    "iso:country": "GB",
    "wof:name": "YO30 2AP",
    "wof:placetype": "postalcode"
  },
  "geometry": {"coordinates":[-1.242523,54.03944],"type":"Point"}
}
