{
  "type": "Feature",
  "properties": {
    "iso:country":"GB",
    "wof:name":"YO30 2AP",
    "wof:placetype":"postalcode"
},
  "geometry": {"coordinates":[-1.24252324248926,54.03944000319392],"type":"Point"}
}