{
  "type": "Feature",
  "properties": {
    "date:inception_lower":"1980-01-01",
    "date:inception_upper":"1980-01-31",
    "iso:country":"GB",
    "wof:name":"TS9 6HQ",
    "wof:placetype":"postalcode"
},
  "geometry": {"coordinates":[-1.114901,54.490114],"type":"Point"}
}