{
  "type": "Feature",
  "properties": {
    "iso:country":"GB",
    "wof:name":"TS9 6HQ",
    "wof:placetype":"postalcode"
},
  "geometry": {"coordinates":[-1.1149012086103,54.49011434256158],"type":"Point"}
}