{
  "type": "Feature",
  "properties": {
    "iso:country": "GB",
    "wof:name": "ST13 8SW",
    "wof:placetype": "postalcode"
  },
  "geometry": {"coordinates":[-2.002516,53.140948],"type":"Point"}
}
