{
  "type": "Feature",
  "properties": {
    "iso:country": "GB",
    "wof:name": "BB12 0JX",
    "wof:placetype": "postalcode"
  },
  "geometry": {"coordinates":[-2.260353,53.796633],"type":"Point"}
}
