{
  "type": "Feature",
  "properties": {
    "iso:country": "GB",
    "wof:name": "LL67 0LG",
    "wof:placetype": "postalcode"
  },
  "geometry": {"coordinates":[-4.455715,53.409604],"type":"Point"}
}
