{
  "type": "Feature",
  "properties": {
    "iso:country":"GB",
    "wof:name":"RG19 3QZ",
    "wof:placetype":"postalcode"
},
  "geometry": {"coordinates":[-1.26468485157784,51.40236866509085],"type":"Point"}
}