{
  "type": "Feature",
  "properties": {
    "iso:country": "GB",
    "wof:name": "LA12 0DE",
    "wof:placetype": "postalcode"
  },
  "geometry": {"coordinates":[-3.093738,54.192421],"type":"Point"}
}
