{
  "type": "Feature",
  "properties": {
    "iso:country": "GB",
    "wof:name": "CM22 7UG",
    "wof:placetype": "postalcode"
  },
  "geometry": {"coordinates":[0.209506,51.845132],"type":"Point"}
}
