{
  "type": "Feature",
  "properties": {
    "iso:country":"GB",
    "wof:name":"TD6 9JW",
    "wof:placetype":"postalcode"
},
  "geometry": {"coordinates":[-2.73915996083965,55.49986141560689],"type":"Point"}
}