{
  "type": "Feature",
  "properties": {
    "iso:country":"GB",
    "wof:name":"CF43 4LU",
    "wof:placetype":"postalcode"
},
  "geometry": {"coordinates":[-3.45041065739367,51.6631010615075],"type":"Point"}
}