{
  "type": "Feature",
  "properties": {
    "date:inception_lower":"1980-01-01",
    "date:inception_upper":"1980-01-31",
    "iso:country":"GB",
    "wof:name":"IP13 0JQ",
    "wof:placetype":"postalcode"
},
  "geometry": {"coordinates":[1.32994,52.135972],"type":"Point"}
}