{
  "type": "Feature",
  "properties": {
    "iso:country": "GB",
    "wof:name": "IP13 0JQ",
    "wof:placetype": "postalcode"
  },
  "geometry": {"coordinates":[1.32994,52.135972],"type":"Point"}
}
