{
  "type": "Feature",
  "properties": {
    "iso:country": "GB",
    "wof:name": "SP10 2BF",
    "wof:placetype": "postalcode"
  },
  "geometry": {"coordinates":[-1.490133,51.196834],"type":"Point"}
}
