{
  "type": "Feature",
  "properties": {
    "iso:country":"GB",
    "wof:name":"TS21 1JU",
    "wof:placetype":"postalcode"
},
  "geometry": {"coordinates":[-1.42547310097351,54.60455928901774],"type":"Point"}
}