{
  "type": "Feature",
  "properties": {
    "date:inception_lower": "1980-01-01",
    "date:inception_upper": "1980-01-01",
    "iso:country": "GB",
    "wof:name": "TS21 1JU",
    "wof:placetype": "postalcode"
  },
  "geometry": {"coordinates":[-1.425473,54.604559],"type":"Point"}
}
