{
  "type": "Feature",
  "properties": {
    "iso:country":"GB",
    "wof:name":"B63 3UH",
    "wof:placetype":"postalcode"
},
  "geometry": {"coordinates":[-2.06302645373346,52.45403620281765],"type":"Point"}
}