{
  "type": "Feature",
  "properties": {
    "iso:country":"GB",
    "wof:name":"RH2 7RS",
    "wof:placetype":"postalcode"
},
  "geometry": {"coordinates":[-0.20382740429019,51.23638117262922],"type":"Point"}
}