{
  "type": "Feature",
  "properties": {
    "iso:country": "GB",
    "wof:name": "RH2 7RS",
    "wof:placetype": "postalcode"
  },
  "geometry": {"coordinates":[-0.203827,51.236381],"type":"Point"}
}
