{
  "type": "Feature",
  "properties": {
    "iso:country": "GB",
    "wof:name": "LS28 5BR",
    "wof:placetype": "postalcode"
  },
  "geometry": {"coordinates":[-1.674061,53.808976],"type":"Point"}
}
