{
  "type": "Feature",
  "properties": {
    "iso:country":"GB",
    "wof:name":"LL55 4SR",
    "wof:placetype":"postalcode"
},
  "geometry": {"coordinates":[-4.13209834344918,53.11294138735983],"type":"Point"}
}