{
  "type": "Feature",
  "properties": {
    "iso:country": "GB",
    "wof:name": "OL3 6LW",
    "wof:placetype": "postalcode"
  },
  "geometry": {"coordinates":[-1.988188,53.554128],"type":"Point"}
}
