{
  "type": "Feature",
  "properties": {
    "iso:country":"GB",
    "wof:name":"IP31 3DN",
    "wof:placetype":"postalcode"
},
  "geometry": {"coordinates":[0.91268616245471,52.28198597559958],"type":"Point"}
}