{
  "type": "Feature",
  "properties": {
    "iso:country":"GB",
    "wof:name":"LS29 6LL",
    "wof:placetype":"postalcode"
},
  "geometry": {"coordinates":[-1.74497011307823,53.89054219276403],"type":"Point"}
}