{
  "type": "Feature",
  "properties": {
    "iso:country":"GB",
    "wof:name":"RM14 2UE",
    "wof:placetype":"postalcode"
},
  "geometry": {"coordinates":[0.25270796339877,51.5580642142163],"type":"Point"}
}