{
  "type": "Feature",
  "properties": {
    "iso:country": "GB",
    "wof:name": "UB5 5BJ",
    "wof:placetype": "postalcode"
  },
  "geometry": {"coordinates":[-0.372805,51.545144],"type":"Point"}
}
