{
  "type": "Feature",
  "properties": {
    "iso:country":"GB",
    "wof:name":"UB5 5BJ",
    "wof:placetype":"postalcode"
},
  "geometry": {"coordinates":[-0.37280475705855,51.54514362312628],"type":"Point"}
}