{
  "type": "Feature",
  "properties": {
    "iso:country": "GB",
    "wof:name": "E14 7SL",
    "wof:placetype": "postalcode"
  },
  "geometry": {"coordinates":[-0.036956,51.517406],"type":"Point"}
}
