{
  "type": "Feature",
  "properties": {
    "iso:country":"GB",
    "wof:name":"E14 7SL",
    "wof:placetype":"postalcode"
},
  "geometry": {"coordinates":[-0.03695604082428,51.51740635155585],"type":"Point"}
}