{
  "type": "Feature",
  "properties": {
    "iso:country":"GB",
    "wof:name":"BB12 8JD",
    "wof:placetype":"postalcode"
},
  "geometry": {"coordinates":[-2.32103922321844,53.80147400881658],"type":"Point"}
}