{
  "type": "Feature",
  "properties": {
    "iso:country": "GB",
    "wof:name": "NW7 1LN",
    "wof:placetype": "postalcode"
  },
  "geometry": {"coordinates":[-0.207347,51.604465],"type":"Point"}
}
