{
  "type": "Feature",
  "properties": {
    "iso:country":"GB",
    "wof:name":"LS28 8JS",
    "wof:placetype":"postalcode"
},
  "geometry": {"coordinates":[-1.69125077659274,53.80081558000738],"type":"Point"}
}