{
  "type": "Feature",
  "properties": {
    "date:inception_lower": "1980-01-01",
    "date:inception_upper": "1980-01-01",
    "iso:country": "GB",
    "wof:name": "FY8 1EH",
    "wof:placetype": "postalcode"
  },
  "geometry": {"coordinates":[-3.017276,53.743882],"type":"Point"}
}
