{
  "type": "Feature",
  "properties": {
    "iso:country":"GB",
    "wof:name":"FY8 1EH",
    "wof:placetype":"postalcode"
},
  "geometry": {"coordinates":[-3.01727596085736,53.74388195474377],"type":"Point"}
}