{
  "type": "Feature",
  "properties": {
    "iso:country":"GB",
    "wof:name":"CB8 0DW",
    "wof:placetype":"postalcode"
},
  "geometry": {"coordinates":[0.38697980722935,52.25055353564564],"type":"Point"}
}