{
  "type": "Feature",
  "properties": {
    "iso:country":"GB",
    "wof:name":"B71 1EW",
    "wof:placetype":"postalcode"
},
  "geometry": {"coordinates":[-1.99786326704685,52.53002709796776],"type":"Point"}
}