{
  "type": "Feature",
  "properties": {
    "date:inception_lower": "1994-12-01",
    "date:inception_upper": "1994-12-01",
    "iso:country": "GB",
    "wof:name": "UB8 2XN",
    "wof:placetype": "postalcode"
  },
  "geometry": {"coordinates":[-0.487277,51.544699],"type":"Point"}
}
