{
  "type": "Feature",
  "properties": {
    "iso:country":"GB",
    "wof:name":"UB8 2XN",
    "wof:placetype":"postalcode"
},
  "geometry": {"coordinates":[-0.48731284618721,51.54469748044508],"type":"Point"}
}