{
  "type": "Feature",
  "properties": {
    "iso:country": "GB",
    "wof:name": "CM1 6NR",
    "wof:placetype": "postalcode"
  },
  "geometry": {"coordinates":[0.486371,51.746616],"type":"Point"}
}
