{
  "type": "Feature",
  "properties": {
    "iso:country":"GB",
    "wof:name":"CM1 6NR",
    "wof:placetype":"postalcode"
},
  "geometry": {"coordinates":[0.48637102907967,51.74661638148326],"type":"Point"}
}