{
  "type": "Feature",
  "properties": {
    "date:inception_lower":"1980-01-01",
    "date:inception_upper":"1980-01-31",
    "iso:country":"GB",
    "wof:name":"NR9 5AX",
    "wof:placetype":"postalcode"
},
  "geometry": {"coordinates":[1.097496,52.664758],"type":"Point"}
}