{
  "type": "Feature",
  "properties": {
    "iso:country":"GB",
    "wof:name":"NR9 5AX",
    "wof:placetype":"postalcode"
},
  "geometry": {"coordinates":[1.09749584558294,52.66475813395688],"type":"Point"}
}