{
  "type": "Feature",
  "properties": {
    "date:inception_lower": "2017-03-01",
    "date:inception_upper": "2017-03-01",
    "iso:country": "GB",
    "wof:name": "BS16 1LE",
    "wof:placetype": "postalcode"
  },
  "geometry": {"coordinates":[-2.528419,51.496597],"type":"Point"}
}
