{
  "type": "Feature",
  "properties": {
    "iso:country": "GB",
    "wof:name": "WD23 1HN",
    "wof:placetype": "postalcode"
  },
  "geometry": {"coordinates":[-0.348016,51.635825],"type":"Point"}
}
