{
  "type": "Feature",
  "properties": {
    "iso:country": "GB",
    "wof:name": "NN2 8EZ",
    "wof:placetype": "postalcode"
  },
  "geometry": {"coordinates":[-0.906454,52.280758],"type":"Point"}
}
