{
  "type": "Feature",
  "properties": {
    "iso:country": "GB",
    "wof:name": "PO15 6QT",
    "wof:placetype": "postalcode"
  },
  "geometry": {"coordinates":[-1.218533,50.869965],"type":"Point"}
}
