{
  "type": "Feature",
  "properties": {
    "iso:country":"GB",
    "wof:name":"PO15 6QT",
    "wof:placetype":"postalcode"
},
  "geometry": {"coordinates":[-1.22003289042266,50.87035321450583],"type":"Point"}
}