{
  "type": "Feature",
  "properties": {
    "iso:country":"GB",
    "wof:name":"CF23 9NP",
    "wof:placetype":"postalcode"
},
  "geometry": {"coordinates":[-3.14741487842029,51.5170463283134],"type":"Point"}
}