{
  "type": "Feature",
  "properties": {
    "iso:country": "GB",
    "wof:name": "PA5 9BT",
    "wof:placetype": "postalcode"
  },
  "geometry": {"coordinates":[-4.487381,55.829244],"type":"Point"}
}
