{
  "type": "Feature",
  "properties": {
    "date:inception_lower":"2001-06-01",
    "date:inception_upper":"2001-06-30",
    "iso:country":"GB",
    "wof:name":"NE32 3YJ",
    "wof:placetype":"postalcode"
},
  "geometry": {"coordinates":[-1.48694,54.981121],"type":"Point"}
}