{
  "type": "Feature",
  "properties": {
    "date:inception_lower":"2013-01-01",
    "date:inception_upper":"2013-01-31",
    "iso:country":"GB",
    "wof:name":"BS22 7AF",
    "wof:placetype":"postalcode"
},
  "geometry": {"coordinates":[-2.903746,51.36064],"type":"Point"}
}