{
  "type": "Feature",
  "properties": {
    "iso:country":"GB",
    "wof:name":"BS22 7AF",
    "wof:placetype":"postalcode"
},
  "geometry": {"coordinates":[-2.90377001246723,51.36063355033944],"type":"Point"}
}