{
  "type": "Feature",
  "properties": {
    "iso:country": "GB",
    "wof:name": "BS22 7AF",
    "wof:placetype": "postalcode"
  },
  "geometry": {"coordinates":[-2.903746,51.36064],"type":"Point"}
}
