{
  "type": "Feature",
  "properties": {
    "iso:country":"GB",
    "wof:name":"DG4 6QA",
    "wof:placetype":"postalcode"
},
  "geometry": {"coordinates":[-3.99385385054071,55.38350647323804],"type":"Point"}
}