{
  "type": "Feature",
  "properties": {
    "iso:country":"GB",
    "wof:name":"L13 7BF",
    "wof:placetype":"postalcode"
},
  "geometry": {"coordinates":[-2.92388576903943,53.42041875678008],"type":"Point"}
}