{
  "type": "Feature",
  "properties": {
    "iso:country":"GB",
    "wof:name":"GU26 6PE",
    "wof:placetype":"postalcode"
},
  "geometry": {"coordinates":[-0.75981913827578,51.12155675660415],"type":"Point"}
}