{
  "type": "Feature",
  "properties": {
    "date:inception_lower": "1980-01-01",
    "date:inception_upper": "1980-01-01",
    "iso:country": "GB",
    "wof:name": "GU26 6PE",
    "wof:placetype": "postalcode"
  },
  "geometry": {"coordinates":[-0.759819,51.121557],"type":"Point"}
}
