{
  "type": "Feature",
  "properties": {
    "iso:country": "GB",
    "wof:name": "GL17 9ET",
    "wof:placetype": "postalcode"
  },
  "geometry": {"coordinates":[-2.513982,51.856556],"type":"Point"}
}
