{
  "type": "Feature",
  "properties": {
    "date:inception_lower": "1980-01-01",
    "date:inception_upper": "1980-01-01",
    "iso:country": "GB",
    "wof:name": "GL17 9ET",
    "wof:placetype": "postalcode"
  },
  "geometry": {"coordinates":[-2.513982,51.856556],"type":"Point"}
}
