{
  "type": "Feature",
  "properties": {
    "iso:country":"GB",
    "wof:name":"CA14 4HJ",
    "wof:placetype":"postalcode"
},
  "geometry": {"coordinates":[-3.53805684683541,54.63395862270927],"type":"Point"}
}