{
  "type": "Feature",
  "properties": {
    "iso:country":"GB",
    "wof:name":"WF1 5LN",
    "wof:placetype":"postalcode"
},
  "geometry": {"coordinates":[-1.48521383359587,53.66713781019907],"type":"Point"}
}