{
  "type": "Feature",
  "properties": {
    "iso:country":"GB",
    "wof:name":"TQ12 1EE",
    "wof:placetype":"postalcode"
},
  "geometry": {"coordinates":[-3.60377376521073,50.5252214590525],"type":"Point"}
}