{
  "type": "Feature",
  "properties": {
    "iso:country": "GB",
    "wof:name": "TQ12 1EE",
    "wof:placetype": "postalcode"
  },
  "geometry": {"coordinates":[-3.603774,50.525221],"type":"Point"}
}
