{
  "type": "Feature",
  "properties": {
    "iso:country": "GB",
    "wof:name": "ME10 3PR",
    "wof:placetype": "postalcode"
  },
  "geometry": {"coordinates":[0.758331,51.345719],"type":"Point"}
}
