{
  "type": "Feature",
  "properties": {
    "iso:country":"GB",
    "wof:name":"ME10 3PR",
    "wof:placetype":"postalcode"
},
  "geometry": {"coordinates":[0.75833069335522,51.34571946065613],"type":"Point"}
}