{
  "type": "Feature",
  "properties": {
    "iso:country":"GB",
    "wof:name":"NG8 5BB",
    "wof:placetype":"postalcode"
},
  "geometry": {"coordinates":[-1.18356236133641,52.96821646580425],"type":"Point"}
}