{
  "type": "Feature",
  "properties": {
    "iso:country": "GB",
    "wof:name": "NE61 3PJ",
    "wof:placetype": "postalcode"
  },
  "geometry": {"coordinates":[-1.719017,55.166956],"type":"Point"}
}
