{
  "type": "Feature",
  "properties": {
    "iso:country":"GB",
    "wof:name":"DE23 8AU",
    "wof:placetype":"postalcode"
},
  "geometry": {"coordinates":[-1.48419777494126,52.89461444517711],"type":"Point"}
}