{
  "type": "Feature",
  "properties": {
    "iso:country":"GB",
    "wof:name":"B42 2HT",
    "wof:placetype":"postalcode"
},
  "geometry": {"coordinates":[-1.91600143525269,52.54094716502426],"type":"Point"}
}