{
  "type": "Feature",
  "properties": {
    "iso:country": "GB",
    "wof:name": "TN31 6TS",
    "wof:placetype": "postalcode"
  },
  "geometry": {"coordinates":[0.652434,50.989844],"type":"Point"}
}
