{
  "type": "Feature",
  "properties": {
    "iso:country": "GB",
    "wof:name": "CA8 7BH",
    "wof:placetype": "postalcode"
  },
  "geometry": {"coordinates":[-2.573063,54.991015],"type":"Point"}
}
