{
  "type": "Feature",
  "properties": {
    "iso:country":"GB",
    "wof:name":"CA8 7BH",
    "wof:placetype":"postalcode"
},
  "geometry": {"coordinates":[-2.57306281524436,54.99101476468284],"type":"Point"}
}