{
  "type": "Feature",
  "properties": {
    "iso:country":"GB",
    "wof:name":"RG20 0NR",
    "wof:placetype":"postalcode"
},
  "geometry": {"coordinates":[-1.39888468915603,51.36483761472542],"type":"Point"}
}