{
  "type": "Feature",
  "properties": {
    "iso:country":"GB",
    "wof:name":"TD9 8PF",
    "wof:placetype":"postalcode"
},
  "geometry": {"coordinates":[-2.76168733667804,55.43184500175941],"type":"Point"}
}