{
  "type": "Feature",
  "properties": {
    "iso:country":"GB",
    "wof:name":"PL4 0DW",
    "wof:placetype":"postalcode"
},
  "geometry": {"coordinates":[-4.13385552719189,50.36876249123559],"type":"Point"}
}