{
  "type": "Feature",
  "properties": {
    "iso:country": "GB",
    "wof:name": "ST16 1AG",
    "wof:placetype": "postalcode"
  },
  "geometry": {"coordinates":[-2.128901,52.803099],"type":"Point"}
}
