{
  "type": "Feature",
  "properties": {
    "iso:country": "GB",
    "wof:name": "GL6 7QB",
    "wof:placetype": "postalcode"
  },
  "geometry": {"coordinates":[-2.187896,51.762315],"type":"Point"}
}
