{
  "type": "Feature",
  "properties": {
    "iso:country":"GB",
    "wof:name":"GL6 7QB",
    "wof:placetype":"postalcode"
},
  "geometry": {"coordinates":[-2.18789590115183,51.7623151920569],"type":"Point"}
}