{
  "type": "Feature",
  "properties": {
    "iso:country":"GB",
    "wof:name":"WS13 6GE",
    "wof:placetype":"postalcode"
},
  "geometry": {"coordinates":[-1.81639286662692,52.68819502097381],"type":"Point"}
}