{
  "type": "Feature",
  "properties": {
    "date:inception_lower":"2012-05-01",
    "date:inception_upper":"2012-05-31",
    "iso:country":"GB",
    "wof:name":"WS13 6GE",
    "wof:placetype":"postalcode"
},
  "geometry": {"coordinates":[-1.816393,52.688195],"type":"Point"}
}