{
  "type": "Feature",
  "properties": {
    "iso:country":"GB",
    "wof:name":"ME15 6UA",
    "wof:placetype":"postalcode"
},
  "geometry": {"coordinates":[0.52238152910162,51.26284845794149],"type":"Point"}
}