{
  "type": "Feature",
  "properties": {
    "iso:country": "GB",
    "wof:name": "CA7 9LQ",
    "wof:placetype": "postalcode"
  },
  "geometry": {"coordinates":[-3.15185,54.817929],"type":"Point"}
}
