{
  "type": "Feature",
  "properties": {
    "date:inception_lower":"1999-06-01",
    "date:inception_upper":"1999-06-30",
    "iso:country":"GB",
    "wof:name":"CF11 8NE",
    "wof:placetype":"postalcode"
},
  "geometry": {"coordinates":[-3.194646,51.470869],"type":"Point"}
}