{
  "type": "Feature",
  "properties": {
    "iso:country":"GB",
    "wof:name":"NG22 9UH",
    "wof:placetype":"postalcode"
},
  "geometry": {"coordinates":[-1.00230595578525,53.19687295912928],"type":"Point"}
}