{
  "type": "Feature",
  "properties": {
    "iso:country":"GB",
    "wof:name":"M44 6QH",
    "wof:placetype":"postalcode"
},
  "geometry": {"coordinates":[-2.41795208343621,53.45727462024938],"type":"Point"}
}