{
  "type": "Feature",
  "properties": {
    "date:inception_lower": "1994-05-01",
    "date:inception_upper": "1994-05-01",
    "iso:country": "GB",
    "wof:name": "M44 6QH",
    "wof:placetype": "postalcode"
  },
  "geometry": {"coordinates":[-2.417952,53.457275],"type":"Point"}
}
