{
  "type": "Feature",
  "properties": {
    "iso:country":"GB",
    "wof:name":"BB9 8PF",
    "wof:placetype":"postalcode"
},
  "geometry": {"coordinates":[-2.22074862545485,53.84646066602973],"type":"Point"}
}