{
  "type": "Feature",
  "properties": {
    "iso:country": "GB",
    "wof:name": "BB9 8PF",
    "wof:placetype": "postalcode"
  },
  "geometry": {"coordinates":[-2.220796,53.846475],"type":"Point"}
}
