{
  "type": "Feature",
  "properties": {
    "date:inception_lower": "2019-11-01",
    "date:inception_upper": "2019-11-01",
    "iso:country": "GB",
    "wof:name": "B78 3EY",
    "wof:placetype": "postalcode"
  },
  "geometry": {"coordinates":[-1.718021,52.630566],"type":"Point"}
}
