{
  "type": "Feature",
  "properties": {
    "iso:country":"GB",
    "wof:name":"BD17 7NP",
    "wof:placetype":"postalcode"
},
  "geometry": {"coordinates":[-1.77568591452323,53.8429048055673],"type":"Point"}
}