{
  "type": "Feature",
  "properties": {
    "iso:country":"GB",
    "wof:name":"FK2 8LP",
    "wof:placetype":"postalcode"
},
  "geometry": {"coordinates":[-3.79634848066545,56.08196722493111],"type":"Point"}
}