{
  "type": "Feature",
  "properties": {
    "iso:country": "GB",
    "wof:name": "FK2 8LP",
    "wof:placetype": "postalcode"
  },
  "geometry": {"coordinates":[-3.796348,56.081967],"type":"Point"}
}
