{
  "type": "Feature",
  "properties": {
    "iso:country":"GB",
    "wof:name":"TW18 2ER",
    "wof:placetype":"postalcode"
},
  "geometry": {"coordinates":[-0.505611301608,51.42580368874093],"type":"Point"}
}