{
  "type": "Feature",
  "properties": {
    "iso:country":"GB",
    "wof:name":"W3 6RU",
    "wof:placetype":"postalcode"
},
  "geometry": {"coordinates":[-0.26184343702112,51.52205155440995],"type":"Point"}
}