{
  "type": "Feature",
  "properties": {
    "date:inception_lower":"1984-02-01",
    "date:inception_upper":"1984-02-29",
    "iso:country":"GB",
    "wof:name":"S5 7DT",
    "wof:placetype":"postalcode"
},
  "geometry": {"coordinates":[-1.458275,53.422254],"type":"Point"}
}