{
  "type": "Feature",
  "properties": {
    "iso:country":"GB",
    "wof:name":"S5 7DT",
    "wof:placetype":"postalcode"
},
  "geometry": {"coordinates":[-1.45827519924892,53.42224542311811],"type":"Point"}
}