{
  "type": "Feature",
  "properties": {
    "iso:country":"GB",
    "wof:name":"CF31 3NN",
    "wof:placetype":"postalcode"
},
  "geometry": {"coordinates":[-3.57990220430785,51.50117253279083],"type":"Point"}
}