{
  "type": "Feature",
  "properties": {
    "date:inception_lower": "2004-03-01",
    "date:inception_upper": "2004-03-01",
    "iso:country": "GB",
    "wof:name": "SN16 0QD",
    "wof:placetype": "postalcode"
  },
  "geometry": {"coordinates":[-2.112088,51.587344],"type":"Point"}
}
