{
  "type": "Feature",
  "properties": {
    "iso:country":"GB",
    "wof:name":"SN16 0QD",
    "wof:placetype":"postalcode"
},
  "geometry": {"coordinates":[-2.11208776725319,51.58734446918385],"type":"Point"}
}