{
  "type": "Feature",
  "properties": {
    "iso:country":"GB",
    "wof:name":"BH8 0PE",
    "wof:placetype":"postalcode"
},
  "geometry": {"coordinates":[-1.84863301053216,50.75429299896346],"type":"Point"}
}