{
  "type": "Feature",
  "properties": {
    "iso:country":"GB",
    "wof:name":"NG21 9AY",
    "wof:placetype":"postalcode"
},
  "geometry": {"coordinates":[-1.10313077411814,53.17713403281667],"type":"Point"}
}