{
  "type": "Feature",
  "properties": {
    "date:inception_lower": "1994-12-01",
    "date:inception_upper": "1994-12-01",
    "iso:country": "GB",
    "wof:name": "NG21 9AY",
    "wof:placetype": "postalcode"
  },
  "geometry": {"coordinates":[-1.103188,53.177154],"type":"Point"}
}
