{
  "type": "Feature",
  "properties": {
    "iso:country": "GB",
    "wof:name": "NG21 9AY",
    "wof:placetype": "postalcode"
  },
  "geometry": {"coordinates":[-1.103131,53.177134],"type":"Point"}
}
