{
  "type": "Feature",
  "properties": {
    "date:inception_lower":"1994-12-01",
    "date:inception_upper":"1994-12-31",
    "iso:country":"GB",
    "wof:name":"NG21 9AY",
    "wof:placetype":"postalcode"
},
  "geometry": {"coordinates":[-1.103131,53.177134],"type":"Point"}
}