{
  "type": "Feature",
  "properties": {
    "date:inception_lower": "1991-01-01",
    "date:inception_upper": "1991-01-01",
    "iso:country": "GB",
    "wof:name": "NN16 9JG",
    "wof:placetype": "postalcode"
  },
  "geometry": {"coordinates":[-0.725595,52.41958],"type":"Point"}
}
