{
  "type": "Feature",
  "properties": {
    "iso:country":"GB",
    "wof:name":"NN16 9JG",
    "wof:placetype":"postalcode"
},
  "geometry": {"coordinates":[-0.72559533587069,52.41957999745917],"type":"Point"}
}