{
  "type": "Feature",
  "properties": {
    "iso:country": "GB",
    "wof:name": "RH16 4WP",
    "wof:placetype": "postalcode"
  },
  "geometry": {"coordinates":[-0.111673,50.994227],"type":"Point"}
}
