{
  "type": "Feature",
  "properties": {
    "date:inception_lower": "1980-01-01",
    "date:inception_upper": "1980-01-01",
    "iso:country": "GB",
    "wof:name": "WA14 1NQ",
    "wof:placetype": "postalcode"
  },
  "geometry": {"coordinates":[-2.347567,53.395272],"type":"Point"}
}
