{
  "type": "Feature",
  "properties": {
    "iso:country":"GB",
    "wof:name":"TN12 5PD",
    "wof:placetype":"postalcode"
},
  "geometry": {"coordinates":[0.39262550667663,51.21430118898688],"type":"Point"}
}