{
  "type": "Feature",
  "properties": {
    "iso:country": "GB",
    "wof:name": "TN12 5PD",
    "wof:placetype": "postalcode"
  },
  "geometry": {"coordinates":[0.392626,51.214301],"type":"Point"}
}
