{
  "type": "Feature",
  "properties": {
    "iso:country":"GB",
    "wof:name":"CO4 9XR",
    "wof:placetype":"postalcode"
},
  "geometry": {"coordinates":[0.91521635681013,51.91075707664336],"type":"Point"}
}