{
  "type": "Feature",
  "properties": {
    "date:inception_lower": "1995-12-01",
    "date:inception_upper": "1995-12-01",
    "iso:country": "GB",
    "wof:name": "CV12 0LE",
    "wof:placetype": "postalcode"
  },
  "geometry": {"coordinates":[-1.509337,52.468301],"type":"Point"}
}
