{
  "type": "Feature",
  "properties": {
    "iso:country":"GB",
    "wof:name":"SE1 3GR",
    "wof:placetype":"postalcode"
},
  "geometry": {"coordinates":[-0.07367093751177,51.49818643550334],"type":"Point"}
}