{
  "type": "Feature",
  "properties": {
    "date:inception_lower": "1980-01-01",
    "date:inception_upper": "1980-01-01",
    "iso:country": "GB",
    "wof:name": "CF48 4PP",
    "wof:placetype": "postalcode"
  },
  "geometry": {"coordinates":[-3.346568,51.690976],"type":"Point"}
}
