{
  "type": "Feature",
  "properties": {
    "iso:country":"GB",
    "wof:name":"CH2 1PN",
    "wof:placetype":"postalcode"
},
  "geometry": {"coordinates":[-2.87313145461896,53.21090796167387],"type":"Point"}
}