{
  "type": "Feature",
  "properties": {
    "iso:country": "GB",
    "wof:name": "CH2 1PN",
    "wof:placetype": "postalcode"
  },
  "geometry": {"coordinates":[-2.873131,53.210908],"type":"Point"}
}
