{
  "type": "Feature",
  "properties": {
    "iso:country": "GB",
    "wof:name": "CH47 2DT",
    "wof:placetype": "postalcode"
  },
  "geometry": {"coordinates":[-3.177664,53.395317],"type":"Point"}
}
