{
  "type": "Feature",
  "properties": {
    "date:inception_lower": "2021-12-01",
    "date:inception_upper": "2021-12-01",
    "iso:country": "GB",
    "wof:name": "IG11 7ZP",
    "wof:placetype": "postalcode"
  },
  "geometry": {"coordinates":[0.074111,51.535109],"type":"Point"}
}
