{
  "type": "Feature",
  "properties": {
    "date:inception_lower": "1980-01-01",
    "date:inception_upper": "1980-01-01",
    "iso:country": "GB",
    "wof:name": "LL11 4RU",
    "wof:placetype": "postalcode"
  },
  "geometry": {"coordinates":[-3.019103,53.077246],"type":"Point"}
}
