{
  "type": "Feature",
  "properties": {
    "iso:country":"GB",
    "wof:name":"LL11 4RU",
    "wof:placetype":"postalcode"
},
  "geometry": {"coordinates":[-3.01910293990193,53.07724576730457],"type":"Point"}
}