{
  "type": "Feature",
  "properties": {
    "date:inception_lower": "1981-06-01",
    "date:inception_upper": "1981-06-01",
    "iso:country": "GB",
    "wof:name": "RH6 9AL",
    "wof:placetype": "postalcode"
  },
  "geometry": {"coordinates":[-0.155627,51.180028],"type":"Point"}
}
