{
  "type": "Feature",
  "properties": {
    "iso:country":"GB",
    "wof:name":"LS20 8QH",
    "wof:placetype":"postalcode"
},
  "geometry": {"coordinates":[-1.70921165946096,53.87113707697289],"type":"Point"}
}