{
  "type": "Feature",
  "properties": {
    "date:inception_lower": "2006-05-01",
    "date:inception_upper": "2006-05-01",
    "iso:country": "GB",
    "wof:name": "L23 6AD",
    "wof:placetype": "postalcode"
  },
  "geometry": {"coordinates":[-3.04604,53.484777],"type":"Point"}
}
