{
  "type": "Feature",
  "properties": {
    "iso:country":"GB",
    "wof:name":"L23 6AD",
    "wof:placetype":"postalcode"
},
  "geometry": {"coordinates":[-3.04602677826166,53.48473358776566],"type":"Point"}
}