{
  "type": "Feature",
  "properties": {
    "iso:country": "GB",
    "wof:name": "BN2 5QP",
    "wof:placetype": "postalcode"
  },
  "geometry": {"coordinates":[-0.104366,50.827456],"type":"Point"}
}
