{
  "type": "Feature",
  "properties": {
    "iso:country":"GB",
    "wof:name":"PE30 2BA",
    "wof:placetype":"postalcode"
},
  "geometry": {"coordinates":[0.40354160050348,52.75995382752924],"type":"Point"}
}