{
  "type": "Feature",
  "properties": {
    "iso:country": "GB",
    "wof:name": "PE30 2BA",
    "wof:placetype": "postalcode"
  },
  "geometry": {"coordinates":[0.403542,52.759954],"type":"Point"}
}
