{
  "type": "Feature",
  "properties": {
    "date:inception_lower": "1980-01-01",
    "date:inception_upper": "1980-01-01",
    "iso:country": "GB",
    "wof:name": "EX20 1LY",
    "wof:placetype": "postalcode"
  },
  "geometry": {"coordinates":[-3.99671,50.74068],"type":"Point"}
}
