{
  "type": "Feature",
  "properties": {
    "iso:country":"GB",
    "wof:name":"EX20 1LY",
    "wof:placetype":"postalcode"
},
  "geometry": {"coordinates":[-3.996709670009,50.74068045305225],"type":"Point"}
}