{
  "type": "Feature",
  "properties": {
    "iso:country":"GB",
    "wof:name":"SY3 9HQ",
    "wof:placetype":"postalcode"
},
  "geometry": {"coordinates":[-2.76440846348208,52.68696736406849],"type":"Point"}
}