{
  "type": "Feature",
  "properties": {
    "iso:country": "GB",
    "wof:name": "CO4 0EA",
    "wof:placetype": "postalcode"
  },
  "geometry": {"coordinates":[0.920939,51.89475],"type":"Point"}
}
