{
  "type": "Feature",
  "properties": {
    "date:inception_lower": "1995-01-01",
    "date:inception_upper": "1995-01-01",
    "iso:country": "GB",
    "wof:name": "KT4 8HE",
    "wof:placetype": "postalcode"
  },
  "geometry": {"coordinates":[-0.228937,51.378911],"type":"Point"}
}
