{
  "type": "Feature",
  "properties": {
    "date:inception_lower": "1980-01-01",
    "date:inception_upper": "1980-01-01",
    "iso:country": "GB",
    "wof:name": "LA6 3HN",
    "wof:placetype": "postalcode"
  },
  "geometry": {"coordinates":[-2.482027,54.151191],"type":"Point"}
}
