{
  "type": "Feature",
  "properties": {
    "iso:country":"GB",
    "wof:name":"LA6 3HN",
    "wof:placetype":"postalcode"
},
  "geometry": {"coordinates":[-2.48200889347714,54.15115277905364],"type":"Point"}
}