{
  "type": "Feature",
  "properties": {
    "iso:country":"GB",
    "wof:name":"BA6 8QE",
    "wof:placetype":"postalcode"
},
  "geometry": {"coordinates":[-2.63551060894896,51.11378589356895],"type":"Point"}
}