{
  "type": "Feature",
  "properties": {
    "iso:country":"GB",
    "wof:name":"LE10 1AN",
    "wof:placetype":"postalcode"
},
  "geometry": {"coordinates":[-1.3702274930926,52.53708250410899],"type":"Point"}
}