{
  "type": "Feature",
  "properties": {
    "date:inception_lower":"1980-01-01",
    "date:inception_upper":"1980-01-31",
    "iso:country":"GB",
    "wof:name":"LE10 1AN",
    "wof:placetype":"postalcode"
},
  "geometry": {"coordinates":[-1.370227,52.537082],"type":"Point"}
}