{
  "type": "Feature",
  "properties": {
    "iso:country":"GB",
    "wof:name":"B74 2LW",
    "wof:placetype":"postalcode"
},
  "geometry": {"coordinates":[-1.87914278761944,52.57766582975407],"type":"Point"}
}