{
  "type": "Feature",
  "properties": {
    "iso:country":"GB",
    "wof:name":"SS7 2HJ",
    "wof:placetype":"postalcode"
},
  "geometry": {"coordinates":[0.61744758845149,51.55353186201172],"type":"Point"}
}