{
  "type": "Feature",
  "properties": {
    "iso:country": "GB",
    "wof:name": "SS7 2HJ",
    "wof:placetype": "postalcode"
  },
  "geometry": {"coordinates":[0.617448,51.553532],"type":"Point"}
}
