{
  "type": "Feature",
  "properties": {
    "iso:country":"GB",
    "wof:name":"PO20 3SB",
    "wof:placetype":"postalcode"
},
  "geometry": {"coordinates":[-0.66390409792609,50.85381998949318],"type":"Point"}
}