{
  "type": "Feature",
  "properties": {
    "date:inception_lower":"2002-06-01",
    "date:inception_upper":"2002-06-30",
    "iso:country":"GB",
    "wof:name":"PO20 3SB",
    "wof:placetype":"postalcode"
},
  "geometry": {"coordinates":[-0.663904,50.85382],"type":"Point"}
}