{
  "type": "Feature",
  "properties": {
    "date:inception_lower": "2020-08-01",
    "date:inception_upper": "2020-08-01",
    "iso:country": "GB",
    "wof:name": "BB11 1EX",
    "wof:placetype": "postalcode"
  },
  "geometry": {"coordinates":[-2.251917,53.789762],"type":"Point"}
}
