{
  "type": "Feature",
  "properties": {
    "iso:country": "GB",
    "wof:name": "CA5 7LD",
    "wof:placetype": "postalcode"
  },
  "geometry": {"coordinates":[-2.981621,54.859453],"type":"Point"}
}
