{
  "type": "Feature",
  "properties": {
    "date:inception_lower": "2022-02-01",
    "date:inception_upper": "2022-02-01",
    "iso:country": "GB",
    "wof:name": "LU7 0GT",
    "wof:placetype": "postalcode"
  },
  "geometry": {"coordinates":[-0.758026,51.924892],"type":"Point"}
}
