{
  "type": "Feature",
  "properties": {
    "date:inception_lower": "2002-06-01",
    "date:inception_upper": "2002-06-01",
    "iso:country": "GB",
    "wof:name": "DN20 9FB",
    "wof:placetype": "postalcode"
  },
  "geometry": {"coordinates":[-0.523213,53.508329],"type":"Point"}
}
