{
  "type": "Feature",
  "properties": {
    "iso:country":"GB",
    "wof:name":"DN20 9FB",
    "wof:placetype":"postalcode"
},
  "geometry": {"coordinates":[-0.52321260593355,53.5083286307414],"type":"Point"}
}