{
  "type": "Feature",
  "properties": {
    "iso:country":"GB",
    "wof:name":"W8 7AU",
    "wof:placetype":"postalcode"
},
  "geometry": {"coordinates":[-0.20022155543005,51.50813718294071],"type":"Point"}
}