{
  "type": "Feature",
  "properties": {
    "iso:country": "GB",
    "wof:name": "GU14 7SS",
    "wof:placetype": "postalcode"
  },
  "geometry": {"coordinates":[-0.763738,51.289719],"type":"Point"}
}
