{
  "type": "Feature",
  "properties": {
    "iso:country": "GB",
    "wof:name": "EH41 3AH",
    "wof:placetype": "postalcode"
  },
  "geometry": {"coordinates":[-2.783735,55.956599],"type":"Point"}
}
