{
  "type": "Feature",
  "properties": {
    "date:inception_lower":"1980-01-01",
    "date:inception_upper":"1980-01-31",
    "iso:country":"GB",
    "wof:name":"EH41 3AH",
    "wof:placetype":"postalcode"
},
  "geometry": {"coordinates":[-2.783735,55.956599],"type":"Point"}
}