{
  "type": "Feature",
  "properties": {
    "date:inception_lower":"1980-01-01",
    "date:inception_upper":"1980-01-31",
    "iso:country":"GB",
    "wof:name":"IV55 8GR",
    "wof:placetype":"postalcode"
},
  "geometry": {"coordinates":[-6.568961,57.544828],"type":"Point"}
}