{
  "type": "Feature",
  "properties": {
    "iso:country":"GB",
    "wof:name":"IV55 8GR",
    "wof:placetype":"postalcode"
},
  "geometry": {"coordinates":[-6.56896131004481,57.5448282145715],"type":"Point"}
}