{
  "type": "Feature",
  "properties": {
    "iso:country":"GB",
    "wof:name":"G61 2ER",
    "wof:placetype":"postalcode"
},
  "geometry": {"coordinates":[-4.31265092627087,55.91598334788277],"type":"Point"}
}