{
  "type": "Feature",
  "properties": {
    "iso:country":"GB",
    "wof:name":"SY21 7QU",
    "wof:placetype":"postalcode"
},
  "geometry": {"coordinates":[-3.14079229589917,52.66504456382545],"type":"Point"}
}