{
  "type": "Feature",
  "properties": {
    "iso:country": "GB",
    "wof:name": "ST3 1PH",
    "wof:placetype": "postalcode"
  },
  "geometry": {"coordinates":[-2.13019,52.985815],"type":"Point"}
}
