{
  "type": "Feature",
  "properties": {
    "iso:country":"GB",
    "wof:name":"GU2 4DH",
    "wof:placetype":"postalcode"
},
  "geometry": {"coordinates":[-0.57920378489955,51.23336567537299],"type":"Point"}
}