{
  "type": "Feature",
  "properties": {
    "iso:country": "GB",
    "wof:name": "CT15 5EF",
    "wof:placetype": "postalcode"
  },
  "geometry": {"coordinates":[1.319832,51.144635],"type":"Point"}
}
