{
  "type": "Feature",
  "properties": {
    "iso:country":"GB",
    "wof:name":"TA4 2JD",
    "wof:placetype":"postalcode"
},
  "geometry": {"coordinates":[-3.41544283722198,51.0755503699101],"type":"Point"}
}