{
  "type": "Feature",
  "properties": {
    "date:inception_lower":"1987-10-01",
    "date:inception_upper":"1987-10-31",
    "iso:country":"GB",
    "wof:name":"BN2 5HT",
    "wof:placetype":"postalcode"
},
  "geometry": {"coordinates":[-0.104322,50.829596],"type":"Point"}
}