{
  "type": "Feature",
  "properties": {
    "iso:country":"GB",
    "wof:name":"BN2 5HT",
    "wof:placetype":"postalcode"
},
  "geometry": {"coordinates":[-0.10432170177649,50.82959551945704],"type":"Point"}
}