{
  "type": "Feature",
  "properties": {
    "iso:country": "GB",
    "wof:name": "BN2 5HT",
    "wof:placetype": "postalcode"
  },
  "geometry": {"coordinates":[-0.104322,50.829596],"type":"Point"}
}
