{
  "type": "Feature",
  "properties": {
    "date:inception_lower": "1980-01-01",
    "date:inception_upper": "1980-01-01",
    "iso:country": "GB",
    "wof:name": "SP2 7JZ",
    "wof:placetype": "postalcode"
  },
  "geometry": {"coordinates":[-1.819918,51.075103],"type":"Point"}
}
