{
  "type": "Feature",
  "properties": {
    "iso:country":"GB",
    "wof:name":"L14 1QA",
    "wof:placetype":"postalcode"
},
  "geometry": {"coordinates":[-2.90122495582131,53.41262783120978],"type":"Point"}
}