{
  "type": "Feature",
  "properties": {
    "iso:country": "GB",
    "wof:name": "SP2 0PB",
    "wof:placetype": "postalcode"
  },
  "geometry": {"coordinates":[-1.889886,51.118379],"type":"Point"}
}
