{
  "type": "Feature",
  "properties": {
    "iso:country": "GB",
    "wof:name": "CF83 8LD",
    "wof:placetype": "postalcode"
  },
  "geometry": {"coordinates":[-3.136248,51.5947],"type":"Point"}
}
