{
  "type": "Feature",
  "properties": {
    "iso:country":"GB",
    "wof:name":"CF83 8LD",
    "wof:placetype":"postalcode"
},
  "geometry": {"coordinates":[-3.13624810887881,51.59470013930929],"type":"Point"}
}