{
  "type": "Feature",
  "properties": {
    "iso:country":"GB",
    "wof:name":"BN41 2LF",
    "wof:placetype":"postalcode"
},
  "geometry": {"coordinates":[-0.22008338069529,50.84226499767445],"type":"Point"}
}