{
  "type": "Feature",
  "properties": {
    "iso:country": "GB",
    "wof:name": "BN41 2LF",
    "wof:placetype": "postalcode"
  },
  "geometry": {"coordinates":[-0.220083,50.842265],"type":"Point"}
}
