{
  "type": "Feature",
  "properties": {
    "iso:country":"GB",
    "wof:name":"HD8 0HS",
    "wof:placetype":"postalcode"
},
  "geometry": {"coordinates":[-1.7083062646453,53.63127949940588],"type":"Point"}
}