{
  "type": "Feature",
  "properties": {
    "date:inception_lower":"1980-01-01",
    "date:inception_upper":"1980-01-31",
    "iso:country":"GB",
    "wof:name":"HD8 0HS",
    "wof:placetype":"postalcode"
},
  "geometry": {"coordinates":[-1.708309,53.631295],"type":"Point"}
}