{
  "type": "Feature",
  "properties": {
    "iso:country":"GB",
    "wof:name":"EC3R 8AB",
    "wof:placetype":"postalcode"
},
  "geometry": {"coordinates":[-0.08545647586335,51.51055539326375],"type":"Point"}
}