{
  "type": "Feature",
  "properties": {
    "iso:country": "GB",
    "wof:name": "SP11 9GP",
    "wof:placetype": "postalcode"
  },
  "geometry": {"coordinates":[-1.627291,51.250904],"type":"Point"}
}
