{
  "type": "Feature",
  "properties": {
    "date:inception_lower": "2019-05-01",
    "date:inception_upper": "2019-05-01",
    "iso:country": "GB",
    "wof:name": "SP11 9GP",
    "wof:placetype": "postalcode"
  },
  "geometry": {"coordinates":[-1.627291,51.250904],"type":"Point"}
}
