{
  "type": "Feature",
  "properties": {
    "iso:country":"GB",
    "wof:name":"N3 3EE",
    "wof:placetype":"postalcode"
},
  "geometry": {"coordinates":[-0.20630140013452,51.58921572374116],"type":"Point"}
}