{
  "type": "Feature",
  "properties": {
    "iso:country":"GB",
    "wof:name":"CV32 5YA",
    "wof:placetype":"postalcode"
},
  "geometry": {"coordinates":[-1.52703507440235,52.29533964570881],"type":"Point"}
}