{
  "type": "Feature",
  "properties": {
    "iso:country": "GB",
    "wof:name": "CV32 5YA",
    "wof:placetype": "postalcode"
  },
  "geometry": {"coordinates":[-1.527464,52.295374],"type":"Point"}
}
