{
  "type": "Feature",
  "properties": {
    "iso:country":"GB",
    "wof:name":"TW15 2LR",
    "wof:placetype":"postalcode"
},
  "geometry": {"coordinates":[-0.46770289141045,51.4307366407199],"type":"Point"}
}