{
  "type": "Feature",
  "properties": {
    "iso:country":"GB",
    "wof:name":"RM14 3AU",
    "wof:placetype":"postalcode"
},
  "geometry": {"coordinates":[0.25760117647426,51.5499574209093],"type":"Point"}
}