{
  "type": "Feature",
  "properties": {
    "date:inception_lower": "1980-01-01",
    "date:inception_upper": "1980-01-01",
    "iso:country": "GB",
    "wof:name": "MK46 5AF",
    "wof:placetype": "postalcode"
  },
  "geometry": {"coordinates":[-0.711723,52.151359],"type":"Point"}
}
