{
  "type": "Feature",
  "properties": {
    "iso:country":"GB",
    "wof:name":"MK46 5AF",
    "wof:placetype":"postalcode"
},
  "geometry": {"coordinates":[-0.71172286523544,52.15135923549535],"type":"Point"}
}