{
  "type": "Feature",
  "properties": {
    "iso:country":"GB",
    "wof:name":"NN11 4UA",
    "wof:placetype":"postalcode"
},
  "geometry": {"coordinates":[-1.16129793950746,52.24702636808275],"type":"Point"}
}