{
  "type": "Feature",
  "properties": {
    "iso:country": "GB",
    "wof:name": "NN11 4UA",
    "wof:placetype": "postalcode"
  },
  "geometry": {"coordinates":[-1.161298,52.247026],"type":"Point"}
}
