{
  "type": "Feature",
  "properties": {
    "iso:country":"GB",
    "wof:name":"BH23 2EN",
    "wof:placetype":"postalcode"
},
  "geometry": {"coordinates":[-1.80172005469609,50.74190287018544],"type":"Point"}
}