{
  "type": "Feature",
  "properties": {
    "iso:country":"GB",
    "wof:name":"CT5 4JG",
    "wof:placetype":"postalcode"
},
  "geometry": {"coordinates":[1.02525985231556,51.35032357440868],"type":"Point"}
}