{
  "type": "Feature",
  "properties": {
    "date:inception_lower": "1980-01-01",
    "date:inception_upper": "1980-01-01",
    "iso:country": "GB",
    "wof:name": "CT5 4JG",
    "wof:placetype": "postalcode"
  },
  "geometry": {"coordinates":[1.025276,51.350328],"type":"Point"}
}
