{
  "type": "Feature",
  "properties": {
    "iso:country": "GB",
    "wof:name": "MK45 2FN",
    "wof:placetype": "postalcode"
  },
  "geometry": {"coordinates":[-0.507342,52.021113],"type":"Point"}
}
