{
  "type": "Feature",
  "properties": {
    "iso:country":"GB",
    "wof:name":"WR8 0QX",
    "wof:placetype":"postalcode"
},
  "geometry": {"coordinates":[-2.24381455547621,52.04725860456378],"type":"Point"}
}