{
  "type": "Feature",
  "properties": {
    "date:inception_lower": "1980-01-01",
    "date:inception_upper": "1980-01-01",
    "iso:country": "GB",
    "wof:name": "CA11 7ER",
    "wof:placetype": "postalcode"
  },
  "geometry": {"coordinates":[-2.755653,54.659128],"type":"Point"}
}
