{
  "type": "Feature",
  "properties": {
    "iso:country":"GB",
    "wof:name":"HD6 4DT",
    "wof:placetype":"postalcode"
},
  "geometry": {"coordinates":[-1.77903512393812,53.72035963575446],"type":"Point"}
}