{
  "type": "Feature",
  "properties": {
    "iso:country": "GB",
    "wof:name": "HD6 4DT",
    "wof:placetype": "postalcode"
  },
  "geometry": {"coordinates":[-1.779035,53.72036],"type":"Point"}
}
