{
  "type": "Feature",
  "properties": {
    "iso:country": "GB",
    "wof:name": "BS40 6HL",
    "wof:placetype": "postalcode"
  },
  "geometry": {"coordinates":[-2.636718,51.316666],"type":"Point"}
}
