{
  "type": "Feature",
  "properties": {
    "iso:country":"GB",
    "wof:name":"DH9 8QD",
    "wof:placetype":"postalcode"
},
  "geometry": {"coordinates":[-1.7386467564877,54.86006782468299],"type":"Point"}
}