{
  "type": "Feature",
  "properties": {
    "date:inception_lower":"1980-01-01",
    "date:inception_upper":"1980-01-31",
    "iso:country":"GB",
    "wof:name":"SP3 6RU",
    "wof:placetype":"postalcode"
},
  "geometry": {"coordinates":[-2.06634,51.047605],"type":"Point"}
}