{
  "type": "Feature",
  "properties": {
    "iso:country":"GB",
    "wof:name":"SP3 6RU",
    "wof:placetype":"postalcode"
},
  "geometry": {"coordinates":[-2.06634036769395,51.04760476205929],"type":"Point"}
}