{
  "type": "Feature",
  "properties": {
    "date:inception_lower": "2003-03-01",
    "date:inception_upper": "2003-03-01",
    "iso:country": "GB",
    "wof:name": "WS12 3YD",
    "wof:placetype": "postalcode"
  },
  "geometry": {"coordinates":[-1.996673,52.690404],"type":"Point"}
}
