{
  "type": "Feature",
  "properties": {
    "iso:country":"GB",
    "wof:name":"BA22 8JB",
    "wof:placetype":"postalcode"
},
  "geometry": {"coordinates":[-2.64403194812572,51.04028167067754],"type":"Point"}
}