{
  "type": "Feature",
  "properties": {
    "iso:country": "GB",
    "wof:name": "N1 8HF",
    "wof:placetype": "postalcode"
  },
  "geometry": {"coordinates":[-0.098754,51.533487],"type":"Point"}
}
