{
  "type": "Feature",
  "properties": {
    "iso:country": "GB",
    "wof:name": "CO9 3JZ",
    "wof:placetype": "postalcode"
  },
  "geometry": {"coordinates":[0.589974,51.973657],"type":"Point"}
}
