{
  "type": "Feature",
  "properties": {
    "iso:country":"GB",
    "wof:name":"CO9 3JZ",
    "wof:placetype":"postalcode"
},
  "geometry": {"coordinates":[0.58997433219676,51.97365661417815],"type":"Point"}
}