{
  "type": "Feature",
  "properties": {
    "date:inception_lower":"1980-01-01",
    "date:inception_upper":"1980-01-31",
    "iso:country":"GB",
    "wof:name":"CO9 3JZ",
    "wof:placetype":"postalcode"
},
  "geometry": {"coordinates":[0.589974,51.973657],"type":"Point"}
}