{
  "type": "Feature",
  "properties": {
    "iso:country":"GB",
    "wof:name":"NE66 3HA",
    "wof:placetype":"postalcode"
},
  "geometry": {"coordinates":[-1.68080134466683,55.4878675087678],"type":"Point"}
}