{
  "type": "Feature",
  "properties": {
    "iso:country": "GB",
    "wof:name": "RH12 3ED",
    "wof:placetype": "postalcode"
  },
  "geometry": {"coordinates":[-0.441584,51.096625],"type":"Point"}
}
