{
  "type": "Feature",
  "properties": {
    "iso:country": "GB",
    "wof:name": "EX37 9EN",
    "wof:placetype": "postalcode"
  },
  "geometry": {"coordinates":[-3.99304,50.965618],"type":"Point"}
}
