{
  "type": "Feature",
  "properties": {
    "iso:country":"GB",
    "wof:name":"CV33 9BN",
    "wof:placetype":"postalcode"
},
  "geometry": {"coordinates":[-1.46948454994911,52.32099640137722],"type":"Point"}
}