{
  "type": "Feature",
  "properties": {
    "date:inception_lower":"1980-01-01",
    "date:inception_upper":"1980-01-31",
    "iso:country":"GB",
    "wof:name":"GL53 9QQ",
    "wof:placetype":"postalcode"
},
  "geometry": {"coordinates":[-2.069332,51.868611],"type":"Point"}
}