{
  "type": "Feature",
  "properties": {
    "iso:country":"GB",
    "wof:name":"B46 2RP",
    "wof:placetype":"postalcode"
},
  "geometry": {"coordinates":[-1.64882384832152,52.50298663411225],"type":"Point"}
}