{
  "type": "Feature",
  "properties": {
    "date:inception_lower": "1980-01-01",
    "date:inception_upper": "1980-01-01",
    "iso:country": "GB",
    "wof:name": "GL7 6HS",
    "wof:placetype": "postalcode"
  },
  "geometry": {"coordinates":[-1.95322,51.695509],"type":"Point"}
}
