{
  "type": "Feature",
  "properties": {
    "iso:country":"GB",
    "wof:name":"SG19 3LA",
    "wof:placetype":"postalcode"
},
  "geometry": {"coordinates":[-0.19613536508872,52.15450944053956],"type":"Point"}
}