{
  "type": "Feature",
  "properties": {
    "iso:country": "GB",
    "wof:name": "AB15 7RD",
    "wof:placetype": "postalcode"
  },
  "geometry": {"coordinates":[-2.160908,57.130056],"type":"Point"}
}
