{
  "type": "Feature",
  "properties": {
    "iso:country": "GB",
    "wof:name": "SG1 3JE",
    "wof:placetype": "postalcode"
  },
  "geometry": {"coordinates":[-0.20406,51.909775],"type":"Point"}
}
