{
  "type": "Feature",
  "properties": {
    "iso:country":"GB",
    "wof:name":"SG1 3JE",
    "wof:placetype":"postalcode"
},
  "geometry": {"coordinates":[-0.20401003776659,51.90978524657145],"type":"Point"}
}