{
  "type": "Feature",
  "properties": {
    "iso:country": "GB",
    "wof:name": "CV8 3EU",
    "wof:placetype": "postalcode"
  },
  "geometry": {"coordinates":[-1.435626,52.368415],"type":"Point"}
}
