{
  "type": "Feature",
  "properties": {
    "date:inception_lower": "1980-01-01",
    "date:inception_upper": "1980-01-01",
    "iso:country": "GB",
    "wof:name": "CV8 3EU",
    "wof:placetype": "postalcode"
  },
  "geometry": {"coordinates":[-1.43589,52.368417],"type":"Point"}
}
