{
  "type": "Feature",
  "properties": {
    "iso:country": "GB",
    "wof:name": "DL16 7GE",
    "wof:placetype": "postalcode"
  },
  "geometry": {"coordinates":[-1.613187,54.69962],"type":"Point"}
}
