{
  "type": "Feature",
  "properties": {
    "date:inception_lower": "2007-01-01",
    "date:inception_upper": "2007-01-01",
    "iso:country": "GB",
    "wof:name": "DL16 7GE",
    "wof:placetype": "postalcode"
  },
  "geometry": {"coordinates":[-1.613187,54.69962],"type":"Point"}
}
