{
  "type": "Feature",
  "properties": {
    "iso:country":"GB",
    "wof:name":"PE27 5PH",
    "wof:placetype":"postalcode"
},
  "geometry": {"coordinates":[-0.07411353758618,52.32573105132943],"type":"Point"}
}