{
  "type": "Feature",
  "properties": {
    "iso:country": "GB",
    "wof:name": "PE27 5PH",
    "wof:placetype": "postalcode"
  },
  "geometry": {"coordinates":[-0.074073,52.325791],"type":"Point"}
}
