{
  "type": "Feature",
  "properties": {
    "iso:country":"GB",
    "wof:name":"CO2 7UE",
    "wof:placetype":"postalcode"
},
  "geometry": {"coordinates":[0.89472196005939,51.87767221022317],"type":"Point"}
}