{
  "type": "Feature",
  "properties": {
    "iso:country": "GB",
    "wof:name": "RM3 0EA",
    "wof:placetype": "postalcode"
  },
  "geometry": {"coordinates":[0.226175,51.594938],"type":"Point"}
}
