{
  "type": "Feature",
  "properties": {
    "iso:country":"GB",
    "wof:name":"RM3 0EA",
    "wof:placetype":"postalcode"
},
  "geometry": {"coordinates":[0.22617472360898,51.59493795715186],"type":"Point"}
}