{
  "type": "Feature",
  "properties": {
    "iso:country":"GB",
    "wof:name":"HP1 3QZ",
    "wof:placetype":"postalcode"
},
  "geometry": {"coordinates":[-0.49381310478998,51.76069556819208],"type":"Point"}
}