{
  "type": "Feature",
  "properties": {
    "iso:country":"GB",
    "wof:name":"SO45 3PU",
    "wof:placetype":"postalcode"
},
  "geometry": {"coordinates":[-1.39998900802957,50.84732553565448],"type":"Point"}
}