{
  "type": "Feature",
  "properties": {
    "iso:country":"GB",
    "wof:name":"DY8 2DW",
    "wof:placetype":"postalcode"
},
  "geometry": {"coordinates":[-2.1534567448541,52.44669831136035],"type":"Point"}
}