{
  "type": "Feature",
  "properties": {
    "iso:country": "GB",
    "wof:name": "DY8 2DW",
    "wof:placetype": "postalcode"
  },
  "geometry": {"coordinates":[-2.153495,52.446641],"type":"Point"}
}
