{
  "type": "Feature",
  "properties": {
    "iso:country": "GB",
    "wof:name": "NE12 7AA",
    "wof:placetype": "postalcode"
  },
  "geometry": {"coordinates":[-1.562669,55.026178],"type":"Point"}
}
