{
  "type": "Feature",
  "properties": {
    "iso:country":"GB",
    "wof:name":"NE12 7AA",
    "wof:placetype":"postalcode"
},
  "geometry": {"coordinates":[-1.5626692719926,55.02617755685133],"type":"Point"}
}