{
  "type": "Feature",
  "properties": {
    "iso:country":"GB",
    "wof:name":"G52 1NW",
    "wof:placetype":"postalcode"
},
  "geometry": {"coordinates":[-4.32325079263176,55.83821182951726],"type":"Point"}
}