{
  "type": "Feature",
  "properties": {
    "iso:country": "GB",
    "wof:name": "G52 1NW",
    "wof:placetype": "postalcode"
  },
  "geometry": {"coordinates":[-4.323251,55.838212],"type":"Point"}
}
