{
  "type": "Feature",
  "properties": {
    "iso:country": "GB",
    "wof:name": "GU14 9DR",
    "wof:placetype": "postalcode"
  },
  "geometry": {"coordinates":[-0.777581,51.302139],"type":"Point"}
}
