{
  "type": "Feature",
  "properties": {
    "iso:country":"GB",
    "wof:name":"E11 4EE",
    "wof:placetype":"postalcode"
},
  "geometry": {"coordinates":[-0.00209831301677,51.55935292213299],"type":"Point"}
}