{
  "type": "Feature",
  "properties": {
    "iso:country":"GB",
    "wof:name":"MK40 3DR",
    "wof:placetype":"postalcode"
},
  "geometry": {"coordinates":[-0.45014617996737,52.14122608029631],"type":"Point"}
}