{
  "type": "Feature",
  "properties": {
    "iso:country":"GB",
    "wof:name":"IP7 5BS",
    "wof:placetype":"postalcode"
},
  "geometry": {"coordinates":[0.96097017153637,52.04681176904528],"type":"Point"}
}