{
  "type": "Feature",
  "properties": {
    "iso:country": "GB",
    "wof:name": "IP7 5BS",
    "wof:placetype": "postalcode"
  },
  "geometry": {"coordinates":[0.96097,52.046812],"type":"Point"}
}
