{
  "type": "Feature",
  "properties": {
    "iso:country":"GB",
    "wof:name":"BN12 6BQ",
    "wof:placetype":"postalcode"
},
  "geometry": {"coordinates":[-0.42527704856038,50.82019545558155],"type":"Point"}
}