{
  "type": "Feature",
  "properties": {
    "iso:country": "GB",
    "wof:name": "DE24 0QD",
    "wof:placetype": "postalcode"
  },
  "geometry": {"coordinates":[-1.416827,52.894977],"type":"Point"}
}
