{
  "type": "Feature",
  "properties": {
    "date:inception_lower":"1994-05-01",
    "date:inception_upper":"1994-05-31",
    "iso:country":"GB",
    "wof:name":"M20 4RA",
    "wof:placetype":"postalcode"
},
  "geometry": {"coordinates":[-2.218428,53.426311],"type":"Point"}
}