{
  "type": "Feature",
  "properties": {
    "date:inception_lower": "1980-01-01",
    "date:inception_upper": "1980-01-01",
    "iso:country": "GB",
    "wof:name": "DY6 9NX",
    "wof:placetype": "postalcode"
  },
  "geometry": {"coordinates":[-2.164422,52.488771],"type":"Point"}
}
