{
  "type": "Feature",
  "properties": {
    "iso:country":"GB",
    "wof:name":"DY6 9NX",
    "wof:placetype":"postalcode"
},
  "geometry": {"coordinates":[-2.16439831775911,52.48877470025777],"type":"Point"}
}