{
  "type": "Feature",
  "properties": {
    "date:inception_lower": "2018-04-01",
    "date:inception_upper": "2018-04-01",
    "iso:country": "GB",
    "wof:name": "TF1 1AH",
    "wof:placetype": "postalcode"
  },
  "geometry": {"coordinates":[-2.518141,52.70269],"type":"Point"}
}
