{
  "type": "Feature",
  "properties": {
    "iso:country": "GB",
    "wof:name": "SR2 0FE",
    "wof:placetype": "postalcode"
  },
  "geometry": {"coordinates":[-1.378587,54.870109],"type":"Point"}
}
