{
  "type": "Feature",
  "properties": {
    "iso:country":"GB",
    "wof:name":"LE17 5EQ",
    "wof:placetype":"postalcode"
},
  "geometry": {"coordinates":[-1.25484912936222,52.50896595869999],"type":"Point"}
}