{
  "type": "Feature",
  "properties": {
    "iso:country": "GB",
    "wof:name": "EH7 4FP",
    "wof:placetype": "postalcode"
  },
  "geometry": {"coordinates":[-3.180713,55.962747],"type":"Point"}
}
