{
  "type": "Feature",
  "properties": {
    "iso:country":"GB",
    "wof:name":"LE6 0AE",
    "wof:placetype":"postalcode"
},
  "geometry": {"coordinates":[-1.23420551372273,52.68519981314925],"type":"Point"}
}