{
  "type": "Feature",
  "properties": {
    "date:inception_lower": "1980-01-01",
    "date:inception_upper": "1980-01-01",
    "iso:country": "GB",
    "wof:name": "LE6 0AE",
    "wof:placetype": "postalcode"
  },
  "geometry": {"coordinates":[-1.234205,52.6852],"type":"Point"}
}
