{
  "type": "Feature",
  "properties": {
    "date:inception_lower":"2006-05-01",
    "date:inception_upper":"2006-05-31",
    "iso:country":"GB",
    "wof:name":"WA5 8DQ",
    "wof:placetype":"postalcode"
},
  "geometry": {"coordinates":[-2.636452,53.400329],"type":"Point"}
}