{
  "type": "Feature",
  "properties": {
    "iso:country":"GB",
    "wof:name":"WA5 8DQ",
    "wof:placetype":"postalcode"
},
  "geometry": {"coordinates":[-2.63645188570916,53.40032858158525],"type":"Point"}
}