{
  "type": "Feature",
  "properties": {
    "iso:country":"GB",
    "wof:name":"DL1 4ES",
    "wof:placetype":"postalcode"
},
  "geometry": {"coordinates":[-1.53396633661404,54.52131228499837],"type":"Point"}
}