{
  "type": "Feature",
  "properties": {
    "iso:country": "GB",
    "wof:name": "BN8 6QP",
    "wof:placetype": "postalcode"
  },
  "geometry": {"coordinates":[0.182916,50.926973],"type":"Point"}
}
