{
  "type": "Feature",
  "properties": {
    "iso:country":"GB",
    "wof:name":"BN8 6QP",
    "wof:placetype":"postalcode"
},
  "geometry": {"coordinates":[0.18290379143054,50.92700434051475],"type":"Point"}
}