{
  "type": "Feature",
  "properties": {
    "iso:country": "GB",
    "wof:name": "DN7 4HW",
    "wof:placetype": "postalcode"
  },
  "geometry": {"coordinates":[-1.015783,53.571582],"type":"Point"}
}
