{
  "type": "Feature",
  "properties": {
    "date:inception_lower":"1981-09-01",
    "date:inception_upper":"1981-09-30",
    "iso:country":"GB",
    "wof:name":"DN7 4HW",
    "wof:placetype":"postalcode"
},
  "geometry": {"coordinates":[-1.015783,53.571582],"type":"Point"}
}