{
  "type": "Feature",
  "properties": {
    "date:inception_lower": "1980-01-01",
    "date:inception_upper": "1980-01-01",
    "iso:country": "GB",
    "wof:name": "DG5 4EE",
    "wof:placetype": "postalcode"
  },
  "geometry": {"coordinates":[-3.815751,54.927972],"type":"Point"}
}
