{
  "type": "Feature",
  "properties": {
    "iso:country": "GB",
    "wof:name": "DG5 4EE",
    "wof:placetype": "postalcode"
  },
  "geometry": {"coordinates":[-3.815757,54.92801],"type":"Point"}
}
