{
  "type": "Feature",
  "properties": {
    "date:inception_lower":"2006-09-01",
    "date:inception_upper":"2006-09-30",
    "iso:country":"GB",
    "wof:name":"WA5 8WD",
    "wof:placetype":"postalcode"
},
  "geometry": {"coordinates":[-2.634326,53.411169],"type":"Point"}
}