{
  "type": "Feature",
  "properties": {
    "date:inception_lower": "2006-09-01",
    "date:inception_upper": "2006-09-01",
    "iso:country": "GB",
    "wof:name": "WA5 8WD",
    "wof:placetype": "postalcode"
  },
  "geometry": {"coordinates":[-2.634557,53.411483],"type":"Point"}
}
