{
  "type": "Feature",
  "properties": {
    "iso:country": "GB",
    "wof:name": "WA5 8WD",
    "wof:placetype": "postalcode"
  },
  "geometry": {"coordinates":[-2.634326,53.411169],"type":"Point"}
}
