{
  "type": "Feature",
  "properties": {
    "date:inception_lower": "2018-06-01",
    "date:inception_upper": "2018-06-01",
    "iso:country": "GB",
    "wof:name": "RH11 0GE",
    "wof:placetype": "postalcode"
  },
  "geometry": {"coordinates":[-0.22596,51.117118],"type":"Point"}
}
