{
  "type": "Feature",
  "properties": {
    "iso:country": "GB",
    "wof:name": "RH11 0GE",
    "wof:placetype": "postalcode"
  },
  "geometry": {"coordinates":[-0.225767,51.117286],"type":"Point"}
}
