{
  "type": "Feature",
  "properties": {
    "date:inception_lower": "1987-10-01",
    "date:inception_upper": "1987-10-01",
    "iso:country": "GB",
    "wof:name": "TS18 2HF",
    "wof:placetype": "postalcode"
  },
  "geometry": {"coordinates":[-1.304347,54.569468],"type":"Point"}
}
