{
  "type": "Feature",
  "properties": {
    "iso:country":"GB",
    "wof:name":"IP9 1LJ",
    "wof:placetype":"postalcode"
},
  "geometry": {"coordinates":[1.23086166803489,51.96670958153286],"type":"Point"}
}