{
  "type": "Feature",
  "properties": {
    "iso:country":"GB",
    "wof:name":"B90 1LF",
    "wof:placetype":"postalcode"
},
  "geometry": {"coordinates":[-1.86466548334567,52.40970008105216],"type":"Point"}
}