{
  "type": "Feature",
  "properties": {
    "iso:country": "GB",
    "wof:name": "MK18 3EB",
    "wof:placetype": "postalcode"
  },
  "geometry": {"coordinates":[-0.880628,51.942405],"type":"Point"}
}
