{
  "type": "Feature",
  "properties": {
    "date:inception_lower": "2022-02-01",
    "date:inception_upper": "2022-02-01",
    "iso:country": "GB",
    "wof:name": "PR4 5DS",
    "wof:placetype": "postalcode"
  },
  "geometry": {"coordinates":[-2.781307,53.726614],"type":"Point"}
}
