{
  "type": "Feature",
  "properties": {
    "iso:country":"GB",
    "wof:name":"WF3 2FQ",
    "wof:placetype":"postalcode"
},
  "geometry": {"coordinates":[-1.53572720965213,53.73248160042676],"type":"Point"}
}