{
  "type": "Feature",
  "properties": {
    "iso:country": "GB",
    "wof:name": "WF3 2FQ",
    "wof:placetype": "postalcode"
  },
  "geometry": {"coordinates":[-1.533067,53.730771],"type":"Point"}
}
