{
  "type": "Feature",
  "properties": {
    "iso:country":"GB",
    "wof:name":"SE26 5DR",
    "wof:placetype":"postalcode"
},
  "geometry": {"coordinates":[-0.04675268142554,51.42311984114749],"type":"Point"}
}