{
  "type": "Feature",
  "properties": {
    "date:inception_lower": "1995-07-01",
    "date:inception_upper": "1995-07-01",
    "iso:country": "GB",
    "wof:name": "CM7 3RG",
    "wof:placetype": "postalcode"
  },
  "geometry": {"coordinates":[0.568049,51.875413],"type":"Point"}
}
