{
  "type": "Feature",
  "properties": {
    "iso:country": "GB",
    "wof:name": "CM7 3RG",
    "wof:placetype": "postalcode"
  },
  "geometry": {"coordinates":[0.568592,51.87549],"type":"Point"}
}
