{
  "type": "Feature",
  "properties": {
    "iso:country": "GB",
    "wof:name": "ST9 9HP",
    "wof:placetype": "postalcode"
  },
  "geometry": {"coordinates":[-2.113817,53.080586],"type":"Point"}
}
