{
  "type": "Feature",
  "properties": {
    "iso:country":"GB",
    "wof:name":"S40 1PH",
    "wof:placetype":"postalcode"
},
  "geometry": {"coordinates":[-1.4306502335218,53.23586924080911],"type":"Point"}
}