{
  "type": "Feature",
  "properties": {
    "date:inception_lower": "1980-01-01",
    "date:inception_upper": "1980-01-01",
    "iso:country": "GB",
    "wof:name": "BS13 8LE",
    "wof:placetype": "postalcode"
  },
  "geometry": {"coordinates":[-2.618915,51.412776],"type":"Point"}
}
