{
  "type": "Feature",
  "properties": {
    "iso:country": "GB",
    "wof:name": "BS13 8LE",
    "wof:placetype": "postalcode"
  },
  "geometry": {"coordinates":[-2.618915,51.412776],"type":"Point"}
}
