{
  "type": "Feature",
  "properties": {
    "iso:country":"GB",
    "wof:name":"BS13 8LE",
    "wof:placetype":"postalcode"
},
  "geometry": {"coordinates":[-2.61891464458568,51.41277611707756],"type":"Point"}
}