{
  "type": "Feature",
  "properties": {
    "iso:country": "GB",
    "wof:name": "GL4 6ER",
    "wof:placetype": "postalcode"
  },
  "geometry": {"coordinates":[-2.217153,51.841341],"type":"Point"}
}
