{
  "type": "Feature",
  "properties": {
    "iso:country":"GB",
    "wof:name":"EX32 0LU",
    "wof:placetype":"postalcode"
},
  "geometry": {"coordinates":[-4.00081950758532,51.06041015279765],"type":"Point"}
}