{
  "type": "Feature",
  "properties": {
    "iso:country": "GB",
    "wof:name": "EX32 0LU",
    "wof:placetype": "postalcode"
  },
  "geometry": {"coordinates":[-4.000842,51.060407],"type":"Point"}
}
