{
  "type": "Feature",
  "properties": {
    "date:inception_lower": "1980-01-01",
    "date:inception_upper": "1980-01-01",
    "iso:country": "GB",
    "wof:name": "EX32 0LU",
    "wof:placetype": "postalcode"
  },
  "geometry": {"coordinates":[-4.000784,51.06039],"type":"Point"}
}
