{
  "type": "Feature",
  "properties": {
    "iso:country":"GB",
    "wof:name":"BN16 3PS",
    "wof:placetype":"postalcode"
},
  "geometry": {"coordinates":[-0.51592865347443,50.81873073207767],"type":"Point"}
}