{
  "type": "Feature",
  "properties": {
    "iso:country":"GB",
    "wof:name":"E14 7RE",
    "wof:placetype":"postalcode"
},
  "geometry": {"coordinates":[-0.03495584232622,51.51699516664618],"type":"Point"}
}