{
  "type": "Feature",
  "properties": {
    "iso:country":"GB",
    "wof:name":"BS3 1RH",
    "wof:placetype":"postalcode"
},
  "geometry": {"coordinates":[-2.61371193564829,51.44515557778443],"type":"Point"}
}