{
  "type": "Feature",
  "properties": {
    "iso:country": "GB",
    "wof:name": "SO32 2NL",
    "wof:placetype": "postalcode"
  },
  "geometry": {"coordinates":[-1.204274,50.937871],"type":"Point"}
}
