{
  "type": "Feature",
  "properties": {
    "iso:country":"GB",
    "wof:name":"M16 9QD",
    "wof:placetype":"postalcode"
},
  "geometry": {"coordinates":[-2.27055342608665,53.45872430316461],"type":"Point"}
}