{
  "type": "Feature",
  "properties": {
    "iso:country":"GB",
    "wof:name":"TR14 8DT",
    "wof:placetype":"postalcode"
},
  "geometry": {"coordinates":[-5.29176848480532,50.21481380484071],"type":"Point"}
}