{
  "type": "Feature",
  "properties": {
    "iso:country":"GB",
    "wof:name":"PE12 7PH",
    "wof:placetype":"postalcode"
},
  "geometry": {"coordinates":[0.02213787552134,52.80776360140631],"type":"Point"}
}