{
  "type": "Feature",
  "properties": {
    "iso:country":"GB",
    "wof:name":"HA2 8DQ",
    "wof:placetype":"postalcode"
},
  "geometry": {"coordinates":[-0.35837001811563,51.56593936272105],"type":"Point"}
}