{
  "type": "Feature",
  "properties": {
    "iso:country":"GB",
    "wof:name":"PL9 9TB",
    "wof:placetype":"postalcode"
},
  "geometry": {"coordinates":[-4.11910426198324,50.35772641251443],"type":"Point"}
}