{
  "type": "Feature",
  "properties": {
    "date:inception_lower": "2019-11-01",
    "date:inception_upper": "2019-11-01",
    "iso:country": "GB",
    "wof:name": "PH33 6FH",
    "wof:placetype": "postalcode"
  },
  "geometry": {"coordinates":[-5.114942,56.816206],"type":"Point"}
}
