{
  "type": "Feature",
  "properties": {
    "iso:country": "GB",
    "wof:name": "PH33 6FH",
    "wof:placetype": "postalcode"
  },
  "geometry": {"coordinates":[-5.114942,56.816206],"type":"Point"}
}
