{
  "type": "Feature",
  "properties": {
    "date:inception_lower": "2002-06-01",
    "date:inception_upper": "2002-06-01",
    "iso:country": "GB",
    "wof:name": "BL9 8ET",
    "wof:placetype": "postalcode"
  },
  "geometry": {"coordinates":[-2.2908,53.562915],"type":"Point"}
}
