{
  "type": "Feature",
  "properties": {
    "iso:country":"GB",
    "wof:name":"NE61 6HS",
    "wof:placetype":"postalcode"
},
  "geometry": {"coordinates":[-1.66653649575303,55.1090076530912],"type":"Point"}
}