{
  "type": "Feature",
  "properties": {
    "iso:country": "GB",
    "wof:name": "NE61 6HS",
    "wof:placetype": "postalcode"
  },
  "geometry": {"coordinates":[-1.666536,55.109008],"type":"Point"}
}
