{
  "type": "Feature",
  "properties": {
    "date:inception_lower": "1981-06-01",
    "date:inception_upper": "1981-06-01",
    "iso:country": "GB",
    "wof:name": "NE61 6HS",
    "wof:placetype": "postalcode"
  },
  "geometry": {"coordinates":[-1.666536,55.109008],"type":"Point"}
}
