{
  "type": "Feature",
  "properties": {
    "date:inception_lower":"1992-08-01",
    "date:inception_upper":"1992-08-31",
    "iso:country":"GB",
    "wof:name":"WR4 0JB",
    "wof:placetype":"postalcode"
},
  "geometry": {"coordinates":[-2.183991,52.200557],"type":"Point"}
}