{
  "type": "Feature",
  "properties": {
    "iso:country":"GB",
    "wof:name":"WR4 0JB",
    "wof:placetype":"postalcode"
},
  "geometry": {"coordinates":[-2.18399085180054,52.20055670515718],"type":"Point"}
}