{
  "type": "Feature",
  "properties": {
    "iso:country":"GB",
    "wof:name":"CB25 0FA",
    "wof:placetype":"postalcode"
},
  "geometry": {"coordinates":[0.30282564790278,52.25709040550757],"type":"Point"}
}