{
  "type": "Feature",
  "properties": {
    "iso:country": "GB",
    "wof:name": "CB25 0FA",
    "wof:placetype": "postalcode"
  },
  "geometry": {"coordinates":[0.302841,52.257108],"type":"Point"}
}
