{
  "type": "Feature",
  "properties": {
    "date:inception_lower":"1980-01-01",
    "date:inception_upper":"1980-01-31",
    "iso:country":"GB",
    "wof:name":"EH32 9DB",
    "wof:placetype":"postalcode"
},
  "geometry": {"coordinates":[-2.990631,55.952171],"type":"Point"}
}