{
  "type": "Feature",
  "properties": {
    "iso:country":"GB",
    "wof:name":"EH32 9DB",
    "wof:placetype":"postalcode"
},
  "geometry": {"coordinates":[-2.99063097006771,55.952170820246],"type":"Point"}
}