{
  "type": "Feature",
  "properties": {
    "date:inception_lower":"1980-01-01",
    "date:inception_upper":"1980-01-31",
    "iso:country":"GB",
    "wof:name":"SN3 3SU",
    "wof:placetype":"postalcode"
},
  "geometry": {"coordinates":[-1.739007,51.553993],"type":"Point"}
}