{
  "type": "Feature",
  "properties": {
    "iso:country":"GB",
    "wof:name":"SN3 3SU",
    "wof:placetype":"postalcode"
},
  "geometry": {"coordinates":[-1.73900690042664,51.55399344170939],"type":"Point"}
}