{
  "type": "Feature",
  "properties": {
    "iso:country": "GB",
    "wof:name": "SE7 7RH",
    "wof:placetype": "postalcode"
  },
  "geometry": {"coordinates":[0.021504,51.487088],"type":"Point"}
}
