{
  "type": "Feature",
  "properties": {
    "date:inception_lower": "1980-01-01",
    "date:inception_upper": "1980-01-01",
    "iso:country": "GB",
    "wof:name": "SE7 7RH",
    "wof:placetype": "postalcode"
  },
  "geometry": {"coordinates":[0.021532,51.487134],"type":"Point"}
}
