{
  "type": "Feature",
  "properties": {
    "iso:country":"GB",
    "wof:name":"SE7 7RH",
    "wof:placetype":"postalcode"
},
  "geometry": {"coordinates":[0.02150379949554,51.48708806894591],"type":"Point"}
}