{
  "type": "Feature",
  "properties": {
    "iso:country":"GB",
    "wof:name":"B76 1NE",
    "wof:placetype":"postalcode"
},
  "geometry": {"coordinates":[-1.80094524660936,52.53876917129032],"type":"Point"}
}