{
  "type": "Feature",
  "properties": {
    "iso:country":"GB",
    "wof:name":"DA1 3NF",
    "wof:placetype":"postalcode"
},
  "geometry": {"coordinates":[0.18801731475916,51.44556401348694],"type":"Point"}
}