{
  "type": "Feature",
  "properties": {
    "iso:country":"GB",
    "wof:name":"TR6 0PE",
    "wof:placetype":"postalcode"
},
  "geometry": {"coordinates":[-5.14258363338336,50.33661446821283],"type":"Point"}
}