{
  "type": "Feature",
  "properties": {
    "iso:country": "GB",
    "wof:name": "HA6 1QF",
    "wof:placetype": "postalcode"
  },
  "geometry": {"coordinates":[-0.403195,51.605997],"type":"Point"}
}
