{
  "type": "Feature",
  "properties": {
    "iso:country":"GB",
    "wof:name":"TA1 4PU",
    "wof:placetype":"postalcode"
},
  "geometry": {"coordinates":[-3.11175453407363,51.01204653703278],"type":"Point"}
}