{
  "type": "Feature",
  "properties": {
    "iso:country": "GB",
    "wof:name": "TA1 4PU",
    "wof:placetype": "postalcode"
  },
  "geometry": {"coordinates":[-3.111754,51.012047],"type":"Point"}
}
