{
  "type": "Feature",
  "properties": {
    "iso:country":"GB",
    "wof:name":"NG18 4XW",
    "wof:placetype":"postalcode"
},
  "geometry": {"coordinates":[-1.18148489642753,53.13244643627504],"type":"Point"}
}