{
  "type": "Feature",
  "properties": {
    "iso:country": "GB",
    "wof:name": "NG18 4XW",
    "wof:placetype": "postalcode"
  },
  "geometry": {"coordinates":[-1.181485,53.132446],"type":"Point"}
}
