{
  "type": "Feature",
  "properties": {
    "iso:country":"GB",
    "wof:name":"ML11 0SJ",
    "wof:placetype":"postalcode"
},
  "geometry": {"coordinates":[-3.92359895428902,55.53443232895273],"type":"Point"}
}