{
  "type": "Feature",
  "properties": {
    "iso:country": "GB",
    "wof:name": "SW14 7AL",
    "wof:placetype": "postalcode"
  },
  "geometry": {"coordinates":[-0.272618,51.460514],"type":"Point"}
}
