{
  "type": "Feature",
  "properties": {
    "iso:country":"GB",
    "wof:name":"W1T 6AE",
    "wof:placetype":"postalcode"
},
  "geometry": {"coordinates":[-0.14223196267895,51.52377917763247],"type":"Point"}
}