{
  "type": "Feature",
  "properties": {
    "iso:country":"GB",
    "wof:name":"AB54 4HJ",
    "wof:placetype":"postalcode"
},
  "geometry": {"coordinates":[-2.83318293880275,57.33363762157421],"type":"Point"}
}