{
  "type": "Feature",
  "properties": {
    "iso:country": "GB",
    "wof:name": "AB54 4HJ",
    "wof:placetype": "postalcode"
  },
  "geometry": {"coordinates":[-2.833183,57.333638],"type":"Point"}
}
