{
  "type": "Feature",
  "properties": {
    "iso:country": "GB",
    "wof:name": "AB13 0AH",
    "wof:placetype": "postalcode"
  },
  "geometry": {"coordinates":[-2.252877,57.098987],"type":"Point"}
}
