{
  "type": "Feature",
  "properties": {
    "iso:country":"GB",
    "wof:name":"LE9 4DT",
    "wof:placetype":"postalcode"
},
  "geometry": {"coordinates":[-1.28041713334677,52.55561173609667],"type":"Point"}
}