{
  "type": "Feature",
  "properties": {
    "iso:country":"GB",
    "wof:name":"NR7 8JB",
    "wof:placetype":"postalcode"
},
  "geometry": {"coordinates":[1.33678121908128,52.65338210084895],"type":"Point"}
}