{
  "type": "Feature",
  "properties": {
    "iso:country":"GB",
    "wof:name":"BD20 6FF",
    "wof:placetype":"postalcode"
},
  "geometry": {"coordinates":[-1.95738087228726,53.90069161986164],"type":"Point"}
}