{
  "type": "Feature",
  "properties": {
    "iso:country":"GB",
    "wof:name":"NE62 5XX",
    "wof:placetype":"postalcode"
},
  "geometry": {"coordinates":[-1.59204272195484,55.16662423232828],"type":"Point"}
}