{
  "type": "Feature",
  "properties": {
    "date:inception_lower":"1980-01-01",
    "date:inception_upper":"1980-01-31",
    "iso:country":"GB",
    "wof:name":"NE62 5XX",
    "wof:placetype":"postalcode"
},
  "geometry": {"coordinates":[-1.592043,55.166624],"type":"Point"}
}