{
  "type": "Feature",
  "properties": {
    "iso:country": "GB",
    "wof:name": "NE62 5XX",
    "wof:placetype": "postalcode"
  },
  "geometry": {"coordinates":[-1.592043,55.166624],"type":"Point"}
}
