{
  "type": "Feature",
  "properties": {
    "iso:country":"GB",
    "wof:name":"TD14 5QR",
    "wof:placetype":"postalcode"
},
  "geometry": {"coordinates":[-2.12814450044132,55.84436992908594],"type":"Point"}
}