{
  "type": "Feature",
  "properties": {
    "iso:country": "GB",
    "wof:name": "BH23 3BU",
    "wof:placetype": "postalcode"
  },
  "geometry": {"coordinates":[-1.748951,50.742997],"type":"Point"}
}
