{
  "type": "Feature",
  "properties": {
    "iso:country":"GB",
    "wof:name":"BH23 3BU",
    "wof:placetype":"postalcode"
},
  "geometry": {"coordinates":[-1.74895070113855,50.74299735340954],"type":"Point"}
}