{
  "type": "Feature",
  "properties": {
    "iso:country":"GB",
    "wof:name":"PH32 4BY",
    "wof:placetype":"postalcode"
},
  "geometry": {"coordinates":[-4.68581437044962,57.13287484587499],"type":"Point"}
}