{
  "type": "Feature",
  "properties": {
    "iso:country": "GB",
    "wof:name": "PH10 6TQ",
    "wof:placetype": "postalcode"
  },
  "geometry": {"coordinates":[-3.336366,56.581627],"type":"Point"}
}
