{
  "type": "Feature",
  "properties": {
    "iso:country":"GB",
    "wof:name":"CF32 9AY",
    "wof:placetype":"postalcode"
},
  "geometry": {"coordinates":[-3.59821263866487,51.54104765748863],"type":"Point"}
}