{
  "type": "Feature",
  "properties": {
    "date:inception_lower": "1980-01-01",
    "date:inception_upper": "1980-01-01",
    "iso:country": "GB",
    "wof:name": "CF32 9AY",
    "wof:placetype": "postalcode"
  },
  "geometry": {"coordinates":[-3.598213,51.541048],"type":"Point"}
}
