{
  "type": "Feature",
  "properties": {
    "iso:country": "GB",
    "wof:name": "CF32 9AY",
    "wof:placetype": "postalcode"
  },
  "geometry": {"coordinates":[-3.598213,51.541048],"type":"Point"}
}
