{
  "type": "Feature",
  "properties": {
    "iso:country": "GB",
    "wof:name": "CA11 0BY",
    "wof:placetype": "postalcode"
  },
  "geometry": {"coordinates":[-2.811776,54.666493],"type":"Point"}
}
