{
  "type": "Feature",
  "properties": {
    "iso:country":"GB",
    "wof:name":"CA11 0BY",
    "wof:placetype":"postalcode"
},
  "geometry": {"coordinates":[-2.8117760172155,54.666493368098],"type":"Point"}
}