{
  "type": "Feature",
  "properties": {
    "iso:country":"GB",
    "wof:name":"G65 9PE",
    "wof:placetype":"postalcode"
},
  "geometry": {"coordinates":[-4.07079373250517,55.98222697598379],"type":"Point"}
}