{
  "type": "Feature",
  "properties": {
    "iso:country":"GB",
    "wof:name":"NN3 2JN",
    "wof:placetype":"postalcode"
},
  "geometry": {"coordinates":[-0.86793925902552,52.25568184093326],"type":"Point"}
}