{
  "type": "Feature",
  "properties": {
    "iso:country":"GB",
    "wof:name":"EX9 6NR",
    "wof:placetype":"postalcode"
},
  "geometry": {"coordinates":[-3.32135839843352,50.62924388011911],"type":"Point"}
}