{
  "type": "Feature",
  "properties": {
    "date:inception_lower": "2003-11-01",
    "date:inception_upper": "2003-11-01",
    "iso:country": "GB",
    "wof:name": "KT3 4JD",
    "wof:placetype": "postalcode"
  },
  "geometry": {"coordinates":[-0.250721,51.404588],"type":"Point"}
}
