{
  "type": "Feature",
  "properties": {
    "iso:country": "GB",
    "wof:name": "KT3 4JD",
    "wof:placetype": "postalcode"
  },
  "geometry": {"coordinates":[-0.250367,51.404673],"type":"Point"}
}
