{
  "type": "Feature",
  "properties": {
    "iso:country":"GB",
    "wof:name":"KT3 4JD",
    "wof:placetype":"postalcode"
},
  "geometry": {"coordinates":[-0.25036701081857,51.40467328746045],"type":"Point"}
}