{
  "type": "Feature",
  "properties": {
    "iso:country":"GB",
    "wof:name":"SG19 3NZ",
    "wof:placetype":"postalcode"
},
  "geometry": {"coordinates":[-0.19786495204314,52.17429928252982],"type":"Point"}
}