{
  "type": "Feature",
  "properties": {
    "iso:country": "GB",
    "wof:name": "SG19 3NZ",
    "wof:placetype": "postalcode"
  },
  "geometry": {"coordinates":[-0.197865,52.174299],"type":"Point"}
}
