{
  "type": "Feature",
  "properties": {
    "iso:country": "GB",
    "wof:name": "BA7 7BG",
    "wof:placetype": "postalcode"
  },
  "geometry": {"coordinates":[-2.514174,51.088764],"type":"Point"}
}
