{
  "type": "Feature",
  "properties": {
    "date:inception_lower":"1980-01-01",
    "date:inception_upper":"1980-01-31",
    "iso:country":"GB",
    "wof:name":"BA7 7BG",
    "wof:placetype":"postalcode"
},
  "geometry": {"coordinates":[-2.514174,51.088764],"type":"Point"}
}