{
  "type": "Feature",
  "properties": {
    "iso:country":"GB",
    "wof:name":"BA7 7BG",
    "wof:placetype":"postalcode"
},
  "geometry": {"coordinates":[-2.51417408574266,51.08875498841642],"type":"Point"}
}