{
  "type": "Feature",
  "properties": {
    "iso:country":"GB",
    "wof:name":"L31 3HB",
    "wof:placetype":"postalcode"
},
  "geometry": {"coordinates":[-2.93145512949421,53.50780303977377],"type":"Point"}
}