{
  "type": "Feature",
  "properties": {
    "iso:country":"GB",
    "wof:name":"SE11 4DJ",
    "wof:placetype":"postalcode"
},
  "geometry": {"coordinates":[-0.10807569745114,51.48670547449335],"type":"Point"}
}