{
  "type": "Feature",
  "properties": {
    "iso:country":"GB",
    "wof:name":"CH60 4RD",
    "wof:placetype":"postalcode"
},
  "geometry": {"coordinates":[-3.1010682768862,53.32648159166149],"type":"Point"}
}