{
  "type": "Feature",
  "properties": {
    "iso:country": "GB",
    "wof:name": "CH60 4RD",
    "wof:placetype": "postalcode"
  },
  "geometry": {"coordinates":[-3.101067,53.326461],"type":"Point"}
}
