{
  "type": "Feature",
  "properties": {
    "date:inception_lower": "1999-06-01",
    "date:inception_upper": "1999-06-01",
    "iso:country": "GB",
    "wof:name": "CH60 4RD",
    "wof:placetype": "postalcode"
  },
  "geometry": {"coordinates":[-3.101071,53.326623],"type":"Point"}
}
