{
  "type": "Feature",
  "properties": {
    "iso:country":"GB",
    "wof:name":"LE10 0DH",
    "wof:placetype":"postalcode"
},
  "geometry": {"coordinates":[-1.37416250828775,52.5475587362421],"type":"Point"}
}