{
  "type": "Feature",
  "properties": {
    "date:inception_lower": "1980-01-01",
    "date:inception_upper": "1980-01-01",
    "iso:country": "GB",
    "wof:name": "PL14 3BW",
    "wof:placetype": "postalcode"
  },
  "geometry": {"coordinates":[-4.45972,50.455122],"type":"Point"}
}
