{
  "type": "Feature",
  "properties": {
    "iso:country":"GB",
    "wof:name":"PL14 3BW",
    "wof:placetype":"postalcode"
},
  "geometry": {"coordinates":[-4.45972033886947,50.45512193909423],"type":"Point"}
}