{
  "type": "Feature",
  "properties": {
    "iso:country": "GB",
    "wof:name": "EN11 8JJ",
    "wof:placetype": "postalcode"
  },
  "geometry": {"coordinates":[-0.009711,51.765347],"type":"Point"}
}
