{
  "type": "Feature",
  "properties": {
    "iso:country":"GB",
    "wof:name":"EN11 8JJ",
    "wof:placetype":"postalcode"
},
  "geometry": {"coordinates":[-0.00971116597511,51.76534668094315],"type":"Point"}
}