{
  "type": "Feature",
  "properties": {
    "date:inception_lower": "2024-01-01",
    "date:inception_upper": "2024-01-01",
    "iso:country": "GB",
    "wof:name": "B77 4GZ",
    "wof:placetype": "postalcode"
  },
  "geometry": {"coordinates":[-1.656978,52.625811],"type":"Point"}
}
