{
  "type": "Feature",
  "properties": {
    "iso:country":"GB",
    "wof:name":"CM9 4UP",
    "wof:placetype":"postalcode"
},
  "geometry": {"coordinates":[0.6726943818943,51.74309153797174],"type":"Point"}
}