{
  "type": "Feature",
  "properties": {
    "iso:country": "GB",
    "wof:name": "CM9 4UP",
    "wof:placetype": "postalcode"
  },
  "geometry": {"coordinates":[0.672694,51.743092],"type":"Point"}
}
