{
  "type": "Feature",
  "properties": {
    "date:inception_lower": "1981-09-01",
    "date:inception_upper": "1981-09-01",
    "iso:country": "GB",
    "wof:name": "DY5 3NU",
    "wof:placetype": "postalcode"
  },
  "geometry": {"coordinates":[-2.132882,52.466327],"type":"Point"}
}
