{
  "type": "Feature",
  "properties": {
    "iso:country":"GB",
    "wof:name":"SW9 6BE",
    "wof:placetype":"postalcode"
},
  "geometry": {"coordinates":[-0.11276913398275,51.47733889497891],"type":"Point"}
}