{
  "type": "Feature",
  "properties": {
    "date:inception_lower": "1997-12-01",
    "date:inception_upper": "1997-12-01",
    "iso:country": "GB",
    "wof:name": "BS29 6HH",
    "wof:placetype": "postalcode"
  },
  "geometry": {"coordinates":[-2.877952,51.328666],"type":"Point"}
}
