{
  "type": "Feature",
  "properties": {
    "iso:country":"GB",
    "wof:name":"BS29 6HH",
    "wof:placetype":"postalcode"
},
  "geometry": {"coordinates":[-2.87795210361439,51.3286657749651],"type":"Point"}
}