{
  "type": "Feature",
  "properties": {
    "date:inception_lower": "1980-01-01",
    "date:inception_upper": "1980-01-01",
    "iso:country": "GB",
    "wof:name": "ME19 6QR",
    "wof:placetype": "postalcode"
  },
  "geometry": {"coordinates":[0.408834,51.295153],"type":"Point"}
}
