{
  "type": "Feature",
  "properties": {
    "iso:country": "GB",
    "wof:name": "ME19 6QR",
    "wof:placetype": "postalcode"
  },
  "geometry": {"coordinates":[0.408962,51.295412],"type":"Point"}
}
