{
  "type": "Feature",
  "properties": {
    "iso:country":"GB",
    "wof:name":"KA9 2TR",
    "wof:placetype":"postalcode"
},
  "geometry": {"coordinates":[-4.58733502839289,55.49908749499901],"type":"Point"}
}