{
  "type": "Feature",
  "properties": {
    "date:inception_lower": "1996-06-01",
    "date:inception_upper": "1996-06-01",
    "iso:country": "GB",
    "wof:name": "KA9 2TR",
    "wof:placetype": "postalcode"
  },
  "geometry": {"coordinates":[-4.587335,55.499087],"type":"Point"}
}
