{
  "type": "Feature",
  "properties": {
    "iso:country":"GB",
    "wof:name":"GL19 3DZ",
    "wof:placetype":"postalcode"
},
  "geometry": {"coordinates":[-2.40227108437061,51.87168291663703],"type":"Point"}
}