{
  "type": "Feature",
  "properties": {
    "iso:country":"GB",
    "wof:name":"BS31 2SH",
    "wof:placetype":"postalcode"
},
  "geometry": {"coordinates":[-2.52766741945567,51.40164131527391],"type":"Point"}
}