{
  "type": "Feature",
  "properties": {
    "iso:country": "GB",
    "wof:name": "BS31 2SH",
    "wof:placetype": "postalcode"
  },
  "geometry": {"coordinates":[-2.527667,51.401641],"type":"Point"}
}
