{
  "type": "Feature",
  "properties": {
    "date:inception_lower":"1980-01-01",
    "date:inception_upper":"1980-01-31",
    "iso:country":"GB",
    "wof:name":"RH10 5JZ",
    "wof:placetype":"postalcode"
},
  "geometry": {"coordinates":[-0.178498,51.100646],"type":"Point"}
}