{
  "type": "Feature",
  "properties": {
    "iso:country":"GB",
    "wof:name":"KT4 8BG",
    "wof:placetype":"postalcode"
},
  "geometry": {"coordinates":[-0.23769270171839,51.38541914195942],"type":"Point"}
}