{
  "type": "Feature",
  "properties": {
    "date:inception_lower": "2004-02-01",
    "date:inception_upper": "2004-02-01",
    "iso:country": "GB",
    "wof:name": "KT4 8BG",
    "wof:placetype": "postalcode"
  },
  "geometry": {"coordinates":[-0.237811,51.385447],"type":"Point"}
}
