{
  "type": "Feature",
  "properties": {
    "iso:country":"GB",
    "wof:name":"SL3 0LP",
    "wof:placetype":"postalcode"
},
  "geometry": {"coordinates":[-0.53131710358903,51.48315704370401],"type":"Point"}
}