{
  "type": "Feature",
  "properties": {
    "date:inception_lower": "1980-01-01",
    "date:inception_upper": "1980-01-01",
    "iso:country": "GB",
    "wof:name": "LS15 7TA",
    "wof:placetype": "postalcode"
  },
  "geometry": {"coordinates":[-1.46191,53.798649],"type":"Point"}
}
