{
  "type": "Feature",
  "properties": {
    "date:inception_lower": "1980-01-01",
    "date:inception_upper": "1980-01-01",
    "iso:country": "GB",
    "wof:name": "DE15 9SP",
    "wof:placetype": "postalcode"
  },
  "geometry": {"coordinates":[-1.608899,52.783333],"type":"Point"}
}
