{
  "type": "Feature",
  "properties": {
    "iso:country":"GB",
    "wof:name":"DE15 9SP",
    "wof:placetype":"postalcode"
},
  "geometry": {"coordinates":[-1.60889917283746,52.78333314249245],"type":"Point"}
}