{
  "type": "Feature",
  "properties": {
    "date:inception_lower": "1998-06-01",
    "date:inception_upper": "1998-06-01",
    "iso:country": "GB",
    "wof:name": "YO24 2UQ",
    "wof:placetype": "postalcode"
  },
  "geometry": {"coordinates":[-1.120894,53.935979],"type":"Point"}
}
