{
  "type": "Feature",
  "properties": {
    "iso:country":"GB",
    "wof:name":"YO24 2UQ",
    "wof:placetype":"postalcode"
},
  "geometry": {"coordinates":[-1.12089430695073,53.93597871121035],"type":"Point"}
}