{
  "type": "Feature",
  "properties": {
    "iso:country":"GB",
    "wof:name":"CF34 0PF",
    "wof:placetype":"postalcode"
},
  "geometry": {"coordinates":[-3.64817444690363,51.63820903223015],"type":"Point"}
}