{
  "type": "Feature",
  "properties": {
    "iso:country": "GB",
    "wof:name": "CF34 0PF",
    "wof:placetype": "postalcode"
  },
  "geometry": {"coordinates":[-3.648174,51.638209],"type":"Point"}
}
