{
  "type": "Feature",
  "properties": {
    "date:inception_lower": "1980-01-01",
    "date:inception_upper": "1980-01-01",
    "iso:country": "GB",
    "wof:name": "BD8 8AN",
    "wof:placetype": "postalcode"
  },
  "geometry": {"coordinates":[-1.769778,53.806142],"type":"Point"}
}
