{
  "type": "Feature",
  "properties": {
    "iso:country": "GB",
    "wof:name": "BD8 8AN",
    "wof:placetype": "postalcode"
  },
  "geometry": {"coordinates":[-1.769778,53.806142],"type":"Point"}
}
