{
  "type": "Feature",
  "properties": {
    "iso:country":"GB",
    "wof:name":"BD8 8AN",
    "wof:placetype":"postalcode"
},
  "geometry": {"coordinates":[-1.76977769363257,53.80614195454844],"type":"Point"}
}