{
  "type": "Feature",
  "properties": {
    "date:inception_lower": "1992-08-01",
    "date:inception_upper": "1992-08-01",
    "iso:country": "GB",
    "wof:name": "SW11 4SH",
    "wof:placetype": "postalcode"
  },
  "geometry": {"coordinates":[-0.164287,51.475027],"type":"Point"}
}
