{
  "type": "Feature",
  "properties": {
    "iso:country":"GB",
    "wof:name":"RH4 2HT",
    "wof:placetype":"postalcode"
},
  "geometry": {"coordinates":[-0.33299067779555,51.22703333463082],"type":"Point"}
}