{
  "type": "Feature",
  "properties": {
    "iso:country":"GB",
    "wof:name":"B28 0PE",
    "wof:placetype":"postalcode"
},
  "geometry": {"coordinates":[-1.84635510533127,52.41624948644786],"type":"Point"}
}