{
  "type": "Feature",
  "properties": {
    "iso:country": "GB",
    "wof:name": "NG34 7HL",
    "wof:placetype": "postalcode"
  },
  "geometry": {"coordinates":[-0.402852,52.999111],"type":"Point"}
}
