{
  "type": "Feature",
  "properties": {
    "iso:country":"GB",
    "wof:name":"NG34 7HL",
    "wof:placetype":"postalcode"
},
  "geometry": {"coordinates":[-0.40285188249351,52.99911090649854],"type":"Point"}
}