{
  "type": "Feature",
  "properties": {
    "date:inception_lower": "1980-01-01",
    "date:inception_upper": "1980-01-01",
    "iso:country": "GB",
    "wof:name": "SY2 6HD",
    "wof:placetype": "postalcode"
  },
  "geometry": {"coordinates":[-2.732242,52.691293],"type":"Point"}
}
