{
  "type": "Feature",
  "properties": {
    "iso:country":"GB",
    "wof:name":"SY2 6HD",
    "wof:placetype":"postalcode"
},
  "geometry": {"coordinates":[-2.7322299570489,52.69128790727644],"type":"Point"}
}