{
  "type": "Feature",
  "properties": {
    "iso:country":"GB",
    "wof:name":"HG1 4ST",
    "wof:placetype":"postalcode"
},
  "geometry": {"coordinates":[-1.52045153033478,53.99555273574729],"type":"Point"}
}