{
  "type": "Feature",
  "properties": {
    "iso:country": "GB",
    "wof:name": "SA33 6LG",
    "wof:placetype": "postalcode"
  },
  "geometry": {"coordinates":[-4.326977,51.960131],"type":"Point"}
}
