{
  "type": "Feature",
  "properties": {
    "iso:country":"GB",
    "wof:name":"SA33 6LG",
    "wof:placetype":"postalcode"
},
  "geometry": {"coordinates":[-4.33124900851278,51.96628492145982],"type":"Point"}
}