{
  "type": "Feature",
  "properties": {
    "iso:country": "GB",
    "wof:name": "B67 6DA",
    "wof:placetype": "postalcode"
  },
  "geometry": {"coordinates":[-1.975068,52.487736],"type":"Point"}
}
