{
  "type": "Feature",
  "properties": {
    "iso:country":"GB",
    "wof:name":"B67 6DA",
    "wof:placetype":"postalcode"
},
  "geometry": {"coordinates":[-1.97506816018078,52.4877359876978],"type":"Point"}
}