{
  "type": "Feature",
  "properties": {
    "iso:country": "GB",
    "wof:name": "RG20 9US",
    "wof:placetype": "postalcode"
  },
  "geometry": {"coordinates":[-1.391111,51.350932],"type":"Point"}
}
