{
  "type": "Feature",
  "properties": {
    "iso:country":"GB",
    "wof:name":"RG20 9US",
    "wof:placetype":"postalcode"
},
  "geometry": {"coordinates":[-1.39111140225351,51.35093214772587],"type":"Point"}
}