{
  "type": "Feature",
  "properties": {
    "iso:country":"GB",
    "wof:name":"CT14 7NQ",
    "wof:placetype":"postalcode"
},
  "geometry": {"coordinates":[1.39472658812567,51.20249125626114],"type":"Point"}
}