{
  "type": "Feature",
  "properties": {
    "iso:country": "GB",
    "wof:name": "CT14 7NQ",
    "wof:placetype": "postalcode"
  },
  "geometry": {"coordinates":[1.394727,51.202491],"type":"Point"}
}
