{
  "type": "Feature",
  "properties": {
    "iso:country":"GB",
    "wof:name":"M13 0LW",
    "wof:placetype":"postalcode"
},
  "geometry": {"coordinates":[-2.20732306565306,53.46053172825254],"type":"Point"}
}