{
  "type": "Feature",
  "properties": {
    "iso:country":"GB",
    "wof:name":"SO53 2JW",
    "wof:placetype":"postalcode"
},
  "geometry": {"coordinates":[-1.37287089644353,50.98300541562433],"type":"Point"}
}