{
  "type": "Feature",
  "properties": {
    "iso:country":"GB",
    "wof:name":"YO23 7AL",
    "wof:placetype":"postalcode"
},
  "geometry": {"coordinates":[-1.19266708090077,53.86580022172781],"type":"Point"}
}