{
  "type": "Feature",
  "properties": {
    "iso:country":"GB",
    "wof:name":"YO7 4LE",
    "wof:placetype":"postalcode"
},
  "geometry": {"coordinates":[-1.47547782081394,54.21546255627048],"type":"Point"}
}