{
  "type": "Feature",
  "properties": {
    "date:inception_lower": "1993-01-01",
    "date:inception_upper": "1993-01-01",
    "iso:country": "GB",
    "wof:name": "YO7 4LE",
    "wof:placetype": "postalcode"
  },
  "geometry": {"coordinates":[-1.475486,54.215475],"type":"Point"}
}
