{
  "type": "Feature",
  "properties": {
    "iso:country": "GB",
    "wof:name": "YO7 4LE",
    "wof:placetype": "postalcode"
  },
  "geometry": {"coordinates":[-1.476024,54.215307],"type":"Point"}
}
