{
  "type": "Feature",
  "properties": {
    "iso:country":"GB",
    "wof:name":"PE14 7BL",
    "wof:placetype":"postalcode"
},
  "geometry": {"coordinates":[0.18639044940643,52.662527129546],"type":"Point"}
}