{
  "type": "Feature",
  "properties": {
    "date:inception_lower":"1980-01-01",
    "date:inception_upper":"1980-01-31",
    "iso:country":"GB",
    "wof:name":"PE14 7BL",
    "wof:placetype":"postalcode"
},
  "geometry": {"coordinates":[0.18639,52.662527],"type":"Point"}
}