{
  "type": "Feature",
  "properties": {
    "iso:country":"GB",
    "wof:name":"SO45 5SW",
    "wof:placetype":"postalcode"
},
  "geometry": {"coordinates":[-1.42518048064754,50.85830629164945],"type":"Point"}
}