{
  "type": "Feature",
  "properties": {
    "date:inception_lower":"1994-12-01",
    "date:inception_upper":"1994-12-31",
    "iso:country":"GB",
    "wof:name":"SO45 5SW",
    "wof:placetype":"postalcode"
},
  "geometry": {"coordinates":[-1.42518,50.858306],"type":"Point"}
}