{
  "type": "Feature",
  "properties": {
    "date:inception_lower":"1980-01-01",
    "date:inception_upper":"1980-01-31",
    "iso:country":"GB",
    "wof:name":"SP6 3QY",
    "wof:placetype":"postalcode"
},
  "geometry": {"coordinates":[-1.802287,50.975359],"type":"Point"}
}