{
  "type": "Feature",
  "properties": {
    "iso:country":"GB",
    "wof:name":"SP6 3QY",
    "wof:placetype":"postalcode"
},
  "geometry": {"coordinates":[-1.80205235295916,50.97563562920872],"type":"Point"}
}