{
  "type": "Feature",
  "properties": {
    "iso:country":"GB",
    "wof:name":"SW15 1QJ",
    "wof:placetype":"postalcode"
},
  "geometry": {"coordinates":[-0.22369743568961,51.46547518993673],"type":"Point"}
}