{
  "type": "Feature",
  "properties": {
    "iso:country": "GB",
    "wof:name": "SK11 8HS",
    "wof:placetype": "postalcode"
  },
  "geometry": {"coordinates":[-2.137283,53.258936],"type":"Point"}
}
