{
  "type": "Feature",
  "properties": {
    "iso:country":"GB",
    "wof:name":"TN18 5JP",
    "wof:placetype":"postalcode"
},
  "geometry": {"coordinates":[0.56709283742457,51.02557857433158],"type":"Point"}
}