{
  "type": "Feature",
  "properties": {
    "iso:country":"GB",
    "wof:name":"CV2 1UJ",
    "wof:placetype":"postalcode"
},
  "geometry": {"coordinates":[-1.46637449842677,52.43923961745689],"type":"Point"}
}