{
  "type": "Feature",
  "properties": {
    "date:inception_lower":"2014-01-01",
    "date:inception_upper":"2014-01-31",
    "iso:country":"GB",
    "wof:name":"CV2 1UJ",
    "wof:placetype":"postalcode"
},
  "geometry": {"coordinates":[-1.466365,52.439392],"type":"Point"}
}