{
  "type": "Feature",
  "properties": {
    "iso:country": "GB",
    "wof:name": "CV2 1UJ",
    "wof:placetype": "postalcode"
  },
  "geometry": {"coordinates":[-1.466365,52.439392],"type":"Point"}
}
