{
  "type": "Feature",
  "properties": {
    "iso:country": "GB",
    "wof:name": "E2 7LA",
    "wof:placetype": "postalcode"
  },
  "geometry": {"coordinates":[-0.073901,51.52622],"type":"Point"}
}
