{
  "type": "Feature",
  "properties": {
    "iso:country":"GB",
    "wof:name":"E2 7LA",
    "wof:placetype":"postalcode"
},
  "geometry": {"coordinates":[-0.07390075839184,51.5262200999323],"type":"Point"}
}