{
  "type": "Feature",
  "properties": {
    "iso:country":"GB",
    "wof:name":"LD2 3JZ",
    "wof:placetype":"postalcode"
},
  "geometry": {"coordinates":[-3.21539713171811,52.10788251647363],"type":"Point"}
}