{
  "type": "Feature",
  "properties": {
    "iso:country":"GB",
    "wof:name":"B37 7TH",
    "wof:placetype":"postalcode"
},
  "geometry": {"coordinates":[-1.72583008750524,52.47643577423737],"type":"Point"}
}