{
  "type": "Feature",
  "properties": {
    "date:inception_lower": "1980-01-01",
    "date:inception_upper": "1980-01-01",
    "iso:country": "GB",
    "wof:name": "NE26 3QW",
    "wof:placetype": "postalcode"
  },
  "geometry": {"coordinates":[-1.450975,55.043806],"type":"Point"}
}
