{
  "type": "Feature",
  "properties": {
    "iso:country": "GB",
    "wof:name": "NE26 3QW",
    "wof:placetype": "postalcode"
  },
  "geometry": {"coordinates":[-1.450975,55.043806],"type":"Point"}
}
