{
  "type": "Feature",
  "properties": {
    "iso:country":"GB",
    "wof:name":"B63 2SJ",
    "wof:placetype":"postalcode"
},
  "geometry": {"coordinates":[-2.07841759616689,52.46161452125129],"type":"Point"}
}