{
  "type": "Feature",
  "properties": {
    "date:inception_lower":"1980-01-01",
    "date:inception_upper":"1980-01-31",
    "iso:country":"GB",
    "wof:name":"NE15 8QW",
    "wof:placetype":"postalcode"
},
  "geometry": {"coordinates":[-1.729805,54.982604],"type":"Point"}
}