{
  "type": "Feature",
  "properties": {
    "iso:country":"GB",
    "wof:name":"NE15 8QW",
    "wof:placetype":"postalcode"
},
  "geometry": {"coordinates":[-1.72980503747552,54.98260372482085],"type":"Point"}
}