{
  "type": "Feature",
  "properties": {
    "iso:country":"GB",
    "wof:name":"TR11 5SR",
    "wof:placetype":"postalcode"
},
  "geometry": {"coordinates":[-5.05572461859901,50.18654430825897],"type":"Point"}
}