{
  "type": "Feature",
  "properties": {
    "iso:country":"GB",
    "wof:name":"SA3 4AJ",
    "wof:placetype":"postalcode"
},
  "geometry": {"coordinates":[-4.00333728197788,51.57361237305855],"type":"Point"}
}