{
  "type": "Feature",
  "properties": {
    "iso:country":"GB",
    "wof:name":"GL7 2EY",
    "wof:placetype":"postalcode"
},
  "geometry": {"coordinates":[-1.97020234077944,51.7231620135739],"type":"Point"}
}