{
  "type": "Feature",
  "properties": {
    "iso:country": "GB",
    "wof:name": "BN20 8PN",
    "wof:placetype": "postalcode"
  },
  "geometry": {"coordinates":[0.252715,50.779797],"type":"Point"}
}
