{
  "type": "Feature",
  "properties": {
    "iso:country":"GB",
    "wof:name":"ST8 7HE",
    "wof:placetype":"postalcode"
},
  "geometry": {"coordinates":[-2.16767159003409,53.1212244055716],"type":"Point"}
}