{
  "type": "Feature",
  "properties": {
    "iso:country": "GB",
    "wof:name": "ST8 7HE",
    "wof:placetype": "postalcode"
  },
  "geometry": {"coordinates":[-2.167672,53.121224],"type":"Point"}
}
