{
  "type": "Feature",
  "properties": {
    "iso:country":"GB",
    "wof:name":"CO8 5JQ",
    "wof:placetype":"postalcode"
},
  "geometry": {"coordinates":[0.77612481858859,51.9729114009406],"type":"Point"}
}