{
  "type": "Feature",
  "properties": {
    "date:inception_lower":"1981-06-01",
    "date:inception_upper":"1981-06-30",
    "iso:country":"GB",
    "wof:name":"S63 6HR",
    "wof:placetype":"postalcode"
},
  "geometry": {"coordinates":[-1.342961,53.4907],"type":"Point"}
}