{
  "type": "Feature",
  "properties": {
    "iso:country": "GB",
    "wof:name": "S63 6HR",
    "wof:placetype": "postalcode"
  },
  "geometry": {"coordinates":[-1.342961,53.4907],"type":"Point"}
}
