{
  "type": "Feature",
  "properties": {
    "iso:country":"GB",
    "wof:name":"NP4 8DJ",
    "wof:placetype":"postalcode"
},
  "geometry": {"coordinates":[-3.03718251210748,51.71367676209412],"type":"Point"}
}