{
  "type": "Feature",
  "properties": {
    "iso:country":"GB",
    "wof:name":"SE8 3EZ",
    "wof:placetype":"postalcode"
},
  "geometry": {"coordinates":[-0.02526815569366,51.48170711955106],"type":"Point"}
}