{
  "type": "Feature",
  "properties": {
    "date:inception_lower":"1982-03-01",
    "date:inception_upper":"1982-03-31",
    "iso:country":"GB",
    "wof:name":"SE8 3EZ",
    "wof:placetype":"postalcode"
},
  "geometry": {"coordinates":[-0.025268,51.481707],"type":"Point"}
}