{
  "type": "Feature",
  "properties": {
    "iso:country": "GB",
    "wof:name": "CA10 3EG",
    "wof:placetype": "postalcode"
  },
  "geometry": {"coordinates":[-2.677097,54.569957],"type":"Point"}
}
