{
  "type": "Feature",
  "properties": {
    "iso:country":"GB",
    "wof:name":"NE48 1NG",
    "wof:placetype":"postalcode"
},
  "geometry": {"coordinates":[-2.33439861659778,55.19419076871345],"type":"Point"}
}