{
  "type": "Feature",
  "properties": {
    "iso:country":"GB",
    "wof:name":"NE46 1HY",
    "wof:placetype":"postalcode"
},
  "geometry": {"coordinates":[-2.08476872186279,54.96767783825939],"type":"Point"}
}