{
  "type": "Feature",
  "properties": {
    "iso:country":"GB",
    "wof:name":"TS2 1QG",
    "wof:placetype":"postalcode"
},
  "geometry": {"coordinates":[-1.22131714216781,54.57759003082846],"type":"Point"}
}