{
  "type": "Feature",
  "properties": {
    "iso:country": "GB",
    "wof:name": "TN24 0YA",
    "wof:placetype": "postalcode"
  },
  "geometry": {"coordinates":[0.892232,51.138541],"type":"Point"}
}
