{
  "type": "Feature",
  "properties": {
    "iso:country":"GB",
    "wof:name":"UB8 3NH",
    "wof:placetype":"postalcode"
},
  "geometry": {"coordinates":[-0.45803553737884,51.52554978328852],"type":"Point"}
}