{
  "type": "Feature",
  "properties": {
    "iso:country": "GB",
    "wof:name": "PE28 3LZ",
    "wof:placetype": "postalcode"
  },
  "geometry": {"coordinates":[0.016932,52.363837],"type":"Point"}
}
