{
  "type": "Feature",
  "properties": {
    "date:inception_lower": "1986-07-01",
    "date:inception_upper": "1986-07-01",
    "iso:country": "GB",
    "wof:name": "TR3 6QP",
    "wof:placetype": "postalcode"
  },
  "geometry": {"coordinates":[-5.059024,50.221827],"type":"Point"}
}
