{
  "type": "Feature",
  "properties": {
    "iso:country": "GB",
    "wof:name": "TR3 6QP",
    "wof:placetype": "postalcode"
  },
  "geometry": {"coordinates":[-5.057998,50.221442],"type":"Point"}
}
