{
  "type": "Feature",
  "properties": {
    "date:inception_lower":"1986-07-01",
    "date:inception_upper":"1986-07-31",
    "iso:country":"GB",
    "wof:name":"TR3 6QP",
    "wof:placetype":"postalcode"
},
  "geometry": {"coordinates":[-5.057998,50.221442],"type":"Point"}
}