{
  "type": "Feature",
  "properties": {
    "date:inception_lower": "1980-01-01",
    "date:inception_upper": "1980-01-01",
    "iso:country": "GB",
    "wof:name": "TN17 3DP",
    "wof:placetype": "postalcode"
  },
  "geometry": {"coordinates":[0.532946,51.095812],"type":"Point"}
}
