{
  "type": "Feature",
  "properties": {
    "iso:country":"GB",
    "wof:name":"TN17 3DP",
    "wof:placetype":"postalcode"
},
  "geometry": {"coordinates":[0.53294582894969,51.0958116003257],"type":"Point"}
}