{
  "type": "Feature",
  "properties": {
    "iso:country":"GB",
    "wof:name":"B92 0HB",
    "wof:placetype":"postalcode"
},
  "geometry": {"coordinates":[-1.70442960788164,52.43363671739176],"type":"Point"}
}