{
  "type": "Feature",
  "properties": {
    "iso:country": "GB",
    "wof:name": "B92 0HB",
    "wof:placetype": "postalcode"
  },
  "geometry": {"coordinates":[-1.70443,52.433637],"type":"Point"}
}
