{
  "type": "Feature",
  "properties": {
    "date:inception_lower": "1990-02-01",
    "date:inception_upper": "1990-02-01",
    "iso:country": "GB",
    "wof:name": "B92 0HB",
    "wof:placetype": "postalcode"
  },
  "geometry": {"coordinates":[-1.70443,52.433637],"type":"Point"}
}
