{
  "type": "Feature",
  "properties": {
    "date:inception_lower": "1996-06-01",
    "date:inception_upper": "1996-06-01",
    "iso:country": "GB",
    "wof:name": "AB42 1DU",
    "wof:placetype": "postalcode"
  },
  "geometry": {"coordinates":[-1.777546,57.503674],"type":"Point"}
}
