{
  "type": "Feature",
  "properties": {
    "iso:country": "GB",
    "wof:name": "AB42 1DU",
    "wof:placetype": "postalcode"
  },
  "geometry": {"coordinates":[-1.777546,57.503674],"type":"Point"}
}
