{
  "type": "Feature",
  "properties": {
    "iso:country":"GB",
    "wof:name":"AB42 1DU",
    "wof:placetype":"postalcode"
},
  "geometry": {"coordinates":[-1.77754626235006,57.50367366210521],"type":"Point"}
}