{
  "type": "Feature",
  "properties": {
    "iso:country":"GB",
    "wof:name":"CM9 6SL",
    "wof:placetype":"postalcode"
},
  "geometry": {"coordinates":[0.64470593732019,51.70787757618543],"type":"Point"}
}