{
  "type": "Feature",
  "properties": {
    "date:inception_lower": "1980-01-01",
    "date:inception_upper": "1980-01-01",
    "iso:country": "GB",
    "wof:name": "LL29 9TD",
    "wof:placetype": "postalcode"
  },
  "geometry": {"coordinates":[-3.704004,53.291838],"type":"Point"}
}
