{
  "type": "Feature",
  "properties": {
    "iso:country":"GB",
    "wof:name":"DD3 7AS",
    "wof:placetype":"postalcode"
},
  "geometry": {"coordinates":[-2.97545207416104,56.46963145659536],"type":"Point"}
}