{
  "type": "Feature",
  "properties": {
    "date:inception_lower":"2004-01-01",
    "date:inception_upper":"2004-01-31",
    "iso:country":"GB",
    "wof:name":"TR27 4HD",
    "wof:placetype":"postalcode"
},
  "geometry": {"coordinates":[-5.422888,50.18343],"type":"Point"}
}