{
  "type": "Feature",
  "properties": {
    "iso:country":"GB",
    "wof:name":"TR27 4HD",
    "wof:placetype":"postalcode"
},
  "geometry": {"coordinates":[-5.42266714675263,50.18341724374605],"type":"Point"}
}