{
  "type": "Feature",
  "properties": {
    "iso:country": "GB",
    "wof:name": "TN29 9EQ",
    "wof:placetype": "postalcode"
  },
  "geometry": {"coordinates":[0.909663,50.952272],"type":"Point"}
}
