{
  "type": "Feature",
  "properties": {
    "date:inception_lower": "1980-01-01",
    "date:inception_upper": "1980-01-01",
    "iso:country": "GB",
    "wof:name": "CA7 8JG",
    "wof:placetype": "postalcode"
  },
  "geometry": {"coordinates":[-3.024833,54.738222],"type":"Point"}
}
