{
  "type": "Feature",
  "properties": {
    "iso:country":"GB",
    "wof:name":"CF44 8HW",
    "wof:placetype":"postalcode"
},
  "geometry": {"coordinates":[-3.46235574215786,51.72150777634738],"type":"Point"}
}