{
  "type": "Feature",
  "properties": {
    "iso:country": "GB",
    "wof:name": "SR5 3JL",
    "wof:placetype": "postalcode"
  },
  "geometry": {"coordinates":[-1.458708,54.912352],"type":"Point"}
}
