{
  "type": "Feature",
  "properties": {
    "iso:country":"GB",
    "wof:name":"SN7 8BY",
    "wof:placetype":"postalcode"
},
  "geometry": {"coordinates":[-1.66669022944345,51.67613741024164],"type":"Point"}
}