{
  "type": "Feature",
  "properties": {
    "iso:country": "GB",
    "wof:name": "SN7 8BY",
    "wof:placetype": "postalcode"
  },
  "geometry": {"coordinates":[-1.66669,51.676137],"type":"Point"}
}
