{
  "type": "Feature",
  "properties": {
    "iso:country": "GB",
    "wof:name": "LE9 8JQ",
    "wof:placetype": "postalcode"
  },
  "geometry": {"coordinates":[-1.359572,52.584439],"type":"Point"}
}
