{
  "type": "Feature",
  "properties": {
    "iso:country":"GB",
    "wof:name":"LE9 8JQ",
    "wof:placetype":"postalcode"
},
  "geometry": {"coordinates":[-1.35957194154506,52.58443851498566],"type":"Point"}
}