{
  "type": "Feature",
  "properties": {
    "iso:country":"GB",
    "wof:name":"PR7 3AX",
    "wof:placetype":"postalcode"
},
  "geometry": {"coordinates":[-2.62084175391164,53.64481779661282],"type":"Point"}
}