{
  "type": "Feature",
  "properties": {
    "iso:country":"GB",
    "wof:name":"HA4 6HL",
    "wof:placetype":"postalcode"
},
  "geometry": {"coordinates":[-0.42349788954213,51.56597810246483],"type":"Point"}
}