{
  "type": "Feature",
  "properties": {
    "date:inception_lower":"1981-06-01",
    "date:inception_upper":"1981-06-30",
    "iso:country":"GB",
    "wof:name":"BH24 2NE",
    "wof:placetype":"postalcode"
},
  "geometry": {"coordinates":[-1.823786,50.836459],"type":"Point"}
}