{
  "type": "Feature",
  "properties": {
    "iso:country":"GB",
    "wof:name":"S45 8DP",
    "wof:placetype":"postalcode"
},
  "geometry": {"coordinates":[-1.37635781232542,53.16751493777423],"type":"Point"}
}