{
  "type": "Feature",
  "properties": {
    "date:inception_lower": "1980-01-01",
    "date:inception_upper": "1980-01-01",
    "iso:country": "GB",
    "wof:name": "S45 8DP",
    "wof:placetype": "postalcode"
  },
  "geometry": {"coordinates":[-1.376358,53.167515],"type":"Point"}
}
