{
  "type": "Feature",
  "properties": {
    "date:inception_lower": "1980-01-01",
    "date:inception_upper": "1980-01-01",
    "iso:country": "GB",
    "wof:name": "HG3 5QG",
    "wof:placetype": "postalcode"
  },
  "geometry": {"coordinates":[-1.740119,54.073989],"type":"Point"}
}
