{
  "type": "Feature",
  "properties": {
    "date:inception_lower":"2012-02-01",
    "date:inception_upper":"2012-02-29",
    "iso:country":"GB",
    "wof:name":"PE22 9GB",
    "wof:placetype":"postalcode"
},
  "geometry": {"coordinates":[0.094698,53.03286],"type":"Point"}
}