{
  "type": "Feature",
  "properties": {
    "iso:country":"GB",
    "wof:name":"PE22 9GB",
    "wof:placetype":"postalcode"
},
  "geometry": {"coordinates":[0.09469829998234,53.03286029210002],"type":"Point"}
}