{
  "type": "Feature",
  "properties": {
    "iso:country":"GB",
    "wof:name":"B20 1EL",
    "wof:placetype":"postalcode"
},
  "geometry": {"coordinates":[-1.93748384317032,52.530738924072],"type":"Point"}
}