{
  "type": "Feature",
  "properties": {
    "iso:country":"GB",
    "wof:name":"NG14 6LB",
    "wof:placetype":"postalcode"
},
  "geometry": {"coordinates":[-1.08844313618484,53.04192217423223],"type":"Point"}
}