{
  "type": "Feature",
  "properties": {
    "iso:country": "GB",
    "wof:name": "G32 7HW",
    "wof:placetype": "postalcode"
  },
  "geometry": {"coordinates":[-4.175131,55.853332],"type":"Point"}
}
