{
  "type": "Feature",
  "properties": {
    "iso:country":"GB",
    "wof:name":"E20 1DG",
    "wof:placetype":"postalcode"
},
  "geometry": {"coordinates":[-0.01031952370797,51.54684003283253],"type":"Point"}
}