{
  "type": "Feature",
  "properties": {
    "iso:country":"GB",
    "wof:name":"BS16 3XG",
    "wof:placetype":"postalcode"
},
  "geometry": {"coordinates":[-2.52190631982259,51.47890530167838],"type":"Point"}
}