{
  "type": "Feature",
  "properties": {
    "iso:country":"GB",
    "wof:name":"IG1 2SR",
    "wof:placetype":"postalcode"
},
  "geometry": {"coordinates":[0.08310672091038,51.54702578316505],"type":"Point"}
}