{
  "type": "Feature",
  "properties": {
    "iso:country":"GB",
    "wof:name":"EH10 5HN",
    "wof:placetype":"postalcode"
},
  "geometry": {"coordinates":[-3.21022430940914,55.92698187149558],"type":"Point"}
}