{
  "type": "Feature",
  "properties": {
    "iso:country":"GB",
    "wof:name":"B29 5LY",
    "wof:placetype":"postalcode"
},
  "geometry": {"coordinates":[-1.97445119292034,52.43364310212713],"type":"Point"}
}