{
  "type": "Feature",
  "properties": {
    "date:inception_lower":"1999-06-01",
    "date:inception_upper":"1999-06-30",
    "iso:country":"GB",
    "wof:name":"CH47 5AE",
    "wof:placetype":"postalcode"
},
  "geometry": {"coordinates":[-3.173148,53.396827],"type":"Point"}
}