{
  "type": "Feature",
  "properties": {
    "iso:country": "GB",
    "wof:name": "MK41 8JU",
    "wof:placetype": "postalcode"
  },
  "geometry": {"coordinates":[-0.440501,52.155467],"type":"Point"}
}
