{
  "type": "Feature",
  "properties": {
    "iso:country":"GB",
    "wof:name":"NN14 2RW",
    "wof:placetype":"postalcode"
},
  "geometry": {"coordinates":[-0.81220791567831,52.44361428532365],"type":"Point"}
}