{
  "type": "Feature",
  "properties": {
    "iso:country":"GB",
    "wof:name":"UB10 0HQ",
    "wof:placetype":"postalcode"
},
  "geometry": {"coordinates":[-0.45543873372629,51.53753812819748],"type":"Point"}
}