{
  "type": "Feature",
  "properties": {
    "iso:country": "GB",
    "wof:name": "UB10 0HQ",
    "wof:placetype": "postalcode"
  },
  "geometry": {"coordinates":[-0.455439,51.537538],"type":"Point"}
}
