{
  "type": "Feature",
  "properties": {
    "date:inception_lower": "1981-06-01",
    "date:inception_upper": "1981-06-01",
    "iso:country": "GB",
    "wof:name": "OL9 9TB",
    "wof:placetype": "postalcode"
  },
  "geometry": {"coordinates":[-2.164881,53.546033],"type":"Point"}
}
