{
  "type": "Feature",
  "properties": {
    "iso:country": "GB",
    "wof:name": "RG31 7ZH",
    "wof:placetype": "postalcode"
  },
  "geometry": {"coordinates":[-1.02745,51.43784],"type":"Point"}
}
