{
  "type": "Feature",
  "properties": {
    "iso:country":"GB",
    "wof:name":"SA19 7EU",
    "wof:placetype":"postalcode"
},
  "geometry": {"coordinates":[-4.02563049674695,51.93154904674514],"type":"Point"}
}