{
  "type": "Feature",
  "properties": {
    "iso:country":"GB",
    "wof:name":"SN8 1PH",
    "wof:placetype":"postalcode"
},
  "geometry": {"coordinates":[-1.72610355471458,51.42074590844151],"type":"Point"}
}