{
  "type": "Feature",
  "properties": {
    "iso:country": "GB",
    "wof:name": "BA11 4HT",
    "wof:placetype": "postalcode"
  },
  "geometry": {"coordinates":[-2.337274,51.226726],"type":"Point"}
}
