{
  "type": "Feature",
  "properties": {
    "iso:country": "GB",
    "wof:name": "NE3 2JP",
    "wof:placetype": "postalcode"
  },
  "geometry": {"coordinates":[-1.623308,55.020332],"type":"Point"}
}
