{
  "type": "Feature",
  "properties": {
    "iso:country":"GB",
    "wof:name":"NE3 2JP",
    "wof:placetype":"postalcode"
},
  "geometry": {"coordinates":[-1.62330761410318,55.02033249614894],"type":"Point"}
}