{
  "type": "Feature",
  "properties": {
    "date:inception_lower":"1991-01-01",
    "date:inception_upper":"1991-01-31",
    "iso:country":"GB",
    "wof:name":"NE3 2JP",
    "wof:placetype":"postalcode"
},
  "geometry": {"coordinates":[-1.623308,55.020332],"type":"Point"}
}