{
  "type": "Feature",
  "properties": {
    "iso:country": "GB",
    "wof:name": "SG5 4PU",
    "wof:placetype": "postalcode"
  },
  "geometry": {"coordinates":[-0.218813,52.013623],"type":"Point"}
}
