{
  "type": "Feature",
  "properties": {
    "iso:country": "GB",
    "wof:name": "NR14 6DZ",
    "wof:placetype": "postalcode"
  },
  "geometry": {"coordinates":[1.470501,52.508411],"type":"Point"}
}
