{
  "type": "Feature",
  "properties": {
    "date:inception_lower": "1980-01-01",
    "date:inception_upper": "1980-01-01",
    "iso:country": "GB",
    "wof:name": "NR14 6DZ",
    "wof:placetype": "postalcode"
  },
  "geometry": {"coordinates":[1.470501,52.508411],"type":"Point"}
}
