{
  "type": "Feature",
  "properties": {
    "date:inception_lower": "2019-09-01",
    "date:inception_upper": "2019-09-01",
    "iso:country": "GB",
    "wof:name": "HR2 0BT",
    "wof:placetype": "postalcode"
  },
  "geometry": {"coordinates":[-2.952301,52.039156],"type":"Point"}
}
