{
  "type": "Feature",
  "properties": {
    "iso:country":"GB",
    "wof:name":"KY14 6AF",
    "wof:placetype":"postalcode"
},
  "geometry": {"coordinates":[-3.2360434786438,56.3477751096397],"type":"Point"}
}