{
  "type": "Feature",
  "properties": {
    "date:inception_lower":"1985-10-01",
    "date:inception_upper":"1985-10-31",
    "iso:country":"GB",
    "wof:name":"NE20 9EQ",
    "wof:placetype":"postalcode"
},
  "geometry": {"coordinates":[-1.736879,55.050231],"type":"Point"}
}