{
  "type": "Feature",
  "properties": {
    "iso:country":"GB",
    "wof:name":"AL2 3NB",
    "wof:placetype":"postalcode"
},
  "geometry": {"coordinates":[-0.36241963116999,51.70529247414795],"type":"Point"}
}