{
  "type": "Feature",
  "properties": {
    "iso:country":"GB",
    "wof:name":"LS23 6FL",
    "wof:placetype":"postalcode"
},
  "geometry": {"coordinates":[-1.35096212627647,53.90749387963762],"type":"Point"}
}