{
  "type": "Feature",
  "properties": {
    "date:inception_lower": "2013-03-01",
    "date:inception_upper": "2013-03-01",
    "iso:country": "GB",
    "wof:name": "LS23 6FL",
    "wof:placetype": "postalcode"
  },
  "geometry": {"coordinates":[-1.350962,53.907494],"type":"Point"}
}
