{
  "type": "Feature",
  "properties": {
    "date:inception_lower": "1998-12-01",
    "date:inception_upper": "1998-12-01",
    "iso:country": "GB",
    "wof:name": "L25 2NJ",
    "wof:placetype": "postalcode"
  },
  "geometry": {"coordinates":[-2.859537,53.393304],"type":"Point"}
}
