{
  "type": "Feature",
  "properties": {
    "date:inception_lower": "1980-01-01",
    "date:inception_upper": "1980-01-01",
    "iso:country": "GB",
    "wof:name": "B94 5LP",
    "wof:placetype": "postalcode"
  },
  "geometry": {"coordinates":[-1.846591,52.373502],"type":"Point"}
}
