{
  "type": "Feature",
  "properties": {
    "iso:country": "GB",
    "wof:name": "B94 5LP",
    "wof:placetype": "postalcode"
  },
  "geometry": {"coordinates":[-1.846591,52.373502],"type":"Point"}
}
