{
  "type": "Feature",
  "properties": {
    "iso:country":"GB",
    "wof:name":"B94 5LP",
    "wof:placetype":"postalcode"
},
  "geometry": {"coordinates":[-1.84659136307912,52.37350188498525],"type":"Point"}
}