{
  "type": "Feature",
  "properties": {
    "iso:country":"GB",
    "wof:name":"CM23 3UB",
    "wof:placetype":"postalcode"
},
  "geometry": {"coordinates":[0.15801778778552,51.86717575981993],"type":"Point"}
}