{
  "type": "Feature",
  "properties": {
    "iso:country": "GB",
    "wof:name": "LE11 1RD",
    "wof:placetype": "postalcode"
  },
  "geometry": {"coordinates":[-1.197559,52.765742],"type":"Point"}
}
