{
  "type": "Feature",
  "properties": {
    "iso:country":"GB",
    "wof:name":"LE11 1RD",
    "wof:placetype":"postalcode"
},
  "geometry": {"coordinates":[-1.19760913696355,52.76575830146123],"type":"Point"}
}