{
  "type": "Feature",
  "properties": {
    "iso:country":"GB",
    "wof:name":"CT15 4FB",
    "wof:placetype":"postalcode"
},
  "geometry": {"coordinates":[1.24072803149346,51.22809897252084],"type":"Point"}
}