{
  "type": "Feature",
  "properties": {
    "date:inception_lower":"2014-10-01",
    "date:inception_upper":"2014-10-31",
    "iso:country":"GB",
    "wof:name":"CT15 4FB",
    "wof:placetype":"postalcode"
},
  "geometry": {"coordinates":[1.240728,51.228099],"type":"Point"}
}