{
  "type": "Feature",
  "properties": {
    "iso:country":"GB",
    "wof:name":"DY4 0HP",
    "wof:placetype":"postalcode"
},
  "geometry": {"coordinates":[-2.03836067468988,52.53500120364266],"type":"Point"}
}