{
  "type": "Feature",
  "properties": {
    "iso:country":"GB",
    "wof:name":"SY20 8JZ",
    "wof:placetype":"postalcode"
},
  "geometry": {"coordinates":[-3.74454354720806,52.62441765750236],"type":"Point"}
}