{
  "type": "Feature",
  "properties": {
    "iso:country":"GB",
    "wof:name":"BL9 8HA",
    "wof:placetype":"postalcode"
},
  "geometry": {"coordinates":[-2.2913353045194,53.56172767528079],"type":"Point"}
}