{
  "type": "Feature",
  "properties": {
    "iso:country": "GB",
    "wof:name": "BL9 8HA",
    "wof:placetype": "postalcode"
  },
  "geometry": {"coordinates":[-2.291335,53.561728],"type":"Point"}
}
