{
  "type": "Feature",
  "properties": {
    "iso:country":"GB",
    "wof:name":"CO6 2TT",
    "wof:placetype":"postalcode"
},
  "geometry": {"coordinates":[0.69483700988943,51.92742478331587],"type":"Point"}
}