{
  "type": "Feature",
  "properties": {
    "date:inception_lower": "2003-11-01",
    "date:inception_upper": "2003-11-01",
    "iso:country": "GB",
    "wof:name": "CO6 2TT",
    "wof:placetype": "postalcode"
  },
  "geometry": {"coordinates":[0.694837,51.927425],"type":"Point"}
}
