{
  "type": "Feature",
  "properties": {
    "iso:country": "GB",
    "wof:name": "CO9 4DD",
    "wof:placetype": "postalcode"
  },
  "geometry": {"coordinates":[0.501189,52.053472],"type":"Point"}
}
