{
  "type": "Feature",
  "properties": {
    "iso:country":"GB",
    "wof:name":"CO9 4DD",
    "wof:placetype":"postalcode"
},
  "geometry": {"coordinates":[0.50118904797284,52.05347185543206],"type":"Point"}
}