{
  "type": "Feature",
  "properties": {
    "iso:country":"GB",
    "wof:name":"WR10 2BX",
    "wof:placetype":"postalcode"
},
  "geometry": {"coordinates":[-2.07347135242818,52.12547243771697],"type":"Point"}
}