{
  "type": "Feature",
  "properties": {
    "iso:country":"GB",
    "wof:name":"TQ9 7PH",
    "wof:placetype":"postalcode"
},
  "geometry": {"coordinates":[-3.79022302603143,50.39778444336218],"type":"Point"}
}