{
  "type": "Feature",
  "properties": {
    "date:inception_lower": "1980-01-01",
    "date:inception_upper": "1980-01-01",
    "iso:country": "GB",
    "wof:name": "OL11 2HU",
    "wof:placetype": "postalcode"
  },
  "geometry": {"coordinates":[-2.155186,53.59789],"type":"Point"}
}
