{
  "type": "Feature",
  "properties": {
    "iso:country":"GB",
    "wof:name":"OL11 2HU",
    "wof:placetype":"postalcode"
},
  "geometry": {"coordinates":[-2.15518648515992,53.59789031550422],"type":"Point"}
}