{
  "type": "Feature",
  "properties": {
    "iso:country":"GB",
    "wof:name":"AB25 2TR",
    "wof:placetype":"postalcode"
},
  "geometry": {"coordinates":[-2.11352697750687,57.14994222959714],"type":"Point"}
}