{
  "type": "Feature",
  "properties": {
    "iso:country":"GB",
    "wof:name":"GU14 6RJ",
    "wof:placetype":"postalcode"
},
  "geometry": {"coordinates":[-0.74702377262324,51.28643056515111],"type":"Point"}
}