{
  "type": "Feature",
  "properties": {
    "iso:country":"GB",
    "wof:name":"HX1 2TA",
    "wof:placetype":"postalcode"
},
  "geometry": {"coordinates":[-1.86645939414313,53.71977870297793],"type":"Point"}
}