{
  "type": "Feature",
  "properties": {
    "iso:country": "GB",
    "wof:name": "WF10 5HY",
    "wof:placetype": "postalcode"
  },
  "geometry": {"coordinates":[-1.367547,53.715138],"type":"Point"}
}
