{
  "type": "Feature",
  "properties": {
    "iso:country":"GB",
    "wof:name":"WF10 5HY",
    "wof:placetype":"postalcode"
},
  "geometry": {"coordinates":[-1.36754754218524,53.71513813542121],"type":"Point"}
}