{
  "type": "Feature",
  "properties": {
    "iso:country": "GB",
    "wof:name": "WV14 9PL",
    "wof:placetype": "postalcode"
  },
  "geometry": {"coordinates":[-2.094192,52.549659],"type":"Point"}
}
