{
  "type": "Feature",
  "properties": {
    "iso:country":"GB",
    "wof:name":"PE9 2NE",
    "wof:placetype":"postalcode"
},
  "geometry": {"coordinates":[-0.49006230461335,52.65301018276076],"type":"Point"}
}