{
  "type": "Feature",
  "properties": {
    "iso:country": "GB",
    "wof:name": "PE9 2NE",
    "wof:placetype": "postalcode"
  },
  "geometry": {"coordinates":[-0.489897,52.652793],"type":"Point"}
}
