{
  "type": "Feature",
  "properties": {
    "date:inception_lower": "1997-06-01",
    "date:inception_upper": "1997-06-01",
    "iso:country": "GB",
    "wof:name": "S26 5QQ",
    "wof:placetype": "postalcode"
  },
  "geometry": {"coordinates":[-1.273806,53.343397],"type":"Point"}
}
