{
  "type": "Feature",
  "properties": {
    "iso:country":"GB",
    "wof:name":"S26 5QQ",
    "wof:placetype":"postalcode"
},
  "geometry": {"coordinates":[-1.27380652397981,53.34339679670654],"type":"Point"}
}