{
  "type": "Feature",
  "properties": {
    "iso:country":"GB",
    "wof:name":"BS34 5SF",
    "wof:placetype":"postalcode"
},
  "geometry": {"coordinates":[-2.58815838036837,51.53030208139636],"type":"Point"}
}