{
  "type": "Feature",
  "properties": {
    "date:inception_lower": "2021-08-01",
    "date:inception_upper": "2021-08-01",
    "iso:country": "GB",
    "wof:name": "LE12 6BH",
    "wof:placetype": "postalcode"
  },
  "geometry": {"coordinates":[-1.170188,52.839737],"type":"Point"}
}
