{
  "type": "Feature",
  "properties": {
    "iso:country":"GB",
    "wof:name":"S1 4HG",
    "wof:placetype":"postalcode"
},
  "geometry": {"coordinates":[-1.47618459218304,53.3779302545859],"type":"Point"}
}