{
  "type": "Feature",
  "properties": {
    "iso:country":"GB",
    "wof:name":"SG1 4DU",
    "wof:placetype":"postalcode"
},
  "geometry": {"coordinates":[-0.1826572707254,51.92371859611369],"type":"Point"}
}