{
  "type": "Feature",
  "properties": {
    "iso:country":"GB",
    "wof:name":"DL14 8JG",
    "wof:placetype":"postalcode"
},
  "geometry": {"coordinates":[-1.61757483395729,54.66527774635835],"type":"Point"}
}