{
  "type": "Feature",
  "properties": {
    "date:inception_lower":"1980-01-01",
    "date:inception_upper":"1980-01-31",
    "iso:country":"GB",
    "wof:name":"LE16 8LW",
    "wof:placetype":"postalcode"
},
  "geometry": {"coordinates":[-0.877895,52.453102],"type":"Point"}
}