{
  "type": "Feature",
  "properties": {
    "iso:country": "GB",
    "wof:name": "LE16 8LW",
    "wof:placetype": "postalcode"
  },
  "geometry": {"coordinates":[-0.877895,52.453102],"type":"Point"}
}
