{
  "type": "Feature",
  "properties": {
    "iso:country":"GB",
    "wof:name":"LE16 8LW",
    "wof:placetype":"postalcode"
},
  "geometry": {"coordinates":[-0.87789460581514,52.45310224446587],"type":"Point"}
}