{
  "type": "Feature",
  "properties": {
    "iso:country":"GB",
    "wof:name":"DL11 6RA",
    "wof:placetype":"postalcode"
},
  "geometry": {"coordinates":[-1.99001281040896,54.41281958014731],"type":"Point"}
}