{
  "type": "Feature",
  "properties": {
    "iso:country":"GB",
    "wof:name":"EH9 1JH",
    "wof:placetype":"postalcode"
},
  "geometry": {"coordinates":[-3.19235869194134,55.93829815229768],"type":"Point"}
}