{
  "type": "Feature",
  "properties": {
    "iso:country": "GB",
    "wof:name": "CV2 1TZ",
    "wof:placetype": "postalcode"
  },
  "geometry": {"coordinates":[-1.473918,52.44447],"type":"Point"}
}
