{
  "type": "Feature",
  "properties": {
    "iso:country":"GB",
    "wof:name":"CV2 1TZ",
    "wof:placetype":"postalcode"
},
  "geometry": {"coordinates":[-1.47391765182365,52.44446968011478],"type":"Point"}
}