{
  "type": "Feature",
  "properties": {
    "date:inception_lower": "2000-06-01",
    "date:inception_upper": "2000-06-01",
    "iso:country": "GB",
    "wof:name": "CV2 1TZ",
    "wof:placetype": "postalcode"
  },
  "geometry": {"coordinates":[-1.473918,52.44447],"type":"Point"}
}
