{
  "type": "Feature",
  "properties": {
    "iso:country":"GB",
    "wof:name":"TA3 7PL",
    "wof:placetype":"postalcode"
},
  "geometry": {"coordinates":[-3.12529534456868,50.89883414230171],"type":"Point"}
}