{
  "type": "Feature",
  "properties": {
    "iso:country": "GB",
    "wof:name": "TA3 7PL",
    "wof:placetype": "postalcode"
  },
  "geometry": {"coordinates":[-3.125295,50.898834],"type":"Point"}
}
