{
  "type": "Feature",
  "properties": {
    "date:inception_lower":"1980-01-01",
    "date:inception_upper":"1980-01-31",
    "iso:country":"GB",
    "wof:name":"TA3 7PL",
    "wof:placetype":"postalcode"
},
  "geometry": {"coordinates":[-3.125295,50.898834],"type":"Point"}
}