{
  "type": "Feature",
  "properties": {
    "iso:country": "GB",
    "wof:name": "PA23 8QU",
    "wof:placetype": "postalcode"
  },
  "geometry": {"coordinates":[-4.980947,56.026813],"type":"Point"}
}
