{
  "type": "Feature",
  "properties": {
    "iso:country":"GB",
    "wof:name":"SR7 8HQ",
    "wof:placetype":"postalcode"
},
  "geometry": {"coordinates":[-1.36127948876708,54.83148597708311],"type":"Point"}
}