{
  "type": "Feature",
  "properties": {
    "date:inception_lower": "1988-03-01",
    "date:inception_upper": "1988-03-01",
    "iso:country": "GB",
    "wof:name": "SR7 8HQ",
    "wof:placetype": "postalcode"
  },
  "geometry": {"coordinates":[-1.361279,54.831486],"type":"Point"}
}
