{
  "type": "Feature",
  "properties": {
    "iso:country":"GB",
    "wof:name":"WA6 8NG",
    "wof:placetype":"postalcode"
},
  "geometry": {"coordinates":[-2.65533987334025,53.2532589032356],"type":"Point"}
}