{
  "type": "Feature",
  "properties": {
    "iso:country":"GB",
    "wof:name":"TR11 5PN",
    "wof:placetype":"postalcode"
},
  "geometry": {"coordinates":[-5.16668364068861,50.13052016249546],"type":"Point"}
}