{
  "type": "Feature",
  "properties": {
    "iso:country": "GB",
    "wof:name": "TR11 5PN",
    "wof:placetype": "postalcode"
  },
  "geometry": {"coordinates":[-5.165035,50.128108],"type":"Point"}
}
