{
  "type": "Feature",
  "properties": {
    "iso:country":"GB",
    "wof:name":"TS10 2NQ",
    "wof:placetype":"postalcode"
},
  "geometry": {"coordinates":[-1.04829483435707,54.60406092749072],"type":"Point"}
}