{
  "type": "Feature",
  "properties": {
    "iso:country": "GB",
    "wof:name": "PO20 0RG",
    "wof:placetype": "postalcode"
  },
  "geometry": {"coordinates":[-0.790034,50.732855],"type":"Point"}
}
