{
  "type": "Feature",
  "properties": {
    "iso:country":"GB",
    "wof:name":"PO20 0RG",
    "wof:placetype":"postalcode"
},
  "geometry": {"coordinates":[-0.79003410487586,50.7328554744802],"type":"Point"}
}