{
  "type": "Feature",
  "properties": {
    "iso:country": "GB",
    "wof:name": "G31 4HF",
    "wof:placetype": "postalcode"
  },
  "geometry": {"coordinates":[-4.187293,55.846812],"type":"Point"}
}
