{
  "type": "Feature",
  "properties": {
    "date:inception_lower":"2008-11-01",
    "date:inception_upper":"2008-11-30",
    "iso:country":"GB",
    "wof:name":"ME19 4JY",
    "wof:placetype":"postalcode"
},
  "geometry": {"coordinates":[0.420014,51.273707],"type":"Point"}
}