{
  "type": "Feature",
  "properties": {
    "iso:country":"GB",
    "wof:name":"ME19 4JY",
    "wof:placetype":"postalcode"
},
  "geometry": {"coordinates":[0.42001400206678,51.27370703098822],"type":"Point"}
}