{
  "type": "Feature",
  "properties": {
    "iso:country": "GB",
    "wof:name": "NE70 7DX",
    "wof:placetype": "postalcode"
  },
  "geometry": {"coordinates":[-1.802504,55.596261],"type":"Point"}
}
