{
  "type": "Feature",
  "properties": {
    "iso:country":"GB",
    "wof:name":"BD20 5DN",
    "wof:placetype":"postalcode"
},
  "geometry": {"coordinates":[-1.89330649454648,53.88368292149114],"type":"Point"}
}