{
  "type": "Feature",
  "properties": {
    "iso:country":"GB",
    "wof:name":"BS6 6EA",
    "wof:placetype":"postalcode"
},
  "geometry": {"coordinates":[-2.60333490124214,51.46351645029048],"type":"Point"}
}