{
  "type": "Feature",
  "properties": {
    "iso:country":"GB",
    "wof:name":"LL54 7DU",
    "wof:placetype":"postalcode"
},
  "geometry": {"coordinates":[-4.27465291995955,53.077906933903],"type":"Point"}
}