{
  "type": "Feature",
  "properties": {
    "iso:country": "GB",
    "wof:name": "TW8 0NY",
    "wof:placetype": "postalcode"
  },
  "geometry": {"coordinates":[-0.303939,51.48775],"type":"Point"}
}
