{
  "type": "Feature",
  "properties": {
    "iso:country": "GB",
    "wof:name": "LL11 6NH",
    "wof:placetype": "postalcode"
  },
  "geometry": {"coordinates":[-3.033846,53.06456],"type":"Point"}
}
