{
  "type": "Feature",
  "properties": {
    "iso:country":"GB",
    "wof:name":"HA7 2ER",
    "wof:placetype":"postalcode"
},
  "geometry": {"coordinates":[-0.31256015749028,51.60411797132006],"type":"Point"}
}