{
  "type": "Feature",
  "properties": {
    "iso:country":"GB",
    "wof:name":"IP12 1EW",
    "wof:placetype":"postalcode"
},
  "geometry": {"coordinates":[1.31399995921264,52.09787238314431],"type":"Point"}
}