{
  "type": "Feature",
  "properties": {
    "iso:country":"GB",
    "wof:name":"SM4 6QJ",
    "wof:placetype":"postalcode"
},
  "geometry": {"coordinates":[-0.1895876262085,51.39277910282875],"type":"Point"}
}