{
  "type": "Feature",
  "properties": {
    "date:inception_lower":"2006-10-01",
    "date:inception_upper":"2006-10-31",
    "iso:country":"GB",
    "wof:name":"CF64 3RR",
    "wof:placetype":"postalcode"
},
  "geometry": {"coordinates":[-3.192063,51.426439],"type":"Point"}
}