{
  "type": "Feature",
  "properties": {
    "iso:country": "GB",
    "wof:name": "CF64 3RR",
    "wof:placetype": "postalcode"
  },
  "geometry": {"coordinates":[-3.192063,51.426439],"type":"Point"}
}
