{
  "type": "Feature",
  "properties": {
    "date:inception_lower": "1980-01-01",
    "date:inception_upper": "1980-01-01",
    "iso:country": "GB",
    "wof:name": "CF31 3LL",
    "wof:placetype": "postalcode"
  },
  "geometry": {"coordinates":[-3.575871,51.495004],"type":"Point"}
}
