{
  "type": "Feature",
  "properties": {
    "date:inception_lower": "1980-01-01",
    "date:inception_upper": "1980-01-01",
    "iso:country": "GB",
    "wof:name": "CT4 8JA",
    "wof:placetype": "postalcode"
  },
  "geometry": {"coordinates":[0.922548,51.249651],"type":"Point"}
}
