{
  "type": "Feature",
  "properties": {
    "iso:country": "GB",
    "wof:name": "NP10 8NF",
    "wof:placetype": "postalcode"
  },
  "geometry": {"coordinates":[-3.043374,51.574423],"type":"Point"}
}
