{
  "type": "Feature",
  "properties": {
    "iso:country":"GB",
    "wof:name":"TQ7 4PA",
    "wof:placetype":"postalcode"
},
  "geometry": {"coordinates":[-3.83998085171753,50.30589750006949],"type":"Point"}
}