{
  "type": "Feature",
  "properties": {
    "iso:country": "GB",
    "wof:name": "KT9 2LZ",
    "wof:placetype": "postalcode"
  },
  "geometry": {"coordinates":[-0.32056,51.355171],"type":"Point"}
}
