{
  "type": "Feature",
  "properties": {
    "iso:country":"GB",
    "wof:name":"KT9 2LZ",
    "wof:placetype":"postalcode"
},
  "geometry": {"coordinates":[-0.32055966374179,51.35517136004719],"type":"Point"}
}