{
  "type": "Feature",
  "properties": {
    "iso:country":"GB",
    "wof:name":"B27 7ET",
    "wof:placetype":"postalcode"
},
  "geometry": {"coordinates":[-1.81669353529506,52.44252115861731],"type":"Point"}
}