{
  "type": "Feature",
  "properties": {
    "iso:country":"GB",
    "wof:name":"SW19 8BD",
    "wof:placetype":"postalcode"
},
  "geometry": {"coordinates":[-0.20045116480215,51.43863771592299],"type":"Point"}
}