{
  "type": "Feature",
  "properties": {
    "date:inception_lower":"1990-07-01",
    "date:inception_upper":"1990-07-31",
    "iso:country":"GB",
    "wof:name":"TQ12 6SD",
    "wof:placetype":"postalcode"
},
  "geometry": {"coordinates":[-3.655598,50.568052],"type":"Point"}
}