{
  "type": "Feature",
  "properties": {
    "date:inception_lower": "1980-01-01",
    "date:inception_upper": "1980-01-01",
    "iso:country": "GB",
    "wof:name": "NN9 6NE",
    "wof:placetype": "postalcode"
  },
  "geometry": {"coordinates":[-0.533437,52.342639],"type":"Point"}
}
