{
  "type": "Feature",
  "properties": {
    "iso:country": "GB",
    "wof:name": "NW5 1DH",
    "wof:placetype": "postalcode"
  },
  "geometry": {"coordinates":[-0.141981,51.558612],"type":"Point"}
}
