{
  "type": "Feature",
  "properties": {
    "iso:country":"GB",
    "wof:name":"NW5 1DH",
    "wof:placetype":"postalcode"
},
  "geometry": {"coordinates":[-0.14198138866421,51.55861202311632],"type":"Point"}
}