{
  "type": "Feature",
  "properties": {
    "date:inception_lower": "1980-01-01",
    "date:inception_upper": "1980-01-01",
    "iso:country": "GB",
    "wof:name": "SO24 9RP",
    "wof:placetype": "postalcode"
  },
  "geometry": {"coordinates":[-1.099021,51.144921],"type":"Point"}
}
