{
  "type": "Feature",
  "properties": {
    "iso:country":"GB",
    "wof:name":"BD18 2DD",
    "wof:placetype":"postalcode"
},
  "geometry": {"coordinates":[-1.770846293616,53.82461423664424],"type":"Point"}
}