{
  "type": "Feature",
  "properties": {
    "iso:country":"GB",
    "wof:name":"OX10 8JT",
    "wof:placetype":"postalcode"
},
  "geometry": {"coordinates":[-1.12752706497843,51.60755368966084],"type":"Point"}
}