{
  "type": "Feature",
  "properties": {
    "iso:country":"GB",
    "wof:name":"GL51 3AT",
    "wof:placetype":"postalcode"
},
  "geometry": {"coordinates":[-2.1003553073728,51.88827825151999],"type":"Point"}
}