{
  "type": "Feature",
  "properties": {
    "date:inception_lower": "2000-10-01",
    "date:inception_upper": "2000-10-01",
    "iso:country": "GB",
    "wof:name": "GL51 3AT",
    "wof:placetype": "postalcode"
  },
  "geometry": {"coordinates":[-2.099752,51.887737],"type":"Point"}
}
