{
  "type": "Feature",
  "properties": {
    "date:inception_lower": "1999-06-01",
    "date:inception_upper": "1999-06-01",
    "iso:country": "GB",
    "wof:name": "CH47 1HY",
    "wof:placetype": "postalcode"
  },
  "geometry": {"coordinates":[-3.19294,53.388208],"type":"Point"}
}
