{
  "type": "Feature",
  "properties": {
    "date:inception_lower": "1999-06-01",
    "date:inception_upper": "1999-06-01",
    "iso:country": "GB",
    "wof:name": "CH65 8DW",
    "wof:placetype": "postalcode"
  },
  "geometry": {"coordinates":[-2.906328,53.28109],"type":"Point"}
}
