{
  "type": "Feature",
  "properties": {
    "iso:country":"GB",
    "wof:name":"CH65 8DW",
    "wof:placetype":"postalcode"
},
  "geometry": {"coordinates":[-2.90632853704159,53.28108970278325],"type":"Point"}
}