{
  "type": "Feature",
  "properties": {
    "iso:country": "GB",
    "wof:name": "DN20 9AH",
    "wof:placetype": "postalcode"
  },
  "geometry": {"coordinates":[-0.539787,53.537657],"type":"Point"}
}
