{
  "type": "Feature",
  "properties": {
    "iso:country":"GB",
    "wof:name":"PE37 8HB",
    "wof:placetype":"postalcode"
},
  "geometry": {"coordinates":[0.77463710021655,52.64872500384446],"type":"Point"}
}