{
  "type": "Feature",
  "properties": {
    "date:inception_lower": "1980-01-01",
    "date:inception_upper": "1980-01-01",
    "iso:country": "GB",
    "wof:name": "BB7 2HQ",
    "wof:placetype": "postalcode"
  },
  "geometry": {"coordinates":[-2.391224,53.874028],"type":"Point"}
}
