{
  "type": "Feature",
  "properties": {
    "iso:country":"GB",
    "wof:name":"BB7 2HQ",
    "wof:placetype":"postalcode"
},
  "geometry": {"coordinates":[-2.39128313078385,53.87387898186822],"type":"Point"}
}