{
  "type": "Feature",
  "properties": {
    "iso:country": "GB",
    "wof:name": "YO32 2PJ",
    "wof:placetype": "postalcode"
  },
  "geometry": {"coordinates":[-1.084161,54.019778],"type":"Point"}
}
