{
  "type": "Feature",
  "properties": {
    "date:inception_lower":"1998-06-01",
    "date:inception_upper":"1998-06-30",
    "iso:country":"GB",
    "wof:name":"YO32 2PJ",
    "wof:placetype":"postalcode"
},
  "geometry": {"coordinates":[-1.084161,54.019778],"type":"Point"}
}