{
  "type": "Feature",
  "properties": {
    "iso:country":"GB",
    "wof:name":"YO32 2PJ",
    "wof:placetype":"postalcode"
},
  "geometry": {"coordinates":[-1.08416124576536,54.01977841904272],"type":"Point"}
}