{
  "type": "Feature",
  "properties": {
    "date:inception_lower":"1980-03-01",
    "date:inception_upper":"1980-03-31",
    "iso:country":"GB",
    "wof:name":"FK2 7BX",
    "wof:placetype":"postalcode"
},
  "geometry": {"coordinates":[-3.785125,56.008488],"type":"Point"}
}