{
  "type": "Feature",
  "properties": {
    "date:inception_lower": "1995-07-01",
    "date:inception_upper": "1995-07-01",
    "iso:country": "GB",
    "wof:name": "WA7 6SQ",
    "wof:placetype": "postalcode"
  },
  "geometry": {"coordinates":[-2.670613,53.327935],"type":"Point"}
}
