{
  "type": "Feature",
  "properties": {
    "iso:country": "GB",
    "wof:name": "WA7 6SQ",
    "wof:placetype": "postalcode"
  },
  "geometry": {"coordinates":[-2.670613,53.327935],"type":"Point"}
}
