{
  "type": "Feature",
  "properties": {
    "iso:country":"GB",
    "wof:name":"M24 4NS",
    "wof:placetype":"postalcode"
},
  "geometry": {"coordinates":[-2.22946690285297,53.55327862626586],"type":"Point"}
}