{
  "type": "Feature",
  "properties": {
    "date:inception_lower": "1997-06-01",
    "date:inception_upper": "1997-06-01",
    "iso:country": "GB",
    "wof:name": "S18 8QX",
    "wof:placetype": "postalcode"
  },
  "geometry": {"coordinates":[-1.49077,53.304375],"type":"Point"}
}
