{
  "type": "Feature",
  "properties": {
    "iso:country":"GB",
    "wof:name":"B13 0NA",
    "wof:placetype":"postalcode"
},
  "geometry": {"coordinates":[-1.87291195567702,52.42016465714794],"type":"Point"}
}