{
  "type": "Feature",
  "properties": {
    "date:inception_lower":"1990-02-01",
    "date:inception_upper":"1990-02-28",
    "iso:country":"GB",
    "wof:name":"TF5 0NL",
    "wof:placetype":"postalcode"
},
  "geometry": {"coordinates":[-2.535818,52.719928],"type":"Point"}
}