{
  "type": "Feature",
  "properties": {
    "iso:country":"GB",
    "wof:name":"SW11 2PR",
    "wof:placetype":"postalcode"
},
  "geometry": {"coordinates":[-0.16794844895337,51.46989594188388],"type":"Point"}
}