{
  "type": "Feature",
  "properties": {
    "iso:country": "GB",
    "wof:name": "S43 1EX",
    "wof:placetype": "postalcode"
  },
  "geometry": {"coordinates":[-1.398413,53.260107],"type":"Point"}
}
