{
  "type": "Feature",
  "properties": {
    "iso:country": "GB",
    "wof:name": "BB7 4SN",
    "wof:placetype": "postalcode"
  },
  "geometry": {"coordinates":[-2.389828,53.895679],"type":"Point"}
}
