{
  "type": "Feature",
  "properties": {
    "iso:country": "GB",
    "wof:name": "TF1 7GR",
    "wof:placetype": "postalcode"
  },
  "geometry": {"coordinates":[-2.460871,52.718104],"type":"Point"}
}
