{
  "type": "Feature",
  "properties": {
    "iso:country":"GB",
    "wof:name":"DL12 8NJ",
    "wof:placetype":"postalcode"
},
  "geometry": {"coordinates":[-1.92014970895998,54.54159453382998],"type":"Point"}
}