{
  "type": "Feature",
  "properties": {
    "iso:country":"GB",
    "wof:name":"CH4 9DT",
    "wof:placetype":"postalcode"
},
  "geometry": {"coordinates":[-2.9478025648678,53.13199598155693],"type":"Point"}
}