{
  "type": "Feature",
  "properties": {
    "date:inception_lower":"2007-01-01",
    "date:inception_upper":"2007-01-31",
    "iso:country":"GB",
    "wof:name":"HX3 0RG",
    "wof:placetype":"postalcode"
},
  "geometry": {"coordinates":[-1.858014,53.703294],"type":"Point"}
}