{
  "type": "Feature",
  "properties": {
    "iso:country":"GB",
    "wof:name":"TR8 4JD",
    "wof:placetype":"postalcode"
},
  "geometry": {"coordinates":[-4.95801168511644,50.42382287452153],"type":"Point"}
}