{
  "type": "Feature",
  "properties": {
    "iso:country":"GB",
    "wof:name":"S60 5LN",
    "wof:placetype":"postalcode"
},
  "geometry": {"coordinates":[-1.35869152851463,53.40104248772813],"type":"Point"}
}