{
  "type": "Feature",
  "properties": {
    "iso:country":"GB",
    "wof:name":"SA9 2YN",
    "wof:placetype":"postalcode"
},
  "geometry": {"coordinates":[-3.80882127013151,51.79574213538229],"type":"Point"}
}