{
  "type": "Feature",
  "properties": {
    "iso:country":"GB",
    "wof:name":"HU3 3JG",
    "wof:placetype":"postalcode"
},
  "geometry": {"coordinates":[-0.36849080555887,53.74091978143328],"type":"Point"}
}