{
  "type": "Feature",
  "properties": {
    "iso:country": "GB",
    "wof:name": "HU18 1HW",
    "wof:placetype": "postalcode"
  },
  "geometry": {"coordinates":[-0.165769,53.919419],"type":"Point"}
}
