{
  "type": "Feature",
  "properties": {
    "date:inception_lower":"1982-03-01",
    "date:inception_upper":"1982-03-31",
    "iso:country":"GB",
    "wof:name":"HU18 1HW",
    "wof:placetype":"postalcode"
},
  "geometry": {"coordinates":[-0.165769,53.919419],"type":"Point"}
}