{
  "type": "Feature",
  "properties": {
    "iso:country":"GB",
    "wof:name":"SE5 8AU",
    "wof:placetype":"postalcode"
},
  "geometry": {"coordinates":[-0.08743865445334,51.46252226082982],"type":"Point"}
}