{
  "type": "Feature",
  "properties": {
    "iso:country": "GB",
    "wof:name": "B78 2EJ",
    "wof:placetype": "postalcode"
  },
  "geometry": {"coordinates":[-1.671707,52.575574],"type":"Point"}
}
