{
  "type": "Feature",
  "properties": {
    "date:inception_lower":"1987-04-01",
    "date:inception_upper":"1987-04-30",
    "iso:country":"GB",
    "wof:name":"SP10 1RE",
    "wof:placetype":"postalcode"
},
  "geometry": {"coordinates":[-1.482244,51.212527],"type":"Point"}
}