{
  "type": "Feature",
  "properties": {
    "iso:country":"GB",
    "wof:name":"SP10 1RE",
    "wof:placetype":"postalcode"
},
  "geometry": {"coordinates":[-1.48224362851029,51.21252651678147],"type":"Point"}
}