{
  "type": "Feature",
  "properties": {
    "iso:country":"GB",
    "wof:name":"CV5 7HJ",
    "wof:placetype":"postalcode"
},
  "geometry": {"coordinates":[-1.569214746419,52.41225684731523],"type":"Point"}
}