{
  "type": "Feature",
  "properties": {
    "iso:country": "GB",
    "wof:name": "NR14 7XN",
    "wof:placetype": "postalcode"
  },
  "geometry": {"coordinates":[1.343864,52.563728],"type":"Point"}
}
