{
  "type": "Feature",
  "properties": {
    "iso:country": "GB",
    "wof:name": "OL8 3JY",
    "wof:placetype": "postalcode"
  },
  "geometry": {"coordinates":[-2.124522,53.518928],"type":"Point"}
}
