{
  "type": "Feature",
  "properties": {
    "iso:country":"GB",
    "wof:name":"OL8 3JY",
    "wof:placetype":"postalcode"
},
  "geometry": {"coordinates":[-2.12452246167777,53.51892784606399],"type":"Point"}
}