{
  "type": "Feature",
  "properties": {
    "date:inception_lower":"1980-01-01",
    "date:inception_upper":"1980-01-31",
    "iso:country":"GB",
    "wof:name":"NG22 9HN",
    "wof:placetype":"postalcode"
},
  "geometry": {"coordinates":[-0.993182,53.210604],"type":"Point"}
}