{
  "type": "Feature",
  "properties": {
    "iso:country": "GB",
    "wof:name": "NG22 9HN",
    "wof:placetype": "postalcode"
  },
  "geometry": {"coordinates":[-0.993182,53.210604],"type":"Point"}
}
