{
  "type": "Feature",
  "properties": {
    "iso:country":"GB",
    "wof:name":"TA20 2HD",
    "wof:placetype":"postalcode"
},
  "geometry": {"coordinates":[-2.97125580093365,50.86990338710451],"type":"Point"}
}