{
  "type": "Feature",
  "properties": {
    "iso:country":"GB",
    "wof:name":"YO26 8ER",
    "wof:placetype":"postalcode"
},
  "geometry": {"coordinates":[-1.22683169053829,54.01441683135653],"type":"Point"}
}