{
  "type": "Feature",
  "properties": {
    "date:inception_lower":"1980-01-01",
    "date:inception_upper":"1980-01-31",
    "iso:country":"GB",
    "wof:name":"TS9 5JL",
    "wof:placetype":"postalcode"
},
  "geometry": {"coordinates":[-1.187629,54.469679],"type":"Point"}
}