{
  "type": "Feature",
  "properties": {
    "iso:country":"GB",
    "wof:name":"TS9 5JL",
    "wof:placetype":"postalcode"
},
  "geometry": {"coordinates":[-1.18758527518401,54.46967524811267],"type":"Point"}
}