{
  "type": "Feature",
  "properties": {
    "iso:country": "GB",
    "wof:name": "TS9 5JL",
    "wof:placetype": "postalcode"
  },
  "geometry": {"coordinates":[-1.187629,54.469679],"type":"Point"}
}
