{
  "type": "Feature",
  "properties": {
    "date:inception_lower":"1983-07-01",
    "date:inception_upper":"1983-07-31",
    "iso:country":"GB",
    "wof:name":"EC4M 7AQ",
    "wof:placetype":"postalcode"
},
  "geometry": {"coordinates":[-0.100851,51.51436],"type":"Point"}
}