{
  "type": "Feature",
  "properties": {
    "iso:country":"GB",
    "wof:name":"EC4M 7AQ",
    "wof:placetype":"postalcode"
},
  "geometry": {"coordinates":[-0.10092685098456,51.51419710509214],"type":"Point"}
}