{
  "type": "Feature",
  "properties": {
    "iso:country": "GB",
    "wof:name": "BD20 5TB",
    "wof:placetype": "postalcode"
  },
  "geometry": {"coordinates":[-1.85079,53.874075],"type":"Point"}
}
