{
  "type": "Feature",
  "properties": {
    "iso:country":"GB",
    "wof:name":"SW8 2PA",
    "wof:placetype":"postalcode"
},
  "geometry": {"coordinates":[-0.12933542435735,51.47544614811218],"type":"Point"}
}