{
  "type": "Feature",
  "properties": {
    "iso:country": "GB",
    "wof:name": "CH8 9TE",
    "wof:placetype": "postalcode"
  },
  "geometry": {"coordinates":[-3.301775,53.330546],"type":"Point"}
}
