{
  "type": "Feature",
  "properties": {
    "date:inception_lower": "1980-01-01",
    "date:inception_upper": "1980-01-01",
    "iso:country": "GB",
    "wof:name": "CH8 9TE",
    "wof:placetype": "postalcode"
  },
  "geometry": {"coordinates":[-3.301775,53.330546],"type":"Point"}
}
