{
  "type": "Feature",
  "properties": {
    "iso:country":"GB",
    "wof:name":"CH8 9TE",
    "wof:placetype":"postalcode"
},
  "geometry": {"coordinates":[-3.30177516727471,53.3305457371438],"type":"Point"}
}