{
  "type": "Feature",
  "properties": {
    "iso:country":"GB",
    "wof:name":"NW8 9UL",
    "wof:placetype":"postalcode"
},
  "geometry": {"coordinates":[-0.18009868806041,51.52998407346961],"type":"Point"}
}