{
  "type": "Feature",
  "properties": {
    "iso:country": "GB",
    "wof:name": "BR3 6RP",
    "wof:placetype": "postalcode"
  },
  "geometry": {"coordinates":[-0.005685,51.398696],"type":"Point"}
}
