{
  "type": "Feature",
  "properties": {
    "iso:country":"GB",
    "wof:name":"BR3 6RP",
    "wof:placetype":"postalcode"
},
  "geometry": {"coordinates":[-0.00568547630828,51.39869618410434],"type":"Point"}
}