{
  "type": "Feature",
  "properties": {
    "iso:country": "GB",
    "wof:name": "M45 7PU",
    "wof:placetype": "postalcode"
  },
  "geometry": {"coordinates":[-2.30548,53.542709],"type":"Point"}
}
