{
  "type": "Feature",
  "properties": {
    "iso:country":"GB",
    "wof:name":"M45 7PU",
    "wof:placetype":"postalcode"
},
  "geometry": {"coordinates":[-2.3054800546644,53.54270893411715],"type":"Point"}
}