{
  "type": "Feature",
  "properties": {
    "iso:country":"GB",
    "wof:name":"NR7 8DB",
    "wof:placetype":"postalcode"
},
  "geometry": {"coordinates":[1.32746528093688,52.66215233513047],"type":"Point"}
}