{
  "type": "Feature",
  "properties": {
    "iso:country":"GB",
    "wof:name":"DG3 5BL",
    "wof:placetype":"postalcode"
},
  "geometry": {"coordinates":[-3.75277136369275,55.31575374145219],"type":"Point"}
}