{
  "type": "Feature",
  "properties": {
    "date:inception_lower": "1990-02-01",
    "date:inception_upper": "1990-02-01",
    "iso:country": "GB",
    "wof:name": "DH4 5PJ",
    "wof:placetype": "postalcode"
  },
  "geometry": {"coordinates":[-1.489653,54.84214],"type":"Point"}
}
