{
  "type": "Feature",
  "properties": {
    "date:inception_lower": "1980-01-01",
    "date:inception_upper": "1980-01-01",
    "iso:country": "GB",
    "wof:name": "HA6 1PA",
    "wof:placetype": "postalcode"
  },
  "geometry": {"coordinates":[-0.409826,51.601366],"type":"Point"}
}
