{
  "type": "Feature",
  "properties": {
    "iso:country":"GB",
    "wof:name":"HA6 1PA",
    "wof:placetype":"postalcode"
},
  "geometry": {"coordinates":[-0.40982588445194,51.60136646733255],"type":"Point"}
}