{
  "type": "Feature",
  "properties": {
    "iso:country": "GB",
    "wof:name": "HA6 1PA",
    "wof:placetype": "postalcode"
  },
  "geometry": {"coordinates":[-0.409826,51.601366],"type":"Point"}
}
