{
  "type": "Feature",
  "properties": {
    "iso:country":"GB",
    "wof:name":"BS2 9YY",
    "wof:placetype":"postalcode"
},
  "geometry": {"coordinates":[-2.57542400011192,51.47157841200674],"type":"Point"}
}