{
  "type": "Feature",
  "properties": {
    "iso:country": "GB",
    "wof:name": "PL21 9UF",
    "wof:placetype": "postalcode"
  },
  "geometry": {"coordinates":[-3.941563,50.387315],"type":"Point"}
}
