{
  "type": "Feature",
  "properties": {
    "date:inception_lower": "1987-04-01",
    "date:inception_upper": "1987-04-01",
    "iso:country": "GB",
    "wof:name": "PL21 9UF",
    "wof:placetype": "postalcode"
  },
  "geometry": {"coordinates":[-3.941563,50.387315],"type":"Point"}
}
