{
  "type": "Feature",
  "properties": {
    "iso:country":"GB",
    "wof:name":"SK9 7JF",
    "wof:placetype":"postalcode"
},
  "geometry": {"coordinates":[-2.2131520524493,53.30124340038827],"type":"Point"}
}