{
  "type": "Feature",
  "properties": {
    "iso:country": "GB",
    "wof:name": "TA9 3DP",
    "wof:placetype": "postalcode"
  },
  "geometry": {"coordinates":[-2.984623,51.2156],"type":"Point"}
}
