{
  "type": "Feature",
  "properties": {
    "iso:country":"GB",
    "wof:name":"TA9 3DP",
    "wof:placetype":"postalcode"
},
  "geometry": {"coordinates":[-2.98464118091038,51.21556880433829],"type":"Point"}
}