{
  "type": "Feature",
  "properties": {
    "date:inception_lower": "2021-10-01",
    "date:inception_upper": "2021-10-01",
    "iso:country": "GB",
    "wof:name": "ST16 1YU",
    "wof:placetype": "postalcode"
  },
  "geometry": {"coordinates":[-2.141838,52.804799],"type":"Point"}
}
