{
  "type": "Feature",
  "properties": {
    "iso:country":"GB",
    "wof:name":"KY16 8DR",
    "wof:placetype":"postalcode"
},
  "geometry": {"coordinates":[-2.78624169316966,56.33295549926631],"type":"Point"}
}