{
  "type": "Feature",
  "properties": {
    "iso:country": "GB",
    "wof:name": "EX13 5LT",
    "wof:placetype": "postalcode"
  },
  "geometry": {"coordinates":[-2.999868,50.779095],"type":"Point"}
}
