{
  "type": "Feature",
  "properties": {
    "iso:country":"GB",
    "wof:name":"EX13 5LT",
    "wof:placetype":"postalcode"
},
  "geometry": {"coordinates":[-2.99986842420386,50.77909538063797],"type":"Point"}
}