{
  "type": "Feature",
  "properties": {
    "iso:country":"GB",
    "wof:name":"SW19 6HD",
    "wof:placetype":"postalcode"
},
  "geometry": {"coordinates":[-0.21985890273585,51.44017501987791],"type":"Point"}
}