{
  "type": "Feature",
  "properties": {
    "iso:country":"GB",
    "wof:name":"FY5 1PS",
    "wof:placetype":"postalcode"
},
  "geometry": {"coordinates":[-3.04348994433644,53.86786713656238],"type":"Point"}
}