{
  "type": "Feature",
  "properties": {
    "date:inception_lower": "1980-01-01",
    "date:inception_upper": "1980-01-01",
    "iso:country": "GB",
    "wof:name": "FY5 1PS",
    "wof:placetype": "postalcode"
  },
  "geometry": {"coordinates":[-3.04349,53.867867],"type":"Point"}
}
