{
  "type": "Feature",
  "properties": {
    "iso:country":"GB",
    "wof:name":"CO1 2GD",
    "wof:placetype":"postalcode"
},
  "geometry": {"coordinates":[0.90797905675609,51.88945051236144],"type":"Point"}
}