{
  "type": "Feature",
  "properties": {
    "iso:country": "GB",
    "wof:name": "CO1 2GD",
    "wof:placetype": "postalcode"
  },
  "geometry": {"coordinates":[0.907979,51.889451],"type":"Point"}
}
