{
  "type": "Feature",
  "properties": {
    "iso:country":"GB",
    "wof:name":"TN6 2SB",
    "wof:placetype":"postalcode"
},
  "geometry": {"coordinates":[0.17301896523566,51.06042872288306],"type":"Point"}
}