{
  "type": "Feature",
  "properties": {
    "date:inception_lower":"1980-01-01",
    "date:inception_upper":"1980-01-31",
    "iso:country":"GB",
    "wof:name":"TN6 2SB",
    "wof:placetype":"postalcode"
},
  "geometry": {"coordinates":[0.173019,51.060429],"type":"Point"}
}