{
  "type": "Feature",
  "properties": {
    "iso:country":"GB",
    "wof:name":"OL12 9RB",
    "wof:placetype":"postalcode"
},
  "geometry": {"coordinates":[-2.12808067802983,53.63824367092292],"type":"Point"}
}