{
  "type": "Feature",
  "properties": {
    "date:inception_lower":"1980-01-01",
    "date:inception_upper":"1980-01-31",
    "iso:country":"GB",
    "wof:name":"NE5 2DA",
    "wof:placetype":"postalcode"
},
  "geometry": {"coordinates":[-1.691181,54.990429],"type":"Point"}
}