{
  "type": "Feature",
  "properties": {
    "iso:country":"GB",
    "wof:name":"E10 7QY",
    "wof:placetype":"postalcode"
},
  "geometry": {"coordinates":[-0.03748020390423,51.57091201583948],"type":"Point"}
}