{
  "type": "Feature",
  "properties": {
    "iso:country":"GB",
    "wof:name":"BH20 7QF",
    "wof:placetype":"postalcode"
},
  "geometry": {"coordinates":[-2.09405773381793,50.70951535900395],"type":"Point"}
}