{
  "type": "Feature",
  "properties": {
    "date:inception_lower":"1990-02-01",
    "date:inception_upper":"1990-02-28",
    "iso:country":"GB",
    "wof:name":"BH20 7QF",
    "wof:placetype":"postalcode"
},
  "geometry": {"coordinates":[-2.094058,50.709515],"type":"Point"}
}