{
  "type": "Feature",
  "properties": {
    "iso:country":"GB",
    "wof:name":"DY6 8AU",
    "wof:placetype":"postalcode"
},
  "geometry": {"coordinates":[-2.1589039145628,52.50067591492695],"type":"Point"}
}