{
  "type": "Feature",
  "properties": {
    "iso:country": "GB",
    "wof:name": "EN1 2RY",
    "wof:placetype": "postalcode"
  },
  "geometry": {"coordinates":[-0.077184,51.647738],"type":"Point"}
}
