{
  "type": "Feature",
  "properties": {
    "iso:country":"GB",
    "wof:name":"EN1 2RY",
    "wof:placetype":"postalcode"
},
  "geometry": {"coordinates":[-0.07718130801439,51.64774433300073],"type":"Point"}
}