{
  "type": "Feature",
  "properties": {
    "iso:country":"GB",
    "wof:name":"BS13 8BN",
    "wof:placetype":"postalcode"
},
  "geometry": {"coordinates":[-2.62760331526499,51.41725272917864],"type":"Point"}
}