{
  "type": "Feature",
  "properties": {
    "iso:country": "GB",
    "wof:name": "SA62 6AD",
    "wof:placetype": "postalcode"
  },
  "geometry": {"coordinates":[-5.04616,51.828683],"type":"Point"}
}
