{
  "type": "Feature",
  "properties": {
    "date:inception_lower": "1980-01-01",
    "date:inception_upper": "1980-01-01",
    "iso:country": "GB",
    "wof:name": "SA62 6AD",
    "wof:placetype": "postalcode"
  },
  "geometry": {"coordinates":[-5.04616,51.828683],"type":"Point"}
}
