{
  "type": "Feature",
  "properties": {
    "iso:country": "GB",
    "wof:name": "TQ12 1RW",
    "wof:placetype": "postalcode"
  },
  "geometry": {"coordinates":[-3.634011,50.537158],"type":"Point"}
}
