{
  "type": "Feature",
  "properties": {
    "iso:country":"GB",
    "wof:name":"SW3 5BB",
    "wof:placetype":"postalcode"
},
  "geometry": {"coordinates":[-0.17303425619663,51.48242994079242],"type":"Point"}
}