{
  "type": "Feature",
  "properties": {
    "iso:country":"GB",
    "wof:name":"LU1 5DA",
    "wof:placetype":"postalcode"
},
  "geometry": {"coordinates":[-0.41731528253143,51.87592720247737],"type":"Point"}
}