{
  "type": "Feature",
  "properties": {
    "iso:country": "GB",
    "wof:name": "LU1 5DA",
    "wof:placetype": "postalcode"
  },
  "geometry": {"coordinates":[-0.417315,51.875927],"type":"Point"}
}
