{
  "type": "Feature",
  "properties": {
    "date:inception_lower": "2000-06-01",
    "date:inception_upper": "2000-06-01",
    "iso:country": "GB",
    "wof:name": "NW1 3UD",
    "wof:placetype": "postalcode"
  },
  "geometry": {"coordinates":[-0.13929,51.525234],"type":"Point"}
}
