{
  "type": "Feature",
  "properties": {
    "iso:country": "GB",
    "wof:name": "TS15 9FA",
    "wof:placetype": "postalcode"
  },
  "geometry": {"coordinates":[-1.353947,54.492169],"type":"Point"}
}
