{
  "type": "Feature",
  "properties": {
    "iso:country":"GB",
    "wof:name":"HP15 7AW",
    "wof:placetype":"postalcode"
},
  "geometry": {"coordinates":[-0.71766854498587,51.65985660044475],"type":"Point"}
}