{
  "type": "Feature",
  "properties": {
    "iso:country":"GB",
    "wof:name":"DA15 7DQ",
    "wof:placetype":"postalcode"
},
  "geometry": {"coordinates":[0.10239317286432,51.42998167882397],"type":"Point"}
}