{
  "type": "Feature",
  "properties": {
    "date:inception_lower": "1986-07-01",
    "date:inception_upper": "1986-07-01",
    "iso:country": "GB",
    "wof:name": "DA15 7DQ",
    "wof:placetype": "postalcode"
  },
  "geometry": {"coordinates":[0.102393,51.429982],"type":"Point"}
}
