{
  "type": "Feature",
  "properties": {
    "iso:country":"GB",
    "wof:name":"EH41 4PY",
    "wof:placetype":"postalcode"
},
  "geometry": {"coordinates":[-2.66895512929727,55.97185805503281],"type":"Point"}
}