{
  "type": "Feature",
  "properties": {
    "date:inception_lower":"1980-01-01",
    "date:inception_upper":"1980-01-31",
    "iso:country":"GB",
    "wof:name":"EH41 4PY",
    "wof:placetype":"postalcode"
},
  "geometry": {"coordinates":[-2.668955,55.971858],"type":"Point"}
}