{
  "type": "Feature",
  "properties": {
    "iso:country": "GB",
    "wof:name": "BS1 3NX",
    "wof:placetype": "postalcode"
  },
  "geometry": {"coordinates":[-2.591687,51.459988],"type":"Point"}
}
