{
  "type": "Feature",
  "properties": {
    "iso:country":"GB",
    "wof:name":"LS6 2BB",
    "wof:placetype":"postalcode"
},
  "geometry": {"coordinates":[-1.56919716201853,53.82288260754608],"type":"Point"}
}