{
  "type": "Feature",
  "properties": {
    "iso:country":"GB",
    "wof:name":"NE7 7GR",
    "wof:placetype":"postalcode"
},
  "geometry": {"coordinates":[-1.56202735992676,55.00182258574601],"type":"Point"}
}