{
  "type": "Feature",
  "properties": {
    "date:inception_lower":"2000-12-01",
    "date:inception_upper":"2000-12-31",
    "iso:country":"GB",
    "wof:name":"NE7 7GR",
    "wof:placetype":"postalcode"
},
  "geometry": {"coordinates":[-1.562027,55.001823],"type":"Point"}
}