{
  "type": "Feature",
  "properties": {
    "iso:country": "GB",
    "wof:name": "BL7 0AQ",
    "wof:placetype": "postalcode"
  },
  "geometry": {"coordinates":[-2.395767,53.64305],"type":"Point"}
}
