{
  "type": "Feature",
  "properties": {
    "iso:country":"GB",
    "wof:name":"BL7 0AQ",
    "wof:placetype":"postalcode"
},
  "geometry": {"coordinates":[-2.39576729189103,53.64305039753577],"type":"Point"}
}