{
  "type": "Feature",
  "properties": {
    "iso:country":"GB",
    "wof:name":"IP28 8PN",
    "wof:placetype":"postalcode"
},
  "geometry": {"coordinates":[0.46886218539838,52.34723599498513],"type":"Point"}
}