{
  "type": "Feature",
  "properties": {
    "iso:country":"GB",
    "wof:name":"DN36 5PE",
    "wof:placetype":"postalcode"
},
  "geometry": {"coordinates":[-0.0208043390437,53.50541668581943],"type":"Point"}
}