{
  "type": "Feature",
  "properties": {
    "iso:country": "GB",
    "wof:name": "DN36 5PE",
    "wof:placetype": "postalcode"
  },
  "geometry": {"coordinates":[-0.02124,53.492621],"type":"Point"}
}
