{
  "type": "Feature",
  "properties": {
    "date:inception_lower": "2023-05-01",
    "date:inception_upper": "2023-05-01",
    "iso:country": "GB",
    "wof:name": "OX18 2GB",
    "wof:placetype": "postalcode"
  },
  "geometry": {"coordinates":[-1.533714,51.727965],"type":"Point"}
}
