{
  "type": "Feature",
  "properties": {
    "iso:country":"GB",
    "wof:name":"DH9 6DA",
    "wof:placetype":"postalcode"
},
  "geometry": {"coordinates":[-1.67922581446776,54.85492911024811],"type":"Point"}
}