{
  "type": "Feature",
  "properties": {
    "iso:country": "GB",
    "wof:name": "NG9 5JH",
    "wof:placetype": "postalcode"
  },
  "geometry": {"coordinates":[-1.236841,52.907136],"type":"Point"}
}
