{
  "type": "Feature",
  "properties": {
    "iso:country":"GB",
    "wof:name":"CF33 4RR",
    "wof:placetype":"postalcode"
},
  "geometry": {"coordinates":[-3.69029704604361,51.50239367576792],"type":"Point"}
}