{
  "type": "Feature",
  "properties": {
    "date:inception_lower":"1980-01-01",
    "date:inception_upper":"1980-01-31",
    "iso:country":"GB",
    "wof:name":"CF33 4RR",
    "wof:placetype":"postalcode"
},
  "geometry": {"coordinates":[-3.690297,51.502394],"type":"Point"}
}