{
  "type": "Feature",
  "properties": {
    "iso:country":"GB",
    "wof:name":"WA16 0LJ",
    "wof:placetype":"postalcode"
},
  "geometry": {"coordinates":[-2.4693058345043,53.29454153336146],"type":"Point"}
}