{
  "type": "Feature",
  "properties": {
    "iso:country":"GB",
    "wof:name":"CH5 2BQ",
    "wof:placetype":"postalcode"
},
  "geometry": {"coordinates":[-3.01938810055312,53.19220821287794],"type":"Point"}
}