{
  "type": "Feature",
  "properties": {
    "date:inception_lower": "1980-01-01",
    "date:inception_upper": "1980-01-01",
    "iso:country": "GB",
    "wof:name": "CH5 2BQ",
    "wof:placetype": "postalcode"
  },
  "geometry": {"coordinates":[-3.019388,53.192208],"type":"Point"}
}
