{
  "type": "Feature",
  "properties": {
    "date:inception_lower": "2019-04-01",
    "date:inception_upper": "2019-04-01",
    "iso:country": "GB",
    "wof:name": "EH9 1AB",
    "wof:placetype": "postalcode"
  },
  "geometry": {"coordinates":[-3.175028,55.935324],"type":"Point"}
}
