{
  "type": "Feature",
  "properties": {
    "iso:country": "GB",
    "wof:name": "EH9 1AB",
    "wof:placetype": "postalcode"
  },
  "geometry": {"coordinates":[-3.175201,55.935223],"type":"Point"}
}
