{
  "type": "Feature",
  "properties": {
    "iso:country":"GB",
    "wof:name":"W1K 7FR",
    "wof:placetype":"postalcode"
},
  "geometry": {"coordinates":[-0.15645160582392,51.51220538853903],"type":"Point"}
}