{
  "type": "Feature",
  "properties": {
    "iso:country": "GB",
    "wof:name": "TR19 7EQ",
    "wof:placetype": "postalcode"
  },
  "geometry": {"coordinates":[-5.668118,50.153856],"type":"Point"}
}
