{
  "type": "Feature",
  "properties": {
    "date:inception_lower":"1980-01-01",
    "date:inception_upper":"1980-01-31",
    "iso:country":"GB",
    "wof:name":"TR19 7EQ",
    "wof:placetype":"postalcode"
},
  "geometry": {"coordinates":[-5.668118,50.153856],"type":"Point"}
}