{
  "type": "Feature",
  "properties": {
    "iso:country":"GB",
    "wof:name":"TR19 7EQ",
    "wof:placetype":"postalcode"
},
  "geometry": {"coordinates":[-5.66811833789738,50.15385591659364],"type":"Point"}
}