{
  "type": "Feature",
  "properties": {
    "iso:country":"GB",
    "wof:name":"LA1 5DA",
    "wof:placetype":"postalcode"
},
  "geometry": {"coordinates":[-2.81990023627696,54.06009470805978],"type":"Point"}
}