{
  "type": "Feature",
  "properties": {
    "iso:country": "GB",
    "wof:name": "LA1 5DA",
    "wof:placetype": "postalcode"
  },
  "geometry": {"coordinates":[-2.8199,54.060095],"type":"Point"}
}
