{
  "type": "Feature",
  "properties": {
    "date:inception_lower": "1980-01-01",
    "date:inception_upper": "1980-01-01",
    "iso:country": "GB",
    "wof:name": "LA1 5DA",
    "wof:placetype": "postalcode"
  },
  "geometry": {"coordinates":[-2.8199,54.060095],"type":"Point"}
}
