{
  "type": "Feature",
  "properties": {
    "iso:country":"GB",
    "wof:name":"GL11 5RY",
    "wof:placetype":"postalcode"
},
  "geometry": {"coordinates":[-2.36506642714859,51.69494098004132],"type":"Point"}
}