{
  "type": "Feature",
  "properties": {
    "date:inception_lower": "1980-01-01",
    "date:inception_upper": "1980-01-01",
    "iso:country": "GB",
    "wof:name": "CV34 5YZ",
    "wof:placetype": "postalcode"
  },
  "geometry": {"coordinates":[-1.58165,52.295833],"type":"Point"}
}
