{
  "type": "Feature",
  "properties": {
    "iso:country":"GB",
    "wof:name":"DE6 2JJ",
    "wof:placetype":"postalcode"
},
  "geometry": {"coordinates":[-1.76722772689115,53.00033837224228],"type":"Point"}
}