{
  "type": "Feature",
  "properties": {
    "iso:country":"GB",
    "wof:name":"CW1 5PR",
    "wof:placetype":"postalcode"
},
  "geometry": {"coordinates":[-2.39572783615036,53.09916453552096],"type":"Point"}
}