{
  "type": "Feature",
  "properties": {
    "iso:country": "GB",
    "wof:name": "CM0 7LD",
    "wof:placetype": "postalcode"
  },
  "geometry": {"coordinates":[0.828842,51.679843],"type":"Point"}
}
