{
  "type": "Feature",
  "properties": {
    "iso:country":"GB",
    "wof:name":"CM0 7LD",
    "wof:placetype":"postalcode"
},
  "geometry": {"coordinates":[0.82884162917741,51.67984254597351],"type":"Point"}
}