{
  "type": "Feature",
  "properties": {
    "date:inception_lower": "1980-01-01",
    "date:inception_upper": "1980-01-01",
    "iso:country": "GB",
    "wof:name": "CM0 7LD",
    "wof:placetype": "postalcode"
  },
  "geometry": {"coordinates":[0.828842,51.679843],"type":"Point"}
}
