{
  "type": "Feature",
  "properties": {
    "date:inception_lower": "1980-01-01",
    "date:inception_upper": "1980-01-01",
    "iso:country": "GB",
    "wof:name": "EX22 7XT",
    "wof:placetype": "postalcode"
  },
  "geometry": {"coordinates":[-4.312211,50.927787],"type":"Point"}
}
