{
  "type": "Feature",
  "properties": {
    "iso:country":"GB",
    "wof:name":"EX22 7XT",
    "wof:placetype":"postalcode"
},
  "geometry": {"coordinates":[-4.3122115304731,50.9277868198941],"type":"Point"}
}