{
  "type": "Feature",
  "properties": {
    "iso:country":"GB",
    "wof:name":"B92 9LB",
    "wof:placetype":"postalcode"
},
  "geometry": {"coordinates":[-1.76337558513894,52.43208807631564],"type":"Point"}
}