{
  "type": "Feature",
  "properties": {
    "iso:country": "GB",
    "wof:name": "KT13 0UX",
    "wof:placetype": "postalcode"
  },
  "geometry": {"coordinates":[-0.464155,51.347295],"type":"Point"}
}
