{
  "type": "Feature",
  "properties": {
    "iso:country":"GB",
    "wof:name":"SW6 5PQ",
    "wof:placetype":"postalcode"
},
  "geometry": {"coordinates":[-0.19897062849731,51.47736373593407],"type":"Point"}
}