{
  "type": "Feature",
  "properties": {
    "iso:country":"GB",
    "wof:name":"LE67 9WJ",
    "wof:placetype":"postalcode"
},
  "geometry": {"coordinates":[-1.27759732085589,52.68502259731093],"type":"Point"}
}