{
  "type": "Feature",
  "properties": {
    "date:inception_lower": "1992-08-01",
    "date:inception_upper": "1992-08-01",
    "iso:country": "GB",
    "wof:name": "LE67 9WJ",
    "wof:placetype": "postalcode"
  },
  "geometry": {"coordinates":[-1.277597,52.685023],"type":"Point"}
}
