{
  "type": "Feature",
  "properties": {
    "iso:country":"GB",
    "wof:name":"L31 1AJ",
    "wof:placetype":"postalcode"
},
  "geometry": {"coordinates":[-2.90750009946915,53.49884580773676],"type":"Point"}
}