{
  "type": "Feature",
  "properties": {
    "date:inception_lower":"2015-04-01",
    "date:inception_upper":"2015-04-30",
    "iso:country":"GB",
    "wof:name":"DN18 5FQ",
    "wof:placetype":"postalcode"
},
  "geometry": {"coordinates":[-0.442027,53.685663],"type":"Point"}
}