{
  "type": "Feature",
  "properties": {
    "iso:country":"GB",
    "wof:name":"DN18 5FQ",
    "wof:placetype":"postalcode"
},
  "geometry": {"coordinates":[-0.44202730451471,53.68566263473371],"type":"Point"}
}