{
  "type": "Feature",
  "properties": {
    "date:inception_lower": "1980-01-01",
    "date:inception_upper": "1980-01-01",
    "iso:country": "GB",
    "wof:name": "DE4 3HD",
    "wof:placetype": "postalcode"
  },
  "geometry": {"coordinates":[-1.551934,53.145149],"type":"Point"}
}
