{
  "type": "Feature",
  "properties": {
    "iso:country":"GB",
    "wof:name":"DE4 3HD",
    "wof:placetype":"postalcode"
},
  "geometry": {"coordinates":[-1.55193449955785,53.14514869396012],"type":"Point"}
}