{
  "type": "Feature",
  "properties": {
    "iso:country": "GB",
    "wof:name": "DE4 3HD",
    "wof:placetype": "postalcode"
  },
  "geometry": {"coordinates":[-1.551934,53.145149],"type":"Point"}
}
