{
  "type": "Feature",
  "properties": {
    "iso:country": "GB",
    "wof:name": "BS4 3EA",
    "wof:placetype": "postalcode"
  },
  "geometry": {"coordinates":[-2.566994,51.443116],"type":"Point"}
}
