{
  "type": "Feature",
  "properties": {
    "iso:country":"GB",
    "wof:name":"M26 3WQ",
    "wof:placetype":"postalcode"
},
  "geometry": {"coordinates":[-2.32823317754473,53.56179383005477],"type":"Point"}
}