{
  "type": "Feature",
  "properties": {
    "iso:country": "GB",
    "wof:name": "M26 3WQ",
    "wof:placetype": "postalcode"
  },
  "geometry": {"coordinates":[-2.328233,53.561794],"type":"Point"}
}
