{
  "type": "Feature",
  "properties": {
    "iso:country":"GB",
    "wof:name":"NE24 1SD",
    "wof:placetype":"postalcode"
},
  "geometry": {"coordinates":[-1.51049643718698,55.13566393259416],"type":"Point"}
}