{
  "type": "Feature",
  "properties": {
    "iso:country":"GB",
    "wof:name":"IP25 6PS",
    "wof:placetype":"postalcode"
},
  "geometry": {"coordinates":[0.84399035023136,52.55544440983801],"type":"Point"}
}