{
  "type": "Feature",
  "properties": {
    "date:inception_lower": "2016-07-01",
    "date:inception_upper": "2016-07-01",
    "iso:country": "GB",
    "wof:name": "LE15 6JL",
    "wof:placetype": "postalcode"
  },
  "geometry": {"coordinates":[-0.726451,52.663204],"type":"Point"}
}
