{
  "type": "Feature",
  "properties": {
    "iso:country": "GB",
    "wof:name": "DL10 7HA",
    "wof:placetype": "postalcode"
  },
  "geometry": {"coordinates":[-1.676253,54.395913],"type":"Point"}
}
