{
  "type": "Feature",
  "properties": {
    "date:inception_lower": "1980-01-01",
    "date:inception_upper": "1980-01-01",
    "iso:country": "GB",
    "wof:name": "DL10 7HA",
    "wof:placetype": "postalcode"
  },
  "geometry": {"coordinates":[-1.676253,54.395913],"type":"Point"}
}
