{
  "type": "Feature",
  "properties": {
    "iso:country":"GB",
    "wof:name":"NN18 8QY",
    "wof:placetype":"postalcode"
},
  "geometry": {"coordinates":[-0.7042536612769,52.46387854086203],"type":"Point"}
}