{
  "type": "Feature",
  "properties": {
    "iso:country":"GB",
    "wof:name":"SS0 8PX",
    "wof:placetype":"postalcode"
},
  "geometry": {"coordinates":[0.67070635314968,51.53918249389572],"type":"Point"}
}