{
  "type": "Feature",
  "properties": {
    "iso:country": "GB",
    "wof:name": "TN33 9JU",
    "wof:placetype": "postalcode"
  },
  "geometry": {"coordinates":[0.412741,50.888388],"type":"Point"}
}
