{
  "type": "Feature",
  "properties": {
    "iso:country":"GB",
    "wof:name":"WR5 3NU",
    "wof:placetype":"postalcode"
},
  "geometry": {"coordinates":[-2.21352111397661,52.14031585689374],"type":"Point"}
}