{
  "type": "Feature",
  "properties": {
    "iso:country":"GB",
    "wof:name":"LS7 4JR",
    "wof:placetype":"postalcode"
},
  "geometry": {"coordinates":[-1.5268606768382,53.82552745574674],"type":"Point"}
}