{
  "type": "Feature",
  "properties": {
    "date:inception_lower":"2005-07-01",
    "date:inception_upper":"2005-07-31",
    "iso:country":"GB",
    "wof:name":"W1F 0TH",
    "wof:placetype":"postalcode"
},
  "geometry": {"coordinates":[-0.13382,51.513394],"type":"Point"}
}