{
  "type": "Feature",
  "properties": {
    "iso:country": "GB",
    "wof:name": "W1F 0TH",
    "wof:placetype": "postalcode"
  },
  "geometry": {"coordinates":[-0.13382,51.513394],"type":"Point"}
}
