{
  "type": "Feature",
  "properties": {
    "iso:country": "GB",
    "wof:name": "CF5 3NY",
    "wof:placetype": "postalcode"
  },
  "geometry": {"coordinates":[-3.235093,51.496222],"type":"Point"}
}
