{
  "type": "Feature",
  "properties": {
    "iso:country":"GB",
    "wof:name":"CB1 2LS",
    "wof:placetype":"postalcode"
},
  "geometry": {"coordinates":[0.13851065451657,52.20505262911334],"type":"Point"}
}