{
  "type": "Feature",
  "properties": {
    "date:inception_lower": "1980-01-01",
    "date:inception_upper": "1980-01-01",
    "iso:country": "GB",
    "wof:name": "TS13 4JZ",
    "wof:placetype": "postalcode"
  },
  "geometry": {"coordinates":[-0.882206,54.554631],"type":"Point"}
}
