{
  "type": "Feature",
  "properties": {
    "iso:country":"GB",
    "wof:name":"TS13 4JZ",
    "wof:placetype":"postalcode"
},
  "geometry": {"coordinates":[-0.88220596096252,54.55463126515528],"type":"Point"}
}