{
  "type": "Feature",
  "properties": {
    "iso:country": "GB",
    "wof:name": "WA16 9QT",
    "wof:placetype": "postalcode"
  },
  "geometry": {"coordinates":[-2.380056,53.262626],"type":"Point"}
}
