{
  "type": "Feature",
  "properties": {
    "date:inception_lower": "1996-06-01",
    "date:inception_upper": "1996-06-01",
    "iso:country": "GB",
    "wof:name": "AB15 8PE",
    "wof:placetype": "postalcode"
  },
  "geometry": {"coordinates":[-2.218638,57.152112],"type":"Point"}
}
