{
  "type": "Feature",
  "properties": {
    "date:inception_lower": "1980-01-01",
    "date:inception_upper": "1980-01-01",
    "iso:country": "GB",
    "wof:name": "BR8 7TT",
    "wof:placetype": "postalcode"
  },
  "geometry": {"coordinates":[0.165211,51.405789],"type":"Point"}
}
