{
  "type": "Feature",
  "properties": {
    "iso:country":"GB",
    "wof:name":"BR8 7TT",
    "wof:placetype":"postalcode"
},
  "geometry": {"coordinates":[0.16521113465892,51.40578882584845],"type":"Point"}
}