{
  "type": "Feature",
  "properties": {
    "iso:country":"GB",
    "wof:name":"SL6 4RW",
    "wof:placetype":"postalcode"
},
  "geometry": {"coordinates":[-0.74400858208264,51.51752199529161],"type":"Point"}
}