{
  "type": "Feature",
  "properties": {
    "date:inception_lower": "1984-10-01",
    "date:inception_upper": "1984-10-01",
    "iso:country": "GB",
    "wof:name": "WA8 7XZ",
    "wof:placetype": "postalcode"
  },
  "geometry": {"coordinates":[-2.730168,53.361707],"type":"Point"}
}
