{
  "type": "Feature",
  "properties": {
    "iso:country": "GB",
    "wof:name": "WA8 7XZ",
    "wof:placetype": "postalcode"
  },
  "geometry": {"coordinates":[-2.730168,53.361707],"type":"Point"}
}
