{
  "type": "Feature",
  "properties": {
    "iso:country":"GB",
    "wof:name":"ML4 3JX",
    "wof:placetype":"postalcode"
},
  "geometry": {"coordinates":[-4.04912695031334,55.82098574454267],"type":"Point"}
}