{
  "type": "Feature",
  "properties": {
    "iso:country": "GB",
    "wof:name": "CT14 7AD",
    "wof:placetype": "postalcode"
  },
  "geometry": {"coordinates":[1.402955,51.22242],"type":"Point"}
}
