{
  "type": "Feature",
  "properties": {
    "iso:country":"GB",
    "wof:name":"EX9 7AN",
    "wof:placetype":"postalcode"
},
  "geometry": {"coordinates":[-3.35208466001924,50.63078885377872],"type":"Point"}
}