{
  "type": "Feature",
  "properties": {
    "date:inception_lower": "1980-01-01",
    "date:inception_upper": "1980-01-01",
    "iso:country": "GB",
    "wof:name": "EX9 7AN",
    "wof:placetype": "postalcode"
  },
  "geometry": {"coordinates":[-3.352085,50.630789],"type":"Point"}
}
