{
  "type": "Feature",
  "properties": {
    "iso:country": "GB",
    "wof:name": "EX9 7AN",
    "wof:placetype": "postalcode"
  },
  "geometry": {"coordinates":[-3.352085,50.630789],"type":"Point"}
}
