{
  "type": "Feature",
  "properties": {
    "iso:country":"GB",
    "wof:name":"N11 3DY",
    "wof:placetype":"postalcode"
},
  "geometry": {"coordinates":[-0.15053939782381,51.61469790358112],"type":"Point"}
}