{
  "type": "Feature",
  "properties": {
    "iso:country":"GB",
    "wof:name":"LS4 2LE",
    "wof:placetype":"postalcode"
},
  "geometry": {"coordinates":[-1.58034380731207,53.80953896107281],"type":"Point"}
}