{
  "type": "Feature",
  "properties": {
    "iso:country":"GB",
    "wof:name":"TN35 4DL",
    "wof:placetype":"postalcode"
},
  "geometry": {"coordinates":[0.66775695119072,50.8785050922204],"type":"Point"}
}