{
  "type": "Feature",
  "properties": {
    "iso:country": "GB",
    "wof:name": "SE26 4LN",
    "wof:placetype": "postalcode"
  },
  "geometry": {"coordinates":[-0.056011,51.431709],"type":"Point"}
}
