{
  "type": "Feature",
  "properties": {
    "iso:country":"GB",
    "wof:name":"KA7 1SZ",
    "wof:placetype":"postalcode"
},
  "geometry": {"coordinates":[-4.62769866396642,55.4582002410828],"type":"Point"}
}