{
  "type": "Feature",
  "properties": {
    "iso:country": "GB",
    "wof:name": "KA7 1SZ",
    "wof:placetype": "postalcode"
  },
  "geometry": {"coordinates":[-4.627699,55.4582],"type":"Point"}
}
