{
  "type": "Feature",
  "properties": {
    "iso:country":"GB",
    "wof:name":"HA2 7NS",
    "wof:placetype":"postalcode"
},
  "geometry": {"coordinates":[-0.36905462937927,51.5822562738103],"type":"Point"}
}