{
  "type": "Feature",
  "properties": {
    "iso:country":"GB",
    "wof:name":"IP28 7NA",
    "wof:placetype":"postalcode"
},
  "geometry": {"coordinates":[0.51619439049789,52.34995094000281],"type":"Point"}
}