{
  "type": "Feature",
  "properties": {
    "iso:country":"GB",
    "wof:name":"SA33 4JY",
    "wof:placetype":"postalcode"
},
  "geometry": {"coordinates":[-4.53863475318303,51.84546322140812],"type":"Point"}
}