{
  "type": "Feature",
  "properties": {
    "iso:country":"GB",
    "wof:name":"EH32 0HN",
    "wof:placetype":"postalcode"
},
  "geometry": {"coordinates":[-2.96065686317387,55.97047743224011],"type":"Point"}
}