{
  "type": "Feature",
  "properties": {
    "iso:country":"GB",
    "wof:name":"WV7 3HN",
    "wof:placetype":"postalcode"
},
  "geometry": {"coordinates":[-2.28696801638639,52.63727788997177],"type":"Point"}
}