{
  "type": "Feature",
  "properties": {
    "iso:country":"GB",
    "wof:name":"TW13 6RL",
    "wof:placetype":"postalcode"
},
  "geometry": {"coordinates":[-0.39340105379735,51.43074899990705],"type":"Point"}
}