{
  "type": "Feature",
  "properties": {
    "iso:country":"GB",
    "wof:name":"B20 3WD",
    "wof:placetype":"postalcode"
},
  "geometry": {"coordinates":[-1.90333793808213,52.51309584389154],"type":"Point"}
}