{
  "type": "Feature",
  "properties": {
    "date:inception_lower": "2014-12-01",
    "date:inception_upper": "2014-12-01",
    "iso:country": "GB",
    "wof:name": "B20 3WD",
    "wof:placetype": "postalcode"
  },
  "geometry": {"coordinates":[-1.902788,52.513191],"type":"Point"}
}
