{
  "type": "Feature",
  "properties": {
    "date:inception_lower": "1998-06-01",
    "date:inception_upper": "1998-06-01",
    "iso:country": "GB",
    "wof:name": "BA22 8ET",
    "wof:placetype": "postalcode"
  },
  "geometry": {"coordinates":[-2.679375,50.946534],"type":"Point"}
}
