{
  "type": "Feature",
  "properties": {
    "iso:country": "GB",
    "wof:name": "BA22 8ET",
    "wof:placetype": "postalcode"
  },
  "geometry": {"coordinates":[-2.679375,50.946534],"type":"Point"}
}
