{
  "type": "Feature",
  "properties": {
    "iso:country":"GB",
    "wof:name":"WD3 6EE",
    "wof:placetype":"postalcode"
},
  "geometry": {"coordinates":[-0.52565207336991,51.67287149695211],"type":"Point"}
}