{
  "type": "Feature",
  "properties": {
    "iso:country": "GB",
    "wof:name": "WD3 6EE",
    "wof:placetype": "postalcode"
  },
  "geometry": {"coordinates":[-0.525673,51.672894],"type":"Point"}
}
