{
  "type": "Feature",
  "properties": {
    "iso:country":"GB",
    "wof:name":"SG8 7SZ",
    "wof:placetype":"postalcode"
},
  "geometry": {"coordinates":[0.07176996474203,52.09290946361407],"type":"Point"}
}