{
  "type": "Feature",
  "properties": {
    "date:inception_lower": "1980-01-01",
    "date:inception_upper": "1980-01-01",
    "iso:country": "GB",
    "wof:name": "SG8 7SZ",
    "wof:placetype": "postalcode"
  },
  "geometry": {"coordinates":[0.07177,52.092909],"type":"Point"}
}
