{
  "type": "Feature",
  "properties": {
    "date:inception_lower": "1980-01-01",
    "date:inception_upper": "1980-01-01",
    "iso:country": "GB",
    "wof:name": "DN34 4PG",
    "wof:placetype": "postalcode"
  },
  "geometry": {"coordinates":[-0.100171,53.563322],"type":"Point"}
}
