{
  "type": "Feature",
  "properties": {
    "date:inception_lower": "1980-01-01",
    "date:inception_upper": "1980-01-01",
    "iso:country": "GB",
    "wof:name": "LL12 9RS",
    "wof:placetype": "postalcode"
  },
  "geometry": {"coordinates":[-3.020331,53.127909],"type":"Point"}
}
