{
  "type": "Feature",
  "properties": {
    "iso:country":"GB",
    "wof:name":"SM7 3HD",
    "wof:placetype":"postalcode"
},
  "geometry": {"coordinates":[-0.17876130909646,51.32440186826268],"type":"Point"}
}