{
  "type": "Feature",
  "properties": {
    "date:inception_lower": "2024-09-01",
    "date:inception_upper": "2024-09-01",
    "iso:country": "GB",
    "wof:name": "NE23 8GP",
    "wof:placetype": "postalcode"
  },
  "geometry": {"coordinates":[-1.607912,55.08331],"type":"Point"}
}
