{
  "type": "Feature",
  "properties": {
    "iso:country":"GB",
    "wof:name":"E17 8DL",
    "wof:placetype":"postalcode"
},
  "geometry": {"coordinates":[-0.02974652922951,51.57789552304622],"type":"Point"}
}