{
  "type": "Feature",
  "properties": {
    "date:inception_lower": "1999-06-01",
    "date:inception_upper": "1999-06-01",
    "iso:country": "GB",
    "wof:name": "CH42 9NG",
    "wof:placetype": "postalcode"
  },
  "geometry": {"coordinates":[-3.035561,53.381083],"type":"Point"}
}
