{
  "type": "Feature",
  "properties": {
    "iso:country":"GB",
    "wof:name":"CH42 9NG",
    "wof:placetype":"postalcode"
},
  "geometry": {"coordinates":[-3.0355611920884,53.38108348953789],"type":"Point"}
}