{
  "type": "Feature",
  "properties": {
    "iso:country":"GB",
    "wof:name":"W2 3JN",
    "wof:placetype":"postalcode"
},
  "geometry": {"coordinates":[-0.18685720979897,51.51264339143996],"type":"Point"}
}