{
  "type": "Feature",
  "properties": {
    "date:inception_lower":"1980-01-01",
    "date:inception_upper":"1980-01-31",
    "iso:country":"GB",
    "wof:name":"W2 3JN",
    "wof:placetype":"postalcode"
},
  "geometry": {"coordinates":[-0.186857,51.512643],"type":"Point"}
}