{
  "type": "Feature",
  "properties": {
    "iso:country":"GB",
    "wof:name":"LS29 8DQ",
    "wof:placetype":"postalcode"
},
  "geometry": {"coordinates":[-1.8232533271065,53.92657107927025],"type":"Point"}
}