{
  "type": "Feature",
  "properties": {
    "iso:country":"GB",
    "wof:name":"ML5 2HB",
    "wof:placetype":"postalcode"
},
  "geometry": {"coordinates":[-4.03990851773442,55.868401711699],"type":"Point"}
}