{
  "type": "Feature",
  "properties": {
    "iso:country":"GB",
    "wof:name":"LL19 8EE",
    "wof:placetype":"postalcode"
},
  "geometry": {"coordinates":[-3.41454164809858,53.32623230511515],"type":"Point"}
}