{
  "type": "Feature",
  "properties": {
    "date:inception_lower": "1996-06-01",
    "date:inception_upper": "1996-06-01",
    "iso:country": "GB",
    "wof:name": "BD17 6DG",
    "wof:placetype": "postalcode"
  },
  "geometry": {"coordinates":[-1.756911,53.849133],"type":"Point"}
}
