{
  "type": "Feature",
  "properties": {
    "iso:country":"GB",
    "wof:name":"OL1 3RE",
    "wof:placetype":"postalcode"
},
  "geometry": {"coordinates":[-2.10565406005282,53.54875144649559],"type":"Point"}
}