{
  "type": "Feature",
  "properties": {
    "date:inception_lower": "1980-01-01",
    "date:inception_upper": "1980-01-01",
    "iso:country": "GB",
    "wof:name": "DD5 3DQ",
    "wof:placetype": "postalcode"
  },
  "geometry": {"coordinates":[-2.875839,56.476537],"type":"Point"}
}
