{
  "type": "Feature",
  "properties": {
    "iso:country":"GB",
    "wof:name":"SN14 7JH",
    "wof:placetype":"postalcode"
},
  "geometry": {"coordinates":[-2.28383715078475,51.49268940598142],"type":"Point"}
}