{
  "type": "Feature",
  "properties": {
    "iso:country": "GB",
    "wof:name": "SN14 7JH",
    "wof:placetype": "postalcode"
  },
  "geometry": {"coordinates":[-2.283837,51.492689],"type":"Point"}
}
