{
  "type": "Feature",
  "properties": {
    "iso:country": "GB",
    "wof:name": "B98 8BP",
    "wof:placetype": "postalcode"
  },
  "geometry": {"coordinates":[-1.939945,52.307379],"type":"Point"}
}
