{
  "type": "Feature",
  "properties": {
    "iso:country":"GB",
    "wof:name":"B98 8BP",
    "wof:placetype":"postalcode"
},
  "geometry": {"coordinates":[-1.94005623440444,52.30741835936509],"type":"Point"}
}