{
  "type": "Feature",
  "properties": {
    "date:inception_lower": "1985-10-01",
    "date:inception_upper": "1985-10-01",
    "iso:country": "GB",
    "wof:name": "B98 8BP",
    "wof:placetype": "postalcode"
  },
  "geometry": {"coordinates":[-1.940106,52.307424],"type":"Point"}
}
