{
  "type": "Feature",
  "properties": {
    "iso:country":"GB",
    "wof:name":"RG22 6SU",
    "wof:placetype":"postalcode"
},
  "geometry": {"coordinates":[-1.1285019877715,51.2562603242711],"type":"Point"}
}