{
  "type": "Feature",
  "properties": {
    "iso:country": "GB",
    "wof:name": "RG22 6SU",
    "wof:placetype": "postalcode"
  },
  "geometry": {"coordinates":[-1.128502,51.25626],"type":"Point"}
}
