{
  "type": "Feature",
  "properties": {
    "iso:country":"GB",
    "wof:name":"PH49 4JA",
    "wof:placetype":"postalcode"
},
  "geometry": {"coordinates":[-5.02569194268554,56.58993862790465],"type":"Point"}
}