{
  "type": "Feature",
  "properties": {
    "date:inception_lower":"2000-12-01",
    "date:inception_upper":"2000-12-31",
    "iso:country":"GB",
    "wof:name":"PH49 4JA",
    "wof:placetype":"postalcode"
},
  "geometry": {"coordinates":[-5.023981,56.587493],"type":"Point"}
}