{
  "type": "Feature",
  "properties": {
    "iso:country":"GB",
    "wof:name":"LE9 7FZ",
    "wof:placetype":"postalcode"
},
  "geometry": {"coordinates":[-1.31411271172285,52.57217345424254],"type":"Point"}
}