{
  "type": "Feature",
  "properties": {
    "iso:country":"GB",
    "wof:name":"LS27 8RP",
    "wof:placetype":"postalcode"
},
  "geometry": {"coordinates":[-1.59110635727127,53.74594068477425],"type":"Point"}
}