{
  "type": "Feature",
  "properties": {
    "date:inception_lower":"1980-01-01",
    "date:inception_upper":"1980-01-31",
    "iso:country":"GB",
    "wof:name":"LS27 8RP",
    "wof:placetype":"postalcode"
},
  "geometry": {"coordinates":[-1.591106,53.745941],"type":"Point"}
}