{
  "type": "Feature",
  "properties": {
    "iso:country":"GB",
    "wof:name":"HR2 7EA",
    "wof:placetype":"postalcode"
},
  "geometry": {"coordinates":[-2.73329607677939,52.03607558011311],"type":"Point"}
}