{
  "type": "Feature",
  "properties": {
    "iso:country":"GB",
    "wof:name":"B60 3GL",
    "wof:placetype":"postalcode"
},
  "geometry": {"coordinates":[-2.05288636973893,52.31850641192899],"type":"Point"}
}