{
  "type": "Feature",
  "properties": {
    "date:inception_lower": "2005-06-01",
    "date:inception_upper": "2005-06-01",
    "iso:country": "GB",
    "wof:name": "B60 3GL",
    "wof:placetype": "postalcode"
  },
  "geometry": {"coordinates":[-2.052886,52.318506],"type":"Point"}
}
