{
  "type": "Feature",
  "properties": {
    "iso:country":"GB",
    "wof:name":"B62 9HB",
    "wof:placetype":"postalcode"
},
  "geometry": {"coordinates":[-2.03085618800031,52.47162446065968],"type":"Point"}
}