{
  "type": "Feature",
  "properties": {
    "iso:country":"GB",
    "wof:name":"DD2 5AJ",
    "wof:placetype":"postalcode"
},
  "geometry": {"coordinates":[-3.06017151287133,56.4570232211882],"type":"Point"}
}