{
  "type": "Feature",
  "properties": {
    "iso:country": "GB",
    "wof:name": "SY2 6LW",
    "wof:placetype": "postalcode"
  },
  "geometry": {"coordinates":[-2.728342,52.693263],"type":"Point"}
}
