{
  "type": "Feature",
  "properties": {
    "iso:country":"GB",
    "wof:name":"LE11 3QD",
    "wof:placetype":"postalcode"
},
  "geometry": {"coordinates":[-1.2260464878114,52.75843173937883],"type":"Point"}
}