{
  "type": "Feature",
  "properties": {
    "iso:country":"GB",
    "wof:name":"MK42 0SP",
    "wof:placetype":"postalcode"
},
  "geometry": {"coordinates":[-0.44645573695922,52.12002997815789],"type":"Point"}
}