{
  "type": "Feature",
  "properties": {
    "date:inception_lower": "2016-10-01",
    "date:inception_upper": "2016-10-01",
    "iso:country": "GB",
    "wof:name": "EH28 8TF",
    "wof:placetype": "postalcode"
  },
  "geometry": {"coordinates":[-3.365408,55.923898],"type":"Point"}
}
