{
  "type": "Feature",
  "properties": {
    "date:inception_lower":"2000-12-01",
    "date:inception_upper":"2000-12-31",
    "iso:country":"GB",
    "wof:name":"HP2 4FB",
    "wof:placetype":"postalcode"
},
  "geometry": {"coordinates":[-0.422546,51.749186],"type":"Point"}
}