{
  "type": "Feature",
  "properties": {
    "iso:country": "GB",
    "wof:name": "NN3 9BH",
    "wof:placetype": "postalcode"
  },
  "geometry": {"coordinates":[-0.814104,52.254389],"type":"Point"}
}
