{
  "type": "Feature",
  "properties": {
    "iso:country":"GB",
    "wof:name":"NN3 9BH",
    "wof:placetype":"postalcode"
},
  "geometry": {"coordinates":[-0.81410400813287,52.25438922438651],"type":"Point"}
}