{
  "type": "Feature",
  "properties": {
    "iso:country":"GB",
    "wof:name":"OL8 2PY",
    "wof:placetype":"postalcode"
},
  "geometry": {"coordinates":[-2.10010915292055,53.52070356646579],"type":"Point"}
}