{
  "type": "Feature",
  "properties": {
    "iso:country":"GB",
    "wof:name":"YO62 6UH",
    "wof:placetype":"postalcode"
},
  "geometry": {"coordinates":[-0.91062379188193,54.27858624095949],"type":"Point"}
}