{
  "type": "Feature",
  "properties": {
    "date:inception_lower":"1998-06-01",
    "date:inception_upper":"1998-06-30",
    "iso:country":"GB",
    "wof:name":"YO62 6UH",
    "wof:placetype":"postalcode"
},
  "geometry": {"coordinates":[-0.910636,54.278601],"type":"Point"}
}