{
  "type": "Feature",
  "properties": {
    "iso:country": "GB",
    "wof:name": "YO62 6UH",
    "wof:placetype": "postalcode"
  },
  "geometry": {"coordinates":[-0.910636,54.278601],"type":"Point"}
}
