{
  "type": "Feature",
  "properties": {
    "iso:country":"GB",
    "wof:name":"BR5 2NB",
    "wof:placetype":"postalcode"
},
  "geometry": {"coordinates":[0.10751549262344,51.39497906614093],"type":"Point"}
}