{
  "type": "Feature",
  "properties": {
    "iso:country": "GB",
    "wof:name": "OX4 4XZ",
    "wof:placetype": "postalcode"
  },
  "geometry": {"coordinates":[-1.22954,51.7113],"type":"Point"}
}
