{
  "type": "Feature",
  "properties": {
    "iso:country": "GB",
    "wof:name": "EH17 7AR",
    "wof:placetype": "postalcode"
  },
  "geometry": {"coordinates":[-3.131388,55.907289],"type":"Point"}
}
