{
  "type": "Feature",
  "properties": {
    "iso:country":"GB",
    "wof:name":"SS6 9HS",
    "wof:placetype":"postalcode"
},
  "geometry": {"coordinates":[0.59699760301927,51.59263130903609],"type":"Point"}
}