{
  "type": "Feature",
  "properties": {
    "iso:country":"GB",
    "wof:name":"G64 3JP",
    "wof:placetype":"postalcode"
},
  "geometry": {"coordinates":[-4.21163776065283,55.92160516850878],"type":"Point"}
}