{
  "type": "Feature",
  "properties": {
    "iso:country": "GB",
    "wof:name": "B75 6JE",
    "wof:placetype": "postalcode"
  },
  "geometry": {"coordinates":[-1.798605,52.573259],"type":"Point"}
}
