{
  "type": "Feature",
  "properties": {
    "iso:country":"GB",
    "wof:name":"B75 6JE",
    "wof:placetype":"postalcode"
},
  "geometry": {"coordinates":[-1.7986055167142,52.57325929652263],"type":"Point"}
}