{
  "type": "Feature",
  "properties": {
    "iso:country":"GB",
    "wof:name":"E6 1HD",
    "wof:placetype":"postalcode"
},
  "geometry": {"coordinates":[0.04531130430983,51.53465143410256],"type":"Point"}
}