{
  "type": "Feature",
  "properties": {
    "date:inception_lower":"1980-01-01",
    "date:inception_upper":"1980-01-31",
    "iso:country":"GB",
    "wof:name":"CM21 9ES",
    "wof:placetype":"postalcode"
},
  "geometry": {"coordinates":[0.146741,51.810631],"type":"Point"}
}