{
  "type": "Feature",
  "properties": {
    "iso:country":"GB",
    "wof:name":"CM21 9ES",
    "wof:placetype":"postalcode"
},
  "geometry": {"coordinates":[0.14674145290646,51.81063088660861],"type":"Point"}
}