{
  "type": "Feature",
  "properties": {
    "iso:country": "GB",
    "wof:name": "DY8 5HT",
    "wof:placetype": "postalcode"
  },
  "geometry": {"coordinates":[-2.172375,52.473845],"type":"Point"}
}
