{
  "type": "Feature",
  "properties": {
    "date:inception_lower":"2002-09-01",
    "date:inception_upper":"2002-09-30",
    "iso:country":"GB",
    "wof:name":"LN1 2GR",
    "wof:placetype":"postalcode"
},
  "geometry": {"coordinates":[-0.669446,53.272243],"type":"Point"}
}