{
  "type": "Feature",
  "properties": {
    "iso:country":"GB",
    "wof:name":"LN1 2GR",
    "wof:placetype":"postalcode"
},
  "geometry": {"coordinates":[-0.66944594564649,53.27224345920739],"type":"Point"}
}