{
  "type": "Feature",
  "properties": {
    "iso:country": "GB",
    "wof:name": "LL11 3DA",
    "wof:placetype": "postalcode"
  },
  "geometry": {"coordinates":[-3.091608,53.058983],"type":"Point"}
}
