{
  "type": "Feature",
  "properties": {
    "iso:country":"GB",
    "wof:name":"LL11 3DA",
    "wof:placetype":"postalcode"
},
  "geometry": {"coordinates":[-3.09160773520845,53.05898314589592],"type":"Point"}
}