{
  "type": "Feature",
  "properties": {
    "iso:country":"GB",
    "wof:name":"EH41 3PU",
    "wof:placetype":"postalcode"
},
  "geometry": {"coordinates":[-2.79767847578282,55.95863876791469],"type":"Point"}
}