{
  "type": "Feature",
  "properties": {
    "iso:country": "GB",
    "wof:name": "EH41 3PU",
    "wof:placetype": "postalcode"
  },
  "geometry": {"coordinates":[-2.797678,55.958639],"type":"Point"}
}
