{
  "type": "Feature",
  "properties": {
    "date:inception_lower": "1980-01-01",
    "date:inception_upper": "1980-01-01",
    "iso:country": "GB",
    "wof:name": "ST2 8NW",
    "wof:placetype": "postalcode"
  },
  "geometry": {"coordinates":[-2.132952,53.031351],"type":"Point"}
}
