{
  "type": "Feature",
  "properties": {
    "iso:country": "GB",
    "wof:name": "YO61 4AB",
    "wof:placetype": "postalcode"
  },
  "geometry": {"coordinates":[-1.182982,54.187474],"type":"Point"}
}
