{
  "type": "Feature",
  "properties": {
    "date:inception_lower": "1980-01-01",
    "date:inception_upper": "1980-01-01",
    "iso:country": "GB",
    "wof:name": "L22 2BH",
    "wof:placetype": "postalcode"
  },
  "geometry": {"coordinates":[-3.036252,53.481995],"type":"Point"}
}
