{
  "type": "Feature",
  "properties": {
    "iso:country":"GB",
    "wof:name":"L22 2BH",
    "wof:placetype":"postalcode"
},
  "geometry": {"coordinates":[-3.03600272421492,53.4821692129997],"type":"Point"}
}