{
  "type": "Feature",
  "properties": {
    "iso:country":"GB",
    "wof:name":"BS26 2BZ",
    "wof:placetype":"postalcode"
},
  "geometry": {"coordinates":[-2.8222609454038,51.28679888378527],"type":"Point"}
}