{
  "type": "Feature",
  "properties": {
    "date:inception_lower":"1997-12-01",
    "date:inception_upper":"1997-12-31",
    "iso:country":"GB",
    "wof:name":"LL29 6AJ",
    "wof:placetype":"postalcode"
},
  "geometry": {"coordinates":[-3.742624,53.293689],"type":"Point"}
}