{
  "type": "Feature",
  "properties": {
    "iso:country":"GB",
    "wof:name":"LL29 6AJ",
    "wof:placetype":"postalcode"
},
  "geometry": {"coordinates":[-3.74262394997961,53.29368868736461],"type":"Point"}
}