{
  "type": "Feature",
  "properties": {
    "iso:country":"GB",
    "wof:name":"RH17 7BG",
    "wof:placetype":"postalcode"
},
  "geometry": {"coordinates":[-0.02150187097873,51.05298413467285],"type":"Point"}
}