{
  "type": "Feature",
  "properties": {
    "date:inception_lower":"1980-01-01",
    "date:inception_upper":"1980-01-31",
    "iso:country":"GB",
    "wof:name":"RH17 7BG",
    "wof:placetype":"postalcode"
},
  "geometry": {"coordinates":[-0.021502,51.052984],"type":"Point"}
}