{
  "type": "Feature",
  "properties": {
    "date:inception_lower": "1991-09-01",
    "date:inception_upper": "1991-09-01",
    "iso:country": "GB",
    "wof:name": "B31 2YS",
    "wof:placetype": "postalcode"
  },
  "geometry": {"coordinates":[-1.979747,52.400381],"type":"Point"}
}
