{
  "type": "Feature",
  "properties": {
    "iso:country":"GB",
    "wof:name":"EH4 2JX",
    "wof:placetype":"postalcode"
},
  "geometry": {"coordinates":[-3.23850699649359,55.95765590041482],"type":"Point"}
}