{
  "type": "Feature",
  "properties": {
    "iso:country":"GB",
    "wof:name":"WV9 5BZ",
    "wof:placetype":"postalcode"
},
  "geometry": {"coordinates":[-2.13441652184071,52.65813591020195],"type":"Point"}
}