{
  "type": "Feature",
  "properties": {
    "date:inception_lower": "2017-03-01",
    "date:inception_upper": "2017-03-01",
    "iso:country": "GB",
    "wof:name": "SN6 8FE",
    "wof:placetype": "postalcode"
  },
  "geometry": {"coordinates":[-1.6507,51.613486],"type":"Point"}
}
