{
  "type": "Feature",
  "properties": {
    "iso:country": "GB",
    "wof:name": "SN6 8FE",
    "wof:placetype": "postalcode"
  },
  "geometry": {"coordinates":[-1.6507,51.613486],"type":"Point"}
}
