{
  "type": "Feature",
  "properties": {
    "iso:country":"GB",
    "wof:name":"WS11 9RB",
    "wof:placetype":"postalcode"
},
  "geometry": {"coordinates":[-1.97262737693821,52.67288048206016],"type":"Point"}
}