{
  "type": "Feature",
  "properties": {
    "iso:country":"GB",
    "wof:name":"LN4 4AJ",
    "wof:placetype":"postalcode"
},
  "geometry": {"coordinates":[-0.23425205224124,53.00605862060387],"type":"Point"}
}