{
  "type": "Feature",
  "properties": {
    "iso:country":"GB",
    "wof:name":"RH12 3LW",
    "wof:placetype":"postalcode"
},
  "geometry": {"coordinates":[-0.3617905520834,51.07161304657456],"type":"Point"}
}