{
  "type": "Feature",
  "properties": {
    "iso:country":"GB",
    "wof:name":"SR7 8DY",
    "wof:placetype":"postalcode"
},
  "geometry": {"coordinates":[-1.36532179956018,54.83479625793447],"type":"Point"}
}