{
  "type": "Feature",
  "properties": {
    "iso:country": "GB",
    "wof:name": "WA2 8LF",
    "wof:placetype": "postalcode"
  },
  "geometry": {"coordinates":[-2.596927,53.430465],"type":"Point"}
}
