{
  "type": "Feature",
  "properties": {
    "iso:country":"GB",
    "wof:name":"WA2 8LF",
    "wof:placetype":"postalcode"
},
  "geometry": {"coordinates":[-2.59692737289531,53.43046507626016],"type":"Point"}
}