{
  "type": "Feature",
  "properties": {
    "iso:country": "GB",
    "wof:name": "IV32 7NF",
    "wof:placetype": "postalcode"
  },
  "geometry": {"coordinates":[-3.113901,57.664779],"type":"Point"}
}
