{
  "type": "Feature",
  "properties": {
    "iso:country":"GB",
    "wof:name":"DY5 1PQ",
    "wof:placetype":"postalcode"
},
  "geometry": {"coordinates":[-2.12595157908195,52.49071883566033],"type":"Point"}
}