{
  "type": "Feature",
  "properties": {
    "iso:country": "GB",
    "wof:name": "DY5 1PQ",
    "wof:placetype": "postalcode"
  },
  "geometry": {"coordinates":[-2.125952,52.490719],"type":"Point"}
}
