{
  "type": "Feature",
  "properties": {
    "date:inception_lower":"1980-01-01",
    "date:inception_upper":"1980-01-31",
    "iso:country":"GB",
    "wof:name":"LS5 3PS",
    "wof:placetype":"postalcode"
},
  "geometry": {"coordinates":[-1.616046,53.831149],"type":"Point"}
}