{
  "type": "Feature",
  "properties": {
    "iso:country": "GB",
    "wof:name": "LS5 3PS",
    "wof:placetype": "postalcode"
  },
  "geometry": {"coordinates":[-1.616046,53.831149],"type":"Point"}
}
