{
  "type": "Feature",
  "properties": {
    "iso:country": "GB",
    "wof:name": "TR20 8TY",
    "wof:placetype": "postalcode"
  },
  "geometry": {"coordinates":[-5.582893,50.116558],"type":"Point"}
}
