{
  "type": "Feature",
  "properties": {
    "iso:country": "GB",
    "wof:name": "EN8 0NU",
    "wof:placetype": "postalcode"
  },
  "geometry": {"coordinates":[-0.037536,51.714226],"type":"Point"}
}
