{
  "type": "Feature",
  "properties": {
    "iso:country":"GB",
    "wof:name":"SW14 7EZ",
    "wof:placetype":"postalcode"
},
  "geometry": {"coordinates":[-0.26903823866537,51.46913881686857],"type":"Point"}
}