{
  "type": "Feature",
  "properties": {
    "date:inception_lower": "1980-01-01",
    "date:inception_upper": "1980-01-01",
    "iso:country": "GB",
    "wof:name": "SW14 7EZ",
    "wof:placetype": "postalcode"
  },
  "geometry": {"coordinates":[-0.269038,51.469139],"type":"Point"}
}
