{
  "type": "Feature",
  "properties": {
    "iso:country":"GB",
    "wof:name":"SG9 9LR",
    "wof:placetype":"postalcode"
},
  "geometry": {"coordinates":[0.00550771925493,51.91531229568297],"type":"Point"}
}