{
  "type": "Feature",
  "properties": {
    "iso:country": "GB",
    "wof:name": "SR2 9TE",
    "wof:placetype": "postalcode"
  },
  "geometry": {"coordinates":[-1.371099,54.878688],"type":"Point"}
}
