{
  "type": "Feature",
  "properties": {
    "iso:country":"GB",
    "wof:name":"SA11 1NJ",
    "wof:placetype":"postalcode"
},
  "geometry": {"coordinates":[-3.81302925223057,51.65614595881341],"type":"Point"}
}