{
  "type": "Feature",
  "properties": {
    "iso:country": "GB",
    "wof:name": "SA11 1NJ",
    "wof:placetype": "postalcode"
  },
  "geometry": {"coordinates":[-3.813045,51.656151],"type":"Point"}
}
