{
  "type": "Feature",
  "properties": {
    "date:inception_lower": "2015-03-01",
    "date:inception_upper": "2015-03-01",
    "iso:country": "GB",
    "wof:name": "BB5 0TP",
    "wof:placetype": "postalcode"
  },
  "geometry": {"coordinates":[-2.380839,53.752134],"type":"Point"}
}
