{
  "type": "Feature",
  "properties": {
    "iso:country":"GB",
    "wof:name":"BB5 0TP",
    "wof:placetype":"postalcode"
},
  "geometry": {"coordinates":[-2.38083861348521,53.75213428750817],"type":"Point"}
}