{
  "type": "Feature",
  "properties": {
    "iso:country": "GB",
    "wof:name": "YO32 5BD",
    "wof:placetype": "postalcode"
  },
  "geometry": {"coordinates":[-1.03949,54.034627],"type":"Point"}
}
