{
  "type": "Feature",
  "properties": {
    "iso:country":"GB",
    "wof:name":"YO32 5BD",
    "wof:placetype":"postalcode"
},
  "geometry": {"coordinates":[-1.03952601175758,54.03461993393471],"type":"Point"}
}