{
  "type": "Feature",
  "properties": {
    "iso:country": "GB",
    "wof:name": "BH25 5GP",
    "wof:placetype": "postalcode"
  },
  "geometry": {"coordinates":[-1.641573,50.75947],"type":"Point"}
}
