{
  "type": "Feature",
  "properties": {
    "date:inception_lower":"1980-01-01",
    "date:inception_upper":"1980-01-31",
    "iso:country":"GB",
    "wof:name":"SP11 9PD",
    "wof:placetype":"postalcode"
},
  "geometry": {"coordinates":[-1.601917,51.252037],"type":"Point"}
}