{
  "type": "Feature",
  "properties": {
    "iso:country":"GB",
    "wof:name":"S65 4RE",
    "wof:placetype":"postalcode"
},
  "geometry": {"coordinates":[-1.26020291697756,53.43768654192215],"type":"Point"}
}