{
  "type": "Feature",
  "properties": {
    "date:inception_lower": "1980-01-01",
    "date:inception_upper": "1980-01-01",
    "iso:country": "GB",
    "wof:name": "MK43 0XE",
    "wof:placetype": "postalcode"
  },
  "geometry": {"coordinates":[-0.601355,52.011477],"type":"Point"}
}
