{
  "type": "Feature",
  "properties": {
    "date:inception_lower":"1980-01-01",
    "date:inception_upper":"1980-01-31",
    "iso:country":"GB",
    "wof:name":"MK43 0XE",
    "wof:placetype":"postalcode"
},
  "geometry": {"coordinates":[-0.601206,52.011592],"type":"Point"}
}