{
  "type": "Feature",
  "properties": {
    "iso:country":"GB",
    "wof:name":"SE18 1NQ",
    "wof:placetype":"postalcode"
},
  "geometry": {"coordinates":[0.08370190294577,51.48363412619734],"type":"Point"}
}