{
  "type": "Feature",
  "properties": {
    "iso:country":"GB",
    "wof:name":"BN23 7HT",
    "wof:placetype":"postalcode"
},
  "geometry": {"coordinates":[0.30962163989028,50.79892066346658],"type":"Point"}
}