{
  "type": "Feature",
  "properties": {
    "iso:country":"GB",
    "wof:name":"KT1 3RN",
    "wof:placetype":"postalcode"
},
  "geometry": {"coordinates":[-0.28034459107886,51.41080026814687],"type":"Point"}
}