{
  "type": "Feature",
  "properties": {
    "iso:country":"GB",
    "wof:name":"HU15 1FE",
    "wof:placetype":"postalcode"
},
  "geometry": {"coordinates":[-0.56356284870596,53.73418490088199],"type":"Point"}
}