{
  "type": "Feature",
  "properties": {
    "iso:country":"GB",
    "wof:name":"SE23 2QX",
    "wof:placetype":"postalcode"
},
  "geometry": {"coordinates":[-0.04192044835169,51.43353373178871],"type":"Point"}
}