{
  "type": "Feature",
  "properties": {
    "iso:country":"GB",
    "wof:name":"W1F 7AE",
    "wof:placetype":"postalcode"
},
  "geometry": {"coordinates":[-0.13655127832174,51.5135635105132],"type":"Point"}
}