{
  "type": "Feature",
  "properties": {
    "date:inception_lower": "1980-01-01",
    "date:inception_upper": "1980-01-01",
    "iso:country": "GB",
    "wof:name": "LL40 1TN",
    "wof:placetype": "postalcode"
  },
  "geometry": {"coordinates":[-3.934188,52.716795],"type":"Point"}
}
