{
  "type": "Feature",
  "properties": {
    "iso:country": "GB",
    "wof:name": "WV13 3ES",
    "wof:placetype": "postalcode"
  },
  "geometry": {"coordinates":[-2.065097,52.580253],"type":"Point"}
}
