{
  "type": "Feature",
  "properties": {
    "iso:country":"GB",
    "wof:name":"WV13 3ES",
    "wof:placetype":"postalcode"
},
  "geometry": {"coordinates":[-2.06509705400896,52.58025330843596],"type":"Point"}
}