{
  "type": "Feature",
  "properties": {
    "iso:country": "GB",
    "wof:name": "S80 4EG",
    "wof:placetype": "postalcode"
  },
  "geometry": {"coordinates":[-1.226839,53.261018],"type":"Point"}
}
