{
  "type": "Feature",
  "properties": {
    "date:inception_lower": "1980-01-01",
    "date:inception_upper": "1980-01-01",
    "iso:country": "GB",
    "wof:name": "FY8 2QY",
    "wof:placetype": "postalcode"
  },
  "geometry": {"coordinates":[-3.0424,53.762209],"type":"Point"}
}
