{
  "type": "Feature",
  "properties": {
    "date:inception_lower": "2002-06-01",
    "date:inception_upper": "2002-06-01",
    "iso:country": "GB",
    "wof:name": "TN24 9LQ",
    "wof:placetype": "postalcode"
  },
  "geometry": {"coordinates":[0.876811,51.170582],"type":"Point"}
}
