{
  "type": "Feature",
  "properties": {
    "iso:country":"GB",
    "wof:name":"NE28 6EQ",
    "wof:placetype":"postalcode"
},
  "geometry": {"coordinates":[-1.52736588269771,54.98743175485296],"type":"Point"}
}