{
  "type": "Feature",
  "properties": {
    "iso:country":"GB",
    "wof:name":"KY11 3DJ",
    "wof:placetype":"postalcode"
},
  "geometry": {"coordinates":[-3.45716589928983,56.04889552046696],"type":"Point"}
}