{
  "type": "Feature",
  "properties": {
    "iso:country":"GB",
    "wof:name":"CH47 3DA",
    "wof:placetype":"postalcode"
},
  "geometry": {"coordinates":[-3.16920182705404,53.39660478621527],"type":"Point"}
}