{
  "type": "Feature",
  "properties": {
    "date:inception_lower": "1999-06-01",
    "date:inception_upper": "1999-06-01",
    "iso:country": "GB",
    "wof:name": "CH47 3DA",
    "wof:placetype": "postalcode"
  },
  "geometry": {"coordinates":[-3.169202,53.396605],"type":"Point"}
}
