{
  "type": "Feature",
  "properties": {
    "iso:country":"GB",
    "wof:name":"KY11 8LA",
    "wof:placetype":"postalcode"
},
  "geometry": {"coordinates":[-3.40350818763836,56.0581797543326],"type":"Point"}
}