{
  "type": "Feature",
  "properties": {
    "iso:country": "GB",
    "wof:name": "LA22 0PP",
    "wof:placetype": "postalcode"
  },
  "geometry": {"coordinates":[-3.024617,54.383018],"type":"Point"}
}
