{
  "type": "Feature",
  "properties": {
    "iso:country":"GB",
    "wof:name":"L6 9HY",
    "wof:placetype":"postalcode"
},
  "geometry": {"coordinates":[-2.95126243370831,53.41323738916735],"type":"Point"}
}