{
  "type": "Feature",
  "properties": {
    "iso:country":"GB",
    "wof:name":"SO53 3BN",
    "wof:placetype":"postalcode"
},
  "geometry": {"coordinates":[-1.37779769709795,50.97464185947344],"type":"Point"}
}