{
  "type": "Feature",
  "properties": {
    "iso:country":"GB",
    "wof:name":"MK43 0DR",
    "wof:placetype":"postalcode"
},
  "geometry": {"coordinates":[-0.60715085568497,52.06860287055247],"type":"Point"}
}