{
  "type": "Feature",
  "properties": {
    "iso:country":"GB",
    "wof:name":"LU3 2DU",
    "wof:placetype":"postalcode"
},
  "geometry": {"coordinates":[-0.43273016102325,51.91682076392715],"type":"Point"}
}