{
  "type": "Feature",
  "properties": {
    "iso:country":"GB",
    "wof:name":"EN1 3AL",
    "wof:placetype":"postalcode"
},
  "geometry": {"coordinates":[-0.07276635719612,51.6526627308773],"type":"Point"}
}