{
  "type": "Feature",
  "properties": {
    "iso:country":"GB",
    "wof:name":"SO41 0JL",
    "wof:placetype":"postalcode"
},
  "geometry": {"coordinates":[-1.58754780543716,50.7467471426182],"type":"Point"}
}