{
  "type": "Feature",
  "properties": {
    "date:inception_lower": "1998-06-01",
    "date:inception_upper": "1998-06-01",
    "iso:country": "GB",
    "wof:name": "BA16 9NB",
    "wof:placetype": "postalcode"
  },
  "geometry": {"coordinates":[-2.749191,51.130989],"type":"Point"}
}
