{
  "type": "Feature",
  "properties": {
    "iso:country":"GB",
    "wof:name":"SW19 4RZ",
    "wof:placetype":"postalcode"
},
  "geometry": {"coordinates":[-0.21500074312788,51.42306028593771],"type":"Point"}
}