{
  "type": "Feature",
  "properties": {
    "date:inception_lower":"1980-01-01",
    "date:inception_upper":"1980-01-31",
    "iso:country":"GB",
    "wof:name":"SW19 4RZ",
    "wof:placetype":"postalcode"
},
  "geometry": {"coordinates":[-0.215001,51.42306],"type":"Point"}
}