{
  "type": "Feature",
  "properties": {
    "iso:country":"GB",
    "wof:name":"DY14 0QD",
    "wof:placetype":"postalcode"
},
  "geometry": {"coordinates":[-2.57997795443107,52.39209918505578],"type":"Point"}
}