{
  "type": "Feature",
  "properties": {
    "date:inception_lower": "1980-01-01",
    "date:inception_upper": "1980-01-01",
    "iso:country": "GB",
    "wof:name": "CM12 9EQ",
    "wof:placetype": "postalcode"
  },
  "geometry": {"coordinates":[0.415849,51.628768],"type":"Point"}
}
