{
  "type": "Feature",
  "properties": {
    "iso:country":"GB",
    "wof:name":"KT7 0AR",
    "wof:placetype":"postalcode"
},
  "geometry": {"coordinates":[-0.3232652657474,51.38609039248723],"type":"Point"}
}