{
  "type": "Feature",
  "properties": {
    "iso:country": "GB",
    "wof:name": "KT7 0AR",
    "wof:placetype": "postalcode"
  },
  "geometry": {"coordinates":[-0.323265,51.38609],"type":"Point"}
}
