{
  "type": "Feature",
  "properties": {
    "iso:country":"GB",
    "wof:name":"LE9 6RH",
    "wof:placetype":"postalcode"
},
  "geometry": {"coordinates":[-1.22916474111856,52.53187011765678],"type":"Point"}
}