{
  "type": "Feature",
  "properties": {
    "iso:country":"GB",
    "wof:name":"BN25 3SD",
    "wof:placetype":"postalcode"
},
  "geometry": {"coordinates":[0.12352605128973,50.78012603310187],"type":"Point"}
}