{
  "type": "Feature",
  "properties": {
    "iso:country":"GB",
    "wof:name":"DD2 5QQ",
    "wof:placetype":"postalcode"
},
  "geometry": {"coordinates":[-3.05461177077697,56.49937893590983],"type":"Point"}
}