{
  "type": "Feature",
  "properties": {
    "iso:country": "GB",
    "wof:name": "SY14 8BD",
    "wof:placetype": "postalcode"
  },
  "geometry": {"coordinates":[-2.716752,53.084762],"type":"Point"}
}
