{
  "type": "Feature",
  "properties": {
    "iso:country":"GB",
    "wof:name":"SY14 8BD",
    "wof:placetype":"postalcode"
},
  "geometry": {"coordinates":[-2.71467968670305,53.08587332862345],"type":"Point"}
}