{
  "type": "Feature",
  "properties": {
    "iso:country":"GB",
    "wof:name":"SS9 5RG",
    "wof:placetype":"postalcode"
},
  "geometry": {"coordinates":[0.65278632987374,51.5710217424072],"type":"Point"}
}