{
  "type": "Feature",
  "properties": {
    "date:inception_lower": "1980-01-01",
    "date:inception_upper": "1980-01-01",
    "iso:country": "GB",
    "wof:name": "SG19 2DT",
    "wof:placetype": "postalcode"
  },
  "geometry": {"coordinates":[-0.204421,52.119326],"type":"Point"}
}
