{
  "type": "Feature",
  "properties": {
    "iso:country":"GB",
    "wof:name":"SG19 2DT",
    "wof:placetype":"postalcode"
},
  "geometry": {"coordinates":[-0.20442139993233,52.11932599341194],"type":"Point"}
}