{
  "type": "Feature",
  "properties": {
    "iso:country":"GB",
    "wof:name":"BD20 0LN",
    "wof:placetype":"postalcode"
},
  "geometry": {"coordinates":[-1.92126385840256,53.91819064935148],"type":"Point"}
}