{
  "type": "Feature",
  "properties": {
    "iso:country": "GB",
    "wof:name": "BD20 0LN",
    "wof:placetype": "postalcode"
  },
  "geometry": {"coordinates":[-1.921264,53.918191],"type":"Point"}
}
