{
  "type": "Feature",
  "properties": {
    "date:inception_lower": "1980-01-01",
    "date:inception_upper": "1980-01-01",
    "iso:country": "GB",
    "wof:name": "B61 0PH",
    "wof:placetype": "postalcode"
  },
  "geometry": {"coordinates":[-2.056897,52.36867],"type":"Point"}
}
