{
  "type": "Feature",
  "properties": {
    "iso:country":"GB",
    "wof:name":"B61 0PH",
    "wof:placetype":"postalcode"
},
  "geometry": {"coordinates":[-2.05689737321552,52.36866967548969],"type":"Point"}
}