{
  "type": "Feature",
  "properties": {
    "iso:country":"GB",
    "wof:name":"SG19 1NE",
    "wof:placetype":"postalcode"
},
  "geometry": {"coordinates":[-0.29577846325238,52.12679607006835],"type":"Point"}
}