{
  "type": "Feature",
  "properties": {
    "iso:country":"GB",
    "wof:name":"ST6 5QN",
    "wof:placetype":"postalcode"
},
  "geometry": {"coordinates":[-2.22221550825673,53.07578530823405],"type":"Point"}
}