{
  "type": "Feature",
  "properties": {
    "date:inception_lower": "1980-01-01",
    "date:inception_upper": "1980-01-01",
    "iso:country": "GB",
    "wof:name": "ST9 9EE",
    "wof:placetype": "postalcode"
  },
  "geometry": {"coordinates":[-2.11638,53.073455],"type":"Point"}
}
