{
  "type": "Feature",
  "properties": {
    "date:inception_lower": "1980-01-01",
    "date:inception_upper": "1980-01-01",
    "iso:country": "GB",
    "wof:name": "LN2 1SW",
    "wof:placetype": "postalcode"
  },
  "geometry": {"coordinates":[-0.533044,53.242794],"type":"Point"}
}
