{
  "type": "Feature",
  "properties": {
    "iso:country":"GB",
    "wof:name":"LN2 1SW",
    "wof:placetype":"postalcode"
},
  "geometry": {"coordinates":[-0.53304421944823,53.2427937316883],"type":"Point"}
}