{
  "type": "Feature",
  "properties": {
    "iso:country":"GB",
    "wof:name":"G81 1QS",
    "wof:placetype":"postalcode"
},
  "geometry": {"coordinates":[-4.40011583703118,55.90000060435425],"type":"Point"}
}