{
  "type": "Feature",
  "properties": {
    "iso:country":"GB",
    "wof:name":"WV14 6AF",
    "wof:placetype":"postalcode"
},
  "geometry": {"coordinates":[-2.07652607607843,52.56713030676696],"type":"Point"}
}