{
  "type": "Feature",
  "properties": {
    "iso:country":"GB",
    "wof:name":"B29 5NS",
    "wof:placetype":"postalcode"
},
  "geometry": {"coordinates":[-1.96918413121766,52.43561966482618],"type":"Point"}
}