{
  "type": "Feature",
  "properties": {
    "iso:country": "GB",
    "wof:name": "B29 5NS",
    "wof:placetype": "postalcode"
  },
  "geometry": {"coordinates":[-1.969184,52.43562],"type":"Point"}
}
