{
  "type": "Feature",
  "properties": {
    "date:inception_lower": "1980-01-01",
    "date:inception_upper": "1980-01-01",
    "iso:country": "GB",
    "wof:name": "B29 5NS",
    "wof:placetype": "postalcode"
  },
  "geometry": {"coordinates":[-1.969184,52.43562],"type":"Point"}
}
