{
  "type": "Feature",
  "properties": {
    "date:inception_lower":"1995-07-01",
    "date:inception_upper":"1995-07-31",
    "iso:country":"GB",
    "wof:name":"RG12 0GG",
    "wof:placetype":"postalcode"
},
  "geometry": {"coordinates":[-0.73217,51.393566],"type":"Point"}
}