{
  "type": "Feature",
  "properties": {
    "iso:country": "GB",
    "wof:name": "RG12 0GG",
    "wof:placetype": "postalcode"
  },
  "geometry": {"coordinates":[-0.73217,51.393566],"type":"Point"}
}
