{
  "type": "Feature",
  "properties": {
    "iso:country": "GB",
    "wof:name": "EX8 5AP",
    "wof:placetype": "postalcode"
  },
  "geometry": {"coordinates":[-3.431807,50.663921],"type":"Point"}
}
