{
  "type": "Feature",
  "properties": {
    "iso:country":"GB",
    "wof:name":"DN36 5UX",
    "wof:placetype":"postalcode"
},
  "geometry": {"coordinates":[0.02807863776437,53.48160960714937],"type":"Point"}
}