{
  "type": "Feature",
  "properties": {
    "iso:country":"GB",
    "wof:name":"SY15 6SD",
    "wof:placetype":"postalcode"
},
  "geometry": {"coordinates":[-3.2078340696003,52.57642831254998],"type":"Point"}
}