{
  "type": "Feature",
  "properties": {
    "iso:country": "GB",
    "wof:name": "EH26 9LY",
    "wof:placetype": "postalcode"
  },
  "geometry": {"coordinates":[-3.317343,55.796685],"type":"Point"}
}
