{
  "type": "Feature",
  "properties": {
    "iso:country": "GB",
    "wof:name": "NN11 3RF",
    "wof:placetype": "postalcode"
  },
  "geometry": {"coordinates":[-1.204704,52.168767],"type":"Point"}
}
