{
  "type": "Feature",
  "properties": {
    "iso:country":"GB",
    "wof:name":"NN11 3RF",
    "wof:placetype":"postalcode"
},
  "geometry": {"coordinates":[-1.20470432211606,52.16876690275926],"type":"Point"}
}