{
  "type": "Feature",
  "properties": {
    "iso:country":"GB",
    "wof:name":"TR26 1DZ",
    "wof:placetype":"postalcode"
},
  "geometry": {"coordinates":[-5.48655953947956,50.21247173464582],"type":"Point"}
}