{
  "type": "Feature",
  "properties": {
    "iso:country":"GB",
    "wof:name":"WS3 2QF",
    "wof:placetype":"postalcode"
},
  "geometry": {"coordinates":[-2.01799057450881,52.61575258975785],"type":"Point"}
}