{
  "type": "Feature",
  "properties": {
    "iso:country": "GB",
    "wof:name": "HG5 9JT",
    "wof:placetype": "postalcode"
  },
  "geometry": {"coordinates":[-1.436089,54.047511],"type":"Point"}
}
