{
  "type": "Feature",
  "properties": {
    "iso:country":"GB",
    "wof:name":"HG5 9JT",
    "wof:placetype":"postalcode"
},
  "geometry": {"coordinates":[-1.4357141538018,54.0476554841801],"type":"Point"}
}