{
  "type": "Feature",
  "properties": {
    "date:inception_lower":"1991-09-01",
    "date:inception_upper":"1991-09-30",
    "iso:country":"GB",
    "wof:name":"OX18 2AT",
    "wof:placetype":"postalcode"
},
  "geometry": {"coordinates":[-1.564436,51.747742],"type":"Point"}
}