{
  "type": "Feature",
  "properties": {
    "iso:country": "GB",
    "wof:name": "RH10 6NE",
    "wof:placetype": "postalcode"
  },
  "geometry": {"coordinates":[-0.170344,51.104242],"type":"Point"}
}
