{
  "type": "Feature",
  "properties": {
    "iso:country":"GB",
    "wof:name":"PE13 3UU",
    "wof:placetype":"postalcode"
},
  "geometry": {"coordinates":[0.174823176882,52.66782914549485],"type":"Point"}
}