{
  "type": "Feature",
  "properties": {
    "date:inception_lower": "1980-01-01",
    "date:inception_upper": "1980-01-01",
    "iso:country": "GB",
    "wof:name": "PE13 3UU",
    "wof:placetype": "postalcode"
  },
  "geometry": {"coordinates":[0.174823,52.667829],"type":"Point"}
}
