{
  "type": "Feature",
  "properties": {
    "date:inception_lower": "2017-09-01",
    "date:inception_upper": "2017-09-01",
    "iso:country": "GB",
    "wof:name": "PE11 3PD",
    "wof:placetype": "postalcode"
  },
  "geometry": {"coordinates":[-0.165967,52.791214],"type":"Point"}
}
