{
  "type": "Feature",
  "properties": {
    "iso:country": "GB",
    "wof:name": "MK42 0JA",
    "wof:placetype": "postalcode"
  },
  "geometry": {"coordinates":[-0.456738,52.125128],"type":"Point"}
}
