{
  "type": "Feature",
  "properties": {
    "iso:country":"GB",
    "wof:name":"HR4 9UA",
    "wof:placetype":"postalcode"
},
  "geometry": {"coordinates":[-2.72023260606651,52.07315325305161],"type":"Point"}
}