{
  "type": "Feature",
  "properties": {
    "date:inception_lower": "1990-07-01",
    "date:inception_upper": "1990-07-01",
    "iso:country": "GB",
    "wof:name": "SA3 4UX",
    "wof:placetype": "postalcode"
  },
  "geometry": {"coordinates":[-4.018971,51.578605],"type":"Point"}
}
