{
  "type": "Feature",
  "properties": {
    "date:inception_lower": "1980-01-01",
    "date:inception_upper": "1980-01-01",
    "iso:country": "GB",
    "wof:name": "CT3 2NQ",
    "wof:placetype": "postalcode"
  },
  "geometry": {"coordinates":[1.299197,51.300178],"type":"Point"}
}
