{
  "type": "Feature",
  "properties": {
    "iso:country":"GB",
    "wof:name":"CT3 2NQ",
    "wof:placetype":"postalcode"
},
  "geometry": {"coordinates":[1.29919710993743,51.3001783472674],"type":"Point"}
}