{
  "type": "Feature",
  "properties": {
    "iso:country": "GB",
    "wof:name": "EH55 8AQ",
    "wof:placetype": "postalcode"
  },
  "geometry": {"coordinates":[-3.567874,55.851679],"type":"Point"}
}
