{
  "type": "Feature",
  "properties": {
    "iso:country":"GB",
    "wof:name":"PE2 6YD",
    "wof:placetype":"postalcode"
},
  "geometry": {"coordinates":[-0.30975009407876,52.55854570478794],"type":"Point"}
}