{
  "type": "Feature",
  "properties": {
    "iso:country":"GB",
    "wof:name":"WA8 7EU",
    "wof:placetype":"postalcode"
},
  "geometry": {"coordinates":[-2.74433486310402,53.3675696311855],"type":"Point"}
}