{
  "type": "Feature",
  "properties": {
    "date:inception_lower": "1996-06-01",
    "date:inception_upper": "1996-06-01",
    "iso:country": "GB",
    "wof:name": "WA8 7EU",
    "wof:placetype": "postalcode"
  },
  "geometry": {"coordinates":[-2.744335,53.36757],"type":"Point"}
}
