{
  "type": "Feature",
  "properties": {
    "iso:country": "GB",
    "wof:name": "TN11 0FP",
    "wof:placetype": "postalcode"
  },
  "geometry": {"coordinates":[0.291516,51.187482],"type":"Point"}
}
