{
  "type": "Feature",
  "properties": {
    "iso:country":"GB",
    "wof:name":"CV33 9JA",
    "wof:placetype":"postalcode"
},
  "geometry": {"coordinates":[-1.4565245480028,52.23390175703219],"type":"Point"}
}