{
  "type": "Feature",
  "properties": {
    "iso:country": "GB",
    "wof:name": "EH26 0FZ",
    "wof:placetype": "postalcode"
  },
  "geometry": {"coordinates":[-3.220378,55.84262],"type":"Point"}
}
