{
  "type": "Feature",
  "properties": {
    "date:inception_lower": "2018-12-01",
    "date:inception_upper": "2018-12-01",
    "iso:country": "GB",
    "wof:name": "EH26 0FZ",
    "wof:placetype": "postalcode"
  },
  "geometry": {"coordinates":[-3.220378,55.84262],"type":"Point"}
}
