{
  "type": "Feature",
  "properties": {
    "date:inception_lower":"1990-02-01",
    "date:inception_upper":"1990-02-28",
    "iso:country":"GB",
    "wof:name":"OL11 5TY",
    "wof:placetype":"postalcode"
},
  "geometry": {"coordinates":[-2.219826,53.629706],"type":"Point"}
}