{
  "type": "Feature",
  "properties": {
    "iso:country": "GB",
    "wof:name": "OL11 5TY",
    "wof:placetype": "postalcode"
  },
  "geometry": {"coordinates":[-2.219826,53.629706],"type":"Point"}
}
