{
  "type": "Feature",
  "properties": {
    "iso:country": "GB",
    "wof:name": "LS21 2QF",
    "wof:placetype": "postalcode"
  },
  "geometry": {"coordinates":[-1.672424,53.921626],"type":"Point"}
}
