{
  "type": "Feature",
  "properties": {
    "iso:country":"GB",
    "wof:name":"E7 9NT",
    "wof:placetype":"postalcode"
},
  "geometry": {"coordinates":[0.02255744472669,51.54244694284942],"type":"Point"}
}