{
  "type": "Feature",
  "properties": {
    "iso:country":"GB",
    "wof:name":"LS7 2RF",
    "wof:placetype":"postalcode"
},
  "geometry": {"coordinates":[-1.55536996583781,53.82895301118236],"type":"Point"}
}