{
  "type": "Feature",
  "properties": {
    "date:inception_lower": "1980-01-01",
    "date:inception_upper": "1980-01-01",
    "iso:country": "GB",
    "wof:name": "LS7 2RF",
    "wof:placetype": "postalcode"
  },
  "geometry": {"coordinates":[-1.55537,53.828953],"type":"Point"}
}
