{
  "type": "Feature",
  "properties": {
    "iso:country": "GB",
    "wof:name": "LS7 2RF",
    "wof:placetype": "postalcode"
  },
  "geometry": {"coordinates":[-1.55537,53.828953],"type":"Point"}
}
