{
  "type": "Feature",
  "properties": {
    "iso:country":"GB",
    "wof:name":"AB21 9WJ",
    "wof:placetype":"postalcode"
},
  "geometry": {"coordinates":[-2.14645457458777,57.17619230321709],"type":"Point"}
}