{
  "type": "Feature",
  "properties": {
    "date:inception_lower": "2000-06-01",
    "date:inception_upper": "2000-06-01",
    "iso:country": "GB",
    "wof:name": "PE29 1LW",
    "wof:placetype": "postalcode"
  },
  "geometry": {"coordinates":[-0.177294,52.337457],"type":"Point"}
}
