{
  "type": "Feature",
  "properties": {
    "iso:country": "GB",
    "wof:name": "DE21 4EZ",
    "wof:placetype": "postalcode"
  },
  "geometry": {"coordinates":[-1.44898,52.941849],"type":"Point"}
}
