{
  "type": "Feature",
  "properties": {
    "iso:country":"GB",
    "wof:name":"DE21 4EZ",
    "wof:placetype":"postalcode"
},
  "geometry": {"coordinates":[-1.44897963971936,52.94184850811493],"type":"Point"}
}