{
  "type": "Feature",
  "properties": {
    "iso:country":"GB",
    "wof:name":"FY1 4BX",
    "wof:placetype":"postalcode"
},
  "geometry": {"coordinates":[-3.04597809639541,53.8127648922302],"type":"Point"}
}