{
  "type": "Feature",
  "properties": {
    "iso:country": "GB",
    "wof:name": "FY1 4BX",
    "wof:placetype": "postalcode"
  },
  "geometry": {"coordinates":[-3.045978,53.812765],"type":"Point"}
}
