{
  "type": "Feature",
  "properties": {
    "iso:country":"GB",
    "wof:name":"L7 3PD",
    "wof:placetype":"postalcode"
},
  "geometry": {"coordinates":[-2.95872526067436,53.40322697242215],"type":"Point"}
}