{
  "type": "Feature",
  "properties": {
    "iso:country": "GB",
    "wof:name": "L7 3PD",
    "wof:placetype": "postalcode"
  },
  "geometry": {"coordinates":[-2.958725,53.403227],"type":"Point"}
}
