{
  "type": "Feature",
  "properties": {
    "iso:country": "GB",
    "wof:name": "DG8 8JY",
    "wof:placetype": "postalcode"
  },
  "geometry": {"coordinates":[-4.399759,54.708387],"type":"Point"}
}
