{
  "type": "Feature",
  "properties": {
    "date:inception_lower": "2023-06-01",
    "date:inception_upper": "2023-06-01",
    "iso:country": "GB",
    "wof:name": "LS7 2FF",
    "wof:placetype": "postalcode"
  },
  "geometry": {"coordinates":[-1.55799,53.827352],"type":"Point"}
}
