{
  "type": "Feature",
  "properties": {
    "iso:country":"GB",
    "wof:name":"PL14 4NZ",
    "wof:placetype":"postalcode"
},
  "geometry": {"coordinates":[-4.55832981085228,50.44390976471801],"type":"Point"}
}