{
  "type": "Feature",
  "properties": {
    "date:inception_lower":"1990-02-01",
    "date:inception_upper":"1990-02-28",
    "iso:country":"GB",
    "wof:name":"PL14 4NZ",
    "wof:placetype":"postalcode"
},
  "geometry": {"coordinates":[-4.55833,50.44391],"type":"Point"}
}