{
  "type": "Feature",
  "properties": {
    "iso:country":"GB",
    "wof:name":"SO16 9AG",
    "wof:placetype":"postalcode"
},
  "geometry": {"coordinates":[-1.46064758512826,50.92071251391605],"type":"Point"}
}