{
  "type": "Feature",
  "properties": {
    "iso:country":"GB",
    "wof:name":"B80 7QW",
    "wof:placetype":"postalcode"
},
  "geometry": {"coordinates":[-1.89857262590386,52.26497407928365],"type":"Point"}
}