{
  "type": "Feature",
  "properties": {
    "iso:country":"GB",
    "wof:name":"PE34 3DS",
    "wof:placetype":"postalcode"
},
  "geometry": {"coordinates":[0.35637961298784,52.70037794141457],"type":"Point"}
}