{
  "type": "Feature",
  "properties": {
    "date:inception_lower":"1980-01-01",
    "date:inception_upper":"1980-01-31",
    "iso:country":"GB",
    "wof:name":"PE34 3DS",
    "wof:placetype":"postalcode"
},
  "geometry": {"coordinates":[0.35638,52.700378],"type":"Point"}
}