{
  "type": "Feature",
  "properties": {
    "iso:country":"GB",
    "wof:name":"NE13 6PW",
    "wof:placetype":"postalcode"
},
  "geometry": {"coordinates":[-1.62588937449366,55.04206003490118],"type":"Point"}
}