{
  "type": "Feature",
  "properties": {
    "date:inception_lower": "1998-06-01",
    "date:inception_upper": "1998-06-01",
    "iso:country": "GB",
    "wof:name": "NE13 6PW",
    "wof:placetype": "postalcode"
  },
  "geometry": {"coordinates":[-1.625889,55.04206],"type":"Point"}
}
