{
  "type": "Feature",
  "properties": {
    "iso:country": "GB",
    "wof:name": "NE13 6PW",
    "wof:placetype": "postalcode"
  },
  "geometry": {"coordinates":[-1.625889,55.04206],"type":"Point"}
}
