{
  "type": "Feature",
  "properties": {
    "iso:country":"GB",
    "wof:name":"CM8 1DL",
    "wof:placetype":"postalcode"
},
  "geometry": {"coordinates":[0.63150134901417,51.79056172970593],"type":"Point"}
}