{
  "type": "Feature",
  "properties": {
    "date:inception_lower": "2002-06-01",
    "date:inception_upper": "2002-06-01",
    "iso:country": "GB",
    "wof:name": "SW19 3NA",
    "wof:placetype": "postalcode"
  },
  "geometry": {"coordinates":[-0.208097,51.412127],"type":"Point"}
}
