{
  "type": "Feature",
  "properties": {
    "iso:country":"GB",
    "wof:name":"SW19 3NA",
    "wof:placetype":"postalcode"
},
  "geometry": {"coordinates":[-0.20806680044401,51.41205549228086],"type":"Point"}
}