{
  "type": "Feature",
  "properties": {
    "date:inception_lower": "1980-01-01",
    "date:inception_upper": "1980-01-01",
    "iso:country": "GB",
    "wof:name": "OX7 5PS",
    "wof:placetype": "postalcode"
  },
  "geometry": {"coordinates":[-1.544232,51.95319],"type":"Point"}
}
