{
  "type": "Feature",
  "properties": {
    "date:inception_lower":"2015-11-01",
    "date:inception_upper":"2015-11-30",
    "iso:country":"GB",
    "wof:name":"EX20 1US",
    "wof:placetype":"postalcode"
},
  "geometry": {"coordinates":[-3.982255,50.743573],"type":"Point"}
}