{
  "type": "Feature",
  "properties": {
    "iso:country": "GB",
    "wof:name": "EX20 1US",
    "wof:placetype": "postalcode"
  },
  "geometry": {"coordinates":[-3.982255,50.743573],"type":"Point"}
}
