{
  "type": "Feature",
  "properties": {
    "date:inception_lower": "1980-01-01",
    "date:inception_upper": "1980-01-01",
    "iso:country": "GB",
    "wof:name": "EX39 1ND",
    "wof:placetype": "postalcode"
  },
  "geometry": {"coordinates":[-4.205194,51.050153],"type":"Point"}
}
