{
  "type": "Feature",
  "properties": {
    "iso:country":"GB",
    "wof:name":"EX39 1ND",
    "wof:placetype":"postalcode"
},
  "geometry": {"coordinates":[-4.20519526141934,51.05012085698923],"type":"Point"}
}