{
  "type": "Feature",
  "properties": {
    "iso:country":"GB",
    "wof:name":"YO10 3EL",
    "wof:placetype":"postalcode"
},
  "geometry": {"coordinates":[-1.0643934072123,53.95590106606065],"type":"Point"}
}