{
  "type": "Feature",
  "properties": {
    "date:inception_lower": "2024-01-01",
    "date:inception_upper": "2024-01-01",
    "iso:country": "GB",
    "wof:name": "NP18 1DE",
    "wof:placetype": "postalcode"
  },
  "geometry": {"coordinates":[-2.929152,51.602792],"type":"Point"}
}
