{
  "type": "Feature",
  "properties": {
    "date:inception_lower": "2007-01-01",
    "date:inception_upper": "2007-01-01",
    "iso:country": "GB",
    "wof:name": "BB1 1QZ",
    "wof:placetype": "postalcode"
  },
  "geometry": {"coordinates":[-2.457765,53.744441],"type":"Point"}
}
