{
  "type": "Feature",
  "properties": {
    "iso:country":"GB",
    "wof:name":"BB1 1QZ",
    "wof:placetype":"postalcode"
},
  "geometry": {"coordinates":[-2.4577646335015,53.74444085228478],"type":"Point"}
}