{
  "type": "Feature",
  "properties": {
    "iso:country":"GB",
    "wof:name":"SG12 7QP",
    "wof:placetype":"postalcode"
},
  "geometry": {"coordinates":[0.0135975086207,51.82046818289884],"type":"Point"}
}