{
  "type": "Feature",
  "properties": {
    "iso:country": "GB",
    "wof:name": "KT11 2TG",
    "wof:placetype": "postalcode"
  },
  "geometry": {"coordinates":[-0.395528,51.338768],"type":"Point"}
}
