{
  "type": "Feature",
  "properties": {
    "date:inception_lower": "1992-01-01",
    "date:inception_upper": "1992-01-01",
    "iso:country": "GB",
    "wof:name": "KT11 2TG",
    "wof:placetype": "postalcode"
  },
  "geometry": {"coordinates":[-0.395528,51.338768],"type":"Point"}
}
