{
  "type": "Feature",
  "properties": {
    "iso:country":"GB",
    "wof:name":"KT11 2TG",
    "wof:placetype":"postalcode"
},
  "geometry": {"coordinates":[-0.39552768697449,51.33876771103938],"type":"Point"}
}