{
  "type": "Feature",
  "properties": {
    "iso:country":"GB",
    "wof:name":"NR7 0NS",
    "wof:placetype":"postalcode"
},
  "geometry": {"coordinates":[1.3669884083836,52.63656284549944],"type":"Point"}
}