{
  "type": "Feature",
  "properties": {
    "iso:country":"GB",
    "wof:name":"TD9 8NY",
    "wof:placetype":"postalcode"
},
  "geometry": {"coordinates":[-2.68475088035346,55.45327258670166],"type":"Point"}
}