{
  "type": "Feature",
  "properties": {
    "iso:country":"GB",
    "wof:name":"TS14 6ET",
    "wof:placetype":"postalcode"
},
  "geometry": {"coordinates":[-1.05835008795985,54.53658281555036],"type":"Point"}
}