{
  "type": "Feature",
  "properties": {
    "date:inception_lower": "2003-09-01",
    "date:inception_upper": "2003-09-01",
    "iso:country": "GB",
    "wof:name": "LA12 8RB",
    "wof:placetype": "postalcode"
  },
  "geometry": {"coordinates":[-2.992343,54.251522],"type":"Point"}
}
