{
  "type": "Feature",
  "properties": {
    "iso:country":"GB",
    "wof:name":"DE75 7WA",
    "wof:placetype":"postalcode"
},
  "geometry": {"coordinates":[-1.36659227053719,53.01577106288136],"type":"Point"}
}