{
  "type": "Feature",
  "properties": {
    "iso:country":"GB",
    "wof:name":"SP6 2EH",
    "wof:placetype":"postalcode"
},
  "geometry": {"coordinates":[-1.77543923271847,50.96221601372149],"type":"Point"}
}