{
  "type": "Feature",
  "properties": {
    "iso:country": "GB",
    "wof:name": "SP6 2EH",
    "wof:placetype": "postalcode"
  },
  "geometry": {"coordinates":[-1.775133,50.9621],"type":"Point"}
}
