{
  "type": "Feature",
  "properties": {
    "iso:country":"GB",
    "wof:name":"DH5 0PS",
    "wof:placetype":"postalcode"
},
  "geometry": {"coordinates":[-1.43943578555592,54.80502893501127],"type":"Point"}
}