{
  "type": "Feature",
  "properties": {
    "iso:country":"GB",
    "wof:name":"BA2 3JD",
    "wof:placetype":"postalcode"
},
  "geometry": {"coordinates":[-2.38001458411268,51.37864620835044],"type":"Point"}
}