{
  "type": "Feature",
  "properties": {
    "iso:country":"GB",
    "wof:name":"IP23 7AN",
    "wof:placetype":"postalcode"
},
  "geometry": {"coordinates":[1.14609287102053,52.31972965259776],"type":"Point"}
}