{
  "type": "Feature",
  "properties": {
    "iso:country":"GB",
    "wof:name":"SP1 3BG",
    "wof:placetype":"postalcode"
},
  "geometry": {"coordinates":[-1.78832342306916,51.07558698109187],"type":"Point"}
}