{
  "type": "Feature",
  "properties": {
    "iso:country":"GB",
    "wof:name":"BD5 0DG",
    "wof:placetype":"postalcode"
},
  "geometry": {"coordinates":[-1.75175589441497,53.79284878133163],"type":"Point"}
}