{
  "type": "Feature",
  "properties": {
    "date:inception_lower": "1980-01-01",
    "date:inception_upper": "1980-01-01",
    "iso:country": "GB",
    "wof:name": "ST4 6LS",
    "wof:placetype": "postalcode"
  },
  "geometry": {"coordinates":[-2.205171,52.985053],"type":"Point"}
}
