{
  "type": "Feature",
  "properties": {
    "iso:country": "GB",
    "wof:name": "N16 0DR",
    "wof:placetype": "postalcode"
  },
  "geometry": {"coordinates":[-0.077723,51.559357],"type":"Point"}
}
