{
  "type": "Feature",
  "properties": {
    "iso:country":"GB",
    "wof:name":"N16 0DR",
    "wof:placetype":"postalcode"
},
  "geometry": {"coordinates":[-0.07772345251382,51.55935736780609],"type":"Point"}
}