{
  "type": "Feature",
  "properties": {
    "iso:country":"GB",
    "wof:name":"HU5 3EZ",
    "wof:placetype":"postalcode"
},
  "geometry": {"coordinates":[-0.36749674898347,53.75874066281705],"type":"Point"}
}