{
  "type": "Feature",
  "properties": {
    "iso:country":"GB",
    "wof:name":"PA14 6QD",
    "wof:placetype":"postalcode"
},
  "geometry": {"coordinates":[-4.64631740855702,55.92713984463871],"type":"Point"}
}