{
  "type": "Feature",
  "properties": {
    "iso:country":"GB",
    "wof:name":"DN41 7SA",
    "wof:placetype":"postalcode"
},
  "geometry": {"coordinates":[-0.1668579631564,53.58100291540967],"type":"Point"}
}