{
  "type": "Feature",
  "properties": {
    "date:inception_lower": "1997-06-01",
    "date:inception_upper": "1997-06-01",
    "iso:country": "GB",
    "wof:name": "DN41 7SA",
    "wof:placetype": "postalcode"
  },
  "geometry": {"coordinates":[-0.166858,53.581003],"type":"Point"}
}
