{
  "type": "Feature",
  "properties": {
    "iso:country": "GB",
    "wof:name": "DN41 7SA",
    "wof:placetype": "postalcode"
  },
  "geometry": {"coordinates":[-0.166858,53.581003],"type":"Point"}
}
