{
  "type": "Feature",
  "properties": {
    "iso:country":"GB",
    "wof:name":"PL1 3RL",
    "wof:placetype":"postalcode"
},
  "geometry": {"coordinates":[-4.16319061006741,50.36536907876097],"type":"Point"}
}