{
  "type": "Feature",
  "properties": {
    "date:inception_lower": "1992-08-01",
    "date:inception_upper": "1992-08-01",
    "iso:country": "GB",
    "wof:name": "DE23 8WA",
    "wof:placetype": "postalcode"
  },
  "geometry": {"coordinates":[-1.479748,52.896339],"type":"Point"}
}
