{
  "type": "Feature",
  "properties": {
    "iso:country":"GB",
    "wof:name":"DE23 8WA",
    "wof:placetype":"postalcode"
},
  "geometry": {"coordinates":[-1.47974754823147,52.89633899655984],"type":"Point"}
}