{
  "type": "Feature",
  "properties": {
    "iso:country":"GB",
    "wof:name":"PA34 5JA",
    "wof:placetype":"postalcode"
},
  "geometry": {"coordinates":[-5.47220976825286,56.41779267861349],"type":"Point"}
}