{
  "type": "Feature",
  "properties": {
    "iso:country":"GB",
    "wof:name":"HR8 1EA",
    "wof:placetype":"postalcode"
},
  "geometry": {"coordinates":[-2.42351768131167,52.03651799427877],"type":"Point"}
}