{
  "type": "Feature",
  "properties": {
    "iso:country":"GB",
    "wof:name":"LL55 2RJ",
    "wof:placetype":"postalcode"
},
  "geometry": {"coordinates":[-4.26629936347524,53.13996915877761],"type":"Point"}
}