{
  "type": "Feature",
  "properties": {
    "date:inception_lower":"1998-06-01",
    "date:inception_upper":"1998-06-30",
    "iso:country":"GB",
    "wof:name":"LL55 2RJ",
    "wof:placetype":"postalcode"
},
  "geometry": {"coordinates":[-4.266299,53.139969],"type":"Point"}
}