{
  "type": "Feature",
  "properties": {
    "iso:country":"GB",
    "wof:name":"RG9 5TL",
    "wof:placetype":"postalcode"
},
  "geometry": {"coordinates":[-1.01204817653787,51.55817397233504],"type":"Point"}
}