{
  "type": "Feature",
  "properties": {
    "date:inception_lower": "2014-09-01",
    "date:inception_upper": "2014-09-01",
    "iso:country": "GB",
    "wof:name": "LA2 8AX",
    "wof:placetype": "postalcode"
  },
  "geometry": {"coordinates":[-2.637545,54.106839],"type":"Point"}
}
