{
  "type": "Feature",
  "properties": {
    "date:inception_lower": "2007-02-01",
    "date:inception_upper": "2007-02-01",
    "iso:country": "GB",
    "wof:name": "TN13 3BH",
    "wof:placetype": "postalcode"
  },
  "geometry": {"coordinates":[0.184723,51.278381],"type":"Point"}
}
