{
  "type": "Feature",
  "properties": {
    "iso:country":"GB",
    "wof:name":"TN13 3BH",
    "wof:placetype":"postalcode"
},
  "geometry": {"coordinates":[0.18472330652123,51.27838056155751],"type":"Point"}
}