{
  "type": "Feature",
  "properties": {
    "iso:country": "GB",
    "wof:name": "CA3 9AS",
    "wof:placetype": "postalcode"
  },
  "geometry": {"coordinates":[-2.92791,54.907592],"type":"Point"}
}
