{
  "type": "Feature",
  "properties": {
    "iso:country":"GB",
    "wof:name":"CA3 9AS",
    "wof:placetype":"postalcode"
},
  "geometry": {"coordinates":[-2.92803124537484,54.90760282159223],"type":"Point"}
}