{
  "type": "Feature",
  "properties": {
    "date:inception_lower": "1980-01-01",
    "date:inception_upper": "1980-01-01",
    "iso:country": "GB",
    "wof:name": "CA3 9AS",
    "wof:placetype": "postalcode"
  },
  "geometry": {"coordinates":[-2.92791,54.907592],"type":"Point"}
}
