{
  "type": "Feature",
  "properties": {
    "iso:country": "GB",
    "wof:name": "GU26 6NX",
    "wof:placetype": "postalcode"
  },
  "geometry": {"coordinates":[-0.756286,51.124891],"type":"Point"}
}
