{
  "type": "Feature",
  "properties": {
    "date:inception_lower":"1980-01-01",
    "date:inception_upper":"1980-01-31",
    "iso:country":"GB",
    "wof:name":"GU26 6NX",
    "wof:placetype":"postalcode"
},
  "geometry": {"coordinates":[-0.756286,51.124891],"type":"Point"}
}