{
  "type": "Feature",
  "properties": {
    "iso:country": "GB",
    "wof:name": "SO30 2SP",
    "wof:placetype": "postalcode"
  },
  "geometry": {"coordinates":[-1.274859,50.919141],"type":"Point"}
}
