{
  "type": "Feature",
  "properties": {
    "iso:country":"GB",
    "wof:name":"SO30 2SP",
    "wof:placetype":"postalcode"
},
  "geometry": {"coordinates":[-1.27485690092549,50.91914041763378],"type":"Point"}
}