{
  "type": "Feature",
  "properties": {
    "date:inception_lower": "1994-12-01",
    "date:inception_upper": "1994-12-01",
    "iso:country": "GB",
    "wof:name": "SO30 2SP",
    "wof:placetype": "postalcode"
  },
  "geometry": {"coordinates":[-1.274859,50.919141],"type":"Point"}
}
