{
  "type": "Feature",
  "properties": {
    "date:inception_lower": "2018-07-01",
    "date:inception_upper": "2018-07-01",
    "iso:country": "GB",
    "wof:name": "EX23 8GN",
    "wof:placetype": "postalcode"
  },
  "geometry": {"coordinates":[-4.523108,50.82516],"type":"Point"}
}
