{
  "type": "Feature",
  "properties": {
    "iso:country": "GB",
    "wof:name": "EX23 8GN",
    "wof:placetype": "postalcode"
  },
  "geometry": {"coordinates":[-4.523967,50.825294],"type":"Point"}
}
