{
  "type": "Feature",
  "properties": {
    "iso:country": "GB",
    "wof:name": "FK8 3LA",
    "wof:placetype": "postalcode"
  },
  "geometry": {"coordinates":[-4.272613,56.186536],"type":"Point"}
}
