{
  "type": "Feature",
  "properties": {
    "iso:country":"GB",
    "wof:name":"FK8 3LA",
    "wof:placetype":"postalcode"
},
  "geometry": {"coordinates":[-4.27261258195711,56.18653553780807],"type":"Point"}
}