{
  "type": "Feature",
  "properties": {
    "iso:country": "GB",
    "wof:name": "B65 8NT",
    "wof:placetype": "postalcode"
  },
  "geometry": {"coordinates":[-2.061198,52.493368],"type":"Point"}
}
