{
  "type": "Feature",
  "properties": {
    "date:inception_lower": "1980-01-01",
    "date:inception_upper": "1980-01-01",
    "iso:country": "GB",
    "wof:name": "DA12 5PA",
    "wof:placetype": "postalcode"
  },
  "geometry": {"coordinates":[0.376616,51.430821],"type":"Point"}
}
