{
  "type": "Feature",
  "properties": {
    "iso:country":"GB",
    "wof:name":"BN2 9YF",
    "wof:placetype":"postalcode"
},
  "geometry": {"coordinates":[-0.11611673681053,50.82832063897095],"type":"Point"}
}