{
  "type": "Feature",
  "properties": {
    "iso:country":"GB",
    "wof:name":"SO40 4XH",
    "wof:placetype":"postalcode"
},
  "geometry": {"coordinates":[-1.46074133780369,50.89042632697419],"type":"Point"}
}