{
  "type": "Feature",
  "properties": {
    "date:inception_lower": "1980-01-01",
    "date:inception_upper": "1980-01-01",
    "iso:country": "GB",
    "wof:name": "B31 3RL",
    "wof:placetype": "postalcode"
  },
  "geometry": {"coordinates":[-1.967316,52.394876],"type":"Point"}
}
