{
  "type": "Feature",
  "properties": {
    "iso:country":"GB",
    "wof:name":"B31 3RL",
    "wof:placetype":"postalcode"
},
  "geometry": {"coordinates":[-1.96731652201283,52.39487622804383],"type":"Point"}
}