{
  "type": "Feature",
  "properties": {
    "date:inception_lower": "1998-06-01",
    "date:inception_upper": "1998-06-01",
    "iso:country": "GB",
    "wof:name": "YO62 5HR",
    "wof:placetype": "postalcode"
  },
  "geometry": {"coordinates":[-1.054319,54.248405],"type":"Point"}
}
