{
  "type": "Feature",
  "properties": {
    "iso:country":"GB",
    "wof:name":"YO62 5HR",
    "wof:placetype":"postalcode"
},
  "geometry": {"coordinates":[-1.05431930228437,54.24840461078991],"type":"Point"}
}