{
  "type": "Feature",
  "properties": {
    "date:inception_lower": "1980-01-01",
    "date:inception_upper": "1980-01-01",
    "iso:country": "GB",
    "wof:name": "M13 0FL",
    "wof:placetype": "postalcode"
  },
  "geometry": {"coordinates":[-2.216037,53.459168],"type":"Point"}
}
