{
  "type": "Feature",
  "properties": {
    "iso:country":"GB",
    "wof:name":"BD3 7JF",
    "wof:placetype":"postalcode"
},
  "geometry": {"coordinates":[-1.72243236529805,53.80142201855399],"type":"Point"}
}