{
  "type": "Feature",
  "properties": {
    "date:inception_lower":"1980-01-01",
    "date:inception_upper":"1980-01-31",
    "iso:country":"GB",
    "wof:name":"BD3 7JF",
    "wof:placetype":"postalcode"
},
  "geometry": {"coordinates":[-1.722432,53.801422],"type":"Point"}
}