{
  "type": "Feature",
  "properties": {
    "iso:country":"GB",
    "wof:name":"G76 0ER",
    "wof:placetype":"postalcode"
},
  "geometry": {"coordinates":[-4.28209948785325,55.76417867778214],"type":"Point"}
}