{
  "type": "Feature",
  "properties": {
    "iso:country":"GB",
    "wof:name":"B8 2RR",
    "wof:placetype":"postalcode"
},
  "geometry": {"coordinates":[-1.82438432000548,52.49893596295875],"type":"Point"}
}