{
  "type": "Feature",
  "properties": {
    "iso:country":"GB",
    "wof:name":"BS16 1NH",
    "wof:placetype":"postalcode"
},
  "geometry": {"coordinates":[-2.51931483512049,51.4979519531616],"type":"Point"}
}