{
  "type": "Feature",
  "properties": {
    "iso:country": "GB",
    "wof:name": "CA3 0HB",
    "wof:placetype": "postalcode"
  },
  "geometry": {"coordinates":[-2.952693,54.922102],"type":"Point"}
}
