{
  "type": "Feature",
  "properties": {
    "date:inception_lower": "1996-06-01",
    "date:inception_upper": "1996-06-01",
    "iso:country": "GB",
    "wof:name": "NG5 9QU",
    "wof:placetype": "postalcode"
  },
  "geometry": {"coordinates":[-1.157631,53.00998],"type":"Point"}
}
