{
  "type": "Feature",
  "properties": {
    "iso:country":"GB",
    "wof:name":"M23 2GQ",
    "wof:placetype":"postalcode"
},
  "geometry": {"coordinates":[-2.27914448717127,53.3862747574542],"type":"Point"}
}