{
  "type": "Feature",
  "properties": {
    "iso:country": "GB",
    "wof:name": "RG20 0LX",
    "wof:placetype": "postalcode"
  },
  "geometry": {"coordinates":[-1.358551,51.368668],"type":"Point"}
}
