{
  "type": "Feature",
  "properties": {
    "date:inception_lower":"1995-07-01",
    "date:inception_upper":"1995-07-31",
    "iso:country":"GB",
    "wof:name":"RG20 0LX",
    "wof:placetype":"postalcode"
},
  "geometry": {"coordinates":[-1.358551,51.368668],"type":"Point"}
}