{
  "type": "Feature",
  "properties": {
    "iso:country": "GB",
    "wof:name": "BA3 4SL",
    "wof:placetype": "postalcode"
  },
  "geometry": {"coordinates":[-2.541854,51.261353],"type":"Point"}
}
