{
  "type": "Feature",
  "properties": {
    "iso:country":"GB",
    "wof:name":"BA3 4SL",
    "wof:placetype":"postalcode"
},
  "geometry": {"coordinates":[-2.54016055504696,51.26008921648724],"type":"Point"}
}