{
  "type": "Feature",
  "properties": {
    "iso:country":"GB",
    "wof:name":"OL12 7PR",
    "wof:placetype":"postalcode"
},
  "geometry": {"coordinates":[-2.19247990897835,53.62820735557359],"type":"Point"}
}