{
  "type": "Feature",
  "properties": {
    "date:inception_lower": "1980-01-01",
    "date:inception_upper": "1980-01-01",
    "iso:country": "GB",
    "wof:name": "SW2 4BW",
    "wof:placetype": "postalcode"
  },
  "geometry": {"coordinates":[-0.134182,51.44101],"type":"Point"}
}
