{
  "type": "Feature",
  "properties": {
    "iso:country": "GB",
    "wof:name": "OX1 3QY",
    "wof:placetype": "postalcode"
  },
  "geometry": {"coordinates":[-1.253939,51.758976],"type":"Point"}
}
