{
  "type": "Feature",
  "properties": {
    "iso:country":"GB",
    "wof:name":"OX1 3QY",
    "wof:placetype":"postalcode"
},
  "geometry": {"coordinates":[-1.25393916969558,51.75897607784279],"type":"Point"}
}