{
  "type": "Feature",
  "properties": {
    "iso:country":"GB",
    "wof:name":"CB6 2ER",
    "wof:placetype":"postalcode"
},
  "geometry": {"coordinates":[0.23810081274264,52.46219942957001],"type":"Point"}
}