{
  "type": "Feature",
  "properties": {
    "iso:country":"GB",
    "wof:name":"SS14 3DP",
    "wof:placetype":"postalcode"
},
  "geometry": {"coordinates":[0.49015278863717,51.58869734985292],"type":"Point"}
}