{
  "type": "Feature",
  "properties": {
    "date:inception_lower":"2001-12-01",
    "date:inception_upper":"2001-12-31",
    "iso:country":"GB",
    "wof:name":"SS14 3DP",
    "wof:placetype":"postalcode"
},
  "geometry": {"coordinates":[0.490153,51.588697],"type":"Point"}
}