{
  "type": "Feature",
  "properties": {
    "iso:country": "GB",
    "wof:name": "ME15 6JF",
    "wof:placetype": "postalcode"
  },
  "geometry": {"coordinates":[0.526912,51.260484],"type":"Point"}
}
