{
  "type": "Feature",
  "properties": {
    "iso:country":"GB",
    "wof:name":"TR27 4LS",
    "wof:placetype":"postalcode"
},
  "geometry": {"coordinates":[-5.40881253792194,50.19013156582368],"type":"Point"}
}