{
  "type": "Feature",
  "properties": {
    "date:inception_lower": "1980-01-01",
    "date:inception_upper": "1980-01-01",
    "iso:country": "GB",
    "wof:name": "NR27 9NX",
    "wof:placetype": "postalcode"
  },
  "geometry": {"coordinates":[1.270987,52.935923],"type":"Point"}
}
