{
  "type": "Feature",
  "properties": {
    "iso:country": "GB",
    "wof:name": "NR27 9NX",
    "wof:placetype": "postalcode"
  },
  "geometry": {"coordinates":[1.270987,52.935923],"type":"Point"}
}
