{
  "type": "Feature",
  "properties": {
    "iso:country":"GB",
    "wof:name":"DD2 2UJ",
    "wof:placetype":"postalcode"
},
  "geometry": {"coordinates":[-3.02248947808666,56.46411374969772],"type":"Point"}
}