{
  "type": "Feature",
  "properties": {
    "iso:country": "GB",
    "wof:name": "BS7 9PW",
    "wof:placetype": "postalcode"
  },
  "geometry": {"coordinates":[-2.580764,51.485093],"type":"Point"}
}
