{
  "type": "Feature",
  "properties": {
    "date:inception_lower": "1980-01-01",
    "date:inception_upper": "1980-01-01",
    "iso:country": "GB",
    "wof:name": "LA2 0DR",
    "wof:placetype": "postalcode"
  },
  "geometry": {"coordinates":[-2.826367,53.985121],"type":"Point"}
}
