{
  "type": "Feature",
  "properties": {
    "date:inception_lower": "2018-01-01",
    "date:inception_upper": "2018-01-01",
    "iso:country": "GB",
    "wof:name": "MK8 1BZ",
    "wof:placetype": "postalcode"
  },
  "geometry": {"coordinates":[-0.81953,52.031254],"type":"Point"}
}
