{
  "type": "Feature",
  "properties": {
    "iso:country":"GB",
    "wof:name":"YO10 3NU",
    "wof:placetype":"postalcode"
},
  "geometry": {"coordinates":[-1.03228517607602,53.95779495095115],"type":"Point"}
}