{
  "type": "Feature",
  "properties": {
    "iso:country": "GB",
    "wof:name": "NR32 2EY",
    "wof:placetype": "postalcode"
  },
  "geometry": {"coordinates":[1.737687,52.478766],"type":"Point"}
}
