{
  "type": "Feature",
  "properties": {
    "date:inception_lower": "1980-01-01",
    "date:inception_upper": "1980-01-01",
    "iso:country": "GB",
    "wof:name": "NR32 2EY",
    "wof:placetype": "postalcode"
  },
  "geometry": {"coordinates":[1.737687,52.478766],"type":"Point"}
}
