{
  "type": "Feature",
  "properties": {
    "date:inception_lower":"1994-12-01",
    "date:inception_upper":"1994-12-31",
    "iso:country":"GB",
    "wof:name":"CB5 8PD",
    "wof:placetype":"postalcode"
},
  "geometry": {"coordinates":[0.156896,52.217199],"type":"Point"}
}