{
  "type": "Feature",
  "properties": {
    "iso:country":"GB",
    "wof:name":"BN2 9QP",
    "wof:placetype":"postalcode"
},
  "geometry": {"coordinates":[-0.13255657773625,50.82592287818988],"type":"Point"}
}