{
  "type": "Feature",
  "properties": {
    "iso:country":"GB",
    "wof:name":"IP14 1JB",
    "wof:placetype":"postalcode"
},
  "geometry": {"coordinates":[0.99229578560574,52.19213766353477],"type":"Point"}
}