{
  "type": "Feature",
  "properties": {
    "iso:country":"GB",
    "wof:name":"AB42 4QF",
    "wof:placetype":"postalcode"
},
  "geometry": {"coordinates":[-2.17576216143214,57.54079029124037],"type":"Point"}
}