{
  "type": "Feature",
  "properties": {
    "iso:country": "GB",
    "wof:name": "AB42 4QF",
    "wof:placetype": "postalcode"
  },
  "geometry": {"coordinates":[-2.175767,57.540775],"type":"Point"}
}
