{
  "type": "Feature",
  "properties": {
    "iso:country":"GB",
    "wof:name":"NG3 7AY",
    "wof:placetype":"postalcode"
},
  "geometry": {"coordinates":[-1.11426657162184,52.96448426284376],"type":"Point"}
}