{
  "type": "Feature",
  "properties": {
    "iso:country":"GB",
    "wof:name":"CT14 6BE",
    "wof:placetype":"postalcode"
},
  "geometry": {"coordinates":[1.40278911793898,51.2267690684185],"type":"Point"}
}