{
  "type": "Feature",
  "properties": {
    "iso:country":"GB",
    "wof:name":"EH3 9NG",
    "wof:placetype":"postalcode"
},
  "geometry": {"coordinates":[-3.20574450624076,55.94145654650664],"type":"Point"}
}