{
  "type": "Feature",
  "properties": {
    "date:inception_lower":"2014-08-01",
    "date:inception_upper":"2014-08-31",
    "iso:country":"GB",
    "wof:name":"BR3 4FB",
    "wof:placetype":"postalcode"
},
  "geometry": {"coordinates":[-0.04236,51.399351],"type":"Point"}
}