{
  "type": "Feature",
  "properties": {
    "iso:country":"GB",
    "wof:name":"BR3 4FB",
    "wof:placetype":"postalcode"
},
  "geometry": {"coordinates":[-0.04235996160314,51.39935062245441],"type":"Point"}
}