{
  "type": "Feature",
  "properties": {
    "iso:country": "GB",
    "wof:name": "BR3 4FB",
    "wof:placetype": "postalcode"
  },
  "geometry": {"coordinates":[-0.04236,51.399351],"type":"Point"}
}
