{
  "type": "Feature",
  "properties": {
    "date:inception_lower": "2023-07-01",
    "date:inception_upper": "2023-07-01",
    "iso:country": "GB",
    "wof:name": "MK18 2RB",
    "wof:placetype": "postalcode"
  },
  "geometry": {"coordinates":[-0.991004,51.933062],"type":"Point"}
}
