{
  "type": "Feature",
  "properties": {
    "iso:country": "GB",
    "wof:name": "SN3 4AZ",
    "wof:placetype": "postalcode"
  },
  "geometry": {"coordinates":[-1.7411,51.574112],"type":"Point"}
}
