{
  "type": "Feature",
  "properties": {
    "iso:country":"GB",
    "wof:name":"EN7 6RG",
    "wof:placetype":"postalcode"
},
  "geometry": {"coordinates":[-0.07560734828188,51.72241797297779],"type":"Point"}
}