{
  "type": "Feature",
  "properties": {
    "iso:country": "GB",
    "wof:name": "BH6 3BY",
    "wof:placetype": "postalcode"
  },
  "geometry": {"coordinates":[-1.792287,50.727768],"type":"Point"}
}
