{
  "type": "Feature",
  "properties": {
    "iso:country":"GB",
    "wof:name":"BH6 3BY",
    "wof:placetype":"postalcode"
},
  "geometry": {"coordinates":[-1.79228705459681,50.72776799574114],"type":"Point"}
}