{
  "type": "Feature",
  "properties": {
    "iso:country": "GB",
    "wof:name": "TQ5 9HY",
    "wof:placetype": "postalcode"
  },
  "geometry": {"coordinates":[-3.515358,50.3908],"type":"Point"}
}
