{
  "type": "Feature",
  "properties": {
    "date:inception_lower": "1980-01-01",
    "date:inception_upper": "1980-01-01",
    "iso:country": "GB",
    "wof:name": "GU1 4TX",
    "wof:placetype": "postalcode"
  },
  "geometry": {"coordinates":[-0.58164,51.243373],"type":"Point"}
}
