{
  "type": "Feature",
  "properties": {
    "iso:country": "GB",
    "wof:name": "GU22 9LN",
    "wof:placetype": "postalcode"
  },
  "geometry": {"coordinates":[-0.545399,51.302399],"type":"Point"}
}
