{
  "type": "Feature",
  "properties": {
    "iso:country":"GB",
    "wof:name":"N22 6PB",
    "wof:placetype":"postalcode"
},
  "geometry": {"coordinates":[-0.10524739417616,51.59584684998465],"type":"Point"}
}