{
  "type": "Feature",
  "properties": {
    "date:inception_lower":"2015-04-01",
    "date:inception_upper":"2015-04-30",
    "iso:country":"GB",
    "wof:name":"OX11 6DP",
    "wof:placetype":"postalcode"
},
  "geometry": {"coordinates":[-1.269604,51.60573],"type":"Point"}
}