{
  "type": "Feature",
  "properties": {
    "iso:country":"GB",
    "wof:name":"OX11 6DP",
    "wof:placetype":"postalcode"
},
  "geometry": {"coordinates":[-1.26906963841788,51.60504925509772],"type":"Point"}
}