{
  "type": "Feature",
  "properties": {
    "iso:country":"GB",
    "wof:name":"KY11 2RE",
    "wof:placetype":"postalcode"
},
  "geometry": {"coordinates":[-3.42445579138439,56.03961795822455],"type":"Point"}
}