{
  "type": "Feature",
  "properties": {
    "date:inception_lower": "2021-01-01",
    "date:inception_upper": "2021-01-01",
    "iso:country": "GB",
    "wof:name": "PR4 0FY",
    "wof:placetype": "postalcode"
  },
  "geometry": {"coordinates":[-2.742065,53.793592],"type":"Point"}
}
