{
  "type": "Feature",
  "properties": {
    "date:inception_lower": "1980-01-01",
    "date:inception_upper": "1980-01-01",
    "iso:country": "GB",
    "wof:name": "SO21 2NL",
    "wof:placetype": "postalcode"
  },
  "geometry": {"coordinates":[-1.381078,51.079303],"type":"Point"}
}
