{
  "type": "Feature",
  "properties": {
    "iso:country": "GB",
    "wof:name": "GL17 0AX",
    "wof:placetype": "postalcode"
  },
  "geometry": {"coordinates":[-2.489583,51.865355],"type":"Point"}
}
