{
  "type": "Feature",
  "properties": {
    "iso:country":"GB",
    "wof:name":"NG3 5AW",
    "wof:placetype":"postalcode"
},
  "geometry": {"coordinates":[-1.14601918188975,52.96926523332532],"type":"Point"}
}