{
  "type": "Feature",
  "properties": {
    "iso:country":"GB",
    "wof:name":"ST15 8TG",
    "wof:placetype":"postalcode"
},
  "geometry": {"coordinates":[-2.11109337689458,52.92756598108942],"type":"Point"}
}