{
  "type": "Feature",
  "properties": {
    "iso:country": "GB",
    "wof:name": "ST15 8TG",
    "wof:placetype": "postalcode"
  },
  "geometry": {"coordinates":[-2.11124,52.927582],"type":"Point"}
}
