{
  "type": "Feature",
  "properties": {
    "iso:country":"GB",
    "wof:name":"DL3 9JB",
    "wof:placetype":"postalcode"
},
  "geometry": {"coordinates":[-1.57318341639155,54.533930823636],"type":"Point"}
}