{
  "type": "Feature",
  "properties": {
    "iso:country": "GB",
    "wof:name": "DE55 3AA",
    "wof:placetype": "postalcode"
  },
  "geometry": {"coordinates":[-1.332746,53.097559],"type":"Point"}
}
