{
  "type": "Feature",
  "properties": {
    "iso:country":"GB",
    "wof:name":"DE55 3AA",
    "wof:placetype":"postalcode"
},
  "geometry": {"coordinates":[-1.33274570052163,53.09755900525486],"type":"Point"}
}