{
  "type": "Feature",
  "properties": {
    "iso:country":"GB",
    "wof:name":"KY1 1HD",
    "wof:placetype":"postalcode"
},
  "geometry": {"coordinates":[-3.15752772759246,56.11324224617147],"type":"Point"}
}