{
  "type": "Feature",
  "properties": {
    "date:inception_lower": "2013-07-01",
    "date:inception_upper": "2013-07-01",
    "iso:country": "GB",
    "wof:name": "KY1 1HD",
    "wof:placetype": "postalcode"
  },
  "geometry": {"coordinates":[-3.157528,56.113242],"type":"Point"}
}
