{
  "type": "Feature",
  "properties": {
    "iso:country": "GB",
    "wof:name": "WA4 6RS",
    "wof:placetype": "postalcode"
  },
  "geometry": {"coordinates":[-2.582979,53.37573],"type":"Point"}
}
