{
  "type": "Feature",
  "properties": {
    "iso:country": "GB",
    "wof:name": "YO17 8FB",
    "wof:placetype": "postalcode"
  },
  "geometry": {"coordinates":[-0.695927,54.160482],"type":"Point"}
}
