{
  "type": "Feature",
  "properties": {
    "iso:country":"GB",
    "wof:name":"GU47 0RQ",
    "wof:placetype":"postalcode"
},
  "geometry": {"coordinates":[-0.77362092526196,51.34953158112616],"type":"Point"}
}