{
  "type": "Feature",
  "properties": {
    "iso:country": "GB",
    "wof:name": "GU47 0RQ",
    "wof:placetype": "postalcode"
  },
  "geometry": {"coordinates":[-0.773621,51.349532],"type":"Point"}
}
