{
  "type": "Feature",
  "properties": {
    "iso:country":"GB",
    "wof:name":"BN2 0LA",
    "wof:placetype":"postalcode"
},
  "geometry": {"coordinates":[-0.13382431235596,50.82368580346213],"type":"Point"}
}