{
  "type": "Feature",
  "properties": {
    "iso:country":"GB",
    "wof:name":"SR4 7EQ",
    "wof:placetype":"postalcode"
},
  "geometry": {"coordinates":[-1.39924135485898,54.90429072697534],"type":"Point"}
}