{
  "type": "Feature",
  "properties": {
    "iso:country":"GB",
    "wof:name":"BA1 4EA",
    "wof:placetype":"postalcode"
},
  "geometry": {"coordinates":[-2.3976861523277,51.39673274893657],"type":"Point"}
}