{
  "type": "Feature",
  "properties": {
    "iso:country":"GB",
    "wof:name":"PE11 4EU",
    "wof:placetype":"postalcode"
},
  "geometry": {"coordinates":[-0.20476004497737,52.85459503764434],"type":"Point"}
}