{
  "type": "Feature",
  "properties": {
    "date:inception_lower": "2017-11-01",
    "date:inception_upper": "2017-11-01",
    "iso:country": "GB",
    "wof:name": "PR25 5AN",
    "wof:placetype": "postalcode"
  },
  "geometry": {"coordinates":[-2.669726,53.700963],"type":"Point"}
}
