{
  "type": "Feature",
  "properties": {
    "iso:country":"GB",
    "wof:name":"HU3 3SG",
    "wof:placetype":"postalcode"
},
  "geometry": {"coordinates":[-0.37077395500711,53.73520678465109],"type":"Point"}
}