{
  "type": "Feature",
  "properties": {
    "iso:country":"GB",
    "wof:name":"SE4 1EG",
    "wof:placetype":"postalcode"
},
  "geometry": {"coordinates":[-0.03177826030329,51.45359749766819],"type":"Point"}
}