{
  "type": "Feature",
  "properties": {
    "date:inception_lower": "1980-01-01",
    "date:inception_upper": "1980-01-01",
    "iso:country": "GB",
    "wof:name": "S74 0RX",
    "wof:placetype": "postalcode"
  },
  "geometry": {"coordinates":[-1.446743,53.515377],"type":"Point"}
}
