{
  "type": "Feature",
  "properties": {
    "iso:country":"GB",
    "wof:name":"S74 0RX",
    "wof:placetype":"postalcode"
},
  "geometry": {"coordinates":[-1.44674322460918,53.51537713681052],"type":"Point"}
}