{
  "type": "Feature",
  "properties": {
    "iso:country": "GB",
    "wof:name": "NE67 5HE",
    "wof:placetype": "postalcode"
  },
  "geometry": {"coordinates":[-1.739087,55.52587],"type":"Point"}
}
