{
  "type": "Feature",
  "properties": {
    "iso:country":"GB",
    "wof:name":"BA3 3PY",
    "wof:placetype":"postalcode"
},
  "geometry": {"coordinates":[-2.44379424181193,51.29094086645112],"type":"Point"}
}