{
  "type": "Feature",
  "properties": {
    "iso:country": "GB",
    "wof:name": "TA1 3AG",
    "wof:placetype": "postalcode"
  },
  "geometry": {"coordinates":[-3.090458,51.012661],"type":"Point"}
}
