{
  "type": "Feature",
  "properties": {
    "iso:country":"GB",
    "wof:name":"TA1 3AG",
    "wof:placetype":"postalcode"
},
  "geometry": {"coordinates":[-3.09045771255316,51.01266095048931],"type":"Point"}
}