{
  "type": "Feature",
  "properties": {
    "iso:country":"GB",
    "wof:name":"S25 1ZH",
    "wof:placetype":"postalcode"
},
  "geometry": {"coordinates":[-1.22072552467668,53.38786251219233],"type":"Point"}
}