{
  "type": "Feature",
  "properties": {
    "date:inception_lower": "1980-01-01",
    "date:inception_upper": "1980-01-01",
    "iso:country": "GB",
    "wof:name": "RG14 7EN",
    "wof:placetype": "postalcode"
  },
  "geometry": {"coordinates":[-1.326089,51.386355],"type":"Point"}
}
