{
  "type": "Feature",
  "properties": {
    "iso:country":"GB",
    "wof:name":"ST3 4EW",
    "wof:placetype":"postalcode"
},
  "geometry": {"coordinates":[-2.13725449439462,52.97763564079425],"type":"Point"}
}