{
  "type": "Feature",
  "properties": {
    "iso:country":"GB",
    "wof:name":"IV31 6BL",
    "wof:placetype":"postalcode"
},
  "geometry": {"coordinates":[-3.28909181497231,57.72347269945985],"type":"Point"}
}