{
  "type": "Feature",
  "properties": {
    "iso:country":"GB",
    "wof:name":"CV10 8JF",
    "wof:placetype":"postalcode"
},
  "geometry": {"coordinates":[-1.50702958431502,52.52142314344349],"type":"Point"}
}