{
  "type": "Feature",
  "properties": {
    "iso:country":"GB",
    "wof:name":"BS23 3AP",
    "wof:placetype":"postalcode"
},
  "geometry": {"coordinates":[-2.97196055435138,51.34958489661005],"type":"Point"}
}