{
  "type": "Feature",
  "properties": {
    "iso:country":"GB",
    "wof:name":"NG8 4JJ",
    "wof:placetype":"postalcode"
},
  "geometry": {"coordinates":[-1.22117080288447,52.96177159513618],"type":"Point"}
}