{
  "type": "Feature",
  "properties": {
    "iso:country":"GB",
    "wof:name":"EH22 4NB",
    "wof:placetype":"postalcode"
},
  "geometry": {"coordinates":[-3.06958602749329,55.86919550963334],"type":"Point"}
}