{
  "type": "Feature",
  "properties": {
    "iso:country":"GB",
    "wof:name":"TN29 0QD",
    "wof:placetype":"postalcode"
},
  "geometry": {"coordinates":[0.98834918437114,51.01865259717679],"type":"Point"}
}