{
  "type": "Feature",
  "properties": {
    "iso:country":"GB",
    "wof:name":"NR24 2BS",
    "wof:placetype":"postalcode"
},
  "geometry": {"coordinates":[1.03426386610019,52.85596547253205],"type":"Point"}
}