{
  "type": "Feature",
  "properties": {
    "date:inception_lower":"1990-07-01",
    "date:inception_upper":"1990-07-31",
    "iso:country":"GB",
    "wof:name":"NG18 3BY",
    "wof:placetype":"postalcode"
},
  "geometry": {"coordinates":[-1.166705,53.145459],"type":"Point"}
}