{
  "type": "Feature",
  "properties": {
    "iso:country":"GB",
    "wof:name":"CV5 8EA",
    "wof:placetype":"postalcode"
},
  "geometry": {"coordinates":[-1.53785088195186,52.4071309803222],"type":"Point"}
}