{
  "type": "Feature",
  "properties": {
    "date:inception_lower": "1980-01-01",
    "date:inception_upper": "1980-01-01",
    "iso:country": "GB",
    "wof:name": "NR9 5QS",
    "wof:placetype": "postalcode"
  },
  "geometry": {"coordinates":[1.089049,52.728783],"type":"Point"}
}
