{
  "type": "Feature",
  "properties": {
    "iso:country": "GB",
    "wof:name": "PO21 4UN",
    "wof:placetype": "postalcode"
  },
  "geometry": {"coordinates":[-0.742178,50.770552],"type":"Point"}
}
