{
  "type": "Feature",
  "properties": {
    "iso:country":"GB",
    "wof:name":"PO21 4UN",
    "wof:placetype":"postalcode"
},
  "geometry": {"coordinates":[-0.74217766290081,50.77055160765224],"type":"Point"}
}