{
  "type": "Feature",
  "properties": {
    "iso:country":"GB",
    "wof:name":"ML5 3NL",
    "wof:placetype":"postalcode"
},
  "geometry": {"coordinates":[-4.01866279550376,55.86215571635228],"type":"Point"}
}