{
  "type": "Feature",
  "properties": {
    "date:inception_lower": "1991-01-01",
    "date:inception_upper": "1991-01-01",
    "iso:country": "GB",
    "wof:name": "PO31 8RE",
    "wof:placetype": "postalcode"
  },
  "geometry": {"coordinates":[-1.324343,50.749432],"type":"Point"}
}
