{
  "type": "Feature",
  "properties": {
    "date:inception_lower":"2009-01-01",
    "date:inception_upper":"2009-01-31",
    "iso:country":"GB",
    "wof:name":"S26 6LN",
    "wof:placetype":"postalcode"
},
  "geometry": {"coordinates":[-1.268036,53.341],"type":"Point"}
}