{
  "type": "Feature",
  "properties": {
    "iso:country":"GB",
    "wof:name":"S26 6LN",
    "wof:placetype":"postalcode"
},
  "geometry": {"coordinates":[-1.26803509963248,53.34097950293071],"type":"Point"}
}