{
  "type": "Feature",
  "properties": {
    "iso:country": "GB",
    "wof:name": "SW17 7LG",
    "wof:placetype": "postalcode"
  },
  "geometry": {"coordinates":[-0.166421,51.43329],"type":"Point"}
}
