{
  "type": "Feature",
  "properties": {
    "date:inception_lower":"1980-01-01",
    "date:inception_upper":"1980-01-31",
    "iso:country":"GB",
    "wof:name":"SL7 3BH",
    "wof:placetype":"postalcode"
},
  "geometry": {"coordinates":[-0.781334,51.578629],"type":"Point"}
}