{
  "type": "Feature",
  "properties": {
    "iso:country": "GB",
    "wof:name": "SL7 3BH",
    "wof:placetype": "postalcode"
  },
  "geometry": {"coordinates":[-0.781334,51.578629],"type":"Point"}
}
