{
  "type": "Feature",
  "properties": {
    "iso:country":"GB",
    "wof:name":"SL7 3BH",
    "wof:placetype":"postalcode"
},
  "geometry": {"coordinates":[-0.78133407100494,51.5786285959903],"type":"Point"}
}