{
  "type": "Feature",
  "properties": {
    "date:inception_lower": "2023-10-01",
    "date:inception_upper": "2023-10-01",
    "iso:country": "GB",
    "wof:name": "CO12 4NG",
    "wof:placetype": "postalcode"
  },
  "geometry": {"coordinates":[1.245428,51.927099],"type":"Point"}
}
