{
  "type": "Feature",
  "properties": {
    "iso:country":"GB",
    "wof:name":"WC1B 5AB",
    "wof:placetype":"postalcode"
},
  "geometry": {"coordinates":[-0.12267909577041,51.52076112231536],"type":"Point"}
}