{
  "type": "Feature",
  "properties": {
    "iso:country": "GB",
    "wof:name": "TF10 9EX",
    "wof:placetype": "postalcode"
  },
  "geometry": {"coordinates":[-2.396475,52.741251],"type":"Point"}
}
