{
  "type": "Feature",
  "properties": {
    "iso:country": "GB",
    "wof:name": "EH32 0BF",
    "wof:placetype": "postalcode"
  },
  "geometry": {"coordinates":[-2.948141,55.969563],"type":"Point"}
}
