{
  "type": "Feature",
  "properties": {
    "iso:country":"GB",
    "wof:name":"LU1 3TD",
    "wof:placetype":"postalcode"
},
  "geometry": {"coordinates":[-0.40145124674613,51.84520378522213],"type":"Point"}
}