{
  "type": "Feature",
  "properties": {
    "iso:country":"GB",
    "wof:name":"LE16 7US",
    "wof:placetype":"postalcode"
},
  "geometry": {"coordinates":[-0.93073506710374,52.48789891137167],"type":"Point"}
}