{
  "type": "Feature",
  "properties": {
    "iso:country": "GB",
    "wof:name": "LE16 7US",
    "wof:placetype": "postalcode"
  },
  "geometry": {"coordinates":[-0.930735,52.487899],"type":"Point"}
}
