{
  "type": "Feature",
  "properties": {
    "iso:country": "GB",
    "wof:name": "M19 3ZF",
    "wof:placetype": "postalcode"
  },
  "geometry": {"coordinates":[-2.170957,53.447286],"type":"Point"}
}
