{
  "type": "Feature",
  "properties": {
    "iso:country":"GB",
    "wof:name":"M19 3ZF",
    "wof:placetype":"postalcode"
},
  "geometry": {"coordinates":[-2.17095733170627,53.4472864101722],"type":"Point"}
}