{
  "type": "Feature",
  "properties": {
    "date:inception_lower":"1995-01-01",
    "date:inception_upper":"1995-01-31",
    "iso:country":"GB",
    "wof:name":"M19 3ZF",
    "wof:placetype":"postalcode"
},
  "geometry": {"coordinates":[-2.170957,53.447286],"type":"Point"}
}