{
  "type": "Feature",
  "properties": {
    "iso:country":"GB",
    "wof:name":"YO8 4YY",
    "wof:placetype":"postalcode"
},
  "geometry": {"coordinates":[-1.08189132481917,53.78907134810451],"type":"Point"}
}