{
  "type": "Feature",
  "properties": {
    "date:inception_lower": "1998-06-01",
    "date:inception_upper": "1998-06-01",
    "iso:country": "GB",
    "wof:name": "YO8 4YY",
    "wof:placetype": "postalcode"
  },
  "geometry": {"coordinates":[-1.081891,53.789071],"type":"Point"}
}
