{
  "type": "Feature",
  "properties": {
    "iso:country":"GB",
    "wof:name":"BS48 3PG",
    "wof:placetype":"postalcode"
},
  "geometry": {"coordinates":[-2.72695025389806,51.41862968433961],"type":"Point"}
}