{
  "type": "Feature",
  "properties": {
    "iso:country":"GB",
    "wof:name":"CB24 6ZL",
    "wof:placetype":"postalcode"
},
  "geometry": {"coordinates":[0.15794188518719,52.24179054412009],"type":"Point"}
}