{
  "type": "Feature",
  "properties": {
    "iso:country": "GB",
    "wof:name": "CB24 6ZL",
    "wof:placetype": "postalcode"
  },
  "geometry": {"coordinates":[0.157942,52.241791],"type":"Point"}
}
