{
  "type": "Feature",
  "properties": {
    "iso:country":"GB",
    "wof:name":"SL2 1PF",
    "wof:placetype":"postalcode"
},
  "geometry": {"coordinates":[-0.60635991201254,51.53056166408469],"type":"Point"}
}