{
  "type": "Feature",
  "properties": {
    "date:inception_lower":"1980-01-01",
    "date:inception_upper":"1980-01-31",
    "iso:country":"GB",
    "wof:name":"SL2 1PF",
    "wof:placetype":"postalcode"
},
  "geometry": {"coordinates":[-0.60636,51.530562],"type":"Point"}
}