{
  "type": "Feature",
  "properties": {
    "date:inception_lower": "2022-10-01",
    "date:inception_upper": "2022-10-01",
    "iso:country": "GB",
    "wof:name": "TN25 7LJ",
    "wof:placetype": "postalcode"
  },
  "geometry": {"coordinates":[0.883076,51.106262],"type":"Point"}
}
