{
  "type": "Feature",
  "properties": {
    "date:inception_lower": "2018-04-01",
    "date:inception_upper": "2018-04-01",
    "iso:country": "GB",
    "wof:name": "E14 5LJ",
    "wof:placetype": "postalcode"
  },
  "geometry": {"coordinates":[-0.017463,51.503978],"type":"Point"}
}
