{
  "type": "Feature",
  "properties": {
    "iso:country":"GB",
    "wof:name":"LN2 2RS",
    "wof:placetype":"postalcode"
},
  "geometry": {"coordinates":[-0.4762534491244,53.26286550261803],"type":"Point"}
}