{
  "type": "Feature",
  "properties": {
    "iso:country":"GB",
    "wof:name":"PO1 5LF",
    "wof:placetype":"postalcode"
},
  "geometry": {"coordinates":[-1.07327648557434,50.80478476255886],"type":"Point"}
}