{
  "type": "Feature",
  "properties": {
    "date:inception_lower": "1980-01-01",
    "date:inception_upper": "1980-01-01",
    "iso:country": "GB",
    "wof:name": "PO1 5LF",
    "wof:placetype": "postalcode"
  },
  "geometry": {"coordinates":[-1.073276,50.804785],"type":"Point"}
}
