{
  "type": "Feature",
  "properties": {
    "date:inception_lower":"2009-07-01",
    "date:inception_upper":"2009-07-31",
    "iso:country":"GB",
    "wof:name":"BA4 4FF",
    "wof:placetype":"postalcode"
},
  "geometry": {"coordinates":[-2.613672,51.165877],"type":"Point"}
}