{
  "type": "Feature",
  "properties": {
    "iso:country":"GB",
    "wof:name":"GU20 6JN",
    "wof:placetype":"postalcode"
},
  "geometry": {"coordinates":[-0.66873366362589,51.37642444389535],"type":"Point"}
}