{
  "type": "Feature",
  "properties": {
    "iso:country": "GB",
    "wof:name": "DY12 2LB",
    "wof:placetype": "postalcode"
  },
  "geometry": {"coordinates":[-2.333343,52.375252],"type":"Point"}
}
