{
  "type": "Feature",
  "properties": {
    "iso:country":"GB",
    "wof:name":"LL55 2SG",
    "wof:placetype":"postalcode"
},
  "geometry": {"coordinates":[-4.24587653212356,53.13226450159152],"type":"Point"}
}