{
  "type": "Feature",
  "properties": {
    "iso:country":"GB",
    "wof:name":"EX5 1LH",
    "wof:placetype":"postalcode"
},
  "geometry": {"coordinates":[-3.40497321735688,50.67414018660752],"type":"Point"}
}