{
  "type": "Feature",
  "properties": {
    "date:inception_lower":"1980-01-01",
    "date:inception_upper":"1980-01-31",
    "iso:country":"GB",
    "wof:name":"EX5 1LH",
    "wof:placetype":"postalcode"
},
  "geometry": {"coordinates":[-3.404973,50.67414],"type":"Point"}
}