{
  "type": "Feature",
  "properties": {
    "iso:country":"GB",
    "wof:name":"BR2 9EP",
    "wof:placetype":"postalcode"
},
  "geometry": {"coordinates":[0.01719780003119,51.38684756336209],"type":"Point"}
}