{
  "type": "Feature",
  "properties": {
    "iso:country":"GB",
    "wof:name":"YO10 3TT",
    "wof:placetype":"postalcode"
},
  "geometry": {"coordinates":[-1.05311344967639,53.95803277398134],"type":"Point"}
}