{
  "type": "Feature",
  "properties": {
    "iso:country":"GB",
    "wof:name":"HR1 3NQ",
    "wof:placetype":"postalcode"
},
  "geometry": {"coordinates":[-2.66464319534462,52.08291120850298],"type":"Point"}
}