{
  "type": "Feature",
  "properties": {
    "date:inception_lower": "2020-09-01",
    "date:inception_upper": "2020-09-01",
    "iso:country": "GB",
    "wof:name": "S41 8FG",
    "wof:placetype": "postalcode"
  },
  "geometry": {"coordinates":[-1.45249,53.262031],"type":"Point"}
}
