{
  "type": "Feature",
  "properties": {
    "iso:country":"GB",
    "wof:name":"N22 6XD",
    "wof:placetype":"postalcode"
},
  "geometry": {"coordinates":[-0.10966453048635,51.59552240973665],"type":"Point"}
}