{
  "type": "Feature",
  "properties": {
    "iso:country": "GB",
    "wof:name": "NG4 4HU",
    "wof:placetype": "postalcode"
  },
  "geometry": {"coordinates":[-1.094716,52.982388],"type":"Point"}
}
