{
  "type": "Feature",
  "properties": {
    "iso:country":"GB",
    "wof:name":"HA3 7LL",
    "wof:placetype":"postalcode"
},
  "geometry": {"coordinates":[-0.32198910666962,51.60061130128491],"type":"Point"}
}