{
  "type": "Feature",
  "properties": {
    "date:inception_lower":"1980-01-01",
    "date:inception_upper":"1980-01-31",
    "iso:country":"GB",
    "wof:name":"DL15 8LQ",
    "wof:placetype":"postalcode"
},
  "geometry": {"coordinates":[-1.747461,54.710623],"type":"Point"}
}