{
  "type": "Feature",
  "properties": {
    "iso:country":"GB",
    "wof:name":"DL15 8LQ",
    "wof:placetype":"postalcode"
},
  "geometry": {"coordinates":[-1.74746120732188,54.71062293525185],"type":"Point"}
}