{
  "type": "Feature",
  "properties": {
    "iso:country": "GB",
    "wof:name": "DL15 8LQ",
    "wof:placetype": "postalcode"
  },
  "geometry": {"coordinates":[-1.747461,54.710623],"type":"Point"}
}
