{
  "type": "Feature",
  "properties": {
    "iso:country": "GB",
    "wof:name": "DT6 9DD",
    "wof:placetype": "postalcode"
  },
  "geometry": {"coordinates":[-2.759434,50.734183],"type":"Point"}
}
