{
  "type": "Feature",
  "properties": {
    "iso:country":"GB",
    "wof:name":"TQ9 6QZ",
    "wof:placetype":"postalcode"
},
  "geometry": {"coordinates":[-3.62412800469784,50.40337967610909],"type":"Point"}
}