{
  "type": "Feature",
  "properties": {
    "date:inception_lower":"1994-12-01",
    "date:inception_upper":"1994-12-31",
    "iso:country":"GB",
    "wof:name":"S75 4HF",
    "wof:placetype":"postalcode"
},
  "geometry": {"coordinates":[-1.567599,53.548063],"type":"Point"}
}