{
  "type": "Feature",
  "properties": {
    "iso:country":"GB",
    "wof:name":"S75 4HF",
    "wof:placetype":"postalcode"
},
  "geometry": {"coordinates":[-1.56759941112788,53.54806261647737],"type":"Point"}
}