{
  "type": "Feature",
  "properties": {
    "iso:country": "GB",
    "wof:name": "S75 4HF",
    "wof:placetype": "postalcode"
  },
  "geometry": {"coordinates":[-1.567599,53.548063],"type":"Point"}
}
