{
  "type": "Feature",
  "properties": {
    "iso:country": "GB",
    "wof:name": "BA6 9SB",
    "wof:placetype": "postalcode"
  },
  "geometry": {"coordinates":[-2.775106,51.171402],"type":"Point"}
}
