{
  "type": "Feature",
  "properties": {
    "iso:country":"GB",
    "wof:name":"BA6 9SB",
    "wof:placetype":"postalcode"
},
  "geometry": {"coordinates":[-2.77510629640767,51.17140182594014],"type":"Point"}
}