{
  "type": "Feature",
  "properties": {
    "date:inception_lower": "2002-09-01",
    "date:inception_upper": "2002-09-01",
    "iso:country": "GB",
    "wof:name": "BA6 9SB",
    "wof:placetype": "postalcode"
  },
  "geometry": {"coordinates":[-2.775106,51.171402],"type":"Point"}
}
