{
  "type": "Feature",
  "properties": {
    "iso:country": "GB",
    "wof:name": "KT15 1FH",
    "wof:placetype": "postalcode"
  },
  "geometry": {"coordinates":[-0.505183,51.357331],"type":"Point"}
}
