{
  "type": "Feature",
  "properties": {
    "date:inception_lower": "2014-02-01",
    "date:inception_upper": "2014-02-01",
    "iso:country": "GB",
    "wof:name": "KT15 1FH",
    "wof:placetype": "postalcode"
  },
  "geometry": {"coordinates":[-0.505183,51.357331],"type":"Point"}
}
