{
  "type": "Feature",
  "properties": {
    "iso:country":"GB",
    "wof:name":"DA15 8HS",
    "wof:placetype":"postalcode"
},
  "geometry": {"coordinates":[0.09401284973397,51.44711928818611],"type":"Point"}
}