{
  "type": "Feature",
  "properties": {
    "iso:country": "GB",
    "wof:name": "SA15 1TT",
    "wof:placetype": "postalcode"
  },
  "geometry": {"coordinates":[-4.16151,51.678501],"type":"Point"}
}
