{
  "type": "Feature",
  "properties": {
    "iso:country":"GB",
    "wof:name":"LA16 7AT",
    "wof:placetype":"postalcode"
},
  "geometry": {"coordinates":[-3.2088769948891,54.1872844624092],"type":"Point"}
}