{
  "type": "Feature",
  "properties": {
    "iso:country": "GB",
    "wof:name": "OX14 5DG",
    "wof:placetype": "postalcode"
  },
  "geometry": {"coordinates":[-1.288748,51.669768],"type":"Point"}
}
