{
  "type": "Feature",
  "properties": {
    "iso:country":"GB",
    "wof:name":"PL7 1RE",
    "wof:placetype":"postalcode"
},
  "geometry": {"coordinates":[-4.0650176034412,50.38653718995589],"type":"Point"}
}