{
  "type": "Feature",
  "properties": {
    "iso:country": "GB",
    "wof:name": "BS22 9AD",
    "wof:placetype": "postalcode"
  },
  "geometry": {"coordinates":[-2.944693,51.360086],"type":"Point"}
}
