{
  "type": "Feature",
  "properties": {
    "iso:country":"GB",
    "wof:name":"BS22 9AD",
    "wof:placetype":"postalcode"
},
  "geometry": {"coordinates":[-2.94469272858464,51.36008582928494],"type":"Point"}
}