{
  "type": "Feature",
  "properties": {
    "date:inception_lower":"1980-01-01",
    "date:inception_upper":"1980-01-31",
    "iso:country":"GB",
    "wof:name":"BS22 9AD",
    "wof:placetype":"postalcode"
},
  "geometry": {"coordinates":[-2.944693,51.360086],"type":"Point"}
}