{
  "type": "Feature",
  "properties": {
    "iso:country":"GB",
    "wof:name":"TN1 2EA",
    "wof:placetype":"postalcode"
},
  "geometry": {"coordinates":[0.26729086797943,51.14087469146139],"type":"Point"}
}