{
  "type": "Feature",
  "properties": {
    "date:inception_lower": "1980-01-01",
    "date:inception_upper": "1980-01-01",
    "iso:country": "GB",
    "wof:name": "TN1 2EA",
    "wof:placetype": "postalcode"
  },
  "geometry": {"coordinates":[0.267291,51.140875],"type":"Point"}
}
