{
  "type": "Feature",
  "properties": {
    "iso:country": "GB",
    "wof:name": "YO23 1BS",
    "wof:placetype": "postalcode"
  },
  "geometry": {"coordinates":[-1.090033,53.95279],"type":"Point"}
}
