{
  "type": "Feature",
  "properties": {
    "iso:country":"GB",
    "wof:name":"PE38 9HZ",
    "wof:placetype":"postalcode"
},
  "geometry": {"coordinates":[0.37427570490023,52.60163325859109],"type":"Point"}
}