{
  "type": "Feature",
  "properties": {
    "iso:country":"GB",
    "wof:name":"SA19 7SU",
    "wof:placetype":"postalcode"
},
  "geometry": {"coordinates":[-4.01384966991481,51.89779691248519],"type":"Point"}
}