{
  "type": "Feature",
  "properties": {
    "iso:country": "GB",
    "wof:name": "SA19 7SU",
    "wof:placetype": "postalcode"
  },
  "geometry": {"coordinates":[-4.01385,51.897797],"type":"Point"}
}
