{
  "type": "Feature",
  "properties": {
    "iso:country":"GB",
    "wof:name":"WS1 2JJ",
    "wof:placetype":"postalcode"
},
  "geometry": {"coordinates":[-1.97204840943428,52.58273131422978],"type":"Point"}
}