{
  "type": "Feature",
  "properties": {
    "iso:country":"GB",
    "wof:name":"RH2 8DF",
    "wof:placetype":"postalcode"
},
  "geometry": {"coordinates":[-0.20426256400294,51.21747592057271],"type":"Point"}
}