{
  "type": "Feature",
  "properties": {
    "iso:country":"GB",
    "wof:name":"WA1 2GE",
    "wof:placetype":"postalcode"
},
  "geometry": {"coordinates":[-2.58494650789405,53.3887809555404],"type":"Point"}
}