{
  "type": "Feature",
  "properties": {
    "iso:country":"GB",
    "wof:name":"SE15 5JQ",
    "wof:placetype":"postalcode"
},
  "geometry": {"coordinates":[-0.07744004951427,51.47640522451287],"type":"Point"}
}