{
  "type": "Feature",
  "properties": {
    "date:inception_lower": "1997-12-01",
    "date:inception_upper": "1997-12-01",
    "iso:country": "GB",
    "wof:name": "SE15 5JQ",
    "wof:placetype": "postalcode"
  },
  "geometry": {"coordinates":[-0.07744,51.476405],"type":"Point"}
}
