{
  "type": "Feature",
  "properties": {
    "iso:country":"GB",
    "wof:name":"S5 0TX",
    "wof:placetype":"postalcode"
},
  "geometry": {"coordinates":[-1.43678727948059,53.4313324695912],"type":"Point"}
}