{
  "type": "Feature",
  "properties": {
    "iso:country": "GB",
    "wof:name": "CA1 3DB",
    "wof:placetype": "postalcode"
  },
  "geometry": {"coordinates":[-2.908023,54.877772],"type":"Point"}
}
