{
  "type": "Feature",
  "properties": {
    "date:inception_lower": "1993-08-01",
    "date:inception_upper": "1993-08-01",
    "iso:country": "GB",
    "wof:name": "NN10 8DN",
    "wof:placetype": "postalcode"
  },
  "geometry": {"coordinates":[-0.590223,52.307852],"type":"Point"}
}
