{
  "type": "Feature",
  "properties": {
    "iso:country":"GB",
    "wof:name":"NN10 8DN",
    "wof:placetype":"postalcode"
},
  "geometry": {"coordinates":[-0.5902232100769,52.30785201432963],"type":"Point"}
}