{
  "type": "Feature",
  "properties": {
    "date:inception_lower":"1980-01-01",
    "date:inception_upper":"1980-01-31",
    "iso:country":"GB",
    "wof:name":"SS7 2HS",
    "wof:placetype":"postalcode"
},
  "geometry": {"coordinates":[0.621833,51.554531],"type":"Point"}
}