{
  "type": "Feature",
  "properties": {
    "iso:country":"GB",
    "wof:name":"SS7 2HS",
    "wof:placetype":"postalcode"
},
  "geometry": {"coordinates":[0.62183300879502,51.5545311161574],"type":"Point"}
}