{
  "type": "Feature",
  "properties": {
    "date:inception_lower": "2016-08-01",
    "date:inception_upper": "2016-08-01",
    "iso:country": "GB",
    "wof:name": "ML3 9GE",
    "wof:placetype": "postalcode"
  },
  "geometry": {"coordinates":[-4.082417,55.774714],"type":"Point"}
}
