{
  "type": "Feature",
  "properties": {
    "date:inception_lower":"1980-01-01",
    "date:inception_upper":"1980-01-31",
    "iso:country":"GB",
    "wof:name":"NG31 8RD",
    "wof:placetype":"postalcode"
},
  "geometry": {"coordinates":[-0.665814,52.915891],"type":"Point"}
}