{
  "type": "Feature",
  "properties": {
    "iso:country":"GB",
    "wof:name":"TR11 2DZ",
    "wof:placetype":"postalcode"
},
  "geometry": {"coordinates":[-5.08080104937726,50.15537638531434],"type":"Point"}
}