{
  "type": "Feature",
  "properties": {
    "iso:country":"GB",
    "wof:name":"NW9 5TE",
    "wof:placetype":"postalcode"
},
  "geometry": {"coordinates":[-0.24642556492858,51.60478521612297],"type":"Point"}
}