{
  "type": "Feature",
  "properties": {
    "date:inception_lower": "2002-07-01",
    "date:inception_upper": "2002-07-01",
    "iso:country": "GB",
    "wof:name": "CO2 8JP",
    "wof:placetype": "postalcode"
  },
  "geometry": {"coordinates":[0.926039,51.881969],"type":"Point"}
}
