{
  "type": "Feature",
  "properties": {
    "iso:country":"GB",
    "wof:name":"CO2 8JP",
    "wof:placetype":"postalcode"
},
  "geometry": {"coordinates":[0.9260393125594,51.88196947487599],"type":"Point"}
}