{
  "type": "Feature",
  "properties": {
    "iso:country":"GB",
    "wof:name":"LE13 0LY",
    "wof:placetype":"postalcode"
},
  "geometry": {"coordinates":[-0.89865490855276,52.77233218607993],"type":"Point"}
}