{
  "type": "Feature",
  "properties": {
    "iso:country": "GB",
    "wof:name": "LE13 0LY",
    "wof:placetype": "postalcode"
  },
  "geometry": {"coordinates":[-0.898655,52.772332],"type":"Point"}
}
