{
  "type": "Feature",
  "properties": {
    "iso:country": "GB",
    "wof:name": "BB18 6UB",
    "wof:placetype": "postalcode"
  },
  "geometry": {"coordinates":[-2.150452,53.897324],"type":"Point"}
}
