{
  "type": "Feature",
  "properties": {
    "date:inception_lower": "1994-12-01",
    "date:inception_upper": "1994-12-01",
    "iso:country": "GB",
    "wof:name": "BD13 5AA",
    "wof:placetype": "postalcode"
  },
  "geometry": {"coordinates":[-1.896534,53.827053],"type":"Point"}
}
