{
  "type": "Feature",
  "properties": {
    "iso:country":"GB",
    "wof:name":"AB30 1AL",
    "wof:placetype":"postalcode"
},
  "geometry": {"coordinates":[-2.46345523281079,56.83405486194503],"type":"Point"}
}