{
  "type": "Feature",
  "properties": {
    "iso:country": "GB",
    "wof:name": "CV6 5NS",
    "wof:placetype": "postalcode"
  },
  "geometry": {"coordinates":[-1.489891,52.4212],"type":"Point"}
}
