{
  "type": "Feature",
  "properties": {
    "date:inception_lower": "2003-09-01",
    "date:inception_upper": "2003-09-01",
    "iso:country": "GB",
    "wof:name": "CW8 1GF",
    "wof:placetype": "postalcode"
  },
  "geometry": {"coordinates":[-2.516368,53.259614],"type":"Point"}
}
