{
  "type": "Feature",
  "properties": {
    "iso:country": "GB",
    "wof:name": "LU6 2EU",
    "wof:placetype": "postalcode"
  },
  "geometry": {"coordinates":[-0.603985,51.870431],"type":"Point"}
}
