{
  "type": "Feature",
  "properties": {
    "iso:country":"GB",
    "wof:name":"LU6 2EU",
    "wof:placetype":"postalcode"
},
  "geometry": {"coordinates":[-0.60398486015149,51.87043134666324],"type":"Point"}
}