{
  "type": "Feature",
  "properties": {
    "date:inception_lower": "1991-01-01",
    "date:inception_upper": "1991-01-01",
    "iso:country": "GB",
    "wof:name": "S44 6XJ",
    "wof:placetype": "postalcode"
  },
  "geometry": {"coordinates":[-1.280956,53.230737],"type":"Point"}
}
