{
  "type": "Feature",
  "properties": {
    "iso:country": "GB",
    "wof:name": "S44 6XJ",
    "wof:placetype": "postalcode"
  },
  "geometry": {"coordinates":[-1.280956,53.230737],"type":"Point"}
}
