{
  "type": "Feature",
  "properties": {
    "iso:country":"GB",
    "wof:name":"IV8 8NJ",
    "wof:placetype":"postalcode"
},
  "geometry": {"coordinates":[-4.2627201986511,57.54926366603542],"type":"Point"}
}