{
  "type": "Feature",
  "properties": {
    "date:inception_lower": "1980-01-01",
    "date:inception_upper": "1980-01-01",
    "iso:country": "GB",
    "wof:name": "NE2 3QR",
    "wof:placetype": "postalcode"
  },
  "geometry": {"coordinates":[-1.607203,55.002092],"type":"Point"}
}
