{
  "type": "Feature",
  "properties": {
    "iso:country":"GB",
    "wof:name":"NE2 3QR",
    "wof:placetype":"postalcode"
},
  "geometry": {"coordinates":[-1.60718874387071,55.00208449935356],"type":"Point"}
}