{
  "type": "Feature",
  "properties": {
    "iso:country":"GB",
    "wof:name":"SL1 8LP",
    "wof:placetype":"postalcode"
},
  "geometry": {"coordinates":[-0.67080051863832,51.54102968628785],"type":"Point"}
}