{
  "type": "Feature",
  "properties": {
    "iso:country":"GB",
    "wof:name":"KW15 1PA",
    "wof:placetype":"postalcode"
},
  "geometry": {"coordinates":[-2.9579989333342,58.98115752638358],"type":"Point"}
}