{
  "type": "Feature",
  "properties": {
    "iso:country":"GB",
    "wof:name":"NW9 8XU",
    "wof:placetype":"postalcode"
},
  "geometry": {"coordinates":[-0.26603798764556,51.58047375248172],"type":"Point"}
}