{
  "type": "Feature",
  "properties": {
    "iso:country": "GB",
    "wof:name": "WD6 1EF",
    "wof:placetype": "postalcode"
  },
  "geometry": {"coordinates":[-0.273131,51.656796],"type":"Point"}
}
