{
  "type": "Feature",
  "properties": {
    "date:inception_lower": "1980-01-01",
    "date:inception_upper": "1980-01-01",
    "iso:country": "GB",
    "wof:name": "ST8 7LR",
    "wof:placetype": "postalcode"
  },
  "geometry": {"coordinates":[-2.141935,53.119361],"type":"Point"}
}
