{
  "type": "Feature",
  "properties": {
    "iso:country":"GB",
    "wof:name":"ST8 7LR",
    "wof:placetype":"postalcode"
},
  "geometry": {"coordinates":[-2.14193482461055,53.11936124716409],"type":"Point"}
}