{
  "type": "Feature",
  "properties": {
    "iso:country": "GB",
    "wof:name": "SK9 7AA",
    "wof:placetype": "postalcode"
  },
  "geometry": {"coordinates":[-2.236712,53.298889],"type":"Point"}
}
