{
  "type": "Feature",
  "properties": {
    "iso:country":"GB",
    "wof:name":"SK9 7AA",
    "wof:placetype":"postalcode"
},
  "geometry": {"coordinates":[-2.23677244053137,53.29896959860383],"type":"Point"}
}