{
  "type": "Feature",
  "properties": {
    "iso:country":"GB",
    "wof:name":"IG11 0FF",
    "wof:placetype":"postalcode"
},
  "geometry": {"coordinates":[0.10085670256662,51.52656543910108],"type":"Point"}
}