{
  "type": "Feature",
  "properties": {
    "iso:country":"GB",
    "wof:name":"EH10 4AY",
    "wof:placetype":"postalcode"
},
  "geometry": {"coordinates":[-3.20950287531346,55.93053824149065],"type":"Point"}
}