{
  "type": "Feature",
  "properties": {
    "date:inception_lower": "1980-01-01",
    "date:inception_upper": "1980-01-01",
    "iso:country": "GB",
    "wof:name": "EH10 4AY",
    "wof:placetype": "postalcode"
  },
  "geometry": {"coordinates":[-3.209503,55.930538],"type":"Point"}
}
