{
  "type": "Feature",
  "properties": {
    "date:inception_lower": "1988-03-01",
    "date:inception_upper": "1988-03-01",
    "iso:country": "GB",
    "wof:name": "DN4 0AJ",
    "wof:placetype": "postalcode"
  },
  "geometry": {"coordinates":[-1.147075,53.518137],"type":"Point"}
}
