{
  "type": "Feature",
  "properties": {
    "iso:country":"GB",
    "wof:name":"WF12 9AY",
    "wof:placetype":"postalcode"
},
  "geometry": {"coordinates":[-1.62580396938748,53.68222917855275],"type":"Point"}
}