{
  "type": "Feature",
  "properties": {
    "date:inception_lower": "1980-01-01",
    "date:inception_upper": "1980-01-01",
    "iso:country": "GB",
    "wof:name": "WF12 9AY",
    "wof:placetype": "postalcode"
  },
  "geometry": {"coordinates":[-1.625804,53.682229],"type":"Point"}
}
