{
  "type": "Feature",
  "properties": {
    "date:inception_lower": "2023-10-01",
    "date:inception_upper": "2023-10-01",
    "iso:country": "GB",
    "wof:name": "DY2 0BE",
    "wof:placetype": "postalcode"
  },
  "geometry": {"coordinates":[-2.094601,52.49533],"type":"Point"}
}
