{
  "type": "Feature",
  "properties": {
    "date:inception_lower":"1999-12-01",
    "date:inception_upper":"1999-12-31",
    "iso:country":"GB",
    "wof:name":"BB3 0SQ",
    "wof:placetype":"postalcode"
},
  "geometry": {"coordinates":[-2.483962,53.712448],"type":"Point"}
}