{
  "type": "Feature",
  "properties": {
    "iso:country":"GB",
    "wof:name":"BB3 0SQ",
    "wof:placetype":"postalcode"
},
  "geometry": {"coordinates":[-2.48396180400123,53.71244790314371],"type":"Point"}
}