{
  "type": "Feature",
  "properties": {
    "iso:country": "GB",
    "wof:name": "BB3 0SQ",
    "wof:placetype": "postalcode"
  },
  "geometry": {"coordinates":[-2.483962,53.712448],"type":"Point"}
}
