{
  "type": "Feature",
  "properties": {
    "date:inception_lower": "2006-05-01",
    "date:inception_upper": "2006-05-01",
    "iso:country": "GB",
    "wof:name": "KY11 8HF",
    "wof:placetype": "postalcode"
  },
  "geometry": {"coordinates":[-3.412846,56.06417],"type":"Point"}
}
