{
  "type": "Feature",
  "properties": {
    "date:inception_lower":"1991-09-01",
    "date:inception_upper":"1991-09-30",
    "iso:country":"GB",
    "wof:name":"OX18 4SA",
    "wof:placetype":"postalcode"
},
  "geometry": {"coordinates":[-1.634974,51.809409],"type":"Point"}
}