{
  "type": "Feature",
  "properties": {
    "iso:country": "GB",
    "wof:name": "OX18 4SA",
    "wof:placetype": "postalcode"
  },
  "geometry": {"coordinates":[-1.634974,51.809409],"type":"Point"}
}
