{
  "type": "Feature",
  "properties": {
    "iso:country":"GB",
    "wof:name":"TW12 2NZ",
    "wof:placetype":"postalcode"
},
  "geometry": {"coordinates":[-0.37178487211672,51.41926421903288],"type":"Point"}
}