{
  "type": "Feature",
  "properties": {
    "date:inception_lower": "2000-06-01",
    "date:inception_upper": "2000-06-01",
    "iso:country": "GB",
    "wof:name": "TW12 2NZ",
    "wof:placetype": "postalcode"
  },
  "geometry": {"coordinates":[-0.371785,51.419264],"type":"Point"}
}
