{
  "type": "Feature",
  "properties": {
    "iso:country":"GB",
    "wof:name":"LE15 7PX",
    "wof:placetype":"postalcode"
},
  "geometry": {"coordinates":[-0.68294191820535,52.73753554892601],"type":"Point"}
}