{
  "type": "Feature",
  "properties": {
    "iso:country": "GB",
    "wof:name": "LE15 7PX",
    "wof:placetype": "postalcode"
  },
  "geometry": {"coordinates":[-0.682942,52.737536],"type":"Point"}
}
