{
  "type": "Feature",
  "properties": {
    "date:inception_lower": "1980-01-01",
    "date:inception_upper": "1980-01-01",
    "iso:country": "GB",
    "wof:name": "NE32 4XQ",
    "wof:placetype": "postalcode"
  },
  "geometry": {"coordinates":[-1.494189,54.953797],"type":"Point"}
}
