{
  "type": "Feature",
  "properties": {
    "iso:country":"GB",
    "wof:name":"NE32 4XQ",
    "wof:placetype":"postalcode"
},
  "geometry": {"coordinates":[-1.49418931127728,54.95379741863467],"type":"Point"}
}