{
  "type": "Feature",
  "properties": {
    "iso:country": "GB",
    "wof:name": "CB1 3PS",
    "wof:placetype": "postalcode"
  },
  "geometry": {"coordinates":[0.148537,52.193837],"type":"Point"}
}
