{
  "type": "Feature",
  "properties": {
    "iso:country": "GB",
    "wof:name": "SO23 9NX",
    "wof:placetype": "postalcode"
  },
  "geometry": {"coordinates":[-1.308834,51.057973],"type":"Point"}
}
