{
  "type": "Feature",
  "properties": {
    "iso:country": "GB",
    "wof:name": "L20 4DB",
    "wof:placetype": "postalcode"
  },
  "geometry": {"coordinates":[-3.000257,53.44882],"type":"Point"}
}
