{
  "type": "Feature",
  "properties": {
    "iso:country": "GB",
    "wof:name": "NE32 3PF",
    "wof:placetype": "postalcode"
  },
  "geometry": {"coordinates":[-1.486683,54.982683],"type":"Point"}
}
