{
  "type": "Feature",
  "properties": {
    "iso:country":"GB",
    "wof:name":"ME18 5JN",
    "wof:placetype":"postalcode"
},
  "geometry": {"coordinates":[0.35316091981877,51.24742439369253],"type":"Point"}
}