{
  "type": "Feature",
  "properties": {
    "iso:country": "GB",
    "wof:name": "ME18 5JN",
    "wof:placetype": "postalcode"
  },
  "geometry": {"coordinates":[0.353161,51.247424],"type":"Point"}
}
