{
  "type": "Feature",
  "properties": {
    "iso:country": "GB",
    "wof:name": "HU11 4QT",
    "wof:placetype": "postalcode"
  },
  "geometry": {"coordinates":[-0.145451,53.841809],"type":"Point"}
}
