{
  "type": "Feature",
  "properties": {
    "iso:country":"GB",
    "wof:name":"BS39 5SE",
    "wof:placetype":"postalcode"
},
  "geometry": {"coordinates":[-2.54209790664678,51.32969529937206],"type":"Point"}
}