{
  "type": "Feature",
  "properties": {
    "iso:country":"GB",
    "wof:name":"PO9 3NG",
    "wof:placetype":"postalcode"
},
  "geometry": {"coordinates":[-1.00555137962171,50.85769828475983],"type":"Point"}
}