{
  "type": "Feature",
  "properties": {
    "date:inception_lower": "2016-04-01",
    "date:inception_upper": "2016-04-01",
    "iso:country": "GB",
    "wof:name": "GU22 9FF",
    "wof:placetype": "postalcode"
  },
  "geometry": {"coordinates":[-0.561616,51.306331],"type":"Point"}
}
