{
  "type": "Feature",
  "properties": {
    "iso:country": "GB",
    "wof:name": "GU22 9FF",
    "wof:placetype": "postalcode"
  },
  "geometry": {"coordinates":[-0.561616,51.306331],"type":"Point"}
}
