{
  "type": "Feature",
  "properties": {
    "iso:country":"GB",
    "wof:name":"BB2 4SH",
    "wof:placetype":"postalcode"
},
  "geometry": {"coordinates":[-2.51871970550702,53.73346955351604],"type":"Point"}
}