{
  "type": "Feature",
  "properties": {
    "iso:country": "GB",
    "wof:name": "BB2 4SH",
    "wof:placetype": "postalcode"
  },
  "geometry": {"coordinates":[-2.518733,53.73353],"type":"Point"}
}
