{
  "type": "Feature",
  "properties": {
    "date:inception_lower": "2018-11-01",
    "date:inception_upper": "2018-11-01",
    "iso:country": "GB",
    "wof:name": "LU1 4FR",
    "wof:placetype": "postalcode"
  },
  "geometry": {"coordinates":[-0.464876,51.879929],"type":"Point"}
}
