{
  "type": "Feature",
  "properties": {
    "iso:country": "GB",
    "wof:name": "LU1 4FR",
    "wof:placetype": "postalcode"
  },
  "geometry": {"coordinates":[-0.464876,51.879929],"type":"Point"}
}
