{
  "type": "Feature",
  "properties": {
    "iso:country":"GB",
    "wof:name":"BA8 0BP",
    "wof:placetype":"postalcode"
},
  "geometry": {"coordinates":[-2.43501077744787,51.02122132577507],"type":"Point"}
}