{
  "type": "Feature",
  "properties": {
    "iso:country": "GB",
    "wof:name": "BA8 0BP",
    "wof:placetype": "postalcode"
  },
  "geometry": {"coordinates":[-2.435011,51.021221],"type":"Point"}
}
