{
  "type": "Feature",
  "properties": {
    "iso:country": "GB",
    "wof:name": "DT1 3RL",
    "wof:placetype": "postalcode"
  },
  "geometry": {"coordinates":[-2.465005,50.712492],"type":"Point"}
}
