{
  "type": "Feature",
  "properties": {
    "date:inception_lower": "2003-05-01",
    "date:inception_upper": "2003-05-01",
    "iso:country": "GB",
    "wof:name": "DT1 3RL",
    "wof:placetype": "postalcode"
  },
  "geometry": {"coordinates":[-2.464975,50.712492],"type":"Point"}
}
