{
  "type": "Feature",
  "properties": {
    "iso:country":"GB",
    "wof:name":"HA4 8FQ",
    "wof:placetype":"postalcode"
},
  "geometry": {"coordinates":[-0.40725173385142,51.58166582064005],"type":"Point"}
}