{
  "type": "Feature",
  "properties": {
    "iso:country": "GB",
    "wof:name": "S5 8LT",
    "wof:placetype": "postalcode"
  },
  "geometry": {"coordinates":[-1.491653,53.415758],"type":"Point"}
}
