{
  "type": "Feature",
  "properties": {
    "date:inception_lower": "1997-12-01",
    "date:inception_upper": "1997-12-01",
    "iso:country": "GB",
    "wof:name": "CV37 8QY",
    "wof:placetype": "postalcode"
  },
  "geometry": {"coordinates":[-1.776299,52.135893],"type":"Point"}
}
