{
  "type": "Feature",
  "properties": {
    "iso:country": "GB",
    "wof:name": "CV37 8QY",
    "wof:placetype": "postalcode"
  },
  "geometry": {"coordinates":[-1.776299,52.135893],"type":"Point"}
}
