{
  "type": "Feature",
  "properties": {
    "iso:country":"GB",
    "wof:name":"M20 1JP",
    "wof:placetype":"postalcode"
},
  "geometry": {"coordinates":[-2.23906279548261,53.42942605444919],"type":"Point"}
}