{
  "type": "Feature",
  "properties": {
    "iso:country": "GB",
    "wof:name": "LE12 7WX",
    "wof:placetype": "postalcode"
  },
  "geometry": {"coordinates":[-1.111336,52.730164],"type":"Point"}
}
