{
  "type": "Feature",
  "properties": {
    "iso:country":"GB",
    "wof:name":"LE12 7WX",
    "wof:placetype":"postalcode"
},
  "geometry": {"coordinates":[-1.11133573304925,52.73016414953654],"type":"Point"}
}