{
  "type": "Feature",
  "properties": {
    "date:inception_lower": "2016-05-01",
    "date:inception_upper": "2016-05-01",
    "iso:country": "GB",
    "wof:name": "WR5 2SR",
    "wof:placetype": "postalcode"
  },
  "geometry": {"coordinates":[-2.182925,52.180872],"type":"Point"}
}
