{
  "type": "Feature",
  "properties": {
    "date:inception_lower": "2007-09-01",
    "date:inception_upper": "2007-09-01",
    "iso:country": "GB",
    "wof:name": "MK9 3PW",
    "wof:placetype": "postalcode"
  },
  "geometry": {"coordinates":[-0.750526,52.043812],"type":"Point"}
}
