{
  "type": "Feature",
  "properties": {
    "iso:country":"GB",
    "wof:name":"MK9 3PW",
    "wof:placetype":"postalcode"
},
  "geometry": {"coordinates":[-0.75052649343945,52.04381190913081],"type":"Point"}
}