{
  "type": "Feature",
  "properties": {
    "iso:country": "GB",
    "wof:name": "HU1 2AZ",
    "wof:placetype": "postalcode"
  },
  "geometry": {"coordinates":[-0.335356,53.743682],"type":"Point"}
}
