{
  "type": "Feature",
  "properties": {
    "iso:country":"GB",
    "wof:name":"NG22 8DL",
    "wof:placetype":"postalcode"
},
  "geometry": {"coordinates":[-1.02773772874055,53.10421471358014],"type":"Point"}
}