{
  "type": "Feature",
  "properties": {
    "iso:country": "GB",
    "wof:name": "NG22 8DL",
    "wof:placetype": "postalcode"
  },
  "geometry": {"coordinates":[-1.02775,53.104216],"type":"Point"}
}
