{
  "type": "Feature",
  "properties": {
    "iso:country":"GB",
    "wof:name":"CF11 7DQ",
    "wof:placetype":"postalcode"
},
  "geometry": {"coordinates":[-3.18389094676118,51.46307400932195],"type":"Point"}
}