{
  "type": "Feature",
  "properties": {
    "date:inception_lower":"2007-01-01",
    "date:inception_upper":"2007-01-31",
    "iso:country":"GB",
    "wof:name":"M5 4UU",
    "wof:placetype":"postalcode"
},
  "geometry": {"coordinates":[-2.266424,53.472684],"type":"Point"}
}