{
  "type": "Feature",
  "properties": {
    "iso:country": "GB",
    "wof:name": "M5 4UU",
    "wof:placetype": "postalcode"
  },
  "geometry": {"coordinates":[-2.266424,53.472684],"type":"Point"}
}
