{
  "type": "Feature",
  "properties": {
    "iso:country":"GB",
    "wof:name":"MK44 1DF",
    "wof:placetype":"postalcode"
},
  "geometry": {"coordinates":[-0.47277076385548,52.25511579521376],"type":"Point"}
}