{
  "type": "Feature",
  "properties": {
    "iso:country":"GB",
    "wof:name":"SR8 4HF",
    "wof:placetype":"postalcode"
},
  "geometry": {"coordinates":[-1.30556859755627,54.76130880591191],"type":"Point"}
}