{
  "type": "Feature",
  "properties": {
    "date:inception_lower": "1980-01-01",
    "date:inception_upper": "1980-01-01",
    "iso:country": "GB",
    "wof:name": "SR8 4HF",
    "wof:placetype": "postalcode"
  },
  "geometry": {"coordinates":[-1.305569,54.761309],"type":"Point"}
}
