{
  "type": "Feature",
  "properties": {
    "iso:country":"GB",
    "wof:name":"LL59 5AA",
    "wof:placetype":"postalcode"
},
  "geometry": {"coordinates":[-4.17517139285429,53.22548988359972],"type":"Point"}
}