{
  "type": "Feature",
  "properties": {
    "iso:country": "GB",
    "wof:name": "LL59 5AA",
    "wof:placetype": "postalcode"
  },
  "geometry": {"coordinates":[-4.175171,53.22549],"type":"Point"}
}
