{
  "type": "Feature",
  "properties": {
    "iso:country": "GB",
    "wof:name": "B33 0YR",
    "wof:placetype": "postalcode"
  },
  "geometry": {"coordinates":[-1.775824,52.477359],"type":"Point"}
}
