{
  "type": "Feature",
  "properties": {
    "iso:country":"GB",
    "wof:name":"B33 0YR",
    "wof:placetype":"postalcode"
},
  "geometry": {"coordinates":[-1.77582452116535,52.47735904232162],"type":"Point"}
}