{
  "type": "Feature",
  "properties": {
    "iso:country":"GB",
    "wof:name":"NG34 8PS",
    "wof:placetype":"postalcode"
},
  "geometry": {"coordinates":[-0.44599970680009,52.98935302356041],"type":"Point"}
}