{
  "type": "Feature",
  "properties": {
    "date:inception_lower": "1980-01-01",
    "date:inception_upper": "1980-01-01",
    "iso:country": "GB",
    "wof:name": "NG5 7FX",
    "wof:placetype": "postalcode"
  },
  "geometry": {"coordinates":[-1.123267,53.005336],"type":"Point"}
}
