{
  "type": "Feature",
  "properties": {
    "iso:country":"GB",
    "wof:name":"NG5 7FX",
    "wof:placetype":"postalcode"
},
  "geometry": {"coordinates":[-1.1232665835614,53.005336216067],"type":"Point"}
}