{
  "type": "Feature",
  "properties": {
    "iso:country":"GB",
    "wof:name":"MK10 7AB",
    "wof:placetype":"postalcode"
},
  "geometry": {"coordinates":[-0.69841879824163,52.05365971895667],"type":"Point"}
}