{
  "type": "Feature",
  "properties": {
    "date:inception_lower": "2008-07-01",
    "date:inception_upper": "2008-07-01",
    "iso:country": "GB",
    "wof:name": "MK10 7AB",
    "wof:placetype": "postalcode"
  },
  "geometry": {"coordinates":[-0.698419,52.05366],"type":"Point"}
}
