{
  "type": "Feature",
  "properties": {
    "iso:country":"GB",
    "wof:name":"N18 1NT",
    "wof:placetype":"postalcode"
},
  "geometry": {"coordinates":[-0.07747546837697,51.61891946581207],"type":"Point"}
}