{
  "type": "Feature",
  "properties": {
    "date:inception_lower": "2000-12-01",
    "date:inception_upper": "2000-12-01",
    "iso:country": "GB",
    "wof:name": "NG33 5RR",
    "wof:placetype": "postalcode"
  },
  "geometry": {"coordinates":[-0.629784,52.764857],"type":"Point"}
}
