{
  "type": "Feature",
  "properties": {
    "iso:country":"GB",
    "wof:name":"NG33 5RR",
    "wof:placetype":"postalcode"
},
  "geometry": {"coordinates":[-0.6297845210578,52.76485702638672],"type":"Point"}
}