{
  "type": "Feature",
  "properties": {
    "iso:country": "GB",
    "wof:name": "WF15 7BA",
    "wof:placetype": "postalcode"
  },
  "geometry": {"coordinates":[-1.677589,53.701746],"type":"Point"}
}
