{
  "type": "Feature",
  "properties": {
    "iso:country":"GB",
    "wof:name":"SE6 3EB",
    "wof:placetype":"postalcode"
},
  "geometry": {"coordinates":[-0.01932387211415,51.42841486345046],"type":"Point"}
}