{
  "type": "Feature",
  "properties": {
    "date:inception_lower":"1980-01-01",
    "date:inception_upper":"1980-01-31",
    "iso:country":"GB",
    "wof:name":"M33 5LR",
    "wof:placetype":"postalcode"
},
  "geometry": {"coordinates":[-2.357247,53.428825],"type":"Point"}
}