{
  "type": "Feature",
  "properties": {
    "iso:country":"GB",
    "wof:name":"M33 5LR",
    "wof:placetype":"postalcode"
},
  "geometry": {"coordinates":[-2.35724694293208,53.42882519034543],"type":"Point"}
}