{
  "type": "Feature",
  "properties": {
    "date:inception_lower": "2018-07-01",
    "date:inception_upper": "2018-07-01",
    "iso:country": "GB",
    "wof:name": "SP10 4FA",
    "wof:placetype": "postalcode"
  },
  "geometry": {"coordinates":[-1.494236,51.222295],"type":"Point"}
}
