{
  "type": "Feature",
  "properties": {
    "iso:country":"GB",
    "wof:name":"SL2 5SZ",
    "wof:placetype":"postalcode"
},
  "geometry": {"coordinates":[-0.57982670808267,51.52288800663139],"type":"Point"}
}