{
  "type": "Feature",
  "properties": {
    "iso:country":"GB",
    "wof:name":"E9 5SB",
    "wof:placetype":"postalcode"
},
  "geometry": {"coordinates":[-0.04247387586579,51.54771369491269],"type":"Point"}
}