{
  "type": "Feature",
  "properties": {
    "date:inception_lower": "2008-10-01",
    "date:inception_upper": "2008-10-01",
    "iso:country": "GB",
    "wof:name": "LE5 1WA",
    "wof:placetype": "postalcode"
  },
  "geometry": {"coordinates":[-1.06304,52.661936],"type":"Point"}
}
