{
  "type": "Feature",
  "properties": {
    "iso:country":"GB",
    "wof:name":"LE5 1WA",
    "wof:placetype":"postalcode"
},
  "geometry": {"coordinates":[-1.06304003134874,52.66193640795979],"type":"Point"}
}