{
  "type": "Feature",
  "properties": {
    "date:inception_lower": "1980-01-01",
    "date:inception_upper": "1980-01-01",
    "iso:country": "GB",
    "wof:name": "TQ12 6JZ",
    "wof:placetype": "postalcode"
  },
  "geometry": {"coordinates":[-3.69853,50.541359],"type":"Point"}
}
