{
  "type": "Feature",
  "properties": {
    "iso:country": "GB",
    "wof:name": "TQ12 6JZ",
    "wof:placetype": "postalcode"
  },
  "geometry": {"coordinates":[-3.698722,50.541295],"type":"Point"}
}
