{
  "type": "Feature",
  "properties": {
    "iso:country":"GB",
    "wof:name":"TQ12 6JZ",
    "wof:placetype":"postalcode"
},
  "geometry": {"coordinates":[-3.69872226535056,50.54129522126866],"type":"Point"}
}