{
  "type": "Feature",
  "properties": {
    "date:inception_lower": "2005-02-01",
    "date:inception_upper": "2005-02-01",
    "iso:country": "GB",
    "wof:name": "EX8 4QB",
    "wof:placetype": "postalcode"
  },
  "geometry": {"coordinates":[-3.401137,50.637026],"type":"Point"}
}
