{
  "type": "Feature",
  "properties": {
    "iso:country":"GB",
    "wof:name":"EX8 4QB",
    "wof:placetype":"postalcode"
},
  "geometry": {"coordinates":[-3.40113675552649,50.6370260834046],"type":"Point"}
}