{
  "type": "Feature",
  "properties": {
    "iso:country":"GB",
    "wof:name":"SY16 1PX",
    "wof:placetype":"postalcode"
},
  "geometry": {"coordinates":[-3.33080025989117,52.50796882101169],"type":"Point"}
}