{
  "type": "Feature",
  "properties": {
    "iso:country":"GB",
    "wof:name":"M27 8LL",
    "wof:placetype":"postalcode"
},
  "geometry": {"coordinates":[-2.31571909480849,53.52146071527073],"type":"Point"}
}