{
  "type": "Feature",
  "properties": {
    "iso:country": "GB",
    "wof:name": "WA5 4NA",
    "wof:placetype": "postalcode"
  },
  "geometry": {"coordinates":[-2.648457,53.432192],"type":"Point"}
}
