{
  "type": "Feature",
  "properties": {
    "iso:country":"GB",
    "wof:name":"DE24 3FG",
    "wof:placetype":"postalcode"
},
  "geometry": {"coordinates":[-1.50980079771757,52.8755753179901],"type":"Point"}
}