{
  "type": "Feature",
  "properties": {
    "date:inception_lower":"2014-07-01",
    "date:inception_upper":"2014-07-31",
    "iso:country":"GB",
    "wof:name":"DE24 3FG",
    "wof:placetype":"postalcode"
},
  "geometry": {"coordinates":[-1.510002,52.875882],"type":"Point"}
}