{
  "type": "Feature",
  "properties": {
    "iso:country": "GB",
    "wof:name": "CA12 5JY",
    "wof:placetype": "postalcode"
  },
  "geometry": {"coordinates":[-3.13816,54.601998],"type":"Point"}
}
