{
  "type": "Feature",
  "properties": {
    "iso:country":"GB",
    "wof:name":"W1J 7HB",
    "wof:placetype":"postalcode"
},
  "geometry": {"coordinates":[-0.14961982543071,51.50404052383281],"type":"Point"}
}