{
  "type": "Feature",
  "properties": {
    "iso:country":"GB",
    "wof:name":"TR12 7JJ",
    "wof:placetype":"postalcode"
},
  "geometry": {"coordinates":[-5.18463878851696,49.99514961620229],"type":"Point"}
}