{
  "type": "Feature",
  "properties": {
    "iso:country": "GB",
    "wof:name": "TR12 7JJ",
    "wof:placetype": "postalcode"
  },
  "geometry": {"coordinates":[-5.184514,49.995204],"type":"Point"}
}
