{
  "type": "Feature",
  "properties": {
    "iso:country":"GB",
    "wof:name":"PE8 6YA",
    "wof:placetype":"postalcode"
},
  "geometry": {"coordinates":[-0.52384915170559,52.56321576805987],"type":"Point"}
}