{
  "type": "Feature",
  "properties": {
    "iso:country": "GB",
    "wof:name": "WS7 3AA",
    "wof:placetype": "postalcode"
  },
  "geometry": {"coordinates":[-1.934342,52.670744],"type":"Point"}
}
