{
  "type": "Feature",
  "properties": {
    "iso:country":"GB",
    "wof:name":"SR1 3BT",
    "wof:placetype":"postalcode"
},
  "geometry": {"coordinates":[-1.38323195302282,54.90688853153387],"type":"Point"}
}