{
  "type": "Feature",
  "properties": {
    "iso:country":"GB",
    "wof:name":"LE19 1LU",
    "wof:placetype":"postalcode"
},
  "geometry": {"coordinates":[-1.19135151154257,52.61293291206057],"type":"Point"}
}