{
  "type": "Feature",
  "properties": {
    "date:inception_lower": "2002-06-01",
    "date:inception_upper": "2002-06-01",
    "iso:country": "GB",
    "wof:name": "LE19 1LU",
    "wof:placetype": "postalcode"
  },
  "geometry": {"coordinates":[-1.190734,52.613172],"type":"Point"}
}
