{
  "type": "Feature",
  "properties": {
    "iso:country":"GB",
    "wof:name":"WD3 1LR",
    "wof:placetype":"postalcode"
},
  "geometry": {"coordinates":[-0.45501046699595,51.63444005855872],"type":"Point"}
}