{
  "type": "Feature",
  "properties": {
    "iso:country":"GB",
    "wof:name":"PR6 9SD",
    "wof:placetype":"postalcode"
},
  "geometry": {"coordinates":[-2.60724863366692,53.61997182270753],"type":"Point"}
}