{
  "type": "Feature",
  "properties": {
    "date:inception_lower":"2003-02-01",
    "date:inception_upper":"2003-02-28",
    "iso:country":"GB",
    "wof:name":"PR6 9SD",
    "wof:placetype":"postalcode"
},
  "geometry": {"coordinates":[-2.607249,53.619972],"type":"Point"}
}