{
  "type": "Feature",
  "properties": {
    "date:inception_lower":"2006-12-01",
    "date:inception_upper":"2006-12-31",
    "iso:country":"GB",
    "wof:name":"NR6 5DU",
    "wof:placetype":"postalcode"
},
  "geometry": {"coordinates":[1.263517,52.654488],"type":"Point"}
}