{
  "type": "Feature",
  "properties": {
    "iso:country":"GB",
    "wof:name":"NR6 5DU",
    "wof:placetype":"postalcode"
},
  "geometry": {"coordinates":[1.26330291392609,52.65446791645562],"type":"Point"}
}