{
  "type": "Feature",
  "properties": {
    "date:inception_lower": "2006-12-01",
    "date:inception_upper": "2006-12-01",
    "iso:country": "GB",
    "wof:name": "NR6 5DU",
    "wof:placetype": "postalcode"
  },
  "geometry": {"coordinates":[1.263325,52.654493],"type":"Point"}
}
