{
  "type": "Feature",
  "properties": {
    "date:inception_lower":"1980-01-01",
    "date:inception_upper":"1980-01-31",
    "iso:country":"GB",
    "wof:name":"SA6 6NW",
    "wof:placetype":"postalcode"
},
  "geometry": {"coordinates":[-3.940554,51.6821],"type":"Point"}
}