{
  "type": "Feature",
  "properties": {
    "iso:country":"GB",
    "wof:name":"BD6 1LA",
    "wof:placetype":"postalcode"
},
  "geometry": {"coordinates":[-1.77314394828218,53.76758987139391],"type":"Point"}
}