{
  "type": "Feature",
  "properties": {
    "date:inception_lower": "1980-01-01",
    "date:inception_upper": "1980-01-01",
    "iso:country": "GB",
    "wof:name": "BD6 1LA",
    "wof:placetype": "postalcode"
  },
  "geometry": {"coordinates":[-1.773144,53.76759],"type":"Point"}
}
