{
  "type": "Feature",
  "properties": {
    "iso:country":"GB",
    "wof:name":"CT19 4DR",
    "wof:placetype":"postalcode"
},
  "geometry": {"coordinates":[1.14845889363666,51.08726826213842],"type":"Point"}
}