{
  "type": "Feature",
  "properties": {
    "date:inception_lower": "1980-01-01",
    "date:inception_upper": "1980-01-01",
    "iso:country": "GB",
    "wof:name": "AL3 8LL",
    "wof:placetype": "postalcode"
  },
  "geometry": {"coordinates":[-0.458556,51.837307],"type":"Point"}
}
