{
  "type": "Feature",
  "properties": {
    "iso:country":"GB",
    "wof:name":"AL3 8LL",
    "wof:placetype":"postalcode"
},
  "geometry": {"coordinates":[-0.4585564665857,51.83730694324482],"type":"Point"}
}