{
  "type": "Feature",
  "properties": {
    "iso:country":"GB",
    "wof:name":"DH7 7BT",
    "wof:placetype":"postalcode"
},
  "geometry": {"coordinates":[-1.64951018369587,54.77895620459164],"type":"Point"}
}