{
  "type": "Feature",
  "properties": {
    "iso:country": "GB",
    "wof:name": "DH7 7BT",
    "wof:placetype": "postalcode"
  },
  "geometry": {"coordinates":[-1.64951,54.778956],"type":"Point"}
}
