{
  "type": "Feature",
  "properties": {
    "iso:country":"GB",
    "wof:name":"DN36 4LG",
    "wof:placetype":"postalcode"
},
  "geometry": {"coordinates":[-0.06130922123497,53.52719780399171],"type":"Point"}
}