{
  "type": "Feature",
  "properties": {
    "iso:country":"GB",
    "wof:name":"EH47 0SN",
    "wof:placetype":"postalcode"
},
  "geometry": {"coordinates":[-3.70984925014453,55.86204522845059],"type":"Point"}
}