{
  "type": "Feature",
  "properties": {
    "iso:country": "GB",
    "wof:name": "EH47 0SN",
    "wof:placetype": "postalcode"
  },
  "geometry": {"coordinates":[-3.710683,55.861922],"type":"Point"}
}
