{
  "type": "Feature",
  "properties": {
    "date:inception_lower":"2015-04-01",
    "date:inception_upper":"2015-04-30",
    "iso:country":"GB",
    "wof:name":"EH47 0SN",
    "wof:placetype":"postalcode"
},
  "geometry": {"coordinates":[-3.709842,55.862042],"type":"Point"}
}