{
  "type": "Feature",
  "properties": {
    "date:inception_lower":"1980-01-01",
    "date:inception_upper":"1980-01-31",
    "iso:country":"GB",
    "wof:name":"BH21 4AD",
    "wof:placetype":"postalcode"
},
  "geometry": {"coordinates":[-2.078248,50.791837],"type":"Point"}
}