{
  "type": "Feature",
  "properties": {
    "iso:country":"GB",
    "wof:name":"BH21 4AD",
    "wof:placetype":"postalcode"
},
  "geometry": {"coordinates":[-2.07824831124786,50.79183657670567],"type":"Point"}
}