{
  "type": "Feature",
  "properties": {
    "iso:country": "GB",
    "wof:name": "BH21 4AD",
    "wof:placetype": "postalcode"
  },
  "geometry": {"coordinates":[-2.078248,50.791837],"type":"Point"}
}
