{
  "type": "Feature",
  "properties": {
    "iso:country":"GB",
    "wof:name":"PL7 2AQ",
    "wof:placetype":"postalcode"
},
  "geometry": {"coordinates":[-4.05055017847259,50.3867302909188],"type":"Point"}
}