{
  "type": "Feature",
  "properties": {
    "iso:country": "GB",
    "wof:name": "SL3 8WF",
    "wof:placetype": "postalcode"
  },
  "geometry": {"coordinates":[-0.531097,51.498531],"type":"Point"}
}
