{
  "type": "Feature",
  "properties": {
    "iso:country":"GB",
    "wof:name":"E20 1DS",
    "wof:placetype":"postalcode"
},
  "geometry": {"coordinates":[-0.00987363530594,51.54912558621771],"type":"Point"}
}