{
  "type": "Feature",
  "properties": {
    "iso:country": "GB",
    "wof:name": "GU17 9DL",
    "wof:placetype": "postalcode"
  },
  "geometry": {"coordinates":[-0.782178,51.329541],"type":"Point"}
}
