{
  "type": "Feature",
  "properties": {
    "iso:country":"GB",
    "wof:name":"SK5 7QQ",
    "wof:placetype":"postalcode"
},
  "geometry": {"coordinates":[-2.1502930659087,53.4240699458144],"type":"Point"}
}