{
  "type": "Feature",
  "properties": {
    "iso:country":"GB",
    "wof:name":"CV9 3DP",
    "wof:placetype":"postalcode"
},
  "geometry": {"coordinates":[-1.5766494257631,52.60450738603677],"type":"Point"}
}