{
  "type": "Feature",
  "properties": {
    "date:inception_lower": "2002-06-01",
    "date:inception_upper": "2002-06-01",
    "iso:country": "GB",
    "wof:name": "HP10 0FA",
    "wof:placetype": "postalcode"
  },
  "geometry": {"coordinates":[-0.685675,51.596309],"type":"Point"}
}
