{
  "type": "Feature",
  "properties": {
    "iso:country":"GB",
    "wof:name":"SS2 6LE",
    "wof:placetype":"postalcode"
},
  "geometry": {"coordinates":[0.70793354625162,51.55041620537094],"type":"Point"}
}