{
  "type": "Feature",
  "properties": {
    "iso:country":"GB",
    "wof:name":"EH31 2AE",
    "wof:placetype":"postalcode"
},
  "geometry": {"coordinates":[-2.83175955098674,56.03462449040121],"type":"Point"}
}