{
  "type": "Feature",
  "properties": {
    "iso:country":"GB",
    "wof:name":"HR2 7TP",
    "wof:placetype":"postalcode"
},
  "geometry": {"coordinates":[-2.7396182203932,52.03843660010224],"type":"Point"}
}