{
  "type": "Feature",
  "properties": {
    "iso:country": "GB",
    "wof:name": "HR2 7TP",
    "wof:placetype": "postalcode"
  },
  "geometry": {"coordinates":[-2.739618,52.038437],"type":"Point"}
}
