{
  "type": "Feature",
  "properties": {
    "iso:country":"GB",
    "wof:name":"LE8 9GY",
    "wof:placetype":"postalcode"
},
  "geometry": {"coordinates":[-1.02783574746179,52.57721806676479],"type":"Point"}
}