{
  "type": "Feature",
  "properties": {
    "iso:country":"GB",
    "wof:name":"LE19 3EX",
    "wof:placetype":"postalcode"
},
  "geometry": {"coordinates":[-1.21301390136489,52.57523084041267],"type":"Point"}
}