{
  "type": "Feature",
  "properties": {
    "iso:country":"GB",
    "wof:name":"WA5 0HJ",
    "wof:placetype":"postalcode"
},
  "geometry": {"coordinates":[-2.60829442915448,53.41070453592777],"type":"Point"}
}