{
  "type": "Feature",
  "properties": {
    "iso:country":"GB",
    "wof:name":"GU16 7QH",
    "wof:placetype":"postalcode"
},
  "geometry": {"coordinates":[-0.74696313378961,51.31184198845174],"type":"Point"}
}