{
  "type": "Feature",
  "properties": {
    "iso:country": "GB",
    "wof:name": "GU16 7QH",
    "wof:placetype": "postalcode"
  },
  "geometry": {"coordinates":[-0.746963,51.311842],"type":"Point"}
}
