{
  "type": "Feature",
  "properties": {
    "date:inception_lower": "2024-06-01",
    "date:inception_upper": "2024-06-01",
    "iso:country": "GB",
    "wof:name": "SG18 9GT",
    "wof:placetype": "postalcode"
  },
  "geometry": {"coordinates":[-0.265644,52.045875],"type":"Point"}
}
