{
  "type": "Feature",
  "properties": {
    "date:inception_lower": "1987-04-01",
    "date:inception_upper": "1987-04-01",
    "iso:country": "GB",
    "wof:name": "WS15 3RJ",
    "wof:placetype": "postalcode"
  },
  "geometry": {"coordinates":[-1.881975,52.759431],"type":"Point"}
}
