{
  "type": "Feature",
  "properties": {
    "iso:country": "GB",
    "wof:name": "WS15 3RJ",
    "wof:placetype": "postalcode"
  },
  "geometry": {"coordinates":[-1.881975,52.759431],"type":"Point"}
}
