{
  "type": "Feature",
  "properties": {
    "iso:country": "GB",
    "wof:name": "BA5 1NQ",
    "wof:placetype": "postalcode"
  },
  "geometry": {"coordinates":[-2.67689,51.203187],"type":"Point"}
}
