{
  "type": "Feature",
  "properties": {
    "iso:country":"GB",
    "wof:name":"BA5 1NQ",
    "wof:placetype":"postalcode"
},
  "geometry": {"coordinates":[-2.67689017024367,51.203187097385],"type":"Point"}
}