{
  "type": "Feature",
  "properties": {
    "date:inception_lower": "2020-02-01",
    "date:inception_upper": "2020-02-01",
    "iso:country": "GB",
    "wof:name": "RG40 4AR",
    "wof:placetype": "postalcode"
  },
  "geometry": {"coordinates":[-0.901511,51.376168],"type":"Point"}
}
