{
  "type": "Feature",
  "properties": {
    "date:inception_lower": "1980-01-01",
    "date:inception_upper": "1980-01-01",
    "iso:country": "GB",
    "wof:name": "TF11 8AL",
    "wof:placetype": "postalcode"
  },
  "geometry": {"coordinates":[-2.375955,52.668322],"type":"Point"}
}
