{
  "type": "Feature",
  "properties": {
    "iso:country":"GB",
    "wof:name":"TF11 8AL",
    "wof:placetype":"postalcode"
},
  "geometry": {"coordinates":[-2.37595497177945,52.66832206946012],"type":"Point"}
}