{
  "type": "Feature",
  "properties": {
    "iso:country":"GB",
    "wof:name":"NR33 7UA",
    "wof:placetype":"postalcode"
},
  "geometry": {"coordinates":[1.71825943909362,52.41857329717998],"type":"Point"}
}