{
  "type": "Feature",
  "properties": {
    "date:inception_lower": "1980-01-01",
    "date:inception_upper": "1980-01-01",
    "iso:country": "GB",
    "wof:name": "NR33 7UA",
    "wof:placetype": "postalcode"
  },
  "geometry": {"coordinates":[1.718259,52.418573],"type":"Point"}
}
