{
  "type": "Feature",
  "properties": {
    "date:inception_lower": "2000-06-01",
    "date:inception_upper": "2000-06-01",
    "iso:country": "GB",
    "wof:name": "SN2 8BH",
    "wof:placetype": "postalcode"
  },
  "geometry": {"coordinates":[-1.772487,51.570598],"type":"Point"}
}
