{
  "type": "Feature",
  "properties": {
    "iso:country":"GB",
    "wof:name":"SN2 8BH",
    "wof:placetype":"postalcode"
},
  "geometry": {"coordinates":[-1.77248701439008,51.57059820519574],"type":"Point"}
}