{
  "type": "Feature",
  "properties": {
    "iso:country": "GB",
    "wof:name": "DN3 1NW",
    "wof:placetype": "postalcode"
  },
  "geometry": {"coordinates":[-1.068421,53.563554],"type":"Point"}
}
