{
  "type": "Feature",
  "properties": {
    "iso:country":"GB",
    "wof:name":"DN3 1NW",
    "wof:placetype":"postalcode"
},
  "geometry": {"coordinates":[-1.06842135213822,53.56355408672204],"type":"Point"}
}