{
  "type": "Feature",
  "properties": {
    "iso:country":"GB",
    "wof:name":"ML1 4PW",
    "wof:placetype":"postalcode"
},
  "geometry": {"coordinates":[-3.96655787428999,55.8186404739013],"type":"Point"}
}