{
  "type": "Feature",
  "properties": {
    "iso:country": "GB",
    "wof:name": "ML1 4PW",
    "wof:placetype": "postalcode"
  },
  "geometry": {"coordinates":[-3.966558,55.81864],"type":"Point"}
}
