{
  "type": "Feature",
  "properties": {
    "iso:country":"GB",
    "wof:name":"WS3 2LY",
    "wof:placetype":"postalcode"
},
  "geometry": {"coordinates":[-2.01945415405866,52.61884482853484],"type":"Point"}
}