{
  "type": "Feature",
  "properties": {
    "date:inception_lower": "1984-10-01",
    "date:inception_upper": "1984-10-01",
    "iso:country": "GB",
    "wof:name": "SA32 8NR",
    "wof:placetype": "postalcode"
  },
  "geometry": {"coordinates":[-4.17438,51.828889],"type":"Point"}
}
