{
  "type": "Feature",
  "properties": {
    "iso:country": "GB",
    "wof:name": "SA32 8NR",
    "wof:placetype": "postalcode"
  },
  "geometry": {"coordinates":[-4.17438,51.828889],"type":"Point"}
}
