{
  "type": "Feature",
  "properties": {
    "iso:country":"GB",
    "wof:name":"SA32 8NR",
    "wof:placetype":"postalcode"
},
  "geometry": {"coordinates":[-4.17437986661562,51.82888948653186],"type":"Point"}
}