{
  "type": "Feature",
  "properties": {
    "iso:country":"GB",
    "wof:name":"BN2 3HY",
    "wof:placetype":"postalcode"
},
  "geometry": {"coordinates":[-0.12710135701348,50.83521561487765],"type":"Point"}
}