{
  "type": "Feature",
  "properties": {
    "iso:country":"GB",
    "wof:name":"W12 0JR",
    "wof:placetype":"postalcode"
},
  "geometry": {"coordinates":[-0.2354507096257,51.50749447674254],"type":"Point"}
}