{
  "type": "Feature",
  "properties": {
    "date:inception_lower": "2022-09-01",
    "date:inception_upper": "2022-09-01",
    "iso:country": "GB",
    "wof:name": "BS4 1GE",
    "wof:placetype": "postalcode"
  },
  "geometry": {"coordinates":[-2.582575,51.428193],"type":"Point"}
}
