{
  "type": "Feature",
  "properties": {
    "iso:country":"GB",
    "wof:name":"RG14 5SH",
    "wof:placetype":"postalcode"
},
  "geometry": {"coordinates":[-1.30939351011753,51.40139967295103],"type":"Point"}
}