{
  "type": "Feature",
  "properties": {
    "iso:country":"GB",
    "wof:name":"TW18 1ED",
    "wof:placetype":"postalcode"
},
  "geometry": {"coordinates":[-0.49447221387005,51.42729774829892],"type":"Point"}
}