{
  "type": "Feature",
  "properties": {
    "date:inception_lower":"1980-01-01",
    "date:inception_upper":"1980-01-31",
    "iso:country":"GB",
    "wof:name":"TW18 1ED",
    "wof:placetype":"postalcode"
},
  "geometry": {"coordinates":[-0.494472,51.427298],"type":"Point"}
}