{
  "type": "Feature",
  "properties": {
    "date:inception_lower": "1980-01-01",
    "date:inception_upper": "1980-01-01",
    "iso:country": "GB",
    "wof:name": "LS21 2HA",
    "wof:placetype": "postalcode"
  },
  "geometry": {"coordinates":[-1.698173,53.924261],"type":"Point"}
}
