{
  "type": "Feature",
  "properties": {
    "date:inception_lower": "1980-01-01",
    "date:inception_upper": "1980-01-01",
    "iso:country": "GB",
    "wof:name": "EX20 4QS",
    "wof:placetype": "postalcode"
  },
  "geometry": {"coordinates":[-4.216209,50.684908],"type":"Point"}
}
