{
  "type": "Feature",
  "properties": {
    "iso:country": "GB",
    "wof:name": "NE62 5RQ",
    "wof:placetype": "postalcode"
  },
  "geometry": {"coordinates":[-1.603466,55.152832],"type":"Point"}
}
