{
  "type": "Feature",
  "properties": {
    "iso:country":"GB",
    "wof:name":"NE62 5RQ",
    "wof:placetype":"postalcode"
},
  "geometry": {"coordinates":[-1.60346596947758,55.15283245020282],"type":"Point"}
}