{
  "type": "Feature",
  "properties": {
    "iso:country":"GB",
    "wof:name":"IP7 7LP",
    "wof:placetype":"postalcode"
},
  "geometry": {"coordinates":[0.91446919561749,52.14665635243009],"type":"Point"}
}