{
  "type": "Feature",
  "properties": {
    "iso:country":"GB",
    "wof:name":"WR3 7JA",
    "wof:placetype":"postalcode"
},
  "geometry": {"coordinates":[-2.22315464989918,52.21123257997898],"type":"Point"}
}