{
  "type": "Feature",
  "properties": {
    "iso:country":"GB",
    "wof:name":"NG9 2EJ",
    "wof:placetype":"postalcode"
},
  "geometry": {"coordinates":[-1.20727768959434,52.92854455194485],"type":"Point"}
}