{
  "type": "Feature",
  "properties": {
    "date:inception_lower": "1990-07-01",
    "date:inception_upper": "1990-07-01",
    "iso:country": "GB",
    "wof:name": "CM8 1XY",
    "wof:placetype": "postalcode"
  },
  "geometry": {"coordinates":[0.644214,51.790951],"type":"Point"}
}
