{
  "type": "Feature",
  "properties": {
    "date:inception_lower": "2023-07-01",
    "date:inception_upper": "2023-07-01",
    "iso:country": "GB",
    "wof:name": "PE19 0DE",
    "wof:placetype": "postalcode"
  },
  "geometry": {"coordinates":[-0.248602,52.223163],"type":"Point"}
}
