{
  "type": "Feature",
  "properties": {
    "iso:country":"GB",
    "wof:name":"L40 3SJ",
    "wof:placetype":"postalcode"
},
  "geometry": {"coordinates":[-2.76451398370973,53.61446819480799],"type":"Point"}
}