{
  "type": "Feature",
  "properties": {
    "date:inception_lower": "1980-01-01",
    "date:inception_upper": "1980-01-01",
    "iso:country": "GB",
    "wof:name": "L40 3SJ",
    "wof:placetype": "postalcode"
  },
  "geometry": {"coordinates":[-2.764681,53.613764],"type":"Point"}
}
