{
  "type": "Feature",
  "properties": {
    "iso:country": "GB",
    "wof:name": "L40 3SJ",
    "wof:placetype": "postalcode"
  },
  "geometry": {"coordinates":[-2.764666,53.613764],"type":"Point"}
}
