{
  "type": "Feature",
  "properties": {
    "iso:country": "GB",
    "wof:name": "L40 3SJ",
    "wof:placetype": "postalcode"
  },
  "geometry": {"coordinates":[-2.764513,53.614484],"type":"Point"}
}
