{
  "type": "Feature",
  "properties": {
    "iso:country":"GB",
    "wof:name":"SN1 4FZ",
    "wof:placetype":"postalcode"
},
  "geometry": {"coordinates":[-1.77798905789538,51.55181673565031],"type":"Point"}
}