{
  "type": "Feature",
  "properties": {
    "date:inception_lower": "1995-07-01",
    "date:inception_upper": "1995-07-01",
    "iso:country": "GB",
    "wof:name": "RG20 0NQ",
    "wof:placetype": "postalcode"
  },
  "geometry": {"coordinates":[-1.392306,51.365955],"type":"Point"}
}
