{
  "type": "Feature",
  "properties": {
    "date:inception_lower": "1980-01-01",
    "date:inception_upper": "1980-01-01",
    "iso:country": "GB",
    "wof:name": "CO15 4DZ",
    "wof:placetype": "postalcode"
  },
  "geometry": {"coordinates":[1.1519,51.805824],"type":"Point"}
}
