{
  "type": "Feature",
  "properties": {
    "iso:country": "GB",
    "wof:name": "DH1 2TQ",
    "wof:placetype": "postalcode"
  },
  "geometry": {"coordinates":[-1.538465,54.748282],"type":"Point"}
}
