{
  "type": "Feature",
  "properties": {
    "iso:country":"GB",
    "wof:name":"DH1 2TQ",
    "wof:placetype":"postalcode"
},
  "geometry": {"coordinates":[-1.53846487924944,54.74828203195892],"type":"Point"}
}