{
  "type": "Feature",
  "properties": {
    "date:inception_lower": "1980-01-01",
    "date:inception_upper": "1980-01-01",
    "iso:country": "GB",
    "wof:name": "W8 6DN",
    "wof:placetype": "postalcode"
  },
  "geometry": {"coordinates":[-0.197047,51.495094],"type":"Point"}
}
