{
  "type": "Feature",
  "properties": {
    "iso:country":"GB",
    "wof:name":"RH19 1UZ",
    "wof:placetype":"postalcode"
},
  "geometry": {"coordinates":[-0.01644973384566,51.12743437492848],"type":"Point"}
}