{
  "type": "Feature",
  "properties": {
    "date:inception_lower": "1992-01-01",
    "date:inception_upper": "1992-01-01",
    "iso:country": "GB",
    "wof:name": "RH19 1UZ",
    "wof:placetype": "postalcode"
  },
  "geometry": {"coordinates":[-0.016422,51.127431],"type":"Point"}
}
