{
  "type": "Feature",
  "properties": {
    "iso:country": "GB",
    "wof:name": "NE23 7DJ",
    "wof:placetype": "postalcode"
  },
  "geometry": {"coordinates":[-1.589519,55.054542],"type":"Point"}
}
