{
  "type": "Feature",
  "properties": {
    "iso:country":"GB",
    "wof:name":"NE23 7DJ",
    "wof:placetype":"postalcode"
},
  "geometry": {"coordinates":[-1.58951938312362,55.05454151248114],"type":"Point"}
}