{
  "type": "Feature",
  "properties": {
    "date:inception_lower": "2024-04-01",
    "date:inception_upper": "2024-04-01",
    "iso:country": "GB",
    "wof:name": "SY8 2EZ",
    "wof:placetype": "postalcode"
  },
  "geometry": {"coordinates":[-2.729546,52.425258],"type":"Point"}
}
