{
  "type": "Feature",
  "properties": {
    "iso:country":"GB",
    "wof:name":"PR8 1RY",
    "wof:placetype":"postalcode"
},
  "geometry": {"coordinates":[-3.01108627192294,53.65340194627255],"type":"Point"}
}