{
  "type": "Feature",
  "properties": {
    "date:inception_lower": "2003-04-01",
    "date:inception_upper": "2003-04-01",
    "iso:country": "GB",
    "wof:name": "BN1 6XP",
    "wof:placetype": "postalcode"
  },
  "geometry": {"coordinates":[-0.15621,50.85336],"type":"Point"}
}
