{
  "type": "Feature",
  "properties": {
    "iso:country":"GB",
    "wof:name":"BN1 6XP",
    "wof:placetype":"postalcode"
},
  "geometry": {"coordinates":[-0.15621048314281,50.85336031436074],"type":"Point"}
}