{
  "type": "Feature",
  "properties": {
    "date:inception_lower": "1980-01-01",
    "date:inception_upper": "1980-01-01",
    "iso:country": "GB",
    "wof:name": "PE12 0XL",
    "wof:placetype": "postalcode"
  },
  "geometry": {"coordinates":[-0.08195,52.752025],"type":"Point"}
}
