{
  "type": "Feature",
  "properties": {
    "iso:country":"GB",
    "wof:name":"PE12 0XL",
    "wof:placetype":"postalcode"
},
  "geometry": {"coordinates":[-0.08239582776471,52.75228119980896],"type":"Point"}
}