{
  "type": "Feature",
  "properties": {
    "iso:country":"GB",
    "wof:name":"SK1 4DS",
    "wof:placetype":"postalcode"
},
  "geometry": {"coordinates":[-2.14268346138684,53.40755835671478],"type":"Point"}
}