{
  "type": "Feature",
  "properties": {
    "iso:country": "GB",
    "wof:name": "DE56 0LX",
    "wof:placetype": "postalcode"
  },
  "geometry": {"coordinates":[-1.436586,53.008132],"type":"Point"}
}
