{
  "type": "Feature",
  "properties": {
    "iso:country":"GB",
    "wof:name":"OL5 0ED",
    "wof:placetype":"postalcode"
},
  "geometry": {"coordinates":[-2.04633369414487,53.51482226187944],"type":"Point"}
}