{
  "type": "Feature",
  "properties": {
    "iso:country":"GB",
    "wof:name":"SO52 9NA",
    "wof:placetype":"postalcode"
},
  "geometry": {"coordinates":[-1.44912299870614,50.97501781471674],"type":"Point"}
}