{
  "type": "Feature",
  "properties": {
    "date:inception_lower": "1986-01-01",
    "date:inception_upper": "1986-01-01",
    "iso:country": "GB",
    "wof:name": "SO52 9NA",
    "wof:placetype": "postalcode"
  },
  "geometry": {"coordinates":[-1.449123,50.975018],"type":"Point"}
}
