{
  "type": "Feature",
  "properties": {
    "date:inception_lower": "1980-01-01",
    "date:inception_upper": "1980-01-01",
    "iso:country": "GB",
    "wof:name": "TW19 7TB",
    "wof:placetype": "postalcode"
  },
  "geometry": {"coordinates":[-0.470676,51.451557],"type":"Point"}
}
