{
  "type": "Feature",
  "properties": {
    "iso:country":"GB",
    "wof:name":"SW6 7SE",
    "wof:placetype":"postalcode"
},
  "geometry": {"coordinates":[-0.20284359061238,51.48397867840093],"type":"Point"}
}