{
  "type": "Feature",
  "properties": {
    "iso:country": "GB",
    "wof:name": "WA5 2PN",
    "wof:placetype": "postalcode"
  },
  "geometry": {"coordinates":[-2.655466,53.380028],"type":"Point"}
}
