{
  "type": "Feature",
  "properties": {
    "iso:country":"GB",
    "wof:name":"WA5 2PN",
    "wof:placetype":"postalcode"
},
  "geometry": {"coordinates":[-2.6554664060542,53.38002797729983],"type":"Point"}
}