{
  "type": "Feature",
  "properties": {
    "iso:country":"GB",
    "wof:name":"RG42 4US",
    "wof:placetype":"postalcode"
},
  "geometry": {"coordinates":[-0.77332734253218,51.42341653106028],"type":"Point"}
}