{
  "type": "Feature",
  "properties": {
    "iso:country": "GB",
    "wof:name": "RG42 4US",
    "wof:placetype": "postalcode"
  },
  "geometry": {"coordinates":[-0.773327,51.423417],"type":"Point"}
}
