{
  "type": "Feature",
  "properties": {
    "iso:country":"GB",
    "wof:name":"SS5 6JG",
    "wof:placetype":"postalcode"
},
  "geometry": {"coordinates":[0.61577027262202,51.62356536911627],"type":"Point"}
}