{
  "type": "Feature",
  "properties": {
    "date:inception_lower": "1980-01-01",
    "date:inception_upper": "1980-01-01",
    "iso:country": "GB",
    "wof:name": "SS5 6JG",
    "wof:placetype": "postalcode"
  },
  "geometry": {"coordinates":[0.615798,51.623588],"type":"Point"}
}
