{
  "type": "Feature",
  "properties": {
    "iso:country": "GB",
    "wof:name": "PR1 3XJ",
    "wof:placetype": "postalcode"
  },
  "geometry": {"coordinates":[-2.695861,53.757055],"type":"Point"}
}
