{
  "type": "Feature",
  "properties": {
    "iso:country":"GB",
    "wof:name":"PR1 3XJ",
    "wof:placetype":"postalcode"
},
  "geometry": {"coordinates":[-2.69586078958918,53.75705547619755],"type":"Point"}
}