{
  "type": "Feature",
  "properties": {
    "date:inception_lower": "1980-01-01",
    "date:inception_upper": "1980-01-01",
    "iso:country": "GB",
    "wof:name": "PR1 3XJ",
    "wof:placetype": "postalcode"
  },
  "geometry": {"coordinates":[-2.695861,53.757055],"type":"Point"}
}
