{
  "type": "Feature",
  "properties": {
    "iso:country": "GB",
    "wof:name": "SO16 3GG",
    "wof:placetype": "postalcode"
  },
  "geometry": {"coordinates":[-1.400484,50.939429],"type":"Point"}
}
