{
  "type": "Feature",
  "properties": {
    "iso:country":"GB",
    "wof:name":"DD3 7BP",
    "wof:placetype":"postalcode"
},
  "geometry": {"coordinates":[-2.96125081066909,56.47482745630195],"type":"Point"}
}