{
  "type": "Feature",
  "properties": {
    "date:inception_lower": "2015-09-01",
    "date:inception_upper": "2015-09-01",
    "iso:country": "GB",
    "wof:name": "DD3 7BP",
    "wof:placetype": "postalcode"
  },
  "geometry": {"coordinates":[-2.961378,56.474565],"type":"Point"}
}
