{
  "type": "Feature",
  "properties": {
    "iso:country":"GB",
    "wof:name":"HG4 1SP",
    "wof:placetype":"postalcode"
},
  "geometry": {"coordinates":[-1.52925821804116,54.13161559430651],"type":"Point"}
}