{
  "type": "Feature",
  "properties": {
    "iso:country": "GB",
    "wof:name": "HG4 1SP",
    "wof:placetype": "postalcode"
  },
  "geometry": {"coordinates":[-1.529258,54.131616],"type":"Point"}
}
