{
  "type": "Feature",
  "properties": {
    "date:inception_lower": "1994-05-01",
    "date:inception_upper": "1994-05-01",
    "iso:country": "GB",
    "wof:name": "KT12 5HZ",
    "wof:placetype": "postalcode"
  },
  "geometry": {"coordinates":[-0.414807,51.372113],"type":"Point"}
}
