{
  "type": "Feature",
  "properties": {
    "date:inception_lower":"1995-01-01",
    "date:inception_upper":"1995-01-31",
    "iso:country":"GB",
    "wof:name":"S43 4UX",
    "wof:placetype":"postalcode"
},
  "geometry": {"coordinates":[-1.286257,53.28499],"type":"Point"}
}