{
  "type": "Feature",
  "properties": {
    "iso:country":"GB",
    "wof:name":"S64 9EG",
    "wof:placetype":"postalcode"
},
  "geometry": {"coordinates":[-1.30142211138469,53.4962439770278],"type":"Point"}
}