{
  "type": "Feature",
  "properties": {
    "iso:country":"GB",
    "wof:name":"HX2 6JN",
    "wof:placetype":"postalcode"
},
  "geometry": {"coordinates":[-1.95670790274534,53.71115362096116],"type":"Point"}
}