{
  "type": "Feature",
  "properties": {
    "iso:country": "GB",
    "wof:name": "SW17 7PD",
    "wof:placetype": "postalcode"
  },
  "geometry": {"coordinates":[-0.162021,51.434651],"type":"Point"}
}
