{
  "type": "Feature",
  "properties": {
    "iso:country":"GB",
    "wof:name":"HP12 3EH",
    "wof:placetype":"postalcode"
},
  "geometry": {"coordinates":[-0.77376895585076,51.63073804891582],"type":"Point"}
}