{
  "type": "Feature",
  "properties": {
    "iso:country": "GB",
    "wof:name": "SW18 1JH",
    "wof:placetype": "postalcode"
  },
  "geometry": {"coordinates":[-0.181915,51.460842],"type":"Point"}
}
