{
  "type": "Feature",
  "properties": {
    "iso:country":"GB",
    "wof:name":"SW18 1JH",
    "wof:placetype":"postalcode"
},
  "geometry": {"coordinates":[-0.18191473472716,51.46084204337616],"type":"Point"}
}