{
  "type": "Feature",
  "properties": {
    "iso:country":"GB",
    "wof:name":"CB9 9JR",
    "wof:placetype":"postalcode"
},
  "geometry": {"coordinates":[0.43247163690562,52.09160054117056],"type":"Point"}
}