{
  "type": "Feature",
  "properties": {
    "date:inception_lower":"2001-06-01",
    "date:inception_upper":"2001-06-30",
    "iso:country":"GB",
    "wof:name":"PO31 7UN",
    "wof:placetype":"postalcode"
},
  "geometry": {"coordinates":[-1.307413,50.753926],"type":"Point"}
}