{
  "type": "Feature",
  "properties": {
    "iso:country":"GB",
    "wof:name":"PO31 7UN",
    "wof:placetype":"postalcode"
},
  "geometry": {"coordinates":[-1.30740835389996,50.75393665903214],"type":"Point"}
}