{
  "type": "Feature",
  "properties": {
    "iso:country":"GB",
    "wof:name":"RG7 5PD",
    "wof:placetype":"postalcode"
},
  "geometry": {"coordinates":[-1.1594959946129,51.41499660746374],"type":"Point"}
}