{
  "type": "Feature",
  "properties": {
    "iso:country":"GB",
    "wof:name":"ME7 2BS",
    "wof:placetype":"postalcode"
},
  "geometry": {"coordinates":[0.56168319830552,51.37607978834473],"type":"Point"}
}