{
  "type": "Feature",
  "properties": {
    "iso:country": "GB",
    "wof:name": "ME7 2BS",
    "wof:placetype": "postalcode"
  },
  "geometry": {"coordinates":[0.561683,51.37608],"type":"Point"}
}
