{
  "type": "Feature",
  "properties": {
    "date:inception_lower": "1980-01-01",
    "date:inception_upper": "1980-01-01",
    "iso:country": "GB",
    "wof:name": "S9 3WG",
    "wof:placetype": "postalcode"
  },
  "geometry": {"coordinates":[-1.433418,53.393798],"type":"Point"}
}
