{
  "type": "Feature",
  "properties": {
    "iso:country":"GB",
    "wof:name":"HU9 2RF",
    "wof:placetype":"postalcode"
},
  "geometry": {"coordinates":[-0.30743952587147,53.75310744919442],"type":"Point"}
}