{
  "type": "Feature",
  "properties": {
    "iso:country":"GB",
    "wof:name":"DL3 9DB",
    "wof:placetype":"postalcode"
},
  "geometry": {"coordinates":[-1.5884980755179,54.53085640598035],"type":"Point"}
}