{
  "type": "Feature",
  "properties": {
    "iso:country": "GB",
    "wof:name": "ST10 4SF",
    "wof:placetype": "postalcode"
  },
  "geometry": {"coordinates":[-1.914075,52.946348],"type":"Point"}
}
