{
  "type": "Feature",
  "properties": {
    "iso:country":"GB",
    "wof:name":"ST10 4SF",
    "wof:placetype":"postalcode"
},
  "geometry": {"coordinates":[-1.91407486195909,52.94634787391233],"type":"Point"}
}