{
  "type": "Feature",
  "properties": {
    "date:inception_lower": "1999-12-01",
    "date:inception_upper": "1999-12-01",
    "iso:country": "GB",
    "wof:name": "ST10 4SF",
    "wof:placetype": "postalcode"
  },
  "geometry": {"coordinates":[-1.914075,52.946348],"type":"Point"}
}
