{
  "type": "Feature",
  "properties": {
    "iso:country":"GB",
    "wof:name":"BD20 7AY",
    "wof:placetype":"postalcode"
},
  "geometry": {"coordinates":[-2.00069375369368,53.88534790441496],"type":"Point"}
}