{
  "type": "Feature",
  "properties": {
    "date:inception_lower": "1980-01-01",
    "date:inception_upper": "1980-01-01",
    "iso:country": "GB",
    "wof:name": "BD20 7AY",
    "wof:placetype": "postalcode"
  },
  "geometry": {"coordinates":[-2.000697,53.885362],"type":"Point"}
}
