{
  "type": "Feature",
  "properties": {
    "iso:country": "GB",
    "wof:name": "CF47 8DN",
    "wof:placetype": "postalcode"
  },
  "geometry": {"coordinates":[-3.378554,51.744614],"type":"Point"}
}
