{
  "type": "Feature",
  "properties": {
    "iso:country":"GB",
    "wof:name":"CF47 8DN",
    "wof:placetype":"postalcode"
},
  "geometry": {"coordinates":[-3.37855379335158,51.74461373269388],"type":"Point"}
}