{
  "type": "Feature",
  "properties": {
    "iso:country":"GB",
    "wof:name":"DN40 2JG",
    "wof:placetype":"postalcode"
},
  "geometry": {"coordinates":[-0.21339808063697,53.61972381534321],"type":"Point"}
}