{
  "type": "Feature",
  "properties": {
    "iso:country": "GB",
    "wof:name": "YO17 6QW",
    "wof:placetype": "postalcode"
  },
  "geometry": {"coordinates":[-0.825632,54.150313],"type":"Point"}
}
