{
  "type": "Feature",
  "properties": {
    "date:inception_lower": "1998-06-01",
    "date:inception_upper": "1998-06-01",
    "iso:country": "GB",
    "wof:name": "YO17 6QW",
    "wof:placetype": "postalcode"
  },
  "geometry": {"coordinates":[-0.825632,54.150313],"type":"Point"}
}
