{
  "type": "Feature",
  "properties": {
    "date:inception_lower": "1980-01-01",
    "date:inception_upper": "1980-01-01",
    "iso:country": "GB",
    "wof:name": "BS26 2SF",
    "wof:placetype": "postalcode"
  },
  "geometry": {"coordinates":[-2.888408,51.266232],"type":"Point"}
}
