{
  "type": "Feature",
  "properties": {
    "iso:country":"GB",
    "wof:name":"B12 0SQ",
    "wof:placetype":"postalcode"
},
  "geometry": {"coordinates":[-1.88995079451971,52.46883567228813],"type":"Point"}
}