{
  "type": "Feature",
  "properties": {
    "iso:country": "GB",
    "wof:name": "LE2 1LL",
    "wof:placetype": "postalcode"
  },
  "geometry": {"coordinates":[-1.112441,52.624604],"type":"Point"}
}
