{
  "type": "Feature",
  "properties": {
    "iso:country":"GB",
    "wof:name":"LE2 1LL",
    "wof:placetype":"postalcode"
},
  "geometry": {"coordinates":[-1.11249979080198,52.62460399253546],"type":"Point"}
}