{
  "type": "Feature",
  "properties": {
    "iso:country":"GB",
    "wof:name":"SP4 7JR",
    "wof:placetype":"postalcode"
},
  "geometry": {"coordinates":[-1.76078701329698,51.1645823866826],"type":"Point"}
}