{
  "type": "Feature",
  "properties": {
    "date:inception_lower":"1980-01-01",
    "date:inception_upper":"1980-01-31",
    "iso:country":"GB",
    "wof:name":"SP4 7JR",
    "wof:placetype":"postalcode"
},
  "geometry": {"coordinates":[-1.760787,51.164582],"type":"Point"}
}