{
  "type": "Feature",
  "properties": {
    "iso:country": "GB",
    "wof:name": "KY1 1BN",
    "wof:placetype": "postalcode"
  },
  "geometry": {"coordinates":[-3.157824,56.117211],"type":"Point"}
}
