{
  "type": "Feature",
  "properties": {
    "iso:country":"GB",
    "wof:name":"KY1 1BN",
    "wof:placetype":"postalcode"
},
  "geometry": {"coordinates":[-3.15782383036705,56.11721092939721],"type":"Point"}
}