{
  "type": "Feature",
  "properties": {
    "iso:country":"GB",
    "wof:name":"WS14 0LW",
    "wof:placetype":"postalcode"
},
  "geometry": {"coordinates":[-1.83627648586823,52.63656036309361],"type":"Point"}
}