{
  "type": "Feature",
  "properties": {
    "iso:country": "GB",
    "wof:name": "WS14 0LW",
    "wof:placetype": "postalcode"
  },
  "geometry": {"coordinates":[-1.836276,52.63656],"type":"Point"}
}
