{
  "type": "Feature",
  "properties": {
    "iso:country":"GB",
    "wof:name":"BN8 6AE",
    "wof:placetype":"postalcode"
},
  "geometry": {"coordinates":[0.16245234891528,50.92296909457815],"type":"Point"}
}