{
  "type": "Feature",
  "properties": {
    "date:inception_lower":"2008-07-01",
    "date:inception_upper":"2008-07-31",
    "iso:country":"GB",
    "wof:name":"BN8 6AE",
    "wof:placetype":"postalcode"
},
  "geometry": {"coordinates":[0.162452,50.922969],"type":"Point"}
}