{
  "type": "Feature",
  "properties": {
    "iso:country":"GB",
    "wof:name":"TR18 2BH",
    "wof:placetype":"postalcode"
},
  "geometry": {"coordinates":[-5.53848895593043,50.12116766492309],"type":"Point"}
}