{
  "type": "Feature",
  "properties": {
    "iso:country": "GB",
    "wof:name": "NR14 7BN",
    "wof:placetype": "postalcode"
  },
  "geometry": {"coordinates":[1.431747,52.561887],"type":"Point"}
}
