{
  "type": "Feature",
  "properties": {
    "iso:country":"GB",
    "wof:name":"BD2 4PH",
    "wof:placetype":"postalcode"
},
  "geometry": {"coordinates":[-1.73260580732479,53.80846471636568],"type":"Point"}
}