{
  "type": "Feature",
  "properties": {
    "date:inception_lower": "1995-07-01",
    "date:inception_upper": "1995-07-01",
    "iso:country": "GB",
    "wof:name": "RG40 2BT",
    "wof:placetype": "postalcode"
  },
  "geometry": {"coordinates":[-0.833285,51.407618],"type":"Point"}
}
