{
  "type": "Feature",
  "properties": {
    "iso:country": "GB",
    "wof:name": "RG40 2BT",
    "wof:placetype": "postalcode"
  },
  "geometry": {"coordinates":[-0.833303,51.407618],"type":"Point"}
}
