{
  "type": "Feature",
  "properties": {
    "iso:country": "GB",
    "wof:name": "PR7 3DB",
    "wof:placetype": "postalcode"
  },
  "geometry": {"coordinates":[-2.627329,53.642609],"type":"Point"}
}
