{
  "type": "Feature",
  "properties": {
    "iso:country":"GB",
    "wof:name":"PR7 3DB",
    "wof:placetype":"postalcode"
},
  "geometry": {"coordinates":[-2.62732868575616,53.64260878850065],"type":"Point"}
}