{
  "type": "Feature",
  "properties": {
    "iso:country":"GB",
    "wof:name":"DA9 9PG",
    "wof:placetype":"postalcode"
},
  "geometry": {"coordinates":[0.27473483814769,51.4489311862223],"type":"Point"}
}