{
  "type": "Feature",
  "properties": {
    "iso:country":"GB",
    "wof:name":"DT6 6RY",
    "wof:placetype":"postalcode"
},
  "geometry": {"coordinates":[-2.82058485585307,50.73294094687197],"type":"Point"}
}