{
  "type": "Feature",
  "properties": {
    "iso:country": "GB",
    "wof:name": "DT6 6RY",
    "wof:placetype": "postalcode"
  },
  "geometry": {"coordinates":[-2.820374,50.732931],"type":"Point"}
}
