{
  "type": "Feature",
  "properties": {
    "iso:country":"GB",
    "wof:name":"AL5 3EE",
    "wof:placetype":"postalcode"
},
  "geometry": {"coordinates":[-0.37841310870827,51.82578088237233],"type":"Point"}
}