{
  "type": "Feature",
  "properties": {
    "date:inception_lower": "1980-01-01",
    "date:inception_upper": "1980-01-01",
    "iso:country": "GB",
    "wof:name": "AL5 3EE",
    "wof:placetype": "postalcode"
  },
  "geometry": {"coordinates":[-0.378413,51.825781],"type":"Point"}
}
