{
  "type": "Feature",
  "properties": {
    "iso:country": "GB",
    "wof:name": "GU22 7UD",
    "wof:placetype": "postalcode"
  },
  "geometry": {"coordinates":[-0.566275,51.311792],"type":"Point"}
}
