{
  "type": "Feature",
  "properties": {
    "iso:country":"GB",
    "wof:name":"RG21 7PY",
    "wof:placetype":"postalcode"
},
  "geometry": {"coordinates":[-1.08187607529737,51.26466231374633],"type":"Point"}
}