{
  "type": "Feature",
  "properties": {
    "date:inception_lower": "2022-08-01",
    "date:inception_upper": "2022-08-01",
    "iso:country": "GB",
    "wof:name": "GU10 1FU",
    "wof:placetype": "postalcode"
  },
  "geometry": {"coordinates":[-0.73461,51.232359],"type":"Point"}
}
