{
  "type": "Feature",
  "properties": {
    "date:inception_lower": "1980-01-01",
    "date:inception_upper": "1980-01-01",
    "iso:country": "GB",
    "wof:name": "BB10 1DZ",
    "wof:placetype": "postalcode"
  },
  "geometry": {"coordinates":[-2.234348,53.804862],"type":"Point"}
}
