{
  "type": "Feature",
  "properties": {
    "iso:country":"GB",
    "wof:name":"SL4 4BE",
    "wof:placetype":"postalcode"
},
  "geometry": {"coordinates":[-0.63896114371556,51.46702899877189],"type":"Point"}
}