{
  "type": "Feature",
  "properties": {
    "date:inception_lower":"2011-02-01",
    "date:inception_upper":"2011-02-28",
    "iso:country":"GB",
    "wof:name":"DE22 3DS",
    "wof:placetype":"postalcode"
},
  "geometry": {"coordinates":[-1.493874,52.926541],"type":"Point"}
}