{
  "type": "Feature",
  "properties": {
    "iso:country":"GB",
    "wof:name":"DE22 3DS",
    "wof:placetype":"postalcode"
},
  "geometry": {"coordinates":[-1.49387427725999,52.92654143230444],"type":"Point"}
}