{
  "type": "Feature",
  "properties": {
    "iso:country": "GB",
    "wof:name": "DE22 3DS",
    "wof:placetype": "postalcode"
  },
  "geometry": {"coordinates":[-1.493874,52.926541],"type":"Point"}
}
