{
  "type": "Feature",
  "properties": {
    "iso:country": "GB",
    "wof:name": "GL6 8GY",
    "wof:placetype": "postalcode"
  },
  "geometry": {"coordinates":[-2.149608,51.720993],"type":"Point"}
}
