{
  "type": "Feature",
  "properties": {
    "iso:country":"GB",
    "wof:name":"GL6 8GY",
    "wof:placetype":"postalcode"
},
  "geometry": {"coordinates":[-2.14960826724434,51.72099320547103],"type":"Point"}
}