{
  "type": "Feature",
  "properties": {
    "date:inception_lower":"2005-08-01",
    "date:inception_upper":"2005-08-31",
    "iso:country":"GB",
    "wof:name":"GL6 8GY",
    "wof:placetype":"postalcode"
},
  "geometry": {"coordinates":[-2.149608,51.720993],"type":"Point"}
}