{
  "type": "Feature",
  "properties": {
    "date:inception_lower":"1980-01-01",
    "date:inception_upper":"1980-01-31",
    "iso:country":"GB",
    "wof:name":"DY7 5EE",
    "wof:placetype":"postalcode"
},
  "geometry": {"coordinates":[-2.256672,52.520561],"type":"Point"}
}