{
  "type": "Feature",
  "properties": {
    "iso:country": "GB",
    "wof:name": "DY7 5EE",
    "wof:placetype": "postalcode"
  },
  "geometry": {"coordinates":[-2.256672,52.520561],"type":"Point"}
}
