{
  "type": "Feature",
  "properties": {
    "iso:country": "GB",
    "wof:name": "NE12 5XA",
    "wof:placetype": "postalcode"
  },
  "geometry": {"coordinates":[-1.580755,55.040934],"type":"Point"}
}
