{
  "type": "Feature",
  "properties": {
    "iso:country":"GB",
    "wof:name":"NE12 5XA",
    "wof:placetype":"postalcode"
},
  "geometry": {"coordinates":[-1.58075456248299,55.04093357119091],"type":"Point"}
}