{
  "type": "Feature",
  "properties": {
    "date:inception_lower": "1980-01-01",
    "date:inception_upper": "1980-01-01",
    "iso:country": "GB",
    "wof:name": "PL26 8TD",
    "wof:placetype": "postalcode"
  },
  "geometry": {"coordinates":[-4.796546,50.376185],"type":"Point"}
}
