{
  "type": "Feature",
  "properties": {
    "iso:country":"GB",
    "wof:name":"PL26 8TD",
    "wof:placetype":"postalcode"
},
  "geometry": {"coordinates":[-4.79650450146551,50.3761969384185],"type":"Point"}
}