{
  "type": "Feature",
  "properties": {
    "date:inception_lower": "1980-01-01",
    "date:inception_upper": "1980-01-01",
    "iso:country": "GB",
    "wof:name": "CW1 3LE",
    "wof:placetype": "postalcode"
  },
  "geometry": {"coordinates":[-2.457154,53.104787],"type":"Point"}
}
