{
  "type": "Feature",
  "properties": {
    "iso:country":"GB",
    "wof:name":"LL40 1AB",
    "wof:placetype":"postalcode"
},
  "geometry": {"coordinates":[-3.88444472058648,52.74298632187325],"type":"Point"}
}