{
  "type": "Feature",
  "properties": {
    "iso:country":"GB",
    "wof:name":"TN26 1HG",
    "wof:placetype":"postalcode"
},
  "geometry": {"coordinates":[0.83643733044803,51.11463455655026],"type":"Point"}
}