{
  "type": "Feature",
  "properties": {
    "iso:country": "GB",
    "wof:name": "LA9 7LZ",
    "wof:placetype": "postalcode"
  },
  "geometry": {"coordinates":[-2.72897,54.310149],"type":"Point"}
}
