{
  "type": "Feature",
  "properties": {
    "date:inception_lower": "1994-12-01",
    "date:inception_upper": "1994-12-01",
    "iso:country": "GB",
    "wof:name": "SO16 8JW",
    "wof:placetype": "postalcode"
  },
  "geometry": {"coordinates":[-1.455254,50.951289],"type":"Point"}
}
