{
  "type": "Feature",
  "properties": {
    "iso:country":"GB",
    "wof:name":"TS18 5BU",
    "wof:placetype":"postalcode"
},
  "geometry": {"coordinates":[-1.33987935920693,54.55676167964712],"type":"Point"}
}