{
  "type": "Feature",
  "properties": {
    "date:inception_lower": "1980-01-01",
    "date:inception_upper": "1980-01-01",
    "iso:country": "GB",
    "wof:name": "TS18 5BU",
    "wof:placetype": "postalcode"
  },
  "geometry": {"coordinates":[-1.339879,54.556762],"type":"Point"}
}
