{
  "type": "Feature",
  "properties": {
    "iso:country":"GB",
    "wof:name":"LD8 2EW",
    "wof:placetype":"postalcode"
},
  "geometry": {"coordinates":[-3.02576028464008,52.30473932853191],"type":"Point"}
}