{
  "type": "Feature",
  "properties": {
    "iso:country":"GB",
    "wof:name":"TR20 8HQ",
    "wof:placetype":"postalcode"
},
  "geometry": {"coordinates":[-5.49523861626638,50.14172289160269],"type":"Point"}
}