{
  "type": "Feature",
  "properties": {
    "iso:country": "GB",
    "wof:name": "TR20 8HQ",
    "wof:placetype": "postalcode"
  },
  "geometry": {"coordinates":[-5.495239,50.141723],"type":"Point"}
}
