{
  "type": "Feature",
  "properties": {
    "iso:country":"GB",
    "wof:name":"HA6 2YU",
    "wof:placetype":"postalcode"
},
  "geometry": {"coordinates":[-0.42305631820486,51.60750669252965],"type":"Point"}
}