{
  "type": "Feature",
  "properties": {
    "iso:country":"GB",
    "wof:name":"CH4 8DR",
    "wof:placetype":"postalcode"
},
  "geometry": {"coordinates":[-2.91402932282745,53.17662205211006],"type":"Point"}
}