{
  "type": "Feature",
  "properties": {
    "iso:country": "GB",
    "wof:name": "RH3 7LR",
    "wof:placetype": "postalcode"
  },
  "geometry": {"coordinates":[-0.281577,51.237719],"type":"Point"}
}
