{
  "type": "Feature",
  "properties": {
    "iso:country":"GB",
    "wof:name":"RH3 7LR",
    "wof:placetype":"postalcode"
},
  "geometry": {"coordinates":[-0.28157727486789,51.23771946505636],"type":"Point"}
}