{
  "type": "Feature",
  "properties": {
    "iso:country": "GB",
    "wof:name": "EX16 7RZ",
    "wof:placetype": "postalcode"
  },
  "geometry": {"coordinates":[-3.468802,50.95553],"type":"Point"}
}
