{
  "type": "Feature",
  "properties": {
    "iso:country":"GB",
    "wof:name":"EX16 7RZ",
    "wof:placetype":"postalcode"
},
  "geometry": {"coordinates":[-3.46880170525577,50.95553010461767],"type":"Point"}
}