{
  "type": "Feature",
  "properties": {
    "iso:country":"GB",
    "wof:name":"SW15 3DF",
    "wof:placetype":"postalcode"
},
  "geometry": {"coordinates":[-0.22703474466431,51.45440199988179],"type":"Point"}
}