{
  "type": "Feature",
  "properties": {
    "iso:country": "GB",
    "wof:name": "LU2 0JA",
    "wof:placetype": "postalcode"
  },
  "geometry": {"coordinates":[-0.40869,51.882815],"type":"Point"}
}
