{
  "type": "Feature",
  "properties": {
    "iso:country":"GB",
    "wof:name":"LU2 0JA",
    "wof:placetype":"postalcode"
},
  "geometry": {"coordinates":[-0.40868985109572,51.88281539893187],"type":"Point"}
}