{
  "type": "Feature",
  "properties": {
    "iso:country":"GB",
    "wof:name":"WR9 9DT",
    "wof:placetype":"postalcode"
},
  "geometry": {"coordinates":[-2.16525769369986,52.27408048720709],"type":"Point"}
}