{
  "type": "Feature",
  "properties": {
    "iso:country":"GB",
    "wof:name":"BR2 9DJ",
    "wof:placetype":"postalcode"
},
  "geometry": {"coordinates":[0.01153841893495,51.391513237717],"type":"Point"}
}