{
  "type": "Feature",
  "properties": {
    "date:inception_lower": "1980-01-01",
    "date:inception_upper": "1980-01-01",
    "iso:country": "GB",
    "wof:name": "DN36 5BP",
    "wof:placetype": "postalcode"
  },
  "geometry": {"coordinates":[-0.054412,53.502677],"type":"Point"}
}
