{
  "type": "Feature",
  "properties": {
    "iso:country":"GB",
    "wof:name":"DN36 5BP",
    "wof:placetype":"postalcode"
},
  "geometry": {"coordinates":[-0.05437721476616,53.50265963722178],"type":"Point"}
}