{
  "type": "Feature",
  "properties": {
    "iso:country":"GB",
    "wof:name":"WV14 0ST",
    "wof:placetype":"postalcode"
},
  "geometry": {"coordinates":[-2.07284686690094,52.56373448012581],"type":"Point"}
}