{
  "type": "Feature",
  "properties": {
    "date:inception_lower": "1995-12-01",
    "date:inception_upper": "1995-12-01",
    "iso:country": "GB",
    "wof:name": "WV14 0ST",
    "wof:placetype": "postalcode"
  },
  "geometry": {"coordinates":[-2.073314,52.563956],"type":"Point"}
}
