{
  "type": "Feature",
  "properties": {
    "iso:country":"GB",
    "wof:name":"HP18 9LJ",
    "wof:placetype":"postalcode"
},
  "geometry": {"coordinates":[-1.00363684250688,51.79225967190202],"type":"Point"}
}