{
  "type": "Feature",
  "properties": {
    "iso:country": "GB",
    "wof:name": "HP18 9LJ",
    "wof:placetype": "postalcode"
  },
  "geometry": {"coordinates":[-1.003615,51.792266],"type":"Point"}
}
