{
  "type": "Feature",
  "properties": {
    "iso:country":"GB",
    "wof:name":"RG1 8HD",
    "wof:placetype":"postalcode"
},
  "geometry": {"coordinates":[-0.98546480009084,51.46140263072668],"type":"Point"}
}