{
  "type": "Feature",
  "properties": {
    "iso:country":"GB",
    "wof:name":"PE1 5EY",
    "wof:placetype":"postalcode"
},
  "geometry": {"coordinates":[-0.22845474916015,52.57712818708439],"type":"Point"}
}