{
  "type": "Feature",
  "properties": {
    "iso:country":"GB",
    "wof:name":"CM11 2AE",
    "wof:placetype":"postalcode"
},
  "geometry": {"coordinates":[0.42399898205382,51.62714344238814],"type":"Point"}
}