{
  "type": "Feature",
  "properties": {
    "iso:country": "GB",
    "wof:name": "CM11 2AE",
    "wof:placetype": "postalcode"
  },
  "geometry": {"coordinates":[0.423999,51.627143],"type":"Point"}
}
