{
  "type": "Feature",
  "properties": {
    "date:inception_lower": "1990-02-01",
    "date:inception_upper": "1990-02-01",
    "iso:country": "GB",
    "wof:name": "CA11 7SQ",
    "wof:placetype": "postalcode"
  },
  "geometry": {"coordinates":[-2.747256,54.672085],"type":"Point"}
}
