{
  "type": "Feature",
  "properties": {
    "iso:country": "GB",
    "wof:name": "CA11 7SQ",
    "wof:placetype": "postalcode"
  },
  "geometry": {"coordinates":[-2.747256,54.672085],"type":"Point"}
}
