{
  "type": "Feature",
  "properties": {
    "iso:country":"GB",
    "wof:name":"HA3 6TH",
    "wof:placetype":"postalcode"
},
  "geometry": {"coordinates":[-0.34385829825829,51.60912273449699],"type":"Point"}
}