{
  "type": "Feature",
  "properties": {
    "iso:country": "GB",
    "wof:name": "CV47 7SH",
    "wof:placetype": "postalcode"
  },
  "geometry": {"coordinates":[-1.305683,52.199672],"type":"Point"}
}
