{
  "type": "Feature",
  "properties": {
    "date:inception_lower":"1999-12-01",
    "date:inception_upper":"1999-12-31",
    "iso:country":"GB",
    "wof:name":"CV47 7SH",
    "wof:placetype":"postalcode"
},
  "geometry": {"coordinates":[-1.305683,52.199672],"type":"Point"}
}