{
  "type": "Feature",
  "properties": {
    "iso:country": "GB",
    "wof:name": "RH13 9JB",
    "wof:placetype": "postalcode"
  },
  "geometry": {"coordinates":[-0.352398,51.022973],"type":"Point"}
}
