{
  "type": "Feature",
  "properties": {
    "iso:country":"GB",
    "wof:name":"PE37 7RB",
    "wof:placetype":"postalcode"
},
  "geometry": {"coordinates":[0.69114068911641,52.64672212773711],"type":"Point"}
}