{
  "type": "Feature",
  "properties": {
    "iso:country": "GB",
    "wof:name": "BN24 5NH",
    "wof:placetype": "postalcode"
  },
  "geometry": {"coordinates":[0.322424,50.811816],"type":"Point"}
}
