{
  "type": "Feature",
  "properties": {
    "date:inception_lower":"1995-07-01",
    "date:inception_upper":"1995-07-31",
    "iso:country":"GB",
    "wof:name":"BN24 5NH",
    "wof:placetype":"postalcode"
},
  "geometry": {"coordinates":[0.322424,50.811816],"type":"Point"}
}