{
  "type": "Feature",
  "properties": {
    "iso:country":"GB",
    "wof:name":"BN24 5NH",
    "wof:placetype":"postalcode"
},
  "geometry": {"coordinates":[0.32295180685032,50.81187710455469],"type":"Point"}
}