{
  "type": "Feature",
  "properties": {
    "date:inception_lower": "1980-01-01",
    "date:inception_upper": "1980-01-01",
    "iso:country": "GB",
    "wof:name": "ST16 3QW",
    "wof:placetype": "postalcode"
  },
  "geometry": {"coordinates":[-2.096443,52.815023],"type":"Point"}
}
