{
  "type": "Feature",
  "properties": {
    "iso:country":"GB",
    "wof:name":"S8 9RD",
    "wof:placetype":"postalcode"
},
  "geometry": {"coordinates":[-1.46577956112728,53.35651798613706],"type":"Point"}
}