{
  "type": "Feature",
  "properties": {
    "iso:country":"GB",
    "wof:name":"KA18 3PG",
    "wof:placetype":"postalcode"
},
  "geometry": {"coordinates":[-4.07886412851416,55.51844987435354],"type":"Point"}
}