{
  "type": "Feature",
  "properties": {
    "date:inception_lower": "1980-01-01",
    "date:inception_upper": "1980-01-01",
    "iso:country": "GB",
    "wof:name": "SP3 6ET",
    "wof:placetype": "postalcode"
  },
  "geometry": {"coordinates":[-2.122337,51.098149],"type":"Point"}
}
