{
  "type": "Feature",
  "properties": {
    "date:inception_lower": "2022-07-01",
    "date:inception_upper": "2022-07-01",
    "iso:country": "GB",
    "wof:name": "LA12 2AW",
    "wof:placetype": "postalcode"
  },
  "geometry": {"coordinates":[-3.094536,54.194813],"type":"Point"}
}
