{
  "type": "Feature",
  "properties": {
    "iso:country":"GB",
    "wof:name":"ME1 2HS",
    "wof:placetype":"postalcode"
},
  "geometry": {"coordinates":[0.50406542296142,51.37805433579531],"type":"Point"}
}