{
  "type": "Feature",
  "properties": {
    "iso:country":"GB",
    "wof:name":"ST5 1JQ",
    "wof:placetype":"postalcode"
},
  "geometry": {"coordinates":[-2.21905650460067,53.01514162369974],"type":"Point"}
}