{
  "type": "Feature",
  "properties": {
    "iso:country": "GB",
    "wof:name": "HP11 1TR",
    "wof:placetype": "postalcode"
  },
  "geometry": {"coordinates":[-0.771907,51.614623],"type":"Point"}
}
