{
  "type": "Feature",
  "properties": {
    "date:inception_lower": "1980-01-01",
    "date:inception_upper": "1980-01-01",
    "iso:country": "GB",
    "wof:name": "RG10 9QS",
    "wof:placetype": "postalcode"
  },
  "geometry": {"coordinates":[-0.882181,51.479025],"type":"Point"}
}
