{
  "type": "Feature",
  "properties": {
    "iso:country":"GB",
    "wof:name":"KA26 0JB",
    "wof:placetype":"postalcode"
},
  "geometry": {"coordinates":[-4.88722609647192,55.17851323263224],"type":"Point"}
}