{
  "type": "Feature",
  "properties": {
    "iso:country":"GB",
    "wof:name":"BH19 3HY",
    "wof:placetype":"postalcode"
},
  "geometry": {"coordinates":[-2.00497846566052,50.60936499725492],"type":"Point"}
}