{
  "type": "Feature",
  "properties": {
    "iso:country":"GB",
    "wof:name":"SY10 9LH",
    "wof:placetype":"postalcode"
},
  "geometry": {"coordinates":[-3.21252038920672,52.8052431199297],"type":"Point"}
}