{
  "type": "Feature",
  "properties": {
    "iso:country": "GB",
    "wof:name": "SY10 9LH",
    "wof:placetype": "postalcode"
  },
  "geometry": {"coordinates":[-3.214299,52.804673],"type":"Point"}
}
