{
  "type": "Feature",
  "properties": {
    "date:inception_lower":"1986-09-01",
    "date:inception_upper":"1986-09-30",
    "iso:country":"GB",
    "wof:name":"KY15 5NR",
    "wof:placetype":"postalcode"
},
  "geometry": {"coordinates":[-2.968949,56.290637],"type":"Point"}
}