{
  "type": "Feature",
  "properties": {
    "iso:country": "GB",
    "wof:name": "KY15 5NR",
    "wof:placetype": "postalcode"
  },
  "geometry": {"coordinates":[-2.968949,56.290637],"type":"Point"}
}
