{
  "type": "Feature",
  "properties": {
    "iso:country":"GB",
    "wof:name":"M30 7DB",
    "wof:placetype":"postalcode"
},
  "geometry": {"coordinates":[-2.37135331072165,53.47591800131349],"type":"Point"}
}