{
  "type": "Feature",
  "properties": {
    "date:inception_lower": "1980-01-01",
    "date:inception_upper": "1980-01-01",
    "iso:country": "GB",
    "wof:name": "M30 7DB",
    "wof:placetype": "postalcode"
  },
  "geometry": {"coordinates":[-2.371353,53.475918],"type":"Point"}
}
