{
  "type": "Feature",
  "properties": {
    "date:inception_lower": "1980-01-01",
    "date:inception_upper": "1980-01-01",
    "iso:country": "GB",
    "wof:name": "CO10 0EP",
    "wof:placetype": "postalcode"
  },
  "geometry": {"coordinates":[0.752738,52.028171],"type":"Point"}
}
