{
  "type": "Feature",
  "properties": {
    "iso:country":"GB",
    "wof:name":"CO10 0EP",
    "wof:placetype":"postalcode"
},
  "geometry": {"coordinates":[0.75269329217832,52.02818538951068],"type":"Point"}
}