{
  "type": "Feature",
  "properties": {
    "date:inception_lower":"2012-12-01",
    "date:inception_upper":"2012-12-31",
    "iso:country":"GB",
    "wof:name":"PE38 0LE",
    "wof:placetype":"postalcode"
},
  "geometry": {"coordinates":[0.366364,52.567182],"type":"Point"}
}