{
  "type": "Feature",
  "properties": {
    "iso:country": "GB",
    "wof:name": "PE38 0LE",
    "wof:placetype": "postalcode"
  },
  "geometry": {"coordinates":[0.366364,52.567182],"type":"Point"}
}
