{
  "type": "Feature",
  "properties": {
    "iso:country":"GB",
    "wof:name":"PE38 0LE",
    "wof:placetype":"postalcode"
},
  "geometry": {"coordinates":[0.36636383545377,52.56718221346723],"type":"Point"}
}