{
  "type": "Feature",
  "properties": {
    "iso:country": "GB",
    "wof:name": "RG8 9PA",
    "wof:placetype": "postalcode"
  },
  "geometry": {"coordinates":[-1.129136,51.502238],"type":"Point"}
}
