{
  "type": "Feature",
  "properties": {
    "iso:country":"GB",
    "wof:name":"RH20 2HA",
    "wof:placetype":"postalcode"
},
  "geometry": {"coordinates":[-0.47328457347119,50.9521951519252],"type":"Point"}
}