{
  "type": "Feature",
  "properties": {
    "iso:country":"GB",
    "wof:name":"TD14 5QJ",
    "wof:placetype":"postalcode"
},
  "geometry": {"coordinates":[-2.12229137616589,55.84171636229242],"type":"Point"}
}