{
  "type": "Feature",
  "properties": {
    "date:inception_lower": "1980-01-01",
    "date:inception_upper": "1980-01-01",
    "iso:country": "GB",
    "wof:name": "TD14 5QJ",
    "wof:placetype": "postalcode"
  },
  "geometry": {"coordinates":[-2.122291,55.841716],"type":"Point"}
}
