{
  "type": "Feature",
  "properties": {
    "iso:country": "GB",
    "wof:name": "N19 5HA",
    "wof:placetype": "postalcode"
  },
  "geometry": {"coordinates":[-0.134161,51.555116],"type":"Point"}
}
