{
  "type": "Feature",
  "properties": {
    "iso:country": "GB",
    "wof:name": "SA9 2JS",
    "wof:placetype": "postalcode"
  },
  "geometry": {"coordinates":[-3.778975,51.768071],"type":"Point"}
}
