{
  "type": "Feature",
  "properties": {
    "date:inception_lower":"1980-01-01",
    "date:inception_upper":"1980-01-31",
    "iso:country":"GB",
    "wof:name":"SA9 2JS",
    "wof:placetype":"postalcode"
},
  "geometry": {"coordinates":[-3.778975,51.768071],"type":"Point"}
}