{
  "type": "Feature",
  "properties": {
    "iso:country":"GB",
    "wof:name":"G81 1HS",
    "wof:placetype":"postalcode"
},
  "geometry": {"coordinates":[-4.41017909992056,55.90207784709145],"type":"Point"}
}