{
  "type": "Feature",
  "properties": {
    "date:inception_lower":"1992-10-01",
    "date:inception_upper":"1992-10-31",
    "iso:country":"GB",
    "wof:name":"G81 1HS",
    "wof:placetype":"postalcode"
},
  "geometry": {"coordinates":[-4.410266,55.902178],"type":"Point"}
}