{
  "type": "Feature",
  "properties": {
    "iso:country":"GB",
    "wof:name":"CA25 5AY",
    "wof:placetype":"postalcode"
},
  "geometry": {"coordinates":[-3.51950031583708,54.51892413732408],"type":"Point"}
}