{
  "type": "Feature",
  "properties": {
    "date:inception_lower": "1980-01-01",
    "date:inception_upper": "1980-01-01",
    "iso:country": "GB",
    "wof:name": "CA25 5AY",
    "wof:placetype": "postalcode"
  },
  "geometry": {"coordinates":[-3.5195,54.518924],"type":"Point"}
}
