{
  "type": "Feature",
  "properties": {
    "iso:country":"GB",
    "wof:name":"FK16 6EA",
    "wof:placetype":"postalcode"
},
  "geometry": {"coordinates":[-4.04654731169239,56.18567788116024],"type":"Point"}
}