{
  "type": "Feature",
  "properties": {
    "date:inception_lower": "1980-01-01",
    "date:inception_upper": "1980-01-01",
    "iso:country": "GB",
    "wof:name": "DD1 1LZ",
    "wof:placetype": "postalcode"
  },
  "geometry": {"coordinates":[-2.975574,56.462218],"type":"Point"}
}
