{
  "type": "Feature",
  "properties": {
    "date:inception_lower": "2012-05-01",
    "date:inception_upper": "2012-05-01",
    "iso:country": "GB",
    "wof:name": "LL29 8DU",
    "wof:placetype": "postalcode"
  },
  "geometry": {"coordinates":[-3.722123,53.29431],"type":"Point"}
}
