{
  "type": "Feature",
  "properties": {
    "iso:country":"GB",
    "wof:name":"GL56 0DX",
    "wof:placetype":"postalcode"
},
  "geometry": {"coordinates":[-1.70138727210531,51.98540357668339],"type":"Point"}
}