{
  "type": "Feature",
  "properties": {
    "date:inception_lower": "1980-01-01",
    "date:inception_upper": "1980-01-01",
    "iso:country": "GB",
    "wof:name": "GL56 0DX",
    "wof:placetype": "postalcode"
  },
  "geometry": {"coordinates":[-1.701387,51.985404],"type":"Point"}
}
