{
  "type": "Feature",
  "properties": {
    "iso:country": "GB",
    "wof:name": "GL56 0DX",
    "wof:placetype": "postalcode"
  },
  "geometry": {"coordinates":[-1.701387,51.985404],"type":"Point"}
}
