{
  "type": "Feature",
  "properties": {
    "iso:country":"GB",
    "wof:name":"TQ2 5ES",
    "wof:placetype":"postalcode"
},
  "geometry": {"coordinates":[-3.52697668290406,50.4638385461291],"type":"Point"}
}