{
  "type": "Feature",
  "properties": {
    "iso:country":"GB",
    "wof:name":"W1J 5JN",
    "wof:placetype":"postalcode"
},
  "geometry": {"coordinates":[-0.14853591775774,51.50696396768571],"type":"Point"}
}