{
  "type": "Feature",
  "properties": {
    "iso:country":"GB",
    "wof:name":"BD17 5DY",
    "wof:placetype":"postalcode"
},
  "geometry": {"coordinates":[-1.79049537484618,53.84768614366346],"type":"Point"}
}