{
  "type": "Feature",
  "properties": {
    "date:inception_lower": "2017-07-01",
    "date:inception_upper": "2017-07-01",
    "iso:country": "GB",
    "wof:name": "HU9 1NR",
    "wof:placetype": "postalcode"
  },
  "geometry": {"coordinates":[-0.316721,53.751416],"type":"Point"}
}
