{
  "type": "Feature",
  "properties": {
    "date:inception_lower": "2017-04-01",
    "date:inception_upper": "2017-04-01",
    "iso:country": "GB",
    "wof:name": "PO6 2NF",
    "wof:placetype": "postalcode"
  },
  "geometry": {"coordinates":[-1.050747,50.838776],"type":"Point"}
}
