{
  "type": "Feature",
  "properties": {
    "iso:country":"GB",
    "wof:name":"LL30 2LF",
    "wof:placetype":"postalcode"
},
  "geometry": {"coordinates":[-3.82794805824094,53.3244513863464],"type":"Point"}
}