{
  "type": "Feature",
  "properties": {
    "iso:country":"GB",
    "wof:name":"NW10 4EA",
    "wof:placetype":"postalcode"
},
  "geometry": {"coordinates":[-0.24692436122353,51.53856432974037],"type":"Point"}
}