{
  "type": "Feature",
  "properties": {
    "iso:country":"GB",
    "wof:name":"BL5 3PR",
    "wof:placetype":"postalcode"
},
  "geometry": {"coordinates":[-2.52542155936918,53.56088305689795],"type":"Point"}
}