{
  "type": "Feature",
  "properties": {
    "iso:country": "GB",
    "wof:name": "LS14 6AL",
    "wof:placetype": "postalcode"
  },
  "geometry": {"coordinates":[-1.47704,53.8041],"type":"Point"}
}
