{
  "type": "Feature",
  "properties": {
    "iso:country":"GB",
    "wof:name":"SR3 3ED",
    "wof:placetype":"postalcode"
},
  "geometry": {"coordinates":[-1.42604821635823,54.87368650159168],"type":"Point"}
}