{
  "type": "Feature",
  "properties": {
    "date:inception_lower": "1980-01-01",
    "date:inception_upper": "1980-01-01",
    "iso:country": "GB",
    "wof:name": "SR3 3ED",
    "wof:placetype": "postalcode"
  },
  "geometry": {"coordinates":[-1.426048,54.873686],"type":"Point"}
}
