{
  "type": "Feature",
  "properties": {
    "iso:country":"GB",
    "wof:name":"LE13 0JH",
    "wof:placetype":"postalcode"
},
  "geometry": {"coordinates":[-0.9031517593586,52.76975776074852],"type":"Point"}
}