{
  "type": "Feature",
  "properties": {
    "iso:country": "GB",
    "wof:name": "HA3 6HW",
    "wof:placetype": "postalcode"
  },
  "geometry": {"coordinates":[-0.341794,51.605919],"type":"Point"}
}
