{
  "type": "Feature",
  "properties": {
    "iso:country":"GB",
    "wof:name":"HA3 6HW",
    "wof:placetype":"postalcode"
},
  "geometry": {"coordinates":[-0.34179426521378,51.60591936655369],"type":"Point"}
}