{
  "type": "Feature",
  "properties": {
    "iso:country":"GB",
    "wof:name":"IG7 6DP",
    "wof:placetype":"postalcode"
},
  "geometry": {"coordinates":[0.08000237975924,51.6288062892008],"type":"Point"}
}