{
  "type": "Feature",
  "properties": {
    "iso:country":"GB",
    "wof:name":"W1H 2LN",
    "wof:placetype":"postalcode"
},
  "geometry": {"coordinates":[-0.15991767447414,51.5181049304073],"type":"Point"}
}