{
  "type": "Feature",
  "properties": {
    "iso:country":"GB",
    "wof:name":"MK2 3HE",
    "wof:placetype":"postalcode"
},
  "geometry": {"coordinates":[-0.72957380744529,51.98205207885862],"type":"Point"}
}