{
  "type": "Feature",
  "properties": {
    "date:inception_lower": "1980-01-01",
    "date:inception_upper": "1980-01-01",
    "iso:country": "GB",
    "wof:name": "MK2 3HE",
    "wof:placetype": "postalcode"
  },
  "geometry": {"coordinates":[-0.729574,51.982052],"type":"Point"}
}
