{
  "type": "Feature",
  "properties": {
    "date:inception_lower": "1980-01-01",
    "date:inception_upper": "1980-01-01",
    "iso:country": "GB",
    "wof:name": "TN18 4AQ",
    "wof:placetype": "postalcode"
  },
  "geometry": {"coordinates":[0.508295,51.048073],"type":"Point"}
}
