{
  "type": "Feature",
  "properties": {
    "iso:country":"GB",
    "wof:name":"LU2 7AJ",
    "wof:placetype":"postalcode"
},
  "geometry": {"coordinates":[-0.42271242164206,51.9201217506678],"type":"Point"}
}