{
  "type": "Feature",
  "properties": {
    "iso:country": "GB",
    "wof:name": "LU2 7AJ",
    "wof:placetype": "postalcode"
  },
  "geometry": {"coordinates":[-0.422696,51.920166],"type":"Point"}
}
