{
  "type": "Feature",
  "properties": {
    "iso:country": "GB",
    "wof:name": "LS16 8NR",
    "wof:placetype": "postalcode"
  },
  "geometry": {"coordinates":[-1.582254,53.848023],"type":"Point"}
}
