{
  "type": "Feature",
  "properties": {
    "iso:country":"GB",
    "wof:name":"LS16 8NR",
    "wof:placetype":"postalcode"
},
  "geometry": {"coordinates":[-1.5822544319737,53.84802317165318],"type":"Point"}
}