{
  "type": "Feature",
  "properties": {
    "iso:country":"GB",
    "wof:name":"BL1 4LA",
    "wof:placetype":"postalcode"
},
  "geometry": {"coordinates":[-2.45332984719348,53.58450299225078],"type":"Point"}
}