{
  "type": "Feature",
  "properties": {
    "iso:country": "GB",
    "wof:name": "BL1 4LA",
    "wof:placetype": "postalcode"
  },
  "geometry": {"coordinates":[-2.45333,53.584503],"type":"Point"}
}
