{
  "type": "Feature",
  "properties": {
    "iso:country":"GB",
    "wof:name":"SO32 1DP",
    "wof:placetype":"postalcode"
},
  "geometry": {"coordinates":[-1.21628738450408,50.95216030099446],"type":"Point"}
}