{
  "type": "Feature",
  "properties": {
    "iso:country":"GB",
    "wof:name":"WC2H 7DE",
    "wof:placetype":"postalcode"
},
  "geometry": {"coordinates":[-0.12994806064075,51.5101042040754],"type":"Point"}
}