{
  "type": "Feature",
  "properties": {
    "date:inception_lower": "2009-05-01",
    "date:inception_upper": "2009-05-01",
    "iso:country": "GB",
    "wof:name": "WC2H 7DE",
    "wof:placetype": "postalcode"
  },
  "geometry": {"coordinates":[-0.129948,51.510104],"type":"Point"}
}
