{
  "type": "Feature",
  "properties": {
    "iso:country":"GB",
    "wof:name":"CM14 5AE",
    "wof:placetype":"postalcode"
},
  "geometry": {"coordinates":[0.31130072785182,51.61076546186143],"type":"Point"}
}