{
  "type": "Feature",
  "properties": {
    "date:inception_lower": "1990-07-01",
    "date:inception_upper": "1990-07-01",
    "iso:country": "GB",
    "wof:name": "EX2 8PF",
    "wof:placetype": "postalcode"
  },
  "geometry": {"coordinates":[-3.524642,50.697482],"type":"Point"}
}
