{
  "type": "Feature",
  "properties": {
    "iso:country": "GB",
    "wof:name": "TN5 7BN",
    "wof:placetype": "postalcode"
  },
  "geometry": {"coordinates":[0.410111,51.048269],"type":"Point"}
}
