{
  "type": "Feature",
  "properties": {
    "iso:country":"GB",
    "wof:name":"WD19 6JT",
    "wof:placetype":"postalcode"
},
  "geometry": {"coordinates":[-0.39316542208952,51.62419532858675],"type":"Point"}
}