{
  "type": "Feature",
  "properties": {
    "iso:country":"GB",
    "wof:name":"E11 4ET",
    "wof:placetype":"postalcode"
},
  "geometry": {"coordinates":[-0.00221755149947,51.55597373095203],"type":"Point"}
}