{
  "type": "Feature",
  "properties": {
    "iso:country": "GB",
    "wof:name": "B98 9AY",
    "wof:placetype": "postalcode"
  },
  "geometry": {"coordinates":[-1.883664,52.312384],"type":"Point"}
}
