{
  "type": "Feature",
  "properties": {
    "iso:country":"GB",
    "wof:name":"B98 9AY",
    "wof:placetype":"postalcode"
},
  "geometry": {"coordinates":[-1.88366413853579,52.31238396278466],"type":"Point"}
}