{
  "type": "Feature",
  "properties": {
    "date:inception_lower": "1980-01-01",
    "date:inception_upper": "1980-01-01",
    "iso:country": "GB",
    "wof:name": "IV12 4TS",
    "wof:placetype": "postalcode"
  },
  "geometry": {"coordinates":[-3.880394,57.582797],"type":"Point"}
}
