{
  "type": "Feature",
  "properties": {
    "iso:country":"GB",
    "wof:name":"OX33 1RR",
    "wof:placetype":"postalcode"
},
  "geometry": {"coordinates":[-1.17191744558295,51.74001287995688],"type":"Point"}
}