{
  "type": "Feature",
  "properties": {
    "iso:country": "GB",
    "wof:name": "TQ9 7PN",
    "wof:placetype": "postalcode"
  },
  "geometry": {"coordinates":[-3.693963,50.421765],"type":"Point"}
}
