{
  "type": "Feature",
  "properties": {
    "iso:country":"GB",
    "wof:name":"PA3 4DH",
    "wof:placetype":"postalcode"
},
  "geometry": {"coordinates":[-4.42156023510579,55.85494695775037],"type":"Point"}
}