{
  "type": "Feature",
  "properties": {
    "iso:country":"GB",
    "wof:name":"ME12 1YB",
    "wof:placetype":"postalcode"
},
  "geometry": {"coordinates":[0.76344895884957,51.43524137646251],"type":"Point"}
}