{
  "type": "Feature",
  "properties": {
    "iso:country": "GB",
    "wof:name": "ME12 1YB",
    "wof:placetype": "postalcode"
  },
  "geometry": {"coordinates":[0.763449,51.435241],"type":"Point"}
}
