{
  "type": "Feature",
  "properties": {
    "date:inception_lower":"2000-12-01",
    "date:inception_upper":"2000-12-31",
    "iso:country":"GB",
    "wof:name":"WC2H 8DW",
    "wof:placetype":"postalcode"
},
  "geometry": {"coordinates":[-0.125805,51.516585],"type":"Point"}
}