{
  "type": "Feature",
  "properties": {
    "iso:country":"GB",
    "wof:name":"WC2H 8DW",
    "wof:placetype":"postalcode"
},
  "geometry": {"coordinates":[-0.12580551763097,51.51658463698053],"type":"Point"}
}