{
  "type": "Feature",
  "properties": {
    "iso:country": "GB",
    "wof:name": "GU34 2BQ",
    "wof:placetype": "postalcode"
  },
  "geometry": {"coordinates":[-0.986239,51.152199],"type":"Point"}
}
