{
  "type": "Feature",
  "properties": {
    "iso:country":"GB",
    "wof:name":"GU34 2BQ",
    "wof:placetype":"postalcode"
},
  "geometry": {"coordinates":[-0.98623907140395,51.15219908677922],"type":"Point"}
}