{
  "type": "Feature",
  "properties": {
    "date:inception_lower": "1990-07-01",
    "date:inception_upper": "1990-07-01",
    "iso:country": "GB",
    "wof:name": "BN41 1GW",
    "wof:placetype": "postalcode"
  },
  "geometry": {"coordinates":[-0.213087,50.834667],"type":"Point"}
}
