{
  "type": "Feature",
  "properties": {
    "iso:country":"GB",
    "wof:name":"BN41 1GW",
    "wof:placetype":"postalcode"
},
  "geometry": {"coordinates":[-0.21308695207022,50.83466658680268],"type":"Point"}
}