{
  "type": "Feature",
  "properties": {
    "date:inception_lower": "2023-06-01",
    "date:inception_upper": "2023-06-01",
    "iso:country": "GB",
    "wof:name": "M38 9AU",
    "wof:placetype": "postalcode"
  },
  "geometry": {"coordinates":[-2.422401,53.535439],"type":"Point"}
}
