{
  "type": "Feature",
  "properties": {
    "iso:country":"GB",
    "wof:name":"HA7 3FJ",
    "wof:placetype":"postalcode"
},
  "geometry": {"coordinates":[-0.32154862154875,51.61529821873689],"type":"Point"}
}