{
  "type": "Feature",
  "properties": {
    "iso:country":"GB",
    "wof:name":"LA6 3EP",
    "wof:placetype":"postalcode"
},
  "geometry": {"coordinates":[-2.46979536497025,54.15425683045321],"type":"Point"}
}