{
  "type": "Feature",
  "properties": {
    "iso:country": "GB",
    "wof:name": "LA6 3EP",
    "wof:placetype": "postalcode"
  },
  "geometry": {"coordinates":[-2.469798,54.154268],"type":"Point"}
}
