{
  "type": "Feature",
  "properties": {
    "iso:country":"GB",
    "wof:name":"ST4 4PE",
    "wof:placetype":"postalcode"
},
  "geometry": {"coordinates":[-2.16799846736534,52.99819933690807],"type":"Point"}
}