{
  "type": "Feature",
  "properties": {
    "iso:country":"GB",
    "wof:name":"LE8 6JZ",
    "wof:placetype":"postalcode"
},
  "geometry": {"coordinates":[-1.18103631369111,52.57209230509781],"type":"Point"}
}