{
  "type": "Feature",
  "properties": {
    "iso:country": "GB",
    "wof:name": "RH13 0JZ",
    "wof:placetype": "postalcode"
  },
  "geometry": {"coordinates":[-0.351167,51.046468],"type":"Point"}
}
