{
  "type": "Feature",
  "properties": {
    "iso:country":"GB",
    "wof:name":"RH13 0JZ",
    "wof:placetype":"postalcode"
},
  "geometry": {"coordinates":[-0.35123506887487,51.0465002806261],"type":"Point"}
}