{
  "type": "Feature",
  "properties": {
    "iso:country": "GB",
    "wof:name": "HP13 7DJ",
    "wof:placetype": "postalcode"
  },
  "geometry": {"coordinates":[-0.713104,51.617666],"type":"Point"}
}
