{
  "type": "Feature",
  "properties": {
    "date:inception_lower": "2019-01-01",
    "date:inception_upper": "2019-01-01",
    "iso:country": "GB",
    "wof:name": "RG42 5AR",
    "wof:placetype": "postalcode"
  },
  "geometry": {"coordinates":[-0.758918,51.430154],"type":"Point"}
}
