{
  "type": "Feature",
  "properties": {
    "iso:country": "GB",
    "wof:name": "EX2 9TG",
    "wof:placetype": "postalcode"
  },
  "geometry": {"coordinates":[-3.569502,50.702222],"type":"Point"}
}
