{
  "type": "Feature",
  "properties": {
    "iso:country":"GB",
    "wof:name":"EX2 9TG",
    "wof:placetype":"postalcode"
},
  "geometry": {"coordinates":[-3.57200555961658,50.70211617669047],"type":"Point"}
}