{
  "type": "Feature",
  "properties": {
    "iso:country":"GB",
    "wof:name":"RH1 3PR",
    "wof:placetype":"postalcode"
},
  "geometry": {"coordinates":[-0.13808495752274,51.25847438048729],"type":"Point"}
}