{
  "type": "Feature",
  "properties": {
    "iso:country": "GB",
    "wof:name": "RH1 3PR",
    "wof:placetype": "postalcode"
  },
  "geometry": {"coordinates":[-0.138085,51.258474],"type":"Point"}
}
