{
  "type": "Feature",
  "properties": {
    "iso:country":"GB",
    "wof:name":"WF6 1EX",
    "wof:placetype":"postalcode"
},
  "geometry": {"coordinates":[-1.41774120185186,53.69797326019874],"type":"Point"}
}