{
  "type": "Feature",
  "properties": {
    "iso:country":"GB",
    "wof:name":"DE45 1BX",
    "wof:placetype":"postalcode"
},
  "geometry": {"coordinates":[-1.67560961439579,53.21419797047745],"type":"Point"}
}