{
  "type": "Feature",
  "properties": {
    "iso:country": "GB",
    "wof:name": "SS9 3JP",
    "wof:placetype": "postalcode"
  },
  "geometry": {"coordinates":[0.663113,51.547701],"type":"Point"}
}
