{
  "type": "Feature",
  "properties": {
    "date:inception_lower": "1996-06-01",
    "date:inception_upper": "1996-06-01",
    "iso:country": "GB",
    "wof:name": "CH5 3QZ",
    "wof:placetype": "postalcode"
  },
  "geometry": {"coordinates":[-2.994545,53.176802],"type":"Point"}
}
