{
  "type": "Feature",
  "properties": {
    "iso:country": "GB",
    "wof:name": "CH5 3QZ",
    "wof:placetype": "postalcode"
  },
  "geometry": {"coordinates":[-2.994095,53.177426],"type":"Point"}
}
