{
  "type": "Feature",
  "properties": {
    "iso:country":"GB",
    "wof:name":"CH5 3QZ",
    "wof:placetype":"postalcode"
},
  "geometry": {"coordinates":[-2.99454415366639,53.17678591306579],"type":"Point"}
}