{
  "type": "Feature",
  "properties": {
    "iso:country":"GB",
    "wof:name":"NN2 8UN",
    "wof:placetype":"postalcode"
},
  "geometry": {"coordinates":[-0.91832045313541,52.27079992638142],"type":"Point"}
}