{
  "type": "Feature",
  "properties": {
    "date:inception_lower": "1980-01-01",
    "date:inception_upper": "1980-01-01",
    "iso:country": "GB",
    "wof:name": "DN3 2BZ",
    "wof:placetype": "postalcode"
  },
  "geometry": {"coordinates":[-1.061114,53.541225],"type":"Point"}
}
