{
  "type": "Feature",
  "properties": {
    "iso:country":"GB",
    "wof:name":"DN3 2BZ",
    "wof:placetype":"postalcode"
},
  "geometry": {"coordinates":[-1.06103904947897,53.53964940962575],"type":"Point"}
}