{
  "type": "Feature",
  "properties": {
    "iso:country": "GB",
    "wof:name": "DN3 2BZ",
    "wof:placetype": "postalcode"
  },
  "geometry": {"coordinates":[-1.061039,53.539649],"type":"Point"}
}
