{
  "type": "Feature",
  "properties": {
    "iso:country":"GB",
    "wof:name":"EH19 3EQ",
    "wof:placetype":"postalcode"
},
  "geometry": {"coordinates":[-3.10860800520836,55.87134812339976],"type":"Point"}
}