{
  "type": "Feature",
  "properties": {
    "iso:country":"GB",
    "wof:name":"W9 1BY",
    "wof:placetype":"postalcode"
},
  "geometry": {"coordinates":[-0.1784390281673,51.52460780944011],"type":"Point"}
}