{
  "type": "Feature",
  "properties": {
    "iso:country":"GB",
    "wof:name":"B31 3NN",
    "wof:placetype":"postalcode"
},
  "geometry": {"coordinates":[-1.95889801507878,52.39253619623369],"type":"Point"}
}