{
  "type": "Feature",
  "properties": {
    "iso:country":"GB",
    "wof:name":"CT16 3EA",
    "wof:placetype":"postalcode"
},
  "geometry": {"coordinates":[1.25877622293759,51.1491874344995],"type":"Point"}
}