{
  "type": "Feature",
  "properties": {
    "date:inception_lower": "1994-12-01",
    "date:inception_upper": "1994-12-01",
    "iso:country": "GB",
    "wof:name": "SO53 5QE",
    "wof:placetype": "postalcode"
  },
  "geometry": {"coordinates":[-1.391088,51.002032],"type":"Point"}
}
