{
  "type": "Feature",
  "properties": {
    "iso:country":"GB",
    "wof:name":"SO53 5QE",
    "wof:placetype":"postalcode"
},
  "geometry": {"coordinates":[-1.39109870086162,51.0020396998887],"type":"Point"}
}