{
  "type": "Feature",
  "properties": {
    "date:inception_lower": "1981-09-01",
    "date:inception_upper": "1981-09-01",
    "iso:country": "GB",
    "wof:name": "WV9 5LS",
    "wof:placetype": "postalcode"
  },
  "geometry": {"coordinates":[-2.143116,52.623938],"type":"Point"}
}
