{
  "type": "Feature",
  "properties": {
    "date:inception_lower": "2008-06-01",
    "date:inception_upper": "2008-06-01",
    "iso:country": "GB",
    "wof:name": "NN14 4FR",
    "wof:placetype": "postalcode"
  },
  "geometry": {"coordinates":[-0.520428,52.393255],"type":"Point"}
}
