{
  "type": "Feature",
  "properties": {
    "iso:country":"GB",
    "wof:name":"NN14 4FR",
    "wof:placetype":"postalcode"
},
  "geometry": {"coordinates":[-0.52233976411273,52.39325417363417],"type":"Point"}
}