{
  "type": "Feature",
  "properties": {
    "iso:country":"GB",
    "wof:name":"WR3 8QX",
    "wof:placetype":"postalcode"
},
  "geometry": {"coordinates":[-2.20557168706489,52.20672440968863],"type":"Point"}
}