{
  "type": "Feature",
  "properties": {
    "date:inception_lower": "2000-12-01",
    "date:inception_upper": "2000-12-01",
    "iso:country": "GB",
    "wof:name": "WR3 8QX",
    "wof:placetype": "postalcode"
  },
  "geometry": {"coordinates":[-2.205572,52.206724],"type":"Point"}
}
