{
  "type": "Feature",
  "properties": {
    "iso:country": "GB",
    "wof:name": "BS3 2UN",
    "wof:placetype": "postalcode"
  },
  "geometry": {"coordinates":[-2.633072,51.429873],"type":"Point"}
}
