{
  "type": "Feature",
  "properties": {
    "date:inception_lower": "1980-01-01",
    "date:inception_upper": "1980-01-01",
    "iso:country": "GB",
    "wof:name": "BS3 2UN",
    "wof:placetype": "postalcode"
  },
  "geometry": {"coordinates":[-2.633072,51.429873],"type":"Point"}
}
