{
  "type": "Feature",
  "properties": {
    "date:inception_lower":"1980-01-01",
    "date:inception_upper":"1980-01-31",
    "iso:country":"GB",
    "wof:name":"LA14 1NG",
    "wof:placetype":"postalcode"
},
  "geometry": {"coordinates":[-3.232673,54.116037],"type":"Point"}
}