{
  "type": "Feature",
  "properties": {
    "iso:country": "GB",
    "wof:name": "LA14 1NG",
    "wof:placetype": "postalcode"
  },
  "geometry": {"coordinates":[-3.232673,54.116037],"type":"Point"}
}
