{
  "type": "Feature",
  "properties": {
    "iso:country": "GB",
    "wof:name": "DE13 0PW",
    "wof:placetype": "postalcode"
  },
  "geometry": {"coordinates":[-1.652904,52.822457],"type":"Point"}
}
