{
  "type": "Feature",
  "properties": {
    "iso:country":"GB",
    "wof:name":"E10 7FG",
    "wof:placetype":"postalcode"
},
  "geometry": {"coordinates":[-0.01292386779791,51.57213538091695],"type":"Point"}
}