{
  "type": "Feature",
  "properties": {
    "date:inception_lower":"2010-08-01",
    "date:inception_upper":"2010-08-31",
    "iso:country":"GB",
    "wof:name":"E10 7FG",
    "wof:placetype":"postalcode"
},
  "geometry": {"coordinates":[-0.012924,51.572135],"type":"Point"}
}