{
  "type": "Feature",
  "properties": {
    "iso:country":"GB",
    "wof:name":"ST14 7BP",
    "wof:placetype":"postalcode"
},
  "geometry": {"coordinates":[-1.86719559741001,52.90287760267869],"type":"Point"}
}