{
  "type": "Feature",
  "properties": {
    "iso:country":"GB",
    "wof:name":"TN28 8PU",
    "wof:placetype":"postalcode"
},
  "geometry": {"coordinates":[0.96017858164092,50.98430874088169],"type":"Point"}
}