{
  "type": "Feature",
  "properties": {
    "iso:country":"GB",
    "wof:name":"GU31 5LT",
    "wof:placetype":"postalcode"
},
  "geometry": {"coordinates":[-0.86844043614715,50.96762683390725],"type":"Point"}
}