{
  "type": "Feature",
  "properties": {
    "iso:country": "GB",
    "wof:name": "GU31 5LT",
    "wof:placetype": "postalcode"
  },
  "geometry": {"coordinates":[-0.86844,50.967627],"type":"Point"}
}
