{
  "type": "Feature",
  "properties": {
    "date:inception_lower":"1980-01-01",
    "date:inception_upper":"1980-01-31",
    "iso:country":"GB",
    "wof:name":"GU31 5LT",
    "wof:placetype":"postalcode"
},
  "geometry": {"coordinates":[-0.86844,50.967627],"type":"Point"}
}