{
  "type": "Feature",
  "properties": {
    "date:inception_lower": "1980-01-01",
    "date:inception_upper": "1980-01-01",
    "iso:country": "GB",
    "wof:name": "OX7 3JT",
    "wof:placetype": "postalcode"
  },
  "geometry": {"coordinates":[-1.49391,51.89404],"type":"Point"}
}
