{
  "type": "Feature",
  "properties": {
    "iso:country": "GB",
    "wof:name": "OX7 3JT",
    "wof:placetype": "postalcode"
  },
  "geometry": {"coordinates":[-1.49391,51.89404],"type":"Point"}
}
