{
  "type": "Feature",
  "properties": {
    "iso:country":"GB",
    "wof:name":"OX7 3JT",
    "wof:placetype":"postalcode"
},
  "geometry": {"coordinates":[-1.49391043199698,51.89404033923716],"type":"Point"}
}