{
  "type": "Feature",
  "properties": {
    "iso:country":"GB",
    "wof:name":"SA15 4PP",
    "wof:placetype":"postalcode"
},
  "geometry": {"coordinates":[-4.19572160922686,51.70573489404151],"type":"Point"}
}