{
  "type": "Feature",
  "properties": {
    "iso:country":"GB",
    "wof:name":"LE12 8SP",
    "wof:placetype":"postalcode"
},
  "geometry": {"coordinates":[-1.23756724389339,52.72406650932295],"type":"Point"}
}