{
  "type": "Feature",
  "properties": {
    "date:inception_lower":"1980-01-01",
    "date:inception_upper":"1980-01-31",
    "iso:country":"GB",
    "wof:name":"LE12 8SP",
    "wof:placetype":"postalcode"
},
  "geometry": {"coordinates":[-1.237567,52.724067],"type":"Point"}
}