{
  "type": "Feature",
  "properties": {
    "date:inception_lower": "1980-01-01",
    "date:inception_upper": "1980-01-01",
    "iso:country": "GB",
    "wof:name": "UB7 9JL",
    "wof:placetype": "postalcode"
  },
  "geometry": {"coordinates":[-0.467922,51.502435],"type":"Point"}
}
