{
  "type": "Feature",
  "properties": {
    "iso:country":"GB",
    "wof:name":"UB7 9JL",
    "wof:placetype":"postalcode"
},
  "geometry": {"coordinates":[-0.46792172014712,51.50243456372105],"type":"Point"}
}