{
  "type": "Feature",
  "properties": {
    "iso:country":"GB",
    "wof:name":"LA1 5NY",
    "wof:placetype":"postalcode"
},
  "geometry": {"coordinates":[-2.81339625382683,54.04780754921678],"type":"Point"}
}