{
  "type": "Feature",
  "properties": {
    "date:inception_lower":"1980-01-01",
    "date:inception_upper":"1980-01-31",
    "iso:country":"GB",
    "wof:name":"LA1 5NY",
    "wof:placetype":"postalcode"
},
  "geometry": {"coordinates":[-2.813396,54.047808],"type":"Point"}
}