{
  "type": "Feature",
  "properties": {
    "iso:country":"GB",
    "wof:name":"L35 4NG",
    "wof:placetype":"postalcode"
},
  "geometry": {"coordinates":[-2.75937906187938,53.41489074692574],"type":"Point"}
}