{
  "type": "Feature",
  "properties": {
    "date:inception_lower": "1980-01-01",
    "date:inception_upper": "1980-01-01",
    "iso:country": "GB",
    "wof:name": "L35 4NG",
    "wof:placetype": "postalcode"
  },
  "geometry": {"coordinates":[-2.759379,53.414891],"type":"Point"}
}
