{
  "type": "Feature",
  "properties": {
    "iso:country": "GB",
    "wof:name": "BL0 9EG",
    "wof:placetype": "postalcode"
  },
  "geometry": {"coordinates":[-2.322516,53.64967],"type":"Point"}
}
