{
  "type": "Feature",
  "properties": {
    "iso:country":"GB",
    "wof:name":"BL0 9EG",
    "wof:placetype":"postalcode"
},
  "geometry": {"coordinates":[-2.32251642066063,53.64966990290724],"type":"Point"}
}