{
  "type": "Feature",
  "properties": {
    "iso:country":"GB",
    "wof:name":"G13 2JF",
    "wof:placetype":"postalcode"
},
  "geometry": {"coordinates":[-4.33871162099952,55.90227924270093],"type":"Point"}
}