{
  "type": "Feature",
  "properties": {
    "date:inception_lower": "2016-03-01",
    "date:inception_upper": "2016-03-01",
    "iso:country": "GB",
    "wof:name": "M19 3BP",
    "wof:placetype": "postalcode"
  },
  "geometry": {"coordinates":[-2.191819,53.445861],"type":"Point"}
}
