{
  "type": "Feature",
  "properties": {
    "date:inception_lower": "2011-11-01",
    "date:inception_upper": "2011-11-01",
    "iso:country": "GB",
    "wof:name": "W6 0JY",
    "wof:placetype": "postalcode"
  },
  "geometry": {"coordinates":[-0.231139,51.494184],"type":"Point"}
}
