{
  "type": "Feature",
  "properties": {
    "iso:country":"GB",
    "wof:name":"W6 0JY",
    "wof:placetype":"postalcode"
},
  "geometry": {"coordinates":[-0.23113878755072,51.49418368767469],"type":"Point"}
}