{
  "type": "Feature",
  "properties": {
    "iso:country":"GB",
    "wof:name":"N22 7BF",
    "wof:placetype":"postalcode"
},
  "geometry": {"coordinates":[-0.11139961127871,51.59685424436623],"type":"Point"}
}