{
  "type": "Feature",
  "properties": {
    "iso:country":"GB",
    "wof:name":"LE12 6PG",
    "wof:placetype":"postalcode"
},
  "geometry": {"coordinates":[-1.17726992321431,52.83128893902018],"type":"Point"}
}