{
  "type": "Feature",
  "properties": {
    "iso:country":"GB",
    "wof:name":"CH46 1PB",
    "wof:placetype":"postalcode"
},
  "geometry": {"coordinates":[-3.09800576269273,53.41297575546757],"type":"Point"}
}