{
  "type": "Feature",
  "properties": {
    "date:inception_lower": "1999-06-01",
    "date:inception_upper": "1999-06-01",
    "iso:country": "GB",
    "wof:name": "CH46 1PB",
    "wof:placetype": "postalcode"
  },
  "geometry": {"coordinates":[-3.098006,53.412976],"type":"Point"}
}
