{
  "type": "Feature",
  "properties": {
    "iso:country": "GB",
    "wof:name": "WA16 7LH",
    "wof:placetype": "postalcode"
  },
  "geometry": {"coordinates":[-2.297868,53.324612],"type":"Point"}
}
