{
  "type": "Feature",
  "properties": {
    "date:inception_lower": "1992-08-01",
    "date:inception_upper": "1992-08-01",
    "iso:country": "GB",
    "wof:name": "DE72 2GW",
    "wof:placetype": "postalcode"
  },
  "geometry": {"coordinates":[-1.366432,52.871859],"type":"Point"}
}
