{
  "type": "Feature",
  "properties": {
    "date:inception_lower":"2004-03-01",
    "date:inception_upper":"2004-03-31",
    "iso:country":"GB",
    "wof:name":"HP13 6AP",
    "wof:placetype":"postalcode"
},
  "geometry": {"coordinates":[-0.739241,51.627468],"type":"Point"}
}