{
  "type": "Feature",
  "properties": {
    "date:inception_lower": "1980-01-01",
    "date:inception_upper": "1980-01-01",
    "iso:country": "GB",
    "wof:name": "RH15 8JW",
    "wof:placetype": "postalcode"
  },
  "geometry": {"coordinates":[-0.130199,50.961577],"type":"Point"}
}
