{
  "type": "Feature",
  "properties": {
    "iso:country": "GB",
    "wof:name": "DE13 7HX",
    "wof:placetype": "postalcode"
  },
  "geometry": {"coordinates":[-1.817298,52.747806],"type":"Point"}
}
