{
  "type": "Feature",
  "properties": {
    "iso:country":"GB",
    "wof:name":"DE13 7HX",
    "wof:placetype":"postalcode"
},
  "geometry": {"coordinates":[-1.81729826181167,52.7478064965952],"type":"Point"}
}