{
  "type": "Feature",
  "properties": {
    "date:inception_lower": "1987-04-01",
    "date:inception_upper": "1987-04-01",
    "iso:country": "GB",
    "wof:name": "DE13 7HX",
    "wof:placetype": "postalcode"
  },
  "geometry": {"coordinates":[-1.817298,52.747806],"type":"Point"}
}
