{
  "type": "Feature",
  "properties": {
    "iso:country":"GB",
    "wof:name":"SA18 2HU",
    "wof:placetype":"postalcode"
},
  "geometry": {"coordinates":[-3.97329389019416,51.78456211040392],"type":"Point"}
}