{
  "type": "Feature",
  "properties": {
    "iso:country": "GB",
    "wof:name": "SA18 2HU",
    "wof:placetype": "postalcode"
  },
  "geometry": {"coordinates":[-3.973294,51.784562],"type":"Point"}
}
