{
  "type": "Feature",
  "properties": {
    "date:inception_lower": "2010-04-01",
    "date:inception_upper": "2010-04-01",
    "iso:country": "GB",
    "wof:name": "CF10 1XR",
    "wof:placetype": "postalcode"
  },
  "geometry": {"coordinates":[-3.181101,51.477337],"type":"Point"}
}
