{
  "type": "Feature",
  "properties": {
    "iso:country": "GB",
    "wof:name": "CF10 1XR",
    "wof:placetype": "postalcode"
  },
  "geometry": {"coordinates":[-3.18105,51.477364],"type":"Point"}
}
