{
  "type": "Feature",
  "properties": {
    "iso:country":"GB",
    "wof:name":"ST3 7WL",
    "wof:placetype":"postalcode"
},
  "geometry": {"coordinates":[-2.10399148139123,52.96828472680479],"type":"Point"}
}