{
  "type": "Feature",
  "properties": {
    "date:inception_lower": "2015-04-01",
    "date:inception_upper": "2015-04-01",
    "iso:country": "GB",
    "wof:name": "RM13 8FU",
    "wof:placetype": "postalcode"
  },
  "geometry": {"coordinates":[0.16946,51.529777],"type":"Point"}
}
