{
  "type": "Feature",
  "properties": {
    "iso:country":"GB",
    "wof:name":"RM13 8FU",
    "wof:placetype":"postalcode"
},
  "geometry": {"coordinates":[0.16946029729057,51.52977698770088],"type":"Point"}
}