{
  "type": "Feature",
  "properties": {
    "iso:country": "GB",
    "wof:name": "RM13 8FU",
    "wof:placetype": "postalcode"
  },
  "geometry": {"coordinates":[0.16946,51.529777],"type":"Point"}
}
