{
  "type": "Feature",
  "properties": {
    "iso:country":"GB",
    "wof:name":"E3 2GF",
    "wof:placetype":"postalcode"
},
  "geometry": {"coordinates":[-0.02386755709188,51.53108016956799],"type":"Point"}
}