{
  "type": "Feature",
  "properties": {
    "date:inception_lower": "2003-10-01",
    "date:inception_upper": "2003-10-01",
    "iso:country": "GB",
    "wof:name": "E3 2GF",
    "wof:placetype": "postalcode"
  },
  "geometry": {"coordinates":[-0.023546,51.530888],"type":"Point"}
}
