{
  "type": "Feature",
  "properties": {
    "iso:country": "GB",
    "wof:name": "E3 2GF",
    "wof:placetype": "postalcode"
  },
  "geometry": {"coordinates":[-0.02384,51.531082],"type":"Point"}
}
