{
  "type": "Feature",
  "properties": {
    "iso:country": "GB",
    "wof:name": "SY2 5BF",
    "wof:placetype": "postalcode"
  },
  "geometry": {"coordinates":[-2.740608,52.709009],"type":"Point"}
}
