{
  "type": "Feature",
  "properties": {
    "date:inception_lower":"2007-07-01",
    "date:inception_upper":"2007-07-31",
    "iso:country":"GB",
    "wof:name":"SY2 5BF",
    "wof:placetype":"postalcode"
},
  "geometry": {"coordinates":[-2.740608,52.709009],"type":"Point"}
}