{
  "type": "Feature",
  "properties": {
    "iso:country":"GB",
    "wof:name":"LA12 8ER",
    "wof:placetype":"postalcode"
},
  "geometry": {"coordinates":[-3.10908423423873,54.26637616175675],"type":"Point"}
}