{
  "type": "Feature",
  "properties": {
    "date:inception_lower": "1980-01-01",
    "date:inception_upper": "1980-01-01",
    "iso:country": "GB",
    "wof:name": "LA12 8ER",
    "wof:placetype": "postalcode"
  },
  "geometry": {"coordinates":[-3.109038,54.266358],"type":"Point"}
}
