{
  "type": "Feature",
  "properties": {
    "iso:country":"GB",
    "wof:name":"MK44 3NF",
    "wof:placetype":"postalcode"
},
  "geometry": {"coordinates":[-0.3165916914482,52.14823390771867],"type":"Point"}
}