{
  "type": "Feature",
  "properties": {
    "date:inception_lower": "1980-01-01",
    "date:inception_upper": "1980-01-01",
    "iso:country": "GB",
    "wof:name": "MK44 3NF",
    "wof:placetype": "postalcode"
  },
  "geometry": {"coordinates":[-0.316592,52.148234],"type":"Point"}
}
