{
  "type": "Feature",
  "properties": {
    "date:inception_lower": "1980-01-01",
    "date:inception_upper": "1980-01-01",
    "iso:country": "GB",
    "wof:name": "NN14 3JY",
    "wof:placetype": "postalcode"
  },
  "geometry": {"coordinates":[-0.551904,52.402789],"type":"Point"}
}
