{
  "type": "Feature",
  "properties": {
    "iso:country":"GB",
    "wof:name":"ME5 9AR",
    "wof:placetype":"postalcode"
},
  "geometry": {"coordinates":[0.52137215437127,51.34491938891298],"type":"Point"}
}