{
  "type": "Feature",
  "properties": {
    "date:inception_lower": "2022-05-01",
    "date:inception_upper": "2022-05-01",
    "iso:country": "GB",
    "wof:name": "WS2 8EU",
    "wof:placetype": "postalcode"
  },
  "geometry": {"coordinates":[-1.995375,52.59316],"type":"Point"}
}
