{
  "type": "Feature",
  "properties": {
    "iso:country":"GB",
    "wof:name":"LE18 4WN",
    "wof:placetype":"postalcode"
},
  "geometry": {"coordinates":[-1.12901196004018,52.58907202311074],"type":"Point"}
}