{
  "type": "Feature",
  "properties": {
    "date:inception_lower": "1992-08-01",
    "date:inception_upper": "1992-08-01",
    "iso:country": "GB",
    "wof:name": "LE18 4WN",
    "wof:placetype": "postalcode"
  },
  "geometry": {"coordinates":[-1.129012,52.589072],"type":"Point"}
}
