{
  "type": "Feature",
  "properties": {
    "iso:country": "GB",
    "wof:name": "EX17 4AL",
    "wof:placetype": "postalcode"
  },
  "geometry": {"coordinates":[-3.597202,50.849983],"type":"Point"}
}
