{
  "type": "Feature",
  "properties": {
    "iso:country": "GB",
    "wof:name": "S1 4UP",
    "wof:placetype": "postalcode"
  },
  "geometry": {"coordinates":[-1.477059,53.37406],"type":"Point"}
}
