{
  "type": "Feature",
  "properties": {
    "date:inception_lower":"1990-07-01",
    "date:inception_upper":"1990-07-31",
    "iso:country":"GB",
    "wof:name":"SE6 1BA",
    "wof:placetype":"postalcode"
},
  "geometry": {"coordinates":[-0.009646,51.440913],"type":"Point"}
}