{
  "type": "Feature",
  "properties": {
    "iso:country": "GB",
    "wof:name": "SY6 7DQ",
    "wof:placetype": "postalcode"
  },
  "geometry": {"coordinates":[-2.760635,52.513107],"type":"Point"}
}
