{
  "type": "Feature",
  "properties": {
    "date:inception_lower": "1980-01-01",
    "date:inception_upper": "1980-01-01",
    "iso:country": "GB",
    "wof:name": "E17 5AR",
    "wof:placetype": "postalcode"
  },
  "geometry": {"coordinates":[-0.015211,51.598801],"type":"Point"}
}
