{
  "type": "Feature",
  "properties": {
    "iso:country":"GB",
    "wof:name":"E17 5AR",
    "wof:placetype":"postalcode"
},
  "geometry": {"coordinates":[-0.01521106768293,51.5988010520141],"type":"Point"}
}