{
  "type": "Feature",
  "properties": {
    "iso:country": "GB",
    "wof:name": "WS11 4AS",
    "wof:placetype": "postalcode"
  },
  "geometry": {"coordinates":[-2.035115,52.697618],"type":"Point"}
}
