{
  "type": "Feature",
  "properties": {
    "iso:country":"GB",
    "wof:name":"WS11 4AS",
    "wof:placetype":"postalcode"
},
  "geometry": {"coordinates":[-2.03511548895963,52.69761780399287],"type":"Point"}
}