{
  "type": "Feature",
  "properties": {
    "iso:country": "GB",
    "wof:name": "CV32 7SL",
    "wof:placetype": "postalcode"
  },
  "geometry": {"coordinates":[-1.516098,52.303654],"type":"Point"}
}
