{
  "type": "Feature",
  "properties": {
    "iso:country":"GB",
    "wof:name":"G76 8RA",
    "wof:placetype":"postalcode"
},
  "geometry": {"coordinates":[-4.29815998724445,55.78489242250119],"type":"Point"}
}