{
  "type": "Feature",
  "properties": {
    "iso:country":"GB",
    "wof:name":"RH2 0NT",
    "wof:placetype":"postalcode"
},
  "geometry": {"coordinates":[-0.19237299895058,51.24062029249313],"type":"Point"}
}