{
  "type": "Feature",
  "properties": {
    "iso:country": "GB",
    "wof:name": "KY15 5DG",
    "wof:placetype": "postalcode"
  },
  "geometry": {"coordinates":[-3.023167,56.313597],"type":"Point"}
}
