{
  "type": "Feature",
  "properties": {
    "iso:country":"GB",
    "wof:name":"NP20 1JF",
    "wof:placetype":"postalcode"
},
  "geometry": {"coordinates":[-2.99734448877378,51.58640477235061],"type":"Point"}
}