{
  "type": "Feature",
  "properties": {
    "date:inception_lower":"1999-06-01",
    "date:inception_upper":"1999-06-30",
    "iso:country":"GB",
    "wof:name":"NP20 1JF",
    "wof:placetype":"postalcode"
},
  "geometry": {"coordinates":[-2.997351,51.586407],"type":"Point"}
}