{
  "type": "Feature",
  "properties": {
    "date:inception_lower": "1980-01-01",
    "date:inception_upper": "1980-01-01",
    "iso:country": "GB",
    "wof:name": "SW18 1RX",
    "wof:placetype": "postalcode"
  },
  "geometry": {"coordinates":[-0.201133,51.45729],"type":"Point"}
}
