{
  "type": "Feature",
  "properties": {
    "iso:country":"GB",
    "wof:name":"LE9 4JT",
    "wof:placetype":"postalcode"
},
  "geometry": {"coordinates":[-1.27602657330227,52.54635221316812],"type":"Point"}
}