{
  "type": "Feature",
  "properties": {
    "iso:country": "GB",
    "wof:name": "CT2 0BZ",
    "wof:placetype": "postalcode"
  },
  "geometry": {"coordinates":[1.124843,51.29481],"type":"Point"}
}
