{
  "type": "Feature",
  "properties": {
    "iso:country":"GB",
    "wof:name":"CT2 0BZ",
    "wof:placetype":"postalcode"
},
  "geometry": {"coordinates":[1.12484320810101,51.2948098851252],"type":"Point"}
}