{
  "type": "Feature",
  "properties": {
    "iso:country":"GB",
    "wof:name":"RG24 7HT",
    "wof:placetype":"postalcode"
},
  "geometry": {"coordinates":[-1.04113723613469,51.2648933285442],"type":"Point"}
}