{
  "type": "Feature",
  "properties": {
    "iso:country":"GB",
    "wof:name":"W1J 7BN",
    "wof:placetype":"postalcode"
},
  "geometry": {"coordinates":[-0.14581618217489,51.50651633858928],"type":"Point"}
}