{
  "type": "Feature",
  "properties": {
    "iso:country":"GB",
    "wof:name":"GL6 8BP",
    "wof:placetype":"postalcode"
},
  "geometry": {"coordinates":[-2.14831200137375,51.72742350594964],"type":"Point"}
}