{
  "type": "Feature",
  "properties": {
    "iso:country": "GB",
    "wof:name": "GL6 8BP",
    "wof:placetype": "postalcode"
  },
  "geometry": {"coordinates":[-2.148312,51.727424],"type":"Point"}
}
