{
  "type": "Feature",
  "properties": {
    "date:inception_lower": "1980-01-01",
    "date:inception_upper": "1980-01-01",
    "iso:country": "GB",
    "wof:name": "HX6 2NN",
    "wof:placetype": "postalcode"
  },
  "geometry": {"coordinates":[-1.910176,53.713393],"type":"Point"}
}
