{
  "type": "Feature",
  "properties": {
    "iso:country": "GB",
    "wof:name": "TA19 0EP",
    "wof:placetype": "postalcode"
  },
  "geometry": {"coordinates":[-2.910264,50.919684],"type":"Point"}
}
