{
  "type": "Feature",
  "properties": {
    "date:inception_lower": "2005-01-01",
    "date:inception_upper": "2005-01-01",
    "iso:country": "GB",
    "wof:name": "MK19 6LD",
    "wof:placetype": "postalcode"
  },
  "geometry": {"coordinates":[-0.888194,52.04939],"type":"Point"}
}
