{
  "type": "Feature",
  "properties": {
    "iso:country": "GB",
    "wof:name": "DE75 7XD",
    "wof:placetype": "postalcode"
  },
  "geometry": {"coordinates":[-1.368311,53.011375],"type":"Point"}
}
