{
  "type": "Feature",
  "properties": {
    "iso:country": "GB",
    "wof:name": "RM3 8NA",
    "wof:placetype": "postalcode"
  },
  "geometry": {"coordinates":[0.223214,51.601202],"type":"Point"}
}
