{
  "type": "Feature",
  "properties": {
    "iso:country":"GB",
    "wof:name":"RM3 8NA",
    "wof:placetype":"postalcode"
},
  "geometry": {"coordinates":[0.22316275471142,51.60126307659517],"type":"Point"}
}