{
  "type": "Feature",
  "properties": {
    "iso:country":"GB",
    "wof:name":"BN7 1XD",
    "wof:placetype":"postalcode"
},
  "geometry": {"coordinates":[0.01049059826405,50.87291115594981],"type":"Point"}
}