{
  "type": "Feature",
  "properties": {
    "iso:country":"GB",
    "wof:name":"SW18 3PG",
    "wof:placetype":"postalcode"
},
  "geometry": {"coordinates":[-0.1807486187629,51.43984433889251],"type":"Point"}
}