{
  "type": "Feature",
  "properties": {
    "iso:country":"GB",
    "wof:name":"SA11 3SE",
    "wof:placetype":"postalcode"
},
  "geometry": {"coordinates":[-3.79103823473993,51.64987422876296],"type":"Point"}
}