{
  "type": "Feature",
  "properties": {
    "iso:country":"GB",
    "wof:name":"GU9 9DR",
    "wof:placetype":"postalcode"
},
  "geometry": {"coordinates":[-0.77706481285622,51.23515945477239],"type":"Point"}
}