{
  "type": "Feature",
  "properties": {
    "iso:country":"GB",
    "wof:name":"EH52 6JW",
    "wof:placetype":"postalcode"
},
  "geometry": {"coordinates":[-3.47724969569692,55.93621728291293],"type":"Point"}
}