{
  "type": "Feature",
  "properties": {
    "iso:country":"GB",
    "wof:name":"NE44 6DZ",
    "wof:placetype":"postalcode"
},
  "geometry": {"coordinates":[-1.96676387568704,54.94645967039566],"type":"Point"}
}