{
  "type": "Feature",
  "properties": {
    "iso:country": "GB",
    "wof:name": "TA11 6DF",
    "wof:placetype": "postalcode"
  },
  "geometry": {"coordinates":[-2.650353,51.088292],"type":"Point"}
}
