{
  "type": "Feature",
  "properties": {
    "iso:country":"GB",
    "wof:name":"TA11 6DF",
    "wof:placetype":"postalcode"
},
  "geometry": {"coordinates":[-2.65035289357365,51.08829229110697],"type":"Point"}
}