{
  "type": "Feature",
  "properties": {
    "iso:country": "GB",
    "wof:name": "BS8 3TY",
    "wof:placetype": "postalcode"
  },
  "geometry": {"coordinates":[-2.704505,51.451569],"type":"Point"}
}
