{
  "type": "Feature",
  "properties": {
    "iso:country":"GB",
    "wof:name":"BS8 3TY",
    "wof:placetype":"postalcode"
},
  "geometry": {"coordinates":[-2.70450517630865,51.45156856045691],"type":"Point"}
}