{
  "type": "Feature",
  "properties": {
    "iso:country":"GB",
    "wof:name":"WA10 3BP",
    "wof:placetype":"postalcode"
},
  "geometry": {"coordinates":[-2.77448428702413,53.43887458263995],"type":"Point"}
}