{
  "type": "Feature",
  "properties": {
    "iso:country": "GB",
    "wof:name": "WA10 3BP",
    "wof:placetype": "postalcode"
  },
  "geometry": {"coordinates":[-2.774811,53.438709],"type":"Point"}
}
