{
  "type": "Feature",
  "properties": {
    "date:inception_lower": "1980-01-01",
    "date:inception_upper": "1980-01-01",
    "iso:country": "GB",
    "wof:name": "WA10 3BP",
    "wof:placetype": "postalcode"
  },
  "geometry": {"coordinates":[-2.774811,53.438709],"type":"Point"}
}
