{
  "type": "Feature",
  "properties": {
    "iso:country":"GB",
    "wof:name":"WR1 1DN",
    "wof:placetype":"postalcode"
},
  "geometry": {"coordinates":[-2.22174624229334,52.19586165709512],"type":"Point"}
}