{
  "type": "Feature",
  "properties": {
    "date:inception_lower": "1998-06-01",
    "date:inception_upper": "1998-06-01",
    "iso:country": "GB",
    "wof:name": "LS12 5TR",
    "wof:placetype": "postalcode"
  },
  "geometry": {"coordinates":[-1.622408,53.779191],"type":"Point"}
}
