{
  "type": "Feature",
  "properties": {
    "iso:country":"GB",
    "wof:name":"LS12 5TR",
    "wof:placetype":"postalcode"
},
  "geometry": {"coordinates":[-1.62240832296424,53.77919130106153],"type":"Point"}
}