{
  "type": "Feature",
  "properties": {
    "iso:country":"GB",
    "wof:name":"TR3 7HU",
    "wof:placetype":"postalcode"
},
  "geometry": {"coordinates":[-5.13718806878446,50.19172938401176],"type":"Point"}
}