{
  "type": "Feature",
  "properties": {
    "iso:country":"GB",
    "wof:name":"TA24 6RL",
    "wof:placetype":"postalcode"
},
  "geometry": {"coordinates":[-3.44037993901941,51.1875726675938],"type":"Point"}
}