{
  "type": "Feature",
  "properties": {
    "iso:country":"GB",
    "wof:name":"B75 6DG",
    "wof:placetype":"postalcode"
},
  "geometry": {"coordinates":[-1.82081698559844,52.57210828098409],"type":"Point"}
}