{
  "type": "Feature",
  "properties": {
    "iso:country":"GB",
    "wof:name":"ML6 7QD",
    "wof:placetype":"postalcode"
},
  "geometry": {"coordinates":[-3.8883896936213,55.89104946344792],"type":"Point"}
}