{
  "type": "Feature",
  "properties": {
    "iso:country": "GB",
    "wof:name": "NE44 6AH",
    "wof:placetype": "postalcode"
  },
  "geometry": {"coordinates":[-2.004957,54.938015],"type":"Point"}
}
