{
  "type": "Feature",
  "properties": {
    "iso:country":"GB",
    "wof:name":"DY10 4HP",
    "wof:placetype":"postalcode"
},
  "geometry": {"coordinates":[-2.23289250658411,52.36029945686128],"type":"Point"}
}