{
  "type": "Feature",
  "properties": {
    "iso:country": "GB",
    "wof:name": "DY10 4HP",
    "wof:placetype": "postalcode"
  },
  "geometry": {"coordinates":[-2.232892,52.360299],"type":"Point"}
}
