{
  "type": "Feature",
  "properties": {
    "iso:country": "GB",
    "wof:name": "NG6 8ZJ",
    "wof:placetype": "postalcode"
  },
  "geometry": {"coordinates":[-1.196203,53.002626],"type":"Point"}
}
