{
  "type": "Feature",
  "properties": {
    "iso:country":"GB",
    "wof:name":"AB21 9JX",
    "wof:placetype":"postalcode"
},
  "geometry": {"coordinates":[-2.18132319867394,57.19384316572236],"type":"Point"}
}