{
  "type": "Feature",
  "properties": {
    "iso:country":"GB",
    "wof:name":"MK40 4NQ",
    "wof:placetype":"postalcode"
},
  "geometry": {"coordinates":[-0.49719472339654,52.13230424236622],"type":"Point"}
}