{
  "type": "Feature",
  "properties": {
    "iso:country": "GB",
    "wof:name": "WA11 7RH",
    "wof:placetype": "postalcode"
  },
  "geometry": {"coordinates":[-2.752963,53.475821],"type":"Point"}
}
