{
  "type": "Feature",
  "properties": {
    "date:inception_lower":"2005-03-01",
    "date:inception_upper":"2005-03-31",
    "iso:country":"GB",
    "wof:name":"WA11 7RH",
    "wof:placetype":"postalcode"
},
  "geometry": {"coordinates":[-2.752963,53.475821],"type":"Point"}
}