{
  "type": "Feature",
  "properties": {
    "date:inception_lower":"1985-10-01",
    "date:inception_upper":"1985-10-31",
    "iso:country":"GB",
    "wof:name":"GL8 8PQ",
    "wof:placetype":"postalcode"
},
  "geometry": {"coordinates":[-2.166586,51.641443],"type":"Point"}
}