{
  "type": "Feature",
  "properties": {
    "iso:country": "GB",
    "wof:name": "GL8 8PQ",
    "wof:placetype": "postalcode"
  },
  "geometry": {"coordinates":[-2.166586,51.641443],"type":"Point"}
}
