{
  "type": "Feature",
  "properties": {
    "date:inception_lower": "1980-01-01",
    "date:inception_upper": "1980-01-01",
    "iso:country": "GB",
    "wof:name": "IG8 9PQ",
    "wof:placetype": "postalcode"
  },
  "geometry": {"coordinates":[0.004623,51.603257],"type":"Point"}
}
