{
  "type": "Feature",
  "properties": {
    "iso:country":"GB",
    "wof:name":"IG8 9PQ",
    "wof:placetype":"postalcode"
},
  "geometry": {"coordinates":[0.00462273193596,51.60325699277264],"type":"Point"}
}