{
  "type": "Feature",
  "properties": {
    "iso:country":"GB",
    "wof:name":"BH21 1NX",
    "wof:placetype":"postalcode"
},
  "geometry": {"coordinates":[-1.9829896442823,50.80466718662594],"type":"Point"}
}