{
  "type": "Feature",
  "properties": {
    "iso:country":"GB",
    "wof:name":"BS40 6AH",
    "wof:placetype":"postalcode"
},
  "geometry": {"coordinates":[-2.60906645395344,51.29488227526529],"type":"Point"}
}