{
  "type": "Feature",
  "properties": {
    "date:inception_lower": "2006-03-01",
    "date:inception_upper": "2006-03-01",
    "iso:country": "GB",
    "wof:name": "RH15 0FY",
    "wof:placetype": "postalcode"
  },
  "geometry": {"coordinates":[-0.121264,50.946541],"type":"Point"}
}
