{
  "type": "Feature",
  "properties": {
    "iso:country": "GB",
    "wof:name": "EH41 4JN",
    "wof:placetype": "postalcode"
  },
  "geometry": {"coordinates":[-2.76777,55.877442],"type":"Point"}
}
