{
  "type": "Feature",
  "properties": {
    "iso:country":"GB",
    "wof:name":"EH41 4JN",
    "wof:placetype":"postalcode"
},
  "geometry": {"coordinates":[-2.76776957240687,55.87744176171114],"type":"Point"}
}