{
  "type": "Feature",
  "properties": {
    "iso:country":"GB",
    "wof:name":"M25 0DR",
    "wof:placetype":"postalcode"
},
  "geometry": {"coordinates":[-2.24854440234936,53.52730003012015],"type":"Point"}
}