{
  "type": "Feature",
  "properties": {
    "iso:country":"GB",
    "wof:name":"W5 1LZ",
    "wof:placetype":"postalcode"
},
  "geometry": {"coordinates":[-0.31549184722496,51.52680881305513],"type":"Point"}
}