{
  "type": "Feature",
  "properties": {
    "iso:country":"GB",
    "wof:name":"LL13 9AG",
    "wof:placetype":"postalcode"
},
  "geometry": {"coordinates":[-2.97110422066032,53.04977103619793],"type":"Point"}
}