{
  "type": "Feature",
  "properties": {
    "iso:country": "GB",
    "wof:name": "LL13 9AG",
    "wof:placetype": "postalcode"
  },
  "geometry": {"coordinates":[-2.971104,53.049771],"type":"Point"}
}
