{
  "type": "Feature",
  "properties": {
    "date:inception_lower":"2012-09-01",
    "date:inception_upper":"2012-09-30",
    "iso:country":"GB",
    "wof:name":"LL13 9AG",
    "wof:placetype":"postalcode"
},
  "geometry": {"coordinates":[-2.971104,53.049771],"type":"Point"}
}