{
  "type": "Feature",
  "properties": {
    "iso:country": "GB",
    "wof:name": "CT15 7DS",
    "wof:placetype": "postalcode"
  },
  "geometry": {"coordinates":[1.237532,51.139901],"type":"Point"}
}
