{
  "type": "Feature",
  "properties": {
    "date:inception_lower": "1980-01-01",
    "date:inception_upper": "1980-01-01",
    "iso:country": "GB",
    "wof:name": "CT15 7DS",
    "wof:placetype": "postalcode"
  },
  "geometry": {"coordinates":[1.237532,51.139901],"type":"Point"}
}
