{
  "type": "Feature",
  "properties": {
    "iso:country":"GB",
    "wof:name":"SP2 7DJ",
    "wof:placetype":"postalcode"
},
  "geometry": {"coordinates":[-1.80712045591393,51.07602410768479],"type":"Point"}
}