{
  "type": "Feature",
  "properties": {
    "date:inception_lower":"1980-01-01",
    "date:inception_upper":"1980-01-31",
    "iso:country":"GB",
    "wof:name":"LN6 7UB",
    "wof:placetype":"postalcode"
},
  "geometry": {"coordinates":[-0.556161,53.218498],"type":"Point"}
}