{
  "type": "Feature",
  "properties": {
    "iso:country": "GB",
    "wof:name": "LN6 7UB",
    "wof:placetype": "postalcode"
  },
  "geometry": {"coordinates":[-0.556161,53.218498],"type":"Point"}
}
