{
  "type": "Feature",
  "properties": {
    "iso:country":"GB",
    "wof:name":"CO16 0BX",
    "wof:placetype":"postalcode"
},
  "geometry": {"coordinates":[1.10151166033794,51.89427250630708],"type":"Point"}
}