{
  "type": "Feature",
  "properties": {
    "date:inception_lower": "1980-01-01",
    "date:inception_upper": "1980-01-01",
    "iso:country": "GB",
    "wof:name": "DN16 3DU",
    "wof:placetype": "postalcode"
  },
  "geometry": {"coordinates":[-0.641799,53.563435],"type":"Point"}
}
