{
  "type": "Feature",
  "properties": {
    "iso:country":"GB",
    "wof:name":"DN16 3DU",
    "wof:placetype":"postalcode"
},
  "geometry": {"coordinates":[-0.64179910882947,53.56343549371108],"type":"Point"}
}