{
  "type": "Feature",
  "properties": {
    "iso:country": "GB",
    "wof:name": "LS11 0LF",
    "wof:placetype": "postalcode"
  },
  "geometry": {"coordinates":[-1.58761,53.770125],"type":"Point"}
}
