{
  "type": "Feature",
  "properties": {
    "iso:country":"GB",
    "wof:name":"SL3 7RY",
    "wof:placetype":"postalcode"
},
  "geometry": {"coordinates":[-0.56374179462589,51.50175863427625],"type":"Point"}
}