{
  "type": "Feature",
  "properties": {
    "iso:country":"GB",
    "wof:name":"PO20 8AT",
    "wof:placetype":"postalcode"
},
  "geometry": {"coordinates":[-0.90384148378804,50.78111269725233],"type":"Point"}
}