{
  "type": "Feature",
  "properties": {
    "iso:country":"GB",
    "wof:name":"TW7 6AX",
    "wof:placetype":"postalcode"
},
  "geometry": {"coordinates":[-0.32317535636032,51.47617520615857],"type":"Point"}
}