{
  "type": "Feature",
  "properties": {
    "iso:country": "GB",
    "wof:name": "EH47 0BF",
    "wof:placetype": "postalcode"
  },
  "geometry": {"coordinates":[-3.711892,55.858526],"type":"Point"}
}
