{
  "type": "Feature",
  "properties": {
    "iso:country": "GB",
    "wof:name": "M1 4AL",
    "wof:placetype": "postalcode"
  },
  "geometry": {"coordinates":[-2.238973,53.480364],"type":"Point"}
}
