{
  "type": "Feature",
  "properties": {
    "date:inception_lower":"2011-02-01",
    "date:inception_upper":"2011-02-28",
    "iso:country":"GB",
    "wof:name":"M1 4AL",
    "wof:placetype":"postalcode"
},
  "geometry": {"coordinates":[-2.238973,53.480364],"type":"Point"}
}