{
  "type": "Feature",
  "properties": {
    "date:inception_lower": "2011-02-01",
    "date:inception_upper": "2011-02-01",
    "iso:country": "GB",
    "wof:name": "M1 4AL",
    "wof:placetype": "postalcode"
  },
  "geometry": {"coordinates":[-2.237414,53.479556],"type":"Point"}
}
