{
  "type": "Feature",
  "properties": {
    "iso:country": "GB",
    "wof:name": "M1 4AL",
    "wof:placetype": "postalcode"
  },
  "geometry": {"coordinates":[-2.237414,53.479556],"type":"Point"}
}
