{
  "type": "Feature",
  "properties": {
    "iso:country":"GB",
    "wof:name":"SG6 4NR",
    "wof:placetype":"postalcode"
},
  "geometry": {"coordinates":[-0.22688187662334,51.99235308243735],"type":"Point"}
}