{
  "type": "Feature",
  "properties": {
    "date:inception_lower":"1980-01-01",
    "date:inception_upper":"1980-01-31",
    "iso:country":"GB",
    "wof:name":"TS9 7LL",
    "wof:placetype":"postalcode"
},
  "geometry": {"coordinates":[-1.105766,54.352374],"type":"Point"}
}