{
  "type": "Feature",
  "properties": {
    "iso:country":"GB",
    "wof:name":"TS9 7LL",
    "wof:placetype":"postalcode"
},
  "geometry": {"coordinates":[-1.10575473790501,54.35236053709953],"type":"Point"}
}