{
  "type": "Feature",
  "properties": {
    "iso:country":"GB",
    "wof:name":"DN7 4EB",
    "wof:placetype":"postalcode"
},
  "geometry": {"coordinates":[-1.02553814413696,53.5840932042946],"type":"Point"}
}