{
  "type": "Feature",
  "properties": {
    "iso:country": "GB",
    "wof:name": "DN7 4EB",
    "wof:placetype": "postalcode"
  },
  "geometry": {"coordinates":[-1.025538,53.584093],"type":"Point"}
}
