{
  "type": "Feature",
  "properties": {
    "date:inception_lower": "1980-01-01",
    "date:inception_upper": "1980-01-01",
    "iso:country": "GB",
    "wof:name": "WR5 2PS",
    "wof:placetype": "postalcode"
  },
  "geometry": {"coordinates":[-2.179259,52.159199],"type":"Point"}
}
