{
  "type": "Feature",
  "properties": {
    "iso:country":"GB",
    "wof:name":"YO24 1LX",
    "wof:placetype":"postalcode"
},
  "geometry": {"coordinates":[-1.11273937574489,53.9369613825844],"type":"Point"}
}