{
  "type": "Feature",
  "properties": {
    "iso:country":"GB",
    "wof:name":"BB9 0LQ",
    "wof:placetype":"postalcode"
},
  "geometry": {"coordinates":[-2.19746992961303,53.83175212313034],"type":"Point"}
}