{
  "type": "Feature",
  "properties": {
    "iso:country":"GB",
    "wof:name":"B92 0HR",
    "wof:placetype":"postalcode"
},
  "geometry": {"coordinates":[-1.72082245154633,52.41149800460509],"type":"Point"}
}