{
  "type": "Feature",
  "properties": {
    "date:inception_lower": "1980-01-01",
    "date:inception_upper": "1980-01-01",
    "iso:country": "GB",
    "wof:name": "B92 0HR",
    "wof:placetype": "postalcode"
  },
  "geometry": {"coordinates":[-1.720949,52.4111],"type":"Point"}
}
