{
  "type": "Feature",
  "properties": {
    "iso:country": "GB",
    "wof:name": "B92 0HR",
    "wof:placetype": "postalcode"
  },
  "geometry": {"coordinates":[-1.720949,52.4111],"type":"Point"}
}
