{
  "type": "Feature",
  "properties": {
    "date:inception_lower": "2017-12-01",
    "date:inception_upper": "2017-12-01",
    "iso:country": "GB",
    "wof:name": "YO42 2RW",
    "wof:placetype": "postalcode"
  },
  "geometry": {"coordinates":[-0.792477,53.936345],"type":"Point"}
}
