{
  "type": "Feature",
  "properties": {
    "iso:country":"GB",
    "wof:name":"BR6 9EF",
    "wof:placetype":"postalcode"
},
  "geometry": {"coordinates":[0.10375525986836,51.36910189671585],"type":"Point"}
}