{
  "type": "Feature",
  "properties": {
    "date:inception_lower":"2014-03-01",
    "date:inception_upper":"2014-03-31",
    "iso:country":"GB",
    "wof:name":"SA15 4BZ",
    "wof:placetype":"postalcode"
},
  "geometry": {"coordinates":[-4.17511,51.685937],"type":"Point"}
}