{
  "type": "Feature",
  "properties": {
    "iso:country":"GB",
    "wof:name":"SA15 4BZ",
    "wof:placetype":"postalcode"
},
  "geometry": {"coordinates":[-4.17552584327124,51.68603017390452],"type":"Point"}
}