{
  "type": "Feature",
  "properties": {
    "iso:country":"GB",
    "wof:name":"BB9 6RE",
    "wof:placetype":"postalcode"
},
  "geometry": {"coordinates":[-2.20411328685491,53.86681175693221],"type":"Point"}
}