{
  "type": "Feature",
  "properties": {
    "iso:country":"GB",
    "wof:name":"KA11 5BH",
    "wof:placetype":"postalcode"
},
  "geometry": {"coordinates":[-4.64046304347382,55.56836196167993],"type":"Point"}
}