{
  "type": "Feature",
  "properties": {
    "iso:country": "GB",
    "wof:name": "KA11 5BH",
    "wof:placetype": "postalcode"
  },
  "geometry": {"coordinates":[-4.640889,55.56792],"type":"Point"}
}
