{
  "type": "Feature",
  "properties": {
    "iso:country": "GB",
    "wof:name": "KA11 5BH",
    "wof:placetype": "postalcode"
  },
  "geometry": {"coordinates":[-4.640443,55.568361],"type":"Point"}
}
