{
  "type": "Feature",
  "properties": {
    "iso:country": "GB",
    "wof:name": "YO11 2DD",
    "wof:placetype": "postalcode"
  },
  "geometry": {"coordinates":[-0.399431,54.275168],"type":"Point"}
}
