{
  "type": "Feature",
  "properties": {
    "iso:country":"GB",
    "wof:name":"NR7 0DE",
    "wof:placetype":"postalcode"
},
  "geometry": {"coordinates":[1.33035786387864,52.63309328182559],"type":"Point"}
}