{
  "type": "Feature",
  "properties": {
    "iso:country":"GB",
    "wof:name":"BS3 1LE",
    "wof:placetype":"postalcode"
},
  "geometry": {"coordinates":[-2.60689425332724,51.44210694180278],"type":"Point"}
}