{
  "type": "Feature",
  "properties": {
    "date:inception_lower":"2009-06-01",
    "date:inception_upper":"2009-06-30",
    "iso:country":"GB",
    "wof:name":"ML7 4DS",
    "wof:placetype":"postalcode"
},
  "geometry": {"coordinates":[-3.81061,55.82313],"type":"Point"}
}