{
  "type": "Feature",
  "properties": {
    "iso:country":"GB",
    "wof:name":"SR4 6DR",
    "wof:placetype":"postalcode"
},
  "geometry": {"coordinates":[-1.39968224982666,54.91134727438598],"type":"Point"}
}