{
  "type": "Feature",
  "properties": {
    "iso:country":"GB",
    "wof:name":"SE12 8UJ",
    "wof:placetype":"postalcode"
},
  "geometry": {"coordinates":[0.02221861049577,51.45440505099462],"type":"Point"}
}