{
  "type": "Feature",
  "properties": {
    "iso:country": "GB",
    "wof:name": "TN2 3GN",
    "wof:placetype": "postalcode"
  },
  "geometry": {"coordinates":[0.277408,51.146875],"type":"Point"}
}
