{
  "type": "Feature",
  "properties": {
    "iso:country":"GB",
    "wof:name":"SK22 4EE",
    "wof:placetype":"postalcode"
},
  "geometry": {"coordinates":[-1.99947980179834,53.3754828050895],"type":"Point"}
}