{
  "type": "Feature",
  "properties": {
    "iso:country":"GB",
    "wof:name":"HA1 2LZ",
    "wof:placetype":"postalcode"
},
  "geometry": {"coordinates":[-0.3247493255115,51.5793572026674],"type":"Point"}
}