{
  "type": "Feature",
  "properties": {
    "iso:country": "GB",
    "wof:name": "HA1 2LZ",
    "wof:placetype": "postalcode"
  },
  "geometry": {"coordinates":[-0.324749,51.579357],"type":"Point"}
}
