{
  "type": "Feature",
  "properties": {
    "date:inception_lower": "1980-01-01",
    "date:inception_upper": "1980-01-01",
    "iso:country": "GB",
    "wof:name": "PR8 6PQ",
    "wof:placetype": "postalcode"
  },
  "geometry": {"coordinates":[-2.989841,53.639196],"type":"Point"}
}
