{
  "type": "Feature",
  "properties": {
    "iso:country":"GB",
    "wof:name":"WA11 9PW",
    "wof:placetype":"postalcode"
},
  "geometry": {"coordinates":[-2.72157032642464,53.46198337156292],"type":"Point"}
}