{
  "type": "Feature",
  "properties": {
    "iso:country": "GB",
    "wof:name": "WA11 9PW",
    "wof:placetype": "postalcode"
  },
  "geometry": {"coordinates":[-2.721553,53.461919],"type":"Point"}
}
