{
  "type": "Feature",
  "properties": {
    "date:inception_lower":"1980-01-01",
    "date:inception_upper":"1980-01-31",
    "iso:country":"GB",
    "wof:name":"DL4 2JD",
    "wof:placetype":"postalcode"
},
  "geometry": {"coordinates":[-1.644199,54.625063],"type":"Point"}
}