{
  "type": "Feature",
  "properties": {
    "iso:country":"GB",
    "wof:name":"DL4 2JD",
    "wof:placetype":"postalcode"
},
  "geometry": {"coordinates":[-1.64367950360606,54.62487200640773],"type":"Point"}
}