{
  "type": "Feature",
  "properties": {
    "iso:country": "GB",
    "wof:name": "DL4 2JD",
    "wof:placetype": "postalcode"
  },
  "geometry": {"coordinates":[-1.644199,54.625063],"type":"Point"}
}
