{
  "type": "Feature",
  "properties": {
    "iso:country":"GB",
    "wof:name":"SG12 7LQ",
    "wof:placetype":"postalcode"
},
  "geometry": {"coordinates":[-0.01728084534988,51.81648780314286],"type":"Point"}
}