{
  "type": "Feature",
  "properties": {
    "date:inception_lower":"1980-01-01",
    "date:inception_upper":"1980-01-31",
    "iso:country":"GB",
    "wof:name":"SG12 7LQ",
    "wof:placetype":"postalcode"
},
  "geometry": {"coordinates":[-0.017281,51.816488],"type":"Point"}
}