{
  "type": "Feature",
  "properties": {
    "iso:country": "GB",
    "wof:name": "EX4 8JU",
    "wof:placetype": "postalcode"
  },
  "geometry": {"coordinates":[-3.479847,50.738172],"type":"Point"}
}
