{
  "type": "Feature",
  "properties": {
    "date:inception_lower": "1980-01-01",
    "date:inception_upper": "1980-01-01",
    "iso:country": "GB",
    "wof:name": "EX4 8JU",
    "wof:placetype": "postalcode"
  },
  "geometry": {"coordinates":[-3.479847,50.738172],"type":"Point"}
}
