{
  "type": "Feature",
  "properties": {
    "iso:country":"GB",
    "wof:name":"HU8 9QA",
    "wof:placetype":"postalcode"
},
  "geometry": {"coordinates":[-0.26571066729397,53.78115062761753],"type":"Point"}
}