{
  "type": "Feature",
  "properties": {
    "iso:country": "GB",
    "wof:name": "CB24 1BL",
    "wof:placetype": "postalcode"
  },
  "geometry": {"coordinates":[0.055902,52.285781],"type":"Point"}
}
