{
  "type": "Feature",
  "properties": {
    "date:inception_lower": "1980-01-01",
    "date:inception_upper": "1980-01-01",
    "iso:country": "GB",
    "wof:name": "BH20 6BN",
    "wof:placetype": "postalcode"
  },
  "geometry": {"coordinates":[-2.216279,50.681655],"type":"Point"}
}
