{
  "type": "Feature",
  "properties": {
    "date:inception_lower": "1980-01-01",
    "date:inception_upper": "1980-01-01",
    "iso:country": "GB",
    "wof:name": "CF5 1GX",
    "wof:placetype": "postalcode"
  },
  "geometry": {"coordinates":[-3.204645,51.48206],"type":"Point"}
}
