{
  "type": "Feature",
  "properties": {
    "iso:country":"GB",
    "wof:name":"CF5 1GX",
    "wof:placetype":"postalcode"
},
  "geometry": {"coordinates":[-3.20464514884731,51.48206037647056],"type":"Point"}
}