{
  "type": "Feature",
  "properties": {
    "iso:country": "GB",
    "wof:name": "CF5 1GX",
    "wof:placetype": "postalcode"
  },
  "geometry": {"coordinates":[-3.204645,51.48206],"type":"Point"}
}
