{
  "type": "Feature",
  "properties": {
    "date:inception_lower": "2006-05-01",
    "date:inception_upper": "2006-05-01",
    "iso:country": "GB",
    "wof:name": "RG27 9QQ",
    "wof:placetype": "postalcode"
  },
  "geometry": {"coordinates":[-0.981325,51.277229],"type":"Point"}
}
