{
  "type": "Feature",
  "properties": {
    "iso:country":"GB",
    "wof:name":"RG27 9QQ",
    "wof:placetype":"postalcode"
},
  "geometry": {"coordinates":[-0.9813253101457,51.27722903807853],"type":"Point"}
}