{
  "type": "Feature",
  "properties": {
    "iso:country":"GB",
    "wof:name":"PE1 5HN",
    "wof:placetype":"postalcode"
},
  "geometry": {"coordinates":[-0.22960930307779,52.57374688391258],"type":"Point"}
}