{
  "type": "Feature",
  "properties": {
    "date:inception_lower":"1980-01-01",
    "date:inception_upper":"1980-01-31",
    "iso:country":"GB",
    "wof:name":"PE1 5HN",
    "wof:placetype":"postalcode"
},
  "geometry": {"coordinates":[-0.229609,52.573747],"type":"Point"}
}