{
  "type": "Feature",
  "properties": {
    "date:inception_lower": "1980-01-01",
    "date:inception_upper": "1980-01-01",
    "iso:country": "GB",
    "wof:name": "E17 7PT",
    "wof:placetype": "postalcode"
  },
  "geometry": {"coordinates":[-0.022589,51.57987],"type":"Point"}
}
