{
  "type": "Feature",
  "properties": {
    "date:inception_lower":"1980-01-01",
    "date:inception_upper":"1980-01-31",
    "iso:country":"GB",
    "wof:name":"SW11 6PR",
    "wof:placetype":"postalcode"
},
  "geometry": {"coordinates":[-0.164698,51.456887],"type":"Point"}
}