{
  "type": "Feature",
  "properties": {
    "iso:country":"GB",
    "wof:name":"SW11 6PR",
    "wof:placetype":"postalcode"
},
  "geometry": {"coordinates":[-0.16469808624353,51.45688684667711],"type":"Point"}
}