{
  "type": "Feature",
  "properties": {
    "iso:country": "GB",
    "wof:name": "LS29 6JE",
    "wof:placetype": "postalcode"
  },
  "geometry": {"coordinates":[-1.735626,53.890899],"type":"Point"}
}
