{
  "type": "Feature",
  "properties": {
    "iso:country":"GB",
    "wof:name":"LS29 6JE",
    "wof:placetype":"postalcode"
},
  "geometry": {"coordinates":[-1.73562563875182,53.89089948938981],"type":"Point"}
}