{
  "type": "Feature",
  "properties": {
    "iso:country":"GB",
    "wof:name":"TA4 4QN",
    "wof:placetype":"postalcode"
},
  "geometry": {"coordinates":[-3.31999947783676,51.16219560121228],"type":"Point"}
}