{
  "type": "Feature",
  "properties": {
    "iso:country": "GB",
    "wof:name": "LL29 9SW",
    "wof:placetype": "postalcode"
  },
  "geometry": {"coordinates":[-3.702573,53.29095],"type":"Point"}
}
