{
  "type": "Feature",
  "properties": {
    "iso:country": "GB",
    "wof:name": "IP28 6US",
    "wof:placetype": "postalcode"
  },
  "geometry": {"coordinates":[0.641888,52.265355],"type":"Point"}
}
