{
  "type": "Feature",
  "properties": {
    "date:inception_lower":"2006-07-01",
    "date:inception_upper":"2006-07-31",
    "iso:country":"GB",
    "wof:name":"IP28 6US",
    "wof:placetype":"postalcode"
},
  "geometry": {"coordinates":[0.641888,52.265355],"type":"Point"}
}