{
  "type": "Feature",
  "properties": {
    "date:inception_lower": "2022-09-01",
    "date:inception_upper": "2022-09-01",
    "iso:country": "GB",
    "wof:name": "BA2 2FP",
    "wof:placetype": "postalcode"
  },
  "geometry": {"coordinates":[-2.382128,51.351355],"type":"Point"}
}
