{
  "type": "Feature",
  "properties": {
    "date:inception_lower": "2019-06-01",
    "date:inception_upper": "2019-06-01",
    "iso:country": "GB",
    "wof:name": "CV32 4BW",
    "wof:placetype": "postalcode"
  },
  "geometry": {"coordinates":[-1.530965,52.290102],"type":"Point"}
}
