{
  "type": "Feature",
  "properties": {
    "iso:country":"GB",
    "wof:name":"NE15 0NN",
    "wof:placetype":"postalcode"
},
  "geometry": {"coordinates":[-1.85574162953486,54.98834448913728],"type":"Point"}
}