{
  "type": "Feature",
  "properties": {
    "date:inception_lower": "1980-01-01",
    "date:inception_upper": "1980-01-01",
    "iso:country": "GB",
    "wof:name": "NE15 0NN",
    "wof:placetype": "postalcode"
  },
  "geometry": {"coordinates":[-1.855628,54.988369],"type":"Point"}
}
