{
  "type": "Feature",
  "properties": {
    "iso:country": "GB",
    "wof:name": "BH17 7DY",
    "wof:placetype": "postalcode"
  },
  "geometry": {"coordinates":[-1.996447,50.744022],"type":"Point"}
}
