{
  "type": "Feature",
  "properties": {
    "date:inception_lower": "1980-01-01",
    "date:inception_upper": "1980-01-01",
    "iso:country": "GB",
    "wof:name": "PE14 7JH",
    "wof:placetype": "postalcode"
  },
  "geometry": {"coordinates":[0.192144,52.739344],"type":"Point"}
}
