{
  "type": "Feature",
  "properties": {
    "iso:country":"GB",
    "wof:name":"PE14 7JH",
    "wof:placetype":"postalcode"
},
  "geometry": {"coordinates":[0.19215901823295,52.73933266270863],"type":"Point"}
}