{
  "type": "Feature",
  "properties": {
    "iso:country": "GB",
    "wof:name": "PE14 7JH",
    "wof:placetype": "postalcode"
  },
  "geometry": {"coordinates":[0.192144,52.739344],"type":"Point"}
}
