{
  "type": "Feature",
  "properties": {
    "iso:country":"GB",
    "wof:name":"MK44 1RD",
    "wof:placetype":"postalcode"
},
  "geometry": {"coordinates":[-0.50947967093471,52.19451736083217],"type":"Point"}
}