{
  "type": "Feature",
  "properties": {
    "iso:country":"GB",
    "wof:name":"CH1 3NS",
    "wof:placetype":"postalcode"
},
  "geometry": {"coordinates":[-2.87983169358756,53.19662883689766],"type":"Point"}
}