{
  "type": "Feature",
  "properties": {
    "iso:country":"GB",
    "wof:name":"SM6 9FY",
    "wof:placetype":"postalcode"
},
  "geometry": {"coordinates":[-0.1272627804058,51.35472260863659],"type":"Point"}
}