{
  "type": "Feature",
  "properties": {
    "iso:country": "GB",
    "wof:name": "SM6 9FY",
    "wof:placetype": "postalcode"
  },
  "geometry": {"coordinates":[-0.127263,51.354723],"type":"Point"}
}
