{
  "type": "Feature",
  "properties": {
    "date:inception_lower":"2001-12-01",
    "date:inception_upper":"2001-12-31",
    "iso:country":"GB",
    "wof:name":"SM6 9FY",
    "wof:placetype":"postalcode"
},
  "geometry": {"coordinates":[-0.127263,51.354723],"type":"Point"}
}