{
  "type": "Feature",
  "properties": {
    "iso:country":"GB",
    "wof:name":"CB1 2DZ",
    "wof:placetype":"postalcode"
},
  "geometry": {"coordinates":[0.13513790843056,52.1988103732044],"type":"Point"}
}