{
  "type": "Feature",
  "properties": {
    "date:inception_lower": "2022-04-01",
    "date:inception_upper": "2022-04-01",
    "iso:country": "GB",
    "wof:name": "CM6 4AT",
    "wof:placetype": "postalcode"
  },
  "geometry": {"coordinates":[0.345362,51.877347],"type":"Point"}
}
