{
  "type": "Feature",
  "properties": {
    "iso:country": "GB",
    "wof:name": "HU15 1HG",
    "wof:placetype": "postalcode"
  },
  "geometry": {"coordinates":[-0.581021,53.735714],"type":"Point"}
}
