{
  "type": "Feature",
  "properties": {
    "iso:country":"GB",
    "wof:name":"HU15 1HG",
    "wof:placetype":"postalcode"
},
  "geometry": {"coordinates":[-0.58102135846583,53.73571424474116],"type":"Point"}
}