{
  "type": "Feature",
  "properties": {
    "date:inception_lower":"1980-01-01",
    "date:inception_upper":"1980-01-31",
    "iso:country":"GB",
    "wof:name":"W4 4DD",
    "wof:placetype":"postalcode"
},
  "geometry": {"coordinates":[-0.274825,51.491318],"type":"Point"}
}