{
  "type": "Feature",
  "properties": {
    "date:inception_lower": "1980-01-01",
    "date:inception_upper": "1980-01-01",
    "iso:country": "GB",
    "wof:name": "PH37 4LT",
    "wof:placetype": "postalcode"
  },
  "geometry": {"coordinates":[-5.444431,56.870925],"type":"Point"}
}
