{
  "type": "Feature",
  "properties": {
    "iso:country":"GB",
    "wof:name":"PH37 4LT",
    "wof:placetype":"postalcode"
},
  "geometry": {"coordinates":[-5.44486955171383,56.86966427395461],"type":"Point"}
}