{
  "type": "Feature",
  "properties": {
    "date:inception_lower":"1987-04-01",
    "date:inception_upper":"1987-04-30",
    "iso:country":"GB",
    "wof:name":"SS3 8XB",
    "wof:placetype":"postalcode"
},
  "geometry": {"coordinates":[0.783532,51.539895],"type":"Point"}
}