{
  "type": "Feature",
  "properties": {
    "iso:country":"GB",
    "wof:name":"SS3 8XB",
    "wof:placetype":"postalcode"
},
  "geometry": {"coordinates":[0.78353154132837,51.53989519836035],"type":"Point"}
}