{
  "type": "Feature",
  "properties": {
    "iso:country": "GB",
    "wof:name": "SS3 8XB",
    "wof:placetype": "postalcode"
  },
  "geometry": {"coordinates":[0.783532,51.539895],"type":"Point"}
}
