{
  "type": "Feature",
  "properties": {
    "date:inception_lower": "2020-12-01",
    "date:inception_upper": "2020-12-01",
    "iso:country": "GB",
    "wof:name": "LE8 9HN",
    "wof:placetype": "postalcode"
  },
  "geometry": {"coordinates":[-1.021171,52.576543],"type":"Point"}
}
