{
  "type": "Feature",
  "properties": {
    "iso:country":"GB",
    "wof:name":"M26 1JE",
    "wof:placetype":"postalcode"
},
  "geometry": {"coordinates":[-2.31411281299668,53.55100079948348],"type":"Point"}
}