{
  "type": "Feature",
  "properties": {
    "date:inception_lower":"1980-01-01",
    "date:inception_upper":"1980-01-31",
    "iso:country":"GB",
    "wof:name":"SR8 3AJ",
    "wof:placetype":"postalcode"
},
  "geometry": {"coordinates":[-1.350149,54.782989],"type":"Point"}
}