{
  "type": "Feature",
  "properties": {
    "iso:country":"GB",
    "wof:name":"SR8 3AJ",
    "wof:placetype":"postalcode"
},
  "geometry": {"coordinates":[-1.35014884900914,54.78298897372177],"type":"Point"}
}