{
  "type": "Feature",
  "properties": {
    "iso:country":"GB",
    "wof:name":"TN15 8BP",
    "wof:placetype":"postalcode"
},
  "geometry": {"coordinates":[0.3054851909359,51.29208135300197],"type":"Point"}
}