{
  "type": "Feature",
  "properties": {
    "iso:country":"GB",
    "wof:name":"BS39 5BH",
    "wof:placetype":"postalcode"
},
  "geometry": {"coordinates":[-2.54308157212018,51.31819918983496],"type":"Point"}
}