{
  "type": "Feature",
  "properties": {
    "iso:country": "GB",
    "wof:name": "CH4 0LL",
    "wof:placetype": "postalcode"
  },
  "geometry": {"coordinates":[-3.040568,53.155778],"type":"Point"}
}
