{
  "type": "Feature",
  "properties": {
    "iso:country":"GB",
    "wof:name":"TQ5 0NN",
    "wof:placetype":"postalcode"
},
  "geometry": {"coordinates":[-3.56446470466693,50.39576143367717],"type":"Point"}
}