{
  "type": "Feature",
  "properties": {
    "iso:country": "GB",
    "wof:name": "TQ5 0NN",
    "wof:placetype": "postalcode"
  },
  "geometry": {"coordinates":[-3.564537,50.395736],"type":"Point"}
}
