{
  "type": "Feature",
  "properties": {
    "iso:country": "GB",
    "wof:name": "BN26 6NP",
    "wof:placetype": "postalcode"
  },
  "geometry": {"coordinates":[0.241019,50.82591],"type":"Point"}
}
