{
  "type": "Feature",
  "properties": {
    "iso:country":"GB",
    "wof:name":"SP3 4TF",
    "wof:placetype":"postalcode"
},
  "geometry": {"coordinates":[-1.89954797353003,51.16730126839802],"type":"Point"}
}