{
  "type": "Feature",
  "properties": {
    "date:inception_lower":"2018-05-01",
    "date:inception_upper":"2018-05-31",
    "iso:country":"GB",
    "wof:name":"LE12 7XX",
    "wof:placetype":"postalcode"
},
  "geometry": {"coordinates":[-1.15141,52.723627],"type":"Point"}
}