{
  "type": "Feature",
  "properties": {
    "iso:country": "GB",
    "wof:name": "BN14 8DF",
    "wof:placetype": "postalcode"
  },
  "geometry": {"coordinates":[-0.370775,50.820589],"type":"Point"}
}
