{
  "type": "Feature",
  "properties": {
    "date:inception_lower": "2021-05-01",
    "date:inception_upper": "2021-05-01",
    "iso:country": "GB",
    "wof:name": "PE12 7NW",
    "wof:placetype": "postalcode"
  },
  "geometry": {"coordinates":[0.006371,52.79827],"type":"Point"}
}
