{
  "type": "Feature",
  "properties": {
    "iso:country": "GB",
    "wof:name": "AB45 2YN",
    "wof:placetype": "postalcode"
  },
  "geometry": {"coordinates":[-2.688304,57.651608],"type":"Point"}
}
