{
  "type": "Feature",
  "properties": {
    "iso:country":"GB",
    "wof:name":"AB45 2YN",
    "wof:placetype":"postalcode"
},
  "geometry": {"coordinates":[-2.68830231250783,57.65162403016343],"type":"Point"}
}