{
  "type": "Feature",
  "properties": {
    "iso:country": "GB",
    "wof:name": "AB45 2YN",
    "wof:placetype": "postalcode"
  },
  "geometry": {"coordinates":[-2.693748,57.649773],"type":"Point"}
}
