{
  "type": "Feature",
  "properties": {
    "iso:country":"GB",
    "wof:name":"ML9 2TS",
    "wof:placetype":"postalcode"
},
  "geometry": {"coordinates":[-3.95661530988234,55.72260292903739],"type":"Point"}
}