{
  "type": "Feature",
  "properties": {
    "date:inception_lower": "2019-09-01",
    "date:inception_upper": "2019-09-01",
    "iso:country": "GB",
    "wof:name": "M30 0ZB",
    "wof:placetype": "postalcode"
  },
  "geometry": {"coordinates":[-2.345122,53.477892],"type":"Point"}
}
