{
  "type": "Feature",
  "properties": {
    "date:inception_lower": "1990-02-01",
    "date:inception_upper": "1990-02-01",
    "iso:country": "GB",
    "wof:name": "SK16 5BQ",
    "wof:placetype": "postalcode"
  },
  "geometry": {"coordinates":[-2.083125,53.466247],"type":"Point"}
}
