{
  "type": "Feature",
  "properties": {
    "iso:country":"GB",
    "wof:name":"SK16 5BQ",
    "wof:placetype":"postalcode"
},
  "geometry": {"coordinates":[-2.08312497059361,53.46624680417366],"type":"Point"}
}