{
  "type": "Feature",
  "properties": {
    "date:inception_lower":"1999-12-01",
    "date:inception_upper":"1999-12-31",
    "iso:country":"GB",
    "wof:name":"KT6 6RP",
    "wof:placetype":"postalcode"
},
  "geometry": {"coordinates":[-0.313514,51.387848],"type":"Point"}
}