{
  "type": "Feature",
  "properties": {
    "iso:country": "GB",
    "wof:name": "S5 7SD",
    "wof:placetype": "postalcode"
  },
  "geometry": {"coordinates":[-1.464162,53.424339],"type":"Point"}
}
