{
  "type": "Feature",
  "properties": {
    "iso:country":"GB",
    "wof:name":"CH6 5BS",
    "wof:placetype":"postalcode"
},
  "geometry": {"coordinates":[-3.1353857716844,53.24988625850477],"type":"Point"}
}