{
  "type": "Feature",
  "properties": {
    "iso:country":"GB",
    "wof:name":"OL8 3PF",
    "wof:placetype":"postalcode"
},
  "geometry": {"coordinates":[-2.12838261060295,53.51368352531395],"type":"Point"}
}