{
  "type": "Feature",
  "properties": {
    "iso:country": "GB",
    "wof:name": "DH8 9NG",
    "wof:placetype": "postalcode"
  },
  "geometry": {"coordinates":[-1.979953,54.841411],"type":"Point"}
}
