{
  "type": "Feature",
  "properties": {
    "date:inception_lower": "2000-06-01",
    "date:inception_upper": "2000-06-01",
    "iso:country": "GB",
    "wof:name": "ST2 0TD",
    "wof:placetype": "postalcode"
  },
  "geometry": {"coordinates":[-2.121778,53.003173],"type":"Point"}
}
