{
  "type": "Feature",
  "properties": {
    "iso:country":"GB",
    "wof:name":"E16 1FR",
    "wof:placetype":"postalcode"
},
  "geometry": {"coordinates":[0.03519013113048,51.50848784131912],"type":"Point"}
}