{
  "type": "Feature",
  "properties": {
    "iso:country": "GB",
    "wof:name": "E16 1FR",
    "wof:placetype": "postalcode"
  },
  "geometry": {"coordinates":[0.03519,51.508488],"type":"Point"}
}
