{
  "type": "Feature",
  "properties": {
    "iso:country":"GB",
    "wof:name":"TS9 7HE",
    "wof:placetype":"postalcode"
},
  "geometry": {"coordinates":[-1.15062561686976,54.44308850637517],"type":"Point"}
}