{
  "type": "Feature",
  "properties": {
    "date:inception_lower":"2001-12-01",
    "date:inception_upper":"2001-12-31",
    "iso:country":"GB",
    "wof:name":"TS9 7HE",
    "wof:placetype":"postalcode"
},
  "geometry": {"coordinates":[-1.15125,54.443348],"type":"Point"}
}