{
  "type": "Feature",
  "properties": {
    "date:inception_lower": "2001-12-01",
    "date:inception_upper": "2001-12-01",
    "iso:country": "GB",
    "wof:name": "TS9 7HE",
    "wof:placetype": "postalcode"
  },
  "geometry": {"coordinates":[-1.150638,54.443101],"type":"Point"}
}
