{
  "type": "Feature",
  "properties": {
    "iso:country": "GB",
    "wof:name": "TS9 7HE",
    "wof:placetype": "postalcode"
  },
  "geometry": {"coordinates":[-1.15125,54.443348],"type":"Point"}
}
