{
  "type": "Feature",
  "properties": {
    "iso:country": "GB",
    "wof:name": "SS5 4HJ",
    "wof:placetype": "postalcode"
  },
  "geometry": {"coordinates":[0.668782,51.598188],"type":"Point"}
}
