{
  "type": "Feature",
  "properties": {
    "iso:country":"GB",
    "wof:name":"SS5 4HJ",
    "wof:placetype":"postalcode"
},
  "geometry": {"coordinates":[0.66878159078358,51.59818815817701],"type":"Point"}
}