{
  "type": "Feature",
  "properties": {
    "date:inception_lower":"1980-01-01",
    "date:inception_upper":"1980-01-31",
    "iso:country":"GB",
    "wof:name":"SS5 4HJ",
    "wof:placetype":"postalcode"
},
  "geometry": {"coordinates":[0.668782,51.598188],"type":"Point"}
}