{
  "type": "Feature",
  "properties": {
    "iso:country":"GB",
    "wof:name":"RG6 1NN",
    "wof:placetype":"postalcode"
},
  "geometry": {"coordinates":[-0.93396206856781,51.44900458107044],"type":"Point"}
}