{
  "type": "Feature",
  "properties": {
    "iso:country": "GB",
    "wof:name": "RG6 1NN",
    "wof:placetype": "postalcode"
  },
  "geometry": {"coordinates":[-0.933962,51.449005],"type":"Point"}
}
