{
  "type": "Feature",
  "properties": {
    "iso:country":"GB",
    "wof:name":"BH23 3SQ",
    "wof:placetype":"postalcode"
},
  "geometry": {"coordinates":[-1.74813565192918,50.72847244553537],"type":"Point"}
}