{
  "type": "Feature",
  "properties": {
    "iso:country":"GB",
    "wof:name":"M35 9HZ",
    "wof:placetype":"postalcode"
},
  "geometry": {"coordinates":[-2.14300219812996,53.51131194155757],"type":"Point"}
}