{
  "type": "Feature",
  "properties": {
    "iso:country":"GB",
    "wof:name":"NG34 7UE",
    "wof:placetype":"postalcode"
},
  "geometry": {"coordinates":[-0.42392281320533,52.99379122486858],"type":"Point"}
}