{
  "type": "Feature",
  "properties": {
    "iso:country":"GB",
    "wof:name":"SP1 3DU",
    "wof:placetype":"postalcode"
},
  "geometry": {"coordinates":[-1.78262994145673,51.08434387000948],"type":"Point"}
}