{
  "type": "Feature",
  "properties": {
    "iso:country":"GB",
    "wof:name":"LA15 8TZ",
    "wof:placetype":"postalcode"
},
  "geometry": {"coordinates":[-3.18156459794618,54.15654696206599],"type":"Point"}
}