{
  "type": "Feature",
  "properties": {
    "iso:country": "GB",
    "wof:name": "WA14 5DW",
    "wof:placetype": "postalcode"
  },
  "geometry": {"coordinates":[-2.363833,53.396428],"type":"Point"}
}
