{
  "type": "Feature",
  "properties": {
    "date:inception_lower":"2016-07-01",
    "date:inception_upper":"2016-07-31",
    "iso:country":"GB",
    "wof:name":"SW1X 7DS",
    "wof:placetype":"postalcode"
},
  "geometry": {"coordinates":[-0.152708,51.501086],"type":"Point"}
}