{
  "type": "Feature",
  "properties": {
    "iso:country": "GB",
    "wof:name": "SW1X 7DS",
    "wof:placetype": "postalcode"
  },
  "geometry": {"coordinates":[-0.152708,51.501086],"type":"Point"}
}
