{
  "type": "Feature",
  "properties": {
    "iso:country": "GB",
    "wof:name": "IG11 9TQ",
    "wof:placetype": "postalcode"
  },
  "geometry": {"coordinates":[0.087977,51.539358],"type":"Point"}
}
