{
  "type": "Feature",
  "properties": {
    "iso:country":"GB",
    "wof:name":"WA8 8LR",
    "wof:placetype":"postalcode"
},
  "geometry": {"coordinates":[-2.77645260969355,53.34781419628821],"type":"Point"}
}