{
  "type": "Feature",
  "properties": {
    "iso:country":"GB",
    "wof:name":"MK45 4LA",
    "wof:placetype":"postalcode"
},
  "geometry": {"coordinates":[-0.42240285145123,51.96171273945124],"type":"Point"}
}