{
  "type": "Feature",
  "properties": {
    "iso:country": "GB",
    "wof:name": "MK45 4LA",
    "wof:placetype": "postalcode"
  },
  "geometry": {"coordinates":[-0.422403,51.961713],"type":"Point"}
}
