{
  "type": "Feature",
  "properties": {
    "iso:country":"GB",
    "wof:name":"G43 2NZ",
    "wof:placetype":"postalcode"
},
  "geometry": {"coordinates":[-4.27937343905126,55.81932326438761],"type":"Point"}
}