{
  "type": "Feature",
  "properties": {
    "iso:country":"GB",
    "wof:name":"CH44 6RA",
    "wof:placetype":"postalcode"
},
  "geometry": {"coordinates":[-3.02339526782205,53.41101385430621],"type":"Point"}
}