{
  "type": "Feature",
  "properties": {
    "iso:country":"GB",
    "wof:name":"E11 3DZ",
    "wof:placetype":"postalcode"
},
  "geometry": {"coordinates":[0.01368327319093,51.56617829920092],"type":"Point"}
}