{
  "type": "Feature",
  "properties": {
    "date:inception_lower": "1980-01-01",
    "date:inception_upper": "1980-01-01",
    "iso:country": "GB",
    "wof:name": "IP13 8HP",
    "wof:placetype": "postalcode"
  },
  "geometry": {"coordinates":[1.374017,52.276434],"type":"Point"}
}
