{
  "type": "Feature",
  "properties": {
    "iso:country": "GB",
    "wof:name": "IP13 8HP",
    "wof:placetype": "postalcode"
  },
  "geometry": {"coordinates":[1.373845,52.276286],"type":"Point"}
}
