{
  "type": "Feature",
  "properties": {
    "iso:country":"GB",
    "wof:name":"CV35 9PB",
    "wof:placetype":"postalcode"
},
  "geometry": {"coordinates":[-1.59150626295701,52.19816040665192],"type":"Point"}
}