{
  "type": "Feature",
  "properties": {
    "iso:country":"GB",
    "wof:name":"TN29 9EU",
    "wof:placetype":"postalcode"
},
  "geometry": {"coordinates":[0.90163483063604,50.94789306726609],"type":"Point"}
}