{
  "type": "Feature",
  "properties": {
    "iso:country": "GB",
    "wof:name": "TN29 9EU",
    "wof:placetype": "postalcode"
  },
  "geometry": {"coordinates":[0.901635,50.947893],"type":"Point"}
}
