{
  "type": "Feature",
  "properties": {
    "iso:country":"GB",
    "wof:name":"LA5 9NW",
    "wof:placetype":"postalcode"
},
  "geometry": {"coordinates":[-2.77658314923571,54.14084066412188],"type":"Point"}
}