{
  "type": "Feature",
  "properties": {
    "date:inception_lower": "1980-01-01",
    "date:inception_upper": "1980-01-01",
    "iso:country": "GB",
    "wof:name": "ST5 0NU",
    "wof:placetype": "postalcode"
  },
  "geometry": {"coordinates":[-2.217049,53.021941],"type":"Point"}
}
