{
  "type": "Feature",
  "properties": {
    "iso:country":"GB",
    "wof:name":"ST5 0NU",
    "wof:placetype":"postalcode"
},
  "geometry": {"coordinates":[-2.21704859359345,53.02194110971925],"type":"Point"}
}