{
  "type": "Feature",
  "properties": {
    "iso:country": "GB",
    "wof:name": "NR24 2PN",
    "wof:placetype": "postalcode"
  },
  "geometry": {"coordinates":[1.024213,52.890862],"type":"Point"}
}
