{
  "type": "Feature",
  "properties": {
    "iso:country":"GB",
    "wof:name":"NR24 2PN",
    "wof:placetype":"postalcode"
},
  "geometry": {"coordinates":[1.02421253035018,52.89086218135563],"type":"Point"}
}