{
  "type": "Feature",
  "properties": {
    "iso:country":"GB",
    "wof:name":"PO32 6HS",
    "wof:placetype":"postalcode"
},
  "geometry": {"coordinates":[-1.28168184787557,50.74816961322504],"type":"Point"}
}