{
  "type": "Feature",
  "properties": {
    "iso:country":"GB",
    "wof:name":"BS6 7RQ",
    "wof:placetype":"postalcode"
},
  "geometry": {"coordinates":[-2.60691932124351,51.47762378259877],"type":"Point"}
}