{
  "type": "Feature",
  "properties": {
    "iso:country":"GB",
    "wof:name":"B68 9QU",
    "wof:placetype":"postalcode"
},
  "geometry": {"coordinates":[-2.00092823612191,52.48857461789802],"type":"Point"}
}