{
  "type": "Feature",
  "properties": {
    "date:inception_lower":"2007-03-01",
    "date:inception_upper":"2007-03-31",
    "iso:country":"GB",
    "wof:name":"BL6 6TR",
    "wof:placetype":"postalcode"
},
  "geometry": {"coordinates":[-2.524583,53.601712],"type":"Point"}
}