{
  "type": "Feature",
  "properties": {
    "iso:country":"GB",
    "wof:name":"BL6 6TR",
    "wof:placetype":"postalcode"
},
  "geometry": {"coordinates":[-2.52458344108231,53.60171201990455],"type":"Point"}
}