{
  "type": "Feature",
  "properties": {
    "iso:country": "GB",
    "wof:name": "BL6 6TR",
    "wof:placetype": "postalcode"
  },
  "geometry": {"coordinates":[-2.524583,53.601712],"type":"Point"}
}
