{
  "type": "Feature",
  "properties": {
    "date:inception_lower":"2001-06-01",
    "date:inception_upper":"2001-06-30",
    "iso:country":"GB",
    "wof:name":"CF31 5ED",
    "wof:placetype":"postalcode"
},
  "geometry": {"coordinates":[-3.591523,51.501816],"type":"Point"}
}