{
  "type": "Feature",
  "properties": {
    "iso:country":"GB",
    "wof:name":"CF31 5ED",
    "wof:placetype":"postalcode"
},
  "geometry": {"coordinates":[-3.59152286346731,51.50181568429282],"type":"Point"}
}