{
  "type": "Feature",
  "properties": {
    "iso:country": "GB",
    "wof:name": "CF31 5ED",
    "wof:placetype": "postalcode"
  },
  "geometry": {"coordinates":[-3.591523,51.501816],"type":"Point"}
}
