{
  "type": "Feature",
  "properties": {
    "iso:country": "GB",
    "wof:name": "BH16 5FJ",
    "wof:placetype": "postalcode"
  },
  "geometry": {"coordinates":[-2.023608,50.737158],"type":"Point"}
}
