{
  "type": "Feature",
  "properties": {
    "date:inception_lower": "2022-08-01",
    "date:inception_upper": "2022-08-01",
    "iso:country": "GB",
    "wof:name": "TA14 6AD",
    "wof:placetype": "postalcode"
  },
  "geometry": {"coordinates":[-2.753818,50.954891],"type":"Point"}
}
