{
  "type": "Feature",
  "properties": {
    "date:inception_lower": "1980-01-01",
    "date:inception_upper": "1980-01-01",
    "iso:country": "GB",
    "wof:name": "NG14 5EY",
    "wof:placetype": "postalcode"
  },
  "geometry": {"coordinates":[-1.03296,52.987808],"type":"Point"}
}
