{
  "type": "Feature",
  "properties": {
    "iso:country":"GB",
    "wof:name":"BH4 8HZ",
    "wof:placetype":"postalcode"
},
  "geometry": {"coordinates":[-1.89935931024349,50.71243293044835],"type":"Point"}
}