{
  "type": "Feature",
  "properties": {
    "date:inception_lower": "2016-02-01",
    "date:inception_upper": "2016-02-01",
    "iso:country": "GB",
    "wof:name": "W12 7FJ",
    "wof:placetype": "postalcode"
  },
  "geometry": {"coordinates":[-0.23522,51.510845],"type":"Point"}
}
