{
  "type": "Feature",
  "properties": {
    "iso:country":"GB",
    "wof:name":"E14 8HY",
    "wof:placetype":"postalcode"
},
  "geometry": {"coordinates":[-0.02286934042244,51.51052416932409],"type":"Point"}
}