{
  "type": "Feature",
  "properties": {
    "iso:country":"GB",
    "wof:name":"B29 6TQ",
    "wof:placetype":"postalcode"
},
  "geometry": {"coordinates":[-1.94356301362316,52.44522959178229],"type":"Point"}
}