{
  "type": "Feature",
  "properties": {
    "iso:country": "GB",
    "wof:name": "B96 6NH",
    "wof:placetype": "postalcode"
  },
  "geometry": {"coordinates":[-1.93787,52.239527],"type":"Point"}
}
