{
  "type": "Feature",
  "properties": {
    "date:inception_lower": "1992-01-01",
    "date:inception_upper": "1992-01-01",
    "iso:country": "GB",
    "wof:name": "B96 6NH",
    "wof:placetype": "postalcode"
  },
  "geometry": {"coordinates":[-1.937797,52.239545],"type":"Point"}
}
