{
  "type": "Feature",
  "properties": {
    "iso:country":"GB",
    "wof:name":"B96 6NH",
    "wof:placetype":"postalcode"
},
  "geometry": {"coordinates":[-1.93787748054785,52.23951368845423],"type":"Point"}
}