{
  "type": "Feature",
  "properties": {
    "iso:country":"GB",
    "wof:name":"LS11 7JF",
    "wof:placetype":"postalcode"
},
  "geometry": {"coordinates":[-1.56035067027373,53.77256247629285],"type":"Point"}
}