{
  "type": "Feature",
  "properties": {
    "iso:country":"GB",
    "wof:name":"GU33 7AE",
    "wof:placetype":"postalcode"
},
  "geometry": {"coordinates":[-0.89495409342934,51.0427887819842],"type":"Point"}
}