{
  "type": "Feature",
  "properties": {
    "iso:country":"GB",
    "wof:name":"SY9 5AX",
    "wof:placetype":"postalcode"
},
  "geometry": {"coordinates":[-2.99524925111802,52.48934021109879],"type":"Point"}
}