{
  "type": "Feature",
  "properties": {
    "iso:country":"GB",
    "wof:name":"BR7 5PX",
    "wof:placetype":"postalcode"
},
  "geometry": {"coordinates":[0.07563170041475,51.40832718444359],"type":"Point"}
}