{
  "type": "Feature",
  "properties": {
    "date:inception_lower": "1980-01-01",
    "date:inception_upper": "1980-01-01",
    "iso:country": "GB",
    "wof:name": "KY6 2BA",
    "wof:placetype": "postalcode"
  },
  "geometry": {"coordinates":[-3.179897,56.190959],"type":"Point"}
}
