{
  "type": "Feature",
  "properties": {
    "date:inception_lower": "1980-01-01",
    "date:inception_upper": "1980-01-01",
    "iso:country": "GB",
    "wof:name": "FK1 1SZ",
    "wof:placetype": "postalcode"
  },
  "geometry": {"coordinates":[-3.772294,55.998707],"type":"Point"}
}
