{
  "type": "Feature",
  "properties": {
    "iso:country":"GB",
    "wof:name":"WF3 1AL",
    "wof:placetype":"postalcode"
},
  "geometry": {"coordinates":[-1.57714800617659,53.72560609430945],"type":"Point"}
}