{
  "type": "Feature",
  "properties": {
    "iso:country":"GB",
    "wof:name":"NE15 6TA",
    "wof:placetype":"postalcode"
},
  "geometry": {"coordinates":[-1.68024644413265,54.97402761439674],"type":"Point"}
}