{
  "type": "Feature",
  "properties": {
    "date:inception_lower": "1980-01-01",
    "date:inception_upper": "1980-01-01",
    "iso:country": "GB",
    "wof:name": "NE30 2BS",
    "wof:placetype": "postalcode"
  },
  "geometry": {"coordinates":[-1.447358,55.016606],"type":"Point"}
}
