{
  "type": "Feature",
  "properties": {
    "iso:country": "GB",
    "wof:name": "NE30 2BS",
    "wof:placetype": "postalcode"
  },
  "geometry": {"coordinates":[-1.447358,55.016606],"type":"Point"}
}
