{
  "type": "Feature",
  "properties": {
    "iso:country":"GB",
    "wof:name":"KA4 8DW",
    "wof:placetype":"postalcode"
},
  "geometry": {"coordinates":[-4.38419326152445,55.59988071362112],"type":"Point"}
}