{
  "type": "Feature",
  "properties": {
    "iso:country":"GB",
    "wof:name":"NG3 1NU",
    "wof:placetype":"postalcode"
},
  "geometry": {"coordinates":[-1.14031308039173,52.96041441227358],"type":"Point"}
}