{
  "type": "Feature",
  "properties": {
    "date:inception_lower":"1980-01-01",
    "date:inception_upper":"1980-01-31",
    "iso:country":"GB",
    "wof:name":"IP13 0BZ",
    "wof:placetype":"postalcode"
},
  "geometry": {"coordinates":[1.397737,52.167109],"type":"Point"}
}