{
  "type": "Feature",
  "properties": {
    "iso:country": "GB",
    "wof:name": "IP13 0BZ",
    "wof:placetype": "postalcode"
  },
  "geometry": {"coordinates":[1.397737,52.167109],"type":"Point"}
}
