{
  "type": "Feature",
  "properties": {
    "iso:country":"GB",
    "wof:name":"IP13 0BZ",
    "wof:placetype":"postalcode"
},
  "geometry": {"coordinates":[1.39770577518771,52.16709159127528],"type":"Point"}
}