{
  "type": "Feature",
  "properties": {
    "iso:country":"GB",
    "wof:name":"G64 2AF",
    "wof:placetype":"postalcode"
},
  "geometry": {"coordinates":[-4.23393066726816,55.90125078216953],"type":"Point"}
}