{
  "type": "Feature",
  "properties": {
    "date:inception_lower": "2022-11-01",
    "date:inception_upper": "2022-11-01",
    "iso:country": "GB",
    "wof:name": "NG12 4LY",
    "wof:placetype": "postalcode"
  },
  "geometry": {"coordinates":[-1.121305,52.903509],"type":"Point"}
}
