{
  "type": "Feature",
  "properties": {
    "iso:country":"GB",
    "wof:name":"HR2 9AR",
    "wof:placetype":"postalcode"
},
  "geometry": {"coordinates":[-2.79860134849479,52.00472231210174],"type":"Point"}
}