{
  "type": "Feature",
  "properties": {
    "iso:country":"GB",
    "wof:name":"LA3 1HP",
    "wof:placetype":"postalcode"
},
  "geometry": {"coordinates":[-2.88488282154331,54.05967900344042],"type":"Point"}
}