{
  "type": "Feature",
  "properties": {
    "iso:country":"GB",
    "wof:name":"RG4 7BS",
    "wof:placetype":"postalcode"
},
  "geometry": {"coordinates":[-0.98635238706537,51.47461929848641],"type":"Point"}
}