{
  "type": "Feature",
  "properties": {
    "iso:country":"GB",
    "wof:name":"TN39 4BS",
    "wof:placetype":"postalcode"
},
  "geometry": {"coordinates":[0.46429172088567,50.85618655683515],"type":"Point"}
}