{
  "type": "Feature",
  "properties": {
    "date:inception_lower": "2016-10-01",
    "date:inception_upper": "2016-10-01",
    "iso:country": "GB",
    "wof:name": "DA10 1BQ",
    "wof:placetype": "postalcode"
  },
  "geometry": {"coordinates":[0.310267,51.437453],"type":"Point"}
}
