{
  "type": "Feature",
  "properties": {
    "date:inception_lower": "2016-10-01",
    "date:inception_upper": "2016-10-01",
    "iso:country": "GB",
    "wof:name": "NG22 0DU",
    "wof:placetype": "postalcode"
  },
  "geometry": {"coordinates":[-0.898589,53.23165],"type":"Point"}
}
