{
  "type": "Feature",
  "properties": {
    "iso:country":"GB",
    "wof:name":"W6 8DG",
    "wof:placetype":"postalcode"
},
  "geometry": {"coordinates":[-0.21670404150473,51.4838485668818],"type":"Point"}
}