{
  "type": "Feature",
  "properties": {
    "date:inception_lower": "1996-12-01",
    "date:inception_upper": "1996-12-01",
    "iso:country": "GB",
    "wof:name": "W6 8DG",
    "wof:placetype": "postalcode"
  },
  "geometry": {"coordinates":[-0.216704,51.483849],"type":"Point"}
}
