{
  "type": "Feature",
  "properties": {
    "iso:country":"GB",
    "wof:name":"SW20 9LR",
    "wof:placetype":"postalcode"
},
  "geometry": {"coordinates":[-0.23424679441055,51.40176071747029],"type":"Point"}
}