{
  "type": "Feature",
  "properties": {
    "date:inception_lower": "1980-01-01",
    "date:inception_upper": "1980-01-01",
    "iso:country": "GB",
    "wof:name": "LN5 0RB",
    "wof:placetype": "postalcode"
  },
  "geometry": {"coordinates":[-0.664263,53.068152],"type":"Point"}
}
