{
  "type": "Feature",
  "properties": {
    "iso:country":"GB",
    "wof:name":"LN5 0RB",
    "wof:placetype":"postalcode"
},
  "geometry": {"coordinates":[-0.6645595910769,53.07219748993937],"type":"Point"}
}