{
  "type": "Feature",
  "properties": {
    "iso:country": "GB",
    "wof:name": "EX10 9XX",
    "wof:placetype": "postalcode"
  },
  "geometry": {"coordinates":[-3.239207,50.700051],"type":"Point"}
}
