{
  "type": "Feature",
  "properties": {
    "iso:country":"GB",
    "wof:name":"LU3 1ED",
    "wof:placetype":"postalcode"
},
  "geometry": {"coordinates":[-0.42393589778569,51.88559221343087],"type":"Point"}
}