{
  "type": "Feature",
  "properties": {
    "date:inception_lower":"2002-11-01",
    "date:inception_upper":"2002-11-30",
    "iso:country":"GB",
    "wof:name":"PL5 3UN",
    "wof:placetype":"postalcode"
},
  "geometry": {"coordinates":[-4.14317,50.405693],"type":"Point"}
}