{
  "type": "Feature",
  "properties": {
    "iso:country":"GB",
    "wof:name":"PL5 3UN",
    "wof:placetype":"postalcode"
},
  "geometry": {"coordinates":[-4.14317044000544,50.40569286839336],"type":"Point"}
}