{
  "type": "Feature",
  "properties": {
    "iso:country":"GB",
    "wof:name":"HP7 0DT",
    "wof:placetype":"postalcode"
},
  "geometry": {"coordinates":[-0.61890289120293,51.66716213589181],"type":"Point"}
}