{
  "type": "Feature",
  "properties": {
    "date:inception_lower": "1980-01-01",
    "date:inception_upper": "1980-01-01",
    "iso:country": "GB",
    "wof:name": "HP7 0DT",
    "wof:placetype": "postalcode"
  },
  "geometry": {"coordinates":[-0.618903,51.667162],"type":"Point"}
}
