{
  "type": "Feature",
  "properties": {
    "iso:country":"GB",
    "wof:name":"RM13 9RZ",
    "wof:placetype":"postalcode"
},
  "geometry": {"coordinates":[0.21406561170198,51.52197390330301],"type":"Point"}
}