{
  "type": "Feature",
  "properties": {
    "date:inception_lower": "1980-01-01",
    "date:inception_upper": "1980-01-01",
    "iso:country": "GB",
    "wof:name": "RM13 9RZ",
    "wof:placetype": "postalcode"
  },
  "geometry": {"coordinates":[0.214181,51.521991],"type":"Point"}
}
