{
  "type": "Feature",
  "properties": {
    "iso:country":"GB",
    "wof:name":"LN11 0BY",
    "wof:placetype":"postalcode"
},
  "geometry": {"coordinates":[0.00810248974509,53.37130567370237],"type":"Point"}
}