{
  "type": "Feature",
  "properties": {
    "date:inception_lower": "1980-01-01",
    "date:inception_upper": "1980-01-01",
    "iso:country": "GB",
    "wof:name": "LN11 0BY",
    "wof:placetype": "postalcode"
  },
  "geometry": {"coordinates":[0.007927,53.371136],"type":"Point"}
}
