{
  "type": "Feature",
  "properties": {
    "iso:country": "GB",
    "wof:name": "PE31 8WA",
    "wof:placetype": "postalcode"
  },
  "geometry": {"coordinates":[0.624271,52.902239],"type":"Point"}
}
