{
  "type": "Feature",
  "properties": {
    "date:inception_lower": "2017-11-01",
    "date:inception_upper": "2017-11-01",
    "iso:country": "GB",
    "wof:name": "S1 4TP",
    "wof:placetype": "postalcode"
  },
  "geometry": {"coordinates":[-1.470152,53.375863],"type":"Point"}
}
