{
  "type": "Feature",
  "properties": {
    "iso:country":"GB",
    "wof:name":"M44 5FP",
    "wof:placetype":"postalcode"
},
  "geometry": {"coordinates":[-2.44454582808014,53.42821740465006],"type":"Point"}
}