{
  "type": "Feature",
  "properties": {
    "iso:country":"GB",
    "wof:name":"W10 5FR",
    "wof:placetype":"postalcode"
},
  "geometry": {"coordinates":[-0.20658117582549,51.52489756784272],"type":"Point"}
}