{
  "type": "Feature",
  "properties": {
    "iso:country": "GB",
    "wof:name": "DE55 2FJ",
    "wof:placetype": "postalcode"
  },
  "geometry": {"coordinates":[-1.324898,53.106576],"type":"Point"}
}
