{
  "type": "Feature",
  "properties": {
    "iso:country":"GB",
    "wof:name":"TS19 8WJ",
    "wof:placetype":"postalcode"
},
  "geometry": {"coordinates":[-1.35153680372897,54.58706588122175],"type":"Point"}
}