{
  "type": "Feature",
  "properties": {
    "date:inception_lower": "2010-05-01",
    "date:inception_upper": "2010-05-01",
    "iso:country": "GB",
    "wof:name": "TS19 8WJ",
    "wof:placetype": "postalcode"
  },
  "geometry": {"coordinates":[-1.351537,54.587066],"type":"Point"}
}
