{
  "type": "Feature",
  "properties": {
    "iso:country": "GB",
    "wof:name": "TS19 8WJ",
    "wof:placetype": "postalcode"
  },
  "geometry": {"coordinates":[-1.351537,54.587066],"type":"Point"}
}
