{
  "type": "Feature",
  "properties": {
    "iso:country":"GB",
    "wof:name":"OL11 2RS",
    "wof:placetype":"postalcode"
},
  "geometry": {"coordinates":[-2.15836379611226,53.59498293493952],"type":"Point"}
}