{
  "type": "Feature",
  "properties": {
    "iso:country":"GB",
    "wof:name":"W1U 1BS",
    "wof:placetype":"postalcode"
},
  "geometry": {"coordinates":[-0.15095101713009,51.51529315105164],"type":"Point"}
}