{
  "type": "Feature",
  "properties": {
    "iso:country":"GB",
    "wof:name":"NR33 9HZ",
    "wof:placetype":"postalcode"
},
  "geometry": {"coordinates":[1.71655509350223,52.45878009717059],"type":"Point"}
}