{
  "type": "Feature",
  "properties": {
    "iso:country":"GB",
    "wof:name":"PL4 7EB",
    "wof:placetype":"postalcode"
},
  "geometry": {"coordinates":[-4.13274293459065,50.38126708784018],"type":"Point"}
}