{
  "type": "Feature",
  "properties": {
    "iso:country":"GB",
    "wof:name":"DN21 3PT",
    "wof:placetype":"postalcode"
},
  "geometry": {"coordinates":[-0.72281276405722,53.46785754782528],"type":"Point"}
}