{
  "type": "Feature",
  "properties": {
    "iso:country": "GB",
    "wof:name": "SW19 8DJ",
    "wof:placetype": "postalcode"
  },
  "geometry": {"coordinates":[-0.199364,51.437371],"type":"Point"}
}
