{
  "type": "Feature",
  "properties": {
    "date:inception_lower": "1980-01-01",
    "date:inception_upper": "1980-01-01",
    "iso:country": "GB",
    "wof:name": "SW19 8DJ",
    "wof:placetype": "postalcode"
  },
  "geometry": {"coordinates":[-0.199385,51.437327],"type":"Point"}
}
