{
  "type": "Feature",
  "properties": {
    "iso:country":"GB",
    "wof:name":"SW19 8DJ",
    "wof:placetype":"postalcode"
},
  "geometry": {"coordinates":[-0.19936429216848,51.43737106163342],"type":"Point"}
}