{
  "type": "Feature",
  "properties": {
    "iso:country":"GB",
    "wof:name":"FK6 5JJ",
    "wof:placetype":"postalcode"
},
  "geometry": {"coordinates":[-4.00489279584609,56.04224267153619],"type":"Point"}
}