{
  "type": "Feature",
  "properties": {
    "iso:country": "GB",
    "wof:name": "GL2 2DH",
    "wof:placetype": "postalcode"
  },
  "geometry": {"coordinates":[-2.26714,51.82375],"type":"Point"}
}
