{
  "type": "Feature",
  "properties": {
    "iso:country":"GB",
    "wof:name":"GL2 2DH",
    "wof:placetype":"postalcode"
},
  "geometry": {"coordinates":[-2.26713989596828,51.8237502360526],"type":"Point"}
}