{
  "type": "Feature",
  "properties": {
    "date:inception_lower": "2006-09-01",
    "date:inception_upper": "2006-09-01",
    "iso:country": "GB",
    "wof:name": "GL2 2DH",
    "wof:placetype": "postalcode"
  },
  "geometry": {"coordinates":[-2.26714,51.82375],"type":"Point"}
}
