{
  "type": "Feature",
  "properties": {
    "iso:country":"GB",
    "wof:name":"SR2 8BL",
    "wof:placetype":"postalcode"
},
  "geometry": {"coordinates":[-1.36796606931781,54.90171479392437],"type":"Point"}
}