{
  "type": "Feature",
  "properties": {
    "date:inception_lower": "1980-01-01",
    "date:inception_upper": "1980-01-01",
    "iso:country": "GB",
    "wof:name": "SR2 8BL",
    "wof:placetype": "postalcode"
  },
  "geometry": {"coordinates":[-1.368194,54.901967],"type":"Point"}
}
