{
  "type": "Feature",
  "properties": {
    "iso:country":"GB",
    "wof:name":"TA18 7LU",
    "wof:placetype":"postalcode"
},
  "geometry": {"coordinates":[-2.79510018706573,50.8846266924191],"type":"Point"}
}