{
  "type": "Feature",
  "properties": {
    "date:inception_lower":"1980-01-01",
    "date:inception_upper":"1980-01-31",
    "iso:country":"GB",
    "wof:name":"GU5 0EQ",
    "wof:placetype":"postalcode"
},
  "geometry": {"coordinates":[-0.548498,51.187694],"type":"Point"}
}