{
  "type": "Feature",
  "properties": {
    "iso:country":"GB",
    "wof:name":"GU5 0EQ",
    "wof:placetype":"postalcode"
},
  "geometry": {"coordinates":[-0.54849794334709,51.18769355177903],"type":"Point"}
}