{
  "type": "Feature",
  "properties": {
    "iso:country":"GB",
    "wof:name":"CF32 8NF",
    "wof:placetype":"postalcode"
},
  "geometry": {"coordinates":[-3.58699115063181,51.62008791433433],"type":"Point"}
}