{
  "type": "Feature",
  "properties": {
    "iso:country": "GB",
    "wof:name": "S21 5RS",
    "wof:placetype": "postalcode"
  },
  "geometry": {"coordinates":[-1.395646,53.307491],"type":"Point"}
}
