{
  "type": "Feature",
  "properties": {
    "iso:country": "GB",
    "wof:name": "TS7 8SH",
    "wof:placetype": "postalcode"
  },
  "geometry": {"coordinates":[-1.209368,54.535534],"type":"Point"}
}
