{
  "type": "Feature",
  "properties": {
    "iso:country":"GB",
    "wof:name":"TS7 8SH",
    "wof:placetype":"postalcode"
},
  "geometry": {"coordinates":[-1.2093675588222,54.53553386342853],"type":"Point"}
}