{
  "type": "Feature",
  "properties": {
    "iso:country":"GB",
    "wof:name":"PO7 5NN",
    "wof:placetype":"postalcode"
},
  "geometry": {"coordinates":[-1.037397221787,50.87051004710781],"type":"Point"}
}