{
  "type": "Feature",
  "properties": {
    "iso:country":"GB",
    "wof:name":"S2 2RE",
    "wof:placetype":"postalcode"
},
  "geometry": {"coordinates":[-1.44645257366674,53.37200743055838],"type":"Point"}
}