{
  "type": "Feature",
  "properties": {
    "date:inception_lower": "1980-01-01",
    "date:inception_upper": "1980-01-01",
    "iso:country": "GB",
    "wof:name": "EX37 9SS",
    "wof:placetype": "postalcode"
  },
  "geometry": {"coordinates":[-3.877243,50.959194],"type":"Point"}
}
