{
  "type": "Feature",
  "properties": {
    "iso:country": "GB",
    "wof:name": "CV10 9GH",
    "wof:placetype": "postalcode"
  },
  "geometry": {"coordinates":[-1.507624,52.530792],"type":"Point"}
}
