{
  "type": "Feature",
  "properties": {
    "iso:country":"GB",
    "wof:name":"SG14 2JQ",
    "wof:placetype":"postalcode"
},
  "geometry": {"coordinates":[-0.10556396335245,51.80410441162805],"type":"Point"}
}