{
  "type": "Feature",
  "properties": {
    "date:inception_lower":"1994-12-01",
    "date:inception_upper":"1994-12-31",
    "iso:country":"GB",
    "wof:name":"SG14 2JQ",
    "wof:placetype":"postalcode"
},
  "geometry": {"coordinates":[-0.105564,51.804104],"type":"Point"}
}