{
  "type": "Feature",
  "properties": {
    "date:inception_lower":"2000-06-01",
    "date:inception_upper":"2000-06-30",
    "iso:country":"GB",
    "wof:name":"PE27 3HH",
    "wof:placetype":"postalcode"
},
  "geometry": {"coordinates":[-0.074914,52.340427],"type":"Point"}
}