{
  "type": "Feature",
  "properties": {
    "iso:country":"GB",
    "wof:name":"PE27 3HH",
    "wof:placetype":"postalcode"
},
  "geometry": {"coordinates":[-0.07491360797563,52.34042715372895],"type":"Point"}
}