{
  "type": "Feature",
  "properties": {
    "iso:country":"GB",
    "wof:name":"NG18 3AD",
    "wof:placetype":"postalcode"
},
  "geometry": {"coordinates":[-1.17482960024675,53.14358309903339],"type":"Point"}
}