{
  "type": "Feature",
  "properties": {
    "date:inception_lower": "1992-01-01",
    "date:inception_upper": "1992-01-01",
    "iso:country": "GB",
    "wof:name": "OL8 2EH",
    "wof:placetype": "postalcode"
  },
  "geometry": {"coordinates":[-2.085224,53.528634],"type":"Point"}
}
