{
  "type": "Feature",
  "properties": {
    "iso:country":"GB",
    "wof:name":"CT6 7UE",
    "wof:placetype":"postalcode"
},
  "geometry": {"coordinates":[1.13878542725732,51.35465610378472],"type":"Point"}
}