{
  "type": "Feature",
  "properties": {
    "iso:country":"GB",
    "wof:name":"S3 7RL",
    "wof:placetype":"postalcode"
},
  "geometry": {"coordinates":[-1.4844362748542,53.38050096823012],"type":"Point"}
}