{
  "type": "Feature",
  "properties": {
    "iso:country": "GB",
    "wof:name": "M40 7WZ",
    "wof:placetype": "postalcode"
  },
  "geometry": {"coordinates":[-2.221139,53.490385],"type":"Point"}
}
