{
  "type": "Feature",
  "properties": {
    "iso:country":"GB",
    "wof:name":"M40 7WZ",
    "wof:placetype":"postalcode"
},
  "geometry": {"coordinates":[-2.22113887306048,53.49038457611153],"type":"Point"}
}