{
  "type": "Feature",
  "properties": {
    "iso:country": "GB",
    "wof:name": "SK6 4PF",
    "wof:placetype": "postalcode"
  },
  "geometry": {"coordinates":[-2.08578,53.415846],"type":"Point"}
}
