{
  "type": "Feature",
  "properties": {
    "iso:country":"GB",
    "wof:name":"EH22 3BP",
    "wof:placetype":"postalcode"
},
  "geometry": {"coordinates":[-3.08235634559009,55.88993907635913],"type":"Point"}
}