{
  "type": "Feature",
  "properties": {
    "iso:country": "GB",
    "wof:name": "TA3 5NX",
    "wof:placetype": "postalcode"
  },
  "geometry": {"coordinates":[-3.027683,51.01805],"type":"Point"}
}
