{
  "type": "Feature",
  "properties": {
    "iso:country": "GB",
    "wof:name": "BR3 4JT",
    "wof:placetype": "postalcode"
  },
  "geometry": {"coordinates":[-0.042085,51.40511],"type":"Point"}
}
