{
  "type": "Feature",
  "properties": {
    "iso:country":"GB",
    "wof:name":"LS12 1DL",
    "wof:placetype":"postalcode"
},
  "geometry": {"coordinates":[-1.56166527954784,53.79493855691512],"type":"Point"}
}