{
  "type": "Feature",
  "properties": {
    "iso:country": "GB",
    "wof:name": "LS12 1DL",
    "wof:placetype": "postalcode"
  },
  "geometry": {"coordinates":[-1.561665,53.794939],"type":"Point"}
}
