{
  "type": "Feature",
  "properties": {
    "date:inception_lower": "2023-10-01",
    "date:inception_upper": "2023-10-01",
    "iso:country": "GB",
    "wof:name": "BH22 8FX",
    "wof:placetype": "postalcode"
  },
  "geometry": {"coordinates":[-1.879135,50.780694],"type":"Point"}
}
