{
  "type": "Feature",
  "properties": {
    "iso:country":"GB",
    "wof:name":"DA7 6HR",
    "wof:placetype":"postalcode"
},
  "geometry": {"coordinates":[0.15504387104158,51.46444859681465],"type":"Point"}
}