{
  "type": "Feature",
  "properties": {
    "iso:country": "GB",
    "wof:name": "DY14 9AD",
    "wof:placetype": "postalcode"
  },
  "geometry": {"coordinates":[-2.484426,52.342005],"type":"Point"}
}
