{
  "type": "Feature",
  "properties": {
    "date:inception_lower": "1980-01-01",
    "date:inception_upper": "1980-01-01",
    "iso:country": "GB",
    "wof:name": "DY14 9AD",
    "wof:placetype": "postalcode"
  },
  "geometry": {"coordinates":[-2.484426,52.342005],"type":"Point"}
}
