{
  "type": "Feature",
  "properties": {
    "iso:country":"GB",
    "wof:name":"DY14 9AD",
    "wof:placetype":"postalcode"
},
  "geometry": {"coordinates":[-2.48442625953258,52.34200457642807],"type":"Point"}
}