{
  "type": "Feature",
  "properties": {
    "iso:country":"GB",
    "wof:name":"S20 1FP",
    "wof:placetype":"postalcode"
},
  "geometry": {"coordinates":[-1.34743231877318,53.34358824121684],"type":"Point"}
}