{
  "type": "Feature",
  "properties": {
    "date:inception_lower": "2021-08-01",
    "date:inception_upper": "2021-08-01",
    "iso:country": "GB",
    "wof:name": "DH5 0AP",
    "wof:placetype": "postalcode"
  },
  "geometry": {"coordinates":[-1.446342,54.810579],"type":"Point"}
}
