{
  "type": "Feature",
  "properties": {
    "iso:country":"GB",
    "wof:name":"NG22 8DP",
    "wof:placetype":"postalcode"
},
  "geometry": {"coordinates":[-1.02988153069333,53.10585927454409],"type":"Point"}
}