{
  "type": "Feature",
  "properties": {
    "date:inception_lower": "2001-12-01",
    "date:inception_upper": "2001-12-01",
    "iso:country": "GB",
    "wof:name": "EH13 0QT",
    "wof:placetype": "postalcode"
  },
  "geometry": {"coordinates":[-3.263337,55.90562],"type":"Point"}
}
