{
  "type": "Feature",
  "properties": {
    "iso:country":"GB",
    "wof:name":"EH13 0QT",
    "wof:placetype":"postalcode"
},
  "geometry": {"coordinates":[-3.26333688792285,55.90561985480161],"type":"Point"}
}