{
  "type": "Feature",
  "properties": {
    "iso:country": "GB",
    "wof:name": "RH2 2SL",
    "wof:placetype": "postalcode"
  },
  "geometry": {"coordinates":[-0.20508,51.239539],"type":"Point"}
}
