{
  "type": "Feature",
  "properties": {
    "iso:country":"GB",
    "wof:name":"IP33 3GH",
    "wof:placetype":"postalcode"
},
  "geometry": {"coordinates":[0.7052657462315,52.24876643707378],"type":"Point"}
}