{
  "type": "Feature",
  "properties": {
    "iso:country":"GB",
    "wof:name":"DY13 9SF",
    "wof:placetype":"postalcode"
},
  "geometry": {"coordinates":[-2.25210500244771,52.31226131486647],"type":"Point"}
}