{
  "type": "Feature",
  "properties": {
    "date:inception_lower": "1980-01-01",
    "date:inception_upper": "1980-01-01",
    "iso:country": "GB",
    "wof:name": "DY13 9SF",
    "wof:placetype": "postalcode"
  },
  "geometry": {"coordinates":[-2.252101,52.312275],"type":"Point"}
}
