{
  "type": "Feature",
  "properties": {
    "date:inception_lower": "1980-01-01",
    "date:inception_upper": "1980-01-01",
    "iso:country": "GB",
    "wof:name": "PO16 9LL",
    "wof:placetype": "postalcode"
  },
  "geometry": {"coordinates":[-1.124219,50.839243],"type":"Point"}
}
