{
  "type": "Feature",
  "properties": {
    "iso:country":"GB",
    "wof:name":"SY23 4UD",
    "wof:placetype":"postalcode"
},
  "geometry": {"coordinates":[-4.0734387197969,52.37925962583914],"type":"Point"}
}