{
  "type": "Feature",
  "properties": {
    "date:inception_lower": "1980-01-01",
    "date:inception_upper": "1980-01-01",
    "iso:country": "GB",
    "wof:name": "NR31 9DX",
    "wof:placetype": "postalcode"
  },
  "geometry": {"coordinates":[1.69019,52.574621],"type":"Point"}
}
