{
  "type": "Feature",
  "properties": {
    "iso:country":"GB",
    "wof:name":"NR31 9DX",
    "wof:placetype":"postalcode"
},
  "geometry": {"coordinates":[1.68360878615983,52.57227302933823],"type":"Point"}
}