{
  "type": "Feature",
  "properties": {
    "iso:country": "GB",
    "wof:name": "CW9 8UY",
    "wof:placetype": "postalcode"
  },
  "geometry": {"coordinates":[-2.518681,53.246327],"type":"Point"}
}
