{
  "type": "Feature",
  "properties": {
    "date:inception_lower":"2002-09-01",
    "date:inception_upper":"2002-09-30",
    "iso:country":"GB",
    "wof:name":"CW9 8UY",
    "wof:placetype":"postalcode"
},
  "geometry": {"coordinates":[-2.518681,53.246327],"type":"Point"}
}