{
  "type": "Feature",
  "properties": {
    "date:inception_lower": "1993-08-01",
    "date:inception_upper": "1993-08-01",
    "iso:country": "GB",
    "wof:name": "NN4 8LR",
    "wof:placetype": "postalcode"
  },
  "geometry": {"coordinates":[-0.907842,52.221875],"type":"Point"}
}
