{
  "type": "Feature",
  "properties": {
    "iso:country": "GB",
    "wof:name": "NN4 8LR",
    "wof:placetype": "postalcode"
  },
  "geometry": {"coordinates":[-0.907842,52.221875],"type":"Point"}
}
