{
  "type": "Feature",
  "properties": {
    "iso:country": "GB",
    "wof:name": "ST17 4HU",
    "wof:placetype": "postalcode"
  },
  "geometry": {"coordinates":[-2.084896,52.782625],"type":"Point"}
}
