{
  "type": "Feature",
  "properties": {
    "date:inception_lower": "1980-01-01",
    "date:inception_upper": "1980-01-01",
    "iso:country": "GB",
    "wof:name": "ST17 4HU",
    "wof:placetype": "postalcode"
  },
  "geometry": {"coordinates":[-2.084896,52.782625],"type":"Point"}
}
