{
  "type": "Feature",
  "properties": {
    "date:inception_lower": "2018-02-01",
    "date:inception_upper": "2018-02-01",
    "iso:country": "GB",
    "wof:name": "FY4 5GW",
    "wof:placetype": "postalcode"
  },
  "geometry": {"coordinates":[-3.017566,53.784261],"type":"Point"}
}
