{
  "type": "Feature",
  "properties": {
    "iso:country":"GB",
    "wof:name":"SW8 3PQ",
    "wof:placetype":"postalcode"
},
  "geometry": {"coordinates":[-0.15118285387316,51.46968672845651],"type":"Point"}
}