{
  "type": "Feature",
  "properties": {
    "iso:country":"GB",
    "wof:name":"IP22 4WW",
    "wof:placetype":"postalcode"
},
  "geometry": {"coordinates":[1.12159284527937,52.37277653479101],"type":"Point"}
}