{
  "type": "Feature",
  "properties": {
    "iso:country":"GB",
    "wof:name":"WD17 2JD",
    "wof:placetype":"postalcode"
},
  "geometry": {"coordinates":[-0.38454015408532,51.647393409355],"type":"Point"}
}