{
  "type": "Feature",
  "properties": {
    "iso:country": "GB",
    "wof:name": "WD17 2JD",
    "wof:placetype": "postalcode"
  },
  "geometry": {"coordinates":[-0.38454,51.647393],"type":"Point"}
}
