{
  "type": "Feature",
  "properties": {
    "iso:country":"GB",
    "wof:name":"DE21 7JZ",
    "wof:placetype":"postalcode"
},
  "geometry": {"coordinates":[-1.40209791896771,52.9251354440722],"type":"Point"}
}