{
  "type": "Feature",
  "properties": {
    "iso:country":"GB",
    "wof:name":"NR21 8JF",
    "wof:placetype":"postalcode"
},
  "geometry": {"coordinates":[0.86628473341574,52.83750816346975],"type":"Point"}
}