{
  "type": "Feature",
  "properties": {
    "date:inception_lower": "1980-01-01",
    "date:inception_upper": "1980-01-01",
    "iso:country": "GB",
    "wof:name": "NR21 8JF",
    "wof:placetype": "postalcode"
  },
  "geometry": {"coordinates":[0.866271,52.837507],"type":"Point"}
}
