{
  "type": "Feature",
  "properties": {
    "iso:country":"GB",
    "wof:name":"CV2 5NE",
    "wof:placetype":"postalcode"
},
  "geometry": {"coordinates":[-1.45445233512909,52.41116296630995],"type":"Point"}
}