{
  "type": "Feature",
  "properties": {
    "iso:country":"GB",
    "wof:name":"S43 3AR",
    "wof:placetype":"postalcode"
},
  "geometry": {"coordinates":[-1.32636715208475,53.27630639924909],"type":"Point"}
}