{
  "type": "Feature",
  "properties": {
    "date:inception_lower": "1980-01-01",
    "date:inception_upper": "1980-01-01",
    "iso:country": "GB",
    "wof:name": "S43 3AR",
    "wof:placetype": "postalcode"
  },
  "geometry": {"coordinates":[-1.326367,53.276306],"type":"Point"}
}
