{
  "type": "Feature",
  "properties": {
    "iso:country": "GB",
    "wof:name": "B97 9SD",
    "wof:placetype": "postalcode"
  },
  "geometry": {"coordinates":[-1.938197,52.305143],"type":"Point"}
}
