{
  "type": "Feature",
  "properties": {
    "iso:country": "GB",
    "wof:name": "TN24 0HX",
    "wof:placetype": "postalcode"
  },
  "geometry": {"coordinates":[0.907905,51.144269],"type":"Point"}
}
