{
  "type": "Feature",
  "properties": {
    "iso:country":"GB",
    "wof:name":"TQ8 8AN",
    "wof:placetype":"postalcode"
},
  "geometry": {"coordinates":[-3.77647958559568,50.23549894761183],"type":"Point"}
}