{
  "type": "Feature",
  "properties": {
    "iso:country": "GB",
    "wof:name": "TQ8 8AN",
    "wof:placetype": "postalcode"
  },
  "geometry": {"coordinates":[-3.77648,50.235499],"type":"Point"}
}
