{
  "type": "Feature",
  "properties": {
    "iso:country":"GB",
    "wof:name":"BH12 4ED",
    "wof:placetype":"postalcode"
},
  "geometry": {"coordinates":[-1.92539566837521,50.73675062031742],"type":"Point"}
}