{
  "type": "Feature",
  "properties": {
    "iso:country": "GB",
    "wof:name": "BH12 4ED",
    "wof:placetype": "postalcode"
  },
  "geometry": {"coordinates":[-1.925396,50.736751],"type":"Point"}
}
