{
  "type": "Feature",
  "properties": {
    "iso:country": "GB",
    "wof:name": "FY3 7NL",
    "wof:placetype": "postalcode"
  },
  "geometry": {"coordinates":[-3.023956,53.833332],"type":"Point"}
}
