{
  "type": "Feature",
  "properties": {
    "iso:country":"GB",
    "wof:name":"FY3 7NL",
    "wof:placetype":"postalcode"
},
  "geometry": {"coordinates":[-3.0239559982616,53.83333156006493],"type":"Point"}
}