{
  "type": "Feature",
  "properties": {
    "iso:country": "GB",
    "wof:name": "WD3 5DY",
    "wof:placetype": "postalcode"
  },
  "geometry": {"coordinates":[-0.500744,51.65111],"type":"Point"}
}
