{
  "type": "Feature",
  "properties": {
    "iso:country":"GB",
    "wof:name":"WD3 5DY",
    "wof:placetype":"postalcode"
},
  "geometry": {"coordinates":[-0.50074369221282,51.65111048491951],"type":"Point"}
}