{
  "type": "Feature",
  "properties": {
    "date:inception_lower": "1996-12-01",
    "date:inception_upper": "1996-12-01",
    "iso:country": "GB",
    "wof:name": "KA12 8QG",
    "wof:placetype": "postalcode"
  },
  "geometry": {"coordinates":[-4.677823,55.609852],"type":"Point"}
}
