{
  "type": "Feature",
  "properties": {
    "iso:country":"GB",
    "wof:name":"PR4 4QD",
    "wof:placetype":"postalcode"
},
  "geometry": {"coordinates":[-2.79462620944949,53.70457865753087],"type":"Point"}
}