{
  "type": "Feature",
  "properties": {
    "iso:country": "GB",
    "wof:name": "PR4 4QD",
    "wof:placetype": "postalcode"
  },
  "geometry": {"coordinates":[-2.794626,53.704579],"type":"Point"}
}
