{
  "type": "Feature",
  "properties": {
    "iso:country":"GB",
    "wof:name":"DT11 7XL",
    "wof:placetype":"postalcode"
},
  "geometry": {"coordinates":[-2.15511755248733,50.86941880188155],"type":"Point"}
}