{
  "type": "Feature",
  "properties": {
    "iso:country":"GB",
    "wof:name":"E17 9BY",
    "wof:placetype":"postalcode"
},
  "geometry": {"coordinates":[-0.01022950365796,51.57897803558185],"type":"Point"}
}