{
  "type": "Feature",
  "properties": {
    "iso:country":"GB",
    "wof:name":"NR2 4LR",
    "wof:placetype":"postalcode"
},
  "geometry": {"coordinates":[1.2746296115094,52.64218473118093],"type":"Point"}
}