{
  "type": "Feature",
  "properties": {
    "date:inception_lower": "1993-08-01",
    "date:inception_upper": "1993-08-01",
    "iso:country": "GB",
    "wof:name": "NP4 6TR",
    "wof:placetype": "postalcode"
  },
  "geometry": {"coordinates":[-3.075872,51.710586],"type":"Point"}
}
