{
  "type": "Feature",
  "properties": {
    "iso:country": "GB",
    "wof:name": "DH6 1LU",
    "wof:placetype": "postalcode"
  },
  "geometry": {"coordinates":[-1.438643,54.765646],"type":"Point"}
}
