{
  "type": "Feature",
  "properties": {
    "iso:country":"GB",
    "wof:name":"DH6 1LU",
    "wof:placetype":"postalcode"
},
  "geometry": {"coordinates":[-1.4386433661387,54.76564591482512],"type":"Point"}
}