{
  "type": "Feature",
  "properties": {
    "iso:country":"GB",
    "wof:name":"KA9 1GA",
    "wof:placetype":"postalcode"
},
  "geometry": {"coordinates":[-4.61941138606033,55.49471075298198],"type":"Point"}
}