{
  "type": "Feature",
  "properties": {
    "date:inception_lower":"1999-12-01",
    "date:inception_upper":"1999-12-31",
    "iso:country":"GB",
    "wof:name":"KA9 1GA",
    "wof:placetype":"postalcode"
},
  "geometry": {"coordinates":[-4.619411,55.494711],"type":"Point"}
}