{
  "type": "Feature",
  "properties": {
    "iso:country":"GB",
    "wof:name":"E1 3HY",
    "wof:placetype":"postalcode"
},
  "geometry": {"coordinates":[-0.04938357995144,51.51868381378873],"type":"Point"}
}