{
  "type": "Feature",
  "properties": {
    "iso:country":"GB",
    "wof:name":"SN14 0DH",
    "wof:placetype":"postalcode"
},
  "geometry": {"coordinates":[-2.1413102642436,51.45994920645147],"type":"Point"}
}