{
  "type": "Feature",
  "properties": {
    "iso:country":"GB",
    "wof:name":"TQ4 6BU",
    "wof:placetype":"postalcode"
},
  "geometry": {"coordinates":[-3.5626336347335,50.4282086130715],"type":"Point"}
}