{
  "type": "Feature",
  "properties": {
    "iso:country":"GB",
    "wof:name":"S32 1BQ",
    "wof:placetype":"postalcode"
},
  "geometry": {"coordinates":[-1.66766708935619,53.34267077376922],"type":"Point"}
}