{
  "type": "Feature",
  "properties": {
    "iso:country": "GB",
    "wof:name": "S32 1BQ",
    "wof:placetype": "postalcode"
  },
  "geometry": {"coordinates":[-1.667667,53.342671],"type":"Point"}
}
