{
  "type": "Feature",
  "properties": {
    "iso:country": "GB",
    "wof:name": "WD18 0LJ",
    "wof:placetype": "postalcode"
  },
  "geometry": {"coordinates":[-0.409059,51.651379],"type":"Point"}
}
