{
  "type": "Feature",
  "properties": {
    "iso:country":"GB",
    "wof:name":"TW12 2QD",
    "wof:placetype":"postalcode"
},
  "geometry": {"coordinates":[-0.37709344443418,51.4171886611217],"type":"Point"}
}