{
  "type": "Feature",
  "properties": {
    "iso:country": "GB",
    "wof:name": "SK16 4SE",
    "wof:placetype": "postalcode"
  },
  "geometry": {"coordinates":[-2.098451,53.482091],"type":"Point"}
}
