{
  "type": "Feature",
  "properties": {
    "date:inception_lower":"1983-03-01",
    "date:inception_upper":"1983-03-31",
    "iso:country":"GB",
    "wof:name":"SK16 4SE",
    "wof:placetype":"postalcode"
},
  "geometry": {"coordinates":[-2.098451,53.482091],"type":"Point"}
}