{
  "type": "Feature",
  "properties": {
    "iso:country":"GB",
    "wof:name":"OX28 5AJ",
    "wof:placetype":"postalcode"
},
  "geometry": {"coordinates":[-1.50403626931226,51.78725214906671],"type":"Point"}
}