{
  "type": "Feature",
  "properties": {
    "iso:country": "GB",
    "wof:name": "WN1 3QZ",
    "wof:placetype": "postalcode"
  },
  "geometry": {"coordinates":[-2.625254,53.547324],"type":"Point"}
}
