{
  "type": "Feature",
  "properties": {
    "iso:country": "GB",
    "wof:name": "M21 7PT",
    "wof:placetype": "postalcode"
  },
  "geometry": {"coordinates":[-2.263507,53.42017],"type":"Point"}
}
