{
  "type": "Feature",
  "properties": {
    "date:inception_lower": "2016-11-01",
    "date:inception_upper": "2016-11-01",
    "iso:country": "GB",
    "wof:name": "CF62 5BH",
    "wof:placetype": "postalcode"
  },
  "geometry": {"coordinates":[-3.278288,51.393391],"type":"Point"}
}
