{
  "type": "Feature",
  "properties": {
    "date:inception_lower":"1980-01-01",
    "date:inception_upper":"1980-01-31",
    "iso:country":"GB",
    "wof:name":"DD7 7EL",
    "wof:placetype":"postalcode"
},
  "geometry": {"coordinates":[-2.719608,56.499463],"type":"Point"}
}