{
  "type": "Feature",
  "properties": {
    "iso:country":"GB",
    "wof:name":"DD7 7EL",
    "wof:placetype":"postalcode"
},
  "geometry": {"coordinates":[-2.71960762533702,56.49946303871913],"type":"Point"}
}