{
  "type": "Feature",
  "properties": {
    "iso:country":"GB",
    "wof:name":"CM1 2FQ",
    "wof:placetype":"postalcode"
},
  "geometry": {"coordinates":[0.46453391854257,51.74334440936354],"type":"Point"}
}