{
  "type": "Feature",
  "properties": {
    "iso:country": "GB",
    "wof:name": "CM1 2FQ",
    "wof:placetype": "postalcode"
  },
  "geometry": {"coordinates":[0.464534,51.743344],"type":"Point"}
}
