{
  "type": "Feature",
  "properties": {
    "date:inception_lower":"2010-08-01",
    "date:inception_upper":"2010-08-31",
    "iso:country":"GB",
    "wof:name":"CM1 2FQ",
    "wof:placetype":"postalcode"
},
  "geometry": {"coordinates":[0.464534,51.743344],"type":"Point"}
}