{
  "type": "Feature",
  "properties": {
    "iso:country":"GB",
    "wof:name":"SY2 5XN",
    "wof:placetype":"postalcode"
},
  "geometry": {"coordinates":[-2.71964788566127,52.71430696430349],"type":"Point"}
}