{
  "type": "Feature",
  "properties": {
    "iso:country": "GB",
    "wof:name": "NR23 1SA",
    "wof:placetype": "postalcode"
  },
  "geometry": {"coordinates":[0.820289,52.931951],"type":"Point"}
}
