{
  "type": "Feature",
  "properties": {
    "iso:country":"GB",
    "wof:name":"NR23 1SA",
    "wof:placetype":"postalcode"
},
  "geometry": {"coordinates":[0.82018568283429,52.93197094492003],"type":"Point"}
}