{
  "type": "Feature",
  "properties": {
    "date:inception_lower": "2001-12-01",
    "date:inception_upper": "2001-12-01",
    "iso:country": "GB",
    "wof:name": "SP6 1GD",
    "wof:placetype": "postalcode"
  },
  "geometry": {"coordinates":[-1.796744,50.925557],"type":"Point"}
}
