{
  "type": "Feature",
  "properties": {
    "iso:country":"GB",
    "wof:name":"NG19 9NP",
    "wof:placetype":"postalcode"
},
  "geometry": {"coordinates":[-1.19943016272969,53.16250238807696],"type":"Point"}
}