{
  "type": "Feature",
  "properties": {
    "iso:country": "GB",
    "wof:name": "NG19 9NP",
    "wof:placetype": "postalcode"
  },
  "geometry": {"coordinates":[-1.199534,53.162432],"type":"Point"}
}
