{
  "type": "Feature",
  "properties": {
    "date:inception_lower": "2019-02-01",
    "date:inception_upper": "2019-02-01",
    "iso:country": "GB",
    "wof:name": "HR6 9FF",
    "wof:placetype": "postalcode"
  },
  "geometry": {"coordinates":[-2.798821,52.213083],"type":"Point"}
}
