{
  "type": "Feature",
  "properties": {
    "iso:country": "GB",
    "wof:name": "SN3 5BX",
    "wof:placetype": "postalcode"
  },
  "geometry": {"coordinates":[-1.730171,51.562803],"type":"Point"}
}
