{
  "type": "Feature",
  "properties": {
    "iso:country":"GB",
    "wof:name":"B92 8RA",
    "wof:placetype":"postalcode"
},
  "geometry": {"coordinates":[-1.78608230468711,52.435682345651],"type":"Point"}
}