{
  "type": "Feature",
  "properties": {
    "iso:country":"GB",
    "wof:name":"RG9 6QG",
    "wof:placetype":"postalcode"
},
  "geometry": {"coordinates":[-0.87937648072527,51.6152665904572],"type":"Point"}
}