{
  "type": "Feature",
  "properties": {
    "iso:country":"GB",
    "wof:name":"DL2 2RF",
    "wof:placetype":"postalcode"
},
  "geometry": {"coordinates":[-1.66104115171833,54.51672917424814],"type":"Point"}
}