{
  "type": "Feature",
  "properties": {
    "date:inception_lower":"1980-01-01",
    "date:inception_upper":"1980-01-31",
    "iso:country":"GB",
    "wof:name":"DL2 2RF",
    "wof:placetype":"postalcode"
},
  "geometry": {"coordinates":[-1.661041,54.516729],"type":"Point"}
}