{
  "type": "Feature",
  "properties": {
    "iso:country": "GB",
    "wof:name": "HU14 3EQ",
    "wof:placetype": "postalcode"
  },
  "geometry": {"coordinates":[-0.514524,53.722881],"type":"Point"}
}
