{
  "type": "Feature",
  "properties": {
    "iso:country":"GB",
    "wof:name":"HU14 3EQ",
    "wof:placetype":"postalcode"
},
  "geometry": {"coordinates":[-0.51452376794281,53.72288123761082],"type":"Point"}
}