{
  "type": "Feature",
  "properties": {
    "date:inception_lower":"1990-02-01",
    "date:inception_upper":"1990-02-28",
    "iso:country":"GB",
    "wof:name":"HU14 3EQ",
    "wof:placetype":"postalcode"
},
  "geometry": {"coordinates":[-0.514524,53.722881],"type":"Point"}
}