{
  "type": "Feature",
  "properties": {
    "iso:country": "GB",
    "wof:name": "B23 7SF",
    "wof:placetype": "postalcode"
  },
  "geometry": {"coordinates":[-1.874613,52.52045],"type":"Point"}
}
