{
  "type": "Feature",
  "properties": {
    "iso:country":"GB",
    "wof:name":"B23 7SF",
    "wof:placetype":"postalcode"
},
  "geometry": {"coordinates":[-1.87461294916646,52.52044967553186],"type":"Point"}
}