{
  "type": "Feature",
  "properties": {
    "iso:country":"GB",
    "wof:name":"HP4 2PP",
    "wof:placetype":"postalcode"
},
  "geometry": {"coordinates":[-0.54694856979237,51.76158918105001],"type":"Point"}
}