{
  "type": "Feature",
  "properties": {
    "iso:country": "GB",
    "wof:name": "NG14 6LU",
    "wof:placetype": "postalcode"
  },
  "geometry": {"coordinates":[-1.095806,53.039308],"type":"Point"}
}
