{
  "type": "Feature",
  "properties": {
    "iso:country":"GB",
    "wof:name":"AL7 3DJ",
    "wof:placetype":"postalcode"
},
  "geometry": {"coordinates":[-0.17150772189187,51.79249659284734],"type":"Point"}
}