{
  "type": "Feature",
  "properties": {
    "iso:country": "GB",
    "wof:name": "AL7 3DJ",
    "wof:placetype": "postalcode"
  },
  "geometry": {"coordinates":[-0.171508,51.792497],"type":"Point"}
}
