{
  "type": "Feature",
  "properties": {
    "iso:country":"GB",
    "wof:name":"EC4R 9AQ",
    "wof:placetype":"postalcode"
},
  "geometry": {"coordinates":[-0.08833816459501,51.51022471094504],"type":"Point"}
}