{
  "type": "Feature",
  "properties": {
    "iso:country":"GB",
    "wof:name":"CB11 3HB",
    "wof:placetype":"postalcode"
},
  "geometry": {"coordinates":[0.24194727471473,52.01917861764173],"type":"Point"}
}