{
  "type": "Feature",
  "properties": {
    "iso:country": "GB",
    "wof:name": "CB11 3HB",
    "wof:placetype": "postalcode"
  },
  "geometry": {"coordinates":[0.241947,52.019179],"type":"Point"}
}
