{
  "type": "Feature",
  "properties": {
    "iso:country":"GB",
    "wof:name":"BD6 2SL",
    "wof:placetype":"postalcode"
},
  "geometry": {"coordinates":[-1.79102894038929,53.7556412982201],"type":"Point"}
}