{
  "type": "Feature",
  "properties": {
    "iso:country": "GB",
    "wof:name": "W10 6SL",
    "wof:placetype": "postalcode"
  },
  "geometry": {"coordinates":[-0.214908,51.515079],"type":"Point"}
}
