{
  "type": "Feature",
  "properties": {
    "iso:country":"GB",
    "wof:name":"W10 6SL",
    "wof:placetype":"postalcode"
},
  "geometry": {"coordinates":[-0.21490812204248,51.51507897116814],"type":"Point"}
}