{
  "type": "Feature",
  "properties": {
    "iso:country": "GB",
    "wof:name": "KA11 2FY",
    "wof:placetype": "postalcode"
  },
  "geometry": {"coordinates":[-4.65424,55.631747],"type":"Point"}
}
