{
  "type": "Feature",
  "properties": {
    "iso:country":"GB",
    "wof:name":"LS17 5NR",
    "wof:placetype":"postalcode"
},
  "geometry": {"coordinates":[-1.54739185952303,53.84321408796937],"type":"Point"}
}