{
  "type": "Feature",
  "properties": {
    "date:inception_lower":"1980-01-01",
    "date:inception_upper":"1980-01-31",
    "iso:country":"GB",
    "wof:name":"LS17 5NR",
    "wof:placetype":"postalcode"
},
  "geometry": {"coordinates":[-1.547392,53.843214],"type":"Point"}
}