{
  "type": "Feature",
  "properties": {
    "iso:country": "GB",
    "wof:name": "DL1 5EZ",
    "wof:placetype": "postalcode"
  },
  "geometry": {"coordinates":[-1.550256,54.517359],"type":"Point"}
}
