{
  "type": "Feature",
  "properties": {
    "iso:country":"GB",
    "wof:name":"DL1 5EZ",
    "wof:placetype":"postalcode"
},
  "geometry": {"coordinates":[-1.55038590218005,54.51733925648917],"type":"Point"}
}