{
  "type": "Feature",
  "properties": {
    "date:inception_lower": "1980-01-01",
    "date:inception_upper": "1980-01-01",
    "iso:country": "GB",
    "wof:name": "DL1 5EZ",
    "wof:placetype": "postalcode"
  },
  "geometry": {"coordinates":[-1.550256,54.517359],"type":"Point"}
}
