{
  "type": "Feature",
  "properties": {
    "iso:country":"GB",
    "wof:name":"PO33 2NB",
    "wof:placetype":"postalcode"
},
  "geometry": {"coordinates":[-1.16225805201872,50.73171660720221],"type":"Point"}
}