{
  "type": "Feature",
  "properties": {
    "date:inception_lower":"1980-01-01",
    "date:inception_upper":"1980-01-31",
    "iso:country":"GB",
    "wof:name":"PO33 2NB",
    "wof:placetype":"postalcode"
},
  "geometry": {"coordinates":[-1.162258,50.731717],"type":"Point"}
}