{
  "type": "Feature",
  "properties": {
    "date:inception_lower": "2016-03-01",
    "date:inception_upper": "2016-03-01",
    "iso:country": "GB",
    "wof:name": "CM14 9ZZ",
    "wof:placetype": "postalcode"
  },
  "geometry": {"coordinates":[0.303594,51.620306],"type":"Point"}
}
