{
  "type": "Feature",
  "properties": {
    "iso:country":"GB",
    "wof:name":"TN4 8BY",
    "wof:placetype":"postalcode"
},
  "geometry": {"coordinates":[0.25740126212702,51.12951839090179],"type":"Point"}
}