{
  "type": "Feature",
  "properties": {
    "iso:country":"GB",
    "wof:name":"B78 3DB",
    "wof:placetype":"postalcode"
},
  "geometry": {"coordinates":[-1.75857765467694,52.62641312556092],"type":"Point"}
}