{
  "type": "Feature",
  "properties": {
    "date:inception_lower": "1980-01-01",
    "date:inception_upper": "1980-01-01",
    "iso:country": "GB",
    "wof:name": "B78 3DB",
    "wof:placetype": "postalcode"
  },
  "geometry": {"coordinates":[-1.758578,52.626413],"type":"Point"}
}
