{
  "type": "Feature",
  "properties": {
    "iso:country":"GB",
    "wof:name":"EX4 6BQ",
    "wof:placetype":"postalcode"
},
  "geometry": {"coordinates":[-3.52590468897727,50.72941206824097],"type":"Point"}
}