{
  "type": "Feature",
  "properties": {
    "iso:country":"GB",
    "wof:name":"CW5 7SH",
    "wof:placetype":"postalcode"
},
  "geometry": {"coordinates":[-2.51302411117123,53.05763615027707],"type":"Point"}
}