{
  "type": "Feature",
  "properties": {
    "date:inception_lower": "2008-05-01",
    "date:inception_upper": "2008-05-01",
    "iso:country": "GB",
    "wof:name": "CW5 7SH",
    "wof:placetype": "postalcode"
  },
  "geometry": {"coordinates":[-2.513024,53.057636],"type":"Point"}
}
