{
  "type": "Feature",
  "properties": {
    "iso:country": "GB",
    "wof:name": "CF36 5BE",
    "wof:placetype": "postalcode"
  },
  "geometry": {"coordinates":[-3.685505,51.483426],"type":"Point"}
}
