{
  "type": "Feature",
  "properties": {
    "date:inception_lower": "1980-01-01",
    "date:inception_upper": "1980-01-01",
    "iso:country": "GB",
    "wof:name": "CF36 5BE",
    "wof:placetype": "postalcode"
  },
  "geometry": {"coordinates":[-3.685723,51.483379],"type":"Point"}
}
