{
  "type": "Feature",
  "properties": {
    "iso:country":"GB",
    "wof:name":"CF36 5BE",
    "wof:placetype":"postalcode"
},
  "geometry": {"coordinates":[-3.68550515154128,51.48342586176151],"type":"Point"}
}