{
  "type": "Feature",
  "properties": {
    "date:inception_lower":"1980-01-01",
    "date:inception_upper":"1980-01-31",
    "iso:country":"GB",
    "wof:name":"M4 7HZ",
    "wof:placetype":"postalcode"
},
  "geometry": {"coordinates":[-2.216787,53.482357],"type":"Point"}
}