{
  "type": "Feature",
  "properties": {
    "iso:country":"GB",
    "wof:name":"M4 7HZ",
    "wof:placetype":"postalcode"
},
  "geometry": {"coordinates":[-2.21678737189058,53.48235688740591],"type":"Point"}
}