{
  "type": "Feature",
  "properties": {
    "date:inception_lower":"1980-01-01",
    "date:inception_upper":"1980-01-31",
    "iso:country":"GB",
    "wof:name":"IP17 1SA",
    "wof:placetype":"postalcode"
},
  "geometry": {"coordinates":[1.510056,52.171723],"type":"Point"}
}