{
  "type": "Feature",
  "properties": {
    "date:inception_lower": "1980-01-01",
    "date:inception_upper": "1980-01-01",
    "iso:country": "GB",
    "wof:name": "IP17 1SA",
    "wof:placetype": "postalcode"
  },
  "geometry": {"coordinates":[1.511435,52.173987],"type":"Point"}
}
