{
  "type": "Feature",
  "properties": {
    "iso:country":"GB",
    "wof:name":"IP17 1SA",
    "wof:placetype":"postalcode"
},
  "geometry": {"coordinates":[1.51005625778183,52.17172283928934],"type":"Point"}
}