{
  "type": "Feature",
  "properties": {
    "iso:country": "GB",
    "wof:name": "WR9 8SN",
    "wof:placetype": "postalcode"
  },
  "geometry": {"coordinates":[-2.16556,52.260756],"type":"Point"}
}
