{
  "type": "Feature",
  "properties": {
    "iso:country": "GB",
    "wof:name": "CV23 0FY",
    "wof:placetype": "postalcode"
  },
  "geometry": {"coordinates":[-1.239835,52.41076],"type":"Point"}
}
