{
  "type": "Feature",
  "properties": {
    "date:inception_lower": "2004-05-01",
    "date:inception_upper": "2004-05-01",
    "iso:country": "GB",
    "wof:name": "TN37 7GA",
    "wof:placetype": "postalcode"
  },
  "geometry": {"coordinates":[0.55274,50.886484],"type":"Point"}
}
