{
  "type": "Feature",
  "properties": {
    "iso:country":"GB",
    "wof:name":"W1D 3QL",
    "wof:placetype":"postalcode"
},
  "geometry": {"coordinates":[-0.13171238468531,51.51594148805983],"type":"Point"}
}