{
  "type": "Feature",
  "properties": {
    "iso:country":"GB",
    "wof:name":"CB2 1RJ",
    "wof:placetype":"postalcode"
},
  "geometry": {"coordinates":[0.11757831667608,52.20251682760409],"type":"Point"}
}