{
  "type": "Feature",
  "properties": {
    "date:inception_lower":"1980-01-01",
    "date:inception_upper":"1980-01-31",
    "iso:country":"GB",
    "wof:name":"CB2 1RJ",
    "wof:placetype":"postalcode"
},
  "geometry": {"coordinates":[0.117607,52.20253],"type":"Point"}
}