{
  "type": "Feature",
  "properties": {
    "iso:country": "GB",
    "wof:name": "EX12 3EB",
    "wof:placetype": "postalcode"
  },
  "geometry": {"coordinates":[-3.090953,50.69983],"type":"Point"}
}
