{
  "type": "Feature",
  "properties": {
    "iso:country":"GB",
    "wof:name":"LA14 2TW",
    "wof:placetype":"postalcode"
},
  "geometry": {"coordinates":[-3.22997359069033,54.10083917314301],"type":"Point"}
}