{
  "type": "Feature",
  "properties": {
    "iso:country": "GB",
    "wof:name": "LA14 2TW",
    "wof:placetype": "postalcode"
  },
  "geometry": {"coordinates":[-3.229974,54.100839],"type":"Point"}
}
