{
  "type": "Feature",
  "properties": {
    "iso:country":"GB",
    "wof:name":"DH3 3HD",
    "wof:placetype":"postalcode"
},
  "geometry": {"coordinates":[-1.57431145208262,54.85280064348161],"type":"Point"}
}