{
  "type": "Feature",
  "properties": {
    "date:inception_lower":"2002-06-01",
    "date:inception_upper":"2002-06-30",
    "iso:country":"GB",
    "wof:name":"DH3 3HD",
    "wof:placetype":"postalcode"
},
  "geometry": {"coordinates":[-1.574311,54.852801],"type":"Point"}
}