{
  "type": "Feature",
  "properties": {
    "iso:country":"GB",
    "wof:name":"NN14 1EL",
    "wof:placetype":"postalcode"
},
  "geometry": {"coordinates":[-0.73770002313303,52.36024566815589],"type":"Point"}
}