{
  "type": "Feature",
  "properties": {
    "date:inception_lower": "1980-01-01",
    "date:inception_upper": "1980-01-01",
    "iso:country": "GB",
    "wof:name": "NN14 1EL",
    "wof:placetype": "postalcode"
  },
  "geometry": {"coordinates":[-0.7377,52.360246],"type":"Point"}
}
