{
  "type": "Feature",
  "properties": {
    "date:inception_lower": "2007-07-01",
    "date:inception_upper": "2007-07-01",
    "iso:country": "GB",
    "wof:name": "TS10 1AX",
    "wof:placetype": "postalcode"
  },
  "geometry": {"coordinates":[-1.072315,54.619328],"type":"Point"}
}
