{
  "type": "Feature",
  "properties": {
    "iso:country":"GB",
    "wof:name":"TS10 1AX",
    "wof:placetype":"postalcode"
},
  "geometry": {"coordinates":[-1.07231462197583,54.61932770511337],"type":"Point"}
}