{
  "type": "Feature",
  "properties": {
    "iso:country":"GB",
    "wof:name":"HA2 6JW",
    "wof:placetype":"postalcode"
},
  "geometry": {"coordinates":[-0.35889264487289,51.59589960855467],"type":"Point"}
}