{
  "type": "Feature",
  "properties": {
    "iso:country": "GB",
    "wof:name": "DE4 5NH",
    "wof:placetype": "postalcode"
  },
  "geometry": {"coordinates":[-1.482203,53.086788],"type":"Point"}
}
