{
  "type": "Feature",
  "properties": {
    "iso:country":"GB",
    "wof:name":"DE4 5NH",
    "wof:placetype":"postalcode"
},
  "geometry": {"coordinates":[-1.48220295259402,53.086787569607],"type":"Point"}
}