{
  "type": "Feature",
  "properties": {
    "iso:country": "GB",
    "wof:name": "LS22 9FY",
    "wof:placetype": "postalcode"
  },
  "geometry": {"coordinates":[-1.384305,53.930156],"type":"Point"}
}
