{
  "type": "Feature",
  "properties": {
    "date:inception_lower":"1980-01-01",
    "date:inception_upper":"1980-01-31",
    "iso:country":"GB",
    "wof:name":"GU26 6DX",
    "wof:placetype":"postalcode"
},
  "geometry": {"coordinates":[-0.768953,51.113362],"type":"Point"}
}