{
  "type": "Feature",
  "properties": {
    "iso:country":"GB",
    "wof:name":"DN2 4DX",
    "wof:placetype":"postalcode"
},
  "geometry": {"coordinates":[-1.11518162897114,53.53383301123093],"type":"Point"}
}