{
  "type": "Feature",
  "properties": {
    "iso:country": "GB",
    "wof:name": "DN2 4DX",
    "wof:placetype": "postalcode"
  },
  "geometry": {"coordinates":[-1.115182,53.533833],"type":"Point"}
}
