{
  "type": "Feature",
  "properties": {
    "iso:country":"GB",
    "wof:name":"RG2 9FG",
    "wof:placetype":"postalcode"
},
  "geometry": {"coordinates":[-0.90447008423679,51.38605884540269],"type":"Point"}
}