{
  "type": "Feature",
  "properties": {
    "iso:country": "GB",
    "wof:name": "RG2 9FG",
    "wof:placetype": "postalcode"
  },
  "geometry": {"coordinates":[-0.90447,51.386059],"type":"Point"}
}
