{
  "type": "Feature",
  "properties": {
    "iso:country":"GB",
    "wof:name":"OL4 4SQ",
    "wof:placetype":"postalcode"
},
  "geometry": {"coordinates":[-2.0606201960932,53.53961474140936],"type":"Point"}
}