{
  "type": "Feature",
  "properties": {
    "iso:country": "GB",
    "wof:name": "OL4 4SQ",
    "wof:placetype": "postalcode"
  },
  "geometry": {"coordinates":[-2.06062,53.539615],"type":"Point"}
}
