{
  "type": "Feature",
  "properties": {
    "date:inception_lower": "1995-12-01",
    "date:inception_upper": "1995-12-01",
    "iso:country": "GB",
    "wof:name": "OL4 4SQ",
    "wof:placetype": "postalcode"
  },
  "geometry": {"coordinates":[-2.060603,53.539641],"type":"Point"}
}
