{
  "type": "Feature",
  "properties": {
    "date:inception_lower": "1980-01-01",
    "date:inception_upper": "1980-01-01",
    "iso:country": "GB",
    "wof:name": "CT1 2JE",
    "wof:placetype": "postalcode"
  },
  "geometry": {"coordinates":[1.07945,51.279558],"type":"Point"}
}
