{
  "type": "Feature",
  "properties": {
    "iso:country":"GB",
    "wof:name":"SA73 2ED",
    "wof:placetype":"postalcode"
},
  "geometry": {"coordinates":[-5.03395443425966,51.71660988152261],"type":"Point"}
}