{
  "type": "Feature",
  "properties": {
    "iso:country":"GB",
    "wof:name":"BS27 3TY",
    "wof:placetype":"postalcode"
},
  "geometry": {"coordinates":[-2.75382669953263,51.25581463676383],"type":"Point"}
}