{
  "type": "Feature",
  "properties": {
    "iso:country": "GB",
    "wof:name": "BS27 3TY",
    "wof:placetype": "postalcode"
  },
  "geometry": {"coordinates":[-2.753827,51.255815],"type":"Point"}
}
