{
  "type": "Feature",
  "properties": {
    "iso:country":"GB",
    "wof:name":"PL15 8BX",
    "wof:placetype":"postalcode"
},
  "geometry": {"coordinates":[-4.36387741285587,50.63942607264683],"type":"Point"}
}