{
  "type": "Feature",
  "properties": {
    "date:inception_lower":"1993-08-01",
    "date:inception_upper":"1993-08-31",
    "iso:country":"GB",
    "wof:name":"BB4 8UH",
    "wof:placetype":"postalcode"
},
  "geometry": {"coordinates":[-2.294165,53.736407],"type":"Point"}
}