{
  "type": "Feature",
  "properties": {
    "date:inception_lower": "1980-01-01",
    "date:inception_upper": "1980-01-01",
    "iso:country": "GB",
    "wof:name": "NP7 9RT",
    "wof:placetype": "postalcode"
  },
  "geometry": {"coordinates":[-3.084221,51.816038],"type":"Point"}
}
