{
  "type": "Feature",
  "properties": {
    "iso:country":"GB",
    "wof:name":"NP7 9RT",
    "wof:placetype":"postalcode"
},
  "geometry": {"coordinates":[-3.08564497591921,51.81581311806374],"type":"Point"}
}