{
  "type": "Feature",
  "properties": {
    "iso:country":"GB",
    "wof:name":"GU33 6BE",
    "wof:placetype":"postalcode"
},
  "geometry": {"coordinates":[-0.89383684273637,51.08011504047465],"type":"Point"}
}