{
  "type": "Feature",
  "properties": {
    "iso:country": "GB",
    "wof:name": "SW6 5TN",
    "wof:placetype": "postalcode"
  },
  "geometry": {"coordinates":[-0.200322,51.477061],"type":"Point"}
}
