{
  "type": "Feature",
  "properties": {
    "iso:country":"GB",
    "wof:name":"SW6 5TN",
    "wof:placetype":"postalcode"
},
  "geometry": {"coordinates":[-0.20032181066318,51.47706075220677],"type":"Point"}
}