{
  "type": "Feature",
  "properties": {
    "date:inception_lower": "1994-12-01",
    "date:inception_upper": "1994-12-01",
    "iso:country": "GB",
    "wof:name": "CF31 2DB",
    "wof:placetype": "postalcode"
  },
  "geometry": {"coordinates":[-3.561451,51.519837],"type":"Point"}
}
