{
  "type": "Feature",
  "properties": {
    "iso:country":"GB",
    "wof:name":"PO1 2DJ",
    "wof:placetype":"postalcode"
},
  "geometry": {"coordinates":[-1.09057835092444,50.79516372123569],"type":"Point"}
}