{
  "type": "Feature",
  "properties": {
    "date:inception_lower": "1993-01-01",
    "date:inception_upper": "1993-01-01",
    "iso:country": "GB",
    "wof:name": "CF64 2PS",
    "wof:placetype": "postalcode"
  },
  "geometry": {"coordinates":[-3.193327,51.448438],"type":"Point"}
}
