{
  "type": "Feature",
  "properties": {
    "iso:country":"GB",
    "wof:name":"CF64 2PS",
    "wof:placetype":"postalcode"
},
  "geometry": {"coordinates":[-3.19332667409369,51.44843832324393],"type":"Point"}
}