{
  "type": "Feature",
  "properties": {
    "iso:country":"GB",
    "wof:name":"SA9 1XH",
    "wof:placetype":"postalcode"
},
  "geometry": {"coordinates":[-3.72271631191247,51.79972429945978],"type":"Point"}
}