{
  "type": "Feature",
  "properties": {
    "iso:country": "GB",
    "wof:name": "SA9 1XH",
    "wof:placetype": "postalcode"
  },
  "geometry": {"coordinates":[-3.722716,51.799724],"type":"Point"}
}
