{
  "type": "Feature",
  "properties": {
    "iso:country":"GB",
    "wof:name":"TN13 1EN",
    "wof:placetype":"postalcode"
},
  "geometry": {"coordinates":[0.18597560589158,51.271837090156],"type":"Point"}
}