{
  "type": "Feature",
  "properties": {
    "iso:country": "GB",
    "wof:name": "KY11 8BX",
    "wof:placetype": "postalcode"
  },
  "geometry": {"coordinates":[-3.423014,56.058019],"type":"Point"}
}
