{
  "type": "Feature",
  "properties": {
    "date:inception_lower": "1998-12-01",
    "date:inception_upper": "1998-12-01",
    "iso:country": "GB",
    "wof:name": "KY11 8BX",
    "wof:placetype": "postalcode"
  },
  "geometry": {"coordinates":[-3.423014,56.058019],"type":"Point"}
}
