{
  "type": "Feature",
  "properties": {
    "iso:country":"GB",
    "wof:name":"S44 6AU",
    "wof:placetype":"postalcode"
},
  "geometry": {"coordinates":[-1.27739028756587,53.25038325691015],"type":"Point"}
}