{
  "type": "Feature",
  "properties": {
    "iso:country":"GB",
    "wof:name":"BA2 4BZ",
    "wof:placetype":"postalcode"
},
  "geometry": {"coordinates":[-2.35245077350756,51.3853682779665],"type":"Point"}
}