{
  "type": "Feature",
  "properties": {
    "iso:country": "GB",
    "wof:name": "GU15 1EJ",
    "wof:placetype": "postalcode"
  },
  "geometry": {"coordinates":[-0.716652,51.326953],"type":"Point"}
}
