{
  "type": "Feature",
  "properties": {
    "iso:country":"GB",
    "wof:name":"SM4 5SH",
    "wof:placetype":"postalcode"
},
  "geometry": {"coordinates":[-0.19361645610343,51.39486461799314],"type":"Point"}
}