{
  "type": "Feature",
  "properties": {
    "iso:country": "GB",
    "wof:name": "SM4 5SH",
    "wof:placetype": "postalcode"
  },
  "geometry": {"coordinates":[-0.193846,51.394616],"type":"Point"}
}
