{
  "type": "Feature",
  "properties": {
    "iso:country": "GB",
    "wof:name": "EH33 2JB",
    "wof:placetype": "postalcode"
  },
  "geometry": {"coordinates":[-2.956585,55.940507],"type":"Point"}
}
