{
  "type": "Feature",
  "properties": {
    "date:inception_lower":"2015-11-01",
    "date:inception_upper":"2015-11-30",
    "iso:country":"GB",
    "wof:name":"KY16 9JW",
    "wof:placetype":"postalcode"
},
  "geometry": {"coordinates":[-2.789613,56.335647],"type":"Point"}
}