{
  "type": "Feature",
  "properties": {
    "iso:country":"GB",
    "wof:name":"KY16 9JW",
    "wof:placetype":"postalcode"
},
  "geometry": {"coordinates":[-2.78961283070354,56.33564738096916],"type":"Point"}
}