{
  "type": "Feature",
  "properties": {
    "iso:country": "GB",
    "wof:name": "SW18 1BS",
    "wof:placetype": "postalcode"
  },
  "geometry": {"coordinates":[-0.188158,51.459231],"type":"Point"}
}
