{
  "type": "Feature",
  "properties": {
    "iso:country":"GB",
    "wof:name":"G82 1PQ",
    "wof:placetype":"postalcode"
},
  "geometry": {"coordinates":[-4.57178746603923,55.94372058783392],"type":"Point"}
}