{
  "type": "Feature",
  "properties": {
    "iso:country": "GB",
    "wof:name": "TF12 5JB",
    "wof:placetype": "postalcode"
  },
  "geometry": {"coordinates":[-2.482073,52.611083],"type":"Point"}
}
