{
  "type": "Feature",
  "properties": {
    "iso:country":"GB",
    "wof:name":"TF12 5JB",
    "wof:placetype":"postalcode"
},
  "geometry": {"coordinates":[-2.48207542599856,52.6110862451022],"type":"Point"}
}