{
  "type": "Feature",
  "properties": {
    "date:inception_lower":"1985-10-01",
    "date:inception_upper":"1985-10-31",
    "iso:country":"GB",
    "wof:name":"TF12 5JB",
    "wof:placetype":"postalcode"
},
  "geometry": {"coordinates":[-2.482073,52.611083],"type":"Point"}
}