{
  "type": "Feature",
  "properties": {
    "iso:country":"GB",
    "wof:name":"SK10 5TN",
    "wof:placetype":"postalcode"
},
  "geometry": {"coordinates":[-2.08073095047192,53.27662488679996],"type":"Point"}
}