{
  "type": "Feature",
  "properties": {
    "iso:country":"GB",
    "wof:name":"SE6 1BQ",
    "wof:placetype":"postalcode"
},
  "geometry": {"coordinates":[-0.00917653176382,51.44045511640363],"type":"Point"}
}