{
  "type": "Feature",
  "properties": {
    "iso:country":"GB",
    "wof:name":"PO5 2JT",
    "wof:placetype":"postalcode"
},
  "geometry": {"coordinates":[-1.08498439558406,50.78371712937807],"type":"Point"}
}