{
  "type": "Feature",
  "properties": {
    "date:inception_lower": "1980-01-01",
    "date:inception_upper": "1980-01-01",
    "iso:country": "GB",
    "wof:name": "PO5 2JT",
    "wof:placetype": "postalcode"
  },
  "geometry": {"coordinates":[-1.084984,50.783717],"type":"Point"}
}
