{
  "type": "Feature",
  "properties": {
    "iso:country": "GB",
    "wof:name": "DL2 1QH",
    "wof:placetype": "postalcode"
  },
  "geometry": {"coordinates":[-1.520586,54.497159],"type":"Point"}
}
