{
  "type": "Feature",
  "properties": {
    "iso:country": "GB",
    "wof:name": "BN21 3TG",
    "wof:placetype": "postalcode"
  },
  "geometry": {"coordinates":[0.286713,50.770632],"type":"Point"}
}
