{
  "type": "Feature",
  "properties": {
    "iso:country":"GB",
    "wof:name":"EH8 9HY",
    "wof:placetype":"postalcode"
},
  "geometry": {"coordinates":[-3.18165137827402,55.9425975500052],"type":"Point"}
}