{
  "type": "Feature",
  "properties": {
    "iso:country": "GB",
    "wof:name": "EH8 9HY",
    "wof:placetype": "postalcode"
  },
  "geometry": {"coordinates":[-3.181651,55.942598],"type":"Point"}
}
