{
  "type": "Feature",
  "properties": {
    "iso:country": "GB",
    "wof:name": "B91 1JX",
    "wof:placetype": "postalcode"
  },
  "geometry": {"coordinates":[-1.792811,52.421796],"type":"Point"}
}
