{
  "type": "Feature",
  "properties": {
    "iso:country":"GB",
    "wof:name":"CH43 9YG",
    "wof:placetype":"postalcode"
},
  "geometry": {"coordinates":[-3.06650783784151,53.37956148148346],"type":"Point"}
}