{
  "type": "Feature",
  "properties": {
    "iso:country":"GB",
    "wof:name":"BN20 0AD",
    "wof:placetype":"postalcode"
},
  "geometry": {"coordinates":[0.22582054021682,50.73949030837494],"type":"Point"}
}