{
  "type": "Feature",
  "properties": {
    "date:inception_lower": "2020-08-01",
    "date:inception_upper": "2020-08-01",
    "iso:country": "GB",
    "wof:name": "CO6 2FE",
    "wof:placetype": "postalcode"
  },
  "geometry": {"coordinates":[0.696099,51.929791],"type":"Point"}
}
