{
  "type": "Feature",
  "properties": {
    "date:inception_lower": "1995-07-01",
    "date:inception_upper": "1995-07-01",
    "iso:country": "GB",
    "wof:name": "RG41 5AF",
    "wof:placetype": "postalcode"
  },
  "geometry": {"coordinates":[-0.867546,51.423528],"type":"Point"}
}
