{
  "type": "Feature",
  "properties": {
    "date:inception_lower": "1980-01-01",
    "date:inception_upper": "1980-01-01",
    "iso:country": "GB",
    "wof:name": "G73 3PS",
    "wof:placetype": "postalcode"
  },
  "geometry": {"coordinates":[-4.206164,55.822987],"type":"Point"}
}
