{
  "type": "Feature",
  "properties": {
    "iso:country":"GB",
    "wof:name":"G73 3PS",
    "wof:placetype":"postalcode"
},
  "geometry": {"coordinates":[-4.20616438301139,55.82298652032505],"type":"Point"}
}