{
  "type": "Feature",
  "properties": {
    "iso:country": "GB",
    "wof:name": "NP24 6LX",
    "wof:placetype": "postalcode"
  },
  "geometry": {"coordinates":[-3.250984,51.723526],"type":"Point"}
}
