{
  "type": "Feature",
  "properties": {
    "iso:country":"GB",
    "wof:name":"ST3 5NG",
    "wof:placetype":"postalcode"
},
  "geometry": {"coordinates":[-2.10837327068501,52.97593062214855],"type":"Point"}
}