{
  "type": "Feature",
  "properties": {
    "iso:country":"GB",
    "wof:name":"SN10 3RD",
    "wof:placetype":"postalcode"
},
  "geometry": {"coordinates":[-1.8980236858653,51.32693239921953],"type":"Point"}
}