{
  "type": "Feature",
  "properties": {
    "iso:country": "GB",
    "wof:name": "CM23 2AL",
    "wof:placetype": "postalcode"
  },
  "geometry": {"coordinates":[0.169806,51.875484],"type":"Point"}
}
