{
  "type": "Feature",
  "properties": {
    "iso:country":"GB",
    "wof:name":"MK40 1HJ",
    "wof:placetype":"postalcode"
},
  "geometry": {"coordinates":[-0.47149908505382,52.13645165556633],"type":"Point"}
}