{
  "type": "Feature",
  "properties": {
    "iso:country":"GB",
    "wof:name":"EX8 2SB",
    "wof:placetype":"postalcode"
},
  "geometry": {"coordinates":[-3.40939870804968,50.61775260342535],"type":"Point"}
}