{
  "type": "Feature",
  "properties": {
    "iso:country":"GB",
    "wof:name":"ML1 4UF",
    "wof:placetype":"postalcode"
},
  "geometry": {"coordinates":[-3.98856146126766,55.83317790628055],"type":"Point"}
}