{
  "type": "Feature",
  "properties": {
    "date:inception_lower": "2004-05-01",
    "date:inception_upper": "2004-05-01",
    "iso:country": "GB",
    "wof:name": "ML1 4UF",
    "wof:placetype": "postalcode"
  },
  "geometry": {"coordinates":[-3.988613,55.833775],"type":"Point"}
}
