{
  "type": "Feature",
  "properties": {
    "iso:country":"GB",
    "wof:name":"B76 1GP",
    "wof:placetype":"postalcode"
},
  "geometry": {"coordinates":[-1.79344809875036,52.53718311471663],"type":"Point"}
}