{
  "type": "Feature",
  "properties": {
    "iso:country":"GB",
    "wof:name":"NN18 9AH",
    "wof:placetype":"postalcode"
},
  "geometry": {"coordinates":[-0.72911362252873,52.47773291914255],"type":"Point"}
}