{
  "type": "Feature",
  "properties": {
    "iso:country":"GB",
    "wof:name":"SG2 9XS",
    "wof:placetype":"postalcode"
},
  "geometry": {"coordinates":[-0.17690396783857,51.88982899301097],"type":"Point"}
}