{
  "type": "Feature",
  "properties": {
    "iso:country": "GB",
    "wof:name": "SG2 9XS",
    "wof:placetype": "postalcode"
  },
  "geometry": {"coordinates":[-0.176904,51.889829],"type":"Point"}
}
