{
  "type": "Feature",
  "properties": {
    "iso:country":"GB",
    "wof:name":"CH47 9RZ",
    "wof:placetype":"postalcode"
},
  "geometry": {"coordinates":[-3.15374223389972,53.39386072509026],"type":"Point"}
}