{
  "type": "Feature",
  "properties": {
    "iso:country":"GB",
    "wof:name":"CV23 0TA",
    "wof:placetype":"postalcode"
},
  "geometry": {"coordinates":[-1.21958138414091,52.38205746791645],"type":"Point"}
}