{
  "type": "Feature",
  "properties": {
    "iso:country": "GB",
    "wof:name": "CV23 0TA",
    "wof:placetype": "postalcode"
  },
  "geometry": {"coordinates":[-1.219581,52.382057],"type":"Point"}
}
