{
  "type": "Feature",
  "properties": {
    "iso:country": "GB",
    "wof:name": "ST4 7RW",
    "wof:placetype": "postalcode"
  },
  "geometry": {"coordinates":[-2.186706,53.007008],"type":"Point"}
}
