{
  "type": "Feature",
  "properties": {
    "iso:country": "GB",
    "wof:name": "CV3 3BZ",
    "wof:placetype": "postalcode"
  },
  "geometry": {"coordinates":[-1.461355,52.389987],"type":"Point"}
}
