{
  "type": "Feature",
  "properties": {
    "iso:country":"GB",
    "wof:name":"LE4 0RQ",
    "wof:placetype":"postalcode"
},
  "geometry": {"coordinates":[-1.15187953409288,52.66002515987014],"type":"Point"}
}