{
  "type": "Feature",
  "properties": {
    "iso:country":"GB",
    "wof:name":"HA6 2DF",
    "wof:placetype":"postalcode"
},
  "geometry": {"coordinates":[-0.43506538014465,51.6135661834366],"type":"Point"}
}