{
  "type": "Feature",
  "properties": {
    "iso:country":"GB",
    "wof:name":"SE24 0PR",
    "wof:placetype":"postalcode"
},
  "geometry": {"coordinates":[-0.10771496997999,51.45853482945223],"type":"Point"}
}