{
  "type": "Feature",
  "properties": {
    "date:inception_lower": "1980-01-01",
    "date:inception_upper": "1980-01-01",
    "iso:country": "GB",
    "wof:name": "GU15 2EQ",
    "wof:placetype": "postalcode"
  },
  "geometry": {"coordinates":[-0.739091,51.335731],"type":"Point"}
}
