{
  "type": "Feature",
  "properties": {
    "date:inception_lower":"2009-04-01",
    "date:inception_upper":"2009-04-30",
    "iso:country":"GB",
    "wof:name":"G51 2XW",
    "wof:placetype":"postalcode"
},
  "geometry": {"coordinates":[-4.311833,55.850345],"type":"Point"}
}