{
  "type": "Feature",
  "properties": {
    "iso:country":"GB",
    "wof:name":"G51 2XW",
    "wof:placetype":"postalcode"
},
  "geometry": {"coordinates":[-4.31183273692957,55.85034458832189],"type":"Point"}
}