{
  "type": "Feature",
  "properties": {
    "iso:country":"GB",
    "wof:name":"HA1 4BY",
    "wof:placetype":"postalcode"
},
  "geometry": {"coordinates":[-0.35206533020447,51.57829619389717],"type":"Point"}
}