{
  "type": "Feature",
  "properties": {
    "iso:country":"GB",
    "wof:name":"DY6 9SN",
    "wof:placetype":"postalcode"
},
  "geometry": {"coordinates":[-2.17859357461325,52.48837651652777],"type":"Point"}
}