{
  "type": "Feature",
  "properties": {
    "iso:country": "GB",
    "wof:name": "NR30 5NE",
    "wof:placetype": "postalcode"
  },
  "geometry": {"coordinates":[1.724077,52.656592],"type":"Point"}
}
