{
  "type": "Feature",
  "properties": {
    "iso:country":"GB",
    "wof:name":"MK9 3PE",
    "wof:placetype":"postalcode"
},
  "geometry": {"coordinates":[-0.75943867081583,52.03632652658032],"type":"Point"}
}