{
  "type": "Feature",
  "properties": {
    "iso:country":"GB",
    "wof:name":"TD14 5TZ",
    "wof:placetype":"postalcode"
},
  "geometry": {"coordinates":[-2.20350502676257,55.8903786915921],"type":"Point"}
}