{
  "type": "Feature",
  "properties": {
    "date:inception_lower": "2000-12-01",
    "date:inception_upper": "2000-12-01",
    "iso:country": "GB",
    "wof:name": "EX39 1UX",
    "wof:placetype": "postalcode"
  },
  "geometry": {"coordinates":[-4.206008,51.038108],"type":"Point"}
}
