{
  "type": "Feature",
  "properties": {
    "iso:country":"GB",
    "wof:name":"EX39 1UX",
    "wof:placetype":"postalcode"
},
  "geometry": {"coordinates":[-4.20600833034007,51.03810809553878],"type":"Point"}
}