{
  "type": "Feature",
  "properties": {
    "iso:country":"GB",
    "wof:name":"CM19 4QQ",
    "wof:placetype":"postalcode"
},
  "geometry": {"coordinates":[0.08726999884075,51.75050832197859],"type":"Point"}
}