{
  "type": "Feature",
  "properties": {
    "date:inception_lower": "1980-01-01",
    "date:inception_upper": "1980-01-01",
    "iso:country": "GB",
    "wof:name": "CM19 4QQ",
    "wof:placetype": "postalcode"
  },
  "geometry": {"coordinates":[0.08727,51.750508],"type":"Point"}
}
