{
  "type": "Feature",
  "properties": {
    "iso:country":"GB",
    "wof:name":"EX5 2BU",
    "wof:placetype":"postalcode"
},
  "geometry": {"coordinates":[-3.36384694167652,50.71909125412709],"type":"Point"}
}