{
  "type": "Feature",
  "properties": {
    "iso:country": "GB",
    "wof:name": "EX5 2BU",
    "wof:placetype": "postalcode"
  },
  "geometry": {"coordinates":[-3.363847,50.719091],"type":"Point"}
}
