{
  "type": "Feature",
  "properties": {
    "iso:country": "GB",
    "wof:name": "RG7 3EX",
    "wof:placetype": "postalcode"
  },
  "geometry": {"coordinates":[-1.06328,51.397894],"type":"Point"}
}
