{
  "type": "Feature",
  "properties": {
    "iso:country":"GB",
    "wof:name":"RG7 3EX",
    "wof:placetype":"postalcode"
},
  "geometry": {"coordinates":[-1.06329941916119,51.39789332720876],"type":"Point"}
}