{
  "type": "Feature",
  "properties": {
    "iso:country": "GB",
    "wof:name": "BA16 0RU",
    "wof:placetype": "postalcode"
  },
  "geometry": {"coordinates":[-2.746216,51.113995],"type":"Point"}
}
