{
  "type": "Feature",
  "properties": {
    "iso:country":"GB",
    "wof:name":"NG23 5GG",
    "wof:placetype":"postalcode"
},
  "geometry": {"coordinates":[-0.75900137814945,52.99157533045989],"type":"Point"}
}