{
  "type": "Feature",
  "properties": {
    "iso:country": "GB",
    "wof:name": "NG23 5GG",
    "wof:placetype": "postalcode"
  },
  "geometry": {"coordinates":[-0.759001,52.991575],"type":"Point"}
}
