{
  "type": "Feature",
  "properties": {
    "iso:country":"GB",
    "wof:name":"HD6 2PD",
    "wof:placetype":"postalcode"
},
  "geometry": {"coordinates":[-1.80279245895851,53.71470258607474],"type":"Point"}
}