{
  "type": "Feature",
  "properties": {
    "date:inception_lower": "1980-01-01",
    "date:inception_upper": "1980-01-01",
    "iso:country": "GB",
    "wof:name": "PL6 8PQ",
    "wof:placetype": "postalcode"
  },
  "geometry": {"coordinates":[-4.092999,50.398683],"type":"Point"}
}
