{
  "type": "Feature",
  "properties": {
    "iso:country":"GB",
    "wof:name":"RH5 4AG",
    "wof:placetype":"postalcode"
},
  "geometry": {"coordinates":[-0.32191645569403,51.23184803463025],"type":"Point"}
}