{
  "type": "Feature",
  "properties": {
    "iso:country": "GB",
    "wof:name": "TR12 6TJ",
    "wof:placetype": "postalcode"
  },
  "geometry": {"coordinates":[-5.10081,50.028609],"type":"Point"}
}
