{
  "type": "Feature",
  "properties": {
    "iso:country":"GB",
    "wof:name":"TR12 6TJ",
    "wof:placetype":"postalcode"
},
  "geometry": {"coordinates":[-5.10117704167272,50.02902488260856],"type":"Point"}
}