{
  "type": "Feature",
  "properties": {
    "iso:country":"GB",
    "wof:name":"CM9 8SW",
    "wof:placetype":"postalcode"
},
  "geometry": {"coordinates":[0.84028872177456,51.7570377824049],"type":"Point"}
}