{
  "type": "Feature",
  "properties": {
    "iso:country":"GB",
    "wof:name":"NP8 1DG",
    "wof:placetype":"postalcode"
},
  "geometry": {"coordinates":[-3.13946839633095,51.86242750272432],"type":"Point"}
}