{
  "type": "Feature",
  "properties": {
    "iso:country": "GB",
    "wof:name": "NG31 6SJ",
    "wof:placetype": "postalcode"
  },
  "geometry": {"coordinates":[-0.640223,52.912531],"type":"Point"}
}
