{
  "type": "Feature",
  "properties": {
    "date:inception_lower": "1980-01-01",
    "date:inception_upper": "1980-01-01",
    "iso:country": "GB",
    "wof:name": "NG31 6SJ",
    "wof:placetype": "postalcode"
  },
  "geometry": {"coordinates":[-0.640223,52.912531],"type":"Point"}
}
