{
  "type": "Feature",
  "properties": {
    "iso:country": "GB",
    "wof:name": "PL25 5NS",
    "wof:placetype": "postalcode"
  },
  "geometry": {"coordinates":[-4.798537,50.340482],"type":"Point"}
}
