{
  "type": "Feature",
  "properties": {
    "iso:country":"GB",
    "wof:name":"BA14 0HB",
    "wof:placetype":"postalcode"
},
  "geometry": {"coordinates":[-2.22365585092523,51.30683678665622],"type":"Point"}
}