{
  "type": "Feature",
  "properties": {
    "iso:country":"GB",
    "wof:name":"PA34 5NU",
    "wof:placetype":"postalcode"
},
  "geometry": {"coordinates":[-5.47286874190633,56.41665939282705],"type":"Point"}
}