{
  "type": "Feature",
  "properties": {
    "iso:country": "GB",
    "wof:name": "WN8 0HY",
    "wof:placetype": "postalcode"
  },
  "geometry": {"coordinates":[-2.731511,53.543387],"type":"Point"}
}
