{
  "type": "Feature",
  "properties": {
    "iso:country":"GB",
    "wof:name":"TN22 3XU",
    "wof:placetype":"postalcode"
},
  "geometry": {"coordinates":[0.06023550500079,50.99520992397981],"type":"Point"}
}