{
  "type": "Feature",
  "properties": {
    "iso:country":"GB",
    "wof:name":"TQ5 0EE",
    "wof:placetype":"postalcode"
},
  "geometry": {"coordinates":[-3.5236363520199,50.38573585497525],"type":"Point"}
}