{
  "type": "Feature",
  "properties": {
    "date:inception_lower":"1992-01-01",
    "date:inception_upper":"1992-01-31",
    "iso:country":"GB",
    "wof:name":"S64 0NE",
    "wof:placetype":"postalcode"
},
  "geometry": {"coordinates":[-1.292126,53.508612],"type":"Point"}
}