{
  "type": "Feature",
  "properties": {
    "iso:country": "GB",
    "wof:name": "S64 0NE",
    "wof:placetype": "postalcode"
  },
  "geometry": {"coordinates":[-1.292126,53.508612],"type":"Point"}
}
