{
  "type": "Feature",
  "properties": {
    "iso:country": "GB",
    "wof:name": "TN29 0JT",
    "wof:placetype": "postalcode"
  },
  "geometry": {"coordinates":[1.004459,51.035242],"type":"Point"}
}
