{
  "type": "Feature",
  "properties": {
    "date:inception_lower": "1980-01-01",
    "date:inception_upper": "1980-01-01",
    "iso:country": "GB",
    "wof:name": "TN29 0JT",
    "wof:placetype": "postalcode"
  },
  "geometry": {"coordinates":[1.004459,51.035242],"type":"Point"}
}
