{
  "type": "Feature",
  "properties": {
    "iso:country":"GB",
    "wof:name":"TN29 0JT",
    "wof:placetype":"postalcode"
},
  "geometry": {"coordinates":[1.00436903600138,51.03526859268318],"type":"Point"}
}