{
  "type": "Feature",
  "properties": {
    "iso:country":"GB",
    "wof:name":"CB9 0AA",
    "wof:placetype":"postalcode"
},
  "geometry": {"coordinates":[0.44481994361782,52.08915080745887],"type":"Point"}
}