{
  "type": "Feature",
  "properties": {
    "date:inception_lower": "1980-01-01",
    "date:inception_upper": "1980-01-01",
    "iso:country": "GB",
    "wof:name": "CB9 0AA",
    "wof:placetype": "postalcode"
  },
  "geometry": {"coordinates":[0.44482,52.089151],"type":"Point"}
}
