{
  "type": "Feature",
  "properties": {
    "iso:country":"GB",
    "wof:name":"HA5 1HH",
    "wof:placetype":"postalcode"
},
  "geometry": {"coordinates":[-0.38258462117366,51.58818948827211],"type":"Point"}
}