{
  "type": "Feature",
  "properties": {
    "date:inception_lower": "1980-01-01",
    "date:inception_upper": "1980-01-01",
    "iso:country": "GB",
    "wof:name": "NE29 0ER",
    "wof:placetype": "postalcode"
  },
  "geometry": {"coordinates":[-1.455972,55.007631],"type":"Point"}
}
