{
  "type": "Feature",
  "properties": {
    "date:inception_lower": "1980-01-01",
    "date:inception_upper": "1980-01-01",
    "iso:country": "GB",
    "wof:name": "TD15 2JZ",
    "wof:placetype": "postalcode"
  },
  "geometry": {"coordinates":[-2.165804,55.717753],"type":"Point"}
}
