{
  "type": "Feature",
  "properties": {
    "iso:country":"GB",
    "wof:name":"CM19 5RQ",
    "wof:placetype":"postalcode"
},
  "geometry": {"coordinates":[0.07171905075752,51.74690777450297],"type":"Point"}
}