{
  "type": "Feature",
  "properties": {
    "iso:country": "GB",
    "wof:name": "SN7 7AP",
    "wof:placetype": "postalcode"
  },
  "geometry": {"coordinates":[-1.581345,51.656231],"type":"Point"}
}
