{
  "type": "Feature",
  "properties": {
    "iso:country":"GB",
    "wof:name":"SN7 7AP",
    "wof:placetype":"postalcode"
},
  "geometry": {"coordinates":[-1.58187330038636,51.65695769706906],"type":"Point"}
}