{
  "type": "Feature",
  "properties": {
    "iso:country":"GB",
    "wof:name":"CV35 8EA",
    "wof:placetype":"postalcode"
},
  "geometry": {"coordinates":[-1.6025040207237,52.23477993843874],"type":"Point"}
}