{
  "type": "Feature",
  "properties": {
    "date:inception_lower":"1980-01-01",
    "date:inception_upper":"1980-01-31",
    "iso:country":"GB",
    "wof:name":"CV35 8EA",
    "wof:placetype":"postalcode"
},
  "geometry": {"coordinates":[-1.602507,52.234759],"type":"Point"}
}