{
  "type": "Feature",
  "properties": {
    "date:inception_lower": "1980-01-01",
    "date:inception_upper": "1980-01-01",
    "iso:country": "GB",
    "wof:name": "NG19 9NE",
    "wof:placetype": "postalcode"
  },
  "geometry": {"coordinates":[-1.198417,53.161408],"type":"Point"}
}
