{
  "type": "Feature",
  "properties": {
    "iso:country":"GB",
    "wof:name":"NG19 9NE",
    "wof:placetype":"postalcode"
},
  "geometry": {"coordinates":[-1.19849412493364,53.16136346039811],"type":"Point"}
}