{
  "type": "Feature",
  "properties": {
    "date:inception_lower":"1980-01-01",
    "date:inception_upper":"1980-01-31",
    "iso:country":"GB",
    "wof:name":"BD6 1DR",
    "wof:placetype":"postalcode"
},
  "geometry": {"coordinates":[-1.764589,53.761875],"type":"Point"}
}