{
  "type": "Feature",
  "properties": {
    "iso:country":"GB",
    "wof:name":"BD6 1DR",
    "wof:placetype":"postalcode"
},
  "geometry": {"coordinates":[-1.76458918219706,53.76187498833656],"type":"Point"}
}