{
  "type": "Feature",
  "properties": {
    "iso:country": "GB",
    "wof:name": "BD6 1DR",
    "wof:placetype": "postalcode"
  },
  "geometry": {"coordinates":[-1.764589,53.761875],"type":"Point"}
}
