{
  "type": "Feature",
  "properties": {
    "iso:country":"GB",
    "wof:name":"PR4 0HR",
    "wof:placetype":"postalcode"
},
  "geometry": {"coordinates":[-2.80299440087087,53.81459329791038],"type":"Point"}
}