{
  "type": "Feature",
  "properties": {
    "iso:country":"GB",
    "wof:name":"KT20 7SA",
    "wof:placetype":"postalcode"
},
  "geometry": {"coordinates":[-0.25008894798129,51.28265723480466],"type":"Point"}
}