{
  "type": "Feature",
  "properties": {
    "iso:country": "GB",
    "wof:name": "SE26 5DQ",
    "wof:placetype": "postalcode"
  },
  "geometry": {"coordinates":[-0.05056,51.424901],"type":"Point"}
}
