{
  "type": "Feature",
  "properties": {
    "date:inception_lower":"1980-01-01",
    "date:inception_upper":"1980-01-31",
    "iso:country":"GB",
    "wof:name":"SE26 5DQ",
    "wof:placetype":"postalcode"
},
  "geometry": {"coordinates":[-0.05056,51.424901],"type":"Point"}
}