{
  "type": "Feature",
  "properties": {
    "iso:country":"GB",
    "wof:name":"SE26 5DQ",
    "wof:placetype":"postalcode"
},
  "geometry": {"coordinates":[-0.0505605193819,51.42490085393951],"type":"Point"}
}