{
  "type": "Feature",
  "properties": {
    "date:inception_lower": "1980-01-01",
    "date:inception_upper": "1980-01-01",
    "iso:country": "GB",
    "wof:name": "DD1 5BJ",
    "wof:placetype": "postalcode"
  },
  "geometry": {"coordinates":[-2.985836,56.461175],"type":"Point"}
}
