{
  "type": "Feature",
  "properties": {
    "iso:country":"GB",
    "wof:name":"DD1 5BJ",
    "wof:placetype":"postalcode"
},
  "geometry": {"coordinates":[-2.98583245597032,56.46118486800132],"type":"Point"}
}