{
  "type": "Feature",
  "properties": {
    "date:inception_lower": "1980-01-01",
    "date:inception_upper": "1980-01-01",
    "iso:country": "GB",
    "wof:name": "ST12 9DY",
    "wof:placetype": "postalcode"
  },
  "geometry": {"coordinates":[-2.173499,52.939537],"type":"Point"}
}
