{
  "type": "Feature",
  "properties": {
    "date:inception_lower": "1992-08-01",
    "date:inception_upper": "1992-08-01",
    "iso:country": "GB",
    "wof:name": "LE67 4SG",
    "wof:placetype": "postalcode"
  },
  "geometry": {"coordinates":[-1.339025,52.720882],"type":"Point"}
}
