{
  "type": "Feature",
  "properties": {
    "iso:country":"GB",
    "wof:name":"LE67 4SG",
    "wof:placetype":"postalcode"
},
  "geometry": {"coordinates":[-1.33902488145834,52.72088150544009],"type":"Point"}
}