{
  "type": "Feature",
  "properties": {
    "iso:country":"GB",
    "wof:name":"CF81 9AW",
    "wof:placetype":"postalcode"
},
  "geometry": {"coordinates":[-3.22671176902046,51.69544964330817],"type":"Point"}
}