{
  "type": "Feature",
  "properties": {
    "iso:country":"GB",
    "wof:name":"KY16 0JX",
    "wof:placetype":"postalcode"
},
  "geometry": {"coordinates":[-2.88221226204486,56.37909185096203],"type":"Point"}
}