{
  "type": "Feature",
  "properties": {
    "date:inception_lower": "1981-09-01",
    "date:inception_upper": "1981-09-01",
    "iso:country": "GB",
    "wof:name": "WR14 4XQ",
    "wof:placetype": "postalcode"
  },
  "geometry": {"coordinates":[-2.330057,52.091714],"type":"Point"}
}
