{
  "type": "Feature",
  "properties": {
    "iso:country": "GB",
    "wof:name": "WR14 4XQ",
    "wof:placetype": "postalcode"
  },
  "geometry": {"coordinates":[-2.330057,52.091714],"type":"Point"}
}
