{
  "type": "Feature",
  "properties": {
    "iso:country":"GB",
    "wof:name":"NR20 4HP",
    "wof:placetype":"postalcode"
},
  "geometry": {"coordinates":[0.89011421474669,52.73566486113465],"type":"Point"}
}