{
  "type": "Feature",
  "properties": {
    "iso:country":"GB",
    "wof:name":"NG23 7RA",
    "wof:placetype":"postalcode"
},
  "geometry": {"coordinates":[-0.75534424590661,53.14454991230504],"type":"Point"}
}