{
  "type": "Feature",
  "properties": {
    "iso:country":"GB",
    "wof:name":"KA22 8HU",
    "wof:placetype":"postalcode"
},
  "geometry": {"coordinates":[-4.81438025334554,55.64375589233187],"type":"Point"}
}