{
  "type": "Feature",
  "properties": {
    "iso:country":"GB",
    "wof:name":"TQ7 2DW",
    "wof:placetype":"postalcode"
},
  "geometry": {"coordinates":[-3.74851322763345,50.29091347614208],"type":"Point"}
}