{
  "type": "Feature",
  "properties": {
    "iso:country": "GB",
    "wof:name": "TQ7 2DW",
    "wof:placetype": "postalcode"
  },
  "geometry": {"coordinates":[-3.748513,50.290913],"type":"Point"}
}
