{
  "type": "Feature",
  "properties": {
    "iso:country":"GB",
    "wof:name":"SO50 5NA",
    "wof:placetype":"postalcode"
},
  "geometry": {"coordinates":[-1.35453735815341,50.96239394210204],"type":"Point"}
}