{
  "type": "Feature",
  "properties": {
    "iso:country":"GB",
    "wof:name":"E14 0HN",
    "wof:placetype":"postalcode"
},
  "geometry": {"coordinates":[-0.00926704619037,51.50948472819079],"type":"Point"}
}