{
  "type": "Feature",
  "properties": {
    "date:inception_lower": "1980-01-01",
    "date:inception_upper": "1980-01-01",
    "iso:country": "GB",
    "wof:name": "GL5 4DD",
    "wof:placetype": "postalcode"
  },
  "geometry": {"coordinates":[-2.23337,51.755077],"type":"Point"}
}
