{
  "type": "Feature",
  "properties": {
    "iso:country":"GB",
    "wof:name":"GL5 4DD",
    "wof:placetype":"postalcode"
},
  "geometry": {"coordinates":[-2.23337008989744,51.75507670924743],"type":"Point"}
}