{
  "type": "Feature",
  "properties": {
    "iso:country":"GB",
    "wof:name":"CO3 3DN",
    "wof:placetype":"postalcode"
},
  "geometry": {"coordinates":[0.89160984220886,51.88419719278522],"type":"Point"}
}