{
  "type": "Feature",
  "properties": {
    "iso:country": "GB",
    "wof:name": "CO3 3DN",
    "wof:placetype": "postalcode"
  },
  "geometry": {"coordinates":[0.89161,51.884197],"type":"Point"}
}
