{
  "type": "Feature",
  "properties": {
    "date:inception_lower": "1998-06-01",
    "date:inception_upper": "1998-06-01",
    "iso:country": "GB",
    "wof:name": "HD8 8QE",
    "wof:placetype": "postalcode"
  },
  "geometry": {"coordinates":[-1.66295,53.573132],"type":"Point"}
}
