{
  "type": "Feature",
  "properties": {
    "iso:country":"GB",
    "wof:name":"HD8 8QE",
    "wof:placetype":"postalcode"
},
  "geometry": {"coordinates":[-1.66294965212968,53.57313204676847],"type":"Point"}
}