{
  "type": "Feature",
  "properties": {
    "iso:country":"GB",
    "wof:name":"G69 8LF",
    "wof:placetype":"postalcode"
},
  "geometry": {"coordinates":[-4.08806997587402,55.8860531954996],"type":"Point"}
}