{
  "type": "Feature",
  "properties": {
    "date:inception_lower": "2005-01-01",
    "date:inception_upper": "2005-01-01",
    "iso:country": "GB",
    "wof:name": "G69 8LF",
    "wof:placetype": "postalcode"
  },
  "geometry": {"coordinates":[-4.08807,55.886053],"type":"Point"}
}
