{
  "type": "Feature",
  "properties": {
    "date:inception_lower": "1997-12-01",
    "date:inception_upper": "1997-12-01",
    "iso:country": "GB",
    "wof:name": "BS40 7SQ",
    "wof:placetype": "postalcode"
  },
  "geometry": {"coordinates":[-2.698215,51.329512],"type":"Point"}
}
