{
  "type": "Feature",
  "properties": {
    "iso:country":"GB",
    "wof:name":"TQ12 3NG",
    "wof:placetype":"postalcode"
},
  "geometry": {"coordinates":[-3.59773745048293,50.55701597651572],"type":"Point"}
}