{
  "type": "Feature",
  "properties": {
    "iso:country": "GB",
    "wof:name": "BL3 6LG",
    "wof:placetype": "postalcode"
  },
  "geometry": {"coordinates":[-2.446328,53.567937],"type":"Point"}
}
