{
  "type": "Feature",
  "properties": {
    "iso:country": "GB",
    "wof:name": "L32 0UR",
    "wof:placetype": "postalcode"
  },
  "geometry": {"coordinates":[-2.897058,53.484111],"type":"Point"}
}
