{
  "type": "Feature",
  "properties": {
    "iso:country":"GB",
    "wof:name":"L32 0UR",
    "wof:placetype":"postalcode"
},
  "geometry": {"coordinates":[-2.89705843318317,53.4841112067402],"type":"Point"}
}