{
  "type": "Feature",
  "properties": {
    "iso:country": "GB",
    "wof:name": "DE11 0XL",
    "wof:placetype": "postalcode"
  },
  "geometry": {"coordinates":[-1.560055,52.788358],"type":"Point"}
}
