{
  "type": "Feature",
  "properties": {
    "iso:country": "GB",
    "wof:name": "CA8 7HS",
    "wof:placetype": "postalcode"
  },
  "geometry": {"coordinates":[-2.540432,54.990032],"type":"Point"}
}
