{
  "type": "Feature",
  "properties": {
    "iso:country":"GB",
    "wof:name":"CA8 7HS",
    "wof:placetype":"postalcode"
},
  "geometry": {"coordinates":[-2.54043191770518,54.99003188962516],"type":"Point"}
}