{
  "type": "Feature",
  "properties": {
    "iso:country":"GB",
    "wof:name":"S42 7LJ",
    "wof:placetype":"postalcode"
},
  "geometry": {"coordinates":[-1.48535121653672,53.20708359062843],"type":"Point"}
}