{
  "type": "Feature",
  "properties": {
    "date:inception_lower": "1980-01-01",
    "date:inception_upper": "1980-01-01",
    "iso:country": "GB",
    "wof:name": "S42 7LJ",
    "wof:placetype": "postalcode"
  },
  "geometry": {"coordinates":[-1.485351,53.207084],"type":"Point"}
}
