{
  "type": "Feature",
  "properties": {
    "iso:country": "GB",
    "wof:name": "S42 7LJ",
    "wof:placetype": "postalcode"
  },
  "geometry": {"coordinates":[-1.485351,53.207084],"type":"Point"}
}
