{
  "type": "Feature",
  "properties": {
    "iso:country":"GB",
    "wof:name":"L40 4AX",
    "wof:placetype":"postalcode"
},
  "geometry": {"coordinates":[-2.83569361270608,53.60895861995929],"type":"Point"}
}