{
  "type": "Feature",
  "properties": {
    "iso:country": "GB",
    "wof:name": "L40 4AX",
    "wof:placetype": "postalcode"
  },
  "geometry": {"coordinates":[-2.835694,53.608959],"type":"Point"}
}
