{
  "type": "Feature",
  "properties": {
    "date:inception_lower": "1980-01-01",
    "date:inception_upper": "1980-01-01",
    "iso:country": "GB",
    "wof:name": "L40 4AX",
    "wof:placetype": "postalcode"
  },
  "geometry": {"coordinates":[-2.835694,53.608959],"type":"Point"}
}
