{
  "type": "Feature",
  "properties": {
    "iso:country": "GB",
    "wof:name": "TS23 3NX",
    "wof:placetype": "postalcode"
  },
  "geometry": {"coordinates":[-1.274884,54.617259],"type":"Point"}
}
