{
  "type": "Feature",
  "properties": {
    "date:inception_lower": "1992-08-01",
    "date:inception_upper": "1992-08-01",
    "iso:country": "GB",
    "wof:name": "WN4 0YX",
    "wof:placetype": "postalcode"
  },
  "geometry": {"coordinates":[-2.6643,53.481947],"type":"Point"}
}
