{
  "type": "Feature",
  "properties": {
    "iso:country":"GB",
    "wof:name":"B14 6DA",
    "wof:placetype":"postalcode"
},
  "geometry": {"coordinates":[-1.89694526918476,52.42360420990332],"type":"Point"}
}