{
  "type": "Feature",
  "properties": {
    "iso:country": "GB",
    "wof:name": "B14 6DA",
    "wof:placetype": "postalcode"
  },
  "geometry": {"coordinates":[-1.896945,52.423604],"type":"Point"}
}
