{
  "type": "Feature",
  "properties": {
    "iso:country":"GB",
    "wof:name":"E17 9HH",
    "wof:placetype":"postalcode"
},
  "geometry": {"coordinates":[-0.00381864035961,51.58397693715767],"type":"Point"}
}