{
  "type": "Feature",
  "properties": {
    "iso:country": "GB",
    "wof:name": "SW19 8JF",
    "wof:placetype": "postalcode"
  },
  "geometry": {"coordinates":[-0.192239,51.427963],"type":"Point"}
}
