{
  "type": "Feature",
  "properties": {
    "iso:country": "GB",
    "wof:name": "CB8 9LL",
    "wof:placetype": "postalcode"
  },
  "geometry": {"coordinates":[0.436072,52.151206],"type":"Point"}
}
