{
  "type": "Feature",
  "properties": {
    "iso:country":"GB",
    "wof:name":"WA15 6QU",
    "wof:placetype":"postalcode"
},
  "geometry": {"coordinates":[-2.32602687501582,53.40047469427697],"type":"Point"}
}