{
  "type": "Feature",
  "properties": {
    "iso:country":"GB",
    "wof:name":"HX7 5JS",
    "wof:placetype":"postalcode"
},
  "geometry": {"coordinates":[-1.97504554248604,53.72757102616502],"type":"Point"}
}