{
  "type": "Feature",
  "properties": {
    "iso:country":"GB",
    "wof:name":"NG4 4PX",
    "wof:placetype":"postalcode"
},
  "geometry": {"coordinates":[-1.06166080159465,53.00180077696486],"type":"Point"}
}