{
  "type": "Feature",
  "properties": {
    "iso:country":"GB",
    "wof:name":"AL9 5NH",
    "wof:placetype":"postalcode"
},
  "geometry": {"coordinates":[-0.21167984387396,51.75424183055539],"type":"Point"}
}