{
  "type": "Feature",
  "properties": {
    "iso:country":"GB",
    "wof:name":"OL1 4RF",
    "wof:placetype":"postalcode"
},
  "geometry": {"coordinates":[-2.07130761453155,53.56898267013038],"type":"Point"}
}