{
  "type": "Feature",
  "properties": {
    "iso:country": "GB",
    "wof:name": "PO19 7HJ",
    "wof:placetype": "postalcode"
  },
  "geometry": {"coordinates":[-0.769686,50.837726],"type":"Point"}
}
