{
  "type": "Feature",
  "properties": {
    "date:inception_lower":"2000-12-01",
    "date:inception_upper":"2000-12-31",
    "iso:country":"GB",
    "wof:name":"W1D 2LW",
    "wof:placetype":"postalcode"
},
  "geometry": {"coordinates":[-0.140733,51.515275],"type":"Point"}
}