{
  "type": "Feature",
  "properties": {
    "iso:country":"GB",
    "wof:name":"W1D 2LW",
    "wof:placetype":"postalcode"
},
  "geometry": {"coordinates":[-0.14073315066664,51.51527550468161],"type":"Point"}
}