{
  "type": "Feature",
  "properties": {
    "iso:country": "GB",
    "wof:name": "CH45 1LF",
    "wof:placetype": "postalcode"
  },
  "geometry": {"coordinates":[-3.036451,53.43501],"type":"Point"}
}
