{
  "type": "Feature",
  "properties": {
    "iso:country":"GB",
    "wof:name":"RG6 5GU",
    "wof:placetype":"postalcode"
},
  "geometry": {"coordinates":[-0.93732924106603,51.42855159173313],"type":"Point"}
}