{
  "type": "Feature",
  "properties": {
    "date:inception_lower": "1980-01-01",
    "date:inception_upper": "1980-01-01",
    "iso:country": "GB",
    "wof:name": "MK40 2BD",
    "wof:placetype": "postalcode"
  },
  "geometry": {"coordinates":[-0.484346,52.14453],"type":"Point"}
}
