{
  "type": "Feature",
  "properties": {
    "date:inception_lower": "1999-06-01",
    "date:inception_upper": "1999-06-01",
    "iso:country": "GB",
    "wof:name": "LS25 7RT",
    "wof:placetype": "postalcode"
  },
  "geometry": {"coordinates":[-1.383946,53.77815],"type":"Point"}
}
