{
  "type": "Feature",
  "properties": {
    "iso:country":"GB",
    "wof:name":"NN6 9TY",
    "wof:placetype":"postalcode"
},
  "geometry": {"coordinates":[-0.82822362998044,52.35729385063999],"type":"Point"}
}