{
  "type": "Feature",
  "properties": {
    "date:inception_lower":"1997-12-01",
    "date:inception_upper":"1997-12-31",
    "iso:country":"GB",
    "wof:name":"NN6 9TY",
    "wof:placetype":"postalcode"
},
  "geometry": {"coordinates":[-0.828209,52.357308],"type":"Point"}
}