{
  "type": "Feature",
  "properties": {
    "iso:country": "GB",
    "wof:name": "NN6 9TY",
    "wof:placetype": "postalcode"
  },
  "geometry": {"coordinates":[-0.822861,52.361291],"type":"Point"}
}
