{
  "type": "Feature",
  "properties": {
    "iso:country": "GB",
    "wof:name": "TN11 8AD",
    "wof:placetype": "postalcode"
  },
  "geometry": {"coordinates":[0.197243,51.166251],"type":"Point"}
}
