{
  "type": "Feature",
  "properties": {
    "iso:country":"GB",
    "wof:name":"TN11 8AD",
    "wof:placetype":"postalcode"
},
  "geometry": {"coordinates":[0.19724291971781,51.16625141405838],"type":"Point"}
}