{
  "type": "Feature",
  "properties": {
    "iso:country":"GB",
    "wof:name":"SW9 0TE",
    "wof:placetype":"postalcode"
},
  "geometry": {"coordinates":[-0.11575041550825,51.46929351094896],"type":"Point"}
}