{
  "type": "Feature",
  "properties": {
    "iso:country": "GB",
    "wof:name": "SW9 0TE",
    "wof:placetype": "postalcode"
  },
  "geometry": {"coordinates":[-0.11575,51.469294],"type":"Point"}
}
