{
  "type": "Feature",
  "properties": {
    "date:inception_lower": "1980-01-01",
    "date:inception_upper": "1980-01-01",
    "iso:country": "GB",
    "wof:name": "LU2 8LZ",
    "wof:placetype": "postalcode"
  },
  "geometry": {"coordinates":[-0.3819,51.935006],"type":"Point"}
}
