{
  "type": "Feature",
  "properties": {
    "date:inception_lower":"2017-08-01",
    "date:inception_upper":"2017-08-31",
    "iso:country":"GB",
    "wof:name":"HU3 6UB",
    "wof:placetype":"postalcode"
},
  "geometry": {"coordinates":[-0.38589,53.742488],"type":"Point"}
}