{
  "type": "Feature",
  "properties": {
    "iso:country": "GB",
    "wof:name": "CH6 5FJ",
    "wof:placetype": "postalcode"
  },
  "geometry": {"coordinates":[-3.121824,53.238525],"type":"Point"}
}
