{
  "type": "Feature",
  "properties": {
    "date:inception_lower": "2018-12-01",
    "date:inception_upper": "2018-12-01",
    "iso:country": "GB",
    "wof:name": "CH6 5FJ",
    "wof:placetype": "postalcode"
  },
  "geometry": {"coordinates":[-3.121824,53.238525],"type":"Point"}
}
