{
  "type": "Feature",
  "properties": {
    "date:inception_lower": "2021-06-01",
    "date:inception_upper": "2021-06-01",
    "iso:country": "GB",
    "wof:name": "RG4 9EZ",
    "wof:placetype": "postalcode"
  },
  "geometry": {"coordinates":[-0.982297,51.511003],"type":"Point"}
}
