{
  "type": "Feature",
  "properties": {
    "iso:country":"GB",
    "wof:name":"LL53 6JB",
    "wof:placetype":"postalcode"
},
  "geometry": {"coordinates":[-4.56049499729072,52.92516389726605],"type":"Point"}
}