{
  "type": "Feature",
  "properties": {
    "iso:country": "GB",
    "wof:name": "LL53 6JB",
    "wof:placetype": "postalcode"
  },
  "geometry": {"coordinates":[-4.560495,52.925164],"type":"Point"}
}
