{
  "type": "Feature",
  "properties": {
    "iso:country":"GB",
    "wof:name":"NE34 0BE",
    "wof:placetype":"postalcode"
},
  "geometry": {"coordinates":[-1.44350567812815,54.97067717393543],"type":"Point"}
}