{
  "type": "Feature",
  "properties": {
    "iso:country":"GB",
    "wof:name":"SP1 1JH",
    "wof:placetype":"postalcode"
},
  "geometry": {"coordinates":[-1.79454739613093,51.069015826337],"type":"Point"}
}