{
  "type": "Feature",
  "properties": {
    "iso:country":"GB",
    "wof:name":"NG21 0HY",
    "wof:placetype":"postalcode"
},
  "geometry": {"coordinates":[-1.09869104064563,53.11765461676123],"type":"Point"}
}