{
  "type": "Feature",
  "properties": {
    "iso:country": "GB",
    "wof:name": "GU8 5FA",
    "wof:placetype": "postalcode"
  },
  "geometry": {"coordinates":[-0.649042,51.167936],"type":"Point"}
}
