{
  "type": "Feature",
  "properties": {
    "iso:country":"GB",
    "wof:name":"ME1 2QW",
    "wof:placetype":"postalcode"
},
  "geometry": {"coordinates":[0.51217773321728,51.37109946960907],"type":"Point"}
}