{
  "type": "Feature",
  "properties": {
    "date:inception_lower": "2006-09-01",
    "date:inception_upper": "2006-09-01",
    "iso:country": "GB",
    "wof:name": "CB23 6DS",
    "wof:placetype": "postalcode"
  },
  "geometry": {"coordinates":[-0.085924,52.21726],"type":"Point"}
}
