{
  "type": "Feature",
  "properties": {
    "iso:country": "GB",
    "wof:name": "CB23 6DS",
    "wof:placetype": "postalcode"
  },
  "geometry": {"coordinates":[-0.085924,52.21726],"type":"Point"}
}
