{
  "type": "Feature",
  "properties": {
    "iso:country":"GB",
    "wof:name":"YO21 2NN",
    "wof:placetype":"postalcode"
},
  "geometry": {"coordinates":[-0.93988230450004,54.43580650102304],"type":"Point"}
}