{
  "type": "Feature",
  "properties": {
    "date:inception_lower": "1980-01-01",
    "date:inception_upper": "1980-01-01",
    "iso:country": "GB",
    "wof:name": "YO21 2NN",
    "wof:placetype": "postalcode"
  },
  "geometry": {"coordinates":[-0.938731,54.440402],"type":"Point"}
}
