{
  "type": "Feature",
  "properties": {
    "date:inception_lower": "1990-02-01",
    "date:inception_upper": "1990-02-01",
    "iso:country": "GB",
    "wof:name": "SM7 2DX",
    "wof:placetype": "postalcode"
  },
  "geometry": {"coordinates":[-0.203794,51.319573],"type":"Point"}
}
