{
  "type": "Feature",
  "properties": {
    "iso:country":"GB",
    "wof:name":"SM7 2DX",
    "wof:placetype":"postalcode"
},
  "geometry": {"coordinates":[-0.20379437967098,51.31957271892242],"type":"Point"}
}