{
  "type": "Feature",
  "properties": {
    "iso:country": "GB",
    "wof:name": "SM7 2DX",
    "wof:placetype": "postalcode"
  },
  "geometry": {"coordinates":[-0.203794,51.319573],"type":"Point"}
}
