{
  "type": "Feature",
  "properties": {
    "iso:country":"GB",
    "wof:name":"NW9 5AR",
    "wof:placetype":"postalcode"
},
  "geometry": {"coordinates":[-0.25925277415411,51.59562419668075],"type":"Point"}
}