{
  "type": "Feature",
  "properties": {
    "iso:country": "GB",
    "wof:name": "SA2 9HR",
    "wof:placetype": "postalcode"
  },
  "geometry": {"coordinates":[-3.997662,51.62681],"type":"Point"}
}
