{
  "type": "Feature",
  "properties": {
    "date:inception_lower": "1992-01-01",
    "date:inception_upper": "1992-01-01",
    "iso:country": "GB",
    "wof:name": "SA2 9HR",
    "wof:placetype": "postalcode"
  },
  "geometry": {"coordinates":[-3.997662,51.62681],"type":"Point"}
}
