{
  "type": "Feature",
  "properties": {
    "iso:country":"GB",
    "wof:name":"SA2 9HR",
    "wof:placetype":"postalcode"
},
  "geometry": {"coordinates":[-3.9976618316904,51.62681018852702],"type":"Point"}
}