{
  "type": "Feature",
  "properties": {
    "date:inception_lower": "2008-07-01",
    "date:inception_upper": "2008-07-01",
    "iso:country": "GB",
    "wof:name": "M1 3BU",
    "wof:placetype": "postalcode"
  },
  "geometry": {"coordinates":[-2.234714,53.475986],"type":"Point"}
}
