{
  "type": "Feature",
  "properties": {
    "iso:country":"GB",
    "wof:name":"M1 3BU",
    "wof:placetype":"postalcode"
},
  "geometry": {"coordinates":[-2.23471429569828,53.47598612366762],"type":"Point"}
}