{
  "type": "Feature",
  "properties": {
    "date:inception_lower":"1980-01-01",
    "date:inception_upper":"1980-01-31",
    "iso:country":"GB",
    "wof:name":"B42 2AD",
    "wof:placetype":"postalcode"
},
  "geometry": {"coordinates":[-1.901726,52.535488],"type":"Point"}
}