{
  "type": "Feature",
  "properties": {
    "iso:country":"GB",
    "wof:name":"PE12 0RY",
    "wof:placetype":"postalcode"
},
  "geometry": {"coordinates":[-0.01139740220566,52.72701607201967],"type":"Point"}
}