{
  "type": "Feature",
  "properties": {
    "iso:country":"GB",
    "wof:name":"LS28 8HU",
    "wof:placetype":"postalcode"
},
  "geometry": {"coordinates":[-1.67736195338826,53.79046082721476],"type":"Point"}
}