{
  "type": "Feature",
  "properties": {
    "iso:country":"GB",
    "wof:name":"BS39 4DZ",
    "wof:placetype":"postalcode"
},
  "geometry": {"coordinates":[-2.56896595713634,51.36442001878655],"type":"Point"}
}