{
  "type": "Feature",
  "properties": {
    "iso:country":"GB",
    "wof:name":"BA3 5DE",
    "wof:placetype":"postalcode"
},
  "geometry": {"coordinates":[-2.4747767023133,51.24151673628985],"type":"Point"}
}