{
  "type": "Feature",
  "properties": {
    "date:inception_lower": "2005-03-01",
    "date:inception_upper": "2005-03-01",
    "iso:country": "GB",
    "wof:name": "AB39 2TB",
    "wof:placetype": "postalcode"
  },
  "geometry": {"coordinates":[-2.215759,56.964171],"type":"Point"}
}
