{
  "type": "Feature",
  "properties": {
    "iso:country":"GB",
    "wof:name":"NN18 0NP",
    "wof:placetype":"postalcode"
},
  "geometry": {"coordinates":[-0.71916485320439,52.48212989763235],"type":"Point"}
}