{
  "type": "Feature",
  "properties": {
    "date:inception_lower": "1980-01-01",
    "date:inception_upper": "1980-01-01",
    "iso:country": "GB",
    "wof:name": "LA14 5PZ",
    "wof:placetype": "postalcode"
  },
  "geometry": {"coordinates":[-3.217766,54.129932],"type":"Point"}
}
