{
  "type": "Feature",
  "properties": {
    "iso:country":"GB",
    "wof:name":"RG5 4NR",
    "wof:placetype":"postalcode"
},
  "geometry": {"coordinates":[-0.89886746024794,51.45720461956162],"type":"Point"}
}