{
  "type": "Feature",
  "properties": {
    "iso:country":"GB",
    "wof:name":"EX16 5PB",
    "wof:placetype":"postalcode"
},
  "geometry": {"coordinates":[-3.49938134934285,50.89301786437363],"type":"Point"}
}