{
  "type": "Feature",
  "properties": {
    "date:inception_lower": "1980-01-01",
    "date:inception_upper": "1980-01-01",
    "iso:country": "GB",
    "wof:name": "TN31 7JH",
    "wof:placetype": "postalcode"
  },
  "geometry": {"coordinates":[0.734168,50.951613],"type":"Point"}
}
