{
  "type": "Feature",
  "properties": {
    "iso:country":"GB",
    "wof:name":"DE23 6EU",
    "wof:placetype":"postalcode"
},
  "geometry": {"coordinates":[-1.51310112178402,52.90725860440671],"type":"Point"}
}