{
  "type": "Feature",
  "properties": {
    "iso:country":"GB",
    "wof:name":"PO40 9NG",
    "wof:placetype":"postalcode"
},
  "geometry": {"coordinates":[-1.53162297110981,50.68650955987427],"type":"Point"}
}