{
  "type": "Feature",
  "properties": {
    "iso:country": "GB",
    "wof:name": "SK8 6SQ",
    "wof:placetype": "postalcode"
  },
  "geometry": {"coordinates":[-2.20495,53.36825],"type":"Point"}
}
