{
  "type": "Feature",
  "properties": {
    "date:inception_lower":"1980-01-01",
    "date:inception_upper":"1980-01-31",
    "iso:country":"GB",
    "wof:name":"SK8 6SQ",
    "wof:placetype":"postalcode"
},
  "geometry": {"coordinates":[-2.20495,53.36825],"type":"Point"}
}