{
  "type": "Feature",
  "properties": {
    "date:inception_lower": "2005-10-01",
    "date:inception_upper": "2005-10-01",
    "iso:country": "GB",
    "wof:name": "HP10 8WU",
    "wof:placetype": "postalcode"
  },
  "geometry": {"coordinates":[-0.770389,51.622161],"type":"Point"}
}
