{
  "type": "Feature",
  "properties": {
    "iso:country":"GB",
    "wof:name":"EX16 8RF",
    "wof:placetype":"postalcode"
},
  "geometry": {"coordinates":[-3.50622988380591,50.85451130785798],"type":"Point"}
}