{
  "type": "Feature",
  "properties": {
    "iso:country": "GB",
    "wof:name": "GL2 9JP",
    "wof:placetype": "postalcode"
  },
  "geometry": {"coordinates":[-2.223266,51.873894],"type":"Point"}
}
