{
  "type": "Feature",
  "properties": {
    "date:inception_lower": "1980-01-01",
    "date:inception_upper": "1980-01-01",
    "iso:country": "GB",
    "wof:name": "CF38 2RD",
    "wof:placetype": "postalcode"
  },
  "geometry": {"coordinates":[-3.359155,51.562947],"type":"Point"}
}
