{
  "type": "Feature",
  "properties": {
    "iso:country":"GB",
    "wof:name":"CF38 2RD",
    "wof:placetype":"postalcode"
},
  "geometry": {"coordinates":[-3.35912735098781,51.56287286023537],"type":"Point"}
}