{
  "type": "Feature",
  "properties": {
    "iso:country": "GB",
    "wof:name": "GU46 6DS",
    "wof:placetype": "postalcode"
  },
  "geometry": {"coordinates":[-0.829457,51.332397],"type":"Point"}
}
