{
  "type": "Feature",
  "properties": {
    "iso:country":"GB",
    "wof:name":"GU46 6DS",
    "wof:placetype":"postalcode"
},
  "geometry": {"coordinates":[-0.82945676600496,51.33239722506606],"type":"Point"}
}