{
  "type": "Feature",
  "properties": {
    "iso:country": "GB",
    "wof:name": "SY24 5LS",
    "wof:placetype": "postalcode"
  },
  "geometry": {"coordinates":[-4.048219,52.478182],"type":"Point"}
}
