{
  "type": "Feature",
  "properties": {
    "iso:country":"GB",
    "wof:name":"SY24 5LS",
    "wof:placetype":"postalcode"
},
  "geometry": {"coordinates":[-4.04840241500364,52.47790161456498],"type":"Point"}
}