{
  "type": "Feature",
  "properties": {
    "iso:country":"GB",
    "wof:name":"TA3 5JH",
    "wof:placetype":"postalcode"
},
  "geometry": {"coordinates":[-3.04932520850209,51.01869399355618],"type":"Point"}
}