{
  "type": "Feature",
  "properties": {
    "date:inception_lower":"1980-01-01",
    "date:inception_upper":"1980-01-31",
    "iso:country":"GB",
    "wof:name":"SP4 0JG",
    "wof:placetype":"postalcode"
},
  "geometry": {"coordinates":[-1.700254,51.135111],"type":"Point"}
}