{
  "type": "Feature",
  "properties": {
    "iso:country": "GB",
    "wof:name": "SP4 0JG",
    "wof:placetype": "postalcode"
  },
  "geometry": {"coordinates":[-1.700254,51.135111],"type":"Point"}
}
