{
  "type": "Feature",
  "properties": {
    "iso:country":"GB",
    "wof:name":"SA33 6NA",
    "wof:placetype":"postalcode"
},
  "geometry": {"coordinates":[-4.37069189935302,51.89437417344801],"type":"Point"}
}