{
  "type": "Feature",
  "properties": {
    "iso:country":"GB",
    "wof:name":"ST3 7RZ",
    "wof:placetype":"postalcode"
},
  "geometry": {"coordinates":[-2.10302638828841,52.96942719964321],"type":"Point"}
}