{
  "type": "Feature",
  "properties": {
    "date:inception_lower": "2023-03-01",
    "date:inception_upper": "2023-03-01",
    "iso:country": "GB",
    "wof:name": "PR5 5BY",
    "wof:placetype": "postalcode"
  },
  "geometry": {"coordinates":[-2.686752,53.73815],"type":"Point"}
}
