{
  "type": "Feature",
  "properties": {
    "date:inception_lower": "2022-06-01",
    "date:inception_upper": "2022-06-01",
    "iso:country": "GB",
    "wof:name": "PR5 5BY",
    "wof:placetype": "postalcode"
  },
  "geometry": {"coordinates":[-2.686803,53.738527],"type":"Point"}
}
