{
  "type": "Feature",
  "properties": {
    "iso:country":"GB",
    "wof:name":"NW3 4DE",
    "wof:placetype":"postalcode"
},
  "geometry": {"coordinates":[-0.1662654088451,51.54953403141658],"type":"Point"}
}