{
  "type": "Feature",
  "properties": {
    "iso:country": "GB",
    "wof:name": "NW3 4DE",
    "wof:placetype": "postalcode"
  },
  "geometry": {"coordinates":[-0.166265,51.549534],"type":"Point"}
}
