{
  "type": "Feature",
  "properties": {
    "iso:country": "GB",
    "wof:name": "CV5 6PD",
    "wof:placetype": "postalcode"
  },
  "geometry": {"coordinates":[-1.52171,52.3976],"type":"Point"}
}
