{
  "type": "Feature",
  "properties": {
    "iso:country":"GB",
    "wof:name":"CV5 9NJ",
    "wof:placetype":"postalcode"
},
  "geometry": {"coordinates":[-1.56257551733978,52.41463285052412],"type":"Point"}
}