{
  "type": "Feature",
  "properties": {
    "iso:country": "GB",
    "wof:name": "LN10 6DA",
    "wof:placetype": "postalcode"
  },
  "geometry": {"coordinates":[-0.220366,53.151392],"type":"Point"}
}
