{
  "type": "Feature",
  "properties": {
    "iso:country":"GB",
    "wof:name":"B68 8HA",
    "wof:placetype":"postalcode"
},
  "geometry": {"coordinates":[-2.00550864725525,52.49106469724865],"type":"Point"}
}