{
  "type": "Feature",
  "properties": {
    "iso:country": "GB",
    "wof:name": "B68 8HA",
    "wof:placetype": "postalcode"
  },
  "geometry": {"coordinates":[-2.005509,52.491065],"type":"Point"}
}
