{
  "type": "Feature",
  "properties": {
    "iso:country": "GB",
    "wof:name": "CM3 4EQ",
    "wof:placetype": "postalcode"
  },
  "geometry": {"coordinates":[0.572438,51.71567],"type":"Point"}
}
