{
  "type": "Feature",
  "properties": {
    "iso:country":"GB",
    "wof:name":"CM3 4EQ",
    "wof:placetype":"postalcode"
},
  "geometry": {"coordinates":[0.57243746721215,51.71567022380196],"type":"Point"}
}