{
  "type": "Feature",
  "properties": {
    "iso:country":"GB",
    "wof:name":"CM19 5PD",
    "wof:placetype":"postalcode"
},
  "geometry": {"coordinates":[0.06645851544046,51.75416737749048],"type":"Point"}
}