{
  "type": "Feature",
  "properties": {
    "date:inception_lower":"1980-01-01",
    "date:inception_upper":"1980-01-31",
    "iso:country":"GB",
    "wof:name":"CM19 5PD",
    "wof:placetype":"postalcode"
},
  "geometry": {"coordinates":[0.066459,51.754167],"type":"Point"}
}