{
  "type": "Feature",
  "properties": {
    "iso:country": "GB",
    "wof:name": "CM19 5PD",
    "wof:placetype": "postalcode"
  },
  "geometry": {"coordinates":[0.066459,51.754167],"type":"Point"}
}
