{
  "type": "Feature",
  "properties": {
    "iso:country": "GB",
    "wof:name": "TF9 3QQ",
    "wof:placetype": "postalcode"
  },
  "geometry": {"coordinates":[-2.537235,52.881986],"type":"Point"}
}
