{
  "type": "Feature",
  "properties": {
    "iso:country":"GB",
    "wof:name":"TF9 3QQ",
    "wof:placetype":"postalcode"
},
  "geometry": {"coordinates":[-2.53723490488988,52.88198582952209],"type":"Point"}
}