{
  "type": "Feature",
  "properties": {
    "iso:country":"GB",
    "wof:name":"IG9 6BB",
    "wof:placetype":"postalcode"
},
  "geometry": {"coordinates":[0.04731580974481,51.62585581463817],"type":"Point"}
}