{
  "type": "Feature",
  "properties": {
    "iso:country":"GB",
    "wof:name":"W1G 7JL",
    "wof:placetype":"postalcode"
},
  "geometry": {"coordinates":[-0.14807534880464,51.5218752474695],"type":"Point"}
}