{
  "type": "Feature",
  "properties": {
    "iso:country":"GB",
    "wof:name":"NG5 2EU",
    "wof:placetype":"postalcode"
},
  "geometry": {"coordinates":[-1.15217169636542,52.97825378573985],"type":"Point"}
}