{
  "type": "Feature",
  "properties": {
    "iso:country":"GB",
    "wof:name":"EX6 8LW",
    "wof:placetype":"postalcode"
},
  "geometry": {"coordinates":[-3.4742110699251,50.63717641554736],"type":"Point"}
}