{
  "type": "Feature",
  "properties": {
    "iso:country":"GB",
    "wof:name":"LS26 9EU",
    "wof:placetype":"postalcode"
},
  "geometry": {"coordinates":[-1.42315183330268,53.74646382719241],"type":"Point"}
}