{
  "type": "Feature",
  "properties": {
    "iso:country":"GB",
    "wof:name":"WA6 0PX",
    "wof:placetype":"postalcode"
},
  "geometry": {"coordinates":[-2.76058933758376,53.27773992474417],"type":"Point"}
}