{
  "type": "Feature",
  "properties": {
    "iso:country":"GB",
    "wof:name":"PR3 2LL",
    "wof:placetype":"postalcode"
},
  "geometry": {"coordinates":[-2.69972356361935,53.86249981471512],"type":"Point"}
}