{
  "type": "Feature",
  "properties": {
    "iso:country": "GB",
    "wof:name": "SP6 2EE",
    "wof:placetype": "postalcode"
  },
  "geometry": {"coordinates":[-1.776029,50.95641],"type":"Point"}
}
