{
  "type": "Feature",
  "properties": {
    "date:inception_lower": "1980-01-01",
    "date:inception_upper": "1980-01-01",
    "iso:country": "GB",
    "wof:name": "SP6 2EE",
    "wof:placetype": "postalcode"
  },
  "geometry": {"coordinates":[-1.776029,50.95641],"type":"Point"}
}
