{
  "type": "Feature",
  "properties": {
    "iso:country":"GB",
    "wof:name":"SP6 2EE",
    "wof:placetype":"postalcode"
},
  "geometry": {"coordinates":[-1.77606503541048,50.95643515578683],"type":"Point"}
}