{
  "type": "Feature",
  "properties": {
    "date:inception_lower":"1980-01-01",
    "date:inception_upper":"1980-01-31",
    "iso:country":"GB",
    "wof:name":"NE28 7HB",
    "wof:placetype":"postalcode"
},
  "geometry": {"coordinates":[-1.521502,54.998228],"type":"Point"}
}