{
  "type": "Feature",
  "properties": {
    "iso:country":"GB",
    "wof:name":"SL6 5HY",
    "wof:placetype":"postalcode"
},
  "geometry": {"coordinates":[-0.75460675563413,51.52420805919299],"type":"Point"}
}