{
  "type": "Feature",
  "properties": {
    "date:inception_lower": "1980-01-01",
    "date:inception_upper": "1980-01-01",
    "iso:country": "GB",
    "wof:name": "SL6 5HY",
    "wof:placetype": "postalcode"
  },
  "geometry": {"coordinates":[-0.754721,51.524077],"type":"Point"}
}
