{
  "type": "Feature",
  "properties": {
    "date:inception_lower": "1999-06-01",
    "date:inception_upper": "1999-06-01",
    "iso:country": "GB",
    "wof:name": "CF10 3DU",
    "wof:placetype": "postalcode"
  },
  "geometry": {"coordinates":[-3.185538,51.488837],"type":"Point"}
}
