{
  "type": "Feature",
  "properties": {
    "iso:country": "GB",
    "wof:name": "CF10 3DU",
    "wof:placetype": "postalcode"
  },
  "geometry": {"coordinates":[-3.185538,51.488837],"type":"Point"}
}
