{
  "type": "Feature",
  "properties": {
    "iso:country":"GB",
    "wof:name":"S74 8ED",
    "wof:placetype":"postalcode"
},
  "geometry": {"coordinates":[-1.42553489782381,53.49564621438336],"type":"Point"}
}