{
  "type": "Feature",
  "properties": {
    "iso:country":"GB",
    "wof:name":"LL20 8AQ",
    "wof:placetype":"postalcode"
},
  "geometry": {"coordinates":[-3.16646982484704,52.96396203399395],"type":"Point"}
}