{
  "type": "Feature",
  "properties": {
    "iso:country": "GB",
    "wof:name": "LL20 8AQ",
    "wof:placetype": "postalcode"
  },
  "geometry": {"coordinates":[-3.165967,52.96355],"type":"Point"}
}
