{
  "type": "Feature",
  "properties": {
    "date:inception_lower":"1980-01-01",
    "date:inception_upper":"1980-01-31",
    "iso:country":"GB",
    "wof:name":"GU29 0JN",
    "wof:placetype":"postalcode"
},
  "geometry": {"coordinates":[-0.781888,50.980779],"type":"Point"}
}