{
  "type": "Feature",
  "properties": {
    "iso:country":"GB",
    "wof:name":"GU29 0JN",
    "wof:placetype":"postalcode"
},
  "geometry": {"coordinates":[-0.78266107490768,50.9802714953033],"type":"Point"}
}