{
  "type": "Feature",
  "properties": {
    "iso:country": "GB",
    "wof:name": "GU29 0JN",
    "wof:placetype": "postalcode"
  },
  "geometry": {"coordinates":[-0.781888,50.980779],"type":"Point"}
}
