{
  "type": "Feature",
  "properties": {
    "iso:country":"GB",
    "wof:name":"DD8 2AY",
    "wof:placetype":"postalcode"
},
  "geometry": {"coordinates":[-2.88193364566936,56.6378071784279],"type":"Point"}
}