{
  "type": "Feature",
  "properties": {
    "date:inception_lower": "2006-11-01",
    "date:inception_upper": "2006-11-01",
    "iso:country": "GB",
    "wof:name": "DN20 8TQ",
    "wof:placetype": "postalcode"
  },
  "geometry": {"coordinates":[-0.465709,53.568561],"type":"Point"}
}
