{
  "type": "Feature",
  "properties": {
    "iso:country":"GB",
    "wof:name":"DN20 8TQ",
    "wof:placetype":"postalcode"
},
  "geometry": {"coordinates":[-0.46570937753303,53.56856083446156],"type":"Point"}
}