{
  "type": "Feature",
  "properties": {
    "iso:country": "GB",
    "wof:name": "DN20 8TQ",
    "wof:placetype": "postalcode"
  },
  "geometry": {"coordinates":[-0.465709,53.568561],"type":"Point"}
}
