{
  "type": "Feature",
  "properties": {
    "date:inception_lower":"1995-01-01",
    "date:inception_upper":"1995-01-31",
    "iso:country":"GB",
    "wof:name":"HU12 9HN",
    "wof:placetype":"postalcode"
},
  "geometry": {"coordinates":[-0.141485,53.732922],"type":"Point"}
}