{
  "type": "Feature",
  "properties": {
    "iso:country":"GB",
    "wof:name":"HU12 9HN",
    "wof:placetype":"postalcode"
},
  "geometry": {"coordinates":[-0.14148503490131,53.7329217254675],"type":"Point"}
}