{
  "type": "Feature",
  "properties": {
    "iso:country":"GB",
    "wof:name":"SS3 8XJ",
    "wof:placetype":"postalcode"
},
  "geometry": {"coordinates":[0.78342929387823,51.54129166418338],"type":"Point"}
}