{
  "type": "Feature",
  "properties": {
    "iso:country":"GB",
    "wof:name":"BN41 2RW",
    "wof:placetype":"postalcode"
},
  "geometry": {"coordinates":[-0.23434873403619,50.85531521745269],"type":"Point"}
}