{
  "type": "Feature",
  "properties": {
    "iso:country": "GB",
    "wof:name": "BN41 2RW",
    "wof:placetype": "postalcode"
  },
  "geometry": {"coordinates":[-0.234349,50.855315],"type":"Point"}
}
