{
  "type": "Feature",
  "properties": {
    "iso:country":"GB",
    "wof:name":"LE7 9AJ",
    "wof:placetype":"postalcode"
},
  "geometry": {"coordinates":[-0.93946967119191,52.61817424950209],"type":"Point"}
}