{
  "type": "Feature",
  "properties": {
    "iso:country": "GB",
    "wof:name": "LE7 9AJ",
    "wof:placetype": "postalcode"
  },
  "geometry": {"coordinates":[-0.93947,52.618174],"type":"Point"}
}
