{
  "type": "Feature",
  "properties": {
    "date:inception_lower":"1980-01-01",
    "date:inception_upper":"1980-01-31",
    "iso:country":"GB",
    "wof:name":"DN12 3PQ",
    "wof:placetype":"postalcode"
},
  "geometry": {"coordinates":[-1.247355,53.483251],"type":"Point"}
}