{
  "type": "Feature",
  "properties": {
    "iso:country":"GB",
    "wof:name":"B75 6SN",
    "wof:placetype":"postalcode"
},
  "geometry": {"coordinates":[-1.82075482519224,52.58012710850593],"type":"Point"}
}