{
  "type": "Feature",
  "properties": {
    "date:inception_lower": "1980-01-01",
    "date:inception_upper": "1980-01-01",
    "iso:country": "GB",
    "wof:name": "B75 6SN",
    "wof:placetype": "postalcode"
  },
  "geometry": {"coordinates":[-1.820755,52.580127],"type":"Point"}
}
