{
  "type": "Feature",
  "properties": {
    "iso:country":"GB",
    "wof:name":"RH20 3NJ",
    "wof:placetype":"postalcode"
},
  "geometry": {"coordinates":[-0.443862673274,50.92343388030928],"type":"Point"}
}