{
  "type": "Feature",
  "properties": {
    "iso:country":"GB",
    "wof:name":"DG8 7BL",
    "wof:placetype":"postalcode"
},
  "geometry": {"coordinates":[-4.34152265271185,55.0227804434781],"type":"Point"}
}