{
  "type": "Feature",
  "properties": {
    "iso:country": "GB",
    "wof:name": "M1 6AA",
    "wof:placetype": "postalcode"
  },
  "geometry": {"coordinates":[-2.240429,53.477105],"type":"Point"}
}
