{
  "type": "Feature",
  "properties": {
    "iso:country":"GB",
    "wof:name":"N15 5QR",
    "wof:placetype":"postalcode"
},
  "geometry": {"coordinates":[-0.08666120979352,51.58357635287229],"type":"Point"}
}