{
  "type": "Feature",
  "properties": {
    "date:inception_lower": "1980-01-01",
    "date:inception_upper": "1980-01-01",
    "iso:country": "GB",
    "wof:name": "HG3 2JZ",
    "wof:placetype": "postalcode"
  },
  "geometry": {"coordinates":[-1.643246,54.011295],"type":"Point"}
}
