{
  "type": "Feature",
  "properties": {
    "iso:country":"GB",
    "wof:name":"HG3 2JZ",
    "wof:placetype":"postalcode"
},
  "geometry": {"coordinates":[-1.64324647935578,54.01129468025336],"type":"Point"}
}