{
  "type": "Feature",
  "properties": {
    "iso:country":"GB",
    "wof:name":"DN12 1AU",
    "wof:placetype":"postalcode"
},
  "geometry": {"coordinates":[-1.19092136462857,53.483942951637],"type":"Point"}
}