{
  "type": "Feature",
  "properties": {
    "date:inception_lower": "1985-10-01",
    "date:inception_upper": "1985-10-01",
    "iso:country": "GB",
    "wof:name": "CM16 4AU",
    "wof:placetype": "postalcode"
  },
  "geometry": {"coordinates":[0.113288,51.700162],"type":"Point"}
}
