{
  "type": "Feature",
  "properties": {
    "iso:country": "GB",
    "wof:name": "CM16 4AU",
    "wof:placetype": "postalcode"
  },
  "geometry": {"coordinates":[0.113288,51.700162],"type":"Point"}
}
