{
  "type": "Feature",
  "properties": {
    "iso:country":"GB",
    "wof:name":"CH3 5LA",
    "wof:placetype":"postalcode"
},
  "geometry": {"coordinates":[-2.85637884287185,53.19455247349504],"type":"Point"}
}