{
  "type": "Feature",
  "properties": {
    "iso:country": "GB",
    "wof:name": "CH3 5LA",
    "wof:placetype": "postalcode"
  },
  "geometry": {"coordinates":[-2.856379,53.194552],"type":"Point"}
}
