{
  "type": "Feature",
  "properties": {
    "iso:country":"GB",
    "wof:name":"LN2 5EB",
    "wof:placetype":"postalcode"
},
  "geometry": {"coordinates":[-0.52512734409507,53.22896885617767],"type":"Point"}
}