{
  "type": "Feature",
  "properties": {
    "iso:country": "GB",
    "wof:name": "RM14 1XJ",
    "wof:placetype": "postalcode"
  },
  "geometry": {"coordinates":[0.267509,51.56154],"type":"Point"}
}
