{
  "type": "Feature",
  "properties": {
    "iso:country":"GB",
    "wof:name":"SO30 4DA",
    "wof:placetype":"postalcode"
},
  "geometry": {"coordinates":[-1.32226126225698,50.91603491314405],"type":"Point"}
}