{
  "type": "Feature",
  "properties": {
    "iso:country":"GB",
    "wof:name":"OX15 6PX",
    "wof:placetype":"postalcode"
},
  "geometry": {"coordinates":[-1.39357521069549,52.07142314786226],"type":"Point"}
}