{
  "type": "Feature",
  "properties": {
    "iso:country":"GB",
    "wof:name":"NR16 1JS",
    "wof:placetype":"postalcode"
},
  "geometry": {"coordinates":[1.18513909523011,52.50360012099107],"type":"Point"}
}