{
  "type": "Feature",
  "properties": {
    "iso:country":"GB",
    "wof:name":"SA8 3AJ",
    "wof:placetype":"postalcode"
},
  "geometry": {"coordinates":[-3.8459788927399,51.71413607324421],"type":"Point"}
}