{
  "type": "Feature",
  "properties": {
    "iso:country":"GB",
    "wof:name":"WF3 3SJ",
    "wof:placetype":"postalcode"
},
  "geometry": {"coordinates":[-1.50550959450825,53.71757526343546],"type":"Point"}
}