{
  "type": "Feature",
  "properties": {
    "iso:country": "GB",
    "wof:name": "BH16 6DW",
    "wof:placetype": "postalcode"
  },
  "geometry": {"coordinates":[-2.079541,50.751315],"type":"Point"}
}
