{
  "type": "Feature",
  "properties": {
    "iso:country":"GB",
    "wof:name":"LL12 0LG",
    "wof:placetype":"postalcode"
},
  "geometry": {"coordinates":[-2.9623873800532,53.11045737654251],"type":"Point"}
}