{
  "type": "Feature",
  "properties": {
    "date:inception_lower":"1982-03-01",
    "date:inception_upper":"1982-03-31",
    "iso:country":"GB",
    "wof:name":"LL12 0LG",
    "wof:placetype":"postalcode"
},
  "geometry": {"coordinates":[-2.962387,53.110457],"type":"Point"}
}