{
  "type": "Feature",
  "properties": {
    "iso:country": "GB",
    "wof:name": "YO60 7RY",
    "wof:placetype": "postalcode"
  },
  "geometry": {"coordinates":[-0.936776,54.036128],"type":"Point"}
}
