{
  "type": "Feature",
  "properties": {
    "date:inception_lower": "2016-12-01",
    "date:inception_upper": "2016-12-01",
    "iso:country": "GB",
    "wof:name": "PE10 0XE",
    "wof:placetype": "postalcode"
  },
  "geometry": {"coordinates":[-0.386136,52.757795],"type":"Point"}
}
