{
  "type": "Feature",
  "properties": {
    "iso:country":"GB",
    "wof:name":"CM9 8LW",
    "wof:placetype":"postalcode"
},
  "geometry": {"coordinates":[0.75516559865536,51.77372448729838],"type":"Point"}
}