{
  "type": "Feature",
  "properties": {
    "date:inception_lower": "1980-01-01",
    "date:inception_upper": "1980-01-01",
    "iso:country": "GB",
    "wof:name": "NR3 3JR",
    "wof:placetype": "postalcode"
  },
  "geometry": {"coordinates":[1.287995,52.647498],"type":"Point"}
}
