{
  "type": "Feature",
  "properties": {
    "date:inception_lower":"1980-01-01",
    "date:inception_upper":"1980-01-31",
    "iso:country":"GB",
    "wof:name":"NG20 9LH",
    "wof:placetype":"postalcode"
},
  "geometry": {"coordinates":[-1.158315,53.243418],"type":"Point"}
}