{
  "type": "Feature",
  "properties": {
    "iso:country":"GB",
    "wof:name":"NG20 9LH",
    "wof:placetype":"postalcode"
},
  "geometry": {"coordinates":[-1.15831535312363,53.24341783894872],"type":"Point"}
}