{
  "type": "Feature",
  "properties": {
    "iso:country":"GB",
    "wof:name":"SN6 6HA",
    "wof:placetype":"postalcode"
},
  "geometry": {"coordinates":[-1.87868682684779,51.63883795603135],"type":"Point"}
}