{
  "type": "Feature",
  "properties": {
    "iso:country":"GB",
    "wof:name":"SN3 6PA",
    "wof:placetype":"postalcode"
},
  "geometry": {"coordinates":[-1.72761382285828,51.55377875638701],"type":"Point"}
}