{
  "type": "Feature",
  "properties": {
    "iso:country":"GB",
    "wof:name":"WD18 9QQ",
    "wof:placetype":"postalcode"
},
  "geometry": {"coordinates":[-0.42720679561109,51.63951111225482],"type":"Point"}
}