{
  "type": "Feature",
  "properties": {
    "date:inception_lower":"1980-01-01",
    "date:inception_upper":"1980-01-31",
    "iso:country":"GB",
    "wof:name":"IG11 9TJ",
    "wof:placetype":"postalcode"
},
  "geometry": {"coordinates":[0.085228,51.541062],"type":"Point"}
}