{
  "type": "Feature",
  "properties": {
    "iso:country":"GB",
    "wof:name":"PR2 1XX",
    "wof:placetype":"postalcode"
},
  "geometry": {"coordinates":[-2.7745310194098,53.7659565502474],"type":"Point"}
}