{
  "type": "Feature",
  "properties": {
    "iso:country":"GB",
    "wof:name":"WA3 6LT",
    "wof:placetype":"postalcode"
},
  "geometry": {"coordinates":[-2.53540695211966,53.42024010614782],"type":"Point"}
}