{
  "type": "Feature",
  "properties": {
    "date:inception_lower": "1980-01-01",
    "date:inception_upper": "1980-01-01",
    "iso:country": "GB",
    "wof:name": "WA3 6LT",
    "wof:placetype": "postalcode"
  },
  "geometry": {"coordinates":[-2.535059,53.420061],"type":"Point"}
}
