{
  "type": "Feature",
  "properties": {
    "date:inception_lower": "1980-01-01",
    "date:inception_upper": "1980-01-01",
    "iso:country": "GB",
    "wof:name": "HA1 4UP",
    "wof:placetype": "postalcode"
  },
  "geometry": {"coordinates":[-0.34482,51.5926],"type":"Point"}
}
