{
  "type": "Feature",
  "properties": {
    "iso:country":"GB",
    "wof:name":"W1F 9BZ",
    "wof:placetype":"postalcode"
},
  "geometry": {"coordinates":[-0.13601633069341,51.51148673226201],"type":"Point"}
}