{
  "type": "Feature",
  "properties": {
    "iso:country":"GB",
    "wof:name":"KT2 5DZ",
    "wof:placetype":"postalcode"
},
  "geometry": {"coordinates":[-0.30218649394631,51.41935581848815],"type":"Point"}
}