{
  "type": "Feature",
  "properties": {
    "date:inception_lower": "2005-01-01",
    "date:inception_upper": "2005-01-01",
    "iso:country": "GB",
    "wof:name": "KT2 5DZ",
    "wof:placetype": "postalcode"
  },
  "geometry": {"coordinates":[-0.302186,51.419356],"type":"Point"}
}
