{
  "type": "Feature",
  "properties": {
    "date:inception_lower": "1995-07-01",
    "date:inception_upper": "1995-07-01",
    "iso:country": "GB",
    "wof:name": "CF81 8RT",
    "wof:placetype": "postalcode"
  },
  "geometry": {"coordinates":[-3.231194,51.690529],"type":"Point"}
}
