{
  "type": "Feature",
  "properties": {
    "iso:country":"GB",
    "wof:name":"DT3 4FN",
    "wof:placetype":"postalcode"
},
  "geometry": {"coordinates":[-2.49460599169017,50.62092215652321],"type":"Point"}
}