{
  "type": "Feature",
  "properties": {
    "date:inception_lower":"2015-11-01",
    "date:inception_upper":"2015-11-30",
    "iso:country":"GB",
    "wof:name":"DT3 4FN",
    "wof:placetype":"postalcode"
},
  "geometry": {"coordinates":[-2.494795,50.621702],"type":"Point"}
}