{
  "type": "Feature",
  "properties": {
    "iso:country": "GB",
    "wof:name": "DT3 4FN",
    "wof:placetype": "postalcode"
  },
  "geometry": {"coordinates":[-2.494811,50.621819],"type":"Point"}
}
