{
  "type": "Feature",
  "properties": {
    "iso:country":"GB",
    "wof:name":"SA10 7TH",
    "wof:placetype":"postalcode"
},
  "geometry": {"coordinates":[-3.81540567422545,51.6812335573856],"type":"Point"}
}