{
  "type": "Feature",
  "properties": {
    "iso:country":"GB",
    "wof:name":"B96 6JL",
    "wof:placetype":"postalcode"
},
  "geometry": {"coordinates":[-1.98553037627309,52.23928630141679],"type":"Point"}
}