{
  "type": "Feature",
  "properties": {
    "iso:country":"GB",
    "wof:name":"NN6 7QQ",
    "wof:placetype":"postalcode"
},
  "geometry": {"coordinates":[-1.07970950174555,52.30450672242105],"type":"Point"}
}