{
  "type": "Feature",
  "properties": {
    "iso:country":"GB",
    "wof:name":"TF3 1NT",
    "wof:placetype":"postalcode"
},
  "geometry": {"coordinates":[-2.43521558094953,52.6482428103663],"type":"Point"}
}