{
  "type": "Feature",
  "properties": {
    "iso:country": "GB",
    "wof:name": "TF3 1NT",
    "wof:placetype": "postalcode"
  },
  "geometry": {"coordinates":[-2.435216,52.648243],"type":"Point"}
}
