{
  "type": "Feature",
  "properties": {
    "iso:country":"GB",
    "wof:name":"NR14 6AG",
    "wof:placetype":"postalcode"
},
  "geometry": {"coordinates":[1.43856232216131,52.5522278210963],"type":"Point"}
}