{
  "type": "Feature",
  "properties": {
    "iso:country": "GB",
    "wof:name": "NR14 6AG",
    "wof:placetype": "postalcode"
  },
  "geometry": {"coordinates":[1.438562,52.552228],"type":"Point"}
}
