{
  "type": "Feature",
  "properties": {
    "iso:country":"GB",
    "wof:name":"M28 1ZF",
    "wof:placetype":"postalcode"
},
  "geometry": {"coordinates":[-2.41543498888637,53.50793360464946],"type":"Point"}
}