{
  "type": "Feature",
  "properties": {
    "date:inception_lower": "1994-05-01",
    "date:inception_upper": "1994-05-01",
    "iso:country": "GB",
    "wof:name": "M28 1ZF",
    "wof:placetype": "postalcode"
  },
  "geometry": {"coordinates":[-2.415435,53.507934],"type":"Point"}
}
