{
  "type": "Feature",
  "properties": {
    "iso:country":"GB",
    "wof:name":"ST7 1AW",
    "wof:placetype":"postalcode"
},
  "geometry": {"coordinates":[-2.24382928656349,53.08108244698865],"type":"Point"}
}