{
  "type": "Feature",
  "properties": {
    "iso:country":"GB",
    "wof:name":"IV40 8BQ",
    "wof:placetype":"postalcode"
},
  "geometry": {"coordinates":[-5.71265313060898,57.2839137962936],"type":"Point"}
}