{
  "type": "Feature",
  "properties": {
    "iso:country":"GB",
    "wof:name":"BH20 6AF",
    "wof:placetype":"postalcode"
},
  "geometry": {"coordinates":[-2.15512045724736,50.68195923696842],"type":"Point"}
}