{
  "type": "Feature",
  "properties": {
    "iso:country": "GB",
    "wof:name": "BH20 6AF",
    "wof:placetype": "postalcode"
  },
  "geometry": {"coordinates":[-2.15512,50.681959],"type":"Point"}
}
