{
  "type": "Feature",
  "properties": {
    "date:inception_lower":"1983-07-01",
    "date:inception_upper":"1983-07-31",
    "iso:country":"GB",
    "wof:name":"CV31 3QJ",
    "wof:placetype":"postalcode"
},
  "geometry": {"coordinates":[-1.542428,52.285984],"type":"Point"}
}