{
  "type": "Feature",
  "properties": {
    "iso:country": "GB",
    "wof:name": "CV31 3QJ",
    "wof:placetype": "postalcode"
  },
  "geometry": {"coordinates":[-1.542428,52.285984],"type":"Point"}
}
