{
  "type": "Feature",
  "properties": {
    "iso:country": "GB",
    "wof:name": "BA1 7BQ",
    "wof:placetype": "postalcode"
  },
  "geometry": {"coordinates":[-2.340885,51.399178],"type":"Point"}
}
