{
  "type": "Feature",
  "properties": {
    "iso:country":"GB",
    "wof:name":"BD4 6JX",
    "wof:placetype":"postalcode"
},
  "geometry": {"coordinates":[-1.72540585374907,53.76688794615345],"type":"Point"}
}