{
  "type": "Feature",
  "properties": {
    "iso:country": "GB",
    "wof:name": "AB41 9HH",
    "wof:placetype": "postalcode"
  },
  "geometry": {"coordinates":[-2.078573,57.358132],"type":"Point"}
}
