{
  "type": "Feature",
  "properties": {
    "iso:country": "GB",
    "wof:name": "DN32 7EA",
    "wof:placetype": "postalcode"
  },
  "geometry": {"coordinates":[-0.073733,53.568581],"type":"Point"}
}
