{
  "type": "Feature",
  "properties": {
    "iso:country":"GB",
    "wof:name":"SA14 9UX",
    "wof:placetype":"postalcode"
},
  "geometry": {"coordinates":[-4.12807425923494,51.6783568340473],"type":"Point"}
}