{
  "type": "Feature",
  "properties": {
    "date:inception_lower": "2008-12-01",
    "date:inception_upper": "2008-12-01",
    "iso:country": "GB",
    "wof:name": "SA14 9UX",
    "wof:placetype": "postalcode"
  },
  "geometry": {"coordinates":[-4.128074,51.678357],"type":"Point"}
}
