{
  "type": "Feature",
  "properties": {
    "iso:country": "GB",
    "wof:name": "NR30 5XA",
    "wof:placetype": "postalcode"
  },
  "geometry": {"coordinates":[1.725076,52.655714],"type":"Point"}
}
