{
  "type": "Feature",
  "properties": {
    "iso:country":"GB",
    "wof:name":"GL12 8BY",
    "wof:placetype":"postalcode"
},
  "geometry": {"coordinates":[-2.4618105365153,51.63630088859903],"type":"Point"}
}