{
  "type": "Feature",
  "properties": {
    "iso:country": "GB",
    "wof:name": "GL12 8BY",
    "wof:placetype": "postalcode"
  },
  "geometry": {"coordinates":[-2.46181,51.636301],"type":"Point"}
}
