{
  "type": "Feature",
  "properties": {
    "iso:country": "GB",
    "wof:name": "PL32 9YS",
    "wof:placetype": "postalcode"
  },
  "geometry": {"coordinates":[-4.677272,50.625311],"type":"Point"}
}
