{
  "type": "Feature",
  "properties": {
    "date:inception_lower": "1985-10-01",
    "date:inception_upper": "1985-10-01",
    "iso:country": "GB",
    "wof:name": "PL32 9YS",
    "wof:placetype": "postalcode"
  },
  "geometry": {"coordinates":[-4.677272,50.625311],"type":"Point"}
}
