{
  "type": "Feature",
  "properties": {
    "iso:country":"GB",
    "wof:name":"PL32 9YS",
    "wof:placetype":"postalcode"
},
  "geometry": {"coordinates":[-4.67727242590162,50.62531146847713],"type":"Point"}
}