{
  "type": "Feature",
  "properties": {
    "iso:country":"GB",
    "wof:name":"SE7 8RH",
    "wof:placetype":"postalcode"
},
  "geometry": {"coordinates":[0.03902202907465,51.48973436302838],"type":"Point"}
}