{
  "type": "Feature",
  "properties": {
    "iso:country":"GB",
    "wof:name":"YO24 3WY",
    "wof:placetype":"postalcode"
},
  "geometry": {"coordinates":[-1.12930307570636,53.94912655022483],"type":"Point"}
}