{
  "type": "Feature",
  "properties": {
    "iso:country":"GB",
    "wof:name":"NW1 1BP",
    "wof:placetype":"postalcode"
},
  "geometry": {"coordinates":[-0.13391858294973,51.53037360236533],"type":"Point"}
}