{
  "type": "Feature",
  "properties": {
    "iso:country": "GB",
    "wof:name": "ML9 3NT",
    "wof:placetype": "postalcode"
  },
  "geometry": {"coordinates":[-3.991914,55.692474],"type":"Point"}
}
