{
  "type": "Feature",
  "properties": {
    "iso:country":"GB",
    "wof:name":"ML9 3NT",
    "wof:placetype":"postalcode"
},
  "geometry": {"coordinates":[-3.99184279921153,55.69237913205917],"type":"Point"}
}