{
  "type": "Feature",
  "properties": {
    "date:inception_lower":"1980-01-01",
    "date:inception_upper":"1980-01-31",
    "iso:country":"GB",
    "wof:name":"HP20 1QH",
    "wof:placetype":"postalcode"
},
  "geometry": {"coordinates":[-0.785862,51.819083],"type":"Point"}
}