{
  "type": "Feature",
  "properties": {
    "iso:country":"GB",
    "wof:name":"AB31 4PR",
    "wof:placetype":"postalcode"
},
  "geometry": {"coordinates":[-2.68793776069815,57.13249361179307],"type":"Point"}
}