{
  "type": "Feature",
  "properties": {
    "iso:country":"GB",
    "wof:name":"TS6 9TJ",
    "wof:placetype":"postalcode"
},
  "geometry": {"coordinates":[-1.15438542925451,54.56964577744711],"type":"Point"}
}