{
  "type": "Feature",
  "properties": {
    "date:inception_lower":"2002-11-01",
    "date:inception_upper":"2002-11-30",
    "iso:country":"GB",
    "wof:name":"LN2 1ED",
    "wof:placetype":"postalcode"
},
  "geometry": {"coordinates":[-0.539213,53.229763],"type":"Point"}
}