{
  "type": "Feature",
  "properties": {
    "date:inception_lower": "2010-06-01",
    "date:inception_upper": "2010-06-01",
    "iso:country": "GB",
    "wof:name": "EX39 4FS",
    "wof:placetype": "postalcode"
  },
  "geometry": {"coordinates":[-4.18721,51.019377],"type":"Point"}
}
