{
  "type": "Feature",
  "properties": {
    "iso:country":"GB",
    "wof:name":"NP20 1UL",
    "wof:placetype":"postalcode"
},
  "geometry": {"coordinates":[-2.99591060198724,51.58683955801674],"type":"Point"}
}