{
  "type": "Feature",
  "properties": {
    "date:inception_lower": "2004-05-01",
    "date:inception_upper": "2004-05-01",
    "iso:country": "GB",
    "wof:name": "LE67 1HS",
    "wof:placetype": "postalcode"
  },
  "geometry": {"coordinates":[-1.35091,52.677194],"type":"Point"}
}
