{
  "type": "Feature",
  "properties": {
    "iso:country": "GB",
    "wof:name": "SA43 1SD",
    "wof:placetype": "postalcode"
  },
  "geometry": {"coordinates":[-4.615394,52.104151],"type":"Point"}
}
