{
  "type": "Feature",
  "properties": {
    "iso:country":"GB",
    "wof:name":"SA43 1SD",
    "wof:placetype":"postalcode"
},
  "geometry": {"coordinates":[-4.61519691177714,52.10388001766451],"type":"Point"}
}