{
  "type": "Feature",
  "properties": {
    "date:inception_lower": "2023-07-01",
    "date:inception_upper": "2023-07-01",
    "iso:country": "GB",
    "wof:name": "NG17 3LX",
    "wof:placetype": "postalcode"
  },
  "geometry": {"coordinates":[-1.269068,53.140477],"type":"Point"}
}
