{
  "type": "Feature",
  "properties": {
    "iso:country":"GB",
    "wof:name":"GL5 1AP",
    "wof:placetype":"postalcode"
},
  "geometry": {"coordinates":[-2.21572284687672,51.74557990106616],"type":"Point"}
}