{
  "type": "Feature",
  "properties": {
    "iso:country": "GB",
    "wof:name": "GL5 1AP",
    "wof:placetype": "postalcode"
  },
  "geometry": {"coordinates":[-2.215723,51.74558],"type":"Point"}
}
