{
  "type": "Feature",
  "properties": {
    "iso:country":"GB",
    "wof:name":"PR4 4GJ",
    "wof:placetype":"postalcode"
},
  "geometry": {"coordinates":[-2.8048163512553,53.69559415192931],"type":"Point"}
}