{
  "type": "Feature",
  "properties": {
    "iso:country":"GB",
    "wof:name":"NG8 5NX",
    "wof:placetype":"postalcode"
},
  "geometry": {"coordinates":[-1.20097578362113,52.98074916873401],"type":"Point"}
}