{
  "type": "Feature",
  "properties": {
    "iso:country":"GB",
    "wof:name":"IP12 3DL",
    "wof:placetype":"postalcode"
},
  "geometry": {"coordinates":[1.34954821823306,52.09673185331101],"type":"Point"}
}