{
  "type": "Feature",
  "properties": {
    "iso:country": "GB",
    "wof:name": "IP12 3DL",
    "wof:placetype": "postalcode"
  },
  "geometry": {"coordinates":[1.349548,52.096732],"type":"Point"}
}
