{
  "type": "Feature",
  "properties": {
    "date:inception_lower": "2021-04-01",
    "date:inception_upper": "2021-04-01",
    "iso:country": "GB",
    "wof:name": "PE12 7FL",
    "wof:placetype": "postalcode"
  },
  "geometry": {"coordinates":[-0.005479,52.799935],"type":"Point"}
}
