{
  "type": "Feature",
  "properties": {
    "iso:country":"GB",
    "wof:name":"M45 6AN",
    "wof:placetype":"postalcode"
},
  "geometry": {"coordinates":[-2.28904638048,53.54488006112339],"type":"Point"}
}