{
  "type": "Feature",
  "properties": {
    "date:inception_lower":"1980-01-01",
    "date:inception_upper":"1980-01-31",
    "iso:country":"GB",
    "wof:name":"PE22 7PZ",
    "wof:placetype":"postalcode"
},
  "geometry": {"coordinates":[-0.085265,53.130905],"type":"Point"}
}