{
  "type": "Feature",
  "properties": {
    "iso:country":"GB",
    "wof:name":"PE22 7PZ",
    "wof:placetype":"postalcode"
},
  "geometry": {"coordinates":[-0.08526521832769,53.13090473296209],"type":"Point"}
}