{
  "type": "Feature",
  "properties": {
    "iso:country": "GB",
    "wof:name": "NR18 9FP",
    "wof:placetype": "postalcode"
  },
  "geometry": {"coordinates":[1.124058,52.557802],"type":"Point"}
}
