{
  "type": "Feature",
  "properties": {
    "iso:country":"GB",
    "wof:name":"ME4 6LR",
    "wof:placetype":"postalcode"
},
  "geometry": {"coordinates":[0.52175722156667,51.36761992893754],"type":"Point"}
}