{
  "type": "Feature",
  "properties": {
    "date:inception_lower":"1980-01-01",
    "date:inception_upper":"1980-01-31",
    "iso:country":"GB",
    "wof:name":"LL54 7YL",
    "wof:placetype":"postalcode"
},
  "geometry": {"coordinates":[-4.276015,53.102579],"type":"Point"}
}