{
  "type": "Feature",
  "properties": {
    "iso:country":"GB",
    "wof:name":"LL54 7YL",
    "wof:placetype":"postalcode"
},
  "geometry": {"coordinates":[-4.27601481558664,53.10257915956856],"type":"Point"}
}