{
  "type": "Feature",
  "properties": {
    "iso:country":"GB",
    "wof:name":"DH2 2HJ",
    "wof:placetype":"postalcode"
},
  "geometry": {"coordinates":[-1.58055222359776,54.86529553011713],"type":"Point"}
}