{
  "type": "Feature",
  "properties": {
    "iso:country": "GB",
    "wof:name": "CT19 5AW",
    "wof:placetype": "postalcode"
  },
  "geometry": {"coordinates":[1.174344,51.083343],"type":"Point"}
}
