{
  "type": "Feature",
  "properties": {
    "date:inception_lower": "2019-10-01",
    "date:inception_upper": "2019-10-01",
    "iso:country": "GB",
    "wof:name": "SG8 6FW",
    "wof:placetype": "postalcode"
  },
  "geometry": {"coordinates":[0.023964,52.079796],"type":"Point"}
}
