{
  "type": "Feature",
  "properties": {
    "date:inception_lower": "1980-01-01",
    "date:inception_upper": "1980-01-01",
    "iso:country": "GB",
    "wof:name": "S40 3BD",
    "wof:placetype": "postalcode"
  },
  "geometry": {"coordinates":[-1.458486,53.231235],"type":"Point"}
}
