{
  "type": "Feature",
  "properties": {
    "iso:country": "GB",
    "wof:name": "EH4 1NT",
    "wof:placetype": "postalcode"
  },
  "geometry": {"coordinates":[-3.212304,55.956685],"type":"Point"}
}
