{
  "type": "Feature",
  "properties": {
    "iso:country":"GB",
    "wof:name":"EH4 1NT",
    "wof:placetype":"postalcode"
},
  "geometry": {"coordinates":[-3.21230439981484,55.9566854858389],"type":"Point"}
}