{
  "type": "Feature",
  "properties": {
    "iso:country":"GB",
    "wof:name":"TS7 8DU",
    "wof:placetype":"postalcode"
},
  "geometry": {"coordinates":[-1.19891342601615,54.5311422926878],"type":"Point"}
}