{
  "type": "Feature",
  "properties": {
    "date:inception_lower":"1980-01-01",
    "date:inception_upper":"1980-01-31",
    "iso:country":"GB",
    "wof:name":"OL9 7BL",
    "wof:placetype":"postalcode"
},
  "geometry": {"coordinates":[-2.133627,53.531753],"type":"Point"}
}