{
  "type": "Feature",
  "properties": {
    "iso:country":"GB",
    "wof:name":"BS7 0EB",
    "wof:placetype":"postalcode"
},
  "geometry": {"coordinates":[-2.56948060374733,51.49606455777983],"type":"Point"}
}