{
  "type": "Feature",
  "properties": {
    "date:inception_lower":"1980-01-01",
    "date:inception_upper":"1980-01-31",
    "iso:country":"GB",
    "wof:name":"BS7 0EB",
    "wof:placetype":"postalcode"
},
  "geometry": {"coordinates":[-2.569481,51.496065],"type":"Point"}
}