{
  "type": "Feature",
  "properties": {
    "iso:country": "GB",
    "wof:name": "EH12 6UY",
    "wof:placetype": "postalcode"
  },
  "geometry": {"coordinates":[-3.280217,55.947965],"type":"Point"}
}
