{
  "type": "Feature",
  "properties": {
    "iso:country": "GB",
    "wof:name": "NR10 5JZ",
    "wof:placetype": "postalcode"
  },
  "geometry": {"coordinates":[1.341333,52.764101],"type":"Point"}
}
