{
  "type": "Feature",
  "properties": {
    "iso:country":"GB",
    "wof:name":"E13 8QN",
    "wof:placetype":"postalcode"
},
  "geometry": {"coordinates":[0.02867375450325,51.52334878301749],"type":"Point"}
}