{
  "type": "Feature",
  "properties": {
    "iso:country":"GB",
    "wof:name":"EX31 1AL",
    "wof:placetype":"postalcode"
},
  "geometry": {"coordinates":[-4.05769433663662,51.07948642372793],"type":"Point"}
}