{
  "type": "Feature",
  "properties": {
    "iso:country": "GB",
    "wof:name": "EX10 0QE",
    "wof:placetype": "postalcode"
  },
  "geometry": {"coordinates":[-3.228205,50.727155],"type":"Point"}
}
