{
  "type": "Feature",
  "properties": {
    "iso:country":"GB",
    "wof:name":"YO41 5QL",
    "wof:placetype":"postalcode"
},
  "geometry": {"coordinates":[-0.84362896601247,53.98012623716148],"type":"Point"}
}