{
  "type": "Feature",
  "properties": {
    "iso:country": "GB",
    "wof:name": "YO41 5QL",
    "wof:placetype": "postalcode"
  },
  "geometry": {"coordinates":[-0.843629,53.980126],"type":"Point"}
}
