{
  "type": "Feature",
  "properties": {
    "iso:country": "GB",
    "wof:name": "WV5 7DT",
    "wof:placetype": "postalcode"
  },
  "geometry": {"coordinates":[-2.306927,52.537968],"type":"Point"}
}
