{
  "type": "Feature",
  "properties": {
    "iso:country":"GB",
    "wof:name":"WV5 7DT",
    "wof:placetype":"postalcode"
},
  "geometry": {"coordinates":[-2.30642919770128,52.53790051894797],"type":"Point"}
}