{
  "type": "Feature",
  "properties": {
    "date:inception_lower": "1980-01-01",
    "date:inception_upper": "1980-01-01",
    "iso:country": "GB",
    "wof:name": "WV5 7DT",
    "wof:placetype": "postalcode"
  },
  "geometry": {"coordinates":[-2.306499,52.537861],"type":"Point"}
}
