{
  "type": "Feature",
  "properties": {
    "iso:country":"GB",
    "wof:name":"SG5 2QT",
    "wof:placetype":"postalcode"
},
  "geometry": {"coordinates":[-0.29604951903672,51.95788392472596],"type":"Point"}
}