{
  "type": "Feature",
  "properties": {
    "iso:country":"GB",
    "wof:name":"GL19 4QG",
    "wof:placetype":"postalcode"
},
  "geometry": {"coordinates":[-2.22671154493334,51.99276431149987],"type":"Point"}
}