{
  "type": "Feature",
  "properties": {
    "iso:country":"GB",
    "wof:name":"HP12 4QD",
    "wof:placetype":"postalcode"
},
  "geometry": {"coordinates":[-0.79456559148686,51.61198980264088],"type":"Point"}
}