{
  "type": "Feature",
  "properties": {
    "date:inception_lower":"2000-12-01",
    "date:inception_upper":"2000-12-31",
    "iso:country":"GB",
    "wof:name":"HP12 4QD",
    "wof:placetype":"postalcode"
},
  "geometry": {"coordinates":[-0.794566,51.61199],"type":"Point"}
}