{
  "type": "Feature",
  "properties": {
    "iso:country":"GB",
    "wof:name":"S10 5DQ",
    "wof:placetype":"postalcode"
},
  "geometry": {"coordinates":[-1.51592594238303,53.3782507313129],"type":"Point"}
}