{
  "type": "Feature",
  "properties": {
    "iso:country":"GB",
    "wof:name":"RG17 7BZ",
    "wof:placetype":"postalcode"
},
  "geometry": {"coordinates":[-1.44760906856862,51.47447012456605],"type":"Point"}
}