{
  "type": "Feature",
  "properties": {
    "iso:country":"GB",
    "wof:name":"CV8 2LG",
    "wof:placetype":"postalcode"
},
  "geometry": {"coordinates":[-1.52711747388224,52.33993178082993],"type":"Point"}
}