{
  "type": "Feature",
  "properties": {
    "iso:country": "GB",
    "wof:name": "BA5 2GR",
    "wof:placetype": "postalcode"
  },
  "geometry": {"coordinates":[-2.663986,51.215368],"type":"Point"}
}
