{
  "type": "Feature",
  "properties": {
    "iso:country":"GB",
    "wof:name":"NN11 3EQ",
    "wof:placetype":"postalcode"
},
  "geometry": {"coordinates":[-1.21409131580913,52.17125726407394],"type":"Point"}
}