{
  "type": "Feature",
  "properties": {
    "iso:country": "GB",
    "wof:name": "NN11 3EQ",
    "wof:placetype": "postalcode"
  },
  "geometry": {"coordinates":[-1.214091,52.171257],"type":"Point"}
}
