{
  "type": "Feature",
  "properties": {
    "iso:country": "GB",
    "wof:name": "HP2 6BA",
    "wof:placetype": "postalcode"
  },
  "geometry": {"coordinates":[-0.454608,51.772434],"type":"Point"}
}
