{
  "type": "Feature",
  "properties": {
    "iso:country":"GB",
    "wof:name":"HP2 6BA",
    "wof:placetype":"postalcode"
},
  "geometry": {"coordinates":[-0.4546076648991,51.77243352817786],"type":"Point"}
}