{
  "type": "Feature",
  "properties": {
    "date:inception_lower": "1980-01-01",
    "date:inception_upper": "1980-01-01",
    "iso:country": "GB",
    "wof:name": "SA1 2HD",
    "wof:placetype": "postalcode"
  },
  "geometry": {"coordinates":[-3.938635,51.630732],"type":"Point"}
}
