{
  "type": "Feature",
  "properties": {
    "iso:country": "GB",
    "wof:name": "SA1 2HD",
    "wof:placetype": "postalcode"
  },
  "geometry": {"coordinates":[-3.938635,51.630732],"type":"Point"}
}
