{
  "type": "Feature",
  "properties": {
    "iso:country":"GB",
    "wof:name":"ME17 4QT",
    "wof:placetype":"postalcode"
},
  "geometry": {"coordinates":[0.49989207192136,51.23223986052107],"type":"Point"}
}