{
  "type": "Feature",
  "properties": {
    "iso:country":"GB",
    "wof:name":"IG3 8UQ",
    "wof:placetype":"postalcode"
},
  "geometry": {"coordinates":[0.10896581014912,51.57224703078251],"type":"Point"}
}