{
  "type": "Feature",
  "properties": {
    "iso:country":"GB",
    "wof:name":"BL3 1SD",
    "wof:placetype":"postalcode"
},
  "geometry": {"coordinates":[-2.40235551995398,53.56765244350909],"type":"Point"}
}