{
  "type": "Feature",
  "properties": {
    "date:inception_lower": "1980-01-01",
    "date:inception_upper": "1980-01-01",
    "iso:country": "GB",
    "wof:name": "NG3 2PR",
    "wof:placetype": "postalcode"
  },
  "geometry": {"coordinates":[-1.122234,52.96646],"type":"Point"}
}
