{
  "type": "Feature",
  "properties": {
    "iso:country":"GB",
    "wof:name":"NG3 2PR",
    "wof:placetype":"postalcode"
},
  "geometry": {"coordinates":[-1.1223287489768,52.96632396821926],"type":"Point"}
}