{
  "type": "Feature",
  "properties": {
    "iso:country":"GB",
    "wof:name":"CT19 4NQ",
    "wof:placetype":"postalcode"
},
  "geometry": {"coordinates":[1.14273868633036,51.09242349323772],"type":"Point"}
}