{
  "type": "Feature",
  "properties": {
    "iso:country":"GB",
    "wof:name":"FY2 0XE",
    "wof:placetype":"postalcode"
},
  "geometry": {"coordinates":[-3.03442236789046,53.8399830039713],"type":"Point"}
}