{
  "type": "Feature",
  "properties": {
    "date:inception_lower": "2010-04-01",
    "date:inception_upper": "2010-04-01",
    "iso:country": "GB",
    "wof:name": "PH6 2AB",
    "wof:placetype": "postalcode"
  },
  "geometry": {"coordinates":[-3.994887,56.355206],"type":"Point"}
}
