{
  "type": "Feature",
  "properties": {
    "iso:country":"GB",
    "wof:name":"PH6 2AB",
    "wof:placetype":"postalcode"
},
  "geometry": {"coordinates":[-3.9947711073335,56.35597131290629],"type":"Point"}
}