{
  "type": "Feature",
  "properties": {
    "iso:country":"GB",
    "wof:name":"DN17 1AB",
    "wof:placetype":"postalcode"
},
  "geometry": {"coordinates":[-0.65635774545337,53.58429262644694],"type":"Point"}
}