{
  "type": "Feature",
  "properties": {
    "iso:country":"GB",
    "wof:name":"B15 3LA",
    "wof:placetype":"postalcode"
},
  "geometry": {"coordinates":[-1.94184776478382,52.46301098194862],"type":"Point"}
}