{
  "type": "Feature",
  "properties": {
    "date:inception_lower": "1980-01-01",
    "date:inception_upper": "1980-01-01",
    "iso:country": "GB",
    "wof:name": "B15 3LA",
    "wof:placetype": "postalcode"
  },
  "geometry": {"coordinates":[-1.941848,52.463011],"type":"Point"}
}
