{
  "type": "Feature",
  "properties": {
    "date:inception_lower": "1980-01-01",
    "date:inception_upper": "1980-01-01",
    "iso:country": "GB",
    "wof:name": "DN32 7EH",
    "wof:placetype": "postalcode"
  },
  "geometry": {"coordinates":[-0.069492,53.568854],"type":"Point"}
}
