{
  "type": "Feature",
  "properties": {
    "iso:country": "GB",
    "wof:name": "DN32 7EH",
    "wof:placetype": "postalcode"
  },
  "geometry": {"coordinates":[-0.069492,53.568854],"type":"Point"}
}
