{
  "type": "Feature",
  "properties": {
    "iso:country":"GB",
    "wof:name":"GL20 8RF",
    "wof:placetype":"postalcode"
},
  "geometry": {"coordinates":[-2.11839580710695,52.0073982512515],"type":"Point"}
}