{
  "type": "Feature",
  "properties": {
    "iso:country": "GB",
    "wof:name": "DA16 2EH",
    "wof:placetype": "postalcode"
  },
  "geometry": {"coordinates":[0.101461,51.462957],"type":"Point"}
}
