{
  "type": "Feature",
  "properties": {
    "iso:country": "GB",
    "wof:name": "N5 1XS",
    "wof:placetype": "postalcode"
  },
  "geometry": {"coordinates":[-0.108419,51.551125],"type":"Point"}
}
