{
  "type": "Feature",
  "properties": {
    "date:inception_lower": "1993-01-01",
    "date:inception_upper": "1993-01-01",
    "iso:country": "GB",
    "wof:name": "N5 1XS",
    "wof:placetype": "postalcode"
  },
  "geometry": {"coordinates":[-0.108419,51.551125],"type":"Point"}
}
