{
  "type": "Feature",
  "properties": {
    "date:inception_lower": "1980-01-01",
    "date:inception_upper": "1980-01-01",
    "iso:country": "GB",
    "wof:name": "LD5 4RA",
    "wof:placetype": "postalcode"
  },
  "geometry": {"coordinates":[-3.639805,52.107624],"type":"Point"}
}
