{
  "type": "Feature",
  "properties": {
    "iso:country":"GB",
    "wof:name":"LD5 4RA",
    "wof:placetype":"postalcode"
},
  "geometry": {"coordinates":[-3.63980471075795,52.10762427638931],"type":"Point"}
}