{
  "type": "Feature",
  "properties": {
    "iso:country": "GB",
    "wof:name": "TR20 8UF",
    "wof:placetype": "postalcode"
  },
  "geometry": {"coordinates":[-5.569094,50.12365],"type":"Point"}
}
