{
  "type": "Feature",
  "properties": {
    "iso:country":"GB",
    "wof:name":"NE30 3RU",
    "wof:placetype":"postalcode"
},
  "geometry": {"coordinates":[-1.43606552059685,55.02563910920096],"type":"Point"}
}