{
  "type": "Feature",
  "properties": {
    "iso:country":"GB",
    "wof:name":"SE8 3PJ",
    "wof:placetype":"postalcode"
},
  "geometry": {"coordinates":[-0.03240884093588,51.49147629885056],"type":"Point"}
}