{
  "type": "Feature",
  "properties": {
    "iso:country": "GB",
    "wof:name": "SE8 3PJ",
    "wof:placetype": "postalcode"
  },
  "geometry": {"coordinates":[-0.032409,51.491476],"type":"Point"}
}
