{
  "type": "Feature",
  "properties": {
    "iso:country":"GB",
    "wof:name":"SA62 5EL",
    "wof:placetype":"postalcode"
},
  "geometry": {"coordinates":[-5.05587134381265,51.92547529226413],"type":"Point"}
}