{
  "type": "Feature",
  "properties": {
    "iso:country":"GB",
    "wof:name":"MK8 0NR",
    "wof:placetype":"postalcode"
},
  "geometry": {"coordinates":[-0.80737397551379,52.02260643376376],"type":"Point"}
}