{
  "type": "Feature",
  "properties": {
    "date:inception_lower": "2003-07-01",
    "date:inception_upper": "2003-07-01",
    "iso:country": "GB",
    "wof:name": "MK8 0NR",
    "wof:placetype": "postalcode"
  },
  "geometry": {"coordinates":[-0.807374,52.022606],"type":"Point"}
}
