{
  "type": "Feature",
  "properties": {
    "iso:country": "GB",
    "wof:name": "IP13 6TF",
    "wof:placetype": "postalcode"
  },
  "geometry": {"coordinates":[1.244164,52.110538],"type":"Point"}
}
