{
  "type": "Feature",
  "properties": {
    "date:inception_lower":"1991-09-01",
    "date:inception_upper":"1991-09-30",
    "iso:country":"GB",
    "wof:name":"EX8 2NR",
    "wof:placetype":"postalcode"
},
  "geometry": {"coordinates":[-3.376771,50.631243],"type":"Point"}
}