{
  "type": "Feature",
  "properties": {
    "iso:country":"GB",
    "wof:name":"EX8 2NR",
    "wof:placetype":"postalcode"
},
  "geometry": {"coordinates":[-3.37543981604519,50.63066829838856],"type":"Point"}
}