{
  "type": "Feature",
  "properties": {
    "iso:country":"GB",
    "wof:name":"SS4 3RJ",
    "wof:placetype":"postalcode"
},
  "geometry": {"coordinates":[0.72330234232789,51.60046974463514],"type":"Point"}
}