{
  "type": "Feature",
  "properties": {
    "date:inception_lower": "1980-01-01",
    "date:inception_upper": "1980-01-01",
    "iso:country": "GB",
    "wof:name": "SS4 3RJ",
    "wof:placetype": "postalcode"
  },
  "geometry": {"coordinates":[0.723302,51.60047],"type":"Point"}
}
