{
  "type": "Feature",
  "properties": {
    "date:inception_lower":"2013-07-01",
    "date:inception_upper":"2013-07-31",
    "iso:country":"GB",
    "wof:name":"BH8 8PF",
    "wof:placetype":"postalcode"
},
  "geometry": {"coordinates":[-1.857539,50.729727],"type":"Point"}
}