{
  "type": "Feature",
  "properties": {
    "iso:country":"GB",
    "wof:name":"PE7 3JF",
    "wof:placetype":"postalcode"
},
  "geometry": {"coordinates":[-0.25277846250528,52.52063991077758],"type":"Point"}
}