{
  "type": "Feature",
  "properties": {
    "iso:country": "GB",
    "wof:name": "PE7 3JF",
    "wof:placetype": "postalcode"
  },
  "geometry": {"coordinates":[-0.252778,52.52064],"type":"Point"}
}
