{
  "type": "Feature",
  "properties": {
    "iso:country":"GB",
    "wof:name":"DA11 8RB",
    "wof:placetype":"postalcode"
},
  "geometry": {"coordinates":[0.35226369079821,51.43372207290094],"type":"Point"}
}