{
  "type": "Feature",
  "properties": {
    "iso:country":"GB",
    "wof:name":"B32 1QN",
    "wof:placetype":"postalcode"
},
  "geometry": {"coordinates":[-2.00660822459697,52.45893450182949],"type":"Point"}
}