{
  "type": "Feature",
  "properties": {
    "iso:country": "GB",
    "wof:name": "SM1 3RZ",
    "wof:placetype": "postalcode"
  },
  "geometry": {"coordinates":[-0.182086,51.369156],"type":"Point"}
}
