{
  "type": "Feature",
  "properties": {
    "iso:country":"GB",
    "wof:name":"SM1 3RZ",
    "wof:placetype":"postalcode"
},
  "geometry": {"coordinates":[-0.18208628756644,51.36915619471014],"type":"Point"}
}