{
  "type": "Feature",
  "properties": {
    "iso:country":"GB",
    "wof:name":"SW17 7QT",
    "wof:placetype":"postalcode"
},
  "geometry": {"coordinates":[-0.16015072418254,51.44074584156299],"type":"Point"}
}