{
  "type": "Feature",
  "properties": {
    "date:inception_lower":"2012-04-01",
    "date:inception_upper":"2012-04-30",
    "iso:country":"GB",
    "wof:name":"N6 5FD",
    "wof:placetype":"postalcode"
},
  "geometry": {"coordinates":[-0.132567,51.573957],"type":"Point"}
}