{
  "type": "Feature",
  "properties": {
    "iso:country":"GB",
    "wof:name":"N6 5FD",
    "wof:placetype":"postalcode"
},
  "geometry": {"coordinates":[-0.13256709805816,51.57395654334037],"type":"Point"}
}