{
  "type": "Feature",
  "properties": {
    "iso:country":"GB",
    "wof:name":"SL6 4BQ",
    "wof:placetype":"postalcode"
},
  "geometry": {"coordinates":[-0.74157399986721,51.51015849277043],"type":"Point"}
}