{
  "type": "Feature",
  "properties": {
    "iso:country":"GB",
    "wof:name":"S3 7NG",
    "wof:placetype":"postalcode"
},
  "geometry": {"coordinates":[-1.48546232589807,53.38268065518535],"type":"Point"}
}