{
  "type": "Feature",
  "properties": {
    "iso:country": "GB",
    "wof:name": "S3 7NG",
    "wof:placetype": "postalcode"
  },
  "geometry": {"coordinates":[-1.485402,53.382707],"type":"Point"}
}
