{
  "type": "Feature",
  "properties": {
    "iso:country": "GB",
    "wof:name": "PH3 1ER",
    "wof:placetype": "postalcode"
  },
  "geometry": {"coordinates":[-3.683576,56.303352],"type":"Point"}
}
