{
  "type": "Feature",
  "properties": {
    "date:inception_lower": "1980-01-01",
    "date:inception_upper": "1980-01-01",
    "iso:country": "GB",
    "wof:name": "PH3 1ER",
    "wof:placetype": "postalcode"
  },
  "geometry": {"coordinates":[-3.684179,56.302742],"type":"Point"}
}
