{
  "type": "Feature",
  "properties": {
    "iso:country":"GB",
    "wof:name":"PH3 1ER",
    "wof:placetype":"postalcode"
},
  "geometry": {"coordinates":[-3.68419743793757,56.30268704909022],"type":"Point"}
}