{
  "type": "Feature",
  "properties": {
    "date:inception_lower":"1992-08-01",
    "date:inception_upper":"1992-08-31",
    "iso:country":"GB",
    "wof:name":"LE7 4UW",
    "wof:placetype":"postalcode"
},
  "geometry": {"coordinates":[-1.104208,52.715214],"type":"Point"}
}