{
  "type": "Feature",
  "properties": {
    "iso:country": "GB",
    "wof:name": "LE7 4UW",
    "wof:placetype": "postalcode"
  },
  "geometry": {"coordinates":[-1.104208,52.715214],"type":"Point"}
}
