{
  "type": "Feature",
  "properties": {
    "iso:country":"GB",
    "wof:name":"LE7 4UW",
    "wof:placetype":"postalcode"
},
  "geometry": {"coordinates":[-1.10420806156788,52.71521431155625],"type":"Point"}
}