{
  "type": "Feature",
  "properties": {
    "iso:country":"GB",
    "wof:name":"SS9 3EJ",
    "wof:placetype":"postalcode"
},
  "geometry": {"coordinates":[0.66186358338258,51.54927650120912],"type":"Point"}
}