{
  "type": "Feature",
  "properties": {
    "date:inception_lower": "1980-01-01",
    "date:inception_upper": "1980-01-01",
    "iso:country": "GB",
    "wof:name": "SS9 3EJ",
    "wof:placetype": "postalcode"
  },
  "geometry": {"coordinates":[0.661856,51.549151],"type":"Point"}
}
