{
  "type": "Feature",
  "properties": {
    "iso:country":"GB",
    "wof:name":"NG14 6GE",
    "wof:placetype":"postalcode"
},
  "geometry": {"coordinates":[-1.07957946303403,53.03510288522847],"type":"Point"}
}