{
  "type": "Feature",
  "properties": {
    "iso:country":"GB",
    "wof:name":"EN5 2AB",
    "wof:placetype":"postalcode"
},
  "geometry": {"coordinates":[-0.24062558457092,51.64125188910072],"type":"Point"}
}