{
  "type": "Feature",
  "properties": {
    "iso:country":"GB",
    "wof:name":"TN10 3HF",
    "wof:placetype":"postalcode"
},
  "geometry": {"coordinates":[0.27657353203569,51.21530418225016],"type":"Point"}
}