{
  "type": "Feature",
  "properties": {
    "iso:country":"GB",
    "wof:name":"CF44 0HW",
    "wof:placetype":"postalcode"
},
  "geometry": {"coordinates":[-3.41836873905083,51.70934175306422],"type":"Point"}
}