{
  "type": "Feature",
  "properties": {
    "date:inception_lower":"2000-12-01",
    "date:inception_upper":"2000-12-31",
    "iso:country":"GB",
    "wof:name":"TS2 1TT",
    "wof:placetype":"postalcode"
},
  "geometry": {"coordinates":[-1.195814,54.59754],"type":"Point"}
}