{
  "type": "Feature",
  "properties": {
    "iso:country":"GB",
    "wof:name":"TS2 1TT",
    "wof:placetype":"postalcode"
},
  "geometry": {"coordinates":[-1.20102569254298,54.59784944680507],"type":"Point"}
}