{
  "type": "Feature",
  "properties": {
    "iso:country": "GB",
    "wof:name": "SW3 5XP",
    "wof:placetype": "postalcode"
  },
  "geometry": {"coordinates":[-0.166893,51.488432],"type":"Point"}
}
