{
  "type": "Feature",
  "properties": {
    "iso:country": "GB",
    "wof:name": "B26 3LR",
    "wof:placetype": "postalcode"
  },
  "geometry": {"coordinates":[-1.774863,52.452176],"type":"Point"}
}
