{
  "type": "Feature",
  "properties": {
    "iso:country":"GB",
    "wof:name":"B26 3LR",
    "wof:placetype":"postalcode"
},
  "geometry": {"coordinates":[-1.77486335902174,52.4521762325198],"type":"Point"}
}