{
  "type": "Feature",
  "properties": {
    "iso:country": "GB",
    "wof:name": "GU51 4HR",
    "wof:placetype": "postalcode"
  },
  "geometry": {"coordinates":[-0.852982,51.282966],"type":"Point"}
}
