{
  "type": "Feature",
  "properties": {
    "iso:country": "GB",
    "wof:name": "OL14 7DL",
    "wof:placetype": "postalcode"
  },
  "geometry": {"coordinates":[-2.118208,53.725717],"type":"Point"}
}
