{
  "type": "Feature",
  "properties": {
    "iso:country":"GB",
    "wof:name":"OX16 4SF",
    "wof:placetype":"postalcode"
},
  "geometry": {"coordinates":[-1.32073726152457,52.06322209540376],"type":"Point"}
}