{
  "type": "Feature",
  "properties": {
    "date:inception_lower": "2000-06-01",
    "date:inception_upper": "2000-06-01",
    "iso:country": "GB",
    "wof:name": "OX16 4SF",
    "wof:placetype": "postalcode"
  },
  "geometry": {"coordinates":[-1.320737,52.063222],"type":"Point"}
}
