{
  "type": "Feature",
  "properties": {
    "date:inception_lower": "2018-12-01",
    "date:inception_upper": "2018-12-01",
    "iso:country": "GB",
    "wof:name": "TS10 2UL",
    "wof:placetype": "postalcode"
  },
  "geometry": {"coordinates":[-1.043771,54.592984],"type":"Point"}
}
