{
  "type": "Feature",
  "properties": {
    "iso:country":"GB",
    "wof:name":"CB1 9LQ",
    "wof:placetype":"postalcode"
},
  "geometry": {"coordinates":[0.17030406678788,52.18893386809243],"type":"Point"}
}