{
  "type": "Feature",
  "properties": {
    "date:inception_lower": "1980-01-01",
    "date:inception_upper": "1980-01-01",
    "iso:country": "GB",
    "wof:name": "KY10 2PP",
    "wof:placetype": "postalcode"
  },
  "geometry": {"coordinates":[-2.732232,56.212597],"type":"Point"}
}
