{
  "type": "Feature",
  "properties": {
    "iso:country":"GB",
    "wof:name":"KY10 2PP",
    "wof:placetype":"postalcode"
},
  "geometry": {"coordinates":[-2.73223185883539,56.21259694685872],"type":"Point"}
}