{
  "type": "Feature",
  "properties": {
    "iso:country":"GB",
    "wof:name":"WN4 0SN",
    "wof:placetype":"postalcode"
},
  "geometry": {"coordinates":[-2.67523230886816,53.49282461671776],"type":"Point"}
}