{
  "type": "Feature",
  "properties": {
    "date:inception_lower":"1980-01-01",
    "date:inception_upper":"1980-01-31",
    "iso:country":"GB",
    "wof:name":"WN4 0SN",
    "wof:placetype":"postalcode"
},
  "geometry": {"coordinates":[-2.675232,53.492825],"type":"Point"}
}