{
  "type": "Feature",
  "properties": {
    "iso:country":"GB",
    "wof:name":"SE16 6SJ",
    "wof:placetype":"postalcode"
},
  "geometry": {"coordinates":[-0.04185257037789,51.50002451805491],"type":"Point"}
}