{
  "type": "Feature",
  "properties": {
    "date:inception_lower": "1980-01-01",
    "date:inception_upper": "1980-01-01",
    "iso:country": "GB",
    "wof:name": "FY8 1DW",
    "wof:placetype": "postalcode"
  },
  "geometry": {"coordinates":[-3.017555,53.741632],"type":"Point"}
}
