{
  "type": "Feature",
  "properties": {
    "iso:country":"GB",
    "wof:name":"KY14 7PS",
    "wof:placetype":"postalcode"
},
  "geometry": {"coordinates":[-3.27414032284342,56.27811429855535],"type":"Point"}
}