{
  "type": "Feature",
  "properties": {
    "iso:country":"GB",
    "wof:name":"S61 3QE",
    "wof:placetype":"postalcode"
},
  "geometry": {"coordinates":[-1.39221182926871,53.43937464499135],"type":"Point"}
}