{
  "type": "Feature",
  "properties": {
    "iso:country": "GB",
    "wof:name": "DN37 9BL",
    "wof:placetype": "postalcode"
  },
  "geometry": {"coordinates":[-0.122281,53.568014],"type":"Point"}
}
