{
  "type": "Feature",
  "properties": {
    "date:inception_lower":"2005-03-01",
    "date:inception_upper":"2005-03-31",
    "iso:country":"GB",
    "wof:name":"BN3 3AZ",
    "wof:placetype":"postalcode"
},
  "geometry": {"coordinates":[-0.16367,50.828009],"type":"Point"}
}