{
  "type": "Feature",
  "properties": {
    "iso:country": "GB",
    "wof:name": "BH21 7BH",
    "wof:placetype": "postalcode"
  },
  "geometry": {"coordinates":[-1.931497,50.82258],"type":"Point"}
}
