{
  "type": "Feature",
  "properties": {
    "iso:country":"GB",
    "wof:name":"BH21 7BH",
    "wof:placetype":"postalcode"
},
  "geometry": {"coordinates":[-1.93150600506651,50.82258853060898],"type":"Point"}
}