{
  "type": "Feature",
  "properties": {
    "iso:country":"GB",
    "wof:name":"PE4 6NN",
    "wof:placetype":"postalcode"
},
  "geometry": {"coordinates":[-0.27816816242943,52.61648618049897],"type":"Point"}
}