{
  "type": "Feature",
  "properties": {
    "date:inception_lower": "1980-01-01",
    "date:inception_upper": "1980-01-01",
    "iso:country": "GB",
    "wof:name": "PE4 6NN",
    "wof:placetype": "postalcode"
  },
  "geometry": {"coordinates":[-0.278168,52.616486],"type":"Point"}
}
