{
  "type": "Feature",
  "properties": {
    "iso:country":"GB",
    "wof:name":"NG9 5DD",
    "wof:placetype":"postalcode"
},
  "geometry": {"coordinates":[-1.23262668337192,52.91760886763782],"type":"Point"}
}