{
  "type": "Feature",
  "properties": {
    "iso:country": "GB",
    "wof:name": "SG12 9JR",
    "wof:placetype": "postalcode"
  },
  "geometry": {"coordinates":[-0.032224,51.807888],"type":"Point"}
}
