{
  "type": "Feature",
  "properties": {
    "date:inception_lower": "2016-10-01",
    "date:inception_upper": "2016-10-01",
    "iso:country": "GB",
    "wof:name": "YO8 9GJ",
    "wof:placetype": "postalcode"
  },
  "geometry": {"coordinates":[-1.165847,53.767861],"type":"Point"}
}
