{
  "type": "Feature",
  "properties": {
    "iso:country": "GB",
    "wof:name": "BN16 4EW",
    "wof:placetype": "postalcode"
  },
  "geometry": {"coordinates":[-0.477513,50.836177],"type":"Point"}
}
