{
  "type": "Feature",
  "properties": {
    "date:inception_lower": "2021-12-01",
    "date:inception_upper": "2021-12-01",
    "iso:country": "GB",
    "wof:name": "E17 6DT",
    "wof:placetype": "postalcode"
  },
  "geometry": {"coordinates":[-0.043873,51.587127],"type":"Point"}
}
