{
  "type": "Feature",
  "properties": {
    "iso:country": "GB",
    "wof:name": "PL2 3RD",
    "wof:placetype": "postalcode"
  },
  "geometry": {"coordinates":[-4.154398,50.400044],"type":"Point"}
}
