{
  "type": "Feature",
  "properties": {
    "iso:country":"GB",
    "wof:name":"PL2 3RD",
    "wof:placetype":"postalcode"
},
  "geometry": {"coordinates":[-4.15439826075334,50.40004379448943],"type":"Point"}
}