{
  "type": "Feature",
  "properties": {
    "date:inception_lower": "2016-11-01",
    "date:inception_upper": "2016-11-01",
    "iso:country": "GB",
    "wof:name": "CV34 5GE",
    "wof:placetype": "postalcode"
  },
  "geometry": {"coordinates":[-1.562489,52.292749],"type":"Point"}
}
