{
  "type": "Feature",
  "properties": {
    "iso:country": "GB",
    "wof:name": "CV34 5GE",
    "wof:placetype": "postalcode"
  },
  "geometry": {"coordinates":[-1.562489,52.292749],"type":"Point"}
}
