{
  "type": "Feature",
  "properties": {
    "iso:country":"GB",
    "wof:name":"HP3 8BY",
    "wof:placetype":"postalcode"
},
  "geometry": {"coordinates":[-0.44134713607938,51.73788263904623],"type":"Point"}
}