{
  "type": "Feature",
  "properties": {
    "iso:country": "GB",
    "wof:name": "TD11 3SX",
    "wof:placetype": "postalcode"
  },
  "geometry": {"coordinates":[-2.217316,55.798295],"type":"Point"}
}
