{
  "type": "Feature",
  "properties": {
    "iso:country":"GB",
    "wof:name":"TQ12 5JL",
    "wof:placetype":"postalcode"
},
  "geometry": {"coordinates":[-3.57372087794963,50.49249909723874],"type":"Point"}
}