{
  "type": "Feature",
  "properties": {
    "iso:country": "GB",
    "wof:name": "TQ12 5JL",
    "wof:placetype": "postalcode"
  },
  "geometry": {"coordinates":[-3.573721,50.492499],"type":"Point"}
}
