{
  "type": "Feature",
  "properties": {
    "iso:country":"GB",
    "wof:name":"WV11 3BD",
    "wof:placetype":"postalcode"
},
  "geometry": {"coordinates":[-2.06657470114528,52.61059300117007],"type":"Point"}
}