{
  "type": "Feature",
  "properties": {
    "iso:country":"GB",
    "wof:name":"M46 0GA",
    "wof:placetype":"postalcode"
},
  "geometry": {"coordinates":[-2.5196065564603,53.52248284389632],"type":"Point"}
}