{
  "type": "Feature",
  "properties": {
    "iso:country":"GB",
    "wof:name":"TF7 4BJ",
    "wof:placetype":"postalcode"
},
  "geometry": {"coordinates":[-2.44092549983239,52.63694850675525],"type":"Point"}
}