{
  "type": "Feature",
  "properties": {
    "date:inception_lower": "1980-01-01",
    "date:inception_upper": "1980-01-01",
    "iso:country": "GB",
    "wof:name": "TF7 4BJ",
    "wof:placetype": "postalcode"
  },
  "geometry": {"coordinates":[-2.440924,52.636963],"type":"Point"}
}
