{
  "type": "Feature",
  "properties": {
    "iso:country":"GB",
    "wof:name":"NE66 2AP",
    "wof:placetype":"postalcode"
},
  "geometry": {"coordinates":[-1.73287015759063,55.40515447820312],"type":"Point"}
}