{
  "type": "Feature",
  "properties": {
    "iso:country":"GB",
    "wof:name":"CR0 8LW",
    "wof:placetype":"postalcode"
},
  "geometry": {"coordinates":[-0.02889769777594,51.36738029571575],"type":"Point"}
}