{
  "type": "Feature",
  "properties": {
    "iso:country": "GB",
    "wof:name": "LA18 4DN",
    "wof:placetype": "postalcode"
  },
  "geometry": {"coordinates":[-3.264757,54.209001],"type":"Point"}
}
