{
  "type": "Feature",
  "properties": {
    "date:inception_lower": "1980-01-01",
    "date:inception_upper": "1980-01-01",
    "iso:country": "GB",
    "wof:name": "BS10 5RD",
    "wof:placetype": "postalcode"
  },
  "geometry": {"coordinates":[-2.597679,51.502137],"type":"Point"}
}
