{
  "type": "Feature",
  "properties": {
    "iso:country":"GB",
    "wof:name":"DE11 8EW",
    "wof:placetype":"postalcode"
},
  "geometry": {"coordinates":[-1.55001621771172,52.75959883974433],"type":"Point"}
}