{
  "type": "Feature",
  "properties": {
    "date:inception_lower": "1999-06-01",
    "date:inception_upper": "1999-06-01",
    "iso:country": "GB",
    "wof:name": "CH49 8HN",
    "wof:placetype": "postalcode"
  },
  "geometry": {"coordinates":[-3.092448,53.375147],"type":"Point"}
}
