{
  "type": "Feature",
  "properties": {
    "iso:country":"GB",
    "wof:name":"WR1 3QN",
    "wof:placetype":"postalcode"
},
  "geometry": {"coordinates":[-2.22359475824416,52.19397017846951],"type":"Point"}
}