{
  "type": "Feature",
  "properties": {
    "iso:country":"GB",
    "wof:name":"BR6 0EJ",
    "wof:placetype":"postalcode"
},
  "geometry": {"coordinates":[0.09440121030663,51.37569050637328],"type":"Point"}
}