{
  "type": "Feature",
  "properties": {
    "date:inception_lower": "1990-08-01",
    "date:inception_upper": "1990-08-01",
    "iso:country": "GB",
    "wof:name": "AB45 2TN",
    "wof:placetype": "postalcode"
  },
  "geometry": {"coordinates":[-2.667981,57.66818],"type":"Point"}
}
