{
  "type": "Feature",
  "properties": {
    "iso:country":"GB",
    "wof:name":"WV1 4JT",
    "wof:placetype":"postalcode"
},
  "geometry": {"coordinates":[-2.13709984489111,52.58501021888764],"type":"Point"}
}