{
  "type": "Feature",
  "properties": {
    "iso:country":"GB",
    "wof:name":"CR8 2HZ",
    "wof:placetype":"postalcode"
},
  "geometry": {"coordinates":[-0.11188087437148,51.33201173013256],"type":"Point"}
}