{
  "type": "Feature",
  "properties": {
    "date:inception_lower": "2002-10-01",
    "date:inception_upper": "2002-10-01",
    "iso:country": "GB",
    "wof:name": "CR8 2HZ",
    "wof:placetype": "postalcode"
  },
  "geometry": {"coordinates":[-0.111577,51.332123],"type":"Point"}
}
