{
  "type": "Feature",
  "properties": {
    "date:inception_lower":"2003-01-01",
    "date:inception_upper":"2003-01-31",
    "iso:country":"GB",
    "wof:name":"SP9 7AD",
    "wof:placetype":"postalcode"
},
  "geometry": {"coordinates":[-1.662844,51.236079],"type":"Point"}
}