{
  "type": "Feature",
  "properties": {
    "iso:country":"GB",
    "wof:name":"BB1 3HQ",
    "wof:placetype":"postalcode"
},
  "geometry": {"coordinates":[-2.45991561408143,53.74979852025449],"type":"Point"}
}