{
  "type": "Feature",
  "properties": {
    "iso:country": "GB",
    "wof:name": "BS9 1AW",
    "wof:placetype": "postalcode"
  },
  "geometry": {"coordinates":[-2.630047,51.483014],"type":"Point"}
}
