{
  "type": "Feature",
  "properties": {
    "iso:country":"GB",
    "wof:name":"L21 9PF",
    "wof:placetype":"postalcode"
},
  "geometry": {"coordinates":[-2.99817283263229,53.47359230623103],"type":"Point"}
}