{
  "type": "Feature",
  "properties": {
    "iso:country": "GB",
    "wof:name": "KY10 3AZ",
    "wof:placetype": "postalcode"
  },
  "geometry": {"coordinates":[-2.691881,56.22264],"type":"Point"}
}
