{
  "type": "Feature",
  "properties": {
    "iso:country":"GB",
    "wof:name":"KY10 3AZ",
    "wof:placetype":"postalcode"
},
  "geometry": {"coordinates":[-2.69188080146093,56.22264049345734],"type":"Point"}
}