{
  "type": "Feature",
  "properties": {
    "iso:country":"GB",
    "wof:name":"N7 6BQ",
    "wof:placetype":"postalcode"
},
  "geometry": {"coordinates":[-0.12343633023187,51.56018731738265],"type":"Point"}
}