{
  "type": "Feature",
  "properties": {
    "iso:country": "GB",
    "wof:name": "N7 6BQ",
    "wof:placetype": "postalcode"
  },
  "geometry": {"coordinates":[-0.123436,51.560187],"type":"Point"}
}
