{
  "type": "Feature",
  "properties": {
    "iso:country":"GB",
    "wof:name":"N1 3DF",
    "wof:placetype":"postalcode"
},
  "geometry": {"coordinates":[-0.09093099221307,51.53817082402404],"type":"Point"}
}