{
  "type": "Feature",
  "properties": {
    "iso:country":"GB",
    "wof:name":"DD10 8UA",
    "wof:placetype":"postalcode"
},
  "geometry": {"coordinates":[-2.46610416682244,56.71086990551507],"type":"Point"}
}