{
  "type": "Feature",
  "properties": {
    "iso:country":"GB",
    "wof:name":"TN37 6QH",
    "wof:placetype":"postalcode"
},
  "geometry": {"coordinates":[0.56221510574133,50.85471540498919],"type":"Point"}
}