{
  "type": "Feature",
  "properties": {
    "iso:country":"GB",
    "wof:name":"SG1 3NB",
    "wof:placetype":"postalcode"
},
  "geometry": {"coordinates":[-0.19374796945425,51.91045544392817],"type":"Point"}
}