{
  "type": "Feature",
  "properties": {
    "iso:country": "GB",
    "wof:name": "MK16 9GF",
    "wof:placetype": "postalcode"
  },
  "geometry": {"coordinates":[-0.709039,52.082899],"type":"Point"}
}
