{
  "type": "Feature",
  "properties": {
    "iso:country":"GB",
    "wof:name":"MK16 9GF",
    "wof:placetype":"postalcode"
},
  "geometry": {"coordinates":[-0.70903932912437,52.08289884329638],"type":"Point"}
}