{
  "type": "Feature",
  "properties": {
    "date:inception_lower": "1997-06-01",
    "date:inception_upper": "1997-06-01",
    "iso:country": "GB",
    "wof:name": "MK16 9GF",
    "wof:placetype": "postalcode"
  },
  "geometry": {"coordinates":[-0.709039,52.082899],"type":"Point"}
}
