{
  "type": "Feature",
  "properties": {
    "iso:country": "GB",
    "wof:name": "DL3 9RG",
    "wof:placetype": "postalcode"
  },
  "geometry": {"coordinates":[-1.587091,54.535561],"type":"Point"}
}
