{
  "type": "Feature",
  "properties": {
    "iso:country": "GB",
    "wof:name": "LE12 6TF",
    "wof:placetype": "postalcode"
  },
  "geometry": {"coordinates":[-1.104757,52.80553],"type":"Point"}
}
