{
  "type": "Feature",
  "properties": {
    "iso:country":"GB",
    "wof:name":"LE12 6TF",
    "wof:placetype":"postalcode"
},
  "geometry": {"coordinates":[-1.10475664618196,52.80553020443269],"type":"Point"}
}