{
  "type": "Feature",
  "properties": {
    "iso:country": "GB",
    "wof:name": "MK42 9DA",
    "wof:placetype": "postalcode"
  },
  "geometry": {"coordinates":[-0.472646,52.130263],"type":"Point"}
}
