{
  "type": "Feature",
  "properties": {
    "iso:country": "GB",
    "wof:name": "EN3 4FL",
    "wof:placetype": "postalcode"
  },
  "geometry": {"coordinates":[-0.048262,51.646344],"type":"Point"}
}
