{
  "type": "Feature",
  "properties": {
    "iso:country":"GB",
    "wof:name":"CT3 4JZ",
    "wof:placetype":"postalcode"
},
  "geometry": {"coordinates":[1.17371295787645,51.31608930931949],"type":"Point"}
}