{
  "type": "Feature",
  "properties": {
    "iso:country":"GB",
    "wof:name":"BH6 3PQ",
    "wof:placetype":"postalcode"
},
  "geometry": {"coordinates":[-1.81158248349641,50.7245903428975],"type":"Point"}
}