{
  "type": "Feature",
  "properties": {
    "iso:country":"GB",
    "wof:name":"PO6 2JT",
    "wof:placetype":"postalcode"
},
  "geometry": {"coordinates":[-1.05274942713782,50.84507834811166],"type":"Point"}
}