{
  "type": "Feature",
  "properties": {
    "iso:country":"GB",
    "wof:name":"SK8 5RX",
    "wof:placetype":"postalcode"
},
  "geometry": {"coordinates":[-2.19250042216568,53.38679663546505],"type":"Point"}
}