{
  "type": "Feature",
  "properties": {
    "date:inception_lower": "2020-07-01",
    "date:inception_upper": "2020-07-01",
    "iso:country": "GB",
    "wof:name": "LS25 4ER",
    "wof:placetype": "postalcode"
  },
  "geometry": {"coordinates":[-1.326926,53.792179],"type":"Point"}
}
