{
  "type": "Feature",
  "properties": {
    "iso:country":"GB",
    "wof:name":"DN7 4EN",
    "wof:placetype":"postalcode"
},
  "geometry": {"coordinates":[-1.01950213923214,53.58447535835553],"type":"Point"}
}