{
  "type": "Feature",
  "properties": {
    "date:inception_lower": "1980-01-01",
    "date:inception_upper": "1980-01-01",
    "iso:country": "GB",
    "wof:name": "DN7 4EN",
    "wof:placetype": "postalcode"
  },
  "geometry": {"coordinates":[-1.019502,53.584475],"type":"Point"}
}
