{
  "type": "Feature",
  "properties": {
    "date:inception_lower": "1980-01-01",
    "date:inception_upper": "1980-01-01",
    "iso:country": "GB",
    "wof:name": "SN1 5BP",
    "wof:placetype": "postalcode"
  },
  "geometry": {"coordinates":[-1.79085,51.562135],"type":"Point"}
}
