{
  "type": "Feature",
  "properties": {
    "iso:country":"GB",
    "wof:name":"WV6 8ED",
    "wof:placetype":"postalcode"
},
  "geometry": {"coordinates":[-2.19220825436249,52.58438510286989],"type":"Point"}
}