{
  "type": "Feature",
  "properties": {
    "date:inception_lower": "1980-01-01",
    "date:inception_upper": "1980-01-01",
    "iso:country": "GB",
    "wof:name": "WV6 8ED",
    "wof:placetype": "postalcode"
  },
  "geometry": {"coordinates":[-2.192208,52.584385],"type":"Point"}
}
