{
  "type": "Feature",
  "properties": {
    "iso:country":"GB",
    "wof:name":"BD2 4JD",
    "wof:placetype":"postalcode"
},
  "geometry": {"coordinates":[-1.7350859238414,53.812514798385],"type":"Point"}
}