{
  "type": "Feature",
  "properties": {
    "iso:country":"GB",
    "wof:name":"BA22 9NN",
    "wof:placetype":"postalcode"
},
  "geometry": {"coordinates":[-2.684668518353,50.90765533009194],"type":"Point"}
}