{
  "type": "Feature",
  "properties": {
    "date:inception_lower": "1980-01-01",
    "date:inception_upper": "1980-01-01",
    "iso:country": "GB",
    "wof:name": "BA22 9NN",
    "wof:placetype": "postalcode"
  },
  "geometry": {"coordinates":[-2.684668,50.907655],"type":"Point"}
}
