{
  "type": "Feature",
  "properties": {
    "date:inception_lower": "1998-06-01",
    "date:inception_upper": "1998-06-01",
    "iso:country": "GB",
    "wof:name": "N11 2EQ",
    "wof:placetype": "postalcode"
  },
  "geometry": {"coordinates":[-0.124584,51.606265],"type":"Point"}
}
