{
  "type": "Feature",
  "properties": {
    "iso:country":"GB",
    "wof:name":"N11 2EQ",
    "wof:placetype":"postalcode"
},
  "geometry": {"coordinates":[-0.12458415142765,51.6062648877458],"type":"Point"}
}