{
  "type": "Feature",
  "properties": {
    "iso:country": "GB",
    "wof:name": "SL1 4RP",
    "wof:placetype": "postalcode"
  },
  "geometry": {"coordinates":[-0.627519,51.521621],"type":"Point"}
}
