{
  "type": "Feature",
  "properties": {
    "iso:country":"GB",
    "wof:name":"SL1 4RP",
    "wof:placetype":"postalcode"
},
  "geometry": {"coordinates":[-0.62751858515994,51.52162125178242],"type":"Point"}
}