{
  "type": "Feature",
  "properties": {
    "iso:country":"GB",
    "wof:name":"L6 4AZ",
    "wof:placetype":"postalcode"
},
  "geometry": {"coordinates":[-2.941419266405,53.4232840799727],"type":"Point"}
}