{
  "type": "Feature",
  "properties": {
    "date:inception_lower": "1995-12-01",
    "date:inception_upper": "1995-12-01",
    "iso:country": "GB",
    "wof:name": "RG10 9EN",
    "wof:placetype": "postalcode"
  },
  "geometry": {"coordinates":[-0.8662,51.484292],"type":"Point"}
}
