{
  "type": "Feature",
  "properties": {
    "iso:country":"GB",
    "wof:name":"GU9 0PD",
    "wof:placetype":"postalcode"
},
  "geometry": {"coordinates":[-0.79670448605106,51.235102207491],"type":"Point"}
}