{
  "type": "Feature",
  "properties": {
    "iso:country":"GB",
    "wof:name":"WR2 4UB",
    "wof:placetype":"postalcode"
},
  "geometry": {"coordinates":[-2.25170146871165,52.14541899823487],"type":"Point"}
}