{
  "type": "Feature",
  "properties": {
    "iso:country":"GB",
    "wof:name":"RG20 7AS",
    "wof:placetype":"postalcode"
},
  "geometry": {"coordinates":[-1.32691481592468,51.54053939996253],"type":"Point"}
}