{
  "type": "Feature",
  "properties": {
    "date:inception_lower": "1980-01-01",
    "date:inception_upper": "1980-01-01",
    "iso:country": "GB",
    "wof:name": "LE4 4LA",
    "wof:placetype": "postalcode"
  },
  "geometry": {"coordinates":[-1.12306,52.68498],"type":"Point"}
}
