{
  "type": "Feature",
  "properties": {
    "iso:country":"GB",
    "wof:name":"LE4 4LA",
    "wof:placetype":"postalcode"
},
  "geometry": {"coordinates":[-1.12300819045054,52.68495995674581],"type":"Point"}
}