{
  "type": "Feature",
  "properties": {
    "iso:country": "GB",
    "wof:name": "FY1 5DX",
    "wof:placetype": "postalcode"
  },
  "geometry": {"coordinates":[-3.053041,53.808681],"type":"Point"}
}
