{
  "type": "Feature",
  "properties": {
    "iso:country":"GB",
    "wof:name":"S75 4PT",
    "wof:placetype":"postalcode"
},
  "geometry": {"coordinates":[-1.56810838172759,53.53512113372421],"type":"Point"}
}