{
  "type": "Feature",
  "properties": {
    "iso:country": "GB",
    "wof:name": "IP1 6LF",
    "wof:placetype": "postalcode"
  },
  "geometry": {"coordinates":[1.121626,52.084906],"type":"Point"}
}
