{
  "type": "Feature",
  "properties": {
    "iso:country":"GB",
    "wof:name":"LL11 6LZ",
    "wof:placetype":"postalcode"
},
  "geometry": {"coordinates":[-3.03133766663488,53.06138180650556],"type":"Point"}
}