{
  "type": "Feature",
  "properties": {
    "date:inception_lower": "2000-12-01",
    "date:inception_upper": "2000-12-01",
    "iso:country": "GB",
    "wof:name": "WD18 6GE",
    "wof:placetype": "postalcode"
  },
  "geometry": {"coordinates":[-0.414624,51.646428],"type":"Point"}
}
