{
  "type": "Feature",
  "properties": {
    "iso:country":"GB",
    "wof:name":"FY3 7BP",
    "wof:placetype":"postalcode"
},
  "geometry": {"coordinates":[-3.0301536804178,53.82767874873905],"type":"Point"}
}