{
  "type": "Feature",
  "properties": {
    "date:inception_lower": "1980-01-01",
    "date:inception_upper": "1980-01-01",
    "iso:country": "GB",
    "wof:name": "FY3 7BP",
    "wof:placetype": "postalcode"
  },
  "geometry": {"coordinates":[-3.030154,53.827679],"type":"Point"}
}
