{
  "type": "Feature",
  "properties": {
    "date:inception_lower":"1998-06-01",
    "date:inception_upper":"1998-06-30",
    "iso:country":"GB",
    "wof:name":"BA10 0DY",
    "wof:placetype":"postalcode"
},
  "geometry": {"coordinates":[-2.454777,51.11346],"type":"Point"}
}