{
  "type": "Feature",
  "properties": {
    "iso:country":"GB",
    "wof:name":"SE10 8SE",
    "wof:placetype":"postalcode"
},
  "geometry": {"coordinates":[-0.01002753337189,51.47582001330841],"type":"Point"}
}