{
  "type": "Feature",
  "properties": {
    "iso:country": "GB",
    "wof:name": "SN15 1FB",
    "wof:placetype": "postalcode"
  },
  "geometry": {"coordinates":[-2.114447,51.465912],"type":"Point"}
}
