{
  "type": "Feature",
  "properties": {
    "iso:country":"GB",
    "wof:name":"SN15 1FB",
    "wof:placetype":"postalcode"
},
  "geometry": {"coordinates":[-2.11445245746435,51.46591296379422],"type":"Point"}
}