{
  "type": "Feature",
  "properties": {
    "date:inception_lower": "2011-12-01",
    "date:inception_upper": "2011-12-01",
    "iso:country": "GB",
    "wof:name": "SN15 1FB",
    "wof:placetype": "postalcode"
  },
  "geometry": {"coordinates":[-2.114404,51.465993],"type":"Point"}
}
