{
  "type": "Feature",
  "properties": {
    "date:inception_lower":"2011-12-01",
    "date:inception_upper":"2011-12-31",
    "iso:country":"GB",
    "wof:name":"SN15 1FB",
    "wof:placetype":"postalcode"
},
  "geometry": {"coordinates":[-2.114447,51.465912],"type":"Point"}
}