{
  "type": "Feature",
  "properties": {
    "iso:country":"GB",
    "wof:name":"RH2 0DU",
    "wof:placetype":"postalcode"
},
  "geometry": {"coordinates":[-0.1964577442873,51.24900166665432],"type":"Point"}
}