{
  "type": "Feature",
  "properties": {
    "iso:country": "GB",
    "wof:name": "CT2 7FN",
    "wof:placetype": "postalcode"
  },
  "geometry": {"coordinates":[1.06264,51.29399],"type":"Point"}
}
