{
  "type": "Feature",
  "properties": {
    "iso:country":"GB",
    "wof:name":"EN6 5PU",
    "wof:placetype":"postalcode"
},
  "geometry": {"coordinates":[-0.17462256594679,51.69122144071055],"type":"Point"}
}