{
  "type": "Feature",
  "properties": {
    "iso:country": "GB",
    "wof:name": "OX10 8ER",
    "wof:placetype": "postalcode"
  },
  "geometry": {"coordinates":[-1.1109,51.598249],"type":"Point"}
}
