{
  "type": "Feature",
  "properties": {
    "date:inception_lower": "1980-01-01",
    "date:inception_upper": "1980-01-01",
    "iso:country": "GB",
    "wof:name": "LS16 5DA",
    "wof:placetype": "postalcode"
  },
  "geometry": {"coordinates":[-1.605891,53.833345],"type":"Point"}
}
