{
  "type": "Feature",
  "properties": {
    "date:inception_lower": "1992-01-01",
    "date:inception_upper": "1992-01-01",
    "iso:country": "GB",
    "wof:name": "DA12 2PA",
    "wof:placetype": "postalcode"
  },
  "geometry": {"coordinates":[0.385117,51.440721],"type":"Point"}
}
