{
  "type": "Feature",
  "properties": {
    "iso:country":"GB",
    "wof:name":"DA12 2PA",
    "wof:placetype":"postalcode"
},
  "geometry": {"coordinates":[0.38455162498093,51.44065083978614],"type":"Point"}
}