{
  "type": "Feature",
  "properties": {
    "iso:country":"GB",
    "wof:name":"PE31 8HY",
    "wof:placetype":"postalcode"
},
  "geometry": {"coordinates":[0.75778929442706,52.93857081401713],"type":"Point"}
}