{
  "type": "Feature",
  "properties": {
    "date:inception_lower": "2009-09-01",
    "date:inception_upper": "2009-09-01",
    "iso:country": "GB",
    "wof:name": "PE31 8HY",
    "wof:placetype": "postalcode"
  },
  "geometry": {"coordinates":[0.757789,52.938571],"type":"Point"}
}
