{
  "type": "Feature",
  "properties": {
    "iso:country": "GB",
    "wof:name": "SA1 7AU",
    "wof:placetype": "postalcode"
  },
  "geometry": {"coordinates":[-3.911431,51.639775],"type":"Point"}
}
