{
  "type": "Feature",
  "properties": {
    "iso:country":"GB",
    "wof:name":"SA1 7AU",
    "wof:placetype":"postalcode"
},
  "geometry": {"coordinates":[-3.91143104026674,51.63977453279174],"type":"Point"}
}