{
  "type": "Feature",
  "properties": {
    "date:inception_lower":"2014-04-01",
    "date:inception_upper":"2014-04-30",
    "iso:country":"GB",
    "wof:name":"TA21 8FD",
    "wof:placetype":"postalcode"
},
  "geometry": {"coordinates":[-3.230669,50.985732],"type":"Point"}
}