{
  "type": "Feature",
  "properties": {
    "date:inception_lower":"1980-01-01",
    "date:inception_upper":"1980-01-31",
    "iso:country":"GB",
    "wof:name":"ME19 5PE",
    "wof:placetype":"postalcode"
},
  "geometry": {"coordinates":[0.372851,51.291679],"type":"Point"}
}