{
  "type": "Feature",
  "properties": {
    "date:inception_lower":"1997-06-01",
    "date:inception_upper":"1997-06-30",
    "iso:country":"GB",
    "wof:name":"PH1 2UD",
    "wof:placetype":"postalcode"
},
  "geometry": {"coordinates":[-3.473226,56.412491],"type":"Point"}
}