{
  "type": "Feature",
  "properties": {
    "iso:country": "GB",
    "wof:name": "PH1 2UD",
    "wof:placetype": "postalcode"
  },
  "geometry": {"coordinates":[-3.473226,56.412491],"type":"Point"}
}
