{
  "type": "Feature",
  "properties": {
    "date:inception_lower": "1999-06-01",
    "date:inception_upper": "1999-06-01",
    "iso:country": "GB",
    "wof:name": "NP10 8LS",
    "wof:placetype": "postalcode"
  },
  "geometry": {"coordinates":[-3.057247,51.57777],"type":"Point"}
}
