{
  "type": "Feature",
  "properties": {
    "iso:country":"GB",
    "wof:name":"NP10 8LS",
    "wof:placetype":"postalcode"
},
  "geometry": {"coordinates":[-3.0572471539213,51.57776983540788],"type":"Point"}
}