{
  "type": "Feature",
  "properties": {
    "iso:country":"GB",
    "wof:name":"HD3 4TB",
    "wof:placetype":"postalcode"
},
  "geometry": {"coordinates":[-1.83145095946621,53.64471962436596],"type":"Point"}
}