{
  "type": "Feature",
  "properties": {
    "iso:country":"GB",
    "wof:name":"BS24 9QU",
    "wof:placetype":"postalcode"
},
  "geometry": {"coordinates":[-2.9350880551316,51.32642504112528],"type":"Point"}
}