{
  "type": "Feature",
  "properties": {
    "date:inception_lower": "1984-10-01",
    "date:inception_upper": "1984-10-01",
    "iso:country": "GB",
    "wof:name": "TS17 0SD",
    "wof:placetype": "postalcode"
  },
  "geometry": {"coordinates":[-1.3118,54.52365],"type":"Point"}
}
