{
  "type": "Feature",
  "properties": {
    "iso:country": "GB",
    "wof:name": "NE3 4AU",
    "wof:placetype": "postalcode"
  },
  "geometry": {"coordinates":[-1.632337,55.007788],"type":"Point"}
}
