{
  "type": "Feature",
  "properties": {
    "date:inception_lower":"2008-06-01",
    "date:inception_upper":"2008-06-30",
    "iso:country":"GB",
    "wof:name":"NE3 4AU",
    "wof:placetype":"postalcode"
},
  "geometry": {"coordinates":[-1.632337,55.007788],"type":"Point"}
}