{
  "type": "Feature",
  "properties": {
    "iso:country": "GB",
    "wof:name": "YO12 4BD",
    "wof:placetype": "postalcode"
  },
  "geometry": {"coordinates":[-0.41716,54.264598],"type":"Point"}
}
