{
  "type": "Feature",
  "properties": {
    "iso:country":"GB",
    "wof:name":"DY4 8TS",
    "wof:placetype":"postalcode"
},
  "geometry": {"coordinates":[-2.05542333835278,52.52777553281118],"type":"Point"}
}