{
  "type": "Feature",
  "properties": {
    "iso:country": "GB",
    "wof:name": "DY4 8TS",
    "wof:placetype": "postalcode"
  },
  "geometry": {"coordinates":[-2.055423,52.527776],"type":"Point"}
}
