{
  "type": "Feature",
  "properties": {
    "date:inception_lower": "1994-05-01",
    "date:inception_upper": "1994-05-01",
    "iso:country": "GB",
    "wof:name": "DY4 8TS",
    "wof:placetype": "postalcode"
  },
  "geometry": {"coordinates":[-2.055423,52.527776],"type":"Point"}
}
