{
  "type": "Feature",
  "properties": {
    "iso:country":"GB",
    "wof:name":"WN3 6XU",
    "wof:placetype":"postalcode"
},
  "geometry": {"coordinates":[-2.65364140838072,53.51689023134789],"type":"Point"}
}