{
  "type": "Feature",
  "properties": {
    "iso:country":"GB",
    "wof:name":"E1 4PT",
    "wof:placetype":"postalcode"
},
  "geometry": {"coordinates":[-0.03685465998076,51.52177506799912],"type":"Point"}
}