{
  "type": "Feature",
  "properties": {
    "date:inception_lower":"2001-12-01",
    "date:inception_upper":"2001-12-31",
    "iso:country":"GB",
    "wof:name":"S71 4TA",
    "wof:placetype":"postalcode"
},
  "geometry": {"coordinates":[-1.469824,53.599371],"type":"Point"}
}