{
  "type": "Feature",
  "properties": {
    "iso:country":"GB",
    "wof:name":"S71 4TA",
    "wof:placetype":"postalcode"
},
  "geometry": {"coordinates":[-1.46982393451,53.59937069232576],"type":"Point"}
}