{
  "type": "Feature",
  "properties": {
    "iso:country":"GB",
    "wof:name":"SW15 2UN",
    "wof:placetype":"postalcode"
},
  "geometry": {"coordinates":[-0.20601770922949,51.45520633902608],"type":"Point"}
}