{
  "type": "Feature",
  "properties": {
    "iso:country": "GB",
    "wof:name": "B23 5FU",
    "wof:placetype": "postalcode"
  },
  "geometry": {"coordinates":[-1.832705,52.532648],"type":"Point"}
}
