{
  "type": "Feature",
  "properties": {
    "iso:country":"GB",
    "wof:name":"WF1 5QN",
    "wof:placetype":"postalcode"
},
  "geometry": {"coordinates":[-1.49388256993456,53.67627983757683],"type":"Point"}
}