{
  "type": "Feature",
  "properties": {
    "iso:country":"GB",
    "wof:name":"NE46 2LR",
    "wof:placetype":"postalcode"
},
  "geometry": {"coordinates":[-2.12006158197662,54.96513190490758],"type":"Point"}
}