{
  "type": "Feature",
  "properties": {
    "iso:country":"GB",
    "wof:name":"IP11 7JA",
    "wof:placetype":"postalcode"
},
  "geometry": {"coordinates":[1.3545169885365,51.96304173024909],"type":"Point"}
}