{
  "type": "Feature",
  "properties": {
    "iso:country":"GB",
    "wof:name":"TN16 3HX",
    "wof:placetype":"postalcode"
},
  "geometry": {"coordinates":[0.04552703953054,51.30496112667038],"type":"Point"}
}