{
  "type": "Feature",
  "properties": {
    "iso:country":"GB",
    "wof:name":"EC1Y 8QH",
    "wof:placetype":"postalcode"
},
  "geometry": {"coordinates":[-0.09307809167491,51.5240604849395],"type":"Point"}
}