{
  "type": "Feature",
  "properties": {
    "date:inception_lower":"2016-02-01",
    "date:inception_upper":"2016-02-29",
    "iso:country":"GB",
    "wof:name":"E9 7FA",
    "wof:placetype":"postalcode"
},
  "geometry": {"coordinates":[-0.038858,51.541603],"type":"Point"}
}