{
  "type": "Feature",
  "properties": {
    "iso:country":"GB",
    "wof:name":"E9 7FA",
    "wof:placetype":"postalcode"
},
  "geometry": {"coordinates":[-0.05648197417361,51.53883712787744],"type":"Point"}
}