{
  "type": "Feature",
  "properties": {
    "iso:country": "GB",
    "wof:name": "E9 7FA",
    "wof:placetype": "postalcode"
  },
  "geometry": {"coordinates":[-0.038858,51.541603],"type":"Point"}
}
