{
  "type": "Feature",
  "properties": {
    "date:inception_lower": "1980-01-01",
    "date:inception_upper": "1980-01-01",
    "iso:country": "GB",
    "wof:name": "GL11 4QQ",
    "wof:placetype": "postalcode"
  },
  "geometry": {"coordinates":[-2.34409,51.674199],"type":"Point"}
}
