{
  "type": "Feature",
  "properties": {
    "iso:country":"GB",
    "wof:name":"GL11 4QQ",
    "wof:placetype":"postalcode"
},
  "geometry": {"coordinates":[-2.34408954455673,51.67419866004798],"type":"Point"}
}