{
  "type": "Feature",
  "properties": {
    "iso:country":"GB",
    "wof:name":"AL9 5ED",
    "wof:placetype":"postalcode"
},
  "geometry": {"coordinates":[-0.21404846026704,51.76838641884194],"type":"Point"}
}