{
  "type": "Feature",
  "properties": {
    "date:inception_lower": "2021-06-01",
    "date:inception_upper": "2021-06-01",
    "iso:country": "GB",
    "wof:name": "TN25 6FE",
    "wof:placetype": "postalcode"
  },
  "geometry": {"coordinates":[1.001069,51.103742],"type":"Point"}
}
