{
  "type": "Feature",
  "properties": {
    "iso:country": "GB",
    "wof:name": "BD1 1AG",
    "wof:placetype": "postalcode"
  },
  "geometry": {"coordinates":[-1.75338,53.793424],"type":"Point"}
}
