{
  "type": "Feature",
  "properties": {
    "iso:country": "GB",
    "wof:name": "LS26 0XD",
    "wof:placetype": "postalcode"
  },
  "geometry": {"coordinates":[-1.489509,53.756274],"type":"Point"}
}
