{
  "type": "Feature",
  "properties": {
    "iso:country":"GB",
    "wof:name":"LS26 0XD",
    "wof:placetype":"postalcode"
},
  "geometry": {"coordinates":[-1.48950932419006,53.75627410823609],"type":"Point"}
}