{
  "type": "Feature",
  "properties": {
    "date:inception_lower":"1980-01-01",
    "date:inception_upper":"1980-01-31",
    "iso:country":"GB",
    "wof:name":"CH5 4RF",
    "wof:placetype":"postalcode"
},
  "geometry": {"coordinates":[-3.058929,53.213303],"type":"Point"}
}