{
  "type": "Feature",
  "properties": {
    "iso:country":"GB",
    "wof:name":"CH5 4RF",
    "wof:placetype":"postalcode"
},
  "geometry": {"coordinates":[-3.05892870928816,53.21330270298915],"type":"Point"}
}