{
  "type": "Feature",
  "properties": {
    "date:inception_lower":"1992-08-01",
    "date:inception_upper":"1992-08-31",
    "iso:country":"GB",
    "wof:name":"DE56 2TW",
    "wof:placetype":"postalcode"
},
  "geometry": {"coordinates":[-1.493672,53.034376],"type":"Point"}
}