{
  "type": "Feature",
  "properties": {
    "iso:country":"GB",
    "wof:name":"TS20 1ER",
    "wof:placetype":"postalcode"
},
  "geometry": {"coordinates":[-1.31832224690609,54.59028053219635],"type":"Point"}
}