{
  "type": "Feature",
  "properties": {
    "iso:country": "GB",
    "wof:name": "SO52 9DP",
    "wof:placetype": "postalcode"
  },
  "geometry": {"coordinates":[-1.454582,50.983235],"type":"Point"}
}
