{
  "type": "Feature",
  "properties": {
    "date:inception_lower":"1980-01-01",
    "date:inception_upper":"1980-01-31",
    "iso:country":"GB",
    "wof:name":"SR7 7NN",
    "wof:placetype":"postalcode"
},
  "geometry": {"coordinates":[-1.328995,54.8323],"type":"Point"}
}