{
  "type": "Feature",
  "properties": {
    "date:inception_lower": "1992-08-01",
    "date:inception_upper": "1992-08-01",
    "iso:country": "GB",
    "wof:name": "MK45 1QY",
    "wof:placetype": "postalcode"
  },
  "geometry": {"coordinates":[-0.495975,52.00266],"type":"Point"}
}
