{
  "type": "Feature",
  "properties": {
    "iso:country":"GB",
    "wof:name":"MK45 1QY",
    "wof:placetype":"postalcode"
},
  "geometry": {"coordinates":[-0.49597542347947,52.00266049693882],"type":"Point"}
}