{
  "type": "Feature",
  "properties": {
    "iso:country":"GB",
    "wof:name":"SO21 3PT",
    "wof:placetype":"postalcode"
},
  "geometry": {"coordinates":[-1.31227316974241,51.15519912820405],"type":"Point"}
}