{
  "type": "Feature",
  "properties": {
    "iso:country": "GB",
    "wof:name": "TN19 7LQ",
    "wof:placetype": "postalcode"
  },
  "geometry": {"coordinates":[0.343121,50.986037],"type":"Point"}
}
