{
  "type": "Feature",
  "properties": {
    "iso:country":"GB",
    "wof:name":"PA4 9QE",
    "wof:placetype":"postalcode"
},
  "geometry": {"coordinates":[-4.43516178540792,55.8930386316964],"type":"Point"}
}