{
  "type": "Feature",
  "properties": {
    "date:inception_lower": "1980-01-01",
    "date:inception_upper": "1980-01-01",
    "iso:country": "GB",
    "wof:name": "PA4 9QE",
    "wof:placetype": "postalcode"
  },
  "geometry": {"coordinates":[-4.435162,55.893039],"type":"Point"}
}
