{
  "type": "Feature",
  "properties": {
    "date:inception_lower": "1995-12-01",
    "date:inception_upper": "1995-12-01",
    "iso:country": "GB",
    "wof:name": "BR3 5NY",
    "wof:placetype": "postalcode"
  },
  "geometry": {"coordinates":[-0.011498,51.409191],"type":"Point"}
}
