{
  "type": "Feature",
  "properties": {
    "iso:country":"GB",
    "wof:name":"BR3 5NY",
    "wof:placetype":"postalcode"
},
  "geometry": {"coordinates":[-0.01149832186292,51.40919066262378],"type":"Point"}
}