{
  "type": "Feature",
  "properties": {
    "date:inception_lower":"1980-01-01",
    "date:inception_upper":"1980-01-31",
    "iso:country":"GB",
    "wof:name":"CR0 5HT",
    "wof:placetype":"postalcode"
},
  "geometry": {"coordinates":[-0.050045,51.362977],"type":"Point"}
}