{
  "type": "Feature",
  "properties": {
    "iso:country":"GB",
    "wof:name":"LN6 9HU",
    "wof:placetype":"postalcode"
},
  "geometry": {"coordinates":[-0.68590068715932,53.16444404773491],"type":"Point"}
}