{
  "type": "Feature",
  "properties": {
    "iso:country": "GB",
    "wof:name": "LN6 9HU",
    "wof:placetype": "postalcode"
  },
  "geometry": {"coordinates":[-0.685901,53.164444],"type":"Point"}
}
