{
  "type": "Feature",
  "properties": {
    "iso:country":"GB",
    "wof:name":"CH8 7NQ",
    "wof:placetype":"postalcode"
},
  "geometry": {"coordinates":[-3.23598844306779,53.27807385025216],"type":"Point"}
}