{
  "type": "Feature",
  "properties": {
    "iso:country": "GB",
    "wof:name": "SE22 8QX",
    "wof:placetype": "postalcode"
  },
  "geometry": {"coordinates":[-0.079423,51.456609],"type":"Point"}
}
