{
  "type": "Feature",
  "properties": {
    "iso:country":"GB",
    "wof:name":"LE12 8HL",
    "wof:placetype":"postalcode"
},
  "geometry": {"coordinates":[-1.11552640162974,52.75798306172421],"type":"Point"}
}