{
  "type": "Feature",
  "properties": {
    "iso:country":"GB",
    "wof:name":"KA9 1PU",
    "wof:placetype":"postalcode"
},
  "geometry": {"coordinates":[-4.61533853325358,55.49584955154],"type":"Point"}
}