{
  "type": "Feature",
  "properties": {
    "iso:country":"GB",
    "wof:name":"TR1 1NA",
    "wof:placetype":"postalcode"
},
  "geometry": {"coordinates":[-5.0405407963069,50.27099020067605],"type":"Point"}
}