{
  "type": "Feature",
  "properties": {
    "date:inception_lower":"1983-03-01",
    "date:inception_upper":"1983-03-31",
    "iso:country":"GB",
    "wof:name":"GL5 1UZ",
    "wof:placetype":"postalcode"
},
  "geometry": {"coordinates":[-2.204634,51.753314],"type":"Point"}
}