{
  "type": "Feature",
  "properties": {
    "date:inception_lower": "1980-01-01",
    "date:inception_upper": "1980-01-01",
    "iso:country": "GB",
    "wof:name": "FK2 9RW",
    "wof:placetype": "postalcode"
  },
  "geometry": {"coordinates":[-3.743619,55.991154],"type":"Point"}
}
