{
  "type": "Feature",
  "properties": {
    "iso:country": "GB",
    "wof:name": "LL57 4YS",
    "wof:placetype": "postalcode"
  },
  "geometry": {"coordinates":[-4.072914,53.175672],"type":"Point"}
}
