{
  "type": "Feature",
  "properties": {
    "iso:country":"GB",
    "wof:name":"LL57 4YS",
    "wof:placetype":"postalcode"
},
  "geometry": {"coordinates":[-4.07291372338906,53.17567161465659],"type":"Point"}
}