{
  "type": "Feature",
  "properties": {
    "iso:country":"GB",
    "wof:name":"WV5 9EP",
    "wof:placetype":"postalcode"
},
  "geometry": {"coordinates":[-2.1894557364755,52.53823567318801],"type":"Point"}
}