{
  "type": "Feature",
  "properties": {
    "date:inception_lower": "2016-08-01",
    "date:inception_upper": "2016-08-01",
    "iso:country": "GB",
    "wof:name": "PH2 7UX",
    "wof:placetype": "postalcode"
  },
  "geometry": {"coordinates":[-3.20927,56.396459],"type":"Point"}
}
