{
  "type": "Feature",
  "properties": {
    "iso:country": "GB",
    "wof:name": "AB45 2JX",
    "wof:placetype": "postalcode"
  },
  "geometry": {"coordinates":[-2.579034,57.671046],"type":"Point"}
}
