{
  "type": "Feature",
  "properties": {
    "iso:country": "GB",
    "wof:name": "DE22 2RF",
    "wof:placetype": "postalcode"
  },
  "geometry": {"coordinates":[-1.500867,52.940648],"type":"Point"}
}
