{
  "type": "Feature",
  "properties": {
    "iso:country":"GB",
    "wof:name":"IP29 4HS",
    "wof:placetype":"postalcode"
},
  "geometry": {"coordinates":[0.73166833380889,52.14213146385677],"type":"Point"}
}