{
  "type": "Feature",
  "properties": {
    "iso:country":"GB",
    "wof:name":"SR2 0EE",
    "wof:placetype":"postalcode"
},
  "geometry": {"coordinates":[-1.37519569593725,54.87792895817604],"type":"Point"}
}