{
  "type": "Feature",
  "properties": {
    "date:inception_lower": "1980-01-01",
    "date:inception_upper": "1980-01-01",
    "iso:country": "GB",
    "wof:name": "AL1 5LB",
    "wof:placetype": "postalcode"
  },
  "geometry": {"coordinates":[-0.30948,51.749494],"type":"Point"}
}
