{
  "type": "Feature",
  "properties": {
    "iso:country":"GB",
    "wof:name":"NN2 8DQ",
    "wof:placetype":"postalcode"
},
  "geometry": {"coordinates":[-0.91384901085292,52.27626118314165],"type":"Point"}
}