{
  "type": "Feature",
  "properties": {
    "iso:country": "GB",
    "wof:name": "WA14 5RH",
    "wof:placetype": "postalcode"
  },
  "geometry": {"coordinates":[-2.395335,53.404139],"type":"Point"}
}
