{
  "type": "Feature",
  "properties": {
    "iso:country":"GB",
    "wof:name":"NE65 0GE",
    "wof:placetype":"postalcode"
},
  "geometry": {"coordinates":[-1.59944938939389,55.32811575461211],"type":"Point"}
}