{
  "type": "Feature",
  "properties": {
    "date:inception_lower": "2000-12-01",
    "date:inception_upper": "2000-12-01",
    "iso:country": "GB",
    "wof:name": "NE65 0GE",
    "wof:placetype": "postalcode"
  },
  "geometry": {"coordinates":[-1.599449,55.328116],"type":"Point"}
}
