{
  "type": "Feature",
  "properties": {
    "iso:country": "GB",
    "wof:name": "SR2 9DG",
    "wof:placetype": "postalcode"
  },
  "geometry": {"coordinates":[-1.385715,54.884111],"type":"Point"}
}
