{
  "type": "Feature",
  "properties": {
    "iso:country":"GB",
    "wof:name":"SR2 9DG",
    "wof:placetype":"postalcode"
},
  "geometry": {"coordinates":[-1.3857152583928,54.8841113804701],"type":"Point"}
}