{
  "type": "Feature",
  "properties": {
    "iso:country": "GB",
    "wof:name": "TW10 6TH",
    "wof:placetype": "postalcode"
  },
  "geometry": {"coordinates":[-0.304348,51.458495],"type":"Point"}
}
