{
  "type": "Feature",
  "properties": {
    "iso:country":"GB",
    "wof:name":"EX14 4SU",
    "wof:placetype":"postalcode"
},
  "geometry": {"coordinates":[-3.18810656894856,50.8552259431677],"type":"Point"}
}