{
  "type": "Feature",
  "properties": {
    "date:inception_lower": "1999-12-01",
    "date:inception_upper": "1999-12-01",
    "iso:country": "GB",
    "wof:name": "EX14 4SU",
    "wof:placetype": "postalcode"
  },
  "geometry": {"coordinates":[-3.188107,50.855226],"type":"Point"}
}
