{
  "type": "Feature",
  "properties": {
    "iso:country":"GB",
    "wof:name":"OL11 4PB",
    "wof:placetype":"postalcode"
},
  "geometry": {"coordinates":[-2.17818758135899,53.60236134853664],"type":"Point"}
}