{
  "type": "Feature",
  "properties": {
    "iso:country": "GB",
    "wof:name": "LE4 4ND",
    "wof:placetype": "postalcode"
  },
  "geometry": {"coordinates":[-1.124763,52.680037],"type":"Point"}
}
