{
  "type": "Feature",
  "properties": {
    "iso:country":"GB",
    "wof:name":"L12 9JD",
    "wof:placetype":"postalcode"
},
  "geometry": {"coordinates":[-2.88781119208405,53.42664305854895],"type":"Point"}
}