{
  "type": "Feature",
  "properties": {
    "date:inception_lower":"1980-01-01",
    "date:inception_upper":"1980-01-31",
    "iso:country":"GB",
    "wof:name":"L12 9JD",
    "wof:placetype":"postalcode"
},
  "geometry": {"coordinates":[-2.887811,53.426643],"type":"Point"}
}