{
  "type": "Feature",
  "properties": {
    "date:inception_lower":"2001-12-01",
    "date:inception_upper":"2001-12-31",
    "iso:country":"GB",
    "wof:name":"PE7 8DH",
    "wof:placetype":"postalcode"
},
  "geometry": {"coordinates":[-0.273034,52.53633],"type":"Point"}
}