{
  "type": "Feature",
  "properties": {
    "iso:country":"GB",
    "wof:name":"PE7 8DH",
    "wof:placetype":"postalcode"
},
  "geometry": {"coordinates":[-0.27303411199895,52.53632972104275],"type":"Point"}
}