{
  "type": "Feature",
  "properties": {
    "iso:country":"GB",
    "wof:name":"N14 5DP",
    "wof:placetype":"postalcode"
},
  "geometry": {"coordinates":[-0.14753656054145,51.6313313581728],"type":"Point"}
}