{
  "type": "Feature",
  "properties": {
    "iso:country": "GB",
    "wof:name": "N14 5DP",
    "wof:placetype": "postalcode"
  },
  "geometry": {"coordinates":[-0.147483,51.631307],"type":"Point"}
}
