{
  "type": "Feature",
  "properties": {
    "date:inception_lower": "1980-01-01",
    "date:inception_upper": "1980-01-01",
    "iso:country": "GB",
    "wof:name": "B68 9EA",
    "wof:placetype": "postalcode"
  },
  "geometry": {"coordinates":[-1.996629,52.474901],"type":"Point"}
}
