{
  "type": "Feature",
  "properties": {
    "date:inception_lower": "1980-01-01",
    "date:inception_upper": "1980-01-01",
    "iso:country": "GB",
    "wof:name": "LU3 2ES",
    "wof:placetype": "postalcode"
  },
  "geometry": {"coordinates":[-0.435561,51.910259],"type":"Point"}
}
