{
  "type": "Feature",
  "properties": {
    "iso:country":"GB",
    "wof:name":"LU3 2ES",
    "wof:placetype":"postalcode"
},
  "geometry": {"coordinates":[-0.4355609774596,51.91025857073459],"type":"Point"}
}