{
  "type": "Feature",
  "properties": {
    "iso:country": "GB",
    "wof:name": "B37 6DQ",
    "wof:placetype": "postalcode"
  },
  "geometry": {"coordinates":[-1.75525,52.49448],"type":"Point"}
}
