{
  "type": "Feature",
  "properties": {
    "date:inception_lower":"1980-01-01",
    "date:inception_upper":"1980-01-31",
    "iso:country":"GB",
    "wof:name":"NR33 0LQ",
    "wof:placetype":"postalcode"
},
  "geometry": {"coordinates":[1.736231,52.461245],"type":"Point"}
}