{
  "type": "Feature",
  "properties": {
    "iso:country": "GB",
    "wof:name": "NR33 0LQ",
    "wof:placetype": "postalcode"
  },
  "geometry": {"coordinates":[1.736231,52.461245],"type":"Point"}
}
