{
  "type": "Feature",
  "properties": {
    "iso:country":"GB",
    "wof:name":"NR33 0LQ",
    "wof:placetype":"postalcode"
},
  "geometry": {"coordinates":[1.73623049450667,52.46124471492904],"type":"Point"}
}