{
  "type": "Feature",
  "properties": {
    "iso:country":"GB",
    "wof:name":"RG14 2SF",
    "wof:placetype":"postalcode"
},
  "geometry": {"coordinates":[-1.3009505769743,51.41113266852021],"type":"Point"}
}