{
  "type": "Feature",
  "properties": {
    "iso:country":"GB",
    "wof:name":"MK3 6PZ",
    "wof:placetype":"postalcode"
},
  "geometry": {"coordinates":[-0.74582318236496,52.00866939700358],"type":"Point"}
}