{
  "type": "Feature",
  "properties": {
    "iso:country": "GB",
    "wof:name": "MK3 6PZ",
    "wof:placetype": "postalcode"
  },
  "geometry": {"coordinates":[-0.745823,52.008669],"type":"Point"}
}
