{
  "type": "Feature",
  "properties": {
    "date:inception_lower":"1980-01-01",
    "date:inception_upper":"1980-01-31",
    "iso:country":"GB",
    "wof:name":"MK41 9RL",
    "wof:placetype":"postalcode"
},
  "geometry": {"coordinates":[-0.429827,52.140175],"type":"Point"}
}