{
  "type": "Feature",
  "properties": {
    "iso:country": "GB",
    "wof:name": "IV19 1AW",
    "wof:placetype": "postalcode"
  },
  "geometry": {"coordinates":[-4.056886,57.811267],"type":"Point"}
}
