{
  "type": "Feature",
  "properties": {
    "iso:country":"GB",
    "wof:name":"IV19 1AW",
    "wof:placetype":"postalcode"
},
  "geometry": {"coordinates":[-4.05688639768317,57.81126712738858],"type":"Point"}
}