{
  "type": "Feature",
  "properties": {
    "iso:country":"GB",
    "wof:name":"SA43 2EQ",
    "wof:placetype":"postalcode"
},
  "geometry": {"coordinates":[-4.54219615146992,52.13137673909969],"type":"Point"}
}