{
  "type": "Feature",
  "properties": {
    "iso:country":"GB",
    "wof:name":"HP9 2FE",
    "wof:placetype":"postalcode"
},
  "geometry": {"coordinates":[-0.63405697880549,51.60847878278888],"type":"Point"}
}