{
  "type": "Feature",
  "properties": {
    "iso:country":"GB",
    "wof:name":"WA10 1UF",
    "wof:placetype":"postalcode"
},
  "geometry": {"coordinates":[-2.73628697620833,53.45682394390036],"type":"Point"}
}