{
  "type": "Feature",
  "properties": {
    "iso:country":"GB",
    "wof:name":"CF32 9DR",
    "wof:placetype":"postalcode"
},
  "geometry": {"coordinates":[-3.59587920080782,51.54812930102767],"type":"Point"}
}