{
  "type": "Feature",
  "properties": {
    "iso:country": "GB",
    "wof:name": "WS14 9HH",
    "wof:placetype": "postalcode"
  },
  "geometry": {"coordinates":[-1.807639,52.673699],"type":"Point"}
}
