{
  "type": "Feature",
  "properties": {
    "iso:country":"GB",
    "wof:name":"WS14 9HH",
    "wof:placetype":"postalcode"
},
  "geometry": {"coordinates":[-1.80763922076415,52.67369881135268],"type":"Point"}
}