{
  "type": "Feature",
  "properties": {
    "date:inception_lower": "1980-01-01",
    "date:inception_upper": "1980-01-01",
    "iso:country": "GB",
    "wof:name": "DL10 5JN",
    "wof:placetype": "postalcode"
  },
  "geometry": {"coordinates":[-1.719364,54.442009],"type":"Point"}
}
