{
  "type": "Feature",
  "properties": {
    "iso:country":"GB",
    "wof:name":"BB4 8PW",
    "wof:placetype":"postalcode"
},
  "geometry": {"coordinates":[-2.28482630415143,53.72514923025316],"type":"Point"}
}