{
  "type": "Feature",
  "properties": {
    "date:inception_lower":"1980-01-01",
    "date:inception_upper":"1980-01-31",
    "iso:country":"GB",
    "wof:name":"BB4 8PW",
    "wof:placetype":"postalcode"
},
  "geometry": {"coordinates":[-2.284765,53.725173],"type":"Point"}
}