{
  "type": "Feature",
  "properties": {
    "iso:country":"GB",
    "wof:name":"ML4 2BQ",
    "wof:placetype":"postalcode"
},
  "geometry": {"coordinates":[-4.02897021891949,55.81127253148735],"type":"Point"}
}