{
  "type": "Feature",
  "properties": {
    "iso:country":"GB",
    "wof:name":"WS10 9NW",
    "wof:placetype":"postalcode"
},
  "geometry": {"coordinates":[-2.01805670004564,52.56184978917002],"type":"Point"}
}