{
  "type": "Feature",
  "properties": {
    "iso:country":"GB",
    "wof:name":"HR9 6BZ",
    "wof:placetype":"postalcode"
},
  "geometry": {"coordinates":[-2.64727711333716,51.85365052726226],"type":"Point"}
}