{
  "type": "Feature",
  "properties": {
    "iso:country":"GB",
    "wof:name":"M8 5BD",
    "wof:placetype":"postalcode"
},
  "geometry": {"coordinates":[-2.24138656784991,53.51536014204261],"type":"Point"}
}