{
  "type": "Feature",
  "properties": {
    "date:inception_lower":"1994-05-01",
    "date:inception_upper":"1994-05-31",
    "iso:country":"GB",
    "wof:name":"M8 5BD",
    "wof:placetype":"postalcode"
},
  "geometry": {"coordinates":[-2.241387,53.51536],"type":"Point"}
}