{
  "type": "Feature",
  "properties": {
    "iso:country":"GB",
    "wof:name":"LN2 2AR",
    "wof:placetype":"postalcode"
},
  "geometry": {"coordinates":[-0.53619344939916,53.25326938884783],"type":"Point"}
}