{
  "type": "Feature",
  "properties": {
    "iso:country":"GB",
    "wof:name":"NG3 6HQ",
    "wof:placetype":"postalcode"
},
  "geometry": {"coordinates":[-1.11720365617311,52.976713847815],"type":"Point"}
}