{
  "type": "Feature",
  "properties": {
    "date:inception_lower":"2005-12-01",
    "date:inception_upper":"2005-12-31",
    "iso:country":"GB",
    "wof:name":"DL9 3AD",
    "wof:placetype":"postalcode"
},
  "geometry": {"coordinates":[-1.745378,54.381728],"type":"Point"}
}