{
  "type": "Feature",
  "properties": {
    "iso:country":"GB",
    "wof:name":"SP5 1RB",
    "wof:placetype":"postalcode"
},
  "geometry": {"coordinates":[-1.66082264790713,51.09390061205465],"type":"Point"}
}