{
  "type": "Feature",
  "properties": {
    "date:inception_lower": "1980-01-01",
    "date:inception_upper": "1980-01-01",
    "iso:country": "GB",
    "wof:name": "SP5 1RB",
    "wof:placetype": "postalcode"
  },
  "geometry": {"coordinates":[-1.660823,51.093901],"type":"Point"}
}
