{
  "type": "Feature",
  "properties": {
    "iso:country": "GB",
    "wof:name": "BA2 7FA",
    "wof:placetype": "postalcode"
  },
  "geometry": {"coordinates":[-2.306556,51.347274],"type":"Point"}
}
