{
  "type": "Feature",
  "properties": {
    "iso:country":"GB",
    "wof:name":"BA2 7FA",
    "wof:placetype":"postalcode"
},
  "geometry": {"coordinates":[-2.30655638834315,51.34727371315438],"type":"Point"}
}