{
  "type": "Feature",
  "properties": {
    "iso:country":"GB",
    "wof:name":"CA28 6QD",
    "wof:placetype":"postalcode"
},
  "geometry": {"coordinates":[-3.5697383218997,54.58119777687343],"type":"Point"}
}