{
  "type": "Feature",
  "properties": {
    "iso:country":"GB",
    "wof:name":"DA17 6EN",
    "wof:placetype":"postalcode"
},
  "geometry": {"coordinates":[0.15200380410265,51.48826373213579],"type":"Point"}
}