{
  "type": "Feature",
  "properties": {
    "iso:country": "GB",
    "wof:name": "DG12 5PR",
    "wof:placetype": "postalcode"
  },
  "geometry": {"coordinates":[-3.330743,54.980896],"type":"Point"}
}
