{
  "type": "Feature",
  "properties": {
    "iso:country":"GB",
    "wof:name":"TS20 2JW",
    "wof:placetype":"postalcode"
},
  "geometry": {"coordinates":[-1.31557746641596,54.58415390367922],"type":"Point"}
}