{
  "type": "Feature",
  "properties": {
    "iso:country":"GB",
    "wof:name":"MK46 5ND",
    "wof:placetype":"postalcode"
},
  "geometry": {"coordinates":[-0.71178883080397,52.13742385847016],"type":"Point"}
}