{
  "type": "Feature",
  "properties": {
    "date:inception_lower":"1986-04-01",
    "date:inception_upper":"1986-04-30",
    "iso:country":"GB",
    "wof:name":"MK46 5ND",
    "wof:placetype":"postalcode"
},
  "geometry": {"coordinates":[-0.711789,52.137424],"type":"Point"}
}