{
  "type": "Feature",
  "properties": {
    "iso:country": "GB",
    "wof:name": "MK46 5ND",
    "wof:placetype": "postalcode"
  },
  "geometry": {"coordinates":[-0.711789,52.137424],"type":"Point"}
}
