{
  "type": "Feature",
  "properties": {
    "iso:country": "GB",
    "wof:name": "SA31 3HG",
    "wof:placetype": "postalcode"
  },
  "geometry": {"coordinates":[-4.326491,51.854124],"type":"Point"}
}
