{
  "type": "Feature",
  "properties": {
    "iso:country":"GB",
    "wof:name":"WA9 3UA",
    "wof:placetype":"postalcode"
},
  "geometry": {"coordinates":[-2.72295749319882,53.42838422693942],"type":"Point"}
}