{
  "type": "Feature",
  "properties": {
    "iso:country": "GB",
    "wof:name": "KY2 5DL",
    "wof:placetype": "postalcode"
  },
  "geometry": {"coordinates":[-3.168044,56.125417],"type":"Point"}
}
