{
  "type": "Feature",
  "properties": {
    "iso:country": "GB",
    "wof:name": "SN13 9GL",
    "wof:placetype": "postalcode"
  },
  "geometry": {"coordinates":[-2.214175,51.412631],"type":"Point"}
}
