{
  "type": "Feature",
  "properties": {
    "iso:country":"GB",
    "wof:name":"ML3 8BP",
    "wof:placetype":"postalcode"
},
  "geometry": {"coordinates":[-4.07619766853242,55.76337331410114],"type":"Point"}
}