{
  "type": "Feature",
  "properties": {
    "iso:country":"GB",
    "wof:name":"SW12 0PE",
    "wof:placetype":"postalcode"
},
  "geometry": {"coordinates":[-0.14302082482785,51.44197748836698],"type":"Point"}
}