{
  "type": "Feature",
  "properties": {
    "iso:country":"GB",
    "wof:name":"CA7 4BU",
    "wof:placetype":"postalcode"
},
  "geometry": {"coordinates":[-3.38728274801033,54.86947053753953],"type":"Point"}
}