{
  "type": "Feature",
  "properties": {
    "date:inception_lower":"2004-05-01",
    "date:inception_upper":"2004-05-31",
    "iso:country":"GB",
    "wof:name":"WR7 4BP",
    "wof:placetype":"postalcode"
},
  "geometry": {"coordinates":[-2.114698,52.190243],"type":"Point"}
}