{
  "type": "Feature",
  "properties": {
    "iso:country": "GB",
    "wof:name": "WR7 4BP",
    "wof:placetype": "postalcode"
  },
  "geometry": {"coordinates":[-2.114698,52.190243],"type":"Point"}
}
