{
  "type": "Feature",
  "properties": {
    "iso:country":"GB",
    "wof:name":"BH15 4AE",
    "wof:placetype":"postalcode"
},
  "geometry": {"coordinates":[-1.98894323669027,50.71064112922986],"type":"Point"}
}