{
  "type": "Feature",
  "properties": {
    "date:inception_lower":"1980-01-01",
    "date:inception_upper":"1980-01-31",
    "iso:country":"GB",
    "wof:name":"BS1 5QB",
    "wof:placetype":"postalcode"
},
  "geometry": {"coordinates":[-2.604661,51.453826],"type":"Point"}
}