{
  "type": "Feature",
  "properties": {
    "iso:country":"GB",
    "wof:name":"EH8 9HX",
    "wof:placetype":"postalcode"
},
  "geometry": {"coordinates":[-3.18240695956115,55.94269812553272],"type":"Point"}
}