{
  "type": "Feature",
  "properties": {
    "iso:country": "GB",
    "wof:name": "WN2 1HU",
    "wof:placetype": "postalcode"
  },
  "geometry": {"coordinates":[-2.602672,53.556573],"type":"Point"}
}
