{
  "type": "Feature",
  "properties": {
    "iso:country":"GB",
    "wof:name":"WN2 1HU",
    "wof:placetype":"postalcode"
},
  "geometry": {"coordinates":[-2.60267184932955,53.55657268452088],"type":"Point"}
}