{
  "type": "Feature",
  "properties": {
    "date:inception_lower":"1996-12-01",
    "date:inception_upper":"1996-12-31",
    "iso:country":"GB",
    "wof:name":"WN2 1HU",
    "wof:placetype":"postalcode"
},
  "geometry": {"coordinates":[-2.602672,53.556573],"type":"Point"}
}