{
  "type": "Feature",
  "properties": {
    "iso:country":"GB",
    "wof:name":"B16 8SW",
    "wof:placetype":"postalcode"
},
  "geometry": {"coordinates":[-1.92389785064632,52.47631499042689],"type":"Point"}
}