{
  "type": "Feature",
  "properties": {
    "date:inception_lower": "1998-06-01",
    "date:inception_upper": "1998-06-01",
    "iso:country": "GB",
    "wof:name": "B16 8SW",
    "wof:placetype": "postalcode"
  },
  "geometry": {"coordinates":[-1.923898,52.476315],"type":"Point"}
}
