{
  "type": "Feature",
  "properties": {
    "date:inception_lower":"1980-01-01",
    "date:inception_upper":"1980-01-31",
    "iso:country":"GB",
    "wof:name":"WA2 9NZ",
    "wof:placetype":"postalcode"
},
  "geometry": {"coordinates":[-2.585803,53.408453],"type":"Point"}
}