{
  "type": "Feature",
  "properties": {
    "iso:country":"GB",
    "wof:name":"CA15 7RL",
    "wof:placetype":"postalcode"
},
  "geometry": {"coordinates":[-3.45885114170579,54.69655802442878],"type":"Point"}
}