{
  "type": "Feature",
  "properties": {
    "iso:country":"GB",
    "wof:name":"DE12 7BS",
    "wof:placetype":"postalcode"
},
  "geometry": {"coordinates":[-1.49495622526335,52.68094234993699],"type":"Point"}
}