{
  "type": "Feature",
  "properties": {
    "date:inception_lower":"1993-08-01",
    "date:inception_upper":"1993-08-31",
    "iso:country":"GB",
    "wof:name":"DE12 7BS",
    "wof:placetype":"postalcode"
},
  "geometry": {"coordinates":[-1.494956,52.680942],"type":"Point"}
}