{
  "type": "Feature",
  "properties": {
    "date:inception_lower":"1997-12-01",
    "date:inception_upper":"1997-12-31",
    "iso:country":"GB",
    "wof:name":"CT18 7FY",
    "wof:placetype":"postalcode"
},
  "geometry": {"coordinates":[1.166873,51.112397],"type":"Point"}
}