{
  "type": "Feature",
  "properties": {
    "iso:country":"GB",
    "wof:name":"LS12 5JJ",
    "wof:placetype":"postalcode"
},
  "geometry": {"coordinates":[-1.61073143041086,53.78489734579247],"type":"Point"}
}