{
  "type": "Feature",
  "properties": {
    "iso:country":"GB",
    "wof:name":"CO7 8EH",
    "wof:placetype":"postalcode"
},
  "geometry": {"coordinates":[1.00139751630873,51.85503123272357],"type":"Point"}
}