{
  "type": "Feature",
  "properties": {
    "iso:country":"GB",
    "wof:name":"BS16 6RD",
    "wof:placetype":"postalcode"
},
  "geometry": {"coordinates":[-2.49093986713654,51.49431574762087],"type":"Point"}
}