{
  "type": "Feature",
  "properties": {
    "iso:country": "GB",
    "wof:name": "BS16 6RD",
    "wof:placetype": "postalcode"
  },
  "geometry": {"coordinates":[-2.490969,51.494377],"type":"Point"}
}
