{
  "type": "Feature",
  "properties": {
    "date:inception_lower": "1980-01-01",
    "date:inception_upper": "1980-01-01",
    "iso:country": "GB",
    "wof:name": "TQ13 7JH",
    "wof:placetype": "postalcode"
  },
  "geometry": {"coordinates":[-3.762432,50.506522],"type":"Point"}
}
