{
  "type": "Feature",
  "properties": {
    "iso:country":"GB",
    "wof:name":"CT4 6BE",
    "wof:placetype":"postalcode"
},
  "geometry": {"coordinates":[1.06557601135643,51.18211878473016],"type":"Point"}
}