{
  "type": "Feature",
  "properties": {
    "date:inception_lower": "1980-01-01",
    "date:inception_upper": "1980-01-01",
    "iso:country": "GB",
    "wof:name": "SP5 2JU",
    "wof:placetype": "postalcode"
  },
  "geometry": {"coordinates":[-1.698573,50.991989],"type":"Point"}
}
