{
  "type": "Feature",
  "properties": {
    "iso:country":"GB",
    "wof:name":"SP5 2JU",
    "wof:placetype":"postalcode"
},
  "geometry": {"coordinates":[-1.69858261136347,50.99199649182214],"type":"Point"}
}