{
  "type": "Feature",
  "properties": {
    "iso:country":"GB",
    "wof:name":"SE3 8UN",
    "wof:placetype":"postalcode"
},
  "geometry": {"coordinates":[0.03516196624488,51.47486445104015],"type":"Point"}
}