{
  "type": "Feature",
  "properties": {
    "date:inception_lower": "1980-01-01",
    "date:inception_upper": "1980-01-01",
    "iso:country": "GB",
    "wof:name": "SE3 8UN",
    "wof:placetype": "postalcode"
  },
  "geometry": {"coordinates":[0.035162,51.474864],"type":"Point"}
}
