{
  "type": "Feature",
  "properties": {
    "iso:country": "GB",
    "wof:name": "SE3 8UN",
    "wof:placetype": "postalcode"
  },
  "geometry": {"coordinates":[0.035162,51.474864],"type":"Point"}
}
