{
  "type": "Feature",
  "properties": {
    "iso:country": "GB",
    "wof:name": "TN21 0FX",
    "wof:placetype": "postalcode"
  },
  "geometry": {"coordinates":[0.218331,50.973217],"type":"Point"}
}
