{
  "type": "Feature",
  "properties": {
    "iso:country":"GB",
    "wof:name":"PO7 8NR",
    "wof:placetype":"postalcode"
},
  "geometry": {"coordinates":[-1.01600372459085,50.88087113811805],"type":"Point"}
}