{
  "type": "Feature",
  "properties": {
    "iso:country": "GB",
    "wof:name": "NE9 5BA",
    "wof:placetype": "postalcode"
  },
  "geometry": {"coordinates":[-1.597204,54.94693],"type":"Point"}
}
