{
  "type": "Feature",
  "properties": {
    "iso:country":"GB",
    "wof:name":"NE10 9UP",
    "wof:placetype":"postalcode"
},
  "geometry": {"coordinates":[-1.56269853849636,54.94725131336133],"type":"Point"}
}