{
  "type": "Feature",
  "properties": {
    "date:inception_lower":"2008-01-01",
    "date:inception_upper":"2008-01-31",
    "iso:country":"GB",
    "wof:name":"KY2 6FJ",
    "wof:placetype":"postalcode"
},
  "geometry": {"coordinates":[-3.186524,56.13782],"type":"Point"}
}