{
  "type": "Feature",
  "properties": {
    "date:inception_lower": "1980-01-01",
    "date:inception_upper": "1980-01-01",
    "iso:country": "GB",
    "wof:name": "TS16 9BD",
    "wof:placetype": "postalcode"
  },
  "geometry": {"coordinates":[-1.344315,54.531634],"type":"Point"}
}
