{
  "type": "Feature",
  "properties": {
    "iso:country":"GB",
    "wof:name":"TS16 9BD",
    "wof:placetype":"postalcode"
},
  "geometry": {"coordinates":[-1.34385718611545,54.53145786747426],"type":"Point"}
}