{
  "type": "Feature",
  "properties": {
    "iso:country":"GB",
    "wof:name":"TS12 1NT",
    "wof:placetype":"postalcode"
},
  "geometry": {"coordinates":[-0.99043730113841,54.5804952344417],"type":"Point"}
}