{
  "type": "Feature",
  "properties": {
    "date:inception_lower": "1980-01-01",
    "date:inception_upper": "1980-01-01",
    "iso:country": "GB",
    "wof:name": "TS12 1NT",
    "wof:placetype": "postalcode"
  },
  "geometry": {"coordinates":[-0.990437,54.580495],"type":"Point"}
}
