{
  "type": "Feature",
  "properties": {
    "date:inception_lower": "1998-06-01",
    "date:inception_upper": "1998-06-01",
    "iso:country": "GB",
    "wof:name": "SO18 2XX",
    "wof:placetype": "postalcode"
  },
  "geometry": {"coordinates":[-1.362365,50.948409],"type":"Point"}
}
