{
  "type": "Feature",
  "properties": {
    "iso:country": "GB",
    "wof:name": "EN8 7NB",
    "wof:placetype": "postalcode"
  },
  "geometry": {"coordinates":[-0.023447,51.685735],"type":"Point"}
}
