{
  "type": "Feature",
  "properties": {
    "iso:country":"GB",
    "wof:name":"EN8 7NB",
    "wof:placetype":"postalcode"
},
  "geometry": {"coordinates":[-0.02344752357448,51.68573536607266],"type":"Point"}
}