{
  "type": "Feature",
  "properties": {
    "iso:country":"GB",
    "wof:name":"TA20 4JQ",
    "wof:placetype":"postalcode"
},
  "geometry": {"coordinates":[-2.88438555731383,50.84835526420341],"type":"Point"}
}