{
  "type": "Feature",
  "properties": {
    "date:inception_lower": "1980-01-01",
    "date:inception_upper": "1980-01-01",
    "iso:country": "GB",
    "wof:name": "SK9 7SR",
    "wof:placetype": "postalcode"
  },
  "geometry": {"coordinates":[-2.268952,53.305578],"type":"Point"}
}
