{
  "type": "Feature",
  "properties": {
    "iso:country":"GB",
    "wof:name":"SK9 7SR",
    "wof:placetype":"postalcode"
},
  "geometry": {"coordinates":[-2.26908817425441,53.30557064646597],"type":"Point"}
}