{
  "type": "Feature",
  "properties": {
    "iso:country":"GB",
    "wof:name":"IP9 2AR",
    "wof:placetype":"postalcode"
},
  "geometry": {"coordinates":[1.12537832690754,52.01847691893656],"type":"Point"}
}