{
  "type": "Feature",
  "properties": {
    "iso:country": "GB",
    "wof:name": "IP9 2AR",
    "wof:placetype": "postalcode"
  },
  "geometry": {"coordinates":[1.125378,52.018477],"type":"Point"}
}
