{
  "type": "Feature",
  "properties": {
    "iso:country":"GB",
    "wof:name":"HA0 1PA",
    "wof:placetype":"postalcode"
},
  "geometry": {"coordinates":[-0.2873251845865,51.54134620194222],"type":"Point"}
}