{
  "type": "Feature",
  "properties": {
    "iso:country":"GB",
    "wof:name":"SG9 0QT",
    "wof:placetype":"postalcode"
},
  "geometry": {"coordinates":[-0.08130753500587,51.99218440752097],"type":"Point"}
}