{
  "type": "Feature",
  "properties": {
    "iso:country":"GB",
    "wof:name":"HA6 3DZ",
    "wof:placetype":"postalcode"
},
  "geometry": {"coordinates":[-0.42382353400993,51.6220481682207],"type":"Point"}
}