{
  "type": "Feature",
  "properties": {
    "iso:country":"GB",
    "wof:name":"CM2 0TU",
    "wof:placetype":"postalcode"
},
  "geometry": {"coordinates":[0.47299886293364,51.7253962572492],"type":"Point"}
}