{
  "type": "Feature",
  "properties": {
    "date:inception_lower":"1980-01-01",
    "date:inception_upper":"1980-01-31",
    "iso:country":"GB",
    "wof:name":"BS22 8RQ",
    "wof:placetype":"postalcode"
},
  "geometry": {"coordinates":[-2.93238,51.353539],"type":"Point"}
}