{
  "type": "Feature",
  "properties": {
    "iso:country":"GB",
    "wof:name":"SY3 6AJ",
    "wof:placetype":"postalcode"
},
  "geometry": {"coordinates":[-2.77143224374231,52.69684664292583],"type":"Point"}
}