{
  "type": "Feature",
  "properties": {
    "date:inception_lower": "2006-05-01",
    "date:inception_upper": "2006-05-01",
    "iso:country": "GB",
    "wof:name": "NE63 9GZ",
    "wof:placetype": "postalcode"
  },
  "geometry": {"coordinates":[-1.558955,55.184903],"type":"Point"}
}
