{
  "type": "Feature",
  "properties": {
    "iso:country": "GB",
    "wof:name": "DN14 5LZ",
    "wof:placetype": "postalcode"
  },
  "geometry": {"coordinates":[-0.848271,53.714041],"type":"Point"}
}
