{
  "type": "Feature",
  "properties": {
    "iso:country":"GB",
    "wof:name":"LA14 5SD",
    "wof:placetype":"postalcode"
},
  "geometry": {"coordinates":[-3.23123943485425,54.11878451466392],"type":"Point"}
}