{
  "type": "Feature",
  "properties": {
    "date:inception_lower": "1980-01-01",
    "date:inception_upper": "1980-01-01",
    "iso:country": "GB",
    "wof:name": "S2 4BJ",
    "wof:placetype": "postalcode"
  },
  "geometry": {"coordinates":[-1.466968,53.373242],"type":"Point"}
}
