{
  "type": "Feature",
  "properties": {
    "iso:country":"GB",
    "wof:name":"SK11 0HD",
    "wof:placetype":"postalcode"
},
  "geometry": {"coordinates":[-2.11417390997255,53.24328508727896],"type":"Point"}
}