{
  "type": "Feature",
  "properties": {
    "iso:country":"GB",
    "wof:name":"TN30 7AE",
    "wof:placetype":"postalcode"
},
  "geometry": {"coordinates":[0.69980262930548,51.07372748739785],"type":"Point"}
}