{
  "type": "Feature",
  "properties": {
    "iso:country":"GB",
    "wof:name":"HP17 8QG",
    "wof:placetype":"postalcode"
},
  "geometry": {"coordinates":[-0.8381334491177,51.80483058796757],"type":"Point"}
}