{
  "type": "Feature",
  "properties": {
    "iso:country": "GB",
    "wof:name": "TW16 6NX",
    "wof:placetype": "postalcode"
  },
  "geometry": {"coordinates":[-0.415618,51.415603],"type":"Point"}
}
