{
  "type": "Feature",
  "properties": {
    "iso:country":"GB",
    "wof:name":"TW16 6NX",
    "wof:placetype":"postalcode"
},
  "geometry": {"coordinates":[-0.4156184045121,51.41560254714831],"type":"Point"}
}