{
  "type": "Feature",
  "properties": {
    "iso:country":"GB",
    "wof:name":"WA8 9GN",
    "wof:placetype":"postalcode"
},
  "geometry": {"coordinates":[-2.74163633812099,53.38092583145338],"type":"Point"}
}