{
  "type": "Feature",
  "properties": {
    "iso:country":"GB",
    "wof:name":"TF6 6PU",
    "wof:placetype":"postalcode"
},
  "geometry": {"coordinates":[-2.54610596385079,52.79323675222849],"type":"Point"}
}