{
  "type": "Feature",
  "properties": {
    "date:inception_lower":"1980-01-01",
    "date:inception_upper":"1980-01-31",
    "iso:country":"GB",
    "wof:name":"TF6 6PU",
    "wof:placetype":"postalcode"
},
  "geometry": {"coordinates":[-2.546106,52.793237],"type":"Point"}
}