{
  "type": "Feature",
  "properties": {
    "iso:country":"GB",
    "wof:name":"ME10 1QL",
    "wof:placetype":"postalcode"
},
  "geometry": {"coordinates":[0.72675353707761,51.33271642134707],"type":"Point"}
}