{
  "type": "Feature",
  "properties": {
    "date:inception_lower":"1980-01-01",
    "date:inception_upper":"1980-01-31",
    "iso:country":"GB",
    "wof:name":"PL17 8HQ",
    "wof:placetype":"postalcode"
},
  "geometry": {"coordinates":[-4.305215,50.526103],"type":"Point"}
}