{
  "type": "Feature",
  "properties": {
    "iso:country":"GB",
    "wof:name":"NN6 0LW",
    "wof:placetype":"postalcode"
},
  "geometry": {"coordinates":[-0.74918294253513,52.26868008168035],"type":"Point"}
}