{
  "type": "Feature",
  "properties": {
    "iso:country":"GB",
    "wof:name":"PR25 1DB",
    "wof:placetype":"postalcode"
},
  "geometry": {"coordinates":[-2.72162667187879,53.68694727315749],"type":"Point"}
}