{
  "type": "Feature",
  "properties": {
    "date:inception_lower": "1980-01-01",
    "date:inception_upper": "1980-01-01",
    "iso:country": "GB",
    "wof:name": "WA8 8NL",
    "wof:placetype": "postalcode"
  },
  "geometry": {"coordinates":[-2.790393,53.354291],"type":"Point"}
}
