{
  "type": "Feature",
  "properties": {
    "iso:country":"GB",
    "wof:name":"WA8 8NL",
    "wof:placetype":"postalcode"
},
  "geometry": {"coordinates":[-2.7903017389804,53.35425817071324],"type":"Point"}
}