{
  "type": "Feature",
  "properties": {
    "iso:country":"GB",
    "wof:name":"PO5 2PD",
    "wof:placetype":"postalcode"
},
  "geometry": {"coordinates":[-1.0809682062848,50.78163520492421],"type":"Point"}
}