{
  "type": "Feature",
  "properties": {
    "date:inception_lower": "1996-12-01",
    "date:inception_upper": "1996-12-01",
    "iso:country": "GB",
    "wof:name": "NN16 9XN",
    "wof:placetype": "postalcode"
  },
  "geometry": {"coordinates":[-0.716779,52.418846],"type":"Point"}
}
