{
  "type": "Feature",
  "properties": {
    "iso:country":"GB",
    "wof:name":"ST5 5ER",
    "wof:placetype":"postalcode"
},
  "geometry": {"coordinates":[-2.33650113872815,52.96381727139228],"type":"Point"}
}