{
  "type": "Feature",
  "properties": {
    "iso:country": "GB",
    "wof:name": "ST5 5ER",
    "wof:placetype": "postalcode"
  },
  "geometry": {"coordinates":[-2.336501,52.963833],"type":"Point"}
}
