{
  "type": "Feature",
  "properties": {
    "iso:country":"GB",
    "wof:name":"SN7 7TW",
    "wof:placetype":"postalcode"
},
  "geometry": {"coordinates":[-1.61046849335605,51.6129176447152],"type":"Point"}
}