{
  "type": "Feature",
  "properties": {
    "date:inception_lower":"1980-01-01",
    "date:inception_upper":"1980-01-31",
    "iso:country":"GB",
    "wof:name":"SN12 6NH",
    "wof:placetype":"postalcode"
},
  "geometry": {"coordinates":[-2.093066,51.348448],"type":"Point"}
}