{
  "type": "Feature",
  "properties": {
    "iso:country": "GB",
    "wof:name": "DD8 5AF",
    "wof:placetype": "postalcode"
  },
  "geometry": {"coordinates":[-3.015007,56.673664],"type":"Point"}
}
