{
  "type": "Feature",
  "properties": {
    "iso:country":"GB",
    "wof:name":"DD8 5AF",
    "wof:placetype":"postalcode"
},
  "geometry": {"coordinates":[-3.01500687224862,56.67366441326686],"type":"Point"}
}