{
  "type": "Feature",
  "properties": {
    "iso:country":"GB",
    "wof:name":"IP18 6HA",
    "wof:placetype":"postalcode"
},
  "geometry": {"coordinates":[1.68047465052288,52.32421367920554],"type":"Point"}
}