{
  "type": "Feature",
  "properties": {
    "date:inception_lower": "2005-08-01",
    "date:inception_upper": "2005-08-01",
    "iso:country": "GB",
    "wof:name": "BS3 4AQ",
    "wof:placetype": "postalcode"
  },
  "geometry": {"coordinates":[-2.593686,51.44416],"type":"Point"}
}
