{
  "type": "Feature",
  "properties": {
    "iso:country": "GB",
    "wof:name": "BS3 4AQ",
    "wof:placetype": "postalcode"
  },
  "geometry": {"coordinates":[-2.593413,51.444388],"type":"Point"}
}
