{
  "type": "Feature",
  "properties": {
    "date:inception_lower":"1980-01-01",
    "date:inception_upper":"1980-01-31",
    "iso:country":"GB",
    "wof:name":"MK45 2SJ",
    "wof:placetype":"postalcode"
},
  "geometry": {"coordinates":[-0.487727,52.025213],"type":"Point"}
}