{
  "type": "Feature",
  "properties": {
    "iso:country": "GB",
    "wof:name": "MK45 2SJ",
    "wof:placetype": "postalcode"
  },
  "geometry": {"coordinates":[-0.487727,52.025213],"type":"Point"}
}
