{
  "type": "Feature",
  "properties": {
    "iso:country":"GB",
    "wof:name":"EH6 7EE",
    "wof:placetype":"postalcode"
},
  "geometry": {"coordinates":[-3.17040514012704,55.97050586576476],"type":"Point"}
}