{
  "type": "Feature",
  "properties": {
    "date:inception_lower": "1980-01-01",
    "date:inception_upper": "1980-01-01",
    "iso:country": "GB",
    "wof:name": "TW13 4JE",
    "wof:placetype": "postalcode"
  },
  "geometry": {"coordinates":[-0.415939,51.441694],"type":"Point"}
}
