{
  "type": "Feature",
  "properties": {
    "iso:country":"GB",
    "wof:name":"TW13 4JE",
    "wof:placetype":"postalcode"
},
  "geometry": {"coordinates":[-0.41593878530297,51.44169364204283],"type":"Point"}
}