{
  "type": "Feature",
  "properties": {
    "iso:country": "GB",
    "wof:name": "BL0 9UF",
    "wof:placetype": "postalcode"
  },
  "geometry": {"coordinates":[-2.324938,53.628154],"type":"Point"}
}
