{
  "type": "Feature",
  "properties": {
    "iso:country":"GB",
    "wof:name":"BL0 9UF",
    "wof:placetype":"postalcode"
},
  "geometry": {"coordinates":[-2.32493787444153,53.62815449686986],"type":"Point"}
}