{
  "type": "Feature",
  "properties": {
    "iso:country": "GB",
    "wof:name": "CO16 8PA",
    "wof:placetype": "postalcode"
  },
  "geometry": {"coordinates":[1.07871,51.799484],"type":"Point"}
}
