{
  "type": "Feature",
  "properties": {
    "iso:country":"GB",
    "wof:name":"CO16 8PA",
    "wof:placetype":"postalcode"
},
  "geometry": {"coordinates":[1.07876644758957,51.79949788465569],"type":"Point"}
}