{
  "type": "Feature",
  "properties": {
    "date:inception_lower": "2024-04-01",
    "date:inception_upper": "2024-04-01",
    "iso:country": "GB",
    "wof:name": "G11 6FF",
    "wof:placetype": "postalcode"
  },
  "geometry": {"coordinates":[-4.322206,55.869413],"type":"Point"}
}
