{
  "type": "Feature",
  "properties": {
    "iso:country":"GB",
    "wof:name":"B65 8LD",
    "wof:placetype":"postalcode"
},
  "geometry": {"coordinates":[-2.0589592709518,52.49363912026384],"type":"Point"}
}