{
  "type": "Feature",
  "properties": {
    "iso:country":"GB",
    "wof:name":"PE29 1PQ",
    "wof:placetype":"postalcode"
},
  "geometry": {"coordinates":[-0.16769180218561,52.34178568589099],"type":"Point"}
}