{
  "type": "Feature",
  "properties": {
    "iso:country":"GB",
    "wof:name":"TN21 8SX",
    "wof:placetype":"postalcode"
},
  "geometry": {"coordinates":[0.28355332443392,50.977170742946],"type":"Point"}
}