{
  "type": "Feature",
  "properties": {
    "iso:country":"GB",
    "wof:name":"DL10 4ED",
    "wof:placetype":"postalcode"
},
  "geometry": {"coordinates":[-1.74360084419192,54.40396575667463],"type":"Point"}
}