{
  "type": "Feature",
  "properties": {
    "iso:country":"GB",
    "wof:name":"IP26 5LS",
    "wof:placetype":"postalcode"
},
  "geometry": {"coordinates":[0.58706102841803,52.53598265551324],"type":"Point"}
}