{
  "type": "Feature",
  "properties": {
    "iso:country": "GB",
    "wof:name": "CF31 1DD",
    "wof:placetype": "postalcode"
  },
  "geometry": {"coordinates":[-3.57543,51.503886],"type":"Point"}
}
