{
  "type": "Feature",
  "properties": {
    "iso:country":"GB",
    "wof:name":"BS8 3JJ",
    "wof:placetype":"postalcode"
},
  "geometry": {"coordinates":[-2.62210853051522,51.46160199904249],"type":"Point"}
}