{
  "type": "Feature",
  "properties": {
    "date:inception_lower": "1990-08-01",
    "date:inception_upper": "1990-08-01",
    "iso:country": "GB",
    "wof:name": "AB30 1EX",
    "wof:placetype": "postalcode"
  },
  "geometry": {"coordinates":[-2.539778,56.866071],"type":"Point"}
}
