{
  "type": "Feature",
  "properties": {
    "iso:country":"GB",
    "wof:name":"NE6 2LU",
    "wof:placetype":"postalcode"
},
  "geometry": {"coordinates":[-1.55837793370414,54.96684383259289],"type":"Point"}
}