{
  "type": "Feature",
  "properties": {
    "iso:country": "GB",
    "wof:name": "NE6 2LU",
    "wof:placetype": "postalcode"
  },
  "geometry": {"coordinates":[-1.558378,54.966844],"type":"Point"}
}
