{
  "type": "Feature",
  "properties": {
    "iso:country": "GB",
    "wof:name": "CM22 6NH",
    "wof:placetype": "postalcode"
  },
  "geometry": {"coordinates":[0.229402,51.856437],"type":"Point"}
}
