{
  "type": "Feature",
  "properties": {
    "iso:country":"GB",
    "wof:name":"MK6 2BH",
    "wof:placetype":"postalcode"
},
  "geometry": {"coordinates":[-0.74399512787244,52.03909405537151],"type":"Point"}
}