{
  "type": "Feature",
  "properties": {
    "date:inception_lower":"1980-01-01",
    "date:inception_upper":"1980-01-31",
    "iso:country":"GB",
    "wof:name":"SN14 0RN",
    "wof:placetype":"postalcode"
},
  "geometry": {"coordinates":[-2.137082,51.448255],"type":"Point"}
}