{
  "type": "Feature",
  "properties": {
    "iso:country": "GB",
    "wof:name": "SN14 0RN",
    "wof:placetype": "postalcode"
  },
  "geometry": {"coordinates":[-2.138155,51.446222],"type":"Point"}
}
