{
  "type": "Feature",
  "properties": {
    "iso:country": "GB",
    "wof:name": "SN14 0RN",
    "wof:placetype": "postalcode"
  },
  "geometry": {"coordinates":[-2.137082,51.448255],"type":"Point"}
}
