{
  "type": "Feature",
  "properties": {
    "iso:country":"GB",
    "wof:name":"CV1 5BS",
    "wof:placetype":"postalcode"
},
  "geometry": {"coordinates":[-1.49479270831123,52.41374249578018],"type":"Point"}
}