{
  "type": "Feature",
  "properties": {
    "date:inception_lower": "2016-04-01",
    "date:inception_upper": "2016-04-01",
    "iso:country": "GB",
    "wof:name": "CF64 1TF",
    "wof:placetype": "postalcode"
  },
  "geometry": {"coordinates":[-3.184133,51.444072],"type":"Point"}
}
