{
  "type": "Feature",
  "properties": {
    "date:inception_lower": "2018-11-01",
    "date:inception_upper": "2018-11-01",
    "iso:country": "GB",
    "wof:name": "WV2 2HY",
    "wof:placetype": "postalcode"
  },
  "geometry": {"coordinates":[-2.112585,52.576232],"type":"Point"}
}
