{
  "type": "Feature",
  "properties": {
    "iso:country":"GB",
    "wof:name":"LE2 8SB",
    "wof:placetype":"postalcode"
},
  "geometry": {"coordinates":[-1.1491976893797,52.59784016311782],"type":"Point"}
}