{
  "type": "Feature",
  "properties": {
    "iso:country":"GB",
    "wof:name":"UB3 2JT",
    "wof:placetype":"postalcode"
},
  "geometry": {"coordinates":[-0.41829197413057,51.51681978405364],"type":"Point"}
}