{
  "type": "Feature",
  "properties": {
    "date:inception_lower": "2001-06-01",
    "date:inception_upper": "2001-06-01",
    "iso:country": "GB",
    "wof:name": "OX28 5NP",
    "wof:placetype": "postalcode"
  },
  "geometry": {"coordinates":[-1.50444,51.7782],"type":"Point"}
}
