{
  "type": "Feature",
  "properties": {
    "iso:country": "GB",
    "wof:name": "LN6 9ZR",
    "wof:placetype": "postalcode"
  },
  "geometry": {"coordinates":[-0.604694,53.192462],"type":"Point"}
}
