{
  "type": "Feature",
  "properties": {
    "iso:country":"GB",
    "wof:name":"LN6 9ZR",
    "wof:placetype":"postalcode"
},
  "geometry": {"coordinates":[-0.69288342320615,53.14878011626022],"type":"Point"}
}