{
  "type": "Feature",
  "properties": {
    "date:inception_lower":"2016-01-01",
    "date:inception_upper":"2016-01-31",
    "iso:country":"GB",
    "wof:name":"LN6 9ZR",
    "wof:placetype":"postalcode"
},
  "geometry": {"coordinates":[-0.604694,53.192462],"type":"Point"}
}