{
  "type": "Feature",
  "properties": {
    "iso:country": "GB",
    "wof:name": "NE48 2EB",
    "wof:placetype": "postalcode"
  },
  "geometry": {"coordinates":[-2.195169,55.12842],"type":"Point"}
}
