{
  "type": "Feature",
  "properties": {
    "date:inception_lower":"2007-05-01",
    "date:inception_upper":"2007-05-31",
    "iso:country":"GB",
    "wof:name":"NE48 2EB",
    "wof:placetype":"postalcode"
},
  "geometry": {"coordinates":[-2.195169,55.12842],"type":"Point"}
}