{
  "type": "Feature",
  "properties": {
    "iso:country":"GB",
    "wof:name":"NE48 2EB",
    "wof:placetype":"postalcode"
},
  "geometry": {"coordinates":[-2.1951687933101,55.12841972841262],"type":"Point"}
}