{
  "type": "Feature",
  "properties": {
    "iso:country":"GB",
    "wof:name":"TN16 1LW",
    "wof:placetype":"postalcode"
},
  "geometry": {"coordinates":[0.10285455603455,51.25905188404327],"type":"Point"}
}