{
  "type": "Feature",
  "properties": {
    "iso:country": "GB",
    "wof:name": "TN16 1LW",
    "wof:placetype": "postalcode"
  },
  "geometry": {"coordinates":[0.102445,51.258905],"type":"Point"}
}
