{
  "type": "Feature",
  "properties": {
    "iso:country":"GB",
    "wof:name":"W1H 6AR",
    "wof:placetype":"postalcode"
},
  "geometry": {"coordinates":[-0.15524446806077,51.51497408010312],"type":"Point"}
}