{
  "type": "Feature",
  "properties": {
    "date:inception_lower": "2007-04-01",
    "date:inception_upper": "2007-04-01",
    "iso:country": "GB",
    "wof:name": "RH20 4FF",
    "wof:placetype": "postalcode"
  },
  "geometry": {"coordinates":[-0.462001,50.926111],"type":"Point"}
}
