{
  "type": "Feature",
  "properties": {
    "iso:country":"GB",
    "wof:name":"RH20 4FF",
    "wof:placetype":"postalcode"
},
  "geometry": {"coordinates":[-0.46200100503479,50.92611130869214],"type":"Point"}
}