{
  "type": "Feature",
  "properties": {
    "iso:country":"GB",
    "wof:name":"RG7 1PY",
    "wof:placetype":"postalcode"
},
  "geometry": {"coordinates":[-0.9682944717148,51.37504737970031],"type":"Point"}
}