{
  "type": "Feature",
  "properties": {
    "date:inception_lower": "1980-01-01",
    "date:inception_upper": "1980-01-01",
    "iso:country": "GB",
    "wof:name": "RG7 1PY",
    "wof:placetype": "postalcode"
  },
  "geometry": {"coordinates":[-0.968294,51.375047],"type":"Point"}
}
