{
  "type": "Feature",
  "properties": {
    "iso:country":"GB",
    "wof:name":"KT3 3DW",
    "wof:placetype":"postalcode"
},
  "geometry": {"coordinates":[-0.26192189674262,51.40745306046789],"type":"Point"}
}