{
  "type": "Feature",
  "properties": {
    "date:inception_lower":"1980-01-01",
    "date:inception_upper":"1980-01-31",
    "iso:country":"GB",
    "wof:name":"KT3 3DW",
    "wof:placetype":"postalcode"
},
  "geometry": {"coordinates":[-0.261922,51.407453],"type":"Point"}
}