{
  "type": "Feature",
  "properties": {
    "date:inception_lower": "1980-01-01",
    "date:inception_upper": "1980-01-01",
    "iso:country": "GB",
    "wof:name": "WR9 8DG",
    "wof:placetype": "postalcode"
  },
  "geometry": {"coordinates":[-2.149861,52.267277],"type":"Point"}
}
