{
  "type": "Feature",
  "properties": {
    "date:inception_lower": "1980-01-01",
    "date:inception_upper": "1980-01-01",
    "iso:country": "GB",
    "wof:name": "TN18 5HR",
    "wof:placetype": "postalcode"
  },
  "geometry": {"coordinates":[0.556231,51.029558],"type":"Point"}
}
