{
  "type": "Feature",
  "properties": {
    "iso:country":"GB",
    "wof:name":"G53 7XY",
    "wof:placetype":"postalcode"
},
  "geometry": {"coordinates":[-4.35711734879591,55.80717976129716],"type":"Point"}
}