{
  "type": "Feature",
  "properties": {
    "iso:country": "GB",
    "wof:name": "G53 7XY",
    "wof:placetype": "postalcode"
  },
  "geometry": {"coordinates":[-4.357117,55.80718],"type":"Point"}
}
