{
  "type": "Feature",
  "properties": {
    "iso:country":"GB",
    "wof:name":"CA10 1PP",
    "wof:placetype":"postalcode"
},
  "geometry": {"coordinates":[-2.63790345805672,54.72336887237032],"type":"Point"}
}