{
  "type": "Feature",
  "properties": {
    "date:inception_lower": "1980-01-01",
    "date:inception_upper": "1980-01-01",
    "iso:country": "GB",
    "wof:name": "PL14 6PH",
    "wof:placetype": "postalcode"
  },
  "geometry": {"coordinates":[-4.588225,50.488636],"type":"Point"}
}
