{
  "type": "Feature",
  "properties": {
    "date:inception_lower": "2003-01-01",
    "date:inception_upper": "2003-01-01",
    "iso:country": "GB",
    "wof:name": "TQ13 0AL",
    "wof:placetype": "postalcode"
  },
  "geometry": {"coordinates":[-3.566831,50.584183],"type":"Point"}
}
