{
  "type": "Feature",
  "properties": {
    "iso:country":"GB",
    "wof:name":"TQ13 0AL",
    "wof:placetype":"postalcode"
},
  "geometry": {"coordinates":[-3.56683118711094,50.58418285767959],"type":"Point"}
}