{
  "type": "Feature",
  "properties": {
    "iso:country":"GB",
    "wof:name":"BS8 1SB",
    "wof:placetype":"postalcode"
},
  "geometry": {"coordinates":[-2.60784886759772,51.45764856350613],"type":"Point"}
}