{
  "type": "Feature",
  "properties": {
    "date:inception_lower": "1980-01-01",
    "date:inception_upper": "1980-01-01",
    "iso:country": "GB",
    "wof:name": "PL30 5HP",
    "wof:placetype": "postalcode"
  },
  "geometry": {"coordinates":[-4.745319,50.427115],"type":"Point"}
}
