{
  "type": "Feature",
  "properties": {
    "iso:country": "GB",
    "wof:name": "CW5 7SY",
    "wof:placetype": "postalcode"
  },
  "geometry": {"coordinates":[-2.503734,53.059427],"type":"Point"}
}
