{
  "type": "Feature",
  "properties": {
    "iso:country":"GB",
    "wof:name":"SN25 1SZ",
    "wof:placetype":"postalcode"
},
  "geometry": {"coordinates":[-1.82000693631434,51.59810419131865],"type":"Point"}
}