{
  "type": "Feature",
  "properties": {
    "iso:country": "GB",
    "wof:name": "SN25 1SZ",
    "wof:placetype": "postalcode"
  },
  "geometry": {"coordinates":[-1.820007,51.598104],"type":"Point"}
}
