{
  "type": "Feature",
  "properties": {
    "iso:country":"GB",
    "wof:name":"RM9 6GE",
    "wof:placetype":"postalcode"
},
  "geometry": {"coordinates":[0.14647597635909,51.53493909794168],"type":"Point"}
}