{
  "type": "Feature",
  "properties": {
    "date:inception_lower":"1980-01-01",
    "date:inception_upper":"1980-01-31",
    "iso:country":"GB",
    "wof:name":"TR16 6EB",
    "wof:placetype":"postalcode"
},
  "geometry": {"coordinates":[-5.203459,50.215234],"type":"Point"}
}