{
  "type": "Feature",
  "properties": {
    "iso:country":"GB",
    "wof:name":"TR16 6EB",
    "wof:placetype":"postalcode"
},
  "geometry": {"coordinates":[-5.20345899472251,50.21523373371667],"type":"Point"}
}