{
  "type": "Feature",
  "properties": {
    "iso:country":"GB",
    "wof:name":"WN2 5DZ",
    "wof:placetype":"postalcode"
},
  "geometry": {"coordinates":[-2.60488088694114,53.51883681469221],"type":"Point"}
}