{
  "type": "Feature",
  "properties": {
    "date:inception_lower": "1999-12-01",
    "date:inception_upper": "1999-12-01",
    "iso:country": "GB",
    "wof:name": "WN2 5DZ",
    "wof:placetype": "postalcode"
  },
  "geometry": {"coordinates":[-2.606377,53.519096],"type":"Point"}
}
