{
  "type": "Feature",
  "properties": {
    "date:inception_lower": "1980-01-01",
    "date:inception_upper": "1980-01-01",
    "iso:country": "GB",
    "wof:name": "HX4 9PG",
    "wof:placetype": "postalcode"
  },
  "geometry": {"coordinates":[-1.887005,53.669754],"type":"Point"}
}
