{
  "type": "Feature",
  "properties": {
    "date:inception_lower":"2004-08-01",
    "date:inception_upper":"2004-08-31",
    "iso:country":"GB",
    "wof:name":"LS12 2JR",
    "wof:placetype":"postalcode"
},
  "geometry": {"coordinates":[-1.610681,53.810064],"type":"Point"}
}