{
  "type": "Feature",
  "properties": {
    "iso:country":"GB",
    "wof:name":"LS12 2JR",
    "wof:placetype":"postalcode"
},
  "geometry": {"coordinates":[-1.61068070476975,53.81006363223481],"type":"Point"}
}