{
  "type": "Feature",
  "properties": {
    "iso:country":"GB",
    "wof:name":"WD3 3JH",
    "wof:placetype":"postalcode"
},
  "geometry": {"coordinates":[-0.45368328933492,51.6590156737626],"type":"Point"}
}