{
  "type": "Feature",
  "properties": {
    "date:inception_lower":"1985-04-01",
    "date:inception_upper":"1985-04-30",
    "iso:country":"GB",
    "wof:name":"BD16 2PF",
    "wof:placetype":"postalcode"
},
  "geometry": {"coordinates":[-1.827991,53.848123],"type":"Point"}
}