{
  "type": "Feature",
  "properties": {
    "iso:country": "GB",
    "wof:name": "BD16 2PF",
    "wof:placetype": "postalcode"
  },
  "geometry": {"coordinates":[-1.827991,53.848123],"type":"Point"}
}
