{
  "type": "Feature",
  "properties": {
    "iso:country": "GB",
    "wof:name": "SK16 4AT",
    "wof:placetype": "postalcode"
  },
  "geometry": {"coordinates":[-2.078544,53.473459],"type":"Point"}
}
