{
  "type": "Feature",
  "properties": {
    "iso:country":"GB",
    "wof:name":"DA8 2DX",
    "wof:placetype":"postalcode"
},
  "geometry": {"coordinates":[0.18546736936081,51.46539616477808],"type":"Point"}
}