{
  "type": "Feature",
  "properties": {
    "iso:country": "GB",
    "wof:name": "DA8 2DX",
    "wof:placetype": "postalcode"
  },
  "geometry": {"coordinates":[0.185467,51.465396],"type":"Point"}
}
