{
  "type": "Feature",
  "properties": {
    "date:inception_lower": "2018-08-01",
    "date:inception_upper": "2018-08-01",
    "iso:country": "GB",
    "wof:name": "B60 9LT",
    "wof:placetype": "postalcode"
  },
  "geometry": {"coordinates":[-2.013249,52.301271],"type":"Point"}
}
