{
  "type": "Feature",
  "properties": {
    "date:inception_lower": "1980-01-01",
    "date:inception_upper": "1980-01-01",
    "iso:country": "GB",
    "wof:name": "G2 1EG",
    "wof:placetype": "postalcode"
  },
  "geometry": {"coordinates":[-4.251708,55.861548],"type":"Point"}
}
