{
  "type": "Feature",
  "properties": {
    "iso:country":"GB",
    "wof:name":"G2 1EG",
    "wof:placetype":"postalcode"
},
  "geometry": {"coordinates":[-4.25172273920419,55.86155266805847],"type":"Point"}
}