{
  "type": "Feature",
  "properties": {
    "iso:country":"GB",
    "wof:name":"PO13 9ND",
    "wof:placetype":"postalcode"
},
  "geometry": {"coordinates":[-1.20494529483001,50.80484781586836],"type":"Point"}
}