{
  "type": "Feature",
  "properties": {
    "iso:country":"GB",
    "wof:name":"NR2 1HL",
    "wof:placetype":"postalcode"
},
  "geometry": {"coordinates":[1.29640593623151,52.62997855264386],"type":"Point"}
}