{
  "type": "Feature",
  "properties": {
    "date:inception_lower":"1994-12-01",
    "date:inception_upper":"1994-12-31",
    "iso:country":"GB",
    "wof:name":"SO15 3FY",
    "wof:placetype":"postalcode"
},
  "geometry": {"coordinates":[-1.433559,50.912626],"type":"Point"}
}