{
  "type": "Feature",
  "properties": {
    "iso:country": "GB",
    "wof:name": "SO15 3FY",
    "wof:placetype": "postalcode"
  },
  "geometry": {"coordinates":[-1.433559,50.912626],"type":"Point"}
}
