{
  "type": "Feature",
  "properties": {
    "iso:country":"GB",
    "wof:name":"E14 0SP",
    "wof:placetype":"postalcode"
},
  "geometry": {"coordinates":[-0.01023465915835,51.51671326327275],"type":"Point"}
}