{
  "type": "Feature",
  "properties": {
    "iso:country":"GB",
    "wof:name":"TN29 0ET",
    "wof:placetype":"postalcode"
},
  "geometry": {"coordinates":[0.9703899903812,51.00318118411032],"type":"Point"}
}