{
  "type": "Feature",
  "properties": {
    "date:inception_lower": "2006-09-01",
    "date:inception_upper": "2006-09-01",
    "iso:country": "GB",
    "wof:name": "CB22 4PB",
    "wof:placetype": "postalcode"
  },
  "geometry": {"coordinates":[0.136746,52.115758],"type":"Point"}
}
