{
  "type": "Feature",
  "properties": {
    "iso:country":"GB",
    "wof:name":"CB22 4PB",
    "wof:placetype":"postalcode"
},
  "geometry": {"coordinates":[0.13674610335491,52.11575817731867],"type":"Point"}
}