{
  "type": "Feature",
  "properties": {
    "iso:country": "GB",
    "wof:name": "G82 2BP",
    "wof:placetype": "postalcode"
  },
  "geometry": {"coordinates":[-4.560494,55.955083],"type":"Point"}
}
