{
  "type": "Feature",
  "properties": {
    "date:inception_lower":"2014-04-01",
    "date:inception_upper":"2014-04-30",
    "iso:country":"GB",
    "wof:name":"G82 2BP",
    "wof:placetype":"postalcode"
},
  "geometry": {"coordinates":[-4.560494,55.955083],"type":"Point"}
}