{
  "type": "Feature",
  "properties": {
    "iso:country": "GB",
    "wof:name": "CA11 8QY",
    "wof:placetype": "postalcode"
  },
  "geometry": {"coordinates":[-2.761602,54.677154],"type":"Point"}
}
