{
  "type": "Feature",
  "properties": {
    "iso:country": "GB",
    "wof:name": "NG9 3SX",
    "wof:placetype": "postalcode"
  },
  "geometry": {"coordinates":[-1.239896,52.927157],"type":"Point"}
}
