{
  "type": "Feature",
  "properties": {
    "iso:country":"GB",
    "wof:name":"NG9 3SX",
    "wof:placetype":"postalcode"
},
  "geometry": {"coordinates":[-1.23989575482957,52.92715747607004],"type":"Point"}
}