{
  "type": "Feature",
  "properties": {
    "date:inception_lower": "1980-01-01",
    "date:inception_upper": "1980-01-01",
    "iso:country": "GB",
    "wof:name": "TA4 1EQ",
    "wof:placetype": "postalcode"
  },
  "geometry": {"coordinates":[-3.144398,50.99987],"type":"Point"}
}
