{
  "type": "Feature",
  "properties": {
    "date:inception_lower":"1996-06-01",
    "date:inception_upper":"1996-06-30",
    "iso:country":"GB",
    "wof:name":"AB42 3LR",
    "wof:placetype":"postalcode"
},
  "geometry": {"coordinates":[-1.878223,57.477402],"type":"Point"}
}