{
  "type": "Feature",
  "properties": {
    "iso:country":"GB",
    "wof:name":"DT2 9ST",
    "wof:placetype":"postalcode"
},
  "geometry": {"coordinates":[-2.49160488426773,50.74237357867854],"type":"Point"}
}