{
  "type": "Feature",
  "properties": {
    "date:inception_lower": "1980-01-01",
    "date:inception_upper": "1980-01-01",
    "iso:country": "GB",
    "wof:name": "DT2 9ST",
    "wof:placetype": "postalcode"
  },
  "geometry": {"coordinates":[-2.491618,50.742364],"type":"Point"}
}
