{
  "type": "Feature",
  "properties": {
    "date:inception_lower":"2006-07-01",
    "date:inception_upper":"2006-07-31",
    "iso:country":"GB",
    "wof:name":"TS3 6NB",
    "wof:placetype":"postalcode"
},
  "geometry": {"coordinates":[-1.213373,54.569954],"type":"Point"}
}