{
  "type": "Feature",
  "properties": {
    "iso:country": "GB",
    "wof:name": "TS3 6NB",
    "wof:placetype": "postalcode"
  },
  "geometry": {"coordinates":[-1.213373,54.569954],"type":"Point"}
}
