{
  "type": "Feature",
  "properties": {
    "iso:country":"GB",
    "wof:name":"TS3 6NB",
    "wof:placetype":"postalcode"
},
  "geometry": {"coordinates":[-1.21337304516856,54.56995359082979],"type":"Point"}
}