{
  "type": "Feature",
  "properties": {
    "date:inception_lower": "2017-06-01",
    "date:inception_upper": "2017-06-01",
    "iso:country": "GB",
    "wof:name": "IP14 1UY",
    "wof:placetype": "postalcode"
  },
  "geometry": {"coordinates":[0.981984,52.200708],"type":"Point"}
}
