{
  "type": "Feature",
  "properties": {
    "iso:country":"GB",
    "wof:name":"LS1 4EN",
    "wof:placetype":"postalcode"
},
  "geometry": {"coordinates":[-1.54798306591483,53.79392607745933],"type":"Point"}
}