{
  "type": "Feature",
  "properties": {
    "iso:country": "GB",
    "wof:name": "LS1 4EN",
    "wof:placetype": "postalcode"
  },
  "geometry": {"coordinates":[-1.547983,53.793926],"type":"Point"}
}
