{
  "type": "Feature",
  "properties": {
    "date:inception_lower": "2024-08-01",
    "date:inception_upper": "2024-08-01",
    "iso:country": "GB",
    "wof:name": "ME20 7NY",
    "wof:placetype": "postalcode"
  },
  "geometry": {"coordinates":[0.492382,51.296542],"type":"Point"}
}
