{
  "type": "Feature",
  "properties": {
    "iso:country": "GB",
    "wof:name": "LA12 8QS",
    "wof:placetype": "postalcode"
  },
  "geometry": {"coordinates":[-2.987267,54.251078],"type":"Point"}
}
