{
  "type": "Feature",
  "properties": {
    "iso:country":"GB",
    "wof:name":"LA12 8QS",
    "wof:placetype":"postalcode"
},
  "geometry": {"coordinates":[-2.98729766959764,54.25107761398182],"type":"Point"}
}