{
  "type": "Feature",
  "properties": {
    "iso:country": "GB",
    "wof:name": "LE9 6UX",
    "wof:placetype": "postalcode"
  },
  "geometry": {"coordinates":[-1.223153,52.525025],"type":"Point"}
}
