{
  "type": "Feature",
  "properties": {
    "iso:country":"GB",
    "wof:name":"LE9 6UX",
    "wof:placetype":"postalcode"
},
  "geometry": {"coordinates":[-1.22315290156976,52.52502532423807],"type":"Point"}
}