{
  "type": "Feature",
  "properties": {
    "date:inception_lower": "1994-05-01",
    "date:inception_upper": "1994-05-01",
    "iso:country": "GB",
    "wof:name": "M33 6LJ",
    "wof:placetype": "postalcode"
  },
  "geometry": {"coordinates":[-2.32586,53.431799],"type":"Point"}
}
