{
  "type": "Feature",
  "properties": {
    "iso:country":"GB",
    "wof:name":"HX1 5RR",
    "wof:placetype":"postalcode"
},
  "geometry": {"coordinates":[-1.87731942277149,53.72675604692553],"type":"Point"}
}