{
  "type": "Feature",
  "properties": {
    "iso:country":"GB",
    "wof:name":"WA10 3BD",
    "wof:placetype":"postalcode"
},
  "geometry": {"coordinates":[-2.7724044367002,53.4395711973339],"type":"Point"}
}