{
  "type": "Feature",
  "properties": {
    "date:inception_lower": "1980-01-01",
    "date:inception_upper": "1980-01-01",
    "iso:country": "GB",
    "wof:name": "WA10 3BD",
    "wof:placetype": "postalcode"
  },
  "geometry": {"coordinates":[-2.772076,53.439805],"type":"Point"}
}
