{
  "type": "Feature",
  "properties": {
    "iso:country": "GB",
    "wof:name": "KA18 1LH",
    "wof:placetype": "postalcode"
  },
  "geometry": {"coordinates":[-4.262561,55.452765],"type":"Point"}
}
