{
  "type": "Feature",
  "properties": {
    "iso:country":"GB",
    "wof:name":"KA18 1LH",
    "wof:placetype":"postalcode"
},
  "geometry": {"coordinates":[-4.26257478080895,55.45276247944146],"type":"Point"}
}