{
  "type": "Feature",
  "properties": {
    "date:inception_lower": "2012-03-01",
    "date:inception_upper": "2012-03-01",
    "iso:country": "GB",
    "wof:name": "KA18 1LH",
    "wof:placetype": "postalcode"
  },
  "geometry": {"coordinates":[-4.261001,55.452578],"type":"Point"}
}
