{
  "type": "Feature",
  "properties": {
    "date:inception_lower":"2012-03-01",
    "date:inception_upper":"2012-03-31",
    "iso:country":"GB",
    "wof:name":"KA18 1LH",
    "wof:placetype":"postalcode"
},
  "geometry": {"coordinates":[-4.260834,55.452707],"type":"Point"}
}