{
  "type": "Feature",
  "properties": {
    "iso:country": "GB",
    "wof:name": "CW1 4SY",
    "wof:placetype": "postalcode"
  },
  "geometry": {"coordinates":[-2.464289,53.11959],"type":"Point"}
}
