{
  "type": "Feature",
  "properties": {
    "iso:country":"GB",
    "wof:name":"AB42 4LA",
    "wof:placetype":"postalcode"
},
  "geometry": {"coordinates":[-2.13055417432046,57.5202394344436],"type":"Point"}
}