{
  "type": "Feature",
  "properties": {
    "iso:country": "GB",
    "wof:name": "SG18 9PQ",
    "wof:placetype": "postalcode"
  },
  "geometry": {"coordinates":[-0.26657,52.048334],"type":"Point"}
}
