{
  "type": "Feature",
  "properties": {
    "date:inception_lower":"1980-01-01",
    "date:inception_upper":"1980-01-31",
    "iso:country":"GB",
    "wof:name":"SG18 9PQ",
    "wof:placetype":"postalcode"
},
  "geometry": {"coordinates":[-0.266486,52.048234],"type":"Point"}
}