{
  "type": "Feature",
  "properties": {
    "date:inception_lower": "1980-01-01",
    "date:inception_upper": "1980-01-01",
    "iso:country": "GB",
    "wof:name": "SG18 9PQ",
    "wof:placetype": "postalcode"
  },
  "geometry": {"coordinates":[-0.266599,52.048326],"type":"Point"}
}
