{
  "type": "Feature",
  "properties": {
    "iso:country": "GB",
    "wof:name": "LL65 4LB",
    "wof:placetype": "postalcode"
  },
  "geometry": {"coordinates":[-4.528334,53.376142],"type":"Point"}
}
