{
  "type": "Feature",
  "properties": {
    "date:inception_lower": "2018-03-01",
    "date:inception_upper": "2018-03-01",
    "iso:country": "GB",
    "wof:name": "MK1 1FA",
    "wof:placetype": "postalcode"
  },
  "geometry": {"coordinates":[-0.72643,52.012598],"type":"Point"}
}
