{
  "type": "Feature",
  "properties": {
    "iso:country":"GB",
    "wof:name":"MK16 0JN",
    "wof:placetype":"postalcode"
},
  "geometry": {"coordinates":[-0.72925014515552,52.08399056587796],"type":"Point"}
}