{
  "type": "Feature",
  "properties": {
    "date:inception_lower": "1985-10-01",
    "date:inception_upper": "1985-10-01",
    "iso:country": "GB",
    "wof:name": "MK16 0JN",
    "wof:placetype": "postalcode"
  },
  "geometry": {"coordinates":[-0.72925,52.083991],"type":"Point"}
}
