{
  "type": "Feature",
  "properties": {
    "iso:country":"GB",
    "wof:name":"CF44 8AJ",
    "wof:placetype":"postalcode"
},
  "geometry": {"coordinates":[-3.46750310549342,51.71549100678641],"type":"Point"}
}