{
  "type": "Feature",
  "properties": {
    "date:inception_lower":"1997-12-01",
    "date:inception_upper":"1997-12-31",
    "iso:country":"GB",
    "wof:name":"CF44 8AJ",
    "wof:placetype":"postalcode"
},
  "geometry": {"coordinates":[-3.467503,51.715491],"type":"Point"}
}