{
  "type": "Feature",
  "properties": {
    "iso:country":"GB",
    "wof:name":"UB8 1AX",
    "wof:placetype":"postalcode"
},
  "geometry": {"coordinates":[-0.47591435562921,51.55004415676218],"type":"Point"}
}