{
  "type": "Feature",
  "properties": {
    "date:inception_lower": "1980-01-01",
    "date:inception_upper": "1980-01-01",
    "iso:country": "GB",
    "wof:name": "UB8 1AX",
    "wof:placetype": "postalcode"
  },
  "geometry": {"coordinates":[-0.475914,51.550044],"type":"Point"}
}
