{
  "type": "Feature",
  "properties": {
    "iso:country": "GB",
    "wof:name": "UB8 1AX",
    "wof:placetype": "postalcode"
  },
  "geometry": {"coordinates":[-0.475914,51.550044],"type":"Point"}
}
