{
  "type": "Feature",
  "properties": {
    "date:inception_lower": "2022-03-01",
    "date:inception_upper": "2022-03-01",
    "iso:country": "GB",
    "wof:name": "RG20 8BR",
    "wof:placetype": "postalcode"
  },
  "geometry": {"coordinates":[-1.398259,51.433234],"type":"Point"}
}
