{
  "type": "Feature",
  "properties": {
    "iso:country":"GB",
    "wof:name":"NN6 0LB",
    "wof:placetype":"postalcode"
},
  "geometry": {"coordinates":[-0.75059115938878,52.26863205342968],"type":"Point"}
}