{
  "type": "Feature",
  "properties": {
    "iso:country": "GB",
    "wof:name": "B35 6JE",
    "wof:placetype": "postalcode"
  },
  "geometry": {"coordinates":[-1.785575,52.525078],"type":"Point"}
}
