{
  "type": "Feature",
  "properties": {
    "iso:country":"GB",
    "wof:name":"B35 6JE",
    "wof:placetype":"postalcode"
},
  "geometry": {"coordinates":[-1.78557512790325,52.52507772363149],"type":"Point"}
}