{
  "type": "Feature",
  "properties": {
    "iso:country":"GB",
    "wof:name":"M33 2BU",
    "wof:placetype":"postalcode"
},
  "geometry": {"coordinates":[-2.30926460530671,53.42841984940811],"type":"Point"}
}