{
  "type": "Feature",
  "properties": {
    "iso:country": "GB",
    "wof:name": "DL16 6BH",
    "wof:placetype": "postalcode"
  },
  "geometry": {"coordinates":[-1.602823,54.698904],"type":"Point"}
}
