{
  "type": "Feature",
  "properties": {
    "iso:country":"GB",
    "wof:name":"DL16 6BH",
    "wof:placetype":"postalcode"
},
  "geometry": {"coordinates":[-1.60281320532979,54.69889446255249],"type":"Point"}
}