{
  "type": "Feature",
  "properties": {
    "iso:country": "GB",
    "wof:name": "CV21 3QN",
    "wof:placetype": "postalcode"
  },
  "geometry": {"coordinates":[-1.247805,52.372593],"type":"Point"}
}
