{
  "type": "Feature",
  "properties": {
    "iso:country":"GB",
    "wof:name":"CV21 3QN",
    "wof:placetype":"postalcode"
},
  "geometry": {"coordinates":[-1.24775917790981,52.37261146583752],"type":"Point"}
}