{
  "type": "Feature",
  "properties": {
    "iso:country":"GB",
    "wof:name":"KA20 4JG",
    "wof:placetype":"postalcode"
},
  "geometry": {"coordinates":[-4.73957200719032,55.64749066026412],"type":"Point"}
}