{
  "type": "Feature",
  "properties": {
    "iso:country": "GB",
    "wof:name": "HU17 8LX",
    "wof:placetype": "postalcode"
  },
  "geometry": {"coordinates":[-0.438086,53.835809],"type":"Point"}
}
