{
  "type": "Feature",
  "properties": {
    "iso:country":"GB",
    "wof:name":"HU17 8LX",
    "wof:placetype":"postalcode"
},
  "geometry": {"coordinates":[-0.43808579646225,53.83580873795524],"type":"Point"}
}