{
  "type": "Feature",
  "properties": {
    "iso:country":"GB",
    "wof:name":"NE9 7PJ",
    "wof:placetype":"postalcode"
},
  "geometry": {"coordinates":[-1.55070039638587,54.9185681063467],"type":"Point"}
}