{
  "type": "Feature",
  "properties": {
    "iso:country": "GB",
    "wof:name": "NG7 5QA",
    "wof:placetype": "postalcode"
  },
  "geometry": {"coordinates":[-1.179992,52.961737],"type":"Point"}
}
