{
  "type": "Feature",
  "properties": {
    "date:inception_lower": "1980-01-01",
    "date:inception_upper": "1980-01-01",
    "iso:country": "GB",
    "wof:name": "NG7 5QA",
    "wof:placetype": "postalcode"
  },
  "geometry": {"coordinates":[-1.179992,52.961737],"type":"Point"}
}
