{
  "type": "Feature",
  "properties": {
    "date:inception_lower":"1980-01-01",
    "date:inception_upper":"1980-01-31",
    "iso:country":"GB",
    "wof:name":"BB9 5JP",
    "wof:placetype":"postalcode"
},
  "geometry": {"coordinates":[-2.236139,53.820942],"type":"Point"}
}