{
  "type": "Feature",
  "properties": {
    "iso:country":"GB",
    "wof:name":"BB9 5JP",
    "wof:placetype":"postalcode"
},
  "geometry": {"coordinates":[-2.23613860991225,53.82094158087193],"type":"Point"}
}