{
  "type": "Feature",
  "properties": {
    "iso:country": "GB",
    "wof:name": "BB9 5JP",
    "wof:placetype": "postalcode"
  },
  "geometry": {"coordinates":[-2.236139,53.820942],"type":"Point"}
}
