{
  "type": "Feature",
  "properties": {
    "iso:country": "GB",
    "wof:name": "SO50 9QB",
    "wof:placetype": "postalcode"
  },
  "geometry": {"coordinates":[-1.360039,50.970275],"type":"Point"}
}
