{
  "type": "Feature",
  "properties": {
    "iso:country":"GB",
    "wof:name":"DG7 1QJ",
    "wof:placetype":"postalcode"
},
  "geometry": {"coordinates":[-3.86087280750938,54.87348987678995],"type":"Point"}
}