{
  "type": "Feature",
  "properties": {
    "date:inception_lower": "1980-01-01",
    "date:inception_upper": "1980-01-01",
    "iso:country": "GB",
    "wof:name": "DG7 1QJ",
    "wof:placetype": "postalcode"
  },
  "geometry": {"coordinates":[-3.862276,54.873566],"type":"Point"}
}
