{
  "type": "Feature",
  "properties": {
    "iso:country": "GB",
    "wof:name": "LL68 9HW",
    "wof:placetype": "postalcode"
  },
  "geometry": {"coordinates":[-4.329856,53.41335],"type":"Point"}
}
