{
  "type": "Feature",
  "properties": {
    "iso:country":"GB",
    "wof:name":"LL68 9HW",
    "wof:placetype":"postalcode"
},
  "geometry": {"coordinates":[-4.32985644643592,53.41334971516529],"type":"Point"}
}