{
  "type": "Feature",
  "properties": {
    "date:inception_lower":"1980-01-01",
    "date:inception_upper":"1980-01-31",
    "iso:country":"GB",
    "wof:name":"LA9 4NX",
    "wof:placetype":"postalcode"
},
  "geometry": {"coordinates":[-2.75081,54.328646],"type":"Point"}
}