{
  "type": "Feature",
  "properties": {
    "iso:country": "GB",
    "wof:name": "LA9 4NX",
    "wof:placetype": "postalcode"
  },
  "geometry": {"coordinates":[-2.75081,54.328646],"type":"Point"}
}
