{
  "type": "Feature",
  "properties": {
    "date:inception_lower": "2023-05-01",
    "date:inception_upper": "2023-05-01",
    "iso:country": "GB",
    "wof:name": "PE12 7FS",
    "wof:placetype": "postalcode"
  },
  "geometry": {"coordinates":[0.032847,52.80904],"type":"Point"}
}
