{
  "type": "Feature",
  "properties": {
    "iso:country":"GB",
    "wof:name":"HX2 7PT",
    "wof:placetype":"postalcode"
},
  "geometry": {"coordinates":[-1.89601148724163,53.71873834614699],"type":"Point"}
}