{
  "type": "Feature",
  "properties": {
    "iso:country": "GB",
    "wof:name": "HX2 7PT",
    "wof:placetype": "postalcode"
  },
  "geometry": {"coordinates":[-1.896011,53.718738],"type":"Point"}
}
