{
  "type": "Feature",
  "properties": {
    "iso:country": "GB",
    "wof:name": "SN11 0DE",
    "wof:placetype": "postalcode"
  },
  "geometry": {"coordinates":[-2.008065,51.439579],"type":"Point"}
}
