{
  "type": "Feature",
  "properties": {
    "iso:country":"GB",
    "wof:name":"SN11 0DE",
    "wof:placetype":"postalcode"
},
  "geometry": {"coordinates":[-2.00806550502508,51.43957861926566],"type":"Point"}
}