{
  "type": "Feature",
  "properties": {
    "iso:country":"GB",
    "wof:name":"DL1 2XJ",
    "wof:placetype":"postalcode"
},
  "geometry": {"coordinates":[-1.51773624473771,54.53778469950286],"type":"Point"}
}