{
  "type": "Feature",
  "properties": {
    "iso:country":"GB",
    "wof:name":"PE4 5BJ",
    "wof:placetype":"postalcode"
},
  "geometry": {"coordinates":[-0.28093926780864,52.61927761575195],"type":"Point"}
}