{
  "type": "Feature",
  "properties": {
    "iso:country":"GB",
    "wof:name":"SS8 9PZ",
    "wof:placetype":"postalcode"
},
  "geometry": {"coordinates":[0.57917085539413,51.53256172735838],"type":"Point"}
}