{
  "type": "Feature",
  "properties": {
    "iso:country": "GB",
    "wof:name": "RH17 6ND",
    "wof:placetype": "postalcode"
  },
  "geometry": {"coordinates":[-0.126464,51.055799],"type":"Point"}
}
