{
  "type": "Feature",
  "properties": {
    "iso:country":"GB",
    "wof:name":"RH17 6ND",
    "wof:placetype":"postalcode"
},
  "geometry": {"coordinates":[-0.12644900478288,51.05579299198508],"type":"Point"}
}