{
  "type": "Feature",
  "properties": {
    "iso:country":"GB",
    "wof:name":"HP23 5DU",
    "wof:placetype":"postalcode"
},
  "geometry": {"coordinates":[-0.66010342077213,51.8017051626168],"type":"Point"}
}