{
  "type": "Feature",
  "properties": {
    "iso:country": "GB",
    "wof:name": "BA9 9PL",
    "wof:placetype": "postalcode"
  },
  "geometry": {"coordinates":[-2.382562,51.049416],"type":"Point"}
}
