{
  "type": "Feature",
  "properties": {
    "iso:country":"GB",
    "wof:name":"LS12 5BP",
    "wof:placetype":"postalcode"
},
  "geometry": {"coordinates":[-1.61814404260905,53.78756364484485],"type":"Point"}
}