{
  "type": "Feature",
  "properties": {
    "date:inception_lower":"1980-01-01",
    "date:inception_upper":"1980-01-31",
    "iso:country":"GB",
    "wof:name":"SA18 3RP",
    "wof:placetype":"postalcode"
},
  "geometry": {"coordinates":[-4.049028,51.781412],"type":"Point"}
}