{
  "type": "Feature",
  "properties": {
    "iso:country":"GB",
    "wof:name":"SA18 3RP",
    "wof:placetype":"postalcode"
},
  "geometry": {"coordinates":[-4.04903656004745,51.7813954270632],"type":"Point"}
}