{
  "type": "Feature",
  "properties": {
    "iso:country": "GB",
    "wof:name": "EH22 1SY",
    "wof:placetype": "postalcode"
  },
  "geometry": {"coordinates":[-3.115661,55.917124],"type":"Point"}
}
