{
  "type": "Feature",
  "properties": {
    "date:inception_lower": "1994-06-01",
    "date:inception_upper": "1994-06-01",
    "iso:country": "GB",
    "wof:name": "EH22 1SY",
    "wof:placetype": "postalcode"
  },
  "geometry": {"coordinates":[-3.115661,55.917124],"type":"Point"}
}
