{
  "type": "Feature",
  "properties": {
    "iso:country":"GB",
    "wof:name":"BS3 2RR",
    "wof:placetype":"postalcode"
},
  "geometry": {"coordinates":[-2.62157838675564,51.43106012814428],"type":"Point"}
}