{
  "type": "Feature",
  "properties": {
    "iso:country":"GB",
    "wof:name":"PO22 9NJ",
    "wof:placetype":"postalcode"
},
  "geometry": {"coordinates":[-0.66633800384419,50.80083412588964],"type":"Point"}
}