{
  "type": "Feature",
  "properties": {
    "iso:country": "GB",
    "wof:name": "TR1 3JQ",
    "wof:placetype": "postalcode"
  },
  "geometry": {"coordinates":[-5.058237,50.263202],"type":"Point"}
}
