{
  "type": "Feature",
  "properties": {
    "iso:country":"GB",
    "wof:name":"SR8 4JG",
    "wof:placetype":"postalcode"
},
  "geometry": {"coordinates":[-1.31546238771621,54.76163462215692],"type":"Point"}
}