{
  "type": "Feature",
  "properties": {
    "iso:country":"GB",
    "wof:name":"TS4 2RQ",
    "wof:placetype":"postalcode"
},
  "geometry": {"coordinates":[-1.22517169013689,54.56033263421387],"type":"Point"}
}