{
  "type": "Feature",
  "properties": {
    "iso:country": "GB",
    "wof:name": "HP21 9PB",
    "wof:placetype": "postalcode"
  },
  "geometry": {"coordinates":[-0.790997,51.801198],"type":"Point"}
}
