{
  "type": "Feature",
  "properties": {
    "date:inception_lower":"1986-01-01",
    "date:inception_upper":"1986-01-31",
    "iso:country":"GB",
    "wof:name":"HP21 9PB",
    "wof:placetype":"postalcode"
},
  "geometry": {"coordinates":[-0.791121,51.801255],"type":"Point"}
}