{
  "type": "Feature",
  "properties": {
    "iso:country":"GB",
    "wof:name":"MK2 2HS",
    "wof:placetype":"postalcode"
},
  "geometry": {"coordinates":[-0.72037016282741,51.99128537075942],"type":"Point"}
}