{
  "type": "Feature",
  "properties": {
    "date:inception_lower":"1980-01-01",
    "date:inception_upper":"1980-01-31",
    "iso:country":"GB",
    "wof:name":"MK2 2HS",
    "wof:placetype":"postalcode"
},
  "geometry": {"coordinates":[-0.72037,51.991285],"type":"Point"}
}