{
  "type": "Feature",
  "properties": {
    "date:inception_lower":"1980-01-01",
    "date:inception_upper":"1980-01-31",
    "iso:country":"GB",
    "wof:name":"TA19 0AU",
    "wof:placetype":"postalcode"
},
  "geometry": {"coordinates":[-2.902075,50.926609],"type":"Point"}
}