{
  "type": "Feature",
  "properties": {
    "iso:country":"GB",
    "wof:name":"TA19 0AU",
    "wof:placetype":"postalcode"
},
  "geometry": {"coordinates":[-2.90207548053402,50.92660864842816],"type":"Point"}
}