{
  "type": "Feature",
  "properties": {
    "iso:country":"GB",
    "wof:name":"DG8 8BH",
    "wof:placetype":"postalcode"
},
  "geometry": {"coordinates":[-4.36953177303071,54.78816708642863],"type":"Point"}
}