{
  "type": "Feature",
  "properties": {
    "date:inception_lower": "1980-01-01",
    "date:inception_upper": "1980-01-01",
    "iso:country": "GB",
    "wof:name": "DG8 8BH",
    "wof:placetype": "postalcode"
  },
  "geometry": {"coordinates":[-4.369532,54.788167],"type":"Point"}
}
