{
  "type": "Feature",
  "properties": {
    "iso:country": "GB",
    "wof:name": "PA15 2RF",
    "wof:placetype": "postalcode"
  },
  "geometry": {"coordinates":[-4.713005,55.93616],"type":"Point"}
}
