{
  "type": "Feature",
  "properties": {
    "date:inception_lower": "2007-09-01",
    "date:inception_upper": "2007-09-01",
    "iso:country": "GB",
    "wof:name": "PA15 2RF",
    "wof:placetype": "postalcode"
  },
  "geometry": {"coordinates":[-4.713065,55.936152],"type":"Point"}
}
