{
  "type": "Feature",
  "properties": {
    "iso:country":"GB",
    "wof:name":"E11 4AZ",
    "wof:placetype":"postalcode"
},
  "geometry": {"coordinates":[0.00642234949612,51.56807423300069],"type":"Point"}
}