{
  "type": "Feature",
  "properties": {
    "iso:country": "GB",
    "wof:name": "E11 4AZ",
    "wof:placetype": "postalcode"
  },
  "geometry": {"coordinates":[0.006422,51.568074],"type":"Point"}
}
