{
  "type": "Feature",
  "properties": {
    "date:inception_lower":"1986-07-01",
    "date:inception_upper":"1986-07-31",
    "iso:country":"GB",
    "wof:name":"E11 4AZ",
    "wof:placetype":"postalcode"
},
  "geometry": {"coordinates":[0.006422,51.568074],"type":"Point"}
}