{
  "type": "Feature",
  "properties": {
    "iso:country":"GB",
    "wof:name":"SS12 0EF",
    "wof:placetype":"postalcode"
},
  "geometry": {"coordinates":[0.50493492995903,51.6138516004706],"type":"Point"}
}