{
  "type": "Feature",
  "properties": {
    "iso:country":"GB",
    "wof:name":"BS7 0QG",
    "wof:placetype":"postalcode"
},
  "geometry": {"coordinates":[-2.56916888359712,51.50226125949472],"type":"Point"}
}