{
  "type": "Feature",
  "properties": {
    "iso:country":"GB",
    "wof:name":"CO7 7QR",
    "wof:placetype":"postalcode"
},
  "geometry": {"coordinates":[0.93934566488824,51.92440246605082],"type":"Point"}
}