{
  "type": "Feature",
  "properties": {
    "date:inception_lower": "2018-09-01",
    "date:inception_upper": "2018-09-01",
    "iso:country": "GB",
    "wof:name": "CW8 2WA",
    "wof:placetype": "postalcode"
  },
  "geometry": {"coordinates":[-2.633194,53.268036],"type":"Point"}
}
