{
  "type": "Feature",
  "properties": {
    "iso:country":"GB",
    "wof:name":"SY3 5DQ",
    "wof:placetype":"postalcode"
},
  "geometry": {"coordinates":[-2.81228712270392,52.714346610546],"type":"Point"}
}