{
  "type": "Feature",
  "properties": {
    "date:inception_lower": "1983-03-01",
    "date:inception_upper": "1983-03-01",
    "iso:country": "GB",
    "wof:name": "SY3 5DQ",
    "wof:placetype": "postalcode"
  },
  "geometry": {"coordinates":[-2.812287,52.714347],"type":"Point"}
}
