{
  "type": "Feature",
  "properties": {
    "iso:country": "GB",
    "wof:name": "CH2 1HE",
    "wof:placetype": "postalcode"
  },
  "geometry": {"coordinates":[-2.8819,53.208425],"type":"Point"}
}
