{
  "type": "Feature",
  "properties": {
    "iso:country":"GB",
    "wof:name":"OX7 5PZ",
    "wof:placetype":"postalcode"
},
  "geometry": {"coordinates":[-1.55465881628484,51.96264333097805],"type":"Point"}
}