{
  "type": "Feature",
  "properties": {
    "iso:country":"GB",
    "wof:name":"BL6 5QT",
    "wof:placetype":"postalcode"
},
  "geometry": {"coordinates":[-2.55222445736731,53.59839672762208],"type":"Point"}
}