{
  "type": "Feature",
  "properties": {
    "iso:country": "GB",
    "wof:name": "CF62 8AY",
    "wof:placetype": "postalcode"
  },
  "geometry": {"coordinates":[-3.294305,51.417882],"type":"Point"}
}
