{
  "type": "Feature",
  "properties": {
    "date:inception_lower":"1993-01-01",
    "date:inception_upper":"1993-01-31",
    "iso:country":"GB",
    "wof:name":"CF62 8AY",
    "wof:placetype":"postalcode"
},
  "geometry": {"coordinates":[-3.294305,51.417882],"type":"Point"}
}