{
  "type": "Feature",
  "properties": {
    "iso:country":"GB",
    "wof:name":"DE7 5LD",
    "wof:placetype":"postalcode"
},
  "geometry": {"coordinates":[-1.30793239060635,52.97502819548281],"type":"Point"}
}