{
  "type": "Feature",
  "properties": {
    "iso:country": "GB",
    "wof:name": "OL16 3DZ",
    "wof:placetype": "postalcode"
  },
  "geometry": {"coordinates":[-2.105216,53.609261],"type":"Point"}
}
