{
  "type": "Feature",
  "properties": {
    "iso:country":"GB",
    "wof:name":"NW5 4BP",
    "wof:placetype":"postalcode"
},
  "geometry": {"coordinates":[-0.15560508804862,51.55099456181109],"type":"Point"}
}