{
  "type": "Feature",
  "properties": {
    "date:inception_lower": "1994-02-01",
    "date:inception_upper": "1994-02-01",
    "iso:country": "GB",
    "wof:name": "AB23 8UA",
    "wof:placetype": "postalcode"
  },
  "geometry": {"coordinates":[-2.092096,57.229273],"type":"Point"}
}
