{
  "type": "Feature",
  "properties": {
    "iso:country": "GB",
    "wof:name": "SA8 4PL",
    "wof:placetype": "postalcode"
  },
  "geometry": {"coordinates":[-3.842512,51.731761],"type":"Point"}
}
