{
  "type": "Feature",
  "properties": {
    "iso:country":"GB",
    "wof:name":"CF48 1HA",
    "wof:placetype":"postalcode"
},
  "geometry": {"coordinates":[-3.40447023985563,51.75311867168024],"type":"Point"}
}