{
  "type": "Feature",
  "properties": {
    "iso:country":"GB",
    "wof:name":"CB1 2HR",
    "wof:placetype":"postalcode"
},
  "geometry": {"coordinates":[0.13408312659001,52.20031312822734],"type":"Point"}
}