{
  "type": "Feature",
  "properties": {
    "date:inception_lower": "1980-01-01",
    "date:inception_upper": "1980-01-01",
    "iso:country": "GB",
    "wof:name": "CB1 2HR",
    "wof:placetype": "postalcode"
  },
  "geometry": {"coordinates":[0.134083,52.200313],"type":"Point"}
}
