{
  "type": "Feature",
  "properties": {
    "iso:country":"GB",
    "wof:name":"SW16 2HP",
    "wof:placetype":"postalcode"
},
  "geometry": {"coordinates":[-0.12276201542688,51.42649321614984],"type":"Point"}
}