{
  "type": "Feature",
  "properties": {
    "iso:country":"GB",
    "wof:name":"LE4 7SU",
    "wof:placetype":"postalcode"
},
  "geometry": {"coordinates":[-1.10153586076643,52.67016356633338],"type":"Point"}
}