{
  "type": "Feature",
  "properties": {
    "iso:country":"GB",
    "wof:name":"G75 8HF",
    "wof:placetype":"postalcode"
},
  "geometry": {"coordinates":[-4.20647138322308,55.75508092852134],"type":"Point"}
}