{
  "type": "Feature",
  "properties": {
    "iso:country":"GB",
    "wof:name":"CT7 0QN",
    "wof:placetype":"postalcode"
},
  "geometry": {"coordinates":[1.23041523664115,51.36169763634383],"type":"Point"}
}