{
  "type": "Feature",
  "properties": {
    "iso:country":"GB",
    "wof:name":"CH62 2DU",
    "wof:placetype":"postalcode"
},
  "geometry": {"coordinates":[-2.98952462083498,53.33296039525294],"type":"Point"}
}