{
  "type": "Feature",
  "properties": {
    "iso:country":"GB",
    "wof:name":"TS25 1BE",
    "wof:placetype":"postalcode"
},
  "geometry": {"coordinates":[-1.18965135196304,54.66165347429831],"type":"Point"}
}