{
  "type": "Feature",
  "properties": {
    "iso:country": "GB",
    "wof:name": "TS25 1BE",
    "wof:placetype": "postalcode"
  },
  "geometry": {"coordinates":[-1.189651,54.661653],"type":"Point"}
}
