{
  "type": "Feature",
  "properties": {
    "iso:country":"GB",
    "wof:name":"SW14 7BN",
    "wof:placetype":"postalcode"
},
  "geometry": {"coordinates":[-0.27584455130503,51.46656834912379],"type":"Point"}
}