{
  "type": "Feature",
  "properties": {
    "date:inception_lower": "1980-01-01",
    "date:inception_upper": "1980-01-01",
    "iso:country": "GB",
    "wof:name": "EH22 3LZ",
    "wof:placetype": "postalcode"
  },
  "geometry": {"coordinates":[-3.081251,55.873784],"type":"Point"}
}
