{
  "type": "Feature",
  "properties": {
    "iso:country":"GB",
    "wof:name":"EH22 3LZ",
    "wof:placetype":"postalcode"
},
  "geometry": {"coordinates":[-3.08125150712612,55.87378397365186],"type":"Point"}
}