{
  "type": "Feature",
  "properties": {
    "iso:country": "GB",
    "wof:name": "WF4 2JH",
    "wof:placetype": "postalcode"
  },
  "geometry": {"coordinates":[-1.514114,53.613823],"type":"Point"}
}
