{
  "type": "Feature",
  "properties": {
    "iso:country":"GB",
    "wof:name":"WF4 2JH",
    "wof:placetype":"postalcode"
},
  "geometry": {"coordinates":[-1.51411368974652,53.61382311306777],"type":"Point"}
}