{
  "type": "Feature",
  "properties": {
    "iso:country":"GB",
    "wof:name":"TW7 6HU",
    "wof:placetype":"postalcode"
},
  "geometry": {"coordinates":[-0.33743740799954,51.46808733417501],"type":"Point"}
}