{
  "type": "Feature",
  "properties": {
    "date:inception_lower": "1980-01-01",
    "date:inception_upper": "1980-01-01",
    "iso:country": "GB",
    "wof:name": "TW7 6HU",
    "wof:placetype": "postalcode"
  },
  "geometry": {"coordinates":[-0.337437,51.468087],"type":"Point"}
}
