{
  "type": "Feature",
  "properties": {
    "date:inception_lower": "1999-12-01",
    "date:inception_upper": "1999-12-01",
    "iso:country": "GB",
    "wof:name": "G45 9UU",
    "wof:placetype": "postalcode"
  },
  "geometry": {"coordinates":[-4.232904,55.799271],"type":"Point"}
}
