{
  "type": "Feature",
  "properties": {
    "iso:country":"GB",
    "wof:name":"RG7 6LB",
    "wof:placetype":"postalcode"
},
  "geometry": {"coordinates":[-1.1555073155479,51.43636841737816],"type":"Point"}
}