{
  "type": "Feature",
  "properties": {
    "iso:country": "GB",
    "wof:name": "L11 2TF",
    "wof:placetype": "postalcode"
  },
  "geometry": {"coordinates":[-2.911171,53.443688],"type":"Point"}
}
