{
  "type": "Feature",
  "properties": {
    "date:inception_lower": "1980-01-01",
    "date:inception_upper": "1980-01-01",
    "iso:country": "GB",
    "wof:name": "DH9 7JF",
    "wof:placetype": "postalcode"
  },
  "geometry": {"coordinates":[-1.724832,54.858985],"type":"Point"}
}
