{
  "type": "Feature",
  "properties": {
    "iso:country":"GB",
    "wof:name":"DH9 7JF",
    "wof:placetype":"postalcode"
},
  "geometry": {"coordinates":[-1.72482081374685,54.85897692214256],"type":"Point"}
}