{
  "type": "Feature",
  "properties": {
    "iso:country":"GB",
    "wof:name":"BB4 9DS",
    "wof:placetype":"postalcode"
},
  "geometry": {"coordinates":[-2.25044010711563,53.69996951282604],"type":"Point"}
}