{
  "type": "Feature",
  "properties": {
    "date:inception_lower": "1980-01-01",
    "date:inception_upper": "1980-01-01",
    "iso:country": "GB",
    "wof:name": "BB4 9DS",
    "wof:placetype": "postalcode"
  },
  "geometry": {"coordinates":[-2.25044,53.69997],"type":"Point"}
}
