{
  "type": "Feature",
  "properties": {
    "iso:country":"GB",
    "wof:name":"HD8 9BU",
    "wof:placetype":"postalcode"
},
  "geometry": {"coordinates":[-1.65804296494611,53.58796685535629],"type":"Point"}
}