{
  "type": "Feature",
  "properties": {
    "date:inception_lower":"2013-12-01",
    "date:inception_upper":"2013-12-31",
    "iso:country":"GB",
    "wof:name":"ME2 1FR",
    "wof:placetype":"postalcode"
},
  "geometry": {"coordinates":[0.443304,51.3602],"type":"Point"}
}