{
  "type": "Feature",
  "properties": {
    "iso:country":"GB",
    "wof:name":"BN22 0TE",
    "wof:placetype":"postalcode"
},
  "geometry": {"coordinates":[0.27088626513729,50.80377363393949],"type":"Point"}
}