{
  "type": "Feature",
  "properties": {
    "iso:country": "GB",
    "wof:name": "BN22 0TE",
    "wof:placetype": "postalcode"
  },
  "geometry": {"coordinates":[0.270886,50.803774],"type":"Point"}
}
