{
  "type": "Feature",
  "properties": {
    "iso:country": "GB",
    "wof:name": "SE14 6HZ",
    "wof:placetype": "postalcode"
  },
  "geometry": {"coordinates":[-0.037726,51.480028],"type":"Point"}
}
