{
  "type": "Feature",
  "properties": {
    "iso:country":"GB",
    "wof:name":"TS6 0PP",
    "wof:placetype":"postalcode"
},
  "geometry": {"coordinates":[-1.15212821415623,54.55020879660566],"type":"Point"}
}