{
  "type": "Feature",
  "properties": {
    "iso:country":"GB",
    "wof:name":"WV10 0NF",
    "wof:placetype":"postalcode"
},
  "geometry": {"coordinates":[-2.10167373949297,52.60243225805078],"type":"Point"}
}