{
  "type": "Feature",
  "properties": {
    "iso:country":"GB",
    "wof:name":"SA10 7NB",
    "wof:placetype":"postalcode"
},
  "geometry": {"coordinates":[-3.83485836602397,51.66112124021899],"type":"Point"}
}