{
  "type": "Feature",
  "properties": {
    "iso:country":"GB",
    "wof:name":"E1 2LL",
    "wof:placetype":"postalcode"
},
  "geometry": {"coordinates":[-0.06290102763402,51.5133144480173],"type":"Point"}
}