{
  "type": "Feature",
  "properties": {
    "iso:country":"GB",
    "wof:name":"CH43 1YR",
    "wof:placetype":"postalcode"
},
  "geometry": {"coordinates":[-3.04662687387551,53.38663206139815],"type":"Point"}
}