{
  "type": "Feature",
  "properties": {
    "iso:country": "GB",
    "wof:name": "CH43 1YR",
    "wof:placetype": "postalcode"
  },
  "geometry": {"coordinates":[-3.046627,53.386632],"type":"Point"}
}
