{
  "type": "Feature",
  "properties": {
    "iso:country":"GB",
    "wof:name":"TQ1 3EU",
    "wof:placetype":"postalcode"
},
  "geometry": {"coordinates":[-3.53526885867047,50.47102328681599],"type":"Point"}
}