{
  "type": "Feature",
  "properties": {
    "iso:country":"GB",
    "wof:name":"BB12 7AP",
    "wof:placetype":"postalcode"
},
  "geometry": {"coordinates":[-2.31291785643954,53.79761267710634],"type":"Point"}
}