{
  "type": "Feature",
  "properties": {
    "iso:country": "GB",
    "wof:name": "CM12 9EE",
    "wof:placetype": "postalcode"
  },
  "geometry": {"coordinates":[0.414993,51.629245],"type":"Point"}
}
