{
  "type": "Feature",
  "properties": {
    "date:inception_lower": "1980-01-01",
    "date:inception_upper": "1980-01-01",
    "iso:country": "GB",
    "wof:name": "WA7 5SQ",
    "wof:placetype": "postalcode"
  },
  "geometry": {"coordinates":[-2.720954,53.34018],"type":"Point"}
}
