{
  "type": "Feature",
  "properties": {
    "date:inception_lower": "2006-09-01",
    "date:inception_upper": "2006-09-01",
    "iso:country": "GB",
    "wof:name": "CB23 4NB",
    "wof:placetype": "postalcode"
  },
  "geometry": {"coordinates":[-0.026143,52.259399],"type":"Point"}
}
