{
  "type": "Feature",
  "properties": {
    "iso:country": "GB",
    "wof:name": "CT2 8PE",
    "wof:placetype": "postalcode"
  },
  "geometry": {"coordinates":[1.058321,51.279523],"type":"Point"}
}
