{
  "type": "Feature",
  "properties": {
    "date:inception_lower": "1980-01-01",
    "date:inception_upper": "1980-01-01",
    "iso:country": "GB",
    "wof:name": "SS4 3DB",
    "wof:placetype": "postalcode"
  },
  "geometry": {"coordinates":[0.695851,51.598559],"type":"Point"}
}
