{
  "type": "Feature",
  "properties": {
    "iso:country":"GB",
    "wof:name":"CB24 5JS",
    "wof:placetype":"postalcode"
},
  "geometry": {"coordinates":[0.05632433044108,52.31035039699766],"type":"Point"}
}