{
  "type": "Feature",
  "properties": {
    "iso:country":"GB",
    "wof:name":"AB30 1YX",
    "wof:placetype":"postalcode"
},
  "geometry": {"coordinates":[-2.55605650818215,56.80799235756933],"type":"Point"}
}