{
  "type": "Feature",
  "properties": {
    "iso:country":"GB",
    "wof:name":"SN5 5QT",
    "wof:placetype":"postalcode"
},
  "geometry": {"coordinates":[-1.83066413730649,51.57019291270771],"type":"Point"}
}