{
  "type": "Feature",
  "properties": {
    "iso:country":"GB",
    "wof:name":"GU35 8BW",
    "wof:placetype":"postalcode"
},
  "geometry": {"coordinates":[-0.80675537520082,51.12442803916782],"type":"Point"}
}