{
  "type": "Feature",
  "properties": {
    "iso:country": "GB",
    "wof:name": "GU35 8BW",
    "wof:placetype": "postalcode"
  },
  "geometry": {"coordinates":[-0.806998,51.124457],"type":"Point"}
}
