{
  "type": "Feature",
  "properties": {
    "iso:country":"GB",
    "wof:name":"ML11 0LE",
    "wof:placetype":"postalcode"
},
  "geometry": {"coordinates":[-3.8805682183025,55.59069458619538],"type":"Point"}
}