{
  "type": "Feature",
  "properties": {
    "date:inception_lower":"2018-07-01",
    "date:inception_upper":"2018-07-31",
    "iso:country":"GB",
    "wof:name":"RG5 4BJ",
    "wof:placetype":"postalcode"
},
  "geometry": {"coordinates":[-0.876165,51.458987],"type":"Point"}
}