{
  "type": "Feature",
  "properties": {
    "iso:country": "GB",
    "wof:name": "RG5 4BJ",
    "wof:placetype": "postalcode"
  },
  "geometry": {"coordinates":[-0.876165,51.458987],"type":"Point"}
}
