{
  "type": "Feature",
  "properties": {
    "iso:country":"GB",
    "wof:name":"M25 1QZ",
    "wof:placetype":"postalcode"
},
  "geometry": {"coordinates":[-2.26878257356578,53.53592101211151],"type":"Point"}
}