{
  "type": "Feature",
  "properties": {
    "iso:country":"GB",
    "wof:name":"ML5 4FF",
    "wof:placetype":"postalcode"
},
  "geometry": {"coordinates":[-4.00820586740615,55.84748943278782],"type":"Point"}
}