{
  "type": "Feature",
  "properties": {
    "iso:country": "GB",
    "wof:name": "DN33 3GE",
    "wof:placetype": "postalcode"
  },
  "geometry": {"coordinates":[-0.112046,53.542501],"type":"Point"}
}
