{
  "type": "Feature",
  "properties": {
    "iso:country":"GB",
    "wof:name":"ME2 4GJ",
    "wof:placetype":"postalcode"
},
  "geometry": {"coordinates":[0.49729447746078,51.39912682184647],"type":"Point"}
}