{
  "type": "Feature",
  "properties": {
    "date:inception_lower": "2009-07-01",
    "date:inception_upper": "2009-07-01",
    "iso:country": "GB",
    "wof:name": "ME2 4GJ",
    "wof:placetype": "postalcode"
  },
  "geometry": {"coordinates":[0.49749,51.399285],"type":"Point"}
}
