{
  "type": "Feature",
  "properties": {
    "iso:country": "GB",
    "wof:name": "ME2 4GJ",
    "wof:placetype": "postalcode"
  },
  "geometry": {"coordinates":[0.49749,51.399285],"type":"Point"}
}
