{
  "type": "Feature",
  "properties": {
    "iso:country":"GB",
    "wof:name":"RH4 3AP",
    "wof:placetype":"postalcode"
},
  "geometry": {"coordinates":[-0.33577432936645,51.22013957725571],"type":"Point"}
}