{
  "type": "Feature",
  "properties": {
    "iso:country": "GB",
    "wof:name": "RH4 3AP",
    "wof:placetype": "postalcode"
  },
  "geometry": {"coordinates":[-0.335774,51.22014],"type":"Point"}
}
