{
  "type": "Feature",
  "properties": {
    "iso:country":"GB",
    "wof:name":"L20 6NG",
    "wof:placetype":"postalcode"
},
  "geometry": {"coordinates":[-2.98733893620819,53.46510698268467],"type":"Point"}
}