{
  "type": "Feature",
  "properties": {
    "date:inception_lower":"1980-01-01",
    "date:inception_upper":"1980-01-31",
    "iso:country":"GB",
    "wof:name":"IP28 7HZ",
    "wof:placetype":"postalcode"
},
  "geometry": {"coordinates":[0.523658,52.345961],"type":"Point"}
}