{
  "type": "Feature",
  "properties": {
    "date:inception_lower": "1981-06-01",
    "date:inception_upper": "1981-06-01",
    "iso:country": "GB",
    "wof:name": "WA7 6EL",
    "wof:placetype": "postalcode"
  },
  "geometry": {"coordinates":[-2.675835,53.318242],"type":"Point"}
}
