{
  "type": "Feature",
  "properties": {
    "iso:country":"GB",
    "wof:name":"WA7 6EL",
    "wof:placetype":"postalcode"
},
  "geometry": {"coordinates":[-2.67583498245913,53.31824211450702],"type":"Point"}
}