{
  "type": "Feature",
  "properties": {
    "date:inception_lower": "2018-01-01",
    "date:inception_upper": "2018-01-01",
    "iso:country": "GB",
    "wof:name": "DL12 0BE",
    "wof:placetype": "postalcode"
  },
  "geometry": {"coordinates":[-2.084044,54.624826],"type":"Point"}
}
