{
  "type": "Feature",
  "properties": {
    "date:inception_lower":"2013-01-01",
    "date:inception_upper":"2013-01-31",
    "iso:country":"GB",
    "wof:name":"SK17 9BF",
    "wof:placetype":"postalcode"
},
  "geometry": {"coordinates":[-1.923428,53.25448],"type":"Point"}
}