{
  "type": "Feature",
  "properties": {
    "iso:country": "GB",
    "wof:name": "SK17 9BF",
    "wof:placetype": "postalcode"
  },
  "geometry": {"coordinates":[-1.923428,53.25448],"type":"Point"}
}
