{
  "type": "Feature",
  "properties": {
    "iso:country":"GB",
    "wof:name":"SK17 9BF",
    "wof:placetype":"postalcode"
},
  "geometry": {"coordinates":[-1.92317369890152,53.25421882712055],"type":"Point"}
}