{
  "type": "Feature",
  "properties": {
    "date:inception_lower":"1980-01-01",
    "date:inception_upper":"1980-01-31",
    "iso:country":"GB",
    "wof:name":"LL14 3YF",
    "wof:placetype":"postalcode"
},
  "geometry": {"coordinates":[-3.068776,52.9769],"type":"Point"}
}