{
  "type": "Feature",
  "properties": {
    "iso:country":"GB",
    "wof:name":"LL14 3YF",
    "wof:placetype":"postalcode"
},
  "geometry": {"coordinates":[-3.06877627568052,52.97689997824713],"type":"Point"}
}