{
  "type": "Feature",
  "properties": {
    "iso:country": "GB",
    "wof:name": "LL14 3YF",
    "wof:placetype": "postalcode"
  },
  "geometry": {"coordinates":[-3.068776,52.9769],"type":"Point"}
}
