{
  "type": "Feature",
  "properties": {
    "iso:country": "GB",
    "wof:name": "DE11 9HJ",
    "wof:placetype": "postalcode"
  },
  "geometry": {"coordinates":[-1.575939,52.760566],"type":"Point"}
}
