{
  "type": "Feature",
  "properties": {
    "date:inception_lower": "1980-01-01",
    "date:inception_upper": "1980-01-01",
    "iso:country": "GB",
    "wof:name": "TW20 0DY",
    "wof:placetype": "postalcode"
  },
  "geometry": {"coordinates":[-0.580814,51.43217],"type":"Point"}
}
