{
  "type": "Feature",
  "properties": {
    "iso:country":"GB",
    "wof:name":"TW20 0DY",
    "wof:placetype":"postalcode"
},
  "geometry": {"coordinates":[-0.58081420377911,51.43216952606974],"type":"Point"}
}