{
  "type": "Feature",
  "properties": {
    "date:inception_lower":"1995-12-01",
    "date:inception_upper":"1995-12-31",
    "iso:country":"GB",
    "wof:name":"ML3 0NZ",
    "wof:placetype":"postalcode"
},
  "geometry": {"coordinates":[-4.068791,55.780331],"type":"Point"}
}