{
  "type": "Feature",
  "properties": {
    "iso:country":"GB",
    "wof:name":"ML3 0NZ",
    "wof:placetype":"postalcode"
},
  "geometry": {"coordinates":[-4.06879133402732,55.7803312113659],"type":"Point"}
}