{
  "type": "Feature",
  "properties": {
    "iso:country":"GB",
    "wof:name":"N22 6NE",
    "wof:placetype":"postalcode"
},
  "geometry": {"coordinates":[-0.10502113704775,51.59712012260057],"type":"Point"}
}