{
  "type": "Feature",
  "properties": {
    "iso:country":"GB",
    "wof:name":"WN2 4QS",
    "wof:placetype":"postalcode"
},
  "geometry": {"coordinates":[-2.55404665132159,53.52863806209194],"type":"Point"}
}