{
  "type": "Feature",
  "properties": {
    "iso:country":"GB",
    "wof:name":"TW1 3LS",
    "wof:placetype":"postalcode"
},
  "geometry": {"coordinates":[-0.32647961725384,51.44844495958765],"type":"Point"}
}