{
  "type": "Feature",
  "properties": {
    "date:inception_lower": "2002-05-01",
    "date:inception_upper": "2002-05-01",
    "iso:country": "GB",
    "wof:name": "CV6 4PZ",
    "wof:placetype": "postalcode"
  },
  "geometry": {"coordinates":[-1.517011,52.452457],"type":"Point"}
}
