{
  "type": "Feature",
  "properties": {
    "iso:country":"GB",
    "wof:name":"NG24 3QX",
    "wof:placetype":"postalcode"
},
  "geometry": {"coordinates":[-0.77887902441942,53.06063312207637],"type":"Point"}
}