{
  "type": "Feature",
  "properties": {
    "date:inception_lower": "2002-06-01",
    "date:inception_upper": "2002-06-01",
    "iso:country": "GB",
    "wof:name": "PO20 1AT",
    "wof:placetype": "postalcode"
  },
  "geometry": {"coordinates":[-0.781758,50.80696],"type":"Point"}
}
