{
  "type": "Feature",
  "properties": {
    "iso:country":"GB",
    "wof:name":"PO20 1AT",
    "wof:placetype":"postalcode"
},
  "geometry": {"coordinates":[-0.78193660460815,50.80682851855727],"type":"Point"}
}