{
  "type": "Feature",
  "properties": {
    "iso:country":"GB",
    "wof:name":"LU1 2SJ",
    "wof:placetype":"postalcode"
},
  "geometry": {"coordinates":[-0.41681117081726,51.87745800055652],"type":"Point"}
}