{
  "type": "Feature",
  "properties": {
    "iso:country":"GB",
    "wof:name":"DY11 6NH",
    "wof:placetype":"postalcode"
},
  "geometry": {"coordinates":[-2.26532386088793,52.37884063860236],"type":"Point"}
}