{
  "type": "Feature",
  "properties": {
    "iso:country": "GB",
    "wof:name": "CA7 2DH",
    "wof:placetype": "postalcode"
  },
  "geometry": {"coordinates":[-3.330163,54.73946],"type":"Point"}
}
