{
  "type": "Feature",
  "properties": {
    "date:inception_lower": "2000-06-01",
    "date:inception_upper": "2000-06-01",
    "iso:country": "GB",
    "wof:name": "CA7 2DH",
    "wof:placetype": "postalcode"
  },
  "geometry": {"coordinates":[-3.330071,54.739479],"type":"Point"}
}
