{
  "type": "Feature",
  "properties": {
    "iso:country": "GB",
    "wof:name": "CA7 2DH",
    "wof:placetype": "postalcode"
  },
  "geometry": {"coordinates":[-3.330071,54.739479],"type":"Point"}
}
