{
  "type": "Feature",
  "properties": {
    "iso:country":"GB",
    "wof:name":"CA7 2DH",
    "wof:placetype":"postalcode"
},
  "geometry": {"coordinates":[-3.33006912410972,54.73947194656689],"type":"Point"}
}