{
  "type": "Feature",
  "properties": {
    "iso:country": "GB",
    "wof:name": "SR2 0LJ",
    "wof:placetype": "postalcode"
  },
  "geometry": {"coordinates":[-1.365786,54.86281],"type":"Point"}
}
