{
  "type": "Feature",
  "properties": {
    "iso:country":"GB",
    "wof:name":"SR2 0LJ",
    "wof:placetype":"postalcode"
},
  "geometry": {"coordinates":[-1.36578570850554,54.8628098017661],"type":"Point"}
}