{
  "type": "Feature",
  "properties": {
    "date:inception_lower":"2004-05-01",
    "date:inception_upper":"2004-05-31",
    "iso:country":"GB",
    "wof:name":"SR2 0LJ",
    "wof:placetype":"postalcode"
},
  "geometry": {"coordinates":[-1.365786,54.86281],"type":"Point"}
}