{
  "type": "Feature",
  "properties": {
    "date:inception_lower": "2016-08-01",
    "date:inception_upper": "2016-08-01",
    "iso:country": "GB",
    "wof:name": "NE1 3NP",
    "wof:placetype": "postalcode"
  },
  "geometry": {"coordinates":[-1.61275,54.968132],"type":"Point"}
}
