{
  "type": "Feature",
  "properties": {
    "iso:country": "GB",
    "wof:name": "UB4 0JQ",
    "wof:placetype": "postalcode"
  },
  "geometry": {"coordinates":[-0.397319,51.515663],"type":"Point"}
}
