{
  "type": "Feature",
  "properties": {
    "iso:country":"GB",
    "wof:name":"UB4 0JQ",
    "wof:placetype":"postalcode"
},
  "geometry": {"coordinates":[-0.39731884950522,51.51566286861588],"type":"Point"}
}