{
  "type": "Feature",
  "properties": {
    "iso:country":"GB",
    "wof:name":"KT20 5TF",
    "wof:placetype":"postalcode"
},
  "geometry": {"coordinates":[-0.23268214264316,51.29569599451388],"type":"Point"}
}