{
  "type": "Feature",
  "properties": {
    "iso:country": "GB",
    "wof:name": "KT20 5TF",
    "wof:placetype": "postalcode"
  },
  "geometry": {"coordinates":[-0.232533,51.295557],"type":"Point"}
}
