{
  "type": "Feature",
  "properties": {
    "iso:country": "GB",
    "wof:name": "PR6 0RP",
    "wof:placetype": "postalcode"
  },
  "geometry": {"coordinates":[-2.623303,53.651708],"type":"Point"}
}
