{
  "type": "Feature",
  "properties": {
    "iso:country":"GB",
    "wof:name":"TA4 2AW",
    "wof:placetype":"postalcode"
},
  "geometry": {"coordinates":[-3.32546174256815,51.01384574096107],"type":"Point"}
}