{
  "type": "Feature",
  "properties": {
    "date:inception_lower":"1980-01-01",
    "date:inception_upper":"1980-01-31",
    "iso:country":"GB",
    "wof:name":"TA4 2AW",
    "wof:placetype":"postalcode"
},
  "geometry": {"coordinates":[-3.325462,51.013846],"type":"Point"}
}