{
  "type": "Feature",
  "properties": {
    "iso:country":"GB",
    "wof:name":"NP11 7BX",
    "wof:placetype":"postalcode"
},
  "geometry": {"coordinates":[-3.12640613870021,51.62227363433401],"type":"Point"}
}