{
  "type": "Feature",
  "properties": {
    "iso:country":"GB",
    "wof:name":"WA15 8BW",
    "wof:placetype":"postalcode"
},
  "geometry": {"coordinates":[-2.32935939015522,53.38018722793298],"type":"Point"}
}