{
  "type": "Feature",
  "properties": {
    "date:inception_lower": "2000-12-01",
    "date:inception_upper": "2000-12-01",
    "iso:country": "GB",
    "wof:name": "CM5 9DQ",
    "wof:placetype": "postalcode"
  },
  "geometry": {"coordinates":[0.246059,51.696151],"type":"Point"}
}
