{
  "type": "Feature",
  "properties": {
    "iso:country":"GB",
    "wof:name":"CM5 9DQ",
    "wof:placetype":"postalcode"
},
  "geometry": {"coordinates":[0.24605850744343,51.69615097827973],"type":"Point"}
}