{
  "type": "Feature",
  "properties": {
    "iso:country":"GB",
    "wof:name":"DE22 4AD",
    "wof:placetype":"postalcode"
},
  "geometry": {"coordinates":[-1.51178885994163,52.92612193029234],"type":"Point"}
}