{
  "type": "Feature",
  "properties": {
    "iso:country": "GB",
    "wof:name": "DY5 3UP",
    "wof:placetype": "postalcode"
  },
  "geometry": {"coordinates":[-2.140427,52.485569],"type":"Point"}
}
