{
  "type": "Feature",
  "properties": {
    "iso:country": "GB",
    "wof:name": "EH48 2HQ",
    "wof:placetype": "postalcode"
  },
  "geometry": {"coordinates":[-3.65996,55.887072],"type":"Point"}
}
