{
  "type": "Feature",
  "properties": {
    "iso:country": "GB",
    "wof:name": "CH4 0EY",
    "wof:placetype": "postalcode"
  },
  "geometry": {"coordinates":[-3.044163,53.145526],"type":"Point"}
}
