{
  "type": "Feature",
  "properties": {
    "iso:country": "GB",
    "wof:name": "ML3 0GB",
    "wof:placetype": "postalcode"
  },
  "geometry": {"coordinates":[-4.071553,55.785192],"type":"Point"}
}
