{
  "type": "Feature",
  "properties": {
    "iso:country":"GB",
    "wof:name":"AL3 4JL",
    "wof:placetype":"postalcode"
},
  "geometry": {"coordinates":[-0.36602502826096,51.74460158659765],"type":"Point"}
}