{
  "type": "Feature",
  "properties": {
    "iso:country": "GB",
    "wof:name": "NE47 6AH",
    "wof:placetype": "postalcode"
  },
  "geometry": {"coordinates":[-2.24301,54.97255],"type":"Point"}
}
