{
  "type": "Feature",
  "properties": {
    "iso:country":"GB",
    "wof:name":"HG4 2TN",
    "wof:placetype":"postalcode"
},
  "geometry": {"coordinates":[-1.52879544267061,54.14138324104618],"type":"Point"}
}