{
  "type": "Feature",
  "properties": {
    "iso:country": "GB",
    "wof:name": "PL6 5UH",
    "wof:placetype": "postalcode"
  },
  "geometry": {"coordinates":[-4.105126,50.397996],"type":"Point"}
}
