{
  "type": "Feature",
  "properties": {
    "iso:country":"GB",
    "wof:name":"DE74 2LF",
    "wof:placetype":"postalcode"
},
  "geometry": {"coordinates":[-1.3373614008022,52.84133364857814],"type":"Point"}
}