{
  "type": "Feature",
  "properties": {
    "iso:country":"GB",
    "wof:name":"W1D 3QP",
    "wof:placetype":"postalcode"
},
  "geometry": {"coordinates":[-0.13155351709759,51.51559724188824],"type":"Point"}
}