{
  "type": "Feature",
  "properties": {
    "iso:country": "GB",
    "wof:name": "SA71 5PT",
    "wof:placetype": "postalcode"
  },
  "geometry": {"coordinates":[-4.908119,51.668413],"type":"Point"}
}
