{
  "type": "Feature",
  "properties": {
    "iso:country":"GB",
    "wof:name":"BR8 7DB",
    "wof:placetype":"postalcode"
},
  "geometry": {"coordinates":[0.16633597066556,51.39521020921736],"type":"Point"}
}