{
  "type": "Feature",
  "properties": {
    "iso:country": "GB",
    "wof:name": "BR8 7DB",
    "wof:placetype": "postalcode"
  },
  "geometry": {"coordinates":[0.166336,51.39521],"type":"Point"}
}
