{
  "type": "Feature",
  "properties": {
    "iso:country":"GB",
    "wof:name":"BB7 2LZ",
    "wof:placetype":"postalcode"
},
  "geometry": {"coordinates":[-2.41057607240118,53.86998564789993],"type":"Point"}
}