{
  "type": "Feature",
  "properties": {
    "date:inception_lower": "2021-05-01",
    "date:inception_upper": "2021-05-01",
    "iso:country": "GB",
    "wof:name": "PA7 5HZ",
    "wof:placetype": "postalcode"
  },
  "geometry": {"coordinates":[-4.506162,55.902941],"type":"Point"}
}
