{
  "type": "Feature",
  "properties": {
    "iso:country":"GB",
    "wof:name":"PA8 6JB",
    "wof:placetype":"postalcode"
},
  "geometry": {"coordinates":[-4.4629896544301,55.89829098947592],"type":"Point"}
}