{
  "type": "Feature",
  "properties": {
    "iso:country":"GB",
    "wof:name":"HA5 5PB",
    "wof:placetype":"postalcode"
},
  "geometry": {"coordinates":[-0.38162642013749,51.59159329329359],"type":"Point"}
}