{
  "type": "Feature",
  "properties": {
    "iso:country":"GB",
    "wof:name":"PE19 8EB",
    "wof:placetype":"postalcode"
},
  "geometry": {"coordinates":[-0.28794376409662,52.22022929448276],"type":"Point"}
}