{
  "type": "Feature",
  "properties": {
    "date:inception_lower":"2000-06-01",
    "date:inception_upper":"2000-06-30",
    "iso:country":"GB",
    "wof:name":"PE19 8EB",
    "wof:placetype":"postalcode"
},
  "geometry": {"coordinates":[-0.287944,52.220229],"type":"Point"}
}