{
  "type": "Feature",
  "properties": {
    "iso:country":"GB",
    "wof:name":"SO14 6TS",
    "wof:placetype":"postalcode"
},
  "geometry": {"coordinates":[-1.40326613396006,50.92001085327277],"type":"Point"}
}