{
  "type": "Feature",
  "properties": {
    "iso:country":"GB",
    "wof:name":"CF64 2LD",
    "wof:placetype":"postalcode"
},
  "geometry": {"coordinates":[-3.18495746984614,51.44256155388501],"type":"Point"}
}