{
  "type": "Feature",
  "properties": {
    "iso:country": "GB",
    "wof:name": "CF64 2LD",
    "wof:placetype": "postalcode"
  },
  "geometry": {"coordinates":[-3.184957,51.442562],"type":"Point"}
}
