{
  "type": "Feature",
  "properties": {
    "date:inception_lower": "1993-01-01",
    "date:inception_upper": "1993-01-01",
    "iso:country": "GB",
    "wof:name": "HA9 7NB",
    "wof:placetype": "postalcode"
  },
  "geometry": {"coordinates":[-0.302209,51.564315],"type":"Point"}
}
