{
  "type": "Feature",
  "properties": {
    "iso:country":"GB",
    "wof:name":"HA9 7NB",
    "wof:placetype":"postalcode"
},
  "geometry": {"coordinates":[-0.30219719531804,51.56408800454612],"type":"Point"}
}