{
  "type": "Feature",
  "properties": {
    "iso:country": "GB",
    "wof:name": "EX1 3HY",
    "wof:placetype": "postalcode"
  },
  "geometry": {"coordinates":[-3.488146,50.724154],"type":"Point"}
}
