{
  "type": "Feature",
  "properties": {
    "iso:country":"GB",
    "wof:name":"EX1 3HY",
    "wof:placetype":"postalcode"
},
  "geometry": {"coordinates":[-3.488146383399,50.72415355521581],"type":"Point"}
}