{
  "type": "Feature",
  "properties": {
    "iso:country":"GB",
    "wof:name":"AB45 1DB",
    "wof:placetype":"postalcode"
},
  "geometry": {"coordinates":[-2.52119596998636,57.66525911624568],"type":"Point"}
}