{
  "type": "Feature",
  "properties": {
    "iso:country":"GB",
    "wof:name":"TQ1 4RN",
    "wof:placetype":"postalcode"
},
  "geometry": {"coordinates":[-3.52982244978089,50.48521506310338],"type":"Point"}
}