{
  "type": "Feature",
  "properties": {
    "date:inception_lower": "1980-01-01",
    "date:inception_upper": "1980-01-01",
    "iso:country": "GB",
    "wof:name": "KW16 3NZ",
    "wof:placetype": "postalcode"
  },
  "geometry": {"coordinates":[-3.241871,58.78459],"type":"Point"}
}
