{
  "type": "Feature",
  "properties": {
    "iso:country":"GB",
    "wof:name":"CR2 0LS",
    "wof:placetype":"postalcode"
},
  "geometry": {"coordinates":[-0.09750598325539,51.34185103193168],"type":"Point"}
}