{
  "type": "Feature",
  "properties": {
    "iso:country": "GB",
    "wof:name": "CR2 0LS",
    "wof:placetype": "postalcode"
  },
  "geometry": {"coordinates":[-0.097506,51.341851],"type":"Point"}
}
