{
  "type": "Feature",
  "properties": {
    "iso:country": "GB",
    "wof:name": "BR8 7BY",
    "wof:placetype": "postalcode"
  },
  "geometry": {"coordinates":[0.167149,51.393558],"type":"Point"}
}
