{
  "type": "Feature",
  "properties": {
    "iso:country":"GB",
    "wof:name":"LE10 2HF",
    "wof:placetype":"postalcode"
},
  "geometry": {"coordinates":[-1.35013573052728,52.52485539356243],"type":"Point"}
}