{
  "type": "Feature",
  "properties": {
    "iso:country":"GB",
    "wof:name":"SE3 9LA",
    "wof:placetype":"postalcode"
},
  "geometry": {"coordinates":[0.0094713676785,51.4656763582891],"type":"Point"}
}