{
  "type": "Feature",
  "properties": {
    "iso:country":"GB",
    "wof:name":"TS23 4BL",
    "wof:placetype":"postalcode"
},
  "geometry": {"coordinates":[-1.27891004897447,54.60235543916425],"type":"Point"}
}