{
  "type": "Feature",
  "properties": {
    "iso:country":"GB",
    "wof:name":"LS14 3EQ",
    "wof:placetype":"postalcode"
},
  "geometry": {"coordinates":[-1.42168233962381,53.8611716677203],"type":"Point"}
}