{
  "type": "Feature",
  "properties": {
    "date:inception_lower":"2012-09-01",
    "date:inception_upper":"2012-09-30",
    "iso:country":"GB",
    "wof:name":"NE4 5SN",
    "wof:placetype":"postalcode"
},
  "geometry": {"coordinates":[-1.623312,54.97311],"type":"Point"}
}