{
  "type": "Feature",
  "properties": {
    "iso:country":"GB",
    "wof:name":"UB4 0PH",
    "wof:placetype":"postalcode"
},
  "geometry": {"coordinates":[-0.39493809625507,51.51697015950634],"type":"Point"}
}