{
  "type": "Feature",
  "properties": {
    "iso:country":"GB",
    "wof:name":"SE1 1XY",
    "wof:placetype":"postalcode"
},
  "geometry": {"coordinates":[-0.08916801962604,51.50416824652694],"type":"Point"}
}