{
  "type": "Feature",
  "properties": {
    "iso:country":"GB",
    "wof:name":"M9 6RD",
    "wof:placetype":"postalcode"
},
  "geometry": {"coordinates":[-2.21148938694051,53.53201838151747],"type":"Point"}
}