{
  "type": "Feature",
  "properties": {
    "date:inception_lower": "2021-04-01",
    "date:inception_upper": "2021-04-01",
    "iso:country": "GB",
    "wof:name": "ME16 9GU",
    "wof:placetype": "postalcode"
  },
  "geometry": {"coordinates":[0.477122,51.27101],"type":"Point"}
}
