{
  "type": "Feature",
  "properties": {
    "iso:country":"GB",
    "wof:name":"M19 2RU",
    "wof:placetype":"postalcode"
},
  "geometry": {"coordinates":[-2.18110076841845,53.43559537216346],"type":"Point"}
}