{
  "type": "Feature",
  "properties": {
    "date:inception_lower": "1980-01-01",
    "date:inception_upper": "1980-01-01",
    "iso:country": "GB",
    "wof:name": "M19 2RU",
    "wof:placetype": "postalcode"
  },
  "geometry": {"coordinates":[-2.181101,53.435595],"type":"Point"}
}
