{
  "type": "Feature",
  "properties": {
    "iso:country":"GB",
    "wof:name":"EX2 4HD",
    "wof:placetype":"postalcode"
},
  "geometry": {"coordinates":[-3.52480636804587,50.71871542772513],"type":"Point"}
}