{
  "type": "Feature",
  "properties": {
    "iso:country":"GB",
    "wof:name":"LL34 6PA",
    "wof:placetype":"postalcode"
},
  "geometry": {"coordinates":[-3.93652192825559,53.26635137348466],"type":"Point"}
}