{
  "type": "Feature",
  "properties": {
    "iso:country":"GB",
    "wof:name":"EX10 8PW",
    "wof:placetype":"postalcode"
},
  "geometry": {"coordinates":[-3.236600881004,50.68334219624101],"type":"Point"}
}