{
  "type": "Feature",
  "properties": {
    "iso:country":"GB",
    "wof:name":"NW2 4AN",
    "wof:placetype":"postalcode"
},
  "geometry": {"coordinates":[-0.22478053482829,51.55362627690176],"type":"Point"}
}