{
  "type": "Feature",
  "properties": {
    "iso:country":"GB",
    "wof:name":"CB2 8AA",
    "wof:placetype":"postalcode"
},
  "geometry": {"coordinates":[0.13130054233627,52.18956411708577],"type":"Point"}
}