{
  "type": "Feature",
  "properties": {
    "date:inception_lower": "2020-10-01",
    "date:inception_upper": "2020-10-01",
    "iso:country": "GB",
    "wof:name": "BA3 9DE",
    "wof:placetype": "postalcode"
  },
  "geometry": {"coordinates":[-2.446783,51.291455],"type":"Point"}
}
