{
  "type": "Feature",
  "properties": {
    "date:inception_lower": "1997-06-01",
    "date:inception_upper": "1997-06-01",
    "iso:country": "GB",
    "wof:name": "LE11 2SE",
    "wof:placetype": "postalcode"
  },
  "geometry": {"coordinates":[-1.211901,52.746616],"type":"Point"}
}
