{
  "type": "Feature",
  "properties": {
    "iso:country":"GB",
    "wof:name":"LE11 2SE",
    "wof:placetype":"postalcode"
},
  "geometry": {"coordinates":[-1.21190086324032,52.74661598006526],"type":"Point"}
}