{
  "type": "Feature",
  "properties": {
    "iso:country": "GB",
    "wof:name": "SK7 2RE",
    "wof:placetype": "postalcode"
  },
  "geometry": {"coordinates":[-2.167303,53.364093],"type":"Point"}
}
