{
  "type": "Feature",
  "properties": {
    "iso:country":"GB",
    "wof:name":"CV2 3PD",
    "wof:placetype":"postalcode"
},
  "geometry": {"coordinates":[-1.47119724342984,52.42099332074068],"type":"Point"}
}