{
  "type": "Feature",
  "properties": {
    "iso:country":"GB",
    "wof:name":"TR19 7RQ",
    "wof:placetype":"postalcode"
},
  "geometry": {"coordinates":[-5.66933398929994,50.11288169996095],"type":"Point"}
}