{
  "type": "Feature",
  "properties": {
    "iso:country":"GB",
    "wof:name":"BB12 9DE",
    "wof:placetype":"postalcode"
},
  "geometry": {"coordinates":[-2.29264589124435,53.82530190808065],"type":"Point"}
}