{
  "type": "Feature",
  "properties": {
    "iso:country": "GB",
    "wof:name": "BB12 9DE",
    "wof:placetype": "postalcode"
  },
  "geometry": {"coordinates":[-2.292646,53.825302],"type":"Point"}
}
