{
  "type": "Feature",
  "properties": {
    "iso:country": "GB",
    "wof:name": "MK17 0AS",
    "wof:placetype": "postalcode"
  },
  "geometry": {"coordinates":[-0.771654,51.97678],"type":"Point"}
}
