{
  "type": "Feature",
  "properties": {
    "iso:country":"GB",
    "wof:name":"MK17 0AS",
    "wof:placetype":"postalcode"
},
  "geometry": {"coordinates":[-0.77165398774191,51.97678001218051],"type":"Point"}
}