{
  "type": "Feature",
  "properties": {
    "date:inception_lower": "1980-01-01",
    "date:inception_upper": "1980-01-01",
    "iso:country": "GB",
    "wof:name": "TA8 2AF",
    "wof:placetype": "postalcode"
  },
  "geometry": {"coordinates":[-2.991647,51.24174],"type":"Point"}
}
