{
  "type": "Feature",
  "properties": {
    "iso:country":"GB",
    "wof:name":"TA8 2AF",
    "wof:placetype":"postalcode"
},
  "geometry": {"coordinates":[-2.99164662775899,51.2417398010353],"type":"Point"}
}