{
  "type": "Feature",
  "properties": {
    "date:inception_lower":"1980-01-01",
    "date:inception_upper":"1980-01-31",
    "iso:country":"GB",
    "wof:name":"TA11 6EJ",
    "wof:placetype":"postalcode"
},
  "geometry": {"coordinates":[-2.643614,51.071847],"type":"Point"}
}