{
  "type": "Feature",
  "properties": {
    "iso:country":"GB",
    "wof:name":"NG24 3FD",
    "wof:placetype":"postalcode"
},
  "geometry": {"coordinates":[-0.77172929671663,53.04810887141083],"type":"Point"}
}