{
  "type": "Feature",
  "properties": {
    "date:inception_lower": "2003-08-01",
    "date:inception_upper": "2003-08-01",
    "iso:country": "GB",
    "wof:name": "NG24 3FD",
    "wof:placetype": "postalcode"
  },
  "geometry": {"coordinates":[-0.771729,53.048109],"type":"Point"}
}
