{
  "type": "Feature",
  "properties": {
    "date:inception_lower": "1980-01-01",
    "date:inception_upper": "1980-01-01",
    "iso:country": "GB",
    "wof:name": "TW18 2SX",
    "wof:placetype": "postalcode"
  },
  "geometry": {"coordinates":[-0.492569,51.412553],"type":"Point"}
}
