{
  "type": "Feature",
  "properties": {
    "date:inception_lower":"1984-10-01",
    "date:inception_upper":"1984-10-31",
    "iso:country":"GB",
    "wof:name":"B5 4RW",
    "wof:placetype":"postalcode"
},
  "geometry": {"coordinates":[-1.895081,52.476128],"type":"Point"}
}