{
  "type": "Feature",
  "properties": {
    "iso:country":"GB",
    "wof:name":"TN6 2PW",
    "wof:placetype":"postalcode"
},
  "geometry": {"coordinates":[0.17354263514889,51.04662294506334],"type":"Point"}
}