{
  "type": "Feature",
  "properties": {
    "iso:country":"GB",
    "wof:name":"M8 4QH",
    "wof:placetype":"postalcode"
},
  "geometry": {"coordinates":[-2.23587233525089,53.51902045090694],"type":"Point"}
}