{
  "type": "Feature",
  "properties": {
    "iso:country": "GB",
    "wof:name": "M8 4QH",
    "wof:placetype": "postalcode"
  },
  "geometry": {"coordinates":[-2.235872,53.51902],"type":"Point"}
}
