{
  "type": "Feature",
  "properties": {
    "iso:country":"GB",
    "wof:name":"CO10 7NU",
    "wof:placetype":"postalcode"
},
  "geometry": {"coordinates":[0.7176315771119,52.03181465668055],"type":"Point"}
}