{
  "type": "Feature",
  "properties": {
    "iso:country":"GB",
    "wof:name":"CF40 1RS",
    "wof:placetype":"postalcode"
},
  "geometry": {"coordinates":[-3.44090178206602,51.60445602384587],"type":"Point"}
}