{
  "type": "Feature",
  "properties": {
    "iso:country":"GB",
    "wof:name":"WA14 3LP",
    "wof:placetype":"postalcode"
},
  "geometry": {"coordinates":[-2.37573030226874,53.37445026852652],"type":"Point"}
}