{
  "type": "Feature",
  "properties": {
    "iso:country":"GB",
    "wof:name":"SR4 7YQ",
    "wof:placetype":"postalcode"
},
  "geometry": {"coordinates":[-1.40283144377024,54.90618658420532],"type":"Point"}
}