{
  "type": "Feature",
  "properties": {
    "date:inception_lower": "1980-01-01",
    "date:inception_upper": "1980-01-01",
    "iso:country": "GB",
    "wof:name": "ME13 9JS",
    "wof:placetype": "postalcode"
  },
  "geometry": {"coordinates":[0.963311,51.309599],"type":"Point"}
}
