{
  "type": "Feature",
  "properties": {
    "iso:country":"GB",
    "wof:name":"ME13 9JS",
    "wof:placetype":"postalcode"
},
  "geometry": {"coordinates":[0.96331046173279,51.3095986909462],"type":"Point"}
}