{
  "type": "Feature",
  "properties": {
    "iso:country":"GB",
    "wof:name":"AB56 5ET",
    "wof:placetype":"postalcode"
},
  "geometry": {"coordinates":[-2.99740071431944,57.61886034210551],"type":"Point"}
}