{
  "type": "Feature",
  "properties": {
    "iso:country":"GB",
    "wof:name":"CB24 5NX",
    "wof:placetype":"postalcode"
},
  "geometry": {"coordinates":[0.01293155837232,52.31846212331671],"type":"Point"}
}