{
  "type": "Feature",
  "properties": {
    "iso:country":"GB",
    "wof:name":"SK4 5LF",
    "wof:placetype":"postalcode"
},
  "geometry": {"coordinates":[-2.16992873264913,53.43479385625894],"type":"Point"}
}