{
  "type": "Feature",
  "properties": {
    "date:inception_lower": "2005-07-01",
    "date:inception_upper": "2005-07-01",
    "iso:country": "GB",
    "wof:name": "LN6 3LH",
    "wof:placetype": "postalcode"
  },
  "geometry": {"coordinates":[-0.60909,53.206051],"type":"Point"}
}
