{
  "type": "Feature",
  "properties": {
    "date:inception_lower":"1980-01-01",
    "date:inception_upper":"1980-01-31",
    "iso:country":"GB",
    "wof:name":"BD20 6RF",
    "wof:placetype":"postalcode"
},
  "geometry": {"coordinates":[-1.959131,53.900279],"type":"Point"}
}