{
  "type": "Feature",
  "properties": {
    "iso:country":"GB",
    "wof:name":"SA9 1NU",
    "wof:placetype":"postalcode"
},
  "geometry": {"coordinates":[-3.75690465337264,51.77708891567087],"type":"Point"}
}