{
  "type": "Feature",
  "properties": {
    "iso:country": "GB",
    "wof:name": "KA7 3SP",
    "wof:placetype": "postalcode"
  },
  "geometry": {"coordinates":[-4.612703,55.444429],"type":"Point"}
}
