{
  "type": "Feature",
  "properties": {
    "iso:country": "GB",
    "wof:name": "CB8 8DA",
    "wof:placetype": "postalcode"
  },
  "geometry": {"coordinates":[0.426189,52.239062],"type":"Point"}
}
