{
  "type": "Feature",
  "properties": {
    "iso:country":"GB",
    "wof:name":"CB8 8DA",
    "wof:placetype":"postalcode"
},
  "geometry": {"coordinates":[0.42618940010684,52.23906203511929],"type":"Point"}
}