{
  "type": "Feature",
  "properties": {
    "date:inception_lower": "1980-01-01",
    "date:inception_upper": "1980-01-01",
    "iso:country": "GB",
    "wof:name": "CB8 8DA",
    "wof:placetype": "postalcode"
  },
  "geometry": {"coordinates":[0.426073,52.239108],"type":"Point"}
}
