{
  "type": "Feature",
  "properties": {
    "iso:country":"GB",
    "wof:name":"SW4 0NU",
    "wof:placetype":"postalcode"
},
  "geometry": {"coordinates":[-0.14767096375249,51.46325557123853],"type":"Point"}
}