{
  "type": "Feature",
  "properties": {
    "iso:country":"GB",
    "wof:name":"LL31 9DJ",
    "wof:placetype":"postalcode"
},
  "geometry": {"coordinates":[-3.82764773024068,53.29072550027411],"type":"Point"}
}