{
  "type": "Feature",
  "properties": {
    "iso:country": "GB",
    "wof:name": "LL31 9DJ",
    "wof:placetype": "postalcode"
  },
  "geometry": {"coordinates":[-3.829089,53.291385],"type":"Point"}
}
