{
  "type": "Feature",
  "properties": {
    "iso:country":"GB",
    "wof:name":"DE7 4RL",
    "wof:placetype":"postalcode"
},
  "geometry": {"coordinates":[-1.29689204500679,52.95515978362653],"type":"Point"}
}