{
  "type": "Feature",
  "properties": {
    "date:inception_lower": "2008-07-01",
    "date:inception_upper": "2008-07-01",
    "iso:country": "GB",
    "wof:name": "DE7 4RL",
    "wof:placetype": "postalcode"
  },
  "geometry": {"coordinates":[-1.296892,52.95516],"type":"Point"}
}
