{
  "type": "Feature",
  "properties": {
    "iso:country":"GB",
    "wof:name":"L35 5DH",
    "wof:placetype":"postalcode"
},
  "geometry": {"coordinates":[-2.79754940397093,53.42132950786566],"type":"Point"}
}