{
  "type": "Feature",
  "properties": {
    "iso:country": "GB",
    "wof:name": "L35 5DH",
    "wof:placetype": "postalcode"
  },
  "geometry": {"coordinates":[-2.797549,53.42133],"type":"Point"}
}
