{
  "type": "Feature",
  "properties": {
    "date:inception_lower": "1998-12-01",
    "date:inception_upper": "1998-12-01",
    "iso:country": "GB",
    "wof:name": "CB1 7BJ",
    "wof:placetype": "postalcode"
  },
  "geometry": {"coordinates":[0.142108,52.188253],"type":"Point"}
}
