{
  "type": "Feature",
  "properties": {
    "iso:country":"GB",
    "wof:name":"SK14 3QP",
    "wof:placetype":"postalcode"
},
  "geometry": {"coordinates":[-2.02707770163935,53.44707339631008],"type":"Point"}
}