{
  "type": "Feature",
  "properties": {
    "iso:country": "GB",
    "wof:name": "SK14 3QP",
    "wof:placetype": "postalcode"
  },
  "geometry": {"coordinates":[-2.026836,53.447287],"type":"Point"}
}
