{
  "type": "Feature",
  "properties": {
    "date:inception_lower": "2018-06-01",
    "date:inception_upper": "2018-06-01",
    "iso:country": "GB",
    "wof:name": "WA10 1GL",
    "wof:placetype": "postalcode"
  },
  "geometry": {"coordinates":[-2.738604,53.455001],"type":"Point"}
}
