{
  "type": "Feature",
  "properties": {
    "iso:country":"GB",
    "wof:name":"B12 9PH",
    "wof:placetype":"postalcode"
},
  "geometry": {"coordinates":[-1.89409285184652,52.4541857598355],"type":"Point"}
}