{
  "type": "Feature",
  "properties": {
    "date:inception_lower":"2009-11-01",
    "date:inception_upper":"2009-11-30",
    "iso:country":"GB",
    "wof:name":"G5 0HZ",
    "wof:placetype":"postalcode"
},
  "geometry": {"coordinates":[-4.237462,55.841685],"type":"Point"}
}