{
  "type": "Feature",
  "properties": {
    "iso:country":"GB",
    "wof:name":"DL9 3AJ",
    "wof:placetype":"postalcode"
},
  "geometry": {"coordinates":[-1.73540713730413,54.38454497677579],"type":"Point"}
}