{
  "type": "Feature",
  "properties": {
    "iso:country":"GB",
    "wof:name":"SL3 8UL",
    "wof:placetype":"postalcode"
},
  "geometry": {"coordinates":[-0.53887620965282,51.49493224435411],"type":"Point"}
}