{
  "type": "Feature",
  "properties": {
    "iso:country":"GB",
    "wof:name":"E13 8LF",
    "wof:placetype":"postalcode"
},
  "geometry": {"coordinates":[0.02696348359742,51.5211931271747],"type":"Point"}
}