{
  "type": "Feature",
  "properties": {
    "date:inception_lower": "2005-09-01",
    "date:inception_upper": "2005-09-01",
    "iso:country": "GB",
    "wof:name": "E13 8LF",
    "wof:placetype": "postalcode"
  },
  "geometry": {"coordinates":[0.026964,51.521193],"type":"Point"}
}
