{
  "type": "Feature",
  "properties": {
    "date:inception_lower": "1996-06-01",
    "date:inception_upper": "1996-06-01",
    "iso:country": "GB",
    "wof:name": "CB9 0PH",
    "wof:placetype": "postalcode"
  },
  "geometry": {"coordinates":[0.454302,52.08051],"type":"Point"}
}
