{
  "type": "Feature",
  "properties": {
    "iso:country":"GB",
    "wof:name":"CB9 0PH",
    "wof:placetype":"postalcode"
},
  "geometry": {"coordinates":[0.45430173742042,52.0805096656545],"type":"Point"}
}