{
  "type": "Feature",
  "properties": {
    "date:inception_lower":"2002-11-01",
    "date:inception_upper":"2002-11-30",
    "iso:country":"GB",
    "wof:name":"BN9 9BW",
    "wof:placetype":"postalcode"
},
  "geometry": {"coordinates":[0.052454,50.78916],"type":"Point"}
}