{
  "type": "Feature",
  "properties": {
    "iso:country":"GB",
    "wof:name":"BN9 9BW",
    "wof:placetype":"postalcode"
},
  "geometry": {"coordinates":[0.05245400253975,50.78916016424304],"type":"Point"}
}