{
  "type": "Feature",
  "properties": {
    "iso:country": "GB",
    "wof:name": "BN9 9BW",
    "wof:placetype": "postalcode"
  },
  "geometry": {"coordinates":[0.052454,50.78916],"type":"Point"}
}
