{
  "type": "Feature",
  "properties": {
    "iso:country": "GB",
    "wof:name": "CT9 1TT",
    "wof:placetype": "postalcode"
  },
  "geometry": {"coordinates":[1.389227,51.383122],"type":"Point"}
}
