{
  "type": "Feature",
  "properties": {
    "iso:country":"GB",
    "wof:name":"CT9 1TT",
    "wof:placetype":"postalcode"
},
  "geometry": {"coordinates":[1.38922738273873,51.38312171808322],"type":"Point"}
}