{
  "type": "Feature",
  "properties": {
    "date:inception_lower": "1980-01-01",
    "date:inception_upper": "1980-01-01",
    "iso:country": "GB",
    "wof:name": "CT9 1TT",
    "wof:placetype": "postalcode"
  },
  "geometry": {"coordinates":[1.389227,51.383122],"type":"Point"}
}
