{
  "type": "Feature",
  "properties": {
    "iso:country":"GB",
    "wof:name":"OX18 1DY",
    "wof:placetype":"postalcode"
},
  "geometry": {"coordinates":[-1.60035979658471,51.77393435240967],"type":"Point"}
}