{
  "type": "Feature",
  "properties": {
    "iso:country": "GB",
    "wof:name": "OX18 1DY",
    "wof:placetype": "postalcode"
  },
  "geometry": {"coordinates":[-1.600345,51.77394],"type":"Point"}
}
