{
  "type": "Feature",
  "properties": {
    "iso:country":"GB",
    "wof:name":"LA19 5TJ",
    "wof:placetype":"postalcode"
},
  "geometry": {"coordinates":[-3.37343216557682,54.28775092629492],"type":"Point"}
}