{
  "type": "Feature",
  "properties": {
    "iso:country": "GB",
    "wof:name": "LA19 5TJ",
    "wof:placetype": "postalcode"
  },
  "geometry": {"coordinates":[-3.373432,54.287751],"type":"Point"}
}
