{
  "type": "Feature",
  "properties": {
    "iso:country": "GB",
    "wof:name": "WN6 7GA",
    "wof:placetype": "postalcode"
  },
  "geometry": {"coordinates":[-2.658714,53.554198],"type":"Point"}
}
