{
  "type": "Feature",
  "properties": {
    "iso:country":"GB",
    "wof:name":"PO40 9HH",
    "wof:placetype":"postalcode"
},
  "geometry": {"coordinates":[-1.52434727071772,50.67807185661412],"type":"Point"}
}