{
  "type": "Feature",
  "properties": {
    "iso:country":"GB",
    "wof:name":"S75 4RQ",
    "wof:placetype":"postalcode"
},
  "geometry": {"coordinates":[-1.55835176634025,53.53462711061917],"type":"Point"}
}