{
  "type": "Feature",
  "properties": {
    "iso:country": "GB",
    "wof:name": "HX1 2TU",
    "wof:placetype": "postalcode"
  },
  "geometry": {"coordinates":[-1.870263,53.719585],"type":"Point"}
}
