{
  "type": "Feature",
  "properties": {
    "iso:country": "GB",
    "wof:name": "CH1 6EH",
    "wof:placetype": "postalcode"
  },
  "geometry": {"coordinates":[-2.947675,53.259869],"type":"Point"}
}
