{
  "type": "Feature",
  "properties": {
    "iso:country": "GB",
    "wof:name": "SK11 8XT",
    "wof:placetype": "postalcode"
  },
  "geometry": {"coordinates":[-2.131793,53.247276],"type":"Point"}
}
