{
  "type": "Feature",
  "properties": {
    "iso:country": "GB",
    "wof:name": "NE8 4PS",
    "wof:placetype": "postalcode"
  },
  "geometry": {"coordinates":[-1.609637,54.951167],"type":"Point"}
}
