{
  "type": "Feature",
  "properties": {
    "iso:country":"GB",
    "wof:name":"NE8 4PS",
    "wof:placetype":"postalcode"
},
  "geometry": {"coordinates":[-1.60963678317642,54.95116723764741],"type":"Point"}
}