{
  "type": "Feature",
  "properties": {
    "iso:country": "GB",
    "wof:name": "S6 3GA",
    "wof:placetype": "postalcode"
  },
  "geometry": {"coordinates":[-1.486977,53.387973],"type":"Point"}
}
