{
  "type": "Feature",
  "properties": {
    "date:inception_lower": "1992-08-01",
    "date:inception_upper": "1992-08-01",
    "iso:country": "GB",
    "wof:name": "S6 3GA",
    "wof:placetype": "postalcode"
  },
  "geometry": {"coordinates":[-1.487007,53.38799],"type":"Point"}
}
