{
  "type": "Feature",
  "properties": {
    "date:inception_lower":"1992-08-01",
    "date:inception_upper":"1992-08-31",
    "iso:country":"GB",
    "wof:name":"S6 3GA",
    "wof:placetype":"postalcode"
},
  "geometry": {"coordinates":[-1.486977,53.387973],"type":"Point"}
}