{
  "type": "Feature",
  "properties": {
    "date:inception_lower": "2018-05-01",
    "date:inception_upper": "2018-05-01",
    "iso:country": "GB",
    "wof:name": "SS12 9HB",
    "wof:placetype": "postalcode"
  },
  "geometry": {"coordinates":[0.539321,51.597685],"type":"Point"}
}
