{
  "type": "Feature",
  "properties": {
    "iso:country": "GB",
    "wof:name": "LL18 2AW",
    "wof:placetype": "postalcode"
  },
  "geometry": {"coordinates":[-3.49311,53.313579],"type":"Point"}
}
