{
  "type": "Feature",
  "properties": {
    "date:inception_lower":"1980-01-01",
    "date:inception_upper":"1980-01-31",
    "iso:country":"GB",
    "wof:name":"LE15 9HR",
    "wof:placetype":"postalcode"
},
  "geometry": {"coordinates":[-0.667338,52.573908],"type":"Point"}
}