{
  "type": "Feature",
  "properties": {
    "date:inception_lower": "1980-01-01",
    "date:inception_upper": "1980-01-01",
    "iso:country": "GB",
    "wof:name": "SL2 2EE",
    "wof:placetype": "postalcode"
  },
  "geometry": {"coordinates":[-0.63157,51.536973],"type":"Point"}
}
