{
  "type": "Feature",
  "properties": {
    "iso:country":"GB",
    "wof:name":"SL2 2EE",
    "wof:placetype":"postalcode"
},
  "geometry": {"coordinates":[-0.63156998758028,51.53697295307389],"type":"Point"}
}