{
  "type": "Feature",
  "properties": {
    "iso:country":"GB",
    "wof:name":"BD16 3DT",
    "wof:placetype":"postalcode"
},
  "geometry": {"coordinates":[-1.81855986562881,53.85692640514148],"type":"Point"}
}