{
  "type": "Feature",
  "properties": {
    "date:inception_lower":"1980-01-01",
    "date:inception_upper":"1980-01-31",
    "iso:country":"GB",
    "wof:name":"CO10 0EU",
    "wof:placetype":"postalcode"
},
  "geometry": {"coordinates":[0.754694,52.029901],"type":"Point"}
}