{
  "type": "Feature",
  "properties": {
    "iso:country":"GB",
    "wof:name":"BL9 5DQ",
    "wof:placetype":"postalcode"
},
  "geometry": {"coordinates":[-2.29387499490015,53.60572824070043],"type":"Point"}
}