{
  "type": "Feature",
  "properties": {
    "iso:country":"GB",
    "wof:name":"PR4 2EA",
    "wof:placetype":"postalcode"
},
  "geometry": {"coordinates":[-2.89138985860018,53.78165588737325],"type":"Point"}
}