{
  "type": "Feature",
  "properties": {
    "date:inception_lower": "1980-01-01",
    "date:inception_upper": "1980-01-01",
    "iso:country": "GB",
    "wof:name": "G2 4SQ",
    "wof:placetype": "postalcode"
  },
  "geometry": {"coordinates":[-4.261129,55.864184],"type":"Point"}
}
