{
  "type": "Feature",
  "properties": {
    "iso:country":"GB",
    "wof:name":"S32 4TB",
    "wof:placetype":"postalcode"
},
  "geometry": {"coordinates":[-1.65078224292032,53.27306769488425],"type":"Point"}
}