{
  "type": "Feature",
  "properties": {
    "date:inception_lower": "1980-01-01",
    "date:inception_upper": "1980-01-01",
    "iso:country": "GB",
    "wof:name": "BB12 9EH",
    "wof:placetype": "postalcode"
  },
  "geometry": {"coordinates":[-2.265773,53.832627],"type":"Point"}
}
