{
  "type": "Feature",
  "properties": {
    "date:inception_lower": "1980-01-01",
    "date:inception_upper": "1980-01-01",
    "iso:country": "GB",
    "wof:name": "KT9 1XG",
    "wof:placetype": "postalcode"
  },
  "geometry": {"coordinates":[-0.288423,51.36619],"type":"Point"}
}
