{
  "type": "Feature",
  "properties": {
    "iso:country":"GB",
    "wof:name":"KT9 1XG",
    "wof:placetype":"postalcode"
},
  "geometry": {"coordinates":[-0.28842320513026,51.36618973586679],"type":"Point"}
}