{
  "type": "Feature",
  "properties": {
    "iso:country":"GB",
    "wof:name":"IV54 8XT",
    "wof:placetype":"postalcode"
},
  "geometry": {"coordinates":[-5.86028793943217,57.49085415705372],"type":"Point"}
}