{
  "type": "Feature",
  "properties": {
    "date:inception_lower": "1998-12-01",
    "date:inception_upper": "1998-12-01",
    "iso:country": "GB",
    "wof:name": "IV54 8XT",
    "wof:placetype": "postalcode"
  },
  "geometry": {"coordinates":[-5.860288,57.490854],"type":"Point"}
}
