{
  "type": "Feature",
  "properties": {
    "iso:country": "GB",
    "wof:name": "IV54 8XT",
    "wof:placetype": "postalcode"
  },
  "geometry": {"coordinates":[-5.860288,57.490854],"type":"Point"}
}
