{
  "type": "Feature",
  "properties": {
    "iso:country":"GB",
    "wof:name":"HD9 4HX",
    "wof:placetype":"postalcode"
},
  "geometry": {"coordinates":[-1.82531225735685,53.59271388147994],"type":"Point"}
}