{
  "type": "Feature",
  "properties": {
    "iso:country": "GB",
    "wof:name": "HD9 4HX",
    "wof:placetype": "postalcode"
  },
  "geometry": {"coordinates":[-1.8256,53.592586],"type":"Point"}
}
