{
  "type": "Feature",
  "properties": {
    "iso:country":"GB",
    "wof:name":"TS26 0JB",
    "wof:placetype":"postalcode"
},
  "geometry": {"coordinates":[-1.22853932852511,54.69234590456902],"type":"Point"}
}