{
  "type": "Feature",
  "properties": {
    "date:inception_lower":"1980-01-01",
    "date:inception_upper":"1980-01-31",
    "iso:country":"GB",
    "wof:name":"TS26 0JB",
    "wof:placetype":"postalcode"
},
  "geometry": {"coordinates":[-1.228539,54.692346],"type":"Point"}
}