{
  "type": "Feature",
  "properties": {
    "iso:country":"GB",
    "wof:name":"TW12 3BB",
    "wof:placetype":"postalcode"
},
  "geometry": {"coordinates":[-0.36860930919698,51.42403099263305],"type":"Point"}
}