{
  "type": "Feature",
  "properties": {
    "iso:country": "GB",
    "wof:name": "WR11 3AQ",
    "wof:placetype": "postalcode"
  },
  "geometry": {"coordinates":[-1.93575,52.093753],"type":"Point"}
}
