{
  "type": "Feature",
  "properties": {
    "date:inception_lower": "2001-12-01",
    "date:inception_upper": "2001-12-01",
    "iso:country": "GB",
    "wof:name": "WR11 3AQ",
    "wof:placetype": "postalcode"
  },
  "geometry": {"coordinates":[-1.935647,52.093762],"type":"Point"}
}
