{
  "type": "Feature",
  "properties": {
    "iso:country":"GB",
    "wof:name":"OX17 3DN",
    "wof:placetype":"postalcode"
},
  "geometry": {"coordinates":[-1.23246677069761,52.02093610430792],"type":"Point"}
}