{
  "type": "Feature",
  "properties": {
    "iso:country": "GB",
    "wof:name": "OX17 3DN",
    "wof:placetype": "postalcode"
  },
  "geometry": {"coordinates":[-1.232467,52.020936],"type":"Point"}
}
