{
  "type": "Feature",
  "properties": {
    "date:inception_lower": "1980-01-01",
    "date:inception_upper": "1980-01-01",
    "iso:country": "GB",
    "wof:name": "EN2 6PJ",
    "wof:placetype": "postalcode"
  },
  "geometry": {"coordinates":[-0.08994,51.65199],"type":"Point"}
}
