{
  "type": "Feature",
  "properties": {
    "iso:country": "GB",
    "wof:name": "SP6 1FL",
    "wof:placetype": "postalcode"
  },
  "geometry": {"coordinates":[-1.795095,50.936608],"type":"Point"}
}
