{
  "type": "Feature",
  "properties": {
    "iso:country": "GB",
    "wof:name": "BH21 6SU",
    "wof:placetype": "postalcode"
  },
  "geometry": {"coordinates":[-1.865498,50.840148],"type":"Point"}
}
