{
  "type": "Feature",
  "properties": {
    "iso:country":"GB",
    "wof:name":"BH21 6SU",
    "wof:placetype":"postalcode"
},
  "geometry": {"coordinates":[-1.86549777242435,50.84014757910871],"type":"Point"}
}