{
  "type": "Feature",
  "properties": {
    "iso:country": "GB",
    "wof:name": "TN13 2RT",
    "wof:placetype": "postalcode"
  },
  "geometry": {"coordinates":[0.150658,51.283679],"type":"Point"}
}
