{
  "type": "Feature",
  "properties": {
    "iso:country": "GB",
    "wof:name": "NE40 3BW",
    "wof:placetype": "postalcode"
  },
  "geometry": {"coordinates":[-1.769811,54.970869],"type":"Point"}
}
