{
  "type": "Feature",
  "properties": {
    "iso:country":"GB",
    "wof:name":"SW4 7ST",
    "wof:placetype":"postalcode"
},
  "geometry": {"coordinates":[-0.13690989365062,51.46201494211603],"type":"Point"}
}