{
  "type": "Feature",
  "properties": {
    "iso:country":"GB",
    "wof:name":"RM1 4PP",
    "wof:placetype":"postalcode"
},
  "geometry": {"coordinates":[0.1860975191372,51.59412665612771],"type":"Point"}
}