{
  "type": "Feature",
  "properties": {
    "iso:country":"GB",
    "wof:name":"TW3 1YU",
    "wof:placetype":"postalcode"
},
  "geometry": {"coordinates":[-0.35501242187168,51.46620402679837],"type":"Point"}
}