{
  "type": "Feature",
  "properties": {
    "iso:country": "GB",
    "wof:name": "TW3 1YU",
    "wof:placetype": "postalcode"
  },
  "geometry": {"coordinates":[-0.355012,51.466204],"type":"Point"}
}
