{
  "type": "Feature",
  "properties": {
    "date:inception_lower": "2018-01-01",
    "date:inception_upper": "2018-01-01",
    "iso:country": "GB",
    "wof:name": "PL22 0GB",
    "wof:placetype": "postalcode"
  },
  "geometry": {"coordinates":[-4.673856,50.403844],"type":"Point"}
}
