{
  "type": "Feature",
  "properties": {
    "date:inception_lower": "1980-01-01",
    "date:inception_upper": "1980-01-01",
    "iso:country": "GB",
    "wof:name": "SO24 9SW",
    "wof:placetype": "postalcode"
  },
  "geometry": {"coordinates":[-1.121138,51.095083],"type":"Point"}
}
