{
  "type": "Feature",
  "properties": {
    "iso:country": "GB",
    "wof:name": "E17 4PH",
    "wof:placetype": "postalcode"
  },
  "geometry": {"coordinates":[-0.018279,51.589728],"type":"Point"}
}
