{
  "type": "Feature",
  "properties": {
    "iso:country":"GB",
    "wof:name":"BL6 5UE",
    "wof:placetype":"postalcode"
},
  "geometry": {"coordinates":[-2.54778665347046,53.59408473449468],"type":"Point"}
}