{
  "type": "Feature",
  "properties": {
    "date:inception_lower":"1986-07-01",
    "date:inception_upper":"1986-07-31",
    "iso:country":"GB",
    "wof:name":"BL6 5UE",
    "wof:placetype":"postalcode"
},
  "geometry": {"coordinates":[-2.547786,53.594101],"type":"Point"}
}