{
  "type": "Feature",
  "properties": {
    "iso:country":"GB",
    "wof:name":"BS3 4LX",
    "wof:placetype":"postalcode"
},
  "geometry": {"coordinates":[-2.5925946743054,51.43894312506315],"type":"Point"}
}