{
  "type": "Feature",
  "properties": {
    "iso:country":"GB",
    "wof:name":"WA8 0PB",
    "wof:placetype":"postalcode"
},
  "geometry": {"coordinates":[-2.7464336574352,53.35179908944374],"type":"Point"}
}