{
  "type": "Feature",
  "properties": {
    "iso:country": "GB",
    "wof:name": "WA8 0PB",
    "wof:placetype": "postalcode"
  },
  "geometry": {"coordinates":[-2.746747,53.352525],"type":"Point"}
}
