{
  "type": "Feature",
  "properties": {
    "date:inception_lower": "2013-04-01",
    "date:inception_upper": "2013-04-01",
    "iso:country": "GB",
    "wof:name": "CV21 1RZ",
    "wof:placetype": "postalcode"
  },
  "geometry": {"coordinates":[-1.250159,52.396666],"type":"Point"}
}
