{
  "type": "Feature",
  "properties": {
    "iso:country":"GB",
    "wof:name":"SW8 2AS",
    "wof:placetype":"postalcode"
},
  "geometry": {"coordinates":[-0.13528620623365,51.46900333952307],"type":"Point"}
}