{
  "type": "Feature",
  "properties": {
    "iso:country":"GB",
    "wof:name":"DE56 2UP",
    "wof:placetype":"postalcode"
},
  "geometry": {"coordinates":[-1.50103932629291,53.01881091664715],"type":"Point"}
}