{
  "type": "Feature",
  "properties": {
    "date:inception_lower": "1994-05-01",
    "date:inception_upper": "1994-05-01",
    "iso:country": "GB",
    "wof:name": "M9 6PG",
    "wof:placetype": "postalcode"
  },
  "geometry": {"coordinates":[-2.213035,53.530434],"type":"Point"}
}
