{
  "type": "Feature",
  "properties": {
    "date:inception_lower": "2014-06-01",
    "date:inception_upper": "2014-06-01",
    "iso:country": "GB",
    "wof:name": "PO7 3AU",
    "wof:placetype": "postalcode"
  },
  "geometry": {"coordinates":[-1.040256,50.879985],"type":"Point"}
}
