{
  "type": "Feature",
  "properties": {
    "iso:country":"GB",
    "wof:name":"PO7 3AU",
    "wof:placetype":"postalcode"
},
  "geometry": {"coordinates":[-1.04013064623373,50.87996587967691],"type":"Point"}
}