{
  "type": "Feature",
  "properties": {
    "iso:country":"GB",
    "wof:name":"NN16 8PU",
    "wof:placetype":"postalcode"
},
  "geometry": {"coordinates":[-0.74062503561543,52.40714516463456],"type":"Point"}
}