{
  "type": "Feature",
  "properties": {
    "iso:country": "GB",
    "wof:name": "DY10 4JE",
    "wof:placetype": "postalcode"
  },
  "geometry": {"coordinates":[-2.209592,52.336187],"type":"Point"}
}
