{
  "type": "Feature",
  "properties": {
    "date:inception_lower":"1980-01-01",
    "date:inception_upper":"1980-01-31",
    "iso:country":"GB",
    "wof:name":"DY10 4JE",
    "wof:placetype":"postalcode"
},
  "geometry": {"coordinates":[-2.209592,52.336187],"type":"Point"}
}