{
  "type": "Feature",
  "properties": {
    "iso:country":"GB",
    "wof:name":"DY10 4JE",
    "wof:placetype":"postalcode"
},
  "geometry": {"coordinates":[-2.209591772475,52.33618652889609],"type":"Point"}
}