{
  "type": "Feature",
  "properties": {
    "iso:country": "GB",
    "wof:name": "LE3 8GE",
    "wof:placetype": "postalcode"
  },
  "geometry": {"coordinates":[-1.207515,52.658378],"type":"Point"}
}
