{
  "type": "Feature",
  "properties": {
    "iso:country": "GB",
    "wof:name": "KT22 8PD",
    "wof:placetype": "postalcode"
  },
  "geometry": {"coordinates":[-0.31994,51.289389],"type":"Point"}
}
