{
  "type": "Feature",
  "properties": {
    "iso:country":"GB",
    "wof:name":"S75 1AD",
    "wof:placetype":"postalcode"
},
  "geometry": {"coordinates":[-1.53259863403357,53.56739992010746],"type":"Point"}
}