{
  "type": "Feature",
  "properties": {
    "date:inception_lower": "1983-03-01",
    "date:inception_upper": "1983-03-01",
    "iso:country": "GB",
    "wof:name": "B65 0HL",
    "wof:placetype": "postalcode"
  },
  "geometry": {"coordinates":[-2.042695,52.474147],"type":"Point"}
}
