{
  "type": "Feature",
  "properties": {
    "iso:country":"GB",
    "wof:name":"WS10 9RU",
    "wof:placetype":"postalcode"
},
  "geometry": {"coordinates":[-2.01825081612163,52.5674234526612],"type":"Point"}
}