{
  "type": "Feature",
  "properties": {
    "date:inception_lower":"1980-01-01",
    "date:inception_upper":"1980-01-31",
    "iso:country":"GB",
    "wof:name":"WS10 9RU",
    "wof:placetype":"postalcode"
},
  "geometry": {"coordinates":[-2.018251,52.567423],"type":"Point"}
}