{
  "type": "Feature",
  "properties": {
    "iso:country": "GB",
    "wof:name": "WS10 9RU",
    "wof:placetype": "postalcode"
  },
  "geometry": {"coordinates":[-2.018251,52.567423],"type":"Point"}
}
