{
  "type": "Feature",
  "properties": {
    "iso:country":"GB",
    "wof:name":"E14 0DH",
    "wof:placetype":"postalcode"
},
  "geometry": {"coordinates":[-0.02036087479471,51.51021207445784],"type":"Point"}
}