{
  "type": "Feature",
  "properties": {
    "iso:country": "GB",
    "wof:name": "GL2 9AJ",
    "wof:placetype": "postalcode"
  },
  "geometry": {"coordinates":[-2.234263,51.882657],"type":"Point"}
}
