{
  "type": "Feature",
  "properties": {
    "date:inception_lower":"1990-07-01",
    "date:inception_upper":"1990-07-31",
    "iso:country":"GB",
    "wof:name":"GL2 9AJ",
    "wof:placetype":"postalcode"
},
  "geometry": {"coordinates":[-2.234263,51.882657],"type":"Point"}
}