{
  "type": "Feature",
  "properties": {
    "iso:country":"GB",
    "wof:name":"GL2 9AJ",
    "wof:placetype":"postalcode"
},
  "geometry": {"coordinates":[-2.2342633217808,51.88265707927236],"type":"Point"}
}