{
  "type": "Feature",
  "properties": {
    "iso:country": "GB",
    "wof:name": "CW2 7SY",
    "wof:placetype": "postalcode"
  },
  "geometry": {"coordinates":[-2.467691,53.099856],"type":"Point"}
}
