{
  "type": "Feature",
  "properties": {
    "iso:country":"GB",
    "wof:name":"CW2 7SY",
    "wof:placetype":"postalcode"
},
  "geometry": {"coordinates":[-2.4676909423316,53.09985623448234],"type":"Point"}
}