{
  "type": "Feature",
  "properties": {
    "date:inception_lower":"1995-07-01",
    "date:inception_upper":"1995-07-31",
    "iso:country":"GB",
    "wof:name":"CW2 7SY",
    "wof:placetype":"postalcode"
},
  "geometry": {"coordinates":[-2.467691,53.099856],"type":"Point"}
}