{
  "type": "Feature",
  "properties": {
    "iso:country":"GB",
    "wof:name":"BN2 6UF",
    "wof:placetype":"postalcode"
},
  "geometry": {"coordinates":[-0.06821091376074,50.83163827632816],"type":"Point"}
}