{
  "type": "Feature",
  "properties": {
    "iso:country":"GB",
    "wof:name":"WN2 3DB",
    "wof:placetype":"postalcode"
},
  "geometry": {"coordinates":[-2.58942473866745,53.53751125444035],"type":"Point"}
}