{
  "type": "Feature",
  "properties": {
    "iso:country": "GB",
    "wof:name": "WN2 3DB",
    "wof:placetype": "postalcode"
  },
  "geometry": {"coordinates":[-2.589453,53.537491],"type":"Point"}
}
