{
  "type": "Feature",
  "properties": {
    "iso:country":"GB",
    "wof:name":"SA4 4UN",
    "wof:placetype":"postalcode"
},
  "geometry": {"coordinates":[-4.04455143427869,51.66706265839704],"type":"Point"}
}