{
  "type": "Feature",
  "properties": {
    "date:inception_lower":"1993-01-01",
    "date:inception_upper":"1993-01-31",
    "iso:country":"GB",
    "wof:name":"SA4 4UN",
    "wof:placetype":"postalcode"
},
  "geometry": {"coordinates":[-4.044551,51.667063],"type":"Point"}
}