{
  "type": "Feature",
  "properties": {
    "iso:country":"GB",
    "wof:name":"SA44 4DD",
    "wof:placetype":"postalcode"
},
  "geometry": {"coordinates":[-4.30964722831487,52.04242729015419],"type":"Point"}
}