{
  "type": "Feature",
  "properties": {
    "iso:country":"GB",
    "wof:name":"NE29 8BY",
    "wof:placetype":"postalcode"
},
  "geometry": {"coordinates":[-1.47879598880571,55.02117462505655],"type":"Point"}
}