{
  "type": "Feature",
  "properties": {
    "iso:country":"GB",
    "wof:name":"WA3 6QJ",
    "wof:placetype":"postalcode"
},
  "geometry": {"coordinates":[-2.51290518954858,53.41970970154129],"type":"Point"}
}