{
  "type": "Feature",
  "properties": {
    "iso:country": "GB",
    "wof:name": "WA3 6QJ",
    "wof:placetype": "postalcode"
  },
  "geometry": {"coordinates":[-2.512905,53.41971],"type":"Point"}
}
