{
  "type": "Feature",
  "properties": {
    "date:inception_lower":"1981-09-01",
    "date:inception_upper":"1981-09-30",
    "iso:country":"GB",
    "wof:name":"WA3 6QJ",
    "wof:placetype":"postalcode"
},
  "geometry": {"coordinates":[-2.512905,53.41971],"type":"Point"}
}