{
  "type": "Feature",
  "properties": {
    "iso:country":"GB",
    "wof:name":"LA3 2UQ",
    "wof:placetype":"postalcode"
},
  "geometry": {"coordinates":[-2.8979266583658,54.04253223076054],"type":"Point"}
}