{
  "type": "Feature",
  "properties": {
    "iso:country": "GB",
    "wof:name": "CB1 9AP",
    "wof:placetype": "postalcode"
  },
  "geometry": {"coordinates":[0.191044,52.20341],"type":"Point"}
}
