{
  "type": "Feature",
  "properties": {
    "iso:country":"GB",
    "wof:name":"CB1 9AP",
    "wof:placetype":"postalcode"
},
  "geometry": {"coordinates":[0.19108904667226,52.20341342011196],"type":"Point"}
}