{
  "type": "Feature",
  "properties": {
    "date:inception_lower": "2022-06-01",
    "date:inception_upper": "2022-06-01",
    "iso:country": "GB",
    "wof:name": "PH1 2BF",
    "wof:placetype": "postalcode"
  },
  "geometry": {"coordinates":[-3.457483,56.399693],"type":"Point"}
}
