{
  "type": "Feature",
  "properties": {
    "iso:country":"GB",
    "wof:name":"BL0 9NW",
    "wof:placetype":"postalcode"
},
  "geometry": {"coordinates":[-2.32510815886953,53.64242736508415],"type":"Point"}
}