{
  "type": "Feature",
  "properties": {
    "iso:country":"GB",
    "wof:name":"MK40 3UT",
    "wof:placetype":"postalcode"
},
  "geometry": {"coordinates":[-0.46573606345967,52.13577440729814],"type":"Point"}
}