{
  "type": "Feature",
  "properties": {
    "iso:country":"GB",
    "wof:name":"NP26 5BA",
    "wof:placetype":"postalcode"
},
  "geometry": {"coordinates":[-2.77533311177095,51.61243072985497],"type":"Point"}
}