{
  "type": "Feature",
  "properties": {
    "iso:country": "GB",
    "wof:name": "NP26 5BA",
    "wof:placetype": "postalcode"
  },
  "geometry": {"coordinates":[-2.775333,51.612431],"type":"Point"}
}
