{
  "type": "Feature",
  "properties": {
    "date:inception_lower": "1999-06-01",
    "date:inception_upper": "1999-06-01",
    "iso:country": "GB",
    "wof:name": "NP26 5BA",
    "wof:placetype": "postalcode"
  },
  "geometry": {"coordinates":[-2.775333,51.612431],"type":"Point"}
}
