{
  "type": "Feature",
  "properties": {
    "iso:country":"GB",
    "wof:name":"GU31 5LP",
    "wof:placetype":"postalcode"
},
  "geometry": {"coordinates":[-0.87774981003642,50.96308542086672],"type":"Point"}
}