{
  "type": "Feature",
  "properties": {
    "iso:country":"GB",
    "wof:name":"BH22 9QW",
    "wof:placetype":"postalcode"
},
  "geometry": {"coordinates":[-1.90362567945384,50.81470044232598],"type":"Point"}
}