{
  "type": "Feature",
  "properties": {
    "iso:country":"GB",
    "wof:name":"SW16 5PD",
    "wof:placetype":"postalcode"
},
  "geometry": {"coordinates":[-0.13229910739576,51.42190646007923],"type":"Point"}
}