{
  "type": "Feature",
  "properties": {
    "iso:country": "GB",
    "wof:name": "BS2 9QZ",
    "wof:placetype": "postalcode"
  },
  "geometry": {"coordinates":[-2.576089,51.469525],"type":"Point"}
}
