{
  "type": "Feature",
  "properties": {
    "iso:country":"GB",
    "wof:name":"B29 7RB",
    "wof:placetype":"postalcode"
},
  "geometry": {"coordinates":[-1.91972010426206,52.43376257698733],"type":"Point"}
}