{
  "type": "Feature",
  "properties": {
    "iso:country": "GB",
    "wof:name": "B29 7RB",
    "wof:placetype": "postalcode"
  },
  "geometry": {"coordinates":[-1.91972,52.433763],"type":"Point"}
}
