{
  "type": "Feature",
  "properties": {
    "date:inception_lower": "2021-02-01",
    "date:inception_upper": "2021-02-01",
    "iso:country": "GB",
    "wof:name": "LN2 4ZJ",
    "wof:placetype": "postalcode"
  },
  "geometry": {"coordinates":[-0.492055,53.242044],"type":"Point"}
}
