{
  "type": "Feature",
  "properties": {
    "date:inception_lower":"2018-05-01",
    "date:inception_upper":"2018-05-31",
    "iso:country":"GB",
    "wof:name":"RG24 9AB",
    "wof:placetype":"postalcode"
},
  "geometry": {"coordinates":[-1.108701,51.28253],"type":"Point"}
}