{
  "type": "Feature",
  "properties": {
    "iso:country":"GB",
    "wof:name":"B93 8SY",
    "wof:placetype":"postalcode"
},
  "geometry": {"coordinates":[-1.76503652224979,52.37412325371118],"type":"Point"}
}