{
  "type": "Feature",
  "properties": {
    "iso:country": "GB",
    "wof:name": "B93 8SY",
    "wof:placetype": "postalcode"
  },
  "geometry": {"coordinates":[-1.765036,52.374123],"type":"Point"}
}
