{
  "type": "Feature",
  "properties": {
    "iso:country":"GB",
    "wof:name":"B90 4TG",
    "wof:placetype":"postalcode"
},
  "geometry": {"coordinates":[-1.8011177849578,52.38930178562928],"type":"Point"}
}