{
  "type": "Feature",
  "properties": {
    "iso:country": "GB",
    "wof:name": "DA12 5BT",
    "wof:placetype": "postalcode"
  },
  "geometry": {"coordinates":[0.377744,51.419844],"type":"Point"}
}
