{
  "type": "Feature",
  "properties": {
    "iso:country":"GB",
    "wof:name":"MK14 7NT",
    "wof:placetype":"postalcode"
},
  "geometry": {"coordinates":[-0.74650761535253,52.05664454244065],"type":"Point"}
}