{
  "type": "Feature",
  "properties": {
    "iso:country": "GB",
    "wof:name": "MK14 7NT",
    "wof:placetype": "postalcode"
  },
  "geometry": {"coordinates":[-0.746508,52.056645],"type":"Point"}
}
