{
  "type": "Feature",
  "properties": {
    "date:inception_lower": "1995-07-01",
    "date:inception_upper": "1995-07-01",
    "iso:country": "GB",
    "wof:name": "MK14 7NT",
    "wof:placetype": "postalcode"
  },
  "geometry": {"coordinates":[-0.746508,52.056645],"type":"Point"}
}
