{
  "type": "Feature",
  "properties": {
    "iso:country":"GB",
    "wof:name":"GU32 1HS",
    "wof:placetype":"postalcode"
},
  "geometry": {"coordinates":[-1.08778450449406,51.00984071308934],"type":"Point"}
}