{
  "type": "Feature",
  "properties": {
    "iso:country":"GB",
    "wof:name":"SS17 0DB",
    "wof:placetype":"postalcode"
},
  "geometry": {"coordinates":[0.42831518509692,51.51308356683616],"type":"Point"}
}