{
  "type": "Feature",
  "properties": {
    "iso:country": "GB",
    "wof:name": "SS17 0DB",
    "wof:placetype": "postalcode"
  },
  "geometry": {"coordinates":[0.428315,51.513084],"type":"Point"}
}
