{
  "type": "Feature",
  "properties": {
    "iso:country":"GB",
    "wof:name":"SW14 7DS",
    "wof:placetype":"postalcode"
},
  "geometry": {"coordinates":[-0.27589676158723,51.4628912148961],"type":"Point"}
}