{
  "type": "Feature",
  "properties": {
    "iso:country": "GB",
    "wof:name": "KY4 0FF",
    "wof:placetype": "postalcode"
  },
  "geometry": {"coordinates":[-3.375142,56.137392],"type":"Point"}
}
