{
  "type": "Feature",
  "properties": {
    "date:inception_lower": "2013-11-01",
    "date:inception_upper": "2013-11-01",
    "iso:country": "GB",
    "wof:name": "KY4 0FF",
    "wof:placetype": "postalcode"
  },
  "geometry": {"coordinates":[-3.375141,56.137385],"type":"Point"}
}
