{
  "type": "Feature",
  "properties": {
    "iso:country":"GB",
    "wof:name":"WA14 4PE",
    "wof:placetype":"postalcode"
},
  "geometry": {"coordinates":[-2.39088621792557,53.3848194154192],"type":"Point"}
}