{
  "type": "Feature",
  "properties": {
    "date:inception_lower":"2007-08-01",
    "date:inception_upper":"2007-08-31",
    "iso:country":"GB",
    "wof:name":"WA14 4PE",
    "wof:placetype":"postalcode"
},
  "geometry": {"coordinates":[-2.390886,53.384819],"type":"Point"}
}