{
  "type": "Feature",
  "properties": {
    "iso:country": "GB",
    "wof:name": "WA14 4PE",
    "wof:placetype": "postalcode"
  },
  "geometry": {"coordinates":[-2.390886,53.384819],"type":"Point"}
}
