{
  "type": "Feature",
  "properties": {
    "iso:country": "GB",
    "wof:name": "BS7 0LE",
    "wof:placetype": "postalcode"
  },
  "geometry": {"coordinates":[-2.572882,51.495086],"type":"Point"}
}
