{
  "type": "Feature",
  "properties": {
    "iso:country":"GB",
    "wof:name":"BS7 0LE",
    "wof:placetype":"postalcode"
},
  "geometry": {"coordinates":[-2.57288233222896,51.49508588651901],"type":"Point"}
}