{
  "type": "Feature",
  "properties": {
    "iso:country": "GB",
    "wof:name": "PA16 8QG",
    "wof:placetype": "postalcode"
  },
  "geometry": {"coordinates":[-4.776084,55.94981],"type":"Point"}
}
