{
  "type": "Feature",
  "properties": {
    "date:inception_lower":"1980-01-01",
    "date:inception_upper":"1980-01-31",
    "iso:country":"GB",
    "wof:name":"SG14 1LY",
    "wof:placetype":"postalcode"
},
  "geometry": {"coordinates":[-0.089391,51.797935],"type":"Point"}
}