{
  "type": "Feature",
  "properties": {
    "iso:country": "GB",
    "wof:name": "SG14 1LY",
    "wof:placetype": "postalcode"
  },
  "geometry": {"coordinates":[-0.089391,51.797935],"type":"Point"}
}
