{
  "type": "Feature",
  "properties": {
    "iso:country":"GB",
    "wof:name":"FK9 5DJ",
    "wof:placetype":"postalcode"
},
  "geometry": {"coordinates":[-3.93958768883052,56.13600949393103],"type":"Point"}
}