{
  "type": "Feature",
  "properties": {
    "iso:country":"GB",
    "wof:name":"NE6 3BN",
    "wof:placetype":"postalcode"
},
  "geometry": {"coordinates":[-1.55345714959431,54.96971946248903],"type":"Point"}
}