{
  "type": "Feature",
  "properties": {
    "iso:country":"GB",
    "wof:name":"LL13 0AY",
    "wof:placetype":"postalcode"
},
  "geometry": {"coordinates":[-2.90895957528597,53.00246537373216],"type":"Point"}
}