{
  "type": "Feature",
  "properties": {
    "date:inception_lower":"1981-06-01",
    "date:inception_upper":"1981-06-30",
    "iso:country":"GB",
    "wof:name":"LL13 0AY",
    "wof:placetype":"postalcode"
},
  "geometry": {"coordinates":[-2.90923,53.002562],"type":"Point"}
}