{
  "type": "Feature",
  "properties": {
    "date:inception_lower": "1990-02-01",
    "date:inception_upper": "1990-02-01",
    "iso:country": "GB",
    "wof:name": "EC1M 6EH",
    "wof:placetype": "postalcode"
  },
  "geometry": {"coordinates":[-0.098605,51.521156],"type":"Point"}
}
