{
  "type": "Feature",
  "properties": {
    "iso:country":"GB",
    "wof:name":"EC1M 6EH",
    "wof:placetype":"postalcode"
},
  "geometry": {"coordinates":[-0.09860491887401,51.52115568935287],"type":"Point"}
}