{
  "type": "Feature",
  "properties": {
    "date:inception_lower":"1994-05-01",
    "date:inception_upper":"1994-05-31",
    "iso:country":"GB",
    "wof:name":"M41 5PB",
    "wof:placetype":"postalcode"
},
  "geometry": {"coordinates":[-2.381584,53.452498],"type":"Point"}
}