{
  "type": "Feature",
  "properties": {
    "iso:country":"GB",
    "wof:name":"M41 5PB",
    "wof:placetype":"postalcode"
},
  "geometry": {"coordinates":[-2.38158429775288,53.45249762740481],"type":"Point"}
}