{
  "type": "Feature",
  "properties": {
    "iso:country": "GB",
    "wof:name": "RG22 5QL",
    "wof:placetype": "postalcode"
  },
  "geometry": {"coordinates":[-1.145854,51.243206],"type":"Point"}
}
