{
  "type": "Feature",
  "properties": {
    "iso:country":"GB",
    "wof:name":"W10 6DB",
    "wof:placetype":"postalcode"
},
  "geometry": {"coordinates":[-0.22009298222564,51.52293619852233],"type":"Point"}
}