{
  "type": "Feature",
  "properties": {
    "iso:country":"GB",
    "wof:name":"LU2 0AY",
    "wof:placetype":"postalcode"
},
  "geometry": {"coordinates":[-0.40603168493361,51.88238378585662],"type":"Point"}
}