{
  "type": "Feature",
  "properties": {
    "iso:country":"GB",
    "wof:name":"TN10 4JS",
    "wof:placetype":"postalcode"
},
  "geometry": {"coordinates":[0.30151152456169,51.20856576208615],"type":"Point"}
}