{
  "type": "Feature",
  "properties": {
    "iso:country":"GB",
    "wof:name":"SO40 7LT",
    "wof:placetype":"postalcode"
},
  "geometry": {"coordinates":[-1.54489348590673,50.91531591196266],"type":"Point"}
}