{
  "type": "Feature",
  "properties": {
    "iso:country": "GB",
    "wof:name": "SO40 7LT",
    "wof:placetype": "postalcode"
  },
  "geometry": {"coordinates":[-1.544893,50.915316],"type":"Point"}
}
