{
  "type": "Feature",
  "properties": {
    "date:inception_lower": "2017-04-01",
    "date:inception_upper": "2017-04-01",
    "iso:country": "GB",
    "wof:name": "SY23 3GW",
    "wof:placetype": "postalcode"
  },
  "geometry": {"coordinates":[-3.851709,52.372689],"type":"Point"}
}
