{
  "type": "Feature",
  "properties": {
    "iso:country": "GB",
    "wof:name": "SY23 3GW",
    "wof:placetype": "postalcode"
  },
  "geometry": {"coordinates":[-3.851709,52.372689],"type":"Point"}
}
