{
  "type": "Feature",
  "properties": {
    "iso:country":"GB",
    "wof:name":"LA9 4RR",
    "wof:placetype":"postalcode"
},
  "geometry": {"coordinates":[-2.74989321986425,54.33319942411581],"type":"Point"}
}