{
  "type": "Feature",
  "properties": {
    "iso:country":"GB",
    "wof:name":"TQ14 8TE",
    "wof:placetype":"postalcode"
},
  "geometry": {"coordinates":[-3.49272612846913,50.54975804291292],"type":"Point"}
}