{
  "type": "Feature",
  "properties": {
    "date:inception_lower":"1980-01-01",
    "date:inception_upper":"1980-01-31",
    "iso:country":"GB",
    "wof:name":"TQ14 8TE",
    "wof:placetype":"postalcode"
},
  "geometry": {"coordinates":[-3.492726,50.549758],"type":"Point"}
}