{
  "type": "Feature",
  "properties": {
    "iso:country":"GB",
    "wof:name":"LS17 0BT",
    "wof:placetype":"postalcode"
},
  "geometry": {"coordinates":[-1.58231099779174,53.92938175608757],"type":"Point"}
}