{
  "type": "Feature",
  "properties": {
    "date:inception_lower":"1980-01-01",
    "date:inception_upper":"1980-01-31",
    "iso:country":"GB",
    "wof:name":"WN6 8ET",
    "wof:placetype":"postalcode"
},
  "geometry": {"coordinates":[-2.69942,53.574041],"type":"Point"}
}