{
  "type": "Feature",
  "properties": {
    "iso:country":"GB",
    "wof:name":"WN6 8ET",
    "wof:placetype":"postalcode"
},
  "geometry": {"coordinates":[-2.69942037255574,53.57404084959595],"type":"Point"}
}