{
  "type": "Feature",
  "properties": {
    "date:inception_lower": "2018-01-01",
    "date:inception_upper": "2018-01-01",
    "iso:country": "GB",
    "wof:name": "SO31 7PJ",
    "wof:placetype": "postalcode"
  },
  "geometry": {"coordinates":[-1.278285,50.871474],"type":"Point"}
}
