{
  "type": "Feature",
  "properties": {
    "iso:country":"GB",
    "wof:name":"ZE1 0ED",
    "wof:placetype":"postalcode"
},
  "geometry": {"coordinates":[-1.14618136027531,60.15280236546565],"type":"Point"}
}