{
  "type": "Feature",
  "properties": {
    "date:inception_lower": "1980-01-01",
    "date:inception_upper": "1980-01-01",
    "iso:country": "GB",
    "wof:name": "G45 9PU",
    "wof:placetype": "postalcode"
  },
  "geometry": {"coordinates":[-4.244676,55.802274],"type":"Point"}
}
