{
  "type": "Feature",
  "properties": {
    "iso:country":"GB",
    "wof:name":"G45 9PU",
    "wof:placetype":"postalcode"
},
  "geometry": {"coordinates":[-4.24467624564834,55.80227428326438],"type":"Point"}
}