{
  "type": "Feature",
  "properties": {
    "iso:country":"GB",
    "wof:name":"BN16 3DJ",
    "wof:placetype":"postalcode"
},
  "geometry": {"coordinates":[-0.50754939843617,50.81081781048636],"type":"Point"}
}