{
  "type": "Feature",
  "properties": {
    "iso:country":"GB",
    "wof:name":"DA5 3BP",
    "wof:placetype":"postalcode"
},
  "geometry": {"coordinates":[0.12171299144707,51.44393226160485],"type":"Point"}
}