{
  "type": "Feature",
  "properties": {
    "iso:country":"GB",
    "wof:name":"SK22 3DW",
    "wof:placetype":"postalcode"
},
  "geometry": {"coordinates":[-2.00640802401784,53.36830971658978],"type":"Point"}
}