{
  "type": "Feature",
  "properties": {
    "date:inception_lower": "1980-01-01",
    "date:inception_upper": "1980-01-01",
    "iso:country": "GB",
    "wof:name": "CM23 2EL",
    "wof:placetype": "postalcode"
  },
  "geometry": {"coordinates":[0.162061,51.871273],"type":"Point"}
}
