{
  "type": "Feature",
  "properties": {
    "iso:country":"GB",
    "wof:name":"CM23 2EL",
    "wof:placetype":"postalcode"
},
  "geometry": {"coordinates":[0.16243683225886,51.87148289652399],"type":"Point"}
}