{
  "type": "Feature",
  "properties": {
    "iso:country": "GB",
    "wof:name": "DL9 4HU",
    "wof:placetype": "postalcode"
  },
  "geometry": {"coordinates":[-1.71022,54.359988],"type":"Point"}
}
