{
  "type": "Feature",
  "properties": {
    "iso:country":"GB",
    "wof:name":"DL9 4HU",
    "wof:placetype":"postalcode"
},
  "geometry": {"coordinates":[-1.71022026102149,54.35998830291538],"type":"Point"}
}