{
  "type": "Feature",
  "properties": {
    "iso:country":"GB",
    "wof:name":"YO62 6AW",
    "wof:placetype":"postalcode"
},
  "geometry": {"coordinates":[-0.93563722625175,54.26749401057926],"type":"Point"}
}