{
  "type": "Feature",
  "properties": {
    "date:inception_lower": "1995-01-01",
    "date:inception_upper": "1995-01-01",
    "iso:country": "GB",
    "wof:name": "SG7 5RX",
    "wof:placetype": "postalcode"
  },
  "geometry": {"coordinates":[-0.197957,52.050065],"type":"Point"}
}
