{
  "type": "Feature",
  "properties": {
    "iso:country": "GB",
    "wof:name": "IP25 7RG",
    "wof:placetype": "postalcode"
  },
  "geometry": {"coordinates":[0.846556,52.621452],"type":"Point"}
}
