{
  "type": "Feature",
  "properties": {
    "iso:country":"GB",
    "wof:name":"IP25 7RG",
    "wof:placetype":"postalcode"
},
  "geometry": {"coordinates":[0.84655558305338,52.62145203698815],"type":"Point"}
}