{
  "type": "Feature",
  "properties": {
    "iso:country": "GB",
    "wof:name": "GL18 1DQ",
    "wof:placetype": "postalcode"
  },
  "geometry": {"coordinates":[-2.405818,51.95097],"type":"Point"}
}
