{
  "type": "Feature",
  "properties": {
    "iso:country":"GB",
    "wof:name":"BN7 2SG",
    "wof:placetype":"postalcode"
},
  "geometry": {"coordinates":[0.00026111702884,50.88031774864682],"type":"Point"}
}