{
  "type": "Feature",
  "properties": {
    "date:inception_lower": "1983-03-01",
    "date:inception_upper": "1983-03-01",
    "iso:country": "GB",
    "wof:name": "SY22 5JH",
    "wof:placetype": "postalcode"
  },
  "geometry": {"coordinates":[-3.363915,52.739544],"type":"Point"}
}
