{
  "type": "Feature",
  "properties": {
    "iso:country": "GB",
    "wof:name": "SY22 5JH",
    "wof:placetype": "postalcode"
  },
  "geometry": {"coordinates":[-3.363915,52.739544],"type":"Point"}
}
