{
  "type": "Feature",
  "properties": {
    "date:inception_lower": "1980-01-01",
    "date:inception_upper": "1980-01-01",
    "iso:country": "GB",
    "wof:name": "OL6 8PZ",
    "wof:placetype": "postalcode"
  },
  "geometry": {"coordinates":[-2.090921,53.498375],"type":"Point"}
}
