{
  "type": "Feature",
  "properties": {
    "iso:country":"GB",
    "wof:name":"LE13 1LN",
    "wof:placetype":"postalcode"
},
  "geometry": {"coordinates":[-0.88548140314603,52.77564335422816],"type":"Point"}
}