{
  "type": "Feature",
  "properties": {
    "iso:country": "GB",
    "wof:name": "PO14 4JU",
    "wof:placetype": "postalcode"
  },
  "geometry": {"coordinates":[-1.254611,50.848862],"type":"Point"}
}
