{
  "type": "Feature",
  "properties": {
    "date:inception_lower":"1980-01-01",
    "date:inception_upper":"1980-01-31",
    "iso:country":"GB",
    "wof:name":"PO14 4JU",
    "wof:placetype":"postalcode"
},
  "geometry": {"coordinates":[-1.254611,50.848862],"type":"Point"}
}