{
  "type": "Feature",
  "properties": {
    "date:inception_lower": "2023-12-01",
    "date:inception_upper": "2023-12-01",
    "iso:country": "GB",
    "wof:name": "PE7 2GE",
    "wof:placetype": "postalcode"
  },
  "geometry": {"coordinates":[-0.108317,52.559968],"type":"Point"}
}
