{
  "type": "Feature",
  "properties": {
    "iso:country":"GB",
    "wof:name":"CF11 0SB",
    "wof:placetype":"postalcode"
},
  "geometry": {"coordinates":[-3.18781411530582,51.44951041129094],"type":"Point"}
}