{
  "type": "Feature",
  "properties": {
    "date:inception_lower": "1983-05-01",
    "date:inception_upper": "1983-05-01",
    "iso:country": "GB",
    "wof:name": "DD2 2JQ",
    "wof:placetype": "postalcode"
  },
  "geometry": {"coordinates":[-3.016001,56.466045],"type":"Point"}
}
