{
  "type": "Feature",
  "properties": {
    "iso:country":"GB",
    "wof:name":"DD2 2JQ",
    "wof:placetype":"postalcode"
},
  "geometry": {"coordinates":[-3.0160005868236,56.46604480471493],"type":"Point"}
}