{
  "type": "Feature",
  "properties": {
    "date:inception_lower": "1981-06-01",
    "date:inception_upper": "1981-06-01",
    "iso:country": "GB",
    "wof:name": "WN3 5PS",
    "wof:placetype": "postalcode"
  },
  "geometry": {"coordinates":[-2.641095,53.51996],"type":"Point"}
}
