{
  "type": "Feature",
  "properties": {
    "iso:country": "GB",
    "wof:name": "PL26 8UU",
    "wof:placetype": "postalcode"
  },
  "geometry": {"coordinates":[-4.778691,50.372972],"type":"Point"}
}
