{
  "type": "Feature",
  "properties": {
    "iso:country":"GB",
    "wof:name":"PL26 8UU",
    "wof:placetype":"postalcode"
},
  "geometry": {"coordinates":[-4.77869109546173,50.37297216581288],"type":"Point"}
}