{
  "type": "Feature",
  "properties": {
    "iso:country":"GB",
    "wof:name":"SY18 6JX",
    "wof:placetype":"postalcode"
},
  "geometry": {"coordinates":[-3.47054006530029,52.40188667240006],"type":"Point"}
}