{
  "type": "Feature",
  "properties": {
    "date:inception_lower": "1994-12-01",
    "date:inception_upper": "1994-12-01",
    "iso:country": "GB",
    "wof:name": "SO31 6ER",
    "wof:placetype": "postalcode"
  },
  "geometry": {"coordinates":[-1.289506,50.86077],"type":"Point"}
}
