{
  "type": "Feature",
  "properties": {
    "iso:country":"GB",
    "wof:name":"SO31 6ER",
    "wof:placetype":"postalcode"
},
  "geometry": {"coordinates":[-1.29017050313721,50.8607199746304],"type":"Point"}
}