{
  "type": "Feature",
  "properties": {
    "iso:country":"GB",
    "wof:name":"W1S 3NX",
    "wof:placetype":"postalcode"
},
  "geometry": {"coordinates":[-0.14190859328864,51.51047414875796],"type":"Point"}
}