{
  "type": "Feature",
  "properties": {
    "iso:country":"GB",
    "wof:name":"S80 3LF",
    "wof:placetype":"postalcode"
},
  "geometry": {"coordinates":[-1.14931502446166,53.31640773973787],"type":"Point"}
}