{
  "type": "Feature",
  "properties": {
    "date:inception_lower":"2005-08-01",
    "date:inception_upper":"2005-08-31",
    "iso:country":"GB",
    "wof:name":"S80 3LF",
    "wof:placetype":"postalcode"
},
  "geometry": {"coordinates":[-1.149315,53.316408],"type":"Point"}
}