{
  "type": "Feature",
  "properties": {
    "iso:country":"GB",
    "wof:name":"CM12 0HN",
    "wof:placetype":"postalcode"
},
  "geometry": {"coordinates":[0.41308018926774,51.63404131313274],"type":"Point"}
}