{
  "type": "Feature",
  "properties": {
    "iso:country":"GB",
    "wof:name":"CT20 2RT",
    "wof:placetype":"postalcode"
},
  "geometry": {"coordinates":[1.17050751924948,51.07762290683929],"type":"Point"}
}