{
  "type": "Feature",
  "properties": {
    "iso:country": "GB",
    "wof:name": "MK8 8AY",
    "wof:placetype": "postalcode"
  },
  "geometry": {"coordinates":[-0.804559,52.041801],"type":"Point"}
}
