{
  "type": "Feature",
  "properties": {
    "iso:country":"GB",
    "wof:name":"MK8 8AY",
    "wof:placetype":"postalcode"
},
  "geometry": {"coordinates":[-0.8045595222104,52.04180092380692],"type":"Point"}
}