{
  "type": "Feature",
  "properties": {
    "iso:country":"GB",
    "wof:name":"PL13 1JR",
    "wof:placetype":"postalcode"
},
  "geometry": {"coordinates":[-4.44873514532165,50.35640311043048],"type":"Point"}
}