{
  "type": "Feature",
  "properties": {
    "iso:country":"GB",
    "wof:name":"CV1 2DT",
    "wof:placetype":"postalcode"
},
  "geometry": {"coordinates":[-1.50309928482406,52.40590230471311],"type":"Point"}
}