{
  "type": "Feature",
  "properties": {
    "iso:country": "GB",
    "wof:name": "AB11 8BY",
    "wof:placetype": "postalcode"
  },
  "geometry": {"coordinates":[-2.093764,57.131903],"type":"Point"}
}
