{
  "type": "Feature",
  "properties": {
    "iso:country":"GB",
    "wof:name":"AB11 8BY",
    "wof:placetype":"postalcode"
},
  "geometry": {"coordinates":[-2.09376388298093,57.13190271842121],"type":"Point"}
}