{
  "type": "Feature",
  "properties": {
    "date:inception_lower":"1996-06-01",
    "date:inception_upper":"1996-06-30",
    "iso:country":"GB",
    "wof:name":"AB11 8BY",
    "wof:placetype":"postalcode"
},
  "geometry": {"coordinates":[-2.093764,57.131903],"type":"Point"}
}