{
  "type": "Feature",
  "properties": {
    "date:inception_lower": "2017-07-01",
    "date:inception_upper": "2017-07-01",
    "iso:country": "GB",
    "wof:name": "PA4 8ZS",
    "wof:placetype": "postalcode"
  },
  "geometry": {"coordinates":[-4.376946,55.876609],"type":"Point"}
}
