{
  "type": "Feature",
  "properties": {
    "iso:country":"GB",
    "wof:name":"SR5 5LE",
    "wof:placetype":"postalcode"
},
  "geometry": {"coordinates":[-1.42153645148611,54.92758385077747],"type":"Point"}
}