{
  "type": "Feature",
  "properties": {
    "iso:country":"GB",
    "wof:name":"CF43 4AG",
    "wof:placetype":"postalcode"
},
  "geometry": {"coordinates":[-3.48195612695006,51.67184290353724],"type":"Point"}
}