{
  "type": "Feature",
  "properties": {
    "iso:country": "GB",
    "wof:name": "CF43 4AG",
    "wof:placetype": "postalcode"
  },
  "geometry": {"coordinates":[-3.481956,51.671843],"type":"Point"}
}
