{
  "type": "Feature",
  "properties": {
    "iso:country": "GB",
    "wof:name": "B29 5UA",
    "wof:placetype": "postalcode"
  },
  "geometry": {"coordinates":[-1.976242,52.439712],"type":"Point"}
}
