{
  "type": "Feature",
  "properties": {
    "iso:country":"GB",
    "wof:name":"B29 5UA",
    "wof:placetype":"postalcode"
},
  "geometry": {"coordinates":[-1.97624242040793,52.439711737925],"type":"Point"}
}