{
  "type": "Feature",
  "properties": {
    "iso:country":"GB",
    "wof:name":"SE26 6BE",
    "wof:placetype":"postalcode"
},
  "geometry": {"coordinates":[-0.05742847616451,51.42711918804516],"type":"Point"}
}