{
  "type": "Feature",
  "properties": {
    "iso:country":"GB",
    "wof:name":"PA4 8TJ",
    "wof:placetype":"postalcode"
},
  "geometry": {"coordinates":[-4.37832101749536,55.88212473515905],"type":"Point"}
}