{
  "type": "Feature",
  "properties": {
    "iso:country":"GB",
    "wof:name":"CW3 9RQ",
    "wof:placetype":"postalcode"
},
  "geometry": {"coordinates":[-2.39642616258305,52.97040132624166],"type":"Point"}
}