{
  "type": "Feature",
  "properties": {
    "iso:country":"GB",
    "wof:name":"SN8 2AG",
    "wof:placetype":"postalcode"
},
  "geometry": {"coordinates":[-1.72289972937698,51.42021687273581],"type":"Point"}
}