{
  "type": "Feature",
  "properties": {
    "date:inception_lower":"2009-01-01",
    "date:inception_upper":"2009-01-31",
    "iso:country":"GB",
    "wof:name":"BD8 8RG",
    "wof:placetype":"postalcode"
},
  "geometry": {"coordinates":[-1.774703,53.805136],"type":"Point"}
}