{
  "type": "Feature",
  "properties": {
    "iso:country":"GB",
    "wof:name":"BD8 8RG",
    "wof:placetype":"postalcode"
},
  "geometry": {"coordinates":[-1.77470294401245,53.80513565618499],"type":"Point"}
}