{
  "type": "Feature",
  "properties": {
    "date:inception_lower":"1991-01-01",
    "date:inception_upper":"1991-01-31",
    "iso:country":"GB",
    "wof:name":"DN18 6JS",
    "wof:placetype":"postalcode"
},
  "geometry": {"coordinates":[-0.512218,53.676559],"type":"Point"}
}