{
  "type": "Feature",
  "properties": {
    "iso:country":"GB",
    "wof:name":"DN18 6JS",
    "wof:placetype":"postalcode"
},
  "geometry": {"coordinates":[-0.51221769541734,53.67655924152748],"type":"Point"}
}