{
  "type": "Feature",
  "properties": {
    "iso:country":"GB",
    "wof:name":"DT11 8ST",
    "wof:placetype":"postalcode"
},
  "geometry": {"coordinates":[-2.15658764287352,50.87554968077011],"type":"Point"}
}