{
  "type": "Feature",
  "properties": {
    "iso:country": "GB",
    "wof:name": "DT11 8ST",
    "wof:placetype": "postalcode"
  },
  "geometry": {"coordinates":[-2.156588,50.87555],"type":"Point"}
}
