{
  "type": "Feature",
  "properties": {
    "iso:country":"GB",
    "wof:name":"FK3 8SJ",
    "wof:placetype":"postalcode"
},
  "geometry": {"coordinates":[-3.73069423430658,56.00509425391926],"type":"Point"}
}