{
  "type": "Feature",
  "properties": {
    "date:inception_lower": "1980-01-01",
    "date:inception_upper": "1980-01-01",
    "iso:country": "GB",
    "wof:name": "ME15 8UH",
    "wof:placetype": "postalcode"
  },
  "geometry": {"coordinates":[0.560661,51.24563],"type":"Point"}
}
