{
  "type": "Feature",
  "properties": {
    "date:inception_lower": "1984-10-01",
    "date:inception_upper": "1984-10-01",
    "iso:country": "GB",
    "wof:name": "LA20 6HW",
    "wof:placetype": "postalcode"
  },
  "geometry": {"coordinates":[-3.210822,54.276272],"type":"Point"}
}
