{
  "type": "Feature",
  "properties": {
    "iso:country":"GB",
    "wof:name":"TN22 1RG",
    "wof:placetype":"postalcode"
},
  "geometry": {"coordinates":[0.09716319716006,50.97282440608291],"type":"Point"}
}