{
  "type": "Feature",
  "properties": {
    "iso:country": "GB",
    "wof:name": "HU11 5JN",
    "wof:placetype": "postalcode"
  },
  "geometry": {"coordinates":[-0.286404,53.864022],"type":"Point"}
}
