{
  "type": "Feature",
  "properties": {
    "date:inception_lower":"2006-04-01",
    "date:inception_upper":"2006-04-30",
    "iso:country":"GB",
    "wof:name":"OX14 3GG",
    "wof:placetype":"postalcode"
},
  "geometry": {"coordinates":[-1.240808,51.684664],"type":"Point"}
}