{
  "type": "Feature",
  "properties": {
    "iso:country":"GB",
    "wof:name":"CM20 3AN",
    "wof:placetype":"postalcode"
},
  "geometry": {"coordinates":[0.11411399916921,51.7762055524948],"type":"Point"}
}