{
  "type": "Feature",
  "properties": {
    "iso:country":"GB",
    "wof:name":"BH1 3BG",
    "wof:placetype":"postalcode"
},
  "geometry": {"coordinates":[-1.86376349220752,50.72332295836071],"type":"Point"}
}