{
  "type": "Feature",
  "properties": {
    "iso:country":"GB",
    "wof:name":"PR2 2NQ",
    "wof:placetype":"postalcode"
},
  "geometry": {"coordinates":[-2.72527221773289,53.76420647753454],"type":"Point"}
}