{
  "type": "Feature",
  "properties": {
    "iso:country":"GB",
    "wof:name":"SS8 9LP",
    "wof:placetype":"postalcode"
},
  "geometry": {"coordinates":[0.56626776397104,51.52261026370234],"type":"Point"}
}