{
  "type": "Feature",
  "properties": {
    "iso:country": "GB",
    "wof:name": "SS8 9LP",
    "wof:placetype": "postalcode"
  },
  "geometry": {"coordinates":[0.566268,51.52261],"type":"Point"}
}
