{
  "type": "Feature",
  "properties": {
    "iso:country": "GB",
    "wof:name": "LL36 9LY",
    "wof:placetype": "postalcode"
  },
  "geometry": {"coordinates":[-4.10393,52.630256],"type":"Point"}
}
