{
  "type": "Feature",
  "properties": {
    "iso:country":"GB",
    "wof:name":"LL36 9LY",
    "wof:placetype":"postalcode"
},
  "geometry": {"coordinates":[-4.10392216856368,52.63023954234092],"type":"Point"}
}