{
  "type": "Feature",
  "properties": {
    "date:inception_lower":"1980-01-01",
    "date:inception_upper":"1980-01-31",
    "iso:country":"GB",
    "wof:name":"LL36 9LY",
    "wof:placetype":"postalcode"
},
  "geometry": {"coordinates":[-4.10393,52.630256],"type":"Point"}
}