{
  "type": "Feature",
  "properties": {
    "iso:country":"GB",
    "wof:name":"SW19 1HP",
    "wof:placetype":"postalcode"
},
  "geometry": {"coordinates":[-0.18856836513426,51.41785271105584],"type":"Point"}
}