{
  "type": "Feature",
  "properties": {
    "iso:country": "GB",
    "wof:name": "RH10 7ZE",
    "wof:placetype": "postalcode"
  },
  "geometry": {"coordinates":[-0.140966,51.113038],"type":"Point"}
}
