{
  "type": "Feature",
  "properties": {
    "date:inception_lower": "2016-08-01",
    "date:inception_upper": "2016-08-01",
    "iso:country": "GB",
    "wof:name": "RH10 7ZE",
    "wof:placetype": "postalcode"
  },
  "geometry": {"coordinates":[-0.140966,51.113038],"type":"Point"}
}
