{
  "type": "Feature",
  "properties": {
    "iso:country":"GB",
    "wof:name":"LU7 2TF",
    "wof:placetype":"postalcode"
},
  "geometry": {"coordinates":[-0.66761711792282,51.92309458329395],"type":"Point"}
}