{
  "type": "Feature",
  "properties": {
    "iso:country":"GB",
    "wof:name":"S6 2TY",
    "wof:placetype":"postalcode"
},
  "geometry": {"coordinates":[-1.49135457473102,53.39664732466073],"type":"Point"}
}