{
  "type": "Feature",
  "properties": {
    "iso:country":"GB",
    "wof:name":"CV3 6PT",
    "wof:placetype":"postalcode"
},
  "geometry": {"coordinates":[-1.52071841938126,52.39556439767441],"type":"Point"}
}