{
  "type": "Feature",
  "properties": {
    "iso:country":"GB",
    "wof:name":"BH4 9JZ",
    "wof:placetype":"postalcode"
},
  "geometry": {"coordinates":[-1.89857801144478,50.72666765930705],"type":"Point"}
}