{
  "type": "Feature",
  "properties": {
    "date:inception_lower": "2007-07-01",
    "date:inception_upper": "2007-07-01",
    "iso:country": "GB",
    "wof:name": "OX14 4FG",
    "wof:placetype": "postalcode"
  },
  "geometry": {"coordinates":[-1.297679,51.628919],"type":"Point"}
}
