{
  "type": "Feature",
  "properties": {
    "date:inception_lower":"2007-07-01",
    "date:inception_upper":"2007-07-31",
    "iso:country":"GB",
    "wof:name":"OX14 4FG",
    "wof:placetype":"postalcode"
},
  "geometry": {"coordinates":[-1.297693,51.628919],"type":"Point"}
}