{
  "type": "Feature",
  "properties": {
    "iso:country": "GB",
    "wof:name": "OX14 4FG",
    "wof:placetype": "postalcode"
  },
  "geometry": {"coordinates":[-1.297693,51.628919],"type":"Point"}
}
