{
  "type": "Feature",
  "properties": {
    "date:inception_lower": "1998-12-01",
    "date:inception_upper": "1998-12-01",
    "iso:country": "GB",
    "wof:name": "CO10 2DP",
    "wof:placetype": "postalcode"
  },
  "geometry": {"coordinates":[0.722467,52.037],"type":"Point"}
}
