{
  "type": "Feature",
  "properties": {
    "iso:country": "GB",
    "wof:name": "KA21 6JP",
    "wof:placetype": "postalcode"
  },
  "geometry": {"coordinates":[-4.783799,55.646881],"type":"Point"}
}
