{
  "type": "Feature",
  "properties": {
    "date:inception_lower": "1980-01-01",
    "date:inception_upper": "1980-01-01",
    "iso:country": "GB",
    "wof:name": "KA21 6JP",
    "wof:placetype": "postalcode"
  },
  "geometry": {"coordinates":[-4.783799,55.646881],"type":"Point"}
}
