{
  "type": "Feature",
  "properties": {
    "iso:country": "GB",
    "wof:name": "HU2 0QP",
    "wof:placetype": "postalcode"
  },
  "geometry": {"coordinates":[-0.332009,53.755079],"type":"Point"}
}
