{
  "type": "Feature",
  "properties": {
    "iso:country":"GB",
    "wof:name":"CF3 5SW",
    "wof:placetype":"postalcode"
},
  "geometry": {"coordinates":[-3.10102295703608,51.53141935025326],"type":"Point"}
}