{
  "type": "Feature",
  "properties": {
    "date:inception_lower": "2021-06-01",
    "date:inception_upper": "2021-06-01",
    "iso:country": "GB",
    "wof:name": "M33 7GR",
    "wof:placetype": "postalcode"
  },
  "geometry": {"coordinates":[-2.31749,53.431507],"type":"Point"}
}
