{
  "type": "Feature",
  "properties": {
    "iso:country": "GB",
    "wof:name": "BA22 8UD",
    "wof:placetype": "postalcode"
  },
  "geometry": {"coordinates":[-2.702632,50.938833],"type":"Point"}
}
