{
  "type": "Feature",
  "properties": {
    "date:inception_lower": "1997-12-01",
    "date:inception_upper": "1997-12-01",
    "iso:country": "GB",
    "wof:name": "TN15 6SN",
    "wof:placetype": "postalcode"
  },
  "geometry": {"coordinates":[0.210234,51.307975],"type":"Point"}
}
