{
  "type": "Feature",
  "properties": {
    "iso:country":"GB",
    "wof:name":"L7 5QT",
    "wof:placetype":"postalcode"
},
  "geometry": {"coordinates":[-2.9448478049774,53.40484775424929],"type":"Point"}
}