{
  "type": "Feature",
  "properties": {
    "date:inception_lower": "1980-01-01",
    "date:inception_upper": "1980-01-01",
    "iso:country": "GB",
    "wof:name": "CM15 0HL",
    "wof:placetype": "postalcode"
  },
  "geometry": {"coordinates":[0.30293,51.679379],"type":"Point"}
}
