{
  "type": "Feature",
  "properties": {
    "iso:country":"GB",
    "wof:name":"CM15 0HL",
    "wof:placetype":"postalcode"
},
  "geometry": {"coordinates":[0.30294597105001,51.67937470518376],"type":"Point"}
}