{
  "type": "Feature",
  "properties": {
    "iso:country":"GB",
    "wof:name":"SM6 0DD",
    "wof:placetype":"postalcode"
},
  "geometry": {"coordinates":[-0.15046910814541,51.3622854861776],"type":"Point"}
}