{
  "type": "Feature",
  "properties": {
    "iso:country":"GB",
    "wof:name":"S63 0NF",
    "wof:placetype":"postalcode"
},
  "geometry": {"coordinates":[-1.31826367659982,53.54675800474215],"type":"Point"}
}