{
  "type": "Feature",
  "properties": {
    "date:inception_lower": "1980-01-01",
    "date:inception_upper": "1980-01-01",
    "iso:country": "GB",
    "wof:name": "S63 0NF",
    "wof:placetype": "postalcode"
  },
  "geometry": {"coordinates":[-1.318264,53.546758],"type":"Point"}
}
