{
  "type": "Feature",
  "properties": {
    "iso:country":"GB",
    "wof:name":"WA4 6RT",
    "wof:placetype":"postalcode"
},
  "geometry": {"coordinates":[-2.58287645700248,53.37593721769178],"type":"Point"}
}