{
  "type": "Feature",
  "properties": {
    "iso:country":"GB",
    "wof:name":"BA13 3PN",
    "wof:placetype":"postalcode"
},
  "geometry": {"coordinates":[-2.1854143937785,51.25447239823137],"type":"Point"}
}