{
  "type": "Feature",
  "properties": {
    "iso:country": "GB",
    "wof:name": "TA8 2NZ",
    "wof:placetype": "postalcode"
  },
  "geometry": {"coordinates":[-2.997069,51.247633],"type":"Point"}
}
