{
  "type": "Feature",
  "properties": {
    "date:inception_lower": "2002-07-01",
    "date:inception_upper": "2002-07-01",
    "iso:country": "GB",
    "wof:name": "ME17 3AT",
    "wof:placetype": "postalcode"
  },
  "geometry": {"coordinates":[0.592129,51.204879],"type":"Point"}
}
