{
  "type": "Feature",
  "properties": {
    "date:inception_lower": "1980-01-01",
    "date:inception_upper": "1980-01-01",
    "iso:country": "GB",
    "wof:name": "SN1 1BT",
    "wof:placetype": "postalcode"
  },
  "geometry": {"coordinates":[-1.787887,51.56329],"type":"Point"}
}
