{
  "type": "Feature",
  "properties": {
    "iso:country":"GB",
    "wof:name":"G68 0GL",
    "wof:placetype":"postalcode"
},
  "geometry": {"coordinates":[-4.00608952450157,55.96288830806267],"type":"Point"}
}