{
  "type": "Feature",
  "properties": {
    "iso:country": "GB",
    "wof:name": "OX29 5SX",
    "wof:placetype": "postalcode"
  },
  "geometry": {"coordinates":[-1.391707,51.723742],"type":"Point"}
}
