{
  "type": "Feature",
  "properties": {
    "iso:country":"GB",
    "wof:name":"OX29 5SX",
    "wof:placetype":"postalcode"
},
  "geometry": {"coordinates":[-1.39170678471373,51.72374164906126],"type":"Point"}
}