{
  "type": "Feature",
  "properties": {
    "iso:country": "GB",
    "wof:name": "CO6 4LJ",
    "wof:placetype": "postalcode"
  },
  "geometry": {"coordinates":[0.86301,51.974188],"type":"Point"}
}
