{
  "type": "Feature",
  "properties": {
    "iso:country":"GB",
    "wof:name":"WV2 4JX",
    "wof:placetype":"postalcode"
},
  "geometry": {"coordinates":[-2.12754472848173,52.57791896701072],"type":"Point"}
}