{
  "type": "Feature",
  "properties": {
    "iso:country": "GB",
    "wof:name": "BH14 8AW",
    "wof:placetype": "postalcode"
  },
  "geometry": {"coordinates":[-1.959844,50.721021],"type":"Point"}
}
