{
  "type": "Feature",
  "properties": {
    "iso:country": "GB",
    "wof:name": "CW4 8AT",
    "wof:placetype": "postalcode"
  },
  "geometry": {"coordinates":[-2.334032,53.189603],"type":"Point"}
}
