{
  "type": "Feature",
  "properties": {
    "iso:country":"GB",
    "wof:name":"LE4 0FG",
    "wof:placetype":"postalcode"
},
  "geometry": {"coordinates":[-1.15208766217069,52.64850153246984],"type":"Point"}
}