{
  "type": "Feature",
  "properties": {
    "iso:country": "GB",
    "wof:name": "LE4 0FG",
    "wof:placetype": "postalcode"
  },
  "geometry": {"coordinates":[-1.152088,52.648502],"type":"Point"}
}
