{
  "type": "Feature",
  "properties": {
    "iso:country":"GB",
    "wof:name":"FK19 8PE",
    "wof:placetype":"postalcode"
},
  "geometry": {"coordinates":[-4.37896419385349,56.32753935081176],"type":"Point"}
}