{
  "type": "Feature",
  "properties": {
    "date:inception_lower":"1987-04-01",
    "date:inception_upper":"1987-04-30",
    "iso:country":"GB",
    "wof:name":"CM14 4FJ",
    "wof:placetype":"postalcode"
},
  "geometry": {"coordinates":[0.297547,51.616998],"type":"Point"}
}