{
  "type": "Feature",
  "properties": {
    "iso:country":"GB",
    "wof:name":"CM14 4FJ",
    "wof:placetype":"postalcode"
},
  "geometry": {"coordinates":[0.29754718213888,51.61699784266835],"type":"Point"}
}