{
  "type": "Feature",
  "properties": {
    "iso:country": "GB",
    "wof:name": "CH66 3LH",
    "wof:placetype": "postalcode"
  },
  "geometry": {"coordinates":[-2.923478,53.275807],"type":"Point"}
}
