{
  "type": "Feature",
  "properties": {
    "iso:country": "GB",
    "wof:name": "NG2 7DT",
    "wof:placetype": "postalcode"
  },
  "geometry": {"coordinates":[-1.131333,52.921164],"type":"Point"}
}
