{
  "type": "Feature",
  "properties": {
    "iso:country": "GB",
    "wof:name": "PA31 8QP",
    "wof:placetype": "postalcode"
  },
  "geometry": {"coordinates":[-5.531817,56.218212],"type":"Point"}
}
