{
  "type": "Feature",
  "properties": {
    "iso:country":"GB",
    "wof:name":"PA31 8QP",
    "wof:placetype":"postalcode"
},
  "geometry": {"coordinates":[-5.53181728818052,56.21821176195785],"type":"Point"}
}