{
  "type": "Feature",
  "properties": {
    "iso:country": "GB",
    "wof:name": "CW11 1DY",
    "wof:placetype": "postalcode"
  },
  "geometry": {"coordinates":[-2.355878,53.149287],"type":"Point"}
}
