{
  "type": "Feature",
  "properties": {
    "iso:country":"GB",
    "wof:name":"CW11 1DY",
    "wof:placetype":"postalcode"
},
  "geometry": {"coordinates":[-2.35587791775128,53.14928737974071],"type":"Point"}
}