{
  "type": "Feature",
  "properties": {
    "date:inception_lower": "1980-01-01",
    "date:inception_upper": "1980-01-01",
    "iso:country": "GB",
    "wof:name": "TA3 6BX",
    "wof:placetype": "postalcode"
  },
  "geometry": {"coordinates":[-3.003508,51.015296],"type":"Point"}
}
