{
  "type": "Feature",
  "properties": {
    "iso:country":"GB",
    "wof:name":"TA3 6BX",
    "wof:placetype":"postalcode"
},
  "geometry": {"coordinates":[-3.00477589921855,51.01556961094908],"type":"Point"}
}