{
  "type": "Feature",
  "properties": {
    "date:inception_lower": "2002-11-01",
    "date:inception_upper": "2002-11-01",
    "iso:country": "GB",
    "wof:name": "TW7 7BD",
    "wof:placetype": "postalcode"
  },
  "geometry": {"coordinates":[-0.327825,51.466377],"type":"Point"}
}
