{
  "type": "Feature",
  "properties": {
    "iso:country":"GB",
    "wof:name":"TW7 7BD",
    "wof:placetype":"postalcode"
},
  "geometry": {"coordinates":[-0.32782483918693,51.4663769790722],"type":"Point"}
}