{
  "type": "Feature",
  "properties": {
    "iso:country":"GB",
    "wof:name":"S41 0AF",
    "wof:placetype":"postalcode"
},
  "geometry": {"coordinates":[-1.41410709798206,53.21959102595482],"type":"Point"}
}