{
  "type": "Feature",
  "properties": {
    "iso:country": "GB",
    "wof:name": "ML2 8JX",
    "wof:placetype": "postalcode"
  },
  "geometry": {"coordinates":[-3.916806,55.768372],"type":"Point"}
}
