{
  "type": "Feature",
  "properties": {
    "iso:country":"GB",
    "wof:name":"ML2 8JX",
    "wof:placetype":"postalcode"
},
  "geometry": {"coordinates":[-3.91680639313843,55.76837197552654],"type":"Point"}
}