{
  "type": "Feature",
  "properties": {
    "date:inception_lower":"2001-12-01",
    "date:inception_upper":"2001-12-31",
    "iso:country":"GB",
    "wof:name":"ML2 8JX",
    "wof:placetype":"postalcode"
},
  "geometry": {"coordinates":[-3.916806,55.768372],"type":"Point"}
}