{
  "type": "Feature",
  "properties": {
    "date:inception_lower": "2000-10-01",
    "date:inception_upper": "2000-10-01",
    "iso:country": "GB",
    "wof:name": "W1W 7JS",
    "wof:placetype": "postalcode"
  },
  "geometry": {"coordinates":[-0.139899,51.518059],"type":"Point"}
}
