{
  "type": "Feature",
  "properties": {
    "iso:country":"GB",
    "wof:name":"E3 3HP",
    "wof:placetype":"postalcode"
},
  "geometry": {"coordinates":[-0.0182153491397,51.5254453502388],"type":"Point"}
}