{
  "type": "Feature",
  "properties": {
    "date:inception_lower": "1980-01-01",
    "date:inception_upper": "1980-01-01",
    "iso:country": "GB",
    "wof:name": "CF37 2HF",
    "wof:placetype": "postalcode"
  },
  "geometry": {"coordinates":[-3.344546,51.606031],"type":"Point"}
}
