{
  "type": "Feature",
  "properties": {
    "iso:country":"GB",
    "wof:name":"CF37 2HF",
    "wof:placetype":"postalcode"
},
  "geometry": {"coordinates":[-3.3445458277823,51.60603113578349],"type":"Point"}
}