{
  "type": "Feature",
  "properties": {
    "iso:country":"GB",
    "wof:name":"TQ1 4JT",
    "wof:placetype":"postalcode"
},
  "geometry": {"coordinates":[-3.53449364034554,50.47624084493747],"type":"Point"}
}