{
  "type": "Feature",
  "properties": {
    "iso:country": "GB",
    "wof:name": "HP20 1DG",
    "wof:placetype": "postalcode"
  },
  "geometry": {"coordinates":[-0.810248,51.820593],"type":"Point"}
}
