{
  "type": "Feature",
  "properties": {
    "iso:country":"GB",
    "wof:name":"SE10 0AJ",
    "wof:placetype":"postalcode"
},
  "geometry": {"coordinates":[0.00560618344463,51.48784667622268],"type":"Point"}
}