{
  "type": "Feature",
  "properties": {
    "date:inception_lower": "2007-01-01",
    "date:inception_upper": "2007-01-01",
    "iso:country": "GB",
    "wof:name": "SE10 0AJ",
    "wof:placetype": "postalcode"
  },
  "geometry": {"coordinates":[0.005606,51.487847],"type":"Point"}
}
