{
  "type": "Feature",
  "properties": {
    "iso:country":"GB",
    "wof:name":"L12 1ND",
    "wof:placetype":"postalcode"
},
  "geometry": {"coordinates":[-2.91269842399285,53.42570934508171],"type":"Point"}
}