{
  "type": "Feature",
  "properties": {
    "date:inception_lower":"1990-02-01",
    "date:inception_upper":"1990-02-28",
    "iso:country":"GB",
    "wof:name":"IP14 1UW",
    "wof:placetype":"postalcode"
},
  "geometry": {"coordinates":[0.974932,52.190706],"type":"Point"}
}