{
  "type": "Feature",
  "properties": {
    "iso:country":"GB",
    "wof:name":"IP14 1UW",
    "wof:placetype":"postalcode"
},
  "geometry": {"coordinates":[0.97493236961447,52.19070641767359],"type":"Point"}
}