{
  "type": "Feature",
  "properties": {
    "iso:country": "GB",
    "wof:name": "NR19 1UG",
    "wof:placetype": "postalcode"
  },
  "geometry": {"coordinates":[0.929276,52.663049],"type":"Point"}
}
