{
  "type": "Feature",
  "properties": {
    "iso:country":"GB",
    "wof:name":"NR19 1UG",
    "wof:placetype":"postalcode"
},
  "geometry": {"coordinates":[0.92927590698336,52.66304924491341],"type":"Point"}
}