{
  "type": "Feature",
  "properties": {
    "iso:country": "GB",
    "wof:name": "BN14 7TN",
    "wof:placetype": "postalcode"
  },
  "geometry": {"coordinates":[-0.380531,50.828315],"type":"Point"}
}
