{
  "type": "Feature",
  "properties": {
    "iso:country":"GB",
    "wof:name":"AB24 3HL",
    "wof:placetype":"postalcode"
},
  "geometry": {"coordinates":[-2.09919781706728,57.15617962820721],"type":"Point"}
}