{
  "type": "Feature",
  "properties": {
    "iso:country":"GB",
    "wof:name":"B29 7PT",
    "wof:placetype":"postalcode"
},
  "geometry": {"coordinates":[-1.91678300168941,52.43912759937564],"type":"Point"}
}