{
  "type": "Feature",
  "properties": {
    "iso:country": "GB",
    "wof:name": "B29 7PT",
    "wof:placetype": "postalcode"
  },
  "geometry": {"coordinates":[-1.916783,52.439128],"type":"Point"}
}
