{
  "type": "Feature",
  "properties": {
    "iso:country":"GB",
    "wof:name":"KT6 5DL",
    "wof:placetype":"postalcode"
},
  "geometry": {"coordinates":[-0.31029700279451,51.39051725734538],"type":"Point"}
}