{
  "type": "Feature",
  "properties": {
    "iso:country": "GB",
    "wof:name": "CW7 2BH",
    "wof:placetype": "postalcode"
  },
  "geometry": {"coordinates":[-2.526129,53.193772],"type":"Point"}
}
