{
  "type": "Feature",
  "properties": {
    "iso:country": "GB",
    "wof:name": "M16 8BZ",
    "wof:placetype": "postalcode"
  },
  "geometry": {"coordinates":[-2.260971,53.453225],"type":"Point"}
}
