{
  "type": "Feature",
  "properties": {
    "iso:country":"GB",
    "wof:name":"HR1 4NE",
    "wof:placetype":"postalcode"
},
  "geometry": {"coordinates":[-2.55812969053598,52.03985896359246],"type":"Point"}
}