{
  "type": "Feature",
  "properties": {
    "date:inception_lower": "1996-06-01",
    "date:inception_upper": "1996-06-01",
    "iso:country": "GB",
    "wof:name": "AB55 6LB",
    "wof:placetype": "postalcode"
  },
  "geometry": {"coordinates":[-2.930895,57.560835],"type":"Point"}
}
