{
  "type": "Feature",
  "properties": {
    "iso:country":"GB",
    "wof:name":"AB55 6LB",
    "wof:placetype":"postalcode"
},
  "geometry": {"coordinates":[-2.93089543439922,57.56083522635514],"type":"Point"}
}