{
  "type": "Feature",
  "properties": {
    "iso:country":"GB",
    "wof:name":"N16 6DE",
    "wof:placetype":"postalcode"
},
  "geometry": {"coordinates":[-0.06324083086449,51.57561148289819],"type":"Point"}
}