{
  "type": "Feature",
  "properties": {
    "iso:country":"GB",
    "wof:name":"CR2 7AL",
    "wof:placetype":"postalcode"
},
  "geometry": {"coordinates":[-0.08808477277076,51.35811845764643],"type":"Point"}
}