{
  "type": "Feature",
  "properties": {
    "iso:country":"GB",
    "wof:name":"HU15 1HT",
    "wof:placetype":"postalcode"
},
  "geometry": {"coordinates":[-0.56867015815572,53.7413741928481],"type":"Point"}
}