{
  "type": "Feature",
  "properties": {
    "date:inception_lower": "2019-09-01",
    "date:inception_upper": "2019-09-01",
    "iso:country": "GB",
    "wof:name": "DE15 9PB",
    "wof:placetype": "postalcode"
  },
  "geometry": {"coordinates":[-1.607898,52.795187],"type":"Point"}
}
