{
  "type": "Feature",
  "properties": {
    "iso:country": "GB",
    "wof:name": "DD10 9EZ",
    "wof:placetype": "postalcode"
  },
  "geometry": {"coordinates":[-2.47002,56.728832],"type":"Point"}
}
