{
  "type": "Feature",
  "properties": {
    "iso:country":"GB",
    "wof:name":"MK4 2DY",
    "wof:placetype":"postalcode"
},
  "geometry": {"coordinates":[-0.77698569743804,52.00126459451622],"type":"Point"}
}