{
  "type": "Feature",
  "properties": {
    "iso:country":"GB",
    "wof:name":"NE8 2ER",
    "wof:placetype":"postalcode"
},
  "geometry": {"coordinates":[-1.60469978724797,54.96581692190531],"type":"Point"}
}