{
  "type": "Feature",
  "properties": {
    "iso:country": "GB",
    "wof:name": "HU17 9PA",
    "wof:placetype": "postalcode"
  },
  "geometry": {"coordinates":[-0.413836,53.850961],"type":"Point"}
}
