{
  "type": "Feature",
  "properties": {
    "iso:country":"GB",
    "wof:name":"HU17 9PA",
    "wof:placetype":"postalcode"
},
  "geometry": {"coordinates":[-0.41383594620456,53.85096053620243],"type":"Point"}
}