{
  "type": "Feature",
  "properties": {
    "iso:country": "GB",
    "wof:name": "UB7 8BD",
    "wof:placetype": "postalcode"
  },
  "geometry": {"coordinates":[-0.467126,51.519707],"type":"Point"}
}
