{
  "type": "Feature",
  "properties": {
    "iso:country":"GB",
    "wof:name":"UB7 8BD",
    "wof:placetype":"postalcode"
},
  "geometry": {"coordinates":[-0.46712601222783,51.51970711573632],"type":"Point"}
}