{
  "type": "Feature",
  "properties": {
    "iso:country":"GB",
    "wof:name":"SE18 1RG",
    "wof:placetype":"postalcode"
},
  "geometry": {"coordinates":[0.08882140586696,51.48598008678584],"type":"Point"}
}