{
  "type": "Feature",
  "properties": {
    "iso:country":"GB",
    "wof:name":"IP24 3LE",
    "wof:placetype":"postalcode"
},
  "geometry": {"coordinates":[0.73909559925026,52.40526975617949],"type":"Point"}
}