{
  "type": "Feature",
  "properties": {
    "date:inception_lower": "1995-07-01",
    "date:inception_upper": "1995-07-01",
    "iso:country": "GB",
    "wof:name": "EN11 9BQ",
    "wof:placetype": "postalcode"
  },
  "geometry": {"coordinates":[-0.020834,51.773457],"type":"Point"}
}
