{
  "type": "Feature",
  "properties": {
    "iso:country": "GB",
    "wof:name": "LL21 9EE",
    "wof:placetype": "postalcode"
  },
  "geometry": {"coordinates":[-3.371402,53.010517],"type":"Point"}
}
