{
  "type": "Feature",
  "properties": {
    "iso:country":"GB",
    "wof:name":"EC3R 6HD",
    "wof:placetype":"postalcode"
},
  "geometry": {"coordinates":[-0.08545500562474,51.50921547556102],"type":"Point"}
}