{
  "type": "Feature",
  "properties": {
    "date:inception_lower":"2005-04-01",
    "date:inception_upper":"2005-04-30",
    "iso:country":"GB",
    "wof:name":"EC3R 6HD",
    "wof:placetype":"postalcode"
},
  "geometry": {"coordinates":[-0.085455,51.509215],"type":"Point"}
}