{
  "type": "Feature",
  "properties": {
    "iso:country":"GB",
    "wof:name":"WN2 2SW",
    "wof:placetype":"postalcode"
},
  "geometry": {"coordinates":[-2.5769769188419,53.54308192410883],"type":"Point"}
}