{
  "type": "Feature",
  "properties": {
    "iso:country": "GB",
    "wof:name": "SS16 4NW",
    "wof:placetype": "postalcode"
  },
  "geometry": {"coordinates":[0.485628,51.565573],"type":"Point"}
}
