{
  "type": "Feature",
  "properties": {
    "iso:country":"GB",
    "wof:name":"ME4 5HG",
    "wof:placetype":"postalcode"
},
  "geometry": {"coordinates":[0.538233341216,51.37482760825449],"type":"Point"}
}