{
  "type": "Feature",
  "properties": {
    "iso:country":"GB",
    "wof:name":"CF15 7JT",
    "wof:placetype":"postalcode"
},
  "geometry": {"coordinates":[-3.2472544409642,51.53519772490527],"type":"Point"}
}