{
  "type": "Feature",
  "properties": {
    "date:inception_lower": "1985-04-01",
    "date:inception_upper": "1985-04-01",
    "iso:country": "GB",
    "wof:name": "CA11 8RF",
    "wof:placetype": "postalcode"
  },
  "geometry": {"coordinates":[-2.738896,54.660831],"type":"Point"}
}
