{
  "type": "Feature",
  "properties": {
    "iso:country":"GB",
    "wof:name":"CF45 4BJ",
    "wof:placetype":"postalcode"
},
  "geometry": {"coordinates":[-3.34324025701204,51.65668805089642],"type":"Point"}
}