{
  "type": "Feature",
  "properties": {
    "date:inception_lower":"1980-01-01",
    "date:inception_upper":"1980-01-31",
    "iso:country":"GB",
    "wof:name":"CF45 4BJ",
    "wof:placetype":"postalcode"
},
  "geometry": {"coordinates":[-3.34324,51.656688],"type":"Point"}
}