{
  "type": "Feature",
  "properties": {
    "iso:country":"GB",
    "wof:name":"DT2 9JT",
    "wof:placetype":"postalcode"
},
  "geometry": {"coordinates":[-2.50182558796553,50.69884113784168],"type":"Point"}
}