{
  "type": "Feature",
  "properties": {
    "date:inception_lower": "1980-01-01",
    "date:inception_upper": "1980-01-01",
    "iso:country": "GB",
    "wof:name": "SY8 2NA",
    "wof:placetype": "postalcode"
  },
  "geometry": {"coordinates":[-2.71515,52.377963],"type":"Point"}
}
