{
  "type": "Feature",
  "properties": {
    "iso:country":"GB",
    "wof:name":"SO16 7AD",
    "wof:placetype":"postalcode"
},
  "geometry": {"coordinates":[-1.40859157768853,50.93647612642865],"type":"Point"}
}