{
  "type": "Feature",
  "properties": {
    "iso:country": "GB",
    "wof:name": "SO16 7AD",
    "wof:placetype": "postalcode"
  },
  "geometry": {"coordinates":[-1.408592,50.936476],"type":"Point"}
}
