{
  "type": "Feature",
  "properties": {
    "iso:country":"GB",
    "wof:name":"TS3 0RE",
    "wof:placetype":"postalcode"
},
  "geometry": {"coordinates":[-1.17630360719633,54.55350327106667],"type":"Point"}
}