{
  "type": "Feature",
  "properties": {
    "iso:country":"GB",
    "wof:name":"S36 1DG",
    "wof:placetype":"postalcode"
},
  "geometry": {"coordinates":[-1.59809715889148,53.47829271076731],"type":"Point"}
}