{
  "type": "Feature",
  "properties": {
    "iso:country": "GB",
    "wof:name": "SY11 1RR",
    "wof:placetype": "postalcode"
  },
  "geometry": {"coordinates":[-3.061359,52.858905],"type":"Point"}
}
