{
  "type": "Feature",
  "properties": {
    "date:inception_lower":"1980-01-01",
    "date:inception_upper":"1980-01-31",
    "iso:country":"GB",
    "wof:name":"SY11 1RR",
    "wof:placetype":"postalcode"
},
  "geometry": {"coordinates":[-3.061359,52.858905],"type":"Point"}
}