{
  "type": "Feature",
  "properties": {
    "iso:country":"GB",
    "wof:name":"SY11 1RR",
    "wof:placetype":"postalcode"
},
  "geometry": {"coordinates":[-3.06135888007318,52.85890459865899],"type":"Point"}
}