{
  "type": "Feature",
  "properties": {
    "date:inception_lower": "2017-10-01",
    "date:inception_upper": "2017-10-01",
    "iso:country": "GB",
    "wof:name": "DA13 9PQ",
    "wof:placetype": "postalcode"
  },
  "geometry": {"coordinates":[0.315644,51.411195],"type":"Point"}
}
