{
  "type": "Feature",
  "properties": {
    "iso:country": "GB",
    "wof:name": "DA13 9PQ",
    "wof:placetype": "postalcode"
  },
  "geometry": {"coordinates":[0.315644,51.411195],"type":"Point"}
}
