{
  "type": "Feature",
  "properties": {
    "iso:country":"GB",
    "wof:name":"NP11 3XG",
    "wof:placetype":"postalcode"
},
  "geometry": {"coordinates":[-3.16312323758153,51.69327323493101],"type":"Point"}
}