{
  "type": "Feature",
  "properties": {
    "iso:country": "GB",
    "wof:name": "NP11 3XG",
    "wof:placetype": "postalcode"
  },
  "geometry": {"coordinates":[-3.163123,51.693273],"type":"Point"}
}
