{
  "type": "Feature",
  "properties": {
    "date:inception_lower":"1999-06-01",
    "date:inception_upper":"1999-06-30",
    "iso:country":"GB",
    "wof:name":"NP11 3XG",
    "wof:placetype":"postalcode"
},
  "geometry": {"coordinates":[-3.163123,51.693273],"type":"Point"}
}