{
  "type": "Feature",
  "properties": {
    "iso:country": "GB",
    "wof:name": "SE15 3LD",
    "wof:placetype": "postalcode"
  },
  "geometry": {"coordinates":[-0.056719,51.461801],"type":"Point"}
}
