{
  "type": "Feature",
  "properties": {
    "iso:country":"GB",
    "wof:name":"B11 3LH",
    "wof:placetype":"postalcode"
},
  "geometry": {"coordinates":[-1.86051270727952,52.44932336865888],"type":"Point"}
}