{
  "type": "Feature",
  "properties": {
    "iso:country": "GB",
    "wof:name": "TQ2 8GT",
    "wof:placetype": "postalcode"
  },
  "geometry": {"coordinates":[-3.543357,50.490028],"type":"Point"}
}
