{
  "type": "Feature",
  "properties": {
    "iso:country":"GB",
    "wof:name":"TQ2 8GT",
    "wof:placetype":"postalcode"
},
  "geometry": {"coordinates":[-3.54335727941799,50.49004579253322],"type":"Point"}
}