{
  "type": "Feature",
  "properties": {
    "iso:country":"GB",
    "wof:name":"TR10 8RE",
    "wof:placetype":"postalcode"
},
  "geometry": {"coordinates":[-5.11717104170537,50.17097546715701],"type":"Point"}
}