{
  "type": "Feature",
  "properties": {
    "iso:country":"GB",
    "wof:name":"SO21 1QN",
    "wof:placetype":"postalcode"
},
  "geometry": {"coordinates":[-1.31994899474231,51.0160891203195],"type":"Point"}
}