{
  "type": "Feature",
  "properties": {
    "date:inception_lower": "1980-01-01",
    "date:inception_upper": "1980-01-01",
    "iso:country": "GB",
    "wof:name": "SO21 1QN",
    "wof:placetype": "postalcode"
  },
  "geometry": {"coordinates":[-1.319949,51.016089],"type":"Point"}
}
