{
  "type": "Feature",
  "properties": {
    "iso:country":"GB",
    "wof:name":"HP1 1TQ",
    "wof:placetype":"postalcode"
},
  "geometry": {"coordinates":[-0.4817451836246,51.75673678755293],"type":"Point"}
}