{
  "type": "Feature",
  "properties": {
    "iso:country": "GB",
    "wof:name": "HP1 1TQ",
    "wof:placetype": "postalcode"
  },
  "geometry": {"coordinates":[-0.481745,51.756737],"type":"Point"}
}
