{
  "type": "Feature",
  "properties": {
    "iso:country":"GB",
    "wof:name":"BD21 3PY",
    "wof:placetype":"postalcode"
},
  "geometry": {"coordinates":[-1.90793243365087,53.86686076923756],"type":"Point"}
}