{
  "type": "Feature",
  "properties": {
    "iso:country":"GB",
    "wof:name":"KY11 2WP",
    "wof:placetype":"postalcode"
},
  "geometry": {"coordinates":[-3.43722265111295,56.02552407602638],"type":"Point"}
}