{
  "type": "Feature",
  "properties": {
    "iso:country":"GB",
    "wof:name":"NG23 6LL",
    "wof:placetype":"postalcode"
},
  "geometry": {"coordinates":[-0.86221342014404,53.17349493969416],"type":"Point"}
}