{
  "type": "Feature",
  "properties": {
    "iso:country": "GB",
    "wof:name": "NG23 6LL",
    "wof:placetype": "postalcode"
  },
  "geometry": {"coordinates":[-0.862213,53.173495],"type":"Point"}
}
