{
  "type": "Feature",
  "properties": {
    "iso:country":"GB",
    "wof:name":"NW8 8DL",
    "wof:placetype":"postalcode"
},
  "geometry": {"coordinates":[-0.17159548862283,51.52199244139043],"type":"Point"}
}