{
  "type": "Feature",
  "properties": {
    "date:inception_lower": "1980-01-01",
    "date:inception_upper": "1980-01-01",
    "iso:country": "GB",
    "wof:name": "NW8 8DL",
    "wof:placetype": "postalcode"
  },
  "geometry": {"coordinates":[-0.171595,51.521992],"type":"Point"}
}
