{
  "type": "Feature",
  "properties": {
    "iso:country":"GB",
    "wof:name":"SO43 7BP",
    "wof:placetype":"postalcode"
},
  "geometry": {"coordinates":[-1.57391995705115,50.86771140429074],"type":"Point"}
}