{
  "type": "Feature",
  "properties": {
    "iso:country":"GB",
    "wof:name":"BA1 7TX",
    "wof:placetype":"postalcode"
},
  "geometry": {"coordinates":[-2.30060522232097,51.40102345932011],"type":"Point"}
}