{
  "type": "Feature",
  "properties": {
    "iso:country": "GB",
    "wof:name": "DY9 9JU",
    "wof:placetype": "postalcode"
  },
  "geometry": {"coordinates":[-2.113526,52.43766],"type":"Point"}
}
