{
  "type": "Feature",
  "properties": {
    "iso:country":"GB",
    "wof:name":"DY9 9JU",
    "wof:placetype":"postalcode"
},
  "geometry": {"coordinates":[-2.11353175462591,52.4376455608036],"type":"Point"}
}