{
  "type": "Feature",
  "properties": {
    "iso:country": "GB",
    "wof:name": "DY9 9JU",
    "wof:placetype": "postalcode"
  },
  "geometry": {"coordinates":[-2.11229,52.437526],"type":"Point"}
}
