{
  "type": "Feature",
  "properties": {
    "iso:country":"GB",
    "wof:name":"L23 0TQ",
    "wof:placetype":"postalcode"
},
  "geometry": {"coordinates":[-3.0179910496325,53.48831060577385],"type":"Point"}
}