{
  "type": "Feature",
  "properties": {
    "iso:country": "GB",
    "wof:name": "AB31 5WT",
    "wof:placetype": "postalcode"
  },
  "geometry": {"coordinates":[-2.488716,57.051807],"type":"Point"}
}
