{
  "type": "Feature",
  "properties": {
    "iso:country":"GB",
    "wof:name":"AB31 5WT",
    "wof:placetype":"postalcode"
},
  "geometry": {"coordinates":[-2.48871593819858,57.05180681927619],"type":"Point"}
}