{
  "type": "Feature",
  "properties": {
    "iso:country":"GB",
    "wof:name":"EX2 5LX",
    "wof:placetype":"postalcode"
},
  "geometry": {"coordinates":[-3.49608061298409,50.71437521719148],"type":"Point"}
}