{
  "type": "Feature",
  "properties": {
    "iso:country":"GB",
    "wof:name":"DA13 0BP",
    "wof:placetype":"postalcode"
},
  "geometry": {"coordinates":[0.37386347959301,51.36965875627565],"type":"Point"}
}