{
  "type": "Feature",
  "properties": {
    "iso:country":"GB",
    "wof:name":"PO22 9BA",
    "wof:placetype":"postalcode"
},
  "geometry": {"coordinates":[-0.67917816866819,50.79840818947735],"type":"Point"}
}