{
  "type": "Feature",
  "properties": {
    "iso:country":"GB",
    "wof:name":"NG10 5AR",
    "wof:placetype":"postalcode"
},
  "geometry": {"coordinates":[-1.28753191941616,52.92599624626244],"type":"Point"}
}