{
  "type": "Feature",
  "properties": {
    "date:inception_lower": "2013-01-01",
    "date:inception_upper": "2013-01-01",
    "iso:country": "GB",
    "wof:name": "NG10 5AR",
    "wof:placetype": "postalcode"
  },
  "geometry": {"coordinates":[-1.287532,52.925996],"type":"Point"}
}
