{
  "type": "Feature",
  "properties": {
    "iso:country": "GB",
    "wof:name": "PL6 8EQ",
    "wof:placetype": "postalcode"
  },
  "geometry": {"coordinates":[-4.118155,50.409961],"type":"Point"}
}
