{
  "type": "Feature",
  "properties": {
    "iso:country": "GB",
    "wof:name": "EX1 3XN",
    "wof:placetype": "postalcode"
  },
  "geometry": {"coordinates":[-3.456369,50.736973],"type":"Point"}
}
