{
  "type": "Feature",
  "properties": {
    "iso:country":"GB",
    "wof:name":"SN2 5EP",
    "wof:placetype":"postalcode"
},
  "geometry": {"coordinates":[-1.77830770541197,51.59014754523447],"type":"Point"}
}