{
  "type": "Feature",
  "properties": {
    "iso:country": "GB",
    "wof:name": "SN2 5EP",
    "wof:placetype": "postalcode"
  },
  "geometry": {"coordinates":[-1.778308,51.590148],"type":"Point"}
}
