{
  "type": "Feature",
  "properties": {
    "iso:country":"GB",
    "wof:name":"TF1 3LU",
    "wof:placetype":"postalcode"
},
  "geometry": {"coordinates":[-2.52123988735405,52.70792004913158],"type":"Point"}
}