{
  "type": "Feature",
  "properties": {
    "date:inception_lower":"1980-01-01",
    "date:inception_upper":"1980-01-31",
    "iso:country":"GB",
    "wof:name":"TF1 3LU",
    "wof:placetype":"postalcode"
},
  "geometry": {"coordinates":[-2.52124,52.70792],"type":"Point"}
}