{
  "type": "Feature",
  "properties": {
    "iso:country":"GB",
    "wof:name":"NR11 6DE",
    "wof:placetype":"postalcode"
},
  "geometry": {"coordinates":[1.24303243088643,52.79497147469424],"type":"Point"}
}