{
  "type": "Feature",
  "properties": {
    "iso:country": "GB",
    "wof:name": "SA61 2AL",
    "wof:placetype": "postalcode"
  },
  "geometry": {"coordinates":[-4.968856,51.802912],"type":"Point"}
}
