{
  "type": "Feature",
  "properties": {
    "iso:country": "GB",
    "wof:name": "IV32 7DH",
    "wof:placetype": "postalcode"
  },
  "geometry": {"coordinates":[-3.099081,57.614828],"type":"Point"}
}
