{
  "type": "Feature",
  "properties": {
    "date:inception_lower": "1980-01-01",
    "date:inception_upper": "1980-01-01",
    "iso:country": "GB",
    "wof:name": "SK8 2NT",
    "wof:placetype": "postalcode"
  },
  "geometry": {"coordinates":[-2.219304,53.39785],"type":"Point"}
}
