{
  "type": "Feature",
  "properties": {
    "iso:country":"GB",
    "wof:name":"SK8 2NT",
    "wof:placetype":"postalcode"
},
  "geometry": {"coordinates":[-2.21931973980144,53.39783325288673],"type":"Point"}
}