{
  "type": "Feature",
  "properties": {
    "date:inception_lower": "1980-01-01",
    "date:inception_upper": "1980-01-01",
    "iso:country": "GB",
    "wof:name": "L9 0ER",
    "wof:placetype": "postalcode"
  },
  "geometry": {"coordinates":[-2.956608,53.46569],"type":"Point"}
}
