{
  "type": "Feature",
  "properties": {
    "date:inception_lower":"1980-01-01",
    "date:inception_upper":"1980-01-31",
    "iso:country":"GB",
    "wof:name":"EX2 5QJ",
    "wof:placetype":"postalcode"
},
  "geometry": {"coordinates":[-3.482111,50.721452],"type":"Point"}
}