{
  "type": "Feature",
  "properties": {
    "iso:country":"GB",
    "wof:name":"NE9 7QQ",
    "wof:placetype":"postalcode"
},
  "geometry": {"coordinates":[-1.55697552651452,54.91966050433572],"type":"Point"}
}