{
  "type": "Feature",
  "properties": {
    "iso:country": "GB",
    "wof:name": "NE9 7QQ",
    "wof:placetype": "postalcode"
  },
  "geometry": {"coordinates":[-1.556975,54.919661],"type":"Point"}
}
