{
  "type": "Feature",
  "properties": {
    "iso:country": "GB",
    "wof:name": "OL6 6AH",
    "wof:placetype": "postalcode"
  },
  "geometry": {"coordinates":[-2.080642,53.491666],"type":"Point"}
}
