{
  "type": "Feature",
  "properties": {
    "iso:country":"GB",
    "wof:name":"OL6 6AH",
    "wof:placetype":"postalcode"
},
  "geometry": {"coordinates":[-2.08062793901041,53.49182962004344],"type":"Point"}
}