{
  "type": "Feature",
  "properties": {
    "iso:country":"GB",
    "wof:name":"TN23 7HJ",
    "wof:placetype":"postalcode"
},
  "geometry": {"coordinates":[0.87028679474156,51.14408327369313],"type":"Point"}
}