{
  "type": "Feature",
  "properties": {
    "date:inception_lower": "1980-01-01",
    "date:inception_upper": "1980-01-01",
    "iso:country": "GB",
    "wof:name": "RH16 1HW",
    "wof:placetype": "postalcode"
  },
  "geometry": {"coordinates":[-0.111392,51.000782],"type":"Point"}
}
