{
  "type": "Feature",
  "properties": {
    "date:inception_lower":"1994-05-01",
    "date:inception_upper":"1994-05-31",
    "iso:country":"GB",
    "wof:name":"CB11 4XU",
    "wof:placetype":"postalcode"
},
  "geometry": {"coordinates":[0.20845,52.034775],"type":"Point"}
}