{
  "type": "Feature",
  "properties": {
    "iso:country": "GB",
    "wof:name": "CB11 4XU",
    "wof:placetype": "postalcode"
  },
  "geometry": {"coordinates":[0.20845,52.034775],"type":"Point"}
}
