{
  "type": "Feature",
  "properties": {
    "date:inception_lower":"1980-01-01",
    "date:inception_upper":"1980-01-31",
    "iso:country":"GB",
    "wof:name":"WD7 7LW",
    "wof:placetype":"postalcode"
},
  "geometry": {"coordinates":[-0.314412,51.683149],"type":"Point"}
}