{
  "type": "Feature",
  "properties": {
    "iso:country": "GB",
    "wof:name": "NE37 1TS",
    "wof:placetype": "postalcode"
  },
  "geometry": {"coordinates":[-1.53876,54.90676],"type":"Point"}
}
