{
  "type": "Feature",
  "properties": {
    "iso:country":"GB",
    "wof:name":"YO23 7HJ",
    "wof:placetype":"postalcode"
},
  "geometry": {"coordinates":[-1.15884320839665,53.87282143387436],"type":"Point"}
}