{
  "type": "Feature",
  "properties": {
    "iso:country": "GB",
    "wof:name": "YO23 7HJ",
    "wof:placetype": "postalcode"
  },
  "geometry": {"coordinates":[-1.158843,53.872821],"type":"Point"}
}
