{
  "type": "Feature",
  "properties": {
    "iso:country": "GB",
    "wof:name": "B8 3RJ",
    "wof:placetype": "postalcode"
  },
  "geometry": {"coordinates":[-1.824167,52.486898],"type":"Point"}
}
