{
  "type": "Feature",
  "properties": {
    "iso:country": "GB",
    "wof:name": "BN24 5PA",
    "wof:placetype": "postalcode"
  },
  "geometry": {"coordinates":[0.297797,50.814188],"type":"Point"}
}
