{
  "type": "Feature",
  "properties": {
    "iso:country": "GB",
    "wof:name": "HA3 7ET",
    "wof:placetype": "postalcode"
  },
  "geometry": {"coordinates":[-0.337184,51.601673],"type":"Point"}
}
