{
  "type": "Feature",
  "properties": {
    "iso:country":"GB",
    "wof:name":"HA3 7ET",
    "wof:placetype":"postalcode"
},
  "geometry": {"coordinates":[-0.33718386126841,51.60167279352346],"type":"Point"}
}