{
  "type": "Feature",
  "properties": {
    "iso:country":"GB",
    "wof:name":"AB56 1RT",
    "wof:placetype":"postalcode"
},
  "geometry": {"coordinates":[-2.98098527877672,57.67190681703156],"type":"Point"}
}