{
  "type": "Feature",
  "properties": {
    "iso:country":"GB",
    "wof:name":"OX5 1NY",
    "wof:placetype":"postalcode"
},
  "geometry": {"coordinates":[-1.30072107447839,51.80600874933989],"type":"Point"}
}