{
  "type": "Feature",
  "properties": {
    "iso:country": "GB",
    "wof:name": "OX5 1NY",
    "wof:placetype": "postalcode"
  },
  "geometry": {"coordinates":[-1.300305,51.805737],"type":"Point"}
}
