{
  "type": "Feature",
  "properties": {
    "date:inception_lower":"1994-12-01",
    "date:inception_upper":"1994-12-31",
    "iso:country":"GB",
    "wof:name":"OX5 1NY",
    "wof:placetype":"postalcode"
},
  "geometry": {"coordinates":[-1.300305,51.805737],"type":"Point"}
}