{
  "type": "Feature",
  "properties": {
    "iso:country":"GB",
    "wof:name":"S72 7DT",
    "wof:placetype":"postalcode"
},
  "geometry": {"coordinates":[-1.37987742307119,53.58027861685634],"type":"Point"}
}