{
  "type": "Feature",
  "properties": {
    "iso:country": "GB",
    "wof:name": "S72 7DT",
    "wof:placetype": "postalcode"
  },
  "geometry": {"coordinates":[-1.379877,53.580279],"type":"Point"}
}
