{
  "type": "Feature",
  "properties": {
    "iso:country":"GB",
    "wof:name":"TF7 4NA",
    "wof:placetype":"postalcode"
},
  "geometry": {"coordinates":[-2.42140009991149,52.6394827981171],"type":"Point"}
}