{
  "type": "Feature",
  "properties": {
    "iso:country": "GB",
    "wof:name": "TF7 4NA",
    "wof:placetype": "postalcode"
  },
  "geometry": {"coordinates":[-2.4214,52.639483],"type":"Point"}
}
