{
  "type": "Feature",
  "properties": {
    "date:inception_lower": "1987-10-01",
    "date:inception_upper": "1987-10-01",
    "iso:country": "GB",
    "wof:name": "TF7 4NA",
    "wof:placetype": "postalcode"
  },
  "geometry": {"coordinates":[-2.4214,52.639483],"type":"Point"}
}
