{
  "type": "Feature",
  "properties": {
    "iso:country": "GB",
    "wof:name": "PO30 1RD",
    "wof:placetype": "postalcode"
  },
  "geometry": {"coordinates":[-1.301952,50.694696],"type":"Point"}
}
