{
  "type": "Feature",
  "properties": {
    "date:inception_lower":"1980-01-01",
    "date:inception_upper":"1980-01-31",
    "iso:country":"GB",
    "wof:name":"BN16 1PT",
    "wof:placetype":"postalcode"
},
  "geometry": {"coordinates":[-0.477184,50.807898],"type":"Point"}
}