{
  "type": "Feature",
  "properties": {
    "iso:country":"GB",
    "wof:name":"BN16 1PT",
    "wof:placetype":"postalcode"
},
  "geometry": {"coordinates":[-0.47718375224697,50.80789834034859],"type":"Point"}
}