{
  "type": "Feature",
  "properties": {
    "iso:country":"GB",
    "wof:name":"B6 7BT",
    "wof:placetype":"postalcode"
},
  "geometry": {"coordinates":[-1.87657208665372,52.51552526238465],"type":"Point"}
}