{
  "type": "Feature",
  "properties": {
    "iso:country":"GB",
    "wof:name":"L22 8QE",
    "wof:placetype":"postalcode"
},
  "geometry": {"coordinates":[-3.0327669677832,53.4773791974797],"type":"Point"}
}