{
  "type": "Feature",
  "properties": {
    "iso:country": "GB",
    "wof:name": "TR14 7XL",
    "wof:placetype": "postalcode"
  },
  "geometry": {"coordinates":[-5.298511,50.209108],"type":"Point"}
}
