{
  "type": "Feature",
  "properties": {
    "iso:country":"GB",
    "wof:name":"TR14 7XL",
    "wof:placetype":"postalcode"
},
  "geometry": {"coordinates":[-5.2985106891671,50.20910773776526],"type":"Point"}
}