{
  "type": "Feature",
  "properties": {
    "iso:country":"GB",
    "wof:name":"LE5 3RE",
    "wof:placetype":"postalcode"
},
  "geometry": {"coordinates":[-1.10670658577862,52.63704759397431],"type":"Point"}
}