{
  "type": "Feature",
  "properties": {
    "iso:country":"GB",
    "wof:name":"AB23 8RJ",
    "wof:placetype":"postalcode"
},
  "geometry": {"coordinates":[-2.09638783058756,57.20060260627668],"type":"Point"}
}