{
  "type": "Feature",
  "properties": {
    "iso:country":"GB",
    "wof:name":"BL2 3QB",
    "wof:placetype":"postalcode"
},
  "geometry": {"coordinates":[-2.38708483410821,53.59846096340318],"type":"Point"}
}