{
  "type": "Feature",
  "properties": {
    "iso:country":"GB",
    "wof:name":"PE7 8FB",
    "wof:placetype":"postalcode"
},
  "geometry": {"coordinates":[-0.26915854384408,52.54227006179962],"type":"Point"}
}