{
  "type": "Feature",
  "properties": {
    "iso:country":"GB",
    "wof:name":"PR1 5UT",
    "wof:placetype":"postalcode"
},
  "geometry": {"coordinates":[-2.67668810268497,53.76641413672976],"type":"Point"}
}