{
  "type": "Feature",
  "properties": {
    "iso:country":"GB",
    "wof:name":"SL6 8JT",
    "wof:placetype":"postalcode"
},
  "geometry": {"coordinates":[-0.69955699879189,51.53687392236178],"type":"Point"}
}