{
  "type": "Feature",
  "properties": {
    "date:inception_lower": "1980-01-01",
    "date:inception_upper": "1980-01-01",
    "iso:country": "GB",
    "wof:name": "SL6 8JT",
    "wof:placetype": "postalcode"
  },
  "geometry": {"coordinates":[-0.700299,51.536993],"type":"Point"}
}
