{
  "type": "Feature",
  "properties": {
    "date:inception_lower": "1980-01-01",
    "date:inception_upper": "1980-01-01",
    "iso:country": "GB",
    "wof:name": "LL31 9BW",
    "wof:placetype": "postalcode"
  },
  "geometry": {"coordinates":[-3.831883,53.300648],"type":"Point"}
}
