{
  "type": "Feature",
  "properties": {
    "iso:country":"GB",
    "wof:name":"CR7 7QL",
    "wof:placetype":"postalcode"
},
  "geometry": {"coordinates":[-0.11079800490725,51.40023120530762],"type":"Point"}
}