{
  "type": "Feature",
  "properties": {
    "date:inception_lower": "2019-02-01",
    "date:inception_upper": "2019-02-01",
    "iso:country": "GB",
    "wof:name": "M26 4AQ",
    "wof:placetype": "postalcode"
  },
  "geometry": {"coordinates":[-2.331868,53.582751],"type":"Point"}
}
