{
  "type": "Feature",
  "properties": {
    "iso:country":"GB",
    "wof:name":"SA1 2AA",
    "wof:placetype":"postalcode"
},
  "geometry": {"coordinates":[-3.93766567443119,51.62393133796617],"type":"Point"}
}