{
  "type": "Feature",
  "properties": {
    "date:inception_lower": "2003-11-01",
    "date:inception_upper": "2003-11-01",
    "iso:country": "GB",
    "wof:name": "SA1 2AA",
    "wof:placetype": "postalcode"
  },
  "geometry": {"coordinates":[-3.938301,51.624169],"type":"Point"}
}
