{
  "type": "Feature",
  "properties": {
    "iso:country":"GB",
    "wof:name":"DY3 1YQ",
    "wof:placetype":"postalcode"
},
  "geometry": {"coordinates":[-2.11582080116265,52.53616422045866],"type":"Point"}
}