{
  "type": "Feature",
  "properties": {
    "date:inception_lower": "1994-12-01",
    "date:inception_upper": "1994-12-01",
    "iso:country": "GB",
    "wof:name": "DY3 1YQ",
    "wof:placetype": "postalcode"
  },
  "geometry": {"coordinates":[-2.115815,52.536197],"type":"Point"}
}
