{
  "type": "Feature",
  "properties": {
    "iso:country": "GB",
    "wof:name": "DY3 1YQ",
    "wof:placetype": "postalcode"
  },
  "geometry": {"coordinates":[-2.115815,52.536197],"type":"Point"}
}
