{
  "type": "Feature",
  "properties": {
    "iso:country": "GB",
    "wof:name": "TW12 3UZ",
    "wof:placetype": "postalcode"
  },
  "geometry": {"coordinates":[-0.386789,51.426917],"type":"Point"}
}
