{
  "type": "Feature",
  "properties": {
    "date:inception_lower": "1988-03-01",
    "date:inception_upper": "1988-03-01",
    "iso:country": "GB",
    "wof:name": "TW12 3UZ",
    "wof:placetype": "postalcode"
  },
  "geometry": {"coordinates":[-0.386789,51.426917],"type":"Point"}
}
