{
  "type": "Feature",
  "properties": {
    "iso:country": "GB",
    "wof:name": "B63 4QL",
    "wof:placetype": "postalcode"
  },
  "geometry": {"coordinates":[-2.059531,52.441817],"type":"Point"}
}
