{
  "type": "Feature",
  "properties": {
    "iso:country": "GB",
    "wof:name": "CM13 1EX",
    "wof:placetype": "postalcode"
  },
  "geometry": {"coordinates":[0.347612,51.638772],"type":"Point"}
}
