{
  "type": "Feature",
  "properties": {
    "date:inception_lower": "1980-01-01",
    "date:inception_upper": "1980-01-01",
    "iso:country": "GB",
    "wof:name": "CM13 1EX",
    "wof:placetype": "postalcode"
  },
  "geometry": {"coordinates":[0.347612,51.638772],"type":"Point"}
}
