{
  "type": "Feature",
  "properties": {
    "iso:country":"GB",
    "wof:name":"CM13 1EX",
    "wof:placetype":"postalcode"
},
  "geometry": {"coordinates":[0.34762811308,51.63876800841719],"type":"Point"}
}