{
  "type": "Feature",
  "properties": {
    "iso:country":"GB",
    "wof:name":"CH43 7YW",
    "wof:placetype":"postalcode"
},
  "geometry": {"coordinates":[-3.0828308033343,53.40312756633283],"type":"Point"}
}