{
  "type": "Feature",
  "properties": {
    "date:inception_lower": "1980-01-01",
    "date:inception_upper": "1980-01-01",
    "iso:country": "GB",
    "wof:name": "TN10 4JT",
    "wof:placetype": "postalcode"
  },
  "geometry": {"coordinates":[0.300698,51.209769],"type":"Point"}
}
