{
  "type": "Feature",
  "properties": {
    "iso:country": "GB",
    "wof:name": "NG1 1DU",
    "wof:placetype": "postalcode"
  },
  "geometry": {"coordinates":[-1.13806,52.95382],"type":"Point"}
}
