{
  "type": "Feature",
  "properties": {
    "iso:country":"GB",
    "wof:name":"NG1 1DU",
    "wof:placetype":"postalcode"
},
  "geometry": {"coordinates":[-1.13821020385517,52.95386381733842],"type":"Point"}
}