{
  "type": "Feature",
  "properties": {
    "iso:country":"GB",
    "wof:name":"KT9 1JG",
    "wof:placetype":"postalcode"
},
  "geometry": {"coordinates":[-0.29527583265662,51.36463501906798],"type":"Point"}
}