{
  "type": "Feature",
  "properties": {
    "iso:country":"GB",
    "wof:name":"BA3 3QW",
    "wof:placetype":"postalcode"
},
  "geometry": {"coordinates":[-2.45211905472058,51.282915244043],"type":"Point"}
}