{
  "type": "Feature",
  "properties": {
    "iso:country":"GB",
    "wof:name":"LE9 9QE",
    "wof:placetype":"postalcode"
},
  "geometry": {"coordinates":[-1.34543213610589,52.63400354158235],"type":"Point"}
}