{
  "type": "Feature",
  "properties": {
    "iso:country": "GB",
    "wof:name": "LE9 9QE",
    "wof:placetype": "postalcode"
  },
  "geometry": {"coordinates":[-1.345432,52.634004],"type":"Point"}
}
