{
  "type": "Feature",
  "properties": {
    "date:inception_lower":"2013-07-01",
    "date:inception_upper":"2013-07-31",
    "iso:country":"GB",
    "wof:name":"LE9 9QE",
    "wof:placetype":"postalcode"
},
  "geometry": {"coordinates":[-1.345432,52.634004],"type":"Point"}
}