{
  "type": "Feature",
  "properties": {
    "iso:country":"GB",
    "wof:name":"SO15 3DX",
    "wof:placetype":"postalcode"
},
  "geometry": {"coordinates":[-1.42854523651766,50.91431013580979],"type":"Point"}
}