{
  "type": "Feature",
  "properties": {
    "date:inception_lower": "1980-01-01",
    "date:inception_upper": "1980-01-01",
    "iso:country": "GB",
    "wof:name": "S64 8QH",
    "wof:placetype": "postalcode"
  },
  "geometry": {"coordinates":[-1.315852,53.490404],"type":"Point"}
}
