{
  "type": "Feature",
  "properties": {
    "iso:country":"GB",
    "wof:name":"S64 8QH",
    "wof:placetype":"postalcode"
},
  "geometry": {"coordinates":[-1.31585155254381,53.49040391511431],"type":"Point"}
}