{
  "type": "Feature",
  "properties": {
    "iso:country": "GB",
    "wof:name": "TS15 9JU",
    "wof:placetype": "postalcode"
  },
  "geometry": {"coordinates":[-1.288551,54.50653],"type":"Point"}
}
