{
  "type": "Feature",
  "properties": {
    "iso:country":"GB",
    "wof:name":"WA14 2TT",
    "wof:placetype":"postalcode"
},
  "geometry": {"coordinates":[-2.36212332483012,53.37751253335249],"type":"Point"}
}