{
  "type": "Feature",
  "properties": {
    "iso:country":"GB",
    "wof:name":"YO51 9QP",
    "wof:placetype":"postalcode"
},
  "geometry": {"coordinates":[-1.36165012530719,54.05999401436237],"type":"Point"}
}