{
  "type": "Feature",
  "properties": {
    "iso:country": "GB",
    "wof:name": "RM10 7RP",
    "wof:placetype": "postalcode"
  },
  "geometry": {"coordinates":[0.147977,51.558888],"type":"Point"}
}
