{
  "type": "Feature",
  "properties": {
    "iso:country":"GB",
    "wof:name":"EH23 4JT",
    "wof:placetype":"postalcode"
},
  "geometry": {"coordinates":[-3.04428298659145,55.83741566717796],"type":"Point"}
}