{
  "type": "Feature",
  "properties": {
    "iso:country": "GB",
    "wof:name": "EH23 4JT",
    "wof:placetype": "postalcode"
  },
  "geometry": {"coordinates":[-3.044283,55.837416],"type":"Point"}
}
