{
  "type": "Feature",
  "properties": {
    "date:inception_lower": "1980-01-01",
    "date:inception_upper": "1980-01-01",
    "iso:country": "GB",
    "wof:name": "EH23 4JT",
    "wof:placetype": "postalcode"
  },
  "geometry": {"coordinates":[-3.044283,55.837416],"type":"Point"}
}
