{
  "type": "Feature",
  "properties": {
    "date:inception_lower": "1980-01-01",
    "date:inception_upper": "1980-01-01",
    "iso:country": "GB",
    "wof:name": "GU1 1YB",
    "wof:placetype": "postalcode"
  },
  "geometry": {"coordinates":[-0.542683,51.255443],"type":"Point"}
}
