{
  "type": "Feature",
  "properties": {
    "iso:country":"GB",
    "wof:name":"GU1 1YB",
    "wof:placetype":"postalcode"
},
  "geometry": {"coordinates":[-0.54268267296928,51.25544283464581],"type":"Point"}
}