{
  "type": "Feature",
  "properties": {
    "iso:country": "GB",
    "wof:name": "DL13 1RB",
    "wof:placetype": "postalcode"
  },
  "geometry": {"coordinates":[-2.186638,54.744827],"type":"Point"}
}
