{
  "type": "Feature",
  "properties": {
    "iso:country":"GB",
    "wof:name":"DL13 1RB",
    "wof:placetype":"postalcode"
},
  "geometry": {"coordinates":[-2.1866379945201,54.74482743471793],"type":"Point"}
}