{
  "type": "Feature",
  "properties": {
    "date:inception_lower":"2008-07-01",
    "date:inception_upper":"2008-07-31",
    "iso:country":"GB",
    "wof:name":"TN26 3DW",
    "wof:placetype":"postalcode"
},
  "geometry": {"coordinates":[0.785573,51.132084],"type":"Point"}
}