{
  "type": "Feature",
  "properties": {
    "iso:country":"GB",
    "wof:name":"LE12 7RW",
    "wof:placetype":"postalcode"
},
  "geometry": {"coordinates":[-1.10983629213325,52.72889432632667],"type":"Point"}
}