{
  "type": "Feature",
  "properties": {
    "iso:country": "GB",
    "wof:name": "LE12 7RW",
    "wof:placetype": "postalcode"
  },
  "geometry": {"coordinates":[-1.109766,52.728714],"type":"Point"}
}
