{
  "type": "Feature",
  "properties": {
    "iso:country":"GB",
    "wof:name":"SR3 1QH",
    "wof:placetype":"postalcode"
},
  "geometry": {"coordinates":[-1.41573251700609,54.88549951422327],"type":"Point"}
}