{
  "type": "Feature",
  "properties": {
    "iso:country":"GB",
    "wof:name":"LE4 7ZH",
    "wof:placetype":"postalcode"
},
  "geometry": {"coordinates":[-1.10163351133451,52.66179464935116],"type":"Point"}
}