{
  "type": "Feature",
  "properties": {
    "date:inception_lower": "1993-08-01",
    "date:inception_upper": "1993-08-01",
    "iso:country": "GB",
    "wof:name": "NN12 6AE",
    "wof:placetype": "postalcode"
  },
  "geometry": {"coordinates":[-1.001252,52.12793],"type":"Point"}
}
