{
  "type": "Feature",
  "properties": {
    "iso:country":"GB",
    "wof:name":"WA14 4AN",
    "wof:placetype":"postalcode"
},
  "geometry": {"coordinates":[-2.35494694098512,53.38761035878452],"type":"Point"}
}