{
  "type": "Feature",
  "properties": {
    "date:inception_lower": "2010-03-01",
    "date:inception_upper": "2010-03-01",
    "iso:country": "GB",
    "wof:name": "B11 2DF",
    "wof:placetype": "postalcode"
  },
  "geometry": {"coordinates":[-1.83183,52.454527],"type":"Point"}
}
