{
  "type": "Feature",
  "properties": {
    "iso:country":"GB",
    "wof:name":"B11 2DF",
    "wof:placetype":"postalcode"
},
  "geometry": {"coordinates":[-1.83259565682116,52.45448344074741],"type":"Point"}
}