{
  "type": "Feature",
  "properties": {
    "date:inception_lower": "1980-01-01",
    "date:inception_upper": "1980-01-01",
    "iso:country": "GB",
    "wof:name": "BA5 1NW",
    "wof:placetype": "postalcode"
  },
  "geometry": {"coordinates":[-2.705005,51.192756],"type":"Point"}
}
