{
  "type": "Feature",
  "properties": {
    "iso:country":"GB",
    "wof:name":"BA5 1NW",
    "wof:placetype":"postalcode"
},
  "geometry": {"coordinates":[-2.7048771978749,51.19219533468607],"type":"Point"}
}