{
  "type": "Feature",
  "properties": {
    "iso:country": "GB",
    "wof:name": "BA5 1NW",
    "wof:placetype": "postalcode"
  },
  "geometry": {"coordinates":[-2.704881,51.19219],"type":"Point"}
}
