{
  "type": "Feature",
  "properties": {
    "iso:country":"GB",
    "wof:name":"PE7 3EN",
    "wof:placetype":"postalcode"
},
  "geometry": {"coordinates":[-0.2399714293395,52.5272383302547],"type":"Point"}
}