{
  "type": "Feature",
  "properties": {
    "date:inception_lower":"2004-02-01",
    "date:inception_upper":"2004-02-29",
    "iso:country":"GB",
    "wof:name":"PE7 3EN",
    "wof:placetype":"postalcode"
},
  "geometry": {"coordinates":[-0.239971,52.527238],"type":"Point"}
}