{
  "type": "Feature",
  "properties": {
    "date:inception_lower": "2001-06-01",
    "date:inception_upper": "2001-06-01",
    "iso:country": "GB",
    "wof:name": "OX29 7XW",
    "wof:placetype": "postalcode"
  },
  "geometry": {"coordinates":[-1.488281,51.768969],"type":"Point"}
}
