{
  "type": "Feature",
  "properties": {
    "date:inception_lower": "1980-01-01",
    "date:inception_upper": "1980-01-01",
    "iso:country": "GB",
    "wof:name": "B20 2AN",
    "wof:placetype": "postalcode"
  },
  "geometry": {"coordinates":[-1.913736,52.51554],"type":"Point"}
}
