{
  "type": "Feature",
  "properties": {
    "date:inception_lower":"1995-12-01",
    "date:inception_upper":"1995-12-31",
    "iso:country":"GB",
    "wof:name":"LS27 8GU",
    "wof:placetype":"postalcode"
},
  "geometry": {"coordinates":[-1.587475,53.740481],"type":"Point"}
}