{
  "type": "Feature",
  "properties": {
    "iso:country": "GB",
    "wof:name": "GL19 3BW",
    "wof:placetype": "postalcode"
  },
  "geometry": {"coordinates":[-2.293043,51.922562],"type":"Point"}
}
