{
  "type": "Feature",
  "properties": {
    "iso:country":"GB",
    "wof:name":"DY1 3JJ",
    "wof:placetype":"postalcode"
},
  "geometry": {"coordinates":[-2.08677493942286,52.51259067177791],"type":"Point"}
}