{
  "type": "Feature",
  "properties": {
    "iso:country":"GB",
    "wof:name":"SG2 7EJ",
    "wof:placetype":"postalcode"
},
  "geometry": {"coordinates":[-0.15303438992385,51.88647139436258],"type":"Point"}
}