{
  "type": "Feature",
  "properties": {
    "iso:country":"GB",
    "wof:name":"W1D 7LX",
    "wof:placetype":"postalcode"
},
  "geometry": {"coordinates":[-0.13434119382301,51.51121730012855],"type":"Point"}
}