{
  "type": "Feature",
  "properties": {
    "date:inception_lower":"2013-09-01",
    "date:inception_upper":"2013-09-30",
    "iso:country":"GB",
    "wof:name":"TN8 7AY",
    "wof:placetype":"postalcode"
},
  "geometry": {"coordinates":[0.089377,51.137462],"type":"Point"}
}