{
  "type": "Feature",
  "properties": {
    "iso:country":"GB",
    "wof:name":"TW18 3NH",
    "wof:placetype":"postalcode"
},
  "geometry": {"coordinates":[-0.50534847905859,51.41666419941833],"type":"Point"}
}