{
  "type": "Feature",
  "properties": {
    "iso:country":"GB",
    "wof:name":"WN3 4PN",
    "wof:placetype":"postalcode"
},
  "geometry": {"coordinates":[-2.60721528865323,53.53125609334564],"type":"Point"}
}