{
  "type": "Feature",
  "properties": {
    "iso:country":"GB",
    "wof:name":"NR32 1PW",
    "wof:placetype":"postalcode"
},
  "geometry": {"coordinates":[1.75230379065838,52.47862622610764],"type":"Point"}
}