{
  "type": "Feature",
  "properties": {
    "iso:country": "GB",
    "wof:name": "L4 1XF",
    "wof:placetype": "postalcode"
  },
  "geometry": {"coordinates":[-2.978242,53.439609],"type":"Point"}
}
