{
  "type": "Feature",
  "properties": {
    "date:inception_lower": "1980-01-01",
    "date:inception_upper": "1980-01-01",
    "iso:country": "GB",
    "wof:name": "AL3 5SD",
    "wof:placetype": "postalcode"
  },
  "geometry": {"coordinates":[-0.337433,51.765617],"type":"Point"}
}
