{
  "type": "Feature",
  "properties": {
    "iso:country":"GB",
    "wof:name":"HG3 5PR",
    "wof:placetype":"postalcode"
},
  "geometry": {"coordinates":[-1.77507101236583,54.11343356767664],"type":"Point"}
}