{
  "type": "Feature",
  "properties": {
    "date:inception_lower": "1980-01-01",
    "date:inception_upper": "1980-01-01",
    "iso:country": "GB",
    "wof:name": "SN10 4JZ",
    "wof:placetype": "postalcode"
  },
  "geometry": {"coordinates":[-2.016936,51.286445],"type":"Point"}
}
