{
  "type": "Feature",
  "properties": {
    "iso:country": "GB",
    "wof:name": "SN10 4JZ",
    "wof:placetype": "postalcode"
  },
  "geometry": {"coordinates":[-2.016942,51.286449],"type":"Point"}
}
