{
  "type": "Feature",
  "properties": {
    "iso:country":"GB",
    "wof:name":"SN10 4JZ",
    "wof:placetype":"postalcode"
},
  "geometry": {"coordinates":[-2.01694243938592,51.2864494204376],"type":"Point"}
}