{
  "type": "Feature",
  "properties": {
    "iso:country":"GB",
    "wof:name":"TF6 6ED",
    "wof:placetype":"postalcode"
},
  "geometry": {"coordinates":[-2.49494529526143,52.75032017247362],"type":"Point"}
}