{
  "type": "Feature",
  "properties": {
    "iso:country": "GB",
    "wof:name": "TF6 6ED",
    "wof:placetype": "postalcode"
  },
  "geometry": {"coordinates":[-2.494945,52.75032],"type":"Point"}
}
