{
  "type": "Feature",
  "properties": {
    "iso:country":"GB",
    "wof:name":"TS26 0QZ",
    "wof:placetype":"postalcode"
},
  "geometry": {"coordinates":[-1.24600362470634,54.70515420769193],"type":"Point"}
}