{
  "type": "Feature",
  "properties": {
    "date:inception_lower": "2006-07-01",
    "date:inception_upper": "2006-07-01",
    "iso:country": "GB",
    "wof:name": "TS26 0QZ",
    "wof:placetype": "postalcode"
  },
  "geometry": {"coordinates":[-1.246004,54.705154],"type":"Point"}
}
