{
  "type": "Feature",
  "properties": {
    "date:inception_lower": "2018-03-01",
    "date:inception_upper": "2018-03-01",
    "iso:country": "GB",
    "wof:name": "RG28 7FN",
    "wof:placetype": "postalcode"
  },
  "geometry": {"coordinates":[-1.344112,51.230085],"type":"Point"}
}
