{
  "type": "Feature",
  "properties": {
    "iso:country": "GB",
    "wof:name": "RG28 7FN",
    "wof:placetype": "postalcode"
  },
  "geometry": {"coordinates":[-1.344112,51.230085],"type":"Point"}
}
