{
  "type": "Feature",
  "properties": {
    "date:inception_lower": "1980-01-01",
    "date:inception_upper": "1980-01-01",
    "iso:country": "GB",
    "wof:name": "CO7 6PA",
    "wof:placetype": "postalcode"
  },
  "geometry": {"coordinates":[0.990684,51.978676],"type":"Point"}
}
