{
  "type": "Feature",
  "properties": {
    "iso:country": "GB",
    "wof:name": "CO7 6PA",
    "wof:placetype": "postalcode"
  },
  "geometry": {"coordinates":[0.990667,51.978645],"type":"Point"}
}
