{
  "type": "Feature",
  "properties": {
    "iso:country": "GB",
    "wof:name": "CO7 6PA",
    "wof:placetype": "postalcode"
  },
  "geometry": {"coordinates":[0.990684,51.978676],"type":"Point"}
}
