{
  "type": "Feature",
  "properties": {
    "iso:country":"GB",
    "wof:name":"ST4 6HH",
    "wof:placetype":"postalcode"
},
  "geometry": {"coordinates":[-2.21157852298866,53.01609005034656],"type":"Point"}
}