{
  "type": "Feature",
  "properties": {
    "iso:country": "GB",
    "wof:name": "ST4 6HH",
    "wof:placetype": "postalcode"
  },
  "geometry": {"coordinates":[-2.211578,53.01609],"type":"Point"}
}
