{
  "type": "Feature",
  "properties": {
    "iso:country": "GB",
    "wof:name": "SA19 6NT",
    "wof:placetype": "postalcode"
  },
  "geometry": {"coordinates":[-3.977457,51.897443],"type":"Point"}
}
