{
  "type": "Feature",
  "properties": {
    "date:inception_lower": "1997-12-01",
    "date:inception_upper": "1997-12-01",
    "iso:country": "GB",
    "wof:name": "BS35 4BG",
    "wof:placetype": "postalcode"
  },
  "geometry": {"coordinates":[-2.629291,51.598101],"type":"Point"}
}
