{
  "type": "Feature",
  "properties": {
    "iso:country":"GB",
    "wof:name":"E13 9BP",
    "wof:placetype":"postalcode"
},
  "geometry": {"coordinates":[0.03460882570929,51.5319868791505],"type":"Point"}
}