{
  "type": "Feature",
  "properties": {
    "iso:country":"GB",
    "wof:name":"PL12 4UA",
    "wof:placetype":"postalcode"
},
  "geometry": {"coordinates":[-4.24043905823809,50.41236804931361],"type":"Point"}
}