{
  "type": "Feature",
  "properties": {
    "iso:country":"GB",
    "wof:name":"W1S 1RR",
    "wof:placetype":"postalcode"
},
  "geometry": {"coordinates":[-0.14586555418738,51.51381903294964],"type":"Point"}
}