{
  "type": "Feature",
  "properties": {
    "iso:country": "GB",
    "wof:name": "MK12 5AY",
    "wof:placetype": "postalcode"
  },
  "geometry": {"coordinates":[-0.816275,52.058616],"type":"Point"}
}
