{
  "type": "Feature",
  "properties": {
    "iso:country": "GB",
    "wof:name": "TA23 0TR",
    "wof:placetype": "postalcode"
  },
  "geometry": {"coordinates":[-3.308092,51.177572],"type":"Point"}
}
