{
  "type": "Feature",
  "properties": {
    "iso:country":"GB",
    "wof:name":"TA23 0TR",
    "wof:placetype":"postalcode"
},
  "geometry": {"coordinates":[-3.30809237155442,51.17757164013034],"type":"Point"}
}