{
  "type": "Feature",
  "properties": {
    "date:inception_lower": "2021-06-01",
    "date:inception_upper": "2021-06-01",
    "iso:country": "GB",
    "wof:name": "DE45 1JY",
    "wof:placetype": "postalcode"
  },
  "geometry": {"coordinates":[-1.686637,53.209139],"type":"Point"}
}
