{
  "type": "Feature",
  "properties": {
    "iso:country":"GB",
    "wof:name":"CF64 5QD",
    "wof:placetype":"postalcode"
},
  "geometry": {"coordinates":[-3.17687280984283,51.42024396572631],"type":"Point"}
}