{
  "type": "Feature",
  "properties": {
    "iso:country":"GB",
    "wof:name":"WA4 5RJ",
    "wof:placetype":"postalcode"
},
  "geometry": {"coordinates":[-2.57551700137463,53.34405389666879],"type":"Point"}
}