{
  "type": "Feature",
  "properties": {
    "date:inception_lower": "1996-06-01",
    "date:inception_upper": "1996-06-01",
    "iso:country": "GB",
    "wof:name": "WA4 5RJ",
    "wof:placetype": "postalcode"
  },
  "geometry": {"coordinates":[-2.575517,53.344054],"type":"Point"}
}
