{
  "type": "Feature",
  "properties": {
    "date:inception_lower": "2005-09-01",
    "date:inception_upper": "2005-09-01",
    "iso:country": "GB",
    "wof:name": "S5 6GY",
    "wof:placetype": "postalcode"
  },
  "geometry": {"coordinates":[-1.444199,53.42272],"type":"Point"}
}
