{
  "type": "Feature",
  "properties": {
    "iso:country": "GB",
    "wof:name": "TQ4 6BY",
    "wof:placetype": "postalcode"
  },
  "geometry": {"coordinates":[-3.561564,50.428646],"type":"Point"}
}
