{
  "type": "Feature",
  "properties": {
    "iso:country":"GB",
    "wof:name":"HP22 5XP",
    "wof:placetype":"postalcode"
},
  "geometry": {"coordinates":[-0.78790680761902,51.76695502419242],"type":"Point"}
}