{
  "type": "Feature",
  "properties": {
    "iso:country": "GB",
    "wof:name": "HP22 5XP",
    "wof:placetype": "postalcode"
  },
  "geometry": {"coordinates":[-0.787907,51.766955],"type":"Point"}
}
