{
  "type": "Feature",
  "properties": {
    "date:inception_lower": "2004-02-01",
    "date:inception_upper": "2004-02-01",
    "iso:country": "GB",
    "wof:name": "CF62 3LT",
    "wof:placetype": "postalcode"
  },
  "geometry": {"coordinates":[-3.343583,51.386745],"type":"Point"}
}
