{
  "type": "Feature",
  "properties": {
    "iso:country": "GB",
    "wof:name": "L36 8HR",
    "wof:placetype": "postalcode"
  },
  "geometry": {"coordinates":[-2.828708,53.426457],"type":"Point"}
}
