{
  "type": "Feature",
  "properties": {
    "date:inception_lower":"1992-01-01",
    "date:inception_upper":"1992-01-31",
    "iso:country":"GB",
    "wof:name":"LE3 8SE",
    "wof:placetype":"postalcode"
},
  "geometry": {"coordinates":[-1.200417,52.644352],"type":"Point"}
}