{
  "type": "Feature",
  "properties": {
    "iso:country":"GB",
    "wof:name":"LE3 8SE",
    "wof:placetype":"postalcode"
},
  "geometry": {"coordinates":[-1.20049909363055,52.64425307427078],"type":"Point"}
}