{
  "type": "Feature",
  "properties": {
    "iso:country":"GB",
    "wof:name":"CH3 6DF",
    "wof:placetype":"postalcode"
},
  "geometry": {"coordinates":[-2.86503744186241,53.17333838238179],"type":"Point"}
}