{
  "type": "Feature",
  "properties": {
    "iso:country": "GB",
    "wof:name": "CH3 6DF",
    "wof:placetype": "postalcode"
  },
  "geometry": {"coordinates":[-2.865037,53.173338],"type":"Point"}
}
