{
  "type": "Feature",
  "properties": {
    "date:inception_lower": "1980-01-01",
    "date:inception_upper": "1980-01-01",
    "iso:country": "GB",
    "wof:name": "CH3 6DF",
    "wof:placetype": "postalcode"
  },
  "geometry": {"coordinates":[-2.865037,53.173338],"type":"Point"}
}
