{
  "type": "Feature",
  "properties": {
    "iso:country":"GB",
    "wof:name":"BR2 0HB",
    "wof:placetype":"postalcode"
},
  "geometry": {"coordinates":[0.00254229147736,51.40472493528784],"type":"Point"}
}