{
  "type": "Feature",
  "properties": {
    "iso:country": "GB",
    "wof:name": "TN19 7RD",
    "wof:placetype": "postalcode"
  },
  "geometry": {"coordinates":[0.481266,51.025554],"type":"Point"}
}
