{
  "type": "Feature",
  "properties": {
    "iso:country": "GB",
    "wof:name": "CT14 6TW",
    "wof:placetype": "postalcode"
  },
  "geometry": {"coordinates":[1.399873,51.227637],"type":"Point"}
}
