{
  "type": "Feature",
  "properties": {
    "iso:country":"GB",
    "wof:name":"CT14 6TW",
    "wof:placetype":"postalcode"
},
  "geometry": {"coordinates":[1.39936854759437,51.22778609314076],"type":"Point"}
}