{
  "type": "Feature",
  "properties": {
    "iso:country":"GB",
    "wof:name":"ME2 1JL",
    "wof:placetype":"postalcode"
},
  "geometry": {"coordinates":[0.42979250579609,51.34811463860424],"type":"Point"}
}