{
  "type": "Feature",
  "properties": {
    "date:inception_lower": "1980-01-01",
    "date:inception_upper": "1980-01-01",
    "iso:country": "GB",
    "wof:name": "IP13 7RF",
    "wof:placetype": "postalcode"
  },
  "geometry": {"coordinates":[1.335092,52.176516],"type":"Point"}
}
