{
  "type": "Feature",
  "properties": {
    "iso:country": "GB",
    "wof:name": "IP13 7RF",
    "wof:placetype": "postalcode"
  },
  "geometry": {"coordinates":[1.335092,52.176516],"type":"Point"}
}
