{
  "type": "Feature",
  "properties": {
    "date:inception_lower": "1980-01-01",
    "date:inception_upper": "1980-01-01",
    "iso:country": "GB",
    "wof:name": "SG8 9NN",
    "wof:placetype": "postalcode"
  },
  "geometry": {"coordinates":[-0.076607,52.035584],"type":"Point"}
}
