{
  "type": "Feature",
  "properties": {
    "iso:country":"GB",
    "wof:name":"MK45 1BJ",
    "wof:placetype":"postalcode"
},
  "geometry": {"coordinates":[-0.49800393730694,52.01082362246778],"type":"Point"}
}