{
  "type": "Feature",
  "properties": {
    "date:inception_lower": "1980-01-01",
    "date:inception_upper": "1980-01-01",
    "iso:country": "GB",
    "wof:name": "MK45 1BJ",
    "wof:placetype": "postalcode"
  },
  "geometry": {"coordinates":[-0.498004,52.010824],"type":"Point"}
}
