{
  "type": "Feature",
  "properties": {
    "iso:country": "GB",
    "wof:name": "NE5 1LS",
    "wof:placetype": "postalcode"
  },
  "geometry": {"coordinates":[-1.70851,55.003834],"type":"Point"}
}
