{
  "type": "Feature",
  "properties": {
    "iso:country":"GB",
    "wof:name":"WR9 7EL",
    "wof:placetype":"postalcode"
},
  "geometry": {"coordinates":[-2.13425793187115,52.26832113646995],"type":"Point"}
}