{
  "type": "Feature",
  "properties": {
    "iso:country": "GB",
    "wof:name": "WR9 7EL",
    "wof:placetype": "postalcode"
  },
  "geometry": {"coordinates":[-2.134258,52.268321],"type":"Point"}
}
