{
  "type": "Feature",
  "properties": {
    "date:inception_lower": "2016-07-01",
    "date:inception_upper": "2016-07-01",
    "iso:country": "GB",
    "wof:name": "NE13 9DP",
    "wof:placetype": "postalcode"
  },
  "geometry": {"coordinates":[-1.634888,55.03486],"type":"Point"}
}
