{
  "type": "Feature",
  "properties": {
    "iso:country":"GB",
    "wof:name":"YO32 9LN",
    "wof:placetype":"postalcode"
},
  "geometry": {"coordinates":[-1.06949363066556,53.98761457891008],"type":"Point"}
}