{
  "type": "Feature",
  "properties": {
    "date:inception_lower": "2011-03-01",
    "date:inception_upper": "2011-03-01",
    "iso:country": "GB",
    "wof:name": "YO32 9LN",
    "wof:placetype": "postalcode"
  },
  "geometry": {"coordinates":[-1.069494,53.987615],"type":"Point"}
}
