{
  "type": "Feature",
  "properties": {
    "date:inception_lower": "1980-01-01",
    "date:inception_upper": "1980-01-01",
    "iso:country": "GB",
    "wof:name": "TS19 7EL",
    "wof:placetype": "postalcode"
  },
  "geometry": {"coordinates":[-1.350602,54.568997],"type":"Point"}
}
