{
  "type": "Feature",
  "properties": {
    "iso:country":"GB",
    "wof:name":"TS19 7EL",
    "wof:placetype":"postalcode"
},
  "geometry": {"coordinates":[-1.35060160358791,54.5689970554261],"type":"Point"}
}