{
  "type": "Feature",
  "properties": {
    "iso:country":"GB",
    "wof:name":"PL4 7NN",
    "wof:placetype":"postalcode"
},
  "geometry": {"coordinates":[-4.1192296299473,50.37884288350268],"type":"Point"}
}