{
  "type": "Feature",
  "properties": {
    "iso:country":"GB",
    "wof:name":"EX17 5AZ",
    "wof:placetype":"postalcode"
},
  "geometry": {"coordinates":[-3.87838276976643,50.75504056717233],"type":"Point"}
}