{
  "type": "Feature",
  "properties": {
    "date:inception_lower":"1980-01-01",
    "date:inception_upper":"1980-01-31",
    "iso:country":"GB",
    "wof:name":"EX17 5AZ",
    "wof:placetype":"postalcode"
},
  "geometry": {"coordinates":[-3.878383,50.755041],"type":"Point"}
}