{
  "type": "Feature",
  "properties": {
    "iso:country":"GB",
    "wof:name":"NW10 7FA",
    "wof:placetype":"postalcode"
},
  "geometry": {"coordinates":[-0.28449479077361,51.53301393597814],"type":"Point"}
}