{
  "type": "Feature",
  "properties": {
    "iso:country":"GB",
    "wof:name":"KA18 1PR",
    "wof:placetype":"postalcode"
},
  "geometry": {"coordinates":[-4.25579300077201,55.45696826697667],"type":"Point"}
}