{
  "type": "Feature",
  "properties": {
    "date:inception_lower": "1980-01-01",
    "date:inception_upper": "1980-01-01",
    "iso:country": "GB",
    "wof:name": "KA18 1PR",
    "wof:placetype": "postalcode"
  },
  "geometry": {"coordinates":[-4.255793,55.456968],"type":"Point"}
}
