{
  "type": "Feature",
  "properties": {
    "iso:country":"GB",
    "wof:name":"G66 1LJ",
    "wof:placetype":"postalcode"
},
  "geometry": {"coordinates":[-4.15594102303208,55.93950686942807],"type":"Point"}
}