{
  "type": "Feature",
  "properties": {
    "date:inception_lower":"1995-12-01",
    "date:inception_upper":"1995-12-31",
    "iso:country":"GB",
    "wof:name":"G66 1LJ",
    "wof:placetype":"postalcode"
},
  "geometry": {"coordinates":[-4.155941,55.939507],"type":"Point"}
}