{
  "type": "Feature",
  "properties": {
    "iso:country":"GB",
    "wof:name":"LL53 5LH",
    "wof:placetype":"postalcode"
},
  "geometry": {"coordinates":[-4.41105646909258,52.89172390897558],"type":"Point"}
}