{
  "type": "Feature",
  "properties": {
    "iso:country": "GB",
    "wof:name": "LL53 5LH",
    "wof:placetype": "postalcode"
  },
  "geometry": {"coordinates":[-4.411056,52.891724],"type":"Point"}
}
