{
  "type": "Feature",
  "properties": {
    "date:inception_lower": "1980-01-01",
    "date:inception_upper": "1980-01-01",
    "iso:country": "GB",
    "wof:name": "LL53 5LH",
    "wof:placetype": "postalcode"
  },
  "geometry": {"coordinates":[-4.411056,52.891724],"type":"Point"}
}
