{
  "type": "Feature",
  "properties": {
    "iso:country":"GB",
    "wof:name":"CF10 1FF",
    "wof:placetype":"postalcode"
},
  "geometry": {"coordinates":[-3.1764112776379,51.47785112121757],"type":"Point"}
}