{
  "type": "Feature",
  "properties": {
    "iso:country": "GB",
    "wof:name": "DE7 5AR",
    "wof:placetype": "postalcode"
  },
  "geometry": {"coordinates":[-1.301094,52.961369],"type":"Point"}
}
