{
  "type": "Feature",
  "properties": {
    "iso:country":"GB",
    "wof:name":"LU2 0DE",
    "wof:placetype":"postalcode"
},
  "geometry": {"coordinates":[-0.41254233621888,51.88399139708284],"type":"Point"}
}