{
  "type": "Feature",
  "properties": {
    "iso:country": "GB",
    "wof:name": "NE21 4NL",
    "wof:placetype": "postalcode"
  },
  "geometry": {"coordinates":[-1.741299,54.971459],"type":"Point"}
}
