{
  "type": "Feature",
  "properties": {
    "date:inception_lower": "1980-01-01",
    "date:inception_upper": "1980-01-01",
    "iso:country": "GB",
    "wof:name": "GL14 3HJ",
    "wof:placetype": "postalcode"
  },
  "geometry": {"coordinates":[-2.507398,51.80949],"type":"Point"}
}
