{
  "type": "Feature",
  "properties": {
    "date:inception_lower":"1980-01-01",
    "date:inception_upper":"1980-01-31",
    "iso:country":"GB",
    "wof:name":"ST19 9JR",
    "wof:placetype":"postalcode"
},
  "geometry": {"coordinates":[-2.18931,52.713113],"type":"Point"}
}