{
  "type": "Feature",
  "properties": {
    "iso:country": "GB",
    "wof:name": "ST19 9JR",
    "wof:placetype": "postalcode"
  },
  "geometry": {"coordinates":[-2.18931,52.713113],"type":"Point"}
}
