{
  "type": "Feature",
  "properties": {
    "iso:country":"GB",
    "wof:name":"ST19 9JR",
    "wof:placetype":"postalcode"
},
  "geometry": {"coordinates":[-2.18931050097035,52.71311347485253],"type":"Point"}
}