{
  "type": "Feature",
  "properties": {
    "date:inception_lower": "1980-01-01",
    "date:inception_upper": "1980-01-01",
    "iso:country": "GB",
    "wof:name": "ST19 9JR",
    "wof:placetype": "postalcode"
  },
  "geometry": {"coordinates":[-2.188713,52.712779],"type":"Point"}
}
