{
  "type": "Feature",
  "properties": {
    "iso:country":"GB",
    "wof:name":"UB5 5BD",
    "wof:placetype":"postalcode"
},
  "geometry": {"coordinates":[-0.38166418229649,51.54054524603158],"type":"Point"}
}