{
  "type": "Feature",
  "properties": {
    "iso:country":"GB",
    "wof:name":"NP11 7EU",
    "wof:placetype":"postalcode"
},
  "geometry": {"coordinates":[-3.12363473376645,51.63639012795088],"type":"Point"}
}