{
  "type": "Feature",
  "properties": {
    "iso:country": "GB",
    "wof:name": "NP11 7EU",
    "wof:placetype": "postalcode"
  },
  "geometry": {"coordinates":[-3.123635,51.63639],"type":"Point"}
}
