{
  "type": "Feature",
  "properties": {
    "date:inception_lower": "1980-01-01",
    "date:inception_upper": "1980-01-01",
    "iso:country": "GB",
    "wof:name": "G34 0HN",
    "wof:placetype": "postalcode"
  },
  "geometry": {"coordinates":[-4.101961,55.871177],"type":"Point"}
}
