{
  "type": "Feature",
  "properties": {
    "iso:country": "GB",
    "wof:name": "G34 0HN",
    "wof:placetype": "postalcode"
  },
  "geometry": {"coordinates":[-4.101961,55.871177],"type":"Point"}
}
