{
  "type": "Feature",
  "properties": {
    "iso:country": "GB",
    "wof:name": "RG7 5EE",
    "wof:placetype": "postalcode"
  },
  "geometry": {"coordinates":[-1.097048,51.452792],"type":"Point"}
}
