{
  "type": "Feature",
  "properties": {
    "iso:country":"GB",
    "wof:name":"S63 9DN",
    "wof:placetype":"postalcode"
},
  "geometry": {"coordinates":[-1.30660792545712,53.53226441786686],"type":"Point"}
}