{
  "type": "Feature",
  "properties": {
    "date:inception_lower": "1980-01-01",
    "date:inception_upper": "1980-01-01",
    "iso:country": "GB",
    "wof:name": "S63 9DN",
    "wof:placetype": "postalcode"
  },
  "geometry": {"coordinates":[-1.306608,53.532264],"type":"Point"}
}
