{
  "type": "Feature",
  "properties": {
    "iso:country":"GB",
    "wof:name":"BH2 6LA",
    "wof:placetype":"postalcode"
},
  "geometry": {"coordinates":[-1.88271898648131,50.72313669015843],"type":"Point"}
}