{
  "type": "Feature",
  "properties": {
    "date:inception_lower":"1987-04-01",
    "date:inception_upper":"1987-04-30",
    "iso:country":"GB",
    "wof:name":"BH2 6LA",
    "wof:placetype":"postalcode"
},
  "geometry": {"coordinates":[-1.882719,50.723137],"type":"Point"}
}