{
  "type": "Feature",
  "properties": {
    "iso:country":"GB",
    "wof:name":"SY8 3BN",
    "wof:placetype":"postalcode"
},
  "geometry": {"coordinates":[-2.65704055715044,52.35461993406626],"type":"Point"}
}