{
  "type": "Feature",
  "properties": {
    "iso:country": "GB",
    "wof:name": "SY8 3BN",
    "wof:placetype": "postalcode"
  },
  "geometry": {"coordinates":[-2.657041,52.35462],"type":"Point"}
}
