{
  "type": "Feature",
  "properties": {
    "iso:country":"GB",
    "wof:name":"LE17 6AW",
    "wof:placetype":"postalcode"
},
  "geometry": {"coordinates":[-1.19946471406408,52.40743748441108],"type":"Point"}
}