{
  "type": "Feature",
  "properties": {
    "iso:country":"GB",
    "wof:name":"SK3 0BD",
    "wof:placetype":"postalcode"
},
  "geometry": {"coordinates":[-2.17078192977505,53.40735962424809],"type":"Point"}
}