{
  "type": "Feature",
  "properties": {
    "date:inception_lower":"1988-03-01",
    "date:inception_upper":"1988-03-31",
    "iso:country":"GB",
    "wof:name":"MK42 8TT",
    "wof:placetype":"postalcode"
},
  "geometry": {"coordinates":[-0.491869,52.125178],"type":"Point"}
}