{
  "type": "Feature",
  "properties": {
    "iso:country":"GB",
    "wof:name":"NR25 6PE",
    "wof:placetype":"postalcode"
},
  "geometry": {"coordinates":[1.17862247803798,52.91437288231114],"type":"Point"}
}