{
  "type": "Feature",
  "properties": {
    "iso:country":"GB",
    "wof:name":"HA3 8RT",
    "wof:placetype":"postalcode"
},
  "geometry": {"coordinates":[-0.3146929323527,51.59916693676551],"type":"Point"}
}