{
  "type": "Feature",
  "properties": {
    "iso:country": "GB",
    "wof:name": "TR13 0SL",
    "wof:placetype": "postalcode"
  },
  "geometry": {"coordinates":[-5.272758,50.112588],"type":"Point"}
}
