{
  "type": "Feature",
  "properties": {
    "iso:country":"GB",
    "wof:name":"TR13 0SL",
    "wof:placetype":"postalcode"
},
  "geometry": {"coordinates":[-5.27275791687392,50.11258826220936],"type":"Point"}
}