{
  "type": "Feature",
  "properties": {
    "iso:country":"GB",
    "wof:name":"BR4 9PW",
    "wof:placetype":"postalcode"
},
  "geometry": {"coordinates":[-0.02466243234261,51.37666150438142],"type":"Point"}
}