{
  "type": "Feature",
  "properties": {
    "iso:country":"GB",
    "wof:name":"CV23 8DT",
    "wof:placetype":"postalcode"
},
  "geometry": {"coordinates":[-1.2855575314408,52.29671557171797],"type":"Point"}
}