{
  "type": "Feature",
  "properties": {
    "date:inception_lower": "1997-06-01",
    "date:inception_upper": "1997-06-01",
    "iso:country": "GB",
    "wof:name": "CV23 8DT",
    "wof:placetype": "postalcode"
  },
  "geometry": {"coordinates":[-1.285746,52.296958],"type":"Point"}
}
