{
  "type": "Feature",
  "properties": {
    "iso:country": "GB",
    "wof:name": "CF82 7NE",
    "wof:placetype": "postalcode"
  },
  "geometry": {"coordinates":[-3.226371,51.649101],"type":"Point"}
}
