{
  "type": "Feature",
  "properties": {
    "iso:country":"GB",
    "wof:name":"PE25 2TD",
    "wof:placetype":"postalcode"
},
  "geometry": {"coordinates":[0.34398427470207,53.14550584528306],"type":"Point"}
}