{
  "type": "Feature",
  "properties": {
    "iso:country": "GB",
    "wof:name": "DL10 4PD",
    "wof:placetype": "postalcode"
  },
  "geometry": {"coordinates":[-1.729175,54.412104],"type":"Point"}
}
