{
  "type": "Feature",
  "properties": {
    "iso:country":"GB",
    "wof:name":"CF10 4QQ",
    "wof:placetype":"postalcode"
},
  "geometry": {"coordinates":[-3.15860585738032,51.46677055840757],"type":"Point"}
}