{
  "type": "Feature",
  "properties": {
    "iso:country":"GB",
    "wof:name":"BH1 3SZ",
    "wof:placetype":"postalcode"
},
  "geometry": {"coordinates":[-1.85188256843937,50.72625809442873],"type":"Point"}
}