{
  "type": "Feature",
  "properties": {
    "iso:country":"GB",
    "wof:name":"DA10 0AD",
    "wof:placetype":"postalcode"
},
  "geometry": {"coordinates":[0.30875853836572,51.44778026256036],"type":"Point"}
}