{
  "type": "Feature",
  "properties": {
    "date:inception_lower": "1980-01-01",
    "date:inception_upper": "1980-01-01",
    "iso:country": "GB",
    "wof:name": "DA10 0AD",
    "wof:placetype": "postalcode"
  },
  "geometry": {"coordinates":[0.308759,51.44778],"type":"Point"}
}
