{
  "type": "Feature",
  "properties": {
    "iso:country": "GB",
    "wof:name": "CV8 2AE",
    "wof:placetype": "postalcode"
  },
  "geometry": {"coordinates":[-1.567653,52.335826],"type":"Point"}
}
