{
  "type": "Feature",
  "properties": {
    "iso:country":"GB",
    "wof:name":"CV8 2AE",
    "wof:placetype":"postalcode"
},
  "geometry": {"coordinates":[-1.56765312475448,52.33582558998469],"type":"Point"}
}