{
  "type": "Feature",
  "properties": {
    "iso:country": "GB",
    "wof:name": "M23 9PN",
    "wof:placetype": "postalcode"
  },
  "geometry": {"coordinates":[-2.301264,53.395263],"type":"Point"}
}
