{
  "type": "Feature",
  "properties": {
    "iso:country":"GB",
    "wof:name":"M23 9PN",
    "wof:placetype":"postalcode"
},
  "geometry": {"coordinates":[-2.30126430280029,53.39526348273996],"type":"Point"}
}