{
  "type": "Feature",
  "properties": {
    "iso:country":"GB",
    "wof:name":"DG7 3RP",
    "wof:placetype":"postalcode"
},
  "geometry": {"coordinates":[-4.13888171982806,55.07612748903554],"type":"Point"}
}