{
  "type": "Feature",
  "properties": {
    "iso:country": "GB",
    "wof:name": "DG7 3RP",
    "wof:placetype": "postalcode"
  },
  "geometry": {"coordinates":[-4.139207,55.07605],"type":"Point"}
}
