{
  "type": "Feature",
  "properties": {
    "iso:country":"GB",
    "wof:name":"LU4 0RJ",
    "wof:placetype":"postalcode"
},
  "geometry": {"coordinates":[-0.49227050753214,51.90257357412698],"type":"Point"}
}