{
  "type": "Feature",
  "properties": {
    "iso:country": "GB",
    "wof:name": "LU4 0RJ",
    "wof:placetype": "postalcode"
  },
  "geometry": {"coordinates":[-0.49227,51.902574],"type":"Point"}
}
