{
  "type": "Feature",
  "properties": {
    "date:inception_lower": "1980-01-01",
    "date:inception_upper": "1980-01-01",
    "iso:country": "GB",
    "wof:name": "LU4 0RJ",
    "wof:placetype": "postalcode"
  },
  "geometry": {"coordinates":[-0.49227,51.902574],"type":"Point"}
}
