{
  "type": "Feature",
  "properties": {
    "iso:country":"GB",
    "wof:name":"DL9 3HL",
    "wof:placetype":"postalcode"
},
  "geometry": {"coordinates":[-1.74038372885907,54.37671002265684],"type":"Point"}
}