{
  "type": "Feature",
  "properties": {
    "iso:country":"GB",
    "wof:name":"DN33 1DL",
    "wof:placetype":"postalcode"
},
  "geometry": {"coordinates":[-0.10042211981221,53.55131601202787],"type":"Point"}
}