{
  "type": "Feature",
  "properties": {
    "iso:country":"GB",
    "wof:name":"GL5 2JL",
    "wof:placetype":"postalcode"
},
  "geometry": {"coordinates":[-2.20526639348262,51.73943974462829],"type":"Point"}
}