{
  "type": "Feature",
  "properties": {
    "iso:country":"GB",
    "wof:name":"S21 4DF",
    "wof:placetype":"postalcode"
},
  "geometry": {"coordinates":[-1.3608844095342,53.30780457326141],"type":"Point"}
}