{
  "type": "Feature",
  "properties": {
    "iso:country":"GB",
    "wof:name":"LL18 1DS",
    "wof:placetype":"postalcode"
},
  "geometry": {"coordinates":[-3.49842975975707,53.31418672450376],"type":"Point"}
}