{
  "type": "Feature",
  "properties": {
    "date:inception_lower": "2008-05-01",
    "date:inception_upper": "2008-05-01",
    "iso:country": "GB",
    "wof:name": "EH19 2PP",
    "wof:placetype": "postalcode"
  },
  "geometry": {"coordinates":[-3.122653,55.867923],"type":"Point"}
}
