{
  "type": "Feature",
  "properties": {
    "iso:country":"GB",
    "wof:name":"EH19 2PP",
    "wof:placetype":"postalcode"
},
  "geometry": {"coordinates":[-3.12265280443657,55.86792311874607],"type":"Point"}
}