{
  "type": "Feature",
  "properties": {
    "iso:country": "GB",
    "wof:name": "CM16 5DF",
    "wof:placetype": "postalcode"
  },
  "geometry": {"coordinates":[0.105804,51.699811],"type":"Point"}
}
