{
  "type": "Feature",
  "properties": {
    "iso:country":"GB",
    "wof:name":"CM16 5DF",
    "wof:placetype":"postalcode"
},
  "geometry": {"coordinates":[0.10580417980495,51.69981050864359],"type":"Point"}
}