{
  "type": "Feature",
  "properties": {
    "iso:country": "GB",
    "wof:name": "EN6 3BZ",
    "wof:placetype": "postalcode"
  },
  "geometry": {"coordinates":[-0.208644,51.699496],"type":"Point"}
}
