{
  "type": "Feature",
  "properties": {
    "iso:country":"GB",
    "wof:name":"PE20 1BT",
    "wof:placetype":"postalcode"
},
  "geometry": {"coordinates":[-0.06257608236942,52.93923714815964],"type":"Point"}
}