{
  "type": "Feature",
  "properties": {
    "date:inception_lower": "2004-10-01",
    "date:inception_upper": "2004-10-01",
    "iso:country": "GB",
    "wof:name": "SY6 6WZ",
    "wof:placetype": "postalcode"
  },
  "geometry": {"coordinates":[-2.840288,52.447021],"type":"Point"}
}
