{
  "type": "Feature",
  "properties": {
    "iso:country":"GB",
    "wof:name":"TA3 5DY",
    "wof:placetype":"postalcode"
},
  "geometry": {"coordinates":[-3.03966076412998,51.02960738652845],"type":"Point"}
}