{
  "type": "Feature",
  "properties": {
    "iso:country": "GB",
    "wof:name": "GU51 2TE",
    "wof:placetype": "postalcode"
  },
  "geometry": {"coordinates":[-0.827034,51.295703],"type":"Point"}
}
