{
  "type": "Feature",
  "properties": {
    "date:inception_lower": "1980-01-01",
    "date:inception_upper": "1980-01-01",
    "iso:country": "GB",
    "wof:name": "UB4 0NS",
    "wof:placetype": "postalcode"
  },
  "geometry": {"coordinates":[-0.396859,51.521385],"type":"Point"}
}
