{
  "type": "Feature",
  "properties": {
    "iso:country":"GB",
    "wof:name":"MK11 1LA",
    "wof:placetype":"postalcode"
},
  "geometry": {"coordinates":[-0.85360520133973,52.05331124618029],"type":"Point"}
}