{
  "type": "Feature",
  "properties": {
    "date:inception_lower": "1980-01-01",
    "date:inception_upper": "1980-01-01",
    "iso:country": "GB",
    "wof:name": "MK11 1LA",
    "wof:placetype": "postalcode"
  },
  "geometry": {"coordinates":[-0.853605,52.053311],"type":"Point"}
}
