{
  "type": "Feature",
  "properties": {
    "iso:country":"GB",
    "wof:name":"NR15 2BG",
    "wof:placetype":"postalcode"
},
  "geometry": {"coordinates":[1.17774297614402,52.43069965733137],"type":"Point"}
}