{
  "type": "Feature",
  "properties": {
    "date:inception_lower": "2000-10-01",
    "date:inception_upper": "2000-10-01",
    "iso:country": "GB",
    "wof:name": "W1U 5JH",
    "wof:placetype": "postalcode"
  },
  "geometry": {"coordinates":[-0.152019,51.521659],"type":"Point"}
}
