{
  "type": "Feature",
  "properties": {
    "date:inception_lower": "2013-12-01",
    "date:inception_upper": "2013-12-01",
    "iso:country": "GB",
    "wof:name": "G66 3RJ",
    "wof:placetype": "postalcode"
  },
  "geometry": {"coordinates":[-4.12473,55.930024],"type":"Point"}
}
