{
  "type": "Feature",
  "properties": {
    "iso:country":"GB",
    "wof:name":"DG9 9AS",
    "wof:placetype":"postalcode"
},
  "geometry": {"coordinates":[-5.0152141717212,54.86885873399214],"type":"Point"}
}