{
  "type": "Feature",
  "properties": {
    "iso:country": "GB",
    "wof:name": "TA3 7QF",
    "wof:placetype": "postalcode"
  },
  "geometry": {"coordinates":[-3.149393,50.929786],"type":"Point"}
}
