{
  "type": "Feature",
  "properties": {
    "iso:country":"GB",
    "wof:name":"TA3 7QF",
    "wof:placetype":"postalcode"
},
  "geometry": {"coordinates":[-3.14939349156388,50.92978612408713],"type":"Point"}
}