{
  "type": "Feature",
  "properties": {
    "iso:country":"GB",
    "wof:name":"EX16 5EB",
    "wof:placetype":"postalcode"
},
  "geometry": {"coordinates":[-3.49267767174087,50.89592761043745],"type":"Point"}
}