{
  "type": "Feature",
  "properties": {
    "iso:country":"GB",
    "wof:name":"BH17 7EG",
    "wof:placetype":"postalcode"
},
  "geometry": {"coordinates":[-2.00062816815629,50.74069510311774],"type":"Point"}
}