{
  "type": "Feature",
  "properties": {
    "iso:country":"GB",
    "wof:name":"TN15 7BB",
    "wof:placetype":"postalcode"
},
  "geometry": {"coordinates":[0.30707417324467,51.30918239081938],"type":"Point"}
}