{
  "type": "Feature",
  "properties": {
    "iso:country": "GB",
    "wof:name": "PO2 9HE",
    "wof:placetype": "postalcode"
  },
  "geometry": {"coordinates":[-1.0756,50.822258],"type":"Point"}
}
