{
  "type": "Feature",
  "properties": {
    "iso:country":"GB",
    "wof:name":"PO2 9HE",
    "wof:placetype":"postalcode"
},
  "geometry": {"coordinates":[-1.07559975922518,50.82225813763208],"type":"Point"}
}