{
  "type": "Feature",
  "properties": {
    "iso:country": "GB",
    "wof:name": "DD2 2SQ",
    "wof:placetype": "postalcode"
  },
  "geometry": {"coordinates":[-3.023356,56.478814],"type":"Point"}
}
