{
  "type": "Feature",
  "properties": {
    "iso:country":"GB",
    "wof:name":"DD2 2SQ",
    "wof:placetype":"postalcode"
},
  "geometry": {"coordinates":[-3.02335565011481,56.47881431346772],"type":"Point"}
}