{
  "type": "Feature",
  "properties": {
    "iso:country":"GB",
    "wof:name":"NR12 9AY",
    "wof:placetype":"postalcode"
},
  "geometry": {"coordinates":[1.51626327164189,52.77517465404167],"type":"Point"}
}