{
  "type": "Feature",
  "properties": {
    "iso:country": "GB",
    "wof:name": "NR12 9AY",
    "wof:placetype": "postalcode"
  },
  "geometry": {"coordinates":[1.516263,52.775175],"type":"Point"}
}
