{
  "type": "Feature",
  "properties": {
    "iso:country":"GB",
    "wof:name":"TW5 0PZ",
    "wof:placetype":"postalcode"
},
  "geometry": {"coordinates":[-0.36892025949396,51.4811277324269],"type":"Point"}
}