{
  "type": "Feature",
  "properties": {
    "date:inception_lower": "1980-01-01",
    "date:inception_upper": "1980-01-01",
    "iso:country": "GB",
    "wof:name": "TW5 0PZ",
    "wof:placetype": "postalcode"
  },
  "geometry": {"coordinates":[-0.36892,51.481128],"type":"Point"}
}
