{
  "type": "Feature",
  "properties": {
    "date:inception_lower": "1980-01-01",
    "date:inception_upper": "1980-01-01",
    "iso:country": "GB",
    "wof:name": "ST4 5EH",
    "wof:placetype": "postalcode"
  },
  "geometry": {"coordinates":[-2.195047,52.999614],"type":"Point"}
}
