{
  "type": "Feature",
  "properties": {
    "iso:country":"GB",
    "wof:name":"ST4 5EH",
    "wof:placetype":"postalcode"
},
  "geometry": {"coordinates":[-2.19497338295433,52.99959637814732],"type":"Point"}
}