{
  "type": "Feature",
  "properties": {
    "iso:country": "GB",
    "wof:name": "SO15 3GG",
    "wof:placetype": "postalcode"
  },
  "geometry": {"coordinates":[-1.430032,50.916035],"type":"Point"}
}
