{
  "type": "Feature",
  "properties": {
    "iso:country": "GB",
    "wof:name": "IP6 0SN",
    "wof:placetype": "postalcode"
  },
  "geometry": {"coordinates":[1.102797,52.121118],"type":"Point"}
}
