{
  "type": "Feature",
  "properties": {
    "iso:country": "GB",
    "wof:name": "GU24 9RT",
    "wof:placetype": "postalcode"
  },
  "geometry": {"coordinates":[-0.629909,51.329289],"type":"Point"}
}
