{
  "type": "Feature",
  "properties": {
    "iso:country":"GB",
    "wof:name":"GU24 9RT",
    "wof:placetype":"postalcode"
},
  "geometry": {"coordinates":[-0.62990923110744,51.32928916580438],"type":"Point"}
}