{
  "type": "Feature",
  "properties": {
    "iso:country": "GB",
    "wof:name": "HP22 5RD",
    "wof:placetype": "postalcode"
  },
  "geometry": {"coordinates":[-0.760128,51.792813],"type":"Point"}
}
