{
  "type": "Feature",
  "properties": {
    "iso:country":"GB",
    "wof:name":"HP22 5RD",
    "wof:placetype":"postalcode"
},
  "geometry": {"coordinates":[-0.76012775048875,51.79281270237335],"type":"Point"}
}