{
  "type": "Feature",
  "properties": {
    "iso:country":"GB",
    "wof:name":"L5 9RJ",
    "wof:placetype":"postalcode"
},
  "geometry": {"coordinates":[-2.99209495756678,53.42681990173772],"type":"Point"}
}