{
  "type": "Feature",
  "properties": {
    "date:inception_lower":"2001-12-01",
    "date:inception_upper":"2001-12-31",
    "iso:country":"GB",
    "wof:name":"EN3 6XU",
    "wof:placetype":"postalcode"
},
  "geometry": {"coordinates":[-0.014649,51.664967],"type":"Point"}
}