{
  "type": "Feature",
  "properties": {
    "iso:country": "GB",
    "wof:name": "EN3 6XU",
    "wof:placetype": "postalcode"
  },
  "geometry": {"coordinates":[-0.014649,51.664967],"type":"Point"}
}
