{
  "type": "Feature",
  "properties": {
    "iso:country":"GB",
    "wof:name":"EN3 6XU",
    "wof:placetype":"postalcode"
},
  "geometry": {"coordinates":[-0.01464865117426,51.66496730628681],"type":"Point"}
}