{
  "type": "Feature",
  "properties": {
    "iso:country":"GB",
    "wof:name":"WA14 3DP",
    "wof:placetype":"postalcode"
},
  "geometry": {"coordinates":[-2.36573845986446,53.37137124689043],"type":"Point"}
}