{
  "type": "Feature",
  "properties": {
    "date:inception_lower": "2016-08-01",
    "date:inception_upper": "2016-08-01",
    "iso:country": "GB",
    "wof:name": "FK8 1XY",
    "wof:placetype": "postalcode"
  },
  "geometry": {"coordinates":[-3.960386,56.135315],"type":"Point"}
}
