{
  "type": "Feature",
  "properties": {
    "iso:country": "GB",
    "wof:name": "FK8 1XY",
    "wof:placetype": "postalcode"
  },
  "geometry": {"coordinates":[-3.960386,56.135315],"type":"Point"}
}
