{
  "type": "Feature",
  "properties": {
    "iso:country": "GB",
    "wof:name": "FK2 0EF",
    "wof:placetype": "postalcode"
  },
  "geometry": {"coordinates":[-3.746657,55.979609],"type":"Point"}
}
