{
  "type": "Feature",
  "properties": {
    "date:inception_lower": "1980-07-01",
    "date:inception_upper": "1980-07-01",
    "iso:country": "GB",
    "wof:name": "FK2 0EF",
    "wof:placetype": "postalcode"
  },
  "geometry": {"coordinates":[-3.746657,55.979609],"type":"Point"}
}
