{
  "type": "Feature",
  "properties": {
    "iso:country":"GB",
    "wof:name":"PL8 2DD",
    "wof:placetype":"postalcode"
},
  "geometry": {"coordinates":[-4.03465199845473,50.35284037266728],"type":"Point"}
}