{
  "type": "Feature",
  "properties": {
    "iso:country": "GB",
    "wof:name": "PL8 2DD",
    "wof:placetype": "postalcode"
  },
  "geometry": {"coordinates":[-4.034652,50.35284],"type":"Point"}
}
