{
  "type": "Feature",
  "properties": {
    "date:inception_lower":"1980-01-01",
    "date:inception_upper":"1980-01-31",
    "iso:country":"GB",
    "wof:name":"PL8 2DD",
    "wof:placetype":"postalcode"
},
  "geometry": {"coordinates":[-4.034652,50.35284],"type":"Point"}
}