{
  "type": "Feature",
  "properties": {
    "iso:country":"GB",
    "wof:name":"IP29 5HL",
    "wof:placetype":"postalcode"
},
  "geometry": {"coordinates":[0.59009549560348,52.20909443796721],"type":"Point"}
}