{
  "type": "Feature",
  "properties": {
    "iso:country": "GB",
    "wof:name": "IP29 5HL",
    "wof:placetype": "postalcode"
  },
  "geometry": {"coordinates":[0.590125,52.20911],"type":"Point"}
}
