{
  "type": "Feature",
  "properties": {
    "iso:country":"GB",
    "wof:name":"EH18 1AE",
    "wof:placetype":"postalcode"
},
  "geometry": {"coordinates":[-3.11334950039603,55.88178239571199],"type":"Point"}
}