{
  "type": "Feature",
  "properties": {
    "date:inception_lower":"2005-10-01",
    "date:inception_upper":"2005-10-31",
    "iso:country":"GB",
    "wof:name":"NN14 1TQ",
    "wof:placetype":"postalcode"
},
  "geometry": {"coordinates":[-0.811106,52.377388],"type":"Point"}
}