{
  "type": "Feature",
  "properties": {
    "iso:country": "GB",
    "wof:name": "NN14 1TQ",
    "wof:placetype": "postalcode"
  },
  "geometry": {"coordinates":[-0.811106,52.377388],"type":"Point"}
}
