{
  "type": "Feature",
  "properties": {
    "iso:country":"GB",
    "wof:name":"NN14 1TQ",
    "wof:placetype":"postalcode"
},
  "geometry": {"coordinates":[-0.81110605317242,52.37738776118112],"type":"Point"}
}