{
  "type": "Feature",
  "properties": {
    "date:inception_lower": "2019-03-01",
    "date:inception_upper": "2019-03-01",
    "iso:country": "GB",
    "wof:name": "AB16 7UF",
    "wof:placetype": "postalcode"
  },
  "geometry": {"coordinates":[-2.153386,57.171148],"type":"Point"}
}
