{
  "type": "Feature",
  "properties": {
    "iso:country": "GB",
    "wof:name": "BN6 9DQ",
    "wof:placetype": "postalcode"
  },
  "geometry": {"coordinates":[-0.148868,50.930389],"type":"Point"}
}
