{
  "type": "Feature",
  "properties": {
    "iso:country":"GB",
    "wof:name":"BN6 9DQ",
    "wof:placetype":"postalcode"
},
  "geometry": {"coordinates":[-0.14886849236553,50.93038910551046],"type":"Point"}
}