{
  "type": "Feature",
  "properties": {
    "date:inception_lower": "1994-12-01",
    "date:inception_upper": "1994-12-01",
    "iso:country": "GB",
    "wof:name": "BN6 9DQ",
    "wof:placetype": "postalcode"
  },
  "geometry": {"coordinates":[-0.148868,50.930389],"type":"Point"}
}
