{
  "type": "Feature",
  "properties": {
    "iso:country": "GB",
    "wof:name": "LS11 6AE",
    "wof:placetype": "postalcode"
  },
  "geometry": {"coordinates":[-1.551592,53.781437],"type":"Point"}
}
