{
  "type": "Feature",
  "properties": {
    "iso:country": "GB",
    "wof:name": "CV4 9BQ",
    "wof:placetype": "postalcode"
  },
  "geometry": {"coordinates":[-1.570722,52.400827],"type":"Point"}
}
