{
  "type": "Feature",
  "properties": {
    "date:inception_lower":"1980-01-01",
    "date:inception_upper":"1980-01-31",
    "iso:country":"GB",
    "wof:name":"S62 7QP",
    "wof:placetype":"postalcode"
},
  "geometry": {"coordinates":[-1.348099,53.473164],"type":"Point"}
}