{
  "type": "Feature",
  "properties": {
    "iso:country": "GB",
    "wof:name": "S62 7QP",
    "wof:placetype": "postalcode"
  },
  "geometry": {"coordinates":[-1.348099,53.473164],"type":"Point"}
}
