{
  "type": "Feature",
  "properties": {
    "iso:country":"GB",
    "wof:name":"S62 7QP",
    "wof:placetype":"postalcode"
},
  "geometry": {"coordinates":[-1.34809859660798,53.47316416199574],"type":"Point"}
}