{
  "type": "Feature",
  "properties": {
    "iso:country":"GB",
    "wof:name":"SA73 1NW",
    "wof:placetype":"postalcode"
},
  "geometry": {"coordinates":[-4.92173408801765,51.72730804845938],"type":"Point"}
}