{
  "type": "Feature",
  "properties": {
    "iso:country": "GB",
    "wof:name": "SA73 1NW",
    "wof:placetype": "postalcode"
  },
  "geometry": {"coordinates":[-4.921734,51.727308],"type":"Point"}
}
