{
  "type": "Feature",
  "properties": {
    "date:inception_lower":"2018-09-01",
    "date:inception_upper":"2018-09-30",
    "iso:country":"GB",
    "wof:name":"AB10 1PR",
    "wof:placetype":"postalcode"
},
  "geometry": {"coordinates":[-2.104299,57.145317],"type":"Point"}
}