{
  "type": "Feature",
  "properties": {
    "iso:country": "GB",
    "wof:name": "AB10 1PR",
    "wof:placetype": "postalcode"
  },
  "geometry": {"coordinates":[-2.104332,57.145371],"type":"Point"}
}
