{
  "type": "Feature",
  "properties": {
    "iso:country":"GB",
    "wof:name":"LN10 5HL",
    "wof:placetype":"postalcode"
},
  "geometry": {"coordinates":[-0.2343003184019,53.16940258586108],"type":"Point"}
}