{
  "type": "Feature",
  "properties": {
    "iso:country": "GB",
    "wof:name": "LN10 5HL",
    "wof:placetype": "postalcode"
  },
  "geometry": {"coordinates":[-0.235727,53.169205],"type":"Point"}
}
