{
  "type": "Feature",
  "properties": {
    "iso:country":"GB",
    "wof:name":"TD15 1LX",
    "wof:placetype":"postalcode"
},
  "geometry": {"coordinates":[-2.00301891419314,55.7740217648166],"type":"Point"}
}