{
  "type": "Feature",
  "properties": {
    "iso:country": "GB",
    "wof:name": "TD15 1LX",
    "wof:placetype": "postalcode"
  },
  "geometry": {"coordinates":[-2.003019,55.774022],"type":"Point"}
}
