{
  "type": "Feature",
  "properties": {
    "iso:country":"GB",
    "wof:name":"AB12 5PP",
    "wof:placetype":"postalcode"
},
  "geometry": {"coordinates":[-2.11060633170223,57.11836049449853],"type":"Point"}
}