{
  "type": "Feature",
  "properties": {
    "date:inception_lower": "1996-06-01",
    "date:inception_upper": "1996-06-01",
    "iso:country": "GB",
    "wof:name": "AB12 5PP",
    "wof:placetype": "postalcode"
  },
  "geometry": {"coordinates":[-2.110606,57.11836],"type":"Point"}
}
