{
  "type": "Feature",
  "properties": {
    "iso:country":"GB",
    "wof:name":"W4 5DY",
    "wof:placetype":"postalcode"
},
  "geometry": {"coordinates":[-0.26249424924627,51.50154059979593],"type":"Point"}
}