{
  "type": "Feature",
  "properties": {
    "date:inception_lower":"1986-07-01",
    "date:inception_upper":"1986-07-31",
    "iso:country":"GB",
    "wof:name":"CV35 9SE",
    "wof:placetype":"postalcode"
},
  "geometry": {"coordinates":[-1.600832,52.187736],"type":"Point"}
}