{
  "type": "Feature",
  "properties": {
    "iso:country":"GB",
    "wof:name":"G74 4XR",
    "wof:placetype":"postalcode"
},
  "geometry": {"coordinates":[-4.16865334400507,55.77518515606256],"type":"Point"}
}