{
  "type": "Feature",
  "properties": {
    "iso:country": "GB",
    "wof:name": "G74 4XR",
    "wof:placetype": "postalcode"
  },
  "geometry": {"coordinates":[-4.168606,55.775186],"type":"Point"}
}
