{
  "type": "Feature",
  "properties": {
    "iso:country": "GB",
    "wof:name": "NR25 6TA",
    "wof:placetype": "postalcode"
  },
  "geometry": {"coordinates":[1.066378,52.893764],"type":"Point"}
}
