{
  "type": "Feature",
  "properties": {
    "iso:country":"GB",
    "wof:name":"CH7 1GG",
    "wof:placetype":"postalcode"
},
  "geometry": {"coordinates":[-3.15489482917665,53.16730231440197],"type":"Point"}
}