{
  "type": "Feature",
  "properties": {
    "date:inception_lower":"1993-01-01",
    "date:inception_upper":"1993-01-31",
    "iso:country":"GB",
    "wof:name":"CH7 1GG",
    "wof:placetype":"postalcode"
},
  "geometry": {"coordinates":[-3.154895,53.167302],"type":"Point"}
}