{
  "type": "Feature",
  "properties": {
    "iso:country": "GB",
    "wof:name": "HA8 5SP",
    "wof:placetype": "postalcode"
  },
  "geometry": {"coordinates":[-0.274237,51.602536],"type":"Point"}
}
