{
  "type": "Feature",
  "properties": {
    "date:inception_lower":"1993-08-01",
    "date:inception_upper":"1993-08-31",
    "iso:country":"GB",
    "wof:name":"NN12 6LA",
    "wof:placetype":"postalcode"
},
  "geometry": {"coordinates":[-0.978251,52.125081],"type":"Point"}
}