{
  "type": "Feature",
  "properties": {
    "iso:country":"GB",
    "wof:name":"BS7 0BB",
    "wof:placetype":"postalcode"
},
  "geometry": {"coordinates":[-2.574610499073,51.49390852451125],"type":"Point"}
}