{
  "type": "Feature",
  "properties": {
    "iso:country": "GB",
    "wof:name": "BS7 0BB",
    "wof:placetype": "postalcode"
  },
  "geometry": {"coordinates":[-2.574681,51.493782],"type":"Point"}
}
