{
  "type": "Feature",
  "properties": {
    "date:inception_lower": "1983-03-01",
    "date:inception_upper": "1983-03-01",
    "iso:country": "GB",
    "wof:name": "CM16 5EJ",
    "wof:placetype": "postalcode"
  },
  "geometry": {"coordinates":[0.105271,51.696115],"type":"Point"}
}
