{
  "type": "Feature",
  "properties": {
    "date:inception_lower":"2000-12-01",
    "date:inception_upper":"2000-12-31",
    "iso:country":"GB",
    "wof:name":"WD18 9ET",
    "wof:placetype":"postalcode"
},
  "geometry": {"coordinates":[-0.434279,51.639354],"type":"Point"}
}