{
  "type": "Feature",
  "properties": {
    "iso:country": "GB",
    "wof:name": "WD18 9ET",
    "wof:placetype": "postalcode"
  },
  "geometry": {"coordinates":[-0.434279,51.639354],"type":"Point"}
}
