{
  "type": "Feature",
  "properties": {
    "date:inception_lower": "1980-01-01",
    "date:inception_upper": "1980-01-01",
    "iso:country": "GB",
    "wof:name": "EX8 4LN",
    "wof:placetype": "postalcode"
  },
  "geometry": {"coordinates":[-3.385903,50.637431],"type":"Point"}
}
