{
  "type": "Feature",
  "properties": {
    "iso:country":"GB",
    "wof:name":"TS10 4HF",
    "wof:placetype":"postalcode"
},
  "geometry": {"coordinates":[-1.08362851539106,54.60101721280555],"type":"Point"}
}