{
  "type": "Feature",
  "properties": {
    "iso:country":"GB",
    "wof:name":"N3 2EA",
    "wof:placetype":"postalcode"
},
  "geometry": {"coordinates":[-0.18126260431436,51.60673413636297],"type":"Point"}
}