{
  "type": "Feature",
  "properties": {
    "date:inception_lower":"1981-09-01",
    "date:inception_upper":"1981-09-30",
    "iso:country":"GB",
    "wof:name":"TR1 3UP",
    "wof:placetype":"postalcode"
},
  "geometry": {"coordinates":[-5.093566,50.267934],"type":"Point"}
}