{
  "type": "Feature",
  "properties": {
    "iso:country": "GB",
    "wof:name": "TR1 3UP",
    "wof:placetype": "postalcode"
  },
  "geometry": {"coordinates":[-5.093566,50.267934],"type":"Point"}
}
