{
  "type": "Feature",
  "properties": {
    "iso:country":"GB",
    "wof:name":"TR1 3UP",
    "wof:placetype":"postalcode"
},
  "geometry": {"coordinates":[-5.0935660066523,50.26793441168086],"type":"Point"}
}