{
  "type": "Feature",
  "properties": {
    "iso:country":"GB",
    "wof:name":"CF5 3NS",
    "wof:placetype":"postalcode"
},
  "geometry": {"coordinates":[-3.24467331435424,51.49765692229296],"type":"Point"}
}