{
  "type": "Feature",
  "properties": {
    "iso:country":"GB",
    "wof:name":"NE33 5DU",
    "wof:placetype":"postalcode"
},
  "geometry": {"coordinates":[-1.43678491101502,54.98769332584124],"type":"Point"}
}