{
  "type": "Feature",
  "properties": {
    "date:inception_lower": "1996-12-01",
    "date:inception_upper": "1996-12-01",
    "iso:country": "GB",
    "wof:name": "L2 9UB",
    "wof:placetype": "postalcode"
  },
  "geometry": {"coordinates":[-2.990026,53.405793],"type":"Point"}
}
