{
  "type": "Feature",
  "properties": {
    "iso:country":"GB",
    "wof:name":"LE9 7BG",
    "wof:placetype":"postalcode"
},
  "geometry": {"coordinates":[-1.30715421758397,52.57554016435878],"type":"Point"}
}