{
  "type": "Feature",
  "properties": {
    "date:inception_lower": "1980-01-01",
    "date:inception_upper": "1980-01-01",
    "iso:country": "GB",
    "wof:name": "LE9 7BG",
    "wof:placetype": "postalcode"
  },
  "geometry": {"coordinates":[-1.307154,52.57554],"type":"Point"}
}
