{
  "type": "Feature",
  "properties": {
    "date:inception_lower": "1994-12-01",
    "date:inception_upper": "1994-12-01",
    "iso:country": "GB",
    "wof:name": "SO53 3BG",
    "wof:placetype": "postalcode"
  },
  "geometry": {"coordinates":[-1.376936,50.9765],"type":"Point"}
}
