{
  "type": "Feature",
  "properties": {
    "date:inception_lower": "1990-08-01",
    "date:inception_upper": "1990-08-01",
    "iso:country": "GB",
    "wof:name": "AB54 4HN",
    "wof:placetype": "postalcode"
  },
  "geometry": {"coordinates":[-2.906806,57.340558],"type":"Point"}
}
