{
  "type": "Feature",
  "properties": {
    "iso:country":"GB",
    "wof:name":"SS17 8JN",
    "wof:placetype":"postalcode"
},
  "geometry": {"coordinates":[0.44644859290277,51.53274363971397],"type":"Point"}
}