{
  "type": "Feature",
  "properties": {
    "iso:country": "GB",
    "wof:name": "YO13 0DQ",
    "wof:placetype": "postalcode"
  },
  "geometry": {"coordinates":[-0.459783,54.32352],"type":"Point"}
}
