{
  "type": "Feature",
  "properties": {
    "iso:country":"GB",
    "wof:name":"YO13 0DQ",
    "wof:placetype":"postalcode"
},
  "geometry": {"coordinates":[-0.45978289659086,54.32351979917744],"type":"Point"}
}