{
  "type": "Feature",
  "properties": {
    "date:inception_lower": "1993-08-01",
    "date:inception_upper": "1993-08-01",
    "iso:country": "GB",
    "wof:name": "FK8 1ND",
    "wof:placetype": "postalcode"
  },
  "geometry": {"coordinates":[-3.929403,56.123534],"type":"Point"}
}
