{
  "type": "Feature",
  "properties": {
    "iso:country":"GB",
    "wof:name":"FK8 1ND",
    "wof:placetype":"postalcode"
},
  "geometry": {"coordinates":[-3.92940317833968,56.12353411305702],"type":"Point"}
}