{
  "type": "Feature",
  "properties": {
    "date:inception_lower": "1980-01-01",
    "date:inception_upper": "1980-01-01",
    "iso:country": "GB",
    "wof:name": "CB11 4UR",
    "wof:placetype": "postalcode"
  },
  "geometry": {"coordinates":[0.126171,52.013484],"type":"Point"}
}
