{
  "type": "Feature",
  "properties": {
    "iso:country":"GB",
    "wof:name":"CB11 4UR",
    "wof:placetype":"postalcode"
},
  "geometry": {"coordinates":[0.12617125227722,52.0134843935791],"type":"Point"}
}