{
  "type": "Feature",
  "properties": {
    "iso:country": "GB",
    "wof:name": "SY4 4SQ",
    "wof:placetype": "postalcode"
  },
  "geometry": {"coordinates":[-2.699011,52.72164],"type":"Point"}
}
