{
  "type": "Feature",
  "properties": {
    "date:inception_lower":"1998-06-01",
    "date:inception_upper":"1998-06-30",
    "iso:country":"GB",
    "wof:name":"DL16 6NS",
    "wof:placetype":"postalcode"
},
  "geometry": {"coordinates":[-1.596779,54.698677],"type":"Point"}
}