{
  "type": "Feature",
  "properties": {
    "iso:country":"GB",
    "wof:name":"DL16 6NS",
    "wof:placetype":"postalcode"
},
  "geometry": {"coordinates":[-1.5967794949123,54.69867684749646],"type":"Point"}
}