{
  "type": "Feature",
  "properties": {
    "date:inception_lower": "1980-01-01",
    "date:inception_upper": "1980-01-01",
    "iso:country": "GB",
    "wof:name": "E4 8QQ",
    "wof:placetype": "postalcode"
  },
  "geometry": {"coordinates":[-0.028571,51.611058],"type":"Point"}
}
