{
  "type": "Feature",
  "properties": {
    "iso:country":"GB",
    "wof:name":"E4 8QQ",
    "wof:placetype":"postalcode"
},
  "geometry": {"coordinates":[-0.02857083707149,51.61105820564098],"type":"Point"}
}