{
  "type": "Feature",
  "properties": {
    "iso:country":"GB",
    "wof:name":"PO5 2FB",
    "wof:placetype":"postalcode"
},
  "geometry": {"coordinates":[-1.08126277185348,50.77963212873265],"type":"Point"}
}