{
  "type": "Feature",
  "properties": {
    "iso:country": "GB",
    "wof:name": "PO5 2FB",
    "wof:placetype": "postalcode"
  },
  "geometry": {"coordinates":[-1.081263,50.779632],"type":"Point"}
}
