{
  "type": "Feature",
  "properties": {
    "date:inception_lower": "2003-11-01",
    "date:inception_upper": "2003-11-01",
    "iso:country": "GB",
    "wof:name": "PO5 2FB",
    "wof:placetype": "postalcode"
  },
  "geometry": {"coordinates":[-1.081263,50.779632],"type":"Point"}
}
