{
  "type": "Feature",
  "properties": {
    "date:inception_lower": "1980-01-01",
    "date:inception_upper": "1980-01-01",
    "iso:country": "GB",
    "wof:name": "HU3 1AF",
    "wof:placetype": "postalcode"
  },
  "geometry": {"coordinates":[-0.348404,53.748711],"type":"Point"}
}
