{
  "type": "Feature",
  "properties": {
    "iso:country": "GB",
    "wof:name": "CB8 9HT",
    "wof:placetype": "postalcode"
  },
  "geometry": {"coordinates":[0.505061,52.150488],"type":"Point"}
}
