{
  "type": "Feature",
  "properties": {
    "date:inception_lower": "1980-01-01",
    "date:inception_upper": "1980-01-01",
    "iso:country": "GB",
    "wof:name": "CB8 9HT",
    "wof:placetype": "postalcode"
  },
  "geometry": {"coordinates":[0.494769,52.146822],"type":"Point"}
}
