{
  "type": "Feature",
  "properties": {
    "iso:country":"GB",
    "wof:name":"DN37 9JG",
    "wof:placetype":"postalcode"
},
  "geometry": {"coordinates":[-0.12569993403789,53.57334415446031],"type":"Point"}
}