{
  "type": "Feature",
  "properties": {
    "date:inception_lower": "2007-08-01",
    "date:inception_upper": "2007-08-01",
    "iso:country": "GB",
    "wof:name": "SA45 9TA",
    "wof:placetype": "postalcode"
  },
  "geometry": {"coordinates":[-4.345554,52.204017],"type":"Point"}
}
