{
  "type": "Feature",
  "properties": {
    "date:inception_lower": "1986-07-01",
    "date:inception_upper": "1986-07-01",
    "iso:country": "GB",
    "wof:name": "ME10 2LF",
    "wof:placetype": "postalcode"
  },
  "geometry": {"coordinates":[0.734869,51.356172],"type":"Point"}
}
