{
  "type": "Feature",
  "properties": {
    "iso:country":"GB",
    "wof:name":"BR5 2AX",
    "wof:placetype":"postalcode"
},
  "geometry": {"coordinates":[0.10162819387661,51.38790843274076],"type":"Point"}
}