{
  "type": "Feature",
  "properties": {
    "iso:country":"GB",
    "wof:name":"S81 9BY",
    "wof:placetype":"postalcode"
},
  "geometry": {"coordinates":[-1.11717792701089,53.35563585389641],"type":"Point"}
}