{
  "type": "Feature",
  "properties": {
    "date:inception_lower": "2017-11-01",
    "date:inception_upper": "2017-11-01",
    "iso:country": "GB",
    "wof:name": "ST1 3DX",
    "wof:placetype": "postalcode"
  },
  "geometry": {"coordinates":[-2.165831,53.019956],"type":"Point"}
}
