{
  "type": "Feature",
  "properties": {
    "iso:country": "GB",
    "wof:name": "ST1 3DX",
    "wof:placetype": "postalcode"
  },
  "geometry": {"coordinates":[-2.165831,53.019956],"type":"Point"}
}
