{
  "type": "Feature",
  "properties": {
    "iso:country":"GB",
    "wof:name":"PE7 2AP",
    "wof:placetype":"postalcode"
},
  "geometry": {"coordinates":[-0.10243009554798,52.55766981974948],"type":"Point"}
}