{
  "type": "Feature",
  "properties": {
    "date:inception_lower": "1980-01-01",
    "date:inception_upper": "1980-01-01",
    "iso:country": "GB",
    "wof:name": "PE7 2AP",
    "wof:placetype": "postalcode"
  },
  "geometry": {"coordinates":[-0.10243,52.55767],"type":"Point"}
}
