{
  "type": "Feature",
  "properties": {
    "iso:country":"GB",
    "wof:name":"G83 0RA",
    "wof:placetype":"postalcode"
},
  "geometry": {"coordinates":[-4.57792901939322,55.99681980710707],"type":"Point"}
}