{
  "type": "Feature",
  "properties": {
    "date:inception_lower": "2009-09-01",
    "date:inception_upper": "2009-09-01",
    "iso:country": "GB",
    "wof:name": "TN3 9LQ",
    "wof:placetype": "postalcode"
  },
  "geometry": {"coordinates":[0.204735,51.065336],"type":"Point"}
}
