{
  "type": "Feature",
  "properties": {
    "iso:country":"GB",
    "wof:name":"TN3 9LQ",
    "wof:placetype":"postalcode"
},
  "geometry": {"coordinates":[0.20462193456258,51.06535877466546],"type":"Point"}
}