{
  "type": "Feature",
  "properties": {
    "iso:country":"GB",
    "wof:name":"TQ12 4QX",
    "wof:placetype":"postalcode"
},
  "geometry": {"coordinates":[-3.53108633214471,50.52517506078965],"type":"Point"}
}