{
  "type": "Feature",
  "properties": {
    "iso:country": "GB",
    "wof:name": "TQ12 4QX",
    "wof:placetype": "postalcode"
  },
  "geometry": {"coordinates":[-3.531086,50.525175],"type":"Point"}
}
