{
  "type": "Feature",
  "properties": {
    "iso:country": "GB",
    "wof:name": "NR6 6SH",
    "wof:placetype": "postalcode"
  },
  "geometry": {"coordinates":[1.286311,52.657375],"type":"Point"}
}
