{
  "type": "Feature",
  "properties": {
    "iso:country":"GB",
    "wof:name":"NR6 6SH",
    "wof:placetype":"postalcode"
},
  "geometry": {"coordinates":[1.28631098888538,52.65737498209467],"type":"Point"}
}