{
  "type": "Feature",
  "properties": {
    "date:inception_lower": "2006-03-01",
    "date:inception_upper": "2006-03-01",
    "iso:country": "GB",
    "wof:name": "W1H 1PJ",
    "wof:placetype": "postalcode"
  },
  "geometry": {"coordinates":[-0.159772,51.519928],"type":"Point"}
}
