{
  "type": "Feature",
  "properties": {
    "iso:country":"GB",
    "wof:name":"W1H 1PJ",
    "wof:placetype":"postalcode"
},
  "geometry": {"coordinates":[-0.15977211907228,51.51992811963607],"type":"Point"}
}