{
  "type": "Feature",
  "properties": {
    "date:inception_lower": "1980-01-01",
    "date:inception_upper": "1980-01-01",
    "iso:country": "GB",
    "wof:name": "DN15 0BU",
    "wof:placetype": "postalcode"
  },
  "geometry": {"coordinates":[-0.609059,53.620661],"type":"Point"}
}
