{
  "type": "Feature",
  "properties": {
    "iso:country":"GB",
    "wof:name":"DN15 0BU",
    "wof:placetype":"postalcode"
},
  "geometry": {"coordinates":[-0.60905883727212,53.62066109574188],"type":"Point"}
}