{
  "type": "Feature",
  "properties": {
    "iso:country": "GB",
    "wof:name": "DN15 0BU",
    "wof:placetype": "postalcode"
  },
  "geometry": {"coordinates":[-0.609059,53.620661],"type":"Point"}
}
