{
  "type": "Feature",
  "properties": {
    "iso:country": "GB",
    "wof:name": "SO31 9GS",
    "wof:placetype": "postalcode"
  },
  "geometry": {"coordinates":[-1.300871,50.852089],"type":"Point"}
}
