{
  "type": "Feature",
  "properties": {
    "iso:country":"GB",
    "wof:name":"DE3 0BU",
    "wof:placetype":"postalcode"
},
  "geometry": {"coordinates":[-1.54653152830377,52.90244667115851],"type":"Point"}
}