{
  "type": "Feature",
  "properties": {
    "date:inception_lower": "1999-06-01",
    "date:inception_upper": "1999-06-01",
    "iso:country": "GB",
    "wof:name": "CH62 5EL",
    "wof:placetype": "postalcode"
  },
  "geometry": {"coordinates":[-2.999215,53.357581],"type":"Point"}
}
