{
  "type": "Feature",
  "properties": {
    "date:inception_lower": "2019-05-01",
    "date:inception_upper": "2019-05-01",
    "iso:country": "GB",
    "wof:name": "S70 5TB",
    "wof:placetype": "postalcode"
  },
  "geometry": {"coordinates":[-1.484023,53.505441],"type":"Point"}
}
