{
  "type": "Feature",
  "properties": {
    "date:inception_lower":"1980-01-01",
    "date:inception_upper":"1980-01-31",
    "iso:country":"GB",
    "wof:name":"EX20 3BU",
    "wof:placetype":"postalcode"
},
  "geometry": {"coordinates":[-4.085615,50.767967],"type":"Point"}
}