{
  "type": "Feature",
  "properties": {
    "iso:country": "GB",
    "wof:name": "SN4 8ED",
    "wof:placetype": "postalcode"
  },
  "geometry": {"coordinates":[-1.888384,51.561648],"type":"Point"}
}
