{
  "type": "Feature",
  "properties": {
    "iso:country":"GB",
    "wof:name":"SN4 8ED",
    "wof:placetype":"postalcode"
},
  "geometry": {"coordinates":[-1.88838393882417,51.56164813792011],"type":"Point"}
}