{
  "type": "Feature",
  "properties": {
    "date:inception_lower": "2019-09-01",
    "date:inception_upper": "2019-09-01",
    "iso:country": "GB",
    "wof:name": "AB41 6EG",
    "wof:placetype": "postalcode"
  },
  "geometry": {"coordinates":[-2.003375,57.311724],"type":"Point"}
}
