{
  "type": "Feature",
  "properties": {
    "date:inception_lower": "1980-01-01",
    "date:inception_upper": "1980-01-01",
    "iso:country": "GB",
    "wof:name": "LL22 9NB",
    "wof:placetype": "postalcode"
  },
  "geometry": {"coordinates":[-3.528595,53.297182],"type":"Point"}
}
