{
  "type": "Feature",
  "properties": {
    "iso:country":"GB",
    "wof:name":"MK3 5DD",
    "wof:placetype":"postalcode"
},
  "geometry": {"coordinates":[-0.76120424844549,51.9866688131269],"type":"Point"}
}