{
  "type": "Feature",
  "properties": {
    "iso:country": "GB",
    "wof:name": "MK3 5DD",
    "wof:placetype": "postalcode"
  },
  "geometry": {"coordinates":[-0.761204,51.986669],"type":"Point"}
}
