{
  "type": "Feature",
  "properties": {
    "iso:country":"GB",
    "wof:name":"NE33 3LW",
    "wof:placetype":"postalcode"
},
  "geometry": {"coordinates":[-1.42647619354569,54.99168903042442],"type":"Point"}
}