{
  "type": "Feature",
  "properties": {
    "iso:country": "GB",
    "wof:name": "NE33 3LW",
    "wof:placetype": "postalcode"
  },
  "geometry": {"coordinates":[-1.426476,54.991689],"type":"Point"}
}
