{
  "type": "Feature",
  "properties": {
    "iso:country":"GB",
    "wof:name":"EX17 1DL",
    "wof:placetype":"postalcode"
},
  "geometry": {"coordinates":[-3.65101564529383,50.79487837875061],"type":"Point"}
}