{
  "type": "Feature",
  "properties": {
    "date:inception_lower": "2002-09-01",
    "date:inception_upper": "2002-09-01",
    "iso:country": "GB",
    "wof:name": "EX17 1DL",
    "wof:placetype": "postalcode"
  },
  "geometry": {"coordinates":[-3.651016,50.794878],"type":"Point"}
}
