{
  "type": "Feature",
  "properties": {
    "iso:country":"GB",
    "wof:name":"OL1 1SG",
    "wof:placetype":"postalcode"
},
  "geometry": {"coordinates":[-2.10630128315572,53.5420455690252],"type":"Point"}
}