{
  "type": "Feature",
  "properties": {
    "iso:country":"GB",
    "wof:name":"BR2 0XE",
    "wof:placetype":"postalcode"
},
  "geometry": {"coordinates":[0.00990368107396,51.39455389664456],"type":"Point"}
}