{
  "type": "Feature",
  "properties": {
    "iso:country": "GB",
    "wof:name": "M6 5JX",
    "wof:placetype": "postalcode"
  },
  "geometry": {"coordinates":[-2.288751,53.48598],"type":"Point"}
}
