{
  "type": "Feature",
  "properties": {
    "date:inception_lower":"2008-11-01",
    "date:inception_upper":"2008-11-30",
    "iso:country":"GB",
    "wof:name":"M6 5JX",
    "wof:placetype":"postalcode"
},
  "geometry": {"coordinates":[-2.288751,53.48598],"type":"Point"}
}