{
  "type": "Feature",
  "properties": {
    "iso:country":"GB",
    "wof:name":"DL6 2RJ",
    "wof:placetype":"postalcode"
},
  "geometry": {"coordinates":[-1.41920386988191,54.3615278672991],"type":"Point"}
}