{
  "type": "Feature",
  "properties": {
    "iso:country": "GB",
    "wof:name": "LS12 2HG",
    "wof:placetype": "postalcode"
  },
  "geometry": {"coordinates":[-1.580246,53.801081],"type":"Point"}
}
