{
  "type": "Feature",
  "properties": {
    "date:inception_lower": "1998-12-01",
    "date:inception_upper": "1998-12-01",
    "iso:country": "GB",
    "wof:name": "CF64 1SE",
    "wof:placetype": "postalcode"
  },
  "geometry": {"coordinates":[-3.174735,51.445686],"type":"Point"}
}
