{
  "type": "Feature",
  "properties": {
    "iso:country": "GB",
    "wof:name": "NE8 3AR",
    "wof:placetype": "postalcode"
  },
  "geometry": {"coordinates":[-1.599398,54.964638],"type":"Point"}
}
