{
  "type": "Feature",
  "properties": {
    "iso:country":"GB",
    "wof:name":"NE8 3AR",
    "wof:placetype":"postalcode"
},
  "geometry": {"coordinates":[-1.59941161623164,54.96514363191828],"type":"Point"}
}