{
  "type": "Feature",
  "properties": {
    "iso:country": "GB",
    "wof:name": "LN11 1BQ",
    "wof:placetype": "postalcode"
  },
  "geometry": {"coordinates":[-0.006694,53.367023],"type":"Point"}
}
