{
  "type": "Feature",
  "properties": {
    "iso:country": "GB",
    "wof:name": "NR22 6BN",
    "wof:placetype": "postalcode"
  },
  "geometry": {"coordinates":[0.872183,52.893982],"type":"Point"}
}
