{
  "type": "Feature",
  "properties": {
    "iso:country":"GB",
    "wof:name":"LL23 7UU",
    "wof:placetype":"postalcode"
},
  "geometry": {"coordinates":[-3.59936448722515,52.91128481397863],"type":"Point"}
}