{
  "type": "Feature",
  "properties": {
    "iso:country": "GB",
    "wof:name": "IP17 1HU",
    "wof:placetype": "postalcode"
  },
  "geometry": {"coordinates":[1.485393,52.199591],"type":"Point"}
}
