{
  "type": "Feature",
  "properties": {
    "iso:country":"GB",
    "wof:name":"BA14 0PY",
    "wof:placetype":"postalcode"
},
  "geometry": {"coordinates":[-2.20478739281741,51.30916424407197],"type":"Point"}
}