{
  "type": "Feature",
  "properties": {
    "date:inception_lower":"1993-08-01",
    "date:inception_upper":"1993-08-31",
    "iso:country":"GB",
    "wof:name":"EN8 7PQ",
    "wof:placetype":"postalcode"
},
  "geometry": {"coordinates":[-0.032222,51.685967],"type":"Point"}
}