{
  "type": "Feature",
  "properties": {
    "iso:country":"GB",
    "wof:name":"EN8 7PQ",
    "wof:placetype":"postalcode"
},
  "geometry": {"coordinates":[-0.03230622640144,51.68595605272706],"type":"Point"}
}