{
  "type": "Feature",
  "properties": {
    "iso:country": "GB",
    "wof:name": "GL52 2AF",
    "wof:placetype": "postalcode"
  },
  "geometry": {"coordinates":[-2.070953,51.906199],"type":"Point"}
}
