{
  "type": "Feature",
  "properties": {
    "iso:country":"GB",
    "wof:name":"B31 1RF",
    "wof:placetype":"postalcode"
},
  "geometry": {"coordinates":[-1.97863853031466,52.4125263073671],"type":"Point"}
}