{
  "type": "Feature",
  "properties": {
    "iso:country":"GB",
    "wof:name":"B73 6JT",
    "wof:placetype":"postalcode"
},
  "geometry": {"coordinates":[-1.85822802448894,52.55610304775368],"type":"Point"}
}