{
  "type": "Feature",
  "properties": {
    "iso:country": "GB",
    "wof:name": "NE65 0HT",
    "wof:placetype": "postalcode"
  },
  "geometry": {"coordinates":[-1.58073,55.309695],"type":"Point"}
}
