{
  "type": "Feature",
  "properties": {
    "iso:country":"GB",
    "wof:name":"NG2 6DJ",
    "wof:placetype":"postalcode"
},
  "geometry": {"coordinates":[-1.12612217270202,52.92660020171694],"type":"Point"}
}