{
  "type": "Feature",
  "properties": {
    "iso:country":"GB",
    "wof:name":"SM4 4NU",
    "wof:placetype":"postalcode"
},
  "geometry": {"coordinates":[-0.22681813486571,51.39012906107781],"type":"Point"}
}