{
  "type": "Feature",
  "properties": {
    "date:inception_lower":"1980-01-01",
    "date:inception_upper":"1980-01-31",
    "iso:country":"GB",
    "wof:name":"DA17 5QP",
    "wof:placetype":"postalcode"
},
  "geometry": {"coordinates":[0.149705,51.485932],"type":"Point"}
}