{
  "type": "Feature",
  "properties": {
    "iso:country": "GB",
    "wof:name": "IP4 3LJ",
    "wof:placetype": "postalcode"
  },
  "geometry": {"coordinates":[1.193211,52.06535],"type":"Point"}
}
