{
  "type": "Feature",
  "properties": {
    "iso:country":"GB",
    "wof:name":"IP4 3LJ",
    "wof:placetype":"postalcode"
},
  "geometry": {"coordinates":[1.19321059591232,52.06534994669745],"type":"Point"}
}