{
  "type": "Feature",
  "properties": {
    "iso:country": "GB",
    "wof:name": "TR7 3EX",
    "wof:placetype": "postalcode"
  },
  "geometry": {"coordinates":[-5.043504,50.420222],"type":"Point"}
}
