{
  "type": "Feature",
  "properties": {
    "date:inception_lower": "1980-01-01",
    "date:inception_upper": "1980-01-01",
    "iso:country": "GB",
    "wof:name": "TR7 3EX",
    "wof:placetype": "postalcode"
  },
  "geometry": {"coordinates":[-5.043508,50.42024],"type":"Point"}
}
