{
  "type": "Feature",
  "properties": {
    "iso:country":"GB",
    "wof:name":"TR7 3EX",
    "wof:placetype":"postalcode"
},
  "geometry": {"coordinates":[-5.04350437814261,50.42022158293475],"type":"Point"}
}