{
  "type": "Feature",
  "properties": {
    "iso:country":"GB",
    "wof:name":"IP8 3DR",
    "wof:placetype":"postalcode"
},
  "geometry": {"coordinates":[1.05914280964835,52.05972639294554],"type":"Point"}
}