{
  "type": "Feature",
  "properties": {
    "iso:country":"GB",
    "wof:name":"HX3 9DS",
    "wof:placetype":"postalcode"
},
  "geometry": {"coordinates":[-1.84979096456958,53.70258275463388],"type":"Point"}
}