{
  "type": "Feature",
  "properties": {
    "iso:country":"GB",
    "wof:name":"TQ3 3JQ",
    "wof:placetype":"postalcode"
},
  "geometry": {"coordinates":[-3.5809448972072,50.44028261491685],"type":"Point"}
}