{
  "type": "Feature",
  "properties": {
    "iso:country": "GB",
    "wof:name": "KT13 0HY",
    "wof:placetype": "postalcode"
  },
  "geometry": {"coordinates":[-0.434374,51.364139],"type":"Point"}
}
