{
  "type": "Feature",
  "properties": {
    "date:inception_lower":"1980-01-01",
    "date:inception_upper":"1980-01-31",
    "iso:country":"GB",
    "wof:name":"WS2 0DY",
    "wof:placetype":"postalcode"
},
  "geometry": {"coordinates":[-2.022317,52.585277],"type":"Point"}
}