{
  "type": "Feature",
  "properties": {
    "iso:country": "GB",
    "wof:name": "WS2 0DY",
    "wof:placetype": "postalcode"
  },
  "geometry": {"coordinates":[-2.022317,52.585277],"type":"Point"}
}
