{
  "type": "Feature",
  "properties": {
    "date:inception_lower": "1999-06-01",
    "date:inception_upper": "1999-06-01",
    "iso:country": "GB",
    "wof:name": "CF24 4JH",
    "wof:placetype": "postalcode"
  },
  "geometry": {"coordinates":[-3.183401,51.4942],"type":"Point"}
}
