{
  "type": "Feature",
  "properties": {
    "iso:country":"GB",
    "wof:name":"IP26 4NR",
    "wof:placetype":"postalcode"
},
  "geometry": {"coordinates":[0.55074603014868,52.5228602369097],"type":"Point"}
}