{
  "type": "Feature",
  "properties": {
    "iso:country": "GB",
    "wof:name": "IP26 4NR",
    "wof:placetype": "postalcode"
  },
  "geometry": {"coordinates":[0.550746,52.52286],"type":"Point"}
}
