{
  "type": "Feature",
  "properties": {
    "iso:country":"GB",
    "wof:name":"CM18 6HL",
    "wof:placetype":"postalcode"
},
  "geometry": {"coordinates":[0.12007412367454,51.76202495381413],"type":"Point"}
}