{
  "type": "Feature",
  "properties": {
    "iso:country":"GB",
    "wof:name":"PO40 9LT",
    "wof:placetype":"postalcode"
},
  "geometry": {"coordinates":[-1.53029902993942,50.68583876985225],"type":"Point"}
}