{
  "type": "Feature",
  "properties": {
    "date:inception_lower": "1980-01-01",
    "date:inception_upper": "1980-01-01",
    "iso:country": "GB",
    "wof:name": "TA24 8LB",
    "wof:placetype": "postalcode"
  },
  "geometry": {"coordinates":[-3.595136,51.20862],"type":"Point"}
}
