{
  "type": "Feature",
  "properties": {
    "iso:country":"GB",
    "wof:name":"TA24 8LB",
    "wof:placetype":"postalcode"
},
  "geometry": {"coordinates":[-3.59512035771565,51.20859489404918],"type":"Point"}
}