{
  "type": "Feature",
  "properties": {
    "iso:country":"GB",
    "wof:name":"YO25 4JE",
    "wof:placetype":"postalcode"
},
  "geometry": {"coordinates":[-0.3059931703693,54.09287898264603],"type":"Point"}
}