{
  "type": "Feature",
  "properties": {
    "iso:country": "GB",
    "wof:name": "YO25 4JE",
    "wof:placetype": "postalcode"
  },
  "geometry": {"coordinates":[-0.305993,54.092879],"type":"Point"}
}
