{
  "type": "Feature",
  "properties": {
    "iso:country": "GB",
    "wof:name": "DN3 2QT",
    "wof:placetype": "postalcode"
  },
  "geometry": {"coordinates":[-1.075139,53.547687],"type":"Point"}
}
