{
  "type": "Feature",
  "properties": {
    "iso:country": "GB",
    "wof:name": "PO22 6BA",
    "wof:placetype": "postalcode"
  },
  "geometry": {"coordinates":[-0.6354,50.796025],"type":"Point"}
}
