{
  "type": "Feature",
  "properties": {
    "date:inception_lower": "2001-06-01",
    "date:inception_upper": "2001-06-01",
    "iso:country": "GB",
    "wof:name": "PO22 6BA",
    "wof:placetype": "postalcode"
  },
  "geometry": {"coordinates":[-0.6354,50.796025],"type":"Point"}
}
