{
  "type": "Feature",
  "properties": {
    "iso:country":"GB",
    "wof:name":"BD4 7JT",
    "wof:placetype":"postalcode"
},
  "geometry": {"coordinates":[-1.73782151330721,53.78296831235637],"type":"Point"}
}