{
  "type": "Feature",
  "properties": {
    "iso:country":"GB",
    "wof:name":"EN7 6LB",
    "wof:placetype":"postalcode"
},
  "geometry": {"coordinates":[-0.05484340145678,51.70997236080243],"type":"Point"}
}