{
  "type": "Feature",
  "properties": {
    "date:inception_lower": "1980-01-01",
    "date:inception_upper": "1980-01-01",
    "iso:country": "GB",
    "wof:name": "EN7 6LB",
    "wof:placetype": "postalcode"
  },
  "geometry": {"coordinates":[-0.054843,51.709972],"type":"Point"}
}
