{
  "type": "Feature",
  "properties": {
    "iso:country":"GB",
    "wof:name":"KY11 7HB",
    "wof:placetype":"postalcode"
},
  "geometry": {"coordinates":[-3.37665450707473,56.05315384695733],"type":"Point"}
}