{
  "type": "Feature",
  "properties": {
    "iso:country":"GB",
    "wof:name":"W1U 2SB",
    "wof:placetype":"postalcode"
},
  "geometry": {"coordinates":[-0.1500052055172,51.51658214820638],"type":"Point"}
}