{
  "type": "Feature",
  "properties": {
    "iso:country":"GB",
    "wof:name":"KA3 2HR",
    "wof:placetype":"postalcode"
},
  "geometry": {"coordinates":[-4.49173378369814,55.63320936578735],"type":"Point"}
}