{
  "type": "Feature",
  "properties": {
    "iso:country":"GB",
    "wof:name":"BA14 6AP",
    "wof:placetype":"postalcode"
},
  "geometry": {"coordinates":[-2.1788998849131,51.30007106328556],"type":"Point"}
}