{
  "type": "Feature",
  "properties": {
    "iso:country":"GB",
    "wof:name":"N19 3XZ",
    "wof:placetype":"postalcode"
},
  "geometry": {"coordinates":[-0.12702182556083,51.56772632735079],"type":"Point"}
}