{
  "type": "Feature",
  "properties": {
    "iso:country":"GB",
    "wof:name":"NW2 3RA",
    "wof:placetype":"postalcode"
},
  "geometry": {"coordinates":[-0.20778815889425,51.55179428634065],"type":"Point"}
}