{
  "type": "Feature",
  "properties": {
    "iso:country":"GB",
    "wof:name":"S20 6SF",
    "wof:placetype":"postalcode"
},
  "geometry": {"coordinates":[-1.38550214151412,53.33984417837997],"type":"Point"}
}