{
  "type": "Feature",
  "properties": {
    "iso:country": "GB",
    "wof:name": "G81 3RG",
    "wof:placetype": "postalcode"
  },
  "geometry": {"coordinates":[-4.421378,55.915421],"type":"Point"}
}
