{
  "type": "Feature",
  "properties": {
    "iso:country":"GB",
    "wof:name":"G81 3RG",
    "wof:placetype":"postalcode"
},
  "geometry": {"coordinates":[-4.42137779871144,55.91542061068326],"type":"Point"}
}