{
  "type": "Feature",
  "properties": {
    "date:inception_lower": "1980-01-01",
    "date:inception_upper": "1980-01-01",
    "iso:country": "GB",
    "wof:name": "G81 3RG",
    "wof:placetype": "postalcode"
  },
  "geometry": {"coordinates":[-4.421378,55.915421],"type":"Point"}
}
