{
  "type": "Feature",
  "properties": {
    "iso:country":"GB",
    "wof:name":"LU2 7BP",
    "wof:placetype":"postalcode"
},
  "geometry": {"coordinates":[-0.41760001361494,51.90960484566343],"type":"Point"}
}