{
  "type": "Feature",
  "properties": {
    "date:inception_lower":"1980-01-01",
    "date:inception_upper":"1980-01-31",
    "iso:country":"GB",
    "wof:name":"BD19 4AB",
    "wof:placetype":"postalcode"
},
  "geometry": {"coordinates":[-1.703184,53.725517],"type":"Point"}
}