{
  "type": "Feature",
  "properties": {
    "iso:country": "GB",
    "wof:name": "BD19 4AB",
    "wof:placetype": "postalcode"
  },
  "geometry": {"coordinates":[-1.703184,53.725517],"type":"Point"}
}
