{
  "type": "Feature",
  "properties": {
    "iso:country":"GB",
    "wof:name":"BD19 4AB",
    "wof:placetype":"postalcode"
},
  "geometry": {"coordinates":[-1.70318411947064,53.72551688555441],"type":"Point"}
}