{
  "type": "Feature",
  "properties": {
    "iso:country":"GB",
    "wof:name":"W13 0RJ",
    "wof:placetype":"postalcode"
},
  "geometry": {"coordinates":[-0.32540120086618,51.51133106631392],"type":"Point"}
}