{
  "type": "Feature",
  "properties": {
    "iso:country":"GB",
    "wof:name":"NW9 5EW",
    "wof:placetype":"postalcode"
},
  "geometry": {"coordinates":[-0.2430615668952,51.59578760392196],"type":"Point"}
}