{
  "type": "Feature",
  "properties": {
    "iso:country": "GB",
    "wof:name": "NW9 5EW",
    "wof:placetype": "postalcode"
  },
  "geometry": {"coordinates":[-0.243062,51.595788],"type":"Point"}
}
