{
  "type": "Feature",
  "properties": {
    "iso:country":"GB",
    "wof:name":"PE11 3UQ",
    "wof:placetype":"postalcode"
},
  "geometry": {"coordinates":[-0.15433434592492,52.80769965471302],"type":"Point"}
}