{
  "type": "Feature",
  "properties": {
    "iso:country":"GB",
    "wof:name":"SL3 9PH",
    "wof:placetype":"postalcode"
},
  "geometry": {"coordinates":[-0.53179668314779,51.46956690408277],"type":"Point"}
}