{
  "type": "Feature",
  "properties": {
    "date:inception_lower": "1980-01-01",
    "date:inception_upper": "1980-01-01",
    "iso:country": "GB",
    "wof:name": "SL3 9PH",
    "wof:placetype": "postalcode"
  },
  "geometry": {"coordinates":[-0.531797,51.469567],"type":"Point"}
}
