{
  "type": "Feature",
  "properties": {
    "date:inception_lower": "1980-01-01",
    "date:inception_upper": "1980-01-01",
    "iso:country": "GB",
    "wof:name": "NG7 4FB",
    "wof:placetype": "postalcode"
  },
  "geometry": {"coordinates":[-1.165143,52.958209],"type":"Point"}
}
