{
  "type": "Feature",
  "properties": {
    "iso:country":"GB",
    "wof:name":"NG7 4FB",
    "wof:placetype":"postalcode"
},
  "geometry": {"coordinates":[-1.16514276514019,52.95820913152696],"type":"Point"}
}