{
  "type": "Feature",
  "properties": {
    "iso:country": "GB",
    "wof:name": "NG7 4FB",
    "wof:placetype": "postalcode"
  },
  "geometry": {"coordinates":[-1.165143,52.958209],"type":"Point"}
}
