{
  "type": "Feature",
  "properties": {
    "iso:country": "GB",
    "wof:name": "CH2 3DU",
    "wof:placetype": "postalcode"
  },
  "geometry": {"coordinates":[-2.872346,53.194347],"type":"Point"}
}
