{
  "type": "Feature",
  "properties": {
    "iso:country":"GB",
    "wof:name":"CH2 3DU",
    "wof:placetype":"postalcode"
},
  "geometry": {"coordinates":[-2.87234577035823,53.19434671415341],"type":"Point"}
}