{
  "type": "Feature",
  "properties": {
    "iso:country":"GB",
    "wof:name":"G72 8HU",
    "wof:placetype":"postalcode"
},
  "geometry": {"coordinates":[-4.18629898359243,55.81322161228837],"type":"Point"}
}