{
  "type": "Feature",
  "properties": {
    "date:inception_lower":"2012-02-01",
    "date:inception_upper":"2012-02-29",
    "iso:country":"GB",
    "wof:name":"L5 6RT",
    "wof:placetype":"postalcode"
},
  "geometry": {"coordinates":[-2.965282,53.426437],"type":"Point"}
}