{
  "type": "Feature",
  "properties": {
    "iso:country":"GB",
    "wof:name":"L5 6RT",
    "wof:placetype":"postalcode"
},
  "geometry": {"coordinates":[-2.96528250533894,53.42643741069499],"type":"Point"}
}