{
  "type": "Feature",
  "properties": {
    "iso:country": "GB",
    "wof:name": "SA10 8TF",
    "wof:placetype": "postalcode"
  },
  "geometry": {"coordinates":[-3.751536,51.729781],"type":"Point"}
}
