{
  "type": "Feature",
  "properties": {
    "iso:country":"GB",
    "wof:name":"SW3 3PS",
    "wof:placetype":"postalcode"
},
  "geometry": {"coordinates":[-0.16845334702696,51.49144091537938],"type":"Point"}
}