{
  "type": "Feature",
  "properties": {
    "date:inception_lower": "1980-01-01",
    "date:inception_upper": "1980-01-01",
    "iso:country": "GB",
    "wof:name": "LL22 8HF",
    "wof:placetype": "postalcode"
  },
  "geometry": {"coordinates":[-3.63922,53.289914],"type":"Point"}
}
