{
  "type": "Feature",
  "properties": {
    "iso:country": "GB",
    "wof:name": "LL22 8HF",
    "wof:placetype": "postalcode"
  },
  "geometry": {"coordinates":[-3.63922,53.289914],"type":"Point"}
}
