{
  "type": "Feature",
  "properties": {
    "iso:country": "GB",
    "wof:name": "M27 4JW",
    "wof:placetype": "postalcode"
  },
  "geometry": {"coordinates":[-2.312751,53.503429],"type":"Point"}
}
