{
  "type": "Feature",
  "properties": {
    "iso:country":"GB",
    "wof:name":"M27 4JW",
    "wof:placetype":"postalcode"
},
  "geometry": {"coordinates":[-2.31275062564996,53.50342875266175],"type":"Point"}
}