{
  "type": "Feature",
  "properties": {
    "date:inception_lower": "1980-01-01",
    "date:inception_upper": "1980-01-01",
    "iso:country": "GB",
    "wof:name": "CA2 5EG",
    "wof:placetype": "postalcode"
  },
  "geometry": {"coordinates":[-2.939564,54.887779],"type":"Point"}
}
