{
  "type": "Feature",
  "properties": {
    "iso:country":"GB",
    "wof:name":"CA2 5EG",
    "wof:placetype":"postalcode"
},
  "geometry": {"coordinates":[-2.93956366911531,54.88777935302376],"type":"Point"}
}