{
  "type": "Feature",
  "properties": {
    "iso:country":"GB",
    "wof:name":"BA20 1AD",
    "wof:placetype":"postalcode"
},
  "geometry": {"coordinates":[-2.63927059032218,50.94094216451838],"type":"Point"}
}