{
  "type": "Feature",
  "properties": {
    "date:inception_lower": "1980-01-01",
    "date:inception_upper": "1980-01-01",
    "iso:country": "GB",
    "wof:name": "BA20 1AD",
    "wof:placetype": "postalcode"
  },
  "geometry": {"coordinates":[-2.639271,50.940942],"type":"Point"}
}
