{
  "type": "Feature",
  "properties": {
    "date:inception_lower":"1985-04-01",
    "date:inception_upper":"1985-04-30",
    "iso:country":"GB",
    "wof:name":"NG25 0GA",
    "wof:placetype":"postalcode"
},
  "geometry": {"coordinates":[-0.948385,53.080015],"type":"Point"}
}