{
  "type": "Feature",
  "properties": {
    "iso:country": "GB",
    "wof:name": "NR32 5LP",
    "wof:placetype": "postalcode"
  },
  "geometry": {"coordinates":[1.691265,52.532332],"type":"Point"}
}
