{
  "type": "Feature",
  "properties": {
    "date:inception_lower": "1980-01-01",
    "date:inception_upper": "1980-01-01",
    "iso:country": "GB",
    "wof:name": "NR32 5LP",
    "wof:placetype": "postalcode"
  },
  "geometry": {"coordinates":[1.691265,52.532332],"type":"Point"}
}
