{
  "type": "Feature",
  "properties": {
    "date:inception_lower": "1980-01-01",
    "date:inception_upper": "1980-01-01",
    "iso:country": "GB",
    "wof:name": "G66 3PF",
    "wof:placetype": "postalcode"
  },
  "geometry": {"coordinates":[-4.12635,55.936292],"type":"Point"}
}
