{
  "type": "Feature",
  "properties": {
    "iso:country":"GB",
    "wof:name":"G66 3PF",
    "wof:placetype":"postalcode"
},
  "geometry": {"coordinates":[-4.12634964801302,55.93629171004019],"type":"Point"}
}