{
  "type": "Feature",
  "properties": {
    "iso:country": "GB",
    "wof:name": "G66 3PF",
    "wof:placetype": "postalcode"
  },
  "geometry": {"coordinates":[-4.12635,55.936292],"type":"Point"}
}
