{
  "type": "Feature",
  "properties": {
    "iso:country":"GB",
    "wof:name":"CR7 7JG",
    "wof:placetype":"postalcode"
},
  "geometry": {"coordinates":[-0.09945157250087,51.39823119700986],"type":"Point"}
}