{
  "type": "Feature",
  "properties": {
    "iso:country":"GB",
    "wof:name":"YO22 5JU",
    "wof:placetype":"postalcode"
},
  "geometry": {"coordinates":[-0.72499410035683,54.4024168685071],"type":"Point"}
}