{
  "type": "Feature",
  "properties": {
    "iso:country": "GB",
    "wof:name": "PE13 4AJ",
    "wof:placetype": "postalcode"
  },
  "geometry": {"coordinates":[0.06149,52.608454],"type":"Point"}
}
