{
  "type": "Feature",
  "properties": {
    "date:inception_lower": "2008-08-01",
    "date:inception_upper": "2008-08-01",
    "iso:country": "GB",
    "wof:name": "PE13 4AJ",
    "wof:placetype": "postalcode"
  },
  "geometry": {"coordinates":[0.06149,52.608454],"type":"Point"}
}
