{
  "type": "Feature",
  "properties": {
    "iso:country":"GB",
    "wof:name":"AB55 6TZ",
    "wof:placetype":"postalcode"
},
  "geometry": {"coordinates":[-2.94581324241035,57.5585954131526],"type":"Point"}
}