{
  "type": "Feature",
  "properties": {
    "date:inception_lower":"2008-12-01",
    "date:inception_upper":"2008-12-31",
    "iso:country":"GB",
    "wof:name":"AB55 6TZ",
    "wof:placetype":"postalcode"
},
  "geometry": {"coordinates":[-2.9459,57.558668],"type":"Point"}
}