{
  "type": "Feature",
  "properties": {
    "date:inception_lower": "2005-02-01",
    "date:inception_upper": "2005-02-01",
    "iso:country": "GB",
    "wof:name": "PE15 5TH",
    "wof:placetype": "postalcode"
  },
  "geometry": {"coordinates":[0.090174,52.557905],"type":"Point"}
}
