{
  "type": "Feature",
  "properties": {
    "iso:country":"GB",
    "wof:name":"BB4 9RL",
    "wof:placetype":"postalcode"
},
  "geometry": {"coordinates":[-2.2519455439675,53.71362829346886],"type":"Point"}
}