{
  "type": "Feature",
  "properties": {
    "iso:country": "GB",
    "wof:name": "WV4 6AH",
    "wof:placetype": "postalcode"
  },
  "geometry": {"coordinates":[-2.117301,52.566144],"type":"Point"}
}
