{
  "type": "Feature",
  "properties": {
    "iso:country": "GB",
    "wof:name": "ST7 8HS",
    "wof:placetype": "postalcode"
  },
  "geometry": {"coordinates":[-2.319164,53.05764],"type":"Point"}
}
