{
  "type": "Feature",
  "properties": {
    "date:inception_lower": "1980-01-01",
    "date:inception_upper": "1980-01-01",
    "iso:country": "GB",
    "wof:name": "ST7 8HS",
    "wof:placetype": "postalcode"
  },
  "geometry": {"coordinates":[-2.319164,53.05764],"type":"Point"}
}
