{
  "type": "Feature",
  "properties": {
    "iso:country": "GB",
    "wof:name": "ST1 6UX",
    "wof:placetype": "postalcode"
  },
  "geometry": {"coordinates":[-2.170968,53.037055],"type":"Point"}
}
