{
  "type": "Feature",
  "properties": {
    "date:inception_lower": "1980-01-01",
    "date:inception_upper": "1980-01-01",
    "iso:country": "GB",
    "wof:name": "BN2 1TA",
    "wof:placetype": "postalcode"
  },
  "geometry": {"coordinates":[-0.136058,50.820016],"type":"Point"}
}
