{
  "type": "Feature",
  "properties": {
    "iso:country": "GB",
    "wof:name": "BN2 1TA",
    "wof:placetype": "postalcode"
  },
  "geometry": {"coordinates":[-0.136058,50.820016],"type":"Point"}
}
