{
  "type": "Feature",
  "properties": {
    "iso:country":"GB",
    "wof:name":"NW1 7EB",
    "wof:placetype":"postalcode"
},
  "geometry": {"coordinates":[-0.1471894903835,51.53908184775606],"type":"Point"}
}