{
  "type": "Feature",
  "properties": {
    "iso:country": "GB",
    "wof:name": "NW1 7EB",
    "wof:placetype": "postalcode"
  },
  "geometry": {"coordinates":[-0.147205,51.53913],"type":"Point"}
}
