{
  "type": "Feature",
  "properties": {
    "date:inception_lower": "1980-01-01",
    "date:inception_upper": "1980-01-01",
    "iso:country": "GB",
    "wof:name": "NW1 7EB",
    "wof:placetype": "postalcode"
  },
  "geometry": {"coordinates":[-0.147205,51.53913],"type":"Point"}
}
