{
  "type": "Feature",
  "properties": {
    "iso:country":"GB",
    "wof:name":"AB10 7FG",
    "wof:placetype":"postalcode"
},
  "geometry": {"coordinates":[-2.11344911881503,57.12994608300897],"type":"Point"}
}