{
  "type": "Feature",
  "properties": {
    "date:inception_lower": "1980-01-01",
    "date:inception_upper": "1980-01-01",
    "iso:country": "GB",
    "wof:name": "DN22 6TU",
    "wof:placetype": "postalcode"
  },
  "geometry": {"coordinates":[-0.924952,53.329331],"type":"Point"}
}
