{
  "type": "Feature",
  "properties": {
    "iso:country":"GB",
    "wof:name":"DN22 6TU",
    "wof:placetype":"postalcode"
},
  "geometry": {"coordinates":[-0.92495178564077,53.32933053330971],"type":"Point"}
}