{
  "type": "Feature",
  "properties": {
    "iso:country":"GB",
    "wof:name":"SL4 2RY",
    "wof:placetype":"postalcode"
},
  "geometry": {"coordinates":[-0.58067305375334,51.45714804267672],"type":"Point"}
}