{
  "type": "Feature",
  "properties": {
    "iso:country":"GB",
    "wof:name":"L20 5DE",
    "wof:placetype":"postalcode"
},
  "geometry": {"coordinates":[-2.99541432872059,53.45872978555932],"type":"Point"}
}