{
  "type": "Feature",
  "properties": {
    "iso:country":"GB",
    "wof:name":"IP5 1BL",
    "wof:placetype":"postalcode"
},
  "geometry": {"coordinates":[1.23212710879265,52.06591611160716],"type":"Point"}
}