{
  "type": "Feature",
  "properties": {
    "iso:country":"GB",
    "wof:name":"W5 4DH",
    "wof:placetype":"postalcode"
},
  "geometry": {"coordinates":[-0.31326440314528,51.49345126051302],"type":"Point"}
}