{
  "type": "Feature",
  "properties": {
    "iso:country":"GB",
    "wof:name":"CW2 6LJ",
    "wof:placetype":"postalcode"
},
  "geometry": {"coordinates":[-2.43952574524041,53.08103257802697],"type":"Point"}
}