{
  "type": "Feature",
  "properties": {
    "iso:country":"GB",
    "wof:name":"NR25 7DT",
    "wof:placetype":"postalcode"
},
  "geometry": {"coordinates":[1.10221600215575,52.91502727511646],"type":"Point"}
}