{
  "type": "Feature",
  "properties": {
    "iso:country":"GB",
    "wof:name":"NR33 9EE",
    "wof:placetype":"postalcode"
},
  "geometry": {"coordinates":[1.72033520235886,52.4623939849717],"type":"Point"}
}