{
  "type": "Feature",
  "properties": {
    "iso:country":"GB",
    "wof:name":"WD19 7DQ",
    "wof:placetype":"postalcode"
},
  "geometry": {"coordinates":[-0.39752865415264,51.62869704500052],"type":"Point"}
}