{
  "type": "Feature",
  "properties": {
    "iso:country": "GB",
    "wof:name": "WD19 7DQ",
    "wof:placetype": "postalcode"
  },
  "geometry": {"coordinates":[-0.397529,51.628697],"type":"Point"}
}
