{
  "type": "Feature",
  "properties": {
    "iso:country":"GB",
    "wof:name":"BR3 3LR",
    "wof:placetype":"postalcode"
},
  "geometry": {"coordinates":[-0.02435944887507,51.39971397063724],"type":"Point"}
}