{
  "type": "Feature",
  "properties": {
    "date:inception_lower":"1980-01-01",
    "date:inception_upper":"1980-01-31",
    "iso:country":"GB",
    "wof:name":"PO16 8DB",
    "wof:placetype":"postalcode"
},
  "geometry": {"coordinates":[-1.127867,50.851554],"type":"Point"}
}