{
  "type": "Feature",
  "properties": {
    "iso:country": "GB",
    "wof:name": "PO16 8DB",
    "wof:placetype": "postalcode"
  },
  "geometry": {"coordinates":[-1.127867,50.851554],"type":"Point"}
}
