{
  "type": "Feature",
  "properties": {
    "iso:country":"GB",
    "wof:name":"BB11 3EN",
    "wof:placetype":"postalcode"
},
  "geometry": {"coordinates":[-2.22202102419512,53.78249107143409],"type":"Point"}
}