{
  "type": "Feature",
  "properties": {
    "iso:country": "GB",
    "wof:name": "WF8 1QU",
    "wof:placetype": "postalcode"
  },
  "geometry": {"coordinates":[-1.305155,53.69278],"type":"Point"}
}
