{
  "type": "Feature",
  "properties": {
    "iso:country":"GB",
    "wof:name":"WF8 1QU",
    "wof:placetype":"postalcode"
},
  "geometry": {"coordinates":[-1.30515526448717,53.69278036279449],"type":"Point"}
}