{
  "type": "Feature",
  "properties": {
    "iso:country":"GB",
    "wof:name":"PO20 7NP",
    "wof:placetype":"postalcode"
},
  "geometry": {"coordinates":[-0.80483660227167,50.77704686090664],"type":"Point"}
}