{
  "type": "Feature",
  "properties": {
    "iso:country":"GB",
    "wof:name":"WV3 0SP",
    "wof:placetype":"postalcode"
},
  "geometry": {"coordinates":[-2.13297583376849,52.58297424445946],"type":"Point"}
}