{
  "type": "Feature",
  "properties": {
    "iso:country": "GB",
    "wof:name": "S43 4EX",
    "wof:placetype": "postalcode"
  },
  "geometry": {"coordinates":[-1.290552,53.291002],"type":"Point"}
}
