{
  "type": "Feature",
  "properties": {
    "date:inception_lower":"1980-01-01",
    "date:inception_upper":"1980-01-31",
    "iso:country":"GB",
    "wof:name":"CV11 5NR",
    "wof:placetype":"postalcode"
},
  "geometry": {"coordinates":[-1.469737,52.519374],"type":"Point"}
}