{
  "type": "Feature",
  "properties": {
    "iso:country":"GB",
    "wof:name":"CV11 5NR",
    "wof:placetype":"postalcode"
},
  "geometry": {"coordinates":[-1.46973738529277,52.51937413010898],"type":"Point"}
}