{
  "type": "Feature",
  "properties": {
    "date:inception_lower":"1993-08-01",
    "date:inception_upper":"1993-08-31",
    "iso:country":"GB",
    "wof:name":"SY22 6BB",
    "wof:placetype":"postalcode"
},
  "geometry": {"coordinates":[-3.147803,52.77675],"type":"Point"}
}