{
  "type": "Feature",
  "properties": {
    "iso:country": "GB",
    "wof:name": "SY22 6BB",
    "wof:placetype": "postalcode"
  },
  "geometry": {"coordinates":[-3.147803,52.77675],"type":"Point"}
}
