{
  "type": "Feature",
  "properties": {
    "iso:country":"GB",
    "wof:name":"WR5 3QL",
    "wof:placetype":"postalcode"
},
  "geometry": {"coordinates":[-2.1594954667884,52.14281984906363],"type":"Point"}
}