{
  "type": "Feature",
  "properties": {
    "date:inception_lower": "1980-01-01",
    "date:inception_upper": "1980-01-01",
    "iso:country": "GB",
    "wof:name": "WR5 3QL",
    "wof:placetype": "postalcode"
  },
  "geometry": {"coordinates":[-2.159495,52.14282],"type":"Point"}
}
