{
  "type": "Feature",
  "properties": {
    "iso:country": "GB",
    "wof:name": "NG17 8RY",
    "wof:placetype": "postalcode"
  },
  "geometry": {"coordinates":[-1.25204,53.091551],"type":"Point"}
}
