{
  "type": "Feature",
  "properties": {
    "date:inception_lower": "1983-08-01",
    "date:inception_upper": "1983-08-01",
    "iso:country": "GB",
    "wof:name": "G77 5TZ",
    "wof:placetype": "postalcode"
  },
  "geometry": {"coordinates":[-4.312017,55.775411],"type":"Point"}
}
