{
  "type": "Feature",
  "properties": {
    "iso:country":"GB",
    "wof:name":"G77 5TZ",
    "wof:placetype":"postalcode"
},
  "geometry": {"coordinates":[-4.31201675268416,55.77541111365728],"type":"Point"}
}