{
  "type": "Feature",
  "properties": {
    "iso:country":"GB",
    "wof:name":"PA34 4PH",
    "wof:placetype":"postalcode"
},
  "geometry": {"coordinates":[-5.47087917332665,56.40693349511677],"type":"Point"}
}