{
  "type": "Feature",
  "properties": {
    "iso:country":"GB",
    "wof:name":"SN11 0HB",
    "wof:placetype":"postalcode"
},
  "geometry": {"coordinates":[-2.00944565404784,51.43478601118534],"type":"Point"}
}