{
  "type": "Feature",
  "properties": {
    "iso:country":"GB",
    "wof:name":"B94 6AJ",
    "wof:placetype":"postalcode"
},
  "geometry": {"coordinates":[-1.83136019983305,52.36551590809653],"type":"Point"}
}