{
  "type": "Feature",
  "properties": {
    "iso:country": "GB",
    "wof:name": "B94 6AJ",
    "wof:placetype": "postalcode"
  },
  "geometry": {"coordinates":[-1.83136,52.365516],"type":"Point"}
}
