{
  "type": "Feature",
  "properties": {
    "date:inception_lower":"1991-09-01",
    "date:inception_upper":"1991-09-30",
    "iso:country":"GB",
    "wof:name":"B94 6AJ",
    "wof:placetype":"postalcode"
},
  "geometry": {"coordinates":[-1.83136,52.365516],"type":"Point"}
}