{
  "type": "Feature",
  "properties": {
    "iso:country":"GB",
    "wof:name":"CW7 2ET",
    "wof:placetype":"postalcode"
},
  "geometry": {"coordinates":[-2.54450659061786,53.19357297105293],"type":"Point"}
}