{
  "type": "Feature",
  "properties": {
    "iso:country":"GB",
    "wof:name":"S42 6UY",
    "wof:placetype":"postalcode"
},
  "geometry": {"coordinates":[-1.4326597724852,53.19830497113612],"type":"Point"}
}