{
  "type": "Feature",
  "properties": {
    "iso:country":"GB",
    "wof:name":"TA7 9LR",
    "wof:placetype":"postalcode"
},
  "geometry": {"coordinates":[-2.83176144210433,51.13867665693561],"type":"Point"}
}