{
  "type": "Feature",
  "properties": {
    "date:inception_lower": "1990-07-01",
    "date:inception_upper": "1990-07-01",
    "iso:country": "GB",
    "wof:name": "TA7 9LR",
    "wof:placetype": "postalcode"
  },
  "geometry": {"coordinates":[-2.831761,51.138677],"type":"Point"}
}
