{
  "type": "Feature",
  "properties": {
    "date:inception_lower": "2016-08-01",
    "date:inception_upper": "2016-08-01",
    "iso:country": "GB",
    "wof:name": "CA16 6FL",
    "wof:placetype": "postalcode"
  },
  "geometry": {"coordinates":[-2.481568,54.575754],"type":"Point"}
}
