{
  "type": "Feature",
  "properties": {
    "date:inception_lower": "1980-01-01",
    "date:inception_upper": "1980-01-01",
    "iso:country": "GB",
    "wof:name": "SE27 9QX",
    "wof:placetype": "postalcode"
  },
  "geometry": {"coordinates":[-0.090064,51.427215],"type":"Point"}
}
