{
  "type": "Feature",
  "properties": {
    "iso:country":"GB",
    "wof:name":"LS25 1LH",
    "wof:placetype":"postalcode"
},
  "geometry": {"coordinates":[-1.40463499105594,53.78524706815772],"type":"Point"}
}