{
  "type": "Feature",
  "properties": {
    "iso:country":"GB",
    "wof:name":"S64 0BB",
    "wof:placetype":"postalcode"
},
  "geometry": {"coordinates":[-1.28446741604506,53.50050320073461],"type":"Point"}
}