{
  "type": "Feature",
  "properties": {
    "iso:country":"GB",
    "wof:name":"CH48 9UN",
    "wof:placetype":"postalcode"
},
  "geometry": {"coordinates":[-3.15787222043933,53.37204910707392],"type":"Point"}
}