{
  "type": "Feature",
  "properties": {
    "iso:country": "GB",
    "wof:name": "CH48 9UN",
    "wof:placetype": "postalcode"
  },
  "geometry": {"coordinates":[-3.157872,53.372049],"type":"Point"}
}
