{
  "type": "Feature",
  "properties": {
    "iso:country":"GB",
    "wof:name":"UB4 0DU",
    "wof:placetype":"postalcode"
},
  "geometry": {"coordinates":[-0.40391807276555,51.5218945306671],"type":"Point"}
}