{
  "type": "Feature",
  "properties": {
    "iso:country": "GB",
    "wof:name": "NR20 5QJ",
    "wof:placetype": "postalcode"
  },
  "geometry": {"coordinates":[1.055937,52.802602],"type":"Point"}
}
