{
  "type": "Feature",
  "properties": {
    "iso:country":"GB",
    "wof:name":"NR20 5QJ",
    "wof:placetype":"postalcode"
},
  "geometry": {"coordinates":[1.05500532483518,52.80248318851202],"type":"Point"}
}