{
  "type": "Feature",
  "properties": {
    "date:inception_lower": "1980-01-01",
    "date:inception_upper": "1980-01-01",
    "iso:country": "GB",
    "wof:name": "NR20 5QJ",
    "wof:placetype": "postalcode"
  },
  "geometry": {"coordinates":[1.055936,52.802575],"type":"Point"}
}
