{
  "type": "Feature",
  "properties": {
    "date:inception_lower": "1980-01-01",
    "date:inception_upper": "1980-01-01",
    "iso:country": "GB",
    "wof:name": "PO13 0ET",
    "wof:placetype": "postalcode"
  },
  "geometry": {"coordinates":[-1.173497,50.817812],"type":"Point"}
}
