{
  "type": "Feature",
  "properties": {
    "iso:country":"GB",
    "wof:name":"PO13 0ET",
    "wof:placetype":"postalcode"
},
  "geometry": {"coordinates":[-1.17350910281735,50.81782173318352],"type":"Point"}
}