{
  "type": "Feature",
  "properties": {
    "iso:country": "GB",
    "wof:name": "BS30 8YR",
    "wof:placetype": "postalcode"
  },
  "geometry": {"coordinates":[-2.469535,51.446649],"type":"Point"}
}
