{
  "type": "Feature",
  "properties": {
    "iso:country":"GB",
    "wof:name":"BS30 8YR",
    "wof:placetype":"postalcode"
},
  "geometry": {"coordinates":[-2.46950569116964,51.44662231431768],"type":"Point"}
}