{
  "type": "Feature",
  "properties": {
    "date:inception_lower": "1997-12-01",
    "date:inception_upper": "1997-12-01",
    "iso:country": "GB",
    "wof:name": "BS30 8YR",
    "wof:placetype": "postalcode"
  },
  "geometry": {"coordinates":[-2.469535,51.446649],"type":"Point"}
}
