{
  "type": "Feature",
  "properties": {
    "iso:country":"GB",
    "wof:name":"B15 2PH",
    "wof:placetype":"postalcode"
},
  "geometry": {"coordinates":[-1.94285693602235,52.45655665873758],"type":"Point"}
}