{
  "type": "Feature",
  "properties": {
    "date:inception_lower": "1980-01-01",
    "date:inception_upper": "1980-01-01",
    "iso:country": "GB",
    "wof:name": "SG13 8PX",
    "wof:placetype": "postalcode"
  },
  "geometry": {"coordinates":[-0.10624,51.757226],"type":"Point"}
}
