{
  "type": "Feature",
  "properties": {
    "iso:country":"GB",
    "wof:name":"HA4 6PU",
    "wof:placetype":"postalcode"
},
  "geometry": {"coordinates":[-0.41370335698515,51.56010912714862],"type":"Point"}
}