{
  "type": "Feature",
  "properties": {
    "iso:country":"GB",
    "wof:name":"YO21 2AP",
    "wof:placetype":"postalcode"
},
  "geometry": {"coordinates":[-0.87424328244578,54.43772934416933],"type":"Point"}
}