{
  "type": "Feature",
  "properties": {
    "date:inception_lower": "1980-01-01",
    "date:inception_upper": "1980-01-01",
    "iso:country": "GB",
    "wof:name": "YO21 2AP",
    "wof:placetype": "postalcode"
  },
  "geometry": {"coordinates":[-0.875687,54.437379],"type":"Point"}
}
