{
  "type": "Feature",
  "properties": {
    "date:inception_lower": "2020-04-01",
    "date:inception_upper": "2020-04-01",
    "iso:country": "GB",
    "wof:name": "DN16 1ED",
    "wof:placetype": "postalcode"
  },
  "geometry": {"coordinates":[-0.644783,53.58217],"type":"Point"}
}
