{
  "type": "Feature",
  "properties": {
    "iso:country":"GB",
    "wof:name":"GU46 6JA",
    "wof:placetype":"postalcode"
},
  "geometry": {"coordinates":[-0.82828851081859,51.33655789460062],"type":"Point"}
}