{
  "type": "Feature",
  "properties": {
    "iso:country":"GB",
    "wof:name":"RG26 5JZ",
    "wof:placetype":"postalcode"
},
  "geometry": {"coordinates":[-1.16272931226395,51.33160216295319],"type":"Point"}
}