{
  "type": "Feature",
  "properties": {
    "iso:country": "GB",
    "wof:name": "RG26 5JZ",
    "wof:placetype": "postalcode"
  },
  "geometry": {"coordinates":[-1.162729,51.331602],"type":"Point"}
}
