{
  "type": "Feature",
  "properties": {
    "date:inception_lower": "2017-01-01",
    "date:inception_upper": "2017-01-01",
    "iso:country": "GB",
    "wof:name": "LE7 7HZ",
    "wof:placetype": "postalcode"
  },
  "geometry": {"coordinates":[-1.191328,52.660364],"type":"Point"}
}
