{
  "type": "Feature",
  "properties": {
    "iso:country":"GB",
    "wof:name":"YO7 1FE",
    "wof:placetype":"postalcode"
},
  "geometry": {"coordinates":[-1.34341310369475,54.23879427827889],"type":"Point"}
}