{
  "type": "Feature",
  "properties": {
    "date:inception_lower": "1983-07-01",
    "date:inception_upper": "1983-07-01",
    "iso:country": "GB",
    "wof:name": "YO7 1FE",
    "wof:placetype": "postalcode"
  },
  "geometry": {"coordinates":[-1.343413,54.238794],"type":"Point"}
}
