{
  "type": "Feature",
  "properties": {
    "iso:country":"GB",
    "wof:name":"E17 6RA",
    "wof:placetype":"postalcode"
},
  "geometry": {"coordinates":[-0.02822732560467,51.58865206532704],"type":"Point"}
}