{
  "type": "Feature",
  "properties": {
    "iso:country":"GB",
    "wof:name":"SS9 4RG",
    "wof:placetype":"postalcode"
},
  "geometry": {"coordinates":[0.6376960801335,51.5616490494554],"type":"Point"}
}