{
  "type": "Feature",
  "properties": {
    "date:inception_lower":"1980-01-01",
    "date:inception_upper":"1980-01-31",
    "iso:country":"GB",
    "wof:name":"LN11 9AJ",
    "wof:placetype":"postalcode"
},
  "geometry": {"coordinates":[0.00409,53.368494],"type":"Point"}
}