{
  "type": "Feature",
  "properties": {
    "iso:country":"GB",
    "wof:name":"LN11 9AJ",
    "wof:placetype":"postalcode"
},
  "geometry": {"coordinates":[0.00332779823524,53.36822137318551],"type":"Point"}
}