{
  "type": "Feature",
  "properties": {
    "iso:country":"GB",
    "wof:name":"PL7 2GP",
    "wof:placetype":"postalcode"
},
  "geometry": {"coordinates":[-4.02285007353926,50.3900217306217],"type":"Point"}
}