{
  "type": "Feature",
  "properties": {
    "date:inception_lower": "2022-05-01",
    "date:inception_upper": "2022-05-01",
    "iso:country": "GB",
    "wof:name": "NG24 5BG",
    "wof:placetype": "postalcode"
  },
  "geometry": {"coordinates":[-0.769799,53.050825],"type":"Point"}
}
