{
  "type": "Feature",
  "properties": {
    "date:inception_lower": "2022-05-01",
    "date:inception_upper": "2022-05-01",
    "iso:country": "GB",
    "wof:name": "NG24 5BG",
    "wof:placetype": "postalcode"
  },
  "geometry": {"coordinates":[-0.770146,53.050684],"type":"Point"}
}
