{
  "type": "Feature",
  "properties": {
    "iso:country":"GB",
    "wof:name":"LE18 4NY",
    "wof:placetype":"postalcode"
},
  "geometry": {"coordinates":[-1.12209315140686,52.57482562114694],"type":"Point"}
}