{
  "type": "Feature",
  "properties": {
    "iso:country":"GB",
    "wof:name":"SA42 0UP",
    "wof:placetype":"postalcode"
},
  "geometry": {"coordinates":[-4.89618546587772,52.01292183837688],"type":"Point"}
}