{
  "type": "Feature",
  "properties": {
    "iso:country": "GB",
    "wof:name": "LS7 3AH",
    "wof:placetype": "postalcode"
  },
  "geometry": {"coordinates":[-1.537923,53.8133],"type":"Point"}
}
