{
  "type": "Feature",
  "properties": {
    "iso:country":"GB",
    "wof:name":"CO10 9DJ",
    "wof:placetype":"postalcode"
},
  "geometry": {"coordinates":[0.72112794821878,52.08719418486804],"type":"Point"}
}