{
  "type": "Feature",
  "properties": {
    "iso:country":"GB",
    "wof:name":"TA6 4PW",
    "wof:placetype":"postalcode"
},
  "geometry": {"coordinates":[-2.99173642652732,51.13394913468404],"type":"Point"}
}