{
  "type": "Feature",
  "properties": {
    "date:inception_lower": "1998-06-01",
    "date:inception_upper": "1998-06-01",
    "iso:country": "GB",
    "wof:name": "OL9 6BW",
    "wof:placetype": "postalcode"
  },
  "geometry": {"coordinates":[-2.125944,53.545559],"type":"Point"}
}
