{
  "type": "Feature",
  "properties": {
    "date:inception_lower": "1983-07-01",
    "date:inception_upper": "1983-07-01",
    "iso:country": "GB",
    "wof:name": "EX2 7DJ",
    "wof:placetype": "postalcode"
  },
  "geometry": {"coordinates":[-3.482264,50.692194],"type":"Point"}
}
