{
  "type": "Feature",
  "properties": {
    "iso:country":"GB",
    "wof:name":"EX2 7DJ",
    "wof:placetype":"postalcode"
},
  "geometry": {"coordinates":[-3.48226417774963,50.69219443523978],"type":"Point"}
}