{
  "type": "Feature",
  "properties": {
    "iso:country":"GB",
    "wof:name":"MK3 6HT",
    "wof:placetype":"postalcode"
},
  "geometry": {"coordinates":[-0.74401689136973,51.99772583504203],"type":"Point"}
}