{
  "type": "Feature",
  "properties": {
    "iso:country": "GB",
    "wof:name": "CF31 4PX",
    "wof:placetype": "postalcode"
  },
  "geometry": {"coordinates":[-3.591232,51.514139],"type":"Point"}
}
