{
  "type": "Feature",
  "properties": {
    "iso:country":"GB",
    "wof:name":"LE2 5WW",
    "wof:placetype":"postalcode"
},
  "geometry": {"coordinates":[-1.08006959278943,52.58669728230669],"type":"Point"}
}