{
  "type": "Feature",
  "properties": {
    "iso:country":"GB",
    "wof:name":"SY13 4HS",
    "wof:placetype":"postalcode"
},
  "geometry": {"coordinates":[-2.65357066703393,53.01495795450181],"type":"Point"}
}