{
  "type": "Feature",
  "properties": {
    "iso:country": "GB",
    "wof:name": "SY13 4HS",
    "wof:placetype": "postalcode"
  },
  "geometry": {"coordinates":[-2.653571,53.014958],"type":"Point"}
}
