{
  "type": "Feature",
  "properties": {
    "iso:country":"GB",
    "wof:name":"LU1 1RT",
    "wof:placetype":"postalcode"
},
  "geometry": {"coordinates":[-0.42071072652736,51.88184439903873],"type":"Point"}
}