{
  "type": "Feature",
  "properties": {
    "date:inception_lower": "2022-08-01",
    "date:inception_upper": "2022-08-01",
    "iso:country": "GB",
    "wof:name": "HR2 8FL",
    "wof:placetype": "postalcode"
  },
  "geometry": {"coordinates":[-2.759505,51.976425],"type":"Point"}
}
