{
  "type": "Feature",
  "properties": {
    "date:inception_lower": "1980-01-01",
    "date:inception_upper": "1980-01-01",
    "iso:country": "GB",
    "wof:name": "CM5 0BA",
    "wof:placetype": "postalcode"
  },
  "geometry": {"coordinates":[0.243877,51.712358],"type":"Point"}
}
