{
  "type": "Feature",
  "properties": {
    "iso:country":"GB",
    "wof:name":"CM5 0BA",
    "wof:placetype":"postalcode"
},
  "geometry": {"coordinates":[0.24312596780461,51.71263676364103],"type":"Point"}
}