{
  "type": "Feature",
  "properties": {
    "iso:country":"GB",
    "wof:name":"EX17 2HB",
    "wof:placetype":"postalcode"
},
  "geometry": {"coordinates":[-3.67012167804397,50.79507395898845],"type":"Point"}
}