{
  "type": "Feature",
  "properties": {
    "date:inception_lower": "1997-12-01",
    "date:inception_upper": "1997-12-01",
    "iso:country": "GB",
    "wof:name": "SE13 7HF",
    "wof:placetype": "postalcode"
  },
  "geometry": {"coordinates":[-0.012684,51.462412],"type":"Point"}
}
