{
  "type": "Feature",
  "properties": {
    "iso:country":"GB",
    "wof:name":"SM7 3NE",
    "wof:placetype":"postalcode"
},
  "geometry": {"coordinates":[-0.17551402780284,51.3234070872394],"type":"Point"}
}