{
  "type": "Feature",
  "properties": {
    "iso:country": "GB",
    "wof:name": "SM7 3NE",
    "wof:placetype": "postalcode"
  },
  "geometry": {"coordinates":[-0.175416,51.323422],"type":"Point"}
}
