{
  "type": "Feature",
  "properties": {
    "iso:country": "GB",
    "wof:name": "NW7 3AZ",
    "wof:placetype": "postalcode"
  },
  "geometry": {"coordinates":[-0.258852,51.615683],"type":"Point"}
}
