{
  "type": "Feature",
  "properties": {
    "iso:country":"GB",
    "wof:name":"NG20 8AR",
    "wof:placetype":"postalcode"
},
  "geometry": {"coordinates":[-1.21686736084396,53.19716348577021],"type":"Point"}
}