{
  "type": "Feature",
  "properties": {
    "date:inception_lower": "2008-12-01",
    "date:inception_upper": "2008-12-01",
    "iso:country": "GB",
    "wof:name": "NG20 8AR",
    "wof:placetype": "postalcode"
  },
  "geometry": {"coordinates":[-1.216971,53.197156],"type":"Point"}
}
