{
  "type": "Feature",
  "properties": {
    "iso:country": "GB",
    "wof:name": "NE49 9HJ",
    "wof:placetype": "postalcode"
  },
  "geometry": {"coordinates":[-2.464696,54.971812],"type":"Point"}
}
