{
  "type": "Feature",
  "properties": {
    "iso:country":"GB",
    "wof:name":"M30 0FU",
    "wof:placetype":"postalcode"
},
  "geometry": {"coordinates":[-2.34635306614774,53.48274347629116],"type":"Point"}
}