{
  "type": "Feature",
  "properties": {
    "iso:country": "GB",
    "wof:name": "M30 0FU",
    "wof:placetype": "postalcode"
  },
  "geometry": {"coordinates":[-2.346353,53.482743],"type":"Point"}
}
