{
  "type": "Feature",
  "properties": {
    "iso:country":"GB",
    "wof:name":"GL6 6PJ",
    "wof:placetype":"postalcode"
},
  "geometry": {"coordinates":[-2.23081716256827,51.77999600615183],"type":"Point"}
}