{
  "type": "Feature",
  "properties": {
    "iso:country":"GB",
    "wof:name":"BN2 5TJ",
    "wof:placetype":"postalcode"
},
  "geometry": {"coordinates":[-0.10626883251849,50.81516559464329],"type":"Point"}
}