{
  "type": "Feature",
  "properties": {
    "iso:country": "GB",
    "wof:name": "BN2 5TJ",
    "wof:placetype": "postalcode"
  },
  "geometry": {"coordinates":[-0.106241,50.81516],"type":"Point"}
}
