{
  "type": "Feature",
  "properties": {
    "iso:country": "GB",
    "wof:name": "BN2 5TJ",
    "wof:placetype": "postalcode"
  },
  "geometry": {"coordinates":[-0.105809,50.8167],"type":"Point"}
}
