{
  "type": "Feature",
  "properties": {
    "iso:country":"GB",
    "wof:name":"SY23 3TP",
    "wof:placetype":"postalcode"
},
  "geometry": {"coordinates":[-4.05113101803984,52.41815085740169],"type":"Point"}
}