{
  "type": "Feature",
  "properties": {
    "date:inception_lower": "1995-12-01",
    "date:inception_upper": "1995-12-01",
    "iso:country": "GB",
    "wof:name": "SY23 3TP",
    "wof:placetype": "postalcode"
  },
  "geometry": {"coordinates":[-4.050898,52.417991],"type":"Point"}
}
