{
  "type": "Feature",
  "properties": {
    "iso:country":"GB",
    "wof:name":"BA12 8JJ",
    "wof:placetype":"postalcode"
},
  "geometry": {"coordinates":[-2.19292745328696,51.20424051904662],"type":"Point"}
}