{
  "type": "Feature",
  "properties": {
    "date:inception_lower":"1980-01-01",
    "date:inception_upper":"1980-01-31",
    "iso:country":"GB",
    "wof:name":"BA12 8JJ",
    "wof:placetype":"postalcode"
},
  "geometry": {"coordinates":[-2.192927,51.204241],"type":"Point"}
}