{
  "type": "Feature",
  "properties": {
    "date:inception_lower":"1980-01-01",
    "date:inception_upper":"1980-01-31",
    "iso:country":"GB",
    "wof:name":"B49 6BU",
    "wof:placetype":"postalcode"
},
  "geometry": {"coordinates":[-1.85419,52.235399],"type":"Point"}
}