{
  "type": "Feature",
  "properties": {
    "date:inception_lower": "1980-01-01",
    "date:inception_upper": "1980-01-01",
    "iso:country": "GB",
    "wof:name": "B49 6BU",
    "wof:placetype": "postalcode"
  },
  "geometry": {"coordinates":[-1.854249,52.235417],"type":"Point"}
}
