{
  "type": "Feature",
  "properties": {
    "iso:country": "GB",
    "wof:name": "RG12 7WG",
    "wof:placetype": "postalcode"
  },
  "geometry": {"coordinates":[-0.74497,51.393802],"type":"Point"}
}
