{
  "type": "Feature",
  "properties": {
    "date:inception_lower": "1980-01-01",
    "date:inception_upper": "1980-01-01",
    "iso:country": "GB",
    "wof:name": "RG4 9PY",
    "wof:placetype": "postalcode"
  },
  "geometry": {"coordinates":[-0.944528,51.487956],"type":"Point"}
}
