{
  "type": "Feature",
  "properties": {
    "iso:country":"GB",
    "wof:name":"RG4 9PY",
    "wof:placetype":"postalcode"
},
  "geometry": {"coordinates":[-0.94454767312256,51.48795412636221],"type":"Point"}
}