{
  "type": "Feature",
  "properties": {
    "iso:country":"GB",
    "wof:name":"DL14 0HW",
    "wof:placetype":"postalcode"
},
  "geometry": {"coordinates":[-1.74465909307163,54.6501098903849],"type":"Point"}
}