{
  "type": "Feature",
  "properties": {
    "iso:country":"GB",
    "wof:name":"SE7 7NU",
    "wof:placetype":"postalcode"
},
  "geometry": {"coordinates":[0.02944868343918,51.48338070623779],"type":"Point"}
}