{
  "type": "Feature",
  "properties": {
    "iso:country":"GB",
    "wof:name":"DY14 8RR",
    "wof:placetype":"postalcode"
},
  "geometry": {"coordinates":[-2.49611123737153,52.42724599586396],"type":"Point"}
}