{
  "type": "Feature",
  "properties": {
    "iso:country":"GB",
    "wof:name":"WN7 2RS",
    "wof:placetype":"postalcode"
},
  "geometry": {"coordinates":[-2.50610019378269,53.49660900160481],"type":"Point"}
}