{
  "type": "Feature",
  "properties": {
    "iso:country": "GB",
    "wof:name": "SA61 1QE",
    "wof:placetype": "postalcode"
  },
  "geometry": {"coordinates":[-4.971282,51.798767],"type":"Point"}
}
