{
  "type": "Feature",
  "properties": {
    "iso:country":"GB",
    "wof:name":"SA61 1QE",
    "wof:placetype":"postalcode"
},
  "geometry": {"coordinates":[-4.97124897197123,51.79875397772386],"type":"Point"}
}