{
  "type": "Feature",
  "properties": {
    "date:inception_lower": "1997-12-01",
    "date:inception_upper": "1997-12-01",
    "iso:country": "GB",
    "wof:name": "L20 4XY",
    "wof:placetype": "postalcode"
  },
  "geometry": {"coordinates":[-2.998841,53.457155],"type":"Point"}
}
