{
  "type": "Feature",
  "properties": {
    "date:inception_lower": "1980-01-01",
    "date:inception_upper": "1980-01-01",
    "iso:country": "GB",
    "wof:name": "DY9 8TH",
    "wof:placetype": "postalcode"
  },
  "geometry": {"coordinates":[-2.108052,52.455133],"type":"Point"}
}
