{
  "type": "Feature",
  "properties": {
    "iso:country": "GB",
    "wof:name": "DY9 8TH",
    "wof:placetype": "postalcode"
  },
  "geometry": {"coordinates":[-2.107979,52.45516],"type":"Point"}
}
