{
  "type": "Feature",
  "properties": {
    "iso:country":"GB",
    "wof:name":"NG11 9HD",
    "wof:placetype":"postalcode"
},
  "geometry": {"coordinates":[-1.18705213653742,52.8988233639548],"type":"Point"}
}