{
  "type": "Feature",
  "properties": {
    "iso:country": "GB",
    "wof:name": "NG11 9HD",
    "wof:placetype": "postalcode"
  },
  "geometry": {"coordinates":[-1.187052,52.898823],"type":"Point"}
}
