{
  "type": "Feature",
  "properties": {
    "iso:country":"GB",
    "wof:name":"ME5 8EY",
    "wof:placetype":"postalcode"
},
  "geometry": {"coordinates":[0.53573200308233,51.34516689252315],"type":"Point"}
}