{
  "type": "Feature",
  "properties": {
    "iso:country": "GB",
    "wof:name": "ME5 8EY",
    "wof:placetype": "postalcode"
  },
  "geometry": {"coordinates":[0.535732,51.345167],"type":"Point"}
}
