{
  "type": "Feature",
  "properties": {
    "iso:country": "GB",
    "wof:name": "DT11 0HN",
    "wof:placetype": "postalcode"
  },
  "geometry": {"coordinates":[-2.234079,50.799676],"type":"Point"}
}
