{
  "type": "Feature",
  "properties": {
    "iso:country":"GB",
    "wof:name":"TR18 5AX",
    "wof:placetype":"postalcode"
},
  "geometry": {"coordinates":[-5.55187822109956,50.10376361937534],"type":"Point"}
}