{
  "type": "Feature",
  "properties": {
    "iso:country":"GB",
    "wof:name":"WA14 4HG",
    "wof:placetype":"postalcode"
},
  "geometry": {"coordinates":[-2.35471406019989,53.39576372895039],"type":"Point"}
}