{
  "type": "Feature",
  "properties": {
    "date:inception_lower": "2017-10-01",
    "date:inception_upper": "2017-10-01",
    "iso:country": "GB",
    "wof:name": "BS16 7LJ",
    "wof:placetype": "postalcode"
  },
  "geometry": {"coordinates":[-2.465418,51.494589],"type":"Point"}
}
