{
  "type": "Feature",
  "properties": {
    "iso:country":"GB",
    "wof:name":"OL15 8HR",
    "wof:placetype":"postalcode"
},
  "geometry": {"coordinates":[-2.11728441403296,53.63371571414151],"type":"Point"}
}