{
  "type": "Feature",
  "properties": {
    "date:inception_lower": "2006-07-01",
    "date:inception_upper": "2006-07-01",
    "iso:country": "GB",
    "wof:name": "PA1 2LY",
    "wof:placetype": "postalcode"
  },
  "geometry": {"coordinates":[-4.441067,55.843677],"type":"Point"}
}
