{
  "type": "Feature",
  "properties": {
    "iso:country":"GB",
    "wof:name":"B48 7DH",
    "wof:placetype":"postalcode"
},
  "geometry": {"coordinates":[-1.9629236514788,52.34047566385161],"type":"Point"}
}