{
  "type": "Feature",
  "properties": {
    "date:inception_lower": "1983-07-01",
    "date:inception_upper": "1983-07-01",
    "iso:country": "GB",
    "wof:name": "B48 7DH",
    "wof:placetype": "postalcode"
  },
  "geometry": {"coordinates":[-1.961333,52.338261],"type":"Point"}
}
