{
  "type": "Feature",
  "properties": {
    "iso:country":"GB",
    "wof:name":"SE22 9HE",
    "wof:placetype":"postalcode"
},
  "geometry": {"coordinates":[-0.07248987743433,51.45821275638799],"type":"Point"}
}