{
  "type": "Feature",
  "properties": {
    "iso:country":"GB",
    "wof:name":"LA4 4UF",
    "wof:placetype":"postalcode"
},
  "geometry": {"coordinates":[-2.86058267967228,54.06221019372259],"type":"Point"}
}