{
  "type": "Feature",
  "properties": {
    "iso:country": "GB",
    "wof:name": "LA4 4UF",
    "wof:placetype": "postalcode"
  },
  "geometry": {"coordinates":[-2.860583,54.06221],"type":"Point"}
}
