{
  "type": "Feature",
  "properties": {
    "iso:country": "GB",
    "wof:name": "HP10 9QW",
    "wof:placetype": "postalcode"
  },
  "geometry": {"coordinates":[-0.694038,51.60123],"type":"Point"}
}
