{
  "type": "Feature",
  "properties": {
    "iso:country":"GB",
    "wof:name":"N3 1QN",
    "wof:placetype":"postalcode"
},
  "geometry": {"coordinates":[-0.19145890695778,51.60417599669771],"type":"Point"}
}