{
  "type": "Feature",
  "properties": {
    "date:inception_lower": "1980-01-01",
    "date:inception_upper": "1980-01-01",
    "iso:country": "GB",
    "wof:name": "SK10 4UD",
    "wof:placetype": "postalcode"
  },
  "geometry": {"coordinates":[-2.206406,53.293183],"type":"Point"}
}
