{
  "type": "Feature",
  "properties": {
    "iso:country":"GB",
    "wof:name":"LS7 1SR",
    "wof:placetype":"postalcode"
},
  "geometry": {"coordinates":[-1.53998543470286,53.80896862248873],"type":"Point"}
}