{
  "type": "Feature",
  "properties": {
    "iso:country":"GB",
    "wof:name":"DT2 8QU",
    "wof:placetype":"postalcode"
},
  "geometry": {"coordinates":[-2.30171981636051,50.7200346013805],"type":"Point"}
}