{
  "type": "Feature",
  "properties": {
    "iso:country": "GB",
    "wof:name": "DT2 8QU",
    "wof:placetype": "postalcode"
  },
  "geometry": {"coordinates":[-2.30172,50.720035],"type":"Point"}
}
