{
  "type": "Feature",
  "properties": {
    "date:inception_lower": "2021-12-01",
    "date:inception_upper": "2021-12-01",
    "iso:country": "GB",
    "wof:name": "SN13 8DW",
    "wof:placetype": "postalcode"
  },
  "geometry": {"coordinates":[-2.22417,51.410103],"type":"Point"}
}
