{
  "type": "Feature",
  "properties": {
    "iso:country": "GB",
    "wof:name": "BN14 7SP",
    "wof:placetype": "postalcode"
  },
  "geometry": {"coordinates":[-0.382213,50.830652],"type":"Point"}
}
