{
  "type": "Feature",
  "properties": {
    "date:inception_lower":"1980-01-01",
    "date:inception_upper":"1980-01-31",
    "iso:country":"GB",
    "wof:name":"DH4 5QL",
    "wof:placetype":"postalcode"
},
  "geometry": {"coordinates":[-1.482373,54.839135],"type":"Point"}
}