{
  "type": "Feature",
  "properties": {
    "iso:country":"GB",
    "wof:name":"CV6 5NQ",
    "wof:placetype":"postalcode"
},
  "geometry": {"coordinates":[-1.50360608158306,52.4301688164684],"type":"Point"}
}