{
  "type": "Feature",
  "properties": {
    "iso:country":"GB",
    "wof:name":"SY13 1HD",
    "wof:placetype":"postalcode"
},
  "geometry": {"coordinates":[-2.68134579759238,52.9623221543461],"type":"Point"}
}