{
  "type": "Feature",
  "properties": {
    "date:inception_lower":"1980-01-01",
    "date:inception_upper":"1980-01-31",
    "iso:country":"GB",
    "wof:name":"SY13 1HD",
    "wof:placetype":"postalcode"
},
  "geometry": {"coordinates":[-2.681346,52.962322],"type":"Point"}
}