{
  "type": "Feature",
  "properties": {
    "iso:country":"GB",
    "wof:name":"SA32 8RY",
    "wof:placetype":"postalcode"
},
  "geometry": {"coordinates":[-4.1001091994155,51.88829432230188],"type":"Point"}
}