{
  "type": "Feature",
  "properties": {
    "date:inception_lower": "1980-01-01",
    "date:inception_upper": "1980-01-01",
    "iso:country": "GB",
    "wof:name": "BB8 0BA",
    "wof:placetype": "postalcode"
  },
  "geometry": {"coordinates":[-2.156586,53.861113],"type":"Point"}
}
