{
  "type": "Feature",
  "properties": {
    "iso:country":"GB",
    "wof:name":"G84 0SB",
    "wof:placetype":"postalcode"
},
  "geometry": {"coordinates":[-4.79981150908383,56.01170807837813],"type":"Point"}
}