{
  "type": "Feature",
  "properties": {
    "iso:country": "GB",
    "wof:name": "G84 0SB",
    "wof:placetype": "postalcode"
  },
  "geometry": {"coordinates":[-4.799811,56.011708],"type":"Point"}
}
