{
  "type": "Feature",
  "properties": {
    "iso:country":"GB",
    "wof:name":"SS6 9RY",
    "wof:placetype":"postalcode"
},
  "geometry": {"coordinates":[0.60495075287568,51.60015336662226],"type":"Point"}
}