{
  "type": "Feature",
  "properties": {
    "iso:country": "GB",
    "wof:name": "WR8 9BP",
    "wof:placetype": "postalcode"
  },
  "geometry": {"coordinates":[-2.154394,52.083309],"type":"Point"}
}
