{
  "type": "Feature",
  "properties": {
    "iso:country":"GB",
    "wof:name":"WR8 9BP",
    "wof:placetype":"postalcode"
},
  "geometry": {"coordinates":[-2.15439416856497,52.0833093519663],"type":"Point"}
}