{
  "type": "Feature",
  "properties": {
    "date:inception_lower":"1980-01-01",
    "date:inception_upper":"1980-01-31",
    "iso:country":"GB",
    "wof:name":"SY16 3NW",
    "wof:placetype":"postalcode"
},
  "geometry": {"coordinates":[-3.352605,52.61051],"type":"Point"}
}