{
  "type": "Feature",
  "properties": {
    "iso:country":"GB",
    "wof:name":"SY16 3NW",
    "wof:placetype":"postalcode"
},
  "geometry": {"coordinates":[-3.35260528849733,52.6105097800169],"type":"Point"}
}