{
  "type": "Feature",
  "properties": {
    "iso:country":"GB",
    "wof:name":"KA8 8DW",
    "wof:placetype":"postalcode"
},
  "geometry": {"coordinates":[-4.62911922827222,55.47122151661348],"type":"Point"}
}