{
  "type": "Feature",
  "properties": {
    "date:inception_lower":"1980-01-01",
    "date:inception_upper":"1980-01-31",
    "iso:country":"GB",
    "wof:name":"SW9 0PF",
    "wof:placetype":"postalcode"
},
  "geometry": {"coordinates":[-0.114192,51.476714],"type":"Point"}
}