{
  "type": "Feature",
  "properties": {
    "iso:country":"GB",
    "wof:name":"SW9 0PF",
    "wof:placetype":"postalcode"
},
  "geometry": {"coordinates":[-0.11419176833204,51.47671431799893],"type":"Point"}
}