{
  "type": "Feature",
  "properties": {
    "iso:country": "GB",
    "wof:name": "PE32 1WB",
    "wof:placetype": "postalcode"
  },
  "geometry": {"coordinates":[0.634791,52.704604],"type":"Point"}
}
