{
  "type": "Feature",
  "properties": {
    "iso:country":"GB",
    "wof:name":"BD21 1RL",
    "wof:placetype":"postalcode"
},
  "geometry": {"coordinates":[-1.92318223599167,53.85991486182525],"type":"Point"}
}