{
  "type": "Feature",
  "properties": {
    "iso:country": "GB",
    "wof:name": "PL21 9AF",
    "wof:placetype": "postalcode"
  },
  "geometry": {"coordinates":[-3.920893,50.389712],"type":"Point"}
}
