{
  "type": "Feature",
  "properties": {
    "date:inception_lower":"1980-01-01",
    "date:inception_upper":"1980-01-31",
    "iso:country":"GB",
    "wof:name":"PL21 9AF",
    "wof:placetype":"postalcode"
},
  "geometry": {"coordinates":[-3.920893,50.389712],"type":"Point"}
}