{
  "type": "Feature",
  "properties": {
    "iso:country":"GB",
    "wof:name":"G20 7RY",
    "wof:placetype":"postalcode"
},
  "geometry": {"coordinates":[-4.27485106429633,55.88266115225122],"type":"Point"}
}