{
  "type": "Feature",
  "properties": {
    "iso:country": "GB",
    "wof:name": "ST15 0HU",
    "wof:placetype": "postalcode"
  },
  "geometry": {"coordinates":[-2.155679,52.895469],"type":"Point"}
}
