{
  "type": "Feature",
  "properties": {
    "iso:country":"GB",
    "wof:name":"SR4 8BA",
    "wof:placetype":"postalcode"
},
  "geometry": {"coordinates":[-1.43221566025906,54.89612773832343],"type":"Point"}
}