{
  "type": "Feature",
  "properties": {
    "iso:country": "GB",
    "wof:name": "M43 7QT",
    "wof:placetype": "postalcode"
  },
  "geometry": {"coordinates":[-2.156334,53.48726],"type":"Point"}
}
