{
  "type": "Feature",
  "properties": {
    "date:inception_lower": "1980-01-01",
    "date:inception_upper": "1980-01-01",
    "iso:country": "GB",
    "wof:name": "GL56 0HA",
    "wof:placetype": "postalcode"
  },
  "geometry": {"coordinates":[-1.698066,51.989908],"type":"Point"}
}
