{
  "type": "Feature",
  "properties": {
    "iso:country":"GB",
    "wof:name":"GL56 0HA",
    "wof:placetype":"postalcode"
},
  "geometry": {"coordinates":[-1.69806612689756,51.9899084701478],"type":"Point"}
}