{
  "type": "Feature",
  "properties": {
    "date:inception_lower": "1980-01-01",
    "date:inception_upper": "1980-01-01",
    "iso:country": "GB",
    "wof:name": "NR28 0DL",
    "wof:placetype": "postalcode"
  },
  "geometry": {"coordinates":[1.393143,52.828562],"type":"Point"}
}
