{
  "type": "Feature",
  "properties": {
    "iso:country":"GB",
    "wof:name":"IG6 1ED",
    "wof:placetype":"postalcode"
},
  "geometry": {"coordinates":[0.07995205757492,51.58030981009573],"type":"Point"}
}