{
  "type": "Feature",
  "properties": {
    "iso:country":"GB",
    "wof:name":"W1F 7EX",
    "wof:placetype":"postalcode"
},
  "geometry": {"coordinates":[-0.13825154348161,51.51357252650872],"type":"Point"}
}