{
  "type": "Feature",
  "properties": {
    "iso:country": "GB",
    "wof:name": "SG2 9QA",
    "wof:placetype": "postalcode"
  },
  "geometry": {"coordinates":[-0.158288,51.898001],"type":"Point"}
}
