{
  "type": "Feature",
  "properties": {
    "iso:country":"GB",
    "wof:name":"OL9 9DZ",
    "wof:placetype":"postalcode"
},
  "geometry": {"coordinates":[-2.15069060686291,53.53621826670367],"type":"Point"}
}