{
  "type": "Feature",
  "properties": {
    "date:inception_lower": "1980-01-01",
    "date:inception_upper": "1980-01-01",
    "iso:country": "GB",
    "wof:name": "OL9 9DZ",
    "wof:placetype": "postalcode"
  },
  "geometry": {"coordinates":[-2.150689,53.536234],"type":"Point"}
}
