{
  "type": "Feature",
  "properties": {
    "iso:country":"GB",
    "wof:name":"G46 6NU",
    "wof:placetype":"postalcode"
},
  "geometry": {"coordinates":[-4.29554851867787,55.80936062264453],"type":"Point"}
}