{
  "type": "Feature",
  "properties": {
    "iso:country":"GB",
    "wof:name":"SE9 1JT",
    "wof:placetype":"postalcode"
},
  "geometry": {"coordinates":[0.05426717314045,51.46419852446767],"type":"Point"}
}