{
  "type": "Feature",
  "properties": {
    "iso:country": "GB",
    "wof:name": "LS8 4EX",
    "wof:placetype": "postalcode"
  },
  "geometry": {"coordinates":[-1.52188,53.817695],"type":"Point"}
}
