{
  "type": "Feature",
  "properties": {
    "date:inception_lower": "2000-12-01",
    "date:inception_upper": "2000-12-01",
    "iso:country": "GB",
    "wof:name": "CW11 4QZ",
    "wof:placetype": "postalcode"
  },
  "geometry": {"coordinates":[-2.379768,53.110003],"type":"Point"}
}
