{
  "type": "Feature",
  "properties": {
    "iso:country": "GB",
    "wof:name": "B10 0NY",
    "wof:placetype": "postalcode"
  },
  "geometry": {"coordinates":[-1.869038,52.472015],"type":"Point"}
}
