{
  "type": "Feature",
  "properties": {
    "iso:country":"GB",
    "wof:name":"B10 0NY",
    "wof:placetype":"postalcode"
},
  "geometry": {"coordinates":[-1.86903843624384,52.47201484982951],"type":"Point"}
}