{
  "type": "Feature",
  "properties": {
    "iso:country":"GB",
    "wof:name":"DD1 1LP",
    "wof:placetype":"postalcode"
},
  "geometry": {"coordinates":[-2.97467056848857,56.46193787682557],"type":"Point"}
}