{
  "type": "Feature",
  "properties": {
    "iso:country":"GB",
    "wof:name":"W1H 7EG",
    "wof:placetype":"postalcode"
},
  "geometry": {"coordinates":[-0.15779904886518,51.51452863661302],"type":"Point"}
}