{
  "type": "Feature",
  "properties": {
    "date:inception_lower": "2000-12-01",
    "date:inception_upper": "2000-12-01",
    "iso:country": "GB",
    "wof:name": "W1H 7EG",
    "wof:placetype": "postalcode"
  },
  "geometry": {"coordinates":[-0.157774,51.51453],"type":"Point"}
}
