{
  "type": "Feature",
  "properties": {
    "iso:country":"GB",
    "wof:name":"PR3 1NB",
    "wof:placetype":"postalcode"
},
  "geometry": {"coordinates":[-2.78507988032622,53.89944295487051],"type":"Point"}
}