{
  "type": "Feature",
  "properties": {
    "date:inception_lower": "1980-01-01",
    "date:inception_upper": "1980-01-01",
    "iso:country": "GB",
    "wof:name": "PR3 1NB",
    "wof:placetype": "postalcode"
  },
  "geometry": {"coordinates":[-2.78508,53.899443],"type":"Point"}
}
