{
  "type": "Feature",
  "properties": {
    "iso:country":"GB",
    "wof:name":"B17 8SL",
    "wof:placetype":"postalcode"
},
  "geometry": {"coordinates":[-1.97184109072288,52.46749886705279],"type":"Point"}
}