{
  "type": "Feature",
  "properties": {
    "iso:country":"GB",
    "wof:name":"NW5 1HA",
    "wof:placetype":"postalcode"
},
  "geometry": {"coordinates":[-0.14343061283646,51.56163843782204],"type":"Point"}
}