{
  "type": "Feature",
  "properties": {
    "iso:country":"GB",
    "wof:name":"M28 3QG",
    "wof:placetype":"postalcode"
},
  "geometry": {"coordinates":[-2.39806045212474,53.52995151540271],"type":"Point"}
}