{
  "type": "Feature",
  "properties": {
    "iso:country":"GB",
    "wof:name":"EX4 2LD",
    "wof:placetype":"postalcode"
},
  "geometry": {"coordinates":[-3.59214288761614,50.73304076391735],"type":"Point"}
}