{
  "type": "Feature",
  "properties": {
    "iso:country": "GB",
    "wof:name": "EX4 2LD",
    "wof:placetype": "postalcode"
  },
  "geometry": {"coordinates":[-3.592143,50.733041],"type":"Point"}
}
