{
  "type": "Feature",
  "properties": {
    "date:inception_lower":"2008-11-01",
    "date:inception_upper":"2008-11-30",
    "iso:country":"GB",
    "wof:name":"LE4 3LN",
    "wof:placetype":"postalcode"
},
  "geometry": {"coordinates":[-1.127361,52.687015],"type":"Point"}
}