{
  "type": "Feature",
  "properties": {
    "iso:country":"GB",
    "wof:name":"LE4 3LN",
    "wof:placetype":"postalcode"
},
  "geometry": {"coordinates":[-1.12736087809461,52.68701480117905],"type":"Point"}
}