{
  "type": "Feature",
  "properties": {
    "iso:country": "GB",
    "wof:name": "MK18 1RX",
    "wof:placetype": "postalcode"
  },
  "geometry": {"coordinates":[-0.975469,52.014911],"type":"Point"}
}
