{
  "type": "Feature",
  "properties": {
    "iso:country":"GB",
    "wof:name":"MK18 1RX",
    "wof:placetype":"postalcode"
},
  "geometry": {"coordinates":[-0.97593447540879,52.01510195871412],"type":"Point"}
}