{
  "type": "Feature",
  "properties": {
    "iso:country": "GB",
    "wof:name": "DY12 3HT",
    "wof:placetype": "postalcode"
  },
  "geometry": {"coordinates":[-2.393652,52.40601],"type":"Point"}
}
