{
  "type": "Feature",
  "properties": {
    "iso:country":"GB",
    "wof:name":"DY12 3HT",
    "wof:placetype":"postalcode"
},
  "geometry": {"coordinates":[-2.39365207093711,52.40601046756587],"type":"Point"}
}