{
  "type": "Feature",
  "properties": {
    "iso:country": "GB",
    "wof:name": "PL7 4EY",
    "wof:placetype": "postalcode"
  },
  "geometry": {"coordinates":[-4.055341,50.393733],"type":"Point"}
}
