{
  "type": "Feature",
  "properties": {
    "date:inception_lower": "1980-01-01",
    "date:inception_upper": "1980-01-01",
    "iso:country": "GB",
    "wof:name": "PL7 4EY",
    "wof:placetype": "postalcode"
  },
  "geometry": {"coordinates":[-4.055341,50.393733],"type":"Point"}
}
