{
  "type": "Feature",
  "properties": {
    "iso:country":"GB",
    "wof:name":"WS2 9UD",
    "wof:placetype":"postalcode"
},
  "geometry": {"coordinates":[-2.00320385204586,52.58595284770587],"type":"Point"}
}