{
  "type": "Feature",
  "properties": {
    "date:inception_lower": "1980-01-01",
    "date:inception_upper": "1980-01-01",
    "iso:country": "GB",
    "wof:name": "GL16 8BP",
    "wof:placetype": "postalcode"
  },
  "geometry": {"coordinates":[-2.610665,51.795931],"type":"Point"}
}
