{
  "type": "Feature",
  "properties": {
    "iso:country": "GB",
    "wof:name": "B92 9NG",
    "wof:placetype": "postalcode"
  },
  "geometry": {"coordinates":[-1.766659,52.43142],"type":"Point"}
}
