{
  "type": "Feature",
  "properties": {
    "iso:country":"GB",
    "wof:name":"B92 9NG",
    "wof:placetype":"postalcode"
},
  "geometry": {"coordinates":[-1.76665902689654,52.43142033923613],"type":"Point"}
}