{
  "type": "Feature",
  "properties": {
    "iso:country": "GB",
    "wof:name": "RG20 7ES",
    "wof:placetype": "postalcode"
  },
  "geometry": {"coordinates":[-1.40211,51.492104],"type":"Point"}
}
