{
  "type": "Feature",
  "properties": {
    "iso:country":"GB",
    "wof:name":"RG20 7ES",
    "wof:placetype":"postalcode"
},
  "geometry": {"coordinates":[-1.40211043941881,51.49210440249553],"type":"Point"}
}