{
  "type": "Feature",
  "properties": {
    "date:inception_lower": "1995-07-01",
    "date:inception_upper": "1995-07-01",
    "iso:country": "GB",
    "wof:name": "RG20 7ES",
    "wof:placetype": "postalcode"
  },
  "geometry": {"coordinates":[-1.40211,51.492104],"type":"Point"}
}
