{
  "type": "Feature",
  "properties": {
    "iso:country":"GB",
    "wof:name":"NN1 4AA",
    "wof:placetype":"postalcode"
},
  "geometry": {"coordinates":[-0.88828695296341,52.23992559677556],"type":"Point"}
}