{
  "type": "Feature",
  "properties": {
    "date:inception_lower": "2004-11-01",
    "date:inception_upper": "2004-11-01",
    "iso:country": "GB",
    "wof:name": "CW11 3SD",
    "wof:placetype": "postalcode"
  },
  "geometry": {"coordinates":[-2.390978,53.146831],"type":"Point"}
}
