{
  "type": "Feature",
  "properties": {
    "iso:country":"GB",
    "wof:name":"CW11 3SD",
    "wof:placetype":"postalcode"
},
  "geometry": {"coordinates":[-2.39097807497024,53.14683111975375],"type":"Point"}
}