{
  "type": "Feature",
  "properties": {
    "iso:country":"GB",
    "wof:name":"S60 5QP",
    "wof:placetype":"postalcode"
},
  "geometry": {"coordinates":[-1.35072398562781,53.38497253724022],"type":"Point"}
}