{
  "type": "Feature",
  "properties": {
    "iso:country":"GB",
    "wof:name":"DN8 5SY",
    "wof:placetype":"postalcode"
},
  "geometry": {"coordinates":[-0.85978493077555,53.56378810144697],"type":"Point"}
}