{
  "type": "Feature",
  "properties": {
    "iso:country": "GB",
    "wof:name": "DN8 5SY",
    "wof:placetype": "postalcode"
  },
  "geometry": {"coordinates":[-0.859785,53.563788],"type":"Point"}
}
