{
  "type": "Feature",
  "properties": {
    "iso:country": "GB",
    "wof:name": "CW2 5EL",
    "wof:placetype": "postalcode"
  },
  "geometry": {"coordinates":[-2.44718,53.060491],"type":"Point"}
}
