{
  "type": "Feature",
  "properties": {
    "date:inception_lower": "1980-01-01",
    "date:inception_upper": "1980-01-01",
    "iso:country": "GB",
    "wof:name": "CW2 5EL",
    "wof:placetype": "postalcode"
  },
  "geometry": {"coordinates":[-2.44718,53.060491],"type":"Point"}
}
