{
  "type": "Feature",
  "properties": {
    "iso:country":"GB",
    "wof:name":"CW2 5EL",
    "wof:placetype":"postalcode"
},
  "geometry": {"coordinates":[-2.4471800858828,53.06049084651524],"type":"Point"}
}