{
  "type": "Feature",
  "properties": {
    "iso:country":"GB",
    "wof:name":"BA2 3LN",
    "wof:placetype":"postalcode"
},
  "geometry": {"coordinates":[-2.37839847629819,51.37607082490617],"type":"Point"}
}