{
  "type": "Feature",
  "properties": {
    "iso:country":"GB",
    "wof:name":"CF14 1PX",
    "wof:placetype":"postalcode"
},
  "geometry": {"coordinates":[-3.21378644694692,51.51120782020275],"type":"Point"}
}