{
  "type": "Feature",
  "properties": {
    "date:inception_lower": "1999-12-01",
    "date:inception_upper": "1999-12-01",
    "iso:country": "GB",
    "wof:name": "SK4 4DL",
    "wof:placetype": "postalcode"
  },
  "geometry": {"coordinates":[-2.192063,53.416451],"type":"Point"}
}
