{
  "type": "Feature",
  "properties": {
    "iso:country":"GB",
    "wof:name":"DG8 7BA",
    "wof:placetype":"postalcode"
},
  "geometry": {"coordinates":[-4.40603843703242,54.9364684352842],"type":"Point"}
}