{
  "type": "Feature",
  "properties": {
    "date:inception_lower": "1980-01-01",
    "date:inception_upper": "1980-01-01",
    "iso:country": "GB",
    "wof:name": "DG8 7BA",
    "wof:placetype": "postalcode"
  },
  "geometry": {"coordinates":[-4.405965,54.93647],"type":"Point"}
}
