{
  "type": "Feature",
  "properties": {
    "date:inception_lower": "2022-09-01",
    "date:inception_upper": "2022-09-01",
    "iso:country": "GB",
    "wof:name": "GL15 5GP",
    "wof:placetype": "postalcode"
  },
  "geometry": {"coordinates":[-2.515099,51.7215],"type":"Point"}
}
