{
  "type": "Feature",
  "properties": {
    "iso:country":"GB",
    "wof:name":"NR15 1JR",
    "wof:placetype":"postalcode"
},
  "geometry": {"coordinates":[1.37556823503562,52.54179284038205],"type":"Point"}
}