{
  "type": "Feature",
  "properties": {
    "iso:country":"GB",
    "wof:name":"TS17 8HU",
    "wof:placetype":"postalcode"
},
  "geometry": {"coordinates":[-1.29506113161392,54.54464606230106],"type":"Point"}
}