{
  "type": "Feature",
  "properties": {
    "date:inception_lower":"1997-12-01",
    "date:inception_upper":"1997-12-31",
    "iso:country":"GB",
    "wof:name":"EN4 9EE",
    "wof:placetype":"postalcode"
},
  "geometry": {"coordinates":[-0.149673,51.650564],"type":"Point"}
}