{
  "type": "Feature",
  "properties": {
    "iso:country":"GB",
    "wof:name":"EN4 9EE",
    "wof:placetype":"postalcode"
},
  "geometry": {"coordinates":[-0.14967261355949,51.65056364486347],"type":"Point"}
}