{
  "type": "Feature",
  "properties": {
    "iso:country": "GB",
    "wof:name": "S5 7QL",
    "wof:placetype": "postalcode"
  },
  "geometry": {"coordinates":[-1.47116,53.419489],"type":"Point"}
}
