{
  "type": "Feature",
  "properties": {
    "iso:country":"GB",
    "wof:name":"S5 7QL",
    "wof:placetype":"postalcode"
},
  "geometry": {"coordinates":[-1.4711451436292,53.41948963068835],"type":"Point"}
}