{
  "type": "Feature",
  "properties": {
    "date:inception_lower": "2002-07-01",
    "date:inception_upper": "2002-07-01",
    "iso:country": "GB",
    "wof:name": "OX16 0BW",
    "wof:placetype": "postalcode"
  },
  "geometry": {"coordinates":[-1.33965,52.060679],"type":"Point"}
}
