{
  "type": "Feature",
  "properties": {
    "iso:country": "GB",
    "wof:name": "OX16 0BW",
    "wof:placetype": "postalcode"
  },
  "geometry": {"coordinates":[-1.33965,52.060679],"type":"Point"}
}
