{
  "type": "Feature",
  "properties": {
    "iso:country": "GB",
    "wof:name": "CH2 2AR",
    "wof:placetype": "postalcode"
  },
  "geometry": {"coordinates":[-2.889602,53.202183],"type":"Point"}
}
