{
  "type": "Feature",
  "properties": {
    "iso:country":"GB",
    "wof:name":"NE24 4SD",
    "wof:placetype":"postalcode"
},
  "geometry": {"coordinates":[-1.53871023900092,55.11833196083357],"type":"Point"}
}