{
  "type": "Feature",
  "properties": {
    "iso:country": "GB",
    "wof:name": "BN11 4HB",
    "wof:placetype": "postalcode"
  },
  "geometry": {"coordinates":[-0.382254,50.817889],"type":"Point"}
}
