{
  "type": "Feature",
  "properties": {
    "iso:country":"GB",
    "wof:name":"BN11 4HB",
    "wof:placetype":"postalcode"
},
  "geometry": {"coordinates":[-0.38225441063088,50.8178891477345],"type":"Point"}
}