{
  "type": "Feature",
  "properties": {
    "iso:country": "GB",
    "wof:name": "IP14 1JQ",
    "wof:placetype": "postalcode"
  },
  "geometry": {"coordinates":[0.991585,52.196805],"type":"Point"}
}
