{
  "type": "Feature",
  "properties": {
    "iso:country":"GB",
    "wof:name":"IP14 1JQ",
    "wof:placetype":"postalcode"
},
  "geometry": {"coordinates":[0.9915849972978,52.19680530747151],"type":"Point"}
}