{
  "type": "Feature",
  "properties": {
    "date:inception_lower": "1986-04-01",
    "date:inception_upper": "1986-04-01",
    "iso:country": "GB",
    "wof:name": "IP14 1JQ",
    "wof:placetype": "postalcode"
  },
  "geometry": {"coordinates":[0.991585,52.196805],"type":"Point"}
}
