{
  "type": "Feature",
  "properties": {
    "iso:country": "GB",
    "wof:name": "CB10 2RF",
    "wof:placetype": "postalcode"
  },
  "geometry": {"coordinates":[0.390602,51.993532],"type":"Point"}
}
