{
  "type": "Feature",
  "properties": {
    "date:inception_lower": "2018-07-01",
    "date:inception_upper": "2018-07-01",
    "iso:country": "GB",
    "wof:name": "CB10 2RF",
    "wof:placetype": "postalcode"
  },
  "geometry": {"coordinates":[0.25312,52.02403],"type":"Point"}
}
