{
  "type": "Feature",
  "properties": {
    "iso:country": "GB",
    "wof:name": "IV24 3BP",
    "wof:placetype": "postalcode"
  },
  "geometry": {"coordinates":[-4.44933,57.888882],"type":"Point"}
}
