{
  "type": "Feature",
  "properties": {
    "iso:country":"GB",
    "wof:name":"TS5 8QQ",
    "wof:placetype":"postalcode"
},
  "geometry": {"coordinates":[-1.26895086458068,54.54733107214209],"type":"Point"}
}