{
  "type": "Feature",
  "properties": {
    "iso:country": "GB",
    "wof:name": "MK3 7LN",
    "wof:placetype": "postalcode"
  },
  "geometry": {"coordinates":[-0.750128,52.002998],"type":"Point"}
}
