{
  "type": "Feature",
  "properties": {
    "iso:country":"GB",
    "wof:name":"KA24 4DN",
    "wof:placetype":"postalcode"
},
  "geometry": {"coordinates":[-4.70385614989492,55.70489484772602],"type":"Point"}
}