{
  "type": "Feature",
  "properties": {
    "iso:country":"GB",
    "wof:name":"SY11 3JT",
    "wof:placetype":"postalcode"
},
  "geometry": {"coordinates":[-3.03886137066923,52.89327366560472],"type":"Point"}
}