{
  "type": "Feature",
  "properties": {
    "iso:country":"GB",
    "wof:name":"ST4 7PT",
    "wof:placetype":"postalcode"
},
  "geometry": {"coordinates":[-2.20338401591624,53.01055805177269],"type":"Point"}
}