{
  "type": "Feature",
  "properties": {
    "iso:country":"GB",
    "wof:name":"UB4 8SX",
    "wof:placetype":"postalcode"
},
  "geometry": {"coordinates":[-0.42537652385755,51.53790285524283],"type":"Point"}
}