{
  "type": "Feature",
  "properties": {
    "iso:country":"GB",
    "wof:name":"LN7 6QE",
    "wof:placetype":"postalcode"
},
  "geometry": {"coordinates":[-0.31532176997741,53.49733621689676],"type":"Point"}
}