{
  "type": "Feature",
  "properties": {
    "iso:country": "GB",
    "wof:name": "BS24 0DE",
    "wof:placetype": "postalcode"
  },
  "geometry": {"coordinates":[-2.947715,51.286242],"type":"Point"}
}
