{
  "type": "Feature",
  "properties": {
    "iso:country":"GB",
    "wof:name":"BS24 0DE",
    "wof:placetype":"postalcode"
},
  "geometry": {"coordinates":[-2.94772120233868,51.28620103241126],"type":"Point"}
}