{
  "type": "Feature",
  "properties": {
    "date:inception_lower": "1994-05-01",
    "date:inception_upper": "1994-05-01",
    "iso:country": "GB",
    "wof:name": "PR3 1WF",
    "wof:placetype": "postalcode"
  },
  "geometry": {"coordinates":[-2.782526,53.899612],"type":"Point"}
}
