{
  "type": "Feature",
  "properties": {
    "iso:country": "GB",
    "wof:name": "PE19 2PY",
    "wof:placetype": "postalcode"
  },
  "geometry": {"coordinates":[-0.27217,52.227957],"type":"Point"}
}
