{
  "type": "Feature",
  "properties": {
    "iso:country":"GB",
    "wof:name":"PE19 2PY",
    "wof:placetype":"postalcode"
},
  "geometry": {"coordinates":[-0.27216968215093,52.22795676247959],"type":"Point"}
}