{
  "type": "Feature",
  "properties": {
    "date:inception_lower": "2021-12-01",
    "date:inception_upper": "2021-12-01",
    "iso:country": "GB",
    "wof:name": "M29 8RR",
    "wof:placetype": "postalcode"
  },
  "geometry": {"coordinates":[-2.44016,53.51215],"type":"Point"}
}
