{
  "type": "Feature",
  "properties": {
    "iso:country":"GB",
    "wof:name":"ML2 0FL",
    "wof:placetype":"postalcode"
},
  "geometry": {"coordinates":[-3.94649014212824,55.76774353845047],"type":"Point"}
}