{
  "type": "Feature",
  "properties": {
    "date:inception_lower": "2016-07-01",
    "date:inception_upper": "2016-07-01",
    "iso:country": "GB",
    "wof:name": "UB10 8FH",
    "wof:placetype": "postalcode"
  },
  "geometry": {"coordinates":[-0.438508,51.568168],"type":"Point"}
}
