{
  "type": "Feature",
  "properties": {
    "iso:country": "GB",
    "wof:name": "N14 4AR",
    "wof:placetype": "postalcode"
  },
  "geometry": {"coordinates":[-0.138905,51.64346],"type":"Point"}
}
