{
  "type": "Feature",
  "properties": {
    "iso:country":"GB",
    "wof:name":"N14 4AR",
    "wof:placetype":"postalcode"
},
  "geometry": {"coordinates":[-0.13890503034927,51.64346039462525],"type":"Point"}
}