{
  "type": "Feature",
  "properties": {
    "date:inception_lower": "1980-01-01",
    "date:inception_upper": "1980-01-01",
    "iso:country": "GB",
    "wof:name": "CF5 5TL",
    "wof:placetype": "postalcode"
  },
  "geometry": {"coordinates":[-3.265209,51.464095],"type":"Point"}
}
