{
  "type": "Feature",
  "properties": {
    "iso:country":"GB",
    "wof:name":"CF5 5TL",
    "wof:placetype":"postalcode"
},
  "geometry": {"coordinates":[-3.26520920830324,51.4640948577333],"type":"Point"}
}