{
  "type": "Feature",
  "properties": {
    "iso:country": "GB",
    "wof:name": "CB8 8XU",
    "wof:placetype": "postalcode"
  },
  "geometry": {"coordinates":[0.547488,52.171291],"type":"Point"}
}
