{
  "type": "Feature",
  "properties": {
    "iso:country":"GB",
    "wof:name":"BN17 7AN",
    "wof:placetype":"postalcode"
},
  "geometry": {"coordinates":[-0.54462746766857,50.81208660085318],"type":"Point"}
}