{
  "type": "Feature",
  "properties": {
    "iso:country":"GB",
    "wof:name":"HA3 0UE",
    "wof:placetype":"postalcode"
},
  "geometry": {"coordinates":[-0.29071685705158,51.58513407115694],"type":"Point"}
}