{
  "type": "Feature",
  "properties": {
    "iso:country":"GB",
    "wof:name":"LS29 9HA",
    "wof:placetype":"postalcode"
},
  "geometry": {"coordinates":[-1.83039308540245,53.92715657550062],"type":"Point"}
}