{
  "type": "Feature",
  "properties": {
    "iso:country": "GB",
    "wof:name": "LS29 9HA",
    "wof:placetype": "postalcode"
  },
  "geometry": {"coordinates":[-1.830393,53.927157],"type":"Point"}
}
