{
  "type": "Feature",
  "properties": {
    "iso:country":"GB",
    "wof:name":"SO19 6GE",
    "wof:placetype":"postalcode"
},
  "geometry": {"coordinates":[-1.32921275618423,50.9074512332443],"type":"Point"}
}