{
  "type": "Feature",
  "properties": {
    "iso:country":"GB",
    "wof:name":"G69 8EA",
    "wof:placetype":"postalcode"
},
  "geometry": {"coordinates":[-4.08061380767293,55.8943307232207],"type":"Point"}
}