{
  "type": "Feature",
  "properties": {
    "iso:country":"GB",
    "wof:name":"IP6 8AA",
    "wof:placetype":"postalcode"
},
  "geometry": {"coordinates":[1.05047026629927,52.15652522027536],"type":"Point"}
}