{
  "type": "Feature",
  "properties": {
    "date:inception_lower": "1980-01-01",
    "date:inception_upper": "1980-01-01",
    "iso:country": "GB",
    "wof:name": "IP6 8AA",
    "wof:placetype": "postalcode"
  },
  "geometry": {"coordinates":[1.050468,52.156488],"type":"Point"}
}
