{
  "type": "Feature",
  "properties": {
    "iso:country": "GB",
    "wof:name": "EX20 3RB",
    "wof:placetype": "postalcode"
  },
  "geometry": {"coordinates":[-4.009346,50.805389],"type":"Point"}
}
