{
  "type": "Feature",
  "properties": {
    "date:inception_lower": "1980-01-01",
    "date:inception_upper": "1980-01-01",
    "iso:country": "GB",
    "wof:name": "EX20 3RB",
    "wof:placetype": "postalcode"
  },
  "geometry": {"coordinates":[-4.009346,50.805389],"type":"Point"}
}
