{
  "type": "Feature",
  "properties": {
    "iso:country":"GB",
    "wof:name":"TR7 2HF",
    "wof:placetype":"postalcode"
},
  "geometry": {"coordinates":[-5.07752169385289,50.41154471727307],"type":"Point"}
}