{
  "type": "Feature",
  "properties": {
    "iso:country":"GB",
    "wof:name":"TR3 7PX",
    "wof:placetype":"postalcode"
},
  "geometry": {"coordinates":[-5.11907672328774,50.21117187771438],"type":"Point"}
}