{
  "type": "Feature",
  "properties": {
    "iso:country":"GB",
    "wof:name":"M20 6ED",
    "wof:placetype":"postalcode"
},
  "geometry": {"coordinates":[-2.22004563393887,53.42190328246344],"type":"Point"}
}