{
  "type": "Feature",
  "properties": {
    "iso:country": "GB",
    "wof:name": "M20 6ED",
    "wof:placetype": "postalcode"
  },
  "geometry": {"coordinates":[-2.220046,53.421903],"type":"Point"}
}
