{
  "type": "Feature",
  "properties": {
    "iso:country":"GB",
    "wof:name":"EH9 2AF",
    "wof:placetype":"postalcode"
},
  "geometry": {"coordinates":[-3.19758441570879,55.93436572034936],"type":"Point"}
}