{
  "type": "Feature",
  "properties": {
    "date:inception_lower": "1980-01-01",
    "date:inception_upper": "1980-01-01",
    "iso:country": "GB",
    "wof:name": "WR12 7EN",
    "wof:placetype": "postalcode"
  },
  "geometry": {"coordinates":[-1.855441,52.041687],"type":"Point"}
}
