{
  "type": "Feature",
  "properties": {
    "iso:country":"GB",
    "wof:name":"WR12 7EN",
    "wof:placetype":"postalcode"
},
  "geometry": {"coordinates":[-1.8554405751314,52.04168700276955],"type":"Point"}
}