{
  "type": "Feature",
  "properties": {
    "iso:country":"GB",
    "wof:name":"PE13 1NJ",
    "wof:placetype":"postalcode"
},
  "geometry": {"coordinates":[0.15835875235969,52.66596328804759],"type":"Point"}
}