{
  "type": "Feature",
  "properties": {
    "iso:country":"GB",
    "wof:name":"NG16 5DB",
    "wof:placetype":"postalcode"
},
  "geometry": {"coordinates":[-1.31497640264411,53.04376541047457],"type":"Point"}
}