{
  "type": "Feature",
  "properties": {
    "iso:country":"GB",
    "wof:name":"S80 4UD",
    "wof:placetype":"postalcode"
},
  "geometry": {"coordinates":[-1.20344765640729,53.28313567407228],"type":"Point"}
}