{
  "type": "Feature",
  "properties": {
    "iso:country":"GB",
    "wof:name":"S11 9AD",
    "wof:placetype":"postalcode"
},
  "geometry": {"coordinates":[-1.49180981478198,53.36219561497637],"type":"Point"}
}