{
  "type": "Feature",
  "properties": {
    "iso:country":"GB",
    "wof:name":"SK16 5HG",
    "wof:placetype":"postalcode"
},
  "geometry": {"coordinates":[-2.06508824017606,53.47206457035793],"type":"Point"}
}