{
  "type": "Feature",
  "properties": {
    "iso:country": "GB",
    "wof:name": "E2 8AT",
    "wof:placetype": "postalcode"
  },
  "geometry": {"coordinates":[-0.076434,51.536225],"type":"Point"}
}
