{
  "type": "Feature",
  "properties": {
    "date:inception_lower": "1980-01-01",
    "date:inception_upper": "1980-01-01",
    "iso:country": "GB",
    "wof:name": "CT13 0AL",
    "wof:placetype": "postalcode"
  },
  "geometry": {"coordinates":[1.336336,51.270574],"type":"Point"}
}
