{
  "type": "Feature",
  "properties": {
    "iso:country":"GB",
    "wof:name":"CM11 2SU",
    "wof:placetype":"postalcode"
},
  "geometry": {"coordinates":[0.42764533757121,51.60694146037002],"type":"Point"}
}