{
  "type": "Feature",
  "properties": {
    "iso:country": "GB",
    "wof:name": "CM11 2SU",
    "wof:placetype": "postalcode"
  },
  "geometry": {"coordinates":[0.427645,51.606941],"type":"Point"}
}
