{
  "type": "Feature",
  "properties": {
    "iso:country": "GB",
    "wof:name": "BA11 1PW",
    "wof:placetype": "postalcode"
  },
  "geometry": {"coordinates":[-2.320271,51.230235],"type":"Point"}
}
