{
  "type": "Feature",
  "properties": {
    "date:inception_lower": "2018-07-01",
    "date:inception_upper": "2018-07-01",
    "iso:country": "GB",
    "wof:name": "LA21 8BF",
    "wof:placetype": "postalcode"
  },
  "geometry": {"coordinates":[-3.104232,54.33691],"type":"Point"}
}
