{
  "type": "Feature",
  "properties": {
    "date:inception_lower": "1980-01-01",
    "date:inception_upper": "1980-01-01",
    "iso:country": "GB",
    "wof:name": "M18 7JG",
    "wof:placetype": "postalcode"
  },
  "geometry": {"coordinates":[-2.159757,53.455688],"type":"Point"}
}
