{
  "type": "Feature",
  "properties": {
    "iso:country":"GB",
    "wof:name":"M18 7JG",
    "wof:placetype":"postalcode"
},
  "geometry": {"coordinates":[-2.15975678424873,53.45568819700512],"type":"Point"}
}