{
  "type": "Feature",
  "properties": {
    "iso:country":"GB",
    "wof:name":"BN5 9AA",
    "wof:placetype":"postalcode"
},
  "geometry": {"coordinates":[-0.27481172371052,50.94424284560004],"type":"Point"}
}