{
  "type": "Feature",
  "properties": {
    "date:inception_lower": "2007-11-01",
    "date:inception_upper": "2007-11-01",
    "iso:country": "GB",
    "wof:name": "PO20 0QY",
    "wof:placetype": "postalcode"
  },
  "geometry": {"coordinates":[-0.792027,50.733056],"type":"Point"}
}
