{
  "type": "Feature",
  "properties": {
    "iso:country": "GB",
    "wof:name": "PO20 0QY",
    "wof:placetype": "postalcode"
  },
  "geometry": {"coordinates":[-0.792027,50.733056],"type":"Point"}
}
