{
  "type": "Feature",
  "properties": {
    "iso:country":"GB",
    "wof:name":"TR13 8QH",
    "wof:placetype":"postalcode"
},
  "geometry": {"coordinates":[-5.26815759209662,50.10605178528539],"type":"Point"}
}