{
  "type": "Feature",
  "properties": {
    "iso:country":"GB",
    "wof:name":"SE19 2RN",
    "wof:placetype":"postalcode"
},
  "geometry": {"coordinates":[-0.07635364544428,51.41252142317492],"type":"Point"}
}