{
  "type": "Feature",
  "properties": {
    "iso:country": "GB",
    "wof:name": "SE19 2RN",
    "wof:placetype": "postalcode"
  },
  "geometry": {"coordinates":[-0.076354,51.412521],"type":"Point"}
}
