{
  "type": "Feature",
  "properties": {
    "iso:country":"GB",
    "wof:name":"B47 6EL",
    "wof:placetype":"postalcode"
},
  "geometry": {"coordinates":[-1.88293645771968,52.37704953565842],"type":"Point"}
}