{
  "type": "Feature",
  "properties": {
    "date:inception_lower": "1980-01-01",
    "date:inception_upper": "1980-01-01",
    "iso:country": "GB",
    "wof:name": "B47 6EL",
    "wof:placetype": "postalcode"
  },
  "geometry": {"coordinates":[-1.882936,52.37705],"type":"Point"}
}
