{
  "type": "Feature",
  "properties": {
    "date:inception_lower": "1981-06-01",
    "date:inception_upper": "1981-06-01",
    "iso:country": "GB",
    "wof:name": "SL7 1NT",
    "wof:placetype": "postalcode"
  },
  "geometry": {"coordinates":[-0.767696,51.57153],"type":"Point"}
}
