{
  "type": "Feature",
  "properties": {
    "date:inception_lower": "1980-01-01",
    "date:inception_upper": "1980-01-01",
    "iso:country": "GB",
    "wof:name": "IP31 2RJ",
    "wof:placetype": "postalcode"
  },
  "geometry": {"coordinates":[0.770363,52.271807],"type":"Point"}
}
