{
  "type": "Feature",
  "properties": {
    "iso:country": "GB",
    "wof:name": "ST1 4DN",
    "wof:placetype": "postalcode"
  },
  "geometry": {"coordinates":[-2.180289,53.019189],"type":"Point"}
}
