{
  "type": "Feature",
  "properties": {
    "iso:country":"GB",
    "wof:name":"ST1 4DN",
    "wof:placetype":"postalcode"
},
  "geometry": {"coordinates":[-2.18028895911571,53.01918898628452],"type":"Point"}
}