{
  "type": "Feature",
  "properties": {
    "iso:country":"GB",
    "wof:name":"SR4 6JH",
    "wof:placetype":"postalcode"
},
  "geometry": {"coordinates":[-1.40904733986151,54.90559689069841],"type":"Point"}
}