{
  "type": "Feature",
  "properties": {
    "iso:country":"GB",
    "wof:name":"CW12 3TN",
    "wof:placetype":"postalcode"
},
  "geometry": {"coordinates":[-2.19278012906725,53.15912876760816],"type":"Point"}
}