{
  "type": "Feature",
  "properties": {
    "date:inception_lower": "1990-02-01",
    "date:inception_upper": "1990-02-01",
    "iso:country": "GB",
    "wof:name": "CW12 3TN",
    "wof:placetype": "postalcode"
  },
  "geometry": {"coordinates":[-2.19278,53.159129],"type":"Point"}
}
