{
  "type": "Feature",
  "properties": {
    "iso:country": "GB",
    "wof:name": "GU9 9FD",
    "wof:placetype": "postalcode"
  },
  "geometry": {"coordinates":[-0.782727,51.219669],"type":"Point"}
}
