{
  "type": "Feature",
  "properties": {
    "iso:country":"GB",
    "wof:name":"GU9 9FD",
    "wof:placetype":"postalcode"
},
  "geometry": {"coordinates":[-0.7826585343785,51.21967902978493],"type":"Point"}
}