{
  "type": "Feature",
  "properties": {
    "iso:country":"GB",
    "wof:name":"SR5 5AX",
    "wof:placetype":"postalcode"
},
  "geometry": {"coordinates":[-1.41447072715371,54.92522255363871],"type":"Point"}
}