{
  "type": "Feature",
  "properties": {
    "date:inception_lower": "2018-07-01",
    "date:inception_upper": "2018-07-01",
    "iso:country": "GB",
    "wof:name": "IP28 8ZG",
    "wof:placetype": "postalcode"
  },
  "geometry": {"coordinates":[0.497946,52.305547],"type":"Point"}
}
