{
  "type": "Feature",
  "properties": {
    "iso:country":"GB",
    "wof:name":"WV3 8JX",
    "wof:placetype":"postalcode"
},
  "geometry": {"coordinates":[-2.19403710552596,52.58075922136132],"type":"Point"}
}