{
  "type": "Feature",
  "properties": {
    "date:inception_lower":"1980-01-01",
    "date:inception_upper":"1980-01-31",
    "iso:country":"GB",
    "wof:name":"WV3 8JX",
    "wof:placetype":"postalcode"
},
  "geometry": {"coordinates":[-2.193899,52.580793],"type":"Point"}
}