{
  "type": "Feature",
  "properties": {
    "date:inception_lower": "1980-01-01",
    "date:inception_upper": "1980-01-01",
    "iso:country": "GB",
    "wof:name": "IG3 8LY",
    "wof:placetype": "postalcode"
  },
  "geometry": {"coordinates":[0.097959,51.567319],"type":"Point"}
}
