{
  "type": "Feature",
  "properties": {
    "iso:country":"GB",
    "wof:name":"IG3 8LY",
    "wof:placetype":"postalcode"
},
  "geometry": {"coordinates":[0.09795878044586,51.56731850733576],"type":"Point"}
}