{
  "type": "Feature",
  "properties": {
    "iso:country":"GB",
    "wof:name":"LL58 8NF",
    "wof:placetype":"postalcode"
},
  "geometry": {"coordinates":[-4.08801583016525,53.29362378509985],"type":"Point"}
}