{
  "type": "Feature",
  "properties": {
    "iso:country":"GB",
    "wof:name":"WN6 9HX",
    "wof:placetype":"postalcode"
},
  "geometry": {"coordinates":[-2.71188339683639,53.57697845517218],"type":"Point"}
}