{
  "type": "Feature",
  "properties": {
    "date:inception_lower": "1980-01-01",
    "date:inception_upper": "1980-01-01",
    "iso:country": "GB",
    "wof:name": "WN6 9HX",
    "wof:placetype": "postalcode"
  },
  "geometry": {"coordinates":[-2.711883,53.576978],"type":"Point"}
}
