{
  "type": "Feature",
  "properties": {
    "date:inception_lower":"2007-01-01",
    "date:inception_upper":"2007-01-31",
    "iso:country":"GB",
    "wof:name":"BD8 0BS",
    "wof:placetype":"postalcode"
},
  "geometry": {"coordinates":[-1.807849,53.798686],"type":"Point"}
}