{
  "type": "Feature",
  "properties": {
    "iso:country":"GB",
    "wof:name":"BD8 0BS",
    "wof:placetype":"postalcode"
},
  "geometry": {"coordinates":[-1.80784954469832,53.79868597851434],"type":"Point"}
}