{
  "type": "Feature",
  "properties": {
    "date:inception_lower":"1980-01-01",
    "date:inception_upper":"1980-01-31",
    "iso:country":"GB",
    "wof:name":"PA23 8DU",
    "wof:placetype":"postalcode"
},
  "geometry": {"coordinates":[-4.916515,55.959663],"type":"Point"}
}