{
  "type": "Feature",
  "properties": {
    "iso:country":"GB",
    "wof:name":"LN11 0XW",
    "wof:placetype":"postalcode"
},
  "geometry": {"coordinates":[-0.00627660930164,53.45958685219172],"type":"Point"}
}