{
  "type": "Feature",
  "properties": {
    "date:inception_lower": "1980-01-01",
    "date:inception_upper": "1980-01-01",
    "iso:country": "GB",
    "wof:name": "LN11 0XW",
    "wof:placetype": "postalcode"
  },
  "geometry": {"coordinates":[-0.00625,53.459621],"type":"Point"}
}
