{
  "type": "Feature",
  "properties": {
    "iso:country": "GB",
    "wof:name": "LN11 0XW",
    "wof:placetype": "postalcode"
  },
  "geometry": {"coordinates":[-0.008152,53.459841],"type":"Point"}
}
