{
  "type": "Feature",
  "properties": {
    "iso:country":"GB",
    "wof:name":"WS9 9LG",
    "wof:placetype":"postalcode"
},
  "geometry": {"coordinates":[-1.92802989562796,52.62420962554155],"type":"Point"}
}