{
  "type": "Feature",
  "properties": {
    "date:inception_lower": "1980-01-01",
    "date:inception_upper": "1980-01-01",
    "iso:country": "GB",
    "wof:name": "WS9 9LG",
    "wof:placetype": "postalcode"
  },
  "geometry": {"coordinates":[-1.92803,52.62421],"type":"Point"}
}
