{
  "type": "Feature",
  "properties": {
    "date:inception_lower":"2018-07-01",
    "date:inception_upper":"2018-07-31",
    "iso:country":"GB",
    "wof:name":"AB11 5QJ",
    "wof:placetype":"postalcode"
},
  "geometry": {"coordinates":[-2.096568,57.139889],"type":"Point"}
}