{
  "type": "Feature",
  "properties": {
    "iso:country": "GB",
    "wof:name": "AB11 5QJ",
    "wof:placetype": "postalcode"
  },
  "geometry": {"coordinates":[-2.096568,57.139889],"type":"Point"}
}
