{
  "type": "Feature",
  "properties": {
    "iso:country":"GB",
    "wof:name":"NR17 1UF",
    "wof:placetype":"postalcode"
},
  "geometry": {"coordinates":[0.93788808425727,52.53847353032393],"type":"Point"}
}