{
  "type": "Feature",
  "properties": {
    "iso:country":"GB",
    "wof:name":"LE16 7ND",
    "wof:placetype":"postalcode"
},
  "geometry": {"coordinates":[-0.92948317383475,52.48972162435392],"type":"Point"}
}