{
  "type": "Feature",
  "properties": {
    "iso:country": "GB",
    "wof:name": "LE16 7ND",
    "wof:placetype": "postalcode"
  },
  "geometry": {"coordinates":[-0.929483,52.489722],"type":"Point"}
}
