{
  "type": "Feature",
  "properties": {
    "date:inception_lower":"2004-02-01",
    "date:inception_upper":"2004-02-29",
    "iso:country":"GB",
    "wof:name":"LE16 7ND",
    "wof:placetype":"postalcode"
},
  "geometry": {"coordinates":[-0.929483,52.489722],"type":"Point"}
}