{
  "type": "Feature",
  "properties": {
    "iso:country": "GB",
    "wof:name": "SL6 2TD",
    "wof:placetype": "postalcode"
  },
  "geometry": {"coordinates":[-0.733427,51.510332],"type":"Point"}
}
