{
  "type": "Feature",
  "properties": {
    "iso:country":"GB",
    "wof:name":"SL6 2TD",
    "wof:placetype":"postalcode"
},
  "geometry": {"coordinates":[-0.7334274699835,51.51033158968365],"type":"Point"}
}