{
  "type": "Feature",
  "properties": {
    "iso:country":"GB",
    "wof:name":"BD14 6PZ",
    "wof:placetype":"postalcode"
},
  "geometry": {"coordinates":[-1.83720247821608,53.78534625456528],"type":"Point"}
}