{
  "type": "Feature",
  "properties": {
    "iso:country":"GB",
    "wof:name":"FK21 8RB",
    "wof:placetype":"postalcode"
},
  "geometry": {"coordinates":[-4.35841343242048,56.44086385106962],"type":"Point"}
}