{
  "type": "Feature",
  "properties": {
    "date:inception_lower": "1980-01-01",
    "date:inception_upper": "1980-01-01",
    "iso:country": "GB",
    "wof:name": "FK21 8RB",
    "wof:placetype": "postalcode"
  },
  "geometry": {"coordinates":[-4.358413,56.440864],"type":"Point"}
}
