{
  "type": "Feature",
  "properties": {
    "date:inception_lower":"1980-01-01",
    "date:inception_upper":"1980-01-31",
    "iso:country":"GB",
    "wof:name":"LS12 1RR",
    "wof:placetype":"postalcode"
},
  "geometry": {"coordinates":[-1.584608,53.794838],"type":"Point"}
}