{
  "type": "Feature",
  "properties": {
    "iso:country": "GB",
    "wof:name": "PO16 9NN",
    "wof:placetype": "postalcode"
  },
  "geometry": {"coordinates":[-1.126935,50.838292],"type":"Point"}
}
