{
  "type": "Feature",
  "properties": {
    "iso:country":"GB",
    "wof:name":"LU6 1LW",
    "wof:placetype":"postalcode"
},
  "geometry": {"coordinates":[-0.52880976366699,51.89200335465828],"type":"Point"}
}