{
  "type": "Feature",
  "properties": {
    "iso:country":"GB",
    "wof:name":"WN8 9AU",
    "wof:placetype":"postalcode"
},
  "geometry": {"coordinates":[-2.76455560666389,53.53643852805921],"type":"Point"}
}