{
  "type": "Feature",
  "properties": {
    "iso:country": "GB",
    "wof:name": "WN8 9AU",
    "wof:placetype": "postalcode"
  },
  "geometry": {"coordinates":[-2.764556,53.536439],"type":"Point"}
}
