{
  "type": "Feature",
  "properties": {
    "iso:country":"GB",
    "wof:name":"IP1 5HA",
    "wof:placetype":"postalcode"
},
  "geometry": {"coordinates":[1.12145561054788,52.07012487872064],"type":"Point"}
}