{
  "type": "Feature",
  "properties": {
    "iso:country": "GB",
    "wof:name": "IP1 5HA",
    "wof:placetype": "postalcode"
  },
  "geometry": {"coordinates":[1.121456,52.070125],"type":"Point"}
}
