{
  "type": "Feature",
  "properties": {
    "iso:country":"GB",
    "wof:name":"NE1 7AL",
    "wof:placetype":"postalcode"
},
  "geometry": {"coordinates":[-1.61336598825366,54.97420199145013],"type":"Point"}
}