{
  "type": "Feature",
  "properties": {
    "date:inception_lower": "1992-01-01",
    "date:inception_upper": "1992-01-01",
    "iso:country": "GB",
    "wof:name": "NE1 7AL",
    "wof:placetype": "postalcode"
  },
  "geometry": {"coordinates":[-1.612894,54.974306],"type":"Point"}
}
