{
  "type": "Feature",
  "properties": {
    "date:inception_lower": "1997-12-01",
    "date:inception_upper": "1997-12-01",
    "iso:country": "GB",
    "wof:name": "BS37 6HX",
    "wof:placetype": "postalcode"
  },
  "geometry": {"coordinates":[-2.399275,51.532797],"type":"Point"}
}
