{
  "type": "Feature",
  "properties": {
    "iso:country":"GB",
    "wof:name":"TS3 8NF",
    "wof:placetype":"postalcode"
},
  "geometry": {"coordinates":[-1.19410950463203,54.5639942599136],"type":"Point"}
}