{
  "type": "Feature",
  "properties": {
    "iso:country":"GB",
    "wof:name":"WV10 0NJ",
    "wof:placetype":"postalcode"
},
  "geometry": {"coordinates":[-2.10416948931368,52.60261886926859],"type":"Point"}
}