{
  "type": "Feature",
  "properties": {
    "date:inception_lower": "2004-01-01",
    "date:inception_upper": "2004-01-01",
    "iso:country": "GB",
    "wof:name": "N1 2EG",
    "wof:placetype": "postalcode"
  },
  "geometry": {"coordinates":[-0.090932,51.543647],"type":"Point"}
}
