{
  "type": "Feature",
  "properties": {
    "iso:country":"GB",
    "wof:name":"TW16 7SE",
    "wof:placetype":"postalcode"
},
  "geometry": {"coordinates":[-0.41399898002263,51.42458198708445],"type":"Point"}
}