{
  "type": "Feature",
  "properties": {
    "iso:country":"GB",
    "wof:name":"HP12 4SS",
    "wof:placetype":"postalcode"
},
  "geometry": {"coordinates":[-0.78683282452995,51.61763790335488],"type":"Point"}
}