{
  "type": "Feature",
  "properties": {
    "iso:country":"GB",
    "wof:name":"B71 4DJ",
    "wof:placetype":"postalcode"
},
  "geometry": {"coordinates":[-1.98607077564463,52.52948693110685],"type":"Point"}
}