{
  "type": "Feature",
  "properties": {
    "date:inception_lower": "1980-01-01",
    "date:inception_upper": "1980-01-01",
    "iso:country": "GB",
    "wof:name": "B71 4DJ",
    "wof:placetype": "postalcode"
  },
  "geometry": {"coordinates":[-1.986071,52.529487],"type":"Point"}
}
