{
  "type": "Feature",
  "properties": {
    "iso:country":"GB",
    "wof:name":"LE11 4QW",
    "wof:placetype":"postalcode"
},
  "geometry": {"coordinates":[-1.24323720339884,52.77885939281558],"type":"Point"}
}