{
  "type": "Feature",
  "properties": {
    "date:inception_lower": "2011-12-01",
    "date:inception_upper": "2011-12-01",
    "iso:country": "GB",
    "wof:name": "NP10 8FP",
    "wof:placetype": "postalcode"
  },
  "geometry": {"coordinates":[-3.046309,51.579675],"type":"Point"}
}
