{
  "type": "Feature",
  "properties": {
    "iso:country":"GB",
    "wof:name":"LE7 2AL",
    "wof:placetype":"postalcode"
},
  "geometry": {"coordinates":[-1.06453055600868,52.69461773321607],"type":"Point"}
}