{
  "type": "Feature",
  "properties": {
    "iso:country":"GB",
    "wof:name":"SA35 0BE",
    "wof:placetype":"postalcode"
},
  "geometry": {"coordinates":[-4.57596023733348,51.96703700361061],"type":"Point"}
}