{
  "type": "Feature",
  "properties": {
    "iso:country":"GB",
    "wof:name":"SN11 9AX",
    "wof:placetype":"postalcode"
},
  "geometry": {"coordinates":[-2.00254122135243,51.44573809496585],"type":"Point"}
}