{
  "type": "Feature",
  "properties": {
    "iso:country":"GB",
    "wof:name":"TW4 7PP",
    "wof:placetype":"postalcode"
},
  "geometry": {"coordinates":[-0.39664019505039,51.47217601240614],"type":"Point"}
}