{
  "type": "Feature",
  "properties": {
    "iso:country": "GB",
    "wof:name": "CF3 6AH",
    "wof:placetype": "postalcode"
  },
  "geometry": {"coordinates":[-3.128444,51.531636],"type":"Point"}
}
