{
  "type": "Feature",
  "properties": {
    "iso:country":"GB",
    "wof:name":"BS48 1QH",
    "wof:placetype":"postalcode"
},
  "geometry": {"coordinates":[-2.74768004130636,51.43315579188694],"type":"Point"}
}