{
  "type": "Feature",
  "properties": {
    "iso:country": "GB",
    "wof:name": "AB54 4NP",
    "wof:placetype": "postalcode"
  },
  "geometry": {"coordinates":[-2.764058,57.349127],"type":"Point"}
}
