{
  "type": "Feature",
  "properties": {
    "iso:country":"GB",
    "wof:name":"PO22 6QN",
    "wof:placetype":"postalcode"
},
  "geometry": {"coordinates":[-0.62918655381136,50.79839807572633],"type":"Point"}
}