{
  "type": "Feature",
  "properties": {
    "date:inception_lower": "1980-01-01",
    "date:inception_upper": "1980-01-01",
    "iso:country": "GB",
    "wof:name": "TA20 4HY",
    "wof:placetype": "postalcode"
  },
  "geometry": {"coordinates":[-2.888966,50.852412],"type":"Point"}
}
