{
  "type": "Feature",
  "properties": {
    "iso:country": "GB",
    "wof:name": "RG21 4AD",
    "wof:placetype": "postalcode"
  },
  "geometry": {"coordinates":[-1.082787,51.262835],"type":"Point"}
}
