{
  "type": "Feature",
  "properties": {
    "iso:country":"GB",
    "wof:name":"PH11 8NT",
    "wof:placetype":"postalcode"
},
  "geometry": {"coordinates":[-3.24927303978654,56.59416794124331],"type":"Point"}
}