{
  "type": "Feature",
  "properties": {
    "iso:country": "GB",
    "wof:name": "PH11 8NT",
    "wof:placetype": "postalcode"
  },
  "geometry": {"coordinates":[-3.249273,56.594168],"type":"Point"}
}
