{
  "type": "Feature",
  "properties": {
    "date:inception_lower": "1980-01-01",
    "date:inception_upper": "1980-01-01",
    "iso:country": "GB",
    "wof:name": "KY4 9AA",
    "wof:placetype": "postalcode"
  },
  "geometry": {"coordinates":[-3.342078,56.115831],"type":"Point"}
}
