{
  "type": "Feature",
  "properties": {
    "iso:country":"GB",
    "wof:name":"NG15 6EY",
    "wof:placetype":"postalcode"
},
  "geometry": {"coordinates":[-1.21645100359333,53.02848689994018],"type":"Point"}
}