{
  "type": "Feature",
  "properties": {
    "iso:country": "GB",
    "wof:name": "PR3 1NA",
    "wof:placetype": "postalcode"
  },
  "geometry": {"coordinates":[-2.786967,53.898051],"type":"Point"}
}
