{
  "type": "Feature",
  "properties": {
    "iso:country":"GB",
    "wof:name":"PR3 1NA",
    "wof:placetype":"postalcode"
},
  "geometry": {"coordinates":[-2.78697104823988,53.89803742021995],"type":"Point"}
}