{
  "type": "Feature",
  "properties": {
    "iso:country": "GB",
    "wof:name": "IP17 1GF",
    "wof:placetype": "postalcode"
  },
  "geometry": {"coordinates":[1.495947,52.214309],"type":"Point"}
}
