{
  "type": "Feature",
  "properties": {
    "date:inception_lower": "2022-09-01",
    "date:inception_upper": "2022-09-01",
    "iso:country": "GB",
    "wof:name": "LS17 9FG",
    "wof:placetype": "postalcode"
  },
  "geometry": {"coordinates":[-1.534785,53.918518],"type":"Point"}
}
