{
  "type": "Feature",
  "properties": {
    "iso:country": "GB",
    "wof:name": "LS14 9HE",
    "wof:placetype": "postalcode"
  },
  "geometry": {"coordinates":[-1.456779,53.82718],"type":"Point"}
}
