{
  "type": "Feature",
  "properties": {
    "iso:country":"GB",
    "wof:name":"PO12 1JY",
    "wof:placetype":"postalcode"
},
  "geometry": {"coordinates":[-1.13301585440363,50.79521695923387],"type":"Point"}
}