{
  "type": "Feature",
  "properties": {
    "iso:country": "GB",
    "wof:name": "PO12 1JY",
    "wof:placetype": "postalcode"
  },
  "geometry": {"coordinates":[-1.133016,50.795217],"type":"Point"}
}
