{
  "type": "Feature",
  "properties": {
    "iso:country": "GB",
    "wof:name": "GU51 5BH",
    "wof:placetype": "postalcode"
  },
  "geometry": {"coordinates":[-0.865404,51.282673],"type":"Point"}
}
