{
  "type": "Feature",
  "properties": {
    "date:inception_lower":"2011-03-01",
    "date:inception_upper":"2011-03-31",
    "iso:country":"GB",
    "wof:name":"GU51 5BH",
    "wof:placetype":"postalcode"
},
  "geometry": {"coordinates":[-0.865404,51.282673],"type":"Point"}
}