{
  "type": "Feature",
  "properties": {
    "iso:country":"GB",
    "wof:name":"GU51 5BH",
    "wof:placetype":"postalcode"
},
  "geometry": {"coordinates":[-0.86515220429983,51.28250933108054],"type":"Point"}
}