{
  "type": "Feature",
  "properties": {
    "iso:country":"GB",
    "wof:name":"DY4 7AY",
    "wof:placetype":"postalcode"
},
  "geometry": {"coordinates":[-2.03315318505734,52.53053481908715],"type":"Point"}
}