{
  "type": "Feature",
  "properties": {
    "iso:country":"GB",
    "wof:name":"EX1 3UF",
    "wof:placetype":"postalcode"
},
  "geometry": {"coordinates":[-3.46282298577409,50.73989751512995],"type":"Point"}
}