{
  "type": "Feature",
  "properties": {
    "date:inception_lower":"1990-02-01",
    "date:inception_upper":"1990-02-28",
    "iso:country":"GB",
    "wof:name":"EX1 3UF",
    "wof:placetype":"postalcode"
},
  "geometry": {"coordinates":[-3.462823,50.739898],"type":"Point"}
}