{
  "type": "Feature",
  "properties": {
    "iso:country": "GB",
    "wof:name": "EX1 3UF",
    "wof:placetype": "postalcode"
  },
  "geometry": {"coordinates":[-3.462823,50.739898],"type":"Point"}
}
