{
  "type": "Feature",
  "properties": {
    "iso:country":"GB",
    "wof:name":"HA8 5RP",
    "wof:placetype":"postalcode"
},
  "geometry": {"coordinates":[-0.27825462566137,51.60130880145902],"type":"Point"}
}