{
  "type": "Feature",
  "properties": {
    "iso:country":"GB",
    "wof:name":"SE6 4JR",
    "wof:placetype":"postalcode"
},
  "geometry": {"coordinates":[-0.02074803928838,51.44738664869661],"type":"Point"}
}