{
  "type": "Feature",
  "properties": {
    "date:inception_lower": "2001-06-01",
    "date:inception_upper": "2001-06-01",
    "iso:country": "GB",
    "wof:name": "RH10 8DS",
    "wof:placetype": "postalcode"
  },
  "geometry": {"coordinates":[-0.182035,51.121201],"type":"Point"}
}
