{
  "type": "Feature",
  "properties": {
    "iso:country":"GB",
    "wof:name":"KA12 8HS",
    "wof:placetype":"postalcode"
},
  "geometry": {"coordinates":[-4.66164635118989,55.60219573284152],"type":"Point"}
}