{
  "type": "Feature",
  "properties": {
    "iso:country": "GB",
    "wof:name": "SK17 0AL",
    "wof:placetype": "postalcode"
  },
  "geometry": {"coordinates":[-1.809405,53.140598],"type":"Point"}
}
