{
  "type": "Feature",
  "properties": {
    "iso:country":"GB",
    "wof:name":"SK17 0AL",
    "wof:placetype":"postalcode"
},
  "geometry": {"coordinates":[-1.80940466209256,53.14059791571212],"type":"Point"}
}