{
  "type": "Feature",
  "properties": {
    "date:inception_lower": "2013-12-01",
    "date:inception_upper": "2013-12-01",
    "iso:country": "GB",
    "wof:name": "WS3 2DH",
    "wof:placetype": "postalcode"
  },
  "geometry": {"coordinates":[-2.01557,52.621372],"type":"Point"}
}
