{
  "type": "Feature",
  "properties": {
    "iso:country":"GB",
    "wof:name":"SN16 0RN",
    "wof:placetype":"postalcode"
},
  "geometry": {"coordinates":[-2.09978044740193,51.58290489266525],"type":"Point"}
}