{
  "type": "Feature",
  "properties": {
    "date:inception_lower": "1994-05-01",
    "date:inception_upper": "1994-05-01",
    "iso:country": "GB",
    "wof:name": "SN16 0RN",
    "wof:placetype": "postalcode"
  },
  "geometry": {"coordinates":[-2.09978,51.582905],"type":"Point"}
}
