{
  "type": "Feature",
  "properties": {
    "iso:country": "GB",
    "wof:name": "EH51 0EZ",
    "wof:placetype": "postalcode"
  },
  "geometry": {"coordinates":[-3.619762,56.010933],"type":"Point"}
}
