{
  "type": "Feature",
  "properties": {
    "iso:country": "GB",
    "wof:name": "CA28 7SA",
    "wof:placetype": "postalcode"
  },
  "geometry": {"coordinates":[-3.577871,54.544996],"type":"Point"}
}
