{
  "type": "Feature",
  "properties": {
    "iso:country": "GB",
    "wof:name": "SA19 6RZ",
    "wof:placetype": "postalcode"
  },
  "geometry": {"coordinates":[-3.997607,51.887805],"type":"Point"}
}
