{
  "type": "Feature",
  "properties": {
    "iso:country":"GB",
    "wof:name":"SA19 6RZ",
    "wof:placetype":"postalcode"
},
  "geometry": {"coordinates":[-3.99760663991297,51.88780482997766],"type":"Point"}
}