{
  "type": "Feature",
  "properties": {
    "iso:country":"GB",
    "wof:name":"B70 7RP",
    "wof:placetype":"postalcode"
},
  "geometry": {"coordinates":[-1.99689142095992,52.51380032043816],"type":"Point"}
}