{
  "type": "Feature",
  "properties": {
    "iso:country": "GB",
    "wof:name": "BB4 6EL",
    "wof:placetype": "postalcode"
  },
  "geometry": {"coordinates":[-2.297766,53.692509],"type":"Point"}
}
