{
  "type": "Feature",
  "properties": {
    "iso:country":"GB",
    "wof:name":"BB4 6EL",
    "wof:placetype":"postalcode"
},
  "geometry": {"coordinates":[-2.29776575870369,53.69250882794304],"type":"Point"}
}