{
  "type": "Feature",
  "properties": {
    "iso:country":"GB",
    "wof:name":"DY4 0RS",
    "wof:placetype":"postalcode"
},
  "geometry": {"coordinates":[-2.05374335026987,52.54010143174371],"type":"Point"}
}