{
  "type": "Feature",
  "properties": {
    "date:inception_lower": "1983-01-01",
    "date:inception_upper": "1983-01-01",
    "iso:country": "GB",
    "wof:name": "WS11 1UE",
    "wof:placetype": "postalcode"
  },
  "geometry": {"coordinates":[-2.032041,52.690407],"type":"Point"}
}
