{
  "type": "Feature",
  "properties": {
    "iso:country":"GB",
    "wof:name":"PE13 3UG",
    "wof:placetype":"postalcode"
},
  "geometry": {"coordinates":[0.18042377040212,52.67010893152115],"type":"Point"}
}