{
  "type": "Feature",
  "properties": {
    "iso:country":"GB",
    "wof:name":"CB23 6AX",
    "wof:placetype":"postalcode"
},
  "geometry": {"coordinates":[-0.05469623596379,52.21899758791036],"type":"Point"}
}