{
  "type": "Feature",
  "properties": {
    "iso:country": "GB",
    "wof:name": "BL1 5BF",
    "wof:placetype": "postalcode"
  },
  "geometry": {"coordinates":[-2.465701,53.579],"type":"Point"}
}
