{
  "type": "Feature",
  "properties": {
    "iso:country":"GB",
    "wof:name":"CR0 8HW",
    "wof:placetype":"postalcode"
},
  "geometry": {"coordinates":[-0.02828862262458,51.37487006808313],"type":"Point"}
}