{
  "type": "Feature",
  "properties": {
    "iso:country":"GB",
    "wof:name":"PL14 5LE",
    "wof:placetype":"postalcode"
},
  "geometry": {"coordinates":[-4.45308080129131,50.5143746882972],"type":"Point"}
}