{
  "type": "Feature",
  "properties": {
    "iso:country": "GB",
    "wof:name": "PL14 5LE",
    "wof:placetype": "postalcode"
  },
  "geometry": {"coordinates":[-4.453081,50.514375],"type":"Point"}
}
