{
  "type": "Feature",
  "properties": {
    "date:inception_lower": "2003-01-01",
    "date:inception_upper": "2003-01-01",
    "iso:country": "GB",
    "wof:name": "LS15 8SJ",
    "wof:placetype": "postalcode"
  },
  "geometry": {"coordinates":[-1.442069,53.815636],"type":"Point"}
}
