{
  "type": "Feature",
  "properties": {
    "iso:country": "GB",
    "wof:name": "LS15 8SJ",
    "wof:placetype": "postalcode"
  },
  "geometry": {"coordinates":[-1.442069,53.815636],"type":"Point"}
}
