{
  "type": "Feature",
  "properties": {
    "date:inception_lower": "1983-01-01",
    "date:inception_upper": "1983-01-01",
    "iso:country": "GB",
    "wof:name": "LS10 4RD",
    "wof:placetype": "postalcode"
  },
  "geometry": {"coordinates":[-1.519732,53.74609],"type":"Point"}
}
