{
  "type": "Feature",
  "properties": {
    "iso:country": "GB",
    "wof:name": "LA15 8LL",
    "wof:placetype": "postalcode"
  },
  "geometry": {"coordinates":[-3.184438,54.154739],"type":"Point"}
}
