{
  "type": "Feature",
  "properties": {
    "iso:country":"GB",
    "wof:name":"B90 1DU",
    "wof:placetype":"postalcode"
},
  "geometry": {"coordinates":[-1.85289513044501,52.39494231114511],"type":"Point"}
}