{
  "type": "Feature",
  "properties": {
    "iso:country":"GB",
    "wof:name":"NR3 2QG",
    "wof:placetype":"postalcode"
},
  "geometry": {"coordinates":[1.27556779957933,52.65255534953015],"type":"Point"}
}