{
  "type": "Feature",
  "properties": {
    "iso:country":"GB",
    "wof:name":"LE65 1TD",
    "wof:placetype":"postalcode"
},
  "geometry": {"coordinates":[-1.46559641046964,52.73170447142405],"type":"Point"}
}