{
  "type": "Feature",
  "properties": {
    "iso:country": "GB",
    "wof:name": "LE65 1TD",
    "wof:placetype": "postalcode"
  },
  "geometry": {"coordinates":[-1.465596,52.731704],"type":"Point"}
}
