{
  "type": "Feature",
  "properties": {
    "date:inception_lower": "1992-08-01",
    "date:inception_upper": "1992-08-01",
    "iso:country": "GB",
    "wof:name": "LE65 1TD",
    "wof:placetype": "postalcode"
  },
  "geometry": {"coordinates":[-1.465596,52.731704],"type":"Point"}
}
