{
  "type": "Feature",
  "properties": {
    "iso:country":"GB",
    "wof:name":"NG24 3WR",
    "wof:placetype":"postalcode"
},
  "geometry": {"coordinates":[-0.79067241605223,53.05406526933901],"type":"Point"}
}