{
  "type": "Feature",
  "properties": {
    "date:inception_lower": "2010-11-01",
    "date:inception_upper": "2010-11-01",
    "iso:country": "GB",
    "wof:name": "NG24 3WR",
    "wof:placetype": "postalcode"
  },
  "geometry": {"coordinates":[-0.790615,53.054391],"type":"Point"}
}
