{
  "type": "Feature",
  "properties": {
    "date:inception_lower": "1998-06-01",
    "date:inception_upper": "1998-06-01",
    "iso:country": "GB",
    "wof:name": "YO19 6SH",
    "wof:placetype": "postalcode"
  },
  "geometry": {"coordinates":[-1.101594,53.861495],"type":"Point"}
}
