{
  "type": "Feature",
  "properties": {
    "iso:country":"GB",
    "wof:name":"YO19 6SH",
    "wof:placetype":"postalcode"
},
  "geometry": {"coordinates":[-1.10159435468059,53.86149504097007],"type":"Point"}
}