{
  "type": "Feature",
  "properties": {
    "date:inception_lower":"1992-01-01",
    "date:inception_upper":"1992-01-31",
    "iso:country":"GB",
    "wof:name":"LS21 3NX",
    "wof:placetype":"postalcode"
},
  "geometry": {"coordinates":[-1.69283,53.905265],"type":"Point"}
}