{
  "type": "Feature",
  "properties": {
    "iso:country":"GB",
    "wof:name":"PR7 1XH",
    "wof:placetype":"postalcode"
},
  "geometry": {"coordinates":[-2.63859183333481,53.66423807962617],"type":"Point"}
}