{
  "type": "Feature",
  "properties": {
    "iso:country":"GB",
    "wof:name":"S70 4NW",
    "wof:placetype":"postalcode"
},
  "geometry": {"coordinates":[-1.47344379560272,53.54640001061006],"type":"Point"}
}