{
  "type": "Feature",
  "properties": {
    "date:inception_lower": "1980-01-01",
    "date:inception_upper": "1980-01-01",
    "iso:country": "GB",
    "wof:name": "S70 4NW",
    "wof:placetype": "postalcode"
  },
  "geometry": {"coordinates":[-1.473444,53.5464],"type":"Point"}
}
