{
  "type": "Feature",
  "properties": {
    "iso:country": "GB",
    "wof:name": "CB21 5NH",
    "wof:placetype": "postalcode"
  },
  "geometry": {"coordinates":[0.33874,52.145609],"type":"Point"}
}
