{
  "type": "Feature",
  "properties": {
    "iso:country":"GB",
    "wof:name":"CB21 5NH",
    "wof:placetype":"postalcode"
},
  "geometry": {"coordinates":[0.33873997318884,52.14560872671534],"type":"Point"}
}