{
  "type": "Feature",
  "properties": {
    "iso:country":"GB",
    "wof:name":"ZE2 9PN",
    "wof:placetype":"postalcode"
},
  "geometry": {"coordinates":[-2.05524804740701,60.1338471344448],"type":"Point"}
}