{
  "type": "Feature",
  "properties": {
    "date:inception_lower": "1980-01-01",
    "date:inception_upper": "1980-01-01",
    "iso:country": "GB",
    "wof:name": "ZE2 9PN",
    "wof:placetype": "postalcode"
  },
  "geometry": {"coordinates":[-2.054491,60.133665],"type":"Point"}
}
