{
  "type": "Feature",
  "properties": {
    "iso:country":"GB",
    "wof:name":"SO40 2LN",
    "wof:placetype":"postalcode"
},
  "geometry": {"coordinates":[-1.56753159407548,50.91004241630292],"type":"Point"}
}