{
  "type": "Feature",
  "properties": {
    "iso:country": "GB",
    "wof:name": "SO40 2LN",
    "wof:placetype": "postalcode"
  },
  "geometry": {"coordinates":[-1.56758,50.909999],"type":"Point"}
}
