{
  "type": "Feature",
  "properties": {
    "date:inception_lower": "2004-05-01",
    "date:inception_upper": "2004-05-01",
    "iso:country": "GB",
    "wof:name": "N8 0AF",
    "wof:placetype": "postalcode"
  },
  "geometry": {"coordinates":[-0.102054,51.584483],"type":"Point"}
}
