{
  "type": "Feature",
  "properties": {
    "iso:country":"GB",
    "wof:name":"N8 0AF",
    "wof:placetype":"postalcode"
},
  "geometry": {"coordinates":[-0.10205379102731,51.58448275297147],"type":"Point"}
}