{
  "type": "Feature",
  "properties": {
    "iso:country":"GB",
    "wof:name":"S11 8AN",
    "wof:placetype":"postalcode"
},
  "geometry": {"coordinates":[-1.48229878696935,53.36708956875876],"type":"Point"}
}