{
  "type": "Feature",
  "properties": {
    "iso:country":"GB",
    "wof:name":"TQ10 9ET",
    "wof:placetype":"postalcode"
},
  "geometry": {"coordinates":[-3.81514609754793,50.41150966440189],"type":"Point"}
}