{
  "type": "Feature",
  "properties": {
    "date:inception_lower": "1995-01-01",
    "date:inception_upper": "1995-01-01",
    "iso:country": "GB",
    "wof:name": "NW2 6YY",
    "wof:placetype": "postalcode"
  },
  "geometry": {"coordinates":[-0.223174,51.563017],"type":"Point"}
}
