{
  "type": "Feature",
  "properties": {
    "iso:country":"GB",
    "wof:name":"NW2 6YY",
    "wof:placetype":"postalcode"
},
  "geometry": {"coordinates":[-0.2231740675658,51.56301695181556],"type":"Point"}
}