{
  "type": "Feature",
  "properties": {
    "iso:country":"GB",
    "wof:name":"DE75 7TT",
    "wof:placetype":"postalcode"
},
  "geometry": {"coordinates":[-1.34113087559544,53.01197414579223],"type":"Point"}
}