{
  "type": "Feature",
  "properties": {
    "iso:country":"GB",
    "wof:name":"TS16 9BG",
    "wof:placetype":"postalcode"
},
  "geometry": {"coordinates":[-1.34776193359093,54.52788415891281],"type":"Point"}
}