{
  "type": "Feature",
  "properties": {
    "iso:country": "GB",
    "wof:name": "TS16 9BG",
    "wof:placetype": "postalcode"
  },
  "geometry": {"coordinates":[-1.347762,54.527884],"type":"Point"}
}
