{
  "type": "Feature",
  "properties": {
    "iso:country": "GB",
    "wof:name": "EX23 9RX",
    "wof:placetype": "postalcode"
  },
  "geometry": {"coordinates":[-4.477261,50.871991],"type":"Point"}
}
