{
  "type": "Feature",
  "properties": {
    "iso:country":"GB",
    "wof:name":"EX23 9RX",
    "wof:placetype":"postalcode"
},
  "geometry": {"coordinates":[-4.47726116957866,50.8719911066998],"type":"Point"}
}