{
  "type": "Feature",
  "properties": {
    "iso:country":"GB",
    "wof:name":"YO61 1QJ",
    "wof:placetype":"postalcode"
},
  "geometry": {"coordinates":[-1.22959461836874,54.06559335694832],"type":"Point"}
}