{
  "type": "Feature",
  "properties": {
    "iso:country":"GB",
    "wof:name":"HG4 4NX",
    "wof:placetype":"postalcode"
},
  "geometry": {"coordinates":[-1.66151741551069,54.23235049222899],"type":"Point"}
}