{
  "type": "Feature",
  "properties": {
    "date:inception_lower":"1999-12-01",
    "date:inception_upper":"1999-12-31",
    "iso:country":"GB",
    "wof:name":"TR27 5AT",
    "wof:placetype":"postalcode"
},
  "geometry": {"coordinates":[-5.424489,50.195752],"type":"Point"}
}