{
  "type": "Feature",
  "properties": {
    "iso:country":"GB",
    "wof:name":"WC2N 4LE",
    "wof:placetype":"postalcode"
},
  "geometry": {"coordinates":[-0.12625688170656,51.51120532775571],"type":"Point"}
}