{
  "type": "Feature",
  "properties": {
    "iso:country":"GB",
    "wof:name":"NW11 6PA",
    "wof:placetype":"postalcode"
},
  "geometry": {"coordinates":[-0.18496046424171,51.58389687043662],"type":"Point"}
}