{
  "type": "Feature",
  "properties": {
    "date:inception_lower":"1980-01-01",
    "date:inception_upper":"1980-01-31",
    "iso:country":"GB",
    "wof:name":"NW11 6PA",
    "wof:placetype":"postalcode"
},
  "geometry": {"coordinates":[-0.18496,51.583897],"type":"Point"}
}