{
  "type": "Feature",
  "properties": {
    "iso:country":"GB",
    "wof:name":"CM0 7RJ",
    "wof:placetype":"postalcode"
},
  "geometry": {"coordinates":[0.79805270265275,51.69175955056212],"type":"Point"}
}