{
  "type": "Feature",
  "properties": {
    "iso:country": "GB",
    "wof:name": "CM0 7RJ",
    "wof:placetype": "postalcode"
  },
  "geometry": {"coordinates":[0.798053,51.69176],"type":"Point"}
}
