{
  "type": "Feature",
  "properties": {
    "date:inception_lower": "1980-01-01",
    "date:inception_upper": "1980-01-01",
    "iso:country": "GB",
    "wof:name": "CM0 7RJ",
    "wof:placetype": "postalcode"
  },
  "geometry": {"coordinates":[0.798053,51.69176],"type":"Point"}
}
