{
  "type": "Feature",
  "properties": {
    "iso:country":"GB",
    "wof:name":"LA3 2AZ",
    "wof:placetype":"postalcode"
},
  "geometry": {"coordinates":[-2.89212262632424,54.05318118138073],"type":"Point"}
}