{
  "type": "Feature",
  "properties": {
    "iso:country":"GB",
    "wof:name":"DT3 6SD",
    "wof:placetype":"postalcode"
},
  "geometry": {"coordinates":[-2.42215534953797,50.6489053276778],"type":"Point"}
}