{
  "type": "Feature",
  "properties": {
    "date:inception_lower": "1980-01-01",
    "date:inception_upper": "1980-01-01",
    "iso:country": "GB",
    "wof:name": "GU12 4JF",
    "wof:placetype": "postalcode"
  },
  "geometry": {"coordinates":[-0.75615,51.246377],"type":"Point"}
}
