{
  "type": "Feature",
  "properties": {
    "iso:country":"GB",
    "wof:name":"GU12 4JF",
    "wof:placetype":"postalcode"
},
  "geometry": {"coordinates":[-0.75615009000905,51.24637731777815],"type":"Point"}
}