{
  "type": "Feature",
  "properties": {
    "iso:country": "GB",
    "wof:name": "GU12 4JF",
    "wof:placetype": "postalcode"
  },
  "geometry": {"coordinates":[-0.75615,51.246377],"type":"Point"}
}
