{
  "type": "Feature",
  "properties": {
    "iso:country":"GB",
    "wof:name":"IP7 5HW",
    "wof:placetype":"postalcode"
},
  "geometry": {"coordinates":[0.96294437545148,52.04380323308976],"type":"Point"}
}