{
  "type": "Feature",
  "properties": {
    "date:inception_lower": "2024-09-01",
    "date:inception_upper": "2024-09-01",
    "iso:country": "GB",
    "wof:name": "IG10 3JY",
    "wof:placetype": "postalcode"
  },
  "geometry": {"coordinates":[0.067878,51.647251],"type":"Point"}
}
