{
  "type": "Feature",
  "properties": {
    "iso:country":"GB",
    "wof:name":"YO30 7BN",
    "wof:placetype":"postalcode"
},
  "geometry": {"coordinates":[-1.08508849710319,53.96288234626505],"type":"Point"}
}