{
  "type": "Feature",
  "properties": {
    "iso:country":"GB",
    "wof:name":"PO18 0DD",
    "wof:placetype":"postalcode"
},
  "geometry": {"coordinates":[-0.77912125667523,50.88431778697608],"type":"Point"}
}