{
  "type": "Feature",
  "properties": {
    "date:inception_lower":"2012-05-01",
    "date:inception_upper":"2012-05-31",
    "iso:country":"GB",
    "wof:name":"PO18 0DD",
    "wof:placetype":"postalcode"
},
  "geometry": {"coordinates":[-0.779121,50.884318],"type":"Point"}
}