{
  "type": "Feature",
  "properties": {
    "iso:country": "GB",
    "wof:name": "PO18 0DD",
    "wof:placetype": "postalcode"
  },
  "geometry": {"coordinates":[-0.779121,50.884318],"type":"Point"}
}
