{
  "type": "Feature",
  "properties": {
    "iso:country":"GB",
    "wof:name":"S21 4HF",
    "wof:placetype":"postalcode"
},
  "geometry": {"coordinates":[-1.37529011638142,53.30894153434773],"type":"Point"}
}