{
  "type": "Feature",
  "properties": {
    "iso:country": "GB",
    "wof:name": "S21 4HF",
    "wof:placetype": "postalcode"
  },
  "geometry": {"coordinates":[-1.37529,53.308942],"type":"Point"}
}
