{
  "type": "Feature",
  "properties": {
    "date:inception_lower":"1997-06-01",
    "date:inception_upper":"1997-06-30",
    "iso:country":"GB",
    "wof:name":"S21 4HF",
    "wof:placetype":"postalcode"
},
  "geometry": {"coordinates":[-1.37529,53.308942],"type":"Point"}
}