{
  "type": "Feature",
  "properties": {
    "iso:country":"GB",
    "wof:name":"IP4 1NR",
    "wof:placetype":"postalcode"
},
  "geometry": {"coordinates":[1.16891707136515,52.05592398963987],"type":"Point"}
}