{
  "type": "Feature",
  "properties": {
    "iso:country": "GB",
    "wof:name": "GU30 7UZ",
    "wof:placetype": "postalcode"
  },
  "geometry": {"coordinates":[-0.792257,51.08236],"type":"Point"}
}
