{
  "type": "Feature",
  "properties": {
    "iso:country":"GB",
    "wof:name":"LS29 7BA",
    "wof:placetype":"postalcode"
},
  "geometry": {"coordinates":[-1.77408462406709,53.89761095255687],"type":"Point"}
}