{
  "type": "Feature",
  "properties": {
    "iso:country":"GB",
    "wof:name":"BD6 3AH",
    "wof:placetype":"postalcode"
},
  "geometry": {"coordinates":[-1.78375157486811,53.77287642749759],"type":"Point"}
}