{
  "type": "Feature",
  "properties": {
    "iso:country":"GB",
    "wof:name":"BD2 1HL",
    "wof:placetype":"postalcode"
},
  "geometry": {"coordinates":[-1.73799865700137,53.82277644448043],"type":"Point"}
}