{
  "type": "Feature",
  "properties": {
    "iso:country": "GB",
    "wof:name": "GU21 5AP",
    "wof:placetype": "postalcode"
  },
  "geometry": {"coordinates":[-0.555762,51.319432],"type":"Point"}
}
