{
  "type": "Feature",
  "properties": {
    "iso:country":"GB",
    "wof:name":"M7 3WZ",
    "wof:placetype":"postalcode"
},
  "geometry": {"coordinates":[-2.27270145945363,53.51653315054111],"type":"Point"}
}