{
  "type": "Feature",
  "properties": {
    "iso:country": "GB",
    "wof:name": "M7 3WZ",
    "wof:placetype": "postalcode"
  },
  "geometry": {"coordinates":[-2.272701,53.516533],"type":"Point"}
}
