{
  "type": "Feature",
  "properties": {
    "date:inception_lower":"1980-01-01",
    "date:inception_upper":"1980-01-31",
    "iso:country":"GB",
    "wof:name":"DY4 9JZ",
    "wof:placetype":"postalcode"
},
  "geometry": {"coordinates":[-2.066531,52.543026],"type":"Point"}
}