{
  "type": "Feature",
  "properties": {
    "iso:country":"GB",
    "wof:name":"DY4 9JZ",
    "wof:placetype":"postalcode"
},
  "geometry": {"coordinates":[-2.06653100975805,52.54302560337523],"type":"Point"}
}