{
  "type": "Feature",
  "properties": {
    "iso:country": "GB",
    "wof:name": "CM15 0EQ",
    "wof:placetype": "postalcode"
  },
  "geometry": {"coordinates":[0.290356,51.681294],"type":"Point"}
}
