{
  "type": "Feature",
  "properties": {
    "date:inception_lower": "1980-01-01",
    "date:inception_upper": "1980-01-01",
    "iso:country": "GB",
    "wof:name": "CM15 0EQ",
    "wof:placetype": "postalcode"
  },
  "geometry": {"coordinates":[0.290356,51.681294],"type":"Point"}
}
