{
  "type": "Feature",
  "properties": {
    "iso:country":"GB",
    "wof:name":"CM15 0EQ",
    "wof:placetype":"postalcode"
},
  "geometry": {"coordinates":[0.29035641787462,51.68129360491537],"type":"Point"}
}