{
  "type": "Feature",
  "properties": {
    "iso:country":"GB",
    "wof:name":"NR30 2DW",
    "wof:placetype":"postalcode"
},
  "geometry": {"coordinates":[1.73375524446458,52.60953995643131],"type":"Point"}
}