{
  "type": "Feature",
  "properties": {
    "date:inception_lower": "1980-01-01",
    "date:inception_upper": "1980-01-01",
    "iso:country": "GB",
    "wof:name": "FY3 8PQ",
    "wof:placetype": "postalcode"
  },
  "geometry": {"coordinates":[-3.021261,53.825625],"type":"Point"}
}
