{
  "type": "Feature",
  "properties": {
    "iso:country":"GB",
    "wof:name":"FY3 8PQ",
    "wof:placetype":"postalcode"
},
  "geometry": {"coordinates":[-3.02126123279696,53.82562456365536],"type":"Point"}
}