{
  "type": "Feature",
  "properties": {
    "iso:country":"GB",
    "wof:name":"DN8 4HZ",
    "wof:placetype":"postalcode"
},
  "geometry": {"coordinates":[-0.97233056525662,53.61607028454618],"type":"Point"}
}