{
  "type": "Feature",
  "properties": {
    "iso:country": "GB",
    "wof:name": "DN8 4HZ",
    "wof:placetype": "postalcode"
  },
  "geometry": {"coordinates":[-0.972289,53.616117],"type":"Point"}
}
