{
  "type": "Feature",
  "properties": {
    "iso:country": "GB",
    "wof:name": "TS4 3BU",
    "wof:placetype": "postalcode"
  },
  "geometry": {"coordinates":[-1.220329,54.553175],"type":"Point"}
}
