{
  "type": "Feature",
  "properties": {
    "iso:country":"GB",
    "wof:name":"TS4 3BU",
    "wof:placetype":"postalcode"
},
  "geometry": {"coordinates":[-1.22032876895195,54.55317477641756],"type":"Point"}
}