{
  "type": "Feature",
  "properties": {
    "date:inception_lower": "1999-12-01",
    "date:inception_upper": "1999-12-01",
    "iso:country": "GB",
    "wof:name": "SK11 0SD",
    "wof:placetype": "postalcode"
  },
  "geometry": {"coordinates":[-2.094569,53.159787],"type":"Point"}
}
