{
  "type": "Feature",
  "properties": {
    "iso:country": "GB",
    "wof:name": "SK11 0SD",
    "wof:placetype": "postalcode"
  },
  "geometry": {"coordinates":[-2.094569,53.159787],"type":"Point"}
}
