{
  "type": "Feature",
  "properties": {
    "iso:country":"GB",
    "wof:name":"SP3 5PF",
    "wof:placetype":"postalcode"
},
  "geometry": {"coordinates":[-2.04937361021448,51.04271246777364],"type":"Point"}
}