{
  "type": "Feature",
  "properties": {
    "date:inception_lower": "1980-01-01",
    "date:inception_upper": "1980-01-01",
    "iso:country": "GB",
    "wof:name": "S1 4QA",
    "wof:placetype": "postalcode"
  },
  "geometry": {"coordinates":[-1.472022,53.376591],"type":"Point"}
}
