{
  "type": "Feature",
  "properties": {
    "iso:country":"GB",
    "wof:name":"SE5 0NL",
    "wof:placetype":"postalcode"
},
  "geometry": {"coordinates":[-0.09980138712245,51.48132000745984],"type":"Point"}
}