{
  "type": "Feature",
  "properties": {
    "iso:country": "GB",
    "wof:name": "SE5 0NL",
    "wof:placetype": "postalcode"
  },
  "geometry": {"coordinates":[-0.099801,51.48132],"type":"Point"}
}
