{
  "type": "Feature",
  "properties": {
    "date:inception_lower": "2006-10-01",
    "date:inception_upper": "2006-10-01",
    "iso:country": "GB",
    "wof:name": "DT1 1TF",
    "wof:placetype": "postalcode"
  },
  "geometry": {"coordinates":[-2.444275,50.714767],"type":"Point"}
}
