{
  "type": "Feature",
  "properties": {
    "iso:country": "GB",
    "wof:name": "DT1 1TF",
    "wof:placetype": "postalcode"
  },
  "geometry": {"coordinates":[-2.444601,50.714837],"type":"Point"}
}
