{
  "type": "Feature",
  "properties": {
    "iso:country":"GB",
    "wof:name":"B29 7PU",
    "wof:placetype":"postalcode"
},
  "geometry": {"coordinates":[-1.91606363687333,52.43836294065221],"type":"Point"}
}