{
  "type": "Feature",
  "properties": {
    "date:inception_lower": "2018-07-01",
    "date:inception_upper": "2018-07-01",
    "iso:country": "GB",
    "wof:name": "PH3 1FA",
    "wof:placetype": "postalcode"
  },
  "geometry": {"coordinates":[-3.707331,56.299999],"type":"Point"}
}
