{
  "type": "Feature",
  "properties": {
    "iso:country": "GB",
    "wof:name": "PH3 1FA",
    "wof:placetype": "postalcode"
  },
  "geometry": {"coordinates":[-3.707331,56.299999],"type":"Point"}
}
