{
  "type": "Feature",
  "properties": {
    "iso:country":"GB",
    "wof:name":"IP9 1EQ",
    "wof:placetype":"postalcode"
},
  "geometry": {"coordinates":[1.23675155630542,51.98558838171447],"type":"Point"}
}