{
  "type": "Feature",
  "properties": {
    "iso:country": "GB",
    "wof:name": "IP9 1EQ",
    "wof:placetype": "postalcode"
  },
  "geometry": {"coordinates":[1.236782,51.985601],"type":"Point"}
}
