{
  "type": "Feature",
  "properties": {
    "iso:country":"GB",
    "wof:name":"NE12 9QH",
    "wof:placetype":"postalcode"
},
  "geometry": {"coordinates":[-1.54533144069098,55.02393041302178],"type":"Point"}
}