{
  "type": "Feature",
  "properties": {
    "iso:country": "GB",
    "wof:name": "NE12 9QH",
    "wof:placetype": "postalcode"
  },
  "geometry": {"coordinates":[-1.545331,55.02393],"type":"Point"}
}
