{
  "type": "Feature",
  "properties": {
    "date:inception_lower":"1981-09-01",
    "date:inception_upper":"1981-09-30",
    "iso:country":"GB",
    "wof:name":"NE12 9QH",
    "wof:placetype":"postalcode"
},
  "geometry": {"coordinates":[-1.545331,55.02393],"type":"Point"}
}