{
  "type": "Feature",
  "properties": {
    "date:inception_lower": "2002-12-01",
    "date:inception_upper": "2002-12-01",
    "iso:country": "GB",
    "wof:name": "MK42 9GL",
    "wof:placetype": "postalcode"
  },
  "geometry": {"coordinates":[-0.450393,52.114318],"type":"Point"}
}
