{
  "type": "Feature",
  "properties": {
    "iso:country":"GB",
    "wof:name":"SM4 6DZ",
    "wof:placetype":"postalcode"
},
  "geometry": {"coordinates":[-0.19825031613341,51.38924363791136],"type":"Point"}
}