{
  "type": "Feature",
  "properties": {
    "iso:country": "GB",
    "wof:name": "CF83 3QD",
    "wof:placetype": "postalcode"
  },
  "geometry": {"coordinates":[-3.204963,51.584187],"type":"Point"}
}
