{
  "type": "Feature",
  "properties": {
    "iso:country":"GB",
    "wof:name":"CF83 3QD",
    "wof:placetype":"postalcode"
},
  "geometry": {"coordinates":[-3.20496320310177,51.58418666100885],"type":"Point"}
}