{
  "type": "Feature",
  "properties": {
    "iso:country":"GB",
    "wof:name":"SP1 1JQ",
    "wof:placetype":"postalcode"
},
  "geometry": {"coordinates":[-1.78602054056625,51.07352359514281],"type":"Point"}
}