{
  "type": "Feature",
  "properties": {
    "date:inception_lower": "2007-03-01",
    "date:inception_upper": "2007-03-01",
    "iso:country": "GB",
    "wof:name": "SP1 1JQ",
    "wof:placetype": "postalcode"
  },
  "geometry": {"coordinates":[-1.786021,51.073524],"type":"Point"}
}
