{
  "type": "Feature",
  "properties": {
    "date:inception_lower": "2018-04-01",
    "date:inception_upper": "2018-04-01",
    "iso:country": "GB",
    "wof:name": "KY3 0EB",
    "wof:placetype": "postalcode"
  },
  "geometry": {"coordinates":[-3.299859,56.05523],"type":"Point"}
}
