{
  "type": "Feature",
  "properties": {
    "iso:country": "GB",
    "wof:name": "KY3 0EB",
    "wof:placetype": "postalcode"
  },
  "geometry": {"coordinates":[-3.299859,56.055239],"type":"Point"}
}
