{
  "type": "Feature",
  "properties": {
    "iso:country": "GB",
    "wof:name": "FK2 9UP",
    "wof:placetype": "postalcode"
  },
  "geometry": {"coordinates":[-3.73043,55.985193],"type":"Point"}
}
