{
  "type": "Feature",
  "properties": {
    "date:inception_lower":"1984-02-01",
    "date:inception_upper":"1984-02-29",
    "iso:country":"GB",
    "wof:name":"FK2 9UP",
    "wof:placetype":"postalcode"
},
  "geometry": {"coordinates":[-3.73043,55.985193],"type":"Point"}
}