{
  "type": "Feature",
  "properties": {
    "iso:country": "GB",
    "wof:name": "AL1 3LZ",
    "wof:placetype": "postalcode"
  },
  "geometry": {"coordinates":[-0.338557,51.751419],"type":"Point"}
}
