{
  "type": "Feature",
  "properties": {
    "iso:country": "GB",
    "wof:name": "BR4 9HB",
    "wof:placetype": "postalcode"
  },
  "geometry": {"coordinates":[-0.000524,51.365074],"type":"Point"}
}
