{
  "type": "Feature",
  "properties": {
    "iso:country":"GB",
    "wof:name":"BR4 9HB",
    "wof:placetype":"postalcode"
},
  "geometry": {"coordinates":[-0.0005239686877,51.36507387680087],"type":"Point"}
}