{
  "type": "Feature",
  "properties": {
    "iso:country":"GB",
    "wof:name":"LA13 0AQ",
    "wof:placetype":"postalcode"
},
  "geometry": {"coordinates":[-3.1979395361203,54.12436068896142],"type":"Point"}
}