{
  "type": "Feature",
  "properties": {
    "date:inception_lower":"1980-01-01",
    "date:inception_upper":"1980-01-31",
    "iso:country":"GB",
    "wof:name":"LA13 0AQ",
    "wof:placetype":"postalcode"
},
  "geometry": {"coordinates":[-3.197939,54.124361],"type":"Point"}
}