{
  "type": "Feature",
  "properties": {
    "iso:country":"GB",
    "wof:name":"DE11 0ST",
    "wof:placetype":"postalcode"
},
  "geometry": {"coordinates":[-1.58175942211918,52.78102022651315],"type":"Point"}
}