{
  "type": "Feature",
  "properties": {
    "date:inception_lower": "1980-01-01",
    "date:inception_upper": "1980-01-01",
    "iso:country": "GB",
    "wof:name": "SN14 8HQ",
    "wof:placetype": "postalcode"
  },
  "geometry": {"coordinates":[-2.383937,51.490093],"type":"Point"}
}
