{
  "type": "Feature",
  "properties": {
    "iso:country":"GB",
    "wof:name":"SN14 8HQ",
    "wof:placetype":"postalcode"
},
  "geometry": {"coordinates":[-2.38393687470154,51.4900934110156],"type":"Point"}
}