{
  "type": "Feature",
  "properties": {
    "iso:country":"GB",
    "wof:name":"PO35 5RY",
    "wof:placetype":"postalcode"
},
  "geometry": {"coordinates":[-1.08941982164832,50.69111628813984],"type":"Point"}
}