{
  "type": "Feature",
  "properties": {
    "iso:country": "GB",
    "wof:name": "PO35 5RY",
    "wof:placetype": "postalcode"
  },
  "geometry": {"coordinates":[-1.08942,50.691116],"type":"Point"}
}
