{
  "type": "Feature",
  "properties": {
    "iso:country":"GB",
    "wof:name":"KY14 6JN",
    "wof:placetype":"postalcode"
},
  "geometry": {"coordinates":[-3.20870459087892,56.33569051038955],"type":"Point"}
}