{
  "type": "Feature",
  "properties": {
    "iso:country":"GB",
    "wof:name":"SW7 2JB",
    "wof:placetype":"postalcode"
},
  "geometry": {"coordinates":[-0.17470527464341,51.49540516615418],"type":"Point"}
}