{
  "type": "Feature",
  "properties": {
    "date:inception_lower":"1980-01-01",
    "date:inception_upper":"1980-01-31",
    "iso:country":"GB",
    "wof:name":"SW7 2JB",
    "wof:placetype":"postalcode"
},
  "geometry": {"coordinates":[-0.174807,51.495389],"type":"Point"}
}