{
  "type": "Feature",
  "properties": {
    "iso:country":"GB",
    "wof:name":"NN8 6GS",
    "wof:placetype":"postalcode"
},
  "geometry": {"coordinates":[-0.73761335826391,52.3050326470446],"type":"Point"}
}