{
  "type": "Feature",
  "properties": {
    "iso:country":"GB",
    "wof:name":"WF9 2LE",
    "wof:placetype":"postalcode"
},
  "geometry": {"coordinates":[-1.29949208195368,53.58405972190442],"type":"Point"}
}