{
  "type": "Feature",
  "properties": {
    "iso:country": "GB",
    "wof:name": "BN41 2FJ",
    "wof:placetype": "postalcode"
  },
  "geometry": {"coordinates":[-0.211442,50.845005],"type":"Point"}
}
