{
  "type": "Feature",
  "properties": {
    "iso:country":"GB",
    "wof:name":"BN41 2FJ",
    "wof:placetype":"postalcode"
},
  "geometry": {"coordinates":[-0.21126544852562,50.84479218906672],"type":"Point"}
}