{
  "type": "Feature",
  "properties": {
    "date:inception_lower": "1980-01-01",
    "date:inception_upper": "1980-01-01",
    "iso:country": "GB",
    "wof:name": "EH45 9ER",
    "wof:placetype": "postalcode"
  },
  "geometry": {"coordinates":[-3.189969,55.647931],"type":"Point"}
}
