{
  "type": "Feature",
  "properties": {
    "iso:country": "GB",
    "wof:name": "EH45 9ER",
    "wof:placetype": "postalcode"
  },
  "geometry": {"coordinates":[-3.189969,55.647931],"type":"Point"}
}
