{
  "type": "Feature",
  "properties": {
    "iso:country": "GB",
    "wof:name": "NE19 1SN",
    "wof:placetype": "postalcode"
  },
  "geometry": {"coordinates":[-2.2954,55.28388],"type":"Point"}
}
