{
  "type": "Feature",
  "properties": {
    "date:inception_lower": "1996-06-01",
    "date:inception_upper": "1996-06-01",
    "iso:country": "GB",
    "wof:name": "NG24 1RX",
    "wof:placetype": "postalcode"
  },
  "geometry": {"coordinates":[-0.793757,53.065406],"type":"Point"}
}
