{
  "type": "Feature",
  "properties": {
    "date:inception_lower": "1980-01-01",
    "date:inception_upper": "1980-01-01",
    "iso:country": "GB",
    "wof:name": "G44 4BA",
    "wof:placetype": "postalcode"
  },
  "geometry": {"coordinates":[-4.261349,55.822325],"type":"Point"}
}
