{
  "type": "Feature",
  "properties": {
    "iso:country":"GB",
    "wof:name":"SN16 9ZZ",
    "wof:placetype":"postalcode"
},
  "geometry": {"coordinates":[-2.09791745565566,51.5823400113705],"type":"Point"}
}