{
  "type": "Feature",
  "properties": {
    "iso:country":"GB",
    "wof:name":"EX20 3BT",
    "wof:placetype":"postalcode"
},
  "geometry": {"coordinates":[-4.09139336744344,50.75411155275713],"type":"Point"}
}