{
  "type": "Feature",
  "properties": {
    "date:inception_lower": "1980-01-01",
    "date:inception_upper": "1980-01-01",
    "iso:country": "GB",
    "wof:name": "E18 1LN",
    "wof:placetype": "postalcode"
  },
  "geometry": {"coordinates":[0.029606,51.590698],"type":"Point"}
}
