{
  "type": "Feature",
  "properties": {
    "iso:country":"GB",
    "wof:name":"E18 1LN",
    "wof:placetype":"postalcode"
},
  "geometry": {"coordinates":[0.0296670048055,51.59071353567318],"type":"Point"}
}