{
  "type": "Feature",
  "properties": {
    "iso:country":"GB",
    "wof:name":"CV23 9AU",
    "wof:placetype":"postalcode"
},
  "geometry": {"coordinates":[-1.30749695013777,52.3792516595637],"type":"Point"}
}