{
  "type": "Feature",
  "properties": {
    "iso:country":"GB",
    "wof:name":"NN6 8AR",
    "wof:placetype":"postalcode"
},
  "geometry": {"coordinates":[-0.95680061001054,52.28099084394786],"type":"Point"}
}