{
  "type": "Feature",
  "properties": {
    "date:inception_lower": "2017-11-01",
    "date:inception_upper": "2017-11-01",
    "iso:country": "GB",
    "wof:name": "SE16 4ET",
    "wof:placetype": "postalcode"
  },
  "geometry": {"coordinates":[-0.062359,51.497966],"type":"Point"}
}
