{
  "type": "Feature",
  "properties": {
    "iso:country": "GB",
    "wof:name": "B34 6QT",
    "wof:placetype": "postalcode"
  },
  "geometry": {"coordinates":[-1.79023,52.497793],"type":"Point"}
}
