{
  "type": "Feature",
  "properties": {
    "iso:country":"GB",
    "wof:name":"B34 6QT",
    "wof:placetype":"postalcode"
},
  "geometry": {"coordinates":[-1.79022985259298,52.4977926408806],"type":"Point"}
}