{
  "type": "Feature",
  "properties": {
    "iso:country":"GB",
    "wof:name":"BB8 0HH",
    "wof:placetype":"postalcode"
},
  "geometry": {"coordinates":[-2.16608020417978,53.85503346508509],"type":"Point"}
}