{
  "type": "Feature",
  "properties": {
    "iso:country": "GB",
    "wof:name": "GL11 5LB",
    "wof:placetype": "postalcode"
  },
  "geometry": {"coordinates":[-2.365648,51.702648],"type":"Point"}
}
