{
  "type": "Feature",
  "properties": {
    "iso:country":"GB",
    "wof:name":"S20 5AR",
    "wof:placetype":"postalcode"
},
  "geometry": {"coordinates":[-1.36436579568498,53.32905480223017],"type":"Point"}
}