{
  "type": "Feature",
  "properties": {
    "iso:country":"GB",
    "wof:name":"SN2 7XL",
    "wof:placetype":"postalcode"
},
  "geometry": {"coordinates":[-1.76122429303338,51.59427706767607],"type":"Point"}
}