{
  "type": "Feature",
  "properties": {
    "iso:country":"GB",
    "wof:name":"IV40 8HU",
    "wof:placetype":"postalcode"
},
  "geometry": {"coordinates":[-5.3736863587152,57.18113702375405],"type":"Point"}
}