{
  "type": "Feature",
  "properties": {
    "date:inception_lower": "1980-01-01",
    "date:inception_upper": "1980-01-01",
    "iso:country": "GB",
    "wof:name": "CA2 6AX",
    "wof:placetype": "postalcode"
  },
  "geometry": {"coordinates":[-2.959217,54.872501],"type":"Point"}
}
