{
  "type": "Feature",
  "properties": {
    "iso:country": "GB",
    "wof:name": "CA2 6AX",
    "wof:placetype": "postalcode"
  },
  "geometry": {"coordinates":[-2.959217,54.872501],"type":"Point"}
}
