{
  "type": "Feature",
  "properties": {
    "iso:country":"GB",
    "wof:name":"CA2 6AX",
    "wof:placetype":"postalcode"
},
  "geometry": {"coordinates":[-2.95921748005911,54.87250101277638],"type":"Point"}
}