{
  "type": "Feature",
  "properties": {
    "iso:country":"GB",
    "wof:name":"LL22 9NA",
    "wof:placetype":"postalcode"
},
  "geometry": {"coordinates":[-3.53835143415057,53.30186607728696],"type":"Point"}
}