{
  "type": "Feature",
  "properties": {
    "iso:country":"GB",
    "wof:name":"BB5 2PX",
    "wof:placetype":"postalcode"
},
  "geometry": {"coordinates":[-2.34666261959632,53.73821665818355],"type":"Point"}
}