{
  "type": "Feature",
  "properties": {
    "date:inception_lower": "2022-02-01",
    "date:inception_upper": "2022-02-01",
    "iso:country": "GB",
    "wof:name": "DD4 0FJ",
    "wof:placetype": "postalcode"
  },
  "geometry": {"coordinates":[-2.916385,56.491015],"type":"Point"}
}
