{
  "type": "Feature",
  "properties": {
    "date:inception_lower": "2021-07-01",
    "date:inception_upper": "2021-07-01",
    "iso:country": "GB",
    "wof:name": "BA5 2JY",
    "wof:placetype": "postalcode"
  },
  "geometry": {"coordinates":[-2.668062,51.21601],"type":"Point"}
}
