{
  "type": "Feature",
  "properties": {
    "date:inception_lower": "1999-06-01",
    "date:inception_upper": "1999-06-01",
    "iso:country": "GB",
    "wof:name": "NP12 0DH",
    "wof:placetype": "postalcode"
  },
  "geometry": {"coordinates":[-3.184672,51.672649],"type":"Point"}
}
