{
  "type": "Feature",
  "properties": {
    "date:inception_lower": "2007-09-01",
    "date:inception_upper": "2007-09-01",
    "iso:country": "GB",
    "wof:name": "WR3 7PX",
    "wof:placetype": "postalcode"
  },
  "geometry": {"coordinates":[-2.224214,52.21809],"type":"Point"}
}
