{
  "type": "Feature",
  "properties": {
    "iso:country":"GB",
    "wof:name":"BL7 0LU",
    "wof:placetype":"postalcode"
},
  "geometry": {"coordinates":[-2.41690548832131,53.65294658282634],"type":"Point"}
}