{
  "type": "Feature",
  "properties": {
    "iso:country":"GB",
    "wof:name":"SW4 7AD",
    "wof:placetype":"postalcode"
},
  "geometry": {"coordinates":[-0.13799120540764,51.46126775126054],"type":"Point"}
}