{
  "type": "Feature",
  "properties": {
    "iso:country":"GB",
    "wof:name":"B61 7PE",
    "wof:placetype":"postalcode"
},
  "geometry": {"coordinates":[-2.0751642212897,52.33190766216875],"type":"Point"}
}