{
  "type": "Feature",
  "properties": {
    "iso:country":"GB",
    "wof:name":"LL13 9QD",
    "wof:placetype":"postalcode"
},
  "geometry": {"coordinates":[-2.96367545534916,53.05781407718106],"type":"Point"}
}