{
  "type": "Feature",
  "properties": {
    "date:inception_lower": "1981-06-01",
    "date:inception_upper": "1981-06-01",
    "iso:country": "GB",
    "wof:name": "LL13 9QD",
    "wof:placetype": "postalcode"
  },
  "geometry": {"coordinates":[-2.963675,53.057814],"type":"Point"}
}
