{
  "type": "Feature",
  "properties": {
    "date:inception_lower": "2012-12-01",
    "date:inception_upper": "2012-12-01",
    "iso:country": "GB",
    "wof:name": "FY3 0EL",
    "wof:placetype": "postalcode"
  },
  "geometry": {"coordinates":[-2.989282,53.816218],"type":"Point"}
}
