{
  "type": "Feature",
  "properties": {
    "iso:country": "GB",
    "wof:name": "FY3 0EL",
    "wof:placetype": "postalcode"
  },
  "geometry": {"coordinates":[-2.989282,53.816218],"type":"Point"}
}
