{
  "type": "Feature",
  "properties": {
    "date:inception_lower": "2000-12-01",
    "date:inception_upper": "2000-12-01",
    "iso:country": "GB",
    "wof:name": "WV2 4XA",
    "wof:placetype": "postalcode"
  },
  "geometry": {"coordinates":[-2.133237,52.571943],"type":"Point"}
}
