{
  "type": "Feature",
  "properties": {
    "iso:country":"GB",
    "wof:name":"WV2 4XA",
    "wof:placetype":"postalcode"
},
  "geometry": {"coordinates":[-2.13323749517929,52.57194344658069],"type":"Point"}
}