{
  "type": "Feature",
  "properties": {
    "iso:country":"GB",
    "wof:name":"CF32 9BN",
    "wof:placetype":"postalcode"
},
  "geometry": {"coordinates":[-3.59820608334304,51.54291812198168],"type":"Point"}
}