{
  "type": "Feature",
  "properties": {
    "iso:country": "GB",
    "wof:name": "CF32 9BN",
    "wof:placetype": "postalcode"
  },
  "geometry": {"coordinates":[-3.598193,51.542963],"type":"Point"}
}
