{
  "type": "Feature",
  "properties": {
    "iso:country": "GB",
    "wof:name": "DN20 9LE",
    "wof:placetype": "postalcode"
  },
  "geometry": {"coordinates":[-0.515429,53.54765],"type":"Point"}
}
