{
  "type": "Feature",
  "properties": {
    "iso:country":"GB",
    "wof:name":"DN20 9LE",
    "wof:placetype":"postalcode"
},
  "geometry": {"coordinates":[-0.51542935705271,53.54765007205084],"type":"Point"}
}