{
  "type": "Feature",
  "properties": {
    "iso:country":"GB",
    "wof:name":"DH8 8LY",
    "wof:placetype":"postalcode"
},
  "geometry": {"coordinates":[-1.70494258180825,54.87621113182914],"type":"Point"}
}