{
  "type": "Feature",
  "properties": {
    "iso:country": "GB",
    "wof:name": "DH8 8LY",
    "wof:placetype": "postalcode"
  },
  "geometry": {"coordinates":[-1.847905,54.860135],"type":"Point"}
}
