{
  "type": "Feature",
  "properties": {
    "date:inception_lower":"2002-07-01",
    "date:inception_upper":"2002-07-31",
    "iso:country":"GB",
    "wof:name":"DH8 8LY",
    "wof:placetype":"postalcode"
},
  "geometry": {"coordinates":[-1.847905,54.860135],"type":"Point"}
}