{
  "type": "Feature",
  "properties": {
    "iso:country":"GB",
    "wof:name":"CV37 8LB",
    "wof:placetype":"postalcode"
},
  "geometry": {"coordinates":[-1.73724860176825,52.15268734009986],"type":"Point"}
}