{
  "type": "Feature",
  "properties": {
    "iso:country": "GB",
    "wof:name": "CV37 8LB",
    "wof:placetype": "postalcode"
  },
  "geometry": {"coordinates":[-1.737249,52.152687],"type":"Point"}
}
