{
  "type": "Feature",
  "properties": {
    "iso:country":"GB",
    "wof:name":"SL5 7HJ",
    "wof:placetype":"postalcode"
},
  "geometry": {"coordinates":[-0.67319487270347,51.41195809603163],"type":"Point"}
}