{
  "type": "Feature",
  "properties": {
    "date:inception_lower": "1980-01-01",
    "date:inception_upper": "1980-01-01",
    "iso:country": "GB",
    "wof:name": "E13 8JY",
    "wof:placetype": "postalcode"
  },
  "geometry": {"coordinates":[0.024446,51.520337],"type":"Point"}
}
