{
  "type": "Feature",
  "properties": {
    "iso:country":"GB",
    "wof:name":"E13 8JY",
    "wof:placetype":"postalcode"
},
  "geometry": {"coordinates":[0.02444617220553,51.52033733515337],"type":"Point"}
}