{
  "type": "Feature",
  "properties": {
    "iso:country":"GB",
    "wof:name":"N20 8QT",
    "wof:placetype":"postalcode"
},
  "geometry": {"coordinates":[-0.18669344596892,51.63280592287711],"type":"Point"}
}