{
  "type": "Feature",
  "properties": {
    "iso:country": "GB",
    "wof:name": "BH8 0AZ",
    "wof:placetype": "postalcode"
  },
  "geometry": {"coordinates":[-1.850859,50.75426],"type":"Point"}
}
