{
  "type": "Feature",
  "properties": {
    "iso:country": "GB",
    "wof:name": "GU26 6DY",
    "wof:placetype": "postalcode"
  },
  "geometry": {"coordinates":[-0.76972,51.113523],"type":"Point"}
}
