{
  "type": "Feature",
  "properties": {
    "iso:country":"GB",
    "wof:name":"GU26 6DY",
    "wof:placetype":"postalcode"
},
  "geometry": {"coordinates":[-0.76972032344368,51.11352312289038],"type":"Point"}
}