{
  "type": "Feature",
  "properties": {
    "iso:country": "GB",
    "wof:name": "NN18 9DD",
    "wof:placetype": "postalcode"
  },
  "geometry": {"coordinates":[-0.726543,52.469884],"type":"Point"}
}
