{
  "type": "Feature",
  "properties": {
    "iso:country": "GB",
    "wof:name": "NE32 4BE",
    "wof:placetype": "postalcode"
  },
  "geometry": {"coordinates":[-1.466732,54.966144],"type":"Point"}
}
