{
  "type": "Feature",
  "properties": {
    "iso:country":"GB",
    "wof:name":"NE32 4BE",
    "wof:placetype":"postalcode"
},
  "geometry": {"coordinates":[-1.46673175250313,54.96614422732276],"type":"Point"}
}