{
  "type": "Feature",
  "properties": {
    "iso:country":"GB",
    "wof:name":"E3 5LU",
    "wof:placetype":"postalcode"
},
  "geometry": {"coordinates":[-0.03403783541868,51.5319524894227],"type":"Point"}
}