{
  "type": "Feature",
  "properties": {
    "iso:country": "GB",
    "wof:name": "E3 5LU",
    "wof:placetype": "postalcode"
  },
  "geometry": {"coordinates":[-0.034038,51.531952],"type":"Point"}
}
