{
  "type": "Feature",
  "properties": {
    "date:inception_lower": "1980-01-01",
    "date:inception_upper": "1980-01-01",
    "iso:country": "GB",
    "wof:name": "HA3 0SH",
    "wof:placetype": "postalcode"
  },
  "geometry": {"coordinates":[-0.298669,51.582849],"type":"Point"}
}
