{
  "type": "Feature",
  "properties": {
    "iso:country":"GB",
    "wof:name":"FY5 5NG",
    "wof:placetype":"postalcode"
},
  "geometry": {"coordinates":[-2.99049495853294,53.87705289988541],"type":"Point"}
}