{
  "type": "Feature",
  "properties": {
    "date:inception_lower":"2015-11-01",
    "date:inception_upper":"2015-11-30",
    "iso:country":"GB",
    "wof:name":"CF11 0JZ",
    "wof:placetype":"postalcode"
},
  "geometry": {"coordinates":[-3.178972,51.448359],"type":"Point"}
}