{
  "type": "Feature",
  "properties": {
    "date:inception_lower": "2015-11-01",
    "date:inception_upper": "2015-11-01",
    "iso:country": "GB",
    "wof:name": "CF11 0JZ",
    "wof:placetype": "postalcode"
  },
  "geometry": {"coordinates":[-3.179058,51.448376],"type":"Point"}
}
