{
  "type": "Feature",
  "properties": {
    "iso:country":"GB",
    "wof:name":"CF11 0JZ",
    "wof:placetype":"postalcode"
},
  "geometry": {"coordinates":[-3.1790193941852,51.44887985101617],"type":"Point"}
}