{
  "type": "Feature",
  "properties": {
    "iso:country":"GB",
    "wof:name":"CF48 4QU",
    "wof:placetype":"postalcode"
},
  "geometry": {"coordinates":[-3.34444854671538,51.6940799550136],"type":"Point"}
}