{
  "type": "Feature",
  "properties": {
    "date:inception_lower":"1980-01-01",
    "date:inception_upper":"1980-01-31",
    "iso:country":"GB",
    "wof:name":"BH23 5JT",
    "wof:placetype":"postalcode"
},
  "geometry": {"coordinates":[-1.693225,50.74067],"type":"Point"}
}