{
  "type": "Feature",
  "properties": {
    "date:inception_lower": "1995-01-01",
    "date:inception_upper": "1995-01-01",
    "iso:country": "GB",
    "wof:name": "RH12 5EA",
    "wof:placetype": "postalcode"
  },
  "geometry": {"coordinates":[-0.32256,51.087996],"type":"Point"}
}
