{
  "type": "Feature",
  "properties": {
    "iso:country":"GB",
    "wof:name":"RH12 5EA",
    "wof:placetype":"postalcode"
},
  "geometry": {"coordinates":[-0.32260113727658,51.08799990295091],"type":"Point"}
}