{
  "type": "Feature",
  "properties": {
    "iso:country": "GB",
    "wof:name": "CV12 0AX",
    "wof:placetype": "postalcode"
  },
  "geometry": {"coordinates":[-1.493447,52.481118],"type":"Point"}
}
