{
  "type": "Feature",
  "properties": {
    "date:inception_lower": "2005-08-01",
    "date:inception_upper": "2005-08-01",
    "iso:country": "GB",
    "wof:name": "CV12 0AX",
    "wof:placetype": "postalcode"
  },
  "geometry": {"coordinates":[-1.493447,52.481118],"type":"Point"}
}
