{
  "type": "Feature",
  "properties": {
    "iso:country":"GB",
    "wof:name":"CV12 0AX",
    "wof:placetype":"postalcode"
},
  "geometry": {"coordinates":[-1.49344742436175,52.48111752387778],"type":"Point"}
}