{
  "type": "Feature",
  "properties": {
    "iso:country":"GB",
    "wof:name":"CH48 5JD",
    "wof:placetype":"postalcode"
},
  "geometry": {"coordinates":[-3.17314011316644,53.37794069145245],"type":"Point"}
}