{
  "type": "Feature",
  "properties": {
    "iso:country":"GB",
    "wof:name":"S65 4EB",
    "wof:placetype":"postalcode"
},
  "geometry": {"coordinates":[-1.29045709217403,53.44962721530343],"type":"Point"}
}