{
  "type": "Feature",
  "properties": {
    "iso:country":"GB",
    "wof:name":"DY9 0JG",
    "wof:placetype":"postalcode"
},
  "geometry": {"coordinates":[-2.15319604746222,52.41401085702667],"type":"Point"}
}