{
  "type": "Feature",
  "properties": {
    "iso:country": "GB",
    "wof:name": "DY9 0JG",
    "wof:placetype": "postalcode"
  },
  "geometry": {"coordinates":[-2.153196,52.414011],"type":"Point"}
}
