{
  "type": "Feature",
  "properties": {
    "iso:country":"GB",
    "wof:name":"LS14 1AF",
    "wof:placetype":"postalcode"
},
  "geometry": {"coordinates":[-1.46901893994312,53.83923492545591],"type":"Point"}
}