{
  "type": "Feature",
  "properties": {
    "iso:country":"GB",
    "wof:name":"EX31 3QX",
    "wof:placetype":"postalcode"
},
  "geometry": {"coordinates":[-4.08827670989955,51.0677740775639],"type":"Point"}
}