{
  "type": "Feature",
  "properties": {
    "iso:country":"GB",
    "wof:name":"N12 8PR",
    "wof:placetype":"postalcode"
},
  "geometry": {"coordinates":[-0.17712501753135,51.61701113186013],"type":"Point"}
}