{
  "type": "Feature",
  "properties": {
    "date:inception_lower": "1980-01-01",
    "date:inception_upper": "1980-01-01",
    "iso:country": "GB",
    "wof:name": "N12 8PR",
    "wof:placetype": "postalcode"
  },
  "geometry": {"coordinates":[-0.177015,51.61695],"type":"Point"}
}
