{
  "type": "Feature",
  "properties": {
    "iso:country":"GB",
    "wof:name":"MK43 7RZ",
    "wof:placetype":"postalcode"
},
  "geometry": {"coordinates":[-0.51378469932617,52.16588984750479],"type":"Point"}
}