{
  "type": "Feature",
  "properties": {
    "iso:country": "GB",
    "wof:name": "MK43 7RZ",
    "wof:placetype": "postalcode"
  },
  "geometry": {"coordinates":[-0.513785,52.16589],"type":"Point"}
}
