{
  "type": "Feature",
  "properties": {
    "iso:country":"GB",
    "wof:name":"ML4 1HW",
    "wof:placetype":"postalcode"
},
  "geometry": {"coordinates":[-4.02194684557095,55.82232543421821],"type":"Point"}
}