{
  "type": "Feature",
  "properties": {
    "iso:country":"GB",
    "wof:name":"DN35 0HT",
    "wof:placetype":"postalcode"
},
  "geometry": {"coordinates":[-0.02156764161124,53.54567726049103],"type":"Point"}
}