{
  "type": "Feature",
  "properties": {
    "iso:country":"GB",
    "wof:name":"RM7 7ET",
    "wof:placetype":"postalcode"
},
  "geometry": {"coordinates":[0.17209097235057,51.58259719401665],"type":"Point"}
}