{
  "type": "Feature",
  "properties": {
    "date:inception_lower": "1980-01-01",
    "date:inception_upper": "1980-01-01",
    "iso:country": "GB",
    "wof:name": "ST5 1JT",
    "wof:placetype": "postalcode"
  },
  "geometry": {"coordinates":[-2.215405,53.012343],"type":"Point"}
}
