{
  "type": "Feature",
  "properties": {
    "date:inception_lower":"1980-01-01",
    "date:inception_upper":"1980-01-31",
    "iso:country":"GB",
    "wof:name":"PO3 6AP",
    "wof:placetype":"postalcode"
},
  "geometry": {"coordinates":[-1.063831,50.807326],"type":"Point"}
}