{
  "type": "Feature",
  "properties": {
    "iso:country": "GB",
    "wof:name": "PO3 6AP",
    "wof:placetype": "postalcode"
  },
  "geometry": {"coordinates":[-1.063831,50.807326],"type":"Point"}
}
