{
  "type": "Feature",
  "properties": {
    "iso:country":"GB",
    "wof:name":"LE3 0JD",
    "wof:placetype":"postalcode"
},
  "geometry": {"coordinates":[-1.1521026069267,52.62785166847876],"type":"Point"}
}