{
  "type": "Feature",
  "properties": {
    "iso:country":"GB",
    "wof:name":"IP28 8BZ",
    "wof:placetype":"postalcode"
},
  "geometry": {"coordinates":[0.48583561275358,52.3686772844399],"type":"Point"}
}