{
  "type": "Feature",
  "properties": {
    "iso:country":"GB",
    "wof:name":"PH1 3FW",
    "wof:placetype":"postalcode"
},
  "geometry": {"coordinates":[-3.4629279468966,56.41488581654927],"type":"Point"}
}