{
  "type": "Feature",
  "properties": {
    "iso:country": "GB",
    "wof:name": "PH1 3FW",
    "wof:placetype": "postalcode"
  },
  "geometry": {"coordinates":[-3.462928,56.414886],"type":"Point"}
}
