{
  "type": "Feature",
  "properties": {
    "iso:country": "GB",
    "wof:name": "HA8 8RD",
    "wof:placetype": "postalcode"
  },
  "geometry": {"coordinates":[-0.27176,51.627462],"type":"Point"}
}
