{
  "type": "Feature",
  "properties": {
    "iso:country":"GB",
    "wof:name":"HA8 8RD",
    "wof:placetype":"postalcode"
},
  "geometry": {"coordinates":[-0.27176002533802,51.62746164805272],"type":"Point"}
}