{
  "type": "Feature",
  "properties": {
    "iso:country":"GB",
    "wof:name":"M14 7WP",
    "wof:placetype":"postalcode"
},
  "geometry": {"coordinates":[-2.2373653322466,53.4515861399047],"type":"Point"}
}