{
  "type": "Feature",
  "properties": {
    "date:inception_lower": "1980-01-01",
    "date:inception_upper": "1980-01-01",
    "iso:country": "GB",
    "wof:name": "M14 7WP",
    "wof:placetype": "postalcode"
  },
  "geometry": {"coordinates":[-2.237365,53.451586],"type":"Point"}
}
