{
  "type": "Feature",
  "properties": {
    "iso:country":"GB",
    "wof:name":"IP4 3QJ",
    "wof:placetype":"postalcode"
},
  "geometry": {"coordinates":[1.17983948344757,52.07617175670163],"type":"Point"}
}