{
  "type": "Feature",
  "properties": {
    "date:inception_lower": "2007-07-01",
    "date:inception_upper": "2007-07-01",
    "iso:country": "GB",
    "wof:name": "BB5 5HY",
    "wof:placetype": "postalcode"
  },
  "geometry": {"coordinates":[-2.389434,53.769828],"type":"Point"}
}
