{
  "type": "Feature",
  "properties": {
    "iso:country":"GB",
    "wof:name":"BB5 5HY",
    "wof:placetype":"postalcode"
},
  "geometry": {"coordinates":[-2.38947977892997,53.76982199623517],"type":"Point"}
}