{
  "type": "Feature",
  "properties": {
    "iso:country":"GB",
    "wof:name":"CT12 6HW",
    "wof:placetype":"postalcode"
},
  "geometry": {"coordinates":[1.3919981970765,51.33993672332106],"type":"Point"}
}