{
  "type": "Feature",
  "properties": {
    "date:inception_lower":"1981-06-01",
    "date:inception_upper":"1981-06-30",
    "iso:country":"GB",
    "wof:name":"CT12 6HW",
    "wof:placetype":"postalcode"
},
  "geometry": {"coordinates":[1.391998,51.339937],"type":"Point"}
}