{
  "type": "Feature",
  "properties": {
    "iso:country":"GB",
    "wof:name":"GU26 6TB",
    "wof:placetype":"postalcode"
},
  "geometry": {"coordinates":[-0.73223482485305,51.11658489262962],"type":"Point"}
}