{
  "type": "Feature",
  "properties": {
    "iso:country":"GB",
    "wof:name":"SY3 7JD",
    "wof:placetype":"postalcode"
},
  "geometry": {"coordinates":[-2.75210893567722,52.70298504043261],"type":"Point"}
}