{
  "type": "Feature",
  "properties": {
    "date:inception_lower": "2002-07-01",
    "date:inception_upper": "2002-07-01",
    "iso:country": "GB",
    "wof:name": "SY3 7JD",
    "wof:placetype": "postalcode"
  },
  "geometry": {"coordinates":[-2.752109,52.702985],"type":"Point"}
}
