{
  "type": "Feature",
  "properties": {
    "date:inception_lower": "2017-03-01",
    "date:inception_upper": "2017-03-01",
    "iso:country": "GB",
    "wof:name": "ST17 9ZE",
    "wof:placetype": "postalcode"
  },
  "geometry": {"coordinates":[-2.119401,52.785874],"type":"Point"}
}
