{
  "type": "Feature",
  "properties": {
    "iso:country":"GB",
    "wof:name":"S45 9LN",
    "wof:placetype":"postalcode"
},
  "geometry": {"coordinates":[-1.40140248001602,53.16937825519214],"type":"Point"}
}