{
  "type": "Feature",
  "properties": {
    "iso:country":"GB",
    "wof:name":"CR0 9ER",
    "wof:placetype":"postalcode"
},
  "geometry": {"coordinates":[-0.01943104145858,51.35803891906268],"type":"Point"}
}