{
  "type": "Feature",
  "properties": {
    "iso:country":"GB",
    "wof:name":"RH11 0NQ",
    "wof:placetype":"postalcode"
},
  "geometry": {"coordinates":[-0.21465062633913,51.12766991575693],"type":"Point"}
}