{
  "type": "Feature",
  "properties": {
    "date:inception_lower": "2020-12-01",
    "date:inception_upper": "2020-12-01",
    "iso:country": "GB",
    "wof:name": "LE67 4UJ",
    "wof:placetype": "postalcode"
  },
  "geometry": {"coordinates":[-1.321662,52.723858],"type":"Point"}
}
