{
  "type": "Feature",
  "properties": {
    "iso:country":"GB",
    "wof:name":"W1J 8PD",
    "wof:placetype":"postalcode"
},
  "geometry": {"coordinates":[-0.14482721166601,51.50780461316472],"type":"Point"}
}