{
  "type": "Feature",
  "properties": {
    "iso:country":"GB",
    "wof:name":"PE1 3PR",
    "wof:placetype":"postalcode"
},
  "geometry": {"coordinates":[-0.24468882169059,52.59486624576673],"type":"Point"}
}