{
  "type": "Feature",
  "properties": {
    "iso:country":"GB",
    "wof:name":"E18 1DD",
    "wof:placetype":"postalcode"
},
  "geometry": {"coordinates":[0.02894881118248,51.59403523260002],"type":"Point"}
}