{
  "type": "Feature",
  "properties": {
    "date:inception_lower": "1980-01-01",
    "date:inception_upper": "1980-01-01",
    "iso:country": "GB",
    "wof:name": "BN20 7BL",
    "wof:placetype": "postalcode"
  },
  "geometry": {"coordinates":[0.285647,50.762738],"type":"Point"}
}
