{
  "type": "Feature",
  "properties": {
    "iso:country":"GB",
    "wof:name":"TN14 7AH",
    "wof:placetype":"postalcode"
},
  "geometry": {"coordinates":[0.14701903064864,51.33601376867918],"type":"Point"}
}