{
  "type": "Feature",
  "properties": {
    "iso:country":"GB",
    "wof:name":"CF24 3EB",
    "wof:placetype":"postalcode"
},
  "geometry": {"coordinates":[-3.16527152232375,51.48937310137966],"type":"Point"}
}