{
  "type": "Feature",
  "properties": {
    "date:inception_lower": "2012-07-01",
    "date:inception_upper": "2012-07-01",
    "iso:country": "GB",
    "wof:name": "WS12 4GF",
    "wof:placetype": "postalcode"
  },
  "geometry": {"coordinates":[-2.040769,52.719162],"type":"Point"}
}
