{
  "type": "Feature",
  "properties": {
    "iso:country":"GB",
    "wof:name":"WS12 4GF",
    "wof:placetype":"postalcode"
},
  "geometry": {"coordinates":[-2.04062534122241,52.71911018807538],"type":"Point"}
}