{
  "type": "Feature",
  "properties": {
    "iso:country":"GB",
    "wof:name":"RG23 8TH",
    "wof:placetype":"postalcode"
},
  "geometry": {"coordinates":[-1.1391952646726,51.28603112413857],"type":"Point"}
}