{
  "type": "Feature",
  "properties": {
    "iso:country": "GB",
    "wof:name": "RG23 8TH",
    "wof:placetype": "postalcode"
  },
  "geometry": {"coordinates":[-1.139176,51.286031],"type":"Point"}
}
