{
  "type": "Feature",
  "properties": {
    "date:inception_lower":"1995-07-01",
    "date:inception_upper":"1995-07-31",
    "iso:country":"GB",
    "wof:name":"RG23 8TH",
    "wof:placetype":"postalcode"
},
  "geometry": {"coordinates":[-1.139176,51.286031],"type":"Point"}
}