{
  "type": "Feature",
  "properties": {
    "iso:country":"GB",
    "wof:name":"WR11 4TF",
    "wof:placetype":"postalcode"
},
  "geometry": {"coordinates":[-1.94550094292978,52.12442213908763],"type":"Point"}
}