{
  "type": "Feature",
  "properties": {
    "date:inception_lower": "2005-10-01",
    "date:inception_upper": "2005-10-01",
    "iso:country": "GB",
    "wof:name": "WR11 4TF",
    "wof:placetype": "postalcode"
  },
  "geometry": {"coordinates":[-1.945501,52.124422],"type":"Point"}
}
