{
  "type": "Feature",
  "properties": {
    "iso:country":"GB",
    "wof:name":"EX2 9LE",
    "wof:placetype":"postalcode"
},
  "geometry": {"coordinates":[-3.53924174427585,50.70790456641251],"type":"Point"}
}