{
  "type": "Feature",
  "properties": {
    "iso:country":"GB",
    "wof:name":"EH3 6QH",
    "wof:placetype":"postalcode"
},
  "geometry": {"coordinates":[-3.19868864395482,55.95819348012434],"type":"Point"}
}