{
  "type": "Feature",
  "properties": {
    "date:inception_lower":"2014-06-01",
    "date:inception_upper":"2014-06-30",
    "iso:country":"GB",
    "wof:name":"UB10 0FJ",
    "wof:placetype":"postalcode"
},
  "geometry": {"coordinates":[-0.470401,51.538121],"type":"Point"}
}