{
  "type": "Feature",
  "properties": {
    "iso:country": "GB",
    "wof:name": "UB10 0FJ",
    "wof:placetype": "postalcode"
  },
  "geometry": {"coordinates":[-0.470401,51.538121],"type":"Point"}
}
