{
  "type": "Feature",
  "properties": {
    "iso:country":"GB",
    "wof:name":"UB10 0FJ",
    "wof:placetype":"postalcode"
},
  "geometry": {"coordinates":[-0.47040071953461,51.53812080142561],"type":"Point"}
}