{
  "type": "Feature",
  "properties": {
    "iso:country":"GB",
    "wof:name":"N1 5DD",
    "wof:placetype":"postalcode"
},
  "geometry": {"coordinates":[-0.08783194159393,51.53642076081913],"type":"Point"}
}