{
  "type": "Feature",
  "properties": {
    "date:inception_lower": "1980-01-01",
    "date:inception_upper": "1980-01-01",
    "iso:country": "GB",
    "wof:name": "SS6 7EQ",
    "wof:placetype": "postalcode"
  },
  "geometry": {"coordinates":[0.60724,51.587674],"type":"Point"}
}
