{
  "type": "Feature",
  "properties": {
    "iso:country":"GB",
    "wof:name":"SS6 7EQ",
    "wof:placetype":"postalcode"
},
  "geometry": {"coordinates":[0.60723952730221,51.58767359713734],"type":"Point"}
}