{
  "type": "Feature",
  "properties": {
    "iso:country":"GB",
    "wof:name":"HX2 0UE",
    "wof:placetype":"postalcode"
},
  "geometry": {"coordinates":[-1.91589845488184,53.74623039987911],"type":"Point"}
}