{
  "type": "Feature",
  "properties": {
    "date:inception_lower": "1980-01-01",
    "date:inception_upper": "1980-01-01",
    "iso:country": "GB",
    "wof:name": "SA32 7AE",
    "wof:placetype": "postalcode"
  },
  "geometry": {"coordinates":[-4.247936,51.883575],"type":"Point"}
}
