{
  "type": "Feature",
  "properties": {
    "iso:country": "GB",
    "wof:name": "SA32 7AE",
    "wof:placetype": "postalcode"
  },
  "geometry": {"coordinates":[-4.249761,51.882569],"type":"Point"}
}
