{
  "type": "Feature",
  "properties": {
    "iso:country":"GB",
    "wof:name":"SA32 7AE",
    "wof:placetype":"postalcode"
},
  "geometry": {"coordinates":[-4.24791520563373,51.88356584875193],"type":"Point"}
}