{
  "type": "Feature",
  "properties": {
    "date:inception_lower":"1980-01-01",
    "date:inception_upper":"1980-01-31",
    "iso:country":"GB",
    "wof:name":"SA48 7LB",
    "wof:placetype":"postalcode"
},
  "geometry": {"coordinates":[-4.144812,52.105855],"type":"Point"}
}