{
  "type": "Feature",
  "properties": {
    "iso:country":"GB",
    "wof:name":"SA48 7LB",
    "wof:placetype":"postalcode"
},
  "geometry": {"coordinates":[-4.14481183936384,52.10585467113432],"type":"Point"}
}