{
  "type": "Feature",
  "properties": {
    "iso:country":"GB",
    "wof:name":"TW9 3JS",
    "wof:placetype":"postalcode"
},
  "geometry": {"coordinates":[-0.28998679578454,51.47762028923624],"type":"Point"}
}