{
  "type": "Feature",
  "properties": {
    "iso:country": "GB",
    "wof:name": "EN2 8BA",
    "wof:placetype": "postalcode"
  },
  "geometry": {"coordinates":[-0.110995,51.68423],"type":"Point"}
}
