{
  "type": "Feature",
  "properties": {
    "iso:country":"GB",
    "wof:name":"EN2 8BA",
    "wof:placetype":"postalcode"
},
  "geometry": {"coordinates":[-0.11102073589707,51.68422696252836],"type":"Point"}
}