{
  "type": "Feature",
  "properties": {
    "iso:country":"GB",
    "wof:name":"L30 0PP",
    "wof:placetype":"postalcode"
},
  "geometry": {"coordinates":[-2.98368401370661,53.49269686722811],"type":"Point"}
}