{
  "type": "Feature",
  "properties": {
    "date:inception_lower": "1980-01-01",
    "date:inception_upper": "1980-01-01",
    "iso:country": "GB",
    "wof:name": "L30 0PP",
    "wof:placetype": "postalcode"
  },
  "geometry": {"coordinates":[-2.983684,53.492697],"type":"Point"}
}
