{
  "type": "Feature",
  "properties": {
    "date:inception_lower": "2021-07-01",
    "date:inception_upper": "2021-07-01",
    "iso:country": "GB",
    "wof:name": "SY11 4FJ",
    "wof:placetype": "postalcode"
  },
  "geometry": {"coordinates":[-2.973409,52.825467],"type":"Point"}
}
