{
  "type": "Feature",
  "properties": {
    "iso:country":"GB",
    "wof:name":"LS22 6SJ",
    "wof:placetype":"postalcode"
},
  "geometry": {"coordinates":[-1.394852182699,53.93448003923464],"type":"Point"}
}