{
  "type": "Feature",
  "properties": {
    "date:inception_lower": "1980-01-01",
    "date:inception_upper": "1980-01-01",
    "iso:country": "GB",
    "wof:name": "NW2 2TJ",
    "wof:placetype": "postalcode"
  },
  "geometry": {"coordinates":[-0.198678,51.561235],"type":"Point"}
}
