{
  "type": "Feature",
  "properties": {
    "iso:country":"GB",
    "wof:name":"NW2 2TJ",
    "wof:placetype":"postalcode"
},
  "geometry": {"coordinates":[-0.19806535650623,51.56094348929463],"type":"Point"}
}