{
  "type": "Feature",
  "properties": {
    "iso:country":"GB",
    "wof:name":"BN8 5PZ",
    "wof:placetype":"postalcode"
},
  "geometry": {"coordinates":[0.05486277195591,50.89351602659794],"type":"Point"}
}