{
  "type": "Feature",
  "properties": {
    "date:inception_lower": "1980-01-01",
    "date:inception_upper": "1980-01-01",
    "iso:country": "GB",
    "wof:name": "CF37 2ER",
    "wof:placetype": "postalcode"
  },
  "geometry": {"coordinates":[-3.3447,51.610256],"type":"Point"}
}
