{
  "type": "Feature",
  "properties": {
    "iso:country":"GB",
    "wof:name":"CF37 2ER",
    "wof:placetype":"postalcode"
},
  "geometry": {"coordinates":[-3.34469955131749,51.61025554927061],"type":"Point"}
}