{
  "type": "Feature",
  "properties": {
    "date:inception_lower": "2016-12-01",
    "date:inception_upper": "2016-12-01",
    "iso:country": "GB",
    "wof:name": "WF1 2GF",
    "wof:placetype": "postalcode"
  },
  "geometry": {"coordinates":[-1.502847,53.683983],"type":"Point"}
}
