{
  "type": "Feature",
  "properties": {
    "iso:country":"GB",
    "wof:name":"GL51 7NG",
    "wof:placetype":"postalcode"
},
  "geometry": {"coordinates":[-2.11164347780993,51.90517986008219],"type":"Point"}
}