{
  "type": "Feature",
  "properties": {
    "date:inception_lower": "1980-01-01",
    "date:inception_upper": "1980-01-01",
    "iso:country": "GB",
    "wof:name": "GL51 7NG",
    "wof:placetype": "postalcode"
  },
  "geometry": {"coordinates":[-2.111643,51.90518],"type":"Point"}
}
