{
  "type": "Feature",
  "properties": {
    "iso:country": "GB",
    "wof:name": "TN25 4QS",
    "wof:placetype": "postalcode"
  },
  "geometry": {"coordinates":[0.879691,51.176151],"type":"Point"}
}
