{
  "type": "Feature",
  "properties": {
    "iso:country":"GB",
    "wof:name":"TN25 4QS",
    "wof:placetype":"postalcode"
},
  "geometry": {"coordinates":[0.87969085103621,51.17615087502358],"type":"Point"}
}