{
  "type": "Feature",
  "properties": {
    "iso:country":"GB",
    "wof:name":"SS3 9TJ",
    "wof:placetype":"postalcode"
},
  "geometry": {"coordinates":[0.79714701125147,51.53661222474349],"type":"Point"}
}