{
  "type": "Feature",
  "properties": {
    "iso:country": "GB",
    "wof:name": "ZE2 9EB",
    "wof:placetype": "postalcode"
  },
  "geometry": {"coordinates":[-0.863983,60.758788],"type":"Point"}
}
