{
  "type": "Feature",
  "properties": {
    "iso:country":"GB",
    "wof:name":"ZE2 9EB",
    "wof:placetype":"postalcode"
},
  "geometry": {"coordinates":[-0.86398302861442,60.75878786046012],"type":"Point"}
}