{
  "type": "Feature",
  "properties": {
    "iso:country": "GB",
    "wof:name": "KY6 2LD",
    "wof:placetype": "postalcode"
  },
  "geometry": {"coordinates":[-3.205687,56.189138],"type":"Point"}
}
