{
  "type": "Feature",
  "properties": {
    "iso:country":"GB",
    "wof:name":"MK43 0UN",
    "wof:placetype":"postalcode"
},
  "geometry": {"coordinates":[-0.54417306696547,52.06485672647533],"type":"Point"}
}