{
  "type": "Feature",
  "properties": {
    "iso:country":"GB",
    "wof:name":"TW15 1PW",
    "wof:placetype":"postalcode"
},
  "geometry": {"coordinates":[-0.44110130245999,51.42912698081124],"type":"Point"}
}