{
  "type": "Feature",
  "properties": {
    "iso:country":"GB",
    "wof:name":"BS4 3SB",
    "wof:placetype":"postalcode"
},
  "geometry": {"coordinates":[-2.5519103812994,51.44391636588751],"type":"Point"}
}