{
  "type": "Feature",
  "properties": {
    "date:inception_lower":"1980-01-01",
    "date:inception_upper":"1980-01-31",
    "iso:country":"GB",
    "wof:name":"BS4 3SB",
    "wof:placetype":"postalcode"
},
  "geometry": {"coordinates":[-2.55191,51.443916],"type":"Point"}
}