{
  "type": "Feature",
  "properties": {
    "iso:country":"GB",
    "wof:name":"WA3 4HE",
    "wof:placetype":"postalcode"
},
  "geometry": {"coordinates":[-2.52822830878066,53.4553276664433],"type":"Point"}
}