{
  "type": "Feature",
  "properties": {
    "iso:country":"GB",
    "wof:name":"DL17 0RF",
    "wof:placetype":"postalcode"
},
  "geometry": {"coordinates":[-1.55302894157497,54.65438969316281],"type":"Point"}
}