{
  "type": "Feature",
  "properties": {
    "date:inception_lower": "1980-01-01",
    "date:inception_upper": "1980-01-01",
    "iso:country": "GB",
    "wof:name": "BS26 2BB",
    "wof:placetype": "postalcode"
  },
  "geometry": {"coordinates":[-2.816708,51.285458],"type":"Point"}
}
