{
  "type": "Feature",
  "properties": {
    "iso:country":"GB",
    "wof:name":"BS26 2BB",
    "wof:placetype":"postalcode"
},
  "geometry": {"coordinates":[-2.81693039536478,51.28539748888],"type":"Point"}
}