{
  "type": "Feature",
  "properties": {
    "date:inception_lower":"1985-10-01",
    "date:inception_upper":"1985-10-31",
    "iso:country":"GB",
    "wof:name":"GU7 2QS",
    "wof:placetype":"postalcode"
},
  "geometry": {"coordinates":[-0.619578,51.199507],"type":"Point"}
}