{
  "type": "Feature",
  "properties": {
    "iso:country":"GB",
    "wof:name":"GU7 2QS",
    "wof:placetype":"postalcode"
},
  "geometry": {"coordinates":[-0.61957808113654,51.19950658559761],"type":"Point"}
}