{
  "type": "Feature",
  "properties": {
    "iso:country":"GB",
    "wof:name":"KW16 3HJ",
    "wof:placetype":"postalcode"
},
  "geometry": {"coordinates":[-3.29198879533677,58.9731625809638],"type":"Point"}
}