{
  "type": "Feature",
  "properties": {
    "iso:country": "GB",
    "wof:name": "KW16 3HJ",
    "wof:placetype": "postalcode"
  },
  "geometry": {"coordinates":[-3.291989,58.973163],"type":"Point"}
}
