{
  "type": "Feature",
  "properties": {
    "date:inception_lower": "2002-07-01",
    "date:inception_upper": "2002-07-01",
    "iso:country": "GB",
    "wof:name": "KW16 3HJ",
    "wof:placetype": "postalcode"
  },
  "geometry": {"coordinates":[-3.291989,58.973163],"type":"Point"}
}
