{
  "type": "Feature",
  "properties": {
    "date:inception_lower":"1980-01-01",
    "date:inception_upper":"1980-01-31",
    "iso:country":"GB",
    "wof:name":"ST2 7DN",
    "wof:placetype":"postalcode"
},
  "geometry": {"coordinates":[-2.143702,53.049029],"type":"Point"}
}