{
  "type": "Feature",
  "properties": {
    "date:inception_lower": "1983-07-01",
    "date:inception_upper": "1983-07-01",
    "iso:country": "GB",
    "wof:name": "HD7 5DF",
    "wof:placetype": "postalcode"
  },
  "geometry": {"coordinates":[-1.877683,53.627213],"type":"Point"}
}
