{
  "type": "Feature",
  "properties": {
    "iso:country": "GB",
    "wof:name": "HD7 5DF",
    "wof:placetype": "postalcode"
  },
  "geometry": {"coordinates":[-1.877683,53.627213],"type":"Point"}
}
