{
  "type": "Feature",
  "properties": {
    "iso:country":"GB",
    "wof:name":"HD7 5DF",
    "wof:placetype":"postalcode"
},
  "geometry": {"coordinates":[-1.87768329202562,53.62721272565281],"type":"Point"}
}