{
  "type": "Feature",
  "properties": {
    "date:inception_lower": "2016-10-01",
    "date:inception_upper": "2016-10-01",
    "iso:country": "GB",
    "wof:name": "E15 1GB",
    "wof:placetype": "postalcode"
  },
  "geometry": {"coordinates":[-0.003516,51.548759],"type":"Point"}
}
