{
  "type": "Feature",
  "properties": {
    "iso:country": "GB",
    "wof:name": "E15 1GB",
    "wof:placetype": "postalcode"
  },
  "geometry": {"coordinates":[-0.003516,51.548759],"type":"Point"}
}
