{
  "type": "Feature",
  "properties": {
    "iso:country":"GB",
    "wof:name":"CF5 3LQ",
    "wof:placetype":"postalcode"
},
  "geometry": {"coordinates":[-3.2469190252321,51.49917967652697],"type":"Point"}
}