{
  "type": "Feature",
  "properties": {
    "date:inception_lower": "1980-01-01",
    "date:inception_upper": "1980-01-01",
    "iso:country": "GB",
    "wof:name": "CF5 3LQ",
    "wof:placetype": "postalcode"
  },
  "geometry": {"coordinates":[-3.246919,51.49918],"type":"Point"}
}
