{
  "type": "Feature",
  "properties": {
    "iso:country":"GB",
    "wof:name":"PO7 7DT",
    "wof:placetype":"postalcode"
},
  "geometry": {"coordinates":[-1.03022182957824,50.88002788113406],"type":"Point"}
}