{
  "type": "Feature",
  "properties": {
    "iso:country": "GB",
    "wof:name": "PO7 7DT",
    "wof:placetype": "postalcode"
  },
  "geometry": {"coordinates":[-1.030361,50.880065],"type":"Point"}
}
