{
  "type": "Feature",
  "properties": {
    "iso:country":"GB",
    "wof:name":"N15 5BE",
    "wof:placetype":"postalcode"
},
  "geometry": {"coordinates":[-0.08756887611162,51.58533568725729],"type":"Point"}
}