{
  "type": "Feature",
  "properties": {
    "iso:country":"GB",
    "wof:name":"WR13 6SQ",
    "wof:placetype":"postalcode"
},
  "geometry": {"coordinates":[-2.30432640672389,52.05778064429498],"type":"Point"}
}