{
  "type": "Feature",
  "properties": {
    "iso:country": "GB",
    "wof:name": "WR13 6SQ",
    "wof:placetype": "postalcode"
  },
  "geometry": {"coordinates":[-2.304424,52.057889],"type":"Point"}
}
