{
  "type": "Feature",
  "properties": {
    "iso:country":"GB",
    "wof:name":"SE5 7PR",
    "wof:placetype":"postalcode"
},
  "geometry": {"coordinates":[-0.09186699441717,51.47542689348167],"type":"Point"}
}