{
  "type": "Feature",
  "properties": {
    "date:inception_lower":"1983-07-01",
    "date:inception_upper":"1983-07-31",
    "iso:country":"GB",
    "wof:name":"BA11 2TL",
    "wof:placetype":"postalcode"
},
  "geometry": {"coordinates":[-2.302593,51.238249],"type":"Point"}
}