{
  "type": "Feature",
  "properties": {
    "iso:country":"GB",
    "wof:name":"W1K 2EG",
    "wof:placetype":"postalcode"
},
  "geometry": {"coordinates":[-0.15313779471779,51.50968931115882],"type":"Point"}
}