{
  "type": "Feature",
  "properties": {
    "iso:country": "GB",
    "wof:name": "TN2 4HF",
    "wof:placetype": "postalcode"
  },
  "geometry": {"coordinates":[0.324519,51.144266],"type":"Point"}
}
