{
  "type": "Feature",
  "properties": {
    "date:inception_lower": "1980-01-01",
    "date:inception_upper": "1980-01-01",
    "iso:country": "GB",
    "wof:name": "LA8 0DB",
    "wof:placetype": "postalcode"
  },
  "geometry": {"coordinates":[-2.680012,54.348982],"type":"Point"}
}
