{
  "type": "Feature",
  "properties": {
    "date:inception_lower": "1980-01-01",
    "date:inception_upper": "1980-01-01",
    "iso:country": "GB",
    "wof:name": "LA8 0DB",
    "wof:placetype": "postalcode"
  },
  "geometry": {"coordinates":[-2.672345,54.351362],"type":"Point"}
}
