{
  "type": "Feature",
  "properties": {
    "iso:country":"GB",
    "wof:name":"ME17 4JQ",
    "wof:placetype":"postalcode"
},
  "geometry": {"coordinates":[0.54067717410438,51.23017402509504],"type":"Point"}
}