{
  "type": "Feature",
  "properties": {
    "iso:country": "GB",
    "wof:name": "ME17 4JQ",
    "wof:placetype": "postalcode"
  },
  "geometry": {"coordinates":[0.540677,51.230174],"type":"Point"}
}
