{
  "type": "Feature",
  "properties": {
    "iso:country":"GB",
    "wof:name":"TR27 6BJ",
    "wof:placetype":"postalcode"
},
  "geometry": {"coordinates":[-5.35000872414211,50.15682166274009],"type":"Point"}
}