{
  "type": "Feature",
  "properties": {
    "iso:country":"GB",
    "wof:name":"OX18 4AE",
    "wof:placetype":"postalcode"
},
  "geometry": {"coordinates":[-1.61569844845153,51.77337406317152],"type":"Point"}
}