{
  "type": "Feature",
  "properties": {
    "date:inception_lower": "1991-09-01",
    "date:inception_upper": "1991-09-01",
    "iso:country": "GB",
    "wof:name": "OX18 4AE",
    "wof:placetype": "postalcode"
  },
  "geometry": {"coordinates":[-1.615698,51.773374],"type":"Point"}
}
