{
  "type": "Feature",
  "properties": {
    "iso:country": "GB",
    "wof:name": "OX18 4AE",
    "wof:placetype": "postalcode"
  },
  "geometry": {"coordinates":[-1.615698,51.773374],"type":"Point"}
}
