{
  "type": "Feature",
  "properties": {
    "iso:country":"GB",
    "wof:name":"CF33 4BG",
    "wof:placetype":"postalcode"
},
  "geometry": {"coordinates":[-3.70763344906618,51.51866140587171],"type":"Point"}
}