{
  "type": "Feature",
  "properties": {
    "iso:country":"GB",
    "wof:name":"B46 2RD",
    "wof:placetype":"postalcode"
},
  "geometry": {"coordinates":[-1.66892572703494,52.50000592647753],"type":"Point"}
}