{
  "type": "Feature",
  "properties": {
    "date:inception_lower": "2015-01-01",
    "date:inception_upper": "2015-01-01",
    "iso:country": "GB",
    "wof:name": "DN32 0XQ",
    "wof:placetype": "postalcode"
  },
  "geometry": {"coordinates":[-0.077361,53.572172],"type":"Point"}
}
