{
  "type": "Feature",
  "properties": {
    "iso:country": "GB",
    "wof:name": "PO1 2EZ",
    "wof:placetype": "postalcode"
  },
  "geometry": {"coordinates":[-1.102836,50.791527],"type":"Point"}
}
