{
  "type": "Feature",
  "properties": {
    "iso:country":"GB",
    "wof:name":"BS13 8QF",
    "wof:placetype":"postalcode"
},
  "geometry": {"coordinates":[-2.62281974415881,51.40493262511391],"type":"Point"}
}