{
  "type": "Feature",
  "properties": {
    "iso:country":"GB",
    "wof:name":"S65 3LP",
    "wof:placetype":"postalcode"
},
  "geometry": {"coordinates":[-1.32083810237539,53.43767799713578],"type":"Point"}
}