{
  "type": "Feature",
  "properties": {
    "iso:country":"GB",
    "wof:name":"WD3 1NQ",
    "wof:placetype":"postalcode"
},
  "geometry": {"coordinates":[-0.46838772740915,51.6323942859654],"type":"Point"}
}