{
  "type": "Feature",
  "properties": {
    "iso:country": "GB",
    "wof:name": "L7 2QB",
    "wof:placetype": "postalcode"
  },
  "geometry": {"coordinates":[-2.949842,53.40959],"type":"Point"}
}
