{
  "type": "Feature",
  "properties": {
    "iso:country":"GB",
    "wof:name":"L7 2QB",
    "wof:placetype":"postalcode"
},
  "geometry": {"coordinates":[-2.94984214194909,53.409590216594],"type":"Point"}
}