{
  "type": "Feature",
  "properties": {
    "iso:country":"GB",
    "wof:name":"N15 4JW",
    "wof:placetype":"postalcode"
},
  "geometry": {"coordinates":[-0.0793301994613,51.58935566363825],"type":"Point"}
}