{
  "type": "Feature",
  "properties": {
    "iso:country":"GB",
    "wof:name":"N7 6DB",
    "wof:placetype":"postalcode"
},
  "geometry": {"coordinates":[-0.11361335395245,51.55526378931825],"type":"Point"}
}