{
  "type": "Feature",
  "properties": {
    "iso:country":"GB",
    "wof:name":"CW12 1BH",
    "wof:placetype":"postalcode"
},
  "geometry": {"coordinates":[-2.21159809944508,53.16298000397306],"type":"Point"}
}