{
  "type": "Feature",
  "properties": {
    "iso:country":"GB",
    "wof:name":"TN4 9NH",
    "wof:placetype":"postalcode"
},
  "geometry": {"coordinates":[0.26339952930778,51.13935823678457],"type":"Point"}
}