{
  "type": "Feature",
  "properties": {
    "date:inception_lower": "1980-01-01",
    "date:inception_upper": "1980-01-01",
    "iso:country": "GB",
    "wof:name": "TN4 9NH",
    "wof:placetype": "postalcode"
  },
  "geometry": {"coordinates":[0.2634,51.139358],"type":"Point"}
}
