{
  "type": "Feature",
  "properties": {
    "iso:country": "GB",
    "wof:name": "EC2A 4JY",
    "wof:placetype": "postalcode"
  },
  "geometry": {"coordinates":[-0.084634,51.523293],"type":"Point"}
}
