{
  "type": "Feature",
  "properties": {
    "iso:country":"GB",
    "wof:name":"EC2A 4JY",
    "wof:placetype":"postalcode"
},
  "geometry": {"coordinates":[-0.08463393699877,51.52329342243353],"type":"Point"}
}