{
  "type": "Feature",
  "properties": {
    "date:inception_lower":"1980-01-01",
    "date:inception_upper":"1980-01-31",
    "iso:country":"GB",
    "wof:name":"SE6 1UR",
    "wof:placetype":"postalcode"
},
  "geometry": {"coordinates":[-0.004163,51.44224],"type":"Point"}
}