{
  "type": "Feature",
  "properties": {
    "iso:country":"GB",
    "wof:name":"SE6 1UR",
    "wof:placetype":"postalcode"
},
  "geometry": {"coordinates":[-0.00416315470616,51.44224035305216],"type":"Point"}
}