{
  "type": "Feature",
  "properties": {
    "iso:country": "GB",
    "wof:name": "WV11 3NZ",
    "wof:placetype": "postalcode"
  },
  "geometry": {"coordinates":[-2.057558,52.604422],"type":"Point"}
}
