{
  "type": "Feature",
  "properties": {
    "iso:country":"GB",
    "wof:name":"TD5 7RD",
    "wof:placetype":"postalcode"
},
  "geometry": {"coordinates":[-2.42404162677612,55.60505925677205],"type":"Point"}
}