{
  "type": "Feature",
  "properties": {
    "iso:country":"GB",
    "wof:name":"EH51 0DP",
    "wof:placetype":"postalcode"
},
  "geometry": {"coordinates":[-3.6109602107314,56.01025741007341],"type":"Point"}
}