{
  "type": "Feature",
  "properties": {
    "date:inception_lower": "2022-07-01",
    "date:inception_upper": "2022-07-01",
    "iso:country": "GB",
    "wof:name": "G75 7AT",
    "wof:placetype": "postalcode"
  },
  "geometry": {"coordinates":[-4.228902,55.740929],"type":"Point"}
}
