{
  "type": "Feature",
  "properties": {
    "date:inception_lower":"1994-12-01",
    "date:inception_upper":"1994-12-31",
    "iso:country":"GB",
    "wof:name":"LL18 4GD",
    "wof:placetype":"postalcode"
},
  "geometry": {"coordinates":[-3.465177,53.321549],"type":"Point"}
}