{
  "type": "Feature",
  "properties": {
    "iso:country":"GB",
    "wof:name":"M6 7QP",
    "wof:placetype":"postalcode"
},
  "geometry": {"coordinates":[-2.31176618030827,53.49871239383837],"type":"Point"}
}