{
  "type": "Feature",
  "properties": {
    "date:inception_lower":"1980-01-01",
    "date:inception_upper":"1980-01-31",
    "iso:country":"GB",
    "wof:name":"TQ9 5RD",
    "wof:placetype":"postalcode"
},
  "geometry": {"coordinates":[-3.674561,50.43086],"type":"Point"}
}