{
  "type": "Feature",
  "properties": {
    "iso:country":"GB",
    "wof:name":"WD18 6AE",
    "wof:placetype":"postalcode"
},
  "geometry": {"coordinates":[-0.4187684844724,51.6473647219359],"type":"Point"}
}