{
  "type": "Feature",
  "properties": {
    "iso:country":"GB",
    "wof:name":"ME19 5BD",
    "wof:placetype":"postalcode"
},
  "geometry": {"coordinates":[0.37403070094929,51.30732209805777],"type":"Point"}
}