{
  "type": "Feature",
  "properties": {
    "iso:country": "GB",
    "wof:name": "GL5 5HF",
    "wof:placetype": "postalcode"
  },
  "geometry": {"coordinates":[-2.226837,51.703193],"type":"Point"}
}
