{
  "type": "Feature",
  "properties": {
    "iso:country":"GB",
    "wof:name":"GL5 5HF",
    "wof:placetype":"postalcode"
},
  "geometry": {"coordinates":[-2.22683698532627,51.70319272827259],"type":"Point"}
}