{
  "type": "Feature",
  "properties": {
    "iso:country":"GB",
    "wof:name":"G75 0DN",
    "wof:placetype":"postalcode"
},
  "geometry": {"coordinates":[-4.18488569181446,55.75923251138111],"type":"Point"}
}