{
  "type": "Feature",
  "properties": {
    "iso:country":"GB",
    "wof:name":"SW6 1LG",
    "wof:placetype":"postalcode"
},
  "geometry": {"coordinates":[-0.19815655896044,51.4845002560992],"type":"Point"}
}