{
  "type": "Feature",
  "properties": {
    "iso:country":"GB",
    "wof:name":"EX23 8AW",
    "wof:placetype":"postalcode"
},
  "geometry": {"coordinates":[-4.53647977707841,50.82567515126395],"type":"Point"}
}