{
  "type": "Feature",
  "properties": {
    "iso:country":"GB",
    "wof:name":"IP14 3NQ",
    "wof:placetype":"postalcode"
},
  "geometry": {"coordinates":[0.9370834294367,52.22697204921608],"type":"Point"}
}