{
  "type": "Feature",
  "properties": {
    "iso:country": "GB",
    "wof:name": "EN2 8EG",
    "wof:placetype": "postalcode"
  },
  "geometry": {"coordinates":[-0.095223,51.655628],"type":"Point"}
}
