{
  "type": "Feature",
  "properties": {
    "iso:country":"GB",
    "wof:name":"BN16 4FY",
    "wof:placetype":"postalcode"
},
  "geometry": {"coordinates":[-0.48024761608848,50.82239029643753],"type":"Point"}
}