{
  "type": "Feature",
  "properties": {
    "iso:country":"GB",
    "wof:name":"BH8 0HD",
    "wof:placetype":"postalcode"
},
  "geometry": {"coordinates":[-1.85111482652022,50.75845077873014],"type":"Point"}
}