{
  "type": "Feature",
  "properties": {
    "iso:country":"GB",
    "wof:name":"NR33 7QG",
    "wof:placetype":"postalcode"
},
  "geometry": {"coordinates":[1.7068060354141,52.41935612712302],"type":"Point"}
}