{
  "type": "Feature",
  "properties": {
    "iso:country":"GB",
    "wof:name":"NW1 7JH",
    "wof:placetype":"postalcode"
},
  "geometry": {"coordinates":[-0.13978890224047,51.53561953143065],"type":"Point"}
}