{
  "type": "Feature",
  "properties": {
    "iso:country": "GB",
    "wof:name": "HP14 4RY",
    "wof:placetype": "postalcode"
  },
  "geometry": {"coordinates":[-0.778933,51.664933],"type":"Point"}
}
