{
  "type": "Feature",
  "properties": {
    "date:inception_lower": "2003-11-01",
    "date:inception_upper": "2003-11-01",
    "iso:country": "GB",
    "wof:name": "HP14 4RY",
    "wof:placetype": "postalcode"
  },
  "geometry": {"coordinates":[-0.778933,51.664933],"type":"Point"}
}
