{
  "type": "Feature",
  "properties": {
    "iso:country":"GB",
    "wof:name":"HP14 4RY",
    "wof:placetype":"postalcode"
},
  "geometry": {"coordinates":[-0.77893343562002,51.66493335861344],"type":"Point"}
}