{
  "type": "Feature",
  "properties": {
    "iso:country":"GB",
    "wof:name":"M41 0UB",
    "wof:placetype":"postalcode"
},
  "geometry": {"coordinates":[-2.35425696884645,53.45112569620434],"type":"Point"}
}