{
  "type": "Feature",
  "properties": {
    "date:inception_lower": "2000-06-01",
    "date:inception_upper": "2000-06-01",
    "iso:country": "GB",
    "wof:name": "ST4 5AX",
    "wof:placetype": "postalcode"
  },
  "geometry": {"coordinates":[-2.194192,52.991561],"type":"Point"}
}
