{
  "type": "Feature",
  "properties": {
    "iso:country":"GB",
    "wof:name":"TQ2 5LU",
    "wof:placetype":"postalcode"
},
  "geometry": {"coordinates":[-3.54032139674135,50.46648664994584],"type":"Point"}
}