{
  "type": "Feature",
  "properties": {
    "date:inception_lower": "1983-07-01",
    "date:inception_upper": "1983-07-01",
    "iso:country": "GB",
    "wof:name": "TQ2 5LU",
    "wof:placetype": "postalcode"
  },
  "geometry": {"coordinates":[-3.540321,50.466487],"type":"Point"}
}
