{
  "type": "Feature",
  "properties": {
    "iso:country":"GB",
    "wof:name":"BB3 0RN",
    "wof:placetype":"postalcode"
},
  "geometry": {"coordinates":[-2.47299531242153,53.71945755268376],"type":"Point"}
}