{
  "type": "Feature",
  "properties": {
    "iso:country":"GB",
    "wof:name":"LE17 4LE",
    "wof:placetype":"postalcode"
},
  "geometry": {"coordinates":[-1.18353250862799,52.47335297746478],"type":"Point"}
}