{
  "type": "Feature",
  "properties": {
    "iso:country":"GB",
    "wof:name":"RM13 7YB",
    "wof:placetype":"postalcode"
},
  "geometry": {"coordinates":[0.1975376456368,51.53588204509614],"type":"Point"}
}