{
  "type": "Feature",
  "properties": {
    "date:inception_lower":"1980-01-01",
    "date:inception_upper":"1980-01-31",
    "iso:country":"GB",
    "wof:name":"RM13 7YB",
    "wof:placetype":"postalcode"
},
  "geometry": {"coordinates":[0.197538,51.535882],"type":"Point"}
}