{
  "type": "Feature",
  "properties": {
    "iso:country":"GB",
    "wof:name":"LE12 5ND",
    "wof:placetype":"postalcode"
},
  "geometry": {"coordinates":[-1.2485702180512,52.81869057927167],"type":"Point"}
}