{
  "type": "Feature",
  "properties": {
    "iso:country":"GB",
    "wof:name":"WF12 7DX",
    "wof:placetype":"postalcode"
},
  "geometry": {"coordinates":[-1.6150603915105,53.69984793604665],"type":"Point"}
}