{
  "type": "Feature",
  "properties": {
    "iso:country": "GB",
    "wof:name": "MK3 5EE",
    "wof:placetype": "postalcode"
  },
  "geometry": {"coordinates":[-0.76443,51.986936],"type":"Point"}
}
