{
  "type": "Feature",
  "properties": {
    "iso:country":"GB",
    "wof:name":"MK3 5EE",
    "wof:placetype":"postalcode"
},
  "geometry": {"coordinates":[-0.76442977850574,51.98693646272227],"type":"Point"}
}