{
  "type": "Feature",
  "properties": {
    "iso:country": "GB",
    "wof:name": "ME15 6UQ",
    "wof:placetype": "postalcode"
  },
  "geometry": {"coordinates":[0.521156,51.259835],"type":"Point"}
}
