{
  "type": "Feature",
  "properties": {
    "date:inception_lower":"1980-01-01",
    "date:inception_upper":"1980-01-31",
    "iso:country":"GB",
    "wof:name":"ME15 6UQ",
    "wof:placetype":"postalcode"
},
  "geometry": {"coordinates":[0.521156,51.259835],"type":"Point"}
}