{
  "type": "Feature",
  "properties": {
    "iso:country":"GB",
    "wof:name":"CV32 4JG",
    "wof:placetype":"postalcode"
},
  "geometry": {"coordinates":[-1.53058182156979,52.29133511452059],"type":"Point"}
}