{
  "type": "Feature",
  "properties": {
    "iso:country":"GB",
    "wof:name":"L3 9TX",
    "wof:placetype":"postalcode"
},
  "geometry": {"coordinates":[-2.99363811354503,53.40909889719696],"type":"Point"}
}