{
  "type": "Feature",
  "properties": {
    "iso:country":"GB",
    "wof:name":"NN13 5RD",
    "wof:placetype":"postalcode"
},
  "geometry": {"coordinates":[-1.20313213073925,51.99625022378362],"type":"Point"}
}