{
  "type": "Feature",
  "properties": {
    "date:inception_lower": "1981-09-01",
    "date:inception_upper": "1981-09-01",
    "iso:country": "GB",
    "wof:name": "NN13 5RD",
    "wof:placetype": "postalcode"
  },
  "geometry": {"coordinates":[-1.203132,51.99625],"type":"Point"}
}
