{
  "type": "Feature",
  "properties": {
    "iso:country":"GB",
    "wof:name":"TN27 0BT",
    "wof:placetype":"postalcode"
},
  "geometry": {"coordinates":[0.75006232912409,51.20897050897075],"type":"Point"}
}