{
  "type": "Feature",
  "properties": {
    "date:inception_lower": "1980-01-01",
    "date:inception_upper": "1980-01-01",
    "iso:country": "GB",
    "wof:name": "TN27 0BT",
    "wof:placetype": "postalcode"
  },
  "geometry": {"coordinates":[0.750013,51.20908],"type":"Point"}
}
