{
  "type": "Feature",
  "properties": {
    "iso:country":"GB",
    "wof:name":"TF4 2AR",
    "wof:placetype":"postalcode"
},
  "geometry": {"coordinates":[-2.45916965288396,52.66747136191454],"type":"Point"}
}