{
  "type": "Feature",
  "properties": {
    "iso:country": "GB",
    "wof:name": "TF4 2AR",
    "wof:placetype": "postalcode"
  },
  "geometry": {"coordinates":[-2.45917,52.667471],"type":"Point"}
}
