{
  "type": "Feature",
  "properties": {
    "iso:country":"GB",
    "wof:name":"SM2 5QY",
    "wof:placetype":"postalcode"
},
  "geometry": {"coordinates":[-0.18568395504096,51.34682920666867],"type":"Point"}
}