{
  "type": "Feature",
  "properties": {
    "iso:country":"GB",
    "wof:name":"NR10 4SE",
    "wof:placetype":"postalcode"
},
  "geometry": {"coordinates":[1.13013617597266,52.77836478899319],"type":"Point"}
}