{
  "type": "Feature",
  "properties": {
    "date:inception_lower": "1980-01-01",
    "date:inception_upper": "1980-01-01",
    "iso:country": "GB",
    "wof:name": "NR10 4SE",
    "wof:placetype": "postalcode"
  },
  "geometry": {"coordinates":[1.130158,52.778391],"type":"Point"}
}
