{
  "type": "Feature",
  "properties": {
    "iso:country": "GB",
    "wof:name": "NR10 4SE",
    "wof:placetype": "postalcode"
  },
  "geometry": {"coordinates":[1.130158,52.778391],"type":"Point"}
}
