{
  "type": "Feature",
  "properties": {
    "iso:country":"GB",
    "wof:name":"TS15 0AU",
    "wof:placetype":"postalcode"
},
  "geometry": {"coordinates":[-1.32083574242206,54.46603052936656],"type":"Point"}
}