{
  "type": "Feature",
  "properties": {
    "date:inception_lower": "1980-01-01",
    "date:inception_upper": "1980-01-01",
    "iso:country": "GB",
    "wof:name": "TS15 0AU",
    "wof:placetype": "postalcode"
  },
  "geometry": {"coordinates":[-1.320836,54.466031],"type":"Point"}
}
