{
  "type": "Feature",
  "properties": {
    "iso:country":"GB",
    "wof:name":"N2 0XB",
    "wof:placetype":"postalcode"
},
  "geometry": {"coordinates":[-0.16683164126808,51.58818322089374],"type":"Point"}
}