{
  "type": "Feature",
  "properties": {
    "iso:country":"GB",
    "wof:name":"EX2 8SD",
    "wof:placetype":"postalcode"
},
  "geometry": {"coordinates":[-3.53583388328178,50.70460400783111],"type":"Point"}
}