{
  "type": "Feature",
  "properties": {
    "iso:country":"GB",
    "wof:name":"NR14 6NZ",
    "wof:placetype":"postalcode"
},
  "geometry": {"coordinates":[1.55913130395355,52.51836747700325],"type":"Point"}
}