{
  "type": "Feature",
  "properties": {
    "iso:country": "GB",
    "wof:name": "HU9 2JG",
    "wof:placetype": "postalcode"
  },
  "geometry": {"coordinates":[-0.310459,53.753824],"type":"Point"}
}
