{
  "type": "Feature",
  "properties": {
    "date:inception_lower": "2022-06-01",
    "date:inception_upper": "2022-06-01",
    "iso:country": "GB",
    "wof:name": "CW12 4QE",
    "wof:placetype": "postalcode"
  },
  "geometry": {"coordinates":[-2.247009,53.174974],"type":"Point"}
}
