{
  "type": "Feature",
  "properties": {
    "iso:country": "GB",
    "wof:name": "IV30 8UP",
    "wof:placetype": "postalcode"
  },
  "geometry": {"coordinates":[-3.42608,57.648286],"type":"Point"}
}
