{
  "type": "Feature",
  "properties": {
    "date:inception_lower": "1998-12-01",
    "date:inception_upper": "1998-12-01",
    "iso:country": "GB",
    "wof:name": "IV30 8UP",
    "wof:placetype": "postalcode"
  },
  "geometry": {"coordinates":[-3.432882,57.646613],"type":"Point"}
}
