{
  "type": "Feature",
  "properties": {
    "iso:country":"GB",
    "wof:name":"IV30 8UP",
    "wof:placetype":"postalcode"
},
  "geometry": {"coordinates":[-3.42608049433137,57.64828581454233],"type":"Point"}
}