{
  "type": "Feature",
  "properties": {
    "iso:country": "GB",
    "wof:name": "TS5 8HB",
    "wof:placetype": "postalcode"
  },
  "geometry": {"coordinates":[-1.253465,54.531006],"type":"Point"}
}
