{
  "type": "Feature",
  "properties": {
    "iso:country":"GB",
    "wof:name":"TS5 8HB",
    "wof:placetype":"postalcode"
},
  "geometry": {"coordinates":[-1.25346506371781,54.53100585547347],"type":"Point"}
}