{
  "type": "Feature",
  "properties": {
    "iso:country":"GB",
    "wof:name":"W1T 5AU",
    "wof:placetype":"postalcode"
},
  "geometry": {"coordinates":[-0.13779464171216,51.524068515442],"type":"Point"}
}