{
  "type": "Feature",
  "properties": {
    "iso:country":"GB",
    "wof:name":"SE28 8RP",
    "wof:placetype":"postalcode"
},
  "geometry": {"coordinates":[0.10445459505856,51.50047575961798],"type":"Point"}
}