{
  "type": "Feature",
  "properties": {
    "iso:country": "GB",
    "wof:name": "E7 0AZ",
    "wof:placetype": "postalcode"
  },
  "geometry": {"coordinates":[0.020612,51.552894],"type":"Point"}
}
