{
  "type": "Feature",
  "properties": {
    "iso:country":"GB",
    "wof:name":"E7 0AZ",
    "wof:placetype":"postalcode"
},
  "geometry": {"coordinates":[0.02061187976936,51.55289396280581],"type":"Point"}
}