{
  "type": "Feature",
  "properties": {
    "iso:country":"GB",
    "wof:name":"LE3 6SD",
    "wof:placetype":"postalcode"
},
  "geometry": {"coordinates":[-1.18495309567467,52.63379976134942],"type":"Point"}
}