{
  "type": "Feature",
  "properties": {
    "iso:country":"GB",
    "wof:name":"M27 9TR",
    "wof:placetype":"postalcode"
},
  "geometry": {"coordinates":[-2.34264135265251,53.51765634219345],"type":"Point"}
}