{
  "type": "Feature",
  "properties": {
    "iso:country":"GB",
    "wof:name":"LE12 8GW",
    "wof:placetype":"postalcode"
},
  "geometry": {"coordinates":[-1.14675095221719,52.75025571866944],"type":"Point"}
}