{
  "type": "Feature",
  "properties": {
    "iso:country": "GB",
    "wof:name": "LE12 8GW",
    "wof:placetype": "postalcode"
  },
  "geometry": {"coordinates":[-1.146751,52.750256],"type":"Point"}
}
