{
  "type": "Feature",
  "properties": {
    "iso:country": "GB",
    "wof:name": "S73 0RL",
    "wof:placetype": "postalcode"
  },
  "geometry": {"coordinates":[-1.393433,53.514256],"type":"Point"}
}
