{
  "type": "Feature",
  "properties": {
    "iso:country":"GB",
    "wof:name":"CF10 1FJ",
    "wof:placetype":"postalcode"
},
  "geometry": {"coordinates":[-3.17631934912012,51.47763623752713],"type":"Point"}
}