{
  "type": "Feature",
  "properties": {
    "date:inception_lower": "2015-02-01",
    "date:inception_upper": "2015-02-01",
    "iso:country": "GB",
    "wof:name": "SY11 2WA",
    "wof:placetype": "postalcode"
  },
  "geometry": {"coordinates":[-3.044185,52.864918],"type":"Point"}
}
