{
  "type": "Feature",
  "properties": {
    "iso:country":"GB",
    "wof:name":"RH15 9PU",
    "wof:placetype":"postalcode"
},
  "geometry": {"coordinates":[-0.1483880623956,50.95789195101393],"type":"Point"}
}