{
  "type": "Feature",
  "properties": {
    "date:inception_lower": "2018-09-01",
    "date:inception_upper": "2018-09-01",
    "iso:country": "GB",
    "wof:name": "SG6 9GR",
    "wof:placetype": "postalcode"
  },
  "geometry": {"coordinates":[-0.209223,51.981602],"type":"Point"}
}
