{
  "type": "Feature",
  "properties": {
    "iso:country":"GB",
    "wof:name":"SN16 9FR",
    "wof:placetype":"postalcode"
},
  "geometry": {"coordinates":[-2.09983621078855,51.58857837726589],"type":"Point"}
}