{
  "type": "Feature",
  "properties": {
    "date:inception_lower":"2010-03-01",
    "date:inception_upper":"2010-03-31",
    "iso:country":"GB",
    "wof:name":"SN16 9FR",
    "wof:placetype":"postalcode"
},
  "geometry": {"coordinates":[-2.099836,51.588578],"type":"Point"}
}