{
  "type": "Feature",
  "properties": {
    "iso:country": "GB",
    "wof:name": "SN16 9FR",
    "wof:placetype": "postalcode"
  },
  "geometry": {"coordinates":[-2.099836,51.588578],"type":"Point"}
}
