{
  "type": "Feature",
  "properties": {
    "iso:country":"GB",
    "wof:name":"B74 2EF",
    "wof:placetype":"postalcode"
},
  "geometry": {"coordinates":[-1.87874551814575,52.57724290329045],"type":"Point"}
}