{
  "type": "Feature",
  "properties": {
    "iso:country":"GB",
    "wof:name":"CB7 5DU",
    "wof:placetype":"postalcode"
},
  "geometry": {"coordinates":[0.33743183415617,52.33525300058803],"type":"Point"}
}