{
  "type": "Feature",
  "properties": {
    "iso:country":"GB",
    "wof:name":"DN20 9DP",
    "wof:placetype":"postalcode"
},
  "geometry": {"coordinates":[-0.53472257480164,53.52175635749933],"type":"Point"}
}