{
  "type": "Feature",
  "properties": {
    "iso:country":"GB",
    "wof:name":"BD3 8BZ",
    "wof:placetype":"postalcode"
},
  "geometry": {"coordinates":[-1.71738195127446,53.79381538509848],"type":"Point"}
}