{
  "type": "Feature",
  "properties": {
    "iso:country": "GB",
    "wof:name": "RG40 3AS",
    "wof:placetype": "postalcode"
  },
  "geometry": {"coordinates":[-0.814666,51.385392],"type":"Point"}
}
