{
  "type": "Feature",
  "properties": {
    "iso:country":"GB",
    "wof:name":"RG40 3AS",
    "wof:placetype":"postalcode"
},
  "geometry": {"coordinates":[-0.8146689433996,51.38538287447841],"type":"Point"}
}