{
  "type": "Feature",
  "properties": {
    "iso:country":"GB",
    "wof:name":"HR2 8RB",
    "wof:placetype":"postalcode"
},
  "geometry": {"coordinates":[-2.77249544109928,51.8895872653483],"type":"Point"}
}