{
  "type": "Feature",
  "properties": {
    "iso:country": "GB",
    "wof:name": "HR2 8RB",
    "wof:placetype": "postalcode"
  },
  "geometry": {"coordinates":[-2.772495,51.889587],"type":"Point"}
}
