{
  "type": "Feature",
  "properties": {
    "date:inception_lower":"1980-01-01",
    "date:inception_upper":"1980-01-31",
    "iso:country":"GB",
    "wof:name":"HR2 8RB",
    "wof:placetype":"postalcode"
},
  "geometry": {"coordinates":[-2.772495,51.889587],"type":"Point"}
}