{
  "type": "Feature",
  "properties": {
    "iso:country":"GB",
    "wof:name":"NR10 3PF",
    "wof:placetype":"postalcode"
},
  "geometry": {"coordinates":[1.31907955562311,52.68615793368962],"type":"Point"}
}