{
  "type": "Feature",
  "properties": {
    "date:inception_lower": "1980-01-01",
    "date:inception_upper": "1980-01-01",
    "iso:country": "GB",
    "wof:name": "M1 2AN",
    "wof:placetype": "postalcode"
  },
  "geometry": {"coordinates":[-2.233687,53.480995],"type":"Point"}
}
