{
  "type": "Feature",
  "properties": {
    "iso:country": "GB",
    "wof:name": "N15 5DJ",
    "wof:placetype": "postalcode"
  },
  "geometry": {"coordinates":[-0.082853,51.584983],"type":"Point"}
}
