{
  "type": "Feature",
  "properties": {
    "iso:country":"GB",
    "wof:name":"N15 5DJ",
    "wof:placetype":"postalcode"
},
  "geometry": {"coordinates":[-0.08294940520278,51.58499953517488],"type":"Point"}
}