{
  "type": "Feature",
  "properties": {
    "iso:country":"GB",
    "wof:name":"WD5 0AU",
    "wof:placetype":"postalcode"
},
  "geometry": {"coordinates":[-0.41860419027318,51.70772565644619],"type":"Point"}
}