{
  "type": "Feature",
  "properties": {
    "iso:country":"GB",
    "wof:name":"DD5 2QX",
    "wof:placetype":"postalcode"
},
  "geometry": {"coordinates":[-2.8476562446573,56.47453202786875],"type":"Point"}
}