{
  "type": "Feature",
  "properties": {
    "iso:country":"GB",
    "wof:name":"BA4 6AJ",
    "wof:placetype":"postalcode"
},
  "geometry": {"coordinates":[-2.43322345044569,51.15355653209519],"type":"Point"}
}