{
  "type": "Feature",
  "properties": {
    "date:inception_lower":"1980-01-01",
    "date:inception_upper":"1980-01-31",
    "iso:country":"GB",
    "wof:name":"BA4 6AJ",
    "wof:placetype":"postalcode"
},
  "geometry": {"coordinates":[-2.432796,51.152249],"type":"Point"}
}