{
  "type": "Feature",
  "properties": {
    "iso:country":"GB",
    "wof:name":"BR2 9AG",
    "wof:placetype":"postalcode"
},
  "geometry": {"coordinates":[0.01909531308713,51.39599658985409],"type":"Point"}
}