{
  "type": "Feature",
  "properties": {
    "date:inception_lower": "1980-01-01",
    "date:inception_upper": "1980-01-01",
    "iso:country": "GB",
    "wof:name": "BR2 9AG",
    "wof:placetype": "postalcode"
  },
  "geometry": {"coordinates":[0.019095,51.395997],"type":"Point"}
}
