{
  "type": "Feature",
  "properties": {
    "iso:country":"GB",
    "wof:name":"EH35 5LJ",
    "wof:placetype":"postalcode"
},
  "geometry": {"coordinates":[-2.94293265992875,55.91168927358311],"type":"Point"}
}