{
  "type": "Feature",
  "properties": {
    "iso:country": "GB",
    "wof:name": "OL12 9AN",
    "wof:placetype": "postalcode"
  },
  "geometry": {"coordinates":[-2.131221,53.636497],"type":"Point"}
}
