{
  "type": "Feature",
  "properties": {
    "date:inception_lower": "1980-01-01",
    "date:inception_upper": "1980-01-01",
    "iso:country": "GB",
    "wof:name": "RM17 6EG",
    "wof:placetype": "postalcode"
  },
  "geometry": {"coordinates":[0.336609,51.475134],"type":"Point"}
}
