{
  "type": "Feature",
  "properties": {
    "iso:country":"GB",
    "wof:name":"TN24 0TJ",
    "wof:placetype":"postalcode"
},
  "geometry": {"coordinates":[0.88961487253995,51.13234597787342],"type":"Point"}
}