{
  "type": "Feature",
  "properties": {
    "iso:country":"GB",
    "wof:name":"PA19 1RQ",
    "wof:placetype":"postalcode"
},
  "geometry": {"coordinates":[-4.81270856530417,55.95692459095845],"type":"Point"}
}