{
  "type": "Feature",
  "properties": {
    "iso:country": "GB",
    "wof:name": "PA19 1RQ",
    "wof:placetype": "postalcode"
  },
  "geometry": {"coordinates":[-4.812709,55.956925],"type":"Point"}
}
