{
  "type": "Feature",
  "properties": {
    "iso:country":"GB",
    "wof:name":"BD20 0AL",
    "wof:placetype":"postalcode"
},
  "geometry": {"coordinates":[-1.93741122902692,53.91248388691891],"type":"Point"}
}