{
  "type": "Feature",
  "properties": {
    "iso:country":"GB",
    "wof:name":"SL6 8BT",
    "wof:placetype":"postalcode"
},
  "geometry": {"coordinates":[-0.71087611877003,51.52154169452889],"type":"Point"}
}