{
  "type": "Feature",
  "properties": {
    "date:inception_lower": "1994-05-01",
    "date:inception_upper": "1994-05-01",
    "iso:country": "GB",
    "wof:name": "M28 2DE",
    "wof:placetype": "postalcode"
  },
  "geometry": {"coordinates":[-2.371185,53.508448],"type":"Point"}
}
