{
  "type": "Feature",
  "properties": {
    "iso:country":"GB",
    "wof:name":"M28 2DE",
    "wof:placetype":"postalcode"
},
  "geometry": {"coordinates":[-2.37118544766818,53.50844780430167],"type":"Point"}
}