{
  "type": "Feature",
  "properties": {
    "iso:country": "GB",
    "wof:name": "BD3 7BY",
    "wof:placetype": "postalcode"
  },
  "geometry": {"coordinates":[-1.707093,53.80206],"type":"Point"}
}
