{
  "type": "Feature",
  "properties": {
    "date:inception_lower": "1994-05-01",
    "date:inception_upper": "1994-05-01",
    "iso:country": "GB",
    "wof:name": "M8 8WL",
    "wof:placetype": "postalcode"
  },
  "geometry": {"coordinates":[-2.231258,53.50259],"type":"Point"}
}
