{
  "type": "Feature",
  "properties": {
    "iso:country":"GB",
    "wof:name":"DA3 8QD",
    "wof:placetype":"postalcode"
},
  "geometry": {"coordinates":[0.30833378787841,51.37084265789978],"type":"Point"}
}