{
  "type": "Feature",
  "properties": {
    "iso:country":"GB",
    "wof:name":"KT2 7SW",
    "wof:placetype":"postalcode"
},
  "geometry": {"coordinates":[-0.28600901836813,51.41890454199527],"type":"Point"}
}