{
  "type": "Feature",
  "properties": {
    "iso:country":"GB",
    "wof:name":"NR4 7RJ",
    "wof:placetype":"postalcode"
},
  "geometry": {"coordinates":[1.22961322955823,52.61535271599115],"type":"Point"}
}