{
  "type": "Feature",
  "properties": {
    "date:inception_lower":"1984-10-01",
    "date:inception_upper":"1984-10-31",
    "iso:country":"GB",
    "wof:name":"NR4 7RJ",
    "wof:placetype":"postalcode"
},
  "geometry": {"coordinates":[1.229613,52.615353],"type":"Point"}
}