{
  "type": "Feature",
  "properties": {
    "iso:country":"GB",
    "wof:name":"LS10 2QE",
    "wof:placetype":"postalcode"
},
  "geometry": {"coordinates":[-1.52828207626467,53.78009851044607],"type":"Point"}
}