{
  "type": "Feature",
  "properties": {
    "date:inception_lower":"1981-06-01",
    "date:inception_upper":"1981-06-30",
    "iso:country":"GB",
    "wof:name":"LS10 2QE",
    "wof:placetype":"postalcode"
},
  "geometry": {"coordinates":[-1.528282,53.780099],"type":"Point"}
}