{
  "type": "Feature",
  "properties": {
    "iso:country":"GB",
    "wof:name":"TF12 5SE",
    "wof:placetype":"postalcode"
},
  "geometry": {"coordinates":[-2.4733806059643,52.60868508207975],"type":"Point"}
}