{
  "type": "Feature",
  "properties": {
    "iso:country":"GB",
    "wof:name":"PR2 2RU",
    "wof:placetype":"postalcode"
},
  "geometry": {"coordinates":[-2.72457168791956,53.76581061842671],"type":"Point"}
}