{
  "type": "Feature",
  "properties": {
    "iso:country":"GB",
    "wof:name":"BL5 1AA",
    "wof:placetype":"postalcode"
},
  "geometry": {"coordinates":[-2.46927824750634,53.55016872931076],"type":"Point"}
}