{
  "type": "Feature",
  "properties": {
    "iso:country":"GB",
    "wof:name":"TA5 1QW",
    "wof:placetype":"postalcode"
},
  "geometry": {"coordinates":[-3.12487821665302,51.11131503880945],"type":"Point"}
}