{
  "type": "Feature",
  "properties": {
    "date:inception_lower": "1998-06-01",
    "date:inception_upper": "1998-06-01",
    "iso:country": "GB",
    "wof:name": "TA5 1QW",
    "wof:placetype": "postalcode"
  },
  "geometry": {"coordinates":[-3.131198,51.111735],"type":"Point"}
}
