{
  "type": "Feature",
  "properties": {
    "iso:country": "GB",
    "wof:name": "TA5 1QW",
    "wof:placetype": "postalcode"
  },
  "geometry": {"coordinates":[-3.131198,51.111735],"type":"Point"}
}
