{
  "type": "Feature",
  "properties": {
    "iso:country":"GB",
    "wof:name":"W14 0PS",
    "wof:placetype":"postalcode"
},
  "geometry": {"coordinates":[-0.21594683794466,51.49623764375271],"type":"Point"}
}