{
  "type": "Feature",
  "properties": {
    "iso:country":"GB",
    "wof:name":"NW4 1TG",
    "wof:placetype":"postalcode"
},
  "geometry": {"coordinates":[-0.21518397480752,51.59168014953242],"type":"Point"}
}