{
  "type": "Feature",
  "properties": {
    "iso:country": "GB",
    "wof:name": "YO32 9GR",
    "wof:placetype": "postalcode"
  },
  "geometry": {"coordinates":[-1.06218,53.978489],"type":"Point"}
}
