{
  "type": "Feature",
  "properties": {
    "date:inception_lower":"2008-08-01",
    "date:inception_upper":"2008-08-31",
    "iso:country":"GB",
    "wof:name":"YO32 9GR",
    "wof:placetype":"postalcode"
},
  "geometry": {"coordinates":[-1.06218,53.978489],"type":"Point"}
}