{
  "type": "Feature",
  "properties": {
    "iso:country":"GB",
    "wof:name":"NE15 9QY",
    "wof:placetype":"postalcode"
},
  "geometry": {"coordinates":[-1.76916508395092,54.99634371161599],"type":"Point"}
}