{
  "type": "Feature",
  "properties": {
    "date:inception_lower": "1980-01-01",
    "date:inception_upper": "1980-01-01",
    "iso:country": "GB",
    "wof:name": "G62 6PQ",
    "wof:placetype": "postalcode"
  },
  "geometry": {"coordinates":[-4.319726,55.94224],"type":"Point"}
}
