{
  "type": "Feature",
  "properties": {
    "iso:country":"GB",
    "wof:name":"FK15 9AN",
    "wof:placetype":"postalcode"
},
  "geometry": {"coordinates":[-3.96808876816511,56.1876261217788],"type":"Point"}
}