{
  "type": "Feature",
  "properties": {
    "iso:country": "GB",
    "wof:name": "FK15 9AN",
    "wof:placetype": "postalcode"
  },
  "geometry": {"coordinates":[-3.968089,56.187626],"type":"Point"}
}
