{
  "type": "Feature",
  "properties": {
    "iso:country": "GB",
    "wof:name": "DE55 5LG",
    "wof:placetype": "postalcode"
  },
  "geometry": {"coordinates":[-1.333422,53.146474],"type":"Point"}
}
