{
  "type": "Feature",
  "properties": {
    "iso:country":"GB",
    "wof:name":"CB3 9EG",
    "wof:placetype":"postalcode"
},
  "geometry": {"coordinates":[0.09761104657889,52.19618357902848],"type":"Point"}
}