{
  "type": "Feature",
  "properties": {
    "date:inception_lower": "1980-01-01",
    "date:inception_upper": "1980-01-01",
    "iso:country": "GB",
    "wof:name": "CB3 9EG",
    "wof:placetype": "postalcode"
  },
  "geometry": {"coordinates":[0.097611,52.196184],"type":"Point"}
}
