{
  "type": "Feature",
  "properties": {
    "iso:country": "GB",
    "wof:name": "CB3 9EG",
    "wof:placetype": "postalcode"
  },
  "geometry": {"coordinates":[0.097611,52.196184],"type":"Point"}
}
