{
  "type": "Feature",
  "properties": {
    "iso:country":"GB",
    "wof:name":"B95 6BY",
    "wof:placetype":"postalcode"
},
  "geometry": {"coordinates":[-1.77193748519486,52.26610127563409],"type":"Point"}
}