{
  "type": "Feature",
  "properties": {
    "iso:country": "GB",
    "wof:name": "B95 6BY",
    "wof:placetype": "postalcode"
  },
  "geometry": {"coordinates":[-1.771937,52.266101],"type":"Point"}
}
