{
  "type": "Feature",
  "properties": {
    "iso:country":"GB",
    "wof:name":"BL0 9RA",
    "wof:placetype":"postalcode"
},
  "geometry": {"coordinates":[-2.33152520724927,53.63518320905206],"type":"Point"}
}