{
  "type": "Feature",
  "properties": {
    "iso:country":"GB",
    "wof:name":"NN12 6BS",
    "wof:placetype":"postalcode"
},
  "geometry": {"coordinates":[-0.98813726704919,52.13165780161691],"type":"Point"}
}