{
  "type": "Feature",
  "properties": {
    "iso:country": "GB",
    "wof:name": "YO23 2PW",
    "wof:placetype": "postalcode"
  },
  "geometry": {"coordinates":[-1.125927,53.881287],"type":"Point"}
}
