{
  "type": "Feature",
  "properties": {
    "iso:country":"GB",
    "wof:name":"SA43 3DH",
    "wof:placetype":"postalcode"
},
  "geometry": {"coordinates":[-4.66813550421013,52.03269173157375],"type":"Point"}
}