{
  "type": "Feature",
  "properties": {
    "iso:country":"GB",
    "wof:name":"NG19 7FF",
    "wof:placetype":"postalcode"
},
  "geometry": {"coordinates":[-1.20235382132491,53.16050842400427],"type":"Point"}
}