{
  "type": "Feature",
  "properties": {
    "iso:country":"GB",
    "wof:name":"CF39 8SF",
    "wof:placetype":"postalcode"
},
  "geometry": {"coordinates":[-3.47185804703445,51.60211160178118],"type":"Point"}
}