{
  "type": "Feature",
  "properties": {
    "date:inception_lower": "2005-01-01",
    "date:inception_upper": "2005-01-01",
    "iso:country": "GB",
    "wof:name": "CF39 8SF",
    "wof:placetype": "postalcode"
  },
  "geometry": {"coordinates":[-3.47187,51.602116],"type":"Point"}
}
