{
  "type": "Feature",
  "properties": {
    "iso:country": "GB",
    "wof:name": "CF39 8SF",
    "wof:placetype": "postalcode"
  },
  "geometry": {"coordinates":[-3.472049,51.602276],"type":"Point"}
}
