{
  "type": "Feature",
  "properties": {
    "iso:country": "GB",
    "wof:name": "SK17 7DX",
    "wof:placetype": "postalcode"
  },
  "geometry": {"coordinates":[-1.902782,53.263984],"type":"Point"}
}
