{
  "type": "Feature",
  "properties": {
    "iso:country":"GB",
    "wof:name":"SK17 7DX",
    "wof:placetype":"postalcode"
},
  "geometry": {"coordinates":[-1.90278214208719,53.26398377550324],"type":"Point"}
}