{
  "type": "Feature",
  "properties": {
    "date:inception_lower": "1980-01-01",
    "date:inception_upper": "1980-01-01",
    "iso:country": "GB",
    "wof:name": "KA25 7BE",
    "wof:placetype": "postalcode"
  },
  "geometry": {"coordinates":[-4.685562,55.759561],"type":"Point"}
}
