{
  "type": "Feature",
  "properties": {
    "iso:country":"GB",
    "wof:name":"KA25 7BE",
    "wof:placetype":"postalcode"
},
  "geometry": {"coordinates":[-4.68556182535766,55.75956123518335],"type":"Point"}
}