{
  "type": "Feature",
  "properties": {
    "iso:country":"GB",
    "wof:name":"DH2 2BQ",
    "wof:placetype":"postalcode"
},
  "geometry": {"coordinates":[-1.5872437632143,54.85691611796192],"type":"Point"}
}