{
  "type": "Feature",
  "properties": {
    "iso:country": "GB",
    "wof:name": "ME7 2XH",
    "wof:placetype": "postalcode"
  },
  "geometry": {"coordinates":[0.594776,51.384166],"type":"Point"}
}
