{
  "type": "Feature",
  "properties": {
    "iso:country":"GB",
    "wof:name":"TN2 4NP",
    "wof:placetype":"postalcode"
},
  "geometry": {"coordinates":[0.32040430796423,51.14461721653078],"type":"Point"}
}