{
  "type": "Feature",
  "properties": {
    "iso:country": "GB",
    "wof:name": "BH20 4SW",
    "wof:placetype": "postalcode"
  },
  "geometry": {"coordinates":[-2.121899,50.694344],"type":"Point"}
}
