{
  "type": "Feature",
  "properties": {
    "iso:country":"GB",
    "wof:name":"LE14 4AH",
    "wof:placetype":"postalcode"
},
  "geometry": {"coordinates":[-0.80681735374521,52.81595375541007],"type":"Point"}
}