{
  "type": "Feature",
  "properties": {
    "iso:country": "GB",
    "wof:name": "LE14 4AH",
    "wof:placetype": "postalcode"
  },
  "geometry": {"coordinates":[-0.806817,52.815954],"type":"Point"}
}
