{
  "type": "Feature",
  "properties": {
    "iso:country":"GB",
    "wof:name":"RG21 5PP",
    "wof:placetype":"postalcode"
},
  "geometry": {"coordinates":[-1.08329666537269,51.27178617053178],"type":"Point"}
}