{
  "type": "Feature",
  "properties": {
    "iso:country":"GB",
    "wof:name":"M14 5QT",
    "wof:placetype":"postalcode"
},
  "geometry": {"coordinates":[-2.20781375170936,53.45923653320101],"type":"Point"}
}