{
  "type": "Feature",
  "properties": {
    "iso:country":"GB",
    "wof:name":"PO21 5TY",
    "wof:placetype":"postalcode"
},
  "geometry": {"coordinates":[-0.69384780197699,50.79902299349922],"type":"Point"}
}