{
  "type": "Feature",
  "properties": {
    "iso:country":"GB",
    "wof:name":"NW4 4SL",
    "wof:placetype":"postalcode"
},
  "geometry": {"coordinates":[-0.23544820905228,51.59180671033568],"type":"Point"}
}