{
  "type": "Feature",
  "properties": {
    "iso:country":"GB",
    "wof:name":"PR5 6RL",
    "wof:placetype":"postalcode"
},
  "geometry": {"coordinates":[-2.6569770685825,53.73407639825518],"type":"Point"}
}