{
  "type": "Feature",
  "properties": {
    "iso:country": "GB",
    "wof:name": "LA22 0BD",
    "wof:placetype": "postalcode"
  },
  "geometry": {"coordinates":[-2.961097,54.430348],"type":"Point"}
}
