{
  "type": "Feature",
  "properties": {
    "iso:country":"GB",
    "wof:name":"LA22 0BD",
    "wof:placetype":"postalcode"
},
  "geometry": {"coordinates":[-2.96109723899888,54.43034822320173],"type":"Point"}
}