{
  "type": "Feature",
  "properties": {
    "iso:country":"GB",
    "wof:name":"B90 4BL",
    "wof:placetype":"postalcode"
},
  "geometry": {"coordinates":[-1.81134402988792,52.392923557353],"type":"Point"}
}