{
  "type": "Feature",
  "properties": {
    "date:inception_lower":"2009-04-01",
    "date:inception_upper":"2009-04-30",
    "iso:country":"GB",
    "wof:name":"B90 4BL",
    "wof:placetype":"postalcode"
},
  "geometry": {"coordinates":[-1.811344,52.392924],"type":"Point"}
}