{
  "type": "Feature",
  "properties": {
    "iso:country": "GB",
    "wof:name": "NP19 0HE",
    "wof:placetype": "postalcode"
  },
  "geometry": {"coordinates":[-2.96924,51.579564],"type":"Point"}
}
