{
  "type": "Feature",
  "properties": {
    "iso:country":"GB",
    "wof:name":"TN11 9EN",
    "wof:placetype":"postalcode"
},
  "geometry": {"coordinates":[0.24947233805612,51.21336424570431],"type":"Point"}
}