{
  "type": "Feature",
  "properties": {
    "iso:country":"GB",
    "wof:name":"SK9 2BQ",
    "wof:placetype":"postalcode"
},
  "geometry": {"coordinates":[-2.21310494494878,53.32791296995298],"type":"Point"}
}