{
  "type": "Feature",
  "properties": {
    "iso:country":"GB",
    "wof:name":"DG4 6PH",
    "wof:placetype":"postalcode"
},
  "geometry": {"coordinates":[-4.00653200747997,55.38696590690517],"type":"Point"}
}