{
  "type": "Feature",
  "properties": {
    "iso:country": "GB",
    "wof:name": "E11 4DQ",
    "wof:placetype": "postalcode"
  },
  "geometry": {"coordinates":[0.00071,51.564179],"type":"Point"}
}
