{
  "type": "Feature",
  "properties": {
    "iso:country": "GB",
    "wof:name": "DE23 8NZ",
    "wof:placetype": "postalcode"
  },
  "geometry": {"coordinates":[-1.471166,52.90245],"type":"Point"}
}
