{
  "type": "Feature",
  "properties": {
    "iso:country":"GB",
    "wof:name":"DE23 8NZ",
    "wof:placetype":"postalcode"
},
  "geometry": {"coordinates":[-1.47118584161965,52.90240502813482],"type":"Point"}
}