{
  "type": "Feature",
  "properties": {
    "iso:country": "GB",
    "wof:name": "KA12 0DG",
    "wof:placetype": "postalcode"
  },
  "geometry": {"coordinates":[-4.667265,55.613166],"type":"Point"}
}
