{
  "type": "Feature",
  "properties": {
    "iso:country":"GB",
    "wof:name":"KA12 0DG",
    "wof:placetype":"postalcode"
},
  "geometry": {"coordinates":[-4.66726554412949,55.61316571246264],"type":"Point"}
}