{
  "type": "Feature",
  "properties": {
    "date:inception_lower": "1980-01-01",
    "date:inception_upper": "1980-01-01",
    "iso:country": "GB",
    "wof:name": "KA12 0DG",
    "wof:placetype": "postalcode"
  },
  "geometry": {"coordinates":[-4.667265,55.613166],"type":"Point"}
}
