{
  "type": "Feature",
  "properties": {
    "date:inception_lower":"1980-01-01",
    "date:inception_upper":"1980-01-31",
    "iso:country":"GB",
    "wof:name":"NG9 7HL",
    "wof:placetype":"postalcode"
},
  "geometry": {"coordinates":[-1.269459,52.927738],"type":"Point"}
}