{
  "type": "Feature",
  "properties": {
    "iso:country": "GB",
    "wof:name": "SW19 3NP",
    "wof:placetype": "postalcode"
  },
  "geometry": {"coordinates":[-0.208315,51.411951],"type":"Point"}
}
