{
  "type": "Feature",
  "properties": {
    "iso:country":"GB",
    "wof:name":"GL16 8JR",
    "wof:placetype":"postalcode"
},
  "geometry": {"coordinates":[-2.61434139968057,51.77105510258502],"type":"Point"}
}