{
  "type": "Feature",
  "properties": {
    "date:inception_lower": "1980-01-01",
    "date:inception_upper": "1980-01-01",
    "iso:country": "GB",
    "wof:name": "GL16 8JR",
    "wof:placetype": "postalcode"
  },
  "geometry": {"coordinates":[-2.615979,51.769855],"type":"Point"}
}
