{
  "type": "Feature",
  "properties": {
    "iso:country":"GB",
    "wof:name":"M40 5EF",
    "wof:placetype":"postalcode"
},
  "geometry": {"coordinates":[-2.19129104972791,53.50916800370718],"type":"Point"}
}