{
  "type": "Feature",
  "properties": {
    "iso:country":"GB",
    "wof:name":"AB11 6WF",
    "wof:placetype":"postalcode"
},
  "geometry": {"coordinates":[-2.10310410999129,57.14024060579333],"type":"Point"}
}