{
  "type": "Feature",
  "properties": {
    "iso:country":"GB",
    "wof:name":"B76 9EX",
    "wof:placetype":"postalcode"
},
  "geometry": {"coordinates":[-1.73694621665195,52.53320551505519],"type":"Point"}
}