{
  "type": "Feature",
  "properties": {
    "iso:country":"GB",
    "wof:name":"WR9 8DB",
    "wof:placetype":"postalcode"
},
  "geometry": {"coordinates":[-2.16483598748113,52.25524640549391],"type":"Point"}
}