{
  "type": "Feature",
  "properties": {
    "date:inception_lower": "1994-12-01",
    "date:inception_upper": "1994-12-01",
    "iso:country": "GB",
    "wof:name": "WR9 8DB",
    "wof:placetype": "postalcode"
  },
  "geometry": {"coordinates":[-2.164836,52.255246],"type":"Point"}
}
