{
  "type": "Feature",
  "properties": {
    "iso:country":"GB",
    "wof:name":"PE6 0DG",
    "wof:placetype":"postalcode"
},
  "geometry": {"coordinates":[-0.17057910855056,52.66658910607079],"type":"Point"}
}