{
  "type": "Feature",
  "properties": {
    "date:inception_lower":"1997-06-01",
    "date:inception_upper":"1997-06-30",
    "iso:country":"GB",
    "wof:name":"PE6 0DG",
    "wof:placetype":"postalcode"
},
  "geometry": {"coordinates":[-0.170677,52.666394],"type":"Point"}
}