{
  "type": "Feature",
  "properties": {
    "iso:country": "GB",
    "wof:name": "PE6 0DG",
    "wof:placetype": "postalcode"
  },
  "geometry": {"coordinates":[-0.170677,52.666394],"type":"Point"}
}
