{
  "type": "Feature",
  "properties": {
    "iso:country":"GB",
    "wof:name":"N5 2BQ",
    "wof:placetype":"postalcode"
},
  "geometry": {"coordinates":[-0.09716150885827,51.55231835714066],"type":"Point"}
}