{
  "type": "Feature",
  "properties": {
    "iso:country": "GB",
    "wof:name": "B79 7UJ",
    "wof:placetype": "postalcode"
  },
  "geometry": {"coordinates":[-1.721749,52.642514],"type":"Point"}
}
