{
  "type": "Feature",
  "properties": {
    "date:inception_lower":"1980-01-01",
    "date:inception_upper":"1980-01-31",
    "iso:country":"GB",
    "wof:name":"SK2 5RW",
    "wof:placetype":"postalcode"
},
  "geometry": {"coordinates":[-2.123671,53.397719],"type":"Point"}
}