{
  "type": "Feature",
  "properties": {
    "iso:country":"GB",
    "wof:name":"KT24 5EA",
    "wof:placetype":"postalcode"
},
  "geometry": {"coordinates":[-0.42488251904511,51.28149724090913],"type":"Point"}
}