{
  "type": "Feature",
  "properties": {
    "iso:country":"GB",
    "wof:name":"PR4 1YP",
    "wof:placetype":"postalcode"
},
  "geometry": {"coordinates":[-2.89499498344289,53.75352251380041],"type":"Point"}
}