{
  "type": "Feature",
  "properties": {
    "date:inception_lower":"1980-01-01",
    "date:inception_upper":"1980-01-31",
    "iso:country":"GB",
    "wof:name":"BN17 6DH",
    "wof:placetype":"postalcode"
},
  "geometry": {"coordinates":[-0.531263,50.816389],"type":"Point"}
}