{
  "type": "Feature",
  "properties": {
    "iso:country": "GB",
    "wof:name": "BN17 6DH",
    "wof:placetype": "postalcode"
  },
  "geometry": {"coordinates":[-0.531263,50.816389],"type":"Point"}
}
