{
  "type": "Feature",
  "properties": {
    "iso:country":"GB",
    "wof:name":"BN17 6DH",
    "wof:placetype":"postalcode"
},
  "geometry": {"coordinates":[-0.53126332705325,50.8163887125526],"type":"Point"}
}