{
  "type": "Feature",
  "properties": {
    "iso:country": "GB",
    "wof:name": "IP15 5LT",
    "wof:placetype": "postalcode"
  },
  "geometry": {"coordinates":[1.598237,52.156102],"type":"Point"}
}
