{
  "type": "Feature",
  "properties": {
    "date:inception_lower": "1997-06-01",
    "date:inception_upper": "1997-06-01",
    "iso:country": "GB",
    "wof:name": "IP15 5LT",
    "wof:placetype": "postalcode"
  },
  "geometry": {"coordinates":[1.598237,52.156102],"type":"Point"}
}
