{
  "type": "Feature",
  "properties": {
    "iso:country":"GB",
    "wof:name":"TW11 8TF",
    "wof:placetype":"postalcode"
},
  "geometry": {"coordinates":[-0.33926049526196,51.4265863383873],"type":"Point"}
}