{
  "type": "Feature",
  "properties": {
    "date:inception_lower":"1980-01-01",
    "date:inception_upper":"1980-01-31",
    "iso:country":"GB",
    "wof:name":"NE65 7QD",
    "wof:placetype":"postalcode"
},
  "geometry": {"coordinates":[-1.897356,55.320057],"type":"Point"}
}