{
  "type": "Feature",
  "properties": {
    "iso:country":"GB",
    "wof:name":"NE65 7QD",
    "wof:placetype":"postalcode"
},
  "geometry": {"coordinates":[-1.89735608801322,55.32005731121946],"type":"Point"}
}