{
  "type": "Feature",
  "properties": {
    "iso:country": "GB",
    "wof:name": "PE28 0BE",
    "wof:placetype": "postalcode"
  },
  "geometry": {"coordinates":[-0.3164,52.310075],"type":"Point"}
}
