{
  "type": "Feature",
  "properties": {
    "iso:country":"GB",
    "wof:name":"CF24 4BJ",
    "wof:placetype":"postalcode"
},
  "geometry": {"coordinates":[-3.17884580021687,51.49073006265363],"type":"Point"}
}