{
  "type": "Feature",
  "properties": {
    "iso:country": "GB",
    "wof:name": "PE11 3JH",
    "wof:placetype": "postalcode"
  },
  "geometry": {"coordinates":[-0.25505,52.772473],"type":"Point"}
}
