{
  "type": "Feature",
  "properties": {
    "date:inception_lower": "1980-01-01",
    "date:inception_upper": "1980-01-01",
    "iso:country": "GB",
    "wof:name": "KA9 2AF",
    "wof:placetype": "postalcode"
  },
  "geometry": {"coordinates":[-4.61326,55.484307],"type":"Point"}
}
