{
  "type": "Feature",
  "properties": {
    "iso:country":"GB",
    "wof:name":"KA9 2AF",
    "wof:placetype":"postalcode"
},
  "geometry": {"coordinates":[-4.6132595671753,55.48430743449411],"type":"Point"}
}