{
  "type": "Feature",
  "properties": {
    "iso:country": "GB",
    "wof:name": "KA9 2AF",
    "wof:placetype": "postalcode"
  },
  "geometry": {"coordinates":[-4.61326,55.484307],"type":"Point"}
}
