{
  "type": "Feature",
  "properties": {
    "iso:country":"GB",
    "wof:name":"SP10 5DL",
    "wof:placetype":"postalcode"
},
  "geometry": {"coordinates":[-1.46943794974924,51.22059794393216],"type":"Point"}
}