{
  "type": "Feature",
  "properties": {
    "date:inception_lower":"1980-01-01",
    "date:inception_upper":"1980-01-31",
    "iso:country":"GB",
    "wof:name":"G32 9HE",
    "wof:placetype":"postalcode"
},
  "geometry": {"coordinates":[-4.155138,55.845731],"type":"Point"}
}