{
  "type": "Feature",
  "properties": {
    "iso:country":"GB",
    "wof:name":"WR1 2GB",
    "wof:placetype":"postalcode"
},
  "geometry": {"coordinates":[-2.22021177843936,52.1843747793182],"type":"Point"}
}