{
  "type": "Feature",
  "properties": {
    "date:inception_lower": "2014-05-01",
    "date:inception_upper": "2014-05-01",
    "iso:country": "GB",
    "wof:name": "WR1 2GB",
    "wof:placetype": "postalcode"
  },
  "geometry": {"coordinates":[-2.220212,52.184375],"type":"Point"}
}
