{
  "type": "Feature",
  "properties": {
    "iso:country":"GB",
    "wof:name":"NG9 4ES",
    "wof:placetype":"postalcode"
},
  "geometry": {"coordinates":[-1.23686845712906,52.92250848892554],"type":"Point"}
}