{
  "type": "Feature",
  "properties": {
    "iso:country":"GB",
    "wof:name":"B60 1HE",
    "wof:placetype":"postalcode"
},
  "geometry": {"coordinates":[-2.03598015738002,52.36518976977026],"type":"Point"}
}