{
  "type": "Feature",
  "properties": {
    "iso:country":"GB",
    "wof:name":"G11 7XH",
    "wof:placetype":"postalcode"
},
  "geometry": {"coordinates":[-4.31736273426725,55.87130745339428],"type":"Point"}
}