{
  "type": "Feature",
  "properties": {
    "date:inception_lower": "1980-01-01",
    "date:inception_upper": "1980-01-01",
    "iso:country": "GB",
    "wof:name": "GL7 3BG",
    "wof:placetype": "postalcode"
  },
  "geometry": {"coordinates":[-1.694396,51.698133],"type":"Point"}
}
