{
  "type": "Feature",
  "properties": {
    "date:inception_lower": "1980-01-01",
    "date:inception_upper": "1980-01-01",
    "iso:country": "GB",
    "wof:name": "RH5 6ER",
    "wof:placetype": "postalcode"
  },
  "geometry": {"coordinates":[-0.330333,51.269603],"type":"Point"}
}
