{
  "type": "Feature",
  "properties": {
    "iso:country":"GB",
    "wof:name":"RH5 6ER",
    "wof:placetype":"postalcode"
},
  "geometry": {"coordinates":[-0.33033259150456,51.26960273652552],"type":"Point"}
}