{
  "type": "Feature",
  "properties": {
    "iso:country": "GB",
    "wof:name": "SN11 9FA",
    "wof:placetype": "postalcode"
  },
  "geometry": {"coordinates":[-2.010197,51.447626],"type":"Point"}
}
