{
  "type": "Feature",
  "properties": {
    "date:inception_lower": "1980-01-01",
    "date:inception_upper": "1980-01-01",
    "iso:country": "GB",
    "wof:name": "RH6 8BB",
    "wof:placetype": "postalcode"
  },
  "geometry": {"coordinates":[-0.174655,51.179329],"type":"Point"}
}
