{
  "type": "Feature",
  "properties": {
    "iso:country":"GB",
    "wof:name":"PL7 4HY",
    "wof:placetype":"postalcode"
},
  "geometry": {"coordinates":[-4.05913905208609,50.39664307417773],"type":"Point"}
}