{
  "type": "Feature",
  "properties": {
    "iso:country": "GB",
    "wof:name": "SL5 8TH",
    "wof:placetype": "postalcode"
  },
  "geometry": {"coordinates":[-0.690565,51.414491],"type":"Point"}
}
