{
  "type": "Feature",
  "properties": {
    "iso:country": "GB",
    "wof:name": "BA14 6AL",
    "wof:placetype": "postalcode"
  },
  "geometry": {"coordinates":[-2.17374,51.297291],"type":"Point"}
}
