{
  "type": "Feature",
  "properties": {
    "iso:country": "GB",
    "wof:name": "CT12 6TH",
    "wof:placetype": "postalcode"
  },
  "geometry": {"coordinates":[1.403688,51.352128],"type":"Point"}
}
