{
  "type": "Feature",
  "properties": {
    "iso:country": "GB",
    "wof:name": "HP21 9JF",
    "wof:placetype": "postalcode"
  },
  "geometry": {"coordinates":[-0.811111,51.793852],"type":"Point"}
}
