{
  "type": "Feature",
  "properties": {
    "date:inception_lower": "1980-01-01",
    "date:inception_upper": "1980-01-01",
    "iso:country": "GB",
    "wof:name": "M24 2EB",
    "wof:placetype": "postalcode"
  },
  "geometry": {"coordinates":[-2.174273,53.550891],"type":"Point"}
}
