{
  "type": "Feature",
  "properties": {
    "iso:country":"GB",
    "wof:name":"M24 2EB",
    "wof:placetype":"postalcode"
},
  "geometry": {"coordinates":[-2.17427314052059,53.55089111750809],"type":"Point"}
}