{
  "type": "Feature",
  "properties": {
    "date:inception_lower":"1980-01-01",
    "date:inception_upper":"1980-01-31",
    "iso:country":"GB",
    "wof:name":"PL20 6JT",
    "wof:placetype":"postalcode"
},
  "geometry": {"coordinates":[-4.071338,50.508215],"type":"Point"}
}