{
  "type": "Feature",
  "properties": {
    "iso:country":"GB",
    "wof:name":"PL20 6JT",
    "wof:placetype":"postalcode"
},
  "geometry": {"coordinates":[-4.07133838736653,50.50821523541427],"type":"Point"}
}