{
  "type": "Feature",
  "properties": {
    "iso:country": "GB",
    "wof:name": "SA9 2RX",
    "wof:placetype": "postalcode"
  },
  "geometry": {"coordinates":[-3.83283,51.777359],"type":"Point"}
}
