{
  "type": "Feature",
  "properties": {
    "date:inception_lower": "1994-12-01",
    "date:inception_upper": "1994-12-01",
    "iso:country": "GB",
    "wof:name": "SO40 3JN",
    "wof:placetype": "postalcode"
  },
  "geometry": {"coordinates":[-1.495256,50.919824],"type":"Point"}
}
