{
  "type": "Feature",
  "properties": {
    "iso:country": "GB",
    "wof:name": "SO40 3JN",
    "wof:placetype": "postalcode"
  },
  "geometry": {"coordinates":[-1.495256,50.919824],"type":"Point"}
}
