{
  "type": "Feature",
  "properties": {
    "date:inception_lower": "1980-01-01",
    "date:inception_upper": "1980-01-01",
    "iso:country": "GB",
    "wof:name": "KT15 1UB",
    "wof:placetype": "postalcode"
  },
  "geometry": {"coordinates":[-0.493699,51.373361],"type":"Point"}
}
