{
  "type": "Feature",
  "properties": {
    "date:inception_lower": "1980-01-01",
    "date:inception_upper": "1980-01-01",
    "iso:country": "GB",
    "wof:name": "SA34 0DH",
    "wof:placetype": "postalcode"
  },
  "geometry": {"coordinates":[-4.576038,51.893239],"type":"Point"}
}
