{
  "type": "Feature",
  "properties": {
    "iso:country":"GB",
    "wof:name":"S10 3RR",
    "wof:placetype":"postalcode"
},
  "geometry": {"coordinates":[-1.54614216735375,53.36821215349256],"type":"Point"}
}