{
  "type": "Feature",
  "properties": {
    "iso:country":"GB",
    "wof:name":"SE19 3DU",
    "wof:placetype":"postalcode"
},
  "geometry": {"coordinates":[-0.09484803399758,51.41526056615514],"type":"Point"}
}