{
  "type": "Feature",
  "properties": {
    "date:inception_lower": "2001-06-01",
    "date:inception_upper": "2001-06-01",
    "iso:country": "GB",
    "wof:name": "LN1 1WE",
    "wof:placetype": "postalcode"
  },
  "geometry": {"coordinates":[-0.56065,53.242303],"type":"Point"}
}
