{
  "type": "Feature",
  "properties": {
    "iso:country":"GB",
    "wof:name":"LN1 1WE",
    "wof:placetype":"postalcode"
},
  "geometry": {"coordinates":[-0.56064980159078,53.24230318766902],"type":"Point"}
}