{
  "type": "Feature",
  "properties": {
    "iso:country":"GB",
    "wof:name":"RG27 8BG",
    "wof:placetype":"postalcode"
},
  "geometry": {"coordinates":[-0.85604873424632,51.30091766046915],"type":"Point"}
}