{
  "type": "Feature",
  "properties": {
    "iso:country":"GB",
    "wof:name":"BS5 0LY",
    "wof:placetype":"postalcode"
},
  "geometry": {"coordinates":[-2.5667238252255,51.46543457147285],"type":"Point"}
}