{
  "type": "Feature",
  "properties": {
    "iso:country":"GB",
    "wof:name":"NE28 7SG",
    "wof:placetype":"postalcode"
},
  "geometry": {"coordinates":[-1.52676491881336,54.99601130860744],"type":"Point"}
}