{
  "type": "Feature",
  "properties": {
    "date:inception_lower":"1995-12-01",
    "date:inception_upper":"1995-12-31",
    "iso:country":"GB",
    "wof:name":"KT1 2DR",
    "wof:placetype":"postalcode"
},
  "geometry": {"coordinates":[-0.303587,51.404637],"type":"Point"}
}