{
  "type": "Feature",
  "properties": {
    "iso:country": "GB",
    "wof:name": "KT1 2DR",
    "wof:placetype": "postalcode"
  },
  "geometry": {"coordinates":[-0.303587,51.404637],"type":"Point"}
}
