{
  "type": "Feature",
  "properties": {
    "iso:country":"GB",
    "wof:name":"NR12 0LF",
    "wof:placetype":"postalcode"
},
  "geometry": {"coordinates":[1.46874643168204,52.8416906875928],"type":"Point"}
}