{
  "type": "Feature",
  "properties": {
    "date:inception_lower":"1980-01-01",
    "date:inception_upper":"1980-01-31",
    "iso:country":"GB",
    "wof:name":"NR12 0LF",
    "wof:placetype":"postalcode"
},
  "geometry": {"coordinates":[1.468709,52.84173],"type":"Point"}
}