{
  "type": "Feature",
  "properties": {
    "iso:country":"GB",
    "wof:name":"NE3 3QJ",
    "wof:placetype":"postalcode"
},
  "geometry": {"coordinates":[-1.65324817805263,55.00522576833445],"type":"Point"}
}