{
  "type": "Feature",
  "properties": {
    "iso:country": "GB",
    "wof:name": "TF10 7JZ",
    "wof:placetype": "postalcode"
  },
  "geometry": {"coordinates":[-2.380538,52.775479],"type":"Point"}
}
