{
  "type": "Feature",
  "properties": {
    "iso:country":"GB",
    "wof:name":"TW8 8QR",
    "wof:placetype":"postalcode"
},
  "geometry": {"coordinates":[-0.30452245351407,51.48174304110001],"type":"Point"}
}