{
  "type": "Feature",
  "properties": {
    "iso:country":"GB",
    "wof:name":"GU14 8RB",
    "wof:placetype":"postalcode"
},
  "geometry": {"coordinates":[-0.76345864995313,51.31147776151261],"type":"Point"}
}