{
  "type": "Feature",
  "properties": {
    "iso:country": "GB",
    "wof:name": "YO8 9AB",
    "wof:placetype": "postalcode"
  },
  "geometry": {"coordinates":[-1.081516,53.778462],"type":"Point"}
}
