{
  "type": "Feature",
  "properties": {
    "iso:country":"GB",
    "wof:name":"YO8 9AB",
    "wof:placetype":"postalcode"
},
  "geometry": {"coordinates":[-1.08151582894636,53.77846225119362],"type":"Point"}
}