{
  "type": "Feature",
  "properties": {
    "iso:country":"GB",
    "wof:name":"W2 4RJ",
    "wof:placetype":"postalcode"
},
  "geometry": {"coordinates":[-0.18770651895048,51.51048933569636],"type":"Point"}
}