{
  "type": "Feature",
  "properties": {
    "iso:country":"GB",
    "wof:name":"S10 5TN",
    "wof:placetype":"postalcode"
},
  "geometry": {"coordinates":[-1.53449969081416,53.37880994579066],"type":"Point"}
}