{
  "type": "Feature",
  "properties": {
    "date:inception_lower":"2000-06-01",
    "date:inception_upper":"2000-06-30",
    "iso:country":"GB",
    "wof:name":"EC4M 7LW",
    "wof:placetype":"postalcode"
},
  "geometry": {"coordinates":[-0.104105,51.514015],"type":"Point"}
}