{
  "type": "Feature",
  "properties": {
    "iso:country": "GB",
    "wof:name": "NG4 1EP",
    "wof:placetype": "postalcode"
  },
  "geometry": {"coordinates":[-1.094915,52.965732],"type":"Point"}
}
