{
  "type": "Feature",
  "properties": {
    "date:inception_lower": "2003-09-01",
    "date:inception_upper": "2003-09-01",
    "iso:country": "GB",
    "wof:name": "DH8 7GD",
    "wof:placetype": "postalcode"
  },
  "geometry": {"coordinates":[-1.822798,54.848303],"type":"Point"}
}
