{
  "type": "Feature",
  "properties": {
    "iso:country":"GB",
    "wof:name":"DH8 7GD",
    "wof:placetype":"postalcode"
},
  "geometry": {"coordinates":[-1.8229286482726,54.84837570072016],"type":"Point"}
}