{
  "type": "Feature",
  "properties": {
    "iso:country":"GB",
    "wof:name":"S10 2NH",
    "wof:placetype":"postalcode"
},
  "geometry": {"coordinates":[-1.49560579626723,53.37413971906915],"type":"Point"}
}