{
  "type": "Feature",
  "properties": {
    "iso:country":"GB",
    "wof:name":"NE4 6RE",
    "wof:placetype":"postalcode"
},
  "geometry": {"coordinates":[-1.63329820988209,54.96754195066702],"type":"Point"}
}