{
  "type": "Feature",
  "properties": {
    "iso:country":"GB",
    "wof:name":"DN18 5DA",
    "wof:placetype":"postalcode"
},
  "geometry": {"coordinates":[-0.43930290483834,53.68275963719871],"type":"Point"}
}