{
  "type": "Feature",
  "properties": {
    "date:inception_lower": "2001-06-01",
    "date:inception_upper": "2001-06-01",
    "iso:country": "GB",
    "wof:name": "MK10 9GR",
    "wof:placetype": "postalcode"
  },
  "geometry": {"coordinates":[-0.701657,52.037529],"type":"Point"}
}
