{
  "type": "Feature",
  "properties": {
    "date:inception_lower": "2014-12-01",
    "date:inception_upper": "2014-12-01",
    "iso:country": "GB",
    "wof:name": "BD17 5AY",
    "wof:placetype": "postalcode"
  },
  "geometry": {"coordinates":[-1.772486,53.838818],"type":"Point"}
}
