{
  "type": "Feature",
  "properties": {
    "iso:country": "GB",
    "wof:name": "BD17 5AY",
    "wof:placetype": "postalcode"
  },
  "geometry": {"coordinates":[-1.772486,53.838818],"type":"Point"}
}
