{
  "type": "Feature",
  "properties": {
    "iso:country":"GB",
    "wof:name":"NW7 2BJ",
    "wof:placetype":"postalcode"
},
  "geometry": {"coordinates":[-0.22984783528098,51.61034540004412],"type":"Point"}
}