{
  "type": "Feature",
  "properties": {
    "iso:country":"GB",
    "wof:name":"CT21 5UE",
    "wof:placetype":"postalcode"
},
  "geometry": {"coordinates":[1.08955443992516,51.07347783938668],"type":"Point"}
}