{
  "type": "Feature",
  "properties": {
    "iso:country":"GB",
    "wof:name":"ME9 9DU",
    "wof:placetype":"postalcode"
},
  "geometry": {"coordinates":[0.80732591436958,51.33270064529148],"type":"Point"}
}