{
  "type": "Feature",
  "properties": {
    "iso:country":"GB",
    "wof:name":"PA1 3QZ",
    "wof:placetype":"postalcode"
},
  "geometry": {"coordinates":[-4.41143542669946,55.8478207971105],"type":"Point"}
}