{
  "type": "Feature",
  "properties": {
    "date:inception_lower":"1992-07-01",
    "date:inception_upper":"1992-07-31",
    "iso:country":"GB",
    "wof:name":"PA1 3QZ",
    "wof:placetype":"postalcode"
},
  "geometry": {"coordinates":[-4.411435,55.847821],"type":"Point"}
}