{
  "type": "Feature",
  "properties": {
    "iso:country": "GB",
    "wof:name": "PA1 3QZ",
    "wof:placetype": "postalcode"
  },
  "geometry": {"coordinates":[-4.411435,55.847821],"type":"Point"}
}
