{
  "type": "Feature",
  "properties": {
    "date:inception_lower": "2023-10-01",
    "date:inception_upper": "2023-10-01",
    "iso:country": "GB",
    "wof:name": "ST9 0FF",
    "wof:placetype": "postalcode"
  },
  "geometry": {"coordinates":[-2.090169,53.023588],"type":"Point"}
}
