{
  "type": "Feature",
  "properties": {
    "iso:country": "GB",
    "wof:name": "TS24 8HR",
    "wof:placetype": "postalcode"
  },
  "geometry": {"coordinates":[-1.22715,54.695231],"type":"Point"}
}
