{
  "type": "Feature",
  "properties": {
    "date:inception_lower": "2007-09-01",
    "date:inception_upper": "2007-09-01",
    "iso:country": "GB",
    "wof:name": "DG16 5GA",
    "wof:placetype": "postalcode"
  },
  "geometry": {"coordinates":[-3.070683,54.989809],"type":"Point"}
}
