{
  "type": "Feature",
  "properties": {
    "iso:country":"GB",
    "wof:name":"HX1 5ED",
    "wof:placetype":"postalcode"
},
  "geometry": {"coordinates":[-1.87829046788947,53.72113050134502],"type":"Point"}
}