{
  "type": "Feature",
  "properties": {
    "date:inception_lower": "1991-09-01",
    "date:inception_upper": "1991-09-01",
    "iso:country": "GB",
    "wof:name": "HX1 5ED",
    "wof:placetype": "postalcode"
  },
  "geometry": {"coordinates":[-1.878292,53.721145],"type":"Point"}
}
