{
  "type": "Feature",
  "properties": {
    "iso:country": "GB",
    "wof:name": "HX1 5ED",
    "wof:placetype": "postalcode"
  },
  "geometry": {"coordinates":[-1.87829,53.72113],"type":"Point"}
}
