{
  "type": "Feature",
  "properties": {
    "iso:country": "GB",
    "wof:name": "BN26 6JT",
    "wof:placetype": "postalcode"
  },
  "geometry": {"coordinates":[0.26308,50.820519],"type":"Point"}
}
