{
  "type": "Feature",
  "properties": {
    "iso:country": "GB",
    "wof:name": "SW8 1RL",
    "wof:placetype": "postalcode"
  },
  "geometry": {"coordinates":[-0.124037,51.48289],"type":"Point"}
}
