{
  "type": "Feature",
  "properties": {
    "iso:country":"GB",
    "wof:name":"HD5 8SS",
    "wof:placetype":"postalcode"
},
  "geometry": {"coordinates":[-1.73769793744984,53.63946381315982],"type":"Point"}
}