{
  "type": "Feature",
  "properties": {
    "iso:country":"GB",
    "wof:name":"NG3 6EF",
    "wof:placetype":"postalcode"
},
  "geometry": {"coordinates":[-1.12129791609023,52.97824541584519],"type":"Point"}
}