{
  "type": "Feature",
  "properties": {
    "iso:country":"GB",
    "wof:name":"TS3 0AR",
    "wof:placetype":"postalcode"
},
  "geometry": {"coordinates":[-1.19911732761399,54.54599037869217],"type":"Point"}
}