{
  "type": "Feature",
  "properties": {
    "date:inception_lower": "1997-12-01",
    "date:inception_upper": "1997-12-01",
    "iso:country": "GB",
    "wof:name": "IG10 4QS",
    "wof:placetype": "postalcode"
  },
  "geometry": {"coordinates":[0.044444,51.634934],"type":"Point"}
}
