{
  "type": "Feature",
  "properties": {
    "iso:country":"GB",
    "wof:name":"IG10 4QS",
    "wof:placetype":"postalcode"
},
  "geometry": {"coordinates":[0.04444427482586,51.63493440244605],"type":"Point"}
}