{
  "type": "Feature",
  "properties": {
    "iso:country":"GB",
    "wof:name":"N5 2SD",
    "wof:placetype":"postalcode"
},
  "geometry": {"coordinates":[-0.08825805274882,51.55171499827009],"type":"Point"}
}