{
  "type": "Feature",
  "properties": {
    "iso:country": "GB",
    "wof:name": "FY3 9TY",
    "wof:placetype": "postalcode"
  },
  "geometry": {"coordinates":[-2.998678,53.80317],"type":"Point"}
}
