{
  "type": "Feature",
  "properties": {
    "iso:country":"GB",
    "wof:name":"FY3 9TY",
    "wof:placetype":"postalcode"
},
  "geometry": {"coordinates":[-2.9988039093663,53.80315408592512],"type":"Point"}
}