{
  "type": "Feature",
  "properties": {
    "iso:country": "GB",
    "wof:name": "G33 6FR",
    "wof:placetype": "postalcode"
  },
  "geometry": {"coordinates":[-4.144548,55.884529],"type":"Point"}
}
