{
  "type": "Feature",
  "properties": {
    "iso:country":"GB",
    "wof:name":"ME8 6PT",
    "wof:placetype":"postalcode"
},
  "geometry": {"coordinates":[0.57815202312733,51.37915398392567],"type":"Point"}
}