{
  "type": "Feature",
  "properties": {
    "iso:country":"GB",
    "wof:name":"CR7 8DB",
    "wof:placetype":"postalcode"
},
  "geometry": {"coordinates":[-0.10190052709401,51.40713769765659],"type":"Point"}
}