{
  "type": "Feature",
  "properties": {
    "iso:country": "GB",
    "wof:name": "NE27 0SH",
    "wof:placetype": "postalcode"
  },
  "geometry": {"coordinates":[-1.527325,55.042751],"type":"Point"}
}
