{
  "type": "Feature",
  "properties": {
    "iso:country":"GB",
    "wof:name":"NE27 0SH",
    "wof:placetype":"postalcode"
},
  "geometry": {"coordinates":[-1.52732546508892,55.04275086774742],"type":"Point"}
}