{
  "type": "Feature",
  "properties": {
    "iso:country":"GB",
    "wof:name":"AL1 3GU",
    "wof:placetype":"postalcode"
},
  "geometry": {"coordinates":[-0.32947236958733,51.75380802282343],"type":"Point"}
}