{
  "type": "Feature",
  "properties": {
    "date:inception_lower":"2011-07-01",
    "date:inception_upper":"2011-07-31",
    "iso:country":"GB",
    "wof:name":"AL1 3GU",
    "wof:placetype":"postalcode"
},
  "geometry": {"coordinates":[-0.329472,51.753808],"type":"Point"}
}