{
  "type": "Feature",
  "properties": {
    "iso:country": "GB",
    "wof:name": "AL1 3GU",
    "wof:placetype": "postalcode"
  },
  "geometry": {"coordinates":[-0.329472,51.753808],"type":"Point"}
}
