{
  "type": "Feature",
  "properties": {
    "date:inception_lower":"1980-01-01",
    "date:inception_upper":"1980-01-31",
    "iso:country":"GB",
    "wof:name":"BH20 7DS",
    "wof:placetype":"postalcode"
},
  "geometry": {"coordinates":[-2.122668,50.759164],"type":"Point"}
}