{
  "type": "Feature",
  "properties": {
    "iso:country": "GB",
    "wof:name": "BH20 7DS",
    "wof:placetype": "postalcode"
  },
  "geometry": {"coordinates":[-2.122668,50.759164],"type":"Point"}
}
