{
  "type": "Feature",
  "properties": {
    "iso:country": "GB",
    "wof:name": "BN6 9XP",
    "wof:placetype": "postalcode"
  },
  "geometry": {"coordinates":[-0.194908,50.949816],"type":"Point"}
}
