{
  "type": "Feature",
  "properties": {
    "iso:country":"GB",
    "wof:name":"BN6 9XP",
    "wof:placetype":"postalcode"
},
  "geometry": {"coordinates":[-0.19490776648555,50.94981590586313],"type":"Point"}
}