{
  "type": "Feature",
  "properties": {
    "date:inception_lower":"1993-01-01",
    "date:inception_upper":"1993-01-31",
    "iso:country":"GB",
    "wof:name":"BN6 9XP",
    "wof:placetype":"postalcode"
},
  "geometry": {"coordinates":[-0.194908,50.949816],"type":"Point"}
}