{
  "type": "Feature",
  "properties": {
    "iso:country":"GB",
    "wof:name":"TN38 8AL",
    "wof:placetype":"postalcode"
},
  "geometry": {"coordinates":[0.52049124009122,50.85039875989995],"type":"Point"}
}