{
  "type": "Feature",
  "properties": {
    "iso:country": "GB",
    "wof:name": "DN11 0EZ",
    "wof:placetype": "postalcode"
  },
  "geometry": {"coordinates":[-1.058363,53.480035],"type":"Point"}
}
