{
  "type": "Feature",
  "properties": {
    "iso:country":"GB",
    "wof:name":"DN11 0EZ",
    "wof:placetype":"postalcode"
},
  "geometry": {"coordinates":[-1.05836274291889,53.48001501738397],"type":"Point"}
}