{
  "type": "Feature",
  "properties": {
    "iso:country": "GB",
    "wof:name": "NN29 7JJ",
    "wof:placetype": "postalcode"
  },
  "geometry": {"coordinates":[-0.672601,52.220368],"type":"Point"}
}
