{
  "type": "Feature",
  "properties": {
    "iso:country":"GB",
    "wof:name":"NN29 7JJ",
    "wof:placetype":"postalcode"
},
  "geometry": {"coordinates":[-0.67261757604961,52.22035422077284],"type":"Point"}
}