{
  "type": "Feature",
  "properties": {
    "iso:country":"GB",
    "wof:name":"CV3 2LY",
    "wof:placetype":"postalcode"
},
  "geometry": {"coordinates":[-1.44992437851777,52.39342234869222],"type":"Point"}
}