{
  "type": "Feature",
  "properties": {
    "iso:country":"GB",
    "wof:name":"WV2 2QX",
    "wof:placetype":"postalcode"
},
  "geometry": {"coordinates":[-2.11456504844172,52.57471390982383],"type":"Point"}
}