{
  "type": "Feature",
  "properties": {
    "iso:country": "GB",
    "wof:name": "WV2 2QX",
    "wof:placetype": "postalcode"
  },
  "geometry": {"coordinates":[-2.114565,52.574714],"type":"Point"}
}
