{
  "type": "Feature",
  "properties": {
    "date:inception_lower": "1985-04-01",
    "date:inception_upper": "1985-04-01",
    "iso:country": "GB",
    "wof:name": "WV2 2QX",
    "wof:placetype": "postalcode"
  },
  "geometry": {"coordinates":[-2.114565,52.574714],"type":"Point"}
}
