{
  "type": "Feature",
  "properties": {
    "date:inception_lower":"1980-01-01",
    "date:inception_upper":"1980-01-31",
    "iso:country":"GB",
    "wof:name":"NE5 1EJ",
    "wof:placetype":"postalcode"
},
  "geometry": {"coordinates":[-1.718112,54.994448],"type":"Point"}
}