{
  "type": "Feature",
  "properties": {
    "iso:country":"GB",
    "wof:name":"NE5 1EJ",
    "wof:placetype":"postalcode"
},
  "geometry": {"coordinates":[-1.71811236015733,54.99444799836707],"type":"Point"}
}