{
  "type": "Feature",
  "properties": {
    "date:inception_lower":"2018-01-01",
    "date:inception_upper":"2018-01-31",
    "iso:country":"GB",
    "wof:name":"W12 7FT",
    "wof:placetype":"postalcode"
},
  "geometry": {"coordinates":[-0.226238,51.510352],"type":"Point"}
}