{
  "type": "Feature",
  "properties": {
    "date:inception_lower": "1981-06-01",
    "date:inception_upper": "1981-06-01",
    "iso:country": "GB",
    "wof:name": "RH20 4RD",
    "wof:placetype": "postalcode"
  },
  "geometry": {"coordinates":[-0.444714,50.915939],"type":"Point"}
}
