{
  "type": "Feature",
  "properties": {
    "iso:country": "GB",
    "wof:name": "SW14 8HL",
    "wof:placetype": "postalcode"
  },
  "geometry": {"coordinates":[-0.263549,51.470002],"type":"Point"}
}
