{
  "type": "Feature",
  "properties": {
    "iso:country": "GB",
    "wof:name": "TN33 9RB",
    "wof:placetype": "postalcode"
  },
  "geometry": {"coordinates":[0.425362,50.8839],"type":"Point"}
}
