{
  "type": "Feature",
  "properties": {
    "iso:country":"GB",
    "wof:name":"TN33 9RB",
    "wof:placetype":"postalcode"
},
  "geometry": {"coordinates":[0.42536015201217,50.88388573573899],"type":"Point"}
}