{
  "type": "Feature",
  "properties": {
    "iso:country":"GB",
    "wof:name":"DE6 4NL",
    "wof:placetype":"postalcode"
},
  "geometry": {"coordinates":[-1.60138120609042,52.95696577426755],"type":"Point"}
}