{
  "type": "Feature",
  "properties": {
    "date:inception_lower": "2018-03-01",
    "date:inception_upper": "2018-03-01",
    "iso:country": "GB",
    "wof:name": "HU7 3LG",
    "wof:placetype": "postalcode"
  },
  "geometry": {"coordinates":[-0.341952,53.806286],"type":"Point"}
}
