{
  "type": "Feature",
  "properties": {
    "iso:country":"GB",
    "wof:name":"RH13 6HL",
    "wof:placetype":"postalcode"
},
  "geometry": {"coordinates":[-0.29343114628402,51.07397138275182],"type":"Point"}
}