{
  "type": "Feature",
  "properties": {
    "date:inception_lower": "1980-01-01",
    "date:inception_upper": "1980-01-01",
    "iso:country": "GB",
    "wof:name": "HA2 7AX",
    "wof:placetype": "postalcode"
  },
  "geometry": {"coordinates":[-0.35577,51.58003],"type":"Point"}
}
