{
  "type": "Feature",
  "properties": {
    "iso:country":"GB",
    "wof:name":"HA2 7AX",
    "wof:placetype":"postalcode"
},
  "geometry": {"coordinates":[-0.35576958590913,51.58002968627888],"type":"Point"}
}