{
  "type": "Feature",
  "properties": {
    "date:inception_lower": "1980-01-01",
    "date:inception_upper": "1980-01-01",
    "iso:country": "GB",
    "wof:name": "BD22 8JB",
    "wof:placetype": "postalcode"
  },
  "geometry": {"coordinates":[-1.945249,53.832505],"type":"Point"}
}
