{
  "type": "Feature",
  "properties": {
    "iso:country":"GB",
    "wof:name":"BD22 8JB",
    "wof:placetype":"postalcode"
},
  "geometry": {"coordinates":[-1.94524870772548,53.83250487609691],"type":"Point"}
}