{
  "type": "Feature",
  "properties": {
    "iso:country":"GB",
    "wof:name":"WA14 5HJ",
    "wof:placetype":"postalcode"
},
  "geometry": {"coordinates":[-2.35952888212732,53.39963239846406],"type":"Point"}
}