{
  "type": "Feature",
  "properties": {
    "date:inception_lower":"2010-11-01",
    "date:inception_upper":"2010-11-30",
    "iso:country":"GB",
    "wof:name":"OX4 4GN",
    "wof:placetype":"postalcode"
},
  "geometry": {"coordinates":[-1.229657,51.72485],"type":"Point"}
}