{
  "type": "Feature",
  "properties": {
    "iso:country": "GB",
    "wof:name": "CH2 1EQ",
    "wof:placetype": "postalcode"
  },
  "geometry": {"coordinates":[-2.891012,53.218929],"type":"Point"}
}
