{
  "type": "Feature",
  "properties": {
    "date:inception_lower": "2018-10-01",
    "date:inception_upper": "2018-10-01",
    "iso:country": "GB",
    "wof:name": "DH4 5AA",
    "wof:placetype": "postalcode"
  },
  "geometry": {"coordinates":[-1.485158,54.851386],"type":"Point"}
}
