{
  "type": "Feature",
  "properties": {
    "iso:country":"GB",
    "wof:name":"HP13 5DQ",
    "wof:placetype":"postalcode"
},
  "geometry": {"coordinates":[-0.75308600635815,51.63153632588597],"type":"Point"}
}