{
  "type": "Feature",
  "properties": {
    "iso:country":"GB",
    "wof:name":"TR1 1SA",
    "wof:placetype":"postalcode"
},
  "geometry": {"coordinates":[-5.03927084464964,50.27154519605207],"type":"Point"}
}