{
  "type": "Feature",
  "properties": {
    "iso:country": "GB",
    "wof:name": "DN16 3QA",
    "wof:placetype": "postalcode"
  },
  "geometry": {"coordinates":[-0.642849,53.555636],"type":"Point"}
}
