{
  "type": "Feature",
  "properties": {
    "date:inception_lower":"1996-06-01",
    "date:inception_upper":"1996-06-30",
    "iso:country":"GB",
    "wof:name":"AB11 6NA",
    "wof:placetype":"postalcode"
},
  "geometry": {"coordinates":[-2.096655,57.144486],"type":"Point"}
}