{
  "type": "Feature",
  "properties": {
    "iso:country":"GB",
    "wof:name":"TN34 3NB",
    "wof:placetype":"postalcode"
},
  "geometry": {"coordinates":[0.58937384861169,50.86377558324122],"type":"Point"}
}