{
  "type": "Feature",
  "properties": {
    "date:inception_lower":"1996-12-01",
    "date:inception_upper":"1996-12-31",
    "iso:country":"GB",
    "wof:name":"BL8 3LE",
    "wof:placetype":"postalcode"
},
  "geometry": {"coordinates":[-2.334069,53.610656],"type":"Point"}
}