{
  "type": "Feature",
  "properties": {
    "iso:country": "GB",
    "wof:name": "BL8 3LE",
    "wof:placetype": "postalcode"
  },
  "geometry": {"coordinates":[-2.334069,53.610656],"type":"Point"}
}
