{
  "type": "Feature",
  "properties": {
    "iso:country":"GB",
    "wof:name":"LA6 1DT",
    "wof:placetype":"postalcode"
},
  "geometry": {"coordinates":[-2.73037824593195,54.12128512526731],"type":"Point"}
}