{
  "type": "Feature",
  "properties": {
    "iso:country": "GB",
    "wof:name": "DE12 6AT",
    "wof:placetype": "postalcode"
  },
  "geometry": {"coordinates":[-1.536118,52.733789],"type":"Point"}
}
