{
  "type": "Feature",
  "properties": {
    "date:inception_lower": "1980-01-01",
    "date:inception_upper": "1980-01-01",
    "iso:country": "GB",
    "wof:name": "ME15 9HP",
    "wof:placetype": "postalcode"
  },
  "geometry": {"coordinates":[0.558402,51.241633],"type":"Point"}
}
