{
  "type": "Feature",
  "properties": {
    "iso:country": "GB",
    "wof:name": "CO3 4LR",
    "wof:placetype": "postalcode"
  },
  "geometry": {"coordinates":[0.860073,51.880993],"type":"Point"}
}
