{
  "type": "Feature",
  "properties": {
    "iso:country":"GB",
    "wof:name":"SL2 4GQ",
    "wof:placetype":"postalcode"
},
  "geometry": {"coordinates":[-0.57633315426389,51.53045293625092],"type":"Point"}
}