{
  "type": "Feature",
  "properties": {
    "date:inception_lower": "2003-02-01",
    "date:inception_upper": "2003-02-01",
    "iso:country": "GB",
    "wof:name": "SL2 4GQ",
    "wof:placetype": "postalcode"
  },
  "geometry": {"coordinates":[-0.576333,51.530453],"type":"Point"}
}
