{
  "type": "Feature",
  "properties": {
    "iso:country":"GB",
    "wof:name":"NG3 7DB",
    "wof:placetype":"postalcode"
},
  "geometry": {"coordinates":[-1.11975374962869,52.96041680456278],"type":"Point"}
}