{
  "type": "Feature",
  "properties": {
    "iso:country": "GB",
    "wof:name": "YO22 4PQ",
    "wof:placetype": "postalcode"
  },
  "geometry": {"coordinates":[-0.551134,54.442031],"type":"Point"}
}
