{
  "type": "Feature",
  "properties": {
    "iso:country": "GB",
    "wof:name": "M14 5HL",
    "wof:placetype": "postalcode"
  },
  "geometry": {"coordinates":[-2.217415,53.451831],"type":"Point"}
}
