{
  "type": "Feature",
  "properties": {
    "iso:country":"GB",
    "wof:name":"M14 5HL",
    "wof:placetype":"postalcode"
},
  "geometry": {"coordinates":[-2.21741472919215,53.45183088851036],"type":"Point"}
}