{
  "type": "Feature",
  "properties": {
    "date:inception_lower":"1980-01-01",
    "date:inception_upper":"1980-01-31",
    "iso:country":"GB",
    "wof:name":"M14 5HL",
    "wof:placetype":"postalcode"
},
  "geometry": {"coordinates":[-2.217415,53.451831],"type":"Point"}
}