{
  "type": "Feature",
  "properties": {
    "iso:country":"GB",
    "wof:name":"RM8 2HQ",
    "wof:placetype":"postalcode"
},
  "geometry": {"coordinates":[0.11335169379262,51.54390387805971],"type":"Point"}
}