{
  "type": "Feature",
  "properties": {
    "iso:country":"GB",
    "wof:name":"LS29 6LQ",
    "wof:placetype":"postalcode"
},
  "geometry": {"coordinates":[-1.7417328300119,53.88996005754282],"type":"Point"}
}