{
  "type": "Feature",
  "properties": {
    "date:inception_lower": "1980-01-01",
    "date:inception_upper": "1980-01-01",
    "iso:country": "GB",
    "wof:name": "LS29 6LQ",
    "wof:placetype": "postalcode"
  },
  "geometry": {"coordinates":[-1.741733,53.88996],"type":"Point"}
}
