{
  "type": "Feature",
  "properties": {
    "date:inception_lower":"1980-01-01",
    "date:inception_upper":"1980-01-31",
    "iso:country":"GB",
    "wof:name":"DA3 8LG",
    "wof:placetype":"postalcode"
},
  "geometry": {"coordinates":[0.311072,51.365869],"type":"Point"}
}