{
  "type": "Feature",
  "properties": {
    "iso:country": "GB",
    "wof:name": "DA3 8LG",
    "wof:placetype": "postalcode"
  },
  "geometry": {"coordinates":[0.311072,51.365869],"type":"Point"}
}
