{
  "type": "Feature",
  "properties": {
    "iso:country":"GB",
    "wof:name":"DA3 8LG",
    "wof:placetype":"postalcode"
},
  "geometry": {"coordinates":[0.31107189595355,51.36586934241542],"type":"Point"}
}