{
  "type": "Feature",
  "properties": {
    "iso:country":"GB",
    "wof:name":"NR1 2JU",
    "wof:placetype":"postalcode"
},
  "geometry": {"coordinates":[1.29655014012478,52.61440652471235],"type":"Point"}
}