{
  "type": "Feature",
  "properties": {
    "date:inception_lower": "2000-12-01",
    "date:inception_upper": "2000-12-01",
    "iso:country": "GB",
    "wof:name": "W1U 4QT",
    "wof:placetype": "postalcode"
  },
  "geometry": {"coordinates":[-0.15206,51.520292],"type":"Point"}
}
