{
  "type": "Feature",
  "properties": {
    "iso:country":"GB",
    "wof:name":"W1U 4QT",
    "wof:placetype":"postalcode"
},
  "geometry": {"coordinates":[-0.15206023141854,51.52029246999646],"type":"Point"}
}