{
  "type": "Feature",
  "properties": {
    "iso:country":"GB",
    "wof:name":"HP3 9LY",
    "wof:placetype":"postalcode"
},
  "geometry": {"coordinates":[-0.45006329629553,51.74092026713953],"type":"Point"}
}