{
  "type": "Feature",
  "properties": {
    "iso:country": "GB",
    "wof:name": "G31 5LX",
    "wof:placetype": "postalcode"
  },
  "geometry": {"coordinates":[-4.18752,55.851459],"type":"Point"}
}
