{
  "type": "Feature",
  "properties": {
    "date:inception_lower": "2016-03-01",
    "date:inception_upper": "2016-03-01",
    "iso:country": "GB",
    "wof:name": "G31 5LX",
    "wof:placetype": "postalcode"
  },
  "geometry": {"coordinates":[-4.18752,55.851459],"type":"Point"}
}
