{
  "type": "Feature",
  "properties": {
    "iso:country":"GB",
    "wof:name":"G31 5LX",
    "wof:placetype":"postalcode"
},
  "geometry": {"coordinates":[-4.18751969930076,55.8514590030718],"type":"Point"}
}