{
  "type": "Feature",
  "properties": {
    "iso:country":"GB",
    "wof:name":"IG6 2EZ",
    "wof:placetype":"postalcode"
},
  "geometry": {"coordinates":[0.08445092652228,51.59345821235789],"type":"Point"}
}