{
  "type": "Feature",
  "properties": {
    "iso:country": "GB",
    "wof:name": "TN6 3JZ",
    "wof:placetype": "postalcode"
  },
  "geometry": {"coordinates":[0.191515,51.046233],"type":"Point"}
}
