{
  "type": "Feature",
  "properties": {
    "date:inception_lower": "1992-08-01",
    "date:inception_upper": "1992-08-01",
    "iso:country": "GB",
    "wof:name": "TN6 3JZ",
    "wof:placetype": "postalcode"
  },
  "geometry": {"coordinates":[0.191515,51.046233],"type":"Point"}
}
