{
  "type": "Feature",
  "properties": {
    "iso:country":"GB",
    "wof:name":"TN6 3JZ",
    "wof:placetype":"postalcode"
},
  "geometry": {"coordinates":[0.19151521788652,51.04623326053824],"type":"Point"}
}