{
  "type": "Feature",
  "properties": {
    "iso:country": "GB",
    "wof:name": "PR7 5NH",
    "wof:placetype": "postalcode"
  },
  "geometry": {"coordinates":[-2.665975,53.636916],"type":"Point"}
}
