{
  "type": "Feature",
  "properties": {
    "iso:country": "GB",
    "wof:name": "PO12 2RP",
    "wof:placetype": "postalcode"
  },
  "geometry": {"coordinates":[-1.159867,50.791708],"type":"Point"}
}
