{
  "type": "Feature",
  "properties": {
    "iso:country":"GB",
    "wof:name":"PO12 2RP",
    "wof:placetype":"postalcode"
},
  "geometry": {"coordinates":[-1.15986703836795,50.79170835337626],"type":"Point"}
}