{
  "type": "Feature",
  "properties": {
    "iso:country":"GB",
    "wof:name":"TN18 5LE",
    "wof:placetype":"postalcode"
},
  "geometry": {"coordinates":[0.55795170749632,51.02532942667475],"type":"Point"}
}