{
  "type": "Feature",
  "properties": {
    "iso:country": "GB",
    "wof:name": "TN18 5LE",
    "wof:placetype": "postalcode"
  },
  "geometry": {"coordinates":[0.557371,51.024854],"type":"Point"}
}
