{
  "type": "Feature",
  "properties": {
    "date:inception_lower":"2000-06-01",
    "date:inception_upper":"2000-06-30",
    "iso:country":"GB",
    "wof:name":"OL14 5PN",
    "wof:placetype":"postalcode"
},
  "geometry": {"coordinates":[-2.105437,53.721757],"type":"Point"}
}