{
  "type": "Feature",
  "properties": {
    "iso:country":"GB",
    "wof:name":"WD4 9JN",
    "wof:placetype":"postalcode"
},
  "geometry": {"coordinates":[-0.48346311765037,51.71149407570657],"type":"Point"}
}