{
  "type": "Feature",
  "properties": {
    "date:inception_lower":"1980-01-01",
    "date:inception_upper":"1980-01-31",
    "iso:country":"GB",
    "wof:name":"RH6 7HY",
    "wof:placetype":"postalcode"
},
  "geometry": {"coordinates":[-0.168069,51.175116],"type":"Point"}
}