{
  "type": "Feature",
  "properties": {
    "date:inception_lower":"1995-12-01",
    "date:inception_upper":"1995-12-31",
    "iso:country":"GB",
    "wof:name":"EX8 3RA",
    "wof:placetype":"postalcode"
},
  "geometry": {"coordinates":[-3.398707,50.629033],"type":"Point"}
}