{
  "type": "Feature",
  "properties": {
    "iso:country": "GB",
    "wof:name": "EX8 3RA",
    "wof:placetype": "postalcode"
  },
  "geometry": {"coordinates":[-3.398707,50.629033],"type":"Point"}
}
