{
  "type": "Feature",
  "properties": {
    "iso:country":"GB",
    "wof:name":"KY15 4RB",
    "wof:placetype":"postalcode"
},
  "geometry": {"coordinates":[-2.99192570338191,56.32319537901984],"type":"Point"}
}