{
  "type": "Feature",
  "properties": {
    "iso:country":"GB",
    "wof:name":"BD11 1DT",
    "wof:placetype":"postalcode"
},
  "geometry": {"coordinates":[-1.65131895441278,53.75145177674572],"type":"Point"}
}