{
  "type": "Feature",
  "properties": {
    "iso:country":"GB",
    "wof:name":"HP21 7UT",
    "wof:placetype":"postalcode"
},
  "geometry": {"coordinates":[-0.80298566825764,51.80611455470494],"type":"Point"}
}