{
  "type": "Feature",
  "properties": {
    "iso:country": "GB",
    "wof:name": "TS29 6PQ",
    "wof:placetype": "postalcode"
  },
  "geometry": {"coordinates":[-1.424595,54.701936],"type":"Point"}
}
