{
  "type": "Feature",
  "properties": {
    "iso:country":"GB",
    "wof:name":"TS29 6PQ",
    "wof:placetype":"postalcode"
},
  "geometry": {"coordinates":[-1.42459501561292,54.70193630582961],"type":"Point"}
}