{
  "type": "Feature",
  "properties": {
    "date:inception_lower": "1980-01-01",
    "date:inception_upper": "1980-01-01",
    "iso:country": "GB",
    "wof:name": "PA5 0AP",
    "wof:placetype": "postalcode"
  },
  "geometry": {"coordinates":[-4.508481,55.829827],"type":"Point"}
}
