{
  "type": "Feature",
  "properties": {
    "iso:country":"GB",
    "wof:name":"WS7 2HL",
    "wof:placetype":"postalcode"
},
  "geometry": {"coordinates":[-1.9245965151866,52.68816914611971],"type":"Point"}
}