{
  "type": "Feature",
  "properties": {
    "iso:country": "GB",
    "wof:name": "WS7 2HL",
    "wof:placetype": "postalcode"
  },
  "geometry": {"coordinates":[-1.924596,52.688169],"type":"Point"}
}
