{
  "type": "Feature",
  "properties": {
    "date:inception_lower": "2003-03-01",
    "date:inception_upper": "2003-03-01",
    "iso:country": "GB",
    "wof:name": "WS7 2HL",
    "wof:placetype": "postalcode"
  },
  "geometry": {"coordinates":[-1.924596,52.688169],"type":"Point"}
}
