{
  "type": "Feature",
  "properties": {
    "iso:country": "GB",
    "wof:name": "EH54 5BU",
    "wof:placetype": "postalcode"
  },
  "geometry": {"coordinates":[-3.493459,55.903254],"type":"Point"}
}
