{
  "type": "Feature",
  "properties": {
    "date:inception_lower":"2004-06-01",
    "date:inception_upper":"2004-06-30",
    "iso:country":"GB",
    "wof:name":"EH54 5BU",
    "wof:placetype":"postalcode"
},
  "geometry": {"coordinates":[-3.493459,55.903254],"type":"Point"}
}