{
  "type": "Feature",
  "properties": {
    "iso:country": "GB",
    "wof:name": "TW20 0XD",
    "wof:placetype": "postalcode"
  },
  "geometry": {"coordinates":[-0.594085,51.432419],"type":"Point"}
}
