{
  "type": "Feature",
  "properties": {
    "iso:country": "GB",
    "wof:name": "DL14 6UG",
    "wof:placetype": "postalcode"
  },
  "geometry": {"coordinates":[-1.692384,54.656432],"type":"Point"}
}
