{
  "type": "Feature",
  "properties": {
    "iso:country": "GB",
    "wof:name": "SN13 8EA",
    "wof:placetype": "postalcode"
  },
  "geometry": {"coordinates":[-2.252941,51.414615],"type":"Point"}
}
