{
  "type": "Feature",
  "properties": {
    "iso:country": "GB",
    "wof:name": "PE34 3LZ",
    "wof:placetype": "postalcode"
  },
  "geometry": {"coordinates":[0.385756,52.758065],"type":"Point"}
}
