{
  "type": "Feature",
  "properties": {
    "date:inception_lower": "1980-01-01",
    "date:inception_upper": "1980-01-01",
    "iso:country": "GB",
    "wof:name": "PE34 3LZ",
    "wof:placetype": "postalcode"
  },
  "geometry": {"coordinates":[0.385756,52.758065],"type":"Point"}
}
