{
  "type": "Feature",
  "properties": {
    "iso:country":"GB",
    "wof:name":"FK15 0EB",
    "wof:placetype":"postalcode"
},
  "geometry": {"coordinates":[-3.94731527571728,56.19078586376778],"type":"Point"}
}