{
  "type": "Feature",
  "properties": {
    "iso:country":"GB",
    "wof:name":"WC2H 9LT",
    "wof:placetype":"postalcode"
},
  "geometry": {"coordinates":[-0.12634604905036,51.51394947200168],"type":"Point"}
}