{
  "type": "Feature",
  "properties": {
    "iso:country": "GB",
    "wof:name": "WS14 0GD",
    "wof:placetype": "postalcode"
  },
  "geometry": {"coordinates":[-1.836444,52.670982],"type":"Point"}
}
