{
  "type": "Feature",
  "properties": {
    "date:inception_lower":"2007-07-01",
    "date:inception_upper":"2007-07-31",
    "iso:country":"GB",
    "wof:name":"WS14 0GD",
    "wof:placetype":"postalcode"
},
  "geometry": {"coordinates":[-1.836444,52.670982],"type":"Point"}
}