{
  "type": "Feature",
  "properties": {
    "date:inception_lower":"2018-05-01",
    "date:inception_upper":"2018-05-31",
    "iso:country":"GB",
    "wof:name":"B5 4RX",
    "wof:placetype":"postalcode"
},
  "geometry": {"coordinates":[-1.896362,52.475976],"type":"Point"}
}