{
  "type": "Feature",
  "properties": {
    "iso:country": "GB",
    "wof:name": "B5 4RX",
    "wof:placetype": "postalcode"
  },
  "geometry": {"coordinates":[-1.896362,52.475976],"type":"Point"}
}
