{
  "type": "Feature",
  "properties": {
    "iso:country":"GB",
    "wof:name":"LL17 0HY",
    "wof:placetype":"postalcode"
},
  "geometry": {"coordinates":[-3.46336289263417,53.26455931248304],"type":"Point"}
}