{
  "type": "Feature",
  "properties": {
    "iso:country":"GB",
    "wof:name":"RG40 2AB",
    "wof:placetype":"postalcode"
},
  "geometry": {"coordinates":[-0.8369649280659,51.41062207197754],"type":"Point"}
}