{
  "type": "Feature",
  "properties": {
    "iso:country": "GB",
    "wof:name": "OL12 6NW",
    "wof:placetype": "postalcode"
  },
  "geometry": {"coordinates":[-2.166637,53.631572],"type":"Point"}
}
