{
  "type": "Feature",
  "properties": {
    "iso:country": "GB",
    "wof:name": "BL1 7JD",
    "wof:placetype": "postalcode"
  },
  "geometry": {"coordinates":[-2.434038,53.604942],"type":"Point"}
}
