{
  "type": "Feature",
  "properties": {
    "iso:country":"GB",
    "wof:name":"BL1 7JD",
    "wof:placetype":"postalcode"
},
  "geometry": {"coordinates":[-2.43403845580288,53.60494214483438],"type":"Point"}
}