{
  "type": "Feature",
  "properties": {
    "iso:country": "GB",
    "wof:name": "LE3 3SE",
    "wof:placetype": "postalcode"
  },
  "geometry": {"coordinates":[-1.204006,52.622018],"type":"Point"}
}
