{
  "type": "Feature",
  "properties": {
    "iso:country":"GB",
    "wof:name":"LE3 3SE",
    "wof:placetype":"postalcode"
},
  "geometry": {"coordinates":[-1.2040063188747,52.62201755930541],"type":"Point"}
}