{
  "type": "Feature",
  "properties": {
    "date:inception_lower": "1980-01-01",
    "date:inception_upper": "1980-01-01",
    "iso:country": "GB",
    "wof:name": "L40 7TG",
    "wof:placetype": "postalcode"
  },
  "geometry": {"coordinates":[-2.854035,53.58838],"type":"Point"}
}
