{
  "type": "Feature",
  "properties": {
    "iso:country":"GB",
    "wof:name":"L40 7TG",
    "wof:placetype":"postalcode"
},
  "geometry": {"coordinates":[-2.85403525840138,53.588380141379],"type":"Point"}
}