{
  "type": "Feature",
  "properties": {
    "iso:country":"GB",
    "wof:name":"TN4 8PZ",
    "wof:placetype":"postalcode"
},
  "geometry": {"coordinates":[0.24059482416254,51.13605619639264],"type":"Point"}
}