{
  "type": "Feature",
  "properties": {
    "iso:country": "GB",
    "wof:name": "TN4 8PZ",
    "wof:placetype": "postalcode"
  },
  "geometry": {"coordinates":[0.240595,51.136099],"type":"Point"}
}
