{
  "type": "Feature",
  "properties": {
    "iso:country":"GB",
    "wof:name":"LU4 9AB",
    "wof:placetype":"postalcode"
},
  "geometry": {"coordinates":[-0.46319871059464,51.90769142206902],"type":"Point"}
}