{
  "type": "Feature",
  "properties": {
    "iso:country":"GB",
    "wof:name":"BS15 1UL",
    "wof:placetype":"postalcode"
},
  "geometry": {"coordinates":[-2.50255837600027,51.46758852537777],"type":"Point"}
}