{
  "type": "Feature",
  "properties": {
    "iso:country":"GB",
    "wof:name":"CA15 8SW",
    "wof:placetype":"postalcode"
},
  "geometry": {"coordinates":[-3.4742232655826,54.68614407435582],"type":"Point"}
}