{
  "type": "Feature",
  "properties": {
    "iso:country": "GB",
    "wof:name": "CA15 8SW",
    "wof:placetype": "postalcode"
  },
  "geometry": {"coordinates":[-3.474269,54.686123],"type":"Point"}
}
