{
  "type": "Feature",
  "properties": {
    "date:inception_lower": "1980-01-01",
    "date:inception_upper": "1980-01-01",
    "iso:country": "GB",
    "wof:name": "CM2 8UQ",
    "wof:placetype": "postalcode"
  },
  "geometry": {"coordinates":[0.498369,51.670025],"type":"Point"}
}
