{
  "type": "Feature",
  "properties": {
    "iso:country":"GB",
    "wof:name":"CM2 8UQ",
    "wof:placetype":"postalcode"
},
  "geometry": {"coordinates":[0.498564043981,51.67035682436241],"type":"Point"}
}