{
  "type": "Feature",
  "properties": {
    "iso:country":"GB",
    "wof:name":"IV19 1LB",
    "wof:placetype":"postalcode"
},
  "geometry": {"coordinates":[-4.17811188867435,57.84260298513946],"type":"Point"}
}