{
  "type": "Feature",
  "properties": {
    "date:inception_lower":"1981-06-01",
    "date:inception_upper":"1981-06-30",
    "iso:country":"GB",
    "wof:name":"IP33 3JX",
    "wof:placetype":"postalcode"
},
  "geometry": {"coordinates":[0.702694,52.239958],"type":"Point"}
}