{
  "type": "Feature",
  "properties": {
    "iso:country":"GB",
    "wof:name":"IP33 3JX",
    "wof:placetype":"postalcode"
},
  "geometry": {"coordinates":[0.70269365255224,52.23995846608972],"type":"Point"}
}