{
  "type": "Feature",
  "properties": {
    "date:inception_lower": "1980-01-01",
    "date:inception_upper": "1980-01-01",
    "iso:country": "GB",
    "wof:name": "L23 5TG",
    "wof:placetype": "postalcode"
  },
  "geometry": {"coordinates":[-3.024221,53.487995],"type":"Point"}
}
