{
  "type": "Feature",
  "properties": {
    "iso:country": "GB",
    "wof:name": "B64 6LT",
    "wof:placetype": "postalcode"
  },
  "geometry": {"coordinates":[-2.066909,52.471583],"type":"Point"}
}
