{
  "type": "Feature",
  "properties": {
    "iso:country": "GB",
    "wof:name": "NE32 4NT",
    "wof:placetype": "postalcode"
  },
  "geometry": {"coordinates":[-1.480224,54.954278],"type":"Point"}
}
