{
  "type": "Feature",
  "properties": {
    "iso:country":"GB",
    "wof:name":"CT4 6NE",
    "wof:placetype":"postalcode"
},
  "geometry": {"coordinates":[1.10441841218133,51.16510999326824],"type":"Point"}
}