{
  "type": "Feature",
  "properties": {
    "date:inception_lower": "1980-01-01",
    "date:inception_upper": "1980-01-01",
    "iso:country": "GB",
    "wof:name": "CT4 6NE",
    "wof:placetype": "postalcode"
  },
  "geometry": {"coordinates":[1.104418,51.16511],"type":"Point"}
}
