{
  "type": "Feature",
  "properties": {
    "date:inception_lower": "1981-06-01",
    "date:inception_upper": "1981-06-01",
    "iso:country": "GB",
    "wof:name": "L17 8YD",
    "wof:placetype": "postalcode"
  },
  "geometry": {"coordinates":[-2.947364,53.383353],"type":"Point"}
}
