{
  "type": "Feature",
  "properties": {
    "date:inception_lower": "1997-12-01",
    "date:inception_upper": "1997-12-01",
    "iso:country": "GB",
    "wof:name": "NN12 8JN",
    "wof:placetype": "postalcode"
  },
  "geometry": {"coordinates":[-1.023124,52.182562],"type":"Point"}
}
