{
  "type": "Feature",
  "properties": {
    "iso:country":"GB",
    "wof:name":"DY4 0PA",
    "wof:placetype":"postalcode"
},
  "geometry": {"coordinates":[-2.05332840014562,52.53836657574506],"type":"Point"}
}