{
  "type": "Feature",
  "properties": {
    "date:inception_lower":"2012-10-01",
    "date:inception_upper":"2012-10-31",
    "iso:country":"GB",
    "wof:name":"UB7 9FR",
    "wof:placetype":"postalcode"
},
  "geometry": {"coordinates":[-0.462985,51.506138],"type":"Point"}
}