{
  "type": "Feature",
  "properties": {
    "iso:country":"GB",
    "wof:name":"UB7 9FR",
    "wof:placetype":"postalcode"
},
  "geometry": {"coordinates":[-0.46298483744399,51.50613769973992],"type":"Point"}
}