{
  "type": "Feature",
  "properties": {
    "date:inception_lower":"1990-02-01",
    "date:inception_upper":"1990-02-28",
    "iso:country":"GB",
    "wof:name":"TN17 3DQ",
    "wof:placetype":"postalcode"
},
  "geometry": {"coordinates":[0.532104,51.094787],"type":"Point"}
}