{
  "type": "Feature",
  "properties": {
    "iso:country": "GB",
    "wof:name": "TN17 3DQ",
    "wof:placetype": "postalcode"
  },
  "geometry": {"coordinates":[0.532104,51.094787],"type":"Point"}
}
