{
  "type": "Feature",
  "properties": {
    "date:inception_lower": "2023-11-01",
    "date:inception_upper": "2023-11-01",
    "iso:country": "GB",
    "wof:name": "NR13 6FU",
    "wof:placetype": "postalcode"
  },
  "geometry": {"coordinates":[1.371135,52.664612],"type":"Point"}
}
