{
  "type": "Feature",
  "properties": {
    "iso:country":"GB",
    "wof:name":"BH1 4SS",
    "wof:placetype":"postalcode"
},
  "geometry": {"coordinates":[-1.85755775786634,50.72824353865676],"type":"Point"}
}