{
  "type": "Feature",
  "properties": {
    "iso:country": "GB",
    "wof:name": "LL13 7EF",
    "wof:placetype": "postalcode"
  },
  "geometry": {"coordinates":[-2.993968,53.038507],"type":"Point"}
}
