{
  "type": "Feature",
  "properties": {
    "iso:country": "GB",
    "wof:name": "TQ14 9EY",
    "wof:placetype": "postalcode"
  },
  "geometry": {"coordinates":[-3.511022,50.556903],"type":"Point"}
}
