{
  "type": "Feature",
  "properties": {
    "date:inception_lower": "2023-12-01",
    "date:inception_upper": "2023-12-01",
    "iso:country": "GB",
    "wof:name": "DA12 2FZ",
    "wof:placetype": "postalcode"
  },
  "geometry": {"coordinates":[0.400128,51.43143],"type":"Point"}
}
