{
  "type": "Feature",
  "properties": {
    "iso:country":"GB",
    "wof:name":"AB51 5AS",
    "wof:placetype":"postalcode"
},
  "geometry": {"coordinates":[-2.43878106874446,57.35684004713357],"type":"Point"}
}