{
  "type": "Feature",
  "properties": {
    "iso:country":"GB",
    "wof:name":"RM6 6BE",
    "wof:placetype":"postalcode"
},
  "geometry": {"coordinates":[0.14738940234701,51.5754709423538],"type":"Point"}
}