{
  "type": "Feature",
  "properties": {
    "iso:country":"GB",
    "wof:name":"CT17 0SY",
    "wof:placetype":"postalcode"
},
  "geometry": {"coordinates":[1.30359893977938,51.13159356772272],"type":"Point"}
}