{
  "type": "Feature",
  "properties": {
    "iso:country":"GB",
    "wof:name":"S35 3GW",
    "wof:placetype":"postalcode"
},
  "geometry": {"coordinates":[-1.47929501968295,53.46921438590002],"type":"Point"}
}