{
  "type": "Feature",
  "properties": {
    "iso:country":"GB",
    "wof:name":"TA21 8RF",
    "wof:placetype":"postalcode"
},
  "geometry": {"coordinates":[-3.22429207999399,50.98040909220482],"type":"Point"}
}