{
  "type": "Feature",
  "properties": {
    "iso:country":"GB",
    "wof:name":"YO62 6BL",
    "wof:placetype":"postalcode"
},
  "geometry": {"coordinates":[-0.93223510541082,54.27318013889125],"type":"Point"}
}