{
  "type": "Feature",
  "properties": {
    "date:inception_lower": "2024-01-01",
    "date:inception_upper": "2024-01-01",
    "iso:country": "GB",
    "wof:name": "WS13 8ZU",
    "wof:placetype": "postalcode"
  },
  "geometry": {"coordinates":[-1.770808,52.721736],"type":"Point"}
}
