{
  "type": "Feature",
  "properties": {
    "iso:country":"GB",
    "wof:name":"BL5 1AJ",
    "wof:placetype":"postalcode"
},
  "geometry": {"coordinates":[-2.46258807716951,53.54980830433377],"type":"Point"}
}