{
  "type": "Feature",
  "properties": {
    "iso:country":"GB",
    "wof:name":"KA11 1QS",
    "wof:placetype":"postalcode"
},
  "geometry": {"coordinates":[-4.62834689674988,55.63058154184631],"type":"Point"}
}