{
  "type": "Feature",
  "properties": {
    "iso:country": "GB",
    "wof:name": "PL9 0BU",
    "wof:placetype": "postalcode"
  },
  "geometry": {"coordinates":[-4.111738,50.320331],"type":"Point"}
}
