{
  "type": "Feature",
  "properties": {
    "iso:country":"GB",
    "wof:name":"E16 3PJ",
    "wof:placetype":"postalcode"
},
  "geometry": {"coordinates":[0.02473216794921,51.51151055893727],"type":"Point"}
}