{
  "type": "Feature",
  "properties": {
    "iso:country":"GB",
    "wof:name":"SY10 8LE",
    "wof:placetype":"postalcode"
},
  "geometry": {"coordinates":[-3.07829479431284,52.79373731910027],"type":"Point"}
}