{
  "type": "Feature",
  "properties": {
    "iso:country":"GB",
    "wof:name":"NG23 6RG",
    "wof:placetype":"postalcode"
},
  "geometry": {"coordinates":[-0.81399427038416,53.20654623133016],"type":"Point"}
}