{
  "type": "Feature",
  "properties": {
    "iso:country":"GB",
    "wof:name":"G45 9EL",
    "wof:placetype":"postalcode"
},
  "geometry": {"coordinates":[-4.23669709243369,55.8086570575196],"type":"Point"}
}