{
  "type": "Feature",
  "properties": {
    "iso:country": "GB",
    "wof:name": "MK42 8JX",
    "wof:placetype": "postalcode"
  },
  "geometry": {"coordinates":[-0.49646,52.114618],"type":"Point"}
}
