{
  "type": "Feature",
  "properties": {
    "iso:country": "GB",
    "wof:name": "NE66 3LF",
    "wof:placetype": "postalcode"
  },
  "geometry": {"coordinates":[-1.593741,55.45325],"type":"Point"}
}
