{
  "type": "Feature",
  "properties": {
    "iso:country":"GB",
    "wof:name":"CM12 9JZ",
    "wof:placetype":"postalcode"
},
  "geometry": {"coordinates":[0.41491086570962,51.62252847615063],"type":"Point"}
}