{
  "type": "Feature",
  "properties": {
    "iso:country":"GB",
    "wof:name":"LN9 5JF",
    "wof:placetype":"postalcode"
},
  "geometry": {"coordinates":[-0.12036958472875,53.20914001785759],"type":"Point"}
}