{
  "type": "Feature",
  "properties": {
    "iso:country": "GB",
    "wof:name": "WV11 2JX",
    "wof:placetype": "postalcode"
  },
  "geometry": {"coordinates":[-2.060783,52.619343],"type":"Point"}
}
