{
  "type": "Feature",
  "properties": {
    "iso:country":"GB",
    "wof:name":"BS2 0BT",
    "wof:placetype":"postalcode"
},
  "geometry": {"coordinates":[-2.58299212941245,51.45651601270202],"type":"Point"}
}