{
  "type": "Feature",
  "properties": {
    "iso:country":"GB",
    "wof:name":"M7 4NW",
    "wof:placetype":"postalcode"
},
  "geometry": {"coordinates":[-2.26814330327406,53.51595023494152],"type":"Point"}
}