{
  "type": "Feature",
  "properties": {
    "iso:country":"GB",
    "wof:name":"CO3 8LY",
    "wof:placetype":"postalcode"
},
  "geometry": {"coordinates":[0.81009429611947,51.88302567037597],"type":"Point"}
}