{
  "type": "Feature",
  "properties": {
    "iso:country": "GB",
    "wof:name": "CO3 8LY",
    "wof:placetype": "postalcode"
  },
  "geometry": {"coordinates":[0.810122,51.883037],"type":"Point"}
}
