{
  "type": "Feature",
  "properties": {
    "iso:country": "GB",
    "wof:name": "OX1 1AE",
    "wof:placetype": "postalcode"
  },
  "geometry": {"coordinates":[-1.272707,51.758644],"type":"Point"}
}
