{
  "type": "Feature",
  "properties": {
    "iso:country":"GB",
    "wof:name":"OX1 1AE",
    "wof:placetype":"postalcode"
},
  "geometry": {"coordinates":[-1.27270736260608,51.75864409524892],"type":"Point"}
}