{
  "type": "Feature",
  "properties": {
    "date:inception_lower":"2004-10-01",
    "date:inception_upper":"2004-10-31",
    "iso:country":"GB",
    "wof:name":"OX1 1AE",
    "wof:placetype":"postalcode"
},
  "geometry": {"coordinates":[-1.272707,51.758644],"type":"Point"}
}