{
  "type": "Feature",
  "properties": {
    "iso:country":"GB",
    "wof:name":"G83 7DT",
    "wof:placetype":"postalcode"
},
  "geometry": {"coordinates":[-4.71515858373313,56.29627453492064],"type":"Point"}
}