{
  "type": "Feature",
  "properties": {
    "date:inception_lower": "1985-10-01",
    "date:inception_upper": "1985-10-01",
    "iso:country": "GB",
    "wof:name": "BN7 1HH",
    "wof:placetype": "postalcode"
  },
  "geometry": {"coordinates":[0.008881,50.86953],"type":"Point"}
}
