{
  "type": "Feature",
  "properties": {
    "iso:country":"GB",
    "wof:name":"ST13 8RZ",
    "wof:placetype":"postalcode"
},
  "geometry": {"coordinates":[-2.0429610186357,53.10402218785509],"type":"Point"}
}