{
  "type": "Feature",
  "properties": {
    "iso:country":"GB",
    "wof:name":"IP21 4DR",
    "wof:placetype":"postalcode"
},
  "geometry": {"coordinates":[1.15526413541933,52.36587393711023],"type":"Point"}
}