{
  "type": "Feature",
  "properties": {
    "iso:country": "GB",
    "wof:name": "IP21 4DR",
    "wof:placetype": "postalcode"
  },
  "geometry": {"coordinates":[1.155264,52.365874],"type":"Point"}
}
