{
  "type": "Feature",
  "properties": {
    "iso:country":"GB",
    "wof:name":"CH65 9EW",
    "wof:placetype":"postalcode"
},
  "geometry": {"coordinates":[-2.88723810467227,53.26746207216452],"type":"Point"}
}