{
  "type": "Feature",
  "properties": {
    "iso:country":"GB",
    "wof:name":"LD7 1EA",
    "wof:placetype":"postalcode"
},
  "geometry": {"coordinates":[-3.04639548194402,52.34699376842357],"type":"Point"}
}