{
  "type": "Feature",
  "properties": {
    "iso:country": "GB",
    "wof:name": "LD7 1EA",
    "wof:placetype": "postalcode"
  },
  "geometry": {"coordinates":[-3.046395,52.346994],"type":"Point"}
}
