{
  "type": "Feature",
  "properties": {
    "date:inception_lower":"1993-08-01",
    "date:inception_upper":"1993-08-31",
    "iso:country":"GB",
    "wof:name":"LD7 1EA",
    "wof:placetype":"postalcode"
},
  "geometry": {"coordinates":[-3.046395,52.346994],"type":"Point"}
}