{
  "type": "Feature",
  "properties": {
    "date:inception_lower": "2023-09-01",
    "date:inception_upper": "2023-09-01",
    "iso:country": "GB",
    "wof:name": "CH65 1BE",
    "wof:placetype": "postalcode"
  },
  "geometry": {"coordinates":[-2.907563,53.291946],"type":"Point"}
}
