{
  "type": "Feature",
  "properties": {
    "iso:country":"GB",
    "wof:name":"CA13 0QU",
    "wof:placetype":"postalcode"
},
  "geometry": {"coordinates":[-3.384186207997,54.65333230883792],"type":"Point"}
}