{
  "type": "Feature",
  "properties": {
    "iso:country":"GB",
    "wof:name":"LS26 8FL",
    "wof:placetype":"postalcode"
},
  "geometry": {"coordinates":[-1.38987046132754,53.75258184731403],"type":"Point"}
}