{
  "type": "Feature",
  "properties": {
    "iso:country":"GB",
    "wof:name":"B93 8SZ",
    "wof:placetype":"postalcode"
},
  "geometry": {"coordinates":[-1.76835655405602,52.37405787834034],"type":"Point"}
}