{
  "type": "Feature",
  "properties": {
    "iso:country":"GB",
    "wof:name":"M25 3BD",
    "wof:placetype":"postalcode"
},
  "geometry": {"coordinates":[-2.28729900305008,53.53644418920001],"type":"Point"}
}