{
  "type": "Feature",
  "properties": {
    "iso:country":"GB",
    "wof:name":"WV14 8JH",
    "wof:placetype":"postalcode"
},
  "geometry": {"coordinates":[-2.07927836222106,52.53902622409605],"type":"Point"}
}