{
  "type": "Feature",
  "properties": {
    "iso:country":"GB",
    "wof:name":"GL9 1BH",
    "wof:placetype":"postalcode"
},
  "geometry": {"coordinates":[-2.3205251948163,51.57902052711033],"type":"Point"}
}