{
  "type": "Feature",
  "properties": {
    "iso:country":"GB",
    "wof:name":"SW9 7AR",
    "wof:placetype":"postalcode"
},
  "geometry": {"coordinates":[-0.1071662367793,51.47597163136368],"type":"Point"}
}