{
  "type": "Feature",
  "properties": {
    "iso:country":"GB",
    "wof:name":"SE21 8HN",
    "wof:placetype":"postalcode"
},
  "geometry": {"coordinates":[-0.09067267559672,51.44091168357395],"type":"Point"}
}