{
  "type": "Feature",
  "properties": {
    "iso:country": "GB",
    "wof:name": "SW9 7JB",
    "wof:placetype": "postalcode"
  },
  "geometry": {"coordinates":[-0.108941,51.464733],"type":"Point"}
}
