{
  "type": "Feature",
  "properties": {
    "iso:country":"GB",
    "wof:name":"SW9 7JB",
    "wof:placetype":"postalcode"
},
  "geometry": {"coordinates":[-0.10894146091645,51.46473254573695],"type":"Point"}
}