{
  "type": "Feature",
  "properties": {
    "iso:country":"GB",
    "wof:name":"SA18 1BT",
    "wof:placetype":"postalcode"
},
  "geometry": {"coordinates":[-3.86726381649638,51.81222792416327],"type":"Point"}
}