{
  "type": "Feature",
  "properties": {
    "iso:country": "GB",
    "wof:name": "SA18 1BT",
    "wof:placetype": "postalcode"
  },
  "geometry": {"coordinates":[-3.867266,51.812282],"type":"Point"}
}
