{
  "type": "Feature",
  "properties": {
    "iso:country":"GB",
    "wof:name":"OX2 9BT",
    "wof:placetype":"postalcode"
},
  "geometry": {"coordinates":[-1.31636491680027,51.74689373478919],"type":"Point"}
}