{
  "type": "Feature",
  "properties": {
    "date:inception_lower":"1985-10-01",
    "date:inception_upper":"1985-10-31",
    "iso:country":"GB",
    "wof:name":"OX2 9BT",
    "wof:placetype":"postalcode"
},
  "geometry": {"coordinates":[-1.316365,51.746894],"type":"Point"}
}