{
  "type": "Feature",
  "properties": {
    "iso:country": "GB",
    "wof:name": "NN12 8RB",
    "wof:placetype": "postalcode"
  },
  "geometry": {"coordinates":[-1.086499,52.148995],"type":"Point"}
}
