{
  "type": "Feature",
  "properties": {
    "iso:country": "GB",
    "wof:name": "DN21 5UP",
    "wof:placetype": "postalcode"
  },
  "geometry": {"coordinates":[-0.627887,53.403404],"type":"Point"}
}
