{
  "type": "Feature",
  "properties": {
    "iso:country":"GB",
    "wof:name":"DN21 5UP",
    "wof:placetype":"postalcode"
},
  "geometry": {"coordinates":[-0.62788753908574,53.40340416031052],"type":"Point"}
}