{
  "type": "Feature",
  "properties": {
    "iso:country":"GB",
    "wof:name":"KY16 8QD",
    "wof:placetype":"postalcode"
},
  "geometry": {"coordinates":[-2.65150073952508,56.29299298297692],"type":"Point"}
}