{
  "type": "Feature",
  "properties": {
    "iso:country": "GB",
    "wof:name": "RG7 1DJ",
    "wof:placetype": "postalcode"
  },
  "geometry": {"coordinates":[-0.961038,51.396961],"type":"Point"}
}
