{
  "type": "Feature",
  "properties": {
    "date:inception_lower": "2019-05-01",
    "date:inception_upper": "2019-05-01",
    "iso:country": "GB",
    "wof:name": "RG7 1DJ",
    "wof:placetype": "postalcode"
  },
  "geometry": {"coordinates":[-0.960475,51.397073],"type":"Point"}
}
