{
  "type": "Feature",
  "properties": {
    "iso:country": "GB",
    "wof:name": "DH1 1LR",
    "wof:placetype": "postalcode"
  },
  "geometry": {"coordinates":[-1.520171,54.791059],"type":"Point"}
}
