{
  "type": "Feature",
  "properties": {
    "iso:country":"GB",
    "wof:name":"DH1 1LR",
    "wof:placetype":"postalcode"
},
  "geometry": {"coordinates":[-1.52017136800433,54.79105919901001],"type":"Point"}
}