{
  "type": "Feature",
  "properties": {
    "iso:country":"GB",
    "wof:name":"WR2 6PP",
    "wof:placetype":"postalcode"
},
  "geometry": {"coordinates":[-2.25541511359796,52.22224325305628],"type":"Point"}
}