{
  "type": "Feature",
  "properties": {
    "iso:country":"GB",
    "wof:name":"S18 4BG",
    "wof:placetype":"postalcode"
},
  "geometry": {"coordinates":[-1.43111822211285,53.29775994307842],"type":"Point"}
}