{
  "type": "Feature",
  "properties": {
    "date:inception_lower":"1981-06-01",
    "date:inception_upper":"1981-06-30",
    "iso:country":"GB",
    "wof:name":"PE37 7RX",
    "wof:placetype":"postalcode"
},
  "geometry": {"coordinates":[0.683768,52.637142],"type":"Point"}
}