{
  "type": "Feature",
  "properties": {
    "iso:country": "GB",
    "wof:name": "NE11 9XH",
    "wof:placetype": "postalcode"
  },
  "geometry": {"coordinates":[-1.64372,54.94597],"type":"Point"}
}
