{
  "type": "Feature",
  "properties": {
    "date:inception_lower":"1980-01-01",
    "date:inception_upper":"1980-01-31",
    "iso:country":"GB",
    "wof:name":"NE11 9XH",
    "wof:placetype":"postalcode"
},
  "geometry": {"coordinates":[-1.64372,54.94597],"type":"Point"}
}