{
  "type": "Feature",
  "properties": {
    "date:inception_lower": "1980-01-01",
    "date:inception_upper": "1980-01-01",
    "iso:country": "GB",
    "wof:name": "WA12 8SP",
    "wof:placetype": "postalcode"
  },
  "geometry": {"coordinates":[-2.629294,53.44113],"type":"Point"}
}
