{
  "type": "Feature",
  "properties": {
    "iso:country":"GB",
    "wof:name":"WA12 8SP",
    "wof:placetype":"postalcode"
},
  "geometry": {"coordinates":[-2.62929359079585,53.44113020999455],"type":"Point"}
}