{
  "type": "Feature",
  "properties": {
    "iso:country": "GB",
    "wof:name": "WA12 8SP",
    "wof:placetype": "postalcode"
  },
  "geometry": {"coordinates":[-2.629294,53.44113],"type":"Point"}
}
