{
  "type": "Feature",
  "properties": {
    "date:inception_lower": "2008-09-01",
    "date:inception_upper": "2008-09-01",
    "iso:country": "GB",
    "wof:name": "TS17 6DN",
    "wof:placetype": "postalcode"
  },
  "geometry": {"coordinates":[-1.305841,54.553408],"type":"Point"}
}
