{
  "type": "Feature",
  "properties": {
    "date:inception_lower":"1980-01-01",
    "date:inception_upper":"1980-01-31",
    "iso:country":"GB",
    "wof:name":"ME12 1UJ",
    "wof:placetype":"postalcode"
},
  "geometry": {"coordinates":[0.764894,51.437015],"type":"Point"}
}