{
  "type": "Feature",
  "properties": {
    "iso:country":"GB",
    "wof:name":"SW4 6BQ",
    "wof:placetype":"postalcode"
},
  "geometry": {"coordinates":[-0.13647137335831,51.46465179118353],"type":"Point"}
}