{
  "type": "Feature",
  "properties": {
    "iso:country":"GB",
    "wof:name":"B61 7BU",
    "wof:placetype":"postalcode"
},
  "geometry": {"coordinates":[-2.07514462370878,52.32901283391005],"type":"Point"}
}