{
  "type": "Feature",
  "properties": {
    "iso:country":"GB",
    "wof:name":"RG8 9PX",
    "wof:placetype":"postalcode"
},
  "geometry": {"coordinates":[-1.14875453082326,51.53337609674506],"type":"Point"}
}