{
  "type": "Feature",
  "properties": {
    "iso:country": "GB",
    "wof:name": "EX22 7TL",
    "wof:placetype": "postalcode"
  },
  "geometry": {"coordinates":[-4.387228,50.903126],"type":"Point"}
}
