{
  "type": "Feature",
  "properties": {
    "iso:country":"GB",
    "wof:name":"PE8 5LY",
    "wof:placetype":"postalcode"
},
  "geometry": {"coordinates":[-0.39823542663507,52.47214248606976],"type":"Point"}
}