{
  "type": "Feature",
  "properties": {
    "iso:country": "GB",
    "wof:name": "YO11 3PE",
    "wof:placetype": "postalcode"
  },
  "geometry": {"coordinates":[-0.345107,54.225772],"type":"Point"}
}
