{
  "type": "Feature",
  "properties": {
    "iso:country":"GB",
    "wof:name":"YO11 3PE",
    "wof:placetype":"postalcode"
},
  "geometry": {"coordinates":[-0.34329974070903,54.22488351861477],"type":"Point"}
}