{
  "type": "Feature",
  "properties": {
    "iso:country": "GB",
    "wof:name": "G43 2ST",
    "wof:placetype": "postalcode"
  },
  "geometry": {"coordinates":[-4.278482,55.813313],"type":"Point"}
}
