{
  "type": "Feature",
  "properties": {
    "iso:country":"GB",
    "wof:name":"PO18 8DG",
    "wof:placetype":"postalcode"
},
  "geometry": {"coordinates":[-0.86219298003302,50.85716235775225],"type":"Point"}
}