{
  "type": "Feature",
  "properties": {
    "iso:country": "GB",
    "wof:name": "PO18 8DG",
    "wof:placetype": "postalcode"
  },
  "geometry": {"coordinates":[-0.862146,50.857171],"type":"Point"}
}
