{
  "type": "Feature",
  "properties": {
    "iso:country": "GB",
    "wof:name": "CW10 9QA",
    "wof:placetype": "postalcode"
  },
  "geometry": {"coordinates":[-2.452393,53.197536],"type":"Point"}
}
