{
  "type": "Feature",
  "properties": {
    "iso:country":"GB",
    "wof:name":"TN29 9SD",
    "wof:placetype":"postalcode"
},
  "geometry": {"coordinates":[0.82907930205113,50.99833486792324],"type":"Point"}
}