{
  "type": "Feature",
  "properties": {
    "date:inception_lower":"2013-07-01",
    "date:inception_upper":"2013-07-31",
    "iso:country":"GB",
    "wof:name":"EN8 0FF",
    "wof:placetype":"postalcode"
},
  "geometry": {"coordinates":[-0.041423,51.710694],"type":"Point"}
}