{
  "type": "Feature",
  "properties": {
    "iso:country":"GB",
    "wof:name":"TR7 2HY",
    "wof:placetype":"postalcode"
},
  "geometry": {"coordinates":[-5.07735063564405,50.40695250251735],"type":"Point"}
}