{
  "type": "Feature",
  "properties": {
    "iso:country":"GB",
    "wof:name":"WA3 2LS",
    "wof:placetype":"postalcode"
},
  "geometry": {"coordinates":[-2.56797912465573,53.47516281048996],"type":"Point"}
}