{
  "type": "Feature",
  "properties": {
    "date:inception_lower":"1980-01-01",
    "date:inception_upper":"1980-01-31",
    "iso:country":"GB",
    "wof:name":"BD23 2ES",
    "wof:placetype":"postalcode"
},
  "geometry": {"coordinates":[-2.012221,53.959295],"type":"Point"}
}