{
  "type": "Feature",
  "properties": {
    "date:inception_lower": "1980-01-01",
    "date:inception_upper": "1980-01-01",
    "iso:country": "GB",
    "wof:name": "BA14 9JX",
    "wof:placetype": "postalcode"
  },
  "geometry": {"coordinates":[-2.224892,51.313174],"type":"Point"}
}
