{
  "type": "Feature",
  "properties": {
    "iso:country":"GB",
    "wof:name":"M24 1FF",
    "wof:placetype":"postalcode"
},
  "geometry": {"coordinates":[-2.18653635294795,53.54231568585099],"type":"Point"}
}