{
  "type": "Feature",
  "properties": {
    "date:inception_lower": "1997-06-01",
    "date:inception_upper": "1997-06-01",
    "iso:country": "GB",
    "wof:name": "S35 0HG",
    "wof:placetype": "postalcode"
  },
  "geometry": {"coordinates":[-1.543978,53.433083],"type":"Point"}
}
