{
  "type": "Feature",
  "properties": {
    "iso:country":"GB",
    "wof:name":"S35 0HG",
    "wof:placetype":"postalcode"
},
  "geometry": {"coordinates":[-1.54379675106087,53.43302028623744],"type":"Point"}
}