{
  "type": "Feature",
  "properties": {
    "iso:country":"GB",
    "wof:name":"G33 1SD",
    "wof:placetype":"postalcode"
},
  "geometry": {"coordinates":[-4.19510123692264,55.8969255142719],"type":"Point"}
}