{
  "type": "Feature",
  "properties": {
    "iso:country": "GB",
    "wof:name": "G33 1SD",
    "wof:placetype": "postalcode"
  },
  "geometry": {"coordinates":[-4.195101,55.896926],"type":"Point"}
}
