{
  "type": "Feature",
  "properties": {
    "iso:country":"GB",
    "wof:name":"B13 0NT",
    "wof:placetype":"postalcode"
},
  "geometry": {"coordinates":[-1.87141132613997,52.42044172989334],"type":"Point"}
}