{
  "type": "Feature",
  "properties": {
    "iso:country":"GB",
    "wof:name":"IP22 2RF",
    "wof:placetype":"postalcode"
},
  "geometry": {"coordinates":[0.91552190079033,52.37488694254197],"type":"Point"}
}