{
  "type": "Feature",
  "properties": {
    "iso:country": "GB",
    "wof:name": "SY11 2LL",
    "wof:placetype": "postalcode"
  },
  "geometry": {"coordinates":[-3.033795,52.861521],"type":"Point"}
}
