{
  "type": "Feature",
  "properties": {
    "date:inception_lower":"2009-08-01",
    "date:inception_upper":"2009-08-31",
    "iso:country":"GB",
    "wof:name":"HP21 9BZ",
    "wof:placetype":"postalcode"
},
  "geometry": {"coordinates":[-0.805365,51.800301],"type":"Point"}
}