{
  "type": "Feature",
  "properties": {
    "iso:country": "GB",
    "wof:name": "HP21 9BZ",
    "wof:placetype": "postalcode"
  },
  "geometry": {"coordinates":[-0.805365,51.800301],"type":"Point"}
}
