{
  "type": "Feature",
  "properties": {
    "date:inception_lower": "1980-01-01",
    "date:inception_upper": "1980-01-01",
    "iso:country": "GB",
    "wof:name": "NW11 9RG",
    "wof:placetype": "postalcode"
  },
  "geometry": {"coordinates":[-0.20567,51.57445],"type":"Point"}
}
