{
  "type": "Feature",
  "properties": {
    "iso:country":"GB",
    "wof:name":"LS14 1HL",
    "wof:placetype":"postalcode"
},
  "geometry": {"coordinates":[-1.46681919738647,53.82696551667792],"type":"Point"}
}