{
  "type": "Feature",
  "properties": {
    "date:inception_lower": "1999-12-01",
    "date:inception_upper": "1999-12-01",
    "iso:country": "GB",
    "wof:name": "CV47 1HU",
    "wof:placetype": "postalcode"
  },
  "geometry": {"coordinates":[-1.393746,52.249338],"type":"Point"}
}
