{
  "type": "Feature",
  "properties": {
    "iso:country":"GB",
    "wof:name":"CV47 1HU",
    "wof:placetype":"postalcode"
},
  "geometry": {"coordinates":[-1.39374597413159,52.24933844270382],"type":"Point"}
}