{
  "type": "Feature",
  "properties": {
    "date:inception_lower": "1980-01-01",
    "date:inception_upper": "1980-01-01",
    "iso:country": "GB",
    "wof:name": "CH4 8BU",
    "wof:placetype": "postalcode"
  },
  "geometry": {"coordinates":[-2.916952,53.178907],"type":"Point"}
}
