{
  "type": "Feature",
  "properties": {
    "iso:country":"GB",
    "wof:name":"CH4 8BU",
    "wof:placetype":"postalcode"
},
  "geometry": {"coordinates":[-2.91695045350999,53.17889184686157],"type":"Point"}
}