{
  "type": "Feature",
  "properties": {
    "iso:country":"GB",
    "wof:name":"SY5 7EY",
    "wof:placetype":"postalcode"
},
  "geometry": {"coordinates":[-2.725766919017,52.61201889662156],"type":"Point"}
}