{
  "type": "Feature",
  "properties": {
    "iso:country":"GB",
    "wof:name":"CV3 5JL",
    "wof:placetype":"postalcode"
},
  "geometry": {"coordinates":[-1.49950686848102,52.38821248208993],"type":"Point"}
}