{
  "type": "Feature",
  "properties": {
    "date:inception_lower": "1980-01-01",
    "date:inception_upper": "1980-01-01",
    "iso:country": "GB",
    "wof:name": "DN34 4TX",
    "wof:placetype": "postalcode"
  },
  "geometry": {"coordinates":[-0.099909,53.55974],"type":"Point"}
}
