{
  "type": "Feature",
  "properties": {
    "iso:country":"GB",
    "wof:name":"DN34 4TX",
    "wof:placetype":"postalcode"
},
  "geometry": {"coordinates":[-0.09990879188507,53.55974026302301],"type":"Point"}
}