{
  "type": "Feature",
  "properties": {
    "iso:country": "GB",
    "wof:name": "GU10 1EE",
    "wof:placetype": "postalcode"
  },
  "geometry": {"coordinates":[-0.725873,51.236115],"type":"Point"}
}
