{
  "type": "Feature",
  "properties": {
    "iso:country": "GB",
    "wof:name": "CB23 6HF",
    "wof:placetype": "postalcode"
  },
  "geometry": {"coordinates":[-0.070761,52.220232],"type":"Point"}
}
