{
  "type": "Feature",
  "properties": {
    "date:inception_lower": "1991-09-01",
    "date:inception_upper": "1991-09-01",
    "iso:country": "GB",
    "wof:name": "NG34 7TX",
    "wof:placetype": "postalcode"
  },
  "geometry": {"coordinates":[-0.413305,52.997696],"type":"Point"}
}
