{
  "type": "Feature",
  "properties": {
    "iso:country":"GB",
    "wof:name":"DH1 1UR",
    "wof:placetype":"postalcode"
},
  "geometry": {"coordinates":[-1.56415881368381,54.78025246939685],"type":"Point"}
}