{
  "type": "Feature",
  "properties": {
    "date:inception_lower": "1988-03-01",
    "date:inception_upper": "1988-03-01",
    "iso:country": "GB",
    "wof:name": "DH1 1UR",
    "wof:placetype": "postalcode"
  },
  "geometry": {"coordinates":[-1.564159,54.780252],"type":"Point"}
}
