{
  "type": "Feature",
  "properties": {
    "iso:country":"GB",
    "wof:name":"BS22 7XJ",
    "wof:placetype":"postalcode"
},
  "geometry": {"coordinates":[-2.90032487571186,51.36073201890819],"type":"Point"}
}