{
  "type": "Feature",
  "properties": {
    "iso:country":"GB",
    "wof:name":"IP1 1BB",
    "wof:placetype":"postalcode"
},
  "geometry": {"coordinates":[1.15322536322667,52.05726263073953],"type":"Point"}
}