{
  "type": "Feature",
  "properties": {
    "iso:country": "GB",
    "wof:name": "NG23 7NJ",
    "wof:placetype": "postalcode"
  },
  "geometry": {"coordinates":[-0.758651,53.151201],"type":"Point"}
}
