{
  "type": "Feature",
  "properties": {
    "iso:country":"GB",
    "wof:name":"L33 1UN",
    "wof:placetype":"postalcode"
},
  "geometry": {"coordinates":[-2.88867424116925,53.4953918050242],"type":"Point"}
}