{
  "type": "Feature",
  "properties": {
    "date:inception_lower":"1993-01-01",
    "date:inception_upper":"1993-01-31",
    "iso:country":"GB",
    "wof:name":"L33 1UN",
    "wof:placetype":"postalcode"
},
  "geometry": {"coordinates":[-2.888674,53.495392],"type":"Point"}
}