{
  "type": "Feature",
  "properties": {
    "iso:country":"GB",
    "wof:name":"TA7 8PT",
    "wof:placetype":"postalcode"
},
  "geometry": {"coordinates":[-2.94597883724601,51.15385054090596],"type":"Point"}
}