{
  "type": "Feature",
  "properties": {
    "date:inception_lower":"1980-01-01",
    "date:inception_upper":"1980-01-31",
    "iso:country":"GB",
    "wof:name":"TA7 8PT",
    "wof:placetype":"postalcode"
},
  "geometry": {"coordinates":[-2.946116,51.153889],"type":"Point"}
}