{
  "type": "Feature",
  "properties": {
    "iso:country": "GB",
    "wof:name": "TA7 8PT",
    "wof:placetype": "postalcode"
  },
  "geometry": {"coordinates":[-2.946116,51.153889],"type":"Point"}
}
