{
  "type": "Feature",
  "properties": {
    "iso:country":"GB",
    "wof:name":"GU10 4RR",
    "wof:placetype":"postalcode"
},
  "geometry": {"coordinates":[-0.80321402966079,51.19453262586579],"type":"Point"}
}