{
  "type": "Feature",
  "properties": {
    "iso:country": "GB",
    "wof:name": "GU10 4RR",
    "wof:placetype": "postalcode"
  },
  "geometry": {"coordinates":[-0.802995,51.194024],"type":"Point"}
}
