{
  "type": "Feature",
  "properties": {
    "iso:country": "GB",
    "wof:name": "SA62 6QJ",
    "wof:placetype": "postalcode"
  },
  "geometry": {"coordinates":[-5.245401,51.882206],"type":"Point"}
}
