{
  "type": "Feature",
  "properties": {
    "iso:country":"GB",
    "wof:name":"SA62 6QJ",
    "wof:placetype":"postalcode"
},
  "geometry": {"coordinates":[-5.24541167604462,51.88220715430568],"type":"Point"}
}