{
  "type": "Feature",
  "properties": {
    "date:inception_lower": "1984-02-01",
    "date:inception_upper": "1984-02-01",
    "iso:country": "GB",
    "wof:name": "ST5 4JA",
    "wof:placetype": "postalcode"
  },
  "geometry": {"coordinates":[-2.229333,52.982716],"type":"Point"}
}
