{
  "type": "Feature",
  "properties": {
    "iso:country":"GB",
    "wof:name":"ST5 4JA",
    "wof:placetype":"postalcode"
},
  "geometry": {"coordinates":[-2.22933328456672,52.98271621441732],"type":"Point"}
}