{
  "type": "Feature",
  "properties": {
    "iso:country": "GB",
    "wof:name": "BA22 9FB",
    "wof:placetype": "postalcode"
  },
  "geometry": {"coordinates":[-2.687039,50.919925],"type":"Point"}
}
