{
  "type": "Feature",
  "properties": {
    "iso:country":"GB",
    "wof:name":"G61 9DQ",
    "wof:placetype":"postalcode"
},
  "geometry": {"coordinates":[-4.32057599969495,55.9195191010056],"type":"Point"}
}