{
  "type": "Feature",
  "properties": {
    "iso:country": "GB",
    "wof:name": "RG12 1FA",
    "wof:placetype": "postalcode"
  },
  "geometry": {"coordinates":[-0.752537,51.41515],"type":"Point"}
}
