{
  "type": "Feature",
  "properties": {
    "date:inception_lower": "2018-10-01",
    "date:inception_upper": "2018-10-01",
    "iso:country": "GB",
    "wof:name": "RG12 1FA",
    "wof:placetype": "postalcode"
  },
  "geometry": {"coordinates":[-0.752537,51.41515],"type":"Point"}
}
