{
  "type": "Feature",
  "properties": {
    "iso:country":"GB",
    "wof:name":"CT16 2LU",
    "wof:placetype":"postalcode"
},
  "geometry": {"coordinates":[1.30645867471173,51.13440013511228],"type":"Point"}
}