{
  "type": "Feature",
  "properties": {
    "date:inception_lower": "2005-12-01",
    "date:inception_upper": "2005-12-01",
    "iso:country": "GB",
    "wof:name": "NN14 2GJ",
    "wof:placetype": "postalcode"
  },
  "geometry": {"coordinates":[-0.813484,52.445938],"type":"Point"}
}
