{
  "type": "Feature",
  "properties": {
    "iso:country":"GB",
    "wof:name":"M41 5GS",
    "wof:placetype":"postalcode"
},
  "geometry": {"coordinates":[-2.38420235562526,53.44559502052427],"type":"Point"}
}