{
  "type": "Feature",
  "properties": {
    "iso:country": "GB",
    "wof:name": "AL4 9SX",
    "wof:placetype": "postalcode"
  },
  "geometry": {"coordinates":[-0.304352,51.771549],"type":"Point"}
}
