{
  "type": "Feature",
  "properties": {
    "iso:country":"GB",
    "wof:name":"AL4 9SX",
    "wof:placetype":"postalcode"
},
  "geometry": {"coordinates":[-0.30435170278034,51.77154914048383],"type":"Point"}
}