{
  "type": "Feature",
  "properties": {
    "iso:country": "GB",
    "wof:name": "SO20 8QP",
    "wof:placetype": "postalcode"
  },
  "geometry": {"coordinates":[-1.564136,51.156022],"type":"Point"}
}
