{
  "type": "Feature",
  "properties": {
    "iso:country":"GB",
    "wof:name":"LN11 0RE",
    "wof:placetype":"postalcode"
},
  "geometry": {"coordinates":[-0.12146467762165,53.37528527076481],"type":"Point"}
}