{
  "type": "Feature",
  "properties": {
    "iso:country":"GB",
    "wof:name":"TN14 5AW",
    "wof:placetype":"postalcode"
},
  "geometry": {"coordinates":[0.20163752146975,51.28815404679744],"type":"Point"}
}