{
  "type": "Feature",
  "properties": {
    "iso:country": "GB",
    "wof:name": "TN14 5AW",
    "wof:placetype": "postalcode"
  },
  "geometry": {"coordinates":[0.201638,51.288154],"type":"Point"}
}
