{
  "type": "Feature",
  "properties": {
    "iso:country":"GB",
    "wof:name":"SE17 3AR",
    "wof:placetype":"postalcode"
},
  "geometry": {"coordinates":[-0.09976255928706,51.48952961472975],"type":"Point"}
}