{
  "type": "Feature",
  "properties": {
    "date:inception_lower":"1980-01-01",
    "date:inception_upper":"1980-01-31",
    "iso:country":"GB",
    "wof:name":"BH19 2SY",
    "wof:placetype":"postalcode"
},
  "geometry": {"coordinates":[-1.980741,50.609534],"type":"Point"}
}