{
  "type": "Feature",
  "properties": {
    "iso:country":"GB",
    "wof:name":"BH19 2SY",
    "wof:placetype":"postalcode"
},
  "geometry": {"coordinates":[-1.98074127447355,50.60953443129821],"type":"Point"}
}