{
  "type": "Feature",
  "properties": {
    "iso:country":"GB",
    "wof:name":"BS15 4RF",
    "wof:placetype":"postalcode"
},
  "geometry": {"coordinates":[-2.48813321630535,51.47025705090568],"type":"Point"}
}