{
  "type": "Feature",
  "properties": {
    "iso:country":"GB",
    "wof:name":"B61 9HA",
    "wof:placetype":"postalcode"
},
  "geometry": {"coordinates":[-2.12988727484496,52.32705030064979],"type":"Point"}
}