{
  "type": "Feature",
  "properties": {
    "iso:country":"GB",
    "wof:name":"EH10 6SN",
    "wof:placetype":"postalcode"
},
  "geometry": {"coordinates":[-3.21412685641599,55.9033563893343],"type":"Point"}
}