{
  "type": "Feature",
  "properties": {
    "iso:country":"GB",
    "wof:name":"GL20 8AS",
    "wof:placetype":"postalcode"
},
  "geometry": {"coordinates":[-2.14493644246237,52.00191117765056],"type":"Point"}
}