{
  "type": "Feature",
  "properties": {
    "date:inception_lower": "1980-01-01",
    "date:inception_upper": "1980-01-01",
    "iso:country": "GB",
    "wof:name": "EX7 9LS",
    "wof:placetype": "postalcode"
  },
  "geometry": {"coordinates":[-3.471418,50.583512],"type":"Point"}
}
