{
  "type": "Feature",
  "properties": {
    "date:inception_lower": "2007-01-01",
    "date:inception_upper": "2007-01-01",
    "iso:country": "GB",
    "wof:name": "LN1 3UN",
    "wof:placetype": "postalcode"
  },
  "geometry": {"coordinates":[-0.546304,53.246008],"type":"Point"}
}
