{
  "type": "Feature",
  "properties": {
    "iso:country":"GB",
    "wof:name":"SP5 3ES",
    "wof:placetype":"postalcode"
},
  "geometry": {"coordinates":[-1.73104246663178,51.0656229605725],"type":"Point"}
}