{
  "type": "Feature",
  "properties": {
    "iso:country": "GB",
    "wof:name": "BA12 0PW",
    "wof:placetype": "postalcode"
  },
  "geometry": {"coordinates":[-2.046881,51.158828],"type":"Point"}
}
