{
  "type": "Feature",
  "properties": {
    "iso:country":"GB",
    "wof:name":"BH17 8BS",
    "wof:placetype":"postalcode"
},
  "geometry": {"coordinates":[-1.95302959101519,50.75000212148958],"type":"Point"}
}