{
  "type": "Feature",
  "properties": {
    "iso:country": "GB",
    "wof:name": "BH17 8BS",
    "wof:placetype": "postalcode"
  },
  "geometry": {"coordinates":[-1.95303,50.750002],"type":"Point"}
}
