{
  "type": "Feature",
  "properties": {
    "iso:country":"GB",
    "wof:name":"LU1 3HB",
    "wof:placetype":"postalcode"
},
  "geometry": {"coordinates":[-0.40658052716981,51.87343548121587],"type":"Point"}
}