{
  "type": "Feature",
  "properties": {
    "iso:country": "GB",
    "wof:name": "WF4 4JA",
    "wof:placetype": "postalcode"
  },
  "geometry": {"coordinates":[-1.576561,53.648144],"type":"Point"}
}
