{
  "type": "Feature",
  "properties": {
    "iso:country": "GB",
    "wof:name": "SP4 7BE",
    "wof:placetype": "postalcode"
  },
  "geometry": {"coordinates":[-1.788435,51.17004],"type":"Point"}
}
