{
  "type": "Feature",
  "properties": {
    "iso:country":"GB",
    "wof:name":"RG8 8AN",
    "wof:placetype":"postalcode"
},
  "geometry": {"coordinates":[-1.10166473968905,51.47639533836842],"type":"Point"}
}