{
  "type": "Feature",
  "properties": {
    "date:inception_lower": "2014-07-01",
    "date:inception_upper": "2014-07-01",
    "iso:country": "GB",
    "wof:name": "RG8 8AN",
    "wof:placetype": "postalcode"
  },
  "geometry": {"coordinates":[-1.101665,51.476395],"type":"Point"}
}
