{
  "type": "Feature",
  "properties": {
    "date:inception_lower": "2023-12-01",
    "date:inception_upper": "2023-12-01",
    "iso:country": "GB",
    "wof:name": "EH30 9DY",
    "wof:placetype": "postalcode"
  },
  "geometry": {"coordinates":[-3.419059,55.988852],"type":"Point"}
}
