{
  "type": "Feature",
  "properties": {
    "iso:country":"GB",
    "wof:name":"TN13 1QH",
    "wof:placetype":"postalcode"
},
  "geometry": {"coordinates":[0.1908091795978,51.25680892867268],"type":"Point"}
}