{
  "type": "Feature",
  "properties": {
    "date:inception_lower":"1993-08-01",
    "date:inception_upper":"1993-08-31",
    "iso:country":"GB",
    "wof:name":"NW10 3DW",
    "wof:placetype":"postalcode"
},
  "geometry": {"coordinates":[-0.225565,51.542371],"type":"Point"}
}