{
  "type": "Feature",
  "properties": {
    "date:inception_lower": "1981-06-01",
    "date:inception_upper": "1981-06-01",
    "iso:country": "GB",
    "wof:name": "SE5 0NA",
    "wof:placetype": "postalcode"
  },
  "geometry": {"coordinates":[-0.099222,51.477938],"type":"Point"}
}
