{
  "type": "Feature",
  "properties": {
    "iso:country":"GB",
    "wof:name":"EX23 9PJ",
    "wof:placetype":"postalcode"
},
  "geometry": {"coordinates":[-4.49622186867649,50.91476775212505],"type":"Point"}
}