{
  "type": "Feature",
  "properties": {
    "iso:country": "GB",
    "wof:name": "EX23 9PJ",
    "wof:placetype": "postalcode"
  },
  "geometry": {"coordinates":[-4.49882,50.91488],"type":"Point"}
}
