{
  "type": "Feature",
  "properties": {
    "iso:country":"GB",
    "wof:name":"KA21 6EZ",
    "wof:placetype":"postalcode"
},
  "geometry": {"coordinates":[-4.78544713664542,55.6488302296238],"type":"Point"}
}