{
  "type": "Feature",
  "properties": {
    "iso:country": "GB",
    "wof:name": "KA21 6EZ",
    "wof:placetype": "postalcode"
  },
  "geometry": {"coordinates":[-4.785447,55.64883],"type":"Point"}
}
