{
  "type": "Feature",
  "properties": {
    "iso:country":"GB",
    "wof:name":"WF4 4ET",
    "wof:placetype":"postalcode"
},
  "geometry": {"coordinates":[-1.66959774047246,53.64049981732049],"type":"Point"}
}