{
  "type": "Feature",
  "properties": {
    "iso:country": "GB",
    "wof:name": "KA25 6LN",
    "wof:placetype": "postalcode"
  },
  "geometry": {"coordinates":[-4.683241,55.748062],"type":"Point"}
}
