{
  "type": "Feature",
  "properties": {
    "iso:country":"GB",
    "wof:name":"KA25 6LN",
    "wof:placetype":"postalcode"
},
  "geometry": {"coordinates":[-4.68324132104717,55.74806153809472],"type":"Point"}
}