{
  "type": "Feature",
  "properties": {
    "date:inception_lower": "1994-12-01",
    "date:inception_upper": "1994-12-01",
    "iso:country": "GB",
    "wof:name": "CT1 2BF",
    "wof:placetype": "postalcode"
  },
  "geometry": {"coordinates":[1.079122,51.283466],"type":"Point"}
}
