{
  "type": "Feature",
  "properties": {
    "iso:country":"GB",
    "wof:name":"CT1 2BF",
    "wof:placetype":"postalcode"
},
  "geometry": {"coordinates":[1.07912209041334,51.2834655665466],"type":"Point"}
}