{
  "type": "Feature",
  "properties": {
    "iso:country": "GB",
    "wof:name": "S81 9QP",
    "wof:placetype": "postalcode"
  },
  "geometry": {"coordinates":[-1.121141,53.368214],"type":"Point"}
}
