{
  "type": "Feature",
  "properties": {
    "iso:country": "GB",
    "wof:name": "SL1 3TN",
    "wof:placetype": "postalcode"
  },
  "geometry": {"coordinates":[-0.613464,51.515494],"type":"Point"}
}
