{
  "type": "Feature",
  "properties": {
    "iso:country":"GB",
    "wof:name":"M40 9BP",
    "wof:placetype":"postalcode"
},
  "geometry": {"coordinates":[-2.19419206644664,53.50717688219923],"type":"Point"}
}