{
  "type": "Feature",
  "properties": {
    "iso:country":"GB",
    "wof:name":"SE21 8EZ",
    "wof:placetype":"postalcode"
},
  "geometry": {"coordinates":[-0.09496751635902,51.43694385787823],"type":"Point"}
}