{
  "type": "Feature",
  "properties": {
    "date:inception_lower": "2024-01-01",
    "date:inception_upper": "2024-01-01",
    "iso:country": "GB",
    "wof:name": "N19 9HL",
    "wof:placetype": "postalcode"
  },
  "geometry": {"coordinates":[-0.121432,51.566183],"type":"Point"}
}
