{
  "type": "Feature",
  "properties": {
    "iso:country":"GB",
    "wof:name":"LS10 4RA",
    "wof:placetype":"postalcode"
},
  "geometry": {"coordinates":[-1.520105167942,53.74658540214963],"type":"Point"}
}