{
  "type": "Feature",
  "properties": {
    "iso:country":"GB",
    "wof:name":"HU8 9PG",
    "wof:placetype":"postalcode"
},
  "geometry": {"coordinates":[-0.26762642359815,53.77554208260683],"type":"Point"}
}