{
  "type": "Feature",
  "properties": {
    "iso:country": "GB",
    "wof:name": "HD9 5QZ",
    "wof:placetype": "postalcode"
  },
  "geometry": {"coordinates":[-1.853219,53.596598],"type":"Point"}
}
