{
  "type": "Feature",
  "properties": {
    "iso:country": "GB",
    "wof:name": "HA5 5PZ",
    "wof:placetype": "postalcode"
  },
  "geometry": {"coordinates":[-0.379464,51.594342],"type":"Point"}
}
