{
  "type": "Feature",
  "properties": {
    "iso:country": "GB",
    "wof:name": "M29 7SS",
    "wof:placetype": "postalcode"
  },
  "geometry": {"coordinates":[-2.457725,53.496533],"type":"Point"}
}
