{
  "type": "Feature",
  "properties": {
    "iso:country":"GB",
    "wof:name":"SG2 7DN",
    "wof:placetype":"postalcode"
},
  "geometry": {"coordinates":[-0.15762341904047,51.91247613440932],"type":"Point"}
}