{
  "type": "Feature",
  "properties": {
    "date:inception_lower": "2007-03-01",
    "date:inception_upper": "2007-03-01",
    "iso:country": "GB",
    "wof:name": "NE65 9AJ",
    "wof:placetype": "postalcode"
  },
  "geometry": {"coordinates":[-1.640683,55.33306],"type":"Point"}
}
