{
  "type": "Feature",
  "properties": {
    "iso:country":"GB",
    "wof:name":"BR5 2AF",
    "wof:placetype":"postalcode"
},
  "geometry": {"coordinates":[0.09780350108449,51.3869337963255],"type":"Point"}
}