{
  "type": "Feature",
  "properties": {
    "iso:country":"GB",
    "wof:name":"SE27 0JN",
    "wof:placetype":"postalcode"
},
  "geometry": {"coordinates":[-0.10337043310924,51.42860004799814],"type":"Point"}
}