{
  "type": "Feature",
  "properties": {
    "iso:country": "GB",
    "wof:name": "SE27 0JN",
    "wof:placetype": "postalcode"
  },
  "geometry": {"coordinates":[-0.102741,51.42859],"type":"Point"}
}
