{
  "type": "Feature",
  "properties": {
    "iso:country": "GB",
    "wof:name": "CF11 6BN",
    "wof:placetype": "postalcode"
  },
  "geometry": {"coordinates":[-3.187976,51.469283],"type":"Point"}
}
