{
  "type": "Feature",
  "properties": {
    "iso:country":"GB",
    "wof:name":"IP28 8LH",
    "wof:placetype":"postalcode"
},
  "geometry": {"coordinates":[0.49272052840744,52.30282525438189],"type":"Point"}
}