{
  "type": "Feature",
  "properties": {
    "iso:country": "GB",
    "wof:name": "WA10 5AY",
    "wof:placetype": "postalcode"
  },
  "geometry": {"coordinates":[-2.784861,53.451434],"type":"Point"}
}
