{
  "type": "Feature",
  "properties": {
    "iso:country":"GB",
    "wof:name":"OL9 9AT",
    "wof:placetype":"postalcode"
},
  "geometry": {"coordinates":[-2.13997434312932,53.53963790020837],"type":"Point"}
}