{
  "type": "Feature",
  "properties": {
    "iso:country":"GB",
    "wof:name":"SN3 2RL",
    "wof:placetype":"postalcode"
},
  "geometry": {"coordinates":[-1.74930468258471,51.55932079264136],"type":"Point"}
}