{
  "type": "Feature",
  "properties": {
    "iso:country":"GB",
    "wof:name":"RM8 2AD",
    "wof:placetype":"postalcode"
},
  "geometry": {"coordinates":[0.12170188537866,51.55040780260744],"type":"Point"}
}