{
  "type": "Feature",
  "properties": {
    "date:inception_lower":"1980-01-01",
    "date:inception_upper":"1980-01-31",
    "iso:country":"GB",
    "wof:name":"BR7 6RD",
    "wof:placetype":"postalcode"
},
  "geometry": {"coordinates":[0.089363,51.397274],"type":"Point"}
}