{
  "type": "Feature",
  "properties": {
    "iso:country": "GB",
    "wof:name": "ST5 5BZ",
    "wof:placetype": "postalcode"
  },
  "geometry": {"coordinates":[-2.299658,52.95801],"type":"Point"}
}
