{
  "type": "Feature",
  "properties": {
    "iso:country": "GB",
    "wof:name": "G67 2PX",
    "wof:placetype": "postalcode"
  },
  "geometry": {"coordinates":[-3.982171,55.94381],"type":"Point"}
}
