{
  "type": "Feature",
  "properties": {
    "iso:country": "GB",
    "wof:name": "TS25 2HT",
    "wof:placetype": "postalcode"
  },
  "geometry": {"coordinates":[-1.239261,54.641647],"type":"Point"}
}
