{
  "type": "Feature",
  "properties": {
    "iso:country":"GB",
    "wof:name":"DN7 5HY",
    "wof:placetype":"postalcode"
},
  "geometry": {"coordinates":[-1.02971803480723,53.59022147353517],"type":"Point"}
}