{
  "type": "Feature",
  "properties": {
    "date:inception_lower": "2011-06-01",
    "date:inception_upper": "2011-06-01",
    "iso:country": "GB",
    "wof:name": "DN7 5HY",
    "wof:placetype": "postalcode"
  },
  "geometry": {"coordinates":[-1.029737,53.590287],"type":"Point"}
}
