{
  "type": "Feature",
  "properties": {
    "iso:country": "GB",
    "wof:name": "DN7 5HY",
    "wof:placetype": "postalcode"
  },
  "geometry": {"coordinates":[-1.029737,53.590287],"type":"Point"}
}
