{
  "type": "Feature",
  "properties": {
    "date:inception_lower": "1983-07-01",
    "date:inception_upper": "1983-07-01",
    "iso:country": "GB",
    "wof:name": "ME5 9HN",
    "wof:placetype": "postalcode"
  },
  "geometry": {"coordinates":[0.520874,51.330091],"type":"Point"}
}
