{
  "type": "Feature",
  "properties": {
    "iso:country": "GB",
    "wof:name": "ST6 6QS",
    "wof:placetype": "postalcode"
  },
  "geometry": {"coordinates":[-2.184098,53.073477],"type":"Point"}
}
