{
  "type": "Feature",
  "properties": {
    "iso:country": "GB",
    "wof:name": "DN11 9AG",
    "wof:placetype": "postalcode"
  },
  "geometry": {"coordinates":[-1.147388,53.456692],"type":"Point"}
}
