{
  "type": "Feature",
  "properties": {
    "iso:country":"GB",
    "wof:name":"DN11 9AG",
    "wof:placetype":"postalcode"
},
  "geometry": {"coordinates":[-1.14738811979605,53.45669216828548],"type":"Point"}
}