{
  "type": "Feature",
  "properties": {
    "iso:country":"GB",
    "wof:name":"NR15 2PU",
    "wof:placetype":"postalcode"
},
  "geometry": {"coordinates":[1.2265935361285,52.48645840783751],"type":"Point"}
}