{
  "type": "Feature",
  "properties": {
    "iso:country": "GB",
    "wof:name": "S35 1WX",
    "wof:placetype": "postalcode"
  },
  "geometry": {"coordinates":[-1.467838,53.461425],"type":"Point"}
}
