{
  "type": "Feature",
  "properties": {
    "iso:country":"GB",
    "wof:name":"S35 1WX",
    "wof:placetype":"postalcode"
},
  "geometry": {"coordinates":[-1.46783801307833,53.46142478043237],"type":"Point"}
}