{
  "type": "Feature",
  "properties": {
    "iso:country":"GB",
    "wof:name":"GL17 0PG",
    "wof:placetype":"postalcode"
},
  "geometry": {"coordinates":[-2.44346574037898,51.86309226473894],"type":"Point"}
}