{
  "type": "Feature",
  "properties": {
    "iso:country":"GB",
    "wof:name":"BH13 6JQ",
    "wof:placetype":"postalcode"
},
  "geometry": {"coordinates":[-1.90947970046909,50.70841247939767],"type":"Point"}
}