{
  "type": "Feature",
  "properties": {
    "iso:country":"GB",
    "wof:name":"BH21 3XG",
    "wof:placetype":"postalcode"
},
  "geometry": {"coordinates":[-2.01252860786344,50.77810366289552],"type":"Point"}
}