{
  "type": "Feature",
  "properties": {
    "date:inception_lower":"1990-02-01",
    "date:inception_upper":"1990-02-28",
    "iso:country":"GB",
    "wof:name":"BH21 3XG",
    "wof:placetype":"postalcode"
},
  "geometry": {"coordinates":[-2.012529,50.778104],"type":"Point"}
}