{
  "type": "Feature",
  "properties": {
    "iso:country": "GB",
    "wof:name": "M38 9PB",
    "wof:placetype": "postalcode"
  },
  "geometry": {"coordinates":[-2.416094,53.529054],"type":"Point"}
}
