{
  "type": "Feature",
  "properties": {
    "iso:country":"GB",
    "wof:name":"M46 9WT",
    "wof:placetype":"postalcode"
},
  "geometry": {"coordinates":[-2.49445234134742,53.53582956562099],"type":"Point"}
}