{
  "type": "Feature",
  "properties": {
    "date:inception_lower": "2007-05-01",
    "date:inception_upper": "2007-05-01",
    "iso:country": "GB",
    "wof:name": "SK3 9AG",
    "wof:placetype": "postalcode"
  },
  "geometry": {"coordinates":[-2.166035,53.401693],"type":"Point"}
}
