{
  "type": "Feature",
  "properties": {
    "iso:country": "GB",
    "wof:name": "L8 7LP",
    "wof:placetype": "postalcode"
  },
  "geometry": {"coordinates":[-2.970757,53.396541],"type":"Point"}
}
