{
  "type": "Feature",
  "properties": {
    "iso:country":"GB",
    "wof:name":"L8 7LP",
    "wof:placetype":"postalcode"
},
  "geometry": {"coordinates":[-2.97075664283379,53.39654085450698],"type":"Point"}
}