{
  "type": "Feature",
  "properties": {
    "date:inception_lower": "2008-12-01",
    "date:inception_upper": "2008-12-01",
    "iso:country": "GB",
    "wof:name": "NG9 2JD",
    "wof:placetype": "postalcode"
  },
  "geometry": {"coordinates":[-1.208399,52.933146],"type":"Point"}
}
