{
  "type": "Feature",
  "properties": {
    "iso:country":"GB",
    "wof:name":"NG9 2JD",
    "wof:placetype":"postalcode"
},
  "geometry": {"coordinates":[-1.20839874928876,52.93314565914524],"type":"Point"}
}