{
  "type": "Feature",
  "properties": {
    "date:inception_lower": "1980-01-01",
    "date:inception_upper": "1980-01-01",
    "iso:country": "GB",
    "wof:name": "B36 0HP",
    "wof:placetype": "postalcode"
  },
  "geometry": {"coordinates":[-1.758044,52.503251],"type":"Point"}
}
