{
  "type": "Feature",
  "properties": {
    "iso:country":"GB",
    "wof:name":"B36 0HP",
    "wof:placetype":"postalcode"
},
  "geometry": {"coordinates":[-1.75804417641829,52.50325110872068],"type":"Point"}
}