{
  "type": "Feature",
  "properties": {
    "iso:country":"GB",
    "wof:name":"LE17 6HX",
    "wof:placetype":"postalcode"
},
  "geometry": {"coordinates":[-1.09118389060279,52.44596965841519],"type":"Point"}
}