{
  "type": "Feature",
  "properties": {
    "date:inception_lower": "1980-01-01",
    "date:inception_upper": "1980-01-01",
    "iso:country": "GB",
    "wof:name": "LE17 6HX",
    "wof:placetype": "postalcode"
  },
  "geometry": {"coordinates":[-1.091184,52.44597],"type":"Point"}
}
