{
  "type": "Feature",
  "properties": {
    "date:inception_lower": "1980-01-01",
    "date:inception_upper": "1980-01-01",
    "iso:country": "GB",
    "wof:name": "CF44 8DP",
    "wof:placetype": "postalcode"
  },
  "geometry": {"coordinates":[-3.450663,51.716231],"type":"Point"}
}
