{
  "type": "Feature",
  "properties": {
    "iso:country":"GB",
    "wof:name":"CF44 8DP",
    "wof:placetype":"postalcode"
},
  "geometry": {"coordinates":[-3.45066270147089,51.71623070676159],"type":"Point"}
}