{
  "type": "Feature",
  "properties": {
    "iso:country":"GB",
    "wof:name":"DG2 7LD",
    "wof:placetype":"postalcode"
},
  "geometry": {"coordinates":[-3.61936433848769,55.0592157865614],"type":"Point"}
}