{
  "type": "Feature",
  "properties": {
    "iso:country":"GB",
    "wof:name":"W1J 0AB",
    "wof:placetype":"postalcode"
},
  "geometry": {"coordinates":[-0.13612472846406,51.5095370790934],"type":"Point"}
}