{
  "type": "Feature",
  "properties": {
    "iso:country": "GB",
    "wof:name": "WV8 1XE",
    "wof:placetype": "postalcode"
  },
  "geometry": {"coordinates":[-2.157243,52.617124],"type":"Point"}
}
