{
  "type": "Feature",
  "properties": {
    "iso:country":"GB",
    "wof:name":"WV8 1XE",
    "wof:placetype":"postalcode"
},
  "geometry": {"coordinates":[-2.1572433235367,52.61712361222352],"type":"Point"}
}