{
  "type": "Feature",
  "properties": {
    "iso:country":"GB",
    "wof:name":"PL4 7HU",
    "wof:placetype":"postalcode"
},
  "geometry": {"coordinates":[-4.11843298038682,50.38211335485121],"type":"Point"}
}