{
  "type": "Feature",
  "properties": {
    "iso:country": "GB",
    "wof:name": "PL4 7HU",
    "wof:placetype": "postalcode"
  },
  "geometry": {"coordinates":[-4.118433,50.382113],"type":"Point"}
}
