{
  "type": "Feature",
  "properties": {
    "iso:country":"GB",
    "wof:name":"TA24 8HA",
    "wof:placetype":"postalcode"
},
  "geometry": {"coordinates":[-3.58849124425446,51.21065449224174],"type":"Point"}
}