{
  "type": "Feature",
  "properties": {
    "iso:country": "GB",
    "wof:name": "TA24 8HA",
    "wof:placetype": "postalcode"
  },
  "geometry": {"coordinates":[-3.588491,51.210654],"type":"Point"}
}
