{
  "type": "Feature",
  "properties": {
    "iso:country": "GB",
    "wof:name": "S35 4AA",
    "wof:placetype": "postalcode"
  },
  "geometry": {"coordinates":[-1.494161,53.475759],"type":"Point"}
}
