{
  "type": "Feature",
  "properties": {
    "iso:country":"GB",
    "wof:name":"NR28 0PG",
    "wof:placetype":"postalcode"
},
  "geometry": {"coordinates":[1.39508881524179,52.84777933644722],"type":"Point"}
}