{
  "type": "Feature",
  "properties": {
    "iso:country": "GB",
    "wof:name": "NR28 0PG",
    "wof:placetype": "postalcode"
  },
  "geometry": {"coordinates":[1.395126,52.847825],"type":"Point"}
}
