{
  "type": "Feature",
  "properties": {
    "iso:country": "GB",
    "wof:name": "KT2 5TF",
    "wof:placetype": "postalcode"
  },
  "geometry": {"coordinates":[-0.298409,51.419229],"type":"Point"}
}
