{
  "type": "Feature",
  "properties": {
    "iso:country":"GB",
    "wof:name":"KT2 5TF",
    "wof:placetype":"postalcode"
},
  "geometry": {"coordinates":[-0.29840868427287,51.4192290942025],"type":"Point"}
}