{
  "type": "Feature",
  "properties": {
    "iso:country": "GB",
    "wof:name": "EX10 0ET",
    "wof:placetype": "postalcode"
  },
  "geometry": {"coordinates":[-3.292068,50.700052],"type":"Point"}
}
