{
  "type": "Feature",
  "properties": {
    "iso:country":"GB",
    "wof:name":"B34 7AE",
    "wof:placetype":"postalcode"
},
  "geometry": {"coordinates":[-1.77793648199715,52.49362587025007],"type":"Point"}
}