{
  "type": "Feature",
  "properties": {
    "iso:country": "GB",
    "wof:name": "SY21 7NA",
    "wof:placetype": "postalcode"
  },
  "geometry": {"coordinates":[-3.157425,52.661602],"type":"Point"}
}
