{
  "type": "Feature",
  "properties": {
    "iso:country":"GB",
    "wof:name":"SY21 7NA",
    "wof:placetype":"postalcode"
},
  "geometry": {"coordinates":[-3.15742540489529,52.66160183839825],"type":"Point"}
}