{
  "type": "Feature",
  "properties": {
    "date:inception_lower": "1980-01-01",
    "date:inception_upper": "1980-01-01",
    "iso:country": "GB",
    "wof:name": "LL18 5EY",
    "wof:placetype": "postalcode"
  },
  "geometry": {"coordinates":[-3.517788,53.304278],"type":"Point"}
}
