{
  "type": "Feature",
  "properties": {
    "iso:country":"GB",
    "wof:name":"LL18 5EY",
    "wof:placetype":"postalcode"
},
  "geometry": {"coordinates":[-3.51778767356701,53.30427811385784],"type":"Point"}
}