{
  "type": "Feature",
  "properties": {
    "date:inception_lower":"1998-06-01",
    "date:inception_upper":"1998-06-30",
    "iso:country":"GB",
    "wof:name":"HU13 9DU",
    "wof:placetype":"postalcode"
},
  "geometry": {"coordinates":[-0.427083,53.732319],"type":"Point"}
}