{
  "type": "Feature",
  "properties": {
    "iso:country":"GB",
    "wof:name":"BN1 9GT",
    "wof:placetype":"postalcode"
},
  "geometry": {"coordinates":[-0.1071149419527,50.86269185815386],"type":"Point"}
}