{
  "type": "Feature",
  "properties": {
    "date:inception_lower": "1993-01-01",
    "date:inception_upper": "1993-01-01",
    "iso:country": "GB",
    "wof:name": "BN1 9GT",
    "wof:placetype": "postalcode"
  },
  "geometry": {"coordinates":[-0.107115,50.862692],"type":"Point"}
}
