{
  "type": "Feature",
  "properties": {
    "date:inception_lower":"1980-01-01",
    "date:inception_upper":"1980-01-31",
    "iso:country":"GB",
    "wof:name":"DE11 7LA",
    "wof:placetype":"postalcode"
},
  "geometry": {"coordinates":[-1.542093,52.780379],"type":"Point"}
}