{
  "type": "Feature",
  "properties": {
    "iso:country": "GB",
    "wof:name": "DE11 7LA",
    "wof:placetype": "postalcode"
  },
  "geometry": {"coordinates":[-1.542093,52.780379],"type":"Point"}
}
