{
  "type": "Feature",
  "properties": {
    "date:inception_lower": "2024-08-01",
    "date:inception_upper": "2024-08-01",
    "iso:country": "GB",
    "wof:name": "NN7 4UP",
    "wof:placetype": "postalcode"
  },
  "geometry": {"coordinates":[-1.086146,52.241845],"type":"Point"}
}
