{
  "type": "Feature",
  "properties": {
    "iso:country":"GB",
    "wof:name":"PL20 7RW",
    "wof:placetype":"postalcode"
},
  "geometry": {"coordinates":[-4.10333784193575,50.5053027278034],"type":"Point"}
}