{
  "type": "Feature",
  "properties": {
    "date:inception_lower": "1980-01-01",
    "date:inception_upper": "1980-01-01",
    "iso:country": "GB",
    "wof:name": "PL20 7RW",
    "wof:placetype": "postalcode"
  },
  "geometry": {"coordinates":[-4.103338,50.505303],"type":"Point"}
}
