{
  "type": "Feature",
  "properties": {
    "iso:country":"GB",
    "wof:name":"WV4 4AX",
    "wof:placetype":"postalcode"
},
  "geometry": {"coordinates":[-2.15508813302735,52.56738592317387],"type":"Point"}
}