{
  "type": "Feature",
  "properties": {
    "iso:country":"GB",
    "wof:name":"WF9 4BW",
    "wof:placetype":"postalcode"
},
  "geometry": {"coordinates":[-1.32993117570247,53.60973420185632],"type":"Point"}
}