{
  "type": "Feature",
  "properties": {
    "iso:country": "GB",
    "wof:name": "WV13 3BR",
    "wof:placetype": "postalcode"
  },
  "geometry": {"coordinates":[-2.079813,52.584818],"type":"Point"}
}
