{
  "type": "Feature",
  "properties": {
    "date:inception_lower": "2020-02-01",
    "date:inception_upper": "2020-02-01",
    "iso:country": "GB",
    "wof:name": "WV13 3BR",
    "wof:placetype": "postalcode"
  },
  "geometry": {"coordinates":[-2.079488,52.584665],"type":"Point"}
}
