{
  "type": "Feature",
  "properties": {
    "iso:country": "GB",
    "wof:name": "NE61 6ED",
    "wof:placetype": "postalcode"
  },
  "geometry": {"coordinates":[-1.668065,55.119418],"type":"Point"}
}
