{
  "type": "Feature",
  "properties": {
    "iso:country":"GB",
    "wof:name":"NE61 6ED",
    "wof:placetype":"postalcode"
},
  "geometry": {"coordinates":[-1.66806477608278,55.1194176529885],"type":"Point"}
}