{
  "type": "Feature",
  "properties": {
    "date:inception_lower": "1999-12-01",
    "date:inception_upper": "1999-12-01",
    "iso:country": "GB",
    "wof:name": "HP14 3EL",
    "wof:placetype": "postalcode"
  },
  "geometry": {"coordinates":[-0.791356,51.63984],"type":"Point"}
}
