{
  "type": "Feature",
  "properties": {
    "date:inception_lower": "1991-09-01",
    "date:inception_upper": "1991-09-01",
    "iso:country": "GB",
    "wof:name": "PE33 9HN",
    "wof:placetype": "postalcode"
  },
  "geometry": {"coordinates":[0.526689,52.658105],"type":"Point"}
}
