{
  "type": "Feature",
  "properties": {
    "iso:country": "GB",
    "wof:name": "RM16 6RB",
    "wof:placetype": "postalcode"
  },
  "geometry": {"coordinates":[0.309938,51.488811],"type":"Point"}
}
