{
  "type": "Feature",
  "properties": {
    "iso:country":"GB",
    "wof:name":"RM16 6RB",
    "wof:placetype":"postalcode"
},
  "geometry": {"coordinates":[0.30993797352246,51.48881072336975],"type":"Point"}
}