{
  "type": "Feature",
  "properties": {
    "iso:country":"GB",
    "wof:name":"S81 7RA",
    "wof:placetype":"postalcode"
},
  "geometry": {"coordinates":[-1.13559662603149,53.33119488554743],"type":"Point"}
}