{
  "type": "Feature",
  "properties": {
    "iso:country":"GB",
    "wof:name":"HP4 1FL",
    "wof:placetype":"postalcode"
},
  "geometry": {"coordinates":[-0.57414937663628,51.76381051533355],"type":"Point"}
}