{
  "type": "Feature",
  "properties": {
    "iso:country": "GB",
    "wof:name": "NG10 4FY",
    "wof:placetype": "postalcode"
  },
  "geometry": {"coordinates":[-1.295875,52.903168],"type":"Point"}
}
