{
  "type": "Feature",
  "properties": {
    "iso:country":"GB",
    "wof:name":"NG10 4FY",
    "wof:placetype":"postalcode"
},
  "geometry": {"coordinates":[-1.29587527943924,52.9031677376962],"type":"Point"}
}