{
  "type": "Feature",
  "properties": {
    "date:inception_lower": "1990-02-01",
    "date:inception_upper": "1990-02-01",
    "iso:country": "GB",
    "wof:name": "DA15 7JU",
    "wof:placetype": "postalcode"
  },
  "geometry": {"coordinates":[0.101625,51.427343],"type":"Point"}
}
