{
  "type": "Feature",
  "properties": {
    "iso:country": "GB",
    "wof:name": "DA15 7JU",
    "wof:placetype": "postalcode"
  },
  "geometry": {"coordinates":[0.101625,51.427343],"type":"Point"}
}
