{
  "type": "Feature",
  "properties": {
    "iso:country": "GB",
    "wof:name": "ML11 9FS",
    "wof:placetype": "postalcode"
  },
  "geometry": {"coordinates":[-3.768266,55.666929],"type":"Point"}
}
