{
  "type": "Feature",
  "properties": {
    "iso:country":"GB",
    "wof:name":"LS6 1HZ",
    "wof:placetype":"postalcode"
},
  "geometry": {"coordinates":[-1.56989195041711,53.81139843183406],"type":"Point"}
}