{
  "type": "Feature",
  "properties": {
    "iso:country": "GB",
    "wof:name": "LS6 1HZ",
    "wof:placetype": "postalcode"
  },
  "geometry": {"coordinates":[-1.569892,53.811398],"type":"Point"}
}
