{
  "type": "Feature",
  "properties": {
    "date:inception_lower": "2003-04-01",
    "date:inception_upper": "2003-04-01",
    "iso:country": "GB",
    "wof:name": "OL1 4TP",
    "wof:placetype": "postalcode"
  },
  "geometry": {"coordinates":[-2.077881,53.563541],"type":"Point"}
}
