{
  "type": "Feature",
  "properties": {
    "iso:country":"GB",
    "wof:name":"OL1 4TP",
    "wof:placetype":"postalcode"
},
  "geometry": {"coordinates":[-2.07788102687813,53.56354063087088],"type":"Point"}
}