{
  "type": "Feature",
  "properties": {
    "date:inception_lower": "1980-01-01",
    "date:inception_upper": "1980-01-01",
    "iso:country": "GB",
    "wof:name": "RG26 5PB",
    "wof:placetype": "postalcode"
  },
  "geometry": {"coordinates":[-1.167768,51.359342],"type":"Point"}
}
