{
  "type": "Feature",
  "properties": {
    "iso:country": "GB",
    "wof:name": "RG26 5PB",
    "wof:placetype": "postalcode"
  },
  "geometry": {"coordinates":[-1.167768,51.359342],"type":"Point"}
}
