{
  "type": "Feature",
  "properties": {
    "iso:country":"GB",
    "wof:name":"RG26 5PB",
    "wof:placetype":"postalcode"
},
  "geometry": {"coordinates":[-1.16776766796897,51.35934213097764],"type":"Point"}
}