{
  "type": "Feature",
  "properties": {
    "iso:country":"GB",
    "wof:name":"SW18 1BQ",
    "wof:placetype":"postalcode"
},
  "geometry": {"coordinates":[-0.18941188709123,51.45836821662254],"type":"Point"}
}