{
  "type": "Feature",
  "properties": {
    "date:inception_lower": "2023-05-01",
    "date:inception_upper": "2023-05-01",
    "iso:country": "GB",
    "wof:name": "NG34 6AX",
    "wof:placetype": "postalcode"
  },
  "geometry": {"coordinates":[-0.421389,52.984268],"type":"Point"}
}
