{
  "type": "Feature",
  "properties": {
    "date:inception_lower": "2024-01-01",
    "date:inception_upper": "2024-01-01",
    "iso:country": "GB",
    "wof:name": "NG34 6AX",
    "wof:placetype": "postalcode"
  },
  "geometry": {"coordinates":[-0.422314,52.984649],"type":"Point"}
}
