{
  "type": "Feature",
  "properties": {
    "date:inception_lower": "2016-06-01",
    "date:inception_upper": "2016-06-01",
    "iso:country": "GB",
    "wof:name": "S75 6FU",
    "wof:placetype": "postalcode"
  },
  "geometry": {"coordinates":[-1.502666,53.587207],"type":"Point"}
}
