{
  "type": "Feature",
  "properties": {
    "date:inception_lower": "1986-01-01",
    "date:inception_upper": "1986-01-01",
    "iso:country": "GB",
    "wof:name": "SO51 8FP",
    "wof:placetype": "postalcode"
  },
  "geometry": {"coordinates":[-1.500262,50.994383],"type":"Point"}
}
