{
  "type": "Feature",
  "properties": {
    "iso:country": "GB",
    "wof:name": "CM7 5HA",
    "wof:placetype": "postalcode"
  },
  "geometry": {"coordinates":[0.501055,51.922234],"type":"Point"}
}
