{
  "type": "Feature",
  "properties": {
    "iso:country":"GB",
    "wof:name":"CM7 5HA",
    "wof:placetype":"postalcode"
},
  "geometry": {"coordinates":[0.50105523984324,51.92223411626316],"type":"Point"}
}