{
  "type": "Feature",
  "properties": {
    "iso:country": "GB",
    "wof:name": "S61 1EX",
    "wof:placetype": "postalcode"
  },
  "geometry": {"coordinates":[-1.391711,53.432262],"type":"Point"}
}
