{
  "type": "Feature",
  "properties": {
    "iso:country":"GB",
    "wof:name":"S61 1EX",
    "wof:placetype":"postalcode"
},
  "geometry": {"coordinates":[-1.39171120778878,53.43226207664048],"type":"Point"}
}