{
  "type": "Feature",
  "properties": {
    "iso:country":"GB",
    "wof:name":"DN31 2BJ",
    "wof:placetype":"postalcode"
},
  "geometry": {"coordinates":[-0.10810337058859,53.56693612028816],"type":"Point"}
}