{
  "type": "Feature",
  "properties": {
    "iso:country":"GB",
    "wof:name":"GL2 4SS",
    "wof:placetype":"postalcode"
},
  "geometry": {"coordinates":[-2.33284914265325,51.83513591554912],"type":"Point"}
}