{
  "type": "Feature",
  "properties": {
    "date:inception_lower": "1995-12-01",
    "date:inception_upper": "1995-12-01",
    "iso:country": "GB",
    "wof:name": "GL2 4SS",
    "wof:placetype": "postalcode"
  },
  "geometry": {"coordinates":[-2.332849,51.835136],"type":"Point"}
}
