{
  "type": "Feature",
  "properties": {
    "iso:country": "GB",
    "wof:name": "DY13 0UA",
    "wof:placetype": "postalcode"
  },
  "geometry": {"coordinates":[-2.311454,52.318665],"type":"Point"}
}
