{
  "type": "Feature",
  "properties": {
    "iso:country":"GB",
    "wof:name":"TN2 5HR",
    "wof:placetype":"postalcode"
},
  "geometry": {"coordinates":[0.2633890343846,51.11692859412199],"type":"Point"}
}