{
  "type": "Feature",
  "properties": {
    "iso:country":"GB",
    "wof:name":"SE14 5XA",
    "wof:placetype":"postalcode"
},
  "geometry": {"coordinates":[-0.04720098024463,51.48040181873373],"type":"Point"}
}