{
  "type": "Feature",
  "properties": {
    "iso:country":"GB",
    "wof:name":"FK2 9AA",
    "wof:placetype":"postalcode"
},
  "geometry": {"coordinates":[-3.76109191028569,56.00485248354001],"type":"Point"}
}