{
  "type": "Feature",
  "properties": {
    "iso:country":"GB",
    "wof:name":"E16 1PP",
    "wof:placetype":"postalcode"
},
  "geometry": {"coordinates":[0.02021795298722,51.51436715123896],"type":"Point"}
}