{
  "type": "Feature",
  "properties": {
    "iso:country": "GB",
    "wof:name": "WF14 8DW",
    "wof:placetype": "postalcode"
  },
  "geometry": {"coordinates":[-1.694024,53.676122],"type":"Point"}
}
