{
  "type": "Feature",
  "properties": {
    "iso:country":"GB",
    "wof:name":"SN2 1NA",
    "wof:placetype":"postalcode"
},
  "geometry": {"coordinates":[-1.79971691620544,51.57312039448657],"type":"Point"}
}