{
  "type": "Feature",
  "properties": {
    "iso:country":"GB",
    "wof:name":"DN34 5BB",
    "wof:placetype":"postalcode"
},
  "geometry": {"coordinates":[-0.09017751835753,53.55387674224704],"type":"Point"}
}