{
  "type": "Feature",
  "properties": {
    "date:inception_lower": "2017-05-01",
    "date:inception_upper": "2017-05-01",
    "iso:country": "GB",
    "wof:name": "CA14 5NW",
    "wof:placetype": "postalcode"
  },
  "geometry": {"coordinates":[-3.552613,54.615473],"type":"Point"}
}
