{
  "type": "Feature",
  "properties": {
    "iso:country": "GB",
    "wof:name": "SN6 7DG",
    "wof:placetype": "postalcode"
  },
  "geometry": {"coordinates":[-1.708525,51.633891],"type":"Point"}
}
