{
  "type": "Feature",
  "properties": {
    "date:inception_lower": "1988-03-01",
    "date:inception_upper": "1988-03-01",
    "iso:country": "GB",
    "wof:name": "SN6 7DG",
    "wof:placetype": "postalcode"
  },
  "geometry": {"coordinates":[-1.708525,51.633891],"type":"Point"}
}
