{
  "type": "Feature",
  "properties": {
    "iso:country":"GB",
    "wof:name":"NE25 9TT",
    "wof:placetype":"postalcode"
},
  "geometry": {"coordinates":[-1.46737799710172,55.03535942854474],"type":"Point"}
}