{
  "type": "Feature",
  "properties": {
    "iso:country": "GB",
    "wof:name": "YO61 3RF",
    "wof:placetype": "postalcode"
  },
  "geometry": {"coordinates":[-1.123127,54.151576],"type":"Point"}
}
