{
  "type": "Feature",
  "properties": {
    "iso:country":"GB",
    "wof:name":"YO61 3RF",
    "wof:placetype":"postalcode"
},
  "geometry": {"coordinates":[-1.12925368499809,54.15171337066026],"type":"Point"}
}