{
  "type": "Feature",
  "properties": {
    "iso:country":"GB",
    "wof:name":"YO13 0PW",
    "wof:placetype":"postalcode"
},
  "geometry": {"coordinates":[-0.44582156712241,54.30596651681432],"type":"Point"}
}