{
  "type": "Feature",
  "properties": {
    "iso:country":"GB",
    "wof:name":"M46 9DD",
    "wof:placetype":"postalcode"
},
  "geometry": {"coordinates":[-2.48942075368363,53.523428227896],"type":"Point"}
}