{
  "type": "Feature",
  "properties": {
    "iso:country":"GB",
    "wof:name":"WV16 5LS",
    "wof:placetype":"postalcode"
},
  "geometry": {"coordinates":[-2.430841994016,52.51450752818202],"type":"Point"}
}