{
  "type": "Feature",
  "properties": {
    "date:inception_lower": "1980-01-01",
    "date:inception_upper": "1980-01-01",
    "iso:country": "GB",
    "wof:name": "WV16 5LS",
    "wof:placetype": "postalcode"
  },
  "geometry": {"coordinates":[-2.430842,52.514508],"type":"Point"}
}
