{
  "type": "Feature",
  "properties": {
    "iso:country":"GB",
    "wof:name":"S65 1LP",
    "wof:placetype":"postalcode"
},
  "geometry": {"coordinates":[-1.33654486865435,53.43825161735453],"type":"Point"}
}