{
  "type": "Feature",
  "properties": {
    "iso:country":"GB",
    "wof:name":"IV63 6XF",
    "wof:placetype":"postalcode"
},
  "geometry": {"coordinates":[-4.47635857919857,57.31482116573262],"type":"Point"}
}