{
  "type": "Feature",
  "properties": {
    "iso:country": "GB",
    "wof:name": "IV63 6XF",
    "wof:placetype": "postalcode"
  },
  "geometry": {"coordinates":[-4.476359,57.314821],"type":"Point"}
}
