{
  "type": "Feature",
  "properties": {
    "iso:country":"GB",
    "wof:name":"KA3 5PY",
    "wof:placetype":"postalcode"
},
  "geometry": {"coordinates":[-4.50382084896047,55.6834234395286],"type":"Point"}
}