{
  "type": "Feature",
  "properties": {
    "iso:country": "GB",
    "wof:name": "KA3 5PY",
    "wof:placetype": "postalcode"
  },
  "geometry": {"coordinates":[-4.503821,55.683423],"type":"Point"}
}
