{
  "type": "Feature",
  "properties": {
    "iso:country":"GB",
    "wof:name":"NN7 4AB",
    "wof:placetype":"postalcode"
},
  "geometry": {"coordinates":[-0.96827635058286,52.21412907907168],"type":"Point"}
}