{
  "type": "Feature",
  "properties": {
    "iso:country": "GB",
    "wof:name": "SG8 0QZ",
    "wof:placetype": "postalcode"
  },
  "geometry": {"coordinates":[-0.092852,52.070781],"type":"Point"}
}
