{
  "type": "Feature",
  "properties": {
    "iso:country":"GB",
    "wof:name":"SG8 0QZ",
    "wof:placetype":"postalcode"
},
  "geometry": {"coordinates":[-0.09285186812166,52.07078087559557],"type":"Point"}
}