{
  "type": "Feature",
  "properties": {
    "date:inception_lower": "1980-01-01",
    "date:inception_upper": "1980-01-01",
    "iso:country": "GB",
    "wof:name": "SG8 0QZ",
    "wof:placetype": "postalcode"
  },
  "geometry": {"coordinates":[-0.092852,52.070781],"type":"Point"}
}
