{
  "type": "Feature",
  "properties": {
    "date:inception_lower": "1980-01-01",
    "date:inception_upper": "1980-01-01",
    "iso:country": "GB",
    "wof:name": "DN36 5ET",
    "wof:placetype": "postalcode"
  },
  "geometry": {"coordinates":[-0.065722,53.506959],"type":"Point"}
}
