{
  "type": "Feature",
  "properties": {
    "iso:country": "GB",
    "wof:name": "DN36 5ET",
    "wof:placetype": "postalcode"
  },
  "geometry": {"coordinates":[-0.065722,53.506959],"type":"Point"}
}
