{
  "type": "Feature",
  "properties": {
    "iso:country":"GB",
    "wof:name":"TN25 5NP",
    "wof:placetype":"postalcode"
},
  "geometry": {"coordinates":[0.92696853571527,51.14341510388334],"type":"Point"}
}