{
  "type": "Feature",
  "properties": {
    "date:inception_lower": "1980-01-01",
    "date:inception_upper": "1980-01-01",
    "iso:country": "GB",
    "wof:name": "HG1 5QQ",
    "wof:placetype": "postalcode"
  },
  "geometry": {"coordinates":[-1.534696,53.991663],"type":"Point"}
}
