{
  "type": "Feature",
  "properties": {
    "date:inception_lower":"1980-01-01",
    "date:inception_upper":"1980-01-31",
    "iso:country":"GB",
    "wof:name":"PL19 0AG",
    "wof:placetype":"postalcode"
},
  "geometry": {"coordinates":[-4.145161,50.550248],"type":"Point"}
}