{
  "type": "Feature",
  "properties": {
    "iso:country": "GB",
    "wof:name": "PL19 0AG",
    "wof:placetype": "postalcode"
  },
  "geometry": {"coordinates":[-4.145161,50.550248],"type":"Point"}
}
