{
  "type": "Feature",
  "properties": {
    "iso:country": "GB",
    "wof:name": "DE14 2QG",
    "wof:placetype": "postalcode"
  },
  "geometry": {"coordinates":[-1.641985,52.816123],"type":"Point"}
}
