{
  "type": "Feature",
  "properties": {
    "iso:country":"GB",
    "wof:name":"DE14 2QG",
    "wof:placetype":"postalcode"
},
  "geometry": {"coordinates":[-1.6419157656198,52.81606924093106],"type":"Point"}
}