{
  "type": "Feature",
  "properties": {
    "date:inception_lower": "1992-01-01",
    "date:inception_upper": "1992-01-01",
    "iso:country": "GB",
    "wof:name": "DE14 2QG",
    "wof:placetype": "postalcode"
  },
  "geometry": {"coordinates":[-1.641985,52.816123],"type":"Point"}
}
