{
  "type": "Feature",
  "properties": {
    "iso:country":"GB",
    "wof:name":"RH13 6PF",
    "wof:placetype":"postalcode"
},
  "geometry": {"coordinates":[-0.26170084418597,51.04799065204863],"type":"Point"}
}