{
  "type": "Feature",
  "properties": {
    "date:inception_lower": "2007-07-01",
    "date:inception_upper": "2007-07-01",
    "iso:country": "GB",
    "wof:name": "TQ7 1DY",
    "wof:placetype": "postalcode"
  },
  "geometry": {"coordinates":[-3.777326,50.283245],"type":"Point"}
}
