{
  "type": "Feature",
  "properties": {
    "iso:country":"GB",
    "wof:name":"SE1 3RH",
    "wof:placetype":"postalcode"
},
  "geometry": {"coordinates":[-0.08583531733503,51.49979745722695],"type":"Point"}
}