{
  "type": "Feature",
  "properties": {
    "iso:country":"GB",
    "wof:name":"DT6 6EZ",
    "wof:placetype":"postalcode"
},
  "geometry": {"coordinates":[-2.78581016829167,50.73875610829973],"type":"Point"}
}