{
  "type": "Feature",
  "properties": {
    "iso:country":"GB",
    "wof:name":"PE36 5LD",
    "wof:placetype":"postalcode"
},
  "geometry": {"coordinates":[0.5430420356115,52.93364277800077],"type":"Point"}
}