{
  "type": "Feature",
  "properties": {
    "iso:country": "GB",
    "wof:name": "PE36 5LD",
    "wof:placetype": "postalcode"
  },
  "geometry": {"coordinates":[0.543231,52.933898],"type":"Point"}
}
