{
  "type": "Feature",
  "properties": {
    "iso:country":"GB",
    "wof:name":"NG8 2GE",
    "wof:placetype":"postalcode"
},
  "geometry": {"coordinates":[-1.23105982633121,52.95065307764764],"type":"Point"}
}