{
  "type": "Feature",
  "properties": {
    "iso:country":"GB",
    "wof:name":"G82 1JA",
    "wof:placetype":"postalcode"
},
  "geometry": {"coordinates":[-4.555484366559,55.94082429165647],"type":"Point"}
}