{
  "type": "Feature",
  "properties": {
    "iso:country": "GB",
    "wof:name": "EH54 8TA",
    "wof:placetype": "postalcode"
  },
  "geometry": {"coordinates":[-3.537615,55.91225],"type":"Point"}
}
