{
  "type": "Feature",
  "properties": {
    "iso:country":"GB",
    "wof:name":"EH54 8TA",
    "wof:placetype":"postalcode"
},
  "geometry": {"coordinates":[-3.53761517227152,55.9122496985037],"type":"Point"}
}