{
  "type": "Feature",
  "properties": {
    "iso:country":"GB",
    "wof:name":"LN8 6BU",
    "wof:placetype":"postalcode"
},
  "geometry": {"coordinates":[-0.14910349267096,53.44060615168152],"type":"Point"}
}