{
  "type": "Feature",
  "properties": {
    "iso:country":"GB",
    "wof:name":"WF4 2NW",
    "wof:placetype":"postalcode"
},
  "geometry": {"coordinates":[-1.49108650426267,53.62185291883302],"type":"Point"}
}