{
  "type": "Feature",
  "properties": {
    "date:inception_lower": "1999-12-01",
    "date:inception_upper": "1999-12-01",
    "iso:country": "GB",
    "wof:name": "SE16 5ED",
    "wof:placetype": "postalcode"
  },
  "geometry": {"coordinates":[-0.042481,51.506195],"type":"Point"}
}
