{
  "type": "Feature",
  "properties": {
    "iso:country":"GB",
    "wof:name":"BS4 4PP",
    "wof:placetype":"postalcode"
},
  "geometry": {"coordinates":[-2.55042023804659,51.43845645325928],"type":"Point"}
}