{
  "type": "Feature",
  "properties": {
    "date:inception_lower": "1980-01-01",
    "date:inception_upper": "1980-01-01",
    "iso:country": "GB",
    "wof:name": "DN5 7SW",
    "wof:placetype": "postalcode"
  },
  "geometry": {"coordinates":[-1.224576,53.498602],"type":"Point"}
}
