{
  "type": "Feature",
  "properties": {
    "iso:country": "GB",
    "wof:name": "DN5 7SW",
    "wof:placetype": "postalcode"
  },
  "geometry": {"coordinates":[-1.224576,53.498602],"type":"Point"}
}
