{
  "type": "Feature",
  "properties": {
    "date:inception_lower": "1983-01-01",
    "date:inception_upper": "1983-01-01",
    "iso:country": "GB",
    "wof:name": "PR6 8UE",
    "wof:placetype": "postalcode"
  },
  "geometry": {"coordinates":[-2.559063,53.693911],"type":"Point"}
}
