{
  "type": "Feature",
  "properties": {
    "iso:country":"GB",
    "wof:name":"PR6 8UE",
    "wof:placetype":"postalcode"
},
  "geometry": {"coordinates":[-2.55906261823323,53.69391071067189],"type":"Point"}
}