{
  "type": "Feature",
  "properties": {
    "iso:country":"GB",
    "wof:name":"IP6 9RN",
    "wof:placetype":"postalcode"
},
  "geometry": {"coordinates":[1.14509890891998,52.13029431413499],"type":"Point"}
}