{
  "type": "Feature",
  "properties": {
    "date:inception_lower": "1995-01-01",
    "date:inception_upper": "1995-01-01",
    "iso:country": "GB",
    "wof:name": "EX15 2JG",
    "wof:placetype": "postalcode"
  },
  "geometry": {"coordinates":[-3.34548,50.820135],"type":"Point"}
}
