{
  "type": "Feature",
  "properties": {
    "iso:country":"GB",
    "wof:name":"DN4 9SB",
    "wof:placetype":"postalcode"
},
  "geometry": {"coordinates":[-1.15125684835884,53.495299326251],"type":"Point"}
}