{
  "type": "Feature",
  "properties": {
    "date:inception_lower":"1981-06-01",
    "date:inception_upper":"1981-06-30",
    "iso:country":"GB",
    "wof:name":"DN4 9SB",
    "wof:placetype":"postalcode"
},
  "geometry": {"coordinates":[-1.151257,53.495299],"type":"Point"}
}