{
  "type": "Feature",
  "properties": {
    "iso:country":"GB",
    "wof:name":"DL13 4HE",
    "wof:placetype":"postalcode"
},
  "geometry": {"coordinates":[-1.81101193815527,54.7454985973092],"type":"Point"}
}