{
  "type": "Feature",
  "properties": {
    "iso:country":"GB",
    "wof:name":"TF7 5JF",
    "wof:placetype":"postalcode"
},
  "geometry": {"coordinates":[-2.47325014454641,52.63355145280853],"type":"Point"}
}