{
  "type": "Feature",
  "properties": {
    "iso:country":"GB",
    "wof:name":"HD8 0LX",
    "wof:placetype":"postalcode"
},
  "geometry": {"coordinates":[-1.69068145844442,53.63234084984338],"type":"Point"}
}