{
  "type": "Feature",
  "properties": {
    "iso:country": "GB",
    "wof:name": "HD8 0LX",
    "wof:placetype": "postalcode"
  },
  "geometry": {"coordinates":[-1.690681,53.632341],"type":"Point"}
}
