{
  "type": "Feature",
  "properties": {
    "date:inception_lower":"1980-01-01",
    "date:inception_upper":"1980-01-31",
    "iso:country":"GB",
    "wof:name":"HD8 0LX",
    "wof:placetype":"postalcode"
},
  "geometry": {"coordinates":[-1.690681,53.632341],"type":"Point"}
}