{
  "type": "Feature",
  "properties": {
    "iso:country":"GB",
    "wof:name":"LL20 7SB",
    "wof:placetype":"postalcode"
},
  "geometry": {"coordinates":[-3.08700498315356,52.9614522415824],"type":"Point"}
}