{
  "type": "Feature",
  "properties": {
    "iso:country": "GB",
    "wof:name": "LL20 7SB",
    "wof:placetype": "postalcode"
  },
  "geometry": {"coordinates":[-3.086958,52.961422],"type":"Point"}
}
