{
  "type": "Feature",
  "properties": {
    "iso:country":"GB",
    "wof:name":"PH2 7TQ",
    "wof:placetype":"postalcode"
},
  "geometry": {"coordinates":[-3.25112606109221,56.37748978673081],"type":"Point"}
}