{
  "type": "Feature",
  "properties": {
    "date:inception_lower": "1980-01-01",
    "date:inception_upper": "1980-01-01",
    "iso:country": "GB",
    "wof:name": "W9 2RE",
    "wof:placetype": "postalcode"
  },
  "geometry": {"coordinates":[-0.188353,51.5229],"type":"Point"}
}
