{
  "type": "Feature",
  "properties": {
    "iso:country": "GB",
    "wof:name": "EH46 7JJ",
    "wof:placetype": "postalcode"
  },
  "geometry": {"coordinates":[-3.348516,55.753024],"type":"Point"}
}
