{
  "type": "Feature",
  "properties": {
    "date:inception_lower": "1980-01-01",
    "date:inception_upper": "1980-01-01",
    "iso:country": "GB",
    "wof:name": "B6 6EH",
    "wof:placetype": "postalcode"
  },
  "geometry": {"coordinates":[-1.891377,52.505606],"type":"Point"}
}
