{
  "type": "Feature",
  "properties": {
    "iso:country": "GB",
    "wof:name": "B6 6EH",
    "wof:placetype": "postalcode"
  },
  "geometry": {"coordinates":[-1.891377,52.505606],"type":"Point"}
}
