{
  "type": "Feature",
  "properties": {
    "iso:country":"GB",
    "wof:name":"TW2 6PF",
    "wof:placetype":"postalcode"
},
  "geometry": {"coordinates":[-0.34837228544323,51.44435815430406],"type":"Point"}
}