{
  "type": "Feature",
  "properties": {
    "iso:country": "GB",
    "wof:name": "CO2 8JG",
    "wof:placetype": "postalcode"
  },
  "geometry": {"coordinates":[0.924149,51.881729],"type":"Point"}
}
