{
  "type": "Feature",
  "properties": {
    "iso:country":"GB",
    "wof:name":"W1F 7TS",
    "wof:placetype":"postalcode"
},
  "geometry": {"coordinates":[-0.1413416144322,51.51484451570799],"type":"Point"}
}