{
  "type": "Feature",
  "properties": {
    "iso:country":"GB",
    "wof:name":"W6 7LX",
    "wof:placetype":"postalcode"
},
  "geometry": {"coordinates":[-0.22181044023811,51.50141641508541],"type":"Point"}
}