{
  "type": "Feature",
  "properties": {
    "iso:country": "GB",
    "wof:name": "S66 7QQ",
    "wof:placetype": "postalcode"
  },
  "geometry": {"coordinates":[-1.170386,53.43965],"type":"Point"}
}
