{
  "type": "Feature",
  "properties": {
    "iso:country":"GB",
    "wof:name":"S66 7QQ",
    "wof:placetype":"postalcode"
},
  "geometry": {"coordinates":[-1.17038583747914,53.43964953815679],"type":"Point"}
}