{
  "type": "Feature",
  "properties": {
    "date:inception_lower":"1980-01-01",
    "date:inception_upper":"1980-01-31",
    "iso:country":"GB",
    "wof:name":"S66 7QQ",
    "wof:placetype":"postalcode"
},
  "geometry": {"coordinates":[-1.170386,53.43965],"type":"Point"}
}