{
  "type": "Feature",
  "properties": {
    "iso:country":"GB",
    "wof:name":"TW3 2DS",
    "wof:placetype":"postalcode"
},
  "geometry": {"coordinates":[-0.35762314902185,51.46285950368858],"type":"Point"}
}