{
  "type": "Feature",
  "properties": {
    "date:inception_lower": "1980-01-01",
    "date:inception_upper": "1980-01-01",
    "iso:country": "GB",
    "wof:name": "TW3 2DS",
    "wof:placetype": "postalcode"
  },
  "geometry": {"coordinates":[-0.357623,51.462859],"type":"Point"}
}
