{
  "type": "Feature",
  "properties": {
    "date:inception_lower": "1995-12-01",
    "date:inception_upper": "1995-12-01",
    "iso:country": "GB",
    "wof:name": "WA8 6UA",
    "wof:placetype": "postalcode"
  },
  "geometry": {"coordinates":[-2.723698,53.367409],"type":"Point"}
}
