{
  "type": "Feature",
  "properties": {
    "iso:country":"GB",
    "wof:name":"WA8 6UA",
    "wof:placetype":"postalcode"
},
  "geometry": {"coordinates":[-2.72369775847794,53.36740893695117],"type":"Point"}
}