{
  "type": "Feature",
  "properties": {
    "iso:country":"GB",
    "wof:name":"NW1 4RG",
    "wof:placetype":"postalcode"
},
  "geometry": {"coordinates":[-0.16211849676387,51.52680817599401],"type":"Point"}
}