{
  "type": "Feature",
  "properties": {
    "iso:country":"GB",
    "wof:name":"PL13 1JY",
    "wof:placetype":"postalcode"
},
  "geometry": {"coordinates":[-4.44659849670837,50.35859785488273],"type":"Point"}
}