{
  "type": "Feature",
  "properties": {
    "iso:country":"GB",
    "wof:name":"PE11 4LB",
    "wof:placetype":"postalcode"
},
  "geometry": {"coordinates":[-0.24776158651151,52.84528495432141],"type":"Point"}
}