{
  "type": "Feature",
  "properties": {
    "date:inception_lower": "2014-11-01",
    "date:inception_upper": "2014-11-01",
    "iso:country": "GB",
    "wof:name": "CH3 5HZ",
    "wof:placetype": "postalcode"
  },
  "geometry": {"coordinates":[-2.852536,53.197034],"type":"Point"}
}
