{
  "type": "Feature",
  "properties": {
    "iso:country": "GB",
    "wof:name": "CH3 5HZ",
    "wof:placetype": "postalcode"
  },
  "geometry": {"coordinates":[-2.852536,53.197034],"type":"Point"}
}
