{
  "type": "Feature",
  "properties": {
    "date:inception_lower": "1980-01-01",
    "date:inception_upper": "1980-01-01",
    "iso:country": "GB",
    "wof:name": "LE3 8LP",
    "wof:placetype": "postalcode"
  },
  "geometry": {"coordinates":[-1.199114,52.642383],"type":"Point"}
}
