{
  "type": "Feature",
  "properties": {
    "iso:country": "GB",
    "wof:name": "DN21 1ZR",
    "wof:placetype": "postalcode"
  },
  "geometry": {"coordinates":[-0.758165,53.406703],"type":"Point"}
}
