{
  "type": "Feature",
  "properties": {
    "date:inception_lower": "1994-10-01",
    "date:inception_upper": "1994-10-01",
    "iso:country": "GB",
    "wof:name": "AB22 8PS",
    "wof:placetype": "postalcode"
  },
  "geometry": {"coordinates":[-2.1232,57.200894],"type":"Point"}
}
