{
  "type": "Feature",
  "properties": {
    "iso:country":"GB",
    "wof:name":"AB22 8PS",
    "wof:placetype":"postalcode"
},
  "geometry": {"coordinates":[-2.12320005414126,57.20089351256525],"type":"Point"}
}