{
  "type": "Feature",
  "properties": {
    "iso:country": "GB",
    "wof:name": "AB22 8PS",
    "wof:placetype": "postalcode"
  },
  "geometry": {"coordinates":[-2.1232,57.200894],"type":"Point"}
}
