{
  "type": "Feature",
  "properties": {
    "iso:country":"GB",
    "wof:name":"OX12 7PP",
    "wof:placetype":"postalcode"
},
  "geometry": {"coordinates":[-1.41854265110495,51.61114437049691],"type":"Point"}
}