{
  "type": "Feature",
  "properties": {
    "iso:country": "GB",
    "wof:name": "SK9 3DP",
    "wof:placetype": "postalcode"
  },
  "geometry": {"coordinates":[-2.218107,53.345935],"type":"Point"}
}
