{
  "type": "Feature",
  "properties": {
    "iso:country":"GB",
    "wof:name":"SK9 3DP",
    "wof:placetype":"postalcode"
},
  "geometry": {"coordinates":[-2.21810669488328,53.34593519561397],"type":"Point"}
}