{
  "type": "Feature",
  "properties": {
    "iso:country": "GB",
    "wof:name": "TD7 4JP",
    "wof:placetype": "postalcode"
  },
  "geometry": {"coordinates":[-2.836433,55.55492],"type":"Point"}
}
