{
  "type": "Feature",
  "properties": {
    "iso:country":"GB",
    "wof:name":"GL3 3BD",
    "wof:placetype":"postalcode"
},
  "geometry": {"coordinates":[-2.17055155199066,51.85046247366309],"type":"Point"}
}