{
  "type": "Feature",
  "properties": {
    "iso:country": "GB",
    "wof:name": "GL3 3BD",
    "wof:placetype": "postalcode"
  },
  "geometry": {"coordinates":[-2.170561,51.85046],"type":"Point"}
}
