{
  "type": "Feature",
  "properties": {
    "iso:country":"GB",
    "wof:name":"BN8 4NN",
    "wof:placetype":"postalcode"
},
  "geometry": {"coordinates":[0.01477270759102,50.97082142611384],"type":"Point"}
}