{
  "type": "Feature",
  "properties": {
    "date:inception_lower": "1981-06-01",
    "date:inception_upper": "1981-06-01",
    "iso:country": "GB",
    "wof:name": "BN8 4NN",
    "wof:placetype": "postalcode"
  },
  "geometry": {"coordinates":[0.014773,50.970821],"type":"Point"}
}
