{
  "type": "Feature",
  "properties": {
    "iso:country":"GB",
    "wof:name":"G66 4DZ",
    "wof:placetype":"postalcode"
},
  "geometry": {"coordinates":[-4.1684698085779,55.92358630695898],"type":"Point"}
}