{
  "type": "Feature",
  "properties": {
    "iso:country":"GB",
    "wof:name":"SN4 9BD",
    "wof:placetype":"postalcode"
},
  "geometry": {"coordinates":[-1.78559172243715,51.53603294791538],"type":"Point"}
}