{
  "type": "Feature",
  "properties": {
    "iso:country":"GB",
    "wof:name":"EH3 9DH",
    "wof:placetype":"postalcode"
},
  "geometry": {"coordinates":[-3.20041023161082,55.94550718876133],"type":"Point"}
}