{
  "type": "Feature",
  "properties": {
    "iso:country": "GB",
    "wof:name": "LL11 6BB",
    "wof:placetype": "postalcode"
  },
  "geometry": {"coordinates":[-3.041249,53.073881],"type":"Point"}
}
