{
  "type": "Feature",
  "properties": {
    "iso:country":"GB",
    "wof:name":"EX22 7JJ",
    "wof:placetype":"postalcode"
},
  "geometry": {"coordinates":[-4.38554770530606,50.85356729460613],"type":"Point"}
}