{
  "type": "Feature",
  "properties": {
    "iso:country":"GB",
    "wof:name":"LU6 2AL",
    "wof:placetype":"postalcode"
},
  "geometry": {"coordinates":[-0.54867525547648,51.88163099761885],"type":"Point"}
}