{
  "type": "Feature",
  "properties": {
    "iso:country": "GB",
    "wof:name": "YO18 8EW",
    "wof:placetype": "postalcode"
  },
  "geometry": {"coordinates":[-0.864932,54.342257],"type":"Point"}
}
