{
  "type": "Feature",
  "properties": {
    "iso:country":"GB",
    "wof:name":"YO18 8EW",
    "wof:placetype":"postalcode"
},
  "geometry": {"coordinates":[-0.86493171418517,54.34225651031971],"type":"Point"}
}