{
  "type": "Feature",
  "properties": {
    "iso:country":"GB",
    "wof:name":"YO7 1DN",
    "wof:placetype":"postalcode"
},
  "geometry": {"coordinates":[-1.33200439618856,54.23457041140222],"type":"Point"}
}