{
  "type": "Feature",
  "properties": {
    "iso:country": "GB",
    "wof:name": "DE15 0JX",
    "wof:placetype": "postalcode"
  },
  "geometry": {"coordinates":[-1.608714,52.807236],"type":"Point"}
}
