{
  "type": "Feature",
  "properties": {
    "iso:country": "GB",
    "wof:name": "CF14 1EH",
    "wof:placetype": "postalcode"
  },
  "geometry": {"coordinates":[-3.219143,51.511071],"type":"Point"}
}
