{
  "type": "Feature",
  "properties": {
    "date:inception_lower": "2013-05-01",
    "date:inception_upper": "2013-05-01",
    "iso:country": "GB",
    "wof:name": "SL5 9GG",
    "wof:placetype": "postalcode"
  },
  "geometry": {"coordinates":[-0.674384,51.397188],"type":"Point"}
}
