{
  "type": "Feature",
  "properties": {
    "iso:country":"GB",
    "wof:name":"B44 0JU",
    "wof:placetype":"postalcode"
},
  "geometry": {"coordinates":[-1.87433551706332,52.55059244446653],"type":"Point"}
}