{
  "type": "Feature",
  "properties": {
    "iso:country": "GB",
    "wof:name": "LA23 1PT",
    "wof:placetype": "postalcode"
  },
  "geometry": {"coordinates":[-2.912959,54.386854],"type":"Point"}
}
