{
  "type": "Feature",
  "properties": {
    "iso:country":"GB",
    "wof:name":"GU34 3QW",
    "wof:placetype":"postalcode"
},
  "geometry": {"coordinates":[-1.00022015428609,51.08411247997759],"type":"Point"}
}