{
  "type": "Feature",
  "properties": {
    "iso:country":"GB",
    "wof:name":"DT4 0PT",
    "wof:placetype":"postalcode"
},
  "geometry": {"coordinates":[-2.47870454767918,50.6127241410201],"type":"Point"}
}