{
  "type": "Feature",
  "properties": {
    "iso:country":"GB",
    "wof:name":"NP4 0JG",
    "wof:placetype":"postalcode"
},
  "geometry": {"coordinates":[-3.00644700707351,51.73164827339149],"type":"Point"}
}