{
  "type": "Feature",
  "properties": {
    "iso:country":"GB",
    "wof:name":"S60 5JU",
    "wof:placetype":"postalcode"
},
  "geometry": {"coordinates":[-1.35871593398873,53.39841791270138],"type":"Point"}
}