{
  "type": "Feature",
  "properties": {
    "iso:country":"GB",
    "wof:name":"E13 0BU",
    "wof:placetype":"postalcode"
},
  "geometry": {"coordinates":[0.0223029575256,51.52889937519581],"type":"Point"}
}