{
  "type": "Feature",
  "properties": {
    "iso:country":"GB",
    "wof:name":"GU46 6XH",
    "wof:placetype":"postalcode"
},
  "geometry": {"coordinates":[-0.82251252377236,51.34123883580493],"type":"Point"}
}