{
  "type": "Feature",
  "properties": {
    "iso:country": "GB",
    "wof:name": "GU46 6XH",
    "wof:placetype": "postalcode"
  },
  "geometry": {"coordinates":[-0.822512,51.341239],"type":"Point"}
}
