{
  "type": "Feature",
  "properties": {
    "iso:country": "GB",
    "wof:name": "M14 6GF",
    "wof:placetype": "postalcode"
  },
  "geometry": {"coordinates":[-2.220682,53.443025],"type":"Point"}
}
