{
  "type": "Feature",
  "properties": {
    "iso:country":"GB",
    "wof:name":"M14 6GF",
    "wof:placetype":"postalcode"
},
  "geometry": {"coordinates":[-2.22068181081129,53.44302514584871],"type":"Point"}
}