{
  "type": "Feature",
  "properties": {
    "iso:country":"GB",
    "wof:name":"EX10 9DE",
    "wof:placetype":"postalcode"
},
  "geometry": {"coordinates":[-3.23059798085578,50.68871169281476],"type":"Point"}
}