{
  "type": "Feature",
  "properties": {
    "date:inception_lower":"1998-12-01",
    "date:inception_upper":"1998-12-31",
    "iso:country":"GB",
    "wof:name":"EX10 9DE",
    "wof:placetype":"postalcode"
},
  "geometry": {"coordinates":[-3.230598,50.688712],"type":"Point"}
}