{
  "type": "Feature",
  "properties": {
    "date:inception_lower": "2022-08-01",
    "date:inception_upper": "2022-08-01",
    "iso:country": "GB",
    "wof:name": "RH19 4TY",
    "wof:placetype": "postalcode"
  },
  "geometry": {"coordinates":[-0.046376,51.07563],"type":"Point"}
}
