{
  "type": "Feature",
  "properties": {
    "iso:country":"GB",
    "wof:name":"L32 0XE",
    "wof:placetype":"postalcode"
},
  "geometry": {"coordinates":[-2.89937664919144,53.47971625488685],"type":"Point"}
}