{
  "type": "Feature",
  "properties": {
    "iso:country": "GB",
    "wof:name": "LE8 9DL",
    "wof:placetype": "postalcode"
  },
  "geometry": {"coordinates":[-1.001503,52.575543],"type":"Point"}
}
