{
  "type": "Feature",
  "properties": {
    "iso:country":"GB",
    "wof:name":"LE8 9DL",
    "wof:placetype":"postalcode"
},
  "geometry": {"coordinates":[-1.00150266267451,52.57554259959571],"type":"Point"}
}