{
  "type": "Feature",
  "properties": {
    "iso:country":"GB",
    "wof:name":"TS7 9PD",
    "wof:placetype":"postalcode"
},
  "geometry": {"coordinates":[-1.18127477165818,54.55001404980236],"type":"Point"}
}