{
  "type": "Feature",
  "properties": {
    "iso:country": "GB",
    "wof:name": "CM22 7RN",
    "wof:placetype": "postalcode"
  },
  "geometry": {"coordinates":[0.189886,51.831273],"type":"Point"}
}
