{
  "type": "Feature",
  "properties": {
    "date:inception_lower": "1980-01-01",
    "date:inception_upper": "1980-01-01",
    "iso:country": "GB",
    "wof:name": "OX3 7PF",
    "wof:placetype": "postalcode"
  },
  "geometry": {"coordinates":[-1.215878,51.756972],"type":"Point"}
}
