{
  "type": "Feature",
  "properties": {
    "iso:country": "GB",
    "wof:name": "YO23 2UZ",
    "wof:placetype": "postalcode"
  },
  "geometry": {"coordinates":[-1.124869,53.892308],"type":"Point"}
}
