{
  "type": "Feature",
  "properties": {
    "iso:country":"GB",
    "wof:name":"YO23 2UZ",
    "wof:placetype":"postalcode"
},
  "geometry": {"coordinates":[-1.1328084774305,53.89028892462074],"type":"Point"}
}