{
  "type": "Feature",
  "properties": {
    "iso:country": "GB",
    "wof:name": "TW16 5PF",
    "wof:placetype": "postalcode"
  },
  "geometry": {"coordinates":[-0.397446,51.409699],"type":"Point"}
}
