{
  "type": "Feature",
  "properties": {
    "date:inception_lower": "1980-01-01",
    "date:inception_upper": "1980-01-01",
    "iso:country": "GB",
    "wof:name": "BN2 4EJ",
    "wof:placetype": "postalcode"
  },
  "geometry": {"coordinates":[-0.120243,50.83801],"type":"Point"}
}
