{
  "type": "Feature",
  "properties": {
    "iso:country":"GB",
    "wof:name":"WA7 6HL",
    "wof:placetype":"postalcode"
},
  "geometry": {"coordinates":[-2.66039178089482,53.32623881435048],"type":"Point"}
}