{
  "type": "Feature",
  "properties": {
    "iso:country":"GB",
    "wof:name":"BS24 6SQ",
    "wof:placetype":"postalcode"
},
  "geometry": {"coordinates":[-2.84072898007928,51.37459085301466],"type":"Point"}
}