{
  "type": "Feature",
  "properties": {
    "iso:country": "GB",
    "wof:name": "BS24 6SQ",
    "wof:placetype": "postalcode"
  },
  "geometry": {"coordinates":[-2.84084,51.374884],"type":"Point"}
}
