{
  "type": "Feature",
  "properties": {
    "iso:country": "GB",
    "wof:name": "LL53 7LF",
    "wof:placetype": "postalcode"
  },
  "geometry": {"coordinates":[-4.519401,52.810616],"type":"Point"}
}
