{
  "type": "Feature",
  "properties": {
    "iso:country":"GB",
    "wof:name":"LL53 7LF",
    "wof:placetype":"postalcode"
},
  "geometry": {"coordinates":[-4.51940123767776,52.81061622273325],"type":"Point"}
}