{
  "type": "Feature",
  "properties": {
    "iso:country":"GB",
    "wof:name":"RM3 7DJ",
    "wof:placetype":"postalcode"
},
  "geometry": {"coordinates":[0.204291324359,51.59922697039806],"type":"Point"}
}