{
  "type": "Feature",
  "properties": {
    "iso:country": "GB",
    "wof:name": "RM3 7DJ",
    "wof:placetype": "postalcode"
  },
  "geometry": {"coordinates":[0.204291,51.599227],"type":"Point"}
}
