{
  "type": "Feature",
  "properties": {
    "iso:country":"GB",
    "wof:name":"IP9 2DD",
    "wof:placetype":"postalcode"
},
  "geometry": {"coordinates":[1.07487223248172,51.98900322348161],"type":"Point"}
}