{
  "type": "Feature",
  "properties": {
    "iso:country": "GB",
    "wof:name": "IP9 2DD",
    "wof:placetype": "postalcode"
  },
  "geometry": {"coordinates":[1.074872,51.989003],"type":"Point"}
}
