{
  "type": "Feature",
  "properties": {
    "iso:country": "GB",
    "wof:name": "PO9 3SP",
    "wof:placetype": "postalcode"
  },
  "geometry": {"coordinates":[-1.007573,50.864865],"type":"Point"}
}
