{
  "type": "Feature",
  "properties": {
    "iso:country":"GB",
    "wof:name":"S11 8BA",
    "wof:placetype":"postalcode"
},
  "geometry": {"coordinates":[-1.48324870056966,53.36807345209073],"type":"Point"}
}