{
  "type": "Feature",
  "properties": {
    "iso:country":"GB",
    "wof:name":"NE40 3HB",
    "wof:placetype":"postalcode"
},
  "geometry": {"coordinates":[-1.7526285516454,54.96821137407697],"type":"Point"}
}