{
  "type": "Feature",
  "properties": {
    "iso:country":"GB",
    "wof:name":"LL53 8UA",
    "wof:placetype":"postalcode"
},
  "geometry": {"coordinates":[-4.57165376822437,52.90709208258547],"type":"Point"}
}