{
  "type": "Feature",
  "properties": {
    "iso:country":"GB",
    "wof:name":"LL63 5UL",
    "wof:placetype":"postalcode"
},
  "geometry": {"coordinates":[-4.45711239869033,53.25180926379561],"type":"Point"}
}