{
  "type": "Feature",
  "properties": {
    "iso:country": "GB",
    "wof:name": "TA3 5AP",
    "wof:placetype": "postalcode"
  },
  "geometry": {"coordinates":[-2.972523,51.049339],"type":"Point"}
}
