{
  "type": "Feature",
  "properties": {
    "iso:country":"GB",
    "wof:name":"TA3 5AP",
    "wof:placetype":"postalcode"
},
  "geometry": {"coordinates":[-2.97252285032126,51.04933948780297],"type":"Point"}
}