{
  "type": "Feature",
  "properties": {
    "date:inception_lower":"1980-01-01",
    "date:inception_upper":"1980-01-31",
    "iso:country":"GB",
    "wof:name":"TA3 5AP",
    "wof:placetype":"postalcode"
},
  "geometry": {"coordinates":[-2.972523,51.049339],"type":"Point"}
}