{
  "type": "Feature",
  "properties": {
    "date:inception_lower":"1990-02-01",
    "date:inception_upper":"1990-02-28",
    "iso:country":"GB",
    "wof:name":"S42 7NW",
    "wof:placetype":"postalcode"
},
  "geometry": {"coordinates":[-1.465397,53.224821],"type":"Point"}
}