{
  "type": "Feature",
  "properties": {
    "iso:country":"GB",
    "wof:name":"S42 7NW",
    "wof:placetype":"postalcode"
},
  "geometry": {"coordinates":[-1.46539705583178,53.22482086993089],"type":"Point"}
}