{
  "type": "Feature",
  "properties": {
    "date:inception_lower": "2021-09-01",
    "date:inception_upper": "2021-09-01",
    "iso:country": "GB",
    "wof:name": "SL1 3HZ",
    "wof:placetype": "postalcode"
  },
  "geometry": {"coordinates":[-0.602603,51.510952],"type":"Point"}
}
