{
  "type": "Feature",
  "properties": {
    "date:inception_lower":"1991-01-01",
    "date:inception_upper":"1991-01-31",
    "iso:country":"GB",
    "wof:name":"SL2 1UL",
    "wof:placetype":"postalcode"
},
  "geometry": {"coordinates":[-0.621508,51.53307],"type":"Point"}
}