{
  "type": "Feature",
  "properties": {
    "iso:country": "GB",
    "wof:name": "SL2 1UL",
    "wof:placetype": "postalcode"
  },
  "geometry": {"coordinates":[-0.621508,51.53307],"type":"Point"}
}
