{
  "type": "Feature",
  "properties": {
    "date:inception_lower": "1980-01-01",
    "date:inception_upper": "1980-01-01",
    "iso:country": "GB",
    "wof:name": "DN21 4TP",
    "wof:placetype": "postalcode"
  },
  "geometry": {"coordinates":[-0.520294,53.440549],"type":"Point"}
}
