{
  "type": "Feature",
  "properties": {
    "iso:country":"GB",
    "wof:name":"SN14 0QA",
    "wof:placetype":"postalcode"
},
  "geometry": {"coordinates":[-2.14395061919937,51.45282469125549],"type":"Point"}
}