{
  "type": "Feature",
  "properties": {
    "date:inception_lower":"1980-01-01",
    "date:inception_upper":"1980-01-31",
    "iso:country":"GB",
    "wof:name":"SN14 0QA",
    "wof:placetype":"postalcode"
},
  "geometry": {"coordinates":[-2.143951,51.452825],"type":"Point"}
}