{
  "type": "Feature",
  "properties": {
    "iso:country":"GB",
    "wof:name":"LL49 9HA",
    "wof:placetype":"postalcode"
},
  "geometry": {"coordinates":[-4.13262043496968,52.92767553720419],"type":"Point"}
}