{
  "type": "Feature",
  "properties": {
    "iso:country": "GB",
    "wof:name": "LL49 9HA",
    "wof:placetype": "postalcode"
  },
  "geometry": {"coordinates":[-4.132627,52.927691],"type":"Point"}
}
