{
  "type": "Feature",
  "properties": {
    "date:inception_lower": "1980-01-01",
    "date:inception_upper": "1980-01-01",
    "iso:country": "GB",
    "wof:name": "EX23 9AX",
    "wof:placetype": "postalcode"
  },
  "geometry": {"coordinates":[-4.519488,50.832308],"type":"Point"}
}
