{
  "type": "Feature",
  "properties": {
    "iso:country": "GB",
    "wof:name": "HX7 6AU",
    "wof:placetype": "postalcode"
  },
  "geometry": {"coordinates":[-2.017338,53.741621],"type":"Point"}
}
