{
  "type": "Feature",
  "properties": {
    "date:inception_lower": "2005-05-01",
    "date:inception_upper": "2005-05-01",
    "iso:country": "GB",
    "wof:name": "HX7 6AU",
    "wof:placetype": "postalcode"
  },
  "geometry": {"coordinates":[-2.017338,53.741621],"type":"Point"}
}
