{
  "type": "Feature",
  "properties": {
    "iso:country":"GB",
    "wof:name":"HX7 6AU",
    "wof:placetype":"postalcode"
},
  "geometry": {"coordinates":[-2.0173377633374,53.74162060086589],"type":"Point"}
}