{
  "type": "Feature",
  "properties": {
    "iso:country":"GB",
    "wof:name":"CA7 4LA",
    "wof:placetype":"postalcode"
},
  "geometry": {"coordinates":[-3.41373394885326,54.83269500450202],"type":"Point"}
}