{
  "type": "Feature",
  "properties": {
    "iso:country": "GB",
    "wof:name": "CA7 4LA",
    "wof:placetype": "postalcode"
  },
  "geometry": {"coordinates":[-3.413734,54.832695],"type":"Point"}
}
