{
  "type": "Feature",
  "properties": {
    "iso:country":"GB",
    "wof:name":"B46 2QU",
    "wof:placetype":"postalcode"
},
  "geometry": {"coordinates":[-1.64701472939855,52.48973902012803],"type":"Point"}
}