{
  "type": "Feature",
  "properties": {
    "iso:country": "GB",
    "wof:name": "B46 2QU",
    "wof:placetype": "postalcode"
  },
  "geometry": {"coordinates":[-1.647015,52.489739],"type":"Point"}
}
