{
  "type": "Feature",
  "properties": {
    "iso:country":"GB",
    "wof:name":"WA4 6BP",
    "wof:placetype":"postalcode"
},
  "geometry": {"coordinates":[-2.59187566673393,53.37451764371926],"type":"Point"}
}