{
  "type": "Feature",
  "properties": {
    "iso:country": "GB",
    "wof:name": "DG7 3XW",
    "wof:placetype": "postalcode"
  },
  "geometry": {"coordinates":[-4.176469,55.1039],"type":"Point"}
}
