{
  "type": "Feature",
  "properties": {
    "iso:country": "GB",
    "wof:name": "IG7 5JU",
    "wof:placetype": "postalcode"
  },
  "geometry": {"coordinates":[0.089083,51.610075],"type":"Point"}
}
