{
  "type": "Feature",
  "properties": {
    "iso:country":"GB",
    "wof:name":"IG7 5JU",
    "wof:placetype":"postalcode"
},
  "geometry": {"coordinates":[0.089082869554,51.61007523098517],"type":"Point"}
}