{
  "type": "Feature",
  "properties": {
    "iso:country": "GB",
    "wof:name": "ST5 5DB",
    "wof:placetype": "postalcode"
  },
  "geometry": {"coordinates":[-2.306294,52.959683],"type":"Point"}
}
