{
  "type": "Feature",
  "properties": {
    "iso:country":"GB",
    "wof:name":"DG8 6RR",
    "wof:placetype":"postalcode"
},
  "geometry": {"coordinates":[-4.60020135596281,55.04889760353664],"type":"Point"}
}