{
  "type": "Feature",
  "properties": {
    "iso:country":"GB",
    "wof:name":"WF8 3JW",
    "wof:placetype":"postalcode"
},
  "geometry": {"coordinates":[-1.26343214471992,53.64941397027979],"type":"Point"}
}