{
  "type": "Feature",
  "properties": {
    "iso:country": "GB",
    "wof:name": "WF8 3JW",
    "wof:placetype": "postalcode"
  },
  "geometry": {"coordinates":[-1.263435,53.649433],"type":"Point"}
}
