{
  "type": "Feature",
  "properties": {
    "date:inception_lower": "2021-03-01",
    "date:inception_upper": "2021-03-01",
    "iso:country": "GB",
    "wof:name": "CV37 8YU",
    "wof:placetype": "postalcode"
  },
  "geometry": {"coordinates":[-1.758833,52.116101],"type":"Point"}
}
