{
  "type": "Feature",
  "properties": {
    "iso:country":"GB",
    "wof:name":"TD1 1BG",
    "wof:placetype":"postalcode"
},
  "geometry": {"coordinates":[-2.80744133354487,55.61608182840203],"type":"Point"}
}