{
  "type": "Feature",
  "properties": {
    "date:inception_lower": "1980-01-01",
    "date:inception_upper": "1980-01-01",
    "iso:country": "GB",
    "wof:name": "L36 1UA",
    "wof:placetype": "postalcode"
  },
  "geometry": {"coordinates":[-2.823461,53.421306],"type":"Point"}
}
