{
  "type": "Feature",
  "properties": {
    "iso:country":"GB",
    "wof:name":"TN15 0BS",
    "wof:placetype":"postalcode"
},
  "geometry": {"coordinates":[0.21808309987086,51.29311362219525],"type":"Point"}
}