{
  "type": "Feature",
  "properties": {
    "date:inception_lower": "1980-01-01",
    "date:inception_upper": "1980-01-01",
    "iso:country": "GB",
    "wof:name": "TN15 0BS",
    "wof:placetype": "postalcode"
  },
  "geometry": {"coordinates":[0.218083,51.293114],"type":"Point"}
}
