{
  "type": "Feature",
  "properties": {
    "iso:country": "GB",
    "wof:name": "TN15 0BS",
    "wof:placetype": "postalcode"
  },
  "geometry": {"coordinates":[0.218083,51.293114],"type":"Point"}
}
