{
  "type": "Feature",
  "properties": {
    "date:inception_lower": "1990-02-01",
    "date:inception_upper": "1990-02-01",
    "iso:country": "GB",
    "wof:name": "BN13 3QR",
    "wof:placetype": "postalcode"
  },
  "geometry": {"coordinates":[-0.429117,50.828044],"type":"Point"}
}
