{
  "type": "Feature",
  "properties": {
    "iso:country":"GB",
    "wof:name":"BN3 2JQ",
    "wof:placetype":"postalcode"
},
  "geometry": {"coordinates":[-0.16287070883793,50.82631423586822],"type":"Point"}
}