{
  "type": "Feature",
  "properties": {
    "iso:country":"GB",
    "wof:name":"M38 9TQ",
    "wof:placetype":"postalcode"
},
  "geometry": {"coordinates":[-2.43228630501709,53.53844352447811],"type":"Point"}
}