{
  "type": "Feature",
  "properties": {
    "date:inception_lower": "2017-10-01",
    "date:inception_upper": "2017-10-01",
    "iso:country": "GB",
    "wof:name": "DE12 7DJ",
    "wof:placetype": "postalcode"
  },
  "geometry": {"coordinates":[-1.5344,52.689284],"type":"Point"}
}
