{
  "type": "Feature",
  "properties": {
    "iso:country":"GB",
    "wof:name":"DD2 5EQ",
    "wof:placetype":"postalcode"
},
  "geometry": {"coordinates":[-3.11306090856497,56.45781800681023],"type":"Point"}
}