{
  "type": "Feature",
  "properties": {
    "date:inception_lower": "1980-01-01",
    "date:inception_upper": "1980-01-01",
    "iso:country": "GB",
    "wof:name": "TS19 7HY",
    "wof:placetype": "postalcode"
  },
  "geometry": {"coordinates":[-1.358183,54.572794],"type":"Point"}
}
