{
  "type": "Feature",
  "properties": {
    "iso:country":"GB",
    "wof:name":"DE7 6NY",
    "wof:placetype":"postalcode"
},
  "geometry": {"coordinates":[-1.35892234231589,52.97204185084559],"type":"Point"}
}