{
  "type": "Feature",
  "properties": {
    "date:inception_lower": "1987-04-01",
    "date:inception_upper": "1987-04-01",
    "iso:country": "GB",
    "wof:name": "DE7 6NY",
    "wof:placetype": "postalcode"
  },
  "geometry": {"coordinates":[-1.358922,52.972042],"type":"Point"}
}
