{
  "type": "Feature",
  "properties": {
    "iso:country": "GB",
    "wof:name": "DE7 6NY",
    "wof:placetype": "postalcode"
  },
  "geometry": {"coordinates":[-1.358922,52.972042],"type":"Point"}
}
