{
  "type": "Feature",
  "properties": {
    "iso:country":"GB",
    "wof:name":"NE4 8BW",
    "wof:placetype":"postalcode"
},
  "geometry": {"coordinates":[-1.65771031877174,54.97139626464172],"type":"Point"}
}