{
  "type": "Feature",
  "properties": {
    "iso:country": "GB",
    "wof:name": "CV23 9JY",
    "wof:placetype": "postalcode"
  },
  "geometry": {"coordinates":[-1.313003,52.334953],"type":"Point"}
}
