{
  "type": "Feature",
  "properties": {
    "iso:country":"GB",
    "wof:name":"SW6 3AF",
    "wof:placetype":"postalcode"
},
  "geometry": {"coordinates":[-0.19538671172938,51.470384408816],"type":"Point"}
}