{
  "type": "Feature",
  "properties": {
    "iso:country":"GB",
    "wof:name":"TQ13 9PQ",
    "wof:placetype":"postalcode"
},
  "geometry": {"coordinates":[-3.67062836308405,50.59414375461285],"type":"Point"}
}