{
  "type": "Feature",
  "properties": {
    "iso:country": "GB",
    "wof:name": "TQ13 9PQ",
    "wof:placetype": "postalcode"
  },
  "geometry": {"coordinates":[-3.670628,50.594144],"type":"Point"}
}
