{
  "type": "Feature",
  "properties": {
    "iso:country": "GB",
    "wof:name": "RG19 8XG",
    "wof:placetype": "postalcode"
  },
  "geometry": {"coordinates":[-1.299349,51.387025],"type":"Point"}
}
