{
  "type": "Feature",
  "properties": {
    "date:inception_lower":"1997-12-01",
    "date:inception_upper":"1997-12-31",
    "iso:country":"GB",
    "wof:name":"RG19 8XG",
    "wof:placetype":"postalcode"
},
  "geometry": {"coordinates":[-1.299349,51.387025],"type":"Point"}
}