{
  "type": "Feature",
  "properties": {
    "iso:country": "GB",
    "wof:name": "GU12 6EP",
    "wof:placetype": "postalcode"
  },
  "geometry": {"coordinates":[-0.717113,51.247215],"type":"Point"}
}
