{
  "type": "Feature",
  "properties": {
    "iso:country":"GB",
    "wof:name":"BA3 5FP",
    "wof:placetype":"postalcode"
},
  "geometry": {"coordinates":[-2.47016289649322,51.24422395539834],"type":"Point"}
}