{
  "type": "Feature",
  "properties": {
    "iso:country":"GB",
    "wof:name":"BH16 6BL",
    "wof:placetype":"postalcode"
},
  "geometry": {"coordinates":[-2.08294293258917,50.75907332796269],"type":"Point"}
}