{
  "type": "Feature",
  "properties": {
    "iso:country": "GB",
    "wof:name": "B78 3XL",
    "wof:placetype": "postalcode"
  },
  "geometry": {"coordinates":[-1.70522,52.619334],"type":"Point"}
}
