{
  "type": "Feature",
  "properties": {
    "iso:country":"GB",
    "wof:name":"B78 3XL",
    "wof:placetype":"postalcode"
},
  "geometry": {"coordinates":[-1.70521994623265,52.61933442310289],"type":"Point"}
}