{
  "type": "Feature",
  "properties": {
    "date:inception_lower": "1980-01-01",
    "date:inception_upper": "1980-01-01",
    "iso:country": "GB",
    "wof:name": "SG4 8EP",
    "wof:placetype": "postalcode"
  },
  "geometry": {"coordinates":[-0.30564,51.84637],"type":"Point"}
}
