{
  "type": "Feature",
  "properties": {
    "iso:country": "GB",
    "wof:name": "SG4 8EP",
    "wof:placetype": "postalcode"
  },
  "geometry": {"coordinates":[-0.30564,51.84637],"type":"Point"}
}
