{
  "type": "Feature",
  "properties": {
    "date:inception_lower": "2024-05-01",
    "date:inception_upper": "2024-05-01",
    "iso:country": "GB",
    "wof:name": "CF83 1BN",
    "wof:placetype": "postalcode"
  },
  "geometry": {"coordinates":[-3.220675,51.574432],"type":"Point"}
}
