{
  "type": "Feature",
  "properties": {
    "iso:country":"GB",
    "wof:name":"AB13 0JP",
    "wof:placetype":"postalcode"
},
  "geometry": {"coordinates":[-2.22249600338321,57.10640790144941],"type":"Point"}
}