{
  "type": "Feature",
  "properties": {
    "iso:country": "GB",
    "wof:name": "AB13 0JP",
    "wof:placetype": "postalcode"
  },
  "geometry": {"coordinates":[-2.222496,57.106408],"type":"Point"}
}
