{
  "type": "Feature",
  "properties": {
    "date:inception_lower": "1981-06-01",
    "date:inception_upper": "1981-06-01",
    "iso:country": "GB",
    "wof:name": "BB5 4HL",
    "wof:placetype": "postalcode"
  },
  "geometry": {"coordinates":[-2.390286,53.753677],"type":"Point"}
}
