{
  "type": "Feature",
  "properties": {
    "iso:country":"GB",
    "wof:name":"IV47 8SL",
    "wof:placetype":"postalcode"
},
  "geometry": {"coordinates":[-6.4105974131596,57.32649696581755],"type":"Point"}
}