{
  "type": "Feature",
  "properties": {
    "iso:country": "GB",
    "wof:name": "IV47 8SL",
    "wof:placetype": "postalcode"
  },
  "geometry": {"coordinates":[-6.410597,57.326497],"type":"Point"}
}
