{
  "type": "Feature",
  "properties": {
    "date:inception_lower": "1980-01-01",
    "date:inception_upper": "1980-01-01",
    "iso:country": "GB",
    "wof:name": "DN17 3TT",
    "wof:placetype": "postalcode"
  },
  "geometry": {"coordinates":[-0.657856,53.530285],"type":"Point"}
}
