{
  "type": "Feature",
  "properties": {
    "iso:country":"GB",
    "wof:name":"DN17 3TT",
    "wof:placetype":"postalcode"
},
  "geometry": {"coordinates":[-0.65785653443959,53.53028530383956],"type":"Point"}
}