{
  "type": "Feature",
  "properties": {
    "iso:country": "GB",
    "wof:name": "DN17 3TT",
    "wof:placetype": "postalcode"
  },
  "geometry": {"coordinates":[-0.657856,53.530285],"type":"Point"}
}
