{
  "type": "Feature",
  "properties": {
    "iso:country":"GB",
    "wof:name":"CB7 5JE",
    "wof:placetype":"postalcode"
},
  "geometry": {"coordinates":[0.34191218682701,52.33448084584544],"type":"Point"}
}