{
  "type": "Feature",
  "properties": {
    "date:inception_lower":"1995-12-01",
    "date:inception_upper":"1995-12-31",
    "iso:country":"GB",
    "wof:name":"KA11 1AF",
    "wof:placetype":"postalcode"
},
  "geometry": {"coordinates":[-4.64135,55.624774],"type":"Point"}
}