{
  "type": "Feature",
  "properties": {
    "iso:country": "GB",
    "wof:name": "KA11 1AF",
    "wof:placetype": "postalcode"
  },
  "geometry": {"coordinates":[-4.64135,55.624774],"type":"Point"}
}
