{
  "type": "Feature",
  "properties": {
    "iso:country":"GB",
    "wof:name":"KA11 1AF",
    "wof:placetype":"postalcode"
},
  "geometry": {"coordinates":[-4.6413498695387,55.6247740428766],"type":"Point"}
}