{
  "type": "Feature",
  "properties": {
    "iso:country": "GB",
    "wof:name": "NN8 4LP",
    "wof:placetype": "postalcode"
  },
  "geometry": {"coordinates":[-0.701003,52.303098],"type":"Point"}
}
