{
  "type": "Feature",
  "properties": {
    "iso:country":"GB",
    "wof:name":"WF9 3BP",
    "wof:placetype":"postalcode"
},
  "geometry": {"coordinates":[-1.3154187905882,53.59586383582909],"type":"Point"}
}