{
  "type": "Feature",
  "properties": {
    "iso:country":"GB",
    "wof:name":"SA71 5DS",
    "wof:placetype":"postalcode"
},
  "geometry": {"coordinates":[-4.95618818014362,51.62008306118053],"type":"Point"}
}