{
  "type": "Feature",
  "properties": {
    "iso:country": "GB",
    "wof:name": "SA71 5DS",
    "wof:placetype": "postalcode"
  },
  "geometry": {"coordinates":[-4.956124,51.620105],"type":"Point"}
}
