{
  "type": "Feature",
  "properties": {
    "iso:country":"GB",
    "wof:name":"G15 7TU",
    "wof:placetype":"postalcode"
},
  "geometry": {"coordinates":[-4.37112459454981,55.91146461423133],"type":"Point"}
}