{
  "type": "Feature",
  "properties": {
    "iso:country": "GB",
    "wof:name": "BR5 2FE",
    "wof:placetype": "postalcode"
  },
  "geometry": {"coordinates":[0.104598,51.406273],"type":"Point"}
}
