{
  "type": "Feature",
  "properties": {
    "date:inception_lower":"1980-01-01",
    "date:inception_upper":"1980-01-31",
    "iso:country":"GB",
    "wof:name":"OL16 2AU",
    "wof:placetype":"postalcode"
},
  "geometry": {"coordinates":[-2.144078,53.615367],"type":"Point"}
}