{
  "type": "Feature",
  "properties": {
    "iso:country":"GB",
    "wof:name":"OL16 2AU",
    "wof:placetype":"postalcode"
},
  "geometry": {"coordinates":[-2.14523905406329,53.61400078595003],"type":"Point"}
}