{
  "type": "Feature",
  "properties": {
    "date:inception_lower": "1980-01-01",
    "date:inception_upper": "1980-01-01",
    "iso:country": "GB",
    "wof:name": "CT11 7ET",
    "wof:placetype": "postalcode"
  },
  "geometry": {"coordinates":[1.427123,51.344697],"type":"Point"}
}
