{
  "type": "Feature",
  "properties": {
    "iso:country":"GB",
    "wof:name":"TS12 3DD",
    "wof:placetype":"postalcode"
},
  "geometry": {"coordinates":[-1.00422856299428,54.53137725392825],"type":"Point"}
}