{
  "type": "Feature",
  "properties": {
    "iso:country": "GB",
    "wof:name": "TS12 3DD",
    "wof:placetype": "postalcode"
  },
  "geometry": {"coordinates":[-1.004411,54.531487],"type":"Point"}
}
