{
  "type": "Feature",
  "properties": {
    "date:inception_lower": "1980-01-01",
    "date:inception_upper": "1980-01-01",
    "iso:country": "GB",
    "wof:name": "L13 9BZ",
    "wof:placetype": "postalcode"
  },
  "geometry": {"coordinates":[-2.929122,53.434221],"type":"Point"}
}
