{
  "type": "Feature",
  "properties": {
    "iso:country":"GB",
    "wof:name":"HP13 7SX",
    "wof:placetype":"postalcode"
},
  "geometry": {"coordinates":[-0.71928165379826,51.62826817941171],"type":"Point"}
}