{
  "type": "Feature",
  "properties": {
    "iso:country":"GB",
    "wof:name":"SE1 0QZ",
    "wof:placetype":"postalcode"
},
  "geometry": {"coordinates":[-0.10202288351638,51.5016972052526],"type":"Point"}
}