{
  "type": "Feature",
  "properties": {
    "iso:country":"GB",
    "wof:name":"E18 1LG",
    "wof:placetype":"postalcode"
},
  "geometry": {"coordinates":[0.03065757420397,51.5909122219101],"type":"Point"}
}