{
  "type": "Feature",
  "properties": {
    "date:inception_lower":"1999-06-01",
    "date:inception_upper":"1999-06-30",
    "iso:country":"GB",
    "wof:name":"CF24 3LA",
    "wof:placetype":"postalcode"
},
  "geometry": {"coordinates":[-3.165639,51.493038],"type":"Point"}
}