{
  "type": "Feature",
  "properties": {
    "iso:country":"GB",
    "wof:name":"DY3 1HX",
    "wof:placetype":"postalcode"
},
  "geometry": {"coordinates":[-2.11537062184953,52.5387717247151],"type":"Point"}
}