{
  "type": "Feature",
  "properties": {
    "iso:country":"GB",
    "wof:name":"LL30 2LQ",
    "wof:placetype":"postalcode"
},
  "geometry": {"coordinates":[-3.83440901734116,53.31650391735026],"type":"Point"}
}