{
  "type": "Feature",
  "properties": {
    "date:inception_lower": "1980-01-01",
    "date:inception_upper": "1980-01-01",
    "iso:country": "GB",
    "wof:name": "LS16 7BQ",
    "wof:placetype": "postalcode"
  },
  "geometry": {"coordinates":[-1.623221,53.84939],"type":"Point"}
}
