{
  "type": "Feature",
  "properties": {
    "iso:country": "GB",
    "wof:name": "LS16 7BQ",
    "wof:placetype": "postalcode"
  },
  "geometry": {"coordinates":[-1.623221,53.84939],"type":"Point"}
}
