{
  "type": "Feature",
  "properties": {
    "iso:country":"GB",
    "wof:name":"LS16 7BQ",
    "wof:placetype":"postalcode"
},
  "geometry": {"coordinates":[-1.62322132663194,53.84939005080557],"type":"Point"}
}