{
  "type": "Feature",
  "properties": {
    "iso:country":"GB",
    "wof:name":"TS7 8EA",
    "wof:placetype":"postalcode"
},
  "geometry": {"coordinates":[-1.19780137129437,54.52717159484578],"type":"Point"}
}