{
  "type": "Feature",
  "properties": {
    "iso:country": "GB",
    "wof:name": "SW4 0NF",
    "wof:placetype": "postalcode"
  },
  "geometry": {"coordinates":[-0.147656,51.466466],"type":"Point"}
}
