{
  "type": "Feature",
  "properties": {
    "iso:country":"GB",
    "wof:name":"NE6 5SY",
    "wof:placetype":"postalcode"
},
  "geometry": {"coordinates":[-1.57695048741486,54.99054370116496],"type":"Point"}
}