{
  "type": "Feature",
  "properties": {
    "iso:country":"GB",
    "wof:name":"PE30 4BD",
    "wof:placetype":"postalcode"
},
  "geometry": {"coordinates":[0.4260550150653,52.76073620229129],"type":"Point"}
}