{
  "type": "Feature",
  "properties": {
    "date:inception_lower": "1980-01-01",
    "date:inception_upper": "1980-01-01",
    "iso:country": "GB",
    "wof:name": "PE30 4BD",
    "wof:placetype": "postalcode"
  },
  "geometry": {"coordinates":[0.426055,52.760736],"type":"Point"}
}
