{
  "type": "Feature",
  "properties": {
    "iso:country": "GB",
    "wof:name": "PE30 4BD",
    "wof:placetype": "postalcode"
  },
  "geometry": {"coordinates":[0.426055,52.760736],"type":"Point"}
}
