{
  "type": "Feature",
  "properties": {
    "iso:country": "GB",
    "wof:name": "NN17 1DN",
    "wof:placetype": "postalcode"
  },
  "geometry": {"coordinates":[-0.685809,52.500491],"type":"Point"}
}
