{
  "type": "Feature",
  "properties": {
    "iso:country":"GB",
    "wof:name":"LL61 5TJ",
    "wof:placetype":"postalcode"
},
  "geometry": {"coordinates":[-4.20227273527282,53.22139565150653],"type":"Point"}
}