{
  "type": "Feature",
  "properties": {
    "iso:country": "GB",
    "wof:name": "CW11 4LA",
    "wof:placetype": "postalcode"
  },
  "geometry": {"coordinates":[-2.351123,53.143862],"type":"Point"}
}
