{
  "type": "Feature",
  "properties": {
    "iso:country":"GB",
    "wof:name":"SO16 3BG",
    "wof:placetype":"postalcode"
},
  "geometry": {"coordinates":[-1.38424061044085,50.93869735019081],"type":"Point"}
}