{
  "type": "Feature",
  "properties": {
    "date:inception_lower": "2021-09-01",
    "date:inception_upper": "2021-09-01",
    "iso:country": "GB",
    "wof:name": "PR5 6HT",
    "wof:placetype": "postalcode"
  },
  "geometry": {"coordinates":[-2.6555,53.722209],"type":"Point"}
}
