{
  "type": "Feature",
  "properties": {
    "iso:country":"GB",
    "wof:name":"L40 8HE",
    "wof:placetype":"postalcode"
},
  "geometry": {"coordinates":[-2.90049455938508,53.58222377054915],"type":"Point"}
}