{
  "type": "Feature",
  "properties": {
    "iso:country":"GB",
    "wof:name":"RM3 7GQ",
    "wof:placetype":"postalcode"
},
  "geometry": {"coordinates":[0.21001203644177,51.60968594641005],"type":"Point"}
}