{
  "type": "Feature",
  "properties": {
    "date:inception_lower": "2013-12-01",
    "date:inception_upper": "2013-12-01",
    "iso:country": "GB",
    "wof:name": "RM3 7GQ",
    "wof:placetype": "postalcode"
  },
  "geometry": {"coordinates":[0.210012,51.609686],"type":"Point"}
}
