{
  "type": "Feature",
  "properties": {
    "date:inception_lower": "1992-01-01",
    "date:inception_upper": "1992-01-01",
    "iso:country": "GB",
    "wof:name": "PE2 7AD",
    "wof:placetype": "postalcode"
  },
  "geometry": {"coordinates":[-0.268394,52.558694],"type":"Point"}
}
