{
  "type": "Feature",
  "properties": {
    "iso:country":"GB",
    "wof:name":"PE2 7AD",
    "wof:placetype":"postalcode"
},
  "geometry": {"coordinates":[-0.26839413537976,52.55869427672033],"type":"Point"}
}