{
  "type": "Feature",
  "properties": {
    "iso:country":"GB",
    "wof:name":"SP4 7PF",
    "wof:placetype":"postalcode"
},
  "geometry": {"coordinates":[-1.76846267912469,51.16828453037645],"type":"Point"}
}