{
  "type": "Feature",
  "properties": {
    "date:inception_lower": "1980-01-01",
    "date:inception_upper": "1980-01-01",
    "iso:country": "GB",
    "wof:name": "IP13 9LZ",
    "wof:placetype": "postalcode"
  },
  "geometry": {"coordinates":[1.374142,52.194706],"type":"Point"}
}
