{
  "type": "Feature",
  "properties": {
    "iso:country":"GB",
    "wof:name":"LE7 9QW",
    "wof:placetype":"postalcode"
},
  "geometry": {"coordinates":[-1.04256571292461,52.63536010592356],"type":"Point"}
}