{
  "type": "Feature",
  "properties": {
    "date:inception_lower":"1990-02-01",
    "date:inception_upper":"1990-02-28",
    "iso:country":"GB",
    "wof:name":"LE7 9QW",
    "wof:placetype":"postalcode"
},
  "geometry": {"coordinates":[-1.042566,52.63536],"type":"Point"}
}