{
  "type": "Feature",
  "properties": {
    "date:inception_lower": "2000-06-01",
    "date:inception_upper": "2000-06-01",
    "iso:country": "GB",
    "wof:name": "EH47 7RB",
    "wof:placetype": "postalcode"
  },
  "geometry": {"coordinates":[-3.608731,55.871263],"type":"Point"}
}
