{
  "type": "Feature",
  "properties": {
    "iso:country":"GB",
    "wof:name":"BA3 5LE",
    "wof:placetype":"postalcode"
},
  "geometry": {"coordinates":[-2.47881781828033,51.22233843072799],"type":"Point"}
}