{
  "type": "Feature",
  "properties": {
    "iso:country":"GB",
    "wof:name":"RH4 3JX",
    "wof:placetype":"postalcode"
},
  "geometry": {"coordinates":[-0.36791320677066,51.22161738003683],"type":"Point"}
}