{
  "type": "Feature",
  "properties": {
    "iso:country":"GB",
    "wof:name":"S75 3SB",
    "wof:placetype":"postalcode"
},
  "geometry": {"coordinates":[-1.53139501185931,53.5342009917745],"type":"Point"}
}