{
  "type": "Feature",
  "properties": {
    "date:inception_lower": "1995-07-01",
    "date:inception_upper": "1995-07-01",
    "iso:country": "GB",
    "wof:name": "RG17 7DR",
    "wof:placetype": "postalcode"
  },
  "geometry": {"coordinates":[-1.448034,51.476225],"type":"Point"}
}
