{
  "type": "Feature",
  "properties": {
    "iso:country": "GB",
    "wof:name": "OX14 3BW",
    "wof:placetype": "postalcode"
  },
  "geometry": {"coordinates":[-1.263519,51.654512],"type":"Point"}
}
