{
  "type": "Feature",
  "properties": {
    "iso:country":"GB",
    "wof:name":"OX14 3BW",
    "wof:placetype":"postalcode"
},
  "geometry": {"coordinates":[-1.2635187232114,51.65451241410835],"type":"Point"}
}