{
  "type": "Feature",
  "properties": {
    "iso:country":"GB",
    "wof:name":"BA11 4AW",
    "wof:placetype":"postalcode"
},
  "geometry": {"coordinates":[-2.32549522141457,51.223674883939],"type":"Point"}
}