{
  "type": "Feature",
  "properties": {
    "iso:country":"GB",
    "wof:name":"WV2 2EA",
    "wof:placetype":"postalcode"
},
  "geometry": {"coordinates":[-2.11281029229016,52.56943857304933],"type":"Point"}
}