{
  "type": "Feature",
  "properties": {
    "iso:country": "GB",
    "wof:name": "DN21 5DN",
    "wof:placetype": "postalcode"
  },
  "geometry": {"coordinates":[-0.584894,53.385346],"type":"Point"}
}
