{
  "type": "Feature",
  "properties": {
    "iso:country":"GB",
    "wof:name":"N12 0NT",
    "wof:placetype":"postalcode"
},
  "geometry": {"coordinates":[-0.17352825768691,51.61125408861095],"type":"Point"}
}