{
  "type": "Feature",
  "properties": {
    "date:inception_lower":"1993-01-01",
    "date:inception_upper":"1993-01-31",
    "iso:country":"GB",
    "wof:name":"SG12 0RZ",
    "wof:placetype":"postalcode"
},
  "geometry": {"coordinates":[-0.042006,51.815778],"type":"Point"}
}