{
  "type": "Feature",
  "properties": {
    "iso:country":"GB",
    "wof:name":"SG12 0RZ",
    "wof:placetype":"postalcode"
},
  "geometry": {"coordinates":[-0.04200570748988,51.81577810181574],"type":"Point"}
}