{
  "type": "Feature",
  "properties": {
    "iso:country":"GB",
    "wof:name":"OX26 1AU",
    "wof:placetype":"postalcode"
},
  "geometry": {"coordinates":[-1.17285058146136,51.89659208333022],"type":"Point"}
}