{
  "type": "Feature",
  "properties": {
    "iso:country":"GB",
    "wof:name":"SS7 2HQ",
    "wof:placetype":"postalcode"
},
  "geometry": {"coordinates":[0.61616074530375,51.55448690478006],"type":"Point"}
}