{
  "type": "Feature",
  "properties": {
    "iso:country":"GB",
    "wof:name":"PO12 1SL",
    "wof:placetype":"postalcode"
},
  "geometry": {"coordinates":[-1.13118317626807,50.79228068044009],"type":"Point"}
}