{
  "type": "Feature",
  "properties": {
    "iso:country":"GB",
    "wof:name":"PA16 8QP",
    "wof:placetype":"postalcode"
},
  "geometry": {"coordinates":[-4.7762363707075,55.95104666765972],"type":"Point"}
}