{
  "type": "Feature",
  "properties": {
    "iso:country":"GB",
    "wof:name":"B93 9EG",
    "wof:placetype":"postalcode"
},
  "geometry": {"coordinates":[-1.7506501496677,52.38301202568098],"type":"Point"}
}