{
  "type": "Feature",
  "properties": {
    "date:inception_lower": "1980-01-01",
    "date:inception_upper": "1980-01-01",
    "iso:country": "GB",
    "wof:name": "BN1 2LA",
    "wof:placetype": "postalcode"
  },
  "geometry": {"coordinates":[-0.151267,50.824953],"type":"Point"}
}
