{
  "type": "Feature",
  "properties": {
    "iso:country":"GB",
    "wof:name":"BN1 2LA",
    "wof:placetype":"postalcode"
},
  "geometry": {"coordinates":[-0.15126685792168,50.82495279319825],"type":"Point"}
}