{
  "type": "Feature",
  "properties": {
    "date:inception_lower": "1980-01-01",
    "date:inception_upper": "1980-01-01",
    "iso:country": "GB",
    "wof:name": "PL4 8HF",
    "wof:placetype": "postalcode"
  },
  "geometry": {"coordinates":[-4.134817,50.378238],"type":"Point"}
}
