{
  "type": "Feature",
  "properties": {
    "iso:country": "GB",
    "wof:name": "DG7 3NX",
    "wof:placetype": "postalcode"
  },
  "geometry": {"coordinates":[-3.941435,55.018999],"type":"Point"}
}
