{
  "type": "Feature",
  "properties": {
    "date:inception_lower": "1980-01-01",
    "date:inception_upper": "1980-01-01",
    "iso:country": "GB",
    "wof:name": "DG7 3NX",
    "wof:placetype": "postalcode"
  },
  "geometry": {"coordinates":[-3.941435,55.018999],"type":"Point"}
}
