{
  "type": "Feature",
  "properties": {
    "iso:country": "GB",
    "wof:name": "DG7 3NX",
    "wof:placetype": "postalcode"
  },
  "geometry": {"coordinates":[-3.945907,55.019296],"type":"Point"}
}
