{
  "type": "Feature",
  "properties": {
    "iso:country":"GB",
    "wof:name":"B30 2TL",
    "wof:placetype":"postalcode"
},
  "geometry": {"coordinates":[-1.90606945241794,52.4342290250888],"type":"Point"}
}