{
  "type": "Feature",
  "properties": {
    "iso:country":"GB",
    "wof:name":"NR21 7HE",
    "wof:placetype":"postalcode"
},
  "geometry": {"coordinates":[0.78366470588399,52.78299474641579],"type":"Point"}
}