{
  "type": "Feature",
  "properties": {
    "iso:country":"GB",
    "wof:name":"CA2 7BT",
    "wof:placetype":"postalcode"
},
  "geometry": {"coordinates":[-2.94877189509407,54.88955005258266],"type":"Point"}
}