{
  "type": "Feature",
  "properties": {
    "date:inception_lower": "2015-12-01",
    "date:inception_upper": "2015-12-01",
    "iso:country": "GB",
    "wof:name": "CW2 8GE",
    "wof:placetype": "postalcode"
  },
  "geometry": {"coordinates":[-2.479218,53.099638],"type":"Point"}
}
