{
  "type": "Feature",
  "properties": {
    "iso:country":"GB",
    "wof:name":"CW2 8GE",
    "wof:placetype":"postalcode"
},
  "geometry": {"coordinates":[-2.4629895464668,53.08902477685756],"type":"Point"}
}