{
  "type": "Feature",
  "properties": {
    "iso:country":"GB",
    "wof:name":"EC4R 3TN",
    "wof:placetype":"postalcode"
},
  "geometry": {"coordinates":[-0.08817728172998,51.50959260847226],"type":"Point"}
}