{
  "type": "Feature",
  "properties": {
    "date:inception_lower": "1985-10-01",
    "date:inception_upper": "1985-10-01",
    "iso:country": "GB",
    "wof:name": "EC4R 3TN",
    "wof:placetype": "postalcode"
  },
  "geometry": {"coordinates":[-0.088177,51.509593],"type":"Point"}
}
