{
  "type": "Feature",
  "properties": {
    "iso:country":"GB",
    "wof:name":"YO15 2JN",
    "wof:placetype":"postalcode"
},
  "geometry": {"coordinates":[-0.18602046920202,54.09068056115952],"type":"Point"}
}