{
  "type": "Feature",
  "properties": {
    "date:inception_lower": "2021-05-01",
    "date:inception_upper": "2021-05-01",
    "iso:country": "GB",
    "wof:name": "CV36 4QW",
    "wof:placetype": "postalcode"
  },
  "geometry": {"coordinates":[-1.68925,52.087969],"type":"Point"}
}
