{
  "type": "Feature",
  "properties": {
    "iso:country": "GB",
    "wof:name": "TW13 4QD",
    "wof:placetype": "postalcode"
  },
  "geometry": {"coordinates":[-0.422252,51.433866],"type":"Point"}
}
