{
  "type": "Feature",
  "properties": {
    "iso:country":"GB",
    "wof:name":"TW13 4QD",
    "wof:placetype":"postalcode"
},
  "geometry": {"coordinates":[-0.42225190604941,51.43386553610422],"type":"Point"}
}