{
  "type": "Feature",
  "properties": {
    "date:inception_lower":"1980-01-01",
    "date:inception_upper":"1980-01-31",
    "iso:country":"GB",
    "wof:name":"PL17 8PD",
    "wof:placetype":"postalcode"
},
  "geometry": {"coordinates":[-4.319624,50.549833],"type":"Point"}
}