{
  "type": "Feature",
  "properties": {
    "iso:country":"GB",
    "wof:name":"PL17 8PD",
    "wof:placetype":"postalcode"
},
  "geometry": {"coordinates":[-4.31962440064629,50.54983336910592],"type":"Point"}
}