{
  "type": "Feature",
  "properties": {
    "iso:country": "GB",
    "wof:name": "PL17 8PD",
    "wof:placetype": "postalcode"
  },
  "geometry": {"coordinates":[-4.319624,50.549833],"type":"Point"}
}
