{
  "type": "Feature",
  "properties": {
    "iso:country":"GB",
    "wof:name":"PL29 3SP",
    "wof:placetype":"postalcode"
},
  "geometry": {"coordinates":[-4.83206803677241,50.58956364469194],"type":"Point"}
}