{
  "type": "Feature",
  "properties": {
    "date:inception_lower": "1996-12-01",
    "date:inception_upper": "1996-12-01",
    "iso:country": "GB",
    "wof:name": "LN8 6BP",
    "wof:placetype": "postalcode"
  },
  "geometry": {"coordinates":[-0.128821,53.452642],"type":"Point"}
}
