{
  "type": "Feature",
  "properties": {
    "iso:country":"GB",
    "wof:name":"LN8 6BP",
    "wof:placetype":"postalcode"
},
  "geometry": {"coordinates":[-0.12882771350998,53.45282211820912],"type":"Point"}
}