{
  "type": "Feature",
  "properties": {
    "iso:country":"GB",
    "wof:name":"CV21 4PE",
    "wof:placetype":"postalcode"
},
  "geometry": {"coordinates":[-1.21260159645101,52.35981404446929],"type":"Point"}
}