{
  "type": "Feature",
  "properties": {
    "iso:country":"GB",
    "wof:name":"PA14 6XF",
    "wof:placetype":"postalcode"
},
  "geometry": {"coordinates":[-4.59490326185099,55.92367728951853],"type":"Point"}
}