{
  "type": "Feature",
  "properties": {
    "iso:country":"GB",
    "wof:name":"LE67 4BG",
    "wof:placetype":"postalcode"
},
  "geometry": {"coordinates":[-1.34758562000371,52.71470798736065],"type":"Point"}
}