{
  "type": "Feature",
  "properties": {
    "iso:country":"GB",
    "wof:name":"AL3 7BS",
    "wof:placetype":"postalcode"
},
  "geometry": {"coordinates":[-0.39787265410271,51.79918905221461],"type":"Point"}
}