{
  "type": "Feature",
  "properties": {
    "iso:country":"GB",
    "wof:name":"LU3 2SX",
    "wof:placetype":"postalcode"
},
  "geometry": {"coordinates":[-0.44410977176628,51.90940978736819],"type":"Point"}
}