{
  "type": "Feature",
  "properties": {
    "date:inception_lower": "2002-05-01",
    "date:inception_upper": "2002-05-01",
    "iso:country": "GB",
    "wof:name": "PO19 6GH",
    "wof:placetype": "postalcode"
  },
  "geometry": {"coordinates":[-0.765169,50.84346],"type":"Point"}
}
