{
  "type": "Feature",
  "properties": {
    "iso:country": "GB",
    "wof:name": "PO19 6GH",
    "wof:placetype": "postalcode"
  },
  "geometry": {"coordinates":[-0.765188,50.84347],"type":"Point"}
}
