{
  "type": "Feature",
  "properties": {
    "iso:country":"GB",
    "wof:name":"KW15 1LN",
    "wof:placetype":"postalcode"
},
  "geometry": {"coordinates":[-2.95355050257174,58.98763871550241],"type":"Point"}
}