{
  "type": "Feature",
  "properties": {
    "date:inception_lower": "1980-01-01",
    "date:inception_upper": "1980-01-01",
    "iso:country": "GB",
    "wof:name": "KW15 1LN",
    "wof:placetype": "postalcode"
  },
  "geometry": {"coordinates":[-2.95355,58.987639],"type":"Point"}
}
