{
  "type": "Feature",
  "properties": {
    "iso:country":"GB",
    "wof:name":"M9 8LF",
    "wof:placetype":"postalcode"
},
  "geometry": {"coordinates":[-2.22742324540825,53.53248346589489],"type":"Point"}
}