{
  "type": "Feature",
  "properties": {
    "iso:country":"GB",
    "wof:name":"CT4 5EX",
    "wof:placetype":"postalcode"
},
  "geometry": {"coordinates":[1.15263200861965,51.25565674514128],"type":"Point"}
}