{
  "type": "Feature",
  "properties": {
    "iso:country": "GB",
    "wof:name": "EX39 1ES",
    "wof:placetype": "postalcode"
  },
  "geometry": {"coordinates":[-4.217497,51.043679],"type":"Point"}
}
