{
  "type": "Feature",
  "properties": {
    "iso:country":"GB",
    "wof:name":"EX39 1ES",
    "wof:placetype":"postalcode"
},
  "geometry": {"coordinates":[-4.21760536486475,51.04377928421943],"type":"Point"}
}