{
  "type": "Feature",
  "properties": {
    "iso:country":"GB",
    "wof:name":"NE10 8AT",
    "wof:placetype":"postalcode"
},
  "geometry": {"coordinates":[-1.52803950081902,54.94730152446215],"type":"Point"}
}