{
  "type": "Feature",
  "properties": {
    "iso:country":"GB",
    "wof:name":"HP3 8NH",
    "wof:placetype":"postalcode"
},
  "geometry": {"coordinates":[-0.44258545285843,51.74778111067631],"type":"Point"}
}