{
  "type": "Feature",
  "properties": {
    "iso:country": "GB",
    "wof:name": "HP3 8NH",
    "wof:placetype": "postalcode"
  },
  "geometry": {"coordinates":[-0.442585,51.747781],"type":"Point"}
}
