{
  "type": "Feature",
  "properties": {
    "iso:country":"GB",
    "wof:name":"B70 8JW",
    "wof:placetype":"postalcode"
},
  "geometry": {"coordinates":[-2.01102288885704,52.51468082716499],"type":"Point"}
}