{
  "type": "Feature",
  "properties": {
    "date:inception_lower": "1980-01-01",
    "date:inception_upper": "1980-01-01",
    "iso:country": "GB",
    "wof:name": "B70 8JW",
    "wof:placetype": "postalcode"
  },
  "geometry": {"coordinates":[-2.011023,52.514681],"type":"Point"}
}
