{
  "type": "Feature",
  "properties": {
    "iso:country":"GB",
    "wof:name":"G65 9AS",
    "wof:placetype":"postalcode"
},
  "geometry": {"coordinates":[-4.07412531617532,55.97858517053348],"type":"Point"}
}