{
  "type": "Feature",
  "properties": {
    "iso:country": "GB",
    "wof:name": "G65 9AS",
    "wof:placetype": "postalcode"
  },
  "geometry": {"coordinates":[-4.074125,55.978585],"type":"Point"}
}
