{
  "type": "Feature",
  "properties": {
    "iso:country": "GB",
    "wof:name": "FK1 9EH",
    "wof:placetype": "postalcode"
  },
  "geometry": {"coordinates":[-3.784777,56.001996],"type":"Point"}
}
