{
  "type": "Feature",
  "properties": {
    "date:inception_lower": "1997-06-01",
    "date:inception_upper": "1997-06-01",
    "iso:country": "GB",
    "wof:name": "BB1 5NE",
    "wof:placetype": "postalcode"
  },
  "geometry": {"coordinates":[-2.462174,53.75663],"type":"Point"}
}
