{
  "type": "Feature",
  "properties": {
    "iso:country":"GB",
    "wof:name":"PE15 9QB",
    "wof:placetype":"postalcode"
},
  "geometry": {"coordinates":[0.07863701445298,52.53293244170821],"type":"Point"}
}