{
  "type": "Feature",
  "properties": {
    "iso:country":"GB",
    "wof:name":"BL3 6RD",
    "wof:placetype":"postalcode"
},
  "geometry": {"coordinates":[-2.43253671684329,53.56743021016117],"type":"Point"}
}