{
  "type": "Feature",
  "properties": {
    "iso:country":"GB",
    "wof:name":"OX14 4BB",
    "wof:placetype":"postalcode"
},
  "geometry": {"coordinates":[-1.27647039027513,51.63455104851019],"type":"Point"}
}