{
  "type": "Feature",
  "properties": {
    "iso:country": "GB",
    "wof:name": "OX14 4BB",
    "wof:placetype": "postalcode"
  },
  "geometry": {"coordinates":[-1.27647,51.634551],"type":"Point"}
}
