{
  "type": "Feature",
  "properties": {
    "iso:country":"GB",
    "wof:name":"B12 9LF",
    "wof:placetype":"postalcode"
},
  "geometry": {"coordinates":[-1.89780531961765,52.45875593589793],"type":"Point"}
}