{
  "type": "Feature",
  "properties": {
    "date:inception_lower":"1986-07-01",
    "date:inception_upper":"1986-07-31",
    "iso:country":"GB",
    "wof:name":"DE1 2NZ",
    "wof:placetype":"postalcode"
},
  "geometry": {"coordinates":[-1.474491,52.91888],"type":"Point"}
}