{
  "type": "Feature",
  "properties": {
    "iso:country": "GB",
    "wof:name": "DE1 2NZ",
    "wof:placetype": "postalcode"
  },
  "geometry": {"coordinates":[-1.474491,52.91888],"type":"Point"}
}
