{
  "type": "Feature",
  "properties": {
    "date:inception_lower": "2020-12-01",
    "date:inception_upper": "2020-12-01",
    "iso:country": "GB",
    "wof:name": "ML7 5UA",
    "wof:placetype": "postalcode"
  },
  "geometry": {"coordinates":[-3.779567,55.820318],"type":"Point"}
}
