{
  "type": "Feature",
  "properties": {
    "iso:country":"GB",
    "wof:name":"SE10 9NZ",
    "wof:placetype":"postalcode"
},
  "geometry": {"coordinates":[0.00042315427586,51.48428417392181],"type":"Point"}
}