{
  "type": "Feature",
  "properties": {
    "iso:country":"GB",
    "wof:name":"NE46 4ES",
    "wof:placetype":"postalcode"
},
  "geometry": {"coordinates":[-2.13267219321449,55.02851618506794],"type":"Point"}
}