{
  "type": "Feature",
  "properties": {
    "iso:country": "GB",
    "wof:name": "NE46 4ES",
    "wof:placetype": "postalcode"
  },
  "geometry": {"coordinates":[-2.132672,55.028516],"type":"Point"}
}
