{
  "type": "Feature",
  "properties": {
    "iso:country":"GB",
    "wof:name":"SL4 5UP",
    "wof:placetype":"postalcode"
},
  "geometry": {"coordinates":[-0.66365645129812,51.48016265125835],"type":"Point"}
}