{
  "type": "Feature",
  "properties": {
    "date:inception_lower": "1980-01-01",
    "date:inception_upper": "1980-01-01",
    "iso:country": "GB",
    "wof:name": "SL4 5UP",
    "wof:placetype": "postalcode"
  },
  "geometry": {"coordinates":[-0.663656,51.480163],"type":"Point"}
}
