{
  "type": "Feature",
  "properties": {
    "iso:country":"GB",
    "wof:name":"HR1 3NU",
    "wof:placetype":"postalcode"
},
  "geometry": {"coordinates":[-2.65209431086783,52.09701580179281],"type":"Point"}
}