{
  "type": "Feature",
  "properties": {
    "iso:country": "GB",
    "wof:name": "HR1 3NU",
    "wof:placetype": "postalcode"
  },
  "geometry": {"coordinates":[-2.652094,52.097017],"type":"Point"}
}
