{
  "type": "Feature",
  "properties": {
    "iso:country":"GB",
    "wof:name":"WV1 4NZ",
    "wof:placetype":"postalcode"
},
  "geometry": {"coordinates":[-2.13842905433406,52.5852873536957],"type":"Point"}
}