{
  "type": "Feature",
  "properties": {
    "date:inception_lower": "2020-11-01",
    "date:inception_upper": "2020-11-01",
    "iso:country": "GB",
    "wof:name": "DE3 0BF",
    "wof:placetype": "postalcode"
  },
  "geometry": {"coordinates":[-1.556513,52.91017],"type":"Point"}
}
