{
  "type": "Feature",
  "properties": {
    "iso:country": "GB",
    "wof:name": "TN15 8DD",
    "wof:placetype": "postalcode"
  },
  "geometry": {"coordinates":[0.308283,51.295821],"type":"Point"}
}
