{
  "type": "Feature",
  "properties": {
    "iso:country":"GB",
    "wof:name":"TN15 8DD",
    "wof:placetype":"postalcode"
},
  "geometry": {"coordinates":[0.30828332233588,51.29582140899849],"type":"Point"}
}