{
  "type": "Feature",
  "properties": {
    "iso:country":"GB",
    "wof:name":"IP12 4TD",
    "wof:placetype":"postalcode"
},
  "geometry": {"coordinates":[1.27025866069803,52.07528749968176],"type":"Point"}
}