{
  "type": "Feature",
  "properties": {
    "iso:country":"GB",
    "wof:name":"PA16 8RN",
    "wof:placetype":"postalcode"
},
  "geometry": {"coordinates":[-4.77866746109824,55.94920308272809],"type":"Point"}
}