{
  "type": "Feature",
  "properties": {
    "iso:country": "GB",
    "wof:name": "S40 4BJ",
    "wof:placetype": "postalcode"
  },
  "geometry": {"coordinates":[-1.442217,53.243853],"type":"Point"}
}
