{
  "type": "Feature",
  "properties": {
    "iso:country":"GB",
    "wof:name":"NN13 6DB",
    "wof:placetype":"postalcode"
},
  "geometry": {"coordinates":[-1.1448867419774,52.03442190881412],"type":"Point"}
}