{
  "type": "Feature",
  "properties": {
    "iso:country": "GB",
    "wof:name": "NN13 6DB",
    "wof:placetype": "postalcode"
  },
  "geometry": {"coordinates":[-1.144887,52.034422],"type":"Point"}
}
