{
  "type": "Feature",
  "properties": {
    "date:inception_lower": "1980-01-01",
    "date:inception_upper": "1980-01-01",
    "iso:country": "GB",
    "wof:name": "DN6 0AR",
    "wof:placetype": "postalcode"
  },
  "geometry": {"coordinates":[-1.157662,53.610138],"type":"Point"}
}
