{
  "type": "Feature",
  "properties": {
    "iso:country":"GB",
    "wof:name":"BB1 8JS",
    "wof:placetype":"postalcode"
},
  "geometry": {"coordinates":[-2.49012550230922,53.76299912477666],"type":"Point"}
}