{
  "type": "Feature",
  "properties": {
    "date:inception_lower": "2023-10-01",
    "date:inception_upper": "2023-10-01",
    "iso:country": "GB",
    "wof:name": "CM17 9XG",
    "wof:placetype": "postalcode"
  },
  "geometry": {"coordinates":[0.148236,51.767338],"type":"Point"}
}
