{
  "type": "Feature",
  "properties": {
    "date:inception_lower":"1980-01-01",
    "date:inception_upper":"1980-01-31",
    "iso:country":"GB",
    "wof:name":"B67 5LG",
    "wof:placetype":"postalcode"
},
  "geometry": {"coordinates":[-1.976899,52.477677],"type":"Point"}
}