{
  "type": "Feature",
  "properties": {
    "iso:country": "GB",
    "wof:name": "HG5 0RA",
    "wof:placetype": "postalcode"
  },
  "geometry": {"coordinates":[-1.386874,54.048504],"type":"Point"}
}
