{
  "type": "Feature",
  "properties": {
    "date:inception_lower": "1980-01-01",
    "date:inception_upper": "1980-01-01",
    "iso:country": "GB",
    "wof:name": "LL15 2BG",
    "wof:placetype": "postalcode"
  },
  "geometry": {"coordinates":[-3.370279,53.110475],"type":"Point"}
}
