{
  "type": "Feature",
  "properties": {
    "iso:country":"GB",
    "wof:name":"LL55 2HU",
    "wof:placetype":"postalcode"
},
  "geometry": {"coordinates":[-4.26865425463735,53.13613911270217],"type":"Point"}
}