{
  "type": "Feature",
  "properties": {
    "iso:country":"GB",
    "wof:name":"LS17 7JA",
    "wof:placetype":"postalcode"
},
  "geometry": {"coordinates":[-1.53497217585318,53.85306237978364],"type":"Point"}
}