{
  "type": "Feature",
  "properties": {
    "date:inception_lower": "1980-01-01",
    "date:inception_upper": "1980-01-01",
    "iso:country": "GB",
    "wof:name": "CF32 9TN",
    "wof:placetype": "postalcode"
  },
  "geometry": {"coordinates":[-3.571603,51.542174],"type":"Point"}
}
