{
  "type": "Feature",
  "properties": {
    "iso:country":"GB",
    "wof:name":"CF32 9TN",
    "wof:placetype":"postalcode"
},
  "geometry": {"coordinates":[-3.57157434208133,51.54218992739178],"type":"Point"}
}