{
  "type": "Feature",
  "properties": {
    "iso:country": "GB",
    "wof:name": "CF32 9TN",
    "wof:placetype": "postalcode"
  },
  "geometry": {"coordinates":[-3.571603,51.542174],"type":"Point"}
}
