{
  "type": "Feature",
  "properties": {
    "iso:country": "GB",
    "wof:name": "BA4 6LU",
    "wof:placetype": "postalcode"
  },
  "geometry": {"coordinates":[-2.526237,51.136342],"type":"Point"}
}
