{
  "type": "Feature",
  "properties": {
    "date:inception_lower": "1988-03-01",
    "date:inception_upper": "1988-03-01",
    "iso:country": "GB",
    "wof:name": "TW20 0TR",
    "wof:placetype": "postalcode"
  },
  "geometry": {"coordinates":[-0.576432,51.425516],"type":"Point"}
}
