{
  "type": "Feature",
  "properties": {
    "iso:country": "GB",
    "wof:name": "TW20 0TR",
    "wof:placetype": "postalcode"
  },
  "geometry": {"coordinates":[-0.576432,51.425516],"type":"Point"}
}
