{
  "type": "Feature",
  "properties": {
    "iso:country":"GB",
    "wof:name":"TW20 0TR",
    "wof:placetype":"postalcode"
},
  "geometry": {"coordinates":[-0.5764319061356,51.42551612734916],"type":"Point"}
}