{
  "type": "Feature",
  "properties": {
    "iso:country":"GB",
    "wof:name":"ML6 8AX",
    "wof:placetype":"postalcode"
},
  "geometry": {"coordinates":[-3.95676480708021,55.86138538522833],"type":"Point"}
}