{
  "type": "Feature",
  "properties": {
    "date:inception_lower": "1980-01-01",
    "date:inception_upper": "1980-01-01",
    "iso:country": "GB",
    "wof:name": "OL2 5TR",
    "wof:placetype": "postalcode"
  },
  "geometry": {"coordinates":[-2.130755,53.568986],"type":"Point"}
}
