{
  "type": "Feature",
  "properties": {
    "iso:country":"GB",
    "wof:name":"NE10 0RF",
    "wof:placetype":"postalcode"
},
  "geometry": {"coordinates":[-1.54449330884879,54.9556945626812],"type":"Point"}
}