{
  "type": "Feature",
  "properties": {
    "date:inception_lower": "2021-09-01",
    "date:inception_upper": "2021-09-01",
    "iso:country": "GB",
    "wof:name": "B94 6RE",
    "wof:placetype": "postalcode"
  },
  "geometry": {"coordinates":[-1.777766,52.350222],"type":"Point"}
}
