{
  "type": "Feature",
  "properties": {
    "iso:country":"GB",
    "wof:name":"OL4 5AN",
    "wof:placetype":"postalcode"
},
  "geometry": {"coordinates":[-2.07403027111846,53.53720727343555],"type":"Point"}
}