{
  "type": "Feature",
  "properties": {
    "date:inception_lower": "1980-01-01",
    "date:inception_upper": "1980-01-01",
    "iso:country": "GB",
    "wof:name": "NR10 5JQ",
    "wof:placetype": "postalcode"
  },
  "geometry": {"coordinates":[1.328688,52.760823],"type":"Point"}
}
