{
  "type": "Feature",
  "properties": {
    "iso:country":"GB",
    "wof:name":"NR10 5JQ",
    "wof:placetype":"postalcode"
},
  "geometry": {"coordinates":[1.32868756254697,52.76082315938262],"type":"Point"}
}