{
  "type": "Feature",
  "properties": {
    "iso:country": "GB",
    "wof:name": "CO3 3SH",
    "wof:placetype": "postalcode"
  },
  "geometry": {"coordinates":[0.867663,51.892239],"type":"Point"}
}
