{
  "type": "Feature",
  "properties": {
    "iso:country":"GB",
    "wof:name":"CO3 3SH",
    "wof:placetype":"postalcode"
},
  "geometry": {"coordinates":[0.8676629416619,51.89223926005892],"type":"Point"}
}