{
  "type": "Feature",
  "properties": {
    "iso:country": "GB",
    "wof:name": "SW6 5LL",
    "wof:placetype": "postalcode"
  },
  "geometry": {"coordinates":[-0.209422,51.474143],"type":"Point"}
}
