{
  "type": "Feature",
  "properties": {
    "iso:country":"GB",
    "wof:name":"SW6 5LL",
    "wof:placetype":"postalcode"
},
  "geometry": {"coordinates":[-0.20942199892706,51.47414262608989],"type":"Point"}
}