{
  "type": "Feature",
  "properties": {
    "iso:country":"GB",
    "wof:name":"WR6 6EX",
    "wof:placetype":"postalcode"
},
  "geometry": {"coordinates":[-2.46206382464794,52.2723115121051],"type":"Point"}
}