{
  "type": "Feature",
  "properties": {
    "date:inception_lower":"1980-01-01",
    "date:inception_upper":"1980-01-31",
    "iso:country":"GB",
    "wof:name":"CT21 6AL",
    "wof:placetype":"postalcode"
},
  "geometry": {"coordinates":[1.085591,51.066408],"type":"Point"}
}