{
  "type": "Feature",
  "properties": {
    "iso:country":"GB",
    "wof:name":"CT21 6AL",
    "wof:placetype":"postalcode"
},
  "geometry": {"coordinates":[1.08555715519181,51.06640560028936],"type":"Point"}
}