{
  "type": "Feature",
  "properties": {
    "iso:country":"GB",
    "wof:name":"SW20 8LS",
    "wof:placetype":"postalcode"
},
  "geometry": {"coordinates":[-0.21634495398148,51.40996061006258],"type":"Point"}
}