{
  "type": "Feature",
  "properties": {
    "iso:country":"GB",
    "wof:name":"SW4 7PA",
    "wof:placetype":"postalcode"
},
  "geometry": {"coordinates":[-0.12809629180831,51.46033681709603],"type":"Point"}
}