{
  "type": "Feature",
  "properties": {
    "iso:country":"GB",
    "wof:name":"NE31 1QB",
    "wof:placetype":"postalcode"
},
  "geometry": {"coordinates":[-1.50805984045945,54.97641893932863],"type":"Point"}
}