{
  "type": "Feature",
  "properties": {
    "iso:country": "GB",
    "wof:name": "NE31 1QB",
    "wof:placetype": "postalcode"
  },
  "geometry": {"coordinates":[-1.50806,54.976419],"type":"Point"}
}
