{
  "type": "Feature",
  "properties": {
    "iso:country": "GB",
    "wof:name": "HU3 6HU",
    "wof:placetype": "postalcode"
  },
  "geometry": {"coordinates":[-0.368016,53.745731],"type":"Point"}
}
