{
  "type": "Feature",
  "properties": {
    "date:inception_lower": "2003-01-01",
    "date:inception_upper": "2003-01-01",
    "iso:country": "GB",
    "wof:name": "HU3 6HU",
    "wof:placetype": "postalcode"
  },
  "geometry": {"coordinates":[-0.368016,53.745731],"type":"Point"}
}
