{
  "type": "Feature",
  "properties": {
    "iso:country":"GB",
    "wof:name":"PE14 8TR",
    "wof:placetype":"postalcode"
},
  "geometry": {"coordinates":[0.23098114995188,52.61556044135897],"type":"Point"}
}