{
  "type": "Feature",
  "properties": {
    "date:inception_lower":"2008-02-01",
    "date:inception_upper":"2008-02-29",
    "iso:country":"GB",
    "wof:name":"PE14 8TR",
    "wof:placetype":"postalcode"
},
  "geometry": {"coordinates":[0.230981,52.61556],"type":"Point"}
}