{
  "type": "Feature",
  "properties": {
    "iso:country": "GB",
    "wof:name": "NR3 4JP",
    "wof:placetype": "postalcode"
  },
  "geometry": {"coordinates":[1.299897,52.644343],"type":"Point"}
}
