{
  "type": "Feature",
  "properties": {
    "iso:country":"GB",
    "wof:name":"NR3 4JP",
    "wof:placetype":"postalcode"
},
  "geometry": {"coordinates":[1.29989699053066,52.64434305723388],"type":"Point"}
}