{
  "type": "Feature",
  "properties": {
    "iso:country":"GB",
    "wof:name":"EX16 7LA",
    "wof:placetype":"postalcode"
},
  "geometry": {"coordinates":[-3.31453784763874,50.92442815299457],"type":"Point"}
}