{
  "type": "Feature",
  "properties": {
    "date:inception_lower":"1980-01-01",
    "date:inception_upper":"1980-01-31",
    "iso:country":"GB",
    "wof:name":"EX16 7LA",
    "wof:placetype":"postalcode"
},
  "geometry": {"coordinates":[-3.314538,50.924428],"type":"Point"}
}