{
  "type": "Feature",
  "properties": {
    "iso:country": "GB",
    "wof:name": "EX16 7LA",
    "wof:placetype": "postalcode"
  },
  "geometry": {"coordinates":[-3.314538,50.924428],"type":"Point"}
}
