{
  "type": "Feature",
  "properties": {
    "iso:country":"GB",
    "wof:name":"SO40 3WW",
    "wof:placetype":"postalcode"
},
  "geometry": {"coordinates":[-1.49816623038127,50.93102315156304],"type":"Point"}
}