{
  "type": "Feature",
  "properties": {
    "iso:country":"GB",
    "wof:name":"BS13 0AP",
    "wof:placetype":"postalcode"
},
  "geometry": {"coordinates":[-2.5983458700208,51.41224455612545],"type":"Point"}
}