{
  "type": "Feature",
  "properties": {
    "iso:country": "GB",
    "wof:name": "RH15 9RD",
    "wof:placetype": "postalcode"
  },
  "geometry": {"coordinates":[-0.138877,50.956126],"type":"Point"}
}
