{
  "type": "Feature",
  "properties": {
    "iso:country":"GB",
    "wof:name":"LD4 4AE",
    "wof:placetype":"postalcode"
},
  "geometry": {"coordinates":[-3.53354342478843,52.13361000122391],"type":"Point"}
}