{
  "type": "Feature",
  "properties": {
    "iso:country":"GB",
    "wof:name":"B74 4PP",
    "wof:placetype":"postalcode"
},
  "geometry": {"coordinates":[-1.85661546542825,52.59384936324027],"type":"Point"}
}