{
  "type": "Feature",
  "properties": {
    "iso:country": "GB",
    "wof:name": "B74 4PP",
    "wof:placetype": "postalcode"
  },
  "geometry": {"coordinates":[-1.856615,52.593849],"type":"Point"}
}
