{
  "type": "Feature",
  "properties": {
    "iso:country": "GB",
    "wof:name": "PO20 0EY",
    "wof:placetype": "postalcode"
  },
  "geometry": {"coordinates":[-0.770134,50.737935],"type":"Point"}
}
