{
  "type": "Feature",
  "properties": {
    "date:inception_lower": "2006-01-01",
    "date:inception_upper": "2006-01-01",
    "iso:country": "GB",
    "wof:name": "EX39 1US",
    "wof:placetype": "postalcode"
  },
  "geometry": {"coordinates":[-4.227459,51.040417],"type":"Point"}
}
