{
  "type": "Feature",
  "properties": {
    "iso:country": "GB",
    "wof:name": "NP4 5LX",
    "wof:placetype": "postalcode"
  },
  "geometry": {"coordinates":[-3.022062,51.68697],"type":"Point"}
}
