{
  "type": "Feature",
  "properties": {
    "iso:country":"GB",
    "wof:name":"HG3 1PY",
    "wof:placetype":"postalcode"
},
  "geometry": {"coordinates":[-1.5647649688744,53.97785361481344],"type":"Point"}
}