{
  "type": "Feature",
  "properties": {
    "date:inception_lower": "1980-01-01",
    "date:inception_upper": "1980-01-01",
    "iso:country": "GB",
    "wof:name": "HG3 1PY",
    "wof:placetype": "postalcode"
  },
  "geometry": {"coordinates":[-1.565317,53.978095],"type":"Point"}
}
