{
  "type": "Feature",
  "properties": {
    "iso:country": "GB",
    "wof:name": "AB38 9PL",
    "wof:placetype": "postalcode"
  },
  "geometry": {"coordinates":[-3.226734,57.46913],"type":"Point"}
}
