{
  "type": "Feature",
  "properties": {
    "iso:country":"GB",
    "wof:name":"DE72 3JN",
    "wof:placetype":"postalcode"
},
  "geometry": {"coordinates":[-1.37563419452999,52.91074215384285],"type":"Point"}
}