{
  "type": "Feature",
  "properties": {
    "date:inception_lower": "1997-12-01",
    "date:inception_upper": "1997-12-01",
    "iso:country": "GB",
    "wof:name": "BS31 2TG",
    "wof:placetype": "postalcode"
  },
  "geometry": {"coordinates":[-2.481931,51.385797],"type":"Point"}
}
