{
  "type": "Feature",
  "properties": {
    "iso:country": "GB",
    "wof:name": "BS31 2TG",
    "wof:placetype": "postalcode"
  },
  "geometry": {"coordinates":[-2.481931,51.385797],"type":"Point"}
}
