{
  "type": "Feature",
  "properties": {
    "iso:country":"GB",
    "wof:name":"NP20 5QR",
    "wof:placetype":"postalcode"
},
  "geometry": {"coordinates":[-3.00139876561532,51.60536056147181],"type":"Point"}
}