{
  "type": "Feature",
  "properties": {
    "iso:country": "GB",
    "wof:name": "WS13 8GG",
    "wof:placetype": "postalcode"
  },
  "geometry": {"coordinates":[-1.792015,52.692289],"type":"Point"}
}
