{
  "type": "Feature",
  "properties": {
    "iso:country": "GB",
    "wof:name": "M30 8HF",
    "wof:placetype": "postalcode"
  },
  "geometry": {"coordinates":[-2.363055,53.493911],"type":"Point"}
}
