{
  "type": "Feature",
  "properties": {
    "iso:country":"GB",
    "wof:name":"M30 8HF",
    "wof:placetype":"postalcode"
},
  "geometry": {"coordinates":[-2.36305462031231,53.49391149107661],"type":"Point"}
}