{
  "type": "Feature",
  "properties": {
    "iso:country":"GB",
    "wof:name":"SA48 7NG",
    "wof:placetype":"postalcode"
},
  "geometry": {"coordinates":[-4.163497773374,52.14372042003089],"type":"Point"}
}