{
  "type": "Feature",
  "properties": {
    "date:inception_lower":"1980-01-01",
    "date:inception_upper":"1980-01-31",
    "iso:country":"GB",
    "wof:name":"SL2 5UJ",
    "wof:placetype":"postalcode"
},
  "geometry": {"coordinates":[-0.575373,51.523805],"type":"Point"}
}