{
  "type": "Feature",
  "properties": {
    "iso:country":"GB",
    "wof:name":"SL2 5UJ",
    "wof:placetype":"postalcode"
},
  "geometry": {"coordinates":[-0.57537287728326,51.52380514956632],"type":"Point"}
}