{
  "type": "Feature",
  "properties": {
    "iso:country":"GB",
    "wof:name":"CM1 7HP",
    "wof:placetype":"postalcode"
},
  "geometry": {"coordinates":[0.47134415629431,51.77229374962609],"type":"Point"}
}