{
  "type": "Feature",
  "properties": {
    "iso:country":"GB",
    "wof:name":"OL1 3EB",
    "wof:placetype":"postalcode"
},
  "geometry": {"coordinates":[-2.11171093549815,53.54485397841558],"type":"Point"}
}