{
  "type": "Feature",
  "properties": {
    "iso:country":"GB",
    "wof:name":"E11 3NJ",
    "wof:placetype":"postalcode"
},
  "geometry": {"coordinates":[0.01213062073337,51.55552169866197],"type":"Point"}
}