{
  "type": "Feature",
  "properties": {
    "date:inception_lower": "2022-08-01",
    "date:inception_upper": "2022-08-01",
    "iso:country": "GB",
    "wof:name": "NG12 5SL",
    "wof:placetype": "postalcode"
  },
  "geometry": {"coordinates":[-1.098302,52.874211],"type":"Point"}
}
