{
  "type": "Feature",
  "properties": {
    "iso:country": "GB",
    "wof:name": "SG8 0HB",
    "wof:placetype": "postalcode"
  },
  "geometry": {"coordinates":[-0.081949,52.118512],"type":"Point"}
}
