{
  "type": "Feature",
  "properties": {
    "iso:country":"GB",
    "wof:name":"SG8 0HB",
    "wof:placetype":"postalcode"
},
  "geometry": {"coordinates":[-0.08194874797257,52.11851212210521],"type":"Point"}
}