{
  "type": "Feature",
  "properties": {
    "date:inception_lower":"1980-01-01",
    "date:inception_upper":"1980-01-31",
    "iso:country":"GB",
    "wof:name":"SL7 3EF",
    "wof:placetype":"postalcode"
},
  "geometry": {"coordinates":[-0.772098,51.579153],"type":"Point"}
}