{
  "type": "Feature",
  "properties": {
    "iso:country":"GB",
    "wof:name":"SL7 3EF",
    "wof:placetype":"postalcode"
},
  "geometry": {"coordinates":[-0.77209806088428,51.57915278017931],"type":"Point"}
}