{
  "type": "Feature",
  "properties": {
    "iso:country":"GB",
    "wof:name":"S41 0PU",
    "wof:placetype":"postalcode"
},
  "geometry": {"coordinates":[-1.41486542331462,53.22219255932204],"type":"Point"}
}