{
  "type": "Feature",
  "properties": {
    "iso:country":"GB",
    "wof:name":"SY5 0BE",
    "wof:placetype":"postalcode"
},
  "geometry": {"coordinates":[-2.92544218817199,52.6380104533085],"type":"Point"}
}