{
  "type": "Feature",
  "properties": {
    "date:inception_lower": "2012-05-01",
    "date:inception_upper": "2012-05-01",
    "iso:country": "GB",
    "wof:name": "TS18 2SS",
    "wof:placetype": "postalcode"
  },
  "geometry": {"coordinates":[-1.29373,54.566225],"type":"Point"}
}
