{
  "type": "Feature",
  "properties": {
    "iso:country": "GB",
    "wof:name": "SN10 5AE",
    "wof:placetype": "postalcode"
  },
  "geometry": {"coordinates":[-1.98812,51.346182],"type":"Point"}
}
