{
  "type": "Feature",
  "properties": {
    "iso:country":"GB",
    "wof:name":"SN10 5AE",
    "wof:placetype":"postalcode"
},
  "geometry": {"coordinates":[-1.98811982972868,51.34618228740573],"type":"Point"}
}