{
  "type": "Feature",
  "properties": {
    "iso:country": "GB",
    "wof:name": "SR8 4DP",
    "wof:placetype": "postalcode"
  },
  "geometry": {"coordinates":[-1.312845,54.765682],"type":"Point"}
}
