{
  "type": "Feature",
  "properties": {
    "iso:country":"GB",
    "wof:name":"SR8 4DP",
    "wof:placetype":"postalcode"
},
  "geometry": {"coordinates":[-1.31284519394439,54.76568182848223],"type":"Point"}
}