{
  "type": "Feature",
  "properties": {
    "iso:country":"GB",
    "wof:name":"S17 4HU",
    "wof:placetype":"postalcode"
},
  "geometry": {"coordinates":[-1.52167941627758,53.31951462062494],"type":"Point"}
}