{
  "type": "Feature",
  "properties": {
    "date:inception_lower": "1980-01-01",
    "date:inception_upper": "1980-01-01",
    "iso:country": "GB",
    "wof:name": "S17 4HU",
    "wof:placetype": "postalcode"
  },
  "geometry": {"coordinates":[-1.521693,53.31955],"type":"Point"}
}
