{
  "type": "Feature",
  "properties": {
    "iso:country": "GB",
    "wof:name": "G4 0LS",
    "wof:placetype": "postalcode"
  },
  "geometry": {"coordinates":[-4.240631,55.863759],"type":"Point"}
}
