{
  "type": "Feature",
  "properties": {
    "iso:country": "GB",
    "wof:name": "SA10 7BG",
    "wof:placetype": "postalcode"
  },
  "geometry": {"coordinates":[-3.813532,51.663305],"type":"Point"}
}
