{
  "type": "Feature",
  "properties": {
    "date:inception_lower": "1980-01-01",
    "date:inception_upper": "1980-01-01",
    "iso:country": "GB",
    "wof:name": "DY3 3QB",
    "wof:placetype": "postalcode"
  },
  "geometry": {"coordinates":[-2.133692,52.548944],"type":"Point"}
}
