{
  "type": "Feature",
  "properties": {
    "iso:country": "GB",
    "wof:name": "DY3 3QB",
    "wof:placetype": "postalcode"
  },
  "geometry": {"coordinates":[-2.133692,52.548944],"type":"Point"}
}
