{
  "type": "Feature",
  "properties": {
    "iso:country": "GB",
    "wof:name": "S6 3NF",
    "wof:placetype": "postalcode"
  },
  "geometry": {"coordinates":[-1.495417,53.388871],"type":"Point"}
}
