{
  "type": "Feature",
  "properties": {
    "iso:country": "GB",
    "wof:name": "RH10 7RS",
    "wof:placetype": "postalcode"
  },
  "geometry": {"coordinates":[-0.143709,51.112644],"type":"Point"}
}
