{
  "type": "Feature",
  "properties": {
    "iso:country": "GB",
    "wof:name": "TA1 5HW",
    "wof:placetype": "postalcode"
  },
  "geometry": {"coordinates":[-3.13593,51.013747],"type":"Point"}
}
