{
  "type": "Feature",
  "properties": {
    "iso:country":"GB",
    "wof:name":"S64 9PQ",
    "wof:placetype":"postalcode"
},
  "geometry": {"coordinates":[-1.28910481046082,53.49725001720309],"type":"Point"}
}