{
  "type": "Feature",
  "properties": {
    "date:inception_lower": "1985-10-01",
    "date:inception_upper": "1985-10-01",
    "iso:country": "GB",
    "wof:name": "S64 9PQ",
    "wof:placetype": "postalcode"
  },
  "geometry": {"coordinates":[-1.289105,53.49725],"type":"Point"}
}
