{
  "type": "Feature",
  "properties": {
    "iso:country": "GB",
    "wof:name": "DL13 2TE",
    "wof:placetype": "postalcode"
  },
  "geometry": {"coordinates":[-1.978195,54.722376],"type":"Point"}
}
