{
  "type": "Feature",
  "properties": {
    "iso:country":"GB",
    "wof:name":"DL13 2TE",
    "wof:placetype":"postalcode"
},
  "geometry": {"coordinates":[-1.97854320399607,54.72264699680365],"type":"Point"}
}