{
  "type": "Feature",
  "properties": {
    "iso:country": "GB",
    "wof:name": "RH10 6JE",
    "wof:placetype": "postalcode"
  },
  "geometry": {"coordinates":[-0.17139,51.106677],"type":"Point"}
}
