{
  "type": "Feature",
  "properties": {
    "iso:country":"GB",
    "wof:name":"CF31 1QE",
    "wof:placetype":"postalcode"
},
  "geometry": {"coordinates":[-3.57777823685258,51.52393344021122],"type":"Point"}
}