{
  "type": "Feature",
  "properties": {
    "iso:country":"GB",
    "wof:name":"FK2 0HP",
    "wof:placetype":"postalcode"
},
  "geometry": {"coordinates":[-3.7202726600611,55.98026745640234],"type":"Point"}
}