{
  "type": "Feature",
  "properties": {
    "date:inception_lower": "1980-01-01",
    "date:inception_upper": "1980-01-01",
    "iso:country": "GB",
    "wof:name": "NG23 6RH",
    "wof:placetype": "postalcode"
  },
  "geometry": {"coordinates":[-0.816426,53.208434],"type":"Point"}
}
