{
  "type": "Feature",
  "properties": {
    "iso:country":"GB",
    "wof:name":"NG23 6RH",
    "wof:placetype":"postalcode"
},
  "geometry": {"coordinates":[-0.81642832250898,53.20841325309898],"type":"Point"}
}