{
  "type": "Feature",
  "properties": {
    "iso:country":"GB",
    "wof:name":"SY10 8QB",
    "wof:placetype":"postalcode"
},
  "geometry": {"coordinates":[-3.05843345663004,52.78199557891212],"type":"Point"}
}