{
  "type": "Feature",
  "properties": {
    "date:inception_lower": "1981-06-01",
    "date:inception_upper": "1981-06-01",
    "iso:country": "GB",
    "wof:name": "SY10 8QB",
    "wof:placetype": "postalcode"
  },
  "geometry": {"coordinates":[-3.059983,52.783003],"type":"Point"}
}
