{
  "type": "Feature",
  "properties": {
    "iso:country":"GB",
    "wof:name":"PA8 7ER",
    "wof:placetype":"postalcode"
},
  "geometry": {"coordinates":[-4.44606471237998,55.89066530163499],"type":"Point"}
}