{
  "type": "Feature",
  "properties": {
    "date:inception_lower":"2006-07-01",
    "date:inception_upper":"2006-07-31",
    "iso:country":"GB",
    "wof:name":"SE10 0JE",
    "wof:placetype":"postalcode"
},
  "geometry": {"coordinates":[0.011171,51.485341],"type":"Point"}
}