{
  "type": "Feature",
  "properties": {
    "date:inception_lower": "1980-01-01",
    "date:inception_upper": "1980-01-01",
    "iso:country": "GB",
    "wof:name": "TW13 4AB",
    "wof:placetype": "postalcode"
  },
  "geometry": {"coordinates":[-0.411155,51.443553],"type":"Point"}
}
