{
  "type": "Feature",
  "properties": {
    "iso:country":"GB",
    "wof:name":"IV22 2LQ",
    "wof:placetype":"postalcode"
},
  "geometry": {"coordinates":[-5.67557574460826,57.82594080763986],"type":"Point"}
}