{
  "type": "Feature",
  "properties": {
    "iso:country": "GB",
    "wof:name": "IV22 2LQ",
    "wof:placetype": "postalcode"
  },
  "geometry": {"coordinates":[-5.675576,57.825941],"type":"Point"}
}
