{
  "type": "Feature",
  "properties": {
    "iso:country":"GB",
    "wof:name":"LS6 1PN",
    "wof:placetype":"postalcode"
},
  "geometry": {"coordinates":[-1.57035659875407,53.80902726065246],"type":"Point"}
}