{
  "type": "Feature",
  "properties": {
    "iso:country":"GB",
    "wof:name":"RG22 5JQ",
    "wof:placetype":"postalcode"
},
  "geometry": {"coordinates":[-1.13650713575351,51.25119415203134],"type":"Point"}
}