{
  "type": "Feature",
  "properties": {
    "iso:country": "GB",
    "wof:name": "PE12 6SU",
    "wof:placetype": "postalcode"
  },
  "geometry": {"coordinates":[-0.011445,52.785503],"type":"Point"}
}
