{
  "type": "Feature",
  "properties": {
    "iso:country":"GB",
    "wof:name":"NG17 3JF",
    "wof:placetype":"postalcode"
},
  "geometry": {"coordinates":[-1.31529177073914,53.14432041082583],"type":"Point"}
}