{
  "type": "Feature",
  "properties": {
    "iso:country":"GB",
    "wof:name":"DN32 8QJ",
    "wof:placetype":"postalcode"
},
  "geometry": {"coordinates":[-0.0549275446956,53.55286807963336],"type":"Point"}
}