{
  "type": "Feature",
  "properties": {
    "iso:country": "GB",
    "wof:name": "DN32 8QJ",
    "wof:placetype": "postalcode"
  },
  "geometry": {"coordinates":[-0.054927,53.552868],"type":"Point"}
}
