{
  "type": "Feature",
  "properties": {
    "iso:country":"GB",
    "wof:name":"RM9 5DG",
    "wof:placetype":"postalcode"
},
  "geometry": {"coordinates":[0.14374293568563,51.5473542085162],"type":"Point"}
}