{
  "type": "Feature",
  "properties": {
    "iso:country": "GB",
    "wof:name": "YO41 1HR",
    "wof:placetype": "postalcode"
  },
  "geometry": {"coordinates":[-0.851668,53.983116],"type":"Point"}
}
