{
  "type": "Feature",
  "properties": {
    "iso:country":"GB",
    "wof:name":"YO41 1HR",
    "wof:placetype":"postalcode"
},
  "geometry": {"coordinates":[-0.85170589035447,53.98307990806293],"type":"Point"}
}