{
  "type": "Feature",
  "properties": {
    "date:inception_lower":"1992-01-01",
    "date:inception_upper":"1992-01-31",
    "iso:country":"GB",
    "wof:name":"PE3 9NY",
    "wof:placetype":"postalcode"
},
  "geometry": {"coordinates":[-0.284926,52.573959],"type":"Point"}
}