{
  "type": "Feature",
  "properties": {
    "iso:country":"GB",
    "wof:name":"PE3 9NY",
    "wof:placetype":"postalcode"
},
  "geometry": {"coordinates":[-0.28492600181259,52.57395867727825],"type":"Point"}
}