{
  "type": "Feature",
  "properties": {
    "iso:country":"GB",
    "wof:name":"SN7 7NZ",
    "wof:placetype":"postalcode"
},
  "geometry": {"coordinates":[-1.58164002292255,51.62417458098456],"type":"Point"}
}