{
  "type": "Feature",
  "properties": {
    "iso:country":"GB",
    "wof:name":"W1F 8TB",
    "wof:placetype":"postalcode"
},
  "geometry": {"coordinates":[-0.13611141353436,51.51480648017071],"type":"Point"}
}