{
  "type": "Feature",
  "properties": {
    "date:inception_lower": "1990-07-01",
    "date:inception_upper": "1990-07-01",
    "iso:country": "GB",
    "wof:name": "BL9 8QF",
    "wof:placetype": "postalcode"
  },
  "geometry": {"coordinates":[-2.283016,53.573314],"type":"Point"}
}
