{
  "type": "Feature",
  "properties": {
    "iso:country": "GB",
    "wof:name": "BL9 8QF",
    "wof:placetype": "postalcode"
  },
  "geometry": {"coordinates":[-2.283304,53.57343],"type":"Point"}
}
