{
  "type": "Feature",
  "properties": {
    "iso:country":"GB",
    "wof:name":"BL9 8QF",
    "wof:placetype":"postalcode"
},
  "geometry": {"coordinates":[-2.28330631570008,53.5734138372962],"type":"Point"}
}