{
  "type": "Feature",
  "properties": {
    "iso:country":"GB",
    "wof:name":"NR5 0UP",
    "wof:placetype":"postalcode"
},
  "geometry": {"coordinates":[1.19864620188651,52.64576402083239],"type":"Point"}
}