{
  "type": "Feature",
  "properties": {
    "date:inception_lower": "2009-09-01",
    "date:inception_upper": "2009-09-01",
    "iso:country": "GB",
    "wof:name": "NR5 0UP",
    "wof:placetype": "postalcode"
  },
  "geometry": {"coordinates":[1.198646,52.645764],"type":"Point"}
}
