{
  "type": "Feature",
  "properties": {
    "iso:country":"GB",
    "wof:name":"AB24 2QJ",
    "wof:placetype":"postalcode"
},
  "geometry": {"coordinates":[-2.11626141771232,57.16806741317992],"type":"Point"}
}