{
  "type": "Feature",
  "properties": {
    "date:inception_lower":"1980-01-01",
    "date:inception_upper":"1980-01-31",
    "iso:country":"GB",
    "wof:name":"SY8 4HR",
    "wof:placetype":"postalcode"
},
  "geometry": {"coordinates":[-2.747424,52.298723],"type":"Point"}
}