{
  "type": "Feature",
  "properties": {
    "iso:country":"GB",
    "wof:name":"SY8 4HR",
    "wof:placetype":"postalcode"
},
  "geometry": {"coordinates":[-2.74739947090189,52.29901667337538],"type":"Point"}
}