{
  "type": "Feature",
  "properties": {
    "iso:country": "GB",
    "wof:name": "DL6 1DJ",
    "wof:placetype": "postalcode"
  },
  "geometry": {"coordinates":[-1.426522,54.330641],"type":"Point"}
}
