{
  "type": "Feature",
  "properties": {
    "iso:country":"GB",
    "wof:name":"DL6 1DJ",
    "wof:placetype":"postalcode"
},
  "geometry": {"coordinates":[-1.42651291900188,54.33062859794523],"type":"Point"}
}