{
  "type": "Feature",
  "properties": {
    "date:inception_lower": "2017-01-01",
    "date:inception_upper": "2017-01-01",
    "iso:country": "GB",
    "wof:name": "RH10 0NB",
    "wof:placetype": "postalcode"
  },
  "geometry": {"coordinates":[-0.18815,51.116853],"type":"Point"}
}
