{
  "type": "Feature",
  "properties": {
    "iso:country":"GB",
    "wof:name":"LA2 0LP",
    "wof:placetype":"postalcode"
},
  "geometry": {"coordinates":[-2.79297030218556,53.99295611862121],"type":"Point"}
}