{
  "type": "Feature",
  "properties": {
    "iso:country":"GB",
    "wof:name":"BN13 3UP",
    "wof:placetype":"postalcode"
},
  "geometry": {"coordinates":[-0.45902532391483,50.84256237064959],"type":"Point"}
}