{
  "type": "Feature",
  "properties": {
    "iso:country":"GB",
    "wof:name":"LL22 8NG",
    "wof:placetype":"postalcode"
},
  "geometry": {"coordinates":[-3.64703639127693,53.25909725931734],"type":"Point"}
}