{
  "type": "Feature",
  "properties": {
    "iso:country": "GB",
    "wof:name": "W11 3LW",
    "wof:placetype": "postalcode"
  },
  "geometry": {"coordinates":[-0.205929,51.508485],"type":"Point"}
}
