{
  "type": "Feature",
  "properties": {
    "iso:country":"GB",
    "wof:name":"W11 3LW",
    "wof:placetype":"postalcode"
},
  "geometry": {"coordinates":[-0.20592877012094,51.50848540256489],"type":"Point"}
}