{
  "type": "Feature",
  "properties": {
    "iso:country":"GB",
    "wof:name":"BR5 2RY",
    "wof:placetype":"postalcode"
},
  "geometry": {"coordinates":[0.10046573051626,51.40551950295021],"type":"Point"}
}