{
  "type": "Feature",
  "properties": {
    "date:inception_lower": "1980-01-01",
    "date:inception_upper": "1980-01-01",
    "iso:country": "GB",
    "wof:name": "BR5 2RY",
    "wof:placetype": "postalcode"
  },
  "geometry": {"coordinates":[0.100466,51.405519],"type":"Point"}
}
