{
  "type": "Feature",
  "properties": {
    "iso:country": "GB",
    "wof:name": "SA1 6FR",
    "wof:placetype": "postalcode"
  },
  "geometry": {"coordinates":[-3.945634,51.62951],"type":"Point"}
}
