{
  "type": "Feature",
  "properties": {
    "iso:country":"GB",
    "wof:name":"SA1 6FR",
    "wof:placetype":"postalcode"
},
  "geometry": {"coordinates":[-3.94563367721782,51.62950971931638],"type":"Point"}
}