{
  "type": "Feature",
  "properties": {
    "iso:country": "GB",
    "wof:name": "AB42 1ER",
    "wof:placetype": "postalcode"
  },
  "geometry": {"coordinates":[-1.791519,57.511387],"type":"Point"}
}
