{
  "type": "Feature",
  "properties": {
    "iso:country":"GB",
    "wof:name":"SN15 1DT",
    "wof:placetype":"postalcode"
},
  "geometry": {"coordinates":[-2.12362433423691,51.4719639147343],"type":"Point"}
}