{
  "type": "Feature",
  "properties": {
    "iso:country":"GB",
    "wof:name":"OX1 1LD",
    "wof:placetype":"postalcode"
},
  "geometry": {"coordinates":[-1.26294039713623,51.75073392484757],"type":"Point"}
}