{
  "type": "Feature",
  "properties": {
    "iso:country": "GB",
    "wof:name": "OX15 4NQ",
    "wof:placetype": "postalcode"
  },
  "geometry": {"coordinates":[-1.372099,52.021475],"type":"Point"}
}
