{
  "type": "Feature",
  "properties": {
    "date:inception_lower":"1980-01-01",
    "date:inception_upper":"1980-01-31",
    "iso:country":"GB",
    "wof:name":"OX15 4NQ",
    "wof:placetype":"postalcode"
},
  "geometry": {"coordinates":[-1.372099,52.021475],"type":"Point"}
}