{
  "type": "Feature",
  "properties": {
    "iso:country": "GB",
    "wof:name": "ME5 8RB",
    "wof:placetype": "postalcode"
  },
  "geometry": {"coordinates":[0.536586,51.336964],"type":"Point"}
}
