{
  "type": "Feature",
  "properties": {
    "iso:country":"GB",
    "wof:name":"ME5 8RB",
    "wof:placetype":"postalcode"
},
  "geometry": {"coordinates":[0.53658577611498,51.33696418865715],"type":"Point"}
}