{
  "type": "Feature",
  "properties": {
    "iso:country": "GB",
    "wof:name": "SN6 8FH",
    "wof:placetype": "postalcode"
  },
  "geometry": {"coordinates":[-1.665854,51.599171],"type":"Point"}
}
