{
  "type": "Feature",
  "properties": {
    "iso:country":"GB",
    "wof:name":"N14 6JA",
    "wof:placetype":"postalcode"
},
  "geometry": {"coordinates":[-0.12785599489087,51.63414851462832],"type":"Point"}
}