{
  "type": "Feature",
  "properties": {
    "iso:country":"GB",
    "wof:name":"BA15 1TQ",
    "wof:placetype":"postalcode"
},
  "geometry": {"coordinates":[-2.25206919919028,51.3555502325047],"type":"Point"}
}