{
  "type": "Feature",
  "properties": {
    "date:inception_lower":"1980-01-01",
    "date:inception_upper":"1980-01-31",
    "iso:country":"GB",
    "wof:name":"BA15 1TQ",
    "wof:placetype":"postalcode"
},
  "geometry": {"coordinates":[-2.252069,51.35555],"type":"Point"}
}