{
  "type": "Feature",
  "properties": {
    "iso:country":"GB",
    "wof:name":"OL16 3AE",
    "wof:placetype":"postalcode"
},
  "geometry": {"coordinates":[-2.12750589212909,53.61820055949244],"type":"Point"}
}