{
  "type": "Feature",
  "properties": {
    "iso:country": "GB",
    "wof:name": "SW9 6LW",
    "wof:placetype": "postalcode"
  },
  "geometry": {"coordinates":[-0.1124,51.472675],"type":"Point"}
}
