{
  "type": "Feature",
  "properties": {
    "iso:country":"GB",
    "wof:name":"SW9 6LW",
    "wof:placetype":"postalcode"
},
  "geometry": {"coordinates":[-0.11239708649207,51.47274668439114],"type":"Point"}
}