{
  "type": "Feature",
  "properties": {
    "iso:country": "GB",
    "wof:name": "ML9 2PJ",
    "wof:placetype": "postalcode"
  },
  "geometry": {"coordinates":[-3.960098,55.723084],"type":"Point"}
}
