{
  "type": "Feature",
  "properties": {
    "iso:country":"GB",
    "wof:name":"ML9 2PJ",
    "wof:placetype":"postalcode"
},
  "geometry": {"coordinates":[-3.96011075043235,55.72308640021032],"type":"Point"}
}