{
  "type": "Feature",
  "properties": {
    "iso:country":"GB",
    "wof:name":"RG9 1SS",
    "wof:placetype":"postalcode"
},
  "geometry": {"coordinates":[-0.91182714566564,51.53199378261707],"type":"Point"}
}