{
  "type": "Feature",
  "properties": {
    "iso:country": "GB",
    "wof:name": "RG9 1SS",
    "wof:placetype": "postalcode"
  },
  "geometry": {"coordinates":[-0.911827,51.531994],"type":"Point"}
}
