{
  "type": "Feature",
  "properties": {
    "iso:country":"GB",
    "wof:name":"CM3 2AU",
    "wof:placetype":"postalcode"
},
  "geometry": {"coordinates":[0.56526867318787,51.82194624352445],"type":"Point"}
}