{
  "type": "Feature",
  "properties": {
    "date:inception_lower": "1995-07-01",
    "date:inception_upper": "1995-07-01",
    "iso:country": "GB",
    "wof:name": "WA8 3XR",
    "wof:placetype": "postalcode"
  },
  "geometry": {"coordinates":[-2.67788,53.39137],"type":"Point"}
}
