{
  "type": "Feature",
  "properties": {
    "iso:country":"GB",
    "wof:name":"WA8 3XR",
    "wof:placetype":"postalcode"
},
  "geometry": {"coordinates":[-2.68271202448232,53.39260330504269],"type":"Point"}
}