{
  "type": "Feature",
  "properties": {
    "iso:country": "GB",
    "wof:name": "WA8 3XR",
    "wof:placetype": "postalcode"
  },
  "geometry": {"coordinates":[-2.682712,53.392619],"type":"Point"}
}
