{
  "type": "Feature",
  "properties": {
    "date:inception_lower": "1980-01-01",
    "date:inception_upper": "1980-01-01",
    "iso:country": "GB",
    "wof:name": "ML4 3BY",
    "wof:placetype": "postalcode"
  },
  "geometry": {"coordinates":[-4.034274,55.813207],"type":"Point"}
}
