{
  "type": "Feature",
  "properties": {
    "iso:country":"GB",
    "wof:name":"ML4 3BY",
    "wof:placetype":"postalcode"
},
  "geometry": {"coordinates":[-4.03427394994507,55.81320696683309],"type":"Point"}
}