{
  "type": "Feature",
  "properties": {
    "iso:country":"GB",
    "wof:name":"RH2 0JJ",
    "wof:placetype":"postalcode"
},
  "geometry": {"coordinates":[-0.18157935738002,51.24730562481374],"type":"Point"}
}