{
  "type": "Feature",
  "properties": {
    "iso:country":"GB",
    "wof:name":"TN8 6UP",
    "wof:placetype":"postalcode"
},
  "geometry": {"coordinates":[0.05925236334411,51.2269303767229],"type":"Point"}
}