{
  "type": "Feature",
  "properties": {
    "iso:country":"GB",
    "wof:name":"OX26 6UA",
    "wof:placetype":"postalcode"
},
  "geometry": {"coordinates":[-1.14105621802468,51.89562712228745],"type":"Point"}
}