{
  "type": "Feature",
  "properties": {
    "date:inception_lower":"1980-01-01",
    "date:inception_upper":"1980-01-31",
    "iso:country":"GB",
    "wof:name":"LL42 1AZ",
    "wof:placetype":"postalcode"
},
  "geometry": {"coordinates":[-4.075744,52.741931],"type":"Point"}
}