{
  "type": "Feature",
  "properties": {
    "date:inception_lower":"1980-01-01",
    "date:inception_upper":"1980-01-31",
    "iso:country":"GB",
    "wof:name":"ME9 8NY",
    "wof:placetype":"postalcode"
},
  "geometry": {"coordinates":[0.698687,51.34837],"type":"Point"}
}