{
  "type": "Feature",
  "properties": {
    "iso:country":"GB",
    "wof:name":"ME9 8NY",
    "wof:placetype":"postalcode"
},
  "geometry": {"coordinates":[0.69864291376159,51.34836962578713],"type":"Point"}
}