{
  "type": "Feature",
  "properties": {
    "iso:country":"GB",
    "wof:name":"CH66 2JQ",
    "wof:placetype":"postalcode"
},
  "geometry": {"coordinates":[-2.92212360330957,53.27280650059429],"type":"Point"}
}