{
  "type": "Feature",
  "properties": {
    "iso:country":"GB",
    "wof:name":"KA3 1RB",
    "wof:placetype":"postalcode"
},
  "geometry": {"coordinates":[-4.50501853122986,55.62527161832907],"type":"Point"}
}