{
  "type": "Feature",
  "properties": {
    "iso:country": "GB",
    "wof:name": "CF31 2AX",
    "wof:placetype": "postalcode"
  },
  "geometry": {"coordinates":[-3.559972,51.517492],"type":"Point"}
}
