{
  "type": "Feature",
  "properties": {
    "iso:country":"GB",
    "wof:name":"CF31 2AX",
    "wof:placetype":"postalcode"
},
  "geometry": {"coordinates":[-3.56008521112662,51.51743499934813],"type":"Point"}
}