{
  "type": "Feature",
  "properties": {
    "iso:country":"GB",
    "wof:name":"CF34 0SB",
    "wof:placetype":"postalcode"
},
  "geometry": {"coordinates":[-3.6603994645077,51.62988089000429],"type":"Point"}
}