{
  "type": "Feature",
  "properties": {
    "iso:country":"GB",
    "wof:name":"RG6 4BE",
    "wof:placetype":"postalcode"
},
  "geometry": {"coordinates":[-0.91932785501137,51.42517693527387],"type":"Point"}
}