{
  "type": "Feature",
  "properties": {
    "date:inception_lower":"1998-06-01",
    "date:inception_upper":"1998-06-30",
    "iso:country":"GB",
    "wof:name":"SL1 2DS",
    "wof:placetype":"postalcode"
},
  "geometry": {"coordinates":[-0.594218,51.503962],"type":"Point"}
}