{
  "type": "Feature",
  "properties": {
    "iso:country":"GB",
    "wof:name":"SL1 2DS",
    "wof:placetype":"postalcode"
},
  "geometry": {"coordinates":[-0.59421832224509,51.50396222077008],"type":"Point"}
}