{
  "type": "Feature",
  "properties": {
    "iso:country": "GB",
    "wof:name": "GL15 4UB",
    "wof:placetype": "postalcode"
  },
  "geometry": {"coordinates":[-2.530123,51.760878],"type":"Point"}
}
