{
  "type": "Feature",
  "properties": {
    "iso:country":"GB",
    "wof:name":"GL15 4UB",
    "wof:placetype":"postalcode"
},
  "geometry": {"coordinates":[-2.53015028293417,51.76078362261291],"type":"Point"}
}