{
  "type": "Feature",
  "properties": {
    "iso:country":"GB",
    "wof:name":"B97 4NZ",
    "wof:placetype":"postalcode"
},
  "geometry": {"coordinates":[-1.94820701110127,52.29818922983139],"type":"Point"}
}