{
  "type": "Feature",
  "properties": {
    "date:inception_lower": "1980-01-01",
    "date:inception_upper": "1980-01-01",
    "iso:country": "GB",
    "wof:name": "DL3 6PA",
    "wof:placetype": "postalcode"
  },
  "geometry": {"coordinates":[-1.560637,54.530857],"type":"Point"}
}
