{
  "type": "Feature",
  "properties": {
    "iso:country":"GB",
    "wof:name":"DL3 6PA",
    "wof:placetype":"postalcode"
},
  "geometry": {"coordinates":[-1.56063704874794,54.53085733408527],"type":"Point"}
}