{
  "type": "Feature",
  "properties": {
    "iso:country": "GB",
    "wof:name": "WA3 6DN",
    "wof:placetype": "postalcode"
  },
  "geometry": {"coordinates":[-2.517779,53.404741],"type":"Point"}
}
