{
  "type": "Feature",
  "properties": {
    "iso:country":"GB",
    "wof:name":"WA3 6DN",
    "wof:placetype":"postalcode"
},
  "geometry": {"coordinates":[-2.51777901859135,53.40474054568725],"type":"Point"}
}