{
  "type": "Feature",
  "properties": {
    "iso:country":"GB",
    "wof:name":"DN6 8JS",
    "wof:placetype":"postalcode"
},
  "geometry": {"coordinates":[-1.20188394224962,53.58791593516878],"type":"Point"}
}