{
  "type": "Feature",
  "properties": {
    "iso:country": "GB",
    "wof:name": "BS29 6BP",
    "wof:placetype": "postalcode"
  },
  "geometry": {"coordinates":[-2.861775,51.326724],"type":"Point"}
}
