{
  "type": "Feature",
  "properties": {
    "date:inception_lower":"1997-12-01",
    "date:inception_upper":"1997-12-31",
    "iso:country":"GB",
    "wof:name":"BS29 6BP",
    "wof:placetype":"postalcode"
},
  "geometry": {"coordinates":[-2.861711,51.326709],"type":"Point"}
}