{
  "type": "Feature",
  "properties": {
    "iso:country":"GB",
    "wof:name":"BS29 6BP",
    "wof:placetype":"postalcode"
},
  "geometry": {"coordinates":[-2.86171114881086,51.32670928015857],"type":"Point"}
}