{
  "type": "Feature",
  "properties": {
    "iso:country":"GB",
    "wof:name":"ST8 6DR",
    "wof:placetype":"postalcode"
},
  "geometry": {"coordinates":[-2.16950622062601,53.11660146064497],"type":"Point"}
}