{
  "type": "Feature",
  "properties": {
    "date:inception_lower": "1980-01-01",
    "date:inception_upper": "1980-01-01",
    "iso:country": "GB",
    "wof:name": "ST8 6DR",
    "wof:placetype": "postalcode"
  },
  "geometry": {"coordinates":[-2.169506,53.116601],"type":"Point"}
}
