{
  "type": "Feature",
  "properties": {
    "date:inception_lower": "1980-01-01",
    "date:inception_upper": "1980-01-01",
    "iso:country": "GB",
    "wof:name": "NR14 6HE",
    "wof:placetype": "postalcode"
  },
  "geometry": {"coordinates":[1.4815,52.542535],"type":"Point"}
}
