{
  "type": "Feature",
  "properties": {
    "iso:country":"GB",
    "wof:name":"NR14 6HE",
    "wof:placetype":"postalcode"
},
  "geometry": {"coordinates":[1.48149950627405,52.54253505140922],"type":"Point"}
}