{
  "type": "Feature",
  "properties": {
    "iso:country":"GB",
    "wof:name":"NN3 7LG",
    "wof:placetype":"postalcode"
},
  "geometry": {"coordinates":[-0.86014316137086,52.27976492698759],"type":"Point"}
}