{
  "type": "Feature",
  "properties": {
    "iso:country":"GB",
    "wof:name":"AL4 9DP",
    "wof:placetype":"postalcode"
},
  "geometry": {"coordinates":[-0.3011953461383,51.7830402515329],"type":"Point"}
}