{
  "type": "Feature",
  "properties": {
    "date:inception_lower": "1980-01-01",
    "date:inception_upper": "1980-01-01",
    "iso:country": "GB",
    "wof:name": "BR6 9TF",
    "wof:placetype": "postalcode"
  },
  "geometry": {"coordinates":[0.112604,51.369115],"type":"Point"}
}
