{
  "type": "Feature",
  "properties": {
    "iso:country": "GB",
    "wof:name": "BR6 9TF",
    "wof:placetype": "postalcode"
  },
  "geometry": {"coordinates":[0.112604,51.369115],"type":"Point"}
}
