{
  "type": "Feature",
  "properties": {
    "iso:country":"GB",
    "wof:name":"BR6 9TF",
    "wof:placetype":"postalcode"
},
  "geometry": {"coordinates":[0.11261908893582,51.36908625820192],"type":"Point"}
}