{
  "type": "Feature",
  "properties": {
    "date:inception_lower": "1980-01-01",
    "date:inception_upper": "1980-01-01",
    "iso:country": "GB",
    "wof:name": "HR2 6EB",
    "wof:placetype": "postalcode"
  },
  "geometry": {"coordinates":[-2.706427,52.042425],"type":"Point"}
}
