{
  "type": "Feature",
  "properties": {
    "iso:country": "GB",
    "wof:name": "EX36 4QY",
    "wof:placetype": "postalcode"
  },
  "geometry": {"coordinates":[-3.711908,50.986554],"type":"Point"}
}
