{
  "type": "Feature",
  "properties": {
    "date:inception_lower":"1998-12-01",
    "date:inception_upper":"1998-12-31",
    "iso:country":"GB",
    "wof:name":"EX36 4QY",
    "wof:placetype":"postalcode"
},
  "geometry": {"coordinates":[-3.711908,50.986554],"type":"Point"}
}