{
  "type": "Feature",
  "properties": {
    "iso:country":"GB",
    "wof:name":"EX36 4QY",
    "wof:placetype":"postalcode"
},
  "geometry": {"coordinates":[-3.711907845696,50.98655425669268],"type":"Point"}
}