{
  "type": "Feature",
  "properties": {
    "iso:country":"GB",
    "wof:name":"BH21 2SQ",
    "wof:placetype":"postalcode"
},
  "geometry": {"coordinates":[-1.95786573068691,50.81067688220978],"type":"Point"}
}