{
  "type": "Feature",
  "properties": {
    "date:inception_lower": "2006-09-01",
    "date:inception_upper": "2006-09-01",
    "iso:country": "GB",
    "wof:name": "CB2 8RL",
    "wof:placetype": "postalcode"
  },
  "geometry": {"coordinates":[0.137897,52.186783],"type":"Point"}
}
