{
  "type": "Feature",
  "properties": {
    "iso:country":"GB",
    "wof:name":"CB2 8RL",
    "wof:placetype":"postalcode"
},
  "geometry": {"coordinates":[0.13789713209131,52.18678312598455],"type":"Point"}
}