{
  "type": "Feature",
  "properties": {
    "iso:country":"GB",
    "wof:name":"W10 6AB",
    "wof:placetype":"postalcode"
},
  "geometry": {"coordinates":[-0.22649721234112,51.5217203094354],"type":"Point"}
}