{
  "type": "Feature",
  "properties": {
    "date:inception_lower": "2000-06-01",
    "date:inception_upper": "2000-06-01",
    "iso:country": "GB",
    "wof:name": "NN7 3RY",
    "wof:placetype": "postalcode"
  },
  "geometry": {"coordinates":[-0.943049,52.174369],"type":"Point"}
}
