{
  "type": "Feature",
  "properties": {
    "iso:country": "GB",
    "wof:name": "SA15 4LN",
    "wof:placetype": "postalcode"
  },
  "geometry": {"coordinates":[-4.148894,51.697543],"type":"Point"}
}
