{
  "type": "Feature",
  "properties": {
    "iso:country":"GB",
    "wof:name":"SA15 4LN",
    "wof:placetype":"postalcode"
},
  "geometry": {"coordinates":[-4.14876874001257,51.69749391604119],"type":"Point"}
}