{
  "type": "Feature",
  "properties": {
    "date:inception_lower": "1980-01-01",
    "date:inception_upper": "1980-01-01",
    "iso:country": "GB",
    "wof:name": "SS0 9SY",
    "wof:placetype": "postalcode"
  },
  "geometry": {"coordinates":[0.676889,51.545985],"type":"Point"}
}
