{
  "type": "Feature",
  "properties": {
    "iso:country":"GB",
    "wof:name":"SS0 9SY",
    "wof:placetype":"postalcode"
},
  "geometry": {"coordinates":[0.67688891662411,51.5459845929328],"type":"Point"}
}