{
  "type": "Feature",
  "properties": {
    "date:inception_lower": "1980-01-01",
    "date:inception_upper": "1980-01-01",
    "iso:country": "GB",
    "wof:name": "KT23 3EH",
    "wof:placetype": "postalcode"
  },
  "geometry": {"coordinates":[-0.37887,51.283513],"type":"Point"}
}
