{
  "type": "Feature",
  "properties": {
    "iso:country": "GB",
    "wof:name": "KT23 3EH",
    "wof:placetype": "postalcode"
  },
  "geometry": {"coordinates":[-0.37887,51.283513],"type":"Point"}
}
