{
  "type": "Feature",
  "properties": {
    "iso:country":"GB",
    "wof:name":"SW18 5DW",
    "wof:placetype":"postalcode"
},
  "geometry": {"coordinates":[-0.20155725680092,51.44454480335789],"type":"Point"}
}