{
  "type": "Feature",
  "properties": {
    "iso:country":"GB",
    "wof:name":"UB7 0LB",
    "wof:placetype":"postalcode"
},
  "geometry": {"coordinates":[-0.48000624068858,51.48349239042208],"type":"Point"}
}