{
  "type": "Feature",
  "properties": {
    "iso:country":"GB",
    "wof:name":"G73 2BP",
    "wof:placetype":"postalcode"
},
  "geometry": {"coordinates":[-4.23013096263134,55.82108917527508],"type":"Point"}
}