{
  "type": "Feature",
  "properties": {
    "iso:country": "GB",
    "wof:name": "DH9 6XZ",
    "wof:placetype": "postalcode"
  },
  "geometry": {"coordinates":[-1.678383,54.859025],"type":"Point"}
}
