{
  "type": "Feature",
  "properties": {
    "iso:country":"GB",
    "wof:name":"DH9 6XZ",
    "wof:placetype":"postalcode"
},
  "geometry": {"coordinates":[-1.67880517060422,54.85886404904485],"type":"Point"}
}