{
  "type": "Feature",
  "properties": {
    "iso:country": "GB",
    "wof:name": "KA3 1DQ",
    "wof:placetype": "postalcode"
  },
  "geometry": {"coordinates":[-4.494175,55.615372],"type":"Point"}
}
