{
  "type": "Feature",
  "properties": {
    "date:inception_lower": "1998-12-01",
    "date:inception_upper": "1998-12-01",
    "iso:country": "GB",
    "wof:name": "ST18 9NR",
    "wof:placetype": "postalcode"
  },
  "geometry": {"coordinates":[-2.20803,52.830393],"type":"Point"}
}
