{
  "type": "Feature",
  "properties": {
    "iso:country":"GB",
    "wof:name":"ST18 9NR",
    "wof:placetype":"postalcode"
},
  "geometry": {"coordinates":[-2.20789768024612,52.83020686544744],"type":"Point"}
}