{
  "type": "Feature",
  "properties": {
    "iso:country": "GB",
    "wof:name": "ST18 9NR",
    "wof:placetype": "postalcode"
  },
  "geometry": {"coordinates":[-2.207895,52.830222],"type":"Point"}
}
