{
  "type": "Feature",
  "properties": {
    "iso:country":"GB",
    "wof:name":"B92 0BQ",
    "wof:placetype":"postalcode"
},
  "geometry": {"coordinates":[-1.69392593395687,52.42962742458052],"type":"Point"}
}