{
  "type": "Feature",
  "properties": {
    "iso:country": "GB",
    "wof:name": "B92 0BQ",
    "wof:placetype": "postalcode"
  },
  "geometry": {"coordinates":[-1.693926,52.429627],"type":"Point"}
}
