{
  "type": "Feature",
  "properties": {
    "iso:country":"GB",
    "wof:name":"TN29 0TL",
    "wof:placetype":"postalcode"
},
  "geometry": {"coordinates":[1.01505687492924,51.03663017677305],"type":"Point"}
}