{
  "type": "Feature",
  "properties": {
    "date:inception_lower": "1980-01-01",
    "date:inception_upper": "1980-01-01",
    "iso:country": "GB",
    "wof:name": "TN29 0TL",
    "wof:placetype": "postalcode"
  },
  "geometry": {"coordinates":[1.015254,51.036708],"type":"Point"}
}
