{
  "type": "Feature",
  "properties": {
    "iso:country": "GB",
    "wof:name": "GU23 6ES",
    "wof:placetype": "postalcode"
  },
  "geometry": {"coordinates":[-0.499102,51.290233],"type":"Point"}
}
