{
  "type": "Feature",
  "properties": {
    "iso:country":"GB",
    "wof:name":"GU23 6ES",
    "wof:placetype":"postalcode"
},
  "geometry": {"coordinates":[-0.49910230054898,51.29023265600629],"type":"Point"}
}