{
  "type": "Feature",
  "properties": {
    "iso:country":"GB",
    "wof:name":"ST17 0TD",
    "wof:placetype":"postalcode"
},
  "geometry": {"coordinates":[-2.05595372543301,52.76961622222613],"type":"Point"}
}