{
  "type": "Feature",
  "properties": {
    "date:inception_lower": "1998-06-01",
    "date:inception_upper": "1998-06-01",
    "iso:country": "GB",
    "wof:name": "HP21 8JL",
    "wof:placetype": "postalcode"
  },
  "geometry": {"coordinates":[-0.809015,51.806832],"type":"Point"}
}
