{
  "type": "Feature",
  "properties": {
    "iso:country":"GB",
    "wof:name":"B73 6DZ",
    "wof:placetype":"postalcode"
},
  "geometry": {"coordinates":[-1.82926107273141,52.56340059904056],"type":"Point"}
}