{
  "type": "Feature",
  "properties": {
    "iso:country": "GB",
    "wof:name": "CO9 4DG",
    "wof:placetype": "postalcode"
  },
  "geometry": {"coordinates":[0.530606,52.008734],"type":"Point"}
}
