{
  "type": "Feature",
  "properties": {
    "iso:country": "GB",
    "wof:name": "CF81 8RF",
    "wof:placetype": "postalcode"
  },
  "geometry": {"coordinates":[-3.230914,51.693023],"type":"Point"}
}
