{
  "type": "Feature",
  "properties": {
    "date:inception_lower": "1996-06-01",
    "date:inception_upper": "1996-06-01",
    "iso:country": "GB",
    "wof:name": "SY16 1LW",
    "wof:placetype": "postalcode"
  },
  "geometry": {"coordinates":[-3.320407,52.511241],"type":"Point"}
}
