{
  "type": "Feature",
  "properties": {
    "iso:country":"GB",
    "wof:name":"SY16 1LW",
    "wof:placetype":"postalcode"
},
  "geometry": {"coordinates":[-3.32040741825838,52.51124095001285],"type":"Point"}
}