{
  "type": "Feature",
  "properties": {
    "iso:country": "GB",
    "wof:name": "DH4 4ZH",
    "wof:placetype": "postalcode"
  },
  "geometry": {"coordinates":[-1.488077,54.863126],"type":"Point"}
}
