{
  "type": "Feature",
  "properties": {
    "iso:country": "GB",
    "wof:name": "KA1 5SE",
    "wof:placetype": "postalcode"
  },
  "geometry": {"coordinates":[-4.568099,55.549271],"type":"Point"}
}
