{
  "type": "Feature",
  "properties": {
    "iso:country": "GB",
    "wof:name": "KA1 5SE",
    "wof:placetype": "postalcode"
  },
  "geometry": {"coordinates":[-4.567778,55.549458],"type":"Point"}
}
