{
  "type": "Feature",
  "properties": {
    "date:inception_lower": "2018-07-01",
    "date:inception_upper": "2018-07-01",
    "iso:country": "GB",
    "wof:name": "KA1 5SE",
    "wof:placetype": "postalcode"
  },
  "geometry": {"coordinates":[-4.567571,55.549678],"type":"Point"}
}
