{
  "type": "Feature",
  "properties": {
    "iso:country":"GB",
    "wof:name":"DL4 2LA",
    "wof:placetype":"postalcode"
},
  "geometry": {"coordinates":[-1.6374367457635,54.6232448584673],"type":"Point"}
}