{
  "type": "Feature",
  "properties": {
    "date:inception_lower": "1999-06-01",
    "date:inception_upper": "1999-06-01",
    "iso:country": "GB",
    "wof:name": "DD10 0NG",
    "wof:placetype": "postalcode"
  },
  "geometry": {"coordinates":[-2.288538,56.831213],"type":"Point"}
}
