{
  "type": "Feature",
  "properties": {
    "iso:country":"GB",
    "wof:name":"DD10 0NG",
    "wof:placetype":"postalcode"
},
  "geometry": {"coordinates":[-2.28853783023842,56.83121313735695],"type":"Point"}
}