{
  "type": "Feature",
  "properties": {
    "iso:country": "GB",
    "wof:name": "DT6 3AQ",
    "wof:placetype": "postalcode"
  },
  "geometry": {"coordinates":[-2.758866,50.735876],"type":"Point"}
}
