{
  "type": "Feature",
  "properties": {
    "iso:country":"GB",
    "wof:name":"NE66 3NP",
    "wof:placetype":"postalcode"
},
  "geometry": {"coordinates":[-1.63238865954409,55.39473124437694],"type":"Point"}
}