{
  "type": "Feature",
  "properties": {
    "iso:country":"GB",
    "wof:name":"M45 6DF",
    "wof:placetype":"postalcode"
},
  "geometry": {"coordinates":[-2.28538864091982,53.54403495794471],"type":"Point"}
}