{
  "type": "Feature",
  "properties": {
    "date:inception_lower":"1994-05-01",
    "date:inception_upper":"1994-05-31",
    "iso:country":"GB",
    "wof:name":"M45 6DF",
    "wof:placetype":"postalcode"
},
  "geometry": {"coordinates":[-2.285389,53.544035],"type":"Point"}
}