{
  "type": "Feature",
  "properties": {
    "iso:country":"GB",
    "wof:name":"PR7 1DA",
    "wof:placetype":"postalcode"
},
  "geometry": {"coordinates":[-2.63131349718372,53.65317610260364],"type":"Point"}
}