{
  "type": "Feature",
  "properties": {
    "date:inception_lower": "2020-09-01",
    "date:inception_upper": "2020-09-01",
    "iso:country": "GB",
    "wof:name": "KY11 8ZH",
    "wof:placetype": "postalcode"
  },
  "geometry": {"coordinates":[-3.406169,56.054146],"type":"Point"}
}
