{
  "type": "Feature",
  "properties": {
    "iso:country": "GB",
    "wof:name": "PR8 3AJ",
    "wof:placetype": "postalcode"
  },
  "geometry": {"coordinates":[-3.025387,53.617353],"type":"Point"}
}
