{
  "type": "Feature",
  "properties": {
    "iso:country": "GB",
    "wof:name": "TW14 0JN",
    "wof:placetype": "postalcode"
  },
  "geometry": {"coordinates":[-0.405379,51.456936],"type":"Point"}
}
