{
  "type": "Feature",
  "properties": {
    "iso:country":"GB",
    "wof:name":"TW14 0JN",
    "wof:placetype":"postalcode"
},
  "geometry": {"coordinates":[-0.40537870667344,51.45693633199069],"type":"Point"}
}