{
  "type": "Feature",
  "properties": {
    "iso:country":"GB",
    "wof:name":"NE65 9NL",
    "wof:placetype":"postalcode"
},
  "geometry": {"coordinates":[-1.70761671548802,55.30264216171829],"type":"Point"}
}