{
  "type": "Feature",
  "properties": {
    "date:inception_lower": "1980-01-01",
    "date:inception_upper": "1980-01-01",
    "iso:country": "GB",
    "wof:name": "NE65 9NL",
    "wof:placetype": "postalcode"
  },
  "geometry": {"coordinates":[-1.707393,55.302698],"type":"Point"}
}
