{
  "type": "Feature",
  "properties": {
    "iso:country": "GB",
    "wof:name": "NG13 8FJ",
    "wof:placetype": "postalcode"
  },
  "geometry": {"coordinates":[-0.958768,52.952733],"type":"Point"}
}
