{
  "type": "Feature",
  "properties": {
    "iso:country": "GB",
    "wof:name": "IP14 3RH",
    "wof:placetype": "postalcode"
  },
  "geometry": {"coordinates":[0.971213,52.239122],"type":"Point"}
}
