{
  "type": "Feature",
  "properties": {
    "date:inception_lower":"1980-01-01",
    "date:inception_upper":"1980-01-31",
    "iso:country":"GB",
    "wof:name":"IP14 3RH",
    "wof:placetype":"postalcode"
},
  "geometry": {"coordinates":[0.971213,52.239122],"type":"Point"}
}