{
  "type": "Feature",
  "properties": {
    "date:inception_lower":"1980-01-01",
    "date:inception_upper":"1980-01-31",
    "iso:country":"GB",
    "wof:name":"MK3 6LH",
    "wof:placetype":"postalcode"
},
  "geometry": {"coordinates":[-0.747402,52.001709],"type":"Point"}
}