{
  "type": "Feature",
  "properties": {
    "iso:country":"GB",
    "wof:name":"MK3 6LH",
    "wof:placetype":"postalcode"
},
  "geometry": {"coordinates":[-0.74741743604467,52.00166422747986],"type":"Point"}
}