{
  "type": "Feature",
  "properties": {
    "iso:country":"GB",
    "wof:name":"SL2 5DS",
    "wof:placetype":"postalcode"
},
  "geometry": {"coordinates":[-0.58360524269729,51.512601816154],"type":"Point"}
}