{
  "type": "Feature",
  "properties": {
    "iso:country":"GB",
    "wof:name":"TN26 3ED",
    "wof:placetype":"postalcode"
},
  "geometry": {"coordinates":[0.77070656083746,51.15333078358042],"type":"Point"}
}