{
  "type": "Feature",
  "properties": {
    "iso:country":"GB",
    "wof:name":"DY1 2BD",
    "wof:placetype":"postalcode"
},
  "geometry": {"coordinates":[-2.09848186402117,52.50929117478388],"type":"Point"}
}