{
  "type": "Feature",
  "properties": {
    "iso:country":"GB",
    "wof:name":"AB54 7SZ",
    "wof:placetype":"postalcode"
},
  "geometry": {"coordinates":[-2.63126267973236,57.55872734058651],"type":"Point"}
}