{
  "type": "Feature",
  "properties": {
    "date:inception_lower": "1996-06-01",
    "date:inception_upper": "1996-06-01",
    "iso:country": "GB",
    "wof:name": "AB54 7SZ",
    "wof:placetype": "postalcode"
  },
  "geometry": {"coordinates":[-2.631263,57.558727],"type":"Point"}
}
