{
  "type": "Feature",
  "properties": {
    "iso:country":"GB",
    "wof:name":"CH4 9NE",
    "wof:placetype":"postalcode"
},
  "geometry": {"coordinates":[-2.95729075032112,53.14396572485551],"type":"Point"}
}