{
  "type": "Feature",
  "properties": {
    "iso:country": "GB",
    "wof:name": "CH4 9NE",
    "wof:placetype": "postalcode"
  },
  "geometry": {"coordinates":[-2.957292,53.143981],"type":"Point"}
}
