{
  "type": "Feature",
  "properties": {
    "iso:country":"GB",
    "wof:name":"BN22 8RB",
    "wof:placetype":"postalcode"
},
  "geometry": {"coordinates":[0.30154514731137,50.78329584885896],"type":"Point"}
}