{
  "type": "Feature",
  "properties": {
    "iso:country":"GB",
    "wof:name":"S25 2QQ",
    "wof:placetype":"postalcode"
},
  "geometry": {"coordinates":[-1.21429377075913,53.36560896202624],"type":"Point"}
}