{
  "type": "Feature",
  "properties": {
    "iso:country": "GB",
    "wof:name": "HP4 1QT",
    "wof:placetype": "postalcode"
  },
  "geometry": {"coordinates":[-0.548799,51.800132],"type":"Point"}
}
