{
  "type": "Feature",
  "properties": {
    "date:inception_lower": "1980-01-01",
    "date:inception_upper": "1980-01-01",
    "iso:country": "GB",
    "wof:name": "HP4 1QT",
    "wof:placetype": "postalcode"
  },
  "geometry": {"coordinates":[-0.54879,51.800132],"type":"Point"}
}
