{
  "type": "Feature",
  "properties": {
    "iso:country":"GB",
    "wof:name":"NG32 1AD",
    "wof:placetype":"postalcode"
},
  "geometry": {"coordinates":[-0.68758703996565,52.88799111742037],"type":"Point"}
}