{
  "type": "Feature",
  "properties": {
    "date:inception_lower": "1983-03-01",
    "date:inception_upper": "1983-03-01",
    "iso:country": "GB",
    "wof:name": "TS17 6HL",
    "wof:placetype": "postalcode"
  },
  "geometry": {"coordinates":[-1.300717,54.553765],"type":"Point"}
}
