{
  "type": "Feature",
  "properties": {
    "date:inception_lower": "1994-05-01",
    "date:inception_upper": "1994-05-01",
    "iso:country": "GB",
    "wof:name": "DH8 9EP",
    "wof:placetype": "postalcode"
  },
  "geometry": {"coordinates":[-1.81308,54.832761],"type":"Point"}
}
