{
  "type": "Feature",
  "properties": {
    "iso:country":"GB",
    "wof:name":"DH8 9EP",
    "wof:placetype":"postalcode"
},
  "geometry": {"coordinates":[-1.81308035630465,54.83276055946482],"type":"Point"}
}