{
  "type": "Feature",
  "properties": {
    "iso:country": "GB",
    "wof:name": "DH8 9EP",
    "wof:placetype": "postalcode"
  },
  "geometry": {"coordinates":[-1.81308,54.832761],"type":"Point"}
}
