{
  "type": "Feature",
  "properties": {
    "iso:country": "GB",
    "wof:name": "PE20 2EH",
    "wof:placetype": "postalcode"
  },
  "geometry": {"coordinates":[-0.103945,52.907637],"type":"Point"}
}
