{
  "type": "Feature",
  "properties": {
    "iso:country":"GB",
    "wof:name":"PE20 2EH",
    "wof:placetype":"postalcode"
},
  "geometry": {"coordinates":[-0.10394471577918,52.90763714955517],"type":"Point"}
}