{
  "type": "Feature",
  "properties": {
    "iso:country":"GB",
    "wof:name":"G41 5ND",
    "wof:placetype":"postalcode"
},
  "geometry": {"coordinates":[-4.31119834658661,55.84369669720751],"type":"Point"}
}