{
  "type": "Feature",
  "properties": {
    "date:inception_lower":"2006-01-01",
    "date:inception_upper":"2006-01-31",
    "iso:country":"GB",
    "wof:name":"BL5 3ZG",
    "wof:placetype":"postalcode"
},
  "geometry": {"coordinates":[-2.510513,53.557739],"type":"Point"}
}