{
  "type": "Feature",
  "properties": {
    "iso:country": "GB",
    "wof:name": "CM7 1XS",
    "wof:placetype": "postalcode"
  },
  "geometry": {"coordinates":[0.555081,51.865524],"type":"Point"}
}
