{
  "type": "Feature",
  "properties": {
    "iso:country":"GB",
    "wof:name":"CM7 1XS",
    "wof:placetype":"postalcode"
},
  "geometry": {"coordinates":[0.55508141982369,51.86552358270124],"type":"Point"}
}