{
  "type": "Feature",
  "properties": {
    "iso:country":"GB",
    "wof:name":"HP2 4LE",
    "wof:placetype":"postalcode"
},
  "geometry": {"coordinates":[-0.45914663935333,51.75022936701156],"type":"Point"}
}