{
  "type": "Feature",
  "properties": {
    "date:inception_lower": "1998-06-01",
    "date:inception_upper": "1998-06-01",
    "iso:country": "GB",
    "wof:name": "CV37 9UY",
    "wof:placetype": "postalcode"
  },
  "geometry": {"coordinates":[-1.726039,52.202568],"type":"Point"}
}
