{
  "type": "Feature",
  "properties": {
    "iso:country":"GB",
    "wof:name":"CV37 9UY",
    "wof:placetype":"postalcode"
},
  "geometry": {"coordinates":[-1.7260391413089,52.20256783163217],"type":"Point"}
}