{
  "type": "Feature",
  "properties": {
    "date:inception_lower": "1981-09-01",
    "date:inception_upper": "1981-09-01",
    "iso:country": "GB",
    "wof:name": "SS4 3BY",
    "wof:placetype": "postalcode"
  },
  "geometry": {"coordinates":[0.689968,51.602363],"type":"Point"}
}
