{
  "type": "Feature",
  "properties": {
    "iso:country":"GB",
    "wof:name":"SS4 3BY",
    "wof:placetype":"postalcode"
},
  "geometry": {"coordinates":[0.68996754159599,51.60236298074713],"type":"Point"}
}