{
  "type": "Feature",
  "properties": {
    "iso:country": "GB",
    "wof:name": "SS4 3BY",
    "wof:placetype": "postalcode"
  },
  "geometry": {"coordinates":[0.689968,51.602363],"type":"Point"}
}
