{
  "type": "Feature",
  "properties": {
    "iso:country":"GB",
    "wof:name":"NG5 8JL",
    "wof:placetype":"postalcode"
},
  "geometry": {"coordinates":[-1.13605703477602,53.01036499805658],"type":"Point"}
}