{
  "type": "Feature",
  "properties": {
    "iso:country": "GB",
    "wof:name": "GU35 8RJ",
    "wof:placetype": "postalcode"
  },
  "geometry": {"coordinates":[-0.840654,51.113421],"type":"Point"}
}
