{
  "type": "Feature",
  "properties": {
    "iso:country":"GB",
    "wof:name":"GU35 8RJ",
    "wof:placetype":"postalcode"
},
  "geometry": {"coordinates":[-0.84065443056858,51.11342050560575],"type":"Point"}
}