{
  "type": "Feature",
  "properties": {
    "iso:country":"GB",
    "wof:name":"TW13 7JG",
    "wof:placetype":"postalcode"
},
  "geometry": {"coordinates":[-0.41612035870036,51.4364445803015],"type":"Point"}
}