{
  "type": "Feature",
  "properties": {
    "iso:country": "GB",
    "wof:name": "BS14 9SQ",
    "wof:placetype": "postalcode"
  },
  "geometry": {"coordinates":[-2.570779,51.418928],"type":"Point"}
}
