{
  "type": "Feature",
  "properties": {
    "iso:country": "GB",
    "wof:name": "SK13 5HW",
    "wof:placetype": "postalcode"
  },
  "geometry": {"coordinates":[-1.991893,53.434501],"type":"Point"}
}
