{
  "type": "Feature",
  "properties": {
    "date:inception_lower": "1997-12-01",
    "date:inception_upper": "1997-12-01",
    "iso:country": "GB",
    "wof:name": "SK13 5HW",
    "wof:placetype": "postalcode"
  },
  "geometry": {"coordinates":[-1.991893,53.434501],"type":"Point"}
}
