{
  "type": "Feature",
  "properties": {
    "iso:country": "GB",
    "wof:name": "MK17 8BX",
    "wof:placetype": "postalcode"
  },
  "geometry": {"coordinates":[-0.639266,52.043029],"type":"Point"}
}
