{
  "type": "Feature",
  "properties": {
    "date:inception_lower":"1980-01-01",
    "date:inception_upper":"1980-01-31",
    "iso:country":"GB",
    "wof:name":"MK17 8BX",
    "wof:placetype":"postalcode"
},
  "geometry": {"coordinates":[-0.639266,52.043029],"type":"Point"}
}