{
  "type": "Feature",
  "properties": {
    "iso:country":"GB",
    "wof:name":"MK17 8BX",
    "wof:placetype":"postalcode"
},
  "geometry": {"coordinates":[-0.63926613222476,52.04302932137353],"type":"Point"}
}