{
  "type": "Feature",
  "properties": {
    "iso:country":"GB",
    "wof:name":"RG9 3NA",
    "wof:placetype":"postalcode"
},
  "geometry": {"coordinates":[-0.88275755614931,51.50157103266595],"type":"Point"}
}