{
  "type": "Feature",
  "properties": {
    "date:inception_lower":"1980-01-01",
    "date:inception_upper":"1980-01-31",
    "iso:country":"GB",
    "wof:name":"EX5 5BN",
    "wof:placetype":"postalcode"
},
  "geometry": {"coordinates":[-3.591218,50.770547],"type":"Point"}
}