{
  "type": "Feature",
  "properties": {
    "iso:country":"GB",
    "wof:name":"EX5 5BN",
    "wof:placetype":"postalcode"
},
  "geometry": {"coordinates":[-3.59121796798209,50.77054650616659],"type":"Point"}
}