{
  "type": "Feature",
  "properties": {
    "iso:country": "GB",
    "wof:name": "EX5 5BN",
    "wof:placetype": "postalcode"
  },
  "geometry": {"coordinates":[-3.591218,50.770547],"type":"Point"}
}
