{
  "type": "Feature",
  "properties": {
    "date:inception_lower": "1980-01-01",
    "date:inception_upper": "1980-01-01",
    "iso:country": "GB",
    "wof:name": "GL1 1DQ",
    "wof:placetype": "postalcode"
  },
  "geometry": {"coordinates":[-2.239601,51.864718],"type":"Point"}
}
