{
  "type": "Feature",
  "properties": {
    "date:inception_lower": "1980-01-01",
    "date:inception_upper": "1980-01-01",
    "iso:country": "GB",
    "wof:name": "SG7 5DZ",
    "wof:placetype": "postalcode"
  },
  "geometry": {"coordinates":[-0.160653,52.011893],"type":"Point"}
}
