{
  "type": "Feature",
  "properties": {
    "iso:country":"GB",
    "wof:name":"BL2 1NL",
    "wof:placetype":"postalcode"
},
  "geometry": {"coordinates":[-2.40816320704487,53.57021241801393],"type":"Point"}
}