{
  "type": "Feature",
  "properties": {
    "iso:country":"GB",
    "wof:name":"ML3 9AQ",
    "wof:placetype":"postalcode"
},
  "geometry": {"coordinates":[-4.05777715366541,55.77891643863161],"type":"Point"}
}