{
  "type": "Feature",
  "properties": {
    "date:inception_lower": "1980-01-01",
    "date:inception_upper": "1980-01-01",
    "iso:country": "GB",
    "wof:name": "PE22 0DT",
    "wof:placetype": "postalcode"
  },
  "geometry": {"coordinates":[0.078011,52.994439],"type":"Point"}
}
