{
  "type": "Feature",
  "properties": {
    "iso:country": "GB",
    "wof:name": "PE22 0DT",
    "wof:placetype": "postalcode"
  },
  "geometry": {"coordinates":[0.078011,52.994439],"type":"Point"}
}
