{
  "type": "Feature",
  "properties": {
    "iso:country": "GB",
    "wof:name": "DY10 1PU",
    "wof:placetype": "postalcode"
  },
  "geometry": {"coordinates":[-2.242872,52.38867],"type":"Point"}
}
