{
  "type": "Feature",
  "properties": {
    "iso:country":"GB",
    "wof:name":"DY10 1PU",
    "wof:placetype":"postalcode"
},
  "geometry": {"coordinates":[-2.24287205820289,52.38867020924819],"type":"Point"}
}