{
  "type": "Feature",
  "properties": {
    "iso:country": "GB",
    "wof:name": "YO12 4BE",
    "wof:placetype": "postalcode"
  },
  "geometry": {"coordinates":[-0.417064,54.263905],"type":"Point"}
}
