{
  "type": "Feature",
  "properties": {
    "iso:country":"GB",
    "wof:name":"YO12 4BE",
    "wof:placetype":"postalcode"
},
  "geometry": {"coordinates":[-0.41706411397491,54.26390478481957],"type":"Point"}
}