{
  "type": "Feature",
  "properties": {
    "iso:country":"GB",
    "wof:name":"B91 2NR",
    "wof:placetype":"postalcode"
},
  "geometry": {"coordinates":[-1.769398310895,52.41944195645397],"type":"Point"}
}