{
  "type": "Feature",
  "properties": {
    "date:inception_lower": "1990-02-01",
    "date:inception_upper": "1990-02-01",
    "iso:country": "GB",
    "wof:name": "IP13 8DG",
    "wof:placetype": "postalcode"
  },
  "geometry": {"coordinates":[1.35907,52.300578],"type":"Point"}
}
