{
  "type": "Feature",
  "properties": {
    "iso:country":"GB",
    "wof:name":"IP13 8DG",
    "wof:placetype":"postalcode"
},
  "geometry": {"coordinates":[1.35899302910563,52.30053293752029],"type":"Point"}
}