{
  "type": "Feature",
  "properties": {
    "date:inception_lower": "1980-01-01",
    "date:inception_upper": "1980-01-01",
    "iso:country": "GB",
    "wof:name": "HR4 8NJ",
    "wof:placetype": "postalcode"
  },
  "geometry": {"coordinates":[-2.758996,52.111642],"type":"Point"}
}
