{
  "type": "Feature",
  "properties": {
    "iso:country":"GB",
    "wof:name":"HR4 8NJ",
    "wof:placetype":"postalcode"
},
  "geometry": {"coordinates":[-2.75899510786603,52.11163307421028],"type":"Point"}
}