{
  "type": "Feature",
  "properties": {
    "iso:country":"GB",
    "wof:name":"LN4 4BW",
    "wof:placetype":"postalcode"
},
  "geometry": {"coordinates":[-0.27155197782439,53.0796612608765],"type":"Point"}
}