{
  "type": "Feature",
  "properties": {
    "iso:country": "GB",
    "wof:name": "DH3 1PS",
    "wof:placetype": "postalcode"
  },
  "geometry": {"coordinates":[-1.579452,54.906656],"type":"Point"}
}
