{
  "type": "Feature",
  "properties": {
    "iso:country": "GB",
    "wof:name": "KT11 2BP",
    "wof:placetype": "postalcode"
  },
  "geometry": {"coordinates":[-0.395093,51.34217],"type":"Point"}
}
