{
  "type": "Feature",
  "properties": {
    "date:inception_lower": "1980-01-01",
    "date:inception_upper": "1980-01-01",
    "iso:country": "GB",
    "wof:name": "KT11 2BP",
    "wof:placetype": "postalcode"
  },
  "geometry": {"coordinates":[-0.395093,51.34217],"type":"Point"}
}
