{
  "type": "Feature",
  "properties": {
    "date:inception_lower": "2015-06-01",
    "date:inception_upper": "2015-06-01",
    "iso:country": "GB",
    "wof:name": "NP20 2QL",
    "wof:placetype": "postalcode"
  },
  "geometry": {"coordinates":[-3.003033,51.573354],"type":"Point"}
}
