{
  "type": "Feature",
  "properties": {
    "iso:country":"GB",
    "wof:name":"TQ13 7QY",
    "wof:placetype":"postalcode"
},
  "geometry": {"coordinates":[-3.76994345462243,50.51429594514238],"type":"Point"}
}