{
  "type": "Feature",
  "properties": {
    "iso:country": "GB",
    "wof:name": "TQ13 7QY",
    "wof:placetype": "postalcode"
  },
  "geometry": {"coordinates":[-3.769943,50.514296],"type":"Point"}
}
