{
  "type": "Feature",
  "properties": {
    "iso:country":"GB",
    "wof:name":"NN14 1TW",
    "wof:placetype":"postalcode"
},
  "geometry": {"coordinates":[-0.81369263691543,52.37406025080374],"type":"Point"}
}