{
  "type": "Feature",
  "properties": {
    "date:inception_lower": "2007-09-01",
    "date:inception_upper": "2007-09-01",
    "iso:country": "GB",
    "wof:name": "NN14 1TW",
    "wof:placetype": "postalcode"
  },
  "geometry": {"coordinates":[-0.813693,52.37406],"type":"Point"}
}
