{
  "type": "Feature",
  "properties": {
    "date:inception_lower": "2024-08-01",
    "date:inception_upper": "2024-08-01",
    "iso:country": "GB",
    "wof:name": "WA10 4FX",
    "wof:placetype": "postalcode"
  },
  "geometry": {"coordinates":[-2.766232,53.455528],"type":"Point"}
}
