{
  "type": "Feature",
  "properties": {
    "iso:country": "GB",
    "wof:name": "TD5 8LY",
    "wof:placetype": "postalcode"
  },
  "geometry": {"coordinates":[-2.480954,55.572223],"type":"Point"}
}
