{
  "type": "Feature",
  "properties": {
    "iso:country":"GB",
    "wof:name":"UB1 1EE",
    "wof:placetype":"postalcode"
},
  "geometry": {"coordinates":[-0.38796364080104,51.51040010812832],"type":"Point"}
}