{
  "type": "Feature",
  "properties": {
    "iso:country":"GB",
    "wof:name":"CT10 3DQ",
    "wof:placetype":"postalcode"
},
  "geometry": {"coordinates":[1.42729944711299,51.37264022166165],"type":"Point"}
}