{
  "type": "Feature",
  "properties": {
    "date:inception_lower":"1980-01-01",
    "date:inception_upper":"1980-01-31",
    "iso:country":"GB",
    "wof:name":"CT10 3DQ",
    "wof:placetype":"postalcode"
},
  "geometry": {"coordinates":[1.427299,51.37264],"type":"Point"}
}