{
  "type": "Feature",
  "properties": {
    "iso:country":"GB",
    "wof:name":"PE6 8NN",
    "wof:placetype":"postalcode"
},
  "geometry": {"coordinates":[-0.29012676560551,52.67538702809986],"type":"Point"}
}