{
  "type": "Feature",
  "properties": {
    "iso:country": "GB",
    "wof:name": "PE6 8NN",
    "wof:placetype": "postalcode"
  },
  "geometry": {"coordinates":[-0.290127,52.675387],"type":"Point"}
}
