{
  "type": "Feature",
  "properties": {
    "date:inception_lower": "2022-02-01",
    "date:inception_upper": "2022-02-01",
    "iso:country": "GB",
    "wof:name": "MK17 7AQ",
    "wof:placetype": "postalcode"
  },
  "geometry": {"coordinates":[-0.648533,52.03626],"type":"Point"}
}
