{
  "type": "Feature",
  "properties": {
    "date:inception_lower": "1990-02-01",
    "date:inception_upper": "1990-02-01",
    "iso:country": "GB",
    "wof:name": "RM7 0AN",
    "wof:placetype": "postalcode"
  },
  "geometry": {"coordinates":[0.18457,51.569209],"type":"Point"}
}
