{
  "type": "Feature",
  "properties": {
    "iso:country":"GB",
    "wof:name":"RM7 0AN",
    "wof:placetype":"postalcode"
},
  "geometry": {"coordinates":[0.18512181368575,51.56838039173006],"type":"Point"}
}