{
  "type": "Feature",
  "properties": {
    "iso:country":"GB",
    "wof:name":"LU4 9HS",
    "wof:placetype":"postalcode"
},
  "geometry": {"coordinates":[-0.46654794625674,51.90411149005458],"type":"Point"}
}