{
  "type": "Feature",
  "properties": {
    "date:inception_lower": "2014-06-01",
    "date:inception_upper": "2014-06-01",
    "iso:country": "GB",
    "wof:name": "G63 9SL",
    "wof:placetype": "postalcode"
  },
  "geometry": {"coordinates":[-4.371349,56.044216],"type":"Point"}
}
