{
  "type": "Feature",
  "properties": {
    "iso:country":"GB",
    "wof:name":"BD15 7RN",
    "wof:placetype":"postalcode"
},
  "geometry": {"coordinates":[-1.81587312952899,53.80045120076901],"type":"Point"}
}