{
  "type": "Feature",
  "properties": {
    "iso:country":"GB",
    "wof:name":"BR3 4SE",
    "wof:placetype":"postalcode"
},
  "geometry": {"coordinates":[-0.05240956846787,51.4057680587602],"type":"Point"}
}