{
  "type": "Feature",
  "properties": {
    "iso:country": "GB",
    "wof:name": "RH17 5LP",
    "wof:placetype": "postalcode"
  },
  "geometry": {"coordinates":[-0.137629,51.005817],"type":"Point"}
}
