{
  "type": "Feature",
  "properties": {
    "date:inception_lower": "1981-06-01",
    "date:inception_upper": "1981-06-01",
    "iso:country": "GB",
    "wof:name": "CV37 9UH",
    "wof:placetype": "postalcode"
  },
  "geometry": {"coordinates":[-1.795165,52.187276],"type":"Point"}
}
