{
  "type": "Feature",
  "properties": {
    "date:inception_lower": "1980-01-01",
    "date:inception_upper": "1980-01-01",
    "iso:country": "GB",
    "wof:name": "DE11 8LD",
    "wof:placetype": "postalcode"
  },
  "geometry": {"coordinates":[-1.552836,52.775054],"type":"Point"}
}
