{
  "type": "Feature",
  "properties": {
    "date:inception_lower":"1999-06-01",
    "date:inception_upper":"1999-06-30",
    "iso:country":"GB",
    "wof:name":"L11 4UL",
    "wof:placetype":"postalcode"
},
  "geometry": {"coordinates":[-2.900571,53.448588],"type":"Point"}
}