{
  "type": "Feature",
  "properties": {
    "iso:country": "GB",
    "wof:name": "L11 4UL",
    "wof:placetype": "postalcode"
  },
  "geometry": {"coordinates":[-2.900571,53.448588],"type":"Point"}
}
