{
  "type": "Feature",
  "properties": {
    "iso:country": "GB",
    "wof:name": "HG3 1SJ",
    "wof:placetype": "postalcode"
  },
  "geometry": {"coordinates":[-1.67566,53.988088],"type":"Point"}
}
