{
  "type": "Feature",
  "properties": {
    "iso:country":"GB",
    "wof:name":"RH20 3PN",
    "wof:placetype":"postalcode"
},
  "geometry": {"coordinates":[-0.42725137131031,50.92278864415567],"type":"Point"}
}