{
  "type": "Feature",
  "properties": {
    "iso:country": "GB",
    "wof:name": "RH20 3PN",
    "wof:placetype": "postalcode"
  },
  "geometry": {"coordinates":[-0.427251,50.922789],"type":"Point"}
}
