{
  "type": "Feature",
  "properties": {
    "date:inception_lower":"1990-02-01",
    "date:inception_upper":"1990-02-28",
    "iso:country":"GB",
    "wof:name":"WN6 7EJ",
    "wof:placetype":"postalcode"
},
  "geometry": {"coordinates":[-2.651201,53.551455],"type":"Point"}
}