{
  "type": "Feature",
  "properties": {
    "iso:country":"GB",
    "wof:name":"WN6 7EJ",
    "wof:placetype":"postalcode"
},
  "geometry": {"coordinates":[-2.65120070427986,53.55145544063171],"type":"Point"}
}