{
  "type": "Feature",
  "properties": {
    "iso:country": "GB",
    "wof:name": "HR1 4HQ",
    "wof:placetype": "postalcode"
  },
  "geometry": {"coordinates":[-2.580206,52.060377],"type":"Point"}
}
