{
  "type": "Feature",
  "properties": {
    "iso:country":"GB",
    "wof:name":"HR1 4HQ",
    "wof:placetype":"postalcode"
},
  "geometry": {"coordinates":[-2.58020602196828,52.06037701457836],"type":"Point"}
}