{
  "type": "Feature",
  "properties": {
    "iso:country":"GB",
    "wof:name":"TN10 3LQ",
    "wof:placetype":"postalcode"
},
  "geometry": {"coordinates":[0.27287557269281,51.21784927743671],"type":"Point"}
}