{
  "type": "Feature",
  "properties": {
    "iso:country":"GB",
    "wof:name":"TN25 6HW",
    "wof:placetype":"postalcode"
},
  "geometry": {"coordinates":[1.01455272197069,51.10791750243454],"type":"Point"}
}