{
  "type": "Feature",
  "properties": {
    "date:inception_lower": "1985-04-01",
    "date:inception_upper": "1985-04-01",
    "iso:country": "GB",
    "wof:name": "TN25 6HW",
    "wof:placetype": "postalcode"
  },
  "geometry": {"coordinates":[1.013973,51.107746],"type":"Point"}
}
