{
  "type": "Feature",
  "properties": {
    "iso:country": "GB",
    "wof:name": "OL3 5AU",
    "wof:placetype": "postalcode"
  },
  "geometry": {"coordinates":[-2.015328,53.556006],"type":"Point"}
}
