{
  "type": "Feature",
  "properties": {
    "date:inception_lower":"1986-04-01",
    "date:inception_upper":"1986-04-30",
    "iso:country":"GB",
    "wof:name":"OL3 5AU",
    "wof:placetype":"postalcode"
},
  "geometry": {"coordinates":[-2.015328,53.556006],"type":"Point"}
}