{
  "type": "Feature",
  "properties": {
    "iso:country":"GB",
    "wof:name":"TR4 9PX",
    "wof:placetype":"postalcode"
},
  "geometry": {"coordinates":[-5.11289083663203,50.34250551983357],"type":"Point"}
}