{
  "type": "Feature",
  "properties": {
    "iso:country": "GB",
    "wof:name": "WS7 3RT",
    "wof:placetype": "postalcode"
  },
  "geometry": {"coordinates":[-1.942287,52.674127],"type":"Point"}
}
