{
  "type": "Feature",
  "properties": {
    "date:inception_lower": "1997-12-01",
    "date:inception_upper": "1997-12-01",
    "iso:country": "GB",
    "wof:name": "BS40 6PE",
    "wof:placetype": "postalcode"
  },
  "geometry": {"coordinates":[-2.67731,51.317589],"type":"Point"}
}
