{
  "type": "Feature",
  "properties": {
    "iso:country": "GB",
    "wof:name": "BS40 6PE",
    "wof:placetype": "postalcode"
  },
  "geometry": {"coordinates":[-2.67731,51.317589],"type":"Point"}
}
