{
  "type": "Feature",
  "properties": {
    "iso:country":"GB",
    "wof:name":"GL51 0XT",
    "wof:placetype":"postalcode"
},
  "geometry": {"coordinates":[-2.12047467114802,51.90281553058031],"type":"Point"}
}