{
  "type": "Feature",
  "properties": {
    "iso:country": "GB",
    "wof:name": "GL51 0XT",
    "wof:placetype": "postalcode"
  },
  "geometry": {"coordinates":[-2.120475,51.902816],"type":"Point"}
}
