{
  "type": "Feature",
  "properties": {
    "iso:country":"GB",
    "wof:name":"GL15 4LL",
    "wof:placetype":"postalcode"
},
  "geometry": {"coordinates":[-2.52134572717468,51.73479358807759],"type":"Point"}
}