{
  "type": "Feature",
  "properties": {
    "iso:country":"GB",
    "wof:name":"S1 4GJ",
    "wof:placetype":"postalcode"
},
  "geometry": {"coordinates":[-1.4772998821118,53.37769244560006],"type":"Point"}
}