{
  "type": "Feature",
  "properties": {
    "date:inception_lower": "1981-06-01",
    "date:inception_upper": "1981-06-01",
    "iso:country": "GB",
    "wof:name": "DN33 2HZ",
    "wof:placetype": "postalcode"
  },
  "geometry": {"coordinates":[-0.085865,53.53937],"type":"Point"}
}
