{
  "type": "Feature",
  "properties": {
    "iso:country":"GB",
    "wof:name":"DN33 2HZ",
    "wof:placetype":"postalcode"
},
  "geometry": {"coordinates":[-0.08586546358844,53.53937017068471],"type":"Point"}
}