{
  "type": "Feature",
  "properties": {
    "date:inception_lower": "1980-01-01",
    "date:inception_upper": "1980-01-01",
    "iso:country": "GB",
    "wof:name": "NW11 6UP",
    "wof:placetype": "postalcode"
  },
  "geometry": {"coordinates":[-0.181842,51.577032],"type":"Point"}
}
