{
  "type": "Feature",
  "properties": {
    "iso:country":"GB",
    "wof:name":"NW11 6UP",
    "wof:placetype":"postalcode"
},
  "geometry": {"coordinates":[-0.18184239798576,51.57703239213521],"type":"Point"}
}