{
  "type": "Feature",
  "properties": {
    "iso:country": "GB",
    "wof:name": "BS34 5PU",
    "wof:placetype": "postalcode"
  },
  "geometry": {"coordinates":[-2.578874,51.533684],"type":"Point"}
}
