{
  "type": "Feature",
  "properties": {
    "iso:country":"GB",
    "wof:name":"BS34 5PU",
    "wof:placetype":"postalcode"
},
  "geometry": {"coordinates":[-2.57887421693299,51.53368413012955],"type":"Point"}
}