{
  "type": "Feature",
  "properties": {
    "iso:country": "GB",
    "wof:name": "IP8 3JY",
    "wof:placetype": "postalcode"
  },
  "geometry": {"coordinates":[1.09257,52.029737],"type":"Point"}
}
