{
  "type": "Feature",
  "properties": {
    "date:inception_lower": "1980-01-01",
    "date:inception_upper": "1980-01-01",
    "iso:country": "GB",
    "wof:name": "IP8 3JY",
    "wof:placetype": "postalcode"
  },
  "geometry": {"coordinates":[1.092289,52.029897],"type":"Point"}
}
