{
  "type": "Feature",
  "properties": {
    "iso:country":"GB",
    "wof:name":"IP8 3JY",
    "wof:placetype":"postalcode"
},
  "geometry": {"coordinates":[1.09234298187923,52.02983620557326],"type":"Point"}
}