{
  "type": "Feature",
  "properties": {
    "iso:country":"GB",
    "wof:name":"DN37 7BE",
    "wof:placetype":"postalcode"
},
  "geometry": {"coordinates":[-0.17214495110069,53.54563761441167],"type":"Point"}
}