{
  "type": "Feature",
  "properties": {
    "iso:country": "GB",
    "wof:name": "DN37 7BE",
    "wof:placetype": "postalcode"
  },
  "geometry": {"coordinates":[-0.172145,53.545638],"type":"Point"}
}
