{
  "type": "Feature",
  "properties": {
    "iso:country":"GB",
    "wof:name":"CV8 1HA",
    "wof:placetype":"postalcode"
},
  "geometry": {"coordinates":[-1.57318479414345,52.33901025340054],"type":"Point"}
}