{
  "type": "Feature",
  "properties": {
    "iso:country":"GB",
    "wof:name":"PE1 3PE",
    "wof:placetype":"postalcode"
},
  "geometry": {"coordinates":[-0.23955576883266,52.59179608539932],"type":"Point"}
}