{
  "type": "Feature",
  "properties": {
    "iso:country":"GB",
    "wof:name":"EX6 8PB",
    "wof:placetype":"postalcode"
},
  "geometry": {"coordinates":[-3.45133409840409,50.6331828538537],"type":"Point"}
}