{
  "type": "Feature",
  "properties": {
    "iso:country":"GB",
    "wof:name":"KA25 6JD",
    "wof:placetype":"postalcode"
},
  "geometry": {"coordinates":[-4.68949895202617,55.7428909791643],"type":"Point"}
}