{
  "type": "Feature",
  "properties": {
    "date:inception_lower":"1993-08-01",
    "date:inception_upper":"1993-08-31",
    "iso:country":"GB",
    "wof:name":"LL30 3RF",
    "wof:placetype":"postalcode"
},
  "geometry": {"coordinates":[-3.771626,53.320824],"type":"Point"}
}