{
  "type": "Feature",
  "properties": {
    "iso:country":"GB",
    "wof:name":"LL30 3RF",
    "wof:placetype":"postalcode"
},
  "geometry": {"coordinates":[-3.7716255517213,53.32082437274521],"type":"Point"}
}