{
  "type": "Feature",
  "properties": {
    "iso:country":"GB",
    "wof:name":"TS10 4GY",
    "wof:placetype":"postalcode"
},
  "geometry": {"coordinates":[-1.08155599125867,54.599563570664],"type":"Point"}
}