{
  "type": "Feature",
  "properties": {
    "iso:country": "GB",
    "wof:name": "PE20 3ER",
    "wof:placetype": "postalcode"
  },
  "geometry": {"coordinates":[-0.156649,52.944015],"type":"Point"}
}
