{
  "type": "Feature",
  "properties": {
    "iso:country":"GB",
    "wof:name":"PH2 0RX",
    "wof:placetype":"postalcode"
},
  "geometry": {"coordinates":[-3.58431568393642,56.31250569479685],"type":"Point"}
}