{
  "type": "Feature",
  "properties": {
    "iso:country": "GB",
    "wof:name": "PH2 0RX",
    "wof:placetype": "postalcode"
  },
  "geometry": {"coordinates":[-3.584316,56.312506],"type":"Point"}
}
