{
  "type": "Feature",
  "properties": {
    "date:inception_lower": "1980-01-01",
    "date:inception_upper": "1980-01-01",
    "iso:country": "GB",
    "wof:name": "PH2 0RX",
    "wof:placetype": "postalcode"
  },
  "geometry": {"coordinates":[-3.584316,56.312506],"type":"Point"}
}
