{
  "type": "Feature",
  "properties": {
    "iso:country":"GB",
    "wof:name":"KT12 1AW",
    "wof:placetype":"postalcode"
},
  "geometry": {"coordinates":[-0.42443305080335,51.38675695566508],"type":"Point"}
}