{
  "type": "Feature",
  "properties": {
    "iso:country": "GB",
    "wof:name": "KT12 5HL",
    "wof:placetype": "postalcode"
  },
  "geometry": {"coordinates":[-0.405806,51.365706],"type":"Point"}
}
