{
  "type": "Feature",
  "properties": {
    "iso:country":"GB",
    "wof:name":"S11 8RS",
    "wof:placetype":"postalcode"
},
  "geometry": {"coordinates":[-1.501997689702,53.36865646896381],"type":"Point"}
}