{
  "type": "Feature",
  "properties": {
    "date:inception_lower": "1980-01-01",
    "date:inception_upper": "1980-01-01",
    "iso:country": "GB",
    "wof:name": "NE49 0JA",
    "wof:placetype": "postalcode"
  },
  "geometry": {"coordinates":[-2.472653,54.956397],"type":"Point"}
}
