{
  "type": "Feature",
  "properties": {
    "iso:country": "GB",
    "wof:name": "GL9 1AU",
    "wof:placetype": "postalcode"
  },
  "geometry": {"coordinates":[-2.32178,51.581481],"type":"Point"}
}
