{
  "type": "Feature",
  "properties": {
    "iso:country":"GB",
    "wof:name":"GL9 1AU",
    "wof:placetype":"postalcode"
},
  "geometry": {"coordinates":[-2.32230263220556,51.58139836953533],"type":"Point"}
}