{
  "type": "Feature",
  "properties": {
    "date:inception_lower": "2000-12-01",
    "date:inception_upper": "2000-12-01",
    "iso:country": "GB",
    "wof:name": "PA15 1HW",
    "wof:placetype": "postalcode"
  },
  "geometry": {"coordinates":[-4.745654,55.946341],"type":"Point"}
}
