{
  "type": "Feature",
  "properties": {
    "iso:country": "GB",
    "wof:name": "PA15 1HW",
    "wof:placetype": "postalcode"
  },
  "geometry": {"coordinates":[-4.745654,55.946341],"type":"Point"}
}
