{
  "type": "Feature",
  "properties": {
    "iso:country": "GB",
    "wof:name": "BL3 1BE",
    "wof:placetype": "postalcode"
  },
  "geometry": {"coordinates":[-2.374455,53.562853],"type":"Point"}
}
