{
  "type": "Feature",
  "properties": {
    "iso:country":"GB",
    "wof:name":"SS7 2AS",
    "wof:placetype":"postalcode"
},
  "geometry": {"coordinates":[0.60604830831419,51.54844357925055],"type":"Point"}
}