{
  "type": "Feature",
  "properties": {
    "date:inception_lower": "1980-01-01",
    "date:inception_upper": "1980-01-01",
    "iso:country": "GB",
    "wof:name": "WS13 8JT",
    "wof:placetype": "postalcode"
  },
  "geometry": {"coordinates":[-1.865995,52.669527],"type":"Point"}
}
