{
  "type": "Feature",
  "properties": {
    "iso:country": "GB",
    "wof:name": "CM23 4AG",
    "wof:placetype": "postalcode"
  },
  "geometry": {"coordinates":[0.132911,51.857823],"type":"Point"}
}
