{
  "type": "Feature",
  "properties": {
    "iso:country":"GB",
    "wof:name":"CM23 4AG",
    "wof:placetype":"postalcode"
},
  "geometry": {"coordinates":[0.13291088504412,51.85782303083795],"type":"Point"}
}