{
  "type": "Feature",
  "properties": {
    "date:inception_lower": "1980-01-01",
    "date:inception_upper": "1980-01-01",
    "iso:country": "GB",
    "wof:name": "OX16 0NL",
    "wof:placetype": "postalcode"
  },
  "geometry": {"coordinates":[-1.356807,52.05634],"type":"Point"}
}
