{
  "type": "Feature",
  "properties": {
    "iso:country": "GB",
    "wof:name": "BN21 3DE",
    "wof:placetype": "postalcode"
  },
  "geometry": {"coordinates":[0.290186,50.766543],"type":"Point"}
}
