{
  "type": "Feature",
  "properties": {
    "date:inception_lower": "1980-01-01",
    "date:inception_upper": "1980-01-01",
    "iso:country": "GB",
    "wof:name": "SW15 1HU",
    "wof:placetype": "postalcode"
  },
  "geometry": {"coordinates":[-0.227906,51.470916],"type":"Point"}
}
