{
  "type": "Feature",
  "properties": {
    "iso:country":"GB",
    "wof:name":"SW15 1HU",
    "wof:placetype":"postalcode"
},
  "geometry": {"coordinates":[-0.22790646012694,51.4709163794067],"type":"Point"}
}