{
  "type": "Feature",
  "properties": {
    "iso:country":"GB",
    "wof:name":"NE16 5BD",
    "wof:placetype":"postalcode"
},
  "geometry": {"coordinates":[-1.69962090620052,54.92334046752135],"type":"Point"}
}