{
  "type": "Feature",
  "properties": {
    "iso:country": "GB",
    "wof:name": "NE16 5BD",
    "wof:placetype": "postalcode"
  },
  "geometry": {"coordinates":[-1.699664,54.92333],"type":"Point"}
}
