{
  "type": "Feature",
  "properties": {
    "date:inception_lower":"1980-01-01",
    "date:inception_upper":"1980-01-31",
    "iso:country":"GB",
    "wof:name":"LA14 3TA",
    "wof:placetype":"postalcode"
},
  "geometry": {"coordinates":[-3.254448,54.120765],"type":"Point"}
}