{
  "type": "Feature",
  "properties": {
    "iso:country": "GB",
    "wof:name": "LS19 7TD",
    "wof:placetype": "postalcode"
  },
  "geometry": {"coordinates":[-1.673841,53.866732],"type":"Point"}
}
