{
  "type": "Feature",
  "properties": {
    "iso:country":"GB",
    "wof:name":"LE9 6ST",
    "wof:placetype":"postalcode"
},
  "geometry": {"coordinates":[-1.22715125278507,52.53236043778325],"type":"Point"}
}