{
  "type": "Feature",
  "properties": {
    "date:inception_lower": "1985-04-01",
    "date:inception_upper": "1985-04-01",
    "iso:country": "GB",
    "wof:name": "LE9 6ST",
    "wof:placetype": "postalcode"
  },
  "geometry": {"coordinates":[-1.227151,52.53236],"type":"Point"}
}
