{
  "type": "Feature",
  "properties": {
    "iso:country": "GB",
    "wof:name": "PL5 3JA",
    "wof:placetype": "postalcode"
  },
  "geometry": {"coordinates":[-4.14773,50.410349],"type":"Point"}
}
