{
  "type": "Feature",
  "properties": {
    "date:inception_lower": "1989-04-01",
    "date:inception_upper": "1989-04-01",
    "iso:country": "GB",
    "wof:name": "G21 4NB",
    "wof:placetype": "postalcode"
  },
  "geometry": {"coordinates":[-4.222308,55.877837],"type":"Point"}
}
