{
  "type": "Feature",
  "properties": {
    "iso:country": "GB",
    "wof:name": "PO16 8PY",
    "wof:placetype": "postalcode"
  },
  "geometry": {"coordinates":[-1.148286,50.851246],"type":"Point"}
}
