{
  "type": "Feature",
  "properties": {
    "iso:country":"GB",
    "wof:name":"TA7 9NQ",
    "wof:placetype":"postalcode"
},
  "geometry": {"coordinates":[-2.83502076542856,51.14107233253905],"type":"Point"}
}