{
  "type": "Feature",
  "properties": {
    "iso:country":"GB",
    "wof:name":"WN6 9EN",
    "wof:placetype":"postalcode"
},
  "geometry": {"coordinates":[-2.7127795842911,53.59164232103544],"type":"Point"}
}