{
  "type": "Feature",
  "properties": {
    "date:inception_lower": "1980-01-01",
    "date:inception_upper": "1980-01-01",
    "iso:country": "GB",
    "wof:name": "WN6 9EN",
    "wof:placetype": "postalcode"
  },
  "geometry": {"coordinates":[-2.71278,53.591642],"type":"Point"}
}
