{
  "type": "Feature",
  "properties": {
    "date:inception_lower": "2017-05-01",
    "date:inception_upper": "2017-05-01",
    "iso:country": "GB",
    "wof:name": "BS22 6DX",
    "wof:placetype": "postalcode"
  },
  "geometry": {"coordinates":[-2.911243,51.357714],"type":"Point"}
}
