{
  "type": "Feature",
  "properties": {
    "date:inception_lower": "2023-10-01",
    "date:inception_upper": "2023-10-01",
    "iso:country": "GB",
    "wof:name": "GL3 1PR",
    "wof:placetype": "postalcode"
  },
  "geometry": {"coordinates":[-2.203674,51.89165],"type":"Point"}
}
