{
  "type": "Feature",
  "properties": {
    "iso:country":"GB",
    "wof:name":"G64 1DR",
    "wof:placetype":"postalcode"
},
  "geometry": {"coordinates":[-4.20864933718995,55.90958889406085],"type":"Point"}
}