{
  "type": "Feature",
  "properties": {
    "iso:country": "GB",
    "wof:name": "G64 1DR",
    "wof:placetype": "postalcode"
  },
  "geometry": {"coordinates":[-4.208649,55.909589],"type":"Point"}
}
