{
  "type": "Feature",
  "properties": {
    "iso:country": "GB",
    "wof:name": "NG23 7LX",
    "wof:placetype": "postalcode"
  },
  "geometry": {"coordinates":[-0.76016,53.148133],"type":"Point"}
}
