{
  "type": "Feature",
  "properties": {
    "iso:country":"GB",
    "wof:name":"EN6 4RP",
    "wof:placetype":"postalcode"
},
  "geometry": {"coordinates":[-0.12289126755659,51.71480215404944],"type":"Point"}
}