{
  "type": "Feature",
  "properties": {
    "iso:country":"GB",
    "wof:name":"GL18 1AN",
    "wof:placetype":"postalcode"
},
  "geometry": {"coordinates":[-2.4065317941188,51.93177242159327],"type":"Point"}
}