{
  "type": "Feature",
  "properties": {
    "date:inception_lower": "1995-07-01",
    "date:inception_upper": "1995-07-01",
    "iso:country": "GB",
    "wof:name": "HS2 0AZ",
    "wof:placetype": "postalcode"
  },
  "geometry": {"coordinates":[-6.328842,58.198334],"type":"Point"}
}
