{
  "type": "Feature",
  "properties": {
    "iso:country":"GB",
    "wof:name":"HS2 0AZ",
    "wof:placetype":"postalcode"
},
  "geometry": {"coordinates":[-6.32961216454495,58.19843690278713],"type":"Point"}
}