{
  "type": "Feature",
  "properties": {
    "iso:country":"GB",
    "wof:name":"BS2 0DS",
    "wof:placetype":"postalcode"
},
  "geometry": {"coordinates":[-2.58071982597959,51.45778612233384],"type":"Point"}
}