{
  "type": "Feature",
  "properties": {
    "iso:country": "GB",
    "wof:name": "SG2 7QZ",
    "wof:placetype": "postalcode"
  },
  "geometry": {"coordinates":[-0.104661,51.895072],"type":"Point"}
}
