{
  "type": "Feature",
  "properties": {
    "iso:country": "GB",
    "wof:name": "M29 7UA",
    "wof:placetype": "postalcode"
  },
  "geometry": {"coordinates":[-2.45421,53.499054],"type":"Point"}
}
