{
  "type": "Feature",
  "properties": {
    "iso:country": "GB",
    "wof:name": "M29 7UA",
    "wof:placetype": "postalcode"
  },
  "geometry": {"coordinates":[-2.454119,53.499046],"type":"Point"}
}
