{
  "type": "Feature",
  "properties": {
    "date:inception_lower":"1980-01-01",
    "date:inception_upper":"1980-01-31",
    "iso:country":"GB",
    "wof:name":"SR6 9DN",
    "wof:placetype":"postalcode"
},
  "geometry": {"coordinates":[-1.371154,54.928304],"type":"Point"}
}