{
  "type": "Feature",
  "properties": {
    "date:inception_lower":"1980-01-01",
    "date:inception_upper":"1980-01-31",
    "iso:country":"GB",
    "wof:name":"CF37 4AW",
    "wof:placetype":"postalcode"
},
  "geometry": {"coordinates":[-3.32499,51.601937],"type":"Point"}
}