{
  "type": "Feature",
  "properties": {
    "date:inception_lower": "1980-01-01",
    "date:inception_upper": "1980-01-01",
    "iso:country": "GB",
    "wof:name": "LS7 3RT",
    "wof:placetype": "postalcode"
  },
  "geometry": {"coordinates":[-1.541779,53.832479],"type":"Point"}
}
