{
  "type": "Feature",
  "properties": {
    "iso:country":"GB",
    "wof:name":"LS7 3RT",
    "wof:placetype":"postalcode"
},
  "geometry": {"coordinates":[-1.54177924878974,53.8324791241674],"type":"Point"}
}