{
  "type": "Feature",
  "properties": {
    "iso:country": "GB",
    "wof:name": "TW3 2NH",
    "wof:placetype": "postalcode"
  },
  "geometry": {"coordinates":[-0.361836,51.463809],"type":"Point"}
}
