{
  "type": "Feature",
  "properties": {
    "iso:country":"GB",
    "wof:name":"TW3 2NH",
    "wof:placetype":"postalcode"
},
  "geometry": {"coordinates":[-0.361835914687,51.46380867893117],"type":"Point"}
}