{
  "type": "Feature",
  "properties": {
    "iso:country":"GB",
    "wof:name":"NE40 3EJ",
    "wof:placetype":"postalcode"
},
  "geometry": {"coordinates":[-1.74840785947944,54.96874189940881],"type":"Point"}
}