{
  "type": "Feature",
  "properties": {
    "date:inception_lower": "1980-01-01",
    "date:inception_upper": "1980-01-01",
    "iso:country": "GB",
    "wof:name": "IP31 2LE",
    "wof:placetype": "postalcode"
  },
  "geometry": {"coordinates":[0.823125,52.272076],"type":"Point"}
}
