{
  "type": "Feature",
  "properties": {
    "iso:country":"GB",
    "wof:name":"NE10 8UJ",
    "wof:placetype":"postalcode"
},
  "geometry": {"coordinates":[-1.52186156343182,54.94561492808418],"type":"Point"}
}