{
  "type": "Feature",
  "properties": {
    "iso:country": "GB",
    "wof:name": "NE10 8UJ",
    "wof:placetype": "postalcode"
  },
  "geometry": {"coordinates":[-1.521862,54.945615],"type":"Point"}
}
