{
  "type": "Feature",
  "properties": {
    "iso:country":"GB",
    "wof:name":"B24 8QP",
    "wof:placetype":"postalcode"
},
  "geometry": {"coordinates":[-1.84582264784091,52.51422169176634],"type":"Point"}
}