{
  "type": "Feature",
  "properties": {
    "iso:country": "GB",
    "wof:name": "SA15 1TN",
    "wof:placetype": "postalcode"
  },
  "geometry": {"coordinates":[-4.158947,51.679358],"type":"Point"}
}
