{
  "type": "Feature",
  "properties": {
    "iso:country":"GB",
    "wof:name":"EX6 8QA",
    "wof:placetype":"postalcode"
},
  "geometry": {"coordinates":[-3.44871088905414,50.62558913037844],"type":"Point"}
}