{
  "type": "Feature",
  "properties": {
    "date:inception_lower": "2007-08-01",
    "date:inception_upper": "2007-08-01",
    "iso:country": "GB",
    "wof:name": "LL57 2PD",
    "wof:placetype": "postalcode"
  },
  "geometry": {"coordinates":[-4.169641,53.207663],"type":"Point"}
}
