{
  "type": "Feature",
  "properties": {
    "iso:country":"GB",
    "wof:name":"LL57 2PD",
    "wof:placetype":"postalcode"
},
  "geometry": {"coordinates":[-4.16964064176876,53.20766337781046],"type":"Point"}
}