{
  "type": "Feature",
  "properties": {
    "iso:country":"GB",
    "wof:name":"NG5 2BY",
    "wof:placetype":"postalcode"
},
  "geometry": {"coordinates":[-1.15400919966971,52.97033815763577],"type":"Point"}
}