{
  "type": "Feature",
  "properties": {
    "iso:country":"GB",
    "wof:name":"WD3 3SU",
    "wof:placetype":"postalcode"
},
  "geometry": {"coordinates":[-0.44907324836688,51.64921657102861],"type":"Point"}
}