{
  "type": "Feature",
  "properties": {
    "iso:country":"GB",
    "wof:name":"ML3 8XB",
    "wof:placetype":"postalcode"
},
  "geometry": {"coordinates":[-4.08852074777038,55.76488998131368],"type":"Point"}
}