{
  "type": "Feature",
  "properties": {
    "iso:country":"GB",
    "wof:name":"NP20 1GD",
    "wof:placetype":"postalcode"
},
  "geometry": {"coordinates":[-2.99755680214878,51.58884869315794],"type":"Point"}
}