{
  "type": "Feature",
  "properties": {
    "iso:country":"GB",
    "wof:name":"DG12 6ES",
    "wof:placetype":"postalcode"
},
  "geometry": {"coordinates":[-3.25835188372136,54.98054342867331],"type":"Point"}
}