{
  "type": "Feature",
  "properties": {
    "iso:country":"GB",
    "wof:name":"ME8 6HJ",
    "wof:placetype":"postalcode"
},
  "geometry": {"coordinates":[0.57846100382112,51.37570261080764],"type":"Point"}
}