{
  "type": "Feature",
  "properties": {
    "date:inception_lower": "1980-01-01",
    "date:inception_upper": "1980-01-01",
    "iso:country": "GB",
    "wof:name": "ME8 6HJ",
    "wof:placetype": "postalcode"
  },
  "geometry": {"coordinates":[0.578461,51.375703],"type":"Point"}
}
