{
  "type": "Feature",
  "properties": {
    "date:inception_lower": "2021-01-01",
    "date:inception_upper": "2021-01-01",
    "iso:country": "GB",
    "wof:name": "KA7 4GG",
    "wof:placetype": "postalcode"
  },
  "geometry": {"coordinates":[-4.665816,55.430536],"type":"Point"}
}
