{
  "type": "Feature",
  "properties": {
    "date:inception_lower":"1980-01-01",
    "date:inception_upper":"1980-01-31",
    "iso:country":"GB",
    "wof:name":"PO13 0SQ",
    "wof:placetype":"postalcode"
},
  "geometry": {"coordinates":[-1.18173,50.827448],"type":"Point"}
}