{
  "type": "Feature",
  "properties": {
    "iso:country": "GB",
    "wof:name": "LE3 6NG",
    "wof:placetype": "postalcode"
  },
  "geometry": {"coordinates":[-1.193953,52.636145],"type":"Point"}
}
