{
  "type": "Feature",
  "properties": {
    "iso:country": "GB",
    "wof:name": "TR12 7FD",
    "wof:placetype": "postalcode"
  },
  "geometry": {"coordinates":[-5.244583,50.030901],"type":"Point"}
}
