{
  "type": "Feature",
  "properties": {
    "iso:country":"GB",
    "wof:name":"HD9 5QN",
    "wof:placetype":"postalcode"
},
  "geometry": {"coordinates":[-1.84519839528739,53.5957972284498],"type":"Point"}
}