{
  "type": "Feature",
  "properties": {
    "iso:country":"GB",
    "wof:name":"NE23 2XW",
    "wof:placetype":"postalcode"
},
  "geometry": {"coordinates":[-1.5734991244372,55.09494203585455],"type":"Point"}
}