{
  "type": "Feature",
  "properties": {
    "date:inception_lower":"1996-06-01",
    "date:inception_upper":"1996-06-30",
    "iso:country":"GB",
    "wof:name":"AB54 7QD",
    "wof:placetype":"postalcode"
},
  "geometry": {"coordinates":[-2.63508,57.592716],"type":"Point"}
}