{
  "type": "Feature",
  "properties": {
    "iso:country":"GB",
    "wof:name":"TN33 0LX",
    "wof:placetype":"postalcode"
},
  "geometry": {"coordinates":[0.49008913863894,50.9202976041027],"type":"Point"}
}