{
  "type": "Feature",
  "properties": {
    "iso:country": "GB",
    "wof:name": "KY12 8TN",
    "wof:placetype": "postalcode"
  },
  "geometry": {"coordinates":[-3.586579,56.05952],"type":"Point"}
}
