{
  "type": "Feature",
  "properties": {
    "iso:country":"GB",
    "wof:name":"KY12 8TN",
    "wof:placetype":"postalcode"
},
  "geometry": {"coordinates":[-3.58657871202642,56.059519861351],"type":"Point"}
}