{
  "type": "Feature",
  "properties": {
    "iso:country":"GB",
    "wof:name":"WV14 7DS",
    "wof:placetype":"postalcode"
},
  "geometry": {"coordinates":[-2.06393445251588,52.56227430487922],"type":"Point"}
}