{
  "type": "Feature",
  "properties": {
    "iso:country":"GB",
    "wof:name":"HU12 8PR",
    "wof:placetype":"postalcode"
},
  "geometry": {"coordinates":[-0.19849214862917,53.73603970602024],"type":"Point"}
}