{
  "type": "Feature",
  "properties": {
    "iso:country":"GB",
    "wof:name":"SN4 0AQ",
    "wof:placetype":"postalcode"
},
  "geometry": {"coordinates":[-1.69355952412085,51.54750875473339],"type":"Point"}
}