{
  "type": "Feature",
  "properties": {
    "date:inception_lower":"1980-01-01",
    "date:inception_upper":"1980-01-31",
    "iso:country":"GB",
    "wof:name":"ST18 0XZ",
    "wof:placetype":"postalcode"
},
  "geometry": {"coordinates":[-2.073672,52.808162],"type":"Point"}
}