{
  "type": "Feature",
  "properties": {
    "date:inception_lower": "1980-01-01",
    "date:inception_upper": "1980-01-01",
    "iso:country": "GB",
    "wof:name": "NP44 1AQ",
    "wof:placetype": "postalcode"
  },
  "geometry": {"coordinates":[-3.028274,51.66039],"type":"Point"}
}
