{
  "type": "Feature",
  "properties": {
    "iso:country": "GB",
    "wof:name": "NP18 3DP",
    "wof:placetype": "postalcode"
  },
  "geometry": {"coordinates":[-2.974366,51.61609],"type":"Point"}
}
