{
  "type": "Feature",
  "properties": {
    "iso:country":"GB",
    "wof:name":"YO15 1HJ",
    "wof:placetype":"postalcode"
},
  "geometry": {"coordinates":[-0.17888120471704,54.13113062679497],"type":"Point"}
}