{
  "type": "Feature",
  "properties": {
    "date:inception_lower": "2003-05-01",
    "date:inception_upper": "2003-05-01",
    "iso:country": "GB",
    "wof:name": "ME15 6TB",
    "wof:placetype": "postalcode"
  },
  "geometry": {"coordinates":[0.508979,51.263379],"type":"Point"}
}
