{
  "type": "Feature",
  "properties": {
    "iso:country":"GB",
    "wof:name":"CA2 7DN",
    "wof:placetype":"postalcode"
},
  "geometry": {"coordinates":[-2.95790530883266,54.89207553302331],"type":"Point"}
}