{
  "type": "Feature",
  "properties": {
    "iso:country": "GB",
    "wof:name": "LE67 4UB",
    "wof:placetype": "postalcode"
  },
  "geometry": {"coordinates":[-1.324888,52.725557],"type":"Point"}
}
