{
  "type": "Feature",
  "properties": {
    "date:inception_lower": "2010-05-01",
    "date:inception_upper": "2010-05-01",
    "iso:country": "GB",
    "wof:name": "DL8 2PQ",
    "wof:placetype": "postalcode"
  },
  "geometry": {"coordinates":[-1.552562,54.215719],"type":"Point"}
}
