{
  "type": "Feature",
  "properties": {
    "iso:country":"GB",
    "wof:name":"DL8 2PQ",
    "wof:placetype":"postalcode"
},
  "geometry": {"coordinates":[-1.55256234727538,54.21571932941909],"type":"Point"}
}