{
  "type": "Feature",
  "properties": {
    "iso:country": "GB",
    "wof:name": "DL8 2PQ",
    "wof:placetype": "postalcode"
  },
  "geometry": {"coordinates":[-1.552562,54.215719],"type":"Point"}
}
