{
  "type": "Feature",
  "properties": {
    "iso:country": "GB",
    "wof:name": "SY14 7JA",
    "wof:placetype": "postalcode"
  },
  "geometry": {"coordinates":[-2.825882,53.069548],"type":"Point"}
}
