{
  "type": "Feature",
  "properties": {
    "iso:country":"GB",
    "wof:name":"NG25 0QH",
    "wof:placetype":"postalcode"
},
  "geometry": {"coordinates":[-0.94585386546332,53.07117384987649],"type":"Point"}
}