{
  "type": "Feature",
  "properties": {
    "iso:country":"GB",
    "wof:name":"WS15 1GT",
    "wof:placetype":"postalcode"
},
  "geometry": {"coordinates":[-1.93377933494264,52.7498881745002],"type":"Point"}
}