{
  "type": "Feature",
  "properties": {
    "date:inception_lower":"2009-09-01",
    "date:inception_upper":"2009-09-30",
    "iso:country":"GB",
    "wof:name":"WS15 1GT",
    "wof:placetype":"postalcode"
},
  "geometry": {"coordinates":[-1.933779,52.749888],"type":"Point"}
}