{
  "type": "Feature",
  "properties": {
    "date:inception_lower": "1991-01-01",
    "date:inception_upper": "1991-01-01",
    "iso:country": "GB",
    "wof:name": "MK43 8EW",
    "wof:placetype": "postalcode"
  },
  "geometry": {"coordinates":[-0.629326,52.161022],"type":"Point"}
}
