{
  "type": "Feature",
  "properties": {
    "iso:country": "GB",
    "wof:name": "SY6 6NZ",
    "wof:placetype": "postalcode"
  },
  "geometry": {"coordinates":[-2.78719,52.599661],"type":"Point"}
}
