{
  "type": "Feature",
  "properties": {
    "iso:country":"GB",
    "wof:name":"SY6 6NZ",
    "wof:placetype":"postalcode"
},
  "geometry": {"coordinates":[-2.78718970095333,52.59966083860414],"type":"Point"}
}