{
  "type": "Feature",
  "properties": {
    "iso:country":"GB",
    "wof:name":"DG12 5HG",
    "wof:placetype":"postalcode"
},
  "geometry": {"coordinates":[-3.25411292986661,54.99443604436527],"type":"Point"}
}