{
  "type": "Feature",
  "properties": {
    "iso:country":"GB",
    "wof:name":"SW1V 4QU",
    "wof:placetype":"postalcode"
},
  "geometry": {"coordinates":[-0.14399636175533,51.48995030340009],"type":"Point"}
}