{
  "type": "Feature",
  "properties": {
    "date:inception_lower": "1980-01-01",
    "date:inception_upper": "1980-01-01",
    "iso:country": "GB",
    "wof:name": "ME13 8DJ",
    "wof:placetype": "postalcode"
  },
  "geometry": {"coordinates":[0.903465,51.314085],"type":"Point"}
}
