{
  "type": "Feature",
  "properties": {
    "iso:country":"GB",
    "wof:name":"PL20 6PY",
    "wof:placetype":"postalcode"
},
  "geometry": {"coordinates":[-4.06615918449222,50.4748671171786],"type":"Point"}
}