{
  "type": "Feature",
  "properties": {
    "iso:country": "GB",
    "wof:name": "PL20 6PY",
    "wof:placetype": "postalcode"
  },
  "geometry": {"coordinates":[-4.066185,50.474855],"type":"Point"}
}
