{
  "type": "Feature",
  "properties": {
    "date:inception_lower": "1993-09-01",
    "date:inception_upper": "1993-09-01",
    "iso:country": "GB",
    "wof:name": "EH4 6EL",
    "wof:placetype": "postalcode"
  },
  "geometry": {"coordinates":[-3.300441,55.961313],"type":"Point"}
}
