{
  "type": "Feature",
  "properties": {
    "iso:country":"GB",
    "wof:name":"EH4 6EL",
    "wof:placetype":"postalcode"
},
  "geometry": {"coordinates":[-3.30044076784678,55.96131289811916],"type":"Point"}
}