{
  "type": "Feature",
  "properties": {
    "iso:country":"GB",
    "wof:name":"HX2 6LB",
    "wof:placetype":"postalcode"
},
  "geometry": {"coordinates":[-1.95271363086771,53.71984359375465],"type":"Point"}
}