{
  "type": "Feature",
  "properties": {
    "iso:country":"GB",
    "wof:name":"CA10 1QT",
    "wof:placetype":"postalcode"
},
  "geometry": {"coordinates":[-2.61372579516174,54.66145795141696],"type":"Point"}
}