{
  "type": "Feature",
  "properties": {
    "iso:country": "GB",
    "wof:name": "CA10 1QT",
    "wof:placetype": "postalcode"
  },
  "geometry": {"coordinates":[-2.613726,54.661458],"type":"Point"}
}
