{
  "type": "Feature",
  "properties": {
    "iso:country": "GB",
    "wof:name": "OL10 3BJ",
    "wof:placetype": "postalcode"
  },
  "geometry": {"coordinates":[-2.228872,53.588442],"type":"Point"}
}
