{
  "type": "Feature",
  "properties": {
    "date:inception_lower": "1980-01-01",
    "date:inception_upper": "1980-01-01",
    "iso:country": "GB",
    "wof:name": "KA1 3NH",
    "wof:placetype": "postalcode"
  },
  "geometry": {"coordinates":[-4.484371,55.596462],"type":"Point"}
}
