{
  "type": "Feature",
  "properties": {
    "iso:country":"GB",
    "wof:name":"KA1 3NH",
    "wof:placetype":"postalcode"
},
  "geometry": {"coordinates":[-4.48437086278585,55.59646179600435],"type":"Point"}
}