{
  "type": "Feature",
  "properties": {
    "iso:country":"GB",
    "wof:name":"BN1 8NS",
    "wof:placetype":"postalcode"
},
  "geometry": {"coordinates":[-0.13694996904361,50.86357669060631],"type":"Point"}
}