{
  "type": "Feature",
  "properties": {
    "date:inception_lower": "1980-01-01",
    "date:inception_upper": "1980-01-01",
    "iso:country": "GB",
    "wof:name": "BN1 8NS",
    "wof:placetype": "postalcode"
  },
  "geometry": {"coordinates":[-0.13695,50.863577],"type":"Point"}
}
