{
  "type": "Feature",
  "properties": {
    "iso:country":"GB",
    "wof:name":"NR6 7QH",
    "wof:placetype":"postalcode"
},
  "geometry": {"coordinates":[1.31095260484421,52.65837024937312],"type":"Point"}
}