{
  "type": "Feature",
  "properties": {
    "iso:country":"GB",
    "wof:name":"SA5 8EX",
    "wof:placetype":"postalcode"
},
  "geometry": {"coordinates":[-3.96433510383209,51.63730041463317],"type":"Point"}
}