{
  "type": "Feature",
  "properties": {
    "iso:country":"GB",
    "wof:name":"LE12 7RD",
    "wof:placetype":"postalcode"
},
  "geometry": {"coordinates":[-1.10543918803209,52.7310188169826],"type":"Point"}
}