{
  "type": "Feature",
  "properties": {
    "date:inception_lower": "2020-09-01",
    "date:inception_upper": "2020-09-01",
    "iso:country": "GB",
    "wof:name": "PA14 5BW",
    "wof:placetype": "postalcode"
  },
  "geometry": {"coordinates":[-4.704531,55.934784],"type":"Point"}
}
