{
  "type": "Feature",
  "properties": {
    "date:inception_lower": "1990-02-01",
    "date:inception_upper": "1990-02-01",
    "iso:country": "GB",
    "wof:name": "CT4 6UA",
    "wof:placetype": "postalcode"
  },
  "geometry": {"coordinates":[1.110835,51.152257],"type":"Point"}
}
