{
  "type": "Feature",
  "properties": {
    "iso:country":"GB",
    "wof:name":"CT4 6UA",
    "wof:placetype":"postalcode"
},
  "geometry": {"coordinates":[1.11083491989589,51.15225670584411],"type":"Point"}
}