{
  "type": "Feature",
  "properties": {
    "iso:country":"GB",
    "wof:name":"NE61 5XA",
    "wof:placetype":"postalcode"
},
  "geometry": {"coordinates":[-1.53859405944615,55.21002477996658],"type":"Point"}
}