{
  "type": "Feature",
  "properties": {
    "iso:country": "GB",
    "wof:name": "NE61 5XA",
    "wof:placetype": "postalcode"
  },
  "geometry": {"coordinates":[-1.538561,55.210029],"type":"Point"}
}
