{
  "type": "Feature",
  "properties": {
    "date:inception_lower": "2012-06-01",
    "date:inception_upper": "2012-06-01",
    "iso:country": "GB",
    "wof:name": "NE61 5XA",
    "wof:placetype": "postalcode"
  },
  "geometry": {"coordinates":[-1.538561,55.210029],"type":"Point"}
}
