{
  "type": "Feature",
  "properties": {
    "date:inception_lower": "2010-02-01",
    "date:inception_upper": "2010-02-01",
    "iso:country": "GB",
    "wof:name": "LE14 4PJ",
    "wof:placetype": "postalcode"
  },
  "geometry": {"coordinates":[-0.936555,52.83754],"type":"Point"}
}
