{
  "type": "Feature",
  "properties": {
    "iso:country":"GB",
    "wof:name":"LE14 4PJ",
    "wof:placetype":"postalcode"
},
  "geometry": {"coordinates":[-0.93655455684757,52.83753984242545],"type":"Point"}
}