{
  "type": "Feature",
  "properties": {
    "date:inception_lower":"1980-01-01",
    "date:inception_upper":"1980-01-31",
    "iso:country":"GB",
    "wof:name":"WA15 6UH",
    "wof:placetype":"postalcode"
},
  "geometry": {"coordinates":[-2.310324,53.400328],"type":"Point"}
}