{
  "type": "Feature",
  "properties": {
    "iso:country": "GB",
    "wof:name": "WA15 6UH",
    "wof:placetype": "postalcode"
  },
  "geometry": {"coordinates":[-2.310324,53.400328],"type":"Point"}
}
