{
  "type": "Feature",
  "properties": {
    "iso:country":"GB",
    "wof:name":"GL7 4EF",
    "wof:placetype":"postalcode"
},
  "geometry": {"coordinates":[-1.77411778247702,51.6724726917872],"type":"Point"}
}