{
  "type": "Feature",
  "properties": {
    "iso:country":"GB",
    "wof:name":"TN31 6EH",
    "wof:placetype":"postalcode"
},
  "geometry": {"coordinates":[0.59931172603094,50.93584158981807],"type":"Point"}
}