{
  "type": "Feature",
  "properties": {
    "iso:country":"GB",
    "wof:name":"SN3 4NE",
    "wof:placetype":"postalcode"
},
  "geometry": {"coordinates":[-1.74530088307905,51.58144894634608],"type":"Point"}
}