{
  "type": "Feature",
  "properties": {
    "iso:country":"GB",
    "wof:name":"BA5 1JR",
    "wof:placetype":"postalcode"
},
  "geometry": {"coordinates":[-2.68981836354411,51.20913624874279],"type":"Point"}
}