{
  "type": "Feature",
  "properties": {
    "date:inception_lower":"1980-01-01",
    "date:inception_upper":"1980-01-31",
    "iso:country":"GB",
    "wof:name":"BA5 1JR",
    "wof:placetype":"postalcode"
},
  "geometry": {"coordinates":[-2.689818,51.209136],"type":"Point"}
}