{
  "type": "Feature",
  "properties": {
    "iso:country":"GB",
    "wof:name":"TW5 9TD",
    "wof:placetype":"postalcode"
},
  "geometry": {"coordinates":[-0.4075084031346,51.48135235597233],"type":"Point"}
}