{
  "type": "Feature",
  "properties": {
    "iso:country":"GB",
    "wof:name":"BA16 0FS",
    "wof:placetype":"postalcode"
},
  "geometry": {"coordinates":[-2.74666087837546,51.12387444452266],"type":"Point"}
}