{
  "type": "Feature",
  "properties": {
    "iso:country":"GB",
    "wof:name":"RH13 9AZ",
    "wof:placetype":"postalcode"
},
  "geometry": {"coordinates":[-0.34449977895533,51.03413867303649],"type":"Point"}
}