{
  "type": "Feature",
  "properties": {
    "iso:country": "GB",
    "wof:name": "CA6 4QT",
    "wof:placetype": "postalcode"
  },
  "geometry": {"coordinates":[-2.868296,54.926485],"type":"Point"}
}
