{
  "type": "Feature",
  "properties": {
    "date:inception_lower": "2001-06-01",
    "date:inception_upper": "2001-06-01",
    "iso:country": "GB",
    "wof:name": "CA6 4QT",
    "wof:placetype": "postalcode"
  },
  "geometry": {"coordinates":[-2.868296,54.926485],"type":"Point"}
}
