{
  "type": "Feature",
  "properties": {
    "iso:country":"GB",
    "wof:name":"CA6 4QT",
    "wof:placetype":"postalcode"
},
  "geometry": {"coordinates":[-2.86829558090447,54.92648500753027],"type":"Point"}
}