{
  "type": "Feature",
  "properties": {
    "iso:country":"GB",
    "wof:name":"B65 9DE",
    "wof:placetype":"postalcode"
},
  "geometry": {"coordinates":[-2.0409027109341,52.49446486391706],"type":"Point"}
}