{
  "type": "Feature",
  "properties": {
    "iso:country":"GB",
    "wof:name":"BD10 8SQ",
    "wof:placetype":"postalcode"
},
  "geometry": {"coordinates":[-1.73241367771642,53.82672781282899],"type":"Point"}
}