{
  "type": "Feature",
  "properties": {
    "iso:country": "GB",
    "wof:name": "TF2 7EA",
    "wof:placetype": "postalcode"
  },
  "geometry": {"coordinates":[-2.451959,52.709517],"type":"Point"}
}
