{
  "type": "Feature",
  "properties": {
    "date:inception_lower":"1990-07-01",
    "date:inception_upper":"1990-07-31",
    "iso:country":"GB",
    "wof:name":"TF2 7EA",
    "wof:placetype":"postalcode"
},
  "geometry": {"coordinates":[-2.451959,52.709517],"type":"Point"}
}