{
  "type": "Feature",
  "properties": {
    "iso:country":"GB",
    "wof:name":"NE15 9QT",
    "wof:placetype":"postalcode"
},
  "geometry": {"coordinates":[-1.76529917621736,55.00525959947665],"type":"Point"}
}