{
  "type": "Feature",
  "properties": {
    "iso:country":"GB",
    "wof:name":"IV30 5UF",
    "wof:placetype":"postalcode"
},
  "geometry": {"coordinates":[-3.48937688230539,57.70126878060613],"type":"Point"}
}