{
  "type": "Feature",
  "properties": {
    "date:inception_lower": "1998-12-01",
    "date:inception_upper": "1998-12-01",
    "iso:country": "GB",
    "wof:name": "IV30 5UF",
    "wof:placetype": "postalcode"
  },
  "geometry": {"coordinates":[-3.489341,57.701254],"type":"Point"}
}
