{
  "type": "Feature",
  "properties": {
    "iso:country":"GB",
    "wof:name":"DA16 2NN",
    "wof:placetype":"postalcode"
},
  "geometry": {"coordinates":[0.10024538355744,51.45372546195782],"type":"Point"}
}