{
  "type": "Feature",
  "properties": {
    "iso:country":"GB",
    "wof:name":"TR7 1EP",
    "wof:placetype":"postalcode"
},
  "geometry": {"coordinates":[-5.08591804383008,50.41337308624298],"type":"Point"}
}