{
  "type": "Feature",
  "properties": {
    "iso:country": "GB",
    "wof:name": "TR7 1EP",
    "wof:placetype": "postalcode"
  },
  "geometry": {"coordinates":[-5.085918,50.413373],"type":"Point"}
}
