{
  "type": "Feature",
  "properties": {
    "iso:country":"GB",
    "wof:name":"PE27 4SD",
    "wof:placetype":"postalcode"
},
  "geometry": {"coordinates":[-0.03350679597594,52.33105033571789],"type":"Point"}
}