{
  "type": "Feature",
  "properties": {
    "date:inception_lower": "1980-01-01",
    "date:inception_upper": "1980-01-01",
    "iso:country": "GB",
    "wof:name": "BB6 8AW",
    "wof:placetype": "postalcode"
  },
  "geometry": {"coordinates":[-2.455265,53.817541],"type":"Point"}
}
