{
  "type": "Feature",
  "properties": {
    "date:inception_lower": "2020-11-01",
    "date:inception_upper": "2020-11-01",
    "iso:country": "GB",
    "wof:name": "DE15 9QZ",
    "wof:placetype": "postalcode"
  },
  "geometry": {"coordinates":[-1.598284,52.774667],"type":"Point"}
}
