{
  "type": "Feature",
  "properties": {
    "iso:country":"GB",
    "wof:name":"SL3 6NP",
    "wof:placetype":"postalcode"
},
  "geometry": {"coordinates":[-0.57300548696991,51.54328011252392],"type":"Point"}
}