{
  "type": "Feature",
  "properties": {
    "iso:country": "GB",
    "wof:name": "HP1 2RS",
    "wof:placetype": "postalcode"
  },
  "geometry": {"coordinates":[-0.523354,51.74529],"type":"Point"}
}
