{
  "type": "Feature",
  "properties": {
    "iso:country":"GB",
    "wof:name":"HP1 2RS",
    "wof:placetype":"postalcode"
},
  "geometry": {"coordinates":[-0.52335379302551,51.74528981304567],"type":"Point"}
}