{
  "type": "Feature",
  "properties": {
    "iso:country": "GB",
    "wof:name": "DN41 7RE",
    "wof:placetype": "postalcode"
  },
  "geometry": {"coordinates":[-0.165453,53.580999],"type":"Point"}
}
