{
  "type": "Feature",
  "properties": {
    "iso:country":"GB",
    "wof:name":"DN41 7RE",
    "wof:placetype":"postalcode"
},
  "geometry": {"coordinates":[-0.16545324060952,53.5809993602015],"type":"Point"}
}