{
  "type": "Feature",
  "properties": {
    "iso:country":"GB",
    "wof:name":"OX49 5BE",
    "wof:placetype":"postalcode"
},
  "geometry": {"coordinates":[-1.00785198398409,51.65816117629853],"type":"Point"}
}