{
  "type": "Feature",
  "properties": {
    "iso:country": "GB",
    "wof:name": "OX49 5BE",
    "wof:placetype": "postalcode"
  },
  "geometry": {"coordinates":[-1.007852,51.658161],"type":"Point"}
}
