{
  "type": "Feature",
  "properties": {
    "iso:country":"GB",
    "wof:name":"NG11 8GN",
    "wof:placetype":"postalcode"
},
  "geometry": {"coordinates":[-1.17516012462141,52.91209091008665],"type":"Point"}
}