{
  "type": "Feature",
  "properties": {
    "date:inception_lower": "1980-01-01",
    "date:inception_upper": "1980-01-01",
    "iso:country": "GB",
    "wof:name": "NG11 8GN",
    "wof:placetype": "postalcode"
  },
  "geometry": {"coordinates":[-1.17516,52.912091],"type":"Point"}
}
