{
  "type": "Feature",
  "properties": {
    "iso:country":"GB",
    "wof:name":"SO53 2AG",
    "wof:placetype":"postalcode"
},
  "geometry": {"coordinates":[-1.36749689096007,50.98535044187796],"type":"Point"}
}