{
  "type": "Feature",
  "properties": {
    "iso:country": "GB",
    "wof:name": "LE8 6HL",
    "wof:placetype": "postalcode"
  },
  "geometry": {"coordinates":[-1.177336,52.577443],"type":"Point"}
}
