{
  "type": "Feature",
  "properties": {
    "iso:country":"GB",
    "wof:name":"YO23 1JN",
    "wof:placetype":"postalcode"
},
  "geometry": {"coordinates":[-1.08405939768307,53.95072264012892],"type":"Point"}
}