{
  "type": "Feature",
  "properties": {
    "iso:country":"GB",
    "wof:name":"SY6 6LP",
    "wof:placetype":"postalcode"
},
  "geometry": {"coordinates":[-2.79359993504373,52.55976524340774],"type":"Point"}
}