{
  "type": "Feature",
  "properties": {
    "iso:country": "GB",
    "wof:name": "LS11 8FA",
    "wof:placetype": "postalcode"
  },
  "geometry": {"coordinates":[-1.559286,53.778965],"type":"Point"}
}
