{
  "type": "Feature",
  "properties": {
    "iso:country":"GB",
    "wof:name":"RM17 6QW",
    "wof:placetype":"postalcode"
},
  "geometry": {"coordinates":[0.32644179018759,51.47881675597339],"type":"Point"}
}