{
  "type": "Feature",
  "properties": {
    "iso:country": "GB",
    "wof:name": "RM17 6QW",
    "wof:placetype": "postalcode"
  },
  "geometry": {"coordinates":[0.326534,51.478933],"type":"Point"}
}
