{
  "type": "Feature",
  "properties": {
    "iso:country":"GB",
    "wof:name":"CF23 5QY",
    "wof:placetype":"postalcode"
},
  "geometry": {"coordinates":[-3.17748299390665,51.51497688722173],"type":"Point"}
}