{
  "type": "Feature",
  "properties": {
    "iso:country":"GB",
    "wof:name":"PH1 5QP",
    "wof:placetype":"postalcode"
},
  "geometry": {"coordinates":[-3.43527324240814,56.39763392482207],"type":"Point"}
}