{
  "type": "Feature",
  "properties": {
    "date:inception_lower": "1980-01-01",
    "date:inception_upper": "1980-01-01",
    "iso:country": "GB",
    "wof:name": "PH1 5QP",
    "wof:placetype": "postalcode"
  },
  "geometry": {"coordinates":[-3.435143,56.397644],"type":"Point"}
}
