{
  "type": "Feature",
  "properties": {
    "iso:country":"GB",
    "wof:name":"NN10 9PW",
    "wof:placetype":"postalcode"
},
  "geometry": {"coordinates":[-0.60739531848994,52.2864775375513],"type":"Point"}
}