{
  "type": "Feature",
  "properties": {
    "date:inception_lower": "1980-01-01",
    "date:inception_upper": "1980-01-01",
    "iso:country": "GB",
    "wof:name": "DE6 4PB",
    "wof:placetype": "postalcode"
  },
  "geometry": {"coordinates":[-1.567524,52.98004],"type":"Point"}
}
