{
  "type": "Feature",
  "properties": {
    "iso:country": "GB",
    "wof:name": "DE6 4PB",
    "wof:placetype": "postalcode"
  },
  "geometry": {"coordinates":[-1.567524,52.98004],"type":"Point"}
}
