{
  "type": "Feature",
  "properties": {
    "iso:country":"GB",
    "wof:name":"DE6 4PB",
    "wof:placetype":"postalcode"
},
  "geometry": {"coordinates":[-1.56752431769449,52.98003983654544],"type":"Point"}
}