{
  "type": "Feature",
  "properties": {
    "date:inception_lower":"1999-06-01",
    "date:inception_upper":"1999-06-30",
    "iso:country":"GB",
    "wof:name":"CF3 3EE",
    "wof:placetype":"postalcode"
},
  "geometry": {"coordinates":[-3.120919,51.504462],"type":"Point"}
}