{
  "type": "Feature",
  "properties": {
    "date:inception_lower": "2018-07-01",
    "date:inception_upper": "2018-07-01",
    "iso:country": "GB",
    "wof:name": "NN3 7DR",
    "wof:placetype": "postalcode"
  },
  "geometry": {"coordinates":[-0.838743,52.28644],"type":"Point"}
}
