{
  "type": "Feature",
  "properties": {
    "iso:country":"GB",
    "wof:name":"LS22 5LH",
    "wof:placetype":"postalcode"
},
  "geometry": {"coordinates":[-1.42446693650671,53.90534291567469],"type":"Point"}
}