{
  "type": "Feature",
  "properties": {
    "iso:country": "GB",
    "wof:name": "W14 0DR",
    "wof:placetype": "postalcode"
  },
  "geometry": {"coordinates":[-0.218321,51.500743],"type":"Point"}
}
