{
  "type": "Feature",
  "properties": {
    "iso:country":"GB",
    "wof:name":"W14 0DR",
    "wof:placetype":"postalcode"
},
  "geometry": {"coordinates":[-0.21832111321929,51.50074298077283],"type":"Point"}
}