{
  "type": "Feature",
  "properties": {
    "date:inception_lower":"1980-01-01",
    "date:inception_upper":"1980-01-31",
    "iso:country":"GB",
    "wof:name":"W14 0DR",
    "wof:placetype":"postalcode"
},
  "geometry": {"coordinates":[-0.218321,51.500743],"type":"Point"}
}