{
  "type": "Feature",
  "properties": {
    "iso:country":"GB",
    "wof:name":"DY6 9SS",
    "wof:placetype":"postalcode"
},
  "geometry": {"coordinates":[-2.17809289895602,52.48838626223174],"type":"Point"}
}