{
  "type": "Feature",
  "properties": {
    "iso:country":"GB",
    "wof:name":"HA3 5PU",
    "wof:placetype":"postalcode"
},
  "geometry": {"coordinates":[-0.34681468737518,51.60128727911686],"type":"Point"}
}