{
  "type": "Feature",
  "properties": {
    "date:inception_lower":"2009-04-01",
    "date:inception_upper":"2009-04-30",
    "iso:country":"GB",
    "wof:name":"LL61 6AB",
    "wof:placetype":"postalcode"
},
  "geometry": {"coordinates":[-4.356146,53.168066],"type":"Point"}
}