{
  "type": "Feature",
  "properties": {
    "iso:country": "GB",
    "wof:name": "LL61 6AB",
    "wof:placetype": "postalcode"
  },
  "geometry": {"coordinates":[-4.356146,53.168066],"type":"Point"}
}
