{
  "type": "Feature",
  "properties": {
    "iso:country": "GB",
    "wof:name": "NG19 7PE",
    "wof:placetype": "postalcode"
  },
  "geometry": {"coordinates":[-1.250873,53.175809],"type":"Point"}
}
