{
  "type": "Feature",
  "properties": {
    "iso:country":"GB",
    "wof:name":"NG19 7PE",
    "wof:placetype":"postalcode"
},
  "geometry": {"coordinates":[-1.25077145667323,53.17573567668594],"type":"Point"}
}