{
  "type": "Feature",
  "properties": {
    "iso:country": "GB",
    "wof:name": "SK13 2AJ",
    "wof:placetype": "postalcode"
  },
  "geometry": {"coordinates":[-1.972853,53.457168],"type":"Point"}
}
