{
  "type": "Feature",
  "properties": {
    "iso:country": "GB",
    "wof:name": "EH15 2EB",
    "wof:placetype": "postalcode"
  },
  "geometry": {"coordinates":[-3.10432,55.951627],"type":"Point"}
}
