{
  "type": "Feature",
  "properties": {
    "iso:country":"GB",
    "wof:name":"B24 8HB",
    "wof:placetype":"postalcode"
},
  "geometry": {"coordinates":[-1.84177058089223,52.5100540211341],"type":"Point"}
}