{
  "type": "Feature",
  "properties": {
    "iso:country": "GB",
    "wof:name": "FK2 8SU",
    "wof:placetype": "postalcode"
  },
  "geometry": {"coordinates":[-3.811871,56.042366],"type":"Point"}
}
