{
  "type": "Feature",
  "properties": {
    "iso:country":"GB",
    "wof:name":"SL8 5TW",
    "wof:placetype":"postalcode"
},
  "geometry": {"coordinates":[-0.71008784203557,51.585132709425],"type":"Point"}
}