{
  "type": "Feature",
  "properties": {
    "date:inception_lower": "2024-04-01",
    "date:inception_upper": "2024-04-01",
    "iso:country": "GB",
    "wof:name": "DA10 1GN",
    "wof:placetype": "postalcode"
  },
  "geometry": {"coordinates":[0.281681,51.439012],"type":"Point"}
}
