{
  "type": "Feature",
  "properties": {
    "iso:country":"GB",
    "wof:name":"WA2 7NJ",
    "wof:placetype":"postalcode"
},
  "geometry": {"coordinates":[-2.59716034193037,53.39340358437269],"type":"Point"}
}