{
  "type": "Feature",
  "properties": {
    "date:inception_lower": "1980-01-01",
    "date:inception_upper": "1980-01-01",
    "iso:country": "GB",
    "wof:name": "WA2 7NJ",
    "wof:placetype": "postalcode"
  },
  "geometry": {"coordinates":[-2.59716,53.393404],"type":"Point"}
}
