{
  "type": "Feature",
  "properties": {
    "iso:country": "GB",
    "wof:name": "WA2 7NJ",
    "wof:placetype": "postalcode"
  },
  "geometry": {"coordinates":[-2.59716,53.393404],"type":"Point"}
}
