{
  "type": "Feature",
  "properties": {
    "iso:country":"GB",
    "wof:name":"LS10 2RN",
    "wof:placetype":"postalcode"
},
  "geometry": {"coordinates":[-1.5314836242671,53.77332505716868],"type":"Point"}
}