{
  "type": "Feature",
  "properties": {
    "iso:country":"GB",
    "wof:name":"PO7 6JJ",
    "wof:placetype":"postalcode"
},
  "geometry": {"coordinates":[-1.05531432332759,50.90303896837007],"type":"Point"}
}