{
  "type": "Feature",
  "properties": {
    "iso:country":"GB",
    "wof:name":"KA22 8DU",
    "wof:placetype":"postalcode"
},
  "geometry": {"coordinates":[-4.80651005537988,55.64083504705606],"type":"Point"}
}