{
  "type": "Feature",
  "properties": {
    "date:inception_lower": "1980-01-01",
    "date:inception_upper": "1980-01-01",
    "iso:country": "GB",
    "wof:name": "BD21 3QP",
    "wof:placetype": "postalcode"
  },
  "geometry": {"coordinates":[-1.906097,53.866119],"type":"Point"}
}
