{
  "type": "Feature",
  "properties": {
    "iso:country":"GB",
    "wof:name":"DH7 9TF",
    "wof:placetype":"postalcode"
},
  "geometry": {"coordinates":[-1.66564533412339,54.79813400658981],"type":"Point"}
}