{
  "type": "Feature",
  "properties": {
    "iso:country":"GB",
    "wof:name":"CW2 7JS",
    "wof:placetype":"postalcode"
},
  "geometry": {"coordinates":[-2.44639382329276,53.08978037242739],"type":"Point"}
}