{
  "type": "Feature",
  "properties": {
    "iso:country": "GB",
    "wof:name": "GU22 8PS",
    "wof:placetype": "postalcode"
  },
  "geometry": {"coordinates":[-0.520049,51.327899],"type":"Point"}
}
