{
  "type": "Feature",
  "properties": {
    "iso:country":"GB",
    "wof:name":"DE7 4HN",
    "wof:placetype":"postalcode"
},
  "geometry": {"coordinates":[-1.31720050036371,52.96146284513902],"type":"Point"}
}