{
  "type": "Feature",
  "properties": {
    "iso:country":"GB",
    "wof:name":"WR11 7TR",
    "wof:placetype":"postalcode"
},
  "geometry": {"coordinates":[-1.95596489059598,52.01425582293788],"type":"Point"}
}