{
  "type": "Feature",
  "properties": {
    "date:inception_lower": "2001-12-01",
    "date:inception_upper": "2001-12-01",
    "iso:country": "GB",
    "wof:name": "WR11 7TR",
    "wof:placetype": "postalcode"
  },
  "geometry": {"coordinates":[-1.955965,52.014256],"type":"Point"}
}
