{
  "type": "Feature",
  "properties": {
    "iso:country":"GB",
    "wof:name":"RG1 5LN",
    "wof:placetype":"postalcode"
},
  "geometry": {"coordinates":[-0.95441105859533,51.44837942335651],"type":"Point"}
}