{
  "type": "Feature",
  "properties": {
    "date:inception_lower": "1980-01-01",
    "date:inception_upper": "1980-01-01",
    "iso:country": "GB",
    "wof:name": "M11 2HB",
    "wof:placetype": "postalcode"
  },
  "geometry": {"coordinates":[-2.187019,53.474172],"type":"Point"}
}
