{
  "type": "Feature",
  "properties": {
    "iso:country":"GB",
    "wof:name":"M11 2HB",
    "wof:placetype":"postalcode"
},
  "geometry": {"coordinates":[-2.18674875552741,53.47406637970338],"type":"Point"}
}