{
  "type": "Feature",
  "properties": {
    "iso:country":"GB",
    "wof:name":"RG7 3YJ",
    "wof:placetype":"postalcode"
},
  "geometry": {"coordinates":[-1.05640902100661,51.39883616623604],"type":"Point"}
}