{
  "type": "Feature",
  "properties": {
    "iso:country":"GB",
    "wof:name":"TS1 5JD",
    "wof:placetype":"postalcode"
},
  "geometry": {"coordinates":[-1.24273377702409,54.57563190243402],"type":"Point"}
}