{
  "type": "Feature",
  "properties": {
    "iso:country":"GB",
    "wof:name":"B31 1ND",
    "wof:placetype":"postalcode"
},
  "geometry": {"coordinates":[-1.97339912080272,52.42198279333632],"type":"Point"}
}