{
  "type": "Feature",
  "properties": {
    "date:inception_lower": "2021-08-01",
    "date:inception_upper": "2021-08-01",
    "iso:country": "GB",
    "wof:name": "OX26 5AL",
    "wof:placetype": "postalcode"
  },
  "geometry": {"coordinates":[-1.113905,51.897034],"type":"Point"}
}
