{
  "type": "Feature",
  "properties": {
    "date:inception_lower": "1980-01-01",
    "date:inception_upper": "1980-01-01",
    "iso:country": "GB",
    "wof:name": "BN1 5JH",
    "wof:placetype": "postalcode"
  },
  "geometry": {"coordinates":[-0.159368,50.855086],"type":"Point"}
}
