{
  "type": "Feature",
  "properties": {
    "iso:country":"GB",
    "wof:name":"SA43 3LS",
    "wof:placetype":"postalcode"
},
  "geometry": {"coordinates":[-4.7081201894957,52.09977518655849],"type":"Point"}
}