{
  "type": "Feature",
  "properties": {
    "iso:country":"GB",
    "wof:name":"CO7 0TB",
    "wof:placetype":"postalcode"
},
  "geometry": {"coordinates":[1.02774862678878,51.82006169563],"type":"Point"}
}