{
  "type": "Feature",
  "properties": {
    "iso:country": "GB",
    "wof:name": "RG41 5XS",
    "wof:placetype": "postalcode"
  },
  "geometry": {"coordinates":[-0.878407,51.425215],"type":"Point"}
}
