{
  "type": "Feature",
  "properties": {
    "iso:country": "GB",
    "wof:name": "M25 2SE",
    "wof:placetype": "postalcode"
  },
  "geometry": {"coordinates":[-2.248751,53.549618],"type":"Point"}
}
