{
  "type": "Feature",
  "properties": {
    "iso:country":"GB",
    "wof:name":"NE5 2QW",
    "wof:placetype":"postalcode"
},
  "geometry": {"coordinates":[-1.69872539849744,54.99310756435781],"type":"Point"}
}