{
  "type": "Feature",
  "properties": {
    "iso:country":"GB",
    "wof:name":"WF1 2DZ",
    "wof:placetype":"postalcode"
},
  "geometry": {"coordinates":[-1.50843920208489,53.70543528605208],"type":"Point"}
}