{
  "type": "Feature",
  "properties": {
    "iso:country": "GB",
    "wof:name": "TF2 8DY",
    "wof:placetype": "postalcode"
  },
  "geometry": {"coordinates":[-2.446636,52.71749],"type":"Point"}
}
