{
  "type": "Feature",
  "properties": {
    "date:inception_lower": "2016-11-01",
    "date:inception_upper": "2016-11-01",
    "iso:country": "GB",
    "wof:name": "TF2 8DY",
    "wof:placetype": "postalcode"
  },
  "geometry": {"coordinates":[-2.446636,52.71749],"type":"Point"}
}
