{
  "type": "Feature",
  "properties": {
    "iso:country":"GB",
    "wof:name":"SY15 6BT",
    "wof:placetype":"postalcode"
},
  "geometry": {"coordinates":[-3.06407511157826,52.59735245775111],"type":"Point"}
}