{
  "type": "Feature",
  "properties": {
    "iso:country": "GB",
    "wof:name": "SY15 6BT",
    "wof:placetype": "postalcode"
  },
  "geometry": {"coordinates":[-3.064075,52.597352],"type":"Point"}
}
