{
  "type": "Feature",
  "properties": {
    "date:inception_lower": "1980-01-01",
    "date:inception_upper": "1980-01-01",
    "iso:country": "GB",
    "wof:name": "SY15 6BT",
    "wof:placetype": "postalcode"
  },
  "geometry": {"coordinates":[-3.064075,52.597352],"type":"Point"}
}
