{
  "type": "Feature",
  "properties": {
    "iso:country":"GB",
    "wof:name":"MK6 4AU",
    "wof:placetype":"postalcode"
},
  "geometry": {"coordinates":[-0.72900240083035,52.01509767122393],"type":"Point"}
}