{
  "type": "Feature",
  "properties": {
    "iso:country":"GB",
    "wof:name":"YO8 9AR",
    "wof:placetype":"postalcode"
},
  "geometry": {"coordinates":[-1.08828878943403,53.77614101081185],"type":"Point"}
}