{
  "type": "Feature",
  "properties": {
    "iso:country": "GB",
    "wof:name": "SN4 8EF",
    "wof:placetype": "postalcode"
  },
  "geometry": {"coordinates":[-1.877983,51.561647],"type":"Point"}
}
