{
  "type": "Feature",
  "properties": {
    "iso:country":"GB",
    "wof:name":"SN4 8EF",
    "wof:placetype":"postalcode"
},
  "geometry": {"coordinates":[-1.87798306198322,51.56164680004095],"type":"Point"}
}