{
  "type": "Feature",
  "properties": {
    "iso:country":"GB",
    "wof:name":"ME9 8DU",
    "wof:placetype":"postalcode"
},
  "geometry": {"coordinates":[0.72053505108887,51.32419993241482],"type":"Point"}
}