{
  "type": "Feature",
  "properties": {
    "iso:country": "GB",
    "wof:name": "ME9 8DU",
    "wof:placetype": "postalcode"
  },
  "geometry": {"coordinates":[0.720581,51.3242],"type":"Point"}
}
