{
  "type": "Feature",
  "properties": {
    "iso:country":"GB",
    "wof:name":"NW1 5BZ",
    "wof:placetype":"postalcode"
},
  "geometry": {"coordinates":[-0.16935472036152,51.52035683334491],"type":"Point"}
}