{
  "type": "Feature",
  "properties": {
    "iso:country": "GB",
    "wof:name": "NW1 5BZ",
    "wof:placetype": "postalcode"
  },
  "geometry": {"coordinates":[-0.169355,51.520357],"type":"Point"}
}
