{
  "type": "Feature",
  "properties": {
    "iso:country":"GB",
    "wof:name":"DE55 5QF",
    "wof:placetype":"postalcode"
},
  "geometry": {"coordinates":[-1.33975609486412,53.14398207876843],"type":"Point"}
}