{
  "type": "Feature",
  "properties": {
    "iso:country": "GB",
    "wof:name": "DE55 5QF",
    "wof:placetype": "postalcode"
  },
  "geometry": {"coordinates":[-1.339756,53.143964],"type":"Point"}
}
