{
  "type": "Feature",
  "properties": {
    "iso:country": "GB",
    "wof:name": "LN2 1LY",
    "wof:placetype": "postalcode"
  },
  "geometry": {"coordinates":[-0.538272,53.233635],"type":"Point"}
}
