{
  "type": "Feature",
  "properties": {
    "date:inception_lower": "2010-05-01",
    "date:inception_upper": "2010-05-01",
    "iso:country": "GB",
    "wof:name": "EC1A 9LR",
    "wof:placetype": "postalcode"
  },
  "geometry": {"coordinates":[-0.102952,51.518169],"type":"Point"}
}
