{
  "type": "Feature",
  "properties": {
    "iso:country": "GB",
    "wof:name": "EC1A 9LR",
    "wof:placetype": "postalcode"
  },
  "geometry": {"coordinates":[-0.102952,51.518169],"type":"Point"}
}
