{
  "type": "Feature",
  "properties": {
    "iso:country": "GB",
    "wof:name": "AL3 5FF",
    "wof:placetype": "postalcode"
  },
  "geometry": {"coordinates":[-0.338821,51.755826],"type":"Point"}
}
