{
  "type": "Feature",
  "properties": {
    "date:inception_lower": "1980-01-01",
    "date:inception_upper": "1980-01-01",
    "iso:country": "GB",
    "wof:name": "DN40 3AW",
    "wof:placetype": "postalcode"
  },
  "geometry": {"coordinates":[-0.26707,53.608377],"type":"Point"}
}
