{
  "type": "Feature",
  "properties": {
    "iso:country":"GB",
    "wof:name":"HA3 7NF",
    "wof:placetype":"postalcode"
},
  "geometry": {"coordinates":[-0.33215889226226,51.59654790070622],"type":"Point"}
}