{
  "type": "Feature",
  "properties": {
    "date:inception_lower":"1980-01-01",
    "date:inception_upper":"1980-01-31",
    "iso:country":"GB",
    "wof:name":"HA3 7NF",
    "wof:placetype":"postalcode"
},
  "geometry": {"coordinates":[-0.332159,51.596548],"type":"Point"}
}