{
  "type": "Feature",
  "properties": {
    "iso:country":"GB",
    "wof:name":"OX2 6JF",
    "wof:placetype":"postalcode"
},
  "geometry": {"coordinates":[-1.26303715014532,51.76348411002786],"type":"Point"}
}