{
  "type": "Feature",
  "properties": {
    "iso:country": "GB",
    "wof:name": "CF82 9YX",
    "wof:placetype": "postalcode"
  },
  "geometry": {"coordinates":[-3.250858,51.643924],"type":"Point"}
}
