{
  "type": "Feature",
  "properties": {
    "iso:country": "GB",
    "wof:name": "DG8 7HL",
    "wof:placetype": "postalcode"
  },
  "geometry": {"coordinates":[-4.375241,54.903456],"type":"Point"}
}
