{
  "type": "Feature",
  "properties": {
    "iso:country":"GB",
    "wof:name":"NR6 6EW",
    "wof:placetype":"postalcode"
},
  "geometry": {"coordinates":[1.28171816087231,52.66693663586556],"type":"Point"}
}