{
  "type": "Feature",
  "properties": {
    "date:inception_lower": "1990-02-01",
    "date:inception_upper": "1990-02-01",
    "iso:country": "GB",
    "wof:name": "PR6 0BS",
    "wof:placetype": "postalcode"
  },
  "geometry": {"coordinates":[-2.620101,53.658223],"type":"Point"}
}
