{
  "type": "Feature",
  "properties": {
    "iso:country": "GB",
    "wof:name": "TS22 5QL",
    "wof:placetype": "postalcode"
  },
  "geometry": {"coordinates":[-1.350041,54.637286],"type":"Point"}
}
