{
  "type": "Feature",
  "properties": {
    "iso:country":"GB",
    "wof:name":"LL54 6PP",
    "wof:placetype":"postalcode"
},
  "geometry": {"coordinates":[-4.28214215863912,53.05775840324805],"type":"Point"}
}