{
  "type": "Feature",
  "properties": {
    "iso:country": "GB",
    "wof:name": "IP6 9RE",
    "wof:placetype": "postalcode"
  },
  "geometry": {"coordinates":[1.124921,52.140354],"type":"Point"}
}
