{
  "type": "Feature",
  "properties": {
    "iso:country":"GB",
    "wof:name":"ST4 3RQ",
    "wof:placetype":"postalcode"
},
  "geometry": {"coordinates":[-2.13970189623491,52.99761575542283],"type":"Point"}
}