{
  "type": "Feature",
  "properties": {
    "iso:country":"GB",
    "wof:name":"S1 4RA",
    "wof:placetype":"postalcode"
},
  "geometry": {"coordinates":[-1.4672290389648,53.37402550131528],"type":"Point"}
}