{
  "type": "Feature",
  "properties": {
    "iso:country":"GB",
    "wof:name":"TD11 3JN",
    "wof:placetype":"postalcode"
},
  "geometry": {"coordinates":[-2.25007802319361,55.72368410551961],"type":"Point"}
}