{
  "type": "Feature",
  "properties": {
    "iso:country": "GB",
    "wof:name": "TD11 3JN",
    "wof:placetype": "postalcode"
  },
  "geometry": {"coordinates":[-2.262226,55.728636],"type":"Point"}
}
