{
  "type": "Feature",
  "properties": {
    "date:inception_lower": "1980-01-01",
    "date:inception_upper": "1980-01-01",
    "iso:country": "GB",
    "wof:name": "TD11 3JN",
    "wof:placetype": "postalcode"
  },
  "geometry": {"coordinates":[-2.262226,55.728636],"type":"Point"}
}
