{
  "type": "Feature",
  "properties": {
    "date:inception_lower": "1980-01-01",
    "date:inception_upper": "1980-01-01",
    "iso:country": "GB",
    "wof:name": "S75 2TG",
    "wof:placetype": "postalcode"
  },
  "geometry": {"coordinates":[-1.494911,53.561063],"type":"Point"}
}
