{
  "type": "Feature",
  "properties": {
    "iso:country":"GB",
    "wof:name":"S75 2TG",
    "wof:placetype":"postalcode"
},
  "geometry": {"coordinates":[-1.49491091203786,53.5610627881517],"type":"Point"}
}