{
  "type": "Feature",
  "properties": {
    "date:inception_lower":"2005-05-01",
    "date:inception_upper":"2005-05-31",
    "iso:country":"GB",
    "wof:name":"IV30 5HA",
    "wof:placetype":"postalcode"
},
  "geometry": {"coordinates":[-3.476869,57.699448],"type":"Point"}
}