{
  "type": "Feature",
  "properties": {
    "iso:country":"GB",
    "wof:name":"IV30 5HA",
    "wof:placetype":"postalcode"
},
  "geometry": {"coordinates":[-3.47686858638106,57.69944797394778],"type":"Point"}
}