{
  "type": "Feature",
  "properties": {
    "date:inception_lower": "1980-01-01",
    "date:inception_upper": "1980-01-01",
    "iso:country": "GB",
    "wof:name": "RH19 4JB",
    "wof:placetype": "postalcode"
  },
  "geometry": {"coordinates":[-0.02192,51.069287],"type":"Point"}
}
