{
  "type": "Feature",
  "properties": {
    "iso:country":"GB",
    "wof:name":"BR5 1QY",
    "wof:placetype":"postalcode"
},
  "geometry": {"coordinates":[0.09217918817978,51.38966930756609],"type":"Point"}
}