{
  "type": "Feature",
  "properties": {
    "iso:country": "GB",
    "wof:name": "MK44 3EW",
    "wof:placetype": "postalcode"
  },
  "geometry": {"coordinates":[-0.358883,52.159776],"type":"Point"}
}
