{
  "type": "Feature",
  "properties": {
    "iso:country":"GB",
    "wof:name":"BH10 6AQ",
    "wof:placetype":"postalcode"
},
  "geometry": {"coordinates":[-1.88313095059966,50.75692246578916],"type":"Point"}
}