{
  "type": "Feature",
  "properties": {
    "iso:country": "GB",
    "wof:name": "BH10 6AQ",
    "wof:placetype": "postalcode"
  },
  "geometry": {"coordinates":[-1.883131,50.756922],"type":"Point"}
}
