{
  "type": "Feature",
  "properties": {
    "iso:country":"GB",
    "wof:name":"BL9 6SU",
    "wof:placetype":"postalcode"
},
  "geometry": {"coordinates":[-2.28332607420129,53.61246794189447],"type":"Point"}
}