{
  "type": "Feature",
  "properties": {
    "iso:country": "GB",
    "wof:name": "DN37 0AU",
    "wof:placetype": "postalcode"
  },
  "geometry": {"coordinates":[-0.140889,53.510096],"type":"Point"}
}
