{
  "type": "Feature",
  "properties": {
    "date:inception_lower":"2014-04-01",
    "date:inception_upper":"2014-04-30",
    "iso:country":"GB",
    "wof:name":"LS28 9JU",
    "wof:placetype":"postalcode"
},
  "geometry": {"coordinates":[-1.643575,53.789006],"type":"Point"}
}