{
  "type": "Feature",
  "properties": {
    "iso:country":"GB",
    "wof:name":"LS28 9JU",
    "wof:placetype":"postalcode"
},
  "geometry": {"coordinates":[-1.64357046941152,53.78899006167893],"type":"Point"}
}