{
  "type": "Feature",
  "properties": {
    "iso:country":"GB",
    "wof:name":"GU9 8PF",
    "wof:placetype":"postalcode"
},
  "geometry": {"coordinates":[-0.79664133267011,51.20786382349333],"type":"Point"}
}