{
  "type": "Feature",
  "properties": {
    "date:inception_lower":"1980-01-01",
    "date:inception_upper":"1980-01-31",
    "iso:country":"GB",
    "wof:name":"GU9 8PF",
    "wof:placetype":"postalcode"
},
  "geometry": {"coordinates":[-0.796641,51.207864],"type":"Point"}
}