{
  "type": "Feature",
  "properties": {
    "iso:country": "GB",
    "wof:name": "M11 1PR",
    "wof:placetype": "postalcode"
  },
  "geometry": {"coordinates":[-2.177521,53.479795],"type":"Point"}
}
