{
  "type": "Feature",
  "properties": {
    "iso:country":"GB",
    "wof:name":"L13 2DR",
    "wof:placetype":"postalcode"
},
  "geometry": {"coordinates":[-2.9179783616999,53.414423805442],"type":"Point"}
}