{
  "type": "Feature",
  "properties": {
    "iso:country":"GB",
    "wof:name":"SW12 9EJ",
    "wof:placetype":"postalcode"
},
  "geometry": {"coordinates":[-0.14867684499767,51.449782595591],"type":"Point"}
}