{
  "type": "Feature",
  "properties": {
    "iso:country":"GB",
    "wof:name":"BH22 8TD",
    "wof:placetype":"postalcode"
},
  "geometry": {"coordinates":[-1.90647729450683,50.78690678978912],"type":"Point"}
}