{
  "type": "Feature",
  "properties": {
    "iso:country": "GB",
    "wof:name": "BH22 8TD",
    "wof:placetype": "postalcode"
  },
  "geometry": {"coordinates":[-1.906477,50.786907],"type":"Point"}
}
