{
  "type": "Feature",
  "properties": {
    "date:inception_lower": "1995-07-01",
    "date:inception_upper": "1995-07-01",
    "iso:country": "GB",
    "wof:name": "SY7 8EA",
    "wof:placetype": "postalcode"
  },
  "geometry": {"coordinates":[-2.95459,52.467784],"type":"Point"}
}
