{
  "type": "Feature",
  "properties": {
    "iso:country": "GB",
    "wof:name": "SY7 8EA",
    "wof:placetype": "postalcode"
  },
  "geometry": {"coordinates":[-2.95459,52.467784],"type":"Point"}
}
