{
  "type": "Feature",
  "properties": {
    "iso:country":"GB",
    "wof:name":"SY7 8EA",
    "wof:placetype":"postalcode"
},
  "geometry": {"coordinates":[-2.95459037507462,52.46778399597571],"type":"Point"}
}