{
  "type": "Feature",
  "properties": {
    "iso:country": "GB",
    "wof:name": "EX11 1UW",
    "wof:placetype": "postalcode"
  },
  "geometry": {"coordinates":[-3.31918,50.739723],"type":"Point"}
}
