{
  "type": "Feature",
  "properties": {
    "iso:country":"GB",
    "wof:name":"HX6 4LN",
    "wof:placetype":"postalcode"
},
  "geometry": {"coordinates":[-1.97320368035486,53.66793454499162],"type":"Point"}
}