{
  "type": "Feature",
  "properties": {
    "date:inception_lower": "1981-09-01",
    "date:inception_upper": "1981-09-01",
    "iso:country": "GB",
    "wof:name": "HX6 4LN",
    "wof:placetype": "postalcode"
  },
  "geometry": {"coordinates":[-1.974036,53.668039],"type":"Point"}
}
