{
  "type": "Feature",
  "properties": {
    "iso:country":"GB",
    "wof:name":"B36 8JQ",
    "wof:placetype":"postalcode"
},
  "geometry": {"coordinates":[-1.81212641414082,52.49944757092904],"type":"Point"}
}