{
  "type": "Feature",
  "properties": {
    "iso:country": "GB",
    "wof:name": "M19 1RW",
    "wof:placetype": "postalcode"
  },
  "geometry": {"coordinates":[-2.214134,53.413411],"type":"Point"}
}
