{
  "type": "Feature",
  "properties": {
    "date:inception_lower":"1980-01-01",
    "date:inception_upper":"1980-01-31",
    "iso:country":"GB",
    "wof:name":"SE20 7EG",
    "wof:placetype":"postalcode"
},
  "geometry": {"coordinates":[-0.055533,51.417879],"type":"Point"}
}