{
  "type": "Feature",
  "properties": {
    "iso:country":"GB",
    "wof:name":"SE20 7EG",
    "wof:placetype":"postalcode"
},
  "geometry": {"coordinates":[-0.0555334900184,51.4178792083461],"type":"Point"}
}