{
  "type": "Feature",
  "properties": {
    "date:inception_lower": "1980-01-01",
    "date:inception_upper": "1980-01-01",
    "iso:country": "GB",
    "wof:name": "TN30 6DB",
    "wof:placetype": "postalcode"
  },
  "geometry": {"coordinates":[0.695074,51.081779],"type":"Point"}
}
