{
  "type": "Feature",
  "properties": {
    "iso:country":"GB",
    "wof:name":"TN30 6DB",
    "wof:placetype":"postalcode"
},
  "geometry": {"coordinates":[0.69507387595244,51.08177855035714],"type":"Point"}
}