{
  "type": "Feature",
  "properties": {
    "iso:country":"GB",
    "wof:name":"G73 2NZ",
    "wof:placetype":"postalcode"
},
  "geometry": {"coordinates":[-4.22190560287072,55.82466231299497],"type":"Point"}
}