{
  "type": "Feature",
  "properties": {
    "iso:country": "GB",
    "wof:name": "HU7 3JN",
    "wof:placetype": "postalcode"
  },
  "geometry": {"coordinates":[-0.345793,53.796845],"type":"Point"}
}
