{
  "type": "Feature",
  "properties": {
    "iso:country":"GB",
    "wof:name":"HU7 3JN",
    "wof:placetype":"postalcode"
},
  "geometry": {"coordinates":[-0.3457931278118,53.7968446030387],"type":"Point"}
}