{
  "type": "Feature",
  "properties": {
    "iso:country":"GB",
    "wof:name":"NE8 4EN",
    "wof:placetype":"postalcode"
},
  "geometry": {"coordinates":[-1.60129605906895,54.95464484983545],"type":"Point"}
}