{
  "type": "Feature",
  "properties": {
    "iso:country": "GB",
    "wof:name": "NR15 2UN",
    "wof:placetype": "postalcode"
  },
  "geometry": {"coordinates":[1.208154,52.47722],"type":"Point"}
}
