{
  "type": "Feature",
  "properties": {
    "iso:country":"GB",
    "wof:name":"NR15 2UN",
    "wof:placetype":"postalcode"
},
  "geometry": {"coordinates":[1.20815372404762,52.4772202359042],"type":"Point"}
}