{
  "type": "Feature",
  "properties": {
    "iso:country": "GB",
    "wof:name": "PE6 0SX",
    "wof:placetype": "postalcode"
  },
  "geometry": {"coordinates":[-0.094973,52.61877],"type":"Point"}
}
