{
  "type": "Feature",
  "properties": {
    "date:inception_lower":"1980-01-01",
    "date:inception_upper":"1980-01-31",
    "iso:country":"GB",
    "wof:name":"BL3 1BX",
    "wof:placetype":"postalcode"
},
  "geometry": {"coordinates":[-2.376551,53.562577],"type":"Point"}
}