{
  "type": "Feature",
  "properties": {
    "iso:country":"GB",
    "wof:name":"BN3 6EU",
    "wof:placetype":"postalcode"
},
  "geometry": {"coordinates":[-0.1573173002827,50.83392503648969],"type":"Point"}
}