{
  "type": "Feature",
  "properties": {
    "iso:country":"GB",
    "wof:name":"CB24 9EH",
    "wof:placetype":"postalcode"
},
  "geometry": {"coordinates":[0.10341389347657,52.25397881485649],"type":"Point"}
}