{
  "type": "Feature",
  "properties": {
    "iso:country": "GB",
    "wof:name": "CB24 9EH",
    "wof:placetype": "postalcode"
  },
  "geometry": {"coordinates":[0.103414,52.253979],"type":"Point"}
}
