{
  "type": "Feature",
  "properties": {
    "date:inception_lower": "1980-01-01",
    "date:inception_upper": "1980-01-01",
    "iso:country": "GB",
    "wof:name": "ST3 7DQ",
    "wof:placetype": "postalcode"
  },
  "geometry": {"coordinates":[-2.106345,52.974791],"type":"Point"}
}
