{
  "type": "Feature",
  "properties": {
    "iso:country":"GB",
    "wof:name":"DL13 3EX",
    "wof:placetype":"postalcode"
},
  "geometry": {"coordinates":[-1.87931293066704,54.73580828250672],"type":"Point"}
}