{
  "type": "Feature",
  "properties": {
    "iso:country":"GB",
    "wof:name":"S62 6FL",
    "wof:placetype":"postalcode"
},
  "geometry": {"coordinates":[-1.33772695531713,53.45130072371596],"type":"Point"}
}