{
  "type": "Feature",
  "properties": {
    "date:inception_lower": "2006-11-01",
    "date:inception_upper": "2006-11-01",
    "iso:country": "GB",
    "wof:name": "S62 6FL",
    "wof:placetype": "postalcode"
  },
  "geometry": {"coordinates":[-1.338045,53.451294],"type":"Point"}
}
