{
  "type": "Feature",
  "properties": {
    "date:inception_lower": "1997-12-01",
    "date:inception_upper": "1997-12-01",
    "iso:country": "GB",
    "wof:name": "BS35 4BU",
    "wof:placetype": "postalcode"
  },
  "geometry": {"coordinates":[-2.573299,51.585628],"type":"Point"}
}
