{
  "type": "Feature",
  "properties": {
    "date:inception_lower":"1984-02-01",
    "date:inception_upper":"1984-02-29",
    "iso:country":"GB",
    "wof:name":"SG12 9ET",
    "wof:placetype":"postalcode"
},
  "geometry": {"coordinates":[-0.032055,51.812725],"type":"Point"}
}