{
  "type": "Feature",
  "properties": {
    "iso:country": "GB",
    "wof:name": "SG12 9ET",
    "wof:placetype": "postalcode"
  },
  "geometry": {"coordinates":[-0.032055,51.812725],"type":"Point"}
}
