{
  "type": "Feature",
  "properties": {
    "iso:country":"GB",
    "wof:name":"CH7 6NW",
    "wof:placetype":"postalcode"
},
  "geometry": {"coordinates":[-3.13748133800521,53.17800550080091],"type":"Point"}
}