{
  "type": "Feature",
  "properties": {
    "iso:country":"GB",
    "wof:name":"W8 5BZ",
    "wof:placetype":"postalcode"
},
  "geometry": {"coordinates":[-0.18915529563058,51.49902833694575],"type":"Point"}
}