{
  "type": "Feature",
  "properties": {
    "date:inception_lower": "1999-06-01",
    "date:inception_upper": "1999-06-01",
    "iso:country": "GB",
    "wof:name": "NP20 4EP",
    "wof:placetype": "postalcode"
  },
  "geometry": {"coordinates":[-2.9949,51.584187],"type":"Point"}
}
