{
  "type": "Feature",
  "properties": {
    "iso:country": "GB",
    "wof:name": "PO6 1UR",
    "wof:placetype": "postalcode"
  },
  "geometry": {"coordinates":[-1.042323,50.840938],"type":"Point"}
}
