{
  "type": "Feature",
  "properties": {
    "iso:country":"GB",
    "wof:name":"HP15 6QT",
    "wof:placetype":"postalcode"
},
  "geometry": {"coordinates":[-0.69170423788463,51.6618092190636],"type":"Point"}
}