{
  "type": "Feature",
  "properties": {
    "iso:country":"GB",
    "wof:name":"CH1 3JW",
    "wof:placetype":"postalcode"
},
  "geometry": {"coordinates":[-2.88711002600881,53.19751871637246],"type":"Point"}
}