{
  "type": "Feature",
  "properties": {
    "iso:country": "GB",
    "wof:name": "CH1 3JW",
    "wof:placetype": "postalcode"
  },
  "geometry": {"coordinates":[-2.887095,53.19751],"type":"Point"}
}
