{
  "type": "Feature",
  "properties": {
    "iso:country":"GB",
    "wof:name":"LN13 0ER",
    "wof:placetype":"postalcode"
},
  "geometry": {"coordinates":[0.15899806883643,53.25083249174637],"type":"Point"}
}