{
  "type": "Feature",
  "properties": {
    "date:inception_lower": "1993-08-01",
    "date:inception_upper": "1993-08-01",
    "iso:country": "GB",
    "wof:name": "CA20 1RA",
    "wof:placetype": "postalcode"
  },
  "geometry": {"coordinates":[-3.482993,54.397357],"type":"Point"}
}
