{
  "type": "Feature",
  "properties": {
    "iso:country": "GB",
    "wof:name": "TN39 4GG",
    "wof:placetype": "postalcode"
  },
  "geometry": {"coordinates":[0.425555,50.846004],"type":"Point"}
}
