{
  "type": "Feature",
  "properties": {
    "iso:country":"GB",
    "wof:name":"BN12 4AJ",
    "wof:placetype":"postalcode"
},
  "geometry": {"coordinates":[-0.40145942889906,50.81381013246336],"type":"Point"}
}