{
  "type": "Feature",
  "properties": {
    "iso:country":"GB",
    "wof:name":"SY8 2BF",
    "wof:placetype":"postalcode"
},
  "geometry": {"coordinates":[-2.70463058173393,52.37790923144574],"type":"Point"}
}