{
  "type": "Feature",
  "properties": {
    "date:inception_lower": "2008-11-01",
    "date:inception_upper": "2008-11-01",
    "iso:country": "GB",
    "wof:name": "SY8 2BF",
    "wof:placetype": "postalcode"
  },
  "geometry": {"coordinates":[-2.704631,52.377909],"type":"Point"}
}
