{
  "type": "Feature",
  "properties": {
    "date:inception_lower": "1980-01-01",
    "date:inception_upper": "1980-01-01",
    "iso:country": "GB",
    "wof:name": "IP9 2SZ",
    "wof:placetype": "postalcode"
  },
  "geometry": {"coordinates":[1.124547,51.964513],"type":"Point"}
}
