{
  "type": "Feature",
  "properties": {
    "iso:country": "GB",
    "wof:name": "IP9 2SZ",
    "wof:placetype": "postalcode"
  },
  "geometry": {"coordinates":[1.124547,51.964513],"type":"Point"}
}
