{
  "type": "Feature",
  "properties": {
    "iso:country": "GB",
    "wof:name": "DA1 1EW",
    "wof:placetype": "postalcode"
  },
  "geometry": {"coordinates":[0.216361,51.443026],"type":"Point"}
}
