{
  "type": "Feature",
  "properties": {
    "iso:country":"GB",
    "wof:name":"DA1 1EW",
    "wof:placetype":"postalcode"
},
  "geometry": {"coordinates":[0.21636056303481,51.44302601417075],"type":"Point"}
}