{
  "type": "Feature",
  "properties": {
    "iso:country":"GB",
    "wof:name":"GL14 2TY",
    "wof:placetype":"postalcode"
},
  "geometry": {"coordinates":[-2.49990492891336,51.79165683526497],"type":"Point"}
}