{
  "type": "Feature",
  "properties": {
    "iso:country": "GB",
    "wof:name": "GL14 2TY",
    "wof:placetype": "postalcode"
  },
  "geometry": {"coordinates":[-2.499891,51.791671],"type":"Point"}
}
