{
  "type": "Feature",
  "properties": {
    "date:inception_lower":"1980-01-01",
    "date:inception_upper":"1980-01-31",
    "iso:country":"GB",
    "wof:name":"GL14 2TY",
    "wof:placetype":"postalcode"
},
  "geometry": {"coordinates":[-2.499891,51.791671],"type":"Point"}
}