{
  "type": "Feature",
  "properties": {
    "iso:country":"GB",
    "wof:name":"HP9 2RU",
    "wof:placetype":"postalcode"
},
  "geometry": {"coordinates":[-0.63138317418634,51.602306186942],"type":"Point"}
}