{
  "type": "Feature",
  "properties": {
    "iso:country":"GB",
    "wof:name":"CF42 5BU",
    "wof:placetype":"postalcode"
},
  "geometry": {"coordinates":[-3.54743170864755,51.6784166324825],"type":"Point"}
}