{
  "type": "Feature",
  "properties": {
    "date:inception_lower": "1980-01-01",
    "date:inception_upper": "1980-01-01",
    "iso:country": "GB",
    "wof:name": "CF42 5BU",
    "wof:placetype": "postalcode"
  },
  "geometry": {"coordinates":[-3.547432,51.678417],"type":"Point"}
}
