{
  "type": "Feature",
  "properties": {
    "iso:country": "GB",
    "wof:name": "KT12 2TT",
    "wof:placetype": "postalcode"
  },
  "geometry": {"coordinates":[-0.417958,51.385536],"type":"Point"}
}
