{
  "type": "Feature",
  "properties": {
    "date:inception_lower": "2004-01-01",
    "date:inception_upper": "2004-01-01",
    "iso:country": "GB",
    "wof:name": "LE11 2UF",
    "wof:placetype": "postalcode"
  },
  "geometry": {"coordinates":[-1.209973,52.745111],"type":"Point"}
}
