{
  "type": "Feature",
  "properties": {
    "iso:country": "GB",
    "wof:name": "LE11 2UF",
    "wof:placetype": "postalcode"
  },
  "geometry": {"coordinates":[-1.209973,52.745111],"type":"Point"}
}
