{
  "type": "Feature",
  "properties": {
    "iso:country":"GB",
    "wof:name":"LE11 2UF",
    "wof:placetype":"postalcode"
},
  "geometry": {"coordinates":[-1.20997260536516,52.74511085345392],"type":"Point"}
}