{
  "type": "Feature",
  "properties": {
    "iso:country": "GB",
    "wof:name": "NN16 0BQ",
    "wof:placetype": "postalcode"
  },
  "geometry": {"coordinates":[-0.722247,52.3996],"type":"Point"}
}
