{
  "type": "Feature",
  "properties": {
    "date:inception_lower": "2017-03-01",
    "date:inception_upper": "2017-03-01",
    "iso:country": "GB",
    "wof:name": "NN16 0BQ",
    "wof:placetype": "postalcode"
  },
  "geometry": {"coordinates":[-0.722247,52.3996],"type":"Point"}
}
