{
  "type": "Feature",
  "properties": {
    "date:inception_lower":"1983-07-01",
    "date:inception_upper":"1983-07-31",
    "iso:country":"GB",
    "wof:name":"WF10 5QH",
    "wof:placetype":"postalcode"
},
  "geometry": {"coordinates":[-1.396418,53.713894],"type":"Point"}
}