{
  "type": "Feature",
  "properties": {
    "iso:country":"GB",
    "wof:name":"W12 8DL",
    "wof:placetype":"postalcode"
},
  "geometry": {"coordinates":[-0.2256459955163,51.50282336998961],"type":"Point"}
}