{
  "type": "Feature",
  "properties": {
    "date:inception_lower": "2016-09-01",
    "date:inception_upper": "2016-09-01",
    "iso:country": "GB",
    "wof:name": "NR11 7DQ",
    "wof:placetype": "postalcode"
  },
  "geometry": {"coordinates":[1.171929,52.854929],"type":"Point"}
}
