{
  "type": "Feature",
  "properties": {
    "iso:country": "GB",
    "wof:name": "DE12 8ES",
    "wof:placetype": "postalcode"
  },
  "geometry": {"coordinates":[-1.636357,52.73351],"type":"Point"}
}
