{
  "type": "Feature",
  "properties": {
    "iso:country": "GB",
    "wof:name": "ST2 0SZ",
    "wof:placetype": "postalcode"
  },
  "geometry": {"coordinates":[-2.12251,53.003747],"type":"Point"}
}
