{
  "type": "Feature",
  "properties": {
    "iso:country": "GB",
    "wof:name": "RG7 6SA",
    "wof:placetype": "postalcode"
  },
  "geometry": {"coordinates":[-1.21647,51.419941],"type":"Point"}
}
