{
  "type": "Feature",
  "properties": {
    "iso:country":"GB",
    "wof:name":"RG7 6SA",
    "wof:placetype":"postalcode"
},
  "geometry": {"coordinates":[-1.21647029898888,51.41994102276424],"type":"Point"}
}