{
  "type": "Feature",
  "properties": {
    "date:inception_lower":"1996-12-01",
    "date:inception_upper":"1996-12-31",
    "iso:country":"GB",
    "wof:name":"TR18 4JD",
    "wof:placetype":"postalcode"
},
  "geometry": {"coordinates":[-5.541603,50.117861],"type":"Point"}
}