{
  "type": "Feature",
  "properties": {
    "date:inception_lower": "1986-04-01",
    "date:inception_upper": "1986-04-01",
    "iso:country": "GB",
    "wof:name": "TS20 2UA",
    "wof:placetype": "postalcode"
  },
  "geometry": {"coordinates":[-1.302789,54.588182],"type":"Point"}
}
