{
  "type": "Feature",
  "properties": {
    "iso:country":"GB",
    "wof:name":"TS20 2UA",
    "wof:placetype":"postalcode"
},
  "geometry": {"coordinates":[-1.30269790133696,54.58813354952751],"type":"Point"}
}