{
  "type": "Feature",
  "properties": {
    "iso:country": "GB",
    "wof:name": "TS20 2UA",
    "wof:placetype": "postalcode"
  },
  "geometry": {"coordinates":[-1.302789,54.588182],"type":"Point"}
}
