{
  "type": "Feature",
  "properties": {
    "iso:country":"GB",
    "wof:name":"HR2 6DS",
    "wof:placetype":"postalcode"
},
  "geometry": {"coordinates":[-2.70523423602824,52.03891720653121],"type":"Point"}
}