{
  "type": "Feature",
  "properties": {
    "date:inception_lower":"1993-01-01",
    "date:inception_upper":"1993-01-31",
    "iso:country":"GB",
    "wof:name":"HR2 6DS",
    "wof:placetype":"postalcode"
},
  "geometry": {"coordinates":[-2.705234,52.038917],"type":"Point"}
}