{
  "type": "Feature",
  "properties": {
    "iso:country": "GB",
    "wof:name": "DA1 2ET",
    "wof:placetype": "postalcode"
  },
  "geometry": {"coordinates":[0.210544,51.444755],"type":"Point"}
}
