{
  "type": "Feature",
  "properties": {
    "iso:country":"GB",
    "wof:name":"DA1 2ET",
    "wof:placetype":"postalcode"
},
  "geometry": {"coordinates":[0.21054389895722,51.44475461370236],"type":"Point"}
}