{
  "type": "Feature",
  "properties": {
    "iso:country": "GB",
    "wof:name": "CT12 5AE",
    "wof:placetype": "postalcode"
  },
  "geometry": {"coordinates":[1.386733,51.353671],"type":"Point"}
}
