{
  "type": "Feature",
  "properties": {
    "iso:country":"GB",
    "wof:name":"CT12 5AE",
    "wof:placetype":"postalcode"
},
  "geometry": {"coordinates":[1.38727030267384,51.35449289808604],"type":"Point"}
}