{
  "type": "Feature",
  "properties": {
    "date:inception_lower":"1980-01-01",
    "date:inception_upper":"1980-01-31",
    "iso:country":"GB",
    "wof:name":"CT12 5AE",
    "wof:placetype":"postalcode"
},
  "geometry": {"coordinates":[1.38727,51.354493],"type":"Point"}
}