{
  "type": "Feature",
  "properties": {
    "iso:country":"GB",
    "wof:name":"BS40 6PF",
    "wof:placetype":"postalcode"
},
  "geometry": {"coordinates":[-2.68069479224875,51.31648184823654],"type":"Point"}
}