{
  "type": "Feature",
  "properties": {
    "date:inception_lower":"1997-12-01",
    "date:inception_upper":"1997-12-31",
    "iso:country":"GB",
    "wof:name":"BS40 6PF",
    "wof:placetype":"postalcode"
},
  "geometry": {"coordinates":[-2.680695,51.316482],"type":"Point"}
}