{
  "type": "Feature",
  "properties": {
    "iso:country": "GB",
    "wof:name": "BS40 6PF",
    "wof:placetype": "postalcode"
  },
  "geometry": {"coordinates":[-2.680695,51.316482],"type":"Point"}
}
