{
  "type": "Feature",
  "properties": {
    "iso:country":"GB",
    "wof:name":"M34 5JH",
    "wof:placetype":"postalcode"
},
  "geometry": {"coordinates":[-2.11222648980531,53.47175085456903],"type":"Point"}
}