{
  "type": "Feature",
  "properties": {
    "iso:country":"GB",
    "wof:name":"RH10 6NY",
    "wof:placetype":"postalcode"
},
  "geometry": {"coordinates":[-0.16865425349073,51.10686816788948],"type":"Point"}
}