{
  "type": "Feature",
  "properties": {
    "iso:country":"GB",
    "wof:name":"SO32 3QN",
    "wof:placetype":"postalcode"
},
  "geometry": {"coordinates":[-1.13942541645322,50.96369635023596],"type":"Point"}
}