{
  "type": "Feature",
  "properties": {
    "iso:country":"GB",
    "wof:name":"GU14 6RX",
    "wof:placetype":"postalcode"
},
  "geometry": {"coordinates":[-0.75178810045336,51.28365787546923],"type":"Point"}
}