{
  "type": "Feature",
  "properties": {
    "iso:country":"GB",
    "wof:name":"LS13 4TR",
    "wof:placetype":"postalcode"
},
  "geometry": {"coordinates":[-1.62723643100142,53.80119110366817],"type":"Point"}
}