{
  "type": "Feature",
  "properties": {
    "date:inception_lower": "1980-01-01",
    "date:inception_upper": "1980-01-01",
    "iso:country": "GB",
    "wof:name": "LS13 4TR",
    "wof:placetype": "postalcode"
  },
  "geometry": {"coordinates":[-1.62724,53.801207],"type":"Point"}
}
