{
  "type": "Feature",
  "properties": {
    "iso:country":"GB",
    "wof:name":"KY1 4QQ",
    "wof:placetype":"postalcode"
},
  "geometry": {"coordinates":[-3.05916990830054,56.16580707709647],"type":"Point"}
}