{
  "type": "Feature",
  "properties": {
    "iso:country":"GB",
    "wof:name":"IG2 7RT",
    "wof:placetype":"postalcode"
},
  "geometry": {"coordinates":[0.09453911943913,51.57611153109191],"type":"Point"}
}