{
  "type": "Feature",
  "properties": {
    "iso:country":"GB",
    "wof:name":"KA15 1BH",
    "wof:placetype":"postalcode"
},
  "geometry": {"coordinates":[-4.64119502601365,55.74796638538592],"type":"Point"}
}