{
  "type": "Feature",
  "properties": {
    "iso:country": "GB",
    "wof:name": "KA15 1BH",
    "wof:placetype": "postalcode"
  },
  "geometry": {"coordinates":[-4.641195,55.747966],"type":"Point"}
}
