{
  "type": "Feature",
  "properties": {
    "date:inception_lower": "1980-01-01",
    "date:inception_upper": "1980-01-01",
    "iso:country": "GB",
    "wof:name": "KA15 1BH",
    "wof:placetype": "postalcode"
  },
  "geometry": {"coordinates":[-4.641195,55.747966],"type":"Point"}
}
