{
  "type": "Feature",
  "properties": {
    "date:inception_lower": "2019-10-01",
    "date:inception_upper": "2019-10-01",
    "iso:country": "GB",
    "wof:name": "YO21 3FP",
    "wof:placetype": "postalcode"
  },
  "geometry": {"coordinates":[-0.692514,54.504787],"type":"Point"}
}
