{
  "type": "Feature",
  "properties": {
    "iso:country":"GB",
    "wof:name":"NE34 9DW",
    "wof:placetype":"postalcode"
},
  "geometry": {"coordinates":[-1.46076869899687,54.96354785396304],"type":"Point"}
}