{
  "type": "Feature",
  "properties": {
    "iso:country":"GB",
    "wof:name":"RG40 3DA",
    "wof:placetype":"postalcode"
},
  "geometry": {"coordinates":[-0.80095158693499,51.40436944990419],"type":"Point"}
}