{
  "type": "Feature",
  "properties": {
    "iso:country": "GB",
    "wof:name": "RM5 2UB",
    "wof:placetype": "postalcode"
  },
  "geometry": {"coordinates":[0.162203,51.60816],"type":"Point"}
}
