{
  "type": "Feature",
  "properties": {
    "iso:country":"GB",
    "wof:name":"RM5 2UB",
    "wof:placetype":"postalcode"
},
  "geometry": {"coordinates":[0.16219005360905,51.6081576604423],"type":"Point"}
}