{
  "type": "Feature",
  "properties": {
    "date:inception_lower": "1980-01-01",
    "date:inception_upper": "1980-01-01",
    "iso:country": "GB",
    "wof:name": "RM5 2UB",
    "wof:placetype": "postalcode"
  },
  "geometry": {"coordinates":[0.162203,51.60816],"type":"Point"}
}
