{
  "type": "Feature",
  "properties": {
    "date:inception_lower": "2022-06-01",
    "date:inception_upper": "2022-06-01",
    "iso:country": "GB",
    "wof:name": "IV36 2AF",
    "wof:placetype": "postalcode"
  },
  "geometry": {"coordinates":[-3.629042,57.595123],"type":"Point"}
}
