{
  "type": "Feature",
  "properties": {
    "iso:country": "GB",
    "wof:name": "L40 4BH",
    "wof:placetype": "postalcode"
  },
  "geometry": {"coordinates":[-2.808902,53.592676],"type":"Point"}
}
