{
  "type": "Feature",
  "properties": {
    "iso:country":"GB",
    "wof:name":"L40 4BH",
    "wof:placetype":"postalcode"
},
  "geometry": {"coordinates":[-2.80890200813876,53.59267580108551],"type":"Point"}
}