{
  "type": "Feature",
  "properties": {
    "date:inception_lower": "1980-01-01",
    "date:inception_upper": "1980-01-01",
    "iso:country": "GB",
    "wof:name": "L40 4BH",
    "wof:placetype": "postalcode"
  },
  "geometry": {"coordinates":[-2.808916,53.592683],"type":"Point"}
}
