{
  "type": "Feature",
  "properties": {
    "iso:country":"GB",
    "wof:name":"PL9 9FN",
    "wof:placetype":"postalcode"
},
  "geometry": {"coordinates":[-4.114123703725,50.35574839878853],"type":"Point"}
}