{
  "type": "Feature",
  "properties": {
    "date:inception_lower": "2014-06-01",
    "date:inception_upper": "2014-06-01",
    "iso:country": "GB",
    "wof:name": "PL9 9FN",
    "wof:placetype": "postalcode"
  },
  "geometry": {"coordinates":[-4.115266,50.358016],"type":"Point"}
}
