{
  "type": "Feature",
  "properties": {
    "iso:country":"GB",
    "wof:name":"WD19 4PZ",
    "wof:placetype":"postalcode"
},
  "geometry": {"coordinates":[-0.3880694097908,51.64487917179437],"type":"Point"}
}