{
  "type": "Feature",
  "properties": {
    "date:inception_lower": "1980-01-01",
    "date:inception_upper": "1980-01-01",
    "iso:country": "GB",
    "wof:name": "SY3 0EY",
    "wof:placetype": "postalcode"
  },
  "geometry": {"coordinates":[-2.764209,52.670531],"type":"Point"}
}
