{
  "type": "Feature",
  "properties": {
    "iso:country": "GB",
    "wof:name": "SY3 0EY",
    "wof:placetype": "postalcode"
  },
  "geometry": {"coordinates":[-2.764298,52.670549],"type":"Point"}
}
