{
  "type": "Feature",
  "properties": {
    "date:inception_lower": "2019-03-01",
    "date:inception_upper": "2019-03-01",
    "iso:country": "GB",
    "wof:name": "IG11 0YU",
    "wof:placetype": "postalcode"
  },
  "geometry": {"coordinates":[0.122398,51.524174],"type":"Point"}
}
