{
  "type": "Feature",
  "properties": {
    "iso:country": "GB",
    "wof:name": "PO9 5HS",
    "wof:placetype": "postalcode"
  },
  "geometry": {"coordinates":[-0.976877,50.868889],"type":"Point"}
}
