{
  "type": "Feature",
  "properties": {
    "date:inception_lower": "1980-01-01",
    "date:inception_upper": "1980-01-01",
    "iso:country": "GB",
    "wof:name": "PO9 5HS",
    "wof:placetype": "postalcode"
  },
  "geometry": {"coordinates":[-0.976877,50.868889],"type":"Point"}
}
