{
  "type": "Feature",
  "properties": {
    "iso:country": "GB",
    "wof:name": "CM5 5BJ",
    "wof:placetype": "postalcode"
  },
  "geometry": {"coordinates":[0.245192,51.703816],"type":"Point"}
}
