{
  "type": "Feature",
  "properties": {
    "iso:country":"GB",
    "wof:name":"G1 5PX",
    "wof:placetype":"postalcode"
},
  "geometry": {"coordinates":[-4.24270850737123,55.85377245121717],"type":"Point"}
}