{
  "type": "Feature",
  "properties": {
    "iso:country":"GB",
    "wof:name":"E1 4FY",
    "wof:placetype":"postalcode"
},
  "geometry": {"coordinates":[-0.04143038447993,51.52028684973912],"type":"Point"}
}