{
  "type": "Feature",
  "properties": {
    "date:inception_lower": "1987-04-01",
    "date:inception_upper": "1987-04-01",
    "iso:country": "GB",
    "wof:name": "DE6 1RW",
    "wof:placetype": "postalcode"
  },
  "geometry": {"coordinates":[-1.725076,53.023494],"type":"Point"}
}
