{
  "type": "Feature",
  "properties": {
    "date:inception_lower": "1987-04-01",
    "date:inception_upper": "1987-04-01",
    "iso:country": "GB",
    "wof:name": "L30 6XT",
    "wof:placetype": "postalcode"
  },
  "geometry": {"coordinates":[-2.960769,53.483175],"type":"Point"}
}
