{
  "type": "Feature",
  "properties": {
    "date:inception_lower":"1980-01-01",
    "date:inception_upper":"1980-01-31",
    "iso:country":"GB",
    "wof:name":"RG8 7BE",
    "wof:placetype":"postalcode"
},
  "geometry": {"coordinates":[-1.090784,51.479036],"type":"Point"}
}