{
  "type": "Feature",
  "properties": {
    "iso:country":"GB",
    "wof:name":"RG8 7BE",
    "wof:placetype":"postalcode"
},
  "geometry": {"coordinates":[-1.09078411500389,51.47903600725876],"type":"Point"}
}