{
  "type": "Feature",
  "properties": {
    "iso:country":"GB",
    "wof:name":"PE23 4HL",
    "wof:placetype":"postalcode"
},
  "geometry": {"coordinates":[0.01382127567613,53.16149174555335],"type":"Point"}
}