{
  "type": "Feature",
  "properties": {
    "iso:country":"GB",
    "wof:name":"BD16 3DL",
    "wof:placetype":"postalcode"
},
  "geometry": {"coordinates":[-1.82292694997844,53.85242100140891],"type":"Point"}
}