{
  "type": "Feature",
  "properties": {
    "iso:country":"GB",
    "wof:name":"EX2 4DA",
    "wof:placetype":"postalcode"
},
  "geometry": {"coordinates":[-3.52963420852476,50.71949753722669],"type":"Point"}
}