{
  "type": "Feature",
  "properties": {
    "iso:country": "GB",
    "wof:name": "HU4 6EN",
    "wof:placetype": "postalcode"
  },
  "geometry": {"coordinates":[-0.398006,53.738325],"type":"Point"}
}
