{
  "type": "Feature",
  "properties": {
    "iso:country":"GB",
    "wof:name":"HU4 6EN",
    "wof:placetype":"postalcode"
},
  "geometry": {"coordinates":[-0.39800574933605,53.73832457535847],"type":"Point"}
}