{
  "type": "Feature",
  "properties": {
    "iso:country": "GB",
    "wof:name": "SA68 0XT",
    "wof:placetype": "postalcode"
  },
  "geometry": {"coordinates":[-4.713315,51.727472],"type":"Point"}
}
