{
  "type": "Feature",
  "properties": {
    "iso:country":"GB",
    "wof:name":"SA68 0XT",
    "wof:placetype":"postalcode"
},
  "geometry": {"coordinates":[-4.71325637420545,51.72748105183859],"type":"Point"}
}