{
  "type": "Feature",
  "properties": {
    "iso:country": "GB",
    "wof:name": "PL14 3NP",
    "wof:placetype": "postalcode"
  },
  "geometry": {"coordinates":[-4.455097,50.45781],"type":"Point"}
}
