{
  "type": "Feature",
  "properties": {
    "iso:country":"GB",
    "wof:name":"PL14 3NP",
    "wof:placetype":"postalcode"
},
  "geometry": {"coordinates":[-4.45509752987395,50.45781007473974],"type":"Point"}
}