{
  "type": "Feature",
  "properties": {
    "iso:country": "GB",
    "wof:name": "IP22 2NG",
    "wof:placetype": "postalcode"
  },
  "geometry": {"coordinates":[0.990734,52.413467],"type":"Point"}
}
