{
  "type": "Feature",
  "properties": {
    "date:inception_lower": "2000-10-01",
    "date:inception_upper": "2000-10-01",
    "iso:country": "GB",
    "wof:name": "GU16 7HT",
    "wof:placetype": "postalcode"
  },
  "geometry": {"coordinates":[-0.743722,51.313372],"type":"Point"}
}
