{
  "type": "Feature",
  "properties": {
    "iso:country":"GB",
    "wof:name":"HD2 2LL",
    "wof:placetype":"postalcode"
},
  "geometry": {"coordinates":[-1.7799883494544,53.67120531005235],"type":"Point"}
}