{
  "type": "Feature",
  "properties": {
    "iso:country": "GB",
    "wof:name": "HD2 2LL",
    "wof:placetype": "postalcode"
  },
  "geometry": {"coordinates":[-1.779988,53.671205],"type":"Point"}
}
