{
  "type": "Feature",
  "properties": {
    "iso:country":"GB",
    "wof:name":"YO62 5HT",
    "wof:placetype":"postalcode"
},
  "geometry": {"coordinates":[-1.06331378026134,54.24904103959701],"type":"Point"}
}