{
  "type": "Feature",
  "properties": {
    "iso:country":"GB",
    "wof:name":"DH9 6TL",
    "wof:placetype":"postalcode"
},
  "geometry": {"coordinates":[-1.68713060229954,54.866020967289],"type":"Point"}
}