{
  "type": "Feature",
  "properties": {
    "iso:country": "GB",
    "wof:name": "WF1 2DY",
    "wof:placetype": "postalcode"
  },
  "geometry": {"coordinates":[-1.50194,53.709542],"type":"Point"}
}
