{
  "type": "Feature",
  "properties": {
    "iso:country":"GB",
    "wof:name":"WF1 2DY",
    "wof:placetype":"postalcode"
},
  "geometry": {"coordinates":[-1.50153124579209,53.70929864711154],"type":"Point"}
}