{
  "type": "Feature",
  "properties": {
    "date:inception_lower": "2012-11-01",
    "date:inception_upper": "2012-11-01",
    "iso:country": "GB",
    "wof:name": "NW9 5XW",
    "wof:placetype": "postalcode"
  },
  "geometry": {"coordinates":[-0.253046,51.596075],"type":"Point"}
}
