{
  "type": "Feature",
  "properties": {
    "date:inception_lower":"2009-11-01",
    "date:inception_upper":"2009-11-30",
    "iso:country":"GB",
    "wof:name":"DE21 4TQ",
    "wof:placetype":"postalcode"
},
  "geometry": {"coordinates":[-1.471833,52.934806],"type":"Point"}
}