{
  "type": "Feature",
  "properties": {
    "iso:country":"GB",
    "wof:name":"DE21 4TQ",
    "wof:placetype":"postalcode"
},
  "geometry": {"coordinates":[-1.47183264682517,52.93480567290444],"type":"Point"}
}