{
  "type": "Feature",
  "properties": {
    "iso:country": "GB",
    "wof:name": "SY23 5PG",
    "wof:placetype": "postalcode"
  },
  "geometry": {"coordinates":[-4.183149,52.251046],"type":"Point"}
}
