{
  "type": "Feature",
  "properties": {
    "iso:country":"GB",
    "wof:name":"FY6 7PX",
    "wof:placetype":"postalcode"
},
  "geometry": {"coordinates":[-3.00421465636097,53.84210927789777],"type":"Point"}
}