{
  "type": "Feature",
  "properties": {
    "date:inception_lower": "1980-01-01",
    "date:inception_upper": "1980-01-01",
    "iso:country": "GB",
    "wof:name": "BA14 0HP",
    "wof:placetype": "postalcode"
  },
  "geometry": {"coordinates":[-2.219302,51.308428],"type":"Point"}
}
