{
  "type": "Feature",
  "properties": {
    "iso:country":"GB",
    "wof:name":"M30 7SD",
    "wof:placetype":"postalcode"
},
  "geometry": {"coordinates":[-2.36747445989001,53.47862654772342],"type":"Point"}
}