{
  "type": "Feature",
  "properties": {
    "iso:country": "GB",
    "wof:name": "WS1 3PP",
    "wof:placetype": "postalcode"
  },
  "geometry": {"coordinates":[-1.986395,52.577807],"type":"Point"}
}
