{
  "type": "Feature",
  "properties": {
    "iso:country":"GB",
    "wof:name":"WS1 3PP",
    "wof:placetype":"postalcode"
},
  "geometry": {"coordinates":[-1.98639516403159,52.57780738639683],"type":"Point"}
}