{
  "type": "Feature",
  "properties": {
    "iso:country":"GB",
    "wof:name":"HP3 8DS",
    "wof:placetype":"postalcode"
},
  "geometry": {"coordinates":[-0.45152113187454,51.7474226077765],"type":"Point"}
}