{
  "type": "Feature",
  "properties": {
    "date:inception_lower":"1980-01-01",
    "date:inception_upper":"1980-01-31",
    "iso:country":"GB",
    "wof:name":"CB11 3JT",
    "wof:placetype":"postalcode"
},
  "geometry": {"coordinates":[0.257499,51.990232],"type":"Point"}
}