{
  "type": "Feature",
  "properties": {
    "iso:country": "GB",
    "wof:name": "CB11 3JT",
    "wof:placetype": "postalcode"
  },
  "geometry": {"coordinates":[0.257499,51.990232],"type":"Point"}
}
