{
  "type": "Feature",
  "properties": {
    "iso:country":"GB",
    "wof:name":"CB11 3JT",
    "wof:placetype":"postalcode"
},
  "geometry": {"coordinates":[0.25749897267607,51.99023184870814],"type":"Point"}
}