{
  "type": "Feature",
  "properties": {
    "iso:country":"GB",
    "wof:name":"EX6 8UE",
    "wof:placetype":"postalcode"
},
  "geometry": {"coordinates":[-3.48924469135871,50.67477529819719],"type":"Point"}
}