{
  "type": "Feature",
  "properties": {
    "iso:country":"GB",
    "wof:name":"AB43 7AY",
    "wof:placetype":"postalcode"
},
  "geometry": {"coordinates":[-2.05135723103065,57.61649822231112],"type":"Point"}
}