{
  "type": "Feature",
  "properties": {
    "iso:country":"GB",
    "wof:name":"NG5 5LW",
    "wof:placetype":"postalcode"
},
  "geometry": {"coordinates":[-1.17067422381321,52.99744187000717],"type":"Point"}
}