{
  "type": "Feature",
  "properties": {
    "date:inception_lower": "1980-01-01",
    "date:inception_upper": "1980-01-01",
    "iso:country": "GB",
    "wof:name": "NG5 5LW",
    "wof:placetype": "postalcode"
  },
  "geometry": {"coordinates":[-1.17067,52.997488],"type":"Point"}
}
