{
  "type": "Feature",
  "properties": {
    "date:inception_lower":"2008-03-01",
    "date:inception_upper":"2008-03-31",
    "iso:country":"GB",
    "wof:name":"NE49 9FA",
    "wof:placetype":"postalcode"
},
  "geometry": {"coordinates":[-2.461694,54.970838],"type":"Point"}
}