{
  "type": "Feature",
  "properties": {
    "iso:country":"GB",
    "wof:name":"NE49 9FA",
    "wof:placetype":"postalcode"
},
  "geometry": {"coordinates":[-2.46169365495254,54.97083814627793],"type":"Point"}
}