{
  "type": "Feature",
  "properties": {
    "iso:country":"GB",
    "wof:name":"BN2 5FW",
    "wof:placetype":"postalcode"
},
  "geometry": {"coordinates":[-0.10555632872927,50.83242154224516],"type":"Point"}
}