{
  "type": "Feature",
  "properties": {
    "iso:country": "GB",
    "wof:name": "NP20 3SF",
    "wof:placetype": "postalcode"
  },
  "geometry": {"coordinates":[-3.032026,51.583713],"type":"Point"}
}
