{
  "type": "Feature",
  "properties": {
    "iso:country":"GB",
    "wof:name":"NP20 3SF",
    "wof:placetype":"postalcode"
},
  "geometry": {"coordinates":[-3.03202606981607,51.58371308602673],"type":"Point"}
}