{
  "type": "Feature",
  "properties": {
    "date:inception_lower": "1980-01-01",
    "date:inception_upper": "1980-01-01",
    "iso:country": "GB",
    "wof:name": "IP16 4AN",
    "wof:placetype": "postalcode"
  },
  "geometry": {"coordinates":[1.579318,52.208581],"type":"Point"}
}
