{
  "type": "Feature",
  "properties": {
    "iso:country":"GB",
    "wof:name":"IP16 4AN",
    "wof:placetype":"postalcode"
},
  "geometry": {"coordinates":[1.57928644991753,52.20856064597888],"type":"Point"}
}