{
  "type": "Feature",
  "properties": {
    "date:inception_lower": "1995-12-01",
    "date:inception_upper": "1995-12-01",
    "iso:country": "GB",
    "wof:name": "G5 0RA",
    "wof:placetype": "postalcode"
  },
  "geometry": {"coordinates":[-4.249805,55.848556],"type":"Point"}
}
