{
  "type": "Feature",
  "properties": {
    "iso:country":"GB",
    "wof:name":"G5 0RA",
    "wof:placetype":"postalcode"
},
  "geometry": {"coordinates":[-4.24980463643482,55.84855595893193],"type":"Point"}
}