{
  "type": "Feature",
  "properties": {
    "iso:country":"GB",
    "wof:name":"MK18 2QU",
    "wof:placetype":"postalcode"
},
  "geometry": {"coordinates":[-0.9761847246899,51.93705261104616],"type":"Point"}
}