{
  "type": "Feature",
  "properties": {
    "iso:country":"GB",
    "wof:name":"PR7 3PN",
    "wof:placetype":"postalcode"
},
  "geometry": {"coordinates":[-2.64632978635967,53.63882244822929],"type":"Point"}
}