{
  "type": "Feature",
  "properties": {
    "date:inception_lower": "1980-01-01",
    "date:inception_upper": "1980-01-01",
    "iso:country": "GB",
    "wof:name": "TF9 3TG",
    "wof:placetype": "postalcode"
  },
  "geometry": {"coordinates":[-2.514647,52.965966],"type":"Point"}
}
