{
  "type": "Feature",
  "properties": {
    "iso:country":"GB",
    "wof:name":"TF9 3TG",
    "wof:placetype":"postalcode"
},
  "geometry": {"coordinates":[-2.5146473794903,52.96596579194745],"type":"Point"}
}