{
  "type": "Feature",
  "properties": {
    "iso:country": "GB",
    "wof:name": "TN35 5ED",
    "wof:placetype": "postalcode"
  },
  "geometry": {"coordinates":[0.611311,50.873312],"type":"Point"}
}
