{
  "type": "Feature",
  "properties": {
    "date:inception_lower": "1980-01-01",
    "date:inception_upper": "1980-01-01",
    "iso:country": "GB",
    "wof:name": "TN35 5ED",
    "wof:placetype": "postalcode"
  },
  "geometry": {"coordinates":[0.611311,50.873312],"type":"Point"}
}
