{
  "type": "Feature",
  "properties": {
    "iso:country":"GB",
    "wof:name":"RG42 2QA",
    "wof:placetype":"postalcode"
},
  "geometry": {"coordinates":[-0.74970020997817,51.42907470688233],"type":"Point"}
}