{
  "type": "Feature",
  "properties": {
    "iso:country": "GB",
    "wof:name": "ME4 4WZ",
    "wof:placetype": "postalcode"
  },
  "geometry": {"coordinates":[0.525518,51.380607],"type":"Point"}
}
