{
  "type": "Feature",
  "properties": {
    "date:inception_lower": "2017-11-01",
    "date:inception_upper": "2017-11-01",
    "iso:country": "GB",
    "wof:name": "CW12 1GB",
    "wof:placetype": "postalcode"
  },
  "geometry": {"coordinates":[-2.20088,53.17401],"type":"Point"}
}
