{
  "type": "Feature",
  "properties": {
    "iso:country":"GB",
    "wof:name":"G76 0PR",
    "wof:placetype":"postalcode"
},
  "geometry": {"coordinates":[-4.28698998984295,55.74370371046391],"type":"Point"}
}