{
  "type": "Feature",
  "properties": {
    "date:inception_lower":"1980-01-01",
    "date:inception_upper":"1980-01-31",
    "iso:country":"GB",
    "wof:name":"G76 0PR",
    "wof:placetype":"postalcode"
},
  "geometry": {"coordinates":[-4.28699,55.743704],"type":"Point"}
}