{
  "type": "Feature",
  "properties": {
    "date:inception_lower": "1980-01-01",
    "date:inception_upper": "1980-01-01",
    "iso:country": "GB",
    "wof:name": "WS14 9ED",
    "wof:placetype": "postalcode"
  },
  "geometry": {"coordinates":[-1.823589,52.675683],"type":"Point"}
}
