{
  "type": "Feature",
  "properties": {
    "iso:country": "GB",
    "wof:name": "LL28 4TU",
    "wof:placetype": "postalcode"
  },
  "geometry": {"coordinates":[-3.75162,53.307087],"type":"Point"}
}
