{
  "type": "Feature",
  "properties": {
    "date:inception_lower":"1980-01-01",
    "date:inception_upper":"1980-01-31",
    "iso:country":"GB",
    "wof:name":"G82 4DQ",
    "wof:placetype":"postalcode"
},
  "geometry": {"coordinates":[-4.581725,55.944555],"type":"Point"}
}