{
  "type": "Feature",
  "properties": {
    "iso:country":"GB",
    "wof:name":"E17 7JJ",
    "wof:placetype":"postalcode"
},
  "geometry": {"coordinates":[-0.01940363615409,51.58407914498068],"type":"Point"}
}