{
  "type": "Feature",
  "properties": {
    "date:inception_lower": "2020-12-01",
    "date:inception_upper": "2020-12-01",
    "iso:country": "GB",
    "wof:name": "NE29 6DB",
    "wof:placetype": "postalcode"
  },
  "geometry": {"coordinates":[-1.447384,55.007735],"type":"Point"}
}
