{
  "type": "Feature",
  "properties": {
    "iso:country": "GB",
    "wof:name": "BH22 9JT",
    "wof:placetype": "postalcode"
  },
  "geometry": {"coordinates":[-1.882322,50.808071],"type":"Point"}
}
