{
  "type": "Feature",
  "properties": {
    "iso:country":"GB",
    "wof:name":"TF2 6TG",
    "wof:placetype":"postalcode"
},
  "geometry": {"coordinates":[-2.45709978229019,52.69865572695115],"type":"Point"}
}