{
  "type": "Feature",
  "properties": {
    "date:inception_lower":"1987-04-01",
    "date:inception_upper":"1987-04-30",
    "iso:country":"GB",
    "wof:name":"TF2 6TG",
    "wof:placetype":"postalcode"
},
  "geometry": {"coordinates":[-2.4571,52.698656],"type":"Point"}
}