{
  "type": "Feature",
  "properties": {
    "date:inception_lower": "1980-01-01",
    "date:inception_upper": "1980-01-01",
    "iso:country": "GB",
    "wof:name": "GU10 2NA",
    "wof:placetype": "postalcode"
  },
  "geometry": {"coordinates":[-0.760624,51.136861],"type":"Point"}
}
