{
  "type": "Feature",
  "properties": {
    "iso:country": "GB",
    "wof:name": "DE24 3EU",
    "wof:placetype": "postalcode"
  },
  "geometry": {"coordinates":[-1.506053,52.877232],"type":"Point"}
}
