{
  "type": "Feature",
  "properties": {
    "date:inception_lower": "2014-02-01",
    "date:inception_upper": "2014-02-01",
    "iso:country": "GB",
    "wof:name": "DE24 3EU",
    "wof:placetype": "postalcode"
  },
  "geometry": {"coordinates":[-1.506053,52.877232],"type":"Point"}
}
