{
  "type": "Feature",
  "properties": {
    "iso:country": "GB",
    "wof:name": "RG9 5QS",
    "wof:placetype": "postalcode"
  },
  "geometry": {"coordinates":[-1.023389,51.549979],"type":"Point"}
}
