{
  "type": "Feature",
  "properties": {
    "iso:country":"GB",
    "wof:name":"OX2 9JX",
    "wof:placetype":"postalcode"
},
  "geometry": {"coordinates":[-1.29747169623295,51.75188939079753],"type":"Point"}
}