{
  "type": "Feature",
  "properties": {
    "iso:country": "GB",
    "wof:name": "OX2 9JX",
    "wof:placetype": "postalcode"
  },
  "geometry": {"coordinates":[-1.297472,51.751889],"type":"Point"}
}
