{
  "type": "Feature",
  "properties": {
    "iso:country":"GB",
    "wof:name":"NE40 3HL",
    "wof:placetype":"postalcode"
},
  "geometry": {"coordinates":[-1.75065072990451,54.97230505929121],"type":"Point"}
}