{
  "type": "Feature",
  "properties": {
    "date:inception_lower": "2024-01-01",
    "date:inception_upper": "2024-01-01",
    "iso:country": "GB",
    "wof:name": "HU18 1FG",
    "wof:placetype": "postalcode"
  },
  "geometry": {"coordinates":[-0.176951,53.899969],"type":"Point"}
}
