{
  "type": "Feature",
  "properties": {
    "iso:country": "GB",
    "wof:name": "NE23 1DP",
    "wof:placetype": "postalcode"
  },
  "geometry": {"coordinates":[-1.583406,55.08706],"type":"Point"}
}
