{
  "type": "Feature",
  "properties": {
    "iso:country":"GB",
    "wof:name":"NE23 1DP",
    "wof:placetype":"postalcode"
},
  "geometry": {"coordinates":[-1.58340573736787,55.0870595401101],"type":"Point"}
}