{
  "type": "Feature",
  "properties": {
    "iso:country": "GB",
    "wof:name": "BL2 2DR",
    "wof:placetype": "postalcode"
  },
  "geometry": {"coordinates":[-2.416486,53.587378],"type":"Point"}
}
