{
  "type": "Feature",
  "properties": {
    "iso:country":"GB",
    "wof:name":"L12 5HE",
    "wof:placetype":"postalcode"
},
  "geometry": {"coordinates":[-2.91022357851407,53.43806990983256],"type":"Point"}
}