{
  "type": "Feature",
  "properties": {
    "iso:country":"GB",
    "wof:name":"ML4 3PR",
    "wof:placetype":"postalcode"
},
  "geometry": {"coordinates":[-4.03124188460034,55.83220173718081],"type":"Point"}
}