{
  "type": "Feature",
  "properties": {
    "iso:country":"GB",
    "wof:name":"ML3 8LS",
    "wof:placetype":"postalcode"
},
  "geometry": {"coordinates":[-4.06831640425333,55.7689614647874],"type":"Point"}
}