{
  "type": "Feature",
  "properties": {
    "iso:country": "GB",
    "wof:name": "SY5 6SE",
    "wof:placetype": "postalcode"
  },
  "geometry": {"coordinates":[-2.585977,52.659466],"type":"Point"}
}
