{
  "type": "Feature",
  "properties": {
    "iso:country":"GB",
    "wof:name":"SY5 6SE",
    "wof:placetype":"postalcode"
},
  "geometry": {"coordinates":[-2.58598079102093,52.65945043663022],"type":"Point"}
}