{
  "type": "Feature",
  "properties": {
    "date:inception_lower":"1980-01-01",
    "date:inception_upper":"1980-01-31",
    "iso:country":"GB",
    "wof:name":"SY5 6SE",
    "wof:placetype":"postalcode"
},
  "geometry": {"coordinates":[-2.585977,52.659466],"type":"Point"}
}