{
  "type": "Feature",
  "properties": {
    "iso:country":"GB",
    "wof:name":"NE65 9JJ",
    "wof:placetype":"postalcode"
},
  "geometry": {"coordinates":[-1.73035225959741,55.34115326066866],"type":"Point"}
}