{
  "type": "Feature",
  "properties": {
    "iso:country": "GB",
    "wof:name": "LE11 1PX",
    "wof:placetype": "postalcode"
  },
  "geometry": {"coordinates":[-1.195588,52.771669],"type":"Point"}
}
