{
  "type": "Feature",
  "properties": {
    "iso:country": "GB",
    "wof:name": "SA17 4AD",
    "wof:placetype": "postalcode"
  },
  "geometry": {"coordinates":[-4.23704,51.720315],"type":"Point"}
}
