{
  "type": "Feature",
  "properties": {
    "iso:country":"GB",
    "wof:name":"SA17 4AD",
    "wof:placetype":"postalcode"
},
  "geometry": {"coordinates":[-4.2370405220058,51.72031459440953],"type":"Point"}
}