{
  "type": "Feature",
  "properties": {
    "iso:country":"GB",
    "wof:name":"NP44 8RP",
    "wof:placetype":"postalcode"
},
  "geometry": {"coordinates":[-3.00518645315985,51.64803820724904],"type":"Point"}
}