{
  "type": "Feature",
  "properties": {
    "iso:country": "GB",
    "wof:name": "NP44 8RP",
    "wof:placetype": "postalcode"
  },
  "geometry": {"coordinates":[-3.005186,51.648038],"type":"Point"}
}
