{
  "type": "Feature",
  "properties": {
    "date:inception_lower": "1980-06-01",
    "date:inception_upper": "1980-06-01",
    "iso:country": "GB",
    "wof:name": "KA8 0LF",
    "wof:placetype": "postalcode"
  },
  "geometry": {"coordinates":[-4.596042,55.471622],"type":"Point"}
}
