{
  "type": "Feature",
  "properties": {
    "date:inception_lower":"2008-01-01",
    "date:inception_upper":"2008-01-31",
    "iso:country":"GB",
    "wof:name":"CW3 0DL",
    "wof:placetype":"postalcode"
},
  "geometry": {"coordinates":[-2.509623,52.988155],"type":"Point"}
}