{
  "type": "Feature",
  "properties": {
    "iso:country":"GB",
    "wof:name":"CW3 0DL",
    "wof:placetype":"postalcode"
},
  "geometry": {"coordinates":[-2.50962296940337,52.9881550549567],"type":"Point"}
}