{
  "type": "Feature",
  "properties": {
    "date:inception_lower":"1980-01-01",
    "date:inception_upper":"1980-01-31",
    "iso:country":"GB",
    "wof:name":"LL11 3LX",
    "wof:placetype":"postalcode"
},
  "geometry": {"coordinates":[-3.076969,53.058973],"type":"Point"}
}