{
  "type": "Feature",
  "properties": {
    "iso:country":"GB",
    "wof:name":"LL11 3LX",
    "wof:placetype":"postalcode"
},
  "geometry": {"coordinates":[-3.07696951589978,53.05897275051452],"type":"Point"}
}