{
  "type": "Feature",
  "properties": {
    "iso:country":"GB",
    "wof:name":"BS35 2EQ",
    "wof:placetype":"postalcode"
},
  "geometry": {"coordinates":[-2.52000142045289,51.60751891592641],"type":"Point"}
}