{
  "type": "Feature",
  "properties": {
    "iso:country":"GB",
    "wof:name":"CR0 8EA",
    "wof:placetype":"postalcode"
},
  "geometry": {"coordinates":[-0.03060084750973,51.3769053679573],"type":"Point"}
}