{
  "type": "Feature",
  "properties": {
    "iso:country":"GB",
    "wof:name":"PR7 6PD",
    "wof:placetype":"postalcode"
},
  "geometry": {"coordinates":[-2.6678401108738,53.6619662132067],"type":"Point"}
}