{
  "type": "Feature",
  "properties": {
    "date:inception_lower": "1995-12-01",
    "date:inception_upper": "1995-12-01",
    "iso:country": "GB",
    "wof:name": "KW1 4YN",
    "wof:placetype": "postalcode"
  },
  "geometry": {"coordinates":[-3.122834,58.633325],"type":"Point"}
}
