{
  "type": "Feature",
  "properties": {
    "iso:country":"GB",
    "wof:name":"KW1 4YN",
    "wof:placetype":"postalcode"
},
  "geometry": {"coordinates":[-3.12236848153029,58.63349420534707],"type":"Point"}
}