{
  "type": "Feature",
  "properties": {
    "iso:country": "GB",
    "wof:name": "KW1 4YN",
    "wof:placetype": "postalcode"
  },
  "geometry": {"coordinates":[-3.122374,58.633482],"type":"Point"}
}
