{
  "type": "Feature",
  "properties": {
    "iso:country": "GB",
    "wof:name": "DD8 3ED",
    "wof:placetype": "postalcode"
  },
  "geometry": {"coordinates":[-2.873775,56.65072],"type":"Point"}
}
