{
  "type": "Feature",
  "properties": {
    "date:inception_lower": "2014-05-01",
    "date:inception_upper": "2014-05-01",
    "iso:country": "GB",
    "wof:name": "E20 1AF",
    "wof:placetype": "postalcode"
  },
  "geometry": {"coordinates":[-0.006801,51.547473],"type":"Point"}
}
