{
  "type": "Feature",
  "properties": {
    "iso:country":"GB",
    "wof:name":"E20 1AF",
    "wof:placetype":"postalcode"
},
  "geometry": {"coordinates":[-0.00680152686552,51.5474727452894],"type":"Point"}
}