{
  "type": "Feature",
  "properties": {
    "iso:country":"GB",
    "wof:name":"WS9 9RQ",
    "wof:placetype":"postalcode"
},
  "geometry": {"coordinates":[-1.91637736696856,52.6304408763331],"type":"Point"}
}