{
  "type": "Feature",
  "properties": {
    "date:inception_lower": "1990-07-01",
    "date:inception_upper": "1990-07-01",
    "iso:country": "GB",
    "wof:name": "WS9 9RQ",
    "wof:placetype": "postalcode"
  },
  "geometry": {"coordinates":[-1.916377,52.630441],"type":"Point"}
}
