{
  "type": "Feature",
  "properties": {
    "date:inception_lower": "1980-01-01",
    "date:inception_upper": "1980-01-01",
    "iso:country": "GB",
    "wof:name": "EH48 1LU",
    "wof:placetype": "postalcode"
  },
  "geometry": {"coordinates":[-3.61332,55.900201],"type":"Point"}
}
