{
  "type": "Feature",
  "properties": {
    "iso:country": "GB",
    "wof:name": "EH48 1LU",
    "wof:placetype": "postalcode"
  },
  "geometry": {"coordinates":[-3.61332,55.900201],"type":"Point"}
}
