{
  "type": "Feature",
  "properties": {
    "iso:country": "GB",
    "wof:name": "ST6 8BT",
    "wof:placetype": "postalcode"
  },
  "geometry": {"coordinates":[-2.160065,53.060649],"type":"Point"}
}
