{
  "type": "Feature",
  "properties": {
    "iso:country":"GB",
    "wof:name":"ST6 8BT",
    "wof:placetype":"postalcode"
},
  "geometry": {"coordinates":[-2.16006480269386,53.06064879006542],"type":"Point"}
}