{
  "type": "Feature",
  "properties": {
    "iso:country": "GB",
    "wof:name": "NG16 2JJ",
    "wof:placetype": "postalcode"
  },
  "geometry": {"coordinates":[-1.262844,53.003595],"type":"Point"}
}
