{
  "type": "Feature",
  "properties": {
    "iso:country":"GB",
    "wof:name":"NG16 2JJ",
    "wof:placetype":"postalcode"
},
  "geometry": {"coordinates":[-1.26284446309107,53.00359521717564],"type":"Point"}
}