{
  "type": "Feature",
  "properties": {
    "date:inception_lower": "1980-01-01",
    "date:inception_upper": "1980-01-01",
    "iso:country": "GB",
    "wof:name": "CT6 7LF",
    "wof:placetype": "postalcode"
  },
  "geometry": {"coordinates":[1.117313,51.334601],"type":"Point"}
}
