{
  "type": "Feature",
  "properties": {
    "iso:country":"GB",
    "wof:name":"CT6 7LF",
    "wof:placetype":"postalcode"
},
  "geometry": {"coordinates":[1.11724247017441,51.33463409590944],"type":"Point"}
}