{
  "type": "Feature",
  "properties": {
    "iso:country": "GB",
    "wof:name": "ST5 8HB",
    "wof:placetype": "postalcode"
  },
  "geometry": {"coordinates":[-2.233299,53.035951],"type":"Point"}
}
