{
  "type": "Feature",
  "properties": {
    "iso:country": "GB",
    "wof:name": "S10 4AB",
    "wof:placetype": "postalcode"
  },
  "geometry": {"coordinates":[-1.566294,53.363873],"type":"Point"}
}
