{
  "type": "Feature",
  "properties": {
    "iso:country":"GB",
    "wof:name":"DN40 1QF",
    "wof:placetype":"postalcode"
},
  "geometry": {"coordinates":[-0.21248998567407,53.61580880362292],"type":"Point"}
}