{
  "type": "Feature",
  "properties": {
    "date:inception_lower": "1980-01-01",
    "date:inception_upper": "1980-01-01",
    "iso:country": "GB",
    "wof:name": "IP13 7SA",
    "wof:placetype": "postalcode"
  },
  "geometry": {"coordinates":[1.268875,52.221732],"type":"Point"}
}
