{
  "type": "Feature",
  "properties": {
    "iso:country":"GB",
    "wof:name":"M23 2YQ",
    "wof:placetype":"postalcode"
},
  "geometry": {"coordinates":[-2.27815047164845,53.38831749319208],"type":"Point"}
}