{
  "type": "Feature",
  "properties": {
    "date:inception_lower": "1998-12-01",
    "date:inception_upper": "1998-12-01",
    "iso:country": "GB",
    "wof:name": "S9 2LF",
    "wof:placetype": "postalcode"
  },
  "geometry": {"coordinates":[-1.421676,53.402506],"type":"Point"}
}
