{
  "type": "Feature",
  "properties": {
    "iso:country":"GB",
    "wof:name":"S9 2LF",
    "wof:placetype":"postalcode"
},
  "geometry": {"coordinates":[-1.42166111057567,53.4024785249856],"type":"Point"}
}