{
  "type": "Feature",
  "properties": {
    "date:inception_lower": "1986-01-01",
    "date:inception_upper": "1986-01-01",
    "iso:country": "GB",
    "wof:name": "SO41 8FH",
    "wof:placetype": "postalcode"
  },
  "geometry": {"coordinates":[-1.541573,50.749723],"type":"Point"}
}
