{
  "type": "Feature",
  "properties": {
    "iso:country":"GB",
    "wof:name":"SO41 8FH",
    "wof:placetype":"postalcode"
},
  "geometry": {"coordinates":[-1.54105684122966,50.7497299893512],"type":"Point"}
}