{
  "type": "Feature",
  "properties": {
    "iso:country":"GB",
    "wof:name":"B7 4NQ",
    "wof:placetype":"postalcode"
},
  "geometry": {"coordinates":[-1.8813871632107,52.48943241303425],"type":"Point"}
}