{
  "type": "Feature",
  "properties": {
    "date:inception_lower": "1980-01-01",
    "date:inception_upper": "1980-01-01",
    "iso:country": "GB",
    "wof:name": "BD16 1BS",
    "wof:placetype": "postalcode"
  },
  "geometry": {"coordinates":[-1.877149,53.842638],"type":"Point"}
}
