{
  "type": "Feature",
  "properties": {
    "iso:country":"GB",
    "wof:name":"BD16 1BS",
    "wof:placetype":"postalcode"
},
  "geometry": {"coordinates":[-1.87714882592461,53.84263791504085],"type":"Point"}
}