{
  "type": "Feature",
  "properties": {
    "iso:country": "GB",
    "wof:name": "EX39 1TB",
    "wof:placetype": "postalcode"
  },
  "geometry": {"coordinates":[-4.21265,51.04494],"type":"Point"}
}
