{
  "type": "Feature",
  "properties": {
    "iso:country":"GB",
    "wof:name":"EX39 1TB",
    "wof:placetype":"postalcode"
},
  "geometry": {"coordinates":[-4.21261057960696,51.04494423908258],"type":"Point"}
}