{
  "type": "Feature",
  "properties": {
    "date:inception_lower": "1990-02-01",
    "date:inception_upper": "1990-02-01",
    "iso:country": "GB",
    "wof:name": "EX39 1TB",
    "wof:placetype": "postalcode"
  },
  "geometry": {"coordinates":[-4.21265,51.04494],"type":"Point"}
}
