{
  "type": "Feature",
  "properties": {
    "iso:country":"GB",
    "wof:name":"NW3 5UP",
    "wof:placetype":"postalcode"
},
  "geometry": {"coordinates":[-0.17389814821617,51.55486867965283],"type":"Point"}
}