{
  "type": "Feature",
  "properties": {
    "iso:country":"GB",
    "wof:name":"UB7 7RB",
    "wof:placetype":"postalcode"
},
  "geometry": {"coordinates":[-0.47684523523678,51.5122263500829],"type":"Point"}
}