{
  "type": "Feature",
  "properties": {
    "date:inception_lower":"1980-01-01",
    "date:inception_upper":"1980-01-31",
    "iso:country":"GB",
    "wof:name":"AL7 4SN",
    "wof:placetype":"postalcode"
},
  "geometry": {"coordinates":[-0.205355,51.790608],"type":"Point"}
}