{
  "type": "Feature",
  "properties": {
    "date:inception_lower":"2016-07-01",
    "date:inception_upper":"2016-07-31",
    "iso:country":"GB",
    "wof:name":"NN14 2UJ",
    "wof:placetype":"postalcode"
},
  "geometry": {"coordinates":[-0.817354,52.444304],"type":"Point"}
}