{
  "type": "Feature",
  "properties": {
    "iso:country": "GB",
    "wof:name": "IV2 4RE",
    "wof:placetype": "postalcode"
  },
  "geometry": {"coordinates":[-4.240626,57.456443],"type":"Point"}
}
