{
  "type": "Feature",
  "properties": {
    "date:inception_lower":"1980-01-01",
    "date:inception_upper":"1980-01-31",
    "iso:country":"GB",
    "wof:name":"IV2 4RE",
    "wof:placetype":"postalcode"
},
  "geometry": {"coordinates":[-4.240626,57.456443],"type":"Point"}
}