{
  "type": "Feature",
  "properties": {
    "iso:country":"GB",
    "wof:name":"IV2 4RE",
    "wof:placetype":"postalcode"
},
  "geometry": {"coordinates":[-4.24062622968505,57.45644327281899],"type":"Point"}
}