{
  "type": "Feature",
  "properties": {
    "iso:country": "GB",
    "wof:name": "S72 0HN",
    "wof:placetype": "postalcode"
  },
  "geometry": {"coordinates":[-1.360942,53.545879],"type":"Point"}
}
