{
  "type": "Feature",
  "properties": {
    "iso:country": "GB",
    "wof:name": "SG18 8LW",
    "wof:placetype": "postalcode"
  },
  "geometry": {"coordinates":[-0.247558,52.093677],"type":"Point"}
}
