{
  "type": "Feature",
  "properties": {
    "iso:country": "GB",
    "wof:name": "G74 3PD",
    "wof:placetype": "postalcode"
  },
  "geometry": {"coordinates":[-4.136926,55.777287],"type":"Point"}
}
