{
  "type": "Feature",
  "properties": {
    "iso:country":"GB",
    "wof:name":"LE4 0DP",
    "wof:placetype":"postalcode"
},
  "geometry": {"coordinates":[-1.13780731444645,52.65611190849263],"type":"Point"}
}