{
  "type": "Feature",
  "properties": {
    "iso:country":"GB",
    "wof:name":"PO22 6QB",
    "wof:placetype":"postalcode"
},
  "geometry": {"coordinates":[-0.63353159919411,50.8007332852669],"type":"Point"}
}