{
  "type": "Feature",
  "properties": {
    "iso:country":"GB",
    "wof:name":"CM4 9AH",
    "wof:placetype":"postalcode"
},
  "geometry": {"coordinates":[0.37028715800563,51.66059728954676],"type":"Point"}
}