{
  "type": "Feature",
  "properties": {
    "iso:country":"GB",
    "wof:name":"WA8 4TP",
    "wof:placetype":"postalcode"
},
  "geometry": {"coordinates":[-2.77374101472312,53.37807029960024],"type":"Point"}
}