{
  "type": "Feature",
  "properties": {
    "iso:country":"GB",
    "wof:name":"LS12 1UW",
    "wof:placetype":"postalcode"
},
  "geometry": {"coordinates":[-1.58725639821292,53.79531692211721],"type":"Point"}
}