{
  "type": "Feature",
  "properties": {
    "date:inception_lower": "1980-01-01",
    "date:inception_upper": "1980-01-01",
    "iso:country": "GB",
    "wof:name": "WV10 9NG",
    "wof:placetype": "postalcode"
  },
  "geometry": {"coordinates":[-2.116666,52.604513],"type":"Point"}
}
