{
  "type": "Feature",
  "properties": {
    "iso:country":"GB",
    "wof:name":"MK10 9TN",
    "wof:placetype":"postalcode"
},
  "geometry": {"coordinates":[-0.71721581298035,52.03947993501044],"type":"Point"}
}