{
  "type": "Feature",
  "properties": {
    "iso:country": "GB",
    "wof:name": "MK10 9TN",
    "wof:placetype": "postalcode"
  },
  "geometry": {"coordinates":[-0.717437,52.039401],"type":"Point"}
}
