{
  "type": "Feature",
  "properties": {
    "iso:country":"GB",
    "wof:name":"S80 4RN",
    "wof:placetype":"postalcode"
},
  "geometry": {"coordinates":[-1.20877655500347,53.28371946329239],"type":"Point"}
}