{
  "type": "Feature",
  "properties": {
    "date:inception_lower": "1980-01-01",
    "date:inception_upper": "1980-01-01",
    "iso:country": "GB",
    "wof:name": "S80 4RN",
    "wof:placetype": "postalcode"
  },
  "geometry": {"coordinates":[-1.208777,53.283719],"type":"Point"}
}
