{
  "type": "Feature",
  "properties": {
    "iso:country":"GB",
    "wof:name":"BD9 4AG",
    "wof:placetype":"postalcode"
},
  "geometry": {"coordinates":[-1.78274834558629,53.81440807623801],"type":"Point"}
}