{
  "type": "Feature",
  "properties": {
    "date:inception_lower": "1980-01-01",
    "date:inception_upper": "1980-01-01",
    "iso:country": "GB",
    "wof:name": "PA8 6DA",
    "wof:placetype": "postalcode"
  },
  "geometry": {"coordinates":[-4.468929,55.908931],"type":"Point"}
}
