{
  "type": "Feature",
  "properties": {
    "date:inception_lower": "1980-01-01",
    "date:inception_upper": "1980-01-01",
    "iso:country": "GB",
    "wof:name": "EH41 3AB",
    "wof:placetype": "postalcode"
  },
  "geometry": {"coordinates":[-2.78155,55.954708],"type":"Point"}
}
