{
  "type": "Feature",
  "properties": {
    "iso:country":"GB",
    "wof:name":"EH15 2QG",
    "wof:placetype":"postalcode"
},
  "geometry": {"coordinates":[-3.10389063701947,55.94893477547754],"type":"Point"}
}