{
  "type": "Feature",
  "properties": {
    "iso:country":"GB",
    "wof:name":"AB56 5BS",
    "wof:placetype":"postalcode"
},
  "geometry": {"coordinates":[-3.01001943013996,57.65791659340743],"type":"Point"}
}