{
  "type": "Feature",
  "properties": {
    "iso:country":"GB",
    "wof:name":"DH9 7QU",
    "wof:placetype":"postalcode"
},
  "geometry": {"coordinates":[-1.70993461637894,54.8624739703695],"type":"Point"}
}