{
  "type": "Feature",
  "properties": {
    "iso:country": "GB",
    "wof:name": "DH9 7QU",
    "wof:placetype": "postalcode"
  },
  "geometry": {"coordinates":[-1.709935,54.862474],"type":"Point"}
}
