{
  "type": "Feature",
  "properties": {
    "iso:country": "GB",
    "wof:name": "WN2 2SR",
    "wof:placetype": "postalcode"
  },
  "geometry": {"coordinates":[-2.566416,53.553433],"type":"Point"}
}
