{
  "type": "Feature",
  "properties": {
    "date:inception_lower": "1980-01-01",
    "date:inception_upper": "1980-01-01",
    "iso:country": "GB",
    "wof:name": "WN2 2SR",
    "wof:placetype": "postalcode"
  },
  "geometry": {"coordinates":[-2.566416,53.553433],"type":"Point"}
}
