{
  "type": "Feature",
  "properties": {
    "iso:country":"GB",
    "wof:name":"CF47 8UL",
    "wof:placetype":"postalcode"
},
  "geometry": {"coordinates":[-3.37694717904961,51.74893959020427],"type":"Point"}
}