{
  "type": "Feature",
  "properties": {
    "date:inception_lower": "1985-10-01",
    "date:inception_upper": "1985-10-01",
    "iso:country": "GB",
    "wof:name": "SS12 9BD",
    "wof:placetype": "postalcode"
  },
  "geometry": {"coordinates":[0.527843,51.608612],"type":"Point"}
}
