{
  "type": "Feature",
  "properties": {
    "iso:country": "GB",
    "wof:name": "SL2 4AH",
    "wof:placetype": "postalcode"
  },
  "geometry": {"coordinates":[-0.592567,51.553803],"type":"Point"}
}
