{
  "type": "Feature",
  "properties": {
    "iso:country":"GB",
    "wof:name":"SL2 4AH",
    "wof:placetype":"postalcode"
},
  "geometry": {"coordinates":[-0.59256713013011,51.55380322356681],"type":"Point"}
}