{
  "type": "Feature",
  "properties": {
    "iso:country": "GB",
    "wof:name": "PA15 3LB",
    "wof:placetype": "postalcode"
  },
  "geometry": {"coordinates":[-4.744144,55.938085],"type":"Point"}
}
