{
  "type": "Feature",
  "properties": {
    "iso:country":"GB",
    "wof:name":"IP27 9LS",
    "wof:placetype":"postalcode"
},
  "geometry": {"coordinates":[0.52499126926036,52.41201710080293],"type":"Point"}
}