{
  "type": "Feature",
  "properties": {
    "date:inception_lower":"1997-06-01",
    "date:inception_upper":"1997-06-30",
    "iso:country":"GB",
    "wof:name":"IP27 9LS",
    "wof:placetype":"postalcode"
},
  "geometry": {"coordinates":[0.524991,52.412017],"type":"Point"}
}