{
  "type": "Feature",
  "properties": {
    "date:inception_lower": "1990-07-01",
    "date:inception_upper": "1990-07-01",
    "iso:country": "GB",
    "wof:name": "PL12 4TP",
    "wof:placetype": "postalcode"
  },
  "geometry": {"coordinates":[-4.241144,50.412687],"type":"Point"}
}
