{
  "type": "Feature",
  "properties": {
    "iso:country":"GB",
    "wof:name":"PL12 4TP",
    "wof:placetype":"postalcode"
},
  "geometry": {"coordinates":[-4.24114383849105,50.41268726152907],"type":"Point"}
}