{
  "type": "Feature",
  "properties": {
    "date:inception_lower": "2022-03-01",
    "date:inception_upper": "2022-03-01",
    "iso:country": "GB",
    "wof:name": "CM11 2FA",
    "wof:placetype": "postalcode"
  },
  "geometry": {"coordinates":[0.462484,51.595247],"type":"Point"}
}
