{
  "type": "Feature",
  "properties": {
    "iso:country": "GB",
    "wof:name": "WD25 7DN",
    "wof:placetype": "postalcode"
  },
  "geometry": {"coordinates":[-0.4064,51.693821],"type":"Point"}
}
