{
  "type": "Feature",
  "properties": {
    "iso:country": "GB",
    "wof:name": "M24 2FN",
    "wof:placetype": "postalcode"
  },
  "geometry": {"coordinates":[-2.170644,53.545548],"type":"Point"}
}
