{
  "type": "Feature",
  "properties": {
    "iso:country":"GB",
    "wof:name":"M24 2FN",
    "wof:placetype":"postalcode"
},
  "geometry": {"coordinates":[-2.17064433566987,53.54554829295581],"type":"Point"}
}