{
  "type": "Feature",
  "properties": {
    "date:inception_lower": "2018-10-01",
    "date:inception_upper": "2018-10-01",
    "iso:country": "GB",
    "wof:name": "PL21 0FY",
    "wof:placetype": "postalcode"
  },
  "geometry": {"coordinates":[-3.891399,50.351718],"type":"Point"}
}
