{
  "type": "Feature",
  "properties": {
    "date:inception_lower": "1980-01-01",
    "date:inception_upper": "1980-01-01",
    "iso:country": "GB",
    "wof:name": "ML5 4NB",
    "wof:placetype": "postalcode"
  },
  "geometry": {"coordinates":[-4.016284,55.843691],"type":"Point"}
}
