{
  "type": "Feature",
  "properties": {
    "iso:country":"GB",
    "wof:name":"ML5 4NB",
    "wof:placetype":"postalcode"
},
  "geometry": {"coordinates":[-4.01628377752074,55.84369060045445],"type":"Point"}
}