{
  "type": "Feature",
  "properties": {
    "iso:country":"GB",
    "wof:name":"RM16 2JB",
    "wof:placetype":"postalcode"
},
  "geometry": {"coordinates":[0.32757736320158,51.49800356756555],"type":"Point"}
}