{
  "type": "Feature",
  "properties": {
    "date:inception_lower": "1984-02-01",
    "date:inception_upper": "1984-02-01",
    "iso:country": "GB",
    "wof:name": "WA11 0TX",
    "wof:placetype": "postalcode"
  },
  "geometry": {"coordinates":[-2.699901,53.462301],"type":"Point"}
}
