{
  "type": "Feature",
  "properties": {
    "iso:country":"GB",
    "wof:name":"WA11 0TX",
    "wof:placetype":"postalcode"
},
  "geometry": {"coordinates":[-2.69990135837664,53.46230107200099],"type":"Point"}
}