{
  "type": "Feature",
  "properties": {
    "iso:country": "GB",
    "wof:name": "WA2 8TL",
    "wof:placetype": "postalcode"
  },
  "geometry": {"coordinates":[-2.604636,53.415838],"type":"Point"}
}
