{
  "type": "Feature",
  "properties": {
    "iso:country":"GB",
    "wof:name":"WA2 8TL",
    "wof:placetype":"postalcode"
},
  "geometry": {"coordinates":[-2.60463640413681,53.41583768005818],"type":"Point"}
}