{
  "type": "Feature",
  "properties": {
    "iso:country":"GB",
    "wof:name":"RM8 3SL",
    "wof:placetype":"postalcode"
},
  "geometry": {"coordinates":[0.12913860451605,51.55367233689186],"type":"Point"}
}