{
  "type": "Feature",
  "properties": {
    "iso:country":"GB",
    "wof:name":"BH13 7JX",
    "wof:placetype":"postalcode"
},
  "geometry": {"coordinates":[-1.92254317641904,50.70479780459285],"type":"Point"}
}