{
  "type": "Feature",
  "properties": {
    "iso:country":"GB",
    "wof:name":"GL54 5RW",
    "wof:placetype":"postalcode"
},
  "geometry": {"coordinates":[-1.87068043292857,51.94907343056528],"type":"Point"}
}