{
  "type": "Feature",
  "properties": {
    "iso:country":"GB",
    "wof:name":"WN5 9PG",
    "wof:placetype":"postalcode"
},
  "geometry": {"coordinates":[-2.66165440378726,53.53848155080628],"type":"Point"}
}