{
  "type": "Feature",
  "properties": {
    "iso:country":"GB",
    "wof:name":"DT9 5DJ",
    "wof:placetype":"postalcode"
},
  "geometry": {"coordinates":[-2.4609885076572,50.96524347433335],"type":"Point"}
}