{
  "type": "Feature",
  "properties": {
    "iso:country":"GB",
    "wof:name":"B23 7DE",
    "wof:placetype":"postalcode"
},
  "geometry": {"coordinates":[-1.85973566759192,52.52729230534195],"type":"Point"}
}