{
  "type": "Feature",
  "properties": {
    "date:inception_lower": "2018-12-01",
    "date:inception_upper": "2018-12-01",
    "iso:country": "GB",
    "wof:name": "G4 0EL",
    "wof:placetype": "postalcode"
  },
  "geometry": {"coordinates":[-4.243326,55.864721],"type":"Point"}
}
