{
  "type": "Feature",
  "properties": {
    "iso:country": "GB",
    "wof:name": "G4 0EL",
    "wof:placetype": "postalcode"
  },
  "geometry": {"coordinates":[-4.238152,55.867026],"type":"Point"}
}
