{
  "type": "Feature",
  "properties": {
    "iso:country":"GB",
    "wof:name":"KY7 4JW",
    "wof:placetype":"postalcode"
},
  "geometry": {"coordinates":[-3.16997039741669,56.19094549643859],"type":"Point"}
}