{
  "type": "Feature",
  "properties": {
    "iso:country": "GB",
    "wof:name": "AB45 3QL",
    "wof:placetype": "postalcode"
  },
  "geometry": {"coordinates":[-2.501186,57.660669],"type":"Point"}
}
