{
  "type": "Feature",
  "properties": {
    "iso:country":"GB",
    "wof:name":"AB45 3QL",
    "wof:placetype":"postalcode"
},
  "geometry": {"coordinates":[-2.50118645387954,57.66066913895396],"type":"Point"}
}