{
  "type": "Feature",
  "properties": {
    "date:inception_lower": "2001-06-01",
    "date:inception_upper": "2001-06-01",
    "iso:country": "GB",
    "wof:name": "E8 3EZ",
    "wof:placetype": "postalcode"
  },
  "geometry": {"coordinates":[-0.065284,51.545161],"type":"Point"}
}
