{
  "type": "Feature",
  "properties": {
    "iso:country":"GB",
    "wof:name":"G12 0FG",
    "wof:placetype":"postalcode"
},
  "geometry": {"coordinates":[-4.31768900645759,55.88992356704529],"type":"Point"}
}