{
  "type": "Feature",
  "properties": {
    "iso:country":"GB",
    "wof:name":"TN14 5SA",
    "wof:placetype":"postalcode"
},
  "geometry": {"coordinates":[0.20747503131681,51.31267654574182],"type":"Point"}
}