{
  "type": "Feature",
  "properties": {
    "iso:country":"GB",
    "wof:name":"BS22 8RE",
    "wof:placetype":"postalcode"
},
  "geometry": {"coordinates":[-2.93325198455048,51.3540360494322],"type":"Point"}
}