{
  "type": "Feature",
  "properties": {
    "iso:country": "GB",
    "wof:name": "CM2 9HJ",
    "wof:placetype": "postalcode"
  },
  "geometry": {"coordinates":[0.46931,51.716157],"type":"Point"}
}
