{
  "type": "Feature",
  "properties": {
    "date:inception_lower":"1980-01-01",
    "date:inception_upper":"1980-01-31",
    "iso:country":"GB",
    "wof:name":"CM2 9HJ",
    "wof:placetype":"postalcode"
},
  "geometry": {"coordinates":[0.46931,51.716157],"type":"Point"}
}