{
  "type": "Feature",
  "properties": {
    "iso:country":"GB",
    "wof:name":"CM2 9HJ",
    "wof:placetype":"postalcode"
},
  "geometry": {"coordinates":[0.46930951279444,51.71615706521667],"type":"Point"}
}