{
  "type": "Feature",
  "properties": {
    "iso:country": "GB",
    "wof:name": "DT6 4PA",
    "wof:placetype": "postalcode"
  },
  "geometry": {"coordinates":[-2.704083,50.732137],"type":"Point"}
}
