{
  "type": "Feature",
  "properties": {
    "iso:country":"GB",
    "wof:name":"DT6 4PA",
    "wof:placetype":"postalcode"
},
  "geometry": {"coordinates":[-2.70443062491772,50.73266660422317],"type":"Point"}
}