{
  "type": "Feature",
  "properties": {
    "iso:country": "GB",
    "wof:name": "WV9 5YX",
    "wof:placetype": "postalcode"
  },
  "geometry": {"coordinates":[-2.114955,52.588468],"type":"Point"}
}
