{
  "type": "Feature",
  "properties": {
    "iso:country":"GB",
    "wof:name":"HU17 9AL",
    "wof:placetype":"postalcode"
},
  "geometry": {"coordinates":[-0.42361888951104,53.84549835119424],"type":"Point"}
}