{
  "type": "Feature",
  "properties": {
    "date:inception_lower": "2007-05-01",
    "date:inception_upper": "2007-05-01",
    "iso:country": "GB",
    "wof:name": "HU17 9AL",
    "wof:placetype": "postalcode"
  },
  "geometry": {"coordinates":[-0.423619,53.845498],"type":"Point"}
}
