{
  "type": "Feature",
  "properties": {
    "iso:country":"GB",
    "wof:name":"WS13 6NJ",
    "wof:placetype":"postalcode"
},
  "geometry": {"coordinates":[-1.83716488182982,52.67592747259338],"type":"Point"}
}