{
  "type": "Feature",
  "properties": {
    "iso:country": "GB",
    "wof:name": "WS13 6NJ",
    "wof:placetype": "postalcode"
  },
  "geometry": {"coordinates":[-1.837165,52.675927],"type":"Point"}
}
