{
  "type": "Feature",
  "properties": {
    "date:inception_lower": "1980-01-01",
    "date:inception_upper": "1980-01-01",
    "iso:country": "GB",
    "wof:name": "LA8 8AW",
    "wof:placetype": "postalcode"
  },
  "geometry": {"coordinates":[-2.799367,54.29908],"type":"Point"}
}
