{
  "type": "Feature",
  "properties": {
    "iso:country":"GB",
    "wof:name":"LA8 8AW",
    "wof:placetype":"postalcode"
},
  "geometry": {"coordinates":[-2.79939560569775,54.29902579267289],"type":"Point"}
}