{
  "type": "Feature",
  "properties": {
    "iso:country":"GB",
    "wof:name":"TQ12 6DX",
    "wof:placetype":"postalcode"
},
  "geometry": {"coordinates":[-3.67281309948687,50.5086635483059],"type":"Point"}
}