{
  "type": "Feature",
  "properties": {
    "iso:country": "GB",
    "wof:name": "PE19 5HR",
    "wof:placetype": "postalcode"
  },
  "geometry": {"coordinates":[-0.307504,52.23327],"type":"Point"}
}
