{
  "type": "Feature",
  "properties": {
    "date:inception_lower": "2000-06-01",
    "date:inception_upper": "2000-06-01",
    "iso:country": "GB",
    "wof:name": "PE19 5HR",
    "wof:placetype": "postalcode"
  },
  "geometry": {"coordinates":[-0.307439,52.233292],"type":"Point"}
}
