{
  "type": "Feature",
  "properties": {
    "iso:country":"GB",
    "wof:name":"PE19 5HR",
    "wof:placetype":"postalcode"
},
  "geometry": {"coordinates":[-0.30750423527628,52.23327012215166],"type":"Point"}
}