{
  "type": "Feature",
  "properties": {
    "date:inception_lower":"1996-12-01",
    "date:inception_upper":"1996-12-31",
    "iso:country":"GB",
    "wof:name":"LE17 5FD",
    "wof:placetype":"postalcode"
},
  "geometry": {"coordinates":[-1.276135,52.494903],"type":"Point"}
}