{
  "type": "Feature",
  "properties": {
    "iso:country":"GB",
    "wof:name":"LE17 5FD",
    "wof:placetype":"postalcode"
},
  "geometry": {"coordinates":[-1.27613509393465,52.49490264289367],"type":"Point"}
}