{
  "type": "Feature",
  "properties": {
    "iso:country": "GB",
    "wof:name": "M18 8QZ",
    "wof:placetype": "postalcode"
  },
  "geometry": {"coordinates":[-2.155355,53.466714],"type":"Point"}
}
