{
  "type": "Feature",
  "properties": {
    "iso:country":"GB",
    "wof:name":"TS3 8NP",
    "wof:placetype":"postalcode"
},
  "geometry": {"coordinates":[-1.19073301726277,54.56112282250066],"type":"Point"}
}