{
  "type": "Feature",
  "properties": {
    "iso:country":"GB",
    "wof:name":"SL2 3PY",
    "wof:placetype":"postalcode"
},
  "geometry": {"coordinates":[-0.61555847107255,51.55715196812657],"type":"Point"}
}