{
  "type": "Feature",
  "properties": {
    "date:inception_lower": "1996-06-01",
    "date:inception_upper": "1996-06-01",
    "iso:country": "GB",
    "wof:name": "AB12 4TT",
    "wof:placetype": "postalcode"
  },
  "geometry": {"coordinates":[-2.143055,57.054161],"type":"Point"}
}
