{
  "type": "Feature",
  "properties": {
    "iso:country":"GB",
    "wof:name":"AB12 4TT",
    "wof:placetype":"postalcode"
},
  "geometry": {"coordinates":[-2.14305518571368,57.0541612709538],"type":"Point"}
}