{
  "type": "Feature",
  "properties": {
    "date:inception_lower":"2002-10-01",
    "date:inception_upper":"2002-10-31",
    "iso:country":"GB",
    "wof:name":"LE18 2FR",
    "wof:placetype":"postalcode"
},
  "geometry": {"coordinates":[-1.11121,52.581038],"type":"Point"}
}