{
  "type": "Feature",
  "properties": {
    "iso:country":"GB",
    "wof:name":"CA2 5RF",
    "wof:placetype":"postalcode"
},
  "geometry": {"coordinates":[-2.95554554664753,54.88920937655957],"type":"Point"}
}