{
  "type": "Feature",
  "properties": {
    "date:inception_lower": "1980-01-01",
    "date:inception_upper": "1980-01-01",
    "iso:country": "GB",
    "wof:name": "BA2 7DB",
    "wof:placetype": "postalcode"
  },
  "geometry": {"coordinates":[-2.337305,51.352171],"type":"Point"}
}
