{
  "type": "Feature",
  "properties": {
    "iso:country":"GB",
    "wof:name":"BA2 7DB",
    "wof:placetype":"postalcode"
},
  "geometry": {"coordinates":[-2.33730469809562,51.35217056824811],"type":"Point"}
}