{
  "type": "Feature",
  "properties": {
    "iso:country": "GB",
    "wof:name": "BA2 7DB",
    "wof:placetype": "postalcode"
  },
  "geometry": {"coordinates":[-2.337305,51.352171],"type":"Point"}
}
