{
  "type": "Feature",
  "properties": {
    "date:inception_lower": "2000-06-01",
    "date:inception_upper": "2000-06-01",
    "iso:country": "GB",
    "wof:name": "CO16 7JF",
    "wof:placetype": "postalcode"
  },
  "geometry": {"coordinates":[1.137566,51.800829],"type":"Point"}
}
