{
  "type": "Feature",
  "properties": {
    "iso:country":"GB",
    "wof:name":"TN35 5JX",
    "wof:placetype":"postalcode"
},
  "geometry": {"coordinates":[0.60447679029447,50.86573291880154],"type":"Point"}
}