{
  "type": "Feature",
  "properties": {
    "iso:country": "GB",
    "wof:name": "TN35 5JX",
    "wof:placetype": "postalcode"
  },
  "geometry": {"coordinates":[0.604477,50.865733],"type":"Point"}
}
