{
  "type": "Feature",
  "properties": {
    "iso:country": "GB",
    "wof:name": "YO25 9AQ",
    "wof:placetype": "postalcode"
  },
  "geometry": {"coordinates":[-0.44421,53.932914],"type":"Point"}
}
