{
  "type": "Feature",
  "properties": {
    "iso:country": "GB",
    "wof:name": "GU51 3EA",
    "wof:placetype": "postalcode"
  },
  "geometry": {"coordinates":[-0.822626,51.281847],"type":"Point"}
}
