{
  "type": "Feature",
  "properties": {
    "date:inception_lower":"1980-01-01",
    "date:inception_upper":"1980-01-31",
    "iso:country":"GB",
    "wof:name":"ST13 8BX",
    "wof:placetype":"postalcode"
},
  "geometry": {"coordinates":[-2.035432,53.103216],"type":"Point"}
}