{
  "type": "Feature",
  "properties": {
    "date:inception_lower": "2021-05-01",
    "date:inception_upper": "2021-05-01",
    "iso:country": "GB",
    "wof:name": "TQ7 2FF",
    "wof:placetype": "postalcode"
  },
  "geometry": {"coordinates":[-3.675846,50.255917],"type":"Point"}
}
