{
  "type": "Feature",
  "properties": {
    "iso:country":"GB",
    "wof:name":"W1G 9RQ",
    "wof:placetype":"postalcode"
},
  "geometry": {"coordinates":[-0.14789878403244,51.51698953783774],"type":"Point"}
}