{
  "type": "Feature",
  "properties": {
    "iso:country":"GB",
    "wof:name":"HD9 6AG",
    "wof:placetype":"postalcode"
},
  "geometry": {"coordinates":[-1.79193628254156,53.60238589063717],"type":"Point"}
}