{
  "type": "Feature",
  "properties": {
    "iso:country": "GB",
    "wof:name": "WV13 3HX",
    "wof:placetype": "postalcode"
  },
  "geometry": {"coordinates":[-2.06208,52.575544],"type":"Point"}
}
