{
  "type": "Feature",
  "properties": {
    "iso:country":"GB",
    "wof:name":"WV13 3HX",
    "wof:placetype":"postalcode"
},
  "geometry": {"coordinates":[-2.06207980965749,52.57554427502563],"type":"Point"}
}