{
  "type": "Feature",
  "properties": {
    "iso:country":"GB",
    "wof:name":"IP14 5NQ",
    "wof:placetype":"postalcode"
},
  "geometry": {"coordinates":[1.10200724728034,52.24044898199067],"type":"Point"}
}