{
  "type": "Feature",
  "properties": {
    "date:inception_lower": "1980-01-01",
    "date:inception_upper": "1980-01-01",
    "iso:country": "GB",
    "wof:name": "IP14 5NQ",
    "wof:placetype": "postalcode"
  },
  "geometry": {"coordinates":[1.102168,52.24004],"type":"Point"}
}
