{
  "type": "Feature",
  "properties": {
    "iso:country":"GB",
    "wof:name":"PR1 9RZ",
    "wof:placetype":"postalcode"
},
  "geometry": {"coordinates":[-2.70004953700749,53.73532449205414],"type":"Point"}
}