{
  "type": "Feature",
  "properties": {
    "iso:country": "GB",
    "wof:name": "PR1 9RZ",
    "wof:placetype": "postalcode"
  },
  "geometry": {"coordinates":[-2.700425,53.735338],"type":"Point"}
}
