{
  "type": "Feature",
  "properties": {
    "iso:country": "GB",
    "wof:name": "RH8 0BX",
    "wof:placetype": "postalcode"
  },
  "geometry": {"coordinates":[0.003936,51.259563],"type":"Point"}
}
