{
  "type": "Feature",
  "properties": {
    "iso:country":"GB",
    "wof:name":"LL31 9AH",
    "wof:placetype":"postalcode"
},
  "geometry": {"coordinates":[-3.80749600306934,53.29103272473628],"type":"Point"}
}