{
  "type": "Feature",
  "properties": {
    "iso:country": "GB",
    "wof:name": "LL31 9AH",
    "wof:placetype": "postalcode"
  },
  "geometry": {"coordinates":[-3.807496,53.291033],"type":"Point"}
}
