{
  "type": "Feature",
  "properties": {
    "date:inception_lower":"2010-01-01",
    "date:inception_upper":"2010-01-31",
    "iso:country":"GB",
    "wof:name":"LL31 9AH",
    "wof:placetype":"postalcode"
},
  "geometry": {"coordinates":[-3.807496,53.291033],"type":"Point"}
}