{
  "type": "Feature",
  "properties": {
    "date:inception_lower": "1980-01-01",
    "date:inception_upper": "1980-01-01",
    "iso:country": "GB",
    "wof:name": "WA15 9AB",
    "wof:placetype": "postalcode"
  },
  "geometry": {"coordinates":[-2.347023,53.380218],"type":"Point"}
}
