{
  "type": "Feature",
  "properties": {
    "date:inception_lower": "1980-01-01",
    "date:inception_upper": "1980-01-01",
    "iso:country": "GB",
    "wof:name": "EX36 3NN",
    "wof:placetype": "postalcode"
  },
  "geometry": {"coordinates":[-3.728815,51.026932],"type":"Point"}
}
