{
  "type": "Feature",
  "properties": {
    "iso:country":"GB",
    "wof:name":"EX36 3NN",
    "wof:placetype":"postalcode"
},
  "geometry": {"coordinates":[-3.72543980585371,51.0310056863124],"type":"Point"}
}