{
  "type": "Feature",
  "properties": {
    "iso:country":"GB",
    "wof:name":"CR7 7BB",
    "wof:placetype":"postalcode"
},
  "geometry": {"coordinates":[-0.10314784739406,51.39610586192492],"type":"Point"}
}