{
  "type": "Feature",
  "properties": {
    "iso:country":"GB",
    "wof:name":"PO6 2SA",
    "wof:placetype":"postalcode"
},
  "geometry": {"coordinates":[-1.06222173622489,50.83736713109236],"type":"Point"}
}