{
  "type": "Feature",
  "properties": {
    "iso:country": "GB",
    "wof:name": "PO6 2SA",
    "wof:placetype": "postalcode"
  },
  "geometry": {"coordinates":[-1.062222,50.837367],"type":"Point"}
}
