{
  "type": "Feature",
  "properties": {
    "iso:country": "GB",
    "wof:name": "PL28 8ER",
    "wof:placetype": "postalcode"
  },
  "geometry": {"coordinates":[-4.944443,50.537922],"type":"Point"}
}
