{
  "type": "Feature",
  "properties": {
    "iso:country": "GB",
    "wof:name": "M11 4LJ",
    "wof:placetype": "postalcode"
  },
  "geometry": {"coordinates":[-2.173103,53.486408],"type":"Point"}
}
