{
  "type": "Feature",
  "properties": {
    "iso:country":"GB",
    "wof:name":"M11 4LJ",
    "wof:placetype":"postalcode"
},
  "geometry": {"coordinates":[-2.17307332140424,53.48624836635437],"type":"Point"}
}