{
  "type": "Feature",
  "properties": {
    "date:inception_lower":"1980-01-01",
    "date:inception_upper":"1980-01-31",
    "iso:country":"GB",
    "wof:name":"LL65 4SB",
    "wof:placetype":"postalcode"
},
  "geometry": {"coordinates":[-4.409979,53.255011],"type":"Point"}
}