{
  "type": "Feature",
  "properties": {
    "iso:country":"GB",
    "wof:name":"LL65 4SB",
    "wof:placetype":"postalcode"
},
  "geometry": {"coordinates":[-4.40997905311863,53.25501074123546],"type":"Point"}
}