{
  "type": "Feature",
  "properties": {
    "iso:country":"GB",
    "wof:name":"NR24 2LR",
    "wof:placetype":"postalcode"
},
  "geometry": {"coordinates":[1.05523553977373,52.83537322351251],"type":"Point"}
}