{
  "type": "Feature",
  "properties": {
    "date:inception_lower":"1980-01-01",
    "date:inception_upper":"1980-01-31",
    "iso:country":"GB",
    "wof:name":"NR24 2LR",
    "wof:placetype":"postalcode"
},
  "geometry": {"coordinates":[1.055239,52.835381],"type":"Point"}
}