{
  "type": "Feature",
  "properties": {
    "iso:country": "GB",
    "wof:name": "RM16 3AP",
    "wof:placetype": "postalcode"
  },
  "geometry": {"coordinates":[0.358435,51.496236],"type":"Point"}
}
