{
  "type": "Feature",
  "properties": {
    "iso:country":"GB",
    "wof:name":"RM16 3AP",
    "wof:placetype":"postalcode"
},
  "geometry": {"coordinates":[0.35843495797456,51.49623579182123],"type":"Point"}
}