{
  "type": "Feature",
  "properties": {
    "iso:country":"GB",
    "wof:name":"CH5 1JB",
    "wof:placetype":"postalcode"
},
  "geometry": {"coordinates":[-3.0421392739121,53.21196752166303],"type":"Point"}
}