{
  "type": "Feature",
  "properties": {
    "iso:country":"GB",
    "wof:name":"HP23 6HE",
    "wof:placetype":"postalcode"
},
  "geometry": {"coordinates":[-0.63623972991917,51.78315989174997],"type":"Point"}
}