{
  "type": "Feature",
  "properties": {
    "date:inception_lower": "1997-06-01",
    "date:inception_upper": "1997-06-01",
    "iso:country": "GB",
    "wof:name": "NE65 0XF",
    "wof:placetype": "postalcode"
  },
  "geometry": {"coordinates":[-1.615526,55.350778],"type":"Point"}
}
