{
  "type": "Feature",
  "properties": {
    "iso:country": "GB",
    "wof:name": "NE65 0XF",
    "wof:placetype": "postalcode"
  },
  "geometry": {"coordinates":[-1.614738,55.350766],"type":"Point"}
}
