{
  "type": "Feature",
  "properties": {
    "iso:country": "GB",
    "wof:name": "HD5 9QJ",
    "wof:placetype": "postalcode"
  },
  "geometry": {"coordinates":[-1.754799,53.650798],"type":"Point"}
}
