{
  "type": "Feature",
  "properties": {
    "iso:country":"GB",
    "wof:name":"HU12 0DE",
    "wof:placetype":"postalcode"
},
  "geometry": {"coordinates":[-0.07447090906575,53.72967907029707],"type":"Point"}
}