{
  "type": "Feature",
  "properties": {
    "date:inception_lower":"1980-01-01",
    "date:inception_upper":"1980-01-31",
    "iso:country":"GB",
    "wof:name":"HU12 0DE",
    "wof:placetype":"postalcode"
},
  "geometry": {"coordinates":[-0.074471,53.729679],"type":"Point"}
}