{
  "type": "Feature",
  "properties": {
    "iso:country": "GB",
    "wof:name": "HU12 0DE",
    "wof:placetype": "postalcode"
  },
  "geometry": {"coordinates":[-0.074471,53.729679],"type":"Point"}
}
