{
  "type": "Feature",
  "properties": {
    "iso:country":"GB",
    "wof:name":"N1 5ED",
    "wof:placetype":"postalcode"
},
  "geometry": {"coordinates":[-0.08820375486937,51.53580633596029],"type":"Point"}
}