{
  "type": "Feature",
  "properties": {
    "iso:country":"GB",
    "wof:name":"RG27 9TU",
    "wof:placetype":"postalcode"
},
  "geometry": {"coordinates":[-0.97127053840071,51.28257238334135],"type":"Point"}
}