{
  "type": "Feature",
  "properties": {
    "iso:country": "GB",
    "wof:name": "RG27 9TU",
    "wof:placetype": "postalcode"
  },
  "geometry": {"coordinates":[-0.97127,51.282572],"type":"Point"}
}
