{
  "type": "Feature",
  "properties": {
    "iso:country":"GB",
    "wof:name":"EH39 4NR",
    "wof:placetype":"postalcode"
},
  "geometry": {"coordinates":[-2.72508871042049,56.05443549060499],"type":"Point"}
}