{
  "type": "Feature",
  "properties": {
    "iso:country":"GB",
    "wof:name":"BH23 4RG",
    "wof:placetype":"postalcode"
},
  "geometry": {"coordinates":[-1.71291323620014,50.74705090958306],"type":"Point"}
}