{
  "type": "Feature",
  "properties": {
    "date:inception_lower": "1980-01-01",
    "date:inception_upper": "1980-01-01",
    "iso:country": "GB",
    "wof:name": "AL1 2PD",
    "wof:placetype": "postalcode"
  },
  "geometry": {"coordinates":[-0.344627,51.73834],"type":"Point"}
}
