{
  "type": "Feature",
  "properties": {
    "iso:country":"GB",
    "wof:name":"CF35 6TP",
    "wof:placetype":"postalcode"
},
  "geometry": {"coordinates":[-3.51183123152429,51.52614195371753],"type":"Point"}
}