{
  "type": "Feature",
  "properties": {
    "iso:country":"GB",
    "wof:name":"NR1 4AR",
    "wof:placetype":"postalcode"
},
  "geometry": {"coordinates":[1.31530715555538,52.63032303433076],"type":"Point"}
}