{
  "type": "Feature",
  "properties": {
    "date:inception_lower":"1980-01-01",
    "date:inception_upper":"1980-01-31",
    "iso:country":"GB",
    "wof:name":"NR1 4AR",
    "wof:placetype":"postalcode"
},
  "geometry": {"coordinates":[1.315307,52.630323],"type":"Point"}
}