{
  "type": "Feature",
  "properties": {
    "iso:country":"GB",
    "wof:name":"E10 7QP",
    "wof:placetype":"postalcode"
},
  "geometry": {"coordinates":[-0.04324864053707,51.57099936006524],"type":"Point"}
}