{
  "type": "Feature",
  "properties": {
    "iso:country": "GB",
    "wof:name": "E9 6ET",
    "wof:placetype": "postalcode"
  },
  "geometry": {"coordinates":[-0.049345,51.549267],"type":"Point"}
}
