{
  "type": "Feature",
  "properties": {
    "iso:country": "GB",
    "wof:name": "NR32 3QW",
    "wof:placetype": "postalcode"
  },
  "geometry": {"coordinates":[1.714705,52.492209],"type":"Point"}
}
