{
  "type": "Feature",
  "properties": {
    "iso:country":"GB",
    "wof:name":"IG8 0AL",
    "wof:placetype":"postalcode"
},
  "geometry": {"coordinates":[0.03261024291956,51.6061928134414],"type":"Point"}
}