{
  "type": "Feature",
  "properties": {
    "date:inception_lower": "2018-09-01",
    "date:inception_upper": "2018-09-01",
    "iso:country": "GB",
    "wof:name": "SG9 0FB",
    "wof:placetype": "postalcode"
  },
  "geometry": {"coordinates":[0.002561,51.946817],"type":"Point"}
}
