{
  "type": "Feature",
  "properties": {
    "date:inception_lower":"1994-02-01",
    "date:inception_upper":"1994-02-28",
    "iso:country":"GB",
    "wof:name":"IV51 9RA",
    "wof:placetype":"postalcode"
},
  "geometry": {"coordinates":[-5.975768,57.551005],"type":"Point"}
}