{
  "type": "Feature",
  "properties": {
    "iso:country": "GB",
    "wof:name": "IV51 9RA",
    "wof:placetype": "postalcode"
  },
  "geometry": {"coordinates":[-5.975768,57.551005],"type":"Point"}
}
