{
  "type": "Feature",
  "properties": {
    "date:inception_lower": "2022-02-01",
    "date:inception_upper": "2022-02-01",
    "iso:country": "GB",
    "wof:name": "YO11 3XH",
    "wof:placetype": "postalcode"
  },
  "geometry": {"coordinates":[-0.407216,54.245367],"type":"Point"}
}
