{
  "type": "Feature",
  "properties": {
    "iso:country": "GB",
    "wof:name": "WD5 0TR",
    "wof:placetype": "postalcode"
  },
  "geometry": {"coordinates":[-0.414838,51.702433],"type":"Point"}
}
