{
  "type": "Feature",
  "properties": {
    "date:inception_lower": "1990-02-01",
    "date:inception_upper": "1990-02-01",
    "iso:country": "GB",
    "wof:name": "WD5 0TR",
    "wof:placetype": "postalcode"
  },
  "geometry": {"coordinates":[-0.414838,51.702433],"type":"Point"}
}
