{
  "type": "Feature",
  "properties": {
    "date:inception_lower": "1980-01-01",
    "date:inception_upper": "1980-01-01",
    "iso:country": "GB",
    "wof:name": "OX5 2LJ",
    "wof:placetype": "postalcode"
  },
  "geometry": {"coordinates":[-1.2741,51.816349],"type":"Point"}
}
