{
  "type": "Feature",
  "properties": {
    "date:inception_lower":"2013-02-01",
    "date:inception_upper":"2013-02-28",
    "iso:country":"GB",
    "wof:name":"NE37 3HQ",
    "wof:placetype":"postalcode"
},
  "geometry": {"coordinates":[-1.498916,54.913935],"type":"Point"}
}