{
  "type": "Feature",
  "properties": {
    "iso:country": "GB",
    "wof:name": "NE37 3HQ",
    "wof:placetype": "postalcode"
  },
  "geometry": {"coordinates":[-1.498916,54.913935],"type":"Point"}
}
