{
  "type": "Feature",
  "properties": {
    "iso:country":"GB",
    "wof:name":"CF14 2FJ",
    "wof:placetype":"postalcode"
},
  "geometry": {"coordinates":[-3.22946184817652,51.50573929324383],"type":"Point"}
}