{
  "type": "Feature",
  "properties": {
    "iso:country":"GB",
    "wof:name":"YO15 3NY",
    "wof:placetype":"postalcode"
},
  "geometry": {"coordinates":[-0.21384722577257,54.07649894590035],"type":"Point"}
}