{
  "type": "Feature",
  "properties": {
    "iso:country": "GB",
    "wof:name": "YO15 3NY",
    "wof:placetype": "postalcode"
  },
  "geometry": {"coordinates":[-0.213847,54.076499],"type":"Point"}
}
