{
  "type": "Feature",
  "properties": {
    "iso:country": "GB",
    "wof:name": "AB45 2UJ",
    "wof:placetype": "postalcode"
  },
  "geometry": {"coordinates":[-2.758136,57.677975],"type":"Point"}
}
