{
  "type": "Feature",
  "properties": {
    "iso:country":"GB",
    "wof:name":"SR4 8RW",
    "wof:placetype":"postalcode"
},
  "geometry": {"coordinates":[-1.4307533486139,54.89257124761235],"type":"Point"}
}