{
  "type": "Feature",
  "properties": {
    "iso:country":"GB",
    "wof:name":"OL2 6JH",
    "wof:placetype":"postalcode"
},
  "geometry": {"coordinates":[-2.10891941793465,53.56257255559594],"type":"Point"}
}