{
  "type": "Feature",
  "properties": {
    "iso:country":"GB",
    "wof:name":"RH2 9LP",
    "wof:placetype":"postalcode"
},
  "geometry": {"coordinates":[-0.20677842107984,51.24632751185212],"type":"Point"}
}