{
  "type": "Feature",
  "properties": {
    "date:inception_lower": "1980-01-01",
    "date:inception_upper": "1980-01-01",
    "iso:country": "GB",
    "wof:name": "RH2 9LP",
    "wof:placetype": "postalcode"
  },
  "geometry": {"coordinates":[-0.206778,51.246328],"type":"Point"}
}
