{
  "type": "Feature",
  "properties": {
    "iso:country": "GB",
    "wof:name": "N9 7PE",
    "wof:placetype": "postalcode"
  },
  "geometry": {"coordinates":[-0.059236,51.637812],"type":"Point"}
}
