{
  "type": "Feature",
  "properties": {
    "iso:country":"GB",
    "wof:name":"N9 7PE",
    "wof:placetype":"postalcode"
},
  "geometry": {"coordinates":[-0.05909703676972,51.63795977927044],"type":"Point"}
}