{
  "type": "Feature",
  "properties": {
    "iso:country":"GB",
    "wof:name":"HA4 9LP",
    "wof:placetype":"postalcode"
},
  "geometry": {"coordinates":[-0.40362453018643,51.57025947205222],"type":"Point"}
}