{
  "type": "Feature",
  "properties": {
    "date:inception_lower": "1980-01-01",
    "date:inception_upper": "1980-01-01",
    "iso:country": "GB",
    "wof:name": "RM18 8PA",
    "wof:placetype": "postalcode"
  },
  "geometry": {"coordinates":[0.423815,51.471754],"type":"Point"}
}
