{
  "type": "Feature",
  "properties": {
    "date:inception_lower": "1980-01-01",
    "date:inception_upper": "1980-01-01",
    "iso:country": "GB",
    "wof:name": "BS10 5JE",
    "wof:placetype": "postalcode"
  },
  "geometry": {"coordinates":[-2.603208,51.496435],"type":"Point"}
}
