{
  "type": "Feature",
  "properties": {
    "iso:country":"GB",
    "wof:name":"BS10 5JE",
    "wof:placetype":"postalcode"
},
  "geometry": {"coordinates":[-2.60320779939488,51.49643537425794],"type":"Point"}
}