{
  "type": "Feature",
  "properties": {
    "date:inception_lower": "1992-08-01",
    "date:inception_upper": "1992-08-01",
    "iso:country": "GB",
    "wof:name": "ME5 7TY",
    "wof:placetype": "postalcode"
  },
  "geometry": {"coordinates":[0.547126,51.368573],"type":"Point"}
}
