{
  "type": "Feature",
  "properties": {
    "date:inception_lower": "2000-06-01",
    "date:inception_upper": "2000-06-01",
    "iso:country": "GB",
    "wof:name": "SN25 3TH",
    "wof:placetype": "postalcode"
  },
  "geometry": {"coordinates":[-1.800319,51.593739],"type":"Point"}
}
