{
  "type": "Feature",
  "properties": {
    "iso:country":"GB",
    "wof:name":"SN25 3TH",
    "wof:placetype":"postalcode"
},
  "geometry": {"coordinates":[-1.80031929125392,51.59373857904895],"type":"Point"}
}