{
  "type": "Feature",
  "properties": {
    "iso:country":"GB",
    "wof:name":"PH2 0HQ",
    "wof:placetype":"postalcode"
},
  "geometry": {"coordinates":[-3.44399907140619,56.3876039603928],"type":"Point"}
}