{
  "type": "Feature",
  "properties": {
    "iso:country":"GB",
    "wof:name":"NG16 5PY",
    "wof:placetype":"postalcode"
},
  "geometry": {"coordinates":[-1.34746741099842,53.06026346916049],"type":"Point"}
}