{
  "type": "Feature",
  "properties": {
    "iso:country": "GB",
    "wof:name": "NG16 5PY",
    "wof:placetype": "postalcode"
  },
  "geometry": {"coordinates":[-1.347467,53.060263],"type":"Point"}
}
