{
  "type": "Feature",
  "properties": {
    "iso:country":"GB",
    "wof:name":"DN37 9PD",
    "wof:placetype":"postalcode"
},
  "geometry": {"coordinates":[-0.14099969843144,53.56783850814517],"type":"Point"}
}