{
  "type": "Feature",
  "properties": {
    "iso:country": "GB",
    "wof:name": "CH45 4SB",
    "wof:placetype": "postalcode"
  },
  "geometry": {"coordinates":[-3.052422,53.422852],"type":"Point"}
}
