{
  "type": "Feature",
  "properties": {
    "date:inception_lower":"1999-06-01",
    "date:inception_upper":"1999-06-30",
    "iso:country":"GB",
    "wof:name":"CH45 4SB",
    "wof:placetype":"postalcode"
},
  "geometry": {"coordinates":[-3.052422,53.422852],"type":"Point"}
}