{
  "type": "Feature",
  "properties": {
    "iso:country":"GB",
    "wof:name":"EH3 5JE",
    "wof:placetype":"postalcode"
},
  "geometry": {"coordinates":[-3.20992614725012,55.96157001019754],"type":"Point"}
}