{
  "type": "Feature",
  "properties": {
    "iso:country": "GB",
    "wof:name": "SK10 5AB",
    "wof:placetype": "postalcode"
  },
  "geometry": {"coordinates":[-2.126226,53.285331],"type":"Point"}
}
