{
  "type": "Feature",
  "properties": {
    "iso:country":"GB",
    "wof:name":"SK10 5AB",
    "wof:placetype":"postalcode"
},
  "geometry": {"coordinates":[-2.12622579040216,53.28533135910013],"type":"Point"}
}