{
  "type": "Feature",
  "properties": {
    "date:inception_lower": "1980-01-01",
    "date:inception_upper": "1980-01-01",
    "iso:country": "GB",
    "wof:name": "SK10 5AB",
    "wof:placetype": "postalcode"
  },
  "geometry": {"coordinates":[-2.126226,53.285331],"type":"Point"}
}
