{
  "type": "Feature",
  "properties": {
    "iso:country":"GB",
    "wof:name":"SN3 3RX",
    "wof:placetype":"postalcode"
},
  "geometry": {"coordinates":[-1.74976886242201,51.56937414935069],"type":"Point"}
}