{
  "type": "Feature",
  "properties": {
    "iso:country":"GB",
    "wof:name":"M24 5QJ",
    "wof:placetype":"postalcode"
},
  "geometry": {"coordinates":[-2.21532852628362,53.55718790845092],"type":"Point"}
}