{
  "type": "Feature",
  "properties": {
    "iso:country": "GB",
    "wof:name": "PR4 6AE",
    "wof:placetype": "postalcode"
  },
  "geometry": {"coordinates":[-2.854351,53.696069],"type":"Point"}
}
