{
  "type": "Feature",
  "properties": {
    "iso:country":"GB",
    "wof:name":"PR4 6AE",
    "wof:placetype":"postalcode"
},
  "geometry": {"coordinates":[-2.85435137391355,53.69606894169199],"type":"Point"}
}