{
  "type": "Feature",
  "properties": {
    "iso:country":"GB",
    "wof:name":"DL8 5EZ",
    "wof:placetype":"postalcode"
},
  "geometry": {"coordinates":[-1.82253842803923,54.30657003672123],"type":"Point"}
}