{
  "type": "Feature",
  "properties": {
    "iso:country":"GB",
    "wof:name":"EX32 8BH",
    "wof:placetype":"postalcode"
},
  "geometry": {"coordinates":[-4.05444759702743,51.07935469494635],"type":"Point"}
}