{
  "type": "Feature",
  "properties": {
    "iso:country": "GB",
    "wof:name": "SA10 6JB",
    "wof:placetype": "postalcode"
  },
  "geometry": {"coordinates":[-3.859793,51.640469],"type":"Point"}
}
