{
  "type": "Feature",
  "properties": {
    "iso:country": "GB",
    "wof:name": "B91 1JW",
    "wof:placetype": "postalcode"
  },
  "geometry": {"coordinates":[-1.78215,52.415708],"type":"Point"}
}
