{
  "type": "Feature",
  "properties": {
    "iso:country":"GB",
    "wof:name":"B91 1JW",
    "wof:placetype":"postalcode"
},
  "geometry": {"coordinates":[-1.78215030737362,52.41570825936322],"type":"Point"}
}