{
  "type": "Feature",
  "properties": {
    "iso:country":"GB",
    "wof:name":"HU8 8NR",
    "wof:placetype":"postalcode"
},
  "geometry": {"coordinates":[-0.31147726683508,53.76512900547719],"type":"Point"}
}