{
  "type": "Feature",
  "properties": {
    "date:inception_lower": "1980-01-01",
    "date:inception_upper": "1980-01-01",
    "iso:country": "GB",
    "wof:name": "GU7 3HJ",
    "wof:placetype": "postalcode"
  },
  "geometry": {"coordinates":[-0.606388,51.190552],"type":"Point"}
}
