{
  "type": "Feature",
  "properties": {
    "iso:country":"GB",
    "wof:name":"GU7 3HJ",
    "wof:placetype":"postalcode"
},
  "geometry": {"coordinates":[-0.60640808832282,51.19055581568973],"type":"Point"}
}