{
  "type": "Feature",
  "properties": {
    "iso:country":"GB",
    "wof:name":"PL4 9JG",
    "wof:placetype":"postalcode"
},
  "geometry": {"coordinates":[-4.11458033305691,50.37171407759388],"type":"Point"}
}