{
  "type": "Feature",
  "properties": {
    "iso:country": "GB",
    "wof:name": "PL4 9JG",
    "wof:placetype": "postalcode"
  },
  "geometry": {"coordinates":[-4.11458,50.371714],"type":"Point"}
}
