{
  "type": "Feature",
  "properties": {
    "iso:country":"GB",
    "wof:name":"RH10 1EB",
    "wof:placetype":"postalcode"
},
  "geometry": {"coordinates":[-0.18591925042644,51.11577062823958],"type":"Point"}
}