{
  "type": "Feature",
  "properties": {
    "iso:country": "GB",
    "wof:name": "SE22 0HF",
    "wof:placetype": "postalcode"
  },
  "geometry": {"coordinates":[-0.066285,51.451483],"type":"Point"}
}
