{
  "type": "Feature",
  "properties": {
    "iso:country":"GB",
    "wof:name":"EN8 8QZ",
    "wof:placetype":"postalcode"
},
  "geometry": {"coordinates":[-0.0374701049712,51.68162718512847],"type":"Point"}
}