{
  "type": "Feature",
  "properties": {
    "iso:country":"GB",
    "wof:name":"TN23 1JZ",
    "wof:placetype":"postalcode"
},
  "geometry": {"coordinates":[0.86797259803028,51.14896108111497],"type":"Point"}
}