{
  "type": "Feature",
  "properties": {
    "iso:country": "GB",
    "wof:name": "L17 1AR",
    "wof:placetype": "postalcode"
  },
  "geometry": {"coordinates":[-2.93426,53.389172],"type":"Point"}
}
