{
  "type": "Feature",
  "properties": {
    "date:inception_lower": "2011-08-01",
    "date:inception_upper": "2011-08-01",
    "iso:country": "GB",
    "wof:name": "DY1 2GS",
    "wof:placetype": "postalcode"
  },
  "geometry": {"coordinates":[-2.112497,52.507244],"type":"Point"}
}
