{
  "type": "Feature",
  "properties": {
    "iso:country":"GB",
    "wof:name":"DY1 2GS",
    "wof:placetype":"postalcode"
},
  "geometry": {"coordinates":[-2.11244422635118,52.50719304029705],"type":"Point"}
}