{
  "type": "Feature",
  "properties": {
    "iso:country":"GB",
    "wof:name":"SY16 2PG",
    "wof:placetype":"postalcode"
},
  "geometry": {"coordinates":[-3.31471540149761,52.51455890888099],"type":"Point"}
}