{
  "type": "Feature",
  "properties": {
    "date:inception_lower": "1980-04-01",
    "date:inception_upper": "1980-04-01",
    "iso:country": "GB",
    "wof:name": "G51 3UW",
    "wof:placetype": "postalcode"
  },
  "geometry": {"coordinates":[-4.311598,55.863313],"type":"Point"}
}
