{
  "type": "Feature",
  "properties": {
    "iso:country":"GB",
    "wof:name":"WF9 4JR",
    "wof:placetype":"postalcode"
},
  "geometry": {"coordinates":[-1.34349768425356,53.61501364877056],"type":"Point"}
}