{
  "type": "Feature",
  "properties": {
    "iso:country":"GB",
    "wof:name":"CB7 4QD",
    "wof:placetype":"postalcode"
},
  "geometry": {"coordinates":[0.27248935770627,52.41388683922764],"type":"Point"}
}