{
  "type": "Feature",
  "properties": {
    "iso:country": "GB",
    "wof:name": "CB7 4QD",
    "wof:placetype": "postalcode"
  },
  "geometry": {"coordinates":[0.272489,52.413887],"type":"Point"}
}
