{
  "type": "Feature",
  "properties": {
    "iso:country":"GB",
    "wof:name":"DD6 9HS",
    "wof:placetype":"postalcode"
},
  "geometry": {"coordinates":[-2.88312706062716,56.45008073519092],"type":"Point"}
}