{
  "type": "Feature",
  "properties": {
    "iso:country":"GB",
    "wof:name":"DT11 8HN",
    "wof:placetype":"postalcode"
},
  "geometry": {"coordinates":[-2.22203628343924,50.89917439991417],"type":"Point"}
}