{
  "type": "Feature",
  "properties": {
    "iso:country": "GB",
    "wof:name": "WV16 5AZ",
    "wof:placetype": "postalcode"
  },
  "geometry": {"coordinates":[-2.440027,52.537039],"type":"Point"}
}
