{
  "type": "Feature",
  "properties": {
    "iso:country":"GB",
    "wof:name":"WV16 5AZ",
    "wof:placetype":"postalcode"
},
  "geometry": {"coordinates":[-2.44002655789863,52.53703850757622],"type":"Point"}
}