{
  "type": "Feature",
  "properties": {
    "iso:country":"GB",
    "wof:name":"ML11 9HR",
    "wof:placetype":"postalcode"
},
  "geometry": {"coordinates":[-3.78002746511349,55.59783064886129],"type":"Point"}
}