{
  "type": "Feature",
  "properties": {
    "iso:country":"GB",
    "wof:name":"SS1 2YU",
    "wof:placetype":"postalcode"
},
  "geometry": {"coordinates":[0.73312836670746,51.53081002102669],"type":"Point"}
}