{
  "type": "Feature",
  "properties": {
    "iso:country": "GB",
    "wof:name": "SS1 2YU",
    "wof:placetype": "postalcode"
  },
  "geometry": {"coordinates":[0.733128,51.53081],"type":"Point"}
}
