{
  "type": "Feature",
  "properties": {
    "iso:country": "GB",
    "wof:name": "NN1 3JF",
    "wof:placetype": "postalcode"
  },
  "geometry": {"coordinates":[-0.888564,52.243507],"type":"Point"}
}
