{
  "type": "Feature",
  "properties": {
    "iso:country": "GB",
    "wof:name": "CM3 5ND",
    "wof:placetype": "postalcode"
  },
  "geometry": {"coordinates":[0.612952,51.646417],"type":"Point"}
}
