{
  "type": "Feature",
  "properties": {
    "date:inception_lower": "1980-01-01",
    "date:inception_upper": "1980-01-01",
    "iso:country": "GB",
    "wof:name": "CM3 5ND",
    "wof:placetype": "postalcode"
  },
  "geometry": {"coordinates":[0.612952,51.646417],"type":"Point"}
}
