{
  "type": "Feature",
  "properties": {
    "iso:country": "GB",
    "wof:name": "WA11 0GW",
    "wof:placetype": "postalcode"
  },
  "geometry": {"coordinates":[-2.65771,53.466064],"type":"Point"}
}
