{
  "type": "Feature",
  "properties": {
    "iso:country": "GB",
    "wof:name": "YO12 6EU",
    "wof:placetype": "postalcode"
  },
  "geometry": {"coordinates":[-0.425237,54.286339],"type":"Point"}
}
