{
  "type": "Feature",
  "properties": {
    "iso:country": "GB",
    "wof:name": "MK17 0RG",
    "wof:placetype": "postalcode"
  },
  "geometry": {"coordinates":[-0.880407,51.974457],"type":"Point"}
}
