{
  "type": "Feature",
  "properties": {
    "iso:country":"GB",
    "wof:name":"MK17 0RG",
    "wof:placetype":"postalcode"
},
  "geometry": {"coordinates":[-0.88039417434331,51.97457307030026],"type":"Point"}
}