{
  "type": "Feature",
  "properties": {
    "iso:country": "GB",
    "wof:name": "BH22 9NT",
    "wof:placetype": "postalcode"
  },
  "geometry": {"coordinates":[-1.890491,50.80477],"type":"Point"}
}
