{
  "type": "Feature",
  "properties": {
    "iso:country":"GB",
    "wof:name":"CV5 7FH",
    "wof:placetype":"postalcode"
},
  "geometry": {"coordinates":[-1.60012153179689,52.41507136713629],"type":"Point"}
}