{
  "type": "Feature",
  "properties": {
    "date:inception_lower": "2000-06-01",
    "date:inception_upper": "2000-06-01",
    "iso:country": "GB",
    "wof:name": "MK4 3DW",
    "wof:placetype": "postalcode"
  },
  "geometry": {"coordinates":[-0.784022,51.999108],"type":"Point"}
}
