{
  "type": "Feature",
  "properties": {
    "iso:country":"GB",
    "wof:name":"MK4 3DW",
    "wof:placetype":"postalcode"
},
  "geometry": {"coordinates":[-0.78402187609034,51.99910761663414],"type":"Point"}
}