{
  "type": "Feature",
  "properties": {
    "iso:country":"GB",
    "wof:name":"PR2 3WJ",
    "wof:placetype":"postalcode"
},
  "geometry": {"coordinates":[-2.72588136636735,53.79335152597935],"type":"Point"}
}