{
  "type": "Feature",
  "properties": {
    "iso:country": "GB",
    "wof:name": "PR2 3WJ",
    "wof:placetype": "postalcode"
  },
  "geometry": {"coordinates":[-2.725881,53.793352],"type":"Point"}
}
