{
  "type": "Feature",
  "properties": {
    "iso:country":"GB",
    "wof:name":"SE11 6SS",
    "wof:placetype":"postalcode"
},
  "geometry": {"coordinates":[-0.11044873001128,51.49271480649189],"type":"Point"}
}