{
  "type": "Feature",
  "properties": {
    "date:inception_lower": "1985-10-01",
    "date:inception_upper": "1985-10-01",
    "iso:country": "GB",
    "wof:name": "BL9 6UY",
    "wof:placetype": "postalcode"
  },
  "geometry": {"coordinates":[-2.244504,53.60619],"type":"Point"}
}
