{
  "type": "Feature",
  "properties": {
    "iso:country": "GB",
    "wof:name": "BL9 6UY",
    "wof:placetype": "postalcode"
  },
  "geometry": {"coordinates":[-2.244504,53.60619],"type":"Point"}
}
