{
  "type": "Feature",
  "properties": {
    "iso:country":"GB",
    "wof:name":"BL9 6UY",
    "wof:placetype":"postalcode"
},
  "geometry": {"coordinates":[-2.24450417562882,53.60618993932346],"type":"Point"}
}