{
  "type": "Feature",
  "properties": {
    "iso:country":"GB",
    "wof:name":"G66 3LQ",
    "wof:placetype":"postalcode"
},
  "geometry": {"coordinates":[-4.11892834132126,55.93321124630879],"type":"Point"}
}