{
  "type": "Feature",
  "properties": {
    "iso:country": "GB",
    "wof:name": "SG9 9FF",
    "wof:placetype": "postalcode"
  },
  "geometry": {"coordinates":[-0.019903,51.947539],"type":"Point"}
}
