{
  "type": "Feature",
  "properties": {
    "iso:country":"GB",
    "wof:name":"SG9 9FF",
    "wof:placetype":"postalcode"
},
  "geometry": {"coordinates":[-0.01993127998234,51.94753008390584],"type":"Point"}
}