{
  "type": "Feature",
  "properties": {
    "date:inception_lower":"1996-06-01",
    "date:inception_upper":"1996-06-30",
    "iso:country":"GB",
    "wof:name":"S13 9UZ",
    "wof:placetype":"postalcode"
},
  "geometry": {"coordinates":[-1.349315,53.360992],"type":"Point"}
}