{
  "type": "Feature",
  "properties": {
    "iso:country":"GB",
    "wof:name":"S13 9UZ",
    "wof:placetype":"postalcode"
},
  "geometry": {"coordinates":[-1.34931532314624,53.36099183740788],"type":"Point"}
}