{
  "type": "Feature",
  "properties": {
    "iso:country":"GB",
    "wof:name":"EN9 1LL",
    "wof:placetype":"postalcode"
},
  "geometry": {"coordinates":[0.00838216427889,51.68807297386387],"type":"Point"}
}