{
  "type": "Feature",
  "properties": {
    "iso:country":"GB",
    "wof:name":"EN3 5BT",
    "wof:placetype":"postalcode"
},
  "geometry": {"coordinates":[-0.04851720563169,51.65952809481621],"type":"Point"}
}