{
  "type": "Feature",
  "properties": {
    "iso:country": "GB",
    "wof:name": "PO20 0TQ",
    "wof:placetype": "postalcode"
  },
  "geometry": {"coordinates":[-0.783657,50.736171],"type":"Point"}
}
