{
  "type": "Feature",
  "properties": {
    "date:inception_lower":"1984-10-01",
    "date:inception_upper":"1984-10-31",
    "iso:country":"GB",
    "wof:name":"PO20 0TQ",
    "wof:placetype":"postalcode"
},
  "geometry": {"coordinates":[-0.783657,50.736171],"type":"Point"}
}