{
  "type": "Feature",
  "properties": {
    "iso:country":"GB",
    "wof:name":"PO20 0TQ",
    "wof:placetype":"postalcode"
},
  "geometry": {"coordinates":[-0.78365669599481,50.73617051879061],"type":"Point"}
}