{
  "type": "Feature",
  "properties": {
    "date:inception_lower": "1995-12-01",
    "date:inception_upper": "1995-12-01",
    "iso:country": "GB",
    "wof:name": "GL4 6UX",
    "wof:placetype": "postalcode"
  },
  "geometry": {"coordinates":[-2.232464,51.840961],"type":"Point"}
}
