{
  "type": "Feature",
  "properties": {
    "iso:country":"GB",
    "wof:name":"B16 0PN",
    "wof:placetype":"postalcode"
},
  "geometry": {"coordinates":[-1.95182169134504,52.48132801227508],"type":"Point"}
}