{
  "type": "Feature",
  "properties": {
    "iso:country":"GB",
    "wof:name":"G31 2PY",
    "wof:placetype":"postalcode"
},
  "geometry": {"coordinates":[-4.21665758371077,55.86149749674448],"type":"Point"}
}