{
  "type": "Feature",
  "properties": {
    "date:inception_lower":"2003-02-01",
    "date:inception_upper":"2003-02-28",
    "iso:country":"GB",
    "wof:name":"PL28 8RL",
    "wof:placetype":"postalcode"
},
  "geometry": {"coordinates":[-4.954725,50.533075],"type":"Point"}
}