{
  "type": "Feature",
  "properties": {
    "date:inception_lower": "1980-01-01",
    "date:inception_upper": "1980-01-01",
    "iso:country": "GB",
    "wof:name": "E4 9SD",
    "wof:placetype": "postalcode"
  },
  "geometry": {"coordinates":[0.006619,51.614796],"type":"Point"}
}
