{
  "type": "Feature",
  "properties": {
    "iso:country":"GB",
    "wof:name":"E4 9SD",
    "wof:placetype":"postalcode"
},
  "geometry": {"coordinates":[0.00661893818563,51.61479629536361],"type":"Point"}
}