{
  "type": "Feature",
  "properties": {
    "date:inception_lower": "1980-01-01",
    "date:inception_upper": "1980-01-01",
    "iso:country": "GB",
    "wof:name": "HU11 5EP",
    "wof:placetype": "postalcode"
  },
  "geometry": {"coordinates":[-0.269346,53.83699],"type":"Point"}
}
