{
  "type": "Feature",
  "properties": {
    "iso:country":"GB",
    "wof:name":"ST7 4PE",
    "wof:placetype":"postalcode"
},
  "geometry": {"coordinates":[-2.2244762232888,53.1086180358845],"type":"Point"}
}