{
  "type": "Feature",
  "properties": {
    "date:inception_lower": "1980-01-01",
    "date:inception_upper": "1980-01-01",
    "iso:country": "GB",
    "wof:name": "SK3 9RQ",
    "wof:placetype": "postalcode"
  },
  "geometry": {"coordinates":[-2.175828,53.398371],"type":"Point"}
}
