{
  "type": "Feature",
  "properties": {
    "iso:country": "GB",
    "wof:name": "CM6 1FX",
    "wof:placetype": "postalcode"
  },
  "geometry": {"coordinates":[0.360738,51.876032],"type":"Point"}
}
