{
  "type": "Feature",
  "properties": {
    "date:inception_lower":"2002-11-01",
    "date:inception_upper":"2002-11-30",
    "iso:country":"GB",
    "wof:name":"CM6 1FX",
    "wof:placetype":"postalcode"
},
  "geometry": {"coordinates":[0.360738,51.876032],"type":"Point"}
}