{
  "type": "Feature",
  "properties": {
    "iso:country":"GB",
    "wof:name":"LS8 3JD",
    "wof:placetype":"postalcode"
},
  "geometry": {"coordinates":[-1.49584387490173,53.8175097026701],"type":"Point"}
}