{
  "type": "Feature",
  "properties": {
    "iso:country": "GB",
    "wof:name": "LS8 3JD",
    "wof:placetype": "postalcode"
  },
  "geometry": {"coordinates":[-1.495844,53.81751],"type":"Point"}
}
