{
  "type": "Feature",
  "properties": {
    "iso:country": "GB",
    "wof:name": "SA47 0QA",
    "wof:placetype": "postalcode"
  },
  "geometry": {"coordinates":[-4.321321,52.206119],"type":"Point"}
}
