{
  "type": "Feature",
  "properties": {
    "date:inception_lower":"1980-01-01",
    "date:inception_upper":"1980-01-31",
    "iso:country":"GB",
    "wof:name":"SA47 0QA",
    "wof:placetype":"postalcode"
},
  "geometry": {"coordinates":[-4.321321,52.206119],"type":"Point"}
}