{
  "type": "Feature",
  "properties": {
    "iso:country":"GB",
    "wof:name":"SA47 0QA",
    "wof:placetype":"postalcode"
},
  "geometry": {"coordinates":[-4.32132117958666,52.20611868562258],"type":"Point"}
}