{
  "type": "Feature",
  "properties": {
    "iso:country":"GB",
    "wof:name":"GU16 8UT",
    "wof:placetype":"postalcode"
},
  "geometry": {"coordinates":[-0.7218745528277,51.31111229947629],"type":"Point"}
}