{
  "type": "Feature",
  "properties": {
    "iso:country":"GB",
    "wof:name":"RH17 7HS",
    "wof:placetype":"postalcode"
},
  "geometry": {"coordinates":[0.00136010305945,51.03584927191468],"type":"Point"}
}