{
  "type": "Feature",
  "properties": {
    "iso:country": "GB",
    "wof:name": "RH17 7HS",
    "wof:placetype": "postalcode"
  },
  "geometry": {"coordinates":[0.00136,51.035849],"type":"Point"}
}
