{
  "type": "Feature",
  "properties": {
    "iso:country":"GB",
    "wof:name":"CV22 7DH",
    "wof:placetype":"postalcode"
},
  "geometry": {"coordinates":[-1.28834863622527,52.37140631271969],"type":"Point"}
}