{
  "type": "Feature",
  "properties": {
    "iso:country":"GB",
    "wof:name":"W10 6QX",
    "wof:placetype":"postalcode"
},
  "geometry": {"coordinates":[-0.22101420113814,51.51409265034017],"type":"Point"}
}