{
  "type": "Feature",
  "properties": {
    "date:inception_lower":"1981-06-01",
    "date:inception_upper":"1981-06-30",
    "iso:country":"GB",
    "wof:name":"W10 6QX",
    "wof:placetype":"postalcode"
},
  "geometry": {"coordinates":[-0.221225,51.513981],"type":"Point"}
}