{
  "type": "Feature",
  "properties": {
    "date:inception_lower": "1980-01-01",
    "date:inception_upper": "1980-01-01",
    "iso:country": "GB",
    "wof:name": "OL16 2SD",
    "wof:placetype": "postalcode"
  },
  "geometry": {"coordinates":[-2.123885,53.636064],"type":"Point"}
}
