{
  "type": "Feature",
  "properties": {
    "iso:country":"GB",
    "wof:name":"OL16 2SD",
    "wof:placetype":"postalcode"
},
  "geometry": {"coordinates":[-2.12388482730353,53.6360639617704],"type":"Point"}
}