{
  "type": "Feature",
  "properties": {
    "date:inception_lower":"1980-01-01",
    "date:inception_upper":"1980-01-31",
    "iso:country":"GB",
    "wof:name":"EX37 9PQ",
    "wof:placetype":"postalcode"
},
  "geometry": {"coordinates":[-3.941572,50.982755],"type":"Point"}
}