{
  "type": "Feature",
  "properties": {
    "iso:country": "GB",
    "wof:name": "EX37 9PQ",
    "wof:placetype": "postalcode"
  },
  "geometry": {"coordinates":[-3.941572,50.982755],"type":"Point"}
}
