{
  "type": "Feature",
  "properties": {
    "iso:country":"GB",
    "wof:name":"SO32 3AN",
    "wof:placetype":"postalcode"
},
  "geometry": {"coordinates":[-1.1404438363138,50.96175247406683],"type":"Point"}
}