{
  "type": "Feature",
  "properties": {
    "date:inception_lower": "2011-01-01",
    "date:inception_upper": "2011-01-01",
    "iso:country": "GB",
    "wof:name": "SO32 3AN",
    "wof:placetype": "postalcode"
  },
  "geometry": {"coordinates":[-1.140386,50.961782],"type":"Point"}
}
