{
  "type": "Feature",
  "properties": {
    "iso:country":"GB",
    "wof:name":"AB45 1HX",
    "wof:placetype":"postalcode"
},
  "geometry": {"coordinates":[-2.52385556308427,57.66836502888451],"type":"Point"}
}