{
  "type": "Feature",
  "properties": {
    "iso:country":"GB",
    "wof:name":"BA2 4QG",
    "wof:placetype":"postalcode"
},
  "geometry": {"coordinates":[-2.36060995227286,51.37583922303802],"type":"Point"}
}