{
  "type": "Feature",
  "properties": {
    "iso:country":"GB",
    "wof:name":"MK42 9RE",
    "wof:placetype":"postalcode"
},
  "geometry": {"coordinates":[-0.46525544504627,52.11872066871125],"type":"Point"}
}