{
  "type": "Feature",
  "properties": {
    "date:inception_lower": "2001-06-01",
    "date:inception_upper": "2001-06-01",
    "iso:country": "GB",
    "wof:name": "MK42 9RE",
    "wof:placetype": "postalcode"
  },
  "geometry": {"coordinates":[-0.465276,52.118787],"type":"Point"}
}
