{
  "type": "Feature",
  "properties": {
    "date:inception_lower":"2001-06-01",
    "date:inception_upper":"2001-06-30",
    "iso:country":"GB",
    "wof:name":"MK42 9RE",
    "wof:placetype":"postalcode"
},
  "geometry": {"coordinates":[-0.465255,52.118721],"type":"Point"}
}