{
  "type": "Feature",
  "properties": {
    "iso:country": "GB",
    "wof:name": "HU5 4BP",
    "wof:placetype": "postalcode"
  },
  "geometry": {"coordinates":[-0.379239,53.763439],"type":"Point"}
}
