{
  "type": "Feature",
  "properties": {
    "date:inception_lower": "2024-05-01",
    "date:inception_upper": "2024-05-01",
    "iso:country": "GB",
    "wof:name": "IP6 0FT",
    "wof:placetype": "postalcode"
  },
  "geometry": {"coordinates":[1.09001,52.113268],"type":"Point"}
}
