{
  "type": "Feature",
  "properties": {
    "iso:country":"GB",
    "wof:name":"RG10 9NT",
    "wof:placetype":"postalcode"
},
  "geometry": {"coordinates":[-0.86499586032377,51.47594453510492],"type":"Point"}
}