{
  "type": "Feature",
  "properties": {
    "iso:country":"GB",
    "wof:name":"BA1 4DE",
    "wof:placetype":"postalcode"
},
  "geometry": {"coordinates":[-2.38870222996409,51.39500054197292],"type":"Point"}
}