{
  "type": "Feature",
  "properties": {
    "iso:country":"GB",
    "wof:name":"NG13 8EG",
    "wof:placetype":"postalcode"
},
  "geometry": {"coordinates":[-0.93726871007088,52.95295655753247],"type":"Point"}
}