{
  "type": "Feature",
  "properties": {
    "date:inception_lower": "1980-01-01",
    "date:inception_upper": "1980-01-01",
    "iso:country": "GB",
    "wof:name": "PA20 9LL",
    "wof:placetype": "postalcode"
  },
  "geometry": {"coordinates":[-5.029055,55.823351],"type":"Point"}
}
