{
  "type": "Feature",
  "properties": {
    "date:inception_lower":"1999-12-01",
    "date:inception_upper":"1999-12-31",
    "iso:country":"GB",
    "wof:name":"TD2 6QE",
    "wof:placetype":"postalcode"
},
  "geometry": {"coordinates":[-2.753053,55.72065],"type":"Point"}
}