{
  "type": "Feature",
  "properties": {
    "iso:country":"GB",
    "wof:name":"TD2 6QE",
    "wof:placetype":"postalcode"
},
  "geometry": {"coordinates":[-2.75305262650676,55.72065009389519],"type":"Point"}
}