{
  "type": "Feature",
  "properties": {
    "iso:country": "GB",
    "wof:name": "CV47 2DD",
    "wof:placetype": "postalcode"
  },
  "geometry": {"coordinates":[-1.387133,52.2147],"type":"Point"}
}
