{
  "type": "Feature",
  "properties": {
    "iso:country":"GB",
    "wof:name":"CV47 2DD",
    "wof:placetype":"postalcode"
},
  "geometry": {"coordinates":[-1.38713342858636,52.21470001417083],"type":"Point"}
}