{
  "type": "Feature",
  "properties": {
    "iso:country":"GB",
    "wof:name":"KT8 9JU",
    "wof:placetype":"postalcode"
},
  "geometry": {"coordinates":[-0.35438992009035,51.40103644404388],"type":"Point"}
}