{
  "type": "Feature",
  "properties": {
    "iso:country": "GB",
    "wof:name": "CH2 2HH",
    "wof:placetype": "postalcode"
  },
  "geometry": {"coordinates":[-2.877482,53.205465],"type":"Point"}
}
