{
  "type": "Feature",
  "properties": {
    "date:inception_lower": "2017-02-01",
    "date:inception_upper": "2017-02-01",
    "iso:country": "GB",
    "wof:name": "TN28 8FE",
    "wof:placetype": "postalcode"
  },
  "geometry": {"coordinates":[0.942576,50.992913],"type":"Point"}
}
