{
  "type": "Feature",
  "properties": {
    "date:inception_lower": "1980-01-01",
    "date:inception_upper": "1980-01-01",
    "iso:country": "GB",
    "wof:name": "BL1 5UE",
    "wof:placetype": "postalcode"
  },
  "geometry": {"coordinates":[-2.477513,53.595159],"type":"Point"}
}
