{
  "type": "Feature",
  "properties": {
    "iso:country":"GB",
    "wof:name":"ML9 3LT",
    "wof:placetype":"postalcode"
},
  "geometry": {"coordinates":[-3.97945092974765,55.6996704149204],"type":"Point"}
}