{
  "type": "Feature",
  "properties": {
    "iso:country":"GB",
    "wof:name":"BD5 8JB",
    "wof:placetype":"postalcode"
},
  "geometry": {"coordinates":[-1.75603462704642,53.76962356018483],"type":"Point"}
}