{
  "type": "Feature",
  "properties": {
    "date:inception_lower": "2007-09-01",
    "date:inception_upper": "2007-09-01",
    "iso:country": "GB",
    "wof:name": "FY1 6DF",
    "wof:placetype": "postalcode"
  },
  "geometry": {"coordinates":[-3.038701,53.800379],"type":"Point"}
}
