{
  "type": "Feature",
  "properties": {
    "iso:country":"GB",
    "wof:name":"PR25 3SS",
    "wof:placetype":"postalcode"
},
  "geometry": {"coordinates":[-2.69132111100968,53.69858617721599],"type":"Point"}
}