{
  "type": "Feature",
  "properties": {
    "iso:country": "GB",
    "wof:name": "IP6 9AG",
    "wof:placetype": "postalcode"
  },
  "geometry": {"coordinates":[1.171084,52.084026],"type":"Point"}
}
