{
  "type": "Feature",
  "properties": {
    "iso:country":"GB",
    "wof:name":"IP6 9AG",
    "wof:placetype":"postalcode"
},
  "geometry": {"coordinates":[1.17108404227717,52.08402570034121],"type":"Point"}
}