{
  "type": "Feature",
  "properties": {
    "iso:country": "GB",
    "wof:name": "WV1 2AS",
    "wof:placetype": "postalcode"
  },
  "geometry": {"coordinates":[-2.092683,52.58909],"type":"Point"}
}
