{
  "type": "Feature",
  "properties": {
    "iso:country":"GB",
    "wof:name":"ST5 4AX",
    "wof:placetype":"postalcode"
},
  "geometry": {"coordinates":[-2.23237535247236,52.98893083191111],"type":"Point"}
}