{
  "type": "Feature",
  "properties": {
    "iso:country":"GB",
    "wof:name":"ST8 7ZB",
    "wof:placetype":"postalcode"
},
  "geometry": {"coordinates":[-2.17398418472734,53.11555226735298],"type":"Point"}
}