{
  "type": "Feature",
  "properties": {
    "iso:country":"GB",
    "wof:name":"NW9 7TH",
    "wof:placetype":"postalcode"
},
  "geometry": {"coordinates":[-0.2451008483282,51.58071107254624],"type":"Point"}
}