{
  "type": "Feature",
  "properties": {
    "date:inception_lower": "1997-12-01",
    "date:inception_upper": "1997-12-01",
    "iso:country": "GB",
    "wof:name": "BS15 9YW",
    "wof:placetype": "postalcode"
  },
  "geometry": {"coordinates":[-2.490744,51.455985],"type":"Point"}
}
