{
  "type": "Feature",
  "properties": {
    "iso:country": "GB",
    "wof:name": "SA18 3QS",
    "wof:placetype": "postalcode"
  },
  "geometry": {"coordinates":[-4.009574,51.786285],"type":"Point"}
}
