{
  "type": "Feature",
  "properties": {
    "iso:country":"GB",
    "wof:name":"SA18 3QS",
    "wof:placetype":"postalcode"
},
  "geometry": {"coordinates":[-4.00957365353276,51.78628531438729],"type":"Point"}
}