{
  "type": "Feature",
  "properties": {
    "iso:country":"GB",
    "wof:name":"TA6 5EU",
    "wof:placetype":"postalcode"
},
  "geometry": {"coordinates":[-2.99253201598332,51.12839412249669],"type":"Point"}
}