{
  "type": "Feature",
  "properties": {
    "iso:country":"GB",
    "wof:name":"NE4 8QJ",
    "wof:placetype":"postalcode"
},
  "geometry": {"coordinates":[-1.6595321334118,54.97024214755285],"type":"Point"}
}