{
  "type": "Feature",
  "properties": {
    "iso:country":"GB",
    "wof:name":"G31 3HX",
    "wof:placetype":"postalcode"
},
  "geometry": {"coordinates":[-4.21036235179879,55.86461254814683],"type":"Point"}
}