{
  "type": "Feature",
  "properties": {
    "iso:country": "GB",
    "wof:name": "G31 3HX",
    "wof:placetype": "postalcode"
  },
  "geometry": {"coordinates":[-4.210362,55.864613],"type":"Point"}
}
