{
  "type": "Feature",
  "properties": {
    "iso:country": "GB",
    "wof:name": "DH9 7UH",
    "wof:placetype": "postalcode"
  },
  "geometry": {"coordinates":[-1.733688,54.856004],"type":"Point"}
}
