{
  "type": "Feature",
  "properties": {
    "iso:country":"GB",
    "wof:name":"DH9 7UH",
    "wof:placetype":"postalcode"
},
  "geometry": {"coordinates":[-1.73368850964561,54.85600419953704],"type":"Point"}
}