{
  "type": "Feature",
  "properties": {
    "iso:country":"GB",
    "wof:name":"EH5 1HP",
    "wof:placetype":"postalcode"
},
  "geometry": {"coordinates":[-3.23077810719575,55.97908288900777],"type":"Point"}
}