{
  "type": "Feature",
  "properties": {
    "iso:country":"GB",
    "wof:name":"DH5 0DT",
    "wof:placetype":"postalcode"
},
  "geometry": {"coordinates":[-1.46321857530298,54.81237957195219],"type":"Point"}
}