{
  "type": "Feature",
  "properties": {
    "date:inception_lower": "1980-01-01",
    "date:inception_upper": "1980-01-01",
    "iso:country": "GB",
    "wof:name": "DH5 0DT",
    "wof:placetype": "postalcode"
  },
  "geometry": {"coordinates":[-1.463219,54.81238],"type":"Point"}
}
