{
  "type": "Feature",
  "properties": {
    "iso:country": "GB",
    "wof:name": "IG6 1HZ",
    "wof:placetype": "postalcode"
  },
  "geometry": {"coordinates":[0.081849,51.58613],"type":"Point"}
}
