{
  "type": "Feature",
  "properties": {
    "iso:country":"GB",
    "wof:name":"IG6 1HZ",
    "wof:placetype":"postalcode"
},
  "geometry": {"coordinates":[0.08184911321963,51.58613040461692],"type":"Point"}
}