{
  "type": "Feature",
  "properties": {
    "iso:country":"GB",
    "wof:name":"AL7 3NE",
    "wof:placetype":"postalcode"
},
  "geometry": {"coordinates":[-0.19189657016987,51.79683138246759],"type":"Point"}
}