{
  "type": "Feature",
  "properties": {
    "iso:country":"GB",
    "wof:name":"SY11 2PX",
    "wof:placetype":"postalcode"
},
  "geometry": {"coordinates":[-3.04275812857316,52.85621069713475],"type":"Point"}
}