{
  "type": "Feature",
  "properties": {
    "iso:country":"GB",
    "wof:name":"NW2 3UE",
    "wof:placetype":"postalcode"
},
  "geometry": {"coordinates":[-0.20557184581573,51.54800159521886],"type":"Point"}
}