{
  "type": "Feature",
  "properties": {
    "date:inception_lower":"2013-11-01",
    "date:inception_upper":"2013-11-30",
    "iso:country":"GB",
    "wof:name":"CO11 1UJ",
    "wof:placetype":"postalcode"
},
  "geometry": {"coordinates":[1.081777,51.97034],"type":"Point"}
}