{
  "type": "Feature",
  "properties": {
    "iso:country":"GB",
    "wof:name":"CO11 1UJ",
    "wof:placetype":"postalcode"
},
  "geometry": {"coordinates":[1.08177720789725,51.97034022607529],"type":"Point"}
}