{
  "type": "Feature",
  "properties": {
    "iso:country": "GB",
    "wof:name": "CO11 1UJ",
    "wof:placetype": "postalcode"
  },
  "geometry": {"coordinates":[1.081823,51.97037],"type":"Point"}
}
