{
  "type": "Feature",
  "properties": {
    "iso:country": "GB",
    "wof:name": "KT13 0DQ",
    "wof:placetype": "postalcode"
  },
  "geometry": {"coordinates":[-0.450247,51.363721],"type":"Point"}
}
