{
  "type": "Feature",
  "properties": {
    "iso:country":"GB",
    "wof:name":"BL0 9SQ",
    "wof:placetype":"postalcode"
},
  "geometry": {"coordinates":[-2.32212359004503,53.64577007195479],"type":"Point"}
}