{
  "type": "Feature",
  "properties": {
    "date:inception_lower": "1990-02-01",
    "date:inception_upper": "1990-02-01",
    "iso:country": "GB",
    "wof:name": "BL0 9SQ",
    "wof:placetype": "postalcode"
  },
  "geometry": {"coordinates":[-2.322124,53.64577],"type":"Point"}
}
