{
  "type": "Feature",
  "properties": {
    "date:inception_lower":"1980-01-01",
    "date:inception_upper":"1980-01-31",
    "iso:country":"GB",
    "wof:name":"WA1 2EH",
    "wof:placetype":"postalcode"
},
  "geometry": {"coordinates":[-2.581465,53.390416],"type":"Point"}
}