{
  "type": "Feature",
  "properties": {
    "iso:country":"GB",
    "wof:name":"WA1 2EH",
    "wof:placetype":"postalcode"
},
  "geometry": {"coordinates":[-2.58146540528936,53.39041593414287],"type":"Point"}
}