{
  "type": "Feature",
  "properties": {
    "iso:country":"GB",
    "wof:name":"HP2 7JA",
    "wof:placetype":"postalcode"
},
  "geometry": {"coordinates":[-0.42736860021592,51.76506765083553],"type":"Point"}
}