{
  "type": "Feature",
  "properties": {
    "iso:country":"GB",
    "wof:name":"BN21 3AR",
    "wof:placetype":"postalcode"
},
  "geometry": {"coordinates":[0.28886382236637,50.76822865425233],"type":"Point"}
}