{
  "type": "Feature",
  "properties": {
    "iso:country":"GB",
    "wof:name":"RH16 3BB",
    "wof:placetype":"postalcode"
},
  "geometry": {"coordinates":[-0.10389905570512,51.0006785898442],"type":"Point"}
}