{
  "type": "Feature",
  "properties": {
    "date:inception_lower": "2009-05-01",
    "date:inception_upper": "2009-05-01",
    "iso:country": "GB",
    "wof:name": "RH16 3BB",
    "wof:placetype": "postalcode"
  },
  "geometry": {"coordinates":[-0.103899,51.000679],"type":"Point"}
}
