{
  "type": "Feature",
  "properties": {
    "date:inception_lower": "2020-02-01",
    "date:inception_upper": "2020-02-01",
    "iso:country": "GB",
    "wof:name": "NN11 8NW",
    "wof:placetype": "postalcode"
  },
  "geometry": {"coordinates":[-1.181361,52.258331],"type":"Point"}
}
