{
  "type": "Feature",
  "properties": {
    "iso:country": "GB",
    "wof:name": "NN11 8NW",
    "wof:placetype": "postalcode"
  },
  "geometry": {"coordinates":[-1.183246,52.25705],"type":"Point"}
}
