{
  "type": "Feature",
  "properties": {
    "date:inception_lower":"1980-01-01",
    "date:inception_upper":"1980-01-31",
    "iso:country":"GB",
    "wof:name":"IG10 1QE",
    "wof:placetype":"postalcode"
},
  "geometry": {"coordinates":[0.068267,51.654148],"type":"Point"}
}