{
  "type": "Feature",
  "properties": {
    "iso:country":"GB",
    "wof:name":"M21 8FQ",
    "wof:placetype":"postalcode"
},
  "geometry": {"coordinates":[-2.28067755756329,53.43414429758104],"type":"Point"}
}