{
  "type": "Feature",
  "properties": {
    "iso:country":"GB",
    "wof:name":"SY14 7HU",
    "wof:placetype":"postalcode"
},
  "geometry": {"coordinates":[-2.82449132334522,53.08267298389688],"type":"Point"}
}