{
  "type": "Feature",
  "properties": {
    "iso:country": "GB",
    "wof:name": "SY14 7HU",
    "wof:placetype": "postalcode"
  },
  "geometry": {"coordinates":[-2.824491,53.082673],"type":"Point"}
}
