{
  "type": "Feature",
  "properties": {
    "date:inception_lower": "2006-09-01",
    "date:inception_upper": "2006-09-01",
    "iso:country": "GB",
    "wof:name": "G33 5DQ",
    "wof:placetype": "postalcode"
  },
  "geometry": {"coordinates":[-4.139587,55.874932],"type":"Point"}
}
