{
  "type": "Feature",
  "properties": {
    "iso:country":"GB",
    "wof:name":"NG2 7TE",
    "wof:placetype":"postalcode"
},
  "geometry": {"coordinates":[-1.15248574216509,52.91115827172511],"type":"Point"}
}