{
  "type": "Feature",
  "properties": {
    "iso:country": "GB",
    "wof:name": "NG2 7TE",
    "wof:placetype": "postalcode"
  },
  "geometry": {"coordinates":[-1.152486,52.911158],"type":"Point"}
}
