{
  "type": "Feature",
  "properties": {
    "date:inception_lower": "1990-02-01",
    "date:inception_upper": "1990-02-01",
    "iso:country": "GB",
    "wof:name": "CF35 6RF",
    "wof:placetype": "postalcode"
  },
  "geometry": {"coordinates":[-3.519141,51.526212],"type":"Point"}
}
