{
  "type": "Feature",
  "properties": {
    "iso:country":"GB",
    "wof:name":"TR3 7JS",
    "wof:placetype":"postalcode"
},
  "geometry": {"coordinates":[-5.11933557098792,50.21105697108909],"type":"Point"}
}