{
  "type": "Feature",
  "properties": {
    "iso:country": "GB",
    "wof:name": "TR3 7JS",
    "wof:placetype": "postalcode"
  },
  "geometry": {"coordinates":[-5.119336,50.211057],"type":"Point"}
}
