{
  "type": "Feature",
  "properties": {
    "iso:country": "GB",
    "wof:name": "CB4 1PW",
    "wof:placetype": "postalcode"
  },
  "geometry": {"coordinates":[0.136426,52.220781],"type":"Point"}
}
