{
  "type": "Feature",
  "properties": {
    "date:inception_lower": "1980-01-01",
    "date:inception_upper": "1980-01-01",
    "iso:country": "GB",
    "wof:name": "CB4 1PW",
    "wof:placetype": "postalcode"
  },
  "geometry": {"coordinates":[0.136426,52.220781],"type":"Point"}
}
