{
  "type": "Feature",
  "properties": {
    "date:inception_lower": "2008-04-01",
    "date:inception_upper": "2008-04-01",
    "iso:country": "GB",
    "wof:name": "SY23 4QT",
    "wof:placetype": "postalcode"
  },
  "geometry": {"coordinates":[-4.032264,52.342423],"type":"Point"}
}
