{
  "type": "Feature",
  "properties": {
    "iso:country": "GB",
    "wof:name": "SY23 4QT",
    "wof:placetype": "postalcode"
  },
  "geometry": {"coordinates":[-4.032264,52.342423],"type":"Point"}
}
