{
  "type": "Feature",
  "properties": {
    "iso:country":"GB",
    "wof:name":"DT11 0LU",
    "wof:placetype":"postalcode"
},
  "geometry": {"coordinates":[-2.21366985559908,50.84528929855188],"type":"Point"}
}