{
  "type": "Feature",
  "properties": {
    "iso:country": "GB",
    "wof:name": "PO20 1LQ",
    "wof:placetype": "postalcode"
  },
  "geometry": {"coordinates":[-0.74594,50.814946],"type":"Point"}
}
