{
  "type": "Feature",
  "properties": {
    "date:inception_lower": "1980-01-01",
    "date:inception_upper": "1980-01-01",
    "iso:country": "GB",
    "wof:name": "NE3 3RX",
    "wof:placetype": "postalcode"
  },
  "geometry": {"coordinates":[-1.652691,55.006291],"type":"Point"}
}
