{
  "type": "Feature",
  "properties": {
    "iso:country": "GB",
    "wof:name": "LS15 0LQ",
    "wof:placetype": "postalcode"
  },
  "geometry": {"coordinates":[-1.469211,53.795158],"type":"Point"}
}
