{
  "type": "Feature",
  "properties": {
    "date:inception_lower": "2024-02-01",
    "date:inception_upper": "2024-02-01",
    "iso:country": "GB",
    "wof:name": "PE10 2BW",
    "wof:placetype": "postalcode"
  },
  "geometry": {"coordinates":[-0.383214,52.763473],"type":"Point"}
}
