{
  "type": "Feature",
  "properties": {
    "iso:country":"GB",
    "wof:name":"SA18 3DB",
    "wof:placetype":"postalcode"
},
  "geometry": {"coordinates":[-3.98795450702813,51.79220125597784],"type":"Point"}
}