{
  "type": "Feature",
  "properties": {
    "iso:country":"GB",
    "wof:name":"FK10 1JE",
    "wof:placetype":"postalcode"
},
  "geometry": {"coordinates":[-3.79173483287547,56.11515739198123],"type":"Point"}
}