{
  "type": "Feature",
  "properties": {
    "iso:country":"GB",
    "wof:name":"DN8 5UJ",
    "wof:placetype":"postalcode"
},
  "geometry": {"coordinates":[-0.97144875074902,53.6137885805667],"type":"Point"}
}