{
  "type": "Feature",
  "properties": {
    "date:inception_lower":"2000-12-01",
    "date:inception_upper":"2000-12-31",
    "iso:country":"GB",
    "wof:name":"DN8 5UJ",
    "wof:placetype":"postalcode"
},
  "geometry": {"coordinates":[-0.971454,53.613809],"type":"Point"}
}