{
  "type": "Feature",
  "properties": {
    "iso:country": "GB",
    "wof:name": "DN8 5UJ",
    "wof:placetype": "postalcode"
  },
  "geometry": {"coordinates":[-0.971454,53.613809],"type":"Point"}
}
