{
  "type": "Feature",
  "properties": {
    "iso:country": "GB",
    "wof:name": "WS11 1BB",
    "wof:placetype": "postalcode"
  },
  "geometry": {"coordinates":[-2.037399,52.686263],"type":"Point"}
}
