{
  "type": "Feature",
  "properties": {
    "iso:country":"GB",
    "wof:name":"SY4 2GD",
    "wof:placetype":"postalcode"
},
  "geometry": {"coordinates":[-2.85801074841323,52.79104915989091],"type":"Point"}
}