{
  "type": "Feature",
  "properties": {
    "date:inception_lower":"2007-09-01",
    "date:inception_upper":"2007-09-30",
    "iso:country":"GB",
    "wof:name":"SY4 2GD",
    "wof:placetype":"postalcode"
},
  "geometry": {"coordinates":[-2.858011,52.791049],"type":"Point"}
}