{
  "type": "Feature",
  "properties": {
    "iso:country":"GB",
    "wof:name":"DT3 4AF",
    "wof:placetype":"postalcode"
},
  "geometry": {"coordinates":[-2.49488162822969,50.6162087090749],"type":"Point"}
}