{
  "type": "Feature",
  "properties": {
    "iso:country":"GB",
    "wof:name":"KA6 7HB",
    "wof:placetype":"postalcode"
},
  "geometry": {"coordinates":[-4.44760256962624,55.40044661700612],"type":"Point"}
}