{
  "type": "Feature",
  "properties": {
    "date:inception_lower": "1980-01-01",
    "date:inception_upper": "1980-01-01",
    "iso:country": "GB",
    "wof:name": "KA6 7HB",
    "wof:placetype": "postalcode"
  },
  "geometry": {"coordinates":[-4.447603,55.400447],"type":"Point"}
}
