{
  "type": "Feature",
  "properties": {
    "iso:country":"GB",
    "wof:name":"DE14 2BD",
    "wof:placetype":"postalcode"
},
  "geometry": {"coordinates":[-1.66663379203785,52.81040588534724],"type":"Point"}
}