{
  "type": "Feature",
  "properties": {
    "iso:country": "GB",
    "wof:name": "LE9 7EA",
    "wof:placetype": "postalcode"
  },
  "geometry": {"coordinates":[-1.316231,52.577328],"type":"Point"}
}
