{
  "type": "Feature",
  "properties": {
    "iso:country":"GB",
    "wof:name":"KT17 2NX",
    "wof:placetype":"postalcode"
},
  "geometry": {"coordinates":[-0.24739471019106,51.3605562850876],"type":"Point"}
}