{
  "type": "Feature",
  "properties": {
    "date:inception_lower": "2018-01-01",
    "date:inception_upper": "2018-01-01",
    "iso:country": "GB",
    "wof:name": "PE23 5RD",
    "wof:placetype": "postalcode"
  },
  "geometry": {"coordinates":[0.082323,53.175129],"type":"Point"}
}
