{
  "type": "Feature",
  "properties": {
    "iso:country": "GB",
    "wof:name": "NN9 5TU",
    "wof:placetype": "postalcode"
  },
  "geometry": {"coordinates":[-0.613909,52.326695],"type":"Point"}
}
