{
  "type": "Feature",
  "properties": {
    "date:inception_lower": "1990-02-01",
    "date:inception_upper": "1990-02-01",
    "iso:country": "GB",
    "wof:name": "ME20 7TA",
    "wof:placetype": "postalcode"
  },
  "geometry": {"coordinates":[0.478816,51.319792],"type":"Point"}
}
