{
  "type": "Feature",
  "properties": {
    "iso:country": "GB",
    "wof:name": "DE11 8AJ",
    "wof:placetype": "postalcode"
  },
  "geometry": {"coordinates":[-1.514759,52.758669],"type":"Point"}
}
