{
  "type": "Feature",
  "properties": {
    "iso:country":"GB",
    "wof:name":"DE11 8AJ",
    "wof:placetype":"postalcode"
},
  "geometry": {"coordinates":[-1.51475889175285,52.75866885859762],"type":"Point"}
}