{
  "type": "Feature",
  "properties": {
    "iso:country": "GB",
    "wof:name": "CW9 8SP",
    "wof:placetype": "postalcode"
  },
  "geometry": {"coordinates":[-2.513748,53.23129],"type":"Point"}
}
