{
  "type": "Feature",
  "properties": {
    "date:inception_lower":"2018-10-01",
    "date:inception_upper":"2018-10-31",
    "iso:country":"GB",
    "wof:name":"CW9 8SP",
    "wof:placetype":"postalcode"
},
  "geometry": {"coordinates":[-2.513361,53.231417],"type":"Point"}
}