{
  "type": "Feature",
  "properties": {
    "iso:country": "GB",
    "wof:name": "CW9 8SP",
    "wof:placetype": "postalcode"
  },
  "geometry": {"coordinates":[-2.513361,53.231417],"type":"Point"}
}
