{
  "type": "Feature",
  "properties": {
    "iso:country":"GB",
    "wof:name":"B63 4JN",
    "wof:placetype":"postalcode"
},
  "geometry": {"coordinates":[-2.06464354412524,52.44293266723372],"type":"Point"}
}