{
  "type": "Feature",
  "properties": {
    "iso:country": "GB",
    "wof:name": "B63 4JN",
    "wof:placetype": "postalcode"
  },
  "geometry": {"coordinates":[-2.064652,52.442947],"type":"Point"}
}
