{
  "type": "Feature",
  "properties": {
    "iso:country": "GB",
    "wof:name": "EH28 8QR",
    "wof:placetype": "postalcode"
  },
  "geometry": {"coordinates":[-3.394492,55.934742],"type":"Point"}
}
