{
  "type": "Feature",
  "properties": {
    "iso:country": "GB",
    "wof:name": "SL6 9SB",
    "wof:placetype": "postalcode"
  },
  "geometry": {"coordinates":[-0.711685,51.560279],"type":"Point"}
}
