{
  "type": "Feature",
  "properties": {
    "iso:country": "GB",
    "wof:name": "BS25 1TH",
    "wof:placetype": "postalcode"
  },
  "geometry": {"coordinates":[-2.797098,51.314826],"type":"Point"}
}
