{
  "type": "Feature",
  "properties": {
    "iso:country": "GB",
    "wof:name": "WA4 2DS",
    "wof:placetype": "postalcode"
  },
  "geometry": {"coordinates":[-2.560648,53.377302],"type":"Point"}
}
