{
  "type": "Feature",
  "properties": {
    "iso:country":"GB",
    "wof:name":"WA4 2DS",
    "wof:placetype":"postalcode"
},
  "geometry": {"coordinates":[-2.56064778863878,53.37730214922712],"type":"Point"}
}