{
  "type": "Feature",
  "properties": {
    "date:inception_lower":"1980-01-01",
    "date:inception_upper":"1980-01-31",
    "iso:country":"GB",
    "wof:name":"TF10 7TU",
    "wof:placetype":"postalcode"
},
  "geometry": {"coordinates":[-2.384562,52.76434],"type":"Point"}
}