{
  "type": "Feature",
  "properties": {
    "date:inception_lower": "2022-02-01",
    "date:inception_upper": "2022-02-01",
    "iso:country": "GB",
    "wof:name": "PE6 0GW",
    "wof:placetype": "postalcode"
  },
  "geometry": {"coordinates":[-0.161874,52.672822],"type":"Point"}
}
