{
  "type": "Feature",
  "properties": {
    "date:inception_lower": "2004-05-01",
    "date:inception_upper": "2004-05-01",
    "iso:country": "GB",
    "wof:name": "BB3 1LU",
    "wof:placetype": "postalcode"
  },
  "geometry": {"coordinates":[-2.472134,53.69555],"type":"Point"}
}
