{
  "type": "Feature",
  "properties": {
    "iso:country":"GB",
    "wof:name":"TA8 2DN",
    "wof:placetype":"postalcode"
},
  "geometry": {"coordinates":[-2.99246149967977,51.24232637462924],"type":"Point"}
}