{
  "type": "Feature",
  "properties": {
    "date:inception_lower":"1990-08-01",
    "date:inception_upper":"1990-08-31",
    "iso:country":"GB",
    "wof:name":"AB56 1NN",
    "wof:placetype":"postalcode"
},
  "geometry": {"coordinates":[-2.954472,57.676718],"type":"Point"}
}