{
  "type": "Feature",
  "properties": {
    "iso:country":"GB",
    "wof:name":"AB56 1NN",
    "wof:placetype":"postalcode"
},
  "geometry": {"coordinates":[-2.95447166270057,57.67671780780378],"type":"Point"}
}