{
  "type": "Feature",
  "properties": {
    "iso:country": "GB",
    "wof:name": "AB56 1NN",
    "wof:placetype": "postalcode"
  },
  "geometry": {"coordinates":[-2.954472,57.676718],"type":"Point"}
}
