{
  "type": "Feature",
  "properties": {
    "iso:country":"GB",
    "wof:name":"PE6 8RR",
    "wof:placetype":"postalcode"
},
  "geometry": {"coordinates":[-0.28111773127444,52.67729760900427],"type":"Point"}
}