{
  "type": "Feature",
  "properties": {
    "date:inception_lower": "1980-01-01",
    "date:inception_upper": "1980-01-01",
    "iso:country": "GB",
    "wof:name": "BS3 3PF",
    "wof:placetype": "postalcode"
  },
  "geometry": {"coordinates":[-2.605033,51.436281],"type":"Point"}
}
