{
  "type": "Feature",
  "properties": {
    "iso:country": "GB",
    "wof:name": "EX35 6LQ",
    "wof:placetype": "postalcode"
  },
  "geometry": {"coordinates":[-3.798471,51.208244],"type":"Point"}
}
