{
  "type": "Feature",
  "properties": {
    "date:inception_lower": "1980-01-01",
    "date:inception_upper": "1980-01-01",
    "iso:country": "GB",
    "wof:name": "CM11 2BD",
    "wof:placetype": "postalcode"
  },
  "geometry": {"coordinates":[0.425231,51.625868],"type":"Point"}
}
