{
  "type": "Feature",
  "properties": {
    "iso:country":"GB",
    "wof:name":"BB9 9NP",
    "wof:placetype":"postalcode"
},
  "geometry": {"coordinates":[-2.19660748131494,53.83576215243129],"type":"Point"}
}