{
  "type": "Feature",
  "properties": {
    "date:inception_lower": "1980-01-01",
    "date:inception_upper": "1980-01-01",
    "iso:country": "GB",
    "wof:name": "BB9 9NP",
    "wof:placetype": "postalcode"
  },
  "geometry": {"coordinates":[-2.196609,53.835758],"type":"Point"}
}
