{
  "type": "Feature",
  "properties": {
    "iso:country":"GB",
    "wof:name":"YO31 7ED",
    "wof:placetype":"postalcode"
},
  "geometry": {"coordinates":[-1.07460061494698,53.96637929673986],"type":"Point"}
}