{
  "type": "Feature",
  "properties": {
    "iso:country": "GB",
    "wof:name": "SG12 7AA",
    "wof:placetype": "postalcode"
  },
  "geometry": {"coordinates":[-0.027078,51.809765],"type":"Point"}
}
