{
  "type": "Feature",
  "properties": {
    "iso:country":"GB",
    "wof:name":"GU21 6JJ",
    "wof:placetype":"postalcode"
},
  "geometry": {"coordinates":[-0.55719630872663,51.32098842692786],"type":"Point"}
}