{
  "type": "Feature",
  "properties": {
    "date:inception_lower": "1980-01-01",
    "date:inception_upper": "1980-01-01",
    "iso:country": "GB",
    "wof:name": "DD9 6AS",
    "wof:placetype": "postalcode"
  },
  "geometry": {"coordinates":[-2.657799,56.732716],"type":"Point"}
}
