{
  "type": "Feature",
  "properties": {
    "iso:country": "GB",
    "wof:name": "DD9 6AS",
    "wof:placetype": "postalcode"
  },
  "geometry": {"coordinates":[-2.657799,56.732716],"type":"Point"}
}
