{
  "type": "Feature",
  "properties": {
    "iso:country":"GB",
    "wof:name":"WA8 8TF",
    "wof:placetype":"postalcode"
},
  "geometry": {"coordinates":[-2.76225787693365,53.36217104643286],"type":"Point"}
}