{
  "type": "Feature",
  "properties": {
    "date:inception_lower":"2003-06-01",
    "date:inception_upper":"2003-06-30",
    "iso:country":"GB",
    "wof:name":"FK2 9GB",
    "wof:placetype":"postalcode"
},
  "geometry": {"coordinates":[-3.776629,56.011747],"type":"Point"}
}