{
  "type": "Feature",
  "properties": {
    "iso:country":"GB",
    "wof:name":"DN8 5SJ",
    "wof:placetype":"postalcode"
},
  "geometry": {"coordinates":[-0.89430198074029,53.58746494481164],"type":"Point"}
}