{
  "type": "Feature",
  "properties": {
    "iso:country": "GB",
    "wof:name": "DN8 5SJ",
    "wof:placetype": "postalcode"
  },
  "geometry": {"coordinates":[-0.894302,53.587465],"type":"Point"}
}
