{
  "type": "Feature",
  "properties": {
    "date:inception_lower":"1993-01-01",
    "date:inception_upper":"1993-01-31",
    "iso:country":"GB",
    "wof:name":"L23 1UW",
    "wof:placetype":"postalcode"
},
  "geometry": {"coordinates":[-2.997206,53.498553],"type":"Point"}
}