{
  "type": "Feature",
  "properties": {
    "iso:country":"GB",
    "wof:name":"CF45 3UB",
    "wof:placetype":"postalcode"
},
  "geometry": {"coordinates":[-3.37450201939233,51.67839210575496],"type":"Point"}
}