{
  "type": "Feature",
  "properties": {
    "iso:country":"GB",
    "wof:name":"SE7 7LF",
    "wof:placetype":"postalcode"
},
  "geometry": {"coordinates":[0.02628615351834,51.48286885959592],"type":"Point"}
}