{
  "type": "Feature",
  "properties": {
    "iso:country":"GB",
    "wof:name":"EN3 5RF",
    "wof:placetype":"postalcode"
},
  "geometry": {"coordinates":[-0.04495217301966,51.66845221466485],"type":"Point"}
}