{
  "type": "Feature",
  "properties": {
    "date:inception_lower": "1980-01-01",
    "date:inception_upper": "1980-01-01",
    "iso:country": "GB",
    "wof:name": "TN14 6QN",
    "wof:placetype": "postalcode"
  },
  "geometry": {"coordinates":[0.19119,51.236808],"type":"Point"}
}
