{
  "type": "Feature",
  "properties": {
    "iso:country":"GB",
    "wof:name":"TS21 1DN",
    "wof:placetype":"postalcode"
},
  "geometry": {"coordinates":[-1.41353814160065,54.54199789194541],"type":"Point"}
}