{
  "type": "Feature",
  "properties": {
    "iso:country":"GB",
    "wof:name":"KY12 8XP",
    "wof:placetype":"postalcode"
},
  "geometry": {"coordinates":[-3.49536182528192,56.05842162070991],"type":"Point"}
}