{
  "type": "Feature",
  "properties": {
    "iso:country":"GB",
    "wof:name":"LA2 8RG",
    "wof:placetype":"postalcode"
},
  "geometry": {"coordinates":[-2.60597532444942,54.10251770834578],"type":"Point"}
}