{
  "type": "Feature",
  "properties": {
    "iso:country": "GB",
    "wof:name": "LA2 8RG",
    "wof:placetype": "postalcode"
  },
  "geometry": {"coordinates":[-2.605975,54.102518],"type":"Point"}
}
