{
  "type": "Feature",
  "properties": {
    "iso:country":"GB",
    "wof:name":"DH1 5PG",
    "wof:placetype":"postalcode"
},
  "geometry": {"coordinates":[-1.57359488580556,54.8025546424202],"type":"Point"}
}