{
  "type": "Feature",
  "properties": {
    "iso:country":"GB",
    "wof:name":"TF7 5HN",
    "wof:placetype":"postalcode"
},
  "geometry": {"coordinates":[-2.46511948012896,52.63735039197422],"type":"Point"}
}