{
  "type": "Feature",
  "properties": {
    "date:inception_lower": "1987-04-01",
    "date:inception_upper": "1987-04-01",
    "iso:country": "GB",
    "wof:name": "BS16 2TT",
    "wof:placetype": "postalcode"
  },
  "geometry": {"coordinates":[-2.514055,51.490143],"type":"Point"}
}
