{
  "type": "Feature",
  "properties": {
    "iso:country": "GB",
    "wof:name": "RH13 8GQ",
    "wof:placetype": "postalcode"
  },
  "geometry": {"coordinates":[-0.375148,51.007689],"type":"Point"}
}
