{
  "type": "Feature",
  "properties": {
    "iso:country":"GB",
    "wof:name":"RH13 8GQ",
    "wof:placetype":"postalcode"
},
  "geometry": {"coordinates":[-0.37514759503043,51.00768889204238],"type":"Point"}
}