{
  "type": "Feature",
  "properties": {
    "iso:country":"GB",
    "wof:name":"WN2 4HA",
    "wof:placetype":"postalcode"
},
  "geometry": {"coordinates":[-2.5478797226732,53.52887322568666],"type":"Point"}
}