{
  "type": "Feature",
  "properties": {
    "iso:country":"GB",
    "wof:name":"B76 1XW",
    "wof:placetype":"postalcode"
},
  "geometry": {"coordinates":[-1.78660987266203,52.53359302510319],"type":"Point"}
}