{
  "type": "Feature",
  "properties": {
    "date:inception_lower": "1993-08-01",
    "date:inception_upper": "1993-08-01",
    "iso:country": "GB",
    "wof:name": "B76 1XW",
    "wof:placetype": "postalcode"
  },
  "geometry": {"coordinates":[-1.78661,52.533593],"type":"Point"}
}
