{
  "type": "Feature",
  "properties": {
    "iso:country": "GB",
    "wof:name": "PR5 6FX",
    "wof:placetype": "postalcode"
  },
  "geometry": {"coordinates":[-2.664567,53.7251],"type":"Point"}
}
