{
  "type": "Feature",
  "properties": {
    "iso:country":"GB",
    "wof:name":"PR5 6FX",
    "wof:placetype":"postalcode"
},
  "geometry": {"coordinates":[-2.66456654958114,53.72510022631224],"type":"Point"}
}