{
  "type": "Feature",
  "properties": {
    "date:inception_lower": "1997-12-01",
    "date:inception_upper": "1997-12-01",
    "iso:country": "GB",
    "wof:name": "BS32 4PA",
    "wof:placetype": "postalcode"
  },
  "geometry": {"coordinates":[-2.563341,51.581028],"type":"Point"}
}
