{
  "type": "Feature",
  "properties": {
    "iso:country":"GB",
    "wof:name":"BS32 4PA",
    "wof:placetype":"postalcode"
},
  "geometry": {"coordinates":[-2.56334094152322,51.58102795099148],"type":"Point"}
}