{
  "type": "Feature",
  "properties": {
    "iso:country": "GB",
    "wof:name": "NE30 3PD",
    "wof:placetype": "postalcode"
  },
  "geometry": {"coordinates":[-1.432087,55.02598],"type":"Point"}
}
