{
  "type": "Feature",
  "properties": {
    "iso:country":"GB",
    "wof:name":"EC2A 2BG",
    "wof:placetype":"postalcode"
},
  "geometry": {"coordinates":[-0.08195926787611,51.52210766065286],"type":"Point"}
}