{
  "type": "Feature",
  "properties": {
    "iso:country":"GB",
    "wof:name":"SN2 7QH",
    "wof:placetype":"postalcode"
},
  "geometry": {"coordinates":[-1.76691715554191,51.58763490440506],"type":"Point"}
}