{
  "type": "Feature",
  "properties": {
    "date:inception_lower": "2016-12-01",
    "date:inception_upper": "2016-12-01",
    "iso:country": "GB",
    "wof:name": "KY5 9JQ",
    "wof:placetype": "postalcode"
  },
  "geometry": {"coordinates":[-3.307759,56.127326],"type":"Point"}
}
