{
  "type": "Feature",
  "properties": {
    "iso:country": "GB",
    "wof:name": "KY5 9JQ",
    "wof:placetype": "postalcode"
  },
  "geometry": {"coordinates":[-3.307759,56.127326],"type":"Point"}
}
