{
  "type": "Feature",
  "properties": {
    "iso:country": "GB",
    "wof:name": "WR1 3PR",
    "wof:placetype": "postalcode"
  },
  "geometry": {"coordinates":[-2.220957,52.192995],"type":"Point"}
}
