{
  "type": "Feature",
  "properties": {
    "date:inception_lower":"1983-07-01",
    "date:inception_upper":"1983-07-31",
    "iso:country":"GB",
    "wof:name":"WR1 3PR",
    "wof:placetype":"postalcode"
},
  "geometry": {"coordinates":[-2.220957,52.192995],"type":"Point"}
}