{
  "type": "Feature",
  "properties": {
    "date:inception_lower": "1980-01-01",
    "date:inception_upper": "1980-01-01",
    "iso:country": "GB",
    "wof:name": "BN3 5HW",
    "wof:placetype": "postalcode"
  },
  "geometry": {"coordinates":[-0.191186,50.835804],"type":"Point"}
}
