{
  "type": "Feature",
  "properties": {
    "iso:country":"GB",
    "wof:name":"ZE1 0QH",
    "wof:placetype":"postalcode"
},
  "geometry": {"coordinates":[-1.16932779203643,60.16132710252793],"type":"Point"}
}