{
  "type": "Feature",
  "properties": {
    "date:inception_lower":"1980-01-01",
    "date:inception_upper":"1980-01-31",
    "iso:country":"GB",
    "wof:name":"SE26 6TT",
    "wof:placetype":"postalcode"
},
  "geometry": {"coordinates":[-0.067662,51.433116],"type":"Point"}
}