{
  "type": "Feature",
  "properties": {
    "iso:country":"GB",
    "wof:name":"SE26 6TT",
    "wof:placetype":"postalcode"
},
  "geometry": {"coordinates":[-0.06766218815051,51.43311563330025],"type":"Point"}
}