{
  "type": "Feature",
  "properties": {
    "iso:country": "GB",
    "wof:name": "CV3 5AS",
    "wof:placetype": "postalcode"
  },
  "geometry": {"coordinates":[-1.496519,52.38481],"type":"Point"}
}
