{
  "type": "Feature",
  "properties": {
    "iso:country":"GB",
    "wof:name":"CV3 5AS",
    "wof:placetype":"postalcode"
},
  "geometry": {"coordinates":[-1.49651865462686,52.38481049806553],"type":"Point"}
}