{
  "type": "Feature",
  "properties": {
    "iso:country":"GB",
    "wof:name":"DN3 2LX",
    "wof:placetype":"postalcode"
},
  "geometry": {"coordinates":[-1.0683649130491,53.55443914135437],"type":"Point"}
}