{
  "type": "Feature",
  "properties": {
    "date:inception_lower":"2006-09-01",
    "date:inception_upper":"2006-09-30",
    "iso:country":"GB",
    "wof:name":"TS12 2GZ",
    "wof:placetype":"postalcode"
},
  "geometry": {"coordinates":[-0.981565,54.562779],"type":"Point"}
}