{
  "type": "Feature",
  "properties": {
    "iso:country": "GB",
    "wof:name": "BN22 8BL",
    "wof:placetype": "postalcode"
  },
  "geometry": {"coordinates":[0.291499,50.773681],"type":"Point"}
}
