{
  "type": "Feature",
  "properties": {
    "iso:country": "GB",
    "wof:name": "SK10 3RL",
    "wof:placetype": "postalcode"
  },
  "geometry": {"coordinates":[-2.164637,53.265275],"type":"Point"}
}
