{
  "type": "Feature",
  "properties": {
    "iso:country":"GB",
    "wof:name":"SK10 3RL",
    "wof:placetype":"postalcode"
},
  "geometry": {"coordinates":[-2.16463723235739,53.26527546523121],"type":"Point"}
}