{
  "type": "Feature",
  "properties": {
    "iso:country":"GB",
    "wof:name":"TS20 1TU",
    "wof:placetype":"postalcode"
},
  "geometry": {"coordinates":[-1.32615529335254,54.59293958084085],"type":"Point"}
}