{
  "type": "Feature",
  "properties": {
    "date:inception_lower":"1995-12-01",
    "date:inception_upper":"1995-12-31",
    "iso:country":"GB",
    "wof:name":"TS20 1TU",
    "wof:placetype":"postalcode"
},
  "geometry": {"coordinates":[-1.326155,54.59294],"type":"Point"}
}