{
  "type": "Feature",
  "properties": {
    "iso:country":"GB",
    "wof:name":"CT17 9JN",
    "wof:placetype":"postalcode"
},
  "geometry": {"coordinates":[1.29135153079928,51.12000260852925],"type":"Point"}
}