{
  "type": "Feature",
  "properties": {
    "iso:country":"GB",
    "wof:name":"TN6 2LF",
    "wof:placetype":"postalcode"
},
  "geometry": {"coordinates":[0.16713388297456,51.04961991099333],"type":"Point"}
}