{
  "type": "Feature",
  "properties": {
    "date:inception_lower":"1980-01-01",
    "date:inception_upper":"1980-01-31",
    "iso:country":"GB",
    "wof:name":"GU27 1EU",
    "wof:placetype":"postalcode"
},
  "geometry": {"coordinates":[-0.7286,51.092329],"type":"Point"}
}