{
  "type": "Feature",
  "properties": {
    "iso:country":"GB",
    "wof:name":"GU27 1EU",
    "wof:placetype":"postalcode"
},
  "geometry": {"coordinates":[-0.72859987513787,51.09232851956885],"type":"Point"}
}