{
  "type": "Feature",
  "properties": {
    "iso:country": "GB",
    "wof:name": "ME16 0TT",
    "wof:placetype": "postalcode"
  },
  "geometry": {"coordinates":[0.504612,51.290625],"type":"Point"}
}
