{
  "type": "Feature",
  "properties": {
    "iso:country":"GB",
    "wof:name":"ME16 0TT",
    "wof:placetype":"postalcode"
},
  "geometry": {"coordinates":[0.50461179453249,51.29062487530249],"type":"Point"}
}