{
  "type": "Feature",
  "properties": {
    "iso:country":"GB",
    "wof:name":"G13 2NN",
    "wof:placetype":"postalcode"
},
  "geometry": {"coordinates":[-4.33287454088189,55.89991843236385],"type":"Point"}
}