{
  "type": "Feature",
  "properties": {
    "iso:country":"GB",
    "wof:name":"TN16 1HE",
    "wof:placetype":"postalcode"
},
  "geometry": {"coordinates":[0.07248030315194,51.26854182335271],"type":"Point"}
}