{
  "type": "Feature",
  "properties": {
    "date:inception_lower": "2000-06-01",
    "date:inception_upper": "2000-06-01",
    "iso:country": "GB",
    "wof:name": "TN16 1HE",
    "wof:placetype": "postalcode"
  },
  "geometry": {"coordinates":[0.07248,51.268542],"type":"Point"}
}
