{
  "type": "Feature",
  "properties": {
    "iso:country":"GB",
    "wof:name":"BS4 1PG",
    "wof:placetype":"postalcode"
},
  "geometry": {"coordinates":[-2.59056311681314,51.42867589979223],"type":"Point"}
}