{
  "type": "Feature",
  "properties": {
    "iso:country": "GB",
    "wof:name": "BS4 1PG",
    "wof:placetype": "postalcode"
  },
  "geometry": {"coordinates":[-2.590563,51.428676],"type":"Point"}
}
