{
  "type": "Feature",
  "properties": {
    "iso:country":"GB",
    "wof:name":"BH23 5SQ",
    "wof:placetype":"postalcode"
},
  "geometry": {"coordinates":[-1.69652978026868,50.7512000406153],"type":"Point"}
}