{
  "type": "Feature",
  "properties": {
    "date:inception_lower": "1981-06-01",
    "date:inception_upper": "1981-06-01",
    "iso:country": "GB",
    "wof:name": "BH23 5SQ",
    "wof:placetype": "postalcode"
  },
  "geometry": {"coordinates":[-1.69653,50.7512],"type":"Point"}
}
