{
  "type": "Feature",
  "properties": {
    "iso:country":"GB",
    "wof:name":"NP12 0EW",
    "wof:placetype":"postalcode"
},
  "geometry": {"coordinates":[-3.18135970805577,51.67908227405241],"type":"Point"}
}