{
  "type": "Feature",
  "properties": {
    "date:inception_lower": "2010-09-01",
    "date:inception_upper": "2010-09-01",
    "iso:country": "GB",
    "wof:name": "NP12 0EW",
    "wof:placetype": "postalcode"
  },
  "geometry": {"coordinates":[-3.18136,51.679082],"type":"Point"}
}
