{
  "type": "Feature",
  "properties": {
    "iso:country":"GB",
    "wof:name":"MK13 8BH",
    "wof:placetype":"postalcode"
},
  "geometry": {"coordinates":[-0.76859103350996,52.04333670241984],"type":"Point"}
}