{
  "type": "Feature",
  "properties": {
    "date:inception_lower": "1990-07-01",
    "date:inception_upper": "1990-07-01",
    "iso:country": "GB",
    "wof:name": "MK18 2SA",
    "wof:placetype": "postalcode"
  },
  "geometry": {"coordinates":[-0.986382,51.938957],"type":"Point"}
}
