{
  "type": "Feature",
  "properties": {
    "iso:country":"GB",
    "wof:name":"MK18 2SA",
    "wof:placetype":"postalcode"
},
  "geometry": {"coordinates":[-0.98638237852228,51.93895704147451],"type":"Point"}
}