{
  "type": "Feature",
  "properties": {
    "iso:country":"GB",
    "wof:name":"SY1 3ET",
    "wof:placetype":"postalcode"
},
  "geometry": {"coordinates":[-2.74123687721053,52.73298954698389],"type":"Point"}
}