{
  "type": "Feature",
  "properties": {
    "date:inception_lower": "1980-01-01",
    "date:inception_upper": "1980-01-01",
    "iso:country": "GB",
    "wof:name": "SY1 3ET",
    "wof:placetype": "postalcode"
  },
  "geometry": {"coordinates":[-2.741237,52.73299],"type":"Point"}
}
