{
  "type": "Feature",
  "properties": {
    "iso:country":"GB",
    "wof:name":"RG31 4TJ",
    "wof:placetype":"postalcode"
},
  "geometry": {"coordinates":[-1.05525784591505,51.44912731159613],"type":"Point"}
}