{
  "type": "Feature",
  "properties": {
    "date:inception_lower": "1995-07-01",
    "date:inception_upper": "1995-07-01",
    "iso:country": "GB",
    "wof:name": "RG31 4TJ",
    "wof:placetype": "postalcode"
  },
  "geometry": {"coordinates":[-1.055258,51.449127],"type":"Point"}
}
