{
  "type": "Feature",
  "properties": {
    "iso:country": "GB",
    "wof:name": "NE1 3HB",
    "wof:placetype": "postalcode"
  },
  "geometry": {"coordinates":[-1.605991,54.969514],"type":"Point"}
}
