{
  "type": "Feature",
  "properties": {
    "iso:country":"GB",
    "wof:name":"NE1 3HB",
    "wof:placetype":"postalcode"
},
  "geometry": {"coordinates":[-1.6059912438186,54.96951446865742],"type":"Point"}
}