{
  "type": "Feature",
  "properties": {
    "iso:country": "GB",
    "wof:name": "DH3 1PE",
    "wof:placetype": "postalcode"
  },
  "geometry": {"coordinates":[-1.577166,54.897069],"type":"Point"}
}
