{
  "type": "Feature",
  "properties": {
    "date:inception_lower":"1985-10-01",
    "date:inception_upper":"1985-10-31",
    "iso:country":"GB",
    "wof:name":"DH3 1PE",
    "wof:placetype":"postalcode"
},
  "geometry": {"coordinates":[-1.577166,54.897069],"type":"Point"}
}