{
  "type": "Feature",
  "properties": {
    "iso:country":"GB",
    "wof:name":"FK8 1XL",
    "wof:placetype":"postalcode"
},
  "geometry": {"coordinates":[-3.92584378786696,56.12892760483392],"type":"Point"}
}