{
  "type": "Feature",
  "properties": {
    "iso:country":"GB",
    "wof:name":"G61 3BP",
    "wof:placetype":"postalcode"
},
  "geometry": {"coordinates":[-4.33383484014324,55.92601812089259],"type":"Point"}
}