{
  "type": "Feature",
  "properties": {
    "iso:country": "GB",
    "wof:name": "SG4 7DT",
    "wof:placetype": "postalcode"
  },
  "geometry": {"coordinates":[-0.151269,51.939397],"type":"Point"}
}
