{
  "type": "Feature",
  "properties": {
    "date:inception_lower": "2015-07-01",
    "date:inception_upper": "2015-07-01",
    "iso:country": "GB",
    "wof:name": "S8 2DG",
    "wof:placetype": "postalcode"
  },
  "geometry": {"coordinates":[-1.484509,53.350839],"type":"Point"}
}
