{
  "type": "Feature",
  "properties": {
    "iso:country":"GB",
    "wof:name":"CV37 8UA",
    "wof:placetype":"postalcode"
},
  "geometry": {"coordinates":[-1.64001226822123,52.11416718166926],"type":"Point"}
}