{
  "type": "Feature",
  "properties": {
    "iso:country": "GB",
    "wof:name": "ME1 1FH",
    "wof:placetype": "postalcode"
  },
  "geometry": {"coordinates":[0.511931,51.385225],"type":"Point"}
}
