{
  "type": "Feature",
  "properties": {
    "iso:country":"GB",
    "wof:name":"ME1 1FH",
    "wof:placetype":"postalcode"
},
  "geometry": {"coordinates":[0.5119309534139,51.38522464387565],"type":"Point"}
}