{
  "type": "Feature",
  "properties": {
    "date:inception_lower":"2013-04-01",
    "date:inception_upper":"2013-04-30",
    "iso:country":"GB",
    "wof:name":"ME1 1FH",
    "wof:placetype":"postalcode"
},
  "geometry": {"coordinates":[0.511931,51.385225],"type":"Point"}
}