{
  "type": "Feature",
  "properties": {
    "iso:country":"GB",
    "wof:name":"BB5 5DE",
    "wof:placetype":"postalcode"
},
  "geometry": {"coordinates":[-2.36886283079474,53.75960490087002],"type":"Point"}
}