{
  "type": "Feature",
  "properties": {
    "date:inception_lower":"2012-08-01",
    "date:inception_upper":"2012-08-31",
    "iso:country":"GB",
    "wof:name":"BB5 5DE",
    "wof:placetype":"postalcode"
},
  "geometry": {"coordinates":[-2.368863,53.759605],"type":"Point"}
}