{
  "type": "Feature",
  "properties": {
    "date:inception_lower": "1980-01-01",
    "date:inception_upper": "1980-01-01",
    "iso:country": "GB",
    "wof:name": "CO2 8ND",
    "wof:placetype": "postalcode"
  },
  "geometry": {"coordinates":[0.901152,51.864932],"type":"Point"}
}
