{
  "type": "Feature",
  "properties": {
    "iso:country":"GB",
    "wof:name":"CO2 8ND",
    "wof:placetype":"postalcode"
},
  "geometry": {"coordinates":[0.90115237442623,51.86493164549532],"type":"Point"}
}