{
  "type": "Feature",
  "properties": {
    "iso:country":"GB",
    "wof:name":"DE13 8RG",
    "wof:placetype":"postalcode"
},
  "geometry": {"coordinates":[-1.80036120709658,52.80716399397672],"type":"Point"}
}