{
  "type": "Feature",
  "properties": {
    "iso:country":"GB",
    "wof:name":"CV9 3NZ",
    "wof:placetype":"postalcode"
},
  "geometry": {"coordinates":[-1.52049661690004,52.59349669451018],"type":"Point"}
}