{
  "type": "Feature",
  "properties": {
    "iso:country": "GB",
    "wof:name": "WF10 5AG",
    "wof:placetype": "postalcode"
  },
  "geometry": {"coordinates":[-1.353698,53.720134],"type":"Point"}
}
