{
  "type": "Feature",
  "properties": {
    "iso:country": "GB",
    "wof:name": "GL7 6PY",
    "wof:placetype": "postalcode"
  },
  "geometry": {"coordinates":[-1.995785,51.705552],"type":"Point"}
}
