{
  "type": "Feature",
  "properties": {
    "iso:country":"GB",
    "wof:name":"GL7 6PY",
    "wof:placetype":"postalcode"
},
  "geometry": {"coordinates":[-1.99578467700384,51.70555202795935],"type":"Point"}
}