{
  "type": "Feature",
  "properties": {
    "iso:country":"GB",
    "wof:name":"SK6 2BR",
    "wof:placetype":"postalcode"
},
  "geometry": {"coordinates":[-2.11528512704933,53.42196967227137],"type":"Point"}
}