{
  "type": "Feature",
  "properties": {
    "iso:country":"GB",
    "wof:name":"IG7 6BX",
    "wof:placetype":"postalcode"
},
  "geometry": {"coordinates":[0.09313777907663,51.6407578191719],"type":"Point"}
}