{
  "type": "Feature",
  "properties": {
    "iso:country": "GB",
    "wof:name": "IG7 6BX",
    "wof:placetype": "postalcode"
  },
  "geometry": {"coordinates":[0.093208,51.640759],"type":"Point"}
}
