{
  "type": "Feature",
  "properties": {
    "iso:country": "GB",
    "wof:name": "PE9 1LS",
    "wof:placetype": "postalcode"
  },
  "geometry": {"coordinates":[-0.481337,52.658203],"type":"Point"}
}
