{
  "type": "Feature",
  "properties": {
    "date:inception_lower": "1980-01-01",
    "date:inception_upper": "1980-01-01",
    "iso:country": "GB",
    "wof:name": "B33 8PR",
    "wof:placetype": "postalcode"
  },
  "geometry": {"coordinates":[-1.810632,52.477051],"type":"Point"}
}
