{
  "type": "Feature",
  "properties": {
    "iso:country":"GB",
    "wof:name":"SW1V 2PS",
    "wof:placetype":"postalcode"
},
  "geometry": {"coordinates":[-0.13532284059052,51.49070296616451],"type":"Point"}
}