{
  "type": "Feature",
  "properties": {
    "iso:country":"GB",
    "wof:name":"TF9 1JH",
    "wof:placetype":"postalcode"
},
  "geometry": {"coordinates":[-2.47638398749415,52.9037572735462],"type":"Point"}
}