{
  "type": "Feature",
  "properties": {
    "date:inception_lower": "2000-06-01",
    "date:inception_upper": "2000-06-01",
    "iso:country": "GB",
    "wof:name": "SN5 3LU",
    "wof:placetype": "postalcode"
  },
  "geometry": {"coordinates":[-1.862189,51.570684],"type":"Point"}
}
