{
  "type": "Feature",
  "properties": {
    "iso:country":"GB",
    "wof:name":"WS12 1AG",
    "wof:placetype":"postalcode"
},
  "geometry": {"coordinates":[-1.99912850147516,52.70926463423291],"type":"Point"}
}