{
  "type": "Feature",
  "properties": {
    "iso:country": "GB",
    "wof:name": "SO14 0AU",
    "wof:placetype": "postalcode"
  },
  "geometry": {"coordinates":[-1.395348,50.911176],"type":"Point"}
}
