{
  "type": "Feature",
  "properties": {
    "date:inception_lower": "1980-01-01",
    "date:inception_upper": "1980-01-01",
    "iso:country": "GB",
    "wof:name": "LL13 9NE",
    "wof:placetype": "postalcode"
  },
  "geometry": {"coordinates":[-2.967618,53.053971],"type":"Point"}
}
