{
  "type": "Feature",
  "properties": {
    "iso:country":"GB",
    "wof:name":"CV6 1HJ",
    "wof:placetype":"postalcode"
},
  "geometry": {"coordinates":[-1.52377338899132,52.4203176213889],"type":"Point"}
}