{
  "type": "Feature",
  "properties": {
    "iso:country":"GB",
    "wof:name":"PE22 8DS",
    "wof:placetype":"postalcode"
},
  "geometry": {"coordinates":[0.03908153167481,53.10392691653287],"type":"Point"}
}