{
  "type": "Feature",
  "properties": {
    "iso:country": "GB",
    "wof:name": "PE22 8DS",
    "wof:placetype": "postalcode"
  },
  "geometry": {"coordinates":[0.038576,53.10452],"type":"Point"}
}
