{
  "type": "Feature",
  "properties": {
    "date:inception_lower": "2017-04-01",
    "date:inception_upper": "2017-04-01",
    "iso:country": "GB",
    "wof:name": "G71 7WT",
    "wof:placetype": "postalcode"
  },
  "geometry": {"coordinates":[-4.104469,55.845372],"type":"Point"}
}
