{
  "type": "Feature",
  "properties": {
    "iso:country":"GB",
    "wof:name":"WS14 9AX",
    "wof:placetype":"postalcode"
},
  "geometry": {"coordinates":[-1.82481857995373,52.67510981646589],"type":"Point"}
}