{
  "type": "Feature",
  "properties": {
    "iso:country":"GB",
    "wof:name":"M33 4JQ",
    "wof:placetype":"postalcode"
},
  "geometry": {"coordinates":[-2.35044834908788,53.4128546718053],"type":"Point"}
}