{
  "type": "Feature",
  "properties": {
    "date:inception_lower":"1997-12-01",
    "date:inception_upper":"1997-12-31",
    "iso:country":"GB",
    "wof:name":"PR4 3EZ",
    "wof:placetype":"postalcode"
},
  "geometry": {"coordinates":[-2.848781,53.789497],"type":"Point"}
}