{
  "type": "Feature",
  "properties": {
    "iso:country":"GB",
    "wof:name":"PR4 3EZ",
    "wof:placetype":"postalcode"
},
  "geometry": {"coordinates":[-2.84878104717715,53.78949734370094],"type":"Point"}
}