{
  "type": "Feature",
  "properties": {
    "date:inception_lower": "1992-01-01",
    "date:inception_upper": "1992-01-01",
    "iso:country": "GB",
    "wof:name": "RG9 6NU",
    "wof:placetype": "postalcode"
  },
  "geometry": {"coordinates":[-0.858138,51.609014],"type":"Point"}
}
