{
  "type": "Feature",
  "properties": {
    "iso:country":"GB",
    "wof:name":"IV30 4HD",
    "wof:placetype":"postalcode"
},
  "geometry": {"coordinates":[-3.30822603347925,57.65628846985634],"type":"Point"}
}