{
  "type": "Feature",
  "properties": {
    "date:inception_lower":"1998-12-01",
    "date:inception_upper":"1998-12-31",
    "iso:country":"GB",
    "wof:name":"IV30 4HD",
    "wof:placetype":"postalcode"
},
  "geometry": {"coordinates":[-3.308226,57.656288],"type":"Point"}
}