{
  "type": "Feature",
  "properties": {
    "iso:country":"GB",
    "wof:name":"TA24 7AD",
    "wof:placetype":"postalcode"
},
  "geometry": {"coordinates":[-3.59850857991364,51.10752424634133],"type":"Point"}
}