{
  "type": "Feature",
  "properties": {
    "date:inception_lower": "1993-01-01",
    "date:inception_upper": "1993-01-01",
    "iso:country": "GB",
    "wof:name": "RH16 1UD",
    "wof:placetype": "postalcode"
  },
  "geometry": {"coordinates":[-0.106181,51.008356],"type":"Point"}
}
