{
  "type": "Feature",
  "properties": {
    "date:inception_lower": "2020-04-01",
    "date:inception_upper": "2020-04-01",
    "iso:country": "GB",
    "wof:name": "NN9 5GW",
    "wof:placetype": "postalcode"
  },
  "geometry": {"coordinates":[-0.614025,52.324395],"type":"Point"}
}
