{
  "type": "Feature",
  "properties": {
    "iso:country": "GB",
    "wof:name": "CV2 5HQ",
    "wof:placetype": "postalcode"
  },
  "geometry": {"coordinates":[-1.464019,52.41144],"type":"Point"}
}
