{
  "type": "Feature",
  "properties": {
    "iso:country":"GB",
    "wof:name":"CV2 5HQ",
    "wof:placetype":"postalcode"
},
  "geometry": {"coordinates":[-1.4640195402607,52.41144044547416],"type":"Point"}
}