{
  "type": "Feature",
  "properties": {
    "date:inception_lower":"2007-09-01",
    "date:inception_upper":"2007-09-30",
    "iso:country":"GB",
    "wof:name":"CV2 5HQ",
    "wof:placetype":"postalcode"
},
  "geometry": {"coordinates":[-1.464019,52.41144],"type":"Point"}
}