{
  "type": "Feature",
  "properties": {
    "iso:country":"GB",
    "wof:name":"TW10 5AY",
    "wof:placetype":"postalcode"
},
  "geometry": {"coordinates":[-0.28748126620879,51.46069598449112],"type":"Point"}
}