{
  "type": "Feature",
  "properties": {
    "date:inception_lower": "1995-07-01",
    "date:inception_upper": "1995-07-01",
    "iso:country": "GB",
    "wof:name": "RG20 5PR",
    "wof:placetype": "postalcode"
  },
  "geometry": {"coordinates":[-1.249528,51.322677],"type":"Point"}
}
