{
  "type": "Feature",
  "properties": {
    "date:inception_lower": "2007-05-01",
    "date:inception_upper": "2007-05-01",
    "iso:country": "GB",
    "wof:name": "PL26 8SH",
    "wof:placetype": "postalcode"
  },
  "geometry": {"coordinates":[-4.758965,50.341347],"type":"Point"}
}
