{
  "type": "Feature",
  "properties": {
    "iso:country":"GB",
    "wof:name":"DN14 8SN",
    "wof:placetype":"postalcode"
},
  "geometry": {"coordinates":[-0.94071753366849,53.68501618848295],"type":"Point"}
}