{
  "type": "Feature",
  "properties": {
    "iso:country":"GB",
    "wof:name":"G69 7EP",
    "wof:placetype":"postalcode"
},
  "geometry": {"coordinates":[-4.10829463821554,55.8494273526109],"type":"Point"}
}