{
  "type": "Feature",
  "properties": {
    "date:inception_lower":"1986-12-01",
    "date:inception_upper":"1986-12-31",
    "iso:country":"GB",
    "wof:name":"G69 7EP",
    "wof:placetype":"postalcode"
},
  "geometry": {"coordinates":[-4.108295,55.849427],"type":"Point"}
}