{
  "type": "Feature",
  "properties": {
    "iso:country":"GB",
    "wof:name":"SO14 2AE",
    "wof:placetype":"postalcode"
},
  "geometry": {"coordinates":[-1.40605341527745,50.89997183928008],"type":"Point"}
}