{
  "type": "Feature",
  "properties": {
    "iso:country":"GB",
    "wof:name":"YO21 1DP",
    "wof:placetype":"postalcode"
},
  "geometry": {"coordinates":[-0.61727882326575,54.48391079428097],"type":"Point"}
}