{
  "type": "Feature",
  "properties": {
    "iso:country":"GB",
    "wof:name":"E3 4QL",
    "wof:placetype":"postalcode"
},
  "geometry": {"coordinates":[-0.02974246689079,51.52491114233207],"type":"Point"}
}