{
  "type": "Feature",
  "properties": {
    "iso:country": "GB",
    "wof:name": "E3 4QL",
    "wof:placetype": "postalcode"
  },
  "geometry": {"coordinates":[-0.029742,51.524911],"type":"Point"}
}
