{
  "type": "Feature",
  "properties": {
    "iso:country": "GB",
    "wof:name": "DY12 3AG",
    "wof:placetype": "postalcode"
  },
  "geometry": {"coordinates":[-2.359839,52.398261],"type":"Point"}
}
