{
  "type": "Feature",
  "properties": {
    "iso:country":"GB",
    "wof:name":"ST3 6HZ",
    "wof:placetype":"postalcode"
},
  "geometry": {"coordinates":[-2.0899278158323,52.97875067685709],"type":"Point"}
}