{
  "type": "Feature",
  "properties": {
    "iso:country":"GB",
    "wof:name":"NP26 5RE",
    "wof:placetype":"postalcode"
},
  "geometry": {"coordinates":[-2.74589242820723,51.58552119963309],"type":"Point"}
}