{
  "type": "Feature",
  "properties": {
    "iso:country":"GB",
    "wof:name":"DY13 9AD",
    "wof:placetype":"postalcode"
},
  "geometry": {"coordinates":[-2.27487379697063,52.3411949433228],"type":"Point"}
}