{
  "type": "Feature",
  "properties": {
    "iso:country":"GB",
    "wof:name":"PO7 7AG",
    "wof:placetype":"postalcode"
},
  "geometry": {"coordinates":[-1.03600217706777,50.8775128346667],"type":"Point"}
}