{
  "type": "Feature",
  "properties": {
    "date:inception_lower": "2019-09-01",
    "date:inception_upper": "2019-09-01",
    "iso:country": "GB",
    "wof:name": "MK42 0YJ",
    "wof:placetype": "postalcode"
  },
  "geometry": {"coordinates":[-0.454456,52.121199],"type":"Point"}
}
