{
  "type": "Feature",
  "properties": {
    "iso:country": "GB",
    "wof:name": "MK42 0YJ",
    "wof:placetype": "postalcode"
  },
  "geometry": {"coordinates":[-0.454515,52.121182],"type":"Point"}
}
