{
  "type": "Feature",
  "properties": {
    "iso:country":"GB",
    "wof:name":"M19 2NW",
    "wof:placetype":"postalcode"
},
  "geometry": {"coordinates":[-2.2018322885011,53.43653285864097],"type":"Point"}
}