{
  "type": "Feature",
  "properties": {
    "iso:country":"GB",
    "wof:name":"B50 4NL",
    "wof:placetype":"postalcode"
},
  "geometry": {"coordinates":[-1.85568385772409,52.16546008719143],"type":"Point"}
}