{
  "type": "Feature",
  "properties": {
    "iso:country":"GB",
    "wof:name":"NG2 4FW",
    "wof:placetype":"postalcode"
},
  "geometry": {"coordinates":[-1.1225763023922,52.951151493746],"type":"Point"}
}