{
  "type": "Feature",
  "properties": {
    "iso:country": "GB",
    "wof:name": "NG2 4FW",
    "wof:placetype": "postalcode"
  },
  "geometry": {"coordinates":[-1.122576,52.951151],"type":"Point"}
}
