{
  "type": "Feature",
  "properties": {
    "iso:country":"GB",
    "wof:name":"CV35 7ND",
    "wof:placetype":"postalcode"
},
  "geometry": {"coordinates":[-1.68189157835437,52.34217560037514],"type":"Point"}
}