{
  "type": "Feature",
  "properties": {
    "iso:country":"GB",
    "wof:name":"SR8 3HL",
    "wof:placetype":"postalcode"
},
  "geometry": {"coordinates":[-1.34033957117009,54.78477833062073],"type":"Point"}
}