{
  "type": "Feature",
  "properties": {
    "iso:country":"GB",
    "wof:name":"E1W 2QW",
    "wof:placetype":"postalcode"
},
  "geometry": {"coordinates":[-0.06172668163119,51.50702720206515],"type":"Point"}
}