{
  "type": "Feature",
  "properties": {
    "iso:country":"GB",
    "wof:name":"BS24 0DN",
    "wof:placetype":"postalcode"
},
  "geometry": {"coordinates":[-2.95275599723629,51.28419989053115],"type":"Point"}
}