{
  "type": "Feature",
  "properties": {
    "date:inception_lower":"2000-10-01",
    "date:inception_upper":"2000-10-31",
    "iso:country":"GB",
    "wof:name":"W1W 6DP",
    "wof:placetype":"postalcode"
},
  "geometry": {"coordinates":[-0.140084,51.519528],"type":"Point"}
}