{
  "type": "Feature",
  "properties": {
    "iso:country":"GB",
    "wof:name":"W1W 6DP",
    "wof:placetype":"postalcode"
},
  "geometry": {"coordinates":[-0.14008431900606,51.5195276633506],"type":"Point"}
}