{
  "type": "Feature",
  "properties": {
    "date:inception_lower": "1980-01-01",
    "date:inception_upper": "1980-01-01",
    "iso:country": "GB",
    "wof:name": "NE25 0BA",
    "wof:placetype": "postalcode"
  },
  "geometry": {"coordinates":[-1.516541,55.070251],"type":"Point"}
}
