{
  "type": "Feature",
  "properties": {
    "iso:country": "GB",
    "wof:name": "NE25 0BA",
    "wof:placetype": "postalcode"
  },
  "geometry": {"coordinates":[-1.516541,55.070251],"type":"Point"}
}
