{
  "type": "Feature",
  "properties": {
    "iso:country":"GB",
    "wof:name":"NE25 0BA",
    "wof:placetype":"postalcode"
},
  "geometry": {"coordinates":[-1.51654082370239,55.07025118162748],"type":"Point"}
}