{
  "type": "Feature",
  "properties": {
    "iso:country": "GB",
    "wof:name": "L37 3AB",
    "wof:placetype": "postalcode"
  },
  "geometry": {"coordinates":[-3.062819,53.55849],"type":"Point"}
}
