{
  "type": "Feature",
  "properties": {
    "date:inception_lower": "1998-12-01",
    "date:inception_upper": "1998-12-01",
    "iso:country": "GB",
    "wof:name": "S40 2EZ",
    "wof:placetype": "postalcode"
  },
  "geometry": {"coordinates":[-1.422142,53.22898],"type":"Point"}
}
