{
  "type": "Feature",
  "properties": {
    "date:inception_lower":"1998-12-01",
    "date:inception_upper":"1998-12-31",
    "iso:country":"GB",
    "wof:name":"S40 2EZ",
    "wof:placetype":"postalcode"
},
  "geometry": {"coordinates":[-1.422965,53.229029],"type":"Point"}
}