{
  "type": "Feature",
  "properties": {
    "iso:country":"GB",
    "wof:name":"S6 1TX",
    "wof:placetype":"postalcode"
},
  "geometry": {"coordinates":[-1.5198433317714,53.41621663045468],"type":"Point"}
}