{
  "type": "Feature",
  "properties": {
    "iso:country": "GB",
    "wof:name": "S6 1TX",
    "wof:placetype": "postalcode"
  },
  "geometry": {"coordinates":[-1.519843,53.416217],"type":"Point"}
}
