{
  "type": "Feature",
  "properties": {
    "iso:country": "GB",
    "wof:name": "SG18 8UQ",
    "wof:placetype": "postalcode"
  },
  "geometry": {"coordinates":[-0.242675,52.087185],"type":"Point"}
}
