{
  "type": "Feature",
  "properties": {
    "date:inception_lower": "1980-01-01",
    "date:inception_upper": "1980-01-01",
    "iso:country": "GB",
    "wof:name": "LS16 9BP",
    "wof:placetype": "postalcode"
  },
  "geometry": {"coordinates":[-1.61401,53.882472],"type":"Point"}
}
