{
  "type": "Feature",
  "properties": {
    "iso:country":"GB",
    "wof:name":"LS16 9BP",
    "wof:placetype":"postalcode"
},
  "geometry": {"coordinates":[-1.61400964007287,53.88247227148882],"type":"Point"}
}