{
  "type": "Feature",
  "properties": {
    "iso:country": "GB",
    "wof:name": "TA10 9TJ",
    "wof:placetype": "postalcode"
  },
  "geometry": {"coordinates":[-2.818329,51.042635],"type":"Point"}
}
