{
  "type": "Feature",
  "properties": {
    "date:inception_lower":"1981-09-01",
    "date:inception_upper":"1981-09-30",
    "iso:country":"GB",
    "wof:name":"TA10 9TJ",
    "wof:placetype":"postalcode"
},
  "geometry": {"coordinates":[-2.818329,51.042635],"type":"Point"}
}