{
  "type": "Feature",
  "properties": {
    "date:inception_lower":"1999-12-01",
    "date:inception_upper":"1999-12-31",
    "iso:country":"GB",
    "wof:name":"CV47 2BX",
    "wof:placetype":"postalcode"
},
  "geometry": {"coordinates":[-1.3907,52.226793],"type":"Point"}
}