{
  "type": "Feature",
  "properties": {
    "iso:country":"GB",
    "wof:name":"BH1 4AH",
    "wof:placetype":"postalcode"
},
  "geometry": {"coordinates":[-1.84121543111093,50.72594732290302],"type":"Point"}
}