{
  "type": "Feature",
  "properties": {
    "iso:country": "GB",
    "wof:name": "PL14 6JZ",
    "wof:placetype": "postalcode"
  },
  "geometry": {"coordinates":[-4.527953,50.458021],"type":"Point"}
}
