{
  "type": "Feature",
  "properties": {
    "iso:country":"GB",
    "wof:name":"CA7 2JJ",
    "wof:placetype":"postalcode"
},
  "geometry": {"coordinates":[-3.27259555505461,54.73448081862453],"type":"Point"}
}