{
  "type": "Feature",
  "properties": {
    "iso:country":"GB",
    "wof:name":"PR3 2TX",
    "wof:placetype":"postalcode"
},
  "geometry": {"coordinates":[-2.58194902452556,53.84435297878679],"type":"Point"}
}