{
  "type": "Feature",
  "properties": {
    "date:inception_lower": "1980-01-01",
    "date:inception_upper": "1980-01-01",
    "iso:country": "GB",
    "wof:name": "PR3 2TX",
    "wof:placetype": "postalcode"
  },
  "geometry": {"coordinates":[-2.584349,53.846485],"type":"Point"}
}
