{
  "type": "Feature",
  "properties": {
    "iso:country": "GB",
    "wof:name": "RM20 3BB",
    "wof:placetype": "postalcode"
  },
  "geometry": {"coordinates":[0.276502,51.483305],"type":"Point"}
}
