{
  "type": "Feature",
  "properties": {
    "iso:country": "GB",
    "wof:name": "M18 8PD",
    "wof:placetype": "postalcode"
  },
  "geometry": {"coordinates":[-2.166547,53.46296],"type":"Point"}
}
