{
  "type": "Feature",
  "properties": {
    "iso:country":"GB",
    "wof:name":"M18 8PD",
    "wof:placetype":"postalcode"
},
  "geometry": {"coordinates":[-2.16654696809853,53.46295957761228],"type":"Point"}
}