{
  "type": "Feature",
  "properties": {
    "date:inception_lower":"1994-05-01",
    "date:inception_upper":"1994-05-31",
    "iso:country":"GB",
    "wof:name":"M18 8PD",
    "wof:placetype":"postalcode"
},
  "geometry": {"coordinates":[-2.166547,53.46296],"type":"Point"}
}