{
  "type": "Feature",
  "properties": {
    "iso:country":"GB",
    "wof:name":"LE12 8ER",
    "wof:placetype":"postalcode"
},
  "geometry": {"coordinates":[-1.17889011655774,52.74134884788656],"type":"Point"}
}