{
  "type": "Feature",
  "properties": {
    "date:inception_lower":"1980-01-01",
    "date:inception_upper":"1980-01-31",
    "iso:country":"GB",
    "wof:name":"LE12 8ER",
    "wof:placetype":"postalcode"
},
  "geometry": {"coordinates":[-1.17889,52.741349],"type":"Point"}
}