{
  "type": "Feature",
  "properties": {
    "iso:country": "GB",
    "wof:name": "CV21 3SS",
    "wof:placetype": "postalcode"
  },
  "geometry": {"coordinates":[-1.252585,52.371409],"type":"Point"}
}
