{
  "type": "Feature",
  "properties": {
    "iso:country":"GB",
    "wof:name":"CV21 3SS",
    "wof:placetype":"postalcode"
},
  "geometry": {"coordinates":[-1.25256871626855,52.37136534312804],"type":"Point"}
}