{
  "type": "Feature",
  "properties": {
    "iso:country": "GB",
    "wof:name": "GU6 7RT",
    "wof:placetype": "postalcode"
  },
  "geometry": {"coordinates":[-0.439549,51.147713],"type":"Point"}
}
