{
  "type": "Feature",
  "properties": {
    "date:inception_lower": "2021-11-01",
    "date:inception_upper": "2021-11-01",
    "iso:country": "GB",
    "wof:name": "LE13 0TQ",
    "wof:placetype": "postalcode"
  },
  "geometry": {"coordinates":[-0.902448,52.782151],"type":"Point"}
}
