{
  "type": "Feature",
  "properties": {
    "iso:country":"GB",
    "wof:name":"YO8 8LU",
    "wof:placetype":"postalcode"
},
  "geometry": {"coordinates":[-0.98215163409543,53.72871800316211],"type":"Point"}
}