{
  "type": "Feature",
  "properties": {
    "date:inception_lower": "2005-04-01",
    "date:inception_upper": "2005-04-01",
    "iso:country": "GB",
    "wof:name": "YO8 8LU",
    "wof:placetype": "postalcode"
  },
  "geometry": {"coordinates":[-0.982152,53.728718],"type":"Point"}
}
