{
  "type": "Feature",
  "properties": {
    "iso:country":"GB",
    "wof:name":"WN2 2AX",
    "wof:placetype":"postalcode"
},
  "geometry": {"coordinates":[-2.60651834667895,53.54265704615915],"type":"Point"}
}