{
  "type": "Feature",
  "properties": {
    "date:inception_lower":"1980-01-01",
    "date:inception_upper":"1980-01-31",
    "iso:country":"GB",
    "wof:name":"WN2 2AX",
    "wof:placetype":"postalcode"
},
  "geometry": {"coordinates":[-2.606518,53.542657],"type":"Point"}
}