{
  "type": "Feature",
  "properties": {
    "iso:country":"GB",
    "wof:name":"TF5 0PJ",
    "wof:placetype":"postalcode"
},
  "geometry": {"coordinates":[-2.53697296550657,52.71874533193279],"type":"Point"}
}