{
  "type": "Feature",
  "properties": {
    "date:inception_lower": "1996-06-01",
    "date:inception_upper": "1996-06-01",
    "iso:country": "GB",
    "wof:name": "TF5 0PJ",
    "wof:placetype": "postalcode"
  },
  "geometry": {"coordinates":[-2.536973,52.718745],"type":"Point"}
}
