{
  "type": "Feature",
  "properties": {
    "iso:country": "GB",
    "wof:name": "GL3 4DS",
    "wof:placetype": "postalcode"
  },
  "geometry": {"coordinates":[-2.164588,51.851343],"type":"Point"}
}
