{
  "type": "Feature",
  "properties": {
    "iso:country":"GB",
    "wof:name":"GL3 4DS",
    "wof:placetype":"postalcode"
},
  "geometry": {"coordinates":[-2.16458795796041,51.85134310177482],"type":"Point"}
}