{
  "type": "Feature",
  "properties": {
    "date:inception_lower": "1997-12-01",
    "date:inception_upper": "1997-12-01",
    "iso:country": "GB",
    "wof:name": "BS35 3NB",
    "wof:placetype": "postalcode"
  },
  "geometry": {"coordinates":[-2.532321,51.590309],"type":"Point"}
}
