{
  "type": "Feature",
  "properties": {
    "date:inception_lower": "1985-10-01",
    "date:inception_upper": "1985-10-01",
    "iso:country": "GB",
    "wof:name": "SP10 5NA",
    "wof:placetype": "postalcode"
  },
  "geometry": {"coordinates":[-1.477107,51.229921],"type":"Point"}
}
