{
  "type": "Feature",
  "properties": {
    "date:inception_lower": "1980-01-01",
    "date:inception_upper": "1980-01-01",
    "iso:country": "GB",
    "wof:name": "HP12 4LE",
    "wof:placetype": "postalcode"
  },
  "geometry": {"coordinates":[-0.785761,51.62696],"type":"Point"}
}
