{
  "type": "Feature",
  "properties": {
    "date:inception_lower": "1980-01-01",
    "date:inception_upper": "1980-01-01",
    "iso:country": "GB",
    "wof:name": "NR12 0LG",
    "wof:placetype": "postalcode"
  },
  "geometry": {"coordinates":[1.467993,52.843422],"type":"Point"}
}
