{
  "type": "Feature",
  "properties": {
    "iso:country":"GB",
    "wof:name":"SY5 6LD",
    "wof:placetype":"postalcode"
},
  "geometry": {"coordinates":[-2.68202098762244,52.66417753138879],"type":"Point"}
}