{
  "type": "Feature",
  "properties": {
    "iso:country":"GB",
    "wof:name":"CW1 3YH",
    "wof:placetype":"postalcode"
},
  "geometry": {"coordinates":[-2.45900671417643,53.11742775061671],"type":"Point"}
}