{
  "type": "Feature",
  "properties": {
    "iso:country": "GB",
    "wof:name": "CW1 3YH",
    "wof:placetype": "postalcode"
  },
  "geometry": {"coordinates":[-2.459007,53.117428],"type":"Point"}
}
