{
  "type": "Feature",
  "properties": {
    "iso:country":"GB",
    "wof:name":"EX16 6TY",
    "wof:placetype":"postalcode"
},
  "geometry": {"coordinates":[-3.47259187058567,50.91507705659441],"type":"Point"}
}