{
  "type": "Feature",
  "properties": {
    "date:inception_lower": "1994-12-01",
    "date:inception_upper": "1994-12-01",
    "iso:country": "GB",
    "wof:name": "EX16 6TY",
    "wof:placetype": "postalcode"
  },
  "geometry": {"coordinates":[-3.472592,50.915077],"type":"Point"}
}
