{
  "type": "Feature",
  "properties": {
    "iso:country":"GB",
    "wof:name":"L31 2LQ",
    "wof:placetype":"postalcode"
},
  "geometry": {"coordinates":[-2.94630553795724,53.52598744364528],"type":"Point"}
}