{
  "type": "Feature",
  "properties": {
    "date:inception_lower": "2021-10-01",
    "date:inception_upper": "2021-10-01",
    "iso:country": "GB",
    "wof:name": "S60 5GB",
    "wof:placetype": "postalcode"
  },
  "geometry": {"coordinates":[-1.342385,53.381737],"type":"Point"}
}
