{
  "type": "Feature",
  "properties": {
    "iso:country":"GB",
    "wof:name":"CV13 0LD",
    "wof:placetype":"postalcode"
},
  "geometry": {"coordinates":[-1.40318145132482,52.62495892053259],"type":"Point"}
}