{
  "type": "Feature",
  "properties": {
    "date:inception_lower": "1980-01-01",
    "date:inception_upper": "1980-01-01",
    "iso:country": "GB",
    "wof:name": "CV13 0LD",
    "wof:placetype": "postalcode"
  },
  "geometry": {"coordinates":[-1.403181,52.624959],"type":"Point"}
}
