{
  "type": "Feature",
  "properties": {
    "iso:country": "GB",
    "wof:name": "CV13 0LD",
    "wof:placetype": "postalcode"
  },
  "geometry": {"coordinates":[-1.403181,52.624959],"type":"Point"}
}
