{
  "type": "Feature",
  "properties": {
    "date:inception_lower": "1996-06-01",
    "date:inception_upper": "1996-06-01",
    "iso:country": "GB",
    "wof:name": "WR6 6NY",
    "wof:placetype": "postalcode"
  },
  "geometry": {"coordinates":[-2.373666,52.307525],"type":"Point"}
}
