{
  "type": "Feature",
  "properties": {
    "iso:country": "GB",
    "wof:name": "TQ4 7DF",
    "wof:placetype": "postalcode"
  },
  "geometry": {"coordinates":[-3.59806,50.428708],"type":"Point"}
}
