{
  "type": "Feature",
  "properties": {
    "iso:country":"GB",
    "wof:name":"TS26 0QH",
    "wof:placetype":"postalcode"
},
  "geometry": {"coordinates":[-1.25327298603011,54.68705472126902],"type":"Point"}
}