{
  "type": "Feature",
  "properties": {
    "date:inception_lower":"2001-06-01",
    "date:inception_upper":"2001-06-30",
    "iso:country":"GB",
    "wof:name":"TS26 0QH",
    "wof:placetype":"postalcode"
},
  "geometry": {"coordinates":[-1.253273,54.687055],"type":"Point"}
}