{
  "type": "Feature",
  "properties": {
    "iso:country": "GB",
    "wof:name": "TS26 0QH",
    "wof:placetype": "postalcode"
  },
  "geometry": {"coordinates":[-1.253273,54.687055],"type":"Point"}
}
