{
  "type": "Feature",
  "properties": {
    "date:inception_lower": "1980-01-01",
    "date:inception_upper": "1980-01-01",
    "iso:country": "GB",
    "wof:name": "SE9 3PR",
    "wof:placetype": "postalcode"
  },
  "geometry": {"coordinates":[0.074916,51.43316],"type":"Point"}
}
