{
  "type": "Feature",
  "properties": {
    "iso:country":"GB",
    "wof:name":"SP10 2PD",
    "wof:placetype":"postalcode"
},
  "geometry": {"coordinates":[-1.46983296545096,51.2086403903857],"type":"Point"}
}