{
  "type": "Feature",
  "properties": {
    "iso:country":"GB",
    "wof:name":"BS14 8TF",
    "wof:placetype":"postalcode"
},
  "geometry": {"coordinates":[-2.54110381837792,51.41099432881189],"type":"Point"}
}