{
  "type": "Feature",
  "properties": {
    "iso:country":"GB",
    "wof:name":"LE3 0DF",
    "wof:placetype":"postalcode"
},
  "geometry": {"coordinates":[-1.15204242758803,52.62332028137572],"type":"Point"}
}