{
  "type": "Feature",
  "properties": {
    "date:inception_lower": "2007-01-01",
    "date:inception_upper": "2007-01-01",
    "iso:country": "GB",
    "wof:name": "BH19 1JY",
    "wof:placetype": "postalcode"
  },
  "geometry": {"coordinates":[-1.964786,50.60954],"type":"Point"}
}
