{
  "type": "Feature",
  "properties": {
    "iso:country": "GB",
    "wof:name": "PE13 3BJ",
    "wof:placetype": "postalcode"
  },
  "geometry": {"coordinates":[0.162994,52.666402],"type":"Point"}
}
