{
  "type": "Feature",
  "properties": {
    "iso:country":"GB",
    "wof:name":"LS14 6SY",
    "wof:placetype":"postalcode"
},
  "geometry": {"coordinates":[-1.46708663904584,53.81067138621523],"type":"Point"}
}