{
  "type": "Feature",
  "properties": {
    "iso:country":"GB",
    "wof:name":"LL27 0JY",
    "wof:placetype":"postalcode"
},
  "geometry": {"coordinates":[-3.82835734242252,53.15231170948405],"type":"Point"}
}