{
  "type": "Feature",
  "properties": {
    "iso:country":"GB",
    "wof:name":"CM7 5BA",
    "wof:placetype":"postalcode"
},
  "geometry": {"coordinates":[0.49530492711359,51.91925367771422],"type":"Point"}
}