{
  "type": "Feature",
  "properties": {
    "iso:country": "GB",
    "wof:name": "CM7 5BA",
    "wof:placetype": "postalcode"
  },
  "geometry": {"coordinates":[0.495305,51.919254],"type":"Point"}
}
