{
  "type": "Feature",
  "properties": {
    "iso:country":"GB",
    "wof:name":"DH8 6AL",
    "wof:placetype":"postalcode"
},
  "geometry": {"coordinates":[-1.82717181097659,54.85399829770981],"type":"Point"}
}