{
  "type": "Feature",
  "properties": {
    "iso:country": "GB",
    "wof:name": "DH8 6AL",
    "wof:placetype": "postalcode"
  },
  "geometry": {"coordinates":[-1.827172,54.853998],"type":"Point"}
}
