{
  "type": "Feature",
  "properties": {
    "iso:country":"GB",
    "wof:name":"NW10 9TJ",
    "wof:placetype":"postalcode"
},
  "geometry": {"coordinates":[-0.24788625081687,51.54580854589184],"type":"Point"}
}