{
  "type": "Feature",
  "properties": {
    "iso:country":"GB",
    "wof:name":"LE8 4GZ",
    "wof:placetype":"postalcode"
},
  "geometry": {"coordinates":[-1.16876533123708,52.57804814721119],"type":"Point"}
}