{
  "type": "Feature",
  "properties": {
    "date:inception_lower": "1996-06-01",
    "date:inception_upper": "1996-06-01",
    "iso:country": "GB",
    "wof:name": "AB54 7TL",
    "wof:placetype": "postalcode"
  },
  "geometry": {"coordinates":[-2.623808,57.562582],"type":"Point"}
}
