{
  "type": "Feature",
  "properties": {
    "iso:country":"GB",
    "wof:name":"SA44 4JL",
    "wof:placetype":"postalcode"
},
  "geometry": {"coordinates":[-4.32879558395026,52.05422593460468],"type":"Point"}
}