{
  "type": "Feature",
  "properties": {
    "date:inception_lower": "1997-12-01",
    "date:inception_upper": "1997-12-01",
    "iso:country": "GB",
    "wof:name": "BS15 9YN",
    "wof:placetype": "postalcode"
  },
  "geometry": {"coordinates":[-2.489975,51.456744],"type":"Point"}
}
