{
  "type": "Feature",
  "properties": {
    "iso:country":"GB",
    "wof:name":"WN1 3LA",
    "wof:placetype":"postalcode"
},
  "geometry": {"coordinates":[-2.61639366309226,53.54826928224925],"type":"Point"}
}