{
  "type": "Feature",
  "properties": {
    "date:inception_lower": "1980-01-01",
    "date:inception_upper": "1980-01-01",
    "iso:country": "GB",
    "wof:name": "SN2 1HN",
    "wof:placetype": "postalcode"
  },
  "geometry": {"coordinates":[-1.795195,51.571134],"type":"Point"}
}
