{
  "type": "Feature",
  "properties": {
    "iso:country":"GB",
    "wof:name":"SN2 1HN",
    "wof:placetype":"postalcode"
},
  "geometry": {"coordinates":[-1.79519503612913,51.57113450097041],"type":"Point"}
}