{
  "type": "Feature",
  "properties": {
    "date:inception_lower": "1980-01-01",
    "date:inception_upper": "1980-01-01",
    "iso:country": "GB",
    "wof:name": "E9 7DU",
    "wof:placetype": "postalcode"
  },
  "geometry": {"coordinates":[-0.044468,51.540267],"type":"Point"}
}
