{
  "type": "Feature",
  "properties": {
    "iso:country":"GB",
    "wof:name":"E9 7DU",
    "wof:placetype":"postalcode"
},
  "geometry": {"coordinates":[-0.0445349231589,51.54034717602786],"type":"Point"}
}