{
  "type": "Feature",
  "properties": {
    "date:inception_lower":"1980-01-01",
    "date:inception_upper":"1980-01-31",
    "iso:country":"GB",
    "wof:name":"E9 7DU",
    "wof:placetype":"postalcode"
},
  "geometry": {"coordinates":[-0.044495,51.540303],"type":"Point"}
}