{
  "type": "Feature",
  "properties": {
    "iso:country":"GB",
    "wof:name":"NE29 7EL",
    "wof:placetype":"postalcode"
},
  "geometry": {"coordinates":[-1.4789604790643,55.0096908911329],"type":"Point"}
}