{
  "type": "Feature",
  "properties": {
    "iso:country": "GB",
    "wof:name": "RH15 8PR",
    "wof:placetype": "postalcode"
  },
  "geometry": {"coordinates":[-0.136793,50.963688],"type":"Point"}
}
