{
  "type": "Feature",
  "properties": {
    "iso:country":"GB",
    "wof:name":"RH15 8PR",
    "wof:placetype":"postalcode"
},
  "geometry": {"coordinates":[-0.1367931566939,50.96368805912992],"type":"Point"}
}