{
  "type": "Feature",
  "properties": {
    "iso:country":"GB",
    "wof:name":"FY8 2JZ",
    "wof:placetype":"postalcode"
},
  "geometry": {"coordinates":[-3.03847913298408,53.76130846782116],"type":"Point"}
}