{
  "type": "Feature",
  "properties": {
    "iso:country":"GB",
    "wof:name":"M2 7AT",
    "wof:placetype":"postalcode"
},
  "geometry": {"coordinates":[-2.24560818690459,53.48132133135283],"type":"Point"}
}