{
  "type": "Feature",
  "properties": {
    "date:inception_lower": "1996-06-01",
    "date:inception_upper": "1996-06-01",
    "iso:country": "GB",
    "wof:name": "M2 7AT",
    "wof:placetype": "postalcode"
  },
  "geometry": {"coordinates":[-2.245306,53.481259],"type":"Point"}
}
