{
  "type": "Feature",
  "properties": {
    "date:inception_lower": "2017-02-01",
    "date:inception_upper": "2017-02-01",
    "iso:country": "GB",
    "wof:name": "NR32 2TG",
    "wof:placetype": "postalcode"
  },
  "geometry": {"coordinates":[1.747479,52.477744],"type":"Point"}
}
