{
  "type": "Feature",
  "properties": {
    "iso:country":"GB",
    "wof:name":"L32 9PZ",
    "wof:placetype":"postalcode"
},
  "geometry": {"coordinates":[-2.88603472267812,53.47435078528299],"type":"Point"}
}