{
  "type": "Feature",
  "properties": {
    "date:inception_lower": "2019-06-01",
    "date:inception_upper": "2019-06-01",
    "iso:country": "GB",
    "wof:name": "TS9 7AZ",
    "wof:placetype": "postalcode"
  },
  "geometry": {"coordinates":[-1.151311,54.44413],"type":"Point"}
}
