{
  "type": "Feature",
  "properties": {
    "iso:country": "GB",
    "wof:name": "TS9 7AZ",
    "wof:placetype": "postalcode"
  },
  "geometry": {"coordinates":[-1.151401,54.444239],"type":"Point"}
}
