{
  "type": "Feature",
  "properties": {
    "iso:country": "GB",
    "wof:name": "TS9 7AZ",
    "wof:placetype": "postalcode"
  },
  "geometry": {"coordinates":[-1.151744,54.444071],"type":"Point"}
}
