{
  "type": "Feature",
  "properties": {
    "iso:country":"GB",
    "wof:name":"WD3 3JR",
    "wof:placetype":"postalcode"
},
  "geometry": {"coordinates":[-0.45161449193478,51.65566138699241],"type":"Point"}
}