{
  "type": "Feature",
  "properties": {
    "iso:country":"GB",
    "wof:name":"TA6 3JG",
    "wof:placetype":"postalcode"
},
  "geometry": {"coordinates":[-3.00382257249969,51.13700229460467],"type":"Point"}
}