{
  "type": "Feature",
  "properties": {
    "iso:country": "GB",
    "wof:name": "TA6 3JG",
    "wof:placetype": "postalcode"
  },
  "geometry": {"coordinates":[-3.003823,51.137002],"type":"Point"}
}
