{
  "type": "Feature",
  "properties": {
    "iso:country": "GB",
    "wof:name": "CV36 5JG",
    "wof:placetype": "postalcode"
  },
  "geometry": {"coordinates":[-1.579994,51.988083],"type":"Point"}
}
