{
  "type": "Feature",
  "properties": {
    "iso:country":"GB",
    "wof:name":"AL6 0ES",
    "wof:placetype":"postalcode"
},
  "geometry": {"coordinates":[-0.17425186685552,51.83117809868847],"type":"Point"}
}