{
  "type": "Feature",
  "properties": {
    "iso:country":"GB",
    "wof:name":"CV6 3GF",
    "wof:placetype":"postalcode"
},
  "geometry": {"coordinates":[-1.51568196523052,52.42202886062604],"type":"Point"}
}