{
  "type": "Feature",
  "properties": {
    "date:inception_lower": "1980-01-01",
    "date:inception_upper": "1980-01-01",
    "iso:country": "GB",
    "wof:name": "PO31 7JP",
    "wof:placetype": "postalcode"
  },
  "geometry": {"coordinates":[-1.301551,50.756959],"type":"Point"}
}
