{
  "type": "Feature",
  "properties": {
    "iso:country":"GB",
    "wof:name":"PA34 5AY",
    "wof:placetype":"postalcode"
},
  "geometry": {"coordinates":[-5.47690425839918,56.41999857871586],"type":"Point"}
}