{
  "type": "Feature",
  "properties": {
    "iso:country": "GB",
    "wof:name": "IV31 6QH",
    "wof:placetype": "postalcode"
  },
  "geometry": {"coordinates":[-3.284916,57.723623],"type":"Point"}
}
