{
  "type": "Feature",
  "properties": {
    "iso:country":"GB",
    "wof:name":"EH14 5PW",
    "wof:placetype":"postalcode"
},
  "geometry": {"coordinates":[-3.31019794044848,55.90066420775318],"type":"Point"}
}