{
  "type": "Feature",
  "properties": {
    "date:inception_lower":"2010-07-01",
    "date:inception_upper":"2010-07-31",
    "iso:country":"GB",
    "wof:name":"BD10 0JD",
    "wof:placetype":"postalcode"
},
  "geometry": {"coordinates":[-1.70955,53.817795],"type":"Point"}
}