{
  "type": "Feature",
  "properties": {
    "iso:country":"GB",
    "wof:name":"EX6 7UB",
    "wof:placetype":"postalcode"
},
  "geometry": {"coordinates":[-3.53648713184628,50.66132832604945],"type":"Point"}
}