{
  "type": "Feature",
  "properties": {
    "date:inception_lower": "1980-01-01",
    "date:inception_upper": "1980-01-01",
    "iso:country": "GB",
    "wof:name": "CV21 4PW",
    "wof:placetype": "postalcode"
  },
  "geometry": {"coordinates":[-1.2009,52.355636],"type":"Point"}
}
