{
  "type": "Feature",
  "properties": {
    "iso:country": "GB",
    "wof:name": "CV21 4PW",
    "wof:placetype": "postalcode"
  },
  "geometry": {"coordinates":[-1.2009,52.355636],"type":"Point"}
}
