{
  "type": "Feature",
  "properties": {
    "iso:country":"GB",
    "wof:name":"CV21 4PW",
    "wof:placetype":"postalcode"
},
  "geometry": {"coordinates":[-1.20089999388383,52.35563591741123],"type":"Point"}
}