{
  "type": "Feature",
  "properties": {
    "iso:country":"GB",
    "wof:name":"NG4 3SJ",
    "wof:placetype":"postalcode"
},
  "geometry": {"coordinates":[-1.10611518832057,52.97638829800943],"type":"Point"}
}