{
  "type": "Feature",
  "properties": {
    "iso:country":"GB",
    "wof:name":"AL7 2AW",
    "wof:placetype":"postalcode"
},
  "geometry": {"coordinates":[-0.17519095108669,51.80363205391306],"type":"Point"}
}