{
  "type": "Feature",
  "properties": {
    "iso:country":"GB",
    "wof:name":"PR8 6ET",
    "wof:placetype":"postalcode"
},
  "geometry": {"coordinates":[-2.97212413605382,53.63954075488695],"type":"Point"}
}