{
  "type": "Feature",
  "properties": {
    "iso:country":"GB",
    "wof:name":"SE18 7TE",
    "wof:placetype":"postalcode"
},
  "geometry": {"coordinates":[0.08021557762485,51.48488308389155],"type":"Point"}
}