{
  "type": "Feature",
  "properties": {
    "iso:country": "GB",
    "wof:name": "SE5 7AQ",
    "wof:placetype": "postalcode"
  },
  "geometry": {"coordinates":[-0.092642,51.475826],"type":"Point"}
}
