{
  "type": "Feature",
  "properties": {
    "iso:country":"GB",
    "wof:name":"SE5 7AQ",
    "wof:placetype":"postalcode"
},
  "geometry": {"coordinates":[-0.09264234862674,51.47582619150316],"type":"Point"}
}