{
  "type": "Feature",
  "properties": {
    "iso:country":"GB",
    "wof:name":"TN6 1XL",
    "wof:placetype":"postalcode"
},
  "geometry": {"coordinates":[0.14019037100524,51.07085544063223],"type":"Point"}
}