{
  "type": "Feature",
  "properties": {
    "iso:country":"GB",
    "wof:name":"IG2 6LT",
    "wof:placetype":"postalcode"
},
  "geometry": {"coordinates":[0.07394420620999,51.57547916832376],"type":"Point"}
}