{
  "type": "Feature",
  "properties": {
    "date:inception_lower":"1980-01-01",
    "date:inception_upper":"1980-01-31",
    "iso:country":"GB",
    "wof:name":"G84 0JT",
    "wof:placetype":"postalcode"
},
  "geometry": {"coordinates":[-4.82098,55.986742],"type":"Point"}
}