{
  "type": "Feature",
  "properties": {
    "iso:country":"GB",
    "wof:name":"G84 0JT",
    "wof:placetype":"postalcode"
},
  "geometry": {"coordinates":[-4.82090577990237,55.98676863427349],"type":"Point"}
}