{
  "type": "Feature",
  "properties": {
    "iso:country":"GB",
    "wof:name":"PO32 6DR",
    "wof:placetype":"postalcode"
},
  "geometry": {"coordinates":[-1.28215446804169,50.75434155743886],"type":"Point"}
}