{
  "type": "Feature",
  "properties": {
    "iso:country":"GB",
    "wof:name":"BS23 4TA",
    "wof:placetype":"postalcode"
},
  "geometry": {"coordinates":[-2.97526824315858,51.32006362716095],"type":"Point"}
}