{
  "type": "Feature",
  "properties": {
    "date:inception_lower": "2019-01-01",
    "date:inception_upper": "2019-01-01",
    "iso:country": "GB",
    "wof:name": "PR4 2FF",
    "wof:placetype": "postalcode"
  },
  "geometry": {"coordinates":[-2.915305,53.771208],"type":"Point"}
}
