{
  "type": "Feature",
  "properties": {
    "date:inception_lower":"1980-01-01",
    "date:inception_upper":"1980-01-31",
    "iso:country":"GB",
    "wof:name":"HR1 4BL",
    "wof:placetype":"postalcode"
},
  "geometry": {"coordinates":[-2.605096,52.072758],"type":"Point"}
}