{
  "type": "Feature",
  "properties": {
    "iso:country":"GB",
    "wof:name":"HR1 4BL",
    "wof:placetype":"postalcode"
},
  "geometry": {"coordinates":[-2.60509654124722,52.072757879214],"type":"Point"}
}