{
  "type": "Feature",
  "properties": {
    "iso:country":"GB",
    "wof:name":"G71 8RN",
    "wof:placetype":"postalcode"
},
  "geometry": {"coordinates":[-4.06596544545048,55.80255899384616],"type":"Point"}
}