{
  "type": "Feature",
  "properties": {
    "iso:country": "GB",
    "wof:name": "G71 8RN",
    "wof:placetype": "postalcode"
  },
  "geometry": {"coordinates":[-4.065965,55.802559],"type":"Point"}
}
