{
  "type": "Feature",
  "properties": {
    "iso:country":"GB",
    "wof:name":"S64 9LU",
    "wof:placetype":"postalcode"
},
  "geometry": {"coordinates":[-1.29458417571981,53.49408252151977],"type":"Point"}
}