{
  "type": "Feature",
  "properties": {
    "iso:country": "GB",
    "wof:name": "S64 9LU",
    "wof:placetype": "postalcode"
  },
  "geometry": {"coordinates":[-1.294584,53.494083],"type":"Point"}
}
