{
  "type": "Feature",
  "properties": {
    "iso:country":"GB",
    "wof:name":"NN11 3EY",
    "wof:placetype":"postalcode"
},
  "geometry": {"coordinates":[-1.15331672342067,52.23155058476715],"type":"Point"}
}