{
  "type": "Feature",
  "properties": {
    "iso:country": "GB",
    "wof:name": "NN11 3EY",
    "wof:placetype": "postalcode"
  },
  "geometry": {"coordinates":[-1.153317,52.231551],"type":"Point"}
}
