{
  "type": "Feature",
  "properties": {
    "iso:country":"GB",
    "wof:name":"SO21 2PT",
    "wof:placetype":"postalcode"
},
  "geometry": {"coordinates":[-1.3926786101012,51.11131280351385],"type":"Point"}
}