{
  "type": "Feature",
  "properties": {
    "iso:country": "GB",
    "wof:name": "WV15 6JY",
    "wof:placetype": "postalcode"
  },
  "geometry": {"coordinates":[-2.34912,52.460891],"type":"Point"}
}
