{
  "type": "Feature",
  "properties": {
    "iso:country":"GB",
    "wof:name":"WV15 6JY",
    "wof:placetype":"postalcode"
},
  "geometry": {"coordinates":[-2.34911993607597,52.46089099525908],"type":"Point"}
}