{
  "type": "Feature",
  "properties": {
    "iso:country":"GB",
    "wof:name":"BS31 3EN",
    "wof:placetype":"postalcode"
},
  "geometry": {"coordinates":[-2.45268561624292,51.40455367159363],"type":"Point"}
}