{
  "type": "Feature",
  "properties": {
    "iso:country": "GB",
    "wof:name": "BS31 3EN",
    "wof:placetype": "postalcode"
  },
  "geometry": {"coordinates":[-2.452686,51.404554],"type":"Point"}
}
