{
  "type": "Feature",
  "properties": {
    "iso:country":"GB",
    "wof:name":"CV3 6GQ",
    "wof:placetype":"postalcode"
},
  "geometry": {"coordinates":[-1.51542989190394,52.39000490422742],"type":"Point"}
}