{
  "type": "Feature",
  "properties": {
    "iso:country": "GB",
    "wof:name": "RG8 7JW",
    "wof:placetype": "postalcode"
  },
  "geometry": {"coordinates":[-1.083134,51.479921],"type":"Point"}
}
