{
  "type": "Feature",
  "properties": {
    "iso:country": "GB",
    "wof:name": "AB24 5AA",
    "wof:placetype": "postalcode"
  },
  "geometry": {"coordinates":[-2.093847,57.148757],"type":"Point"}
}
