{
  "type": "Feature",
  "properties": {
    "date:inception_lower": "1980-01-01",
    "date:inception_upper": "1980-01-01",
    "iso:country": "GB",
    "wof:name": "IP9 1QG",
    "wof:placetype": "postalcode"
  },
  "geometry": {"coordinates":[1.261605,51.959957],"type":"Point"}
}
