{
  "type": "Feature",
  "properties": {
    "iso:country": "GB",
    "wof:name": "CW6 9UH",
    "wof:placetype": "postalcode"
  },
  "geometry": {"coordinates":[-2.692932,53.104816],"type":"Point"}
}
