{
  "type": "Feature",
  "properties": {
    "iso:country":"GB",
    "wof:name":"SW1W 8NB",
    "wof:placetype":"postalcode"
},
  "geometry": {"coordinates":[-0.15104911985744,51.49079910400289],"type":"Point"}
}