{
  "type": "Feature",
  "properties": {
    "iso:country":"GB",
    "wof:name":"PR1 4TP",
    "wof:placetype":"postalcode"
},
  "geometry": {"coordinates":[-2.66957569530443,53.76467442517853],"type":"Point"}
}