{
  "type": "Feature",
  "properties": {
    "date:inception_lower": "1980-01-01",
    "date:inception_upper": "1980-01-01",
    "iso:country": "GB",
    "wof:name": "FK9 4PZ",
    "wof:placetype": "postalcode"
  },
  "geometry": {"coordinates":[-3.949708,56.161381],"type":"Point"}
}
