{
  "type": "Feature",
  "properties": {
    "date:inception_lower": "2022-11-01",
    "date:inception_upper": "2022-11-01",
    "iso:country": "GB",
    "wof:name": "CF24 0AS",
    "wof:placetype": "postalcode"
  },
  "geometry": {"coordinates":[-3.165338,51.48146],"type":"Point"}
}
