{
  "type": "Feature",
  "properties": {
    "date:inception_lower":"1980-01-01",
    "date:inception_upper":"1980-01-31",
    "iso:country":"GB",
    "wof:name":"W11 1PH",
    "wof:placetype":"postalcode"
},
  "geometry": {"coordinates":[-0.210145,51.515258],"type":"Point"}
}