{
  "type": "Feature",
  "properties": {
    "iso:country":"GB",
    "wof:name":"W11 1PH",
    "wof:placetype":"postalcode"
},
  "geometry": {"coordinates":[-0.21014497752583,51.51525817230517],"type":"Point"}
}