{
  "type": "Feature",
  "properties": {
    "iso:country":"GB",
    "wof:name":"B19 2LQ",
    "wof:placetype":"postalcode"
},
  "geometry": {"coordinates":[-1.90031192759575,52.50238634716386],"type":"Point"}
}