{
  "type": "Feature",
  "properties": {
    "iso:country":"GB",
    "wof:name":"IG9 6JB",
    "wof:placetype":"postalcode"
},
  "geometry": {"coordinates":[0.04406435959333,51.61587675393339],"type":"Point"}
}