{
  "type": "Feature",
  "properties": {
    "iso:country": "GB",
    "wof:name": "OX39 4BF",
    "wof:placetype": "postalcode"
  },
  "geometry": {"coordinates":[-0.91508,51.706376],"type":"Point"}
}
