{
  "type": "Feature",
  "properties": {
    "date:inception_lower": "1980-01-01",
    "date:inception_upper": "1980-01-01",
    "iso:country": "GB",
    "wof:name": "AL2 2AW",
    "wof:placetype": "postalcode"
  },
  "geometry": {"coordinates":[-0.353177,51.715099],"type":"Point"}
}
