{
  "type": "Feature",
  "properties": {
    "iso:country":"GB",
    "wof:name":"CH45 3PS",
    "wof:placetype":"postalcode"
},
  "geometry": {"coordinates":[-3.07030221117808,53.43192439937062],"type":"Point"}
}