{
  "type": "Feature",
  "properties": {
    "date:inception_lower":"1980-01-01",
    "date:inception_upper":"1980-01-31",
    "iso:country":"GB",
    "wof:name":"LA20 6AB",
    "wof:placetype":"postalcode"
},
  "geometry": {"coordinates":[-3.211966,54.285958],"type":"Point"}
}