{
  "type": "Feature",
  "properties": {
    "iso:country":"GB",
    "wof:name":"KW12 6XB",
    "wof:placetype":"postalcode"
},
  "geometry": {"coordinates":[-3.46741793363938,58.53999098793494],"type":"Point"}
}