{
  "type": "Feature",
  "properties": {
    "date:inception_lower": "1980-01-01",
    "date:inception_upper": "1980-01-01",
    "iso:country": "GB",
    "wof:name": "KW12 6XB",
    "wof:placetype": "postalcode"
  },
  "geometry": {"coordinates":[-3.467418,58.539991],"type":"Point"}
}
