{
  "type": "Feature",
  "properties": {
    "iso:country": "GB",
    "wof:name": "KT19 8FA",
    "wof:placetype": "postalcode"
  },
  "geometry": {"coordinates":[-0.269946,51.34912],"type":"Point"}
}
