{
  "type": "Feature",
  "properties": {
    "iso:country":"GB",
    "wof:name":"KT19 8FA",
    "wof:placetype":"postalcode"
},
  "geometry": {"coordinates":[-0.26994585071729,51.34912019271276],"type":"Point"}
}