{
  "type": "Feature",
  "properties": {
    "iso:country":"GB",
    "wof:name":"LA6 3DS",
    "wof:placetype":"postalcode"
},
  "geometry": {"coordinates":[-2.48226687489565,54.13252058136505],"type":"Point"}
}