{
  "type": "Feature",
  "properties": {
    "iso:country": "GB",
    "wof:name": "HG1 1JD",
    "wof:placetype": "postalcode"
  },
  "geometry": {"coordinates":[-1.537056,53.991148],"type":"Point"}
}
