{
  "type": "Feature",
  "properties": {
    "iso:country":"GB",
    "wof:name":"HG1 1JD",
    "wof:placetype":"postalcode"
},
  "geometry": {"coordinates":[-1.53705081645073,53.99113288980837],"type":"Point"}
}