{
  "type": "Feature",
  "properties": {
    "iso:country":"GB",
    "wof:name":"PH7 4AX",
    "wof:placetype":"postalcode"
},
  "geometry": {"coordinates":[-3.84340008917031,56.37408609331445],"type":"Point"}
}