{
  "type": "Feature",
  "properties": {
    "date:inception_lower":"2012-08-01",
    "date:inception_upper":"2012-08-31",
    "iso:country":"GB",
    "wof:name":"WF16 9FE",
    "wof:placetype":"postalcode"
},
  "geometry": {"coordinates":[-1.666753,53.710157],"type":"Point"}
}