{
  "type": "Feature",
  "properties": {
    "iso:country":"GB",
    "wof:name":"NW8 8TL",
    "wof:placetype":"postalcode"
},
  "geometry": {"coordinates":[-0.16554460586816,51.52621434860547],"type":"Point"}
}