{
  "type": "Feature",
  "properties": {
    "iso:country":"GB",
    "wof:name":"FY4 2HS",
    "wof:placetype":"postalcode"
},
  "geometry": {"coordinates":[-3.03804381812351,53.78731578073018],"type":"Point"}
}