{
  "type": "Feature",
  "properties": {
    "iso:country": "GB",
    "wof:name": "PE1 3GA",
    "wof:placetype": "postalcode"
  },
  "geometry": {"coordinates":[-0.248835,52.596771],"type":"Point"}
}
