{
  "type": "Feature",
  "properties": {
    "iso:country": "GB",
    "wof:name": "SO50 8AG",
    "wof:placetype": "postalcode"
  },
  "geometry": {"coordinates":[-1.304788,50.97173],"type":"Point"}
}
