{
  "type": "Feature",
  "properties": {
    "iso:country":"GB",
    "wof:name":"SO50 8AG",
    "wof:placetype":"postalcode"
},
  "geometry": {"coordinates":[-1.30478777457636,50.97173043250989],"type":"Point"}
}