{
  "type": "Feature",
  "properties": {
    "iso:country":"GB",
    "wof:name":"SS7 3LH",
    "wof:placetype":"postalcode"
},
  "geometry": {"coordinates":[0.58559308653244,51.57436575967103],"type":"Point"}
}