{
  "type": "Feature",
  "properties": {
    "iso:country": "GB",
    "wof:name": "SS7 3LH",
    "wof:placetype": "postalcode"
  },
  "geometry": {"coordinates":[0.58562,51.57437],"type":"Point"}
}
