{
  "type": "Feature",
  "properties": {
    "date:inception_lower": "2021-07-01",
    "date:inception_upper": "2021-07-01",
    "iso:country": "GB",
    "wof:name": "GL1 1HZ",
    "wof:placetype": "postalcode"
  },
  "geometry": {"coordinates":[-2.244169,51.861309],"type":"Point"}
}
