{
  "type": "Feature",
  "properties": {
    "iso:country":"GB",
    "wof:name":"NP25 5QD",
    "wof:placetype":"postalcode"
},
  "geometry": {"coordinates":[-2.75008085014632,51.83759301437488],"type":"Point"}
}