{
  "type": "Feature",
  "properties": {
    "iso:country":"GB",
    "wof:name":"CM11 1DZ",
    "wof:placetype":"postalcode"
},
  "geometry": {"coordinates":[0.43573704910623,51.64288119085876],"type":"Point"}
}