{
  "type": "Feature",
  "properties": {
    "iso:country":"GB",
    "wof:name":"DY1 2GZ",
    "wof:placetype":"postalcode"
},
  "geometry": {"coordinates":[-2.10327471294251,52.51740496806332],"type":"Point"}
}