{
  "type": "Feature",
  "properties": {
    "date:inception_lower": "1998-12-01",
    "date:inception_upper": "1998-12-01",
    "iso:country": "GB",
    "wof:name": "DY1 2GZ",
    "wof:placetype": "postalcode"
  },
  "geometry": {"coordinates":[-2.103299,52.517429],"type":"Point"}
}
