{
  "type": "Feature",
  "properties": {
    "date:inception_lower": "1980-01-01",
    "date:inception_upper": "1980-01-01",
    "iso:country": "GB",
    "wof:name": "KY16 9PE",
    "wof:placetype": "postalcode"
  },
  "geometry": {"coordinates":[-2.797172,56.340576],"type":"Point"}
}
