{
  "type": "Feature",
  "properties": {
    "date:inception_lower": "1980-01-01",
    "date:inception_upper": "1980-01-01",
    "iso:country": "GB",
    "wof:name": "G41 3YL",
    "wof:placetype": "postalcode"
  },
  "geometry": {"coordinates":[-4.281235,55.82931],"type":"Point"}
}
