{
  "type": "Feature",
  "properties": {
    "iso:country":"GB",
    "wof:name":"BA1 8DQ",
    "wof:placetype":"postalcode"
},
  "geometry": {"coordinates":[-2.3458450749256,51.40311953331994],"type":"Point"}
}