{
  "type": "Feature",
  "properties": {
    "iso:country":"GB",
    "wof:name":"CO2 8YR",
    "wof:placetype":"postalcode"
},
  "geometry": {"coordinates":[0.92783892070644,51.88170883126114],"type":"Point"}
}