{
  "type": "Feature",
  "properties": {
    "iso:country": "GB",
    "wof:name": "KT12 2AT",
    "wof:placetype": "postalcode"
  },
  "geometry": {"coordinates":[-0.407693,51.389147],"type":"Point"}
}
