{
  "type": "Feature",
  "properties": {
    "iso:country":"GB",
    "wof:name":"BN27 3GY",
    "wof:placetype":"postalcode"
},
  "geometry": {"coordinates":[0.25116348567896,50.85967532170772],"type":"Point"}
}