{
  "type": "Feature",
  "properties": {
    "iso:country": "GB",
    "wof:name": "ST9 0FB",
    "wof:placetype": "postalcode"
  },
  "geometry": {"coordinates":[-2.091171,53.025394],"type":"Point"}
}
