{
  "type": "Feature",
  "properties": {
    "date:inception_lower": "2016-10-01",
    "date:inception_upper": "2016-10-01",
    "iso:country": "GB",
    "wof:name": "ST9 0FB",
    "wof:placetype": "postalcode"
  },
  "geometry": {"coordinates":[-2.091171,53.025394],"type":"Point"}
}
