{
  "type": "Feature",
  "properties": {
    "iso:country":"GB",
    "wof:name":"LS9 0PJ",
    "wof:placetype":"postalcode"
},
  "geometry": {"coordinates":[-1.50734352863863,53.77978965378573],"type":"Point"}
}