{
  "type": "Feature",
  "properties": {
    "iso:country": "GB",
    "wof:name": "LS9 0PJ",
    "wof:placetype": "postalcode"
  },
  "geometry": {"coordinates":[-1.508761,53.779542],"type":"Point"}
}
