{
  "type": "Feature",
  "properties": {
    "iso:country":"GB",
    "wof:name":"WA10 4LN",
    "wof:placetype":"postalcode"
},
  "geometry": {"coordinates":[-2.75357693640898,53.45772284113483],"type":"Point"}
}