{
  "type": "Feature",
  "properties": {
    "iso:country": "GB",
    "wof:name": "EH22 4RE",
    "wof:placetype": "postalcode"
  },
  "geometry": {"coordinates":[-3.067815,55.869728],"type":"Point"}
}
