{
  "type": "Feature",
  "properties": {
    "date:inception_lower": "1993-08-01",
    "date:inception_upper": "1993-08-01",
    "iso:country": "GB",
    "wof:name": "NR1 3DD",
    "wof:placetype": "postalcode"
  },
  "geometry": {"coordinates":[1.295902,52.62662],"type":"Point"}
}
