{
  "type": "Feature",
  "properties": {
    "iso:country":"GB",
    "wof:name":"YO12 4SE",
    "wof:placetype":"postalcode"
},
  "geometry": {"coordinates":[-0.44410114670726,54.19746428798256],"type":"Point"}
}