{
  "type": "Feature",
  "properties": {
    "date:inception_lower": "1980-01-01",
    "date:inception_upper": "1980-01-01",
    "iso:country": "GB",
    "wof:name": "YO12 4SE",
    "wof:placetype": "postalcode"
  },
  "geometry": {"coordinates":[-0.444216,54.197654],"type":"Point"}
}
