{
  "type": "Feature",
  "properties": {
    "iso:country": "GB",
    "wof:name": "YO12 4SE",
    "wof:placetype": "postalcode"
  },
  "geometry": {"coordinates":[-0.444216,54.197654],"type":"Point"}
}
