{
  "type": "Feature",
  "properties": {
    "iso:country":"GB",
    "wof:name":"GL2 2GN",
    "wof:placetype":"postalcode"
},
  "geometry": {"coordinates":[-2.26982942698542,51.81978805445767],"type":"Point"}
}