{
  "type": "Feature",
  "properties": {
    "iso:country":"GB",
    "wof:name":"BS5 6YD",
    "wof:placetype":"postalcode"
},
  "geometry": {"coordinates":[-2.55988628963842,51.47016105279514],"type":"Point"}
}