{
  "type": "Feature",
  "properties": {
    "iso:country":"GB",
    "wof:name":"GL4 3YL",
    "wof:placetype":"postalcode"
},
  "geometry": {"coordinates":[-2.20720703195253,51.86266716718759],"type":"Point"}
}