{
  "type": "Feature",
  "properties": {
    "date:inception_lower": "2015-05-01",
    "date:inception_upper": "2015-05-01",
    "iso:country": "GB",
    "wof:name": "CF35 6FL",
    "wof:placetype": "postalcode"
  },
  "geometry": {"coordinates":[-3.560875,51.5279],"type":"Point"}
}
