{
  "type": "Feature",
  "properties": {
    "iso:country": "GB",
    "wof:name": "CF35 6FL",
    "wof:placetype": "postalcode"
  },
  "geometry": {"coordinates":[-3.560875,51.5279],"type":"Point"}
}
