{
  "type": "Feature",
  "properties": {
    "iso:country":"GB",
    "wof:name":"W5 1DZ",
    "wof:placetype":"postalcode"
},
  "geometry": {"coordinates":[-0.29295379657334,51.53390167369849],"type":"Point"}
}