{
  "type": "Feature",
  "properties": {
    "date:inception_lower": "1980-01-01",
    "date:inception_upper": "1980-01-01",
    "iso:country": "GB",
    "wof:name": "W5 1DZ",
    "wof:placetype": "postalcode"
  },
  "geometry": {"coordinates":[-0.292954,51.533902],"type":"Point"}
}
