{
  "type": "Feature",
  "properties": {
    "iso:country": "GB",
    "wof:name": "BS16 6NU",
    "wof:placetype": "postalcode"
  },
  "geometry": {"coordinates":[-2.49394,51.500004],"type":"Point"}
}
