{
  "type": "Feature",
  "properties": {
    "iso:country":"GB",
    "wof:name":"BS16 6NU",
    "wof:placetype":"postalcode"
},
  "geometry": {"coordinates":[-2.49393989131958,51.5000037838071],"type":"Point"}
}