{
  "type": "Feature",
  "properties": {
    "iso:country":"GB",
    "wof:name":"HP15 7SY",
    "wof:placetype":"postalcode"
},
  "geometry": {"coordinates":[-0.70713034687035,51.6435469309115],"type":"Point"}
}