{
  "type": "Feature",
  "properties": {
    "iso:country":"GB",
    "wof:name":"HP21 8PU",
    "wof:placetype":"postalcode"
},
  "geometry": {"coordinates":[-0.82798661362555,51.80684289688199],"type":"Point"}
}