{
  "type": "Feature",
  "properties": {
    "iso:country": "GB",
    "wof:name": "LA15 8AZ",
    "wof:placetype": "postalcode"
  },
  "geometry": {"coordinates":[-3.185852,54.155471],"type":"Point"}
}
