{
  "type": "Feature",
  "properties": {
    "iso:country":"GB",
    "wof:name":"LA15 8AZ",
    "wof:placetype":"postalcode"
},
  "geometry": {"coordinates":[-3.18585230407282,54.15547117940324],"type":"Point"}
}