{
  "type": "Feature",
  "properties": {
    "iso:country": "GB",
    "wof:name": "PL3 4LG",
    "wof:placetype": "postalcode"
  },
  "geometry": {"coordinates":[-4.143638,50.387035],"type":"Point"}
}
