{
  "type": "Feature",
  "properties": {
    "iso:country": "GB",
    "wof:name": "GU9 8LN",
    "wof:placetype": "postalcode"
  },
  "geometry": {"coordinates":[-0.793984,51.206578],"type":"Point"}
}
