{
  "type": "Feature",
  "properties": {
    "date:inception_lower": "1980-01-01",
    "date:inception_upper": "1980-01-01",
    "iso:country": "GB",
    "wof:name": "GU9 8LN",
    "wof:placetype": "postalcode"
  },
  "geometry": {"coordinates":[-0.793984,51.206578],"type":"Point"}
}
