{
  "type": "Feature",
  "properties": {
    "iso:country":"GB",
    "wof:name":"WF4 4RA",
    "wof:placetype":"postalcode"
},
  "geometry": {"coordinates":[-1.60965014546848,53.64608996004966],"type":"Point"}
}