{
  "type": "Feature",
  "properties": {
    "date:inception_lower":"1980-01-01",
    "date:inception_upper":"1980-01-31",
    "iso:country":"GB",
    "wof:name":"SO20 6RB",
    "wof:placetype":"postalcode"
},
  "geometry": {"coordinates":[-1.436016,51.090497],"type":"Point"}
}