{
  "type": "Feature",
  "properties": {
    "iso:country": "GB",
    "wof:name": "SO20 6RB",
    "wof:placetype": "postalcode"
  },
  "geometry": {"coordinates":[-1.436016,51.090497],"type":"Point"}
}
