{
  "type": "Feature",
  "properties": {
    "iso:country":"GB",
    "wof:name":"SO20 6RB",
    "wof:placetype":"postalcode"
},
  "geometry": {"coordinates":[-1.43601578270374,51.09049706176725],"type":"Point"}
}