{
  "type": "Feature",
  "properties": {
    "iso:country":"GB",
    "wof:name":"NE15 0HX",
    "wof:placetype":"postalcode"
},
  "geometry": {"coordinates":[-1.82114026787524,54.99222557579671],"type":"Point"}
}