{
  "type": "Feature",
  "properties": {
    "date:inception_lower": "1980-01-01",
    "date:inception_upper": "1980-01-01",
    "iso:country": "GB",
    "wof:name": "UB3 3BS",
    "wof:placetype": "postalcode"
  },
  "geometry": {"coordinates":[-0.41323,51.504468],"type":"Point"}
}
