{
  "type": "Feature",
  "properties": {
    "iso:country":"GB",
    "wof:name":"UB3 3BS",
    "wof:placetype":"postalcode"
},
  "geometry": {"coordinates":[-0.41322991884935,51.50446804626934],"type":"Point"}
}