{
  "type": "Feature",
  "properties": {
    "date:inception_lower":"1980-01-01",
    "date:inception_upper":"1980-01-31",
    "iso:country":"GB",
    "wof:name":"FY8 3EZ",
    "wof:placetype":"postalcode"
},
  "geometry": {"coordinates":[-3.015422,53.762567],"type":"Point"}
}