{
  "type": "Feature",
  "properties": {
    "date:inception_lower": "2000-12-01",
    "date:inception_upper": "2000-12-01",
    "iso:country": "GB",
    "wof:name": "W1S 2LQ",
    "wof:placetype": "postalcode"
  },
  "geometry": {"coordinates":[-0.142175,51.511009],"type":"Point"}
}
