{
  "type": "Feature",
  "properties": {
    "iso:country":"GB",
    "wof:name":"DE21 7SX",
    "wof:placetype":"postalcode"
},
  "geometry": {"coordinates":[-1.40179011637845,52.911847530509],"type":"Point"}
}