{
  "type": "Feature",
  "properties": {
    "date:inception_lower":"2006-07-01",
    "date:inception_upper":"2006-07-31",
    "iso:country":"GB",
    "wof:name":"DE21 7SX",
    "wof:placetype":"postalcode"
},
  "geometry": {"coordinates":[-1.40179,52.911848],"type":"Point"}
}