{
  "type": "Feature",
  "properties": {
    "date:inception_lower": "1980-01-01",
    "date:inception_upper": "1980-01-01",
    "iso:country": "GB",
    "wof:name": "FK7 7EY",
    "wof:placetype": "postalcode"
  },
  "geometry": {"coordinates":[-3.873096,56.10535],"type":"Point"}
}
