{
  "type": "Feature",
  "properties": {
    "iso:country":"GB",
    "wof:name":"FK7 7EY",
    "wof:placetype":"postalcode"
},
  "geometry": {"coordinates":[-3.87309562342586,56.10535003303541],"type":"Point"}
}