{
  "type": "Feature",
  "properties": {
    "iso:country": "GB",
    "wof:name": "FK7 7EY",
    "wof:placetype": "postalcode"
  },
  "geometry": {"coordinates":[-3.873096,56.10535],"type":"Point"}
}
