{
  "type": "Feature",
  "properties": {
    "iso:country":"GB",
    "wof:name":"BN13 2PS",
    "wof:placetype":"postalcode"
},
  "geometry": {"coordinates":[-0.40724502875615,50.8381889001805],"type":"Point"}
}