{
  "type": "Feature",
  "properties": {
    "iso:country":"GB",
    "wof:name":"B27 7UR",
    "wof:placetype":"postalcode"
},
  "geometry": {"coordinates":[-1.83126200149359,52.44533870474331],"type":"Point"}
}