{
  "type": "Feature",
  "properties": {
    "iso:country": "GB",
    "wof:name": "GL20 5DE",
    "wof:placetype": "postalcode"
  },
  "geometry": {"coordinates":[-2.15338,51.996065],"type":"Point"}
}
