{
  "type": "Feature",
  "properties": {
    "date:inception_lower": "1996-12-01",
    "date:inception_upper": "1996-12-01",
    "iso:country": "GB",
    "wof:name": "NR29 5NF",
    "wof:placetype": "postalcode"
  },
  "geometry": {"coordinates":[1.569794,52.72488],"type":"Point"}
}
