{
  "type": "Feature",
  "properties": {
    "iso:country":"GB",
    "wof:name":"NW9 8TU",
    "wof:placetype":"postalcode"
},
  "geometry": {"coordinates":[-0.25740948023053,51.58040889710266],"type":"Point"}
}