{
  "type": "Feature",
  "properties": {
    "date:inception_lower": "1980-01-01",
    "date:inception_upper": "1980-01-01",
    "iso:country": "GB",
    "wof:name": "DA13 0HY",
    "wof:placetype": "postalcode"
  },
  "geometry": {"coordinates":[0.355333,51.380933],"type":"Point"}
}
