{
  "type": "Feature",
  "properties": {
    "iso:country":"GB",
    "wof:name":"PO11 0LS",
    "wof:placetype":"postalcode"
},
  "geometry": {"coordinates":[-0.97815003498061,50.81712004494103],"type":"Point"}
}