{
  "type": "Feature",
  "properties": {
    "iso:country":"GB",
    "wof:name":"SS3 0QN",
    "wof:placetype":"postalcode"
},
  "geometry": {"coordinates":[0.75887972840734,51.56152316150234],"type":"Point"}
}