{
  "type": "Feature",
  "properties": {
    "iso:country": "GB",
    "wof:name": "KT7 0PA",
    "wof:placetype": "postalcode"
  },
  "geometry": {"coordinates":[-0.336696,51.389438],"type":"Point"}
}
