{
  "type": "Feature",
  "properties": {
    "iso:country":"GB",
    "wof:name":"BN43 5WP",
    "wof:placetype":"postalcode"
},
  "geometry": {"coordinates":[-0.28453852867292,50.83923736745592],"type":"Point"}
}