{
  "type": "Feature",
  "properties": {
    "date:inception_lower": "1993-02-01",
    "date:inception_upper": "1993-02-01",
    "iso:country": "GB",
    "wof:name": "EH51 9TD",
    "wof:placetype": "postalcode"
  },
  "geometry": {"coordinates":[-3.591605,56.018313],"type":"Point"}
}
