{
  "type": "Feature",
  "properties": {
    "iso:country": "GB",
    "wof:name": "EX2 8LG",
    "wof:placetype": "postalcode"
  },
  "geometry": {"coordinates":[-3.535571,50.710397],"type":"Point"}
}
