{
  "type": "Feature",
  "properties": {
    "iso:country": "GB",
    "wof:name": "CH41 1FB",
    "wof:placetype": "postalcode"
  },
  "geometry": {"coordinates":[-3.015451,53.406613],"type":"Point"}
}
