{
  "type": "Feature",
  "properties": {
    "iso:country":"GB",
    "wof:name":"CH41 1FB",
    "wof:placetype":"postalcode"
},
  "geometry": {"coordinates":[-3.0154519267896,53.40659619532754],"type":"Point"}
}