{
  "type": "Feature",
  "properties": {
    "iso:country":"GB",
    "wof:name":"RH10 1QE",
    "wof:placetype":"postalcode"
},
  "geometry": {"coordinates":[-0.16978596057864,51.11691311907706],"type":"Point"}
}