{
  "type": "Feature",
  "properties": {
    "iso:country":"GB",
    "wof:name":"ME16 9LG",
    "wof:placetype":"postalcode"
},
  "geometry": {"coordinates":[0.47981539198432,51.26779641610857],"type":"Point"}
}