{
  "type": "Feature",
  "properties": {
    "iso:country": "GB",
    "wof:name": "L7 7BP",
    "wof:placetype": "postalcode"
  },
  "geometry": {"coordinates":[-2.969488,53.402258],"type":"Point"}
}
