{
  "type": "Feature",
  "properties": {
    "date:inception_lower":"2016-09-01",
    "date:inception_upper":"2016-09-30",
    "iso:country":"GB",
    "wof:name":"L7 7BP",
    "wof:placetype":"postalcode"
},
  "geometry": {"coordinates":[-2.969488,53.402258],"type":"Point"}
}