{
  "type": "Feature",
  "properties": {
    "iso:country":"GB",
    "wof:name":"WV4 4TA",
    "wof:placetype":"postalcode"
},
  "geometry": {"coordinates":[-2.17513277698286,52.55869172185808],"type":"Point"}
}