{
  "type": "Feature",
  "properties": {
    "date:inception_lower": "1986-07-01",
    "date:inception_upper": "1986-07-01",
    "iso:country": "GB",
    "wof:name": "LS27 9LR",
    "wof:placetype": "postalcode"
  },
  "geometry": {"coordinates":[-1.613785,53.748146],"type":"Point"}
}
