{
  "type": "Feature",
  "properties": {
    "date:inception_lower":"1980-01-01",
    "date:inception_upper":"1980-01-31",
    "iso:country":"GB",
    "wof:name":"NE30 4NA",
    "wof:placetype":"postalcode"
},
  "geometry": {"coordinates":[-1.426295,55.019716],"type":"Point"}
}