{
  "type": "Feature",
  "properties": {
    "iso:country": "GB",
    "wof:name": "LE17 6JF",
    "wof:placetype": "postalcode"
  },
  "geometry": {"coordinates":[-1.130801,52.453747],"type":"Point"}
}
