{
  "type": "Feature",
  "properties": {
    "date:inception_lower": "1980-01-01",
    "date:inception_upper": "1980-01-01",
    "iso:country": "GB",
    "wof:name": "LE17 6JF",
    "wof:placetype": "postalcode"
  },
  "geometry": {"coordinates":[-1.130801,52.453747],"type":"Point"}
}
