{
  "type": "Feature",
  "properties": {
    "iso:country":"GB",
    "wof:name":"LE17 6JF",
    "wof:placetype":"postalcode"
},
  "geometry": {"coordinates":[-1.13080062178385,52.45374726446569],"type":"Point"}
}