{
  "type": "Feature",
  "properties": {
    "date:inception_lower": "1980-01-01",
    "date:inception_upper": "1980-01-01",
    "iso:country": "GB",
    "wof:name": "TN4 8RT",
    "wof:placetype": "postalcode"
  },
  "geometry": {"coordinates":[0.2274,51.134555],"type":"Point"}
}
