{
  "type": "Feature",
  "properties": {
    "iso:country": "GB",
    "wof:name": "TN4 8RT",
    "wof:placetype": "postalcode"
  },
  "geometry": {"coordinates":[0.2274,51.134555],"type":"Point"}
}
