{
  "type": "Feature",
  "properties": {
    "iso:country":"GB",
    "wof:name":"TN4 8RT",
    "wof:placetype":"postalcode"
},
  "geometry": {"coordinates":[0.2273998224711,51.13455459570404],"type":"Point"}
}