{
  "type": "Feature",
  "properties": {
    "iso:country": "GB",
    "wof:name": "SK22 3AA",
    "wof:placetype": "postalcode"
  },
  "geometry": {"coordinates":[-2.009247,53.362692],"type":"Point"}
}
