{
  "type": "Feature",
  "properties": {
    "iso:country": "GB",
    "wof:name": "SG19 2EU",
    "wof:placetype": "postalcode"
  },
  "geometry": {"coordinates":[-0.163316,52.110492],"type":"Point"}
}
