{
  "type": "Feature",
  "properties": {
    "date:inception_lower": "1980-01-01",
    "date:inception_upper": "1980-01-01",
    "iso:country": "GB",
    "wof:name": "N9 0EH",
    "wof:placetype": "postalcode"
  },
  "geometry": {"coordinates":[-0.057165,51.624747],"type":"Point"}
}
