{
  "type": "Feature",
  "properties": {
    "iso:country": "GB",
    "wof:name": "NG19 0AG",
    "wof:placetype": "postalcode"
  },
  "geometry": {"coordinates":[-1.162852,53.148318],"type":"Point"}
}
