{
  "type": "Feature",
  "properties": {
    "date:inception_lower": "2016-10-01",
    "date:inception_upper": "2016-10-01",
    "iso:country": "GB",
    "wof:name": "AB42 1UZ",
    "wof:placetype": "postalcode"
  },
  "geometry": {"coordinates":[-1.780668,57.509603],"type":"Point"}
}
