{
  "type": "Feature",
  "properties": {
    "iso:country": "GB",
    "wof:name": "CH63 5PA",
    "wof:placetype": "postalcode"
  },
  "geometry": {"coordinates":[-3.029142,53.357417],"type":"Point"}
}
