{
  "type": "Feature",
  "properties": {
    "iso:country": "GB",
    "wof:name": "ST16 3FY",
    "wof:placetype": "postalcode"
  },
  "geometry": {"coordinates":[-2.112813,52.816636],"type":"Point"}
}
