{
  "type": "Feature",
  "properties": {
    "date:inception_lower": "1980-01-01",
    "date:inception_upper": "1980-01-01",
    "iso:country": "GB",
    "wof:name": "BL6 5QR",
    "wof:placetype": "postalcode"
  },
  "geometry": {"coordinates":[-2.551256,53.598275],"type":"Point"}
}
