{
  "type": "Feature",
  "properties": {
    "iso:country":"GB",
    "wof:name":"BL6 5QR",
    "wof:placetype":"postalcode"
},
  "geometry": {"coordinates":[-2.55125581532334,53.59827535849305],"type":"Point"}
}