{
  "type": "Feature",
  "properties": {
    "iso:country":"GB",
    "wof:name":"IP30 0LB",
    "wof:placetype":"postalcode"
},
  "geometry": {"coordinates":[0.77537295065985,52.16188445671845],"type":"Point"}
}