{
  "type": "Feature",
  "properties": {
    "date:inception_lower": "2007-03-01",
    "date:inception_upper": "2007-03-01",
    "iso:country": "GB",
    "wof:name": "ML3 0RW",
    "wof:placetype": "postalcode"
  },
  "geometry": {"coordinates":[-4.068978,55.78626],"type":"Point"}
}
