{
  "type": "Feature",
  "properties": {
    "iso:country":"GB",
    "wof:name":"LL57 3RF",
    "wof:placetype":"postalcode"
},
  "geometry": {"coordinates":[-4.05413079974071,53.17435187099431],"type":"Point"}
}