{
  "type": "Feature",
  "properties": {
    "date:inception_lower": "1987-04-01",
    "date:inception_upper": "1987-04-01",
    "iso:country": "GB",
    "wof:name": "GU17 9LX",
    "wof:placetype": "postalcode"
  },
  "geometry": {"coordinates":[-0.789591,51.324924],"type":"Point"}
}
