{
  "type": "Feature",
  "properties": {
    "iso:country":"GB",
    "wof:name":"GU17 9LX",
    "wof:placetype":"postalcode"
},
  "geometry": {"coordinates":[-0.78959080832515,51.3249242685587],"type":"Point"}
}