{
  "type": "Feature",
  "properties": {
    "date:inception_lower": "2024-03-01",
    "date:inception_upper": "2024-03-01",
    "iso:country": "GB",
    "wof:name": "LA3 3FZ",
    "wof:placetype": "postalcode"
  },
  "geometry": {"coordinates":[-2.838714,54.053765],"type":"Point"}
}
