{
  "type": "Feature",
  "properties": {
    "iso:country":"GB",
    "wof:name":"TS3 7NG",
    "wof:placetype":"postalcode"
},
  "geometry": {"coordinates":[-1.20658169150744,54.55327416717655],"type":"Point"}
}