{
  "type": "Feature",
  "properties": {
    "iso:country":"GB",
    "wof:name":"KA13 7JZ",
    "wof:placetype":"postalcode"
},
  "geometry": {"coordinates":[-4.68097539714661,55.65577904752458],"type":"Point"}
}