{
  "type": "Feature",
  "properties": {
    "date:inception_lower": "1980-01-01",
    "date:inception_upper": "1980-01-01",
    "iso:country": "GB",
    "wof:name": "KA13 7JZ",
    "wof:placetype": "postalcode"
  },
  "geometry": {"coordinates":[-4.680975,55.655779],"type":"Point"}
}
