{
  "type": "Feature",
  "properties": {
    "iso:country":"GB",
    "wof:name":"EX15 3TX",
    "wof:placetype":"postalcode"
},
  "geometry": {"coordinates":[-3.18279085994095,50.92360723145669],"type":"Point"}
}