{
  "type": "Feature",
  "properties": {
    "iso:country": "GB",
    "wof:name": "SO31 7FH",
    "wof:placetype": "postalcode"
  },
  "geometry": {"coordinates":[-1.280425,50.876289],"type":"Point"}
}
