{
  "type": "Feature",
  "properties": {
    "date:inception_lower":"1994-12-01",
    "date:inception_upper":"1994-12-31",
    "iso:country":"GB",
    "wof:name":"SO31 7FH",
    "wof:placetype":"postalcode"
},
  "geometry": {"coordinates":[-1.280425,50.876289],"type":"Point"}
}