{
  "type": "Feature",
  "properties": {
    "iso:country":"GB",
    "wof:name":"SO31 7FH",
    "wof:placetype":"postalcode"
},
  "geometry": {"coordinates":[-1.28042544346152,50.87628943373048],"type":"Point"}
}