{
  "type": "Feature",
  "properties": {
    "iso:country": "GB",
    "wof:name": "GL18 1QW",
    "wof:placetype": "postalcode"
  },
  "geometry": {"coordinates":[-2.416299,51.929473],"type":"Point"}
}
