{
  "type": "Feature",
  "properties": {
    "iso:country":"GB",
    "wof:name":"GL18 1QW",
    "wof:placetype":"postalcode"
},
  "geometry": {"coordinates":[-2.41629867049675,51.92947257175769],"type":"Point"}
}