{
  "type": "Feature",
  "properties": {
    "iso:country": "GB",
    "wof:name": "G53 5ND",
    "wof:placetype": "postalcode"
  },
  "geometry": {"coordinates":[-4.348514,55.833652],"type":"Point"}
}
