{
  "type": "Feature",
  "properties": {
    "iso:country": "GB",
    "wof:name": "KT14 7HA",
    "wof:placetype": "postalcode"
  },
  "geometry": {"coordinates":[-0.472845,51.33339],"type":"Point"}
}
