{
  "type": "Feature",
  "properties": {
    "iso:country": "GB",
    "wof:name": "OL16 4QW",
    "wof:placetype": "postalcode"
  },
  "geometry": {"coordinates":[-2.13856,53.596266],"type":"Point"}
}
