{
  "type": "Feature",
  "properties": {
    "iso:country":"GB",
    "wof:name":"SE1 0UX",
    "wof:placetype":"postalcode"
},
  "geometry": {"coordinates":[-0.10301708367179,51.50516643547348],"type":"Point"}
}