{
  "type": "Feature",
  "properties": {
    "date:inception_lower": "2018-11-01",
    "date:inception_upper": "2018-11-01",
    "iso:country": "GB",
    "wof:name": "BB4 5BD",
    "wof:placetype": "postalcode"
  },
  "geometry": {"coordinates":[-2.317793,53.713658],"type":"Point"}
}
