{
  "type": "Feature",
  "properties": {
    "iso:country": "GB",
    "wof:name": "BB4 5BD",
    "wof:placetype": "postalcode"
  },
  "geometry": {"coordinates":[-2.317793,53.713658],"type":"Point"}
}
