{
  "type": "Feature",
  "properties": {
    "iso:country":"GB",
    "wof:name":"PL7 1SG",
    "wof:placetype":"postalcode"
},
  "geometry": {"coordinates":[-4.07349149909055,50.38600861250154],"type":"Point"}
}