{
  "type": "Feature",
  "properties": {
    "iso:country":"GB",
    "wof:name":"FY8 2HZ",
    "wof:placetype":"postalcode"
},
  "geometry": {"coordinates":[-3.02848576899006,53.76205979246048],"type":"Point"}
}