{
  "type": "Feature",
  "properties": {
    "iso:country": "GB",
    "wof:name": "FY8 2HZ",
    "wof:placetype": "postalcode"
  },
  "geometry": {"coordinates":[-3.028486,53.76206],"type":"Point"}
}
