{
  "type": "Feature",
  "properties": {
    "date:inception_lower":"1987-04-01",
    "date:inception_upper":"1987-04-30",
    "iso:country":"GB",
    "wof:name":"TN2 3JW",
    "wof:placetype":"postalcode"
},
  "geometry": {"coordinates":[0.289076,51.152088],"type":"Point"}
}