{
  "type": "Feature",
  "properties": {
    "iso:country": "GB",
    "wof:name": "TN2 3JW",
    "wof:placetype": "postalcode"
  },
  "geometry": {"coordinates":[0.289076,51.152088],"type":"Point"}
}
