{
  "type": "Feature",
  "properties": {
    "iso:country":"GB",
    "wof:name":"TN35 5EY",
    "wof:placetype":"postalcode"
},
  "geometry": {"coordinates":[0.61905771568495,50.87458069942737],"type":"Point"}
}