{
  "type": "Feature",
  "properties": {
    "iso:country":"GB",
    "wof:name":"NN3 3RQ",
    "wof:placetype":"postalcode"
},
  "geometry": {"coordinates":[-0.84608860781399,52.26667280754568],"type":"Point"}
}