{
  "type": "Feature",
  "properties": {
    "iso:country":"GB",
    "wof:name":"NG24 4JE",
    "wof:placetype":"postalcode"
},
  "geometry": {"coordinates":[-0.81667796480096,53.06386469044021],"type":"Point"}
}