{
  "type": "Feature",
  "properties": {
    "iso:country": "GB",
    "wof:name": "PE9 3DD",
    "wof:placetype": "postalcode"
  },
  "geometry": {"coordinates":[-0.504259,52.649541],"type":"Point"}
}
