{
  "type": "Feature",
  "properties": {
    "date:inception_lower":"2006-07-01",
    "date:inception_upper":"2006-07-31",
    "iso:country":"GB",
    "wof:name":"CW7 1FZ",
    "wof:placetype":"postalcode"
},
  "geometry": {"coordinates":[-2.536489,53.188078],"type":"Point"}
}