{
  "type": "Feature",
  "properties": {
    "iso:country":"GB",
    "wof:name":"CW7 1FZ",
    "wof:placetype":"postalcode"
},
  "geometry": {"coordinates":[-2.53663929211188,53.18803551009138],"type":"Point"}
}