{
  "type": "Feature",
  "properties": {
    "iso:country":"GB",
    "wof:name":"NP20 2LP",
    "wof:placetype":"postalcode"
},
  "geometry": {"coordinates":[-2.99504440377041,51.5749419663648],"type":"Point"}
}