{
  "type": "Feature",
  "properties": {
    "date:inception_lower": "1997-12-01",
    "date:inception_upper": "1997-12-01",
    "iso:country": "GB",
    "wof:name": "OL14 6LG",
    "wof:placetype": "postalcode"
  },
  "geometry": {"coordinates":[-2.101242,53.710543],"type":"Point"}
}
