{
  "type": "Feature",
  "properties": {
    "iso:country":"GB",
    "wof:name":"DH8 5JH",
    "wof:placetype":"postalcode"
},
  "geometry": {"coordinates":[-1.83220846098102,54.86014304722541],"type":"Point"}
}