{
  "type": "Feature",
  "properties": {
    "date:inception_lower":"1980-01-01",
    "date:inception_upper":"1980-01-31",
    "iso:country":"GB",
    "wof:name":"DH8 5JH",
    "wof:placetype":"postalcode"
},
  "geometry": {"coordinates":[-1.832208,54.860143],"type":"Point"}
}