{
  "type": "Feature",
  "properties": {
    "date:inception_lower": "1980-01-01",
    "date:inception_upper": "1980-01-01",
    "iso:country": "GB",
    "wof:name": "CA28 6ET",
    "wof:placetype": "postalcode"
  },
  "geometry": {"coordinates":[-3.580417,54.561654],"type":"Point"}
}
