{
  "type": "Feature",
  "properties": {
    "iso:country": "GB",
    "wof:name": "EH24 9DY",
    "wof:placetype": "postalcode"
  },
  "geometry": {"coordinates":[-3.155976,55.831493],"type":"Point"}
}
