{
  "type": "Feature",
  "properties": {
    "iso:country":"GB",
    "wof:name":"EH24 9DY",
    "wof:placetype":"postalcode"
},
  "geometry": {"coordinates":[-3.15597592227178,55.83149259250069],"type":"Point"}
}