{
  "type": "Feature",
  "properties": {
    "iso:country":"GB",
    "wof:name":"WC1B 5BA",
    "wof:placetype":"postalcode"
},
  "geometry": {"coordinates":[-0.12408857789483,51.52224046010269],"type":"Point"}
}