{
  "type": "Feature",
  "properties": {
    "date:inception_lower": "1980-01-01",
    "date:inception_upper": "1980-01-01",
    "iso:country": "GB",
    "wof:name": "L25 6EB",
    "wof:placetype": "postalcode"
  },
  "geometry": {"coordinates":[-2.868047,53.380667],"type":"Point"}
}
