{
  "type": "Feature",
  "properties": {
    "iso:country":"GB",
    "wof:name":"L25 6EB",
    "wof:placetype":"postalcode"
},
  "geometry": {"coordinates":[-2.86804740700041,53.3806665903174],"type":"Point"}
}