{
  "type": "Feature",
  "properties": {
    "iso:country":"GB",
    "wof:name":"NG25 0PT",
    "wof:placetype":"postalcode"
},
  "geometry": {"coordinates":[-0.93932732379582,53.08105822703579],"type":"Point"}
}