{
  "type": "Feature",
  "properties": {
    "iso:country":"GB",
    "wof:name":"HD8 8JN",
    "wof:placetype":"postalcode"
},
  "geometry": {"coordinates":[-1.71154302004885,53.60010704775577],"type":"Point"}
}