{
  "type": "Feature",
  "properties": {
    "date:inception_lower": "1980-01-01",
    "date:inception_upper": "1980-01-01",
    "iso:country": "GB",
    "wof:name": "TA7 0BG",
    "wof:placetype": "postalcode"
  },
  "geometry": {"coordinates":[-2.999863,51.074791],"type":"Point"}
}
