{
  "type": "Feature",
  "properties": {
    "iso:country":"GB",
    "wof:name":"DA9 9WT",
    "wof:placetype":"postalcode"
},
  "geometry": {"coordinates":[0.27925161825437,51.44628039413594],"type":"Point"}
}