{
  "type": "Feature",
  "properties": {
    "iso:country": "GB",
    "wof:name": "DA9 9WT",
    "wof:placetype": "postalcode"
  },
  "geometry": {"coordinates":[0.27928,51.44628],"type":"Point"}
}
