{
  "type": "Feature",
  "properties": {
    "date:inception_lower": "1986-01-01",
    "date:inception_upper": "1986-01-01",
    "iso:country": "GB",
    "wof:name": "SO51 8EE",
    "wof:placetype": "postalcode"
  },
  "geometry": {"coordinates":[-1.494938,50.991249],"type":"Point"}
}
