{
  "type": "Feature",
  "properties": {
    "iso:country":"GB",
    "wof:name":"SO51 8EE",
    "wof:placetype":"postalcode"
},
  "geometry": {"coordinates":[-1.49493844993002,50.99124912248625],"type":"Point"}
}