{
  "type": "Feature",
  "properties": {
    "iso:country":"GB",
    "wof:name":"LN5 8AU",
    "wof:placetype":"postalcode"
},
  "geometry": {"coordinates":[-0.54694155324452,53.21785589473226],"type":"Point"}
}