{
  "type": "Feature",
  "properties": {
    "date:inception_lower": "1980-01-01",
    "date:inception_upper": "1980-01-01",
    "iso:country": "GB",
    "wof:name": "LN5 8AU",
    "wof:placetype": "postalcode"
  },
  "geometry": {"coordinates":[-0.546942,53.217856],"type":"Point"}
}
