{
  "type": "Feature",
  "properties": {
    "date:inception_lower": "1998-12-01",
    "date:inception_upper": "1998-12-01",
    "iso:country": "GB",
    "wof:name": "B77 3LB",
    "wof:placetype": "postalcode"
  },
  "geometry": {"coordinates":[-1.676223,52.633526],"type":"Point"}
}
