{
  "type": "Feature",
  "properties": {
    "iso:country":"GB",
    "wof:name":"B77 3LB",
    "wof:placetype":"postalcode"
},
  "geometry": {"coordinates":[-1.67622351582085,52.63352555869984],"type":"Point"}
}