{
  "type": "Feature",
  "properties": {
    "iso:country": "GB",
    "wof:name": "MK42 8JD",
    "wof:placetype": "postalcode"
  },
  "geometry": {"coordinates":[-0.490862,52.116938],"type":"Point"}
}
