{
  "type": "Feature",
  "properties": {
    "iso:country": "GB",
    "wof:name": "AB25 3UY",
    "wof:placetype": "postalcode"
  },
  "geometry": {"coordinates":[-2.111816,57.158199],"type":"Point"}
}
