{
  "type": "Feature",
  "properties": {
    "iso:country":"GB",
    "wof:name":"AB25 3UY",
    "wof:placetype":"postalcode"
},
  "geometry": {"coordinates":[-2.11181655231459,57.15819915147596],"type":"Point"}
}