{
  "type": "Feature",
  "properties": {
    "date:inception_lower": "2023-12-01",
    "date:inception_upper": "2023-12-01",
    "iso:country": "GB",
    "wof:name": "PE29 1AU",
    "wof:placetype": "postalcode"
  },
  "geometry": {"coordinates":[-0.178281,52.339384],"type":"Point"}
}
