{
  "type": "Feature",
  "properties": {
    "iso:country":"GB",
    "wof:name":"TS5 5HZ",
    "wof:placetype":"postalcode"
},
  "geometry": {"coordinates":[-1.26194006144047,54.55290543853252],"type":"Point"}
}