{
  "type": "Feature",
  "properties": {
    "date:inception_lower": "1980-01-01",
    "date:inception_upper": "1980-01-01",
    "iso:country": "GB",
    "wof:name": "TS5 5HZ",
    "wof:placetype": "postalcode"
  },
  "geometry": {"coordinates":[-1.26194,54.552905],"type":"Point"}
}
