{
  "type": "Feature",
  "properties": {
    "iso:country": "GB",
    "wof:name": "ME20 7LE",
    "wof:placetype": "postalcode"
  },
  "geometry": {"coordinates":[0.46986,51.297614],"type":"Point"}
}
