{
  "type": "Feature",
  "properties": {
    "iso:country":"GB",
    "wof:name":"ME20 7LE",
    "wof:placetype":"postalcode"
},
  "geometry": {"coordinates":[0.46985977193614,51.29761393231026],"type":"Point"}
}