{
  "type": "Feature",
  "properties": {
    "date:inception_lower": "2015-08-01",
    "date:inception_upper": "2015-08-01",
    "iso:country": "GB",
    "wof:name": "EX5 7DJ",
    "wof:placetype": "postalcode"
  },
  "geometry": {"coordinates":[-3.412087,50.750308],"type":"Point"}
}
