{
  "type": "Feature",
  "properties": {
    "iso:country": "GB",
    "wof:name": "EX5 7DJ",
    "wof:placetype": "postalcode"
  },
  "geometry": {"coordinates":[-3.412087,50.750308],"type":"Point"}
}
