{
  "type": "Feature",
  "properties": {
    "date:inception_lower": "1980-01-01",
    "date:inception_upper": "1980-01-01",
    "iso:country": "GB",
    "wof:name": "CF37 3BD",
    "wof:placetype": "postalcode"
  },
  "geometry": {"coordinates":[-3.342828,51.621724],"type":"Point"}
}
