{
  "type": "Feature",
  "properties": {
    "iso:country":"GB",
    "wof:name":"CF37 3BD",
    "wof:placetype":"postalcode"
},
  "geometry": {"coordinates":[-3.34282844325723,51.62172359565048],"type":"Point"}
}