{
  "type": "Feature",
  "properties": {
    "iso:country":"GB",
    "wof:name":"LE16 7BD",
    "wof:placetype":"postalcode"
},
  "geometry": {"coordinates":[-0.92550938576744,52.48356317977847],"type":"Point"}
}