{
  "type": "Feature",
  "properties": {
    "iso:country":"GB",
    "wof:name":"DH3 4NJ",
    "wof:placetype":"postalcode"
},
  "geometry": {"coordinates":[-1.54427626206883,54.83810665931389],"type":"Point"}
}