{
  "type": "Feature",
  "properties": {
    "iso:country": "GB",
    "wof:name": "EX5 4JZ",
    "wof:placetype": "postalcode"
  },
  "geometry": {"coordinates":[-3.481518,50.817587],"type":"Point"}
}
