{
  "type": "Feature",
  "properties": {
    "iso:country":"GB",
    "wof:name":"KA11 3AE",
    "wof:placetype":"postalcode"
},
  "geometry": {"coordinates":[-4.58924218140589,55.6122230724744],"type":"Point"}
}