{
  "type": "Feature",
  "properties": {
    "date:inception_lower":"1987-04-01",
    "date:inception_upper":"1987-04-30",
    "iso:country":"GB",
    "wof:name":"WA14 1TF",
    "wof:placetype":"postalcode"
},
  "geometry": {"coordinates":[-2.341916,53.401327],"type":"Point"}
}