{
  "type": "Feature",
  "properties": {
    "iso:country":"GB",
    "wof:name":"PA34 4LS",
    "wof:placetype":"postalcode"
},
  "geometry": {"coordinates":[-5.48077154028411,56.41084555884185],"type":"Point"}
}