{
  "type": "Feature",
  "properties": {
    "iso:country": "GB",
    "wof:name": "PA34 4LS",
    "wof:placetype": "postalcode"
  },
  "geometry": {"coordinates":[-5.480771,56.410846],"type":"Point"}
}
