{
  "type": "Feature",
  "properties": {
    "date:inception_lower": "1980-01-01",
    "date:inception_upper": "1980-01-01",
    "iso:country": "GB",
    "wof:name": "SN7 7AE",
    "wof:placetype": "postalcode"
  },
  "geometry": {"coordinates":[-1.58273,51.658085],"type":"Point"}
}
