{
  "type": "Feature",
  "properties": {
    "iso:country":"GB",
    "wof:name":"SA15 1PE",
    "wof:placetype":"postalcode"
},
  "geometry": {"coordinates":[-4.15254959282913,51.67806351695284],"type":"Point"}
}