{
  "type": "Feature",
  "properties": {
    "iso:country":"GB",
    "wof:name":"WS6 7BL",
    "wof:placetype":"postalcode"
},
  "geometry": {"coordinates":[-2.02707223516917,52.66052861949817],"type":"Point"}
}