{
  "type": "Feature",
  "properties": {
    "iso:country":"GB",
    "wof:name":"OX17 1BZ",
    "wof:placetype":"postalcode"
},
  "geometry": {"coordinates":[-1.39869270686919,52.12489885027452],"type":"Point"}
}