{
  "type": "Feature",
  "properties": {
    "iso:country":"GB",
    "wof:name":"SO21 3PS",
    "wof:placetype":"postalcode"
},
  "geometry": {"coordinates":[-1.30804770235436,51.15473360387104],"type":"Point"}
}