{
  "type": "Feature",
  "properties": {
    "date:inception_lower": "1980-01-01",
    "date:inception_upper": "1980-01-01",
    "iso:country": "GB",
    "wof:name": "N1 7LU",
    "wof:placetype": "postalcode"
  },
  "geometry": {"coordinates":[-0.089805,51.528557],"type":"Point"}
}
