{
  "type": "Feature",
  "properties": {
    "date:inception_lower": "1999-12-01",
    "date:inception_upper": "1999-12-01",
    "iso:country": "GB",
    "wof:name": "NP26 3FG",
    "wof:placetype": "postalcode"
  },
  "geometry": {"coordinates":[-2.81583,51.583536],"type":"Point"}
}
