{
  "type": "Feature",
  "properties": {
    "iso:country":"GB",
    "wof:name":"NP26 3FG",
    "wof:placetype":"postalcode"
},
  "geometry": {"coordinates":[-2.81583041570368,51.58353619580158],"type":"Point"}
}