{
  "type": "Feature",
  "properties": {
    "date:inception_lower": "2017-08-01",
    "date:inception_upper": "2017-08-01",
    "iso:country": "GB",
    "wof:name": "SW6 2XD",
    "wof:placetype": "postalcode"
  },
  "geometry": {"coordinates":[-0.185845,51.475094],"type":"Point"}
}
