{
  "type": "Feature",
  "properties": {
    "iso:country":"GB",
    "wof:name":"NG19 6UB",
    "wof:placetype":"postalcode"
},
  "geometry": {"coordinates":[-1.23103587409057,53.1439951287111],"type":"Point"}
}