{
  "type": "Feature",
  "properties": {
    "iso:country": "GB",
    "wof:name": "NG19 6UB",
    "wof:placetype": "postalcode"
  },
  "geometry": {"coordinates":[-1.231036,53.143995],"type":"Point"}
}
