{
  "type": "Feature",
  "properties": {
    "iso:country": "GB",
    "wof:name": "SY13 1JB",
    "wof:placetype": "postalcode"
  },
  "geometry": {"coordinates":[-2.700106,52.964245],"type":"Point"}
}
