{
  "type": "Feature",
  "properties": {
    "iso:country":"GB",
    "wof:name":"SY13 1JB",
    "wof:placetype":"postalcode"
},
  "geometry": {"coordinates":[-2.70010562587087,52.96424470798802],"type":"Point"}
}