{
  "type": "Feature",
  "properties": {
    "iso:country":"GB",
    "wof:name":"B14 4LB",
    "wof:placetype":"postalcode"
},
  "geometry": {"coordinates":[-1.86696471069738,52.41262445775772],"type":"Point"}
}