{
  "type": "Feature",
  "properties": {
    "date:inception_lower": "2019-09-01",
    "date:inception_upper": "2019-09-01",
    "iso:country": "GB",
    "wof:name": "TF4 2SX",
    "wof:placetype": "postalcode"
  },
  "geometry": {"coordinates":[-2.481541,52.671542],"type":"Point"}
}
