{
  "type": "Feature",
  "properties": {
    "iso:country": "GB",
    "wof:name": "TF4 2SX",
    "wof:placetype": "postalcode"
  },
  "geometry": {"coordinates":[-2.4816,52.671541],"type":"Point"}
}
