{
  "type": "Feature",
  "properties": {
    "iso:country":"GB",
    "wof:name":"SW6 6AB",
    "wof:placetype":"postalcode"
},
  "geometry": {"coordinates":[-0.21472673852771,51.47952907347938],"type":"Point"}
}