{
  "type": "Feature",
  "properties": {
    "date:inception_lower": "1980-01-01",
    "date:inception_upper": "1980-01-01",
    "iso:country": "GB",
    "wof:name": "PO30 4LX",
    "wof:placetype": "postalcode"
  },
  "geometry": {"coordinates":[-1.357574,50.708907],"type":"Point"}
}
