{
  "type": "Feature",
  "properties": {
    "iso:country": "GB",
    "wof:name": "PO30 4LX",
    "wof:placetype": "postalcode"
  },
  "geometry": {"coordinates":[-1.357574,50.708907],"type":"Point"}
}
