{
  "type": "Feature",
  "properties": {
    "iso:country":"GB",
    "wof:name":"PO30 4LX",
    "wof:placetype":"postalcode"
},
  "geometry": {"coordinates":[-1.35084013847859,50.71011285283378],"type":"Point"}
}