{
  "type": "Feature",
  "properties": {
    "iso:country": "GB",
    "wof:name": "DG1 2JS",
    "wof:placetype": "postalcode"
  },
  "geometry": {"coordinates":[-3.604802,55.067475],"type":"Point"}
}
