{
  "type": "Feature",
  "properties": {
    "iso:country":"GB",
    "wof:name":"NG22 9JH",
    "wof:placetype":"postalcode"
},
  "geometry": {"coordinates":[-0.99082334518947,53.20839937920287],"type":"Point"}
}