{
  "type": "Feature",
  "properties": {
    "date:inception_lower": "1980-01-01",
    "date:inception_upper": "1980-01-01",
    "iso:country": "GB",
    "wof:name": "IG10 3EL",
    "wof:placetype": "postalcode"
  },
  "geometry": {"coordinates":[0.061628,51.639112],"type":"Point"}
}
