{
  "type": "Feature",
  "properties": {
    "iso:country": "GB",
    "wof:name": "L35 5BY",
    "wof:placetype": "postalcode"
  },
  "geometry": {"coordinates":[-2.798138,53.420624],"type":"Point"}
}
