{
  "type": "Feature",
  "properties": {
    "iso:country": "GB",
    "wof:name": "PE25 1DX",
    "wof:placetype": "postalcode"
  },
  "geometry": {"coordinates":[0.343561,53.158048],"type":"Point"}
}
