{
  "type": "Feature",
  "properties": {
    "iso:country":"GB",
    "wof:name":"LS16 8HB",
    "wof:placetype":"postalcode"
},
  "geometry": {"coordinates":[-1.58092684890228,53.8439739657093],"type":"Point"}
}