{
  "type": "Feature",
  "properties": {
    "date:inception_lower": "2016-08-01",
    "date:inception_upper": "2016-08-01",
    "iso:country": "GB",
    "wof:name": "CF5 6FB",
    "wof:placetype": "postalcode"
  },
  "geometry": {"coordinates":[-3.268269,51.479052],"type":"Point"}
}
