{
  "type": "Feature",
  "properties": {
    "iso:country":"GB",
    "wof:name":"SY23 2WX",
    "wof:placetype":"postalcode"
},
  "geometry": {"coordinates":[-4.04358407893229,52.40346356783485],"type":"Point"}
}