{
  "type": "Feature",
  "properties": {
    "iso:country":"GB",
    "wof:name":"MK6 2BT",
    "wof:placetype":"postalcode"
},
  "geometry": {"coordinates":[-0.74336238250236,52.03566167790857],"type":"Point"}
}