{
  "type": "Feature",
  "properties": {
    "date:inception_lower": "2021-09-01",
    "date:inception_upper": "2021-09-01",
    "iso:country": "GB",
    "wof:name": "WF9 4FA",
    "wof:placetype": "postalcode"
  },
  "geometry": {"coordinates":[-1.35489,53.615488],"type":"Point"}
}
