{
  "type": "Feature",
  "properties": {
    "iso:country": "GB",
    "wof:name": "CV6 4QL",
    "wof:placetype": "postalcode"
  },
  "geometry": {"coordinates":[-1.525321,52.457551],"type":"Point"}
}
