{
  "type": "Feature",
  "properties": {
    "iso:country":"GB",
    "wof:name":"OL10 4QD",
    "wof:placetype":"postalcode"
},
  "geometry": {"coordinates":[-2.2297925856281,53.59383327939607],"type":"Point"}
}