{
  "type": "Feature",
  "properties": {
    "iso:country": "GB",
    "wof:name": "OL10 4QD",
    "wof:placetype": "postalcode"
  },
  "geometry": {"coordinates":[-2.229791,53.593894],"type":"Point"}
}
