{
  "type": "Feature",
  "properties": {
    "iso:country":"GB",
    "wof:name":"NG16 5FG",
    "wof:placetype":"postalcode"
},
  "geometry": {"coordinates":[-1.28371152951617,53.05195036961116],"type":"Point"}
}