{
  "type": "Feature",
  "properties": {
    "iso:country":"GB",
    "wof:name":"L34 5SG",
    "wof:placetype":"postalcode"
},
  "geometry": {"coordinates":[-2.7984909684459,53.42740861350936],"type":"Point"}
}