{
  "type": "Feature",
  "properties": {
    "date:inception_lower": "2021-05-01",
    "date:inception_upper": "2021-05-01",
    "iso:country": "GB",
    "wof:name": "CT12 4FL",
    "wof:placetype": "postalcode"
  },
  "geometry": {"coordinates":[1.277658,51.339613],"type":"Point"}
}
