{
  "type": "Feature",
  "properties": {
    "iso:country":"GB",
    "wof:name":"BD7 1JG",
    "wof:placetype":"postalcode"
},
  "geometry": {"coordinates":[-1.76339712969375,53.78776710960182],"type":"Point"}
}