{
  "type": "Feature",
  "properties": {
    "date:inception_lower": "2008-09-01",
    "date:inception_upper": "2008-09-01",
    "iso:country": "GB",
    "wof:name": "BD7 1JG",
    "wof:placetype": "postalcode"
  },
  "geometry": {"coordinates":[-1.763397,53.787767],"type":"Point"}
}
