{
  "type": "Feature",
  "properties": {
    "iso:country":"GB",
    "wof:name":"BN21 2HU",
    "wof:placetype":"postalcode"
},
  "geometry": {"coordinates":[0.27278069118047,50.77729443877107],"type":"Point"}
}