{
  "type": "Feature",
  "properties": {
    "date:inception_lower": "1980-01-01",
    "date:inception_upper": "1980-01-01",
    "iso:country": "GB",
    "wof:name": "BN21 2HU",
    "wof:placetype": "postalcode"
  },
  "geometry": {"coordinates":[0.272781,50.777294],"type":"Point"}
}
