{
  "type": "Feature",
  "properties": {
    "date:inception_lower": "2013-09-01",
    "date:inception_upper": "2013-09-01",
    "iso:country": "GB",
    "wof:name": "ST1 3GD",
    "wof:placetype": "postalcode"
  },
  "geometry": {"coordinates":[-2.165383,53.019713],"type":"Point"}
}
