{
  "type": "Feature",
  "properties": {
    "date:inception_lower":"1995-12-01",
    "date:inception_upper":"1995-12-31",
    "iso:country":"GB",
    "wof:name":"KA22 8HD",
    "wof:placetype":"postalcode"
},
  "geometry": {"coordinates":[-4.81319,55.643567],"type":"Point"}
}