{
  "type": "Feature",
  "properties": {
    "iso:country":"GB",
    "wof:name":"BS8 4HZ",
    "wof:placetype":"postalcode"
},
  "geometry": {"coordinates":[-2.62008731215816,51.45584906529717],"type":"Point"}
}