{
  "type": "Feature",
  "properties": {
    "iso:country":"GB",
    "wof:name":"BA9 9AN",
    "wof:placetype":"postalcode"
},
  "geometry": {"coordinates":[-2.41412891103869,51.05537778057878],"type":"Point"}
}