{
  "type": "Feature",
  "properties": {
    "iso:country": "GB",
    "wof:name": "TQ11 0BH",
    "wof:placetype": "postalcode"
  },
  "geometry": {"coordinates":[-3.784338,50.484181],"type":"Point"}
}
