{
  "type": "Feature",
  "properties": {
    "iso:country":"GB",
    "wof:name":"TQ11 0BH",
    "wof:placetype":"postalcode"
},
  "geometry": {"coordinates":[-3.78433792584191,50.48418059860241],"type":"Point"}
}