{
  "type": "Feature",
  "properties": {
    "date:inception_lower": "1999-06-01",
    "date:inception_upper": "1999-06-01",
    "iso:country": "GB",
    "wof:name": "TR3 6GP",
    "wof:placetype": "postalcode"
  },
  "geometry": {"coordinates":[-5.111342,50.26289],"type":"Point"}
}
