{
  "type": "Feature",
  "properties": {
    "iso:country":"GB",
    "wof:name":"TR3 6GP",
    "wof:placetype":"postalcode"
},
  "geometry": {"coordinates":[-5.11134198546015,50.26288958745597],"type":"Point"}
}