{
  "type": "Feature",
  "properties": {
    "iso:country": "GB",
    "wof:name": "NG34 8RG",
    "wof:placetype": "postalcode"
  },
  "geometry": {"coordinates":[-0.433069,53.051035],"type":"Point"}
}
