{
  "type": "Feature",
  "properties": {
    "iso:country":"GB",
    "wof:name":"NG34 8RG",
    "wof:placetype":"postalcode"
},
  "geometry": {"coordinates":[-0.43306943366655,53.05103493202033],"type":"Point"}
}