{
  "type": "Feature",
  "properties": {
    "iso:country":"GB",
    "wof:name":"BS30 8AQ",
    "wof:placetype":"postalcode"
},
  "geometry": {"coordinates":[-2.48949849400479,51.44313268005805],"type":"Point"}
}