{
  "type": "Feature",
  "properties": {
    "date:inception_lower": "1980-01-01",
    "date:inception_upper": "1980-01-01",
    "iso:country": "GB",
    "wof:name": "ML2 7NX",
    "wof:placetype": "postalcode"
  },
  "geometry": {"coordinates":[-3.928631,55.774433],"type":"Point"}
}
