{
  "type": "Feature",
  "properties": {
    "iso:country":"GB",
    "wof:name":"ML2 7NX",
    "wof:placetype":"postalcode"
},
  "geometry": {"coordinates":[-3.92863148868514,55.7744328101839],"type":"Point"}
}