{
  "type": "Feature",
  "properties": {
    "iso:country":"GB",
    "wof:name":"S36 2TE",
    "wof:placetype":"postalcode"
},
  "geometry": {"coordinates":[-1.57701152197701,53.47436391762272],"type":"Point"}
}