{
  "type": "Feature",
  "properties": {
    "date:inception_lower": "2002-05-01",
    "date:inception_upper": "2002-05-01",
    "iso:country": "GB",
    "wof:name": "WN3 6NA",
    "wof:placetype": "postalcode"
  },
  "geometry": {"coordinates":[-2.669796,53.515111],"type":"Point"}
}
