{
  "type": "Feature",
  "properties": {
    "iso:country": "GB",
    "wof:name": "WN3 6NA",
    "wof:placetype": "postalcode"
  },
  "geometry": {"coordinates":[-2.669796,53.515111],"type":"Point"}
}
