{
  "type": "Feature",
  "properties": {
    "date:inception_lower":"2009-06-01",
    "date:inception_upper":"2009-06-30",
    "iso:country":"GB",
    "wof:name":"LE2 7AH",
    "wof:placetype":"postalcode"
},
  "geometry": {"coordinates":[-1.14677,52.621736],"type":"Point"}
}