{
  "type": "Feature",
  "properties": {
    "iso:country":"GB",
    "wof:name":"LE2 7AH",
    "wof:placetype":"postalcode"
},
  "geometry": {"coordinates":[-1.14676987075265,52.62173615682568],"type":"Point"}
}