{
  "type": "Feature",
  "properties": {
    "date:inception_lower": "1980-01-01",
    "date:inception_upper": "1980-01-01",
    "iso:country": "GB",
    "wof:name": "DL10 5NS",
    "wof:placetype": "postalcode"
  },
  "geometry": {"coordinates":[-1.694798,54.471625],"type":"Point"}
}
