{
  "type": "Feature",
  "properties": {
    "iso:country": "GB",
    "wof:name": "DL10 5NS",
    "wof:placetype": "postalcode"
  },
  "geometry": {"coordinates":[-1.694798,54.471625],"type":"Point"}
}
