{
  "type": "Feature",
  "properties": {
    "iso:country": "GB",
    "wof:name": "DL10 5NS",
    "wof:placetype": "postalcode"
  },
  "geometry": {"coordinates":[-1.69452,54.471786],"type":"Point"}
}
