{
  "type": "Feature",
  "properties": {
    "iso:country":"GB",
    "wof:name":"WA6 6EB",
    "wof:placetype":"postalcode"
},
  "geometry": {"coordinates":[-2.73173330916533,53.28555215204757],"type":"Point"}
}