{
  "type": "Feature",
  "properties": {
    "iso:country": "GB",
    "wof:name": "WA6 6EB",
    "wof:placetype": "postalcode"
  },
  "geometry": {"coordinates":[-2.731733,53.285552],"type":"Point"}
}
