{
  "type": "Feature",
  "properties": {
    "iso:country": "GB",
    "wof:name": "RH14 0SN",
    "wof:placetype": "postalcode"
  },
  "geometry": {"coordinates":[-0.51706,51.073461],"type":"Point"}
}
