{
  "type": "Feature",
  "properties": {
    "iso:country":"GB",
    "wof:name":"RG7 3RY",
    "wof:placetype":"postalcode"
},
  "geometry": {"coordinates":[-1.0663280467058,51.37974486256127],"type":"Point"}
}