{
  "type": "Feature",
  "properties": {
    "date:inception_lower": "1980-01-01",
    "date:inception_upper": "1980-01-01",
    "iso:country": "GB",
    "wof:name": "RG7 3RY",
    "wof:placetype": "postalcode"
  },
  "geometry": {"coordinates":[-1.066328,51.379745],"type":"Point"}
}
