{
  "type": "Feature",
  "properties": {
    "iso:country": "GB",
    "wof:name": "YO22 4PS",
    "wof:placetype": "postalcode"
  },
  "geometry": {"coordinates":[-0.570202,54.441782],"type":"Point"}
}
