{
  "type": "Feature",
  "properties": {
    "date:inception_lower":"1992-01-01",
    "date:inception_upper":"1992-01-31",
    "iso:country":"GB",
    "wof:name":"YO22 4PS",
    "wof:placetype":"postalcode"
},
  "geometry": {"coordinates":[-0.570202,54.441782],"type":"Point"}
}