{
  "type": "Feature",
  "properties": {
    "date:inception_lower": "1990-02-01",
    "date:inception_upper": "1990-02-01",
    "iso:country": "GB",
    "wof:name": "ME2 4LW",
    "wof:placetype": "postalcode"
  },
  "geometry": {"coordinates":[0.516826,51.394536],"type":"Point"}
}
