{
  "type": "Feature",
  "properties": {
    "date:inception_lower":"1980-01-01",
    "date:inception_upper":"1980-01-31",
    "iso:country":"GB",
    "wof:name":"HR9 5UF",
    "wof:placetype":"postalcode"
},
  "geometry": {"coordinates":[-2.593478,51.903888],"type":"Point"}
}