{
  "type": "Feature",
  "properties": {
    "iso:country":"GB",
    "wof:name":"HR9 5UF",
    "wof:placetype":"postalcode"
},
  "geometry": {"coordinates":[-2.59347773177558,51.90388831364303],"type":"Point"}
}