{
  "type": "Feature",
  "properties": {
    "iso:country":"GB",
    "wof:name":"CR7 8AU",
    "wof:placetype":"postalcode"
},
  "geometry": {"coordinates":[-0.10355725752267,51.4035854269674],"type":"Point"}
}