{
  "type": "Feature",
  "properties": {
    "iso:country":"GB",
    "wof:name":"SE15 2HJ",
    "wof:placetype":"postalcode"
},
  "geometry": {"coordinates":[-0.05616075328271,51.47290694153254],"type":"Point"}
}