{
  "type": "Feature",
  "properties": {
    "iso:country": "GB",
    "wof:name": "SE15 2HJ",
    "wof:placetype": "postalcode"
  },
  "geometry": {"coordinates":[-0.056161,51.472907],"type":"Point"}
}
