{
  "type": "Feature",
  "properties": {
    "iso:country": "GB",
    "wof:name": "CV11 5TZ",
    "wof:placetype": "postalcode"
  },
  "geometry": {"coordinates":[-1.469626,52.5218],"type":"Point"}
}
