{
  "type": "Feature",
  "properties": {
    "iso:country": "GB",
    "wof:name": "EN9 1DU",
    "wof:placetype": "postalcode"
  },
  "geometry": {"coordinates":[-0.003058,51.686838],"type":"Point"}
}
