{
  "type": "Feature",
  "properties": {
    "iso:country":"GB",
    "wof:name":"TW18 2JX",
    "wof:placetype":"postalcode"
},
  "geometry": {"coordinates":[-0.50681516910754,51.42461406745411],"type":"Point"}
}