{
  "type": "Feature",
  "properties": {
    "iso:country":"GB",
    "wof:name":"IP2 9YY",
    "wof:placetype":"postalcode"
},
  "geometry": {"coordinates":[1.12980517993127,52.03218293497849],"type":"Point"}
}