{
  "type": "Feature",
  "properties": {
    "iso:country": "GB",
    "wof:name": "HP8 4EN",
    "wof:placetype": "postalcode"
  },
  "geometry": {"coordinates":[-0.574458,51.632699],"type":"Point"}
}
