{
  "type": "Feature",
  "properties": {
    "iso:country":"GB",
    "wof:name":"HP8 4EN",
    "wof:placetype":"postalcode"
},
  "geometry": {"coordinates":[-0.57453646365691,51.63268779049668],"type":"Point"}
}