{
  "type": "Feature",
  "properties": {
    "iso:country": "GB",
    "wof:name": "WR4 9RZ",
    "wof:placetype": "postalcode"
  },
  "geometry": {"coordinates":[-2.19528,52.203401],"type":"Point"}
}
