{
  "type": "Feature",
  "properties": {
    "iso:country":"GB",
    "wof:name":"WR4 9RZ",
    "wof:placetype":"postalcode"
},
  "geometry": {"coordinates":[-2.19531354420525,52.2033974294914],"type":"Point"}
}