{
  "type": "Feature",
  "properties": {
    "iso:country":"GB",
    "wof:name":"SO23 7NP",
    "wof:placetype":"postalcode"
},
  "geometry": {"coordinates":[-1.30690494301118,51.10403794805169],"type":"Point"}
}