{
  "type": "Feature",
  "properties": {
    "date:inception_lower": "2018-01-01",
    "date:inception_upper": "2018-01-01",
    "iso:country": "GB",
    "wof:name": "SY7 0QN",
    "wof:placetype": "postalcode"
  },
  "geometry": {"coordinates":[-2.877853,52.367233],"type":"Point"}
}
