{
  "type": "Feature",
  "properties": {
    "iso:country":"GB",
    "wof:name":"NE2 1AD",
    "wof:placetype":"postalcode"
},
  "geometry": {"coordinates":[-1.59975891946957,54.97734813130553],"type":"Point"}
}