{
  "type": "Feature",
  "properties": {
    "iso:country":"GB",
    "wof:name":"NW10 6NF",
    "wof:placetype":"postalcode"
},
  "geometry": {"coordinates":[-0.25499012456902,51.52712041331981],"type":"Point"}
}