{
  "type": "Feature",
  "properties": {
    "date:inception_lower": "2020-10-01",
    "date:inception_upper": "2020-10-01",
    "iso:country": "GB",
    "wof:name": "CM18 6WZ",
    "wof:placetype": "postalcode"
  },
  "geometry": {"coordinates":[0.093959,51.771744],"type":"Point"}
}
