{
  "type": "Feature",
  "properties": {
    "iso:country":"GB",
    "wof:name":"TQ12 1RH",
    "wof:placetype":"postalcode"
},
  "geometry": {"coordinates":[-3.62845635199328,50.53280214903179],"type":"Point"}
}