{
  "type": "Feature",
  "properties": {
    "iso:country": "GB",
    "wof:name": "TQ12 1RH",
    "wof:placetype": "postalcode"
  },
  "geometry": {"coordinates":[-3.628456,50.532802],"type":"Point"}
}
