{
  "type": "Feature",
  "properties": {
    "iso:country": "GB",
    "wof:name": "BS48 1LL",
    "wof:placetype": "postalcode"
  },
  "geometry": {"coordinates":[-2.721135,51.436333],"type":"Point"}
}
