{
  "type": "Feature",
  "properties": {
    "date:inception_lower": "1997-12-01",
    "date:inception_upper": "1997-12-01",
    "iso:country": "GB",
    "wof:name": "BS48 1LL",
    "wof:placetype": "postalcode"
  },
  "geometry": {"coordinates":[-2.720976,51.43628],"type":"Point"}
}
