{
  "type": "Feature",
  "properties": {
    "iso:country": "GB",
    "wof:name": "BS48 1LL",
    "wof:placetype": "postalcode"
  },
  "geometry": {"coordinates":[-2.720976,51.43628],"type":"Point"}
}
