{
  "type": "Feature",
  "properties": {
    "date:inception_lower":"1980-01-01",
    "date:inception_upper":"1980-01-31",
    "iso:country":"GB",
    "wof:name":"WV11 3LQ",
    "wof:placetype":"postalcode"
},
  "geometry": {"coordinates":[-2.062959,52.602369],"type":"Point"}
}