{
  "type": "Feature",
  "properties": {
    "iso:country":"GB",
    "wof:name":"NE1 2PN",
    "wof:placetype":"postalcode"
},
  "geometry": {"coordinates":[-1.59172167247702,54.97493109016629],"type":"Point"}
}