{
  "type": "Feature",
  "properties": {
    "date:inception_lower":"1985-10-01",
    "date:inception_upper":"1985-10-31",
    "iso:country":"GB",
    "wof:name":"NE1 2PN",
    "wof:placetype":"postalcode"
},
  "geometry": {"coordinates":[-1.591722,54.974931],"type":"Point"}
}