{
  "type": "Feature",
  "properties": {
    "iso:country": "GB",
    "wof:name": "ME12 4JP",
    "wof:placetype": "postalcode"
  },
  "geometry": {"coordinates":[0.869631,51.418037],"type":"Point"}
}
