{
  "type": "Feature",
  "properties": {
    "date:inception_lower": "1980-01-01",
    "date:inception_upper": "1980-01-01",
    "iso:country": "GB",
    "wof:name": "ME12 4JP",
    "wof:placetype": "postalcode"
  },
  "geometry": {"coordinates":[0.869966,51.417863],"type":"Point"}
}
