{
  "type": "Feature",
  "properties": {
    "iso:country":"GB",
    "wof:name":"CV31 2EP",
    "wof:placetype":"postalcode"
},
  "geometry": {"coordinates":[-1.52863218216044,52.27609772725584],"type":"Point"}
}