{
  "type": "Feature",
  "properties": {
    "iso:country": "GB",
    "wof:name": "CO10 8PX",
    "wof:placetype": "postalcode"
  },
  "geometry": {"coordinates":[0.58108,52.080759],"type":"Point"}
}
