{
  "type": "Feature",
  "properties": {
    "date:inception_lower": "1980-01-01",
    "date:inception_upper": "1980-01-01",
    "iso:country": "GB",
    "wof:name": "DL13 1PF",
    "wof:placetype": "postalcode"
  },
  "geometry": {"coordinates":[-2.116174,54.74408],"type":"Point"}
}
