{
  "type": "Feature",
  "properties": {
    "iso:country": "GB",
    "wof:name": "DL13 1PF",
    "wof:placetype": "postalcode"
  },
  "geometry": {"coordinates":[-2.116174,54.74408],"type":"Point"}
}
