{
  "type": "Feature",
  "properties": {
    "iso:country":"GB",
    "wof:name":"DL13 1PF",
    "wof:placetype":"postalcode"
},
  "geometry": {"coordinates":[-2.11617446926835,54.7440798022143],"type":"Point"}
}