{
  "type": "Feature",
  "properties": {
    "iso:country": "GB",
    "wof:name": "WS12 3YN",
    "wof:placetype": "postalcode"
  },
  "geometry": {"coordinates":[-1.999499,52.689326],"type":"Point"}
}
