{
  "type": "Feature",
  "properties": {
    "iso:country":"GB",
    "wof:name":"WS12 3YN",
    "wof:placetype":"postalcode"
},
  "geometry": {"coordinates":[-1.99949863857346,52.68932565239413],"type":"Point"}
}