{
  "type": "Feature",
  "properties": {
    "iso:country": "GB",
    "wof:name": "BL6 6GL",
    "wof:placetype": "postalcode"
  },
  "geometry": {"coordinates":[-2.535227,53.591416],"type":"Point"}
}
