{
  "type": "Feature",
  "properties": {
    "date:inception_lower": "2007-09-01",
    "date:inception_upper": "2007-09-01",
    "iso:country": "GB",
    "wof:name": "NG4 1GQ",
    "wof:placetype": "postalcode"
  },
  "geometry": {"coordinates":[-1.096895,52.965605],"type":"Point"}
}
