{
  "type": "Feature",
  "properties": {
    "date:inception_lower":"2007-09-01",
    "date:inception_upper":"2007-09-30",
    "iso:country":"GB",
    "wof:name":"NG4 1GQ",
    "wof:placetype":"postalcode"
},
  "geometry": {"coordinates":[-1.096898,52.965585],"type":"Point"}
}