{
  "type": "Feature",
  "properties": {
    "iso:country": "GB",
    "wof:name": "NG4 1GQ",
    "wof:placetype": "postalcode"
  },
  "geometry": {"coordinates":[-1.096898,52.965585],"type":"Point"}
}
