{
  "type": "Feature",
  "properties": {
    "iso:country":"GB",
    "wof:name":"BB4 7PD",
    "wof:placetype":"postalcode"
},
  "geometry": {"coordinates":[-2.27728817781098,53.70124955350891],"type":"Point"}
}