{
  "type": "Feature",
  "properties": {
    "iso:country":"GB",
    "wof:name":"YO17 7DU",
    "wof:placetype":"postalcode"
},
  "geometry": {"coordinates":[-0.79079230726678,54.13318741379349],"type":"Point"}
}