{
  "type": "Feature",
  "properties": {
    "iso:country": "GB",
    "wof:name": "YO17 7DU",
    "wof:placetype": "postalcode"
  },
  "geometry": {"coordinates":[-0.790803,54.133205],"type":"Point"}
}
