{
  "type": "Feature",
  "properties": {
    "date:inception_lower": "1980-01-01",
    "date:inception_upper": "1980-01-01",
    "iso:country": "GB",
    "wof:name": "TN17 3JQ",
    "wof:placetype": "postalcode"
  },
  "geometry": {"coordinates":[0.538841,51.09679],"type":"Point"}
}
