{
  "type": "Feature",
  "properties": {
    "iso:country":"GB",
    "wof:name":"TN17 3JQ",
    "wof:placetype":"postalcode"
},
  "geometry": {"coordinates":[0.53884123922321,51.09678992531666],"type":"Point"}
}