{
  "type": "Feature",
  "properties": {
    "iso:country":"GB",
    "wof:name":"WN6 0QF",
    "wof:placetype":"postalcode"
},
  "geometry": {"coordinates":[-2.67119822079631,53.59615239505334],"type":"Point"}
}