{
  "type": "Feature",
  "properties": {
    "iso:country":"GB",
    "wof:name":"DT4 8NY",
    "wof:placetype":"postalcode"
},
  "geometry": {"coordinates":[-2.45400999531274,50.61091655025619],"type":"Point"}
}