{
  "type": "Feature",
  "properties": {
    "iso:country":"GB",
    "wof:name":"G33 2AF",
    "wof:placetype":"postalcode"
},
  "geometry": {"coordinates":[-4.19502788902225,55.86985709715973],"type":"Point"}
}