{
  "type": "Feature",
  "properties": {
    "iso:country":"GB",
    "wof:name":"WD17 4QN",
    "wof:placetype":"postalcode"
},
  "geometry": {"coordinates":[-0.40215786738821,51.66635583987104],"type":"Point"}
}