{
  "type": "Feature",
  "properties": {
    "date:inception_lower": "1980-01-01",
    "date:inception_upper": "1980-01-01",
    "iso:country": "GB",
    "wof:name": "OL11 1AG",
    "wof:placetype": "postalcode"
  },
  "geometry": {"coordinates":[-2.147036,53.604768],"type":"Point"}
}
