{
  "type": "Feature",
  "properties": {
    "iso:country":"GB",
    "wof:name":"BS49 5WQ",
    "wof:placetype":"postalcode"
},
  "geometry": {"coordinates":[-2.82025693931827,51.38670415315954],"type":"Point"}
}