{
  "type": "Feature",
  "properties": {
    "date:inception_lower":"2018-07-01",
    "date:inception_upper":"2018-07-31",
    "iso:country":"GB",
    "wof:name":"BS49 5WQ",
    "wof:placetype":"postalcode"
},
  "geometry": {"coordinates":[-2.820261,51.386702],"type":"Point"}
}