{
  "type": "Feature",
  "properties": {
    "iso:country":"GB",
    "wof:name":"SE25 6RG",
    "wof:placetype":"postalcode"
},
  "geometry": {"coordinates":[-0.0908794457307,51.39798393494349],"type":"Point"}
}