{
  "type": "Feature",
  "properties": {
    "iso:country":"GB",
    "wof:name":"DD8 1BJ",
    "wof:placetype":"postalcode"
},
  "geometry": {"coordinates":[-2.89137859925614,56.64355264232268],"type":"Point"}
}