{
  "type": "Feature",
  "properties": {
    "iso:country": "GB",
    "wof:name": "CF62 8HR",
    "wof:placetype": "postalcode"
  },
  "geometry": {"coordinates":[-3.279486,51.405779],"type":"Point"}
}
