{
  "type": "Feature",
  "properties": {
    "iso:country": "GB",
    "wof:name": "NP20 4HB",
    "wof:placetype": "postalcode"
  },
  "geometry": {"coordinates":[-3.00629,51.582992],"type":"Point"}
}
