{
  "type": "Feature",
  "properties": {
    "iso:country":"GB",
    "wof:name":"NP20 4HB",
    "wof:placetype":"postalcode"
},
  "geometry": {"coordinates":[-3.00629031134928,51.5829924943373],"type":"Point"}
}