{
  "type": "Feature",
  "properties": {
    "iso:country":"GB",
    "wof:name":"CW9 6HL",
    "wof:placetype":"postalcode"
},
  "geometry": {"coordinates":[-2.50569265199994,53.29495903339269],"type":"Point"}
}