{
  "type": "Feature",
  "properties": {
    "date:inception_lower":"1993-08-01",
    "date:inception_upper":"1993-08-31",
    "iso:country":"GB",
    "wof:name":"DT10 1JF",
    "wof:placetype":"postalcode"
},
  "geometry": {"coordinates":[-2.303594,50.932829],"type":"Point"}
}