{
  "type": "Feature",
  "properties": {
    "iso:country":"GB",
    "wof:name":"CM11 1BP",
    "wof:placetype":"postalcode"
},
  "geometry": {"coordinates":[0.42860381369301,51.63706656953428],"type":"Point"}
}