{
  "type": "Feature",
  "properties": {
    "iso:country":"GB",
    "wof:name":"S75 4RW",
    "wof:placetype":"postalcode"
},
  "geometry": {"coordinates":[-1.55306144706849,53.53124579234346],"type":"Point"}
}