{
  "type": "Feature",
  "properties": {
    "iso:country": "GB",
    "wof:name": "GU47 0SB",
    "wof:placetype": "postalcode"
  },
  "geometry": {"coordinates":[-0.785253,51.356001],"type":"Point"}
}
