{
  "type": "Feature",
  "properties": {
    "iso:country":"GB",
    "wof:name":"ST8 7AU",
    "wof:placetype":"postalcode"
},
  "geometry": {"coordinates":[-2.17710343041081,53.1074935113397],"type":"Point"}
}