{
  "type": "Feature",
  "properties": {
    "date:inception_lower": "1980-01-01",
    "date:inception_upper": "1980-01-01",
    "iso:country": "GB",
    "wof:name": "ST8 7AU",
    "wof:placetype": "postalcode"
  },
  "geometry": {"coordinates":[-2.177103,53.107494],"type":"Point"}
}
