{
  "type": "Feature",
  "properties": {
    "iso:country": "GB",
    "wof:name": "CH64 2XE",
    "wof:placetype": "postalcode"
  },
  "geometry": {"coordinates":[-3.002388,53.292339],"type":"Point"}
}
