{
  "type": "Feature",
  "properties": {
    "date:inception_lower": "1999-06-01",
    "date:inception_upper": "1999-06-01",
    "iso:country": "GB",
    "wof:name": "CH64 2XE",
    "wof:placetype": "postalcode"
  },
  "geometry": {"coordinates":[-3.002388,53.292339],"type":"Point"}
}
