{
  "type": "Feature",
  "properties": {
    "iso:country":"GB",
    "wof:name":"CH64 2XE",
    "wof:placetype":"postalcode"
},
  "geometry": {"coordinates":[-3.00238770880802,53.29233920448274],"type":"Point"}
}