{
  "type": "Feature",
  "properties": {
    "date:inception_lower": "1980-01-01",
    "date:inception_upper": "1980-01-01",
    "iso:country": "GB",
    "wof:name": "EX39 2HR",
    "wof:placetype": "postalcode"
  },
  "geometry": {"coordinates":[-4.2051,51.016338],"type":"Point"}
}
