{
  "type": "Feature",
  "properties": {
    "iso:country": "GB",
    "wof:name": "EX39 2HR",
    "wof:placetype": "postalcode"
  },
  "geometry": {"coordinates":[-4.2051,51.016338],"type":"Point"}
}
