{
  "type": "Feature",
  "properties": {
    "iso:country":"GB",
    "wof:name":"DD1 1NE",
    "wof:placetype":"postalcode"
},
  "geometry": {"coordinates":[-2.97550160870593,56.46143720002574],"type":"Point"}
}