{
  "type": "Feature",
  "properties": {
    "date:inception_lower":"1980-01-01",
    "date:inception_upper":"1980-01-31",
    "iso:country":"GB",
    "wof:name":"NR34 8ED",
    "wof:placetype":"postalcode"
},
  "geometry": {"coordinates":[1.539428,52.398902],"type":"Point"}
}