{
  "type": "Feature",
  "properties": {
    "date:inception_lower": "1992-08-01",
    "date:inception_upper": "1992-08-01",
    "iso:country": "GB",
    "wof:name": "TS9 5QD",
    "wof:placetype": "postalcode"
  },
  "geometry": {"coordinates":[-1.193235,54.475824],"type":"Point"}
}
