{
  "type": "Feature",
  "properties": {
    "iso:country":"GB",
    "wof:name":"TS9 5QD",
    "wof:placetype":"postalcode"
},
  "geometry": {"coordinates":[-1.19323510343912,54.47582439517578],"type":"Point"}
}