{
  "type": "Feature",
  "properties": {
    "date:inception_lower": "2014-09-01",
    "date:inception_upper": "2014-09-01",
    "iso:country": "GB",
    "wof:name": "NP19 0NX",
    "wof:placetype": "postalcode"
  },
  "geometry": {"coordinates":[-2.988607,51.587218],"type":"Point"}
}
