{
  "type": "Feature",
  "properties": {
    "iso:country":"GB",
    "wof:name":"NP19 0NX",
    "wof:placetype":"postalcode"
},
  "geometry": {"coordinates":[-2.98864398617318,51.58721571424147],"type":"Point"}
}