{
  "type": "Feature",
  "properties": {
    "iso:country":"GB",
    "wof:name":"B45 9FD",
    "wof:placetype":"postalcode"
},
  "geometry": {"coordinates":[-2.01343344115366,52.40019301927407],"type":"Point"}
}