{
  "type": "Feature",
  "properties": {
    "iso:country": "GB",
    "wof:name": "WV16 6BW",
    "wof:placetype": "postalcode"
  },
  "geometry": {"coordinates":[-2.421058,52.502565],"type":"Point"}
}
