{
  "type": "Feature",
  "properties": {
    "date:inception_lower":"1992-01-01",
    "date:inception_upper":"1992-01-31",
    "iso:country":"GB",
    "wof:name":"WV16 6BW",
    "wof:placetype":"postalcode"
},
  "geometry": {"coordinates":[-2.421058,52.502565],"type":"Point"}
}