{
  "type": "Feature",
  "properties": {
    "iso:country": "GB",
    "wof:name": "PL5 1TW",
    "wof:placetype": "postalcode"
  },
  "geometry": {"coordinates":[-4.183592,50.402674],"type":"Point"}
}
