{
  "type": "Feature",
  "properties": {
    "date:inception_lower": "1980-01-01",
    "date:inception_upper": "1980-01-01",
    "iso:country": "GB",
    "wof:name": "CT3 1TU",
    "wof:placetype": "postalcode"
  },
  "geometry": {"coordinates":[1.166855,51.277162],"type":"Point"}
}
