{
  "type": "Feature",
  "properties": {
    "iso:country":"GB",
    "wof:name":"CT3 1TU",
    "wof:placetype":"postalcode"
},
  "geometry": {"coordinates":[1.16676742271523,51.27715023571674],"type":"Point"}
}