{
  "type": "Feature",
  "properties": {
    "iso:country":"GB",
    "wof:name":"HA2 8TF",
    "wof:placetype":"postalcode"
},
  "geometry": {"coordinates":[-0.3660825640804,51.55847557293195],"type":"Point"}
}