{
  "type": "Feature",
  "properties": {
    "iso:country": "GB",
    "wof:name": "NE1 5EE",
    "wof:placetype": "postalcode"
  },
  "geometry": {"coordinates":[-1.619158,54.969637],"type":"Point"}
}
