{
  "type": "Feature",
  "properties": {
    "iso:country":"GB",
    "wof:name":"NE1 5EE",
    "wof:placetype":"postalcode"
},
  "geometry": {"coordinates":[-1.61915816618614,54.96963725810482],"type":"Point"}
}