{
  "type": "Feature",
  "properties": {
    "date:inception_lower":"1980-01-01",
    "date:inception_upper":"1980-01-31",
    "iso:country":"GB",
    "wof:name":"NE1 5EE",
    "wof:placetype":"postalcode"
},
  "geometry": {"coordinates":[-1.619158,54.969637],"type":"Point"}
}