{
  "type": "Feature",
  "properties": {
    "iso:country":"GB",
    "wof:name":"NG8 5HB",
    "wof:placetype":"postalcode"
},
  "geometry": {"coordinates":[-1.19838514398972,52.96862295457458],"type":"Point"}
}