{
  "type": "Feature",
  "properties": {
    "date:inception_lower": "1989-10-01",
    "date:inception_upper": "1989-10-01",
    "iso:country": "GB",
    "wof:name": "KY16 8XX",
    "wof:placetype": "postalcode"
  },
  "geometry": {"coordinates":[-2.815775,56.330725],"type":"Point"}
}
