{
  "type": "Feature",
  "properties": {
    "iso:country": "GB",
    "wof:name": "LL11 1RE",
    "wof:placetype": "postalcode"
  },
  "geometry": {"coordinates":[-2.997786,53.047544],"type":"Point"}
}
