{
  "type": "Feature",
  "properties": {
    "iso:country": "GB",
    "wof:name": "B64 6QX",
    "wof:placetype": "postalcode"
  },
  "geometry": {"coordinates":[-2.059935,52.475047],"type":"Point"}
}
