{
  "type": "Feature",
  "properties": {
    "date:inception_lower": "1980-01-01",
    "date:inception_upper": "1980-01-01",
    "iso:country": "GB",
    "wof:name": "B64 6QX",
    "wof:placetype": "postalcode"
  },
  "geometry": {"coordinates":[-2.059935,52.475047],"type":"Point"}
}
