{
  "type": "Feature",
  "properties": {
    "iso:country":"GB",
    "wof:name":"BD21 4JT",
    "wof:placetype":"postalcode"
},
  "geometry": {"coordinates":[-1.89229416546254,53.86911272856563],"type":"Point"}
}