{
  "type": "Feature",
  "properties": {
    "iso:country":"GB",
    "wof:name":"BD4 6BH",
    "wof:placetype":"postalcode"
},
  "geometry": {"coordinates":[-1.72815485696912,53.76875472715878],"type":"Point"}
}