{
  "type": "Feature",
  "properties": {
    "date:inception_lower": "2000-12-01",
    "date:inception_upper": "2000-12-01",
    "iso:country": "GB",
    "wof:name": "BD4 6BH",
    "wof:placetype": "postalcode"
  },
  "geometry": {"coordinates":[-1.728155,53.768755],"type":"Point"}
}
