{
  "type": "Feature",
  "properties": {
    "iso:country":"GB",
    "wof:name":"NR30 4BA",
    "wof:placetype":"postalcode"
},
  "geometry": {"coordinates":[1.73275113244096,52.62724635526802],"type":"Point"}
}