{
  "type": "Feature",
  "properties": {
    "date:inception_lower":"1992-08-01",
    "date:inception_upper":"1992-08-31",
    "iso:country":"GB",
    "wof:name":"NG17 1DX",
    "wof:placetype":"postalcode"
},
  "geometry": {"coordinates":[-1.271099,53.120408],"type":"Point"}
}