{
  "type": "Feature",
  "properties": {
    "iso:country":"GB",
    "wof:name":"AB45 2NW",
    "wof:placetype":"postalcode"
},
  "geometry": {"coordinates":[-2.57606485306389,57.67846782707545],"type":"Point"}
}