{
  "type": "Feature",
  "properties": {
    "iso:country": "GB",
    "wof:name": "SP2 8TB",
    "wof:placetype": "postalcode"
  },
  "geometry": {"coordinates":[-1.791987,51.054309],"type":"Point"}
}
