{
  "type": "Feature",
  "properties": {
    "iso:country":"GB",
    "wof:name":"SP2 8TB",
    "wof:placetype":"postalcode"
},
  "geometry": {"coordinates":[-1.79198718376658,51.05430913314917],"type":"Point"}
}