{
  "type": "Feature",
  "properties": {
    "date:inception_lower": "2023-08-01",
    "date:inception_upper": "2023-08-01",
    "iso:country": "GB",
    "wof:name": "DN21 5FT",
    "wof:placetype": "postalcode"
  },
  "geometry": {"coordinates":[-0.578722,53.379776],"type":"Point"}
}
