{
  "type": "Feature",
  "properties": {
    "date:inception_lower": "2023-04-01",
    "date:inception_upper": "2023-04-01",
    "iso:country": "GB",
    "wof:name": "CH61 1BF",
    "wof:placetype": "postalcode"
  },
  "geometry": {"coordinates":[-3.079704,53.340266],"type":"Point"}
}
