{
  "type": "Feature",
  "properties": {
    "iso:country": "GB",
    "wof:name": "SE1 7GP",
    "wof:placetype": "postalcode"
  },
  "geometry": {"coordinates":[-0.118114,51.501417],"type":"Point"}
}
