{
  "type": "Feature",
  "properties": {
    "iso:country":"GB",
    "wof:name":"SE1 7GP",
    "wof:placetype":"postalcode"
},
  "geometry": {"coordinates":[-0.11811425406869,51.50141696900065],"type":"Point"}
}