{
  "type": "Feature",
  "properties": {
    "iso:country":"GB",
    "wof:name":"GU34 1FH",
    "wof:placetype":"postalcode"
},
  "geometry": {"coordinates":[-0.97680384137884,51.14113733507375],"type":"Point"}
}