{
  "type": "Feature",
  "properties": {
    "date:inception_lower":"2007-11-01",
    "date:inception_upper":"2007-11-30",
    "iso:country":"GB",
    "wof:name":"GU34 1FH",
    "wof:placetype":"postalcode"
},
  "geometry": {"coordinates":[-0.976804,51.141137],"type":"Point"}
}