{
  "type": "Feature",
  "properties": {
    "date:inception_lower": "2013-03-01",
    "date:inception_upper": "2013-03-01",
    "iso:country": "GB",
    "wof:name": "WS3 1RZ",
    "wof:placetype": "postalcode"
  },
  "geometry": {"coordinates":[-1.971022,52.609545],"type":"Point"}
}
