{
  "type": "Feature",
  "properties": {
    "iso:country":"GB",
    "wof:name":"BA8 0TQ",
    "wof:placetype":"postalcode"
},
  "geometry": {"coordinates":[-2.37892973326517,50.98191369737824],"type":"Point"}
}