{
  "type": "Feature",
  "properties": {
    "date:inception_lower":"1980-01-01",
    "date:inception_upper":"1980-01-31",
    "iso:country":"GB",
    "wof:name":"BA8 0TQ",
    "wof:placetype":"postalcode"
},
  "geometry": {"coordinates":[-2.37893,50.981914],"type":"Point"}
}