{
  "type": "Feature",
  "properties": {
    "date:inception_lower":"1980-01-01",
    "date:inception_upper":"1980-01-31",
    "iso:country":"GB",
    "wof:name":"LS12 5HA",
    "wof:placetype":"postalcode"
},
  "geometry": {"coordinates":[-1.626312,53.787329],"type":"Point"}
}