{
  "type": "Feature",
  "properties": {
    "iso:country":"GB",
    "wof:name":"LS12 5HA",
    "wof:placetype":"postalcode"
},
  "geometry": {"coordinates":[-1.62631195319786,53.78732870489247],"type":"Point"}
}