{
  "type": "Feature",
  "properties": {
    "date:inception_lower": "2006-09-01",
    "date:inception_upper": "2006-09-01",
    "iso:country": "GB",
    "wof:name": "CB2 0XZ",
    "wof:placetype": "postalcode"
  },
  "geometry": {"coordinates":[0.142195,52.176967],"type":"Point"}
}
