{
  "type": "Feature",
  "properties": {
    "iso:country":"GB",
    "wof:name":"CB2 0XZ",
    "wof:placetype":"postalcode"
},
  "geometry": {"coordinates":[0.14219451608278,52.17696685692824],"type":"Point"}
}