{
  "type": "Feature",
  "properties": {
    "iso:country": "GB",
    "wof:name": "SY5 9EN",
    "wof:placetype": "postalcode"
  },
  "geometry": {"coordinates":[-2.926463,52.708103],"type":"Point"}
}
