{
  "type": "Feature",
  "properties": {
    "iso:country": "GB",
    "wof:name": "IV15 9ND",
    "wof:placetype": "postalcode"
  },
  "geometry": {"coordinates":[-4.431742,57.606577],"type":"Point"}
}
