{
  "type": "Feature",
  "properties": {
    "iso:country":"GB",
    "wof:name":"IV15 9ND",
    "wof:placetype":"postalcode"
},
  "geometry": {"coordinates":[-4.43174193871327,57.60657680893813],"type":"Point"}
}