{
  "type": "Feature",
  "properties": {
    "iso:country":"GB",
    "wof:name":"HU17 7JH",
    "wof:placetype":"postalcode"
},
  "geometry": {"coordinates":[-0.44043934806182,53.85344859756583],"type":"Point"}
}