{
  "type": "Feature",
  "properties": {
    "iso:country":"GB",
    "wof:name":"OX14 2QR",
    "wof:placetype":"postalcode"
},
  "geometry": {"coordinates":[-1.26619056431881,51.68688907228582],"type":"Point"}
}