{
  "type": "Feature",
  "properties": {
    "date:inception_lower": "2018-06-01",
    "date:inception_upper": "2018-06-01",
    "iso:country": "GB",
    "wof:name": "CO4 6DU",
    "wof:placetype": "postalcode"
  },
  "geometry": {"coordinates":[0.913795,51.92336],"type":"Point"}
}
