{
  "type": "Feature",
  "properties": {
    "iso:country":"GB",
    "wof:name":"WV12 5AH",
    "wof:placetype":"postalcode"
},
  "geometry": {"coordinates":[-2.04517633638207,52.61085485499846],"type":"Point"}
}