{
  "type": "Feature",
  "properties": {
    "iso:country": "GB",
    "wof:name": "WV12 5AH",
    "wof:placetype": "postalcode"
  },
  "geometry": {"coordinates":[-2.045176,52.610855],"type":"Point"}
}
