{
  "type": "Feature",
  "properties": {
    "iso:country": "GB",
    "wof:name": "NG16 1DR",
    "wof:placetype": "postalcode"
  },
  "geometry": {"coordinates":[-1.245927,52.993547],"type":"Point"}
}
