{
  "type": "Feature",
  "properties": {
    "iso:country":"GB",
    "wof:name":"NW6 3SP",
    "wof:placetype":"postalcode"
},
  "geometry": {"coordinates":[-0.18381384458812,51.54531078700013],"type":"Point"}
}