{
  "type": "Feature",
  "properties": {
    "date:inception_lower":"1999-12-01",
    "date:inception_upper":"1999-12-31",
    "iso:country":"GB",
    "wof:name":"LS29 0SH",
    "wof:placetype":"postalcode"
},
  "geometry": {"coordinates":[-1.893222,53.946993],"type":"Point"}
}