{
  "type": "Feature",
  "properties": {
    "iso:country":"GB",
    "wof:name":"ST7 3EY",
    "wof:placetype":"postalcode"
},
  "geometry": {"coordinates":[-2.28360272371917,53.0975970219646],"type":"Point"}
}