{
  "type": "Feature",
  "properties": {
    "iso:country": "GB",
    "wof:name": "ST17 9PA",
    "wof:placetype": "postalcode"
  },
  "geometry": {"coordinates":[-2.118494,52.783333],"type":"Point"}
}
