{
  "type": "Feature",
  "properties": {
    "iso:country":"GB",
    "wof:name":"ST17 9PA",
    "wof:placetype":"postalcode"
},
  "geometry": {"coordinates":[-2.11849381121256,52.78333304659798],"type":"Point"}
}