{
  "type": "Feature",
  "properties": {
    "iso:country":"GB",
    "wof:name":"NG15 7FU",
    "wof:placetype":"postalcode"
},
  "geometry": {"coordinates":[-1.21133405054682,53.04089434916727],"type":"Point"}
}