{
  "type": "Feature",
  "properties": {
    "iso:country":"GB",
    "wof:name":"BD21 5DZ",
    "wof:placetype":"postalcode"
},
  "geometry": {"coordinates":[-1.91642905612212,53.85352897701255],"type":"Point"}
}