{
  "type": "Feature",
  "properties": {
    "date:inception_lower": "2002-08-01",
    "date:inception_upper": "2002-08-01",
    "iso:country": "GB",
    "wof:name": "BD21 5DZ",
    "wof:placetype": "postalcode"
  },
  "geometry": {"coordinates":[-1.916429,53.853529],"type":"Point"}
}
