{
  "type": "Feature",
  "properties": {
    "iso:country":"GB",
    "wof:name":"KY14 6HY",
    "wof:placetype":"postalcode"
},
  "geometry": {"coordinates":[-3.20750770405859,56.33569319721351],"type":"Point"}
}