{
  "type": "Feature",
  "properties": {
    "iso:country":"GB",
    "wof:name":"B71 4HG",
    "wof:placetype":"postalcode"
},
  "geometry": {"coordinates":[-1.98732488835423,52.52537869164474],"type":"Point"}
}