{
  "type": "Feature",
  "properties": {
    "iso:country":"GB",
    "wof:name":"BN41 1SN",
    "wof:placetype":"postalcode"
},
  "geometry": {"coordinates":[-0.21936130403773,50.83884549756708],"type":"Point"}
}