{
  "type": "Feature",
  "properties": {
    "iso:country": "GB",
    "wof:name": "SS7 3BB",
    "wof:placetype": "postalcode"
  },
  "geometry": {"coordinates":[0.579597,51.56813],"type":"Point"}
}
