{
  "type": "Feature",
  "properties": {
    "iso:country":"GB",
    "wof:name":"TF12 5QW",
    "wof:placetype":"postalcode"
},
  "geometry": {"coordinates":[-2.48654588294695,52.62268282338878],"type":"Point"}
}