{
  "type": "Feature",
  "properties": {
    "iso:country": "GB",
    "wof:name": "WD23 2NZ",
    "wof:placetype": "postalcode"
  },
  "geometry": {"coordinates":[-0.384967,51.65628],"type":"Point"}
}
