{
  "type": "Feature",
  "properties": {
    "iso:country":"GB",
    "wof:name":"WD23 2NZ",
    "wof:placetype":"postalcode"
},
  "geometry": {"coordinates":[-0.38550185835267,51.65653356338679],"type":"Point"}
}