{
  "type": "Feature",
  "properties": {
    "iso:country":"GB",
    "wof:name":"S62 5JU",
    "wof:placetype":"postalcode"
},
  "geometry": {"coordinates":[-1.32657496240175,53.46519778132871],"type":"Point"}
}