{
  "type": "Feature",
  "properties": {
    "iso:country":"GB",
    "wof:name":"HA8 9AF",
    "wof:placetype":"postalcode"
},
  "geometry": {"coordinates":[-0.27131957876713,51.60939879712345],"type":"Point"}
}