{
  "type": "Feature",
  "properties": {
    "iso:country":"GB",
    "wof:name":"SK16 4JD",
    "wof:placetype":"postalcode"
},
  "geometry": {"coordinates":[-2.09386761372631,53.48104280020353],"type":"Point"}
}