{
  "type": "Feature",
  "properties": {
    "date:inception_lower": "2010-01-01",
    "date:inception_upper": "2010-01-01",
    "iso:country": "GB",
    "wof:name": "E2 9BF",
    "wof:placetype": "postalcode"
  },
  "geometry": {"coordinates":[-0.059436,51.532097],"type":"Point"}
}
