{
  "type": "Feature",
  "properties": {
    "iso:country":"GB",
    "wof:name":"M30 8DH",
    "wof:placetype":"postalcode"
},
  "geometry": {"coordinates":[-2.36809636413287,53.49128041555843],"type":"Point"}
}