{
  "type": "Feature",
  "properties": {
    "iso:country":"GB",
    "wof:name":"RG40 1JR",
    "wof:placetype":"postalcode"
},
  "geometry": {"coordinates":[-0.80926866461191,51.40962465230806],"type":"Point"}
}