{
  "type": "Feature",
  "properties": {
    "iso:country": "GB",
    "wof:name": "RG40 1JR",
    "wof:placetype": "postalcode"
  },
  "geometry": {"coordinates":[-0.809642,51.409521],"type":"Point"}
}
