{
  "type": "Feature",
  "properties": {
    "iso:country": "GB",
    "wof:name": "RG40 1JR",
    "wof:placetype": "postalcode"
  },
  "geometry": {"coordinates":[-0.809627,51.409548],"type":"Point"}
}
