{
  "type": "Feature",
  "properties": {
    "iso:country":"GB",
    "wof:name":"SE9 5PE",
    "wof:placetype":"postalcode"
},
  "geometry": {"coordinates":[0.0521229938642,51.44175402817143],"type":"Point"}
}