{
  "type": "Feature",
  "properties": {
    "iso:country": "GB",
    "wof:name": "SK4 5LS",
    "wof:placetype": "postalcode"
  },
  "geometry": {"coordinates":[-2.168329,53.437466],"type":"Point"}
}
