{
  "type": "Feature",
  "properties": {
    "date:inception_lower": "1980-01-01",
    "date:inception_upper": "1980-01-01",
    "iso:country": "GB",
    "wof:name": "PO10 7LJ",
    "wof:placetype": "postalcode"
  },
  "geometry": {"coordinates":[-0.952335,50.847907],"type":"Point"}
}
