{
  "type": "Feature",
  "properties": {
    "iso:country": "GB",
    "wof:name": "CV3 1JX",
    "wof:placetype": "postalcode"
  },
  "geometry": {"coordinates":[-1.467058,52.403255],"type":"Point"}
}
