{
  "type": "Feature",
  "properties": {
    "date:inception_lower": "1980-01-01",
    "date:inception_upper": "1980-01-01",
    "iso:country": "GB",
    "wof:name": "SW1E 6PL",
    "wof:placetype": "postalcode"
  },
  "geometry": {"coordinates":[-0.139981,51.498717],"type":"Point"}
}
