{
  "type": "Feature",
  "properties": {
    "iso:country":"GB",
    "wof:name":"SW1E 6PL",
    "wof:placetype":"postalcode"
},
  "geometry": {"coordinates":[-0.13998073765693,51.49871734603369],"type":"Point"}
}