{
  "type": "Feature",
  "properties": {
    "iso:country": "GB",
    "wof:name": "BR5 2RR",
    "wof:placetype": "postalcode"
  },
  "geometry": {"coordinates":[0.098231,51.407277],"type":"Point"}
}
