{
  "type": "Feature",
  "properties": {
    "iso:country":"GB",
    "wof:name":"BR5 2RR",
    "wof:placetype":"postalcode"
},
  "geometry": {"coordinates":[0.09823124304835,51.40727718926483],"type":"Point"}
}