{
  "type": "Feature",
  "properties": {
    "iso:country":"GB",
    "wof:name":"SA33 6UL",
    "wof:placetype":"postalcode"
},
  "geometry": {"coordinates":[-4.36512403919111,51.93363129343893],"type":"Point"}
}