{
  "type": "Feature",
  "properties": {
    "iso:country": "GB",
    "wof:name": "TN27 8HJ",
    "wof:placetype": "postalcode"
  },
  "geometry": {"coordinates":[0.636,51.116899],"type":"Point"}
}
