{
  "type": "Feature",
  "properties": {
    "iso:country":"GB",
    "wof:name":"TN27 8HJ",
    "wof:placetype":"postalcode"
},
  "geometry": {"coordinates":[0.6359996124133,51.11689903427518],"type":"Point"}
}