{
  "type": "Feature",
  "properties": {
    "iso:country":"GB",
    "wof:name":"WA3 3LY",
    "wof:placetype":"postalcode"
},
  "geometry": {"coordinates":[-2.59159942731478,53.47595601094058],"type":"Point"}
}