{
  "type": "Feature",
  "properties": {
    "iso:country": "GB",
    "wof:name": "TA17 8SY",
    "wof:placetype": "postalcode"
  },
  "geometry": {"coordinates":[-2.851228,50.914455],"type":"Point"}
}
