{
  "type": "Feature",
  "properties": {
    "date:inception_lower":"1980-01-01",
    "date:inception_upper":"1980-01-31",
    "iso:country":"GB",
    "wof:name":"L35 7JT",
    "wof:placetype":"postalcode"
},
  "geometry": {"coordinates":[-2.783131,53.429389],"type":"Point"}
}