{
  "type": "Feature",
  "properties": {
    "iso:country": "GB",
    "wof:name": "L35 7JT",
    "wof:placetype": "postalcode"
  },
  "geometry": {"coordinates":[-2.783131,53.429389],"type":"Point"}
}
