{
  "type": "Feature",
  "properties": {
    "iso:country":"GB",
    "wof:name":"DL8 1UT",
    "wof:placetype":"postalcode"
},
  "geometry": {"coordinates":[-1.5824735056445,54.29394459448665],"type":"Point"}
}