{
  "type": "Feature",
  "properties": {
    "iso:country":"GB",
    "wof:name":"NR20 4BW",
    "wof:placetype":"postalcode"
},
  "geometry": {"coordinates":[0.92503518510081,52.71865724896408],"type":"Point"}
}