{
  "type": "Feature",
  "properties": {
    "iso:country":"GB",
    "wof:name":"LS16 8AZ",
    "wof:placetype":"postalcode"
},
  "geometry": {"coordinates":[-1.57380917828493,53.88186899924234],"type":"Point"}
}