{
  "type": "Feature",
  "properties": {
    "date:inception_lower": "1980-01-01",
    "date:inception_upper": "1980-01-01",
    "iso:country": "GB",
    "wof:name": "LS16 8AZ",
    "wof:placetype": "postalcode"
  },
  "geometry": {"coordinates":[-1.573809,53.881869],"type":"Point"}
}
