{
  "type": "Feature",
  "properties": {
    "date:inception_lower":"1980-01-01",
    "date:inception_upper":"1980-01-31",
    "iso:country":"GB",
    "wof:name":"SW1P 1DW",
    "wof:placetype":"postalcode"
},
  "geometry": {"coordinates":[-0.138127,51.495055],"type":"Point"}
}