{
  "type": "Feature",
  "properties": {
    "iso:country": "GB",
    "wof:name": "G83 9DU",
    "wof:placetype": "postalcode"
  },
  "geometry": {"coordinates":[-4.56371,55.981675],"type":"Point"}
}
