{
  "type": "Feature",
  "properties": {
    "iso:country": "GB",
    "wof:name": "SA33 4HR",
    "wof:placetype": "postalcode"
  },
  "geometry": {"coordinates":[-4.539826,51.790851],"type":"Point"}
}
