{
  "type": "Feature",
  "properties": {
    "iso:country":"GB",
    "wof:name":"SA33 4HR",
    "wof:placetype":"postalcode"
},
  "geometry": {"coordinates":[-4.53947069015648,51.79092928483127],"type":"Point"}
}