{
  "type": "Feature",
  "properties": {
    "iso:country":"GB",
    "wof:name":"PR2 1YQ",
    "wof:placetype":"postalcode"
},
  "geometry": {"coordinates":[-2.76685332317994,53.76837882033947],"type":"Point"}
}