{
  "type": "Feature",
  "properties": {
    "iso:country": "GB",
    "wof:name": "PR2 1YQ",
    "wof:placetype": "postalcode"
  },
  "geometry": {"coordinates":[-2.766853,53.768379],"type":"Point"}
}
