{
  "type": "Feature",
  "properties": {
    "iso:country": "GB",
    "wof:name": "WV1 4LE",
    "wof:placetype": "postalcode"
  },
  "geometry": {"coordinates":[-2.130788,52.583774],"type":"Point"}
}
