{
  "type": "Feature",
  "properties": {
    "date:inception_lower": "2012-03-01",
    "date:inception_upper": "2012-03-01",
    "iso:country": "GB",
    "wof:name": "WV1 4LE",
    "wof:placetype": "postalcode"
  },
  "geometry": {"coordinates":[-2.130832,52.58372],"type":"Point"}
}
