{
  "type": "Feature",
  "properties": {
    "iso:country":"GB",
    "wof:name":"S36 8YW",
    "wof:placetype":"postalcode"
},
  "geometry": {"coordinates":[-1.60004158585215,53.518288939987],"type":"Point"}
}