{
  "type": "Feature",
  "properties": {
    "iso:country": "GB",
    "wof:name": "S36 8YW",
    "wof:placetype": "postalcode"
  },
  "geometry": {"coordinates":[-1.600042,53.518289],"type":"Point"}
}
