{
  "type": "Feature",
  "properties": {
    "date:inception_lower":"2002-08-01",
    "date:inception_upper":"2002-08-31",
    "iso:country":"GB",
    "wof:name":"HG2 9QN",
    "wof:placetype":"postalcode"
},
  "geometry": {"coordinates":[-1.543299,53.9763],"type":"Point"}
}