{
  "type": "Feature",
  "properties": {
    "iso:country":"GB",
    "wof:name":"DN35 7AX",
    "wof:placetype":"postalcode"
},
  "geometry": {"coordinates":[-0.05457413546673,53.5724152172327],"type":"Point"}
}