{
  "type": "Feature",
  "properties": {
    "iso:country": "GB",
    "wof:name": "B21 0PU",
    "wof:placetype": "postalcode"
  },
  "geometry": {"coordinates":[-1.948395,52.502714],"type":"Point"}
}
