{
  "type": "Feature",
  "properties": {
    "iso:country": "GB",
    "wof:name": "MK8 0AU",
    "wof:placetype": "postalcode"
  },
  "geometry": {"coordinates":[-0.800675,52.025155],"type":"Point"}
}
