{
  "type": "Feature",
  "properties": {
    "iso:country":"GB",
    "wof:name":"MK8 0AU",
    "wof:placetype":"postalcode"
},
  "geometry": {"coordinates":[-0.80067455666495,52.02515485543459],"type":"Point"}
}