{
  "type": "Feature",
  "properties": {
    "iso:country":"GB",
    "wof:name":"HG3 2EY",
    "wof:placetype":"postalcode"
},
  "geometry": {"coordinates":[-1.60598947915608,54.02353650465223],"type":"Point"}
}