{
  "type": "Feature",
  "properties": {
    "iso:country":"GB",
    "wof:name":"TN15 8NJ",
    "wof:placetype":"postalcode"
},
  "geometry": {"coordinates":[0.32697304792824,51.28529782276625],"type":"Point"}
}