{
  "type": "Feature",
  "properties": {
    "date:inception_lower": "1998-06-01",
    "date:inception_upper": "1998-06-01",
    "iso:country": "GB",
    "wof:name": "KT20 6EX",
    "wof:placetype": "postalcode"
  },
  "geometry": {"coordinates":[-0.210177,51.296442],"type":"Point"}
}
