{
  "type": "Feature",
  "properties": {
    "iso:country":"GB",
    "wof:name":"PE13 3HR",
    "wof:placetype":"postalcode"
},
  "geometry": {"coordinates":[0.16915230747339,52.67456872656444],"type":"Point"}
}