{
  "type": "Feature",
  "properties": {
    "iso:country": "GB",
    "wof:name": "PE13 3HR",
    "wof:placetype": "postalcode"
  },
  "geometry": {"coordinates":[0.169152,52.674569],"type":"Point"}
}
