{
  "type": "Feature",
  "properties": {
    "iso:country":"GB",
    "wof:name":"TR7 2AD",
    "wof:placetype":"postalcode"
},
  "geometry": {"coordinates":[-5.08652144317537,50.40836450725478],"type":"Point"}
}