{
  "type": "Feature",
  "properties": {
    "iso:country": "GB",
    "wof:name": "GU11 3NQ",
    "wof:placetype": "postalcode"
  },
  "geometry": {"coordinates":[-0.766437,51.241549],"type":"Point"}
}
