{
  "type": "Feature",
  "properties": {
    "date:inception_lower": "1980-01-01",
    "date:inception_upper": "1980-01-01",
    "iso:country": "GB",
    "wof:name": "GU11 3NQ",
    "wof:placetype": "postalcode"
  },
  "geometry": {"coordinates":[-0.766437,51.241549],"type":"Point"}
}
