{
  "type": "Feature",
  "properties": {
    "date:inception_lower": "1980-01-01",
    "date:inception_upper": "1980-01-01",
    "iso:country": "GB",
    "wof:name": "SA11 2EL",
    "wof:placetype": "postalcode"
  },
  "geometry": {"coordinates":[-3.81597,51.649419],"type":"Point"}
}
