{
  "type": "Feature",
  "properties": {
    "iso:country":"GB",
    "wof:name":"BR1 3JE",
    "wof:placetype":"postalcode"
},
  "geometry": {"coordinates":[0.0249688761728,51.41246006017451],"type":"Point"}
}