{
  "type": "Feature",
  "properties": {
    "iso:country":"GB",
    "wof:name":"SA62 5AQ",
    "wof:placetype":"postalcode"
},
  "geometry": {"coordinates":[-5.0445422517849,51.8935081485571],"type":"Point"}
}