{
  "type": "Feature",
  "properties": {
    "date:inception_lower":"2009-07-01",
    "date:inception_upper":"2009-07-31",
    "iso:country":"GB",
    "wof:name":"SA62 5AQ",
    "wof:placetype":"postalcode"
},
  "geometry": {"coordinates":[-5.044542,51.893508],"type":"Point"}
}