{
  "type": "Feature",
  "properties": {
    "date:inception_lower": "1999-06-01",
    "date:inception_upper": "1999-06-01",
    "iso:country": "GB",
    "wof:name": "CF83 8NP",
    "wof:placetype": "postalcode"
  },
  "geometry": {"coordinates":[-3.164275,51.58664],"type":"Point"}
}
