{
  "type": "Feature",
  "properties": {
    "iso:country": "GB",
    "wof:name": "CF83 8NP",
    "wof:placetype": "postalcode"
  },
  "geometry": {"coordinates":[-3.164275,51.58664],"type":"Point"}
}
