{
  "type": "Feature",
  "properties": {
    "iso:country":"GB",
    "wof:name":"PE15 9TU",
    "wof:placetype":"postalcode"
},
  "geometry": {"coordinates":[0.07519662318874,52.55002252292215],"type":"Point"}
}