{
  "type": "Feature",
  "properties": {
    "date:inception_lower": "2015-01-01",
    "date:inception_upper": "2015-01-01",
    "iso:country": "GB",
    "wof:name": "PE15 9TU",
    "wof:placetype": "postalcode"
  },
  "geometry": {"coordinates":[0.075216,52.55004],"type":"Point"}
}
