{
  "type": "Feature",
  "properties": {
    "iso:country": "GB",
    "wof:name": "S44 5NW",
    "wof:placetype": "postalcode"
  },
  "geometry": {"coordinates":[-1.316022,53.1906],"type":"Point"}
}
