{
  "type": "Feature",
  "properties": {
    "iso:country":"GB",
    "wof:name":"S44 5NW",
    "wof:placetype":"postalcode"
},
  "geometry": {"coordinates":[-1.31602172147215,53.19060043453032],"type":"Point"}
}