{
  "type": "Feature",
  "properties": {
    "iso:country": "GB",
    "wof:name": "DD6 9AT",
    "wof:placetype": "postalcode"
  },
  "geometry": {"coordinates":[-2.888657,56.451371],"type":"Point"}
}
