{
  "type": "Feature",
  "properties": {
    "date:inception_lower":"1980-01-01",
    "date:inception_upper":"1980-01-31",
    "iso:country":"GB",
    "wof:name":"DD6 9AT",
    "wof:placetype":"postalcode"
},
  "geometry": {"coordinates":[-2.888657,56.451371],"type":"Point"}
}