{
  "type": "Feature",
  "properties": {
    "date:inception_lower":"1980-01-01",
    "date:inception_upper":"1980-01-31",
    "iso:country":"GB",
    "wof:name":"DN19 7DR",
    "wof:placetype":"postalcode"
},
  "geometry": {"coordinates":[-0.3855,53.670576],"type":"Point"}
}