{
  "type": "Feature",
  "properties": {
    "iso:country":"GB",
    "wof:name":"S62 7RX",
    "wof:placetype":"postalcode"
},
  "geometry": {"coordinates":[-1.36727933328678,53.47506493378238],"type":"Point"}
}