{
  "type": "Feature",
  "properties": {
    "iso:country":"GB",
    "wof:name":"G66 1LP",
    "wof:placetype":"postalcode"
},
  "geometry": {"coordinates":[-4.15820963720433,55.938838033599],"type":"Point"}
}