{
  "type": "Feature",
  "properties": {
    "date:inception_lower": "2010-08-01",
    "date:inception_upper": "2010-08-01",
    "iso:country": "GB",
    "wof:name": "G66 1LP",
    "wof:placetype": "postalcode"
  },
  "geometry": {"coordinates":[-4.15821,55.938838],"type":"Point"}
}
