{
  "type": "Feature",
  "properties": {
    "iso:country": "GB",
    "wof:name": "NG34 8UH",
    "wof:placetype": "postalcode"
  },
  "geometry": {"coordinates":[-0.410008,53.009554],"type":"Point"}
}
