{
  "type": "Feature",
  "properties": {
    "iso:country":"GB",
    "wof:name":"NR34 7DG",
    "wof:placetype":"postalcode"
},
  "geometry": {"coordinates":[1.58218101209598,52.45211941165771],"type":"Point"}
}