{
  "type": "Feature",
  "properties": {
    "date:inception_lower": "1999-06-01",
    "date:inception_upper": "1999-06-01",
    "iso:country": "GB",
    "wof:name": "NP20 4FA",
    "wof:placetype": "postalcode"
  },
  "geometry": {"coordinates":[-3.003416,51.580275],"type":"Point"}
}
