{
  "type": "Feature",
  "properties": {
    "iso:country":"GB",
    "wof:name":"NP20 4FA",
    "wof:placetype":"postalcode"
},
  "geometry": {"coordinates":[-3.00341601773027,51.58027465572175],"type":"Point"}
}