{
  "type": "Feature",
  "properties": {
    "iso:country":"GB",
    "wof:name":"LD3 7YA",
    "wof:placetype":"postalcode"
},
  "geometry": {"coordinates":[-3.32611794231697,51.93324768556936],"type":"Point"}
}