{
  "type": "Feature",
  "properties": {
    "date:inception_lower": "1980-01-01",
    "date:inception_upper": "1980-01-01",
    "iso:country": "GB",
    "wof:name": "LD3 7YA",
    "wof:placetype": "postalcode"
  },
  "geometry": {"coordinates":[-3.326118,51.933248],"type":"Point"}
}
