{
  "type": "Feature",
  "properties": {
    "iso:country": "GB",
    "wof:name": "LD3 7YA",
    "wof:placetype": "postalcode"
  },
  "geometry": {"coordinates":[-3.326118,51.933248],"type":"Point"}
}
