{
  "type": "Feature",
  "properties": {
    "iso:country":"GB",
    "wof:name":"ST8 6PF",
    "wof:placetype":"postalcode"
},
  "geometry": {"coordinates":[-2.18858489660803,53.10282852966179],"type":"Point"}
}