{
  "type": "Feature",
  "properties": {
    "iso:country": "GB",
    "wof:name": "PR7 3JA",
    "wof:placetype": "postalcode"
  },
  "geometry": {"coordinates":[-2.631574,53.642281],"type":"Point"}
}
