{
  "type": "Feature",
  "properties": {
    "iso:country":"GB",
    "wof:name":"NR13 5AY",
    "wof:placetype":"postalcode"
},
  "geometry": {"coordinates":[1.37762180881132,52.64160222878132],"type":"Point"}
}