{
  "type": "Feature",
  "properties": {
    "iso:country":"GB",
    "wof:name":"HX3 5FD",
    "wof:placetype":"postalcode"
},
  "geometry": {"coordinates":[-1.86397725086094,53.72824268249305],"type":"Point"}
}