{
  "type": "Feature",
  "properties": {
    "date:inception_lower":"2011-06-01",
    "date:inception_upper":"2011-06-30",
    "iso:country":"GB",
    "wof:name":"HX3 5FD",
    "wof:placetype":"postalcode"
},
  "geometry": {"coordinates":[-1.863977,53.728243],"type":"Point"}
}