{
  "type": "Feature",
  "properties": {
    "date:inception_lower": "1980-01-01",
    "date:inception_upper": "1980-01-01",
    "iso:country": "GB",
    "wof:name": "DY5 2TW",
    "wof:placetype": "postalcode"
  },
  "geometry": {"coordinates":[-2.116786,52.474705],"type":"Point"}
}
