{
  "type": "Feature",
  "properties": {
    "iso:country":"GB",
    "wof:name":"DY5 2TW",
    "wof:placetype":"postalcode"
},
  "geometry": {"coordinates":[-2.11677786757508,52.47469017924828],"type":"Point"}
}