{
  "type": "Feature",
  "properties": {
    "iso:country":"GB",
    "wof:name":"SY21 0NT",
    "wof:placetype":"postalcode"
},
  "geometry": {"coordinates":[-3.4960474127798,52.69638788249134],"type":"Point"}
}