{
  "type": "Feature",
  "properties": {
    "iso:country":"GB",
    "wof:name":"SY5 9EH",
    "wof:placetype":"postalcode"
},
  "geometry": {"coordinates":[-2.94114664753248,52.70455644897017],"type":"Point"}
}