{
  "type": "Feature",
  "properties": {
    "iso:country": "GB",
    "wof:name": "SY5 9EH",
    "wof:placetype": "postalcode"
  },
  "geometry": {"coordinates":[-2.941144,52.704571],"type":"Point"}
}
