{
  "type": "Feature",
  "properties": {
    "iso:country": "GB",
    "wof:name": "PA34 5AB",
    "wof:placetype": "postalcode"
  },
  "geometry": {"coordinates":[-5.47622,56.419083],"type":"Point"}
}
