{
  "type": "Feature",
  "properties": {
    "date:inception_lower": "1980-01-01",
    "date:inception_upper": "1980-01-01",
    "iso:country": "GB",
    "wof:name": "PA34 5AB",
    "wof:placetype": "postalcode"
  },
  "geometry": {"coordinates":[-5.478346,56.419323],"type":"Point"}
}
