{
  "type": "Feature",
  "properties": {
    "iso:country":"GB",
    "wof:name":"CA28 8TY",
    "wof:placetype":"postalcode"
},
  "geometry": {"coordinates":[-3.55844766755701,54.53916353435724],"type":"Point"}
}