{
  "type": "Feature",
  "properties": {
    "iso:country": "GB",
    "wof:name": "CA28 8TY",
    "wof:placetype": "postalcode"
  },
  "geometry": {"coordinates":[-3.558449,54.539172],"type":"Point"}
}
