{
  "type": "Feature",
  "properties": {
    "iso:country": "GB",
    "wof:name": "WS11 0DX",
    "wof:placetype": "postalcode"
  },
  "geometry": {"coordinates":[-2.024574,52.686869],"type":"Point"}
}
