{
  "type": "Feature",
  "properties": {
    "iso:country":"GB",
    "wof:name":"TS6 7LJ",
    "wof:placetype":"postalcode"
},
  "geometry": {"coordinates":[-1.14315362751833,54.57122941307905],"type":"Point"}
}