{
  "type": "Feature",
  "properties": {
    "iso:country": "GB",
    "wof:name": "LL23 7EW",
    "wof:placetype": "postalcode"
  },
  "geometry": {"coordinates":[-3.596469,52.893106],"type":"Point"}
}
