{
  "type": "Feature",
  "properties": {
    "iso:country":"GB",
    "wof:name":"LL23 7EW",
    "wof:placetype":"postalcode"
},
  "geometry": {"coordinates":[-3.59629956003667,52.89304884775228],"type":"Point"}
}