{
  "type": "Feature",
  "properties": {
    "iso:country":"GB",
    "wof:name":"CF71 7EN",
    "wof:placetype":"postalcode"
},
  "geometry": {"coordinates":[-3.43757502360621,51.46335761894314],"type":"Point"}
}