{
  "type": "Feature",
  "properties": {
    "iso:country":"GB",
    "wof:name":"PA11 3NU",
    "wof:placetype":"postalcode"
},
  "geometry": {"coordinates":[-4.57965250166808,55.85773668562865],"type":"Point"}
}