{
  "type": "Feature",
  "properties": {
    "date:inception_lower":"1991-09-01",
    "date:inception_upper":"1991-09-30",
    "iso:country":"GB",
    "wof:name":"NG22 9WA",
    "wof:placetype":"postalcode"
},
  "geometry": {"coordinates":[-0.980465,53.228456],"type":"Point"}
}