{
  "type": "Feature",
  "properties": {
    "iso:country": "GB",
    "wof:name": "NG22 9WA",
    "wof:placetype": "postalcode"
  },
  "geometry": {"coordinates":[-0.980465,53.228456],"type":"Point"}
}
