{
  "type": "Feature",
  "properties": {
    "iso:country": "GB",
    "wof:name": "PO15 6LW",
    "wof:placetype": "postalcode"
  },
  "geometry": {"coordinates":[-1.21464,50.866549],"type":"Point"}
}
