{
  "type": "Feature",
  "properties": {
    "iso:country": "GB",
    "wof:name": "RM8 2JJ",
    "wof:placetype": "postalcode"
  },
  "geometry": {"coordinates":[0.113898,51.547608],"type":"Point"}
}
