{
  "type": "Feature",
  "properties": {
    "iso:country":"GB",
    "wof:name":"RM8 2JJ",
    "wof:placetype":"postalcode"
},
  "geometry": {"coordinates":[0.11389836387832,51.54760804388891],"type":"Point"}
}