{
  "type": "Feature",
  "properties": {
    "date:inception_lower": "1980-01-01",
    "date:inception_upper": "1980-01-01",
    "iso:country": "GB",
    "wof:name": "RM8 2JJ",
    "wof:placetype": "postalcode"
  },
  "geometry": {"coordinates":[0.113898,51.547608],"type":"Point"}
}
