{
  "type": "Feature",
  "properties": {
    "date:inception_lower": "1980-01-01",
    "date:inception_upper": "1980-01-01",
    "iso:country": "GB",
    "wof:name": "EX39 6HP",
    "wof:placetype": "postalcode"
  },
  "geometry": {"coordinates":[-4.529885,50.961134],"type":"Point"}
}
