{
  "type": "Feature",
  "properties": {
    "iso:country":"GB",
    "wof:name":"EX39 6HP",
    "wof:placetype":"postalcode"
},
  "geometry": {"coordinates":[-4.5299894843099,50.96100780558453],"type":"Point"}
}