{
  "type": "Feature",
  "properties": {
    "iso:country":"GB",
    "wof:name":"NP25 5SB",
    "wof:placetype":"postalcode"
},
  "geometry": {"coordinates":[-2.72910769834457,51.80970855337235],"type":"Point"}
}