{
  "type": "Feature",
  "properties": {
    "date:inception_lower":"1999-06-01",
    "date:inception_upper":"1999-06-30",
    "iso:country":"GB",
    "wof:name":"NP25 5SB",
    "wof:placetype":"postalcode"
},
  "geometry": {"coordinates":[-2.729108,51.809709],"type":"Point"}
}