{
  "type": "Feature",
  "properties": {
    "iso:country":"GB",
    "wof:name":"W1F 9HR",
    "wof:placetype":"postalcode"
},
  "geometry": {"coordinates":[-0.13689726783171,51.5121481902119],"type":"Point"}
}