{
  "type": "Feature",
  "properties": {
    "iso:country": "GB",
    "wof:name": "NN10 8LF",
    "wof:placetype": "postalcode"
  },
  "geometry": {"coordinates":[-0.587557,52.303603],"type":"Point"}
}
