{
  "type": "Feature",
  "properties": {
    "iso:country": "GB",
    "wof:name": "DN11 0NF",
    "wof:placetype": "postalcode"
  },
  "geometry": {"coordinates":[-1.069432,53.478924],"type":"Point"}
}
