{
  "type": "Feature",
  "properties": {
    "date:inception_lower": "2001-06-01",
    "date:inception_upper": "2001-06-01",
    "iso:country": "GB",
    "wof:name": "CW6 9XZ",
    "wof:placetype": "postalcode"
  },
  "geometry": {"coordinates":[-2.668241,53.158773],"type":"Point"}
}
