{
  "type": "Feature",
  "properties": {
    "iso:country": "GB",
    "wof:name": "WA7 9DE",
    "wof:placetype": "postalcode"
  },
  "geometry": {"coordinates":[-2.694467,53.325791],"type":"Point"}
}
