{
  "type": "Feature",
  "properties": {
    "iso:country": "GB",
    "wof:name": "AB33 8LX",
    "wof:placetype": "postalcode"
  },
  "geometry": {"coordinates":[-2.74011,57.166293],"type":"Point"}
}
