{
  "type": "Feature",
  "properties": {
    "iso:country":"GB",
    "wof:name":"CV3 1EG",
    "wof:placetype":"postalcode"
},
  "geometry": {"coordinates":[-1.47578600204131,52.39734264596144],"type":"Point"}
}