{
  "type": "Feature",
  "properties": {
    "iso:country":"GB",
    "wof:name":"BB1 5AN",
    "wof:placetype":"postalcode"
},
  "geometry": {"coordinates":[-2.47150714375933,53.76249859876928],"type":"Point"}
}