{
  "type": "Feature",
  "properties": {
    "iso:country": "GB",
    "wof:name": "BB1 5AN",
    "wof:placetype": "postalcode"
  },
  "geometry": {"coordinates":[-2.471507,53.762499],"type":"Point"}
}
