{
  "type": "Feature",
  "properties": {
    "iso:country": "GB",
    "wof:name": "DL1 1SQ",
    "wof:placetype": "postalcode"
  },
  "geometry": {"coordinates":[-1.548084,54.525152],"type":"Point"}
}
