{
  "type": "Feature",
  "properties": {
    "iso:country":"GB",
    "wof:name":"DL1 1SQ",
    "wof:placetype":"postalcode"
},
  "geometry": {"coordinates":[-1.54809083223081,54.52514037511442],"type":"Point"}
}