{
  "type": "Feature",
  "properties": {
    "iso:country":"GB",
    "wof:name":"CW9 6DH",
    "wof:placetype":"postalcode"
},
  "geometry": {"coordinates":[-2.48250048892296,53.27920786707692],"type":"Point"}
}