{
  "type": "Feature",
  "properties": {
    "date:inception_lower":"2009-07-01",
    "date:inception_upper":"2009-07-31",
    "iso:country":"GB",
    "wof:name":"LE15 8RQ",
    "wof:placetype":"postalcode"
},
  "geometry": {"coordinates":[-0.68552,52.615782],"type":"Point"}
}