{
  "type": "Feature",
  "properties": {
    "iso:country":"GB",
    "wof:name":"LE15 8RQ",
    "wof:placetype":"postalcode"
},
  "geometry": {"coordinates":[-0.68552018487011,52.61578179817211],"type":"Point"}
}