{
  "type": "Feature",
  "properties": {
    "iso:country":"GB",
    "wof:name":"HG3 3QJ",
    "wof:placetype":"postalcode"
},
  "geometry": {"coordinates":[-1.5087447001768,54.08815957936983],"type":"Point"}
}