{
  "type": "Feature",
  "properties": {
    "iso:country":"GB",
    "wof:name":"M41 7WH",
    "wof:placetype":"postalcode"
},
  "geometry": {"coordinates":[-2.36500151169096,53.46086385830221],"type":"Point"}
}