{
  "type": "Feature",
  "properties": {
    "iso:country":"GB",
    "wof:name":"SY13 4AN",
    "wof:placetype":"postalcode"
},
  "geometry": {"coordinates":[-2.59674395813421,52.98536736668055],"type":"Point"}
}