{
  "type": "Feature",
  "properties": {
    "iso:country": "GB",
    "wof:name": "SY13 4AN",
    "wof:placetype": "postalcode"
  },
  "geometry": {"coordinates":[-2.596744,52.985367],"type":"Point"}
}
