{
  "type": "Feature",
  "properties": {
    "iso:country": "GB",
    "wof:name": "PO36 0NX",
    "wof:placetype": "postalcode"
  },
  "geometry": {"coordinates":[-1.200345,50.661768],"type":"Point"}
}
