{
  "type": "Feature",
  "properties": {
    "iso:country":"GB",
    "wof:name":"PO36 0NX",
    "wof:placetype":"postalcode"
},
  "geometry": {"coordinates":[-1.2003453779517,50.66176754252496],"type":"Point"}
}