{
  "type": "Feature",
  "properties": {
    "date:inception_lower": "2000-12-01",
    "date:inception_upper": "2000-12-01",
    "iso:country": "GB",
    "wof:name": "CM16 4FD",
    "wof:placetype": "postalcode"
  },
  "geometry": {"coordinates":[0.112225,51.694417],"type":"Point"}
}
