{
  "type": "Feature",
  "properties": {
    "iso:country": "GB",
    "wof:name": "CM16 4FD",
    "wof:placetype": "postalcode"
  },
  "geometry": {"coordinates":[0.112225,51.694417],"type":"Point"}
}
