{
  "type": "Feature",
  "properties": {
    "iso:country":"GB",
    "wof:name":"RG8 0SY",
    "wof:placetype":"postalcode"
},
  "geometry": {"coordinates":[-1.03849333792709,51.54634474393432],"type":"Point"}
}