{
  "type": "Feature",
  "properties": {
    "date:inception_lower": "2002-06-01",
    "date:inception_upper": "2002-06-01",
    "iso:country": "GB",
    "wof:name": "RH13 0QD",
    "wof:placetype": "postalcode"
  },
  "geometry": {"coordinates":[-0.387085,51.027302],"type":"Point"}
}
