{
  "type": "Feature",
  "properties": {
    "iso:country":"GB",
    "wof:name":"PO36 8LA",
    "wof:placetype":"postalcode"
},
  "geometry": {"coordinates":[-1.15472394012092,50.65347792814582],"type":"Point"}
}