{
  "type": "Feature",
  "properties": {
    "iso:country": "GB",
    "wof:name": "PO36 8LA",
    "wof:placetype": "postalcode"
  },
  "geometry": {"coordinates":[-1.154714,50.653466],"type":"Point"}
}
