{
  "type": "Feature",
  "properties": {
    "iso:country": "GB",
    "wof:name": "CV23 0XX",
    "wof:placetype": "postalcode"
  },
  "geometry": {"coordinates":[-1.181305,52.38952],"type":"Point"}
}
