{
  "type": "Feature",
  "properties": {
    "date:inception_lower": "2017-04-01",
    "date:inception_upper": "2017-04-01",
    "iso:country": "GB",
    "wof:name": "CV23 0XX",
    "wof:placetype": "postalcode"
  },
  "geometry": {"coordinates":[-1.181305,52.38952],"type":"Point"}
}
