{
  "type": "Feature",
  "properties": {
    "iso:country":"GB",
    "wof:name":"S65 1QR",
    "wof:placetype":"postalcode"
},
  "geometry": {"coordinates":[-1.34688426323276,53.43840744602174],"type":"Point"}
}