{
  "type": "Feature",
  "properties": {
    "iso:country":"GB",
    "wof:name":"G64 3BN",
    "wof:placetype":"postalcode"
},
  "geometry": {"coordinates":[-4.22594318871801,55.9081449835477],"type":"Point"}
}