{
  "type": "Feature",
  "properties": {
    "iso:country":"GB",
    "wof:name":"M19 2LU",
    "wof:placetype":"postalcode"
},
  "geometry": {"coordinates":[-2.20566669110486,53.43569936659383],"type":"Point"}
}