{
  "type": "Feature",
  "properties": {
    "iso:country":"GB",
    "wof:name":"NE47 6AP",
    "wof:placetype":"postalcode"
},
  "geometry": {"coordinates":[-2.20493280274248,54.96497339580766],"type":"Point"}
}