{
  "type": "Feature",
  "properties": {
    "iso:country": "GB",
    "wof:name": "NE47 6AP",
    "wof:placetype": "postalcode"
  },
  "geometry": {"coordinates":[-2.204933,54.964973],"type":"Point"}
}
