{
  "type": "Feature",
  "properties": {
    "date:inception_lower":"1980-01-01",
    "date:inception_upper":"1980-01-31",
    "iso:country":"GB",
    "wof:name":"NE47 6AP",
    "wof:placetype":"postalcode"
},
  "geometry": {"coordinates":[-2.204933,54.964973],"type":"Point"}
}