{
  "type": "Feature",
  "properties": {
    "iso:country": "GB",
    "wof:name": "EN11 8NQ",
    "wof:placetype": "postalcode"
  },
  "geometry": {"coordinates":[-0.01919,51.760687],"type":"Point"}
}
