{
  "type": "Feature",
  "properties": {
    "iso:country":"GB",
    "wof:name":"EN11 8NQ",
    "wof:placetype":"postalcode"
},
  "geometry": {"coordinates":[-0.01919033691273,51.7606869449497],"type":"Point"}
}