{
  "type": "Feature",
  "properties": {
    "iso:country": "GB",
    "wof:name": "CV6 6LS",
    "wof:placetype": "postalcode"
  },
  "geometry": {"coordinates":[-1.475968,52.455797],"type":"Point"}
}
