{
  "type": "Feature",
  "properties": {
    "iso:country": "GB",
    "wof:name": "B70 0TY",
    "wof:placetype": "postalcode"
  },
  "geometry": {"coordinates":[-2.023232,52.538823],"type":"Point"}
}
