{
  "type": "Feature",
  "properties": {
    "iso:country": "GB",
    "wof:name": "BH12 5EB",
    "wof:placetype": "postalcode"
  },
  "geometry": {"coordinates":[-1.909256,50.743726],"type":"Point"}
}
