{
  "type": "Feature",
  "properties": {
    "iso:country": "GB",
    "wof:name": "NG19 8HD",
    "wof:placetype": "postalcode"
  },
  "geometry": {"coordinates":[-1.195762,53.170685],"type":"Point"}
}
