{
  "type": "Feature",
  "properties": {
    "date:inception_lower": "1980-01-01",
    "date:inception_upper": "1980-01-01",
    "iso:country": "GB",
    "wof:name": "NG19 8HD",
    "wof:placetype": "postalcode"
  },
  "geometry": {"coordinates":[-1.195762,53.170685],"type":"Point"}
}
