{
  "type": "Feature",
  "properties": {
    "iso:country":"GB",
    "wof:name":"NG19 8HD",
    "wof:placetype":"postalcode"
},
  "geometry": {"coordinates":[-1.19576234968834,53.17068478959099],"type":"Point"}
}