{
  "type": "Feature",
  "properties": {
    "iso:country": "GB",
    "wof:name": "CB11 3RD",
    "wof:placetype": "postalcode"
  },
  "geometry": {"coordinates":[0.214008,51.98613],"type":"Point"}
}
