{
  "type": "Feature",
  "properties": {
    "iso:country":"GB",
    "wof:name":"S73 8JX",
    "wof:placetype":"postalcode"
},
  "geometry": {"coordinates":[-1.4074412536877,53.52521108817874],"type":"Point"}
}