{
  "type": "Feature",
  "properties": {
    "date:inception_lower":"2016-10-01",
    "date:inception_upper":"2016-10-31",
    "iso:country":"GB",
    "wof:name":"CM4 9BJ",
    "wof:placetype":"postalcode"
},
  "geometry": {"coordinates":[0.442643,51.66384],"type":"Point"}
}