{
  "type": "Feature",
  "properties": {
    "date:inception_lower":"1983-03-01",
    "date:inception_upper":"1983-03-31",
    "iso:country":"GB",
    "wof:name":"GL53 9DJ",
    "wof:placetype":"postalcode"
},
  "geometry": {"coordinates":[-2.064358,51.873693],"type":"Point"}
}