{
  "type": "Feature",
  "properties": {
    "iso:country":"GB",
    "wof:name":"GL53 9DJ",
    "wof:placetype":"postalcode"
},
  "geometry": {"coordinates":[-2.06435821449278,51.87369334673233],"type":"Point"}
}