{
  "type": "Feature",
  "properties": {
    "iso:country": "GB",
    "wof:name": "RH2 8QB",
    "wof:placetype": "postalcode"
  },
  "geometry": {"coordinates":[-0.240988,51.19351],"type":"Point"}
}
