{
  "type": "Feature",
  "properties": {
    "date:inception_lower": "1980-01-01",
    "date:inception_upper": "1980-01-01",
    "iso:country": "GB",
    "wof:name": "SE14 5QP",
    "wof:placetype": "postalcode"
  },
  "geometry": {"coordinates":[-0.044157,51.477564],"type":"Point"}
}
