{
  "type": "Feature",
  "properties": {
    "iso:country": "GB",
    "wof:name": "BD13 3PH",
    "wof:placetype": "postalcode"
  },
  "geometry": {"coordinates":[-1.855422,53.792155],"type":"Point"}
}
