{
  "type": "Feature",
  "properties": {
    "iso:country":"GB",
    "wof:name":"BD13 3PH",
    "wof:placetype":"postalcode"
},
  "geometry": {"coordinates":[-1.85542214024311,53.7921554882107],"type":"Point"}
}