{
  "type": "Feature",
  "properties": {
    "date:inception_lower": "2019-02-01",
    "date:inception_upper": "2019-02-01",
    "iso:country": "GB",
    "wof:name": "NR25 7AZ",
    "wof:placetype": "postalcode"
  },
  "geometry": {"coordinates":[1.059853,52.948016],"type":"Point"}
}
