{
  "type": "Feature",
  "properties": {
    "iso:country": "GB",
    "wof:name": "SR8 3PN",
    "wof:placetype": "postalcode"
  },
  "geometry": {"coordinates":[-1.330505,54.788023],"type":"Point"}
}
