{
  "type": "Feature",
  "properties": {
    "iso:country":"GB",
    "wof:name":"SR8 3PN",
    "wof:placetype":"postalcode"
},
  "geometry": {"coordinates":[-1.3305053942374,54.78802260048314],"type":"Point"}
}