{
  "type": "Feature",
  "properties": {
    "date:inception_lower": "2022-10-01",
    "date:inception_upper": "2022-10-01",
    "iso:country": "GB",
    "wof:name": "LU5 6SZ",
    "wof:placetype": "postalcode"
  },
  "geometry": {"coordinates":[-0.531126,51.905762],"type":"Point"}
}
