{
  "type": "Feature",
  "properties": {
    "iso:country":"GB",
    "wof:name":"CF3 1XZ",
    "wof:placetype":"postalcode"
},
  "geometry": {"coordinates":[-3.10998247348529,51.51332430875813],"type":"Point"}
}