{
  "type": "Feature",
  "properties": {
    "date:inception_lower": "1980-01-01",
    "date:inception_upper": "1980-01-01",
    "iso:country": "GB",
    "wof:name": "CR4 1HW",
    "wof:placetype": "postalcode"
  },
  "geometry": {"coordinates":[-0.151268,51.40173],"type":"Point"}
}
