{
  "type": "Feature",
  "properties": {
    "iso:country": "GB",
    "wof:name": "AB36 8TL",
    "wof:placetype": "postalcode"
  },
  "geometry": {"coordinates":[-3.011385,57.197014],"type":"Point"}
}
