{
  "type": "Feature",
  "properties": {
    "iso:country":"GB",
    "wof:name":"AB36 8TL",
    "wof:placetype":"postalcode"
},
  "geometry": {"coordinates":[-3.0113853471605,57.19701393232867],"type":"Point"}
}