{
  "type": "Feature",
  "properties": {
    "date:inception_lower":"1980-01-01",
    "date:inception_upper":"1980-01-31",
    "iso:country":"GB",
    "wof:name":"PO18 9BA",
    "wof:placetype":"postalcode"
},
  "geometry": {"coordinates":[-0.834875,50.865949],"type":"Point"}
}