{
  "type": "Feature",
  "properties": {
    "iso:country":"GB",
    "wof:name":"PO18 9BA",
    "wof:placetype":"postalcode"
},
  "geometry": {"coordinates":[-0.83533032925485,50.8655485222442],"type":"Point"}
}