{
  "type": "Feature",
  "properties": {
    "iso:country": "GB",
    "wof:name": "PO18 9BA",
    "wof:placetype": "postalcode"
  },
  "geometry": {"coordinates":[-0.834875,50.865949],"type":"Point"}
}
