{
  "type": "Feature",
  "properties": {
    "iso:country": "GB",
    "wof:name": "IV36 2TT",
    "wof:placetype": "postalcode"
  },
  "geometry": {"coordinates":[-3.626891,57.600152],"type":"Point"}
}
