{
  "type": "Feature",
  "properties": {
    "iso:country":"GB",
    "wof:name":"IV36 2TT",
    "wof:placetype":"postalcode"
},
  "geometry": {"coordinates":[-3.62689124113081,57.60015167010484],"type":"Point"}
}