{
  "type": "Feature",
  "properties": {
    "date:inception_lower": "2010-12-01",
    "date:inception_upper": "2010-12-01",
    "iso:country": "GB",
    "wof:name": "IV36 2TT",
    "wof:placetype": "postalcode"
  },
  "geometry": {"coordinates":[-3.626891,57.600152],"type":"Point"}
}
