{
  "type": "Feature",
  "properties": {
    "iso:country":"GB",
    "wof:name":"CF83 1AG",
    "wof:placetype":"postalcode"
},
  "geometry": {"coordinates":[-3.22877567021379,51.5755233769862],"type":"Point"}
}