{
  "type": "Feature",
  "properties": {
    "iso:country": "GB",
    "wof:name": "CF83 1AG",
    "wof:placetype": "postalcode"
  },
  "geometry": {"coordinates":[-3.228776,51.575523],"type":"Point"}
}
