{
  "type": "Feature",
  "properties": {
    "iso:country":"GB",
    "wof:name":"HR8 1FA",
    "wof:placetype":"postalcode"
},
  "geometry": {"coordinates":[-2.50268590539772,52.10356478311212],"type":"Point"}
}