{
  "type": "Feature",
  "properties": {
    "date:inception_lower":"2015-08-01",
    "date:inception_upper":"2015-08-31",
    "iso:country":"GB",
    "wof:name":"HR8 1FA",
    "wof:placetype":"postalcode"
},
  "geometry": {"coordinates":[-2.502686,52.103565],"type":"Point"}
}