{
  "type": "Feature",
  "properties": {
    "iso:country":"GB",
    "wof:name":"NP20 3NS",
    "wof:placetype":"postalcode"
},
  "geometry": {"coordinates":[-3.02422754433187,51.57580580902986],"type":"Point"}
}