{
  "type": "Feature",
  "properties": {
    "iso:country": "GB",
    "wof:name": "NP20 3NS",
    "wof:placetype": "postalcode"
  },
  "geometry": {"coordinates":[-3.024228,51.575806],"type":"Point"}
}
