{
  "type": "Feature",
  "properties": {
    "iso:country": "GB",
    "wof:name": "PO33 1XQ",
    "wof:placetype": "postalcode"
  },
  "geometry": {"coordinates":[-1.106217,50.692982],"type":"Point"}
}
