{
  "type": "Feature",
  "properties": {
    "date:inception_lower": "1980-01-01",
    "date:inception_upper": "1980-01-01",
    "iso:country": "GB",
    "wof:name": "RH17 7RJ",
    "wof:placetype": "postalcode"
  },
  "geometry": {"coordinates":[-0.068474,50.964476],"type":"Point"}
}
