{
  "type": "Feature",
  "properties": {
    "iso:country":"GB",
    "wof:name":"RH17 7RJ",
    "wof:placetype":"postalcode"
},
  "geometry": {"coordinates":[-0.06847362975828,50.96447566135337],"type":"Point"}
}