{
  "type": "Feature",
  "properties": {
    "iso:country":"GB",
    "wof:name":"CO5 0NA",
    "wof:placetype":"postalcode"
},
  "geometry": {"coordinates":[0.74023387428569,51.8213161131986],"type":"Point"}
}