{
  "type": "Feature",
  "properties": {
    "iso:country":"GB",
    "wof:name":"DG12 5AG",
    "wof:placetype":"postalcode"
},
  "geometry": {"coordinates":[-3.25763256220855,54.98852226434821],"type":"Point"}
}