{
  "type": "Feature",
  "properties": {
    "iso:country":"GB",
    "wof:name":"N17 6TH",
    "wof:placetype":"postalcode"
},
  "geometry": {"coordinates":[-0.07809460817687,51.59263567317677],"type":"Point"}
}