{
  "type": "Feature",
  "properties": {
    "iso:country":"GB",
    "wof:name":"ST17 9JQ",
    "wof:placetype":"postalcode"
},
  "geometry": {"coordinates":[-2.11683521317659,52.77853430024208],"type":"Point"}
}