{
  "type": "Feature",
  "properties": {
    "iso:country":"GB",
    "wof:name":"BH23 3NQ",
    "wof:placetype":"postalcode"
},
  "geometry": {"coordinates":[-1.7511994825385,50.72781355803107],"type":"Point"}
}