{
  "type": "Feature",
  "properties": {
    "iso:country": "GB",
    "wof:name": "SR5 3EH",
    "wof:placetype": "postalcode"
  },
  "geometry": {"coordinates":[-1.448117,54.915711],"type":"Point"}
}
