{
  "type": "Feature",
  "properties": {
    "iso:country":"GB",
    "wof:name":"ST9 9NA",
    "wof:placetype":"postalcode"
},
  "geometry": {"coordinates":[-2.08708177706396,53.05922356826589],"type":"Point"}
}