{
  "type": "Feature",
  "properties": {
    "iso:country": "GB",
    "wof:name": "G67 4EF",
    "wof:placetype": "postalcode"
  },
  "geometry": {"coordinates":[-4.03105,55.933375],"type":"Point"}
}
