{
  "type": "Feature",
  "properties": {
    "iso:country": "GB",
    "wof:name": "FK3 8EN",
    "wof:placetype": "postalcode"
  },
  "geometry": {"coordinates":[-3.737195,56.020207],"type":"Point"}
}
