{
  "type": "Feature",
  "properties": {
    "date:inception_lower":"1985-05-01",
    "date:inception_upper":"1985-05-31",
    "iso:country":"GB",
    "wof:name":"FK3 8EN",
    "wof:placetype":"postalcode"
},
  "geometry": {"coordinates":[-3.737195,56.020207],"type":"Point"}
}