{
  "type": "Feature",
  "properties": {
    "iso:country": "GB",
    "wof:name": "E18 1JZ",
    "wof:placetype": "postalcode"
  },
  "geometry": {"coordinates":[0.032192,51.591983],"type":"Point"}
}
