{
  "type": "Feature",
  "properties": {
    "iso:country":"GB",
    "wof:name":"E18 1JZ",
    "wof:placetype":"postalcode"
},
  "geometry": {"coordinates":[0.03219236072329,51.59198275260704],"type":"Point"}
}