{
  "type": "Feature",
  "properties": {
    "iso:country": "GB",
    "wof:name": "M19 2PD",
    "wof:placetype": "postalcode"
  },
  "geometry": {"coordinates":[-2.194914,53.441164],"type":"Point"}
}
