{
  "type": "Feature",
  "properties": {
    "iso:country":"GB",
    "wof:name":"M19 2PD",
    "wof:placetype":"postalcode"
},
  "geometry": {"coordinates":[-2.19491422875394,53.44116445753045],"type":"Point"}
}