{
  "type": "Feature",
  "properties": {
    "iso:country":"GB",
    "wof:name":"M11 3WD",
    "wof:placetype":"postalcode"
},
  "geometry": {"coordinates":[-2.20622675574922,53.47980490217279],"type":"Point"}
}