{
  "type": "Feature",
  "properties": {
    "date:inception_lower": "1984-02-01",
    "date:inception_upper": "1984-02-01",
    "iso:country": "GB",
    "wof:name": "M11 3WD",
    "wof:placetype": "postalcode"
  },
  "geometry": {"coordinates":[-2.206227,53.479805],"type":"Point"}
}
