{
  "type": "Feature",
  "properties": {
    "iso:country": "GB",
    "wof:name": "M11 3WD",
    "wof:placetype": "postalcode"
  },
  "geometry": {"coordinates":[-2.206227,53.479805],"type":"Point"}
}
