{
  "type": "Feature",
  "properties": {
    "iso:country":"GB",
    "wof:name":"TS2 1DW",
    "wof:placetype":"postalcode"
},
  "geometry": {"coordinates":[-1.24098365495559,54.58157036361056],"type":"Point"}
}