{
  "type": "Feature",
  "properties": {
    "date:inception_lower": "2020-08-01",
    "date:inception_upper": "2020-08-01",
    "iso:country": "GB",
    "wof:name": "TS2 1DW",
    "wof:placetype": "postalcode"
  },
  "geometry": {"coordinates":[-1.241205,54.581252],"type":"Point"}
}
