{
  "type": "Feature",
  "properties": {
    "iso:country":"GB",
    "wof:name":"HP5 2SB",
    "wof:placetype":"postalcode"
},
  "geometry": {"coordinates":[-0.62535205188934,51.71253830929415],"type":"Point"}
}