{
  "type": "Feature",
  "properties": {
    "iso:country": "GB",
    "wof:name": "OL9 9TL",
    "wof:placetype": "postalcode"
  },
  "geometry": {"coordinates":[-2.16355,53.545772],"type":"Point"}
}
