{
  "type": "Feature",
  "properties": {
    "iso:country":"GB",
    "wof:name":"CO4 5EP",
    "wof:placetype":"postalcode"
},
  "geometry": {"coordinates":[0.8901076464734,51.91445252660775],"type":"Point"}
}