{
  "type": "Feature",
  "properties": {
    "iso:country": "GB",
    "wof:name": "CO4 5EP",
    "wof:placetype": "postalcode"
  },
  "geometry": {"coordinates":[0.890108,51.914453],"type":"Point"}
}
