{
  "type": "Feature",
  "properties": {
    "iso:country":"GB",
    "wof:name":"E17 3ST",
    "wof:placetype":"postalcode"
},
  "geometry": {"coordinates":[0.0000552090514,51.59132984927345],"type":"Point"}
}