{
  "type": "Feature",
  "properties": {
    "iso:country":"GB",
    "wof:name":"HP7 9EW",
    "wof:placetype":"postalcode"
},
  "geometry": {"coordinates":[-0.59600207659873,51.66890480810145],"type":"Point"}
}