{
  "type": "Feature",
  "properties": {
    "date:inception_lower": "1983-01-01",
    "date:inception_upper": "1983-01-01",
    "iso:country": "GB",
    "wof:name": "LS15 8UE",
    "wof:placetype": "postalcode"
  },
  "geometry": {"coordinates":[-1.435996,53.812093],"type":"Point"}
}
