{
  "type": "Feature",
  "properties": {
    "iso:country": "GB",
    "wof:name": "LS15 8UE",
    "wof:placetype": "postalcode"
  },
  "geometry": {"coordinates":[-1.435996,53.812093],"type":"Point"}
}
