{
  "type": "Feature",
  "properties": {
    "iso:country":"GB",
    "wof:name":"SK10 2PP",
    "wof:placetype":"postalcode"
},
  "geometry": {"coordinates":[-2.10927900267961,53.2687548988664],"type":"Point"}
}