{
  "type": "Feature",
  "properties": {
    "iso:country":"GB",
    "wof:name":"TF12 5DY",
    "wof:placetype":"postalcode"
},
  "geometry": {"coordinates":[-2.47792397306804,52.6095837927458],"type":"Point"}
}