{
  "type": "Feature",
  "properties": {
    "iso:country": "GB",
    "wof:name": "TF12 5DY",
    "wof:placetype": "postalcode"
  },
  "geometry": {"coordinates":[-2.477924,52.609584],"type":"Point"}
}
