{
  "type": "Feature",
  "properties": {
    "iso:country":"GB",
    "wof:name":"WF1 5SW",
    "wof:placetype":"postalcode"
},
  "geometry": {"coordinates":[-1.45691007256156,53.67314286041474],"type":"Point"}
}