{
  "type": "Feature",
  "properties": {
    "iso:country": "GB",
    "wof:name": "FK9 4LT",
    "wof:placetype": "postalcode"
  },
  "geometry": {"coordinates":[-3.930614,56.157136],"type":"Point"}
}
