{
  "type": "Feature",
  "properties": {
    "iso:country":"GB",
    "wof:name":"FK9 4LT",
    "wof:placetype":"postalcode"
},
  "geometry": {"coordinates":[-3.93062105255063,56.15714220359646],"type":"Point"}
}