{
  "type": "Feature",
  "properties": {
    "iso:country":"GB",
    "wof:name":"LE7 4YQ",
    "wof:placetype":"postalcode"
},
  "geometry": {"coordinates":[-1.04545576883039,52.71641017449897],"type":"Point"}
}