{
  "type": "Feature",
  "properties": {
    "iso:country":"GB",
    "wof:name":"NR8 6JA",
    "wof:placetype":"postalcode"
},
  "geometry": {"coordinates":[1.15595882373669,52.68288273626169],"type":"Point"}
}