{
  "type": "Feature",
  "properties": {
    "date:inception_lower":"1980-01-01",
    "date:inception_upper":"1980-01-31",
    "iso:country":"GB",
    "wof:name":"NR8 6JA",
    "wof:placetype":"postalcode"
},
  "geometry": {"coordinates":[1.155959,52.682883],"type":"Point"}
}