{
  "type": "Feature",
  "properties": {
    "date:inception_lower": "2008-09-01",
    "date:inception_upper": "2008-09-01",
    "iso:country": "GB",
    "wof:name": "BH12 4FJ",
    "wof:placetype": "postalcode"
  },
  "geometry": {"coordinates":[-1.94328,50.747408],"type":"Point"}
}
