{
  "type": "Feature",
  "properties": {
    "iso:country":"GB",
    "wof:name":"BD2 1JZ",
    "wof:placetype":"postalcode"
},
  "geometry": {"coordinates":[-1.75499346924768,53.81558600915812],"type":"Point"}
}