{
  "type": "Feature",
  "properties": {
    "iso:country":"GB",
    "wof:name":"AB31 4NU",
    "wof:placetype":"postalcode"
},
  "geometry": {"coordinates":[-2.5778187136261,57.14019106176463],"type":"Point"}
}