{
  "type": "Feature",
  "properties": {
    "date:inception_lower": "1990-08-01",
    "date:inception_upper": "1990-08-01",
    "iso:country": "GB",
    "wof:name": "AB31 4NU",
    "wof:placetype": "postalcode"
  },
  "geometry": {"coordinates":[-2.577819,57.140191],"type":"Point"}
}
