{
  "type": "Feature",
  "properties": {
    "iso:country":"GB",
    "wof:name":"RG1 6JW",
    "wof:placetype":"postalcode"
},
  "geometry": {"coordinates":[-0.97678336841832,51.45181383451921],"type":"Point"}
}