{
  "type": "Feature",
  "properties": {
    "iso:country":"GB",
    "wof:name":"IV2 7WB",
    "wof:placetype":"postalcode"
},
  "geometry": {"coordinates":[-4.13597141327049,57.48850455130114],"type":"Point"}
}