{
  "type": "Feature",
  "properties": {
    "iso:country": "GB",
    "wof:name": "IV2 7WB",
    "wof:placetype": "postalcode"
  },
  "geometry": {"coordinates":[-4.135971,57.488505],"type":"Point"}
}
