{
  "type": "Feature",
  "properties": {
    "iso:country":"GB",
    "wof:name":"SL4 4HB",
    "wof:placetype":"postalcode"
},
  "geometry": {"coordinates":[-0.6404202424101,51.47170381904894],"type":"Point"}
}