{
  "type": "Feature",
  "properties": {
    "iso:country":"GB",
    "wof:name":"FY6 7HU",
    "wof:placetype":"postalcode"
},
  "geometry": {"coordinates":[-2.98748967276464,53.84892643015139],"type":"Point"}
}