{
  "type": "Feature",
  "properties": {
    "iso:country": "GB",
    "wof:name": "FY6 7HU",
    "wof:placetype": "postalcode"
  },
  "geometry": {"coordinates":[-2.98749,53.848926],"type":"Point"}
}
