{
  "type": "Feature",
  "properties": {
    "iso:country":"GB",
    "wof:name":"LN2 4TQ",
    "wof:placetype":"postalcode"
},
  "geometry": {"coordinates":[-0.49846092980867,53.24823340131582],"type":"Point"}
}