{
  "type": "Feature",
  "properties": {
    "date:inception_lower": "1991-09-01",
    "date:inception_upper": "1991-09-01",
    "iso:country": "GB",
    "wof:name": "CH3 5YB",
    "wof:placetype": "postalcode"
  },
  "geometry": {"coordinates":[-2.858024,53.181003],"type":"Point"}
}
