{
  "type": "Feature",
  "properties": {
    "iso:country":"GB",
    "wof:name":"CH3 5YB",
    "wof:placetype":"postalcode"
},
  "geometry": {"coordinates":[-2.85802417242896,53.18100295408847],"type":"Point"}
}