{
  "type": "Feature",
  "properties": {
    "iso:country": "GB",
    "wof:name": "IP16 4PE",
    "wof:placetype": "postalcode"
  },
  "geometry": {"coordinates":[1.617327,52.18246],"type":"Point"}
}
