{
  "type": "Feature",
  "properties": {
    "iso:country":"GB",
    "wof:name":"WA2 9SQ",
    "wof:placetype":"postalcode"
},
  "geometry": {"coordinates":[-2.59529747299967,53.41938120808383],"type":"Point"}
}