{
  "type": "Feature",
  "properties": {
    "date:inception_lower":"2007-07-01",
    "date:inception_upper":"2007-07-31",
    "iso:country":"GB",
    "wof:name":"G53 7ZF",
    "wof:placetype":"postalcode"
},
  "geometry": {"coordinates":[-4.361534,55.803949],"type":"Point"}
}