{
  "type": "Feature",
  "properties": {
    "iso:country":"GB",
    "wof:name":"G53 7ZF",
    "wof:placetype":"postalcode"
},
  "geometry": {"coordinates":[-4.36153383207111,55.80394926628596],"type":"Point"}
}