{
  "type": "Feature",
  "properties": {
    "iso:country":"GB",
    "wof:name":"CM2 7AJ",
    "wof:placetype":"postalcode"
},
  "geometry": {"coordinates":[0.51542023060208,51.71743583438446],"type":"Point"}
}