{
  "type": "Feature",
  "properties": {
    "date:inception_lower":"1980-01-01",
    "date:inception_upper":"1980-01-31",
    "iso:country":"GB",
    "wof:name":"CM2 7AJ",
    "wof:placetype":"postalcode"
},
  "geometry": {"coordinates":[0.51542,51.717436],"type":"Point"}
}