{
  "type": "Feature",
  "properties": {
    "date:inception_lower":"1980-01-01",
    "date:inception_upper":"1980-01-31",
    "iso:country":"GB",
    "wof:name":"NR32 2SW",
    "wof:placetype":"postalcode"
},
  "geometry": {"coordinates":[1.740855,52.484494],"type":"Point"}
}