{
  "type": "Feature",
  "properties": {
    "iso:country": "GB",
    "wof:name": "B61 0FD",
    "wof:placetype": "postalcode"
  },
  "geometry": {"coordinates":[-2.052534,52.3479],"type":"Point"}
}
