{
  "type": "Feature",
  "properties": {
    "date:inception_lower": "2017-04-01",
    "date:inception_upper": "2017-04-01",
    "iso:country": "GB",
    "wof:name": "B61 0FD",
    "wof:placetype": "postalcode"
  },
  "geometry": {"coordinates":[-2.052637,52.348008],"type":"Point"}
}
