{
  "type": "Feature",
  "properties": {
    "date:inception_lower":"2017-04-01",
    "date:inception_upper":"2017-04-30",
    "iso:country":"GB",
    "wof:name":"B61 0FD",
    "wof:placetype":"postalcode"
},
  "geometry": {"coordinates":[-2.051521,52.347505],"type":"Point"}
}