{
  "type": "Feature",
  "properties": {
    "iso:country": "GB",
    "wof:name": "B27 6RL",
    "wof:placetype": "postalcode"
  },
  "geometry": {"coordinates":[-1.805778,52.449048],"type":"Point"}
}
