{
  "type": "Feature",
  "properties": {
    "iso:country":"GB",
    "wof:name":"W1J 5NQ",
    "wof:placetype":"postalcode"
},
  "geometry": {"coordinates":[-0.14800094194361,51.509140699932],"type":"Point"}
}