{
  "type": "Feature",
  "properties": {
    "iso:country": "GB",
    "wof:name": "TF3 4NL",
    "wof:placetype": "postalcode"
  },
  "geometry": {"coordinates":[-2.45357,52.676465],"type":"Point"}
}
