{
  "type": "Feature",
  "properties": {
    "date:inception_lower":"1993-01-01",
    "date:inception_upper":"1993-01-31",
    "iso:country":"GB",
    "wof:name":"TF3 4NL",
    "wof:placetype":"postalcode"
},
  "geometry": {"coordinates":[-2.45357,52.676465],"type":"Point"}
}