{
  "type": "Feature",
  "properties": {
    "iso:country":"GB",
    "wof:name":"TF3 4NL",
    "wof:placetype":"postalcode"
},
  "geometry": {"coordinates":[-2.45356977458927,52.67646469526733],"type":"Point"}
}