{
  "type": "Feature",
  "properties": {
    "date:inception_lower":"2003-03-01",
    "date:inception_upper":"2003-03-31",
    "iso:country":"GB",
    "wof:name":"WS7 1JS",
    "wof:placetype":"postalcode"
},
  "geometry": {"coordinates":[-1.934784,52.681622],"type":"Point"}
}