{
  "type": "Feature",
  "properties": {
    "iso:country": "GB",
    "wof:name": "WS7 1JS",
    "wof:placetype": "postalcode"
  },
  "geometry": {"coordinates":[-1.934778,52.681638],"type":"Point"}
}
