{
  "type": "Feature",
  "properties": {
    "date:inception_lower": "2003-03-01",
    "date:inception_upper": "2003-03-01",
    "iso:country": "GB",
    "wof:name": "WS7 1JS",
    "wof:placetype": "postalcode"
  },
  "geometry": {"coordinates":[-1.93534,52.681728],"type":"Point"}
}
