{
  "type": "Feature",
  "properties": {
    "iso:country": "GB",
    "wof:name": "WA3 4EL",
    "wof:placetype": "postalcode"
  },
  "geometry": {"coordinates":[-2.523791,53.45212],"type":"Point"}
}
