{
  "type": "Feature",
  "properties": {
    "iso:country":"GB",
    "wof:name":"WA3 4EL",
    "wof:placetype":"postalcode"
},
  "geometry": {"coordinates":[-2.52379145503419,53.45212030724274],"type":"Point"}
}