{
  "type": "Feature",
  "properties": {
    "iso:country":"GB",
    "wof:name":"OX1 1BX",
    "wof:placetype":"postalcode"
},
  "geometry": {"coordinates":[-1.25691366939719,51.75164906447729],"type":"Point"}
}