{
  "type": "Feature",
  "properties": {
    "date:inception_lower":"1980-01-01",
    "date:inception_upper":"1980-01-31",
    "iso:country":"GB",
    "wof:name":"OX1 1BX",
    "wof:placetype":"postalcode"
},
  "geometry": {"coordinates":[-1.256914,51.751649],"type":"Point"}
}