{
  "type": "Feature",
  "properties": {
    "iso:country":"GB",
    "wof:name":"N12 0AA",
    "wof:placetype":"postalcode"
},
  "geometry": {"coordinates":[-0.17480813682479,51.60995212321304],"type":"Point"}
}