{
  "type": "Feature",
  "properties": {
    "date:inception_lower": "1980-01-01",
    "date:inception_upper": "1980-01-01",
    "iso:country": "GB",
    "wof:name": "KA1 2RQ",
    "wof:placetype": "postalcode"
  },
  "geometry": {"coordinates":[-4.510959,55.611596],"type":"Point"}
}
