{
  "type": "Feature",
  "properties": {
    "iso:country":"GB",
    "wof:name":"KA1 2RQ",
    "wof:placetype":"postalcode"
},
  "geometry": {"coordinates":[-4.51095862320834,55.61159564823902],"type":"Point"}
}