{
  "type": "Feature",
  "properties": {
    "iso:country":"GB",
    "wof:name":"PE1 5PH",
    "wof:placetype":"postalcode"
},
  "geometry": {"coordinates":[-0.20546693283826,52.58927044762726],"type":"Point"}
}