{
  "type": "Feature",
  "properties": {
    "date:inception_lower":"1993-01-01",
    "date:inception_upper":"1993-01-31",
    "iso:country":"GB",
    "wof:name":"PE1 5PH",
    "wof:placetype":"postalcode"
},
  "geometry": {"coordinates":[-0.205467,52.58927],"type":"Point"}
}