{
  "type": "Feature",
  "properties": {
    "iso:country": "GB",
    "wof:name": "KW17 2EN",
    "wof:placetype": "postalcode"
  },
  "geometry": {"coordinates":[-3.118564,59.008771],"type":"Point"}
}
