{
  "type": "Feature",
  "properties": {
    "iso:country":"GB",
    "wof:name":"KW17 2EN",
    "wof:placetype":"postalcode"
},
  "geometry": {"coordinates":[-3.11856456092121,59.00877122034692],"type":"Point"}
}