{
  "type": "Feature",
  "properties": {
    "iso:country": "GB",
    "wof:name": "B79 7RB",
    "wof:placetype": "postalcode"
  },
  "geometry": {"coordinates":[-1.70145,52.634976],"type":"Point"}
}
