{
  "type": "Feature",
  "properties": {
    "iso:country":"GB",
    "wof:name":"NR5 9BZ",
    "wof:placetype":"postalcode"
},
  "geometry": {"coordinates":[1.22743310089941,52.64113354798127],"type":"Point"}
}