{
  "type": "Feature",
  "properties": {
    "iso:country": "GB",
    "wof:name": "EX39 1HJ",
    "wof:placetype": "postalcode"
  },
  "geometry": {"coordinates":[-4.231053,51.043361],"type":"Point"}
}
