{
  "type": "Feature",
  "properties": {
    "iso:country":"GB",
    "wof:name":"SW13 9JB",
    "wof:placetype":"postalcode"
},
  "geometry": {"coordinates":[-0.23390204187066,51.4867975827671],"type":"Point"}
}