{
  "type": "Feature",
  "properties": {
    "iso:country": "GB",
    "wof:name": "EX17 5EE",
    "wof:placetype": "postalcode"
  },
  "geometry": {"coordinates":[-3.832264,50.738607],"type":"Point"}
}
