{
  "type": "Feature",
  "properties": {
    "iso:country":"GB",
    "wof:name":"EX17 5EE",
    "wof:placetype":"postalcode"
},
  "geometry": {"coordinates":[-3.83310659162389,50.73817895277634],"type":"Point"}
}