{
  "type": "Feature",
  "properties": {
    "date:inception_lower": "1980-01-01",
    "date:inception_upper": "1980-01-01",
    "iso:country": "GB",
    "wof:name": "NG9 6FT",
    "wof:placetype": "postalcode"
  },
  "geometry": {"coordinates":[-1.252451,52.908161],"type":"Point"}
}
