{
  "type": "Feature",
  "properties": {
    "date:inception_lower": "1980-01-01",
    "date:inception_upper": "1980-01-01",
    "iso:country": "GB",
    "wof:name": "BN23 6LB",
    "wof:placetype": "postalcode"
  },
  "geometry": {"coordinates":[0.311007,50.789899],"type":"Point"}
}
