{
  "type": "Feature",
  "properties": {
    "iso:country":"GB",
    "wof:name":"IP22 1NP",
    "wof:placetype":"postalcode"
},
  "geometry": {"coordinates":[0.94838586498895,52.33023839041137],"type":"Point"}
}