{
  "type": "Feature",
  "properties": {
    "iso:country":"GB",
    "wof:name":"CM3 6PJ",
    "wof:placetype":"postalcode"
},
  "geometry": {"coordinates":[0.65683036598426,51.68875373888762],"type":"Point"}
}