{
  "type": "Feature",
  "properties": {
    "date:inception_lower": "1980-01-01",
    "date:inception_upper": "1980-01-01",
    "iso:country": "GB",
    "wof:name": "CM3 6PJ",
    "wof:placetype": "postalcode"
  },
  "geometry": {"coordinates":[0.65683,51.688754],"type":"Point"}
}
