{
  "type": "Feature",
  "properties": {
    "iso:country": "GB",
    "wof:name": "TW18 1AL",
    "wof:placetype": "postalcode"
  },
  "geometry": {"coordinates":[-0.496687,51.429493],"type":"Point"}
}
