{
  "type": "Feature",
  "properties": {
    "date:inception_lower": "2000-06-01",
    "date:inception_upper": "2000-06-01",
    "iso:country": "GB",
    "wof:name": "SA8 4EA",
    "wof:placetype": "postalcode"
  },
  "geometry": {"coordinates":[-3.852233,51.71982],"type":"Point"}
}
