{
  "type": "Feature",
  "properties": {
    "iso:country":"GB",
    "wof:name":"SA8 4EA",
    "wof:placetype":"postalcode"
},
  "geometry": {"coordinates":[-3.85223312624027,51.71981960521632],"type":"Point"}
}