{
  "type": "Feature",
  "properties": {
    "iso:country":"GB",
    "wof:name":"AB16 6LH",
    "wof:placetype":"postalcode"
},
  "geometry": {"coordinates":[-2.1718419606519,57.15119630340293],"type":"Point"}
}