{
  "type": "Feature",
  "properties": {
    "iso:country": "GB",
    "wof:name": "DL8 1FD",
    "wof:placetype": "postalcode"
  },
  "geometry": {"coordinates":[-1.575334,54.29498],"type":"Point"}
}
