{
  "type": "Feature",
  "properties": {
    "iso:country":"GB",
    "wof:name":"BS9 4EF",
    "wof:placetype":"postalcode"
},
  "geometry": {"coordinates":[-2.6083379388562,51.48359584783133],"type":"Point"}
}