{
  "type": "Feature",
  "properties": {
    "iso:country": "GB",
    "wof:name": "DY10 1AU",
    "wof:placetype": "postalcode"
  },
  "geometry": {"coordinates":[-2.246457,52.386029],"type":"Point"}
}
