{
  "type": "Feature",
  "properties": {
    "iso:country":"GB",
    "wof:name":"DY10 1AU",
    "wof:placetype":"postalcode"
},
  "geometry": {"coordinates":[-2.24645729397889,52.38602867559839],"type":"Point"}
}