{
  "type": "Feature",
  "properties": {
    "iso:country":"GB",
    "wof:name":"LA2 8EP",
    "wof:placetype":"postalcode"
},
  "geometry": {"coordinates":[-2.39220143761166,54.12102029215225],"type":"Point"}
}