{
  "type": "Feature",
  "properties": {
    "date:inception_lower": "1996-12-01",
    "date:inception_upper": "1996-12-01",
    "iso:country": "GB",
    "wof:name": "LA2 8EP",
    "wof:placetype": "postalcode"
  },
  "geometry": {"coordinates":[-2.392205,54.121032],"type":"Point"}
}
