{
  "type": "Feature",
  "properties": {
    "date:inception_lower":"1996-12-01",
    "date:inception_upper":"1996-12-31",
    "iso:country":"GB",
    "wof:name":"LA2 8EP",
    "wof:placetype":"postalcode"
},
  "geometry": {"coordinates":[-2.392634,54.121121],"type":"Point"}
}