{
  "type": "Feature",
  "properties": {
    "iso:country": "GB",
    "wof:name": "SY10 8BB",
    "wof:placetype": "postalcode"
  },
  "geometry": {"coordinates":[-3.034561,52.818175],"type":"Point"}
}
