{
  "type": "Feature",
  "properties": {
    "iso:country":"GB",
    "wof:name":"CT10 3PL",
    "wof:placetype":"postalcode"
},
  "geometry": {"coordinates":[1.437863722307,51.36901116978745],"type":"Point"}
}