{
  "type": "Feature",
  "properties": {
    "date:inception_lower": "2000-12-01",
    "date:inception_upper": "2000-12-01",
    "iso:country": "GB",
    "wof:name": "CT10 3PL",
    "wof:placetype": "postalcode"
  },
  "geometry": {"coordinates":[1.437864,51.369011],"type":"Point"}
}
