{
  "type": "Feature",
  "properties": {
    "iso:country": "GB",
    "wof:name": "NE47 8AE",
    "wof:placetype": "postalcode"
  },
  "geometry": {"coordinates":[-2.315252,54.82987],"type":"Point"}
}
