{
  "type": "Feature",
  "properties": {
    "date:inception_lower":"1980-01-01",
    "date:inception_upper":"1980-01-31",
    "iso:country":"GB",
    "wof:name":"NE47 8AE",
    "wof:placetype":"postalcode"
},
  "geometry": {"coordinates":[-2.315252,54.82987],"type":"Point"}
}