{
  "type": "Feature",
  "properties": {
    "date:inception_lower": "1980-01-01",
    "date:inception_upper": "1980-01-01",
    "iso:country": "GB",
    "wof:name": "HD5 9NX",
    "wof:placetype": "postalcode"
  },
  "geometry": {"coordinates":[-1.756553,53.653525],"type":"Point"}
}
