{
  "type": "Feature",
  "properties": {
    "iso:country":"GB",
    "wof:name":"HD5 9NX",
    "wof:placetype":"postalcode"
},
  "geometry": {"coordinates":[-1.75655335515109,53.65352520134],"type":"Point"}
}