{
  "type": "Feature",
  "properties": {
    "date:inception_lower": "2004-06-01",
    "date:inception_upper": "2004-06-01",
    "iso:country": "GB",
    "wof:name": "LU4 0PB",
    "wof:placetype": "postalcode"
  },
  "geometry": {"coordinates":[-0.476565,51.89204],"type":"Point"}
}
