{
  "type": "Feature",
  "properties": {
    "iso:country":"GB",
    "wof:name":"E16 3LF",
    "wof:placetype":"postalcode"
},
  "geometry": {"coordinates":[0.03869348560829,51.51626864579524],"type":"Point"}
}