{
  "type": "Feature",
  "properties": {
    "iso:country": "GB",
    "wof:name": "E16 3LF",
    "wof:placetype": "postalcode"
  },
  "geometry": {"coordinates":[0.038694,51.516269],"type":"Point"}
}
