{
  "type": "Feature",
  "properties": {
    "iso:country": "GB",
    "wof:name": "NN14 4GY",
    "wof:placetype": "postalcode"
  },
  "geometry": {"coordinates":[-0.535624,52.395946],"type":"Point"}
}
