{
  "type": "Feature",
  "properties": {
    "iso:country":"GB",
    "wof:name":"NN14 4GY",
    "wof:placetype":"postalcode"
},
  "geometry": {"coordinates":[-0.53562443737519,52.39594590624415],"type":"Point"}
}