{
  "type": "Feature",
  "properties": {
    "iso:country":"GB",
    "wof:name":"W1K 4BB",
    "wof:placetype":"postalcode"
},
  "geometry": {"coordinates":[-0.14542276934173,51.51230129227088],"type":"Point"}
}