{
  "type": "Feature",
  "properties": {
    "iso:country":"GB",
    "wof:name":"B65 0AW",
    "wof:placetype":"postalcode"
},
  "geometry": {"coordinates":[-2.04599072968479,52.47261739826661],"type":"Point"}
}