{
  "type": "Feature",
  "properties": {
    "iso:country":"GB",
    "wof:name":"W1U 2SF",
    "wof:placetype":"postalcode"
},
  "geometry": {"coordinates":[-0.15030675350244,51.51625418182736],"type":"Point"}
}