{
  "type": "Feature",
  "properties": {
    "iso:country":"GB",
    "wof:name":"PL4 0RP",
    "wof:placetype":"postalcode"
},
  "geometry": {"coordinates":[-4.11593021454477,50.36222745107236],"type":"Point"}
}