{
  "type": "Feature",
  "properties": {
    "iso:country":"GB",
    "wof:name":"GU24 0PN",
    "wof:placetype":"postalcode"
},
  "geometry": {"coordinates":[-0.6609322570461,51.30348036872306],"type":"Point"}
}