{
  "type": "Feature",
  "properties": {
    "iso:country":"GB",
    "wof:name":"ME19 4EU",
    "wof:placetype":"postalcode"
},
  "geometry": {"coordinates":[0.40677946063507,51.27232514185548],"type":"Point"}
}