{
  "type": "Feature",
  "properties": {
    "date:inception_lower": "2005-03-01",
    "date:inception_upper": "2005-03-01",
    "iso:country": "GB",
    "wof:name": "ME19 4EU",
    "wof:placetype": "postalcode"
  },
  "geometry": {"coordinates":[0.40678,51.272325],"type":"Point"}
}
