{
  "type": "Feature",
  "properties": {
    "date:inception_lower": "1980-01-01",
    "date:inception_upper": "1980-01-01",
    "iso:country": "GB",
    "wof:name": "SA61 2LX",
    "wof:placetype": "postalcode"
  },
  "geometry": {"coordinates":[-4.966465,51.802769],"type":"Point"}
}
