{
  "type": "Feature",
  "properties": {
    "iso:country":"GB",
    "wof:name":"SA61 2LX",
    "wof:placetype":"postalcode"
},
  "geometry": {"coordinates":[-4.96646472796859,51.80276921257553],"type":"Point"}
}