{
  "type": "Feature",
  "properties": {
    "iso:country": "GB",
    "wof:name": "BS24 9DU",
    "wof:placetype": "postalcode"
  },
  "geometry": {"coordinates":[-2.962144,51.322102],"type":"Point"}
}
