{
  "type": "Feature",
  "properties": {
    "iso:country":"GB",
    "wof:name":"BS24 9DU",
    "wof:placetype":"postalcode"
},
  "geometry": {"coordinates":[-2.96210920382974,51.32212376241279],"type":"Point"}
}