{
  "type": "Feature",
  "properties": {
    "iso:country":"GB",
    "wof:name":"W6 8ED",
    "wof:placetype":"postalcode"
},
  "geometry": {"coordinates":[-0.21844089076182,51.48473824323904],"type":"Point"}
}