{
  "type": "Feature",
  "properties": {
    "iso:country":"GB",
    "wof:name":"NR6 7BD",
    "wof:placetype":"postalcode"
},
  "geometry": {"coordinates":[1.29486056524159,52.66622990064058],"type":"Point"}
}