{
  "type": "Feature",
  "properties": {
    "iso:country": "GB",
    "wof:name": "LS22 5EN",
    "wof:placetype": "postalcode"
  },
  "geometry": {"coordinates":[-1.337718,53.942205],"type":"Point"}
}
