{
  "type": "Feature",
  "properties": {
    "iso:country":"GB",
    "wof:name":"LS22 5EN",
    "wof:placetype":"postalcode"
},
  "geometry": {"coordinates":[-1.33771816599168,53.94220494790117],"type":"Point"}
}