{
  "type": "Feature",
  "properties": {
    "iso:country":"GB",
    "wof:name":"WF10 5LX",
    "wof:placetype":"postalcode"
},
  "geometry": {"coordinates":[-1.37541731938989,53.72088692868064],"type":"Point"}
}