{
  "type": "Feature",
  "properties": {
    "iso:country":"GB",
    "wof:name":"SE24 9JU",
    "wof:placetype":"postalcode"
},
  "geometry": {"coordinates":[-0.10035224405953,51.45315506617796],"type":"Point"}
}