{
  "type": "Feature",
  "properties": {
    "iso:country": "GB",
    "wof:name": "CH60 5TB",
    "wof:placetype": "postalcode"
  },
  "geometry": {"coordinates":[-3.092716,53.329857],"type":"Point"}
}
