{
  "type": "Feature",
  "properties": {
    "iso:country":"GB",
    "wof:name":"HU3 6RE",
    "wof:placetype":"postalcode"
},
  "geometry": {"coordinates":[-0.38103058123836,53.7484159599414],"type":"Point"}
}