{
  "type": "Feature",
  "properties": {
    "iso:country":"GB",
    "wof:name":"NG8 2DT",
    "wof:placetype":"postalcode"
},
  "geometry": {"coordinates":[-1.24471775736063,52.95523534899143],"type":"Point"}
}