{
  "type": "Feature",
  "properties": {
    "date:inception_lower": "1980-01-01",
    "date:inception_upper": "1980-01-01",
    "iso:country": "GB",
    "wof:name": "NG8 2DT",
    "wof:placetype": "postalcode"
  },
  "geometry": {"coordinates":[-1.244718,52.955235],"type":"Point"}
}
