{
  "type": "Feature",
  "properties": {
    "date:inception_lower": "2011-08-01",
    "date:inception_upper": "2011-08-01",
    "iso:country": "GB",
    "wof:name": "ST15 8WN",
    "wof:placetype": "postalcode"
  },
  "geometry": {"coordinates":[-2.147684,52.914139],"type":"Point"}
}
