{
  "type": "Feature",
  "properties": {
    "iso:country":"GB",
    "wof:name":"ST15 8WN",
    "wof:placetype":"postalcode"
},
  "geometry": {"coordinates":[-2.14761103299865,52.9139613063933],"type":"Point"}
}