{
  "type": "Feature",
  "properties": {
    "iso:country":"GB",
    "wof:name":"WV3 8EH",
    "wof:placetype":"postalcode"
},
  "geometry": {"coordinates":[-2.17404820707724,52.57533350920171],"type":"Point"}
}