{
  "type": "Feature",
  "properties": {
    "date:inception_lower": "1980-01-01",
    "date:inception_upper": "1980-01-01",
    "iso:country": "GB",
    "wof:name": "WV3 8EH",
    "wof:placetype": "postalcode"
  },
  "geometry": {"coordinates":[-2.174048,52.575334],"type":"Point"}
}
