{
  "type": "Feature",
  "properties": {
    "iso:country":"GB",
    "wof:name":"EX34 0PL",
    "wof:placetype":"postalcode"
},
  "geometry": {"coordinates":[-4.0177073628654,51.1969065589925],"type":"Point"}
}