{
  "type": "Feature",
  "properties": {
    "iso:country": "GB",
    "wof:name": "GL18 1SR",
    "wof:placetype": "postalcode"
  },
  "geometry": {"coordinates":[-2.405323,51.928405],"type":"Point"}
}
