{
  "type": "Feature",
  "properties": {
    "iso:country": "GB",
    "wof:name": "PE15 0ND",
    "wof:placetype": "postalcode"
  },
  "geometry": {"coordinates":[0.175439,52.4638],"type":"Point"}
}
