{
  "type": "Feature",
  "properties": {
    "date:inception_lower":"1980-01-01",
    "date:inception_upper":"1980-01-31",
    "iso:country":"GB",
    "wof:name":"PE15 0ND",
    "wof:placetype":"postalcode"
},
  "geometry": {"coordinates":[0.175439,52.4638],"type":"Point"}
}