{
  "type": "Feature",
  "properties": {
    "date:inception_lower":"1980-01-01",
    "date:inception_upper":"1980-01-31",
    "iso:country":"GB",
    "wof:name":"WN3 4RJ",
    "wof:placetype":"postalcode"
},
  "geometry": {"coordinates":[-2.61355,53.538468],"type":"Point"}
}