{
  "type": "Feature",
  "properties": {
    "iso:country":"GB",
    "wof:name":"WA5 7NR",
    "wof:placetype":"postalcode"
},
  "geometry": {"coordinates":[-2.63189458854196,53.41148081251459],"type":"Point"}
}