{
  "type": "Feature",
  "properties": {
    "iso:country": "GB",
    "wof:name": "WA5 7NR",
    "wof:placetype": "postalcode"
  },
  "geometry": {"coordinates":[-2.631894,53.411497],"type":"Point"}
}
