{
  "type": "Feature",
  "properties": {
    "date:inception_lower": "1980-01-01",
    "date:inception_upper": "1980-01-01",
    "iso:country": "GB",
    "wof:name": "RM17 5HU",
    "wof:placetype": "postalcode"
  },
  "geometry": {"coordinates":[0.323492,51.482841],"type":"Point"}
}
