{
  "type": "Feature",
  "properties": {
    "iso:country": "GB",
    "wof:name": "TR26 2BF",
    "wof:placetype": "postalcode"
  },
  "geometry": {"coordinates":[-5.483483,50.206995],"type":"Point"}
}
