{
  "type": "Feature",
  "properties": {
    "date:inception_lower": "1995-07-01",
    "date:inception_upper": "1995-07-01",
    "iso:country": "GB",
    "wof:name": "TR26 2BF",
    "wof:placetype": "postalcode"
  },
  "geometry": {"coordinates":[-5.483483,50.206995],"type":"Point"}
}
