{
  "type": "Feature",
  "properties": {
    "iso:country":"GB",
    "wof:name":"TR26 2BF",
    "wof:placetype":"postalcode"
},
  "geometry": {"coordinates":[-5.48348259772764,50.20699532753959],"type":"Point"}
}