{
  "type": "Feature",
  "properties": {
    "iso:country":"GB",
    "wof:name":"DL3 8QR",
    "wof:placetype":"postalcode"
},
  "geometry": {"coordinates":[-1.57683147491381,54.51290519477823],"type":"Point"}
}