{
  "type": "Feature",
  "properties": {
    "iso:country":"GB",
    "wof:name":"SR8 3NT",
    "wof:placetype":"postalcode"
},
  "geometry": {"coordinates":[-1.33032433113755,54.78674549379112],"type":"Point"}
}