{
  "type": "Feature",
  "properties": {
    "date:inception_lower": "2003-09-01",
    "date:inception_upper": "2003-09-01",
    "iso:country": "GB",
    "wof:name": "SR8 3NT",
    "wof:placetype": "postalcode"
  },
  "geometry": {"coordinates":[-1.330324,54.786745],"type":"Point"}
}
