{
  "type": "Feature",
  "properties": {
    "iso:country":"GB",
    "wof:name":"HX4 0EP",
    "wof:placetype":"postalcode"
},
  "geometry": {"coordinates":[-1.9157613788816,53.6628387215714],"type":"Point"}
}