{
  "type": "Feature",
  "properties": {
    "iso:country": "GB",
    "wof:name": "HX4 0EP",
    "wof:placetype": "postalcode"
  },
  "geometry": {"coordinates":[-1.915761,53.662839],"type":"Point"}
}
