{
  "type": "Feature",
  "properties": {
    "date:inception_lower": "2022-06-01",
    "date:inception_upper": "2022-06-01",
    "iso:country": "GB",
    "wof:name": "PE32 1GN",
    "wof:placetype": "postalcode"
  },
  "geometry": {"coordinates":[0.548824,52.76803],"type":"Point"}
}
