{
  "type": "Feature",
  "properties": {
    "iso:country":"GB",
    "wof:name":"DG9 0EU",
    "wof:placetype":"postalcode"
},
  "geometry": {"coordinates":[-5.04143807763425,54.91254596276242],"type":"Point"}
}