{
  "type": "Feature",
  "properties": {
    "date:inception_lower": "2008-06-01",
    "date:inception_upper": "2008-06-01",
    "iso:country": "GB",
    "wof:name": "DT3 6FE",
    "wof:placetype": "postalcode"
  },
  "geometry": {"coordinates":[-2.449611,50.643397],"type":"Point"}
}
