{
  "type": "Feature",
  "properties": {
    "iso:country":"GB",
    "wof:name":"BS14 9QN",
    "wof:placetype":"postalcode"
},
  "geometry": {"coordinates":[-2.57237502453492,51.40856183193003],"type":"Point"}
}