{
  "type": "Feature",
  "properties": {
    "date:inception_lower": "2011-05-01",
    "date:inception_upper": "2011-05-01",
    "iso:country": "GB",
    "wof:name": "EC1R 4AD",
    "wof:placetype": "postalcode"
  },
  "geometry": {"coordinates":[-0.10521,51.528025],"type":"Point"}
}
