{
  "type": "Feature",
  "properties": {
    "iso:country":"GB",
    "wof:name":"EC1R 4AD",
    "wof:placetype":"postalcode"
},
  "geometry": {"coordinates":[-0.10520996137415,51.52802495827057],"type":"Point"}
}