{
  "type": "Feature",
  "properties": {
    "iso:country":"GB",
    "wof:name":"NG8 6NE",
    "wof:placetype":"postalcode"
},
  "geometry": {"coordinates":[-1.23025503072341,52.97419122173508],"type":"Point"}
}