{
  "type": "Feature",
  "properties": {
    "date:inception_lower":"1980-01-01",
    "date:inception_upper":"1980-01-31",
    "iso:country":"GB",
    "wof:name":"NG8 6NE",
    "wof:placetype":"postalcode"
},
  "geometry": {"coordinates":[-1.230255,52.974191],"type":"Point"}
}