{
  "type": "Feature",
  "properties": {
    "iso:country":"GB",
    "wof:name":"HD8 8NY",
    "wof:placetype":"postalcode"
},
  "geometry": {"coordinates":[-1.68223901518822,53.57446113652983],"type":"Point"}
}