{
  "type": "Feature",
  "properties": {
    "date:inception_lower":"1981-06-01",
    "date:inception_upper":"1981-06-30",
    "iso:country":"GB",
    "wof:name":"TQ2 8QJ",
    "wof:placetype":"postalcode"
},
  "geometry": {"coordinates":[-3.53639,50.500373],"type":"Point"}
}