{
  "type": "Feature",
  "properties": {
    "iso:country": "GB",
    "wof:name": "TQ2 8QJ",
    "wof:placetype": "postalcode"
  },
  "geometry": {"coordinates":[-3.53639,50.500373],"type":"Point"}
}
