{
  "type": "Feature",
  "properties": {
    "iso:country":"GB",
    "wof:name":"BD6 2RS",
    "wof:placetype":"postalcode"
},
  "geometry": {"coordinates":[-1.79509004169901,53.7563673427035],"type":"Point"}
}