{
  "type": "Feature",
  "properties": {
    "date:inception_lower": "1980-01-01",
    "date:inception_upper": "1980-01-01",
    "iso:country": "GB",
    "wof:name": "B77 5HF",
    "wof:placetype": "postalcode"
  },
  "geometry": {"coordinates":[-1.67198,52.606221],"type":"Point"}
}
