{
  "type": "Feature",
  "properties": {
    "iso:country":"GB",
    "wof:name":"B77 5HF",
    "wof:placetype":"postalcode"
},
  "geometry": {"coordinates":[-1.67198004484007,52.60622091701532],"type":"Point"}
}