{
  "type": "Feature",
  "properties": {
    "iso:country":"GB",
    "wof:name":"GL19 4BT",
    "wof:placetype":"postalcode"
},
  "geometry": {"coordinates":[-2.17117151693419,51.95242685693447],"type":"Point"}
}