{
  "type": "Feature",
  "properties": {
    "iso:country":"GB",
    "wof:name":"KT5 9JU",
    "wof:placetype":"postalcode"
},
  "geometry": {"coordinates":[-0.275873452623,51.38515985291972],"type":"Point"}
}