{
  "type": "Feature",
  "properties": {
    "iso:country":"GB",
    "wof:name":"S6 5AF",
    "wof:placetype":"postalcode"
},
  "geometry": {"coordinates":[-1.50356239881212,53.39695934700379],"type":"Point"}
}