{
  "type": "Feature",
  "properties": {
    "date:inception_lower":"2014-01-01",
    "date:inception_upper":"2014-01-31",
    "iso:country":"GB",
    "wof:name":"TA10 9BW",
    "wof:placetype":"postalcode"
},
  "geometry": {"coordinates":[-2.822646,51.045563],"type":"Point"}
}