{
  "type": "Feature",
  "properties": {
    "iso:country": "GB",
    "wof:name": "TA10 9BW",
    "wof:placetype": "postalcode"
  },
  "geometry": {"coordinates":[-2.822646,51.045563],"type":"Point"}
}
