{
  "type": "Feature",
  "properties": {
    "date:inception_lower": "2005-03-01",
    "date:inception_upper": "2005-03-01",
    "iso:country": "GB",
    "wof:name": "M8 8EX",
    "wof:placetype": "postalcode"
  },
  "geometry": {"coordinates":[-2.251035,53.497013],"type":"Point"}
}
