{
  "type": "Feature",
  "properties": {
    "iso:country":"GB",
    "wof:name":"IP1 5PX",
    "wof:placetype":"postalcode"
},
  "geometry": {"coordinates":[1.11326673714342,52.08540628827463],"type":"Point"}
}