{
  "type": "Feature",
  "properties": {
    "date:inception_lower": "1997-12-01",
    "date:inception_upper": "1997-12-01",
    "iso:country": "GB",
    "wof:name": "IP1 5PX",
    "wof:placetype": "postalcode"
  },
  "geometry": {"coordinates":[1.113267,52.085406],"type":"Point"}
}
