{
  "type": "Feature",
  "properties": {
    "iso:country":"GB",
    "wof:name":"IP2 0AP",
    "wof:placetype":"postalcode"
},
  "geometry": {"coordinates":[1.13228851710264,52.05642738136591],"type":"Point"}
}