{
  "type": "Feature",
  "properties": {
    "iso:country":"GB",
    "wof:name":"WA9 1SN",
    "wof:placetype":"postalcode"
},
  "geometry": {"coordinates":[-2.70478885251016,53.45183648944094],"type":"Point"}
}