{
  "type": "Feature",
  "properties": {
    "iso:country": "GB",
    "wof:name": "SL4 2EJ",
    "wof:placetype": "postalcode"
  },
  "geometry": {"coordinates":[-0.613567,51.467909],"type":"Point"}
}
