{
  "type": "Feature",
  "properties": {
    "iso:country":"GB",
    "wof:name":"BH31 6US",
    "wof:placetype":"postalcode"
},
  "geometry": {"coordinates":[-1.87749966647697,50.87774025645268],"type":"Point"}
}