{
  "type": "Feature",
  "properties": {
    "date:inception_lower":"1997-06-01",
    "date:inception_upper":"1997-06-30",
    "iso:country":"GB",
    "wof:name":"BH31 6US",
    "wof:placetype":"postalcode"
},
  "geometry": {"coordinates":[-1.8775,50.87774],"type":"Point"}
}