{
  "type": "Feature",
  "properties": {
    "iso:country":"GB",
    "wof:name":"G12 8AG",
    "wof:placetype":"postalcode"
},
  "geometry": {"coordinates":[-4.29148697675739,55.87571968093766],"type":"Point"}
}