{
  "type": "Feature",
  "properties": {
    "iso:country": "GB",
    "wof:name": "G12 8AG",
    "wof:placetype": "postalcode"
  },
  "geometry": {"coordinates":[-4.291487,55.87572],"type":"Point"}
}
