{
  "type": "Feature",
  "properties": {
    "iso:country":"GB",
    "wof:name":"HD4 5JF",
    "wof:placetype":"postalcode"
},
  "geometry": {"coordinates":[-1.81315314032495,53.62633857393613],"type":"Point"}
}