{
  "type": "Feature",
  "properties": {
    "iso:country":"GB",
    "wof:name":"EH6 5RR",
    "wof:placetype":"postalcode"
},
  "geometry": {"coordinates":[-3.17882605404504,55.97396586023122],"type":"Point"}
}