{
  "type": "Feature",
  "properties": {
    "iso:country":"GB",
    "wof:name":"DE22 3UG",
    "wof:placetype":"postalcode"
},
  "geometry": {"coordinates":[-1.48635602430001,52.91700741236814],"type":"Point"}
}