{
  "type": "Feature",
  "properties": {
    "iso:country": "GB",
    "wof:name": "SE16 2SW",
    "wof:placetype": "postalcode"
  },
  "geometry": {"coordinates":[-0.051638,51.488894],"type":"Point"}
}
