{
  "type": "Feature",
  "properties": {
    "iso:country": "GB",
    "wof:name": "HU17 8FR",
    "wof:placetype": "postalcode"
  },
  "geometry": {"coordinates":[-0.442786,53.825452],"type":"Point"}
}
