{
  "type": "Feature",
  "properties": {
    "iso:country":"GB",
    "wof:name":"RG26 5HG",
    "wof:placetype":"postalcode"
},
  "geometry": {"coordinates":[-1.16238341471764,51.35610265843612],"type":"Point"}
}