{
  "type": "Feature",
  "properties": {
    "date:inception_lower": "1983-01-01",
    "date:inception_upper": "1983-01-01",
    "iso:country": "GB",
    "wof:name": "RG26 5HG",
    "wof:placetype": "postalcode"
  },
  "geometry": {"coordinates":[-1.162383,51.356103],"type":"Point"}
}
