{
  "type": "Feature",
  "properties": {
    "iso:country":"GB",
    "wof:name":"LE9 9NL",
    "wof:placetype":"postalcode"
},
  "geometry": {"coordinates":[-1.34610488269014,52.62951231511619],"type":"Point"}
}