{
  "type": "Feature",
  "properties": {
    "iso:country": "GB",
    "wof:name": "LE9 9NL",
    "wof:placetype": "postalcode"
  },
  "geometry": {"coordinates":[-1.346105,52.629512],"type":"Point"}
}
