{
  "type": "Feature",
  "properties": {
    "date:inception_lower": "1980-01-01",
    "date:inception_upper": "1980-01-01",
    "iso:country": "GB",
    "wof:name": "LN4 2NG",
    "wof:placetype": "postalcode"
  },
  "geometry": {"coordinates":[-0.528148,53.191083],"type":"Point"}
}
