{
  "type": "Feature",
  "properties": {
    "iso:country": "GB",
    "wof:name": "LN4 2NG",
    "wof:placetype": "postalcode"
  },
  "geometry": {"coordinates":[-0.528265,53.191165],"type":"Point"}
}
