{
  "type": "Feature",
  "properties": {
    "iso:country":"GB",
    "wof:name":"LN4 2NG",
    "wof:placetype":"postalcode"
},
  "geometry": {"coordinates":[-0.52814984757627,53.19106077414968],"type":"Point"}
}