{
  "type": "Feature",
  "properties": {
    "iso:country":"GB",
    "wof:name":"HA5 1AE",
    "wof:placetype":"postalcode"
},
  "geometry": {"coordinates":[-0.38673569234307,51.59162765939342],"type":"Point"}
}