{
  "type": "Feature",
  "properties": {
    "iso:country":"GB",
    "wof:name":"ST1 2HX",
    "wof:placetype":"postalcode"
},
  "geometry": {"coordinates":[-2.17012028135487,53.0300089311906],"type":"Point"}
}