{
  "type": "Feature",
  "properties": {
    "iso:country":"GB",
    "wof:name":"CR2 8JF",
    "wof:placetype":"postalcode"
},
  "geometry": {"coordinates":[-0.04656932860225,51.34844964152133],"type":"Point"}
}