{
  "type": "Feature",
  "properties": {
    "date:inception_lower": "1980-01-01",
    "date:inception_upper": "1980-01-01",
    "iso:country": "GB",
    "wof:name": "HP18 9HY",
    "wof:placetype": "postalcode"
  },
  "geometry": {"coordinates":[-1.060758,51.76087],"type":"Point"}
}
