{
  "type": "Feature",
  "properties": {
    "iso:country":"GB",
    "wof:name":"HP18 9HY",
    "wof:placetype":"postalcode"
},
  "geometry": {"coordinates":[-1.06078646081219,51.76050506296946],"type":"Point"}
}