{
  "type": "Feature",
  "properties": {
    "date:inception_lower": "1996-06-01",
    "date:inception_upper": "1996-06-01",
    "iso:country": "GB",
    "wof:name": "BB12 0PA",
    "wof:placetype": "postalcode"
  },
  "geometry": {"coordinates":[-2.26077,53.800191],"type":"Point"}
}
