{
  "type": "Feature",
  "properties": {
    "iso:country":"GB",
    "wof:name":"BB12 0PA",
    "wof:placetype":"postalcode"
},
  "geometry": {"coordinates":[-2.26076955206775,53.8001912331146],"type":"Point"}
}