{
  "type": "Feature",
  "properties": {
    "iso:country": "GB",
    "wof:name": "BB12 0PA",
    "wof:placetype": "postalcode"
  },
  "geometry": {"coordinates":[-2.26077,53.800191],"type":"Point"}
}
