{
  "type": "Feature",
  "properties": {
    "iso:country":"GB",
    "wof:name":"B31 4QB",
    "wof:placetype":"postalcode"
},
  "geometry": {"coordinates":[-1.97643093749341,52.3890887563797],"type":"Point"}
}