{
  "type": "Feature",
  "properties": {
    "iso:country":"GB",
    "wof:name":"SN4 7PZ",
    "wof:placetype":"postalcode"
},
  "geometry": {"coordinates":[-1.90161360283887,51.50066216048175],"type":"Point"}
}