{
  "type": "Feature",
  "properties": {
    "iso:country":"GB",
    "wof:name":"SK4 4RQ",
    "wof:placetype":"postalcode"
},
  "geometry": {"coordinates":[-2.18190664078726,53.4269292101397],"type":"Point"}
}