{
  "type": "Feature",
  "properties": {
    "iso:country": "GB",
    "wof:name": "NE65 9JT",
    "wof:placetype": "postalcode"
  },
  "geometry": {"coordinates":[-1.734903,55.325447],"type":"Point"}
}
