{
  "type": "Feature",
  "properties": {
    "iso:country":"GB",
    "wof:name":"NE65 9JT",
    "wof:placetype":"postalcode"
},
  "geometry": {"coordinates":[-1.73490313359141,55.3254472287965],"type":"Point"}
}