{
  "type": "Feature",
  "properties": {
    "iso:country": "GB",
    "wof:name": "BN43 6PE",
    "wof:placetype": "postalcode"
  },
  "geometry": {"coordinates":[-0.264207,50.837905],"type":"Point"}
}
