{
  "type": "Feature",
  "properties": {
    "date:inception_lower":"1990-07-01",
    "date:inception_upper":"1990-07-31",
    "iso:country":"GB",
    "wof:name":"BN43 6PE",
    "wof:placetype":"postalcode"
},
  "geometry": {"coordinates":[-0.264207,50.837905],"type":"Point"}
}