{
  "type": "Feature",
  "properties": {
    "iso:country":"GB",
    "wof:name":"TN37 6RX",
    "wof:placetype":"postalcode"
},
  "geometry": {"coordinates":[0.56103967237218,50.86256623683109],"type":"Point"}
}