{
  "type": "Feature",
  "properties": {
    "date:inception_lower": "1995-07-01",
    "date:inception_upper": "1995-07-01",
    "iso:country": "GB",
    "wof:name": "CF72 9QG",
    "wof:placetype": "postalcode"
  },
  "geometry": {"coordinates":[-3.459302,51.540199],"type":"Point"}
}
