{
  "type": "Feature",
  "properties": {
    "date:inception_lower": "2001-06-01",
    "date:inception_upper": "2001-06-01",
    "iso:country": "GB",
    "wof:name": "YO30 4GR",
    "wof:placetype": "postalcode"
  },
  "geometry": {"coordinates":[-1.100297,53.987121],"type":"Point"}
}
