{
  "type": "Feature",
  "properties": {
    "iso:country":"GB",
    "wof:name":"YO30 4GR",
    "wof:placetype":"postalcode"
},
  "geometry": {"coordinates":[-1.10029655127333,53.98712102612743],"type":"Point"}
}