{
  "type": "Feature",
  "properties": {
    "iso:country":"GB",
    "wof:name":"PL8 1EW",
    "wof:placetype":"postalcode"
},
  "geometry": {"coordinates":[-4.04105712539376,50.31108434945774],"type":"Point"}
}