{
  "type": "Feature",
  "properties": {
    "iso:country":"GB",
    "wof:name":"NE21 4BU",
    "wof:placetype":"postalcode"
},
  "geometry": {"coordinates":[-1.71739660382094,54.96058624437093],"type":"Point"}
}