{
  "type": "Feature",
  "properties": {
    "iso:country": "GB",
    "wof:name": "PL13 2LE",
    "wof:placetype": "postalcode"
  },
  "geometry": {"coordinates":[-4.530753,50.367721],"type":"Point"}
}
