{
  "type": "Feature",
  "properties": {
    "iso:country":"GB",
    "wof:name":"PL13 2LE",
    "wof:placetype":"postalcode"
},
  "geometry": {"coordinates":[-4.53050749802966,50.36779289295654],"type":"Point"}
}