{
  "type": "Feature",
  "properties": {
    "iso:country": "GB",
    "wof:name": "S10 1NL",
    "wof:placetype": "postalcode"
  },
  "geometry": {"coordinates":[-1.501367,53.387944],"type":"Point"}
}
