{
  "type": "Feature",
  "properties": {
    "iso:country":"GB",
    "wof:name":"S10 1NL",
    "wof:placetype":"postalcode"
},
  "geometry": {"coordinates":[-1.50136678192717,53.38794355990115],"type":"Point"}
}