{
  "type": "Feature",
  "properties": {
    "iso:country":"GB",
    "wof:name":"PO18 9DL",
    "wof:placetype":"postalcode"
},
  "geometry": {"coordinates":[-0.86191728191857,50.87432693236742],"type":"Point"}
}