{
  "type": "Feature",
  "properties": {
    "iso:country": "GB",
    "wof:name": "G69 6DL",
    "wof:placetype": "postalcode"
  },
  "geometry": {"coordinates":[-4.113201,55.854466],"type":"Point"}
}
