{
  "type": "Feature",
  "properties": {
    "iso:country":"GB",
    "wof:name":"BA1 4AQ",
    "wof:placetype":"postalcode"
},
  "geometry": {"coordinates":[-2.38295865598879,51.39052362658249],"type":"Point"}
}