{
  "type": "Feature",
  "properties": {
    "date:inception_lower": "1980-01-01",
    "date:inception_upper": "1980-01-01",
    "iso:country": "GB",
    "wof:name": "BA1 4AQ",
    "wof:placetype": "postalcode"
  },
  "geometry": {"coordinates":[-2.382957,51.39052],"type":"Point"}
}
