{
  "type": "Feature",
  "properties": {
    "iso:country":"GB",
    "wof:name":"BN25 1SH",
    "wof:placetype":"postalcode"
},
  "geometry": {"coordinates":[0.10640611024186,50.77354728510004],"type":"Point"}
}