{
  "type": "Feature",
  "properties": {
    "iso:country":"GB",
    "wof:name":"SK4 1NG",
    "wof:placetype":"postalcode"
},
  "geometry": {"coordinates":[-2.16693056388998,53.41873559167134],"type":"Point"}
}