{
  "type": "Feature",
  "properties": {
    "iso:country": "GB",
    "wof:name": "SO16 7GT",
    "wof:placetype": "postalcode"
  },
  "geometry": {"coordinates":[-1.409197,50.949347],"type":"Point"}
}
