{
  "type": "Feature",
  "properties": {
    "iso:country":"GB",
    "wof:name":"SO16 7GT",
    "wof:placetype":"postalcode"
},
  "geometry": {"coordinates":[-1.40919704335955,50.94934734736567],"type":"Point"}
}