{
  "type": "Feature",
  "properties": {
    "iso:country":"GB",
    "wof:name":"NR25 7EU",
    "wof:placetype":"postalcode"
},
  "geometry": {"coordinates":[1.14352515877581,52.94307778084838],"type":"Point"}
}