{
  "type": "Feature",
  "properties": {
    "date:inception_lower": "2020-09-01",
    "date:inception_upper": "2020-09-01",
    "iso:country": "GB",
    "wof:name": "LN5 7BT",
    "wof:placetype": "postalcode"
  },
  "geometry": {"coordinates":[-0.539256,53.227178],"type":"Point"}
}
