{
  "type": "Feature",
  "properties": {
    "iso:country":"GB",
    "wof:name":"DN32 9TL",
    "wof:placetype":"postalcode"
},
  "geometry": {"coordinates":[-0.06508248250784,53.55595451878318],"type":"Point"}
}