{
  "type": "Feature",
  "properties": {
    "iso:country": "GB",
    "wof:name": "DN32 9TL",
    "wof:placetype": "postalcode"
  },
  "geometry": {"coordinates":[-0.065082,53.555955],"type":"Point"}
}
