{
  "type": "Feature",
  "properties": {
    "iso:country":"GB",
    "wof:name":"NN11 9HZ",
    "wof:placetype":"postalcode"
},
  "geometry": {"coordinates":[-1.1749923521253,52.26681209945571],"type":"Point"}
}