{
  "type": "Feature",
  "properties": {
    "date:inception_lower": "1980-01-01",
    "date:inception_upper": "1980-01-01",
    "iso:country": "GB",
    "wof:name": "SA42 0UJ",
    "wof:placetype": "postalcode"
  },
  "geometry": {"coordinates":[-4.892991,52.013601],"type":"Point"}
}
