{
  "type": "Feature",
  "properties": {
    "iso:country":"GB",
    "wof:name":"ML8 4PD",
    "wof:placetype":"postalcode"
},
  "geometry": {"coordinates":[-3.82749338210556,55.72523955647843],"type":"Point"}
}