{
  "type": "Feature",
  "properties": {
    "date:inception_lower": "1984-02-01",
    "date:inception_upper": "1984-02-01",
    "iso:country": "GB",
    "wof:name": "OL16 2YF",
    "wof:placetype": "postalcode"
  },
  "geometry": {"coordinates":[-2.13555,53.618677],"type":"Point"}
}
