{
  "type": "Feature",
  "properties": {
    "iso:country":"GB",
    "wof:name":"OL16 2YF",
    "wof:placetype":"postalcode"
},
  "geometry": {"coordinates":[-2.13554977605174,53.61867706744921],"type":"Point"}
}