{
  "type": "Feature",
  "properties": {
    "iso:country":"GB",
    "wof:name":"HD8 9HU",
    "wof:placetype":"postalcode"
},
  "geometry": {"coordinates":[-1.62191596203997,53.59218162044884],"type":"Point"}
}