{
  "type": "Feature",
  "properties": {
    "iso:country":"GB",
    "wof:name":"MK17 0LE",
    "wof:placetype":"postalcode"
},
  "geometry": {"coordinates":[-0.80399978005569,51.94524800639676],"type":"Point"}
}