{
  "type": "Feature",
  "properties": {
    "date:inception_lower": "2015-05-01",
    "date:inception_upper": "2015-05-01",
    "iso:country": "GB",
    "wof:name": "KT8 9FD",
    "wof:placetype": "postalcode"
  },
  "geometry": {"coordinates":[-0.344089,51.401233],"type":"Point"}
}
