{
  "type": "Feature",
  "properties": {
    "iso:country": "GB",
    "wof:name": "ML8 4JJ",
    "wof:placetype": "postalcode"
  },
  "geometry": {"coordinates":[-3.831144,55.730433],"type":"Point"}
}
