{
  "type": "Feature",
  "properties": {
    "iso:country":"GB",
    "wof:name":"WV10 0HH",
    "wof:placetype":"postalcode"
},
  "geometry": {"coordinates":[-2.10868718101542,52.59053253069241],"type":"Point"}
}