{
  "type": "Feature",
  "properties": {
    "iso:country":"GB",
    "wof:name":"DE7 4PS",
    "wof:placetype":"postalcode"
},
  "geometry": {"coordinates":[-1.34840311750732,52.95263953601751],"type":"Point"}
}