{
  "type": "Feature",
  "properties": {
    "iso:country": "GB",
    "wof:name": "SN5 7FX",
    "wof:placetype": "postalcode"
  },
  "geometry": {"coordinates":[-1.816511,51.560121],"type":"Point"}
}
