{
  "type": "Feature",
  "properties": {
    "iso:country": "GB",
    "wof:name": "TQ2 8EP",
    "wof:placetype": "postalcode"
  },
  "geometry": {"coordinates":[-3.53216,50.489061],"type":"Point"}
}
