{
  "type": "Feature",
  "properties": {
    "iso:country": "GB",
    "wof:name": "CF45 3UH",
    "wof:placetype": "postalcode"
  },
  "geometry": {"coordinates":[-3.371493,51.674534],"type":"Point"}
}
