{
  "type": "Feature",
  "properties": {
    "iso:country":"GB",
    "wof:name":"B7 4HB",
    "wof:placetype":"postalcode"
},
  "geometry": {"coordinates":[-1.87819566128308,52.48252489332978],"type":"Point"}
}