{
  "type": "Feature",
  "properties": {
    "iso:country":"GB",
    "wof:name":"RG24 8NF",
    "wof:placetype":"postalcode"
},
  "geometry": {"coordinates":[-1.0658695026674,51.28076641459688],"type":"Point"}
}