{
  "type": "Feature",
  "properties": {
    "iso:country":"GB",
    "wof:name":"NG6 9BE",
    "wof:placetype":"postalcode"
},
  "geometry": {"coordinates":[-1.19290680400141,52.99414286730006],"type":"Point"}
}