{
  "type": "Feature",
  "properties": {
    "date:inception_lower":"2004-06-01",
    "date:inception_upper":"2004-06-30",
    "iso:country":"GB",
    "wof:name":"GL50 2SR",
    "wof:placetype":"postalcode"
},
  "geometry": {"coordinates":[-2.085704,51.88588],"type":"Point"}
}