{
  "type": "Feature",
  "properties": {
    "iso:country":"GB",
    "wof:name":"SL4 5SH",
    "wof:placetype":"postalcode"
},
  "geometry": {"coordinates":[-0.6541257641028,51.4810517869519],"type":"Point"}
}