{
  "type": "Feature",
  "properties": {
    "date:inception_lower": "1980-01-01",
    "date:inception_upper": "1980-01-01",
    "iso:country": "GB",
    "wof:name": "SL4 5SH",
    "wof:placetype": "postalcode"
  },
  "geometry": {"coordinates":[-0.654126,51.481052],"type":"Point"}
}
