{
  "type": "Feature",
  "properties": {
    "iso:country": "GB",
    "wof:name": "SL4 5SH",
    "wof:placetype": "postalcode"
  },
  "geometry": {"coordinates":[-0.654126,51.481052],"type":"Point"}
}
