{
  "type": "Feature",
  "properties": {
    "iso:country":"GB",
    "wof:name":"L18 9SA",
    "wof:placetype":"postalcode"
},
  "geometry": {"coordinates":[-2.90798091931388,53.37099401429818],"type":"Point"}
}