{
  "type": "Feature",
  "properties": {
    "iso:country":"GB",
    "wof:name":"NG2 2LJ",
    "wof:placetype":"postalcode"
},
  "geometry": {"coordinates":[-1.14018510490106,52.93909035253692],"type":"Point"}
}