{
  "type": "Feature",
  "properties": {
    "iso:country": "GB",
    "wof:name": "NG2 2LJ",
    "wof:placetype": "postalcode"
  },
  "geometry": {"coordinates":[-1.140185,52.93909],"type":"Point"}
}
