{
  "type": "Feature",
  "properties": {
    "iso:country": "GB",
    "wof:name": "HP11 1FQ",
    "wof:placetype": "postalcode"
  },
  "geometry": {"coordinates":[-0.761288,51.616841],"type":"Point"}
}
