{
  "type": "Feature",
  "properties": {
    "date:inception_lower":"2013-05-01",
    "date:inception_upper":"2013-05-31",
    "iso:country":"GB",
    "wof:name":"NE28 8LY",
    "wof:placetype":"postalcode"
},
  "geometry": {"coordinates":[-1.539986,54.99076],"type":"Point"}
}