{
  "type": "Feature",
  "properties": {
    "iso:country":"GB",
    "wof:name":"SE19 2SD",
    "wof:placetype":"postalcode"
},
  "geometry": {"coordinates":[-0.07633826578163,51.41014709235365],"type":"Point"}
}