{
  "type": "Feature",
  "properties": {
    "iso:country":"GB",
    "wof:name":"BR1 4NU",
    "wof:placetype":"postalcode"
},
  "geometry": {"coordinates":[0.00467889506692,51.41971539785212],"type":"Point"}
}