{
  "type": "Feature",
  "properties": {
    "date:inception_lower": "2002-06-01",
    "date:inception_upper": "2002-06-01",
    "iso:country": "GB",
    "wof:name": "M5 5FU",
    "wof:placetype": "postalcode"
  },
  "geometry": {"coordinates":[-2.312202,53.486181],"type":"Point"}
}
