{
  "type": "Feature",
  "properties": {
    "iso:country":"GB",
    "wof:name":"M5 5FU",
    "wof:placetype":"postalcode"
},
  "geometry": {"coordinates":[-2.31220167256724,53.48618134894305],"type":"Point"}
}