{
  "type": "Feature",
  "properties": {
    "iso:country":"GB",
    "wof:name":"S45 9BU",
    "wof:placetype":"postalcode"
},
  "geometry": {"coordinates":[-1.39683612522556,53.16431237429522],"type":"Point"}
}