{
  "type": "Feature",
  "properties": {
    "iso:country": "GB",
    "wof:name": "S45 9BU",
    "wof:placetype": "postalcode"
  },
  "geometry": {"coordinates":[-1.397193,53.164333],"type":"Point"}
}
