{
  "type": "Feature",
  "properties": {
    "iso:country":"GB",
    "wof:name":"SY4 1BA",
    "wof:placetype":"postalcode"
},
  "geometry": {"coordinates":[-2.93037462755981,52.7672560217556],"type":"Point"}
}