{
  "type": "Feature",
  "properties": {
    "date:inception_lower": "2020-11-01",
    "date:inception_upper": "2020-11-01",
    "iso:country": "GB",
    "wof:name": "CW11 3DW",
    "wof:placetype": "postalcode"
  },
  "geometry": {"coordinates":[-2.401804,53.163055],"type":"Point"}
}
