{
  "type": "Feature",
  "properties": {
    "date:inception_lower":"1980-01-01",
    "date:inception_upper":"1980-01-31",
    "iso:country":"GB",
    "wof:name":"SP6 1JY",
    "wof:placetype":"postalcode"
},
  "geometry": {"coordinates":[-1.792324,50.930954],"type":"Point"}
}