{
  "type": "Feature",
  "properties": {
    "iso:country":"GB",
    "wof:name":"NG17 4DY",
    "wof:placetype":"postalcode"
},
  "geometry": {"coordinates":[-1.25750080356269,53.13778071221176],"type":"Point"}
}