{
  "type": "Feature",
  "properties": {
    "iso:country":"GB",
    "wof:name":"SS11 8HF",
    "wof:placetype":"postalcode"
},
  "geometry": {"coordinates":[0.53222228793368,51.61437211471576],"type":"Point"}
}