{
  "type": "Feature",
  "properties": {
    "iso:country":"GB",
    "wof:name":"WR3 8PN",
    "wof:placetype":"postalcode"
},
  "geometry": {"coordinates":[-2.21196555765286,52.20958101906916],"type":"Point"}
}