{
  "type": "Feature",
  "properties": {
    "iso:country":"GB",
    "wof:name":"N17 7NB",
    "wof:placetype":"postalcode"
},
  "geometry": {"coordinates":[-0.09076872905122,51.60748223862412],"type":"Point"}
}