{
  "type": "Feature",
  "properties": {
    "iso:country":"GB",
    "wof:name":"BB5 5TJ",
    "wof:placetype":"postalcode"
},
  "geometry": {"coordinates":[-2.38860052086216,53.77974766095622],"type":"Point"}
}