{
  "type": "Feature",
  "properties": {
    "iso:country": "GB",
    "wof:name": "ME3 9DF",
    "wof:placetype": "postalcode"
  },
  "geometry": {"coordinates":[0.552644,51.425643],"type":"Point"}
}
