{
  "type": "Feature",
  "properties": {
    "date:inception_lower": "1980-01-01",
    "date:inception_upper": "1980-01-01",
    "iso:country": "GB",
    "wof:name": "ME3 9DF",
    "wof:placetype": "postalcode"
  },
  "geometry": {"coordinates":[0.552644,51.425643],"type":"Point"}
}
