{
  "type": "Feature",
  "properties": {
    "iso:country":"GB",
    "wof:name":"ME3 9DF",
    "wof:placetype":"postalcode"
},
  "geometry": {"coordinates":[0.5526440908586,51.42564295983406],"type":"Point"}
}