{
  "type": "Feature",
  "properties": {
    "iso:country": "GB",
    "wof:name": "LD6 5AD",
    "wof:placetype": "postalcode"
  },
  "geometry": {"coordinates":[-3.511158,52.299983],"type":"Point"}
}
