{
  "type": "Feature",
  "properties": {
    "iso:country":"GB",
    "wof:name":"LD6 5AD",
    "wof:placetype":"postalcode"
},
  "geometry": {"coordinates":[-3.51115763150595,52.29998337512068],"type":"Point"}
}