{
  "type": "Feature",
  "properties": {
    "iso:country": "GB",
    "wof:name": "CT4 6PS",
    "wof:placetype": "postalcode"
  },
  "geometry": {"coordinates":[1.157446,51.2027],"type":"Point"}
}
