{
  "type": "Feature",
  "properties": {
    "iso:country":"GB",
    "wof:name":"HA8 0EN",
    "wof:placetype":"postalcode"
},
  "geometry": {"coordinates":[-0.26202607871619,51.60277816490483],"type":"Point"}
}