{
  "type": "Feature",
  "properties": {
    "iso:country": "GB",
    "wof:name": "PE27 3YH",
    "wof:placetype": "postalcode"
  },
  "geometry": {"coordinates":[-0.07182,52.333579],"type":"Point"}
}
