{
  "type": "Feature",
  "properties": {
    "date:inception_lower": "1995-07-01",
    "date:inception_upper": "1995-07-01",
    "iso:country": "GB",
    "wof:name": "RG20 9LL",
    "wof:placetype": "postalcode"
  },
  "geometry": {"coordinates":[-1.338928,51.320786],"type":"Point"}
}
