{
  "type": "Feature",
  "properties": {
    "iso:country": "GB",
    "wof:name": "RG20 9LL",
    "wof:placetype": "postalcode"
  },
  "geometry": {"coordinates":[-1.338928,51.320786],"type":"Point"}
}
