{
  "type": "Feature",
  "properties": {
    "iso:country": "GB",
    "wof:name": "OL6 6BG",
    "wof:placetype": "postalcode"
  },
  "geometry": {"coordinates":[-2.092752,53.487929],"type":"Point"}
}
