{
  "type": "Feature",
  "properties": {
    "iso:country":"GB",
    "wof:name":"OL6 6BG",
    "wof:placetype":"postalcode"
},
  "geometry": {"coordinates":[-2.09275254523965,53.48792881237932],"type":"Point"}
}