{
  "type": "Feature",
  "properties": {
    "iso:country":"GB",
    "wof:name":"WS9 0JX",
    "wof:placetype":"postalcode"
},
  "geometry": {"coordinates":[-1.94079740995029,52.59914423042057],"type":"Point"}
}