{
  "type": "Feature",
  "properties": {
    "iso:country": "GB",
    "wof:name": "WS9 0JX",
    "wof:placetype": "postalcode"
  },
  "geometry": {"coordinates":[-1.940797,52.599144],"type":"Point"}
}
