{
  "type": "Feature",
  "properties": {
    "iso:country":"GB",
    "wof:name":"S72 9EB",
    "wof:placetype":"postalcode"
},
  "geometry": {"coordinates":[-1.37668405734156,53.59406825794714],"type":"Point"}
}