{
  "type": "Feature",
  "properties": {
    "date:inception_lower": "1980-01-01",
    "date:inception_upper": "1980-01-01",
    "iso:country": "GB",
    "wof:name": "IP21 5TQ",
    "wof:placetype": "postalcode"
  },
  "geometry": {"coordinates":[1.295186,52.374512],"type":"Point"}
}
