{
  "type": "Feature",
  "properties": {
    "iso:country": "GB",
    "wof:name": "IP21 5TQ",
    "wof:placetype": "postalcode"
  },
  "geometry": {"coordinates":[1.295195,52.374431],"type":"Point"}
}
