{
  "type": "Feature",
  "properties": {
    "iso:country":"GB",
    "wof:name":"IP21 5TQ",
    "wof:placetype":"postalcode"
},
  "geometry": {"coordinates":[1.2949005250209,52.37459736297942],"type":"Point"}
}