{
  "type": "Feature",
  "properties": {
    "iso:country": "GB",
    "wof:name": "DG8 8NJ",
    "wof:placetype": "postalcode"
  },
  "geometry": {"coordinates":[-4.53543,54.733024],"type":"Point"}
}
