{
  "type": "Feature",
  "properties": {
    "iso:country":"GB",
    "wof:name":"DG8 8NJ",
    "wof:placetype":"postalcode"
},
  "geometry": {"coordinates":[-4.53536875399166,54.73304283270575],"type":"Point"}
}