{
  "type": "Feature",
  "properties": {
    "iso:country": "GB",
    "wof:name": "SA18 1RE",
    "wof:placetype": "postalcode"
  },
  "geometry": {"coordinates":[-3.876521,51.781534],"type":"Point"}
}
