{
  "type": "Feature",
  "properties": {
    "iso:country":"GB",
    "wof:name":"N16 8SZ",
    "wof:placetype":"postalcode"
},
  "geometry": {"coordinates":[-0.07818660005256,51.55795312974431],"type":"Point"}
}