{
  "type": "Feature",
  "properties": {
    "iso:country": "GB",
    "wof:name": "N16 8SZ",
    "wof:placetype": "postalcode"
  },
  "geometry": {"coordinates":[-0.07816,51.557955],"type":"Point"}
}
