{
  "type": "Feature",
  "properties": {
    "iso:country": "GB",
    "wof:name": "SR8 5RA",
    "wof:placetype": "postalcode"
  },
  "geometry": {"coordinates":[-1.327838,54.757534],"type":"Point"}
}
