{
  "type": "Feature",
  "properties": {
    "iso:country":"GB",
    "wof:name":"SR8 5RA",
    "wof:placetype":"postalcode"
},
  "geometry": {"coordinates":[-1.32783845880054,54.75753396685779],"type":"Point"}
}