{
  "type": "Feature",
  "properties": {
    "iso:country":"GB",
    "wof:name":"NW11 6NA",
    "wof:placetype":"postalcode"
},
  "geometry": {"coordinates":[-0.18258280128552,51.58705236144187],"type":"Point"}
}