{
  "type": "Feature",
  "properties": {
    "date:inception_lower": "1997-12-01",
    "date:inception_upper": "1997-12-01",
    "iso:country": "GB",
    "wof:name": "BS30 9BY",
    "wof:placetype": "postalcode"
  },
  "geometry": {"coordinates":[-2.497337,51.438901],"type":"Point"}
}
