{
  "type": "Feature",
  "properties": {
    "iso:country":"GB",
    "wof:name":"BS30 9BY",
    "wof:placetype":"postalcode"
},
  "geometry": {"coordinates":[-2.49733733054875,51.43890058130469],"type":"Point"}
}