{
  "type": "Feature",
  "properties": {
    "date:inception_lower": "1980-01-01",
    "date:inception_upper": "1980-01-01",
    "iso:country": "GB",
    "wof:name": "W14 9RL",
    "wof:placetype": "postalcode"
  },
  "geometry": {"coordinates":[-0.210283,51.486135],"type":"Point"}
}
