{
  "type": "Feature",
  "properties": {
    "iso:country":"GB",
    "wof:name":"W14 9RL",
    "wof:placetype":"postalcode"
},
  "geometry": {"coordinates":[-0.21037431134495,51.48623405759238],"type":"Point"}
}