{
  "type": "Feature",
  "properties": {
    "date:inception_lower": "1996-12-01",
    "date:inception_upper": "1996-12-01",
    "iso:country": "GB",
    "wof:name": "ST4 8FE",
    "wof:placetype": "postalcode"
  },
  "geometry": {"coordinates":[-2.202091,52.966792],"type":"Point"}
}
