{
  "type": "Feature",
  "properties": {
    "date:inception_lower":"1988-03-01",
    "date:inception_upper":"1988-03-31",
    "iso:country":"GB",
    "wof:name":"SA61 2HQ",
    "wof:placetype":"postalcode"
},
  "geometry": {"coordinates":[-4.973567,51.807694],"type":"Point"}
}