{
  "type": "Feature",
  "properties": {
    "iso:country": "GB",
    "wof:name": "SA61 2HQ",
    "wof:placetype": "postalcode"
  },
  "geometry": {"coordinates":[-4.973567,51.807694],"type":"Point"}
}
