{
  "type": "Feature",
  "properties": {
    "iso:country":"GB",
    "wof:name":"TQ1 4PU",
    "wof:placetype":"postalcode"
},
  "geometry": {"coordinates":[-3.52340255907044,50.48283503284839],"type":"Point"}
}