{
  "type": "Feature",
  "properties": {
    "iso:country": "GB",
    "wof:name": "CH65 4BQ",
    "wof:placetype": "postalcode"
  },
  "geometry": {"coordinates":[-2.894815,53.284977],"type":"Point"}
}
