{
  "type": "Feature",
  "properties": {
    "iso:country": "GB",
    "wof:name": "PL26 7LP",
    "wof:placetype": "postalcode"
  },
  "geometry": {"coordinates":[-4.885863,50.328163],"type":"Point"}
}
