{
  "type": "Feature",
  "properties": {
    "date:inception_lower": "2004-09-01",
    "date:inception_upper": "2004-09-01",
    "iso:country": "GB",
    "wof:name": "NN6 7UW",
    "wof:placetype": "postalcode"
  },
  "geometry": {"coordinates":[-1.119601,52.313415],"type":"Point"}
}
