{
  "type": "Feature",
  "properties": {
    "date:inception_lower": "1980-01-01",
    "date:inception_upper": "1980-01-01",
    "iso:country": "GB",
    "wof:name": "RM12 4ND",
    "wof:placetype": "postalcode"
  },
  "geometry": {"coordinates":[0.209339,51.55658],"type":"Point"}
}
