{
  "type": "Feature",
  "properties": {
    "iso:country":"GB",
    "wof:name":"ST10 1XZ",
    "wof:placetype":"postalcode"
},
  "geometry": {"coordinates":[-1.99367361749668,52.98049267829134],"type":"Point"}
}