{
  "type": "Feature",
  "properties": {
    "iso:country": "GB",
    "wof:name": "NE3 3XF",
    "wof:placetype": "postalcode"
  },
  "geometry": {"coordinates":[-1.639963,55.008314],"type":"Point"}
}
