{
  "type": "Feature",
  "properties": {
    "iso:country":"GB",
    "wof:name":"NE3 3XF",
    "wof:placetype":"postalcode"
},
  "geometry": {"coordinates":[-1.63996260168368,55.00831441175995],"type":"Point"}
}