{
  "type": "Feature",
  "properties": {
    "date:inception_lower": "2017-07-01",
    "date:inception_upper": "2017-07-01",
    "iso:country": "GB",
    "wof:name": "LS25 6PZ",
    "wof:placetype": "postalcode"
  },
  "geometry": {"coordinates":[-1.251505,53.795085],"type":"Point"}
}
