{
  "type": "Feature",
  "properties": {
    "iso:country":"GB",
    "wof:name":"G3 8GJ",
    "wof:placetype":"postalcode"
},
  "geometry": {"coordinates":[-4.28028471598598,55.85998397383977],"type":"Point"}
}