{
  "type": "Feature",
  "properties": {
    "iso:country":"GB",
    "wof:name":"EH6 4TB",
    "wof:placetype":"postalcode"
},
  "geometry": {"coordinates":[-3.19462042324786,55.98055285140055],"type":"Point"}
}