{
  "type": "Feature",
  "properties": {
    "iso:country": "GB",
    "wof:name": "EH6 4TB",
    "wof:placetype": "postalcode"
  },
  "geometry": {"coordinates":[-3.19462,55.980553],"type":"Point"}
}
