{
  "type": "Feature",
  "properties": {
    "date:inception_lower":"2016-03-01",
    "date:inception_upper":"2016-03-31",
    "iso:country":"GB",
    "wof:name":"NE43 7XF",
    "wof:placetype":"postalcode"
},
  "geometry": {"coordinates":[-1.842345,54.969412],"type":"Point"}
}