{
  "type": "Feature",
  "properties": {
    "iso:country":"GB",
    "wof:name":"NR5 9DJ",
    "wof:placetype":"postalcode"
},
  "geometry": {"coordinates":[1.22525137540761,52.64061742580433],"type":"Point"}
}