{
  "type": "Feature",
  "properties": {
    "iso:country":"GB",
    "wof:name":"TS9 5PF",
    "wof:placetype":"postalcode"
},
  "geometry": {"coordinates":[-1.19175885405825,54.47242635138483],"type":"Point"}
}