{
  "type": "Feature",
  "properties": {
    "iso:country": "GB",
    "wof:name": "TS9 5PF",
    "wof:placetype": "postalcode"
  },
  "geometry": {"coordinates":[-1.191759,54.472426],"type":"Point"}
}
