{
  "type": "Feature",
  "properties": {
    "iso:country":"GB",
    "wof:name":"AL1 5LL",
    "wof:placetype":"postalcode"
},
  "geometry": {"coordinates":[-0.31194735253629,51.74860304606499],"type":"Point"}
}