{
  "type": "Feature",
  "properties": {
    "date:inception_lower":"1991-09-01",
    "date:inception_upper":"1991-09-30",
    "iso:country":"GB",
    "wof:name":"CT20 2BB",
    "wof:placetype":"postalcode"
},
  "geometry": {"coordinates":[1.176665,51.078292],"type":"Point"}
}