{
  "type": "Feature",
  "properties": {
    "iso:country": "GB",
    "wof:name": "CO3 0AW",
    "wof:placetype": "postalcode"
  },
  "geometry": {"coordinates":[0.835433,51.874641],"type":"Point"}
}
