{
  "type": "Feature",
  "properties": {
    "iso:country":"GB",
    "wof:name":"CO3 9EY",
    "wof:placetype":"postalcode"
},
  "geometry": {"coordinates":[0.85245127093863,51.88730303372084],"type":"Point"}
}