{
  "type": "Feature",
  "properties": {
    "iso:country": "GB",
    "wof:name": "CO3 9EY",
    "wof:placetype": "postalcode"
  },
  "geometry": {"coordinates":[0.852451,51.887303],"type":"Point"}
}
