{
  "type": "Feature",
  "properties": {
    "iso:country":"GB",
    "wof:name":"BH25 6EU",
    "wof:placetype":"postalcode"
},
  "geometry": {"coordinates":[-1.6477258662828,50.75105395532071],"type":"Point"}
}