{
  "type": "Feature",
  "properties": {
    "date:inception_lower": "1980-01-01",
    "date:inception_upper": "1980-01-01",
    "iso:country": "GB",
    "wof:name": "BH25 6EU",
    "wof:placetype": "postalcode"
  },
  "geometry": {"coordinates":[-1.647726,50.751054],"type":"Point"}
}
