{
  "type": "Feature",
  "properties": {
    "iso:country": "GB",
    "wof:name": "BH25 6EU",
    "wof:placetype": "postalcode"
  },
  "geometry": {"coordinates":[-1.647726,50.751054],"type":"Point"}
}
