{
  "type": "Feature",
  "properties": {
    "iso:country":"GB",
    "wof:name":"GL8 8GX",
    "wof:placetype":"postalcode"
},
  "geometry": {"coordinates":[-2.14708881863318,51.64506580577593],"type":"Point"}
}