{
  "type": "Feature",
  "properties": {
    "iso:country": "GB",
    "wof:name": "GL8 8GX",
    "wof:placetype": "postalcode"
  },
  "geometry": {"coordinates":[-2.147084,51.645041],"type":"Point"}
}
