{
  "type": "Feature",
  "properties": {
    "iso:country": "GB",
    "wof:name": "GL8 8GX",
    "wof:placetype": "postalcode"
  },
  "geometry": {"coordinates":[-2.147089,51.645066],"type":"Point"}
}
