{
  "type": "Feature",
  "properties": {
    "iso:country":"GB",
    "wof:name":"TD2 6QL",
    "wof:placetype":"postalcode"
},
  "geometry": {"coordinates":[-2.75144034812326,55.71959071127801],"type":"Point"}
}