{
  "type": "Feature",
  "properties": {
    "iso:country": "GB",
    "wof:name": "TD2 6QL",
    "wof:placetype": "postalcode"
  },
  "geometry": {"coordinates":[-2.75144,55.719591],"type":"Point"}
}
