{
  "type": "Feature",
  "properties": {
    "iso:country": "GB",
    "wof:name": "SG5 1DU",
    "wof:placetype": "postalcode"
  },
  "geometry": {"coordinates":[-0.278823,51.947113],"type":"Point"}
}
