{
  "type": "Feature",
  "properties": {
    "date:inception_lower": "1980-01-01",
    "date:inception_upper": "1980-01-01",
    "iso:country": "GB",
    "wof:name": "SG5 1DU",
    "wof:placetype": "postalcode"
  },
  "geometry": {"coordinates":[-0.278741,51.94711],"type":"Point"}
}
