{
  "type": "Feature",
  "properties": {
    "date:inception_lower": "1995-12-01",
    "date:inception_upper": "1995-12-01",
    "iso:country": "GB",
    "wof:name": "CW1 5TN",
    "wof:placetype": "postalcode"
  },
  "geometry": {"coordinates":[-2.384378,53.105899],"type":"Point"}
}
