{
  "type": "Feature",
  "properties": {
    "iso:country":"GB",
    "wof:name":"S75 6PJ",
    "wof:placetype":"postalcode"
},
  "geometry": {"coordinates":[-1.50304834234329,53.58682163362579],"type":"Point"}
}