{
  "type": "Feature",
  "properties": {
    "date:inception_lower":"2007-05-01",
    "date:inception_upper":"2007-05-31",
    "iso:country":"GB",
    "wof:name":"S75 6PJ",
    "wof:placetype":"postalcode"
},
  "geometry": {"coordinates":[-1.503048,53.586822],"type":"Point"}
}