{
  "type": "Feature",
  "properties": {
    "iso:country": "GB",
    "wof:name": "S75 6PJ",
    "wof:placetype": "postalcode"
  },
  "geometry": {"coordinates":[-1.503048,53.586822],"type":"Point"}
}
