{
  "type": "Feature",
  "properties": {
    "iso:country":"GB",
    "wof:name":"G52 2NX",
    "wof:placetype":"postalcode"
},
  "geometry": {"coordinates":[-4.35073523457576,55.85350783818243],"type":"Point"}
}