{
  "type": "Feature",
  "properties": {
    "iso:country": "GB",
    "wof:name": "W3 7HL",
    "wof:placetype": "postalcode"
  },
  "geometry": {"coordinates":[-0.245071,51.50763],"type":"Point"}
}
