{
  "type": "Feature",
  "properties": {
    "iso:country":"GB",
    "wof:name":"W3 7HL",
    "wof:placetype":"postalcode"
},
  "geometry": {"coordinates":[-0.24507141710977,51.50762982897979],"type":"Point"}
}