{
  "type": "Feature",
  "properties": {
    "iso:country":"GB",
    "wof:name":"WR1 3QZ",
    "wof:placetype":"postalcode"
},
  "geometry": {"coordinates":[-2.22434113063793,52.19692660536219],"type":"Point"}
}