{
  "type": "Feature",
  "properties": {
    "date:inception_lower":"2001-06-01",
    "date:inception_upper":"2001-06-30",
    "iso:country":"GB",
    "wof:name":"WR1 3QZ",
    "wof:placetype":"postalcode"
},
  "geometry": {"coordinates":[-2.224341,52.196927],"type":"Point"}
}