{
  "type": "Feature",
  "properties": {
    "iso:country": "GB",
    "wof:name": "WR1 3QZ",
    "wof:placetype": "postalcode"
  },
  "geometry": {"coordinates":[-2.224341,52.196927],"type":"Point"}
}
