{
  "type": "Feature",
  "properties": {
    "iso:country":"GB",
    "wof:name":"AB24 4RL",
    "wof:placetype":"postalcode"
},
  "geometry": {"coordinates":[-2.11930724752449,57.16395932238319],"type":"Point"}
}