{
  "type": "Feature",
  "properties": {
    "iso:country":"GB",
    "wof:name":"BH6 5QU",
    "wof:placetype":"postalcode"
},
  "geometry": {"coordinates":[-1.80413613508529,50.73687106272877],"type":"Point"}
}