{
  "type": "Feature",
  "properties": {
    "iso:country":"GB",
    "wof:name":"TN6 3RB",
    "wof:placetype":"postalcode"
},
  "geometry": {"coordinates":[0.17410644988676,51.03855426012122],"type":"Point"}
}