{
  "type": "Feature",
  "properties": {
    "iso:country": "GB",
    "wof:name": "TN6 3RB",
    "wof:placetype": "postalcode"
  },
  "geometry": {"coordinates":[0.174106,51.038554],"type":"Point"}
}
