{
  "type": "Feature",
  "properties": {
    "date:inception_lower": "1980-01-01",
    "date:inception_upper": "1980-01-01",
    "iso:country": "GB",
    "wof:name": "TN6 3RB",
    "wof:placetype": "postalcode"
  },
  "geometry": {"coordinates":[0.175202,51.038181],"type":"Point"}
}
