{
  "type": "Feature",
  "properties": {
    "iso:country":"GB",
    "wof:name":"NP24 6XJ",
    "wof:placetype":"postalcode"
},
  "geometry": {"coordinates":[-3.24098438916586,51.72053021774239],"type":"Point"}
}