{
  "type": "Feature",
  "properties": {
    "iso:country": "GB",
    "wof:name": "NP24 6XJ",
    "wof:placetype": "postalcode"
  },
  "geometry": {"coordinates":[-3.240984,51.72053],"type":"Point"}
}
