{
  "type": "Feature",
  "properties": {
    "date:inception_lower": "1999-06-01",
    "date:inception_upper": "1999-06-01",
    "iso:country": "GB",
    "wof:name": "NP24 6XJ",
    "wof:placetype": "postalcode"
  },
  "geometry": {"coordinates":[-3.240984,51.72053],"type":"Point"}
}
