{
  "type": "Feature",
  "properties": {
    "iso:country":"GB",
    "wof:name":"PO41 0SA",
    "wof:placetype":"postalcode"
},
  "geometry": {"coordinates":[-1.52021228667457,50.70606741781351],"type":"Point"}
}