{
  "type": "Feature",
  "properties": {
    "iso:country": "GB",
    "wof:name": "PE28 0PW",
    "wof:placetype": "postalcode"
  },
  "geometry": {"coordinates":[-0.409061,52.361295],"type":"Point"}
}
