{
  "type": "Feature",
  "properties": {
    "iso:country": "GB",
    "wof:name": "WR15 8NB",
    "wof:placetype": "postalcode"
  },
  "geometry": {"coordinates":[-2.55045,52.339895],"type":"Point"}
}
