{
  "type": "Feature",
  "properties": {
    "iso:country":"GB",
    "wof:name":"WR15 8NB",
    "wof:placetype":"postalcode"
},
  "geometry": {"coordinates":[-2.55048167428194,52.33986315951746],"type":"Point"}
}