{
  "type": "Feature",
  "properties": {
    "date:inception_lower":"1980-01-01",
    "date:inception_upper":"1980-01-31",
    "iso:country":"GB",
    "wof:name":"WR15 8NB",
    "wof:placetype":"postalcode"
},
  "geometry": {"coordinates":[-2.55045,52.339895],"type":"Point"}
}