{
  "type": "Feature",
  "properties": {
    "iso:country":"GB",
    "wof:name":"ME5 9AS",
    "wof:placetype":"postalcode"
},
  "geometry": {"coordinates":[0.52158438852351,51.34460004216174],"type":"Point"}
}