{
  "type": "Feature",
  "properties": {
    "iso:country":"GB",
    "wof:name":"DD10 9UE",
    "wof:placetype":"postalcode"
},
  "geometry": {"coordinates":[-2.46642763590149,56.70137285491069],"type":"Point"}
}