{
  "type": "Feature",
  "properties": {
    "iso:country":"GB",
    "wof:name":"SM4 4EF",
    "wof:placetype":"postalcode"
},
  "geometry": {"coordinates":[-0.20991567125186,51.40153545431333],"type":"Point"}
}