{
  "type": "Feature",
  "properties": {
    "date:inception_lower": "1980-01-01",
    "date:inception_upper": "1980-01-01",
    "iso:country": "GB",
    "wof:name": "SM4 4EF",
    "wof:placetype": "postalcode"
  },
  "geometry": {"coordinates":[-0.209862,51.401552],"type":"Point"}
}
