{
  "type": "Feature",
  "properties": {
    "iso:country":"GB",
    "wof:name":"BL9 8EU",
    "wof:placetype":"postalcode"
},
  "geometry": {"coordinates":[-2.28177423307823,53.57238380128288],"type":"Point"}
}