{
  "type": "Feature",
  "properties": {
    "iso:country": "GB",
    "wof:name": "BL9 8EU",
    "wof:placetype": "postalcode"
  },
  "geometry": {"coordinates":[-2.280367,53.572322],"type":"Point"}
}
