{
  "type": "Feature",
  "properties": {
    "iso:country":"GB",
    "wof:name":"PO20 1AW",
    "wof:placetype":"postalcode"
},
  "geometry": {"coordinates":[-0.7800723144064,50.80811301873984],"type":"Point"}
}