{
  "type": "Feature",
  "properties": {
    "date:inception_lower": "2002-06-01",
    "date:inception_upper": "2002-06-01",
    "iso:country": "GB",
    "wof:name": "PO20 1AW",
    "wof:placetype": "postalcode"
  },
  "geometry": {"coordinates":[-0.780072,50.808113],"type":"Point"}
}
