{
  "type": "Feature",
  "properties": {
    "iso:country": "GB",
    "wof:name": "WA3 2SX",
    "wof:placetype": "postalcode"
  },
  "geometry": {"coordinates":[-2.583478,53.470484],"type":"Point"}
}
