{
  "type": "Feature",
  "properties": {
    "iso:country":"GB",
    "wof:name":"TR1 1JE",
    "wof:placetype":"postalcode"
},
  "geometry": {"coordinates":[-5.04641651865735,50.2662933741077],"type":"Point"}
}