{
  "type": "Feature",
  "properties": {
    "iso:country": "GB",
    "wof:name": "TR1 1JE",
    "wof:placetype": "postalcode"
  },
  "geometry": {"coordinates":[-5.046465,50.2663],"type":"Point"}
}
