{
  "type": "Feature",
  "properties": {
    "iso:country":"GB",
    "wof:name":"LS9 7SZ",
    "wof:placetype":"postalcode"
},
  "geometry": {"coordinates":[-1.52517668951305,53.80246652482293],"type":"Point"}
}