{
  "type": "Feature",
  "properties": {
    "iso:country":"GB",
    "wof:name":"KA13 6PH",
    "wof:placetype":"postalcode"
},
  "geometry": {"coordinates":[-4.71969237567379,55.66842779601671],"type":"Point"}
}