{
  "type": "Feature",
  "properties": {
    "iso:country":"GB",
    "wof:name":"UB1 1NZ",
    "wof:placetype":"postalcode"
},
  "geometry": {"coordinates":[-0.38548779258217,51.51276698628202],"type":"Point"}
}