{
  "type": "Feature",
  "properties": {
    "date:inception_lower":"1993-08-01",
    "date:inception_upper":"1993-08-31",
    "iso:country":"GB",
    "wof:name":"SY1 4NT",
    "wof:placetype":"postalcode"
},
  "geometry": {"coordinates":[-2.717069,52.7349],"type":"Point"}
}