{
  "type": "Feature",
  "properties": {
    "iso:country":"GB",
    "wof:name":"SY1 4NT",
    "wof:placetype":"postalcode"
},
  "geometry": {"coordinates":[-2.71680162199466,52.73482088865072],"type":"Point"}
}