{
  "type": "Feature",
  "properties": {
    "date:inception_lower":"2005-10-01",
    "date:inception_upper":"2005-10-31",
    "iso:country":"GB",
    "wof:name":"SY13 4JH",
    "wof:placetype":"postalcode"
},
  "geometry": {"coordinates":[-2.684148,53.034167],"type":"Point"}
}