{
  "type": "Feature",
  "properties": {
    "iso:country":"GB",
    "wof:name":"SY13 4JH",
    "wof:placetype":"postalcode"
},
  "geometry": {"coordinates":[-2.68414835568797,53.03416686114547],"type":"Point"}
}