{
  "type": "Feature",
  "properties": {
    "iso:country":"GB",
    "wof:name":"PO22 7HP",
    "wof:placetype":"postalcode"
},
  "geometry": {"coordinates":[-0.6429661860781,50.79199423693848],"type":"Point"}
}