{
  "type": "Feature",
  "properties": {
    "iso:country":"GB",
    "wof:name":"N8 9BT",
    "wof:placetype":"postalcode"
},
  "geometry": {"coordinates":[-0.11957686979963,51.58204912302519],"type":"Point"}
}