{
  "type": "Feature",
  "properties": {
    "iso:country":"GB",
    "wof:name":"NR13 5RF",
    "wof:placetype":"postalcode"
},
  "geometry": {"coordinates":[1.41776437164895,52.62436880422548],"type":"Point"}
}