{
  "type": "Feature",
  "properties": {
    "iso:country":"GB",
    "wof:name":"NG16 5DP",
    "wof:placetype":"postalcode"
},
  "geometry": {"coordinates":[-1.3474145037981,53.0608025331279],"type":"Point"}
}