{
  "type": "Feature",
  "properties": {
    "date:inception_lower": "2006-03-01",
    "date:inception_upper": "2006-03-01",
    "iso:country": "GB",
    "wof:name": "MK41 0GY",
    "wof:placetype": "postalcode"
  },
  "geometry": {"coordinates":[-0.391432,52.159798],"type":"Point"}
}
