{
  "type": "Feature",
  "properties": {
    "iso:country":"GB",
    "wof:name":"CV2 5AB",
    "wof:placetype":"postalcode"
},
  "geometry": {"coordinates":[-1.45388492915132,52.41663535742153],"type":"Point"}
}