{
  "type": "Feature",
  "properties": {
    "iso:country":"GB",
    "wof:name":"CA8 9BS",
    "wof:placetype":"postalcode"
},
  "geometry": {"coordinates":[-2.76386724802037,54.8834127738272],"type":"Point"}
}