{
  "type": "Feature",
  "properties": {
    "date:inception_lower":"2006-09-01",
    "date:inception_upper":"2006-09-30",
    "iso:country":"GB",
    "wof:name":"CB23 2NP",
    "wof:placetype":"postalcode"
},
  "geometry": {"coordinates":[-0.037429,52.179368],"type":"Point"}
}