{
  "type": "Feature",
  "properties": {
    "iso:country": "GB",
    "wof:name": "CB23 2NP",
    "wof:placetype": "postalcode"
  },
  "geometry": {"coordinates":[-0.037429,52.179368],"type":"Point"}
}
