{
  "type": "Feature",
  "properties": {
    "iso:country":"GB",
    "wof:name":"CB23 2NP",
    "wof:placetype":"postalcode"
},
  "geometry": {"coordinates":[-0.03486179323649,52.17781065394664],"type":"Point"}
}