{
  "type": "Feature",
  "properties": {
    "iso:country":"GB",
    "wof:name":"NW9 5WZ",
    "wof:placetype":"postalcode"
},
  "geometry": {"coordinates":[-0.24109527492867,51.59511071035517],"type":"Point"}
}