{
  "type": "Feature",
  "properties": {
    "date:inception_lower": "1980-01-01",
    "date:inception_upper": "1980-01-01",
    "iso:country": "GB",
    "wof:name": "LL21 9LW",
    "wof:placetype": "postalcode"
  },
  "geometry": {"coordinates":[-3.272478,53.016622],"type":"Point"}
}
