{
  "type": "Feature",
  "properties": {
    "iso:country":"GB",
    "wof:name":"LL21 9LW",
    "wof:placetype":"postalcode"
},
  "geometry": {"coordinates":[-3.27234555239737,53.01668845560894],"type":"Point"}
}