{
  "type": "Feature",
  "properties": {
    "iso:country": "GB",
    "wof:name": "GU21 5TU",
    "wof:placetype": "postalcode"
  },
  "geometry": {"coordinates":[-0.519003,51.337642],"type":"Point"}
}
