{
  "type": "Feature",
  "properties": {
    "iso:country": "GB",
    "wof:name": "BN20 9LA",
    "wof:placetype": "postalcode"
  },
  "geometry": {"coordinates":[0.251212,50.802248],"type":"Point"}
}
