{
  "type": "Feature",
  "properties": {
    "iso:country": "GB",
    "wof:name": "CF42 5NE",
    "wof:placetype": "postalcode"
  },
  "geometry": {"coordinates":[-3.547705,51.680931],"type":"Point"}
}
