{
  "type": "Feature",
  "properties": {
    "iso:country":"GB",
    "wof:name":"HD1 3PJ",
    "wof:placetype":"postalcode"
},
  "geometry": {"coordinates":[-1.78752519229741,53.63825921038991],"type":"Point"}
}