{
  "type": "Feature",
  "properties": {
    "date:inception_lower": "1980-01-01",
    "date:inception_upper": "1980-01-01",
    "iso:country": "GB",
    "wof:name": "HD1 3PJ",
    "wof:placetype": "postalcode"
  },
  "geometry": {"coordinates":[-1.787525,53.638259],"type":"Point"}
}
