{
  "type": "Feature",
  "properties": {
    "date:inception_lower": "2020-02-01",
    "date:inception_upper": "2020-02-01",
    "iso:country": "GB",
    "wof:name": "RH3 7DD",
    "wof:placetype": "postalcode"
  },
  "geometry": {"coordinates":[-0.281356,51.235313],"type":"Point"}
}
