{
  "type": "Feature",
  "properties": {
    "iso:country":"GB",
    "wof:name":"L12 0HD",
    "wof:placetype":"postalcode"
},
  "geometry": {"coordinates":[-2.88718899521962,53.43795561861977],"type":"Point"}
}