{
  "type": "Feature",
  "properties": {
    "date:inception_lower": "2018-06-01",
    "date:inception_upper": "2018-06-01",
    "iso:country": "GB",
    "wof:name": "NR32 3RF",
    "wof:placetype": "postalcode"
  },
  "geometry": {"coordinates":[1.715506,52.47593],"type":"Point"}
}
