{
  "type": "Feature",
  "properties": {
    "iso:country": "GB",
    "wof:name": "NR32 3RF",
    "wof:placetype": "postalcode"
  },
  "geometry": {"coordinates":[1.715481,52.475985],"type":"Point"}
}
