{
  "type": "Feature",
  "properties": {
    "iso:country":"GB",
    "wof:name":"TW6 1DJ",
    "wof:placetype":"postalcode"
},
  "geometry": {"coordinates":[-0.4535343371129,51.47116865635368],"type":"Point"}
}