{
  "type": "Feature",
  "properties": {
    "iso:country":"GB",
    "wof:name":"GL51 0HY",
    "wof:placetype":"postalcode"
},
  "geometry": {"coordinates":[-2.11845549751628,51.90324914526769],"type":"Point"}
}