{
  "type": "Feature",
  "properties": {
    "date:inception_lower": "1987-10-01",
    "date:inception_upper": "1987-10-01",
    "iso:country": "GB",
    "wof:name": "PL15 7HE",
    "wof:placetype": "postalcode"
  },
  "geometry": {"coordinates":[-4.364034,50.631274],"type":"Point"}
}
