{
  "type": "Feature",
  "properties": {
    "iso:country":"GB",
    "wof:name":"DA11 0EW",
    "wof:placetype":"postalcode"
},
  "geometry": {"coordinates":[0.35629622033273,51.44246343467781],"type":"Point"}
}