{
  "type": "Feature",
  "properties": {
    "iso:country": "GB",
    "wof:name": "LS28 6PA",
    "wof:placetype": "postalcode"
  },
  "geometry": {"coordinates":[-1.649265,53.810479],"type":"Point"}
}
