{
  "type": "Feature",
  "properties": {
    "iso:country":"GB",
    "wof:name":"CW1 2BD",
    "wof:placetype":"postalcode"
},
  "geometry": {"coordinates":[-2.43886082159699,53.10077509558889],"type":"Point"}
}