{
  "type": "Feature",
  "properties": {
    "iso:country":"GB",
    "wof:name":"NE16 4BF",
    "wof:placetype":"postalcode"
},
  "geometry": {"coordinates":[-1.67618483134171,54.94679749106901],"type":"Point"}
}