{
  "type": "Feature",
  "properties": {
    "date:inception_lower":"2016-01-01",
    "date:inception_upper":"2016-01-31",
    "iso:country":"GB",
    "wof:name":"NE16 4BF",
    "wof:placetype":"postalcode"
},
  "geometry": {"coordinates":[-1.676185,54.946797],"type":"Point"}
}