{
  "type": "Feature",
  "properties": {
    "iso:country": "GB",
    "wof:name": "NE16 4BF",
    "wof:placetype": "postalcode"
  },
  "geometry": {"coordinates":[-1.676185,54.946797],"type":"Point"}
}
