{
  "type": "Feature",
  "properties": {
    "date:inception_lower": "1980-01-01",
    "date:inception_upper": "1980-01-01",
    "iso:country": "GB",
    "wof:name": "SN6 6EA",
    "wof:placetype": "postalcode"
  },
  "geometry": {"coordinates":[-1.853074,51.640967],"type":"Point"}
}
