{
  "type": "Feature",
  "properties": {
    "iso:country":"GB",
    "wof:name":"N22 6AG",
    "wof:placetype":"postalcode"
},
  "geometry": {"coordinates":[-0.09203169505582,51.59458063539021],"type":"Point"}
}