{
  "type": "Feature",
  "properties": {
    "date:inception_lower": "1980-01-01",
    "date:inception_upper": "1980-01-01",
    "iso:country": "GB",
    "wof:name": "PE4 6RA",
    "wof:placetype": "postalcode"
  },
  "geometry": {"coordinates":[-0.270363,52.616624],"type":"Point"}
}
