{
  "type": "Feature",
  "properties": {
    "date:inception_lower":"1994-05-01",
    "date:inception_upper":"1994-05-31",
    "iso:country":"GB",
    "wof:name":"SK17 8JF",
    "wof:placetype":"postalcode"
},
  "geometry": {"coordinates":[-1.799287,53.300322],"type":"Point"}
}