{
  "type": "Feature",
  "properties": {
    "iso:country":"GB",
    "wof:name":"SK17 8JF",
    "wof:placetype":"postalcode"
},
  "geometry": {"coordinates":[-1.79928730093491,53.30032207631071],"type":"Point"}
}