{
  "type": "Feature",
  "properties": {
    "date:inception_lower":"2012-02-01",
    "date:inception_upper":"2012-02-29",
    "iso:country":"GB",
    "wof:name":"WR14 1GW",
    "wof:placetype":"postalcode"
},
  "geometry": {"coordinates":[-2.334347,52.130595],"type":"Point"}
}