{
  "type": "Feature",
  "properties": {
    "iso:country": "GB",
    "wof:name": "NW2 1QS",
    "wof:placetype": "postalcode"
  },
  "geometry": {"coordinates":[-0.209526,51.568981],"type":"Point"}
}
