{
  "type": "Feature",
  "properties": {
    "iso:country": "GB",
    "wof:name": "NE49 0AW",
    "wof:placetype": "postalcode"
  },
  "geometry": {"coordinates":[-2.470581,54.965376],"type":"Point"}
}
