{
  "type": "Feature",
  "properties": {
    "date:inception_lower": "1980-01-01",
    "date:inception_upper": "1980-01-01",
    "iso:country": "GB",
    "wof:name": "WA15 0BB",
    "wof:placetype": "postalcode"
  },
  "geometry": {"coordinates":[-2.310438,53.360283],"type":"Point"}
}
