{
  "type": "Feature",
  "properties": {
    "iso:country":"GB",
    "wof:name":"HR2 7EB",
    "wof:placetype":"postalcode"
},
  "geometry": {"coordinates":[-2.73428007736805,52.03651899090681],"type":"Point"}
}