{
  "type": "Feature",
  "properties": {
    "iso:country":"GB",
    "wof:name":"NN14 6EY",
    "wof:placetype":"postalcode"
},
  "geometry": {"coordinates":[-0.79716391890143,52.42389885599457],"type":"Point"}
}