{
  "type": "Feature",
  "properties": {
    "iso:country": "GB",
    "wof:name": "BL3 3FB",
    "wof:placetype": "postalcode"
  },
  "geometry": {"coordinates":[-2.432294,53.556951],"type":"Point"}
}
