{
  "type": "Feature",
  "properties": {
    "date:inception_lower":"1995-07-01",
    "date:inception_upper":"1995-07-31",
    "iso:country":"GB",
    "wof:name":"BL3 3FB",
    "wof:placetype":"postalcode"
},
  "geometry": {"coordinates":[-2.432294,53.556951],"type":"Point"}
}