{
  "type": "Feature",
  "properties": {
    "iso:country":"GB",
    "wof:name":"BL3 3FB",
    "wof:placetype":"postalcode"
},
  "geometry": {"coordinates":[-2.43229390105602,53.55695062972305],"type":"Point"}
}