{
  "type": "Feature",
  "properties": {
    "iso:country": "GB",
    "wof:name": "B37 5BD",
    "wof:placetype": "postalcode"
  },
  "geometry": {"coordinates":[-1.75878,52.479151],"type":"Point"}
}
