{
  "type": "Feature",
  "properties": {
    "iso:country":"GB",
    "wof:name":"B43 5AW",
    "wof:placetype":"postalcode"
},
  "geometry": {"coordinates":[-1.94890120637416,52.53676759506844],"type":"Point"}
}