{
  "type": "Feature",
  "properties": {
    "date:inception_lower": "1980-01-01",
    "date:inception_upper": "1980-01-01",
    "iso:country": "GB",
    "wof:name": "B43 5AW",
    "wof:placetype": "postalcode"
  },
  "geometry": {"coordinates":[-1.948901,52.536768],"type":"Point"}
}
