{
  "type": "Feature",
  "properties": {
    "date:inception_lower": "1980-01-01",
    "date:inception_upper": "1980-01-01",
    "iso:country": "GB",
    "wof:name": "SK5 7EQ",
    "wof:placetype": "postalcode"
  },
  "geometry": {"coordinates":[-2.153436,53.43176],"type":"Point"}
}
