{
  "type": "Feature",
  "properties": {
    "iso:country": "GB",
    "wof:name": "LL32 8RS",
    "wof:placetype": "postalcode"
  },
  "geometry": {"coordinates":[-3.837949,53.276173],"type":"Point"}
}
