{
  "type": "Feature",
  "properties": {
    "iso:country":"GB",
    "wof:name":"NG1 7AT",
    "wof:placetype":"postalcode"
},
  "geometry": {"coordinates":[-1.15119726286743,52.95120645579922],"type":"Point"}
}