{
  "type": "Feature",
  "properties": {
    "date:inception_lower": "1980-01-01",
    "date:inception_upper": "1980-01-01",
    "iso:country": "GB",
    "wof:name": "W9 1LW",
    "wof:placetype": "postalcode"
  },
  "geometry": {"coordinates":[-0.188782,51.529525],"type":"Point"}
}
