{
  "type": "Feature",
  "properties": {
    "iso:country":"GB",
    "wof:name":"W9 1LW",
    "wof:placetype":"postalcode"
},
  "geometry": {"coordinates":[-0.18878167327629,51.52952495971852],"type":"Point"}
}