{
  "type": "Feature",
  "properties": {
    "iso:country":"GB",
    "wof:name":"LE15 7TN",
    "wof:placetype":"postalcode"
},
  "geometry": {"coordinates":[-0.73949529912772,52.67787082455195],"type":"Point"}
}