{
  "type": "Feature",
  "properties": {
    "date:inception_lower": "2014-06-01",
    "date:inception_upper": "2014-06-01",
    "iso:country": "GB",
    "wof:name": "LE15 7TN",
    "wof:placetype": "postalcode"
  },
  "geometry": {"coordinates":[-0.739584,52.678035],"type":"Point"}
}
