{
  "type": "Feature",
  "properties": {
    "iso:country":"GB",
    "wof:name":"BS48 2XQ",
    "wof:placetype":"postalcode"
},
  "geometry": {"coordinates":[-2.77502809841377,51.43323887729666],"type":"Point"}
}