{
  "type": "Feature",
  "properties": {
    "date:inception_lower": "1997-12-01",
    "date:inception_upper": "1997-12-01",
    "iso:country": "GB",
    "wof:name": "BS48 2XQ",
    "wof:placetype": "postalcode"
  },
  "geometry": {"coordinates":[-2.775028,51.433239],"type":"Point"}
}
