{
  "type": "Feature",
  "properties": {
    "iso:country":"GB",
    "wof:name":"LS28 8JB",
    "wof:placetype":"postalcode"
},
  "geometry": {"coordinates":[-1.67465766163211,53.78880872105974],"type":"Point"}
}