{
  "type": "Feature",
  "properties": {
    "date:inception_lower": "1980-01-01",
    "date:inception_upper": "1980-01-01",
    "iso:country": "GB",
    "wof:name": "LL68 9RA",
    "wof:placetype": "postalcode"
  },
  "geometry": {"coordinates":[-4.367092,53.354842],"type":"Point"}
}
