{
  "type": "Feature",
  "properties": {
    "iso:country":"GB",
    "wof:name":"WS6 7LJ",
    "wof:placetype":"postalcode"
},
  "geometry": {"coordinates":[-2.03991790745515,52.65810673550929],"type":"Point"}
}