{
  "type": "Feature",
  "properties": {
    "iso:country": "GB",
    "wof:name": "WS6 7LJ",
    "wof:placetype": "postalcode"
  },
  "geometry": {"coordinates":[-2.039918,52.658107],"type":"Point"}
}
