{
  "type": "Feature",
  "properties": {
    "iso:country":"GB",
    "wof:name":"LU7 1AA",
    "wof:placetype":"postalcode"
},
  "geometry": {"coordinates":[-0.66424316717648,51.9152608046894],"type":"Point"}
}