{
  "type": "Feature",
  "properties": {
    "iso:country": "GB",
    "wof:name": "LU7 1AA",
    "wof:placetype": "postalcode"
  },
  "geometry": {"coordinates":[-0.664243,51.915261],"type":"Point"}
}
