{
  "type": "Feature",
  "properties": {
    "date:inception_lower":"2001-06-01",
    "date:inception_upper":"2001-06-30",
    "iso:country":"GB",
    "wof:name":"LU7 1AA",
    "wof:placetype":"postalcode"
},
  "geometry": {"coordinates":[-0.664243,51.915261],"type":"Point"}
}