{
  "type": "Feature",
  "properties": {
    "iso:country":"GB",
    "wof:name":"NW8 9NH",
    "wof:placetype":"postalcode"
},
  "geometry": {"coordinates":[-0.17546101217996,51.53347303933362],"type":"Point"}
}