{
  "type": "Feature",
  "properties": {
    "iso:country":"GB",
    "wof:name":"WN4 9SF",
    "wof:placetype":"postalcode"
},
  "geometry": {"coordinates":[-2.64235175838992,53.4923857011043],"type":"Point"}
}