{
  "type": "Feature",
  "properties": {
    "date:inception_lower":"1995-01-01",
    "date:inception_upper":"1995-01-31",
    "iso:country":"GB",
    "wof:name":"BH21 4BB",
    "wof:placetype":"postalcode"
},
  "geometry": {"coordinates":[-2.075375,50.795894],"type":"Point"}
}