{
  "type": "Feature",
  "properties": {
    "iso:country":"GB",
    "wof:name":"BH21 4BB",
    "wof:placetype":"postalcode"
},
  "geometry": {"coordinates":[-2.0753748208726,50.79589411895449],"type":"Point"}
}