{
  "type": "Feature",
  "properties": {
    "iso:country": "GB",
    "wof:name": "BH21 4BB",
    "wof:placetype": "postalcode"
  },
  "geometry": {"coordinates":[-2.075375,50.795894],"type":"Point"}
}
