{
  "type": "Feature",
  "properties": {
    "date:inception_lower":"1980-01-01",
    "date:inception_upper":"1980-01-31",
    "iso:country":"GB",
    "wof:name":"PL9 0EZ",
    "wof:placetype":"postalcode"
},
  "geometry": {"coordinates":[-4.074921,50.324948],"type":"Point"}
}