{
  "type": "Feature",
  "properties": {
    "iso:country": "GB",
    "wof:name": "PL9 0EZ",
    "wof:placetype": "postalcode"
  },
  "geometry": {"coordinates":[-4.074921,50.324948],"type":"Point"}
}
