{
  "type": "Feature",
  "properties": {
    "iso:country":"GB",
    "wof:name":"PL9 0EZ",
    "wof:placetype":"postalcode"
},
  "geometry": {"coordinates":[-4.07492054738565,50.32494759591588],"type":"Point"}
}