{
  "type": "Feature",
  "properties": {
    "iso:country":"GB",
    "wof:name":"DN4 6PP",
    "wof:placetype":"postalcode"
},
  "geometry": {"coordinates":[-1.08825360335128,53.51470057716357],"type":"Point"}
}