{
  "type": "Feature",
  "properties": {
    "iso:country":"GB",
    "wof:name":"CM7 1HN",
    "wof:placetype":"postalcode"
},
  "geometry": {"coordinates":[0.55003107981825,51.87587623701053],"type":"Point"}
}