{
  "type": "Feature",
  "properties": {
    "date:inception_lower":"1995-07-01",
    "date:inception_upper":"1995-07-31",
    "iso:country":"GB",
    "wof:name":"CM7 1HN",
    "wof:placetype":"postalcode"
},
  "geometry": {"coordinates":[0.550031,51.875876],"type":"Point"}
}