{
  "type": "Feature",
  "properties": {
    "iso:country": "GB",
    "wof:name": "HX2 0AG",
    "wof:placetype": "postalcode"
  },
  "geometry": {"coordinates":[-1.90035,53.723029],"type":"Point"}
}
