{
  "type": "Feature",
  "properties": {
    "iso:country":"GB",
    "wof:name":"TD7 5AW",
    "wof:placetype":"postalcode"
},
  "geometry": {"coordinates":[-2.84660014158618,55.54562184980726],"type":"Point"}
}