{
  "type": "Feature",
  "properties": {
    "iso:country":"GB",
    "wof:name":"SE1 3TP",
    "wof:placetype":"postalcode"
},
  "geometry": {"coordinates":[-0.08137370666212,51.49899614814323],"type":"Point"}
}