{
  "type": "Feature",
  "properties": {
    "iso:country":"GB",
    "wof:name":"DL9 4UU",
    "wof:placetype":"postalcode"
},
  "geometry": {"coordinates":[-1.68851178448959,54.38179100106317],"type":"Point"}
}