{
  "type": "Feature",
  "properties": {
    "date:inception_lower": "1995-07-01",
    "date:inception_upper": "1995-07-01",
    "iso:country": "GB",
    "wof:name": "DL9 4UU",
    "wof:placetype": "postalcode"
  },
  "geometry": {"coordinates":[-1.688512,54.381791],"type":"Point"}
}
