{
  "type": "Feature",
  "properties": {
    "date:inception_lower": "1980-01-01",
    "date:inception_upper": "1980-01-01",
    "iso:country": "GB",
    "wof:name": "HP16 9NG",
    "wof:placetype": "postalcode"
  },
  "geometry": {"coordinates":[-0.687899,51.736964],"type":"Point"}
}
