{
  "type": "Feature",
  "properties": {
    "iso:country":"GB",
    "wof:name":"PO19 8AQ",
    "wof:placetype":"postalcode"
},
  "geometry": {"coordinates":[-0.77792318204883,50.83173293343503],"type":"Point"}
}