{
  "type": "Feature",
  "properties": {
    "iso:country":"GB",
    "wof:name":"DH5 0RR",
    "wof:placetype":"postalcode"
},
  "geometry": {"coordinates":[-1.44828877014587,54.81866616721792],"type":"Point"}
}