{
  "type": "Feature",
  "properties": {
    "iso:country":"GB",
    "wof:name":"CV34 5DE",
    "wof:placetype":"postalcode"
},
  "geometry": {"coordinates":[-1.59079825076701,52.29437292533202],"type":"Point"}
}