{
  "type": "Feature",
  "properties": {
    "iso:country":"GB",
    "wof:name":"B11 1DQ",
    "wof:placetype":"postalcode"
},
  "geometry": {"coordinates":[-1.86143063799051,52.46160478836027],"type":"Point"}
}