{
  "type": "Feature",
  "properties": {
    "iso:country": "GB",
    "wof:name": "B11 1DQ",
    "wof:placetype": "postalcode"
  },
  "geometry": {"coordinates":[-1.861205,52.461556],"type":"Point"}
}
