{
  "type": "Feature",
  "properties": {
    "date:inception_lower":"1980-01-01",
    "date:inception_upper":"1980-01-31",
    "iso:country":"GB",
    "wof:name":"SM6 7JZ",
    "wof:placetype":"postalcode"
},
  "geometry": {"coordinates":[-0.152992,51.368485],"type":"Point"}
}