{
  "type": "Feature",
  "properties": {
    "iso:country":"GB",
    "wof:name":"SM6 7JZ",
    "wof:placetype":"postalcode"
},
  "geometry": {"coordinates":[-0.15299203993756,51.36848528921342],"type":"Point"}
}