{
  "type": "Feature",
  "properties": {
    "iso:country":"GB",
    "wof:name":"LU2 9PJ",
    "wof:placetype":"postalcode"
},
  "geometry": {"coordinates":[-0.36819398335085,51.86641730598348],"type":"Point"}
}