{
  "type": "Feature",
  "properties": {
    "date:inception_lower":"1980-01-01",
    "date:inception_upper":"1980-01-31",
    "iso:country":"GB",
    "wof:name":"LU2 9PJ",
    "wof:placetype":"postalcode"
},
  "geometry": {"coordinates":[-0.368194,51.866417],"type":"Point"}
}