{
  "type": "Feature",
  "properties": {
    "iso:country": "GB",
    "wof:name": "LU2 9PJ",
    "wof:placetype": "postalcode"
  },
  "geometry": {"coordinates":[-0.368194,51.866417],"type":"Point"}
}
