{
  "type": "Feature",
  "properties": {
    "iso:country":"GB",
    "wof:name":"G78 4BE",
    "wof:placetype":"postalcode"
},
  "geometry": {"coordinates":[-4.51322343707829,55.76148286529857],"type":"Point"}
}