{
  "type": "Feature",
  "properties": {
    "date:inception_lower":"2006-01-01",
    "date:inception_upper":"2006-01-31",
    "iso:country":"GB",
    "wof:name":"BH14 0JL",
    "wof:placetype":"postalcode"
},
  "geometry": {"coordinates":[-1.956879,50.725355],"type":"Point"}
}