{
  "type": "Feature",
  "properties": {
    "iso:country": "GB",
    "wof:name": "BN20 0BP",
    "wof:placetype": "postalcode"
  },
  "geometry": {"coordinates":[0.207283,50.760619],"type":"Point"}
}
