{
  "type": "Feature",
  "properties": {
    "iso:country":"GB",
    "wof:name":"NR9 5AE",
    "wof:placetype":"postalcode"
},
  "geometry": {"coordinates":[1.10383177484899,52.72238208591266],"type":"Point"}
}