{
  "type": "Feature",
  "properties": {
    "date:inception_lower":"1980-01-01",
    "date:inception_upper":"1980-01-31",
    "iso:country":"GB",
    "wof:name":"NR9 5AE",
    "wof:placetype":"postalcode"
},
  "geometry": {"coordinates":[1.103832,52.722382],"type":"Point"}
}