{
  "type": "Feature",
  "properties": {
    "iso:country":"GB",
    "wof:name":"EN5 2FG",
    "wof:placetype":"postalcode"
},
  "geometry": {"coordinates":[-0.20125204333469,51.64466586035759],"type":"Point"}
}