{
  "type": "Feature",
  "properties": {
    "date:inception_lower": "1990-08-01",
    "date:inception_upper": "1990-08-01",
    "iso:country": "GB",
    "wof:name": "AB23 8YG",
    "wof:placetype": "postalcode"
  },
  "geometry": {"coordinates":[-2.088775,57.24881],"type":"Point"}
}
