{
  "type": "Feature",
  "properties": {
    "iso:country": "GB",
    "wof:name": "AB23 8YG",
    "wof:placetype": "postalcode"
  },
  "geometry": {"coordinates":[-2.088775,57.24881],"type":"Point"}
}
