{
  "type": "Feature",
  "properties": {
    "iso:country": "GB",
    "wof:name": "NG20 0JD",
    "wof:placetype": "postalcode"
  },
  "geometry": {"coordinates":[-1.150173,53.196779],"type":"Point"}
}
