{
  "type": "Feature",
  "properties": {
    "iso:country":"GB",
    "wof:name":"PO7 7FJ",
    "wof:placetype":"postalcode"
},
  "geometry": {"coordinates":[-1.04669047292534,50.88798712874342],"type":"Point"}
}