{
  "type": "Feature",
  "properties": {
    "iso:country":"GB",
    "wof:name":"RG7 1SA",
    "wof:placetype":"postalcode"
},
  "geometry": {"coordinates":[-0.96708321496668,51.39375797874789],"type":"Point"}
}