{
  "type": "Feature",
  "properties": {
    "iso:country": "GB",
    "wof:name": "RG7 1SA",
    "wof:placetype": "postalcode"
  },
  "geometry": {"coordinates":[-0.967083,51.393758],"type":"Point"}
}
