{
  "type": "Feature",
  "properties": {
    "iso:country":"GB",
    "wof:name":"TQ1 3TH",
    "wof:placetype":"postalcode"
},
  "geometry": {"coordinates":[-3.50776639659969,50.47561894715681],"type":"Point"}
}