{
  "type": "Feature",
  "properties": {
    "date:inception_lower":"1986-07-01",
    "date:inception_upper":"1986-07-31",
    "iso:country":"GB",
    "wof:name":"HX1 5TW",
    "wof:placetype":"postalcode"
},
  "geometry": {"coordinates":[-1.864893,53.726329],"type":"Point"}
}