{
  "type": "Feature",
  "properties": {
    "iso:country":"GB",
    "wof:name":"SW1V 1JY",
    "wof:placetype":"postalcode"
},
  "geometry": {"coordinates":[-0.14435416499721,51.49497379814179],"type":"Point"}
}