{
  "type": "Feature",
  "properties": {
    "iso:country":"GB",
    "wof:name":"TS24 8DF",
    "wof:placetype":"postalcode"
},
  "geometry": {"coordinates":[-1.21377672256952,54.69038179496652],"type":"Point"}
}