{
  "type": "Feature",
  "properties": {
    "date:inception_lower":"2007-09-01",
    "date:inception_upper":"2007-09-30",
    "iso:country":"GB",
    "wof:name":"NG23 5FX",
    "wof:placetype":"postalcode"
},
  "geometry": {"coordinates":[-0.757281,52.993364],"type":"Point"}
}