{
  "type": "Feature",
  "properties": {
    "date:inception_lower": "2020-04-01",
    "date:inception_upper": "2020-04-01",
    "iso:country": "GB",
    "wof:name": "DE23 3BA",
    "wof:placetype": "postalcode"
  },
  "geometry": {"coordinates":[-1.529797,52.889185],"type":"Point"}
}
