{
  "type": "Feature",
  "properties": {
    "iso:country": "GB",
    "wof:name": "DE23 3BA",
    "wof:placetype": "postalcode"
  },
  "geometry": {"coordinates":[-1.52987,52.889338],"type":"Point"}
}
