{
  "type": "Feature",
  "properties": {
    "iso:country":"GB",
    "wof:name":"TN4 0HJ",
    "wof:placetype":"postalcode"
},
  "geometry": {"coordinates":[0.25887948469186,51.15687503740953],"type":"Point"}
}