{
  "type": "Feature",
  "properties": {
    "iso:country":"GB",
    "wof:name":"DE73 6QT",
    "wof:placetype":"postalcode"
},
  "geometry": {"coordinates":[-1.42801922485209,52.8713443238561],"type":"Point"}
}