{
  "type": "Feature",
  "properties": {
    "iso:country": "GB",
    "wof:name": "DE73 6QT",
    "wof:placetype": "postalcode"
  },
  "geometry": {"coordinates":[-1.428019,52.871344],"type":"Point"}
}
