{
  "type": "Feature",
  "properties": {
    "iso:country":"GB",
    "wof:name":"CM23 2UG",
    "wof:placetype":"postalcode"
},
  "geometry": {"coordinates":[0.16998837923486,51.87595693514545],"type":"Point"}
}