{
  "type": "Feature",
  "properties": {
    "iso:country": "GB",
    "wof:name": "PR25 3ZD",
    "wof:placetype": "postalcode"
  },
  "geometry": {"coordinates":[-2.70209,53.701328],"type":"Point"}
}
