{
  "type": "Feature",
  "properties": {
    "date:inception_lower":"2012-02-01",
    "date:inception_upper":"2012-02-29",
    "iso:country":"GB",
    "wof:name":"WN3 4AY",
    "wof:placetype":"postalcode"
},
  "geometry": {"coordinates":[-2.612734,53.52686],"type":"Point"}
}