{
  "type": "Feature",
  "properties": {
    "date:inception_lower": "2020-09-01",
    "date:inception_upper": "2020-09-01",
    "iso:country": "GB",
    "wof:name": "AL7 4FU",
    "wof:placetype": "postalcode"
  },
  "geometry": {"coordinates":[-0.18045,51.789828],"type":"Point"}
}
