{
  "type": "Feature",
  "properties": {
    "iso:country":"GB",
    "wof:name":"BH15 2HS",
    "wof:placetype":"postalcode"
},
  "geometry": {"coordinates":[-1.96886531151657,50.72457618886822],"type":"Point"}
}