{
  "type": "Feature",
  "properties": {
    "iso:country": "GB",
    "wof:name": "BH15 2HS",
    "wof:placetype": "postalcode"
  },
  "geometry": {"coordinates":[-1.968865,50.724576],"type":"Point"}
}
