{
  "type": "Feature",
  "properties": {
    "iso:country":"GB",
    "wof:name":"S73 0HN",
    "wof:placetype":"postalcode"
},
  "geometry": {"coordinates":[-1.39042033185566,53.51930999085039],"type":"Point"}
}