{
  "type": "Feature",
  "properties": {
    "date:inception_lower":"1984-10-01",
    "date:inception_upper":"1984-10-31",
    "iso:country":"GB",
    "wof:name":"TR13 8UX",
    "wof:placetype":"postalcode"
},
  "geometry": {"coordinates":[-5.275721,50.109473],"type":"Point"}
}