{
  "type": "Feature",
  "properties": {
    "iso:country":"GB",
    "wof:name":"TR13 8UX",
    "wof:placetype":"postalcode"
},
  "geometry": {"coordinates":[-5.27572081893598,50.10947289168151],"type":"Point"}
}