{
  "type": "Feature",
  "properties": {
    "iso:country":"GB",
    "wof:name":"NW9 8RL",
    "wof:placetype":"postalcode"
},
  "geometry": {"coordinates":[-0.26376424510009,51.56666395504924],"type":"Point"}
}