{
  "type": "Feature",
  "properties": {
    "iso:country":"GB",
    "wof:name":"W1F 8GB",
    "wof:placetype":"postalcode"
},
  "geometry": {"coordinates":[-0.13585968271309,51.51532404511037],"type":"Point"}
}