{
  "type": "Feature",
  "properties": {
    "iso:country":"GB",
    "wof:name":"ME1 2SW",
    "wof:placetype":"postalcode"
},
  "geometry": {"coordinates":[0.51200753786471,51.3637913492495],"type":"Point"}
}