{
  "type": "Feature",
  "properties": {
    "date:inception_lower":"1980-01-01",
    "date:inception_upper":"1980-01-31",
    "iso:country":"GB",
    "wof:name":"ME1 2SW",
    "wof:placetype":"postalcode"
},
  "geometry": {"coordinates":[0.512008,51.363791],"type":"Point"}
}