{
  "type": "Feature",
  "properties": {
    "iso:country":"GB",
    "wof:name":"NP26 3NW",
    "wof:placetype":"postalcode"
},
  "geometry": {"coordinates":[-2.82298573082858,51.58175085814791],"type":"Point"}
}