{
  "type": "Feature",
  "properties": {
    "iso:country":"GB",
    "wof:name":"RG8 7AR",
    "wof:placetype":"postalcode"
},
  "geometry": {"coordinates":[-1.08732732058893,51.48340612747069],"type":"Point"}
}