{
  "type": "Feature",
  "properties": {
    "iso:country":"GB",
    "wof:name":"PE12 6TR",
    "wof:placetype":"postalcode"
},
  "geometry": {"coordinates":[-0.03070305714043,52.79842968411679],"type":"Point"}
}