{
  "type": "Feature",
  "properties": {
    "iso:country": "GB",
    "wof:name": "SA44 6HS",
    "wof:placetype": "postalcode"
  },
  "geometry": {"coordinates":[-4.384181,52.146181],"type":"Point"}
}
