{
  "type": "Feature",
  "properties": {
    "iso:country":"GB",
    "wof:name":"SA44 6HS",
    "wof:placetype":"postalcode"
},
  "geometry": {"coordinates":[-4.38418132562433,52.1461805913284],"type":"Point"}
}