{
  "type": "Feature",
  "properties": {
    "iso:country":"GB",
    "wof:name":"E17 4DS",
    "wof:placetype":"postalcode"
},
  "geometry": {"coordinates":[0.00070250606251,51.59850387431492],"type":"Point"}
}