{
  "type": "Feature",
  "properties": {
    "iso:country":"GB",
    "wof:name":"NR21 8LN",
    "wof:placetype":"postalcode"
},
  "geometry": {"coordinates":[0.87401026266767,52.83037008516874],"type":"Point"}
}