{
  "type": "Feature",
  "properties": {
    "iso:country":"GB",
    "wof:name":"CF24 3YX",
    "wof:placetype":"postalcode"
},
  "geometry": {"coordinates":[-3.16929201782669,51.4933884196224],"type":"Point"}
}