{
  "type": "Feature",
  "properties": {
    "iso:country": "GB",
    "wof:name": "LS22 6SH",
    "wof:placetype": "postalcode"
  },
  "geometry": {"coordinates":[-1.397741,53.931672],"type":"Point"}
}
