{
  "type": "Feature",
  "properties": {
    "iso:country":"GB",
    "wof:name":"PO16 8ED",
    "wof:placetype":"postalcode"
},
  "geometry": {"coordinates":[-1.12558037650513,50.85150986797007],"type":"Point"}
}