{
  "type": "Feature",
  "properties": {
    "iso:country":"GB",
    "wof:name":"NE11 0AP",
    "wof:placetype":"postalcode"
},
  "geometry": {"coordinates":[-1.63984243428468,54.93613644930416],"type":"Point"}
}