{
  "type": "Feature",
  "properties": {
    "date:inception_lower":"1997-12-01",
    "date:inception_upper":"1997-12-31",
    "iso:country":"GB",
    "wof:name":"BS35 3JB",
    "wof:placetype":"postalcode"
},
  "geometry": {"coordinates":[-2.528711,51.599001],"type":"Point"}
}