{
  "type": "Feature",
  "properties": {
    "iso:country":"GB",
    "wof:name":"BS35 3JB",
    "wof:placetype":"postalcode"
},
  "geometry": {"coordinates":[-2.52871101665933,51.59900111361259],"type":"Point"}
}