{
  "type": "Feature",
  "properties": {
    "iso:country": "GB",
    "wof:name": "BS35 3JB",
    "wof:placetype": "postalcode"
  },
  "geometry": {"coordinates":[-2.528711,51.599001],"type":"Point"}
}
