{
  "type": "Feature",
  "properties": {
    "date:inception_lower": "2005-03-01",
    "date:inception_upper": "2005-03-01",
    "iso:country": "GB",
    "wof:name": "EX4 7BS",
    "wof:placetype": "postalcode"
  },
  "geometry": {"coordinates":[-3.506763,50.732089],"type":"Point"}
}
