{
  "type": "Feature",
  "properties": {
    "iso:country": "GB",
    "wof:name": "EX4 7BS",
    "wof:placetype": "postalcode"
  },
  "geometry": {"coordinates":[-3.506763,50.732089],"type":"Point"}
}
