{
  "type": "Feature",
  "properties": {
    "iso:country":"GB",
    "wof:name":"EX4 7BS",
    "wof:placetype":"postalcode"
},
  "geometry": {"coordinates":[-3.50676258912141,50.73208927010121],"type":"Point"}
}