{
  "type": "Feature",
  "properties": {
    "iso:country":"GB",
    "wof:name":"LE12 9LL",
    "wof:placetype":"postalcode"
},
  "geometry": {"coordinates":[-1.3014540746267,52.76781736573229],"type":"Point"}
}