{
  "type": "Feature",
  "properties": {
    "date:inception_lower": "1985-10-01",
    "date:inception_upper": "1985-10-01",
    "iso:country": "GB",
    "wof:name": "CM2 6HW",
    "wof:placetype": "postalcode"
  },
  "geometry": {"coordinates":[0.484599,51.732814],"type":"Point"}
}
