{
  "type": "Feature",
  "properties": {
    "iso:country":"GB",
    "wof:name":"PH2 9EE",
    "wof:placetype":"postalcode"
},
  "geometry": {"coordinates":[-3.44040907899224,56.3525763600919],"type":"Point"}
}