{
  "type": "Feature",
  "properties": {
    "iso:country":"GB",
    "wof:name":"KT4 8BF",
    "wof:placetype":"postalcode"
},
  "geometry": {"coordinates":[-0.23831688326086,51.3852576692382],"type":"Point"}
}