{
  "type": "Feature",
  "properties": {
    "iso:country":"GB",
    "wof:name":"SG17 5QQ",
    "wof:placetype":"postalcode"
},
  "geometry": {"coordinates":[-0.37956425809155,52.0646506186566],"type":"Point"}
}