{
  "type": "Feature",
  "properties": {
    "iso:country": "GB",
    "wof:name": "SN9 5JR",
    "wof:placetype": "postalcode"
  },
  "geometry": {"coordinates":[-1.774722,51.342487],"type":"Point"}
}
