{
  "type": "Feature",
  "properties": {
    "date:inception_lower": "2007-05-01",
    "date:inception_upper": "2007-05-01",
    "iso:country": "GB",
    "wof:name": "SN9 5JR",
    "wof:placetype": "postalcode"
  },
  "geometry": {"coordinates":[-1.774722,51.342487],"type":"Point"}
}
