{
  "type": "Feature",
  "properties": {
    "iso:country":"GB",
    "wof:name":"B77 2ER",
    "wof:placetype":"postalcode"
},
  "geometry": {"coordinates":[-1.66353759124844,52.62112930480746],"type":"Point"}
}