{
  "type": "Feature",
  "properties": {
    "iso:country":"GB",
    "wof:name":"TN26 2NF",
    "wof:placetype":"postalcode"
},
  "geometry": {"coordinates":[0.8023397135431,51.0527124922289],"type":"Point"}
}