{
  "type": "Feature",
  "properties": {
    "iso:country": "GB",
    "wof:name": "PE34 4FF",
    "wof:placetype": "postalcode"
  },
  "geometry": {"coordinates":[0.330718,52.757374],"type":"Point"}
}
