{
  "type": "Feature",
  "properties": {
    "date:inception_lower":"2009-12-01",
    "date:inception_upper":"2009-12-31",
    "iso:country":"GB",
    "wof:name":"CF11 8AW",
    "wof:placetype":"postalcode"
},
  "geometry": {"coordinates":[-3.200726,51.471796],"type":"Point"}
}