{
  "type": "Feature",
  "properties": {
    "iso:country":"GB",
    "wof:name":"CF11 8AW",
    "wof:placetype":"postalcode"
},
  "geometry": {"coordinates":[-3.20061331573181,51.47166209155335],"type":"Point"}
}