{
  "type": "Feature",
  "properties": {
    "iso:country":"GB",
    "wof:name":"IP32 6QF",
    "wof:placetype":"postalcode"
},
  "geometry": {"coordinates":[0.69357167010758,52.25549980185086],"type":"Point"}
}