{
  "type": "Feature",
  "properties": {
    "iso:country": "GB",
    "wof:name": "NP11 6NN",
    "wof:placetype": "postalcode"
  },
  "geometry": {"coordinates":[-3.0838,51.601409],"type":"Point"}
}
