{
  "type": "Feature",
  "properties": {
    "iso:country":"GB",
    "wof:name":"UB2 5XT",
    "wof:placetype":"postalcode"
},
  "geometry": {"coordinates":[-0.40838274194616,51.49594966665465],"type":"Point"}
}