{
  "type": "Feature",
  "properties": {
    "iso:country":"GB",
    "wof:name":"LE67 9SS",
    "wof:placetype":"postalcode"
},
  "geometry": {"coordinates":[-1.27262501343009,52.68245706852508],"type":"Point"}
}