{
  "type": "Feature",
  "properties": {
    "date:inception_lower": "1992-08-01",
    "date:inception_upper": "1992-08-01",
    "iso:country": "GB",
    "wof:name": "LE67 9SS",
    "wof:placetype": "postalcode"
  },
  "geometry": {"coordinates":[-1.272625,52.682457],"type":"Point"}
}
