{
  "type": "Feature",
  "properties": {
    "iso:country":"GB",
    "wof:name":"FY1 4BU",
    "wof:placetype":"postalcode"
},
  "geometry": {"coordinates":[-3.04729641177099,53.81203431441966],"type":"Point"}
}