{
  "type": "Feature",
  "properties": {
    "iso:country": "GB",
    "wof:name": "CF35 5PN",
    "wof:placetype": "postalcode"
  },
  "geometry": {"coordinates":[-3.499947,51.523356],"type":"Point"}
}
