{
  "type": "Feature",
  "properties": {
    "iso:country":"GB",
    "wof:name":"CV2 5AX",
    "wof:placetype":"postalcode"
},
  "geometry": {"coordinates":[-1.45652756984447,52.41456181030409],"type":"Point"}
}