{
  "type": "Feature",
  "properties": {
    "iso:country": "GB",
    "wof:name": "GU2 8LR",
    "wof:placetype": "postalcode"
  },
  "geometry": {"coordinates":[-0.614302,51.247959],"type":"Point"}
}
