{
  "type": "Feature",
  "properties": {
    "iso:country":"GB",
    "wof:name":"GU2 8LR",
    "wof:placetype":"postalcode"
},
  "geometry": {"coordinates":[-0.61430241865299,51.24795852513755],"type":"Point"}
}