{
  "type": "Feature",
  "properties": {
    "iso:country":"GB",
    "wof:name":"RG6 7LW",
    "wof:placetype":"postalcode"
},
  "geometry": {"coordinates":[-0.91247146491049,51.43347603360908],"type":"Point"}
}