{
  "type": "Feature",
  "properties": {
    "date:inception_lower": "1995-07-01",
    "date:inception_upper": "1995-07-01",
    "iso:country": "GB",
    "wof:name": "RG6 7LW",
    "wof:placetype": "postalcode"
  },
  "geometry": {"coordinates":[-0.912471,51.433476],"type":"Point"}
}
