{
  "type": "Feature",
  "properties": {
    "iso:country":"GB",
    "wof:name":"CR3 5BL",
    "wof:placetype":"postalcode"
},
  "geometry": {"coordinates":[-0.12100645030657,51.27345337069291],"type":"Point"}
}