{
  "type": "Feature",
  "properties": {
    "iso:country": "GB",
    "wof:name": "N10 2JN",
    "wof:placetype": "postalcode"
  },
  "geometry": {"coordinates":[-0.14115,51.593148],"type":"Point"}
}
