{
  "type": "Feature",
  "properties": {
    "iso:country": "GB",
    "wof:name": "KA12 9HQ",
    "wof:placetype": "postalcode"
  },
  "geometry": {"coordinates":[-4.660105,55.627254],"type":"Point"}
}
