{
  "type": "Feature",
  "properties": {
    "iso:country": "GB",
    "wof:name": "TS2 1HB",
    "wof:placetype": "postalcode"
  },
  "geometry": {"coordinates":[-1.250018,54.581645],"type":"Point"}
}
