{
  "type": "Feature",
  "properties": {
    "iso:country":"GB",
    "wof:name":"TS2 1HB",
    "wof:placetype":"postalcode"
},
  "geometry": {"coordinates":[-1.25001798133372,54.58164463650161],"type":"Point"}
}