{
  "type": "Feature",
  "properties": {
    "date:inception_lower":"2000-06-01",
    "date:inception_upper":"2000-06-30",
    "iso:country":"GB",
    "wof:name":"TS2 1HB",
    "wof:placetype":"postalcode"
},
  "geometry": {"coordinates":[-1.250018,54.581645],"type":"Point"}
}