{
  "type": "Feature",
  "properties": {
    "date:inception_lower": "1980-01-01",
    "date:inception_upper": "1980-01-01",
    "iso:country": "GB",
    "wof:name": "LS10 3HA",
    "wof:placetype": "postalcode"
  },
  "geometry": {"coordinates":[-1.531845,53.758935],"type":"Point"}
}
