{
  "type": "Feature",
  "properties": {
    "iso:country":"GB",
    "wof:name":"LS10 3HA",
    "wof:placetype":"postalcode"
},
  "geometry": {"coordinates":[-1.53190861911406,53.75966481556683],"type":"Point"}
}