{
  "type": "Feature",
  "properties": {
    "iso:country":"GB",
    "wof:name":"RG42 6PA",
    "wof:placetype":"postalcode"
},
  "geometry": {"coordinates":[-0.7134899542948,51.43024756655454],"type":"Point"}
}