{
  "type": "Feature",
  "properties": {
    "iso:country":"GB",
    "wof:name":"CO5 9JD",
    "wof:placetype":"postalcode"
},
  "geometry": {"coordinates":[0.70437493809905,51.83973755630578],"type":"Point"}
}