{
  "type": "Feature",
  "properties": {
    "iso:country": "GB",
    "wof:name": "EX12 4AW",
    "wof:placetype": "postalcode"
  },
  "geometry": {"coordinates":[-3.050164,50.714099],"type":"Point"}
}
