{
  "type": "Feature",
  "properties": {
    "date:inception_lower":"1980-01-01",
    "date:inception_upper":"1980-01-31",
    "iso:country":"GB",
    "wof:name":"EX12 4AW",
    "wof:placetype":"postalcode"
},
  "geometry": {"coordinates":[-3.050164,50.714099],"type":"Point"}
}