{
  "type": "Feature",
  "properties": {
    "iso:country":"GB",
    "wof:name":"EN5 1RX",
    "wof:placetype":"postalcode"
},
  "geometry": {"coordinates":[-0.18067540680246,51.64561675288108],"type":"Point"}
}