{
  "type": "Feature",
  "properties": {
    "iso:country":"GB",
    "wof:name":"L31 2LS",
    "wof:placetype":"postalcode"
},
  "geometry": {"coordinates":[-2.94609060861888,53.523112752419],"type":"Point"}
}