{
  "type": "Feature",
  "properties": {
    "iso:country":"GB",
    "wof:name":"SN8 3TQ",
    "wof:placetype":"postalcode"
},
  "geometry": {"coordinates":[-1.67005379495404,51.35357775920001],"type":"Point"}
}