{
  "type": "Feature",
  "properties": {
    "iso:country":"GB",
    "wof:name":"AB10 7JR",
    "wof:placetype":"postalcode"
},
  "geometry": {"coordinates":[-2.12163247248415,57.1269380613959],"type":"Point"}
}