{
  "type": "Feature",
  "properties": {
    "date:inception_lower": "1997-06-01",
    "date:inception_upper": "1997-06-01",
    "iso:country": "GB",
    "wof:name": "S21 2DR",
    "wof:placetype": "postalcode"
  },
  "geometry": {"coordinates":[-1.302659,53.327904],"type":"Point"}
}
