{
  "type": "Feature",
  "properties": {
    "iso:country":"GB",
    "wof:name":"LS10 4QE",
    "wof:placetype":"postalcode"
},
  "geometry": {"coordinates":[-1.52648090907072,53.74865104896692],"type":"Point"}
}