{
  "type": "Feature",
  "properties": {
    "iso:country": "GB",
    "wof:name": "SG12 8AW",
    "wof:placetype": "postalcode"
  },
  "geometry": {"coordinates":[0.000492,51.784039],"type":"Point"}
}
