{
  "type": "Feature",
  "properties": {
    "date:inception_lower":"2010-10-01",
    "date:inception_upper":"2010-10-31",
    "iso:country":"GB",
    "wof:name":"SG12 8AW",
    "wof:placetype":"postalcode"
},
  "geometry": {"coordinates":[0.000492,51.784039],"type":"Point"}
}