{
  "type": "Feature",
  "properties": {
    "iso:country":"GB",
    "wof:name":"SG12 8AW",
    "wof:placetype":"postalcode"
},
  "geometry": {"coordinates":[0.00049202891375,51.78403933886034],"type":"Point"}
}