{
  "type": "Feature",
  "properties": {
    "iso:country": "GB",
    "wof:name": "KY1 2EY",
    "wof:placetype": "postalcode"
  },
  "geometry": {"coordinates":[-3.147624,56.124084],"type":"Point"}
}
