{
  "type": "Feature",
  "properties": {
    "iso:country":"GB",
    "wof:name":"KY1 2EY",
    "wof:placetype":"postalcode"
},
  "geometry": {"coordinates":[-3.14829173224702,56.12386809925737],"type":"Point"}
}