{
  "type": "Feature",
  "properties": {
    "date:inception_lower": "1980-01-01",
    "date:inception_upper": "1980-01-01",
    "iso:country": "GB",
    "wof:name": "KY1 2EY",
    "wof:placetype": "postalcode"
  },
  "geometry": {"coordinates":[-3.147624,56.124084],"type":"Point"}
}
