{
  "type": "Feature",
  "properties": {
    "iso:country": "GB",
    "wof:name": "B72 1RT",
    "wof:placetype": "postalcode"
  },
  "geometry": {"coordinates":[-1.822415,52.560019],"type":"Point"}
}
