{
  "type": "Feature",
  "properties": {
    "iso:country":"GB",
    "wof:name":"B72 1RT",
    "wof:placetype":"postalcode"
},
  "geometry": {"coordinates":[-1.82241526863679,52.55995642479461],"type":"Point"}
}