{
  "type": "Feature",
  "properties": {
    "date:inception_lower": "1980-01-01",
    "date:inception_upper": "1980-01-01",
    "iso:country": "GB",
    "wof:name": "PH22 1RH",
    "wof:placetype": "postalcode"
  },
  "geometry": {"coordinates":[-3.82933,57.191184],"type":"Point"}
}
