{
  "type": "Feature",
  "properties": {
    "iso:country":"GB",
    "wof:name":"WF3 2AG",
    "wof:placetype":"postalcode"
},
  "geometry": {"coordinates":[-1.5383311623009,53.72170587503561],"type":"Point"}
}