{
  "type": "Feature",
  "properties": {
    "iso:country":"GB",
    "wof:name":"SA39 9EE",
    "wof:placetype":"postalcode"
},
  "geometry": {"coordinates":[-4.19502859621748,52.02578061358744],"type":"Point"}
}