{
  "type": "Feature",
  "properties": {
    "iso:country":"GB",
    "wof:name":"FK4 2BX",
    "wof:placetype":"postalcode"
},
  "geometry": {"coordinates":[-3.89472372224271,55.99533137100697],"type":"Point"}
}