{
  "type": "Feature",
  "properties": {
    "date:inception_lower": "1980-01-01",
    "date:inception_upper": "1980-01-01",
    "iso:country": "GB",
    "wof:name": "SG9 0RR",
    "wof:placetype": "postalcode"
  },
  "geometry": {"coordinates":[-0.05988,51.97536],"type":"Point"}
}
