{
  "type": "Feature",
  "properties": {
    "iso:country":"GB",
    "wof:name":"SG9 0RR",
    "wof:placetype":"postalcode"
},
  "geometry": {"coordinates":[-0.0598805362925,51.97536008198279],"type":"Point"}
}