{
  "type": "Feature",
  "properties": {
    "iso:country":"GB",
    "wof:name":"BR6 9RR",
    "wof:placetype":"postalcode"
},
  "geometry": {"coordinates":[0.08311122967007,51.3694528478375],"type":"Point"}
}