{
  "type": "Feature",
  "properties": {
    "iso:country": "GB",
    "wof:name": "AL7 4QG",
    "wof:placetype": "postalcode"
  },
  "geometry": {"coordinates":[-0.185401,51.786318],"type":"Point"}
}
