{
  "type": "Feature",
  "properties": {
    "iso:country":"GB",
    "wof:name":"AL7 4QG",
    "wof:placetype":"postalcode"
},
  "geometry": {"coordinates":[-0.18540101549892,51.78631849139971],"type":"Point"}
}