{
  "type": "Feature",
  "properties": {
    "iso:country":"GB",
    "wof:name":"LN9 5AX",
    "wof:placetype":"postalcode"
},
  "geometry": {"coordinates":[-0.1197995197284,53.212583263583],"type":"Point"}
}