{
  "type": "Feature",
  "properties": {
    "date:inception_lower":"1983-03-01",
    "date:inception_upper":"1983-03-31",
    "iso:country":"GB",
    "wof:name":"NN10 0PT",
    "wof:placetype":"postalcode"
},
  "geometry": {"coordinates":[-0.596098,52.289059],"type":"Point"}
}