{
  "type": "Feature",
  "properties": {
    "iso:country":"GB",
    "wof:name":"NN10 0PT",
    "wof:placetype":"postalcode"
},
  "geometry": {"coordinates":[-0.59609809008484,52.28905904642821],"type":"Point"}
}