{
  "type": "Feature",
  "properties": {
    "iso:country": "GB",
    "wof:name": "NN10 0PT",
    "wof:placetype": "postalcode"
  },
  "geometry": {"coordinates":[-0.596098,52.289059],"type":"Point"}
}
