{
  "type": "Feature",
  "properties": {
    "iso:country":"GB",
    "wof:name":"SN5 7YE",
    "wof:placetype":"postalcode"
},
  "geometry": {"coordinates":[-1.81309664436256,51.55457524160492],"type":"Point"}
}