{
  "type": "Feature",
  "properties": {
    "iso:country":"GB",
    "wof:name":"BD5 7UQ",
    "wof:placetype":"postalcode"
},
  "geometry": {"coordinates":[-1.75296063291627,53.781562342959],"type":"Point"}
}