{
  "type": "Feature",
  "properties": {
    "iso:country": "GB",
    "wof:name": "BD5 7UQ",
    "wof:placetype": "postalcode"
  },
  "geometry": {"coordinates":[-1.752964,53.781577],"type":"Point"}
}
