{
  "type": "Feature",
  "properties": {
    "iso:country": "GB",
    "wof:name": "BD5 7UQ",
    "wof:placetype": "postalcode"
  },
  "geometry": {"coordinates":[-1.752554,53.781612],"type":"Point"}
}
