{
  "type": "Feature",
  "properties": {
    "iso:country":"GB",
    "wof:name":"LE13 0HN",
    "wof:placetype":"postalcode"
},
  "geometry": {"coordinates":[-0.89577264833806,52.76673162433795],"type":"Point"}
}