{
  "type": "Feature",
  "properties": {
    "iso:country":"GB",
    "wof:name":"GU1 4ST",
    "wof:placetype":"postalcode"
},
  "geometry": {"coordinates":[-0.57895173278062,51.23875809510918],"type":"Point"}
}