{
  "type": "Feature",
  "properties": {
    "iso:country":"GB",
    "wof:name":"LS6 2RF",
    "wof:placetype":"postalcode"
},
  "geometry": {"coordinates":[-1.55566732708105,53.81376438997659],"type":"Point"}
}