{
  "type": "Feature",
  "properties": {
    "date:inception_lower":"1980-01-01",
    "date:inception_upper":"1980-01-31",
    "iso:country":"GB",
    "wof:name":"HD3 4GF",
    "wof:placetype":"postalcode"
},
  "geometry": {"coordinates":[-1.830108,53.655252],"type":"Point"}
}