{
  "type": "Feature",
  "properties": {
    "iso:country":"GB",
    "wof:name":"HD3 4GF",
    "wof:placetype":"postalcode"
},
  "geometry": {"coordinates":[-1.83010779770063,53.65525188787035],"type":"Point"}
}