{
  "type": "Feature",
  "properties": {
    "date:inception_lower":"2010-08-01",
    "date:inception_upper":"2010-08-31",
    "iso:country":"GB",
    "wof:name":"EN3 7FP",
    "wof:placetype":"postalcode"
},
  "geometry": {"coordinates":[-0.023818,51.672568],"type":"Point"}
}