{
  "type": "Feature",
  "properties": {
    "iso:country":"GB",
    "wof:name":"EN3 7FP",
    "wof:placetype":"postalcode"
},
  "geometry": {"coordinates":[-0.0238183716642,51.67256771287178],"type":"Point"}
}