{
  "type": "Feature",
  "properties": {
    "iso:country":"GB",
    "wof:name":"CA16 6UQ",
    "wof:placetype":"postalcode"
},
  "geometry": {"coordinates":[-2.48298703282625,54.57578540719294],"type":"Point"}
}