{
  "type": "Feature",
  "properties": {
    "iso:country":"GB",
    "wof:name":"EH17 8EY",
    "wof:placetype":"postalcode"
},
  "geometry": {"coordinates":[-3.15654780270803,55.89752204643614],"type":"Point"}
}