{
  "type": "Feature",
  "properties": {
    "iso:country":"GB",
    "wof:name":"L32 2BZ",
    "wof:placetype":"postalcode"
},
  "geometry": {"coordinates":[-2.9079531821671,53.48759744637855],"type":"Point"}
}