{
  "type": "Feature",
  "properties": {
    "iso:country": "GB",
    "wof:name": "L32 2BZ",
    "wof:placetype": "postalcode"
  },
  "geometry": {"coordinates":[-2.907953,53.487597],"type":"Point"}
}
