{
  "type": "Feature",
  "properties": {
    "iso:country": "GB",
    "wof:name": "LL54 6LF",
    "wof:placetype": "postalcode"
  },
  "geometry": {"coordinates":[-4.249571,53.060465],"type":"Point"}
}
