{
  "type": "Feature",
  "properties": {
    "date:inception_lower":"1980-01-01",
    "date:inception_upper":"1980-01-31",
    "iso:country":"GB",
    "wof:name":"LL54 6LF",
    "wof:placetype":"postalcode"
},
  "geometry": {"coordinates":[-4.249571,53.060465],"type":"Point"}
}