{
  "type": "Feature",
  "properties": {
    "iso:country":"GB",
    "wof:name":"LL54 6LF",
    "wof:placetype":"postalcode"
},
  "geometry": {"coordinates":[-4.24957082478627,53.06046494730645],"type":"Point"}
}