{
  "type": "Feature",
  "properties": {
    "iso:country":"GB",
    "wof:name":"B74 2AG",
    "wof:placetype":"postalcode"
},
  "geometry": {"coordinates":[-1.88725237621519,52.5629664576489],"type":"Point"}
}