{
  "type": "Feature",
  "properties": {
    "iso:country": "GB",
    "wof:name": "TW13 7NW",
    "wof:placetype": "postalcode"
  },
  "geometry": {"coordinates":[-0.398938,51.432857],"type":"Point"}
}
