{
  "type": "Feature",
  "properties": {
    "iso:country":"GB",
    "wof:name":"TW13 7NW",
    "wof:placetype":"postalcode"
},
  "geometry": {"coordinates":[-0.39893775697092,51.43285702281801],"type":"Point"}
}