{
  "type": "Feature",
  "properties": {
    "iso:country":"GB",
    "wof:name":"TS2 1JR",
    "wof:placetype":"postalcode"
},
  "geometry": {"coordinates":[-1.23615731523458,54.58482926666979],"type":"Point"}
}