{
  "type": "Feature",
  "properties": {
    "date:inception_lower": "2000-12-01",
    "date:inception_upper": "2000-12-01",
    "iso:country": "GB",
    "wof:name": "SS4 1GB",
    "wof:placetype": "postalcode"
  },
  "geometry": {"coordinates":[0.704483,51.585364],"type":"Point"}
}
