{
  "type": "Feature",
  "properties": {
    "iso:country":"GB",
    "wof:name":"SS4 1GB",
    "wof:placetype":"postalcode"
},
  "geometry": {"coordinates":[0.70448253514071,51.58536414681718],"type":"Point"}
}