{
  "type": "Feature",
  "properties": {
    "iso:country":"GB",
    "wof:name":"TS23 2RJ",
    "wof:placetype":"postalcode"
},
  "geometry": {"coordinates":[-1.29786114373329,54.60394065458534],"type":"Point"}
}