{
  "type": "Feature",
  "properties": {
    "iso:country": "GB",
    "wof:name": "TS23 2RJ",
    "wof:placetype": "postalcode"
  },
  "geometry": {"coordinates":[-1.297861,54.603941],"type":"Point"}
}
