{
  "type": "Feature",
  "properties": {
    "date:inception_lower":"1980-01-01",
    "date:inception_upper":"1980-01-31",
    "iso:country":"GB",
    "wof:name":"GL51 7AD",
    "wof:placetype":"postalcode"
},
  "geometry": {"coordinates":[-2.103787,51.895864],"type":"Point"}
}