{
  "type": "Feature",
  "properties": {
    "iso:country":"GB",
    "wof:name":"GL51 7AD",
    "wof:placetype":"postalcode"
},
  "geometry": {"coordinates":[-2.1037873648879,51.89586355563616],"type":"Point"}
}