{
  "type": "Feature",
  "properties": {
    "iso:country": "GB",
    "wof:name": "PR3 2DL",
    "wof:placetype": "postalcode"
  },
  "geometry": {"coordinates":[-2.614964,53.834288],"type":"Point"}
}
