{
  "type": "Feature",
  "properties": {
    "iso:country": "GB",
    "wof:name": "TA11 6RB",
    "wof:placetype": "postalcode"
  },
  "geometry": {"coordinates":[-2.739046,51.052931],"type":"Point"}
}
