{
  "type": "Feature",
  "properties": {
    "iso:country":"GB",
    "wof:name":"KA5 6AL",
    "wof:placetype":"postalcode"
},
  "geometry": {"coordinates":[-4.37708888911598,55.51678878967454],"type":"Point"}
}