{
  "type": "Feature",
  "properties": {
    "iso:country":"GB",
    "wof:name":"EN4 9AB",
    "wof:placetype":"postalcode"
},
  "geometry": {"coordinates":[-0.16207231296256,51.65207125693246],"type":"Point"}
}