{
  "type": "Feature",
  "properties": {
    "date:inception_lower": "1980-01-01",
    "date:inception_upper": "1980-01-01",
    "iso:country": "GB",
    "wof:name": "EN4 9AB",
    "wof:placetype": "postalcode"
  },
  "geometry": {"coordinates":[-0.16199,51.652037],"type":"Point"}
}
