{
  "type": "Feature",
  "properties": {
    "date:inception_lower": "1980-01-01",
    "date:inception_upper": "1980-01-01",
    "iso:country": "GB",
    "wof:name": "TQ12 6NT",
    "wof:placetype": "postalcode"
  },
  "geometry": {"coordinates":[-3.676884,50.536378],"type":"Point"}
}
