{
  "type": "Feature",
  "properties": {
    "iso:country":"GB",
    "wof:name":"DN35 0AZ",
    "wof:placetype":"postalcode"
},
  "geometry": {"coordinates":[-0.02062186481346,53.55235908677597],"type":"Point"}
}