{
  "type": "Feature",
  "properties": {
    "iso:country":"GB",
    "wof:name":"B15 2AS",
    "wof:placetype":"postalcode"
},
  "geometry": {"coordinates":[-1.90438772927217,52.47057426427697],"type":"Point"}
}