{
  "type": "Feature",
  "properties": {
    "date:inception_lower":"2005-07-01",
    "date:inception_upper":"2005-07-31",
    "iso:country":"GB",
    "wof:name":"CF33 4PQ",
    "wof:placetype":"postalcode"
},
  "geometry": {"coordinates":[-3.708359,51.524963],"type":"Point"}
}