{
  "type": "Feature",
  "properties": {
    "iso:country":"GB",
    "wof:name":"NR1 4PD",
    "wof:placetype":"postalcode"
},
  "geometry": {"coordinates":[1.32268330041364,52.63188796086501],"type":"Point"}
}