{
  "type": "Feature",
  "properties": {
    "iso:country":"GB",
    "wof:name":"B7 4EH",
    "wof:placetype":"postalcode"
},
  "geometry": {"coordinates":[-1.88472550388344,52.48560598578074],"type":"Point"}
}