{
  "type": "Feature",
  "properties": {
    "iso:country":"GB",
    "wof:name":"LL48 6RR",
    "wof:placetype":"postalcode"
},
  "geometry": {"coordinates":[-4.07125100491025,52.93148590015278],"type":"Point"}
}