{
  "type": "Feature",
  "properties": {
    "iso:country":"GB",
    "wof:name":"CH62 6BU",
    "wof:placetype":"postalcode"
},
  "geometry": {"coordinates":[-2.98370969238609,53.31519219205197],"type":"Point"}
}