{
  "type": "Feature",
  "properties": {
    "iso:country":"GB",
    "wof:name":"W1T 3QG",
    "wof:placetype":"postalcode"
},
  "geometry": {"coordinates":[-0.13779431089952,51.51700939799404],"type":"Point"}
}