{
  "type": "Feature",
  "properties": {
    "iso:country":"GB",
    "wof:name":"NG4 2NB",
    "wof:placetype":"postalcode"
},
  "geometry": {"coordinates":[-1.07064784111906,52.96841237466639],"type":"Point"}
}