{
  "type": "Feature",
  "properties": {
    "iso:country": "GB",
    "wof:name": "OL16 2BH",
    "wof:placetype": "postalcode"
  },
  "geometry": {"coordinates":[-2.1403,53.615256],"type":"Point"}
}
