{
  "type": "Feature",
  "properties": {
    "iso:country":"GB",
    "wof:name":"S44 6JE",
    "wof:placetype":"postalcode"
},
  "geometry": {"coordinates":[-1.30474659225901,53.22516096075205],"type":"Point"}
}