{
  "type": "Feature",
  "properties": {
    "iso:country":"GB",
    "wof:name":"BA3 3ET",
    "wof:placetype":"postalcode"
},
  "geometry": {"coordinates":[-2.43902355894381,51.29444769462792],"type":"Point"}
}