{
  "type": "Feature",
  "properties": {
    "iso:country": "GB",
    "wof:name": "BD14 6HG",
    "wof:placetype": "postalcode"
  },
  "geometry": {"coordinates":[-1.808297,53.783803],"type":"Point"}
}
