{
  "type": "Feature",
  "properties": {
    "iso:country": "GB",
    "wof:name": "CH41 0BA",
    "wof:placetype": "postalcode"
  },
  "geometry": {"coordinates":[-3.054263,53.398736],"type":"Point"}
}
