{
  "type": "Feature",
  "properties": {
    "iso:country":"GB",
    "wof:name":"SO16 5AN",
    "wof:placetype":"postalcode"
},
  "geometry": {"coordinates":[-1.43605314999195,50.93455264159],"type":"Point"}
}