{
  "type": "Feature",
  "properties": {
    "iso:country": "GB",
    "wof:name": "SO16 5AN",
    "wof:placetype": "postalcode"
  },
  "geometry": {"coordinates":[-1.436053,50.934553],"type":"Point"}
}
