{
  "type": "Feature",
  "properties": {
    "iso:country":"GB",
    "wof:name":"CH7 5TQ",
    "wof:placetype":"postalcode"
},
  "geometry": {"coordinates":[-3.21279680790688,53.11300533353369],"type":"Point"}
}