{
  "type": "Feature",
  "properties": {
    "iso:country":"GB",
    "wof:name":"PA3 3JX",
    "wof:placetype":"postalcode"
},
  "geometry": {"coordinates":[-4.50537441190186,55.84805507209219],"type":"Point"}
}