{
  "type": "Feature",
  "properties": {
    "iso:country":"GB",
    "wof:name":"AL4 0AN",
    "wof:placetype":"postalcode"
},
  "geometry": {"coordinates":[-0.28945843510981,51.73341407007398],"type":"Point"}
}