{
  "type": "Feature",
  "properties": {
    "iso:country": "GB",
    "wof:name": "NP11 5HR",
    "wof:placetype": "postalcode"
  },
  "geometry": {"coordinates":[-3.132925,51.682707],"type":"Point"}
}
