{
  "type": "Feature",
  "properties": {
    "iso:country":"GB",
    "wof:name":"OL16 5BD",
    "wof:placetype":"postalcode"
},
  "geometry": {"coordinates":[-2.13609420053804,53.6140475064938],"type":"Point"}
}