{
  "type": "Feature",
  "properties": {
    "iso:country":"GB",
    "wof:name":"BS2 9XZ",
    "wof:placetype":"postalcode"
},
  "geometry": {"coordinates":[-2.57725516897558,51.47065226402719],"type":"Point"}
}