{
  "type": "Feature",
  "properties": {
    "iso:country":"GB",
    "wof:name":"NG7 1HA",
    "wof:placetype":"postalcode"
},
  "geometry": {"coordinates":[-1.16919057406317,52.946623057451],"type":"Point"}
}