{
  "type": "Feature",
  "properties": {
    "iso:country":"GB",
    "wof:name":"M18 8UB",
    "wof:placetype":"postalcode"
},
  "geometry": {"coordinates":[-2.16983920677556,53.46137296497108],"type":"Point"}
}