{
  "type": "Feature",
  "properties": {
    "iso:country": "GB",
    "wof:name": "S60 5JY",
    "wof:placetype": "postalcode"
  },
  "geometry": {"coordinates":[-1.357951,53.399268],"type":"Point"}
}
