{
  "type": "Feature",
  "properties": {
    "date:inception_lower": "2023-03-01",
    "date:inception_upper": "2023-03-01",
    "iso:country": "GB",
    "wof:name": "SW18 1FJ",
    "wof:placetype": "postalcode"
  },
  "geometry": {"coordinates":[-0.196826,51.462107],"type":"Point"}
}
