{
  "type": "Feature",
  "properties": {
    "iso:country": "GB",
    "wof:name": "NN1 3JU",
    "wof:placetype": "postalcode"
  },
  "geometry": {"coordinates":[-0.889389,52.240976],"type":"Point"}
}
