{
  "type": "Feature",
  "properties": {
    "date:inception_lower": "2021-11-01",
    "date:inception_upper": "2021-11-01",
    "iso:country": "GB",
    "wof:name": "BS49 4GF",
    "wof:placetype": "postalcode"
  },
  "geometry": {"coordinates":[-2.79471,51.392525],"type":"Point"}
}
