{
  "type": "Feature",
  "properties": {
    "date:inception_lower":"1980-01-01",
    "date:inception_upper":"1980-01-31",
    "iso:country":"GB",
    "wof:name":"SY23 3AT",
    "wof:placetype":"postalcode"
},
  "geometry": {"coordinates":[-4.05394,52.411835],"type":"Point"}
}