{
  "type": "Feature",
  "properties": {
    "iso:country":"GB",
    "wof:name":"SY23 3AT",
    "wof:placetype":"postalcode"
},
  "geometry": {"coordinates":[-4.05394035420328,52.41183496758832],"type":"Point"}
}