{
  "type": "Feature",
  "properties": {
    "iso:country":"GB",
    "wof:name":"ME2 4DF",
    "wof:placetype":"postalcode"
},
  "geometry": {"coordinates":[0.49669235055688,51.39757478659421],"type":"Point"}
}