{
  "type": "Feature",
  "properties": {
    "iso:country":"GB",
    "wof:name":"SW8 2LE",
    "wof:placetype":"postalcode"
},
  "geometry": {"coordinates":[-0.12615179826571,51.48566482532573],"type":"Point"}
}