{
  "type": "Feature",
  "properties": {
    "date:inception_lower": "1996-12-01",
    "date:inception_upper": "1996-12-01",
    "iso:country": "GB",
    "wof:name": "SK23 7TB",
    "wof:placetype": "postalcode"
  },
  "geometry": {"coordinates":[-1.966699,53.332915],"type":"Point"}
}
