{
  "type": "Feature",
  "properties": {
    "iso:country": "GB",
    "wof:name": "SK23 7TB",
    "wof:placetype": "postalcode"
  },
  "geometry": {"coordinates":[-1.966774,53.332906],"type":"Point"}
}
