{
  "type": "Feature",
  "properties": {
    "iso:country":"GB",
    "wof:name":"SK23 7TB",
    "wof:placetype":"postalcode"
},
  "geometry": {"coordinates":[-1.96677491342035,53.33289014146516],"type":"Point"}
}