{
  "type": "Feature",
  "properties": {
    "iso:country":"GB",
    "wof:name":"B66 2NN",
    "wof:placetype":"postalcode"
},
  "geometry": {"coordinates":[-1.95639930620776,52.49806006261443],"type":"Point"}
}