{
  "type": "Feature",
  "properties": {
    "iso:country":"GB",
    "wof:name":"SE18 5LZ",
    "wof:placetype":"postalcode"
},
  "geometry": {"coordinates":[0.05799704194416,51.49269421624675],"type":"Point"}
}