{
  "type": "Feature",
  "properties": {
    "iso:country":"GB",
    "wof:name":"HU9 2BD",
    "wof:placetype":"postalcode"
},
  "geometry": {"coordinates":[-0.31090250378546,53.75072022878594],"type":"Point"}
}