{
  "type": "Feature",
  "properties": {
    "iso:country":"GB",
    "wof:name":"CA15 8PB",
    "wof:placetype":"postalcode"
},
  "geometry": {"coordinates":[-3.51515150287887,54.69542666773111],"type":"Point"}
}