{
  "type": "Feature",
  "properties": {
    "iso:country": "GB",
    "wof:name": "CW1 4GG",
    "wof:placetype": "postalcode"
  },
  "geometry": {"coordinates":[-2.437802,53.114162],"type":"Point"}
}
