{
  "type": "Feature",
  "properties": {
    "iso:country":"GB",
    "wof:name":"E12 5FD",
    "wof:placetype":"postalcode"
},
  "geometry": {"coordinates":[0.04537030946909,51.5501178336042],"type":"Point"}
}