{
  "type": "Feature",
  "properties": {
    "date:inception_lower": "2013-11-01",
    "date:inception_upper": "2013-11-01",
    "iso:country": "GB",
    "wof:name": "E12 5FD",
    "wof:placetype": "postalcode"
  },
  "geometry": {"coordinates":[0.045407,51.55002],"type":"Point"}
}
