{
  "type": "Feature",
  "properties": {
    "date:inception_lower": "1980-01-01",
    "date:inception_upper": "1980-01-01",
    "iso:country": "GB",
    "wof:name": "RH13 5AN",
    "wof:placetype": "postalcode"
  },
  "geometry": {"coordinates":[-0.326826,51.05797],"type":"Point"}
}
