{
  "type": "Feature",
  "properties": {
    "iso:country":"GB",
    "wof:name":"BS9 4QE",
    "wof:placetype":"postalcode"
},
  "geometry": {"coordinates":[-2.604510895856,51.48931631735469],"type":"Point"}
}