{
  "type": "Feature",
  "properties": {
    "iso:country": "GB",
    "wof:name": "L28 3QG",
    "wof:placetype": "postalcode"
  },
  "geometry": {"coordinates":[-2.862135,53.431809],"type":"Point"}
}
