{
  "type": "Feature",
  "properties": {
    "date:inception_lower": "1980-01-01",
    "date:inception_upper": "1980-01-01",
    "iso:country": "GB",
    "wof:name": "DD8 4LS",
    "wof:placetype": "postalcode"
  },
  "geometry": {"coordinates":[-2.994646,56.702965],"type":"Point"}
}
