{
  "type": "Feature",
  "properties": {
    "iso:country":"GB",
    "wof:name":"DD8 4LS",
    "wof:placetype":"postalcode"
},
  "geometry": {"coordinates":[-2.99464563046141,56.70296452042111],"type":"Point"}
}