{
  "type": "Feature",
  "properties": {
    "iso:country": "GB",
    "wof:name": "S62 6FS",
    "wof:placetype": "postalcode"
  },
  "geometry": {"coordinates":[-1.338232,53.458557],"type":"Point"}
}
