{
  "type": "Feature",
  "properties": {
    "iso:country":"GB",
    "wof:name":"RG27 9BD",
    "wof:placetype":"postalcode"
},
  "geometry": {"coordinates":[-0.98231450425628,51.29994268464277],"type":"Point"}
}