{
  "type": "Feature",
  "properties": {
    "iso:country":"GB",
    "wof:name":"NR9 5NF",
    "wof:placetype":"postalcode"
},
  "geometry": {"coordinates":[1.14365816449882,52.72462359701171],"type":"Point"}
}