{
  "type": "Feature",
  "properties": {
    "date:inception_lower": "1980-01-01",
    "date:inception_upper": "1980-01-01",
    "iso:country": "GB",
    "wof:name": "NR9 5NF",
    "wof:placetype": "postalcode"
  },
  "geometry": {"coordinates":[1.143665,52.724649],"type":"Point"}
}
