{
  "type": "Feature",
  "properties": {
    "iso:country": "GB",
    "wof:name": "NR9 5NF",
    "wof:placetype": "postalcode"
  },
  "geometry": {"coordinates":[1.143658,52.724624],"type":"Point"}
}
