{
  "type": "Feature",
  "properties": {
    "date:inception_lower": "1998-12-01",
    "date:inception_upper": "1998-12-01",
    "iso:country": "GB",
    "wof:name": "CA4 0BQ",
    "wof:placetype": "postalcode"
  },
  "geometry": {"coordinates":[-2.846619,54.852595],"type":"Point"}
}
