{
  "type": "Feature",
  "properties": {
    "iso:country":"GB",
    "wof:name":"CA4 0BQ",
    "wof:placetype":"postalcode"
},
  "geometry": {"coordinates":[-2.84693400773534,54.85297219924544],"type":"Point"}
}