{
  "type": "Feature",
  "properties": {
    "iso:country":"GB",
    "wof:name":"IP11 0YH",
    "wof:placetype":"postalcode"
},
  "geometry": {"coordinates":[1.31811847018555,51.98177494304537],"type":"Point"}
}