{
  "type": "Feature",
  "properties": {
    "iso:country":"GB",
    "wof:name":"TS6 0LZ",
    "wof:placetype":"postalcode"
},
  "geometry": {"coordinates":[-1.153189336062,54.55570736932953],"type":"Point"}
}