{
  "type": "Feature",
  "properties": {
    "date:inception_lower": "1980-01-01",
    "date:inception_upper": "1980-01-01",
    "iso:country": "GB",
    "wof:name": "CM20 1LS",
    "wof:placetype": "postalcode"
  },
  "geometry": {"coordinates":[0.092743,51.768612],"type":"Point"}
}
