{
  "type": "Feature",
  "properties": {
    "iso:country":"GB",
    "wof:name":"CM20 1LS",
    "wof:placetype":"postalcode"
},
  "geometry": {"coordinates":[0.09274313150439,51.7686117179621],"type":"Point"}
}