{
  "type": "Feature",
  "properties": {
    "iso:country":"GB",
    "wof:name":"TN29 0QQ",
    "wof:placetype":"postalcode"
},
  "geometry": {"coordinates":[0.98364725739314,51.01494107919528],"type":"Point"}
}