{
  "type": "Feature",
  "properties": {
    "date:inception_lower":"1980-01-01",
    "date:inception_upper":"1980-01-31",
    "iso:country":"GB",
    "wof:name":"TN29 0QQ",
    "wof:placetype":"postalcode"
},
  "geometry": {"coordinates":[0.983647,51.014941],"type":"Point"}
}