{
  "type": "Feature",
  "properties": {
    "iso:country": "GB",
    "wof:name": "EH32 9AW",
    "wof:placetype": "postalcode"
  },
  "geometry": {"coordinates":[-2.976044,55.962432],"type":"Point"}
}
