{
  "type": "Feature",
  "properties": {
    "iso:country":"GB",
    "wof:name":"ST1 4DU",
    "wof:placetype":"postalcode"
},
  "geometry": {"coordinates":[-2.17850853313425,53.01761857463815],"type":"Point"}
}