{
  "type": "Feature",
  "properties": {
    "iso:country":"GB",
    "wof:name":"LS15 8NJ",
    "wof:placetype":"postalcode"
},
  "geometry": {"coordinates":[-1.44547288199717,53.80401216963534],"type":"Point"}
}