{
  "type": "Feature",
  "properties": {
    "iso:country": "GB",
    "wof:name": "G1 5AX",
    "wof:placetype": "postalcode"
  },
  "geometry": {"coordinates":[-4.239591,55.855968],"type":"Point"}
}
