{
  "type": "Feature",
  "properties": {
    "date:inception_lower": "1980-01-01",
    "date:inception_upper": "1980-01-01",
    "iso:country": "GB",
    "wof:name": "DH1 4EP",
    "wof:placetype": "postalcode"
  },
  "geometry": {"coordinates":[-1.587121,54.775848],"type":"Point"}
}
