{
  "type": "Feature",
  "properties": {
    "iso:country":"GB",
    "wof:name":"DH1 4EP",
    "wof:placetype":"postalcode"
},
  "geometry": {"coordinates":[-1.58712066870799,54.7758484319697],"type":"Point"}
}