{
  "type": "Feature",
  "properties": {
    "iso:country": "GB",
    "wof:name": "HP13 6UE",
    "wof:placetype": "postalcode"
  },
  "geometry": {"coordinates":[-0.731672,51.639858],"type":"Point"}
}
