{
  "type": "Feature",
  "properties": {
    "iso:country":"GB",
    "wof:name":"SR4 8DF",
    "wof:placetype":"postalcode"
},
  "geometry": {"coordinates":[-1.42547922522333,54.89945702441938],"type":"Point"}
}