{
  "type": "Feature",
  "properties": {
    "date:inception_lower": "2022-06-01",
    "date:inception_upper": "2022-06-01",
    "iso:country": "GB",
    "wof:name": "PR25 1EH",
    "wof:placetype": "postalcode"
  },
  "geometry": {"coordinates":[-2.713372,53.682519],"type":"Point"}
}
