{
  "type": "Feature",
  "properties": {
    "iso:country":"GB",
    "wof:name":"SY1 4UG",
    "wof:placetype":"postalcode"
},
  "geometry": {"coordinates":[-2.71229347365945,52.73718539490169],"type":"Point"}
}