{
  "type": "Feature",
  "properties": {
    "date:inception_lower": "1980-01-01",
    "date:inception_upper": "1980-01-01",
    "iso:country": "GB",
    "wof:name": "HR6 0QN",
    "wof:placetype": "postalcode"
  },
  "geometry": {"coordinates":[-2.694207,52.223642],"type":"Point"}
}
