{
  "type": "Feature",
  "properties": {
    "iso:country":"GB",
    "wof:name":"HR6 0QN",
    "wof:placetype":"postalcode"
},
  "geometry": {"coordinates":[-2.69420672441683,52.22364176253346],"type":"Point"}
}