{
  "type": "Feature",
  "properties": {
    "date:inception_lower":"1980-01-01",
    "date:inception_upper":"1980-01-31",
    "iso:country":"GB",
    "wof:name":"YO11 1LS",
    "wof:placetype":"postalcode"
},
  "geometry": {"coordinates":[-0.406766,54.280559],"type":"Point"}
}