{
  "type": "Feature",
  "properties": {
    "iso:country":"GB",
    "wof:name":"YO11 1LS",
    "wof:placetype":"postalcode"
},
  "geometry": {"coordinates":[-0.40674929840832,54.28054117004542],"type":"Point"}
}