{
  "type": "Feature",
  "properties": {
    "date:inception_lower": "2014-07-01",
    "date:inception_upper": "2014-07-01",
    "iso:country": "GB",
    "wof:name": "SS0 0RX",
    "wof:placetype": "postalcode"
  },
  "geometry": {"coordinates":[0.701749,51.550964],"type":"Point"}
}
