{
  "type": "Feature",
  "properties": {
    "iso:country":"GB",
    "wof:name":"SA33 4DJ",
    "wof:placetype":"postalcode"
},
  "geometry": {"coordinates":[-4.49206114893659,51.83241279580652],"type":"Point"}
}