{
  "type": "Feature",
  "properties": {
    "iso:country":"GB",
    "wof:name":"LS26 0AT",
    "wof:placetype":"postalcode"
},
  "geometry": {"coordinates":[-1.47683278607005,53.74870540103412],"type":"Point"}
}