{
  "type": "Feature",
  "properties": {
    "iso:country":"GB",
    "wof:name":"E9 6AF",
    "wof:placetype":"postalcode"
},
  "geometry": {"coordinates":[-0.04163542209304,51.55111687951737],"type":"Point"}
}