{
  "type": "Feature",
  "properties": {
    "iso:country": "GB",
    "wof:name": "S75 2ER",
    "wof:placetype": "postalcode"
  },
  "geometry": {"coordinates":[-1.500447,53.55634],"type":"Point"}
}
