{
  "type": "Feature",
  "properties": {
    "iso:country": "GB",
    "wof:name": "NG2 6DS",
    "wof:placetype": "postalcode"
  },
  "geometry": {"coordinates":[-1.129881,52.928176],"type":"Point"}
}
