{
  "type": "Feature",
  "properties": {
    "iso:country":"GB",
    "wof:name":"NG2 6DS",
    "wof:placetype":"postalcode"
},
  "geometry": {"coordinates":[-1.12957678611725,52.92791105735913],"type":"Point"}
}