{
  "type": "Feature",
  "properties": {
    "iso:country":"GB",
    "wof:name":"LU2 9RG",
    "wof:placetype":"postalcode"
},
  "geometry": {"coordinates":[-0.38121549808011,51.8937072548807],"type":"Point"}
}