{
  "type": "Feature",
  "properties": {
    "date:inception_lower": "1980-01-01",
    "date:inception_upper": "1980-01-01",
    "iso:country": "GB",
    "wof:name": "LU2 9RG",
    "wof:placetype": "postalcode"
  },
  "geometry": {"coordinates":[-0.381215,51.893707],"type":"Point"}
}
