{
  "type": "Feature",
  "properties": {
    "date:inception_lower": "1990-07-01",
    "date:inception_upper": "1990-07-01",
    "iso:country": "GB",
    "wof:name": "PO20 9HP",
    "wof:placetype": "postalcode"
  },
  "geometry": {"coordinates":[-0.778875,50.744356],"type":"Point"}
}
