{
  "type": "Feature",
  "properties": {
    "iso:country":"GB",
    "wof:name":"PO20 9HP",
    "wof:placetype":"postalcode"
},
  "geometry": {"coordinates":[-0.77943385398912,50.74379746543949],"type":"Point"}
}