{
  "type": "Feature",
  "properties": {
    "iso:country":"GB",
    "wof:name":"PL26 8NF",
    "wof:placetype":"postalcode"
},
  "geometry": {"coordinates":[-4.86193583912465,50.41324773015226],"type":"Point"}
}