{
  "type": "Feature",
  "properties": {
    "iso:country":"GB",
    "wof:name":"ST3 2EF",
    "wof:placetype":"postalcode"
},
  "geometry": {"coordinates":[-2.15324763182518,52.98558049882953],"type":"Point"}
}