{
  "type": "Feature",
  "properties": {
    "iso:country":"GB",
    "wof:name":"B18 7JU",
    "wof:placetype":"postalcode"
},
  "geometry": {"coordinates":[-1.92684844037741,52.49049400317083],"type":"Point"}
}