{
  "type": "Feature",
  "properties": {
    "iso:country":"GB",
    "wof:name":"KY1 2UX",
    "wof:placetype":"postalcode"
},
  "geometry": {"coordinates":[-3.12010149318247,56.13025484654727],"type":"Point"}
}