{
  "type": "Feature",
  "properties": {
    "iso:country":"GB",
    "wof:name":"ZE2 9SN",
    "wof:placetype":"postalcode"
},
  "geometry": {"coordinates":[-1.35127273122227,60.39892750980583],"type":"Point"}
}