{
  "type": "Feature",
  "properties": {
    "iso:country": "GB",
    "wof:name": "E17 3RT",
    "wof:placetype": "postalcode"
  },
  "geometry": {"coordinates":[0.00036,51.59137],"type":"Point"}
}
