{
  "type": "Feature",
  "properties": {
    "iso:country":"GB",
    "wof:name":"E17 3RT",
    "wof:placetype":"postalcode"
},
  "geometry": {"coordinates":[0.0003601335623,51.59136961501324],"type":"Point"}
}