{
  "type": "Feature",
  "properties": {
    "iso:country": "GB",
    "wof:name": "CF39 8HZ",
    "wof:placetype": "postalcode"
  },
  "geometry": {"coordinates":[-3.449404,51.581692],"type":"Point"}
}
