{
  "type": "Feature",
  "properties": {
    "date:inception_lower":"2008-09-01",
    "date:inception_upper":"2008-09-30",
    "iso:country":"GB",
    "wof:name":"CF39 8HZ",
    "wof:placetype":"postalcode"
},
  "geometry": {"coordinates":[-3.449404,51.581692],"type":"Point"}
}