{
  "type": "Feature",
  "properties": {
    "iso:country":"GB",
    "wof:name":"LL77 7UR",
    "wof:placetype":"postalcode"
},
  "geometry": {"coordinates":[-4.31638412647915,53.31245730183262],"type":"Point"}
}