{
  "type": "Feature",
  "properties": {
    "iso:country": "GB",
    "wof:name": "LL77 7UR",
    "wof:placetype": "postalcode"
  },
  "geometry": {"coordinates":[-4.316384,53.312457],"type":"Point"}
}
