{
  "type": "Feature",
  "properties": {
    "iso:country":"GB",
    "wof:name":"HR9 5AA",
    "wof:placetype":"postalcode"
},
  "geometry": {"coordinates":[-2.58247527139116,51.912925257708],"type":"Point"}
}