{
  "type": "Feature",
  "properties": {
    "iso:country":"GB",
    "wof:name":"BB2 3DJ",
    "wof:placetype":"postalcode"
},
  "geometry": {"coordinates":[-2.48021452641333,53.74126104341485],"type":"Point"}
}