{
  "type": "Feature",
  "properties": {
    "iso:country":"GB",
    "wof:name":"BS3 5LS",
    "wof:placetype":"postalcode"
},
  "geometry": {"coordinates":[-2.59714510841028,51.43153786282335],"type":"Point"}
}