{
  "type": "Feature",
  "properties": {
    "iso:country":"GB",
    "wof:name":"RG7 4SR",
    "wof:placetype":"postalcode"
},
  "geometry": {"coordinates":[-1.19929701421448,51.38217630066424],"type":"Point"}
}