{
  "type": "Feature",
  "properties": {
    "date:inception_lower": "2016-05-01",
    "date:inception_upper": "2016-05-01",
    "iso:country": "GB",
    "wof:name": "LE9 7NX",
    "wof:placetype": "postalcode"
  },
  "geometry": {"coordinates":[-1.323955,52.56671],"type":"Point"}
}
