{
  "type": "Feature",
  "properties": {
    "iso:country":"GB",
    "wof:name":"NR35 2JT",
    "wof:placetype":"postalcode"
},
  "geometry": {"coordinates":[1.42230491185128,52.48668299710538],"type":"Point"}
}