{
  "type": "Feature",
  "properties": {
    "iso:country": "GB",
    "wof:name": "NR35 2JT",
    "wof:placetype": "postalcode"
  },
  "geometry": {"coordinates":[1.422305,52.486683],"type":"Point"}
}
