{
  "type": "Feature",
  "properties": {
    "date:inception_lower": "1980-01-01",
    "date:inception_upper": "1980-01-01",
    "iso:country": "GB",
    "wof:name": "B70 8SS",
    "wof:placetype": "postalcode"
  },
  "geometry": {"coordinates":[-1.994267,52.521819],"type":"Point"}
}
