{
  "type": "Feature",
  "properties": {
    "iso:country": "GB",
    "wof:name": "DD2 1HZ",
    "wof:placetype": "postalcode"
  },
  "geometry": {"coordinates":[-3.004452,56.459562],"type":"Point"}
}
