{
  "type": "Feature",
  "properties": {
    "iso:country":"GB",
    "wof:name":"DD2 1HZ",
    "wof:placetype":"postalcode"
},
  "geometry": {"coordinates":[-3.00445199010884,56.45956211442149],"type":"Point"}
}