{
  "type": "Feature",
  "properties": {
    "date:inception_lower":"1980-01-01",
    "date:inception_upper":"1980-01-31",
    "iso:country":"GB",
    "wof:name":"B20 2HL",
    "wof:placetype":"postalcode"
},
  "geometry": {"coordinates":[-1.92902,52.514049],"type":"Point"}
}