{
  "type": "Feature",
  "properties": {
    "iso:country":"GB",
    "wof:name":"B20 2HL",
    "wof:placetype":"postalcode"
},
  "geometry": {"coordinates":[-1.92901979523831,52.51404892560456],"type":"Point"}
}