{
  "type": "Feature",
  "properties": {
    "iso:country":"GB",
    "wof:name":"NG18 1QQ",
    "wof:placetype":"postalcode"
},
  "geometry": {"coordinates":[-1.20050460460982,53.1473358775249],"type":"Point"}
}