{
  "type": "Feature",
  "properties": {
    "iso:country":"GB",
    "wof:name":"EC1N 8EL",
    "wof:placetype":"postalcode"
},
  "geometry": {"coordinates":[-0.10817227958139,51.52055501792164],"type":"Point"}
}