{
  "type": "Feature",
  "properties": {
    "iso:country":"GB",
    "wof:name":"LD7 1ED",
    "wof:placetype":"postalcode"
},
  "geometry": {"coordinates":[-3.04644726978563,52.34483557951025],"type":"Point"}
}