{
  "type": "Feature",
  "properties": {
    "iso:country": "GB",
    "wof:name": "SP11 8BS",
    "wof:placetype": "postalcode"
  },
  "geometry": {"coordinates":[-1.575108,51.195995],"type":"Point"}
}
