{
  "type": "Feature",
  "properties": {
    "date:inception_lower": "1985-04-01",
    "date:inception_upper": "1985-04-01",
    "iso:country": "GB",
    "wof:name": "SP11 8BS",
    "wof:placetype": "postalcode"
  },
  "geometry": {"coordinates":[-1.575108,51.195995],"type":"Point"}
}
