{
  "type": "Feature",
  "properties": {
    "date:inception_lower":"1980-01-01",
    "date:inception_upper":"1980-01-31",
    "iso:country":"GB",
    "wof:name":"WV13 3LD",
    "wof:placetype":"postalcode"
},
  "geometry": {"coordinates":[-2.069746,52.580377],"type":"Point"}
}