{
  "type": "Feature",
  "properties": {
    "iso:country": "GB",
    "wof:name": "WV13 3LD",
    "wof:placetype": "postalcode"
  },
  "geometry": {"coordinates":[-2.069746,52.580377],"type":"Point"}
}
