{
  "type": "Feature",
  "properties": {
    "iso:country":"GB",
    "wof:name":"WV13 3LD",
    "wof:placetype":"postalcode"
},
  "geometry": {"coordinates":[-2.06974591567515,52.58037650877753],"type":"Point"}
}