{
  "type": "Feature",
  "properties": {
    "iso:country": "GB",
    "wof:name": "LS11 8LN",
    "wof:placetype": "postalcode"
  },
  "geometry": {"coordinates":[-1.573388,53.76914],"type":"Point"}
}
