{
  "type": "Feature",
  "properties": {
    "date:inception_lower": "2008-12-01",
    "date:inception_upper": "2008-12-01",
    "iso:country": "GB",
    "wof:name": "LS11 8LN",
    "wof:placetype": "postalcode"
  },
  "geometry": {"coordinates":[-1.573388,53.76914],"type":"Point"}
}
