{
  "type": "Feature",
  "properties": {
    "date:inception_lower": "1991-01-01",
    "date:inception_upper": "1991-01-01",
    "iso:country": "GB",
    "wof:name": "AL1 1SU",
    "wof:placetype": "postalcode"
  },
  "geometry": {"coordinates":[-0.328981,51.745933],"type":"Point"}
}
