{
  "type": "Feature",
  "properties": {
    "iso:country":"GB",
    "wof:name":"AL1 1SU",
    "wof:placetype":"postalcode"
},
  "geometry": {"coordinates":[-0.32898065178545,51.74593306118254],"type":"Point"}
}