{
  "type": "Feature",
  "properties": {
    "date:inception_lower": "1980-01-01",
    "date:inception_upper": "1980-01-01",
    "iso:country": "GB",
    "wof:name": "EX17 4RW",
    "wof:placetype": "postalcode"
  },
  "geometry": {"coordinates":[-3.692047,50.865823],"type":"Point"}
}
