{
  "type": "Feature",
  "properties": {
    "date:inception_lower": "2020-05-01",
    "date:inception_upper": "2020-05-01",
    "iso:country": "GB",
    "wof:name": "GU11 4DU",
    "wof:placetype": "postalcode"
  },
  "geometry": {"coordinates":[-0.770686,51.256664],"type":"Point"}
}
