{
  "type": "Feature",
  "properties": {
    "iso:country":"GB",
    "wof:name":"TS4 2XG",
    "wof:placetype":"postalcode"
},
  "geometry": {"coordinates":[-1.22286510908207,54.56534162264101],"type":"Point"}
}