{
  "type": "Feature",
  "properties": {
    "iso:country":"GB",
    "wof:name":"GL54 2QP",
    "wof:placetype":"postalcode"
},
  "geometry": {"coordinates":[-1.69727580282243,51.87150620105982],"type":"Point"}
}