{
  "type": "Feature",
  "properties": {
    "date:inception_lower":"1980-01-01",
    "date:inception_upper":"1980-01-31",
    "iso:country":"GB",
    "wof:name":"GL3 2DJ",
    "wof:placetype":"postalcode"
},
  "geometry": {"coordinates":[-2.185253,51.884489],"type":"Point"}
}