{
  "type": "Feature",
  "properties": {
    "iso:country": "GB",
    "wof:name": "GL3 2DJ",
    "wof:placetype": "postalcode"
  },
  "geometry": {"coordinates":[-2.185253,51.884489],"type":"Point"}
}
