{
  "type": "Feature",
  "properties": {
    "iso:country": "GB",
    "wof:name": "CV10 8LT",
    "wof:placetype": "postalcode"
  },
  "geometry": {"coordinates":[-1.514095,52.518225],"type":"Point"}
}
