{
  "type": "Feature",
  "properties": {
    "iso:country":"GB",
    "wof:name":"CV10 8LT",
    "wof:placetype":"postalcode"
},
  "geometry": {"coordinates":[-1.51409491690039,52.51822494098098],"type":"Point"}
}