{
  "type": "Feature",
  "properties": {
    "date:inception_lower":"1997-12-01",
    "date:inception_upper":"1997-12-31",
    "iso:country":"GB",
    "wof:name":"SE5 8QT",
    "wof:placetype":"postalcode"
},
  "geometry": {"coordinates":[-0.081205,51.472547],"type":"Point"}
}