{
  "type": "Feature",
  "properties": {
    "iso:country":"GB",
    "wof:name":"SE5 8QT",
    "wof:placetype":"postalcode"
},
  "geometry": {"coordinates":[-0.08123091015644,51.47254653627846],"type":"Point"}
}