{
  "type": "Feature",
  "properties": {
    "iso:country": "GB",
    "wof:name": "SE5 8QT",
    "wof:placetype": "postalcode"
  },
  "geometry": {"coordinates":[-0.081205,51.472547],"type":"Point"}
}
