{
  "type": "Feature",
  "properties": {
    "iso:country": "GB",
    "wof:name": "CV6 6BQ",
    "wof:placetype": "postalcode"
  },
  "geometry": {"coordinates":[-1.477258,52.453142],"type":"Point"}
}
