{
  "type": "Feature",
  "properties": {
    "iso:country":"GB",
    "wof:name":"CV6 6BQ",
    "wof:placetype":"postalcode"
},
  "geometry": {"coordinates":[-1.47725774851478,52.45314194974565],"type":"Point"}
}