{
  "type": "Feature",
  "properties": {
    "iso:country": "GB",
    "wof:name": "TW9 4AL",
    "wof:placetype": "postalcode"
  },
  "geometry": {"coordinates":[-0.280247,51.477379],"type":"Point"}
}
