{
  "type": "Feature",
  "properties": {
    "iso:country":"GB",
    "wof:name":"ST13 5PG",
    "wof:placetype":"postalcode"
},
  "geometry": {"coordinates":[-2.02951663538544,53.10155433292127],"type":"Point"}
}