{
  "type": "Feature",
  "properties": {
    "iso:country":"GB",
    "wof:name":"OL2 8AY",
    "wof:placetype":"postalcode"
},
  "geometry": {"coordinates":[-2.09075321035961,53.58176878793826],"type":"Point"}
}