{
  "type": "Feature",
  "properties": {
    "iso:country":"GB",
    "wof:name":"CW2 8BX",
    "wof:placetype":"postalcode"
},
  "geometry": {"coordinates":[-2.46547173630301,53.08105972117765],"type":"Point"}
}