{
  "type": "Feature",
  "properties": {
    "iso:country":"GB",
    "wof:name":"CM1 6EG",
    "wof:placetype":"postalcode"
},
  "geometry": {"coordinates":[0.5065117374525,51.75425518423712],"type":"Point"}
}