{
  "type": "Feature",
  "properties": {
    "iso:country": "GB",
    "wof:name": "CM1 6EG",
    "wof:placetype": "postalcode"
  },
  "geometry": {"coordinates":[0.506512,51.754255],"type":"Point"}
}
