{
  "type": "Feature",
  "properties": {
    "date:inception_lower": "1980-01-01",
    "date:inception_upper": "1980-01-01",
    "iso:country": "GB",
    "wof:name": "SA9 2RS",
    "wof:placetype": "postalcode"
  },
  "geometry": {"coordinates":[-3.82482,51.786824],"type":"Point"}
}
