{
  "type": "Feature",
  "properties": {
    "date:inception_lower": "1980-01-01",
    "date:inception_upper": "1980-01-01",
    "iso:country": "GB",
    "wof:name": "DN5 7PA",
    "wof:placetype": "postalcode"
  },
  "geometry": {"coordinates":[-1.195855,53.5131],"type":"Point"}
}
