{
  "type": "Feature",
  "properties": {
    "iso:country":"GB",
    "wof:name":"DN5 7PA",
    "wof:placetype":"postalcode"
},
  "geometry": {"coordinates":[-1.19585545638842,53.51309951731361],"type":"Point"}
}