{
  "type": "Feature",
  "properties": {
    "iso:country": "GB",
    "wof:name": "CM3 2QZ",
    "wof:placetype": "postalcode"
  },
  "geometry": {"coordinates":[0.530637,51.801132],"type":"Point"}
}
