{
  "type": "Feature",
  "properties": {
    "iso:country":"GB",
    "wof:name":"CM3 2QZ",
    "wof:placetype":"postalcode"
},
  "geometry": {"coordinates":[0.53063737919849,51.80113156147787],"type":"Point"}
}