{
  "type": "Feature",
  "properties": {
    "iso:country": "GB",
    "wof:name": "SY12 9EA",
    "wof:placetype": "postalcode"
  },
  "geometry": {"coordinates":[-2.944642,52.937957],"type":"Point"}
}
