{
  "type": "Feature",
  "properties": {
    "iso:country": "GB",
    "wof:name": "SN7 7AY",
    "wof:placetype": "postalcode"
  },
  "geometry": {"coordinates":[-1.582444,51.65624],"type":"Point"}
}
