{
  "type": "Feature",
  "properties": {
    "iso:country":"GB",
    "wof:name":"SN7 7AY",
    "wof:placetype":"postalcode"
},
  "geometry": {"coordinates":[-1.58244366996928,51.65624042277408],"type":"Point"}
}