{
  "type": "Feature",
  "properties": {
    "date:inception_lower": "1980-01-01",
    "date:inception_upper": "1980-01-01",
    "iso:country": "GB",
    "wof:name": "SN7 7AY",
    "wof:placetype": "postalcode"
  },
  "geometry": {"coordinates":[-1.582444,51.65624],"type":"Point"}
}
