{
  "type": "Feature",
  "properties": {
    "iso:country":"GB",
    "wof:name":"GU9 0RB",
    "wof:placetype":"postalcode"
},
  "geometry": {"coordinates":[-0.78780708301307,51.23464172591363],"type":"Point"}
}