{
  "type": "Feature",
  "properties": {
    "iso:country":"GB",
    "wof:name":"DY2 0EJ",
    "wof:placetype":"postalcode"
},
  "geometry": {"coordinates":[-2.09078595717593,52.47843488325768],"type":"Point"}
}