{
  "type": "Feature",
  "properties": {
    "iso:country": "GB",
    "wof:name": "CT19 4EN",
    "wof:placetype": "postalcode"
  },
  "geometry": {"coordinates":[1.153137,51.087385],"type":"Point"}
}
