{
  "type": "Feature",
  "properties": {
    "iso:country": "GB",
    "wof:name": "ME10 5BQ",
    "wof:placetype": "postalcode"
  },
  "geometry": {"coordinates":[0.710225,51.349912],"type":"Point"}
}
