{
  "type": "Feature",
  "properties": {
    "iso:country":"GB",
    "wof:name":"CA2 6BP",
    "wof:placetype":"postalcode"
},
  "geometry": {"coordinates":[-2.96469525176308,54.87087594761764],"type":"Point"}
}