{
  "type": "Feature",
  "properties": {
    "date:inception_lower": "2015-06-01",
    "date:inception_upper": "2015-06-01",
    "iso:country": "GB",
    "wof:name": "CA2 6BP",
    "wof:placetype": "postalcode"
  },
  "geometry": {"coordinates":[-2.964695,54.870876],"type":"Point"}
}
