{
  "type": "Feature",
  "properties": {
    "iso:country":"GB",
    "wof:name":"M31 4LH",
    "wof:placetype":"postalcode"
},
  "geometry": {"coordinates":[-2.43789375870948,53.41796802346366],"type":"Point"}
}