{
  "type": "Feature",
  "properties": {
    "date:inception_lower": "2004-06-01",
    "date:inception_upper": "2004-06-01",
    "iso:country": "GB",
    "wof:name": "DY5 3QU",
    "wof:placetype": "postalcode"
  },
  "geometry": {"coordinates":[-2.134031,52.476439],"type":"Point"}
}
