{
  "type": "Feature",
  "properties": {
    "date:inception_lower": "2019-07-01",
    "date:inception_upper": "2019-07-01",
    "iso:country": "GB",
    "wof:name": "CB22 5GB",
    "wof:placetype": "postalcode"
  },
  "geometry": {"coordinates":[0.106199,52.148503],"type":"Point"}
}
