{
  "type": "Feature",
  "properties": {
    "iso:country":"GB",
    "wof:name":"WF5 9ER",
    "wof:placetype":"postalcode"
},
  "geometry": {"coordinates":[-1.58490297000033,53.68604931448992],"type":"Point"}
}