{
  "type": "Feature",
  "properties": {
    "iso:country":"GB",
    "wof:name":"PL17 8PG",
    "wof:placetype":"postalcode"
},
  "geometry": {"coordinates":[-4.31426735488593,50.55113626423879],"type":"Point"}
}