{
  "type": "Feature",
  "properties": {
    "date:inception_lower":"1995-07-01",
    "date:inception_upper":"1995-07-31",
    "iso:country":"GB",
    "wof:name":"CF72 9HG",
    "wof:placetype":"postalcode"
},
  "geometry": {"coordinates":[-3.402218,51.532296],"type":"Point"}
}