{
  "type": "Feature",
  "properties": {
    "iso:country": "GB",
    "wof:name": "CF72 9HG",
    "wof:placetype": "postalcode"
  },
  "geometry": {"coordinates":[-3.402218,51.532296],"type":"Point"}
}
