{
  "type": "Feature",
  "properties": {
    "iso:country": "GB",
    "wof:name": "PL20 6FJ",
    "wof:placetype": "postalcode"
  },
  "geometry": {"coordinates":[-4.085251,50.493969],"type":"Point"}
}
