{
  "type": "Feature",
  "properties": {
    "iso:country": "GB",
    "wof:name": "EX4 8EA",
    "wof:placetype": "postalcode"
  },
  "geometry": {"coordinates":[-3.500554,50.734238],"type":"Point"}
}
