{
  "type": "Feature",
  "properties": {
    "iso:country":"GB",
    "wof:name":"EX4 8EA",
    "wof:placetype":"postalcode"
},
  "geometry": {"coordinates":[-3.50055381922286,50.73423781304416],"type":"Point"}
}