{
  "type": "Feature",
  "properties": {
    "iso:country": "GB",
    "wof:name": "BH15 3DG",
    "wof:placetype": "postalcode"
  },
  "geometry": {"coordinates":[-1.973196,50.732788],"type":"Point"}
}
