{
  "type": "Feature",
  "properties": {
    "iso:country":"GB",
    "wof:name":"BH15 3DG",
    "wof:placetype":"postalcode"
},
  "geometry": {"coordinates":[-1.9731957935914,50.73278755159716],"type":"Point"}
}