{
  "type": "Feature",
  "properties": {
    "date:inception_lower": "1984-10-01",
    "date:inception_upper": "1984-10-01",
    "iso:country": "GB",
    "wof:name": "RH19 4TE",
    "wof:placetype": "postalcode"
  },
  "geometry": {"coordinates":[-0.00433,51.122162],"type":"Point"}
}
