{
  "type": "Feature",
  "properties": {
    "iso:country": "GB",
    "wof:name": "NR30 3DH",
    "wof:placetype": "postalcode"
  },
  "geometry": {"coordinates":[1.730246,52.595736],"type":"Point"}
}
