{
  "type": "Feature",
  "properties": {
    "date:inception_lower": "1980-01-01",
    "date:inception_upper": "1980-01-01",
    "iso:country": "GB",
    "wof:name": "BA12 0BA",
    "wof:placetype": "postalcode"
  },
  "geometry": {"coordinates":[-2.178105,51.209704],"type":"Point"}
}
