{
  "type": "Feature",
  "properties": {
    "iso:country": "GB",
    "wof:name": "BA12 0BA",
    "wof:placetype": "postalcode"
  },
  "geometry": {"coordinates":[-2.178105,51.209704],"type":"Point"}
}
