{
  "type": "Feature",
  "properties": {
    "date:inception_lower": "2019-08-01",
    "date:inception_upper": "2019-08-01",
    "iso:country": "GB",
    "wof:name": "CO4 6BS",
    "wof:placetype": "postalcode"
  },
  "geometry": {"coordinates":[0.893694,51.91953],"type":"Point"}
}
