{
  "type": "Feature",
  "properties": {
    "iso:country":"GB",
    "wof:name":"S35 4NR",
    "wof:placetype":"postalcode"
},
  "geometry": {"coordinates":[-1.49139013496791,53.47438992390579],"type":"Point"}
}