{
  "type": "Feature",
  "properties": {
    "iso:country":"GB",
    "wof:name":"UB2 4HB",
    "wof:placetype":"postalcode"
},
  "geometry": {"coordinates":[-0.37204193155096,51.49618823862617],"type":"Point"}
}