{
  "type": "Feature",
  "properties": {
    "iso:country": "GB",
    "wof:name": "IV7 8FH",
    "wof:placetype": "postalcode"
  },
  "geometry": {"coordinates":[-4.427574,57.564424],"type":"Point"}
}
