{
  "type": "Feature",
  "properties": {
    "date:inception_lower": "2016-11-01",
    "date:inception_upper": "2016-11-01",
    "iso:country": "GB",
    "wof:name": "IV7 8FH",
    "wof:placetype": "postalcode"
  },
  "geometry": {"coordinates":[-4.427332,57.564546],"type":"Point"}
}
