{
  "type": "Feature",
  "properties": {
    "iso:country":"GB",
    "wof:name":"B31 4QT",
    "wof:placetype":"postalcode"
},
  "geometry": {"coordinates":[-1.97772387376841,52.38933173681375],"type":"Point"}
}