{
  "type": "Feature",
  "properties": {
    "iso:country":"GB",
    "wof:name":"FY8 3RX",
    "wof:placetype":"postalcode"
},
  "geometry": {"coordinates":[-3.01479657599472,53.76431573696733],"type":"Point"}
}