{
  "type": "Feature",
  "properties": {
    "iso:country": "GB",
    "wof:name": "FY8 3RX",
    "wof:placetype": "postalcode"
  },
  "geometry": {"coordinates":[-3.014797,53.764316],"type":"Point"}
}
