{
  "type": "Feature",
  "properties": {
    "iso:country":"GB",
    "wof:name":"DL14 6TP",
    "wof:placetype":"postalcode"
},
  "geometry": {"coordinates":[-1.6944133233757,54.64419723494102],"type":"Point"}
}