{
  "type": "Feature",
  "properties": {
    "iso:country": "GB",
    "wof:name": "M19 3HZ",
    "wof:placetype": "postalcode"
  },
  "geometry": {"coordinates":[-2.1782,53.443734],"type":"Point"}
}
