{
  "type": "Feature",
  "properties": {
    "iso:country":"GB",
    "wof:name":"M19 3HZ",
    "wof:placetype":"postalcode"
},
  "geometry": {"coordinates":[-2.17819966232695,53.44373434239602],"type":"Point"}
}