{
  "type": "Feature",
  "properties": {
    "iso:country":"GB",
    "wof:name":"YO17 9ES",
    "wof:placetype":"postalcode"
},
  "geometry": {"coordinates":[-0.78501860434368,54.13226643371073],"type":"Point"}
}