{
  "type": "Feature",
  "properties": {
    "iso:country":"GB",
    "wof:name":"ST15 8GA",
    "wof:placetype":"postalcode"
},
  "geometry": {"coordinates":[-2.13252546813956,52.89237779163867],"type":"Point"}
}