{
  "type": "Feature",
  "properties": {
    "iso:country":"GB",
    "wof:name":"DT1 3WL",
    "wof:placetype":"postalcode"
},
  "geometry": {"coordinates":[-2.46053508900917,50.71167345109554],"type":"Point"}
}