{
  "type": "Feature",
  "properties": {
    "date:inception_lower": "2001-06-01",
    "date:inception_upper": "2001-06-01",
    "iso:country": "GB",
    "wof:name": "DT1 3WL",
    "wof:placetype": "postalcode"
  },
  "geometry": {"coordinates":[-2.460535,50.711673],"type":"Point"}
}
