{
  "type": "Feature",
  "properties": {
    "iso:country":"GB",
    "wof:name":"OL1 4JS",
    "wof:placetype":"postalcode"
},
  "geometry": {"coordinates":[-2.07602177972147,53.56230144383111],"type":"Point"}
}