{
  "type": "Feature",
  "properties": {
    "iso:country": "GB",
    "wof:name": "TN25 4HE",
    "wof:placetype": "postalcode"
  },
  "geometry": {"coordinates":[0.947223,51.21148],"type":"Point"}
}
