{
  "type": "Feature",
  "properties": {
    "date:inception_lower":"1980-01-01",
    "date:inception_upper":"1980-01-31",
    "iso:country":"GB",
    "wof:name":"TN25 4HE",
    "wof:placetype":"postalcode"
},
  "geometry": {"coordinates":[0.947223,51.21148],"type":"Point"}
}