{
  "type": "Feature",
  "properties": {
    "iso:country":"GB",
    "wof:name":"W8 4DG",
    "wof:placetype":"postalcode"
},
  "geometry": {"coordinates":[-0.19322058454037,51.50443256033959],"type":"Point"}
}