{
  "type": "Feature",
  "properties": {
    "iso:country": "GB",
    "wof:name": "MK5 6AG",
    "wof:placetype": "postalcode"
  },
  "geometry": {"coordinates":[-0.785686,52.018339],"type":"Point"}
}
