{
  "type": "Feature",
  "properties": {
    "date:inception_lower": "1980-01-01",
    "date:inception_upper": "1980-01-01",
    "iso:country": "GB",
    "wof:name": "MK5 6AG",
    "wof:placetype": "postalcode"
  },
  "geometry": {"coordinates":[-0.785686,52.018339],"type":"Point"}
}
