{
  "type": "Feature",
  "properties": {
    "iso:country":"GB",
    "wof:name":"MK5 6AG",
    "wof:placetype":"postalcode"
},
  "geometry": {"coordinates":[-0.78568649819445,52.01833891139142],"type":"Point"}
}