{
  "type": "Feature",
  "properties": {
    "date:inception_lower": "1980-01-01",
    "date:inception_upper": "1980-01-01",
    "iso:country": "GB",
    "wof:name": "NR35 2RR",
    "wof:placetype": "postalcode"
  },
  "geometry": {"coordinates":[1.459543,52.472186],"type":"Point"}
}
