{
  "type": "Feature",
  "properties": {
    "iso:country":"GB",
    "wof:name":"DL1 4AE",
    "wof:placetype":"postalcode"
},
  "geometry": {"coordinates":[-1.54476739810959,54.52250372829328],"type":"Point"}
}