{
  "type": "Feature",
  "properties": {
    "date:inception_lower": "2015-09-01",
    "date:inception_upper": "2015-09-01",
    "iso:country": "GB",
    "wof:name": "DL1 4AE",
    "wof:placetype": "postalcode"
  },
  "geometry": {"coordinates":[-1.544767,54.522504],"type":"Point"}
}
