{
  "type": "Feature",
  "properties": {
    "iso:country":"GB",
    "wof:name":"SN14 0LW",
    "wof:placetype":"postalcode"
},
  "geometry": {"coordinates":[-2.13705267524902,51.46091636331084],"type":"Point"}
}