{
  "type": "Feature",
  "properties": {
    "iso:country": "GB",
    "wof:name": "RH10 7SG",
    "wof:placetype": "postalcode"
  },
  "geometry": {"coordinates":[-0.145829,51.117516],"type":"Point"}
}
