{
  "type": "Feature",
  "properties": {
    "iso:country":"GB",
    "wof:name":"M29 8DF",
    "wof:placetype":"postalcode"
},
  "geometry": {"coordinates":[-2.46276258587682,53.51462686478634],"type":"Point"}
}