{
  "type": "Feature",
  "properties": {
    "iso:country":"GB",
    "wof:name":"NR12 7JQ",
    "wof:placetype":"postalcode"
},
  "geometry": {"coordinates":[1.35891030390735,52.73340309748978],"type":"Point"}
}