{
  "type": "Feature",
  "properties": {
    "iso:country": "GB",
    "wof:name": "NR12 7JQ",
    "wof:placetype": "postalcode"
  },
  "geometry": {"coordinates":[1.35891,52.733403],"type":"Point"}
}
