{
  "type": "Feature",
  "properties": {
    "iso:country":"GB",
    "wof:name":"BH15 4NJ",
    "wof:placetype":"postalcode"
},
  "geometry": {"coordinates":[-2.01265414360528,50.718932163109],"type":"Point"}
}