{
  "type": "Feature",
  "properties": {
    "iso:country": "GB",
    "wof:name": "WV4 5LG",
    "wof:placetype": "postalcode"
  },
  "geometry": {"coordinates":[-2.156174,52.553342],"type":"Point"}
}
