{
  "type": "Feature",
  "properties": {
    "iso:country":"GB",
    "wof:name":"WV4 5LG",
    "wof:placetype":"postalcode"
},
  "geometry": {"coordinates":[-2.15617417832189,52.55334235758681],"type":"Point"}
}