{
  "type": "Feature",
  "properties": {
    "iso:country":"GB",
    "wof:name":"PA1 2DJ",
    "wof:placetype":"postalcode"
},
  "geometry": {"coordinates":[-4.42885947109005,55.84516801850901],"type":"Point"}
}