{
  "type": "Feature",
  "properties": {
    "iso:country": "GB",
    "wof:name": "PA1 2DJ",
    "wof:placetype": "postalcode"
  },
  "geometry": {"coordinates":[-4.428701,55.845166],"type":"Point"}
}
