{
  "type": "Feature",
  "properties": {
    "iso:country":"GB",
    "wof:name":"BN13 2PU",
    "wof:placetype":"postalcode"
},
  "geometry": {"coordinates":[-0.41238316867782,50.83702685377773],"type":"Point"}
}