{
  "type": "Feature",
  "properties": {
    "date:inception_lower": "1992-08-01",
    "date:inception_upper": "1992-08-01",
    "iso:country": "GB",
    "wof:name": "CH7 1EQ",
    "wof:placetype": "postalcode"
  },
  "geometry": {"coordinates":[-3.131306,53.159411],"type":"Point"}
}
