{
  "type": "Feature",
  "properties": {
    "iso:country":"GB",
    "wof:name":"CH7 1EQ",
    "wof:placetype":"postalcode"
},
  "geometry": {"coordinates":[-3.13130615906243,53.1594113166871],"type":"Point"}
}