{
  "type": "Feature",
  "properties": {
    "date:inception_lower": "1990-02-01",
    "date:inception_upper": "1990-02-01",
    "iso:country": "GB",
    "wof:name": "TW18 4EZ",
    "wof:placetype": "postalcode"
  },
  "geometry": {"coordinates":[-0.506453,51.434402],"type":"Point"}
}
