{
  "type": "Feature",
  "properties": {
    "iso:country": "GB",
    "wof:name": "KA6 7EE",
    "wof:placetype": "postalcode"
  },
  "geometry": {"coordinates":[-4.467067,55.420297],"type":"Point"}
}
