{
  "type": "Feature",
  "properties": {
    "date:inception_lower":"2007-02-01",
    "date:inception_upper":"2007-02-28",
    "iso:country":"GB",
    "wof:name":"PR9 8EQ",
    "wof:placetype":"postalcode"
},
  "geometry": {"coordinates":[-2.899422,53.663965],"type":"Point"}
}