{
  "type": "Feature",
  "properties": {
    "iso:country":"GB",
    "wof:name":"PR9 8EQ",
    "wof:placetype":"postalcode"
},
  "geometry": {"coordinates":[-2.89942179736927,53.66396469919233],"type":"Point"}
}