{
  "type": "Feature",
  "properties": {
    "iso:country": "GB",
    "wof:name": "PR9 8EQ",
    "wof:placetype": "postalcode"
  },
  "geometry": {"coordinates":[-2.899422,53.663965],"type":"Point"}
}
