{
  "type": "Feature",
  "properties": {
    "date:inception_lower": "2024-07-01",
    "date:inception_upper": "2024-07-01",
    "iso:country": "GB",
    "wof:name": "BL1 2FU",
    "wof:placetype": "postalcode"
  },
  "geometry": {"coordinates":[-2.430083,53.581764],"type":"Point"}
}
