{
  "type": "Feature",
  "properties": {
    "iso:country": "GB",
    "wof:name": "NW1 8YD",
    "wof:placetype": "postalcode"
  },
  "geometry": {"coordinates":[-0.155887,51.540091],"type":"Point"}
}
