{
  "type": "Feature",
  "properties": {
    "iso:country":"GB",
    "wof:name":"NW1 8YD",
    "wof:placetype":"postalcode"
},
  "geometry": {"coordinates":[-0.15588732087702,51.54009116329405],"type":"Point"}
}