{
  "type": "Feature",
  "properties": {
    "iso:country": "GB",
    "wof:name": "WF10 5FQ",
    "wof:placetype": "postalcode"
  },
  "geometry": {"coordinates":[-1.372015,53.713247],"type":"Point"}
}
