{
  "type": "Feature",
  "properties": {
    "date:inception_lower": "2022-10-01",
    "date:inception_upper": "2022-10-01",
    "iso:country": "GB",
    "wof:name": "ME13 9NL",
    "wof:placetype": "postalcode"
  },
  "geometry": {"coordinates":[0.947937,51.283322],"type":"Point"}
}
