{
  "type": "Feature",
  "properties": {
    "iso:country":"GB",
    "wof:name":"ME13 9NL",
    "wof:placetype":"postalcode"
},
  "geometry": {"coordinates":[0.9479064302489,51.28331942980847],"type":"Point"}
}