{
  "type": "Feature",
  "properties": {
    "date:inception_lower":"1980-01-01",
    "date:inception_upper":"1980-01-31",
    "iso:country":"GB",
    "wof:name":"LE12 5PQ",
    "wof:placetype":"postalcode"
},
  "geometry": {"coordinates":[-1.252331,52.820009],"type":"Point"}
}