{
  "type": "Feature",
  "properties": {
    "iso:country": "GB",
    "wof:name": "LE12 5PQ",
    "wof:placetype": "postalcode"
  },
  "geometry": {"coordinates":[-1.252331,52.820009],"type":"Point"}
}
