{
  "type": "Feature",
  "properties": {
    "iso:country":"GB",
    "wof:name":"LE12 5PQ",
    "wof:placetype":"postalcode"
},
  "geometry": {"coordinates":[-1.25233145572748,52.82000883116578],"type":"Point"}
}