{
  "type": "Feature",
  "properties": {
    "iso:country":"GB",
    "wof:name":"BA4 5LX",
    "wof:placetype":"postalcode"
},
  "geometry": {"coordinates":[-2.54148046845057,51.19068305815986],"type":"Point"}
}