{
  "type": "Feature",
  "properties": {
    "iso:country":"GB",
    "wof:name":"S12 3LL",
    "wof:placetype":"postalcode"
},
  "geometry": {"coordinates":[-1.4321055180512,53.34097383102738],"type":"Point"}
}