{
  "type": "Feature",
  "properties": {
    "iso:country":"GB",
    "wof:name":"SK17 0HW",
    "wof:placetype":"postalcode"
},
  "geometry": {"coordinates":[-1.83330292322417,53.14194610055485],"type":"Point"}
}