{
  "type": "Feature",
  "properties": {
    "iso:country":"GB",
    "wof:name":"FK2 9FJ",
    "wof:placetype":"postalcode"
},
  "geometry": {"coordinates":[-3.7769585785617,56.01019630267118],"type":"Point"}
}