{
  "type": "Feature",
  "properties": {
    "date:inception_lower":"2008-08-01",
    "date:inception_upper":"2008-08-31",
    "iso:country":"GB",
    "wof:name":"FK2 9FJ",
    "wof:placetype":"postalcode"
},
  "geometry": {"coordinates":[-3.776959,56.010196],"type":"Point"}
}