{
  "type": "Feature",
  "properties": {
    "iso:country":"GB",
    "wof:name":"WD6 5PY",
    "wof:placetype":"postalcode"
},
  "geometry": {"coordinates":[-0.26355823205145,51.66592608812265],"type":"Point"}
}