{
  "type": "Feature",
  "properties": {
    "iso:country": "GB",
    "wof:name": "B31 2GF",
    "wof:placetype": "postalcode"
  },
  "geometry": {"coordinates":[-1.990116,52.393897],"type":"Point"}
}
