{
  "type": "Feature",
  "properties": {
    "iso:country": "GB",
    "wof:name": "DE24 8HH",
    "wof:placetype": "postalcode"
  },
  "geometry": {"coordinates":[-1.453103,52.916922],"type":"Point"}
}
