{
  "type": "Feature",
  "properties": {
    "iso:country":"GB",
    "wof:name":"DE24 8HH",
    "wof:placetype":"postalcode"
},
  "geometry": {"coordinates":[-1.45310317910595,52.91692200735829],"type":"Point"}
}