{
  "type": "Feature",
  "properties": {
    "iso:country": "GB",
    "wof:name": "DL11 6ET",
    "wof:placetype": "postalcode"
  },
  "geometry": {"coordinates":[-2.007824,54.411058],"type":"Point"}
}
