{
  "type": "Feature",
  "properties": {
    "iso:country":"GB",
    "wof:name":"DL11 6ET",
    "wof:placetype":"postalcode"
},
  "geometry": {"coordinates":[-2.0078241484535,54.41105824271336],"type":"Point"}
}