{
  "type": "Feature",
  "properties": {
    "iso:country":"GB",
    "wof:name":"BA9 9AE",
    "wof:placetype":"postalcode"
},
  "geometry": {"coordinates":[-2.41231958958588,51.05568092363703],"type":"Point"}
}