{
  "type": "Feature",
  "properties": {
    "date:inception_lower": "2017-04-01",
    "date:inception_upper": "2017-04-01",
    "iso:country": "GB",
    "wof:name": "TF10 9BF",
    "wof:placetype": "postalcode"
  },
  "geometry": {"coordinates":[-2.367234,52.753487],"type":"Point"}
}
