{
  "type": "Feature",
  "properties": {
    "date:inception_lower": "1997-06-01",
    "date:inception_upper": "1997-06-01",
    "iso:country": "GB",
    "wof:name": "S32 1AJ",
    "wof:placetype": "postalcode"
  },
  "geometry": {"coordinates":[-1.649514,53.332857],"type":"Point"}
}
