{
  "type": "Feature",
  "properties": {
    "iso:country":"GB",
    "wof:name":"S32 1AJ",
    "wof:placetype":"postalcode"
},
  "geometry": {"coordinates":[-1.64951364200548,53.33285715309692],"type":"Point"}
}