{
  "type": "Feature",
  "properties": {
    "iso:country": "GB",
    "wof:name": "S32 1AJ",
    "wof:placetype": "postalcode"
  },
  "geometry": {"coordinates":[-1.649514,53.332857],"type":"Point"}
}
