{
  "type": "Feature",
  "properties": {
    "date:inception_lower":"1980-01-01",
    "date:inception_upper":"1980-01-31",
    "iso:country":"GB",
    "wof:name":"RH11 9NJ",
    "wof:placetype":"postalcode"
},
  "geometry": {"coordinates":[-0.201219,51.098183],"type":"Point"}
}