{
  "type": "Feature",
  "properties": {
    "date:inception_lower": "1994-05-01",
    "date:inception_upper": "1994-05-01",
    "iso:country": "GB",
    "wof:name": "BA1 4PA",
    "wof:placetype": "postalcode"
  },
  "geometry": {"coordinates":[-2.398128,51.399573],"type":"Point"}
}
