{
  "type": "Feature",
  "properties": {
    "iso:country":"GB",
    "wof:name":"BA1 4PA",
    "wof:placetype":"postalcode"
},
  "geometry": {"coordinates":[-2.39812766060419,51.39957261636295],"type":"Point"}
}