{
  "type": "Feature",
  "properties": {
    "iso:country":"GB",
    "wof:name":"SA4 3US",
    "wof:placetype":"postalcode"
},
  "geometry": {"coordinates":[-4.08183936491965,51.62368349004546],"type":"Point"}
}