{
  "type": "Feature",
  "properties": {
    "iso:country": "GB",
    "wof:name": "SA4 3US",
    "wof:placetype": "postalcode"
  },
  "geometry": {"coordinates":[-4.081839,51.623683],"type":"Point"}
}
