{
  "type": "Feature",
  "properties": {
    "iso:country": "GB",
    "wof:name": "DA12 4NR",
    "wof:placetype": "postalcode"
  },
  "geometry": {"coordinates":[0.394031,51.42159],"type":"Point"}
}
