{
  "type": "Feature",
  "properties": {
    "iso:country": "GB",
    "wof:name": "HU3 1QU",
    "wof:placetype": "postalcode"
  },
  "geometry": {"coordinates":[-0.351569,53.752913],"type":"Point"}
}
