{
  "type": "Feature",
  "properties": {
    "date:inception_lower":"1980-01-01",
    "date:inception_upper":"1980-01-31",
    "iso:country":"GB",
    "wof:name":"WD3 4LZ",
    "wof:placetype":"postalcode"
},
  "geometry": {"coordinates":[-0.454926,51.673482],"type":"Point"}
}