{
  "type": "Feature",
  "properties": {
    "iso:country": "GB",
    "wof:name": "WD3 4LZ",
    "wof:placetype": "postalcode"
  },
  "geometry": {"coordinates":[-0.454926,51.673482],"type":"Point"}
}
