{
  "type": "Feature",
  "properties": {
    "iso:country":"GB",
    "wof:name":"WS1 3HN",
    "wof:placetype":"postalcode"
},
  "geometry": {"coordinates":[-1.97953682629508,52.56998527669001],"type":"Point"}
}