{
  "type": "Feature",
  "properties": {
    "iso:country": "GB",
    "wof:name": "WS1 3HN",
    "wof:placetype": "postalcode"
  },
  "geometry": {"coordinates":[-1.979537,52.569985],"type":"Point"}
}
