{
  "type": "Feature",
  "properties": {
    "iso:country":"GB",
    "wof:name":"LL55 3PD",
    "wof:placetype":"postalcode"
},
  "geometry": {"coordinates":[-4.15279330530612,53.14641889887626],"type":"Point"}
}