{
  "type": "Feature",
  "properties": {
    "iso:country":"GB",
    "wof:name":"IV30 6RE",
    "wof:placetype":"postalcode"
},
  "geometry": {"coordinates":[-3.29195226220189,57.63882160936537],"type":"Point"}
}