{
  "type": "Feature",
  "properties": {
    "iso:country":"GB",
    "wof:name":"LS12 2SD",
    "wof:placetype":"postalcode"
},
  "geometry": {"coordinates":[-1.61471097120902,53.80610394031461],"type":"Point"}
}