{
  "type": "Feature",
  "properties": {
    "date:inception_lower": "1981-06-01",
    "date:inception_upper": "1981-06-01",
    "iso:country": "GB",
    "wof:name": "TN23 3LD",
    "wof:placetype": "postalcode"
  },
  "geometry": {"coordinates":[0.846642,51.149509],"type":"Point"}
}
