{
  "type": "Feature",
  "properties": {
    "date:inception_lower": "2007-04-01",
    "date:inception_upper": "2007-04-01",
    "iso:country": "GB",
    "wof:name": "NR30 9SD",
    "wof:placetype": "postalcode"
  },
  "geometry": {"coordinates":[1.725253,52.605994],"type":"Point"}
}
