{
  "type": "Feature",
  "properties": {
    "iso:country":"GB",
    "wof:name":"TW20 8BF",
    "wof:placetype":"postalcode"
},
  "geometry": {"coordinates":[-0.53367213492,51.42407185410139],"type":"Point"}
}