{
  "type": "Feature",
  "properties": {
    "iso:country":"GB",
    "wof:name":"NW11 7YE",
    "wof:placetype":"postalcode"
},
  "geometry": {"coordinates":[-0.19882985638573,51.5828516217897],"type":"Point"}
}