{
  "type": "Feature",
  "properties": {
    "iso:country":"GB",
    "wof:name":"HU9 4BW",
    "wof:placetype":"postalcode"
},
  "geometry": {"coordinates":[-0.25739813189843,53.77407242712933],"type":"Point"}
}