{
  "type": "Feature",
  "properties": {
    "iso:country": "GB",
    "wof:name": "HU9 4BW",
    "wof:placetype": "postalcode"
  },
  "geometry": {"coordinates":[-0.257398,53.774072],"type":"Point"}
}
