{
  "type": "Feature",
  "properties": {
    "iso:country":"GB",
    "wof:name":"TA20 4PW",
    "wof:placetype":"postalcode"
},
  "geometry": {"coordinates":[-2.88825936165877,50.81223805859395],"type":"Point"}
}