{
  "type": "Feature",
  "properties": {
    "iso:country": "GB",
    "wof:name": "TA20 4PW",
    "wof:placetype": "postalcode"
  },
  "geometry": {"coordinates":[-2.888259,50.812238],"type":"Point"}
}
