{
  "type": "Feature",
  "properties": {
    "iso:country":"GB",
    "wof:name":"EH22 2NX",
    "wof:placetype":"postalcode"
},
  "geometry": {"coordinates":[-2.99913571319603,55.89810950489179],"type":"Point"}
}