{
  "type": "Feature",
  "properties": {
    "iso:country": "GB",
    "wof:name": "EH22 2NX",
    "wof:placetype": "postalcode"
  },
  "geometry": {"coordinates":[-2.999136,55.89811],"type":"Point"}
}
