{
  "type": "Feature",
  "properties": {
    "date:inception_lower": "1980-01-01",
    "date:inception_upper": "1980-01-01",
    "iso:country": "GB",
    "wof:name": "NN8 4LR",
    "wof:placetype": "postalcode"
  },
  "geometry": {"coordinates":[-0.700867,52.302728],"type":"Point"}
}
