{
  "type": "Feature",
  "properties": {
    "date:inception_lower": "2000-12-01",
    "date:inception_upper": "2000-12-01",
    "iso:country": "GB",
    "wof:name": "SL8 5SW",
    "wof:placetype": "postalcode"
  },
  "geometry": {"coordinates":[-0.71447,51.58126],"type":"Point"}
}
