{
  "type": "Feature",
  "properties": {
    "iso:country":"GB",
    "wof:name":"SL8 5SW",
    "wof:placetype":"postalcode"
},
  "geometry": {"coordinates":[-0.71446954173545,51.58126033025383],"type":"Point"}
}