{
  "type": "Feature",
  "properties": {
    "iso:country":"GB",
    "wof:name":"B43 5JU",
    "wof:placetype":"postalcode"
},
  "geometry": {"coordinates":[-1.94526807992806,52.54188121415883],"type":"Point"}
}