{
  "type": "Feature",
  "properties": {
    "iso:country":"GB",
    "wof:name":"WN1 1PF",
    "wof:placetype":"postalcode"
},
  "geometry": {"coordinates":[-2.63130051874718,53.54593538191246],"type":"Point"}
}