{
  "type": "Feature",
  "properties": {
    "date:inception_lower": "1980-01-01",
    "date:inception_upper": "1980-01-01",
    "iso:country": "GB",
    "wof:name": "WN1 1PF",
    "wof:placetype": "postalcode"
  },
  "geometry": {"coordinates":[-2.6313,53.545935],"type":"Point"}
}
