{
  "type": "Feature",
  "properties": {
    "iso:country":"GB",
    "wof:name":"PE21 9QL",
    "wof:placetype":"postalcode"
},
  "geometry": {"coordinates":[-0.03760089207144,52.98862655992315],"type":"Point"}
}