{
  "type": "Feature",
  "properties": {
    "iso:country": "GB",
    "wof:name": "PE21 9QL",
    "wof:placetype": "postalcode"
  },
  "geometry": {"coordinates":[-0.037601,52.988627],"type":"Point"}
}
