{
  "type": "Feature",
  "properties": {
    "date:inception_lower": "2004-09-01",
    "date:inception_upper": "2004-09-01",
    "iso:country": "GB",
    "wof:name": "G31 3LS",
    "wof:placetype": "postalcode"
  },
  "geometry": {"coordinates":[-4.203041,55.86318],"type":"Point"}
}
