{
  "type": "Feature",
  "properties": {
    "iso:country":"GB",
    "wof:name":"G31 3LS",
    "wof:placetype":"postalcode"
},
  "geometry": {"coordinates":[-4.20304138107553,55.86318007337844],"type":"Point"}
}