{
  "type": "Feature",
  "properties": {
    "date:inception_lower":"2017-05-01",
    "date:inception_upper":"2017-05-31",
    "iso:country":"GB",
    "wof:name":"BA9 0AJ",
    "wof:placetype":"postalcode"
},
  "geometry": {"coordinates":[-2.409923,51.057347],"type":"Point"}
}