{
  "type": "Feature",
  "properties": {
    "iso:country":"GB",
    "wof:name":"BA6 8LW",
    "wof:placetype":"postalcode"
},
  "geometry": {"coordinates":[-2.64387511227345,51.13485371952544],"type":"Point"}
}