{
  "type": "Feature",
  "properties": {
    "iso:country":"GB",
    "wof:name":"W1T 2LR",
    "wof:placetype":"postalcode"
},
  "geometry": {"coordinates":[-0.13433991201423,51.51830337884967],"type":"Point"}
}