{
  "type": "Feature",
  "properties": {
    "iso:country":"GB",
    "wof:name":"M26 2RF",
    "wof:placetype":"postalcode"
},
  "geometry": {"coordinates":[-2.31420387756673,53.56531901299579],"type":"Point"}
}