{
  "type": "Feature",
  "properties": {
    "iso:country": "GB",
    "wof:name": "SW3 5PU",
    "wof:placetype": "postalcode"
  },
  "geometry": {"coordinates":[-0.16798,51.486002],"type":"Point"}
}
