{
  "type": "Feature",
  "properties": {
    "iso:country":"GB",
    "wof:name":"SW3 5PU",
    "wof:placetype":"postalcode"
},
  "geometry": {"coordinates":[-0.16797992911224,51.48600204477466],"type":"Point"}
}