{
  "type": "Feature",
  "properties": {
    "iso:country":"GB",
    "wof:name":"CR0 4HX",
    "wof:placetype":"postalcode"
},
  "geometry": {"coordinates":[-0.1068758231673,51.36708367376168],"type":"Point"}
}