{
  "type": "Feature",
  "properties": {
    "iso:country": "GB",
    "wof:name": "CR0 4HX",
    "wof:placetype": "postalcode"
  },
  "geometry": {"coordinates":[-0.106876,51.367084],"type":"Point"}
}
