{
  "type": "Feature",
  "properties": {
    "iso:country":"GB",
    "wof:name":"CH46 6AJ",
    "wof:placetype":"postalcode"
},
  "geometry": {"coordinates":[-3.11509135633303,53.4006821961833],"type":"Point"}
}