{
  "type": "Feature",
  "properties": {
    "iso:country":"GB",
    "wof:name":"NW10 8SW",
    "wof:placetype":"postalcode"
},
  "geometry": {"coordinates":[-0.25551867354596,51.54157897997781],"type":"Point"}
}