{
  "type": "Feature",
  "properties": {
    "iso:country": "GB",
    "wof:name": "CV34 6PY",
    "wof:placetype": "postalcode"
  },
  "geometry": {"coordinates":[-1.612219,52.273018],"type":"Point"}
}
