{
  "type": "Feature",
  "properties": {
    "date:inception_lower": "1980-01-01",
    "date:inception_upper": "1980-01-01",
    "iso:country": "GB",
    "wof:name": "ME18 5JT",
    "wof:placetype": "postalcode"
  },
  "geometry": {"coordinates":[0.35471,51.251673],"type":"Point"}
}
