{
  "type": "Feature",
  "properties": {
    "iso:country": "GB",
    "wof:name": "ME18 5JT",
    "wof:placetype": "postalcode"
  },
  "geometry": {"coordinates":[0.35536,51.251193],"type":"Point"}
}
