{
  "type": "Feature",
  "properties": {
    "iso:country":"GB",
    "wof:name":"ME18 5JT",
    "wof:placetype":"postalcode"
},
  "geometry": {"coordinates":[0.35535969382727,51.25119339397542],"type":"Point"}
}