{
  "type": "Feature",
  "properties": {
    "iso:country":"GB",
    "wof:name":"NW2 5DP",
    "wof:placetype":"postalcode"
},
  "geometry": {"coordinates":[-0.2307959975051,51.54952669985511],"type":"Point"}
}