{
  "type": "Feature",
  "properties": {
    "iso:country": "GB",
    "wof:name": "RH15 0YY",
    "wof:placetype": "postalcode"
  },
  "geometry": {"coordinates":[-0.110127,50.944234],"type":"Point"}
}
