{
  "type": "Feature",
  "properties": {
    "date:inception_lower": "2019-02-01",
    "date:inception_upper": "2019-02-01",
    "iso:country": "GB",
    "wof:name": "RH15 0YY",
    "wof:placetype": "postalcode"
  },
  "geometry": {"coordinates":[-0.109642,50.944613],"type":"Point"}
}
