{
  "type": "Feature",
  "properties": {
    "iso:country":"GB",
    "wof:name":"NE25 8QA",
    "wof:placetype":"postalcode"
},
  "geometry": {"coordinates":[-1.44102456529268,55.03910540792618],"type":"Point"}
}