{
  "type": "Feature",
  "properties": {
    "iso:country":"GB",
    "wof:name":"DL13 2EW",
    "wof:placetype":"postalcode"
},
  "geometry": {"coordinates":[-2.01176305876826,54.76050854275312],"type":"Point"}
}