{
  "type": "Feature",
  "properties": {
    "iso:country": "GB",
    "wof:name": "FK8 1JD",
    "wof:placetype": "postalcode"
  },
  "geometry": {"coordinates":[-3.951517,56.127332],"type":"Point"}
}
