{
  "type": "Feature",
  "properties": {
    "iso:country":"GB",
    "wof:name":"G66 4NF",
    "wof:placetype":"postalcode"
},
  "geometry": {"coordinates":[-4.14801038319536,55.92699157680503],"type":"Point"}
}