{
  "type": "Feature",
  "properties": {
    "date:inception_lower": "1995-07-01",
    "date:inception_upper": "1995-07-01",
    "iso:country": "GB",
    "wof:name": "RG42 6HT",
    "wof:placetype": "postalcode"
  },
  "geometry": {"coordinates":[-0.725273,51.452425],"type":"Point"}
}
