{
  "type": "Feature",
  "properties": {
    "iso:country":"GB",
    "wof:name":"RG42 6HT",
    "wof:placetype":"postalcode"
},
  "geometry": {"coordinates":[-0.72527263396497,51.4524247725481],"type":"Point"}
}