{
  "type": "Feature",
  "properties": {
    "iso:country":"GB",
    "wof:name":"LS26 8WP",
    "wof:placetype":"postalcode"
},
  "geometry": {"coordinates":[-1.4381783240749,53.75559522941604],"type":"Point"}
}