{
  "type": "Feature",
  "properties": {
    "date:inception_lower": "1998-12-01",
    "date:inception_upper": "1998-12-01",
    "iso:country": "GB",
    "wof:name": "LS26 8WP",
    "wof:placetype": "postalcode"
  },
  "geometry": {"coordinates":[-1.438178,53.755595],"type":"Point"}
}
