{
  "type": "Feature",
  "properties": {
    "date:inception_lower": "1995-12-01",
    "date:inception_upper": "1995-12-01",
    "iso:country": "GB",
    "wof:name": "WN2 5RY",
    "wof:placetype": "postalcode"
  },
  "geometry": {"coordinates":[-2.591582,53.508297],"type":"Point"}
}
