{
  "type": "Feature",
  "properties": {
    "iso:country":"GB",
    "wof:name":"WN2 5RY",
    "wof:placetype":"postalcode"
},
  "geometry": {"coordinates":[-2.59158246501547,53.50829692312402],"type":"Point"}
}