{
  "type": "Feature",
  "properties": {
    "iso:country":"GB",
    "wof:name":"CR0 6JN",
    "wof:placetype":"postalcode"
},
  "geometry": {"coordinates":[-0.08208844577203,51.38647355108483],"type":"Point"}
}