{
  "type": "Feature",
  "properties": {
    "iso:country": "GB",
    "wof:name": "L23 0UH",
    "wof:placetype": "postalcode"
  },
  "geometry": {"coordinates":[-3.018301,53.486789],"type":"Point"}
}
