{
  "type": "Feature",
  "properties": {
    "iso:country":"GB",
    "wof:name":"L23 0UH",
    "wof:placetype":"postalcode"
},
  "geometry": {"coordinates":[-3.0183012375248,53.48678884901238],"type":"Point"}
}