{
  "type": "Feature",
  "properties": {
    "date:inception_lower": "1995-12-01",
    "date:inception_upper": "1995-12-01",
    "iso:country": "GB",
    "wof:name": "LL11 2SJ",
    "wof:placetype": "postalcode"
  },
  "geometry": {"coordinates":[-2.992384,53.051348],"type":"Point"}
}
