{
  "type": "Feature",
  "properties": {
    "iso:country": "GB",
    "wof:name": "LL11 2SJ",
    "wof:placetype": "postalcode"
  },
  "geometry": {"coordinates":[-2.992384,53.051348],"type":"Point"}
}
