{
  "type": "Feature",
  "properties": {
    "iso:country":"GB",
    "wof:name":"LL11 2SJ",
    "wof:placetype":"postalcode"
},
  "geometry": {"coordinates":[-2.99238391383115,53.05134833052437],"type":"Point"}
}