{
  "type": "Feature",
  "properties": {
    "iso:country": "GB",
    "wof:name": "SE28 0DT",
    "wof:placetype": "postalcode"
  },
  "geometry": {"coordinates":[0.088405,51.497975],"type":"Point"}
}
