{
  "type": "Feature",
  "properties": {
    "date:inception_lower": "1998-06-01",
    "date:inception_upper": "1998-06-01",
    "iso:country": "GB",
    "wof:name": "SE28 0DT",
    "wof:placetype": "postalcode"
  },
  "geometry": {"coordinates":[0.088405,51.497975],"type":"Point"}
}
