{
  "type": "Feature",
  "properties": {
    "iso:country":"GB",
    "wof:name":"CB24 9LU",
    "wof:placetype":"postalcode"
},
  "geometry": {"coordinates":[0.11259301999719,52.24549742759794],"type":"Point"}
}