{
  "type": "Feature",
  "properties": {
    "iso:country":"GB",
    "wof:name":"BS25 5RP",
    "wof:placetype":"postalcode"
},
  "geometry": {"coordinates":[-2.8300987822524,51.33177531786475],"type":"Point"}
}