{
  "type": "Feature",
  "properties": {
    "iso:country": "GB",
    "wof:name": "BS25 5RP",
    "wof:placetype": "postalcode"
  },
  "geometry": {"coordinates":[-2.830099,51.331775],"type":"Point"}
}
