{
  "type": "Feature",
  "properties": {
    "iso:country":"GB",
    "wof:name":"G22 5HE",
    "wof:placetype":"postalcode"
},
  "geometry": {"coordinates":[-4.24928583875183,55.88269973429583],"type":"Point"}
}