{
  "type": "Feature",
  "properties": {
    "date:inception_lower":"1994-05-01",
    "date:inception_upper":"1994-05-31",
    "iso:country":"GB",
    "wof:name":"M35 9RB",
    "wof:placetype":"postalcode"
},
  "geometry": {"coordinates":[-2.151583,53.507248],"type":"Point"}
}