{
  "type": "Feature",
  "properties": {
    "iso:country":"GB",
    "wof:name":"CO5 8HD",
    "wof:placetype":"postalcode"
},
  "geometry": {"coordinates":[0.92956749755815,51.78243801665761],"type":"Point"}
}