{
  "type": "Feature",
  "properties": {
    "iso:country": "GB",
    "wof:name": "CO5 8HD",
    "wof:placetype": "postalcode"
  },
  "geometry": {"coordinates":[0.929568,51.782438],"type":"Point"}
}
