{
  "type": "Feature",
  "properties": {
    "date:inception_lower": "1996-12-01",
    "date:inception_upper": "1996-12-01",
    "iso:country": "GB",
    "wof:name": "SO30 2XN",
    "wof:placetype": "postalcode"
  },
  "geometry": {"coordinates":[-1.301672,50.932739],"type":"Point"}
}
