{
  "type": "Feature",
  "properties": {
    "iso:country":"GB",
    "wof:name":"B66 3JE",
    "wof:placetype":"postalcode"
},
  "geometry": {"coordinates":[-1.95306252591666,52.49148715038555],"type":"Point"}
}