{
  "type": "Feature",
  "properties": {
    "iso:country":"GB",
    "wof:name":"W1W 6DR",
    "wof:placetype":"postalcode"
},
  "geometry": {"coordinates":[-0.14004293550811,51.51948204464092],"type":"Point"}
}