{
  "type": "Feature",
  "properties": {
    "date:inception_lower": "1991-01-01",
    "date:inception_upper": "1991-01-01",
    "iso:country": "GB",
    "wof:name": "LL29 9ER",
    "wof:placetype": "postalcode"
  },
  "geometry": {"coordinates":[-3.685798,53.290514],"type":"Point"}
}
