{
  "type": "Feature",
  "properties": {
    "iso:country":"GB",
    "wof:name":"TR10 8QH",
    "wof:placetype":"postalcode"
},
  "geometry": {"coordinates":[-5.11484689396752,50.16991338923967],"type":"Point"}
}