{
  "type": "Feature",
  "properties": {
    "date:inception_lower":"1980-01-01",
    "date:inception_upper":"1980-01-31",
    "iso:country":"GB",
    "wof:name":"TR10 8QH",
    "wof:placetype":"postalcode"
},
  "geometry": {"coordinates":[-5.114847,50.169913],"type":"Point"}
}