{
  "type": "Feature",
  "properties": {
    "date:inception_lower":"1980-01-01",
    "date:inception_upper":"1980-01-31",
    "iso:country":"GB",
    "wof:name":"IG7 5AS",
    "wof:placetype":"postalcode"
},
  "geometry": {"coordinates":[0.073107,51.617328],"type":"Point"}
}