{
  "type": "Feature",
  "properties": {
    "iso:country":"GB",
    "wof:name":"CF44 8BZ",
    "wof:placetype":"postalcode"
},
  "geometry": {"coordinates":[-3.46702808416534,51.71646805621707],"type":"Point"}
}