{
  "type": "Feature",
  "properties": {
    "iso:country": "GB",
    "wof:name": "CF44 8BZ",
    "wof:placetype": "postalcode"
  },
  "geometry": {"coordinates":[-3.467028,51.716468],"type":"Point"}
}
