{
  "type": "Feature",
  "properties": {
    "iso:country":"GB",
    "wof:name":"NE10 8NQ",
    "wof:placetype":"postalcode"
},
  "geometry": {"coordinates":[-1.55328808095421,54.93707155520788],"type":"Point"}
}