{
  "type": "Feature",
  "properties": {
    "iso:country":"GB",
    "wof:name":"KA13 7LW",
    "wof:placetype":"postalcode"
},
  "geometry": {"coordinates":[-4.68677114048208,55.65474434373973],"type":"Point"}
}