{
  "type": "Feature",
  "properties": {
    "iso:country":"GB",
    "wof:name":"NW2 3UU",
    "wof:placetype":"postalcode"
},
  "geometry": {"coordinates":[-0.21568537603881,51.55418971965774],"type":"Point"}
}