{
  "type": "Feature",
  "properties": {
    "date:inception_lower": "1980-01-01",
    "date:inception_upper": "1980-01-01",
    "iso:country": "GB",
    "wof:name": "NW2 3UU",
    "wof:placetype": "postalcode"
  },
  "geometry": {"coordinates":[-0.215685,51.55419],"type":"Point"}
}
