{
  "type": "Feature",
  "properties": {
    "iso:country":"GB",
    "wof:name":"TW1 3JS",
    "wof:placetype":"postalcode"
},
  "geometry": {"coordinates":[-0.32792396801572,51.44790803997886],"type":"Point"}
}