{
  "type": "Feature",
  "properties": {
    "date:inception_lower":"2000-06-01",
    "date:inception_upper":"2000-06-30",
    "iso:country":"GB",
    "wof:name":"CO10 2PA",
    "wof:placetype":"postalcode"
},
  "geometry": {"coordinates":[0.754851,52.044772],"type":"Point"}
}