{
  "type": "Feature",
  "properties": {
    "iso:country": "GB",
    "wof:name": "HA1 2BG",
    "wof:placetype": "postalcode"
  },
  "geometry": {"coordinates":[-0.331323,51.584848],"type":"Point"}
}
