{
  "type": "Feature",
  "properties": {
    "iso:country": "GB",
    "wof:name": "TQ2 5HG",
    "wof:placetype": "postalcode"
  },
  "geometry": {"coordinates":[-3.536992,50.464574],"type":"Point"}
}
