{
  "type": "Feature",
  "properties": {
    "date:inception_lower": "2009-06-01",
    "date:inception_upper": "2009-06-01",
    "iso:country": "GB",
    "wof:name": "CH66 1QD",
    "wof:placetype": "postalcode"
  },
  "geometry": {"coordinates":[-2.940408,53.287388],"type":"Point"}
}
