{
  "type": "Feature",
  "properties": {
    "iso:country":"GB",
    "wof:name":"CH66 1QD",
    "wof:placetype":"postalcode"
},
  "geometry": {"coordinates":[-2.94040851417216,53.2873877776593],"type":"Point"}
}