{
  "type": "Feature",
  "properties": {
    "iso:country": "GB",
    "wof:name": "MK2 2UT",
    "wof:placetype": "postalcode"
  },
  "geometry": {"coordinates":[-0.730512,51.996754],"type":"Point"}
}
