{
  "type": "Feature",
  "properties": {
    "iso:country":"GB",
    "wof:name":"MK2 2UT",
    "wof:placetype":"postalcode"
},
  "geometry": {"coordinates":[-0.73051237027178,51.99675388593293],"type":"Point"}
}