{
  "type": "Feature",
  "properties": {
    "date:inception_lower": "1980-01-01",
    "date:inception_upper": "1980-01-01",
    "iso:country": "GB",
    "wof:name": "TW15 3ER",
    "wof:placetype": "postalcode"
  },
  "geometry": {"coordinates":[-0.473508,51.441288],"type":"Point"}
}
