{
  "type": "Feature",
  "properties": {
    "date:inception_lower": "1993-08-01",
    "date:inception_upper": "1993-08-01",
    "iso:country": "GB",
    "wof:name": "PE15 9SF",
    "wof:placetype": "postalcode"
  },
  "geometry": {"coordinates":[0.079297,52.543144],"type":"Point"}
}
