{
  "type": "Feature",
  "properties": {
    "iso:country":"GB",
    "wof:name":"FY4 4UB",
    "wof:placetype":"postalcode"
},
  "geometry": {"coordinates":[-3.00014474143795,53.79952059827314],"type":"Point"}
}