{
  "type": "Feature",
  "properties": {
    "date:inception_lower": "2003-01-01",
    "date:inception_upper": "2003-01-01",
    "iso:country": "GB",
    "wof:name": "NN12 6BU",
    "wof:placetype": "postalcode"
  },
  "geometry": {"coordinates":[-0.98832,52.131309],"type":"Point"}
}
