{
  "type": "Feature",
  "properties": {
    "date:inception_lower": "2004-05-01",
    "date:inception_upper": "2004-05-01",
    "iso:country": "GB",
    "wof:name": "N14 6PW",
    "wof:placetype": "postalcode"
  },
  "geometry": {"coordinates":[-0.127368,51.631254],"type":"Point"}
}
