{
  "type": "Feature",
  "properties": {
    "iso:country": "GB",
    "wof:name": "SA10 9AR",
    "wof:placetype": "postalcode"
  },
  "geometry": {"coordinates":[-3.707944,51.76613],"type":"Point"}
}
