{
  "type": "Feature",
  "properties": {
    "iso:country":"GB",
    "wof:name":"SA10 9AR",
    "wof:placetype":"postalcode"
},
  "geometry": {"coordinates":[-3.70794445970208,51.76613009471632],"type":"Point"}
}