{
  "type": "Feature",
  "properties": {
    "date:inception_lower":"1980-01-01",
    "date:inception_upper":"1980-01-31",
    "iso:country":"GB",
    "wof:name":"WR9 0RD",
    "wof:placetype":"postalcode"
},
  "geometry": {"coordinates":[-2.167927,52.263019],"type":"Point"}
}