{
  "type": "Feature",
  "properties": {
    "iso:country":"GB",
    "wof:name":"WR9 0RD",
    "wof:placetype":"postalcode"
},
  "geometry": {"coordinates":[-2.16792714870254,52.26301865703277],"type":"Point"}
}