{
  "type": "Feature",
  "properties": {
    "iso:country": "GB",
    "wof:name": "NE5 2FF",
    "wof:placetype": "postalcode"
  },
  "geometry": {"coordinates":[-1.695104,54.988244],"type":"Point"}
}
