{
  "type": "Feature",
  "properties": {
    "iso:country": "GB",
    "wof:name": "EX19 8QW",
    "wof:placetype": "postalcode"
  },
  "geometry": {"coordinates":[-4.030457,50.891533],"type":"Point"}
}
