{
  "type": "Feature",
  "properties": {
    "iso:country":"GB",
    "wof:name":"EX19 8QW",
    "wof:placetype":"postalcode"
},
  "geometry": {"coordinates":[-4.03045700653631,50.89153263331469],"type":"Point"}
}