{
  "type": "Feature",
  "properties": {
    "iso:country":"GB",
    "wof:name":"B35 7AG",
    "wof:placetype":"postalcode"
},
  "geometry": {"coordinates":[-1.7918635033803,52.51057921097006],"type":"Point"}
}