{
  "type": "Feature",
  "properties": {
    "iso:country":"GB",
    "wof:name":"S18 4BA",
    "wof:placetype":"postalcode"
},
  "geometry": {"coordinates":[-1.43744403424571,53.30506189372532],"type":"Point"}
}