{
  "type": "Feature",
  "properties": {
    "date:inception_lower": "1997-06-01",
    "date:inception_upper": "1997-06-01",
    "iso:country": "GB",
    "wof:name": "S18 4BA",
    "wof:placetype": "postalcode"
  },
  "geometry": {"coordinates":[-1.437442,53.305107],"type":"Point"}
}
