{
  "type": "Feature",
  "properties": {
    "iso:country":"GB",
    "wof:name":"BL1 5DN",
    "wof:placetype":"postalcode"
},
  "geometry": {"coordinates":[-2.49119471358083,53.58023677753809],"type":"Point"}
}