{
  "type": "Feature",
  "properties": {
    "date:inception_lower": "1998-06-01",
    "date:inception_upper": "1998-06-01",
    "iso:country": "GB",
    "wof:name": "YO51 9PT",
    "wof:placetype": "postalcode"
  },
  "geometry": {"coordinates":[-1.362392,54.063413],"type":"Point"}
}
