{
  "type": "Feature",
  "properties": {
    "iso:country":"GB",
    "wof:name":"M32 8PD",
    "wof:placetype":"postalcode"
},
  "geometry": {"coordinates":[-2.30022830096327,53.44671661628232],"type":"Point"}
}