{
  "type": "Feature",
  "properties": {
    "date:inception_lower":"1980-01-01",
    "date:inception_upper":"1980-01-31",
    "iso:country":"GB",
    "wof:name":"M32 8PD",
    "wof:placetype":"postalcode"
},
  "geometry": {"coordinates":[-2.300228,53.446717],"type":"Point"}
}