{
  "type": "Feature",
  "properties": {
    "iso:country": "GB",
    "wof:name": "M32 8PD",
    "wof:placetype": "postalcode"
  },
  "geometry": {"coordinates":[-2.300228,53.446717],"type":"Point"}
}
