{
  "type": "Feature",
  "properties": {
    "iso:country":"GB",
    "wof:name":"NG1 1EN",
    "wof:placetype":"postalcode"
},
  "geometry": {"coordinates":[-1.14086639837646,52.95427857956645],"type":"Point"}
}