{
  "type": "Feature",
  "properties": {
    "iso:country": "GB",
    "wof:name": "NG1 1EN",
    "wof:placetype": "postalcode"
  },
  "geometry": {"coordinates":[-1.140866,52.954279],"type":"Point"}
}
