{
  "type": "Feature",
  "properties": {
    "iso:country":"GB",
    "wof:name":"CT11 9PY",
    "wof:placetype":"postalcode"
},
  "geometry": {"coordinates":[1.40595821531338,51.33433201361924],"type":"Point"}
}