{
  "type": "Feature",
  "properties": {
    "date:inception_lower": "2012-10-01",
    "date:inception_upper": "2012-10-01",
    "iso:country": "GB",
    "wof:name": "G12 9PH",
    "wof:placetype": "postalcode"
  },
  "geometry": {"coordinates":[-4.297805,55.878176],"type":"Point"}
}
