{
  "type": "Feature",
  "properties": {
    "iso:country": "GB",
    "wof:name": "RG6 1PG",
    "wof:placetype": "postalcode"
  },
  "geometry": {"coordinates":[-0.931185,51.445904],"type":"Point"}
}
