{
  "type": "Feature",
  "properties": {
    "date:inception_lower": "1980-01-01",
    "date:inception_upper": "1980-01-01",
    "iso:country": "GB",
    "wof:name": "RG6 1PG",
    "wof:placetype": "postalcode"
  },
  "geometry": {"coordinates":[-0.931185,51.445904],"type":"Point"}
}
