{
  "type": "Feature",
  "properties": {
    "iso:country":"GB",
    "wof:name":"EN5 2TR",
    "wof:placetype":"postalcode"
},
  "geometry": {"coordinates":[-0.2073872103785,51.65218727742252],"type":"Point"}
}