{
  "type": "Feature",
  "properties": {
    "iso:country":"GB",
    "wof:name":"DE24 9HL",
    "wof:placetype":"postalcode"
},
  "geometry": {"coordinates":[-1.48376177356748,52.88751989269863],"type":"Point"}
}