{
  "type": "Feature",
  "properties": {
    "iso:country": "GB",
    "wof:name": "DE24 9HL",
    "wof:placetype": "postalcode"
  },
  "geometry": {"coordinates":[-1.486673,52.887308],"type":"Point"}
}
