{
  "type": "Feature",
  "properties": {
    "iso:country": "GB",
    "wof:name": "WV14 7HG",
    "wof:placetype": "postalcode"
  },
  "geometry": {"coordinates":[-2.06069,52.567173],"type":"Point"}
}
