{
  "type": "Feature",
  "properties": {
    "date:inception_lower": "1991-09-01",
    "date:inception_upper": "1991-09-01",
    "iso:country": "GB",
    "wof:name": "WV14 7HG",
    "wof:placetype": "postalcode"
  },
  "geometry": {"coordinates":[-2.06069,52.567173],"type":"Point"}
}
