{
  "type": "Feature",
  "properties": {
    "iso:country":"GB",
    "wof:name":"WV14 7HG",
    "wof:placetype":"postalcode"
},
  "geometry": {"coordinates":[-2.06069586266408,52.56715749394943],"type":"Point"}
}