{
  "type": "Feature",
  "properties": {
    "date:inception_lower": "1980-01-01",
    "date:inception_upper": "1980-01-01",
    "iso:country": "GB",
    "wof:name": "PE23 5SQ",
    "wof:placetype": "postalcode"
  },
  "geometry": {"coordinates":[0.166996,53.197885],"type":"Point"}
}
