{
  "type": "Feature",
  "properties": {
    "iso:country": "GB",
    "wof:name": "HD9 4HN",
    "wof:placetype": "postalcode"
  },
  "geometry": {"coordinates":[-1.864309,53.58691],"type":"Point"}
}
