{
  "type": "Feature",
  "properties": {
    "iso:country":"GB",
    "wof:name":"HD9 4HN",
    "wof:placetype":"postalcode"
},
  "geometry": {"coordinates":[-1.87364438520077,53.58721082874154],"type":"Point"}
}