{
  "type": "Feature",
  "properties": {
    "iso:country": "GB",
    "wof:name": "M43 7SL",
    "wof:placetype": "postalcode"
  },
  "geometry": {"coordinates":[-2.156157,53.488213],"type":"Point"}
}
