{
  "type": "Feature",
  "properties": {
    "iso:country":"GB",
    "wof:name":"DH6 3AE",
    "wof:placetype":"postalcode"
},
  "geometry": {"coordinates":[-1.42562710155,54.75190731096311],"type":"Point"}
}