{
  "type": "Feature",
  "properties": {
    "date:inception_lower": "1997-06-01",
    "date:inception_upper": "1997-06-01",
    "iso:country": "GB",
    "wof:name": "S20 5EB",
    "wof:placetype": "postalcode"
  },
  "geometry": {"coordinates":[-1.360711,53.325467],"type":"Point"}
}
