{
  "type": "Feature",
  "properties": {
    "iso:country": "GB",
    "wof:name": "S20 5EB",
    "wof:placetype": "postalcode"
  },
  "geometry": {"coordinates":[-1.360711,53.325467],"type":"Point"}
}
