{
  "type": "Feature",
  "properties": {
    "date:inception_lower": "1980-01-01",
    "date:inception_upper": "1980-01-01",
    "iso:country": "GB",
    "wof:name": "LL36 0DW",
    "wof:placetype": "postalcode"
  },
  "geometry": {"coordinates":[-4.087866,52.580082],"type":"Point"}
}
