{
  "type": "Feature",
  "properties": {
    "date:inception_lower": "1980-01-01",
    "date:inception_upper": "1980-01-01",
    "iso:country": "GB",
    "wof:name": "KY1 3DH",
    "wof:placetype": "postalcode"
  },
  "geometry": {"coordinates":[-3.134519,56.12758],"type":"Point"}
}
