{
  "type": "Feature",
  "properties": {
    "iso:country":"GB",
    "wof:name":"KY1 3DH",
    "wof:placetype":"postalcode"
},
  "geometry": {"coordinates":[-3.13451870988051,56.12758046464523],"type":"Point"}
}