{
  "type": "Feature",
  "properties": {
    "iso:country":"GB",
    "wof:name":"LA14 1XW",
    "wof:placetype":"postalcode"
},
  "geometry": {"coordinates":[-3.23284820800013,54.11370772790278],"type":"Point"}
}