{
  "type": "Feature",
  "properties": {
    "iso:country": "GB",
    "wof:name": "LA14 1XW",
    "wof:placetype": "postalcode"
  },
  "geometry": {"coordinates":[-3.232845,54.113716],"type":"Point"}
}
