{
  "type": "Feature",
  "properties": {
    "iso:country":"GB",
    "wof:name":"FY4 1NB",
    "wof:placetype":"postalcode"
},
  "geometry": {"coordinates":[-3.05757011625649,53.7887810018507],"type":"Point"}
}