{
  "type": "Feature",
  "properties": {
    "iso:country": "GB",
    "wof:name": "IP4 5AQ",
    "wof:placetype": "postalcode"
  },
  "geometry": {"coordinates":[1.182253,52.053478],"type":"Point"}
}
