{
  "type": "Feature",
  "properties": {
    "iso:country": "GB",
    "wof:name": "DN41 8HB",
    "wof:placetype": "postalcode"
  },
  "geometry": {"coordinates":[-0.249102,53.572558],"type":"Point"}
}
