{
  "type": "Feature",
  "properties": {
    "date:inception_lower": "1997-06-01",
    "date:inception_upper": "1997-06-01",
    "iso:country": "GB",
    "wof:name": "RG21 4PP",
    "wof:placetype": "postalcode"
  },
  "geometry": {"coordinates":[-1.070243,51.265838],"type":"Point"}
}
