{
  "type": "Feature",
  "properties": {
    "iso:country": "GB",
    "wof:name": "RG21 4PP",
    "wof:placetype": "postalcode"
  },
  "geometry": {"coordinates":[-1.070243,51.265838],"type":"Point"}
}
