{
  "type": "Feature",
  "properties": {
    "iso:country":"GB",
    "wof:name":"RG21 4PP",
    "wof:placetype":"postalcode"
},
  "geometry": {"coordinates":[-1.07024273179661,51.26583841007835],"type":"Point"}
}