{
  "type": "Feature",
  "properties": {
    "iso:country": "GB",
    "wof:name": "CR2 9HE",
    "wof:placetype": "postalcode"
  },
  "geometry": {"coordinates":[-0.075287,51.329321],"type":"Point"}
}
