{
  "type": "Feature",
  "properties": {
    "iso:country":"GB",
    "wof:name":"SW1E 5BH",
    "wof:placetype":"postalcode"
},
  "geometry": {"coordinates":[-0.14160387295117,51.49742117698364],"type":"Point"}
}