{
  "type": "Feature",
  "properties": {
    "iso:country":"GB",
    "wof:name":"ST4 5PZ",
    "wof:placetype":"postalcode"
},
  "geometry": {"coordinates":[-2.20070902423425,52.99297078292652],"type":"Point"}
}