{
  "type": "Feature",
  "properties": {
    "iso:country":"GB",
    "wof:name":"RH10 8HL",
    "wof:placetype":"postalcode"
},
  "geometry": {"coordinates":[-0.18483594750494,51.12409032988196],"type":"Point"}
}