{
  "type": "Feature",
  "properties": {
    "iso:country": "GB",
    "wof:name": "RH10 8HL",
    "wof:placetype": "postalcode"
  },
  "geometry": {"coordinates":[-0.184836,51.12409],"type":"Point"}
}
