{
  "type": "Feature",
  "properties": {
    "iso:country":"GB",
    "wof:name":"TF2 6DB",
    "wof:placetype":"postalcode"
},
  "geometry": {"coordinates":[-2.46275790492162,52.69357256120897],"type":"Point"}
}