{
  "type": "Feature",
  "properties": {
    "iso:country": "GB",
    "wof:name": "TF2 6DB",
    "wof:placetype": "postalcode"
  },
  "geometry": {"coordinates":[-2.462758,52.693573],"type":"Point"}
}
