{
  "type": "Feature",
  "properties": {
    "date:inception_lower":"1980-01-01",
    "date:inception_upper":"1980-01-31",
    "iso:country":"GB",
    "wof:name":"NR12 9PE",
    "wof:placetype":"postalcode"
},
  "geometry": {"coordinates":[1.520005,52.770946],"type":"Point"}
}