{
  "type": "Feature",
  "properties": {
    "iso:country":"GB",
    "wof:name":"NR12 9PE",
    "wof:placetype":"postalcode"
},
  "geometry": {"coordinates":[1.51998319666857,52.77091796474713],"type":"Point"}
}