{
  "type": "Feature",
  "properties": {
    "iso:country": "GB",
    "wof:name": "G78 3RA",
    "wof:placetype": "postalcode"
  },
  "geometry": {"coordinates":[-4.420097,55.788218],"type":"Point"}
}
