{
  "type": "Feature",
  "properties": {
    "iso:country":"GB",
    "wof:name":"CO9 2TH",
    "wof:placetype":"postalcode"
},
  "geometry": {"coordinates":[0.6500009430689,51.94907337270737],"type":"Point"}
}