{
  "type": "Feature",
  "properties": {
    "date:inception_lower":"1980-01-01",
    "date:inception_upper":"1980-01-31",
    "iso:country":"GB",
    "wof:name":"WR2 6LE",
    "wof:placetype":"postalcode"
},
  "geometry": {"coordinates":[-2.256665,52.22581],"type":"Point"}
}