{
  "type": "Feature",
  "properties": {
    "iso:country":"GB",
    "wof:name":"LA22 0PW",
    "wof:placetype":"postalcode"
},
  "geometry": {"coordinates":[-3.02071624483186,54.37980767320515],"type":"Point"}
}