{
  "type": "Feature",
  "properties": {
    "date:inception_lower": "1980-01-01",
    "date:inception_upper": "1980-01-01",
    "iso:country": "GB",
    "wof:name": "LA22 0PW",
    "wof:placetype": "postalcode"
  },
  "geometry": {"coordinates":[-3.020766,54.379824],"type":"Point"}
}
