{
  "type": "Feature",
  "properties": {
    "iso:country": "GB",
    "wof:name": "LA22 0PW",
    "wof:placetype": "postalcode"
  },
  "geometry": {"coordinates":[-3.020502,54.379736],"type":"Point"}
}
