{
  "type": "Feature",
  "properties": {
    "iso:country":"GB",
    "wof:name":"CF64 4NN",
    "wof:placetype":"postalcode"
},
  "geometry": {"coordinates":[-3.20824583896149,51.4346626001687],"type":"Point"}
}