{
  "type": "Feature",
  "properties": {
    "iso:country": "GB",
    "wof:name": "DY5 3YQ",
    "wof:placetype": "postalcode"
  },
  "geometry": {"coordinates":[-2.130746,52.488358],"type":"Point"}
}
