{
  "type": "Feature",
  "properties": {
    "iso:country":"GB",
    "wof:name":"DY5 3YQ",
    "wof:placetype":"postalcode"
},
  "geometry": {"coordinates":[-2.1307457909875,52.48835825805102],"type":"Point"}
}