{
  "type": "Feature",
  "properties": {
    "date:inception_lower": "1996-12-01",
    "date:inception_upper": "1996-12-01",
    "iso:country": "GB",
    "wof:name": "IP25 7HU",
    "wof:placetype": "postalcode"
  },
  "geometry": {"coordinates":[0.810039,52.57987],"type":"Point"}
}
