{
  "type": "Feature",
  "properties": {
    "iso:country":"GB",
    "wof:name":"IP25 7HU",
    "wof:placetype":"postalcode"
},
  "geometry": {"coordinates":[0.81003924888172,52.57987030543409],"type":"Point"}
}