{
  "type": "Feature",
  "properties": {
    "date:inception_lower": "2002-11-01",
    "date:inception_upper": "2002-11-01",
    "iso:country": "GB",
    "wof:name": "ML9 3FE",
    "wof:placetype": "postalcode"
  },
  "geometry": {"coordinates":[-3.9446,55.732023],"type":"Point"}
}
