{
  "type": "Feature",
  "properties": {
    "date:inception_lower":"1980-01-01",
    "date:inception_upper":"1980-01-31",
    "iso:country":"GB",
    "wof:name":"CH6 6LH",
    "wof:placetype":"postalcode"
},
  "geometry": {"coordinates":[-3.189283,53.276931],"type":"Point"}
}