{
  "type": "Feature",
  "properties": {
    "iso:country": "GB",
    "wof:name": "CH6 6LH",
    "wof:placetype": "postalcode"
  },
  "geometry": {"coordinates":[-3.189283,53.276931],"type":"Point"}
}
