{
  "type": "Feature",
  "properties": {
    "iso:country":"GB",
    "wof:name":"SK9 2LA",
    "wof:placetype":"postalcode"
},
  "geometry": {"coordinates":[-2.22457791119645,53.33399521758184],"type":"Point"}
}