{
  "type": "Feature",
  "properties": {
    "iso:country":"GB",
    "wof:name":"LS8 1AB",
    "wof:placetype":"postalcode"
},
  "geometry": {"coordinates":[-1.51652211042312,53.84339034866482],"type":"Point"}
}