{
  "type": "Feature",
  "properties": {
    "iso:country":"GB",
    "wof:name":"WF1 3NN",
    "wof:placetype":"postalcode"
},
  "geometry": {"coordinates":[-1.49584956829428,53.6865077517248],"type":"Point"}
}