{
  "type": "Feature",
  "properties": {
    "iso:country":"GB",
    "wof:name":"CT11 8BA",
    "wof:placetype":"postalcode"
},
  "geometry": {"coordinates":[1.4308469423848,51.34302294373703],"type":"Point"}
}