{
  "type": "Feature",
  "properties": {
    "date:inception_lower": "1980-01-01",
    "date:inception_upper": "1980-01-01",
    "iso:country": "GB",
    "wof:name": "CT11 8BA",
    "wof:placetype": "postalcode"
  },
  "geometry": {"coordinates":[1.430847,51.343023],"type":"Point"}
}
