{
  "type": "Feature",
  "properties": {
    "iso:country":"GB",
    "wof:name":"RM13 7LB",
    "wof:placetype":"postalcode"
},
  "geometry": {"coordinates":[0.19024966283504,51.54026300645069],"type":"Point"}
}