{
  "type": "Feature",
  "properties": {
    "iso:country":"GB",
    "wof:name":"LE2 9UU",
    "wof:placetype":"postalcode"
},
  "geometry": {"coordinates":[-1.14706366361377,52.58076170352317],"type":"Point"}
}