{
  "type": "Feature",
  "properties": {
    "iso:country": "GB",
    "wof:name": "LE2 9UU",
    "wof:placetype": "postalcode"
  },
  "geometry": {"coordinates":[-1.147083,52.580879],"type":"Point"}
}
