{
  "type": "Feature",
  "properties": {
    "date:inception_lower":"2002-06-01",
    "date:inception_upper":"2002-06-30",
    "iso:country":"GB",
    "wof:name":"LE2 9UU",
    "wof:placetype":"postalcode"
},
  "geometry": {"coordinates":[-1.147083,52.580879],"type":"Point"}
}