{
  "type": "Feature",
  "properties": {
    "iso:country":"GB",
    "wof:name":"ST7 4BZ",
    "wof:placetype":"postalcode"
},
  "geometry": {"coordinates":[-2.23306658404867,53.09225045957819],"type":"Point"}
}