{
  "type": "Feature",
  "properties": {
    "iso:country":"GB",
    "wof:name":"YO16 6RG",
    "wof:placetype":"postalcode"
},
  "geometry": {"coordinates":[-0.18219599225589,54.09421840554761],"type":"Point"}
}