{
  "type": "Feature",
  "properties": {
    "iso:country": "GB",
    "wof:name": "LA1 4AD",
    "wof:placetype": "postalcode"
  },
  "geometry": {"coordinates":[-2.78926,54.039502],"type":"Point"}
}
