{
  "type": "Feature",
  "properties": {
    "iso:country":"GB",
    "wof:name":"AB56 1UA",
    "wof:placetype":"postalcode"
},
  "geometry": {"coordinates":[-2.9498902331589,57.68105503756253],"type":"Point"}
}