{
  "type": "Feature",
  "properties": {
    "iso:country": "GB",
    "wof:name": "BD16 3DJ",
    "wof:placetype": "postalcode"
  },
  "geometry": {"coordinates":[-1.820555,53.852525],"type":"Point"}
}
