{
  "type": "Feature",
  "properties": {
    "date:inception_lower":"1980-01-01",
    "date:inception_upper":"1980-01-31",
    "iso:country":"GB",
    "wof:name":"BD16 3DJ",
    "wof:placetype":"postalcode"
},
  "geometry": {"coordinates":[-1.820555,53.852525],"type":"Point"}
}