{
  "type": "Feature",
  "properties": {
    "iso:country":"GB",
    "wof:name":"BD16 3DJ",
    "wof:placetype":"postalcode"
},
  "geometry": {"coordinates":[-1.82055507185164,53.85252533805097],"type":"Point"}
}