{
  "type": "Feature",
  "properties": {
    "date:inception_lower": "1980-01-01",
    "date:inception_upper": "1980-01-01",
    "iso:country": "GB",
    "wof:name": "BA3 2SA",
    "wof:placetype": "postalcode"
  },
  "geometry": {"coordinates":[-2.495488,51.289196],"type":"Point"}
}
