{
  "type": "Feature",
  "properties": {
    "iso:country":"GB",
    "wof:name":"BA3 2SA",
    "wof:placetype":"postalcode"
},
  "geometry": {"coordinates":[-2.49548817725244,51.28919581852511],"type":"Point"}
}