{
  "type": "Feature",
  "properties": {
    "iso:country":"GB",
    "wof:name":"NN10 9TN",
    "wof:placetype":"postalcode"
},
  "geometry": {"coordinates":[-0.60723354597515,52.29163641579542],"type":"Point"}
}