{
  "type": "Feature",
  "properties": {
    "iso:country": "GB",
    "wof:name": "AB54 4JS",
    "wof:placetype": "postalcode"
  },
  "geometry": {"coordinates":[-2.878846,57.273804],"type":"Point"}
}
