{
  "type": "Feature",
  "properties": {
    "iso:country": "GB",
    "wof:name": "BS49 5BJ",
    "wof:placetype": "postalcode"
  },
  "geometry": {"coordinates":[-2.800271,51.373451],"type":"Point"}
}
