{
  "type": "Feature",
  "properties": {
    "iso:country":"GB",
    "wof:name":"E11 2TF",
    "wof:placetype":"postalcode"
},
  "geometry": {"coordinates":[0.0211522928653,51.5787474541019],"type":"Point"}
}