{
  "type": "Feature",
  "properties": {
    "iso:country": "GB",
    "wof:name": "YO25 9BZ",
    "wof:placetype": "postalcode"
  },
  "geometry": {"coordinates":[-0.56548,53.935439],"type":"Point"}
}
