{
  "type": "Feature",
  "properties": {
    "iso:country":"GB",
    "wof:name":"YO25 9BZ",
    "wof:placetype":"postalcode"
},
  "geometry": {"coordinates":[-0.56547957474917,53.9354390544848],"type":"Point"}
}