{
  "type": "Feature",
  "properties": {
    "iso:country": "GB",
    "wof:name": "DN1 3JU",
    "wof:placetype": "postalcode"
  },
  "geometry": {"coordinates":[-1.132214,53.520747],"type":"Point"}
}
