{
  "type": "Feature",
  "properties": {
    "iso:country":"GB",
    "wof:name":"DN1 3JU",
    "wof:placetype":"postalcode"
},
  "geometry": {"coordinates":[-1.13248682420011,53.5205576717989],"type":"Point"}
}