{
  "type": "Feature",
  "properties": {
    "iso:country": "GB",
    "wof:name": "L33 2DE",
    "wof:placetype": "postalcode"
  },
  "geometry": {"coordinates":[-2.891656,53.492367],"type":"Point"}
}
