{
  "type": "Feature",
  "properties": {
    "iso:country":"GB",
    "wof:name":"DT11 7QT",
    "wof:placetype":"postalcode"
},
  "geometry": {"coordinates":[-2.15894575408573,50.85850579532587],"type":"Point"}
}