{
  "type": "Feature",
  "properties": {
    "iso:country": "GB",
    "wof:name": "WF10 4AQ",
    "wof:placetype": "postalcode"
  },
  "geometry": {"coordinates":[-1.34938,53.724002],"type":"Point"}
}
