{
  "type": "Feature",
  "properties": {
    "iso:country":"GB",
    "wof:name":"WF10 4AQ",
    "wof:placetype":"postalcode"
},
  "geometry": {"coordinates":[-1.34937967239018,53.72400218246214],"type":"Point"}
}