{
  "type": "Feature",
  "properties": {
    "date:inception_lower": "1980-01-01",
    "date:inception_upper": "1980-01-01",
    "iso:country": "GB",
    "wof:name": "NG12 1DE",
    "wof:placetype": "postalcode"
  },
  "geometry": {"coordinates":[-1.027413,52.950905],"type":"Point"}
}
