{
  "type": "Feature",
  "properties": {
    "iso:country":"GB",
    "wof:name":"NG12 1DE",
    "wof:placetype":"postalcode"
},
  "geometry": {"coordinates":[-1.02741273662592,52.95090548043141],"type":"Point"}
}