{
  "type": "Feature",
  "properties": {
    "iso:country": "GB",
    "wof:name": "DL1 4PD",
    "wof:placetype": "postalcode"
  },
  "geometry": {"coordinates":[-1.526776,54.520547],"type":"Point"}
}
