{
  "type": "Feature",
  "properties": {
    "iso:country":"GB",
    "wof:name":"LL15 2YE",
    "wof:placetype":"postalcode"
},
  "geometry": {"coordinates":[-3.27313889965721,53.09523190660012],"type":"Point"}
}