{
  "type": "Feature",
  "properties": {
    "iso:country": "GB",
    "wof:name": "CF24 3QW",
    "wof:placetype": "postalcode"
  },
  "geometry": {"coordinates":[-3.16109,51.488614],"type":"Point"}
}
