{
  "type": "Feature",
  "properties": {
    "iso:country": "GB",
    "wof:name": "UB3 1PG",
    "wof:placetype": "postalcode"
  },
  "geometry": {"coordinates":[-0.439424,51.498165],"type":"Point"}
}
