{
  "type": "Feature",
  "properties": {
    "iso:country":"GB",
    "wof:name":"UB3 1PG",
    "wof:placetype":"postalcode"
},
  "geometry": {"coordinates":[-0.43942424915796,51.49816524472858],"type":"Point"}
}