{
  "type": "Feature",
  "properties": {
    "date:inception_lower": "1980-01-01",
    "date:inception_upper": "1980-01-01",
    "iso:country": "GB",
    "wof:name": "UB3 1PG",
    "wof:placetype": "postalcode"
  },
  "geometry": {"coordinates":[-0.439708,51.498539],"type":"Point"}
}
