{
  "type": "Feature",
  "properties": {
    "iso:country": "GB",
    "wof:name": "AB51 5RL",
    "wof:placetype": "postalcode"
  },
  "geometry": {"coordinates":[-2.438898,57.233912],"type":"Point"}
}
