{
  "type": "Feature",
  "properties": {
    "iso:country":"GB",
    "wof:name":"AB51 5RL",
    "wof:placetype":"postalcode"
},
  "geometry": {"coordinates":[-2.43839619039421,57.23391931734151],"type":"Point"}
}