{
  "type": "Feature",
  "properties": {
    "iso:country":"GB",
    "wof:name":"TW9 2AJ",
    "wof:placetype":"postalcode"
},
  "geometry": {"coordinates":[-0.28784441305873,51.47368632718129],"type":"Point"}
}