{
  "type": "Feature",
  "properties": {
    "iso:country": "GB",
    "wof:name": "NR3 2EH",
    "wof:placetype": "postalcode"
  },
  "geometry": {"coordinates":[1.270269,52.646955],"type":"Point"}
}
