{
  "type": "Feature",
  "properties": {
    "iso:country":"GB",
    "wof:name":"NR3 2EH",
    "wof:placetype":"postalcode"
},
  "geometry": {"coordinates":[1.27026938611627,52.64695493706004],"type":"Point"}
}