{
  "type": "Feature",
  "properties": {
    "date:inception_lower": "1980-01-01",
    "date:inception_upper": "1980-01-01",
    "iso:country": "GB",
    "wof:name": "WC2E 9DS",
    "wof:placetype": "postalcode"
  },
  "geometry": {"coordinates":[-0.125281,51.511902],"type":"Point"}
}
