{
  "type": "Feature",
  "properties": {
    "iso:country":"GB",
    "wof:name":"WC2E 9DS",
    "wof:placetype":"postalcode"
},
  "geometry": {"coordinates":[-0.1249585132843,51.51193995023124],"type":"Point"}
}