{
  "type": "Feature",
  "properties": {
    "iso:country":"GB",
    "wof:name":"KA7 1DZ",
    "wof:placetype":"postalcode"
},
  "geometry": {"coordinates":[-4.63627126706548,55.46244728248178],"type":"Point"}
}