{
  "type": "Feature",
  "properties": {
    "iso:country": "GB",
    "wof:name": "NE43 7NX",
    "wof:placetype": "postalcode"
  },
  "geometry": {"coordinates":[-1.906524,54.944308],"type":"Point"}
}
