{
  "type": "Feature",
  "properties": {
    "iso:country":"GB",
    "wof:name":"B71 4HR",
    "wof:placetype":"postalcode"
},
  "geometry": {"coordinates":[-1.98826721101438,52.52918150828881],"type":"Point"}
}