{
  "type": "Feature",
  "properties": {
    "iso:country":"GB",
    "wof:name":"N15 3BA",
    "wof:placetype":"postalcode"
},
  "geometry": {"coordinates":[-0.09303849056238,51.58295176528154],"type":"Point"}
}