{
  "type": "Feature",
  "properties": {
    "date:inception_lower":"2006-11-01",
    "date:inception_upper":"2006-11-30",
    "iso:country":"GB",
    "wof:name":"BD22 7AZ",
    "wof:placetype":"postalcode"
},
  "geometry": {"coordinates":[-1.924803,53.846542],"type":"Point"}
}