{
  "type": "Feature",
  "properties": {
    "iso:country":"GB",
    "wof:name":"WA4 2AU",
    "wof:placetype":"postalcode"
},
  "geometry": {"coordinates":[-2.57074239177615,53.37116892714216],"type":"Point"}
}