{
  "type": "Feature",
  "properties": {
    "date:inception_lower":"1984-02-01",
    "date:inception_upper":"1984-02-29",
    "iso:country":"GB",
    "wof:name":"LU2 7LX",
    "wof:placetype":"postalcode"
},
  "geometry": {"coordinates":[-0.407015,51.89896],"type":"Point"}
}