{
  "type": "Feature",
  "properties": {
    "iso:country":"GB",
    "wof:name":"LU2 7LX",
    "wof:placetype":"postalcode"
},
  "geometry": {"coordinates":[-0.40701486163795,51.89895978660375],"type":"Point"}
}