{
  "type": "Feature",
  "properties": {
    "date:inception_lower": "1980-01-01",
    "date:inception_upper": "1980-01-01",
    "iso:country": "GB",
    "wof:name": "NW6 5TE",
    "wof:placetype": "postalcode"
  },
  "geometry": {"coordinates":[-0.193836,51.53588],"type":"Point"}
}
