{
  "type": "Feature",
  "properties": {
    "iso:country": "GB",
    "wof:name": "NW6 5TE",
    "wof:placetype": "postalcode"
  },
  "geometry": {"coordinates":[-0.193836,51.53588],"type":"Point"}
}
