{
  "type": "Feature",
  "properties": {
    "date:inception_lower": "2024-04-01",
    "date:inception_upper": "2024-04-01",
    "iso:country": "GB",
    "wof:name": "NR13 6GQ",
    "wof:placetype": "postalcode"
  },
  "geometry": {"coordinates":[1.371184,52.670628],"type":"Point"}
}
