{
  "type": "Feature",
  "properties": {
    "iso:country": "GB",
    "wof:name": "EH14 5JZ",
    "wof:placetype": "postalcode"
  },
  "geometry": {"coordinates":[-3.300068,55.899055],"type":"Point"}
}
