{
  "type": "Feature",
  "properties": {
    "iso:country":"GB",
    "wof:name":"HP10 8LD",
    "wof:placetype":"postalcode"
},
  "geometry": {"coordinates":[-0.69033255385191,51.63465676233898],"type":"Point"}
}