{
  "type": "Feature",
  "properties": {
    "iso:country": "GB",
    "wof:name": "L24 2TA",
    "wof:placetype": "postalcode"
  },
  "geometry": {"coordinates":[-2.829475,53.344464],"type":"Point"}
}
