{
  "type": "Feature",
  "properties": {
    "date:inception_lower": "1980-01-01",
    "date:inception_upper": "1980-01-01",
    "iso:country": "GB",
    "wof:name": "L24 2TA",
    "wof:placetype": "postalcode"
  },
  "geometry": {"coordinates":[-2.829461,53.344534],"type":"Point"}
}
