{
  "type": "Feature",
  "properties": {
    "iso:country": "GB",
    "wof:name": "HP17 8DY",
    "wof:placetype": "postalcode"
  },
  "geometry": {"coordinates":[-0.925849,51.775031],"type":"Point"}
}
