{
  "type": "Feature",
  "properties": {
    "iso:country":"GB",
    "wof:name":"PE14 0HU",
    "wof:placetype":"postalcode"
},
  "geometry": {"coordinates":[0.16401754747462,52.62244063155061],"type":"Point"}
}