{
  "type": "Feature",
  "properties": {
    "iso:country": "GB",
    "wof:name": "PE14 0HU",
    "wof:placetype": "postalcode"
  },
  "geometry": {"coordinates":[0.164018,52.622441],"type":"Point"}
}
