{
  "type": "Feature",
  "properties": {
    "iso:country":"GB",
    "wof:name":"DL1 3AE",
    "wof:placetype":"postalcode"
},
  "geometry": {"coordinates":[-1.54794774190636,54.5562885410715],"type":"Point"}
}