{
  "type": "Feature",
  "properties": {
    "iso:country":"GB",
    "wof:name":"LS10 1PF",
    "wof:placetype":"postalcode"
},
  "geometry": {"coordinates":[-1.53166404678794,53.78574727862092],"type":"Point"}
}