{
  "type": "Feature",
  "properties": {
    "iso:country":"GB",
    "wof:name":"M9 8PT",
    "wof:placetype":"postalcode"
},
  "geometry": {"coordinates":[-2.22441557146519,53.52290753761081],"type":"Point"}
}