{
  "type": "Feature",
  "properties": {
    "iso:country": "GB",
    "wof:name": "M9 8PT",
    "wof:placetype": "postalcode"
  },
  "geometry": {"coordinates":[-2.224416,53.522908],"type":"Point"}
}
