{
  "type": "Feature",
  "properties": {
    "iso:country":"GB",
    "wof:name":"CW2 8AB",
    "wof:placetype":"postalcode"
},
  "geometry": {"coordinates":[-2.4549713178086,53.08901076867114],"type":"Point"}
}