{
  "type": "Feature",
  "properties": {
    "iso:country":"GB",
    "wof:name":"CV35 0HT",
    "wof:placetype":"postalcode"
},
  "geometry": {"coordinates":[-1.51591195915751,52.15739945142655],"type":"Point"}
}