{
  "type": "Feature",
  "properties": {
    "iso:country": "GB",
    "wof:name": "CV35 0HT",
    "wof:placetype": "postalcode"
  },
  "geometry": {"coordinates":[-1.515912,52.157399],"type":"Point"}
}
