{
  "type": "Feature",
  "properties": {
    "date:inception_lower": "1980-01-01",
    "date:inception_upper": "1980-01-01",
    "iso:country": "GB",
    "wof:name": "NW2 5RE",
    "wof:placetype": "postalcode"
  },
  "geometry": {"coordinates":[-0.217397,51.546665],"type":"Point"}
}
