{
  "type": "Feature",
  "properties": {
    "iso:country": "GB",
    "wof:name": "RH6 0AR",
    "wof:placetype": "postalcode"
  },
  "geometry": {"coordinates":[-0.186819,51.16652],"type":"Point"}
}
