{
  "type": "Feature",
  "properties": {
    "date:inception_lower": "1980-01-01",
    "date:inception_upper": "1980-01-01",
    "iso:country": "GB",
    "wof:name": "RH6 0AR",
    "wof:placetype": "postalcode"
  },
  "geometry": {"coordinates":[-0.186734,51.166141],"type":"Point"}
}
