{
  "type": "Feature",
  "properties": {
    "date:inception_lower":"1980-01-01",
    "date:inception_upper":"1980-01-31",
    "iso:country":"GB",
    "wof:name":"HU10 6LP",
    "wof:placetype":"postalcode"
},
  "geometry": {"coordinates":[-0.437729,53.753483],"type":"Point"}
}