{
  "type": "Feature",
  "properties": {
    "iso:country":"GB",
    "wof:name":"B91 1PL",
    "wof:placetype":"postalcode"
},
  "geometry": {"coordinates":[-1.80920355795918,52.41905430038129],"type":"Point"}
}