{
  "type": "Feature",
  "properties": {
    "date:inception_lower":"1995-07-01",
    "date:inception_upper":"1995-07-31",
    "iso:country":"GB",
    "wof:name":"RG29 1NA",
    "wof:placetype":"postalcode"
},
  "geometry": {"coordinates":[-0.95264,51.253129],"type":"Point"}
}