{
  "type": "Feature",
  "properties": {
    "iso:country": "GB",
    "wof:name": "RG29 1NA",
    "wof:placetype": "postalcode"
  },
  "geometry": {"coordinates":[-0.95264,51.253129],"type":"Point"}
}
