{
  "type": "Feature",
  "properties": {
    "iso:country":"GB",
    "wof:name":"RG29 1NA",
    "wof:placetype":"postalcode"
},
  "geometry": {"coordinates":[-0.95264024858682,51.25312882110871],"type":"Point"}
}