{
  "type": "Feature",
  "properties": {
    "iso:country": "GB",
    "wof:name": "KY4 9BX",
    "wof:placetype": "postalcode"
  },
  "geometry": {"coordinates":[-3.35467,56.11856],"type":"Point"}
}
