{
  "type": "Feature",
  "properties": {
    "iso:country":"GB",
    "wof:name":"NG21 0NA",
    "wof:placetype":"postalcode"
},
  "geometry": {"coordinates":[-1.1522206476849,53.10427615599486],"type":"Point"}
}