{
  "type": "Feature",
  "properties": {
    "date:inception_lower":"2009-02-01",
    "date:inception_upper":"2009-02-28",
    "iso:country":"GB",
    "wof:name":"NR34 9HR",
    "wof:placetype":"postalcode"
},
  "geometry": {"coordinates":[1.574315,52.44703],"type":"Point"}
}