{
  "type": "Feature",
  "properties": {
    "iso:country": "GB",
    "wof:name": "NR34 9HR",
    "wof:placetype": "postalcode"
  },
  "geometry": {"coordinates":[1.574315,52.44703],"type":"Point"}
}
