{
  "type": "Feature",
  "properties": {
    "iso:country": "GB",
    "wof:name": "PH7 4BF",
    "wof:placetype": "postalcode"
  },
  "geometry": {"coordinates":[-3.873205,56.335332],"type":"Point"}
}
