{
  "type": "Feature",
  "properties": {
    "date:inception_lower": "2008-03-01",
    "date:inception_upper": "2008-03-01",
    "iso:country": "GB",
    "wof:name": "PH7 4BF",
    "wof:placetype": "postalcode"
  },
  "geometry": {"coordinates":[-3.873205,56.335332],"type":"Point"}
}
