{
  "type": "Feature",
  "properties": {
    "iso:country":"GB",
    "wof:name":"PH7 4BF",
    "wof:placetype":"postalcode"
},
  "geometry": {"coordinates":[-3.87320516625494,56.3353318410183],"type":"Point"}
}