{
  "type": "Feature",
  "properties": {
    "iso:country":"GB",
    "wof:name":"BL1 8EF",
    "wof:placetype":"postalcode"
},
  "geometry": {"coordinates":[-2.43294133717959,53.59224560810249],"type":"Point"}
}