{
  "type": "Feature",
  "properties": {
    "iso:country":"GB",
    "wof:name":"IP32 7JT",
    "wof:placetype":"postalcode"
},
  "geometry": {"coordinates":[0.74487449966722,52.24529761811167],"type":"Point"}
}