{
  "type": "Feature",
  "properties": {
    "iso:country":"GB",
    "wof:name":"NR17 1YF",
    "wof:placetype":"postalcode"
},
  "geometry": {"coordinates":[1.00086034877466,52.50813280665924],"type":"Point"}
}