{
  "type": "Feature",
  "properties": {
    "iso:country": "GB",
    "wof:name": "NR17 1YF",
    "wof:placetype": "postalcode"
  },
  "geometry": {"coordinates":[1.00086,52.508133],"type":"Point"}
}
