{
  "type": "Feature",
  "properties": {
    "date:inception_lower": "1991-09-01",
    "date:inception_upper": "1991-09-01",
    "iso:country": "GB",
    "wof:name": "NR17 1YF",
    "wof:placetype": "postalcode"
  },
  "geometry": {"coordinates":[1.00086,52.508133],"type":"Point"}
}
