{
  "type": "Feature",
  "properties": {
    "iso:country":"GB",
    "wof:name":"TR18 4QA",
    "wof:placetype":"postalcode"
},
  "geometry": {"coordinates":[-5.54991344104682,50.1142599386429],"type":"Point"}
}