{
  "type": "Feature",
  "properties": {
    "iso:country":"GB",
    "wof:name":"BD23 1DA",
    "wof:placetype":"postalcode"
},
  "geometry": {"coordinates":[-2.01717058493051,53.9601428398359],"type":"Point"}
}