{
  "type": "Feature",
  "properties": {
    "date:inception_lower": "1980-01-01",
    "date:inception_upper": "1980-01-01",
    "iso:country": "GB",
    "wof:name": "BD23 1DA",
    "wof:placetype": "postalcode"
  },
  "geometry": {"coordinates":[-2.017022,53.960229],"type":"Point"}
}
