{
  "type": "Feature",
  "properties": {
    "iso:country":"GB",
    "wof:name":"CW5 6LA",
    "wof:placetype":"postalcode"
},
  "geometry": {"coordinates":[-2.51010979288437,53.07111445594293],"type":"Point"}
}