{
  "type": "Feature",
  "properties": {
    "iso:country": "GB",
    "wof:name": "WA7 5AY",
    "wof:placetype": "postalcode"
  },
  "geometry": {"coordinates":[-2.733577,53.337962],"type":"Point"}
}
