{
  "type": "Feature",
  "properties": {
    "date:inception_lower": "1980-01-01",
    "date:inception_upper": "1980-01-01",
    "iso:country": "GB",
    "wof:name": "S6 1NJ",
    "wof:placetype": "postalcode"
  },
  "geometry": {"coordinates":[-1.509903,53.423655],"type":"Point"}
}
