{
  "type": "Feature",
  "properties": {
    "iso:country": "GB",
    "wof:name": "EN3 5BS",
    "wof:placetype": "postalcode"
  },
  "geometry": {"coordinates":[-0.048517,51.659528],"type":"Point"}
}
