{
  "type": "Feature",
  "properties": {
    "iso:country":"GB",
    "wof:name":"B61 0RB",
    "wof:placetype":"postalcode"
},
  "geometry": {"coordinates":[-2.05754595820423,52.38172301340168],"type":"Point"}
}