{
  "type": "Feature",
  "properties": {
    "date:inception_lower": "1980-01-01",
    "date:inception_upper": "1980-01-01",
    "iso:country": "GB",
    "wof:name": "RM2 5RL",
    "wof:placetype": "postalcode"
  },
  "geometry": {"coordinates":[0.187156,51.591862],"type":"Point"}
}
