{
  "type": "Feature",
  "properties": {
    "iso:country": "GB",
    "wof:name": "NW10 5NS",
    "wof:placetype": "postalcode"
  },
  "geometry": {"coordinates":[-0.229657,51.530922],"type":"Point"}
}
