{
  "type": "Feature",
  "properties": {
    "date:inception_lower": "2024-03-01",
    "date:inception_upper": "2024-03-01",
    "iso:country": "GB",
    "wof:name": "TQ6 0GB",
    "wof:placetype": "postalcode"
  },
  "geometry": {"coordinates":[-3.61031,50.346408],"type":"Point"}
}
