{
  "type": "Feature",
  "properties": {
    "date:inception_lower": "2024-01-01",
    "date:inception_upper": "2024-01-01",
    "iso:country": "GB",
    "wof:name": "EH52 6GN",
    "wof:placetype": "postalcode"
  },
  "geometry": {"coordinates":[-3.470652,55.961165],"type":"Point"}
}
