{
  "type": "Feature",
  "properties": {
    "iso:country":"GB",
    "wof:name":"TN15 9AR",
    "wof:placetype":"postalcode"
},
  "geometry": {"coordinates":[0.28291846096086,51.27146122340195],"type":"Point"}
}