{
  "type": "Feature",
  "properties": {
    "date:inception_lower":"1980-01-01",
    "date:inception_upper":"1980-01-31",
    "iso:country":"GB",
    "wof:name":"TN15 9AR",
    "wof:placetype":"postalcode"
},
  "geometry": {"coordinates":[0.282946,51.271459],"type":"Point"}
}