{
  "type": "Feature",
  "properties": {
    "iso:country": "GB",
    "wof:name": "DL7 0JP",
    "wof:placetype": "postalcode"
  },
  "geometry": {"coordinates":[-1.550975,54.438166],"type":"Point"}
}
