{
  "type": "Feature",
  "properties": {
    "iso:country":"GB",
    "wof:name":"GL55 6DF",
    "wof:placetype":"postalcode"
},
  "geometry": {"coordinates":[-1.77861566762553,52.04558670803003],"type":"Point"}
}