{
  "type": "Feature",
  "properties": {
    "iso:country":"GB",
    "wof:name":"CA28 8JZ",
    "wof:placetype":"postalcode"
},
  "geometry": {"coordinates":[-3.56871930946317,54.52929677460502],"type":"Point"}
}