{
  "type": "Feature",
  "properties": {
    "iso:country": "GB",
    "wof:name": "CA28 8JZ",
    "wof:placetype": "postalcode"
  },
  "geometry": {"coordinates":[-3.56872,54.529305],"type":"Point"}
}
