{
  "type": "Feature",
  "properties": {
    "iso:country":"GB",
    "wof:name":"B63 2QB",
    "wof:placetype":"postalcode"
},
  "geometry": {"coordinates":[-2.10128695260618,52.4669821009829],"type":"Point"}
}