{
  "type": "Feature",
  "properties": {
    "iso:country":"GB",
    "wof:name":"IG11 8RQ",
    "wof:placetype":"postalcode"
},
  "geometry": {"coordinates":[0.07983661707361,51.54300110630581],"type":"Point"}
}