{
  "type": "Feature",
  "properties": {
    "iso:country": "GB",
    "wof:name": "OX33 1LB",
    "wof:placetype": "postalcode"
  },
  "geometry": {"coordinates":[-1.092709,51.75385],"type":"Point"}
}
