{
  "type": "Feature",
  "properties": {
    "iso:country":"GB",
    "wof:name":"TN8 5LS",
    "wof:placetype":"postalcode"
},
  "geometry": {"coordinates":[0.0666049666288,51.1995424757426],"type":"Point"}
}