{
  "type": "Feature",
  "properties": {
    "iso:country":"GB",
    "wof:name":"KY8 3AS",
    "wof:placetype":"postalcode"
},
  "geometry": {"coordinates":[-3.00732858937219,56.18900836991284],"type":"Point"}
}