{
  "type": "Feature",
  "properties": {
    "iso:country":"GB",
    "wof:name":"BD21 3BE",
    "wof:placetype":"postalcode"
},
  "geometry": {"coordinates":[-1.90926076931674,53.87142760624443],"type":"Point"}
}