{
  "type": "Feature",
  "properties": {
    "iso:country":"GB",
    "wof:name":"CA11 9JX",
    "wof:placetype":"postalcode"
},
  "geometry": {"coordinates":[-2.75868503453008,54.67293068708489],"type":"Point"}
}