{
  "type": "Feature",
  "properties": {
    "iso:country":"GB",
    "wof:name":"DE65 5GG",
    "wof:placetype":"postalcode"
},
  "geometry": {"coordinates":[-1.63996381275544,52.87275080658223],"type":"Point"}
}