{
  "type": "Feature",
  "properties": {
    "iso:country": "GB",
    "wof:name": "DE65 5GG",
    "wof:placetype": "postalcode"
  },
  "geometry": {"coordinates":[-1.639964,52.872751],"type":"Point"}
}
