{
  "type": "Feature",
  "properties": {
    "iso:country":"GB",
    "wof:name":"WS10 0PP",
    "wof:placetype":"postalcode"
},
  "geometry": {"coordinates":[-2.00354080915072,52.55692471500867],"type":"Point"}
}