{
  "type": "Feature",
  "properties": {
    "date:inception_lower":"1980-01-01",
    "date:inception_upper":"1980-01-31",
    "iso:country":"GB",
    "wof:name":"WS10 0PP",
    "wof:placetype":"postalcode"
},
  "geometry": {"coordinates":[-2.003541,52.556925],"type":"Point"}
}