{
  "type": "Feature",
  "properties": {
    "iso:country":"GB",
    "wof:name":"DY5 4PH",
    "wof:placetype":"postalcode"
},
  "geometry": {"coordinates":[-2.13769555358625,52.49263856463625],"type":"Point"}
}