{
  "type": "Feature",
  "properties": {
    "date:inception_lower": "1980-01-01",
    "date:inception_upper": "1980-01-01",
    "iso:country": "GB",
    "wof:name": "DY5 4PH",
    "wof:placetype": "postalcode"
  },
  "geometry": {"coordinates":[-2.137675,52.492644],"type":"Point"}
}
