{
  "type": "Feature",
  "properties": {
    "iso:country": "GB",
    "wof:name": "DY5 4PH",
    "wof:placetype": "postalcode"
  },
  "geometry": {"coordinates":[-2.137675,52.492644],"type":"Point"}
}
