{
  "type": "Feature",
  "properties": {
    "iso:country":"GB",
    "wof:name":"S9 1SA",
    "wof:placetype":"postalcode"
},
  "geometry": {"coordinates":[-1.39394809275907,53.41361296864321],"type":"Point"}
}