{
  "type": "Feature",
  "properties": {
    "iso:country":"GB",
    "wof:name":"MK42 9NB",
    "wof:placetype":"postalcode"
},
  "geometry": {"coordinates":[-0.46269408724541,52.12312001482528],"type":"Point"}
}