{
  "type": "Feature",
  "properties": {
    "date:inception_lower": "2020-06-01",
    "date:inception_upper": "2020-06-01",
    "iso:country": "GB",
    "wof:name": "S61 2FD",
    "wof:placetype": "postalcode"
  },
  "geometry": {"coordinates":[-1.437839,53.457827],"type":"Point"}
}
