{
  "type": "Feature",
  "properties": {
    "date:inception_lower": "2005-01-01",
    "date:inception_upper": "2005-01-01",
    "iso:country": "GB",
    "wof:name": "AL2 1UD",
    "wof:placetype": "postalcode"
  },
  "geometry": {"coordinates":[-0.317726,51.723301],"type":"Point"}
}
