{
  "type": "Feature",
  "properties": {
    "date:inception_lower": "1980-01-01",
    "date:inception_upper": "1980-01-01",
    "iso:country": "GB",
    "wof:name": "DA1 5JY",
    "wof:placetype": "postalcode"
  },
  "geometry": {"coordinates":[0.233053,51.455992],"type":"Point"}
}
