{
  "type": "Feature",
  "properties": {
    "iso:country": "GB",
    "wof:name": "G63 9QU",
    "wof:placetype": "postalcode"
  },
  "geometry": {"coordinates":[-4.404141,56.034695],"type":"Point"}
}
