{
  "type": "Feature",
  "properties": {
    "iso:country":"GB",
    "wof:name":"PO14 4LW",
    "wof:placetype":"postalcode"
},
  "geometry": {"coordinates":[-1.2475247949042,50.85667601951204],"type":"Point"}
}