{
  "type": "Feature",
  "properties": {
    "iso:country": "GB",
    "wof:name": "PO14 4LW",
    "wof:placetype": "postalcode"
  },
  "geometry": {"coordinates":[-1.247525,50.856676],"type":"Point"}
}
