{
  "type": "Feature",
  "properties": {
    "date:inception_lower": "2004-05-01",
    "date:inception_upper": "2004-05-01",
    "iso:country": "GB",
    "wof:name": "PO14 4LW",
    "wof:placetype": "postalcode"
  },
  "geometry": {"coordinates":[-1.247525,50.856676],"type":"Point"}
}
