{
  "type": "Feature",
  "properties": {
    "date:inception_lower":"2004-06-01",
    "date:inception_upper":"2004-06-30",
    "iso:country":"GB",
    "wof:name":"G72 0JH",
    "wof:placetype":"postalcode"
},
  "geometry": {"coordinates":[-4.094731,55.769826],"type":"Point"}
}