{
  "type": "Feature",
  "properties": {
    "date:inception_lower": "1980-01-01",
    "date:inception_upper": "1980-01-01",
    "iso:country": "GB",
    "wof:name": "CH7 3DX",
    "wof:placetype": "postalcode"
  },
  "geometry": {"coordinates":[-3.056667,53.172511],"type":"Point"}
}
