{
  "type": "Feature",
  "properties": {
    "date:inception_lower":"1980-01-01",
    "date:inception_upper":"1980-01-31",
    "iso:country":"GB",
    "wof:name":"SW1H 0BH",
    "wof:placetype":"postalcode"
},
  "geometry": {"coordinates":[-0.13291,51.499342],"type":"Point"}
}