{
  "type": "Feature",
  "properties": {
    "date:inception_lower": "2023-08-01",
    "date:inception_upper": "2023-08-01",
    "iso:country": "GB",
    "wof:name": "WN3 6NG",
    "wof:placetype": "postalcode"
  },
  "geometry": {"coordinates":[-2.663359,53.529759],"type":"Point"}
}
