{
  "type": "Feature",
  "properties": {
    "iso:country":"GB",
    "wof:name":"NG6 8LX",
    "wof:placetype":"postalcode"
},
  "geometry": {"coordinates":[-1.1534677118867,53.03081520827752],"type":"Point"}
}