{
  "type": "Feature",
  "properties": {
    "iso:country":"GB",
    "wof:name":"DA2 6LR",
    "wof:placetype":"postalcode"
},
  "geometry": {"coordinates":[0.25196928119698,51.43613297817014],"type":"Point"}
}