{
  "type": "Feature",
  "properties": {
    "iso:country": "GB",
    "wof:name": "UB11 1TD",
    "wof:placetype": "postalcode"
  },
  "geometry": {"coordinates":[-0.438369,51.509239],"type":"Point"}
}
