{
  "type": "Feature",
  "properties": {
    "iso:country": "GB",
    "wof:name": "PR5 5UH",
    "wof:placetype": "postalcode"
  },
  "geometry": {"coordinates":[-2.688798,53.736091],"type":"Point"}
}
