{
  "type": "Feature",
  "properties": {
    "iso:country": "GB",
    "wof:name": "NG8 6DW",
    "wof:placetype": "postalcode"
  },
  "geometry": {"coordinates":[-1.206974,52.980987],"type":"Point"}
}
