{
  "type": "Feature",
  "properties": {
    "iso:country":"GB",
    "wof:name":"NG8 6DW",
    "wof:placetype":"postalcode"
},
  "geometry": {"coordinates":[-1.20697377344616,52.98098708259381],"type":"Point"}
}