{
  "type": "Feature",
  "properties": {
    "iso:country":"GB",
    "wof:name":"ME2 4NZ",
    "wof:placetype":"postalcode"
},
  "geometry": {"coordinates":[0.52052037964416,51.39218100241286],"type":"Point"}
}