{
  "type": "Feature",
  "properties": {
    "iso:country":"GB",
    "wof:name":"NP26 4QF",
    "wof:placetype":"postalcode"
},
  "geometry": {"coordinates":[-2.76184949857895,51.58859267919464],"type":"Point"}
}