{
  "type": "Feature",
  "properties": {
    "iso:country": "GB",
    "wof:name": "NP26 4QF",
    "wof:placetype": "postalcode"
  },
  "geometry": {"coordinates":[-2.761849,51.588593],"type":"Point"}
}
