{
  "type": "Feature",
  "properties": {
    "iso:country":"GB",
    "wof:name":"HG3 4AZ",
    "wof:placetype":"postalcode"
},
  "geometry": {"coordinates":[-1.80488437226327,54.02208199003967],"type":"Point"}
}