{
  "type": "Feature",
  "properties": {
    "iso:country":"GB",
    "wof:name":"NG24 2TU",
    "wof:placetype":"postalcode"
},
  "geometry": {"coordinates":[-0.79740620045105,53.08764676173274],"type":"Point"}
}