{
  "type": "Feature",
  "properties": {
    "date:inception_lower": "1980-01-01",
    "date:inception_upper": "1980-01-01",
    "iso:country": "GB",
    "wof:name": "YO11 2AX",
    "wof:placetype": "postalcode"
  },
  "geometry": {"coordinates":[-0.399564,54.272176],"type":"Point"}
}
