{
  "type": "Feature",
  "properties": {
    "iso:country": "GB",
    "wof:name": "SP11 7DH",
    "wof:placetype": "postalcode"
  },
  "geometry": {"coordinates":[-1.507161,51.195756],"type":"Point"}
}
