{
  "type": "Feature",
  "properties": {
    "iso:country":"GB",
    "wof:name":"SP11 7DH",
    "wof:placetype":"postalcode"
},
  "geometry": {"coordinates":[-1.50716125631145,51.19575607935869],"type":"Point"}
}