{
  "type": "Feature",
  "properties": {
    "date:inception_lower": "1982-06-01",
    "date:inception_upper": "1982-06-01",
    "iso:country": "GB",
    "wof:name": "EH30 9UP",
    "wof:placetype": "postalcode"
  },
  "geometry": {"coordinates":[-3.395478,55.984328],"type":"Point"}
}
