{
  "type": "Feature",
  "properties": {
    "iso:country": "GB",
    "wof:name": "DH4 7RE",
    "wof:placetype": "postalcode"
  },
  "geometry": {"coordinates":[-1.496184,54.872928],"type":"Point"}
}
