{
  "type": "Feature",
  "properties": {
    "date:inception_lower": "1980-01-01",
    "date:inception_upper": "1980-01-01",
    "iso:country": "GB",
    "wof:name": "DH4 7RE",
    "wof:placetype": "postalcode"
  },
  "geometry": {"coordinates":[-1.496184,54.872928],"type":"Point"}
}
