{
  "type": "Feature",
  "properties": {
    "iso:country":"GB",
    "wof:name":"DH4 7RE",
    "wof:placetype":"postalcode"
},
  "geometry": {"coordinates":[-1.49618358948338,54.87292808835159],"type":"Point"}
}