{
  "type": "Feature",
  "properties": {
    "date:inception_lower": "1980-01-01",
    "date:inception_upper": "1980-01-01",
    "iso:country": "GB",
    "wof:name": "SR8 3EX",
    "wof:placetype": "postalcode"
  },
  "geometry": {"coordinates":[-1.33751,54.787585],"type":"Point"}
}
