{
  "type": "Feature",
  "properties": {
    "iso:country": "GB",
    "wof:name": "TS3 6QL",
    "wof:placetype": "postalcode"
  },
  "geometry": {"coordinates":[-1.205342,54.573307],"type":"Point"}
}
