{
  "type": "Feature",
  "properties": {
    "iso:country":"GB",
    "wof:name":"TS3 6QL",
    "wof:placetype":"postalcode"
},
  "geometry": {"coordinates":[-1.20534195825008,54.57330723942714],"type":"Point"}
}