{
  "type": "Feature",
  "properties": {
    "date:inception_lower":"1985-10-01",
    "date:inception_upper":"1985-10-31",
    "iso:country":"GB",
    "wof:name":"TS3 6QL",
    "wof:placetype":"postalcode"
},
  "geometry": {"coordinates":[-1.205342,54.573307],"type":"Point"}
}