{
  "type": "Feature",
  "properties": {
    "iso:country":"GB",
    "wof:name":"NN4 8GT",
    "wof:placetype":"postalcode"
},
  "geometry": {"coordinates":[-0.89266631286106,52.2316682896255],"type":"Point"}
}