{
  "type": "Feature",
  "properties": {
    "iso:country":"GB",
    "wof:name":"AB42 0SU",
    "wof:placetype":"postalcode"
},
  "geometry": {"coordinates":[-1.91080091907141,57.3904867233133],"type":"Point"}
}