{
  "type": "Feature",
  "properties": {
    "iso:country": "GB",
    "wof:name": "PE11 2PF",
    "wof:placetype": "postalcode"
  },
  "geometry": {"coordinates":[-0.147553,52.783643],"type":"Point"}
}
