{
  "type": "Feature",
  "properties": {
    "iso:country": "GB",
    "wof:name": "SA14 9UP",
    "wof:placetype": "postalcode"
  },
  "geometry": {"coordinates":[-4.092304,51.688739],"type":"Point"}
}
