{
  "type": "Feature",
  "properties": {
    "iso:country":"GB",
    "wof:name":"SA14 9UP",
    "wof:placetype":"postalcode"
},
  "geometry": {"coordinates":[-4.09230387164583,51.68873869580435],"type":"Point"}
}