{
  "type": "Feature",
  "properties": {
    "iso:country":"GB",
    "wof:name":"SW16 6JD",
    "wof:placetype":"postalcode"
},
  "geometry": {"coordinates":[-0.13441331810271,51.4236757120303],"type":"Point"}
}