{
  "type": "Feature",
  "properties": {
    "iso:country":"GB",
    "wof:name":"KT10 8AX",
    "wof:placetype":"postalcode"
},
  "geometry": {"coordinates":[-0.36882763403964,51.3819315312389],"type":"Point"}
}