{
  "type": "Feature",
  "properties": {
    "iso:country":"GB",
    "wof:name":"BR5 2LT",
    "wof:placetype":"postalcode"
},
  "geometry": {"coordinates":[0.10195929423691,51.39983615359861],"type":"Point"}
}