{
  "type": "Feature",
  "properties": {
    "iso:country":"GB",
    "wof:name":"NW4 4JX",
    "wof:placetype":"postalcode"
},
  "geometry": {"coordinates":[-0.22682449198459,51.59082247416185],"type":"Point"}
}