{
  "type": "Feature",
  "properties": {
    "iso:country":"GB",
    "wof:name":"BR2 9FR",
    "wof:placetype":"postalcode"
},
  "geometry": {"coordinates":[0.03832797956924,51.38593328019795],"type":"Point"}
}