{
  "type": "Feature",
  "properties": {
    "iso:country":"GB",
    "wof:name":"SS2 6TG",
    "wof:placetype":"postalcode"
},
  "geometry": {"coordinates":[0.68773452877816,51.56308521219894],"type":"Point"}
}