{
  "type": "Feature",
  "properties": {
    "date:inception_lower": "1980-01-01",
    "date:inception_upper": "1980-01-01",
    "iso:country": "GB",
    "wof:name": "BH24 1NU",
    "wof:placetype": "postalcode"
  },
  "geometry": {"coordinates":[-1.785077,50.845207],"type":"Point"}
}
