{
  "type": "Feature",
  "properties": {
    "iso:country":"GB",
    "wof:name":"BH10 7JB",
    "wof:placetype":"postalcode"
},
  "geometry": {"coordinates":[-1.89784730996539,50.76960683327638],"type":"Point"}
}