{
  "type": "Feature",
  "properties": {
    "iso:country":"GB",
    "wof:name":"PR4 0LH",
    "wof:placetype":"postalcode"
},
  "geometry": {"coordinates":[-2.75574130787327,53.79419165646602],"type":"Point"}
}