{
  "type": "Feature",
  "properties": {
    "date:inception_lower": "1993-01-01",
    "date:inception_upper": "1993-01-01",
    "iso:country": "GB",
    "wof:name": "SN14 6BD",
    "wof:placetype": "postalcode"
  },
  "geometry": {"coordinates":[-2.112255,51.514694],"type":"Point"}
}
