{
  "type": "Feature",
  "properties": {
    "iso:country":"GB",
    "wof:name":"M23 9FJ",
    "wof:placetype":"postalcode"
},
  "geometry": {"coordinates":[-2.30605796924492,53.40734093775183],"type":"Point"}
}