{
  "type": "Feature",
  "properties": {
    "iso:country": "GB",
    "wof:name": "LN1 2PW",
    "wof:placetype": "postalcode"
  },
  "geometry": {"coordinates":[-0.699843,53.2747],"type":"Point"}
}
