{
  "type": "Feature",
  "properties": {
    "iso:country":"GB",
    "wof:name":"LN1 2PW",
    "wof:placetype":"postalcode"
},
  "geometry": {"coordinates":[-0.69984327695683,53.27470022927602],"type":"Point"}
}