{
  "type": "Feature",
  "properties": {
    "iso:country":"GB",
    "wof:name":"NR13 3DX",
    "wof:placetype":"postalcode"
},
  "geometry": {"coordinates":[1.54832063248109,52.63796609250445],"type":"Point"}
}