{
  "type": "Feature",
  "properties": {
    "date:inception_lower": "2022-11-01",
    "date:inception_upper": "2022-11-01",
    "iso:country": "GB",
    "wof:name": "SE14 9FA",
    "wof:placetype": "postalcode"
  },
  "geometry": {"coordinates":[-0.045491,51.474646],"type":"Point"}
}
