{
  "type": "Feature",
  "properties": {
    "iso:country":"GB",
    "wof:name":"BS37 6GA",
    "wof:placetype":"postalcode"
},
  "geometry": {"coordinates":[-2.39514002548013,51.54306998120288],"type":"Point"}
}