{
  "type": "Feature",
  "properties": {
    "iso:country": "GB",
    "wof:name": "BS37 6GA",
    "wof:placetype": "postalcode"
  },
  "geometry": {"coordinates":[-2.395298,51.543258],"type":"Point"}
}
