{
  "type": "Feature",
  "properties": {
    "date:inception_lower": "2012-02-01",
    "date:inception_upper": "2012-02-01",
    "iso:country": "GB",
    "wof:name": "BS37 6GA",
    "wof:placetype": "postalcode"
  },
  "geometry": {"coordinates":[-2.395298,51.543258],"type":"Point"}
}
