{
  "type": "Feature",
  "properties": {
    "iso:country": "GB",
    "wof:name": "WD4 9BF",
    "wof:placetype": "postalcode"
  },
  "geometry": {"coordinates":[-0.489196,51.703859],"type":"Point"}
}
