{
  "type": "Feature",
  "properties": {
    "iso:country":"GB",
    "wof:name":"DD10 9JX",
    "wof:placetype":"postalcode"
},
  "geometry": {"coordinates":[-2.5483245759229,56.76972910570621],"type":"Point"}
}