{
  "type": "Feature",
  "properties": {
    "date:inception_lower": "1980-01-01",
    "date:inception_upper": "1980-01-01",
    "iso:country": "GB",
    "wof:name": "DD10 9JX",
    "wof:placetype": "postalcode"
  },
  "geometry": {"coordinates":[-2.548325,56.769729],"type":"Point"}
}
