{
  "type": "Feature",
  "properties": {
    "iso:country":"GB",
    "wof:name":"CF48 1YB",
    "wof:placetype":"postalcode"
},
  "geometry": {"coordinates":[-3.36929175339286,51.73386906706406],"type":"Point"}
}