{
  "type": "Feature",
  "properties": {
    "iso:country":"GB",
    "wof:name":"CV2 1QY",
    "wof:placetype":"postalcode"
},
  "geometry": {"coordinates":[-1.47104504675748,52.43494533012242],"type":"Point"}
}