{
  "type": "Feature",
  "properties": {
    "iso:country":"GB",
    "wof:name":"B7 4LF",
    "wof:placetype":"postalcode"
},
  "geometry": {"coordinates":[-1.8775359579125,52.48678545295108],"type":"Point"}
}