{
  "type": "Feature",
  "properties": {
    "iso:country":"GB",
    "wof:name":"BB10 2QA",
    "wof:placetype":"postalcode"
},
  "geometry": {"coordinates":[-2.22669784675969,53.8110820571466],"type":"Point"}
}