{
  "type": "Feature",
  "properties": {
    "iso:country":"GB",
    "wof:name":"EX4 3BR",
    "wof:placetype":"postalcode"
},
  "geometry": {"coordinates":[-3.53688989822909,50.72000463898338],"type":"Point"}
}