{
  "type": "Feature",
  "properties": {
    "iso:country": "GB",
    "wof:name": "EX4 3BR",
    "wof:placetype": "postalcode"
  },
  "geometry": {"coordinates":[-3.536917,50.719949],"type":"Point"}
}
