{
  "type": "Feature",
  "properties": {
    "iso:country":"GB",
    "wof:name":"SY5 6NN",
    "wof:placetype":"postalcode"
},
  "geometry": {"coordinates":[-2.65870211614106,52.61001963015584],"type":"Point"}
}