{
  "type": "Feature",
  "properties": {
    "iso:country":"GB",
    "wof:name":"S40 1RZ",
    "wof:placetype":"postalcode"
},
  "geometry": {"coordinates":[-1.45713373632238,53.23628936614185],"type":"Point"}
}