{
  "type": "Feature",
  "properties": {
    "iso:country": "GB",
    "wof:name": "HG1 4LJ",
    "wof:placetype": "postalcode"
  },
  "geometry": {"coordinates":[-1.5364,54.004369],"type":"Point"}
}
