{
  "type": "Feature",
  "properties": {
    "iso:country":"GB",
    "wof:name":"HG1 4LJ",
    "wof:placetype":"postalcode"
},
  "geometry": {"coordinates":[-1.53640054451797,54.00436933243115],"type":"Point"}
}