{
  "type": "Feature",
  "properties": {
    "iso:country":"GB",
    "wof:name":"LE8 8BL",
    "wof:placetype":"postalcode"
},
  "geometry": {"coordinates":[-1.04932728464116,52.53671203009541],"type":"Point"}
}