{
  "type": "Feature",
  "properties": {
    "iso:country":"GB",
    "wof:name":"CR5 1PR",
    "wof:placetype":"postalcode"
},
  "geometry": {"coordinates":[-0.12567013183101,51.30681060562917],"type":"Point"}
}