{
  "type": "Feature",
  "properties": {
    "iso:country":"GB",
    "wof:name":"G66 3QH",
    "wof:placetype":"postalcode"
},
  "geometry": {"coordinates":[-4.12048545351689,55.93797454772583],"type":"Point"}
}