{
  "type": "Feature",
  "properties": {
    "date:inception_lower": "1980-01-01",
    "date:inception_upper": "1980-01-01",
    "iso:country": "GB",
    "wof:name": "SW2 1SR",
    "wof:placetype": "postalcode"
  },
  "geometry": {"coordinates":[-0.117165,51.45661],"type":"Point"}
}
