{
  "type": "Feature",
  "properties": {
    "iso:country": "GB",
    "wof:name": "SW2 1SR",
    "wof:placetype": "postalcode"
  },
  "geometry": {"coordinates":[-0.117165,51.45661],"type":"Point"}
}
