{
  "type": "Feature",
  "properties": {
    "iso:country":"GB",
    "wof:name":"SW2 1SR",
    "wof:placetype":"postalcode"
},
  "geometry": {"coordinates":[-0.11716523182336,51.45660969224494],"type":"Point"}
}