{
  "type": "Feature",
  "properties": {
    "iso:country": "GB",
    "wof:name": "YO13 0HN",
    "wof:placetype": "postalcode"
  },
  "geometry": {"coordinates":[-0.44365,54.31872],"type":"Point"}
}
