{
  "type": "Feature",
  "properties": {
    "iso:country":"GB",
    "wof:name":"YO13 0HN",
    "wof:placetype":"postalcode"
},
  "geometry": {"coordinates":[-0.44364970251815,54.31871978913453],"type":"Point"}
}