{
  "type": "Feature",
  "properties": {
    "date:inception_lower": "1980-01-01",
    "date:inception_upper": "1980-01-01",
    "iso:country": "GB",
    "wof:name": "WA6 8DT",
    "wof:placetype": "postalcode"
  },
  "geometry": {"coordinates":[-2.675208,53.265184],"type":"Point"}
}
