{
  "type": "Feature",
  "properties": {
    "iso:country":"GB",
    "wof:name":"PO8 0PE",
    "wof:placetype":"postalcode"
},
  "geometry": {"coordinates":[-1.00922986469309,50.94020131033963],"type":"Point"}
}