{
  "type": "Feature",
  "properties": {
    "iso:country":"GB",
    "wof:name":"TA6 3EP",
    "wof:placetype":"postalcode"
},
  "geometry": {"coordinates":[-3.0072070130129,51.12832257113713],"type":"Point"}
}