{
  "type": "Feature",
  "properties": {
    "iso:country": "GB",
    "wof:name": "DH6 2DA",
    "wof:placetype": "postalcode"
  },
  "geometry": {"coordinates":[-1.419986,54.783505],"type":"Point"}
}
