{
  "type": "Feature",
  "properties": {
    "iso:country":"GB",
    "wof:name":"DH6 2DA",
    "wof:placetype":"postalcode"
},
  "geometry": {"coordinates":[-1.41998630710957,54.78350451417847],"type":"Point"}
}