{
  "type": "Feature",
  "properties": {
    "iso:country":"GB",
    "wof:name":"WN3 6AH",
    "wof:placetype":"postalcode"
},
  "geometry": {"coordinates":[-2.67936570921463,53.52885435475645],"type":"Point"}
}