{
  "type": "Feature",
  "properties": {
    "date:inception_lower": "2024-10-01",
    "date:inception_upper": "2024-10-01",
    "iso:country": "GB",
    "wof:name": "NR13 3FX",
    "wof:placetype": "postalcode"
  },
  "geometry": {"coordinates":[1.555387,52.592143],"type":"Point"}
}
