{
  "type": "Feature",
  "properties": {
    "iso:country":"GB",
    "wof:name":"DG10 9AB",
    "wof:placetype":"postalcode"
},
  "geometry": {"coordinates":[-3.44412215563903,55.3342259924168],"type":"Point"}
}