{
  "type": "Feature",
  "properties": {
    "iso:country": "GB",
    "wof:name": "E11 1EL",
    "wof:placetype": "postalcode"
  },
  "geometry": {"coordinates":[0.001971,51.571864],"type":"Point"}
}
