{
  "type": "Feature",
  "properties": {
    "iso:country":"GB",
    "wof:name":"E11 1EL",
    "wof:placetype":"postalcode"
},
  "geometry": {"coordinates":[0.00197136293201,51.57186420461649],"type":"Point"}
}