{
  "type": "Feature",
  "properties": {
    "iso:country": "GB",
    "wof:name": "PE2 8UL",
    "wof:placetype": "postalcode"
  },
  "geometry": {"coordinates":[-0.20397,52.550416],"type":"Point"}
}
