{
  "type": "Feature",
  "properties": {
    "iso:country":"GB",
    "wof:name":"PE2 8UL",
    "wof:placetype":"postalcode"
},
  "geometry": {"coordinates":[-0.20396987627938,52.5504157499241],"type":"Point"}
}