{
  "type": "Feature",
  "properties": {
    "date:inception_lower":"2006-10-01",
    "date:inception_upper":"2006-10-31",
    "iso:country":"GB",
    "wof:name":"GU8 5HE",
    "wof:placetype":"postalcode"
},
  "geometry": {"coordinates":[-0.645305,51.174385],"type":"Point"}
}