{
  "type": "Feature",
  "properties": {
    "iso:country":"GB",
    "wof:name":"NE13 7DQ",
    "wof:placetype":"postalcode"
},
  "geometry": {"coordinates":[-1.63584778755092,55.04141624707163],"type":"Point"}
}