{
  "type": "Feature",
  "properties": {
    "iso:country": "GB",
    "wof:name": "NE13 7DQ",
    "wof:placetype": "postalcode"
  },
  "geometry": {"coordinates":[-1.635848,55.041416],"type":"Point"}
}
