{
  "type": "Feature",
  "properties": {
    "date:inception_lower": "1980-01-01",
    "date:inception_upper": "1980-01-01",
    "iso:country": "GB",
    "wof:name": "NE13 7DQ",
    "wof:placetype": "postalcode"
  },
  "geometry": {"coordinates":[-1.635848,55.041416],"type":"Point"}
}
