{
  "type": "Feature",
  "properties": {
    "iso:country":"GB",
    "wof:name":"WA6 6PP",
    "wof:placetype":"postalcode"
},
  "geometry": {"coordinates":[-2.72291349408553,53.29444207415705],"type":"Point"}
}