{
  "type": "Feature",
  "properties": {
    "iso:country":"GB",
    "wof:name":"M28 1YA",
    "wof:placetype":"postalcode"
},
  "geometry": {"coordinates":[-2.42592699301583,53.49868347707116],"type":"Point"}
}