{
  "type": "Feature",
  "properties": {
    "date:inception_lower":"1995-12-01",
    "date:inception_upper":"1995-12-31",
    "iso:country":"GB",
    "wof:name":"M28 1YA",
    "wof:placetype":"postalcode"
},
  "geometry": {"coordinates":[-2.425927,53.498683],"type":"Point"}
}