{
  "type": "Feature",
  "properties": {
    "iso:country": "GB",
    "wof:name": "M28 1YA",
    "wof:placetype": "postalcode"
  },
  "geometry": {"coordinates":[-2.425927,53.498683],"type":"Point"}
}
