{
  "type": "Feature",
  "properties": {
    "iso:country": "GB",
    "wof:name": "CT4 6AS",
    "wof:placetype": "postalcode"
  },
  "geometry": {"coordinates":[1.064984,51.181604],"type":"Point"}
}
