{
  "type": "Feature",
  "properties": {
    "iso:country":"GB",
    "wof:name":"CT4 6AS",
    "wof:placetype":"postalcode"
},
  "geometry": {"coordinates":[1.06498368155114,51.18160362855841],"type":"Point"}
}