{
  "type": "Feature",
  "properties": {
    "iso:country":"GB",
    "wof:name":"BB1 2JL",
    "wof:placetype":"postalcode"
},
  "geometry": {"coordinates":[-2.44597294414251,53.74060246419067],"type":"Point"}
}