{
  "type": "Feature",
  "properties": {
    "iso:country":"GB",
    "wof:name":"WD6 2PF",
    "wof:placetype":"postalcode"
},
  "geometry": {"coordinates":[-0.25465738262592,51.65182929894097],"type":"Point"}
}