{
  "type": "Feature",
  "properties": {
    "iso:country":"GB",
    "wof:name":"FK7 7XH",
    "wof:placetype":"postalcode"
},
  "geometry": {"coordinates":[-3.90853802984776,56.11738815821492],"type":"Point"}
}