{
  "type": "Feature",
  "properties": {
    "date:inception_lower":"1997-06-01",
    "date:inception_upper":"1997-06-30",
    "iso:country":"GB",
    "wof:name":"FK7 7XH",
    "wof:placetype":"postalcode"
},
  "geometry": {"coordinates":[-3.908531,56.117381],"type":"Point"}
}