{
  "type": "Feature",
  "properties": {
    "iso:country": "GB",
    "wof:name": "FK7 7XH",
    "wof:placetype": "postalcode"
  },
  "geometry": {"coordinates":[-3.907201,56.117159],"type":"Point"}
}
