{
  "type": "Feature",
  "properties": {
    "iso:country":"GB",
    "wof:name":"E12 6EJ",
    "wof:placetype":"postalcode"
},
  "geometry": {"coordinates":[0.05288221997101,51.55101178895291],"type":"Point"}
}