{
  "type": "Feature",
  "properties": {
    "date:inception_lower": "1980-01-01",
    "date:inception_upper": "1980-01-01",
    "iso:country": "GB",
    "wof:name": "HD4 7WW",
    "wof:placetype": "postalcode"
  },
  "geometry": {"coordinates":[-1.812914,53.61202],"type":"Point"}
}
