{
  "type": "Feature",
  "properties": {
    "iso:country":"GB",
    "wof:name":"OL1 4RW",
    "wof:placetype":"postalcode"
},
  "geometry": {"coordinates":[-2.07681706547845,53.56792761561787],"type":"Point"}
}