{
  "type": "Feature",
  "properties": {
    "date:inception_lower": "1990-12-01",
    "date:inception_upper": "1990-12-01",
    "iso:country": "GB",
    "wof:name": "PA4 9BJ",
    "wof:placetype": "postalcode"
  },
  "geometry": {"coordinates":[-4.397219,55.878199],"type":"Point"}
}
