{
  "type": "Feature",
  "properties": {
    "iso:country":"GB",
    "wof:name":"PA4 9BJ",
    "wof:placetype":"postalcode"
},
  "geometry": {"coordinates":[-4.39721891012477,55.87819883991842],"type":"Point"}
}