{
  "type": "Feature",
  "properties": {
    "date:inception_lower":"1991-09-01",
    "date:inception_upper":"1991-09-30",
    "iso:country":"GB",
    "wof:name":"GU8 4JD",
    "wof:placetype":"postalcode"
},
  "geometry": {"coordinates":[-0.56908,51.145916],"type":"Point"}
}