{
  "type": "Feature",
  "properties": {
    "iso:country":"GB",
    "wof:name":"GU8 4JD",
    "wof:placetype":"postalcode"
},
  "geometry": {"coordinates":[-0.569080533595,51.14591578337021],"type":"Point"}
}