{
  "type": "Feature",
  "properties": {
    "iso:country":"GB",
    "wof:name":"BS37 6DR",
    "wof:placetype":"postalcode"
},
  "geometry": {"coordinates":[-2.38837520394782,51.53437986624859],"type":"Point"}
}