{
  "type": "Feature",
  "properties": {
    "iso:country": "GB",
    "wof:name": "BS37 6DR",
    "wof:placetype": "postalcode"
  },
  "geometry": {"coordinates":[-2.388375,51.53438],"type":"Point"}
}
