{
  "type": "Feature",
  "properties": {
    "iso:country":"GB",
    "wof:name":"NG2 6QP",
    "wof:placetype":"postalcode"
},
  "geometry": {"coordinates":[-1.10264401400469,52.92681181620135],"type":"Point"}
}