{
  "type": "Feature",
  "properties": {
    "date:inception_lower": "1980-01-01",
    "date:inception_upper": "1980-01-01",
    "iso:country": "GB",
    "wof:name": "ML6 7AU",
    "wof:placetype": "postalcode"
  },
  "geometry": {"coordinates":[-3.947619,55.869574],"type":"Point"}
}
