{
  "type": "Feature",
  "properties": {
    "iso:country": "GB",
    "wof:name": "ML6 7AU",
    "wof:placetype": "postalcode"
  },
  "geometry": {"coordinates":[-3.947619,55.869574],"type":"Point"}
}
