{
  "type": "Feature",
  "properties": {
    "iso:country":"GB",
    "wof:name":"ML6 7AU",
    "wof:placetype":"postalcode"
},
  "geometry": {"coordinates":[-3.94761880283803,55.86957369701998],"type":"Point"}
}