{
  "type": "Feature",
  "properties": {
    "iso:country":"GB",
    "wof:name":"BN2 9QU",
    "wof:placetype":"postalcode"
},
  "geometry": {"coordinates":[-0.12994325175234,50.82558423318666],"type":"Point"}
}