{
  "type": "Feature",
  "properties": {
    "iso:country":"GB",
    "wof:name":"CV22 7FZ",
    "wof:placetype":"postalcode"
},
  "geometry": {"coordinates":[-1.30583575451544,52.36057806994733],"type":"Point"}
}