{
  "type": "Feature",
  "properties": {
    "date:inception_lower": "2002-08-01",
    "date:inception_upper": "2002-08-01",
    "iso:country": "GB",
    "wof:name": "CV22 7FZ",
    "wof:placetype": "postalcode"
  },
  "geometry": {"coordinates":[-1.305836,52.360578],"type":"Point"}
}
