{
  "type": "Feature",
  "properties": {
    "iso:country":"GB",
    "wof:name":"GU35 8AF",
    "wof:placetype":"postalcode"
},
  "geometry": {"coordinates":[-0.81118865094438,51.12373580271235],"type":"Point"}
}