{
  "type": "Feature",
  "properties": {
    "iso:country":"GB",
    "wof:name":"TN28 8JH",
    "wof:placetype":"postalcode"
},
  "geometry": {"coordinates":[0.94595354802356,50.99324955663136],"type":"Point"}
}