{
  "type": "Feature",
  "properties": {
    "date:inception_lower": "2018-06-01",
    "date:inception_upper": "2018-06-01",
    "iso:country": "GB",
    "wof:name": "L8 3UH",
    "wof:placetype": "postalcode"
  },
  "geometry": {"coordinates":[-2.957605,53.389509],"type":"Point"}
}
