{
  "type": "Feature",
  "properties": {
    "iso:country":"GB",
    "wof:name":"HP12 3ER",
    "wof:placetype":"postalcode"
},
  "geometry": {"coordinates":[-0.77346898188778,51.6359681023254],"type":"Point"}
}