{
  "type": "Feature",
  "properties": {
    "date:inception_lower": "2013-11-01",
    "date:inception_upper": "2013-11-01",
    "iso:country": "GB",
    "wof:name": "HP12 3ER",
    "wof:placetype": "postalcode"
  },
  "geometry": {"coordinates":[-0.773469,51.635968],"type":"Point"}
}
