{
  "type": "Feature",
  "properties": {
    "iso:country": "GB",
    "wof:name": "BS14 8JG",
    "wof:placetype": "postalcode"
  },
  "geometry": {"coordinates":[-2.54434,51.41472],"type":"Point"}
}
