{
  "type": "Feature",
  "properties": {
    "iso:country": "GB",
    "wof:name": "EH12 7PR",
    "wof:placetype": "postalcode"
  },
  "geometry": {"coordinates":[-3.291353,55.938082],"type":"Point"}
}
