{
  "type": "Feature",
  "properties": {
    "date:inception_lower":"2002-05-01",
    "date:inception_upper":"2002-05-31",
    "iso:country":"GB",
    "wof:name":"E14 7JH",
    "wof:placetype":"postalcode"
},
  "geometry": {"coordinates":[-0.040413,51.512078],"type":"Point"}
}