{
  "type": "Feature",
  "properties": {
    "iso:country": "GB",
    "wof:name": "E14 7JH",
    "wof:placetype": "postalcode"
  },
  "geometry": {"coordinates":[-0.040413,51.512078],"type":"Point"}
}
