{
  "type": "Feature",
  "properties": {
    "iso:country":"GB",
    "wof:name":"CO7 8QZ",
    "wof:placetype":"postalcode"
},
  "geometry": {"coordinates":[1.09637276165617,51.83962541326829],"type":"Point"}
}