{
  "type": "Feature",
  "properties": {
    "date:inception_lower": "1980-01-01",
    "date:inception_upper": "1980-01-01",
    "iso:country": "GB",
    "wof:name": "CO7 8QZ",
    "wof:placetype": "postalcode"
  },
  "geometry": {"coordinates":[1.096373,51.839625],"type":"Point"}
}
