{
  "type": "Feature",
  "properties": {
    "iso:country":"GB",
    "wof:name":"LS16 6AT",
    "wof:placetype":"postalcode"
},
  "geometry": {"coordinates":[-1.59468051564901,53.85037566101117],"type":"Point"}
}