{
  "type": "Feature",
  "properties": {
    "iso:country":"GB",
    "wof:name":"MK44 2QS",
    "wof:placetype":"postalcode"
},
  "geometry": {"coordinates":[-0.41353512621882,52.18287248949817],"type":"Point"}
}