{
  "type": "Feature",
  "properties": {
    "iso:country": "GB",
    "wof:name": "MK44 2QS",
    "wof:placetype": "postalcode"
  },
  "geometry": {"coordinates":[-0.413535,52.182872],"type":"Point"}
}
