{
  "type": "Feature",
  "properties": {
    "date:inception_lower": "2016-10-01",
    "date:inception_upper": "2016-10-01",
    "iso:country": "GB",
    "wof:name": "CO4 6AF",
    "wof:placetype": "postalcode"
  },
  "geometry": {"coordinates":[0.886921,51.91644],"type":"Point"}
}
