{
  "type": "Feature",
  "properties": {
    "iso:country":"GB",
    "wof:name":"M14 4LU",
    "wof:placetype":"postalcode"
},
  "geometry": {"coordinates":[-2.23637572388562,53.45776320093395],"type":"Point"}
}