{
  "type": "Feature",
  "properties": {
    "iso:country": "GB",
    "wof:name": "M14 4LU",
    "wof:placetype": "postalcode"
  },
  "geometry": {"coordinates":[-2.236179,53.45778],"type":"Point"}
}
