{
  "type": "Feature",
  "properties": {
    "iso:country": "GB",
    "wof:name": "DG8 6EJ",
    "wof:placetype": "postalcode"
  },
  "geometry": {"coordinates":[-4.483149,54.956733],"type":"Point"}
}
