{
  "type": "Feature",
  "properties": {
    "iso:country": "GB",
    "wof:name": "LA2 7FJ",
    "wof:placetype": "postalcode"
  },
  "geometry": {"coordinates":[-2.518046,54.113974],"type":"Point"}
}
