{
  "type": "Feature",
  "properties": {
    "iso:country":"GB",
    "wof:name":"LA2 7FJ",
    "wof:placetype":"postalcode"
},
  "geometry": {"coordinates":[-2.51804573014374,54.1139742847491],"type":"Point"}
}