{
  "type": "Feature",
  "properties": {
    "date:inception_lower":"2007-04-01",
    "date:inception_upper":"2007-04-30",
    "iso:country":"GB",
    "wof:name":"LA2 7FJ",
    "wof:placetype":"postalcode"
},
  "geometry": {"coordinates":[-2.518046,54.113974],"type":"Point"}
}