{
  "type": "Feature",
  "properties": {
    "iso:country":"GB",
    "wof:name":"NN3 2AB",
    "wof:placetype":"postalcode"
},
  "geometry": {"coordinates":[-0.8659293992857,52.26210891296806],"type":"Point"}
}