{
  "type": "Feature",
  "properties": {
    "iso:country": "GB",
    "wof:name": "ML5 4UN",
    "wof:placetype": "postalcode"
  },
  "geometry": {"coordinates":[-3.998713,55.845236],"type":"Point"}
}
