{
  "type": "Feature",
  "properties": {
    "date:inception_lower":"2006-05-01",
    "date:inception_upper":"2006-05-31",
    "iso:country":"GB",
    "wof:name":"ML5 4UN",
    "wof:placetype":"postalcode"
},
  "geometry": {"coordinates":[-3.998713,55.845236],"type":"Point"}
}