{
  "type": "Feature",
  "properties": {
    "date:inception_lower": "2004-07-01",
    "date:inception_upper": "2004-07-01",
    "iso:country": "GB",
    "wof:name": "WA3 6BX",
    "wof:placetype": "postalcode"
  },
  "geometry": {"coordinates":[-2.525176,53.430136],"type":"Point"}
}
