{
  "type": "Feature",
  "properties": {
    "iso:country":"GB",
    "wof:name":"DE1 3SL",
    "wof:placetype":"postalcode"
},
  "geometry": {"coordinates":[-1.49071277255482,52.93102261619112],"type":"Point"}
}