{
  "type": "Feature",
  "properties": {
    "iso:country":"GB",
    "wof:name":"NN5 4AY",
    "wof:placetype":"postalcode"
},
  "geometry": {"coordinates":[-0.94359692927666,52.23396012091702],"type":"Point"}
}