{
  "type": "Feature",
  "properties": {
    "iso:country": "GB",
    "wof:name": "NN5 4AY",
    "wof:placetype": "postalcode"
  },
  "geometry": {"coordinates":[-0.945693,52.235705],"type":"Point"}
}
