{
  "type": "Feature",
  "properties": {
    "iso:country":"GB",
    "wof:name":"RG31 4RB",
    "wof:placetype":"postalcode"
},
  "geometry": {"coordinates":[-1.0519675554105,51.44123291548715],"type":"Point"}
}