{
  "type": "Feature",
  "properties": {
    "iso:country":"GB",
    "wof:name":"IV2 4UP",
    "wof:placetype":"postalcode"
},
  "geometry": {"coordinates":[-4.21464832106672,57.4640817879768],"type":"Point"}
}