{
  "type": "Feature",
  "properties": {
    "iso:country":"GB",
    "wof:name":"CT19 5PG",
    "wof:placetype":"postalcode"
},
  "geometry": {"coordinates":[1.18189781773694,51.09107555098573],"type":"Point"}
}