{
  "type": "Feature",
  "properties": {
    "iso:country":"GB",
    "wof:name":"BB6 7FN",
    "wof:placetype":"postalcode"
},
  "geometry": {"coordinates":[-2.40072095431709,53.78881262834015],"type":"Point"}
}