{
  "type": "Feature",
  "properties": {
    "date:inception_lower":"2009-05-01",
    "date:inception_upper":"2009-05-31",
    "iso:country":"GB",
    "wof:name":"BB6 7FN",
    "wof:placetype":"postalcode"
},
  "geometry": {"coordinates":[-2.400721,53.788813],"type":"Point"}
}