{
  "type": "Feature",
  "properties": {
    "iso:country":"GB",
    "wof:name":"W5 2TU",
    "wof:placetype":"postalcode"
},
  "geometry": {"coordinates":[-0.31403732510052,51.51349728764151],"type":"Point"}
}