{
  "type": "Feature",
  "properties": {
    "iso:country":"GB",
    "wof:name":"EX15 2QE",
    "wof:placetype":"postalcode"
},
  "geometry": {"coordinates":[-3.37800245911442,50.89524264116707],"type":"Point"}
}