{
  "type": "Feature",
  "properties": {
    "iso:country": "GB",
    "wof:name": "EX15 2QE",
    "wof:placetype": "postalcode"
  },
  "geometry": {"coordinates":[-3.378002,50.895243],"type":"Point"}
}
