{
  "type": "Feature",
  "properties": {
    "date:inception_lower": "1980-01-01",
    "date:inception_upper": "1980-01-01",
    "iso:country": "GB",
    "wof:name": "EX15 2QE",
    "wof:placetype": "postalcode"
  },
  "geometry": {"coordinates":[-3.378002,50.895243],"type":"Point"}
}
