{
  "type": "Feature",
  "properties": {
    "iso:country": "GB",
    "wof:name": "BH21 4AY",
    "wof:placetype": "postalcode"
  },
  "geometry": {"coordinates":[-2.073545,50.796165],"type":"Point"}
}
