{
  "type": "Feature",
  "properties": {
    "iso:country":"GB",
    "wof:name":"LL19 9DE",
    "wof:placetype":"postalcode"
},
  "geometry": {"coordinates":[-3.40510583543075,53.33152175194143],"type":"Point"}
}