{
  "type": "Feature",
  "properties": {
    "iso:country":"GB",
    "wof:name":"HP13 7PZ",
    "wof:placetype":"postalcode"
},
  "geometry": {"coordinates":[-0.7218406236533,51.64003031755945],"type":"Point"}
}