{
  "type": "Feature",
  "properties": {
    "iso:country": "GB",
    "wof:name": "HP13 7PZ",
    "wof:placetype": "postalcode"
  },
  "geometry": {"coordinates":[-0.721841,51.64003],"type":"Point"}
}
