{
  "type": "Feature",
  "properties": {
    "iso:country":"GB",
    "wof:name":"BR4 9QN",
    "wof:placetype":"postalcode"
},
  "geometry": {"coordinates":[-0.00677674731615,51.37226681381497],"type":"Point"}
}