{
  "type": "Feature",
  "properties": {
    "date:inception_lower": "1992-08-01",
    "date:inception_upper": "1992-08-01",
    "iso:country": "GB",
    "wof:name": "BR4 9QN",
    "wof:placetype": "postalcode"
  },
  "geometry": {"coordinates":[-0.006777,51.372267],"type":"Point"}
}
