{
  "type": "Feature",
  "properties": {
    "iso:country":"GB",
    "wof:name":"SY13 4DN",
    "wof:placetype":"postalcode"
},
  "geometry": {"coordinates":[-2.64331906203844,52.95105467620314],"type":"Point"}
}