{
  "type": "Feature",
  "properties": {
    "iso:country": "GB",
    "wof:name": "SY13 4DN",
    "wof:placetype": "postalcode"
  },
  "geometry": {"coordinates":[-2.643319,52.951055],"type":"Point"}
}
