{
  "type": "Feature",
  "properties": {
    "iso:country": "GB",
    "wof:name": "S9 1JQ",
    "wof:placetype": "postalcode"
  },
  "geometry": {"coordinates":[-1.412528,53.418039],"type":"Point"}
}
