{
  "type": "Feature",
  "properties": {
    "date:inception_lower": "2002-10-01",
    "date:inception_upper": "2002-10-01",
    "iso:country": "GB",
    "wof:name": "S9 1JQ",
    "wof:placetype": "postalcode"
  },
  "geometry": {"coordinates":[-1.412573,53.418039],"type":"Point"}
}
