{
  "type": "Feature",
  "properties": {
    "iso:country":"GB",
    "wof:name":"M26 1NW",
    "wof:placetype":"postalcode"
},
  "geometry": {"coordinates":[-2.32377011814697,53.55858817129715],"type":"Point"}
}