{
  "type": "Feature",
  "properties": {
    "date:inception_lower": "1994-05-01",
    "date:inception_upper": "1994-05-01",
    "iso:country": "GB",
    "wof:name": "M26 1NW",
    "wof:placetype": "postalcode"
  },
  "geometry": {"coordinates":[-2.323737,53.558568],"type":"Point"}
}
