{
  "type": "Feature",
  "properties": {
    "iso:country":"GB",
    "wof:name":"NG21 0JT",
    "wof:placetype":"postalcode"
},
  "geometry": {"coordinates":[-1.10988802945414,53.11954568048835],"type":"Point"}
}