{
  "type": "Feature",
  "properties": {
    "iso:country": "GB",
    "wof:name": "CT15 5ER",
    "wof:placetype": "postalcode"
  },
  "geometry": {"coordinates":[1.324871,51.154648],"type":"Point"}
}
