{
  "type": "Feature",
  "properties": {
    "iso:country":"GB",
    "wof:name":"CT15 5ER",
    "wof:placetype":"postalcode"
},
  "geometry": {"coordinates":[1.32487092229202,51.15464762243327],"type":"Point"}
}