{
  "type": "Feature",
  "properties": {
    "iso:country":"GB",
    "wof:name":"LA19 5TD",
    "wof:placetype":"postalcode"
},
  "geometry": {"coordinates":[-3.3775304382282,54.28258098383967],"type":"Point"}
}