{
  "type": "Feature",
  "properties": {
    "iso:country":"GB",
    "wof:name":"BH9 2RP",
    "wof:placetype":"postalcode"
},
  "geometry": {"coordinates":[-1.88571490948273,50.74953308422512],"type":"Point"}
}