{
  "type": "Feature",
  "properties": {
    "iso:country":"GB",
    "wof:name":"CO6 3SL",
    "wof:placetype":"postalcode"
},
  "geometry": {"coordinates":[0.86045707693773,51.91334265576456],"type":"Point"}
}