{
  "type": "Feature",
  "properties": {
    "iso:country":"GB",
    "wof:name":"NN3 9EX",
    "wof:placetype":"postalcode"
},
  "geometry": {"coordinates":[-0.80814316627789,52.24448428576848],"type":"Point"}
}