{
  "type": "Feature",
  "properties": {
    "iso:country":"GB",
    "wof:name":"SA70 7TJ",
    "wof:placetype":"postalcode"
},
  "geometry": {"coordinates":[-4.7932029153343,51.6474517127702],"type":"Point"}
}