{
  "type": "Feature",
  "properties": {
    "iso:country": "GB",
    "wof:name": "PA19 1GY",
    "wof:placetype": "postalcode"
  },
  "geometry": {"coordinates":[-4.857483,55.947885],"type":"Point"}
}
