{
  "type": "Feature",
  "properties": {
    "date:inception_lower":"2004-02-01",
    "date:inception_upper":"2004-02-29",
    "iso:country":"GB",
    "wof:name":"S73 0DX",
    "wof:placetype":"postalcode"
},
  "geometry": {"coordinates":[-1.390271,53.523426],"type":"Point"}
}