{
  "type": "Feature",
  "properties": {
    "iso:country": "GB",
    "wof:name": "S73 0DX",
    "wof:placetype": "postalcode"
  },
  "geometry": {"coordinates":[-1.390271,53.523426],"type":"Point"}
}
