{
  "type": "Feature",
  "properties": {
    "iso:country":"GB",
    "wof:name":"S73 0DX",
    "wof:placetype":"postalcode"
},
  "geometry": {"coordinates":[-1.39027076532707,53.52342597143232],"type":"Point"}
}