{
  "type": "Feature",
  "properties": {
    "date:inception_lower": "1980-01-01",
    "date:inception_upper": "1980-01-01",
    "iso:country": "GB",
    "wof:name": "G20 0BX",
    "wof:placetype": "postalcode"
  },
  "geometry": {"coordinates":[-4.299711,55.896642],"type":"Point"}
}
