{
  "type": "Feature",
  "properties": {
    "iso:country":"GB",
    "wof:name":"G20 0BX",
    "wof:placetype":"postalcode"
},
  "geometry": {"coordinates":[-4.29971080807939,55.89664199318845],"type":"Point"}
}