{
  "type": "Feature",
  "properties": {
    "iso:country": "GB",
    "wof:name": "WD25 8DW",
    "wof:placetype": "postalcode"
  },
  "geometry": {"coordinates":[-0.352387,51.664864],"type":"Point"}
}
