{
  "type": "Feature",
  "properties": {
    "iso:country":"GB",
    "wof:name":"WD25 8DW",
    "wof:placetype":"postalcode"
},
  "geometry": {"coordinates":[-0.3517293026606,51.66452595700147],"type":"Point"}
}