{
  "type": "Feature",
  "properties": {
    "date:inception_lower": "1996-12-01",
    "date:inception_upper": "1996-12-01",
    "iso:country": "GB",
    "wof:name": "MK18 4LJ",
    "wof:placetype": "postalcode"
  },
  "geometry": {"coordinates":[-1.041935,51.963626],"type":"Point"}
}
