{
  "type": "Feature",
  "properties": {
    "iso:country":"GB",
    "wof:name":"SK9 5PU",
    "wof:placetype":"postalcode"
},
  "geometry": {"coordinates":[-2.24959399681231,53.33116795723559],"type":"Point"}
}