{
  "type": "Feature",
  "properties": {
    "date:inception_lower": "1980-01-01",
    "date:inception_upper": "1980-01-01",
    "iso:country": "GB",
    "wof:name": "SK9 5PU",
    "wof:placetype": "postalcode"
  },
  "geometry": {"coordinates":[-2.249563,53.331238],"type":"Point"}
}
