{
  "type": "Feature",
  "properties": {
    "date:inception_lower": "1981-06-01",
    "date:inception_upper": "1981-06-01",
    "iso:country": "GB",
    "wof:name": "WR13 6SF",
    "wof:placetype": "postalcode"
  },
  "geometry": {"coordinates":[-2.304613,52.059128],"type":"Point"}
}
