{
  "type": "Feature",
  "properties": {
    "iso:country": "GB",
    "wof:name": "WR13 6SF",
    "wof:placetype": "postalcode"
  },
  "geometry": {"coordinates":[-2.304613,52.059128],"type":"Point"}
}
