{
  "type": "Feature",
  "properties": {
    "date:inception_lower": "1980-01-01",
    "date:inception_upper": "1980-01-01",
    "iso:country": "GB",
    "wof:name": "NG22 0UH",
    "wof:placetype": "postalcode"
  },
  "geometry": {"coordinates":[-0.786672,53.259443],"type":"Point"}
}
