{
  "type": "Feature",
  "properties": {
    "iso:country": "GB",
    "wof:name": "NG22 0UH",
    "wof:placetype": "postalcode"
  },
  "geometry": {"coordinates":[-0.786672,53.259443],"type":"Point"}
}
