{
  "type": "Feature",
  "properties": {
    "iso:country":"GB",
    "wof:name":"NN2 6JE",
    "wof:placetype":"postalcode"
},
  "geometry": {"coordinates":[-0.89458246483593,52.25356071258553],"type":"Point"}
}