{
  "type": "Feature",
  "properties": {
    "iso:country":"GB",
    "wof:name":"BA22 7BX",
    "wof:placetype":"postalcode"
},
  "geometry": {"coordinates":[-2.52860592384518,51.05339618360941],"type":"Point"}
}