{
  "type": "Feature",
  "properties": {
    "iso:country": "GB",
    "wof:name": "BA22 7BX",
    "wof:placetype": "postalcode"
  },
  "geometry": {"coordinates":[-2.528606,51.053396],"type":"Point"}
}
