{
  "type": "Feature",
  "properties": {
    "date:inception_lower": "1980-01-01",
    "date:inception_upper": "1980-01-01",
    "iso:country": "GB",
    "wof:name": "SR4 8HS",
    "wof:placetype": "postalcode"
  },
  "geometry": {"coordinates":[-1.433497,54.890382],"type":"Point"}
}
