{
  "type": "Feature",
  "properties": {
    "iso:country":"GB",
    "wof:name":"SR4 8HS",
    "wof:placetype":"postalcode"
},
  "geometry": {"coordinates":[-1.43349685993044,54.89038238024933],"type":"Point"}
}