{
  "type": "Feature",
  "properties": {
    "iso:country":"GB",
    "wof:name":"KT9 2HE",
    "wof:placetype":"postalcode"
},
  "geometry": {"coordinates":[-0.29871733399835,51.36208620026289],"type":"Point"}
}