{
  "type": "Feature",
  "properties": {
    "date:inception_lower":"1980-01-01",
    "date:inception_upper":"1980-01-31",
    "iso:country":"GB",
    "wof:name":"KT9 2HE",
    "wof:placetype":"postalcode"
},
  "geometry": {"coordinates":[-0.298717,51.362086],"type":"Point"}
}