{
  "type": "Feature",
  "properties": {
    "iso:country":"GB",
    "wof:name":"OL5 0HH",
    "wof:placetype":"postalcode"
},
  "geometry": {"coordinates":[-2.04411995058963,53.51776230490113],"type":"Point"}
}