{
  "type": "Feature",
  "properties": {
    "iso:country": "GB",
    "wof:name": "NE40 3JA",
    "wof:placetype": "postalcode"
  },
  "geometry": {"coordinates":[-1.754599,54.970417],"type":"Point"}
}
