{
  "type": "Feature",
  "properties": {
    "iso:country":"GB",
    "wof:name":"NE40 3JA",
    "wof:placetype":"postalcode"
},
  "geometry": {"coordinates":[-1.75414541483592,54.97048796211755],"type":"Point"}
}