{
  "type": "Feature",
  "properties": {
    "iso:country":"GB",
    "wof:name":"CT19 5PU",
    "wof:placetype":"postalcode"
},
  "geometry": {"coordinates":[1.17320905038179,51.09392945214448],"type":"Point"}
}