{
  "type": "Feature",
  "properties": {
    "iso:country":"GB",
    "wof:name":"ML4 2LJ",
    "wof:placetype":"postalcode"
},
  "geometry": {"coordinates":[-4.01971041216225,55.81582864169584],"type":"Point"}
}