{
  "type": "Feature",
  "properties": {
    "date:inception_lower":"1980-01-01",
    "date:inception_upper":"1980-01-31",
    "iso:country":"GB",
    "wof:name":"S9 2PU",
    "wof:placetype":"postalcode"
},
  "geometry": {"coordinates":[-1.429776,53.399659],"type":"Point"}
}