{
  "type": "Feature",
  "properties": {
    "iso:country":"GB",
    "wof:name":"TA2 6BY",
    "wof:placetype":"postalcode"
},
  "geometry": {"coordinates":[-3.12897019318014,51.02947087643666],"type":"Point"}
}