{
  "type": "Feature",
  "properties": {
    "date:inception_lower": "1994-12-01",
    "date:inception_upper": "1994-12-01",
    "iso:country": "GB",
    "wof:name": "TA2 6BY",
    "wof:placetype": "postalcode"
  },
  "geometry": {"coordinates":[-3.12897,51.029471],"type":"Point"}
}
