{
  "type": "Feature",
  "properties": {
    "iso:country": "GB",
    "wof:name": "TA2 6BY",
    "wof:placetype": "postalcode"
  },
  "geometry": {"coordinates":[-3.12897,51.029471],"type":"Point"}
}
