{
  "type": "Feature",
  "properties": {
    "iso:country":"GB",
    "wof:name":"LN2 2RT",
    "wof:placetype":"postalcode"
},
  "geometry": {"coordinates":[-0.48196711744368,53.2636755349502],"type":"Point"}
}