{
  "type": "Feature",
  "properties": {
    "iso:country": "GB",
    "wof:name": "W3 6TP",
    "wof:placetype": "postalcode"
  },
  "geometry": {"coordinates":[-0.264519,51.518773],"type":"Point"}
}
