{
  "type": "Feature",
  "properties": {
    "date:inception_lower": "1980-01-01",
    "date:inception_upper": "1980-01-01",
    "iso:country": "GB",
    "wof:name": "HA0 2JS",
    "wof:placetype": "postalcode"
  },
  "geometry": {"coordinates":[-0.304839,51.55356],"type":"Point"}
}
