{
  "type": "Feature",
  "properties": {
    "iso:country":"GB",
    "wof:name":"HA0 2JS",
    "wof:placetype":"postalcode"
},
  "geometry": {"coordinates":[-0.30483941553805,51.55356029493716],"type":"Point"}
}