{
  "type": "Feature",
  "properties": {
    "date:inception_lower": "1980-01-01",
    "date:inception_upper": "1980-01-01",
    "iso:country": "GB",
    "wof:name": "CT21 4NN",
    "wof:placetype": "postalcode"
  },
  "geometry": {"coordinates":[1.023276,51.060436],"type":"Point"}
}
