{
  "type": "Feature",
  "properties": {
    "iso:country": "GB",
    "wof:name": "DL14 0PB",
    "wof:placetype": "postalcode"
  },
  "geometry": {"coordinates":[-1.777858,54.635302],"type":"Point"}
}
