{
  "type": "Feature",
  "properties": {
    "iso:country":"GB",
    "wof:name":"DL14 0PB",
    "wof:placetype":"postalcode"
},
  "geometry": {"coordinates":[-1.77785832494554,54.63530224330055],"type":"Point"}
}