{
  "type": "Feature",
  "properties": {
    "iso:country": "GB",
    "wof:name": "NP7 8HB",
    "wof:placetype": "postalcode"
  },
  "geometry": {"coordinates":[-2.883569,51.932556],"type":"Point"}
}
