{
  "type": "Feature",
  "properties": {
    "iso:country": "GB",
    "wof:name": "RH4 2EB",
    "wof:placetype": "postalcode"
  },
  "geometry": {"coordinates":[-0.330422,51.228364],"type":"Point"}
}
