{
  "type": "Feature",
  "properties": {
    "iso:country": "GB",
    "wof:name": "CM3 4EU",
    "wof:placetype": "postalcode"
  },
  "geometry": {"coordinates":[0.584894,51.695207],"type":"Point"}
}
