{
  "type": "Feature",
  "properties": {
    "iso:country":"GB",
    "wof:name":"CM3 4EG",
    "wof:placetype":"postalcode"
},
  "geometry": {"coordinates":[0.5700870726069,51.71456155588846],"type":"Point"}
}