{
  "type": "Feature",
  "properties": {
    "date:inception_lower": "1980-01-01",
    "date:inception_upper": "1980-01-01",
    "iso:country": "GB",
    "wof:name": "CM3 4EG",
    "wof:placetype": "postalcode"
  },
  "geometry": {"coordinates":[0.570087,51.714562],"type":"Point"}
}
