{
  "type": "Feature",
  "properties": {
    "iso:country":"GB",
    "wof:name":"FY7 7EG",
    "wof:placetype":"postalcode"
},
  "geometry": {"coordinates":[-3.0313420019356,53.9161851807989],"type":"Point"}
}