{
  "type": "Feature",
  "properties": {
    "iso:country":"GB",
    "wof:name":"MK45 4HY",
    "wof:placetype":"postalcode"
},
  "geometry": {"coordinates":[-0.38102486402474,52.01052384514056],"type":"Point"}
}