{
  "type": "Feature",
  "properties": {
    "date:inception_lower":"1980-01-01",
    "date:inception_upper":"1980-01-31",
    "iso:country":"GB",
    "wof:name":"LN11 7PZ",
    "wof:placetype":"postalcode"
},
  "geometry": {"coordinates":[0.141937,53.439886],"type":"Point"}
}