{
  "type": "Feature",
  "properties": {
    "iso:country": "GB",
    "wof:name": "LN11 7PZ",
    "wof:placetype": "postalcode"
  },
  "geometry": {"coordinates":[0.141937,53.439886],"type":"Point"}
}
