{
  "type": "Feature",
  "properties": {
    "iso:country":"GB",
    "wof:name":"LN11 7PZ",
    "wof:placetype":"postalcode"
},
  "geometry": {"coordinates":[0.14193714113408,53.43988561498418],"type":"Point"}
}