{
  "type": "Feature",
  "properties": {
    "date:inception_lower":"1980-01-01",
    "date:inception_upper":"1980-01-31",
    "iso:country":"GB",
    "wof:name":"BD5 7EZ",
    "wof:placetype":"postalcode"
},
  "geometry": {"coordinates":[-1.753459,53.77946],"type":"Point"}
}