{
  "type": "Feature",
  "properties": {
    "iso:country": "GB",
    "wof:name": "EX4 8DH",
    "wof:placetype": "postalcode"
  },
  "geometry": {"coordinates":[-3.48803,50.735693],"type":"Point"}
}
