{
  "type": "Feature",
  "properties": {
    "date:inception_lower":"1980-01-01",
    "date:inception_upper":"1980-01-31",
    "iso:country":"GB",
    "wof:name":"EX4 8DH",
    "wof:placetype":"postalcode"
},
  "geometry": {"coordinates":[-3.48803,50.735693],"type":"Point"}
}