{
  "type": "Feature",
  "properties": {
    "date:inception_lower": "1980-01-01",
    "date:inception_upper": "1980-01-01",
    "iso:country": "GB",
    "wof:name": "TA6 6PJ",
    "wof:placetype": "postalcode"
  },
  "geometry": {"coordinates":[-3.066588,51.075109],"type":"Point"}
}
