{
  "type": "Feature",
  "properties": {
    "iso:country":"GB",
    "wof:name":"TA6 6PJ",
    "wof:placetype":"postalcode"
},
  "geometry": {"coordinates":[-3.06658833698402,51.07510939779652],"type":"Point"}
}