{
  "type": "Feature",
  "properties": {
    "date:inception_lower": "2023-01-01",
    "date:inception_upper": "2023-01-01",
    "iso:country": "GB",
    "wof:name": "NE61 5JZ",
    "wof:placetype": "postalcode"
  },
  "geometry": {"coordinates":[-1.569659,55.220431],"type":"Point"}
}
