{
  "type": "Feature",
  "properties": {
    "date:inception_lower": "1980-01-01",
    "date:inception_upper": "1980-01-01",
    "iso:country": "GB",
    "wof:name": "PR5 0SJ",
    "wof:placetype": "postalcode"
  },
  "geometry": {"coordinates":[-2.584056,53.728171],"type":"Point"}
}
