{
  "type": "Feature",
  "properties": {
    "iso:country":"GB",
    "wof:name":"PR5 0SJ",
    "wof:placetype":"postalcode"
},
  "geometry": {"coordinates":[-2.5840561573035,53.72817136938228],"type":"Point"}
}