{
  "type": "Feature",
  "properties": {
    "date:inception_lower": "1993-08-01",
    "date:inception_upper": "1993-08-01",
    "iso:country": "GB",
    "wof:name": "SS12 9PR",
    "wof:placetype": "postalcode"
  },
  "geometry": {"coordinates":[0.52706,51.604924],"type":"Point"}
}
