{
  "type": "Feature",
  "properties": {
    "iso:country": "GB",
    "wof:name": "SS12 9PR",
    "wof:placetype": "postalcode"
  },
  "geometry": {"coordinates":[0.52706,51.604924],"type":"Point"}
}
