{
  "type": "Feature",
  "properties": {
    "iso:country": "GB",
    "wof:name": "BB8 8FF",
    "wof:placetype": "postalcode"
  },
  "geometry": {"coordinates":[-2.183127,53.848722],"type":"Point"}
}
