{
  "type": "Feature",
  "properties": {
    "iso:country":"GB",
    "wof:name":"BA12 9PB",
    "wof:placetype":"postalcode"
},
  "geometry": {"coordinates":[-2.18207500416282,51.19631805202901],"type":"Point"}
}