{
  "type": "Feature",
  "properties": {
    "iso:country": "GB",
    "wof:name": "CF35 6RT",
    "wof:placetype": "postalcode"
  },
  "geometry": {"coordinates":[-3.49123,51.530066],"type":"Point"}
}
