{
  "type": "Feature",
  "properties": {
    "iso:country":"GB",
    "wof:name":"LS18 5HD",
    "wof:placetype":"postalcode"
},
  "geometry": {"coordinates":[-1.64734958332332,53.84878024667864],"type":"Point"}
}