{
  "type": "Feature",
  "properties": {
    "iso:country": "GB",
    "wof:name": "LS18 5HD",
    "wof:placetype": "postalcode"
  },
  "geometry": {"coordinates":[-1.64735,53.84878],"type":"Point"}
}
