{
  "type": "Feature",
  "properties": {
    "iso:country":"GB",
    "wof:name":"CB6 2UQ",
    "wof:placetype":"postalcode"
},
  "geometry": {"coordinates":[0.25229589380592,52.43285945557028],"type":"Point"}
}