{
  "type": "Feature",
  "properties": {
    "iso:country":"GB",
    "wof:name":"PR7 7DQ",
    "wof:placetype":"postalcode"
},
  "geometry": {"coordinates":[-2.6611840308891,53.67758892231125],"type":"Point"}
}