{
  "type": "Feature",
  "properties": {
    "iso:country": "GB",
    "wof:name": "PR7 7DQ",
    "wof:placetype": "postalcode"
  },
  "geometry": {"coordinates":[-2.661184,53.677589],"type":"Point"}
}
