{
  "type": "Feature",
  "properties": {
    "date:inception_lower": "2009-10-01",
    "date:inception_upper": "2009-10-01",
    "iso:country": "GB",
    "wof:name": "PR7 7DQ",
    "wof:placetype": "postalcode"
  },
  "geometry": {"coordinates":[-2.661184,53.677589],"type":"Point"}
}
