{
  "type": "Feature",
  "properties": {
    "iso:country":"GB",
    "wof:name":"EN5 5NB",
    "wof:placetype":"postalcode"
},
  "geometry": {"coordinates":[-0.18485890637473,51.65559097528495],"type":"Point"}
}