{
  "type": "Feature",
  "properties": {
    "iso:country": "GB",
    "wof:name": "EN5 5NB",
    "wof:placetype": "postalcode"
  },
  "geometry": {"coordinates":[-0.184859,51.655591],"type":"Point"}
}
