{
  "type": "Feature",
  "properties": {
    "iso:country":"GB",
    "wof:name":"WF5 9SJ",
    "wof:placetype":"postalcode"
},
  "geometry": {"coordinates":[-1.55760048364357,53.68481014689232],"type":"Point"}
}