{
  "type": "Feature",
  "properties": {
    "date:inception_lower":"1980-01-01",
    "date:inception_upper":"1980-01-31",
    "iso:country":"GB",
    "wof:name":"WF5 9SJ",
    "wof:placetype":"postalcode"
},
  "geometry": {"coordinates":[-1.5576,53.68481],"type":"Point"}
}