{
  "type": "Feature",
  "properties": {
    "date:inception_lower":"2013-07-01",
    "date:inception_upper":"2013-07-31",
    "iso:country":"GB",
    "wof:name":"TF9 1GD",
    "wof:placetype":"postalcode"
},
  "geometry": {"coordinates":[-2.481446,52.908456],"type":"Point"}
}