{
  "type": "Feature",
  "properties": {
    "iso:country":"GB",
    "wof:name":"TF9 1GD",
    "wof:placetype":"postalcode"
},
  "geometry": {"coordinates":[-2.48144645010482,52.90845628615921],"type":"Point"}
}