{
  "type": "Feature",
  "properties": {
    "iso:country":"GB",
    "wof:name":"SA6 5NJ",
    "wof:placetype":"postalcode"
},
  "geometry": {"coordinates":[-3.88422639135025,51.69852060727602],"type":"Point"}
}