{
  "type": "Feature",
  "properties": {
    "date:inception_lower": "1985-10-01",
    "date:inception_upper": "1985-10-01",
    "iso:country": "GB",
    "wof:name": "L30 4XR",
    "wof:placetype": "postalcode"
  },
  "geometry": {"coordinates":[-2.970653,53.469988],"type":"Point"}
}
