{
  "type": "Feature",
  "properties": {
    "iso:country":"GB",
    "wof:name":"L30 4XR",
    "wof:placetype":"postalcode"
},
  "geometry": {"coordinates":[-2.97072855612879,53.46992629956561],"type":"Point"}
}