{
  "type": "Feature",
  "properties": {
    "date:inception_lower": "2001-12-01",
    "date:inception_upper": "2001-12-01",
    "iso:country": "GB",
    "wof:name": "ME15 6GE",
    "wof:placetype": "postalcode"
  },
  "geometry": {"coordinates":[0.523214,51.259467],"type":"Point"}
}
