{
  "type": "Feature",
  "properties": {
    "iso:country":"GB",
    "wof:name":"ME15 6GE",
    "wof:placetype":"postalcode"
},
  "geometry": {"coordinates":[0.52321406498067,51.2594668580946],"type":"Point"}
}