{
  "type": "Feature",
  "properties": {
    "iso:country":"GB",
    "wof:name":"RM5 2AR",
    "wof:placetype":"postalcode"
},
  "geometry": {"coordinates":[0.15709991789283,51.59736109788224],"type":"Point"}
}