{
  "type": "Feature",
  "properties": {
    "date:inception_lower":"1980-01-01",
    "date:inception_upper":"1980-01-31",
    "iso:country":"GB",
    "wof:name":"RM5 2AR",
    "wof:placetype":"postalcode"
},
  "geometry": {"coordinates":[0.157083,51.597337],"type":"Point"}
}