{
  "type": "Feature",
  "properties": {
    "iso:country": "GB",
    "wof:name": "SW1V 4PS",
    "wof:placetype": "postalcode"
  },
  "geometry": {"coordinates":[-0.144046,51.4905],"type":"Point"}
}
