{
  "type": "Feature",
  "properties": {
    "date:inception_lower":"1980-01-01",
    "date:inception_upper":"1980-01-31",
    "iso:country":"GB",
    "wof:name":"SW1V 4PS",
    "wof:placetype":"postalcode"
},
  "geometry": {"coordinates":[-0.144046,51.4905],"type":"Point"}
}