{
  "type": "Feature",
  "properties": {
    "iso:country":"GB",
    "wof:name":"EN5 2AY",
    "wof:placetype":"postalcode"
},
  "geometry": {"coordinates":[-0.2355163627482,51.63772220786915],"type":"Point"}
}