{
  "type": "Feature",
  "properties": {
    "iso:country":"GB",
    "wof:name":"PA5 9TQ",
    "wof:placetype":"postalcode"
},
  "geometry": {"coordinates":[-4.5088929836292,55.82481201995134],"type":"Point"}
}