{
  "type": "Feature",
  "properties": {
    "iso:country":"GB",
    "wof:name":"G74 4DY",
    "wof:placetype":"postalcode"
},
  "geometry": {"coordinates":[-4.17316491984216,55.77087238539486],"type":"Point"}
}