{
  "type": "Feature",
  "properties": {
    "iso:country":"GB",
    "wof:name":"NE11 9TW",
    "wof:placetype":"postalcode"
},
  "geometry": {"coordinates":[-1.62824129920359,54.94511481886073],"type":"Point"}
}