{
  "type": "Feature",
  "properties": {
    "iso:country":"GB",
    "wof:name":"E6 1LQ",
    "wof:placetype":"postalcode"
},
  "geometry": {"coordinates":[0.04461623725217,51.53362039842883],"type":"Point"}
}