{
  "type": "Feature",
  "properties": {
    "date:inception_lower": "2003-06-01",
    "date:inception_upper": "2003-06-01",
    "iso:country": "GB",
    "wof:name": "ME19 4BQ",
    "wof:placetype": "postalcode"
  },
  "geometry": {"coordinates":[0.411081,51.269053],"type":"Point"}
}
