{
  "type": "Feature",
  "properties": {
    "iso:country":"GB",
    "wof:name":"ME19 4BQ",
    "wof:placetype":"postalcode"
},
  "geometry": {"coordinates":[0.41108145357998,51.26905287634111],"type":"Point"}
}