{
  "type": "Feature",
  "properties": {
    "iso:country": "GB",
    "wof:name": "BH5 2BU",
    "wof:placetype": "postalcode"
  },
  "geometry": {"coordinates":[-1.818032,50.727433],"type":"Point"}
}
