{
  "type": "Feature",
  "properties": {
    "date:inception_lower": "1995-12-01",
    "date:inception_upper": "1995-12-01",
    "iso:country": "GB",
    "wof:name": "GL4 3TY",
    "wof:placetype": "postalcode"
  },
  "geometry": {"coordinates":[-2.200241,51.857204],"type":"Point"}
}
