{
  "type": "Feature",
  "properties": {
    "iso:country": "GB",
    "wof:name": "NW11 6PN",
    "wof:placetype": "postalcode"
  },
  "geometry": {"coordinates":[-0.185461,51.580389],"type":"Point"}
}
