{
  "type": "Feature",
  "properties": {
    "date:inception_lower": "1980-01-01",
    "date:inception_upper": "1980-01-01",
    "iso:country": "GB",
    "wof:name": "HP6 5PQ",
    "wof:placetype": "postalcode"
  },
  "geometry": {"coordinates":[-0.616479,51.687878],"type":"Point"}
}
