{
  "type": "Feature",
  "properties": {
    "iso:country": "GB",
    "wof:name": "HP6 5PQ",
    "wof:placetype": "postalcode"
  },
  "geometry": {"coordinates":[-0.616479,51.687878],"type":"Point"}
}
