{
  "type": "Feature",
  "properties": {
    "iso:country":"GB",
    "wof:name":"CM2 8HH",
    "wof:placetype":"postalcode"
},
  "geometry": {"coordinates":[0.50457184045669,51.71133651481452],"type":"Point"}
}