{
  "type": "Feature",
  "properties": {
    "iso:country":"GB",
    "wof:name":"S6 2NJ",
    "wof:placetype":"postalcode"
},
  "geometry": {"coordinates":[-1.49921819770182,53.39935017703442],"type":"Point"}
}