{
  "type": "Feature",
  "properties": {
    "iso:country":"GB",
    "wof:name":"CF23 7BR",
    "wof:placetype":"postalcode"
},
  "geometry": {"coordinates":[-3.1462226292402,51.52810895080778],"type":"Point"}
}