{
  "type": "Feature",
  "properties": {
    "date:inception_lower": "1999-06-01",
    "date:inception_upper": "1999-06-01",
    "iso:country": "GB",
    "wof:name": "CF23 7BR",
    "wof:placetype": "postalcode"
  },
  "geometry": {"coordinates":[-3.146223,51.528109],"type":"Point"}
}
