{
  "type": "Feature",
  "properties": {
    "iso:country":"GB",
    "wof:name":"ML6 8AR",
    "wof:placetype":"postalcode"
},
  "geometry": {"coordinates":[-3.95528431971309,55.86245139452559],"type":"Point"}
}