{
  "type": "Feature",
  "properties": {
    "iso:country": "GB",
    "wof:name": "CM7 9AZ",
    "wof:placetype": "postalcode"
  },
  "geometry": {"coordinates":[0.556179,51.886408],"type":"Point"}
}
