{
  "type": "Feature",
  "properties": {
    "iso:country":"GB",
    "wof:name":"CM7 9AZ",
    "wof:placetype":"postalcode"
},
  "geometry": {"coordinates":[0.55617888687977,51.88640847285771],"type":"Point"}
}