{
  "type": "Feature",
  "properties": {
    "iso:country":"GB",
    "wof:name":"HU12 9SY",
    "wof:placetype":"postalcode"
},
  "geometry": {"coordinates":[-0.11654651377461,53.7118743954734],"type":"Point"}
}