{
  "type": "Feature",
  "properties": {
    "iso:country": "GB",
    "wof:name": "HU12 9SY",
    "wof:placetype": "postalcode"
  },
  "geometry": {"coordinates":[-0.116546,53.711874],"type":"Point"}
}
