{
  "type": "Feature",
  "properties": {
    "iso:country":"GB",
    "wof:name":"IV26 2SW",
    "wof:placetype":"postalcode"
},
  "geometry": {"coordinates":[-5.13080971819275,57.89075743467981],"type":"Point"}
}