{
  "type": "Feature",
  "properties": {
    "iso:country": "GB",
    "wof:name": "IV26 2SW",
    "wof:placetype": "postalcode"
  },
  "geometry": {"coordinates":[-5.13081,57.890757],"type":"Point"}
}
