{
  "type": "Feature",
  "properties": {
    "date:inception_lower": "2001-12-01",
    "date:inception_upper": "2001-12-01",
    "iso:country": "GB",
    "wof:name": "IV26 2SW",
    "wof:placetype": "postalcode"
  },
  "geometry": {"coordinates":[-5.13081,57.890757],"type":"Point"}
}
