{
  "type": "Feature",
  "properties": {
    "iso:country":"GB",
    "wof:name":"B33 0NJ",
    "wof:placetype":"postalcode"
},
  "geometry": {"coordinates":[-1.76891661237049,52.47787617604816],"type":"Point"}
}