{
  "type": "Feature",
  "properties": {
    "iso:country":"GB",
    "wof:name":"CB6 1AE",
    "wof:placetype":"postalcode"
},
  "geometry": {"coordinates":[0.26155601837947,52.40166980102934],"type":"Point"}
}