{
  "type": "Feature",
  "properties": {
    "iso:country":"GB",
    "wof:name":"TD9 0DF",
    "wof:placetype":"postalcode"
},
  "geometry": {"coordinates":[-2.7974561125904,55.41572109392142],"type":"Point"}
}