{
  "type": "Feature",
  "properties": {
    "iso:country":"GB",
    "wof:name":"SL9 0EP",
    "wof:placetype":"postalcode"
},
  "geometry": {"coordinates":[-0.54691404331713,51.61536346461601],"type":"Point"}
}