{
  "type": "Feature",
  "properties": {
    "date:inception_lower":"2014-11-01",
    "date:inception_upper":"2014-11-30",
    "iso:country":"GB",
    "wof:name":"M8 9FG",
    "wof:placetype":"postalcode"
},
  "geometry": {"coordinates":[-2.242932,53.508661],"type":"Point"}
}