{
  "type": "Feature",
  "properties": {
    "iso:country":"GB",
    "wof:name":"M8 9FG",
    "wof:placetype":"postalcode"
},
  "geometry": {"coordinates":[-2.24293167365233,53.50866064311281],"type":"Point"}
}