{
  "type": "Feature",
  "properties": {
    "iso:country":"GB",
    "wof:name":"SG8 6NS",
    "wof:placetype":"postalcode"
},
  "geometry": {"coordinates":[0.00789788855429,52.10324057152989],"type":"Point"}
}