{
  "type": "Feature",
  "properties": {
    "iso:country": "GB",
    "wof:name": "M45 7UN",
    "wof:placetype": "postalcode"
  },
  "geometry": {"coordinates":[-2.299637,53.557285],"type":"Point"}
}
