{
  "type": "Feature",
  "properties": {
    "iso:country":"GB",
    "wof:name":"M45 7UN",
    "wof:placetype":"postalcode"
},
  "geometry": {"coordinates":[-2.2996374889448,53.55728488025006],"type":"Point"}
}