{
  "type": "Feature",
  "properties": {
    "date:inception_lower": "2015-10-01",
    "date:inception_upper": "2015-10-01",
    "iso:country": "GB",
    "wof:name": "TD1 2QZ",
    "wof:placetype": "postalcode"
  },
  "geometry": {"coordinates":[-2.762231,55.613792],"type":"Point"}
}
