{
  "type": "Feature",
  "properties": {
    "iso:country": "GB",
    "wof:name": "TD1 2QZ",
    "wof:placetype": "postalcode"
  },
  "geometry": {"coordinates":[-2.762154,55.6139],"type":"Point"}
}
