{
  "type": "Feature",
  "properties": {
    "iso:country":"GB",
    "wof:name":"TD1 2QZ",
    "wof:placetype":"postalcode"
},
  "geometry": {"coordinates":[-2.76211743310186,55.61387391705807],"type":"Point"}
}