{
  "type": "Feature",
  "properties": {
    "date:inception_lower":"2015-10-01",
    "date:inception_upper":"2015-10-31",
    "iso:country":"GB",
    "wof:name":"TD1 2QZ",
    "wof:placetype":"postalcode"
},
  "geometry": {"coordinates":[-2.762154,55.6139],"type":"Point"}
}