{
  "type": "Feature",
  "properties": {
    "iso:country": "GB",
    "wof:name": "OX10 6BN",
    "wof:placetype": "postalcode"
  },
  "geometry": {"coordinates":[-1.081289,51.563871],"type":"Point"}
}
