{
  "type": "Feature",
  "properties": {
    "iso:country":"GB",
    "wof:name":"SP6 3PT",
    "wof:placetype":"postalcode"
},
  "geometry": {"coordinates":[-1.8221377573454,50.91151658595965],"type":"Point"}
}