{
  "type": "Feature",
  "properties": {
    "iso:country":"GB",
    "wof:name":"DE56 1SW",
    "wof:placetype":"postalcode"
},
  "geometry": {"coordinates":[-1.48149275424729,53.01163484199953],"type":"Point"}
}