{
  "type": "Feature",
  "properties": {
    "iso:country":"GB",
    "wof:name":"TN33 0LR",
    "wof:placetype":"postalcode"
},
  "geometry": {"coordinates":[0.48546104959952,50.93144099091191],"type":"Point"}
}