{
  "type": "Feature",
  "properties": {
    "iso:country":"GB",
    "wof:name":"EX2 4TX",
    "wof:placetype":"postalcode"
},
  "geometry": {"coordinates":[-3.50972904802985,50.72166365008957],"type":"Point"}
}