{
  "type": "Feature",
  "properties": {
    "iso:country":"GB",
    "wof:name":"FY4 3NJ",
    "wof:placetype":"postalcode"
},
  "geometry": {"coordinates":[-3.02720196715806,53.7865193203976],"type":"Point"}
}