{
  "type": "Feature",
  "properties": {
    "date:inception_lower":"1980-01-01",
    "date:inception_upper":"1980-01-31",
    "iso:country":"GB",
    "wof:name":"KA19 7QU",
    "wof:placetype":"postalcode"
},
  "geometry": {"coordinates":[-4.598759,55.330165],"type":"Point"}
}