{
  "type": "Feature",
  "properties": {
    "iso:country": "GB",
    "wof:name": "KA19 7QU",
    "wof:placetype": "postalcode"
  },
  "geometry": {"coordinates":[-4.598759,55.330165],"type":"Point"}
}
