{
  "type": "Feature",
  "properties": {
    "iso:country":"GB",
    "wof:name":"BA5 1BR",
    "wof:placetype":"postalcode"
},
  "geometry": {"coordinates":[-2.67148490418637,51.22519479198258],"type":"Point"}
}