{
  "type": "Feature",
  "properties": {
    "date:inception_lower": "1980-01-01",
    "date:inception_upper": "1980-01-01",
    "iso:country": "GB",
    "wof:name": "BA5 1BR",
    "wof:placetype": "postalcode"
  },
  "geometry": {"coordinates":[-2.671488,51.22519],"type":"Point"}
}
