{
  "type": "Feature",
  "properties": {
    "iso:country":"GB",
    "wof:name":"EH5 1EB",
    "wof:placetype":"postalcode"
},
  "geometry": {"coordinates":[-3.22780220576812,55.97721663440647],"type":"Point"}
}