{
  "type": "Feature",
  "properties": {
    "iso:country":"GB",
    "wof:name":"NE11 0AW",
    "wof:placetype":"postalcode"
},
  "geometry": {"coordinates":[-1.63946041564139,54.93871438809676],"type":"Point"}
}