{
  "type": "Feature",
  "properties": {
    "iso:country": "GB",
    "wof:name": "NE11 0AW",
    "wof:placetype": "postalcode"
  },
  "geometry": {"coordinates":[-1.63946,54.938714],"type":"Point"}
}
