{
  "type": "Feature",
  "properties": {
    "iso:country": "GB",
    "wof:name": "HR3 6HG",
    "wof:placetype": "postalcode"
  },
  "geometry": {"coordinates":[-3.093528,52.129306],"type":"Point"}
}
