{
  "type": "Feature",
  "properties": {
    "iso:country":"GB",
    "wof:name":"HR3 6HG",
    "wof:placetype":"postalcode"
},
  "geometry": {"coordinates":[-3.09352789633585,52.12930570121974],"type":"Point"}
}