{
  "type": "Feature",
  "properties": {
    "iso:country": "GB",
    "wof:name": "GL51 7RU",
    "wof:placetype": "postalcode"
  },
  "geometry": {"coordinates":[-2.114139,51.903262],"type":"Point"}
}
