{
  "type": "Feature",
  "properties": {
    "iso:country": "GB",
    "wof:name": "B5 6NE",
    "wof:placetype": "postalcode"
  },
  "geometry": {"coordinates":[-1.894759,52.47089],"type":"Point"}
}
