{
  "type": "Feature",
  "properties": {
    "iso:country":"GB",
    "wof:name":"BN7 3HR",
    "wof:placetype":"postalcode"
},
  "geometry": {"coordinates":[0.01637945172147,50.83710501150677],"type":"Point"}
}