{
  "type": "Feature",
  "properties": {
    "iso:country":"GB",
    "wof:name":"RG23 7DP",
    "wof:placetype":"postalcode"
},
  "geometry": {"coordinates":[-1.1718254406761,51.25208770852981],"type":"Point"}
}