{
  "type": "Feature",
  "properties": {
    "iso:country":"GB",
    "wof:name":"SG14 2BF",
    "wof:placetype":"postalcode"
},
  "geometry": {"coordinates":[-0.10268366363567,51.82675411594382],"type":"Point"}
}