{
  "type": "Feature",
  "properties": {
    "iso:country": "GB",
    "wof:name": "SG14 2BF",
    "wof:placetype": "postalcode"
  },
  "geometry": {"coordinates":[-0.103233,51.826833],"type":"Point"}
}
