{
  "type": "Feature",
  "properties": {
    "date:inception_lower": "1980-01-01",
    "date:inception_upper": "1980-01-01",
    "iso:country": "GB",
    "wof:name": "HG3 5AN",
    "wof:placetype": "postalcode"
  },
  "geometry": {"coordinates":[-1.759139,54.085658],"type":"Point"}
}
