{
  "type": "Feature",
  "properties": {
    "iso:country":"GB",
    "wof:name":"HG3 5AN",
    "wof:placetype":"postalcode"
},
  "geometry": {"coordinates":[-1.75913954072555,54.08565828556072],"type":"Point"}
}