{
  "type": "Feature",
  "properties": {
    "iso:country": "GB",
    "wof:name": "CF44 8EX",
    "wof:placetype": "postalcode"
  },
  "geometry": {"coordinates":[-3.464475,51.72136],"type":"Point"}
}
