{
  "type": "Feature",
  "properties": {
    "date:inception_lower": "2017-10-01",
    "date:inception_upper": "2017-10-01",
    "iso:country": "GB",
    "wof:name": "CF44 8EX",
    "wof:placetype": "postalcode"
  },
  "geometry": {"coordinates":[-3.464475,51.72136],"type":"Point"}
}
