{
  "type": "Feature",
  "properties": {
    "iso:country": "GB",
    "wof:name": "RG9 3JD",
    "wof:placetype": "postalcode"
  },
  "geometry": {"coordinates":[-0.890938,51.532341],"type":"Point"}
}
