{
  "type": "Feature",
  "properties": {
    "iso:country":"GB",
    "wof:name":"RG9 3JD",
    "wof:placetype":"postalcode"
},
  "geometry": {"coordinates":[-0.89095760806593,51.53233790519577],"type":"Point"}
}