{
  "type": "Feature",
  "properties": {
    "iso:country":"GB",
    "wof:name":"YO42 1TE",
    "wof:placetype":"postalcode"
},
  "geometry": {"coordinates":[-0.77216789973033,54.00050400888017],"type":"Point"}
}