{
  "type": "Feature",
  "properties": {
    "iso:country": "GB",
    "wof:name": "YO42 1TE",
    "wof:placetype": "postalcode"
  },
  "geometry": {"coordinates":[-0.772168,54.000504],"type":"Point"}
}
