{
  "type": "Feature",
  "properties": {
    "date:inception_lower": "1980-01-01",
    "date:inception_upper": "1980-01-01",
    "iso:country": "GB",
    "wof:name": "BN21 3UL",
    "wof:placetype": "postalcode"
  },
  "geometry": {"coordinates":[0.280884,50.770957],"type":"Point"}
}
