{
  "type": "Feature",
  "properties": {
    "date:inception_lower": "1986-07-01",
    "date:inception_upper": "1986-07-01",
    "iso:country": "GB",
    "wof:name": "OL4 3DZ",
    "wof:placetype": "postalcode"
  },
  "geometry": {"coordinates":[-2.071301,53.539697],"type":"Point"}
}
