{
  "type": "Feature",
  "properties": {
    "iso:country":"GB",
    "wof:name":"OL4 3DZ",
    "wof:placetype":"postalcode"
},
  "geometry": {"coordinates":[-2.07160563340632,53.5399142481901],"type":"Point"}
}