{
  "type": "Feature",
  "properties": {
    "iso:country":"GB",
    "wof:name":"S70 6NB",
    "wof:placetype":"postalcode"
},
  "geometry": {"coordinates":[-1.49300300557979,53.54385086779883],"type":"Point"}
}