{
  "type": "Feature",
  "properties": {
    "iso:country":"GB",
    "wof:name":"FY6 7SZ",
    "wof:placetype":"postalcode"
},
  "geometry": {"coordinates":[-2.99550553269696,53.84721531957863],"type":"Point"}
}