{
  "type": "Feature",
  "properties": {
    "date:inception_lower": "1980-01-01",
    "date:inception_upper": "1980-01-01",
    "iso:country": "GB",
    "wof:name": "FY6 7SZ",
    "wof:placetype": "postalcode"
  },
  "geometry": {"coordinates":[-2.995505,53.847215],"type":"Point"}
}
