{
  "type": "Feature",
  "properties": {
    "iso:country":"GB",
    "wof:name":"CF5 2QD",
    "wof:placetype":"postalcode"
},
  "geometry": {"coordinates":[-3.23057757166254,51.49901961375088],"type":"Point"}
}