{
  "type": "Feature",
  "properties": {
    "iso:country": "GB",
    "wof:name": "KY11 2AJ",
    "wof:placetype": "postalcode"
  },
  "geometry": {"coordinates":[-3.43504,56.030267],"type":"Point"}
}
