{
  "type": "Feature",
  "properties": {
    "iso:country":"GB",
    "wof:name":"KY11 2AJ",
    "wof:placetype":"postalcode"
},
  "geometry": {"coordinates":[-3.43503989250422,56.0302669830426],"type":"Point"}
}