{
  "type": "Feature",
  "properties": {
    "iso:country":"GB",
    "wof:name":"N7 8BE",
    "wof:placetype":"postalcode"
},
  "geometry": {"coordinates":[-0.11236718510509,51.5445966403835],"type":"Point"}
}