{
  "type": "Feature",
  "properties": {
    "date:inception_lower": "1980-01-01",
    "date:inception_upper": "1980-01-01",
    "iso:country": "GB",
    "wof:name": "N7 8BE",
    "wof:placetype": "postalcode"
  },
  "geometry": {"coordinates":[-0.112367,51.544597],"type":"Point"}
}
