{
  "type": "Feature",
  "properties": {
    "iso:country": "GB",
    "wof:name": "SY21 7AU",
    "wof:placetype": "postalcode"
  },
  "geometry": {"coordinates":[-3.142287,52.657137],"type":"Point"}
}
