{
  "type": "Feature",
  "properties": {
    "iso:country": "GB",
    "wof:name": "DN22 9JH",
    "wof:placetype": "postalcode"
  },
  "geometry": {"coordinates":[-0.944566,53.350477],"type":"Point"}
}
