{
  "type": "Feature",
  "properties": {
    "iso:country": "GB",
    "wof:name": "AL10 0FG",
    "wof:placetype": "postalcode"
  },
  "geometry": {"coordinates":[-0.2326,51.763182],"type":"Point"}
}
