{
  "type": "Feature",
  "properties": {
    "date:inception_lower": "2008-11-01",
    "date:inception_upper": "2008-11-01",
    "iso:country": "GB",
    "wof:name": "AL10 0FG",
    "wof:placetype": "postalcode"
  },
  "geometry": {"coordinates":[-0.2326,51.763182],"type":"Point"}
}
