{
  "type": "Feature",
  "properties": {
    "iso:country":"GB",
    "wof:name":"DG6 4TA",
    "wof:placetype":"postalcode"
},
  "geometry": {"coordinates":[-4.12535957942247,54.85662711865803],"type":"Point"}
}