{
  "type": "Feature",
  "properties": {
    "iso:country":"GB",
    "wof:name":"SL6 4LB",
    "wof:placetype":"postalcode"
},
  "geometry": {"coordinates":[-0.75256291919063,51.51934870023597],"type":"Point"}
}