{
  "type": "Feature",
  "properties": {
    "iso:country":"GB",
    "wof:name":"SL6 7SX",
    "wof:placetype":"postalcode"
},
  "geometry": {"coordinates":[-0.73219012509832,51.53673649136591],"type":"Point"}
}