{
  "type": "Feature",
  "properties": {
    "iso:country": "GB",
    "wof:name": "SL6 7SX",
    "wof:placetype": "postalcode"
  },
  "geometry": {"coordinates":[-0.73219,51.536736],"type":"Point"}
}
