{
  "type": "Feature",
  "properties": {
    "date:inception_lower": "1980-01-01",
    "date:inception_upper": "1980-01-01",
    "iso:country": "GB",
    "wof:name": "SL6 7SX",
    "wof:placetype": "postalcode"
  },
  "geometry": {"coordinates":[-0.73219,51.536736],"type":"Point"}
}
