{
  "type": "Feature",
  "properties": {
    "date:inception_lower":"1981-06-01",
    "date:inception_upper":"1981-06-30",
    "iso:country":"GB",
    "wof:name":"NR33 8LT",
    "wof:placetype":"postalcode"
},
  "geometry": {"coordinates":[1.706977,52.459054],"type":"Point"}
}