{
  "type": "Feature",
  "properties": {
    "iso:country":"GB",
    "wof:name":"SA1 7DZ",
    "wof:placetype":"postalcode"
},
  "geometry": {"coordinates":[-3.90714035829467,51.64738893683498],"type":"Point"}
}