{
  "type": "Feature",
  "properties": {
    "iso:country": "GB",
    "wof:name": "TQ4 7LQ",
    "wof:placetype": "postalcode"
  },
  "geometry": {"coordinates":[-3.564078,50.414375],"type":"Point"}
}
