{
  "type": "Feature",
  "properties": {
    "date:inception_lower": "2013-01-01",
    "date:inception_upper": "2013-01-01",
    "iso:country": "GB",
    "wof:name": "TQ4 7LQ",
    "wof:placetype": "postalcode"
  },
  "geometry": {"coordinates":[-3.564078,50.414375],"type":"Point"}
}
