{
  "type": "Feature",
  "properties": {
    "date:inception_lower": "1994-12-01",
    "date:inception_upper": "1994-12-01",
    "iso:country": "GB",
    "wof:name": "SE16 3BB",
    "wof:placetype": "postalcode"
  },
  "geometry": {"coordinates":[-0.061048,51.486],"type":"Point"}
}
