{
  "type": "Feature",
  "properties": {
    "iso:country":"GB",
    "wof:name":"TS27 3AS",
    "wof:placetype":"postalcode"
},
  "geometry": {"coordinates":[-1.27432664626574,54.70946095292965],"type":"Point"}
}