{
  "type": "Feature",
  "properties": {
    "iso:country": "GB",
    "wof:name": "TS27 3AS",
    "wof:placetype": "postalcode"
  },
  "geometry": {"coordinates":[-1.274327,54.709461],"type":"Point"}
}
