{
  "type": "Feature",
  "properties": {
    "date:inception_lower":"1980-01-01",
    "date:inception_upper":"1980-01-31",
    "iso:country":"GB",
    "wof:name":"TS27 3AS",
    "wof:placetype":"postalcode"
},
  "geometry": {"coordinates":[-1.274327,54.709461],"type":"Point"}
}