{
  "type": "Feature",
  "properties": {
    "iso:country":"GB",
    "wof:name":"ME14 4BF",
    "wof:placetype":"postalcode"
},
  "geometry": {"coordinates":[0.58129643031792,51.27202340253568],"type":"Point"}
}