{
  "type": "Feature",
  "properties": {
    "iso:country":"GB",
    "wof:name":"CM3 1DH",
    "wof:placetype":"postalcode"
},
  "geometry": {"coordinates":[0.45369970667682,51.79280773575384],"type":"Point"}
}