{
  "type": "Feature",
  "properties": {
    "iso:country":"GB",
    "wof:name":"W1D 6NQ",
    "wof:placetype":"postalcode"
},
  "geometry": {"coordinates":[-0.13161345229158,51.5120191752745],"type":"Point"}
}