{
  "type": "Feature",
  "properties": {
    "iso:country":"GB",
    "wof:name":"HU4 7SD",
    "wof:placetype":"postalcode"
},
  "geometry": {"coordinates":[-0.41371705056538,53.74507760823725],"type":"Point"}
}