{
  "type": "Feature",
  "properties": {
    "date:inception_lower":"1980-01-01",
    "date:inception_upper":"1980-01-31",
    "iso:country":"GB",
    "wof:name":"HU4 7SD",
    "wof:placetype":"postalcode"
},
  "geometry": {"coordinates":[-0.413717,53.745078],"type":"Point"}
}