{
  "type": "Feature",
  "properties": {
    "iso:country": "GB",
    "wof:name": "HU4 7SD",
    "wof:placetype": "postalcode"
  },
  "geometry": {"coordinates":[-0.413717,53.745078],"type":"Point"}
}
