{
  "type": "Feature",
  "properties": {
    "iso:country":"GB",
    "wof:name":"CM5 0SR",
    "wof:placetype":"postalcode"
},
  "geometry": {"coordinates":[0.33309981734052,51.75516476843246],"type":"Point"}
}