{
  "type": "Feature",
  "properties": {
    "iso:country": "GB",
    "wof:name": "LL30 2PX",
    "wof:placetype": "postalcode"
  },
  "geometry": {"coordinates":[-3.836613,53.313989],"type":"Point"}
}
