{
  "type": "Feature",
  "properties": {
    "iso:country":"GB",
    "wof:name":"LL30 2PX",
    "wof:placetype":"postalcode"
},
  "geometry": {"coordinates":[-3.83661293515813,53.31398875338827],"type":"Point"}
}