{
  "type": "Feature",
  "properties": {
    "date:inception_lower": "1980-01-01",
    "date:inception_upper": "1980-01-01",
    "iso:country": "GB",
    "wof:name": "G44 3QR",
    "wof:placetype": "postalcode"
  },
  "geometry": {"coordinates":[-4.27311,55.808825],"type":"Point"}
}
