{
  "type": "Feature",
  "properties": {
    "iso:country": "GB",
    "wof:name": "G44 3QR",
    "wof:placetype": "postalcode"
  },
  "geometry": {"coordinates":[-4.27311,55.808825],"type":"Point"}
}
