{
  "type": "Feature",
  "properties": {
    "date:inception_lower": "1980-01-01",
    "date:inception_upper": "1980-01-01",
    "iso:country": "GB",
    "wof:name": "PR1 3RX",
    "wof:placetype": "postalcode"
  },
  "geometry": {"coordinates":[-2.69606,53.755524],"type":"Point"}
}
