{
  "type": "Feature",
  "properties": {
    "iso:country":"GB",
    "wof:name":"TW20 8LH",
    "wof:placetype":"postalcode"
},
  "geometry": {"coordinates":[-0.53552068067513,51.41978768244385],"type":"Point"}
}