{
  "type": "Feature",
  "properties": {
    "date:inception_lower": "1980-01-01",
    "date:inception_upper": "1980-01-01",
    "iso:country": "GB",
    "wof:name": "LL77 7YJ",
    "wof:placetype": "postalcode"
  },
  "geometry": {"coordinates":[-4.308006,53.255124],"type":"Point"}
}
