{
  "type": "Feature",
  "properties": {
    "iso:country": "GB",
    "wof:name": "BB9 5RZ",
    "wof:placetype": "postalcode"
  },
  "geometry": {"coordinates":[-2.232263,53.826018],"type":"Point"}
}
