{
  "type": "Feature",
  "properties": {
    "iso:country": "GB",
    "wof:name": "HP15 7DL",
    "wof:placetype": "postalcode"
  },
  "geometry": {"coordinates":[-0.709927,51.657047],"type":"Point"}
}
