{
  "type": "Feature",
  "properties": {
    "date:inception_lower":"2006-07-01",
    "date:inception_upper":"2006-07-31",
    "iso:country":"GB",
    "wof:name":"HP15 7DL",
    "wof:placetype":"postalcode"
},
  "geometry": {"coordinates":[-0.709927,51.657047],"type":"Point"}
}