{
  "type": "Feature",
  "properties": {
    "iso:country": "GB",
    "wof:name": "WF11 8PY",
    "wof:placetype": "postalcode"
  },
  "geometry": {"coordinates":[-1.273031,53.710566],"type":"Point"}
}
