{
  "type": "Feature",
  "properties": {
    "iso:country":"GB",
    "wof:name":"G69 0BN",
    "wof:placetype":"postalcode"
},
  "geometry": {"coordinates":[-4.08394828011373,55.91177204894685],"type":"Point"}
}