{
  "type": "Feature",
  "properties": {
    "iso:country": "GB",
    "wof:name": "CF3 3LN",
    "wof:placetype": "postalcode"
  },
  "geometry": {"coordinates":[-3.130264,51.507709],"type":"Point"}
}
