{
  "type": "Feature",
  "properties": {
    "date:inception_lower": "1999-06-01",
    "date:inception_upper": "1999-06-01",
    "iso:country": "GB",
    "wof:name": "CF3 3LN",
    "wof:placetype": "postalcode"
  },
  "geometry": {"coordinates":[-3.130264,51.507709],"type":"Point"}
}
