{
  "type": "Feature",
  "properties": {
    "iso:country":"GB",
    "wof:name":"DL13 4LF",
    "wof:placetype":"postalcode"
},
  "geometry": {"coordinates":[-1.81438422347915,54.74179235204075],"type":"Point"}
}