{
  "type": "Feature",
  "properties": {
    "date:inception_lower": "1980-01-01",
    "date:inception_upper": "1980-01-01",
    "iso:country": "GB",
    "wof:name": "GL20 6AW",
    "wof:placetype": "postalcode"
  },
  "geometry": {"coordinates":[-2.217629,52.020814],"type":"Point"}
}
