{
  "type": "Feature",
  "properties": {
    "iso:country":"GB",
    "wof:name":"GL20 6AW",
    "wof:placetype":"postalcode"
},
  "geometry": {"coordinates":[-2.21762885293044,52.02081446263971],"type":"Point"}
}