{
  "type": "Feature",
  "properties": {
    "date:inception_lower": "1980-01-01",
    "date:inception_upper": "1980-01-01",
    "iso:country": "GB",
    "wof:name": "CO10 8BY",
    "wof:placetype": "postalcode"
  },
  "geometry": {"coordinates":[0.631804,52.090222],"type":"Point"}
}
