{
  "type": "Feature",
  "properties": {
    "iso:country":"GB",
    "wof:name":"TS3 0SS",
    "wof:placetype":"postalcode"
},
  "geometry": {"coordinates":[-1.20038283922207,54.54688847147565],"type":"Point"}
}