{
  "type": "Feature",
  "properties": {
    "date:inception_lower":"1985-04-01",
    "date:inception_upper":"1985-04-30",
    "iso:country":"GB",
    "wof:name":"TS3 0SS",
    "wof:placetype":"postalcode"
},
  "geometry": {"coordinates":[-1.200383,54.546888],"type":"Point"}
}