{
  "type": "Feature",
  "properties": {
    "iso:country": "GB",
    "wof:name": "NN8 1RS",
    "wof:placetype": "postalcode"
  },
  "geometry": {"coordinates":[-0.670042,52.299127],"type":"Point"}
}
