{
  "type": "Feature",
  "properties": {
    "date:inception_lower": "1993-08-01",
    "date:inception_upper": "1993-08-01",
    "iso:country": "GB",
    "wof:name": "NN8 1RS",
    "wof:placetype": "postalcode"
  },
  "geometry": {"coordinates":[-0.670042,52.299127],"type":"Point"}
}
