{
  "type": "Feature",
  "properties": {
    "iso:country":"GB",
    "wof:name":"NN8 1RS",
    "wof:placetype":"postalcode"
},
  "geometry": {"coordinates":[-0.67003112663429,52.29905841757543],"type":"Point"}
}