{
  "type": "Feature",
  "properties": {
    "date:inception_lower":"1986-04-01",
    "date:inception_upper":"1986-04-30",
    "iso:country":"GB",
    "wof:name":"RM1 4QN",
    "wof:placetype":"postalcode"
},
  "geometry": {"coordinates":[0.173352,51.586036],"type":"Point"}
}