{
  "type": "Feature",
  "properties": {
    "iso:country": "GB",
    "wof:name": "TN4 9JR",
    "wof:placetype": "postalcode"
  },
  "geometry": {"coordinates":[0.264775,51.139413],"type":"Point"}
}
