{
  "type": "Feature",
  "properties": {
    "iso:country":"GB",
    "wof:name":"PE16 6HG",
    "wof:placetype":"postalcode"
},
  "geometry": {"coordinates":[0.04221607473636,52.44990147594283],"type":"Point"}
}