{
  "type": "Feature",
  "properties": {
    "iso:country":"GB",
    "wof:name":"BD19 4QL",
    "wof:placetype":"postalcode"
},
  "geometry": {"coordinates":[-1.67910517172247,53.72904113312443],"type":"Point"}
}