{
  "type": "Feature",
  "properties": {
    "iso:country":"GB",
    "wof:name":"BB3 1AG",
    "wof:placetype":"postalcode"
},
  "geometry": {"coordinates":[-2.47031574180847,53.69661116059194],"type":"Point"}
}