{
  "type": "Feature",
  "properties": {
    "iso:country":"GB",
    "wof:name":"EH54 6NT",
    "wof:placetype":"postalcode"
},
  "geometry": {"coordinates":[-3.511259617545,55.878815641113],"type":"Point"}
}