{
  "type": "Feature",
  "properties": {
    "iso:country":"GB",
    "wof:name":"B66 4AN",
    "wof:placetype":"postalcode"
},
  "geometry": {"coordinates":[-1.96749289257492,52.47546287637709],"type":"Point"}
}