{
  "type": "Feature",
  "properties": {
    "date:inception_lower": "1980-01-01",
    "date:inception_upper": "1980-01-01",
    "iso:country": "GB",
    "wof:name": "B43 7EL",
    "wof:placetype": "postalcode"
  },
  "geometry": {"coordinates":[-1.903896,52.554387],"type":"Point"}
}
