{
  "type": "Feature",
  "properties": {
    "iso:country":"GB",
    "wof:name":"B43 7EL",
    "wof:placetype":"postalcode"
},
  "geometry": {"coordinates":[-1.90389643095664,52.55438681116638],"type":"Point"}
}