{
  "type": "Feature",
  "properties": {
    "date:inception_lower": "1990-07-01",
    "date:inception_upper": "1990-07-01",
    "iso:country": "GB",
    "wof:name": "NE46 2HZ",
    "wof:placetype": "postalcode"
  },
  "geometry": {"coordinates":[-2.112929,54.961598],"type":"Point"}
}
