{
  "type": "Feature",
  "properties": {
    "iso:country": "GB",
    "wof:name": "WS9 8SD",
    "wof:placetype": "postalcode"
  },
  "geometry": {"coordinates":[-1.914315,52.61967],"type":"Point"}
}
