{
  "type": "Feature",
  "properties": {
    "date:inception_lower": "1980-01-01",
    "date:inception_upper": "1980-01-01",
    "iso:country": "GB",
    "wof:name": "SY22 5EY",
    "wof:placetype": "postalcode"
  },
  "geometry": {"coordinates":[-3.257987,52.797479],"type":"Point"}
}
