{
  "type": "Feature",
  "properties": {
    "date:inception_lower": "2014-02-01",
    "date:inception_upper": "2014-02-01",
    "iso:country": "GB",
    "wof:name": "RG12 8FR",
    "wof:placetype": "postalcode"
  },
  "geometry": {"coordinates":[-0.777429,51.404432],"type":"Point"}
}
