{
  "type": "Feature",
  "properties": {
    "iso:country": "GB",
    "wof:name": "RG12 8FR",
    "wof:placetype": "postalcode"
  },
  "geometry": {"coordinates":[-0.777429,51.404432],"type":"Point"}
}
