{
  "type": "Feature",
  "properties": {
    "iso:country": "GB",
    "wof:name": "SA4 8QR",
    "wof:placetype": "postalcode"
  },
  "geometry": {"coordinates":[-4.034653,51.732376],"type":"Point"}
}
