{
  "type": "Feature",
  "properties": {
    "iso:country":"GB",
    "wof:name":"SA4 8QR",
    "wof:placetype":"postalcode"
},
  "geometry": {"coordinates":[-4.03465306813449,51.73237605141757],"type":"Point"}
}