{
  "type": "Feature",
  "properties": {
    "iso:country":"GB",
    "wof:name":"NE16 5HU",
    "wof:placetype":"postalcode"
},
  "geometry": {"coordinates":[-1.68064570222933,54.93745455410977],"type":"Point"}
}