{
  "type": "Feature",
  "properties": {
    "date:inception_lower": "1980-01-01",
    "date:inception_upper": "1980-01-01",
    "iso:country": "GB",
    "wof:name": "DN22 0SQ",
    "wof:placetype": "postalcode"
  },
  "geometry": {"coordinates":[-0.908107,53.329216],"type":"Point"}
}
