{
  "type": "Feature",
  "properties": {
    "iso:country":"GB",
    "wof:name":"NE5 3HH",
    "wof:placetype":"postalcode"
},
  "geometry": {"coordinates":[-1.66021986742015,54.99796659380075],"type":"Point"}
}