{
  "type": "Feature",
  "properties": {
    "iso:country":"GB",
    "wof:name":"CA7 4DE",
    "wof:placetype":"postalcode"
},
  "geometry": {"coordinates":[-3.38097163711379,54.86992892729822],"type":"Point"}
}