{
  "type": "Feature",
  "properties": {
    "iso:country":"GB",
    "wof:name":"M40 7JT",
    "wof:placetype":"postalcode"
},
  "geometry": {"coordinates":[-2.21838705898463,53.48868183788436],"type":"Point"}
}