{
  "type": "Feature",
  "properties": {
    "date:inception_lower": "1990-07-01",
    "date:inception_upper": "1990-07-01",
    "iso:country": "GB",
    "wof:name": "SW4 0LG",
    "wof:placetype": "postalcode"
  },
  "geometry": {"coordinates":[-0.142039,51.46413],"type":"Point"}
}
