{
  "type": "Feature",
  "properties": {
    "iso:country":"GB",
    "wof:name":"SW4 0LG",
    "wof:placetype":"postalcode"
},
  "geometry": {"coordinates":[-0.14213716450022,51.46410323783973],"type":"Point"}
}