{
  "type": "Feature",
  "properties": {
    "iso:country": "GB",
    "wof:name": "PR4 5DD",
    "wof:placetype": "postalcode"
  },
  "geometry": {"coordinates":[-2.781886,53.724345],"type":"Point"}
}
