{
  "type": "Feature",
  "properties": {
    "date:inception_lower": "2014-05-01",
    "date:inception_upper": "2014-05-01",
    "iso:country": "GB",
    "wof:name": "PR4 5DD",
    "wof:placetype": "postalcode"
  },
  "geometry": {"coordinates":[-2.781958,53.72412],"type":"Point"}
}
