{
  "type": "Feature",
  "properties": {
    "date:inception_lower": "1980-01-01",
    "date:inception_upper": "1980-01-01",
    "iso:country": "GB",
    "wof:name": "CA11 7YE",
    "wof:placetype": "postalcode"
  },
  "geometry": {"coordinates":[-2.751568,54.664337],"type":"Point"}
}
