{
  "type": "Feature",
  "properties": {
    "iso:country":"GB",
    "wof:name":"CA11 7YE",
    "wof:placetype":"postalcode"
},
  "geometry": {"coordinates":[-2.75116420864554,54.66452987151938],"type":"Point"}
}