{
  "type": "Feature",
  "properties": {
    "iso:country":"GB",
    "wof:name":"OL1 2QL",
    "wof:placetype":"postalcode"
},
  "geometry": {"coordinates":[-2.13332085456929,53.55428752536394],"type":"Point"}
}