{
  "type": "Feature",
  "properties": {
    "iso:country": "GB",
    "wof:name": "OL1 2QL",
    "wof:placetype": "postalcode"
  },
  "geometry": {"coordinates":[-2.133321,53.554288],"type":"Point"}
}
