{
  "type": "Feature",
  "properties": {
    "iso:country": "GB",
    "wof:name": "RG6 3DU",
    "wof:placetype": "postalcode"
  },
  "geometry": {"coordinates":[-0.920788,51.431566],"type":"Point"}
}
