{
  "type": "Feature",
  "properties": {
    "iso:country":"GB",
    "wof:name":"RG6 3DU",
    "wof:placetype":"postalcode"
},
  "geometry": {"coordinates":[-0.92078829990112,51.43156566407959],"type":"Point"}
}