{
  "type": "Feature",
  "properties": {
    "date:inception_lower": "1980-01-01",
    "date:inception_upper": "1980-01-01",
    "iso:country": "GB",
    "wof:name": "SA15 2UB",
    "wof:placetype": "postalcode"
  },
  "geometry": {"coordinates":[-4.165449,51.676477],"type":"Point"}
}
