{
  "type": "Feature",
  "properties": {
    "iso:country":"GB",
    "wof:name":"SA15 2UB",
    "wof:placetype":"postalcode"
},
  "geometry": {"coordinates":[-4.16544895925113,51.6764774020994],"type":"Point"}
}