{
  "type": "Feature",
  "properties": {
    "iso:country":"GB",
    "wof:name":"LE9 1SA",
    "wof:placetype":"postalcode"
},
  "geometry": {"coordinates":[-1.19197668257656,52.55406145432114],"type":"Point"}
}