{
  "type": "Feature",
  "properties": {
    "iso:country":"GB",
    "wof:name":"PL33 9TS",
    "wof:placetype":"postalcode"
},
  "geometry": {"coordinates":[-4.72710418730475,50.62167230475868],"type":"Point"}
}