{
  "type": "Feature",
  "properties": {
    "iso:country":"GB",
    "wof:name":"SY1 1PQ",
    "wof:placetype":"postalcode"
},
  "geometry": {"coordinates":[-2.75532156803215,52.70905071812346],"type":"Point"}
}