{
  "type": "Feature",
  "properties": {
    "date:inception_lower":"2008-07-01",
    "date:inception_upper":"2008-07-31",
    "iso:country":"GB",
    "wof:name":"YO8 3EH",
    "wof:placetype":"postalcode"
},
  "geometry": {"coordinates":[-1.065496,53.788459],"type":"Point"}
}