{
  "type": "Feature",
  "properties": {
    "iso:country": "GB",
    "wof:name": "PH35 4HL",
    "wof:placetype": "postalcode"
  },
  "geometry": {"coordinates":[-4.787398,57.070504],"type":"Point"}
}
