{
  "type": "Feature",
  "properties": {
    "iso:country":"GB",
    "wof:name":"PH35 4HL",
    "wof:placetype":"postalcode"
},
  "geometry": {"coordinates":[-4.78739792427024,57.07050398053702],"type":"Point"}
}