{
  "type": "Feature",
  "properties": {
    "date:inception_lower": "1980-01-01",
    "date:inception_upper": "1980-01-01",
    "iso:country": "GB",
    "wof:name": "LE12 9TX",
    "wof:placetype": "postalcode"
  },
  "geometry": {"coordinates":[-1.338698,52.780688],"type":"Point"}
}
