{
  "type": "Feature",
  "properties": {
    "iso:country": "GB",
    "wof:name": "LE12 9TX",
    "wof:placetype": "postalcode"
  },
  "geometry": {"coordinates":[-1.338698,52.780688],"type":"Point"}
}
