{
  "type": "Feature",
  "properties": {
    "iso:country": "GB",
    "wof:name": "B45 9UH",
    "wof:placetype": "postalcode"
  },
  "geometry": {"coordinates":[-2.023586,52.394384],"type":"Point"}
}
