{
  "type": "Feature",
  "properties": {
    "date:inception_lower": "1996-12-01",
    "date:inception_upper": "1996-12-01",
    "iso:country": "GB",
    "wof:name": "NG24 3LD",
    "wof:placetype": "postalcode"
  },
  "geometry": {"coordinates":[-0.77412,53.060054],"type":"Point"}
}
