{
  "type": "Feature",
  "properties": {
    "iso:country":"GB",
    "wof:name":"BS7 9LQ",
    "wof:placetype":"postalcode"
},
  "geometry": {"coordinates":[-2.57943461452844,51.48017261118918],"type":"Point"}
}