{
  "type": "Feature",
  "properties": {
    "iso:country": "GB",
    "wof:name": "B23 6BA",
    "wof:placetype": "postalcode"
  },
  "geometry": {"coordinates":[-1.844967,52.521149],"type":"Point"}
}
