{
  "type": "Feature",
  "properties": {
    "iso:country":"GB",
    "wof:name":"B23 6BA",
    "wof:placetype":"postalcode"
},
  "geometry": {"coordinates":[-1.84497317232531,52.5211338237839],"type":"Point"}
}