{
  "type": "Feature",
  "properties": {
    "iso:country":"GB",
    "wof:name":"SS17 0EH",
    "wof:placetype":"postalcode"
},
  "geometry": {"coordinates":[0.44329920760319,51.50678276581185],"type":"Point"}
}