{
  "type": "Feature",
  "properties": {
    "iso:country": "GB",
    "wof:name": "L40 5UL",
    "wof:placetype": "postalcode"
  },
  "geometry": {"coordinates":[-2.816496,53.589236],"type":"Point"}
}
