{
  "type": "Feature",
  "properties": {
    "iso:country":"GB",
    "wof:name":"L40 5UL",
    "wof:placetype":"postalcode"
},
  "geometry": {"coordinates":[-2.81649568821424,53.5892355295868],"type":"Point"}
}