{
  "type": "Feature",
  "properties": {
    "iso:country": "GB",
    "wof:name": "LL52 0RB",
    "wof:placetype": "postalcode"
  },
  "geometry": {"coordinates":[-4.202412,52.93845],"type":"Point"}
}
