{
  "type": "Feature",
  "properties": {
    "iso:country":"GB",
    "wof:name":"LL52 0RB",
    "wof:placetype":"postalcode"
},
  "geometry": {"coordinates":[-4.20241190683065,52.93844981676381],"type":"Point"}
}