{
  "type": "Feature",
  "properties": {
    "iso:country":"GB",
    "wof:name":"SW4 7NA",
    "wof:placetype":"postalcode"
},
  "geometry": {"coordinates":[-0.13002358080606,51.46213911418992],"type":"Point"}
}