{
  "type": "Feature",
  "properties": {
    "iso:country": "GB",
    "wof:name": "SG5 4EW",
    "wof:placetype": "postalcode"
  },
  "geometry": {"coordinates":[-0.230423,52.021863],"type":"Point"}
}
