{
  "type": "Feature",
  "properties": {
    "iso:country":"GB",
    "wof:name":"RM15 5NG",
    "wof:placetype":"postalcode"
},
  "geometry": {"coordinates":[0.2798064835154,51.50361855373138],"type":"Point"}
}