{
  "type": "Feature",
  "properties": {
    "iso:country": "GB",
    "wof:name": "RM15 5NG",
    "wof:placetype": "postalcode"
  },
  "geometry": {"coordinates":[0.279807,51.503619],"type":"Point"}
}
