{
  "type": "Feature",
  "properties": {
    "date:inception_lower": "2016-05-01",
    "date:inception_upper": "2016-05-01",
    "iso:country": "GB",
    "wof:name": "CM20 2GJ",
    "wof:placetype": "postalcode"
  },
  "geometry": {"coordinates":[0.123992,51.789606],"type":"Point"}
}
