{
  "type": "Feature",
  "properties": {
    "date:inception_lower": "1985-04-01",
    "date:inception_upper": "1985-04-01",
    "iso:country": "GB",
    "wof:name": "ME19 5QT",
    "wof:placetype": "postalcode"
  },
  "geometry": {"coordinates":[0.427219,51.301312],"type":"Point"}
}
