{
  "type": "Feature",
  "properties": {
    "date:inception_lower": "1995-12-01",
    "date:inception_upper": "1995-12-01",
    "iso:country": "GB",
    "wof:name": "DE14 2HQ",
    "wof:placetype": "postalcode"
  },
  "geometry": {"coordinates":[-1.65079,52.810288],"type":"Point"}
}
