{
  "type": "Feature",
  "properties": {
    "iso:country":"GB",
    "wof:name":"SA4 6UG",
    "wof:placetype":"postalcode"
},
  "geometry": {"coordinates":[-4.0650583156868,51.66072367659426],"type":"Point"}
}