{
  "type": "Feature",
  "properties": {
    "iso:country":"GB",
    "wof:name":"PH2 7SU",
    "wof:placetype":"postalcode"
},
  "geometry": {"coordinates":[-3.21743772573537,56.43005428040025],"type":"Point"}
}