{
  "type": "Feature",
  "properties": {
    "date:inception_lower": "2019-01-01",
    "date:inception_upper": "2019-01-01",
    "iso:country": "GB",
    "wof:name": "YO10 5GR",
    "wof:placetype": "postalcode"
  },
  "geometry": {"coordinates":[-1.028278,53.947633],"type":"Point"}
}
