{
  "type": "Feature",
  "properties": {
    "iso:country": "GB",
    "wof:name": "M33 7UF",
    "wof:placetype": "postalcode"
  },
  "geometry": {"coordinates":[-2.329922,53.41987],"type":"Point"}
}
