{
  "type": "Feature",
  "properties": {
    "date:inception_lower":"1980-01-01",
    "date:inception_upper":"1980-01-31",
    "iso:country":"GB",
    "wof:name":"SA19 7UG",
    "wof:placetype":"postalcode"
},
  "geometry": {"coordinates":[-4.072662,51.919562],"type":"Point"}
}