{
  "type": "Feature",
  "properties": {
    "iso:country":"GB",
    "wof:name":"SA19 7UG",
    "wof:placetype":"postalcode"
},
  "geometry": {"coordinates":[-4.0724820016651,51.91951985403495],"type":"Point"}
}