{
  "type": "Feature",
  "properties": {
    "iso:country":"GB",
    "wof:name":"AB34 4YE",
    "wof:placetype":"postalcode"
},
  "geometry": {"coordinates":[-2.86262893299674,57.1291497250265],"type":"Point"}
}