{
  "type": "Feature",
  "properties": {
    "date:inception_lower":"1980-01-01",
    "date:inception_upper":"1980-01-31",
    "iso:country":"GB",
    "wof:name":"NE34 8HW",
    "wof:placetype":"postalcode"
},
  "geometry": {"coordinates":[-1.430629,54.956644],"type":"Point"}
}