{
  "type": "Feature",
  "properties": {
    "date:inception_lower": "1980-01-01",
    "date:inception_upper": "1980-01-01",
    "iso:country": "GB",
    "wof:name": "TD9 9SY",
    "wof:placetype": "postalcode"
  },
  "geometry": {"coordinates":[-2.638402,55.379481],"type":"Point"}
}
