{
  "type": "Feature",
  "properties": {
    "date:inception_lower": "1980-01-01",
    "date:inception_upper": "1980-01-01",
    "iso:country": "GB",
    "wof:name": "G63 9HX",
    "wof:placetype": "postalcode"
  },
  "geometry": {"coordinates":[-4.318946,55.988664],"type":"Point"}
}
