{
  "type": "Feature",
  "properties": {
    "iso:country":"GB",
    "wof:name":"G63 9HX",
    "wof:placetype":"postalcode"
},
  "geometry": {"coordinates":[-4.31894627117752,55.98866360613031],"type":"Point"}
}