{
  "type": "Feature",
  "properties": {
    "iso:country": "GB",
    "wof:name": "SS4 1FA",
    "wof:placetype": "postalcode"
  },
  "geometry": {"coordinates":[0.697039,51.595228],"type":"Point"}
}
