{
  "type": "Feature",
  "properties": {
    "date:inception_lower": "2014-12-01",
    "date:inception_upper": "2014-12-01",
    "iso:country": "GB",
    "wof:name": "SS4 1FA",
    "wof:placetype": "postalcode"
  },
  "geometry": {"coordinates":[0.697039,51.595228],"type":"Point"}
}
