{
  "type": "Feature",
  "properties": {
    "iso:country":"GB",
    "wof:name":"ML5 2ND",
    "wof:placetype":"postalcode"
},
  "geometry": {"coordinates":[-4.05694651063736,55.87324063686337],"type":"Point"}
}