{
  "type": "Feature",
  "properties": {
    "date:inception_lower":"2009-06-01",
    "date:inception_upper":"2009-06-30",
    "iso:country":"GB",
    "wof:name":"ML5 2ND",
    "wof:placetype":"postalcode"
},
  "geometry": {"coordinates":[-4.056946,55.873241],"type":"Point"}
}