{
  "type": "Feature",
  "properties": {
    "iso:country": "GB",
    "wof:name": "ML5 2ND",
    "wof:placetype": "postalcode"
  },
  "geometry": {"coordinates":[-4.056946,55.873241],"type":"Point"}
}
