{
  "type": "Feature",
  "properties": {
    "iso:country": "GB",
    "wof:name": "CF5 6AD",
    "wof:placetype": "postalcode"
  },
  "geometry": {"coordinates":[-3.265303,51.439905],"type":"Point"}
}
