{
  "type": "Feature",
  "properties": {
    "iso:country":"GB",
    "wof:name":"CF5 6AD",
    "wof:placetype":"postalcode"
},
  "geometry": {"coordinates":[-3.26530308396865,51.43990529517732],"type":"Point"}
}