{
  "type": "Feature",
  "properties": {
    "date:inception_lower":"2016-09-01",
    "date:inception_upper":"2016-09-30",
    "iso:country":"GB",
    "wof:name":"RG5 4AX",
    "wof:placetype":"postalcode"
},
  "geometry": {"coordinates":[-0.895991,51.450957],"type":"Point"}
}