{
  "type": "Feature",
  "properties": {
    "iso:country": "GB",
    "wof:name": "NR9 3DF",
    "wof:placetype": "postalcode"
  },
  "geometry": {"coordinates":[1.178919,52.591838],"type":"Point"}
}
