{
  "type": "Feature",
  "properties": {
    "iso:country":"GB",
    "wof:name":"NR9 3DF",
    "wof:placetype":"postalcode"
},
  "geometry": {"coordinates":[1.17783428807214,52.5926430087014],"type":"Point"}
}