{
  "type": "Feature",
  "properties": {
    "iso:country":"GB",
    "wof:name":"BN27 2LQ",
    "wof:placetype":"postalcode"
},
  "geometry": {"coordinates":[0.26591169631523,50.86051405974656],"type":"Point"}
}