{
  "type": "Feature",
  "properties": {
    "iso:country": "GB",
    "wof:name": "LU2 7QS",
    "wof:placetype": "postalcode"
  },
  "geometry": {"coordinates":[-0.416194,51.885911],"type":"Point"}
}
