{
  "type": "Feature",
  "properties": {
    "date:inception_lower": "1981-06-01",
    "date:inception_upper": "1981-06-01",
    "iso:country": "GB",
    "wof:name": "NE3 1PG",
    "wof:placetype": "postalcode"
  },
  "geometry": {"coordinates":[-1.611705,55.003923],"type":"Point"}
}
