{
  "type": "Feature",
  "properties": {
    "iso:country":"GB",
    "wof:name":"NE3 1PG",
    "wof:placetype":"postalcode"
},
  "geometry": {"coordinates":[-1.61170461271963,55.00392318708858],"type":"Point"}
}