{
  "type": "Feature",
  "properties": {
    "iso:country":"GB",
    "wof:name":"LA14 3PJ",
    "wof:placetype":"postalcode"
},
  "geometry": {"coordinates":[-3.24909188042635,54.11005279360118],"type":"Point"}
}