{
  "type": "Feature",
  "properties": {
    "iso:country":"GB",
    "wof:name":"E12 5JR",
    "wof:placetype":"postalcode"
},
  "geometry": {"coordinates":[0.05930159138374,51.55485606606342],"type":"Point"}
}