{
  "type": "Feature",
  "properties": {
    "date:inception_lower": "2021-12-01",
    "date:inception_upper": "2021-12-01",
    "iso:country": "GB",
    "wof:name": "KY16 0FJ",
    "wof:placetype": "postalcode"
  },
  "geometry": {"coordinates":[-2.897112,56.361834],"type":"Point"}
}
