{
  "type": "Feature",
  "properties": {
    "date:inception_lower": "2004-02-01",
    "date:inception_upper": "2004-02-01",
    "iso:country": "GB",
    "wof:name": "HR4 7QT",
    "wof:placetype": "postalcode"
  },
  "geometry": {"coordinates":[-2.750845,52.08456],"type":"Point"}
}
