{
  "type": "Feature",
  "properties": {
    "iso:country":"GB",
    "wof:name":"HR4 7QT",
    "wof:placetype":"postalcode"
},
  "geometry": {"coordinates":[-2.75084458292866,52.08456023850115],"type":"Point"}
}