{
  "type": "Feature",
  "properties": {
    "iso:country": "GB",
    "wof:name": "CH3 7RG",
    "wof:placetype": "postalcode"
  },
  "geometry": {"coordinates":[-2.760584,53.148118],"type":"Point"}
}
