{
  "type": "Feature",
  "properties": {
    "iso:country":"GB",
    "wof:name":"CH3 5SA",
    "wof:placetype":"postalcode"
},
  "geometry": {"coordinates":[-2.85686015069832,53.18641382441019],"type":"Point"}
}