{
  "type": "Feature",
  "properties": {
    "date:inception_lower": "1980-01-01",
    "date:inception_upper": "1980-01-01",
    "iso:country": "GB",
    "wof:name": "CH3 5SA",
    "wof:placetype": "postalcode"
  },
  "geometry": {"coordinates":[-2.85686,53.186414],"type":"Point"}
}
