{
  "type": "Feature",
  "properties": {
    "iso:country":"GB",
    "wof:name":"CT3 1JZ",
    "wof:placetype":"postalcode"
},
  "geometry": {"coordinates":[1.25637234074709,51.26236703071712],"type":"Point"}
}