{
  "type": "Feature",
  "properties": {
    "date:inception_lower": "1983-01-01",
    "date:inception_upper": "1983-01-01",
    "iso:country": "GB",
    "wof:name": "CF5 2QJ",
    "wof:placetype": "postalcode"
  },
  "geometry": {"coordinates":[-3.229909,51.50042],"type":"Point"}
}
