{
  "type": "Feature",
  "properties": {
    "iso:country":"GB",
    "wof:name":"SL3 6PG",
    "wof:placetype":"postalcode"
},
  "geometry": {"coordinates":[-0.57022489136086,51.54733763545836],"type":"Point"}
}