{
  "type": "Feature",
  "properties": {
    "date:inception_lower": "1980-01-01",
    "date:inception_upper": "1980-01-01",
    "iso:country": "GB",
    "wof:name": "SL3 6PG",
    "wof:placetype": "postalcode"
  },
  "geometry": {"coordinates":[-0.570225,51.547338],"type":"Point"}
}
