{
  "type": "Feature",
  "properties": {
    "iso:country":"GB",
    "wof:name":"SP5 2DD",
    "wof:placetype":"postalcode"
},
  "geometry": {"coordinates":[-1.64877750072155,50.957030274836],"type":"Point"}
}