{
  "type": "Feature",
  "properties": {
    "iso:country": "GB",
    "wof:name": "SP5 2DD",
    "wof:placetype": "postalcode"
  },
  "geometry": {"coordinates":[-1.648777,50.95703],"type":"Point"}
}
