{
  "type": "Feature",
  "properties": {
    "date:inception_lower":"1980-01-01",
    "date:inception_upper":"1980-01-31",
    "iso:country":"GB",
    "wof:name":"SP5 2DD",
    "wof:placetype":"postalcode"
},
  "geometry": {"coordinates":[-1.648777,50.95703],"type":"Point"}
}