{
  "type": "Feature",
  "properties": {
    "date:inception_lower": "1984-10-01",
    "date:inception_upper": "1984-10-01",
    "iso:country": "GB",
    "wof:name": "SP10 1LG",
    "wof:placetype": "postalcode"
  },
  "geometry": {"coordinates":[-1.4744,51.208625],"type":"Point"}
}
