{
  "type": "Feature",
  "properties": {
    "date:inception_lower":"1980-01-01",
    "date:inception_upper":"1980-01-31",
    "iso:country":"GB",
    "wof:name":"CV10 0UE",
    "wof:placetype":"postalcode"
},
  "geometry": {"coordinates":[-1.522498,52.551081],"type":"Point"}
}