{
  "type": "Feature",
  "properties": {
    "iso:country":"GB",
    "wof:name":"CV3 1DB",
    "wof:placetype":"postalcode"
},
  "geometry": {"coordinates":[-1.47907260750132,52.3978066751913],"type":"Point"}
}