{
  "type": "Feature",
  "properties": {
    "iso:country": "GB",
    "wof:name": "ST2 0BG",
    "wof:placetype": "postalcode"
  },
  "geometry": {"coordinates":[-2.136116,53.013234],"type":"Point"}
}
