{
  "type": "Feature",
  "properties": {
    "iso:country":"GB",
    "wof:name":"G22 5DU",
    "wof:placetype":"postalcode"
},
  "geometry": {"coordinates":[-4.24196825799265,55.88473860689051],"type":"Point"}
}