{
  "type": "Feature",
  "properties": {
    "date:inception_lower":"2004-09-01",
    "date:inception_upper":"2004-09-30",
    "iso:country":"GB",
    "wof:name":"WS15 2TD",
    "wof:placetype":"postalcode"
},
  "geometry": {"coordinates":[-1.945013,52.770516],"type":"Point"}
}