{
  "type": "Feature",
  "properties": {
    "date:inception_lower": "1980-01-01",
    "date:inception_upper": "1980-01-01",
    "iso:country": "GB",
    "wof:name": "TA7 0JR",
    "wof:placetype": "postalcode"
  },
  "geometry": {"coordinates":[-2.869542,51.044414],"type":"Point"}
}
