{
  "type": "Feature",
  "properties": {
    "date:inception_lower": "2002-06-01",
    "date:inception_upper": "2002-06-01",
    "iso:country": "GB",
    "wof:name": "PE8 6QZ",
    "wof:placetype": "postalcode"
  },
  "geometry": {"coordinates":[-0.444784,52.556602],"type":"Point"}
}
