{
  "type": "Feature",
  "properties": {
    "iso:country":"GB",
    "wof:name":"PE8 6QZ",
    "wof:placetype":"postalcode"
},
  "geometry": {"coordinates":[-0.44478412069794,52.55660244374236],"type":"Point"}
}