{
  "type": "Feature",
  "properties": {
    "iso:country": "GB",
    "wof:name": "PE8 6QZ",
    "wof:placetype": "postalcode"
  },
  "geometry": {"coordinates":[-0.444784,52.556602],"type":"Point"}
}
