{
  "type": "Feature",
  "properties": {
    "iso:country": "GB",
    "wof:name": "DY3 1RL",
    "wof:placetype": "postalcode"
  },
  "geometry": {"coordinates":[-2.12223,52.542394],"type":"Point"}
}
