{
  "type": "Feature",
  "properties": {
    "iso:country":"GB",
    "wof:name":"W1D 6BH",
    "wof:placetype":"postalcode"
},
  "geometry": {"coordinates":[-0.1318731705457,51.51060249428841],"type":"Point"}
}