{
  "type": "Feature",
  "properties": {
    "date:inception_lower":"2000-12-01",
    "date:inception_upper":"2000-12-31",
    "iso:country":"GB",
    "wof:name":"W1D 6BH",
    "wof:placetype":"postalcode"
},
  "geometry": {"coordinates":[-0.131873,51.510602],"type":"Point"}
}