{
  "type": "Feature",
  "properties": {
    "iso:country": "GB",
    "wof:name": "NE99 4DA",
    "wof:placetype": "postalcode"
  },
  "geometry": {"coordinates":[-1.615396,54.967467],"type":"Point"}
}
