{
  "type": "Feature",
  "properties": {
    "iso:country":"GB",
    "wof:name":"S18 8QG",
    "wof:placetype":"postalcode"
},
  "geometry": {"coordinates":[-1.49728064540389,53.30203903118063],"type":"Point"}
}