{
  "type": "Feature",
  "properties": {
    "iso:country":"GB",
    "wof:name":"SE18 1EN",
    "wof:placetype":"postalcode"
},
  "geometry": {"coordinates":[0.09554977774784,51.48884564567265],"type":"Point"}
}