{
  "type": "Feature",
  "properties": {
    "iso:country": "GB",
    "wof:name": "DL13 3EP",
    "wof:placetype": "postalcode"
  },
  "geometry": {"coordinates":[-1.882058,54.731875],"type":"Point"}
}
