{
  "type": "Feature",
  "properties": {
    "iso:country":"GB",
    "wof:name":"ME16 8QP",
    "wof:placetype":"postalcode"
},
  "geometry": {"coordinates":[0.51156998817749,51.27435910251964],"type":"Point"}
}