{
  "type": "Feature",
  "properties": {
    "date:inception_lower": "1980-01-01",
    "date:inception_upper": "1980-01-01",
    "iso:country": "GB",
    "wof:name": "GL7 3ER",
    "wof:placetype": "postalcode"
  },
  "geometry": {"coordinates":[-1.689272,51.700529],"type":"Point"}
}
