{
  "type": "Feature",
  "properties": {
    "iso:country": "GB",
    "wof:name": "G46 7UD",
    "wof:placetype": "postalcode"
  },
  "geometry": {"coordinates":[-4.306141,55.809549],"type":"Point"}
}
