{
  "type": "Feature",
  "properties": {
    "iso:country":"GB",
    "wof:name":"SA12 6DN",
    "wof:placetype":"postalcode"
},
  "geometry": {"coordinates":[-3.80455971108904,51.58594771163308],"type":"Point"}
}