{
  "type": "Feature",
  "properties": {
    "iso:country":"GB",
    "wof:name":"MK41 0RX",
    "wof:placetype":"postalcode"
},
  "geometry": {"coordinates":[-0.41991016252674,52.14661527137102],"type":"Point"}
}