{
  "type": "Feature",
  "properties": {
    "date:inception_lower": "1993-01-01",
    "date:inception_upper": "1993-01-01",
    "iso:country": "GB",
    "wof:name": "MK41 0RX",
    "wof:placetype": "postalcode"
  },
  "geometry": {"coordinates":[-0.41991,52.146615],"type":"Point"}
}
