{
  "type": "Feature",
  "properties": {
    "iso:country":"GB",
    "wof:name":"OX16 1FB",
    "wof:placetype":"postalcode"
},
  "geometry": {"coordinates":[-1.35022133412205,52.07602023827824],"type":"Point"}
}