{
  "type": "Feature",
  "properties": {
    "iso:country":"GB",
    "wof:name":"DL16 7TP",
    "wof:placetype":"postalcode"
},
  "geometry": {"coordinates":[-1.60541707648579,54.69599127836327],"type":"Point"}
}