{
  "type": "Feature",
  "properties": {
    "iso:country": "GB",
    "wof:name": "DT5 1PA",
    "wof:placetype": "postalcode"
  },
  "geometry": {"coordinates":[-2.429054,50.56662],"type":"Point"}
}
