{
  "type": "Feature",
  "properties": {
    "date:inception_lower":"1996-06-01",
    "date:inception_upper":"1996-06-30",
    "iso:country":"GB",
    "wof:name":"DT5 1PA",
    "wof:placetype":"postalcode"
},
  "geometry": {"coordinates":[-2.429054,50.56662],"type":"Point"}
}