{
  "type": "Feature",
  "properties": {
    "iso:country":"GB",
    "wof:name":"DT5 1PA",
    "wof:placetype":"postalcode"
},
  "geometry": {"coordinates":[-2.42891249745126,50.56770178831525],"type":"Point"}
}