{
  "type": "Feature",
  "properties": {
    "iso:country": "GB",
    "wof:name": "TA19 9FW",
    "wof:placetype": "postalcode"
  },
  "geometry": {"coordinates":[-2.928043,50.952],"type":"Point"}
}
