{
  "type": "Feature",
  "properties": {
    "iso:country": "GB",
    "wof:name": "TA19 9FW",
    "wof:placetype": "postalcode"
  },
  "geometry": {"coordinates":[-2.927957,50.951982],"type":"Point"}
}
