{
  "type": "Feature",
  "properties": {
    "date:inception_lower": "2019-07-01",
    "date:inception_upper": "2019-07-01",
    "iso:country": "GB",
    "wof:name": "TA19 9FW",
    "wof:placetype": "postalcode"
  },
  "geometry": {"coordinates":[-2.927929,50.952027],"type":"Point"}
}
