{
  "type": "Feature",
  "properties": {
    "iso:country": "GB",
    "wof:name": "G3 8TY",
    "wof:placetype": "postalcode"
  },
  "geometry": {"coordinates":[-4.28537,55.864908],"type":"Point"}
}
