{
  "type": "Feature",
  "properties": {
    "date:inception_lower":"2016-12-01",
    "date:inception_upper":"2016-12-31",
    "iso:country":"GB",
    "wof:name":"G3 8TY",
    "wof:placetype":"postalcode"
},
  "geometry": {"coordinates":[-4.28537,55.864908],"type":"Point"}
}