{
  "type": "Feature",
  "properties": {
    "date:inception_lower": "1980-01-01",
    "date:inception_upper": "1980-01-01",
    "iso:country": "GB",
    "wof:name": "DN7 6JE",
    "wof:placetype": "postalcode"
  },
  "geometry": {"coordinates":[-1.006703,53.575624],"type":"Point"}
}
