{
  "type": "Feature",
  "properties": {
    "iso:country":"GB",
    "wof:name":"PL27 6EX",
    "wof:placetype":"postalcode"
},
  "geometry": {"coordinates":[-4.84432703852434,50.53485363708197],"type":"Point"}
}