{
  "type": "Feature",
  "properties": {
    "iso:country": "GB",
    "wof:name": "PL27 6EX",
    "wof:placetype": "postalcode"
  },
  "geometry": {"coordinates":[-4.8457,50.53519],"type":"Point"}
}
