{
  "type": "Feature",
  "properties": {
    "iso:country":"GB",
    "wof:name":"SY5 8JN",
    "wof:placetype":"postalcode"
},
  "geometry": {"coordinates":[-2.84224909440333,52.6797691813742],"type":"Point"}
}