{
  "type": "Feature",
  "properties": {
    "iso:country": "GB",
    "wof:name": "SY5 8JN",
    "wof:placetype": "postalcode"
  },
  "geometry": {"coordinates":[-2.842249,52.679769],"type":"Point"}
}
