{
  "type": "Feature",
  "properties": {
    "date:inception_lower":"1980-01-01",
    "date:inception_upper":"1980-01-31",
    "iso:country":"GB",
    "wof:name":"G5 9JF",
    "wof:placetype":"postalcode"
},
  "geometry": {"coordinates":[-4.257973,55.852765],"type":"Point"}
}