{
  "type": "Feature",
  "properties": {
    "iso:country":"GB",
    "wof:name":"BD20 6RQ",
    "wof:placetype":"postalcode"
},
  "geometry": {"coordinates":[-1.95890263891008,53.90082696404129],"type":"Point"}
}