{
  "type": "Feature",
  "properties": {
    "iso:country":"GB",
    "wof:name":"WD3 3LZ",
    "wof:placetype":"postalcode"
},
  "geometry": {"coordinates":[-0.44639828053229,51.65431563818043],"type":"Point"}
}