{
  "type": "Feature",
  "properties": {
    "iso:country":"GB",
    "wof:name":"BS8 2RR",
    "wof:placetype":"postalcode"
},
  "geometry": {"coordinates":[-2.61193597714334,51.46729330430601],"type":"Point"}
}