{
  "type": "Feature",
  "properties": {
    "iso:country":"GB",
    "wof:name":"GU25 4HR",
    "wof:placetype":"postalcode"
},
  "geometry": {"coordinates":[-0.56731671984823,51.39502035837269],"type":"Point"}
}