{
  "type": "Feature",
  "properties": {
    "iso:country":"GB",
    "wof:name":"CA22 2JU",
    "wof:placetype":"postalcode"
},
  "geometry": {"coordinates":[-3.53886997133458,54.47607621999652],"type":"Point"}
}