{
  "type": "Feature",
  "properties": {
    "date:inception_lower": "1993-08-01",
    "date:inception_upper": "1993-08-01",
    "iso:country": "GB",
    "wof:name": "CA22 2JU",
    "wof:placetype": "postalcode"
  },
  "geometry": {"coordinates":[-3.53887,54.476076],"type":"Point"}
}
