{
  "type": "Feature",
  "properties": {
    "iso:country": "GB",
    "wof:name": "LL30 2BZ",
    "wof:placetype": "postalcode"
  },
  "geometry": {"coordinates":[-3.833487,53.316698],"type":"Point"}
}
