{
  "type": "Feature",
  "properties": {
    "iso:country":"GB",
    "wof:name":"ME7 3QZ",
    "wof:placetype":"postalcode"
},
  "geometry": {"coordinates":[0.57309267385504,51.35018872666267],"type":"Point"}
}