{
  "type": "Feature",
  "properties": {
    "iso:country": "GB",
    "wof:name": "SY8 1AW",
    "wof:placetype": "postalcode"
  },
  "geometry": {"coordinates":[-2.719169,52.367775],"type":"Point"}
}
