{
  "type": "Feature",
  "properties": {
    "iso:country":"GB",
    "wof:name":"SY8 1AW",
    "wof:placetype":"postalcode"
},
  "geometry": {"coordinates":[-2.71914315246911,52.36786952787522],"type":"Point"}
}