{
  "type": "Feature",
  "properties": {
    "iso:country":"GB",
    "wof:name":"NG16 3PT",
    "wof:placetype":"postalcode"
},
  "geometry": {"coordinates":[-1.29340348682817,53.02123793911031],"type":"Point"}
}