{
  "type": "Feature",
  "properties": {
    "date:inception_lower": "2007-02-01",
    "date:inception_upper": "2007-02-01",
    "iso:country": "GB",
    "wof:name": "M46 0FT",
    "wof:placetype": "postalcode"
  },
  "geometry": {"coordinates":[-2.505557,53.520656],"type":"Point"}
}
