{
  "type": "Feature",
  "properties": {
    "iso:country":"GB",
    "wof:name":"M46 0FT",
    "wof:placetype":"postalcode"
},
  "geometry": {"coordinates":[-2.50555734340409,53.52065552291094],"type":"Point"}
}