{
  "type": "Feature",
  "properties": {
    "date:inception_lower":"1990-07-01",
    "date:inception_upper":"1990-07-31",
    "iso:country":"GB",
    "wof:name":"IP13 7LP",
    "wof:placetype":"postalcode"
},
  "geometry": {"coordinates":[1.257116,52.268313],"type":"Point"}
}