{
  "type": "Feature",
  "properties": {
    "iso:country":"GB",
    "wof:name":"IP13 7LP",
    "wof:placetype":"postalcode"
},
  "geometry": {"coordinates":[1.25711612068583,52.26831279236988],"type":"Point"}
}