{
  "type": "Feature",
  "properties": {
    "iso:country":"GB",
    "wof:name":"HA8 9NS",
    "wof:placetype":"postalcode"
},
  "geometry": {"coordinates":[-0.26173656046028,51.61414006775506],"type":"Point"}
}