{
  "type": "Feature",
  "properties": {
    "date:inception_lower":"1980-01-01",
    "date:inception_upper":"1980-01-31",
    "iso:country":"GB",
    "wof:name":"HG1 2RZ",
    "wof:placetype":"postalcode"
},
  "geometry": {"coordinates":[-1.545855,53.993593],"type":"Point"}
}