{
  "type": "Feature",
  "properties": {
    "iso:country": "GB",
    "wof:name": "HG1 2RZ",
    "wof:placetype": "postalcode"
  },
  "geometry": {"coordinates":[-1.545855,53.993593],"type":"Point"}
}
