{
  "type": "Feature",
  "properties": {
    "iso:country":"GB",
    "wof:name":"LL59 5AT",
    "wof:placetype":"postalcode"
},
  "geometry": {"coordinates":[-4.16332139995588,53.22579557796283],"type":"Point"}
}