{
  "type": "Feature",
  "properties": {
    "iso:country": "GB",
    "wof:name": "KT13 9XE",
    "wof:placetype": "postalcode"
  },
  "geometry": {"coordinates":[-0.447588,51.368667],"type":"Point"}
}
