{
  "type": "Feature",
  "properties": {
    "iso:country":"GB",
    "wof:name":"CV34 6AR",
    "wof:placetype":"postalcode"
},
  "geometry": {"coordinates":[-1.5962509556502,52.27681561994811],"type":"Point"}
}