{
  "type": "Feature",
  "properties": {
    "iso:country": "GB",
    "wof:name": "CV34 6AR",
    "wof:placetype": "postalcode"
  },
  "geometry": {"coordinates":[-1.596251,52.276816],"type":"Point"}
}
