{
  "type": "Feature",
  "properties": {
    "iso:country":"GB",
    "wof:name":"BB3 1JN",
    "wof:placetype":"postalcode"
},
  "geometry": {"coordinates":[-2.48686107297793,53.7011110321103],"type":"Point"}
}