{
  "type": "Feature",
  "properties": {
    "iso:country": "GB",
    "wof:name": "ST3 4NU",
    "wof:placetype": "postalcode"
  },
  "geometry": {"coordinates":[-2.131274,52.974928],"type":"Point"}
}
