{
  "type": "Feature",
  "properties": {
    "iso:country":"GB",
    "wof:name":"ST3 4NU",
    "wof:placetype":"postalcode"
},
  "geometry": {"coordinates":[-2.1312742973865,52.97492766692701],"type":"Point"}
}