{
  "type": "Feature",
  "properties": {
    "iso:country":"GB",
    "wof:name":"N3 2JT",
    "wof:placetype":"postalcode"
},
  "geometry": {"coordinates":[-0.19307749447507,51.59868862923663],"type":"Point"}
}