{
  "type": "Feature",
  "properties": {
    "date:inception_lower": "2000-12-01",
    "date:inception_upper": "2000-12-01",
    "iso:country": "GB",
    "wof:name": "RG1 7RY",
    "wof:placetype": "postalcode"
  },
  "geometry": {"coordinates":[-0.975068,51.453238],"type":"Point"}
}
