{
  "type": "Feature",
  "properties": {
    "iso:country": "GB",
    "wof:name": "RG1 7RY",
    "wof:placetype": "postalcode"
  },
  "geometry": {"coordinates":[-0.975068,51.453238],"type":"Point"}
}
