{
  "type": "Feature",
  "properties": {
    "iso:country":"GB",
    "wof:name":"GL6 9HL",
    "wof:placetype":"postalcode"
},
  "geometry": {"coordinates":[-2.2077526691469,51.70056667974769],"type":"Point"}
}