{
  "type": "Feature",
  "properties": {
    "date:inception_lower": "1998-06-01",
    "date:inception_upper": "1998-06-01",
    "iso:country": "GB",
    "wof:name": "YO24 2RQ",
    "wof:placetype": "postalcode"
  },
  "geometry": {"coordinates":[-1.122832,53.93584],"type":"Point"}
}
