{
  "type": "Feature",
  "properties": {
    "iso:country": "GB",
    "wof:name": "KA28 0AX",
    "wof:placetype": "postalcode"
  },
  "geometry": {"coordinates":[-4.934272,55.75156],"type":"Point"}
}
