{
  "type": "Feature",
  "properties": {
    "date:inception_lower": "1980-01-01",
    "date:inception_upper": "1980-01-01",
    "iso:country": "GB",
    "wof:name": "KA28 0AX",
    "wof:placetype": "postalcode"
  },
  "geometry": {"coordinates":[-4.934272,55.75156],"type":"Point"}
}
