{
  "type": "Feature",
  "properties": {
    "date:inception_lower": "2016-05-01",
    "date:inception_upper": "2016-05-01",
    "iso:country": "GB",
    "wof:name": "HA8 8GA",
    "wof:placetype": "postalcode"
  },
  "geometry": {"coordinates":[-0.290349,51.620315],"type":"Point"}
}
