{
  "type": "Feature",
  "properties": {
    "iso:country": "GB",
    "wof:name": "CF14 4BH",
    "wof:placetype": "postalcode"
  },
  "geometry": {"coordinates":[-3.19538,51.512143],"type":"Point"}
}
