{
  "type": "Feature",
  "properties": {
    "iso:country":"GB",
    "wof:name":"CF14 4BH",
    "wof:placetype":"postalcode"
},
  "geometry": {"coordinates":[-3.19538002942661,51.5121432183462],"type":"Point"}
}