{
  "type": "Feature",
  "properties": {
    "date:inception_lower":"1999-12-01",
    "date:inception_upper":"1999-12-31",
    "iso:country":"GB",
    "wof:name":"BN23 5BB",
    "wof:placetype":"postalcode"
},
  "geometry": {"coordinates":[0.334712,50.800328],"type":"Point"}
}