{
  "type": "Feature",
  "properties": {
    "iso:country": "GB",
    "wof:name": "BN23 5BB",
    "wof:placetype": "postalcode"
  },
  "geometry": {"coordinates":[0.334712,50.800328],"type":"Point"}
}
