{
  "type": "Feature",
  "properties": {
    "iso:country": "GB",
    "wof:name": "L31 5LN",
    "wof:placetype": "postalcode"
  },
  "geometry": {"coordinates":[-2.940922,53.498147],"type":"Point"}
}
