{
  "type": "Feature",
  "properties": {
    "iso:country":"GB",
    "wof:name":"L31 5LN",
    "wof:placetype":"postalcode"
},
  "geometry": {"coordinates":[-2.94092159160056,53.49814687034683],"type":"Point"}
}