{
  "type": "Feature",
  "properties": {
    "iso:country":"GB",
    "wof:name":"WR12 7RD",
    "wof:placetype":"postalcode"
},
  "geometry": {"coordinates":[-1.85884666715092,52.03881411987938],"type":"Point"}
}