{
  "type": "Feature",
  "properties": {
    "date:inception_lower": "1983-07-01",
    "date:inception_upper": "1983-07-01",
    "iso:country": "GB",
    "wof:name": "WR12 7RD",
    "wof:placetype": "postalcode"
  },
  "geometry": {"coordinates":[-1.858847,52.038814],"type":"Point"}
}
