{
  "type": "Feature",
  "properties": {
    "iso:country":"GB",
    "wof:name":"M25 3JF",
    "wof:placetype":"postalcode"
},
  "geometry": {"coordinates":[-2.2888127714085,53.53052618019039],"type":"Point"}
}