{
  "type": "Feature",
  "properties": {
    "date:inception_lower": "2021-06-01",
    "date:inception_upper": "2021-06-01",
    "iso:country": "GB",
    "wof:name": "G3 6BL",
    "wof:placetype": "postalcode"
  },
  "geometry": {"coordinates":[-4.277268,55.869849],"type":"Point"}
}
