{
  "type": "Feature",
  "properties": {
    "iso:country": "GB",
    "wof:name": "PO20 0BW",
    "wof:placetype": "postalcode"
  },
  "geometry": {"coordinates":[-0.786092,50.732428],"type":"Point"}
}
