{
  "type": "Feature",
  "properties": {
    "iso:country": "GB",
    "wof:name": "IG7 4GF",
    "wof:placetype": "postalcode"
  },
  "geometry": {"coordinates":[0.138732,51.607196],"type":"Point"}
}
