{
  "type": "Feature",
  "properties": {
    "iso:country":"GB",
    "wof:name":"OX4 7XZ",
    "wof:placetype":"postalcode"
},
  "geometry": {"coordinates":[-1.19367679542996,51.71604941523787],"type":"Point"}
}