{
  "type": "Feature",
  "properties": {
    "date:inception_lower": "2014-06-01",
    "date:inception_upper": "2014-06-01",
    "iso:country": "GB",
    "wof:name": "ML6 8XB",
    "wof:placetype": "postalcode"
  },
  "geometry": {"coordinates":[-3.94765,55.83572],"type":"Point"}
}
