{
  "type": "Feature",
  "properties": {
    "iso:country":"GB",
    "wof:name":"ML6 8XB",
    "wof:placetype":"postalcode"
},
  "geometry": {"coordinates":[-3.94765026635094,55.83571987710758],"type":"Point"}
}