{
  "type": "Feature",
  "properties": {
    "iso:country":"GB",
    "wof:name":"DD11 5HB",
    "wof:placetype":"postalcode"
},
  "geometry": {"coordinates":[-2.56454807249569,56.56863355230359],"type":"Point"}
}