{
  "type": "Feature",
  "properties": {
    "iso:country": "GB",
    "wof:name": "MK15 9AP",
    "wof:placetype": "postalcode"
  },
  "geometry": {"coordinates":[-0.734998,52.057223],"type":"Point"}
}
