{
  "type": "Feature",
  "properties": {
    "iso:country": "GB",
    "wof:name": "B24 9BL",
    "wof:placetype": "postalcode"
  },
  "geometry": {"coordinates":[-1.83512,52.519412],"type":"Point"}
}
