{
  "type": "Feature",
  "properties": {
    "iso:country":"GB",
    "wof:name":"B24 9BL",
    "wof:placetype":"postalcode"
},
  "geometry": {"coordinates":[-1.83511997691591,52.51941244818367],"type":"Point"}
}