{
  "type": "Feature",
  "properties": {
    "iso:country":"GB",
    "wof:name":"TQ1 2LW",
    "wof:placetype":"postalcode"
},
  "geometry": {"coordinates":[-3.51218208428169,50.4598587210555],"type":"Point"}
}