{
  "type": "Feature",
  "properties": {
    "iso:country": "GB",
    "wof:name": "HP3 0DW",
    "wof:placetype": "postalcode"
  },
  "geometry": {"coordinates":[-0.510968,51.732086],"type":"Point"}
}
