{
  "type": "Feature",
  "properties": {
    "iso:country":"GB",
    "wof:name":"HP3 0DW",
    "wof:placetype":"postalcode"
},
  "geometry": {"coordinates":[-0.51096846895037,51.73208645511567],"type":"Point"}
}