{
  "type": "Feature",
  "properties": {
    "date:inception_lower":"1980-01-01",
    "date:inception_upper":"1980-01-31",
    "iso:country":"GB",
    "wof:name":"OX16 0LG",
    "wof:placetype":"postalcode"
},
  "geometry": {"coordinates":[-1.354995,52.056626],"type":"Point"}
}