{
  "type": "Feature",
  "properties": {
    "iso:country":"GB",
    "wof:name":"OX16 0LG",
    "wof:placetype":"postalcode"
},
  "geometry": {"coordinates":[-1.35499473335466,52.05662646689179],"type":"Point"}
}