{
  "type": "Feature",
  "properties": {
    "iso:country":"GB",
    "wof:name":"SG8 6BT",
    "wof:placetype":"postalcode"
},
  "geometry": {"coordinates":[0.01729030769095,52.08195820098567],"type":"Point"}
}