{
  "type": "Feature",
  "properties": {
    "iso:country": "GB",
    "wof:name": "SG8 6BT",
    "wof:placetype": "postalcode"
  },
  "geometry": {"coordinates":[0.01729,52.081958],"type":"Point"}
}
