{
  "type": "Feature",
  "properties": {
    "iso:country": "GB",
    "wof:name": "N1 4NL",
    "wof:placetype": "postalcode"
  },
  "geometry": {"coordinates":[-0.079777,51.54896],"type":"Point"}
}
