{
  "type": "Feature",
  "properties": {
    "iso:country":"GB",
    "wof:name":"N1 4NL",
    "wof:placetype":"postalcode"
},
  "geometry": {"coordinates":[-0.07977719523769,51.54895967288989],"type":"Point"}
}