{
  "type": "Feature",
  "properties": {
    "iso:country":"GB",
    "wof:name":"BL6 5SU",
    "wof:placetype":"postalcode"
},
  "geometry": {"coordinates":[-2.5716467731432,53.58314204995127],"type":"Point"}
}