{
  "type": "Feature",
  "properties": {
    "iso:country":"GB",
    "wof:name":"SW6 1JS",
    "wof:placetype":"postalcode"
},
  "geometry": {"coordinates":[-0.19971230473132,51.48303139906994],"type":"Point"}
}