{
  "type": "Feature",
  "properties": {
    "iso:country": "GB",
    "wof:name": "BD20 8FD",
    "wof:placetype": "postalcode"
  },
  "geometry": {"coordinates":[-2.011751,53.918365],"type":"Point"}
}
