{
  "type": "Feature",
  "properties": {
    "iso:country": "GB",
    "wof:name": "GU10 5JD",
    "wof:placetype": "postalcode"
  },
  "geometry": {"coordinates":[-0.857697,51.190491],"type":"Point"}
}
