{
  "type": "Feature",
  "properties": {
    "iso:country":"GB",
    "wof:name":"GU10 5JD",
    "wof:placetype":"postalcode"
},
  "geometry": {"coordinates":[-0.85769700233933,51.19049104211427],"type":"Point"}
}