{
  "type": "Feature",
  "properties": {
    "iso:country":"GB",
    "wof:name":"B46 3FH",
    "wof:placetype":"postalcode"
},
  "geometry": {"coordinates":[-1.70343612717216,52.49402015245388],"type":"Point"}
}