{
  "type": "Feature",
  "properties": {
    "date:inception_lower": "2015-07-01",
    "date:inception_upper": "2015-07-01",
    "iso:country": "GB",
    "wof:name": "B46 3FH",
    "wof:placetype": "postalcode"
  },
  "geometry": {"coordinates":[-1.703436,52.49402],"type":"Point"}
}
