{
  "type": "Feature",
  "properties": {
    "iso:country":"GB",
    "wof:name":"TQ9 5BQ",
    "wof:placetype":"postalcode"
},
  "geometry": {"coordinates":[-3.67652879144496,50.43276547877918],"type":"Point"}
}