{
  "type": "Feature",
  "properties": {
    "iso:country":"GB",
    "wof:name":"KT8 2NQ",
    "wof:placetype":"postalcode"
},
  "geometry": {"coordinates":[-0.37544884464322,51.39501758013976],"type":"Point"}
}