{
  "type": "Feature",
  "properties": {
    "iso:country":"GB",
    "wof:name":"W2 6DT",
    "wof:placetype":"postalcode"
},
  "geometry": {"coordinates":[-0.18107463993967,51.51490089044838],"type":"Point"}
}