{
  "type": "Feature",
  "properties": {
    "iso:country":"GB",
    "wof:name":"LS27 0SW",
    "wof:placetype":"postalcode"
},
  "geometry": {"coordinates":[-1.60159807406633,53.73323085608104],"type":"Point"}
}