{
  "type": "Feature",
  "properties": {
    "iso:country": "GB",
    "wof:name": "LS27 0SW",
    "wof:placetype": "postalcode"
  },
  "geometry": {"coordinates":[-1.602871,53.733637],"type":"Point"}
}
