{
  "type": "Feature",
  "properties": {
    "date:inception_lower": "1980-01-01",
    "date:inception_upper": "1980-01-01",
    "iso:country": "GB",
    "wof:name": "SE22 8HH",
    "wof:placetype": "postalcode"
  },
  "geometry": {"coordinates":[-0.075457,51.458163],"type":"Point"}
}
