{
  "type": "Feature",
  "properties": {
    "iso:country": "GB",
    "wof:name": "SE22 8HH",
    "wof:placetype": "postalcode"
  },
  "geometry": {"coordinates":[-0.075457,51.458163],"type":"Point"}
}
