{
  "type": "Feature",
  "properties": {
    "iso:country":"GB",
    "wof:name":"EN2 0PZ",
    "wof:placetype":"postalcode"
},
  "geometry": {"coordinates":[-0.08266365938216,51.6603244017337],"type":"Point"}
}