{
  "type": "Feature",
  "properties": {
    "date:inception_lower": "2022-06-01",
    "date:inception_upper": "2022-06-01",
    "iso:country": "GB",
    "wof:name": "GL3 4XS",
    "wof:placetype": "postalcode"
  },
  "geometry": {"coordinates":[-2.163806,51.853194],"type":"Point"}
}
