{
  "type": "Feature",
  "properties": {
    "iso:country":"GB",
    "wof:name":"TN25 6SZ",
    "wof:placetype":"postalcode"
},
  "geometry": {"coordinates":[0.94845644377728,51.11465006845994],"type":"Point"}
}