{
  "type": "Feature",
  "properties": {
    "date:inception_lower":"1981-06-01",
    "date:inception_upper":"1981-06-30",
    "iso:country":"GB",
    "wof:name":"MK3 6DJ",
    "wof:placetype":"postalcode"
},
  "geometry": {"coordinates":[-0.745725,51.995514],"type":"Point"}
}