{
  "type": "Feature",
  "properties": {
    "iso:country": "GB",
    "wof:name": "MK3 6DJ",
    "wof:placetype": "postalcode"
  },
  "geometry": {"coordinates":[-0.745725,51.995514],"type":"Point"}
}
