{
  "type": "Feature",
  "properties": {
    "iso:country":"GB",
    "wof:name":"AB21 9QL",
    "wof:placetype":"postalcode"
},
  "geometry": {"coordinates":[-2.18744282246524,57.17697312556773],"type":"Point"}
}