{
  "type": "Feature",
  "properties": {
    "iso:country":"GB",
    "wof:name":"WA3 5NU",
    "wof:placetype":"postalcode"
},
  "geometry": {"coordinates":[-2.4943326752144,53.47245216942417],"type":"Point"}
}