{
  "type": "Feature",
  "properties": {
    "date:inception_lower":"1983-07-01",
    "date:inception_upper":"1983-07-31",
    "iso:country":"GB",
    "wof:name":"WA3 5NU",
    "wof:placetype":"postalcode"
},
  "geometry": {"coordinates":[-2.494347,53.472486],"type":"Point"}
}