{
  "type": "Feature",
  "properties": {
    "iso:country":"GB",
    "wof:name":"HP23 5JD",
    "wof:placetype":"postalcode"
},
  "geometry": {"coordinates":[-0.65450866832055,51.79817952477914],"type":"Point"}
}