{
  "type": "Feature",
  "properties": {
    "iso:country":"GB",
    "wof:name":"PH6 2DE",
    "wof:placetype":"postalcode"
},
  "geometry": {"coordinates":[-3.97828537709148,56.37081126798098],"type":"Point"}
}