{
  "type": "Feature",
  "properties": {
    "date:inception_lower": "2000-12-01",
    "date:inception_upper": "2000-12-01",
    "iso:country": "GB",
    "wof:name": "PH6 2DE",
    "wof:placetype": "postalcode"
  },
  "geometry": {"coordinates":[-3.978285,56.370811],"type":"Point"}
}
