{
  "type": "Feature",
  "properties": {
    "iso:country": "GB",
    "wof:name": "PH6 2DE",
    "wof:placetype": "postalcode"
  },
  "geometry": {"coordinates":[-3.978285,56.370811],"type":"Point"}
}
