{
  "type": "Feature",
  "properties": {
    "iso:country":"GB",
    "wof:name":"PE19 6GW",
    "wof:placetype":"postalcode"
},
  "geometry": {"coordinates":[-0.24574462385954,52.22970689414593],"type":"Point"}
}