{
  "type": "Feature",
  "properties": {
    "date:inception_lower": "2011-05-01",
    "date:inception_upper": "2011-05-01",
    "iso:country": "GB",
    "wof:name": "PE19 6GW",
    "wof:placetype": "postalcode"
  },
  "geometry": {"coordinates":[-0.245745,52.229707],"type":"Point"}
}
