{
  "type": "Feature",
  "properties": {
    "iso:country":"GB",
    "wof:name":"GL3 1DN",
    "wof:placetype":"postalcode"
},
  "geometry": {"coordinates":[-2.198642721931,51.88650784081963],"type":"Point"}
}