{
  "type": "Feature",
  "properties": {
    "iso:country": "GB",
    "wof:name": "BH10 5DL",
    "wof:placetype": "postalcode"
  },
  "geometry": {"coordinates":[-1.897215,50.753878],"type":"Point"}
}
