{
  "type": "Feature",
  "properties": {
    "date:inception_lower": "1980-01-01",
    "date:inception_upper": "1980-01-01",
    "iso:country": "GB",
    "wof:name": "CO8 5LB",
    "wof:placetype": "postalcode"
  },
  "geometry": {"coordinates":[0.784887,51.978445],"type":"Point"}
}
