{
  "type": "Feature",
  "properties": {
    "iso:country":"GB",
    "wof:name":"CV5 7DY",
    "wof:placetype":"postalcode"
},
  "geometry": {"coordinates":[-1.59449606661491,52.41445887382544],"type":"Point"}
}