{
  "type": "Feature",
  "properties": {
    "iso:country": "GB",
    "wof:name": "CV5 7DY",
    "wof:placetype": "postalcode"
  },
  "geometry": {"coordinates":[-1.594496,52.414459],"type":"Point"}
}
