{
  "type": "Feature",
  "properties": {
    "iso:country":"GB",
    "wof:name":"WA1 3TY",
    "wof:placetype":"postalcode"
},
  "geometry": {"coordinates":[-2.57234499841042,53.39876557539622],"type":"Point"}
}