{
  "type": "Feature",
  "properties": {
    "iso:country":"GB",
    "wof:name":"BD4 8HQ",
    "wof:placetype":"postalcode"
},
  "geometry": {"coordinates":[-1.70350639090755,53.7896114818527],"type":"Point"}
}