{
  "type": "Feature",
  "properties": {
    "iso:country": "GB",
    "wof:name": "CB7 4TG",
    "wof:placetype": "postalcode"
  },
  "geometry": {"coordinates":[0.381414,52.475595],"type":"Point"}
}
