{
  "type": "Feature",
  "properties": {
    "iso:country":"GB",
    "wof:name":"NP11 4HQ",
    "wof:placetype":"postalcode"
},
  "geometry": {"coordinates":[-3.16669759725475,51.658979704994],"type":"Point"}
}