{
  "type": "Feature",
  "properties": {
    "date:inception_lower": "2013-02-01",
    "date:inception_upper": "2013-02-01",
    "iso:country": "GB",
    "wof:name": "BS34 7PQ",
    "wof:placetype": "postalcode"
  },
  "geometry": {"coordinates":[-2.577847,51.506103],"type":"Point"}
}
