{
  "type": "Feature",
  "properties": {
    "iso:country":"GB",
    "wof:name":"BS34 7PQ",
    "wof:placetype":"postalcode"
},
  "geometry": {"coordinates":[-2.57784730753825,51.50610316233151],"type":"Point"}
}