{
  "type": "Feature",
  "properties": {
    "iso:country":"GB",
    "wof:name":"MK43 0DX",
    "wof:placetype":"postalcode"
},
  "geometry": {"coordinates":[-0.60544500205297,52.06716208497456],"type":"Point"}
}