{
  "type": "Feature",
  "properties": {
    "iso:country":"GB",
    "wof:name":"ME2 2XA",
    "wof:placetype":"postalcode"
},
  "geometry": {"coordinates":[0.46134463533213,51.3947254473716],"type":"Point"}
}