{
  "type": "Feature",
  "properties": {
    "iso:country":"GB",
    "wof:name":"GL17 0HQ",
    "wof:placetype":"postalcode"
},
  "geometry": {"coordinates":[-2.50415416843276,51.85151008557462],"type":"Point"}
}