{
  "type": "Feature",
  "properties": {
    "date:inception_lower": "1980-01-01",
    "date:inception_upper": "1980-01-01",
    "iso:country": "GB",
    "wof:name": "S71 5AY",
    "wof:placetype": "postalcode"
  },
  "geometry": {"coordinates":[-1.433671,53.546875],"type":"Point"}
}
