{
  "type": "Feature",
  "properties": {
    "iso:country": "GB",
    "wof:name": "S71 5AY",
    "wof:placetype": "postalcode"
  },
  "geometry": {"coordinates":[-1.433671,53.546875],"type":"Point"}
}
