{
  "type": "Feature",
  "properties": {
    "iso:country":"GB",
    "wof:name":"S71 5AY",
    "wof:placetype":"postalcode"
},
  "geometry": {"coordinates":[-1.43367056895016,53.54687453388467],"type":"Point"}
}