{
  "type": "Feature",
  "properties": {
    "date:inception_lower": "1980-01-01",
    "date:inception_upper": "1980-01-01",
    "iso:country": "GB",
    "wof:name": "WF10 3AH",
    "wof:placetype": "postalcode"
  },
  "geometry": {"coordinates":[-1.328423,53.721882],"type":"Point"}
}
