{
  "type": "Feature",
  "properties": {
    "iso:country": "GB",
    "wof:name": "WF10 3AH",
    "wof:placetype": "postalcode"
  },
  "geometry": {"coordinates":[-1.328423,53.721882],"type":"Point"}
}
