{
  "type": "Feature",
  "properties": {
    "iso:country":"GB",
    "wof:name":"OX12 8BS",
    "wof:placetype":"postalcode"
},
  "geometry": {"coordinates":[-1.42614166589507,51.58800188105327],"type":"Point"}
}