{
  "type": "Feature",
  "properties": {
    "date:inception_lower": "1980-01-01",
    "date:inception_upper": "1980-01-01",
    "iso:country": "GB",
    "wof:name": "OX12 8BS",
    "wof:placetype": "postalcode"
  },
  "geometry": {"coordinates":[-1.426038,51.588012],"type":"Point"}
}
