{
  "type": "Feature",
  "properties": {
    "iso:country": "GB",
    "wof:name": "ME17 4HJ",
    "wof:placetype": "postalcode"
  },
  "geometry": {"coordinates":[0.494432,51.230612],"type":"Point"}
}
