{
  "type": "Feature",
  "properties": {
    "iso:country":"GB",
    "wof:name":"PL9 8DW",
    "wof:placetype":"postalcode"
},
  "geometry": {"coordinates":[-4.06236500736472,50.3623626485007],"type":"Point"}
}