{
  "type": "Feature",
  "properties": {
    "iso:country":"GB",
    "wof:name":"BA12 8RB",
    "wof:placetype":"postalcode"
},
  "geometry": {"coordinates":[-2.18275282856732,51.20846509592123],"type":"Point"}
}