{
  "type": "Feature",
  "properties": {
    "iso:country":"GB",
    "wof:name":"DH5 0QA",
    "wof:placetype":"postalcode"
},
  "geometry": {"coordinates":[-1.43548233952483,54.80740105247382],"type":"Point"}
}