{
  "type": "Feature",
  "properties": {
    "iso:country":"GB",
    "wof:name":"KY13 9XS",
    "wof:placetype":"postalcode"
},
  "geometry": {"coordinates":[-3.42248416538195,56.22661162840771],"type":"Point"}
}