{
  "type": "Feature",
  "properties": {
    "date:inception_lower": "1998-12-01",
    "date:inception_upper": "1998-12-01",
    "iso:country": "GB",
    "wof:name": "KY13 9XS",
    "wof:placetype": "postalcode"
  },
  "geometry": {"coordinates":[-3.423109,56.226543],"type":"Point"}
}
