{
  "type": "Feature",
  "properties": {
    "date:inception_lower":"1995-07-01",
    "date:inception_upper":"1995-07-31",
    "iso:country":"GB",
    "wof:name":"RM20 4AX",
    "wof:placetype":"postalcode"
},
  "geometry": {"coordinates":[0.294449,51.475841],"type":"Point"}
}