{
  "type": "Feature",
  "properties": {
    "iso:country":"GB",
    "wof:name":"SK12 2DD",
    "wof:placetype":"postalcode"
},
  "geometry": {"coordinates":[-2.02942279019464,53.35531766304954],"type":"Point"}
}