{
  "type": "Feature",
  "properties": {
    "iso:country":"GB",
    "wof:name":"HP1 3AE",
    "wof:placetype":"postalcode"
},
  "geometry": {"coordinates":[-0.47202676955128,51.75834627788661],"type":"Point"}
}