{
  "type": "Feature",
  "properties": {
    "iso:country":"GB",
    "wof:name":"B50 4LW",
    "wof:placetype":"postalcode"
},
  "geometry": {"coordinates":[-1.8202768227545,52.17566963517741],"type":"Point"}
}