{
  "type": "Feature",
  "properties": {
    "iso:country":"GB",
    "wof:name":"E14 3BE",
    "wof:placetype":"postalcode"
},
  "geometry": {"coordinates":[-0.01196276928325,51.48728256769682],"type":"Point"}
}