{
  "type": "Feature",
  "properties": {
    "iso:country": "GB",
    "wof:name": "TN27 8BU",
    "wof:placetype": "postalcode"
  },
  "geometry": {"coordinates":[0.643288,51.104889],"type":"Point"}
}
