{
  "type": "Feature",
  "properties": {
    "iso:country":"GB",
    "wof:name":"TN27 8BU",
    "wof:placetype":"postalcode"
},
  "geometry": {"coordinates":[0.64328777266556,51.10488921668382],"type":"Point"}
}