{
  "type": "Feature",
  "properties": {
    "iso:country": "GB",
    "wof:name": "LE9 7NZ",
    "wof:placetype": "postalcode"
  },
  "geometry": {"coordinates":[-1.326717,52.57612],"type":"Point"}
}
