{
  "type": "Feature",
  "properties": {
    "iso:country":"GB",
    "wof:name":"CO11 1LH",
    "wof:placetype":"postalcode"
},
  "geometry": {"coordinates":[1.08583449480261,51.94314428640182],"type":"Point"}
}