{
  "type": "Feature",
  "properties": {
    "date:inception_lower": "1980-01-01",
    "date:inception_upper": "1980-01-01",
    "iso:country": "GB",
    "wof:name": "CO11 1LH",
    "wof:placetype": "postalcode"
  },
  "geometry": {"coordinates":[1.085835,51.943144],"type":"Point"}
}
