{
  "type": "Feature",
  "properties": {
    "iso:country":"GB",
    "wof:name":"RM8 1HJ",
    "wof:placetype":"postalcode"
},
  "geometry": {"coordinates":[0.14324227636206,51.56830758184573],"type":"Point"}
}