{
  "type": "Feature",
  "properties": {
    "iso:country": "GB",
    "wof:name": "RG20 0AB",
    "wof:placetype": "postalcode"
  },
  "geometry": {"coordinates":[-1.405788,51.348589],"type":"Point"}
}
