{
  "type": "Feature",
  "properties": {
    "iso:country":"GB",
    "wof:name":"RG20 0AB",
    "wof:placetype":"postalcode"
},
  "geometry": {"coordinates":[-1.40578842396453,51.34858868134896],"type":"Point"}
}