{
  "type": "Feature",
  "properties": {
    "iso:country": "GB",
    "wof:name": "SK5 8NH",
    "wof:placetype": "postalcode"
  },
  "geometry": {"coordinates":[-2.138621,53.430313],"type":"Point"}
}
