{
  "type": "Feature",
  "properties": {
    "date:inception_lower": "1995-07-01",
    "date:inception_upper": "1995-07-01",
    "iso:country": "GB",
    "wof:name": "LE16 8JF",
    "wof:placetype": "postalcode"
  },
  "geometry": {"coordinates":[-0.904025,52.47879],"type":"Point"}
}
