{
  "type": "Feature",
  "properties": {
    "date:inception_lower":"1999-06-01",
    "date:inception_upper":"1999-06-30",
    "iso:country":"GB",
    "wof:name":"CF14 6LZ",
    "wof:placetype":"postalcode"
},
  "geometry": {"coordinates":[-3.204027,51.524733],"type":"Point"}
}