{
  "type": "Feature",
  "properties": {
    "iso:country":"GB",
    "wof:name":"CF14 6LZ",
    "wof:placetype":"postalcode"
},
  "geometry": {"coordinates":[-3.20402703831332,51.52473330936778],"type":"Point"}
}