{
  "type": "Feature",
  "properties": {
    "iso:country":"GB",
    "wof:name":"PR2 6HX",
    "wof:placetype":"postalcode"
},
  "geometry": {"coordinates":[-2.65925517162056,53.77694657518538],"type":"Point"}
}