{
  "type": "Feature",
  "properties": {
    "iso:country":"GB",
    "wof:name":"WS6 7NP",
    "wof:placetype":"postalcode"
},
  "geometry": {"coordinates":[-2.02195346154796,52.65407509430948],"type":"Point"}
}