{
  "type": "Feature",
  "properties": {
    "iso:country": "GB",
    "wof:name": "GU24 8RG",
    "wof:placetype": "postalcode"
  },
  "geometry": {"coordinates":[-0.601435,51.357485],"type":"Point"}
}
