{
  "type": "Feature",
  "properties": {
    "iso:country":"GB",
    "wof:name":"EX34 9FF",
    "wof:placetype":"postalcode"
},
  "geometry": {"coordinates":[-4.11513699434152,51.208737859802],"type":"Point"}
}