{
  "type": "Feature",
  "properties": {
    "date:inception_lower": "2012-05-01",
    "date:inception_upper": "2012-05-01",
    "iso:country": "GB",
    "wof:name": "EX34 9FF",
    "wof:placetype": "postalcode"
  },
  "geometry": {"coordinates":[-4.115137,51.208738],"type":"Point"}
}
