{
  "type": "Feature",
  "properties": {
    "date:inception_lower":"1980-01-01",
    "date:inception_upper":"1980-01-31",
    "iso:country":"GB",
    "wof:name":"BN1 1NX",
    "wof:placetype":"postalcode"
},
  "geometry": {"coordinates":[-0.138328,50.821114],"type":"Point"}
}