{
  "type": "Feature",
  "properties": {
    "iso:country":"GB",
    "wof:name":"BN1 1NX",
    "wof:placetype":"postalcode"
},
  "geometry": {"coordinates":[-0.13832816211495,50.82111368218869],"type":"Point"}
}