{
  "type": "Feature",
  "properties": {
    "iso:country":"GB",
    "wof:name":"CB9 9PR",
    "wof:placetype":"postalcode"
},
  "geometry": {"coordinates":[0.41389418297911,52.08281020338836],"type":"Point"}
}