{
  "type": "Feature",
  "properties": {
    "date:inception_lower": "2003-03-01",
    "date:inception_upper": "2003-03-01",
    "iso:country": "GB",
    "wof:name": "WS12 1BH",
    "wof:placetype": "postalcode"
  },
  "geometry": {"coordinates":[-1.994215,52.705309],"type":"Point"}
}
