{
  "type": "Feature",
  "properties": {
    "iso:country": "GB",
    "wof:name": "SY4 3SE",
    "wof:placetype": "postalcode"
  },
  "geometry": {"coordinates":[-2.782994,52.809643],"type":"Point"}
}
