{
  "type": "Feature",
  "properties": {
    "date:inception_lower":"1980-01-01",
    "date:inception_upper":"1980-01-31",
    "iso:country":"GB",
    "wof:name":"LN13 9PX",
    "wof:placetype":"postalcode"
},
  "geometry": {"coordinates":[0.204336,53.266706],"type":"Point"}
}