{
  "type": "Feature",
  "properties": {
    "iso:country":"GB",
    "wof:name":"DY6 9UB",
    "wof:placetype":"postalcode"
},
  "geometry": {"coordinates":[-2.17059944954703,52.48904459687335],"type":"Point"}
}