{
  "type": "Feature",
  "properties": {
    "date:inception_lower": "1980-01-01",
    "date:inception_upper": "1980-01-01",
    "iso:country": "GB",
    "wof:name": "B28 8LX",
    "wof:placetype": "postalcode"
  },
  "geometry": {"coordinates":[-1.844224,52.44105],"type":"Point"}
}
