{
  "type": "Feature",
  "properties": {
    "iso:country":"GB",
    "wof:name":"B28 8LX",
    "wof:placetype":"postalcode"
},
  "geometry": {"coordinates":[-1.84422415039547,52.44105023683503],"type":"Point"}
}