{
  "type": "Feature",
  "properties": {
    "iso:country": "GB",
    "wof:name": "B28 8LX",
    "wof:placetype": "postalcode"
  },
  "geometry": {"coordinates":[-1.844224,52.44105],"type":"Point"}
}
