{
  "type": "Feature",
  "properties": {
    "iso:country":"GB",
    "wof:name":"EX39 3JX",
    "wof:placetype":"postalcode"
},
  "geometry": {"coordinates":[-4.21051938999969,51.02169945287729],"type":"Point"}
}