{
  "type": "Feature",
  "properties": {
    "date:inception_lower": "1980-01-01",
    "date:inception_upper": "1980-01-01",
    "iso:country": "GB",
    "wof:name": "EX39 3JX",
    "wof:placetype": "postalcode"
  },
  "geometry": {"coordinates":[-4.210546,51.02174],"type":"Point"}
}
