{
  "type": "Feature",
  "properties": {
    "iso:country": "GB",
    "wof:name": "EX39 3JX",
    "wof:placetype": "postalcode"
  },
  "geometry": {"coordinates":[-4.210519,51.021699],"type":"Point"}
}
