{
  "type": "Feature",
  "properties": {
    "iso:country": "GB",
    "wof:name": "ML1 4GR",
    "wof:placetype": "postalcode"
  },
  "geometry": {"coordinates":[-3.962058,55.806931],"type":"Point"}
}
