{
  "type": "Feature",
  "properties": {
    "date:inception_lower":"2008-09-01",
    "date:inception_upper":"2008-09-30",
    "iso:country":"GB",
    "wof:name":"ML1 4GR",
    "wof:placetype":"postalcode"
},
  "geometry": {"coordinates":[-3.962058,55.806931],"type":"Point"}
}