{
  "type": "Feature",
  "properties": {
    "iso:country":"GB",
    "wof:name":"ML1 4GR",
    "wof:placetype":"postalcode"
},
  "geometry": {"coordinates":[-3.96205764664348,55.80693055441779],"type":"Point"}
}