{
  "type": "Feature",
  "properties": {
    "iso:country":"GB",
    "wof:name":"WD18 6GJ",
    "wof:placetype":"postalcode"
},
  "geometry": {"coordinates":[-0.41236049510259,51.6475030643249],"type":"Point"}
}