{
  "type": "Feature",
  "properties": {
    "date:inception_lower": "2023-02-01",
    "date:inception_upper": "2023-02-01",
    "iso:country": "GB",
    "wof:name": "NE12 5AG",
    "wof:placetype": "postalcode"
  },
  "geometry": {"coordinates":[-1.589387,55.041348],"type":"Point"}
}
