{
  "type": "Feature",
  "properties": {
    "iso:country":"GB",
    "wof:name":"TF7 4DB",
    "wof:placetype":"postalcode"
},
  "geometry": {"coordinates":[-2.43738882434611,52.63496588936251],"type":"Point"}
}