{
  "type": "Feature",
  "properties": {
    "iso:country": "GB",
    "wof:name": "SN5 5AP",
    "wof:placetype": "postalcode"
  },
  "geometry": {"coordinates":[-1.840553,51.576923],"type":"Point"}
}
