{
  "type": "Feature",
  "properties": {
    "iso:country":"GB",
    "wof:name":"TN40 1NS",
    "wof:placetype":"postalcode"
},
  "geometry": {"coordinates":[0.48521147413472,50.84047963421625],"type":"Point"}
}