{
  "type": "Feature",
  "properties": {
    "iso:country": "GB",
    "wof:name": "TN40 1NS",
    "wof:placetype": "postalcode"
  },
  "geometry": {"coordinates":[0.485212,50.84048],"type":"Point"}
}
