{
  "type": "Feature",
  "properties": {
    "date:inception_lower": "1980-01-01",
    "date:inception_upper": "1980-01-01",
    "iso:country": "GB",
    "wof:name": "SY14 8PS",
    "wof:placetype": "postalcode"
  },
  "geometry": {"coordinates":[-2.762638,53.017553],"type":"Point"}
}
