{
  "type": "Feature",
  "properties": {
    "iso:country":"GB",
    "wof:name":"CR0 5UF",
    "wof:placetype":"postalcode"
},
  "geometry": {"coordinates":[-0.08771578437649,51.37111598285954],"type":"Point"}
}