{
  "type": "Feature",
  "properties": {
    "iso:country": "GB",
    "wof:name": "LE13 0PS",
    "wof:placetype": "postalcode"
  },
  "geometry": {"coordinates":[-0.895384,52.778903],"type":"Point"}
}
