{
  "type": "Feature",
  "properties": {
    "iso:country":"GB",
    "wof:name":"SM5 1JD",
    "wof:placetype":"postalcode"
},
  "geometry": {"coordinates":[-0.17063587008894,51.38538056889301],"type":"Point"}
}