{
  "type": "Feature",
  "properties": {
    "iso:country":"GB",
    "wof:name":"LD3 7SQ",
    "wof:placetype":"postalcode"
},
  "geometry": {"coordinates":[-3.22782192740494,51.8896004129102],"type":"Point"}
}