{
  "type": "Feature",
  "properties": {
    "iso:country":"GB",
    "wof:name":"CM13 3QW",
    "wof:placetype":"postalcode"
},
  "geometry": {"coordinates":[0.34245777679432,51.61219809899171],"type":"Point"}
}