{
  "type": "Feature",
  "properties": {
    "iso:country": "GB",
    "wof:name": "CM13 3QW",
    "wof:placetype": "postalcode"
  },
  "geometry": {"coordinates":[0.342486,51.612201],"type":"Point"}
}
