{
  "type": "Feature",
  "properties": {
    "iso:country":"GB",
    "wof:name":"SG4 8EH",
    "wof:placetype":"postalcode"
},
  "geometry": {"coordinates":[-0.29406702454503,51.84323682106125],"type":"Point"}
}