{
  "type": "Feature",
  "properties": {
    "date:inception_lower": "1998-06-01",
    "date:inception_upper": "1998-06-01",
    "iso:country": "GB",
    "wof:name": "YO26 8BW",
    "wof:placetype": "postalcode"
  },
  "geometry": {"coordinates":[-1.298136,54.004114],"type":"Point"}
}
