{
  "type": "Feature",
  "properties": {
    "iso:country":"GB",
    "wof:name":"YO26 8BW",
    "wof:placetype":"postalcode"
},
  "geometry": {"coordinates":[-1.29813583800963,54.00411362324709],"type":"Point"}
}