{
  "type": "Feature",
  "properties": {
    "date:inception_lower":"1994-05-01",
    "date:inception_upper":"1994-05-31",
    "iso:country":"GB",
    "wof:name":"M9 4AB",
    "wof:placetype":"postalcode"
},
  "geometry": {"coordinates":[-2.211784,53.515533],"type":"Point"}
}