{
  "type": "Feature",
  "properties": {
    "iso:country": "GB",
    "wof:name": "BS35 4DZ",
    "wof:placetype": "postalcode"
  },
  "geometry": {"coordinates":[-2.573125,51.58099],"type":"Point"}
}
