{
  "type": "Feature",
  "properties": {
    "date:inception_lower": "1980-01-01",
    "date:inception_upper": "1980-01-01",
    "iso:country": "GB",
    "wof:name": "ST10 1DP",
    "wof:placetype": "postalcode"
  },
  "geometry": {"coordinates":[-1.993585,52.976636],"type":"Point"}
}
