{
  "type": "Feature",
  "properties": {
    "iso:country":"GB",
    "wof:name":"ST10 1DP",
    "wof:placetype":"postalcode"
},
  "geometry": {"coordinates":[-1.99358480316365,52.97663630821684],"type":"Point"}
}