{
  "type": "Feature",
  "properties": {
    "iso:country":"GB",
    "wof:name":"DL1 3PR",
    "wof:placetype":"postalcode"
},
  "geometry": {"coordinates":[-1.52564392030331,54.54758474831264],"type":"Point"}
}