{
  "type": "Feature",
  "properties": {
    "iso:country":"GB",
    "wof:name":"SW17 7DH",
    "wof:placetype":"postalcode"
},
  "geometry": {"coordinates":[-0.16689612152213,51.43974543363412],"type":"Point"}
}