{
  "type": "Feature",
  "properties": {
    "iso:country": "GB",
    "wof:name": "SW17 7DH",
    "wof:placetype": "postalcode"
  },
  "geometry": {"coordinates":[-0.166896,51.439745],"type":"Point"}
}
