{
  "type": "Feature",
  "properties": {
    "iso:country": "GB",
    "wof:name": "DG1 1QW",
    "wof:placetype": "postalcode"
  },
  "geometry": {"coordinates":[-3.587724,55.107543],"type":"Point"}
}
