{
  "type": "Feature",
  "properties": {
    "iso:country":"GB",
    "wof:name":"NW9 5BX",
    "wof:placetype":"postalcode"
},
  "geometry": {"coordinates":[-0.26010794759973,51.59855935977056],"type":"Point"}
}