{
  "type": "Feature",
  "properties": {
    "date:inception_lower": "2017-09-01",
    "date:inception_upper": "2017-09-01",
    "iso:country": "GB",
    "wof:name": "BH24 2YQ",
    "wof:placetype": "postalcode"
  },
  "geometry": {"coordinates":[-1.786621,50.86021],"type":"Point"}
}
