{
  "type": "Feature",
  "properties": {
    "date:inception_lower": "1980-01-01",
    "date:inception_upper": "1980-01-01",
    "iso:country": "GB",
    "wof:name": "WA6 8NZ",
    "wof:placetype": "postalcode"
  },
  "geometry": {"coordinates":[-2.633582,53.250581],"type":"Point"}
}
