{
  "type": "Feature",
  "properties": {
    "iso:country":"GB",
    "wof:name":"PE38 9BA",
    "wof:placetype":"postalcode"
},
  "geometry": {"coordinates":[0.38212866824145,52.59748315803573],"type":"Point"}
}