{
  "type": "Feature",
  "properties": {
    "date:inception_lower": "1980-01-01",
    "date:inception_upper": "1980-01-01",
    "iso:country": "GB",
    "wof:name": "PE38 9BA",
    "wof:placetype": "postalcode"
  },
  "geometry": {"coordinates":[0.382095,52.59762],"type":"Point"}
}
