{
  "type": "Feature",
  "properties": {
    "iso:country":"GB",
    "wof:name":"RM14 2JP",
    "wof:placetype":"postalcode"
},
  "geometry": {"coordinates":[0.24565428212518,51.54900866750891],"type":"Point"}
}