{
  "type": "Feature",
  "properties": {
    "iso:country":"GB",
    "wof:name":"FY5 2RL",
    "wof:placetype":"postalcode"
},
  "geometry": {"coordinates":[-3.01304936603928,53.88256316590279],"type":"Point"}
}