{
  "type": "Feature",
  "properties": {
    "iso:country": "GB",
    "wof:name": "NE1 2ES",
    "wof:placetype": "postalcode"
  },
  "geometry": {"coordinates":[-1.607563,54.970086],"type":"Point"}
}
