{
  "type": "Feature",
  "properties": {
    "iso:country":"GB",
    "wof:name":"S74 0JQ",
    "wof:placetype":"postalcode"
},
  "geometry": {"coordinates":[-1.42436768750759,53.50726277788032],"type":"Point"}
}