{
  "type": "Feature",
  "properties": {
    "iso:country": "GB",
    "wof:name": "S74 0JQ",
    "wof:placetype": "postalcode"
  },
  "geometry": {"coordinates":[-1.424368,53.507263],"type":"Point"}
}
