{
  "type": "Feature",
  "properties": {
    "iso:country":"GB",
    "wof:name":"CV32 6RX",
    "wof:placetype":"postalcode"
},
  "geometry": {"coordinates":[-1.55445110353847,52.3000851850305],"type":"Point"}
}