{
  "type": "Feature",
  "properties": {
    "date:inception_lower": "1985-04-01",
    "date:inception_upper": "1985-04-01",
    "iso:country": "GB",
    "wof:name": "CV32 6RX",
    "wof:placetype": "postalcode"
  },
  "geometry": {"coordinates":[-1.55444,52.3001],"type":"Point"}
}
