{
  "type": "Feature",
  "properties": {
    "date:inception_lower":"1980-01-01",
    "date:inception_upper":"1980-01-31",
    "iso:country":"GB",
    "wof:name":"SP7 8HN",
    "wof:placetype":"postalcode"
},
  "geometry": {"coordinates":[-2.204526,51.001674],"type":"Point"}
}