{
  "type": "Feature",
  "properties": {
    "iso:country": "GB",
    "wof:name": "WF12 8BZ",
    "wof:placetype": "postalcode"
  },
  "geometry": {"coordinates":[-1.618841,53.688805],"type":"Point"}
}
