{
  "type": "Feature",
  "properties": {
    "iso:country":"GB",
    "wof:name":"WF12 8BZ",
    "wof:placetype":"postalcode"
},
  "geometry": {"coordinates":[-1.61884070079856,53.68880456480236],"type":"Point"}
}