{
  "type": "Feature",
  "properties": {
    "date:inception_lower":"1980-01-01",
    "date:inception_upper":"1980-01-31",
    "iso:country":"GB",
    "wof:name":"WA11 7DG",
    "wof:placetype":"postalcode"
},
  "geometry": {"coordinates":[-2.731506,53.480062],"type":"Point"}
}