{
  "type": "Feature",
  "properties": {
    "iso:country": "GB",
    "wof:name": "WA11 7DG",
    "wof:placetype": "postalcode"
  },
  "geometry": {"coordinates":[-2.731506,53.480062],"type":"Point"}
}
