{
  "type": "Feature",
  "properties": {
    "iso:country": "GB",
    "wof:name": "HX4 8BQ",
    "wof:placetype": "postalcode"
  },
  "geometry": {"coordinates":[-1.862503,53.682959],"type":"Point"}
}
