{
  "type": "Feature",
  "properties": {
    "iso:country":"GB",
    "wof:name":"HX4 8BQ",
    "wof:placetype":"postalcode"
},
  "geometry": {"coordinates":[-1.86250290490111,53.68295894447154],"type":"Point"}
}