{
  "type": "Feature",
  "properties": {
    "date:inception_lower":"1980-01-01",
    "date:inception_upper":"1980-01-31",
    "iso:country":"GB",
    "wof:name":"DG13 0HQ",
    "wof:placetype":"postalcode"
},
  "geometry": {"coordinates":[-2.987244,55.175681],"type":"Point"}
}