{
  "type": "Feature",
  "properties": {
    "iso:country":"GB",
    "wof:name":"DG13 0HQ",
    "wof:placetype":"postalcode"
},
  "geometry": {"coordinates":[-2.98724450883,55.1756811490203],"type":"Point"}
}