{
  "type": "Feature",
  "properties": {
    "date:inception_lower": "1994-05-01",
    "date:inception_upper": "1994-05-01",
    "iso:country": "GB",
    "wof:name": "M21 8XG",
    "wof:placetype": "postalcode"
  },
  "geometry": {"coordinates":[-2.271384,53.44026],"type":"Point"}
}
