{
  "type": "Feature",
  "properties": {
    "iso:country":"GB",
    "wof:name":"M21 8XG",
    "wof:placetype":"postalcode"
},
  "geometry": {"coordinates":[-2.27138440781138,53.44026001493554],"type":"Point"}
}