{
  "type": "Feature",
  "properties": {
    "iso:country": "GB",
    "wof:name": "BA1 5DF",
    "wof:placetype": "postalcode"
  },
  "geometry": {"coordinates":[-2.357501,51.389831],"type":"Point"}
}
