{
  "type": "Feature",
  "properties": {
    "iso:country": "GB",
    "wof:name": "CB25 0GA",
    "wof:placetype": "postalcode"
  },
  "geometry": {"coordinates":[0.3244,52.27931],"type":"Point"}
}
