{
  "type": "Feature",
  "properties": {
    "iso:country":"GB",
    "wof:name":"L35 1QW",
    "wof:placetype":"postalcode"
},
  "geometry": {"coordinates":[-2.79819856082625,53.37484402649299],"type":"Point"}
}