{
  "type": "Feature",
  "properties": {
    "date:inception_lower":"1980-01-01",
    "date:inception_upper":"1980-01-31",
    "iso:country":"GB",
    "wof:name":"L35 1QW",
    "wof:placetype":"postalcode"
},
  "geometry": {"coordinates":[-2.798199,53.374844],"type":"Point"}
}