{
  "type": "Feature",
  "properties": {
    "date:inception_lower": "1980-01-01",
    "date:inception_upper": "1980-01-01",
    "iso:country": "GB",
    "wof:name": "DL14 6PR",
    "wof:placetype": "postalcode"
  },
  "geometry": {"coordinates":[-1.681625,54.644748],"type":"Point"}
}
