{
  "type": "Feature",
  "properties": {
    "iso:country":"GB",
    "wof:name":"DL14 6PR",
    "wof:placetype":"postalcode"
},
  "geometry": {"coordinates":[-1.68162524789174,54.64474846378745],"type":"Point"}
}