{
  "type": "Feature",
  "properties": {
    "iso:country":"GB",
    "wof:name":"PR2 2AY",
    "wof:placetype":"postalcode"
},
  "geometry": {"coordinates":[-2.71812497503843,53.77029858752806],"type":"Point"}
}