{
  "type": "Feature",
  "properties": {
    "date:inception_lower": "1980-01-01",
    "date:inception_upper": "1980-01-01",
    "iso:country": "GB",
    "wof:name": "CF5 4RA",
    "wof:placetype": "postalcode"
  },
  "geometry": {"coordinates":[-3.256973,51.47608],"type":"Point"}
}
