{
  "type": "Feature",
  "properties": {
    "iso:country":"GB",
    "wof:name":"CF5 4RA",
    "wof:placetype":"postalcode"
},
  "geometry": {"coordinates":[-3.25697322353159,51.47607986768175],"type":"Point"}
}