{
  "type": "Feature",
  "properties": {
    "date:inception_lower": "1980-01-01",
    "date:inception_upper": "1980-01-01",
    "iso:country": "GB",
    "wof:name": "DA11 9PZ",
    "wof:placetype": "postalcode"
  },
  "geometry": {"coordinates":[0.341988,51.440961],"type":"Point"}
}
