{
  "type": "Feature",
  "properties": {
    "iso:country":"GB",
    "wof:name":"DA11 9PZ",
    "wof:placetype":"postalcode"
},
  "geometry": {"coordinates":[0.34188579771998,51.44095364188692],"type":"Point"}
}