{
  "type": "Feature",
  "properties": {
    "iso:country":"GB",
    "wof:name":"EN1 3AZ",
    "wof:placetype":"postalcode"
},
  "geometry": {"coordinates":[-0.07658965199316,51.6542091649798],"type":"Point"}
}