{
  "type": "Feature",
  "properties": {
    "iso:country":"GB",
    "wof:name":"ME14 1RH",
    "wof:placetype":"postalcode"
},
  "geometry": {"coordinates":[0.52223651942901,51.27721453127744],"type":"Point"}
}