{
  "type": "Feature",
  "properties": {
    "date:inception_lower":"1980-01-01",
    "date:inception_upper":"1980-01-31",
    "iso:country":"GB",
    "wof:name":"ME14 1RH",
    "wof:placetype":"postalcode"
},
  "geometry": {"coordinates":[0.522237,51.277215],"type":"Point"}
}