{
  "type": "Feature",
  "properties": {
    "date:inception_lower": "1980-01-01",
    "date:inception_upper": "1980-01-01",
    "iso:country": "GB",
    "wof:name": "GL20 6JJ",
    "wof:placetype": "postalcode"
  },
  "geometry": {"coordinates":[-2.157771,52.022843],"type":"Point"}
}
