{
  "type": "Feature",
  "properties": {
    "iso:country":"GB",
    "wof:name":"GL20 6JJ",
    "wof:placetype":"postalcode"
},
  "geometry": {"coordinates":[-2.15777062285652,52.02284295067117],"type":"Point"}
}