{
  "type": "Feature",
  "properties": {
    "iso:country":"GB",
    "wof:name":"HP13 7LT",
    "wof:placetype":"postalcode"
},
  "geometry": {"coordinates":[-0.72413074972955,51.63566724040997],"type":"Point"}
}