{
  "type": "Feature",
  "properties": {
    "iso:country":"GB",
    "wof:name":"NE66 5RD",
    "wof:placetype":"postalcode"
},
  "geometry": {"coordinates":[-1.85902760787391,55.55700312218369],"type":"Point"}
}