{
  "type": "Feature",
  "properties": {
    "date:inception_lower": "1980-01-01",
    "date:inception_upper": "1980-01-01",
    "iso:country": "GB",
    "wof:name": "NE66 5RD",
    "wof:placetype": "postalcode"
  },
  "geometry": {"coordinates":[-1.85904,55.557003],"type":"Point"}
}
