{
  "type": "Feature",
  "properties": {
    "date:inception_lower": "1980-01-01",
    "date:inception_upper": "1980-01-01",
    "iso:country": "GB",
    "wof:name": "IV51 9DX",
    "wof:placetype": "postalcode"
  },
  "geometry": {"coordinates":[-6.194442,57.415187],"type":"Point"}
}
