{
  "type": "Feature",
  "properties": {
    "iso:country":"GB",
    "wof:name":"WN2 1XX",
    "wof:placetype":"postalcode"
},
  "geometry": {"coordinates":[-2.5802667358329,53.56844940099484],"type":"Point"}
}