{
  "type": "Feature",
  "properties": {
    "date:inception_lower": "1980-01-01",
    "date:inception_upper": "1980-01-01",
    "iso:country": "GB",
    "wof:name": "WN2 1XX",
    "wof:placetype": "postalcode"
  },
  "geometry": {"coordinates":[-2.580267,53.568449],"type":"Point"}
}
