{
  "type": "Feature",
  "properties": {
    "iso:country":"GB",
    "wof:name":"PL26 6NB",
    "wof:placetype":"postalcode"
},
  "geometry": {"coordinates":[-4.86194493530903,50.25399393449162],"type":"Point"}
}