{
  "type": "Feature",
  "properties": {
    "date:inception_lower": "1980-01-01",
    "date:inception_upper": "1980-01-01",
    "iso:country": "GB",
    "wof:name": "PL26 6NB",
    "wof:placetype": "postalcode"
  },
  "geometry": {"coordinates":[-4.861406,50.253618],"type":"Point"}
}
