{
  "type": "Feature",
  "properties": {
    "iso:country":"GB",
    "wof:name":"RG20 6RD",
    "wof:placetype":"postalcode"
},
  "geometry": {"coordinates":[-1.23858702456697,51.51262023046453],"type":"Point"}
}