{
  "type": "Feature",
  "properties": {
    "date:inception_lower": "1992-08-01",
    "date:inception_upper": "1992-08-01",
    "iso:country": "GB",
    "wof:name": "BA11 3AY",
    "wof:placetype": "postalcode"
  },
  "geometry": {"coordinates":[-2.328768,51.231187],"type":"Point"}
}
