{
  "type": "Feature",
  "properties": {
    "iso:country": "GB",
    "wof:name": "BA11 3AY",
    "wof:placetype": "postalcode"
  },
  "geometry": {"coordinates":[-2.328628,51.231219],"type":"Point"}
}
