{
  "type": "Feature",
  "properties": {
    "iso:country":"GB",
    "wof:name":"PO16 0NH",
    "wof:placetype":"postalcode"
},
  "geometry": {"coordinates":[-1.17857968412013,50.85084267841334],"type":"Point"}
}