{
  "type": "Feature",
  "properties": {
    "iso:country": "GB",
    "wof:name": "BL8 1GS",
    "wof:placetype": "postalcode"
  },
  "geometry": {"coordinates":[-2.316674,53.608915],"type":"Point"}
}
