{
  "type": "Feature",
  "properties": {
    "iso:country":"GB",
    "wof:name":"CA3 0BP",
    "wof:placetype":"postalcode"
},
  "geometry": {"coordinates":[-2.94397608095578,54.92379082251899],"type":"Point"}
}