{
  "type": "Feature",
  "properties": {
    "iso:country": "GB",
    "wof:name": "CA3 0BP",
    "wof:placetype": "postalcode"
  },
  "geometry": {"coordinates":[-2.943964,54.923797],"type":"Point"}
}
