{
  "type": "Feature",
  "properties": {
    "iso:country": "GB",
    "wof:name": "CA28 9SJ",
    "wof:placetype": "postalcode"
  },
  "geometry": {"coordinates":[-3.578792,54.526802],"type":"Point"}
}
