{
  "type": "Feature",
  "properties": {
    "iso:country":"GB",
    "wof:name":"CM1 6BG",
    "wof:placetype":"postalcode"
},
  "geometry": {"coordinates":[0.50449118353088,51.75806637106292],"type":"Point"}
}