{
  "type": "Feature",
  "properties": {
    "iso:country":"GB",
    "wof:name":"EH32 9AH",
    "wof:placetype":"postalcode"
},
  "geometry": {"coordinates":[-2.97859797282735,55.96144988993887],"type":"Point"}
}