{
  "type": "Feature",
  "properties": {
    "date:inception_lower":"1980-01-01",
    "date:inception_upper":"1980-01-31",
    "iso:country":"GB",
    "wof:name":"BD17 6SW",
    "wof:placetype":"postalcode"
},
  "geometry": {"coordinates":[-1.754641,53.852472],"type":"Point"}
}