{
  "type": "Feature",
  "properties": {
    "iso:country":"GB",
    "wof:name":"BD17 6SW",
    "wof:placetype":"postalcode"
},
  "geometry": {"coordinates":[-1.75464151740564,53.85247173691382],"type":"Point"}
}