{
  "type": "Feature",
  "properties": {
    "date:inception_lower": "1980-01-01",
    "date:inception_upper": "1980-01-01",
    "iso:country": "GB",
    "wof:name": "CT6 7QW",
    "wof:placetype": "postalcode"
  },
  "geometry": {"coordinates":[1.103709,51.360233],"type":"Point"}
}
