{
  "type": "Feature",
  "properties": {
    "iso:country":"GB",
    "wof:name":"CT6 7QW",
    "wof:placetype":"postalcode"
},
  "geometry": {"coordinates":[1.10370925415704,51.36023259311895],"type":"Point"}
}