{
  "type": "Feature",
  "properties": {
    "iso:country":"GB",
    "wof:name":"DE6 1QA",
    "wof:placetype":"postalcode"
},
  "geometry": {"coordinates":[-1.71934505662803,53.08650377526162],"type":"Point"}
}