{
  "type": "Feature",
  "properties": {
    "iso:country":"GB",
    "wof:name":"GU34 4DX",
    "wof:placetype":"postalcode"
},
  "geometry": {"coordinates":[-1.00389673757818,51.17280817982775],"type":"Point"}
}