{
  "type": "Feature",
  "properties": {
    "iso:country":"GB",
    "wof:name":"TN33 9LF",
    "wof:placetype":"postalcode"
},
  "geometry": {"coordinates":[0.42298078280261,50.88625563382271],"type":"Point"}
}