{
  "type": "Feature",
  "properties": {
    "date:inception_lower": "1981-06-01",
    "date:inception_upper": "1981-06-01",
    "iso:country": "GB",
    "wof:name": "TN33 9LF",
    "wof:placetype": "postalcode"
  },
  "geometry": {"coordinates":[0.422996,50.886251],"type":"Point"}
}
