{
  "type": "Feature",
  "properties": {
    "iso:country": "GB",
    "wof:name": "NN6 7DF",
    "wof:placetype": "postalcode"
  },
  "geometry": {"coordinates":[-1.067232,52.341358],"type":"Point"}
}
