{
  "type": "Feature",
  "properties": {
    "iso:country":"GB",
    "wof:name":"WA13 9UA",
    "wof:placetype":"postalcode"
},
  "geometry": {"coordinates":[-2.41273565733046,53.39924450473043],"type":"Point"}
}