{
  "type": "Feature",
  "properties": {
    "date:inception_lower": "1980-01-01",
    "date:inception_upper": "1980-01-01",
    "iso:country": "GB",
    "wof:name": "TA2 7LF",
    "wof:placetype": "postalcode"
  },
  "geometry": {"coordinates":[-3.09455,51.034137],"type":"Point"}
}
