{
  "type": "Feature",
  "properties": {
    "iso:country":"GB",
    "wof:name":"TQ14 9QJ",
    "wof:placetype":"postalcode"
},
  "geometry": {"coordinates":[-3.53853809436486,50.5495393220535],"type":"Point"}
}