{
  "type": "Feature",
  "properties": {
    "date:inception_lower": "1980-01-01",
    "date:inception_upper": "1980-01-01",
    "iso:country": "GB",
    "wof:name": "DE5 3JN",
    "wof:placetype": "postalcode"
  },
  "geometry": {"coordinates":[-1.395638,53.042881],"type":"Point"}
}
