{
  "type": "Feature",
  "properties": {
    "iso:country":"GB",
    "wof:name":"B46 3ND",
    "wof:placetype":"postalcode"
},
  "geometry": {"coordinates":[-1.70622395531206,52.49119526009132],"type":"Point"}
}