{
  "type": "Feature",
  "properties": {
    "date:inception_lower": "1980-01-01",
    "date:inception_upper": "1980-01-01",
    "iso:country": "GB",
    "wof:name": "B46 3ND",
    "wof:placetype": "postalcode"
  },
  "geometry": {"coordinates":[-1.706224,52.491195],"type":"Point"}
}
