{
  "type": "Feature",
  "properties": {
    "date:inception_lower": "1980-01-01",
    "date:inception_upper": "1980-01-01",
    "iso:country": "GB",
    "wof:name": "BA4 5XL",
    "wof:placetype": "postalcode"
  },
  "geometry": {"coordinates":[-2.559481,51.188206],"type":"Point"}
}
