{
  "type": "Feature",
  "properties": {
    "iso:country":"GB",
    "wof:name":"GU15 3GH",
    "wof:placetype":"postalcode"
},
  "geometry": {"coordinates":[-0.74941731266607,51.33767583448959],"type":"Point"}
}