{
  "type": "Feature",
  "properties": {
    "iso:country": "GB",
    "wof:name": "GU15 3GH",
    "wof:placetype": "postalcode"
  },
  "geometry": {"coordinates":[-0.749417,51.337676],"type":"Point"}
}
