{
  "type": "Feature",
  "properties": {
    "iso:country":"GB",
    "wof:name":"WF3 3JU",
    "wof:placetype":"postalcode"
},
  "geometry": {"coordinates":[-1.51861325966104,53.72586175318092],"type":"Point"}
}