{
  "type": "Feature",
  "properties": {
    "iso:country":"GB",
    "wof:name":"BA3 4AH",
    "wof:placetype":"postalcode"
},
  "geometry": {"coordinates":[-2.47475680311158,51.27851849045241],"type":"Point"}
}