{
  "type": "Feature",
  "properties": {
    "iso:country": "GB",
    "wof:name": "BA3 4AH",
    "wof:placetype": "postalcode"
  },
  "geometry": {"coordinates":[-2.474757,51.278518],"type":"Point"}
}
