{
  "type": "Feature",
  "properties": {
    "date:inception_lower": "2004-01-01",
    "date:inception_upper": "2004-01-01",
    "iso:country": "GB",
    "wof:name": "HA7 3SY",
    "wof:placetype": "postalcode"
  },
  "geometry": {"coordinates":[-0.321823,51.616084],"type":"Point"}
}
