{
  "type": "Feature",
  "properties": {
    "iso:country":"GB",
    "wof:name":"HA7 3SY",
    "wof:placetype":"postalcode"
},
  "geometry": {"coordinates":[-0.32182294702964,51.61608445882963],"type":"Point"}
}