{
  "type": "Feature",
  "properties": {
    "iso:country":"GB",
    "wof:name":"BR1 3SL",
    "wof:placetype":"postalcode"
},
  "geometry": {"coordinates":[0.0053162108204,51.41521708195074],"type":"Point"}
}