{
  "type": "Feature",
  "properties": {
    "iso:country":"GB",
    "wof:name":"SW6 4LZ",
    "wof:placetype":"postalcode"
},
  "geometry": {"coordinates":[-0.20657653263477,51.47142836972505],"type":"Point"}
}