{
  "type": "Feature",
  "properties": {
    "iso:country":"GB",
    "wof:name":"DN35 7UB",
    "wof:placetype":"postalcode"
},
  "geometry": {"coordinates":[-0.04176720373717,53.56291971225146],"type":"Point"}
}