{
  "type": "Feature",
  "properties": {
    "iso:country":"GB",
    "wof:name":"TA4 2BG",
    "wof:placetype":"postalcode"
},
  "geometry": {"coordinates":[-3.36590356042081,51.00795720423689],"type":"Point"}
}