{
  "type": "Feature",
  "properties": {
    "date:inception_lower": "2019-05-01",
    "date:inception_upper": "2019-05-01",
    "iso:country": "GB",
    "wof:name": "HP15 6AZ",
    "wof:placetype": "postalcode"
  },
  "geometry": {"coordinates":[-0.719608,51.675977],"type":"Point"}
}
