{
  "type": "Feature",
  "properties": {
    "date:inception_lower": "2021-05-01",
    "date:inception_upper": "2021-05-01",
    "iso:country": "GB",
    "wof:name": "LL13 7AH",
    "wof:placetype": "postalcode"
  },
  "geometry": {"coordinates":[-2.998886,53.040271],"type":"Point"}
}
