{
  "type": "Feature",
  "properties": {
    "iso:country": "GB",
    "wof:name": "L3 5ND",
    "wof:placetype": "postalcode"
  },
  "geometry": {"coordinates":[-2.971148,53.407145],"type":"Point"}
}
