{
  "type": "Feature",
  "properties": {
    "iso:country":"GB",
    "wof:name":"LE4 2DG",
    "wof:placetype":"postalcode"
},
  "geometry": {"coordinates":[-1.14172774943039,52.66125563941453],"type":"Point"}
}