{
  "type": "Feature",
  "properties": {
    "iso:country":"GB",
    "wof:name":"DG2 9SG",
    "wof:placetype":"postalcode"
},
  "geometry": {"coordinates":[-3.64398943693769,55.06713604326347],"type":"Point"}
}