{
  "type": "Feature",
  "properties": {
    "date:inception_lower":"2014-09-01",
    "date:inception_upper":"2014-09-30",
    "iso:country":"GB",
    "wof:name":"DG2 9SG",
    "wof:placetype":"postalcode"
},
  "geometry": {"coordinates":[-3.643989,55.067136],"type":"Point"}
}