{
  "type": "Feature",
  "properties": {
    "date:inception_lower":"1980-01-01",
    "date:inception_upper":"1980-01-31",
    "iso:country":"GB",
    "wof:name":"ST5 4DX",
    "wof:placetype":"postalcode"
},
  "geometry": {"coordinates":[-2.246446,52.972021],"type":"Point"}
}