{
  "type": "Feature",
  "properties": {
    "iso:country": "GB",
    "wof:name": "ST5 4DX",
    "wof:placetype": "postalcode"
  },
  "geometry": {"coordinates":[-2.246446,52.972021],"type":"Point"}
}
