{
  "type": "Feature",
  "properties": {
    "iso:country":"GB",
    "wof:name":"ST5 4DX",
    "wof:placetype":"postalcode"
},
  "geometry": {"coordinates":[-2.25368347755114,52.9721672875097],"type":"Point"}
}