{
  "type": "Feature",
  "properties": {
    "iso:country":"GB",
    "wof:name":"LL12 0HS",
    "wof:placetype":"postalcode"
},
  "geometry": {"coordinates":[-2.96497316199921,53.10784750440497],"type":"Point"}
}