{
  "type": "Feature",
  "properties": {
    "iso:country": "GB",
    "wof:name": "NN3 6QF",
    "wof:placetype": "postalcode"
  },
  "geometry": {"coordinates":[-0.858977,52.274941],"type":"Point"}
}
