{
  "type": "Feature",
  "properties": {
    "iso:country":"GB",
    "wof:name":"AL6 0UN",
    "wof:placetype":"postalcode"
},
  "geometry": {"coordinates":[-0.18481153694293,51.84323798370027],"type":"Point"}
}