{
  "type": "Feature",
  "properties": {
    "iso:country":"GB",
    "wof:name":"SM1 1RE",
    "wof:placetype":"postalcode"
},
  "geometry": {"coordinates":[-0.19692649989116,51.37355811905719],"type":"Point"}
}