{
  "type": "Feature",
  "properties": {
    "iso:country": "GB",
    "wof:name": "SW9 9AJ",
    "wof:placetype": "postalcode"
  },
  "geometry": {"coordinates":[-0.126657,51.469191],"type":"Point"}
}
