{
  "type": "Feature",
  "properties": {
    "iso:country":"GB",
    "wof:name":"SW9 9AJ",
    "wof:placetype":"postalcode"
},
  "geometry": {"coordinates":[-0.12662313487195,51.46924292750407],"type":"Point"}
}