{
  "type": "Feature",
  "properties": {
    "date:inception_lower":"1980-01-01",
    "date:inception_upper":"1980-01-31",
    "iso:country":"GB",
    "wof:name":"SW9 9AJ",
    "wof:placetype":"postalcode"
},
  "geometry": {"coordinates":[-0.126598,51.469244],"type":"Point"}
}