{
  "type": "Feature",
  "properties": {
    "iso:country": "GB",
    "wof:name": "SS13 3EF",
    "wof:placetype": "postalcode"
  },
  "geometry": {"coordinates":[0.501169,51.568201],"type":"Point"}
}
