{
  "type": "Feature",
  "properties": {
    "iso:country":"GB",
    "wof:name":"L5 1XH",
    "wof:placetype":"postalcode"
},
  "geometry": {"coordinates":[-2.96554182251563,53.42791848008082],"type":"Point"}
}