{
  "type": "Feature",
  "properties": {
    "iso:country":"GB",
    "wof:name":"SR2 0JH",
    "wof:placetype":"postalcode"
},
  "geometry": {"coordinates":[-1.37558871849624,54.86762343588338],"type":"Point"}
}