{
  "type": "Feature",
  "properties": {
    "iso:country":"GB",
    "wof:name":"DE3 0RR",
    "wof:placetype":"postalcode"
},
  "geometry": {"coordinates":[-1.55359041195652,52.90997053373563],"type":"Point"}
}