{
  "type": "Feature",
  "properties": {
    "iso:country":"GB",
    "wof:name":"LE7 7BQ",
    "wof:placetype":"postalcode"
},
  "geometry": {"coordinates":[-1.18054291325846,52.67687607305668],"type":"Point"}
}