{
  "type": "Feature",
  "properties": {
    "iso:country":"GB",
    "wof:name":"MK5 6ED",
    "wof:placetype":"postalcode"
},
  "geometry": {"coordinates":[-0.79362562265902,52.02766335577656],"type":"Point"}
}