{
  "type": "Feature",
  "properties": {
    "date:inception_lower": "1990-02-01",
    "date:inception_upper": "1990-02-01",
    "iso:country": "GB",
    "wof:name": "MK5 6ED",
    "wof:placetype": "postalcode"
  },
  "geometry": {"coordinates":[-0.793626,52.027663],"type":"Point"}
}
