{
  "type": "Feature",
  "properties": {
    "iso:country": "GB",
    "wof:name": "SW16 4BE",
    "wof:placetype": "postalcode"
  },
  "geometry": {"coordinates":[-0.121824,51.407693],"type":"Point"}
}
