{
  "type": "Feature",
  "properties": {
    "iso:country":"GB",
    "wof:name":"SW16 4BE",
    "wof:placetype":"postalcode"
},
  "geometry": {"coordinates":[-0.12180996994462,51.40761136132099],"type":"Point"}
}