{
  "type": "Feature",
  "properties": {
    "iso:country": "GB",
    "wof:name": "NN1 1AG",
    "wof:placetype": "postalcode"
  },
  "geometry": {"coordinates":[-0.894019,52.235583],"type":"Point"}
}
