{
  "type": "Feature",
  "properties": {
    "date:inception_lower":"2008-03-01",
    "date:inception_upper":"2008-03-31",
    "iso:country":"GB",
    "wof:name":"NN1 1AG",
    "wof:placetype":"postalcode"
},
  "geometry": {"coordinates":[-0.894019,52.235583],"type":"Point"}
}