{
  "type": "Feature",
  "properties": {
    "iso:country": "GB",
    "wof:name": "S40 3JA",
    "wof:placetype": "postalcode"
  },
  "geometry": {"coordinates":[-1.444573,53.225032],"type":"Point"}
}
