{
  "type": "Feature",
  "properties": {
    "iso:country":"GB",
    "wof:name":"CM0 8SW",
    "wof:placetype":"postalcode"
},
  "geometry": {"coordinates":[0.81281769020005,51.63208424303946],"type":"Point"}
}