{
  "type": "Feature",
  "properties": {
    "iso:country":"GB",
    "wof:name":"G71 8NQ",
    "wof:placetype":"postalcode"
},
  "geometry": {"coordinates":[-4.06075348770244,55.80055248667758],"type":"Point"}
}