{
  "type": "Feature",
  "properties": {
    "iso:country": "GB",
    "wof:name": "E3 2BY",
    "wof:placetype": "postalcode"
  },
  "geometry": {"coordinates":[-0.027097,51.529122],"type":"Point"}
}
