{
  "type": "Feature",
  "properties": {
    "iso:country":"GB",
    "wof:name":"E3 2BY",
    "wof:placetype":"postalcode"
},
  "geometry": {"coordinates":[-0.02763508855834,51.5293090865134],"type":"Point"}
}