{
  "type": "Feature",
  "properties": {
    "iso:country":"GB",
    "wof:name":"LL19 7UP",
    "wof:placetype":"postalcode"
},
  "geometry": {"coordinates":[-3.42215878287332,53.3349424023189],"type":"Point"}
}