{
  "type": "Feature",
  "properties": {
    "date:inception_lower":"2008-10-01",
    "date:inception_upper":"2008-10-31",
    "iso:country":"GB",
    "wof:name":"FK4 2HX",
    "wof:placetype":"postalcode"
},
  "geometry": {"coordinates":[-3.965718,55.98065],"type":"Point"}
}