{
  "type": "Feature",
  "properties": {
    "iso:country":"GB",
    "wof:name":"FK4 2HX",
    "wof:placetype":"postalcode"
},
  "geometry": {"coordinates":[-3.96571850783673,55.98064972043525],"type":"Point"}
}