{
  "type": "Feature",
  "properties": {
    "iso:country":"GB",
    "wof:name":"BH19 3AU",
    "wof:placetype":"postalcode"
},
  "geometry": {"coordinates":[-1.94846857900219,50.64311287394593],"type":"Point"}
}