{
  "type": "Feature",
  "properties": {
    "date:inception_lower":"2015-11-01",
    "date:inception_upper":"2015-11-30",
    "iso:country":"GB",
    "wof:name":"ME10 4FB",
    "wof:placetype":"postalcode"
},
  "geometry": {"coordinates":[0.742623,51.33857],"type":"Point"}
}