{
  "type": "Feature",
  "properties": {
    "iso:country": "GB",
    "wof:name": "ME10 4FB",
    "wof:placetype": "postalcode"
  },
  "geometry": {"coordinates":[0.742623,51.33857],"type":"Point"}
}
