{
  "type": "Feature",
  "properties": {
    "iso:country":"GB",
    "wof:name":"ME10 4FB",
    "wof:placetype":"postalcode"
},
  "geometry": {"coordinates":[0.74262317104323,51.33856952622418],"type":"Point"}
}