{
  "type": "Feature",
  "properties": {
    "iso:country":"GB",
    "wof:name":"NE8 1DD",
    "wof:placetype":"postalcode"
},
  "geometry": {"coordinates":[-1.60413718620069,54.96266989512833],"type":"Point"}
}