{
  "type": "Feature",
  "properties": {
    "iso:country":"GB",
    "wof:name":"RH6 9BA",
    "wof:placetype":"postalcode"
},
  "geometry": {"coordinates":[-0.15340204767415,51.17053259575338],"type":"Point"}
}