{
  "type": "Feature",
  "properties": {
    "iso:country":"GB",
    "wof:name":"DY8 3AA",
    "wof:placetype":"postalcode"
},
  "geometry": {"coordinates":[-2.16295747233663,52.44166914996289],"type":"Point"}
}