{
  "type": "Feature",
  "properties": {
    "iso:country": "GB",
    "wof:name": "LN5 9PS",
    "wof:placetype": "postalcode"
  },
  "geometry": {"coordinates":[-0.559606,53.186307],"type":"Point"}
}
