{
  "type": "Feature",
  "properties": {
    "iso:country":"GB",
    "wof:name":"E14 3WW",
    "wof:placetype":"postalcode"
},
  "geometry": {"coordinates":[-0.01743389132023,51.48700650032678],"type":"Point"}
}