{
  "type": "Feature",
  "properties": {
    "iso:country":"GB",
    "wof:name":"SL0 0EE",
    "wof:placetype":"postalcode"
},
  "geometry": {"coordinates":[-0.49444396346252,51.54273899907127],"type":"Point"}
}