{
  "type": "Feature",
  "properties": {
    "iso:country":"GB",
    "wof:name":"CH2 1SE",
    "wof:placetype":"postalcode"
},
  "geometry": {"coordinates":[-2.87599099826317,53.21235219915975],"type":"Point"}
}