{
  "type": "Feature",
  "properties": {
    "date:inception_lower":"1980-01-01",
    "date:inception_upper":"1980-01-31",
    "iso:country":"GB",
    "wof:name":"CH2 1SE",
    "wof:placetype":"postalcode"
},
  "geometry": {"coordinates":[-2.875991,53.212352],"type":"Point"}
}