{
  "type": "Feature",
  "properties": {
    "iso:country": "GB",
    "wof:name": "CH2 1SE",
    "wof:placetype": "postalcode"
  },
  "geometry": {"coordinates":[-2.875991,53.212352],"type":"Point"}
}
