{
  "type": "Feature",
  "properties": {
    "iso:country":"GB",
    "wof:name":"TN30 6NP",
    "wof:placetype":"postalcode"
},
  "geometry": {"coordinates":[0.6959156833909,51.07857518129909],"type":"Point"}
}