{
  "type": "Feature",
  "properties": {
    "iso:country": "GB",
    "wof:name": "DE23 8GX",
    "wof:placetype": "postalcode"
  },
  "geometry": {"coordinates":[-1.469359,52.909597],"type":"Point"}
}
