{
  "type": "Feature",
  "properties": {
    "iso:country":"GB",
    "wof:name":"DE23 8GX",
    "wof:placetype":"postalcode"
},
  "geometry": {"coordinates":[-1.46935856461948,52.9095974034131],"type":"Point"}
}