{
  "type": "Feature",
  "properties": {
    "date:inception_lower": "2009-04-01",
    "date:inception_upper": "2009-04-01",
    "iso:country": "GB",
    "wof:name": "CW1 3ET",
    "wof:placetype": "postalcode"
  },
  "geometry": {"coordinates":[-2.448241,53.103687],"type":"Point"}
}
