{
  "type": "Feature",
  "properties": {
    "iso:country":"GB",
    "wof:name":"CW1 3ET",
    "wof:placetype":"postalcode"
},
  "geometry": {"coordinates":[-2.44871641882818,53.10348000254529],"type":"Point"}
}