{
  "type": "Feature",
  "properties": {
    "date:inception_lower": "1980-01-01",
    "date:inception_upper": "1980-01-01",
    "iso:country": "GB",
    "wof:name": "TQ8 8ET",
    "wof:placetype": "postalcode"
  },
  "geometry": {"coordinates":[-3.76697,50.237326],"type":"Point"}
}
