{
  "type": "Feature",
  "properties": {
    "iso:country": "GB",
    "wof:name": "CM22 6LR",
    "wof:placetype": "postalcode"
  },
  "geometry": {"coordinates":[0.229389,51.916337],"type":"Point"}
}
