{
  "type": "Feature",
  "properties": {
    "iso:country":"GB",
    "wof:name":"CM22 6LR",
    "wof:placetype":"postalcode"
},
  "geometry": {"coordinates":[0.22938885335917,51.91633738561658],"type":"Point"}
}