{
  "type": "Feature",
  "properties": {
    "iso:country":"GB",
    "wof:name":"TR7 3AU",
    "wof:placetype":"postalcode"
},
  "geometry": {"coordinates":[-5.0658833387144,50.41944455185975],"type":"Point"}
}