{
  "type": "Feature",
  "properties": {
    "iso:country": "GB",
    "wof:name": "WS15 4QR",
    "wof:placetype": "postalcode"
  },
  "geometry": {"coordinates":[-1.881215,52.728533],"type":"Point"}
}
