{
  "type": "Feature",
  "properties": {
    "date:inception_lower":"2009-05-01",
    "date:inception_upper":"2009-05-31",
    "iso:country":"GB",
    "wof:name":"CB3 0FS",
    "wof:placetype":"postalcode"
},
  "geometry": {"coordinates":[0.086512,52.210421],"type":"Point"}
}