{
  "type": "Feature",
  "properties": {
    "iso:country": "GB",
    "wof:name": "CB3 0FS",
    "wof:placetype": "postalcode"
  },
  "geometry": {"coordinates":[0.086512,52.210421],"type":"Point"}
}
