{
  "type": "Feature",
  "properties": {
    "iso:country":"GB",
    "wof:name":"CB3 0FS",
    "wof:placetype":"postalcode"
},
  "geometry": {"coordinates":[0.08744221141822,52.20962695058101],"type":"Point"}
}