{
  "type": "Feature",
  "properties": {
    "iso:country":"GB",
    "wof:name":"NW2 6PT",
    "wof:placetype":"postalcode"
},
  "geometry": {"coordinates":[-0.22607213173776,51.55898726784567],"type":"Point"}
}