{
  "type": "Feature",
  "properties": {
    "date:inception_lower":"1980-01-01",
    "date:inception_upper":"1980-01-31",
    "iso:country":"GB",
    "wof:name":"NW2 6PT",
    "wof:placetype":"postalcode"
},
  "geometry": {"coordinates":[-0.226118,51.559036],"type":"Point"}
}