{
  "type": "Feature",
  "properties": {
    "iso:country":"GB",
    "wof:name":"DL7 9HU",
    "wof:placetype":"postalcode"
},
  "geometry": {"coordinates":[-1.42554872129703,54.28060949480262],"type":"Point"}
}