{
  "type": "Feature",
  "properties": {
    "date:inception_lower": "1980-01-01",
    "date:inception_upper": "1980-01-01",
    "iso:country": "GB",
    "wof:name": "DL12 9DD",
    "wof:placetype": "postalcode"
  },
  "geometry": {"coordinates":[-1.978599,54.55465],"type":"Point"}
}
