{
  "type": "Feature",
  "properties": {
    "iso:country": "GB",
    "wof:name": "DL12 9DD",
    "wof:placetype": "postalcode"
  },
  "geometry": {"coordinates":[-1.978599,54.55465],"type":"Point"}
}
