{
  "type": "Feature",
  "properties": {
    "iso:country":"GB",
    "wof:name":"DL12 9DD",
    "wof:placetype":"postalcode"
},
  "geometry": {"coordinates":[-1.97859947687506,54.55464976706242],"type":"Point"}
}