{
  "type": "Feature",
  "properties": {
    "iso:country": "GB",
    "wof:name": "PE25 3EJ",
    "wof:placetype": "postalcode"
  },
  "geometry": {"coordinates":[0.342227,53.136865],"type":"Point"}
}
