{
  "type": "Feature",
  "properties": {
    "iso:country":"GB",
    "wof:name":"BA6 9AS",
    "wof:placetype":"postalcode"
},
  "geometry": {"coordinates":[-2.70901154338185,51.15761365625412],"type":"Point"}
}