{
  "type": "Feature",
  "properties": {
    "date:inception_lower": "1980-01-01",
    "date:inception_upper": "1980-01-01",
    "iso:country": "GB",
    "wof:name": "BA6 9AS",
    "wof:placetype": "postalcode"
  },
  "geometry": {"coordinates":[-2.709012,51.157614],"type":"Point"}
}
