{
  "type": "Feature",
  "properties": {
    "date:inception_lower": "1980-01-01",
    "date:inception_upper": "1980-01-01",
    "iso:country": "GB",
    "wof:name": "DY8 4EB",
    "wof:placetype": "postalcode"
  },
  "geometry": {"coordinates":[-2.151909,52.468875],"type":"Point"}
}
