{
  "type": "Feature",
  "properties": {
    "iso:country": "GB",
    "wof:name": "DY8 4EB",
    "wof:placetype": "postalcode"
  },
  "geometry": {"coordinates":[-2.151909,52.468875],"type":"Point"}
}
