{
  "type": "Feature",
  "properties": {
    "iso:country":"GB",
    "wof:name":"DY8 4EB",
    "wof:placetype":"postalcode"
},
  "geometry": {"coordinates":[-2.15198823886044,52.46884258073938],"type":"Point"}
}