{
  "type": "Feature",
  "properties": {
    "date:inception_lower":"1980-01-01",
    "date:inception_upper":"1980-01-31",
    "iso:country":"GB",
    "wof:name":"RM3 8NL",
    "wof:placetype":"postalcode"
},
  "geometry": {"coordinates":[0.224656,51.601156],"type":"Point"}
}