{
  "type": "Feature",
  "properties": {
    "iso:country":"GB",
    "wof:name":"RM3 8NL",
    "wof:placetype":"postalcode"
},
  "geometry": {"coordinates":[0.22460109158017,51.60114589109515],"type":"Point"}
}