{
  "type": "Feature",
  "properties": {
    "iso:country":"GB",
    "wof:name":"M38 9UX",
    "wof:placetype":"postalcode"
},
  "geometry": {"coordinates":[-2.43626429974521,53.53497751452434],"type":"Point"}
}