{
  "type": "Feature",
  "properties": {
    "iso:country":"GB",
    "wof:name":"OX12 9UH",
    "wof:placetype":"postalcode"
},
  "geometry": {"coordinates":[-1.48146099425457,51.58351169986652],"type":"Point"}
}