{
  "type": "Feature",
  "properties": {
    "iso:country": "GB",
    "wof:name": "PE31 7FH",
    "wof:placetype": "postalcode"
  },
  "geometry": {"coordinates":[0.495144,52.872722],"type":"Point"}
}
