{
  "type": "Feature",
  "properties": {
    "iso:country":"GB",
    "wof:name":"DE6 2AY",
    "wof:placetype":"postalcode"
},
  "geometry": {"coordinates":[-1.78784017572841,53.05407800827901],"type":"Point"}
}