{
  "type": "Feature",
  "properties": {
    "date:inception_lower": "1995-12-01",
    "date:inception_upper": "1995-12-01",
    "iso:country": "GB",
    "wof:name": "KY16 9XL",
    "wof:placetype": "postalcode"
  },
  "geometry": {"coordinates":[-2.809947,56.349326],"type":"Point"}
}
