{
  "type": "Feature",
  "properties": {
    "iso:country":"GB",
    "wof:name":"KY16 9XL",
    "wof:placetype":"postalcode"
},
  "geometry": {"coordinates":[-2.80889440710462,56.34565752449002],"type":"Point"}
}