{
  "type": "Feature",
  "properties": {
    "iso:country":"GB",
    "wof:name":"WA5 8GG",
    "wof:placetype":"postalcode"
},
  "geometry": {"coordinates":[-2.63156874751972,53.39964441096126],"type":"Point"}
}