{
  "type": "Feature",
  "properties": {
    "date:inception_lower":"2004-08-01",
    "date:inception_upper":"2004-08-31",
    "iso:country":"GB",
    "wof:name":"WA5 8GG",
    "wof:placetype":"postalcode"
},
  "geometry": {"coordinates":[-2.631569,53.399644],"type":"Point"}
}