{
  "type": "Feature",
  "properties": {
    "iso:country":"GB",
    "wof:name":"AB42 0SF",
    "wof:placetype":"postalcode"
},
  "geometry": {"coordinates":[-1.88706346058193,57.41165780027487],"type":"Point"}
}