{
  "type": "Feature",
  "properties": {
    "iso:country":"GB",
    "wof:name":"NW6 4QP",
    "wof:placetype":"postalcode"
},
  "geometry": {"coordinates":[-0.19194479082513,51.53847625103841],"type":"Point"}
}