{
  "type": "Feature",
  "properties": {
    "iso:country":"GB",
    "wof:name":"BH25 5TN",
    "wof:placetype":"postalcode"
},
  "geometry": {"coordinates":[-1.6644333604856,50.77555416001267],"type":"Point"}
}