{
  "type": "Feature",
  "properties": {
    "iso:country": "GB",
    "wof:name": "LL55 2AY",
    "wof:placetype": "postalcode"
  },
  "geometry": {"coordinates":[-4.277803,53.139677],"type":"Point"}
}
