{
  "type": "Feature",
  "properties": {
    "iso:country":"GB",
    "wof:name":"LL55 2AY",
    "wof:placetype":"postalcode"
},
  "geometry": {"coordinates":[-4.27674051872284,53.13949115724611],"type":"Point"}
}