{
  "type": "Feature",
  "properties": {
    "iso:country": "GB",
    "wof:name": "BS34 6RF",
    "wof:placetype": "postalcode"
  },
  "geometry": {"coordinates":[-2.550119,51.528112],"type":"Point"}
}
