{
  "type": "Feature",
  "properties": {
    "iso:country":"GB",
    "wof:name":"W1D 4PS",
    "wof:placetype":"postalcode"
},
  "geometry": {"coordinates":[-0.13207127982586,51.51351023289427],"type":"Point"}
}