{
  "type": "Feature",
  "properties": {
    "iso:country":"GB",
    "wof:name":"B10 0ER",
    "wof:placetype":"postalcode"
},
  "geometry": {"coordinates":[-1.8519091718991,52.46128761339595],"type":"Point"}
}