{
  "type": "Feature",
  "properties": {
    "iso:country": "GB",
    "wof:name": "LA6 1JY",
    "wof:placetype": "postalcode"
  },
  "geometry": {"coordinates":[-2.737356,54.150605],"type":"Point"}
}
