{
  "type": "Feature",
  "properties": {
    "iso:country":"GB",
    "wof:name":"LA6 1JY",
    "wof:placetype":"postalcode"
},
  "geometry": {"coordinates":[-2.73735565500642,54.15060531835422],"type":"Point"}
}