{
  "type": "Feature",
  "properties": {
    "iso:country":"GB",
    "wof:name":"CB10 1RG",
    "wof:placetype":"postalcode"
},
  "geometry": {"coordinates":[0.19549651247026,52.09859163507726],"type":"Point"}
}