{
  "type": "Feature",
  "properties": {
    "iso:country":"GB",
    "wof:name":"ST5 2HZ",
    "wof:placetype":"postalcode"
},
  "geometry": {"coordinates":[-2.2370505892548,53.0020997489446],"type":"Point"}
}