{
  "type": "Feature",
  "properties": {
    "date:inception_lower": "1980-01-01",
    "date:inception_upper": "1980-01-01",
    "iso:country": "GB",
    "wof:name": "S40 2BG",
    "wof:placetype": "postalcode"
  },
  "geometry": {"coordinates":[-1.445995,53.233353],"type":"Point"}
}
