{
  "type": "Feature",
  "properties": {
    "iso:country":"GB",
    "wof:name":"S40 2BG",
    "wof:placetype":"postalcode"
},
  "geometry": {"coordinates":[-1.44599468679458,53.23335269730593],"type":"Point"}
}