{
  "type": "Feature",
  "properties": {
    "iso:country": "GB",
    "wof:name": "AL2 2JS",
    "wof:placetype": "postalcode"
  },
  "geometry": {"coordinates":[-0.336337,51.720374],"type":"Point"}
}
