{
  "type": "Feature",
  "properties": {
    "iso:country": "GB",
    "wof:name": "KY8 4FZ",
    "wof:placetype": "postalcode"
  },
  "geometry": {"coordinates":[-3.020329,56.197888],"type":"Point"}
}
