{
  "type": "Feature",
  "properties": {
    "date:inception_lower": "2017-10-01",
    "date:inception_upper": "2017-10-01",
    "iso:country": "GB",
    "wof:name": "KY8 4FZ",
    "wof:placetype": "postalcode"
  },
  "geometry": {"coordinates":[-3.020345,56.197879],"type":"Point"}
}
