{
  "type": "Feature",
  "properties": {
    "iso:country": "GB",
    "wof:name": "NP23 5TW",
    "wof:placetype": "postalcode"
  },
  "geometry": {"coordinates":[-3.220092,51.801592],"type":"Point"}
}
