{
  "type": "Feature",
  "properties": {
    "iso:country":"GB",
    "wof:name":"NP23 5TW",
    "wof:placetype":"postalcode"
},
  "geometry": {"coordinates":[-3.22009192320367,51.80159197179496],"type":"Point"}
}