{
  "type": "Feature",
  "properties": {
    "iso:country": "GB",
    "wof:name": "GL14 1EH",
    "wof:placetype": "postalcode"
  },
  "geometry": {"coordinates":[-2.437556,51.771798],"type":"Point"}
}
