{
  "type": "Feature",
  "properties": {
    "date:inception_lower": "1982-03-01",
    "date:inception_upper": "1982-03-01",
    "iso:country": "GB",
    "wof:name": "RG22 4LY",
    "wof:placetype": "postalcode"
  },
  "geometry": {"coordinates":[-1.101198,51.242548],"type":"Point"}
}
