{
  "type": "Feature",
  "properties": {
    "iso:country":"GB",
    "wof:name":"RG22 4LY",
    "wof:placetype":"postalcode"
},
  "geometry": {"coordinates":[-1.10119793957074,51.24254781200114],"type":"Point"}
}