{
  "type": "Feature",
  "properties": {
    "iso:country":"GB",
    "wof:name":"GL20 8JJ",
    "wof:placetype":"postalcode"
},
  "geometry": {"coordinates":[-2.12748415605681,51.99632119932283],"type":"Point"}
}