{
  "type": "Feature",
  "properties": {
    "iso:country": "GB",
    "wof:name": "S2 1QN",
    "wof:placetype": "postalcode"
  },
  "geometry": {"coordinates":[-1.421542,53.370199],"type":"Point"}
}
