{
  "type": "Feature",
  "properties": {
    "iso:country":"GB",
    "wof:name":"BL8 3AA",
    "wof:placetype":"postalcode"
},
  "geometry": {"coordinates":[-2.33213768209039,53.59957896259966],"type":"Point"}
}