{
  "type": "Feature",
  "properties": {
    "iso:country": "GB",
    "wof:name": "EH41 4BF",
    "wof:placetype": "postalcode"
  },
  "geometry": {"coordinates":[-2.768789,55.957295],"type":"Point"}
}
