{
  "type": "Feature",
  "properties": {
    "iso:country":"GB",
    "wof:name":"EH41 4BF",
    "wof:placetype":"postalcode"
},
  "geometry": {"coordinates":[-2.76878939261334,55.95729495572831],"type":"Point"}
}