{
  "type": "Feature",
  "properties": {
    "iso:country":"GB",
    "wof:name":"GU2 8LL",
    "wof:placetype":"postalcode"
},
  "geometry": {"coordinates":[-0.61088065129297,51.24644321365049],"type":"Point"}
}