{
  "type": "Feature",
  "properties": {
    "iso:country": "GB",
    "wof:name": "GU2 8LL",
    "wof:placetype": "postalcode"
  },
  "geometry": {"coordinates":[-0.610881,51.246443],"type":"Point"}
}
