{
  "type": "Feature",
  "properties": {
    "iso:country": "GB",
    "wof:name": "B63 1JT",
    "wof:placetype": "postalcode"
  },
  "geometry": {"coordinates":[-2.079748,52.443999],"type":"Point"}
}
