{
  "type": "Feature",
  "properties": {
    "iso:country":"GB",
    "wof:name":"TS3 7PW",
    "wof:placetype":"postalcode"
},
  "geometry": {"coordinates":[-1.20916442266855,54.55723640626471],"type":"Point"}
}