{
  "type": "Feature",
  "properties": {
    "iso:country":"GB",
    "wof:name":"WN2 4DR",
    "wof:placetype":"postalcode"
},
  "geometry": {"coordinates":[-2.56341996904714,53.53584795007302],"type":"Point"}
}