{
  "type": "Feature",
  "properties": {
    "iso:country":"GB",
    "wof:name":"BL1 7PT",
    "wof:placetype":"postalcode"
},
  "geometry": {"coordinates":[-2.49025388670204,53.60594735266356],"type":"Point"}
}