{
  "type": "Feature",
  "properties": {
    "iso:country":"GB",
    "wof:name":"PL14 5LW",
    "wof:placetype":"postalcode"
},
  "geometry": {"coordinates":[-4.4550855685721,50.51413452188201],"type":"Point"}
}