{
  "type": "Feature",
  "properties": {
    "iso:country":"GB",
    "wof:name":"RG7 5AY",
    "wof:placetype":"postalcode"
},
  "geometry": {"coordinates":[-1.07868707065936,51.43904506778998],"type":"Point"}
}