{
  "type": "Feature",
  "properties": {
    "iso:country":"GB",
    "wof:name":"CR4 3AP",
    "wof:placetype":"postalcode"
},
  "geometry": {"coordinates":[-0.16933178968521,51.40365122773714],"type":"Point"}
}