{
  "type": "Feature",
  "properties": {
    "iso:country":"GB",
    "wof:name":"DE7 5LT",
    "wof:placetype":"postalcode"
},
  "geometry": {"coordinates":[-1.30061724723526,52.97337630223583],"type":"Point"}
}