{
  "type": "Feature",
  "properties": {
    "date:inception_lower": "1980-01-01",
    "date:inception_upper": "1980-01-01",
    "iso:country": "GB",
    "wof:name": "PA2 9BX",
    "wof:placetype": "postalcode"
  },
  "geometry": {"coordinates":[-4.458043,55.832976],"type":"Point"}
}
