{
  "type": "Feature",
  "properties": {
    "iso:country":"GB",
    "wof:name":"L14 9NW",
    "wof:placetype":"postalcode"
},
  "geometry": {"coordinates":[-2.86889462830795,53.42447208582311],"type":"Point"}
}