{
  "type": "Feature",
  "properties": {
    "iso:country": "GB",
    "wof:name": "TA6 6LA",
    "wof:placetype": "postalcode"
  },
  "geometry": {"coordinates":[-3.014002,51.117845],"type":"Point"}
}
