{
  "type": "Feature",
  "properties": {
    "date:inception_lower": "1989-07-01",
    "date:inception_upper": "1989-07-01",
    "iso:country": "GB",
    "wof:name": "G78 3HH",
    "wof:placetype": "postalcode"
  },
  "geometry": {"coordinates":[-4.420999,55.783999],"type":"Point"}
}
