{
  "type": "Feature",
  "properties": {
    "date:inception_lower":"2015-12-01",
    "date:inception_upper":"2015-12-31",
    "iso:country":"GB",
    "wof:name":"SE1 5YL",
    "wof:placetype":"postalcode"
},
  "geometry": {"coordinates":[-0.075656,51.492178],"type":"Point"}
}