{
  "type": "Feature",
  "properties": {
    "iso:country": "GB",
    "wof:name": "SE1 5YL",
    "wof:placetype": "postalcode"
  },
  "geometry": {"coordinates":[-0.075656,51.492178],"type":"Point"}
}
