{
  "type": "Feature",
  "properties": {
    "iso:country":"GB",
    "wof:name":"SE1 5YL",
    "wof:placetype":"postalcode"
},
  "geometry": {"coordinates":[-0.07621705642333,51.4921222517096],"type":"Point"}
}