{
  "type": "Feature",
  "properties": {
    "iso:country":"GB",
    "wof:name":"BD13 1AX",
    "wof:placetype":"postalcode"
},
  "geometry": {"coordinates":[-1.84048503416974,53.76818358360468],"type":"Point"}
}