{
  "type": "Feature",
  "properties": {
    "iso:country":"GB",
    "wof:name":"SE28 0NW",
    "wof:placetype":"postalcode"
},
  "geometry": {"coordinates":[0.08939187647583,51.50286741518942],"type":"Point"}
}