{
  "type": "Feature",
  "properties": {
    "date:inception_lower":"2005-06-01",
    "date:inception_upper":"2005-06-30",
    "iso:country":"GB",
    "wof:name":"SE28 0NW",
    "wof:placetype":"postalcode"
},
  "geometry": {"coordinates":[0.089392,51.502867],"type":"Point"}
}