{
  "type": "Feature",
  "properties": {
    "iso:country":"GB",
    "wof:name":"PL7 2ZW",
    "wof:placetype":"postalcode"
},
  "geometry": {"coordinates":[-4.05482576837812,50.39093607363816],"type":"Point"}
}