{
  "type": "Feature",
  "properties": {
    "iso:country":"GB",
    "wof:name":"N7 9DL",
    "wof:placetype":"postalcode"
},
  "geometry": {"coordinates":[-0.1191718316965,51.54360884598191],"type":"Point"}
}