{
  "type": "Feature",
  "properties": {
    "iso:country": "GB",
    "wof:name": "N7 9DL",
    "wof:placetype": "postalcode"
  },
  "geometry": {"coordinates":[-0.119172,51.543609],"type":"Point"}
}
