{
  "type": "Feature",
  "properties": {
    "iso:country": "GB",
    "wof:name": "NP12 2JJ",
    "wof:placetype": "postalcode"
  },
  "geometry": {"coordinates":[-3.184947,51.656369],"type":"Point"}
}
