{
  "type": "Feature",
  "properties": {
    "iso:country": "GB",
    "wof:name": "NE25 8UL",
    "wof:placetype": "postalcode"
  },
  "geometry": {"coordinates":[-1.458946,55.032968],"type":"Point"}
}
