{
  "type": "Feature",
  "properties": {
    "date:inception_lower": "1980-01-01",
    "date:inception_upper": "1980-01-01",
    "iso:country": "GB",
    "wof:name": "NE25 8UL",
    "wof:placetype": "postalcode"
  },
  "geometry": {"coordinates":[-1.458946,55.032968],"type":"Point"}
}
