{
  "type": "Feature",
  "properties": {
    "iso:country": "GB",
    "wof:name": "WS2 8NN",
    "wof:placetype": "postalcode"
  },
  "geometry": {"coordinates":[-1.990643,52.590133],"type":"Point"}
}
