{
  "type": "Feature",
  "properties": {
    "date:inception_lower":"1980-01-01",
    "date:inception_upper":"1980-01-31",
    "iso:country":"GB",
    "wof:name":"WS2 8NN",
    "wof:placetype":"postalcode"
},
  "geometry": {"coordinates":[-1.990643,52.590133],"type":"Point"}
}