{
  "type": "Feature",
  "properties": {
    "iso:country":"GB",
    "wof:name":"GL7 3NQ",
    "wof:placetype":"postalcode"
},
  "geometry": {"coordinates":[-1.713586779813,51.74554692062886],"type":"Point"}
}