{
  "type": "Feature",
  "properties": {
    "iso:country":"GB",
    "wof:name":"WF11 8BD",
    "wof:placetype":"postalcode"
},
  "geometry": {"coordinates":[-1.23699446104728,53.7076639000058],"type":"Point"}
}