{
  "type": "Feature",
  "properties": {
    "iso:country":"GB",
    "wof:name":"G3 6SG",
    "wof:placetype":"postalcode"
},
  "geometry": {"coordinates":[-4.26172112409791,55.86777730647509],"type":"Point"}
}