{
  "type": "Feature",
  "properties": {
    "iso:country": "GB",
    "wof:name": "G3 6SG",
    "wof:placetype": "postalcode"
  },
  "geometry": {"coordinates":[-4.261721,55.867777],"type":"Point"}
}
