{
  "type": "Feature",
  "properties": {
    "date:inception_lower": "2019-04-01",
    "date:inception_upper": "2019-04-01",
    "iso:country": "GB",
    "wof:name": "DE7 4SJ",
    "wof:placetype": "postalcode"
  },
  "geometry": {"coordinates":[-1.310799,52.958389],"type":"Point"}
}
