{
  "type": "Feature",
  "properties": {
    "date:inception_lower": "1987-04-01",
    "date:inception_upper": "1987-04-01",
    "iso:country": "GB",
    "wof:name": "BS16 2TP",
    "wof:placetype": "postalcode"
  },
  "geometry": {"coordinates":[-2.512442,51.488856],"type":"Point"}
}
