{
  "type": "Feature",
  "properties": {
    "iso:country":"GB",
    "wof:name":"YO12 7NP",
    "wof:placetype":"postalcode"
},
  "geometry": {"coordinates":[-0.41315035382068,54.28664774473142],"type":"Point"}
}