{
  "type": "Feature",
  "properties": {
    "date:inception_lower": "1980-01-01",
    "date:inception_upper": "1980-01-01",
    "iso:country": "GB",
    "wof:name": "YO12 7NP",
    "wof:placetype": "postalcode"
  },
  "geometry": {"coordinates":[-0.41315,54.286648],"type":"Point"}
}
