{
  "type": "Feature",
  "properties": {
    "iso:country": "GB",
    "wof:name": "YO12 7NP",
    "wof:placetype": "postalcode"
  },
  "geometry": {"coordinates":[-0.41315,54.286648],"type":"Point"}
}
