{
  "type": "Feature",
  "properties": {
    "iso:country":"GB",
    "wof:name":"SG12 0QJ",
    "wof:placetype":"postalcode"
},
  "geometry": {"coordinates":[-0.02852786488138,51.81875412342028],"type":"Point"}
}