{
  "type": "Feature",
  "properties": {
    "iso:country":"GB",
    "wof:name":"EH47 7PB",
    "wof:placetype":"postalcode"
},
  "geometry": {"coordinates":[-3.61630344464768,55.87886475635584],"type":"Point"}
}