{
  "type": "Feature",
  "properties": {
    "iso:country": "GB",
    "wof:name": "EH47 7PB",
    "wof:placetype": "postalcode"
  },
  "geometry": {"coordinates":[-3.616303,55.878865],"type":"Point"}
}
