{
  "type": "Feature",
  "properties": {
    "date:inception_lower": "1990-02-01",
    "date:inception_upper": "1990-02-01",
    "iso:country": "GB",
    "wof:name": "B69 3LY",
    "wof:placetype": "postalcode"
  },
  "geometry": {"coordinates":[-2.03485,52.51366],"type":"Point"}
}
