{
  "type": "Feature",
  "properties": {
    "date:inception_lower":"1980-01-01",
    "date:inception_upper":"1980-01-31",
    "iso:country":"GB",
    "wof:name":"OX7 3EY",
    "wof:placetype":"postalcode"
},
  "geometry": {"coordinates":[-1.471151,51.869494],"type":"Point"}
}