{
  "type": "Feature",
  "properties": {
    "date:inception_lower": "2018-08-01",
    "date:inception_upper": "2018-08-01",
    "iso:country": "GB",
    "wof:name": "NN6 9WU",
    "wof:placetype": "postalcode"
  },
  "geometry": {"coordinates":[-0.903016,52.318495],"type":"Point"}
}
