{
  "type": "Feature",
  "properties": {
    "iso:country": "GB",
    "wof:name": "CH46 6DZ",
    "wof:placetype": "postalcode"
  },
  "geometry": {"coordinates":[-3.122829,53.39581],"type":"Point"}
}
