{
  "type": "Feature",
  "properties": {
    "date:inception_lower": "1999-06-01",
    "date:inception_upper": "1999-06-01",
    "iso:country": "GB",
    "wof:name": "CH46 6DZ",
    "wof:placetype": "postalcode"
  },
  "geometry": {"coordinates":[-3.122829,53.39581],"type":"Point"}
}
