{
  "type": "Feature",
  "properties": {
    "iso:country":"GB",
    "wof:name":"CH46 6DZ",
    "wof:placetype":"postalcode"
},
  "geometry": {"coordinates":[-3.12282938905263,53.39580950561658],"type":"Point"}
}