{
  "type": "Feature",
  "properties": {
    "date:inception_lower": "1980-01-01",
    "date:inception_upper": "1980-01-01",
    "iso:country": "GB",
    "wof:name": "E4 6SH",
    "wof:placetype": "postalcode"
  },
  "geometry": {"coordinates":[-0.01812,51.617546],"type":"Point"}
}
