{
  "type": "Feature",
  "properties": {
    "iso:country":"GB",
    "wof:name":"SA67 8BB",
    "wof:placetype":"postalcode"
},
  "geometry": {"coordinates":[-4.8671537830578,51.75779318940614],"type":"Point"}
}