{
  "type": "Feature",
  "properties": {
    "iso:country": "GB",
    "wof:name": "SA67 8BB",
    "wof:placetype": "postalcode"
  },
  "geometry": {"coordinates":[-4.867154,51.757793],"type":"Point"}
}
