{
  "type": "Feature",
  "properties": {
    "date:inception_lower": "1980-01-01",
    "date:inception_upper": "1980-01-01",
    "iso:country": "GB",
    "wof:name": "SA67 8BB",
    "wof:placetype": "postalcode"
  },
  "geometry": {"coordinates":[-4.867154,51.757793],"type":"Point"}
}
