{
  "type": "Feature",
  "properties": {
    "date:inception_lower": "2008-02-01",
    "date:inception_upper": "2008-02-01",
    "iso:country": "GB",
    "wof:name": "BN43 6AN",
    "wof:placetype": "postalcode"
  },
  "geometry": {"coordinates":[-0.250867,50.832688],"type":"Point"}
}
