{
  "type": "Feature",
  "properties": {
    "iso:country":"GB",
    "wof:name":"BN43 6AN",
    "wof:placetype":"postalcode"
},
  "geometry": {"coordinates":[-0.25094025739388,50.8326141118318],"type":"Point"}
}