{
  "type": "Feature",
  "properties": {
    "iso:country": "GB",
    "wof:name": "WA8 7UU",
    "wof:placetype": "postalcode"
  },
  "geometry": {"coordinates":[-2.765242,53.37186],"type":"Point"}
}
