{
  "type": "Feature",
  "properties": {
    "iso:country":"GB",
    "wof:name":"WA8 7UU",
    "wof:placetype":"postalcode"
},
  "geometry": {"coordinates":[-2.76524155698886,53.37185989234771],"type":"Point"}
}