{
  "type": "Feature",
  "properties": {
    "iso:country":"GB",
    "wof:name":"PR4 0ZD",
    "wof:placetype":"postalcode"
},
  "geometry": {"coordinates":[-2.80977487919541,53.7684470398543],"type":"Point"}
}