{
  "type": "Feature",
  "properties": {
    "iso:country": "GB",
    "wof:name": "PR4 0ZD",
    "wof:placetype": "postalcode"
  },
  "geometry": {"coordinates":[-2.809775,53.768447],"type":"Point"}
}
