{
  "type": "Feature",
  "properties": {
    "date:inception_lower":"2007-01-01",
    "date:inception_upper":"2007-01-31",
    "iso:country":"GB",
    "wof:name":"M4 7EF",
    "wof:placetype":"postalcode"
},
  "geometry": {"coordinates":[-2.218414,53.479253],"type":"Point"}
}