{
  "type": "Feature",
  "properties": {
    "iso:country":"GB",
    "wof:name":"W1C 1AX",
    "wof:placetype":"postalcode"
},
  "geometry": {"coordinates":[-0.14904774375877,51.5149573863894],"type":"Point"}
}