{
  "type": "Feature",
  "properties": {
    "iso:country":"GB",
    "wof:name":"DE4 2GU",
    "wof:placetype":"postalcode"
},
  "geometry": {"coordinates":[-1.5991916112446,53.16625236305892],"type":"Point"}
}