{
  "type": "Feature",
  "properties": {
    "iso:country":"GB",
    "wof:name":"SA11 2LB",
    "wof:placetype":"postalcode"
},
  "geometry": {"coordinates":[-3.82129952698204,51.6402994427906],"type":"Point"}
}