{
  "type": "Feature",
  "properties": {
    "date:inception_lower":"1980-01-01",
    "date:inception_upper":"1980-01-31",
    "iso:country":"GB",
    "wof:name":"SA11 2LB",
    "wof:placetype":"postalcode"
},
  "geometry": {"coordinates":[-3.821299,51.640299],"type":"Point"}
}