{
  "type": "Feature",
  "properties": {
    "date:inception_lower": "2022-07-01",
    "date:inception_upper": "2022-07-01",
    "iso:country": "GB",
    "wof:name": "PR3 1TT",
    "wof:placetype": "postalcode"
  },
  "geometry": {"coordinates":[-2.770021,53.887646],"type":"Point"}
}
