{
  "type": "Feature",
  "properties": {
    "iso:country":"GB",
    "wof:name":"SG6 1RX",
    "wof:placetype":"postalcode"
},
  "geometry": {"coordinates":[-0.22151727652578,51.97923414421158],"type":"Point"}
}