{
  "type": "Feature",
  "properties": {
    "iso:country": "GB",
    "wof:name": "WS9 0PH",
    "wof:placetype": "postalcode"
  },
  "geometry": {"coordinates":[-1.888395,52.589568],"type":"Point"}
}
