{
  "type": "Feature",
  "properties": {
    "iso:country":"GB",
    "wof:name":"WS9 0PH",
    "wof:placetype":"postalcode"
},
  "geometry": {"coordinates":[-1.88839466196822,52.58956839994113],"type":"Point"}
}