{
  "type": "Feature",
  "properties": {
    "date:inception_lower":"1980-01-01",
    "date:inception_upper":"1980-01-31",
    "iso:country":"GB",
    "wof:name":"DH8 9JA",
    "wof:placetype":"postalcode"
},
  "geometry": {"coordinates":[-1.856616,54.896129],"type":"Point"}
}