{
  "type": "Feature",
  "properties": {
    "iso:country": "GB",
    "wof:name": "DH8 9JA",
    "wof:placetype": "postalcode"
  },
  "geometry": {"coordinates":[-1.856616,54.896129],"type":"Point"}
}
