{
  "type": "Feature",
  "properties": {
    "iso:country":"GB",
    "wof:name":"DH8 9JA",
    "wof:placetype":"postalcode"
},
  "geometry": {"coordinates":[-1.85661651629015,54.8961286273182],"type":"Point"}
}