{
  "type": "Feature",
  "properties": {
    "iso:country":"GB",
    "wof:name":"PA10 2JZ",
    "wof:placetype":"postalcode"
},
  "geometry": {"coordinates":[-4.5527739375236,55.83997058447903],"type":"Point"}
}