{
  "type": "Feature",
  "properties": {
    "iso:country":"GB",
    "wof:name":"SL6 9QX",
    "wof:placetype":"postalcode"
},
  "geometry": {"coordinates":[-0.69818996243476,51.55143466419614],"type":"Point"}
}