{
  "type": "Feature",
  "properties": {
    "iso:country":"GB",
    "wof:name":"LU3 2BX",
    "wof:placetype":"postalcode"
},
  "geometry": {"coordinates":[-0.43583454979565,51.9149378520583],"type":"Point"}
}