{
  "type": "Feature",
  "properties": {
    "date:inception_lower":"1980-01-01",
    "date:inception_upper":"1980-01-31",
    "iso:country":"GB",
    "wof:name":"CW8 2DZ",
    "wof:placetype":"postalcode"
},
  "geometry": {"coordinates":[-2.607362,53.232119],"type":"Point"}
}