{
  "type": "Feature",
  "properties": {
    "iso:country":"GB",
    "wof:name":"CW8 2DZ",
    "wof:placetype":"postalcode"
},
  "geometry": {"coordinates":[-2.60736196686556,53.23211940007744],"type":"Point"}
}