{
  "type": "Feature",
  "properties": {
    "iso:country": "GB",
    "wof:name": "SY16 2LT",
    "wof:placetype": "postalcode"
  },
  "geometry": {"coordinates":[-3.314397,52.515162],"type":"Point"}
}
