{
  "type": "Feature",
  "properties": {
    "iso:country":"GB",
    "wof:name":"SS1 2YT",
    "wof:placetype":"postalcode"
},
  "geometry": {"coordinates":[0.73209888593273,51.53047426467494],"type":"Point"}
}