{
  "type": "Feature",
  "properties": {
    "iso:country": "GB",
    "wof:name": "NP19 8PA",
    "wof:placetype": "postalcode"
  },
  "geometry": {"coordinates":[-2.973159,51.587363],"type":"Point"}
}
