{
  "type": "Feature",
  "properties": {
    "iso:country":"GB",
    "wof:name":"NP19 8PA",
    "wof:placetype":"postalcode"
},
  "geometry": {"coordinates":[-2.97315923943081,51.58736314043105],"type":"Point"}
}