{
  "type": "Feature",
  "properties": {
    "date:inception_lower": "1980-01-01",
    "date:inception_upper": "1980-01-01",
    "iso:country": "GB",
    "wof:name": "TW18 4PU",
    "wof:placetype": "postalcode"
  },
  "geometry": {"coordinates":[-0.510966,51.433659],"type":"Point"}
}
