{
  "type": "Feature",
  "properties": {
    "iso:country":"GB",
    "wof:name":"TW18 4PU",
    "wof:placetype":"postalcode"
},
  "geometry": {"coordinates":[-0.51096569211863,51.43365910914886],"type":"Point"}
}