{
  "type": "Feature",
  "properties": {
    "date:inception_lower":"1994-05-01",
    "date:inception_upper":"1994-05-31",
    "iso:country":"GB",
    "wof:name":"M25 0AQ",
    "wof:placetype":"postalcode"
},
  "geometry": {"coordinates":[-2.268741,53.524578],"type":"Point"}
}