{
  "type": "Feature",
  "properties": {
    "iso:country":"GB",
    "wof:name":"NP15 1BT",
    "wof:placetype":"postalcode"
},
  "geometry": {"coordinates":[-2.89834732114655,51.70435459668499],"type":"Point"}
}