{
  "type": "Feature",
  "properties": {
    "date:inception_lower": "1999-06-01",
    "date:inception_upper": "1999-06-01",
    "iso:country": "GB",
    "wof:name": "NP15 1BT",
    "wof:placetype": "postalcode"
  },
  "geometry": {"coordinates":[-2.898327,51.704439],"type":"Point"}
}
