{
  "type": "Feature",
  "properties": {
    "iso:country":"GB",
    "wof:name":"MK16 9AH",
    "wof:placetype":"postalcode"
},
  "geometry": {"coordinates":[-0.71497634261898,52.08655116192376],"type":"Point"}
}