{
  "type": "Feature",
  "properties": {
    "iso:country":"GB",
    "wof:name":"DL1 1HF",
    "wof:placetype":"postalcode"
},
  "geometry": {"coordinates":[-1.53908201079613,54.52387518712927],"type":"Point"}
}