{
  "type": "Feature",
  "properties": {
    "date:inception_lower": "1984-02-01",
    "date:inception_upper": "1984-02-01",
    "iso:country": "GB",
    "wof:name": "DL1 1HF",
    "wof:placetype": "postalcode"
  },
  "geometry": {"coordinates":[-1.539091,54.523913],"type":"Point"}
}
