{
  "type": "Feature",
  "properties": {
    "iso:country": "GB",
    "wof:name": "PE32 2NR",
    "wof:placetype": "postalcode"
  },
  "geometry": {"coordinates":[0.793993,52.724526],"type":"Point"}
}
