{
  "type": "Feature",
  "properties": {
    "iso:country":"GB",
    "wof:name":"PE32 2NR",
    "wof:placetype":"postalcode"
},
  "geometry": {"coordinates":[0.79399330781134,52.72452608124912],"type":"Point"}
}