{
  "type": "Feature",
  "properties": {
    "iso:country":"GB",
    "wof:name":"BD21 1EA",
    "wof:placetype":"postalcode"
},
  "geometry": {"coordinates":[-1.91311700287386,53.85994397097917],"type":"Point"}
}