{
  "type": "Feature",
  "properties": {
    "iso:country": "GB",
    "wof:name": "BD21 1EA",
    "wof:placetype": "postalcode"
  },
  "geometry": {"coordinates":[-1.913117,53.859944],"type":"Point"}
}
