{
  "type": "Feature",
  "properties": {
    "iso:country": "GB",
    "wof:name": "WV3 9PN",
    "wof:placetype": "postalcode"
  },
  "geometry": {"coordinates":[-2.145536,52.587598],"type":"Point"}
}
