{
  "type": "Feature",
  "properties": {
    "iso:country":"GB",
    "wof:name":"W4 5BL",
    "wof:placetype":"postalcode"
},
  "geometry": {"coordinates":[-0.26744658538093,51.49898808559338],"type":"Point"}
}