{
  "type": "Feature",
  "properties": {
    "iso:country": "GB",
    "wof:name": "WF11 8ST",
    "wof:placetype": "postalcode"
  },
  "geometry": {"coordinates":[-1.274263,53.709405],"type":"Point"}
}
