{
  "type": "Feature",
  "properties": {
    "iso:country":"GB",
    "wof:name":"WF11 8ST",
    "wof:placetype":"postalcode"
},
  "geometry": {"coordinates":[-1.27426288039417,53.70940540405761],"type":"Point"}
}