{
  "type": "Feature",
  "properties": {
    "date:inception_lower":"1980-01-01",
    "date:inception_upper":"1980-01-31",
    "iso:country":"GB",
    "wof:name":"WF11 8ST",
    "wof:placetype":"postalcode"
},
  "geometry": {"coordinates":[-1.274263,53.709405],"type":"Point"}
}