{
  "type": "Feature",
  "properties": {
    "iso:country":"GB",
    "wof:name":"YO7 2LE",
    "wof:placetype":"postalcode"
},
  "geometry": {"coordinates":[-1.30109216542698,54.32524924836411],"type":"Point"}
}