{
  "type": "Feature",
  "properties": {
    "iso:country":"GB",
    "wof:name":"M15 4LY",
    "wof:placetype":"postalcode"
},
  "geometry": {"coordinates":[-2.26389828167455,53.4711163469911],"type":"Point"}
}