{
  "type": "Feature",
  "properties": {
    "date:inception_lower":"2005-06-01",
    "date:inception_upper":"2005-06-30",
    "iso:country":"GB",
    "wof:name":"CA22 2WB",
    "wof:placetype":"postalcode"
},
  "geometry": {"coordinates":[-3.545409,54.506228],"type":"Point"}
}