{
  "type": "Feature",
  "properties": {
    "iso:country":"GB",
    "wof:name":"SN15 4NB",
    "wof:placetype":"postalcode"
},
  "geometry": {"coordinates":[-2.04531042862035,51.49398670985911],"type":"Point"}
}