{
  "type": "Feature",
  "properties": {
    "iso:country": "GB",
    "wof:name": "SN15 4NB",
    "wof:placetype": "postalcode"
  },
  "geometry": {"coordinates":[-2.04531,51.493987],"type":"Point"}
}
