{
  "type": "Feature",
  "properties": {
    "date:inception_lower":"2001-12-01",
    "date:inception_upper":"2001-12-31",
    "iso:country":"GB",
    "wof:name":"G81 5EQ",
    "wof:placetype":"postalcode"
},
  "geometry": {"coordinates":[-4.391011,55.929595],"type":"Point"}
}