{
  "type": "Feature",
  "properties": {
    "date:inception_lower": "1989-10-01",
    "date:inception_upper": "1989-10-01",
    "iso:country": "GB",
    "wof:name": "DD4 0LU",
    "wof:placetype": "postalcode"
  },
  "geometry": {"coordinates":[-2.914328,56.490752],"type":"Point"}
}
