{
  "type": "Feature",
  "properties": {
    "iso:country":"GB",
    "wof:name":"NG11 9FP",
    "wof:placetype":"postalcode"
},
  "geometry": {"coordinates":[-1.18382912649612,52.89629318129895],"type":"Point"}
}