{
  "type": "Feature",
  "properties": {
    "iso:country": "GB",
    "wof:name": "TN22 3BB",
    "wof:placetype": "postalcode"
  },
  "geometry": {"coordinates":[0.0895,51.008402],"type":"Point"}
}
