{
  "type": "Feature",
  "properties": {
    "iso:country": "GB",
    "wof:name": "PE37 9AW",
    "wof:placetype": "postalcode"
  },
  "geometry": {"coordinates":[0.685498,52.648662],"type":"Point"}
}
