{
  "type": "Feature",
  "properties": {
    "iso:country": "GB",
    "wof:name": "OL11 1JZ",
    "wof:placetype": "postalcode"
  },
  "geometry": {"coordinates":[-2.151673,53.608859],"type":"Point"}
}
