{
  "type": "Feature",
  "properties": {
    "iso:country":"GB",
    "wof:name":"SP7 9AL",
    "wof:placetype":"postalcode"
},
  "geometry": {"coordinates":[-2.17818334728942,51.04080632945701],"type":"Point"}
}