{
  "type": "Feature",
  "properties": {
    "iso:country": "GB",
    "wof:name": "NG34 9WH",
    "wof:placetype": "postalcode"
  },
  "geometry": {"coordinates":[-0.293185,52.98622],"type":"Point"}
}
