{
  "type": "Feature",
  "properties": {
    "date:inception_lower": "2016-06-01",
    "date:inception_upper": "2016-06-01",
    "iso:country": "GB",
    "wof:name": "NG34 9WH",
    "wof:placetype": "postalcode"
  },
  "geometry": {"coordinates":[-0.2932,52.986211],"type":"Point"}
}
