{
  "type": "Feature",
  "properties": {
    "iso:country":"GB",
    "wof:name":"SK11 0HN",
    "wof:placetype":"postalcode"
},
  "geometry": {"coordinates":[-2.10831084913595,53.23577593023288],"type":"Point"}
}