{
  "type": "Feature",
  "properties": {
    "iso:country": "GB",
    "wof:name": "SS15 6LQ",
    "wof:placetype": "postalcode"
  },
  "geometry": {"coordinates":[0.408202,51.573861],"type":"Point"}
}
