{
  "type": "Feature",
  "properties": {
    "iso:country":"GB",
    "wof:name":"KT24 6JF",
    "wof:placetype":"postalcode"
},
  "geometry": {"coordinates":[-0.45742352782235,51.26975461722525],"type":"Point"}
}