{
  "type": "Feature",
  "properties": {
    "date:inception_lower": "1980-01-01",
    "date:inception_upper": "1980-01-01",
    "iso:country": "GB",
    "wof:name": "KT24 6JF",
    "wof:placetype": "postalcode"
  },
  "geometry": {"coordinates":[-0.457423,51.269755],"type":"Point"}
}
