{
  "type": "Feature",
  "properties": {
    "date:inception_lower":"2004-02-01",
    "date:inception_upper":"2004-02-29",
    "iso:country":"GB",
    "wof:name":"HX4 0FD",
    "wof:placetype":"postalcode"
},
  "geometry": {"coordinates":[-1.932965,53.674166],"type":"Point"}
}