{
  "type": "Feature",
  "properties": {
    "iso:country":"GB",
    "wof:name":"HX4 0FD",
    "wof:placetype":"postalcode"
},
  "geometry": {"coordinates":[-1.93296502031279,53.67416563336113],"type":"Point"}
}