{
  "type": "Feature",
  "properties": {
    "date:inception_lower":"2002-06-01",
    "date:inception_upper":"2002-06-30",
    "iso:country":"GB",
    "wof:name":"WF2 9UE",
    "wof:placetype":"postalcode"
},
  "geometry": {"coordinates":[-1.533365,53.688403],"type":"Point"}
}