{
  "type": "Feature",
  "properties": {
    "iso:country":"GB",
    "wof:name":"WF2 9UE",
    "wof:placetype":"postalcode"
},
  "geometry": {"coordinates":[-1.53336517210683,53.68840340476977],"type":"Point"}
}