{
  "type": "Feature",
  "properties": {
    "date:inception_lower": "2023-08-01",
    "date:inception_upper": "2023-08-01",
    "iso:country": "GB",
    "wof:name": "LE67 9AL",
    "wof:placetype": "postalcode"
  },
  "geometry": {"coordinates":[-1.309049,52.689993],"type":"Point"}
}
