{
  "type": "Feature",
  "properties": {
    "iso:country":"GB",
    "wof:name":"CF14 2SA",
    "wof:placetype":"postalcode"
},
  "geometry": {"coordinates":[-3.20645928074731,51.50222858749697],"type":"Point"}
}