{
  "type": "Feature",
  "properties": {
    "date:inception_lower": "2002-06-01",
    "date:inception_upper": "2002-06-01",
    "iso:country": "GB",
    "wof:name": "GU21 6ND",
    "wof:placetype": "postalcode"
  },
  "geometry": {"coordinates":[-0.569373,51.317064],"type":"Point"}
}
