{
  "type": "Feature",
  "properties": {
    "iso:country":"GB",
    "wof:name":"TF2 7PE",
    "wof:placetype":"postalcode"
},
  "geometry": {"coordinates":[-2.43469260366534,52.71467874964743],"type":"Point"}
}