{
  "type": "Feature",
  "properties": {
    "iso:country": "GB",
    "wof:name": "TF2 7PE",
    "wof:placetype": "postalcode"
  },
  "geometry": {"coordinates":[-2.434693,52.714679],"type":"Point"}
}
