{
  "type": "Feature",
  "properties": {
    "iso:country":"GB",
    "wof:name":"RH1 1AR",
    "wof:placetype":"postalcode"
},
  "geometry": {"coordinates":[-0.16288895470309,51.24277811102184],"type":"Point"}
}