{
  "type": "Feature",
  "properties": {
    "iso:country": "GB",
    "wof:name": "SA40 9TJ",
    "wof:placetype": "postalcode"
  },
  "geometry": {"coordinates":[-4.245544,52.137451],"type":"Point"}
}
