{
  "type": "Feature",
  "properties": {
    "iso:country":"GB",
    "wof:name":"SA40 9TJ",
    "wof:placetype":"postalcode"
},
  "geometry": {"coordinates":[-4.24145084151465,52.14155352576402],"type":"Point"}
}