{
  "type": "Feature",
  "properties": {
    "iso:country":"GB",
    "wof:name":"OX16 5AF",
    "wof:placetype":"postalcode"
},
  "geometry": {"coordinates":[-1.3360572973642,52.05902976398226],"type":"Point"}
}