{
  "type": "Feature",
  "properties": {
    "date:inception_lower": "2004-03-01",
    "date:inception_upper": "2004-03-01",
    "iso:country": "GB",
    "wof:name": "OX16 5AF",
    "wof:placetype": "postalcode"
  },
  "geometry": {"coordinates":[-1.336057,52.05903],"type":"Point"}
}
