{
  "type": "Feature",
  "properties": {
    "date:inception_lower": "1995-07-01",
    "date:inception_upper": "1995-07-01",
    "iso:country": "GB",
    "wof:name": "PO13 9XW",
    "wof:placetype": "postalcode"
  },
  "geometry": {"coordinates":[-1.16702,50.805923],"type":"Point"}
}
