{
  "type": "Feature",
  "properties": {
    "iso:country":"GB",
    "wof:name":"PO13 9XW",
    "wof:placetype":"postalcode"
},
  "geometry": {"coordinates":[-1.16702039430398,50.80592319979453],"type":"Point"}
}