{
  "type": "Feature",
  "properties": {
    "date:inception_lower": "2007-07-01",
    "date:inception_upper": "2007-07-01",
    "iso:country": "GB",
    "wof:name": "SL5 9WX",
    "wof:placetype": "postalcode"
  },
  "geometry": {"coordinates":[-0.65342,51.401787],"type":"Point"}
}
