{
  "type": "Feature",
  "properties": {
    "iso:country":"GB",
    "wof:name":"CR2 7SH",
    "wof:placetype":"postalcode"
},
  "geometry": {"coordinates":[-0.06286003143684,51.34592343270985],"type":"Point"}
}