{
  "type": "Feature",
  "properties": {
    "iso:country":"GB",
    "wof:name":"DY9 9PR",
    "wof:placetype":"postalcode"
},
  "geometry": {"coordinates":[-2.11173836658184,52.41492044047904],"type":"Point"}
}