{
  "type": "Feature",
  "properties": {
    "iso:country":"GB",
    "wof:name":"S70 3LS",
    "wof:placetype":"postalcode"
},
  "geometry": {"coordinates":[-1.45950913728525,53.5384909558224],"type":"Point"}
}