{
  "type": "Feature",
  "properties": {
    "iso:country":"GB",
    "wof:name":"M24 4RF",
    "wof:placetype":"postalcode"
},
  "geometry": {"coordinates":[-2.23354204672157,53.54227797175157],"type":"Point"}
}