{
  "type": "Feature",
  "properties": {
    "iso:country": "GB",
    "wof:name": "L33 4DJ",
    "wof:placetype": "postalcode"
  },
  "geometry": {"coordinates":[-2.879093,53.507328],"type":"Point"}
}
