{
  "type": "Feature",
  "properties": {
    "date:inception_lower":"1980-01-01",
    "date:inception_upper":"1980-01-31",
    "iso:country":"GB",
    "wof:name":"L33 4DJ",
    "wof:placetype":"postalcode"
},
  "geometry": {"coordinates":[-2.879093,53.507328],"type":"Point"}
}