{
  "type": "Feature",
  "properties": {
    "iso:country":"GB",
    "wof:name":"OX18 4EF",
    "wof:placetype":"postalcode"
},
  "geometry": {"coordinates":[-1.59039443716014,51.81490831890289],"type":"Point"}
}