{
  "type": "Feature",
  "properties": {
    "iso:country": "GB",
    "wof:name": "OX18 4EF",
    "wof:placetype": "postalcode"
  },
  "geometry": {"coordinates":[-1.590394,51.814908],"type":"Point"}
}
