{
  "type": "Feature",
  "properties": {
    "date:inception_lower": "2004-10-01",
    "date:inception_upper": "2004-10-01",
    "iso:country": "GB",
    "wof:name": "SN3 3HT",
    "wof:placetype": "postalcode"
  },
  "geometry": {"coordinates":[-1.755631,51.568568],"type":"Point"}
}
