{
  "type": "Feature",
  "properties": {
    "iso:country":"GB",
    "wof:name":"SA5 5JX",
    "wof:placetype":"postalcode"
},
  "geometry": {"coordinates":[-3.9716818353504,51.65174501660978],"type":"Point"}
}