{
  "type": "Feature",
  "properties": {
    "iso:country": "GB",
    "wof:name": "SA5 5JX",
    "wof:placetype": "postalcode"
  },
  "geometry": {"coordinates":[-3.971557,51.651771],"type":"Point"}
}
