{
  "type": "Feature",
  "properties": {
    "iso:country":"GB",
    "wof:name":"PR3 3XY",
    "wof:placetype":"postalcode"
},
  "geometry": {"coordinates":[-2.508071691695,53.83086514353123],"type":"Point"}
}