{
  "type": "Feature",
  "properties": {
    "date:inception_lower":"1980-01-01",
    "date:inception_upper":"1980-01-31",
    "iso:country":"GB",
    "wof:name":"PR3 3XY",
    "wof:placetype":"postalcode"
},
  "geometry": {"coordinates":[-2.508072,53.830865],"type":"Point"}
}