{
  "type": "Feature",
  "properties": {
    "iso:country":"GB",
    "wof:name":"S14 1TJ",
    "wof:placetype":"postalcode"
},
  "geometry": {"coordinates":[-1.43886880445209,53.34405300151184],"type":"Point"}
}