{
  "type": "Feature",
  "properties": {
    "iso:country": "GB",
    "wof:name": "S14 1TJ",
    "wof:placetype": "postalcode"
  },
  "geometry": {"coordinates":[-1.438869,53.344053],"type":"Point"}
}
