{
  "type": "Feature",
  "properties": {
    "iso:country":"GB",
    "wof:name":"LE67 1EQ",
    "wof:placetype":"postalcode"
},
  "geometry": {"coordinates":[-1.36444566575225,52.69438376766163],"type":"Point"}
}