{
  "type": "Feature",
  "properties": {
    "iso:country":"GB",
    "wof:name":"M14 5BX",
    "wof:placetype":"postalcode"
},
  "geometry": {"coordinates":[-2.21456818819144,53.454703370371],"type":"Point"}
}