{
  "type": "Feature",
  "properties": {
    "iso:country":"GB",
    "wof:name":"YO32 2JL",
    "wof:placetype":"postalcode"
},
  "geometry": {"coordinates":[-1.07999019959426,54.01789505844165],"type":"Point"}
}