{
  "type": "Feature",
  "properties": {
    "iso:country": "GB",
    "wof:name": "YO32 2JL",
    "wof:placetype": "postalcode"
  },
  "geometry": {"coordinates":[-1.08003,54.017903],"type":"Point"}
}
