{
  "type": "Feature",
  "properties": {
    "iso:country":"GB",
    "wof:name":"B29 4HU",
    "wof:placetype":"postalcode"
},
  "geometry": {"coordinates":[-1.97023478270517,52.42619837673367],"type":"Point"}
}