{
  "type": "Feature",
  "properties": {
    "iso:country":"GB",
    "wof:name":"WR7 4JR",
    "wof:placetype":"postalcode"
},
  "geometry": {"coordinates":[-1.98991493261143,52.21251349408828],"type":"Point"}
}