{
  "type": "Feature",
  "properties": {
    "date:inception_lower":"2014-03-01",
    "date:inception_upper":"2014-03-31",
    "iso:country":"GB",
    "wof:name":"WR7 4JR",
    "wof:placetype":"postalcode"
},
  "geometry": {"coordinates":[-1.989915,52.212513],"type":"Point"}
}