{
  "type": "Feature",
  "properties": {
    "iso:country": "GB",
    "wof:name": "WR7 4JR",
    "wof:placetype": "postalcode"
  },
  "geometry": {"coordinates":[-1.989915,52.212513],"type":"Point"}
}
