{
  "type": "Feature",
  "properties": {
    "date:inception_lower": "1984-02-01",
    "date:inception_upper": "1984-02-01",
    "iso:country": "GB",
    "wof:name": "LN12 2SP",
    "wof:placetype": "postalcode"
  },
  "geometry": {"coordinates":[0.279724,53.310702],"type":"Point"}
}
