{
  "type": "Feature",
  "properties": {
    "date:inception_lower":"1980-01-01",
    "date:inception_upper":"1980-01-31",
    "iso:country":"GB",
    "wof:name":"WD4 9BH",
    "wof:placetype":"postalcode"
},
  "geometry": {"coordinates":[-0.492139,51.70479],"type":"Point"}
}