{
  "type": "Feature",
  "properties": {
    "iso:country":"GB",
    "wof:name":"WD4 9BH",
    "wof:placetype":"postalcode"
},
  "geometry": {"coordinates":[-0.49213909253212,51.70478990217435],"type":"Point"}
}