{
  "type": "Feature",
  "properties": {
    "iso:country":"GB",
    "wof:name":"GL54 2PU",
    "wof:placetype":"postalcode"
},
  "geometry": {"coordinates":[-1.76078039592457,51.88188394772342],"type":"Point"}
}