{
  "type": "Feature",
  "properties": {
    "date:inception_lower": "1987-04-01",
    "date:inception_upper": "1987-04-01",
    "iso:country": "GB",
    "wof:name": "GL54 2PU",
    "wof:placetype": "postalcode"
  },
  "geometry": {"coordinates":[-1.76078,51.881884],"type":"Point"}
}
