{
  "type": "Feature",
  "properties": {
    "iso:country":"GB",
    "wof:name":"WD3 3QA",
    "wof:placetype":"postalcode"
},
  "geometry": {"coordinates":[-0.44565643041245,51.64980083637767],"type":"Point"}
}