{
  "type": "Feature",
  "properties": {
    "iso:country":"GB",
    "wof:name":"DE14 3QW",
    "wof:placetype":"postalcode"
},
  "geometry": {"coordinates":[-1.63482755767162,52.80140375884854],"type":"Point"}
}