{
  "type": "Feature",
  "properties": {
    "iso:country": "GB",
    "wof:name": "DE14 3QW",
    "wof:placetype": "postalcode"
  },
  "geometry": {"coordinates":[-1.634601,52.801268],"type":"Point"}
}
