{
  "type": "Feature",
  "properties": {
    "iso:country":"GB",
    "wof:name":"ST5 0RX",
    "wof:placetype":"postalcode"
},
  "geometry": {"coordinates":[-2.21888786036513,53.02304340042175],"type":"Point"}
}