{
  "type": "Feature",
  "properties": {
    "iso:country": "GB",
    "wof:name": "BS1 6WF",
    "wof:placetype": "postalcode"
  },
  "geometry": {"coordinates":[-2.588985,51.454551],"type":"Point"}
}
