{
  "type": "Feature",
  "properties": {
    "iso:country":"GB",
    "wof:name":"DN16 3FB",
    "wof:placetype":"postalcode"
},
  "geometry": {"coordinates":[-0.63061229050936,53.55871454482595],"type":"Point"}
}