{
  "type": "Feature",
  "properties": {
    "iso:country": "GB",
    "wof:name": "DN16 3FB",
    "wof:placetype": "postalcode"
  },
  "geometry": {"coordinates":[-0.630612,53.558715],"type":"Point"}
}
