{
  "type": "Feature",
  "properties": {
    "date:inception_lower":"2003-08-01",
    "date:inception_upper":"2003-08-31",
    "iso:country":"GB",
    "wof:name":"DN16 3FB",
    "wof:placetype":"postalcode"
},
  "geometry": {"coordinates":[-0.630612,53.558715],"type":"Point"}
}