{
  "type": "Feature",
  "properties": {
    "iso:country":"GB",
    "wof:name":"TD1 2SS",
    "wof:placetype":"postalcode"
},
  "geometry": {"coordinates":[-2.86854311931597,55.69103516541045],"type":"Point"}
}