{
  "type": "Feature",
  "properties": {
    "date:inception_lower": "1980-01-01",
    "date:inception_upper": "1980-01-01",
    "iso:country": "GB",
    "wof:name": "TD1 2SS",
    "wof:placetype": "postalcode"
  },
  "geometry": {"coordinates":[-2.868543,55.691035],"type":"Point"}
}
