{
  "type": "Feature",
  "properties": {
    "iso:country": "GB",
    "wof:name": "SA70 8EF",
    "wof:placetype": "postalcode"
  },
  "geometry": {"coordinates":[-4.716868,51.672996],"type":"Point"}
}
