{
  "type": "Feature",
  "properties": {
    "iso:country":"GB",
    "wof:name":"N15 6JR",
    "wof:placetype":"postalcode"
},
  "geometry": {"coordinates":[-0.07272639902798,51.57893301667222],"type":"Point"}
}