{
  "type": "Feature",
  "properties": {
    "iso:country":"GB",
    "wof:name":"CV35 8PW",
    "wof:placetype":"postalcode"
},
  "geometry": {"coordinates":[-1.73646938697915,52.27477508909769],"type":"Point"}
}