{
  "type": "Feature",
  "properties": {
    "iso:country": "GB",
    "wof:name": "CV35 8PW",
    "wof:placetype": "postalcode"
  },
  "geometry": {"coordinates":[-1.736469,52.274775],"type":"Point"}
}
