{
  "type": "Feature",
  "properties": {
    "iso:country":"GB",
    "wof:name":"SE13 7EA",
    "wof:placetype":"postalcode"
},
  "geometry": {"coordinates":[-0.00481835522669,51.46715242453868],"type":"Point"}
}