{
  "type": "Feature",
  "properties": {
    "date:inception_lower": "1980-01-01",
    "date:inception_upper": "1980-01-01",
    "iso:country": "GB",
    "wof:name": "KT16 0LG",
    "wof:placetype": "postalcode"
  },
  "geometry": {"coordinates":[-0.530185,51.360111],"type":"Point"}
}
