{
  "type": "Feature",
  "properties": {
    "iso:country": "GB",
    "wof:name": "GU23 7DY",
    "wof:placetype": "postalcode"
  },
  "geometry": {"coordinates":[-0.541196,51.294272],"type":"Point"}
}
