{
  "type": "Feature",
  "properties": {
    "iso:country":"GB",
    "wof:name":"GU23 7DY",
    "wof:placetype":"postalcode"
},
  "geometry": {"coordinates":[-0.54119556263742,51.29427166152546],"type":"Point"}
}