{
  "type": "Feature",
  "properties": {
    "date:inception_lower":"2004-09-01",
    "date:inception_upper":"2004-09-30",
    "iso:country":"GB",
    "wof:name":"GU23 7DY",
    "wof:placetype":"postalcode"
},
  "geometry": {"coordinates":[-0.541196,51.294272],"type":"Point"}
}