{
  "type": "Feature",
  "properties": {
    "date:inception_lower": "1980-01-01",
    "date:inception_upper": "1980-01-01",
    "iso:country": "GB",
    "wof:name": "PL14 5QN",
    "wof:placetype": "postalcode"
  },
  "geometry": {"coordinates":[-4.416174,50.499243],"type":"Point"}
}
