{
  "type": "Feature",
  "properties": {
    "date:inception_lower":"1980-01-01",
    "date:inception_upper":"1980-01-31",
    "iso:country":"GB",
    "wof:name":"SE2 9UZ",
    "wof:placetype":"postalcode"
},
  "geometry": {"coordinates":[0.126387,51.499298],"type":"Point"}
}