{
  "type": "Feature",
  "properties": {
    "iso:country":"GB",
    "wof:name":"SE2 9UZ",
    "wof:placetype":"postalcode"
},
  "geometry": {"coordinates":[0.12638713600428,51.49929771520347],"type":"Point"}
}