{
  "type": "Feature",
  "properties": {
    "iso:country": "GB",
    "wof:name": "HX2 9NL",
    "wof:placetype": "postalcode"
  },
  "geometry": {"coordinates":[-1.894344,53.761394],"type":"Point"}
}
