{
  "type": "Feature",
  "properties": {
    "iso:country":"GB",
    "wof:name":"HX2 9NL",
    "wof:placetype":"postalcode"
},
  "geometry": {"coordinates":[-1.8943440383923,53.76139416220909],"type":"Point"}
}