{
  "type": "Feature",
  "properties": {
    "iso:country":"GB",
    "wof:name":"CO10 2RX",
    "wof:placetype":"postalcode"
},
  "geometry": {"coordinates":[0.74460468015198,52.03941778501024],"type":"Point"}
}