{
  "type": "Feature",
  "properties": {
    "date:inception_lower": "2006-09-01",
    "date:inception_upper": "2006-09-01",
    "iso:country": "GB",
    "wof:name": "CB21 5EU",
    "wof:placetype": "postalcode"
  },
  "geometry": {"coordinates":[0.239084,52.189578],"type":"Point"}
}
