{
  "type": "Feature",
  "properties": {
    "iso:country":"GB",
    "wof:name":"CB21 5EU",
    "wof:placetype":"postalcode"
},
  "geometry": {"coordinates":[0.23905740160587,52.19077804604866],"type":"Point"}
}