{
  "type": "Feature",
  "properties": {
    "iso:country":"GB",
    "wof:name":"B43 5SB",
    "wof:placetype":"postalcode"
},
  "geometry": {"coordinates":[-1.94029699843799,52.54342507914046],"type":"Point"}
}