{
  "type": "Feature",
  "properties": {
    "date:inception_lower":"2008-09-01",
    "date:inception_upper":"2008-09-30",
    "iso:country":"GB",
    "wof:name":"SK15 3AT",
    "wof:placetype":"postalcode"
},
  "geometry": {"coordinates":[-2.050791,53.484538],"type":"Point"}
}