{
  "type": "Feature",
  "properties": {
    "iso:country":"GB",
    "wof:name":"SK15 3AT",
    "wof:placetype":"postalcode"
},
  "geometry": {"coordinates":[-2.05079125367981,53.48453849862366],"type":"Point"}
}