{
  "type": "Feature",
  "properties": {
    "date:inception_lower": "1985-04-01",
    "date:inception_upper": "1985-04-01",
    "iso:country": "GB",
    "wof:name": "B19 2YF",
    "wof:placetype": "postalcode"
  },
  "geometry": {"coordinates":[-1.901127,52.493604],"type":"Point"}
}
