{
  "type": "Feature",
  "properties": {
    "iso:country":"GB",
    "wof:name":"B19 2YF",
    "wof:placetype":"postalcode"
},
  "geometry": {"coordinates":[-1.90064047249167,52.49385517578155],"type":"Point"}
}