{
  "type": "Feature",
  "properties": {
    "iso:country":"GB",
    "wof:name":"CW4 7JS",
    "wof:placetype":"postalcode"
},
  "geometry": {"coordinates":[-2.36804884955765,53.19993905822354],"type":"Point"}
}