{
  "type": "Feature",
  "properties": {
    "iso:country": "GB",
    "wof:name": "WF5 8DW",
    "wof:placetype": "postalcode"
  },
  "geometry": {"coordinates":[-1.588136,53.685216],"type":"Point"}
}
