{
  "type": "Feature",
  "properties": {
    "iso:country":"GB",
    "wof:name":"WF5 8DW",
    "wof:placetype":"postalcode"
},
  "geometry": {"coordinates":[-1.5881362615595,53.68521557817102],"type":"Point"}
}