{
  "type": "Feature",
  "properties": {
    "iso:country":"GB",
    "wof:name":"E14 6ED",
    "wof:placetype":"postalcode"
},
  "geometry": {"coordinates":[-0.01750798396939,51.51385087174035],"type":"Point"}
}