{
  "type": "Feature",
  "properties": {
    "date:inception_lower":"1980-01-01",
    "date:inception_upper":"1980-01-31",
    "iso:country":"GB",
    "wof:name":"E14 6ED",
    "wof:placetype":"postalcode"
},
  "geometry": {"coordinates":[-0.017508,51.513851],"type":"Point"}
}