{
  "type": "Feature",
  "properties": {
    "date:inception_lower": "1980-01-01",
    "date:inception_upper": "1980-01-01",
    "iso:country": "GB",
    "wof:name": "B42 1TG",
    "wof:placetype": "postalcode"
  },
  "geometry": {"coordinates":[-1.93164,52.544113],"type":"Point"}
}
