{
  "type": "Feature",
  "properties": {
    "iso:country": "GB",
    "wof:name": "B42 1TG",
    "wof:placetype": "postalcode"
  },
  "geometry": {"coordinates":[-1.93164,52.544113],"type":"Point"}
}
