{
  "type": "Feature",
  "properties": {
    "iso:country":"GB",
    "wof:name":"B42 1TG",
    "wof:placetype":"postalcode"
},
  "geometry": {"coordinates":[-1.93164043529583,52.54411263582324],"type":"Point"}
}