{
  "type": "Feature",
  "properties": {
    "iso:country":"GB",
    "wof:name":"UB4 9BB",
    "wof:placetype":"postalcode"
},
  "geometry": {"coordinates":[-0.3984695461421,51.52723358721943],"type":"Point"}
}