{
  "type": "Feature",
  "properties": {
    "iso:country":"GB",
    "wof:name":"ST3 2LL",
    "wof:placetype":"postalcode"
},
  "geometry": {"coordinates":[-2.14506730355168,52.98920443378758],"type":"Point"}
}