{
  "type": "Feature",
  "properties": {
    "iso:country":"GB",
    "wof:name":"DL11 7HY",
    "wof:placetype":"postalcode"
},
  "geometry": {"coordinates":[-1.8244072057096,54.4705779987335],"type":"Point"}
}