{
  "type": "Feature",
  "properties": {
    "iso:country": "GB",
    "wof:name": "DL11 7HY",
    "wof:placetype": "postalcode"
  },
  "geometry": {"coordinates":[-1.824492,54.47057],"type":"Point"}
}
