{
  "type": "Feature",
  "properties": {
    "iso:country": "GB",
    "wof:name": "BH19 2RB",
    "wof:placetype": "postalcode"
  },
  "geometry": {"coordinates":[-1.966145,50.606168],"type":"Point"}
}
