{
  "type": "Feature",
  "properties": {
    "date:inception_lower":"2001-12-01",
    "date:inception_upper":"2001-12-31",
    "iso:country":"GB",
    "wof:name":"EX2 8NL",
    "wof:placetype":"postalcode"
},
  "geometry": {"coordinates":[-3.517511,50.696795],"type":"Point"}
}