{
  "type": "Feature",
  "properties": {
    "iso:country":"GB",
    "wof:name":"EX2 8NL",
    "wof:placetype":"postalcode"
},
  "geometry": {"coordinates":[-3.51749828949221,50.69684014714868],"type":"Point"}
}