{
  "type": "Feature",
  "properties": {
    "date:inception_lower": "1987-04-01",
    "date:inception_upper": "1987-04-01",
    "iso:country": "GB",
    "wof:name": "ME15 6FE",
    "wof:placetype": "postalcode"
  },
  "geometry": {"coordinates":[0.506156,51.263935],"type":"Point"}
}
