{
  "type": "Feature",
  "properties": {
    "iso:country":"GB",
    "wof:name":"ME15 6FE",
    "wof:placetype":"postalcode"
},
  "geometry": {"coordinates":[0.50615619987559,51.26393457082656],"type":"Point"}
}