{
  "type": "Feature",
  "properties": {
    "iso:country": "GB",
    "wof:name": "E1 2DP",
    "wof:placetype": "postalcode"
  },
  "geometry": {"coordinates":[-0.059113,51.516984],"type":"Point"}
}
