{
  "type": "Feature",
  "properties": {
    "date:inception_lower":"1980-01-01",
    "date:inception_upper":"1980-01-31",
    "iso:country":"GB",
    "wof:name":"SY23 5AS",
    "wof:placetype":"postalcode"
},
  "geometry": {"coordinates":[-4.095734,52.31454],"type":"Point"}
}