{
  "type": "Feature",
  "properties": {
    "iso:country":"GB",
    "wof:name":"SY23 5AS",
    "wof:placetype":"postalcode"
},
  "geometry": {"coordinates":[-4.09573452827678,52.31453969756058],"type":"Point"}
}