{
  "type": "Feature",
  "properties": {
    "iso:country":"GB",
    "wof:name":"DL17 0DT",
    "wof:placetype":"postalcode"
},
  "geometry": {"coordinates":[-1.52983054774163,54.67282363380656],"type":"Point"}
}