{
  "type": "Feature",
  "properties": {
    "iso:country": "GB",
    "wof:name": "CB3 0UF",
    "wof:placetype": "postalcode"
  },
  "geometry": {"coordinates":[0.09825,52.224061],"type":"Point"}
}
