{
  "type": "Feature",
  "properties": {
    "date:inception_lower": "2020-01-01",
    "date:inception_upper": "2020-01-01",
    "iso:country": "GB",
    "wof:name": "CB3 0UF",
    "wof:placetype": "postalcode"
  },
  "geometry": {"coordinates":[0.099012,52.224074],"type":"Point"}
}
