{
  "type": "Feature",
  "properties": {
    "date:inception_lower": "1980-01-01",
    "date:inception_upper": "1980-01-01",
    "iso:country": "GB",
    "wof:name": "SP11 9DX",
    "wof:placetype": "postalcode"
  },
  "geometry": {"coordinates":[-1.554708,51.276901],"type":"Point"}
}
