{
  "type": "Feature",
  "properties": {
    "date:inception_lower": "2016-08-01",
    "date:inception_upper": "2016-08-01",
    "iso:country": "GB",
    "wof:name": "DA2 6FU",
    "wof:placetype": "postalcode"
  },
  "geometry": {"coordinates":[0.247848,51.443335],"type":"Point"}
}
