{
  "type": "Feature",
  "properties": {
    "iso:country":"GB",
    "wof:name":"M18 8JL",
    "wof:placetype":"postalcode"
},
  "geometry": {"coordinates":[-2.17593333735732,53.46362024147204],"type":"Point"}
}