{
  "type": "Feature",
  "properties": {
    "date:inception_lower": "2001-06-01",
    "date:inception_upper": "2001-06-01",
    "iso:country": "GB",
    "wof:name": "OX28 5PB",
    "wof:placetype": "postalcode"
  },
  "geometry": {"coordinates":[-1.506289,51.778729],"type":"Point"}
}
