{
  "type": "Feature",
  "properties": {
    "iso:country": "GB",
    "wof:name": "OX28 5PB",
    "wof:placetype": "postalcode"
  },
  "geometry": {"coordinates":[-1.506289,51.778729],"type":"Point"}
}
