{
  "type": "Feature",
  "properties": {
    "iso:country":"GB",
    "wof:name":"GL4 8AR",
    "wof:placetype":"postalcode"
},
  "geometry": {"coordinates":[-2.20203928909621,51.83396809405076],"type":"Point"}
}