{
  "type": "Feature",
  "properties": {
    "iso:country":"GB",
    "wof:name":"RH17 6AP",
    "wof:placetype":"postalcode"
},
  "geometry": {"coordinates":[-0.19329402536669,51.03764523804525],"type":"Point"}
}