{
  "type": "Feature",
  "properties": {
    "iso:country": "GB",
    "wof:name": "RH17 6AP",
    "wof:placetype": "postalcode"
  },
  "geometry": {"coordinates":[-0.193264,51.037704],"type":"Point"}
}
