{
  "type": "Feature",
  "properties": {
    "date:inception_lower":"1994-12-01",
    "date:inception_upper":"1994-12-31",
    "iso:country":"GB",
    "wof:name":"SO15 2ND",
    "wof:placetype":"postalcode"
},
  "geometry": {"coordinates":[-1.414499,50.914843],"type":"Point"}
}