{
  "type": "Feature",
  "properties": {
    "iso:country":"GB",
    "wof:name":"SL6 7UG",
    "wof:placetype":"postalcode"
},
  "geometry": {"coordinates":[-0.73078777443715,51.53790826247538],"type":"Point"}
}