{
  "type": "Feature",
  "properties": {
    "iso:country": "GB",
    "wof:name": "CB24 1BP",
    "wof:placetype": "postalcode"
  },
  "geometry": {"coordinates":[0.056447,52.286472],"type":"Point"}
}
