{
  "type": "Feature",
  "properties": {
    "date:inception_lower": "2018-12-01",
    "date:inception_upper": "2018-12-01",
    "iso:country": "GB",
    "wof:name": "CM19 5GJ",
    "wof:placetype": "postalcode"
  },
  "geometry": {"coordinates":[0.059332,51.762544],"type":"Point"}
}
