{
  "type": "Feature",
  "properties": {
    "iso:country":"GB",
    "wof:name":"M50 2UG",
    "wof:placetype":"postalcode"
},
  "geometry": {"coordinates":[-2.28942691703569,53.47680981616471],"type":"Point"}
}