{
  "type": "Feature",
  "properties": {
    "date:inception_lower":"2009-03-01",
    "date:inception_upper":"2009-03-31",
    "iso:country":"GB",
    "wof:name":"M50 2UG",
    "wof:placetype":"postalcode"
},
  "geometry": {"coordinates":[-2.289427,53.47681],"type":"Point"}
}