{
  "type": "Feature",
  "properties": {
    "iso:country":"GB",
    "wof:name":"WD25 0NJ",
    "wof:placetype":"postalcode"
},
  "geometry": {"coordinates":[-0.3889923109285,51.69222583184087],"type":"Point"}
}