{
  "type": "Feature",
  "properties": {
    "iso:country":"GB",
    "wof:name":"TN9 2JR",
    "wof:placetype":"postalcode"
},
  "geometry": {"coordinates":[0.27470986380719,51.18388136630359],"type":"Point"}
}