{
  "type": "Feature",
  "properties": {
    "iso:country":"GB",
    "wof:name":"L32 0SS",
    "wof:placetype":"postalcode"
},
  "geometry": {"coordinates":[-2.90233247642098,53.48337935780744],"type":"Point"}
}