{
  "type": "Feature",
  "properties": {
    "date:inception_lower": "1980-01-01",
    "date:inception_upper": "1980-01-01",
    "iso:country": "GB",
    "wof:name": "TR19 6RL",
    "wof:placetype": "postalcode"
  },
  "geometry": {"coordinates":[-5.540779,50.083393],"type":"Point"}
}
