{
  "type": "Feature",
  "properties": {
    "iso:country": "GB",
    "wof:name": "TR19 6RL",
    "wof:placetype": "postalcode"
  },
  "geometry": {"coordinates":[-5.540751,50.083016],"type":"Point"}
}
