{
  "type": "Feature",
  "properties": {
    "iso:country":"GB",
    "wof:name":"TR19 6RL",
    "wof:placetype":"postalcode"
},
  "geometry": {"coordinates":[-5.54066891327567,50.0830362031305],"type":"Point"}
}