{
  "type": "Feature",
  "properties": {
    "iso:country":"GB",
    "wof:name":"LE14 2UN",
    "wof:placetype":"postalcode"
},
  "geometry": {"coordinates":[-0.86980846149225,52.74028129136386],"type":"Point"}
}