{
  "type": "Feature",
  "properties": {
    "iso:country": "GB",
    "wof:name": "GU35 9EN",
    "wof:placetype": "postalcode"
  },
  "geometry": {"coordinates":[-0.880908,51.108309],"type":"Point"}
}
