{
  "type": "Feature",
  "properties": {
    "date:inception_lower": "1980-01-01",
    "date:inception_upper": "1980-01-01",
    "iso:country": "GB",
    "wof:name": "GU35 9EN",
    "wof:placetype": "postalcode"
  },
  "geometry": {"coordinates":[-0.880908,51.108309],"type":"Point"}
}
