{
  "type": "Feature",
  "properties": {
    "iso:country":"GB",
    "wof:name":"GU35 9EN",
    "wof:placetype":"postalcode"
},
  "geometry": {"coordinates":[-0.88090786098665,51.10830924063097],"type":"Point"}
}