{
  "type": "Feature",
  "properties": {
    "iso:country":"GB",
    "wof:name":"PL20 7RS",
    "wof:placetype":"postalcode"
},
  "geometry": {"coordinates":[-4.10173686880106,50.50672575096236],"type":"Point"}
}