{
  "type": "Feature",
  "properties": {
    "date:inception_lower":"1980-01-01",
    "date:inception_upper":"1980-01-31",
    "iso:country":"GB",
    "wof:name":"PL20 7RS",
    "wof:placetype":"postalcode"
},
  "geometry": {"coordinates":[-4.101737,50.506726],"type":"Point"}
}