{
  "type": "Feature",
  "properties": {
    "iso:country":"GB",
    "wof:name":"SY5 0QA",
    "wof:placetype":"postalcode"
},
  "geometry": {"coordinates":[-2.88480457476489,52.64902805648809],"type":"Point"}
}