{
  "type": "Feature",
  "properties": {
    "iso:country":"GB",
    "wof:name":"EN4 9PH",
    "wof:placetype":"postalcode"
},
  "geometry": {"coordinates":[-0.17060475973185,51.65090960804539],"type":"Point"}
}