{
  "type": "Feature",
  "properties": {
    "iso:country":"GB",
    "wof:name":"AB14 0RT",
    "wof:placetype":"postalcode"
},
  "geometry": {"coordinates":[-2.26417978831472,57.09721804743638],"type":"Point"}
}