{
  "type": "Feature",
  "properties": {
    "iso:country":"GB",
    "wof:name":"EX33 2BH",
    "wof:placetype":"postalcode"
},
  "geometry": {"coordinates":[-4.15620580342356,51.101866402699],"type":"Point"}
}