{
  "type": "Feature",
  "properties": {
    "iso:country":"GB",
    "wof:name":"CA4 8DT",
    "wof:placetype":"postalcode"
},
  "geometry": {"coordinates":[-2.86078199528849,54.86471928127146],"type":"Point"}
}