{
  "type": "Feature",
  "properties": {
    "iso:country": "GB",
    "wof:name": "WD3 8JF",
    "wof:placetype": "postalcode"
  },
  "geometry": {"coordinates":[-0.492205,51.63834],"type":"Point"}
}
