{
  "type": "Feature",
  "properties": {
    "iso:country": "GB",
    "wof:name": "WD18 8RJ",
    "wof:placetype": "postalcode"
  },
  "geometry": {"coordinates":[-0.429586,51.642996],"type":"Point"}
}
