{
  "type": "Feature",
  "properties": {
    "iso:country":"GB",
    "wof:name":"WD3 4FR",
    "wof:placetype":"postalcode"
},
  "geometry": {"coordinates":[-0.5060755620363,51.69557143576944],"type":"Point"}
}