{
  "type": "Feature",
  "properties": {
    "date:inception_lower": "2007-07-01",
    "date:inception_upper": "2007-07-01",
    "iso:country": "GB",
    "wof:name": "WD3 4FR",
    "wof:placetype": "postalcode"
  },
  "geometry": {"coordinates":[-0.506054,51.695577],"type":"Point"}
}
