{
  "type": "Feature",
  "properties": {
    "iso:country": "GB",
    "wof:name": "EX2 4QX",
    "wof:placetype": "postalcode"
  },
  "geometry": {"coordinates":[-3.51749,50.714557],"type":"Point"}
}
