{
  "type": "Feature",
  "properties": {
    "iso:country":"GB",
    "wof:name":"EX2 4QX",
    "wof:placetype":"postalcode"
},
  "geometry": {"coordinates":[-3.51748972972152,50.71455708892087],"type":"Point"}
}