{
  "type": "Feature",
  "properties": {
    "date:inception_lower":"2009-08-01",
    "date:inception_upper":"2009-08-31",
    "iso:country":"GB",
    "wof:name":"EX2 4QX",
    "wof:placetype":"postalcode"
},
  "geometry": {"coordinates":[-3.51749,50.714557],"type":"Point"}
}