{
  "type": "Feature",
  "properties": {
    "iso:country": "GB",
    "wof:name": "CM4 0BX",
    "wof:placetype": "postalcode"
  },
  "geometry": {"coordinates":[0.384421,51.671512],"type":"Point"}
}
