{
  "type": "Feature",
  "properties": {
    "iso:country":"GB",
    "wof:name":"DY9 0US",
    "wof:placetype":"postalcode"
},
  "geometry": {"coordinates":[-2.12460288686017,52.44611198064701],"type":"Point"}
}