{
  "type": "Feature",
  "properties": {
    "date:inception_lower": "1980-01-01",
    "date:inception_upper": "1980-01-01",
    "iso:country": "GB",
    "wof:name": "KT6 5AH",
    "wof:placetype": "postalcode"
  },
  "geometry": {"coordinates":[-0.30245,51.377679],"type":"Point"}
}
