{
  "type": "Feature",
  "properties": {
    "iso:country":"GB",
    "wof:name":"SM2 6LZ",
    "wof:placetype":"postalcode"
},
  "geometry": {"coordinates":[-0.20004214359657,51.35785990601567],"type":"Point"}
}