{
  "type": "Feature",
  "properties": {
    "iso:country": "GB",
    "wof:name": "SM2 6LZ",
    "wof:placetype": "postalcode"
  },
  "geometry": {"coordinates":[-0.200003,51.357841],"type":"Point"}
}
