{
  "type": "Feature",
  "properties": {
    "iso:country":"GB",
    "wof:name":"HA5 3NH",
    "wof:placetype":"postalcode"
},
  "geometry": {"coordinates":[-0.39340227049331,51.5970334410347],"type":"Point"}
}