{
  "type": "Feature",
  "properties": {
    "date:inception_lower":"1980-01-01",
    "date:inception_upper":"1980-01-31",
    "iso:country":"GB",
    "wof:name":"DD4 9BH",
    "wof:placetype":"postalcode"
},
  "geometry": {"coordinates":[-2.966898,56.481118],"type":"Point"}
}