{
  "type": "Feature",
  "properties": {
    "iso:country":"GB",
    "wof:name":"DD4 9BH",
    "wof:placetype":"postalcode"
},
  "geometry": {"coordinates":[-2.96689783342303,56.48111765803795],"type":"Point"}
}