{
  "type": "Feature",
  "properties": {
    "iso:country": "GB",
    "wof:name": "LN8 3PL",
    "wof:placetype": "postalcode"
  },
  "geometry": {"coordinates":[-0.40265,53.434108],"type":"Point"}
}
