{
  "type": "Feature",
  "properties": {
    "iso:country":"GB",
    "wof:name":"LN8 3PL",
    "wof:placetype":"postalcode"
},
  "geometry": {"coordinates":[-0.40265046128473,53.43410763832585],"type":"Point"}
}