{
  "type": "Feature",
  "properties": {
    "iso:country":"GB",
    "wof:name":"LA22 0AJ",
    "wof:placetype":"postalcode"
},
  "geometry": {"coordinates":[-2.95737293758565,54.42664802712832],"type":"Point"}
}