{
  "type": "Feature",
  "properties": {
    "iso:country":"GB",
    "wof:name":"B66 4EJ",
    "wof:placetype":"postalcode"
},
  "geometry": {"coordinates":[-1.96852148858661,52.47826802066837],"type":"Point"}
}