{
  "type": "Feature",
  "properties": {
    "iso:country":"GB",
    "wof:name":"SL3 7BB",
    "wof:placetype":"postalcode"
},
  "geometry": {"coordinates":[-0.56953227188884,51.50916693225427],"type":"Point"}
}