{
  "type": "Feature",
  "properties": {
    "iso:country": "GB",
    "wof:name": "SL3 7BB",
    "wof:placetype": "postalcode"
  },
  "geometry": {"coordinates":[-0.569532,51.509167],"type":"Point"}
}
