{
  "type": "Feature",
  "properties": {
    "date:inception_lower": "1980-01-01",
    "date:inception_upper": "1980-01-01",
    "iso:country": "GB",
    "wof:name": "SL3 7BB",
    "wof:placetype": "postalcode"
  },
  "geometry": {"coordinates":[-0.569532,51.509167],"type":"Point"}
}
