{
  "type": "Feature",
  "properties": {
    "iso:country": "GB",
    "wof:name": "SO23 7QL",
    "wof:placetype": "postalcode"
  },
  "geometry": {"coordinates":[-1.29679,51.088187],"type":"Point"}
}
