{
  "type": "Feature",
  "properties": {
    "date:inception_lower": "2019-10-01",
    "date:inception_upper": "2019-10-01",
    "iso:country": "GB",
    "wof:name": "SR3 2GB",
    "wof:placetype": "postalcode"
  },
  "geometry": {"coordinates":[-1.42358,54.860806],"type":"Point"}
}
