{
  "type": "Feature",
  "properties": {
    "iso:country":"GB",
    "wof:name":"CR7 7RT",
    "wof:placetype":"postalcode"
},
  "geometry": {"coordinates":[-0.10409669989433,51.40027584892158],"type":"Point"}
}