{
  "type": "Feature",
  "properties": {
    "iso:country": "GB",
    "wof:name": "CR7 7RT",
    "wof:placetype": "postalcode"
  },
  "geometry": {"coordinates":[-0.104097,51.400276],"type":"Point"}
}
