{
  "type": "Feature",
  "properties": {
    "iso:country":"GB",
    "wof:name":"B71 2HQ",
    "wof:placetype":"postalcode"
},
  "geometry": {"coordinates":[-2.00064951574805,52.54125546029228],"type":"Point"}
}