{
  "type": "Feature",
  "properties": {
    "iso:country": "GB",
    "wof:name": "WN3 4JP",
    "wof:placetype": "postalcode"
  },
  "geometry": {"coordinates":[-2.610378,53.530889],"type":"Point"}
}
