{
  "type": "Feature",
  "properties": {
    "iso:country":"GB",
    "wof:name":"PE6 8ED",
    "wof:placetype":"postalcode"
},
  "geometry": {"coordinates":[-0.31352757303512,52.67459847736338],"type":"Point"}
}