{
  "type": "Feature",
  "properties": {
    "iso:country":"GB",
    "wof:name":"BA1 4AR",
    "wof:placetype":"postalcode"
},
  "geometry": {"coordinates":[-2.38242719949776,51.39400514118662],"type":"Point"}
}