{
  "type": "Feature",
  "properties": {
    "date:inception_lower": "1980-01-01",
    "date:inception_upper": "1980-01-01",
    "iso:country": "GB",
    "wof:name": "BA1 4AR",
    "wof:placetype": "postalcode"
  },
  "geometry": {"coordinates":[-2.382199,51.39424],"type":"Point"}
}
