{
  "type": "Feature",
  "properties": {
    "iso:country":"GB",
    "wof:name":"DY5 3HD",
    "wof:placetype":"postalcode"
},
  "geometry": {"coordinates":[-2.12526569784909,52.48259264757326],"type":"Point"}
}