{
  "type": "Feature",
  "properties": {
    "iso:country":"GB",
    "wof:name":"S81 7DE",
    "wof:placetype":"postalcode"
},
  "geometry": {"coordinates":[-1.13087328475045,53.31682318146444],"type":"Point"}
}