{
  "type": "Feature",
  "properties": {
    "iso:country":"GB",
    "wof:name":"BR1 3DQ",
    "wof:placetype":"postalcode"
},
  "geometry": {"coordinates":[0.02463230090502,51.40126078714374],"type":"Point"}
}