{
  "type": "Feature",
  "properties": {
    "iso:country":"GB",
    "wof:name":"SK9 7TP",
    "wof:placetype":"postalcode"
},
  "geometry": {"coordinates":[-2.27774955815673,53.28979351074672],"type":"Point"}
}