{
  "type": "Feature",
  "properties": {
    "iso:country": "GB",
    "wof:name": "SK9 7TP",
    "wof:placetype": "postalcode"
  },
  "geometry": {"coordinates":[-2.27775,53.289794],"type":"Point"}
}
