{
  "type": "Feature",
  "properties": {
    "date:inception_lower": "1980-01-01",
    "date:inception_upper": "1980-01-01",
    "iso:country": "GB",
    "wof:name": "CH3 6EQ",
    "wof:placetype": "postalcode"
  },
  "geometry": {"coordinates":[-2.831621,53.15434],"type":"Point"}
}
