{
  "type": "Feature",
  "properties": {
    "date:inception_lower": "1992-08-01",
    "date:inception_upper": "1992-08-01",
    "iso:country": "GB",
    "wof:name": "BB4 5AU",
    "wof:placetype": "postalcode"
  },
  "geometry": {"coordinates":[-2.323686,53.715538],"type":"Point"}
}
