{
  "type": "Feature",
  "properties": {
    "iso:country":"GB",
    "wof:name":"BB4 5AU",
    "wof:placetype":"postalcode"
},
  "geometry": {"coordinates":[-2.32362636201322,53.71551425385348],"type":"Point"}
}