{
  "type": "Feature",
  "properties": {
    "iso:country":"GB",
    "wof:name":"W2 3UA",
    "wof:placetype":"postalcode"
},
  "geometry": {"coordinates":[-0.17541576143634,51.51404863839391],"type":"Point"}
}