{
  "type": "Feature",
  "properties": {
    "date:inception_lower": "2017-03-01",
    "date:inception_upper": "2017-03-01",
    "iso:country": "GB",
    "wof:name": "AB15 8FJ",
    "wof:placetype": "postalcode"
  },
  "geometry": {"coordinates":[-2.216164,57.134925],"type":"Point"}
}
