{
  "type": "Feature",
  "properties": {
    "iso:country": "GB",
    "wof:name": "M14 6XY",
    "wof:placetype": "postalcode"
  },
  "geometry": {"coordinates":[-2.217624,53.440054],"type":"Point"}
}
