{
  "type": "Feature",
  "properties": {
    "iso:country":"GB",
    "wof:name":"M14 6XY",
    "wof:placetype":"postalcode"
},
  "geometry": {"coordinates":[-2.2185749172153,53.44025157328967],"type":"Point"}
}