{
  "type": "Feature",
  "properties": {
    "date:inception_lower": "1983-07-01",
    "date:inception_upper": "1983-07-01",
    "iso:country": "GB",
    "wof:name": "DA1 4SZ",
    "wof:placetype": "postalcode"
  },
  "geometry": {"coordinates":[0.184985,51.462536],"type":"Point"}
}
