{
  "type": "Feature",
  "properties": {
    "date:inception_lower": "2001-06-01",
    "date:inception_upper": "2001-06-01",
    "iso:country": "GB",
    "wof:name": "WA5 0AB",
    "wof:placetype": "postalcode"
  },
  "geometry": {"coordinates":[-2.609966,53.397202],"type":"Point"}
}
