{
  "type": "Feature",
  "properties": {
    "iso:country":"GB",
    "wof:name":"WA5 0AB",
    "wof:placetype":"postalcode"
},
  "geometry": {"coordinates":[-2.61002602399729,53.3971497317185],"type":"Point"}
}