{
  "type": "Feature",
  "properties": {
    "iso:country":"GB",
    "wof:name":"SN12 7GF",
    "wof:placetype":"postalcode"
},
  "geometry": {"coordinates":[-2.11948739613002,51.3765405198305],"type":"Point"}
}