{
  "type": "Feature",
  "properties": {
    "date:inception_lower":"2013-08-01",
    "date:inception_upper":"2013-08-31",
    "iso:country":"GB",
    "wof:name":"SN12 7GF",
    "wof:placetype":"postalcode"
},
  "geometry": {"coordinates":[-2.119487,51.376541],"type":"Point"}
}