{
  "type": "Feature",
  "properties": {
    "date:inception_lower": "2000-06-01",
    "date:inception_upper": "2000-06-01",
    "iso:country": "GB",
    "wof:name": "CW5 5SZ",
    "wof:placetype": "postalcode"
  },
  "geometry": {"coordinates":[-2.518366,53.066341],"type":"Point"}
}
