{
  "type": "Feature",
  "properties": {
    "iso:country":"GB",
    "wof:name":"CW5 5SZ",
    "wof:placetype":"postalcode"
},
  "geometry": {"coordinates":[-2.51836572458874,53.06634147357194],"type":"Point"}
}