{
  "type": "Feature",
  "properties": {
    "iso:country":"GB",
    "wof:name":"TA8 1HS",
    "wof:placetype":"postalcode"
},
  "geometry": {"coordinates":[-2.98757701407394,51.23366329323188],"type":"Point"}
}