{
  "type": "Feature",
  "properties": {
    "iso:country": "GB",
    "wof:name": "TA8 1HS",
    "wof:placetype": "postalcode"
  },
  "geometry": {"coordinates":[-2.987657,51.23364],"type":"Point"}
}
