{
  "type": "Feature",
  "properties": {
    "date:inception_lower": "1990-07-01",
    "date:inception_upper": "1990-07-01",
    "iso:country": "GB",
    "wof:name": "TF3 5BT",
    "wof:placetype": "postalcode"
  },
  "geometry": {"coordinates":[-2.470954,52.685225],"type":"Point"}
}
