{
  "type": "Feature",
  "properties": {
    "iso:country":"GB",
    "wof:name":"TF3 5BT",
    "wof:placetype":"postalcode"
},
  "geometry": {"coordinates":[-2.47095377672821,52.68522477957983],"type":"Point"}
}