{
  "type": "Feature",
  "properties": {
    "iso:country": "GB",
    "wof:name": "W2 6QJ",
    "wof:placetype": "postalcode"
  },
  "geometry": {"coordinates":[-0.18221,51.517158],"type":"Point"}
}
