{
  "type": "Feature",
  "properties": {
    "iso:country":"GB",
    "wof:name":"BD2 1LE",
    "wof:placetype":"postalcode"
},
  "geometry": {"coordinates":[-1.75146098370255,53.81707973810199],"type":"Point"}
}