{
  "type": "Feature",
  "properties": {
    "iso:country":"GB",
    "wof:name":"IP28 8AX",
    "wof:placetype":"postalcode"
},
  "geometry": {"coordinates":[0.4988608445205,52.37300653159109],"type":"Point"}
}