{
  "type": "Feature",
  "properties": {
    "iso:country":"GB",
    "wof:name":"PO33 2QW",
    "wof:placetype":"postalcode"
},
  "geometry": {"coordinates":[-1.16594375810838,50.7244408294431],"type":"Point"}
}