{
  "type": "Feature",
  "properties": {
    "iso:country":"GB",
    "wof:name":"M41 0TH",
    "wof:placetype":"postalcode"
},
  "geometry": {"coordinates":[-2.34787819660016,53.4573555224482],"type":"Point"}
}