{
  "type": "Feature",
  "properties": {
    "iso:country": "GB",
    "wof:name": "SP11 6UN",
    "wof:placetype": "postalcode"
  },
  "geometry": {"coordinates":[-1.460362,51.225372],"type":"Point"}
}
