{
  "type": "Feature",
  "properties": {
    "date:inception_lower":"2014-04-01",
    "date:inception_upper":"2014-04-30",
    "iso:country":"GB",
    "wof:name":"SP11 6UN",
    "wof:placetype":"postalcode"
},
  "geometry": {"coordinates":[-1.460362,51.225372],"type":"Point"}
}