{
  "type": "Feature",
  "properties": {
    "iso:country":"GB",
    "wof:name":"CM6 3DU",
    "wof:placetype":"postalcode"
},
  "geometry": {"coordinates":[0.443638491075,51.85774816061794],"type":"Point"}
}