{
  "type": "Feature",
  "properties": {
    "iso:country":"GB",
    "wof:name":"NW9 9AH",
    "wof:placetype":"postalcode"
},
  "geometry": {"coordinates":[-0.26805275733985,51.58973855869337],"type":"Point"}
}