{
  "type": "Feature",
  "properties": {
    "iso:country": "GB",
    "wof:name": "ML1 5JY",
    "wof:placetype": "postalcode"
  },
  "geometry": {"coordinates":[-3.94937,55.811698],"type":"Point"}
}
