{
  "type": "Feature",
  "properties": {
    "iso:country":"GB",
    "wof:name":"MK7 8PU",
    "wof:placetype":"postalcode"
},
  "geometry": {"coordinates":[-0.68026577106018,52.01785262921945],"type":"Point"}
}