{
  "type": "Feature",
  "properties": {
    "date:inception_lower":"1992-08-01",
    "date:inception_upper":"1992-08-31",
    "iso:country":"GB",
    "wof:name":"MK7 8PU",
    "wof:placetype":"postalcode"
},
  "geometry": {"coordinates":[-0.680266,52.017853],"type":"Point"}
}