{
  "type": "Feature",
  "properties": {
    "iso:country": "GB",
    "wof:name": "G44 4EB",
    "wof:placetype": "postalcode"
  },
  "geometry": {"coordinates":[-4.259645,55.819094],"type":"Point"}
}
