{
  "type": "Feature",
  "properties": {
    "iso:country":"GB",
    "wof:name":"G44 4EB",
    "wof:placetype":"postalcode"
},
  "geometry": {"coordinates":[-4.25964502038683,55.81909428248647],"type":"Point"}
}