{
  "type": "Feature",
  "properties": {
    "date:inception_lower": "2002-06-01",
    "date:inception_upper": "2002-06-01",
    "iso:country": "GB",
    "wof:name": "G44 4EB",
    "wof:placetype": "postalcode"
  },
  "geometry": {"coordinates":[-4.259645,55.819094],"type":"Point"}
}
