{
  "type": "Feature",
  "properties": {
    "iso:country":"GB",
    "wof:name":"TR4 9DU",
    "wof:placetype":"postalcode"
},
  "geometry": {"coordinates":[-5.07924851162726,50.28703510228949],"type":"Point"}
}