{
  "type": "Feature",
  "properties": {
    "iso:country": "GB",
    "wof:name": "TR4 9DU",
    "wof:placetype": "postalcode"
  },
  "geometry": {"coordinates":[-5.079248,50.287035],"type":"Point"}
}
