{
  "type": "Feature",
  "properties": {
    "iso:country":"GB",
    "wof:name":"BN1 5LH",
    "wof:placetype":"postalcode"
},
  "geometry": {"coordinates":[-0.17147766228752,50.85714394213993],"type":"Point"}
}