{
  "type": "Feature",
  "properties": {
    "iso:country": "GB",
    "wof:name": "RH12 4RB",
    "wof:placetype": "postalcode"
  },
  "geometry": {"coordinates":[-0.277618,51.121537],"type":"Point"}
}
