{
  "type": "Feature",
  "properties": {
    "iso:country": "GB",
    "wof:name": "LS26 0DZ",
    "wof:placetype": "postalcode"
  },
  "geometry": {"coordinates":[-1.481258,53.746746],"type":"Point"}
}
