{
  "type": "Feature",
  "properties": {
    "date:inception_lower": "1980-01-01",
    "date:inception_upper": "1980-01-01",
    "iso:country": "GB",
    "wof:name": "HA6 2UE",
    "wof:placetype": "postalcode"
  },
  "geometry": {"coordinates":[-0.43777,51.608],"type":"Point"}
}
