{
  "type": "Feature",
  "properties": {
    "date:inception_lower": "1994-05-01",
    "date:inception_upper": "1994-05-01",
    "iso:country": "GB",
    "wof:name": "PL22 0HG",
    "wof:placetype": "postalcode"
  },
  "geometry": {"coordinates":[-4.665742,50.409491],"type":"Point"}
}
