{
  "type": "Feature",
  "properties": {
    "date:inception_lower": "1991-07-01",
    "date:inception_upper": "1991-07-01",
    "iso:country": "GB",
    "wof:name": "KA3 4EW",
    "wof:placetype": "postalcode"
  },
  "geometry": {"coordinates":[-4.510964,55.740223],"type":"Point"}
}
