{
  "type": "Feature",
  "properties": {
    "iso:country": "GB",
    "wof:name": "KA3 4EW",
    "wof:placetype": "postalcode"
  },
  "geometry": {"coordinates":[-4.510886,55.740247],"type":"Point"}
}
