{
  "type": "Feature",
  "properties": {
    "iso:country":"GB",
    "wof:name":"KA3 4EW",
    "wof:placetype":"postalcode"
},
  "geometry": {"coordinates":[-4.51108849362755,55.74017954157221],"type":"Point"}
}