{
  "type": "Feature",
  "properties": {
    "iso:country":"GB",
    "wof:name":"DT1 1PP",
    "wof:placetype":"postalcode"
},
  "geometry": {"coordinates":[-2.433580348341,50.70991537164723],"type":"Point"}
}