{
  "type": "Feature",
  "properties": {
    "iso:country": "GB",
    "wof:name": "DT1 1PP",
    "wof:placetype": "postalcode"
  },
  "geometry": {"coordinates":[-2.43358,50.709915],"type":"Point"}
}
