{
  "type": "Feature",
  "properties": {
    "iso:country":"GB",
    "wof:name":"SE8 3EL",
    "wof:placetype":"postalcode"
},
  "geometry": {"coordinates":[-0.02610789168177,51.48127162494047],"type":"Point"}
}