{
  "type": "Feature",
  "properties": {
    "iso:country":"GB",
    "wof:name":"SA3 4RZ",
    "wof:placetype":"postalcode"
},
  "geometry": {"coordinates":[-4.0237279380257,51.57489003998027],"type":"Point"}
}