{
  "type": "Feature",
  "properties": {
    "date:inception_lower":"1983-07-01",
    "date:inception_upper":"1983-07-31",
    "iso:country":"GB",
    "wof:name":"SA3 4RZ",
    "wof:placetype":"postalcode"
},
  "geometry": {"coordinates":[-4.023747,51.574877],"type":"Point"}
}