{
  "type": "Feature",
  "properties": {
    "iso:country": "GB",
    "wof:name": "SA3 4RZ",
    "wof:placetype": "postalcode"
  },
  "geometry": {"coordinates":[-4.023747,51.574877],"type":"Point"}
}
