{
  "type": "Feature",
  "properties": {
    "iso:country":"GB",
    "wof:name":"LA3 1AX",
    "wof:placetype":"postalcode"
},
  "geometry": {"coordinates":[-2.87721182114801,54.06177545916415],"type":"Point"}
}