{
  "type": "Feature",
  "properties": {
    "iso:country":"GB",
    "wof:name":"UB1 2XU",
    "wof:placetype":"postalcode"
},
  "geometry": {"coordinates":[-0.37444502767996,51.53067989228434],"type":"Point"}
}