{
  "type": "Feature",
  "properties": {
    "date:inception_lower":"1994-05-01",
    "date:inception_upper":"1994-05-31",
    "iso:country":"GB",
    "wof:name":"UB1 2XU",
    "wof:placetype":"postalcode"
},
  "geometry": {"coordinates":[-0.374445,51.53068],"type":"Point"}
}