{
  "type": "Feature",
  "properties": {
    "iso:country":"GB",
    "wof:name":"SL2 3AR",
    "wof:placetype":"postalcode"
},
  "geometry": {"coordinates":[-0.61192758471331,51.53283969918685],"type":"Point"}
}