{
  "type": "Feature",
  "properties": {
    "iso:country":"GB",
    "wof:name":"DE21 4SP",
    "wof:placetype":"postalcode"
},
  "geometry": {"coordinates":[-1.45412199026928,52.93762025678232],"type":"Point"}
}