{
  "type": "Feature",
  "properties": {
    "date:inception_lower": "1980-01-01",
    "date:inception_upper": "1980-01-01",
    "iso:country": "GB",
    "wof:name": "DN5 7PW",
    "wof:placetype": "postalcode"
  },
  "geometry": {"coordinates":[-1.193177,53.515167],"type":"Point"}
}
