{
  "type": "Feature",
  "properties": {
    "iso:country": "GB",
    "wof:name": "DN5 7PW",
    "wof:placetype": "postalcode"
  },
  "geometry": {"coordinates":[-1.193177,53.515167],"type":"Point"}
}
