{
  "type": "Feature",
  "properties": {
    "iso:country":"GB",
    "wof:name":"DN5 7PW",
    "wof:placetype":"postalcode"
},
  "geometry": {"coordinates":[-1.19317716390471,53.51516684355654],"type":"Point"}
}