{
  "type": "Feature",
  "properties": {
    "iso:country":"GB",
    "wof:name":"PE2 8XF",
    "wof:placetype":"postalcode"
},
  "geometry": {"coordinates":[-0.20368944843341,52.55258731587331],"type":"Point"}
}