{
  "type": "Feature",
  "properties": {
    "iso:country": "GB",
    "wof:name": "PE2 8XF",
    "wof:placetype": "postalcode"
  },
  "geometry": {"coordinates":[-0.203689,52.552587],"type":"Point"}
}
