{
  "type": "Feature",
  "properties": {
    "iso:country":"GB",
    "wof:name":"ST3 7TL",
    "wof:placetype":"postalcode"
},
  "geometry": {"coordinates":[-2.09669590956754,52.96840776071674],"type":"Point"}
}