{
  "type": "Feature",
  "properties": {
    "iso:country":"GB",
    "wof:name":"ME10 1PJ",
    "wof:placetype":"postalcode"
},
  "geometry": {"coordinates":[0.71002300396473,51.34724335383522],"type":"Point"}
}