{
  "type": "Feature",
  "properties": {
    "iso:country": "GB",
    "wof:name": "ME10 1PJ",
    "wof:placetype": "postalcode"
  },
  "geometry": {"coordinates":[0.710039,51.347254],"type":"Point"}
}
