{
  "type": "Feature",
  "properties": {
    "date:inception_lower": "2007-05-01",
    "date:inception_upper": "2007-05-01",
    "iso:country": "GB",
    "wof:name": "CF11 6QE",
    "wof:placetype": "postalcode"
  },
  "geometry": {"coordinates":[-3.184077,51.472155],"type":"Point"}
}
