{
  "type": "Feature",
  "properties": {
    "iso:country": "GB",
    "wof:name": "HA2 8RS",
    "wof:placetype": "postalcode"
  },
  "geometry": {"coordinates":[-0.372432,51.561657],"type":"Point"}
}
