{
  "type": "Feature",
  "properties": {
    "iso:country":"GB",
    "wof:name":"HA2 8RS",
    "wof:placetype":"postalcode"
},
  "geometry": {"coordinates":[-0.37243181079011,51.56165712285922],"type":"Point"}
}