{
  "type": "Feature",
  "properties": {
    "iso:country":"GB",
    "wof:name":"DA17 5EQ",
    "wof:placetype":"postalcode"
},
  "geometry": {"coordinates":[0.14583231634594,51.48383543005357],"type":"Point"}
}