{
  "type": "Feature",
  "properties": {
    "iso:country":"GB",
    "wof:name":"SW7 3AQ",
    "wof:placetype":"postalcode"
},
  "geometry": {"coordinates":[-0.1767127905308,51.49166854036769],"type":"Point"}
}