{
  "type": "Feature",
  "properties": {
    "date:inception_lower": "2023-05-01",
    "date:inception_upper": "2023-05-01",
    "iso:country": "GB",
    "wof:name": "NE65 0DF",
    "wof:placetype": "postalcode"
  },
  "geometry": {"coordinates":[-1.572242,55.325429],"type":"Point"}
}
