{
  "type": "Feature",
  "properties": {
    "iso:country":"GB",
    "wof:name":"B28 0RS",
    "wof:placetype":"postalcode"
},
  "geometry": {"coordinates":[-1.85213795619599,52.41926851651387],"type":"Point"}
}