{
  "type": "Feature",
  "properties": {
    "date:inception_lower": "1980-01-01",
    "date:inception_upper": "1980-01-01",
    "iso:country": "GB",
    "wof:name": "B28 0RS",
    "wof:placetype": "postalcode"
  },
  "geometry": {"coordinates":[-1.852138,52.419269],"type":"Point"}
}
