{
  "type": "Feature",
  "properties": {
    "iso:country":"GB",
    "wof:name":"RM11 2AL",
    "wof:placetype":"postalcode"
},
  "geometry": {"coordinates":[0.21304685780524,51.57378327039464],"type":"Point"}
}