{
  "type": "Feature",
  "properties": {
    "date:inception_lower": "1980-01-01",
    "date:inception_upper": "1980-01-01",
    "iso:country": "GB",
    "wof:name": "RM11 2AL",
    "wof:placetype": "postalcode"
  },
  "geometry": {"coordinates":[0.213088,51.573785],"type":"Point"}
}
