{
  "type": "Feature",
  "properties": {
    "iso:country": "GB",
    "wof:name": "RM11 2AL",
    "wof:placetype": "postalcode"
  },
  "geometry": {"coordinates":[0.213088,51.573785],"type":"Point"}
}
