{
  "type": "Feature",
  "properties": {
    "date:inception_lower": "1980-01-01",
    "date:inception_upper": "1980-01-01",
    "iso:country": "GB",
    "wof:name": "LE4 7RJ",
    "wof:placetype": "postalcode"
  },
  "geometry": {"coordinates":[-1.119549,52.660545],"type":"Point"}
}
