{
  "type": "Feature",
  "properties": {
    "iso:country":"GB",
    "wof:name":"GL3 1NG",
    "wof:placetype":"postalcode"
},
  "geometry": {"coordinates":[-2.19011552161831,51.89031609476366],"type":"Point"}
}