{
  "type": "Feature",
  "properties": {
    "date:inception_lower": "1990-02-01",
    "date:inception_upper": "1990-02-01",
    "iso:country": "GB",
    "wof:name": "GL3 1NG",
    "wof:placetype": "postalcode"
  },
  "geometry": {"coordinates":[-2.190115,51.890316],"type":"Point"}
}
