{
  "type": "Feature",
  "properties": {
    "iso:country":"GB",
    "wof:name":"M4 4BU",
    "wof:placetype":"postalcode"
},
  "geometry": {"coordinates":[-2.23464348205367,53.48771619647405],"type":"Point"}
}