{
  "type": "Feature",
  "properties": {
    "date:inception_lower": "2019-02-01",
    "date:inception_upper": "2019-02-01",
    "iso:country": "GB",
    "wof:name": "HD8 9WN",
    "wof:placetype": "postalcode"
  },
  "geometry": {"coordinates":[-1.622388,53.595471],"type":"Point"}
}
