{
  "type": "Feature",
  "properties": {
    "iso:country": "GB",
    "wof:name": "HD8 9WN",
    "wof:placetype": "postalcode"
  },
  "geometry": {"coordinates":[-1.622388,53.595471],"type":"Point"}
}
