{
  "type": "Feature",
  "properties": {
    "date:inception_lower": "2019-02-01",
    "date:inception_upper": "2019-02-01",
    "iso:country": "GB",
    "wof:name": "HD8 9WN",
    "wof:placetype": "postalcode"
  },
  "geometry": {"coordinates":[-1.622496,53.595211],"type":"Point"}
}
