{
  "type": "Feature",
  "properties": {
    "iso:country":"GB",
    "wof:name":"BH22 0BU",
    "wof:placetype":"postalcode"
},
  "geometry": {"coordinates":[-1.86840673237013,50.82078103407024],"type":"Point"}
}