{
  "type": "Feature",
  "properties": {
    "date:inception_lower": "1980-01-01",
    "date:inception_upper": "1980-01-01",
    "iso:country": "GB",
    "wof:name": "CW2 7SA",
    "wof:placetype": "postalcode"
  },
  "geometry": {"coordinates":[-2.46704,53.094915],"type":"Point"}
}
