{
  "type": "Feature",
  "properties": {
    "iso:country":"GB",
    "wof:name":"CW2 7SA",
    "wof:placetype":"postalcode"
},
  "geometry": {"coordinates":[-2.46703999565159,53.0949147870029],"type":"Point"}
}