{
  "type": "Feature",
  "properties": {
    "iso:country": "GB",
    "wof:name": "CW2 7SA",
    "wof:placetype": "postalcode"
  },
  "geometry": {"coordinates":[-2.46704,53.094915],"type":"Point"}
}
