{
  "type": "Feature",
  "properties": {
    "date:inception_lower":"1980-01-01",
    "date:inception_upper":"1980-01-31",
    "iso:country":"GB",
    "wof:name":"YO15 1NN",
    "wof:placetype":"postalcode"
},
  "geometry": {"coordinates":[-0.120616,54.115151],"type":"Point"}
}