{
  "type": "Feature",
  "properties": {
    "iso:country":"GB",
    "wof:name":"YO15 1NN",
    "wof:placetype":"postalcode"
},
  "geometry": {"coordinates":[-0.12061590073734,54.11515147471512],"type":"Point"}
}