{
  "type": "Feature",
  "properties": {
    "iso:country":"GB",
    "wof:name":"TQ3 3JS",
    "wof:placetype":"postalcode"
},
  "geometry": {"coordinates":[-3.57491467621409,50.43298954047604],"type":"Point"}
}