{
  "type": "Feature",
  "properties": {
    "date:inception_lower": "1980-01-01",
    "date:inception_upper": "1980-01-01",
    "iso:country": "GB",
    "wof:name": "SA62 5DJ",
    "wof:placetype": "postalcode"
  },
  "geometry": {"coordinates":[-4.922636,51.917611],"type":"Point"}
}
