{
  "type": "Feature",
  "properties": {
    "iso:country": "GB",
    "wof:name": "TQ14 9LX",
    "wof:placetype": "postalcode"
  },
  "geometry": {"coordinates":[-3.505792,50.56111],"type":"Point"}
}
