{
  "type": "Feature",
  "properties": {
    "iso:country":"GB",
    "wof:name":"TQ14 9LX",
    "wof:placetype":"postalcode"
},
  "geometry": {"coordinates":[-3.50579187095404,50.56111047436893],"type":"Point"}
}