{
  "type": "Feature",
  "properties": {
    "iso:country": "GB",
    "wof:name": "G33 4DA",
    "wof:placetype": "postalcode"
  },
  "geometry": {"coordinates":[-4.14995,55.865409],"type":"Point"}
}
