{
  "type": "Feature",
  "properties": {
    "iso:country":"GB",
    "wof:name":"G33 4DA",
    "wof:placetype":"postalcode"
},
  "geometry": {"coordinates":[-4.15089605909381,55.86552282146266],"type":"Point"}
}