{
  "type": "Feature",
  "properties": {
    "date:inception_lower": "1998-12-01",
    "date:inception_upper": "1998-12-01",
    "iso:country": "GB",
    "wof:name": "M6 7LY",
    "wof:placetype": "postalcode"
  },
  "geometry": {"coordinates":[-2.290578,53.490964],"type":"Point"}
}
