{
  "type": "Feature",
  "properties": {
    "iso:country":"GB",
    "wof:name":"M26 2QN",
    "wof:placetype":"postalcode"
},
  "geometry": {"coordinates":[-2.30186358118425,53.57098650449837],"type":"Point"}
}