{
  "type": "Feature",
  "properties": {
    "iso:country":"GB",
    "wof:name":"CH2 1SW",
    "wof:placetype":"postalcode"
},
  "geometry": {"coordinates":[-2.8738107550836,53.21338398283316],"type":"Point"}
}