{
  "type": "Feature",
  "properties": {
    "date:inception_lower": "2023-01-01",
    "date:inception_upper": "2023-01-01",
    "iso:country": "GB",
    "wof:name": "RG45 6UN",
    "wof:placetype": "postalcode"
  },
  "geometry": {"coordinates":[-0.789564,51.382546],"type":"Point"}
}
