{
  "type": "Feature",
  "properties": {
    "iso:country": "GB",
    "wof:name": "WS2 8SE",
    "wof:placetype": "postalcode"
  },
  "geometry": {"coordinates":[-2.005359,52.589495],"type":"Point"}
}
