{
  "type": "Feature",
  "properties": {
    "iso:country":"GB",
    "wof:name":"WV6 8JU",
    "wof:placetype":"postalcode"
},
  "geometry": {"coordinates":[-2.18262349507932,52.59355191128954],"type":"Point"}
}