{
  "type": "Feature",
  "properties": {
    "iso:country":"GB",
    "wof:name":"WF3 1PF",
    "wof:placetype":"postalcode"
},
  "geometry": {"coordinates":[-1.56014768853263,53.72807959440739],"type":"Point"}
}