{
  "type": "Feature",
  "properties": {
    "date:inception_lower":"1980-01-01",
    "date:inception_upper":"1980-01-31",
    "iso:country":"GB",
    "wof:name":"WF3 1PF",
    "wof:placetype":"postalcode"
},
  "geometry": {"coordinates":[-1.560148,53.72808],"type":"Point"}
}