{
  "type": "Feature",
  "properties": {
    "iso:country":"GB",
    "wof:name":"IP1 6BH",
    "wof:placetype":"postalcode"
},
  "geometry": {"coordinates":[1.13233060992788,52.07786764472757],"type":"Point"}
}