{
  "type": "Feature",
  "properties": {
    "iso:country":"GB",
    "wof:name":"M33 5BB",
    "wof:placetype":"postalcode"
},
  "geometry": {"coordinates":[-2.33597891886019,53.42089611808915],"type":"Point"}
}