{
  "type": "Feature",
  "properties": {
    "date:inception_lower": "1997-06-01",
    "date:inception_upper": "1997-06-01",
    "iso:country": "GB",
    "wof:name": "S26 3YA",
    "wof:placetype": "postalcode"
  },
  "geometry": {"coordinates":[-1.297512,53.383432],"type":"Point"}
}
