{
  "type": "Feature",
  "properties": {
    "iso:country": "GB",
    "wof:name": "S26 3YA",
    "wof:placetype": "postalcode"
  },
  "geometry": {"coordinates":[-1.297179,53.38352],"type":"Point"}
}
