{
  "type": "Feature",
  "properties": {
    "iso:country":"GB",
    "wof:name":"S26 3YA",
    "wof:placetype":"postalcode"
},
  "geometry": {"coordinates":[-1.29717937725749,53.38350091705484],"type":"Point"}
}