{
  "type": "Feature",
  "properties": {
    "iso:country":"GB",
    "wof:name":"TW3 2LW",
    "wof:placetype":"postalcode"
},
  "geometry": {"coordinates":[-0.36810883253402,51.45705298303672],"type":"Point"}
}