{
  "type": "Feature",
  "properties": {
    "iso:country":"GB",
    "wof:name":"MK16 8HH",
    "wof:placetype":"postalcode"
},
  "geometry": {"coordinates":[-0.72027916224082,52.08638406447177],"type":"Point"}
}