{
  "type": "Feature",
  "properties": {
    "iso:country":"GB",
    "wof:name":"BB9 5DJ",
    "wof:placetype":"postalcode"
},
  "geometry": {"coordinates":[-2.23099976275413,53.8256253256359],"type":"Point"}
}