{
  "type": "Feature",
  "properties": {
    "date:inception_lower": "1980-01-01",
    "date:inception_upper": "1980-01-01",
    "iso:country": "GB",
    "wof:name": "KT12 2EJ",
    "wof:placetype": "postalcode"
  },
  "geometry": {"coordinates":[-0.404714,51.39256],"type":"Point"}
}
