{
  "type": "Feature",
  "properties": {
    "iso:country":"GB",
    "wof:name":"KT12 2EJ",
    "wof:placetype":"postalcode"
},
  "geometry": {"coordinates":[-0.40471437251275,51.39256004165753],"type":"Point"}
}