{
  "type": "Feature",
  "properties": {
    "iso:country":"GB",
    "wof:name":"EN4 8RD",
    "wof:placetype":"postalcode"
},
  "geometry": {"coordinates":[-0.16793945234066,51.64745997701109],"type":"Point"}
}