{
  "type": "Feature",
  "properties": {
    "iso:country":"GB",
    "wof:name":"BH23 3SB",
    "wof:placetype":"postalcode"
},
  "geometry": {"coordinates":[-1.7482994765193,50.73227669925931],"type":"Point"}
}