{
  "type": "Feature",
  "properties": {
    "iso:country":"GB",
    "wof:name":"UB3 1RG",
    "wof:placetype":"postalcode"
},
  "geometry": {"coordinates":[-0.43763778214793,51.50322206107119],"type":"Point"}
}