{
  "type": "Feature",
  "properties": {
    "date:inception_lower": "1980-01-01",
    "date:inception_upper": "1980-01-01",
    "iso:country": "GB",
    "wof:name": "UB3 1RG",
    "wof:placetype": "postalcode"
  },
  "geometry": {"coordinates":[-0.437638,51.503222],"type":"Point"}
}
