{
  "type": "Feature",
  "properties": {
    "iso:country":"GB",
    "wof:name":"EX20 2FN",
    "wof:placetype":"postalcode"
},
  "geometry": {"coordinates":[-3.89637934076263,50.79513031042445],"type":"Point"}
}