{
  "type": "Feature",
  "properties": {
    "date:inception_lower": "2015-10-01",
    "date:inception_upper": "2015-10-01",
    "iso:country": "GB",
    "wof:name": "EX20 2FN",
    "wof:placetype": "postalcode"
  },
  "geometry": {"coordinates":[-3.897356,50.7949],"type":"Point"}
}
