{
  "type": "Feature",
  "properties": {
    "iso:country": "GB",
    "wof:name": "EX20 2FN",
    "wof:placetype": "postalcode"
  },
  "geometry": {"coordinates":[-3.897356,50.7949],"type":"Point"}
}
