{
  "type": "Feature",
  "properties": {
    "iso:country":"GB",
    "wof:name":"SW17 7JN",
    "wof:placetype":"postalcode"
},
  "geometry": {"coordinates":[-0.15547896830625,51.44205728081899],"type":"Point"}
}