{
  "type": "Feature",
  "properties": {
    "iso:country":"GB",
    "wof:name":"DA1 1YN",
    "wof:placetype":"postalcode"
},
  "geometry": {"coordinates":[0.23311688602343,51.4419615157836],"type":"Point"}
}