{
  "type": "Feature",
  "properties": {
    "iso:country":"GB",
    "wof:name":"G76 0EQ",
    "wof:placetype":"postalcode"
},
  "geometry": {"coordinates":[-4.28832214117101,55.75665709086043],"type":"Point"}
}