{
  "type": "Feature",
  "properties": {
    "iso:country":"GB",
    "wof:name":"TR12 7JZ",
    "wof:placetype":"postalcode"
},
  "geometry": {"coordinates":[-5.18240455623883,49.98858077977613],"type":"Point"}
}