{
  "type": "Feature",
  "properties": {
    "iso:country":"GB",
    "wof:name":"TA1 1JS",
    "wof:placetype":"postalcode"
},
  "geometry": {"coordinates":[-3.10054759968265,51.01796185645777],"type":"Point"}
}