{
  "type": "Feature",
  "properties": {
    "iso:country":"GB",
    "wof:name":"LS7 4SA",
    "wof:placetype":"postalcode"
},
  "geometry": {"coordinates":[-1.5298098768628,53.82263591796919],"type":"Point"}
}