{
  "type": "Feature",
  "properties": {
    "date:inception_lower":"1980-01-01",
    "date:inception_upper":"1980-01-31",
    "iso:country":"GB",
    "wof:name":"TW19 7DN",
    "wof:placetype":"postalcode"
},
  "geometry": {"coordinates":[-0.473567,51.450317],"type":"Point"}
}