{
  "type": "Feature",
  "properties": {
    "date:inception_lower": "1997-12-01",
    "date:inception_upper": "1997-12-01",
    "iso:country": "GB",
    "wof:name": "DL3 0UN",
    "wof:placetype": "postalcode"
  },
  "geometry": {"coordinates":[-1.579996,54.546213],"type":"Point"}
}
