{
  "type": "Feature",
  "properties": {
    "iso:country":"GB",
    "wof:name":"DL3 0UN",
    "wof:placetype":"postalcode"
},
  "geometry": {"coordinates":[-1.57999612320933,54.54621281186827],"type":"Point"}
}