{
  "type": "Feature",
  "properties": {
    "iso:country":"GB",
    "wof:name":"TA20 1GT",
    "wof:placetype":"postalcode"
},
  "geometry": {"coordinates":[-2.95416200024532,50.87838063894691],"type":"Point"}
}