{
  "type": "Feature",
  "properties": {
    "iso:country":"GB",
    "wof:name":"RG4 6DH",
    "wof:placetype":"postalcode"
},
  "geometry": {"coordinates":[-0.95925164786697,51.47092909875282],"type":"Point"}
}