{
  "type": "Feature",
  "properties": {
    "iso:country":"GB",
    "wof:name":"NE25 9NA",
    "wof:placetype":"postalcode"
},
  "geometry": {"coordinates":[-1.47496738350431,55.0460590295416],"type":"Point"}
}