{
  "type": "Feature",
  "properties": {
    "date:inception_lower": "1987-04-01",
    "date:inception_upper": "1987-04-01",
    "iso:country": "GB",
    "wof:name": "NE25 9NA",
    "wof:placetype": "postalcode"
  },
  "geometry": {"coordinates":[-1.474967,55.046059],"type":"Point"}
}
