{
  "type": "Feature",
  "properties": {
    "date:inception_lower":"2008-04-01",
    "date:inception_upper":"2008-04-30",
    "iso:country":"GB",
    "wof:name":"L23 1TE",
    "wof:placetype":"postalcode"
},
  "geometry": {"coordinates":[-3.003505,53.499705],"type":"Point"}
}