{
  "type": "Feature",
  "properties": {
    "iso:country":"GB",
    "wof:name":"L23 1TE",
    "wof:placetype":"postalcode"
},
  "geometry": {"coordinates":[-3.00350496094601,53.49970512289746],"type":"Point"}
}