{
  "type": "Feature",
  "properties": {
    "iso:country": "GB",
    "wof:name": "TQ6 9GB",
    "wof:placetype": "postalcode"
  },
  "geometry": {"coordinates":[-3.601966,50.348744],"type":"Point"}
}
