{
  "type": "Feature",
  "properties": {
    "date:inception_lower": "1997-06-01",
    "date:inception_upper": "1997-06-01",
    "iso:country": "GB",
    "wof:name": "TQ6 9GB",
    "wof:placetype": "postalcode"
  },
  "geometry": {"coordinates":[-3.601966,50.348744],"type":"Point"}
}
