{
  "type": "Feature",
  "properties": {
    "date:inception_lower": "1990-09-01",
    "date:inception_upper": "1990-09-01",
    "iso:country": "GB",
    "wof:name": "KA8 9PS",
    "wof:placetype": "postalcode"
  },
  "geometry": {"coordinates":[-4.608189,55.475364],"type":"Point"}
}
