{
  "type": "Feature",
  "properties": {
    "iso:country":"GB",
    "wof:name":"KA8 9PS",
    "wof:placetype":"postalcode"
},
  "geometry": {"coordinates":[-4.60818870998523,55.47536393696463],"type":"Point"}
}