{
  "type": "Feature",
  "properties": {
    "iso:country":"GB",
    "wof:name":"RG20 5RJ",
    "wof:placetype":"postalcode"
},
  "geometry": {"coordinates":[-1.24314308002804,51.32695185755195],"type":"Point"}
}