{
  "type": "Feature",
  "properties": {
    "date:inception_lower":"2008-02-01",
    "date:inception_upper":"2008-02-29",
    "iso:country":"GB",
    "wof:name":"BH12 1JY",
    "wof:placetype":"postalcode"
},
  "geometry": {"coordinates":[-1.91159,50.730995],"type":"Point"}
}