{
  "type": "Feature",
  "properties": {
    "iso:country": "GB",
    "wof:name": "NW2 1JG",
    "wof:placetype": "postalcode"
  },
  "geometry": {"coordinates":[-0.210883,51.569233],"type":"Point"}
}
