{
  "type": "Feature",
  "properties": {
    "iso:country":"GB",
    "wof:name":"NW2 1JG",
    "wof:placetype":"postalcode"
},
  "geometry": {"coordinates":[-0.21088301150998,51.5692327469251],"type":"Point"}
}