{
  "type": "Feature",
  "properties": {
    "iso:country": "GB",
    "wof:name": "IP10 0DP",
    "wof:placetype": "postalcode"
  },
  "geometry": {"coordinates":[1.264617,52.032188],"type":"Point"}
}
