{
  "type": "Feature",
  "properties": {
    "date:inception_lower":"1980-01-01",
    "date:inception_upper":"1980-01-31",
    "iso:country":"GB",
    "wof:name":"IP10 0DP",
    "wof:placetype":"postalcode"
},
  "geometry": {"coordinates":[1.264617,52.032188],"type":"Point"}
}