{
  "type": "Feature",
  "properties": {
    "iso:country":"GB",
    "wof:name":"GL5 4BU",
    "wof:placetype":"postalcode"
},
  "geometry": {"coordinates":[-2.23554992539432,51.75081057911058],"type":"Point"}
}