{
  "type": "Feature",
  "properties": {
    "iso:country": "GB",
    "wof:name": "PR4 6UR",
    "wof:placetype": "postalcode"
  },
  "geometry": {"coordinates":[-2.832793,53.675114],"type":"Point"}
}
