{
  "type": "Feature",
  "properties": {
    "iso:country":"GB",
    "wof:name":"PR4 6UR",
    "wof:placetype":"postalcode"
},
  "geometry": {"coordinates":[-2.83280945490944,53.67510692076927],"type":"Point"}
}