{
  "type": "Feature",
  "properties": {
    "date:inception_lower": "1980-01-01",
    "date:inception_upper": "1980-01-01",
    "iso:country": "GB",
    "wof:name": "CA2 6LZ",
    "wof:placetype": "postalcode"
  },
  "geometry": {"coordinates":[-2.970009,54.878679],"type":"Point"}
}
