{
  "type": "Feature",
  "properties": {
    "date:inception_lower": "2015-05-01",
    "date:inception_upper": "2015-05-01",
    "iso:country": "GB",
    "wof:name": "SK1 1AP",
    "wof:placetype": "postalcode"
  },
  "geometry": {"coordinates":[-2.152074,53.408751],"type":"Point"}
}
