{
  "type": "Feature",
  "properties": {
    "iso:country":"GB",
    "wof:name":"SK1 1AP",
    "wof:placetype":"postalcode"
},
  "geometry": {"coordinates":[-2.15207420010754,53.40875121331219],"type":"Point"}
}