{
  "type": "Feature",
  "properties": {
    "iso:country":"GB",
    "wof:name":"TF9 3AL",
    "wof:placetype":"postalcode"
},
  "geometry": {"coordinates":[-2.48592516629945,52.90873469252155],"type":"Point"}
}