{
  "type": "Feature",
  "properties": {
    "iso:country": "GB",
    "wof:name": "FK12 5AE",
    "wof:placetype": "postalcode"
  },
  "geometry": {"coordinates":[-3.800422,56.152369],"type":"Point"}
}
