{
  "type": "Feature",
  "properties": {
    "iso:country":"GB",
    "wof:name":"NE63 9TL",
    "wof:placetype":"postalcode"
},
  "geometry": {"coordinates":[-1.54204710104319,55.17476785771265],"type":"Point"}
}