{
  "type": "Feature",
  "properties": {
    "date:inception_lower":"1980-01-01",
    "date:inception_upper":"1980-01-31",
    "iso:country":"GB",
    "wof:name":"EH25 9NT",
    "wof:placetype":"postalcode"
},
  "geometry": {"coordinates":[-3.175706,55.85678],"type":"Point"}
}