{
  "type": "Feature",
  "properties": {
    "iso:country":"GB",
    "wof:name":"EH25 9NT",
    "wof:placetype":"postalcode"
},
  "geometry": {"coordinates":[-3.17570585228902,55.8567797644745],"type":"Point"}
}