{
  "type": "Feature",
  "properties": {
    "date:inception_lower": "1999-06-01",
    "date:inception_upper": "1999-06-01",
    "iso:country": "GB",
    "wof:name": "CH44 1DL",
    "wof:placetype": "postalcode"
  },
  "geometry": {"coordinates":[-3.035924,53.422034],"type":"Point"}
}
