{
  "type": "Feature",
  "properties": {
    "iso:country":"GB",
    "wof:name":"CH44 1DL",
    "wof:placetype":"postalcode"
},
  "geometry": {"coordinates":[-3.03592427490353,53.42203412385455],"type":"Point"}
}