{
  "type": "Feature",
  "properties": {
    "iso:country":"GB",
    "wof:name":"SS7 3PF",
    "wof:placetype":"postalcode"
},
  "geometry": {"coordinates":[0.58197687690152,51.56887848195691],"type":"Point"}
}