{
  "type": "Feature",
  "properties": {
    "iso:country":"GB",
    "wof:name":"DN5 8UY",
    "wof:placetype":"postalcode"
},
  "geometry": {"coordinates":[-1.17990775702542,53.5431930224589],"type":"Point"}
}