{
  "type": "Feature",
  "properties": {
    "iso:country": "GB",
    "wof:name": "NG16 3TS",
    "wof:placetype": "postalcode"
  },
  "geometry": {"coordinates":[-1.290744,53.019686],"type":"Point"}
}
