{
  "type": "Feature",
  "properties": {
    "iso:country":"GB",
    "wof:name":"CA10 3RG",
    "wof:placetype":"postalcode"
},
  "geometry": {"coordinates":[-2.58121394819724,54.4688392039367],"type":"Point"}
}