{
  "type": "Feature",
  "properties": {
    "iso:country": "GB",
    "wof:name": "BD16 1TU",
    "wof:placetype": "postalcode"
  },
  "geometry": {"coordinates":[-1.81589,53.834659],"type":"Point"}
}
