{
  "type": "Feature",
  "properties": {
    "iso:country":"GB",
    "wof:name":"BD16 1TU",
    "wof:placetype":"postalcode"
},
  "geometry": {"coordinates":[-1.81589048079399,53.8346593249697],"type":"Point"}
}