{
  "type": "Feature",
  "properties": {
    "iso:country": "GB",
    "wof:name": "SG4 9ER",
    "wof:placetype": "postalcode"
  },
  "geometry": {"coordinates":[-0.277479,51.943811],"type":"Point"}
}
