{
  "type": "Feature",
  "properties": {
    "date:inception_lower": "2020-04-01",
    "date:inception_upper": "2020-04-01",
    "iso:country": "GB",
    "wof:name": "SY12 9FE",
    "wof:placetype": "postalcode"
  },
  "geometry": {"coordinates":[-2.90579,52.909445],"type":"Point"}
}
