{
  "type": "Feature",
  "properties": {
    "iso:country": "GB",
    "wof:name": "BS4 2BZ",
    "wof:placetype": "postalcode"
  },
  "geometry": {"coordinates":[-2.575799,51.439629],"type":"Point"}
}
