{
  "type": "Feature",
  "properties": {
    "iso:country":"GB",
    "wof:name":"NE26 3AH",
    "wof:placetype":"postalcode"
},
  "geometry": {"coordinates":[-1.45840613165963,55.04629204865358],"type":"Point"}
}