{
  "type": "Feature",
  "properties": {
    "iso:country":"GB",
    "wof:name":"CH64 2UY",
    "wof:placetype":"postalcode"
},
  "geometry": {"coordinates":[-3.0159772539801,53.29475012850333],"type":"Point"}
}