{
  "type": "Feature",
  "properties": {
    "iso:country": "GB",
    "wof:name": "NG21 0TR",
    "wof:placetype": "postalcode"
  },
  "geometry": {"coordinates":[-1.11502,53.096661],"type":"Point"}
}
