{
  "type": "Feature",
  "properties": {
    "iso:country":"GB",
    "wof:name":"WA13 0HF",
    "wof:placetype":"postalcode"
},
  "geometry": {"coordinates":[-2.49046527684909,53.38005618882971],"type":"Point"}
}