{
  "type": "Feature",
  "properties": {
    "iso:country":"GB",
    "wof:name":"TR18 4LQ",
    "wof:placetype":"postalcode"
},
  "geometry": {"coordinates":[-5.5450810820508,50.11797044759045],"type":"Point"}
}