{
  "type": "Feature",
  "properties": {
    "date:inception_lower":"1980-01-01",
    "date:inception_upper":"1980-01-31",
    "iso:country":"GB",
    "wof:name":"TR18 4LQ",
    "wof:placetype":"postalcode"
},
  "geometry": {"coordinates":[-5.545081,50.11797],"type":"Point"}
}