{
  "type": "Feature",
  "properties": {
    "iso:country":"GB",
    "wof:name":"W2 2RN",
    "wof:placetype":"postalcode"
},
  "geometry": {"coordinates":[-0.16960904970591,51.51653001173113],"type":"Point"}
}