{
  "type": "Feature",
  "properties": {
    "iso:country":"GB",
    "wof:name":"HU16 5PA",
    "wof:placetype":"postalcode"
},
  "geometry": {"coordinates":[-0.4225554117968,53.78197737109438],"type":"Point"}
}