{
  "type": "Feature",
  "properties": {
    "iso:country": "GB",
    "wof:name": "NR30 4DU",
    "wof:placetype": "postalcode"
  },
  "geometry": {"coordinates":[1.731964,52.623907],"type":"Point"}
}
