{
  "type": "Feature",
  "properties": {
    "iso:country": "GB",
    "wof:name": "SE18 6AY",
    "wof:placetype": "postalcode"
  },
  "geometry": {"coordinates":[0.069509,51.49081],"type":"Point"}
}
