{
  "type": "Feature",
  "properties": {
    "iso:country":"GB",
    "wof:name":"SE18 6AY",
    "wof:placetype":"postalcode"
},
  "geometry": {"coordinates":[0.06950848585571,51.49080996098866],"type":"Point"}
}