{
  "type": "Feature",
  "properties": {
    "iso:country":"GB",
    "wof:name":"PH1 2UB",
    "wof:placetype":"postalcode"
},
  "geometry": {"coordinates":[-3.46976106219315,56.41259466600626],"type":"Point"}
}