{
  "type": "Feature",
  "properties": {
    "iso:country":"GB",
    "wof:name":"B11 1LN",
    "wof:placetype":"postalcode"
},
  "geometry": {"coordinates":[-1.87141158541123,52.46086087713159],"type":"Point"}
}