{
  "type": "Feature",
  "properties": {
    "iso:country":"GB",
    "wof:name":"SO40 4XA",
    "wof:placetype":"postalcode"
},
  "geometry": {"coordinates":[-1.45380399857959,50.88914413517766],"type":"Point"}
}