{
  "type": "Feature",
  "properties": {
    "date:inception_lower":"1994-12-01",
    "date:inception_upper":"1994-12-31",
    "iso:country":"GB",
    "wof:name":"SO40 4XA",
    "wof:placetype":"postalcode"
},
  "geometry": {"coordinates":[-1.453804,50.889144],"type":"Point"}
}