{
  "type": "Feature",
  "properties": {
    "iso:country":"GB",
    "wof:name":"SN14 6PA",
    "wof:placetype":"postalcode"
},
  "geometry": {"coordinates":[-2.24175000858936,51.55541820050972],"type":"Point"}
}