{
  "type": "Feature",
  "properties": {
    "iso:country": "GB",
    "wof:name": "SN14 6PA",
    "wof:placetype": "postalcode"
  },
  "geometry": {"coordinates":[-2.24175,51.555418],"type":"Point"}
}
