{
  "type": "Feature",
  "properties": {
    "iso:country":"GB",
    "wof:name":"M33 5BF",
    "wof:placetype":"postalcode"
},
  "geometry": {"coordinates":[-2.33512667501778,53.41967606863945],"type":"Point"}
}