{
  "type": "Feature",
  "properties": {
    "iso:country":"GB",
    "wof:name":"HU5 5XB",
    "wof:placetype":"postalcode"
},
  "geometry": {"coordinates":[-0.40555408104198,53.7580124307251],"type":"Point"}
}