{
  "type": "Feature",
  "properties": {
    "iso:country":"GB",
    "wof:name":"SG15 6TD",
    "wof:placetype":"postalcode"
},
  "geometry": {"coordinates":[-0.26312844811501,52.01622663037028],"type":"Point"}
}