{
  "type": "Feature",
  "properties": {
    "iso:country":"GB",
    "wof:name":"NW11 0QD",
    "wof:placetype":"postalcode"
},
  "geometry": {"coordinates":[-0.19948850525521,51.58189055544583],"type":"Point"}
}