{
  "type": "Feature",
  "properties": {
    "date:inception_lower": "1980-01-01",
    "date:inception_upper": "1980-01-01",
    "iso:country": "GB",
    "wof:name": "NW11 0QD",
    "wof:placetype": "postalcode"
  },
  "geometry": {"coordinates":[-0.199488,51.581891],"type":"Point"}
}
