{
  "type": "Feature",
  "properties": {
    "iso:country": "GB",
    "wof:name": "HR7 4EF",
    "wof:placetype": "postalcode"
  },
  "geometry": {"coordinates":[-2.510841,52.190031],"type":"Point"}
}
