{
  "type": "Feature",
  "properties": {
    "iso:country":"GB",
    "wof:name":"HR7 4EF",
    "wof:placetype":"postalcode"
},
  "geometry": {"coordinates":[-2.51080052092387,52.19010894643229],"type":"Point"}
}