{
  "type": "Feature",
  "properties": {
    "date:inception_lower": "1987-04-01",
    "date:inception_upper": "1987-04-01",
    "iso:country": "GB",
    "wof:name": "SN15 3UN",
    "wof:placetype": "postalcode"
  },
  "geometry": {"coordinates":[-2.103658,51.447904],"type":"Point"}
}
