{
  "type": "Feature",
  "properties": {
    "iso:country":"GB",
    "wof:name":"SN15 3UN",
    "wof:placetype":"postalcode"
},
  "geometry": {"coordinates":[-2.1036581729674,51.44790399328276],"type":"Point"}
}