{
  "type": "Feature",
  "properties": {
    "iso:country":"GB",
    "wof:name":"E5 0EN",
    "wof:placetype":"postalcode"
},
  "geometry": {"coordinates":[-0.03702980332033,51.5542322734569],"type":"Point"}
}