{
  "type": "Feature",
  "properties": {
    "date:inception_lower": "1980-01-01",
    "date:inception_upper": "1980-01-01",
    "iso:country": "GB",
    "wof:name": "E5 0EN",
    "wof:placetype": "postalcode"
  },
  "geometry": {"coordinates":[-0.03703,51.554232],"type":"Point"}
}
