{
  "type": "Feature",
  "properties": {
    "date:inception_lower":"2004-10-01",
    "date:inception_upper":"2004-10-31",
    "iso:country":"GB",
    "wof:name":"AB34 4UW",
    "wof:placetype":"postalcode"
},
  "geometry": {"coordinates":[-2.856791,57.128139],"type":"Point"}
}