{
  "type": "Feature",
  "properties": {
    "iso:country":"GB",
    "wof:name":"KT17 2LE",
    "wof:placetype":"postalcode"
},
  "geometry": {"coordinates":[-0.2410367766988,51.36454363781611],"type":"Point"}
}