{
  "type": "Feature",
  "properties": {
    "date:inception_lower": "1980-01-01",
    "date:inception_upper": "1980-01-01",
    "iso:country": "GB",
    "wof:name": "KT17 2LE",
    "wof:placetype": "postalcode"
  },
  "geometry": {"coordinates":[-0.241037,51.364544],"type":"Point"}
}
