{
  "type": "Feature",
  "properties": {
    "iso:country": "GB",
    "wof:name": "WA3 5NB",
    "wof:placetype": "postalcode"
  },
  "geometry": {"coordinates":[-2.493363,53.469364],"type":"Point"}
}
