{
  "type": "Feature",
  "properties": {
    "iso:country":"GB",
    "wof:name":"WA3 5NB",
    "wof:placetype":"postalcode"
},
  "geometry": {"coordinates":[-2.4933627805724,53.46936411965243],"type":"Point"}
}