{
  "type": "Feature",
  "properties": {
    "iso:country":"GB",
    "wof:name":"BS16 6AN",
    "wof:placetype":"postalcode"
},
  "geometry": {"coordinates":[-2.49638887897694,51.4893924054151],"type":"Point"}
}