{
  "type": "Feature",
  "properties": {
    "iso:country": "GB",
    "wof:name": "BS16 6AN",
    "wof:placetype": "postalcode"
  },
  "geometry": {"coordinates":[-2.496389,51.489392],"type":"Point"}
}
