{
  "type": "Feature",
  "properties": {
    "iso:country": "GB",
    "wof:name": "TF11 8GB",
    "wof:placetype": "postalcode"
  },
  "geometry": {"coordinates":[-2.377452,52.675838],"type":"Point"}
}
