{
  "type": "Feature",
  "properties": {
    "iso:country":"GB",
    "wof:name":"LS15 8AJ",
    "wof:placetype":"postalcode"
},
  "geometry": {"coordinates":[-1.43699167374908,53.80804427361144],"type":"Point"}
}