{
  "type": "Feature",
  "properties": {
    "date:inception_lower":"2014-01-01",
    "date:inception_upper":"2014-01-31",
    "iso:country":"GB",
    "wof:name":"LS15 8AJ",
    "wof:placetype":"postalcode"
},
  "geometry": {"coordinates":[-1.436992,53.808044],"type":"Point"}
}