{
  "type": "Feature",
  "properties": {
    "iso:country":"GB",
    "wof:name":"NN2 7TB",
    "wof:placetype":"postalcode"
},
  "geometry": {"coordinates":[-0.8960812560596,52.26518174345804],"type":"Point"}
}