{
  "type": "Feature",
  "properties": {
    "iso:country":"GB",
    "wof:name":"L11 7AN",
    "wof:placetype":"postalcode"
},
  "geometry": {"coordinates":[-2.93190800814971,53.45008253125518],"type":"Point"}
}