{
  "type": "Feature",
  "properties": {
    "iso:country":"GB",
    "wof:name":"HD6 3RA",
    "wof:placetype":"postalcode"
},
  "geometry": {"coordinates":[-1.7790772846342,53.6978265238938],"type":"Point"}
}