{
  "type": "Feature",
  "properties": {
    "iso:country": "GB",
    "wof:name": "LL40 2TU",
    "wof:placetype": "postalcode"
  },
  "geometry": {"coordinates":[-3.94374,52.759768],"type":"Point"}
}
