{
  "type": "Feature",
  "properties": {
    "date:inception_lower": "1980-01-01",
    "date:inception_upper": "1980-01-01",
    "iso:country": "GB",
    "wof:name": "LL40 2TU",
    "wof:placetype": "postalcode"
  },
  "geometry": {"coordinates":[-3.943821,52.761113],"type":"Point"}
}
