{
  "type": "Feature",
  "properties": {
    "iso:country":"GB",
    "wof:name":"LL40 2TU",
    "wof:placetype":"postalcode"
},
  "geometry": {"coordinates":[-3.9437398460413,52.75976808331777],"type":"Point"}
}