{
  "type": "Feature",
  "properties": {
    "iso:country":"GB",
    "wof:name":"SA20 0TY",
    "wof:placetype":"postalcode"
},
  "geometry": {"coordinates":[-3.80419464653938,52.01478401003526],"type":"Point"}
}