{
  "type": "Feature",
  "properties": {
    "iso:country": "GB",
    "wof:name": "SA20 0TY",
    "wof:placetype": "postalcode"
  },
  "geometry": {"coordinates":[-3.804273,52.014585],"type":"Point"}
}
