{
  "type": "Feature",
  "properties": {
    "iso:country": "GB",
    "wof:name": "PL21 9BW",
    "wof:placetype": "postalcode"
  },
  "geometry": {"coordinates":[-3.931321,50.388691],"type":"Point"}
}
