{
  "type": "Feature",
  "properties": {
    "iso:country":"GB",
    "wof:name":"PL21 9BW",
    "wof:placetype":"postalcode"
},
  "geometry": {"coordinates":[-3.93132135052376,50.38869097576629],"type":"Point"}
}