{
  "type": "Feature",
  "properties": {
    "iso:country":"GB",
    "wof:name":"BA11 2DE",
    "wof:placetype":"postalcode"
},
  "geometry": {"coordinates":[-2.29873309513645,51.23717122823054],"type":"Point"}
}