{
  "type": "Feature",
  "properties": {
    "iso:country":"GB",
    "wof:name":"CB1 2NB",
    "wof:placetype":"postalcode"
},
  "geometry": {"coordinates":[0.1361572935819,52.20572469941362],"type":"Point"}
}