{
  "type": "Feature",
  "properties": {
    "iso:country":"GB",
    "wof:name":"TS17 9JP",
    "wof:placetype":"postalcode"
},
  "geometry": {"coordinates":[-1.28944194320571,54.53353214796902],"type":"Point"}
}