{
  "type": "Feature",
  "properties": {
    "iso:country":"GB",
    "wof:name":"SE2 0RU",
    "wof:placetype":"postalcode"
},
  "geometry": {"coordinates":[0.12575863073963,51.47959675017748],"type":"Point"}
}