{
  "type": "Feature",
  "properties": {
    "iso:country":"GB",
    "wof:name":"SO53 2DF",
    "wof:placetype":"postalcode"
},
  "geometry": {"coordinates":[-1.36927756345495,50.98641217258216],"type":"Point"}
}