{
  "type": "Feature",
  "properties": {
    "date:inception_lower": "1995-07-01",
    "date:inception_upper": "1995-07-01",
    "iso:country": "GB",
    "wof:name": "SA10 7RX",
    "wof:placetype": "postalcode"
  },
  "geometry": {"coordinates":[-3.821301,51.670612],"type":"Point"}
}
