{
  "type": "Feature",
  "properties": {
    "iso:country":"GB",
    "wof:name":"SA10 7RX",
    "wof:placetype":"postalcode"
},
  "geometry": {"coordinates":[-3.82130071292491,51.67061235604492],"type":"Point"}
}