{
  "type": "Feature",
  "properties": {
    "iso:country":"GB",
    "wof:name":"PO37 7PR",
    "wof:placetype":"postalcode"
},
  "geometry": {"coordinates":[-1.19433886817407,50.63077242450384],"type":"Point"}
}