{
  "type": "Feature",
  "properties": {
    "iso:country":"GB",
    "wof:name":"CF44 9HW",
    "wof:placetype":"postalcode"
},
  "geometry": {"coordinates":[-3.50226476275191,51.73443796826444],"type":"Point"}
}