{
  "type": "Feature",
  "properties": {
    "iso:country":"GB",
    "wof:name":"HD7 6JS",
    "wof:placetype":"postalcode"
},
  "geometry": {"coordinates":[-1.91853675676528,53.60457908565804],"type":"Point"}
}