{
  "type": "Feature",
  "properties": {
    "date:inception_lower":"1980-01-01",
    "date:inception_upper":"1980-01-31",
    "iso:country":"GB",
    "wof:name":"FK8 3RL",
    "wof:placetype":"postalcode"
},
  "geometry": {"coordinates":[-4.377092,56.145079],"type":"Point"}
}