{
  "type": "Feature",
  "properties": {
    "date:inception_lower": "2024-02-01",
    "date:inception_upper": "2024-02-01",
    "iso:country": "GB",
    "wof:name": "BD23 6FH",
    "wof:placetype": "postalcode"
  },
  "geometry": {"coordinates":[-1.985026,53.978205],"type":"Point"}
}
