{
  "type": "Feature",
  "properties": {
    "iso:country": "GB",
    "wof:name": "ST18 9HF",
    "wof:placetype": "postalcode"
  },
  "geometry": {"coordinates":[-2.206095,52.78804],"type":"Point"}
}
