{
  "type": "Feature",
  "properties": {
    "iso:country":"GB",
    "wof:name":"ST18 9HF",
    "wof:placetype":"postalcode"
},
  "geometry": {"coordinates":[-2.20609496693369,52.78804040516807],"type":"Point"}
}