{
  "type": "Feature",
  "properties": {
    "iso:country":"GB",
    "wof:name":"S35 8PL",
    "wof:placetype":"postalcode"
},
  "geometry": {"coordinates":[-1.50198037761381,53.44359473308118],"type":"Point"}
}