{
  "type": "Feature",
  "properties": {
    "iso:country": "GB",
    "wof:name": "S35 8PL",
    "wof:placetype": "postalcode"
  },
  "geometry": {"coordinates":[-1.50198,53.443595],"type":"Point"}
}
