{
  "type": "Feature",
  "properties": {
    "iso:country":"GB",
    "wof:name":"HR9 5HP",
    "wof:placetype":"postalcode"
},
  "geometry": {"coordinates":[-2.58525112765227,51.9139724129492],"type":"Point"}
}