{
  "type": "Feature",
  "properties": {
    "iso:country": "GB",
    "wof:name": "HR9 5HP",
    "wof:placetype": "postalcode"
  },
  "geometry": {"coordinates":[-2.585251,51.913972],"type":"Point"}
}
