{
  "type": "Feature",
  "properties": {
    "iso:country":"GB",
    "wof:name":"LN4 4ZN",
    "wof:placetype":"postalcode"
},
  "geometry": {"coordinates":[-0.19860876007743,53.07098259225072],"type":"Point"}
}