{
  "type": "Feature",
  "properties": {
    "iso:country": "GB",
    "wof:name": "LN4 4ZN",
    "wof:placetype": "postalcode"
  },
  "geometry": {"coordinates":[-0.198609,53.070983],"type":"Point"}
}
