{
  "type": "Feature",
  "properties": {
    "iso:country":"GB",
    "wof:name":"TQ12 6QP",
    "wof:placetype":"postalcode"
},
  "geometry": {"coordinates":[-3.62608411030129,50.55408728302676],"type":"Point"}
}