{
  "type": "Feature",
  "properties": {
    "iso:country": "GB",
    "wof:name": "TQ12 6QP",
    "wof:placetype": "postalcode"
  },
  "geometry": {"coordinates":[-3.626084,50.554087],"type":"Point"}
}
