{
  "type": "Feature",
  "properties": {
    "date:inception_lower": "1980-01-01",
    "date:inception_upper": "1980-01-01",
    "iso:country": "GB",
    "wof:name": "TQ12 6QP",
    "wof:placetype": "postalcode"
  },
  "geometry": {"coordinates":[-3.626084,50.554087],"type":"Point"}
}
