{
  "type": "Feature",
  "properties": {
    "date:inception_lower": "2022-08-01",
    "date:inception_upper": "2022-08-01",
    "iso:country": "GB",
    "wof:name": "PL6 7FU",
    "wof:placetype": "postalcode"
  },
  "geometry": {"coordinates":[-4.094512,50.429826],"type":"Point"}
}
