{
  "type": "Feature",
  "properties": {
    "iso:country":"GB",
    "wof:name":"DG9 7SB",
    "wof:placetype":"postalcode"
},
  "geometry": {"coordinates":[-5.02256999466996,54.90317250180966],"type":"Point"}
}