{
  "type": "Feature",
  "properties": {
    "date:inception_lower":"1980-01-01",
    "date:inception_upper":"1980-01-31",
    "iso:country":"GB",
    "wof:name":"DG9 7SB",
    "wof:placetype":"postalcode"
},
  "geometry": {"coordinates":[-5.02267,54.903172],"type":"Point"}
}