{
  "type": "Feature",
  "properties": {
    "iso:country": "GB",
    "wof:name": "DG9 7SB",
    "wof:placetype": "postalcode"
  },
  "geometry": {"coordinates":[-5.02267,54.903172],"type":"Point"}
}
