{
  "type": "Feature",
  "properties": {
    "date:inception_lower": "1994-05-01",
    "date:inception_upper": "1994-05-01",
    "iso:country": "GB",
    "wof:name": "M27 6DE",
    "wof:placetype": "postalcode"
  },
  "geometry": {"coordinates":[-2.332009,53.517838],"type":"Point"}
}
