{
  "type": "Feature",
  "properties": {
    "date:inception_lower": "1980-01-01",
    "date:inception_upper": "1980-01-01",
    "iso:country": "GB",
    "wof:name": "TQ12 5UJ",
    "wof:placetype": "postalcode"
  },
  "geometry": {"coordinates":[-3.650743,50.477865],"type":"Point"}
}
