{
  "type": "Feature",
  "properties": {
    "iso:country":"GB",
    "wof:name":"TQ12 5UJ",
    "wof:placetype":"postalcode"
},
  "geometry": {"coordinates":[-3.66124173173204,50.47673063941567],"type":"Point"}
}