{
  "type": "Feature",
  "properties": {
    "iso:country":"GB",
    "wof:name":"M22 0LJ",
    "wof:placetype":"postalcode"
},
  "geometry": {"coordinates":[-2.2533588221335,53.36844496896143],"type":"Point"}
}