{
  "type": "Feature",
  "properties": {
    "date:inception_lower": "1996-12-01",
    "date:inception_upper": "1996-12-01",
    "iso:country": "GB",
    "wof:name": "PE12 8DH",
    "wof:placetype": "postalcode"
  },
  "geometry": {"coordinates":[0.002467,52.826232],"type":"Point"}
}
