{
  "type": "Feature",
  "properties": {
    "iso:country":"GB",
    "wof:name":"PE12 8DH",
    "wof:placetype":"postalcode"
},
  "geometry": {"coordinates":[0.00246709993163,52.8262318768071],"type":"Point"}
}