{
  "type": "Feature",
  "properties": {
    "iso:country":"GB",
    "wof:name":"WR3 8AG",
    "wof:placetype":"postalcode"
},
  "geometry": {"coordinates":[-2.22518547887058,52.2076595334411],"type":"Point"}
}