{
  "type": "Feature",
  "properties": {
    "date:inception_lower": "1990-02-01",
    "date:inception_upper": "1990-02-01",
    "iso:country": "GB",
    "wof:name": "WR3 8AG",
    "wof:placetype": "postalcode"
  },
  "geometry": {"coordinates":[-2.225185,52.20766],"type":"Point"}
}
