{
  "type": "Feature",
  "properties": {
    "iso:country": "GB",
    "wof:name": "WR3 8AG",
    "wof:placetype": "postalcode"
  },
  "geometry": {"coordinates":[-2.225185,52.20766],"type":"Point"}
}
