{
  "type": "Feature",
  "properties": {
    "date:inception_lower":"1999-06-01",
    "date:inception_upper":"1999-06-30",
    "iso:country":"GB",
    "wof:name":"CH46 4TB",
    "wof:placetype":"postalcode"
},
  "geometry": {"coordinates":[-3.12742,53.411893],"type":"Point"}
}