{
  "type": "Feature",
  "properties": {
    "iso:country": "GB",
    "wof:name": "IP14 1SN",
    "wof:placetype": "postalcode"
  },
  "geometry": {"coordinates":[0.976711,52.189491],"type":"Point"}
}
