{
  "type": "Feature",
  "properties": {
    "iso:country":"GB",
    "wof:name":"IP14 1SN",
    "wof:placetype":"postalcode"
},
  "geometry": {"coordinates":[0.97667863049255,52.18946621981949],"type":"Point"}
}