{
  "type": "Feature",
  "properties": {
    "date:inception_lower": "1980-01-01",
    "date:inception_upper": "1980-01-01",
    "iso:country": "GB",
    "wof:name": "IP14 1SN",
    "wof:placetype": "postalcode"
  },
  "geometry": {"coordinates":[0.977074,52.189446],"type":"Point"}
}
