{
  "type": "Feature",
  "properties": {
    "iso:country":"GB",
    "wof:name":"TW16 5LB",
    "wof:placetype":"postalcode"
},
  "geometry": {"coordinates":[-0.39985755126095,51.4094085105683],"type":"Point"}
}