{
  "type": "Feature",
  "properties": {
    "date:inception_lower":"1980-01-01",
    "date:inception_upper":"1980-01-31",
    "iso:country":"GB",
    "wof:name":"TW16 5LB",
    "wof:placetype":"postalcode"
},
  "geometry": {"coordinates":[-0.399858,51.409409],"type":"Point"}
}