{
  "type": "Feature",
  "properties": {
    "iso:country":"GB",
    "wof:name":"LU5 5DA",
    "wof:placetype":"postalcode"
},
  "geometry": {"coordinates":[-0.520357497639,51.90024155976177],"type":"Point"}
}