{
  "type": "Feature",
  "properties": {
    "iso:country":"GB",
    "wof:name":"ML7 4AE",
    "wof:placetype":"postalcode"
},
  "geometry": {"coordinates":[-3.80977303924188,55.82125480355957],"type":"Point"}
}