{
  "type": "Feature",
  "properties": {
    "iso:country":"GB",
    "wof:name":"SA7 9GP",
    "wof:placetype":"postalcode"
},
  "geometry": {"coordinates":[-3.87269620698111,51.66810428469337],"type":"Point"}
}