{
  "type": "Feature",
  "properties": {
    "date:inception_lower": "2012-07-01",
    "date:inception_upper": "2012-07-01",
    "iso:country": "GB",
    "wof:name": "SA7 9GP",
    "wof:placetype": "postalcode"
  },
  "geometry": {"coordinates":[-3.872696,51.668104],"type":"Point"}
}
