{
  "type": "Feature",
  "properties": {
    "iso:country": "GB",
    "wof:name": "SA7 9GP",
    "wof:placetype": "postalcode"
  },
  "geometry": {"coordinates":[-3.872696,51.668104],"type":"Point"}
}
