{
  "type": "Feature",
  "properties": {
    "iso:country":"GB",
    "wof:name":"PE14 0AZ",
    "wof:placetype":"postalcode"
},
  "geometry": {"coordinates":[0.15113870456153,52.63488556143081],"type":"Point"}
}