{
  "type": "Feature",
  "properties": {
    "iso:country":"GB",
    "wof:name":"GL7 1EL",
    "wof:placetype":"postalcode"
},
  "geometry": {"coordinates":[-1.96605426564785,51.71398994828301],"type":"Point"}
}