{
  "type": "Feature",
  "properties": {
    "date:inception_lower":"1987-04-01",
    "date:inception_upper":"1987-04-30",
    "iso:country":"GB",
    "wof:name":"HA6 1DH",
    "wof:placetype":"postalcode"
},
  "geometry": {"coordinates":[-0.415184,51.603399],"type":"Point"}
}