{
  "type": "Feature",
  "properties": {
    "iso:country": "GB",
    "wof:name": "HA6 1DH",
    "wof:placetype": "postalcode"
  },
  "geometry": {"coordinates":[-0.415184,51.603399],"type":"Point"}
}
