{
  "type": "Feature",
  "properties": {
    "iso:country":"GB",
    "wof:name":"HA6 1DH",
    "wof:placetype":"postalcode"
},
  "geometry": {"coordinates":[-0.4151843579443,51.60339920790855],"type":"Point"}
}