{
  "type": "Feature",
  "properties": {
    "date:inception_lower":"1985-10-01",
    "date:inception_upper":"1985-10-31",
    "iso:country":"GB",
    "wof:name":"ST3 2HG",
    "wof:placetype":"postalcode"
},
  "geometry": {"coordinates":[-2.146726,52.981975],"type":"Point"}
}