{
  "type": "Feature",
  "properties": {
    "iso:country":"GB",
    "wof:name":"ST3 2HG",
    "wof:placetype":"postalcode"
},
  "geometry": {"coordinates":[-2.14672608754522,52.98197508249602],"type":"Point"}
}