{
  "type": "Feature",
  "properties": {
    "iso:country":"GB",
    "wof:name":"ME18 6EH",
    "wof:placetype":"postalcode"
},
  "geometry": {"coordinates":[0.43381420404145,51.22852480064613],"type":"Point"}
}