{
  "type": "Feature",
  "properties": {
    "iso:country": "GB",
    "wof:name": "ME18 6EH",
    "wof:placetype": "postalcode"
  },
  "geometry": {"coordinates":[0.433814,51.228525],"type":"Point"}
}
