{
  "type": "Feature",
  "properties": {
    "iso:country": "GB",
    "wof:name": "FY4 1TL",
    "wof:placetype": "postalcode"
  },
  "geometry": {"coordinates":[-3.047777,53.789421],"type":"Point"}
}
