{
  "type": "Feature",
  "properties": {
    "iso:country":"GB",
    "wof:name":"CV5 7PT",
    "wof:placetype":"postalcode"
},
  "geometry": {"coordinates":[-1.57278610883708,52.41846398999154],"type":"Point"}
}