{
  "type": "Feature",
  "properties": {
    "date:inception_lower": "1980-01-01",
    "date:inception_upper": "1980-01-01",
    "iso:country": "GB",
    "wof:name": "EX12 2EB",
    "wof:placetype": "postalcode"
  },
  "geometry": {"coordinates":[-3.074834,50.715718],"type":"Point"}
}
