{
  "type": "Feature",
  "properties": {
    "iso:country": "GB",
    "wof:name": "NG20 8NJ",
    "wof:placetype": "postalcode"
  },
  "geometry": {"coordinates":[-1.228538,53.20497],"type":"Point"}
}
