{
  "type": "Feature",
  "properties": {
    "iso:country":"GB",
    "wof:name":"NG20 8NJ",
    "wof:placetype":"postalcode"
},
  "geometry": {"coordinates":[-1.22853781959542,53.20497020787715],"type":"Point"}
}