{
  "type": "Feature",
  "properties": {
    "iso:country":"GB",
    "wof:name":"B20 2RH",
    "wof:placetype":"postalcode"
},
  "geometry": {"coordinates":[-1.92029559082125,52.50632105538642],"type":"Point"}
}