{
  "type": "Feature",
  "properties": {
    "iso:country":"GB",
    "wof:name":"LN4 2TG",
    "wof:placetype":"postalcode"
},
  "geometry": {"coordinates":[-0.53242645848619,53.19819740879606],"type":"Point"}
}