{
  "type": "Feature",
  "properties": {
    "iso:country": "GB",
    "wof:name": "LN4 2TG",
    "wof:placetype": "postalcode"
  },
  "geometry": {"coordinates":[-0.532426,53.198197],"type":"Point"}
}
