{
  "type": "Feature",
  "properties": {
    "date:inception_lower": "2015-10-01",
    "date:inception_upper": "2015-10-01",
    "iso:country": "GB",
    "wof:name": "LN4 2TG",
    "wof:placetype": "postalcode"
  },
  "geometry": {"coordinates":[-0.532426,53.198197],"type":"Point"}
}
