{
  "type": "Feature",
  "properties": {
    "iso:country":"GB",
    "wof:name":"BS25 1HQ",
    "wof:placetype":"postalcode"
},
  "geometry": {"coordinates":[-2.82952946842673,51.31693365841386],"type":"Point"}
}