{
  "type": "Feature",
  "properties": {
    "date:inception_lower": "1980-01-01",
    "date:inception_upper": "1980-01-01",
    "iso:country": "GB",
    "wof:name": "BS25 1HQ",
    "wof:placetype": "postalcode"
  },
  "geometry": {"coordinates":[-2.829529,51.316934],"type":"Point"}
}
