{
  "type": "Feature",
  "properties": {
    "iso:country":"GB",
    "wof:name":"KT24 6AF",
    "wof:placetype":"postalcode"
},
  "geometry": {"coordinates":[-0.43443648611976,51.26154503140688],"type":"Point"}
}