{
  "type": "Feature",
  "properties": {
    "iso:country":"GB",
    "wof:name":"DD2 1RG",
    "wof:placetype":"postalcode"
},
  "geometry": {"coordinates":[-2.99543493481802,56.46038946302477],"type":"Point"}
}