{
  "type": "Feature",
  "properties": {
    "iso:country":"GB",
    "wof:name":"NG5 2HJ",
    "wof:placetype":"postalcode"
},
  "geometry": {"coordinates":[-1.15164001799659,52.98182780097424],"type":"Point"}
}