{
  "type": "Feature",
  "properties": {
    "iso:country":"GB",
    "wof:name":"DE21 7FG",
    "wof:placetype":"postalcode"
},
  "geometry": {"coordinates":[-1.40451197341055,52.92048205532803],"type":"Point"}
}