{
  "type": "Feature",
  "properties": {
    "iso:country":"GB",
    "wof:name":"TN22 5TZ",
    "wof:placetype":"postalcode"
},
  "geometry": {"coordinates":[0.09982372704861,50.9579102851026],"type":"Point"}
}