{
  "type": "Feature",
  "properties": {
    "date:inception_lower":"1985-10-01",
    "date:inception_upper":"1985-10-31",
    "iso:country":"GB",
    "wof:name":"TN22 5TZ",
    "wof:placetype":"postalcode"
},
  "geometry": {"coordinates":[0.099824,50.95791],"type":"Point"}
}