{
  "type": "Feature",
  "properties": {
    "iso:country": "GB",
    "wof:name": "SE2 0BP",
    "wof:placetype": "postalcode"
  },
  "geometry": {"coordinates":[0.10848,51.487166],"type":"Point"}
}
