{
  "type": "Feature",
  "properties": {
    "iso:country":"GB",
    "wof:name":"SE2 0BP",
    "wof:placetype":"postalcode"
},
  "geometry": {"coordinates":[0.10847982207848,51.48716599566501],"type":"Point"}
}