{
  "type": "Feature",
  "properties": {
    "iso:country":"GB",
    "wof:name":"CM0 7HG",
    "wof:placetype":"postalcode"
},
  "geometry": {"coordinates":[0.82750228780702,51.66043937794342],"type":"Point"}
}