{
  "type": "Feature",
  "properties": {
    "iso:country":"GB",
    "wof:name":"SP4 8LW",
    "wof:placetype":"postalcode"
},
  "geometry": {"coordinates":[-1.79913105575472,51.19052432923848],"type":"Point"}
}