{
  "type": "Feature",
  "properties": {
    "date:inception_lower": "1980-01-01",
    "date:inception_upper": "1980-01-01",
    "iso:country": "GB",
    "wof:name": "SP4 8LW",
    "wof:placetype": "postalcode"
  },
  "geometry": {"coordinates":[-1.799131,51.190524],"type":"Point"}
}
