{
  "type": "Feature",
  "properties": {
    "iso:country":"GB",
    "wof:name":"WF5 9SQ",
    "wof:placetype":"postalcode"
},
  "geometry": {"coordinates":[-1.54842575365746,53.67906841446557],"type":"Point"}
}