{
  "type": "Feature",
  "properties": {
    "iso:country": "GB",
    "wof:name": "WS2 9BF",
    "wof:placetype": "postalcode"
  },
  "geometry": {"coordinates":[-2.000311,52.575372],"type":"Point"}
}
