{
  "type": "Feature",
  "properties": {
    "date:inception_lower": "2008-12-01",
    "date:inception_upper": "2008-12-01",
    "iso:country": "GB",
    "wof:name": "WS2 9BF",
    "wof:placetype": "postalcode"
  },
  "geometry": {"coordinates":[-2.000311,52.575372],"type":"Point"}
}
