{
  "type": "Feature",
  "properties": {
    "iso:country":"GB",
    "wof:name":"WS2 9BF",
    "wof:placetype":"postalcode"
},
  "geometry": {"coordinates":[-2.0003108360411,52.575371897883],"type":"Point"}
}