{
  "type": "Feature",
  "properties": {
    "iso:country": "GB",
    "wof:name": "PO15 5LX",
    "wof:placetype": "postalcode"
  },
  "geometry": {"coordinates":[-1.214191,50.85178],"type":"Point"}
}
