{
  "type": "Feature",
  "properties": {
    "iso:country":"GB",
    "wof:name":"LE65 1EP",
    "wof:placetype":"postalcode"
},
  "geometry": {"coordinates":[-1.46353919715163,52.74126019793706],"type":"Point"}
}