{
  "type": "Feature",
  "properties": {
    "date:inception_lower":"1980-01-01",
    "date:inception_upper":"1980-01-31",
    "iso:country":"GB",
    "wof:name":"L10 2JR",
    "wof:placetype":"postalcode"
},
  "geometry": {"coordinates":[-2.944905,53.484075],"type":"Point"}
}