{
  "type": "Feature",
  "properties": {
    "iso:country":"GB",
    "wof:name":"L10 2JR",
    "wof:placetype":"postalcode"
},
  "geometry": {"coordinates":[-2.94490504032334,53.48407497122046],"type":"Point"}
}