{
  "type": "Feature",
  "properties": {
    "iso:country": "GB",
    "wof:name": "L10 2JR",
    "wof:placetype": "postalcode"
  },
  "geometry": {"coordinates":[-2.944905,53.484075],"type":"Point"}
}
