{
  "type": "Feature",
  "properties": {
    "iso:country": "GB",
    "wof:name": "B95 5HQ",
    "wof:placetype": "postalcode"
  },
  "geometry": {"coordinates":[-1.728204,52.311362],"type":"Point"}
}
