{
  "type": "Feature",
  "properties": {
    "iso:country":"GB",
    "wof:name":"HP21 8UE",
    "wof:placetype":"postalcode"
},
  "geometry": {"coordinates":[-0.82563585544931,51.81358100202483],"type":"Point"}
}