{
  "type": "Feature",
  "properties": {
    "iso:country":"GB",
    "wof:name":"CB7 5SJ",
    "wof:placetype":"postalcode"
},
  "geometry": {"coordinates":[0.41572326542672,52.34669821696758],"type":"Point"}
}