{
  "type": "Feature",
  "properties": {
    "iso:country":"GB",
    "wof:name":"LN3 5AB",
    "wof:placetype":"postalcode"
},
  "geometry": {"coordinates":[-0.3686197232012,53.32304818981703],"type":"Point"}
}