{
  "type": "Feature",
  "properties": {
    "iso:country": "GB",
    "wof:name": "LN3 5AB",
    "wof:placetype": "postalcode"
  },
  "geometry": {"coordinates":[-0.36862,53.323048],"type":"Point"}
}
