{
  "type": "Feature",
  "properties": {
    "iso:country":"GB",
    "wof:name":"SP2 0JU",
    "wof:placetype":"postalcode"
},
  "geometry": {"coordinates":[-1.86586738690112,51.07787758523813],"type":"Point"}
}