{
  "type": "Feature",
  "properties": {
    "iso:country":"GB",
    "wof:name":"SE5 7BJ",
    "wof:placetype":"postalcode"
},
  "geometry": {"coordinates":[-0.0912050057527,51.47438196744445],"type":"Point"}
}