{
  "type": "Feature",
  "properties": {
    "iso:country":"GB",
    "wof:name":"CM19 5NP",
    "wof:placetype":"postalcode"
},
  "geometry": {"coordinates":[0.07111507946309,51.75777229902985],"type":"Point"}
}