{
  "type": "Feature",
  "properties": {
    "date:inception_lower":"1980-01-01",
    "date:inception_upper":"1980-01-31",
    "iso:country":"GB",
    "wof:name":"TN17 4HT",
    "wof:placetype":"postalcode"
},
  "geometry": {"coordinates":[0.576913,51.052965],"type":"Point"}
}