{
  "type": "Feature",
  "properties": {
    "iso:country":"GB",
    "wof:name":"TN17 4HT",
    "wof:placetype":"postalcode"
},
  "geometry": {"coordinates":[0.57691264040396,51.05296514299368],"type":"Point"}
}