{
  "type": "Feature",
  "properties": {
    "iso:country": "GB",
    "wof:name": "CH65 5AZ",
    "wof:placetype": "postalcode"
  },
  "geometry": {"coordinates":[-2.89282,53.274144],"type":"Point"}
}
