{
  "type": "Feature",
  "properties": {
    "iso:country": "GB",
    "wof:name": "LN8 3LH",
    "wof:placetype": "postalcode"
  },
  "geometry": {"coordinates":[-0.362605,53.386001],"type":"Point"}
}
