{
  "type": "Feature",
  "properties": {
    "iso:country":"GB",
    "wof:name":"LN8 3LH",
    "wof:placetype":"postalcode"
},
  "geometry": {"coordinates":[-0.36260513023062,53.38600141799807],"type":"Point"}
}