{
  "type": "Feature",
  "properties": {
    "date:inception_lower": "1980-01-01",
    "date:inception_upper": "1980-01-01",
    "iso:country": "GB",
    "wof:name": "GL10 3BN",
    "wof:placetype": "postalcode"
  },
  "geometry": {"coordinates":[-2.327125,51.748137],"type":"Point"}
}
