{
  "type": "Feature",
  "properties": {
    "iso:country": "GB",
    "wof:name": "N11 3PW",
    "wof:placetype": "postalcode"
  },
  "geometry": {"coordinates":[-0.143116,51.611571],"type":"Point"}
}
