{
  "type": "Feature",
  "properties": {
    "iso:country":"GB",
    "wof:name":"N11 3PW",
    "wof:placetype":"postalcode"
},
  "geometry": {"coordinates":[-0.14242747226195,51.61172823014024],"type":"Point"}
}