{
  "type": "Feature",
  "properties": {
    "iso:country":"GB",
    "wof:name":"BN24 6HS",
    "wof:placetype":"postalcode"
},
  "geometry": {"coordinates":[0.34812746551143,50.81115708315778],"type":"Point"}
}