{
  "type": "Feature",
  "properties": {
    "iso:country":"GB",
    "wof:name":"BN17 5JG",
    "wof:placetype":"postalcode"
},
  "geometry": {"coordinates":[-0.53868684234202,50.80731793965253],"type":"Point"}
}