{
  "type": "Feature",
  "properties": {
    "iso:country": "GB",
    "wof:name": "GU6 8GU",
    "wof:placetype": "postalcode"
  },
  "geometry": {"coordinates":[-0.500776,51.139319],"type":"Point"}
}
