{
  "type": "Feature",
  "properties": {
    "iso:country": "GB",
    "wof:name": "M25 0GR",
    "wof:placetype": "postalcode"
  },
  "geometry": {"coordinates":[-2.259513,53.525075],"type":"Point"}
}
