{
  "type": "Feature",
  "properties": {
    "iso:country":"GB",
    "wof:name":"M25 0GR",
    "wof:placetype":"postalcode"
},
  "geometry": {"coordinates":[-2.25951255822713,53.52507454916092],"type":"Point"}
}