{
  "type": "Feature",
  "properties": {
    "date:inception_lower": "1980-01-01",
    "date:inception_upper": "1980-01-01",
    "iso:country": "GB",
    "wof:name": "G71 7DQ",
    "wof:placetype": "postalcode"
  },
  "geometry": {"coordinates":[-4.095176,55.825027],"type":"Point"}
}
