{
  "type": "Feature",
  "properties": {
    "iso:country":"GB",
    "wof:name":"PE11 3ED",
    "wof:placetype":"postalcode"
},
  "geometry": {"coordinates":[-0.16977786870948,52.74765600568912],"type":"Point"}
}