{
  "type": "Feature",
  "properties": {
    "iso:country": "GB",
    "wof:name": "PE11 3ED",
    "wof:placetype": "postalcode"
  },
  "geometry": {"coordinates":[-0.169778,52.747656],"type":"Point"}
}
