{
  "type": "Feature",
  "properties": {
    "iso:country": "GB",
    "wof:name": "TQ12 4FN",
    "wof:placetype": "postalcode"
  },
  "geometry": {"coordinates":[-3.583604,50.532923],"type":"Point"}
}
