{
  "type": "Feature",
  "properties": {
    "iso:country": "GB",
    "wof:name": "ML11 8RE",
    "wof:placetype": "postalcode"
  },
  "geometry": {"coordinates":[-3.662744,55.687805],"type":"Point"}
}
