{
  "type": "Feature",
  "properties": {
    "date:inception_lower":"1980-01-01",
    "date:inception_upper":"1980-01-31",
    "iso:country":"GB",
    "wof:name":"ML11 8RE",
    "wof:placetype":"postalcode"
},
  "geometry": {"coordinates":[-3.662744,55.687805],"type":"Point"}
}