{
  "type": "Feature",
  "properties": {
    "iso:country": "GB",
    "wof:name": "EH49 6JL",
    "wof:placetype": "postalcode"
  },
  "geometry": {"coordinates":[-3.654218,55.974181],"type":"Point"}
}
