{
  "type": "Feature",
  "properties": {
    "iso:country":"GB",
    "wof:name":"BD11 2PS",
    "wof:placetype":"postalcode"
},
  "geometry": {"coordinates":[-1.6846189932482,53.75988486075592],"type":"Point"}
}