{
  "type": "Feature",
  "properties": {
    "date:inception_lower": "2001-06-01",
    "date:inception_upper": "2001-06-01",
    "iso:country": "GB",
    "wof:name": "OX28 1EA",
    "wof:placetype": "postalcode"
  },
  "geometry": {"coordinates":[-1.475958,51.79319],"type":"Point"}
}
