{
  "type": "Feature",
  "properties": {
    "iso:country":"GB",
    "wof:name":"OX28 1EA",
    "wof:placetype":"postalcode"
},
  "geometry": {"coordinates":[-1.47595811003161,51.79319042672292],"type":"Point"}
}