{
  "type": "Feature",
  "properties": {
    "iso:country": "GB",
    "wof:name": "NR11 6NW",
    "wof:placetype": "postalcode"
  },
  "geometry": {"coordinates":[1.175635,52.826581],"type":"Point"}
}
