{
  "type": "Feature",
  "properties": {
    "date:inception_lower":"1984-10-01",
    "date:inception_upper":"1984-10-31",
    "iso:country":"GB",
    "wof:name":"NR11 6NW",
    "wof:placetype":"postalcode"
},
  "geometry": {"coordinates":[1.175635,52.826581],"type":"Point"}
}