{
  "type": "Feature",
  "properties": {
    "date:inception_lower": "2010-08-01",
    "date:inception_upper": "2010-08-01",
    "iso:country": "GB",
    "wof:name": "BD1 2SA",
    "wof:placetype": "postalcode"
  },
  "geometry": {"coordinates":[-1.75681,53.792976],"type":"Point"}
}
