{
  "type": "Feature",
  "properties": {
    "iso:country": "GB",
    "wof:name": "TN29 9JN",
    "wof:placetype": "postalcode"
  },
  "geometry": {"coordinates":[0.884454,50.944631],"type":"Point"}
}
