{
  "type": "Feature",
  "properties": {
    "date:inception_lower": "1980-01-01",
    "date:inception_upper": "1980-01-01",
    "iso:country": "GB",
    "wof:name": "CO7 6NJ",
    "wof:placetype": "postalcode"
  },
  "geometry": {"coordinates":[0.988899,51.996709],"type":"Point"}
}
