{
  "type": "Feature",
  "properties": {
    "iso:country":"GB",
    "wof:name":"CO7 6NJ",
    "wof:placetype":"postalcode"
},
  "geometry": {"coordinates":[0.98885417614275,51.99669632344357],"type":"Point"}
}