{
  "type": "Feature",
  "properties": {
    "date:inception_lower":"1980-01-01",
    "date:inception_upper":"1980-01-31",
    "iso:country":"GB",
    "wof:name":"PO7 5JS",
    "wof:placetype":"postalcode"
},
  "geometry": {"coordinates":[-1.036618,50.857995],"type":"Point"}
}