{
  "type": "Feature",
  "properties": {
    "iso:country": "GB",
    "wof:name": "PO7 5JS",
    "wof:placetype": "postalcode"
  },
  "geometry": {"coordinates":[-1.036618,50.857995],"type":"Point"}
}
