{
  "type": "Feature",
  "properties": {
    "date:inception_lower":"1994-05-01",
    "date:inception_upper":"1994-05-31",
    "iso:country":"GB",
    "wof:name":"SA6 5TF",
    "wof:placetype":"postalcode"
},
  "geometry": {"coordinates":[-3.916296,51.716715],"type":"Point"}
}