{
  "type": "Feature",
  "properties": {
    "iso:country": "GB",
    "wof:name": "SA6 5TF",
    "wof:placetype": "postalcode"
  },
  "geometry": {"coordinates":[-3.916296,51.716715],"type":"Point"}
}
