{
  "type": "Feature",
  "properties": {
    "date:inception_lower":"2010-10-01",
    "date:inception_upper":"2010-10-31",
    "iso:country":"GB",
    "wof:name":"DD10 0AF",
    "wof:placetype":"postalcode"
},
  "geometry": {"coordinates":[-2.47847,56.770044],"type":"Point"}
}