{
  "type": "Feature",
  "properties": {
    "iso:country":"GB",
    "wof:name":"DD10 0AF",
    "wof:placetype":"postalcode"
},
  "geometry": {"coordinates":[-2.47846991834084,56.77004371223828],"type":"Point"}
}