{
  "type": "Feature",
  "properties": {
    "iso:country":"GB",
    "wof:name":"PO12 1QJ",
    "wof:placetype":"postalcode"
},
  "geometry": {"coordinates":[-1.13789648431408,50.79060386150495],"type":"Point"}
}