{
  "type": "Feature",
  "properties": {
    "date:inception_lower": "1980-01-01",
    "date:inception_upper": "1980-01-01",
    "iso:country": "GB",
    "wof:name": "BN20 9AA",
    "wof:placetype": "postalcode"
  },
  "geometry": {"coordinates":[0.254919,50.789037],"type":"Point"}
}
