{
  "type": "Feature",
  "properties": {
    "iso:country":"GB",
    "wof:name":"HR2 0SX",
    "wof:placetype":"postalcode"
},
  "geometry": {"coordinates":[-2.98895809126179,52.03228245807913],"type":"Point"}
}