{
  "type": "Feature",
  "properties": {
    "iso:country":"GB",
    "wof:name":"LS15 7AX",
    "wof:placetype":"postalcode"
},
  "geometry": {"coordinates":[-1.44574857360679,53.79807232440881],"type":"Point"}
}