{
  "type": "Feature",
  "properties": {
    "iso:country":"GB",
    "wof:name":"E1 6QQ",
    "wof:placetype":"postalcode"
},
  "geometry": {"coordinates":[-0.07397437388001,51.51969270228624],"type":"Point"}
}