{
  "type": "Feature",
  "properties": {
    "iso:country": "GB",
    "wof:name": "E1 6QQ",
    "wof:placetype": "postalcode"
  },
  "geometry": {"coordinates":[-0.07402,51.519704],"type":"Point"}
}
