{
  "type": "Feature",
  "properties": {
    "iso:country":"GB",
    "wof:name":"EX14 3NY",
    "wof:placetype":"postalcode"
},
  "geometry": {"coordinates":[-3.21949242678175,50.7975542838073],"type":"Point"}
}