{
  "type": "Feature",
  "properties": {
    "iso:country":"GB",
    "wof:name":"NE4 5TN",
    "wof:placetype":"postalcode"
},
  "geometry": {"coordinates":[-1.62283956699684,54.97351281470168],"type":"Point"}
}