{
  "type": "Feature",
  "properties": {
    "iso:country":"GB",
    "wof:name":"SO40 3PD",
    "wof:placetype":"postalcode"
},
  "geometry": {"coordinates":[-1.49871177825957,50.92660122403925],"type":"Point"}
}