{
  "type": "Feature",
  "properties": {
    "iso:country": "GB",
    "wof:name": "SO40 3PD",
    "wof:placetype": "postalcode"
  },
  "geometry": {"coordinates":[-1.498712,50.926601],"type":"Point"}
}
