{
  "type": "Feature",
  "properties": {
    "iso:country":"GB",
    "wof:name":"PE22 9QH",
    "wof:placetype":"postalcode"
},
  "geometry": {"coordinates":[0.07714624462468,53.05307363967538],"type":"Point"}
}