{
  "type": "Feature",
  "properties": {
    "iso:country":"GB",
    "wof:name":"SW18 3QX",
    "wof:placetype":"postalcode"
},
  "geometry": {"coordinates":[-0.18222647064648,51.43850039622484],"type":"Point"}
}