{
  "type": "Feature",
  "properties": {
    "date:inception_lower": "1980-01-01",
    "date:inception_upper": "1980-01-01",
    "iso:country": "GB",
    "wof:name": "B75 5ND",
    "wof:placetype": "postalcode"
  },
  "geometry": {"coordinates":[-1.815516,52.590637],"type":"Point"}
}
