{
  "type": "Feature",
  "properties": {
    "iso:country":"GB",
    "wof:name":"B75 5ND",
    "wof:placetype":"postalcode"
},
  "geometry": {"coordinates":[-1.81551607494665,52.59063715162854],"type":"Point"}
}