{
  "type": "Feature",
  "properties": {
    "iso:country":"GB",
    "wof:name":"DL12 0UE",
    "wof:placetype":"postalcode"
},
  "geometry": {"coordinates":[-2.13920896360852,54.64858169747338],"type":"Point"}
}