{
  "type": "Feature",
  "properties": {
    "iso:country": "GB",
    "wof:name": "DL12 0UE",
    "wof:placetype": "postalcode"
  },
  "geometry": {"coordinates":[-2.139209,54.648582],"type":"Point"}
}
