{
  "type": "Feature",
  "properties": {
    "iso:country":"GB",
    "wof:name":"SL6 6DN",
    "wof:placetype":"postalcode"
},
  "geometry": {"coordinates":[-0.74197666443718,51.52483763017217],"type":"Point"}
}