{
  "type": "Feature",
  "properties": {
    "iso:country": "GB",
    "wof:name": "SL6 6DN",
    "wof:placetype": "postalcode"
  },
  "geometry": {"coordinates":[-0.741977,51.524838],"type":"Point"}
}
