{
  "type": "Feature",
  "properties": {
    "iso:country":"GB",
    "wof:name":"CR8 4HP",
    "wof:placetype":"postalcode"
},
  "geometry": {"coordinates":[-0.12772348327235,51.32721213035578],"type":"Point"}
}