{
  "type": "Feature",
  "properties": {
    "iso:country":"GB",
    "wof:name":"EH12 5JU",
    "wof:placetype":"postalcode"
},
  "geometry": {"coordinates":[-3.2200078746755,55.94648278133106],"type":"Point"}
}