{
  "type": "Feature",
  "properties": {
    "iso:country": "GB",
    "wof:name": "NE23 7HN",
    "wof:placetype": "postalcode"
  },
  "geometry": {"coordinates":[-1.594197,55.056345],"type":"Point"}
}
