{
  "type": "Feature",
  "properties": {
    "iso:country": "GB",
    "wof:name": "LL14 2EG",
    "wof:placetype": "postalcode"
  },
  "geometry": {"coordinates":[-3.066876,52.998906],"type":"Point"}
}
