{
  "type": "Feature",
  "properties": {
    "iso:country":"GB",
    "wof:name":"SK2 6EW",
    "wof:placetype":"postalcode"
},
  "geometry": {"coordinates":[-2.1449488123374,53.39252674278701],"type":"Point"}
}