{
  "type": "Feature",
  "properties": {
    "date:inception_lower":"1980-01-01",
    "date:inception_upper":"1980-01-31",
    "iso:country":"GB",
    "wof:name":"NG8 2QG",
    "wof:placetype":"postalcode"
},
  "geometry": {"coordinates":[-1.22783,52.948978],"type":"Point"}
}