{
  "type": "Feature",
  "properties": {
    "iso:country": "GB",
    "wof:name": "NG8 2QG",
    "wof:placetype": "postalcode"
  },
  "geometry": {"coordinates":[-1.22783,52.948978],"type":"Point"}
}
