{
  "type": "Feature",
  "properties": {
    "iso:country":"GB",
    "wof:name":"NG8 2QG",
    "wof:placetype":"postalcode"
},
  "geometry": {"coordinates":[-1.22783009733811,52.94897808443945],"type":"Point"}
}