{
  "type": "Feature",
  "properties": {
    "iso:country": "GB",
    "wof:name": "BN21 3UE",
    "wof:placetype": "postalcode"
  },
  "geometry": {"coordinates":[0.279705,50.770045],"type":"Point"}
}
