{
  "type": "Feature",
  "properties": {
    "iso:country": "GB",
    "wof:name": "BA1 7QQ",
    "wof:placetype": "postalcode"
  },
  "geometry": {"coordinates":[-2.304706,51.403746],"type":"Point"}
}
