{
  "type": "Feature",
  "properties": {
    "iso:country":"GB",
    "wof:name":"BA1 7QQ",
    "wof:placetype":"postalcode"
},
  "geometry": {"coordinates":[-2.30470585473083,51.40374632044203],"type":"Point"}
}