{
  "type": "Feature",
  "properties": {
    "iso:country":"GB",
    "wof:name":"BN15 8AZ",
    "wof:placetype":"postalcode"
},
  "geometry": {"coordinates":[-0.32493884815728,50.82158596487371],"type":"Point"}
}