{
  "type": "Feature",
  "properties": {
    "iso:country":"GB",
    "wof:name":"SA15 5YT",
    "wof:placetype":"postalcode"
},
  "geometry": {"coordinates":[-4.18909209256061,51.72879891700887],"type":"Point"}
}