{
  "type": "Feature",
  "properties": {
    "iso:country":"GB",
    "wof:name":"AB16 5YB",
    "wof:placetype":"postalcode"
},
  "geometry": {"coordinates":[-2.14154757614297,57.16026211818231],"type":"Point"}
}