{
  "type": "Feature",
  "properties": {
    "iso:country":"GB",
    "wof:name":"PR1 1UP",
    "wof:placetype":"postalcode"
},
  "geometry": {"coordinates":[-2.69125133743143,53.76268180949651],"type":"Point"}
}