{
  "type": "Feature",
  "properties": {
    "date:inception_lower":"1991-01-01",
    "date:inception_upper":"1991-01-31",
    "iso:country":"GB",
    "wof:name":"SA18 1HB",
    "wof:placetype":"postalcode"
},
  "geometry": {"coordinates":[-3.883337,51.79162],"type":"Point"}
}