{
  "type": "Feature",
  "properties": {
    "iso:country":"GB",
    "wof:name":"SA18 1HB",
    "wof:placetype":"postalcode"
},
  "geometry": {"coordinates":[-3.88324585151683,51.79157879346515],"type":"Point"}
}