{
  "type": "Feature",
  "properties": {
    "iso:country": "GB",
    "wof:name": "SA18 1HB",
    "wof:placetype": "postalcode"
  },
  "geometry": {"coordinates":[-3.883337,51.79162],"type":"Point"}
}
