{
  "type": "Feature",
  "properties": {
    "iso:country":"GB",
    "wof:name":"BR3 5AU",
    "wof:placetype":"postalcode"
},
  "geometry": {"coordinates":[-0.02258871842344,51.41276861328019],"type":"Point"}
}