{
  "type": "Feature",
  "properties": {
    "date:inception_lower": "1995-12-01",
    "date:inception_upper": "1995-12-01",
    "iso:country": "GB",
    "wof:name": "BR3 5AU",
    "wof:placetype": "postalcode"
  },
  "geometry": {"coordinates":[-0.022562,51.412768],"type":"Point"}
}
