{
  "type": "Feature",
  "properties": {
    "iso:country":"GB",
    "wof:name":"N17 8EJ",
    "wof:placetype":"postalcode"
},
  "geometry": {"coordinates":[-0.07506172899166,51.60802602785172],"type":"Point"}
}