{
  "type": "Feature",
  "properties": {
    "iso:country":"GB",
    "wof:name":"S71 2LD",
    "wof:placetype":"postalcode"
},
  "geometry": {"coordinates":[-1.44560007605355,53.5671454082829],"type":"Point"}
}