{
  "type": "Feature",
  "properties": {
    "iso:country": "GB",
    "wof:name": "S71 2LD",
    "wof:placetype": "postalcode"
  },
  "geometry": {"coordinates":[-1.4456,53.567145],"type":"Point"}
}
