{
  "type": "Feature",
  "properties": {
    "iso:country": "GB",
    "wof:name": "WA15 7QG",
    "wof:placetype": "postalcode"
  },
  "geometry": {"coordinates":[-2.328278,53.390033],"type":"Point"}
}
