{
  "type": "Feature",
  "properties": {
    "iso:country":"GB",
    "wof:name":"WA15 7QG",
    "wof:placetype":"postalcode"
},
  "geometry": {"coordinates":[-2.32827764745574,53.39003275069059],"type":"Point"}
}