{
  "type": "Feature",
  "properties": {
    "date:inception_lower": "1980-01-01",
    "date:inception_upper": "1980-01-01",
    "iso:country": "GB",
    "wof:name": "NR31 8QN",
    "wof:placetype": "postalcode"
  },
  "geometry": {"coordinates":[1.6964,52.575328],"type":"Point"}
}
