{
  "type": "Feature",
  "properties": {
    "iso:country":"GB",
    "wof:name":"NR31 8QN",
    "wof:placetype":"postalcode"
},
  "geometry": {"coordinates":[1.69639978068754,52.5753279012016],"type":"Point"}
}