{
  "type": "Feature",
  "properties": {
    "iso:country":"GB",
    "wof:name":"AL7 4BP",
    "wof:placetype":"postalcode"
},
  "geometry": {"coordinates":[-0.18689218758583,51.78709683338871],"type":"Point"}
}