{
  "type": "Feature",
  "properties": {
    "iso:country": "GB",
    "wof:name": "CF64 4PP",
    "wof:placetype": "postalcode"
  },
  "geometry": {"coordinates":[-3.204554,51.435052],"type":"Point"}
}
