{
  "type": "Feature",
  "properties": {
    "iso:country":"GB",
    "wof:name":"CF64 4PP",
    "wof:placetype":"postalcode"
},
  "geometry": {"coordinates":[-3.20455831118162,51.43503326370248],"type":"Point"}
}