{
  "type": "Feature",
  "properties": {
    "iso:country":"GB",
    "wof:name":"S62 5EL",
    "wof:placetype":"postalcode"
},
  "geometry": {"coordinates":[-1.33151555964975,53.46712211383272],"type":"Point"}
}