{
  "type": "Feature",
  "properties": {
    "iso:country": "GB",
    "wof:name": "GU3 1HG",
    "wof:placetype": "postalcode"
  },
  "geometry": {"coordinates":[-0.585748,51.222672],"type":"Point"}
}
