{
  "type": "Feature",
  "properties": {
    "iso:country":"GB",
    "wof:name":"GU21 4UL",
    "wof:placetype":"postalcode"
},
  "geometry": {"coordinates":[-0.57776033980908,51.32612277228188],"type":"Point"}
}