{
  "type": "Feature",
  "properties": {
    "iso:country": "GB",
    "wof:name": "CM22 7DX",
    "wof:placetype": "postalcode"
  },
  "geometry": {"coordinates":[0.20342,51.813609],"type":"Point"}
}
