{
  "type": "Feature",
  "properties": {
    "iso:country":"GB",
    "wof:name":"CM22 7DX",
    "wof:placetype":"postalcode"
},
  "geometry": {"coordinates":[0.20330455418068,51.8135771061627],"type":"Point"}
}