{
  "type": "Feature",
  "properties": {
    "iso:country":"GB",
    "wof:name":"WS11 4NN",
    "wof:placetype":"postalcode"
},
  "geometry": {"coordinates":[-2.02876094062186,52.71006115854509],"type":"Point"}
}