{
  "type": "Feature",
  "properties": {
    "iso:country":"GB",
    "wof:name":"SN10 4HN",
    "wof:placetype":"postalcode"
},
  "geometry": {"coordinates":[-1.99457368407837,51.28233232812862],"type":"Point"}
}