{
  "type": "Feature",
  "properties": {
    "iso:country":"GB",
    "wof:name":"PE11 1ST",
    "wof:placetype":"postalcode"
},
  "geometry": {"coordinates":[-0.1507327328556,52.78698288934629],"type":"Point"}
}