{
  "type": "Feature",
  "properties": {
    "iso:country":"GB",
    "wof:name":"BB2 4SP",
    "wof:placetype":"postalcode"
},
  "geometry": {"coordinates":[-2.51575188507846,53.73126229241786],"type":"Point"}
}