{
  "type": "Feature",
  "properties": {
    "iso:country":"GB",
    "wof:name":"DD1 5BY",
    "wof:placetype":"postalcode"
},
  "geometry": {"coordinates":[-2.98487850178574,56.46194714104244],"type":"Point"}
}