{
  "type": "Feature",
  "properties": {
    "iso:country":"GB",
    "wof:name":"RM4 1QA",
    "wof:placetype":"postalcode"
},
  "geometry": {"coordinates":[0.18687784354427,51.62298796237876],"type":"Point"}
}