{
  "type": "Feature",
  "properties": {
    "iso:country": "GB",
    "wof:name": "SM6 9BF",
    "wof:placetype": "postalcode"
  },
  "geometry": {"coordinates":[-0.134305,51.35434],"type":"Point"}
}
