{
  "type": "Feature",
  "properties": {
    "iso:country":"GB",
    "wof:name":"SM6 9BF",
    "wof:placetype":"postalcode"
},
  "geometry": {"coordinates":[-0.13406375791493,51.3545343815021],"type":"Point"}
}