{
  "type": "Feature",
  "properties": {
    "iso:country": "GB",
    "wof:name": "EX34 8ED",
    "wof:placetype": "postalcode"
  },
  "geometry": {"coordinates":[-4.130835,51.204847],"type":"Point"}
}
