{
  "type": "Feature",
  "properties": {
    "iso:country":"GB",
    "wof:name":"EN5 2FN",
    "wof:placetype":"postalcode"
},
  "geometry": {"coordinates":[-0.20050482654899,51.64455549653114],"type":"Point"}
}