{
  "type": "Feature",
  "properties": {
    "iso:country":"GB",
    "wof:name":"HD4 5SN",
    "wof:placetype":"postalcode"
},
  "geometry": {"coordinates":[-1.82366078909874,53.63743696408149],"type":"Point"}
}