{
  "type": "Feature",
  "properties": {
    "iso:country":"GB",
    "wof:name":"WD6 4AT",
    "wof:placetype":"postalcode"
},
  "geometry": {"coordinates":[-0.2864223289823,51.66011129340172],"type":"Point"}
}