{
  "type": "Feature",
  "properties": {
    "iso:country": "GB",
    "wof:name": "HA9 9QW",
    "wof:placetype": "postalcode"
  },
  "geometry": {"coordinates":[-0.284553,51.569038],"type":"Point"}
}
