{
  "type": "Feature",
  "properties": {
    "iso:country":"GB",
    "wof:name":"NW4 1TN",
    "wof:placetype":"postalcode"
},
  "geometry": {"coordinates":[-0.21833921284879,51.59331972735912],"type":"Point"}
}