{
  "type": "Feature",
  "properties": {
    "iso:country":"GB",
    "wof:name":"BD3 7AW",
    "wof:placetype":"postalcode"
},
  "geometry": {"coordinates":[-1.70669579993598,53.80023414002384],"type":"Point"}
}