{
  "type": "Feature",
  "properties": {
    "iso:country":"GB",
    "wof:name":"PE22 7JE",
    "wof:placetype":"postalcode"
},
  "geometry": {"coordinates":[-0.08163884495399,53.10089935451594],"type":"Point"}
}