{
  "type": "Feature",
  "properties": {
    "iso:country":"GB",
    "wof:name":"PO14 3TR",
    "wof:placetype":"postalcode"
},
  "geometry": {"coordinates":[-1.22281887549592,50.83012974650247],"type":"Point"}
}