{
  "type": "Feature",
  "properties": {
    "date:inception_lower": "1984-10-01",
    "date:inception_upper": "1984-10-01",
    "iso:country": "GB",
    "wof:name": "PO14 3TR",
    "wof:placetype": "postalcode"
  },
  "geometry": {"coordinates":[-1.222819,50.83013],"type":"Point"}
}
