{
  "type": "Feature",
  "properties": {
    "iso:country": "GB",
    "wof:name": "PO14 3TR",
    "wof:placetype": "postalcode"
  },
  "geometry": {"coordinates":[-1.222819,50.83013],"type":"Point"}
}
