{
  "type": "Feature",
  "properties": {
    "iso:country":"GB",
    "wof:name":"TS3 7DE",
    "wof:placetype":"postalcode"
},
  "geometry": {"coordinates":[-1.21100759861063,54.55787753172474],"type":"Point"}
}