{
  "type": "Feature",
  "properties": {
    "date:inception_lower": "1980-01-01",
    "date:inception_upper": "1980-01-01",
    "iso:country": "GB",
    "wof:name": "TS3 7DE",
    "wof:placetype": "postalcode"
  },
  "geometry": {"coordinates":[-1.211022,54.557891],"type":"Point"}
}
