{
  "type": "Feature",
  "properties": {
    "iso:country":"GB",
    "wof:name":"LE2 3RG",
    "wof:placetype":"postalcode"
},
  "geometry": {"coordinates":[-1.09778378072451,52.6060183311839],"type":"Point"}
}