{
  "type": "Feature",
  "properties": {
    "date:inception_lower": "1996-06-01",
    "date:inception_upper": "1996-06-01",
    "iso:country": "GB",
    "wof:name": "AB54 6HX",
    "wof:placetype": "postalcode"
  },
  "geometry": {"coordinates":[-2.772692,57.443733],"type":"Point"}
}
