{
  "type": "Feature",
  "properties": {
    "iso:country": "GB",
    "wof:name": "SE13 6SA",
    "wof:placetype": "postalcode"
  },
  "geometry": {"coordinates":[-0.008674,51.451022],"type":"Point"}
}
