{
  "type": "Feature",
  "properties": {
    "iso:country":"GB",
    "wof:name":"BS36 2LU",
    "wof:placetype":"postalcode"
},
  "geometry": {"coordinates":[-2.46748503433939,51.52484791052613],"type":"Point"}
}