{
  "type": "Feature",
  "properties": {
    "iso:country": "GB",
    "wof:name": "SO40 2NT",
    "wof:placetype": "postalcode"
  },
  "geometry": {"coordinates":[-1.591183,50.931917],"type":"Point"}
}
