{
  "type": "Feature",
  "properties": {
    "iso:country":"GB",
    "wof:name":"SO40 2NT",
    "wof:placetype":"postalcode"
},
  "geometry": {"coordinates":[-1.59057499539176,50.92608696938642],"type":"Point"}
}