{
  "type": "Feature",
  "properties": {
    "iso:country":"GB",
    "wof:name":"NG14 6DL",
    "wof:placetype":"postalcode"
},
  "geometry": {"coordinates":[-1.04977213108217,53.02271482250249],"type":"Point"}
}