{
  "type": "Feature",
  "properties": {
    "date:inception_lower": "2021-12-01",
    "date:inception_upper": "2021-12-01",
    "iso:country": "GB",
    "wof:name": "SN15 4FJ",
    "wof:placetype": "postalcode"
  },
  "geometry": {"coordinates":[-2.061231,51.511459],"type":"Point"}
}
