{
  "type": "Feature",
  "properties": {
    "iso:country":"GB",
    "wof:name":"BB2 6JL",
    "wof:placetype":"postalcode"
},
  "geometry": {"coordinates":[-2.50524988462545,53.75294151456009],"type":"Point"}
}