{
  "type": "Feature",
  "properties": {
    "iso:country": "GB",
    "wof:name": "BB2 6JL",
    "wof:placetype": "postalcode"
  },
  "geometry": {"coordinates":[-2.50525,53.752942],"type":"Point"}
}
