{
  "type": "Feature",
  "properties": {
    "date:inception_lower":"1980-01-01",
    "date:inception_upper":"1980-01-31",
    "iso:country":"GB",
    "wof:name":"BB2 6JL",
    "wof:placetype":"postalcode"
},
  "geometry": {"coordinates":[-2.50525,53.752942],"type":"Point"}
}