{
  "type": "Feature",
  "properties": {
    "iso:country":"GB",
    "wof:name":"SW16 5RU",
    "wof:placetype":"postalcode"
},
  "geometry": {"coordinates":[-0.12954045909115,51.42007292941734],"type":"Point"}
}