{
  "type": "Feature",
  "properties": {
    "iso:country": "GB",
    "wof:name": "PA12 4EW",
    "wof:placetype": "postalcode"
  },
  "geometry": {"coordinates":[-4.622472,55.799494],"type":"Point"}
}
