{
  "type": "Feature",
  "properties": {
    "iso:country":"GB",
    "wof:name":"SL5 0WL",
    "wof:placetype":"postalcode"
},
  "geometry": {"coordinates":[-0.65342007905138,51.40178727106648],"type":"Point"}
}