{
  "type": "Feature",
  "properties": {
    "iso:country":"GB",
    "wof:name":"DT11 8TF",
    "wof:placetype":"postalcode"
},
  "geometry": {"coordinates":[-2.19635218787383,50.8850034705337],"type":"Point"}
}