{
  "type": "Feature",
  "properties": {
    "date:inception_lower":"1980-01-01",
    "date:inception_upper":"1980-01-31",
    "iso:country":"GB",
    "wof:name":"DT11 8TF",
    "wof:placetype":"postalcode"
},
  "geometry": {"coordinates":[-2.196352,50.885003],"type":"Point"}
}