{
  "type": "Feature",
  "properties": {
    "iso:country": "GB",
    "wof:name": "LN8 2AU",
    "wof:placetype": "postalcode"
  },
  "geometry": {"coordinates":[-0.548234,53.398237],"type":"Point"}
}
