{
  "type": "Feature",
  "properties": {
    "iso:country":"GB",
    "wof:name":"LN8 2AU",
    "wof:placetype":"postalcode"
},
  "geometry": {"coordinates":[-0.54839901468064,53.39957877814979],"type":"Point"}
}