{
  "type": "Feature",
  "properties": {
    "date:inception_lower": "1996-12-01",
    "date:inception_upper": "1996-12-01",
    "iso:country": "GB",
    "wof:name": "LN8 2AU",
    "wof:placetype": "postalcode"
  },
  "geometry": {"coordinates":[-0.548234,53.398237],"type":"Point"}
}
