{
  "type": "Feature",
  "properties": {
    "iso:country":"GB",
    "wof:name":"LE65 1JD",
    "wof:placetype":"postalcode"
},
  "geometry": {"coordinates":[-1.4518508030523,52.74729278498452],"type":"Point"}
}