{
  "type": "Feature",
  "properties": {
    "iso:country": "GB",
    "wof:name": "DH7 0NP",
    "wof:placetype": "postalcode"
  },
  "geometry": {"coordinates":[-1.734849,54.816781],"type":"Point"}
}
