{
  "type": "Feature",
  "properties": {
    "date:inception_lower": "1990-02-01",
    "date:inception_upper": "1990-02-01",
    "iso:country": "GB",
    "wof:name": "DH7 0NP",
    "wof:placetype": "postalcode"
  },
  "geometry": {"coordinates":[-1.734849,54.816781],"type":"Point"}
}
