{
  "type": "Feature",
  "properties": {
    "iso:country":"GB",
    "wof:name":"DH7 0NP",
    "wof:placetype":"postalcode"
},
  "geometry": {"coordinates":[-1.73484890898053,54.81678096889323],"type":"Point"}
}