{
  "type": "Feature",
  "properties": {
    "iso:country": "GB",
    "wof:name": "GL51 3JE",
    "wof:placetype": "postalcode"
  },
  "geometry": {"coordinates":[-2.117542,51.8873],"type":"Point"}
}
