{
  "type": "Feature",
  "properties": {
    "date:inception_lower":"2000-10-01",
    "date:inception_upper":"2000-10-31",
    "iso:country":"GB",
    "wof:name":"GL51 3JE",
    "wof:placetype":"postalcode"
},
  "geometry": {"coordinates":[-2.117542,51.8873],"type":"Point"}
}