{
  "type": "Feature",
  "properties": {
    "iso:country":"GB",
    "wof:name":"TR7 1NG",
    "wof:placetype":"postalcode"
},
  "geometry": {"coordinates":[-5.09443566156735,50.40927851364033],"type":"Point"}
}