{
  "type": "Feature",
  "properties": {
    "iso:country": "GB",
    "wof:name": "WD18 0AF",
    "wof:placetype": "postalcode"
  },
  "geometry": {"coordinates":[-0.400391,51.65698],"type":"Point"}
}
