{
  "type": "Feature",
  "properties": {
    "iso:country":"GB",
    "wof:name":"B10 9QZ",
    "wof:placetype":"postalcode"
},
  "geometry": {"coordinates":[-1.8607653542143,52.47189754135277],"type":"Point"}
}