{
  "type": "Feature",
  "properties": {
    "date:inception_lower":"1990-02-01",
    "date:inception_upper":"1990-02-28",
    "iso:country":"GB",
    "wof:name":"TW4 5EH",
    "wof:placetype":"postalcode"
},
  "geometry": {"coordinates":[-0.381036,51.461899],"type":"Point"}
}