{
  "type": "Feature",
  "properties": {
    "date:inception_lower": "1984-02-01",
    "date:inception_upper": "1984-02-01",
    "iso:country": "GB",
    "wof:name": "GU9 9PR",
    "wof:placetype": "postalcode"
  },
  "geometry": {"coordinates":[-0.784528,51.217729],"type":"Point"}
}
