{
  "type": "Feature",
  "properties": {
    "iso:country":"GB",
    "wof:name":"B94 5EJ",
    "wof:placetype":"postalcode"
},
  "geometry": {"coordinates":[-1.85711367213013,52.35363784358699],"type":"Point"}
}