{
  "type": "Feature",
  "properties": {
    "iso:country": "GB",
    "wof:name": "B94 5EJ",
    "wof:placetype": "postalcode"
  },
  "geometry": {"coordinates":[-1.857114,52.353638],"type":"Point"}
}
