{
  "type": "Feature",
  "properties": {
    "iso:country":"GB",
    "wof:name":"NR13 4TB",
    "wof:placetype":"postalcode"
},
  "geometry": {"coordinates":[1.49958908456161,52.63090859270727],"type":"Point"}
}