{
  "type": "Feature",
  "properties": {
    "iso:country":"GB",
    "wof:name":"ME10 2TT",
    "wof:placetype":"postalcode"
},
  "geometry": {"coordinates":[0.74813057628871,51.35885667487853],"type":"Point"}
}