{
  "type": "Feature",
  "properties": {
    "iso:country": "GB",
    "wof:name": "ME10 2TT",
    "wof:placetype": "postalcode"
  },
  "geometry": {"coordinates":[0.748131,51.358857],"type":"Point"}
}
