{
  "type": "Feature",
  "properties": {
    "iso:country": "GB",
    "wof:name": "LE4 3JY",
    "wof:placetype": "postalcode"
  },
  "geometry": {"coordinates":[-1.13635,52.682801],"type":"Point"}
}
