{
  "type": "Feature",
  "properties": {
    "iso:country":"GB",
    "wof:name":"LE4 3JY",
    "wof:placetype":"postalcode"
},
  "geometry": {"coordinates":[-1.13635001598529,52.68280141395673],"type":"Point"}
}