{
  "type": "Feature",
  "properties": {
    "date:inception_lower": "1980-01-01",
    "date:inception_upper": "1980-01-01",
    "iso:country": "GB",
    "wof:name": "LE4 3JY",
    "wof:placetype": "postalcode"
  },
  "geometry": {"coordinates":[-1.13635,52.682801],"type":"Point"}
}
