{
  "type": "Feature",
  "properties": {
    "date:inception_lower": "2023-10-01",
    "date:inception_upper": "2023-10-01",
    "iso:country": "GB",
    "wof:name": "WF10 9EW",
    "wof:placetype": "postalcode"
  },
  "geometry": {"coordinates":[-1.390336,53.716452],"type":"Point"}
}
