{
  "type": "Feature",
  "properties": {
    "iso:country":"GB",
    "wof:name":"SR1 3EB",
    "wof:placetype":"postalcode"
},
  "geometry": {"coordinates":[-1.38639284449481,54.90620358114928],"type":"Point"}
}