{
  "type": "Feature",
  "properties": {
    "iso:country": "GB",
    "wof:name": "HG3 3HP",
    "wof:placetype": "postalcode"
  },
  "geometry": {"coordinates":[-1.615395,54.057025],"type":"Point"}
}
