{
  "type": "Feature",
  "properties": {
    "iso:country":"GB",
    "wof:name":"HG3 3HP",
    "wof:placetype":"postalcode"
},
  "geometry": {"coordinates":[-1.61535834031829,54.05698291184354],"type":"Point"}
}