{
  "type": "Feature",
  "properties": {
    "iso:country":"GB",
    "wof:name":"TN30 7EX",
    "wof:placetype":"postalcode"
},
  "geometry": {"coordinates":[0.7251766184836,51.00161568249231],"type":"Point"}
}