{
  "type": "Feature",
  "properties": {
    "iso:country":"GB",
    "wof:name":"GL6 6LD",
    "wof:placetype":"postalcode"
},
  "geometry": {"coordinates":[-2.22350520380252,51.75525774179727],"type":"Point"}
}