{
  "type": "Feature",
  "properties": {
    "iso:country":"GB",
    "wof:name":"CA2 7NF",
    "wof:placetype":"postalcode"
},
  "geometry": {"coordinates":[-2.97327233483836,54.89765097096376],"type":"Point"}
}