{
  "type": "Feature",
  "properties": {
    "iso:country":"GB",
    "wof:name":"YO16 4TQ",
    "wof:placetype":"postalcode"
},
  "geometry": {"coordinates":[-0.21394956990709,54.08372753150082],"type":"Point"}
}