{
  "type": "Feature",
  "properties": {
    "iso:country": "GB",
    "wof:name": "YO16 4TQ",
    "wof:placetype": "postalcode"
  },
  "geometry": {"coordinates":[-0.21395,54.083728],"type":"Point"}
}
