{
  "type": "Feature",
  "properties": {
    "iso:country":"GB",
    "wof:name":"BB11 4LS",
    "wof:placetype":"postalcode"
},
  "geometry": {"coordinates":[-2.25452208584535,53.78644405653827],"type":"Point"}
}