{
  "type": "Feature",
  "properties": {
    "date:inception_lower": "1980-01-01",
    "date:inception_upper": "1980-01-01",
    "iso:country": "GB",
    "wof:name": "BB11 4LS",
    "wof:placetype": "postalcode"
  },
  "geometry": {"coordinates":[-2.254522,53.786444],"type":"Point"}
}
