{
  "type": "Feature",
  "properties": {
    "date:inception_lower":"1996-12-01",
    "date:inception_upper":"1996-12-31",
    "iso:country":"GB",
    "wof:name":"L35 3XQ",
    "wof:placetype":"postalcode"
},
  "geometry": {"coordinates":[-2.792086,53.413159],"type":"Point"}
}