{
  "type": "Feature",
  "properties": {
    "iso:country": "GB",
    "wof:name": "PR7 5QZ",
    "wof:placetype": "postalcode"
  },
  "geometry": {"coordinates":[-2.732872,53.646548],"type":"Point"}
}
