{
  "type": "Feature",
  "properties": {
    "date:inception_lower":"1980-01-01",
    "date:inception_upper":"1980-01-31",
    "iso:country":"GB",
    "wof:name":"GU11 3RL",
    "wof:placetype":"postalcode"
},
  "geometry": {"coordinates":[-0.755654,51.233441],"type":"Point"}
}