{
  "type": "Feature",
  "properties": {
    "iso:country": "GB",
    "wof:name": "GU11 3RL",
    "wof:placetype": "postalcode"
  },
  "geometry": {"coordinates":[-0.755654,51.233441],"type":"Point"}
}
