{
  "type": "Feature",
  "properties": {
    "iso:country":"GB",
    "wof:name":"BL2 5BS",
    "wof:placetype":"postalcode"
},
  "geometry": {"coordinates":[-2.39743529202874,53.59040942596715],"type":"Point"}
}