{
  "type": "Feature",
  "properties": {
    "date:inception_lower":"1980-01-01",
    "date:inception_upper":"1980-01-31",
    "iso:country":"GB",
    "wof:name":"BL2 5BS",
    "wof:placetype":"postalcode"
},
  "geometry": {"coordinates":[-2.397435,53.590409],"type":"Point"}
}