{
  "type": "Feature",
  "properties": {
    "iso:country":"GB",
    "wof:name":"S75 5HG",
    "wof:placetype":"postalcode"
},
  "geometry": {"coordinates":[-1.53165890724165,53.58549883987423],"type":"Point"}
}