{
  "type": "Feature",
  "properties": {
    "iso:country":"GB",
    "wof:name":"YO42 2AP",
    "wof:placetype":"postalcode"
},
  "geometry": {"coordinates":[-0.77848297285074,53.93067509255284],"type":"Point"}
}