{
  "type": "Feature",
  "properties": {
    "date:inception_lower":"1997-12-01",
    "date:inception_upper":"1997-12-31",
    "iso:country":"GB",
    "wof:name":"BB18 6AP",
    "wof:placetype":"postalcode"
},
  "geometry": {"coordinates":[-2.184202,53.917374],"type":"Point"}
}