{
  "type": "Feature",
  "properties": {
    "iso:country": "GB",
    "wof:name": "BB18 6AP",
    "wof:placetype": "postalcode"
  },
  "geometry": {"coordinates":[-2.184202,53.917374],"type":"Point"}
}
