{
  "type": "Feature",
  "properties": {
    "iso:country":"GB",
    "wof:name":"ST4 3RL",
    "wof:placetype":"postalcode"
},
  "geometry": {"coordinates":[-2.13905499733821,53.00031326703888],"type":"Point"}
}