{
  "type": "Feature",
  "properties": {
    "date:inception_lower": "1983-07-01",
    "date:inception_upper": "1983-07-01",
    "iso:country": "GB",
    "wof:name": "ST4 3RL",
    "wof:placetype": "postalcode"
  },
  "geometry": {"coordinates":[-2.139055,53.000313],"type":"Point"}
}
