{
  "type": "Feature",
  "properties": {
    "iso:country": "GB",
    "wof:name": "ST4 3RL",
    "wof:placetype": "postalcode"
  },
  "geometry": {"coordinates":[-2.139055,53.000313],"type":"Point"}
}
