{
  "type": "Feature",
  "properties": {
    "iso:country": "GB",
    "wof:name": "CV1 3BP",
    "wof:placetype": "postalcode"
  },
  "geometry": {"coordinates":[-1.519893,52.404406],"type":"Point"}
}
