{
  "type": "Feature",
  "properties": {
    "date:inception_lower":"1980-01-01",
    "date:inception_upper":"1980-01-31",
    "iso:country":"GB",
    "wof:name":"DG1 4SY",
    "wof:placetype":"postalcode"
},
  "geometry": {"coordinates":[-3.602748,55.045811],"type":"Point"}
}