{
  "type": "Feature",
  "properties": {
    "iso:country":"GB",
    "wof:name":"DG1 4SY",
    "wof:placetype":"postalcode"
},
  "geometry": {"coordinates":[-3.60274847615012,55.04581099389981],"type":"Point"}
}