{
  "type": "Feature",
  "properties": {
    "iso:country": "GB",
    "wof:name": "DG1 4SY",
    "wof:placetype": "postalcode"
  },
  "geometry": {"coordinates":[-3.602748,55.045811],"type":"Point"}
}
