{
  "type": "Feature",
  "properties": {
    "iso:country":"GB",
    "wof:name":"EX10 9LS",
    "wof:placetype":"postalcode"
},
  "geometry": {"coordinates":[-3.23175388774136,50.69825017482656],"type":"Point"}
}