{
  "type": "Feature",
  "properties": {
    "iso:country": "GB",
    "wof:name": "HP21 8YE",
    "wof:placetype": "postalcode"
  },
  "geometry": {"coordinates":[-0.827846,51.805007],"type":"Point"}
}
