{
  "type": "Feature",
  "properties": {
    "iso:country":"GB",
    "wof:name":"HP21 8YE",
    "wof:placetype":"postalcode"
},
  "geometry": {"coordinates":[-0.82784566188642,51.80500723986631],"type":"Point"}
}