{
  "type": "Feature",
  "properties": {
    "iso:country":"GB",
    "wof:name":"NW11 7HN",
    "wof:placetype":"postalcode"
},
  "geometry": {"coordinates":[-0.18462637212831,51.57163510673057],"type":"Point"}
}