{
  "type": "Feature",
  "properties": {
    "iso:country": "GB",
    "wof:name": "NW11 7HN",
    "wof:placetype": "postalcode"
  },
  "geometry": {"coordinates":[-0.184601,51.571638],"type":"Point"}
}
