{
  "type": "Feature",
  "properties": {
    "date:inception_lower":"1980-01-01",
    "date:inception_upper":"1980-01-31",
    "iso:country":"GB",
    "wof:name":"TD9 7QL",
    "wof:placetype":"postalcode"
},
  "geometry": {"coordinates":[-2.7897,55.436322],"type":"Point"}
}