{
  "type": "Feature",
  "properties": {
    "iso:country": "GB",
    "wof:name": "TF5 0EB",
    "wof:placetype": "postalcode"
  },
  "geometry": {"coordinates":[-2.543512,52.719552],"type":"Point"}
}
