{
  "type": "Feature",
  "properties": {
    "iso:country":"GB",
    "wof:name":"CH64 6UA",
    "wof:placetype":"postalcode"
},
  "geometry": {"coordinates":[-3.0759783499138,53.2882729565749],"type":"Point"}
}