{
  "type": "Feature",
  "properties": {
    "iso:country":"GB",
    "wof:name":"DA1 3QQ",
    "wof:placetype":"postalcode"
},
  "geometry": {"coordinates":[0.18027230165609,51.44490796624413],"type":"Point"}
}