{
  "type": "Feature",
  "properties": {
    "date:inception_lower": "1980-01-01",
    "date:inception_upper": "1980-01-01",
    "iso:country": "GB",
    "wof:name": "DA1 3QQ",
    "wof:placetype": "postalcode"
  },
  "geometry": {"coordinates":[0.180272,51.444908],"type":"Point"}
}
