{
  "type": "Feature",
  "properties": {
    "iso:country":"GB",
    "wof:name":"TN11 0JU",
    "wof:placetype":"postalcode"
},
  "geometry": {"coordinates":[0.35545098161664,51.21652157472547],"type":"Point"}
}