{
  "type": "Feature",
  "properties": {
    "iso:country": "GB",
    "wof:name": "TN11 0JU",
    "wof:placetype": "postalcode"
  },
  "geometry": {"coordinates":[0.355451,51.216522],"type":"Point"}
}
