{
  "type": "Feature",
  "properties": {
    "date:inception_lower":"2012-05-01",
    "date:inception_upper":"2012-05-31",
    "iso:country":"GB",
    "wof:name":"KW14 7AT",
    "wof:placetype":"postalcode"
},
  "geometry": {"coordinates":[-3.539996,58.585688],"type":"Point"}
}