{
  "type": "Feature",
  "properties": {
    "iso:country": "GB",
    "wof:name": "GL52 3JR",
    "wof:placetype": "postalcode"
  },
  "geometry": {"coordinates":[-2.058346,51.913696],"type":"Point"}
}
