{
  "type": "Feature",
  "properties": {
    "iso:country": "GB",
    "wof:name": "CV31 3LD",
    "wof:placetype": "postalcode"
  },
  "geometry": {"coordinates":[-1.536717,52.276963],"type":"Point"}
}
