{
  "type": "Feature",
  "properties": {
    "iso:country": "GB",
    "wof:name": "WF12 9DS",
    "wof:placetype": "postalcode"
  },
  "geometry": {"coordinates":[-1.631588,53.675245],"type":"Point"}
}
