{
  "type": "Feature",
  "properties": {
    "date:inception_lower": "1980-01-01",
    "date:inception_upper": "1980-01-01",
    "iso:country": "GB",
    "wof:name": "ML5 4EJ",
    "wof:placetype": "postalcode"
  },
  "geometry": {"coordinates":[-4.020566,55.851938],"type":"Point"}
}
