{
  "type": "Feature",
  "properties": {
    "date:inception_lower":"2013-07-01",
    "date:inception_upper":"2013-07-31",
    "iso:country":"GB",
    "wof:name":"RG26 4PY",
    "wof:placetype":"postalcode"
},
  "geometry": {"coordinates":[-1.147196,51.358052],"type":"Point"}
}