{
  "type": "Feature",
  "properties": {
    "iso:country":"GB",
    "wof:name":"RG26 4PY",
    "wof:placetype":"postalcode"
},
  "geometry": {"coordinates":[-1.14719603436402,51.35805227018478],"type":"Point"}
}