{
  "type": "Feature",
  "properties": {
    "iso:country":"GB",
    "wof:name":"M5 3LD",
    "wof:placetype":"postalcode"
},
  "geometry": {"coordinates":[-2.27678332666621,53.47412527577549],"type":"Point"}
}