{
  "type": "Feature",
  "properties": {
    "date:inception_lower": "1980-01-01",
    "date:inception_upper": "1980-01-01",
    "iso:country": "GB",
    "wof:name": "LS10 2QT",
    "wof:placetype": "postalcode"
  },
  "geometry": {"coordinates":[-1.526671,53.777951],"type":"Point"}
}
