{
  "type": "Feature",
  "properties": {
    "iso:country":"GB",
    "wof:name":"LS10 2QT",
    "wof:placetype":"postalcode"
},
  "geometry": {"coordinates":[-1.52674302403375,53.77796227536523],"type":"Point"}
}