{
  "type": "Feature",
  "properties": {
    "iso:country": "GB",
    "wof:name": "LS10 2QT",
    "wof:placetype": "postalcode"
  },
  "geometry": {"coordinates":[-1.526671,53.777951],"type":"Point"}
}
