{
  "type": "Feature",
  "properties": {
    "iso:country":"GB",
    "wof:name":"KY2 6HU",
    "wof:placetype":"postalcode"
},
  "geometry": {"coordinates":[-3.17688628246364,56.13681616467953],"type":"Point"}
}