{
  "type": "Feature",
  "properties": {
    "iso:country": "GB",
    "wof:name": "KY2 6HU",
    "wof:placetype": "postalcode"
  },
  "geometry": {"coordinates":[-3.176886,56.136816],"type":"Point"}
}
