{
  "type": "Feature",
  "properties": {
    "iso:country":"GB",
    "wof:name":"AB21 9DG",
    "wof:placetype":"postalcode"
},
  "geometry": {"coordinates":[-2.18226432181664,57.17664839128139],"type":"Point"}
}