{
  "type": "Feature",
  "properties": {
    "iso:country": "GB",
    "wof:name": "PO30 5FJ",
    "wof:placetype": "postalcode"
  },
  "geometry": {"coordinates":[-1.305253,50.702224],"type":"Point"}
}
