{
  "type": "Feature",
  "properties": {
    "iso:country":"GB",
    "wof:name":"TS5 7QJ",
    "wof:placetype":"postalcode"
},
  "geometry": {"coordinates":[-1.23765346633601,54.55274591491714],"type":"Point"}
}