{
  "type": "Feature",
  "properties": {
    "iso:country": "GB",
    "wof:name": "OL2 8NX",
    "wof:placetype": "postalcode"
  },
  "geometry": {"coordinates":[-2.093367,53.576345],"type":"Point"}
}
