{
  "type": "Feature",
  "properties": {
    "iso:country":"GB",
    "wof:name":"EN5 4BQ",
    "wof:placetype":"postalcode"
},
  "geometry": {"coordinates":[-0.20234437829959,51.65322522445315],"type":"Point"}
}