{
  "type": "Feature",
  "properties": {
    "iso:country": "GB",
    "wof:name": "HU12 0TU",
    "wof:placetype": "postalcode"
  },
  "geometry": {"coordinates":[0.116422,53.649937],"type":"Point"}
}
