{
  "type": "Feature",
  "properties": {
    "iso:country":"GB",
    "wof:name":"HU12 0TU",
    "wof:placetype":"postalcode"
},
  "geometry": {"coordinates":[0.11642183079629,53.64993653686019],"type":"Point"}
}