{
  "type": "Feature",
  "properties": {
    "iso:country": "GB",
    "wof:name": "WF4 5HE",
    "wof:placetype": "postalcode"
  },
  "geometry": {"coordinates":[-1.547313,53.661375],"type":"Point"}
}
