{
  "type": "Feature",
  "properties": {
    "date:inception_lower": "2000-12-01",
    "date:inception_upper": "2000-12-01",
    "iso:country": "GB",
    "wof:name": "WD18 0QR",
    "wof:placetype": "postalcode"
  },
  "geometry": {"coordinates":[-0.402897,51.656852],"type":"Point"}
}
