{
  "type": "Feature",
  "properties": {
    "iso:country":"GB",
    "wof:name":"WD18 0QR",
    "wof:placetype":"postalcode"
},
  "geometry": {"coordinates":[-0.40289691802087,51.65685233871051],"type":"Point"}
}