{
  "type": "Feature",
  "properties": {
    "date:inception_lower": "2016-07-01",
    "date:inception_upper": "2016-07-01",
    "iso:country": "GB",
    "wof:name": "EX36 4FL",
    "wof:placetype": "postalcode"
  },
  "geometry": {"coordinates":[-3.836607,51.016145],"type":"Point"}
}
