{
  "type": "Feature",
  "properties": {
    "date:inception_lower": "1982-09-01",
    "date:inception_upper": "1982-09-01",
    "iso:country": "GB",
    "wof:name": "G33 1QE",
    "wof:placetype": "postalcode"
  },
  "geometry": {"coordinates":[-4.176081,55.880897],"type":"Point"}
}
