{
  "type": "Feature",
  "properties": {
    "iso:country": "GB",
    "wof:name": "DG10 9BU",
    "wof:placetype": "postalcode"
  },
  "geometry": {"coordinates":[-3.43496,55.335898],"type":"Point"}
}
