{
  "type": "Feature",
  "properties": {
    "date:inception_lower": "2018-04-01",
    "date:inception_upper": "2018-04-01",
    "iso:country": "GB",
    "wof:name": "E17 6TF",
    "wof:placetype": "postalcode"
  },
  "geometry": {"coordinates":[-0.041172,51.588484],"type":"Point"}
}
