{
  "type": "Feature",
  "properties": {
    "iso:country":"GB",
    "wof:name":"BN41 1SJ",
    "wof:placetype":"postalcode"
},
  "geometry": {"coordinates":[-0.2190899116964,50.83739342415661],"type":"Point"}
}