{
  "type": "Feature",
  "properties": {
    "iso:country": "GB",
    "wof:name": "BN41 1SJ",
    "wof:placetype": "postalcode"
  },
  "geometry": {"coordinates":[-0.21909,50.837393],"type":"Point"}
}
