{
  "type": "Feature",
  "properties": {
    "iso:country": "GB",
    "wof:name": "GL3 2PY",
    "wof:placetype": "postalcode"
  },
  "geometry": {"coordinates":[-2.166356,51.873971],"type":"Point"}
}
