{
  "type": "Feature",
  "properties": {
    "iso:country":"GB",
    "wof:name":"BD4 0QB",
    "wof:placetype":"postalcode"
},
  "geometry": {"coordinates":[-1.70387740996649,53.76707942991649],"type":"Point"}
}