{
  "type": "Feature",
  "properties": {
    "iso:country":"GB",
    "wof:name":"UB8 2LH",
    "wof:placetype":"postalcode"
},
  "geometry": {"coordinates":[-0.48375900283501,51.52188356021252],"type":"Point"}
}