{
  "type": "Feature",
  "properties": {
    "iso:country":"GB",
    "wof:name":"TA21 0LR",
    "wof:placetype":"postalcode"
},
  "geometry": {"coordinates":[-3.30201412019754,50.96151993585617],"type":"Point"}
}