{
  "type": "Feature",
  "properties": {
    "date:inception_lower": "2001-12-01",
    "date:inception_upper": "2001-12-01",
    "iso:country": "GB",
    "wof:name": "TA21 0LR",
    "wof:placetype": "postalcode"
  },
  "geometry": {"coordinates":[-3.302026,50.961514],"type":"Point"}
}
