{
  "type": "Feature",
  "properties": {
    "iso:country": "GB",
    "wof:name": "TA21 0LR",
    "wof:placetype": "postalcode"
  },
  "geometry": {"coordinates":[-3.302026,50.961514],"type":"Point"}
}
