{
  "type": "Feature",
  "properties": {
    "iso:country": "GB",
    "wof:name": "SW20 0DF",
    "wof:placetype": "postalcode"
  },
  "geometry": {"coordinates":[-0.234043,51.413763],"type":"Point"}
}
