{
  "type": "Feature",
  "properties": {
    "iso:country":"GB",
    "wof:name":"SW20 0DF",
    "wof:placetype":"postalcode"
},
  "geometry": {"coordinates":[-0.23404325300266,51.41376270415165],"type":"Point"}
}