{
  "type": "Feature",
  "properties": {
    "iso:country":"GB",
    "wof:name":"DN1 3HS",
    "wof:placetype":"postalcode"
},
  "geometry": {"coordinates":[-1.1295626895527,53.518990372668],"type":"Point"}
}