{
  "type": "Feature",
  "properties": {
    "iso:country": "GB",
    "wof:name": "FY2 0RT",
    "wof:placetype": "postalcode"
  },
  "geometry": {"coordinates":[-3.037387,53.841863],"type":"Point"}
}
