{
  "type": "Feature",
  "properties": {
    "iso:country":"GB",
    "wof:name":"NE28 9LY",
    "wof:placetype":"postalcode"
},
  "geometry": {"coordinates":[-1.53538547472393,55.00479712674254],"type":"Point"}
}