{
  "type": "Feature",
  "properties": {
    "iso:country":"GB",
    "wof:name":"BR2 8EU",
    "wof:placetype":"postalcode"
},
  "geometry": {"coordinates":[0.04603123895435,51.38624864924196],"type":"Point"}
}