{
  "type": "Feature",
  "properties": {
    "iso:country": "GB",
    "wof:name": "BR2 8EU",
    "wof:placetype": "postalcode"
  },
  "geometry": {"coordinates":[0.046031,51.386249],"type":"Point"}
}
