{
  "type": "Feature",
  "properties": {
    "iso:country":"GB",
    "wof:name":"M24 2QH",
    "wof:placetype":"postalcode"
},
  "geometry": {"coordinates":[-2.18992828996102,53.5583994751228],"type":"Point"}
}