{
  "type": "Feature",
  "properties": {
    "iso:country":"GB",
    "wof:name":"SL9 9BW",
    "wof:placetype":"postalcode"
},
  "geometry": {"coordinates":[-0.55620151881324,51.60261056824717],"type":"Point"}
}