{
  "type": "Feature",
  "properties": {
    "date:inception_lower": "1980-01-01",
    "date:inception_upper": "1980-01-01",
    "iso:country": "GB",
    "wof:name": "SL9 9BW",
    "wof:placetype": "postalcode"
  },
  "geometry": {"coordinates":[-0.556201,51.602611],"type":"Point"}
}
