{
  "type": "Feature",
  "properties": {
    "iso:country":"GB",
    "wof:name":"S70 6DH",
    "wof:placetype":"postalcode"
},
  "geometry": {"coordinates":[-1.51000308776726,53.54840691678587],"type":"Point"}
}