{
  "type": "Feature",
  "properties": {
    "iso:country":"GB",
    "wof:name":"EX39 3TA",
    "wof:placetype":"postalcode"
},
  "geometry": {"coordinates":[-4.22550675809631,51.01635140683891],"type":"Point"}
}