{
  "type": "Feature",
  "properties": {
    "iso:country": "GB",
    "wof:name": "EH52 6HA",
    "wof:placetype": "postalcode"
  },
  "geometry": {"coordinates":[-3.491617,55.93475],"type":"Point"}
}
