{
  "type": "Feature",
  "properties": {
    "date:inception_lower": "2023-07-01",
    "date:inception_upper": "2023-07-01",
    "iso:country": "GB",
    "wof:name": "GL14 2FE",
    "wof:placetype": "postalcode"
  },
  "geometry": {"coordinates":[-2.495189,51.823017],"type":"Point"}
}
