{
  "type": "Feature",
  "properties": {
    "iso:country": "GB",
    "wof:name": "S9 4GG",
    "wof:placetype": "postalcode"
  },
  "geometry": {"coordinates":[-1.417763,53.378397],"type":"Point"}
}
