{
  "type": "Feature",
  "properties": {
    "iso:country": "GB",
    "wof:name": "GL11 5QA",
    "wof:placetype": "postalcode"
  },
  "geometry": {"coordinates":[-2.363421,51.690082],"type":"Point"}
}
