{
  "type": "Feature",
  "properties": {
    "iso:country":"GB",
    "wof:name":"YO25 8DL",
    "wof:placetype":"postalcode"
},
  "geometry": {"coordinates":[-0.19220389819335,53.94058527308214],"type":"Point"}
}