{
  "type": "Feature",
  "properties": {
    "date:inception_lower":"2011-02-01",
    "date:inception_upper":"2011-02-28",
    "iso:country":"GB",
    "wof:name":"M32 0ZS",
    "wof:placetype":"postalcode"
},
  "geometry": {"coordinates":[-2.292675,53.458331],"type":"Point"}
}