{
  "type": "Feature",
  "properties": {
    "iso:country":"GB",
    "wof:name":"M32 0ZS",
    "wof:placetype":"postalcode"
},
  "geometry": {"coordinates":[-2.29267465972782,53.45833055554274],"type":"Point"}
}