{
  "type": "Feature",
  "properties": {
    "date:inception_lower":"1980-01-01",
    "date:inception_upper":"1980-01-31",
    "iso:country":"GB",
    "wof:name":"PA8 6EG",
    "wof:placetype":"postalcode"
},
  "geometry": {"coordinates":[-4.460415,55.908157],"type":"Point"}
}