{
  "type": "Feature",
  "properties": {
    "iso:country":"GB",
    "wof:name":"DL4 2LL",
    "wof:placetype":"postalcode"
},
  "geometry": {"coordinates":[-1.6388601304256,54.62341087044129],"type":"Point"}
}