{
  "type": "Feature",
  "properties": {
    "iso:country":"GB",
    "wof:name":"EH18 1HG",
    "wof:placetype":"postalcode"
},
  "geometry": {"coordinates":[-3.12756798038665,55.88257846462569],"type":"Point"}
}