{
  "type": "Feature",
  "properties": {
    "iso:country":"GB",
    "wof:name":"EX4 6QU",
    "wof:placetype":"postalcode"
},
  "geometry": {"coordinates":[-3.52304195521223,50.7285232010238],"type":"Point"}
}