{
  "type": "Feature",
  "properties": {
    "date:inception_lower":"1980-01-01",
    "date:inception_upper":"1980-01-31",
    "iso:country":"GB",
    "wof:name":"EX4 6QU",
    "wof:placetype":"postalcode"
},
  "geometry": {"coordinates":[-3.523042,50.728523],"type":"Point"}
}