{
  "type": "Feature",
  "properties": {
    "iso:country":"GB",
    "wof:name":"BA15 2JJ",
    "wof:placetype":"postalcode"
},
  "geometry": {"coordinates":[-2.28005168524865,51.34973192714538],"type":"Point"}
}