{
  "type": "Feature",
  "properties": {
    "iso:country": "GB",
    "wof:name": "BA15 2JJ",
    "wof:placetype": "postalcode"
  },
  "geometry": {"coordinates":[-2.280052,51.349732],"type":"Point"}
}
