{
  "type": "Feature",
  "properties": {
    "iso:country": "GB",
    "wof:name": "TA8 1DA",
    "wof:placetype": "postalcode"
  },
  "geometry": {"coordinates":[-2.997058,51.232526],"type":"Point"}
}
