{
  "type": "Feature",
  "properties": {
    "iso:country":"GB",
    "wof:name":"TA8 1DA",
    "wof:placetype":"postalcode"
},
  "geometry": {"coordinates":[-2.99703455247312,51.23253100294138],"type":"Point"}
}