{
  "type": "Feature",
  "properties": {
    "iso:country": "GB",
    "wof:name": "TN38 9DA",
    "wof:placetype": "postalcode"
  },
  "geometry": {"coordinates":[0.552949,50.872355],"type":"Point"}
}
