{
  "type": "Feature",
  "properties": {
    "iso:country":"GB",
    "wof:name":"TN38 9DA",
    "wof:placetype":"postalcode"
},
  "geometry": {"coordinates":[0.55294921829122,50.87237641682937],"type":"Point"}
}