{
  "type": "Feature",
  "properties": {
    "date:inception_lower": "1986-07-01",
    "date:inception_upper": "1986-07-01",
    "iso:country": "GB",
    "wof:name": "MK45 4BB",
    "wof:placetype": "postalcode"
  },
  "geometry": {"coordinates":[-0.412874,52.031747],"type":"Point"}
}
