{
  "type": "Feature",
  "properties": {
    "iso:country":"GB",
    "wof:name":"MK45 4BB",
    "wof:placetype":"postalcode"
},
  "geometry": {"coordinates":[-0.41289749176816,52.03176389377763],"type":"Point"}
}