{
  "type": "Feature",
  "properties": {
    "iso:country":"GB",
    "wof:name":"SL4 3DN",
    "wof:placetype":"postalcode"
},
  "geometry": {"coordinates":[-0.61631234102887,51.4728336104473],"type":"Point"}
}