{
  "type": "Feature",
  "properties": {
    "iso:country": "GB",
    "wof:name": "SL4 3DN",
    "wof:placetype": "postalcode"
  },
  "geometry": {"coordinates":[-0.616296,51.472826],"type":"Point"}
}
