{
  "type": "Feature",
  "properties": {
    "iso:country":"GB",
    "wof:name":"S8 7JP",
    "wof:placetype":"postalcode"
},
  "geometry": {"coordinates":[-1.49875486187682,53.31967224878125],"type":"Point"}
}