{
  "type": "Feature",
  "properties": {
    "date:inception_lower": "2012-07-01",
    "date:inception_upper": "2012-07-01",
    "iso:country": "GB",
    "wof:name": "S8 7JP",
    "wof:placetype": "postalcode"
  },
  "geometry": {"coordinates":[-1.498769,53.31969],"type":"Point"}
}
