{
  "type": "Feature",
  "properties": {
    "iso:country": "GB",
    "wof:name": "EX3 0JW",
    "wof:placetype": "postalcode"
  },
  "geometry": {"coordinates":[-3.469383,50.684594],"type":"Point"}
}
