{
  "type": "Feature",
  "properties": {
    "iso:country":"GB",
    "wof:name":"EX3 0JW",
    "wof:placetype":"postalcode"
},
  "geometry": {"coordinates":[-3.46927444876267,50.68473262121817],"type":"Point"}
}