{
  "type": "Feature",
  "properties": {
    "iso:country":"GB",
    "wof:name":"ST4 8AA",
    "wof:placetype":"postalcode"
},
  "geometry": {"coordinates":[-2.19953123723087,52.96695799438969],"type":"Point"}
}