{
  "type": "Feature",
  "properties": {
    "date:inception_lower": "1980-01-01",
    "date:inception_upper": "1980-01-01",
    "iso:country": "GB",
    "wof:name": "SA13 1PS",
    "wof:placetype": "postalcode"
  },
  "geometry": {"coordinates":[-3.773698,51.586328],"type":"Point"}
}
