{
  "type": "Feature",
  "properties": {
    "iso:country": "GB",
    "wof:name": "CF39 0LG",
    "wof:placetype": "postalcode"
  },
  "geometry": {"coordinates":[-3.412346,51.615039],"type":"Point"}
}
