{
  "type": "Feature",
  "properties": {
    "iso:country": "GB",
    "wof:name": "CM1 4EF",
    "wof:placetype": "postalcode"
  },
  "geometry": {"coordinates":[0.472347,51.752452],"type":"Point"}
}
