{
  "type": "Feature",
  "properties": {
    "iso:country":"GB",
    "wof:name":"DY11 6LJ",
    "wof:placetype":"postalcode"
},
  "geometry": {"coordinates":[-2.2696541460544,52.37587307355855],"type":"Point"}
}