{
  "type": "Feature",
  "properties": {
    "iso:country": "GB",
    "wof:name": "DY11 6LJ",
    "wof:placetype": "postalcode"
  },
  "geometry": {"coordinates":[-2.269654,52.375873],"type":"Point"}
}
