{
  "type": "Feature",
  "properties": {
    "date:inception_lower": "2005-08-01",
    "date:inception_upper": "2005-08-01",
    "iso:country": "GB",
    "wof:name": "DY11 6LJ",
    "wof:placetype": "postalcode"
  },
  "geometry": {"coordinates":[-2.269654,52.375873],"type":"Point"}
}
