{
  "type": "Feature",
  "properties": {
    "iso:country":"GB",
    "wof:name":"CM8 2SR",
    "wof:placetype":"postalcode"
},
  "geometry": {"coordinates":[0.64417187344483,51.81080889784889],"type":"Point"}
}