{
  "type": "Feature",
  "properties": {
    "date:inception_lower": "1980-01-01",
    "date:inception_upper": "1980-01-01",
    "iso:country": "GB",
    "wof:name": "CM8 2SR",
    "wof:placetype": "postalcode"
  },
  "geometry": {"coordinates":[0.644172,51.810809],"type":"Point"}
}
