{
  "type": "Feature",
  "properties": {
    "iso:country":"GB",
    "wof:name":"E11 2BW",
    "wof:placetype":"postalcode"
},
  "geometry": {"coordinates":[0.0318699396966,51.58346333859045],"type":"Point"}
}