{
  "type": "Feature",
  "properties": {
    "iso:country": "GB",
    "wof:name": "CF10 3DY",
    "wof:placetype": "postalcode"
  },
  "geometry": {"coordinates":[-3.18614,51.489308],"type":"Point"}
}
