{
  "type": "Feature",
  "properties": {
    "iso:country":"GB",
    "wof:name":"GU14 7EE",
    "wof:placetype":"postalcode"
},
  "geometry": {"coordinates":[-0.73851257895748,51.2893246210935],"type":"Point"}
}