{
  "type": "Feature",
  "properties": {
    "iso:country": "GB",
    "wof:name": "GU14 7EE",
    "wof:placetype": "postalcode"
  },
  "geometry": {"coordinates":[-0.738513,51.289325],"type":"Point"}
}
