{
  "type": "Feature",
  "properties": {
    "date:inception_lower":"1980-01-01",
    "date:inception_upper":"1980-01-31",
    "iso:country":"GB",
    "wof:name":"EH30 9HU",
    "wof:placetype":"postalcode"
},
  "geometry": {"coordinates":[-3.39579,55.989428],"type":"Point"}
}