{
  "type": "Feature",
  "properties": {
    "iso:country": "GB",
    "wof:name": "SS11 7DT",
    "wof:placetype": "postalcode"
  },
  "geometry": {"coordinates":[0.526461,51.628202],"type":"Point"}
}
