{
  "type": "Feature",
  "properties": {
    "iso:country":"GB",
    "wof:name":"S33 9JZ",
    "wof:placetype":"postalcode"
},
  "geometry": {"coordinates":[-1.74818659040711,53.33258461240027],"type":"Point"}
}