{
  "type": "Feature",
  "properties": {
    "date:inception_lower": "1997-06-01",
    "date:inception_upper": "1997-06-01",
    "iso:country": "GB",
    "wof:name": "S33 9JZ",
    "wof:placetype": "postalcode"
  },
  "geometry": {"coordinates":[-1.748187,53.332585],"type":"Point"}
}
