{
  "type": "Feature",
  "properties": {
    "iso:country":"GB",
    "wof:name":"DL8 1NU",
    "wof:placetype":"postalcode"
},
  "geometry": {"coordinates":[-1.62667326595408,54.33491842338486],"type":"Point"}
}