{
  "type": "Feature",
  "properties": {
    "iso:country":"GB",
    "wof:name":"CM3 1AU",
    "wof:placetype":"postalcode"
},
  "geometry": {"coordinates":[0.4572823297108,51.79548472700198],"type":"Point"}
}