{
  "type": "Feature",
  "properties": {
    "date:inception_lower": "1998-12-01",
    "date:inception_upper": "1998-12-01",
    "iso:country": "GB",
    "wof:name": "DN33 1SA",
    "wof:placetype": "postalcode"
  },
  "geometry": {"coordinates":[-0.105011,53.546939],"type":"Point"}
}
