{
  "type": "Feature",
  "properties": {
    "iso:country":"GB",
    "wof:name":"DN33 1SA",
    "wof:placetype":"postalcode"
},
  "geometry": {"coordinates":[-0.10501057420091,53.54693887457286],"type":"Point"}
}