{
  "type": "Feature",
  "properties": {
    "date:inception_lower": "1980-01-01",
    "date:inception_upper": "1980-01-01",
    "iso:country": "GB",
    "wof:name": "PO13 9RY",
    "wof:placetype": "postalcode"
  },
  "geometry": {"coordinates":[-1.172315,50.807454],"type":"Point"}
}
