{
  "type": "Feature",
  "properties": {
    "iso:country":"GB",
    "wof:name":"TA3 5EW",
    "wof:placetype":"postalcode"
},
  "geometry": {"coordinates":[-3.03145029151912,51.0400395103272],"type":"Point"}
}