{
  "type": "Feature",
  "properties": {
    "iso:country":"GB",
    "wof:name":"DN11 0HP",
    "wof:placetype":"postalcode"
},
  "geometry": {"coordinates":[-1.03660544844031,53.46928878352246],"type":"Point"}
}