{
  "type": "Feature",
  "properties": {
    "date:inception_lower":"1980-01-01",
    "date:inception_upper":"1980-01-31",
    "iso:country":"GB",
    "wof:name":"DN11 0HP",
    "wof:placetype":"postalcode"
},
  "geometry": {"coordinates":[-1.04128,53.4678],"type":"Point"}
}