{
  "type": "Feature",
  "properties": {
    "iso:country": "GB",
    "wof:name": "DN11 0HP",
    "wof:placetype": "postalcode"
  },
  "geometry": {"coordinates":[-1.04128,53.4678],"type":"Point"}
}
