{
  "type": "Feature",
  "properties": {
    "iso:country": "GB",
    "wof:name": "SS16 6SH",
    "wof:placetype": "postalcode"
  },
  "geometry": {"coordinates":[0.410156,51.566869],"type":"Point"}
}
