{
  "type": "Feature",
  "properties": {
    "iso:country":"GB",
    "wof:name":"SS16 6SH",
    "wof:placetype":"postalcode"
},
  "geometry": {"coordinates":[0.41015587884239,51.56686882902125],"type":"Point"}
}