{
  "type": "Feature",
  "properties": {
    "iso:country":"GB",
    "wof:name":"B11 4QT",
    "wof:placetype":"postalcode"
},
  "geometry": {"coordinates":[-1.86803687441133,52.45738702977663],"type":"Point"}
}