{
  "type": "Feature",
  "properties": {
    "date:inception_lower": "1980-01-01",
    "date:inception_upper": "1980-01-01",
    "iso:country": "GB",
    "wof:name": "B11 4QT",
    "wof:placetype": "postalcode"
  },
  "geometry": {"coordinates":[-1.868037,52.457387],"type":"Point"}
}
