{
  "type": "Feature",
  "properties": {
    "iso:country":"GB",
    "wof:name":"NE1 7AS",
    "wof:placetype":"postalcode"
},
  "geometry": {"coordinates":[-1.61359834950394,54.9760359265083],"type":"Point"}
}