{
  "type": "Feature",
  "properties": {
    "date:inception_lower": "2023-12-01",
    "date:inception_upper": "2023-12-01",
    "iso:country": "GB",
    "wof:name": "MK44 2FN",
    "wof:placetype": "postalcode"
  },
  "geometry": {"coordinates":[-0.459467,52.215665],"type":"Point"}
}
