{
  "type": "Feature",
  "properties": {
    "date:inception_lower": "1980-01-01",
    "date:inception_upper": "1980-01-01",
    "iso:country": "GB",
    "wof:name": "NE22 5YR",
    "wof:placetype": "postalcode"
  },
  "geometry": {"coordinates":[-1.570331,55.140499],"type":"Point"}
}
