{
  "type": "Feature",
  "properties": {
    "iso:country": "GB",
    "wof:name": "NE22 5YR",
    "wof:placetype": "postalcode"
  },
  "geometry": {"coordinates":[-1.570331,55.140499],"type":"Point"}
}
