{
  "type": "Feature",
  "properties": {
    "iso:country": "GB",
    "wof:name": "KY8 3BB",
    "wof:placetype": "postalcode"
  },
  "geometry": {"coordinates":[-3.006188,56.191596],"type":"Point"}
}
