{
  "type": "Feature",
  "properties": {
    "iso:country":"GB",
    "wof:name":"TN29 9UG",
    "wof:placetype":"postalcode"
},
  "geometry": {"coordinates":[0.85256074521252,51.01049979899646],"type":"Point"}
}