{
  "type": "Feature",
  "properties": {
    "iso:country": "GB",
    "wof:name": "TN29 9UG",
    "wof:placetype": "postalcode"
  },
  "geometry": {"coordinates":[0.852561,51.0105],"type":"Point"}
}
