{
  "type": "Feature",
  "properties": {
    "iso:country":"GB",
    "wof:name":"EN10 7AX",
    "wof:placetype":"postalcode"
},
  "geometry": {"coordinates":[-0.014556539014,51.74343340008441],"type":"Point"}
}