{
  "type": "Feature",
  "properties": {
    "iso:country": "GB",
    "wof:name": "EN10 7AX",
    "wof:placetype": "postalcode"
  },
  "geometry": {"coordinates":[-0.014556,51.743433],"type":"Point"}
}
