{
  "type": "Feature",
  "properties": {
    "iso:country": "GB",
    "wof:name": "FK7 7XG",
    "wof:placetype": "postalcode"
  },
  "geometry": {"coordinates":[-3.919723,56.100392],"type":"Point"}
}
