{
  "type": "Feature",
  "properties": {
    "iso:country":"GB",
    "wof:name":"RH1 6TR",
    "wof:placetype":"postalcode"
},
  "geometry": {"coordinates":[-0.16536292663518,51.22236713753846],"type":"Point"}
}