{
  "type": "Feature",
  "properties": {
    "iso:country": "GB",
    "wof:name": "RH1 6TR",
    "wof:placetype": "postalcode"
  },
  "geometry": {"coordinates":[-0.165281,51.222319],"type":"Point"}
}
