{
  "type": "Feature",
  "properties": {
    "iso:country": "GB",
    "wof:name": "SW1P 3DJ",
    "wof:placetype": "postalcode"
  },
  "geometry": {"coordinates":[-0.129351,51.497937],"type":"Point"}
}
