{
  "type": "Feature",
  "properties": {
    "iso:country": "GB",
    "wof:name": "DT2 9UP",
    "wof:placetype": "postalcode"
  },
  "geometry": {"coordinates":[-2.4572,50.751812],"type":"Point"}
}
