{
  "type": "Feature",
  "properties": {
    "iso:country":"GB",
    "wof:name":"DT2 9UP",
    "wof:placetype":"postalcode"
},
  "geometry": {"coordinates":[-2.45721501237335,50.75180300381182],"type":"Point"}
}