{
  "type": "Feature",
  "properties": {
    "iso:country": "GB",
    "wof:name": "HP18 0GL",
    "wof:placetype": "postalcode"
  },
  "geometry": {"coordinates":[-0.85454,51.840184],"type":"Point"}
}
