{
  "type": "Feature",
  "properties": {
    "iso:country":"GB",
    "wof:name":"HP18 0GL",
    "wof:placetype":"postalcode"
},
  "geometry": {"coordinates":[-0.8545403483463,51.84018382021701],"type":"Point"}
}