{
  "type": "Feature",
  "properties": {
    "date:inception_lower": "1980-01-01",
    "date:inception_upper": "1980-01-01",
    "iso:country": "GB",
    "wof:name": "BR3 1UP",
    "wof:placetype": "postalcode"
  },
  "geometry": {"coordinates":[-0.02252,51.418694],"type":"Point"}
}
