{
  "type": "Feature",
  "properties": {
    "iso:country":"GB",
    "wof:name":"BR3 1UP",
    "wof:placetype":"postalcode"
},
  "geometry": {"coordinates":[-0.02251997616294,51.41869369450984],"type":"Point"}
}