{
  "type": "Feature",
  "properties": {
    "iso:country":"GB",
    "wof:name":"EX6 6PN",
    "wof:placetype":"postalcode"
},
  "geometry": {"coordinates":[-3.78724513113825,50.70283610225012],"type":"Point"}
}