{
  "type": "Feature",
  "properties": {
    "date:inception_lower": "2018-01-01",
    "date:inception_upper": "2018-01-01",
    "iso:country": "GB",
    "wof:name": "M12 5UG",
    "wof:placetype": "postalcode"
  },
  "geometry": {"coordinates":[-2.204853,53.470197],"type":"Point"}
}
