{
  "type": "Feature",
  "properties": {
    "iso:country": "GB",
    "wof:name": "NN8 4JX",
    "wof:placetype": "postalcode"
  },
  "geometry": {"coordinates":[-0.700399,52.318196],"type":"Point"}
}
