{
  "type": "Feature",
  "properties": {
    "date:inception_lower": "2005-05-01",
    "date:inception_upper": "2005-05-01",
    "iso:country": "GB",
    "wof:name": "NN8 4JX",
    "wof:placetype": "postalcode"
  },
  "geometry": {"coordinates":[-0.700399,52.318196],"type":"Point"}
}
