{
  "type": "Feature",
  "properties": {
    "iso:country":"GB",
    "wof:name":"GL7 4HB",
    "wof:placetype":"postalcode"
},
  "geometry": {"coordinates":[-1.78034808331786,51.67295203602436],"type":"Point"}
}