{
  "type": "Feature",
  "properties": {
    "iso:country": "GB",
    "wof:name": "CM16 6PN",
    "wof:placetype": "postalcode"
  },
  "geometry": {"coordinates":[0.079327,51.724927],"type":"Point"}
}
