{
  "type": "Feature",
  "properties": {
    "date:inception_lower": "2009-08-01",
    "date:inception_upper": "2009-08-01",
    "iso:country": "GB",
    "wof:name": "BA14 6FD",
    "wof:placetype": "postalcode"
  },
  "geometry": {"coordinates":[-2.206814,51.34181],"type":"Point"}
}
