{
  "type": "Feature",
  "properties": {
    "iso:country": "GB",
    "wof:name": "CM7 3NZ",
    "wof:placetype": "postalcode"
  },
  "geometry": {"coordinates":[0.574413,51.873861],"type":"Point"}
}
