{
  "type": "Feature",
  "properties": {
    "iso:country":"GB",
    "wof:name":"CM7 3NZ",
    "wof:placetype":"postalcode"
},
  "geometry": {"coordinates":[0.57441251540828,51.8738611954583],"type":"Point"}
}