{
  "type": "Feature",
  "properties": {
    "iso:country":"GB",
    "wof:name":"BR3 3NT",
    "wof:placetype":"postalcode"
},
  "geometry": {"coordinates":[-0.03498515985397,51.40269839387449],"type":"Point"}
}