{
  "type": "Feature",
  "properties": {
    "iso:country": "GB",
    "wof:name": "SK5 7PS",
    "wof:placetype": "postalcode"
  },
  "geometry": {"coordinates":[-2.162703,53.422813],"type":"Point"}
}
