{
  "type": "Feature",
  "properties": {
    "iso:country":"GB",
    "wof:name":"DA4 0BD",
    "wof:placetype":"postalcode"
},
  "geometry": {"coordinates":[0.22350265148095,51.37732204202339],"type":"Point"}
}