{
  "type": "Feature",
  "properties": {
    "iso:country":"GB",
    "wof:name":"KA20 3LH",
    "wof:placetype":"postalcode"
},
  "geometry": {"coordinates":[-4.74255985299591,55.63270896955245],"type":"Point"}
}