{
  "type": "Feature",
  "properties": {
    "date:inception_lower": "2007-01-01",
    "date:inception_upper": "2007-01-01",
    "iso:country": "GB",
    "wof:name": "TD9 0DT",
    "wof:placetype": "postalcode"
  },
  "geometry": {"coordinates":[-2.796648,55.412482],"type":"Point"}
}
