{
  "type": "Feature",
  "properties": {
    "iso:country":"GB",
    "wof:name":"TD9 0DT",
    "wof:placetype":"postalcode"
},
  "geometry": {"coordinates":[-2.79664848075681,55.4124824663554],"type":"Point"}
}