{
  "type": "Feature",
  "properties": {
    "date:inception_lower":"2000-12-01",
    "date:inception_upper":"2000-12-31",
    "iso:country":"GB",
    "wof:name":"CW1 3AW",
    "wof:placetype":"postalcode"
},
  "geometry": {"coordinates":[-2.45397,53.098813],"type":"Point"}
}