{
  "type": "Feature",
  "properties": {
    "iso:country":"GB",
    "wof:name":"SO16 8DR",
    "wof:placetype":"postalcode"
},
  "geometry": {"coordinates":[-1.45329553459353,50.94716102569798],"type":"Point"}
}