{
  "type": "Feature",
  "properties": {
    "iso:country":"GB",
    "wof:name":"NG3 2BX",
    "wof:placetype":"postalcode"
},
  "geometry": {"coordinates":[-1.12771474104628,52.95616050988123],"type":"Point"}
}