{
  "type": "Feature",
  "properties": {
    "iso:country": "GB",
    "wof:name": "CB7 5ZX",
    "wof:placetype": "postalcode"
  },
  "geometry": {"coordinates":[0.337378,52.346476],"type":"Point"}
}
