{
  "type": "Feature",
  "properties": {
    "date:inception_lower": "1980-01-01",
    "date:inception_upper": "1980-01-01",
    "iso:country": "GB",
    "wof:name": "LL28 4NT",
    "wof:placetype": "postalcode"
  },
  "geometry": {"coordinates":[-3.74232,53.313793],"type":"Point"}
}
