{
  "type": "Feature",
  "properties": {
    "date:inception_lower":"1997-12-01",
    "date:inception_upper":"1997-12-31",
    "iso:country":"GB",
    "wof:name":"BS30 8AN",
    "wof:placetype":"postalcode"
},
  "geometry": {"coordinates":[-2.487694,51.442574],"type":"Point"}
}