{
  "type": "Feature",
  "properties": {
    "iso:country":"GB",
    "wof:name":"CV10 7PN",
    "wof:placetype":"postalcode"
},
  "geometry": {"coordinates":[-1.47988415876934,52.5062577673008],"type":"Point"}
}