{
  "type": "Feature",
  "properties": {
    "date:inception_lower": "1980-01-01",
    "date:inception_upper": "1980-01-01",
    "iso:country": "GB",
    "wof:name": "PE20 2AH",
    "wof:placetype": "postalcode"
  },
  "geometry": {"coordinates":[-0.049707,52.907721],"type":"Point"}
}
