{
  "type": "Feature",
  "properties": {
    "iso:country":"GB",
    "wof:name":"B27 6LW",
    "wof:placetype":"postalcode"
},
  "geometry": {"coordinates":[-1.81589837807237,52.45329895784608],"type":"Point"}
}