{
  "type": "Feature",
  "properties": {
    "iso:country": "GB",
    "wof:name": "B27 6LW",
    "wof:placetype": "postalcode"
  },
  "geometry": {"coordinates":[-1.815898,52.453299],"type":"Point"}
}
