{
  "type": "Feature",
  "properties": {
    "iso:country":"GB",
    "wof:name":"SP9 7YH",
    "wof:placetype":"postalcode"
},
  "geometry": {"coordinates":[-1.67522658072429,51.20662965594555],"type":"Point"}
}