{
  "type": "Feature",
  "properties": {
    "date:inception_lower": "1984-10-01",
    "date:inception_upper": "1984-10-01",
    "iso:country": "GB",
    "wof:name": "SP9 7YH",
    "wof:placetype": "postalcode"
  },
  "geometry": {"coordinates":[-1.675227,51.20663],"type":"Point"}
}
