{
  "type": "Feature",
  "properties": {
    "iso:country":"GB",
    "wof:name":"WF10 5EH",
    "wof:placetype":"postalcode"
},
  "geometry": {"coordinates":[-1.3560613300206,53.72015534021904],"type":"Point"}
}