{
  "type": "Feature",
  "properties": {
    "iso:country": "GB",
    "wof:name": "TA8 2HD",
    "wof:placetype": "postalcode"
  },
  "geometry": {"coordinates":[-2.998792,51.242911],"type":"Point"}
}
