{
  "type": "Feature",
  "properties": {
    "iso:country":"GB",
    "wof:name":"LE11 4HD",
    "wof:placetype":"postalcode"
},
  "geometry": {"coordinates":[-1.24849215431309,52.76640606409949],"type":"Point"}
}