{
  "type": "Feature",
  "properties": {
    "iso:country":"GB",
    "wof:name":"TF3 4LR",
    "wof:placetype":"postalcode"
},
  "geometry": {"coordinates":[-2.45640677411045,52.67762246465761],"type":"Point"}
}