{
  "type": "Feature",
  "properties": {
    "iso:country":"GB",
    "wof:name":"WA11 0NZ",
    "wof:placetype":"postalcode"
},
  "geometry": {"coordinates":[-2.65571665405099,53.46766633995453],"type":"Point"}
}