{
  "type": "Feature",
  "properties": {
    "date:inception_lower": "1990-07-01",
    "date:inception_upper": "1990-07-01",
    "iso:country": "GB",
    "wof:name": "CR6 9NU",
    "wof:placetype": "postalcode"
  },
  "geometry": {"coordinates":[-0.056642,51.31198],"type":"Point"}
}
