{
  "type": "Feature",
  "properties": {
    "date:inception_lower":"1980-01-01",
    "date:inception_upper":"1980-01-31",
    "iso:country":"GB",
    "wof:name":"SK14 1PP",
    "wof:placetype":"postalcode"
},
  "geometry": {"coordinates":[-2.070188,53.449653],"type":"Point"}
}