{
  "type": "Feature",
  "properties": {
    "iso:country":"GB",
    "wof:name":"SK14 1PP",
    "wof:placetype":"postalcode"
},
  "geometry": {"coordinates":[-2.07018837110758,53.44965342523525],"type":"Point"}
}