{
  "type": "Feature",
  "properties": {
    "iso:country":"GB",
    "wof:name":"SS13 3QR",
    "wof:placetype":"postalcode"
},
  "geometry": {"coordinates":[0.5089995764863,51.57492278805206],"type":"Point"}
}