{
  "type": "Feature",
  "properties": {
    "iso:country": "GB",
    "wof:name": "SS13 3QR",
    "wof:placetype": "postalcode"
  },
  "geometry": {"coordinates":[0.509,51.574923],"type":"Point"}
}
