{
  "type": "Feature",
  "properties": {
    "date:inception_lower": "1983-03-01",
    "date:inception_upper": "1983-03-01",
    "iso:country": "GB",
    "wof:name": "SS13 3QR",
    "wof:placetype": "postalcode"
  },
  "geometry": {"coordinates":[0.509,51.574923],"type":"Point"}
}
