{
  "type": "Feature",
  "properties": {
    "date:inception_lower": "2001-06-01",
    "date:inception_upper": "2001-06-01",
    "iso:country": "GB",
    "wof:name": "NN4 0DF",
    "wof:placetype": "postalcode"
  },
  "geometry": {"coordinates":[-0.900841,52.194721],"type":"Point"}
}
