{
  "type": "Feature",
  "properties": {
    "iso:country":"GB",
    "wof:name":"MK16 8LF",
    "wof:placetype":"postalcode"
},
  "geometry": {"coordinates":[-0.74364787442016,52.10502215637084],"type":"Point"}
}