{
  "type": "Feature",
  "properties": {
    "iso:country": "GB",
    "wof:name": "IV20 1UF",
    "wof:placetype": "postalcode"
  },
  "geometry": {"coordinates":[-3.910719,57.755804],"type":"Point"}
}
