{
  "type": "Feature",
  "properties": {
    "iso:country":"GB",
    "wof:name":"IV20 1UF",
    "wof:placetype":"postalcode"
},
  "geometry": {"coordinates":[-3.91071885223362,57.75580351431196],"type":"Point"}
}