{
  "type": "Feature",
  "properties": {
    "date:inception_lower": "2016-12-01",
    "date:inception_upper": "2016-12-01",
    "iso:country": "GB",
    "wof:name": "PR6 7XR",
    "wof:placetype": "postalcode"
  },
  "geometry": {"coordinates":[-2.635521,53.67458],"type":"Point"}
}
