{
  "type": "Feature",
  "properties": {
    "date:inception_lower": "2023-10-01",
    "date:inception_upper": "2023-10-01",
    "iso:country": "GB",
    "wof:name": "YO17 9FR",
    "wof:placetype": "postalcode"
  },
  "geometry": {"coordinates":[-0.791852,54.116093],"type":"Point"}
}
