{
  "type": "Feature",
  "properties": {
    "date:inception_lower": "2004-05-01",
    "date:inception_upper": "2004-05-01",
    "iso:country": "GB",
    "wof:name": "EH49 6PZ",
    "wof:placetype": "postalcode"
  },
  "geometry": {"coordinates":[-3.612945,55.964735],"type":"Point"}
}
