{
  "type": "Feature",
  "properties": {
    "iso:country":"GB",
    "wof:name":"NG17 7LQ",
    "wof:placetype":"postalcode"
},
  "geometry": {"coordinates":[-1.24032465208817,53.09795810496543],"type":"Point"}
}