{
  "type": "Feature",
  "properties": {
    "iso:country":"GB",
    "wof:name":"SA34 0AW",
    "wof:placetype":"postalcode"
},
  "geometry": {"coordinates":[-4.61356875289324,51.81837038428311],"type":"Point"}
}