{
  "type": "Feature",
  "properties": {
    "iso:country": "GB",
    "wof:name": "E3 3UY",
    "wof:placetype": "postalcode"
  },
  "geometry": {"coordinates":[-0.018267,51.518982],"type":"Point"}
}
