{
  "type": "Feature",
  "properties": {
    "iso:country":"GB",
    "wof:name":"GL7 1TY",
    "wof:placetype":"postalcode"
},
  "geometry": {"coordinates":[-1.96701805627393,51.70220283179104],"type":"Point"}
}