{
  "type": "Feature",
  "properties": {
    "iso:country": "GB",
    "wof:name": "EH8 8FA",
    "wof:placetype": "postalcode"
  },
  "geometry": {"coordinates":[-3.17994,55.951078],"type":"Point"}
}
