{
  "type": "Feature",
  "properties": {
    "date:inception_lower": "2013-01-01",
    "date:inception_upper": "2013-01-01",
    "iso:country": "GB",
    "wof:name": "EH8 8FA",
    "wof:placetype": "postalcode"
  },
  "geometry": {"coordinates":[-3.17994,55.951078],"type":"Point"}
}
