{
  "type": "Feature",
  "properties": {
    "iso:country":"GB",
    "wof:name":"EH8 8FA",
    "wof:placetype":"postalcode"
},
  "geometry": {"coordinates":[-3.17993996053134,55.95107826272351],"type":"Point"}
}