{
  "type": "Feature",
  "properties": {
    "iso:country":"GB",
    "wof:name":"E16 4LE",
    "wof:placetype":"postalcode"
},
  "geometry": {"coordinates":[0.01211340064642,51.52243802081431],"type":"Point"}
}