{
  "type": "Feature",
  "properties": {
    "iso:country": "GB",
    "wof:name": "GU16 8BU",
    "wof:placetype": "postalcode"
  },
  "geometry": {"coordinates":[-0.735104,51.312523],"type":"Point"}
}
