{
  "type": "Feature",
  "properties": {
    "iso:country":"GB",
    "wof:name":"WF2 0XW",
    "wof:placetype":"postalcode"
},
  "geometry": {"coordinates":[-1.52474307120053,53.71449820205903],"type":"Point"}
}