{
  "type": "Feature",
  "properties": {
    "iso:country":"GB",
    "wof:name":"TN20 6TD",
    "wof:placetype":"postalcode"
},
  "geometry": {"coordinates":[0.26708529062953,51.02132689704229],"type":"Point"}
}