{
  "type": "Feature",
  "properties": {
    "date:inception_lower": "2022-06-01",
    "date:inception_upper": "2022-06-01",
    "iso:country": "GB",
    "wof:name": "MK45 2PG",
    "wof:placetype": "postalcode"
  },
  "geometry": {"coordinates":[-0.455685,52.028486],"type":"Point"}
}
