{
  "type": "Feature",
  "properties": {
    "iso:country":"GB",
    "wof:name":"LS10 1LD",
    "wof:placetype":"postalcode"
},
  "geometry": {"coordinates":[-1.53497206344914,53.78855543212426],"type":"Point"}
}