{
  "type": "Feature",
  "properties": {
    "iso:country":"GB",
    "wof:name":"TW5 9LG",
    "wof:placetype":"postalcode"
},
  "geometry": {"coordinates":[-0.39928691085297,51.48418089749456],"type":"Point"}
}