{
  "type": "Feature",
  "properties": {
    "date:inception_lower": "1980-01-01",
    "date:inception_upper": "1980-01-01",
    "iso:country": "GB",
    "wof:name": "TW5 9LG",
    "wof:placetype": "postalcode"
  },
  "geometry": {"coordinates":[-0.399287,51.484181],"type":"Point"}
}
