{
  "type": "Feature",
  "properties": {
    "iso:country":"GB",
    "wof:name":"BD23 2QX",
    "wof:placetype":"postalcode"
},
  "geometry": {"coordinates":[-2.01948259101895,53.95047169754692],"type":"Point"}
}