{
  "type": "Feature",
  "properties": {
    "iso:country":"GB",
    "wof:name":"BB5 0LJ",
    "wof:placetype":"postalcode"
},
  "geometry": {"coordinates":[-2.38182236996326,53.75024365788809],"type":"Point"}
}