{
  "type": "Feature",
  "properties": {
    "iso:country": "GB",
    "wof:name": "BB5 0LJ",
    "wof:placetype": "postalcode"
  },
  "geometry": {"coordinates":[-2.381822,53.750244],"type":"Point"}
}
