{
  "type": "Feature",
  "properties": {
    "iso:country":"GB",
    "wof:name":"SW5 9QN",
    "wof:placetype":"postalcode"
},
  "geometry": {"coordinates":[-0.19870449584299,51.49398674223845],"type":"Point"}
}