{
  "type": "Feature",
  "properties": {
    "iso:country":"GB",
    "wof:name":"CB4 2AF",
    "wof:placetype":"postalcode"
},
  "geometry": {"coordinates":[0.12656097876296,52.22175978466423],"type":"Point"}
}