{
  "type": "Feature",
  "properties": {
    "date:inception_lower": "1980-01-01",
    "date:inception_upper": "1980-01-01",
    "iso:country": "GB",
    "wof:name": "CB4 2AF",
    "wof:placetype": "postalcode"
  },
  "geometry": {"coordinates":[0.126631,52.221719],"type":"Point"}
}
