{
  "type": "Feature",
  "properties": {
    "iso:country": "GB",
    "wof:name": "CB4 2AF",
    "wof:placetype": "postalcode"
  },
  "geometry": {"coordinates":[0.126631,52.221719],"type":"Point"}
}
