{
  "type": "Feature",
  "properties": {
    "iso:country":"GB",
    "wof:name":"M45 7LH",
    "wof:placetype":"postalcode"
},
  "geometry": {"coordinates":[-2.31081238343471,53.54550854558865],"type":"Point"}
}