{
  "type": "Feature",
  "properties": {
    "iso:country": "GB",
    "wof:name": "DA10 0NG",
    "wof:placetype": "postalcode"
  },
  "geometry": {"coordinates":[0.304651,51.44081],"type":"Point"}
}
