{
  "type": "Feature",
  "properties": {
    "date:inception_lower":"1990-07-01",
    "date:inception_upper":"1990-07-31",
    "iso:country":"GB",
    "wof:name":"DA10 0NG",
    "wof:placetype":"postalcode"
},
  "geometry": {"coordinates":[0.304651,51.44081],"type":"Point"}
}