{
  "type": "Feature",
  "properties": {
    "iso:country":"GB",
    "wof:name":"EH13 0DD",
    "wof:placetype":"postalcode"
},
  "geometry": {"coordinates":[-3.25237104355637,55.90386287836701],"type":"Point"}
}