{
  "type": "Feature",
  "properties": {
    "iso:country":"GB",
    "wof:name":"CB6 3LG",
    "wof:placetype":"postalcode"
},
  "geometry": {"coordinates":[0.23434489303896,52.32454258624729],"type":"Point"}
}