{
  "type": "Feature",
  "properties": {
    "iso:country": "GB",
    "wof:name": "CR3 6FJ",
    "wof:placetype": "postalcode"
  },
  "geometry": {"coordinates":[-0.077235,51.287545],"type":"Point"}
}
