{
  "type": "Feature",
  "properties": {
    "iso:country":"GB",
    "wof:name":"PE1 5SL",
    "wof:placetype":"postalcode"
},
  "geometry": {"coordinates":[-0.20977140907179,52.57855545880562],"type":"Point"}
}