{
  "type": "Feature",
  "properties": {
    "date:inception_lower": "1999-12-01",
    "date:inception_upper": "1999-12-01",
    "iso:country": "GB",
    "wof:name": "PE1 5SL",
    "wof:placetype": "postalcode"
  },
  "geometry": {"coordinates":[-0.209771,52.578555],"type":"Point"}
}
