{
  "type": "Feature",
  "properties": {
    "iso:country": "GB",
    "wof:name": "SS9 1DR",
    "wof:placetype": "postalcode"
  },
  "geometry": {"coordinates":[0.663391,51.540113],"type":"Point"}
}
