{
  "type": "Feature",
  "properties": {
    "iso:country":"GB",
    "wof:name":"LL41 4RY",
    "wof:placetype":"postalcode"
},
  "geometry": {"coordinates":[-3.92362896472795,52.90286973320131],"type":"Point"}
}