{
  "type": "Feature",
  "properties": {
    "iso:country":"GB",
    "wof:name":"G67 1NG",
    "wof:placetype":"postalcode"
},
  "geometry": {"coordinates":[-3.98885075332098,55.94822281978273],"type":"Point"}
}