{
  "type": "Feature",
  "properties": {
    "iso:country":"GB",
    "wof:name":"GU30 7AR",
    "wof:placetype":"postalcode"
},
  "geometry": {"coordinates":[-0.80315235980676,51.08080462332236],"type":"Point"}
}