{
  "type": "Feature",
  "properties": {
    "date:inception_lower": "1980-01-01",
    "date:inception_upper": "1980-01-01",
    "iso:country": "GB",
    "wof:name": "TW11 8EZ",
    "wof:placetype": "postalcode"
  },
  "geometry": {"coordinates":[-0.332207,51.427898],"type":"Point"}
}
