{
  "type": "Feature",
  "properties": {
    "iso:country":"GB",
    "wof:name":"TW11 8EZ",
    "wof:placetype":"postalcode"
},
  "geometry": {"coordinates":[-0.33220753682168,51.42789800840516],"type":"Point"}
}