{
  "type": "Feature",
  "properties": {
    "iso:country": "GB",
    "wof:name": "LU1 5HH",
    "wof:placetype": "postalcode"
  },
  "geometry": {"coordinates":[-0.42398,51.871854],"type":"Point"}
}
