{
  "type": "Feature",
  "properties": {
    "date:inception_lower": "2023-06-01",
    "date:inception_upper": "2023-06-01",
    "iso:country": "GB",
    "wof:name": "CH46 8AQ",
    "wof:placetype": "postalcode"
  },
  "geometry": {"coordinates":[-3.111736,53.407653],"type":"Point"}
}
