{
  "type": "Feature",
  "properties": {
    "iso:country":"GB",
    "wof:name":"IP1 5EB",
    "wof:placetype":"postalcode"
},
  "geometry": {"coordinates":[1.12584858730732,52.07576442122674],"type":"Point"}
}