{
  "type": "Feature",
  "properties": {
    "iso:country":"GB",
    "wof:name":"DN15 8XP",
    "wof:placetype":"postalcode"
},
  "geometry": {"coordinates":[-0.67954576305005,53.62500104574968],"type":"Point"}
}