{
  "type": "Feature",
  "properties": {
    "iso:country":"GB",
    "wof:name":"IP33 2RA",
    "wof:placetype":"postalcode"
},
  "geometry": {"coordinates":[0.71210067259657,52.23327673358535],"type":"Point"}
}