{
  "type": "Feature",
  "properties": {
    "iso:country":"GB",
    "wof:name":"BN26 5BN",
    "wof:placetype":"postalcode"
},
  "geometry": {"coordinates":[0.24430942892863,50.82020732999483],"type":"Point"}
}