{
  "type": "Feature",
  "properties": {
    "iso:country":"GB",
    "wof:name":"LS23 7AW",
    "wof:placetype":"postalcode"
},
  "geometry": {"coordinates":[-1.34816240740831,53.91231424460629],"type":"Point"}
}