{
  "type": "Feature",
  "properties": {
    "date:inception_lower":"1980-01-01",
    "date:inception_upper":"1980-01-31",
    "iso:country":"GB",
    "wof:name":"LS23 7AW",
    "wof:placetype":"postalcode"
},
  "geometry": {"coordinates":[-1.348168,53.912331],"type":"Point"}
}