{
  "type": "Feature",
  "properties": {
    "iso:country":"GB",
    "wof:name":"TR26 2NT",
    "wof:placetype":"postalcode"
},
  "geometry": {"coordinates":[-5.4575416023716,50.19661559259328],"type":"Point"}
}