{
  "type": "Feature",
  "properties": {
    "date:inception_lower":"1999-06-01",
    "date:inception_upper":"1999-06-30",
    "iso:country":"GB",
    "wof:name":"EX16 6UG",
    "wof:placetype":"postalcode"
},
  "geometry": {"coordinates":[-3.476262,50.914617],"type":"Point"}
}