{
  "type": "Feature",
  "properties": {
    "iso:country": "GB",
    "wof:name": "EX16 6UG",
    "wof:placetype": "postalcode"
  },
  "geometry": {"coordinates":[-3.476262,50.914617],"type":"Point"}
}
