{
  "type": "Feature",
  "properties": {
    "iso:country":"GB",
    "wof:name":"E1 4AH",
    "wof:placetype":"postalcode"
},
  "geometry": {"coordinates":[-0.0473565859803,51.52226511319757],"type":"Point"}
}