{
  "type": "Feature",
  "properties": {
    "iso:country":"GB",
    "wof:name":"MK15 9JP",
    "wof:placetype":"postalcode"
},
  "geometry": {"coordinates":[-0.72452661784869,52.06333190318296],"type":"Point"}
}