{
  "type": "Feature",
  "properties": {
    "date:inception_lower": "1987-10-01",
    "date:inception_upper": "1987-10-01",
    "iso:country": "GB",
    "wof:name": "MK15 9JP",
    "wof:placetype": "postalcode"
  },
  "geometry": {"coordinates":[-0.724527,52.063332],"type":"Point"}
}
