{
  "type": "Feature",
  "properties": {
    "iso:country": "GB",
    "wof:name": "RG7 5ES",
    "wof:placetype": "postalcode"
  },
  "geometry": {"coordinates":[-1.09758,51.445486],"type":"Point"}
}
