{
  "type": "Feature",
  "properties": {
    "iso:country":"GB",
    "wof:name":"RG7 5ES",
    "wof:placetype":"postalcode"
},
  "geometry": {"coordinates":[-1.0975802727138,51.44548624178783],"type":"Point"}
}