{
  "type": "Feature",
  "properties": {
    "iso:country": "GB",
    "wof:name": "SK13 1EN",
    "wof:placetype": "postalcode"
  },
  "geometry": {"coordinates":[-1.955003,53.461144],"type":"Point"}
}
