{
  "type": "Feature",
  "properties": {
    "iso:country":"GB",
    "wof:name":"SA1 4QH",
    "wof:placetype":"postalcode"
},
  "geometry": {"coordinates":[-3.96270665057465,51.61766111790027],"type":"Point"}
}