{
  "type": "Feature",
  "properties": {
    "iso:country":"GB",
    "wof:name":"SE1 3RQ",
    "wof:placetype":"postalcode"
},
  "geometry": {"coordinates":[-0.08679594398133,51.50025376974064],"type":"Point"}
}