{
  "type": "Feature",
  "properties": {
    "iso:country": "GB",
    "wof:name": "SO19 6AB",
    "wof:placetype": "postalcode"
  },
  "geometry": {"coordinates":[-1.327073,50.909885],"type":"Point"}
}
