{
  "type": "Feature",
  "properties": {
    "iso:country":"GB",
    "wof:name":"HP16 0RD",
    "wof:placetype":"postalcode"
},
  "geometry": {"coordinates":[-0.6720969950413,51.70242067876833],"type":"Point"}
}