{
  "type": "Feature",
  "properties": {
    "iso:country": "GB",
    "wof:name": "HP16 0RD",
    "wof:placetype": "postalcode"
  },
  "geometry": {"coordinates":[-0.672097,51.702421],"type":"Point"}
}
