{
  "type": "Feature",
  "properties": {
    "date:inception_lower": "1980-01-01",
    "date:inception_upper": "1980-01-01",
    "iso:country": "GB",
    "wof:name": "DY10 2RQ",
    "wof:placetype": "postalcode"
  },
  "geometry": {"coordinates":[-2.232212,52.395794],"type":"Point"}
}
