{
  "type": "Feature",
  "properties": {
    "iso:country":"GB",
    "wof:name":"DY10 2RQ",
    "wof:placetype":"postalcode"
},
  "geometry": {"coordinates":[-2.23221245222409,52.39579384029108],"type":"Point"}
}