{
  "type": "Feature",
  "properties": {
    "iso:country": "GB",
    "wof:name": "EX12 3NE",
    "wof:placetype": "postalcode"
  },
  "geometry": {"coordinates":[-3.091452,50.696912],"type":"Point"}
}
