{
  "type": "Feature",
  "properties": {
    "date:inception_lower":"2018-08-01",
    "date:inception_upper":"2018-08-31",
    "iso:country":"GB",
    "wof:name":"EX12 3NE",
    "wof:placetype":"postalcode"
},
  "geometry": {"coordinates":[-3.091452,50.696912],"type":"Point"}
}