{
  "type": "Feature",
  "properties": {
    "iso:country":"GB",
    "wof:name":"SW9 6ER",
    "wof:placetype":"postalcode"
},
  "geometry": {"coordinates":[-0.10837132026244,51.4785179980523],"type":"Point"}
}