{
  "type": "Feature",
  "properties": {
    "iso:country":"GB",
    "wof:name":"HU5 1RH",
    "wof:placetype":"postalcode"
},
  "geometry": {"coordinates":[-0.33668373134821,53.75845189155135],"type":"Point"}
}