{
  "type": "Feature",
  "properties": {
    "iso:country": "GB",
    "wof:name": "HU5 1RH",
    "wof:placetype": "postalcode"
  },
  "geometry": {"coordinates":[-0.336462,53.75847],"type":"Point"}
}
