{
  "type": "Feature",
  "properties": {
    "date:inception_lower": "2023-06-01",
    "date:inception_upper": "2023-06-01",
    "iso:country": "GB",
    "wof:name": "KT2 7FP",
    "wof:placetype": "postalcode"
  },
  "geometry": {"coordinates":[-0.262478,51.42934],"type":"Point"}
}
