{
  "type": "Feature",
  "properties": {
    "date:inception_lower":"1984-10-01",
    "date:inception_upper":"1984-10-31",
    "iso:country":"GB",
    "wof:name":"MK45 2HJ",
    "wof:placetype":"postalcode"
},
  "geometry": {"coordinates":[-0.496329,52.033847],"type":"Point"}
}