{
  "type": "Feature",
  "properties": {
    "date:inception_lower": "1998-06-01",
    "date:inception_upper": "1998-06-01",
    "iso:country": "GB",
    "wof:name": "YO31 9HA",
    "wof:placetype": "postalcode"
  },
  "geometry": {"coordinates":[-1.061989,53.984006],"type":"Point"}
}
