{
  "type": "Feature",
  "properties": {
    "iso:country":"GB",
    "wof:name":"CA2 6EA",
    "wof:placetype":"postalcode"
},
  "geometry": {"coordinates":[-2.95325073925876,54.88247836355187],"type":"Point"}
}