{
  "type": "Feature",
  "properties": {
    "iso:country": "GB",
    "wof:name": "SA13 3BS",
    "wof:placetype": "postalcode"
  },
  "geometry": {"coordinates":[-3.6322,51.680677],"type":"Point"}
}
