{
  "type": "Feature",
  "properties": {
    "date:inception_lower":"1980-01-01",
    "date:inception_upper":"1980-01-31",
    "iso:country":"GB",
    "wof:name":"SA13 3BS",
    "wof:placetype":"postalcode"
},
  "geometry": {"coordinates":[-3.6322,51.680677],"type":"Point"}
}