{
  "type": "Feature",
  "properties": {
    "iso:country":"GB",
    "wof:name":"BS35 2BL",
    "wof:placetype":"postalcode"
},
  "geometry": {"coordinates":[-2.52471820225218,51.6058165295761],"type":"Point"}
}