{
  "type": "Feature",
  "properties": {
    "iso:country": "GB",
    "wof:name": "NR33 7AH",
    "wof:placetype": "postalcode"
  },
  "geometry": {"coordinates":[1.719694,52.419356],"type":"Point"}
}
