{
  "type": "Feature",
  "properties": {
    "iso:country":"GB",
    "wof:name":"NR33 7AH",
    "wof:placetype":"postalcode"
},
  "geometry": {"coordinates":[1.71969353702424,52.41935566501258],"type":"Point"}
}