{
  "type": "Feature",
  "properties": {
    "date:inception_lower":"2009-11-01",
    "date:inception_upper":"2009-11-30",
    "iso:country":"GB",
    "wof:name":"NR33 7AH",
    "wof:placetype":"postalcode"
},
  "geometry": {"coordinates":[1.719694,52.419356],"type":"Point"}
}