{
  "type": "Feature",
  "properties": {
    "iso:country":"GB",
    "wof:name":"LA13 9UA",
    "wof:placetype":"postalcode"
},
  "geometry": {"coordinates":[-3.20181559495802,54.12822286733117],"type":"Point"}
}