{
  "type": "Feature",
  "properties": {
    "iso:country":"GB",
    "wof:name":"BN3 6DJ",
    "wof:placetype":"postalcode"
},
  "geometry": {"coordinates":[-0.17369324074694,50.84989399464955],"type":"Point"}
}