{
  "type": "Feature",
  "properties": {
    "date:inception_lower": "1980-01-01",
    "date:inception_upper": "1980-01-01",
    "iso:country": "GB",
    "wof:name": "BN3 6DJ",
    "wof:placetype": "postalcode"
  },
  "geometry": {"coordinates":[-0.173693,50.849894],"type":"Point"}
}
