{
  "type": "Feature",
  "properties": {
    "iso:country":"GB",
    "wof:name":"RG9 1NG",
    "wof:placetype":"postalcode"
},
  "geometry": {"coordinates":[-0.90769321388757,51.52521153460834],"type":"Point"}
}