{
  "type": "Feature",
  "properties": {
    "date:inception_lower": "1980-01-01",
    "date:inception_upper": "1980-01-01",
    "iso:country": "GB",
    "wof:name": "RG9 1NG",
    "wof:placetype": "postalcode"
  },
  "geometry": {"coordinates":[-0.907693,51.525212],"type":"Point"}
}
