{
  "type": "Feature",
  "properties": {
    "iso:country":"GB",
    "wof:name":"LE7 9XJ",
    "wof:placetype":"postalcode"
},
  "geometry": {"coordinates":[-0.8585281037601,52.59756270339886],"type":"Point"}
}