{
  "type": "Feature",
  "properties": {
    "iso:country": "GB",
    "wof:name": "LE7 9XJ",
    "wof:placetype": "postalcode"
  },
  "geometry": {"coordinates":[-0.858528,52.597563],"type":"Point"}
}
