{
  "type": "Feature",
  "properties": {
    "iso:country": "GB",
    "wof:name": "B60 4DZ",
    "wof:placetype": "postalcode"
  },
  "geometry": {"coordinates":[-2.086474,52.29967],"type":"Point"}
}
