{
  "type": "Feature",
  "properties": {
    "iso:country":"GB",
    "wof:name":"B60 4DZ",
    "wof:placetype":"postalcode"
},
  "geometry": {"coordinates":[-2.08647420851946,52.299669991168],"type":"Point"}
}