{
  "type": "Feature",
  "properties": {
    "iso:country": "GB",
    "wof:name": "GL56 0ET",
    "wof:placetype": "postalcode"
  },
  "geometry": {"coordinates":[-1.703299,51.984779],"type":"Point"}
}
