{
  "type": "Feature",
  "properties": {
    "iso:country":"GB",
    "wof:name":"DA1 3QX",
    "wof:placetype":"postalcode"
},
  "geometry": {"coordinates":[0.17455013158289,51.44411497223388],"type":"Point"}
}