{
  "type": "Feature",
  "properties": {
    "date:inception_lower":"2002-06-01",
    "date:inception_upper":"2002-06-30",
    "iso:country":"GB",
    "wof:name":"DA1 3QX",
    "wof:placetype":"postalcode"
},
  "geometry": {"coordinates":[0.17455,51.444115],"type":"Point"}
}