{
  "type": "Feature",
  "properties": {
    "date:inception_lower":"2000-06-01",
    "date:inception_upper":"2000-06-30",
    "iso:country":"GB",
    "wof:name":"PE26 2LR",
    "wof:placetype":"postalcode"
},
  "geometry": {"coordinates":[-0.115056,52.43855],"type":"Point"}
}