{
  "type": "Feature",
  "properties": {
    "iso:country":"GB",
    "wof:name":"MK3 6HS",
    "wof:placetype":"postalcode"
},
  "geometry": {"coordinates":[-0.74486521661724,51.99864298941628],"type":"Point"}
}