{
  "type": "Feature",
  "properties": {
    "date:inception_lower": "2019-09-01",
    "date:inception_upper": "2019-09-01",
    "iso:country": "GB",
    "wof:name": "NE66 1DF",
    "wof:placetype": "postalcode"
  },
  "geometry": {"coordinates":[-1.712327,55.406799],"type":"Point"}
}
