{
  "type": "Feature",
  "properties": {
    "iso:country":"GB",
    "wof:name":"OX15 6ET",
    "wof:placetype":"postalcode"
},
  "geometry": {"coordinates":[-1.43323999173567,52.04292210045495],"type":"Point"}
}