{
  "type": "Feature",
  "properties": {
    "iso:country":"GB",
    "wof:name":"NR15 1AD",
    "wof:placetype":"postalcode"
},
  "geometry": {"coordinates":[1.20776184428265,52.52261243713129],"type":"Point"}
}