{
  "type": "Feature",
  "properties": {
    "iso:country": "GB",
    "wof:name": "NR15 1AD",
    "wof:placetype": "postalcode"
  },
  "geometry": {"coordinates":[1.207762,52.522612],"type":"Point"}
}
