{
  "type": "Feature",
  "properties": {
    "iso:country":"GB",
    "wof:name":"S21 4FD",
    "wof:placetype":"postalcode"
},
  "geometry": {"coordinates":[-1.35312841960482,53.30959651254083],"type":"Point"}
}