{
  "type": "Feature",
  "properties": {
    "date:inception_lower": "1992-08-01",
    "date:inception_upper": "1992-08-01",
    "iso:country": "GB",
    "wof:name": "NN6 7BJ",
    "wof:placetype": "postalcode"
  },
  "geometry": {"coordinates":[-1.072663,52.344154],"type":"Point"}
}
