{
  "type": "Feature",
  "properties": {
    "iso:country":"GB",
    "wof:name":"NN6 7BJ",
    "wof:placetype":"postalcode"
},
  "geometry": {"coordinates":[-1.07266264168318,52.34415363706156],"type":"Point"}
}