{
  "type": "Feature",
  "properties": {
    "iso:country":"GB",
    "wof:name":"CA7 4JZ",
    "wof:placetype":"postalcode"
},
  "geometry": {"coordinates":[-3.39740804108014,54.85179332514416],"type":"Point"}
}