{
  "type": "Feature",
  "properties": {
    "iso:country": "GB",
    "wof:name": "CA7 4JZ",
    "wof:placetype": "postalcode"
  },
  "geometry": {"coordinates":[-3.397408,54.851793],"type":"Point"}
}
