{
  "type": "Feature",
  "properties": {
    "date:inception_lower": "2022-07-01",
    "date:inception_upper": "2022-07-01",
    "iso:country": "GB",
    "wof:name": "RM13 8RW",
    "wof:placetype": "postalcode"
  },
  "geometry": {"coordinates":[0.170787,51.523729],"type":"Point"}
}
