{
  "type": "Feature",
  "properties": {
    "iso:country":"GB",
    "wof:name":"RG7 5PE",
    "wof:placetype":"postalcode"
},
  "geometry": {"coordinates":[-1.15881957482971,51.41502772376507],"type":"Point"}
}