{
  "type": "Feature",
  "properties": {
    "iso:country":"GB",
    "wof:name":"M45 8RE",
    "wof:placetype":"postalcode"
},
  "geometry": {"coordinates":[-2.27243467790577,53.55483325161296],"type":"Point"}
}