{
  "type": "Feature",
  "properties": {
    "iso:country":"GB",
    "wof:name":"LS27 0BQ",
    "wof:placetype":"postalcode"
},
  "geometry": {"coordinates":[-1.61342656384518,53.73601094162467],"type":"Point"}
}