{
  "type": "Feature",
  "properties": {
    "iso:country":"GB",
    "wof:name":"BN11 4SF",
    "wof:placetype":"postalcode"
},
  "geometry": {"coordinates":[-0.38674101879653,50.81416511918245],"type":"Point"}
}