{
  "type": "Feature",
  "properties": {
    "iso:country": "GB",
    "wof:name": "BN11 4SF",
    "wof:placetype": "postalcode"
  },
  "geometry": {"coordinates":[-0.386716,50.814157],"type":"Point"}
}
