{
  "type": "Feature",
  "properties": {
    "iso:country":"GB",
    "wof:name":"PE7 1YP",
    "wof:placetype":"postalcode"
},
  "geometry": {"coordinates":[-0.10978503085417,52.56296636762887],"type":"Point"}
}