{
  "type": "Feature",
  "properties": {
    "iso:country":"GB",
    "wof:name":"SS16 5JU",
    "wof:placetype":"postalcode"
},
  "geometry": {"coordinates":[0.46314892091485,51.55361818626955],"type":"Point"}
}