{
  "type": "Feature",
  "properties": {
    "iso:country":"GB",
    "wof:name":"BS40 8XX",
    "wof:placetype":"postalcode"
},
  "geometry": {"coordinates":[-2.63289193210935,51.35244762510188],"type":"Point"}
}