{
  "type": "Feature",
  "properties": {
    "date:inception_lower": "2023-11-01",
    "date:inception_upper": "2023-11-01",
    "iso:country": "GB",
    "wof:name": "DD11 5FP",
    "wof:placetype": "postalcode"
  },
  "geometry": {"coordinates":[-2.559608,56.57648],"type":"Point"}
}
