{
  "type": "Feature",
  "properties": {
    "iso:country":"GB",
    "wof:name":"SY3 8SW",
    "wof:placetype":"postalcode"
},
  "geometry": {"coordinates":[-2.80321550973837,52.70805261188203],"type":"Point"}
}