{
  "type": "Feature",
  "properties": {
    "date:inception_lower":"1995-01-01",
    "date:inception_upper":"1995-01-31",
    "iso:country":"GB",
    "wof:name":"PR6 7UQ",
    "wof:placetype":"postalcode"
},
  "geometry": {"coordinates":[-2.647311,53.696945],"type":"Point"}
}