{
  "type": "Feature",
  "properties": {
    "iso:country":"GB",
    "wof:name":"PR6 7UQ",
    "wof:placetype":"postalcode"
},
  "geometry": {"coordinates":[-2.64731107958758,53.69694462337505],"type":"Point"}
}