{
  "type": "Feature",
  "properties": {
    "iso:country":"GB",
    "wof:name":"NG32 1AU",
    "wof:placetype":"postalcode"
},
  "geometry": {"coordinates":[-0.68363599226296,52.91391040116652],"type":"Point"}
}