{
  "type": "Feature",
  "properties": {
    "date:inception_lower": "1980-01-01",
    "date:inception_upper": "1980-01-01",
    "iso:country": "GB",
    "wof:name": "NG32 1AU",
    "wof:placetype": "postalcode"
  },
  "geometry": {"coordinates":[-0.683636,52.91391],"type":"Point"}
}
