{
  "type": "Feature",
  "properties": {
    "iso:country": "GB",
    "wof:name": "GU52 7UG",
    "wof:placetype": "postalcode"
  },
  "geometry": {"coordinates":[-0.840539,51.270884],"type":"Point"}
}
