{
  "type": "Feature",
  "properties": {
    "iso:country":"GB",
    "wof:name":"GU52 7UG",
    "wof:placetype":"postalcode"
},
  "geometry": {"coordinates":[-0.8405386276548,51.27088408763311],"type":"Point"}
}