{
  "type": "Feature",
  "properties": {
    "iso:country":"GB",
    "wof:name":"NN17 2TX",
    "wof:placetype":"postalcode"
},
  "geometry": {"coordinates":[-0.720147296509,52.49749633704023],"type":"Point"}
}