{
  "type": "Feature",
  "properties": {
    "iso:country":"GB",
    "wof:name":"E17 8JU",
    "wof:placetype":"postalcode"
},
  "geometry": {"coordinates":[-0.01805081573671,51.57569322311499],"type":"Point"}
}