{
  "type": "Feature",
  "properties": {
    "date:inception_lower":"1996-12-01",
    "date:inception_upper":"1996-12-31",
    "iso:country":"GB",
    "wof:name":"CB6 3SJ",
    "wof:placetype":"postalcode"
},
  "geometry": {"coordinates":[0.174896,52.353266],"type":"Point"}
}