{
  "type": "Feature",
  "properties": {
    "iso:country":"GB",
    "wof:name":"CB6 3SJ",
    "wof:placetype":"postalcode"
},
  "geometry": {"coordinates":[0.17489612222779,52.35326617631353],"type":"Point"}
}