{
  "type": "Feature",
  "properties": {
    "iso:country": "GB",
    "wof:name": "CB6 3SJ",
    "wof:placetype": "postalcode"
  },
  "geometry": {"coordinates":[0.174896,52.353266],"type":"Point"}
}
