{
  "type": "Feature",
  "properties": {
    "date:inception_lower":"1980-01-01",
    "date:inception_upper":"1980-01-31",
    "iso:country":"GB",
    "wof:name":"CM3 1PL",
    "wof:placetype":"postalcode"
},
  "geometry": {"coordinates":[0.517899,51.810713],"type":"Point"}
}