{
  "type": "Feature",
  "properties": {
    "iso:country":"GB",
    "wof:name":"CM3 1PL",
    "wof:placetype":"postalcode"
},
  "geometry": {"coordinates":[0.51781068583772,51.81068784573161],"type":"Point"}
}