{
  "type": "Feature",
  "properties": {
    "date:inception_lower":"1980-01-01",
    "date:inception_upper":"1980-01-31",
    "iso:country":"GB",
    "wof:name":"SK13 8BS",
    "wof:placetype":"postalcode"
},
  "geometry": {"coordinates":[-1.948472,53.443884],"type":"Point"}
}