{
  "type": "Feature",
  "properties": {
    "date:inception_lower": "2021-02-01",
    "date:inception_upper": "2021-02-01",
    "iso:country": "GB",
    "wof:name": "NG31 8SX",
    "wof:placetype": "postalcode"
  },
  "geometry": {"coordinates":[-0.674767,52.916881],"type":"Point"}
}
