{
  "type": "Feature",
  "properties": {
    "iso:country":"GB",
    "wof:name":"WS3 4QX",
    "wof:placetype":"postalcode"
},
  "geometry": {"coordinates":[-1.98057280188971,52.63036077254858],"type":"Point"}
}