{
  "type": "Feature",
  "properties": {
    "date:inception_lower": "1980-01-01",
    "date:inception_upper": "1980-01-01",
    "iso:country": "GB",
    "wof:name": "CA1 2TN",
    "wof:placetype": "postalcode"
  },
  "geometry": {"coordinates":[-2.90487,54.88887],"type":"Point"}
}
