{
  "type": "Feature",
  "properties": {
    "iso:country":"GB",
    "wof:name":"CA1 2TN",
    "wof:placetype":"postalcode"
},
  "geometry": {"coordinates":[-2.9048704584142,54.888869551738],"type":"Point"}
}