{
  "type": "Feature",
  "properties": {
    "iso:country": "GB",
    "wof:name": "CA1 2TN",
    "wof:placetype": "postalcode"
  },
  "geometry": {"coordinates":[-2.90487,54.88887],"type":"Point"}
}
