{
  "type": "Feature",
  "properties": {
    "date:inception_lower": "1980-01-01",
    "date:inception_upper": "1980-01-01",
    "iso:country": "GB",
    "wof:name": "BS20 0PP",
    "wof:placetype": "postalcode"
  },
  "geometry": {"coordinates":[-2.700477,51.474198],"type":"Point"}
}
