{
  "type": "Feature",
  "properties": {
    "iso:country": "GB",
    "wof:name": "GL2 8EX",
    "wof:placetype": "postalcode"
  },
  "geometry": {"coordinates":[-2.271525,51.88941],"type":"Point"}
}
