{
  "type": "Feature",
  "properties": {
    "iso:country":"GB",
    "wof:name":"BH3 7HZ",
    "wof:placetype":"postalcode"
},
  "geometry": {"coordinates":[-1.88740943417649,50.74037123254968],"type":"Point"}
}