{
  "type": "Feature",
  "properties": {
    "date:inception_lower": "2001-12-01",
    "date:inception_upper": "2001-12-01",
    "iso:country": "GB",
    "wof:name": "WR11 8UY",
    "wof:placetype": "postalcode"
  },
  "geometry": {"coordinates":[-1.899533,52.16395],"type":"Point"}
}
