{
  "type": "Feature",
  "properties": {
    "date:inception_lower":"2005-04-01",
    "date:inception_upper":"2005-04-30",
    "iso:country":"GB",
    "wof:name":"BL5 3WG",
    "wof:placetype":"postalcode"
},
  "geometry": {"coordinates":[-2.524998,53.560785],"type":"Point"}
}