{
  "type": "Feature",
  "properties": {
    "iso:country":"GB",
    "wof:name":"BL5 3WG",
    "wof:placetype":"postalcode"
},
  "geometry": {"coordinates":[-2.52458782397078,53.56060807684395],"type":"Point"}
}