{
  "type": "Feature",
  "properties": {
    "date:inception_lower":"1980-01-01",
    "date:inception_upper":"1980-01-31",
    "iso:country":"GB",
    "wof:name":"SY11 4HE",
    "wof:placetype":"postalcode"
},
  "geometry": {"coordinates":[-2.915688,52.830952],"type":"Point"}
}