{
  "type": "Feature",
  "properties": {
    "iso:country": "GB",
    "wof:name": "SY11 4HE",
    "wof:placetype": "postalcode"
  },
  "geometry": {"coordinates":[-2.915688,52.830952],"type":"Point"}
}
