{
  "type": "Feature",
  "properties": {
    "iso:country": "GB",
    "wof:name": "BB7 3EA",
    "wof:placetype": "postalcode"
  },
  "geometry": {"coordinates":[-2.462577,53.95031],"type":"Point"}
}
