{
  "type": "Feature",
  "properties": {
    "iso:country":"GB",
    "wof:name":"DN3 3NU",
    "wof:placetype":"postalcode"
},
  "geometry": {"coordinates":[-1.03181061441145,53.50985242535184],"type":"Point"}
}