{
  "type": "Feature",
  "properties": {
    "iso:country":"GB",
    "wof:name":"BS22 9SX",
    "wof:placetype":"postalcode"
},
  "geometry": {"coordinates":[-2.95225479227767,51.36251536186585],"type":"Point"}
}