{
  "type": "Feature",
  "properties": {
    "iso:country":"GB",
    "wof:name":"S61 1JL",
    "wof:placetype":"postalcode"
},
  "geometry": {"coordinates":[-1.39769562835527,53.43907881627919],"type":"Point"}
}