{
  "type": "Feature",
  "properties": {
    "iso:country":"GB",
    "wof:name":"AB10 6SS",
    "wof:placetype":"postalcode"
},
  "geometry": {"coordinates":[-2.1225849729865,57.14024100991645],"type":"Point"}
}