{
  "type": "Feature",
  "properties": {
    "date:inception_lower": "2016-01-01",
    "date:inception_upper": "2016-01-01",
    "iso:country": "GB",
    "wof:name": "WA15 7AG",
    "wof:placetype": "postalcode"
  },
  "geometry": {"coordinates":[-2.317944,53.393629],"type":"Point"}
}
