{
  "type": "Feature",
  "properties": {
    "date:inception_lower": "2005-02-01",
    "date:inception_upper": "2005-02-01",
    "iso:country": "GB",
    "wof:name": "TA1 9SH",
    "wof:placetype": "postalcode"
  },
  "geometry": {"coordinates":[-3.106795,51.021077],"type":"Point"}
}
