{
  "type": "Feature",
  "properties": {
    "date:inception_lower": "1980-01-01",
    "date:inception_upper": "1980-01-01",
    "iso:country": "GB",
    "wof:name": "IP32 6ED",
    "wof:placetype": "postalcode"
  },
  "geometry": {"coordinates":[0.70653,52.256777],"type":"Point"}
}
