{
  "type": "Feature",
  "properties": {
    "iso:country": "GB",
    "wof:name": "SN3 4NF",
    "wof:placetype": "postalcode"
  },
  "geometry": {"coordinates":[-1.746324,51.581667],"type":"Point"}
}
