{
  "type": "Feature",
  "properties": {
    "iso:country": "GB",
    "wof:name": "DH7 7DT",
    "wof:placetype": "postalcode"
  },
  "geometry": {"coordinates":[-1.641262,54.785106],"type":"Point"}
}
