{
  "type": "Feature",
  "properties": {
    "iso:country":"GB",
    "wof:name":"DH7 7DT",
    "wof:placetype":"postalcode"
},
  "geometry": {"coordinates":[-1.64126254956966,54.78510586907082],"type":"Point"}
}