{
  "type": "Feature",
  "properties": {
    "iso:country":"GB",
    "wof:name":"WS14 0EY",
    "wof:placetype":"postalcode"
},
  "geometry": {"coordinates":[-1.88031786486391,52.64482054470451],"type":"Point"}
}