{
  "type": "Feature",
  "properties": {
    "iso:country":"GB",
    "wof:name":"NE3 1YN",
    "wof:placetype":"postalcode"
},
  "geometry": {"coordinates":[-1.60700731968797,55.00625352003722],"type":"Point"}
}