{
  "type": "Feature",
  "properties": {
    "date:inception_lower": "1980-01-01",
    "date:inception_upper": "1980-01-01",
    "iso:country": "GB",
    "wof:name": "NE3 1YN",
    "wof:placetype": "postalcode"
  },
  "geometry": {"coordinates":[-1.607007,55.006254],"type":"Point"}
}
