{
  "type": "Feature",
  "properties": {
    "iso:country": "GB",
    "wof:name": "B91 1TP",
    "wof:placetype": "postalcode"
  },
  "geometry": {"coordinates":[-1.803626,52.406783],"type":"Point"}
}
