{
  "type": "Feature",
  "properties": {
    "iso:country":"GB",
    "wof:name":"ST12 9AQ",
    "wof:placetype":"postalcode"
},
  "geometry": {"coordinates":[-2.15806065623909,52.94532043184022],"type":"Point"}
}