{
  "type": "Feature",
  "properties": {
    "iso:country": "GB",
    "wof:name": "KA11 1PQ",
    "wof:placetype": "postalcode"
  },
  "geometry": {"coordinates":[-4.630168,55.618468],"type":"Point"}
}
