{
  "type": "Feature",
  "properties": {
    "iso:country":"GB",
    "wof:name":"KA11 1PQ",
    "wof:placetype":"postalcode"
},
  "geometry": {"coordinates":[-4.63052577386684,55.6185259582694],"type":"Point"}
}