{
  "type": "Feature",
  "properties": {
    "iso:country":"GB",
    "wof:name":"EX23 8HA",
    "wof:placetype":"postalcode"
},
  "geometry": {"coordinates":[-4.53343142382115,50.83389023501672],"type":"Point"}
}