{
  "type": "Feature",
  "properties": {
    "iso:country": "GB",
    "wof:name": "WC1B 4HS",
    "wof:placetype": "postalcode"
  },
  "geometry": {"coordinates":[-0.124395,51.521168],"type":"Point"}
}
