{
  "type": "Feature",
  "properties": {
    "date:inception_lower": "2017-12-01",
    "date:inception_upper": "2017-12-01",
    "iso:country": "GB",
    "wof:name": "LE67 2DZ",
    "wof:placetype": "postalcode"
  },
  "geometry": {"coordinates":[-1.36474,52.708176],"type":"Point"}
}
