{
  "type": "Feature",
  "properties": {
    "iso:country": "GB",
    "wof:name": "TF2 9EF",
    "wof:placetype": "postalcode"
  },
  "geometry": {"coordinates":[-2.435844,52.689081],"type":"Point"}
}
