{
  "type": "Feature",
  "properties": {
    "iso:country":"GB",
    "wof:name":"TF2 9EF",
    "wof:placetype":"postalcode"
},
  "geometry": {"coordinates":[-2.43584367185664,52.68908088098825],"type":"Point"}
}