{
  "type": "Feature",
  "properties": {
    "date:inception_lower":"1980-01-01",
    "date:inception_upper":"1980-01-31",
    "iso:country":"GB",
    "wof:name":"TF2 9EF",
    "wof:placetype":"postalcode"
},
  "geometry": {"coordinates":[-2.435844,52.689081],"type":"Point"}
}