{
  "type": "Feature",
  "properties": {
    "iso:country":"GB",
    "wof:name":"NG2 7GS",
    "wof:placetype":"postalcode"
},
  "geometry": {"coordinates":[-1.1475904581009,52.91509664895553],"type":"Point"}
}