{
  "type": "Feature",
  "properties": {
    "iso:country":"GB",
    "wof:name":"OX17 3RQ",
    "wof:placetype":"postalcode"
},
  "geometry": {"coordinates":[-1.27550471359135,52.02073201378234],"type":"Point"}
}