{
  "type": "Feature",
  "properties": {
    "iso:country": "GB",
    "wof:name": "OX17 3RQ",
    "wof:placetype": "postalcode"
  },
  "geometry": {"coordinates":[-1.275505,52.020732],"type":"Point"}
}
