{
  "type": "Feature",
  "properties": {
    "iso:country":"GB",
    "wof:name":"SA4 8RF",
    "wof:placetype":"postalcode"
},
  "geometry": {"coordinates":[-4.03796881864336,51.71337150037256],"type":"Point"}
}