{
  "type": "Feature",
  "properties": {
    "date:inception_lower": "1980-01-01",
    "date:inception_upper": "1980-01-01",
    "iso:country": "GB",
    "wof:name": "TS10 1PS",
    "wof:placetype": "postalcode"
  },
  "geometry": {"coordinates":[-1.080533,54.609235],"type":"Point"}
}
