{
  "type": "Feature",
  "properties": {
    "date:inception_lower": "1998-12-01",
    "date:inception_upper": "1998-12-01",
    "iso:country": "GB",
    "wof:name": "EX31 3UR",
    "wof:placetype": "postalcode"
  },
  "geometry": {"coordinates":[-4.093881,51.0686],"type":"Point"}
}
