{
  "type": "Feature",
  "properties": {
    "date:inception_lower": "1987-10-01",
    "date:inception_upper": "1987-10-01",
    "iso:country": "GB",
    "wof:name": "WF10 3TB",
    "wof:placetype": "postalcode"
  },
  "geometry": {"coordinates":[-1.30163,53.721846],"type":"Point"}
}
