{
  "type": "Feature",
  "properties": {
    "iso:country":"GB",
    "wof:name":"WF10 3TB",
    "wof:placetype":"postalcode"
},
  "geometry": {"coordinates":[-1.30163031677696,53.72184598152733],"type":"Point"}
}