{
  "type": "Feature",
  "properties": {
    "iso:country":"GB",
    "wof:name":"TD11 3HY",
    "wof:placetype":"postalcode"
},
  "geometry": {"coordinates":[-2.29078263114837,55.71684658519326],"type":"Point"}
}