{
  "type": "Feature",
  "properties": {
    "iso:country": "GB",
    "wof:name": "HX1 4TY",
    "wof:placetype": "postalcode"
  },
  "geometry": {"coordinates":[-1.88551,53.730063],"type":"Point"}
}
