{
  "type": "Feature",
  "properties": {
    "date:inception_lower": "2004-09-01",
    "date:inception_upper": "2004-09-01",
    "iso:country": "GB",
    "wof:name": "DE73 8FD",
    "wof:placetype": "postalcode"
  },
  "geometry": {"coordinates":[-1.424328,52.825345],"type":"Point"}
}
