{
  "type": "Feature",
  "properties": {
    "iso:country": "GB",
    "wof:name": "DE73 8FD",
    "wof:placetype": "postalcode"
  },
  "geometry": {"coordinates":[-1.424328,52.825345],"type":"Point"}
}
