{
  "type": "Feature",
  "properties": {
    "iso:country":"GB",
    "wof:name":"LE5 1UF",
    "wof:placetype":"postalcode"
},
  "geometry": {"coordinates":[-1.07275005411922,52.65794028963811],"type":"Point"}
}