{
  "type": "Feature",
  "properties": {
    "iso:country": "GB",
    "wof:name": "LE65 1HN",
    "wof:placetype": "postalcode"
  },
  "geometry": {"coordinates":[-1.459175,52.744441],"type":"Point"}
}
