{
  "type": "Feature",
  "properties": {
    "date:inception_lower": "1995-01-01",
    "date:inception_upper": "1995-01-01",
    "iso:country": "GB",
    "wof:name": "LE65 1HN",
    "wof:placetype": "postalcode"
  },
  "geometry": {"coordinates":[-1.459175,52.744441],"type":"Point"}
}
