{
  "type": "Feature",
  "properties": {
    "iso:country": "GB",
    "wof:name": "SK5 7PL",
    "wof:placetype": "postalcode"
  },
  "geometry": {"coordinates":[-2.163123,53.422507],"type":"Point"}
}
