{
  "type": "Feature",
  "properties": {
    "iso:country":"GB",
    "wof:name":"SK5 7PL",
    "wof:placetype":"postalcode"
},
  "geometry": {"coordinates":[-2.16312324054525,53.42250705725994],"type":"Point"}
}