{
  "type": "Feature",
  "properties": {
    "iso:country": "GB",
    "wof:name": "NN17 3AY",
    "wof:placetype": "postalcode"
  },
  "geometry": {"coordinates":[-0.596308,52.557057],"type":"Point"}
}
