{
  "type": "Feature",
  "properties": {
    "iso:country":"GB",
    "wof:name":"NN17 3AY",
    "wof:placetype":"postalcode"
},
  "geometry": {"coordinates":[-0.5963220204214,52.55703951688041],"type":"Point"}
}