{
  "type": "Feature",
  "properties": {
    "iso:country": "GB",
    "wof:name": "NN17 3AY",
    "wof:placetype": "postalcode"
  },
  "geometry": {"coordinates":[-0.597793,52.556293],"type":"Point"}
}
