{
  "type": "Feature",
  "properties": {
    "iso:country":"GB",
    "wof:name":"W12 9JB",
    "wof:placetype":"postalcode"
},
  "geometry": {"coordinates":[-0.23538364988773,51.50288935291729],"type":"Point"}
}