{
  "type": "Feature",
  "properties": {
    "iso:country":"GB",
    "wof:name":"BN11 3QN",
    "wof:placetype":"postalcode"
},
  "geometry": {"coordinates":[-0.39009603959381,50.80865364041715],"type":"Point"}
}