{
  "type": "Feature",
  "properties": {
    "iso:country":"GB",
    "wof:name":"E3 4JT",
    "wof:placetype":"postalcode"
},
  "geometry": {"coordinates":[-0.03388690656644,51.5200617229446],"type":"Point"}
}