{
  "type": "Feature",
  "properties": {
    "iso:country": "GB",
    "wof:name": "CH6 6LU",
    "wof:placetype": "postalcode"
  },
  "geometry": {"coordinates":[-3.189039,53.276762],"type":"Point"}
}
