{
  "type": "Feature",
  "properties": {
    "iso:country":"GB",
    "wof:name":"CH6 6LU",
    "wof:placetype":"postalcode"
},
  "geometry": {"coordinates":[-3.18903869315313,53.27676248762324],"type":"Point"}
}