{
  "type": "Feature",
  "properties": {
    "iso:country": "GB",
    "wof:name": "BD23 6EL",
    "wof:placetype": "postalcode"
  },
  "geometry": {"coordinates":[-1.950725,53.986338],"type":"Point"}
}
