{
  "type": "Feature",
  "properties": {
    "iso:country":"GB",
    "wof:name":"BD23 6EL",
    "wof:placetype":"postalcode"
},
  "geometry": {"coordinates":[-1.95000426349096,53.98647673660695],"type":"Point"}
}