{
  "type": "Feature",
  "properties": {
    "iso:country": "GB",
    "wof:name": "BB2 7FS",
    "wof:placetype": "postalcode"
  },
  "geometry": {"coordinates":[-2.52422,53.774833],"type":"Point"}
}
