{
  "type": "Feature",
  "properties": {
    "iso:country":"GB",
    "wof:name":"TQ13 8RQ",
    "wof:placetype":"postalcode"
},
  "geometry": {"coordinates":[-3.82128680676105,50.64388637608405],"type":"Point"}
}