{
  "type": "Feature",
  "properties": {
    "date:inception_lower": "1990-08-01",
    "date:inception_upper": "1990-08-01",
    "iso:country": "GB",
    "wof:name": "AB53 8DT",
    "wof:placetype": "postalcode"
  },
  "geometry": {"coordinates":[-2.426,57.524109],"type":"Point"}
}
