{
  "type": "Feature",
  "properties": {
    "iso:country": "GB",
    "wof:name": "BS26 2EU",
    "wof:placetype": "postalcode"
  },
  "geometry": {"coordinates":[-2.853411,51.291674],"type":"Point"}
}
