{
  "type": "Feature",
  "properties": {
    "iso:country":"GB",
    "wof:name":"BS26 2EU",
    "wof:placetype":"postalcode"
},
  "geometry": {"coordinates":[-2.85341109889482,51.29167438805354],"type":"Point"}
}