{
  "type": "Feature",
  "properties": {
    "iso:country":"GB",
    "wof:name":"TQ5 9SY",
    "wof:placetype":"postalcode"
},
  "geometry": {"coordinates":[-3.51139305607328,50.39486241912918],"type":"Point"}
}