{
  "type": "Feature",
  "properties": {
    "iso:country":"GB",
    "wof:name":"G83 7DA",
    "wof:placetype":"postalcode"
},
  "geometry": {"coordinates":[-4.72408553415561,56.20251120241439],"type":"Point"}
}