{
  "type": "Feature",
  "properties": {
    "date:inception_lower": "2018-06-01",
    "date:inception_upper": "2018-06-01",
    "iso:country": "GB",
    "wof:name": "LS25 7FJ",
    "wof:placetype": "postalcode"
  },
  "geometry": {"coordinates":[-1.367442,53.774926],"type":"Point"}
}
