{
  "type": "Feature",
  "properties": {
    "iso:country":"GB",
    "wof:name":"CB2 9JA",
    "wof:placetype":"postalcode"
},
  "geometry": {"coordinates":[0.11385462131483,52.17400728678756],"type":"Point"}
}