{
  "type": "Feature",
  "properties": {
    "iso:country": "GB",
    "wof:name": "SN25 2JW",
    "wof:placetype": "postalcode"
  },
  "geometry": {"coordinates":[-1.832645,51.600524],"type":"Point"}
}
