{
  "type": "Feature",
  "properties": {
    "iso:country": "GB",
    "wof:name": "PR6 8BB",
    "wof:placetype": "postalcode"
  },
  "geometry": {"coordinates":[-2.58839,53.707513],"type":"Point"}
}
