{
  "type": "Feature",
  "properties": {
    "iso:country":"GB",
    "wof:name":"PR6 8BB",
    "wof:placetype":"postalcode"
},
  "geometry": {"coordinates":[-2.58839047894728,53.7075132090536],"type":"Point"}
}