{
  "type": "Feature",
  "properties": {
    "iso:country":"GB",
    "wof:name":"M24 4RR",
    "wof:placetype":"postalcode"
},
  "geometry": {"coordinates":[-2.23503864893815,53.5427604082324],"type":"Point"}
}