{
  "type": "Feature",
  "properties": {
    "date:inception_lower": "1980-01-01",
    "date:inception_upper": "1980-01-01",
    "iso:country": "GB",
    "wof:name": "BH10 5NL",
    "wof:placetype": "postalcode"
  },
  "geometry": {"coordinates":[-1.898784,50.762548],"type":"Point"}
}
