{
  "type": "Feature",
  "properties": {
    "iso:country":"GB",
    "wof:name":"WF5 0AB",
    "wof:placetype":"postalcode"
},
  "geometry": {"coordinates":[-1.57434709477667,53.67574776158148],"type":"Point"}
}