{
  "type": "Feature",
  "properties": {
    "date:inception_lower": "1980-01-01",
    "date:inception_upper": "1980-01-01",
    "iso:country": "GB",
    "wof:name": "WF5 0AB",
    "wof:placetype": "postalcode"
  },
  "geometry": {"coordinates":[-1.574347,53.675748],"type":"Point"}
}
