{
  "type": "Feature",
  "properties": {
    "iso:country":"GB",
    "wof:name":"WR9 0JP",
    "wof:placetype":"postalcode"
},
  "geometry": {"coordinates":[-2.24157141065601,52.27964870590733],"type":"Point"}
}