{
  "type": "Feature",
  "properties": {
    "iso:country": "GB",
    "wof:name": "PH7 3AF",
    "wof:placetype": "postalcode"
  },
  "geometry": {"coordinates":[-3.837735,56.372571],"type":"Point"}
}
