{
  "type": "Feature",
  "properties": {
    "iso:country":"GB",
    "wof:name":"NE34 9AZ",
    "wof:placetype":"postalcode"
},
  "geometry": {"coordinates":[-1.45151077758561,54.96671459840251],"type":"Point"}
}