{
  "type": "Feature",
  "properties": {
    "iso:country":"GB",
    "wof:name":"PE28 0RX",
    "wof:placetype":"postalcode"
},
  "geometry": {"coordinates":[-0.4712872168742,52.36721462974361],"type":"Point"}
}