{
  "type": "Feature",
  "properties": {
    "date:inception_lower": "2000-06-01",
    "date:inception_upper": "2000-06-01",
    "iso:country": "GB",
    "wof:name": "PE28 0RX",
    "wof:placetype": "postalcode"
  },
  "geometry": {"coordinates":[-0.471287,52.367215],"type":"Point"}
}
