{
  "type": "Feature",
  "properties": {
    "date:inception_lower": "1980-01-01",
    "date:inception_upper": "1980-01-01",
    "iso:country": "GB",
    "wof:name": "ST3 4QA",
    "wof:placetype": "postalcode"
  },
  "geometry": {"coordinates":[-2.134699,52.979625],"type":"Point"}
}
