{
  "type": "Feature",
  "properties": {
    "iso:country": "GB",
    "wof:name": "SW4 8HL",
    "wof:placetype": "postalcode"
  },
  "geometry": {"coordinates":[-0.134636,51.449992],"type":"Point"}
}
