{
  "type": "Feature",
  "properties": {
    "date:inception_lower": "2006-01-01",
    "date:inception_upper": "2006-01-01",
    "iso:country": "GB",
    "wof:name": "EH27 8BZ",
    "wof:placetype": "postalcode"
  },
  "geometry": {"coordinates":[-3.428292,55.887867],"type":"Point"}
}
