{
  "type": "Feature",
  "properties": {
    "iso:country": "GB",
    "wof:name": "EH27 8BZ",
    "wof:placetype": "postalcode"
  },
  "geometry": {"coordinates":[-3.428292,55.887867],"type":"Point"}
}
