{
  "type": "Feature",
  "properties": {
    "iso:country":"GB",
    "wof:name":"M43 7JT",
    "wof:placetype":"postalcode"
},
  "geometry": {"coordinates":[-2.13106460610593,53.48856699025757],"type":"Point"}
}