{
  "type": "Feature",
  "properties": {
    "iso:country":"GB",
    "wof:name":"NN6 9QD",
    "wof:placetype":"postalcode"
},
  "geometry": {"coordinates":[-0.82344485118217,52.34205220046533],"type":"Point"}
}