{
  "type": "Feature",
  "properties": {
    "iso:country": "GB",
    "wof:name": "NN6 9QD",
    "wof:placetype": "postalcode"
  },
  "geometry": {"coordinates":[-0.823445,52.342052],"type":"Point"}
}
