{
  "type": "Feature",
  "properties": {
    "iso:country": "GB",
    "wof:name": "CT3 4EB",
    "wof:placetype": "postalcode"
  },
  "geometry": {"coordinates":[1.187371,51.345383],"type":"Point"}
}
