{
  "type": "Feature",
  "properties": {
    "iso:country":"GB",
    "wof:name":"CT3 4EB",
    "wof:placetype":"postalcode"
},
  "geometry": {"coordinates":[1.18737137385242,51.34538282358035],"type":"Point"}
}