{
  "type": "Feature",
  "properties": {
    "date:inception_lower": "2019-01-01",
    "date:inception_upper": "2019-01-01",
    "iso:country": "GB",
    "wof:name": "CV34 7BW",
    "wof:placetype": "postalcode"
  },
  "geometry": {"coordinates":[-1.55505,52.265516],"type":"Point"}
}
