{
  "type": "Feature",
  "properties": {
    "iso:country": "GB",
    "wof:name": "CV34 7BW",
    "wof:placetype": "postalcode"
  },
  "geometry": {"coordinates":[-1.554276,52.265226],"type":"Point"}
}
