{
  "type": "Feature",
  "properties": {
    "iso:country":"GB",
    "wof:name":"DT2 7ED",
    "wof:placetype":"postalcode"
},
  "geometry": {"coordinates":[-2.40987733233938,50.88075265967963],"type":"Point"}
}