{
  "type": "Feature",
  "properties": {
    "iso:country": "GB",
    "wof:name": "TA12 6BX",
    "wof:placetype": "postalcode"
  },
  "geometry": {"coordinates":[-2.777191,50.970995],"type":"Point"}
}
