{
  "type": "Feature",
  "properties": {
    "iso:country":"GB",
    "wof:name":"TA12 6BX",
    "wof:placetype":"postalcode"
},
  "geometry": {"coordinates":[-2.77719085735324,50.97099458508769],"type":"Point"}
}