{
  "type": "Feature",
  "properties": {
    "iso:country":"GB",
    "wof:name":"G66 4NH",
    "wof:placetype":"postalcode"
},
  "geometry": {"coordinates":[-4.14763844484371,55.92431989855709],"type":"Point"}
}