{
  "type": "Feature",
  "properties": {
    "date:inception_lower": "1980-01-01",
    "date:inception_upper": "1980-01-01",
    "iso:country": "GB",
    "wof:name": "MK12 5DB",
    "wof:placetype": "postalcode"
  },
  "geometry": {"coordinates":[-0.81445,52.054821],"type":"Point"}
}
