{
  "type": "Feature",
  "properties": {
    "iso:country":"GB",
    "wof:name":"MK12 5DB",
    "wof:placetype":"postalcode"
},
  "geometry": {"coordinates":[-0.81445052482242,52.0548210295136],"type":"Point"}
}