{
  "type": "Feature",
  "properties": {
    "iso:country": "GB",
    "wof:name": "MK12 5DB",
    "wof:placetype": "postalcode"
  },
  "geometry": {"coordinates":[-0.81445,52.054821],"type":"Point"}
}
