{
  "type": "Feature",
  "properties": {
    "date:inception_lower": "1980-01-01",
    "date:inception_upper": "1980-01-01",
    "iso:country": "GB",
    "wof:name": "HU5 4DY",
    "wof:placetype": "postalcode"
  },
  "geometry": {"coordinates":[-0.374233,53.761853],"type":"Point"}
}
