{
  "type": "Feature",
  "properties": {
    "iso:country":"GB",
    "wof:name":"HU5 4DY",
    "wof:placetype":"postalcode"
},
  "geometry": {"coordinates":[-0.37423314852327,53.76185255384519],"type":"Point"}
}