{
  "type": "Feature",
  "properties": {
    "date:inception_lower": "1980-01-01",
    "date:inception_upper": "1980-01-01",
    "iso:country": "GB",
    "wof:name": "TF3 5AF",
    "wof:placetype": "postalcode"
  },
  "geometry": {"coordinates":[-2.472259,52.68148],"type":"Point"}
}
