{
  "type": "Feature",
  "properties": {
    "iso:country": "GB",
    "wof:name": "TN21 8TU",
    "wof:placetype": "postalcode"
  },
  "geometry": {"coordinates":[0.286749,50.985958],"type":"Point"}
}
