{
  "type": "Feature",
  "properties": {
    "iso:country":"GB",
    "wof:name":"TN21 8TU",
    "wof:placetype":"postalcode"
},
  "geometry": {"coordinates":[0.28674886316489,50.98595805332863],"type":"Point"}
}