{
  "type": "Feature",
  "properties": {
    "iso:country":"GB",
    "wof:name":"NP26 3FE",
    "wof:placetype":"postalcode"
},
  "geometry": {"coordinates":[-2.81422988887265,51.57716331584064],"type":"Point"}
}