{
  "type": "Feature",
  "properties": {
    "date:inception_lower": "1999-06-01",
    "date:inception_upper": "1999-06-01",
    "iso:country": "GB",
    "wof:name": "NP26 3FE",
    "wof:placetype": "postalcode"
  },
  "geometry": {"coordinates":[-2.81425,51.577182],"type":"Point"}
}
