{
  "type": "Feature",
  "properties": {
    "iso:country": "GB",
    "wof:name": "NP26 3FE",
    "wof:placetype": "postalcode"
  },
  "geometry": {"coordinates":[-2.81423,51.577163],"type":"Point"}
}
