{
  "type": "Feature",
  "properties": {
    "date:inception_lower": "1980-01-01",
    "date:inception_upper": "1980-01-01",
    "iso:country": "GB",
    "wof:name": "TA19 9LH",
    "wof:placetype": "postalcode"
  },
  "geometry": {"coordinates":[-2.951805,50.945756],"type":"Point"}
}
