{
  "type": "Feature",
  "properties": {
    "date:inception_lower": "2014-06-01",
    "date:inception_upper": "2014-06-01",
    "iso:country": "GB",
    "wof:name": "AL10 9UQ",
    "wof:placetype": "postalcode"
  },
  "geometry": {"coordinates":[-0.232328,51.754563],"type":"Point"}
}
