{
  "type": "Feature",
  "properties": {
    "iso:country": "GB",
    "wof:name": "AL10 9UQ",
    "wof:placetype": "postalcode"
  },
  "geometry": {"coordinates":[-0.232328,51.754563],"type":"Point"}
}
