{
  "type": "Feature",
  "properties": {
    "iso:country":"GB",
    "wof:name":"AL10 9UQ",
    "wof:placetype":"postalcode"
},
  "geometry": {"coordinates":[-0.23232793355773,51.75456319002019],"type":"Point"}
}