{
  "type": "Feature",
  "properties": {
    "iso:country": "GB",
    "wof:name": "SN25 1PZ",
    "wof:placetype": "postalcode"
  },
  "geometry": {"coordinates":[-1.815184,51.594734],"type":"Point"}
}
