{
  "type": "Feature",
  "properties": {
    "iso:country":"GB",
    "wof:name":"CH4 8TH",
    "wof:placetype":"postalcode"
},
  "geometry": {"coordinates":[-2.92801814058332,53.17381709657546],"type":"Point"}
}