{
  "type": "Feature",
  "properties": {
    "date:inception_lower": "2018-05-01",
    "date:inception_upper": "2018-05-01",
    "iso:country": "GB",
    "wof:name": "PO10 8GH",
    "wof:placetype": "postalcode"
  },
  "geometry": {"coordinates":[-0.900458,50.846629],"type":"Point"}
}
