{
  "type": "Feature",
  "properties": {
    "iso:country": "GB",
    "wof:name": "PO10 8GH",
    "wof:placetype": "postalcode"
  },
  "geometry": {"coordinates":[-0.900217,50.846618],"type":"Point"}
}
