{
  "type": "Feature",
  "properties": {
    "date:inception_lower":"1980-01-01",
    "date:inception_upper":"1980-01-31",
    "iso:country":"GB",
    "wof:name":"BD1 2LF",
    "wof:placetype":"postalcode"
},
  "geometry": {"coordinates":[-1.767033,53.797927],"type":"Point"}
}