{
  "type": "Feature",
  "properties": {
    "iso:country":"GB",
    "wof:name":"LS24 9JP",
    "wof:placetype":"postalcode"
},
  "geometry": {"coordinates":[-1.27394036466888,53.88638955603557],"type":"Point"}
}