{
  "type": "Feature",
  "properties": {
    "iso:country":"GB",
    "wof:name":"DL10 4DW",
    "wof:placetype":"postalcode"
},
  "geometry": {"coordinates":[-1.73874692619519,54.40418902931366],"type":"Point"}
}