{
  "type": "Feature",
  "properties": {
    "iso:country": "GB",
    "wof:name": "DL10 4DW",
    "wof:placetype": "postalcode"
  },
  "geometry": {"coordinates":[-1.738416,54.40401],"type":"Point"}
}
