{
  "type": "Feature",
  "properties": {
    "iso:country": "GB",
    "wof:name": "KA7 1RL",
    "wof:placetype": "postalcode"
  },
  "geometry": {"coordinates":[-4.628408,55.46054],"type":"Point"}
}
