{
  "type": "Feature",
  "properties": {
    "iso:country":"GB",
    "wof:name":"KA7 1RL",
    "wof:placetype":"postalcode"
},
  "geometry": {"coordinates":[-4.62840804898316,55.46054007740371],"type":"Point"}
}