{
  "type": "Feature",
  "properties": {
    "date:inception_lower": "1980-01-01",
    "date:inception_upper": "1980-01-01",
    "iso:country": "GB",
    "wof:name": "CT17 0EF",
    "wof:placetype": "postalcode"
  },
  "geometry": {"coordinates":[1.301319,51.132495],"type":"Point"}
}
