{
  "type": "Feature",
  "properties": {
    "iso:country":"GB",
    "wof:name":"G68 0HD",
    "wof:placetype":"postalcode"
},
  "geometry": {"coordinates":[-3.94749865980486,55.98011223113098],"type":"Point"}
}