{
  "type": "Feature",
  "properties": {
    "date:inception_lower": "1980-01-01",
    "date:inception_upper": "1980-01-01",
    "iso:country": "GB",
    "wof:name": "G68 0HD",
    "wof:placetype": "postalcode"
  },
  "geometry": {"coordinates":[-3.947499,55.980112],"type":"Point"}
}
