{
  "type": "Feature",
  "properties": {
    "iso:country":"GB",
    "wof:name":"CV1 2WT",
    "wof:placetype":"postalcode"
},
  "geometry": {"coordinates":[-1.50812226565679,52.40099669004616],"type":"Point"}
}