{
  "type": "Feature",
  "properties": {
    "iso:country":"GB",
    "wof:name":"DE3 9FH",
    "wof:placetype":"postalcode"
},
  "geometry": {"coordinates":[-1.54328575692942,52.91563065506284],"type":"Point"}
}