{
  "type": "Feature",
  "properties": {
    "iso:country": "GB",
    "wof:name": "NG5 8QW",
    "wof:placetype": "postalcode"
  },
  "geometry": {"coordinates":[-1.109246,53.008109],"type":"Point"}
}
