{
  "type": "Feature",
  "properties": {
    "iso:country":"GB",
    "wof:name":"NG5 8QW",
    "wof:placetype":"postalcode"
},
  "geometry": {"coordinates":[-1.10924568501893,53.00810867405188],"type":"Point"}
}