{
  "type": "Feature",
  "properties": {
    "iso:country":"GB",
    "wof:name":"DD2 5AE",
    "wof:placetype":"postalcode"
},
  "geometry": {"coordinates":[-3.05990836351999,56.45922669717252],"type":"Point"}
}