{
  "type": "Feature",
  "properties": {
    "iso:country":"GB",
    "wof:name":"SO32 3QP",
    "wof:placetype":"postalcode"
},
  "geometry": {"coordinates":[-1.13922257071402,50.9615726251931],"type":"Point"}
}