{
  "type": "Feature",
  "properties": {
    "iso:country":"GB",
    "wof:name":"DY3 3PW",
    "wof:placetype":"postalcode"
},
  "geometry": {"coordinates":[-2.13648440546597,52.54374758631451],"type":"Point"}
}