{
  "type": "Feature",
  "properties": {
    "iso:country":"GB",
    "wof:name":"TR15 3DS",
    "wof:placetype":"postalcode"
},
  "geometry": {"coordinates":[-5.2663245610017,50.22612107014347],"type":"Point"}
}