{
  "type": "Feature",
  "properties": {
    "iso:country":"GB",
    "wof:name":"PA19 1RP",
    "wof:placetype":"postalcode"
},
  "geometry": {"coordinates":[-4.80715912192331,55.95706919574648],"type":"Point"}
}