{
  "type": "Feature",
  "properties": {
    "date:inception_lower":"2005-09-01",
    "date:inception_upper":"2005-09-30",
    "iso:country":"GB",
    "wof:name":"LL32 8QG",
    "wof:placetype":"postalcode"
},
  "geometry": {"coordinates":[-3.830023,53.278211],"type":"Point"}
}