{
  "type": "Feature",
  "properties": {
    "iso:country": "GB",
    "wof:name": "EH10 7BR",
    "wof:placetype": "postalcode"
  },
  "geometry": {"coordinates":[-3.214642,55.90141],"type":"Point"}
}
