{
  "type": "Feature",
  "properties": {
    "iso:country":"GB",
    "wof:name":"DH8 9QT",
    "wof:placetype":"postalcode"
},
  "geometry": {"coordinates":[-1.87889952428725,54.83291579594368],"type":"Point"}
}