{
  "type": "Feature",
  "properties": {
    "date:inception_lower": "1980-01-01",
    "date:inception_upper": "1980-01-01",
    "iso:country": "GB",
    "wof:name": "L25 4UB",
    "wof:placetype": "postalcode"
  },
  "geometry": {"coordinates":[-2.871923,53.386391],"type":"Point"}
}
