{
  "type": "Feature",
  "properties": {
    "iso:country":"GB",
    "wof:name":"OX12 0BH",
    "wof:placetype":"postalcode"
},
  "geometry": {"coordinates":[-1.4244662267707,51.60865595368188],"type":"Point"}
}