{
  "type": "Feature",
  "properties": {
    "iso:country":"GB",
    "wof:name":"BS9 3BQ",
    "wof:placetype":"postalcode"
},
  "geometry": {"coordinates":[-2.61790684869532,51.49046933403903],"type":"Point"}
}