{
  "type": "Feature",
  "properties": {
    "iso:country":"GB",
    "wof:name":"RG40 1PB",
    "wof:placetype":"postalcode"
},
  "geometry": {"coordinates":[-0.80200558968142,51.41080054349117],"type":"Point"}
}