{
  "type": "Feature",
  "properties": {
    "iso:country":"GB",
    "wof:name":"S36 1DF",
    "wof:placetype":"postalcode"
},
  "geometry": {"coordinates":[-1.59870889073891,53.4789329486356],"type":"Point"}
}