{
  "type": "Feature",
  "properties": {
    "iso:country":"GB",
    "wof:name":"GU21 3RX",
    "wof:placetype":"postalcode"
},
  "geometry": {"coordinates":[-0.59744583257399,51.32303297933546],"type":"Point"}
}