{
  "type": "Feature",
  "properties": {
    "date:inception_lower": "1991-09-01",
    "date:inception_upper": "1991-09-01",
    "iso:country": "GB",
    "wof:name": "GU21 3RX",
    "wof:placetype": "postalcode"
  },
  "geometry": {"coordinates":[-0.597446,51.323033],"type":"Point"}
}
