{
  "type": "Feature",
  "properties": {
    "iso:country": "GB",
    "wof:name": "LA3 2YF",
    "wof:placetype": "postalcode"
  },
  "geometry": {"coordinates":[-2.902007,54.04269],"type":"Point"}
}
