{
  "type": "Feature",
  "properties": {
    "iso:country":"GB",
    "wof:name":"LA3 2YF",
    "wof:placetype":"postalcode"
},
  "geometry": {"coordinates":[-2.90200753223762,54.04269042863567],"type":"Point"}
}