{
  "type": "Feature",
  "properties": {
    "iso:country": "GB",
    "wof:name": "TS16 0DB",
    "wof:placetype": "postalcode"
  },
  "geometry": {"coordinates":[-1.350364,54.527326],"type":"Point"}
}
