{
  "type": "Feature",
  "properties": {
    "date:inception_lower":"1980-01-01",
    "date:inception_upper":"1980-01-31",
    "iso:country":"GB",
    "wof:name":"TS16 0DB",
    "wof:placetype":"postalcode"
},
  "geometry": {"coordinates":[-1.350364,54.527326],"type":"Point"}
}