{
  "type": "Feature",
  "properties": {
    "iso:country":"GB",
    "wof:name":"AB51 7JF",
    "wof:placetype":"postalcode"
},
  "geometry": {"coordinates":[-2.50075175328363,57.18898645192423],"type":"Point"}
}