{
  "type": "Feature",
  "properties": {
    "date:inception_lower":"2002-05-01",
    "date:inception_upper":"2002-05-31",
    "iso:country":"GB",
    "wof:name":"AB51 7JF",
    "wof:placetype":"postalcode"
},
  "geometry": {"coordinates":[-2.500752,57.188986],"type":"Point"}
}