{
  "type": "Feature",
  "properties": {
    "iso:country":"GB",
    "wof:name":"SG14 1BJ",
    "wof:placetype":"postalcode"
},
  "geometry": {"coordinates":[-0.07600393327918,51.79693420504453],"type":"Point"}
}