{
  "type": "Feature",
  "properties": {
    "iso:country": "GB",
    "wof:name": "ST10 2EG",
    "wof:placetype": "postalcode"
  },
  "geometry": {"coordinates":[-1.99823,53.006301],"type":"Point"}
}
