{
  "type": "Feature",
  "properties": {
    "iso:country":"GB",
    "wof:name":"TN22 5EP",
    "wof:placetype":"postalcode"
},
  "geometry": {"coordinates":[0.08974037124469,50.98928966925888],"type":"Point"}
}