{
  "type": "Feature",
  "properties": {
    "iso:country":"GB",
    "wof:name":"KT22 9JQ",
    "wof:placetype":"postalcode"
},
  "geometry": {"coordinates":[-0.35537159554444,51.29623354940718],"type":"Point"}
}