{
  "type": "Feature",
  "properties": {
    "iso:country":"GB",
    "wof:name":"TA9 3LE",
    "wof:placetype":"postalcode"
},
  "geometry": {"coordinates":[-2.97220078918491,51.2285586270453],"type":"Point"}
}