{
  "type": "Feature",
  "properties": {
    "iso:country":"GB",
    "wof:name":"SW16 2EB",
    "wof:placetype":"postalcode"
},
  "geometry": {"coordinates":[-0.12979756293822,51.42716323480106],"type":"Point"}
}