{
  "type": "Feature",
  "properties": {
    "date:inception_lower": "2022-05-01",
    "date:inception_upper": "2022-05-01",
    "iso:country": "GB",
    "wof:name": "EH41 3FJ",
    "wof:placetype": "postalcode"
  },
  "geometry": {"coordinates":[-2.80328,55.949712],"type":"Point"}
}
