{
  "type": "Feature",
  "properties": {
    "iso:country":"GB",
    "wof:name":"BS16 9QR",
    "wof:placetype":"postalcode"
},
  "geometry": {"coordinates":[-2.48422157406232,51.47474209097138],"type":"Point"}
}