{
  "type": "Feature",
  "properties": {
    "date:inception_lower": "2009-06-01",
    "date:inception_upper": "2009-06-01",
    "iso:country": "GB",
    "wof:name": "BS16 9QR",
    "wof:placetype": "postalcode"
  },
  "geometry": {"coordinates":[-2.484222,51.474742],"type":"Point"}
}
