{
  "type": "Feature",
  "properties": {
    "iso:country": "GB",
    "wof:name": "WA5 0AJ",
    "wof:placetype": "postalcode"
  },
  "geometry": {"coordinates":[-2.61287,53.397243],"type":"Point"}
}
