{
  "type": "Feature",
  "properties": {
    "iso:country":"GB",
    "wof:name":"WA5 0AJ",
    "wof:placetype":"postalcode"
},
  "geometry": {"coordinates":[-2.61286973476652,53.39724302812539],"type":"Point"}
}