{
  "type": "Feature",
  "properties": {
    "iso:country": "GB",
    "wof:name": "PE32 2QH",
    "wof:placetype": "postalcode"
  },
  "geometry": {"coordinates":[0.773683,52.723295],"type":"Point"}
}
