{
  "type": "Feature",
  "properties": {
    "iso:country":"GB",
    "wof:name":"W1D 4JG",
    "wof:placetype":"postalcode"
},
  "geometry": {"coordinates":[-0.13299511541054,51.51276957093589],"type":"Point"}
}