{
  "type": "Feature",
  "properties": {
    "iso:country":"GB",
    "wof:name":"SG6 2AG",
    "wof:placetype":"postalcode"
},
  "geometry": {"coordinates":[-0.21743515554493,51.96101800898193],"type":"Point"}
}