{
  "type": "Feature",
  "properties": {
    "iso:country":"GB",
    "wof:name":"G81 5DY",
    "wof:placetype":"postalcode"
},
  "geometry": {"coordinates":[-4.39462241692395,55.9292188381965],"type":"Point"}
}