{
  "type": "Feature",
  "properties": {
    "iso:country":"GB",
    "wof:name":"SY6 7HQ",
    "wof:placetype":"postalcode"
},
  "geometry": {"coordinates":[-2.76452086520738,52.52641469990466],"type":"Point"}
}