{
  "type": "Feature",
  "properties": {
    "iso:country": "GB",
    "wof:name": "SY6 7HQ",
    "wof:placetype": "postalcode"
  },
  "geometry": {"coordinates":[-2.762209,52.524916],"type":"Point"}
}
