{
  "type": "Feature",
  "properties": {
    "iso:country":"GB",
    "wof:name":"L31 2HT",
    "wof:placetype":"postalcode"
},
  "geometry": {"coordinates":[-2.94595391568849,53.52036328265831],"type":"Point"}
}