{
  "type": "Feature",
  "properties": {
    "iso:country":"GB",
    "wof:name":"TR26 1JN",
    "wof:placetype":"postalcode"
},
  "geometry": {"coordinates":[-5.48238011715061,50.21264221443096],"type":"Point"}
}