{
  "type": "Feature",
  "properties": {
    "date:inception_lower": "2013-09-01",
    "date:inception_upper": "2013-09-01",
    "iso:country": "GB",
    "wof:name": "RG9 2FA",
    "wof:placetype": "postalcode"
  },
  "geometry": {"coordinates":[-0.906173,51.536914],"type":"Point"}
}
