{
  "type": "Feature",
  "properties": {
    "iso:country":"GB",
    "wof:name":"WS10 8AR",
    "wof:placetype":"postalcode"
},
  "geometry": {"coordinates":[-2.0317950136341,52.568265603808],"type":"Point"}
}