{
  "type": "Feature",
  "properties": {
    "iso:country":"GB",
    "wof:name":"BN17 7BW",
    "wof:placetype":"postalcode"
},
  "geometry": {"coordinates":[-0.54720406540965,50.81139027060813],"type":"Point"}
}