{
  "type": "Feature",
  "properties": {
    "iso:country": "GB",
    "wof:name": "OL2 6JQ",
    "wof:placetype": "postalcode"
  },
  "geometry": {"coordinates":[-2.107485,53.562538],"type":"Point"}
}
