{
  "type": "Feature",
  "properties": {
    "date:inception_lower": "1980-01-01",
    "date:inception_upper": "1980-01-01",
    "iso:country": "GB",
    "wof:name": "OL2 6JQ",
    "wof:placetype": "postalcode"
  },
  "geometry": {"coordinates":[-2.107485,53.562538],"type":"Point"}
}
