{
  "type": "Feature",
  "properties": {
    "iso:country":"GB",
    "wof:name":"BS2 8HR",
    "wof:placetype":"postalcode"
},
  "geometry": {"coordinates":[-2.59821359563241,51.46156454151831],"type":"Point"}
}