{
  "type": "Feature",
  "properties": {
    "iso:country": "GB",
    "wof:name": "SW18 1HF",
    "wof:placetype": "postalcode"
  },
  "geometry": {"coordinates":[-0.19515,51.45923],"type":"Point"}
}
