{
  "type": "Feature",
  "properties": {
    "iso:country": "GB",
    "wof:name": "W3 7LB",
    "wof:placetype": "postalcode"
  },
  "geometry": {"coordinates":[-0.256856,51.507698],"type":"Point"}
}
