{
  "type": "Feature",
  "properties": {
    "iso:country":"GB",
    "wof:name":"W3 7LB",
    "wof:placetype":"postalcode"
},
  "geometry": {"coordinates":[-0.2568562625899,51.50769765827512],"type":"Point"}
}