{
  "type": "Feature",
  "properties": {
    "iso:country":"GB",
    "wof:name":"SL4 4QL",
    "wof:placetype":"postalcode"
},
  "geometry": {"coordinates":[-0.70439528895016,51.46901106372077],"type":"Point"}
}