{
  "type": "Feature",
  "properties": {
    "date:inception_lower": "2023-07-01",
    "date:inception_upper": "2023-07-01",
    "iso:country": "GB",
    "wof:name": "NP44 3FX",
    "wof:placetype": "postalcode"
  },
  "geometry": {"coordinates":[-3.021893,51.647007],"type":"Point"}
}
