{
  "type": "Feature",
  "properties": {
    "iso:country":"GB",
    "wof:name":"BB7 9XD",
    "wof:placetype":"postalcode"
},
  "geometry": {"coordinates":[-2.42533565467936,53.83329933957593],"type":"Point"}
}