{
  "type": "Feature",
  "properties": {
    "date:inception_lower": "2023-05-01",
    "date:inception_upper": "2023-05-01",
    "iso:country": "GB",
    "wof:name": "NE23 8GB",
    "wof:placetype": "postalcode"
  },
  "geometry": {"coordinates":[-1.619794,55.080814],"type":"Point"}
}
