{
  "type": "Feature",
  "properties": {
    "iso:country":"GB",
    "wof:name":"EX17 6LN",
    "wof:placetype":"postalcode"
},
  "geometry": {"coordinates":[-3.84631969835737,50.80742736054526],"type":"Point"}
}