{
  "type": "Feature",
  "properties": {
    "iso:country": "GB",
    "wof:name": "EX17 6LN",
    "wof:placetype": "postalcode"
  },
  "geometry": {"coordinates":[-3.846606,50.808413],"type":"Point"}
}
