{
  "type": "Feature",
  "properties": {
    "date:inception_lower": "1980-01-01",
    "date:inception_upper": "1980-01-01",
    "iso:country": "GB",
    "wof:name": "EX17 6LN",
    "wof:placetype": "postalcode"
  },
  "geometry": {"coordinates":[-3.846606,50.808413],"type":"Point"}
}
