{
  "type": "Feature",
  "properties": {
    "iso:country": "GB",
    "wof:name": "EX17 6LN",
    "wof:placetype": "postalcode"
  },
  "geometry": {"coordinates":[-3.846339,50.807419],"type":"Point"}
}
