{
  "type": "Feature",
  "properties": {
    "date:inception_lower": "1980-01-01",
    "date:inception_upper": "1980-01-01",
    "iso:country": "GB",
    "wof:name": "LA6 2BU",
    "wof:placetype": "postalcode"
  },
  "geometry": {"coordinates":[-2.59545,54.200364],"type":"Point"}
}
