{
  "type": "Feature",
  "properties": {
    "iso:country":"GB",
    "wof:name":"LA6 2BU",
    "wof:placetype":"postalcode"
},
  "geometry": {"coordinates":[-2.59541862772153,54.20031928939781],"type":"Point"}
}