{
  "type": "Feature",
  "properties": {
    "iso:country":"GB",
    "wof:name":"N2 9BB",
    "wof:placetype":"postalcode"
},
  "geometry": {"coordinates":[-0.16758230634305,51.59392308206321],"type":"Point"}
}