{
  "type": "Feature",
  "properties": {
    "date:inception_lower":"2009-08-01",
    "date:inception_upper":"2009-08-31",
    "iso:country":"GB",
    "wof:name":"SR2 7RU",
    "wof:placetype":"postalcode"
},
  "geometry": {"coordinates":[-1.388528,54.897057],"type":"Point"}
}