{
  "type": "Feature",
  "properties": {
    "iso:country":"GB",
    "wof:name":"SY7 9AZ",
    "wof:placetype":"postalcode"
},
  "geometry": {"coordinates":[-2.80622159293935,52.40648723485621],"type":"Point"}
}