{
  "type": "Feature",
  "properties": {
    "iso:country":"GB",
    "wof:name":"BH17 8AT",
    "wof:placetype":"postalcode"
},
  "geometry": {"coordinates":[-1.96208771926679,50.7494118838959],"type":"Point"}
}