{
  "type": "Feature",
  "properties": {
    "date:inception_lower":"1980-01-01",
    "date:inception_upper":"1980-01-31",
    "iso:country":"GB",
    "wof:name":"WV12 5QQ",
    "wof:placetype":"postalcode"
},
  "geometry": {"coordinates":[-2.039263,52.604249],"type":"Point"}
}