{
  "type": "Feature",
  "properties": {
    "iso:country":"GB",
    "wof:name":"WV12 5QQ",
    "wof:placetype":"postalcode"
},
  "geometry": {"coordinates":[-2.03926320819155,52.60424949948779],"type":"Point"}
}