{
  "type": "Feature",
  "properties": {
    "date:inception_lower":"2004-03-01",
    "date:inception_upper":"2004-03-31",
    "iso:country":"GB",
    "wof:name":"SN25 2EL",
    "wof:placetype":"postalcode"
},
  "geometry": {"coordinates":[-1.807299,51.602202],"type":"Point"}
}