{
  "type": "Feature",
  "properties": {
    "iso:country":"GB",
    "wof:name":"SN25 2EL",
    "wof:placetype":"postalcode"
},
  "geometry": {"coordinates":[-1.80729932803485,51.60220207347484],"type":"Point"}
}