{
  "type": "Feature",
  "properties": {
    "iso:country":"GB",
    "wof:name":"TW15 2SB",
    "wof:placetype":"postalcode"
},
  "geometry": {"coordinates":[-0.46754482989048,51.42987131528598],"type":"Point"}
}