{
  "type": "Feature",
  "properties": {
    "date:inception_lower": "1991-09-01",
    "date:inception_upper": "1991-09-01",
    "iso:country": "GB",
    "wof:name": "TW15 2SB",
    "wof:placetype": "postalcode"
  },
  "geometry": {"coordinates":[-0.467545,51.429871],"type":"Point"}
}
