{
  "type": "Feature",
  "properties": {
    "iso:country":"GB",
    "wof:name":"N9 9EZ",
    "wof:placetype":"postalcode"
},
  "geometry": {"coordinates":[-0.06498366873152,51.62766169691852],"type":"Point"}
}