{
  "type": "Feature",
  "properties": {
    "iso:country": "GB",
    "wof:name": "AB56 5RG",
    "wof:placetype": "postalcode"
  },
  "geometry": {"coordinates":[-3.013706,57.663897],"type":"Point"}
}
