{
  "type": "Feature",
  "properties": {
    "iso:country":"GB",
    "wof:name":"AB56 5RG",
    "wof:placetype":"postalcode"
},
  "geometry": {"coordinates":[-3.01370564237401,57.66389664373919],"type":"Point"}
}