{
  "type": "Feature",
  "properties": {
    "date:inception_lower":"1997-12-01",
    "date:inception_upper":"1997-12-31",
    "iso:country":"GB",
    "wof:name":"BS31 1QF",
    "wof:placetype":"postalcode"
},
  "geometry": {"coordinates":[-2.490313,51.406362],"type":"Point"}
}