{
  "type": "Feature",
  "properties": {
    "date:inception_lower": "1980-01-01",
    "date:inception_upper": "1980-01-01",
    "iso:country": "GB",
    "wof:name": "BN11 2DN",
    "wof:placetype": "postalcode"
  },
  "geometry": {"coordinates":[-0.353506,50.817091],"type":"Point"}
}
