{
  "type": "Feature",
  "properties": {
    "date:inception_lower": "1980-01-01",
    "date:inception_upper": "1980-01-01",
    "iso:country": "GB",
    "wof:name": "CV7 7GD",
    "wof:placetype": "postalcode"
  },
  "geometry": {"coordinates":[-1.641961,52.386527],"type":"Point"}
}
