{
  "type": "Feature",
  "properties": {
    "iso:country":"GB",
    "wof:name":"NE22 5LB",
    "wof:placetype":"postalcode"
},
  "geometry": {"coordinates":[-1.5793687925379,55.13287465404072],"type":"Point"}
}