{
  "type": "Feature",
  "properties": {
    "iso:country": "GB",
    "wof:name": "NE22 5LB",
    "wof:placetype": "postalcode"
  },
  "geometry": {"coordinates":[-1.579369,55.132875],"type":"Point"}
}
