{
  "type": "Feature",
  "properties": {
    "date:inception_lower":"2005-08-01",
    "date:inception_upper":"2005-08-31",
    "iso:country":"GB",
    "wof:name":"SN3 4RB",
    "wof:placetype":"postalcode"
},
  "geometry": {"coordinates":[-1.724848,51.579587],"type":"Point"}
}