{
  "type": "Feature",
  "properties": {
    "iso:country": "GB",
    "wof:name": "SN3 4RB",
    "wof:placetype": "postalcode"
  },
  "geometry": {"coordinates":[-1.724848,51.579587],"type":"Point"}
}
