{
  "type": "Feature",
  "properties": {
    "iso:country":"GB",
    "wof:name":"DY8 4HF",
    "wof:placetype":"postalcode"
},
  "geometry": {"coordinates":[-2.15373343115383,52.46697040506271],"type":"Point"}
}