{
  "type": "Feature",
  "properties": {
    "date:inception_lower": "2003-06-01",
    "date:inception_upper": "2003-06-01",
    "iso:country": "GB",
    "wof:name": "G20 7SN",
    "wof:placetype": "postalcode"
  },
  "geometry": {"coordinates":[-4.263628,55.884612],"type":"Point"}
}
