{
  "type": "Feature",
  "properties": {
    "iso:country":"GB",
    "wof:name":"B33 8RB",
    "wof:placetype":"postalcode"
},
  "geometry": {"coordinates":[-1.8018711043475,52.48038115036204],"type":"Point"}
}