{
  "type": "Feature",
  "properties": {
    "iso:country":"GB",
    "wof:name":"N17 6QE",
    "wof:placetype":"postalcode"
},
  "geometry": {"coordinates":[-0.07081239113312,51.59141011909436],"type":"Point"}
}