{
  "type": "Feature",
  "properties": {
    "iso:country":"GB",
    "wof:name":"G83 9LU",
    "wof:placetype":"postalcode"
},
  "geometry": {"coordinates":[-4.5425991173288,56.00319828218478],"type":"Point"}
}