{
  "type": "Feature",
  "properties": {
    "iso:country": "GB",
    "wof:name": "G69 7RR",
    "wof:placetype": "postalcode"
  },
  "geometry": {"coordinates":[-4.07253,55.852727],"type":"Point"}
}
