{
  "type": "Feature",
  "properties": {
    "iso:country":"GB",
    "wof:name":"G69 7RR",
    "wof:placetype":"postalcode"
},
  "geometry": {"coordinates":[-4.07198870614123,55.85194057166532],"type":"Point"}
}