{
  "type": "Feature",
  "properties": {
    "iso:country":"GB",
    "wof:name":"AB31 5JN",
    "wof:placetype":"postalcode"
},
  "geometry": {"coordinates":[-2.41628338471038,57.05757530374464],"type":"Point"}
}