{
  "type": "Feature",
  "properties": {
    "iso:country": "GB",
    "wof:name": "NG16 6AD",
    "wof:placetype": "postalcode"
  },
  "geometry": {"coordinates":[-1.293306,53.066284],"type":"Point"}
}
