{
  "type": "Feature",
  "properties": {
    "iso:country":"GB",
    "wof:name":"AB56 4YJ",
    "wof:placetype":"postalcode"
},
  "geometry": {"coordinates":[-2.96097269577118,57.67717163092099],"type":"Point"}
}