{
  "type": "Feature",
  "properties": {
    "date:inception_lower": "1980-01-01",
    "date:inception_upper": "1980-01-01",
    "iso:country": "GB",
    "wof:name": "TN2 4NJ",
    "wof:placetype": "postalcode"
  },
  "geometry": {"coordinates":[0.314179,51.144777],"type":"Point"}
}
