{
  "type": "Feature",
  "properties": {
    "iso:country":"GB",
    "wof:name":"TN2 4NJ",
    "wof:placetype":"postalcode"
},
  "geometry": {"coordinates":[0.31417846840612,51.1447765845008],"type":"Point"}
}