{
  "type": "Feature",
  "properties": {
    "date:inception_lower": "2011-06-01",
    "date:inception_upper": "2011-06-01",
    "iso:country": "GB",
    "wof:name": "RG9 1FB",
    "wof:placetype": "postalcode"
  },
  "geometry": {"coordinates":[-0.90387,51.535543],"type":"Point"}
}
