{
  "type": "Feature",
  "properties": {
    "iso:country": "GB",
    "wof:name": "WA7 1NA",
    "wof:placetype": "postalcode"
  },
  "geometry": {"coordinates":[-2.732462,53.342086],"type":"Point"}
}
