{
  "type": "Feature",
  "properties": {
    "date:inception_lower":"1980-01-01",
    "date:inception_upper":"1980-01-31",
    "iso:country":"GB",
    "wof:name":"WA7 1NA",
    "wof:placetype":"postalcode"
},
  "geometry": {"coordinates":[-2.732462,53.342086],"type":"Point"}
}