{
  "type": "Feature",
  "properties": {
    "iso:country":"GB",
    "wof:name":"WA7 1NA",
    "wof:placetype":"postalcode"
},
  "geometry": {"coordinates":[-2.73246055583771,53.34206987251167],"type":"Point"}
}