{
  "type": "Feature",
  "properties": {
    "date:inception_lower": "1987-04-01",
    "date:inception_upper": "1987-04-01",
    "iso:country": "GB",
    "wof:name": "DL14 9TT",
    "wof:placetype": "postalcode"
  },
  "geometry": {"coordinates":[-1.692903,54.640357],"type":"Point"}
}
