{
  "type": "Feature",
  "properties": {
    "iso:country": "GB",
    "wof:name": "DL14 9TT",
    "wof:placetype": "postalcode"
  },
  "geometry": {"coordinates":[-1.692903,54.640357],"type":"Point"}
}
