{
  "type": "Feature",
  "properties": {
    "iso:country":"GB",
    "wof:name":"CW9 8FP",
    "wof:placetype":"postalcode"
},
  "geometry": {"coordinates":[-2.51716533347162,53.24117440576012],"type":"Point"}
}