{
  "type": "Feature",
  "properties": {
    "date:inception_lower": "1980-01-01",
    "date:inception_upper": "1980-01-01",
    "iso:country": "GB",
    "wof:name": "SK11 0HQ",
    "wof:placetype": "postalcode"
  },
  "geometry": {"coordinates":[-2.111849,53.242415],"type":"Point"}
}
