{
  "type": "Feature",
  "properties": {
    "iso:country":"GB",
    "wof:name":"SK11 0HQ",
    "wof:placetype":"postalcode"
},
  "geometry": {"coordinates":[-2.11184899919209,53.24241538268726],"type":"Point"}
}