{
  "type": "Feature",
  "properties": {
    "iso:country": "GB",
    "wof:name": "DH6 4BU",
    "wof:placetype": "postalcode"
  },
  "geometry": {"coordinates":[-1.512091,54.725542],"type":"Point"}
}
