{
  "type": "Feature",
  "properties": {
    "iso:country":"GB",
    "wof:name":"EH53 0JY",
    "wof:placetype":"postalcode"
},
  "geometry": {"coordinates":[-3.48479417028073,55.8852662102181],"type":"Point"}
}