{
  "type": "Feature",
  "properties": {
    "date:inception_lower":"2014-02-01",
    "date:inception_upper":"2014-02-28",
    "iso:country":"GB",
    "wof:name":"LE1 2AU",
    "wof:placetype":"postalcode"
},
  "geometry": {"coordinates":[-1.126042,52.637425],"type":"Point"}
}