{
  "type": "Feature",
  "properties": {
    "iso:country":"GB",
    "wof:name":"LE1 2AU",
    "wof:placetype":"postalcode"
},
  "geometry": {"coordinates":[-1.12604245118475,52.63742549204074],"type":"Point"}
}