{
  "type": "Feature",
  "properties": {
    "iso:country":"GB",
    "wof:name":"B46 1EH",
    "wof:placetype":"postalcode"
},
  "geometry": {"coordinates":[-1.71029248179224,52.50634437246326],"type":"Point"}
}