{
  "type": "Feature",
  "properties": {
    "date:inception_lower": "1996-12-01",
    "date:inception_upper": "1996-12-01",
    "iso:country": "GB",
    "wof:name": "CT6 8FJ",
    "wof:placetype": "postalcode"
  },
  "geometry": {"coordinates":[1.096165,51.363185],"type":"Point"}
}
