{
  "type": "Feature",
  "properties": {
    "iso:country":"GB",
    "wof:name":"CT6 8FJ",
    "wof:placetype":"postalcode"
},
  "geometry": {"coordinates":[1.09616471037917,51.36318471588864],"type":"Point"}
}