{
  "type": "Feature",
  "properties": {
    "iso:country":"GB",
    "wof:name":"GU32 1LF",
    "wof:placetype":"postalcode"
},
  "geometry": {"coordinates":[-1.08878032075871,51.0128519612592],"type":"Point"}
}