{
  "type": "Feature",
  "properties": {
    "iso:country": "GB",
    "wof:name": "KA13 6QY",
    "wof:placetype": "postalcode"
  },
  "geometry": {"coordinates":[-4.724316,55.652586],"type":"Point"}
}
