{
  "type": "Feature",
  "properties": {
    "date:inception_lower": "2004-11-01",
    "date:inception_upper": "2004-11-01",
    "iso:country": "GB",
    "wof:name": "DL10 7BP",
    "wof:placetype": "postalcode"
  },
  "geometry": {"coordinates":[-1.735558,54.405145],"type":"Point"}
}
