{
  "type": "Feature",
  "properties": {
    "date:inception_lower": "1980-01-01",
    "date:inception_upper": "1980-01-01",
    "iso:country": "GB",
    "wof:name": "ME8 6XE",
    "wof:placetype": "postalcode"
  },
  "geometry": {"coordinates":[0.585964,51.373442],"type":"Point"}
}
