{
  "type": "Feature",
  "properties": {
    "iso:country":"GB",
    "wof:name":"ME8 6XE",
    "wof:placetype":"postalcode"
},
  "geometry": {"coordinates":[0.58596418864022,51.3734416504746],"type":"Point"}
}