{
  "type": "Feature",
  "properties": {
    "iso:country": "GB",
    "wof:name": "ME8 6XE",
    "wof:placetype": "postalcode"
  },
  "geometry": {"coordinates":[0.585964,51.373442],"type":"Point"}
}
