{
  "type": "Feature",
  "properties": {
    "date:inception_lower":"1980-01-01",
    "date:inception_upper":"1980-01-31",
    "iso:country":"GB",
    "wof:name":"BN26 6UJ",
    "wof:placetype":"postalcode"
},
  "geometry": {"coordinates":[0.127564,50.830004],"type":"Point"}
}