{
  "type": "Feature",
  "properties": {
    "iso:country": "GB",
    "wof:name": "BN26 6UJ",
    "wof:placetype": "postalcode"
  },
  "geometry": {"coordinates":[0.127564,50.830004],"type":"Point"}
}
