{
  "type": "Feature",
  "properties": {
    "date:inception_lower": "1990-02-01",
    "date:inception_upper": "1990-02-01",
    "iso:country": "GB",
    "wof:name": "CH3 5PE",
    "wof:placetype": "postalcode"
  },
  "geometry": {"coordinates":[-2.868256,53.194898],"type":"Point"}
}
