{
  "type": "Feature",
  "properties": {
    "iso:country":"GB",
    "wof:name":"CH3 5PE",
    "wof:placetype":"postalcode"
},
  "geometry": {"coordinates":[-2.86825563365432,53.19489797033122],"type":"Point"}
}