{
  "type": "Feature",
  "properties": {
    "iso:country":"GB",
    "wof:name":"CT15 7NN",
    "wof:placetype":"postalcode"
},
  "geometry": {"coordinates":[1.22926805943952,51.18617558371219],"type":"Point"}
}