{
  "type": "Feature",
  "properties": {
    "date:inception_lower": "1980-01-01",
    "date:inception_upper": "1980-01-01",
    "iso:country": "GB",
    "wof:name": "CT15 7NN",
    "wof:placetype": "postalcode"
  },
  "geometry": {"coordinates":[1.229268,51.186176],"type":"Point"}
}
