{
  "type": "Feature",
  "properties": {
    "iso:country":"GB",
    "wof:name":"TQ14 9QS",
    "wof:placetype":"postalcode"
},
  "geometry": {"coordinates":[-3.5430584939552,50.5539672765216],"type":"Point"}
}