{
  "type": "Feature",
  "properties": {
    "date:inception_lower": "2022-02-01",
    "date:inception_upper": "2022-02-01",
    "iso:country": "GB",
    "wof:name": "PR2 5DW",
    "wof:placetype": "postalcode"
  },
  "geometry": {"coordinates":[-2.640566,53.805312],"type":"Point"}
}
