{
  "type": "Feature",
  "properties": {
    "iso:country": "GB",
    "wof:name": "S73 0UH",
    "wof:placetype": "postalcode"
  },
  "geometry": {"coordinates":[-1.379461,53.508611],"type":"Point"}
}
