{
  "type": "Feature",
  "properties": {
    "iso:country":"GB",
    "wof:name":"S73 0UH",
    "wof:placetype":"postalcode"
},
  "geometry": {"coordinates":[-1.37946099121749,53.50861120864759],"type":"Point"}
}