{
  "type": "Feature",
  "properties": {
    "iso:country":"GB",
    "wof:name":"NG3 1NH",
    "wof:placetype":"postalcode"
},
  "geometry": {"coordinates":[-1.14592087333199,52.96065259517478],"type":"Point"}
}