{
  "type": "Feature",
  "properties": {
    "iso:country":"GB",
    "wof:name":"DN5 0QA",
    "wof:placetype":"postalcode"
},
  "geometry": {"coordinates":[-1.13743184930157,53.55853450358327],"type":"Point"}
}