{
  "type": "Feature",
  "properties": {
    "date:inception_lower": "2020-11-01",
    "date:inception_upper": "2020-11-01",
    "iso:country": "GB",
    "wof:name": "BB12 6EQ",
    "wof:placetype": "postalcode"
  },
  "geometry": {"coordinates":[-2.287446,53.793619],"type":"Point"}
}
