{
  "type": "Feature",
  "properties": {
    "iso:country":"GB",
    "wof:name":"W1T 1AL",
    "wof:placetype":"postalcode"
},
  "geometry": {"coordinates":[-0.13220280172569,51.51769384591172],"type":"Point"}
}