{
  "type": "Feature",
  "properties": {
    "iso:country": "GB",
    "wof:name": "NP26 3PP",
    "wof:placetype": "postalcode"
  },
  "geometry": {"coordinates":[-2.810464,51.581254],"type":"Point"}
}
