{
  "type": "Feature",
  "properties": {
    "iso:country": "GB",
    "wof:name": "TS16 0GB",
    "wof:placetype": "postalcode"
  },
  "geometry": {"coordinates":[-1.367817,54.522967],"type":"Point"}
}
