{
  "type": "Feature",
  "properties": {
    "iso:country":"GB",
    "wof:name":"TS16 0GB",
    "wof:placetype":"postalcode"
},
  "geometry": {"coordinates":[-1.36781684748397,54.52296684097274],"type":"Point"}
}