{
  "type": "Feature",
  "properties": {
    "date:inception_lower": "2001-12-01",
    "date:inception_upper": "2001-12-01",
    "iso:country": "GB",
    "wof:name": "TS16 0GB",
    "wof:placetype": "postalcode"
  },
  "geometry": {"coordinates":[-1.367817,54.522967],"type":"Point"}
}
