{
  "type": "Feature",
  "properties": {
    "date:inception_lower": "1980-01-01",
    "date:inception_upper": "1980-01-01",
    "iso:country": "GB",
    "wof:name": "PA8 6AS",
    "wof:placetype": "postalcode"
  },
  "geometry": {"coordinates":[-4.47491,55.901341],"type":"Point"}
}
