{
  "type": "Feature",
  "properties": {
    "iso:country":"GB",
    "wof:name":"LE65 1AT",
    "wof:placetype":"postalcode"
},
  "geometry": {"coordinates":[-1.45956098331867,52.74674381948928],"type":"Point"}
}