{
  "type": "Feature",
  "properties": {
    "date:inception_lower": "2013-07-01",
    "date:inception_upper": "2013-07-01",
    "iso:country": "GB",
    "wof:name": "LE65 1AT",
    "wof:placetype": "postalcode"
  },
  "geometry": {"coordinates":[-1.459211,52.746769],"type":"Point"}
}
