{
  "type": "Feature",
  "properties": {
    "iso:country": "GB",
    "wof:name": "CH5 3JY",
    "wof:placetype": "postalcode"
  },
  "geometry": {"coordinates":[-3.04849,53.182589],"type":"Point"}
}
