{
  "type": "Feature",
  "properties": {
    "iso:country":"GB",
    "wof:name":"CH5 3JY",
    "wof:placetype":"postalcode"
},
  "geometry": {"coordinates":[-3.04848990170091,53.18258874162346],"type":"Point"}
}