{
  "type": "Feature",
  "properties": {
    "iso:country":"GB",
    "wof:name":"HX1 2PW",
    "wof:placetype":"postalcode"
},
  "geometry": {"coordinates":[-1.86058560664445,53.71342643749021],"type":"Point"}
}