{
  "type": "Feature",
  "properties": {
    "iso:country":"GB",
    "wof:name":"S13 7JR",
    "wof:placetype":"postalcode"
},
  "geometry": {"coordinates":[-1.37064897275576,53.35920056285327],"type":"Point"}
}