{
  "type": "Feature",
  "properties": {
    "iso:country": "GB",
    "wof:name": "HR2 6EG",
    "wof:placetype": "postalcode"
  },
  "geometry": {"coordinates":[-2.701081,52.04092],"type":"Point"}
}
