{
  "type": "Feature",
  "properties": {
    "date:inception_lower": "1980-01-01",
    "date:inception_upper": "1980-01-01",
    "iso:country": "GB",
    "wof:name": "HG3 3BB",
    "wof:placetype": "postalcode"
  },
  "geometry": {"coordinates":[-1.554961,54.034231],"type":"Point"}
}
