{
  "type": "Feature",
  "properties": {
    "date:inception_lower":"2005-08-01",
    "date:inception_upper":"2005-08-31",
    "iso:country":"GB",
    "wof:name":"SN11 9RA",
    "wof:placetype":"postalcode"
},
  "geometry": {"coordinates":[-1.995979,51.452401],"type":"Point"}
}