{
  "type": "Feature",
  "properties": {
    "iso:country":"GB",
    "wof:name":"SN11 9RA",
    "wof:placetype":"postalcode"
},
  "geometry": {"coordinates":[-1.99597925709112,51.45240080131967],"type":"Point"}
}