{
  "type": "Feature",
  "properties": {
    "iso:country": "GB",
    "wof:name": "RG1 7YZ",
    "wof:placetype": "postalcode"
  },
  "geometry": {"coordinates":[-0.987917,51.455032],"type":"Point"}
}
