{
  "type": "Feature",
  "properties": {
    "iso:country":"GB",
    "wof:name":"RG1 7YZ",
    "wof:placetype":"postalcode"
},
  "geometry": {"coordinates":[-0.98793761119131,51.45503079710024],"type":"Point"}
}