{
  "type": "Feature",
  "properties": {
    "iso:country": "GB",
    "wof:name": "NN8 3FR",
    "wof:placetype": "postalcode"
  },
  "geometry": {"coordinates":[-0.717025,52.305917],"type":"Point"}
}
