{
  "type": "Feature",
  "properties": {
    "iso:country":"GB",
    "wof:name":"S61 4NU",
    "wof:placetype":"postalcode"
},
  "geometry": {"coordinates":[-1.3676022692976,53.45333216319306],"type":"Point"}
}