{
  "type": "Feature",
  "properties": {
    "date:inception_lower": "1980-01-01",
    "date:inception_upper": "1980-01-01",
    "iso:country": "GB",
    "wof:name": "S61 4NU",
    "wof:placetype": "postalcode"
  },
  "geometry": {"coordinates":[-1.367604,53.453351],"type":"Point"}
}
