{
  "type": "Feature",
  "properties": {
    "date:inception_lower":"1999-06-01",
    "date:inception_upper":"1999-06-30",
    "iso:country":"GB",
    "wof:name":"M17 8DD",
    "wof:placetype":"postalcode"
},
  "geometry": {"coordinates":[-2.365595,53.468637],"type":"Point"}
}