{
  "type": "Feature",
  "properties": {
    "iso:country":"GB",
    "wof:name":"M17 8DD",
    "wof:placetype":"postalcode"
},
  "geometry": {"coordinates":[-2.36559548587433,53.46863710401917],"type":"Point"}
}