{
  "type": "Feature",
  "properties": {
    "date:inception_lower": "2023-07-01",
    "date:inception_upper": "2023-07-01",
    "iso:country": "GB",
    "wof:name": "PE25 3BN",
    "wof:placetype": "postalcode"
  },
  "geometry": {"coordinates":[0.340266,53.13462],"type":"Point"}
}
