{
  "type": "Feature",
  "properties": {
    "iso:country":"GB",
    "wof:name":"DH1 3NB",
    "wof:placetype":"postalcode"
},
  "geometry": {"coordinates":[-1.57518541324897,54.7769575363027],"type":"Point"}
}