{
  "type": "Feature",
  "properties": {
    "iso:country":"GB",
    "wof:name":"NG5 2FE",
    "wof:placetype":"postalcode"
},
  "geometry": {"coordinates":[-1.15048008192316,52.97945529176707],"type":"Point"}
}