{
  "type": "Feature",
  "properties": {
    "iso:country": "GB",
    "wof:name": "GU31 5QH",
    "wof:placetype": "postalcode"
  },
  "geometry": {"coordinates":[-0.884242,50.96848],"type":"Point"}
}
