{
  "type": "Feature",
  "properties": {
    "iso:country":"GB",
    "wof:name":"CR2 9BY",
    "wof:placetype":"postalcode"
},
  "geometry": {"coordinates":[-0.06447183759348,51.31993378626982],"type":"Point"}
}