{
  "type": "Feature",
  "properties": {
    "date:inception_lower": "1980-01-01",
    "date:inception_upper": "1980-01-01",
    "iso:country": "GB",
    "wof:name": "S71 2DX",
    "wof:placetype": "postalcode"
  },
  "geometry": {"coordinates":[-1.453362,53.569392],"type":"Point"}
}
