{
  "type": "Feature",
  "properties": {
    "iso:country":"GB",
    "wof:name":"NE33 5LW",
    "wof:placetype":"postalcode"
},
  "geometry": {"coordinates":[-1.44040750120705,54.98116799221768],"type":"Point"}
}