{
  "type": "Feature",
  "properties": {
    "iso:country": "GB",
    "wof:name": "TN2 5LT",
    "wof:placetype": "postalcode"
  },
  "geometry": {"coordinates":[0.25332,51.114677],"type":"Point"}
}
