{
  "type": "Feature",
  "properties": {
    "date:inception_lower":"1994-05-01",
    "date:inception_upper":"1994-05-31",
    "iso:country":"GB",
    "wof:name":"M30 8NU",
    "wof:placetype":"postalcode"
},
  "geometry": {"coordinates":[-2.365428,53.486012],"type":"Point"}
}