{
  "type": "Feature",
  "properties": {
    "iso:country":"GB",
    "wof:name":"M30 8NU",
    "wof:placetype":"postalcode"
},
  "geometry": {"coordinates":[-2.36542850033322,53.48601237206985],"type":"Point"}
}