{
  "type": "Feature",
  "properties": {
    "iso:country":"GB",
    "wof:name":"FY6 8GD",
    "wof:placetype":"postalcode"
},
  "geometry": {"coordinates":[-2.97346587457035,53.84397166510281],"type":"Point"}
}