{
  "type": "Feature",
  "properties": {
    "iso:country": "GB",
    "wof:name": "FY6 8GD",
    "wof:placetype": "postalcode"
  },
  "geometry": {"coordinates":[-2.973466,53.843972],"type":"Point"}
}
