{
  "type": "Feature",
  "properties": {
    "iso:country": "GB",
    "wof:name": "WF11 9JT",
    "wof:placetype": "postalcode"
  },
  "geometry": {"coordinates":[-1.286398,53.745252],"type":"Point"}
}
