{
  "type": "Feature",
  "properties": {
    "iso:country":"GB",
    "wof:name":"W13 0BH",
    "wof:placetype":"postalcode"
},
  "geometry": {"coordinates":[-0.32742566556458,51.52530700268296],"type":"Point"}
}