{
  "type": "Feature",
  "properties": {
    "iso:country":"GB",
    "wof:name":"WD18 8RE",
    "wof:placetype":"postalcode"
},
  "geometry": {"coordinates":[-0.42636267798423,51.64719697127087],"type":"Point"}
}