{
  "type": "Feature",
  "properties": {
    "date:inception_lower": "1996-06-01",
    "date:inception_upper": "1996-06-01",
    "iso:country": "GB",
    "wof:name": "WR3 8EH",
    "wof:placetype": "postalcode"
  },
  "geometry": {"coordinates":[-2.20759,52.206514],"type":"Point"}
}
