{
  "type": "Feature",
  "properties": {
    "iso:country":"GB",
    "wof:name":"HP17 8DR",
    "wof:placetype":"postalcode"
},
  "geometry": {"coordinates":[-0.92509245872753,51.77273102188601],"type":"Point"}
}