{
  "type": "Feature",
  "properties": {
    "iso:country": "GB",
    "wof:name": "HP17 8DR",
    "wof:placetype": "postalcode"
  },
  "geometry": {"coordinates":[-0.925092,51.772731],"type":"Point"}
}
