{
  "type": "Feature",
  "properties": {
    "iso:country": "GB",
    "wof:name": "CM9 8PY",
    "wof:placetype": "postalcode"
  },
  "geometry": {"coordinates":[0.68554,51.773781],"type":"Point"}
}
