{
  "type": "Feature",
  "properties": {
    "iso:country":"GB",
    "wof:name":"CM9 8PY",
    "wof:placetype":"postalcode"
},
  "geometry": {"coordinates":[0.68596361817021,51.77383398150855],"type":"Point"}
}