{
  "type": "Feature",
  "properties": {
    "iso:country":"GB",
    "wof:name":"HG3 2TF",
    "wof:placetype":"postalcode"
},
  "geometry": {"coordinates":[-1.56719292958833,54.00546373367206],"type":"Point"}
}