{
  "type": "Feature",
  "properties": {
    "iso:country": "GB",
    "wof:name": "NR13 3EL",
    "wof:placetype": "postalcode"
  },
  "geometry": {"coordinates":[1.544547,52.643773],"type":"Point"}
}
