{
  "type": "Feature",
  "properties": {
    "iso:country":"GB",
    "wof:name":"CB23 1HR",
    "wof:placetype":"postalcode"
},
  "geometry": {"coordinates":[-0.00911861985175,52.16145453140922],"type":"Point"}
}