{
  "type": "Feature",
  "properties": {
    "iso:country": "GB",
    "wof:name": "CB23 1HR",
    "wof:placetype": "postalcode"
  },
  "geometry": {"coordinates":[-0.00933,52.161336],"type":"Point"}
}
