{
  "type": "Feature",
  "properties": {
    "iso:country":"GB",
    "wof:name":"B63 3RL",
    "wof:placetype":"postalcode"
},
  "geometry": {"coordinates":[-2.05976005618205,52.4543525553755],"type":"Point"}
}