{
  "type": "Feature",
  "properties": {
    "date:inception_lower":"1980-01-01",
    "date:inception_upper":"1980-01-31",
    "iso:country":"GB",
    "wof:name":"B63 3RL",
    "wof:placetype":"postalcode"
},
  "geometry": {"coordinates":[-2.059725,52.454403],"type":"Point"}
}