{
  "type": "Feature",
  "properties": {
    "date:inception_lower": "1980-01-01",
    "date:inception_upper": "1980-01-01",
    "iso:country": "GB",
    "wof:name": "DY3 4NJ",
    "wof:placetype": "postalcode"
  },
  "geometry": {"coordinates":[-2.201282,52.516029],"type":"Point"}
}
