{
  "type": "Feature",
  "properties": {
    "iso:country":"GB",
    "wof:name":"G12 9QT",
    "wof:placetype":"postalcode"
},
  "geometry": {"coordinates":[-4.30858554406063,55.8793635496331],"type":"Point"}
}