{
  "type": "Feature",
  "properties": {
    "date:inception_lower": "1980-01-01",
    "date:inception_upper": "1980-01-01",
    "iso:country": "GB",
    "wof:name": "BB12 8HG",
    "wof:placetype": "postalcode"
  },
  "geometry": {"coordinates":[-2.317353,53.801884],"type":"Point"}
}
