{
  "type": "Feature",
  "properties": {
    "iso:country": "GB",
    "wof:name": "BB12 8HG",
    "wof:placetype": "postalcode"
  },
  "geometry": {"coordinates":[-2.317353,53.80187],"type":"Point"}
}
