{
  "type": "Feature",
  "properties": {
    "date:inception_lower": "1980-01-01",
    "date:inception_upper": "1980-01-01",
    "iso:country": "GB",
    "wof:name": "DY10 4EL",
    "wof:placetype": "postalcode"
  },
  "geometry": {"coordinates":[-2.213375,52.347606],"type":"Point"}
}
