{
  "type": "Feature",
  "properties": {
    "iso:country":"GB",
    "wof:name":"RH2 8PT",
    "wof:placetype":"postalcode"
},
  "geometry": {"coordinates":[-0.21164872908346,51.20275982813787],"type":"Point"}
}