{
  "type": "Feature",
  "properties": {
    "iso:country": "GB",
    "wof:name": "M27 0DF",
    "wof:placetype": "postalcode"
  },
  "geometry": {"coordinates":[-2.349634,53.500576],"type":"Point"}
}
