{
  "type": "Feature",
  "properties": {
    "iso:country":"GB",
    "wof:name":"M27 0DF",
    "wof:placetype":"postalcode"
},
  "geometry": {"coordinates":[-2.34963418140927,53.50057602245769],"type":"Point"}
}