{
  "type": "Feature",
  "properties": {
    "iso:country":"GB",
    "wof:name":"BA2 3PZ",
    "wof:placetype":"postalcode"
},
  "geometry": {"coordinates":[-2.38150950590933,51.37699586711799],"type":"Point"}
}