{
  "type": "Feature",
  "properties": {
    "date:inception_lower": "1987-04-01",
    "date:inception_upper": "1987-04-01",
    "iso:country": "GB",
    "wof:name": "BN1 9JU",
    "wof:placetype": "postalcode"
  },
  "geometry": {"coordinates":[-0.10095,50.856692],"type":"Point"}
}
