{
  "type": "Feature",
  "properties": {
    "iso:country": "GB",
    "wof:name": "L34 2TF",
    "wof:placetype": "postalcode"
  },
  "geometry": {"coordinates":[-2.792867,53.427644],"type":"Point"}
}
