{
  "type": "Feature",
  "properties": {
    "iso:country":"GB",
    "wof:name":"WA14 4AH",
    "wof:placetype":"postalcode"
},
  "geometry": {"coordinates":[-2.3572528074412,53.38825964618517],"type":"Point"}
}