{
  "type": "Feature",
  "properties": {
    "iso:country": "GB",
    "wof:name": "WA14 4AH",
    "wof:placetype": "postalcode"
  },
  "geometry": {"coordinates":[-2.357253,53.38826],"type":"Point"}
}
