{
  "type": "Feature",
  "properties": {
    "iso:country":"GB",
    "wof:name":"HX2 7HD",
    "wof:placetype":"postalcode"
},
  "geometry": {"coordinates":[-1.89018701237716,53.71507501333146],"type":"Point"}
}