{
  "type": "Feature",
  "properties": {
    "iso:country":"GB",
    "wof:name":"HP16 9HZ",
    "wof:placetype":"postalcode"
},
  "geometry": {"coordinates":[-0.72298606746757,51.70366813100946],"type":"Point"}
}