{
  "type": "Feature",
  "properties": {
    "iso:country": "GB",
    "wof:name": "HP16 9HZ",
    "wof:placetype": "postalcode"
  },
  "geometry": {"coordinates":[-0.722986,51.703668],"type":"Point"}
}
