{
  "type": "Feature",
  "properties": {
    "date:inception_lower":"1991-01-01",
    "date:inception_upper":"1991-01-31",
    "iso:country":"GB",
    "wof:name":"TN9 2PZ",
    "wof:placetype":"postalcode"
},
  "geometry": {"coordinates":[0.256643,51.186345],"type":"Point"}
}