{
  "type": "Feature",
  "properties": {
    "date:inception_lower": "1995-12-01",
    "date:inception_upper": "1995-12-01",
    "iso:country": "GB",
    "wof:name": "L35 3UZ",
    "wof:placetype": "postalcode"
  },
  "geometry": {"coordinates":[-2.793658,53.411962],"type":"Point"}
}
