{
  "type": "Feature",
  "properties": {
    "iso:country":"GB",
    "wof:name":"LU7 9PT",
    "wof:placetype":"postalcode"
},
  "geometry": {"coordinates":[-0.58095946483507,51.90881943834924],"type":"Point"}
}