{
  "type": "Feature",
  "properties": {
    "date:inception_lower":"1980-01-01",
    "date:inception_upper":"1980-01-31",
    "iso:country":"GB",
    "wof:name":"LU7 9PT",
    "wof:placetype":"postalcode"
},
  "geometry": {"coordinates":[-0.580959,51.908819],"type":"Point"}
}