{
  "type": "Feature",
  "properties": {
    "iso:country":"GB",
    "wof:name":"CW2 5DZ",
    "wof:placetype":"postalcode"
},
  "geometry": {"coordinates":[-2.45997068537819,53.05797004466217],"type":"Point"}
}