{
  "type": "Feature",
  "properties": {
    "iso:country": "GB",
    "wof:name": "IP31 1NP",
    "wof:placetype": "postalcode"
  },
  "geometry": {"coordinates":[0.717791,52.304306],"type":"Point"}
}
