{
  "type": "Feature",
  "properties": {
    "iso:country":"GB",
    "wof:name":"IP31 1NP",
    "wof:placetype":"postalcode"
},
  "geometry": {"coordinates":[0.71779089018089,52.30430593149641],"type":"Point"}
}