{
  "type": "Feature",
  "properties": {
    "iso:country": "GB",
    "wof:name": "LA1 9TN",
    "wof:placetype": "postalcode"
  },
  "geometry": {"coordinates":[-2.797747,54.047292],"type":"Point"}
}
