{
  "type": "Feature",
  "properties": {
    "iso:country": "GB",
    "wof:name": "BL9 9UG",
    "wof:placetype": "postalcode"
  },
  "geometry": {"coordinates":[-2.309893,53.581067],"type":"Point"}
}
