{
  "type": "Feature",
  "properties": {
    "iso:country":"GB",
    "wof:name":"KA26 9EF",
    "wof:placetype":"postalcode"
},
  "geometry": {"coordinates":[-4.84553611744625,55.24393220666318],"type":"Point"}
}