{
  "type": "Feature",
  "properties": {
    "iso:country": "GB",
    "wof:name": "SL3 0PQ",
    "wof:placetype": "postalcode"
  },
  "geometry": {"coordinates":[-0.512835,51.478851],"type":"Point"}
}
