{
  "type": "Feature",
  "properties": {
    "date:inception_lower": "2018-01-01",
    "date:inception_upper": "2018-01-01",
    "iso:country": "GB",
    "wof:name": "PR3 1ZR",
    "wof:placetype": "postalcode"
  },
  "geometry": {"coordinates":[-2.783659,53.896096],"type":"Point"}
}
