{
  "type": "Feature",
  "properties": {
    "iso:country":"GB",
    "wof:name":"DN5 9SE",
    "wof:placetype":"postalcode"
},
  "geometry": {"coordinates":[-1.14384707334568,53.53164165405212],"type":"Point"}
}