{
  "type": "Feature",
  "properties": {
    "iso:country": "GB",
    "wof:name": "B98 0FJ",
    "wof:placetype": "postalcode"
  },
  "geometry": {"coordinates":[-1.902256,52.295931],"type":"Point"}
}
