{
  "type": "Feature",
  "properties": {
    "iso:country":"GB",
    "wof:name":"IP16 4NN",
    "wof:placetype":"postalcode"
},
  "geometry": {"coordinates":[1.61356891383362,52.17998143676508],"type":"Point"}
}