{
  "type": "Feature",
  "properties": {
    "date:inception_lower": "1980-01-01",
    "date:inception_upper": "1980-01-01",
    "iso:country": "GB",
    "wof:name": "IP16 4NN",
    "wof:placetype": "postalcode"
  },
  "geometry": {"coordinates":[1.613569,52.179981],"type":"Point"}
}
