{
  "type": "Feature",
  "properties": {
    "iso:country":"GB",
    "wof:name":"SA12 9HN",
    "wof:placetype":"postalcode"
},
  "geometry": {"coordinates":[-3.77184932730134,51.60854930667178],"type":"Point"}
}