{
  "type": "Feature",
  "properties": {
    "iso:country": "GB",
    "wof:name": "SA12 9HN",
    "wof:placetype": "postalcode"
  },
  "geometry": {"coordinates":[-3.771849,51.608549],"type":"Point"}
}
