{
  "type": "Feature",
  "properties": {
    "iso:country":"GB",
    "wof:name":"AB56 5BD",
    "wof:placetype":"postalcode"
},
  "geometry": {"coordinates":[-2.98586999687157,57.66162841582206],"type":"Point"}
}