{
  "type": "Feature",
  "properties": {
    "iso:country": "GB",
    "wof:name": "AB56 5BD",
    "wof:placetype": "postalcode"
  },
  "geometry": {"coordinates":[-2.98587,57.661628],"type":"Point"}
}
