{
  "type": "Feature",
  "properties": {
    "iso:country":"GB",
    "wof:name":"NN8 2ER",
    "wof:placetype":"postalcode"
},
  "geometry": {"coordinates":[-0.70468253781725,52.2910820297402],"type":"Point"}
}