{
  "type": "Feature",
  "properties": {
    "iso:country":"GB",
    "wof:name":"PE24 4TW",
    "wof:placetype":"postalcode"
},
  "geometry": {"coordinates":[0.31877199123441,53.19600738913135],"type":"Point"}
}