{
  "type": "Feature",
  "properties": {
    "iso:country": "GB",
    "wof:name": "CB1 8RF",
    "wof:placetype": "postalcode"
  },
  "geometry": {"coordinates":[0.155224,52.183572],"type":"Point"}
}
