{
  "type": "Feature",
  "properties": {
    "iso:country":"GB",
    "wof:name":"LL21 9TB",
    "wof:placetype":"postalcode"
},
  "geometry": {"coordinates":[-3.54384347006145,53.03852816420013],"type":"Point"}
}