{
  "type": "Feature",
  "properties": {
    "iso:country":"GB",
    "wof:name":"BH14 8SB",
    "wof:placetype":"postalcode"
},
  "geometry": {"coordinates":[-1.94626980987621,50.72373169999098],"type":"Point"}
}