{
  "type": "Feature",
  "properties": {
    "date:inception_lower":"1980-01-01",
    "date:inception_upper":"1980-01-31",
    "iso:country":"GB",
    "wof:name":"CM7 4LJ",
    "wof:placetype":"postalcode"
},
  "geometry": {"coordinates":[0.454722,51.954559],"type":"Point"}
}