{
  "type": "Feature",
  "properties": {
    "iso:country":"GB",
    "wof:name":"CA1 3BX",
    "wof:placetype":"postalcode"
},
  "geometry": {"coordinates":[-2.90876791305401,54.87225097967325],"type":"Point"}
}