{
  "type": "Feature",
  "properties": {
    "date:inception_lower": "1980-01-01",
    "date:inception_upper": "1980-01-01",
    "iso:country": "GB",
    "wof:name": "CA1 3BX",
    "wof:placetype": "postalcode"
  },
  "geometry": {"coordinates":[-2.908138,54.872478],"type":"Point"}
}
