{
  "type": "Feature",
  "properties": {
    "iso:country": "GB",
    "wof:name": "NG17 3NA",
    "wof:placetype": "postalcode"
  },
  "geometry": {"coordinates":[-1.281099,53.140784],"type":"Point"}
}
