{
  "type": "Feature",
  "properties": {
    "iso:country": "GB",
    "wof:name": "IG10 3RN",
    "wof:placetype": "postalcode"
  },
  "geometry": {"coordinates":[0.080948,51.645678],"type":"Point"}
}
