{
  "type": "Feature",
  "properties": {
    "iso:country":"GB",
    "wof:name":"M22 5ET",
    "wof:placetype":"postalcode"
},
  "geometry": {"coordinates":[-2.2461339034242,53.37953408042758],"type":"Point"}
}