{
  "type": "Feature",
  "properties": {
    "iso:country":"GB",
    "wof:name":"SY16 4ND",
    "wof:placetype":"postalcode"
},
  "geometry": {"coordinates":[-3.2242095814706,52.51584468343143],"type":"Point"}
}