{
  "type": "Feature",
  "properties": {
    "date:inception_lower": "1980-01-01",
    "date:inception_upper": "1980-01-01",
    "iso:country": "GB",
    "wof:name": "HR2 0PN",
    "wof:placetype": "postalcode"
  },
  "geometry": {"coordinates":[-3.042273,52.011251],"type":"Point"}
}
