{
  "type": "Feature",
  "properties": {
    "iso:country": "GB",
    "wof:name": "HR2 0PN",
    "wof:placetype": "postalcode"
  },
  "geometry": {"coordinates":[-3.042273,52.011251],"type":"Point"}
}
