{
  "type": "Feature",
  "properties": {
    "iso:country":"GB",
    "wof:name":"HR2 0PN",
    "wof:placetype":"postalcode"
},
  "geometry": {"coordinates":[-3.04227321275833,52.01125130556304],"type":"Point"}
}