{
  "type": "Feature",
  "properties": {
    "date:inception_lower":"1980-01-01",
    "date:inception_upper":"1980-01-31",
    "iso:country":"GB",
    "wof:name":"DL14 9JD",
    "wof:placetype":"postalcode"
},
  "geometry": {"coordinates":[-1.716861,54.631509],"type":"Point"}
}