{
  "type": "Feature",
  "properties": {
    "iso:country":"GB",
    "wof:name":"DL14 9JD",
    "wof:placetype":"postalcode"
},
  "geometry": {"coordinates":[-1.71686138002748,54.63150855413948],"type":"Point"}
}