{
  "type": "Feature",
  "properties": {
    "iso:country": "GB",
    "wof:name": "DL14 9JD",
    "wof:placetype": "postalcode"
  },
  "geometry": {"coordinates":[-1.716861,54.631509],"type":"Point"}
}
