{
  "type": "Feature",
  "properties": {
    "iso:country":"GB",
    "wof:name":"M11 4DZ",
    "wof:placetype":"postalcode"
},
  "geometry": {"coordinates":[-2.18583818587278,53.48288547232188],"type":"Point"}
}