{
  "type": "Feature",
  "properties": {
    "iso:country":"GB",
    "wof:name":"NW1 7LU",
    "wof:placetype":"postalcode"
},
  "geometry": {"coordinates":[-0.14195764624114,51.5344129401142],"type":"Point"}
}