{
  "type": "Feature",
  "properties": {
    "iso:country": "GB",
    "wof:name": "NW2 6SY",
    "wof:placetype": "postalcode"
  },
  "geometry": {"coordinates":[-0.222291,51.557545],"type":"Point"}
}
