{
  "type": "Feature",
  "properties": {
    "iso:country":"GB",
    "wof:name":"LN11 0GS",
    "wof:placetype":"postalcode"
},
  "geometry": {"coordinates":[-0.00007356441952,53.37165872789069],"type":"Point"}
}