{
  "type": "Feature",
  "properties": {
    "iso:country": "GB",
    "wof:name": "LN11 0GS",
    "wof:placetype": "postalcode"
  },
  "geometry": {"coordinates":[0.000204,53.37185],"type":"Point"}
}
