{
  "type": "Feature",
  "properties": {
    "iso:country": "GB",
    "wof:name": "LN11 0GS",
    "wof:placetype": "postalcode"
  },
  "geometry": {"coordinates":[-0.000074,53.371684],"type":"Point"}
}
