{
  "type": "Feature",
  "properties": {
    "iso:country": "GB",
    "wof:name": "WR9 7HX",
    "wof:placetype": "postalcode"
  },
  "geometry": {"coordinates":[-2.157106,52.252515],"type":"Point"}
}
