{
  "type": "Feature",
  "properties": {
    "date:inception_lower": "1995-12-01",
    "date:inception_upper": "1995-12-01",
    "iso:country": "GB",
    "wof:name": "WR9 7HX",
    "wof:placetype": "postalcode"
  },
  "geometry": {"coordinates":[-2.157106,52.252515],"type":"Point"}
}
