{
  "type": "Feature",
  "properties": {
    "date:inception_lower": "2010-11-01",
    "date:inception_upper": "2010-11-01",
    "iso:country": "GB",
    "wof:name": "FK5 4WP",
    "wof:placetype": "postalcode"
  },
  "geometry": {"coordinates":[-3.826396,56.039093],"type":"Point"}
}
