{
  "type": "Feature",
  "properties": {
    "date:inception_lower":"1980-01-01",
    "date:inception_upper":"1980-01-31",
    "iso:country":"GB",
    "wof:name":"GL6 9LD",
    "wof:placetype":"postalcode"
},
  "geometry": {"coordinates":[-2.180693,51.707409],"type":"Point"}
}