{
  "type": "Feature",
  "properties": {
    "iso:country":"GB",
    "wof:name":"GL6 9LD",
    "wof:placetype":"postalcode"
},
  "geometry": {"coordinates":[-2.18069254364485,51.70740878843696],"type":"Point"}
}