{
  "type": "Feature",
  "properties": {
    "iso:country": "GB",
    "wof:name": "GL6 9LD",
    "wof:placetype": "postalcode"
  },
  "geometry": {"coordinates":[-2.180693,51.707409],"type":"Point"}
}
