{
  "type": "Feature",
  "properties": {
    "iso:country":"GB",
    "wof:name":"LL17 0ER",
    "wof:placetype":"postalcode"
},
  "geometry": {"coordinates":[-3.45101640419757,53.2524035013655],"type":"Point"}
}