{
  "type": "Feature",
  "properties": {
    "date:inception_lower": "1980-01-01",
    "date:inception_upper": "1980-01-01",
    "iso:country": "GB",
    "wof:name": "IP14 2LX",
    "wof:placetype": "postalcode"
  },
  "geometry": {"coordinates":[0.948446,52.14447],"type":"Point"}
}
