{
  "type": "Feature",
  "properties": {
    "iso:country":"GB",
    "wof:name":"BR7 6JG",
    "wof:placetype":"postalcode"
},
  "geometry": {"coordinates":[0.06386931831816,51.42429048103453],"type":"Point"}
}