{
  "type": "Feature",
  "properties": {
    "iso:country": "GB",
    "wof:name": "PL12 5JB",
    "wof:placetype": "postalcode"
  },
  "geometry": {"coordinates":[-4.332331,50.435098],"type":"Point"}
}
