{
  "type": "Feature",
  "properties": {
    "iso:country":"GB",
    "wof:name":"PL12 5JB",
    "wof:placetype":"postalcode"
},
  "geometry": {"coordinates":[-4.33233099902519,50.43509818570457],"type":"Point"}
}