{
  "type": "Feature",
  "properties": {
    "date:inception_lower":"1980-01-01",
    "date:inception_upper":"1980-01-31",
    "iso:country":"GB",
    "wof:name":"PL12 5JB",
    "wof:placetype":"postalcode"
},
  "geometry": {"coordinates":[-4.332331,50.435098],"type":"Point"}
}