{
  "type": "Feature",
  "properties": {
    "iso:country":"GB",
    "wof:name":"NN16 9XP",
    "wof:placetype":"postalcode"
},
  "geometry": {"coordinates":[-0.71517243578257,52.41846925262478],"type":"Point"}
}