{
  "type": "Feature",
  "properties": {
    "date:inception_lower":"1996-12-01",
    "date:inception_upper":"1996-12-31",
    "iso:country":"GB",
    "wof:name":"NN16 9XP",
    "wof:placetype":"postalcode"
},
  "geometry": {"coordinates":[-0.715172,52.418469],"type":"Point"}
}