{
  "type": "Feature",
  "properties": {
    "iso:country": "GB",
    "wof:name": "SP3 6NW",
    "wof:placetype": "postalcode"
  },
  "geometry": {"coordinates":[-2.084839,51.056965],"type":"Point"}
}
