{
  "type": "Feature",
  "properties": {
    "date:inception_lower":"1980-01-01",
    "date:inception_upper":"1980-01-31",
    "iso:country":"GB",
    "wof:name":"SP3 6NW",
    "wof:placetype":"postalcode"
},
  "geometry": {"coordinates":[-2.084839,51.056965],"type":"Point"}
}