{
  "type": "Feature",
  "properties": {
    "date:inception_lower": "1980-01-01",
    "date:inception_upper": "1980-01-01",
    "iso:country": "GB",
    "wof:name": "GU12 5BG",
    "wof:placetype": "postalcode"
  },
  "geometry": {"coordinates":[-0.720071,51.255251],"type":"Point"}
}
