{
  "type": "Feature",
  "properties": {
    "date:inception_lower":"1980-01-01",
    "date:inception_upper":"1980-01-31",
    "iso:country":"GB",
    "wof:name":"NG5 2FF",
    "wof:placetype":"postalcode"
},
  "geometry": {"coordinates":[-1.150955,52.979549],"type":"Point"}
}