{
  "type": "Feature",
  "properties": {
    "iso:country":"GB",
    "wof:name":"NG5 2FF",
    "wof:placetype":"postalcode"
},
  "geometry": {"coordinates":[-1.15095485423986,52.97954857697769],"type":"Point"}
}