{
  "type": "Feature",
  "properties": {
    "iso:country": "GB",
    "wof:name": "NG5 2FF",
    "wof:placetype": "postalcode"
  },
  "geometry": {"coordinates":[-1.150955,52.979549],"type":"Point"}
}
