{
  "type": "Feature",
  "properties": {
    "iso:country":"GB",
    "wof:name":"DT1 2EW",
    "wof:placetype":"postalcode"
},
  "geometry": {"coordinates":[-2.44439479574673,50.70779730462824],"type":"Point"}
}