{
  "type": "Feature",
  "properties": {
    "iso:country": "GB",
    "wof:name": "DT1 2EW",
    "wof:placetype": "postalcode"
  },
  "geometry": {"coordinates":[-2.444395,50.707797],"type":"Point"}
}
