{
  "type": "Feature",
  "properties": {
    "iso:country":"GB",
    "wof:name":"KT4 8FF",
    "wof:placetype":"postalcode"
},
  "geometry": {"coordinates":[-0.23764947081643,51.38392572377931],"type":"Point"}
}