{
  "type": "Feature",
  "properties": {
    "iso:country": "GB",
    "wof:name": "KT4 8FF",
    "wof:placetype": "postalcode"
  },
  "geometry": {"coordinates":[-0.237649,51.383926],"type":"Point"}
}
