{
  "type": "Feature",
  "properties": {
    "iso:country":"GB",
    "wof:name":"HR4 8BE",
    "wof:placetype":"postalcode"
},
  "geometry": {"coordinates":[-2.75306109559554,52.13384219182783],"type":"Point"}
}