{
  "type": "Feature",
  "properties": {
    "iso:country": "GB",
    "wof:name": "HR4 8BE",
    "wof:placetype": "postalcode"
  },
  "geometry": {"coordinates":[-2.753061,52.133842],"type":"Point"}
}
