{
  "type": "Feature",
  "properties": {
    "iso:country":"GB",
    "wof:name":"RH19 3SG",
    "wof:placetype":"postalcode"
},
  "geometry": {"coordinates":[0.04352249796557,51.11068135110313],"type":"Point"}
}