{
  "type": "Feature",
  "properties": {
    "iso:country":"GB",
    "wof:name":"AL1 5AT",
    "wof:placetype":"postalcode"
},
  "geometry": {"coordinates":[-0.30585187645292,51.7438664757161],"type":"Point"}
}