{
  "type": "Feature",
  "properties": {
    "iso:country": "GB",
    "wof:name": "MK10 9EE",
    "wof:placetype": "postalcode"
  },
  "geometry": {"coordinates":[-0.696347,52.035654],"type":"Point"}
}
