{
  "type": "Feature",
  "properties": {
    "iso:country":"GB",
    "wof:name":"MK10 9EE",
    "wof:placetype":"postalcode"
},
  "geometry": {"coordinates":[-0.69634671877095,52.03565443893704],"type":"Point"}
}