{
  "type": "Feature",
  "properties": {
    "date:inception_lower": "1980-01-01",
    "date:inception_upper": "1980-01-01",
    "iso:country": "GB",
    "wof:name": "CO10 9RU",
    "wof:placetype": "postalcode"
  },
  "geometry": {"coordinates":[0.79276,52.104176],"type":"Point"}
}
