{
  "type": "Feature",
  "properties": {
    "iso:country":"GB",
    "wof:name":"CO10 9RU",
    "wof:placetype":"postalcode"
},
  "geometry": {"coordinates":[0.79272897290799,52.10417043015354],"type":"Point"}
}