{
  "type": "Feature",
  "properties": {
    "iso:country": "GB",
    "wof:name": "CO10 9RU",
    "wof:placetype": "postalcode"
  },
  "geometry": {"coordinates":[0.79276,52.104176],"type":"Point"}
}
