{
  "type": "Feature",
  "properties": {
    "iso:country":"GB",
    "wof:name":"E10 6EU",
    "wof:placetype":"postalcode"
},
  "geometry": {"coordinates":[-0.00728695270794,51.57464763563733],"type":"Point"}
}