{
  "type": "Feature",
  "properties": {
    "iso:country": "GB",
    "wof:name": "LN7 6ET",
    "wof:placetype": "postalcode"
  },
  "geometry": {"coordinates":[-0.428439,53.499309],"type":"Point"}
}
