{
  "type": "Feature",
  "properties": {
    "iso:country":"GB",
    "wof:name":"LN7 6ET",
    "wof:placetype":"postalcode"
},
  "geometry": {"coordinates":[-0.42843904827652,53.49930851217881],"type":"Point"}
}