{
  "type": "Feature",
  "properties": {
    "date:inception_lower": "2001-12-01",
    "date:inception_upper": "2001-12-01",
    "iso:country": "GB",
    "wof:name": "EN4 0AJ",
    "wof:placetype": "postalcode"
  },
  "geometry": {"coordinates":[-0.181543,51.664397],"type":"Point"}
}
