{
  "type": "Feature",
  "properties": {
    "date:inception_lower":"1980-01-01",
    "date:inception_upper":"1980-01-31",
    "iso:country":"GB",
    "wof:name":"CF5 4NH",
    "wof:placetype":"postalcode"
},
  "geometry": {"coordinates":[-3.25627,51.475125],"type":"Point"}
}