{
  "type": "Feature",
  "properties": {
    "iso:country":"GB",
    "wof:name":"TN34 1PH",
    "wof:placetype":"postalcode"
},
  "geometry": {"coordinates":[0.58058801822733,50.85703566461515],"type":"Point"}
}