{
  "type": "Feature",
  "properties": {
    "iso:country":"GB",
    "wof:name":"CF81 9FG",
    "wof:placetype":"postalcode"
},
  "geometry": {"coordinates":[-3.22046820157168,51.68925651016271],"type":"Point"}
}