{
  "type": "Feature",
  "properties": {
    "iso:country":"GB",
    "wof:name":"B31 1SP",
    "wof:placetype":"postalcode"
},
  "geometry": {"coordinates":[-1.98241586355308,52.41503514753687],"type":"Point"}
}