{
  "type": "Feature",
  "properties": {
    "iso:country":"GB",
    "wof:name":"WN7 3DL",
    "wof:placetype":"postalcode"
},
  "geometry": {"coordinates":[-2.49833465913623,53.48869579703885],"type":"Point"}
}