{
  "type": "Feature",
  "properties": {
    "date:inception_lower":"1980-01-01",
    "date:inception_upper":"1980-01-31",
    "iso:country":"GB",
    "wof:name":"WN7 3DL",
    "wof:placetype":"postalcode"
},
  "geometry": {"coordinates":[-2.498335,53.488696],"type":"Point"}
}