{
  "type": "Feature",
  "properties": {
    "iso:country":"GB",
    "wof:name":"ME10 3EU",
    "wof:placetype":"postalcode"
},
  "geometry": {"coordinates":[0.75666770551991,51.35055242114496],"type":"Point"}
}