{
  "type": "Feature",
  "properties": {
    "iso:country":"GB",
    "wof:name":"KA3 5HP",
    "wof:placetype":"postalcode"
},
  "geometry": {"coordinates":[-4.51248488835011,55.67935439661674],"type":"Point"}
}