{
  "type": "Feature",
  "properties": {
    "iso:country":"GB",
    "wof:name":"M46 0GD",
    "wof:placetype":"postalcode"
},
  "geometry": {"coordinates":[-2.51089049794691,53.52265524966604],"type":"Point"}
}