{
  "type": "Feature",
  "properties": {
    "date:inception_lower":"1980-01-01",
    "date:inception_upper":"1980-01-31",
    "iso:country":"GB",
    "wof:name":"OL12 0RD",
    "wof:placetype":"postalcode"
},
  "geometry": {"coordinates":[-2.156041,53.624638],"type":"Point"}
}