{
  "type": "Feature",
  "properties": {
    "iso:country":"GB",
    "wof:name":"GL14 2QW",
    "wof:placetype":"postalcode"
},
  "geometry": {"coordinates":[-2.49616022598742,51.82694465733409],"type":"Point"}
}