{
  "type": "Feature",
  "properties": {
    "iso:country": "GB",
    "wof:name": "TN35 5FT",
    "wof:placetype": "postalcode"
  },
  "geometry": {"coordinates":[0.613845,50.876442],"type":"Point"}
}
