{
  "type": "Feature",
  "properties": {
    "date:inception_lower": "2011-05-01",
    "date:inception_upper": "2011-05-01",
    "iso:country": "GB",
    "wof:name": "TN35 5FT",
    "wof:placetype": "postalcode"
  },
  "geometry": {"coordinates":[0.613845,50.876442],"type":"Point"}
}
