{
  "type": "Feature",
  "properties": {
    "iso:country":"GB",
    "wof:name":"SN15 2HS",
    "wof:placetype":"postalcode"
},
  "geometry": {"coordinates":[-2.04088074770716,51.38949749580251],"type":"Point"}
}