{
  "type": "Feature",
  "properties": {
    "date:inception_lower":"2000-10-01",
    "date:inception_upper":"2000-10-31",
    "iso:country":"GB",
    "wof:name":"WD19 6UW",
    "wof:placetype":"postalcode"
},
  "geometry": {"coordinates":[-0.39673,51.61652],"type":"Point"}
}