{
  "type": "Feature",
  "properties": {
    "iso:country":"GB",
    "wof:name":"WD19 6UW",
    "wof:placetype":"postalcode"
},
  "geometry": {"coordinates":[-0.39672980387605,51.61651985817569],"type":"Point"}
}