{
  "type": "Feature",
  "properties": {
    "iso:country":"GB",
    "wof:name":"SK14 4TE",
    "wof:placetype":"postalcode"
},
  "geometry": {"coordinates":[-2.08027337545028,53.46378592172548],"type":"Point"}
}