{
  "type": "Feature",
  "properties": {
    "iso:country":"GB",
    "wof:name":"GL2 4TT",
    "wof:placetype":"postalcode"
},
  "geometry": {"coordinates":[-2.28659459815353,51.82112398171078],"type":"Point"}
}