{
  "type": "Feature",
  "properties": {
    "iso:country": "GB",
    "wof:name": "GL2 4TT",
    "wof:placetype": "postalcode"
  },
  "geometry": {"coordinates":[-2.286595,51.821124],"type":"Point"}
}
