{
  "type": "Feature",
  "properties": {
    "iso:country": "GB",
    "wof:name": "BB18 6RP",
    "wof:placetype": "postalcode"
  },
  "geometry": {"coordinates":[-2.135996,53.916225],"type":"Point"}
}
