{
  "type": "Feature",
  "properties": {
    "iso:country":"GB",
    "wof:name":"GL12 8SG",
    "wof:placetype":"postalcode"
},
  "geometry": {"coordinates":[-2.36571944533849,51.62519375150305],"type":"Point"}
}