{
  "type": "Feature",
  "properties": {
    "iso:country":"GB",
    "wof:name":"SG2 8BT",
    "wof:placetype":"postalcode"
},
  "geometry": {"coordinates":[-0.18390524437964,51.88630452073925],"type":"Point"}
}