{
  "type": "Feature",
  "properties": {
    "iso:country":"GB",
    "wof:name":"HR4 9PL",
    "wof:placetype":"postalcode"
},
  "geometry": {"coordinates":[-2.73676672575446,52.07070443624617],"type":"Point"}
}