{
  "type": "Feature",
  "properties": {
    "iso:country":"GB",
    "wof:name":"PL3 5HJ",
    "wof:placetype":"postalcode"
},
  "geometry": {"coordinates":[-4.12741041343103,50.39035014125403],"type":"Point"}
}