{
  "type": "Feature",
  "properties": {
    "date:inception_lower": "1980-01-01",
    "date:inception_upper": "1980-01-01",
    "iso:country": "GB",
    "wof:name": "PL3 5HJ",
    "wof:placetype": "postalcode"
  },
  "geometry": {"coordinates":[-4.12741,50.39035],"type":"Point"}
}
