{
  "type": "Feature",
  "properties": {
    "iso:country": "GB",
    "wof:name": "PL3 5HJ",
    "wof:placetype": "postalcode"
  },
  "geometry": {"coordinates":[-4.12741,50.39035],"type":"Point"}
}
