{
  "type": "Feature",
  "properties": {
    "date:inception_lower": "1981-06-01",
    "date:inception_upper": "1981-06-01",
    "iso:country": "GB",
    "wof:name": "DY10 4JR",
    "wof:placetype": "postalcode"
  },
  "geometry": {"coordinates":[-2.227884,52.368634],"type":"Point"}
}
