{
  "type": "Feature",
  "properties": {
    "iso:country": "GB",
    "wof:name": "DY10 4JR",
    "wof:placetype": "postalcode"
  },
  "geometry": {"coordinates":[-2.227884,52.368634],"type":"Point"}
}
