{
  "type": "Feature",
  "properties": {
    "iso:country":"GB",
    "wof:name":"S43 3EL",
    "wof:placetype":"postalcode"
},
  "geometry": {"coordinates":[-1.36490910989825,53.25196007191497],"type":"Point"}
}