{
  "type": "Feature",
  "properties": {
    "iso:country":"GB",
    "wof:name":"DD8 3PW",
    "wof:placetype":"postalcode"
},
  "geometry": {"coordinates":[-2.81482496826452,56.6936065239255],"type":"Point"}
}