{
  "type": "Feature",
  "properties": {
    "iso:country":"GB",
    "wof:name":"AB24 1US",
    "wof:placetype":"postalcode"
},
  "geometry": {"coordinates":[-2.09173919458589,57.16810574818438],"type":"Point"}
}