{
  "type": "Feature",
  "properties": {
    "iso:country": "GB",
    "wof:name": "DE21 4NQ",
    "wof:placetype": "postalcode"
  },
  "geometry": {"coordinates":[-1.430598,52.936521],"type":"Point"}
}
