{
  "type": "Feature",
  "properties": {
    "iso:country":"GB",
    "wof:name":"DE21 4NQ",
    "wof:placetype":"postalcode"
},
  "geometry": {"coordinates":[-1.43059760872601,52.93652109333842],"type":"Point"}
}