{
  "type": "Feature",
  "properties": {
    "iso:country":"GB",
    "wof:name":"SO15 7RT",
    "wof:placetype":"postalcode"
},
  "geometry": {"coordinates":[-1.42196174504696,50.93018538981983],"type":"Point"}
}