{
  "type": "Feature",
  "properties": {
    "date:inception_lower": "1980-01-01",
    "date:inception_upper": "1980-01-01",
    "iso:country": "GB",
    "wof:name": "PO1 4NF",
    "wof:placetype": "postalcode"
  },
  "geometry": {"coordinates":[-1.08392,50.806261],"type":"Point"}
}
