{
  "type": "Feature",
  "properties": {
    "iso:country": "GB",
    "wof:name": "PO1 4NF",
    "wof:placetype": "postalcode"
  },
  "geometry": {"coordinates":[-1.08392,50.806261],"type":"Point"}
}
