{
  "type": "Feature",
  "properties": {
    "iso:country": "GB",
    "wof:name": "CF44 6EJ",
    "wof:placetype": "postalcode"
  },
  "geometry": {"coordinates":[-3.441459,51.707208],"type":"Point"}
}
