{
  "type": "Feature",
  "properties": {
    "date:inception_lower":"1980-01-01",
    "date:inception_upper":"1980-01-31",
    "iso:country":"GB",
    "wof:name":"CF44 6EJ",
    "wof:placetype":"postalcode"
},
  "geometry": {"coordinates":[-3.441459,51.707208],"type":"Point"}
}