{
  "type": "Feature",
  "properties": {
    "iso:country":"GB",
    "wof:name":"CF44 6EJ",
    "wof:placetype":"postalcode"
},
  "geometry": {"coordinates":[-3.44145866194345,51.70720834947819],"type":"Point"}
}