{
  "type": "Feature",
  "properties": {
    "iso:country":"GB",
    "wof:name":"W9 1NW",
    "wof:placetype":"postalcode"
},
  "geometry": {"coordinates":[-0.18905679204403,51.53203809445914],"type":"Point"}
}