{
  "type": "Feature",
  "properties": {
    "date:inception_lower":"1980-01-01",
    "date:inception_upper":"1980-01-31",
    "iso:country":"GB",
    "wof:name":"LS8 4AD",
    "wof:placetype":"postalcode"
},
  "geometry": {"coordinates":[-1.509094,53.826121],"type":"Point"}
}