{
  "type": "Feature",
  "properties": {
    "date:inception_lower": "1980-01-01",
    "date:inception_upper": "1980-01-01",
    "iso:country": "GB",
    "wof:name": "BS9 1QR",
    "wof:placetype": "postalcode"
  },
  "geometry": {"coordinates":[-2.63868,51.473965],"type":"Point"}
}
