{
  "type": "Feature",
  "properties": {
    "iso:country": "GB",
    "wof:name": "SW9 1EG",
    "wof:placetype": "postalcode"
  },
  "geometry": {"coordinates":[-0.113562,51.468675],"type":"Point"}
}
