{
  "type": "Feature",
  "properties": {
    "iso:country":"GB",
    "wof:name":"LA4 5EG",
    "wof:placetype":"postalcode"
},
  "geometry": {"coordinates":[-2.86411039497256,54.07316806804507],"type":"Point"}
}