{
  "type": "Feature",
  "properties": {
    "date:inception_lower": "1980-01-01",
    "date:inception_upper": "1980-01-01",
    "iso:country": "GB",
    "wof:name": "GL20 5HT",
    "wof:placetype": "postalcode"
  },
  "geometry": {"coordinates":[-2.154845,51.983737],"type":"Point"}
}
