{
  "type": "Feature",
  "properties": {
    "iso:country":"GB",
    "wof:name":"TA1 1NB",
    "wof:placetype":"postalcode"
},
  "geometry": {"coordinates":[-3.10274548933791,51.01565701923121],"type":"Point"}
}