{
  "type": "Feature",
  "properties": {
    "date:inception_lower": "2018-06-01",
    "date:inception_upper": "2018-06-01",
    "iso:country": "GB",
    "wof:name": "G74 5DQ",
    "wof:placetype": "postalcode"
  },
  "geometry": {"coordinates":[-4.227764,55.772649],"type":"Point"}
}
