{
  "type": "Feature",
  "properties": {
    "iso:country":"GB",
    "wof:name":"TS12 2RY",
    "wof:placetype":"postalcode"
},
  "geometry": {"coordinates":[-0.95059316436262,54.56317042166771],"type":"Point"}
}