{
  "type": "Feature",
  "properties": {
    "iso:country":"GB",
    "wof:name":"DD4 0LT",
    "wof:placetype":"postalcode"
},
  "geometry": {"coordinates":[-2.9124526776123,56.49109813543805],"type":"Point"}
}