{
  "type": "Feature",
  "properties": {
    "iso:country": "GB",
    "wof:name": "YO41 1DJ",
    "wof:placetype": "postalcode"
  },
  "geometry": {"coordinates":[-0.916279,53.987005],"type":"Point"}
}
