{
  "type": "Feature",
  "properties": {
    "date:inception_lower":"2012-03-01",
    "date:inception_upper":"2012-03-31",
    "iso:country":"GB",
    "wof:name":"EH21 8NL",
    "wof:placetype":"postalcode"
},
  "geometry": {"coordinates":[-3.034162,55.916267],"type":"Point"}
}