{
  "type": "Feature",
  "properties": {
    "iso:country": "GB",
    "wof:name": "EH21 8NL",
    "wof:placetype": "postalcode"
  },
  "geometry": {"coordinates":[-3.034162,55.916267],"type":"Point"}
}
