{
  "type": "Feature",
  "properties": {
    "iso:country":"GB",
    "wof:name":"EH21 8NL",
    "wof:placetype":"postalcode"
},
  "geometry": {"coordinates":[-3.03416236265331,55.91626718798689],"type":"Point"}
}