{
  "type": "Feature",
  "properties": {
    "date:inception_lower":"2016-03-01",
    "date:inception_upper":"2016-03-31",
    "iso:country":"GB",
    "wof:name":"W1B 4HS",
    "wof:placetype":"postalcode"
},
  "geometry": {"coordinates":[-0.138734,51.510586],"type":"Point"}
}