{
  "type": "Feature",
  "properties": {
    "iso:country":"GB",
    "wof:name":"W1B 4HS",
    "wof:placetype":"postalcode"
},
  "geometry": {"coordinates":[-0.13877460063413,51.51064027712854],"type":"Point"}
}