{
  "type": "Feature",
  "properties": {
    "iso:country":"GB",
    "wof:name":"YO24 2UB",
    "wof:placetype":"postalcode"
},
  "geometry": {"coordinates":[-1.12317805196799,53.94111859644342],"type":"Point"}
}