{
  "type": "Feature",
  "properties": {
    "iso:country":"GB",
    "wof:name":"NR3 3HN",
    "wof:placetype":"postalcode"
},
  "geometry": {"coordinates":[1.29222150264965,52.63920555961572],"type":"Point"}
}