{
  "type": "Feature",
  "properties": {
    "date:inception_lower": "1980-01-01",
    "date:inception_upper": "1980-01-01",
    "iso:country": "GB",
    "wof:name": "NR3 3HN",
    "wof:placetype": "postalcode"
  },
  "geometry": {"coordinates":[1.292222,52.639206],"type":"Point"}
}
