{
  "type": "Feature",
  "properties": {
    "iso:country":"GB",
    "wof:name":"BD12 0QS",
    "wof:placetype":"postalcode"
},
  "geometry": {"coordinates":[-1.76500161280285,53.75047896092893],"type":"Point"}
}