{
  "type": "Feature",
  "properties": {
    "iso:country":"GB",
    "wof:name":"CF82 8AQ",
    "wof:placetype":"postalcode"
},
  "geometry": {"coordinates":[-3.22851764738971,51.66275506221174],"type":"Point"}
}