{
  "type": "Feature",
  "properties": {
    "iso:country":"GB",
    "wof:name":"RM8 3DG",
    "wof:placetype":"postalcode"
},
  "geometry": {"coordinates":[0.13302505565906,51.5612006388115],"type":"Point"}
}