{
  "type": "Feature",
  "properties": {
    "iso:country":"GB",
    "wof:name":"W5 2AR",
    "wof:placetype":"postalcode"
},
  "geometry": {"coordinates":[-0.3120644330958,51.51501559261558],"type":"Point"}
}