{
  "type": "Feature",
  "properties": {
    "iso:country":"GB",
    "wof:name":"EX6 8HB",
    "wof:placetype":"postalcode"
},
  "geometry": {"coordinates":[-3.51012042286584,50.62581639497866],"type":"Point"}
}