{
  "type": "Feature",
  "properties": {
    "date:inception_lower":"2013-12-01",
    "date:inception_upper":"2013-12-31",
    "iso:country":"GB",
    "wof:name":"PL8 2PL",
    "wof:placetype":"postalcode"
},
  "geometry": {"coordinates":[-4.006645,50.348407],"type":"Point"}
}