{
  "type": "Feature",
  "properties": {
    "date:inception_lower": "1993-01-01",
    "date:inception_upper": "1993-01-01",
    "iso:country": "GB",
    "wof:name": "MK14 6EJ",
    "wof:placetype": "postalcode"
  },
  "geometry": {"coordinates":[-0.765318,52.062624],"type":"Point"}
}
