{
  "type": "Feature",
  "properties": {
    "iso:country":"GB",
    "wof:name":"RM7 8NB",
    "wof:placetype":"postalcode"
},
  "geometry": {"coordinates":[0.15876531581949,51.59502832552449],"type":"Point"}
}