{
  "type": "Feature",
  "properties": {
    "date:inception_lower": "1980-01-01",
    "date:inception_upper": "1980-01-01",
    "iso:country": "GB",
    "wof:name": "RM7 8NB",
    "wof:placetype": "postalcode"
  },
  "geometry": {"coordinates":[0.158779,51.595049],"type":"Point"}
}
