{
  "type": "Feature",
  "properties": {
    "date:inception_lower": "1981-09-01",
    "date:inception_upper": "1981-09-01",
    "iso:country": "GB",
    "wof:name": "GU10 1DA",
    "wof:placetype": "postalcode"
  },
  "geometry": {"coordinates":[-0.730088,51.238076],"type":"Point"}
}
