{
  "type": "Feature",
  "properties": {
    "iso:country":"GB",
    "wof:name":"LE3 3GQ",
    "wof:placetype":"postalcode"
},
  "geometry": {"coordinates":[-1.2070984637272,52.62665912888928],"type":"Point"}
}