{
  "type": "Feature",
  "properties": {
    "iso:country": "GB",
    "wof:name": "LE3 3GQ",
    "wof:placetype": "postalcode"
  },
  "geometry": {"coordinates":[-1.207098,52.626659],"type":"Point"}
}
