{
  "type": "Feature",
  "properties": {
    "date:inception_lower":"2012-11-01",
    "date:inception_upper":"2012-11-30",
    "iso:country":"GB",
    "wof:name":"LE3 3GQ",
    "wof:placetype":"postalcode"
},
  "geometry": {"coordinates":[-1.207098,52.626659],"type":"Point"}
}