{
  "type": "Feature",
  "properties": {
    "iso:country": "GB",
    "wof:name": "TR21 0LJ",
    "wof:placetype": "postalcode"
  },
  "geometry": {"coordinates":[-6.316351,49.914895],"type":"Point"}
}
