{
  "type": "Feature",
  "properties": {
    "iso:country":"GB",
    "wof:name":"WA1 3UA",
    "wof:placetype":"postalcode"
},
  "geometry": {"coordinates":[-2.54863315328932,53.39802300279798],"type":"Point"}
}