{
  "type": "Feature",
  "properties": {
    "date:inception_lower": "1980-01-01",
    "date:inception_upper": "1980-01-01",
    "iso:country": "GB",
    "wof:name": "WA1 3UA",
    "wof:placetype": "postalcode"
  },
  "geometry": {"coordinates":[-2.548694,53.398048],"type":"Point"}
}
