{
  "type": "Feature",
  "properties": {
    "iso:country": "GB",
    "wof:name": "NE40 4HP",
    "wof:placetype": "postalcode"
  },
  "geometry": {"coordinates":[-1.79101,54.9645],"type":"Point"}
}
