{
  "type": "Feature",
  "properties": {
    "iso:country":"GB",
    "wof:name":"NE71 6LE",
    "wof:placetype":"postalcode"
},
  "geometry": {"coordinates":[-2.01518707445652,55.54584225814178],"type":"Point"}
}