{
  "type": "Feature",
  "properties": {
    "date:inception_lower":"2005-10-01",
    "date:inception_upper":"2005-10-31",
    "iso:country":"GB",
    "wof:name":"LN11 0FE",
    "wof:placetype":"postalcode"
},
  "geometry": {"coordinates":[-0.008565,53.36976],"type":"Point"}
}