{
  "type": "Feature",
  "properties": {
    "iso:country":"GB",
    "wof:name":"LN11 0FE",
    "wof:placetype":"postalcode"
},
  "geometry": {"coordinates":[-0.00856525067784,53.36975995715991],"type":"Point"}
}