{
  "type": "Feature",
  "properties": {
    "iso:country": "GB",
    "wof:name": "LN11 0FE",
    "wof:placetype": "postalcode"
  },
  "geometry": {"coordinates":[-0.008565,53.36976],"type":"Point"}
}
