{
  "type": "Feature",
  "properties": {
    "iso:country": "GB",
    "wof:name": "SR6 9QZ",
    "wof:placetype": "postalcode"
  },
  "geometry": {"coordinates":[-1.378559,54.921665],"type":"Point"}
}
