{
  "type": "Feature",
  "properties": {
    "iso:country":"GB",
    "wof:name":"CA7 9AQ",
    "wof:placetype":"postalcode"
},
  "geometry": {"coordinates":[-3.16090212428105,54.8263985377468],"type":"Point"}
}