{
  "type": "Feature",
  "properties": {
    "date:inception_lower": "1994-05-01",
    "date:inception_upper": "1994-05-01",
    "iso:country": "GB",
    "wof:name": "CA7 9AQ",
    "wof:placetype": "postalcode"
  },
  "geometry": {"coordinates":[-3.160902,54.826399],"type":"Point"}
}
