{
  "type": "Feature",
  "properties": {
    "iso:country":"GB",
    "wof:name":"LE7 9DR",
    "wof:placetype":"postalcode"
},
  "geometry": {"coordinates":[-0.91554220601352,52.64081962497885],"type":"Point"}
}