{
  "type": "Feature",
  "properties": {
    "iso:country": "GB",
    "wof:name": "RM16 6RW",
    "wof:placetype": "postalcode"
  },
  "geometry": {"coordinates":[0.303072,51.489782],"type":"Point"}
}
