{
  "type": "Feature",
  "properties": {
    "date:inception_lower":"2000-06-01",
    "date:inception_upper":"2000-06-30",
    "iso:country":"GB",
    "wof:name":"RM16 6RW",
    "wof:placetype":"postalcode"
},
  "geometry": {"coordinates":[0.303072,51.489782],"type":"Point"}
}