{
  "type": "Feature",
  "properties": {
    "iso:country":"GB",
    "wof:name":"PR5 0JJ",
    "wof:placetype":"postalcode"
},
  "geometry": {"coordinates":[-2.61589923833112,53.73947183825028],"type":"Point"}
}