{
  "type": "Feature",
  "properties": {
    "date:inception_lower": "1980-01-01",
    "date:inception_upper": "1980-01-01",
    "iso:country": "GB",
    "wof:name": "PR5 0JJ",
    "wof:placetype": "postalcode"
  },
  "geometry": {"coordinates":[-2.615899,53.739472],"type":"Point"}
}
