{
  "type": "Feature",
  "properties": {
    "date:inception_lower": "1996-12-01",
    "date:inception_upper": "1996-12-01",
    "iso:country": "GB",
    "wof:name": "BB7 3JS",
    "wof:placetype": "postalcode"
  },
  "geometry": {"coordinates":[-2.399442,53.901715],"type":"Point"}
}
