{
  "type": "Feature",
  "properties": {
    "iso:country":"GB",
    "wof:name":"BB7 3JS",
    "wof:placetype":"postalcode"
},
  "geometry": {"coordinates":[-2.39944225713145,53.90171453735912],"type":"Point"}
}