{
  "type": "Feature",
  "properties": {
    "iso:country": "GB",
    "wof:name": "DN14 8PA",
    "wof:placetype": "postalcode"
  },
  "geometry": {"coordinates":[-0.947875,53.685187],"type":"Point"}
}
