{
  "type": "Feature",
  "properties": {
    "iso:country": "GB",
    "wof:name": "NE3 2NB",
    "wof:placetype": "postalcode"
  },
  "geometry": {"coordinates":[-1.63946,55.015547],"type":"Point"}
}
