{
  "type": "Feature",
  "properties": {
    "iso:country":"GB",
    "wof:name":"NE3 2NB",
    "wof:placetype":"postalcode"
},
  "geometry": {"coordinates":[-1.63945997707861,55.01554681341148],"type":"Point"}
}