{
  "type": "Feature",
  "properties": {
    "iso:country":"GB",
    "wof:name":"NP22 5HJ",
    "wof:placetype":"postalcode"
},
  "geometry": {"coordinates":[-3.28822119525768,51.76578903814789],"type":"Point"}
}