{
  "type": "Feature",
  "properties": {
    "iso:country": "GB",
    "wof:name": "NP22 5HJ",
    "wof:placetype": "postalcode"
  },
  "geometry": {"coordinates":[-3.288221,51.765789],"type":"Point"}
}
