{
  "type": "Feature",
  "properties": {
    "iso:country":"GB",
    "wof:name":"BH24 2DS",
    "wof:placetype":"postalcode"
},
  "geometry": {"coordinates":[-1.84111590934715,50.83925370759791],"type":"Point"}
}