{
  "type": "Feature",
  "properties": {
    "iso:country": "GB",
    "wof:name": "CV2 3BP",
    "wof:placetype": "postalcode"
  },
  "geometry": {"coordinates":[-1.451505,52.422378],"type":"Point"}
}
