{
  "type": "Feature",
  "properties": {
    "iso:country":"GB",
    "wof:name":"CV2 3BP",
    "wof:placetype":"postalcode"
},
  "geometry": {"coordinates":[-1.45150531271596,52.42237804773315],"type":"Point"}
}