{
  "type": "Feature",
  "properties": {
    "date:inception_lower":"1995-07-01",
    "date:inception_upper":"1995-07-31",
    "iso:country":"GB",
    "wof:name":"CM7 2TN",
    "wof:placetype":"postalcode"
},
  "geometry": {"coordinates":[0.537605,51.886397],"type":"Point"}
}