{
  "type": "Feature",
  "properties": {
    "iso:country":"GB",
    "wof:name":"CM7 2TN",
    "wof:placetype":"postalcode"
},
  "geometry": {"coordinates":[0.53760536984618,51.88639698871884],"type":"Point"}
}