{
  "type": "Feature",
  "properties": {
    "iso:country": "GB",
    "wof:name": "RM12 5SX",
    "wof:placetype": "postalcode"
  },
  "geometry": {"coordinates":[0.210224,51.551617],"type":"Point"}
}
