{
  "type": "Feature",
  "properties": {
    "iso:country":"GB",
    "wof:name":"BS4 2RF",
    "wof:placetype":"postalcode"
},
  "geometry": {"coordinates":[-2.57398235034898,51.43471977062148],"type":"Point"}
}