{
  "type": "Feature",
  "properties": {
    "iso:country":"GB",
    "wof:name":"RM10 9NS",
    "wof:placetype":"postalcode"
},
  "geometry": {"coordinates":[0.14846642793394,51.53893144438536],"type":"Point"}
}