{
  "type": "Feature",
  "properties": {
    "date:inception_lower": "1980-01-01",
    "date:inception_upper": "1980-01-01",
    "iso:country": "GB",
    "wof:name": "IG6 1BT",
    "wof:placetype": "postalcode"
  },
  "geometry": {"coordinates":[0.085369,51.585494],"type":"Point"}
}
