{
  "type": "Feature",
  "properties": {
    "iso:country":"GB",
    "wof:name":"IG6 1BT",
    "wof:placetype":"postalcode"
},
  "geometry": {"coordinates":[0.08534219080738,51.58549285001561],"type":"Point"}
}