{
  "type": "Feature",
  "properties": {
    "iso:country": "GB",
    "wof:name": "BD14 6JQ",
    "wof:placetype": "postalcode"
  },
  "geometry": {"coordinates":[-1.81725,53.780437],"type":"Point"}
}
