{
  "type": "Feature",
  "properties": {
    "iso:country":"GB",
    "wof:name":"BD14 6JQ",
    "wof:placetype":"postalcode"
},
  "geometry": {"coordinates":[-1.81725054040026,53.78043707270267],"type":"Point"}
}