{
  "type": "Feature",
  "properties": {
    "iso:country":"GB",
    "wof:name":"SR6 7RN",
    "wof:placetype":"postalcode"
},
  "geometry": {"coordinates":[-1.41575430821994,54.95402116029589],"type":"Point"}
}