{
  "type": "Feature",
  "properties": {
    "iso:country": "GB",
    "wof:name": "NN12 6NN",
    "wof:placetype": "postalcode"
  },
  "geometry": {"coordinates":[-0.974531,52.121582],"type":"Point"}
}
