{
  "type": "Feature",
  "properties": {
    "iso:country":"GB",
    "wof:name":"IG11 0LQ",
    "wof:placetype":"postalcode"
},
  "geometry": {"coordinates":[0.10756287489608,51.52786598744024],"type":"Point"}
}