{
  "type": "Feature",
  "properties": {
    "iso:country":"GB",
    "wof:name":"SM6 0RL",
    "wof:placetype":"postalcode"
},
  "geometry": {"coordinates":[-0.14836511660551,51.34998618550458],"type":"Point"}
}