{
  "type": "Feature",
  "properties": {
    "date:inception_lower":"1980-01-01",
    "date:inception_upper":"1980-01-31",
    "iso:country":"GB",
    "wof:name":"SM6 0RL",
    "wof:placetype":"postalcode"
},
  "geometry": {"coordinates":[-0.148365,51.349986],"type":"Point"}
}