{
  "type": "Feature",
  "properties": {
    "iso:country":"GB",
    "wof:name":"GL4 4WA",
    "wof:placetype":"postalcode"
},
  "geometry": {"coordinates":[-2.21122664494084,51.84965912660353],"type":"Point"}
}