{
  "type": "Feature",
  "properties": {
    "iso:country":"GB",
    "wof:name":"N17 9QQ",
    "wof:placetype":"postalcode"
},
  "geometry": {"coordinates":[-0.05786676225671,51.58995563715823],"type":"Point"}
}