{
  "type": "Feature",
  "properties": {
    "iso:country":"GB",
    "wof:name":"BN6 8BQ",
    "wof:placetype":"postalcode"
},
  "geometry": {"coordinates":[-0.12987476544105,50.92353028118112],"type":"Point"}
}