{
  "type": "Feature",
  "properties": {
    "iso:country": "GB",
    "wof:name": "BN6 8BQ",
    "wof:placetype": "postalcode"
  },
  "geometry": {"coordinates":[-0.129875,50.92353],"type":"Point"}
}
