{
  "type": "Feature",
  "properties": {
    "iso:country":"GB",
    "wof:name":"NG23 6QN",
    "wof:placetype":"postalcode"
},
  "geometry": {"coordinates":[-0.81893935851425,53.1878794042799],"type":"Point"}
}