{
  "type": "Feature",
  "properties": {
    "date:inception_lower": "1980-01-01",
    "date:inception_upper": "1980-01-01",
    "iso:country": "GB",
    "wof:name": "NG23 6QN",
    "wof:placetype": "postalcode"
  },
  "geometry": {"coordinates":[-0.818939,53.187879],"type":"Point"}
}
