{
  "type": "Feature",
  "properties": {
    "date:inception_lower": "1980-01-01",
    "date:inception_upper": "1980-01-01",
    "iso:country": "GB",
    "wof:name": "LD8 2NF",
    "wof:placetype": "postalcode"
  },
  "geometry": {"coordinates":[-3.031984,52.282883],"type":"Point"}
}
