{
  "type": "Feature",
  "properties": {
    "iso:country":"GB",
    "wof:name":"SY8 2NQ",
    "wof:placetype":"postalcode"
},
  "geometry": {"coordinates":[-2.7144861069144,52.37507204430494],"type":"Point"}
}