{
  "type": "Feature",
  "properties": {
    "iso:country":"GB",
    "wof:name":"FK7 7QU",
    "wof:placetype":"postalcode"
},
  "geometry": {"coordinates":[-3.92841048580421,56.10659222072423],"type":"Point"}
}