{
  "type": "Feature",
  "properties": {
    "iso:country": "GB",
    "wof:name": "NP19 4DS",
    "wof:placetype": "postalcode"
  },
  "geometry": {"coordinates":[-2.934506,51.578724],"type":"Point"}
}
