{
  "type": "Feature",
  "properties": {
    "iso:country":"GB",
    "wof:name":"PL2 3EL",
    "wof:placetype":"postalcode"
},
  "geometry": {"coordinates":[-4.15736655719774,50.38700988437397],"type":"Point"}
}