{
  "type": "Feature",
  "properties": {
    "date:inception_lower": "1980-01-01",
    "date:inception_upper": "1980-01-01",
    "iso:country": "GB",
    "wof:name": "RG7 6NY",
    "wof:placetype": "postalcode"
  },
  "geometry": {"coordinates":[-1.180189,51.419504],"type":"Point"}
}
