{
  "type": "Feature",
  "properties": {
    "iso:country":"GB",
    "wof:name":"RG7 6NY",
    "wof:placetype":"postalcode"
},
  "geometry": {"coordinates":[-1.18020851306355,51.41950427723296],"type":"Point"}
}