{
  "type": "Feature",
  "properties": {
    "iso:country":"GB",
    "wof:name":"AB33 8BZ",
    "wof:placetype":"postalcode"
},
  "geometry": {"coordinates":[-2.69923630606985,57.23048313007401],"type":"Point"}
}