{
  "type": "Feature",
  "properties": {
    "iso:country": "GB",
    "wof:name": "AB33 8BZ",
    "wof:placetype": "postalcode"
  },
  "geometry": {"coordinates":[-2.699236,57.230483],"type":"Point"}
}
