{
  "type": "Feature",
  "properties": {
    "iso:country":"GB",
    "wof:name":"SO17 1DT",
    "wof:placetype":"postalcode"
},
  "geometry": {"coordinates":[-1.40038202651336,50.92635375174282],"type":"Point"}
}