{
  "type": "Feature",
  "properties": {
    "iso:country":"GB",
    "wof:name":"S35 2YJ",
    "wof:placetype":"postalcode"
},
  "geometry": {"coordinates":[-1.47195034167178,53.4674563686012],"type":"Point"}
}