{
  "type": "Feature",
  "properties": {
    "date:inception_lower": "2023-06-01",
    "date:inception_upper": "2023-06-01",
    "iso:country": "GB",
    "wof:name": "OX39 4GQ",
    "wof:placetype": "postalcode"
  },
  "geometry": {"coordinates":[-0.911726,51.695348],"type":"Point"}
}
