{
  "type": "Feature",
  "properties": {
    "iso:country":"GB",
    "wof:name":"LA23 2BQ",
    "wof:placetype":"postalcode"
},
  "geometry": {"coordinates":[-2.90017802085914,54.37276800041268],"type":"Point"}
}