{
  "type": "Feature",
  "properties": {
    "date:inception_lower": "1980-01-01",
    "date:inception_upper": "1980-01-01",
    "iso:country": "GB",
    "wof:name": "LA23 2BQ",
    "wof:placetype": "postalcode"
  },
  "geometry": {"coordinates":[-2.900178,54.372768],"type":"Point"}
}
