{
  "type": "Feature",
  "properties": {
    "iso:country": "GB",
    "wof:name": "DE22 4EZ",
    "wof:placetype": "postalcode"
  },
  "geometry": {"coordinates":[-1.519427,52.929515],"type":"Point"}
}
