{
  "type": "Feature",
  "properties": {
    "iso:country":"GB",
    "wof:name":"DE22 4EZ",
    "wof:placetype":"postalcode"
},
  "geometry": {"coordinates":[-1.51942688273891,52.929515069651],"type":"Point"}
}