{
  "type": "Feature",
  "properties": {
    "iso:country":"GB",
    "wof:name":"SM5 4LE",
    "wof:placetype":"postalcode"
},
  "geometry": {"coordinates":[-0.16229132972932,51.35330798310765],"type":"Point"}
}