{
  "type": "Feature",
  "properties": {
    "iso:country":"GB",
    "wof:name":"TF2 8DG",
    "wof:placetype":"postalcode"
},
  "geometry": {"coordinates":[-2.43306473505619,52.71771422665392],"type":"Point"}
}