{
  "type": "Feature",
  "properties": {
    "iso:country":"GB",
    "wof:name":"TN21 0AE",
    "wof:placetype":"postalcode"
},
  "geometry": {"coordinates":[0.24869364858258,50.96597553914413],"type":"Point"}
}