{
  "type": "Feature",
  "properties": {
    "iso:country":"GB",
    "wof:name":"SA66 7SB",
    "wof:placetype":"postalcode"
},
  "geometry": {"coordinates":[-4.67782434047718,51.94692060754153],"type":"Point"}
}