{
  "type": "Feature",
  "properties": {
    "date:inception_lower": "2015-05-01",
    "date:inception_upper": "2015-05-01",
    "iso:country": "GB",
    "wof:name": "MK42 7GT",
    "wof:placetype": "postalcode"
  },
  "geometry": {"coordinates":[-0.513295,52.107719],"type":"Point"}
}
