{
  "type": "Feature",
  "properties": {
    "iso:country": "GB",
    "wof:name": "DY14 8HZ",
    "wof:placetype": "postalcode"
  },
  "geometry": {"coordinates":[-2.442687,52.414805],"type":"Point"}
}
