{
  "type": "Feature",
  "properties": {
    "iso:country":"GB",
    "wof:name":"DY14 8HZ",
    "wof:placetype":"postalcode"
},
  "geometry": {"coordinates":[-2.44268953344769,52.41479109188814],"type":"Point"}
}