{
  "type": "Feature",
  "properties": {
    "iso:country": "GB",
    "wof:name": "DY14 8HZ",
    "wof:placetype": "postalcode"
  },
  "geometry": {"coordinates":[-2.440934,52.415908],"type":"Point"}
}
