{
  "type": "Feature",
  "properties": {
    "date:inception_lower":"1980-01-01",
    "date:inception_upper":"1980-01-31",
    "iso:country":"GB",
    "wof:name":"NR5 0SD",
    "wof:placetype":"postalcode"
},
  "geometry": {"coordinates":[1.20797,52.646897],"type":"Point"}
}