{
  "type": "Feature",
  "properties": {
    "iso:country":"GB",
    "wof:name":"AL3 5SQ",
    "wof:placetype":"postalcode"
},
  "geometry": {"coordinates":[-0.33956486456031,51.75159514371479],"type":"Point"}
}