{
  "type": "Feature",
  "properties": {
    "date:inception_lower":"1986-07-01",
    "date:inception_upper":"1986-07-31",
    "iso:country":"GB",
    "wof:name":"AL3 5SQ",
    "wof:placetype":"postalcode"
},
  "geometry": {"coordinates":[-0.339565,51.751595],"type":"Point"}
}