{
  "type": "Feature",
  "properties": {
    "iso:country": "GB",
    "wof:name": "NE4 6JG",
    "wof:placetype": "postalcode"
  },
  "geometry": {"coordinates":[-1.635272,54.972068],"type":"Point"}
}
