{
  "type": "Feature",
  "properties": {
    "date:inception_lower":"1980-01-01",
    "date:inception_upper":"1980-01-31",
    "iso:country":"GB",
    "wof:name":"NE4 6JG",
    "wof:placetype":"postalcode"
},
  "geometry": {"coordinates":[-1.635272,54.972068],"type":"Point"}
}