{
  "type": "Feature",
  "properties": {
    "iso:country":"GB",
    "wof:name":"TA4 2EQ",
    "wof:placetype":"postalcode"
},
  "geometry": {"coordinates":[-3.35323971478049,51.06941683580116],"type":"Point"}
}