{
  "type": "Feature",
  "properties": {
    "date:inception_lower": "1980-01-01",
    "date:inception_upper": "1980-01-01",
    "iso:country": "GB",
    "wof:name": "TA4 2EQ",
    "wof:placetype": "postalcode"
  },
  "geometry": {"coordinates":[-3.35324,51.069417],"type":"Point"}
}
