{
  "type": "Feature",
  "properties": {
    "iso:country": "GB",
    "wof:name": "CB11 4BZ",
    "wof:placetype": "postalcode"
  },
  "geometry": {"coordinates":[0.235956,52.012431],"type":"Point"}
}
