{
  "type": "Feature",
  "properties": {
    "iso:country": "GB",
    "wof:name": "ST3 4SN",
    "wof:placetype": "postalcode"
  },
  "geometry": {"coordinates":[-2.133647,52.981253],"type":"Point"}
}
