{
  "type": "Feature",
  "properties": {
    "iso:country":"GB",
    "wof:name":"B76 2QN",
    "wof:placetype":"postalcode"
},
  "geometry": {"coordinates":[-1.79935848278305,52.54726192864568],"type":"Point"}
}