{
  "type": "Feature",
  "properties": {
    "iso:country": "GB",
    "wof:name": "NN13 6QG",
    "wof:placetype": "postalcode"
  },
  "geometry": {"coordinates":[-1.157185,52.040885],"type":"Point"}
}
