{
  "type": "Feature",
  "properties": {
    "date:inception_lower": "2007-01-01",
    "date:inception_upper": "2007-01-01",
    "iso:country": "GB",
    "wof:name": "LS3 1HY",
    "wof:placetype": "postalcode"
  },
  "geometry": {"coordinates":[-1.564535,53.800701],"type":"Point"}
}
