{
  "type": "Feature",
  "properties": {
    "iso:country":"GB",
    "wof:name":"LS3 1HY",
    "wof:placetype":"postalcode"
},
  "geometry": {"coordinates":[-1.56453551623113,53.80070134828984],"type":"Point"}
}