{
  "type": "Feature",
  "properties": {
    "iso:country":"GB",
    "wof:name":"WF17 0NS",
    "wof:placetype":"postalcode"
},
  "geometry": {"coordinates":[-1.64896399160644,53.73194974054498],"type":"Point"}
}