{
  "type": "Feature",
  "properties": {
    "iso:country": "GB",
    "wof:name": "TF11 8GH",
    "wof:placetype": "postalcode"
  },
  "geometry": {"coordinates":[-2.37474,52.677016],"type":"Point"}
}
