{
  "type": "Feature",
  "properties": {
    "iso:country": "GB",
    "wof:name": "SG16 6LH",
    "wof:placetype": "postalcode"
  },
  "geometry": {"coordinates":[-0.321268,52.002773],"type":"Point"}
}
