{
  "type": "Feature",
  "properties": {
    "iso:country":"GB",
    "wof:name":"SG16 6LH",
    "wof:placetype":"postalcode"
},
  "geometry": {"coordinates":[-0.32126795439417,52.00277284566985],"type":"Point"}
}