{
  "type": "Feature",
  "properties": {
    "iso:country":"GB",
    "wof:name":"E2 6QX",
    "wof:placetype":"postalcode"
},
  "geometry": {"coordinates":[-0.05881928140689,51.53067460170431],"type":"Point"}
}