{
  "type": "Feature",
  "properties": {
    "iso:country":"GB",
    "wof:name":"RG6 7EP",
    "wof:placetype":"postalcode"
},
  "geometry": {"coordinates":[-0.91919764104884,51.440453010231],"type":"Point"}
}