{
  "type": "Feature",
  "properties": {
    "iso:country": "GB",
    "wof:name": "DE4 5FU",
    "wof:placetype": "postalcode"
  },
  "geometry": {"coordinates":[-1.518242,53.136397],"type":"Point"}
}
