{
  "type": "Feature",
  "properties": {
    "date:inception_lower":"2014-02-01",
    "date:inception_upper":"2014-02-28",
    "iso:country":"GB",
    "wof:name":"DE4 5FU",
    "wof:placetype":"postalcode"
},
  "geometry": {"coordinates":[-1.518004,53.136252],"type":"Point"}
}