{
  "type": "Feature",
  "properties": {
    "iso:country": "GB",
    "wof:name": "TR7 3BX",
    "wof:placetype": "postalcode"
  },
  "geometry": {"coordinates":[-5.054571,50.419787],"type":"Point"}
}
