{
  "type": "Feature",
  "properties": {
    "iso:country":"GB",
    "wof:name":"TR7 3BX",
    "wof:placetype":"postalcode"
},
  "geometry": {"coordinates":[-5.05457131843736,50.41978735230305],"type":"Point"}
}