{
  "type": "Feature",
  "properties": {
    "date:inception_lower": "1981-06-01",
    "date:inception_upper": "1981-06-01",
    "iso:country": "GB",
    "wof:name": "SP10 1LH",
    "wof:placetype": "postalcode"
  },
  "geometry": {"coordinates":[-1.478969,51.207144],"type":"Point"}
}
