{
  "type": "Feature",
  "properties": {
    "iso:country": "GB",
    "wof:name": "SP10 1LH",
    "wof:placetype": "postalcode"
  },
  "geometry": {"coordinates":[-1.478969,51.207144],"type":"Point"}
}
