{
  "type": "Feature",
  "properties": {
    "date:inception_lower":"1995-07-01",
    "date:inception_upper":"1995-07-31",
    "iso:country":"GB",
    "wof:name":"SP6 1LS",
    "wof:placetype":"postalcode"
},
  "geometry": {"coordinates":[-1.795754,50.927444],"type":"Point"}
}