{
  "type": "Feature",
  "properties": {
    "iso:country": "GB",
    "wof:name": "SP6 1LS",
    "wof:placetype": "postalcode"
  },
  "geometry": {"coordinates":[-1.795754,50.927444],"type":"Point"}
}
