{
  "type": "Feature",
  "properties": {
    "iso:country":"GB",
    "wof:name":"SP6 1LS",
    "wof:placetype":"postalcode"
},
  "geometry": {"coordinates":[-1.79575419896916,50.92744393099489],"type":"Point"}
}