{
  "type": "Feature",
  "properties": {
    "date:inception_lower":"1980-01-01",
    "date:inception_upper":"1980-01-31",
    "iso:country":"GB",
    "wof:name":"CF37 1EB",
    "wof:placetype":"postalcode"
},
  "geometry": {"coordinates":[-3.349355,51.598755],"type":"Point"}
}