{
  "type": "Feature",
  "properties": {
    "iso:country":"GB",
    "wof:name":"CF37 1EB",
    "wof:placetype":"postalcode"
},
  "geometry": {"coordinates":[-3.34935541246813,51.5987554604019],"type":"Point"}
}