{
  "type": "Feature",
  "properties": {
    "iso:country":"GB",
    "wof:name":"DN7 6SP",
    "wof:placetype":"postalcode"
},
  "geometry": {"coordinates":[-1.00709250389262,53.57835961413022],"type":"Point"}
}