{
  "type": "Feature",
  "properties": {
    "iso:country": "GB",
    "wof:name": "SA62 6HD",
    "wof:placetype": "postalcode"
  },
  "geometry": {"coordinates":[-5.069474,51.857927],"type":"Point"}
}
