{
  "type": "Feature",
  "properties": {
    "iso:country":"GB",
    "wof:name":"SA62 6HD",
    "wof:placetype":"postalcode"
},
  "geometry": {"coordinates":[-5.06947394243521,51.85792736636486],"type":"Point"}
}