{
  "type": "Feature",
  "properties": {
    "date:inception_lower": "1980-01-01",
    "date:inception_upper": "1980-01-01",
    "iso:country": "GB",
    "wof:name": "SA62 6HD",
    "wof:placetype": "postalcode"
  },
  "geometry": {"coordinates":[-5.069474,51.857927],"type":"Point"}
}
