{
  "type": "Feature",
  "properties": {
    "date:inception_lower": "1980-01-01",
    "date:inception_upper": "1980-01-01",
    "iso:country": "GB",
    "wof:name": "SA44 6JA",
    "wof:placetype": "postalcode"
  },
  "geometry": {"coordinates":[-4.335027,52.164655],"type":"Point"}
}
