{
  "type": "Feature",
  "properties": {
    "iso:country":"GB",
    "wof:name":"WF7 5EG",
    "wof:placetype":"postalcode"
},
  "geometry": {"coordinates":[-1.35973462374561,53.67482917444023],"type":"Point"}
}