{
  "type": "Feature",
  "properties": {
    "date:inception_lower":"1992-08-01",
    "date:inception_upper":"1992-08-31",
    "iso:country":"GB",
    "wof:name":"WF7 5EG",
    "wof:placetype":"postalcode"
},
  "geometry": {"coordinates":[-1.359735,53.674829],"type":"Point"}
}