{
  "type": "Feature",
  "properties": {
    "iso:country": "GB",
    "wof:name": "NR10 3RR",
    "wof:placetype": "postalcode"
  },
  "geometry": {"coordinates":[1.236012,52.699798],"type":"Point"}
}
