{
  "type": "Feature",
  "properties": {
    "iso:country":"GB",
    "wof:name":"NR10 3RR",
    "wof:placetype":"postalcode"
},
  "geometry": {"coordinates":[1.2360114623601,52.69979752979629],"type":"Point"}
}