{
  "type": "Feature",
  "properties": {
    "iso:country":"GB",
    "wof:name":"SO31 6EF",
    "wof:placetype":"postalcode"
},
  "geometry": {"coordinates":[-1.28491412661382,50.86345761837644],"type":"Point"}
}