{
  "type": "Feature",
  "properties": {
    "iso:country":"GB",
    "wof:name":"SW16 2DP",
    "wof:placetype":"postalcode"
},
  "geometry": {"coordinates":[-0.1269864542098,51.43504984991537],"type":"Point"}
}