{
  "type": "Feature",
  "properties": {
    "iso:country":"GB",
    "wof:name":"LE15 6AH",
    "wof:placetype":"postalcode"
},
  "geometry": {"coordinates":[-0.72838781556897,52.66968794773815],"type":"Point"}
}