{
  "type": "Feature",
  "properties": {
    "date:inception_lower": "1980-01-01",
    "date:inception_upper": "1980-01-01",
    "iso:country": "GB",
    "wof:name": "WR2 6PH",
    "wof:placetype": "postalcode"
  },
  "geometry": {"coordinates":[-2.249809,52.211916],"type":"Point"}
}
