{
  "type": "Feature",
  "properties": {
    "iso:country":"GB",
    "wof:name":"WR2 6PH",
    "wof:placetype":"postalcode"
},
  "geometry": {"coordinates":[-2.24980902906392,52.21191632451902],"type":"Point"}
}