{
  "type": "Feature",
  "properties": {
    "iso:country": "GB",
    "wof:name": "OX18 3FT",
    "wof:placetype": "postalcode"
  },
  "geometry": {"coordinates":[-1.597,51.762198],"type":"Point"}
}
