{
  "type": "Feature",
  "properties": {
    "date:inception_lower": "1980-01-01",
    "date:inception_upper": "1980-01-01",
    "iso:country": "GB",
    "wof:name": "TD2 6SA",
    "wof:placetype": "postalcode"
  },
  "geometry": {"coordinates":[-2.714936,55.686067],"type":"Point"}
}
