{
  "type": "Feature",
  "properties": {
    "iso:country":"GB",
    "wof:name":"TD2 6SA",
    "wof:placetype":"postalcode"
},
  "geometry": {"coordinates":[-2.71492646483206,55.68582605816367],"type":"Point"}
}