{
  "type": "Feature",
  "properties": {
    "iso:country":"GB",
    "wof:name":"YO11 2BZ",
    "wof:placetype":"postalcode"
},
  "geometry": {"coordinates":[-0.40081868194781,54.27462923292423],"type":"Point"}
}