{
  "type": "Feature",
  "properties": {
    "iso:country":"GB",
    "wof:name":"CH7 4BY",
    "wof:placetype":"postalcode"
},
  "geometry": {"coordinates":[-3.19185011065403,53.11245283530457],"type":"Point"}
}