{
  "type": "Feature",
  "properties": {
    "iso:country": "GB",
    "wof:name": "LN11 8HT",
    "wof:placetype": "postalcode"
  },
  "geometry": {"coordinates":[0.078025,53.341483],"type":"Point"}
}
