{
  "type": "Feature",
  "properties": {
    "iso:country":"GB",
    "wof:name":"BN25 1BQ",
    "wof:placetype":"postalcode"
},
  "geometry": {"coordinates":[0.11126862259304,50.76593152753103],"type":"Point"}
}