{
  "type": "Feature",
  "properties": {
    "iso:country": "GB",
    "wof:name": "DY3 2BF",
    "wof:placetype": "postalcode"
  },
  "geometry": {"coordinates":[-2.122823,52.520209],"type":"Point"}
}
