{
  "type": "Feature",
  "properties": {
    "iso:country":"GB",
    "wof:name":"DY3 2BF",
    "wof:placetype":"postalcode"
},
  "geometry": {"coordinates":[-2.12282328965614,52.52020908260543],"type":"Point"}
}