{
  "type": "Feature",
  "properties": {
    "date:inception_lower":"1980-01-01",
    "date:inception_upper":"1980-01-31",
    "iso:country":"GB",
    "wof:name":"SY4 3RN",
    "wof:placetype":"postalcode"
},
  "geometry": {"coordinates":[-2.787382,52.810094],"type":"Point"}
}