{
  "type": "Feature",
  "properties": {
    "iso:country":"GB",
    "wof:name":"SY4 3RN",
    "wof:placetype":"postalcode"
},
  "geometry": {"coordinates":[-2.78738171483793,52.81009371825355],"type":"Point"}
}