{
  "type": "Feature",
  "properties": {
    "iso:country":"GB",
    "wof:name":"TQ3 3DD",
    "wof:placetype":"postalcode"
},
  "geometry": {"coordinates":[-3.5732295379261,50.43737431363439],"type":"Point"}
}