{
  "type": "Feature",
  "properties": {
    "iso:country":"GB",
    "wof:name":"M15 4NU",
    "wof:placetype":"postalcode"
},
  "geometry": {"coordinates":[-2.26092876605777,53.47328909649229],"type":"Point"}
}