{
  "type": "Feature",
  "properties": {
    "date:inception_lower": "2002-06-01",
    "date:inception_upper": "2002-06-01",
    "iso:country": "GB",
    "wof:name": "M15 4NU",
    "wof:placetype": "postalcode"
  },
  "geometry": {"coordinates":[-2.260929,53.473289],"type":"Point"}
}
