{
  "type": "Feature",
  "properties": {
    "iso:country": "GB",
    "wof:name": "M15 4NU",
    "wof:placetype": "postalcode"
  },
  "geometry": {"coordinates":[-2.260929,53.473289],"type":"Point"}
}
