{
  "type": "Feature",
  "properties": {
    "iso:country":"GB",
    "wof:name":"WV7 3EL",
    "wof:placetype":"postalcode"
},
  "geometry": {"coordinates":[-2.28385287745336,52.63770791829274],"type":"Point"}
}