{
  "type": "Feature",
  "properties": {
    "iso:country":"GB",
    "wof:name":"SO41 5SR",
    "wof:placetype":"postalcode"
},
  "geometry": {"coordinates":[-1.47277418818456,50.7790183613773],"type":"Point"}
}