{
  "type": "Feature",
  "properties": {
    "iso:country": "GB",
    "wof:name": "SO41 5SR",
    "wof:placetype": "postalcode"
  },
  "geometry": {"coordinates":[-1.472766,50.778919],"type":"Point"}
}
