{
  "type": "Feature",
  "properties": {
    "iso:country": "GB",
    "wof:name": "CB21 6DF",
    "wof:placetype": "postalcode"
  },
  "geometry": {"coordinates":[0.227087,52.112273],"type":"Point"}
}
