{
  "type": "Feature",
  "properties": {
    "iso:country": "GB",
    "wof:name": "IP23 7HY",
    "wof:placetype": "postalcode"
  },
  "geometry": {"coordinates":[1.151993,52.314985],"type":"Point"}
}
