{
  "type": "Feature",
  "properties": {
    "iso:country":"GB",
    "wof:name":"TN13 1AB",
    "wof:placetype":"postalcode"
},
  "geometry": {"coordinates":[0.18179879001954,51.27446010740638],"type":"Point"}
}