{
  "type": "Feature",
  "properties": {
    "date:inception_lower":"1999-12-01",
    "date:inception_upper":"1999-12-31",
    "iso:country":"GB",
    "wof:name":"TN13 1AB",
    "wof:placetype":"postalcode"
},
  "geometry": {"coordinates":[0.181799,51.27446],"type":"Point"}
}