{
  "type": "Feature",
  "properties": {
    "date:inception_lower": "1983-07-01",
    "date:inception_upper": "1983-07-01",
    "iso:country": "GB",
    "wof:name": "SY16 2PP",
    "wof:placetype": "postalcode"
  },
  "geometry": {"coordinates":[-3.315442,52.514704],"type":"Point"}
}
