{
  "type": "Feature",
  "properties": {
    "iso:country": "GB",
    "wof:name": "SY16 2PP",
    "wof:placetype": "postalcode"
  },
  "geometry": {"coordinates":[-3.315442,52.514704],"type":"Point"}
}
