{
  "type": "Feature",
  "properties": {
    "date:inception_lower": "2021-04-01",
    "date:inception_upper": "2021-04-01",
    "iso:country": "GB",
    "wof:name": "HP22 7DZ",
    "wof:placetype": "postalcode"
  },
  "geometry": {"coordinates":[-0.768702,51.823724],"type":"Point"}
}
