{
  "type": "Feature",
  "properties": {
    "iso:country":"GB",
    "wof:name":"TQ5 9AY",
    "wof:placetype":"postalcode"
},
  "geometry": {"coordinates":[-3.50052214908582,50.3981330233884],"type":"Point"}
}