{
  "type": "Feature",
  "properties": {
    "date:inception_lower":"1980-01-01",
    "date:inception_upper":"1980-01-31",
    "iso:country":"GB",
    "wof:name":"TQ5 9AY",
    "wof:placetype":"postalcode"
},
  "geometry": {"coordinates":[-3.500522,50.398133],"type":"Point"}
}