{
  "type": "Feature",
  "properties": {
    "iso:country":"GB",
    "wof:name":"LE12 6PZ",
    "wof:placetype":"postalcode"
},
  "geometry": {"coordinates":[-1.18687029719795,52.82827160932502],"type":"Point"}
}