{
  "type": "Feature",
  "properties": {
    "iso:country":"GB",
    "wof:name":"CF83 3DL",
    "wof:placetype":"postalcode"
},
  "geometry": {"coordinates":[-3.17291343213334,51.57941307575788],"type":"Point"}
}