{
  "type": "Feature",
  "properties": {
    "iso:country":"GB",
    "wof:name":"PE6 9RA",
    "wof:placetype":"postalcode"
},
  "geometry": {"coordinates":[-0.33301979257579,52.70146856208453],"type":"Point"}
}