{
  "type": "Feature",
  "properties": {
    "date:inception_lower": "1980-01-01",
    "date:inception_upper": "1980-01-01",
    "iso:country": "GB",
    "wof:name": "PE6 9RA",
    "wof:placetype": "postalcode"
  },
  "geometry": {"coordinates":[-0.33302,52.701469],"type":"Point"}
}
