{
  "type": "Feature",
  "properties": {
    "iso:country": "GB",
    "wof:name": "EX4 7AY",
    "wof:placetype": "postalcode"
  },
  "geometry": {"coordinates":[-3.513191,50.731044],"type":"Point"}
}
