{
  "type": "Feature",
  "properties": {
    "iso:country":"GB",
    "wof:name":"EX4 7AY",
    "wof:placetype":"postalcode"
},
  "geometry": {"coordinates":[-3.51319054859227,50.73104372081446],"type":"Point"}
}