{
  "type": "Feature",
  "properties": {
    "iso:country":"GB",
    "wof:name":"NE25 9LH",
    "wof:placetype":"postalcode"
},
  "geometry": {"coordinates":[-1.49958616453713,55.04474283721942],"type":"Point"}
}