{
  "type": "Feature",
  "properties": {
    "iso:country": "GB",
    "wof:name": "NE25 9LH",
    "wof:placetype": "postalcode"
  },
  "geometry": {"coordinates":[-1.499586,55.044743],"type":"Point"}
}
