{
  "type": "Feature",
  "properties": {
    "iso:country":"GB",
    "wof:name":"BN11 4TH",
    "wof:placetype":"postalcode"
},
  "geometry": {"coordinates":[-0.38274227849636,50.81157366178622],"type":"Point"}
}