{
  "type": "Feature",
  "properties": {
    "iso:country": "GB",
    "wof:name": "DD6 8NP",
    "wof:placetype": "postalcode"
  },
  "geometry": {"coordinates":[-2.956411,56.431479],"type":"Point"}
}
