{
  "type": "Feature",
  "properties": {
    "date:inception_lower":"1982-03-01",
    "date:inception_upper":"1982-03-31",
    "iso:country":"GB",
    "wof:name":"DD6 8NP",
    "wof:placetype":"postalcode"
},
  "geometry": {"coordinates":[-2.956411,56.431479],"type":"Point"}
}