{
  "type": "Feature",
  "properties": {
    "iso:country":"GB",
    "wof:name":"DD6 8NP",
    "wof:placetype":"postalcode"
},
  "geometry": {"coordinates":[-2.95641069961955,56.43147868233498],"type":"Point"}
}