{
  "type": "Feature",
  "properties": {
    "iso:country":"GB",
    "wof:name":"PE30 4QU",
    "wof:placetype":"postalcode"
},
  "geometry": {"coordinates":[0.43346494872669,52.75380462591773],"type":"Point"}
}