{
  "type": "Feature",
  "properties": {
    "iso:country":"GB",
    "wof:name":"ST3 3AG",
    "wof:placetype":"postalcode"
},
  "geometry": {"coordinates":[-2.15217831252444,52.97801296751697],"type":"Point"}
}