{
  "type": "Feature",
  "properties": {
    "iso:country":"GB",
    "wof:name":"B11 4DA",
    "wof:placetype":"postalcode"
},
  "geometry": {"coordinates":[-1.85852876145807,52.44396296739198],"type":"Point"}
}