{
  "type": "Feature",
  "properties": {
    "iso:country":"GB",
    "wof:name":"GU33 7BE",
    "wof:placetype":"postalcode"
},
  "geometry": {"coordinates":[-0.88483267800948,51.04787235263741],"type":"Point"}
}