{
  "type": "Feature",
  "properties": {
    "date:inception_lower": "1997-06-01",
    "date:inception_upper": "1997-06-01",
    "iso:country": "GB",
    "wof:name": "S21 4FQ",
    "wof:placetype": "postalcode"
  },
  "geometry": {"coordinates":[-1.370378,53.306156],"type":"Point"}
}
