{
  "type": "Feature",
  "properties": {
    "iso:country":"GB",
    "wof:name":"S21 4FQ",
    "wof:placetype":"postalcode"
},
  "geometry": {"coordinates":[-1.37037844335925,53.30615614576161],"type":"Point"}
}