{
  "type": "Feature",
  "properties": {
    "iso:country": "GB",
    "wof:name": "SE1 1PA",
    "wof:placetype": "postalcode"
  },
  "geometry": {"coordinates":[-0.097474,51.500221],"type":"Point"}
}
