{
  "type": "Feature",
  "properties": {
    "iso:country": "GB",
    "wof:name": "E18 1BH",
    "wof:placetype": "postalcode"
  },
  "geometry": {"coordinates":[0.026892,51.588369],"type":"Point"}
}
