{
  "type": "Feature",
  "properties": {
    "iso:country":"GB",
    "wof:name":"E18 1BH",
    "wof:placetype":"postalcode"
},
  "geometry": {"coordinates":[0.02689183631873,51.58836946741479],"type":"Point"}
}