{
  "type": "Feature",
  "properties": {
    "iso:country":"GB",
    "wof:name":"B31 4QU",
    "wof:placetype":"postalcode"
},
  "geometry": {"coordinates":[-1.97831145608581,52.38969144862054],"type":"Point"}
}