{
  "type": "Feature",
  "properties": {
    "iso:country":"GB",
    "wof:name":"GU34 2DP",
    "wof:placetype":"postalcode"
},
  "geometry": {"coordinates":[-0.97053160842861,51.15513729553636],"type":"Point"}
}