{
  "type": "Feature",
  "properties": {
    "date:inception_lower": "1980-01-01",
    "date:inception_upper": "1980-01-01",
    "iso:country": "GB",
    "wof:name": "GU34 2DP",
    "wof:placetype": "postalcode"
  },
  "geometry": {"coordinates":[-0.970532,51.155137],"type":"Point"}
}
