{
  "type": "Feature",
  "properties": {
    "iso:country":"GB",
    "wof:name":"S21 1SP",
    "wof:placetype":"postalcode"
},
  "geometry": {"coordinates":[-1.3253734236945,53.32037330311304],"type":"Point"}
}