{
  "type": "Feature",
  "properties": {
    "iso:country": "GB",
    "wof:name": "LL18 5FP",
    "wof:placetype": "postalcode"
  },
  "geometry": {"coordinates":[-3.514453,53.303304],"type":"Point"}
}
