{
  "type": "Feature",
  "properties": {
    "date:inception_lower": "1998-12-01",
    "date:inception_upper": "1998-12-01",
    "iso:country": "GB",
    "wof:name": "LL18 5FP",
    "wof:placetype": "postalcode"
  },
  "geometry": {"coordinates":[-3.514453,53.303304],"type":"Point"}
}
