{
  "type": "Feature",
  "properties": {
    "iso:country":"GB",
    "wof:name":"LL18 5FP",
    "wof:placetype":"postalcode"
},
  "geometry": {"coordinates":[-3.51443527533153,53.30326895398117],"type":"Point"}
}