{
  "type": "Feature",
  "properties": {
    "iso:country":"GB",
    "wof:name":"BL4 0QT",
    "wof:placetype":"postalcode"
},
  "geometry": {"coordinates":[-2.42741247232882,53.54442037328738],"type":"Point"}
}