{
  "type": "Feature",
  "properties": {
    "iso:country": "GB",
    "wof:name": "BL4 0QT",
    "wof:placetype": "postalcode"
  },
  "geometry": {"coordinates":[-2.427412,53.54442],"type":"Point"}
}
