{
  "type": "Feature",
  "properties": {
    "iso:country": "GB",
    "wof:name": "NP44 6EH",
    "wof:placetype": "postalcode"
  },
  "geometry": {"coordinates":[-3.054269,51.635487],"type":"Point"}
}
