{
  "type": "Feature",
  "properties": {
    "date:inception_lower":"1980-01-01",
    "date:inception_upper":"1980-01-31",
    "iso:country":"GB",
    "wof:name":"KA1 2NB",
    "wof:placetype":"postalcode"
},
  "geometry": {"coordinates":[-4.513975,55.612819],"type":"Point"}
}