{
  "type": "Feature",
  "properties": {
    "iso:country":"GB",
    "wof:name":"KA1 2NB",
    "wof:placetype":"postalcode"
},
  "geometry": {"coordinates":[-4.51397477453922,55.61281916252403],"type":"Point"}
}