{
  "type": "Feature",
  "properties": {
    "date:inception_lower": "1980-01-01",
    "date:inception_upper": "1980-01-01",
    "iso:country": "GB",
    "wof:name": "PR1 2EP",
    "wof:placetype": "postalcode"
  },
  "geometry": {"coordinates":[-2.701054,53.760349],"type":"Point"}
}
