{
  "type": "Feature",
  "properties": {
    "iso:country":"GB",
    "wof:name":"PR1 2EP",
    "wof:placetype":"postalcode"
},
  "geometry": {"coordinates":[-2.70096626947869,53.7603423711756],"type":"Point"}
}