{
  "type": "Feature",
  "properties": {
    "iso:country":"GB",
    "wof:name":"HX2 8TS",
    "wof:placetype":"postalcode"
},
  "geometry": {"coordinates":[-1.89392861702658,53.73958883236711],"type":"Point"}
}