{
  "type": "Feature",
  "properties": {
    "iso:country": "GB",
    "wof:name": "HX2 8TS",
    "wof:placetype": "postalcode"
  },
  "geometry": {"coordinates":[-1.893929,53.739589],"type":"Point"}
}
