{
  "type": "Feature",
  "properties": {
    "date:inception_lower": "2011-05-01",
    "date:inception_upper": "2011-05-01",
    "iso:country": "GB",
    "wof:name": "ML11 9ZL",
    "wof:placetype": "postalcode"
  },
  "geometry": {"coordinates":[-3.925519,55.678618],"type":"Point"}
}
