{
  "type": "Feature",
  "properties": {
    "iso:country":"GB",
    "wof:name":"ML11 9ZL",
    "wof:placetype":"postalcode"
},
  "geometry": {"coordinates":[-3.92551864637248,55.67861800750352],"type":"Point"}
}