{
  "type": "Feature",
  "properties": {
    "date:inception_lower": "2023-04-01",
    "date:inception_upper": "2023-04-01",
    "iso:country": "GB",
    "wof:name": "PA75 6AP",
    "wof:placetype": "postalcode"
  },
  "geometry": {"coordinates":[-6.066901,56.61616],"type":"Point"}
}
