{
  "type": "Feature",
  "properties": {
    "iso:country":"GB",
    "wof:name":"PO18 8LW",
    "wof:placetype":"postalcode"
},
  "geometry": {"coordinates":[-0.85901686888391,50.83243702568519],"type":"Point"}
}