{
  "type": "Feature",
  "properties": {
    "date:inception_lower": "2006-07-01",
    "date:inception_upper": "2006-07-01",
    "iso:country": "GB",
    "wof:name": "PO18 8LW",
    "wof:placetype": "postalcode"
  },
  "geometry": {"coordinates":[-0.859017,50.832437],"type":"Point"}
}
