{
  "type": "Feature",
  "properties": {
    "iso:country":"GB",
    "wof:name":"RH20 4RQ",
    "wof:placetype":"postalcode"
},
  "geometry": {"coordinates":[-0.4598751864291,50.9219734799495],"type":"Point"}
}