{
  "type": "Feature",
  "properties": {
    "date:inception_lower": "1980-01-01",
    "date:inception_upper": "1980-01-01",
    "iso:country": "GB",
    "wof:name": "BD16 1QB",
    "wof:placetype": "postalcode"
  },
  "geometry": {"coordinates":[-1.823521,53.830509],"type":"Point"}
}
