{
  "type": "Feature",
  "properties": {
    "iso:country":"GB",
    "wof:name":"LL18 3UG",
    "wof:placetype":"postalcode"
},
  "geometry": {"coordinates":[-3.46738409660097,53.32810198343791],"type":"Point"}
}