{
  "type": "Feature",
  "properties": {
    "iso:country":"GB",
    "wof:name":"HR1 1DS",
    "wof:placetype":"postalcode"
},
  "geometry": {"coordinates":[-2.70198895333835,52.06719460179799],"type":"Point"}
}