{
  "type": "Feature",
  "properties": {
    "iso:country":"GB",
    "wof:name":"S5 7LS",
    "wof:placetype":"postalcode"
},
  "geometry": {"coordinates":[-1.4750366416934,53.41505741344334],"type":"Point"}
}