{
  "type": "Feature",
  "properties": {
    "iso:country": "GB",
    "wof:name": "PE19 6HZ",
    "wof:placetype": "postalcode"
  },
  "geometry": {"coordinates":[-0.255704,52.250193],"type":"Point"}
}
