{
  "type": "Feature",
  "properties": {
    "date:inception_lower":"2004-03-01",
    "date:inception_upper":"2004-03-31",
    "iso:country":"GB",
    "wof:name":"PE19 6HZ",
    "wof:placetype":"postalcode"
},
  "geometry": {"coordinates":[-0.255704,52.250193],"type":"Point"}
}