{
  "type": "Feature",
  "properties": {
    "iso:country":"GB",
    "wof:name":"PE19 6HZ",
    "wof:placetype":"postalcode"
},
  "geometry": {"coordinates":[-0.25570402142758,52.25019297102429],"type":"Point"}
}