{
  "type": "Feature",
  "properties": {
    "iso:country": "GB",
    "wof:name": "TA6 3BU",
    "wof:placetype": "postalcode"
  },
  "geometry": {"coordinates":[-3.003515,51.128085],"type":"Point"}
}
