{
  "type": "Feature",
  "properties": {
    "iso:country":"GB",
    "wof:name":"WV14 6EG",
    "wof:placetype":"postalcode"
},
  "geometry": {"coordinates":[-2.08744256800603,52.57406286701053],"type":"Point"}
}