{
  "type": "Feature",
  "properties": {
    "date:inception_lower":"1980-01-01",
    "date:inception_upper":"1980-01-31",
    "iso:country":"GB",
    "wof:name":"DA15 9HN",
    "wof:placetype":"postalcode"
},
  "geometry": {"coordinates":[0.106057,51.446139],"type":"Point"}
}