{
  "type": "Feature",
  "properties": {
    "iso:country":"GB",
    "wof:name":"CO16 7EJ",
    "wof:placetype":"postalcode"
},
  "geometry": {"coordinates":[1.12124097343791,51.79991517021256],"type":"Point"}
}