{
  "type": "Feature",
  "properties": {
    "iso:country": "GB",
    "wof:name": "PL6 6FR",
    "wof:placetype": "postalcode"
  },
  "geometry": {"coordinates":[-4.150064,50.426744],"type":"Point"}
}
