{
  "type": "Feature",
  "properties": {
    "iso:country":"GB",
    "wof:name":"HA7 2AL",
    "wof:placetype":"postalcode"
},
  "geometry": {"coordinates":[-0.3211240968613,51.60253225237981],"type":"Point"}
}