{
  "type": "Feature",
  "properties": {
    "iso:country":"GB",
    "wof:name":"CM23 5DD",
    "wof:placetype":"postalcode"
},
  "geometry": {"coordinates":[0.18034891376295,51.87959612438406],"type":"Point"}
}