{
  "type": "Feature",
  "properties": {
    "date:inception_lower": "2003-11-01",
    "date:inception_upper": "2003-11-01",
    "iso:country": "GB",
    "wof:name": "CM23 5DD",
    "wof:placetype": "postalcode"
  },
  "geometry": {"coordinates":[0.180349,51.879596],"type":"Point"}
}
