{
  "type": "Feature",
  "properties": {
    "iso:country":"GB",
    "wof:name":"PE12 8PE",
    "wof:placetype":"postalcode"
},
  "geometry": {"coordinates":[0.03482120336244,52.79976957428993],"type":"Point"}
}