{
  "type": "Feature",
  "properties": {
    "iso:country":"GB",
    "wof:name":"DN22 6EA",
    "wof:placetype":"postalcode"
},
  "geometry": {"coordinates":[-0.94088830357944,53.32124799424403],"type":"Point"}
}