{
  "type": "Feature",
  "properties": {
    "iso:country": "GB",
    "wof:name": "IP25 6UZ",
    "wof:placetype": "postalcode"
  },
  "geometry": {"coordinates":[0.841751,52.570233],"type":"Point"}
}
