{
  "type": "Feature",
  "properties": {
    "iso:country":"GB",
    "wof:name":"IP25 6UZ",
    "wof:placetype":"postalcode"
},
  "geometry": {"coordinates":[0.84174311255122,52.56997667430063],"type":"Point"}
}