{
  "type": "Feature",
  "properties": {
    "iso:country": "GB",
    "wof:name": "WS10 9JX",
    "wof:placetype": "postalcode"
  },
  "geometry": {"coordinates":[-2.027782,52.568572],"type":"Point"}
}
