{
  "type": "Feature",
  "properties": {
    "iso:country": "GB",
    "wof:name": "YO26 5QL",
    "wof:placetype": "postalcode"
  },
  "geometry": {"coordinates":[-1.1385,53.960203],"type":"Point"}
}
