{
  "type": "Feature",
  "properties": {
    "iso:country":"GB",
    "wof:name":"WA3 2SB",
    "wof:placetype":"postalcode"
},
  "geometry": {"coordinates":[-2.58237291762116,53.47444632507838],"type":"Point"}
}