{
  "type": "Feature",
  "properties": {
    "iso:country":"GB",
    "wof:name":"YO8 3UU",
    "wof:placetype":"postalcode"
},
  "geometry": {"coordinates":[-1.10229891089767,53.81363799163675],"type":"Point"}
}