{
  "type": "Feature",
  "properties": {
    "date:inception_lower": "1980-01-01",
    "date:inception_upper": "1980-01-01",
    "iso:country": "GB",
    "wof:name": "BL3 2AG",
    "wof:placetype": "postalcode"
  },
  "geometry": {"coordinates":[-2.423143,53.56723],"type":"Point"}
}
