{
  "type": "Feature",
  "properties": {
    "date:inception_lower": "2008-06-01",
    "date:inception_upper": "2008-06-01",
    "iso:country": "GB",
    "wof:name": "S1 4BZ",
    "wof:placetype": "postalcode"
  },
  "geometry": {"coordinates":[-1.477121,53.384919],"type":"Point"}
}
