{
  "type": "Feature",
  "properties": {
    "iso:country":"GB",
    "wof:name":"LU6 2EP",
    "wof:placetype":"postalcode"
},
  "geometry": {"coordinates":[-0.59103554077291,51.86183394082648],"type":"Point"}
}