{
  "type": "Feature",
  "properties": {
    "iso:country":"GB",
    "wof:name":"BS10 6QW",
    "wof:placetype":"postalcode"
},
  "geometry": {"coordinates":[-2.60831563164167,51.51220717304352],"type":"Point"}
}