{
  "type": "Feature",
  "properties": {
    "iso:country": "GB",
    "wof:name": "N6 4LS",
    "wof:placetype": "postalcode"
  },
  "geometry": {"coordinates":[-0.157099,51.582536],"type":"Point"}
}
