{
  "type": "Feature",
  "properties": {
    "date:inception_lower": "1980-01-01",
    "date:inception_upper": "1980-01-01",
    "iso:country": "GB",
    "wof:name": "KT22 8AY",
    "wof:placetype": "postalcode"
  },
  "geometry": {"coordinates":[-0.326224,51.294301],"type":"Point"}
}
