{
  "type": "Feature",
  "properties": {
    "iso:country":"GB",
    "wof:name":"SS2 5SD",
    "wof:placetype":"postalcode"
},
  "geometry": {"coordinates":[0.7131735115791,51.54029412890562],"type":"Point"}
}