{
  "type": "Feature",
  "properties": {
    "iso:country":"GB",
    "wof:name":"TA6 5YS",
    "wof:placetype":"postalcode"
},
  "geometry": {"coordinates":[-2.99387263211984,51.12161150961195],"type":"Point"}
}