{
  "type": "Feature",
  "properties": {
    "iso:country":"GB",
    "wof:name":"B1 1DD",
    "wof:placetype":"postalcode"
},
  "geometry": {"coordinates":[-1.89918376251521,52.47385129596238],"type":"Point"}
}