{
  "type": "Feature",
  "properties": {
    "date:inception_lower": "1980-01-01",
    "date:inception_upper": "1980-01-01",
    "iso:country": "GB",
    "wof:name": "B1 1DD",
    "wof:placetype": "postalcode"
  },
  "geometry": {"coordinates":[-1.899184,52.473851],"type":"Point"}
}
