{
  "type": "Feature",
  "properties": {
    "iso:country":"GB",
    "wof:name":"FK8 3HD",
    "wof:placetype":"postalcode"
},
  "geometry": {"coordinates":[-4.23538390536273,56.12637225570582],"type":"Point"}
}