{
  "type": "Feature",
  "properties": {
    "date:inception_lower": "2022-08-01",
    "date:inception_upper": "2022-08-01",
    "iso:country": "GB",
    "wof:name": "EN8 9GA",
    "wof:placetype": "postalcode"
  },
  "geometry": {"coordinates":[-0.024048,51.705236],"type":"Point"}
}
