{
  "type": "Feature",
  "properties": {
    "iso:country":"GB",
    "wof:name":"TW14 9NB",
    "wof:placetype":"postalcode"
},
  "geometry": {"coordinates":[-0.41508519181397,51.44889393974699],"type":"Point"}
}