{
  "type": "Feature",
  "properties": {
    "iso:country": "GB",
    "wof:name": "TW14 9NB",
    "wof:placetype": "postalcode"
  },
  "geometry": {"coordinates":[-0.415085,51.448894],"type":"Point"}
}
