{
  "type": "Feature",
  "properties": {
    "iso:country":"GB",
    "wof:name":"LE17 4NQ",
    "wof:placetype":"postalcode"
},
  "geometry": {"coordinates":[-1.19906391117571,52.46040533958536],"type":"Point"}
}