{
  "type": "Feature",
  "properties": {
    "iso:country":"GB",
    "wof:name":"TS12 2TW",
    "wof:placetype":"postalcode"
},
  "geometry": {"coordinates":[-0.94166048680179,54.56531250391841],"type":"Point"}
}