{
  "type": "Feature",
  "properties": {
    "iso:country":"GB",
    "wof:name":"SW9 0RR",
    "wof:placetype":"postalcode"
},
  "geometry": {"coordinates":[-0.11618269006716,51.47557728565975],"type":"Point"}
}