{
  "type": "Feature",
  "properties": {
    "iso:country":"GB",
    "wof:name":"NN4 8GS",
    "wof:placetype":"postalcode"
},
  "geometry": {"coordinates":[-0.89229911896281,52.23112539954369],"type":"Point"}
}