{
  "type": "Feature",
  "properties": {
    "iso:country":"GB",
    "wof:name":"HA4 0HH",
    "wof:placetype":"postalcode"
},
  "geometry": {"coordinates":[-0.39687408549536,51.55705688172359],"type":"Point"}
}