{
  "type": "Feature",
  "properties": {
    "date:inception_lower":"2000-12-01",
    "date:inception_upper":"2000-12-31",
    "iso:country":"GB",
    "wof:name":"HA4 0HH",
    "wof:placetype":"postalcode"
},
  "geometry": {"coordinates":[-0.396874,51.557057],"type":"Point"}
}