{
  "type": "Feature",
  "properties": {
    "iso:country":"GB",
    "wof:name":"NR11 6NF",
    "wof:placetype":"postalcode"
},
  "geometry": {"coordinates":[1.22855383664489,52.81061027932778],"type":"Point"}
}