{
  "type": "Feature",
  "properties": {
    "iso:country":"GB",
    "wof:name":"SN8 3DZ",
    "wof:placetype":"postalcode"
},
  "geometry": {"coordinates":[-1.65218785322327,51.28735563598628],"type":"Point"}
}