{
  "type": "Feature",
  "properties": {
    "iso:country":"GB",
    "wof:name":"SY14 8DE",
    "wof:placetype":"postalcode"
},
  "geometry": {"coordinates":[-2.75896026278216,53.02289872645486],"type":"Point"}
}