{
  "type": "Feature",
  "properties": {
    "iso:country":"GB",
    "wof:name":"DN15 9PF",
    "wof:placetype":"postalcode"
},
  "geometry": {"coordinates":[-0.58947394178243,53.68926951211046],"type":"Point"}
}