{
  "type": "Feature",
  "properties": {
    "iso:country":"GB",
    "wof:name":"EX4 1BX",
    "wof:placetype":"postalcode"
},
  "geometry": {"coordinates":[-3.54382940673393,50.7190765475039],"type":"Point"}
}