{
  "type": "Feature",
  "properties": {
    "iso:country": "GB",
    "wof:name": "KY14 7BF",
    "wof:placetype": "postalcode"
  },
  "geometry": {"coordinates":[-3.224804,56.293932],"type":"Point"}
}
