{
  "type": "Feature",
  "properties": {
    "date:inception_lower": "1992-10-01",
    "date:inception_upper": "1992-10-01",
    "iso:country": "GB",
    "wof:name": "KY14 7BF",
    "wof:placetype": "postalcode"
  },
  "geometry": {"coordinates":[-3.224804,56.293932],"type":"Point"}
}
