{
  "type": "Feature",
  "properties": {
    "iso:country":"GB",
    "wof:name":"LA23 3HZ",
    "wof:placetype":"postalcode"
},
  "geometry": {"coordinates":[-2.91364433879859,54.35390995683284],"type":"Point"}
}