{
  "type": "Feature",
  "properties": {
    "iso:country": "GB",
    "wof:name": "LA23 3HZ",
    "wof:placetype": "postalcode"
  },
  "geometry": {"coordinates":[-2.913644,54.35391],"type":"Point"}
}
