{
  "type": "Feature",
  "properties": {
    "date:inception_lower": "1980-01-01",
    "date:inception_upper": "1980-01-01",
    "iso:country": "GB",
    "wof:name": "LA23 3HZ",
    "wof:placetype": "postalcode"
  },
  "geometry": {"coordinates":[-2.913644,54.35391],"type":"Point"}
}
