{
  "type": "Feature",
  "properties": {
    "iso:country": "GB",
    "wof:name": "NR29 4FG",
    "wof:placetype": "postalcode"
  },
  "geometry": {"coordinates":[1.633076,52.708907],"type":"Point"}
}
