{
  "type": "Feature",
  "properties": {
    "date:inception_lower": "2016-05-01",
    "date:inception_upper": "2016-05-01",
    "iso:country": "GB",
    "wof:name": "NR29 4FG",
    "wof:placetype": "postalcode"
  },
  "geometry": {"coordinates":[1.633076,52.708907],"type":"Point"}
}
