{
  "type": "Feature",
  "properties": {
    "date:inception_lower": "1980-01-01",
    "date:inception_upper": "1980-01-01",
    "iso:country": "GB",
    "wof:name": "SY16 3LE",
    "wof:placetype": "postalcode"
  },
  "geometry": {"coordinates":[-3.320498,52.544628],"type":"Point"}
}
