{
  "type": "Feature",
  "properties": {
    "iso:country":"GB",
    "wof:name":"SY16 3LE",
    "wof:placetype":"postalcode"
},
  "geometry": {"coordinates":[-3.30597825883554,52.54243628674563],"type":"Point"}
}