{
  "type": "Feature",
  "properties": {
    "iso:country": "GB",
    "wof:name": "M29 7SF",
    "wof:placetype": "postalcode"
  },
  "geometry": {"coordinates":[-2.45866,53.496441],"type":"Point"}
}
