{
  "type": "Feature",
  "properties": {
    "iso:country":"GB",
    "wof:name":"B43 6LN",
    "wof:placetype":"postalcode"
},
  "geometry": {"coordinates":[-1.93622181920732,52.54721668362516],"type":"Point"}
}