{
  "type": "Feature",
  "properties": {
    "iso:country":"GB",
    "wof:name":"SL4 4YT",
    "wof:placetype":"postalcode"
},
  "geometry": {"coordinates":[-0.65174992671924,51.47224825333299],"type":"Point"}
}