{
  "type": "Feature",
  "properties": {
    "iso:country":"GB",
    "wof:name":"BR1 4NW",
    "wof:placetype":"postalcode"
},
  "geometry": {"coordinates":[0.00442526468686,51.42049311744865],"type":"Point"}
}