{
  "type": "Feature",
  "properties": {
    "iso:country": "GB",
    "wof:name": "DN4 5NG",
    "wof:placetype": "postalcode"
  },
  "geometry": {"coordinates":[-1.120643,53.512114],"type":"Point"}
}
