{
  "type": "Feature",
  "properties": {
    "iso:country":"GB",
    "wof:name":"TN24 8HY",
    "wof:placetype":"postalcode"
},
  "geometry": {"coordinates":[0.87016807348403,51.15530221026241],"type":"Point"}
}