{
  "type": "Feature",
  "properties": {
    "date:inception_lower": "1980-01-01",
    "date:inception_upper": "1980-01-01",
    "iso:country": "GB",
    "wof:name": "TQ3 3RJ",
    "wof:placetype": "postalcode"
  },
  "geometry": {"coordinates":[-3.575158,50.431835],"type":"Point"}
}
