{
  "type": "Feature",
  "properties": {
    "iso:country": "GB",
    "wof:name": "TQ3 3RJ",
    "wof:placetype": "postalcode"
  },
  "geometry": {"coordinates":[-3.575158,50.431835],"type":"Point"}
}
