{
  "type": "Feature",
  "properties": {
    "iso:country":"GB",
    "wof:name":"TQ3 3RJ",
    "wof:placetype":"postalcode"
},
  "geometry": {"coordinates":[-3.57515797176229,50.43183504528645],"type":"Point"}
}