{
  "type": "Feature",
  "properties": {
    "iso:country": "GB",
    "wof:name": "SO16 4NB",
    "wof:placetype": "postalcode"
  },
  "geometry": {"coordinates":[-1.449589,50.925948],"type":"Point"}
}
