{
  "type": "Feature",
  "properties": {
    "iso:country":"GB",
    "wof:name":"SO16 4NB",
    "wof:placetype":"postalcode"
},
  "geometry": {"coordinates":[-1.44958862387581,50.92594848889831],"type":"Point"}
}