{
  "type": "Feature",
  "properties": {
    "date:inception_lower": "1980-01-01",
    "date:inception_upper": "1980-01-01",
    "iso:country": "GB",
    "wof:name": "CT9 2JR",
    "wof:placetype": "postalcode"
  },
  "geometry": {"coordinates":[1.402694,51.389477],"type":"Point"}
}
