{
  "type": "Feature",
  "properties": {
    "iso:country":"GB",
    "wof:name":"CT9 2JR",
    "wof:placetype":"postalcode"
},
  "geometry": {"coordinates":[1.4026942270465,51.3894773989112],"type":"Point"}
}