{
  "type": "Feature",
  "properties": {
    "iso:country": "GB",
    "wof:name": "WV6 7NU",
    "wof:placetype": "postalcode"
  },
  "geometry": {"coordinates":[-2.20209,52.598905],"type":"Point"}
}
