{
  "type": "Feature",
  "properties": {
    "iso:country": "GB",
    "wof:name": "OX12 7JY",
    "wof:placetype": "postalcode"
  },
  "geometry": {"coordinates":[-1.422112,51.608707],"type":"Point"}
}
