{
  "type": "Feature",
  "properties": {
    "iso:country": "GB",
    "wof:name": "NG8 2DY",
    "wof:placetype": "postalcode"
  },
  "geometry": {"coordinates":[-1.226939,52.955562],"type":"Point"}
}
