{
  "type": "Feature",
  "properties": {
    "iso:country":"GB",
    "wof:name":"NG8 2DY",
    "wof:placetype":"postalcode"
},
  "geometry": {"coordinates":[-1.22693882579801,52.95556156694646],"type":"Point"}
}