{
  "type": "Feature",
  "properties": {
    "date:inception_lower": "1994-05-01",
    "date:inception_upper": "1994-05-01",
    "iso:country": "GB",
    "wof:name": "M16 0WJ",
    "wof:placetype": "postalcode"
  },
  "geometry": {"coordinates":[-2.276915,53.459582],"type":"Point"}
}
