{
  "type": "Feature",
  "properties": {
    "iso:country":"GB",
    "wof:name":"BR7 6RG",
    "wof:placetype":"postalcode"
},
  "geometry": {"coordinates":[0.09738493649931,51.39820946699734],"type":"Point"}
}