{
  "type": "Feature",
  "properties": {
    "iso:country": "GB",
    "wof:name": "RG2 0EL",
    "wof:placetype": "postalcode"
  },
  "geometry": {"coordinates":[-0.9655,51.442005],"type":"Point"}
}
