{
  "type": "Feature",
  "properties": {
    "iso:country":"GB",
    "wof:name":"RG2 0EL",
    "wof:placetype":"postalcode"
},
  "geometry": {"coordinates":[-0.96552060938694,51.44200380342261],"type":"Point"}
}