{
  "type": "Feature",
  "properties": {
    "date:inception_lower": "2017-12-01",
    "date:inception_upper": "2017-12-01",
    "iso:country": "GB",
    "wof:name": "SG18 8TW",
    "wof:placetype": "postalcode"
  },
  "geometry": {"coordinates":[-0.24317,52.094286],"type":"Point"}
}
