{
  "type": "Feature",
  "properties": {
    "date:inception_lower":"1980-01-01",
    "date:inception_upper":"1980-01-31",
    "iso:country":"GB",
    "wof:name":"IG8 7LP",
    "wof:placetype":"postalcode"
},
  "geometry": {"coordinates":[0.044677,51.604751],"type":"Point"}
}