{
  "type": "Feature",
  "properties": {
    "iso:country": "GB",
    "wof:name": "CF3 5ST",
    "wof:placetype": "postalcode"
  },
  "geometry": {"coordinates":[-3.112122,51.523295],"type":"Point"}
}
