{
  "type": "Feature",
  "properties": {
    "iso:country": "GB",
    "wof:name": "EX22 7AS",
    "wof:placetype": "postalcode"
  },
  "geometry": {"coordinates":[-4.261196,50.864741],"type":"Point"}
}
