{
  "type": "Feature",
  "properties": {
    "date:inception_lower":"1980-01-01",
    "date:inception_upper":"1980-01-31",
    "iso:country":"GB",
    "wof:name":"CR0 1ST",
    "wof:placetype":"postalcode"
},
  "geometry": {"coordinates":[-0.100524,51.369553],"type":"Point"}
}