{
  "type": "Feature",
  "properties": {
    "iso:country":"GB",
    "wof:name":"CR0 1ST",
    "wof:placetype":"postalcode"
},
  "geometry": {"coordinates":[-0.10052437853657,51.36955278851503],"type":"Point"}
}