{
  "type": "Feature",
  "properties": {
    "iso:country":"GB",
    "wof:name":"CF23 8LE",
    "wof:placetype":"postalcode"
},
  "geometry": {"coordinates":[-3.14523233405775,51.53460172694788],"type":"Point"}
}