{
  "type": "Feature",
  "properties": {
    "iso:country": "GB",
    "wof:name": "CF23 8LE",
    "wof:placetype": "postalcode"
  },
  "geometry": {"coordinates":[-3.145232,51.534602],"type":"Point"}
}
