{
  "type": "Feature",
  "properties": {
    "iso:country": "GB",
    "wof:name": "SA10 8NS",
    "wof:placetype": "postalcode"
  },
  "geometry": {"coordinates":[-3.746959,51.732772],"type":"Point"}
}
