{
  "type": "Feature",
  "properties": {
    "iso:country":"GB",
    "wof:name":"SA10 8NS",
    "wof:placetype":"postalcode"
},
  "geometry": {"coordinates":[-3.74695948531218,51.73277151801745],"type":"Point"}
}