{
  "type": "Feature",
  "properties": {
    "iso:country": "GB",
    "wof:name": "HD2 1UF",
    "wof:placetype": "postalcode"
  },
  "geometry": {"coordinates":[-1.748834,53.6718],"type":"Point"}
}
