{
  "type": "Feature",
  "properties": {
    "iso:country":"GB",
    "wof:name":"SW1P 2DW",
    "wof:placetype":"postalcode"
},
  "geometry": {"coordinates":[-0.13200391701909,51.49718772311553],"type":"Point"}
}