{
  "type": "Feature",
  "properties": {
    "date:inception_lower": "1980-01-01",
    "date:inception_upper": "1980-01-01",
    "iso:country": "GB",
    "wof:name": "SW1P 2DW",
    "wof:placetype": "postalcode"
  },
  "geometry": {"coordinates":[-0.132004,51.497188],"type":"Point"}
}
