{
  "type": "Feature",
  "properties": {
    "date:inception_lower":"1980-01-01",
    "date:inception_upper":"1980-01-31",
    "iso:country":"GB",
    "wof:name":"CV34 5TW",
    "wof:placetype":"postalcode"
},
  "geometry": {"coordinates":[-1.578788,52.293303],"type":"Point"}
}