{
  "type": "Feature",
  "properties": {
    "iso:country":"GB",
    "wof:name":"CV35 8UE",
    "wof:placetype":"postalcode"
},
  "geometry": {"coordinates":[-1.61680112756312,52.28345596558999],"type":"Point"}
}