{
  "type": "Feature",
  "properties": {
    "date:inception_lower": "1980-01-01",
    "date:inception_upper": "1980-01-01",
    "iso:country": "GB",
    "wof:name": "SN5 0AG",
    "wof:placetype": "postalcode"
  },
  "geometry": {"coordinates":[-1.938751,51.588929],"type":"Point"}
}
