{
  "type": "Feature",
  "properties": {
    "iso:country":"GB",
    "wof:name":"SN5 0AG",
    "wof:placetype":"postalcode"
},
  "geometry": {"coordinates":[-1.93875058850997,51.58892890470874],"type":"Point"}
}