{
  "type": "Feature",
  "properties": {
    "iso:country": "GB",
    "wof:name": "GU35 0RU",
    "wof:placetype": "postalcode"
  },
  "geometry": {"coordinates":[-0.849874,51.118403],"type":"Point"}
}
