{
  "type": "Feature",
  "properties": {
    "iso:country":"GB",
    "wof:name":"NG7 6LY",
    "wof:placetype":"postalcode"
},
  "geometry": {"coordinates":[-1.15861959711142,52.97063156313788],"type":"Point"}
}