{
  "type": "Feature",
  "properties": {
    "iso:country": "GB",
    "wof:name": "NG5 6ET",
    "wof:placetype": "postalcode"
  },
  "geometry": {"coordinates":[-1.141067,52.995227],"type":"Point"}
}
