{
  "type": "Feature",
  "properties": {
    "iso:country":"GB",
    "wof:name":"NG5 6ET",
    "wof:placetype":"postalcode"
},
  "geometry": {"coordinates":[-1.14106726297128,52.99522710877652],"type":"Point"}
}