{
  "type": "Feature",
  "properties": {
    "iso:country": "GB",
    "wof:name": "DL17 0GZ",
    "wof:placetype": "postalcode"
  },
  "geometry": {"coordinates":[-1.559214,54.656696],"type":"Point"}
}
