{
  "type": "Feature",
  "properties": {
    "iso:country":"GB",
    "wof:name":"HU3 2TG",
    "wof:placetype":"postalcode"
},
  "geometry": {"coordinates":[-0.36589614210472,53.74174738802618],"type":"Point"}
}