{
  "type": "Feature",
  "properties": {
    "iso:country":"GB",
    "wof:name":"ML1 5AN",
    "wof:placetype":"postalcode"
},
  "geometry": {"coordinates":[-3.95049281306531,55.81084414365402],"type":"Point"}
}