{
  "type": "Feature",
  "properties": {
    "date:inception_lower": "1980-01-01",
    "date:inception_upper": "1980-01-01",
    "iso:country": "GB",
    "wof:name": "B90 3JF",
    "wof:placetype": "postalcode"
  },
  "geometry": {"coordinates":[-1.820458,52.413957],"type":"Point"}
}
