{
  "type": "Feature",
  "properties": {
    "iso:country":"GB",
    "wof:name":"KA11 4HP",
    "wof:placetype":"postalcode"
},
  "geometry": {"coordinates":[-4.642813582581,55.61135831970865],"type":"Point"}
}