{
  "type": "Feature",
  "properties": {
    "date:inception_lower": "1980-01-01",
    "date:inception_upper": "1980-01-01",
    "iso:country": "GB",
    "wof:name": "PL15 7LA",
    "wof:placetype": "postalcode"
  },
  "geometry": {"coordinates":[-4.391654,50.611813],"type":"Point"}
}
