{
  "type": "Feature",
  "properties": {
    "iso:country":"GB",
    "wof:name":"PL15 7LA",
    "wof:placetype":"postalcode"
},
  "geometry": {"coordinates":[-4.39165402642685,50.61181293610146],"type":"Point"}
}