{
  "type": "Feature",
  "properties": {
    "date:inception_lower": "2022-03-01",
    "date:inception_upper": "2022-03-01",
    "iso:country": "GB",
    "wof:name": "G1 4BY",
    "wof:placetype": "postalcode"
  },
  "geometry": {"coordinates":[-4.253147,55.856857],"type":"Point"}
}
