{
  "type": "Feature",
  "properties": {
    "iso:country":"GB",
    "wof:name":"WF9 5DR",
    "wof:placetype":"postalcode"
},
  "geometry": {"coordinates":[-1.3807972216785,53.63309920936941],"type":"Point"}
}