{
  "type": "Feature",
  "properties": {
    "date:inception_lower":"1980-01-01",
    "date:inception_upper":"1980-01-31",
    "iso:country":"GB",
    "wof:name":"WF9 5DR",
    "wof:placetype":"postalcode"
},
  "geometry": {"coordinates":[-1.380797,53.633099],"type":"Point"}
}