{
  "type": "Feature",
  "properties": {
    "iso:country": "GB",
    "wof:name": "WF9 5DR",
    "wof:placetype": "postalcode"
  },
  "geometry": {"coordinates":[-1.380797,53.633099],"type":"Point"}
}
