{
  "type": "Feature",
  "properties": {
    "iso:country": "GB",
    "wof:name": "EH31 2HH",
    "wof:placetype": "postalcode"
  },
  "geometry": {"coordinates":[-2.81996,56.035189],"type":"Point"}
}
