{
  "type": "Feature",
  "properties": {
    "iso:country":"GB",
    "wof:name":"MK7 7BL",
    "wof:placetype":"postalcode"
},
  "geometry": {"coordinates":[-0.69183013339302,52.01607545452446],"type":"Point"}
}