{
  "type": "Feature",
  "properties": {
    "iso:country": "GB",
    "wof:name": "MK7 7BL",
    "wof:placetype": "postalcode"
  },
  "geometry": {"coordinates":[-0.69183,52.016075],"type":"Point"}
}
