{
  "type": "Feature",
  "properties": {
    "iso:country":"GB",
    "wof:name":"FK7 7UN",
    "wof:placetype":"postalcode"
},
  "geometry": {"coordinates":[-3.92794846979426,56.09896095600604],"type":"Point"}
}