{
  "type": "Feature",
  "properties": {
    "iso:country": "GB",
    "wof:name": "FK7 7UN",
    "wof:placetype": "postalcode"
  },
  "geometry": {"coordinates":[-3.927948,56.098961],"type":"Point"}
}
