{
  "type": "Feature",
  "properties": {
    "date:inception_lower":"1987-11-01",
    "date:inception_upper":"1987-11-30",
    "iso:country":"GB",
    "wof:name":"FK7 7UN",
    "wof:placetype":"postalcode"
},
  "geometry": {"coordinates":[-3.927948,56.098961],"type":"Point"}
}