{
  "type": "Feature",
  "properties": {
    "date:inception_lower": "1991-01-01",
    "date:inception_upper": "1991-01-01",
    "iso:country": "GB",
    "wof:name": "HR6 9UX",
    "wof:placetype": "postalcode"
  },
  "geometry": {"coordinates":[-2.854875,52.312762],"type":"Point"}
}
