{
  "type": "Feature",
  "properties": {
    "iso:country":"GB",
    "wof:name":"HR6 9UX",
    "wof:placetype":"postalcode"
},
  "geometry": {"coordinates":[-2.85487542367328,52.31276208782948],"type":"Point"}
}