{
  "type": "Feature",
  "properties": {
    "iso:country": "GB",
    "wof:name": "GL17 0GX",
    "wof:placetype": "postalcode"
  },
  "geometry": {"coordinates":[-2.489406,51.865095],"type":"Point"}
}
