{
  "type": "Feature",
  "properties": {
    "iso:country":"GB",
    "wof:name":"CO3 3PJ",
    "wof:placetype":"postalcode"
},
  "geometry": {"coordinates":[0.88899397774128,51.88782294879737],"type":"Point"}
}