{
  "type": "Feature",
  "properties": {
    "date:inception_lower": "2008-07-01",
    "date:inception_upper": "2008-07-01",
    "iso:country": "GB",
    "wof:name": "DN18 5EW",
    "wof:placetype": "postalcode"
  },
  "geometry": {"coordinates":[-0.452486,53.68827],"type":"Point"}
}
