{
  "type": "Feature",
  "properties": {
    "iso:country": "GB",
    "wof:name": "DN18 5EW",
    "wof:placetype": "postalcode"
  },
  "geometry": {"coordinates":[-0.452486,53.68827],"type":"Point"}
}
