{
  "type": "Feature",
  "properties": {
    "iso:country":"GB",
    "wof:name":"LN1 3RQ",
    "wof:placetype":"postalcode"
},
  "geometry": {"coordinates":[-0.54525343449685,53.25264313219639],"type":"Point"}
}