{
  "type": "Feature",
  "properties": {
    "iso:country": "GB",
    "wof:name": "NE4 9BA",
    "wof:placetype": "postalcode"
  },
  "geometry": {"coordinates":[-1.651479,54.980212],"type":"Point"}
}
