{
  "type": "Feature",
  "properties": {
    "iso:country": "GB",
    "wof:name": "BD2 4NU",
    "wof:placetype": "postalcode"
  },
  "geometry": {"coordinates":[-1.732055,53.809782],"type":"Point"}
}
