{
  "type": "Feature",
  "properties": {
    "iso:country":"GB",
    "wof:name":"BL0 9UY",
    "wof:placetype":"postalcode"
},
  "geometry": {"coordinates":[-2.32752529195977,53.62838113452453],"type":"Point"}
}