{
  "type": "Feature",
  "properties": {
    "iso:country": "GB",
    "wof:name": "BL0 9UY",
    "wof:placetype": "postalcode"
  },
  "geometry": {"coordinates":[-2.327525,53.628381],"type":"Point"}
}
