{
  "type": "Feature",
  "properties": {
    "iso:country": "GB",
    "wof:name": "AL5 3BY",
    "wof:placetype": "postalcode"
  },
  "geometry": {"coordinates":[-0.375723,51.825528],"type":"Point"}
}
