{
  "type": "Feature",
  "properties": {
    "iso:country":"GB",
    "wof:name":"GU6 8DR",
    "wof:placetype":"postalcode"
},
  "geometry": {"coordinates":[-0.48328352866,51.14032936834259],"type":"Point"}
}