{
  "type": "Feature",
  "properties": {
    "date:inception_lower": "1980-01-01",
    "date:inception_upper": "1980-01-01",
    "iso:country": "GB",
    "wof:name": "GU6 8DR",
    "wof:placetype": "postalcode"
  },
  "geometry": {"coordinates":[-0.483283,51.140329],"type":"Point"}
}
