{
  "type": "Feature",
  "properties": {
    "iso:country":"GB",
    "wof:name":"GL7 2EP",
    "wof:placetype":"postalcode"
},
  "geometry": {"coordinates":[-1.96829188030503,51.72244222829506],"type":"Point"}
}