{
  "type": "Feature",
  "properties": {
    "iso:country":"GB",
    "wof:name":"NG5 9RU",
    "wof:placetype":"postalcode"
},
  "geometry": {"coordinates":[-1.17801482587136,52.99770857019119],"type":"Point"}
}