{
  "type": "Feature",
  "properties": {
    "date:inception_lower": "1980-01-01",
    "date:inception_upper": "1980-01-01",
    "iso:country": "GB",
    "wof:name": "IV6 7SR",
    "wof:placetype": "postalcode"
  },
  "geometry": {"coordinates":[-4.456969,57.514765],"type":"Point"}
}
