{
  "type": "Feature",
  "properties": {
    "iso:country": "GB",
    "wof:name": "IV6 7SR",
    "wof:placetype": "postalcode"
  },
  "geometry": {"coordinates":[-4.457105,57.515041],"type":"Point"}
}
