{
  "type": "Feature",
  "properties": {
    "date:inception_lower":"2002-12-01",
    "date:inception_upper":"2002-12-31",
    "iso:country":"GB",
    "wof:name":"ML1 2EB",
    "wof:placetype":"postalcode"
},
  "geometry": {"coordinates":[-3.991274,55.779392],"type":"Point"}
}