{
  "type": "Feature",
  "properties": {
    "iso:country":"GB",
    "wof:name":"ML1 2EB",
    "wof:placetype":"postalcode"
},
  "geometry": {"coordinates":[-3.99127387013743,55.77939199915127],"type":"Point"}
}