{
  "type": "Feature",
  "properties": {
    "iso:country": "GB",
    "wof:name": "BN42 4TU",
    "wof:placetype": "postalcode"
  },
  "geometry": {"coordinates":[-0.237207,50.837902],"type":"Point"}
}
