{
  "type": "Feature",
  "properties": {
    "date:inception_lower": "1991-09-01",
    "date:inception_upper": "1991-09-01",
    "iso:country": "GB",
    "wof:name": "LE16 8BY",
    "wof:placetype": "postalcode"
  },
  "geometry": {"coordinates":[-0.908082,52.477866],"type":"Point"}
}
