{
  "type": "Feature",
  "properties": {
    "iso:country":"GB",
    "wof:name":"LE16 8BY",
    "wof:placetype":"postalcode"
},
  "geometry": {"coordinates":[-0.90808235651218,52.47786558623289],"type":"Point"}
}