{
  "type": "Feature",
  "properties": {
    "iso:country": "GB",
    "wof:name": "PL33 9ZX",
    "wof:placetype": "postalcode"
  },
  "geometry": {"coordinates":[-4.729098,50.62518],"type":"Point"}
}
