{
  "type": "Feature",
  "properties": {
    "date:inception_lower":"2018-07-01",
    "date:inception_upper":"2018-07-31",
    "iso:country":"GB",
    "wof:name":"PL33 9ZX",
    "wof:placetype":"postalcode"
},
  "geometry": {"coordinates":[-4.729098,50.62518],"type":"Point"}
}