{
  "type": "Feature",
  "properties": {
    "date:inception_lower":"2015-04-01",
    "date:inception_upper":"2015-04-30",
    "iso:country":"GB",
    "wof:name":"ME12 3FU",
    "wof:placetype":"postalcode"
},
  "geometry": {"coordinates":[0.797733,51.417474],"type":"Point"}
}