{
  "type": "Feature",
  "properties": {
    "iso:country": "GB",
    "wof:name": "OX7 3RG",
    "wof:placetype": "postalcode"
  },
  "geometry": {"coordinates":[-1.474997,51.877225],"type":"Point"}
}
