{
  "type": "Feature",
  "properties": {
    "date:inception_lower": "1980-01-01",
    "date:inception_upper": "1980-01-01",
    "iso:country": "GB",
    "wof:name": "HR1 1EQ",
    "wof:placetype": "postalcode"
  },
  "geometry": {"coordinates":[-2.706781,52.061196],"type":"Point"}
}
