{
  "type": "Feature",
  "properties": {
    "iso:country":"GB",
    "wof:name":"HR1 1EQ",
    "wof:placetype":"postalcode"
},
  "geometry": {"coordinates":[-2.70678127251801,52.06119608509476],"type":"Point"}
}