{
  "type": "Feature",
  "properties": {
    "iso:country":"GB",
    "wof:name":"PL11 2HT",
    "wof:placetype":"postalcode"
},
  "geometry": {"coordinates":[-4.20144436366476,50.37065920135848],"type":"Point"}
}