{
  "type": "Feature",
  "properties": {
    "iso:country": "GB",
    "wof:name": "EX8 2AP",
    "wof:placetype": "postalcode"
  },
  "geometry": {"coordinates":[-3.40921,50.616163],"type":"Point"}
}
