{
  "type": "Feature",
  "properties": {
    "iso:country":"GB",
    "wof:name":"S72 8UX",
    "wof:placetype":"postalcode"
},
  "geometry": {"coordinates":[-1.42612055215617,53.57507126800707],"type":"Point"}
}