{
  "type": "Feature",
  "properties": {
    "date:inception_lower":"1980-01-01",
    "date:inception_upper":"1980-01-31",
    "iso:country":"GB",
    "wof:name":"S72 8UX",
    "wof:placetype":"postalcode"
},
  "geometry": {"coordinates":[-1.426121,53.575071],"type":"Point"}
}