{
  "type": "Feature",
  "properties": {
    "date:inception_lower":"1980-01-01",
    "date:inception_upper":"1980-01-31",
    "iso:country":"GB",
    "wof:name":"NP44 6HJ",
    "wof:placetype":"postalcode"
},
  "geometry": {"coordinates":[-3.060106,51.641045],"type":"Point"}
}