{
  "type": "Feature",
  "properties": {
    "iso:country":"GB",
    "wof:name":"M20 2TZ",
    "wof:placetype":"postalcode"
},
  "geometry": {"coordinates":[-2.2408815801169,53.41838446498109],"type":"Point"}
}