{
  "type": "Feature",
  "properties": {
    "iso:country":"GB",
    "wof:name":"BN14 8NJ",
    "wof:placetype":"postalcode"
},
  "geometry": {"coordinates":[-0.36388169769309,50.82852376935814],"type":"Point"}
}