{
  "type": "Feature",
  "properties": {
    "iso:country": "GB",
    "wof:name": "M44 5EB",
    "wof:placetype": "postalcode"
  },
  "geometry": {"coordinates":[-2.448097,53.420995],"type":"Point"}
}
