{
  "type": "Feature",
  "properties": {
    "iso:country":"GB",
    "wof:name":"M44 5EB",
    "wof:placetype":"postalcode"
},
  "geometry": {"coordinates":[-2.44809684718021,53.42099527185351],"type":"Point"}
}