{
  "type": "Feature",
  "properties": {
    "date:inception_lower": "1990-02-01",
    "date:inception_upper": "1990-02-01",
    "iso:country": "GB",
    "wof:name": "LN4 3XA",
    "wof:placetype": "postalcode"
  },
  "geometry": {"coordinates":[-0.410611,53.1391],"type":"Point"}
}
