{
  "type": "Feature",
  "properties": {
    "iso:country":"GB",
    "wof:name":"HU5 5GB",
    "wof:placetype":"postalcode"
},
  "geometry": {"coordinates":[-0.39623820479122,53.7556768414032],"type":"Point"}
}