{
  "type": "Feature",
  "properties": {
    "date:inception_lower":"1991-09-01",
    "date:inception_upper":"1991-09-30",
    "iso:country":"GB",
    "wof:name":"HU5 5GB",
    "wof:placetype":"postalcode"
},
  "geometry": {"coordinates":[-0.396238,53.755677],"type":"Point"}
}