{
  "type": "Feature",
  "properties": {
    "iso:country":"GB",
    "wof:name":"BD8 0DP",
    "wof:placetype":"postalcode"
},
  "geometry": {"coordinates":[-1.80794752574108,53.79717615623149],"type":"Point"}
}