{
  "type": "Feature",
  "properties": {
    "iso:country":"GB",
    "wof:name":"FK8 3JW",
    "wof:placetype":"postalcode"
},
  "geometry": {"coordinates":[-4.18118395147357,56.10208817072483],"type":"Point"}
}