{
  "type": "Feature",
  "properties": {
    "iso:country": "GB",
    "wof:name": "HD7 5JY",
    "wof:placetype": "postalcode"
  },
  "geometry": {"coordinates":[-1.879229,53.620698],"type":"Point"}
}
