{
  "type": "Feature",
  "properties": {
    "iso:country":"GB",
    "wof:name":"HD7 5JY",
    "wof:placetype":"postalcode"
},
  "geometry": {"coordinates":[-1.87922901444247,53.62069782947678],"type":"Point"}
}