{
  "type": "Feature",
  "properties": {
    "iso:country": "GB",
    "wof:name": "GL55 6TF",
    "wof:placetype": "postalcode"
  },
  "geometry": {"coordinates":[-1.757019,52.095149],"type":"Point"}
}
