{
  "type": "Feature",
  "properties": {
    "date:inception_lower": "1980-01-01",
    "date:inception_upper": "1980-01-01",
    "iso:country": "GB",
    "wof:name": "GL55 6TF",
    "wof:placetype": "postalcode"
  },
  "geometry": {"coordinates":[-1.757019,52.095149],"type":"Point"}
}
