{
  "type": "Feature",
  "properties": {
    "iso:country":"GB",
    "wof:name":"GL55 6TF",
    "wof:placetype":"postalcode"
},
  "geometry": {"coordinates":[-1.75758495192911,52.09505663411187],"type":"Point"}
}