{
  "type": "Feature",
  "properties": {
    "iso:country":"GB",
    "wof:name":"PE19 5HT",
    "wof:placetype":"postalcode"
},
  "geometry": {"coordinates":[-0.30671375998851,52.23018375463427],"type":"Point"}
}