{
  "type": "Feature",
  "properties": {
    "date:inception_lower": "2000-06-01",
    "date:inception_upper": "2000-06-01",
    "iso:country": "GB",
    "wof:name": "PE19 5HT",
    "wof:placetype": "postalcode"
  },
  "geometry": {"coordinates":[-0.306693,52.230197],"type":"Point"}
}
