{
  "type": "Feature",
  "properties": {
    "iso:country":"GB",
    "wof:name":"HU13 9NW",
    "wof:placetype":"postalcode"
},
  "geometry": {"coordinates":[-0.41850846155522,53.72570654821184],"type":"Point"}
}