{
  "type": "Feature",
  "properties": {
    "iso:country": "GB",
    "wof:name": "HU13 9NW",
    "wof:placetype": "postalcode"
  },
  "geometry": {"coordinates":[-0.419048,53.725616],"type":"Point"}
}
