{
  "type": "Feature",
  "properties": {
    "iso:country": "GB",
    "wof:name": "NN15 7QL",
    "wof:placetype": "postalcode"
  },
  "geometry": {"coordinates":[-0.72693,52.395185],"type":"Point"}
}
