{
  "type": "Feature",
  "properties": {
    "iso:country":"GB",
    "wof:name":"NN15 7QL",
    "wof:placetype":"postalcode"
},
  "geometry": {"coordinates":[-0.72693008968052,52.3951848025406],"type":"Point"}
}