{
  "type": "Feature",
  "properties": {
    "iso:country":"GB",
    "wof:name":"CO8 5BE",
    "wof:placetype":"postalcode"
},
  "geometry": {"coordinates":[0.77174502645322,51.96848202397791],"type":"Point"}
}