{
  "type": "Feature",
  "properties": {
    "date:inception_lower": "1980-01-01",
    "date:inception_upper": "1980-01-01",
    "iso:country": "GB",
    "wof:name": "CO8 5BE",
    "wof:placetype": "postalcode"
  },
  "geometry": {"coordinates":[0.771745,51.968482],"type":"Point"}
}
