{
  "type": "Feature",
  "properties": {
    "iso:country": "GB",
    "wof:name": "IP7 6BN",
    "wof:placetype": "postalcode"
  },
  "geometry": {"coordinates":[0.9596,52.049688],"type":"Point"}
}
