{
  "type": "Feature",
  "properties": {
    "iso:country":"GB",
    "wof:name":"IP7 6BN",
    "wof:placetype":"postalcode"
},
  "geometry": {"coordinates":[0.95959963030713,52.04968818175544],"type":"Point"}
}