{
  "type": "Feature",
  "properties": {
    "iso:country":"GB",
    "wof:name":"CO16 8QS",
    "wof:placetype":"postalcode"
},
  "geometry": {"coordinates":[1.08081565911982,51.80146783078515],"type":"Point"}
}