{
  "type": "Feature",
  "properties": {
    "iso:country":"GB",
    "wof:name":"BD4 8RN",
    "wof:placetype":"postalcode"
},
  "geometry": {"coordinates":[-1.72179323980487,53.78097284574541],"type":"Point"}
}