{
  "type": "Feature",
  "properties": {
    "iso:country":"GB",
    "wof:name":"TN8 5DE",
    "wof:placetype":"postalcode"
},
  "geometry": {"coordinates":[0.06958521155922,51.18906668230243],"type":"Point"}
}