{
  "type": "Feature",
  "properties": {
    "date:inception_lower":"1983-03-01",
    "date:inception_upper":"1983-03-31",
    "iso:country":"GB",
    "wof:name":"TR18 2NB",
    "wof:placetype":"postalcode"
},
  "geometry": {"coordinates":[-5.534454,50.118259],"type":"Point"}
}