{
  "type": "Feature",
  "properties": {
    "iso:country": "GB",
    "wof:name": "TR18 2NB",
    "wof:placetype": "postalcode"
  },
  "geometry": {"coordinates":[-5.534454,50.118259],"type":"Point"}
}
