{
  "type": "Feature",
  "properties": {
    "iso:country":"GB",
    "wof:name":"TR18 2NB",
    "wof:placetype":"postalcode"
},
  "geometry": {"coordinates":[-5.53445442878372,50.11825882713247],"type":"Point"}
}