{
  "type": "Feature",
  "properties": {
    "iso:country":"GB",
    "wof:name":"N10 1JT",
    "wof:placetype":"postalcode"
},
  "geometry": {"coordinates":[-0.15246028909576,51.60189605214143],"type":"Point"}
}