{
  "type": "Feature",
  "properties": {
    "iso:country": "GB",
    "wof:name": "ST13 8QJ",
    "wof:placetype": "postalcode"
  },
  "geometry": {"coordinates":[-2.115573,53.106715],"type":"Point"}
}
