{
  "type": "Feature",
  "properties": {
    "iso:country":"GB",
    "wof:name":"NR24 2QY",
    "wof:placetype":"postalcode"
},
  "geometry": {"coordinates":[0.99969201095356,52.84949750389883],"type":"Point"}
}