{
  "type": "Feature",
  "properties": {
    "iso:country": "GB",
    "wof:name": "NR24 2QY",
    "wof:placetype": "postalcode"
  },
  "geometry": {"coordinates":[0.999766,52.849487],"type":"Point"}
}
