{
  "type": "Feature",
  "properties": {
    "iso:country":"GB",
    "wof:name":"PE6 9HG",
    "wof:placetype":"postalcode"
},
  "geometry": {"coordinates":[-0.34516368153982,52.65194739067493],"type":"Point"}
}