{
  "type": "Feature",
  "properties": {
    "iso:country": "GB",
    "wof:name": "PE6 9HG",
    "wof:placetype": "postalcode"
  },
  "geometry": {"coordinates":[-0.345901,52.651671],"type":"Point"}
}
