{
  "type": "Feature",
  "properties": {
    "iso:country":"GB",
    "wof:name":"LE5 3HN",
    "wof:placetype":"postalcode"
},
  "geometry": {"coordinates":[-1.11052327083968,52.63684255917618],"type":"Point"}
}