{
  "type": "Feature",
  "properties": {
    "date:inception_lower": "1983-07-01",
    "date:inception_upper": "1983-07-01",
    "iso:country": "GB",
    "wof:name": "PE34 3BZ",
    "wof:placetype": "postalcode"
  },
  "geometry": {"coordinates":[0.356979,52.670028],"type":"Point"}
}
