{
  "type": "Feature",
  "properties": {
    "iso:country":"GB",
    "wof:name":"EX34 8EW",
    "wof:placetype":"postalcode"
},
  "geometry": {"coordinates":[-4.12400191382963,51.19666115564727],"type":"Point"}
}