{
  "type": "Feature",
  "properties": {
    "iso:country":"GB",
    "wof:name":"EH17 8PE",
    "wof:placetype":"postalcode"
},
  "geometry": {"coordinates":[-3.14183631635314,55.89920487937832],"type":"Point"}
}