{
  "type": "Feature",
  "properties": {
    "date:inception_lower":"2009-06-01",
    "date:inception_upper":"2009-06-30",
    "iso:country":"GB",
    "wof:name":"SP4 7FH",
    "wof:placetype":"postalcode"
},
  "geometry": {"coordinates":[-1.779726,51.172748],"type":"Point"}
}