{
  "type": "Feature",
  "properties": {
    "iso:country":"GB",
    "wof:name":"SP4 7FH",
    "wof:placetype":"postalcode"
},
  "geometry": {"coordinates":[-1.77972618598786,51.17274829592482],"type":"Point"}
}