{
  "type": "Feature",
  "properties": {
    "iso:country":"GB",
    "wof:name":"WA12 0BL",
    "wof:placetype":"postalcode"
},
  "geometry": {"coordinates":[-2.60752175648845,53.45568768991791],"type":"Point"}
}