{
  "type": "Feature",
  "properties": {
    "iso:country": "GB",
    "wof:name": "WA12 0BL",
    "wof:placetype": "postalcode"
  },
  "geometry": {"coordinates":[-2.607522,53.455688],"type":"Point"}
}
