{
  "type": "Feature",
  "properties": {
    "iso:country":"GB",
    "wof:name":"BB9 9PD",
    "wof:placetype":"postalcode"
},
  "geometry": {"coordinates":[-2.19721075476425,53.8380261150221],"type":"Point"}
}