{
  "type": "Feature",
  "properties": {
    "date:inception_lower":"1997-12-01",
    "date:inception_upper":"1997-12-31",
    "iso:country":"GB",
    "wof:name":"BS39 4HX",
    "wof:placetype":"postalcode"
},
  "geometry": {"coordinates":[-2.530264,51.37755],"type":"Point"}
}