{
  "type": "Feature",
  "properties": {
    "iso:country":"GB",
    "wof:name":"BS39 4HX",
    "wof:placetype":"postalcode"
},
  "geometry": {"coordinates":[-2.53026380782949,51.37754976745597],"type":"Point"}
}