{
  "type": "Feature",
  "properties": {
    "iso:country": "GB",
    "wof:name": "SO52 9JU",
    "wof:placetype": "postalcode"
  },
  "geometry": {"coordinates":[-1.401728,50.995855],"type":"Point"}
}
