{
  "type": "Feature",
  "properties": {
    "iso:country":"GB",
    "wof:name":"SO52 9JU",
    "wof:placetype":"postalcode"
},
  "geometry": {"coordinates":[-1.40165382386706,50.99579956912755],"type":"Point"}
}