{
  "type": "Feature",
  "properties": {
    "iso:country": "GB",
    "wof:name": "OL4 4BJ",
    "wof:placetype": "postalcode"
  },
  "geometry": {"coordinates":[-2.05773,53.544416],"type":"Point"}
}
