{
  "type": "Feature",
  "properties": {
    "date:inception_lower": "1995-01-01",
    "date:inception_upper": "1995-01-01",
    "iso:country": "GB",
    "wof:name": "M5 3PH",
    "wof:placetype": "postalcode"
  },
  "geometry": {"coordinates":[-2.280291,53.473882],"type":"Point"}
}
