{
  "type": "Feature",
  "properties": {
    "iso:country": "GB",
    "wof:name": "SA43 2RX",
    "wof:placetype": "postalcode"
  },
  "geometry": {"coordinates":[-4.655758,52.054105],"type":"Point"}
}
