{
  "type": "Feature",
  "properties": {
    "date:inception_lower":"1980-01-01",
    "date:inception_upper":"1980-01-31",
    "iso:country":"GB",
    "wof:name":"SA43 2RX",
    "wof:placetype":"postalcode"
},
  "geometry": {"coordinates":[-4.655758,52.054105],"type":"Point"}
}