{
  "type": "Feature",
  "properties": {
    "iso:country":"GB",
    "wof:name":"SA43 2RX",
    "wof:placetype":"postalcode"
},
  "geometry": {"coordinates":[-4.65575799895987,52.0541050682256],"type":"Point"}
}