{
  "type": "Feature",
  "properties": {
    "date:inception_lower": "2006-02-01",
    "date:inception_upper": "2006-02-01",
    "iso:country": "GB",
    "wof:name": "OX12 0LU",
    "wof:placetype": "postalcode"
  },
  "geometry": {"coordinates":[-1.414818,51.634416],"type":"Point"}
}
