{
  "type": "Feature",
  "properties": {
    "iso:country":"GB",
    "wof:name":"WD24 7FQ",
    "wof:placetype":"postalcode"
},
  "geometry": {"coordinates":[-0.39583517357119,51.67505484766955],"type":"Point"}
}