{
  "type": "Feature",
  "properties": {
    "iso:country": "GB",
    "wof:name": "WD24 7FQ",
    "wof:placetype": "postalcode"
  },
  "geometry": {"coordinates":[-0.395835,51.675055],"type":"Point"}
}
