{
  "type": "Feature",
  "properties": {
    "iso:country":"GB",
    "wof:name":"GU8 4LT",
    "wof:placetype":"postalcode"
},
  "geometry": {"coordinates":[-0.57395783774541,51.11846692032655],"type":"Point"}
}