{
  "type": "Feature",
  "properties": {
    "date:inception_lower": "2000-10-01",
    "date:inception_upper": "2000-10-01",
    "iso:country": "GB",
    "wof:name": "OX27 0BS",
    "wof:placetype": "postalcode"
  },
  "geometry": {"coordinates":[-1.024286,51.914399],"type":"Point"}
}
