{
  "type": "Feature",
  "properties": {
    "iso:country":"GB",
    "wof:name":"OX27 0BS",
    "wof:placetype":"postalcode"
},
  "geometry": {"coordinates":[-1.02428578503942,51.9143987848061],"type":"Point"}
}