{
  "type": "Feature",
  "properties": {
    "iso:country":"GB",
    "wof:name":"AL2 1LN",
    "wof:placetype":"postalcode"
},
  "geometry": {"coordinates":[-0.30226329902188,51.7201926492413],"type":"Point"}
}