{
  "type": "Feature",
  "properties": {
    "iso:country":"GB",
    "wof:name":"WD17 4DR",
    "wof:placetype":"postalcode"
},
  "geometry": {"coordinates":[-0.4030069194354,51.66441612126922],"type":"Point"}
}