{
  "type": "Feature",
  "properties": {
    "date:inception_lower":"2000-12-01",
    "date:inception_upper":"2000-12-31",
    "iso:country":"GB",
    "wof:name":"WD17 4DR",
    "wof:placetype":"postalcode"
},
  "geometry": {"coordinates":[-0.403007,51.664416],"type":"Point"}
}