{
  "type": "Feature",
  "properties": {
    "iso:country": "GB",
    "wof:name": "ME6 5BU",
    "wof:placetype": "postalcode"
  },
  "geometry": {"coordinates":[0.434438,51.324401],"type":"Point"}
}
