{
  "type": "Feature",
  "properties": {
    "iso:country":"GB",
    "wof:name":"NE46 4DB",
    "wof:placetype":"postalcode"
},
  "geometry": {"coordinates":[-2.2168669779003,55.03762386757646],"type":"Point"}
}