{
  "type": "Feature",
  "properties": {
    "iso:country": "GB",
    "wof:name": "NE46 4DB",
    "wof:placetype": "postalcode"
  },
  "geometry": {"coordinates":[-2.216867,55.037624],"type":"Point"}
}
