{
  "type": "Feature",
  "properties": {
    "iso:country": "GB",
    "wof:name": "S36 9AF",
    "wof:placetype": "postalcode"
  },
  "geometry": {"coordinates":[-1.639552,53.520562],"type":"Point"}
}
