{
  "type": "Feature",
  "properties": {
    "iso:country":"GB",
    "wof:name":"EN1 1JZ",
    "wof:placetype":"postalcode"
},
  "geometry": {"coordinates":[-0.07095811529634,51.64622145587202],"type":"Point"}
}