{
  "type": "Feature",
  "properties": {
    "date:inception_lower": "1980-01-01",
    "date:inception_upper": "1980-01-01",
    "iso:country": "GB",
    "wof:name": "CO16 0HG",
    "wof:placetype": "postalcode"
  },
  "geometry": {"coordinates":[1.159935,51.852814],"type":"Point"}
}
