{
  "type": "Feature",
  "properties": {
    "iso:country":"GB",
    "wof:name":"CO16 0HG",
    "wof:placetype":"postalcode"
},
  "geometry": {"coordinates":[1.15967876871987,51.85249305660999],"type":"Point"}
}