{
  "type": "Feature",
  "properties": {
    "iso:country":"GB",
    "wof:name":"CH1 2DQ",
    "wof:placetype":"postalcode"
},
  "geometry": {"coordinates":[-2.8907667415147,53.18689318629054],"type":"Point"}
}