{
  "type": "Feature",
  "properties": {
    "date:inception_lower": "1980-01-01",
    "date:inception_upper": "1980-01-01",
    "iso:country": "GB",
    "wof:name": "CH1 2DQ",
    "wof:placetype": "postalcode"
  },
  "geometry": {"coordinates":[-2.890767,53.186893],"type":"Point"}
}
