{
  "type": "Feature",
  "properties": {
    "iso:country": "GB",
    "wof:name": "M43 6WL",
    "wof:placetype": "postalcode"
  },
  "geometry": {"coordinates":[-2.167827,53.485708],"type":"Point"}
}
