{
  "type": "Feature",
  "properties": {
    "iso:country":"GB",
    "wof:name":"M43 6WL",
    "wof:placetype":"postalcode"
},
  "geometry": {"coordinates":[-2.16782673265399,53.48570756515853],"type":"Point"}
}