{
  "type": "Feature",
  "properties": {
    "date:inception_lower": "1994-05-01",
    "date:inception_upper": "1994-05-01",
    "iso:country": "GB",
    "wof:name": "M43 6WL",
    "wof:placetype": "postalcode"
  },
  "geometry": {"coordinates":[-2.167827,53.485708],"type":"Point"}
}
