{
  "type": "Feature",
  "properties": {
    "iso:country": "GB",
    "wof:name": "S44 6PX",
    "wof:placetype": "postalcode"
  },
  "geometry": {"coordinates":[-1.30172,53.22615],"type":"Point"}
}
