{
  "type": "Feature",
  "properties": {
    "date:inception_lower": "1980-01-01",
    "date:inception_upper": "1980-01-01",
    "iso:country": "GB",
    "wof:name": "SW17 7AL",
    "wof:placetype": "postalcode"
  },
  "geometry": {"coordinates":[-0.158031,51.437368],"type":"Point"}
}
