{
  "type": "Feature",
  "properties": {
    "iso:country":"GB",
    "wof:name":"SW17 7AL",
    "wof:placetype":"postalcode"
},
  "geometry": {"coordinates":[-0.15843731656582,51.43755354471534],"type":"Point"}
}