{
  "type": "Feature",
  "properties": {
    "date:inception_lower": "1981-06-01",
    "date:inception_upper": "1981-06-01",
    "iso:country": "GB",
    "wof:name": "HP14 3TF",
    "wof:placetype": "postalcode"
  },
  "geometry": {"coordinates":[-0.899241,51.661033],"type":"Point"}
}
