{
  "type": "Feature",
  "properties": {
    "iso:country":"GB",
    "wof:name":"CM3 1DB",
    "wof:placetype":"postalcode"
},
  "geometry": {"coordinates":[0.45699923662297,51.79214526870162],"type":"Point"}
}