{
  "type": "Feature",
  "properties": {
    "date:inception_lower": "2002-06-01",
    "date:inception_upper": "2002-06-01",
    "iso:country": "GB",
    "wof:name": "SA4 8LL",
    "wof:placetype": "postalcode"
  },
  "geometry": {"coordinates":[-4.038068,51.711715],"type":"Point"}
}
