{
  "type": "Feature",
  "properties": {
    "iso:country":"GB",
    "wof:name":"TF2 9EY",
    "wof:placetype":"postalcode"
},
  "geometry": {"coordinates":[-2.43400443372263,52.69158677049925],"type":"Point"}
}