{
  "type": "Feature",
  "properties": {
    "iso:country":"GB",
    "wof:name":"S80 4BG",
    "wof:placetype":"postalcode"
},
  "geometry": {"coordinates":[-1.20998218006741,53.26144374082485],"type":"Point"}
}