{
  "type": "Feature",
  "properties": {
    "iso:country":"GB",
    "wof:name":"CF83 3GD",
    "wof:placetype":"postalcode"
},
  "geometry": {"coordinates":[-3.22769587412462,51.58632484930642],"type":"Point"}
}