{
  "type": "Feature",
  "properties": {
    "iso:country":"GB",
    "wof:name":"WF7 5LB",
    "wof:placetype":"postalcode"
},
  "geometry": {"coordinates":[-1.3537946403312,53.67423102155082],"type":"Point"}
}