{
  "type": "Feature",
  "properties": {
    "date:inception_lower":"1980-01-01",
    "date:inception_upper":"1980-01-31",
    "iso:country":"GB",
    "wof:name":"WF7 5LB",
    "wof:placetype":"postalcode"
},
  "geometry": {"coordinates":[-1.353795,53.674231],"type":"Point"}
}