{
  "type": "Feature",
  "properties": {
    "iso:country":"GB",
    "wof:name":"PR4 0UL",
    "wof:placetype":"postalcode"
},
  "geometry": {"coordinates":[-2.81719191656848,53.83548480767202],"type":"Point"}
}