{
  "type": "Feature",
  "properties": {
    "date:inception_lower":"1980-01-01",
    "date:inception_upper":"1980-01-31",
    "iso:country":"GB",
    "wof:name":"PR4 0UL",
    "wof:placetype":"postalcode"
},
  "geometry": {"coordinates":[-2.817192,53.835485],"type":"Point"}
}