{
  "type": "Feature",
  "properties": {
    "iso:country": "GB",
    "wof:name": "PR6 9ED",
    "wof:placetype": "postalcode"
  },
  "geometry": {"coordinates":[-2.609586,53.641577],"type":"Point"}
}
