{
  "type": "Feature",
  "properties": {
    "iso:country":"GB",
    "wof:name":"EH9 3HT",
    "wof:placetype":"postalcode"
},
  "geometry": {"coordinates":[-3.18918653185691,55.92672854202363],"type":"Point"}
}