{
  "type": "Feature",
  "properties": {
    "iso:country":"GB",
    "wof:name":"SO19 9EZ",
    "wof:placetype":"postalcode"
},
  "geometry": {"coordinates":[-1.36503279553371,50.89436053339103],"type":"Point"}
}