{
  "type": "Feature",
  "properties": {
    "date:inception_lower":"1998-06-01",
    "date:inception_upper":"1998-06-30",
    "iso:country":"GB",
    "wof:name":"YO23 3PT",
    "wof:placetype":"postalcode"
},
  "geometry": {"coordinates":[-1.183335,53.924097],"type":"Point"}
}