{
  "type": "Feature",
  "properties": {
    "iso:country":"GB",
    "wof:name":"YO23 3PT",
    "wof:placetype":"postalcode"
},
  "geometry": {"coordinates":[-1.18333509123082,53.92409675295801],"type":"Point"}
}