{
  "type": "Feature",
  "properties": {
    "iso:country":"GB",
    "wof:name":"CM7 3DP",
    "wof:placetype":"postalcode"
},
  "geometry": {"coordinates":[0.57339413065308,51.88019659431649],"type":"Point"}
}