{
  "type": "Feature",
  "properties": {
    "iso:country":"GB",
    "wof:name":"BR1 2TH",
    "wof:placetype":"postalcode"
},
  "geometry": {"coordinates":[0.0373802110221,51.41312622996053],"type":"Point"}
}