{
  "type": "Feature",
  "properties": {
    "iso:country":"GB",
    "wof:name":"NE22 5DA",
    "wof:placetype":"postalcode"
},
  "geometry": {"coordinates":[-1.59007307445123,55.13212931748355],"type":"Point"}
}