{
  "type": "Feature",
  "properties": {
    "iso:country": "GB",
    "wof:name": "NG7 6JH",
    "wof:placetype": "postalcode"
  },
  "geometry": {"coordinates":[-1.159245,52.969081],"type":"Point"}
}
