{
  "type": "Feature",
  "properties": {
    "iso:country":"GB",
    "wof:name":"NG7 6JH",
    "wof:placetype":"postalcode"
},
  "geometry": {"coordinates":[-1.15924531034508,52.96908080961052],"type":"Point"}
}