{
  "type": "Feature",
  "properties": {
    "date:inception_lower": "1980-01-01",
    "date:inception_upper": "1980-01-01",
    "iso:country": "GB",
    "wof:name": "G83 7AL",
    "wof:placetype": "postalcode"
  },
  "geometry": {"coordinates":[-4.749241,56.209055],"type":"Point"}
}
