{
  "type": "Feature",
  "properties": {
    "date:inception_lower": "2018-12-01",
    "date:inception_upper": "2018-12-01",
    "iso:country": "GB",
    "wof:name": "WA10 1DY",
    "wof:placetype": "postalcode"
  },
  "geometry": {"coordinates":[-2.734679,53.453596],"type":"Point"}
}
