{
  "type": "Feature",
  "properties": {
    "date:inception_lower": "2020-02-01",
    "date:inception_upper": "2020-02-01",
    "iso:country": "GB",
    "wof:name": "G78 2BW",
    "wof:placetype": "postalcode"
  },
  "geometry": {"coordinates":[-4.392577,55.788415],"type":"Point"}
}
