{
  "type": "Feature",
  "properties": {
    "iso:country":"GB",
    "wof:name":"L12 0AR",
    "wof:placetype":"postalcode"
},
  "geometry": {"coordinates":[-2.89115480120978,53.44978232438121],"type":"Point"}
}