{
  "type": "Feature",
  "properties": {
    "iso:country":"GB",
    "wof:name":"SG2 9JZ",
    "wof:placetype":"postalcode"
},
  "geometry": {"coordinates":[-0.16838943442169,51.89551455041308],"type":"Point"}
}