{
  "type": "Feature",
  "properties": {
    "date:inception_lower": "1980-01-01",
    "date:inception_upper": "1980-01-01",
    "iso:country": "GB",
    "wof:name": "KT14 7PD",
    "wof:placetype": "postalcode"
  },
  "geometry": {"coordinates":[-0.476497,51.339723],"type":"Point"}
}
