{
  "type": "Feature",
  "properties": {
    "iso:country":"GB",
    "wof:name":"KT14 7PD",
    "wof:placetype":"postalcode"
},
  "geometry": {"coordinates":[-0.47649667696329,51.3397228790034],"type":"Point"}
}