{
  "type": "Feature",
  "properties": {
    "iso:country":"GB",
    "wof:name":"WF11 0NG",
    "wof:placetype":"postalcode"
},
  "geometry": {"coordinates":[-1.25639282593087,53.69868065552767],"type":"Point"}
}