{
  "type": "Feature",
  "properties": {
    "date:inception_lower":"1980-01-01",
    "date:inception_upper":"1980-01-31",
    "iso:country":"GB",
    "wof:name":"WF11 0NG",
    "wof:placetype":"postalcode"
},
  "geometry": {"coordinates":[-1.256393,53.698681],"type":"Point"}
}