{
  "type": "Feature",
  "properties": {
    "date:inception_lower":"2005-01-01",
    "date:inception_upper":"2005-01-31",
    "iso:country":"GB",
    "wof:name":"RG27 0HP",
    "wof:placetype":"postalcode"
},
  "geometry": {"coordinates":[-1.025172,51.312222],"type":"Point"}
}