{
  "type": "Feature",
  "properties": {
    "iso:country": "GB",
    "wof:name": "RG27 0HP",
    "wof:placetype": "postalcode"
  },
  "geometry": {"coordinates":[-1.025172,51.312222],"type":"Point"}
}
