{
  "type": "Feature",
  "properties": {
    "iso:country":"GB",
    "wof:name":"RG27 0HP",
    "wof:placetype":"postalcode"
},
  "geometry": {"coordinates":[-1.02517225745212,51.31222167044492],"type":"Point"}
}