{
  "type": "Feature",
  "properties": {
    "iso:country":"GB",
    "wof:name":"ST10 2NT",
    "wof:placetype":"postalcode"
},
  "geometry": {"coordinates":[-2.02132789386897,52.97391976774038],"type":"Point"}
}