{
  "type": "Feature",
  "properties": {
    "iso:country":"GB",
    "wof:name":"B10 9NA",
    "wof:placetype":"postalcode"
},
  "geometry": {"coordinates":[-1.8426691130136,52.47291773794701],"type":"Point"}
}