{
  "type": "Feature",
  "properties": {
    "date:inception_lower": "2021-11-01",
    "date:inception_upper": "2021-11-01",
    "iso:country": "GB",
    "wof:name": "SG5 4TJ",
    "wof:placetype": "postalcode"
  },
  "geometry": {"coordinates":[-0.223008,52.021861],"type":"Point"}
}
