{
  "type": "Feature",
  "properties": {
    "date:inception_lower": "1980-01-01",
    "date:inception_upper": "1980-01-01",
    "iso:country": "GB",
    "wof:name": "IP7 7EX",
    "wof:placetype": "postalcode"
  },
  "geometry": {"coordinates":[0.909575,52.104308],"type":"Point"}
}
