{
  "type": "Feature",
  "properties": {
    "date:inception_lower": "1980-01-01",
    "date:inception_upper": "1980-01-01",
    "iso:country": "GB",
    "wof:name": "BN8 4RX",
    "wof:placetype": "postalcode"
  },
  "geometry": {"coordinates":[0.01488,50.963094],"type":"Point"}
}
