{
  "type": "Feature",
  "properties": {
    "iso:country":"GB",
    "wof:name":"LS11 0LN",
    "wof:placetype":"postalcode"
},
  "geometry": {"coordinates":[-1.58331093839223,53.76756616068592],"type":"Point"}
}