{
  "type": "Feature",
  "properties": {
    "iso:country": "GB",
    "wof:name": "LS11 0LN",
    "wof:placetype": "postalcode"
  },
  "geometry": {"coordinates":[-1.583311,53.767566],"type":"Point"}
}
