{
  "type": "Feature",
  "properties": {
    "date:inception_lower": "1990-02-01",
    "date:inception_upper": "1990-02-01",
    "iso:country": "GB",
    "wof:name": "PO22 6PF",
    "wof:placetype": "postalcode"
  },
  "geometry": {"coordinates":[-0.622883,50.796579],"type":"Point"}
}
