{
  "type": "Feature",
  "properties": {
    "iso:country": "GB",
    "wof:name": "CA12 4QE",
    "wof:placetype": "postalcode"
  },
  "geometry": {"coordinates":[-3.190362,54.64397],"type":"Point"}
}
