{
  "type": "Feature",
  "properties": {
    "iso:country":"GB",
    "wof:name":"CA12 4QE",
    "wof:placetype":"postalcode"
},
  "geometry": {"coordinates":[-3.19036181266378,54.64396969676868],"type":"Point"}
}