{
  "type": "Feature",
  "properties": {
    "iso:country":"GB",
    "wof:name":"BH18 8AY",
    "wof:placetype":"postalcode"
},
  "geometry": {"coordinates":[-1.99661624429054,50.75981338413967],"type":"Point"}
}