{
  "type": "Feature",
  "properties": {
    "date:inception_lower": "2011-07-01",
    "date:inception_upper": "2011-07-01",
    "iso:country": "GB",
    "wof:name": "BH18 8AY",
    "wof:placetype": "postalcode"
  },
  "geometry": {"coordinates":[-1.996582,50.759732],"type":"Point"}
}
