{
  "type": "Feature",
  "properties": {
    "iso:country": "GB",
    "wof:name": "LS29 8NU",
    "wof:placetype": "postalcode"
  },
  "geometry": {"coordinates":[-1.80396,53.926379],"type":"Point"}
}
