{
  "type": "Feature",
  "properties": {
    "iso:country": "GB",
    "wof:name": "SL4 3AQ",
    "wof:placetype": "postalcode"
  },
  "geometry": {"coordinates":[-0.610547,51.475391],"type":"Point"}
}
