{
  "type": "Feature",
  "properties": {
    "iso:country": "GB",
    "wof:name": "WV8 2AZ",
    "wof:placetype": "postalcode"
  },
  "geometry": {"coordinates":[-2.209823,52.622849],"type":"Point"}
}
