{
  "type": "Feature",
  "properties": {
    "iso:country":"GB",
    "wof:name":"WV8 2AZ",
    "wof:placetype":"postalcode"
},
  "geometry": {"coordinates":[-2.20982267887678,52.62284942486036],"type":"Point"}
}