{
  "type": "Feature",
  "properties": {
    "iso:country":"GB",
    "wof:name":"HU10 6UU",
    "wof:placetype":"postalcode"
},
  "geometry": {"coordinates":[-0.42330231715199,53.73896568061744],"type":"Point"}
}