{
  "type": "Feature",
  "properties": {
    "iso:country": "GB",
    "wof:name": "WA15 6PG",
    "wof:placetype": "postalcode"
  },
  "geometry": {"coordinates":[-2.3249,53.400586],"type":"Point"}
}
