{
  "type": "Feature",
  "properties": {
    "iso:country":"GB",
    "wof:name":"PL22 0JN",
    "wof:placetype":"postalcode"
},
  "geometry": {"coordinates":[-4.67589383845842,50.39303269018249],"type":"Point"}
}