{
  "type": "Feature",
  "properties": {
    "iso:country": "GB",
    "wof:name": "PL22 0JN",
    "wof:placetype": "postalcode"
  },
  "geometry": {"coordinates":[-4.675894,50.393033],"type":"Point"}
}
