{
  "type": "Feature",
  "properties": {
    "iso:country":"GB",
    "wof:name":"NP13 3DY",
    "wof:placetype":"postalcode"
},
  "geometry": {"coordinates":[-3.15920530620134,51.75959761339548],"type":"Point"}
}