{
  "type": "Feature",
  "properties": {
    "date:inception_lower": "1980-01-01",
    "date:inception_upper": "1980-01-01",
    "iso:country": "GB",
    "wof:name": "B31 1EU",
    "wof:placetype": "postalcode"
  },
  "geometry": {"coordinates":[-1.982661,52.427612],"type":"Point"}
}
