{
  "type": "Feature",
  "properties": {
    "iso:country":"GB",
    "wof:name":"B31 1EU",
    "wof:placetype":"postalcode"
},
  "geometry": {"coordinates":[-1.9826609473397,52.42761225993104],"type":"Point"}
}