{
  "type": "Feature",
  "properties": {
    "date:inception_lower": "1980-01-01",
    "date:inception_upper": "1980-01-01",
    "iso:country": "GB",
    "wof:name": "PE20 3RD",
    "wof:placetype": "postalcode"
  },
  "geometry": {"coordinates":[-0.15299,52.98086],"type":"Point"}
}
