{
  "type": "Feature",
  "properties": {
    "iso:country":"GB",
    "wof:name":"PE20 3RD",
    "wof:placetype":"postalcode"
},
  "geometry": {"coordinates":[-0.1529961061164,52.980837649753],"type":"Point"}
}