{
  "type": "Feature",
  "properties": {
    "iso:country": "GB",
    "wof:name": "PE20 3RD",
    "wof:placetype": "postalcode"
  },
  "geometry": {"coordinates":[-0.159107,52.97958],"type":"Point"}
}
