{
  "type": "Feature",
  "properties": {
    "iso:country":"GB",
    "wof:name":"ML12 6DX",
    "wof:placetype":"postalcode"
},
  "geometry": {"coordinates":[-3.53054100855814,55.62423148787632],"type":"Point"}
}