{
  "type": "Feature",
  "properties": {
    "date:inception_lower":"1980-01-01",
    "date:inception_upper":"1980-01-31",
    "iso:country":"GB",
    "wof:name":"ML12 6DX",
    "wof:placetype":"postalcode"
},
  "geometry": {"coordinates":[-3.530541,55.624231],"type":"Point"}
}