{
  "type": "Feature",
  "properties": {
    "iso:country": "GB",
    "wof:name": "ML12 6DX",
    "wof:placetype": "postalcode"
  },
  "geometry": {"coordinates":[-3.530541,55.624231],"type":"Point"}
}
