{
  "type": "Feature",
  "properties": {
    "iso:country": "GB",
    "wof:name": "SN6 8AR",
    "wof:placetype": "postalcode"
  },
  "geometry": {"coordinates":[-1.661858,51.596704],"type":"Point"}
}
