{
  "type": "Feature",
  "properties": {
    "date:inception_lower":"2015-10-01",
    "date:inception_upper":"2015-10-31",
    "iso:country":"GB",
    "wof:name":"LS25 2DT",
    "wof:placetype":"postalcode"
},
  "geometry": {"coordinates":[-1.380913,53.816172],"type":"Point"}
}