{
  "type": "Feature",
  "properties": {
    "iso:country":"GB",
    "wof:name":"LS25 2DT",
    "wof:placetype":"postalcode"
},
  "geometry": {"coordinates":[-1.38091283664111,53.8161719224766],"type":"Point"}
}