{
  "type": "Feature",
  "properties": {
    "iso:country":"GB",
    "wof:name":"BB3 1EQ",
    "wof:placetype":"postalcode"
},
  "geometry": {"coordinates":[-2.47302604489511,53.70329668840527],"type":"Point"}
}