{
  "type": "Feature",
  "properties": {
    "iso:country": "GB",
    "wof:name": "BB3 1EQ",
    "wof:placetype": "postalcode"
  },
  "geometry": {"coordinates":[-2.473026,53.703297],"type":"Point"}
}
