{
  "type": "Feature",
  "properties": {
    "iso:country":"GB",
    "wof:name":"AB22 8DD",
    "wof:placetype":"postalcode"
},
  "geometry": {"coordinates":[-2.12904101840272,57.18631728734002],"type":"Point"}
}