{
  "type": "Feature",
  "properties": {
    "iso:country": "GB",
    "wof:name": "AB22 8DD",
    "wof:placetype": "postalcode"
  },
  "geometry": {"coordinates":[-2.129041,57.186317],"type":"Point"}
}
