{
  "type": "Feature",
  "properties": {
    "iso:country": "GB",
    "wof:name": "G52 1AW",
    "wof:placetype": "postalcode"
  },
  "geometry": {"coordinates":[-4.328426,55.848606],"type":"Point"}
}
