{
  "type": "Feature",
  "properties": {
    "iso:country":"GB",
    "wof:name":"G52 1AW",
    "wof:placetype":"postalcode"
},
  "geometry": {"coordinates":[-4.32832618719472,55.84856846978543],"type":"Point"}
}