{
  "type": "Feature",
  "properties": {
    "date:inception_lower": "1980-01-01",
    "date:inception_upper": "1980-01-01",
    "iso:country": "GB",
    "wof:name": "CM1 4PG",
    "wof:placetype": "postalcode"
  },
  "geometry": {"coordinates":[0.378553,51.749604],"type":"Point"}
}
