{
  "type": "Feature",
  "properties": {
    "date:inception_lower": "1991-09-01",
    "date:inception_upper": "1991-09-01",
    "iso:country": "GB",
    "wof:name": "CB6 3UQ",
    "wof:placetype": "postalcode"
  },
  "geometry": {"coordinates":[0.147805,52.35271],"type":"Point"}
}
