{
  "type": "Feature",
  "properties": {
    "iso:country":"GB",
    "wof:name":"N4 2QJ",
    "wof:placetype":"postalcode"
},
  "geometry": {"coordinates":[-0.10516206384102,51.56111660061809],"type":"Point"}
}