{
  "type": "Feature",
  "properties": {
    "iso:country":"GB",
    "wof:name":"W1U 1EA",
    "wof:placetype":"postalcode"
},
  "geometry": {"coordinates":[-0.15098549342178,51.51550951435158],"type":"Point"}
}