{
  "type": "Feature",
  "properties": {
    "iso:country":"GB",
    "wof:name":"PH39 4NP",
    "wof:placetype":"postalcode"
},
  "geometry": {"coordinates":[-5.84112947502152,56.91044063536864],"type":"Point"}
}