{
  "type": "Feature",
  "properties": {
    "iso:country": "GB",
    "wof:name": "NE33 3NA",
    "wof:placetype": "postalcode"
  },
  "geometry": {"coordinates":[-1.415798,54.996248],"type":"Point"}
}
