{
  "type": "Feature",
  "properties": {
    "date:inception_lower":"2003-08-01",
    "date:inception_upper":"2003-08-31",
    "iso:country":"GB",
    "wof:name":"NE33 3NA",
    "wof:placetype":"postalcode"
},
  "geometry": {"coordinates":[-1.415798,54.996248],"type":"Point"}
}