{
  "type": "Feature",
  "properties": {
    "iso:country":"GB",
    "wof:name":"DG12 6ET",
    "wof:placetype":"postalcode"
},
  "geometry": {"coordinates":[-3.25955100733021,54.98240928072394],"type":"Point"}
}