{
  "type": "Feature",
  "properties": {
    "iso:country": "GB",
    "wof:name": "DG12 6ET",
    "wof:placetype": "postalcode"
  },
  "geometry": {"coordinates":[-3.259551,54.982409],"type":"Point"}
}
