{
  "type": "Feature",
  "properties": {
    "date:inception_lower":"2016-05-01",
    "date:inception_upper":"2016-05-31",
    "iso:country":"GB",
    "wof:name":"IP8 4DW",
    "wof:placetype":"postalcode"
},
  "geometry": {"coordinates":[1.103664,52.08861],"type":"Point"}
}