{
  "type": "Feature",
  "properties": {
    "iso:country": "GB",
    "wof:name": "NR23 1HX",
    "wof:placetype": "postalcode"
  },
  "geometry": {"coordinates":[0.853418,52.950969],"type":"Point"}
}
