{
  "type": "Feature",
  "properties": {
    "iso:country":"GB",
    "wof:name":"UB3 4HQ",
    "wof:placetype":"postalcode"
},
  "geometry": {"coordinates":[-0.4138201754,51.49701247523829],"type":"Point"}
}