{
  "type": "Feature",
  "properties": {
    "date:inception_lower": "1980-01-01",
    "date:inception_upper": "1980-01-01",
    "iso:country": "GB",
    "wof:name": "CV4 8AW",
    "wof:placetype": "postalcode"
  },
  "geometry": {"coordinates":[-1.58973,52.394635],"type":"Point"}
}
