{
  "type": "Feature",
  "properties": {
    "iso:country":"GB",
    "wof:name":"B74 2QW",
    "wof:placetype":"postalcode"
},
  "geometry": {"coordinates":[-1.83482378986401,52.57487950161133],"type":"Point"}
}