{
  "type": "Feature",
  "properties": {
    "iso:country":"GB",
    "wof:name":"AB42 1SQ",
    "wof:placetype":"postalcode"
},
  "geometry": {"coordinates":[-1.79391430781208,57.50699800365181],"type":"Point"}
}