{
  "type": "Feature",
  "properties": {
    "iso:country":"GB",
    "wof:name":"LE3 6PQ",
    "wof:placetype":"postalcode"
},
  "geometry": {"coordinates":[-1.19750664562402,52.63736453588821],"type":"Point"}
}