{
  "type": "Feature",
  "properties": {
    "date:inception_lower": "1980-01-01",
    "date:inception_upper": "1980-01-01",
    "iso:country": "GB",
    "wof:name": "LE3 6PQ",
    "wof:placetype": "postalcode"
  },
  "geometry": {"coordinates":[-1.197507,52.637365],"type":"Point"}
}
