{
  "type": "Feature",
  "properties": {
    "iso:country": "GB",
    "wof:name": "LE3 6PQ",
    "wof:placetype": "postalcode"
  },
  "geometry": {"coordinates":[-1.197507,52.637365],"type":"Point"}
}
