{
  "type": "Feature",
  "properties": {
    "date:inception_lower": "2020-07-01",
    "date:inception_upper": "2020-07-01",
    "iso:country": "GB",
    "wof:name": "SE7 7GJ",
    "wof:placetype": "postalcode"
  },
  "geometry": {"coordinates":[0.024547,51.485607],"type":"Point"}
}
