{
  "type": "Feature",
  "properties": {
    "date:inception_lower": "2000-10-01",
    "date:inception_upper": "2000-10-01",
    "iso:country": "GB",
    "wof:name": "WD19 6TT",
    "wof:placetype": "postalcode"
  },
  "geometry": {"coordinates":[-0.39437,51.618718],"type":"Point"}
}
