{
  "type": "Feature",
  "properties": {
    "iso:country": "GB",
    "wof:name": "HP19 0ZJ",
    "wof:placetype": "postalcode"
  },
  "geometry": {"coordinates":[-0.806006,51.836734],"type":"Point"}
}
