{
  "type": "Feature",
  "properties": {
    "date:inception_lower": "2000-06-01",
    "date:inception_upper": "2000-06-01",
    "iso:country": "GB",
    "wof:name": "HP19 0ZJ",
    "wof:placetype": "postalcode"
  },
  "geometry": {"coordinates":[-0.806006,51.836734],"type":"Point"}
}
