{
  "type": "Feature",
  "properties": {
    "iso:country":"GB",
    "wof:name":"TA21 0EB",
    "wof:placetype":"postalcode"
},
  "geometry": {"coordinates":[-3.26370417347538,50.97130228197216],"type":"Point"}
}