{
  "type": "Feature",
  "properties": {
    "date:inception_lower":"1980-01-01",
    "date:inception_upper":"1980-01-31",
    "iso:country":"GB",
    "wof:name":"TA21 0EB",
    "wof:placetype":"postalcode"
},
  "geometry": {"coordinates":[-3.263704,50.971302],"type":"Point"}
}