{
  "type": "Feature",
  "properties": {
    "date:inception_lower": "1980-01-01",
    "date:inception_upper": "1980-01-01",
    "iso:country": "GB",
    "wof:name": "TF10 7TB",
    "wof:placetype": "postalcode"
  },
  "geometry": {"coordinates":[-2.37152,52.774639],"type":"Point"}
}
