{
  "type": "Feature",
  "properties": {
    "iso:country":"GB",
    "wof:name":"LS9 9DH",
    "wof:placetype":"postalcode"
},
  "geometry": {"coordinates":[-1.50724229787058,53.79621044200579],"type":"Point"}
}