{
  "type": "Feature",
  "properties": {
    "iso:country": "GB",
    "wof:name": "BS15 4HP",
    "wof:placetype": "postalcode"
  },
  "geometry": {"coordinates":[-2.491548,51.462474],"type":"Point"}
}
