{
  "type": "Feature",
  "properties": {
    "iso:country":"GB",
    "wof:name":"CH7 3PF",
    "wof:placetype":"postalcode"
},
  "geometry": {"coordinates":[-3.08427779203369,53.17520268039749],"type":"Point"}
}