{
  "type": "Feature",
  "properties": {
    "iso:country": "GB",
    "wof:name": "CH7 3PF",
    "wof:placetype": "postalcode"
  },
  "geometry": {"coordinates":[-3.083811,53.175115],"type":"Point"}
}
