{
  "type": "Feature",
  "properties": {
    "date:inception_lower":"1980-01-01",
    "date:inception_upper":"1980-01-31",
    "iso:country":"GB",
    "wof:name":"TR16 6LB",
    "wof:placetype":"postalcode"
},
  "geometry": {"coordinates":[-5.260286,50.208002],"type":"Point"}
}