{
  "type": "Feature",
  "properties": {
    "iso:country":"GB",
    "wof:name":"TR16 6LB",
    "wof:placetype":"postalcode"
},
  "geometry": {"coordinates":[-5.26021192224377,50.20805785641255],"type":"Point"}
}