{
  "type": "Feature",
  "properties": {
    "iso:country":"GB",
    "wof:name":"KT22 8UL",
    "wof:placetype":"postalcode"
},
  "geometry": {"coordinates":[-0.32237944870097,51.2958914108205],"type":"Point"}
}