{
  "type": "Feature",
  "properties": {
    "iso:country":"GB",
    "wof:name":"SS11 7LX",
    "wof:placetype":"postalcode"
},
  "geometry": {"coordinates":[0.51525503670907,51.62676100675873],"type":"Point"}
}