{
  "type": "Feature",
  "properties": {
    "iso:country":"GB",
    "wof:name":"DE73 8ER",
    "wof:placetype":"postalcode"
},
  "geometry": {"coordinates":[-1.42705124575862,52.82187033706483],"type":"Point"}
}