{
  "type": "Feature",
  "properties": {
    "iso:country": "GB",
    "wof:name": "B90 1NP",
    "wof:placetype": "postalcode"
  },
  "geometry": {"coordinates":[-1.866614,52.406996],"type":"Point"}
}
