{
  "type": "Feature",
  "properties": {
    "iso:country":"GB",
    "wof:name":"B90 1NP",
    "wof:placetype":"postalcode"
},
  "geometry": {"coordinates":[-1.86661411398031,52.40699627885898],"type":"Point"}
}