{
  "type": "Feature",
  "properties": {
    "iso:country":"GB",
    "wof:name":"M34 5AN",
    "wof:placetype":"postalcode"
},
  "geometry": {"coordinates":[-2.11264541437765,53.46498215035605],"type":"Point"}
}