{
  "type": "Feature",
  "properties": {
    "date:inception_lower": "2012-04-01",
    "date:inception_upper": "2012-04-01",
    "iso:country": "GB",
    "wof:name": "CF35 6DF",
    "wof:placetype": "postalcode"
  },
  "geometry": {"coordinates":[-3.561051,51.529247],"type":"Point"}
}
