{
  "type": "Feature",
  "properties": {
    "date:inception_lower": "1980-01-01",
    "date:inception_upper": "1980-01-01",
    "iso:country": "GB",
    "wof:name": "PL5 3RG",
    "wof:placetype": "postalcode"
  },
  "geometry": {"coordinates":[-4.160002,50.41496],"type":"Point"}
}
