{
  "type": "Feature",
  "properties": {
    "date:inception_lower": "1992-10-01",
    "date:inception_upper": "1992-10-01",
    "iso:country": "GB",
    "wof:name": "G21 1NB",
    "wof:placetype": "postalcode"
  },
  "geometry": {"coordinates":[-4.23587,55.884355],"type":"Point"}
}
