{
  "type": "Feature",
  "properties": {
    "iso:country":"GB",
    "wof:name":"EX14 9PT",
    "wof:placetype":"postalcode"
},
  "geometry": {"coordinates":[-3.13774536883433,50.85069193501872],"type":"Point"}
}