{
  "type": "Feature",
  "properties": {
    "iso:country":"GB",
    "wof:name":"SN12 7BL",
    "wof:placetype":"postalcode"
},
  "geometry": {"coordinates":[-2.12581006112102,51.37691153761896],"type":"Point"}
}