{
  "type": "Feature",
  "properties": {
    "iso:country": "GB",
    "wof:name": "SN12 7BL",
    "wof:placetype": "postalcode"
  },
  "geometry": {"coordinates":[-2.12581,51.376912],"type":"Point"}
}
