{
  "type": "Feature",
  "properties": {
    "iso:country":"GB",
    "wof:name":"SW3 1LE",
    "wof:placetype":"postalcode"
},
  "geometry": {"coordinates":[-0.16634169310299,51.49739692304995],"type":"Point"}
}