{
  "type": "Feature",
  "properties": {
    "iso:country": "GB",
    "wof:name": "BD4 6NT",
    "wof:placetype": "postalcode"
  },
  "geometry": {"coordinates":[-1.696013,53.761586],"type":"Point"}
}
