{
  "type": "Feature",
  "properties": {
    "iso:country":"GB",
    "wof:name":"BD4 6NT",
    "wof:placetype":"postalcode"
},
  "geometry": {"coordinates":[-1.69601312780671,53.7615860465525],"type":"Point"}
}