{
  "type": "Feature",
  "properties": {
    "iso:country": "GB",
    "wof:name": "LL11 2SQ",
    "wof:placetype": "postalcode"
  },
  "geometry": {"coordinates":[-2.98869,53.06205],"type":"Point"}
}
