{
  "type": "Feature",
  "properties": {
    "iso:country":"GB",
    "wof:name":"LL11 2SQ",
    "wof:placetype":"postalcode"
},
  "geometry": {"coordinates":[-2.98869039343658,53.06204956629135],"type":"Point"}
}