{
  "type": "Feature",
  "properties": {
    "date:inception_lower": "1985-10-01",
    "date:inception_upper": "1985-10-01",
    "iso:country": "GB",
    "wof:name": "LL11 2SQ",
    "wof:placetype": "postalcode"
  },
  "geometry": {"coordinates":[-2.98869,53.06205],"type":"Point"}
}
