{
  "type": "Feature",
  "properties": {
    "iso:country":"GB",
    "wof:name":"GL12 7DW",
    "wof:placetype":"postalcode"
},
  "geometry": {"coordinates":[-2.35188326687696,51.63863309769073],"type":"Point"}
}