{
  "type": "Feature",
  "properties": {
    "iso:country": "GB",
    "wof:name": "GL12 7DW",
    "wof:placetype": "postalcode"
  },
  "geometry": {"coordinates":[-2.351883,51.638633],"type":"Point"}
}
