{
  "type": "Feature",
  "properties": {
    "iso:country":"GB",
    "wof:name":"DD2 1JG",
    "wof:placetype":"postalcode"
},
  "geometry": {"coordinates":[-3.00738092360713,56.45925087038933],"type":"Point"}
}