{
  "type": "Feature",
  "properties": {
    "iso:country":"GB",
    "wof:name":"IP30 0HB",
    "wof:placetype":"postalcode"
},
  "geometry": {"coordinates":[0.79605373082118,52.16124288148923],"type":"Point"}
}