{
  "type": "Feature",
  "properties": {
    "iso:country":"GB",
    "wof:name":"CB3 0PZ",
    "wof:placetype":"postalcode"
},
  "geometry": {"coordinates":[0.07876004709618,52.23684562865635],"type":"Point"}
}