{
  "type": "Feature",
  "properties": {
    "iso:country": "GB",
    "wof:name": "CB3 0PZ",
    "wof:placetype": "postalcode"
  },
  "geometry": {"coordinates":[0.07876,52.236846],"type":"Point"}
}
