{
  "type": "Feature",
  "properties": {
    "date:inception_lower": "1980-01-01",
    "date:inception_upper": "1980-01-01",
    "iso:country": "GB",
    "wof:name": "FK10 4HS",
    "wof:placetype": "postalcode"
  },
  "geometry": {"coordinates":[-3.756619,56.110127],"type":"Point"}
}
