{
  "type": "Feature",
  "properties": {
    "iso:country":"GB",
    "wof:name":"FK10 4HS",
    "wof:placetype":"postalcode"
},
  "geometry": {"coordinates":[-3.75661891801059,56.11012651181951],"type":"Point"}
}