{
  "type": "Feature",
  "properties": {
    "date:inception_lower": "2022-10-01",
    "date:inception_upper": "2022-10-01",
    "iso:country": "GB",
    "wof:name": "HD6 3FE",
    "wof:placetype": "postalcode"
  },
  "geometry": {"coordinates":[-1.800721,53.681916],"type":"Point"}
}
