{
  "type": "Feature",
  "properties": {
    "iso:country":"GB",
    "wof:name":"ST17 9XF",
    "wof:placetype":"postalcode"
},
  "geometry": {"coordinates":[-2.14528988794584,52.79371303807451],"type":"Point"}
}