{
  "type": "Feature",
  "properties": {
    "iso:country": "GB",
    "wof:name": "ST17 9XF",
    "wof:placetype": "postalcode"
  },
  "geometry": {"coordinates":[-2.14529,52.793713],"type":"Point"}
}
