{
  "type": "Feature",
  "properties": {
    "date:inception_lower": "1984-10-01",
    "date:inception_upper": "1984-10-01",
    "iso:country": "GB",
    "wof:name": "ST17 9XF",
    "wof:placetype": "postalcode"
  },
  "geometry": {"coordinates":[-2.14529,52.793713],"type":"Point"}
}
