{
  "type": "Feature",
  "properties": {
    "iso:country":"GB",
    "wof:name":"NG1 6LF",
    "wof:placetype":"postalcode"
},
  "geometry": {"coordinates":[-1.15350837895353,52.95480974531838],"type":"Point"}
}