{
  "type": "Feature",
  "properties": {
    "date:inception_lower": "1980-01-01",
    "date:inception_upper": "1980-01-01",
    "iso:country": "GB",
    "wof:name": "NG1 6LF",
    "wof:placetype": "postalcode"
  },
  "geometry": {"coordinates":[-1.153744,52.954832],"type":"Point"}
}
