{
  "type": "Feature",
  "properties": {
    "date:inception_lower": "2000-12-01",
    "date:inception_upper": "2000-12-01",
    "iso:country": "GB",
    "wof:name": "TF1 2HH",
    "wof:placetype": "postalcode"
  },
  "geometry": {"coordinates":[-2.502208,52.691344],"type":"Point"}
}
