{
  "type": "Feature",
  "properties": {
    "iso:country":"GB",
    "wof:name":"KT6 4TL",
    "wof:placetype":"postalcode"
},
  "geometry": {"coordinates":[-0.30170397118903,51.39861217612273],"type":"Point"}
}