{
  "type": "Feature",
  "properties": {
    "date:inception_lower": "2021-11-01",
    "date:inception_upper": "2021-11-01",
    "iso:country": "GB",
    "wof:name": "ME15 8ZB",
    "wof:placetype": "postalcode"
  },
  "geometry": {"coordinates":[0.56691,51.246167],"type":"Point"}
}
