{
  "type": "Feature",
  "properties": {
    "iso:country":"GB",
    "wof:name":"WF4 4LZ",
    "wof:placetype":"postalcode"
},
  "geometry": {"coordinates":[-1.5853532440956,53.64325792838608],"type":"Point"}
}