{
  "type": "Feature",
  "properties": {
    "iso:country":"GB",
    "wof:name":"SW15 5FH",
    "wof:placetype":"postalcode"
},
  "geometry": {"coordinates":[-0.24258066417133,51.45399760241234],"type":"Point"}
}