{
  "type": "Feature",
  "properties": {
    "iso:country":"GB",
    "wof:name":"PO33 2PJ",
    "wof:placetype":"postalcode"
},
  "geometry": {"coordinates":[-1.16308572024631,50.72979808026214],"type":"Point"}
}