{
  "type": "Feature",
  "properties": {
    "iso:country":"GB",
    "wof:name":"WR14 2NQ",
    "wof:placetype":"postalcode"
},
  "geometry": {"coordinates":[-2.31309989504549,52.12766842664269],"type":"Point"}
}