{
  "type": "Feature",
  "properties": {
    "date:inception_lower":"1998-12-01",
    "date:inception_upper":"1998-12-31",
    "iso:country":"GB",
    "wof:name":"CV21 1TN",
    "wof:placetype":"postalcode"
},
  "geometry": {"coordinates":[-1.265162,52.399332],"type":"Point"}
}