{
  "type": "Feature",
  "properties": {
    "iso:country":"GB",
    "wof:name":"CV21 1TN",
    "wof:placetype":"postalcode"
},
  "geometry": {"coordinates":[-1.26516252183033,52.39933216747425],"type":"Point"}
}