{
  "type": "Feature",
  "properties": {
    "iso:country": "GB",
    "wof:name": "CV21 1TN",
    "wof:placetype": "postalcode"
  },
  "geometry": {"coordinates":[-1.265162,52.399332],"type":"Point"}
}
