{
  "type": "Feature",
  "properties": {
    "iso:country":"GB",
    "wof:name":"NP20 5PG",
    "wof:placetype":"postalcode"
},
  "geometry": {"coordinates":[-3.00214343049713,51.59917696273845],"type":"Point"}
}