{
  "type": "Feature",
  "properties": {
    "iso:country":"GB",
    "wof:name":"TR2 4LT",
    "wof:placetype":"postalcode"
},
  "geometry": {"coordinates":[-4.96082018620675,50.29248958886368],"type":"Point"}
}