{
  "type": "Feature",
  "properties": {
    "iso:country":"GB",
    "wof:name":"G84 9BU",
    "wof:placetype":"postalcode"
},
  "geometry": {"coordinates":[-4.72457536251892,56.01262126929534],"type":"Point"}
}