{
  "type": "Feature",
  "properties": {
    "iso:country": "GB",
    "wof:name": "G84 9BU",
    "wof:placetype": "postalcode"
  },
  "geometry": {"coordinates":[-4.724575,56.012621],"type":"Point"}
}
