{
  "type": "Feature",
  "properties": {
    "iso:country":"GB",
    "wof:name":"SO19 6ED",
    "wof:placetype":"postalcode"
},
  "geometry": {"coordinates":[-1.33904753717975,50.90897307774377],"type":"Point"}
}