{
  "type": "Feature",
  "properties": {
    "date:inception_lower": "1990-07-01",
    "date:inception_upper": "1990-07-01",
    "iso:country": "GB",
    "wof:name": "SE4 2EP",
    "wof:placetype": "postalcode"
  },
  "geometry": {"coordinates":[-0.039757,51.464567],"type":"Point"}
}
