{
  "type": "Feature",
  "properties": {
    "date:inception_lower":"1985-10-01",
    "date:inception_upper":"1985-10-31",
    "iso:country":"GB",
    "wof:name":"TF3 1ED",
    "wof:placetype":"postalcode"
},
  "geometry": {"coordinates":[-2.451865,52.651704],"type":"Point"}
}