{
  "type": "Feature",
  "properties": {
    "iso:country":"GB",
    "wof:name":"TF3 1ED",
    "wof:placetype":"postalcode"
},
  "geometry": {"coordinates":[-2.4518647453729,52.65170444907644],"type":"Point"}
}