{
  "type": "Feature",
  "properties": {
    "date:inception_lower":"2008-02-01",
    "date:inception_upper":"2008-02-29",
    "iso:country":"GB",
    "wof:name":"NN10 0FS",
    "wof:placetype":"postalcode"
},
  "geometry": {"coordinates":[-0.590262,52.285834],"type":"Point"}
}