{
  "type": "Feature",
  "properties": {
    "iso:country": "GB",
    "wof:name": "PA21 2BW",
    "wof:placetype": "postalcode"
  },
  "geometry": {"coordinates":[-5.269269,55.883742],"type":"Point"}
}
