{
  "type": "Feature",
  "properties": {
    "date:inception_lower": "1980-01-01",
    "date:inception_upper": "1980-01-01",
    "iso:country": "GB",
    "wof:name": "PA21 2BW",
    "wof:placetype": "postalcode"
  },
  "geometry": {"coordinates":[-5.270099,55.883909],"type":"Point"}
}
