{
  "type": "Feature",
  "properties": {
    "iso:country": "GB",
    "wof:name": "KA6 6DE",
    "wof:placetype": "postalcode"
  },
  "geometry": {"coordinates":[-4.584171,55.395163],"type":"Point"}
}
