{
  "type": "Feature",
  "properties": {
    "iso:country":"GB",
    "wof:name":"NG9 1QX",
    "wof:placetype":"postalcode"
},
  "geometry": {"coordinates":[-1.20201692832243,52.92339431769138],"type":"Point"}
}