{
  "type": "Feature",
  "properties": {
    "iso:country":"GB",
    "wof:name":"RG5 4LF",
    "wof:placetype":"postalcode"
},
  "geometry": {"coordinates":[-0.90569647726928,51.45873422001636],"type":"Point"}
}