{
  "type": "Feature",
  "properties": {
    "iso:country":"GB",
    "wof:name":"W1J 0DL",
    "wof:placetype":"postalcode"
},
  "geometry": {"coordinates":[-0.136609145977,51.50931996349465],"type":"Point"}
}