{
  "type": "Feature",
  "properties": {
    "date:inception_lower": "2000-12-01",
    "date:inception_upper": "2000-12-01",
    "iso:country": "GB",
    "wof:name": "W1J 0DL",
    "wof:placetype": "postalcode"
  },
  "geometry": {"coordinates":[-0.136609,51.50932],"type":"Point"}
}
