{
  "type": "Feature",
  "properties": {
    "iso:country": "GB",
    "wof:name": "PE19 6GP",
    "wof:placetype": "postalcode"
  },
  "geometry": {"coordinates":[-0.243205,52.230991],"type":"Point"}
}
