{
  "type": "Feature",
  "properties": {
    "date:inception_lower":"2011-02-01",
    "date:inception_upper":"2011-02-28",
    "iso:country":"GB",
    "wof:name":"PE19 6GP",
    "wof:placetype":"postalcode"
},
  "geometry": {"coordinates":[-0.243205,52.230991],"type":"Point"}
}