{
  "type": "Feature",
  "properties": {
    "iso:country": "GB",
    "wof:name": "GL51 0XX",
    "wof:placetype": "postalcode"
  },
  "geometry": {"coordinates":[-2.136582,51.898905],"type":"Point"}
}
