{
  "type": "Feature",
  "properties": {
    "date:inception_lower": "2021-11-01",
    "date:inception_upper": "2021-11-01",
    "iso:country": "GB",
    "wof:name": "WA4 1DF",
    "wof:placetype": "postalcode"
  },
  "geometry": {"coordinates":[-2.564833,53.377856],"type":"Point"}
}
