{
  "type": "Feature",
  "properties": {
    "date:inception_lower": "2011-03-01",
    "date:inception_upper": "2011-03-01",
    "iso:country": "GB",
    "wof:name": "PE6 0GA",
    "wof:placetype": "postalcode"
  },
  "geometry": {"coordinates":[-0.164452,52.662457],"type":"Point"}
}
