{
  "type": "Feature",
  "properties": {
    "iso:country":"GB",
    "wof:name":"BD4 8PQ",
    "wof:placetype":"postalcode"
},
  "geometry": {"coordinates":[-1.71751166758309,53.78579839426564],"type":"Point"}
}