{
  "type": "Feature",
  "properties": {
    "iso:country":"GB",
    "wof:name":"G75 0HP",
    "wof:placetype":"postalcode"
},
  "geometry": {"coordinates":[-4.17494893046174,55.75824947250631],"type":"Point"}
}