{
  "type": "Feature",
  "properties": {
    "iso:country":"GB",
    "wof:name":"RG21 5QZ",
    "wof:placetype":"postalcode"
},
  "geometry": {"coordinates":[-1.08497436392468,51.27753622511607],"type":"Point"}
}