{
  "type": "Feature",
  "properties": {
    "date:inception_lower":"1995-07-01",
    "date:inception_upper":"1995-07-31",
    "iso:country":"GB",
    "wof:name":"RG21 5QZ",
    "wof:placetype":"postalcode"
},
  "geometry": {"coordinates":[-1.084974,51.277536],"type":"Point"}
}