{
  "type": "Feature",
  "properties": {
    "iso:country": "GB",
    "wof:name": "RG21 5QZ",
    "wof:placetype": "postalcode"
  },
  "geometry": {"coordinates":[-1.084974,51.277536],"type":"Point"}
}
