{
  "type": "Feature",
  "properties": {
    "iso:country":"GB",
    "wof:name":"HD8 9LJ",
    "wof:placetype":"postalcode"
},
  "geometry": {"coordinates":[-1.60175652413253,53.58792770689428],"type":"Point"}
}