{
  "type": "Feature",
  "properties": {
    "iso:country": "GB",
    "wof:name": "HD8 9LJ",
    "wof:placetype": "postalcode"
  },
  "geometry": {"coordinates":[-1.601756,53.587928],"type":"Point"}
}
