{
  "type": "Feature",
  "properties": {
    "date:inception_lower": "1992-08-01",
    "date:inception_upper": "1992-08-01",
    "iso:country": "GB",
    "wof:name": "SK2 5LA",
    "wof:placetype": "postalcode"
  },
  "geometry": {"coordinates":[-2.123217,53.396578],"type":"Point"}
}
