{
  "type": "Feature",
  "properties": {
    "iso:country": "GB",
    "wof:name": "SK2 5LA",
    "wof:placetype": "postalcode"
  },
  "geometry": {"coordinates":[-2.123217,53.396578],"type":"Point"}
}
