{
  "type": "Feature",
  "properties": {
    "iso:country":"GB",
    "wof:name":"BN20 8TD",
    "wof:placetype":"postalcode"
},
  "geometry": {"coordinates":[0.24851213422024,50.77734223522238],"type":"Point"}
}