{
  "type": "Feature",
  "properties": {
    "iso:country":"GB",
    "wof:name":"NN14 6EA",
    "wof:placetype":"postalcode"
},
  "geometry": {"coordinates":[-0.79312602968439,52.42259005009741],"type":"Point"}
}