{
  "type": "Feature",
  "properties": {
    "iso:country":"GB",
    "wof:name":"YO30 7AN",
    "wof:placetype":"postalcode"
},
  "geometry": {"coordinates":[-1.0897949939377,53.96863448301423],"type":"Point"}
}