{
  "type": "Feature",
  "properties": {
    "iso:country": "GB",
    "wof:name": "HP13 5JA",
    "wof:placetype": "postalcode"
  },
  "geometry": {"coordinates":[-0.78116,51.643907],"type":"Point"}
}
