{
  "type": "Feature",
  "properties": {
    "iso:country":"GB",
    "wof:name":"CF72 9AW",
    "wof:placetype":"postalcode"
},
  "geometry": {"coordinates":[-3.38408795126498,51.52587573729218],"type":"Point"}
}