{
  "type": "Feature",
  "properties": {
    "date:inception_lower": "1980-01-01",
    "date:inception_upper": "1980-01-01",
    "iso:country": "GB",
    "wof:name": "WS6 6NT",
    "wof:placetype": "postalcode"
  },
  "geometry": {"coordinates":[-2.00911,52.666393],"type":"Point"}
}
