{
  "type": "Feature",
  "properties": {
    "iso:country":"GB",
    "wof:name":"WS6 6NT",
    "wof:placetype":"postalcode"
},
  "geometry": {"coordinates":[-2.00911009539833,52.66639267094913],"type":"Point"}
}