{
  "type": "Feature",
  "properties": {
    "iso:country":"GB",
    "wof:name":"NR6 5RB",
    "wof:placetype":"postalcode"
},
  "geometry": {"coordinates":[1.25487640833248,52.66286598600304],"type":"Point"}
}