{
  "type": "Feature",
  "properties": {
    "iso:country":"GB",
    "wof:name":"BN1 7HU",
    "wof:placetype":"postalcode"
},
  "geometry": {"coordinates":[-0.13213326041521,50.84293171972772],"type":"Point"}
}