{
  "type": "Feature",
  "properties": {
    "iso:country":"GB",
    "wof:name":"N9 8EN",
    "wof:placetype":"postalcode"
},
  "geometry": {"coordinates":[-0.04001822633065,51.63466631909645],"type":"Point"}
}