{
  "type": "Feature",
  "properties": {
    "date:inception_lower":"1980-01-01",
    "date:inception_upper":"1980-01-31",
    "iso:country":"GB",
    "wof:name":"CO7 0PX",
    "wof:placetype":"postalcode"
},
  "geometry": {"coordinates":[1.026188,51.817134],"type":"Point"}
}