{
  "type": "Feature",
  "properties": {
    "iso:country":"GB",
    "wof:name":"CO7 0PX",
    "wof:placetype":"postalcode"
},
  "geometry": {"coordinates":[1.02618812003249,51.81713389557937],"type":"Point"}
}