{
  "type": "Feature",
  "properties": {
    "date:inception_lower":"1994-05-01",
    "date:inception_upper":"1994-05-31",
    "iso:country":"GB",
    "wof:name":"M8 9BE",
    "wof:placetype":"postalcode"
},
  "geometry": {"coordinates":[-2.246091,53.502218],"type":"Point"}
}