{
  "type": "Feature",
  "properties": {
    "iso:country":"GB",
    "wof:name":"G53 7HT",
    "wof:placetype":"postalcode"
},
  "geometry": {"coordinates":[-4.3402618271382,55.80713334562199],"type":"Point"}
}