{
  "type": "Feature",
  "properties": {
    "iso:country":"GB",
    "wof:name":"FK15 0JZ",
    "wof:placetype":"postalcode"
},
  "geometry": {"coordinates":[-3.94499297089654,56.18088349837316],"type":"Point"}
}