{
  "type": "Feature",
  "properties": {
    "date:inception_lower":"1980-01-01",
    "date:inception_upper":"1980-01-31",
    "iso:country":"GB",
    "wof:name":"BS11 0QE",
    "wof:placetype":"postalcode"
},
  "geometry": {"coordinates":[-2.658667,51.50137],"type":"Point"}
}