{
  "type": "Feature",
  "properties": {
    "iso:country":"GB",
    "wof:name":"NR27 0AJ",
    "wof:placetype":"postalcode"
},
  "geometry": {"coordinates":[1.306184891932,52.92787680650115],"type":"Point"}
}