{
  "type": "Feature",
  "properties": {
    "date:inception_lower": "2023-03-01",
    "date:inception_upper": "2023-03-01",
    "iso:country": "GB",
    "wof:name": "SO21 2FS",
    "wof:placetype": "postalcode"
  },
  "geometry": {"coordinates":[-1.378691,51.081811],"type":"Point"}
}
