{
  "type": "Feature",
  "properties": {
    "date:inception_lower": "1980-01-01",
    "date:inception_upper": "1980-01-01",
    "iso:country": "GB",
    "wof:name": "BA14 8PU",
    "wof:placetype": "postalcode"
  },
  "geometry": {"coordinates":[-2.208312,51.324782],"type":"Point"}
}
