{
  "type": "Feature",
  "properties": {
    "iso:country":"GB",
    "wof:name":"CR4 4EH",
    "wof:placetype":"postalcode"
},
  "geometry": {"coordinates":[-0.16960242943426,51.39903324415358],"type":"Point"}
}