{
  "type": "Feature",
  "properties": {
    "iso:country": "GB",
    "wof:name": "SE10 9FT",
    "wof:placetype": "postalcode"
  },
  "geometry": {"coordinates":[0.008568,51.484506],"type":"Point"}
}
