{
  "type": "Feature",
  "properties": {
    "iso:country":"GB",
    "wof:name":"SE10 9FT",
    "wof:placetype":"postalcode"
},
  "geometry": {"coordinates":[0.00850538373994,51.48465859146872],"type":"Point"}
}