{
  "type": "Feature",
  "properties": {
    "iso:country":"GB",
    "wof:name":"PH1 3UP",
    "wof:placetype":"postalcode"
},
  "geometry": {"coordinates":[-3.46477441457536,56.45068795332499],"type":"Point"}
}