{
  "type": "Feature",
  "properties": {
    "date:inception_lower": "1980-01-01",
    "date:inception_upper": "1980-01-01",
    "iso:country": "GB",
    "wof:name": "TD15 1DJ",
    "wof:placetype": "postalcode"
  },
  "geometry": {"coordinates":[-2.0038,55.771147],"type":"Point"}
}
