{
  "type": "Feature",
  "properties": {
    "iso:country":"GB",
    "wof:name":"TW2 7AG",
    "wof:placetype":"postalcode"
},
  "geometry": {"coordinates":[-0.36973377901987,51.45346066679167],"type":"Point"}
}