{
  "type": "Feature",
  "properties": {
    "date:inception_lower": "1992-08-01",
    "date:inception_upper": "1992-08-01",
    "iso:country": "GB",
    "wof:name": "TS17 7BT",
    "wof:placetype": "postalcode"
  },
  "geometry": {"coordinates":[-1.278792,54.556336],"type":"Point"}
}
