{
  "type": "Feature",
  "properties": {
    "iso:country": "GB",
    "wof:name": "TS17 7BT",
    "wof:placetype": "postalcode"
  },
  "geometry": {"coordinates":[-1.273468,54.55661],"type":"Point"}
}
