{
  "type": "Feature",
  "properties": {
    "iso:country":"GB",
    "wof:name":"TS17 7BT",
    "wof:placetype":"postalcode"
},
  "geometry": {"coordinates":[-1.27877886657314,54.55632317056344],"type":"Point"}
}