{
  "type": "Feature",
  "properties": {
    "iso:country": "GB",
    "wof:name": "CV35 0HR",
    "wof:placetype": "postalcode"
  },
  "geometry": {"coordinates":[-1.514355,52.15671],"type":"Point"}
}
