{
  "type": "Feature",
  "properties": {
    "iso:country":"GB",
    "wof:name":"BN9 9RR",
    "wof:placetype":"postalcode"
},
  "geometry": {"coordinates":[0.04560467182061,50.79411911760968],"type":"Point"}
}