{
  "type": "Feature",
  "properties": {
    "iso:country":"GB",
    "wof:name":"NW2 4AD",
    "wof:placetype":"postalcode"
},
  "geometry": {"coordinates":[-0.22122185241427,51.55351842619217],"type":"Point"}
}