{
  "type": "Feature",
  "properties": {
    "iso:country":"GB",
    "wof:name":"L32 8UQ",
    "wof:placetype":"postalcode"
},
  "geometry": {"coordinates":[-2.876925752335,53.47611687010053],"type":"Point"}
}