{
  "type": "Feature",
  "properties": {
    "date:inception_lower": "2008-03-01",
    "date:inception_upper": "2008-03-01",
    "iso:country": "GB",
    "wof:name": "L32 8UQ",
    "wof:placetype": "postalcode"
  },
  "geometry": {"coordinates":[-2.876926,53.476117],"type":"Point"}
}
