{
  "type": "Feature",
  "properties": {
    "iso:country": "GB",
    "wof:name": "PH26 3JF",
    "wof:placetype": "postalcode"
  },
  "geometry": {"coordinates":[-3.613775,57.332101],"type":"Point"}
}
