{
  "type": "Feature",
  "properties": {
    "iso:country":"GB",
    "wof:name":"LN2 3PG",
    "wof:placetype":"postalcode"
},
  "geometry": {"coordinates":[-0.50325339432942,53.33032374071806],"type":"Point"}
}