{
  "type": "Feature",
  "properties": {
    "iso:country":"GB",
    "wof:name":"HX5 0BB",
    "wof:placetype":"postalcode"
},
  "geometry": {"coordinates":[-1.84072093166932,53.6856374374492],"type":"Point"}
}