{
  "type": "Feature",
  "properties": {
    "date:inception_lower": "1980-01-01",
    "date:inception_upper": "1980-01-01",
    "iso:country": "GB",
    "wof:name": "HX5 0BB",
    "wof:placetype": "postalcode"
  },
  "geometry": {"coordinates":[-1.840721,53.685637],"type":"Point"}
}
