{
  "type": "Feature",
  "properties": {
    "date:inception_lower": "1993-01-01",
    "date:inception_upper": "1993-01-01",
    "iso:country": "GB",
    "wof:name": "SE1 5SJ",
    "wof:placetype": "postalcode"
  },
  "geometry": {"coordinates":[-0.075251,51.491792],"type":"Point"}
}
