{
  "type": "Feature",
  "properties": {
    "iso:country":"GB",
    "wof:name":"PL12 6PS",
    "wof:placetype":"postalcode"
},
  "geometry": {"coordinates":[-4.25777590849565,50.43594892465936],"type":"Point"}
}