{
  "type": "Feature",
  "properties": {
    "iso:country":"GB",
    "wof:name":"W1G 8JA",
    "wof:placetype":"postalcode"
},
  "geometry": {"coordinates":[-0.15112233224832,51.5188928472972],"type":"Point"}
}