{
  "type": "Feature",
  "properties": {
    "iso:country":"GB",
    "wof:name":"NR33 9QX",
    "wof:placetype":"postalcode"
},
  "geometry": {"coordinates":[1.71810693914245,52.46914731628531],"type":"Point"}
}