{
  "type": "Feature",
  "properties": {
    "iso:country":"GB",
    "wof:name":"SP8 4BX",
    "wof:placetype":"postalcode"
},
  "geometry": {"coordinates":[-2.28176863949279,51.04165435699124],"type":"Point"}
}