{
  "type": "Feature",
  "properties": {
    "iso:country":"GB",
    "wof:name":"RG5 4JU",
    "wof:placetype":"postalcode"
},
  "geometry": {"coordinates":[-0.90109480582078,51.45076033419005],"type":"Point"}
}