{
  "type": "Feature",
  "properties": {
    "iso:country": "GB",
    "wof:name": "RG5 4JU",
    "wof:placetype": "postalcode"
  },
  "geometry": {"coordinates":[-0.901061,51.45077],"type":"Point"}
}
