{
  "type": "Feature",
  "properties": {
    "iso:country":"GB",
    "wof:name":"SA1 6AZ",
    "wof:placetype":"postalcode"
},
  "geometry": {"coordinates":[-3.95357814273508,51.62070901246826],"type":"Point"}
}