{
  "type": "Feature",
  "properties": {
    "iso:country": "GB",
    "wof:name": "CA11 7QS",
    "wof:placetype": "postalcode"
  },
  "geometry": {"coordinates":[-2.75197,54.667032],"type":"Point"}
}
