{
  "type": "Feature",
  "properties": {
    "date:inception_lower": "1980-01-01",
    "date:inception_upper": "1980-01-01",
    "iso:country": "GB",
    "wof:name": "CA11 7QS",
    "wof:placetype": "postalcode"
  },
  "geometry": {"coordinates":[-2.75197,54.667032],"type":"Point"}
}
