{
  "type": "Feature",
  "properties": {
    "iso:country": "GB",
    "wof:name": "PE15 8ST",
    "wof:placetype": "postalcode"
  },
  "geometry": {"coordinates":[0.090632,52.565054],"type":"Point"}
}
