{
  "type": "Feature",
  "properties": {
    "date:inception_lower": "1980-01-01",
    "date:inception_upper": "1980-01-01",
    "iso:country": "GB",
    "wof:name": "WF12 8NR",
    "wof:placetype": "postalcode"
  },
  "geometry": {"coordinates":[-1.600714,53.684117],"type":"Point"}
}
