{
  "type": "Feature",
  "properties": {
    "iso:country":"GB",
    "wof:name":"M46 0JE",
    "wof:placetype":"postalcode"
},
  "geometry": {"coordinates":[-2.4989235926364,53.52344286347057],"type":"Point"}
}