{
  "type": "Feature",
  "properties": {
    "iso:country":"GB",
    "wof:name":"DE7 6EF",
    "wof:placetype":"postalcode"
},
  "geometry": {"coordinates":[-1.39399168344566,52.99646093693075],"type":"Point"}
}