{
  "type": "Feature",
  "properties": {
    "iso:country":"GB",
    "wof:name":"NN11 4TA",
    "wof:placetype":"postalcode"
},
  "geometry": {"coordinates":[-1.15245660308729,52.25518960013414],"type":"Point"}
}