{
  "type": "Feature",
  "properties": {
    "date:inception_lower": "1983-03-01",
    "date:inception_upper": "1983-03-01",
    "iso:country": "GB",
    "wof:name": "NN11 4TA",
    "wof:placetype": "postalcode"
  },
  "geometry": {"coordinates":[-1.152457,52.25519],"type":"Point"}
}
