{
  "type": "Feature",
  "properties": {
    "iso:country":"GB",
    "wof:name":"SE27 9EB",
    "wof:placetype":"postalcode"
},
  "geometry": {"coordinates":[-0.0987578585751,51.4385251591891],"type":"Point"}
}