{
  "type": "Feature",
  "properties": {
    "date:inception_lower": "2021-04-01",
    "date:inception_upper": "2021-04-01",
    "iso:country": "GB",
    "wof:name": "NR10 3GH",
    "wof:placetype": "postalcode"
  },
  "geometry": {"coordinates":[1.24513,52.705096],"type":"Point"}
}
