{
  "type": "Feature",
  "properties": {
    "iso:country":"GB",
    "wof:name":"SN3 4QG",
    "wof:placetype":"postalcode"
},
  "geometry": {"coordinates":[-1.75095872254843,51.57870971818718],"type":"Point"}
}