{
  "type": "Feature",
  "properties": {
    "iso:country": "GB",
    "wof:name": "IP3 9DW",
    "wof:placetype": "postalcode"
  },
  "geometry": {"coordinates":[1.190551,52.043612],"type":"Point"}
}
