{
  "type": "Feature",
  "properties": {
    "iso:country":"GB",
    "wof:name":"AL2 1AT",
    "wof:placetype":"postalcode"
},
  "geometry": {"coordinates":[-0.28635379560017,51.71824421287058],"type":"Point"}
}