{
  "type": "Feature",
  "properties": {
    "date:inception_lower": "1980-01-01",
    "date:inception_upper": "1980-01-01",
    "iso:country": "GB",
    "wof:name": "AL2 1AT",
    "wof:placetype": "postalcode"
  },
  "geometry": {"coordinates":[-0.286354,51.718244],"type":"Point"}
}
