{
  "type": "Feature",
  "properties": {
    "iso:country": "GB",
    "wof:name": "IP17 1RD",
    "wof:placetype": "postalcode"
  },
  "geometry": {"coordinates":[1.491658,52.176632],"type":"Point"}
}
