{
  "type": "Feature",
  "properties": {
    "iso:country":"GB",
    "wof:name":"DH2 1PJ",
    "wof:placetype":"postalcode"
},
  "geometry": {"coordinates":[-1.63080263868491,54.87335760836844],"type":"Point"}
}