{
  "type": "Feature",
  "properties": {
    "date:inception_lower": "2006-11-01",
    "date:inception_upper": "2006-11-01",
    "iso:country": "GB",
    "wof:name": "DH2 1PJ",
    "wof:placetype": "postalcode"
  },
  "geometry": {"coordinates":[-1.630803,54.873358],"type":"Point"}
}
