{
  "type": "Feature",
  "properties": {
    "iso:country":"GB",
    "wof:name":"CF24 4AD",
    "wof:placetype":"postalcode"
},
  "geometry": {"coordinates":[-3.17325596743037,51.48788174659689],"type":"Point"}
}