{
  "type": "Feature",
  "properties": {
    "iso:country":"GB",
    "wof:name":"SP11 9EA",
    "wof:placetype":"postalcode"
},
  "geometry": {"coordinates":[-1.55033202622807,51.27870954332897],"type":"Point"}
}