{
  "type": "Feature",
  "properties": {
    "iso:country": "GB",
    "wof:name": "EH52 5FB",
    "wof:placetype": "postalcode"
  },
  "geometry": {"coordinates":[-3.461233,55.933564],"type":"Point"}
}
