{
  "type": "Feature",
  "properties": {
    "iso:country":"GB",
    "wof:name":"S81 9QZ",
    "wof:placetype":"postalcode"
},
  "geometry": {"coordinates":[-1.1198453813131,53.36472537076498],"type":"Point"}
}