{
  "type": "Feature",
  "properties": {
    "iso:country": "GB",
    "wof:name": "WV12 5YW",
    "wof:placetype": "postalcode"
  },
  "geometry": {"coordinates":[-2.049271,52.61426],"type":"Point"}
}
