{
  "type": "Feature",
  "properties": {
    "iso:country":"GB",
    "wof:name":"WV12 5YW",
    "wof:placetype":"postalcode"
},
  "geometry": {"coordinates":[-2.04927090200095,52.61426033119385],"type":"Point"}
}