{
  "type": "Feature",
  "properties": {
    "date:inception_lower":"1983-07-01",
    "date:inception_upper":"1983-07-31",
    "iso:country":"GB",
    "wof:name":"WV12 5YW",
    "wof:placetype":"postalcode"
},
  "geometry": {"coordinates":[-2.049271,52.61426],"type":"Point"}
}