{
  "type": "Feature",
  "properties": {
    "date:inception_lower":"1980-01-01",
    "date:inception_upper":"1980-01-31",
    "iso:country":"GB",
    "wof:name":"YO7 3NN",
    "wof:placetype":"postalcode"
},
  "geometry": {"coordinates":[-1.297953,54.168957],"type":"Point"}
}