{
  "type": "Feature",
  "properties": {
    "iso:country":"GB",
    "wof:name":"YO7 3NN",
    "wof:placetype":"postalcode"
},
  "geometry": {"coordinates":[-1.29795349880451,54.16895651588677],"type":"Point"}
}