{
  "type": "Feature",
  "properties": {
    "iso:country":"GB",
    "wof:name":"NP13 2JD",
    "wof:placetype":"postalcode"
},
  "geometry": {"coordinates":[-3.13590346479676,51.69999559741774],"type":"Point"}
}