{
  "type": "Feature",
  "properties": {
    "iso:country":"GB",
    "wof:name":"HG5 9LQ",
    "wof:placetype":"postalcode"
},
  "geometry": {"coordinates":[-1.43936710198429,54.06107322317857],"type":"Point"}
}