{
  "type": "Feature",
  "properties": {
    "iso:country":"GB",
    "wof:name":"DN4 6RD",
    "wof:placetype":"postalcode"
},
  "geometry": {"coordinates":[-1.06809032651994,53.50370472964485],"type":"Point"}
}