{
  "type": "Feature",
  "properties": {
    "iso:country": "GB",
    "wof:name": "NR15 1PA",
    "wof:placetype": "postalcode"
  },
  "geometry": {"coordinates":[1.25955,52.535028],"type":"Point"}
}
