{
  "type": "Feature",
  "properties": {
    "iso:country":"GB",
    "wof:name":"NR15 1PA",
    "wof:placetype":"postalcode"
},
  "geometry": {"coordinates":[1.25955011112128,52.5350284579996],"type":"Point"}
}