{
  "type": "Feature",
  "properties": {
    "iso:country":"GB",
    "wof:name":"WA2 8NX",
    "wof:placetype":"postalcode"
},
  "geometry": {"coordinates":[-2.59780977425172,53.40111263963104],"type":"Point"}
}