{
  "type": "Feature",
  "properties": {
    "iso:country": "GB",
    "wof:name": "UB10 9EX",
    "wof:placetype": "postalcode"
  },
  "geometry": {"coordinates":[-0.443596,51.543586],"type":"Point"}
}
