{
  "type": "Feature",
  "properties": {
    "iso:country":"GB",
    "wof:name":"UB10 9EX",
    "wof:placetype":"postalcode"
},
  "geometry": {"coordinates":[-0.44359613982064,51.54358621135477],"type":"Point"}
}