{
  "type": "Feature",
  "properties": {
    "date:inception_lower": "1980-01-01",
    "date:inception_upper": "1980-01-01",
    "iso:country": "GB",
    "wof:name": "TW10 7JL",
    "wof:placetype": "postalcode"
  },
  "geometry": {"coordinates":[-0.30593,51.43654],"type":"Point"}
}
