{
  "type": "Feature",
  "properties": {
    "iso:country": "GB",
    "wof:name": "TW10 7JL",
    "wof:placetype": "postalcode"
  },
  "geometry": {"coordinates":[-0.30593,51.43654],"type":"Point"}
}
