{
  "type": "Feature",
  "properties": {
    "date:inception_lower": "1980-01-01",
    "date:inception_upper": "1980-01-01",
    "iso:country": "GB",
    "wof:name": "UB10 0BQ",
    "wof:placetype": "postalcode"
  },
  "geometry": {"coordinates":[-0.460357,51.545624],"type":"Point"}
}
