{
  "type": "Feature",
  "properties": {
    "iso:country":"GB",
    "wof:name":"CA12 5DP",
    "wof:placetype":"postalcode"
},
  "geometry": {"coordinates":[-3.13852894243446,54.60080783632743],"type":"Point"}
}