{
  "type": "Feature",
  "properties": {
    "iso:country":"GB",
    "wof:name":"WV11 1ND",
    "wof:placetype":"postalcode"
},
  "geometry": {"coordinates":[-2.08664980734005,52.60595024489582],"type":"Point"}
}