{
  "type": "Feature",
  "properties": {
    "date:inception_lower": "1983-01-01",
    "date:inception_upper": "1983-01-01",
    "iso:country": "GB",
    "wof:name": "DA12 2QU",
    "wof:placetype": "postalcode"
  },
  "geometry": {"coordinates":[0.383587,51.437578],"type":"Point"}
}
