{
  "type": "Feature",
  "properties": {
    "iso:country":"GB",
    "wof:name":"WA16 8QP",
    "wof:placetype":"postalcode"
},
  "geometry": {"coordinates":[-2.35728440186701,53.2950737461767],"type":"Point"}
}