{
  "type": "Feature",
  "properties": {
    "iso:country":"GB",
    "wof:name":"SO19 6DW",
    "wof:placetype":"postalcode"
},
  "geometry": {"coordinates":[-1.33637173359629,50.91210527997096],"type":"Point"}
}