{
  "type": "Feature",
  "properties": {
    "iso:country":"GB",
    "wof:name":"NE22 5BF",
    "wof:placetype":"postalcode"
},
  "geometry": {"coordinates":[-1.59497470933548,55.13286457694033],"type":"Point"}
}