{
  "type": "Feature",
  "properties": {
    "date:inception_lower": "2003-11-01",
    "date:inception_upper": "2003-11-01",
    "iso:country": "GB",
    "wof:name": "NE22 5BF",
    "wof:placetype": "postalcode"
  },
  "geometry": {"coordinates":[-1.594975,55.132865],"type":"Point"}
}
