{
  "type": "Feature",
  "properties": {
    "iso:country": "GB",
    "wof:name": "NE22 5BF",
    "wof:placetype": "postalcode"
  },
  "geometry": {"coordinates":[-1.594975,55.132865],"type":"Point"}
}
