{
  "type": "Feature",
  "properties": {
    "iso:country":"GB",
    "wof:name":"SW3 3HX",
    "wof:placetype":"postalcode"
},
  "geometry": {"coordinates":[-0.16494684079035,51.49123322447411],"type":"Point"}
}