{
  "type": "Feature",
  "properties": {
    "iso:country": "GB",
    "wof:name": "SN1 3UZ",
    "wof:placetype": "postalcode"
  },
  "geometry": {"coordinates":[-1.778321,51.555433],"type":"Point"}
}
