{
  "type": "Feature",
  "properties": {
    "iso:country": "GB",
    "wof:name": "LE14 4DN",
    "wof:placetype": "postalcode"
  },
  "geometry": {"coordinates":[-0.869369,52.811055],"type":"Point"}
}
