{
  "type": "Feature",
  "properties": {
    "iso:country":"GB",
    "wof:name":"LE14 4DN",
    "wof:placetype":"postalcode"
},
  "geometry": {"coordinates":[-0.86936870936293,52.81105516327015],"type":"Point"}
}