{
  "type": "Feature",
  "properties": {
    "date:inception_lower": "1980-01-01",
    "date:inception_upper": "1980-01-01",
    "iso:country": "GB",
    "wof:name": "LE14 4DN",
    "wof:placetype": "postalcode"
  },
  "geometry": {"coordinates":[-0.869369,52.811055],"type":"Point"}
}
