{
  "type": "Feature",
  "properties": {
    "date:inception_lower": "2019-12-01",
    "date:inception_upper": "2019-12-01",
    "iso:country": "GB",
    "wof:name": "EX16 8FD",
    "wof:placetype": "postalcode"
  },
  "geometry": {"coordinates":[-3.69821,50.911305],"type":"Point"}
}
