{
  "type": "Feature",
  "properties": {
    "iso:country":"GB",
    "wof:name":"B10 9WA",
    "wof:placetype":"postalcode"
},
  "geometry": {"coordinates":[-1.85195629353412,52.47798206763591],"type":"Point"}
}