{
  "type": "Feature",
  "properties": {
    "iso:country":"GB",
    "wof:name":"PR8 1RP",
    "wof:placetype":"postalcode"
},
  "geometry": {"coordinates":[-3.01272414453477,53.6447230929949],"type":"Point"}
}