{
  "type": "Feature",
  "properties": {
    "iso:country":"GB",
    "wof:name":"IP4 5TE",
    "wof:placetype":"postalcode"
},
  "geometry": {"coordinates":[1.21082733231504,52.0489244604221],"type":"Point"}
}