{
  "type": "Feature",
  "properties": {
    "iso:country": "GB",
    "wof:name": "PE29 7BN",
    "wof:placetype": "postalcode"
  },
  "geometry": {"coordinates":[-0.178695,52.340158],"type":"Point"}
}
