{
  "type": "Feature",
  "properties": {
    "date:inception_lower":"2000-06-01",
    "date:inception_upper":"2000-06-30",
    "iso:country":"GB",
    "wof:name":"PE29 7BN",
    "wof:placetype":"postalcode"
},
  "geometry": {"coordinates":[-0.178695,52.340158],"type":"Point"}
}