{
  "type": "Feature",
  "properties": {
    "iso:country":"GB",
    "wof:name":"FY8 5HP",
    "wof:placetype":"postalcode"
},
  "geometry": {"coordinates":[-2.95945542376973,53.73770747636735],"type":"Point"}
}