{
  "type": "Feature",
  "properties": {
    "date:inception_lower":"1980-01-01",
    "date:inception_upper":"1980-01-31",
    "iso:country":"GB",
    "wof:name":"FY8 5HP",
    "wof:placetype":"postalcode"
},
  "geometry": {"coordinates":[-2.959338,53.737993],"type":"Point"}
}