{
  "type": "Feature",
  "properties": {
    "iso:country": "GB",
    "wof:name": "FY8 5HP",
    "wof:placetype": "postalcode"
  },
  "geometry": {"coordinates":[-2.959338,53.737993],"type":"Point"}
}
