{
  "type": "Feature",
  "properties": {
    "iso:country":"GB",
    "wof:name":"CV5 6JJ",
    "wof:placetype":"postalcode"
},
  "geometry": {"coordinates":[-1.52957888510729,52.40674776016463],"type":"Point"}
}