{
  "type": "Feature",
  "properties": {
    "iso:country":"GB",
    "wof:name":"UB7 7PA",
    "wof:placetype":"postalcode"
},
  "geometry": {"coordinates":[-0.47848105290947,51.5037859543569],"type":"Point"}
}