{
  "type": "Feature",
  "properties": {
    "iso:country": "GB",
    "wof:name": "UB7 7PA",
    "wof:placetype": "postalcode"
  },
  "geometry": {"coordinates":[-0.478481,51.503786],"type":"Point"}
}
