{
  "type": "Feature",
  "properties": {
    "iso:country":"GB",
    "wof:name":"BA2 9HR",
    "wof:placetype":"postalcode"
},
  "geometry": {"coordinates":[-2.48127120794356,51.36127049413773],"type":"Point"}
}