{
  "type": "Feature",
  "properties": {
    "date:inception_lower":"1980-01-01",
    "date:inception_upper":"1980-01-31",
    "iso:country":"GB",
    "wof:name":"BA2 9HR",
    "wof:placetype":"postalcode"
},
  "geometry": {"coordinates":[-2.481285,51.361285],"type":"Point"}
}