{
  "type": "Feature",
  "properties": {
    "date:inception_lower":"2005-09-01",
    "date:inception_upper":"2005-09-30",
    "iso:country":"GB",
    "wof:name":"BN11 1QZ",
    "wof:placetype":"postalcode"
},
  "geometry": {"coordinates":[-0.372626,50.811037],"type":"Point"}
}