{
  "type": "Feature",
  "properties": {
    "iso:country":"GB",
    "wof:name":"BN11 1QZ",
    "wof:placetype":"postalcode"
},
  "geometry": {"coordinates":[-0.37262604469325,50.81103728509642],"type":"Point"}
}