{
  "type": "Feature",
  "properties": {
    "iso:country": "GB",
    "wof:name": "SA62 6RL",
    "wof:placetype": "postalcode"
  },
  "geometry": {"coordinates":[-5.270645,51.879581],"type":"Point"}
}
