{
  "type": "Feature",
  "properties": {
    "iso:country":"GB",
    "wof:name":"SA62 6RL",
    "wof:placetype":"postalcode"
},
  "geometry": {"coordinates":[-5.27069698366722,51.87956350339338],"type":"Point"}
}