{
  "type": "Feature",
  "properties": {
    "date:inception_lower":"1980-01-01",
    "date:inception_upper":"1980-01-31",
    "iso:country":"GB",
    "wof:name":"SS13 3AB",
    "wof:placetype":"postalcode"
},
  "geometry": {"coordinates":[0.503302,51.564999],"type":"Point"}
}