{
  "type": "Feature",
  "properties": {
    "iso:country":"GB",
    "wof:name":"CR6 9BD",
    "wof:placetype":"postalcode"
},
  "geometry": {"coordinates":[-0.07423004697435,51.30967194894922],"type":"Point"}
}