{
  "type": "Feature",
  "properties": {
    "date:inception_lower":"1990-07-01",
    "date:inception_upper":"1990-07-31",
    "iso:country":"GB",
    "wof:name":"CR6 9BD",
    "wof:placetype":"postalcode"
},
  "geometry": {"coordinates":[-0.07423,51.309672],"type":"Point"}
}