{
  "type": "Feature",
  "properties": {
    "iso:country": "GB",
    "wof:name": "LL11 2RD",
    "wof:placetype": "postalcode"
  },
  "geometry": {"coordinates":[-2.996291,53.059694],"type":"Point"}
}
