{
  "type": "Feature",
  "properties": {
    "date:inception_lower":"1980-01-01",
    "date:inception_upper":"1980-01-31",
    "iso:country":"GB",
    "wof:name":"LL11 2RD",
    "wof:placetype":"postalcode"
},
  "geometry": {"coordinates":[-2.996291,53.059694],"type":"Point"}
}