{
  "type": "Feature",
  "properties": {
    "iso:country":"GB",
    "wof:name":"LL11 2RD",
    "wof:placetype":"postalcode"
},
  "geometry": {"coordinates":[-2.99629122006391,53.05969383816295],"type":"Point"}
}