{
  "type": "Feature",
  "properties": {
    "iso:country":"GB",
    "wof:name":"NW7 1RE",
    "wof:placetype":"postalcode"
},
  "geometry": {"coordinates":[-0.22578009144456,51.61725299944731],"type":"Point"}
}