{
  "type": "Feature",
  "properties": {
    "iso:country": "GB",
    "wof:name": "NW7 1RE",
    "wof:placetype": "postalcode"
  },
  "geometry": {"coordinates":[-0.22578,51.617253],"type":"Point"}
}
