{
  "type": "Feature",
  "properties": {
    "date:inception_lower": "2001-12-01",
    "date:inception_upper": "2001-12-01",
    "iso:country": "GB",
    "wof:name": "BL3 4LR",
    "wof:placetype": "postalcode"
  },
  "geometry": {"coordinates":[-2.465977,53.557372],"type":"Point"}
}
