{
  "type": "Feature",
  "properties": {
    "iso:country": "GB",
    "wof:name": "RG14 2JA",
    "wof:placetype": "postalcode"
  },
  "geometry": {"coordinates":[-1.307127,51.409641],"type":"Point"}
}
