{
  "type": "Feature",
  "properties": {
    "iso:country":"GB",
    "wof:name":"RG14 2JA",
    "wof:placetype":"postalcode"
},
  "geometry": {"coordinates":[-1.30712709311727,51.40964073199815],"type":"Point"}
}