{
  "type": "Feature",
  "properties": {
    "iso:country":"GB",
    "wof:name":"AB10 7DE",
    "wof:placetype":"postalcode"
},
  "geometry": {"coordinates":[-2.12911096601606,57.12110057072946],"type":"Point"}
}