{
  "type": "Feature",
  "properties": {
    "iso:country":"GB",
    "wof:name":"NE1 3PL",
    "wof:placetype":"postalcode"
},
  "geometry": {"coordinates":[-1.61473890975263,54.96786204077085],"type":"Point"}
}