{
  "type": "Feature",
  "properties": {
    "iso:country": "GB",
    "wof:name": "NE1 3PL",
    "wof:placetype": "postalcode"
  },
  "geometry": {"coordinates":[-1.614739,54.967862],"type":"Point"}
}
