{
  "type": "Feature",
  "properties": {
    "date:inception_lower": "2000-06-01",
    "date:inception_upper": "2000-06-01",
    "iso:country": "GB",
    "wof:name": "NE1 3PL",
    "wof:placetype": "postalcode"
  },
  "geometry": {"coordinates":[-1.614739,54.967862],"type":"Point"}
}
