{
  "type": "Feature",
  "properties": {
    "iso:country": "GB",
    "wof:name": "PO22 6NG",
    "wof:placetype": "postalcode"
  },
  "geometry": {"coordinates":[-0.607576,50.795957],"type":"Point"}
}
