{
  "type": "Feature",
  "properties": {
    "iso:country": "GB",
    "wof:name": "PE9 2XN",
    "wof:placetype": "postalcode"
  },
  "geometry": {"coordinates":[-0.495012,52.654368],"type":"Point"}
}
