{
  "type": "Feature",
  "properties": {
    "date:inception_lower": "1980-01-01",
    "date:inception_upper": "1980-01-01",
    "iso:country": "GB",
    "wof:name": "PE9 2XN",
    "wof:placetype": "postalcode"
  },
  "geometry": {"coordinates":[-0.495012,52.654368],"type":"Point"}
}
