{
  "type": "Feature",
  "properties": {
    "iso:country":"GB",
    "wof:name":"M40 7SD",
    "wof:placetype":"postalcode"
},
  "geometry": {"coordinates":[-2.22128925161402,53.49899521631351],"type":"Point"}
}