{
  "type": "Feature",
  "properties": {
    "iso:country": "GB",
    "wof:name": "CR0 7QQ",
    "wof:placetype": "postalcode"
  },
  "geometry": {"coordinates":[-0.04756,51.387972],"type":"Point"}
}
