{
  "type": "Feature",
  "properties": {
    "iso:country":"GB",
    "wof:name":"CR0 7QQ",
    "wof:placetype":"postalcode"
},
  "geometry": {"coordinates":[-0.04755994147319,51.38797158979829],"type":"Point"}
}