{
  "type": "Feature",
  "properties": {
    "date:inception_lower":"1980-01-01",
    "date:inception_upper":"1980-01-31",
    "iso:country":"GB",
    "wof:name":"E11 2LB",
    "wof:placetype":"postalcode"
},
  "geometry": {"coordinates":[0.037377,51.57658],"type":"Point"}
}