{
  "type": "Feature",
  "properties": {
    "date:inception_lower": "1980-01-01",
    "date:inception_upper": "1980-01-01",
    "iso:country": "GB",
    "wof:name": "E11 2LB",
    "wof:placetype": "postalcode"
  },
  "geometry": {"coordinates":[0.037568,51.576649],"type":"Point"}
}
