{
  "type": "Feature",
  "properties": {
    "iso:country":"GB",
    "wof:name":"E11 2LB",
    "wof:placetype":"postalcode"
},
  "geometry": {"coordinates":[0.03735026287233,51.57657888252231],"type":"Point"}
}