{
  "type": "Feature",
  "properties": {
    "iso:country":"GB",
    "wof:name":"RG1 1PB",
    "wof:placetype":"postalcode"
},
  "geometry": {"coordinates":[-0.97631865602699,51.45843677385245],"type":"Point"}
}