{
  "type": "Feature",
  "properties": {
    "date:inception_lower":"1980-01-01",
    "date:inception_upper":"1980-01-31",
    "iso:country":"GB",
    "wof:name":"RG1 1PB",
    "wof:placetype":"postalcode"
},
  "geometry": {"coordinates":[-0.976261,51.458427],"type":"Point"}
}