{
  "type": "Feature",
  "properties": {
    "iso:country":"GB",
    "wof:name":"WS4 1RS",
    "wof:placetype":"postalcode"
},
  "geometry": {"coordinates":[-1.94700139074533,52.62115408700058],"type":"Point"}
}