{
  "type": "Feature",
  "properties": {
    "date:inception_lower": "1980-01-01",
    "date:inception_upper": "1980-01-01",
    "iso:country": "GB",
    "wof:name": "WR5 3AH",
    "wof:placetype": "postalcode"
  },
  "geometry": {"coordinates":[-2.21361,52.177204],"type":"Point"}
}
