{
  "type": "Feature",
  "properties": {
    "iso:country":"GB",
    "wof:name":"BA12 0BH",
    "wof:placetype":"postalcode"
},
  "geometry": {"coordinates":[-2.17846276662756,51.20961370067957],"type":"Point"}
}