{
  "type": "Feature",
  "properties": {
    "iso:country":"GB",
    "wof:name":"LL14 2EW",
    "wof:placetype":"postalcode"
},
  "geometry": {"coordinates":[-3.04984117756206,53.00736366886572],"type":"Point"}
}