{
  "type": "Feature",
  "properties": {
    "iso:country":"GB",
    "wof:name":"KW14 7UJ",
    "wof:placetype":"postalcode"
},
  "geometry": {"coordinates":[-3.54911308420967,58.61214875638081],"type":"Point"}
}