{
  "type": "Feature",
  "properties": {
    "date:inception_lower":"1994-12-01",
    "date:inception_upper":"1994-12-31",
    "iso:country":"GB",
    "wof:name":"SO31 4PD",
    "wof:placetype":"postalcode"
},
  "geometry": {"coordinates":[-1.312964,50.867519],"type":"Point"}
}