{
  "type": "Feature",
  "properties": {
    "iso:country": "GB",
    "wof:name": "TS25 1HN",
    "wof:placetype": "postalcode"
  },
  "geometry": {"coordinates":[-1.211841,54.658117],"type":"Point"}
}
