{
  "type": "Feature",
  "properties": {
    "iso:country":"GB",
    "wof:name":"TS25 1HN",
    "wof:placetype":"postalcode"
},
  "geometry": {"coordinates":[-1.21182662960215,54.65810608813],"type":"Point"}
}