{
  "type": "Feature",
  "properties": {
    "date:inception_lower":"1980-01-01",
    "date:inception_upper":"1980-01-31",
    "iso:country":"GB",
    "wof:name":"TS25 1HN",
    "wof:placetype":"postalcode"
},
  "geometry": {"coordinates":[-1.211841,54.658117],"type":"Point"}
}