{
  "type": "Feature",
  "properties": {
    "iso:country": "GB",
    "wof:name": "B90 4DN",
    "wof:placetype": "postalcode"
  },
  "geometry": {"coordinates":[-1.823627,52.395295],"type":"Point"}
}
