{
  "type": "Feature",
  "properties": {
    "iso:country":"GB",
    "wof:name":"B90 4DN",
    "wof:placetype":"postalcode"
},
  "geometry": {"coordinates":[-1.82385490659945,52.39528025836821],"type":"Point"}
}