{
  "type": "Feature",
  "properties": {
    "iso:country":"GB",
    "wof:name":"M29 8BL",
    "wof:placetype":"postalcode"
},
  "geometry": {"coordinates":[-2.47013850314285,53.51749235920612],"type":"Point"}
}