{
  "type": "Feature",
  "properties": {
    "iso:country": "GB",
    "wof:name": "DG1 1TZ",
    "wof:placetype": "postalcode"
  },
  "geometry": {"coordinates":[-3.585946,55.097474],"type":"Point"}
}
