{
  "type": "Feature",
  "properties": {
    "iso:country":"GB",
    "wof:name":"YO7 4RW",
    "wof:placetype":"postalcode"
},
  "geometry": {"coordinates":[-1.41413191580585,54.23222028553601],"type":"Point"}
}