{
  "type": "Feature",
  "properties": {
    "date:inception_lower": "2018-01-01",
    "date:inception_upper": "2018-01-01",
    "iso:country": "GB",
    "wof:name": "NG21 0WN",
    "wof:placetype": "postalcode"
  },
  "geometry": {"coordinates":[-1.117613,53.112116],"type":"Point"}
}
