{
  "type": "Feature",
  "properties": {
    "iso:country": "GB",
    "wof:name": "NG21 0WN",
    "wof:placetype": "postalcode"
  },
  "geometry": {"coordinates":[-1.117613,53.112116],"type":"Point"}
}
