{
  "type": "Feature",
  "properties": {
    "iso:country":"GB",
    "wof:name":"B75 7PE",
    "wof:placetype":"postalcode"
},
  "geometry": {"coordinates":[-1.79096836535802,52.56575754526517],"type":"Point"}
}