{
  "type": "Feature",
  "properties": {
    "iso:country":"GB",
    "wof:name":"SW12 8HD",
    "wof:placetype":"postalcode"
},
  "geometry": {"coordinates":[-0.16131617636758,51.44110584645397],"type":"Point"}
}