{
  "type": "Feature",
  "properties": {
    "iso:country":"GB",
    "wof:name":"TW5 9LW",
    "wof:placetype":"postalcode"
},
  "geometry": {"coordinates":[-0.39494645057944,51.48269180053572],"type":"Point"}
}