{
  "type": "Feature",
  "properties": {
    "iso:country":"GB",
    "wof:name":"SK6 7ET",
    "wof:placetype":"postalcode"
},
  "geometry": {"coordinates":[-2.05383100586387,53.37445483867904],"type":"Point"}
}