{
  "type": "Feature",
  "properties": {
    "date:inception_lower": "1990-08-01",
    "date:inception_upper": "1990-08-01",
    "iso:country": "GB",
    "wof:name": "AB22 8WR",
    "wof:placetype": "postalcode"
  },
  "geometry": {"coordinates":[-2.108014,57.174992],"type":"Point"}
}
