{
  "type": "Feature",
  "properties": {
    "iso:country":"GB",
    "wof:name":"E6 5XR",
    "wof:placetype":"postalcode"
},
  "geometry": {"coordinates":[0.05840332073012,51.51641897425672],"type":"Point"}
}