{
  "type": "Feature",
  "properties": {
    "date:inception_lower": "2016-08-01",
    "date:inception_upper": "2016-08-01",
    "iso:country": "GB",
    "wof:name": "GL50 3FG",
    "wof:placetype": "postalcode"
  },
  "geometry": {"coordinates":[-2.076627,51.900504],"type":"Point"}
}
