{
  "type": "Feature",
  "properties": {
    "iso:country": "GB",
    "wof:name": "GL50 3FG",
    "wof:placetype": "postalcode"
  },
  "geometry": {"coordinates":[-2.076627,51.900504],"type":"Point"}
}
