{
  "type": "Feature",
  "properties": {
    "iso:country": "GB",
    "wof:name": "SG1 2AU",
    "wof:placetype": "postalcode"
  },
  "geometry": {"coordinates":[-0.21025,51.898748],"type":"Point"}
}
