{
  "type": "Feature",
  "properties": {
    "iso:country":"GB",
    "wof:name":"SG1 2AU",
    "wof:placetype":"postalcode"
},
  "geometry": {"coordinates":[-0.21024969446892,51.89874835172458],"type":"Point"}
}