{
  "type": "Feature",
  "properties": {
    "iso:country":"GB",
    "wof:name":"B71 4JZ",
    "wof:placetype":"postalcode"
},
  "geometry": {"coordinates":[-1.96917652429002,52.5103712540073],"type":"Point"}
}