{
  "type": "Feature",
  "properties": {
    "iso:country":"GB",
    "wof:name":"HA3 9EZ",
    "wof:placetype":"postalcode"
},
  "geometry": {"coordinates":[-0.30184088822892,51.5933975434541],"type":"Point"}
}