{
  "type": "Feature",
  "properties": {
    "date:inception_lower":"1980-01-01",
    "date:inception_upper":"1980-01-31",
    "iso:country":"GB",
    "wof:name":"NE44 6AG",
    "wof:placetype":"postalcode"
},
  "geometry": {"coordinates":[-2.009132,54.942519],"type":"Point"}
}