{
  "type": "Feature",
  "properties": {
    "iso:country":"GB",
    "wof:name":"NE44 6AG",
    "wof:placetype":"postalcode"
},
  "geometry": {"coordinates":[-2.00913240792939,54.94251882071426],"type":"Point"}
}