{
  "type": "Feature",
  "properties": {
    "iso:country": "GB",
    "wof:name": "NE44 6AG",
    "wof:placetype": "postalcode"
  },
  "geometry": {"coordinates":[-2.009132,54.942519],"type":"Point"}
}
