{
  "type": "Feature",
  "properties": {
    "iso:country":"GB",
    "wof:name":"TR11 2BG",
    "wof:placetype":"postalcode"
},
  "geometry": {"coordinates":[-5.07676005192203,50.15677001928],"type":"Point"}
}