{
  "type": "Feature",
  "properties": {
    "iso:country":"GB",
    "wof:name":"S75 5RH",
    "wof:placetype":"postalcode"
},
  "geometry": {"coordinates":[-1.53984690907614,53.58543171940445],"type":"Point"}
}