{
  "type": "Feature",
  "properties": {
    "iso:country":"GB",
    "wof:name":"SW8 1AL",
    "wof:placetype":"postalcode"
},
  "geometry": {"coordinates":[-0.11696092212568,51.47835950233485],"type":"Point"}
}