{
  "type": "Feature",
  "properties": {
    "iso:country":"GB",
    "wof:name":"SR6 9PP",
    "wof:placetype":"postalcode"
},
  "geometry": {"coordinates":[-1.37213882212788,54.92619757305975],"type":"Point"}
}