{
  "type": "Feature",
  "properties": {
    "iso:country": "GB",
    "wof:name": "IP8 4BG",
    "wof:placetype": "postalcode"
  },
  "geometry": {"coordinates":[1.109284,52.078946],"type":"Point"}
}
