{
  "type": "Feature",
  "properties": {
    "iso:country":"GB",
    "wof:name":"IP8 4BG",
    "wof:placetype":"postalcode"
},
  "geometry": {"coordinates":[1.10928439826119,52.07894600635591],"type":"Point"}
}