{
  "type": "Feature",
  "properties": {
    "iso:country":"GB",
    "wof:name":"SL5 0EQ",
    "wof:placetype":"postalcode"
},
  "geometry": {"coordinates":[-0.62832072586878,51.39212635819624],"type":"Point"}
}