{
  "type": "Feature",
  "properties": {
    "iso:country":"GB",
    "wof:name":"G60 5JF",
    "wof:placetype":"postalcode"
},
  "geometry": {"coordinates":[-4.45865934856868,55.92414583759671],"type":"Point"}
}