{
  "type": "Feature",
  "properties": {
    "iso:country": "GB",
    "wof:name": "LL11 6EJ",
    "wof:placetype": "postalcode"
  },
  "geometry": {"coordinates":[-3.040057,53.076444],"type":"Point"}
}
