{
  "type": "Feature",
  "properties": {
    "date:inception_lower":"2004-01-01",
    "date:inception_upper":"2004-01-31",
    "iso:country":"GB",
    "wof:name":"LL11 6EJ",
    "wof:placetype":"postalcode"
},
  "geometry": {"coordinates":[-3.040057,53.076444],"type":"Point"}
}