{
  "type": "Feature",
  "properties": {
    "iso:country":"GB",
    "wof:name":"WF3 1HX",
    "wof:placetype":"postalcode"
},
  "geometry": {"coordinates":[-1.59084979429932,53.73332050112395],"type":"Point"}
}