{
  "type": "Feature",
  "properties": {
    "date:inception_lower": "1980-01-01",
    "date:inception_upper": "1980-01-01",
    "iso:country": "GB",
    "wof:name": "WF3 1HX",
    "wof:placetype": "postalcode"
  },
  "geometry": {"coordinates":[-1.59085,53.73332],"type":"Point"}
}
