{
  "type": "Feature",
  "properties": {
    "iso:country":"GB",
    "wof:name":"WN2 2QR",
    "wof:placetype":"postalcode"
},
  "geometry": {"coordinates":[-2.57251301597057,53.54106300301027],"type":"Point"}
}