{
  "type": "Feature",
  "properties": {
    "date:inception_lower": "1980-01-01",
    "date:inception_upper": "1980-01-01",
    "iso:country": "GB",
    "wof:name": "WN2 2QR",
    "wof:placetype": "postalcode"
  },
  "geometry": {"coordinates":[-2.572513,53.541063],"type":"Point"}
}
