{
  "type": "Feature",
  "properties": {
    "date:inception_lower": "2000-10-01",
    "date:inception_upper": "2000-10-01",
    "iso:country": "GB",
    "wof:name": "W1S 2GF",
    "wof:placetype": "postalcode"
  },
  "geometry": {"coordinates":[-0.140874,51.512877],"type":"Point"}
}
