{
  "type": "Feature",
  "properties": {
    "iso:country": "GB",
    "wof:name": "WA10 6RD",
    "wof:placetype": "postalcode"
  },
  "geometry": {"coordinates":[-2.752496,53.459599],"type":"Point"}
}
