{
  "type": "Feature",
  "properties": {
    "date:inception_lower":"1980-01-01",
    "date:inception_upper":"1980-01-31",
    "iso:country":"GB",
    "wof:name":"WA10 6RD",
    "wof:placetype":"postalcode"
},
  "geometry": {"coordinates":[-2.752496,53.459599],"type":"Point"}
}