{
  "type": "Feature",
  "properties": {
    "iso:country":"GB",
    "wof:name":"WA10 6RD",
    "wof:placetype":"postalcode"
},
  "geometry": {"coordinates":[-2.75249564656262,53.45959930654346],"type":"Point"}
}