{
  "type": "Feature",
  "properties": {
    "iso:country":"GB",
    "wof:name":"NR12 8QR",
    "wof:placetype":"postalcode"
},
  "geometry": {"coordinates":[1.41212139497176,52.71983081562159],"type":"Point"}
}