{
  "type": "Feature",
  "properties": {
    "iso:country": "GB",
    "wof:name": "WF14 9RR",
    "wof:placetype": "postalcode"
  },
  "geometry": {"coordinates":[-1.699192,53.679542],"type":"Point"}
}
