{
  "type": "Feature",
  "properties": {
    "iso:country": "GB",
    "wof:name": "SY21 7AD",
    "wof:placetype": "postalcode"
  },
  "geometry": {"coordinates":[-3.146463,52.659128],"type":"Point"}
}
