{
  "type": "Feature",
  "properties": {
    "date:inception_lower":"1991-09-01",
    "date:inception_upper":"1991-09-30",
    "iso:country":"GB",
    "wof:name":"B77 4PL",
    "wof:placetype":"postalcode"
},
  "geometry": {"coordinates":[-1.64102,52.612766],"type":"Point"}
}