{
  "type": "Feature",
  "properties": {
    "iso:country":"GB",
    "wof:name":"B77 4PL",
    "wof:placetype":"postalcode"
},
  "geometry": {"coordinates":[-1.64102036585163,52.61276568676806],"type":"Point"}
}