{
  "type": "Feature",
  "properties": {
    "iso:country":"GB",
    "wof:name":"PE21 9LL",
    "wof:placetype":"postalcode"
},
  "geometry": {"coordinates":[-0.03393050739131,52.99169465260946],"type":"Point"}
}