{
  "type": "Feature",
  "properties": {
    "iso:country":"GB",
    "wof:name":"DE23 8JS",
    "wof:placetype":"postalcode"
},
  "geometry": {"coordinates":[-1.46637981865087,52.91120216169537],"type":"Point"}
}