{
  "type": "Feature",
  "properties": {
    "iso:country": "GB",
    "wof:name": "S45 8JB",
    "wof:placetype": "postalcode"
  },
  "geometry": {"coordinates":[-1.369164,53.160206],"type":"Point"}
}
