{
  "type": "Feature",
  "properties": {
    "iso:country":"GB",
    "wof:name":"S45 8JB",
    "wof:placetype":"postalcode"
},
  "geometry": {"coordinates":[-1.36930094948495,53.16012474107568],"type":"Point"}
}