{
  "type": "Feature",
  "properties": {
    "date:inception_lower":"1985-10-01",
    "date:inception_upper":"1985-10-31",
    "iso:country":"GB",
    "wof:name":"S45 8JB",
    "wof:placetype":"postalcode"
},
  "geometry": {"coordinates":[-1.369164,53.160206],"type":"Point"}
}