{
  "type": "Feature",
  "properties": {
    "iso:country": "GB",
    "wof:name": "HD6 1HB",
    "wof:placetype": "postalcode"
  },
  "geometry": {"coordinates":[-1.783177,53.695875],"type":"Point"}
}
