{
  "type": "Feature",
  "properties": {
    "iso:country": "GB",
    "wof:name": "CT2 0DP",
    "wof:placetype": "postalcode"
  },
  "geometry": {"coordinates":[1.12485,51.292795],"type":"Point"}
}
