{
  "type": "Feature",
  "properties": {
    "iso:country":"GB",
    "wof:name":"CT2 0DP",
    "wof:placetype":"postalcode"
},
  "geometry": {"coordinates":[1.12484976580265,51.29279489879392],"type":"Point"}
}