{
  "type": "Feature",
  "properties": {
    "date:inception_lower": "2019-12-01",
    "date:inception_upper": "2019-12-01",
    "iso:country": "GB",
    "wof:name": "CM7 0NL",
    "wof:placetype": "postalcode"
  },
  "geometry": {"coordinates":[0.566263,51.87645],"type":"Point"}
}
