{
  "type": "Feature",
  "properties": {
    "date:inception_lower": "1980-01-01",
    "date:inception_upper": "1980-01-01",
    "iso:country": "GB",
    "wof:name": "L11 8LT",
    "wof:placetype": "postalcode"
  },
  "geometry": {"coordinates":[-2.93168,53.439684],"type":"Point"}
}
