{
  "type": "Feature",
  "properties": {
    "iso:country":"GB",
    "wof:name":"L11 8LT",
    "wof:placetype":"postalcode"
},
  "geometry": {"coordinates":[-2.93168039377518,53.43968422678703],"type":"Point"}
}