{
  "type": "Feature",
  "properties": {
    "iso:country":"GB",
    "wof:name":"PE13 1RH",
    "wof:placetype":"postalcode"
},
  "geometry": {"coordinates":[0.15355094417364,52.66503474805096],"type":"Point"}
}