{
  "type": "Feature",
  "properties": {
    "date:inception_lower":"1980-01-01",
    "date:inception_upper":"1980-01-31",
    "iso:country":"GB",
    "wof:name":"PE13 1RH",
    "wof:placetype":"postalcode"
},
  "geometry": {"coordinates":[0.153551,52.665035],"type":"Point"}
}