{
  "type": "Feature",
  "properties": {
    "iso:country":"GB",
    "wof:name":"PO7 7EQ",
    "wof:placetype":"postalcode"
},
  "geometry": {"coordinates":[-1.03165930232958,50.8799408923351],"type":"Point"}
}