{
  "type": "Feature",
  "properties": {
    "date:inception_lower": "1980-01-01",
    "date:inception_upper": "1980-01-01",
    "iso:country": "GB",
    "wof:name": "PO7 7EQ",
    "wof:placetype": "postalcode"
  },
  "geometry": {"coordinates":[-1.031659,50.879941],"type":"Point"}
}
