{
  "type": "Feature",
  "properties": {
    "iso:country":"GB",
    "wof:name":"LU3 2JQ",
    "wof:placetype":"postalcode"
},
  "geometry": {"coordinates":[-0.4421571877792,51.90533772710397],"type":"Point"}
}