{
  "type": "Feature",
  "properties": {
    "iso:country":"GB",
    "wof:name":"M41 5AH",
    "wof:placetype":"postalcode"
},
  "geometry": {"coordinates":[-2.35922597752133,53.44933111934474],"type":"Point"}
}