{
  "type": "Feature",
  "properties": {
    "iso:country": "GB",
    "wof:name": "RG24 7AN",
    "wof:placetype": "postalcode"
  },
  "geometry": {"coordinates":[-1.065585,51.270037],"type":"Point"}
}
