{
  "type": "Feature",
  "properties": {
    "iso:country":"GB",
    "wof:name":"RG24 7AN",
    "wof:placetype":"postalcode"
},
  "geometry": {"coordinates":[-1.06558531272552,51.27003660908623],"type":"Point"}
}