{
  "type": "Feature",
  "properties": {
    "date:inception_lower":"1980-01-01",
    "date:inception_upper":"1980-01-31",
    "iso:country":"GB",
    "wof:name":"SA31 1RL",
    "wof:placetype":"postalcode"
},
  "geometry": {"coordinates":[-4.314966,51.859334],"type":"Point"}
}