{
  "type": "Feature",
  "properties": {
    "iso:country":"GB",
    "wof:name":"TS3 0BY",
    "wof:placetype":"postalcode"
},
  "geometry": {"coordinates":[-1.19766435820248,54.54913523230848],"type":"Point"}
}