{
  "type": "Feature",
  "properties": {
    "iso:country":"GB",
    "wof:name":"ME12 3EF",
    "wof:placetype":"postalcode"
},
  "geometry": {"coordinates":[0.76397289905245,51.41746606478377],"type":"Point"}
}