{
  "type": "Feature",
  "properties": {
    "date:inception_lower": "1980-01-01",
    "date:inception_upper": "1980-01-01",
    "iso:country": "GB",
    "wof:name": "TN3 9RE",
    "wof:placetype": "postalcode"
  },
  "geometry": {"coordinates":[0.186274,51.11307],"type":"Point"}
}
