{
  "type": "Feature",
  "properties": {
    "iso:country":"GB",
    "wof:name":"TN3 9RE",
    "wof:placetype":"postalcode"
},
  "geometry": {"coordinates":[0.18631834471103,51.11308028461825],"type":"Point"}
}