{
  "type": "Feature",
  "properties": {
    "iso:country": "GB",
    "wof:name": "RH13 8JA",
    "wof:placetype": "postalcode"
  },
  "geometry": {"coordinates":[-0.300684,50.962393],"type":"Point"}
}
