{
  "type": "Feature",
  "properties": {
    "iso:country":"GB",
    "wof:name":"DA7 4PD",
    "wof:placetype":"postalcode"
},
  "geometry": {"coordinates":[0.13911068368896,51.4654688507414],"type":"Point"}
}