{
  "type": "Feature",
  "properties": {
    "date:inception_lower": "1980-01-01",
    "date:inception_upper": "1980-01-01",
    "iso:country": "GB",
    "wof:name": "L12 7HQ",
    "wof:placetype": "postalcode"
  },
  "geometry": {"coordinates":[-2.919498,53.429747],"type":"Point"}
}
