{
  "type": "Feature",
  "properties": {
    "iso:country": "GB",
    "wof:name": "DY10 3TQ",
    "wof:placetype": "postalcode"
  },
  "geometry": {"coordinates":[-2.231231,52.416113],"type":"Point"}
}
