{
  "type": "Feature",
  "properties": {
    "iso:country": "GB",
    "wof:name": "GU9 8JU",
    "wof:placetype": "postalcode"
  },
  "geometry": {"coordinates":[-0.792611,51.205403],"type":"Point"}
}
