{
  "type": "Feature",
  "properties": {
    "iso:country":"GB",
    "wof:name":"GU9 8JU",
    "wof:placetype":"postalcode"
},
  "geometry": {"coordinates":[-0.79261142761174,51.20540337809869],"type":"Point"}
}