{
  "type": "Feature",
  "properties": {
    "date:inception_lower": "1980-01-01",
    "date:inception_upper": "1980-01-01",
    "iso:country": "GB",
    "wof:name": "GU9 8JU",
    "wof:placetype": "postalcode"
  },
  "geometry": {"coordinates":[-0.792611,51.205403],"type":"Point"}
}
