{
  "type": "Feature",
  "properties": {
    "iso:country": "GB",
    "wof:name": "M40 7EX",
    "wof:placetype": "postalcode"
  },
  "geometry": {"coordinates":[-2.20853,53.485491],"type":"Point"}
}
