{
  "type": "Feature",
  "properties": {
    "iso:country": "GB",
    "wof:name": "ZE1 0SN",
    "wof:placetype": "postalcode"
  },
  "geometry": {"coordinates":[-1.173567,60.143171],"type":"Point"}
}
