{
  "type": "Feature",
  "properties": {
    "date:inception_lower": "1989-09-01",
    "date:inception_upper": "1989-09-01",
    "iso:country": "GB",
    "wof:name": "ZE1 0SN",
    "wof:placetype": "postalcode"
  },
  "geometry": {"coordinates":[-1.173293,60.1429],"type":"Point"}
}
