{
  "type": "Feature",
  "properties": {
    "iso:country":"GB",
    "wof:name":"ZE1 0SN",
    "wof:placetype":"postalcode"
},
  "geometry": {"coordinates":[-1.17356692126231,60.14317059641843],"type":"Point"}
}