{
  "type": "Feature",
  "properties": {
    "iso:country":"GB",
    "wof:name":"BD21 5HT",
    "wof:placetype":"postalcode"
},
  "geometry": {"coordinates":[-1.91041541192796,53.86484936296568],"type":"Point"}
}