{
  "type": "Feature",
  "properties": {
    "iso:country":"GB",
    "wof:name":"TA20 3EH",
    "wof:placetype":"postalcode"
},
  "geometry": {"coordinates":[-3.00517636362958,50.86517370424878],"type":"Point"}
}