{
  "type": "Feature",
  "properties": {
    "date:inception_lower": "1980-01-01",
    "date:inception_upper": "1980-01-01",
    "iso:country": "GB",
    "wof:name": "TA20 3EH",
    "wof:placetype": "postalcode"
  },
  "geometry": {"coordinates":[-3.005176,50.865174],"type":"Point"}
}
