{
  "type": "Feature",
  "properties": {
    "iso:country": "GB",
    "wof:name": "DE14 3BY",
    "wof:placetype": "postalcode"
  },
  "geometry": {"coordinates":[-1.639448,52.795107],"type":"Point"}
}
