{
  "type": "Feature",
  "properties": {
    "iso:country":"GB",
    "wof:name":"NR29 5QP",
    "wof:placetype":"postalcode"
},
  "geometry": {"coordinates":[1.5332796773205,52.712645093902],"type":"Point"}
}