{
  "type": "Feature",
  "properties": {
    "date:inception_lower":"2002-12-01",
    "date:inception_upper":"2002-12-31",
    "iso:country":"GB",
    "wof:name":"PA28 6RF",
    "wof:placetype":"postalcode"
},
  "geometry": {"coordinates":[-5.574906,55.328321],"type":"Point"}
}