{
  "type": "Feature",
  "properties": {
    "iso:country": "GB",
    "wof:name": "PA28 6RF",
    "wof:placetype": "postalcode"
  },
  "geometry": {"coordinates":[-5.574906,55.328321],"type":"Point"}
}
