{
  "type": "Feature",
  "properties": {
    "iso:country":"GB",
    "wof:name":"PA28 6RF",
    "wof:placetype":"postalcode"
},
  "geometry": {"coordinates":[-5.57490569170545,55.32832108251308],"type":"Point"}
}