{
  "type": "Feature",
  "properties": {
    "iso:country":"GB",
    "wof:name":"HD5 0HX",
    "wof:placetype":"postalcode"
},
  "geometry": {"coordinates":[-1.72991667405338,53.66427195224881],"type":"Point"}
}