{
  "type": "Feature",
  "properties": {
    "iso:country": "GB",
    "wof:name": "PO7 4SD",
    "wof:placetype": "postalcode"
  },
  "geometry": {"coordinates":[-1.054792,50.934437],"type":"Point"}
}
