{
  "type": "Feature",
  "properties": {
    "date:inception_lower":"1981-06-01",
    "date:inception_upper":"1981-06-30",
    "iso:country":"GB",
    "wof:name":"WA11 0YN",
    "wof:placetype":"postalcode"
},
  "geometry": {"coordinates":[-2.689408,53.461652],"type":"Point"}
}