{
  "type": "Feature",
  "properties": {
    "iso:country":"GB",
    "wof:name":"WA11 0YN",
    "wof:placetype":"postalcode"
},
  "geometry": {"coordinates":[-2.68940763026793,53.46165199755163],"type":"Point"}
}