{
  "type": "Feature",
  "properties": {
    "date:inception_lower":"1980-01-01",
    "date:inception_upper":"1980-01-31",
    "iso:country":"GB",
    "wof:name":"TS9 5JD",
    "wof:placetype":"postalcode"
},
  "geometry": {"coordinates":[-1.185411,54.478163],"type":"Point"}
}