{
  "type": "Feature",
  "properties": {
    "iso:country": "GB",
    "wof:name": "SA15 4ER",
    "wof:placetype": "postalcode"
  },
  "geometry": {"coordinates":[-4.169135,51.690959],"type":"Point"}
}
