{
  "type": "Feature",
  "properties": {
    "date:inception_lower":"1985-04-01",
    "date:inception_upper":"1985-04-30",
    "iso:country":"GB",
    "wof:name":"AL2 1DW",
    "wof:placetype":"postalcode"
},
  "geometry": {"coordinates":[-0.307701,51.728262],"type":"Point"}
}