{
  "type": "Feature",
  "properties": {
    "date:inception_lower":"1999-06-01",
    "date:inception_upper":"1999-06-30",
    "iso:country":"GB",
    "wof:name":"CH66 2TL",
    "wof:placetype":"postalcode"
},
  "geometry": {"coordinates":[-2.924864,53.264983],"type":"Point"}
}