{
  "type": "Feature",
  "properties": {
    "iso:country": "GB",
    "wof:name": "CH66 2TL",
    "wof:placetype": "postalcode"
  },
  "geometry": {"coordinates":[-2.924864,53.264983],"type":"Point"}
}
