{
  "type": "Feature",
  "properties": {
    "iso:country":"GB",
    "wof:name":"CH66 2TL",
    "wof:placetype":"postalcode"
},
  "geometry": {"coordinates":[-2.92486384468461,53.2649827438937],"type":"Point"}
}