{
  "type": "Feature",
  "properties": {
    "date:inception_lower": "1999-12-01",
    "date:inception_upper": "1999-12-01",
    "iso:country": "GB",
    "wof:name": "CW5 5HG",
    "wof:placetype": "postalcode"
  },
  "geometry": {"coordinates":[-2.534013,53.064546],"type":"Point"}
}
