{
  "type": "Feature",
  "properties": {
    "date:inception_lower": "1980-01-01",
    "date:inception_upper": "1980-01-01",
    "iso:country": "GB",
    "wof:name": "DD11 3DW",
    "wof:placetype": "postalcode"
  },
  "geometry": {"coordinates":[-2.595567,56.56255],"type":"Point"}
}
