{
  "type": "Feature",
  "properties": {
    "iso:country":"GB",
    "wof:name":"CV9 1DW",
    "wof:placetype":"postalcode"
},
  "geometry": {"coordinates":[-1.54390413709716,52.57409904793613],"type":"Point"}
}