{
  "type": "Feature",
  "properties": {
    "iso:country": "GB",
    "wof:name": "CV9 1DW",
    "wof:placetype": "postalcode"
  },
  "geometry": {"coordinates":[-1.543904,52.574099],"type":"Point"}
}
