{
  "type": "Feature",
  "properties": {
    "iso:country": "GB",
    "wof:name": "RH12 3BY",
    "wof:placetype": "postalcode"
  },
  "geometry": {"coordinates":[-0.443145,51.094034],"type":"Point"}
}
