{
  "type": "Feature",
  "properties": {
    "date:inception_lower":"2002-09-01",
    "date:inception_upper":"2002-09-30",
    "iso:country":"GB",
    "wof:name":"RH12 3BY",
    "wof:placetype":"postalcode"
},
  "geometry": {"coordinates":[-0.443145,51.094034],"type":"Point"}
}