{
  "type": "Feature",
  "properties": {
    "iso:country":"GB",
    "wof:name":"RG21 8TL",
    "wof:placetype":"postalcode"
},
  "geometry": {"coordinates":[-1.09434461121111,51.26398608882583],"type":"Point"}
}