{
  "type": "Feature",
  "properties": {
    "date:inception_lower":"1980-01-01",
    "date:inception_upper":"1980-01-31",
    "iso:country":"GB",
    "wof:name":"BA6 8JL",
    "wof:placetype":"postalcode"
},
  "geometry": {"coordinates":[-2.70463,51.147857],"type":"Point"}
}