{
  "type": "Feature",
  "properties": {
    "iso:country":"GB",
    "wof:name":"BA6 8JL",
    "wof:placetype":"postalcode"
},
  "geometry": {"coordinates":[-2.70463021875327,51.14785668668603],"type":"Point"}
}