{
  "type": "Feature",
  "properties": {
    "iso:country":"GB",
    "wof:name":"WA2 9BB",
    "wof:placetype":"postalcode"
},
  "geometry": {"coordinates":[-2.57664838493408,53.40781444308482],"type":"Point"}
}