{
  "type": "Feature",
  "properties": {
    "iso:country":"GB",
    "wof:name":"BN18 0EJ",
    "wof:placetype":"postalcode"
},
  "geometry": {"coordinates":[-0.60884876648718,50.82287926345664],"type":"Point"}
}