{
  "type": "Feature",
  "properties": {
    "date:inception_lower":"1980-01-01",
    "date:inception_upper":"1980-01-31",
    "iso:country":"GB",
    "wof:name":"BN18 0EJ",
    "wof:placetype":"postalcode"
},
  "geometry": {"coordinates":[-0.608849,50.822879],"type":"Point"}
}