{
  "type": "Feature",
  "properties": {
    "iso:country": "GB",
    "wof:name": "BN18 0EJ",
    "wof:placetype": "postalcode"
  },
  "geometry": {"coordinates":[-0.608849,50.822879],"type":"Point"}
}
