{
  "type": "Feature",
  "properties": {
    "date:inception_lower": "1980-01-01",
    "date:inception_upper": "1980-01-01",
    "iso:country": "GB",
    "wof:name": "CW5 7BJ",
    "wof:placetype": "postalcode"
  },
  "geometry": {"coordinates":[-2.518146,53.062945],"type":"Point"}
}
