{
  "type": "Feature",
  "properties": {
    "iso:country":"GB",
    "wof:name":"CW5 7BJ",
    "wof:placetype":"postalcode"
},
  "geometry": {"coordinates":[-2.51814585688672,53.06294452614843],"type":"Point"}
}