{
  "type": "Feature",
  "properties": {
    "iso:country":"GB",
    "wof:name":"CF63 1NJ",
    "wof:placetype":"postalcode"
},
  "geometry": {"coordinates":[-3.26818389857801,51.40937306268598],"type":"Point"}
}