{
  "type": "Feature",
  "properties": {
    "date:inception_lower":"1980-01-01",
    "date:inception_upper":"1980-01-31",
    "iso:country":"GB",
    "wof:name":"NE61 1NX",
    "wof:placetype":"postalcode"
},
  "geometry": {"coordinates":[-1.689188,55.167476],"type":"Point"}
}