{
  "type": "Feature",
  "properties": {
    "iso:country": "GB",
    "wof:name": "SY21 7PP",
    "wof:placetype": "postalcode"
  },
  "geometry": {"coordinates":[-3.149535,52.664043],"type":"Point"}
}
