{
  "type": "Feature",
  "properties": {
    "iso:country":"GB",
    "wof:name":"UB10 0DY",
    "wof:placetype":"postalcode"
},
  "geometry": {"coordinates":[-0.45336167107743,51.53160292512896],"type":"Point"}
}