{
  "type": "Feature",
  "properties": {
    "iso:country":"GB",
    "wof:name":"FY3 7HH",
    "wof:placetype":"postalcode"
},
  "geometry": {"coordinates":[-3.03141946641081,53.83281819256573],"type":"Point"}
}