{
  "type": "Feature",
  "properties": {
    "iso:country":"GB",
    "wof:name":"DA12 3AL",
    "wof:placetype":"postalcode"
},
  "geometry": {"coordinates":[0.38665471931325,51.39458921482863],"type":"Point"}
}