{
  "type": "Feature",
  "properties": {
    "iso:country":"GB",
    "wof:name":"DL12 9LU",
    "wof:placetype":"postalcode"
},
  "geometry": {"coordinates":[-1.99034548698243,54.50773987381584],"type":"Point"}
}