{
  "type": "Feature",
  "properties": {
    "iso:country":"GB",
    "wof:name":"PL6 6SS",
    "wof:placetype":"postalcode"
},
  "geometry": {"coordinates":[-4.14169120188643,50.42718956458434],"type":"Point"}
}