{
  "type": "Feature",
  "properties": {
    "iso:country": "GB",
    "wof:name": "CO4 5RF",
    "wof:placetype": "postalcode"
  },
  "geometry": {"coordinates":[0.905972,51.939598],"type":"Point"}
}
