{
  "type": "Feature",
  "properties": {
    "iso:country":"GB",
    "wof:name":"CO4 5RF",
    "wof:placetype":"postalcode"
},
  "geometry": {"coordinates":[0.9059399319954,51.9395861955287],"type":"Point"}
}