{
  "type": "Feature",
  "properties": {
    "date:inception_lower": "1980-01-01",
    "date:inception_upper": "1980-01-01",
    "iso:country": "GB",
    "wof:name": "CO4 5RF",
    "wof:placetype": "postalcode"
  },
  "geometry": {"coordinates":[0.910558,51.938972],"type":"Point"}
}
