{
  "type": "Feature",
  "properties": {
    "date:inception_lower": "2017-02-01",
    "date:inception_upper": "2017-02-01",
    "iso:country": "GB",
    "wof:name": "ME10 3FQ",
    "wof:placetype": "postalcode"
  },
  "geometry": {"coordinates":[0.767493,51.34091],"type":"Point"}
}
