{
  "type": "Feature",
  "properties": {
    "iso:country": "GB",
    "wof:name": "FK3 9BN",
    "wof:placetype": "postalcode"
  },
  "geometry": {"coordinates":[-3.713935,56.018871],"type":"Point"}
}
