{
  "type": "Feature",
  "properties": {
    "iso:country":"GB",
    "wof:name":"FK3 9BN",
    "wof:placetype":"postalcode"
},
  "geometry": {"coordinates":[-3.71393492540709,56.01887053774621],"type":"Point"}
}