{
  "type": "Feature",
  "properties": {
    "iso:country":"GB",
    "wof:name":"G11 6QE",
    "wof:placetype":"postalcode"
},
  "geometry": {"coordinates":[-4.3001872925095,55.87010189208203],"type":"Point"}
}