{
  "type": "Feature",
  "properties": {
    "iso:country": "GB",
    "wof:name": "E10 5BL",
    "wof:placetype": "postalcode"
  },
  "geometry": {"coordinates":[-0.011471,51.572363],"type":"Point"}
}
