{
  "type": "Feature",
  "properties": {
    "iso:country":"GB",
    "wof:name":"CV34 6GH",
    "wof:placetype":"postalcode"
},
  "geometry": {"coordinates":[-1.54328265236925,52.26955635032579],"type":"Point"}
}