{
  "type": "Feature",
  "properties": {
    "iso:country": "GB",
    "wof:name": "HP2 6PD",
    "wof:placetype": "postalcode"
  },
  "geometry": {"coordinates":[-0.466755,51.773249],"type":"Point"}
}
