{
  "type": "Feature",
  "properties": {
    "iso:country":"GB",
    "wof:name":"HP2 6PD",
    "wof:placetype":"postalcode"
},
  "geometry": {"coordinates":[-0.46675494592791,51.77324898534884],"type":"Point"}
}