{
  "type": "Feature",
  "properties": {
    "iso:country":"GB",
    "wof:name":"NG6 8YZ",
    "wof:placetype":"postalcode"
},
  "geometry": {"coordinates":[-1.19489144624244,53.01320486138906],"type":"Point"}
}