{
  "type": "Feature",
  "properties": {
    "iso:country": "GB",
    "wof:name": "NG6 8YZ",
    "wof:placetype": "postalcode"
  },
  "geometry": {"coordinates":[-1.194891,53.013205],"type":"Point"}
}
