{
  "type": "Feature",
  "properties": {
    "iso:country": "GB",
    "wof:name": "CV22 6RN",
    "wof:placetype": "postalcode"
  },
  "geometry": {"coordinates":[-1.29126,52.338178],"type":"Point"}
}
