{
  "type": "Feature",
  "properties": {
    "iso:country":"GB",
    "wof:name":"CV22 6RN",
    "wof:placetype":"postalcode"
},
  "geometry": {"coordinates":[-1.29125969012659,52.33817758302409],"type":"Point"}
}