{
  "type": "Feature",
  "properties": {
    "iso:country":"GB",
    "wof:name":"HR2 8PT",
    "wof:placetype":"postalcode"
},
  "geometry": {"coordinates":[-2.72800065102805,51.90834758508536],"type":"Point"}
}