{
  "type": "Feature",
  "properties": {
    "iso:country": "GB",
    "wof:name": "HR2 8PT",
    "wof:placetype": "postalcode"
  },
  "geometry": {"coordinates":[-2.728001,51.908348],"type":"Point"}
}
