{
  "type": "Feature",
  "properties": {
    "date:inception_lower":"1997-06-01",
    "date:inception_upper":"1997-06-30",
    "iso:country":"GB",
    "wof:name":"DN3 2RU",
    "wof:placetype":"postalcode"
},
  "geometry": {"coordinates":[-1.050928,53.539704],"type":"Point"}
}