{
  "type": "Feature",
  "properties": {
    "iso:country": "GB",
    "wof:name": "DN3 2RU",
    "wof:placetype": "postalcode"
  },
  "geometry": {"coordinates":[-1.050928,53.539704],"type":"Point"}
}
