{
  "type": "Feature",
  "properties": {
    "iso:country":"GB",
    "wof:name":"OX9 3YU",
    "wof:placetype":"postalcode"
},
  "geometry": {"coordinates":[-0.9635016883121,51.74797186976588],"type":"Point"}
}