{
  "type": "Feature",
  "properties": {
    "iso:country": "GB",
    "wof:name": "OX9 3YU",
    "wof:placetype": "postalcode"
  },
  "geometry": {"coordinates":[-0.963502,51.747972],"type":"Point"}
}
