{
  "type": "Feature",
  "properties": {
    "iso:country":"GB",
    "wof:name":"TD9 0QT",
    "wof:placetype":"postalcode"
},
  "geometry": {"coordinates":[-2.81184192373688,55.17875468459238],"type":"Point"}
}