{
  "type": "Feature",
  "properties": {
    "date:inception_lower": "2021-06-01",
    "date:inception_upper": "2021-06-01",
    "iso:country": "GB",
    "wof:name": "NR17 1TJ",
    "wof:placetype": "postalcode"
  },
  "geometry": {"coordinates":[0.976903,52.536909],"type":"Point"}
}
