{
  "type": "Feature",
  "properties": {
    "iso:country": "GB",
    "wof:name": "SY20 9HE",
    "wof:placetype": "postalcode"
  },
  "geometry": {"coordinates":[-3.814159,52.646514],"type":"Point"}
}
