{
  "type": "Feature",
  "properties": {
    "iso:country":"GB",
    "wof:name":"SY20 9HE",
    "wof:placetype":"postalcode"
},
  "geometry": {"coordinates":[-3.81415864220292,52.64651425663818],"type":"Point"}
}