{
  "type": "Feature",
  "properties": {
    "date:inception_lower":"1980-01-01",
    "date:inception_upper":"1980-01-31",
    "iso:country":"GB",
    "wof:name":"SY20 9HE",
    "wof:placetype":"postalcode"
},
  "geometry": {"coordinates":[-3.814159,52.646514],"type":"Point"}
}