{
  "type": "Feature",
  "properties": {
    "iso:country":"GB",
    "wof:name":"G81 3DE",
    "wof:placetype":"postalcode"
},
  "geometry": {"coordinates":[-4.40881873258204,55.91084058698521],"type":"Point"}
}