{
  "type": "Feature",
  "properties": {
    "iso:country":"GB",
    "wof:name":"NG3 3DF",
    "wof:placetype":"postalcode"
},
  "geometry": {"coordinates":[-1.12623909117774,52.96955302866328],"type":"Point"}
}