{
  "type": "Feature",
  "properties": {
    "iso:country": "GB",
    "wof:name": "TQ2 5AZ",
    "wof:placetype": "postalcode"
  },
  "geometry": {"coordinates":[-3.542616,50.467715],"type":"Point"}
}
