{
  "type": "Feature",
  "properties": {
    "iso:country":"GB",
    "wof:name":"TQ2 5AZ",
    "wof:placetype":"postalcode"
},
  "geometry": {"coordinates":[-3.5426159102918,50.46771536480415],"type":"Point"}
}