{
  "type": "Feature",
  "properties": {
    "iso:country":"GB",
    "wof:name":"BH7 7HL",
    "wof:placetype":"postalcode"
},
  "geometry": {"coordinates":[-1.82324041870335,50.74386185121072],"type":"Point"}
}