{
  "type": "Feature",
  "properties": {
    "iso:country": "GB",
    "wof:name": "EX2 7EW",
    "wof:placetype": "postalcode"
  },
  "geometry": {"coordinates":[-3.483415,50.691883],"type":"Point"}
}
