{
  "type": "Feature",
  "properties": {
    "iso:country":"GB",
    "wof:name":"EX2 7EW",
    "wof:placetype":"postalcode"
},
  "geometry": {"coordinates":[-3.48341532755371,50.69188300778764],"type":"Point"}
}