{
  "type": "Feature",
  "properties": {
    "iso:country":"GB",
    "wof:name":"CR4 2DS",
    "wof:placetype":"postalcode"
},
  "geometry": {"coordinates":[-0.15672529253863,51.41681666050124],"type":"Point"}
}