{
  "type": "Feature",
  "properties": {
    "iso:country":"GB",
    "wof:name":"W7 3BX",
    "wof:placetype":"postalcode"
},
  "geometry": {"coordinates":[-0.34438539908281,51.51437917597373],"type":"Point"}
}