{
  "type": "Feature",
  "properties": {
    "iso:country":"GB",
    "wof:name":"RG2 8EF",
    "wof:placetype":"postalcode"
},
  "geometry": {"coordinates":[-0.94361694475257,51.42847353258787],"type":"Point"}
}