{
  "type": "Feature",
  "properties": {
    "date:inception_lower": "2018-04-01",
    "date:inception_upper": "2018-04-01",
    "iso:country": "GB",
    "wof:name": "NG12 5DY",
    "wof:placetype": "postalcode"
  },
  "geometry": {"coordinates":[-1.091434,52.87085],"type":"Point"}
}
