{
  "type": "Feature",
  "properties": {
    "iso:country": "GB",
    "wof:name": "MK4 2HE",
    "wof:placetype": "postalcode"
  },
  "geometry": {"coordinates":[-0.778735,52.0087],"type":"Point"}
}
