{
  "type": "Feature",
  "properties": {
    "iso:country": "GB",
    "wof:name": "G84 7EJ",
    "wof:placetype": "postalcode"
  },
  "geometry": {"coordinates":[-4.72826,56.005717],"type":"Point"}
}
