{
  "type": "Feature",
  "properties": {
    "iso:country":"GB",
    "wof:name":"G84 7EJ",
    "wof:placetype":"postalcode"
},
  "geometry": {"coordinates":[-4.72826020984786,56.00571749630139],"type":"Point"}
}