{
  "type": "Feature",
  "properties": {
    "iso:country":"GB",
    "wof:name":"SK9 7LW",
    "wof:placetype":"postalcode"
},
  "geometry": {"coordinates":[-2.22772575942683,53.30758944098417],"type":"Point"}
}