{
  "type": "Feature",
  "properties": {
    "date:inception_lower": "1980-01-01",
    "date:inception_upper": "1980-01-01",
    "iso:country": "GB",
    "wof:name": "SK9 7LW",
    "wof:placetype": "postalcode"
  },
  "geometry": {"coordinates":[-2.227664,53.307561],"type":"Point"}
}
