{
  "type": "Feature",
  "properties": {
    "iso:country":"GB",
    "wof:name":"BD7 3ND",
    "wof:placetype":"postalcode"
},
  "geometry": {"coordinates":[-1.77932331549637,53.77825218606965],"type":"Point"}
}