{
  "type": "Feature",
  "properties": {
    "iso:country":"GB",
    "wof:name":"HR6 9EX",
    "wof:placetype":"postalcode"
},
  "geometry": {"coordinates":[-2.89360035105059,52.22016932899964],"type":"Point"}
}