{
  "type": "Feature",
  "properties": {
    "date:inception_lower": "1980-01-01",
    "date:inception_upper": "1980-01-01",
    "iso:country": "GB",
    "wof:name": "ST14 7BL",
    "wof:placetype": "postalcode"
  },
  "geometry": {"coordinates":[-1.872112,52.904501],"type":"Point"}
}
