{
  "type": "Feature",
  "properties": {
    "iso:country":"GB",
    "wof:name":"RG24 9LY",
    "wof:placetype":"postalcode"
},
  "geometry": {"coordinates":[-1.10946854251834,51.28385760607321],"type":"Point"}
}