{
  "type": "Feature",
  "properties": {
    "iso:country":"GB",
    "wof:name":"IG6 2GQ",
    "wof:placetype":"postalcode"
},
  "geometry": {"coordinates":[0.07630920316875,51.59981647033684],"type":"Point"}
}