{
  "type": "Feature",
  "properties": {
    "iso:country":"GB",
    "wof:name":"SR7 0EH",
    "wof:placetype":"postalcode"
},
  "geometry": {"coordinates":[-1.35660589080213,54.84540849003846],"type":"Point"}
}