{
  "type": "Feature",
  "properties": {
    "iso:country": "GB",
    "wof:name": "SR7 0EH",
    "wof:placetype": "postalcode"
  },
  "geometry": {"coordinates":[-1.356606,54.845408],"type":"Point"}
}
