{
  "type": "Feature",
  "properties": {
    "date:inception_lower":"1993-01-01",
    "date:inception_upper":"1993-01-31",
    "iso:country":"GB",
    "wof:name":"GU30 7EY",
    "wof:placetype":"postalcode"
},
  "geometry": {"coordinates":[-0.80402,51.074833],"type":"Point"}
}