{
  "type": "Feature",
  "properties": {
    "iso:country":"GB",
    "wof:name":"SK6 6DZ",
    "wof:placetype":"postalcode"
},
  "geometry": {"coordinates":[-2.07372250666882,53.39515386142025],"type":"Point"}
}