{
  "type": "Feature",
  "properties": {
    "iso:country":"GB",
    "wof:name":"L12 4XA",
    "wof:placetype":"postalcode"
},
  "geometry": {"coordinates":[-2.89706273816063,53.43288407066623],"type":"Point"}
}