{
  "type": "Feature",
  "properties": {
    "iso:country":"GB",
    "wof:name":"TN6 3PY",
    "wof:placetype":"postalcode"
},
  "geometry": {"coordinates":[0.22350496165797,51.0376515408915],"type":"Point"}
}