{
  "type": "Feature",
  "properties": {
    "iso:country":"GB",
    "wof:name":"SL0 0RA",
    "wof:placetype":"postalcode"
},
  "geometry": {"coordinates":[-0.52709286303276,51.5382616933212],"type":"Point"}
}