{
  "type": "Feature",
  "properties": {
    "iso:country":"GB",
    "wof:name":"AB32 6WA",
    "wof:placetype":"postalcode"
},
  "geometry": {"coordinates":[-2.28705508236847,57.15701301965792],"type":"Point"}
}