{
  "type": "Feature",
  "properties": {
    "date:inception_lower": "1990-08-01",
    "date:inception_upper": "1990-08-01",
    "iso:country": "GB",
    "wof:name": "AB32 6WA",
    "wof:placetype": "postalcode"
  },
  "geometry": {"coordinates":[-2.287055,57.157013],"type":"Point"}
}
