{
  "type": "Feature",
  "properties": {
    "date:inception_lower": "1980-01-01",
    "date:inception_upper": "1980-01-01",
    "iso:country": "GB",
    "wof:name": "CT18 8DE",
    "wof:placetype": "postalcode"
  },
  "geometry": {"coordinates":[1.094037,51.114313],"type":"Point"}
}
