{
  "type": "Feature",
  "properties": {
    "iso:country": "GB",
    "wof:name": "IP7 6BB",
    "wof:placetype": "postalcode"
  },
  "geometry": {"coordinates":[0.961885,52.049172],"type":"Point"}
}
