{
  "type": "Feature",
  "properties": {
    "date:inception_lower": "1996-06-01",
    "date:inception_upper": "1996-06-01",
    "iso:country": "GB",
    "wof:name": "IP7 6BB",
    "wof:placetype": "postalcode"
  },
  "geometry": {"coordinates":[0.961901,52.049177],"type":"Point"}
}
