{
  "type": "Feature",
  "properties": {
    "iso:country":"GB",
    "wof:name":"DN38 6HG",
    "wof:placetype":"postalcode"
},
  "geometry": {"coordinates":[-0.40891139876476,53.57868692789662],"type":"Point"}
}