{
  "type": "Feature",
  "properties": {
    "date:inception_lower": "1980-01-01",
    "date:inception_upper": "1980-01-01",
    "iso:country": "GB",
    "wof:name": "DN38 6HG",
    "wof:placetype": "postalcode"
  },
  "geometry": {"coordinates":[-0.408911,53.578687],"type":"Point"}
}
