{
  "type": "Feature",
  "properties": {
    "iso:country": "GB",
    "wof:name": "DN38 6HG",
    "wof:placetype": "postalcode"
  },
  "geometry": {"coordinates":[-0.408911,53.578687],"type":"Point"}
}
