{
  "type": "Feature",
  "properties": {
    "iso:country":"GB",
    "wof:name":"TN22 5RY",
    "wof:placetype":"postalcode"
},
  "geometry": {"coordinates":[0.1431472805835,50.97598268989907],"type":"Point"}
}