{
  "type": "Feature",
  "properties": {
    "iso:country": "GB",
    "wof:name": "TN22 5RY",
    "wof:placetype": "postalcode"
  },
  "geometry": {"coordinates":[0.143147,50.975983],"type":"Point"}
}
