{
  "type": "Feature",
  "properties": {
    "iso:country":"GB",
    "wof:name":"NG5 2FR",
    "wof:placetype":"postalcode"
},
  "geometry": {"coordinates":[-1.14680274774125,52.98013913409736],"type":"Point"}
}