{
  "type": "Feature",
  "properties": {
    "iso:country":"GB",
    "wof:name":"MK40 3UN",
    "wof:placetype":"postalcode"
},
  "geometry": {"coordinates":[-0.44571415562127,52.13966620947131],"type":"Point"}
}