{
  "type": "Feature",
  "properties": {
    "iso:country":"GB",
    "wof:name":"NE31 1JG",
    "wof:placetype":"postalcode"
},
  "geometry": {"coordinates":[-1.50556968680102,54.97691208109957],"type":"Point"}
}