{
  "type": "Feature",
  "properties": {
    "iso:country": "GB",
    "wof:name": "NE31 1JG",
    "wof:placetype": "postalcode"
  },
  "geometry": {"coordinates":[-1.50557,54.976912],"type":"Point"}
}
