{
  "type": "Feature",
  "properties": {
    "iso:country":"GB",
    "wof:name":"BB2 1XH",
    "wof:placetype":"postalcode"
},
  "geometry": {"coordinates":[-2.49575544534806,53.74258190927082],"type":"Point"}
}