{
  "type": "Feature",
  "properties": {
    "iso:country":"GB",
    "wof:name":"RH13 0SE",
    "wof:placetype":"postalcode"
},
  "geometry": {"coordinates":[-0.4032796928756,51.06844611088945],"type":"Point"}
}