{
  "type": "Feature",
  "properties": {
    "iso:country":"GB",
    "wof:name":"B8 3PE",
    "wof:placetype":"postalcode"
},
  "geometry": {"coordinates":[-1.83343548969212,52.48935675647358],"type":"Point"}
}