{
  "type": "Feature",
  "properties": {
    "iso:country":"GB",
    "wof:name":"RG42 1SA",
    "wof:placetype":"postalcode"
},
  "geometry": {"coordinates":[-0.77231598691025,51.42197621017143],"type":"Point"}
}