{
  "type": "Feature",
  "properties": {
    "iso:country":"GB",
    "wof:name":"PR8 6AX",
    "wof:placetype":"postalcode"
},
  "geometry": {"coordinates":[-2.97723417851285,53.64597990281931],"type":"Point"}
}