{
  "type": "Feature",
  "properties": {
    "iso:country":"GB",
    "wof:name":"SA62 4BT",
    "wof:placetype":"postalcode"
},
  "geometry": {"coordinates":[-4.96644708406786,51.82215133694981],"type":"Point"}
}