{
  "type": "Feature",
  "properties": {
    "iso:country":"GB",
    "wof:name":"EH39 4SS",
    "wof:placetype":"postalcode"
},
  "geometry": {"coordinates":[-2.71746257739492,56.06138942950309],"type":"Point"}
}