{
  "type": "Feature",
  "properties": {
    "date:inception_lower": "2000-06-01",
    "date:inception_upper": "2000-06-01",
    "iso:country": "GB",
    "wof:name": "EH39 4SS",
    "wof:placetype": "postalcode"
  },
  "geometry": {"coordinates":[-2.717463,56.061389],"type":"Point"}
}
