{
  "type": "Feature",
  "properties": {
    "iso:country":"GB",
    "wof:name":"CV2 2BJ",
    "wof:placetype":"postalcode"
},
  "geometry": {"coordinates":[-1.43414779461753,52.42395947905899],"type":"Point"}
}