{
  "type": "Feature",
  "properties": {
    "iso:country": "GB",
    "wof:name": "CV2 2BJ",
    "wof:placetype": "postalcode"
  },
  "geometry": {"coordinates":[-1.434148,52.423959],"type":"Point"}
}
