{
  "type": "Feature",
  "properties": {
    "iso:country":"GB",
    "wof:name":"GU4 8PR",
    "wof:placetype":"postalcode"
},
  "geometry": {"coordinates":[-0.53709350062699,51.23196567092545],"type":"Point"}
}