{
  "type": "Feature",
  "properties": {
    "iso:country":"GB",
    "wof:name":"DN8 5PY",
    "wof:placetype":"postalcode"
},
  "geometry": {"coordinates":[-0.95312877495747,53.60580062806893],"type":"Point"}
}