{
  "type": "Feature",
  "properties": {
    "date:inception_lower": "1980-01-01",
    "date:inception_upper": "1980-01-01",
    "iso:country": "GB",
    "wof:name": "NG12 2GU",
    "wof:placetype": "postalcode"
  },
  "geometry": {"coordinates":[-1.023924,52.947856],"type":"Point"}
}
