{
  "type": "Feature",
  "properties": {
    "iso:country": "GB",
    "wof:name": "NG12 2GU",
    "wof:placetype": "postalcode"
  },
  "geometry": {"coordinates":[-1.023924,52.947856],"type":"Point"}
}
