{
  "type": "Feature",
  "properties": {
    "date:inception_lower":"1987-04-01",
    "date:inception_upper":"1987-04-30",
    "iso:country":"GB",
    "wof:name":"NW1 0XN",
    "wof:placetype":"postalcode"
},
  "geometry": {"coordinates":[-0.132384,51.538991],"type":"Point"}
}