{
  "type": "Feature",
  "properties": {
    "iso:country":"GB",
    "wof:name":"NW1 0XN",
    "wof:placetype":"postalcode"
},
  "geometry": {"coordinates":[-0.13238366323986,51.53899095417243],"type":"Point"}
}