{
  "type": "Feature",
  "properties": {
    "iso:country":"GB",
    "wof:name":"CO12 5EL",
    "wof:placetype":"postalcode"
},
  "geometry": {"coordinates":[1.22639060978054,51.92657425740332],"type":"Point"}
}