{
  "type": "Feature",
  "properties": {
    "iso:country":"GB",
    "wof:name":"BB1 9SZ",
    "wof:placetype":"postalcode"
},
  "geometry": {"coordinates":[-2.47520593168838,53.76496470174602],"type":"Point"}
}