{
  "type": "Feature",
  "properties": {
    "iso:country":"GB",
    "wof:name":"NW3 2TS",
    "wof:placetype":"postalcode"
},
  "geometry": {"coordinates":[-0.16433866631707,51.55583456852428],"type":"Point"}
}