{
  "type": "Feature",
  "properties": {
    "iso:country":"GB",
    "wof:name":"CO6 1JR",
    "wof:placetype":"postalcode"
},
  "geometry": {"coordinates":[0.74713120539343,51.90383999319686],"type":"Point"}
}