{
  "type": "Feature",
  "properties": {
    "iso:country": "GB",
    "wof:name": "RG7 4TG",
    "wof:placetype": "postalcode"
  },
  "geometry": {"coordinates":[-1.194981,51.379998],"type":"Point"}
}
