{
  "type": "Feature",
  "properties": {
    "date:inception_lower": "1980-01-01",
    "date:inception_upper": "1980-01-01",
    "iso:country": "GB",
    "wof:name": "NG6 8BA",
    "wof:placetype": "postalcode"
  },
  "geometry": {"coordinates":[-1.190008,53.016866],"type":"Point"}
}
