{
  "type": "Feature",
  "properties": {
    "iso:country":"GB",
    "wof:name":"NG6 8BA",
    "wof:placetype":"postalcode"
},
  "geometry": {"coordinates":[-1.19000848056454,53.01686635433177],"type":"Point"}
}