{
  "type": "Feature",
  "properties": {
    "iso:country":"GB",
    "wof:name":"CF15 7SL",
    "wof:placetype":"postalcode"
},
  "geometry": {"coordinates":[-3.26766100435922,51.54990549373732],"type":"Point"}
}