{
  "type": "Feature",
  "properties": {
    "date:inception_lower":"1999-06-01",
    "date:inception_upper":"1999-06-30",
    "iso:country":"GB",
    "wof:name":"CF15 7SL",
    "wof:placetype":"postalcode"
},
  "geometry": {"coordinates":[-3.267661,51.549905],"type":"Point"}
}