{
  "type": "Feature",
  "properties": {
    "iso:country":"GB",
    "wof:name":"IP25 6NJ",
    "wof:placetype":"postalcode"
},
  "geometry": {"coordinates":[0.73204299762498,52.58282058442122],"type":"Point"}
}