{
  "type": "Feature",
  "properties": {
    "date:inception_lower": "2007-09-01",
    "date:inception_upper": "2007-09-01",
    "iso:country": "GB",
    "wof:name": "RM17 5DU",
    "wof:placetype": "postalcode"
  },
  "geometry": {"coordinates":[0.320595,51.482243],"type":"Point"}
}
