{
  "type": "Feature",
  "properties": {
    "iso:country":"GB",
    "wof:name":"RM17 5DU",
    "wof:placetype":"postalcode"
},
  "geometry": {"coordinates":[0.3210888954801,51.48287984642184],"type":"Point"}
}