{
  "type": "Feature",
  "properties": {
    "iso:country":"GB",
    "wof:name":"WA16 0NX",
    "wof:placetype":"postalcode"
},
  "geometry": {"coordinates":[-2.38142343675596,53.30845512390303],"type":"Point"}
}