{
  "type": "Feature",
  "properties": {
    "iso:country":"GB",
    "wof:name":"PL17 7QP",
    "wof:placetype":"postalcode"
},
  "geometry": {"coordinates":[-4.30918447814576,50.50547389465478],"type":"Point"}
}