{
  "type": "Feature",
  "properties": {
    "date:inception_lower": "1992-08-01",
    "date:inception_upper": "1992-08-01",
    "iso:country": "GB",
    "wof:name": "PL17 7QP",
    "wof:placetype": "postalcode"
  },
  "geometry": {"coordinates":[-4.309184,50.505474],"type":"Point"}
}
