{
  "type": "Feature",
  "properties": {
    "date:inception_lower":"1997-12-01",
    "date:inception_upper":"1997-12-31",
    "iso:country":"GB",
    "wof:name":"TN24 9SF",
    "wof:placetype":"postalcode"
},
  "geometry": {"coordinates":[0.895286,51.159693],"type":"Point"}
}