{
  "type": "Feature",
  "properties": {
    "date:inception_lower": "1985-04-01",
    "date:inception_upper": "1985-04-01",
    "iso:country": "GB",
    "wof:name": "TS15 9UN",
    "wof:placetype": "postalcode"
  },
  "geometry": {"coordinates":[-1.356708,54.493467],"type":"Point"}
}
