{
  "type": "Feature",
  "properties": {
    "iso:country":"GB",
    "wof:name":"TS15 9UN",
    "wof:placetype":"postalcode"
},
  "geometry": {"coordinates":[-1.35670839172497,54.49346664521983],"type":"Point"}
}