{
  "type": "Feature",
  "properties": {
    "iso:country": "GB",
    "wof:name": "BS48 1LY",
    "wof:placetype": "postalcode"
  },
  "geometry": {"coordinates":[-2.743273,51.435286],"type":"Point"}
}
