{
  "type": "Feature",
  "properties": {
    "iso:country":"GB",
    "wof:name":"BS48 1LY",
    "wof:placetype":"postalcode"
},
  "geometry": {"coordinates":[-2.74326913040222,51.43526094156334],"type":"Point"}
}