{
  "type": "Feature",
  "properties": {
    "iso:country":"GB",
    "wof:name":"DN8 4RY",
    "wof:placetype":"postalcode"
},
  "geometry": {"coordinates":[-0.95092276239645,53.62468449925746],"type":"Point"}
}