{
  "type": "Feature",
  "properties": {
    "iso:country": "GB",
    "wof:name": "DN8 4RY",
    "wof:placetype": "postalcode"
  },
  "geometry": {"coordinates":[-0.950923,53.624684],"type":"Point"}
}
