{
  "type": "Feature",
  "properties": {
    "iso:country":"GB",
    "wof:name":"B60 2DZ",
    "wof:placetype":"postalcode"
},
  "geometry": {"coordinates":[-2.04797665139556,52.3229946298102],"type":"Point"}
}