{
  "type": "Feature",
  "properties": {
    "date:inception_lower":"1997-12-01",
    "date:inception_upper":"1997-12-31",
    "iso:country":"GB",
    "wof:name":"BS15 8DP",
    "wof:placetype":"postalcode"
},
  "geometry": {"coordinates":[-2.51604,51.454204],"type":"Point"}
}