{
  "type": "Feature",
  "properties": {
    "iso:country": "GB",
    "wof:name": "BS15 8DP",
    "wof:placetype": "postalcode"
  },
  "geometry": {"coordinates":[-2.51604,51.454204],"type":"Point"}
}
