{
  "type": "Feature",
  "properties": {
    "iso:country": "GB",
    "wof:name": "NG32 1HA",
    "wof:placetype": "postalcode"
  },
  "geometry": {"coordinates":[-0.799578,52.884258],"type":"Point"}
}
