{
  "type": "Feature",
  "properties": {
    "iso:country":"GB",
    "wof:name":"NG32 1HA",
    "wof:placetype":"postalcode"
},
  "geometry": {"coordinates":[-0.79957821819039,52.88425813940179],"type":"Point"}
}