{
  "type": "Feature",
  "properties": {
    "iso:country":"GB",
    "wof:name":"PR25 3DT",
    "wof:placetype":"postalcode"
},
  "geometry": {"coordinates":[-2.68650619609902,53.68286635893634],"type":"Point"}
}