{
  "type": "Feature",
  "properties": {
    "iso:country": "GB",
    "wof:name": "HD9 6BP",
    "wof:placetype": "postalcode"
  },
  "geometry": {"coordinates":[-1.795084,53.604468],"type":"Point"}
}
