{
  "type": "Feature",
  "properties": {
    "iso:country": "GB",
    "wof:name": "CF3 3AH",
    "wof:placetype": "postalcode"
  },
  "geometry": {"coordinates":[-3.134693,51.502334],"type":"Point"}
}
