{
  "type": "Feature",
  "properties": {
    "iso:country":"GB",
    "wof:name":"S72 9BZ",
    "wof:placetype":"postalcode"
},
  "geometry": {"coordinates":[-1.40381138933951,53.6118236807758],"type":"Point"}
}