{
  "type": "Feature",
  "properties": {
    "date:inception_lower":"1980-01-01",
    "date:inception_upper":"1980-01-31",
    "iso:country":"GB",
    "wof:name":"PE1 4LP",
    "wof:placetype":"postalcode"
},
  "geometry": {"coordinates":[-0.228107,52.597469],"type":"Point"}
}