{
  "type": "Feature",
  "properties": {
    "iso:country":"GB",
    "wof:name":"WS7 0JS",
    "wof:placetype":"postalcode"
},
  "geometry": {"coordinates":[-1.89800820908468,52.66418287448937],"type":"Point"}
}