{
  "type": "Feature",
  "properties": {
    "iso:country": "GB",
    "wof:name": "WS7 0JS",
    "wof:placetype": "postalcode"
  },
  "geometry": {"coordinates":[-1.898008,52.664183],"type":"Point"}
}
