{
  "type": "Feature",
  "properties": {
    "date:inception_lower":"2006-01-01",
    "date:inception_upper":"2006-01-31",
    "iso:country":"GB",
    "wof:name":"LL12 0UG",
    "wof:placetype":"postalcode"
},
  "geometry": {"coordinates":[-3.009726,53.09757],"type":"Point"}
}