{
  "type": "Feature",
  "properties": {
    "iso:country":"GB",
    "wof:name":"LL12 0UG",
    "wof:placetype":"postalcode"
},
  "geometry": {"coordinates":[-3.00972639081107,53.09756989004138],"type":"Point"}
}