{
  "type": "Feature",
  "properties": {
    "iso:country": "GB",
    "wof:name": "LL12 0UG",
    "wof:placetype": "postalcode"
  },
  "geometry": {"coordinates":[-3.009652,53.097596],"type":"Point"}
}
