{
  "type": "Feature",
  "properties": {
    "date:inception_lower": "2003-06-01",
    "date:inception_upper": "2003-06-01",
    "iso:country": "GB",
    "wof:name": "BA14 0RH",
    "wof:placetype": "postalcode"
  },
  "geometry": {"coordinates":[-2.208809,51.310191],"type":"Point"}
}
