{
  "type": "Feature",
  "properties": {
    "iso:country": "GB",
    "wof:name": "BA14 0RH",
    "wof:placetype": "postalcode"
  },
  "geometry": {"coordinates":[-2.208809,51.310191],"type":"Point"}
}
