{
  "type": "Feature",
  "properties": {
    "iso:country": "GB",
    "wof:name": "SA43 1DQ",
    "wof:placetype": "postalcode"
  },
  "geometry": {"coordinates":[-4.652801,52.084685],"type":"Point"}
}
