{
  "type": "Feature",
  "properties": {
    "iso:country":"GB",
    "wof:name":"SA4 8NS",
    "wof:placetype":"postalcode"
},
  "geometry": {"coordinates":[-4.0000431757866,51.71635251724781],"type":"Point"}
}