{
  "type": "Feature",
  "properties": {
    "iso:country":"GB",
    "wof:name":"KT22 7PJ",
    "wof:placetype":"postalcode"
},
  "geometry": {"coordinates":[-0.33282654113996,51.30921477520482],"type":"Point"}
}