{
  "type": "Feature",
  "properties": {
    "iso:country":"GB",
    "wof:name":"BA2 2BQ",
    "wof:placetype":"postalcode"
},
  "geometry": {"coordinates":[-2.38070905624113,51.36364578634694],"type":"Point"}
}