{
  "type": "Feature",
  "properties": {
    "iso:country":"GB",
    "wof:name":"BA21 3AB",
    "wof:placetype":"postalcode"
},
  "geometry": {"coordinates":[-2.64776756627209,50.9460569860019],"type":"Point"}
}