{
  "type": "Feature",
  "properties": {
    "iso:country": "GB",
    "wof:name": "BA21 3AB",
    "wof:placetype": "postalcode"
  },
  "geometry": {"coordinates":[-2.647768,50.946057],"type":"Point"}
}
