{
  "type": "Feature",
  "properties": {
    "iso:country": "GB",
    "wof:name": "KW1 4PL",
    "wof:placetype": "postalcode"
  },
  "geometry": {"coordinates":[-3.067203,58.443147],"type":"Point"}
}
