{
  "type": "Feature",
  "properties": {
    "date:inception_lower":"1995-12-01",
    "date:inception_upper":"1995-12-31",
    "iso:country":"GB",
    "wof:name":"KW1 4PL",
    "wof:placetype":"postalcode"
},
  "geometry": {"coordinates":[-3.067203,58.443147],"type":"Point"}
}