{
  "type": "Feature",
  "properties": {
    "iso:country":"GB",
    "wof:name":"KW1 4PL",
    "wof:placetype":"postalcode"
},
  "geometry": {"coordinates":[-3.06720293099274,58.44314673556735],"type":"Point"}
}