{
  "type": "Feature",
  "properties": {
    "iso:country": "GB",
    "wof:name": "B21 8PT",
    "wof:placetype": "postalcode"
  },
  "geometry": {"coordinates":[-1.946601,52.512341],"type":"Point"}
}
