{
  "type": "Feature",
  "properties": {
    "iso:country":"GB",
    "wof:name":"B21 8PT",
    "wof:placetype":"postalcode"
},
  "geometry": {"coordinates":[-1.9466012814093,52.51234105212752],"type":"Point"}
}