{
  "type": "Feature",
  "properties": {
    "iso:country":"GB",
    "wof:name":"B98 0BZ",
    "wof:placetype":"postalcode"
},
  "geometry": {"coordinates":[-1.89269667054122,52.295472877119],"type":"Point"}
}