{
  "type": "Feature",
  "properties": {
    "iso:country":"GB",
    "wof:name":"GL7 6QA",
    "wof:placetype":"postalcode"
},
  "geometry": {"coordinates":[-1.97789209086418,51.68796335412447],"type":"Point"}
}