{
  "type": "Feature",
  "properties": {
    "iso:country": "GB",
    "wof:name": "GL7 6QA",
    "wof:placetype": "postalcode"
  },
  "geometry": {"coordinates":[-1.977892,51.687963],"type":"Point"}
}
