{
  "type": "Feature",
  "properties": {
    "iso:country":"GB",
    "wof:name":"LN2 2ET",
    "wof:placetype":"postalcode"
},
  "geometry": {"coordinates":[-0.53489988506567,53.247257425971],"type":"Point"}
}