{
  "type": "Feature",
  "properties": {
    "iso:country": "GB",
    "wof:name": "LN2 2ET",
    "wof:placetype": "postalcode"
  },
  "geometry": {"coordinates":[-0.5349,53.247257],"type":"Point"}
}
