{
  "type": "Feature",
  "properties": {
    "iso:country":"GB",
    "wof:name":"GL6 9BD",
    "wof:placetype":"postalcode"
},
  "geometry": {"coordinates":[-2.16676553629903,51.70212462862221],"type":"Point"}
}