{
  "type": "Feature",
  "properties": {
    "date:inception_lower":"1980-01-01",
    "date:inception_upper":"1980-01-31",
    "iso:country":"GB",
    "wof:name":"GL6 9BD",
    "wof:placetype":"postalcode"
},
  "geometry": {"coordinates":[-2.166765,51.702125],"type":"Point"}
}