{
  "type": "Feature",
  "properties": {
    "iso:country":"GB",
    "wof:name":"M15 5AT",
    "wof:placetype":"postalcode"
},
  "geometry": {"coordinates":[-2.24548349535853,53.45974026160717],"type":"Point"}
}