{
  "type": "Feature",
  "properties": {
    "date:inception_lower": "1996-12-01",
    "date:inception_upper": "1996-12-01",
    "iso:country": "GB",
    "wof:name": "M15 5AT",
    "wof:placetype": "postalcode"
  },
  "geometry": {"coordinates":[-2.245483,53.45974],"type":"Point"}
}
