{
  "type": "Feature",
  "properties": {
    "iso:country":"GB",
    "wof:name":"SY5 9NN",
    "wof:placetype":"postalcode"
},
  "geometry": {"coordinates":[-2.88963196707728,52.69894904022808],"type":"Point"}
}