{
  "type": "Feature",
  "properties": {
    "iso:country":"GB",
    "wof:name":"NE25 8TA",
    "wof:placetype":"postalcode"
},
  "geometry": {"coordinates":[-1.46866581940437,55.03735999742776],"type":"Point"}
}