{
  "type": "Feature",
  "properties": {
    "iso:country": "GB",
    "wof:name": "NE25 8TA",
    "wof:placetype": "postalcode"
  },
  "geometry": {"coordinates":[-1.468666,55.03736],"type":"Point"}
}
