{
  "type": "Feature",
  "properties": {
    "iso:country":"GB",
    "wof:name":"CO6 3QG",
    "wof:placetype":"postalcode"
},
  "geometry": {"coordinates":[0.82315999009976,51.8981095215125],"type":"Point"}
}