{
  "type": "Feature",
  "properties": {
    "iso:country": "GB",
    "wof:name": "CO6 3QG",
    "wof:placetype": "postalcode"
  },
  "geometry": {"coordinates":[0.82316,51.89811],"type":"Point"}
}
