{
  "type": "Feature",
  "properties": {
    "iso:country": "GB",
    "wof:name": "EX15 2TL",
    "wof:placetype": "postalcode"
  },
  "geometry": {"coordinates":[-3.366446,50.892465],"type":"Point"}
}
