{
  "type": "Feature",
  "properties": {
    "iso:country":"GB",
    "wof:name":"EX15 2TL",
    "wof:placetype":"postalcode"
},
  "geometry": {"coordinates":[-3.3664459222756,50.89246481761665],"type":"Point"}
}