{
  "type": "Feature",
  "properties": {
    "iso:country":"GB",
    "wof:name":"CB4 2AR",
    "wof:placetype":"postalcode"
},
  "geometry": {"coordinates":[0.13124465168581,52.22234068018876],"type":"Point"}
}