{
  "type": "Feature",
  "properties": {
    "iso:country": "GB",
    "wof:name": "GL52 2TB",
    "wof:placetype": "postalcode"
  },
  "geometry": {"coordinates":[-2.061985,51.901476],"type":"Point"}
}
