{
  "type": "Feature",
  "properties": {
    "iso:country":"GB",
    "wof:name":"CM17 9AT",
    "wof:placetype":"postalcode"
},
  "geometry": {"coordinates":[0.13307402807303,51.76019803474959],"type":"Point"}
}