{
  "type": "Feature",
  "properties": {
    "iso:country":"GB",
    "wof:name":"TF4 3QG",
    "wof:placetype":"postalcode"
},
  "geometry": {"coordinates":[-2.49272748874033,52.65352824749794],"type":"Point"}
}