{
  "type": "Feature",
  "properties": {
    "iso:country":"GB",
    "wof:name":"M25 3AB",
    "wof:placetype":"postalcode"
},
  "geometry": {"coordinates":[-2.28774897747481,53.53382748617921],"type":"Point"}
}