{
  "type": "Feature",
  "properties": {
    "iso:country":"GB",
    "wof:name":"B61 0GJ",
    "wof:placetype":"postalcode"
},
  "geometry": {"coordinates":[-2.05973194890438,52.36865029036041],"type":"Point"}
}