{
  "type": "Feature",
  "properties": {
    "iso:country":"GB",
    "wof:name":"BL0 9EU",
    "wof:placetype":"postalcode"
},
  "geometry": {"coordinates":[-2.32393254307623,53.64889308990957],"type":"Point"}
}