{
  "type": "Feature",
  "properties": {
    "date:inception_lower":"1980-01-01",
    "date:inception_upper":"1980-01-31",
    "iso:country":"GB",
    "wof:name":"BL0 9EU",
    "wof:placetype":"postalcode"
},
  "geometry": {"coordinates":[-2.323991,53.648909],"type":"Point"}
}