{
  "type": "Feature",
  "properties": {
    "iso:country": "GB",
    "wof:name": "BL0 9EU",
    "wof:placetype": "postalcode"
  },
  "geometry": {"coordinates":[-2.323991,53.648909],"type":"Point"}
}
