{
  "type": "Feature",
  "properties": {
    "iso:country": "GB",
    "wof:name": "PE21 6RA",
    "wof:placetype": "postalcode"
  },
  "geometry": {"coordinates":[-0.022126,52.977761],"type":"Point"}
}
