{
  "type": "Feature",
  "properties": {
    "iso:country":"GB",
    "wof:name":"PE21 6RA",
    "wof:placetype":"postalcode"
},
  "geometry": {"coordinates":[-0.02212570509761,52.97776110825973],"type":"Point"}
}