{
  "type": "Feature",
  "properties": {
    "iso:country":"GB",
    "wof:name":"OX7 4AY",
    "wof:placetype":"postalcode"
},
  "geometry": {"coordinates":[-1.46004943133252,51.97781986698121],"type":"Point"}
}