{
  "type": "Feature",
  "properties": {
    "iso:country": "GB",
    "wof:name": "PE28 4RN",
    "wof:placetype": "postalcode"
  },
  "geometry": {"coordinates":[-0.23452,52.318059],"type":"Point"}
}
