{
  "type": "Feature",
  "properties": {
    "iso:country":"GB",
    "wof:name":"PE28 4RN",
    "wof:placetype":"postalcode"
},
  "geometry": {"coordinates":[-0.23452050122335,52.31805929118775],"type":"Point"}
}