{
  "type": "Feature",
  "properties": {
    "date:inception_lower": "2013-07-01",
    "date:inception_upper": "2013-07-01",
    "iso:country": "GB",
    "wof:name": "KY4 9EH",
    "wof:placetype": "postalcode"
  },
  "geometry": {"coordinates":[-3.356132,56.118499],"type":"Point"}
}
