{
  "type": "Feature",
  "properties": {
    "date:inception_lower":"1980-01-01",
    "date:inception_upper":"1980-01-31",
    "iso:country":"GB",
    "wof:name":"WF8 2QL",
    "wof:placetype":"postalcode"
},
  "geometry": {"coordinates":[-1.30444,53.684723],"type":"Point"}
}