{
  "type": "Feature",
  "properties": {
    "iso:country":"GB",
    "wof:name":"WF8 2QL",
    "wof:placetype":"postalcode"
},
  "geometry": {"coordinates":[-1.30443995149331,53.68472268095929],"type":"Point"}
}