{
  "type": "Feature",
  "properties": {
    "iso:country": "GB",
    "wof:name": "WF8 2QL",
    "wof:placetype": "postalcode"
  },
  "geometry": {"coordinates":[-1.30444,53.684723],"type":"Point"}
}
