{
  "type": "Feature",
  "properties": {
    "iso:country":"GB",
    "wof:name":"MK16 9LW",
    "wof:placetype":"postalcode"
},
  "geometry": {"coordinates":[-0.65090754653181,52.09028603250353],"type":"Point"}
}