{
  "type": "Feature",
  "properties": {
    "iso:country":"GB",
    "wof:name":"SS9 5HY",
    "wof:placetype":"postalcode"
},
  "geometry": {"coordinates":[0.64141740478072,51.57282519649345],"type":"Point"}
}