{
  "type": "Feature",
  "properties": {
    "iso:country":"GB",
    "wof:name":"WN5 7JS",
    "wof:placetype":"postalcode"
},
  "geometry": {"coordinates":[-2.70634474905267,53.51470276215066],"type":"Point"}
}