{
  "type": "Feature",
  "properties": {
    "iso:country":"GB",
    "wof:name":"NR27 0DG",
    "wof:placetype":"postalcode"
},
  "geometry": {"coordinates":[1.3142124175067,52.92328217611496],"type":"Point"}
}