{
  "type": "Feature",
  "properties": {
    "date:inception_lower": "1990-02-01",
    "date:inception_upper": "1990-02-01",
    "iso:country": "GB",
    "wof:name": "NR27 0DG",
    "wof:placetype": "postalcode"
  },
  "geometry": {"coordinates":[1.314214,52.9233],"type":"Point"}
}
