{
  "type": "Feature",
  "properties": {
    "iso:country":"GB",
    "wof:name":"SE6 2LT",
    "wof:placetype":"postalcode"
},
  "geometry": {"coordinates":[-0.01628059340647,51.43856118529533],"type":"Point"}
}