{
  "type": "Feature",
  "properties": {
    "iso:country":"GB",
    "wof:name":"RH19 1DD",
    "wof:placetype":"postalcode"
},
  "geometry": {"coordinates":[-0.01784163334043,51.1249668690941],"type":"Point"}
}