{
  "type": "Feature",
  "properties": {
    "iso:country": "GB",
    "wof:name": "TR1 3QF",
    "wof:placetype": "postalcode"
  },
  "geometry": {"coordinates":[-5.079962,50.260181],"type":"Point"}
}
