{
  "type": "Feature",
  "properties": {
    "iso:country":"GB",
    "wof:name":"TR1 3QF",
    "wof:placetype":"postalcode"
},
  "geometry": {"coordinates":[-5.08001356472824,50.26018951755916],"type":"Point"}
}