{
  "type": "Feature",
  "properties": {
    "iso:country":"GB",
    "wof:name":"PE7 8NJ",
    "wof:placetype":"postalcode"
},
  "geometry": {"coordinates":[-0.27579797757632,52.53277364332484],"type":"Point"}
}