{
  "type": "Feature",
  "properties": {
    "date:inception_lower":"2009-03-01",
    "date:inception_upper":"2009-03-31",
    "iso:country":"GB",
    "wof:name":"PE7 8NJ",
    "wof:placetype":"postalcode"
},
  "geometry": {"coordinates":[-0.275798,52.532774],"type":"Point"}
}