{
  "type": "Feature",
  "properties": {
    "iso:country":"GB",
    "wof:name":"YO17 8RS",
    "wof:placetype":"postalcode"
},
  "geometry": {"coordinates":[-0.58890808081512,54.18426396365808],"type":"Point"}
}