{
  "type": "Feature",
  "properties": {
    "date:inception_lower": "1980-01-01",
    "date:inception_upper": "1980-01-01",
    "iso:country": "GB",
    "wof:name": "YO17 8RS",
    "wof:placetype": "postalcode"
  },
  "geometry": {"coordinates":[-0.588908,54.184264],"type":"Point"}
}
