{
  "type": "Feature",
  "properties": {
    "iso:country": "GB",
    "wof:name": "SO22 6DT",
    "wof:placetype": "postalcode"
  },
  "geometry": {"coordinates":[-1.333026,51.076395],"type":"Point"}
}
