{
  "type": "Feature",
  "properties": {
    "iso:country":"GB",
    "wof:name":"SA9 1AF",
    "wof:placetype":"postalcode"
},
  "geometry": {"coordinates":[-3.77259349850696,51.7668451655759],"type":"Point"}
}