{
  "type": "Feature",
  "properties": {
    "date:inception_lower": "1980-01-01",
    "date:inception_upper": "1980-01-01",
    "iso:country": "GB",
    "wof:name": "WF4 1NL",
    "wof:placetype": "postalcode"
  },
  "geometry": {"coordinates":[-1.429026,53.655369],"type":"Point"}
}
