{
  "type": "Feature",
  "properties": {
    "iso:country": "GB",
    "wof:name": "WF4 1NL",
    "wof:placetype": "postalcode"
  },
  "geometry": {"coordinates":[-1.429026,53.655369],"type":"Point"}
}
