{
  "type": "Feature",
  "properties": {
    "iso:country":"GB",
    "wof:name":"BD8 7QH",
    "wof:placetype":"postalcode"
},
  "geometry": {"coordinates":[-1.77040607836647,53.80785985860464],"type":"Point"}
}