{
  "type": "Feature",
  "properties": {
    "date:inception_lower": "2000-10-01",
    "date:inception_upper": "2000-10-01",
    "iso:country": "GB",
    "wof:name": "WD24 5LS",
    "wof:placetype": "postalcode"
  },
  "geometry": {"coordinates":[-0.416309,51.683683],"type":"Point"}
}
