{
  "type": "Feature",
  "properties": {
    "iso:country":"GB",
    "wof:name":"WD24 5LS",
    "wof:placetype":"postalcode"
},
  "geometry": {"coordinates":[-0.41633206476101,51.68367754301158],"type":"Point"}
}