{
  "type": "Feature",
  "properties": {
    "iso:country":"GB",
    "wof:name":"WR14 3SN",
    "wof:placetype":"postalcode"
},
  "geometry": {"coordinates":[-2.30472823126955,52.10177961275137],"type":"Point"}
}