{
  "type": "Feature",
  "properties": {
    "iso:country": "GB",
    "wof:name": "WR14 3SN",
    "wof:placetype": "postalcode"
  },
  "geometry": {"coordinates":[-2.304728,52.10178],"type":"Point"}
}
