{
  "type": "Feature",
  "properties": {
    "date:inception_lower": "2005-03-01",
    "date:inception_upper": "2005-03-01",
    "iso:country": "GB",
    "wof:name": "DT1 3SJ",
    "wof:placetype": "postalcode"
  },
  "geometry": {"coordinates":[-2.468169,50.713243],"type":"Point"}
}
