{
  "type": "Feature",
  "properties": {
    "iso:country":"GB",
    "wof:name":"DT1 3SJ",
    "wof:placetype":"postalcode"
},
  "geometry": {"coordinates":[-2.46815641117117,50.71324378842319],"type":"Point"}
}