{
  "type": "Feature",
  "properties": {
    "iso:country": "GB",
    "wof:name": "AB51 7RP",
    "wof:placetype": "postalcode"
  },
  "geometry": {"coordinates":[-2.544746,57.181168],"type":"Point"}
}
