{
  "type": "Feature",
  "properties": {
    "iso:country":"GB",
    "wof:name":"AB51 7RP",
    "wof:placetype":"postalcode"
},
  "geometry": {"coordinates":[-2.54474621669511,57.18116753774324],"type":"Point"}
}