{
  "type": "Feature",
  "properties": {
    "iso:country":"GB",
    "wof:name":"B21 0LE",
    "wof:placetype":"postalcode"
},
  "geometry": {"coordinates":[-1.95843564874087,52.50995445724079],"type":"Point"}
}