{
  "type": "Feature",
  "properties": {
    "iso:country": "GB",
    "wof:name": "B21 0LE",
    "wof:placetype": "postalcode"
  },
  "geometry": {"coordinates":[-1.958259,52.509972],"type":"Point"}
}
