{
  "type": "Feature",
  "properties": {
    "date:inception_lower": "2009-04-01",
    "date:inception_upper": "2009-04-01",
    "iso:country": "GB",
    "wof:name": "B21 0LE",
    "wof:placetype": "postalcode"
  },
  "geometry": {"coordinates":[-1.958259,52.509972],"type":"Point"}
}
