{
  "type": "Feature",
  "properties": {
    "iso:country": "GB",
    "wof:name": "WA9 4BW",
    "wof:placetype": "postalcode"
  },
  "geometry": {"coordinates":[-2.731031,53.413009],"type":"Point"}
}
