{
  "type": "Feature",
  "properties": {
    "iso:country":"GB",
    "wof:name":"WA9 4BW",
    "wof:placetype":"postalcode"
},
  "geometry": {"coordinates":[-2.73103139518397,53.41300927093941],"type":"Point"}
}