{
  "type": "Feature",
  "properties": {
    "iso:country":"GB",
    "wof:name":"DL16 7AJ",
    "wof:placetype":"postalcode"
},
  "geometry": {"coordinates":[-1.62116745272234,54.68573377302408],"type":"Point"}
}