{
  "type": "Feature",
  "properties": {
    "iso:country": "GB",
    "wof:name": "W2 4AZ",
    "wof:placetype": "postalcode"
  },
  "geometry": {"coordinates":[-0.189991,51.515131],"type":"Point"}
}
