{
  "type": "Feature",
  "properties": {
    "iso:country":"GB",
    "wof:name":"EX10 8DY",
    "wof:placetype":"postalcode"
},
  "geometry": {"coordinates":[-3.24250429479645,50.68175955720491],"type":"Point"}
}