{
  "type": "Feature",
  "properties": {
    "iso:country":"GB",
    "wof:name":"KA7 4JW",
    "wof:placetype":"postalcode"
},
  "geometry": {"coordinates":[-4.66303597900908,55.43658158461206],"type":"Point"}
}