{
  "type": "Feature",
  "properties": {
    "iso:country":"GB",
    "wof:name":"BH22 9LQ",
    "wof:placetype":"postalcode"
},
  "geometry": {"coordinates":[-1.88418413627966,50.80705714008665],"type":"Point"}
}