{
  "type": "Feature",
  "properties": {
    "iso:country":"GB",
    "wof:name":"SY13 1JZ",
    "wof:placetype":"postalcode"
},
  "geometry": {"coordinates":[-2.70544959141884,52.9669279018643],"type":"Point"}
}