{
  "type": "Feature",
  "properties": {
    "iso:country": "GB",
    "wof:name": "SY13 1JZ",
    "wof:placetype": "postalcode"
  },
  "geometry": {"coordinates":[-2.70533,52.966978],"type":"Point"}
}
