{
  "type": "Feature",
  "properties": {
    "date:inception_lower":"1994-05-01",
    "date:inception_upper":"1994-05-31",
    "iso:country":"GB",
    "wof:name":"SY13 1JZ",
    "wof:placetype":"postalcode"
},
  "geometry": {"coordinates":[-2.70533,52.966978],"type":"Point"}
}