{
  "type": "Feature",
  "properties": {
    "iso:country":"GB",
    "wof:name":"ST6 7JZ",
    "wof:placetype":"postalcode"
},
  "geometry": {"coordinates":[-2.19318570629023,53.06965155720341],"type":"Point"}
}