{
  "type": "Feature",
  "properties": {
    "iso:country":"GB",
    "wof:name":"SE22 9LF",
    "wof:placetype":"postalcode"
},
  "geometry": {"coordinates":[-0.07348840550584,51.45364291148177],"type":"Point"}
}