{
  "type": "Feature",
  "properties": {
    "iso:country": "GB",
    "wof:name": "DN10 4NB",
    "wof:placetype": "postalcode"
  },
  "geometry": {"coordinates":[-0.86689,53.4216],"type":"Point"}
}
