{
  "type": "Feature",
  "properties": {
    "iso:country":"GB",
    "wof:name":"N11 2AY",
    "wof:placetype":"postalcode"
},
  "geometry": {"coordinates":[-0.1315168611268,51.60448704919056],"type":"Point"}
}