{
  "type": "Feature",
  "properties": {
    "date:inception_lower": "1980-01-01",
    "date:inception_upper": "1980-01-01",
    "iso:country": "GB",
    "wof:name": "N11 2AY",
    "wof:placetype": "postalcode"
  },
  "geometry": {"coordinates":[-0.131517,51.604487],"type":"Point"}
}
