{
  "type": "Feature",
  "properties": {
    "iso:country": "GB",
    "wof:name": "NE27 0EF",
    "wof:placetype": "postalcode"
  },
  "geometry": {"coordinates":[-1.514849,55.02623],"type":"Point"}
}
