{
  "type": "Feature",
  "properties": {
    "iso:country":"GB",
    "wof:name":"NE27 0EF",
    "wof:placetype":"postalcode"
},
  "geometry": {"coordinates":[-1.51484926798159,55.02623008581614],"type":"Point"}
}