{
  "type": "Feature",
  "properties": {
    "iso:country":"GB",
    "wof:name":"AB43 6SW",
    "wof:placetype":"postalcode"
},
  "geometry": {"coordinates":[-2.09292808771794,57.58712006117993],"type":"Point"}
}