{
  "type": "Feature",
  "properties": {
    "date:inception_lower": "1980-01-01",
    "date:inception_upper": "1980-01-01",
    "iso:country": "GB",
    "wof:name": "WF4 2NL",
    "wof:placetype": "postalcode"
  },
  "geometry": {"coordinates":[-1.48445,53.611892],"type":"Point"}
}
