{
  "type": "Feature",
  "properties": {
    "iso:country":"GB",
    "wof:name":"WF4 2NL",
    "wof:placetype":"postalcode"
},
  "geometry": {"coordinates":[-1.48444976151314,53.61189242113603],"type":"Point"}
}