{
  "type": "Feature",
  "properties": {
    "iso:country":"GB",
    "wof:name":"BL3 6LN",
    "wof:placetype":"postalcode"
},
  "geometry": {"coordinates":[-2.44556201616682,53.56692396945115],"type":"Point"}
}