{
  "type": "Feature",
  "properties": {
    "iso:country":"GB",
    "wof:name":"EX1 2TP",
    "wof:placetype":"postalcode"
},
  "geometry": {"coordinates":[-3.50269276182486,50.72269887309169],"type":"Point"}
}