{
  "type": "Feature",
  "properties": {
    "iso:country":"GB",
    "wof:name":"CO9 2GF",
    "wof:placetype":"postalcode"
},
  "geometry": {"coordinates":[0.63935719610308,51.94700136880143],"type":"Point"}
}