{
  "type": "Feature",
  "properties": {
    "date:inception_lower":"2008-07-01",
    "date:inception_upper":"2008-07-31",
    "iso:country":"GB",
    "wof:name":"CO9 2GF",
    "wof:placetype":"postalcode"
},
  "geometry": {"coordinates":[0.639357,51.947001],"type":"Point"}
}