{
  "type": "Feature",
  "properties": {
    "date:inception_lower":"1980-01-01",
    "date:inception_upper":"1980-01-31",
    "iso:country":"GB",
    "wof:name":"BH5 2BY",
    "wof:placetype":"postalcode"
},
  "geometry": {"coordinates":[-1.817692,50.727433],"type":"Point"}
}