{
  "type": "Feature",
  "properties": {
    "iso:country":"GB",
    "wof:name":"CW9 6AZ",
    "wof:placetype":"postalcode"
},
  "geometry": {"coordinates":[-2.5331556153972,53.29314947995538],"type":"Point"}
}