{
  "type": "Feature",
  "properties": {
    "iso:country":"GB",
    "wof:name":"NE3 5AQ",
    "wof:placetype":"postalcode"
},
  "geometry": {"coordinates":[-1.6278555523058,55.0206969390564],"type":"Point"}
}