{
  "type": "Feature",
  "properties": {
    "date:inception_lower": "1997-06-01",
    "date:inception_upper": "1997-06-01",
    "iso:country": "GB",
    "wof:name": "S66 1AT",
    "wof:placetype": "postalcode"
  },
  "geometry": {"coordinates":[-1.29647,53.419263],"type":"Point"}
}
