{
  "type": "Feature",
  "properties": {
    "date:inception_lower": "1980-01-01",
    "date:inception_upper": "1980-01-01",
    "iso:country": "GB",
    "wof:name": "NG2 4AQ",
    "wof:placetype": "postalcode"
  },
  "geometry": {"coordinates":[-1.122549,52.95027],"type":"Point"}
}
