{
  "type": "Feature",
  "properties": {
    "iso:country":"GB",
    "wof:name":"SM4 4JR",
    "wof:placetype":"postalcode"
},
  "geometry": {"coordinates":[-0.2229033667305,51.39360384029958],"type":"Point"}
}