{
  "type": "Feature",
  "properties": {
    "iso:country":"GB",
    "wof:name":"PL4 6AA",
    "wof:placetype":"postalcode"
},
  "geometry": {"coordinates":[-4.14296378535984,50.37771524169297],"type":"Point"}
}