{
  "type": "Feature",
  "properties": {
    "iso:country": "GB",
    "wof:name": "KT16 0BL",
    "wof:placetype": "postalcode"
  },
  "geometry": {"coordinates":[-0.542475,51.386063],"type":"Point"}
}
