{
  "type": "Feature",
  "properties": {
    "iso:country":"GB",
    "wof:name":"WA10 3BW",
    "wof:placetype":"postalcode"
},
  "geometry": {"coordinates":[-2.77549408697912,53.43893993913636],"type":"Point"}
}