{
  "type": "Feature",
  "properties": {
    "iso:country": "GB",
    "wof:name": "WA10 3BW",
    "wof:placetype": "postalcode"
  },
  "geometry": {"coordinates":[-2.775494,53.43894],"type":"Point"}
}
