{
  "type": "Feature",
  "properties": {
    "iso:country": "GB",
    "wof:name": "SA16 0JW",
    "wof:placetype": "postalcode"
  },
  "geometry": {"coordinates":[-4.276858,51.710367],"type":"Point"}
}
