{
  "type": "Feature",
  "properties": {
    "date:inception_lower":"1980-01-01",
    "date:inception_upper":"1980-01-31",
    "iso:country":"GB",
    "wof:name":"SA16 0JW",
    "wof:placetype":"postalcode"
},
  "geometry": {"coordinates":[-4.276858,51.710367],"type":"Point"}
}