{
  "type": "Feature",
  "properties": {
    "iso:country":"GB",
    "wof:name":"YO25 9BE",
    "wof:placetype":"postalcode"
},
  "geometry": {"coordinates":[-0.43267084991909,53.91078614548697],"type":"Point"}
}