{
  "type": "Feature",
  "properties": {
    "date:inception_lower":"1993-01-01",
    "date:inception_upper":"1993-01-31",
    "iso:country":"GB",
    "wof:name":"YO25 9BE",
    "wof:placetype":"postalcode"
},
  "geometry": {"coordinates":[-0.432671,53.910786],"type":"Point"}
}