{
  "type": "Feature",
  "properties": {
    "iso:country": "GB",
    "wof:name": "NE24 4TL",
    "wof:placetype": "postalcode"
  },
  "geometry": {"coordinates":[-1.528488,55.10757],"type":"Point"}
}
