{
  "type": "Feature",
  "properties": {
    "iso:country":"GB",
    "wof:name":"NE24 4TL",
    "wof:placetype":"postalcode"
},
  "geometry": {"coordinates":[-1.52847336179387,55.10757239495439],"type":"Point"}
}