{
  "type": "Feature",
  "properties": {
    "date:inception_lower":"1980-01-01",
    "date:inception_upper":"1980-01-31",
    "iso:country":"GB",
    "wof:name":"DL14 9HL",
    "wof:placetype":"postalcode"
},
  "geometry": {"coordinates":[-1.722488,54.631018],"type":"Point"}
}