{
  "type": "Feature",
  "properties": {
    "iso:country":"GB",
    "wof:name":"DL14 9HL",
    "wof:placetype":"postalcode"
},
  "geometry": {"coordinates":[-1.72248781762162,54.63101830740629],"type":"Point"}
}