{
  "type": "Feature",
  "properties": {
    "iso:country": "GB",
    "wof:name": "CW8 2UL",
    "wof:placetype": "postalcode"
  },
  "geometry": {"coordinates":[-2.620255,53.242076],"type":"Point"}
}
