{
  "type": "Feature",
  "properties": {
    "iso:country": "GB",
    "wof:name": "CO16 8RY",
    "wof:placetype": "postalcode"
  },
  "geometry": {"coordinates":[1.081017,51.79782],"type":"Point"}
}
