{
  "type": "Feature",
  "properties": {
    "iso:country":"GB",
    "wof:name":"SY3 8UB",
    "wof:placetype":"postalcode"
},
  "geometry": {"coordinates":[-2.78104078146944,52.70790414135815],"type":"Point"}
}