{
  "type": "Feature",
  "properties": {
    "date:inception_lower": "1992-05-01",
    "date:inception_upper": "1992-05-01",
    "iso:country": "GB",
    "wof:name": "AB51 0GU",
    "wof:placetype": "postalcode"
  },
  "geometry": {"coordinates":[-2.32025,57.332782],"type":"Point"}
}
