{
  "type": "Feature",
  "properties": {
    "date:inception_lower": "2020-06-01",
    "date:inception_upper": "2020-06-01",
    "iso:country": "GB",
    "wof:name": "L12 6AB",
    "wof:placetype": "postalcode"
  },
  "geometry": {"coordinates":[-2.87696,53.432519],"type":"Point"}
}
