{
  "type": "Feature",
  "properties": {
    "date:inception_lower": "1980-01-01",
    "date:inception_upper": "1980-01-01",
    "iso:country": "GB",
    "wof:name": "BL6 4LF",
    "wof:placetype": "postalcode"
  },
  "geometry": {"coordinates":[-2.516457,53.583447],"type":"Point"}
}
