{
  "type": "Feature",
  "properties": {
    "iso:country":"GB",
    "wof:name":"BL6 4LF",
    "wof:placetype":"postalcode"
},
  "geometry": {"coordinates":[-2.51645724347026,53.58344705579667],"type":"Point"}
}