{
  "type": "Feature",
  "properties": {
    "iso:country":"GB",
    "wof:name":"W1J 7DG",
    "wof:placetype":"postalcode"
},
  "geometry": {"coordinates":[-0.14786852957935,51.50529880871195],"type":"Point"}
}