{
  "type": "Feature",
  "properties": {
    "iso:country": "GB",
    "wof:name": "YO41 1SB",
    "wof:placetype": "postalcode"
  },
  "geometry": {"coordinates":[-0.904134,53.993358],"type":"Point"}
}
