{
  "type": "Feature",
  "properties": {
    "iso:country": "GB",
    "wof:name": "SO16 7GX",
    "wof:placetype": "postalcode"
  },
  "geometry": {"coordinates":[-1.408407,50.948813],"type":"Point"}
}
