{
  "type": "Feature",
  "properties": {
    "iso:country":"GB",
    "wof:name":"ME20 6LA",
    "wof:placetype":"postalcode"
},
  "geometry": {"coordinates":[0.43619690860493,51.30314893421094],"type":"Point"}
}