{
  "type": "Feature",
  "properties": {
    "iso:country":"GB",
    "wof:name":"G32 7EL",
    "wof:placetype":"postalcode"
},
  "geometry": {"coordinates":[-4.1810052969029,55.8526711393247],"type":"Point"}
}