{
  "type": "Feature",
  "properties": {
    "iso:country": "GB",
    "wof:name": "NP20 3FT",
    "wof:placetype": "postalcode"
  },
  "geometry": {"coordinates":[-3.009358,51.580116],"type":"Point"}
}
