{
  "type": "Feature",
  "properties": {
    "iso:country":"GB",
    "wof:name":"M14 6UE",
    "wof:placetype":"postalcode"
},
  "geometry": {"coordinates":[-2.21745137531539,53.43838401477257],"type":"Point"}
}