{
  "type": "Feature",
  "properties": {
    "date:inception_lower": "1980-01-01",
    "date:inception_upper": "1980-01-01",
    "iso:country": "GB",
    "wof:name": "M14 6UE",
    "wof:placetype": "postalcode"
  },
  "geometry": {"coordinates":[-2.217451,53.438384],"type":"Point"}
}
