{
  "type": "Feature",
  "properties": {
    "iso:country":"GB",
    "wof:name":"HD2 2EF",
    "wof:placetype":"postalcode"
},
  "geometry": {"coordinates":[-1.81509363226135,53.6701859977561],"type":"Point"}
}