{
  "type": "Feature",
  "properties": {
    "iso:country": "GB",
    "wof:name": "WD25 0DF",
    "wof:placetype": "postalcode"
  },
  "geometry": {"coordinates":[-0.39936,51.68708],"type":"Point"}
}
