{
  "type": "Feature",
  "properties": {
    "iso:country":"GB",
    "wof:name":"EH22 5SD",
    "wof:placetype":"postalcode"
},
  "geometry": {"coordinates":[-3.04560095403596,55.86925787468913],"type":"Point"}
}