{
  "type": "Feature",
  "properties": {
    "iso:country": "GB",
    "wof:name": "N17 0WP",
    "wof:placetype": "postalcode"
  },
  "geometry": {"coordinates":[-0.071604,51.59386],"type":"Point"}
}
