{
  "type": "Feature",
  "properties": {
    "iso:country":"GB",
    "wof:name":"LE10 3BN",
    "wof:placetype":"postalcode"
},
  "geometry": {"coordinates":[-1.41281214692845,52.53886556196731],"type":"Point"}
}