{
  "type": "Feature",
  "properties": {
    "iso:country":"GB",
    "wof:name":"M9 7BX",
    "wof:placetype":"postalcode"
},
  "geometry": {"coordinates":[-2.19016651053386,53.52403660515078],"type":"Point"}
}