{
  "type": "Feature",
  "properties": {
    "iso:country":"GB",
    "wof:name":"S66 9NJ",
    "wof:placetype":"postalcode"
},
  "geometry": {"coordinates":[-1.26273756809534,53.3947180187756],"type":"Point"}
}