{
  "type": "Feature",
  "properties": {
    "iso:country":"GB",
    "wof:name":"PR3 0TE",
    "wof:placetype":"postalcode"
},
  "geometry": {"coordinates":[-2.81980643402217,53.86585591678239],"type":"Point"}
}