{
  "type": "Feature",
  "properties": {
    "iso:country": "GB",
    "wof:name": "PR3 0TE",
    "wof:placetype": "postalcode"
  },
  "geometry": {"coordinates":[-2.819806,53.865856],"type":"Point"}
}
