{
  "type": "Feature",
  "properties": {
    "iso:country": "GB",
    "wof:name": "CO7 8RG",
    "wof:placetype": "postalcode"
  },
  "geometry": {"coordinates":[1.066801,51.823672],"type":"Point"}
}
