{
  "type": "Feature",
  "properties": {
    "iso:country":"GB",
    "wof:name":"CO7 8RG",
    "wof:placetype":"postalcode"
},
  "geometry": {"coordinates":[1.06680127604967,51.82367193000231],"type":"Point"}
}