{
  "type": "Feature",
  "properties": {
    "iso:country":"GB",
    "wof:name":"TR18 3JY",
    "wof:placetype":"postalcode"
},
  "geometry": {"coordinates":[-5.55808201087619,50.12535441344294],"type":"Point"}
}