{
  "type": "Feature",
  "properties": {
    "iso:country":"GB",
    "wof:name":"CV7 8JZ",
    "wof:placetype":"postalcode"
},
  "geometry": {"coordinates":[-1.53584409032171,52.46388662266325],"type":"Point"}
}