{
  "type": "Feature",
  "properties": {
    "iso:country": "GB",
    "wof:name": "CV7 8JZ",
    "wof:placetype": "postalcode"
  },
  "geometry": {"coordinates":[-1.535844,52.463887],"type":"Point"}
}
