{
  "type": "Feature",
  "properties": {
    "iso:country":"GB",
    "wof:name":"SA1 5NG",
    "wof:placetype":"postalcode"
},
  "geometry": {"coordinates":[-3.95424495418883,51.6197537007374],"type":"Point"}
}