{
  "type": "Feature",
  "properties": {
    "iso:country":"GB",
    "wof:name":"M44 6ZH",
    "wof:placetype":"postalcode"
},
  "geometry": {"coordinates":[-2.42775983092613,53.44115936442218],"type":"Point"}
}