{
  "type": "Feature",
  "properties": {
    "iso:country": "GB",
    "wof:name": "RG6 3BJ",
    "wof:placetype": "postalcode"
  },
  "geometry": {"coordinates":[-0.902421,51.432043],"type":"Point"}
}
