{
  "type": "Feature",
  "properties": {
    "iso:country":"GB",
    "wof:name":"RG6 3BJ",
    "wof:placetype":"postalcode"
},
  "geometry": {"coordinates":[-0.90242136305435,51.43204258805446],"type":"Point"}
}