{
  "type": "Feature",
  "properties": {
    "date:inception_lower":"1980-01-01",
    "date:inception_upper":"1980-01-31",
    "iso:country":"GB",
    "wof:name":"NE15 9PG",
    "wof:placetype":"postalcode"
},
  "geometry": {"coordinates":[-1.75997,54.991707],"type":"Point"}
}