{
  "type": "Feature",
  "properties": {
    "iso:country": "GB",
    "wof:name": "NE15 9PG",
    "wof:placetype": "postalcode"
  },
  "geometry": {"coordinates":[-1.75997,54.991707],"type":"Point"}
}
