{
  "type": "Feature",
  "properties": {
    "iso:country": "GB",
    "wof:name": "NE6 3AG",
    "wof:placetype": "postalcode"
  },
  "geometry": {"coordinates":[-1.549438,54.975716],"type":"Point"}
}
