{
  "type": "Feature",
  "properties": {
    "iso:country":"GB",
    "wof:name":"PL30 5JS",
    "wof:placetype":"postalcode"
},
  "geometry": {"coordinates":[-4.79704517069732,50.4412819117726],"type":"Point"}
}