{
  "type": "Feature",
  "properties": {
    "date:inception_lower":"1980-01-01",
    "date:inception_upper":"1980-01-31",
    "iso:country":"GB",
    "wof:name":"PL30 5JS",
    "wof:placetype":"postalcode"
},
  "geometry": {"coordinates":[-4.797073,50.441281],"type":"Point"}
}