{
  "type": "Feature",
  "properties": {
    "iso:country":"GB",
    "wof:name":"SS6 9PX",
    "wof:placetype":"postalcode"
},
  "geometry": {"coordinates":[0.60839004915398,51.60170476683324],"type":"Point"}
}