{
  "type": "Feature",
  "properties": {
    "iso:country":"GB",
    "wof:name":"SA1 8EZ",
    "wof:placetype":"postalcode"
},
  "geometry": {"coordinates":[-3.92491421702996,51.62406024606607],"type":"Point"}
}