{
  "type": "Feature",
  "properties": {
    "date:inception_lower": "1980-01-01",
    "date:inception_upper": "1980-01-01",
    "iso:country": "GB",
    "wof:name": "S13 7JY",
    "wof:placetype": "postalcode"
  },
  "geometry": {"coordinates":[-1.372529,53.357027],"type":"Point"}
}
