{
  "type": "Feature",
  "properties": {
    "iso:country":"GB",
    "wof:name":"S13 7JY",
    "wof:placetype":"postalcode"
},
  "geometry": {"coordinates":[-1.37251402959508,53.35702610595362],"type":"Point"}
}