{
  "type": "Feature",
  "properties": {
    "date:inception_lower": "1980-01-01",
    "date:inception_upper": "1980-01-01",
    "iso:country": "GB",
    "wof:name": "GU32 1BL",
    "wof:placetype": "postalcode"
  },
  "geometry": {"coordinates":[-0.964956,51.047],"type":"Point"}
}
