{
  "type": "Feature",
  "properties": {
    "date:inception_lower": "2017-11-01",
    "date:inception_upper": "2017-11-01",
    "iso:country": "GB",
    "wof:name": "TA10 9NY",
    "wof:placetype": "postalcode"
  },
  "geometry": {"coordinates":[-2.780457,51.03974],"type":"Point"}
}
