{
  "type": "Feature",
  "properties": {
    "iso:country": "GB",
    "wof:name": "G78 2BS",
    "wof:placetype": "postalcode"
  },
  "geometry": {"coordinates":[-4.393259,55.790164],"type":"Point"}
}
