{
  "type": "Feature",
  "properties": {
    "date:inception_lower": "1980-01-01",
    "date:inception_upper": "1980-01-01",
    "iso:country": "GB",
    "wof:name": "B60 2AU",
    "wof:placetype": "postalcode"
  },
  "geometry": {"coordinates":[-2.054495,52.326381],"type":"Point"}
}
