{
  "type": "Feature",
  "properties": {
    "iso:country":"GB",
    "wof:name":"IV2 3JL",
    "wof:placetype":"postalcode"
},
  "geometry": {"coordinates":[-4.20656910994865,57.47997480861515],"type":"Point"}
}