{
  "type": "Feature",
  "properties": {
    "iso:country": "GB",
    "wof:name": "IV2 3JL",
    "wof:placetype": "postalcode"
  },
  "geometry": {"coordinates":[-4.206567,57.479959],"type":"Point"}
}
