{
  "type": "Feature",
  "properties": {
    "date:inception_lower":"1998-06-01",
    "date:inception_upper":"1998-06-30",
    "iso:country":"GB",
    "wof:name":"IV2 3JL",
    "wof:placetype":"postalcode"
},
  "geometry": {"coordinates":[-4.206622,57.48003],"type":"Point"}
}