{
  "type": "Feature",
  "properties": {
    "iso:country": "GB",
    "wof:name": "NG32 3BX",
    "wof:placetype": "postalcode"
  },
  "geometry": {"coordinates":[-0.602354,53.018929],"type":"Point"}
}
