{
  "type": "Feature",
  "properties": {
    "iso:country":"GB",
    "wof:name":"NG32 3BX",
    "wof:placetype":"postalcode"
},
  "geometry": {"coordinates":[-0.60235362174246,53.01892861458627],"type":"Point"}
}