{
  "type": "Feature",
  "properties": {
    "iso:country":"GB",
    "wof:name":"OX7 6AW",
    "wof:placetype":"postalcode"
},
  "geometry": {"coordinates":[-1.55977458622293,51.86669381683401],"type":"Point"}
}