{
  "type": "Feature",
  "properties": {
    "iso:country": "GB",
    "wof:name": "OX7 6AW",
    "wof:placetype": "postalcode"
  },
  "geometry": {"coordinates":[-1.559775,51.866694],"type":"Point"}
}
