{
  "type": "Feature",
  "properties": {
    "iso:country":"GB",
    "wof:name":"NW2 1JR",
    "wof:placetype":"postalcode"
},
  "geometry": {"coordinates":[-0.21576212177918,51.57692354550613],"type":"Point"}
}