{
  "type": "Feature",
  "properties": {
    "iso:country":"GB",
    "wof:name":"AB24 5AX",
    "wof:placetype":"postalcode"
},
  "geometry": {"coordinates":[-2.09321171864761,57.14878223249537],"type":"Point"}
}