{
  "type": "Feature",
  "properties": {
    "iso:country":"GB",
    "wof:name":"EH16 5SY",
    "wof:placetype":"postalcode"
},
  "geometry": {"coordinates":[-3.15028860111257,55.92270409604081],"type":"Point"}
}