{
  "type": "Feature",
  "properties": {
    "date:inception_lower": "1980-01-01",
    "date:inception_upper": "1980-01-01",
    "iso:country": "GB",
    "wof:name": "EH16 5SY",
    "wof:placetype": "postalcode"
  },
  "geometry": {"coordinates":[-3.150289,55.922704],"type":"Point"}
}
