{
  "type": "Feature",
  "properties": {
    "iso:country": "GB",
    "wof:name": "CM13 3AZ",
    "wof:placetype": "postalcode"
  },
  "geometry": {"coordinates":[0.298093,51.602347],"type":"Point"}
}
