{
  "type": "Feature",
  "properties": {
    "iso:country":"GB",
    "wof:name":"IP3 0RN",
    "wof:placetype":"postalcode"
},
  "geometry": {"coordinates":[1.18147258412448,52.03305545014798],"type":"Point"}
}