{
  "type": "Feature",
  "properties": {
    "iso:country": "GB",
    "wof:name": "IP3 0RN",
    "wof:placetype": "postalcode"
  },
  "geometry": {"coordinates":[1.181473,52.033055],"type":"Point"}
}
