{
  "type": "Feature",
  "properties": {
    "iso:country":"GB",
    "wof:name":"EH17 8AP",
    "wof:placetype":"postalcode"
},
  "geometry": {"coordinates":[-3.15929342931241,55.89735245365733],"type":"Point"}
}