{
  "type": "Feature",
  "properties": {
    "iso:country":"GB",
    "wof:name":"TR18 4DG",
    "wof:placetype":"postalcode"
},
  "geometry": {"coordinates":[-5.53833909650841,50.11705177025897],"type":"Point"}
}