{
  "type": "Feature",
  "properties": {
    "iso:country":"GB",
    "wof:name":"SA48 7PT",
    "wof:placetype":"postalcode"
},
  "geometry": {"coordinates":[-4.20876848699805,52.20405396097031],"type":"Point"}
}