{
  "type": "Feature",
  "properties": {
    "date:inception_lower":"2002-12-01",
    "date:inception_upper":"2002-12-31",
    "iso:country":"GB",
    "wof:name":"DD2 5EJ",
    "wof:placetype":"postalcode"
},
  "geometry": {"coordinates":[-3.094782,56.462635],"type":"Point"}
}