{
  "type": "Feature",
  "properties": {
    "iso:country": "GB",
    "wof:name": "DD2 5EJ",
    "wof:placetype": "postalcode"
  },
  "geometry": {"coordinates":[-3.094782,56.462635],"type":"Point"}
}
