{
  "type": "Feature",
  "properties": {
    "iso:country":"GB",
    "wof:name":"DD2 5EJ",
    "wof:placetype":"postalcode"
},
  "geometry": {"coordinates":[-3.09478192741956,56.46263463755591],"type":"Point"}
}