{
  "type": "Feature",
  "properties": {
    "iso:country": "GB",
    "wof:name": "G69 7RW",
    "wof:placetype": "postalcode"
  },
  "geometry": {"coordinates":[-4.07066,55.85301],"type":"Point"}
}
