{
  "type": "Feature",
  "properties": {
    "date:inception_lower": "1983-06-01",
    "date:inception_upper": "1983-06-01",
    "iso:country": "GB",
    "wof:name": "G69 7RW",
    "wof:placetype": "postalcode"
  },
  "geometry": {"coordinates":[-4.07066,55.85301],"type":"Point"}
}
