{
  "type": "Feature",
  "properties": {
    "iso:country":"GB",
    "wof:name":"LL18 2NL",
    "wof:placetype":"postalcode"
},
  "geometry": {"coordinates":[-3.4747699523177,53.30976214362256],"type":"Point"}
}