{
  "type": "Feature",
  "properties": {
    "date:inception_lower": "1995-01-01",
    "date:inception_upper": "1995-01-01",
    "iso:country": "GB",
    "wof:name": "SG14 3TW",
    "wof:placetype": "postalcode"
  },
  "geometry": {"coordinates":[-0.110366,51.857811],"type":"Point"}
}
