{
  "type": "Feature",
  "properties": {
    "iso:country":"GB",
    "wof:name":"SG14 3TW",
    "wof:placetype":"postalcode"
},
  "geometry": {"coordinates":[-0.1103665396126,51.85781060854343],"type":"Point"}
}