{
  "type": "Feature",
  "properties": {
    "date:inception_lower":"1996-06-01",
    "date:inception_upper":"1996-06-30",
    "iso:country":"GB",
    "wof:name":"SE7 8TE",
    "wof:placetype":"postalcode"
},
  "geometry": {"coordinates":[0.038394,51.483738],"type":"Point"}
}