{
  "type": "Feature",
  "properties": {
    "iso:country":"GB",
    "wof:name":"SE7 8TE",
    "wof:placetype":"postalcode"
},
  "geometry": {"coordinates":[0.03839444877781,51.48373811284708],"type":"Point"}
}