{
  "type": "Feature",
  "properties": {
    "date:inception_lower": "2019-10-01",
    "date:inception_upper": "2019-10-01",
    "iso:country": "GB",
    "wof:name": "LN2 4NW",
    "wof:placetype": "postalcode"
  },
  "geometry": {"coordinates":[-0.505514,53.250592],"type":"Point"}
}
