{
  "type": "Feature",
  "properties": {
    "iso:country":"GB",
    "wof:name":"B46 1DP",
    "wof:placetype":"postalcode"
},
  "geometry": {"coordinates":[-1.72040287443608,52.49183190908235],"type":"Point"}
}