{
  "type": "Feature",
  "properties": {
    "iso:country":"GB",
    "wof:name":"CA11 0JG",
    "wof:placetype":"postalcode"
},
  "geometry": {"coordinates":[-2.84400924600755,54.65077049396076],"type":"Point"}
}