{
  "type": "Feature",
  "properties": {
    "iso:country": "GB",
    "wof:name": "CA11 0JG",
    "wof:placetype": "postalcode"
  },
  "geometry": {"coordinates":[-2.843642,54.650817],"type":"Point"}
}
