{
  "type": "Feature",
  "properties": {
    "date:inception_lower":"1980-01-01",
    "date:inception_upper":"1980-01-31",
    "iso:country":"GB",
    "wof:name":"SA1 3UR",
    "wof:placetype":"postalcode"
},
  "geometry": {"coordinates":[-3.959376,51.613122],"type":"Point"}
}