{
  "type": "Feature",
  "properties": {
    "iso:country":"GB",
    "wof:name":"SA1 3UR",
    "wof:placetype":"postalcode"
},
  "geometry": {"coordinates":[-3.95937644290453,51.61312160781649],"type":"Point"}
}