{
  "type": "Feature",
  "properties": {
    "date:inception_lower":"1996-06-01",
    "date:inception_upper":"1996-06-30",
    "iso:country":"GB",
    "wof:name":"AB56 5TR",
    "wof:placetype":"postalcode"
},
  "geometry": {"coordinates":[-2.810711,57.648268],"type":"Point"}
}