{
  "type": "Feature",
  "properties": {
    "iso:country":"GB",
    "wof:name":"AB56 5TR",
    "wof:placetype":"postalcode"
},
  "geometry": {"coordinates":[-2.81071080118762,57.64828455779883],"type":"Point"}
}