{
  "type": "Feature",
  "properties": {
    "date:inception_lower": "1997-12-01",
    "date:inception_upper": "1997-12-01",
    "iso:country": "GB",
    "wof:name": "BS40 8UH",
    "wof:placetype": "postalcode"
  },
  "geometry": {"coordinates":[-2.647992,51.360089],"type":"Point"}
}
