{
  "type": "Feature",
  "properties": {
    "iso:country":"GB",
    "wof:name":"BS40 8UH",
    "wof:placetype":"postalcode"
},
  "geometry": {"coordinates":[-2.647991647003,51.36008901340145],"type":"Point"}
}