{
  "type": "Feature",
  "properties": {
    "iso:country": "GB",
    "wof:name": "BS40 8UH",
    "wof:placetype": "postalcode"
  },
  "geometry": {"coordinates":[-2.647992,51.360089],"type":"Point"}
}
