{
  "type": "Feature",
  "properties": {
    "iso:country":"GB",
    "wof:name":"GL3 4GN",
    "wof:placetype":"postalcode"
},
  "geometry": {"coordinates":[-2.18489035704611,51.84222306031283],"type":"Point"}
}