{
  "type": "Feature",
  "properties": {
    "date:inception_lower":"2013-11-01",
    "date:inception_upper":"2013-11-30",
    "iso:country":"GB",
    "wof:name":"GL3 4GN",
    "wof:placetype":"postalcode"
},
  "geometry": {"coordinates":[-2.18489,51.842223],"type":"Point"}
}