{
  "type": "Feature",
  "properties": {
    "iso:country":"GB",
    "wof:name":"NP4 5HE",
    "wof:placetype":"postalcode"
},
  "geometry": {"coordinates":[-3.02774262933975,51.68994128534577],"type":"Point"}
}