{
  "type": "Feature",
  "properties": {
    "date:inception_lower": "2023-08-01",
    "date:inception_upper": "2023-08-01",
    "iso:country": "GB",
    "wof:name": "LN8 3ZL",
    "wof:placetype": "postalcode"
  },
  "geometry": {"coordinates":[-0.31412,53.383948],"type":"Point"}
}
