{
  "type": "Feature",
  "properties": {
    "iso:country":"GB",
    "wof:name":"KA3 2LU",
    "wof:placetype":"postalcode"
},
  "geometry": {"coordinates":[-4.53535280831053,55.62540306722976],"type":"Point"}
}