{
  "type": "Feature",
  "properties": {
    "iso:country": "GB",
    "wof:name": "S75 3NW",
    "wof:placetype": "postalcode"
  },
  "geometry": {"coordinates":[-1.521264,53.536291],"type":"Point"}
}
