{
  "type": "Feature",
  "properties": {
    "date:inception_lower": "1980-01-01",
    "date:inception_upper": "1980-01-01",
    "iso:country": "GB",
    "wof:name": "S75 3NW",
    "wof:placetype": "postalcode"
  },
  "geometry": {"coordinates":[-1.521264,53.536291],"type":"Point"}
}
