{
  "type": "Feature",
  "properties": {
    "iso:country":"GB",
    "wof:name":"S75 3NW",
    "wof:placetype":"postalcode"
},
  "geometry": {"coordinates":[-1.52120243123895,53.53629988862944],"type":"Point"}
}