{
  "type": "Feature",
  "properties": {
    "date:inception_lower":"2005-07-01",
    "date:inception_upper":"2005-07-31",
    "iso:country":"GB",
    "wof:name":"SY23 1WY",
    "wof:placetype":"postalcode"
},
  "geometry": {"coordinates":[-4.043584,52.403464],"type":"Point"}
}