{
  "type": "Feature",
  "properties": {
    "iso:country":"GB",
    "wof:name":"DY8 2DE",
    "wof:placetype":"postalcode"
},
  "geometry": {"coordinates":[-2.14432524587961,52.44831004920842],"type":"Point"}
}