{
  "type": "Feature",
  "properties": {
    "iso:country":"GB",
    "wof:name":"RM18 7AR",
    "wof:placetype":"postalcode"
},
  "geometry": {"coordinates":[0.35453820529136,51.46479297625933],"type":"Point"}
}