{
  "type": "Feature",
  "properties": {
    "iso:country":"GB",
    "wof:name":"IP29 5PP",
    "wof:placetype":"postalcode"
},
  "geometry": {"coordinates":[0.67311662761041,52.21751188054523],"type":"Point"}
}