{
  "type": "Feature",
  "properties": {
    "iso:country":"GB",
    "wof:name":"NN9 6UF",
    "wof:placetype":"postalcode"
},
  "geometry": {"coordinates":[-0.53689453262346,52.3441922075857],"type":"Point"}
}