{
  "type": "Feature",
  "properties": {
    "iso:country": "GB",
    "wof:name": "CF31 2NA",
    "wof:placetype": "postalcode"
  },
  "geometry": {"coordinates":[-3.544809,51.510669],"type":"Point"}
}
