{
  "type": "Feature",
  "properties": {
    "date:inception_lower": "1986-07-01",
    "date:inception_upper": "1986-07-01",
    "iso:country": "GB",
    "wof:name": "CF31 2NA",
    "wof:placetype": "postalcode"
  },
  "geometry": {"coordinates":[-3.544809,51.510669],"type":"Point"}
}
