{
  "type": "Feature",
  "properties": {
    "iso:country":"GB",
    "wof:name":"CF31 2NA",
    "wof:placetype":"postalcode"
},
  "geometry": {"coordinates":[-3.54479511072359,51.51067747076711],"type":"Point"}
}