{
  "type": "Feature",
  "properties": {
    "date:inception_lower": "2003-08-01",
    "date:inception_upper": "2003-08-01",
    "iso:country": "GB",
    "wof:name": "AB24 5QU",
    "wof:placetype": "postalcode"
  },
  "geometry": {"coordinates":[-2.093643,57.159689],"type":"Point"}
}
