{
  "type": "Feature",
  "properties": {
    "iso:country": "GB",
    "wof:name": "AB24 5QU",
    "wof:placetype": "postalcode"
  },
  "geometry": {"coordinates":[-2.09319,57.159733],"type":"Point"}
}
