{
  "type": "Feature",
  "properties": {
    "date:inception_lower": "1980-01-01",
    "date:inception_upper": "1980-01-01",
    "iso:country": "GB",
    "wof:name": "SY8 1HH",
    "wof:placetype": "postalcode"
  },
  "geometry": {"coordinates":[-2.709186,52.373405],"type":"Point"}
}
