{
  "type": "Feature",
  "properties": {
    "iso:country":"GB",
    "wof:name":"SY8 1HH",
    "wof:placetype":"postalcode"
},
  "geometry": {"coordinates":[-2.70918587190472,52.37340481163236],"type":"Point"}
}