{
  "type": "Feature",
  "properties": {
    "date:inception_lower": "2003-10-01",
    "date:inception_upper": "2003-10-01",
    "iso:country": "GB",
    "wof:name": "BA12 8LF",
    "wof:placetype": "postalcode"
  },
  "geometry": {"coordinates":[-2.187617,51.200715],"type":"Point"}
}
