{
  "type": "Feature",
  "properties": {
    "iso:country": "GB",
    "wof:name": "BA12 8LF",
    "wof:placetype": "postalcode"
  },
  "geometry": {"coordinates":[-2.187617,51.200715],"type":"Point"}
}
