{
  "type": "Feature",
  "properties": {
    "iso:country": "GB",
    "wof:name": "CR5 3SG",
    "wof:placetype": "postalcode"
  },
  "geometry": {"coordinates":[-0.166521,51.295191],"type":"Point"}
}
