{
  "type": "Feature",
  "properties": {
    "iso:country":"GB",
    "wof:name":"CR5 3SG",
    "wof:placetype":"postalcode"
},
  "geometry": {"coordinates":[-0.16652060903135,51.29519123497569],"type":"Point"}
}