{
  "type": "Feature",
  "properties": {
    "iso:country":"GB",
    "wof:name":"HA7 3DQ",
    "wof:placetype":"postalcode"
},
  "geometry": {"coordinates":[-0.31208902756576,51.61876845239593],"type":"Point"}
}