{
  "type": "Feature",
  "properties": {
    "iso:country":"GB",
    "wof:name":"G40 4DE",
    "wof:placetype":"postalcode"
},
  "geometry": {"coordinates":[-4.2201156285405,55.84452087366669],"type":"Point"}
}