{
  "type": "Feature",
  "properties": {
    "date:inception_lower": "1995-12-01",
    "date:inception_upper": "1995-12-01",
    "iso:country": "GB",
    "wof:name": "G40 4DE",
    "wof:placetype": "postalcode"
  },
  "geometry": {"coordinates":[-4.220116,55.844521],"type":"Point"}
}
