{
  "type": "Feature",
  "properties": {
    "date:inception_lower": "1997-12-01",
    "date:inception_upper": "1997-12-01",
    "iso:country": "GB",
    "wof:name": "PO41 0ND",
    "wof:placetype": "postalcode"
  },
  "geometry": {"coordinates":[-1.480857,50.707787],"type":"Point"}
}
