{
  "type": "Feature",
  "properties": {
    "iso:country":"GB",
    "wof:name":"HA6 1UA",
    "wof:placetype":"postalcode"
},
  "geometry": {"coordinates":[-0.41722662416296,51.60986509102296],"type":"Point"}
}