{
  "type": "Feature",
  "properties": {
    "iso:country":"GB",
    "wof:name":"B8 1HW",
    "wof:placetype":"postalcode"
},
  "geometry": {"coordinates":[-1.85625914490765,52.48592550035078],"type":"Point"}
}