{
  "type": "Feature",
  "properties": {
    "iso:country":"GB",
    "wof:name":"SM5 3NL",
    "wof:placetype":"postalcode"
},
  "geometry": {"coordinates":[-0.17413763192174,51.356973403171],"type":"Point"}
}