{
  "type": "Feature",
  "properties": {
    "iso:country": "GB",
    "wof:name": "SM5 3NL",
    "wof:placetype": "postalcode"
  },
  "geometry": {"coordinates":[-0.174085,51.356945],"type":"Point"}
}
