{
  "type": "Feature",
  "properties": {
    "iso:country":"GB",
    "wof:name":"SE9 6TB",
    "wof:placetype":"postalcode"
},
  "geometry": {"coordinates":[0.04877693370056,51.45894388423502],"type":"Point"}
}