{
  "type": "Feature",
  "properties": {
    "date:inception_lower":"1994-05-01",
    "date:inception_upper":"1994-05-31",
    "iso:country":"GB",
    "wof:name":"M45 7HL",
    "wof:placetype":"postalcode"
},
  "geometry": {"coordinates":[-2.30566,53.542565],"type":"Point"}
}