{
  "type": "Feature",
  "properties": {
    "iso:country":"GB",
    "wof:name":"M45 7HL",
    "wof:placetype":"postalcode"
},
  "geometry": {"coordinates":[-2.30566009866406,53.54256465965447],"type":"Point"}
}