{
  "type": "Feature",
  "properties": {
    "date:inception_lower":"2005-10-01",
    "date:inception_upper":"2005-10-31",
    "iso:country":"GB",
    "wof:name":"IP5 2BR",
    "wof:placetype":"postalcode"
},
  "geometry": {"coordinates":[1.243152,52.059173],"type":"Point"}
}