{
  "type": "Feature",
  "properties": {
    "date:inception_lower": "1980-01-01",
    "date:inception_upper": "1980-01-01",
    "iso:country": "GB",
    "wof:name": "G66 2JB",
    "wof:placetype": "postalcode"
  },
  "geometry": {"coordinates":[-4.144076,55.942994],"type":"Point"}
}
