{
  "type": "Feature",
  "properties": {
    "iso:country":"GB",
    "wof:name":"CH3 8LJ",
    "wof:placetype":"postalcode"
},
  "geometry": {"coordinates":[-2.76498638709548,53.19641499590195],"type":"Point"}
}