{
  "type": "Feature",
  "properties": {
    "date:inception_lower": "1980-01-01",
    "date:inception_upper": "1980-01-01",
    "iso:country": "GB",
    "wof:name": "BB4 4JP",
    "wof:placetype": "postalcode"
  },
  "geometry": {"coordinates":[-2.329813,53.689106],"type":"Point"}
}
