{
  "type": "Feature",
  "properties": {
    "iso:country": "GB",
    "wof:name": "BB4 4JP",
    "wof:placetype": "postalcode"
  },
  "geometry": {"coordinates":[-2.330055,53.689105],"type":"Point"}
}
