{
  "type": "Feature",
  "properties": {
    "iso:country": "GB",
    "wof:name": "PE30 3FH",
    "wof:placetype": "postalcode"
  },
  "geometry": {"coordinates":[0.432207,52.785485],"type":"Point"}
}
