{
  "type": "Feature",
  "properties": {
    "iso:country": "GB",
    "wof:name": "N15 4UH",
    "wof:placetype": "postalcode"
  },
  "geometry": {"coordinates":[-0.068631,51.58668],"type":"Point"}
}
