{
  "type": "Feature",
  "properties": {
    "iso:country":"GB",
    "wof:name":"N15 4UH",
    "wof:placetype":"postalcode"
},
  "geometry": {"coordinates":[-0.06863092204111,51.58668016133764],"type":"Point"}
}