{
  "type": "Feature",
  "properties": {
    "iso:country":"GB",
    "wof:name":"RG18 9SD",
    "wof:placetype":"postalcode"
},
  "geometry": {"coordinates":[-1.27441365758506,51.4625479681216],"type":"Point"}
}