{
  "type": "Feature",
  "properties": {
    "iso:country":"GB",
    "wof:name":"E12 5DZ",
    "wof:placetype":"postalcode"
},
  "geometry": {"coordinates":[0.03679180094353,51.5634413338896],"type":"Point"}
}