{
  "type": "Feature",
  "properties": {
    "iso:country":"GB",
    "wof:name":"HU8 9QB",
    "wof:placetype":"postalcode"
},
  "geometry": {"coordinates":[-0.26585457534483,53.78134148280547],"type":"Point"}
}