{
  "type": "Feature",
  "properties": {
    "date:inception_lower":"1980-01-01",
    "date:inception_upper":"1980-01-31",
    "iso:country":"GB",
    "wof:name":"HU8 9QB",
    "wof:placetype":"postalcode"
},
  "geometry": {"coordinates":[-0.265862,53.781362],"type":"Point"}
}