{
  "type": "Feature",
  "properties": {
    "iso:country":"GB",
    "wof:name":"HA2 9LE",
    "wof:placetype":"postalcode"
},
  "geometry": {"coordinates":[-0.37726567527554,51.56771285902083],"type":"Point"}
}