{
  "type": "Feature",
  "properties": {
    "iso:country":"GB",
    "wof:name":"B79 7RL",
    "wof:placetype":"postalcode"
},
  "geometry": {"coordinates":[-1.69940663352629,52.63566322117253],"type":"Point"}
}