{
  "type": "Feature",
  "properties": {
    "iso:country":"GB",
    "wof:name":"PE6 8SD",
    "wof:placetype":"postalcode"
},
  "geometry": {"coordinates":[-0.28842236318082,52.67812257662518],"type":"Point"}
}