{
  "type": "Feature",
  "properties": {
    "date:inception_lower": "1980-01-01",
    "date:inception_upper": "1980-01-01",
    "iso:country": "GB",
    "wof:name": "HR9 7AY",
    "wof:placetype": "postalcode"
  },
  "geometry": {"coordinates":[-2.579601,51.9189],"type":"Point"}
}
