{
  "type": "Feature",
  "properties": {
    "date:inception_lower": "2006-09-01",
    "date:inception_upper": "2006-09-01",
    "iso:country": "GB",
    "wof:name": "DL2 1LP",
    "wof:placetype": "postalcode"
  },
  "geometry": {"coordinates":[-1.468601,54.514222],"type":"Point"}
}
