{
  "type": "Feature",
  "properties": {
    "iso:country":"GB",
    "wof:name":"DL2 1LP",
    "wof:placetype":"postalcode"
},
  "geometry": {"coordinates":[-1.4686007794753,54.51422176586328],"type":"Point"}
}