{
  "type": "Feature",
  "properties": {
    "iso:country":"GB",
    "wof:name":"NG12 1DD",
    "wof:placetype":"postalcode"
},
  "geometry": {"coordinates":[-1.02806346253802,52.9517558239208],"type":"Point"}
}