{
  "type": "Feature",
  "properties": {
    "date:inception_lower": "1980-01-01",
    "date:inception_upper": "1980-01-01",
    "iso:country": "GB",
    "wof:name": "NG12 1DD",
    "wof:placetype": "postalcode"
  },
  "geometry": {"coordinates":[-1.028063,52.951756],"type":"Point"}
}
