{
  "type": "Feature",
  "properties": {
    "iso:country":"GB",
    "wof:name":"RH5 5SX",
    "wof:placetype":"postalcode"
},
  "geometry": {"coordinates":[-0.35735314578361,51.15335865380699],"type":"Point"}
}