{
  "type": "Feature",
  "properties": {
    "date:inception_lower": "2023-09-01",
    "date:inception_upper": "2023-09-01",
    "iso:country": "GB",
    "wof:name": "SG14 2GT",
    "wof:placetype": "postalcode"
  },
  "geometry": {"coordinates":[-0.105009,51.798347],"type":"Point"}
}
