{
  "type": "Feature",
  "properties": {
    "iso:country": "GB",
    "wof:name": "SK17 9AS",
    "wof:placetype": "postalcode"
  },
  "geometry": {"coordinates":[-1.921744,53.25749],"type":"Point"}
}
