{
  "type": "Feature",
  "properties": {
    "iso:country":"GB",
    "wof:name":"SK8 2BA",
    "wof:placetype":"postalcode"
},
  "geometry": {"coordinates":[-2.21042043886497,53.3955571982268],"type":"Point"}
}