{
  "type": "Feature",
  "properties": {
    "iso:country": "GB",
    "wof:name": "SK8 2BA",
    "wof:placetype": "postalcode"
  },
  "geometry": {"coordinates":[-2.21042,53.395557],"type":"Point"}
}
