{
  "type": "Feature",
  "properties": {
    "iso:country":"GB",
    "wof:name":"LS6 1BQ",
    "wof:placetype":"postalcode"
},
  "geometry": {"coordinates":[-1.56406799419739,53.81357948298891],"type":"Point"}
}