{
  "type": "Feature",
  "properties": {
    "iso:country": "GB",
    "wof:name": "N2 0PN",
    "wof:placetype": "postalcode"
  },
  "geometry": {"coordinates":[-0.162865,51.584875],"type":"Point"}
}
