{
  "type": "Feature",
  "properties": {
    "iso:country":"GB",
    "wof:name":"DE23 8DF",
    "wof:placetype":"postalcode"
},
  "geometry": {"coordinates":[-1.48398572175662,52.89870371101104],"type":"Point"}
}