{
  "type": "Feature",
  "properties": {
    "iso:country":"GB",
    "wof:name":"EH14 5DD",
    "wof:placetype":"postalcode"
},
  "geometry": {"coordinates":[-3.29670110274146,55.89928852589602],"type":"Point"}
}