{
  "type": "Feature",
  "properties": {
    "iso:country": "GB",
    "wof:name": "EH14 5DD",
    "wof:placetype": "postalcode"
  },
  "geometry": {"coordinates":[-3.296701,55.899289],"type":"Point"}
}
