{
  "type": "Feature",
  "properties": {
    "date:inception_lower":"1998-06-01",
    "date:inception_upper":"1998-06-30",
    "iso:country":"GB",
    "wof:name":"EH14 5DD",
    "wof:placetype":"postalcode"
},
  "geometry": {"coordinates":[-3.296701,55.899289],"type":"Point"}
}