{
  "type": "Feature",
  "properties": {
    "iso:country": "GB",
    "wof:name": "NE26 2ET",
    "wof:placetype": "postalcode"
  },
  "geometry": {"coordinates":[-1.439301,55.040418],"type":"Point"}
}
