{
  "type": "Feature",
  "properties": {
    "iso:country":"GB",
    "wof:name":"NE26 2ET",
    "wof:placetype":"postalcode"
},
  "geometry": {"coordinates":[-1.43930063664662,55.04041846111721],"type":"Point"}
}