{
  "type": "Feature",
  "properties": {
    "iso:country":"GB",
    "wof:name":"CF62 7AE",
    "wof:placetype":"postalcode"
},
  "geometry": {"coordinates":[-3.28485827258725,51.39689918410619],"type":"Point"}
}