{
  "type": "Feature",
  "properties": {
    "iso:country":"GB",
    "wof:name":"UB8 2AF",
    "wof:placetype":"postalcode"
},
  "geometry": {"coordinates":[-0.48323489225539,51.53765796738712],"type":"Point"}
}