{
  "type": "Feature",
  "properties": {
    "iso:country": "GB",
    "wof:name": "UB8 2AF",
    "wof:placetype": "postalcode"
  },
  "geometry": {"coordinates":[-0.483235,51.537658],"type":"Point"}
}
