{
  "type": "Feature",
  "properties": {
    "iso:country":"GB",
    "wof:name":"LU2 8EY",
    "wof:placetype":"postalcode"
},
  "geometry": {"coordinates":[-0.38437708408025,51.90928835178281],"type":"Point"}
}