{
  "type": "Feature",
  "properties": {
    "iso:country":"GB",
    "wof:name":"BB2 3AR",
    "wof:placetype":"postalcode"
},
  "geometry": {"coordinates":[-2.47916458726685,53.73826320997595],"type":"Point"}
}