{
  "type": "Feature",
  "properties": {
    "iso:country": "GB",
    "wof:name": "BB2 3AR",
    "wof:placetype": "postalcode"
  },
  "geometry": {"coordinates":[-2.479165,53.738263],"type":"Point"}
}
