{
  "type": "Feature",
  "properties": {
    "iso:country": "GB",
    "wof:name": "DE7 6BZ",
    "wof:placetype": "postalcode"
  },
  "geometry": {"coordinates":[-1.358382,52.983401],"type":"Point"}
}
