{
  "type": "Feature",
  "properties": {
    "iso:country":"GB",
    "wof:name":"DE7 6BZ",
    "wof:placetype":"postalcode"
},
  "geometry": {"coordinates":[-1.35838188719911,52.98340147795138],"type":"Point"}
}