{
  "type": "Feature",
  "properties": {
    "iso:country":"GB",
    "wof:name":"ML5 4LH",
    "wof:placetype":"postalcode"
},
  "geometry": {"coordinates":[-4.02178852235529,55.84419337519562],"type":"Point"}
}