{
  "type": "Feature",
  "properties": {
    "iso:country": "GB",
    "wof:name": "ML5 4LH",
    "wof:placetype": "postalcode"
  },
  "geometry": {"coordinates":[-4.021788,55.844193],"type":"Point"}
}
