{
  "type": "Feature",
  "properties": {
    "iso:country":"GB",
    "wof:name":"RM15 4HP",
    "wof:placetype":"postalcode"
},
  "geometry": {"coordinates":[0.25156402178207,51.49486548404067],"type":"Point"}
}