{
  "type": "Feature",
  "properties": {
    "date:inception_lower": "2021-08-01",
    "date:inception_upper": "2021-08-01",
    "iso:country": "GB",
    "wof:name": "MK10 9UZ",
    "wof:placetype": "postalcode"
  },
  "geometry": {"coordinates":[-0.70186,52.045904],"type":"Point"}
}
