{
  "type": "Feature",
  "properties": {
    "iso:country":"GB",
    "wof:name":"B97 6AN",
    "wof:placetype":"postalcode"
},
  "geometry": {"coordinates":[-1.94602284647533,52.30970473931971],"type":"Point"}
}