{
  "type": "Feature",
  "properties": {
    "date:inception_lower": "1980-01-01",
    "date:inception_upper": "1980-01-01",
    "iso:country": "GB",
    "wof:name": "B97 6AN",
    "wof:placetype": "postalcode"
  },
  "geometry": {"coordinates":[-1.946023,52.309705],"type":"Point"}
}
