{
  "type": "Feature",
  "properties": {
    "iso:country": "GB",
    "wof:name": "BB2 7PY",
    "wof:placetype": "postalcode"
  },
  "geometry": {"coordinates":[-2.553605,53.768484],"type":"Point"}
}
