{
  "type": "Feature",
  "properties": {
    "iso:country":"GB",
    "wof:name":"BB2 7PY",
    "wof:placetype":"postalcode"
},
  "geometry": {"coordinates":[-2.55360553651682,53.76848404378789],"type":"Point"}
}