{
  "type": "Feature",
  "properties": {
    "date:inception_lower": "1980-01-01",
    "date:inception_upper": "1980-01-01",
    "iso:country": "GB",
    "wof:name": "NE71 6QU",
    "wof:placetype": "postalcode"
  },
  "geometry": {"coordinates":[-1.996931,55.525339],"type":"Point"}
}
