{
  "type": "Feature",
  "properties": {
    "iso:country":"GB",
    "wof:name":"NE71 6QU",
    "wof:placetype":"postalcode"
},
  "geometry": {"coordinates":[-1.99693153402644,55.52533860657343],"type":"Point"}
}