{
  "type": "Feature",
  "properties": {
    "iso:country": "GB",
    "wof:name": "NE71 6QU",
    "wof:placetype": "postalcode"
  },
  "geometry": {"coordinates":[-1.996931,55.525339],"type":"Point"}
}
