{
  "type": "Feature",
  "properties": {
    "date:inception_lower":"1980-01-01",
    "date:inception_upper":"1980-01-31",
    "iso:country":"GB",
    "wof:name":"TQ12 3DJ",
    "wof:placetype":"postalcode"
},
  "geometry": {"coordinates":[-3.588656,50.551861],"type":"Point"}
}