{
  "type": "Feature",
  "properties": {
    "iso:country":"GB",
    "wof:name":"TQ12 3DJ",
    "wof:placetype":"postalcode"
},
  "geometry": {"coordinates":[-3.5886557674042,50.55186102396018],"type":"Point"}
}