{
  "type": "Feature",
  "properties": {
    "date:inception_lower": "2020-02-01",
    "date:inception_upper": "2020-02-01",
    "iso:country": "GB",
    "wof:name": "DA1 5XJ",
    "wof:placetype": "postalcode"
  },
  "geometry": {"coordinates":[0.21986,51.448744],"type":"Point"}
}
