{
  "type": "Feature",
  "properties": {
    "iso:country": "GB",
    "wof:name": "WF4 4AP",
    "wof:placetype": "postalcode"
  },
  "geometry": {"coordinates":[-1.625354,53.634354],"type":"Point"}
}
