{
  "type": "Feature",
  "properties": {
    "iso:country":"GB",
    "wof:name":"SO16 7PN",
    "wof:placetype":"postalcode"
},
  "geometry": {"coordinates":[-1.40303049087936,50.93732011007103],"type":"Point"}
}