{
  "type": "Feature",
  "properties": {
    "iso:country":"GB",
    "wof:name":"BL7 9YE",
    "wof:placetype":"postalcode"
},
  "geometry": {"coordinates":[-2.40716673280995,53.61263176414079],"type":"Point"}
}