{
  "type": "Feature",
  "properties": {
    "date:inception_lower":"1980-01-01",
    "date:inception_upper":"1980-01-31",
    "iso:country":"GB",
    "wof:name":"RM8 2SD",
    "wof:placetype":"postalcode"
},
  "geometry": {"coordinates":[0.123015,51.555069],"type":"Point"}
}