{
  "type": "Feature",
  "properties": {
    "iso:country":"GB",
    "wof:name":"RM8 2SD",
    "wof:placetype":"postalcode"
},
  "geometry": {"coordinates":[0.12301518213814,51.55506927951903],"type":"Point"}
}