{
  "type": "Feature",
  "properties": {
    "date:inception_lower":"2000-12-01",
    "date:inception_upper":"2000-12-31",
    "iso:country":"GB",
    "wof:name":"WV16 6SX",
    "wof:placetype":"postalcode"
},
  "geometry": {"coordinates":[-2.578911,52.49354],"type":"Point"}
}