{
  "type": "Feature",
  "properties": {
    "iso:country":"GB",
    "wof:name":"WV16 6SX",
    "wof:placetype":"postalcode"
},
  "geometry": {"coordinates":[-2.57891143874314,52.49354007800984],"type":"Point"}
}