{
  "type": "Feature",
  "properties": {
    "iso:country":"GB",
    "wof:name":"PO7 5AR",
    "wof:placetype":"postalcode"
},
  "geometry": {"coordinates":[-1.04362980173284,50.86873575197414],"type":"Point"}
}