{
  "type": "Feature",
  "properties": {
    "date:inception_lower": "1995-12-01",
    "date:inception_upper": "1995-12-01",
    "iso:country": "GB",
    "wof:name": "PO7 5AR",
    "wof:placetype": "postalcode"
  },
  "geometry": {"coordinates":[-1.04363,50.868736],"type":"Point"}
}
