{
  "type": "Feature",
  "properties": {
    "iso:country":"GB",
    "wof:name":"AL7 3LY",
    "wof:placetype":"postalcode"
},
  "geometry": {"coordinates":[-0.18053899833842,51.7922050903859],"type":"Point"}
}