{
  "type": "Feature",
  "properties": {
    "date:inception_lower": "1992-01-01",
    "date:inception_upper": "1992-01-01",
    "iso:country": "GB",
    "wof:name": "AL7 3LY",
    "wof:placetype": "postalcode"
  },
  "geometry": {"coordinates":[-0.180499,51.792193],"type":"Point"}
}
