{
  "type": "Feature",
  "properties": {
    "iso:country":"GB",
    "wof:name":"SR7 9NW",
    "wof:placetype":"postalcode"
},
  "geometry": {"coordinates":[-1.3847670625771,54.8143080294763],"type":"Point"}
}