{
  "type": "Feature",
  "properties": {
    "iso:country": "GB",
    "wof:name": "SR7 9NW",
    "wof:placetype": "postalcode"
  },
  "geometry": {"coordinates":[-1.384767,54.814308],"type":"Point"}
}
