{
  "type": "Feature",
  "properties": {
    "iso:country": "GB",
    "wof:name": "LN11 0FN",
    "wof:placetype": "postalcode"
  },
  "geometry": {"coordinates":[0.006098,53.376354],"type":"Point"}
}
