{
  "type": "Feature",
  "properties": {
    "iso:country":"GB",
    "wof:name":"L17 6GA",
    "wof:placetype":"postalcode"
},
  "geometry": {"coordinates":[-2.92435919421474,53.36176247156649],"type":"Point"}
}