{
  "type": "Feature",
  "properties": {
    "iso:country": "GB",
    "wof:name": "L17 6GA",
    "wof:placetype": "postalcode"
  },
  "geometry": {"coordinates":[-2.924359,53.361779],"type":"Point"}
}
