{
  "type": "Feature",
  "properties": {
    "date:inception_lower":"2005-04-01",
    "date:inception_upper":"2005-04-30",
    "iso:country":"GB",
    "wof:name":"L17 6GA",
    "wof:placetype":"postalcode"
},
  "geometry": {"coordinates":[-2.924359,53.361779],"type":"Point"}
}