{
  "type": "Feature",
  "properties": {
    "date:inception_lower": "2005-04-01",
    "date:inception_upper": "2005-04-01",
    "iso:country": "GB",
    "wof:name": "L17 6GA",
    "wof:placetype": "postalcode"
  },
  "geometry": {"coordinates":[-2.924838,53.361712],"type":"Point"}
}
