{
  "type": "Feature",
  "properties": {
    "iso:country":"GB",
    "wof:name":"WF3 2BB",
    "wof:placetype":"postalcode"
},
  "geometry": {"coordinates":[-1.53397757344359,53.72483488727254],"type":"Point"}
}