{
  "type": "Feature",
  "properties": {
    "date:inception_lower": "2000-12-01",
    "date:inception_upper": "2000-12-01",
    "iso:country": "GB",
    "wof:name": "WA14 1DA",
    "wof:placetype": "postalcode"
  },
  "geometry": {"coordinates":[-2.34992,53.388972],"type":"Point"}
}
