{
  "type": "Feature",
  "properties": {
    "iso:country":"GB",
    "wof:name":"SN10 4DJ",
    "wof:placetype":"postalcode"
},
  "geometry": {"coordinates":[-1.98221212579738,51.28821176508949],"type":"Point"}
}