{
  "type": "Feature",
  "properties": {
    "iso:country":"GB",
    "wof:name":"SR3 2EL",
    "wof:placetype":"postalcode"
},
  "geometry": {"coordinates":[-1.39628730404614,54.87030716104761],"type":"Point"}
}