{
  "type": "Feature",
  "properties": {
    "iso:country":"GB",
    "wof:name":"PE26 2PW",
    "wof:placetype":"postalcode"
},
  "geometry": {"coordinates":[-0.14967602836727,52.42480027133158],"type":"Point"}
}