{
  "type": "Feature",
  "properties": {
    "iso:country":"GB",
    "wof:name":"DG7 3AN",
    "wof:placetype":"postalcode"
},
  "geometry": {"coordinates":[-3.94817477317179,54.97106973614182],"type":"Point"}
}