{
  "type": "Feature",
  "properties": {
    "iso:country":"GB",
    "wof:name":"LS7 3NW",
    "wof:placetype":"postalcode"
},
  "geometry": {"coordinates":[-1.54113180354475,53.82637380275095],"type":"Point"}
}