{
  "type": "Feature",
  "properties": {
    "date:inception_lower":"1980-01-01",
    "date:inception_upper":"1980-01-31",
    "iso:country":"GB",
    "wof:name":"ME15 0RL",
    "wof:placetype":"postalcode"
},
  "geometry": {"coordinates":[0.477209,51.21853],"type":"Point"}
}