{
  "type": "Feature",
  "properties": {
    "iso:country":"GB",
    "wof:name":"KY7 4SL",
    "wof:placetype":"postalcode"
},
  "geometry": {"coordinates":[-3.15837043500019,56.17818806258169],"type":"Point"}
}