{
  "type": "Feature",
  "properties": {
    "date:inception_lower":"2005-10-01",
    "date:inception_upper":"2005-10-31",
    "iso:country":"GB",
    "wof:name":"BA20 2FG",
    "wof:placetype":"postalcode"
},
  "geometry": {"coordinates":[-2.670549,50.942387],"type":"Point"}
}