{
  "type": "Feature",
  "properties": {
    "iso:country":"GB",
    "wof:name":"BA20 2FG",
    "wof:placetype":"postalcode"
},
  "geometry": {"coordinates":[-2.67050449574775,50.94241256244502],"type":"Point"}
}