{
  "type": "Feature",
  "properties": {
    "iso:country":"GB",
    "wof:name":"BL2 1LT",
    "wof:placetype":"postalcode"
},
  "geometry": {"coordinates":[-2.41183987648089,53.57251880763268],"type":"Point"}
}