{
  "type": "Feature",
  "properties": {
    "iso:country": "GB",
    "wof:name": "LL12 0TW",
    "wof:placetype": "postalcode"
  },
  "geometry": {"coordinates":[-3.001793,53.096801],"type":"Point"}
}
