{
  "type": "Feature",
  "properties": {
    "date:inception_lower": "1980-01-01",
    "date:inception_upper": "1980-01-01",
    "iso:country": "GB",
    "wof:name": "LL12 0TW",
    "wof:placetype": "postalcode"
  },
  "geometry": {"coordinates":[-3.001793,53.096801],"type":"Point"}
}
