{
  "type": "Feature",
  "properties": {
    "iso:country":"GB",
    "wof:name":"SP5 1GZ",
    "wof:placetype":"postalcode"
},
  "geometry": {"coordinates":[-1.61824751311855,51.04272088662778],"type":"Point"}
}