{
  "type": "Feature",
  "properties": {
    "date:inception_lower": "2009-05-01",
    "date:inception_upper": "2009-05-01",
    "iso:country": "GB",
    "wof:name": "SP5 1GZ",
    "wof:placetype": "postalcode"
  },
  "geometry": {"coordinates":[-1.618117,51.043218],"type":"Point"}
}
