{
  "type": "Feature",
  "properties": {
    "iso:country": "GB",
    "wof:name": "WN5 9RF",
    "wof:placetype": "postalcode"
  },
  "geometry": {"coordinates":[-2.665384,53.541526],"type":"Point"}
}
