{
  "type": "Feature",
  "properties": {
    "date:inception_lower": "1980-01-01",
    "date:inception_upper": "1980-01-01",
    "iso:country": "GB",
    "wof:name": "WN5 9RF",
    "wof:placetype": "postalcode"
  },
  "geometry": {"coordinates":[-2.665323,53.541496],"type":"Point"}
}
