{
  "type": "Feature",
  "properties": {
    "iso:country": "GB",
    "wof:name": "IP6 9PP",
    "wof:placetype": "postalcode"
  },
  "geometry": {"coordinates":[1.118684,52.14482],"type":"Point"}
}
