{
  "type": "Feature",
  "properties": {
    "iso:country":"GB",
    "wof:name":"IP6 9PP",
    "wof:placetype":"postalcode"
},
  "geometry": {"coordinates":[1.11868375718533,52.14481984440412],"type":"Point"}
}