{
  "type": "Feature",
  "properties": {
    "iso:country": "GB",
    "wof:name": "PE24 4UD",
    "wof:placetype": "postalcode"
  },
  "geometry": {"coordinates":[0.297164,53.16485],"type":"Point"}
}
