{
  "type": "Feature",
  "properties": {
    "iso:country":"GB",
    "wof:name":"PE24 4UD",
    "wof:placetype":"postalcode"
},
  "geometry": {"coordinates":[0.29703655036816,53.16470857772567],"type":"Point"}
}