{
  "type": "Feature",
  "properties": {
    "iso:country":"GB",
    "wof:name":"WS3 4HN",
    "wof:placetype":"postalcode"
},
  "geometry": {"coordinates":[-1.96093073665541,52.63797026281097],"type":"Point"}
}