{
  "type": "Feature",
  "properties": {
    "date:inception_lower": "1980-01-01",
    "date:inception_upper": "1980-01-01",
    "iso:country": "GB",
    "wof:name": "WS3 4HN",
    "wof:placetype": "postalcode"
  },
  "geometry": {"coordinates":[-1.960931,52.63797],"type":"Point"}
}
