{
  "type": "Feature",
  "properties": {
    "iso:country":"GB",
    "wof:name":"BS28 4EP",
    "wof:placetype":"postalcode"
},
  "geometry": {"coordinates":[-2.80784173047786,51.23240759559413],"type":"Point"}
}