{
  "type": "Feature",
  "properties": {
    "iso:country":"GB",
    "wof:name":"TQ5 9BE",
    "wof:placetype":"postalcode"
},
  "geometry": {"coordinates":[-3.50116784227468,50.39852940876186],"type":"Point"}
}