{
  "type": "Feature",
  "properties": {
    "date:inception_lower":"2015-12-01",
    "date:inception_upper":"2015-12-31",
    "iso:country":"GB",
    "wof:name":"NR14 6SJ",
    "wof:placetype":"postalcode"
},
  "geometry": {"coordinates":[1.594523,52.521757],"type":"Point"}
}