{
  "type": "Feature",
  "properties": {
    "iso:country":"GB",
    "wof:name":"NR14 6SJ",
    "wof:placetype":"postalcode"
},
  "geometry": {"coordinates":[1.5365230770263,52.52710490301028],"type":"Point"}
}