{
  "type": "Feature",
  "properties": {
    "date:inception_lower": "1980-01-01",
    "date:inception_upper": "1980-01-01",
    "iso:country": "GB",
    "wof:name": "ME17 3HX",
    "wof:placetype": "postalcode"
  },
  "geometry": {"coordinates":[0.603091,51.222569],"type":"Point"}
}
