{
  "type": "Feature",
  "properties": {
    "iso:country":"GB",
    "wof:name":"ME17 3HX",
    "wof:placetype":"postalcode"
},
  "geometry": {"coordinates":[0.60309100614744,51.2225690542716],"type":"Point"}
}