{
  "type": "Feature",
  "properties": {
    "date:inception_lower": "2023-08-01",
    "date:inception_upper": "2023-08-01",
    "iso:country": "GB",
    "wof:name": "BA9 9GL",
    "wof:placetype": "postalcode"
  },
  "geometry": {"coordinates":[-2.423615,51.058251],"type":"Point"}
}
