{
  "type": "Feature",
  "properties": {
    "iso:country":"GB",
    "wof:name":"CH62 4RR",
    "wof:placetype":"postalcode"
},
  "geometry": {"coordinates":[-2.99412640679245,53.35777679395997],"type":"Point"}
}