{
  "type": "Feature",
  "properties": {
    "date:inception_lower":"1980-01-01",
    "date:inception_upper":"1980-01-31",
    "iso:country":"GB",
    "wof:name":"RM3 9BU",
    "wof:placetype":"postalcode"
},
  "geometry": {"coordinates":[0.225127,51.610491],"type":"Point"}
}