{
  "type": "Feature",
  "properties": {
    "iso:country":"GB",
    "wof:name":"RM3 9BU",
    "wof:placetype":"postalcode"
},
  "geometry": {"coordinates":[0.22515764198516,51.61046092028111],"type":"Point"}
}