{
  "type": "Feature",
  "properties": {
    "iso:country": "GB",
    "wof:name": "RM3 9BU",
    "wof:placetype": "postalcode"
  },
  "geometry": {"coordinates":[0.225127,51.610491],"type":"Point"}
}
