{
  "type": "Feature",
  "properties": {
    "iso:country":"GB",
    "wof:name":"SG13 8RB",
    "wof:placetype":"postalcode"
},
  "geometry": {"coordinates":[-0.11606369262812,51.72826217014746],"type":"Point"}
}