{
  "type": "Feature",
  "properties": {
    "date:inception_lower": "1993-08-01",
    "date:inception_upper": "1993-08-01",
    "iso:country": "GB",
    "wof:name": "TS25 2DH",
    "wof:placetype": "postalcode"
  },
  "geometry": {"coordinates":[-1.200367,54.650428],"type":"Point"}
}
