{
  "type": "Feature",
  "properties": {
    "iso:country":"GB",
    "wof:name":"TS25 2DH",
    "wof:placetype":"postalcode"
},
  "geometry": {"coordinates":[-1.20036696078,54.65042804817557],"type":"Point"}
}