{
  "type": "Feature",
  "properties": {
    "iso:country": "GB",
    "wof:name": "TS25 2DH",
    "wof:placetype": "postalcode"
  },
  "geometry": {"coordinates":[-1.200367,54.650428],"type":"Point"}
}
