{
  "type": "Feature",
  "properties": {
    "date:inception_lower":"1995-07-01",
    "date:inception_upper":"1995-07-31",
    "iso:country":"GB",
    "wof:name":"HP22 4SB",
    "wof:placetype":"postalcode"
},
  "geometry": {"coordinates":[-0.742959,51.865821],"type":"Point"}
}