{
  "type": "Feature",
  "properties": {
    "iso:country":"GB",
    "wof:name":"HP22 4SB",
    "wof:placetype":"postalcode"
},
  "geometry": {"coordinates":[-0.74295905167851,51.86582095378306],"type":"Point"}
}