{
  "type": "Feature",
  "properties": {
    "date:inception_lower":"1997-06-01",
    "date:inception_upper":"1997-06-30",
    "iso:country":"GB",
    "wof:name":"S26 3XX",
    "wof:placetype":"postalcode"
},
  "geometry": {"coordinates":[-1.315467,53.373737],"type":"Point"}
}