{
  "type": "Feature",
  "properties": {
    "iso:country":"GB",
    "wof:name":"S26 3XX",
    "wof:placetype":"postalcode"
},
  "geometry": {"coordinates":[-1.31546721925766,53.3737374607767],"type":"Point"}
}