{
  "type": "Feature",
  "properties": {
    "iso:country":"GB",
    "wof:name":"SS5 4NE",
    "wof:placetype":"postalcode"
},
  "geometry": {"coordinates":[0.66278013738778,51.59434039056242],"type":"Point"}
}