{
  "type": "Feature",
  "properties": {
    "iso:country":"GB",
    "wof:name":"S12 4XP",
    "wof:placetype":"postalcode"
},
  "geometry": {"coordinates":[-1.40462889131204,53.34683548969942],"type":"Point"}
}