{
  "type": "Feature",
  "properties": {
    "iso:country": "GB",
    "wof:name": "S12 4XP",
    "wof:placetype": "postalcode"
  },
  "geometry": {"coordinates":[-1.404629,53.346835],"type":"Point"}
}
