{
  "type": "Feature",
  "properties": {
    "iso:country": "GB",
    "wof:name": "SY24 5AS",
    "wof:placetype": "postalcode"
  },
  "geometry": {"coordinates":[-4.029023,52.441407],"type":"Point"}
}
