{
  "type": "Feature",
  "properties": {
    "iso:country":"GB",
    "wof:name":"SY24 5AS",
    "wof:placetype":"postalcode"
},
  "geometry": {"coordinates":[-4.02902276388256,52.44140680926277],"type":"Point"}
}