{
  "type": "Feature",
  "properties": {
    "iso:country": "GB",
    "wof:name": "PL8 2HP",
    "wof:placetype": "postalcode"
  },
  "geometry": {"coordinates":[-3.997776,50.342075],"type":"Point"}
}
