{
  "type": "Feature",
  "properties": {
    "iso:country":"GB",
    "wof:name":"PL8 2HP",
    "wof:placetype":"postalcode"
},
  "geometry": {"coordinates":[-3.99777642617456,50.34207526623447],"type":"Point"}
}