{
  "type": "Feature",
  "properties": {
    "date:inception_lower":"1995-12-01",
    "date:inception_upper":"1995-12-31",
    "iso:country":"GB",
    "wof:name":"GL2 5LE",
    "wof:placetype":"postalcode"
},
  "geometry": {"coordinates":[-2.273367,51.841035],"type":"Point"}
}