{
  "type": "Feature",
  "properties": {
    "iso:country":"GB",
    "wof:name":"GL2 5LE",
    "wof:placetype":"postalcode"
},
  "geometry": {"coordinates":[-2.27336751884374,51.84103454987309],"type":"Point"}
}