{
  "type": "Feature",
  "properties": {
    "iso:country":"GB",
    "wof:name":"LL53 6YD",
    "wof:placetype":"postalcode"
},
  "geometry": {"coordinates":[-4.43708119016422,52.92496460670876],"type":"Point"}
}