{
  "type": "Feature",
  "properties": {
    "iso:country": "GB",
    "wof:name": "LL53 6YD",
    "wof:placetype": "postalcode"
  },
  "geometry": {"coordinates":[-4.437081,52.924965],"type":"Point"}
}
