{
  "type": "Feature",
  "properties": {
    "iso:country": "GB",
    "wof:name": "L25 4TS",
    "wof:placetype": "postalcode"
  },
  "geometry": {"coordinates":[-2.879087,53.388199],"type":"Point"}
}
