{
  "type": "Feature",
  "properties": {
    "iso:country":"GB",
    "wof:name":"L25 4TS",
    "wof:placetype":"postalcode"
},
  "geometry": {"coordinates":[-2.87908682439967,53.38819937104311],"type":"Point"}
}