{
  "type": "Feature",
  "properties": {
    "iso:country": "GB",
    "wof:name": "NE24 1AW",
    "wof:placetype": "postalcode"
  },
  "geometry": {"coordinates":[-1.507442,55.127516],"type":"Point"}
}
