{
  "type": "Feature",
  "properties": {
    "date:inception_lower": "1980-01-01",
    "date:inception_upper": "1980-01-01",
    "iso:country": "GB",
    "wof:name": "NE24 1AW",
    "wof:placetype": "postalcode"
  },
  "geometry": {"coordinates":[-1.507348,55.127516],"type":"Point"}
}
