{
  "type": "Feature",
  "properties": {
    "iso:country":"GB",
    "wof:name":"GL6 9LW",
    "wof:placetype":"postalcode"
},
  "geometry": {"coordinates":[-2.1929130603,51.6918705773809],"type":"Point"}
}