{
  "type": "Feature",
  "properties": {
    "iso:country":"GB",
    "wof:name":"YO31 9AR",
    "wof:placetype":"postalcode"
},
  "geometry": {"coordinates":[-1.0601508045049,53.97785278306068],"type":"Point"}
}