{
  "type": "Feature",
  "properties": {
    "date:inception_lower": "1998-06-01",
    "date:inception_upper": "1998-06-01",
    "iso:country": "GB",
    "wof:name": "YO31 9AR",
    "wof:placetype": "postalcode"
  },
  "geometry": {"coordinates":[-1.060151,53.977853],"type":"Point"}
}
