{
  "type": "Feature",
  "properties": {
    "iso:country":"GB",
    "wof:name":"CW7 3HX",
    "wof:placetype":"postalcode"
},
  "geometry": {"coordinates":[-2.5041709920601,53.20012373414941],"type":"Point"}
}