{
  "type": "Feature",
  "properties": {
    "iso:country":"GB",
    "wof:name":"NP23 4AT",
    "wof:placetype":"postalcode"
},
  "geometry": {"coordinates":[-3.16654832571852,51.79937513626432],"type":"Point"}
}