{
  "type": "Feature",
  "properties": {
    "iso:country": "GB",
    "wof:name": "NP23 4AT",
    "wof:placetype": "postalcode"
  },
  "geometry": {"coordinates":[-3.166548,51.799375],"type":"Point"}
}
