{
  "type": "Feature",
  "properties": {
    "iso:country":"GB",
    "wof:name":"CT3 1LG",
    "wof:placetype":"postalcode"
},
  "geometry": {"coordinates":[1.26650164365438,51.26368568271632],"type":"Point"}
}