{
  "type": "Feature",
  "properties": {
    "iso:country": "GB",
    "wof:name": "CT3 1LG",
    "wof:placetype": "postalcode"
  },
  "geometry": {"coordinates":[1.266502,51.263686],"type":"Point"}
}
