{
  "type": "Feature",
  "properties": {
    "iso:country":"GB",
    "wof:name":"BH23 5SF",
    "wof:placetype":"postalcode"
},
  "geometry": {"coordinates":[-1.69337679011404,50.74779257876202],"type":"Point"}
}