{
  "type": "Feature",
  "properties": {
    "iso:country":"GB",
    "wof:name":"WF17 7BY",
    "wof:placetype":"postalcode"
},
  "geometry": {"coordinates":[-1.64522878873372,53.70747307471297],"type":"Point"}
}