{
  "type": "Feature",
  "properties": {
    "date:inception_lower": "1980-01-01",
    "date:inception_upper": "1980-01-01",
    "iso:country": "GB",
    "wof:name": "WF17 7BY",
    "wof:placetype": "postalcode"
  },
  "geometry": {"coordinates":[-1.645229,53.707473],"type":"Point"}
}
