{
  "type": "Feature",
  "properties": {
    "iso:country":"GB",
    "wof:name":"G61 4AH",
    "wof:placetype":"postalcode"
},
  "geometry": {"coordinates":[-4.34641367434225,55.91537139916167],"type":"Point"}
}