{
  "type": "Feature",
  "properties": {
    "iso:country":"GB",
    "wof:name":"SW16 6TU",
    "wof:placetype":"postalcode"
},
  "geometry": {"coordinates":[-0.14541391723187,51.42801388221898],"type":"Point"}
}