{
  "type": "Feature",
  "properties": {
    "iso:country":"GB",
    "wof:name":"KA21 6BB",
    "wof:placetype":"postalcode"
},
  "geometry": {"coordinates":[-4.79018396477565,55.64502802882198],"type":"Point"}
}