{
  "type": "Feature",
  "properties": {
    "date:inception_lower": "2000-06-01",
    "date:inception_upper": "2000-06-01",
    "iso:country": "GB",
    "wof:name": "ME19 4WA",
    "wof:placetype": "postalcode"
  },
  "geometry": {"coordinates":[0.402413,51.27684],"type":"Point"}
}
