{
  "type": "Feature",
  "properties": {
    "iso:country":"GB",
    "wof:name":"OX4 4YT",
    "wof:placetype":"postalcode"
},
  "geometry": {"coordinates":[-1.2191777171137,51.71124038555017],"type":"Point"}
}