{
  "type": "Feature",
  "properties": {
    "date:inception_lower": "2019-08-01",
    "date:inception_upper": "2019-08-01",
    "iso:country": "GB",
    "wof:name": "GL2 9GE",
    "wof:placetype": "postalcode"
  },
  "geometry": {"coordinates":[-2.211809,51.915812],"type":"Point"}
}
