{
  "type": "Feature",
  "properties": {
    "iso:country":"GB",
    "wof:name":"AL1 3FH",
    "wof:placetype":"postalcode"
},
  "geometry": {"coordinates":[-0.33639759932151,51.7549942742884],"type":"Point"}
}