{
  "type": "Feature",
  "properties": {
    "iso:country": "GB",
    "wof:name": "TR7 2DT",
    "wof:placetype": "postalcode"
  },
  "geometry": {"coordinates":[-5.081431,50.409697],"type":"Point"}
}
