{
  "type": "Feature",
  "properties": {
    "date:inception_lower": "1980-01-01",
    "date:inception_upper": "1980-01-01",
    "iso:country": "GB",
    "wof:name": "NE61 1HX",
    "wof:placetype": "postalcode"
  },
  "geometry": {"coordinates":[-1.690155,55.17225],"type":"Point"}
}
