{
  "type": "Feature",
  "properties": {
    "iso:country":"GB",
    "wof:name":"NE61 1HX",
    "wof:placetype":"postalcode"
},
  "geometry": {"coordinates":[-1.69015526619953,55.17225045231852],"type":"Point"}
}