{
  "type": "Feature",
  "properties": {
    "date:inception_lower": "2009-05-01",
    "date:inception_upper": "2009-05-01",
    "iso:country": "GB",
    "wof:name": "G90 8BU",
    "wof:placetype": "postalcode"
  },
  "geometry": {"coordinates":[-4.243649,55.868692],"type":"Point"}
}
