{
  "type": "Feature",
  "properties": {
    "iso:country":"GB",
    "wof:name":"CV37 8QA",
    "wof:placetype":"postalcode"
},
  "geometry": {"coordinates":[-1.78054115032078,52.16454425210342],"type":"Point"}
}