{
  "type": "Feature",
  "properties": {
    "iso:country": "GB",
    "wof:name": "SW8 9EX",
    "wof:placetype": "postalcode"
  },
  "geometry": {"coordinates":[-0.130353,51.475661],"type":"Point"}
}
