{
  "type": "Feature",
  "properties": {
    "iso:country": "GB",
    "wof:name": "MK4 4LB",
    "wof:placetype": "postalcode"
  },
  "geometry": {"coordinates":[-0.801162,51.994383],"type":"Point"}
}
