{
  "type": "Feature",
  "properties": {
    "date:inception_lower": "2014-06-01",
    "date:inception_upper": "2014-06-01",
    "iso:country": "GB",
    "wof:name": "MK4 4LB",
    "wof:placetype": "postalcode"
  },
  "geometry": {"coordinates":[-0.801162,51.994383],"type":"Point"}
}
