{
  "type": "Feature",
  "properties": {
    "iso:country":"GB",
    "wof:name":"E16 1BT",
    "wof:placetype":"postalcode"
},
  "geometry": {"coordinates":[0.01835124278111,51.50832921959638],"type":"Point"}
}