{
  "type": "Feature",
  "properties": {
    "iso:country": "GB",
    "wof:name": "DE11 7EB",
    "wof:placetype": "postalcode"
  },
  "geometry": {"coordinates":[-1.517713,52.783708],"type":"Point"}
}
