{
  "type": "Feature",
  "properties": {
    "iso:country":"GB",
    "wof:name":"YO41 1LE",
    "wof:placetype":"postalcode"
},
  "geometry": {"coordinates":[-0.93316816574077,54.0249511972161],"type":"Point"}
}