{
  "type": "Feature",
  "properties": {
    "date:inception_lower":"1980-01-01",
    "date:inception_upper":"1980-01-31",
    "iso:country":"GB",
    "wof:name":"NR27 0EW",
    "wof:placetype":"postalcode"
},
  "geometry": {"coordinates":[1.308663,52.918814],"type":"Point"}
}