{
  "type": "Feature",
  "properties": {
    "iso:country": "GB",
    "wof:name": "CW2 7BH",
    "wof:placetype": "postalcode"
  },
  "geometry": {"coordinates":[-2.437551,53.090892],"type":"Point"}
}
