{
  "type": "Feature",
  "properties": {
    "iso:country": "GB",
    "wof:name": "WF2 8PG",
    "wof:placetype": "postalcode"
  },
  "geometry": {"coordinates":[-1.510688,53.668278],"type":"Point"}
}
