{
  "type": "Feature",
  "properties": {
    "iso:country":"GB",
    "wof:name":"WF2 8PG",
    "wof:placetype":"postalcode"
},
  "geometry": {"coordinates":[-1.51068776303503,53.66827819488388],"type":"Point"}
}