{
  "type": "Feature",
  "properties": {
    "iso:country":"GB",
    "wof:name":"B90 4YU",
    "wof:placetype":"postalcode"
},
  "geometry": {"coordinates":[-1.78599346013559,52.38714475017616],"type":"Point"}
}