{
  "type": "Feature",
  "properties": {
    "iso:country": "GB",
    "wof:name": "CF15 7YG",
    "wof:placetype": "postalcode"
  },
  "geometry": {"coordinates":[-3.267488,51.543848],"type":"Point"}
}
