{
  "type": "Feature",
  "properties": {
    "iso:country":"GB",
    "wof:name":"WD19 7QX",
    "wof:placetype":"postalcode"
},
  "geometry": {"coordinates":[-0.40391730148551,51.62903584151093],"type":"Point"}
}