{
  "type": "Feature",
  "properties": {
    "date:inception_lower": "2000-10-01",
    "date:inception_upper": "2000-10-01",
    "iso:country": "GB",
    "wof:name": "WD19 7QX",
    "wof:placetype": "postalcode"
  },
  "geometry": {"coordinates":[-0.403917,51.629036],"type":"Point"}
}
