{
  "type": "Feature",
  "properties": {
    "date:inception_lower": "1992-01-01",
    "date:inception_upper": "1992-01-01",
    "iso:country": "GB",
    "wof:name": "CV10 8RP",
    "wof:placetype": "postalcode"
  },
  "geometry": {"coordinates":[-1.533776,52.523105],"type":"Point"}
}
