{
  "type": "Feature",
  "properties": {
    "iso:country": "GB",
    "wof:name": "CV10 8RP",
    "wof:placetype": "postalcode"
  },
  "geometry": {"coordinates":[-1.533776,52.523105],"type":"Point"}
}
