{
  "type": "Feature",
  "properties": {
    "iso:country":"GB",
    "wof:name":"CH3 8HX",
    "wof:placetype":"postalcode"
},
  "geometry": {"coordinates":[-2.76071586008841,53.1919388113993],"type":"Point"}
}