{
  "type": "Feature",
  "properties": {
    "iso:country": "GB",
    "wof:name": "CH3 8HX",
    "wof:placetype": "postalcode"
  },
  "geometry": {"coordinates":[-2.760716,53.191939],"type":"Point"}
}
