{
  "type": "Feature",
  "properties": {
    "iso:country": "GB",
    "wof:name": "NR33 8GP",
    "wof:placetype": "postalcode"
  },
  "geometry": {"coordinates":[1.700798,52.454373],"type":"Point"}
}
