{
  "type": "Feature",
  "properties": {
    "iso:country": "GB",
    "wof:name": "SS2 5SX",
    "wof:placetype": "postalcode"
  },
  "geometry": {"coordinates":[0.710534,51.562614],"type":"Point"}
}
