{
  "type": "Feature",
  "properties": {
    "iso:country":"GB",
    "wof:name":"SS2 5SX",
    "wof:placetype":"postalcode"
},
  "geometry": {"coordinates":[0.710534320233,51.56261447319182],"type":"Point"}
}