{
  "type": "Feature",
  "properties": {
    "iso:country":"GB",
    "wof:name":"DY3 1TT",
    "wof:placetype":"postalcode"
},
  "geometry": {"coordinates":[-2.11538510988448,52.53306313863023],"type":"Point"}
}