{
  "type": "Feature",
  "properties": {
    "iso:country":"GB",
    "wof:name":"IP22 4BA",
    "wof:placetype":"postalcode"
},
  "geometry": {"coordinates":[1.09912325944429,52.37462743465684],"type":"Point"}
}