{
  "type": "Feature",
  "properties": {
    "iso:country": "GB",
    "wof:name": "IP22 4BA",
    "wof:placetype": "postalcode"
  },
  "geometry": {"coordinates":[1.099123,52.374627],"type":"Point"}
}
