{
  "type": "Feature",
  "properties": {
    "iso:country":"GB",
    "wof:name":"E10 5TW",
    "wof:placetype":"postalcode"
},
  "geometry": {"coordinates":[-0.01579623543942,51.56085333495642],"type":"Point"}
}