{
  "type": "Feature",
  "properties": {
    "iso:country": "GB",
    "wof:name": "SO22 6DZ",
    "wof:placetype": "postalcode"
  },
  "geometry": {"coordinates":[-1.334899,51.077152],"type":"Point"}
}
