{
  "type": "Feature",
  "properties": {
    "iso:country":"GB",
    "wof:name":"NG4 3DR",
    "wof:placetype":"postalcode"
},
  "geometry": {"coordinates":[-1.08316679584224,52.96858147850949],"type":"Point"}
}