{
  "type": "Feature",
  "properties": {
    "iso:country":"GB",
    "wof:name":"TW9 3JD",
    "wof:placetype":"postalcode"
},
  "geometry": {"coordinates":[-0.28532935147854,51.48239018595373],"type":"Point"}
}