{
  "type": "Feature",
  "properties": {
    "iso:country": "GB",
    "wof:name": "CV1 4DT",
    "wof:placetype": "postalcode"
  },
  "geometry": {"coordinates":[-1.507769,52.422203],"type":"Point"}
}
