{
  "type": "Feature",
  "properties": {
    "iso:country":"GB",
    "wof:name":"CV1 4DT",
    "wof:placetype":"postalcode"
},
  "geometry": {"coordinates":[-1.50776878278924,52.42220297623683],"type":"Point"}
}