{
  "type": "Feature",
  "properties": {
    "date:inception_lower":"1980-01-01",
    "date:inception_upper":"1980-01-31",
    "iso:country":"GB",
    "wof:name":"CV1 4DT",
    "wof:placetype":"postalcode"
},
  "geometry": {"coordinates":[-1.507769,52.422203],"type":"Point"}
}