{
  "type": "Feature",
  "properties": {
    "iso:country":"GB",
    "wof:name":"NP8 1HB",
    "wof:placetype":"postalcode"
},
  "geometry": {"coordinates":[-3.12006861181977,51.85490829094102],"type":"Point"}
}