{
  "type": "Feature",
  "properties": {
    "iso:country": "GB",
    "wof:name": "PL27 7LF",
    "wof:placetype": "postalcode"
  },
  "geometry": {"coordinates":[-4.835134,50.493359],"type":"Point"}
}
