{
  "type": "Feature",
  "properties": {
    "iso:country":"GB",
    "wof:name":"CR7 6HN",
    "wof:placetype":"postalcode"
},
  "geometry": {"coordinates":[-0.11668142012259,51.3966479005804],"type":"Point"}
}