{
  "type": "Feature",
  "properties": {
    "date:inception_lower":"1997-06-01",
    "date:inception_upper":"1997-06-30",
    "iso:country":"GB",
    "wof:name":"WV4 4LX",
    "wof:placetype":"postalcode"
},
  "geometry": {"coordinates":[-2.163795,52.567923],"type":"Point"}
}