{
  "type": "Feature",
  "properties": {
    "iso:country":"GB",
    "wof:name":"WV4 4LX",
    "wof:placetype":"postalcode"
},
  "geometry": {"coordinates":[-2.16379461833567,52.56792256060076],"type":"Point"}
}