{
  "type": "Feature",
  "properties": {
    "iso:country":"GB",
    "wof:name":"CB9 8JW",
    "wof:placetype":"postalcode"
},
  "geometry": {"coordinates":[0.4305334425146,52.07904198831465],"type":"Point"}
}