{
  "type": "Feature",
  "properties": {
    "date:inception_lower": "1980-01-01",
    "date:inception_upper": "1980-01-01",
    "iso:country": "GB",
    "wof:name": "KY10 3RJ",
    "wof:placetype": "postalcode"
  },
  "geometry": {"coordinates":[-2.633318,56.256413],"type":"Point"}
}
