{
  "type": "Feature",
  "properties": {
    "iso:country":"GB",
    "wof:name":"NE12 9TB",
    "wof:placetype":"postalcode"
},
  "geometry": {"coordinates":[-1.54445116329393,55.02431353059163],"type":"Point"}
}