{
  "type": "Feature",
  "properties": {
    "iso:country": "GB",
    "wof:name": "RG1 7DS",
    "wof:placetype": "postalcode"
  },
  "geometry": {"coordinates":[-0.98111,51.455943],"type":"Point"}
}
