{
  "type": "Feature",
  "properties": {
    "date:inception_lower":"2009-07-01",
    "date:inception_upper":"2009-07-31",
    "iso:country":"GB",
    "wof:name":"CV32 6QL",
    "wof:placetype":"postalcode"
},
  "geometry": {"coordinates":[-1.529877,52.304267],"type":"Point"}
}