{
  "type": "Feature",
  "properties": {
    "iso:country":"GB",
    "wof:name":"YO32 4DH",
    "wof:placetype":"postalcode"
},
  "geometry": {"coordinates":[-1.07564049864502,53.99654216654066],"type":"Point"}
}