{
  "type": "Feature",
  "properties": {
    "date:inception_lower":"1998-06-01",
    "date:inception_upper":"1998-06-30",
    "iso:country":"GB",
    "wof:name":"YO32 4DH",
    "wof:placetype":"postalcode"
},
  "geometry": {"coordinates":[-1.07564,53.996542],"type":"Point"}
}