{
  "type": "Feature",
  "properties": {
    "iso:country":"GB",
    "wof:name":"W1G 8BY",
    "wof:placetype":"postalcode"
},
  "geometry": {"coordinates":[-0.14987867782476,51.52006024566089],"type":"Point"}
}