{
  "type": "Feature",
  "properties": {
    "iso:country":"GB",
    "wof:name":"B49 5HY",
    "wof:placetype":"postalcode"
},
  "geometry": {"coordinates":[-1.88834318997258,52.25399670660325],"type":"Point"}
}