{
  "type": "Feature",
  "properties": {
    "iso:country":"GB",
    "wof:name":"GL7 5PX",
    "wof:placetype":"postalcode"
},
  "geometry": {"coordinates":[-1.90136643624694,51.70218419206898],"type":"Point"}
}