{
  "type": "Feature",
  "properties": {
    "date:inception_lower":"2014-11-01",
    "date:inception_upper":"2014-11-30",
    "iso:country":"GB",
    "wof:name":"SP11 6UD",
    "wof:placetype":"postalcode"
},
  "geometry": {"coordinates":[-1.44417,51.208306],"type":"Point"}
}