{
  "type": "Feature",
  "properties": {
    "date:inception_lower":"2001-06-01",
    "date:inception_upper":"2001-06-30",
    "iso:country":"GB",
    "wof:name":"DL9 3EH",
    "wof:placetype":"postalcode"
},
  "geometry": {"coordinates":[-1.735355,54.378317],"type":"Point"}
}