{
  "type": "Feature",
  "properties": {
    "iso:country":"GB",
    "wof:name":"DL9 3EH",
    "wof:placetype":"postalcode"
},
  "geometry": {"coordinates":[-1.7353547788724,54.37831679606948],"type":"Point"}
}