{
  "type": "Feature",
  "properties": {
    "date:inception_lower":"2018-05-01",
    "date:inception_upper":"2018-05-31",
    "iso:country":"GB",
    "wof:name":"CR0 3BY",
    "wof:placetype":"postalcode"
},
  "geometry": {"coordinates":[-0.111683,51.378474],"type":"Point"}
}