{
  "type": "Feature",
  "properties": {
    "date:inception_lower": "2020-09-01",
    "date:inception_upper": "2020-09-01",
    "iso:country": "GB",
    "wof:name": "S44 6FU",
    "wof:placetype": "postalcode"
  },
  "geometry": {"coordinates":[-1.274385,53.225969],"type":"Point"}
}
