{
  "type": "Feature",
  "properties": {
    "iso:country":"GB",
    "wof:name":"YO43 3LL",
    "wof:placetype":"postalcode"
},
  "geometry": {"coordinates":[-0.66860794705398,53.90429469858901],"type":"Point"}
}