{
  "type": "Feature",
  "properties": {
    "iso:country":"GB",
    "wof:name":"SM1 3NG",
    "wof:placetype":"postalcode"
},
  "geometry": {"coordinates":[-0.1827818051184,51.37916681423768],"type":"Point"}
}