{
  "type": "Feature",
  "properties": {
    "iso:country":"GB",
    "wof:name":"HU6 8AQ",
    "wof:placetype":"postalcode"
},
  "geometry": {"coordinates":[-0.38252170434946,53.77828883721194],"type":"Point"}
}