{
  "type": "Feature",
  "properties": {
    "iso:country":"GB",
    "wof:name":"SS17 8LA",
    "wof:placetype":"postalcode"
},
  "geometry": {"coordinates":[0.40636225326382,51.52316788364681],"type":"Point"}
}