{
  "type": "Feature",
  "properties": {
    "iso:country": "GB",
    "wof:name": "SS17 8LA",
    "wof:placetype": "postalcode"
  },
  "geometry": {"coordinates":[0.406393,51.523169],"type":"Point"}
}
