{
  "type": "Feature",
  "properties": {
    "iso:country": "GB",
    "wof:name": "TN22 5DZ",
    "wof:placetype": "postalcode"
  },
  "geometry": {"coordinates":[0.09932,50.963477],"type":"Point"}
}
