{
  "type": "Feature",
  "properties": {
    "iso:country":"GB",
    "wof:name":"DH8 9HH",
    "wof:placetype":"postalcode"
},
  "geometry": {"coordinates":[-1.860921131032,54.8232002261235],"type":"Point"}
}