{
  "type": "Feature",
  "properties": {
    "iso:country":"GB",
    "wof:name":"PO21 4TA",
    "wof:placetype":"postalcode"
},
  "geometry": {"coordinates":[-0.74236433388196,50.76517578980157],"type":"Point"}
}