{
  "type": "Feature",
  "properties": {
    "iso:country": "GB",
    "wof:name": "PO21 4TA",
    "wof:placetype": "postalcode"
  },
  "geometry": {"coordinates":[-0.742437,50.765096],"type":"Point"}
}
