{
  "type": "Feature",
  "properties": {
    "iso:country":"GB",
    "wof:name":"OX9 2HQ",
    "wof:placetype":"postalcode"
},
  "geometry": {"coordinates":[-1.01874372680046,51.73618167464154],"type":"Point"}
}