{
  "type": "Feature",
  "properties": {
    "iso:country": "GB",
    "wof:name": "OX9 2HQ",
    "wof:placetype": "postalcode"
  },
  "geometry": {"coordinates":[-1.018744,51.736182],"type":"Point"}
}
