{
  "type": "Feature",
  "properties": {
    "iso:country":"GB",
    "wof:name":"GU14 6NW",
    "wof:placetype":"postalcode"
},
  "geometry": {"coordinates":[-0.74331597242441,51.28147206518113],"type":"Point"}
}