{
  "type": "Feature",
  "properties": {
    "iso:country": "GB",
    "wof:name": "DL12 8RT",
    "wof:placetype": "postalcode"
  },
  "geometry": {"coordinates":[-1.89187,54.5863],"type":"Point"}
}
