{
  "type": "Feature",
  "properties": {
    "iso:country":"GB",
    "wof:name":"GU9 0JY",
    "wof:placetype":"postalcode"
},
  "geometry": {"coordinates":[-0.7891815960827,51.23793814183264],"type":"Point"}
}