{
  "type": "Feature",
  "properties": {
    "iso:country":"GB",
    "wof:name":"WS11 4RH",
    "wof:placetype":"postalcode"
},
  "geometry": {"coordinates":[-2.02645364304371,52.71288443663779],"type":"Point"}
}