{
  "type": "Feature",
  "properties": {
    "iso:country":"GB",
    "wof:name":"DA4 0BE",
    "wof:placetype":"postalcode"
},
  "geometry": {"coordinates":[0.22118206892734,51.37747398542082],"type":"Point"}
}