{
  "type": "Feature",
  "properties": {
    "iso:country": "GB",
    "wof:name": "DA4 0BE",
    "wof:placetype": "postalcode"
  },
  "geometry": {"coordinates":[0.221182,51.377474],"type":"Point"}
}
