{
  "type": "Feature",
  "properties": {
    "date:inception_lower": "1980-01-01",
    "date:inception_upper": "1980-01-01",
    "iso:country": "GB",
    "wof:name": "SP8 5SF",
    "wof:placetype": "postalcode"
  },
  "geometry": {"coordinates":[-2.340938,50.992177],"type":"Point"}
}
