{
  "type": "Feature",
  "properties": {
    "iso:country":"GB",
    "wof:name":"SP8 5SF",
    "wof:placetype":"postalcode"
},
  "geometry": {"coordinates":[-2.34094159708011,50.99218312146141],"type":"Point"}
}