{
  "type": "Feature",
  "properties": {
    "iso:country":"GB",
    "wof:name":"BS31 1WA",
    "wof:placetype":"postalcode"
},
  "geometry": {"coordinates":[-2.5015731318743,51.40662045274649],"type":"Point"}
}