{
  "type": "Feature",
  "properties": {
    "iso:country":"GB",
    "wof:name":"W1W 6NW",
    "wof:placetype":"postalcode"
},
  "geometry": {"coordinates":[-0.14327150629614,51.5205493479597],"type":"Point"}
}