{
  "type": "Feature",
  "properties": {
    "iso:country":"GB",
    "wof:name":"PE11 3AS",
    "wof:placetype":"postalcode"
},
  "geometry": {"coordinates":[-0.17320589991938,52.76700301342051],"type":"Point"}
}