{
  "type": "Feature",
  "properties": {
    "date:inception_lower": "2007-09-01",
    "date:inception_upper": "2007-09-01",
    "iso:country": "GB",
    "wof:name": "L12 6QW",
    "wof:placetype": "postalcode"
  },
  "geometry": {"coordinates":[-2.878953,53.430583],"type":"Point"}
}
