{
  "type": "Feature",
  "properties": {
    "iso:country":"GB",
    "wof:name":"L12 6QW",
    "wof:placetype":"postalcode"
},
  "geometry": {"coordinates":[-2.87895298426545,53.43058277523105],"type":"Point"}
}