{
  "type": "Feature",
  "properties": {
    "iso:country": "GB",
    "wof:name": "RH12 3EF",
    "wof:placetype": "postalcode"
  },
  "geometry": {"coordinates":[-0.443604,51.095582],"type":"Point"}
}
