{
  "type": "Feature",
  "properties": {
    "iso:country":"GB",
    "wof:name":"EX39 6DU",
    "wof:placetype":"postalcode"
},
  "geometry": {"coordinates":[-4.51560058074624,50.99438098555424],"type":"Point"}
}