{
  "type": "Feature",
  "properties": {
    "iso:country": "GB",
    "wof:name": "SL9 7DX",
    "wof:placetype": "postalcode"
  },
  "geometry": {"coordinates":[-0.553933,51.577657],"type":"Point"}
}
