{
  "type": "Feature",
  "properties": {
    "iso:country":"GB",
    "wof:name":"SL9 7DX",
    "wof:placetype":"postalcode"
},
  "geometry": {"coordinates":[-0.55393281244385,51.5776568903607],"type":"Point"}
}