{
  "type": "Feature",
  "properties": {
    "iso:country": "GB",
    "wof:name": "PO22 9HZ",
    "wof:placetype": "postalcode"
  },
  "geometry": {"coordinates":[-0.680786,50.803786],"type":"Point"}
}
