{
  "type": "Feature",
  "properties": {
    "iso:country":"GB",
    "wof:name":"PO22 9HZ",
    "wof:placetype":"postalcode"
},
  "geometry": {"coordinates":[-0.68078633223643,50.80378622570519],"type":"Point"}
}