{
  "type": "Feature",
  "properties": {
    "date:inception_lower":"1981-06-01",
    "date:inception_upper":"1981-06-30",
    "iso:country":"GB",
    "wof:name":"PO22 9HZ",
    "wof:placetype":"postalcode"
},
  "geometry": {"coordinates":[-0.680786,50.803786],"type":"Point"}
}