{
  "type": "Feature",
  "properties": {
    "iso:country":"GB",
    "wof:name":"SE25 5HA",
    "wof:placetype":"postalcode"
},
  "geometry": {"coordinates":[-0.07206884754136,51.38755010874968],"type":"Point"}
}