{
  "type": "Feature",
  "properties": {
    "iso:country": "GB",
    "wof:name": "WF11 9NQ",
    "wof:placetype": "postalcode"
  },
  "geometry": {"coordinates":[-1.252141,53.72064],"type":"Point"}
}
