{
  "type": "Feature",
  "properties": {
    "iso:country": "GB",
    "wof:name": "MK41 6HD",
    "wof:placetype": "postalcode"
  },
  "geometry": {"coordinates":[-0.487411,52.165797],"type":"Point"}
}
