{
  "type": "Feature",
  "properties": {
    "iso:country":"GB",
    "wof:name":"MK41 6HD",
    "wof:placetype":"postalcode"
},
  "geometry": {"coordinates":[-0.48741076330756,52.16579738992282],"type":"Point"}
}