{
  "type": "Feature",
  "properties": {
    "date:inception_lower":"1980-01-01",
    "date:inception_upper":"1980-01-31",
    "iso:country":"GB",
    "wof:name":"MK41 6HD",
    "wof:placetype":"postalcode"
},
  "geometry": {"coordinates":[-0.487411,52.165797],"type":"Point"}
}