{
  "type": "Feature",
  "properties": {
    "iso:country":"GB",
    "wof:name":"BH8 9HP",
    "wof:placetype":"postalcode"
},
  "geometry": {"coordinates":[-1.86006908337515,50.74610597626471],"type":"Point"}
}