{
  "type": "Feature",
  "properties": {
    "iso:country":"GB",
    "wof:name":"PE37 8EN",
    "wof:placetype":"postalcode"
},
  "geometry": {"coordinates":[0.77715619643129,52.65021266309322],"type":"Point"}
}