{
  "type": "Feature",
  "properties": {
    "date:inception_lower": "1980-01-01",
    "date:inception_upper": "1980-01-01",
    "iso:country": "GB",
    "wof:name": "PO4 9RF",
    "wof:placetype": "postalcode"
  },
  "geometry": {"coordinates":[-1.068668,50.781724],"type":"Point"}
}
