{
  "type": "Feature",
  "properties": {
    "iso:country":"GB",
    "wof:name":"SA44 5DP",
    "wof:placetype":"postalcode"
},
  "geometry": {"coordinates":[-4.35848944149437,52.01509324589707],"type":"Point"}
}