{
  "type": "Feature",
  "properties": {
    "iso:country":"GB",
    "wof:name":"HP2 5XR",
    "wof:placetype":"postalcode"
},
  "geometry": {"coordinates":[-0.46350767637348,51.7600335928481],"type":"Point"}
}