{
  "type": "Feature",
  "properties": {
    "iso:country":"GB",
    "wof:name":"NW5 2BD",
    "wof:placetype":"postalcode"
},
  "geometry": {"coordinates":[-0.13432473559737,51.54935418903422],"type":"Point"}
}