{
  "type": "Feature",
  "properties": {
    "iso:country":"GB",
    "wof:name":"LE4 3JW",
    "wof:placetype":"postalcode"
},
  "geometry": {"coordinates":[-1.13491084343061,52.68226950750714],"type":"Point"}
}