{
  "type": "Feature",
  "properties": {
    "iso:country": "GB",
    "wof:name": "TF2 8SZ",
    "wof:placetype": "postalcode"
  },
  "geometry": {"coordinates":[-2.418925,52.714448],"type":"Point"}
}
