{
  "type": "Feature",
  "properties": {
    "date:inception_lower": "2011-02-01",
    "date:inception_upper": "2011-02-01",
    "iso:country": "GB",
    "wof:name": "TF2 8SZ",
    "wof:placetype": "postalcode"
  },
  "geometry": {"coordinates":[-2.418925,52.714448],"type":"Point"}
}
