{
  "type": "Feature",
  "properties": {
    "iso:country":"GB",
    "wof:name":"SW15 1DW",
    "wof:placetype":"postalcode"
},
  "geometry": {"coordinates":[-0.22076657745973,51.46642891614415],"type":"Point"}
}