{
  "type": "Feature",
  "properties": {
    "iso:country":"GB",
    "wof:name":"BR1 5PN",
    "wof:placetype":"postalcode"
},
  "geometry": {"coordinates":[0.00110151394148,51.42770818438544],"type":"Point"}
}