{
  "type": "Feature",
  "properties": {
    "iso:country":"GB",
    "wof:name":"EX14 9JN",
    "wof:placetype":"postalcode"
},
  "geometry": {"coordinates":[-3.12690027401356,50.79088673043574],"type":"Point"}
}