{
  "type": "Feature",
  "properties": {
    "iso:country": "GB",
    "wof:name": "TR1 1BU",
    "wof:placetype": "postalcode"
  },
  "geometry": {"coordinates":[-5.047279,50.271443],"type":"Point"}
}
