{
  "type": "Feature",
  "properties": {
    "iso:country": "GB",
    "wof:name": "KA3 5GZ",
    "wof:placetype": "postalcode"
  },
  "geometry": {"coordinates":[-4.507852,55.676807],"type":"Point"}
}
