{
  "type": "Feature",
  "properties": {
    "iso:country": "GB",
    "wof:name": "TN18 4FA",
    "wof:placetype": "postalcode"
  },
  "geometry": {"coordinates":[0.507357,51.046265],"type":"Point"}
}
