{
  "type": "Feature",
  "properties": {
    "date:inception_lower": "2018-04-01",
    "date:inception_upper": "2018-04-01",
    "iso:country": "GB",
    "wof:name": "TN18 4FA",
    "wof:placetype": "postalcode"
  },
  "geometry": {"coordinates":[0.507357,51.046265],"type":"Point"}
}
