{
  "type": "Feature",
  "properties": {
    "iso:country": "GB",
    "wof:name": "SA33 5BZ",
    "wof:placetype": "postalcode"
  },
  "geometry": {"coordinates":[-4.412211,51.838171],"type":"Point"}
}
