{
  "type": "Feature",
  "properties": {
    "date:inception_lower": "1999-06-01",
    "date:inception_upper": "1999-06-01",
    "iso:country": "GB",
    "wof:name": "NP16 7PF",
    "wof:placetype": "postalcode"
  },
  "geometry": {"coordinates":[-2.677482,51.717357],"type":"Point"}
}
