{
  "type": "Feature",
  "properties": {
    "iso:country":"GB",
    "wof:name":"CA5 7BA",
    "wof:placetype":"postalcode"
},
  "geometry": {"coordinates":[-2.94861416512836,54.83041828753397],"type":"Point"}
}