{
  "type": "Feature",
  "properties": {
    "iso:country": "GB",
    "wof:name": "CA5 7BA",
    "wof:placetype": "postalcode"
  },
  "geometry": {"coordinates":[-2.948496,54.830507],"type":"Point"}
}
