{
  "type": "Feature",
  "properties": {
    "date:inception_lower": "1980-01-01",
    "date:inception_upper": "1980-01-01",
    "iso:country": "GB",
    "wof:name": "SS17 9BQ",
    "wof:placetype": "postalcode"
  },
  "geometry": {"coordinates":[0.465047,51.525753],"type":"Point"}
}
