{
  "type": "Feature",
  "properties": {
    "iso:country":"GB",
    "wof:name":"TQ12 6QU",
    "wof:placetype":"postalcode"
},
  "geometry": {"coordinates":[-3.62219482288945,50.54935693652611],"type":"Point"}
}