{
  "type": "Feature",
  "properties": {
    "iso:country": "GB",
    "wof:name": "TQ12 6QU",
    "wof:placetype": "postalcode"
  },
  "geometry": {"coordinates":[-3.622195,50.549357],"type":"Point"}
}
