{
  "type": "Feature",
  "properties": {
    "iso:country": "GB",
    "wof:name": "BS26 2DT",
    "wof:placetype": "postalcode"
  },
  "geometry": {"coordinates":[-2.820324,51.285603],"type":"Point"}
}
