{
  "type": "Feature",
  "properties": {
    "iso:country":"GB",
    "wof:name":"TS5 8AY",
    "wof:placetype":"postalcode"
},
  "geometry": {"coordinates":[-1.25894116179432,54.54604795297382],"type":"Point"}
}