{
  "type": "Feature",
  "properties": {
    "iso:country": "GB",
    "wof:name": "OX14 4RB",
    "wof:placetype": "postalcode"
  },
  "geometry": {"coordinates":[-1.180554,51.637149],"type":"Point"}
}
