{
  "type": "Feature",
  "properties": {
    "iso:country":"GB",
    "wof:name":"OX14 4RB",
    "wof:placetype":"postalcode"
},
  "geometry": {"coordinates":[-1.18055420955255,51.63714901788506],"type":"Point"}
}