{
  "type": "Feature",
  "properties": {
    "iso:country":"GB",
    "wof:name":"BA2 8LW",
    "wof:placetype":"postalcode"
},
  "geometry": {"coordinates":[-2.42255789528189,51.29899522757573],"type":"Point"}
}