{
  "type": "Feature",
  "properties": {
    "iso:country": "GB",
    "wof:name": "BA2 8LW",
    "wof:placetype": "postalcode"
  },
  "geometry": {"coordinates":[-2.422558,51.298995],"type":"Point"}
}
