{
  "type": "Feature",
  "properties": {
    "date:inception_lower":"2002-06-01",
    "date:inception_upper":"2002-06-30",
    "iso:country":"GB",
    "wof:name":"BL8 3QX",
    "wof:placetype":"postalcode"
},
  "geometry": {"coordinates":[-2.340336,53.614007],"type":"Point"}
}