{
  "type": "Feature",
  "properties": {
    "iso:country":"GB",
    "wof:name":"BL8 3QX",
    "wof:placetype":"postalcode"
},
  "geometry": {"coordinates":[-2.34036941203113,53.61416178705779],"type":"Point"}
}