{
  "type": "Feature",
  "properties": {
    "iso:country": "GB",
    "wof:name": "BL8 3QX",
    "wof:placetype": "postalcode"
  },
  "geometry": {"coordinates":[-2.340336,53.614007],"type":"Point"}
}
