{
  "type": "Feature",
  "properties": {
    "iso:country": "GB",
    "wof:name": "TS17 5BD",
    "wof:placetype": "postalcode"
  },
  "geometry": {"coordinates":[-1.321718,54.508751],"type":"Point"}
}
