{
  "type": "Feature",
  "properties": {
    "date:inception_lower":"1993-08-01",
    "date:inception_upper":"1993-08-31",
    "iso:country":"GB",
    "wof:name":"TS23 1JR",
    "wof:placetype":"postalcode"
},
  "geometry": {"coordinates":[-1.289539,54.594671],"type":"Point"}
}