{
  "type": "Feature",
  "properties": {
    "iso:country":"GB",
    "wof:name":"TS23 1JR",
    "wof:placetype":"postalcode"
},
  "geometry": {"coordinates":[-1.28953915913934,54.59467148301714],"type":"Point"}
}