{
  "type": "Feature",
  "properties": {
    "iso:country":"GB",
    "wof:name":"TD11 3JU",
    "wof:placetype":"postalcode"
},
  "geometry": {"coordinates":[-2.2417344155496,55.79807014826544],"type":"Point"}
}