{
  "type": "Feature",
  "properties": {
    "iso:country": "GB",
    "wof:name": "RH10 6BD",
    "wof:placetype": "postalcode"
  },
  "geometry": {"coordinates":[-0.188707,51.110967],"type":"Point"}
}
