{
  "type": "Feature",
  "properties": {
    "date:inception_lower": "1988-03-01",
    "date:inception_upper": "1988-03-01",
    "iso:country": "GB",
    "wof:name": "CT9 1PR",
    "wof:placetype": "postalcode"
  },
  "geometry": {"coordinates":[1.383447,51.388396],"type":"Point"}
}
