{
  "type": "Feature",
  "properties": {
    "iso:country":"GB",
    "wof:name":"CM2 9BN",
    "wof:placetype":"postalcode"
},
  "geometry": {"coordinates":[0.46059073446113,51.72463163486852],"type":"Point"}
}