{
  "type": "Feature",
  "properties": {
    "date:inception_lower": "1984-10-01",
    "date:inception_upper": "1984-10-01",
    "iso:country": "GB",
    "wof:name": "CM2 9BN",
    "wof:placetype": "postalcode"
  },
  "geometry": {"coordinates":[0.460591,51.724632],"type":"Point"}
}
