{
  "type": "Feature",
  "properties": {
    "iso:country":"GB",
    "wof:name":"ST4 7LQ",
    "wof:placetype":"postalcode"
},
  "geometry": {"coordinates":[-2.19974310757245,53.00317513347434],"type":"Point"}
}