{
  "type": "Feature",
  "properties": {
    "iso:country":"GB",
    "wof:name":"PE30 2DN",
    "wof:placetype":"postalcode"
},
  "geometry": {"coordinates":[0.4033219080927,52.76323123735855],"type":"Point"}
}