{
  "type": "Feature",
  "properties": {
    "date:inception_lower": "1980-01-01",
    "date:inception_upper": "1980-01-01",
    "iso:country": "GB",
    "wof:name": "PE30 2DN",
    "wof:placetype": "postalcode"
  },
  "geometry": {"coordinates":[0.403322,52.763231],"type":"Point"}
}
