{
  "type": "Feature",
  "properties": {
    "iso:country":"GB",
    "wof:name":"WV14 0EP",
    "wof:placetype":"postalcode"
},
  "geometry": {"coordinates":[-2.07997249535735,52.56392764241708],"type":"Point"}
}