{
  "type": "Feature",
  "properties": {
    "iso:country": "GB",
    "wof:name": "PR8 1JY",
    "wof:placetype": "postalcode"
  },
  "geometry": {"coordinates":[-3.00987,53.640496],"type":"Point"}
}
