{
  "type": "Feature",
  "properties": {
    "iso:country":"GB",
    "wof:name":"PR8 1JY",
    "wof:placetype":"postalcode"
},
  "geometry": {"coordinates":[-3.0098699364824,53.6404955999872],"type":"Point"}
}