{
  "type": "Feature",
  "properties": {
    "date:inception_lower": "2003-04-01",
    "date:inception_upper": "2003-04-01",
    "iso:country": "GB",
    "wof:name": "LE12 7NY",
    "wof:placetype": "postalcode"
  },
  "geometry": {"coordinates":[-1.087058,52.75668],"type":"Point"}
}
