{
  "type": "Feature",
  "properties": {
    "iso:country": "GB",
    "wof:name": "CB25 9BT",
    "wof:placetype": "postalcode"
  },
  "geometry": {"coordinates":[0.190701,52.271957],"type":"Point"}
}
