{
  "type": "Feature",
  "properties": {
    "iso:country":"GB",
    "wof:name":"CB25 9BT",
    "wof:placetype":"postalcode"
},
  "geometry": {"coordinates":[0.19070117576498,52.27195739772532],"type":"Point"}
}