{
  "type": "Feature",
  "properties": {
    "iso:country":"GB",
    "wof:name":"BB9 8AW",
    "wof:placetype":"postalcode"
},
  "geometry": {"coordinates":[-2.19851507033826,53.84069337029813],"type":"Point"}
}