{
  "type": "Feature",
  "properties": {
    "date:inception_lower": "1980-01-01",
    "date:inception_upper": "1980-01-01",
    "iso:country": "GB",
    "wof:name": "BB9 8AW",
    "wof:placetype": "postalcode"
  },
  "geometry": {"coordinates":[-2.198502,53.840708],"type":"Point"}
}
