{
  "type": "Feature",
  "properties": {
    "iso:country":"GB",
    "wof:name":"N1C 4DE",
    "wof:placetype":"postalcode"
},
  "geometry": {"coordinates":[-0.12373765326056,51.53042702189428],"type":"Point"}
}