{
  "type": "Feature",
  "properties": {
    "date:inception_lower":"2015-07-01",
    "date:inception_upper":"2015-07-31",
    "iso:country":"GB",
    "wof:name":"N1C 4DE",
    "wof:placetype":"postalcode"
},
  "geometry": {"coordinates":[-0.123738,51.530427],"type":"Point"}
}