{
  "type": "Feature",
  "properties": {
    "iso:country": "GB",
    "wof:name": "N1C 4DE",
    "wof:placetype": "postalcode"
  },
  "geometry": {"coordinates":[-0.123738,51.530427],"type":"Point"}
}
