{
  "type": "Feature",
  "properties": {
    "iso:country": "GB",
    "wof:name": "NP11 7JL",
    "wof:placetype": "postalcode"
  },
  "geometry": {"coordinates":[-3.184604,51.625495],"type":"Point"}
}
