{
  "type": "Feature",
  "properties": {
    "iso:country":"GB",
    "wof:name":"NP11 7JL",
    "wof:placetype":"postalcode"
},
  "geometry": {"coordinates":[-3.18460434829786,51.62549520361774],"type":"Point"}
}