{
  "type": "Feature",
  "properties": {
    "iso:country": "GB",
    "wof:name": "LE8 0SR",
    "wof:placetype": "postalcode"
  },
  "geometry": {"coordinates":[-1.000083,52.540154],"type":"Point"}
}
