{
  "type": "Feature",
  "properties": {
    "iso:country":"GB",
    "wof:name":"DA14 6SJ",
    "wof:placetype":"postalcode"
},
  "geometry": {"coordinates":[0.11623454677794,51.41850037539125],"type":"Point"}
}