{
  "type": "Feature",
  "properties": {
    "iso:country":"GB",
    "wof:name":"DE4 5EL",
    "wof:placetype":"postalcode"
},
  "geometry": {"coordinates":[-1.49450617555723,53.09057091836884],"type":"Point"}
}