{
  "type": "Feature",
  "properties": {
    "iso:country":"GB",
    "wof:name":"DH3 2LG",
    "wof:placetype":"postalcode"
},
  "geometry": {"coordinates":[-1.56162619808946,54.89079511788147],"type":"Point"}
}