{
  "type": "Feature",
  "properties": {
    "date:inception_lower": "1984-10-01",
    "date:inception_upper": "1984-10-01",
    "iso:country": "GB",
    "wof:name": "DH3 2LG",
    "wof:placetype": "postalcode"
  },
  "geometry": {"coordinates":[-1.561638,54.890803],"type":"Point"}
}
