{
  "type": "Feature",
  "properties": {
    "iso:country": "GB",
    "wof:name": "DH3 2LG",
    "wof:placetype": "postalcode"
  },
  "geometry": {"coordinates":[-1.561638,54.890803],"type":"Point"}
}
