{
  "type": "Feature",
  "properties": {
    "date:inception_lower": "2002-06-01",
    "date:inception_upper": "2002-06-01",
    "iso:country": "GB",
    "wof:name": "LE19 2LB",
    "wof:placetype": "postalcode"
  },
  "geometry": {"coordinates":[-1.197403,52.58079],"type":"Point"}
}
