{
  "type": "Feature",
  "properties": {
    "iso:country": "GB",
    "wof:name": "EN7 5FF",
    "wof:placetype": "postalcode"
  },
  "geometry": {"coordinates":[-0.051832,51.707363],"type":"Point"}
}
