{
  "type": "Feature",
  "properties": {
    "iso:country": "GB",
    "wof:name": "BS8 1FD",
    "wof:placetype": "postalcode"
  },
  "geometry": {"coordinates":[-2.60152,51.459048],"type":"Point"}
}
