{
  "type": "Feature",
  "properties": {
    "iso:country":"GB",
    "wof:name":"BS8 1FD",
    "wof:placetype":"postalcode"
},
  "geometry": {"coordinates":[-2.60151995823931,51.45904794492233],"type":"Point"}
}