{
  "type": "Feature",
  "properties": {
    "date:inception_lower":"2008-10-01",
    "date:inception_upper":"2008-10-31",
    "iso:country":"GB",
    "wof:name":"BS8 1FD",
    "wof:placetype":"postalcode"
},
  "geometry": {"coordinates":[-2.60152,51.459048],"type":"Point"}
}