{
  "type": "Feature",
  "properties": {
    "iso:country":"GB",
    "wof:name":"BS9 4RN",
    "wof:placetype":"postalcode"
},
  "geometry": {"coordinates":[-2.60362370368971,51.48866450249746],"type":"Point"}
}