{
  "type": "Feature",
  "properties": {
    "iso:country":"GB",
    "wof:name":"BN25 3PZ",
    "wof:placetype":"postalcode"
},
  "geometry": {"coordinates":[0.11820520105818,50.77790240331273],"type":"Point"}
}