{
  "type": "Feature",
  "properties": {
    "iso:country": "GB",
    "wof:name": "IP25 7AQ",
    "wof:placetype": "postalcode"
  },
  "geometry": {"coordinates":[0.78511,52.597532],"type":"Point"}
}
