{
  "type": "Feature",
  "properties": {
    "iso:country":"GB",
    "wof:name":"SP1 2AN",
    "wof:placetype":"postalcode"
},
  "geometry": {"coordinates":[-1.79313788471098,51.06824901170177],"type":"Point"}
}