{
  "type": "Feature",
  "properties": {
    "iso:country":"GB",
    "wof:name":"WN1 3QN",
    "wof:placetype":"postalcode"
},
  "geometry": {"coordinates":[-2.62416811995063,53.5463413617607],"type":"Point"}
}