{
  "type": "Feature",
  "properties": {
    "date:inception_lower": "1980-01-01",
    "date:inception_upper": "1980-01-01",
    "iso:country": "GB",
    "wof:name": "LL55 2PB",
    "wof:placetype": "postalcode"
  },
  "geometry": {"coordinates":[-4.275102,53.138758],"type":"Point"}
}
