{
  "type": "Feature",
  "properties": {
    "iso:country": "GB",
    "wof:name": "LL55 2PB",
    "wof:placetype": "postalcode"
  },
  "geometry": {"coordinates":[-4.275102,53.138758],"type":"Point"}
}
