{
  "type": "Feature",
  "properties": {
    "date:inception_lower": "2003-07-01",
    "date:inception_upper": "2003-07-01",
    "iso:country": "GB",
    "wof:name": "SW14 7SJ",
    "wof:placetype": "postalcode"
  },
  "geometry": {"coordinates":[-0.272405,51.467669],"type":"Point"}
}
