{
  "type": "Feature",
  "properties": {
    "iso:country": "GB",
    "wof:name": "NN17 9TB",
    "wof:placetype": "postalcode"
  },
  "geometry": {"coordinates":[-0.703238,52.487432],"type":"Point"}
}
