{
  "type": "Feature",
  "properties": {
    "date:inception_lower": "2001-06-01",
    "date:inception_upper": "2001-06-01",
    "iso:country": "GB",
    "wof:name": "B76 2QQ",
    "wof:placetype": "postalcode"
  },
  "geometry": {"coordinates":[-1.801467,52.547292],"type":"Point"}
}
