{
  "type": "Feature",
  "properties": {
    "iso:country":"GB",
    "wof:name":"OX17 2ET",
    "wof:placetype":"postalcode"
},
  "geometry": {"coordinates":[-1.23324107986274,52.10347663062973],"type":"Point"}
}