{
  "type": "Feature",
  "properties": {
    "iso:country":"GB",
    "wof:name":"WF3 3ET",
    "wof:placetype":"postalcode"
},
  "geometry": {"coordinates":[-1.49326919365103,53.72109245841456],"type":"Point"}
}