{
  "type": "Feature",
  "properties": {
    "iso:country": "GB",
    "wof:name": "SG18 8YN",
    "wof:placetype": "postalcode"
  },
  "geometry": {"coordinates":[-0.245293,52.083321],"type":"Point"}
}
