{
  "type": "Feature",
  "properties": {
    "date:inception_lower": "2020-02-01",
    "date:inception_upper": "2020-02-01",
    "iso:country": "GB",
    "wof:name": "SG18 8YN",
    "wof:placetype": "postalcode"
  },
  "geometry": {"coordinates":[-0.245351,52.08334],"type":"Point"}
}
