{
  "type": "Feature",
  "properties": {
    "iso:country": "GB",
    "wof:name": "WS1 1YB",
    "wof:placetype": "postalcode"
  },
  "geometry": {"coordinates":[-1.979464,52.587891],"type":"Point"}
}
