{
  "type": "Feature",
  "properties": {
    "iso:country":"GB",
    "wof:name":"WS1 1YB",
    "wof:placetype":"postalcode"
},
  "geometry": {"coordinates":[-1.97948453301819,52.58741650362587],"type":"Point"}
}