{
  "type": "Feature",
  "properties": {
    "iso:country":"GB",
    "wof:name":"KY5 8ER",
    "wof:placetype":"postalcode"
},
  "geometry": {"coordinates":[-3.32220164548897,56.15716268508177],"type":"Point"}
}