{
  "type": "Feature",
  "properties": {
    "iso:country":"GB",
    "wof:name":"YO1 6LE",
    "wof:placetype":"postalcode"
},
  "geometry": {"coordinates":[-1.08944675579552,53.95663279188458],"type":"Point"}
}