{
  "type": "Feature",
  "properties": {
    "date:inception_lower": "1998-06-01",
    "date:inception_upper": "1998-06-01",
    "iso:country": "GB",
    "wof:name": "YO1 6LE",
    "wof:placetype": "postalcode"
  },
  "geometry": {"coordinates":[-1.089394,53.956686],"type":"Point"}
}
