{
  "type": "Feature",
  "properties": {
    "date:inception_lower":"2005-02-01",
    "date:inception_upper":"2005-02-28",
    "iso:country":"GB",
    "wof:name":"DE4 9TE",
    "wof:placetype":"postalcode"
},
  "geometry": {"coordinates":[-1.554264,53.139683],"type":"Point"}
}