{
  "type": "Feature",
  "properties": {
    "date:inception_lower": "1980-01-01",
    "date:inception_upper": "1980-01-01",
    "iso:country": "GB",
    "wof:name": "IP3 9LY",
    "wof:placetype": "postalcode"
  },
  "geometry": {"coordinates":[1.182948,52.035354],"type":"Point"}
}
