{
  "type": "Feature",
  "properties": {
    "date:inception_lower": "2020-10-01",
    "date:inception_upper": "2020-10-01",
    "iso:country": "GB",
    "wof:name": "WF9 4FL",
    "wof:placetype": "postalcode"
  },
  "geometry": {"coordinates":[-1.361444,53.613914],"type":"Point"}
}
