{
  "type": "Feature",
  "properties": {
    "date:inception_lower":"1994-05-01",
    "date:inception_upper":"1994-05-31",
    "iso:country":"GB",
    "wof:name":"BN2 4EY",
    "wof:placetype":"postalcode"
},
  "geometry": {"coordinates":[-0.123664,50.840889],"type":"Point"}
}