{
  "type": "Feature",
  "properties": {
    "iso:country":"GB",
    "wof:name":"LL12 8YY",
    "wof:placetype":"postalcode"
},
  "geometry": {"coordinates":[-2.96506935863177,53.08745883169248],"type":"Point"}
}