{
  "type": "Feature",
  "properties": {
    "iso:country":"GB",
    "wof:name":"BN8 6HW",
    "wof:placetype":"postalcode"
},
  "geometry": {"coordinates":[0.19710641960646,50.89922609545779],"type":"Point"}
}