{
  "type": "Feature",
  "properties": {
    "iso:country": "GB",
    "wof:name": "BN8 6HW",
    "wof:placetype": "postalcode"
  },
  "geometry": {"coordinates":[0.197351,50.899289],"type":"Point"}
}
