{
  "type": "Feature",
  "properties": {
    "iso:country": "GB",
    "wof:name": "EX22 6DJ",
    "wof:placetype": "postalcode"
  },
  "geometry": {"coordinates":[-4.353379,50.81063],"type":"Point"}
}
