{
  "type": "Feature",
  "properties": {
    "iso:country":"GB",
    "wof:name":"EX22 6DJ",
    "wof:placetype":"postalcode"
},
  "geometry": {"coordinates":[-4.35334964123923,50.81063635629317],"type":"Point"}
}