{
  "type": "Feature",
  "properties": {
    "iso:country": "GB",
    "wof:name": "DT2 8PL",
    "wof:placetype": "postalcode"
  },
  "geometry": {"coordinates":[-2.393417,50.67638],"type":"Point"}
}
