{
  "type": "Feature",
  "properties": {
    "date:inception_lower": "1980-01-01",
    "date:inception_upper": "1980-01-01",
    "iso:country": "GB",
    "wof:name": "DT2 8PL",
    "wof:placetype": "postalcode"
  },
  "geometry": {"coordinates":[-2.393417,50.67638],"type":"Point"}
}
