{
  "type": "Feature",
  "properties": {
    "iso:country":"GB",
    "wof:name":"DT2 8PL",
    "wof:placetype":"postalcode"
},
  "geometry": {"coordinates":[-2.3934173479807,50.67638003984842],"type":"Point"}
}