{
  "type": "Feature",
  "properties": {
    "date:inception_lower": "2018-05-01",
    "date:inception_upper": "2018-05-01",
    "iso:country": "GB",
    "wof:name": "OX25 2BF",
    "wof:placetype": "postalcode"
  },
  "geometry": {"coordinates":[-1.148958,51.883266],"type":"Point"}
}
