{
  "type": "Feature",
  "properties": {
    "iso:country":"GB",
    "wof:name":"IV32 7JX",
    "wof:placetype":"postalcode"
},
  "geometry": {"coordinates":[-3.11783049178392,57.62631466257946],"type":"Point"}
}