{
  "type": "Feature",
  "properties": {
    "iso:country": "GB",
    "wof:name": "CH62 8HB",
    "wof:placetype": "postalcode"
  },
  "geometry": {"coordinates":[-2.97172,53.314706],"type":"Point"}
}
