{
  "type": "Feature",
  "properties": {
    "date:inception_lower":"2000-12-01",
    "date:inception_upper":"2000-12-31",
    "iso:country":"GB",
    "wof:name":"LL13 7HN",
    "wof:placetype":"postalcode"
},
  "geometry": {"coordinates":[-2.995012,53.044998],"type":"Point"}
}