{
  "type": "Feature",
  "properties": {
    "iso:country": "GB",
    "wof:name": "LL13 7HN",
    "wof:placetype": "postalcode"
  },
  "geometry": {"coordinates":[-2.995012,53.044998],"type":"Point"}
}
