{
  "type": "Feature",
  "properties": {
    "iso:country": "GB",
    "wof:name": "CW2 6TB",
    "wof:placetype": "postalcode"
  },
  "geometry": {"coordinates":[-2.45437,53.077282],"type":"Point"}
}
