{
  "type": "Feature",
  "properties": {
    "iso:country":"GB",
    "wof:name":"B45 9SP",
    "wof:placetype":"postalcode"
},
  "geometry": {"coordinates":[-2.02319028137037,52.39583129578068],"type":"Point"}
}