{
  "type": "Feature",
  "properties": {
    "iso:country": "GB",
    "wof:name": "B45 9SP",
    "wof:placetype": "postalcode"
  },
  "geometry": {"coordinates":[-2.02319,52.395831],"type":"Point"}
}
