{
  "type": "Feature",
  "properties": {
    "iso:country": "GB",
    "wof:name": "BL9 9JW",
    "wof:placetype": "postalcode"
  },
  "geometry": {"coordinates":[-2.291566,53.584216],"type":"Point"}
}
