{
  "type": "Feature",
  "properties": {
    "iso:country":"GB",
    "wof:name":"BL9 9JW",
    "wof:placetype":"postalcode"
},
  "geometry": {"coordinates":[-2.291565587926,53.58421591351411],"type":"Point"}
}