{
  "type": "Feature",
  "properties": {
    "iso:country":"GB",
    "wof:name":"YO21 2NG",
    "wof:placetype":"postalcode"
},
  "geometry": {"coordinates":[-0.92366584049781,54.46098989497016],"type":"Point"}
}