{
  "type": "Feature",
  "properties": {
    "date:inception_lower": "1980-01-01",
    "date:inception_upper": "1980-01-01",
    "iso:country": "GB",
    "wof:name": "SY6 7JP",
    "wof:placetype": "postalcode"
  },
  "geometry": {"coordinates":[-2.773035,52.571378],"type":"Point"}
}
