{
  "type": "Feature",
  "properties": {
    "iso:country":"GB",
    "wof:name":"SY6 7JP",
    "wof:placetype":"postalcode"
},
  "geometry": {"coordinates":[-2.76854881617268,52.57727233432425],"type":"Point"}
}