{
  "type": "Feature",
  "properties": {
    "iso:country":"GB",
    "wof:name":"SA47 0RY",
    "wof:placetype":"postalcode"
},
  "geometry": {"coordinates":[-4.25663623935461,52.203957077661],"type":"Point"}
}