{
  "type": "Feature",
  "properties": {
    "date:inception_lower": "1980-01-01",
    "date:inception_upper": "1980-01-01",
    "iso:country": "GB",
    "wof:name": "TN11 0HE",
    "wof:placetype": "postalcode"
  },
  "geometry": {"coordinates":[0.336602,51.227197],"type":"Point"}
}
