{
  "type": "Feature",
  "properties": {
    "iso:country": "GB",
    "wof:name": "TN11 0HE",
    "wof:placetype": "postalcode"
  },
  "geometry": {"coordinates":[0.336602,51.227197],"type":"Point"}
}
