{
  "type": "Feature",
  "properties": {
    "iso:country": "GB",
    "wof:name": "TR3 7NF",
    "wof:placetype": "postalcode"
  },
  "geometry": {"coordinates":[-5.119894,50.211663],"type":"Point"}
}
