{
  "type": "Feature",
  "properties": {
    "iso:country":"GB",
    "wof:name":"TR3 7NF",
    "wof:placetype":"postalcode"
},
  "geometry": {"coordinates":[-5.11989378018433,50.21166268304554],"type":"Point"}
}