{
  "type": "Feature",
  "properties": {
    "date:inception_lower":"1980-01-01",
    "date:inception_upper":"1980-01-31",
    "iso:country":"GB",
    "wof:name":"TR3 7NF",
    "wof:placetype":"postalcode"
},
  "geometry": {"coordinates":[-5.119894,50.211663],"type":"Point"}
}