{
  "type": "Feature",
  "properties": {
    "iso:country":"GB",
    "wof:name":"NR15 2BY",
    "wof:placetype":"postalcode"
},
  "geometry": {"coordinates":[1.18681785165256,52.43187621989969],"type":"Point"}
}