{
  "type": "Feature",
  "properties": {
    "iso:country": "GB",
    "wof:name": "NR15 2BY",
    "wof:placetype": "postalcode"
  },
  "geometry": {"coordinates":[1.186816,52.431907],"type":"Point"}
}
