{
  "type": "Feature",
  "properties": {
    "date:inception_lower":"1983-01-01",
    "date:inception_upper":"1983-01-31",
    "iso:country":"GB",
    "wof:name":"NR15 2BY",
    "wof:placetype":"postalcode"
},
  "geometry": {"coordinates":[1.186818,52.431876],"type":"Point"}
}