{
  "type": "Feature",
  "properties": {
    "date:inception_lower": "2012-12-01",
    "date:inception_upper": "2012-12-01",
    "iso:country": "GB",
    "wof:name": "PR7 3FP",
    "wof:placetype": "postalcode"
  },
  "geometry": {"coordinates":[-2.625281,53.639141],"type":"Point"}
}
