{
  "type": "Feature",
  "properties": {
    "iso:country":"GB",
    "wof:name":"DE1 1PB",
    "wof:placetype":"postalcode"
},
  "geometry": {"coordinates":[-1.48132894609569,52.91828005738656],"type":"Point"}
}