{
  "type": "Feature",
  "properties": {
    "date:inception_lower": "1993-08-01",
    "date:inception_upper": "1993-08-01",
    "iso:country": "GB",
    "wof:name": "SY5 0PG",
    "wof:placetype": "postalcode"
  },
  "geometry": {"coordinates":[-2.937757,52.598246],"type":"Point"}
}
