{
  "type": "Feature",
  "properties": {
    "iso:country":"GB",
    "wof:name":"SY5 0PG",
    "wof:placetype":"postalcode"
},
  "geometry": {"coordinates":[-2.93775872393762,52.59824943052092],"type":"Point"}
}