{
  "type": "Feature",
  "properties": {
    "date:inception_lower": "1992-08-01",
    "date:inception_upper": "1992-08-01",
    "iso:country": "GB",
    "wof:name": "CM2 9XW",
    "wof:placetype": "postalcode"
  },
  "geometry": {"coordinates":[0.462137,51.72057],"type":"Point"}
}
