{
  "type": "Feature",
  "properties": {
    "iso:country":"GB",
    "wof:name":"NE8 2GQ",
    "wof:placetype":"postalcode"
},
  "geometry": {"coordinates":[-1.63516604833255,54.95618891512176],"type":"Point"}
}