{
  "type": "Feature",
  "properties": {
    "date:inception_lower":"2014-07-01",
    "date:inception_upper":"2014-07-31",
    "iso:country":"GB",
    "wof:name":"NE8 2GQ",
    "wof:placetype":"postalcode"
},
  "geometry": {"coordinates":[-1.635166,54.956189],"type":"Point"}
}