{
  "type": "Feature",
  "properties": {
    "iso:country": "GB",
    "wof:name": "BH24 2SG",
    "wof:placetype": "postalcode"
  },
  "geometry": {"coordinates":[-1.83293,50.816833],"type":"Point"}
}
