{
  "type": "Feature",
  "properties": {
    "date:inception_lower": "1980-01-01",
    "date:inception_upper": "1980-01-01",
    "iso:country": "GB",
    "wof:name": "B76 9QE",
    "wof:placetype": "postalcode"
  },
  "geometry": {"coordinates":[-1.75473,52.537559],"type":"Point"}
}
