{
  "type": "Feature",
  "properties": {
    "iso:country":"GB",
    "wof:name":"PL18 9EN",
    "wof:placetype":"postalcode"
},
  "geometry": {"coordinates":[-4.22591080451925,50.51522764903809],"type":"Point"}
}