{
  "type": "Feature",
  "properties": {
    "iso:country": "GB",
    "wof:name": "PL18 9EN",
    "wof:placetype": "postalcode"
  },
  "geometry": {"coordinates":[-4.225911,50.515228],"type":"Point"}
}
