{
  "type": "Feature",
  "properties": {
    "iso:country":"GB",
    "wof:name":"LN6 8QR",
    "wof:placetype":"postalcode"
},
  "geometry": {"coordinates":[-0.59268367093113,53.19175058230987],"type":"Point"}
}