{
  "type": "Feature",
  "properties": {
    "iso:country":"GB",
    "wof:name":"TD15 2AW",
    "wof:placetype":"postalcode"
},
  "geometry": {"coordinates":[-2.01085835609366,55.76240367769874],"type":"Point"}
}