{
  "type": "Feature",
  "properties": {
    "iso:country":"GB",
    "wof:name":"S73 8FL",
    "wof:placetype":"postalcode"
},
  "geometry": {"coordinates":[-1.40088499071915,53.52268861396976],"type":"Point"}
}