{
  "type": "Feature",
  "properties": {
    "iso:country": "GB",
    "wof:name": "S73 8FL",
    "wof:placetype": "postalcode"
  },
  "geometry": {"coordinates":[-1.400885,53.522689],"type":"Point"}
}
