{
  "type": "Feature",
  "properties": {
    "iso:country": "GB",
    "wof:name": "FK1 5LZ",
    "wof:placetype": "postalcode"
  },
  "geometry": {"coordinates":[-3.802264,56.000753],"type":"Point"}
}
