{
  "type": "Feature",
  "properties": {
    "iso:country":"GB",
    "wof:name":"FK1 5LZ",
    "wof:placetype":"postalcode"
},
  "geometry": {"coordinates":[-3.8022639021843,56.00075278819307],"type":"Point"}
}