{
  "type": "Feature",
  "properties": {
    "date:inception_lower": "1986-02-01",
    "date:inception_upper": "1986-02-01",
    "iso:country": "GB",
    "wof:name": "FK1 5LZ",
    "wof:placetype": "postalcode"
  },
  "geometry": {"coordinates":[-3.802264,56.000753],"type":"Point"}
}
