{
  "type": "Feature",
  "properties": {
    "date:inception_lower": "2023-07-01",
    "date:inception_upper": "2023-07-01",
    "iso:country": "GB",
    "wof:name": "AL2 3FT",
    "wof:placetype": "postalcode"
  },
  "geometry": {"coordinates":[-0.348521,51.703629],"type":"Point"}
}
