{
  "type": "Feature",
  "properties": {
    "iso:country": "GB",
    "wof:name": "RH15 9HJ",
    "wof:placetype": "postalcode"
  },
  "geometry": {"coordinates":[-0.139278,50.947477],"type":"Point"}
}
