{
  "type": "Feature",
  "properties": {
    "date:inception_lower":"1980-01-01",
    "date:inception_upper":"1980-01-31",
    "iso:country":"GB",
    "wof:name":"DE55 1BE",
    "wof:placetype":"postalcode"
},
  "geometry": {"coordinates":[-1.393811,53.076383],"type":"Point"}
}