{
  "type": "Feature",
  "properties": {
    "iso:country":"GB",
    "wof:name":"DE55 1BE",
    "wof:placetype":"postalcode"
},
  "geometry": {"coordinates":[-1.39381095521913,53.07638341663286],"type":"Point"}
}