{
  "type": "Feature",
  "properties": {
    "iso:country":"GB",
    "wof:name":"LA9 5BN",
    "wof:placetype":"postalcode"
},
  "geometry": {"coordinates":[-2.75947669507369,54.31915505332217],"type":"Point"}
}