{
  "type": "Feature",
  "properties": {
    "date:inception_lower": "1991-01-01",
    "date:inception_upper": "1991-01-01",
    "iso:country": "GB",
    "wof:name": "LA9 5BN",
    "wof:placetype": "postalcode"
  },
  "geometry": {"coordinates":[-2.759477,54.319155],"type":"Point"}
}
