{
  "type": "Feature",
  "properties": {
    "iso:country":"GB",
    "wof:name":"AL8 7DJ",
    "wof:placetype":"postalcode"
},
  "geometry": {"coordinates":[-0.21439843283858,51.80211190379389],"type":"Point"}
}