{
  "type": "Feature",
  "properties": {
    "iso:country": "GB",
    "wof:name": "CF24 4AS",
    "wof:placetype": "postalcode"
  },
  "geometry": {"coordinates":[-3.179044,51.49027],"type":"Point"}
}
