{
  "type": "Feature",
  "properties": {
    "iso:country": "GB",
    "wof:name": "KT24 5BX",
    "wof:placetype": "postalcode"
  },
  "geometry": {"coordinates":[-0.428382,51.282309],"type":"Point"}
}
