{
  "type": "Feature",
  "properties": {
    "iso:country":"GB",
    "wof:name":"BD15 7DD",
    "wof:placetype":"postalcode"
},
  "geometry": {"coordinates":[-1.82074329658624,53.80126748459939],"type":"Point"}
}