{
  "type": "Feature",
  "properties": {
    "iso:country": "GB",
    "wof:name": "BD15 7DD",
    "wof:placetype": "postalcode"
  },
  "geometry": {"coordinates":[-1.820743,53.801267],"type":"Point"}
}
