{
  "type": "Feature",
  "properties": {
    "iso:country":"GB",
    "wof:name":"S70 1XU",
    "wof:placetype":"postalcode"
},
  "geometry": {"coordinates":[-1.47096895826457,53.54759354639105],"type":"Point"}
}