{
  "type": "Feature",
  "properties": {
    "iso:country": "GB",
    "wof:name": "CM2 8XR",
    "wof:placetype": "postalcode"
  },
  "geometry": {"coordinates":[0.469323,51.710032],"type":"Point"}
}
