{
  "type": "Feature",
  "properties": {
    "date:inception_lower": "1980-01-01",
    "date:inception_upper": "1980-01-01",
    "iso:country": "GB",
    "wof:name": "ST2 0QB",
    "wof:placetype": "postalcode"
  },
  "geometry": {"coordinates":[-2.119159,53.009774],"type":"Point"}
}
