{
  "type": "Feature",
  "properties": {
    "iso:country": "GB",
    "wof:name": "ST2 0QB",
    "wof:placetype": "postalcode"
  },
  "geometry": {"coordinates":[-2.119159,53.009774],"type":"Point"}
}
