{
  "type": "Feature",
  "properties": {
    "iso:country":"GB",
    "wof:name":"ST2 0QB",
    "wof:placetype":"postalcode"
},
  "geometry": {"coordinates":[-2.11915912818083,53.0097735314808],"type":"Point"}
}