{
  "type": "Feature",
  "properties": {
    "iso:country":"GB",
    "wof:name":"HA8 0TN",
    "wof:placetype":"postalcode"
},
  "geometry": {"coordinates":[-0.26360282683889,51.60535529694943],"type":"Point"}
}