{
  "type": "Feature",
  "properties": {
    "date:inception_lower": "2011-05-01",
    "date:inception_upper": "2011-05-01",
    "iso:country": "GB",
    "wof:name": "SN1 2DJ",
    "wof:placetype": "postalcode"
  },
  "geometry": {"coordinates":[-1.779599,51.558995],"type":"Point"}
}
