{
  "type": "Feature",
  "properties": {
    "iso:country": "GB",
    "wof:name": "SN1 2DJ",
    "wof:placetype": "postalcode"
  },
  "geometry": {"coordinates":[-1.779599,51.558995],"type":"Point"}
}
