{
  "type": "Feature",
  "properties": {
    "iso:country":"GB",
    "wof:name":"SN1 2DJ",
    "wof:placetype":"postalcode"
},
  "geometry": {"coordinates":[-1.77959857971213,51.558994897801],"type":"Point"}
}