{
  "type": "Feature",
  "properties": {
    "iso:country": "GB",
    "wof:name": "M43 6GT",
    "wof:placetype": "postalcode"
  },
  "geometry": {"coordinates":[-2.149788,53.477175],"type":"Point"}
}
