{
  "type": "Feature",
  "properties": {
    "iso:country":"GB",
    "wof:name":"M43 6GT",
    "wof:placetype":"postalcode"
},
  "geometry": {"coordinates":[-2.14978789210235,53.47717457517147],"type":"Point"}
}