{
  "type": "Feature",
  "properties": {
    "iso:country":"GB",
    "wof:name":"DL9 3HR",
    "wof:placetype":"postalcode"
},
  "geometry": {"coordinates":[-1.72838383564215,54.37785197512496],"type":"Point"}
}