{
  "type": "Feature",
  "properties": {
    "iso:country": "GB",
    "wof:name": "ME13 8PN",
    "wof:placetype": "postalcode"
  },
  "geometry": {"coordinates":[0.890053,51.314426],"type":"Point"}
}
