{
  "type": "Feature",
  "properties": {
    "iso:country":"GB",
    "wof:name":"KT5 8QB",
    "wof:placetype":"postalcode"
},
  "geometry": {"coordinates":[-0.29382479388156,51.39439714407593],"type":"Point"}
}