{
  "type": "Feature",
  "properties": {
    "date:inception_lower": "1991-09-01",
    "date:inception_upper": "1991-09-01",
    "iso:country": "GB",
    "wof:name": "OX18 3HS",
    "wof:placetype": "postalcode"
  },
  "geometry": {"coordinates":[-1.589657,51.761831],"type":"Point"}
}
