{
  "type": "Feature",
  "properties": {
    "iso:country":"GB",
    "wof:name":"DA1 1XG",
    "wof:placetype":"postalcode"
},
  "geometry": {"coordinates":[0.23487302680336,51.44315109900618],"type":"Point"}
}