{
  "type": "Feature",
  "properties": {
    "iso:country": "GB",
    "wof:name": "CM7 3QY",
    "wof:placetype": "postalcode"
  },
  "geometry": {"coordinates":[0.583089,51.873149],"type":"Point"}
}
