{
  "type": "Feature",
  "properties": {
    "iso:country":"GB",
    "wof:name":"CM7 3QY",
    "wof:placetype":"postalcode"
},
  "geometry": {"coordinates":[0.58308898432193,51.8731493427097],"type":"Point"}
}