{
  "type": "Feature",
  "properties": {
    "iso:country": "GB",
    "wof:name": "OL7 9NZ",
    "wof:placetype": "postalcode"
  },
  "geometry": {"coordinates":[-2.112013,53.499901],"type":"Point"}
}
