{
  "type": "Feature",
  "properties": {
    "date:inception_lower": "2015-12-01",
    "date:inception_upper": "2015-12-01",
    "iso:country": "GB",
    "wof:name": "OL7 9NZ",
    "wof:placetype": "postalcode"
  },
  "geometry": {"coordinates":[-2.112013,53.499901],"type":"Point"}
}
