{
  "type": "Feature",
  "properties": {
    "iso:country":"GB",
    "wof:name":"OL7 9NZ",
    "wof:placetype":"postalcode"
},
  "geometry": {"coordinates":[-2.10831609195318,53.50381619618123],"type":"Point"}
}