{
  "type": "Feature",
  "properties": {
    "date:inception_lower": "2021-01-01",
    "date:inception_upper": "2021-01-01",
    "iso:country": "GB",
    "wof:name": "BS35 1FN",
    "wof:placetype": "postalcode"
  },
  "geometry": {"coordinates":[-2.518081,51.618912],"type":"Point"}
}
