{
  "type": "Feature",
  "properties": {
    "iso:country":"GB",
    "wof:name":"GU21 3PS",
    "wof:placetype":"postalcode"
},
  "geometry": {"coordinates":[-0.59352070936569,51.31763547639323],"type":"Point"}
}