{
  "type": "Feature",
  "properties": {
    "iso:country": "GB",
    "wof:name": "SN12 8BZ",
    "wof:placetype": "postalcode"
  },
  "geometry": {"coordinates":[-2.14505,51.377654],"type":"Point"}
}
