{
  "type": "Feature",
  "properties": {
    "date:inception_lower": "2002-07-01",
    "date:inception_upper": "2002-07-01",
    "iso:country": "GB",
    "wof:name": "SN12 8BZ",
    "wof:placetype": "postalcode"
  },
  "geometry": {"coordinates":[-2.14505,51.377654],"type":"Point"}
}
