{
  "type": "Feature",
  "properties": {
    "iso:country":"GB",
    "wof:name":"CM9 6QP",
    "wof:placetype":"postalcode"
},
  "geometry": {"coordinates":[0.62194634474123,51.75784205488418],"type":"Point"}
}