{
  "type": "Feature",
  "properties": {
    "iso:country": "GB",
    "wof:name": "CM9 6QP",
    "wof:placetype": "postalcode"
  },
  "geometry": {"coordinates":[0.621946,51.757842],"type":"Point"}
}
