{
  "type": "Feature",
  "properties": {
    "iso:country":"GB",
    "wof:name":"DN1 2AY",
    "wof:placetype":"postalcode"
},
  "geometry": {"coordinates":[-1.12817720910681,53.51815332210897],"type":"Point"}
}