{
  "type": "Feature",
  "properties": {
    "date:inception_lower": "1997-06-01",
    "date:inception_upper": "1997-06-01",
    "iso:country": "GB",
    "wof:name": "S20 1EF",
    "wof:placetype": "postalcode"
  },
  "geometry": {"coordinates":[-1.336041,53.348812],"type":"Point"}
}
