{
  "type": "Feature",
  "properties": {
    "iso:country": "GB",
    "wof:name": "S20 1EF",
    "wof:placetype": "postalcode"
  },
  "geometry": {"coordinates":[-1.336056,53.348793],"type":"Point"}
}
