{
  "type": "Feature",
  "properties": {
    "iso:country":"GB",
    "wof:name":"S20 1EF",
    "wof:placetype":"postalcode"
},
  "geometry": {"coordinates":[-1.33605632171832,53.34879296087909],"type":"Point"}
}