{
  "type": "Feature",
  "properties": {
    "iso:country":"GB",
    "wof:name":"PO14 3NJ",
    "wof:placetype":"postalcode"
},
  "geometry": {"coordinates":[-1.22915683426309,50.81947049393735],"type":"Point"}
}