{
  "type": "Feature",
  "properties": {
    "iso:country":"GB",
    "wof:name":"B74 2NA",
    "wof:placetype":"postalcode"
},
  "geometry": {"coordinates":[-1.82237302847319,52.57042952365732],"type":"Point"}
}