{
  "type": "Feature",
  "properties": {
    "date:inception_lower":"1980-01-01",
    "date:inception_upper":"1980-01-31",
    "iso:country":"GB",
    "wof:name":"B74 2NA",
    "wof:placetype":"postalcode"
},
  "geometry": {"coordinates":[-1.822373,52.57043],"type":"Point"}
}