{
  "type": "Feature",
  "properties": {
    "iso:country":"GB",
    "wof:name":"NE21 6AS",
    "wof:placetype":"postalcode"
},
  "geometry": {"coordinates":[-1.72802346451705,54.95255876883278],"type":"Point"}
}