{
  "type": "Feature",
  "properties": {
    "date:inception_lower": "1980-01-01",
    "date:inception_upper": "1980-01-01",
    "iso:country": "GB",
    "wof:name": "PE13 3HJ",
    "wof:placetype": "postalcode"
  },
  "geometry": {"coordinates":[0.172092,52.678372],"type":"Point"}
}
