{
  "type": "Feature",
  "properties": {
    "iso:country":"GB",
    "wof:name":"PE13 3HJ",
    "wof:placetype":"postalcode"
},
  "geometry": {"coordinates":[0.17209236688018,52.67837216470491],"type":"Point"}
}