{
  "type": "Feature",
  "properties": {
    "iso:country":"GB",
    "wof:name":"BA2 7LR",
    "wof:placetype":"postalcode"
},
  "geometry": {"coordinates":[-2.32966559052488,51.30821363873726],"type":"Point"}
}