{
  "type": "Feature",
  "properties": {
    "iso:country": "GB",
    "wof:name": "BA2 7LR",
    "wof:placetype": "postalcode"
  },
  "geometry": {"coordinates":[-2.329663,51.30821],"type":"Point"}
}
