{
  "type": "Feature",
  "properties": {
    "iso:country":"GB",
    "wof:name":"B19 1RH",
    "wof:placetype":"postalcode"
},
  "geometry": {"coordinates":[-1.90631615207034,52.50533993446177],"type":"Point"}
}