{
  "type": "Feature",
  "properties": {
    "iso:country":"GB",
    "wof:name":"EX14 9AW",
    "wof:placetype":"postalcode"
},
  "geometry": {"coordinates":[-3.08020861015341,50.88926923223182],"type":"Point"}
}