{
  "type": "Feature",
  "properties": {
    "iso:country": "GB",
    "wof:name": "EX14 9AW",
    "wof:placetype": "postalcode"
  },
  "geometry": {"coordinates":[-3.080209,50.889269],"type":"Point"}
}
