{
  "type": "Feature",
  "properties": {
    "date:inception_lower":"1980-01-01",
    "date:inception_upper":"1980-01-31",
    "iso:country":"GB",
    "wof:name":"EX14 9AW",
    "wof:placetype":"postalcode"
},
  "geometry": {"coordinates":[-3.080209,50.889269],"type":"Point"}
}