{
  "type": "Feature",
  "properties": {
    "iso:country":"GB",
    "wof:name":"BN1 5NE",
    "wof:placetype":"postalcode"
},
  "geometry": {"coordinates":[-0.15725829151617,50.84443741645437],"type":"Point"}
}