{
  "type": "Feature",
  "properties": {
    "iso:country":"GB",
    "wof:name":"EH26 0QD",
    "wof:placetype":"postalcode"
},
  "geometry": {"coordinates":[-3.19535650410938,55.84223139811692],"type":"Point"}
}