{
  "type": "Feature",
  "properties": {
    "iso:country": "GB",
    "wof:name": "EH26 0QD",
    "wof:placetype": "postalcode"
  },
  "geometry": {"coordinates":[-3.195356,55.842231],"type":"Point"}
}
