{
  "type": "Feature",
  "properties": {
    "iso:country": "GB",
    "wof:name": "NR16 2AS",
    "wof:placetype": "postalcode"
  },
  "geometry": {"coordinates":[1.075378,52.472439],"type":"Point"}
}
