{
  "type": "Feature",
  "properties": {
    "iso:country":"GB",
    "wof:name":"N2 9NL",
    "wof:placetype":"postalcode"
},
  "geometry": {"coordinates":[-0.15544338296767,51.59170964813533],"type":"Point"}
}