{
  "type": "Feature",
  "properties": {
    "iso:country":"GB",
    "wof:name":"BH14 9DE",
    "wof:placetype":"postalcode"
},
  "geometry": {"coordinates":[-1.93494359400235,50.72876184781499],"type":"Point"}
}