{
  "type": "Feature",
  "properties": {
    "iso:country": "GB",
    "wof:name": "HP16 0LT",
    "wof:placetype": "postalcode"
  },
  "geometry": {"coordinates":[-0.740758,51.69583],"type":"Point"}
}
