{
  "type": "Feature",
  "properties": {
    "iso:country":"GB",
    "wof:name":"HP16 0LT",
    "wof:placetype":"postalcode"
},
  "geometry": {"coordinates":[-0.74075763114757,51.69583037580242],"type":"Point"}
}