{
  "type": "Feature",
  "properties": {
    "date:inception_lower":"1988-03-01",
    "date:inception_upper":"1988-03-31",
    "iso:country":"GB",
    "wof:name":"HP16 0LT",
    "wof:placetype":"postalcode"
},
  "geometry": {"coordinates":[-0.740758,51.69583],"type":"Point"}
}