{
  "type": "Feature",
  "properties": {
    "iso:country": "GB",
    "wof:name": "SK12 1LJ",
    "wof:placetype": "postalcode"
  },
  "geometry": {"coordinates":[-2.114894,53.360704],"type":"Point"}
}
