{
  "type": "Feature",
  "properties": {
    "iso:country":"GB",
    "wof:name":"SK12 1LJ",
    "wof:placetype":"postalcode"
},
  "geometry": {"coordinates":[-2.11489394170913,53.36070392129614],"type":"Point"}
}