{
  "type": "Feature",
  "properties": {
    "date:inception_lower":"1990-02-01",
    "date:inception_upper":"1990-02-28",
    "iso:country":"GB",
    "wof:name":"SK12 1LJ",
    "wof:placetype":"postalcode"
},
  "geometry": {"coordinates":[-2.114894,53.360704],"type":"Point"}
}