{
  "type": "Feature",
  "properties": {
    "iso:country": "GB",
    "wof:name": "PH2 6BJ",
    "wof:placetype": "postalcode"
  },
  "geometry": {"coordinates":[-3.454873,56.462449],"type":"Point"}
}
