{
  "type": "Feature",
  "properties": {
    "iso:country":"GB",
    "wof:name":"PH2 6BJ",
    "wof:placetype":"postalcode"
},
  "geometry": {"coordinates":[-3.45487265112147,56.462449174479],"type":"Point"}
}