{
  "type": "Feature",
  "properties": {
    "iso:country":"GB",
    "wof:name":"NP13 1NS",
    "wof:placetype":"postalcode"
},
  "geometry": {"coordinates":[-3.13160542476679,51.74809678579621],"type":"Point"}
}