{
  "type": "Feature",
  "properties": {
    "iso:country":"GB",
    "wof:name":"L23 8TH",
    "wof:placetype":"postalcode"
},
  "geometry": {"coordinates":[-3.04030123469923,53.48847799710826],"type":"Point"}
}