{
  "type": "Feature",
  "properties": {
    "iso:country":"GB",
    "wof:name":"SA2 9AH",
    "wof:placetype":"postalcode"
},
  "geometry": {"coordinates":[-3.98840887662731,51.61676082214368],"type":"Point"}
}