{
  "type": "Feature",
  "properties": {
    "iso:country":"GB",
    "wof:name":"DA17 5PS",
    "wof:placetype":"postalcode"
},
  "geometry": {"coordinates":[0.15006111635441,51.49075443349953],"type":"Point"}
}