{
  "type": "Feature",
  "properties": {
    "iso:country":"GB",
    "wof:name":"TN7 4DP",
    "wof:placetype":"postalcode"
},
  "geometry": {"coordinates":[0.08995732031984,51.09237737165378],"type":"Point"}
}