{
  "type": "Feature",
  "properties": {
    "iso:country":"GB",
    "wof:name":"DH9 6FA",
    "wof:placetype":"postalcode"
},
  "geometry": {"coordinates":[-1.66869109316935,54.85176459023253],"type":"Point"}
}