{
  "type": "Feature",
  "properties": {
    "date:inception_lower":"2015-12-01",
    "date:inception_upper":"2015-12-31",
    "iso:country":"GB",
    "wof:name":"DH9 6FA",
    "wof:placetype":"postalcode"
},
  "geometry": {"coordinates":[-1.668475,54.851539],"type":"Point"}
}