{
  "type": "Feature",
  "properties": {
    "iso:country":"GB",
    "wof:name":"WF1 1RX",
    "wof:placetype":"postalcode"
},
  "geometry": {"coordinates":[-1.49487087514311,53.67845017372086],"type":"Point"}
}