{
  "type": "Feature",
  "properties": {
    "date:inception_lower": "2014-09-01",
    "date:inception_upper": "2014-09-01",
    "iso:country": "GB",
    "wof:name": "WF1 1RX",
    "wof:placetype": "postalcode"
  },
  "geometry": {"coordinates":[-1.494871,53.67845],"type":"Point"}
}
