{
  "type": "Feature",
  "properties": {
    "iso:country": "GB",
    "wof:name": "WF1 1RX",
    "wof:placetype": "postalcode"
  },
  "geometry": {"coordinates":[-1.494871,53.67845],"type":"Point"}
}
