{
  "type": "Feature",
  "properties": {
    "iso:country":"GB",
    "wof:name":"DE7 8QH",
    "wof:placetype":"postalcode"
},
  "geometry": {"coordinates":[-1.31050588823236,52.99111613384822],"type":"Point"}
}