{
  "type": "Feature",
  "properties": {
    "date:inception_lower":"1980-01-01",
    "date:inception_upper":"1980-01-31",
    "iso:country":"GB",
    "wof:name":"DE7 8QH",
    "wof:placetype":"postalcode"
},
  "geometry": {"coordinates":[-1.310506,52.991116],"type":"Point"}
}