{
  "type": "Feature",
  "properties": {
    "iso:country": "GB",
    "wof:name": "S42 7PZ",
    "wof:placetype": "postalcode"
  },
  "geometry": {"coordinates":[-1.478592,53.242147],"type":"Point"}
}
