{
  "type": "Feature",
  "properties": {
    "iso:country":"GB",
    "wof:name":"S42 7PZ",
    "wof:placetype":"postalcode"
},
  "geometry": {"coordinates":[-1.47859243015423,53.2421469995211],"type":"Point"}
}