{
  "type": "Feature",
  "properties": {
    "date:inception_lower": "2023-11-01",
    "date:inception_upper": "2023-11-01",
    "iso:country": "GB",
    "wof:name": "LU5 6RE",
    "wof:placetype": "postalcode"
  },
  "geometry": {"coordinates":[-0.535522,51.917659],"type":"Point"}
}
