{
  "type": "Feature",
  "properties": {
    "iso:country":"GB",
    "wof:name":"NW10 9LB",
    "wof:placetype":"postalcode"
},
  "geometry": {"coordinates":[-0.2500952150384,51.54273915552581],"type":"Point"}
}