{
  "type": "Feature",
  "properties": {
    "iso:country":"GB",
    "wof:name":"TF9 4HW",
    "wof:placetype":"postalcode"
},
  "geometry": {"coordinates":[-2.40243001739858,52.95791300988655],"type":"Point"}
}