{
  "type": "Feature",
  "properties": {
    "iso:country":"GB",
    "wof:name":"HA8 8PD",
    "wof:placetype":"postalcode"
},
  "geometry": {"coordinates":[-0.27216172027689,51.62145177518381],"type":"Point"}
}