{
  "type": "Feature",
  "properties": {
    "iso:country": "GB",
    "wof:name": "SN9 6LL",
    "wof:placetype": "postalcode"
  },
  "geometry": {"coordinates":[-1.84841,51.328368],"type":"Point"}
}
