{
  "type": "Feature",
  "properties": {
    "iso:country": "GB",
    "wof:name": "SN9 6LL",
    "wof:placetype": "postalcode"
  },
  "geometry": {"coordinates":[-1.847662,51.328799],"type":"Point"}
}
