{
  "type": "Feature",
  "properties": {
    "iso:country":"GB",
    "wof:name":"B73 6BB",
    "wof:placetype":"postalcode"
},
  "geometry": {"coordinates":[-1.8293253214317,52.56585491749765],"type":"Point"}
}