{
  "type": "Feature",
  "properties": {
    "iso:country": "GB",
    "wof:name": "PE20 1RJ",
    "wof:placetype": "postalcode"
  },
  "geometry": {"coordinates":[-0.070651,52.944376],"type":"Point"}
}
