{
  "type": "Feature",
  "properties": {
    "date:inception_lower":"2003-02-01",
    "date:inception_upper":"2003-02-28",
    "iso:country":"GB",
    "wof:name":"RG40 2LD",
    "wof:placetype":"postalcode"
},
  "geometry": {"coordinates":[-0.835526,51.409538],"type":"Point"}
}