{
  "type": "Feature",
  "properties": {
    "iso:country":"GB",
    "wof:name":"RG40 2LD",
    "wof:placetype":"postalcode"
},
  "geometry": {"coordinates":[-0.83552584213819,51.40953773601547],"type":"Point"}
}