{
  "type": "Feature",
  "properties": {
    "iso:country": "GB",
    "wof:name": "RG40 2LD",
    "wof:placetype": "postalcode"
  },
  "geometry": {"coordinates":[-0.835526,51.409538],"type":"Point"}
}
