{
  "type": "Feature",
  "properties": {
    "date:inception_lower": "2024-02-01",
    "date:inception_upper": "2024-02-01",
    "iso:country": "GB",
    "wof:name": "NR13 6GE",
    "wof:placetype": "postalcode"
  },
  "geometry": {"coordinates":[1.372044,52.661061],"type":"Point"}
}
