{
  "type": "Feature",
  "properties": {
    "iso:country":"GB",
    "wof:name":"NP20 2AH",
    "wof:placetype":"postalcode"
},
  "geometry": {"coordinates":[-2.98617056432125,51.58097834874351],"type":"Point"}
}