{
  "type": "Feature",
  "properties": {
    "iso:country": "GB",
    "wof:name": "NN2 8EJ",
    "wof:placetype": "postalcode"
  },
  "geometry": {"coordinates":[-0.917046,52.271975],"type":"Point"}
}
