{
  "type": "Feature",
  "properties": {
    "iso:country": "GB",
    "wof:name": "E17 6NS",
    "wof:placetype": "postalcode"
  },
  "geometry": {"coordinates":[-0.04053,51.585567],"type":"Point"}
}
