{
  "type": "Feature",
  "properties": {
    "iso:country":"GB",
    "wof:name":"E17 6NS",
    "wof:placetype":"postalcode"
},
  "geometry": {"coordinates":[-0.04052971546118,51.58556685779902],"type":"Point"}
}