{
  "type": "Feature",
  "properties": {
    "date:inception_lower": "1999-06-01",
    "date:inception_upper": "1999-06-01",
    "iso:country": "GB",
    "wof:name": "CF10 1EP",
    "wof:placetype": "postalcode"
  },
  "geometry": {"coordinates":[-3.178621,51.476661],"type":"Point"}
}
