{
  "type": "Feature",
  "properties": {
    "iso:country":"GB",
    "wof:name":"PL24 2HL",
    "wof:placetype":"postalcode"
},
  "geometry": {"coordinates":[-4.72855404564423,50.34830810817711],"type":"Point"}
}