{
  "type": "Feature",
  "properties": {
    "date:inception_lower":"1980-01-01",
    "date:inception_upper":"1980-01-31",
    "iso:country":"GB",
    "wof:name":"PL24 2HL",
    "wof:placetype":"postalcode"
},
  "geometry": {"coordinates":[-4.728554,50.348308],"type":"Point"}
}