{
  "type": "Feature",
  "properties": {
    "date:inception_lower": "1980-01-01",
    "date:inception_upper": "1980-01-01",
    "iso:country": "GB",
    "wof:name": "RG9 3AZ",
    "wof:placetype": "postalcode"
  },
  "geometry": {"coordinates":[-0.872977,51.559888],"type":"Point"}
}
