{
  "type": "Feature",
  "properties": {
    "iso:country":"GB",
    "wof:name":"RG9 3AZ",
    "wof:placetype":"postalcode"
},
  "geometry": {"coordinates":[-0.8729768766765,51.55988826094217],"type":"Point"}
}