{
  "type": "Feature",
  "properties": {
    "iso:country":"GB",
    "wof:name":"ML5 2QZ",
    "wof:placetype":"postalcode"
},
  "geometry": {"coordinates":[-4.04958829576748,55.89649590629863],"type":"Point"}
}