{
  "type": "Feature",
  "properties": {
    "iso:country":"GB",
    "wof:name":"SN2 7HT",
    "wof:placetype":"postalcode"
},
  "geometry": {"coordinates":[-1.76985477710164,51.58327989013267],"type":"Point"}
}