{
  "type": "Feature",
  "properties": {
    "date:inception_lower": "2000-06-01",
    "date:inception_upper": "2000-06-01",
    "iso:country": "GB",
    "wof:name": "SN2 7HT",
    "wof:placetype": "postalcode"
  },
  "geometry": {"coordinates":[-1.769855,51.58328],"type":"Point"}
}
