{
  "type": "Feature",
  "properties": {
    "iso:country":"GB",
    "wof:name":"DT1 2QZ",
    "wof:placetype":"postalcode"
},
  "geometry": {"coordinates":[-2.44865534567135,50.7031137409079],"type":"Point"}
}