{
  "type": "Feature",
  "properties": {
    "iso:country":"GB",
    "wof:name":"DA15 9HT",
    "wof:placetype":"postalcode"
},
  "geometry": {"coordinates":[0.10721276045429,51.44842950423787],"type":"Point"}
}