{
  "type": "Feature",
  "properties": {
    "iso:country":"GB",
    "wof:name":"SP10 3QT",
    "wof:placetype":"postalcode"
},
  "geometry": {"coordinates":[-1.48336976324045,51.20656080926991],"type":"Point"}
}