{
  "type": "Feature",
  "properties": {
    "iso:country":"GB",
    "wof:name":"E16 1TN",
    "wof:placetype":"postalcode"
},
  "geometry": {"coordinates":[0.0229566282892,51.50526428850764],"type":"Point"}
}