{
  "type": "Feature",
  "properties": {
    "iso:country":"GB",
    "wof:name":"CT14 7DW",
    "wof:placetype":"postalcode"
},
  "geometry": {"coordinates":[1.39822808797833,51.21056625741227],"type":"Point"}
}