{
  "type": "Feature",
  "properties": {
    "iso:country": "GB",
    "wof:name": "CT3 1FD",
    "wof:placetype": "postalcode"
  },
  "geometry": {"coordinates":[1.223404,51.283543],"type":"Point"}
}
