{
  "type": "Feature",
  "properties": {
    "date:inception_lower": "2008-08-01",
    "date:inception_upper": "2008-08-01",
    "iso:country": "GB",
    "wof:name": "CT3 1FD",
    "wof:placetype": "postalcode"
  },
  "geometry": {"coordinates":[1.223404,51.283543],"type":"Point"}
}
