{
  "type": "Feature",
  "properties": {
    "iso:country":"GB",
    "wof:name":"CT3 1FD",
    "wof:placetype":"postalcode"
},
  "geometry": {"coordinates":[1.22415065234824,51.28457760632666],"type":"Point"}
}