{
  "type": "Feature",
  "properties": {
    "iso:country":"GB",
    "wof:name":"B44 9TR",
    "wof:placetype":"postalcode"
},
  "geometry": {"coordinates":[-1.8922537250391,52.54466777043498],"type":"Point"}
}