{
  "type": "Feature",
  "properties": {
    "iso:country":"GB",
    "wof:name":"B6 4NH",
    "wof:placetype":"postalcode"
},
  "geometry": {"coordinates":[-1.89230400604496,52.49385689081874],"type":"Point"}
}