{
  "type": "Feature",
  "properties": {
    "iso:country":"GB",
    "wof:name":"RH12 2PG",
    "wof:placetype":"postalcode"
},
  "geometry": {"coordinates":[-0.33075590576265,51.06495087025124],"type":"Point"}
}