{
  "type": "Feature",
  "properties": {
    "iso:country": "GB",
    "wof:name": "RH12 2PG",
    "wof:placetype": "postalcode"
  },
  "geometry": {"coordinates":[-0.330672,51.064964],"type":"Point"}
}
