{
  "type": "Feature",
  "properties": {
    "iso:country":"GB",
    "wof:name":"DY3 2ND",
    "wof:placetype":"postalcode"
},
  "geometry": {"coordinates":[-2.13033458968941,52.51857386050789],"type":"Point"}
}