{
  "type": "Feature",
  "properties": {
    "iso:country":"GB",
    "wof:name":"LE3 6AX",
    "wof:placetype":"postalcode"
},
  "geometry": {"coordinates":[-1.15667522154401,52.63438405216371],"type":"Point"}
}