{
  "type": "Feature",
  "properties": {
    "iso:country":"GB",
    "wof:name":"BR6 7SN",
    "wof:placetype":"postalcode"
},
  "geometry": {"coordinates":[0.11855243837945,51.35071425613137],"type":"Point"}
}