{
  "type": "Feature",
  "properties": {
    "iso:country":"GB",
    "wof:name":"GU15 2HN",
    "wof:placetype":"postalcode"
},
  "geometry": {"coordinates":[-0.73957146350538,51.33706675559231],"type":"Point"}
}