{
  "type": "Feature",
  "properties": {
    "iso:country":"GB",
    "wof:name":"TQ6 0FG",
    "wof:placetype":"postalcode"
},
  "geometry": {"coordinates":[-3.5858352416934,50.35481078201435],"type":"Point"}
}