{
  "type": "Feature",
  "properties": {
    "iso:country": "GB",
    "wof:name": "LE14 3QH",
    "wof:placetype": "postalcode"
  },
  "geometry": {"coordinates":[-0.975948,52.81632],"type":"Point"}
}
