{
  "type": "Feature",
  "properties": {
    "date:inception_lower":"1980-01-01",
    "date:inception_upper":"1980-01-31",
    "iso:country":"GB",
    "wof:name":"LE14 3QH",
    "wof:placetype":"postalcode"
},
  "geometry": {"coordinates":[-0.975948,52.81632],"type":"Point"}
}