{
  "type": "Feature",
  "properties": {
    "iso:country":"GB",
    "wof:name":"SY18 6DQ",
    "wof:placetype":"postalcode"
},
  "geometry": {"coordinates":[-3.5353046309782,52.44629611868594],"type":"Point"}
}