{
  "type": "Feature",
  "properties": {
    "iso:country":"GB",
    "wof:name":"OX11 0QB",
    "wof:placetype":"postalcode"
},
  "geometry": {"coordinates":[-1.3109547901488,51.58146609410147],"type":"Point"}
}