{
  "type": "Feature",
  "properties": {
    "iso:country": "GB",
    "wof:name": "OX11 0QB",
    "wof:placetype": "postalcode"
  },
  "geometry": {"coordinates":[-1.310955,51.581466],"type":"Point"}
}
