{
  "type": "Feature",
  "properties": {
    "date:inception_lower": "2015-11-01",
    "date:inception_upper": "2015-11-01",
    "iso:country": "GB",
    "wof:name": "B9 5DJ",
    "wof:placetype": "postalcode"
  },
  "geometry": {"coordinates":[-1.861746,52.473553],"type":"Point"}
}
