{
  "type": "Feature",
  "properties": {
    "iso:country":"GB",
    "wof:name":"SS1 1JF",
    "wof:placetype":"postalcode"
},
  "geometry": {"coordinates":[0.71396788282862,51.53667827365321],"type":"Point"}
}