{
  "type": "Feature",
  "properties": {
    "iso:country":"GB",
    "wof:name":"NE9 6DU",
    "wof:placetype":"postalcode"
},
  "geometry": {"coordinates":[-1.60634682441039,54.93632024109684],"type":"Point"}
}