{
  "type": "Feature",
  "properties": {
    "iso:country": "GB",
    "wof:name": "RM16 4TB",
    "wof:placetype": "postalcode"
  },
  "geometry": {"coordinates":[0.369541,51.48897],"type":"Point"}
}
