{
  "type": "Feature",
  "properties": {
    "date:inception_lower":"1980-01-01",
    "date:inception_upper":"1980-01-31",
    "iso:country":"GB",
    "wof:name":"MK18 4QD",
    "wof:placetype":"postalcode"
},
  "geometry": {"coordinates":[-1.048873,51.989963],"type":"Point"}
}