{
  "type": "Feature",
  "properties": {
    "iso:country":"GB",
    "wof:name":"MK18 4QD",
    "wof:placetype":"postalcode"
},
  "geometry": {"coordinates":[-1.0488732516245,51.9899630805506],"type":"Point"}
}