{
  "type": "Feature",
  "properties": {
    "date:inception_lower":"1996-06-01",
    "date:inception_upper":"1996-06-30",
    "iso:country":"GB",
    "wof:name":"IP10 0NE",
    "wof:placetype":"postalcode"
},
  "geometry": {"coordinates":[1.260119,52.012061],"type":"Point"}
}