{
  "type": "Feature",
  "properties": {
    "iso:country":"GB",
    "wof:name":"IP10 0NE",
    "wof:placetype":"postalcode"
},
  "geometry": {"coordinates":[1.26011857688191,52.01206084530983],"type":"Point"}
}