{
  "type": "Feature",
  "properties": {
    "iso:country":"GB",
    "wof:name":"BH1 2HZ",
    "wof:placetype":"postalcode"
},
  "geometry": {"coordinates":[-1.87564039219562,50.7213488226425],"type":"Point"}
}