{
  "type": "Feature",
  "properties": {
    "iso:country": "GB",
    "wof:name": "DE11 9QD",
    "wof:placetype": "postalcode"
  },
  "geometry": {"coordinates":[-1.561809,52.76572],"type":"Point"}
}
