{
  "type": "Feature",
  "properties": {
    "iso:country":"GB",
    "wof:name":"NW2 6QY",
    "wof:placetype":"postalcode"
},
  "geometry": {"coordinates":[-0.2308807510757,51.56146981407876],"type":"Point"}
}