{
  "type": "Feature",
  "properties": {
    "iso:country":"GB",
    "wof:name":"BB10 3LL",
    "wof:placetype":"postalcode"
},
  "geometry": {"coordinates":[-2.18275005226848,53.78016663117353],"type":"Point"}
}