{
  "type": "Feature",
  "properties": {
    "iso:country": "GB",
    "wof:name": "BB10 3LL",
    "wof:placetype": "postalcode"
  },
  "geometry": {"coordinates":[-2.18275,53.780167],"type":"Point"}
}
