{
  "type": "Feature",
  "properties": {
    "iso:country":"GB",
    "wof:name":"PE6 7YG",
    "wof:placetype":"postalcode"
},
  "geometry": {"coordinates":[-0.19779799621795,52.60743256189402],"type":"Point"}
}