{
  "type": "Feature",
  "properties": {
    "date:inception_lower":"1980-01-01",
    "date:inception_upper":"1980-01-31",
    "iso:country":"GB",
    "wof:name":"PE6 7YG",
    "wof:placetype":"postalcode"
},
  "geometry": {"coordinates":[-0.197798,52.607433],"type":"Point"}
}