{
  "type": "Feature",
  "properties": {
    "iso:country": "GB",
    "wof:name": "TR14 8JF",
    "wof:placetype": "postalcode"
  },
  "geometry": {"coordinates":[-5.295211,50.211873],"type":"Point"}
}
