{
  "type": "Feature",
  "properties": {
    "iso:country":"GB",
    "wof:name":"BB8 7PU",
    "wof:placetype":"postalcode"
},
  "geometry": {"coordinates":[-2.16872625263534,53.87787691771317],"type":"Point"}
}