{
  "type": "Feature",
  "properties": {
    "iso:country": "GB",
    "wof:name": "KT20 5NT",
    "wof:placetype": "postalcode"
  },
  "geometry": {"coordinates":[-0.220222,51.306694],"type":"Point"}
}
