{
  "type": "Feature",
  "properties": {
    "iso:country":"GB",
    "wof:name":"KT20 5NT",
    "wof:placetype":"postalcode"
},
  "geometry": {"coordinates":[-0.2202225014458,51.30669420182996],"type":"Point"}
}