{
  "type": "Feature",
  "properties": {
    "iso:country":"GB",
    "wof:name":"BH21 3SR",
    "wof:placetype":"postalcode"
},
  "geometry": {"coordinates":[-2.0163661737841,50.76093631600089],"type":"Point"}
}