{
  "type": "Feature",
  "properties": {
    "iso:country":"GB",
    "wof:name":"PO9 4AN",
    "wof:placetype":"postalcode"
},
  "geometry": {"coordinates":[-1.00563059034616,50.86800462023963],"type":"Point"}
}