{
  "type": "Feature",
  "properties": {
    "date:inception_lower": "1980-01-01",
    "date:inception_upper": "1980-01-01",
    "iso:country": "GB",
    "wof:name": "B23 7LT",
    "wof:placetype": "postalcode"
  },
  "geometry": {"coordinates":[-1.858024,52.518732],"type":"Point"}
}
