{
  "type": "Feature",
  "properties": {
    "iso:country":"GB",
    "wof:name":"NE61 2YU",
    "wof:placetype":"postalcode"
},
  "geometry": {"coordinates":[-1.71103467559863,55.16371110836157],"type":"Point"}
}