{
  "type": "Feature",
  "properties": {
    "iso:country":"GB",
    "wof:name":"DT4 9BU",
    "wof:placetype":"postalcode"
},
  "geometry": {"coordinates":[-2.47032326114728,50.58720941998456],"type":"Point"}
}