{
  "type": "Feature",
  "properties": {
    "date:inception_lower": "2007-04-01",
    "date:inception_upper": "2007-04-01",
    "iso:country": "GB",
    "wof:name": "NG14 6RJ",
    "wof:placetype": "postalcode"
  },
  "geometry": {"coordinates":[-1.084272,53.045216],"type":"Point"}
}
