{
  "type": "Feature",
  "properties": {
    "iso:country":"GB",
    "wof:name":"LL65 2DP",
    "wof:placetype":"postalcode"
},
  "geometry": {"coordinates":[-4.62224237213005,53.30877438680445],"type":"Point"}
}