{
  "type": "Feature",
  "properties": {
    "date:inception_lower": "1980-01-01",
    "date:inception_upper": "1980-01-01",
    "iso:country": "GB",
    "wof:name": "LL65 2DP",
    "wof:placetype": "postalcode"
  },
  "geometry": {"coordinates":[-4.622264,53.308809],"type":"Point"}
}
