{
  "type": "Feature",
  "properties": {
    "iso:country":"GB",
    "wof:name":"SE26 6BL",
    "wof:placetype":"postalcode"
},
  "geometry": {"coordinates":[-0.06410081239394,51.42683390965384],"type":"Point"}
}