{
  "type": "Feature",
  "properties": {
    "iso:country":"GB",
    "wof:name":"EH10 4EZ",
    "wof:placetype":"postalcode"
},
  "geometry": {"coordinates":[-3.20388178972048,55.93611940378862],"type":"Point"}
}