{
  "type": "Feature",
  "properties": {
    "iso:country":"GB",
    "wof:name":"SE7 8AP",
    "wof:placetype":"postalcode"
},
  "geometry": {"coordinates":[0.03430998401588,51.48646191240542],"type":"Point"}
}