{
  "type": "Feature",
  "properties": {
    "date:inception_lower": "2020-05-01",
    "date:inception_upper": "2020-05-01",
    "iso:country": "GB",
    "wof:name": "BA12 2DE",
    "wof:placetype": "postalcode"
  },
  "geometry": {"coordinates":[-2.178365,51.204312],"type":"Point"}
}
