{
  "type": "Feature",
  "properties": {
    "iso:country": "GB",
    "wof:name": "CV9 3AQ",
    "wof:placetype": "postalcode"
  },
  "geometry": {"coordinates":[-1.544009,52.581058],"type":"Point"}
}
