{
  "type": "Feature",
  "properties": {
    "iso:country": "GB",
    "wof:name": "LU5 6FE",
    "wof:placetype": "postalcode"
  },
  "geometry": {"coordinates":[-0.535658,51.941506],"type":"Point"}
}
