{
  "type": "Feature",
  "properties": {
    "date:inception_lower":"2005-06-01",
    "date:inception_upper":"2005-06-30",
    "iso:country":"GB",
    "wof:name":"CW10 0GW",
    "wof:placetype":"postalcode"
},
  "geometry": {"coordinates":[-2.429738,53.195328],"type":"Point"}
}