{
  "type": "Feature",
  "properties": {
    "iso:country": "GB",
    "wof:name": "CW10 0GW",
    "wof:placetype": "postalcode"
  },
  "geometry": {"coordinates":[-2.429738,53.195328],"type":"Point"}
}
