{
  "type": "Feature",
  "properties": {
    "date:inception_lower":"2000-12-01",
    "date:inception_upper":"2000-12-31",
    "iso:country":"GB",
    "wof:name":"DL10 4UF",
    "wof:placetype":"postalcode"
},
  "geometry": {"coordinates":[-1.743305,54.40445],"type":"Point"}
}