{
  "type": "Feature",
  "properties": {
    "date:inception_lower":"2006-01-01",
    "date:inception_upper":"2006-01-31",
    "iso:country":"GB",
    "wof:name":"EH49 7NZ",
    "wof:placetype":"postalcode"
},
  "geometry": {"coordinates":[-3.585204,55.995081],"type":"Point"}
}