{
  "type": "Feature",
  "properties": {
    "iso:country":"GB",
    "wof:name":"AB41 9QW",
    "wof:placetype":"postalcode"
},
  "geometry": {"coordinates":[-2.06971332801801,57.3602629753618],"type":"Point"}
}