{
  "type": "Feature",
  "properties": {
    "date:inception_lower": "2000-06-01",
    "date:inception_upper": "2000-06-01",
    "iso:country": "GB",
    "wof:name": "AB41 9QW",
    "wof:placetype": "postalcode"
  },
  "geometry": {"coordinates":[-2.069713,57.360263],"type":"Point"}
}
