{
  "type": "Feature",
  "properties": {
    "iso:country": "GB",
    "wof:name": "AB41 9QW",
    "wof:placetype": "postalcode"
  },
  "geometry": {"coordinates":[-2.069713,57.360263],"type":"Point"}
}
