{
  "type": "Feature",
  "properties": {
    "iso:country":"GB",
    "wof:name":"B74 4AG",
    "wof:placetype":"postalcode"
},
  "geometry": {"coordinates":[-1.83941228456343,52.58717487619894],"type":"Point"}
}