{
  "type": "Feature",
  "properties": {
    "iso:country": "GB",
    "wof:name": "NN11 7AL",
    "wof:placetype": "postalcode"
  },
  "geometry": {"coordinates":[-1.210842,52.287088],"type":"Point"}
}
