{
  "type": "Feature",
  "properties": {
    "date:inception_lower": "2013-10-01",
    "date:inception_upper": "2013-10-01",
    "iso:country": "GB",
    "wof:name": "SE12 0PQ",
    "wof:placetype": "postalcode"
  },
  "geometry": {"coordinates":[0.013875,51.445098],"type":"Point"}
}
