{
  "type": "Feature",
  "properties": {
    "iso:country":"GB",
    "wof:name":"SE12 0PQ",
    "wof:placetype":"postalcode"
},
  "geometry": {"coordinates":[0.01386440785363,51.44511544847966],"type":"Point"}
}