{
  "type": "Feature",
  "properties": {
    "date:inception_lower": "1980-01-01",
    "date:inception_upper": "1980-01-01",
    "iso:country": "GB",
    "wof:name": "BB8 0JY",
    "wof:placetype": "postalcode"
  },
  "geometry": {"coordinates":[-2.163606,53.855384],"type":"Point"}
}
