{
  "type": "Feature",
  "properties": {
    "iso:country":"GB",
    "wof:name":"BB8 0JY",
    "wof:placetype":"postalcode"
},
  "geometry": {"coordinates":[-2.16355791241775,53.85536948618595],"type":"Point"}
}