{
  "type": "Feature",
  "properties": {
    "iso:country":"GB",
    "wof:name":"BS41 9BJ",
    "wof:placetype":"postalcode"
},
  "geometry": {"coordinates":[-2.67543160720482,51.42500739739594],"type":"Point"}
}