{
  "type": "Feature",
  "properties": {
    "date:inception_lower":"1980-01-01",
    "date:inception_upper":"1980-01-31",
    "iso:country":"GB",
    "wof:name":"LA8 9DR",
    "wof:placetype":"postalcode"
},
  "geometry": {"coordinates":[-2.707143,54.360204],"type":"Point"}
}