{
  "type": "Feature",
  "properties": {
    "iso:country":"GB",
    "wof:name":"LA8 9DR",
    "wof:placetype":"postalcode"
},
  "geometry": {"coordinates":[-2.70714281854385,54.36020395921982],"type":"Point"}
}