{
  "type": "Feature",
  "properties": {
    "iso:country": "GB",
    "wof:name": "LA8 9DR",
    "wof:placetype": "postalcode"
  },
  "geometry": {"coordinates":[-2.707143,54.360204],"type":"Point"}
}
