{
  "type": "Feature",
  "properties": {
    "iso:country":"GB",
    "wof:name":"GL1 3NF",
    "wof:placetype":"postalcode"
},
  "geometry": {"coordinates":[-2.23831985835004,51.86678896865045],"type":"Point"}
}