{
  "type": "Feature",
  "properties": {
    "date:inception_lower": "1980-01-01",
    "date:inception_upper": "1980-01-01",
    "iso:country": "GB",
    "wof:name": "DN14 5JU",
    "wof:placetype": "postalcode"
  },
  "geometry": {"coordinates":[-0.856341,53.708141],"type":"Point"}
}
