{
  "type": "Feature",
  "properties": {
    "iso:country":"GB",
    "wof:name":"DN14 5JU",
    "wof:placetype":"postalcode"
},
  "geometry": {"coordinates":[-0.85634084059268,53.70814119251489],"type":"Point"}
}