{
  "type": "Feature",
  "properties": {
    "date:inception_lower": "1980-01-01",
    "date:inception_upper": "1980-01-01",
    "iso:country": "GB",
    "wof:name": "G84 0AH",
    "wof:placetype": "postalcode"
  },
  "geometry": {"coordinates":[-4.828095,56.078765],"type":"Point"}
}
