{
  "type": "Feature",
  "properties": {
    "iso:country":"GB",
    "wof:name":"KA6 7QN",
    "wof:placetype":"postalcode"
},
  "geometry": {"coordinates":[-4.39733076569083,55.32431349783824],"type":"Point"}
}