{
  "type": "Feature",
  "properties": {
    "iso:country": "GB",
    "wof:name": "KA6 7QN",
    "wof:placetype": "postalcode"
  },
  "geometry": {"coordinates":[-4.397196,55.324172],"type":"Point"}
}
