{
  "type": "Feature",
  "properties": {
    "date:inception_lower":"1990-07-01",
    "date:inception_upper":"1990-07-31",
    "iso:country":"GB",
    "wof:name":"LA16 7HN",
    "wof:placetype":"postalcode"
},
  "geometry": {"coordinates":[-3.206175,54.188192],"type":"Point"}
}