{
  "type": "Feature",
  "properties": {
    "iso:country": "GB",
    "wof:name": "PL4 6PE",
    "wof:placetype": "postalcode"
  },
  "geometry": {"coordinates":[-4.142219,50.38022],"type":"Point"}
}
