{
  "type": "Feature",
  "properties": {
    "iso:country":"GB",
    "wof:name":"OX7 6BB",
    "wof:placetype":"postalcode"
},
  "geometry": {"coordinates":[-1.59462878281011,51.8603634758598],"type":"Point"}
}