{
  "type": "Feature",
  "properties": {
    "date:inception_lower": "1992-01-01",
    "date:inception_upper": "1992-01-01",
    "iso:country": "GB",
    "wof:name": "SW10 0LW",
    "wof:placetype": "postalcode"
  },
  "geometry": {"coordinates":[-0.184659,51.483105],"type":"Point"}
}
