{
  "type": "Feature",
  "properties": {
    "iso:country": "GB",
    "wof:name": "IV17 0AA",
    "wof:placetype": "postalcode"
  },
  "geometry": {"coordinates":[-4.241365,57.697185],"type":"Point"}
}
