{
  "type": "Feature",
  "properties": {
    "iso:country":"GB",
    "wof:name":"S20 8LS",
    "wof:placetype":"postalcode"
},
  "geometry": {"coordinates":[-1.35176377285798,53.33033535599233],"type":"Point"}
}