{
  "type": "Feature",
  "properties": {
    "iso:country":"GB",
    "wof:name":"DY13 8PU",
    "wof:placetype":"postalcode"
},
  "geometry": {"coordinates":[-2.29405851049139,52.35454409803149],"type":"Point"}
}