{
  "type": "Feature",
  "properties": {
    "date:inception_lower": "1990-07-01",
    "date:inception_upper": "1990-07-01",
    "iso:country": "GB",
    "wof:name": "NG16 1QR",
    "wof:placetype": "postalcode"
  },
  "geometry": {"coordinates":[-1.228475,52.984661],"type":"Point"}
}
