{
  "type": "Feature",
  "properties": {
    "iso:country": "GB",
    "wof:name": "NG16 1QR",
    "wof:placetype": "postalcode"
  },
  "geometry": {"coordinates":[-1.228475,52.984661],"type":"Point"}
}
