{
  "type": "Feature",
  "properties": {
    "iso:country":"GB",
    "wof:name":"YO21 2EL",
    "wof:placetype":"postalcode"
},
  "geometry": {"coordinates":[-0.93618963131366,54.46348243765922],"type":"Point"}
}