{
  "type": "Feature",
  "properties": {
    "iso:country": "GB",
    "wof:name": "YO21 2EL",
    "wof:placetype": "postalcode"
  },
  "geometry": {"coordinates":[-0.93619,54.463482],"type":"Point"}
}
