{
  "type": "Feature",
  "properties": {
    "iso:country":"GB",
    "wof:name":"HP5 3JF",
    "wof:placetype":"postalcode"
},
  "geometry": {"coordinates":[-0.60646667639467,51.71664988508022],"type":"Point"}
}