{
  "type": "Feature",
  "properties": {
    "iso:country": "GB",
    "wof:name": "BL1 3ND",
    "wof:placetype": "postalcode"
  },
  "geometry": {"coordinates":[-2.445845,53.590922],"type":"Point"}
}
