{
  "type": "Feature",
  "properties": {
    "date:inception_lower": "1988-03-01",
    "date:inception_upper": "1988-03-01",
    "iso:country": "GB",
    "wof:name": "BL1 3ND",
    "wof:placetype": "postalcode"
  },
  "geometry": {"coordinates":[-2.445845,53.590922],"type":"Point"}
}
