{
  "type": "Feature",
  "properties": {
    "iso:country":"GB",
    "wof:name":"KA29 0EG",
    "wof:placetype":"postalcode"
},
  "geometry": {"coordinates":[-4.86074398394755,55.73694380305921],"type":"Point"}
}