{
  "type": "Feature",
  "properties": {
    "date:inception_lower":"1994-09-01",
    "date:inception_upper":"1994-09-30",
    "iso:country":"GB",
    "wof:name":"KA29 0EG",
    "wof:placetype":"postalcode"
},
  "geometry": {"coordinates":[-4.860744,55.736944],"type":"Point"}
}