{
  "type": "Feature",
  "properties": {
    "iso:country": "GB",
    "wof:name": "KA29 0EG",
    "wof:placetype": "postalcode"
  },
  "geometry": {"coordinates":[-4.860744,55.736944],"type":"Point"}
}
