{
  "type": "Feature",
  "properties": {
    "iso:country": "GB",
    "wof:name": "WA1 3AJ",
    "wof:placetype": "postalcode"
  },
  "geometry": {"coordinates":[-2.580099,53.393917],"type":"Point"}
}
