{
  "type": "Feature",
  "properties": {
    "date:inception_lower": "2009-03-01",
    "date:inception_upper": "2009-03-01",
    "iso:country": "GB",
    "wof:name": "L1 3ED",
    "wof:placetype": "postalcode"
  },
  "geometry": {"coordinates":[-2.985766,53.403726],"type":"Point"}
}
