{
  "type": "Feature",
  "properties": {
    "iso:country": "GB",
    "wof:name": "HP21 9NY",
    "wof:placetype": "postalcode"
  },
  "geometry": {"coordinates":[-0.823581,51.801125],"type":"Point"}
}
