{
  "type": "Feature",
  "properties": {
    "iso:country":"GB",
    "wof:name":"HP21 9NY",
    "wof:placetype":"postalcode"
},
  "geometry": {"coordinates":[-0.82358102638195,51.80112531420433],"type":"Point"}
}