{
  "type": "Feature",
  "properties": {
    "iso:country":"GB",
    "wof:name":"PR7 2JS",
    "wof:placetype":"postalcode"
},
  "geometry": {"coordinates":[-2.63885007834926,53.6432938723808],"type":"Point"}
}