{
  "type": "Feature",
  "properties": {
    "iso:country":"GB",
    "wof:name":"TS3 0NJ",
    "wof:placetype":"postalcode"
},
  "geometry": {"coordinates":[-1.1838175055807,54.55119955047398],"type":"Point"}
}