{
  "type": "Feature",
  "properties": {
    "date:inception_lower": "2003-10-01",
    "date:inception_upper": "2003-10-01",
    "iso:country": "GB",
    "wof:name": "FY5 4FW",
    "wof:placetype": "postalcode"
  },
  "geometry": {"coordinates":[-2.995933,53.878644],"type":"Point"}
}
