{
  "type": "Feature",
  "properties": {
    "date:inception_lower":"1994-12-01",
    "date:inception_upper":"1994-12-31",
    "iso:country":"GB",
    "wof:name":"HD1 3AP",
    "wof:placetype":"postalcode"
},
  "geometry": {"coordinates":[-1.775343,53.639621],"type":"Point"}
}