{
  "type": "Feature",
  "properties": {
    "iso:country":"GB",
    "wof:name":"S6 5HS",
    "wof:placetype":"postalcode"
},
  "geometry": {"coordinates":[-1.518259736109,53.39657008142689],"type":"Point"}
}