{
  "type": "Feature",
  "properties": {
    "iso:country": "GB",
    "wof:name": "DH4 5PS",
    "wof:placetype": "postalcode"
  },
  "geometry": {"coordinates":[-1.481422,54.841665],"type":"Point"}
}
