{
  "type": "Feature",
  "properties": {
    "iso:country":"GB",
    "wof:name":"DH4 5PS",
    "wof:placetype":"postalcode"
},
  "geometry": {"coordinates":[-1.48142215585872,54.84166490633318],"type":"Point"}
}