{
  "type": "Feature",
  "properties": {
    "iso:country":"GB",
    "wof:name":"GU21 5AY",
    "wof:placetype":"postalcode"
},
  "geometry": {"coordinates":[-0.53185885604946,51.33696775102732],"type":"Point"}
}