{
  "type": "Feature",
  "properties": {
    "iso:country": "GB",
    "wof:name": "EX13 5QX",
    "wof:placetype": "postalcode"
  },
  "geometry": {"coordinates":[-3.001902,50.775382],"type":"Point"}
}
