{
  "type": "Feature",
  "properties": {
    "iso:country":"GB",
    "wof:name":"YO14 0QG",
    "wof:placetype":"postalcode"
},
  "geometry": {"coordinates":[-0.3198211920218,54.18465823623541],"type":"Point"}
}