{
  "type": "Feature",
  "properties": {
    "iso:country": "GB",
    "wof:name": "YO14 0QG",
    "wof:placetype": "postalcode"
  },
  "geometry": {"coordinates":[-0.319821,54.184658],"type":"Point"}
}
