{
  "type": "Feature",
  "properties": {
    "iso:country": "GB",
    "wof:name": "NR12 0RX",
    "wof:placetype": "postalcode"
  },
  "geometry": {"coordinates":[1.520842,52.80578],"type":"Point"}
}
