{
  "type": "Feature",
  "properties": {
    "iso:country":"GB",
    "wof:name":"SO40 7GE",
    "wof:placetype":"postalcode"
},
  "geometry": {"coordinates":[-1.53566949959402,50.90878707983346],"type":"Point"}
}