{
  "type": "Feature",
  "properties": {
    "iso:country":"GB",
    "wof:name":"S20 3FS",
    "wof:placetype":"postalcode"
},
  "geometry": {"coordinates":[-1.33350949660994,53.3329314803682],"type":"Point"}
}