{
  "type": "Feature",
  "properties": {
    "iso:country":"GB",
    "wof:name":"DA6 7AB",
    "wof:placetype":"postalcode"
},
  "geometry": {"coordinates":[0.13976649353903,51.45024984476287],"type":"Point"}
}