{
  "type": "Feature",
  "properties": {
    "iso:country": "GB",
    "wof:name": "BH15 4QP",
    "wof:placetype": "postalcode"
  },
  "geometry": {"coordinates":[-2.017709,50.713302],"type":"Point"}
}
