{
  "type": "Feature",
  "properties": {
    "iso:country":"GB",
    "wof:name":"BH15 4QP",
    "wof:placetype":"postalcode"
},
  "geometry": {"coordinates":[-2.01770902321491,50.71330207736842],"type":"Point"}
}