{
  "type": "Feature",
  "properties": {
    "iso:country": "GB",
    "wof:name": "YO61 3GL",
    "wof:placetype": "postalcode"
  },
  "geometry": {"coordinates":[-1.203413,54.124257],"type":"Point"}
}
