{
  "type": "Feature",
  "properties": {
    "iso:country":"GB",
    "wof:name":"ST15 0DR",
    "wof:placetype":"postalcode"
},
  "geometry": {"coordinates":[-2.15828465106389,52.90074223955514],"type":"Point"}
}