{
  "type": "Feature",
  "properties": {
    "iso:country": "GB",
    "wof:name": "WF1 4ET",
    "wof:placetype": "postalcode"
  },
  "geometry": {"coordinates":[-1.482524,53.681633],"type":"Point"}
}
