{
  "type": "Feature",
  "properties": {
    "iso:country":"GB",
    "wof:name":"WF1 4ET",
    "wof:placetype":"postalcode"
},
  "geometry": {"coordinates":[-1.48252392260434,53.68163325943346],"type":"Point"}
}