{
  "type": "Feature",
  "properties": {
    "iso:country":"GB",
    "wof:name":"ST5 8DT",
    "wof:placetype":"postalcode"
},
  "geometry": {"coordinates":[-2.22789863331552,53.03268079553295],"type":"Point"}
}