{
  "type": "Feature",
  "properties": {
    "date:inception_lower": "1987-04-01",
    "date:inception_upper": "1987-04-01",
    "iso:country": "GB",
    "wof:name": "NN15 5NN",
    "wof:placetype": "postalcode"
  },
  "geometry": {"coordinates":[-0.695446,52.389807],"type":"Point"}
}
