{
  "type": "Feature",
  "properties": {
    "iso:country": "GB",
    "wof:name": "NN15 5NN",
    "wof:placetype": "postalcode"
  },
  "geometry": {"coordinates":[-0.695446,52.389807],"type":"Point"}
}
