{
  "type": "Feature",
  "properties": {
    "iso:country": "GB",
    "wof:name": "NW10 2EL",
    "wof:placetype": "postalcode"
  },
  "geometry": {"coordinates":[-0.240339,51.548906],"type":"Point"}
}
