{
  "type": "Feature",
  "properties": {
    "iso:country":"GB",
    "wof:name":"NW10 2EL",
    "wof:placetype":"postalcode"
},
  "geometry": {"coordinates":[-0.2403393526905,51.54890586728205],"type":"Point"}
}