{
  "type": "Feature",
  "properties": {
    "iso:country":"GB",
    "wof:name":"HP2 7SF",
    "wof:placetype":"postalcode"
},
  "geometry": {"coordinates":[-0.43952156628528,51.77447320556845],"type":"Point"}
}