{
  "type": "Feature",
  "properties": {
    "iso:country":"GB",
    "wof:name":"RH10 6PF",
    "wof:placetype":"postalcode"
},
  "geometry": {"coordinates":[-0.17004643436741,51.10308591102146],"type":"Point"}
}