{
  "type": "Feature",
  "properties": {
    "date:inception_lower": "1980-01-01",
    "date:inception_upper": "1980-01-01",
    "iso:country": "GB",
    "wof:name": "CB11 4LT",
    "wof:placetype": "postalcode"
  },
  "geometry": {"coordinates":[0.133112,52.03655],"type":"Point"}
}
