{
  "type": "Feature",
  "properties": {
    "date:inception_lower": "1980-01-01",
    "date:inception_upper": "1980-01-01",
    "iso:country": "GB",
    "wof:name": "BL3 3DU",
    "wof:placetype": "postalcode"
  },
  "geometry": {"coordinates":[-2.435891,53.561737],"type":"Point"}
}
