{
  "type": "Feature",
  "properties": {
    "iso:country": "GB",
    "wof:name": "BL3 3DU",
    "wof:placetype": "postalcode"
  },
  "geometry": {"coordinates":[-2.435891,53.561737],"type":"Point"}
}
