{
  "type": "Feature",
  "properties": {
    "iso:country":"GB",
    "wof:name":"RG30 4JY",
    "wof:placetype":"postalcode"
},
  "geometry": {"coordinates":[-1.03106077061736,51.45147457279133],"type":"Point"}
}