{
  "type": "Feature",
  "properties": {
    "date:inception_lower": "1995-07-01",
    "date:inception_upper": "1995-07-01",
    "iso:country": "GB",
    "wof:name": "RG30 4JY",
    "wof:placetype": "postalcode"
  },
  "geometry": {"coordinates":[-1.031061,51.451475],"type":"Point"}
}
