{
  "type": "Feature",
  "properties": {
    "iso:country":"GB",
    "wof:name":"TF1 3DL",
    "wof:placetype":"postalcode"
},
  "geometry": {"coordinates":[-2.52028541433028,52.70358221276866],"type":"Point"}
}