{
  "type": "Feature",
  "properties": {
    "iso:country":"GB",
    "wof:name":"OX3 7EY",
    "wof:placetype":"postalcode"
},
  "geometry": {"coordinates":[-1.20736229377747,51.74465393587318],"type":"Point"}
}