{
  "type": "Feature",
  "properties": {
    "iso:country": "GB",
    "wof:name": "SA19 8DP",
    "wof:placetype": "postalcode"
  },
  "geometry": {"coordinates":[-3.980998,52.061407],"type":"Point"}
}
