{
  "type": "Feature",
  "properties": {
    "iso:country":"GB",
    "wof:name":"NW5 1EN",
    "wof:placetype":"postalcode"
},
  "geometry": {"coordinates":[-0.14653786503937,51.56008690875895],"type":"Point"}
}