{
  "type": "Feature",
  "properties": {
    "iso:country":"GB",
    "wof:name":"DA1 5LL",
    "wof:placetype":"postalcode"
},
  "geometry": {"coordinates":[0.22301531606203,51.45589493288354],"type":"Point"}
}