{
  "type": "Feature",
  "properties": {
    "date:inception_lower":"1990-02-01",
    "date:inception_upper":"1990-02-28",
    "iso:country":"GB",
    "wof:name":"NG34 8LX",
    "wof:placetype":"postalcode"
},
  "geometry": {"coordinates":[-0.420703,53.024872],"type":"Point"}
}