{
  "type": "Feature",
  "properties": {
    "iso:country":"GB",
    "wof:name":"SE6 2LA",
    "wof:placetype":"postalcode"
},
  "geometry": {"coordinates":[-0.01619322626049,51.44223774252753],"type":"Point"}
}