{
  "type": "Feature",
  "properties": {
    "date:inception_lower": "1980-01-01",
    "date:inception_upper": "1980-01-01",
    "iso:country": "GB",
    "wof:name": "SE6 2LA",
    "wof:placetype": "postalcode"
  },
  "geometry": {"coordinates":[-0.016193,51.442238],"type":"Point"}
}
