{
  "type": "Feature",
  "properties": {
    "iso:country":"GB",
    "wof:name":"RG41 4BH",
    "wof:placetype":"postalcode"
},
  "geometry": {"coordinates":[-0.85769382489335,51.40621300037871],"type":"Point"}
}