{
  "type": "Feature",
  "properties": {
    "iso:country":"GB",
    "wof:name":"W3 9HN",
    "wof:placetype":"postalcode"
},
  "geometry": {"coordinates":[-0.27987577587805,51.51479077032214],"type":"Point"}
}