{
  "type": "Feature",
  "properties": {
    "iso:country": "GB",
    "wof:name": "W3 9HN",
    "wof:placetype": "postalcode"
  },
  "geometry": {"coordinates":[-0.279876,51.514791],"type":"Point"}
}
