{
  "type": "Feature",
  "properties": {
    "iso:country":"GB",
    "wof:name":"RH11 0QS",
    "wof:placetype":"postalcode"
},
  "geometry": {"coordinates":[-0.23037725871943,51.11030975378696],"type":"Point"}
}