{
  "type": "Feature",
  "properties": {
    "iso:country": "GB",
    "wof:name": "WA8 0HA",
    "wof:placetype": "postalcode"
  },
  "geometry": {"coordinates":[-2.721432,53.364978],"type":"Point"}
}
