{
  "type": "Feature",
  "properties": {
    "iso:country":"GB",
    "wof:name":"WA8 0HA",
    "wof:placetype":"postalcode"
},
  "geometry": {"coordinates":[-2.72143243477107,53.36497769753551],"type":"Point"}
}