{
  "type": "Feature",
  "properties": {
    "date:inception_lower": "1990-07-01",
    "date:inception_upper": "1990-07-01",
    "iso:country": "GB",
    "wof:name": "DN22 0BF",
    "wof:placetype": "postalcode"
  },
  "geometry": {"coordinates":[-0.819816,53.321011],"type":"Point"}
}
