{
  "type": "Feature",
  "properties": {
    "iso:country":"GB",
    "wof:name":"DN22 0BF",
    "wof:placetype":"postalcode"
},
  "geometry": {"coordinates":[-0.81981606659501,53.32101089594185],"type":"Point"}
}