{
  "type": "Feature",
  "properties": {
    "iso:country": "GB",
    "wof:name": "DE3 0UJ",
    "wof:placetype": "postalcode"
  },
  "geometry": {"coordinates":[-1.560126,52.895944],"type":"Point"}
}
