{
  "type": "Feature",
  "properties": {
    "date:inception_lower": "2002-06-01",
    "date:inception_upper": "2002-06-01",
    "iso:country": "GB",
    "wof:name": "DE3 0UJ",
    "wof:placetype": "postalcode"
  },
  "geometry": {"coordinates":[-1.560126,52.895944],"type":"Point"}
}
