{
  "type": "Feature",
  "properties": {
    "date:inception_lower":"1980-01-01",
    "date:inception_upper":"1980-01-31",
    "iso:country":"GB",
    "wof:name":"B43 7PY",
    "wof:placetype":"postalcode"
},
  "geometry": {"coordinates":[-1.917146,52.559566],"type":"Point"}
}