{
  "type": "Feature",
  "properties": {
    "iso:country":"GB",
    "wof:name":"B43 7PY",
    "wof:placetype":"postalcode"
},
  "geometry": {"coordinates":[-1.91714604871456,52.55956595423102],"type":"Point"}
}