{
  "type": "Feature",
  "properties": {
    "iso:country": "GB",
    "wof:name": "DE1 1UP",
    "wof:placetype": "postalcode"
  },
  "geometry": {"coordinates":[-1.49094,52.92305],"type":"Point"}
}
