{
  "type": "Feature",
  "properties": {
    "iso:country":"GB",
    "wof:name":"DY6 0LN",
    "wof:placetype":"postalcode"
},
  "geometry": {"coordinates":[-2.1843808489559,52.50586205754507],"type":"Point"}
}