{
  "type": "Feature",
  "properties": {
    "iso:country":"GB",
    "wof:name":"BR6 0AJ",
    "wof:placetype":"postalcode"
},
  "geometry": {"coordinates":[0.09134565243932,51.37958509432737],"type":"Point"}
}