{
  "type": "Feature",
  "properties": {
    "iso:country":"GB",
    "wof:name":"BD1 2SH",
    "wof:placetype":"postalcode"
},
  "geometry": {"coordinates":[-1.75656003578712,53.7942158048597],"type":"Point"}
}