{
  "type": "Feature",
  "properties": {
    "date:inception_lower":"1980-01-01",
    "date:inception_upper":"1980-01-31",
    "iso:country":"GB",
    "wof:name":"BD1 2SH",
    "wof:placetype":"postalcode"
},
  "geometry": {"coordinates":[-1.75656,53.794216],"type":"Point"}
}