{
  "type": "Feature",
  "properties": {
    "iso:country":"GB",
    "wof:name":"WR5 2GH",
    "wof:placetype":"postalcode"
},
  "geometry": {"coordinates":[-2.19498039626026,52.16075638519995],"type":"Point"}
}