{
  "type": "Feature",
  "properties": {
    "iso:country": "GB",
    "wof:name": "WR5 2GH",
    "wof:placetype": "postalcode"
  },
  "geometry": {"coordinates":[-2.19498,52.160756],"type":"Point"}
}
