{
  "type": "Feature",
  "properties": {
    "iso:country":"GB",
    "wof:name":"SN12 8JX",
    "wof:placetype":"postalcode"
},
  "geometry": {"coordinates":[-2.19433366603478,51.39164501678633],"type":"Point"}
}