{
  "type": "Feature",
  "properties": {
    "iso:country":"GB",
    "wof:name":"B68 0JH",
    "wof:placetype":"postalcode"
},
  "geometry": {"coordinates":[-2.00725762795431,52.46980335026544],"type":"Point"}
}