{
  "type": "Feature",
  "properties": {
    "iso:country": "GB",
    "wof:name": "B68 0JH",
    "wof:placetype": "postalcode"
  },
  "geometry": {"coordinates":[-2.007258,52.469803],"type":"Point"}
}
