{
  "type": "Feature",
  "properties": {
    "date:inception_lower":"1980-01-01",
    "date:inception_upper":"1980-01-31",
    "iso:country":"GB",
    "wof:name":"B68 0JH",
    "wof:placetype":"postalcode"
},
  "geometry": {"coordinates":[-2.007258,52.469803],"type":"Point"}
}