{
  "type": "Feature",
  "properties": {
    "iso:country":"GB",
    "wof:name":"WV4 6BD",
    "wof:placetype":"postalcode"
},
  "geometry": {"coordinates":[-2.1219918861681,52.56577957910438],"type":"Point"}
}