{
  "type": "Feature",
  "properties": {
    "iso:country": "GB",
    "wof:name": "WV4 6BD",
    "wof:placetype": "postalcode"
  },
  "geometry": {"coordinates":[-2.121992,52.56578],"type":"Point"}
}
