{
  "type": "Feature",
  "properties": {
    "date:inception_lower":"1999-12-01",
    "date:inception_upper":"1999-12-31",
    "iso:country":"GB",
    "wof:name":"KA1 1RP",
    "wof:placetype":"postalcode"
},
  "geometry": {"coordinates":[-4.515675,55.596722],"type":"Point"}
}