{
  "type": "Feature",
  "properties": {
    "iso:country": "GB",
    "wof:name": "KA1 1RP",
    "wof:placetype": "postalcode"
  },
  "geometry": {"coordinates":[-4.515675,55.596722],"type":"Point"}
}
