{
  "type": "Feature",
  "properties": {
    "iso:country": "GB",
    "wof:name": "GL8 8QW",
    "wof:placetype": "postalcode"
  },
  "geometry": {"coordinates":[-2.213444,51.615445],"type":"Point"}
}
