{
  "type": "Feature",
  "properties": {
    "date:inception_lower": "2010-06-01",
    "date:inception_upper": "2010-06-01",
    "iso:country": "GB",
    "wof:name": "GL8 8QW",
    "wof:placetype": "postalcode"
  },
  "geometry": {"coordinates":[-2.213444,51.615445],"type":"Point"}
}
