{
  "type": "Feature",
  "properties": {
    "iso:country":"GB",
    "wof:name":"WA8 6QL",
    "wof:placetype":"postalcode"
},
  "geometry": {"coordinates":[-2.72139792173543,53.37271727063418],"type":"Point"}
}