{
  "type": "Feature",
  "properties": {
    "iso:country":"GB",
    "wof:name":"DT6 5AU",
    "wof:placetype":"postalcode"
},
  "geometry": {"coordinates":[-2.76658940528249,50.72982833585419],"type":"Point"}
}