{
  "type": "Feature",
  "properties": {
    "iso:country":"GB",
    "wof:name":"B9 4PU",
    "wof:placetype":"postalcode"
},
  "geometry": {"coordinates":[-1.86741935247298,52.47683167536974],"type":"Point"}
}