{
  "type": "Feature",
  "properties": {
    "iso:country": "GB",
    "wof:name": "WA5 8EX",
    "wof:placetype": "postalcode"
  },
  "geometry": {"coordinates":[-2.638167,53.403394],"type":"Point"}
}
