{
  "type": "Feature",
  "properties": {
    "date:inception_lower": "2001-06-01",
    "date:inception_upper": "2001-06-01",
    "iso:country": "GB",
    "wof:name": "WA5 8EX",
    "wof:placetype": "postalcode"
  },
  "geometry": {"coordinates":[-2.638182,53.4034],"type":"Point"}
}
