{
  "type": "Feature",
  "properties": {
    "iso:country":"GB",
    "wof:name":"RH6 9UH",
    "wof:placetype":"postalcode"
},
  "geometry": {"coordinates":[-0.15433252217457,51.1783981358903],"type":"Point"}
}