{
  "type": "Feature",
  "properties": {
    "date:inception_lower":"1980-01-01",
    "date:inception_upper":"1980-01-31",
    "iso:country":"GB",
    "wof:name":"NR26 8DG",
    "wof:placetype":"postalcode"
},
  "geometry": {"coordinates":[1.215826,52.943003],"type":"Point"}
}