{
  "type": "Feature",
  "properties": {
    "iso:country": "GB",
    "wof:name": "NR26 8DG",
    "wof:placetype": "postalcode"
  },
  "geometry": {"coordinates":[1.215826,52.943003],"type":"Point"}
}
