{
  "type": "Feature",
  "properties": {
    "iso:country":"GB",
    "wof:name":"AB51 0UN",
    "wof:placetype":"postalcode"
},
  "geometry": {"coordinates":[-2.31277933197971,57.23749299576541],"type":"Point"}
}