{
  "type": "Feature",
  "properties": {
    "iso:country": "GB",
    "wof:name": "AB51 0UN",
    "wof:placetype": "postalcode"
  },
  "geometry": {"coordinates":[-2.312779,57.237493],"type":"Point"}
}
