{
  "type": "Feature",
  "properties": {
    "date:inception_lower": "1980-01-01",
    "date:inception_upper": "1980-01-01",
    "iso:country": "GB",
    "wof:name": "NG5 4LH",
    "wof:placetype": "postalcode"
  },
  "geometry": {"coordinates":[-1.12654,52.990842],"type":"Point"}
}
