{
  "type": "Feature",
  "properties": {
    "iso:country":"GB",
    "wof:name":"NG7 1AX",
    "wof:placetype":"postalcode"
},
  "geometry": {"coordinates":[-1.1657522651841,52.95361078989476],"type":"Point"}
}