{
  "type": "Feature",
  "properties": {
    "iso:country":"GB",
    "wof:name":"G5 0SQ",
    "wof:placetype":"postalcode"
},
  "geometry": {"coordinates":[-4.25159244808368,55.8463213133649],"type":"Point"}
}