{
  "type": "Feature",
  "properties": {
    "date:inception_lower": "1999-06-01",
    "date:inception_upper": "1999-06-01",
    "iso:country": "GB",
    "wof:name": "G5 0SQ",
    "wof:placetype": "postalcode"
  },
  "geometry": {"coordinates":[-4.251592,55.846321],"type":"Point"}
}
