{
  "type": "Feature",
  "properties": {
    "iso:country":"GB",
    "wof:name":"G69 7TN",
    "wof:placetype":"postalcode"
},
  "geometry": {"coordinates":[-4.07735553292257,55.85820391224177],"type":"Point"}
}