{
  "type": "Feature",
  "properties": {
    "date:inception_lower":"2005-06-01",
    "date:inception_upper":"2005-06-30",
    "iso:country":"GB",
    "wof:name":"G69 7TN",
    "wof:placetype":"postalcode"
},
  "geometry": {"coordinates":[-4.077355,55.858204],"type":"Point"}
}