{
  "type": "Feature",
  "properties": {
    "iso:country": "GB",
    "wof:name": "EH21 7UA",
    "wof:placetype": "postalcode"
  },
  "geometry": {"coordinates":[-3.051629,55.93675],"type":"Point"}
}
