{
  "type": "Feature",
  "properties": {
    "iso:country":"GB",
    "wof:name":"OX11 6DN",
    "wof:placetype":"postalcode"
},
  "geometry": {"coordinates":[-1.27802591522674,51.60208352430932],"type":"Point"}
}