{
  "type": "Feature",
  "properties": {
    "iso:country":"GB",
    "wof:name":"DN2 4RA",
    "wof:placetype":"postalcode"
},
  "geometry": {"coordinates":[-1.0882940650007,53.55567131178206],"type":"Point"}
}