{
  "type": "Feature",
  "properties": {
    "iso:country": "GB",
    "wof:name": "LS1 4PE",
    "wof:placetype": "postalcode"
  },
  "geometry": {"coordinates":[-1.559887,53.799444],"type":"Point"}
}
