{
  "type": "Feature",
  "properties": {
    "iso:country":"GB",
    "wof:name":"LS1 4PE",
    "wof:placetype":"postalcode"
},
  "geometry": {"coordinates":[-1.55988752643218,53.799444044076],"type":"Point"}
}