{
  "type": "Feature",
  "properties": {
    "iso:country":"GB",
    "wof:name":"EX8 1RR",
    "wof:placetype":"postalcode"
},
  "geometry": {"coordinates":[-3.41408247637365,50.62121223447711],"type":"Point"}
}