{
  "type": "Feature",
  "properties": {
    "date:inception_lower":"1993-01-01",
    "date:inception_upper":"1993-01-31",
    "iso:country":"GB",
    "wof:name":"N1 0XF",
    "wof:placetype":"postalcode"
},
  "geometry": {"coordinates":[-0.120623,51.535692],"type":"Point"}
}