{
  "type": "Feature",
  "properties": {
    "iso:country": "GB",
    "wof:name": "M28 3SW",
    "wof:placetype": "postalcode"
  },
  "geometry": {"coordinates":[-2.387553,53.529346],"type":"Point"}
}
