{
  "type": "Feature",
  "properties": {
    "iso:country":"GB",
    "wof:name":"M28 3SW",
    "wof:placetype":"postalcode"
},
  "geometry": {"coordinates":[-2.38774907126057,53.5291045530719],"type":"Point"}
}