{
  "type": "Feature",
  "properties": {
    "iso:country": "GB",
    "wof:name": "HP22 5FW",
    "wof:placetype": "postalcode"
  },
  "geometry": {"coordinates":[-0.713829,51.797899],"type":"Point"}
}
