{
  "type": "Feature",
  "properties": {
    "iso:country":"GB",
    "wof:name":"SA14 7LS",
    "wof:placetype":"postalcode"
},
  "geometry": {"coordinates":[-4.06661997677506,51.81241695184758],"type":"Point"}
}