{
  "type": "Feature",
  "properties": {
    "iso:country": "GB",
    "wof:name": "SA14 7LS",
    "wof:placetype": "postalcode"
  },
  "geometry": {"coordinates":[-4.066568,51.812453],"type":"Point"}
}
