{
  "type": "Feature",
  "properties": {
    "date:inception_lower": "1980-01-01",
    "date:inception_upper": "1980-01-01",
    "iso:country": "GB",
    "wof:name": "SA14 7LS",
    "wof:placetype": "postalcode"
  },
  "geometry": {"coordinates":[-4.06664,51.812425],"type":"Point"}
}
