{
  "type": "Feature",
  "properties": {
    "date:inception_lower":"1980-01-01",
    "date:inception_upper":"1980-01-31",
    "iso:country":"GB",
    "wof:name":"SN15 1JD",
    "wof:placetype":"postalcode"
},
  "geometry": {"coordinates":[-2.144161,51.464891],"type":"Point"}
}