{
  "type": "Feature",
  "properties": {
    "iso:country":"GB",
    "wof:name":"S21 1EB",
    "wof:placetype":"postalcode"
},
  "geometry": {"coordinates":[-1.31629816059943,53.32557115421285],"type":"Point"}
}