{
  "type": "Feature",
  "properties": {
    "iso:country":"GB",
    "wof:name":"NG5 5JH",
    "wof:placetype":"postalcode"
},
  "geometry": {"coordinates":[-1.15943158118523,52.99555607516139],"type":"Point"}
}