{
  "type": "Feature",
  "properties": {
    "iso:country":"GB",
    "wof:name":"EH15 2LH",
    "wof:placetype":"postalcode"
},
  "geometry": {"coordinates":[-3.08857466639512,55.946968485794],"type":"Point"}
}