{
  "type": "Feature",
  "properties": {
    "iso:country":"GB",
    "wof:name":"DH2 2UJ",
    "wof:placetype":"postalcode"
},
  "geometry": {"coordinates":[-1.59803473670511,54.8526028490697],"type":"Point"}
}