{
  "type": "Feature",
  "properties": {
    "iso:country": "GB",
    "wof:name": "DH2 2UJ",
    "wof:placetype": "postalcode"
  },
  "geometry": {"coordinates":[-1.598035,54.852603],"type":"Point"}
}
