{
  "type": "Feature",
  "properties": {
    "iso:country":"GB",
    "wof:name":"GU51 3LP",
    "wof:placetype":"postalcode"
},
  "geometry": {"coordinates":[-0.83844612111029,51.27939695709756],"type":"Point"}
}