{
  "type": "Feature",
  "properties": {
    "iso:country": "GB",
    "wof:name": "CO10 2RD",
    "wof:placetype": "postalcode"
  },
  "geometry": {"coordinates":[0.736071,52.036514],"type":"Point"}
}
