{
  "type": "Feature",
  "properties": {
    "iso:country":"GB",
    "wof:name":"CO10 2RD",
    "wof:placetype":"postalcode"
},
  "geometry": {"coordinates":[0.73607123276326,52.03651373182476],"type":"Point"}
}