{
  "type": "Feature",
  "properties": {
    "iso:country":"GB",
    "wof:name":"BL3 4JJ",
    "wof:placetype":"postalcode"
},
  "geometry": {"coordinates":[-2.46388754361035,53.56373529792168],"type":"Point"}
}