{
  "type": "Feature",
  "properties": {
    "iso:country":"GB",
    "wof:name":"SN15 3UR",
    "wof:placetype":"postalcode"
},
  "geometry": {"coordinates":[-2.09885879937323,51.44440144446459],"type":"Point"}
}