{
  "type": "Feature",
  "properties": {
    "iso:country": "GB",
    "wof:name": "NG34 0BY",
    "wof:placetype": "postalcode"
  },
  "geometry": {"coordinates":[-0.338065,52.965414],"type":"Point"}
}
