{
  "type": "Feature",
  "properties": {
    "iso:country":"GB",
    "wof:name":"NG34 0BY",
    "wof:placetype":"postalcode"
},
  "geometry": {"coordinates":[-0.33807220600404,52.96539081710702],"type":"Point"}
}