{
  "type": "Feature",
  "properties": {
    "iso:country": "GB",
    "wof:name": "PE26 2TB",
    "wof:placetype": "postalcode"
  },
  "geometry": {"coordinates":[-0.150877,52.482174],"type":"Point"}
}
