{
  "type": "Feature",
  "properties": {
    "iso:country":"GB",
    "wof:name":"DG7 2BE",
    "wof:placetype":"postalcode"
},
  "geometry": {"coordinates":[-4.17806134036194,54.89521546244772],"type":"Point"}
}