{
  "type": "Feature",
  "properties": {
    "iso:country":"GB",
    "wof:name":"FK9 5QD",
    "wof:placetype":"postalcode"
},
  "geometry": {"coordinates":[-3.88564164163637,56.13730318309194],"type":"Point"}
}