{
  "type": "Feature",
  "properties": {
    "iso:country": "GB",
    "wof:name": "FK9 5QD",
    "wof:placetype": "postalcode"
  },
  "geometry": {"coordinates":[-3.885642,56.137303],"type":"Point"}
}
