{
  "type": "Feature",
  "properties": {
    "date:inception_lower":"2010-04-01",
    "date:inception_upper":"2010-04-30",
    "iso:country":"GB",
    "wof:name":"FK9 5QD",
    "wof:placetype":"postalcode"
},
  "geometry": {"coordinates":[-3.885642,56.137303],"type":"Point"}
}