{
  "type": "Feature",
  "properties": {
    "iso:country":"GB",
    "wof:name":"WF2 6BH",
    "wof:placetype":"postalcode"
},
  "geometry": {"coordinates":[-1.49163859992469,53.65015044543121],"type":"Point"}
}