{
  "type": "Feature",
  "properties": {
    "date:inception_lower": "1984-10-01",
    "date:inception_upper": "1984-10-01",
    "iso:country": "GB",
    "wof:name": "E3 3JY",
    "wof:placetype": "postalcode"
  },
  "geometry": {"coordinates":[-0.008552,51.522566],"type":"Point"}
}
