{
  "type": "Feature",
  "properties": {
    "iso:country": "GB",
    "wof:name": "E3 3JY",
    "wof:placetype": "postalcode"
  },
  "geometry": {"coordinates":[-0.008552,51.522566],"type":"Point"}
}
