{
  "type": "Feature",
  "properties": {
    "iso:country":"GB",
    "wof:name":"E3 3JY",
    "wof:placetype":"postalcode"
},
  "geometry": {"coordinates":[-0.00855243298748,51.52256590780243],"type":"Point"}
}