{
  "type": "Feature",
  "properties": {
    "iso:country":"GB",
    "wof:name":"DD11 4SU",
    "wof:placetype":"postalcode"
},
  "geometry": {"coordinates":[-2.65835501993474,56.6391998446687],"type":"Point"}
}