{
  "type": "Feature",
  "properties": {
    "iso:country": "GB",
    "wof:name": "DD11 4SU",
    "wof:placetype": "postalcode"
  },
  "geometry": {"coordinates":[-2.658355,56.6392],"type":"Point"}
}
