{
  "type": "Feature",
  "properties": {
    "date:inception_lower":"1980-01-01",
    "date:inception_upper":"1980-01-31",
    "iso:country":"GB",
    "wof:name":"DD11 4SU",
    "wof:placetype":"postalcode"
},
  "geometry": {"coordinates":[-2.658355,56.6392],"type":"Point"}
}