{
  "type": "Feature",
  "properties": {
    "date:inception_lower": "1980-01-01",
    "date:inception_upper": "1980-01-01",
    "iso:country": "GB",
    "wof:name": "DH8 9SZ",
    "wof:placetype": "postalcode"
  },
  "geometry": {"coordinates":[-2.080723,54.850958],"type":"Point"}
}
