{
  "type": "Feature",
  "properties": {
    "iso:country":"GB",
    "wof:name":"DH8 9SZ",
    "wof:placetype":"postalcode"
},
  "geometry": {"coordinates":[-2.08072288363905,54.85095764984709],"type":"Point"}
}