{
  "type": "Feature",
  "properties": {
    "iso:country":"GB",
    "wof:name":"NG22 0RB",
    "wof:placetype":"postalcode"
},
  "geometry": {"coordinates":[-0.88990867263618,53.24932040942669],"type":"Point"}
}