{
  "type": "Feature",
  "properties": {
    "iso:country": "GB",
    "wof:name": "CT5 3JU",
    "wof:placetype": "postalcode"
  },
  "geometry": {"coordinates":[1.062827,51.355157],"type":"Point"}
}
