{
  "type": "Feature",
  "properties": {
    "iso:country":"GB",
    "wof:name":"NW9 8AA",
    "wof:placetype":"postalcode"
},
  "geometry": {"coordinates":[-0.26314682931091,51.58059286173122],"type":"Point"}
}