{
  "type": "Feature",
  "properties": {
    "iso:country":"GB",
    "wof:name":"SR1 2AP",
    "wof:placetype":"postalcode"
},
  "geometry": {"coordinates":[-1.37337241046233,54.90806027453505],"type":"Point"}
}