{
  "type": "Feature",
  "properties": {
    "date:inception_lower": "1986-04-01",
    "date:inception_upper": "1986-04-01",
    "iso:country": "GB",
    "wof:name": "NG2 7LU",
    "wof:placetype": "postalcode"
  },
  "geometry": {"coordinates":[-1.14874,52.914871],"type":"Point"}
}
