{
  "type": "Feature",
  "properties": {
    "iso:country": "GB",
    "wof:name": "B60 3AF",
    "wof:placetype": "postalcode"
  },
  "geometry": {"coordinates":[-2.028227,52.321841],"type":"Point"}
}
