{
  "type": "Feature",
  "properties": {
    "iso:country": "GB",
    "wof:name": "CV11 4QP",
    "wof:placetype": "postalcode"
  },
  "geometry": {"coordinates":[-1.458455,52.506854],"type":"Point"}
}
