{
  "type": "Feature",
  "properties": {
    "iso:country":"GB",
    "wof:name":"LS4 2LA",
    "wof:placetype":"postalcode"
},
  "geometry": {"coordinates":[-1.57897983327484,53.80774556983767],"type":"Point"}
}