{
  "type": "Feature",
  "properties": {
    "iso:country": "GB",
    "wof:name": "LS4 2LA",
    "wof:placetype": "postalcode"
  },
  "geometry": {"coordinates":[-1.57898,53.807746],"type":"Point"}
}
