{
  "type": "Feature",
  "properties": {
    "iso:country":"GB",
    "wof:name":"BS10 7SW",
    "wof:placetype":"postalcode"
},
  "geometry": {"coordinates":[-2.61538885943267,51.52273533981806],"type":"Point"}
}