{
  "type": "Feature",
  "properties": {
    "date:inception_lower": "2005-04-01",
    "date:inception_upper": "2005-04-01",
    "iso:country": "GB",
    "wof:name": "BS10 7SW",
    "wof:placetype": "postalcode"
  },
  "geometry": {"coordinates":[-2.615377,51.522752],"type":"Point"}
}
