{
  "type": "Feature",
  "properties": {
    "iso:country":"GB",
    "wof:name":"EN3 4ET",
    "wof:placetype":"postalcode"
},
  "geometry": {"coordinates":[-0.04679223652577,51.64382561344004],"type":"Point"}
}