{
  "type": "Feature",
  "properties": {
    "iso:country": "GB",
    "wof:name": "UB5 6NQ",
    "wof:placetype": "postalcode"
  },
  "geometry": {"coordinates":[-0.400943,51.535225],"type":"Point"}
}
