{
  "type": "Feature",
  "properties": {
    "iso:country":"GB",
    "wof:name":"UB5 6NQ",
    "wof:placetype":"postalcode"
},
  "geometry": {"coordinates":[-0.40094301764649,51.5352254279583],"type":"Point"}
}