{
  "type": "Feature",
  "properties": {
    "iso:country":"GB",
    "wof:name":"NW11 7TS",
    "wof:placetype":"postalcode"
},
  "geometry": {"coordinates":[-0.19746095241245,51.58096918867673],"type":"Point"}
}