{
  "type": "Feature",
  "properties": {
    "date:inception_lower":"1980-01-01",
    "date:inception_upper":"1980-01-31",
    "iso:country":"GB",
    "wof:name":"ME16 9NS",
    "wof:placetype":"postalcode"
},
  "geometry": {"coordinates":[0.478453,51.284032],"type":"Point"}
}