{
  "type": "Feature",
  "properties": {
    "iso:country":"GB",
    "wof:name":"ME16 9NS",
    "wof:placetype":"postalcode"
},
  "geometry": {"coordinates":[0.47845276636977,51.28403181027105],"type":"Point"}
}