{
  "type": "Feature",
  "properties": {
    "iso:country":"GB",
    "wof:name":"SG5 4LY",
    "wof:placetype":"postalcode"
},
  "geometry": {"coordinates":[-0.22778693197912,52.01553838061984],"type":"Point"}
}