{
  "type": "Feature",
  "properties": {
    "iso:country": "GB",
    "wof:name": "SG5 4LY",
    "wof:placetype": "postalcode"
  },
  "geometry": {"coordinates":[-0.227787,52.015538],"type":"Point"}
}
