{
  "type": "Feature",
  "properties": {
    "iso:country":"GB",
    "wof:name":"L34 0HP",
    "wof:placetype":"postalcode"
},
  "geometry": {"coordinates":[-2.85116733132331,53.45234815602834],"type":"Point"}
}