{
  "type": "Feature",
  "properties": {
    "iso:country": "GB",
    "wof:name": "KY1 4ER",
    "wof:placetype": "postalcode"
  },
  "geometry": {"coordinates":[-3.150033,56.162723],"type":"Point"}
}
