{
  "type": "Feature",
  "properties": {
    "date:inception_lower": "2020-02-01",
    "date:inception_upper": "2020-02-01",
    "iso:country": "GB",
    "wof:name": "KY1 4ER",
    "wof:placetype": "postalcode"
  },
  "geometry": {"coordinates":[-3.150033,56.162723],"type":"Point"}
}
