{
  "type": "Feature",
  "properties": {
    "date:inception_lower":"1980-01-01",
    "date:inception_upper":"1980-01-31",
    "iso:country":"GB",
    "wof:name":"RG8 9SG",
    "wof:placetype":"postalcode"
},
  "geometry": {"coordinates":[-1.196779,51.512009],"type":"Point"}
}