{
  "type": "Feature",
  "properties": {
    "iso:country":"GB",
    "wof:name":"RG8 9SG",
    "wof:placetype":"postalcode"
},
  "geometry": {"coordinates":[-1.19677868967617,51.51200881079797],"type":"Point"}
}