{
  "type": "Feature",
  "properties": {
    "iso:country":"GB",
    "wof:name":"BA6 8NG",
    "wof:placetype":"postalcode"
},
  "geometry": {"coordinates":[-2.63179202493304,51.15011634684974],"type":"Point"}
}