{
  "type": "Feature",
  "properties": {
    "date:inception_lower": "1980-01-01",
    "date:inception_upper": "1980-01-01",
    "iso:country": "GB",
    "wof:name": "BA6 8NG",
    "wof:placetype": "postalcode"
  },
  "geometry": {"coordinates":[-2.632593,51.149926],"type":"Point"}
}
