{
  "type": "Feature",
  "properties": {
    "iso:country": "GB",
    "wof:name": "BA6 8NG",
    "wof:placetype": "postalcode"
  },
  "geometry": {"coordinates":[-2.631795,51.15011],"type":"Point"}
}
