{
  "type": "Feature",
  "properties": {
    "iso:country":"GB",
    "wof:name":"OX15 4GL",
    "wof:placetype":"postalcode"
},
  "geometry": {"coordinates":[-1.31702366764074,52.03986060515652],"type":"Point"}
}