{
  "type": "Feature",
  "properties": {
    "date:inception_lower": "2015-11-01",
    "date:inception_upper": "2015-11-01",
    "iso:country": "GB",
    "wof:name": "OX15 4GL",
    "wof:placetype": "postalcode"
  },
  "geometry": {"coordinates":[-1.317008,52.039871],"type":"Point"}
}
