{
  "type": "Feature",
  "properties": {
    "date:inception_lower": "2020-08-01",
    "date:inception_upper": "2020-08-01",
    "iso:country": "GB",
    "wof:name": "GU34 1GQ",
    "wof:placetype": "postalcode"
  },
  "geometry": {"coordinates":[-0.988866,51.149719],"type":"Point"}
}
