{
  "type": "Feature",
  "properties": {
    "iso:country":"GB",
    "wof:name":"WS1 2DH",
    "wof:placetype":"postalcode"
},
  "geometry": {"coordinates":[-1.96416639808794,52.58393384249121],"type":"Point"}
}