{
  "type": "Feature",
  "properties": {
    "date:inception_lower": "1980-01-01",
    "date:inception_upper": "1980-01-01",
    "iso:country": "GB",
    "wof:name": "WS1 2DH",
    "wof:placetype": "postalcode"
  },
  "geometry": {"coordinates":[-1.96419,52.584012],"type":"Point"}
}
