{
  "type": "Feature",
  "properties": {
    "iso:country":"GB",
    "wof:name":"B93 0JX",
    "wof:placetype":"postalcode"
},
  "geometry": {"coordinates":[-1.73716823942997,52.38956361978337],"type":"Point"}
}