{
  "type": "Feature",
  "properties": {
    "iso:country":"GB",
    "wof:name":"TR15 3YE",
    "wof:placetype":"postalcode"
},
  "geometry": {"coordinates":[-5.26218846016219,50.21442552835373],"type":"Point"}
}