{
  "type": "Feature",
  "properties": {
    "date:inception_lower": "1980-01-01",
    "date:inception_upper": "1980-01-01",
    "iso:country": "GB",
    "wof:name": "TR15 3YE",
    "wof:placetype": "postalcode"
  },
  "geometry": {"coordinates":[-5.262279,50.214405],"type":"Point"}
}
