{
  "type": "Feature",
  "properties": {
    "date:inception_lower": "1980-01-01",
    "date:inception_upper": "1980-01-01",
    "iso:country": "GB",
    "wof:name": "GL15 4SN",
    "wof:placetype": "postalcode"
  },
  "geometry": {"coordinates":[-2.519571,51.761865],"type":"Point"}
}
