{
  "type": "Feature",
  "properties": {
    "iso:country":"GB",
    "wof:name":"GL15 4SN",
    "wof:placetype":"postalcode"
},
  "geometry": {"coordinates":[-2.51957114024498,51.76186486326348],"type":"Point"}
}