{
  "type": "Feature",
  "properties": {
    "iso:country":"GB",
    "wof:name":"DE5 3UX",
    "wof:placetype":"postalcode"
},
  "geometry": {"coordinates":[-1.40514941900688,53.04322548524773],"type":"Point"}
}