{
  "type": "Feature",
  "properties": {
    "date:inception_lower":"1993-01-01",
    "date:inception_upper":"1993-01-31",
    "iso:country":"GB",
    "wof:name":"NG16 1RH",
    "wof:placetype":"postalcode"
},
  "geometry": {"coordinates":[-1.224331,52.984841],"type":"Point"}
}