{
  "type": "Feature",
  "properties": {
    "iso:country":"GB",
    "wof:name":"NG9 4BP",
    "wof:placetype":"postalcode"
},
  "geometry": {"coordinates":[-1.23414778138882,52.92580811488845],"type":"Point"}
}