{
  "type": "Feature",
  "properties": {
    "iso:country":"GB",
    "wof:name":"TN6 1JQ",
    "wof:placetype":"postalcode"
},
  "geometry": {"coordinates":[0.15269547301755,51.05179343114756],"type":"Point"}
}