{
  "type": "Feature",
  "properties": {
    "iso:country": "GB",
    "wof:name": "TN6 1JQ",
    "wof:placetype": "postalcode"
  },
  "geometry": {"coordinates":[0.152795,51.051789],"type":"Point"}
}
