{
  "type": "Feature",
  "properties": {
    "iso:country":"GB",
    "wof:name":"RH1 3QA",
    "wof:placetype":"postalcode"
},
  "geometry": {"coordinates":[-0.14440315479218,51.25781931458653],"type":"Point"}
}