{
  "type": "Feature",
  "properties": {
    "iso:country": "GB",
    "wof:name": "EX32 8QJ",
    "wof:placetype": "postalcode"
  },
  "geometry": {"coordinates":[-4.042719,51.072716],"type":"Point"}
}
