{
  "type": "Feature",
  "properties": {
    "iso:country":"GB",
    "wof:name":"SG5 3NZ",
    "wof:placetype":"postalcode"
},
  "geometry": {"coordinates":[-0.36598907399987,52.00248458447227],"type":"Point"}
}