{
  "type": "Feature",
  "properties": {
    "iso:country": "GB",
    "wof:name": "BN24 6SQ",
    "wof:placetype": "postalcode"
  },
  "geometry": {"coordinates":[0.36669,50.820307],"type":"Point"}
}
