{
  "type": "Feature",
  "properties": {
    "iso:country":"GB",
    "wof:name":"BA2 5AD",
    "wof:placetype":"postalcode"
},
  "geometry": {"coordinates":[-2.34869359346904,51.36371853486452],"type":"Point"}
}