{
  "type": "Feature",
  "properties": {
    "iso:country":"GB",
    "wof:name":"BN2 4TJ",
    "wof:placetype":"postalcode"
},
  "geometry": {"coordinates":[-0.10937399940185,50.84689101237558],"type":"Point"}
}