{
  "type": "Feature",
  "properties": {
    "iso:country":"GB",
    "wof:name":"AB12 5FX",
    "wof:placetype":"postalcode"
},
  "geometry": {"coordinates":[-2.24820964728334,57.0956247698435],"type":"Point"}
}