{
  "type": "Feature",
  "properties": {
    "iso:country": "GB",
    "wof:name": "AB12 5FX",
    "wof:placetype": "postalcode"
  },
  "geometry": {"coordinates":[-2.24821,57.095625],"type":"Point"}
}
