{
  "type": "Feature",
  "properties": {
    "date:inception_lower": "1996-06-01",
    "date:inception_upper": "1996-06-01",
    "iso:country": "GB",
    "wof:name": "AB12 5FX",
    "wof:placetype": "postalcode"
  },
  "geometry": {"coordinates":[-2.24821,57.095625],"type":"Point"}
}
