{
  "type": "Feature",
  "properties": {
    "iso:country":"GB",
    "wof:name":"LE1 1PG",
    "wof:placetype":"postalcode"
},
  "geometry": {"coordinates":[-1.12494194998547,52.6325897442348],"type":"Point"}
}