{
  "type": "Feature",
  "properties": {
    "iso:country":"GB",
    "wof:name":"LU2 7PL",
    "wof:placetype":"postalcode"
},
  "geometry": {"coordinates":[-0.41701984535851,51.88806200751459],"type":"Point"}
}