{
  "type": "Feature",
  "properties": {
    "iso:country": "GB",
    "wof:name": "IP3 0DW",
    "wof:placetype": "postalcode"
  },
  "geometry": {"coordinates":[1.166167,52.050674],"type":"Point"}
}
