{
  "type": "Feature",
  "properties": {
    "iso:country":"GB",
    "wof:name":"IP3 0DW",
    "wof:placetype":"postalcode"
},
  "geometry": {"coordinates":[1.1661674514036,52.05067353634431],"type":"Point"}
}