{
  "type": "Feature",
  "properties": {
    "iso:country":"GB",
    "wof:name":"TW10 7SJ",
    "wof:placetype":"postalcode"
},
  "geometry": {"coordinates":[-0.3209471842669,51.43958926474036],"type":"Point"}
}