{
  "type": "Feature",
  "properties": {
    "iso:country": "GB",
    "wof:name": "TW10 7SJ",
    "wof:placetype": "postalcode"
  },
  "geometry": {"coordinates":[-0.320947,51.439589],"type":"Point"}
}
