{
  "type": "Feature",
  "properties": {
    "date:inception_lower": "1980-01-01",
    "date:inception_upper": "1980-01-01",
    "iso:country": "GB",
    "wof:name": "TW10 7SJ",
    "wof:placetype": "postalcode"
  },
  "geometry": {"coordinates":[-0.320947,51.439589],"type":"Point"}
}
