{
  "type": "Feature",
  "properties": {
    "iso:country":"GB",
    "wof:name":"NE25 9AN",
    "wof:placetype":"postalcode"
},
  "geometry": {"coordinates":[-1.46811201823015,55.04491499583479],"type":"Point"}
}