{
  "type": "Feature",
  "properties": {
    "date:inception_lower":"1995-07-01",
    "date:inception_upper":"1995-07-31",
    "iso:country":"GB",
    "wof:name":"DL3 0GR",
    "wof:placetype":"postalcode"
},
  "geometry": {"coordinates":[-1.563056,54.540186],"type":"Point"}
}