{
  "type": "Feature",
  "properties": {
    "iso:country": "GB",
    "wof:name": "DL3 0GR",
    "wof:placetype": "postalcode"
  },
  "geometry": {"coordinates":[-1.563056,54.540186],"type":"Point"}
}
