{
  "type": "Feature",
  "properties": {
    "iso:country":"GB",
    "wof:name":"DL3 0GR",
    "wof:placetype":"postalcode"
},
  "geometry": {"coordinates":[-1.56305625494507,54.54018554021348],"type":"Point"}
}