{
  "type": "Feature",
  "properties": {
    "iso:country":"GB",
    "wof:name":"ST8 7DR",
    "wof:placetype":"postalcode"
},
  "geometry": {"coordinates":[-2.1631286002745,53.12502407910203],"type":"Point"}
}