{
  "type": "Feature",
  "properties": {
    "iso:country": "GB",
    "wof:name": "ST5 2RY",
    "wof:placetype": "postalcode"
  },
  "geometry": {"coordinates":[-2.230102,53.012558],"type":"Point"}
}
