{
  "type": "Feature",
  "properties": {
    "iso:country":"GB",
    "wof:name":"L20 2EH",
    "wof:placetype":"postalcode"
},
  "geometry": {"coordinates":[-2.98349385486427,53.44278340853072],"type":"Point"}
}