{
  "type": "Feature",
  "properties": {
    "iso:country": "GB",
    "wof:name": "E9 9DL",
    "wof:placetype": "postalcode"
  },
  "geometry": {"coordinates":[-0.060392,51.532726],"type":"Point"}
}
