{
  "type": "Feature",
  "properties": {
    "date:inception_lower": "2013-08-01",
    "date:inception_upper": "2013-08-01",
    "iso:country": "GB",
    "wof:name": "TA24 8QS",
    "wof:placetype": "postalcode"
  },
  "geometry": {"coordinates":[-3.591922,51.212164],"type":"Point"}
}
