{
  "type": "Feature",
  "properties": {
    "date:inception_lower": "1981-06-01",
    "date:inception_upper": "1981-06-01",
    "iso:country": "GB",
    "wof:name": "WV6 7RH",
    "wof:placetype": "postalcode"
  },
  "geometry": {"coordinates":[-2.192039,52.589537],"type":"Point"}
}
