{
  "type": "Feature",
  "properties": {
    "iso:country":"GB",
    "wof:name":"WV6 7RH",
    "wof:placetype":"postalcode"
},
  "geometry": {"coordinates":[-2.19203893246895,52.5895365376198],"type":"Point"}
}