{
  "type": "Feature",
  "properties": {
    "iso:country": "GB",
    "wof:name": "PO33 3EW",
    "wof:placetype": "postalcode"
  },
  "geometry": {"coordinates":[-1.172016,50.717701],"type":"Point"}
}
