{
  "type": "Feature",
  "properties": {
    "iso:country":"GB",
    "wof:name":"PO33 3EW",
    "wof:placetype":"postalcode"
},
  "geometry": {"coordinates":[-1.17202657634676,50.71772154299448],"type":"Point"}
}