{
  "type": "Feature",
  "properties": {
    "iso:country": "GB",
    "wof:name": "IV44 8RD",
    "wof:placetype": "postalcode"
  },
  "geometry": {"coordinates":[-5.858275,57.106439],"type":"Point"}
}
