{
  "type": "Feature",
  "properties": {
    "iso:country":"GB",
    "wof:name":"LE67 9PU",
    "wof:placetype":"postalcode"
},
  "geometry": {"coordinates":[-1.30529327766442,52.70068650675807],"type":"Point"}
}