{
  "type": "Feature",
  "properties": {
    "iso:country": "GB",
    "wof:name": "LE67 9PU",
    "wof:placetype": "postalcode"
  },
  "geometry": {"coordinates":[-1.305293,52.700687],"type":"Point"}
}
