{
  "type": "Feature",
  "properties": {
    "iso:country":"GB",
    "wof:name":"TN33 0EF",
    "wof:placetype":"postalcode"
},
  "geometry": {"coordinates":[0.48408386802576,50.91815007131119],"type":"Point"}
}