{
  "type": "Feature",
  "properties": {
    "date:inception_lower": "2015-09-01",
    "date:inception_upper": "2015-09-01",
    "iso:country": "GB",
    "wof:name": "TR16 4FA",
    "wof:placetype": "postalcode"
  },
  "geometry": {"coordinates":[-5.233834,50.244672],"type":"Point"}
}
