{
  "type": "Feature",
  "properties": {
    "iso:country":"GB",
    "wof:name":"TR16 4FA",
    "wof:placetype":"postalcode"
},
  "geometry": {"coordinates":[-5.233649559799,50.24474014139665],"type":"Point"}
}