{
  "type": "Feature",
  "properties": {
    "iso:country":"GB",
    "wof:name":"LL57 2LA",
    "wof:placetype":"postalcode"
},
  "geometry": {"coordinates":[-4.14919223412624,53.2197848693816],"type":"Point"}
}