{
  "type": "Feature",
  "properties": {
    "iso:country":"GB",
    "wof:name":"SA12 8UP",
    "wof:placetype":"postalcode"
},
  "geometry": {"coordinates":[-3.80148433786844,51.61985104705868],"type":"Point"}
}