{
  "type": "Feature",
  "properties": {
    "date:inception_lower": "1999-06-01",
    "date:inception_upper": "1999-06-01",
    "iso:country": "GB",
    "wof:name": "CH48 5BU",
    "wof:placetype": "postalcode"
  },
  "geometry": {"coordinates":[-3.183409,53.375286],"type":"Point"}
}
