{
  "type": "Feature",
  "properties": {
    "iso:country":"GB",
    "wof:name":"SO51 8EL",
    "wof:placetype":"postalcode"
},
  "geometry": {"coordinates":[-1.50163382832854,50.98870605555769],"type":"Point"}
}