{
  "type": "Feature",
  "properties": {
    "iso:country": "GB",
    "wof:name": "PR4 6WD",
    "wof:placetype": "postalcode"
  },
  "geometry": {"coordinates":[-2.831363,53.67545],"type":"Point"}
}
