{
  "type": "Feature",
  "properties": {
    "iso:country": "GB",
    "wof:name": "CF14 1AG",
    "wof:placetype": "postalcode"
  },
  "geometry": {"coordinates":[-3.219263,51.515566],"type":"Point"}
}
