{
  "type": "Feature",
  "properties": {
    "iso:country":"GB",
    "wof:name":"M32 8JR",
    "wof:placetype":"postalcode"
},
  "geometry": {"coordinates":[-2.30256147529916,53.44663881707597],"type":"Point"}
}