{
  "type": "Feature",
  "properties": {
    "iso:country":"GB",
    "wof:name":"IP31 1RS",
    "wof:placetype":"postalcode"
},
  "geometry": {"coordinates":[0.812331286639,52.33934010208255],"type":"Point"}
}