{
  "type": "Feature",
  "properties": {
    "iso:country":"GB",
    "wof:name":"TQ2 6HL",
    "wof:placetype":"postalcode"
},
  "geometry": {"coordinates":[-3.54714923143463,50.46457033577492],"type":"Point"}
}