{
  "type": "Feature",
  "properties": {
    "iso:country":"GB",
    "wof:name":"NW10 5YD",
    "wof:placetype":"postalcode"
},
  "geometry": {"coordinates":[-0.23934756382716,51.53536648502713],"type":"Point"}
}