{
  "type": "Feature",
  "properties": {
    "iso:country":"GB",
    "wof:name":"NE66 2LP",
    "wof:placetype":"postalcode"
},
  "geometry": {"coordinates":[-1.76597380709325,55.44726560300805],"type":"Point"}
}