{
  "type": "Feature",
  "properties": {
    "date:inception_lower": "1980-01-01",
    "date:inception_upper": "1980-01-01",
    "iso:country": "GB",
    "wof:name": "KT2 5BZ",
    "wof:placetype": "postalcode"
  },
  "geometry": {"coordinates":[-0.301939,51.418831],"type":"Point"}
}
