{
  "type": "Feature",
  "properties": {
    "iso:country":"GB",
    "wof:name":"SP4 7WD",
    "wof:placetype":"postalcode"
},
  "geometry": {"coordinates":[-1.76300371880947,51.17296742979927],"type":"Point"}
}