{
  "type": "Feature",
  "properties": {
    "iso:country": "GB",
    "wof:name": "SP4 7WD",
    "wof:placetype": "postalcode"
  },
  "geometry": {"coordinates":[-1.763004,51.172967],"type":"Point"}
}
