{
  "type": "Feature",
  "properties": {
    "iso:country":"GB",
    "wof:name":"DT2 7EX",
    "wof:placetype":"postalcode"
},
  "geometry": {"coordinates":[-2.29647937558428,50.74932819720127],"type":"Point"}
}