{
  "type": "Feature",
  "properties": {
    "date:inception_lower": "1980-01-01",
    "date:inception_upper": "1980-01-01",
    "iso:country": "GB",
    "wof:name": "NG20 8AF",
    "wof:placetype": "postalcode"
  },
  "geometry": {"coordinates":[-1.2118,53.204052],"type":"Point"}
}
