{
  "type": "Feature",
  "properties": {
    "iso:country":"GB",
    "wof:name":"NG20 8AF",
    "wof:placetype":"postalcode"
},
  "geometry": {"coordinates":[-1.21178644741478,53.20404261120059],"type":"Point"}
}