{
  "type": "Feature",
  "properties": {
    "iso:country": "GB",
    "wof:name": "SS11 7QL",
    "wof:placetype": "postalcode"
  },
  "geometry": {"coordinates":[0.565893,51.63098],"type":"Point"}
}
