{
  "type": "Feature",
  "properties": {
    "iso:country":"GB",
    "wof:name":"SS11 7QL",
    "wof:placetype":"postalcode"
},
  "geometry": {"coordinates":[0.56589306411461,51.63097984482356],"type":"Point"}
}