{
  "type": "Feature",
  "properties": {
    "date:inception_lower":"1980-01-01",
    "date:inception_upper":"1980-01-31",
    "iso:country":"GB",
    "wof:name":"SS11 7QL",
    "wof:placetype":"postalcode"
},
  "geometry": {"coordinates":[0.565893,51.63098],"type":"Point"}
}