{
  "type": "Feature",
  "properties": {
    "iso:country": "GB",
    "wof:name": "OX15 0PJ",
    "wof:placetype": "postalcode"
  },
  "geometry": {"coordinates":[-1.389749,51.981729],"type":"Point"}
}
