{
  "type": "Feature",
  "properties": {
    "date:inception_lower":"1991-01-01",
    "date:inception_upper":"1991-01-31",
    "iso:country":"GB",
    "wof:name":"OX15 0PJ",
    "wof:placetype":"postalcode"
},
  "geometry": {"coordinates":[-1.389749,51.981729],"type":"Point"}
}