{
  "type": "Feature",
  "properties": {
    "iso:country":"GB",
    "wof:name":"NW4 4BB",
    "wof:placetype":"postalcode"
},
  "geometry": {"coordinates":[-0.22604878839831,51.58849973021927],"type":"Point"}
}