{
  "type": "Feature",
  "properties": {
    "iso:country":"GB",
    "wof:name":"SE15 3AT",
    "wof:placetype":"postalcode"
},
  "geometry": {"coordinates":[-0.0504963932918,51.45715664110023],"type":"Point"}
}