{
  "type": "Feature",
  "properties": {
    "date:inception_lower":"2019-02-01",
    "date:inception_upper":"2019-02-28",
    "iso:country":"GB",
    "wof:name":"LA14 4QT",
    "wof:placetype":"postalcode"
},
  "geometry": {"coordinates":[-3.228448,54.145004],"type":"Point"}
}