{
  "type": "Feature",
  "properties": {
    "iso:country": "GB",
    "wof:name": "LA14 4QT",
    "wof:placetype": "postalcode"
  },
  "geometry": {"coordinates":[-3.228448,54.145004],"type":"Point"}
}
