{
  "type": "Feature",
  "properties": {
    "iso:country":"GB",
    "wof:name":"LA14 4QT",
    "wof:placetype":"postalcode"
},
  "geometry": {"coordinates":[-3.23254785915523,54.15203606932356],"type":"Point"}
}