{
  "type": "Feature",
  "properties": {
    "iso:country": "GB",
    "wof:name": "SL3 8PW",
    "wof:placetype": "postalcode"
  },
  "geometry": {"coordinates":[-0.542773,51.495619],"type":"Point"}
}
