{
  "type": "Feature",
  "properties": {
    "iso:country":"GB",
    "wof:name":"SL3 8PW",
    "wof:placetype":"postalcode"
},
  "geometry": {"coordinates":[-0.54277263041649,51.49561915882396],"type":"Point"}
}