{
  "type": "Feature",
  "properties": {
    "date:inception_lower": "1980-01-01",
    "date:inception_upper": "1980-01-01",
    "iso:country": "GB",
    "wof:name": "OL1 4NJ",
    "wof:placetype": "postalcode"
  },
  "geometry": {"coordinates":[-2.090961,53.552143],"type":"Point"}
}
