{
  "type": "Feature",
  "properties": {
    "iso:country": "GB",
    "wof:name": "SM1 2BZ",
    "wof:placetype": "postalcode"
  },
  "geometry": {"coordinates":[-0.204488,51.373197],"type":"Point"}
}
