{
  "type": "Feature",
  "properties": {
    "iso:country":"GB",
    "wof:name":"SM1 2BZ",
    "wof:placetype":"postalcode"
},
  "geometry": {"coordinates":[-0.20442460660513,51.37324162844384],"type":"Point"}
}