{
  "type": "Feature",
  "properties": {
    "iso:country":"GB",
    "wof:name":"NP7 5RP",
    "wof:placetype":"postalcode"
},
  "geometry": {"coordinates":[-3.0108334963604,51.82628065093022],"type":"Point"}
}