{
  "type": "Feature",
  "properties": {
    "iso:country": "GB",
    "wof:name": "SP8 5PR",
    "wof:placetype": "postalcode"
  },
  "geometry": {"coordinates":[-2.313569,51.063739],"type":"Point"}
}
