{
  "type": "Feature",
  "properties": {
    "date:inception_lower": "1980-01-01",
    "date:inception_upper": "1980-01-01",
    "iso:country": "GB",
    "wof:name": "SP8 5PR",
    "wof:placetype": "postalcode"
  },
  "geometry": {"coordinates":[-2.313569,51.063739],"type":"Point"}
}
