{
  "type": "Feature",
  "properties": {
    "iso:country":"GB",
    "wof:name":"SP8 5PR",
    "wof:placetype":"postalcode"
},
  "geometry": {"coordinates":[-2.3135687640065,51.06373902651048],"type":"Point"}
}