{
  "type": "Feature",
  "properties": {
    "iso:country": "GB",
    "wof:name": "IV10 8SS",
    "wof:placetype": "postalcode"
  },
  "geometry": {"coordinates":[-4.112602,57.580114],"type":"Point"}
}
