{
  "type": "Feature",
  "properties": {
    "iso:country":"GB",
    "wof:name":"IV10 8SS",
    "wof:placetype":"postalcode"
},
  "geometry": {"coordinates":[-4.11260186880209,57.5801143695504],"type":"Point"}
}