{
  "type": "Feature",
  "properties": {
    "iso:country":"GB",
    "wof:name":"PL9 0DQ",
    "wof:placetype":"postalcode"
},
  "geometry": {"coordinates":[-4.07302137236855,50.33876984170143],"type":"Point"}
}