{
  "type": "Feature",
  "properties": {
    "iso:country": "GB",
    "wof:name": "PL9 0DQ",
    "wof:placetype": "postalcode"
  },
  "geometry": {"coordinates":[-4.073021,50.33877],"type":"Point"}
}
