{
  "type": "Feature",
  "properties": {
    "iso:country": "GB",
    "wof:name": "OL5 0EX",
    "wof:placetype": "postalcode"
  },
  "geometry": {"coordinates":[-2.046274,53.517266],"type":"Point"}
}
