{
  "type": "Feature",
  "properties": {
    "iso:country":"GB",
    "wof:name":"PL3 6LQ",
    "wof:placetype":"postalcode"
},
  "geometry": {"coordinates":[-4.11443428337905,50.38519025670409],"type":"Point"}
}