{
  "type": "Feature",
  "properties": {
    "date:inception_lower": "1980-01-01",
    "date:inception_upper": "1980-01-01",
    "iso:country": "GB",
    "wof:name": "PL3 6LQ",
    "wof:placetype": "postalcode"
  },
  "geometry": {"coordinates":[-4.114434,50.38519],"type":"Point"}
}
