{
  "type": "Feature",
  "properties": {
    "iso:country":"GB",
    "wof:name":"SN13 9LU",
    "wof:placetype":"postalcode"
},
  "geometry": {"coordinates":[-2.19834412419603,51.4316149966535],"type":"Point"}
}