{
  "type": "Feature",
  "properties": {
    "date:inception_lower": "1980-01-01",
    "date:inception_upper": "1980-01-01",
    "iso:country": "GB",
    "wof:name": "NR18 9PZ",
    "wof:placetype": "postalcode"
  },
  "geometry": {"coordinates":[1.059867,52.577757],"type":"Point"}
}
