{
  "type": "Feature",
  "properties": {
    "iso:country":"GB",
    "wof:name":"MK16 8LS",
    "wof:placetype":"postalcode"
},
  "geometry": {"coordinates":[-0.79997247629705,52.16182037632706],"type":"Point"}
}