{
  "type": "Feature",
  "properties": {
    "iso:country": "GB",
    "wof:name": "DN5 8LP",
    "wof:placetype": "postalcode"
  },
  "geometry": {"coordinates":[-1.173974,53.532465],"type":"Point"}
}
