{
  "type": "Feature",
  "properties": {
    "iso:country":"GB",
    "wof:name":"NR12 8XX",
    "wof:placetype":"postalcode"
},
  "geometry": {"coordinates":[1.48255711698903,52.7146959867167],"type":"Point"}
}