{
  "type": "Feature",
  "properties": {
    "iso:country": "GB",
    "wof:name": "NR12 8XX",
    "wof:placetype": "postalcode"
  },
  "geometry": {"coordinates":[1.482579,52.714723],"type":"Point"}
}
