{
  "type": "Feature",
  "properties": {
    "date:inception_lower": "1980-01-01",
    "date:inception_upper": "1980-01-01",
    "iso:country": "GB",
    "wof:name": "NR12 8XX",
    "wof:placetype": "postalcode"
  },
  "geometry": {"coordinates":[1.483981,52.715401],"type":"Point"}
}
