{
  "type": "Feature",
  "properties": {
    "iso:country":"GB",
    "wof:name":"CF14 7AG",
    "wof:placetype":"postalcode"
},
  "geometry": {"coordinates":[-3.22406770269208,51.51951737231023],"type":"Point"}
}