{
  "type": "Feature",
  "properties": {
    "date:inception_lower":"1990-07-01",
    "date:inception_upper":"1990-07-31",
    "iso:country":"GB",
    "wof:name":"TR10 8AT",
    "wof:placetype":"postalcode"
},
  "geometry": {"coordinates":[-5.100641,50.169761],"type":"Point"}
}