{
  "type": "Feature",
  "properties": {
    "iso:country":"GB",
    "wof:name":"DD5 1DW",
    "wof:placetype":"postalcode"
},
  "geometry": {"coordinates":[-2.88328912238579,56.46824608180849],"type":"Point"}
}