{
  "type": "Feature",
  "properties": {
    "iso:country": "GB",
    "wof:name": "LN1 2GH",
    "wof:placetype": "postalcode"
  },
  "geometry": {"coordinates":[-0.633783,53.262935],"type":"Point"}
}
