{
  "type": "Feature",
  "properties": {
    "iso:country":"GB",
    "wof:name":"N14 6RS",
    "wof:placetype":"postalcode"
},
  "geometry": {"coordinates":[-0.12396227547328,51.63185625520988],"type":"Point"}
}