{
  "type": "Feature",
  "properties": {
    "iso:country": "GB",
    "wof:name": "IV18 0SB",
    "wof:placetype": "postalcode"
  },
  "geometry": {"coordinates":[-4.169837,57.694844],"type":"Point"}
}
