{
  "type": "Feature",
  "properties": {
    "iso:country":"GB",
    "wof:name":"IV18 0SB",
    "wof:placetype":"postalcode"
},
  "geometry": {"coordinates":[-4.16983682039503,57.69484447374455],"type":"Point"}
}