{
  "type": "Feature",
  "properties": {
    "iso:country": "GB",
    "wof:name": "NN6 8BP",
    "wof:placetype": "postalcode"
  },
  "geometry": {"coordinates":[-0.963149,52.342452],"type":"Point"}
}
