{
  "type": "Feature",
  "properties": {
    "iso:country":"GB",
    "wof:name":"NN6 8BP",
    "wof:placetype":"postalcode"
},
  "geometry": {"coordinates":[-0.96314950935161,52.34245244606662],"type":"Point"}
}