{
  "type": "Feature",
  "properties": {
    "date:inception_lower": "1980-01-01",
    "date:inception_upper": "1980-01-01",
    "iso:country": "GB",
    "wof:name": "NG24 1ST",
    "wof:placetype": "postalcode"
  },
  "geometry": {"coordinates":[-0.797222,53.06963],"type":"Point"}
}
