{
  "type": "Feature",
  "properties": {
    "iso:country":"GB",
    "wof:name":"YO12 4LY",
    "wof:placetype":"postalcode"
},
  "geometry": {"coordinates":[-0.42650118503029,54.24147655978616],"type":"Point"}
}