{
  "type": "Feature",
  "properties": {
    "iso:country": "GB",
    "wof:name": "YO12 4LY",
    "wof:placetype": "postalcode"
  },
  "geometry": {"coordinates":[-0.426501,54.241477],"type":"Point"}
}
