{
  "type": "Feature",
  "properties": {
    "iso:country":"GB",
    "wof:name":"AL7 1DA",
    "wof:placetype":"postalcode"
},
  "geometry": {"coordinates":[-0.19255625133176,51.81079717840871],"type":"Point"}
}