{
  "type": "Feature",
  "properties": {
    "iso:country":"GB",
    "wof:name":"IG8 9AW",
    "wof:placetype":"postalcode"
},
  "geometry": {"coordinates":[0.02631756063542,51.60271358141425],"type":"Point"}
}