{
  "type": "Feature",
  "properties": {
    "iso:country": "GB",
    "wof:name": "IG8 9AW",
    "wof:placetype": "postalcode"
  },
  "geometry": {"coordinates":[0.026318,51.602714],"type":"Point"}
}
