{
  "type": "Feature",
  "properties": {
    "date:inception_lower": "1980-01-01",
    "date:inception_upper": "1980-01-01",
    "iso:country": "GB",
    "wof:name": "EX36 3NU",
    "wof:placetype": "postalcode"
  },
  "geometry": {"coordinates":[-3.652473,51.023963],"type":"Point"}
}
