{
  "type": "Feature",
  "properties": {
    "iso:country":"GB",
    "wof:name":"EX36 3NU",
    "wof:placetype":"postalcode"
},
  "geometry": {"coordinates":[-3.65248010586886,51.02385896669848],"type":"Point"}
}