{
  "type": "Feature",
  "properties": {
    "iso:country":"GB",
    "wof:name":"TS17 9AN",
    "wof:placetype":"postalcode"
},
  "geometry": {"coordinates":[-1.28240830146762,54.54599165658194],"type":"Point"}
}