{
  "type": "Feature",
  "properties": {
    "iso:country": "GB",
    "wof:name": "TS17 9AN",
    "wof:placetype": "postalcode"
  },
  "geometry": {"coordinates":[-1.282408,54.545992],"type":"Point"}
}
