{
  "type": "Feature",
  "properties": {
    "date:inception_lower": "1980-01-01",
    "date:inception_upper": "1980-01-01",
    "iso:country": "GB",
    "wof:name": "NG3 7DT",
    "wof:placetype": "postalcode"
  },
  "geometry": {"coordinates":[-1.117802,52.959036],"type":"Point"}
}
