{
  "type": "Feature",
  "properties": {
    "iso:country":"GB",
    "wof:name":"KT21 2QT",
    "wof:placetype":"postalcode"
},
  "geometry": {"coordinates":[-0.30450004006332,51.31088537060514],"type":"Point"}
}