{
  "type": "Feature",
  "properties": {
    "iso:country": "GB",
    "wof:name": "CF48 2PT",
    "wof:placetype": "postalcode"
  },
  "geometry": {"coordinates":[-3.404551,51.761318],"type":"Point"}
}
