{
  "type": "Feature",
  "properties": {
    "iso:country":"GB",
    "wof:name":"SO50 9LL",
    "wof:placetype":"postalcode"
},
  "geometry": {"coordinates":[-1.37386713344749,50.96612305475276],"type":"Point"}
}