{
  "type": "Feature",
  "properties": {
    "iso:country": "GB",
    "wof:name": "SO50 9LL",
    "wof:placetype": "postalcode"
  },
  "geometry": {"coordinates":[-1.373857,50.966115],"type":"Point"}
}
