{
  "type": "Feature",
  "properties": {
    "date:inception_lower": "1980-01-01",
    "date:inception_upper": "1980-01-01",
    "iso:country": "GB",
    "wof:name": "BN1 6RR",
    "wof:placetype": "postalcode"
  },
  "geometry": {"coordinates":[-0.151676,50.8484],"type":"Point"}
}
