{
  "type": "Feature",
  "properties": {
    "iso:country":"GB",
    "wof:name":"BN1 6RR",
    "wof:placetype":"postalcode"
},
  "geometry": {"coordinates":[-0.15141863704429,50.8484280578887],"type":"Point"}
}