{
  "type": "Feature",
  "properties": {
    "iso:country":"GB",
    "wof:name":"KY16 9ET",
    "wof:placetype":"postalcode"
},
  "geometry": {"coordinates":[-2.79885149217626,56.33734013176458],"type":"Point"}
}