{
  "type": "Feature",
  "properties": {
    "date:inception_lower": "1980-01-01",
    "date:inception_upper": "1980-01-01",
    "iso:country": "GB",
    "wof:name": "KY16 9ET",
    "wof:placetype": "postalcode"
  },
  "geometry": {"coordinates":[-2.798851,56.33734],"type":"Point"}
}
