{
  "type": "Feature",
  "properties": {
    "iso:country":"GB",
    "wof:name":"DN5 7JH",
    "wof:placetype":"postalcode"
},
  "geometry": {"coordinates":[-1.18790692499059,53.51079864347507],"type":"Point"}
}