{
  "type": "Feature",
  "properties": {
    "iso:country":"GB",
    "wof:name":"TF2 6PH",
    "wof:placetype":"postalcode"
},
  "geometry": {"coordinates":[-2.46070748994029,52.71242295020804],"type":"Point"}
}