{
  "type": "Feature",
  "properties": {
    "iso:country": "GB",
    "wof:name": "BS16 7NJ",
    "wof:placetype": "postalcode"
  },
  "geometry": {"coordinates":[-2.466779,51.500968],"type":"Point"}
}
