{
  "type": "Feature",
  "properties": {
    "iso:country":"GB",
    "wof:name":"NG6 7AP",
    "wof:placetype":"postalcode"
},
  "geometry": {"coordinates":[-1.21558689805094,52.99144495793473],"type":"Point"}
}