{
  "type": "Feature",
  "properties": {
    "iso:country":"GB",
    "wof:name":"SO53 3BB",
    "wof:placetype":"postalcode"
},
  "geometry": {"coordinates":[-1.37884259832571,50.97639194044712],"type":"Point"}
}