{
  "type": "Feature",
  "properties": {
    "iso:country":"GB",
    "wof:name":"M6 8DA",
    "wof:placetype":"postalcode"
},
  "geometry": {"coordinates":[-2.31091913852248,53.48802732994152],"type":"Point"}
}