{
  "type": "Feature",
  "properties": {
    "iso:country": "GB",
    "wof:name": "LE16 9UZ",
    "wof:placetype": "postalcode"
  },
  "geometry": {"coordinates":[-0.966716,52.47787],"type":"Point"}
}
