{
  "type": "Feature",
  "properties": {
    "iso:country":"GB",
    "wof:name":"TN5 6LS",
    "wof:placetype":"postalcode"
},
  "geometry": {"coordinates":[0.34504369114294,51.05636540299233],"type":"Point"}
}