{
  "type": "Feature",
  "properties": {
    "iso:country":"GB",
    "wof:name":"BA21 5DN",
    "wof:placetype":"postalcode"
},
  "geometry": {"coordinates":[-2.61392768833624,50.94678839077932],"type":"Point"}
}