{
  "type": "Feature",
  "properties": {
    "iso:country":"GB",
    "wof:name":"TN9 1AW",
    "wof:placetype":"postalcode"
},
  "geometry": {"coordinates":[0.27312356517161,51.19410179338026],"type":"Point"}
}