{
  "type": "Feature",
  "properties": {
    "date:inception_lower": "1980-01-01",
    "date:inception_upper": "1980-01-01",
    "iso:country": "GB",
    "wof:name": "NG34 9EJ",
    "wof:placetype": "postalcode"
  },
  "geometry": {"coordinates":[-0.386782,53.046709],"type":"Point"}
}
