{
  "type": "Feature",
  "properties": {
    "iso:country":"GB",
    "wof:name":"NG34 9EJ",
    "wof:placetype":"postalcode"
},
  "geometry": {"coordinates":[-0.386787238839,53.04668547562135],"type":"Point"}
}