{
  "type": "Feature",
  "properties": {
    "iso:country":"GB",
    "wof:name":"BN44 3PU",
    "wof:placetype":"postalcode"
},
  "geometry": {"coordinates":[-0.32720039894681,50.87905825165245],"type":"Point"}
}