{
  "type": "Feature",
  "properties": {
    "iso:country":"GB",
    "wof:name":"NG34 9HN",
    "wof:placetype":"postalcode"
},
  "geometry": {"coordinates":[-0.39189476389321,53.05014388261015],"type":"Point"}
}