{
  "type": "Feature",
  "properties": {
    "date:inception_lower": "2014-07-01",
    "date:inception_upper": "2014-07-01",
    "iso:country": "GB",
    "wof:name": "TA3 7DL",
    "wof:placetype": "postalcode"
  },
  "geometry": {"coordinates":[-3.122371,50.966433],"type":"Point"}
}
