{
  "type": "Feature",
  "properties": {
    "iso:country":"GB",
    "wof:name":"TA3 7DL",
    "wof:placetype":"postalcode"
},
  "geometry": {"coordinates":[-3.12237118815704,50.96643340718825],"type":"Point"}
}