{
  "type": "Feature",
  "properties": {
    "iso:country":"GB",
    "wof:name":"DL15 9RL",
    "wof:placetype":"postalcode"
},
  "geometry": {"coordinates":[-1.75080934994942,54.7214677023951],"type":"Point"}
}