{
  "type": "Feature",
  "properties": {
    "iso:country":"GB",
    "wof:name":"SE5 8HZ",
    "wof:placetype":"postalcode"
},
  "geometry": {"coordinates":[-0.08439005824926,51.47069175668899],"type":"Point"}
}