{
  "type": "Feature",
  "properties": {
    "date:inception_lower": "1980-01-01",
    "date:inception_upper": "1980-01-01",
    "iso:country": "GB",
    "wof:name": "LE6 0FR",
    "wof:placetype": "postalcode"
  },
  "geometry": {"coordinates":[-1.232096,52.667593],"type":"Point"}
}
