{
  "type": "Feature",
  "properties": {
    "iso:country":"GB",
    "wof:name":"LE6 0FR",
    "wof:placetype":"postalcode"
},
  "geometry": {"coordinates":[-1.23260812956318,52.66745247255593],"type":"Point"}
}