{
  "type": "Feature",
  "properties": {
    "iso:country":"GB",
    "wof:name":"SN6 7BE",
    "wof:placetype":"postalcode"
},
  "geometry": {"coordinates":[-1.70960169843204,51.63044079499537],"type":"Point"}
}