{
  "type": "Feature",
  "properties": {
    "date:inception_lower": "1980-01-01",
    "date:inception_upper": "1980-01-01",
    "iso:country": "GB",
    "wof:name": "SK9 5HP",
    "wof:placetype": "postalcode"
  },
  "geometry": {"coordinates":[-2.237634,53.32446],"type":"Point"}
}
