{
  "type": "Feature",
  "properties": {
    "iso:country": "GB",
    "wof:name": "CV22 7PY",
    "wof:placetype": "postalcode"
  },
  "geometry": {"coordinates":[-1.282049,52.361335],"type":"Point"}
}
