{
  "type": "Feature",
  "properties": {
    "iso:country":"GB",
    "wof:name":"W11 2EG",
    "wof:placetype":"postalcode"
},
  "geometry": {"coordinates":[-0.20920423450215,51.51462333575012],"type":"Point"}
}