{
  "type": "Feature",
  "properties": {
    "date:inception_lower": "1980-01-01",
    "date:inception_upper": "1980-01-01",
    "iso:country": "GB",
    "wof:name": "CF43 4AY",
    "wof:placetype": "postalcode"
  },
  "geometry": {"coordinates":[-3.480257,51.671181],"type":"Point"}
}
