{
  "type": "Feature",
  "properties": {
    "date:inception_lower": "2009-10-01",
    "date:inception_upper": "2009-10-01",
    "iso:country": "GB",
    "wof:name": "S1 4RL",
    "wof:placetype": "postalcode"
  },
  "geometry": {"coordinates":[-1.470939,53.374213],"type":"Point"}
}
