{
  "type": "Feature",
  "properties": {
    "iso:country":"GB",
    "wof:name":"LS13 3LD",
    "wof:placetype":"postalcode"
},
  "geometry": {"coordinates":[-1.63941399597074,53.81526755177276],"type":"Point"}
}