{
  "type": "Feature",
  "properties": {
    "iso:country":"GB",
    "wof:name":"RM15 4AH",
    "wof:placetype":"postalcode"
},
  "geometry": {"coordinates":[0.25776490152795,51.49819057429017],"type":"Point"}
}