{
  "type": "Feature",
  "properties": {
    "iso:country":"GB",
    "wof:name":"E17 3DP",
    "wof:placetype":"postalcode"
},
  "geometry": {"coordinates":[-0.01141817521591,51.58811664538823],"type":"Point"}
}