{
  "type": "Feature",
  "properties": {
    "date:inception_lower": "1980-01-01",
    "date:inception_upper": "1980-01-01",
    "iso:country": "GB",
    "wof:name": "E17 3DP",
    "wof:placetype": "postalcode"
  },
  "geometry": {"coordinates":[-0.011453,51.588362],"type":"Point"}
}
