{
  "type": "Feature",
  "properties": {
    "iso:country":"GB",
    "wof:name":"NE5 2XD",
    "wof:placetype":"postalcode"
},
  "geometry": {"coordinates":[-1.68667534635606,54.98904234448271],"type":"Point"}
}