{
  "type": "Feature",
  "properties": {
    "iso:country":"GB",
    "wof:name":"M45 8JX",
    "wof:placetype":"postalcode"
},
  "geometry": {"coordinates":[-2.2733187936608,53.55617049707827],"type":"Point"}
}