{
  "type": "Feature",
  "properties": {
    "date:inception_lower": "1980-01-01",
    "date:inception_upper": "1980-01-01",
    "iso:country": "GB",
    "wof:name": "HR9 7EW",
    "wof:placetype": "postalcode"
  },
  "geometry": {"coordinates":[-2.580373,51.920128],"type":"Point"}
}
