{
  "type": "Feature",
  "properties": {
    "iso:country": "GB",
    "wof:name": "HR9 7EW",
    "wof:placetype": "postalcode"
  },
  "geometry": {"coordinates":[-2.580373,51.920128],"type":"Point"}
}
