{
  "type": "Feature",
  "properties": {
    "iso:country":"GB",
    "wof:name":"CA11 8AX",
    "wof:placetype":"postalcode"
},
  "geometry": {"coordinates":[-2.74165711331684,54.66859661979802],"type":"Point"}
}