{
  "type": "Feature",
  "properties": {
    "iso:country": "GB",
    "wof:name": "CA11 8AX",
    "wof:placetype": "postalcode"
  },
  "geometry": {"coordinates":[-2.741657,54.668597],"type":"Point"}
}
