{
  "type": "Feature",
  "properties": {
    "iso:country": "GB",
    "wof:name": "CV22 7QZ",
    "wof:placetype": "postalcode"
  },
  "geometry": {"coordinates":[-1.294078,52.35293],"type":"Point"}
}
