{
  "type": "Feature",
  "properties": {
    "iso:country": "GB",
    "wof:name": "B43 6AF",
    "wof:placetype": "postalcode"
  },
  "geometry": {"coordinates":[-1.940353,52.545403],"type":"Point"}
}
