{
  "type": "Feature",
  "properties": {
    "iso:country":"GB",
    "wof:name":"BS35 4NL",
    "wof:placetype":"postalcode"
},
  "geometry": {"coordinates":[-2.65667461995077,51.56116601502023],"type":"Point"}
}