{
  "type": "Feature",
  "properties": {
    "date:inception_lower": "1990-02-01",
    "date:inception_upper": "1990-02-01",
    "iso:country": "GB",
    "wof:name": "TA6 4XT",
    "wof:placetype": "postalcode"
  },
  "geometry": {"coordinates":[-2.974327,51.134207],"type":"Point"}
}
