{
  "type": "Feature",
  "properties": {
    "iso:country":"GB",
    "wof:name":"DG10 9ST",
    "wof:placetype":"postalcode"
},
  "geometry": {"coordinates":[-3.44883825840628,55.32651350106612],"type":"Point"}
}