{
  "type": "Feature",
  "properties": {
    "iso:country": "GB",
    "wof:name": "BS15 4BT",
    "wof:placetype": "postalcode"
  },
  "geometry": {"coordinates":[-2.498032,51.463085],"type":"Point"}
}
