{
  "type": "Feature",
  "properties": {
    "iso:country":"GB",
    "wof:name":"TF3 1NU",
    "wof:placetype":"postalcode"
},
  "geometry": {"coordinates":[-2.43572382678902,52.64881628677499],"type":"Point"}
}