{
  "type": "Feature",
  "properties": {
    "date:inception_lower": "1988-03-01",
    "date:inception_upper": "1988-03-01",
    "iso:country": "GB",
    "wof:name": "TF3 1NU",
    "wof:placetype": "postalcode"
  },
  "geometry": {"coordinates":[-2.435724,52.648816],"type":"Point"}
}
