{
  "type": "Feature",
  "properties": {
    "iso:country":"GB",
    "wof:name":"IV2 5NQ",
    "wof:placetype":"postalcode"
},
  "geometry": {"coordinates":[-4.16198050516217,57.47490691281234],"type":"Point"}
}