{
  "type": "Feature",
  "properties": {
    "iso:country":"GB",
    "wof:name":"TS17 8FT",
    "wof:placetype":"postalcode"
},
  "geometry": {"coordinates":[-1.29316023658116,54.54730413021757],"type":"Point"}
}