{
  "type": "Feature",
  "properties": {
    "date:inception_lower":"2002-07-01",
    "date:inception_upper":"2002-07-31",
    "iso:country":"GB",
    "wof:name":"IV63 6XA",
    "wof:placetype":"postalcode"
},
  "geometry": {"coordinates":[-4.484786,57.328206],"type":"Point"}
}