{
  "type": "Feature",
  "properties": {
    "iso:country":"GB",
    "wof:name":"SW5 0NA",
    "wof:placetype":"postalcode"
},
  "geometry": {"coordinates":[-0.18746373567887,51.49409231360229],"type":"Point"}
}