{
  "type": "Feature",
  "properties": {
    "iso:country":"GB",
    "wof:name":"TQ14 9RA",
    "wof:placetype":"postalcode"
},
  "geometry": {"coordinates":[-3.54065627166318,50.55259609826791],"type":"Point"}
}