{
  "type": "Feature",
  "properties": {
    "iso:country": "GB",
    "wof:name": "NG18 3BL",
    "wof:placetype": "postalcode"
  },
  "geometry": {"coordinates":[-1.175424,53.139102],"type":"Point"}
}
