{
  "type": "Feature",
  "properties": {
    "iso:country":"GB",
    "wof:name":"NG18 3BL",
    "wof:placetype":"postalcode"
},
  "geometry": {"coordinates":[-1.17542372005399,53.13910159753261],"type":"Point"}
}