{
  "type": "Feature",
  "properties": {
    "iso:country": "GB",
    "wof:name": "PE15 0GS",
    "wof:placetype": "postalcode"
  },
  "geometry": {"coordinates":[0.083067,52.509927],"type":"Point"}
}
