{
  "type": "Feature",
  "properties": {
    "iso:country":"GB",
    "wof:name":"PE15 0GS",
    "wof:placetype":"postalcode"
},
  "geometry": {"coordinates":[0.08304703118168,52.50990876134351],"type":"Point"}
}