{
  "type": "Feature",
  "properties": {
    "iso:country": "GB",
    "wof:name": "NR35 2UA",
    "wof:placetype": "postalcode"
  },
  "geometry": {"coordinates":[1.418353,52.452269],"type":"Point"}
}
