{
  "type": "Feature",
  "properties": {
    "date:inception_lower": "1980-01-01",
    "date:inception_upper": "1980-01-01",
    "iso:country": "GB",
    "wof:name": "B77 5NA",
    "wof:placetype": "postalcode"
  },
  "geometry": {"coordinates":[-1.662783,52.602913],"type":"Point"}
}
