{
  "type": "Feature",
  "properties": {
    "iso:country":"GB",
    "wof:name":"B77 5NA",
    "wof:placetype":"postalcode"
},
  "geometry": {"coordinates":[-1.6628656008516,52.60283315974235],"type":"Point"}
}