{
  "type": "Feature",
  "properties": {
    "date:inception_lower": "2006-07-01",
    "date:inception_upper": "2006-07-01",
    "iso:country": "GB",
    "wof:name": "NG2 5BR",
    "wof:placetype": "postalcode"
  },
  "geometry": {"coordinates":[-1.129271,52.938696],"type":"Point"}
}
