{
  "type": "Feature",
  "properties": {
    "iso:country":"GB",
    "wof:name":"NG2 5BR",
    "wof:placetype":"postalcode"
},
  "geometry": {"coordinates":[-1.12927115454967,52.9386962770653],"type":"Point"}
}