{
  "type": "Feature",
  "properties": {
    "iso:country":"GB",
    "wof:name":"RG41 5NT",
    "wof:placetype":"postalcode"
},
  "geometry": {"coordinates":[-0.87320215378532,51.42922069909257],"type":"Point"}
}