{
  "type": "Feature",
  "properties": {
    "iso:country": "GB",
    "wof:name": "RG41 5NT",
    "wof:placetype": "postalcode"
  },
  "geometry": {"coordinates":[-0.873202,51.429221],"type":"Point"}
}
