{
  "type": "Feature",
  "properties": {
    "iso:country":"GB",
    "wof:name":"G15 7UD",
    "wof:placetype":"postalcode"
},
  "geometry": {"coordinates":[-4.37549609566479,55.91465184248176],"type":"Point"}
}