{
  "type": "Feature",
  "properties": {
    "iso:country":"GB",
    "wof:name":"WF14 9DL",
    "wof:placetype":"postalcode"
},
  "geometry": {"coordinates":[-1.71151307455277,53.67994041000217],"type":"Point"}
}