{
  "type": "Feature",
  "properties": {
    "date:inception_lower": "2003-09-01",
    "date:inception_upper": "2003-09-01",
    "iso:country": "GB",
    "wof:name": "BA13 4LS",
    "wof:placetype": "postalcode"
  },
  "geometry": {"coordinates":[-2.199579,51.276907],"type":"Point"}
}
