{
  "type": "Feature",
  "properties": {
    "iso:country": "GB",
    "wof:name": "BA13 4LS",
    "wof:placetype": "postalcode"
  },
  "geometry": {"coordinates":[-2.199024,51.276939],"type":"Point"}
}
