{
  "type": "Feature",
  "properties": {
    "iso:country":"GB",
    "wof:name":"BA13 4LS",
    "wof:placetype":"postalcode"
},
  "geometry": {"coordinates":[-2.19902407197983,51.27693860679494],"type":"Point"}
}