{
  "type": "Feature",
  "properties": {
    "date:inception_lower": "1999-12-01",
    "date:inception_upper": "1999-12-01",
    "iso:country": "GB",
    "wof:name": "BN17 6UU",
    "wof:placetype": "postalcode"
  },
  "geometry": {"coordinates":[-0.517629,50.819715],"type":"Point"}
}
