{
  "type": "Feature",
  "properties": {
    "iso:country": "GB",
    "wof:name": "BN17 6UU",
    "wof:placetype": "postalcode"
  },
  "geometry": {"coordinates":[-0.517629,50.819715],"type":"Point"}
}
