{
  "type": "Feature",
  "properties": {
    "date:inception_lower": "1980-01-01",
    "date:inception_upper": "1980-01-01",
    "iso:country": "GB",
    "wof:name": "NN3 2HJ",
    "wof:placetype": "postalcode"
  },
  "geometry": {"coordinates":[-0.862852,52.252369],"type":"Point"}
}
