{
  "type": "Feature",
  "properties": {
    "date:inception_lower": "2017-05-01",
    "date:inception_upper": "2017-05-01",
    "iso:country": "GB",
    "wof:name": "TR8 5FN",
    "wof:placetype": "postalcode"
  },
  "geometry": {"coordinates":[-5.151494,50.379824],"type":"Point"}
}
