{
  "type": "Feature",
  "properties": {
    "iso:country": "GB",
    "wof:name": "GL4 4XG",
    "wof:placetype": "postalcode"
  },
  "geometry": {"coordinates":[-2.215095,51.845058],"type":"Point"}
}
