{
  "type": "Feature",
  "properties": {
    "iso:country":"GB",
    "wof:name":"GL4 4XG",
    "wof:placetype":"postalcode"
},
  "geometry": {"coordinates":[-2.2150953850533,51.84505773598296],"type":"Point"}
}