{
  "type": "Feature",
  "properties": {
    "iso:country":"GB",
    "wof:name":"NN5 6AP",
    "wof:placetype":"postalcode"
},
  "geometry": {"coordinates":[-0.93211300573034,52.24631793598569],"type":"Point"}
}