{
  "type": "Feature",
  "properties": {
    "iso:country":"GB",
    "wof:name":"WA15 9EN",
    "wof:placetype":"postalcode"
},
  "geometry": {"coordinates":[-2.34568295910727,53.38363762142342],"type":"Point"}
}