{
  "type": "Feature",
  "properties": {
    "iso:country":"GB",
    "wof:name":"BA21 3PS",
    "wof:placetype":"postalcode"
},
  "geometry": {"coordinates":[-2.66554860711129,50.96215234080093],"type":"Point"}
}