{
  "type": "Feature",
  "properties": {
    "date:inception_lower": "2003-06-01",
    "date:inception_upper": "2003-06-01",
    "iso:country": "GB",
    "wof:name": "RM20 4DP",
    "wof:placetype": "postalcode"
  },
  "geometry": {"coordinates":[0.292888,51.478309],"type":"Point"}
}
