{
  "type": "Feature",
  "properties": {
    "iso:country": "GB",
    "wof:name": "NP10 9LJ",
    "wof:placetype": "postalcode"
  },
  "geometry": {"coordinates":[-3.066779,51.592853],"type":"Point"}
}
