{
  "type": "Feature",
  "properties": {
    "iso:country": "GB",
    "wof:name": "KY12 9TZ",
    "wof:placetype": "postalcode"
  },
  "geometry": {"coordinates":[-3.57301,56.110565],"type":"Point"}
}
