{
  "type": "Feature",
  "properties": {
    "date:inception_lower": "2019-04-01",
    "date:inception_upper": "2019-04-01",
    "iso:country": "GB",
    "wof:name": "KY12 9TZ",
    "wof:placetype": "postalcode"
  },
  "geometry": {"coordinates":[-3.573058,56.110556],"type":"Point"}
}
