{
  "type": "Feature",
  "properties": {
    "iso:country":"GB",
    "wof:name":"S20 4HH",
    "wof:placetype":"postalcode"
},
  "geometry": {"coordinates":[-1.35086528647282,53.32324727339162],"type":"Point"}
}