{
  "type": "Feature",
  "properties": {
    "iso:country":"GB",
    "wof:name":"LE3 2YB",
    "wof:placetype":"postalcode"
},
  "geometry": {"coordinates":[-1.17858782859097,52.60442149009721],"type":"Point"}
}