{
  "type": "Feature",
  "properties": {
    "date:inception_lower":"2005-08-01",
    "date:inception_upper":"2005-08-31",
    "iso:country":"GB",
    "wof:name":"LE3 2YB",
    "wof:placetype":"postalcode"
},
  "geometry": {"coordinates":[-1.178588,52.604421],"type":"Point"}
}