{
  "type": "Feature",
  "properties": {
    "iso:country":"GB",
    "wof:name":"DY5 2JQ",
    "wof:placetype":"postalcode"
},
  "geometry": {"coordinates":[-2.10663274350014,52.47409745259787],"type":"Point"}
}