{
  "type": "Feature",
  "properties": {
    "date:inception_lower": "2022-03-01",
    "date:inception_upper": "2022-03-01",
    "iso:country": "GB",
    "wof:name": "LE4 6AA",
    "wof:placetype": "postalcode"
  },
  "geometry": {"coordinates":[-1.108765,52.656123],"type":"Point"}
}
