{
  "type": "Feature",
  "properties": {
    "iso:country":"GB",
    "wof:name":"PL13 2LD",
    "wof:placetype":"postalcode"
},
  "geometry": {"coordinates":[-4.52845111676568,50.3674688578408],"type":"Point"}
}