{
  "type": "Feature",
  "properties": {
    "iso:country":"GB",
    "wof:name":"MK3 5JF",
    "wof:placetype":"postalcode"
},
  "geometry": {"coordinates":[-0.76112803884617,51.98995879710553],"type":"Point"}
}