{
  "type": "Feature",
  "properties": {
    "iso:country": "GB",
    "wof:name": "PE11 2LL",
    "wof:placetype": "postalcode"
  },
  "geometry": {"coordinates":[-0.137152,52.791428],"type":"Point"}
}
