{
  "type": "Feature",
  "properties": {
    "iso:country":"GB",
    "wof:name":"PE11 2LL",
    "wof:placetype":"postalcode"
},
  "geometry": {"coordinates":[-0.1371517341514,52.79142763910566],"type":"Point"}
}