{
  "type": "Feature",
  "properties": {
    "iso:country":"GB",
    "wof:name":"BH8 9ER",
    "wof:placetype":"postalcode"
},
  "geometry": {"coordinates":[-1.86175860455164,50.74030773432087],"type":"Point"}
}