{
  "type": "Feature",
  "properties": {
    "iso:country": "GB",
    "wof:name": "SK11 6JS",
    "wof:placetype": "postalcode"
  },
  "geometry": {"coordinates":[-2.12357,53.259141],"type":"Point"}
}
