{
  "type": "Feature",
  "properties": {
    "iso:country": "GB",
    "wof:name": "SK11 7BJ",
    "wof:placetype": "postalcode"
  },
  "geometry": {"coordinates":[-2.11805,53.257726],"type":"Point"}
}
