{
  "type": "Feature",
  "properties": {
    "iso:country":"GB",
    "wof:name":"SK11 7BJ",
    "wof:placetype":"postalcode"
},
  "geometry": {"coordinates":[-2.11804984095032,53.25772628774995],"type":"Point"}
}