{
  "type": "Feature",
  "properties": {
    "iso:country":"GB",
    "wof:name":"EH17 8UT",
    "wof:placetype":"postalcode"
},
  "geometry": {"coordinates":[-3.15041363073177,55.89559372585781],"type":"Point"}
}