{
  "type": "Feature",
  "properties": {
    "date:inception_lower": "2007-07-01",
    "date:inception_upper": "2007-07-01",
    "iso:country": "GB",
    "wof:name": "CF81 9BF",
    "wof:placetype": "postalcode"
  },
  "geometry": {"coordinates":[-3.217665,51.686879],"type":"Point"}
}
