{
  "type": "Feature",
  "properties": {
    "iso:country":"GB",
    "wof:name":"CF81 9BF",
    "wof:placetype":"postalcode"
},
  "geometry": {"coordinates":[-3.2177438174876,51.6869289806042],"type":"Point"}
}