{
  "type": "Feature",
  "properties": {
    "iso:country":"GB",
    "wof:name":"W1H 4NX",
    "wof:placetype":"postalcode"
},
  "geometry": {"coordinates":[-0.16489931707569,51.51931602667098],"type":"Point"}
}