{
  "type": "Feature",
  "properties": {
    "iso:country":"GB",
    "wof:name":"G67 2QE",
    "wof:placetype":"postalcode"
},
  "geometry": {"coordinates":[-3.9769493308272,55.94567345301469],"type":"Point"}
}