{
  "type": "Feature",
  "properties": {
    "iso:country": "GB",
    "wof:name": "TR8 5DX",
    "wof:placetype": "postalcode"
  },
  "geometry": {"coordinates":[-4.970994,50.367594],"type":"Point"}
}
