{
  "type": "Feature",
  "properties": {
    "date:inception_lower":"2013-07-01",
    "date:inception_upper":"2013-07-31",
    "iso:country":"GB",
    "wof:name":"E20 1AS",
    "wof:placetype":"postalcode"
},
  "geometry": {"coordinates":[-0.005575,51.548135],"type":"Point"}
}