{
  "type": "Feature",
  "properties": {
    "iso:country":"GB",
    "wof:name":"E20 1AS",
    "wof:placetype":"postalcode"
},
  "geometry": {"coordinates":[-0.00557543058161,51.54813534628391],"type":"Point"}
}