{
  "type": "Feature",
  "properties": {
    "iso:country":"GB",
    "wof:name":"CF23 6LL",
    "wof:placetype":"postalcode"
},
  "geometry": {"coordinates":[-3.16837512264222,51.51780150731619],"type":"Point"}
}