{
  "type": "Feature",
  "properties": {
    "date:inception_lower": "2019-01-01",
    "date:inception_upper": "2019-01-01",
    "iso:country": "GB",
    "wof:name": "S60 8BX",
    "wof:placetype": "postalcode"
  },
  "geometry": {"coordinates":[-1.364979,53.383872],"type":"Point"}
}
