{
  "type": "Feature",
  "properties": {
    "date:inception_lower":"2002-09-01",
    "date:inception_upper":"2002-09-30",
    "iso:country":"GB",
    "wof:name":"CH41 9AH",
    "wof:placetype":"postalcode"
},
  "geometry": {"coordinates":[-3.013726,53.37958],"type":"Point"}
}