{
  "type": "Feature",
  "properties": {
    "iso:country": "GB",
    "wof:name": "CH41 9AH",
    "wof:placetype": "postalcode"
  },
  "geometry": {"coordinates":[-3.013726,53.37958],"type":"Point"}
}
