{
  "type": "Feature",
  "properties": {
    "iso:country": "GB",
    "wof:name": "G46 6TA",
    "wof:placetype": "postalcode"
  },
  "geometry": {"coordinates":[-4.309244,55.785952],"type":"Point"}
}
