{
  "type": "Feature",
  "properties": {
    "date:inception_lower": "1980-01-01",
    "date:inception_upper": "1980-01-01",
    "iso:country": "GB",
    "wof:name": "OX11 8DG",
    "wof:placetype": "postalcode"
  },
  "geometry": {"coordinates":[-1.237652,51.605713],"type":"Point"}
}
