{
  "type": "Feature",
  "properties": {
    "date:inception_lower": "1980-01-01",
    "date:inception_upper": "1980-01-01",
    "iso:country": "GB",
    "wof:name": "IP3 9BN",
    "wof:placetype": "postalcode"
  },
  "geometry": {"coordinates":[1.184276,52.047253],"type":"Point"}
}
