{
  "type": "Feature",
  "properties": {
    "iso:country": "GB",
    "wof:name": "ML3 7GL",
    "wof:placetype": "postalcode"
  },
  "geometry": {"coordinates":[-3.999774,55.763398],"type":"Point"}
}
