{
  "type": "Feature",
  "properties": {
    "date:inception_lower": "2016-08-01",
    "date:inception_upper": "2016-08-01",
    "iso:country": "GB",
    "wof:name": "ML3 7GL",
    "wof:placetype": "postalcode"
  },
  "geometry": {"coordinates":[-3.999774,55.763398],"type":"Point"}
}
