{
  "type": "Feature",
  "properties": {
    "iso:country":"GB",
    "wof:name":"E10 6JT",
    "wof:placetype":"postalcode"
},
  "geometry": {"coordinates":[-0.00734840419798,51.56961283180481],"type":"Point"}
}