{
  "type": "Feature",
  "properties": {
    "date:inception_lower": "1980-01-01",
    "date:inception_upper": "1980-01-01",
    "iso:country": "GB",
    "wof:name": "E10 6JT",
    "wof:placetype": "postalcode"
  },
  "geometry": {"coordinates":[-0.006823,51.569444],"type":"Point"}
}
