{
  "type": "Feature",
  "properties": {
    "iso:country": "GB",
    "wof:name": "E10 6JT",
    "wof:placetype": "postalcode"
  },
  "geometry": {"coordinates":[-0.006823,51.569444],"type":"Point"}
}
