{
  "type": "Feature",
  "properties": {
    "iso:country":"GB",
    "wof:name":"TS3 0HP",
    "wof:placetype":"postalcode"
},
  "geometry": {"coordinates":[-1.1912767180555,54.55239997510846],"type":"Point"}
}