{
  "type": "Feature",
  "properties": {
    "iso:country":"GB",
    "wof:name":"LD3 7JE",
    "wof:placetype":"postalcode"
},
  "geometry": {"coordinates":[-3.28323765601014,51.89702931312369],"type":"Point"}
}