{
  "type": "Feature",
  "properties": {
    "date:inception_lower":"1980-10-01",
    "date:inception_upper":"1980-10-31",
    "iso:country":"GB",
    "wof:name":"G52 4PX",
    "wof:placetype":"postalcode"
},
  "geometry": {"coordinates":[-4.364789,55.857313],"type":"Point"}
}