{
  "type": "Feature",
  "properties": {
    "iso:country":"GB",
    "wof:name":"WR1 3PD",
    "wof:placetype":"postalcode"
},
  "geometry": {"coordinates":[-2.22608078005554,52.19377663747191],"type":"Point"}
}