{
  "type": "Feature",
  "properties": {
    "date:inception_lower": "2012-05-01",
    "date:inception_upper": "2012-05-01",
    "iso:country": "GB",
    "wof:name": "WR1 3PD",
    "wof:placetype": "postalcode"
  },
  "geometry": {"coordinates":[-2.226081,52.193777],"type":"Point"}
}
