{
  "type": "Feature",
  "properties": {
    "date:inception_lower":"1980-01-01",
    "date:inception_upper":"1980-01-31",
    "iso:country":"GB",
    "wof:name":"EH32 0PJ",
    "wof:placetype":"postalcode"
},
  "geometry": {"coordinates":[-2.827763,55.992628],"type":"Point"}
}