{
  "type": "Feature",
  "properties": {
    "iso:country":"GB",
    "wof:name":"EH32 0PJ",
    "wof:placetype":"postalcode"
},
  "geometry": {"coordinates":[-2.82776329743187,55.99262848887047],"type":"Point"}
}