{
  "type": "Feature",
  "properties": {
    "iso:country": "GB",
    "wof:name": "RM13 8AU",
    "wof:placetype": "postalcode"
  },
  "geometry": {"coordinates":[0.183953,51.528341],"type":"Point"}
}
