{
  "type": "Feature",
  "properties": {
    "iso:country":"GB",
    "wof:name":"RM13 8AU",
    "wof:placetype":"postalcode"
},
  "geometry": {"coordinates":[0.18393870563756,51.52833021684426],"type":"Point"}
}