{
  "type": "Feature",
  "properties": {
    "date:inception_lower": "1980-01-01",
    "date:inception_upper": "1980-01-01",
    "iso:country": "GB",
    "wof:name": "RM13 8AU",
    "wof:placetype": "postalcode"
  },
  "geometry": {"coordinates":[0.183953,51.528341],"type":"Point"}
}
