{
  "type": "Feature",
  "properties": {
    "iso:country":"GB",
    "wof:name":"GU27 3PS",
    "wof:placetype":"postalcode"
},
  "geometry": {"coordinates":[-0.7457965900188,51.07318023592128],"type":"Point"}
}