{
  "type": "Feature",
  "properties": {
    "iso:country": "GB",
    "wof:name": "GU27 3PS",
    "wof:placetype": "postalcode"
  },
  "geometry": {"coordinates":[-0.745797,51.07318],"type":"Point"}
}
