{
  "type": "Feature",
  "properties": {
    "iso:country":"GB",
    "wof:name":"AL1 5QB",
    "wof:placetype":"postalcode"
},
  "geometry": {"coordinates":[-0.3097347014364,51.74073921667543],"type":"Point"}
}