{
  "type": "Feature",
  "properties": {
    "iso:country":"GB",
    "wof:name":"HA2 6DZ",
    "wof:placetype":"postalcode"
},
  "geometry": {"coordinates":[-0.36123133071473,51.58667935203319],"type":"Point"}
}