{
  "type": "Feature",
  "properties": {
    "iso:country": "GB",
    "wof:name": "NG11 8SN",
    "wof:placetype": "postalcode"
  },
  "geometry": {"coordinates":[-1.193952,52.905918],"type":"Point"}
}
