{
  "type": "Feature",
  "properties": {
    "iso:country":"GB",
    "wof:name":"NG11 8SN",
    "wof:placetype":"postalcode"
},
  "geometry": {"coordinates":[-1.19395216642737,52.90591817920355],"type":"Point"}
}