{
  "type": "Feature",
  "properties": {
    "iso:country": "GB",
    "wof:name": "NN12 6FH",
    "wof:placetype": "postalcode"
  },
  "geometry": {"coordinates":[-1.00297,52.133429],"type":"Point"}
}
