{
  "type": "Feature",
  "properties": {
    "iso:country":"GB",
    "wof:name":"NN12 6FH",
    "wof:placetype":"postalcode"
},
  "geometry": {"coordinates":[-1.002970243667,52.13342943093409],"type":"Point"}
}