{
  "type": "Feature",
  "properties": {
    "iso:country": "GB",
    "wof:name": "PL6 5UR",
    "wof:placetype": "postalcode"
  },
  "geometry": {"coordinates":[-4.10193,50.398908],"type":"Point"}
}
