{
  "type": "Feature",
  "properties": {
    "iso:country": "GB",
    "wof:name": "CH5 3GB",
    "wof:placetype": "postalcode"
  },
  "geometry": {"coordinates":[-3.054121,53.18093],"type":"Point"}
}
