{
  "type": "Feature",
  "properties": {
    "iso:country":"GB",
    "wof:name":"CH5 3GB",
    "wof:placetype":"postalcode"
},
  "geometry": {"coordinates":[-3.05412068596878,53.18092995037578],"type":"Point"}
}