{
  "type": "Feature",
  "properties": {
    "date:inception_lower": "1995-07-01",
    "date:inception_upper": "1995-07-01",
    "iso:country": "GB",
    "wof:name": "RG30 2QQ",
    "wof:placetype": "postalcode"
  },
  "geometry": {"coordinates":[-1.011004,51.457251],"type":"Point"}
}
