{
  "type": "Feature",
  "properties": {
    "date:inception_lower": "2022-02-01",
    "date:inception_upper": "2022-02-01",
    "iso:country": "GB",
    "wof:name": "SK5 8BW",
    "wof:placetype": "postalcode"
  },
  "geometry": {"coordinates":[-2.132538,53.425177],"type":"Point"}
}
