{
  "type": "Feature",
  "properties": {
    "iso:country":"GB",
    "wof:name":"SA73 3AL",
    "wof:placetype":"postalcode"
},
  "geometry": {"coordinates":[-5.0367864508963,51.71263323067586],"type":"Point"}
}