{
  "type": "Feature",
  "properties": {
    "iso:country":"GB",
    "wof:name":"BL1 6ND",
    "wof:placetype":"postalcode"
},
  "geometry": {"coordinates":[-2.45479973487317,53.59759343853143],"type":"Point"}
}