{
  "type": "Feature",
  "properties": {
    "iso:country": "GB",
    "wof:name": "AB15 8FF",
    "wof:placetype": "postalcode"
  },
  "geometry": {"coordinates":[-2.156539,57.132136],"type":"Point"}
}
