{
  "type": "Feature",
  "properties": {
    "date:inception_lower": "2002-08-01",
    "date:inception_upper": "2002-08-01",
    "iso:country": "GB",
    "wof:name": "AB15 8FF",
    "wof:placetype": "postalcode"
  },
  "geometry": {"coordinates":[-2.156539,57.132136],"type":"Point"}
}
