{
  "type": "Feature",
  "properties": {
    "iso:country":"GB",
    "wof:name":"B69 2HF",
    "wof:placetype":"postalcode"
},
  "geometry": {"coordinates":[-2.03596645683103,52.5098752086153],"type":"Point"}
}