{
  "type": "Feature",
  "properties": {
    "iso:country": "GB",
    "wof:name": "B69 2HF",
    "wof:placetype": "postalcode"
  },
  "geometry": {"coordinates":[-2.035966,52.509875],"type":"Point"}
}
