{
  "type": "Feature",
  "properties": {
    "iso:country": "GB",
    "wof:name": "RH12 3XR",
    "wof:placetype": "postalcode"
  },
  "geometry": {"coordinates":[-0.348395,51.090675],"type":"Point"}
}
