{
  "type": "Feature",
  "properties": {
    "iso:country":"GB",
    "wof:name":"BS28 4EL",
    "wof:placetype":"postalcode"
},
  "geometry": {"coordinates":[-2.81079818039362,51.22867341921736],"type":"Point"}
}