{
  "type": "Feature",
  "properties": {
    "iso:country":"GB",
    "wof:name":"GL16 8EN",
    "wof:placetype":"postalcode"
},
  "geometry": {"coordinates":[-2.6232791704691,51.79599444566598],"type":"Point"}
}