{
  "type": "Feature",
  "properties": {
    "iso:country": "GB",
    "wof:name": "TN40 2PR",
    "wof:placetype": "postalcode"
  },
  "geometry": {"coordinates":[0.503287,50.848296],"type":"Point"}
}
