{
  "type": "Feature",
  "properties": {
    "date:inception_lower": "1980-01-01",
    "date:inception_upper": "1980-01-01",
    "iso:country": "GB",
    "wof:name": "KA10 7BG",
    "wof:placetype": "postalcode"
  },
  "geometry": {"coordinates":[-4.636339,55.54872],"type":"Point"}
}
