{
  "type": "Feature",
  "properties": {
    "iso:country":"GB",
    "wof:name":"KA10 7BG",
    "wof:placetype":"postalcode"
},
  "geometry": {"coordinates":[-4.63633883793458,55.54872047837283],"type":"Point"}
}