{
  "type": "Feature",
  "properties": {
    "iso:country":"GB",
    "wof:name":"B33 9BS",
    "wof:placetype":"postalcode"
},
  "geometry": {"coordinates":[-1.80009967753568,52.4878847959022],"type":"Point"}
}