{
  "type": "Feature",
  "properties": {
    "iso:country":"GB",
    "wof:name":"PO4 8LR",
    "wof:placetype":"postalcode"
},
  "geometry": {"coordinates":[-1.04034344511636,50.79548980813823],"type":"Point"}
}