{
  "type": "Feature",
  "properties": {
    "date:inception_lower": "1980-01-01",
    "date:inception_upper": "1980-01-01",
    "iso:country": "GB",
    "wof:name": "PO4 8LR",
    "wof:placetype": "postalcode"
  },
  "geometry": {"coordinates":[-1.040343,50.79549],"type":"Point"}
}
