{
  "type": "Feature",
  "properties": {
    "date:inception_lower": "1980-01-01",
    "date:inception_upper": "1980-01-01",
    "iso:country": "GB",
    "wof:name": "PH14 9SY",
    "wof:placetype": "postalcode"
  },
  "geometry": {"coordinates":[-3.201395,56.480768],"type":"Point"}
}
