{
  "type": "Feature",
  "properties": {
    "iso:country":"GB",
    "wof:name":"PH14 9SY",
    "wof:placetype":"postalcode"
},
  "geometry": {"coordinates":[-3.20139553563482,56.48076802664414],"type":"Point"}
}