{
  "type": "Feature",
  "properties": {
    "iso:country":"GB",
    "wof:name":"SA48 7JD",
    "wof:placetype":"postalcode"
},
  "geometry": {"coordinates":[-4.07881267829484,52.11791770288968],"type":"Point"}
}