{
  "type": "Feature",
  "properties": {
    "iso:country":"GB",
    "wof:name":"SW2 1QW",
    "wof:placetype":"postalcode"
},
  "geometry": {"coordinates":[-0.11953729257715,51.4556316000951],"type":"Point"}
}