{
  "type": "Feature",
  "properties": {
    "date:inception_lower": "2005-06-01",
    "date:inception_upper": "2005-06-01",
    "iso:country": "GB",
    "wof:name": "IG1 1NA",
    "wof:placetype": "postalcode"
  },
  "geometry": {"coordinates":[0.077598,51.560019],"type":"Point"}
}
