{
  "type": "Feature",
  "properties": {
    "iso:country":"GB",
    "wof:name":"IG1 1NA",
    "wof:placetype":"postalcode"
},
  "geometry": {"coordinates":[0.07759773409919,51.56001903562222],"type":"Point"}
}