{
  "type": "Feature",
  "properties": {
    "iso:country":"GB",
    "wof:name":"PO18 0FA",
    "wof:placetype":"postalcode"
},
  "geometry": {"coordinates":[-0.78238457073833,50.86928886144255],"type":"Point"}
}