{
  "type": "Feature",
  "properties": {
    "date:inception_lower": "1999-12-01",
    "date:inception_upper": "1999-12-01",
    "iso:country": "GB",
    "wof:name": "GU10 3QJ",
    "wof:placetype": "postalcode"
  },
  "geometry": {"coordinates":[-0.778379,51.201731],"type":"Point"}
}
