{
  "type": "Feature",
  "properties": {
    "iso:country": "GB",
    "wof:name": "ST14 8RZ",
    "wof:placetype": "postalcode"
  },
  "geometry": {"coordinates":[-1.937771,52.881019],"type":"Point"}
}
