{
  "type": "Feature",
  "properties": {
    "iso:country": "GB",
    "wof:name": "ST14 8RZ",
    "wof:placetype": "postalcode"
  },
  "geometry": {"coordinates":[-1.939402,52.881073],"type":"Point"}
}
