{
  "type": "Feature",
  "properties": {
    "date:inception_lower": "1989-04-01",
    "date:inception_upper": "1989-04-01",
    "iso:country": "GB",
    "wof:name": "DG5 4PP",
    "wof:placetype": "postalcode"
  },
  "geometry": {"coordinates":[-3.822874,54.929404],"type":"Point"}
}
