{
  "type": "Feature",
  "properties": {
    "iso:country":"GB",
    "wof:name":"B77 4AN",
    "wof:placetype":"postalcode"
},
  "geometry": {"coordinates":[-1.64919287795349,52.63797052429823],"type":"Point"}
}