{
  "type": "Feature",
  "properties": {
    "date:inception_lower": "2023-05-01",
    "date:inception_upper": "2023-05-01",
    "iso:country": "GB",
    "wof:name": "CB1 0AR",
    "wof:placetype": "postalcode"
  },
  "geometry": {"coordinates":[0.137208,52.192267],"type":"Point"}
}
