{
  "type": "Feature",
  "properties": {
    "date:inception_lower":"1980-01-01",
    "date:inception_upper":"1980-01-31",
    "iso:country":"GB",
    "wof:name":"BB7 4EZ",
    "wof:placetype":"postalcode"
},
  "geometry": {"coordinates":[-2.262386,53.934853],"type":"Point"}
}