{
  "type": "Feature",
  "properties": {
    "iso:country":"GB",
    "wof:name":"BB7 4EZ",
    "wof:placetype":"postalcode"
},
  "geometry": {"coordinates":[-2.26238606413492,53.93485309309367],"type":"Point"}
}