{
  "type": "Feature",
  "properties": {
    "iso:country": "GB",
    "wof:name": "BB7 4EZ",
    "wof:placetype": "postalcode"
  },
  "geometry": {"coordinates":[-2.262386,53.934853],"type":"Point"}
}
