{
  "type": "Feature",
  "properties": {
    "iso:country":"GB",
    "wof:name":"MK7 8AF",
    "wof:placetype":"postalcode"
},
  "geometry": {"coordinates":[-0.67816823510671,52.0197981977901],"type":"Point"}
}