{
  "type": "Feature",
  "properties": {
    "iso:country": "GB",
    "wof:name": "ST7 3FD",
    "wof:placetype": "postalcode"
  },
  "geometry": {"coordinates":[-2.250892,53.107054],"type":"Point"}
}
