{
  "type": "Feature",
  "properties": {
    "iso:country":"GB",
    "wof:name":"ST7 3FD",
    "wof:placetype":"postalcode"
},
  "geometry": {"coordinates":[-2.25089222369658,53.10703710391343],"type":"Point"}
}