{
  "type": "Feature",
  "properties": {
    "date:inception_lower": "1980-01-01",
    "date:inception_upper": "1980-01-01",
    "iso:country": "GB",
    "wof:name": "E18 1JA",
    "wof:placetype": "postalcode"
  },
  "geometry": {"coordinates":[0.035042,51.595989],"type":"Point"}
}
