{
  "type": "Feature",
  "properties": {
    "iso:country":"GB",
    "wof:name":"E18 1JA",
    "wof:placetype":"postalcode"
},
  "geometry": {"coordinates":[0.03504233203495,51.59598903245765],"type":"Point"}
}