{
  "type": "Feature",
  "properties": {
    "date:inception_lower": "1980-01-01",
    "date:inception_upper": "1980-01-01",
    "iso:country": "GB",
    "wof:name": "LL67 0HL",
    "wof:placetype": "postalcode"
  },
  "geometry": {"coordinates":[-4.452495,53.41118],"type":"Point"}
}
