{
  "type": "Feature",
  "properties": {
    "iso:country":"GB",
    "wof:name":"LL67 0HL",
    "wof:placetype":"postalcode"
},
  "geometry": {"coordinates":[-4.45249518672822,53.41118030885114],"type":"Point"}
}