{
  "type": "Feature",
  "properties": {
    "iso:country":"GB",
    "wof:name":"RM3 7NR",
    "wof:placetype":"postalcode"
},
  "geometry": {"coordinates":[0.20161234452221,51.59608480814875],"type":"Point"}
}