{
  "type": "Feature",
  "properties": {
    "iso:country":"GB",
    "wof:name":"NE5 1LA",
    "wof:placetype":"postalcode"
},
  "geometry": {"coordinates":[-1.71321324052369,54.99760868761251],"type":"Point"}
}