{
  "type": "Feature",
  "properties": {
    "iso:country":"GB",
    "wof:name":"BD9 6EF",
    "wof:placetype":"postalcode"
},
  "geometry": {"coordinates":[-1.80172384113711,53.80991097349254],"type":"Point"}
}