{
  "type": "Feature",
  "properties": {
    "iso:country":"GB",
    "wof:name":"KY8 6AB",
    "wof:placetype":"postalcode"
},
  "geometry": {"coordinates":[-2.95101228529729,56.21370455445333],"type":"Point"}
}