{
  "type": "Feature",
  "properties": {
    "iso:country":"GB",
    "wof:name":"DN7 5AS",
    "wof:placetype":"postalcode"
},
  "geometry": {"coordinates":[-1.02932385818057,53.60149003212901],"type":"Point"}
}