{
  "type": "Feature",
  "properties": {
    "date:inception_lower": "1980-01-01",
    "date:inception_upper": "1980-01-01",
    "iso:country": "GB",
    "wof:name": "KA15 1HP",
    "wof:placetype": "postalcode"
  },
  "geometry": {"coordinates":[-4.601179,55.729788],"type":"Point"}
}
