{
  "type": "Feature",
  "properties": {
    "date:inception_lower": "2018-10-01",
    "date:inception_upper": "2018-10-01",
    "iso:country": "GB",
    "wof:name": "NG19 7FJ",
    "wof:placetype": "postalcode"
  },
  "geometry": {"coordinates":[-1.253565,53.174162],"type":"Point"}
}
