{
  "type": "Feature",
  "properties": {
    "iso:country":"GB",
    "wof:name":"BA14 8AJ",
    "wof:placetype":"postalcode"
},
  "geometry": {"coordinates":[-2.20844144735222,51.32087405605733],"type":"Point"}
}