{
  "type": "Feature",
  "properties": {
    "iso:country": "GB",
    "wof:name": "BA14 8AJ",
    "wof:placetype": "postalcode"
  },
  "geometry": {"coordinates":[-2.208441,51.320874],"type":"Point"}
}
