{
  "type": "Feature",
  "properties": {
    "iso:country":"GB",
    "wof:name":"BS5 9RQ",
    "wof:placetype":"postalcode"
},
  "geometry": {"coordinates":[-2.55411163539757,51.45815771627203],"type":"Point"}
}