{
  "type": "Feature",
  "properties": {
    "iso:country":"GB",
    "wof:name":"TW2 6BH",
    "wof:placetype":"postalcode"
},
  "geometry": {"coordinates":[-0.37409965331944,51.44562601279138],"type":"Point"}
}