{
  "type": "Feature",
  "properties": {
    "date:inception_lower": "1985-04-01",
    "date:inception_upper": "1985-04-01",
    "iso:country": "GB",
    "wof:name": "SW6 1SP",
    "wof:placetype": "postalcode"
  },
  "geometry": {"coordinates":[-0.192523,51.483101],"type":"Point"}
}
