{
  "type": "Feature",
  "properties": {
    "iso:country": "GB",
    "wof:name": "SW6 1SP",
    "wof:placetype": "postalcode"
  },
  "geometry": {"coordinates":[-0.192523,51.483101],"type":"Point"}
}
