{
  "type": "Feature",
  "properties": {
    "iso:country":"GB",
    "wof:name":"SW6 1SP",
    "wof:placetype":"postalcode"
},
  "geometry": {"coordinates":[-0.19252276786459,51.48310065009642],"type":"Point"}
}