{
  "type": "Feature",
  "properties": {
    "date:inception_lower": "1985-04-01",
    "date:inception_upper": "1985-04-01",
    "iso:country": "GB",
    "wof:name": "NP4 5JR",
    "wof:placetype": "postalcode"
  },
  "geometry": {"coordinates":[-3.022196,51.681969],"type":"Point"}
}
