{
  "type": "Feature",
  "properties": {
    "iso:country":"GB",
    "wof:name":"LS12 2JP",
    "wof:placetype":"postalcode"
},
  "geometry": {"coordinates":[-1.61353482243854,53.80850894372667],"type":"Point"}
}