{
  "type": "Feature",
  "properties": {
    "iso:country":"GB",
    "wof:name":"M33 4ER",
    "wof:placetype":"postalcode"
},
  "geometry": {"coordinates":[-2.33787811342268,53.40802809826226],"type":"Point"}
}