{
  "type": "Feature",
  "properties": {
    "date:inception_lower": "1980-01-01",
    "date:inception_upper": "1980-01-01",
    "iso:country": "GB",
    "wof:name": "SW18 3EF",
    "wof:placetype": "postalcode"
  },
  "geometry": {"coordinates":[-0.188549,51.444174],"type":"Point"}
}
