{
  "type": "Feature",
  "properties": {
    "iso:country":"GB",
    "wof:name":"SW18 3EF",
    "wof:placetype":"postalcode"
},
  "geometry": {"coordinates":[-0.18854873565736,51.44417365013442],"type":"Point"}
}