{
  "type": "Feature",
  "properties": {
    "iso:country": "GB",
    "wof:name": "PE14 7LX",
    "wof:placetype": "postalcode"
  },
  "geometry": {"coordinates":[0.252946,52.743159],"type":"Point"}
}
