{
  "type": "Feature",
  "properties": {
    "iso:country":"GB",
    "wof:name":"PE14 7LX",
    "wof:placetype":"postalcode"
},
  "geometry": {"coordinates":[0.25293104347074,52.74313875006122],"type":"Point"}
}