{
  "type": "Feature",
  "properties": {
    "iso:country":"GB",
    "wof:name":"BA4 4FW",
    "wof:placetype":"postalcode"
},
  "geometry": {"coordinates":[-2.53615336428029,51.17925174926931],"type":"Point"}
}