{
  "type": "Feature",
  "properties": {
    "date:inception_lower":"2015-02-01",
    "date:inception_upper":"2015-02-28",
    "iso:country":"GB",
    "wof:name":"BA4 4FW",
    "wof:placetype":"postalcode"
},
  "geometry": {"coordinates":[-2.536153,51.179252],"type":"Point"}
}