{
  "type": "Feature",
  "properties": {
    "iso:country": "GB",
    "wof:name": "BA4 4FW",
    "wof:placetype": "postalcode"
  },
  "geometry": {"coordinates":[-2.536153,51.179252],"type":"Point"}
}
