{
  "type": "Feature",
  "properties": {
    "iso:country": "GB",
    "wof:name": "TS3 6JW",
    "wof:placetype": "postalcode"
  },
  "geometry": {"coordinates":[-1.207636,54.572244],"type":"Point"}
}
