{
  "type": "Feature",
  "properties": {
    "date:inception_lower":"1980-01-01",
    "date:inception_upper":"1980-01-31",
    "iso:country":"GB",
    "wof:name":"WF5 0HN",
    "wof:placetype":"postalcode"
},
  "geometry": {"coordinates":[-1.554082,53.669607],"type":"Point"}
}