{
  "type": "Feature",
  "properties": {
    "iso:country": "GB",
    "wof:name": "WF5 0HN",
    "wof:placetype": "postalcode"
  },
  "geometry": {"coordinates":[-1.554082,53.669607],"type":"Point"}
}
