{
  "type": "Feature",
  "properties": {
    "iso:country":"GB",
    "wof:name":"WF5 0HN",
    "wof:placetype":"postalcode"
},
  "geometry": {"coordinates":[-1.55408167684717,53.6696070178271],"type":"Point"}
}