{
  "type": "Feature",
  "properties": {
    "iso:country": "GB",
    "wof:name": "WS14 0LQ",
    "wof:placetype": "postalcode"
  },
  "geometry": {"coordinates":[-1.837121,52.620119],"type":"Point"}
}
