{
  "type": "Feature",
  "properties": {
    "iso:country":"GB",
    "wof:name":"LE67 8QD",
    "wof:placetype":"postalcode"
},
  "geometry": {"coordinates":[-1.38441659693917,52.75148395254742],"type":"Point"}
}