{
  "type": "Feature",
  "properties": {
    "date:inception_lower": "1992-08-01",
    "date:inception_upper": "1992-08-01",
    "iso:country": "GB",
    "wof:name": "LE67 8QD",
    "wof:placetype": "postalcode"
  },
  "geometry": {"coordinates":[-1.384408,52.751502],"type":"Point"}
}
