{
  "type": "Feature",
  "properties": {
    "iso:country":"GB",
    "wof:name":"LA4 6LN",
    "wof:placetype":"postalcode"
},
  "geometry": {"coordinates":[-2.83544374262542,54.07561758258921],"type":"Point"}
}