{
  "type": "Feature",
  "properties": {
    "date:inception_lower": "1995-01-01",
    "date:inception_upper": "1995-01-01",
    "iso:country": "GB",
    "wof:name": "DE55 3BL",
    "wof:placetype": "postalcode"
  },
  "geometry": {"coordinates":[-1.329813,53.095978],"type":"Point"}
}
