{
  "type": "Feature",
  "properties": {
    "iso:country":"GB",
    "wof:name":"HA4 0DT",
    "wof:placetype":"postalcode"
},
  "geometry": {"coordinates":[-0.40676214184205,51.56553627290823],"type":"Point"}
}