{
  "type": "Feature",
  "properties": {
    "iso:country": "GB",
    "wof:name": "PE25 9EP",
    "wof:placetype": "postalcode"
  },
  "geometry": {"coordinates":[0.335997,53.144378],"type":"Point"}
}
