{
  "type": "Feature",
  "properties": {
    "iso:country": "GB",
    "wof:name": "NP12 1WF",
    "wof:placetype": "postalcode"
  },
  "geometry": {"coordinates":[-3.202967,51.6681],"type":"Point"}
}
