{
  "type": "Feature",
  "properties": {
    "iso:country": "GB",
    "wof:name": "ZE1 0SY",
    "wof:placetype": "postalcode"
  },
  "geometry": {"coordinates":[-1.169054,60.150775],"type":"Point"}
}
