{
  "type": "Feature",
  "properties": {
    "iso:country":"GB",
    "wof:name":"CB24 9JB",
    "wof:placetype":"postalcode"
},
  "geometry": {"coordinates":[0.10908727023419,52.25157566532355],"type":"Point"}
}