{
  "type": "Feature",
  "properties": {
    "iso:country": "GB",
    "wof:name": "CA5 6EF",
    "wof:placetype": "postalcode"
  },
  "geometry": {"coordinates":[-3.017692,54.924607],"type":"Point"}
}
