{
  "type": "Feature",
  "properties": {
    "iso:country": "GB",
    "wof:name": "DE45 1TR",
    "wof:placetype": "postalcode"
  },
  "geometry": {"coordinates":[-1.697097,53.244169],"type":"Point"}
}
