{
  "type": "Feature",
  "properties": {
    "iso:country":"GB",
    "wof:name":"DE45 1TR",
    "wof:placetype":"postalcode"
},
  "geometry": {"coordinates":[-1.69709664212746,53.2441693675899],"type":"Point"}
}