{
  "type": "Feature",
  "properties": {
    "date:inception_lower": "1980-01-01",
    "date:inception_upper": "1980-01-01",
    "iso:country": "GB",
    "wof:name": "B71 3JS",
    "wof:placetype": "postalcode"
  },
  "geometry": {"coordinates":[-1.9855,52.545432],"type":"Point"}
}
