{
  "type": "Feature",
  "properties": {
    "iso:country": "GB",
    "wof:name": "WR14 4AJ",
    "wof:placetype": "postalcode"
  },
  "geometry": {"coordinates":[-2.33271,52.091347],"type":"Point"}
}
