{
  "type": "Feature",
  "properties": {
    "iso:country":"GB",
    "wof:name":"WR14 4AJ",
    "wof:placetype":"postalcode"
},
  "geometry": {"coordinates":[-2.33271037297876,52.09134675767054],"type":"Point"}
}