{
  "type": "Feature",
  "properties": {
    "iso:country": "GB",
    "wof:name": "LA12 9ST",
    "wof:placetype": "postalcode"
  },
  "geometry": {"coordinates":[-3.091138,54.142606],"type":"Point"}
}
