{
  "type": "Feature",
  "properties": {
    "date:inception_lower": "1993-08-01",
    "date:inception_upper": "1993-08-01",
    "iso:country": "GB",
    "wof:name": "PL6 7TN",
    "wof:placetype": "postalcode"
  },
  "geometry": {"coordinates":[-4.105735,50.436157],"type":"Point"}
}
