{
  "type": "Feature",
  "properties": {
    "iso:country":"GB",
    "wof:name":"PL6 7TN",
    "wof:placetype":"postalcode"
},
  "geometry": {"coordinates":[-4.10573468695261,50.43615688252446],"type":"Point"}
}