{
  "type": "Feature",
  "properties": {
    "iso:country": "GB",
    "wof:name": "E17 7FZ",
    "wof:placetype": "postalcode"
  },
  "geometry": {"coordinates":[-0.020659,51.584453],"type":"Point"}
}
