{
  "type": "Feature",
  "properties": {
    "date:inception_lower": "1980-01-01",
    "date:inception_upper": "1980-01-01",
    "iso:country": "GB",
    "wof:name": "E2 7JH",
    "wof:placetype": "postalcode"
  },
  "geometry": {"coordinates":[-0.076201,51.525682],"type":"Point"}
}
