{
  "type": "Feature",
  "properties": {
    "iso:country":"GB",
    "wof:name":"E2 7JH",
    "wof:placetype":"postalcode"
},
  "geometry": {"coordinates":[-0.07620119467101,51.52568232791741],"type":"Point"}
}