{
  "type": "Feature",
  "properties": {
    "iso:country": "GB",
    "wof:name": "E2 7JH",
    "wof:placetype": "postalcode"
  },
  "geometry": {"coordinates":[-0.076201,51.525682],"type":"Point"}
}
