{
  "type": "Feature",
  "properties": {
    "iso:country":"GB",
    "wof:name":"BH15 1TH",
    "wof:placetype":"postalcode"
},
  "geometry": {"coordinates":[-1.97488962592545,50.71830973763371],"type":"Point"}
}