{
  "type": "Feature",
  "properties": {
    "iso:country":"GB",
    "wof:name":"RG20 0LS",
    "wof:placetype":"postalcode"
},
  "geometry": {"coordinates":[-1.35386610462642,51.36396867908208],"type":"Point"}
}