{
  "type": "Feature",
  "properties": {
    "date:inception_lower": "2005-01-01",
    "date:inception_upper": "2005-01-01",
    "iso:country": "GB",
    "wof:name": "TQ4 7JN",
    "wof:placetype": "postalcode"
  },
  "geometry": {"coordinates":[-3.56437,50.416808],"type":"Point"}
}
