{
  "type": "Feature",
  "properties": {
    "iso:country":"GB",
    "wof:name":"TQ4 7JN",
    "wof:placetype":"postalcode"
},
  "geometry": {"coordinates":[-3.56436981372748,50.41680816687254],"type":"Point"}
}