{
  "type": "Feature",
  "properties": {
    "iso:country": "GB",
    "wof:name": "TQ4 7JN",
    "wof:placetype": "postalcode"
  },
  "geometry": {"coordinates":[-3.56437,50.416808],"type":"Point"}
}
