{
  "type": "Feature",
  "properties": {
    "iso:country":"GB",
    "wof:name":"FK8 3SR",
    "wof:placetype":"postalcode"
},
  "geometry": {"coordinates":[-4.38490061427513,56.17962925679232],"type":"Point"}
}