{
  "type": "Feature",
  "properties": {
    "date:inception_lower": "1980-01-01",
    "date:inception_upper": "1980-01-01",
    "iso:country": "GB",
    "wof:name": "NG17 2DQ",
    "wof:placetype": "postalcode"
  },
  "geometry": {"coordinates":[-1.265485,53.13241],"type":"Point"}
}
