{
  "type": "Feature",
  "properties": {
    "iso:country":"GB",
    "wof:name":"NE20 9SD",
    "wof:placetype":"postalcode"
},
  "geometry": {"coordinates":[-1.74965619867533,55.05187551406065],"type":"Point"}
}