{
  "type": "Feature",
  "properties": {
    "date:inception_lower":"1980-01-01",
    "date:inception_upper":"1980-01-31",
    "iso:country":"GB",
    "wof:name":"M31 4FQ",
    "wof:placetype":"postalcode"
},
  "geometry": {"coordinates":[-2.42339,53.416546],"type":"Point"}
}