{
  "type": "Feature",
  "properties": {
    "iso:country": "GB",
    "wof:name": "SA38 9HJ",
    "wof:placetype": "postalcode"
  },
  "geometry": {"coordinates":[-4.47047,52.036124],"type":"Point"}
}
