{
  "type": "Feature",
  "properties": {
    "date:inception_lower": "1999-06-01",
    "date:inception_upper": "1999-06-01",
    "iso:country": "GB",
    "wof:name": "CH64 2US",
    "wof:placetype": "postalcode"
  },
  "geometry": {"coordinates":[-3.01131,53.28136],"type":"Point"}
}
