{
  "type": "Feature",
  "properties": {
    "iso:country":"GB",
    "wof:name":"CH64 2US",
    "wof:placetype":"postalcode"
},
  "geometry": {"coordinates":[-3.01130991663703,53.2813600523685],"type":"Point"}
}