{
  "type": "Feature",
  "properties": {
    "date:inception_lower": "2005-02-01",
    "date:inception_upper": "2005-02-01",
    "iso:country": "GB",
    "wof:name": "G31 5HJ",
    "wof:placetype": "postalcode"
  },
  "geometry": {"coordinates":[-4.18953,55.852268],"type":"Point"}
}
