{
  "type": "Feature",
  "properties": {
    "iso:country": "GB",
    "wof:name": "PO2 9RN",
    "wof:placetype": "postalcode"
  },
  "geometry": {"coordinates":[-1.069542,50.83131],"type":"Point"}
}
