{
  "type": "Feature",
  "properties": {
    "iso:country":"GB",
    "wof:name":"B8 2NP",
    "wof:placetype":"postalcode"
},
  "geometry": {"coordinates":[-1.82345233815362,52.49256070750285],"type":"Point"}
}