{
  "type": "Feature",
  "properties": {
    "date:inception_lower": "2019-01-01",
    "date:inception_upper": "2019-01-01",
    "iso:country": "GB",
    "wof:name": "E14 0SX",
    "wof:placetype": "postalcode"
  },
  "geometry": {"coordinates":[0.005659,51.513045],"type":"Point"}
}
