{
  "type": "Feature",
  "properties": {
    "iso:country": "GB",
    "wof:name": "E14 0SX",
    "wof:placetype": "postalcode"
  },
  "geometry": {"coordinates":[0.005833,51.512736],"type":"Point"}
}
