{
  "type": "Feature",
  "properties": {
    "iso:country":"GB",
    "wof:name":"DN3 2RT",
    "wof:placetype":"postalcode"
},
  "geometry": {"coordinates":[-1.05079203039016,53.53767191673735],"type":"Point"}
}