{
  "type": "Feature",
  "properties": {
    "iso:country":"GB",
    "wof:name":"UB6 8RJ",
    "wof:placetype":"postalcode"
},
  "geometry": {"coordinates":[-0.34632933709609,51.53312850141447],"type":"Point"}
}