{
  "type": "Feature",
  "properties": {
    "iso:country":"GB",
    "wof:name":"LS13 3LJ",
    "wof:placetype":"postalcode"
},
  "geometry": {"coordinates":[-1.64330471016792,53.81317598752818],"type":"Point"}
}