{
  "type": "Feature",
  "properties": {
    "iso:country":"GB",
    "wof:name":"SG9 0PY",
    "wof:placetype":"postalcode"
},
  "geometry": {"coordinates":[-0.02643037897253,51.98542371627615],"type":"Point"}
}