{
  "type": "Feature",
  "properties": {
    "iso:country": "GB",
    "wof:name": "SG9 0PY",
    "wof:placetype": "postalcode"
  },
  "geometry": {"coordinates":[-0.026515,51.985839],"type":"Point"}
}
