{
  "type": "Feature",
  "properties": {
    "date:inception_lower":"1980-01-01",
    "date:inception_upper":"1980-01-31",
    "iso:country":"GB",
    "wof:name":"SG9 0PY",
    "wof:placetype":"postalcode"
},
  "geometry": {"coordinates":[-0.026515,51.985839],"type":"Point"}
}