{
  "type": "Feature",
  "properties": {
    "iso:country": "GB",
    "wof:name": "HG4 5FE",
    "wof:placetype": "postalcode"
  },
  "geometry": {"coordinates":[-1.484389,54.135787],"type":"Point"}
}
