{
  "type": "Feature",
  "properties": {
    "date:inception_lower":"2015-11-01",
    "date:inception_upper":"2015-11-30",
    "iso:country":"GB",
    "wof:name":"TR3 6FR",
    "wof:placetype":"postalcode"
},
  "geometry": {"coordinates":[-5.071509,50.230647],"type":"Point"}
}