{
  "type": "Feature",
  "properties": {
    "iso:country": "GB",
    "wof:name": "TR3 6FR",
    "wof:placetype": "postalcode"
  },
  "geometry": {"coordinates":[-5.071509,50.230647],"type":"Point"}
}
