{
  "type": "Feature",
  "properties": {
    "iso:country":"GB",
    "wof:name":"TR3 6FR",
    "wof:placetype":"postalcode"
},
  "geometry": {"coordinates":[-5.09921376774946,50.26002944128604],"type":"Point"}
}