{
  "type": "Feature",
  "properties": {
    "date:inception_lower":"1987-10-01",
    "date:inception_upper":"1987-10-31",
    "iso:country":"GB",
    "wof:name":"CV5 6RT",
    "wof:placetype":"postalcode"
},
  "geometry": {"coordinates":[-1.551003,52.397391],"type":"Point"}
}