{
  "type": "Feature",
  "properties": {
    "iso:country":"GB",
    "wof:name":"CV5 6RT",
    "wof:placetype":"postalcode"
},
  "geometry": {"coordinates":[-1.55100325468903,52.39739135929252],"type":"Point"}
}