{
  "type": "Feature",
  "properties": {
    "date:inception_lower": "1980-01-01",
    "date:inception_upper": "1980-01-01",
    "iso:country": "GB",
    "wof:name": "DL2 2PF",
    "wof:placetype": "postalcode"
  },
  "geometry": {"coordinates":[-1.506609,54.473591],"type":"Point"}
}
