{
  "type": "Feature",
  "properties": {
    "iso:country":"GB",
    "wof:name":"DL2 2PF",
    "wof:placetype":"postalcode"
},
  "geometry": {"coordinates":[-1.50660930937111,54.47359064940012],"type":"Point"}
}