{
  "type": "Feature",
  "properties": {
    "iso:country":"GB",
    "wof:name":"G82 4EB",
    "wof:placetype":"postalcode"
},
  "geometry": {"coordinates":[-4.58778018051506,55.94504834357653],"type":"Point"}
}