{
  "type": "Feature",
  "properties": {
    "iso:country":"GB",
    "wof:name":"ML11 9NB",
    "wof:placetype":"postalcode"
},
  "geometry": {"coordinates":[-3.77878257090369,55.59697699651682],"type":"Point"}
}