{
  "type": "Feature",
  "properties": {
    "iso:country": "GB",
    "wof:name": "CW12 4GX",
    "wof:placetype": "postalcode"
  },
  "geometry": {"coordinates":[-2.233042,53.156747],"type":"Point"}
}
