{
  "type": "Feature",
  "properties": {
    "date:inception_lower": "2011-08-01",
    "date:inception_upper": "2011-08-01",
    "iso:country": "GB",
    "wof:name": "CW12 4GX",
    "wof:placetype": "postalcode"
  },
  "geometry": {"coordinates":[-2.233042,53.156747],"type":"Point"}
}
