{
  "type": "Feature",
  "properties": {
    "iso:country":"GB",
    "wof:name":"CW12 4GX",
    "wof:placetype":"postalcode"
},
  "geometry": {"coordinates":[-2.23304226422694,53.15674655217966],"type":"Point"}
}