{
  "type": "Feature",
  "properties": {
    "date:inception_lower": "2003-02-01",
    "date:inception_upper": "2003-02-01",
    "iso:country": "GB",
    "wof:name": "TS9 5GB",
    "wof:placetype": "postalcode"
  },
  "geometry": {"coordinates":[-1.180537,54.460923],"type":"Point"}
}
