{
  "type": "Feature",
  "properties": {
    "iso:country":"GB",
    "wof:name":"TS9 5GB",
    "wof:placetype":"postalcode"
},
  "geometry": {"coordinates":[-1.18016648520972,54.46103336024427],"type":"Point"}
}