{
  "type": "Feature",
  "properties": {
    "iso:country": "GB",
    "wof:name": "TS9 5GB",
    "wof:placetype": "postalcode"
  },
  "geometry": {"coordinates":[-1.180166,54.461033],"type":"Point"}
}
