{
  "type": "Feature",
  "properties": {
    "date:inception_lower":"1980-01-01",
    "date:inception_upper":"1980-01-31",
    "iso:country":"GB",
    "wof:name":"SP5 5JR",
    "wof:placetype":"postalcode"
},
  "geometry": {"coordinates":[-2.021334,51.018919],"type":"Point"}
}