{
  "type": "Feature",
  "properties": {
    "iso:country":"GB",
    "wof:name":"WF2 9TQ",
    "wof:placetype":"postalcode"
},
  "geometry": {"coordinates":[-1.53655363727813,53.68762481386494],"type":"Point"}
}