{
  "type": "Feature",
  "properties": {
    "date:inception_lower": "1992-01-01",
    "date:inception_upper": "1992-01-01",
    "iso:country": "GB",
    "wof:name": "BA12 0LU",
    "wof:placetype": "postalcode"
  },
  "geometry": {"coordinates":[-2.007578,51.199139],"type":"Point"}
}
