{
  "type": "Feature",
  "properties": {
    "iso:country": "GB",
    "wof:name": "BA12 0LU",
    "wof:placetype": "postalcode"
  },
  "geometry": {"coordinates":[-2.007578,51.199139],"type":"Point"}
}
