{
  "type": "Feature",
  "properties": {
    "date:inception_lower": "1980-01-01",
    "date:inception_upper": "1980-01-01",
    "iso:country": "GB",
    "wof:name": "M12 4PE",
    "wof:placetype": "postalcode"
  },
  "geometry": {"coordinates":[-2.19372,53.456591],"type":"Point"}
}
