{
  "type": "Feature",
  "properties": {
    "iso:country":"GB",
    "wof:name":"M12 4PE",
    "wof:placetype":"postalcode"
},
  "geometry": {"coordinates":[-2.1937199360621,53.45659066485722],"type":"Point"}
}