{
  "type": "Feature",
  "properties": {
    "iso:country":"GB",
    "wof:name":"BN7 2TJ",
    "wof:placetype":"postalcode"
},
  "geometry": {"coordinates":[-0.00453998704112,50.88340377656987],"type":"Point"}
}