{
  "type": "Feature",
  "properties": {
    "iso:country": "GB",
    "wof:name": "BN7 2TJ",
    "wof:placetype": "postalcode"
  },
  "geometry": {"coordinates":[-0.00454,50.883404],"type":"Point"}
}
