{
  "type": "Feature",
  "properties": {
    "iso:country": "GB",
    "wof:name": "B32 3HN",
    "wof:placetype": "postalcode"
  },
  "geometry": {"coordinates":[-1.99085,52.440694],"type":"Point"}
}
