{
  "type": "Feature",
  "properties": {
    "iso:country":"GB",
    "wof:name":"TN12 5DP",
    "wof:placetype":"postalcode"
},
  "geometry": {"coordinates":[0.37947018750928,51.21077423597228],"type":"Point"}
}