{
  "type": "Feature",
  "properties": {
    "date:inception_lower": "1980-01-01",
    "date:inception_upper": "1980-01-01",
    "iso:country": "GB",
    "wof:name": "ML11 9SF",
    "wof:placetype": "postalcode"
  },
  "geometry": {"coordinates":[-3.921148,55.669286],"type":"Point"}
}
