{
  "type": "Feature",
  "properties": {
    "date:inception_lower": "2009-01-01",
    "date:inception_upper": "2009-01-01",
    "iso:country": "GB",
    "wof:name": "LE3 3AW",
    "wof:placetype": "postalcode"
  },
  "geometry": {"coordinates":[-1.208059,52.629561],"type":"Point"}
}
