{
  "type": "Feature",
  "properties": {
    "iso:country":"GB",
    "wof:name":"LE3 3AW",
    "wof:placetype":"postalcode"
},
  "geometry": {"coordinates":[-1.2075947057474,52.62944933446796],"type":"Point"}
}