{
  "type": "Feature",
  "properties": {
    "iso:country": "GB",
    "wof:name": "LE3 3AW",
    "wof:placetype": "postalcode"
  },
  "geometry": {"coordinates":[-1.207999,52.629632],"type":"Point"}
}
