{
  "type": "Feature",
  "properties": {
    "date:inception_lower": "2015-10-01",
    "date:inception_upper": "2015-10-01",
    "iso:country": "GB",
    "wof:name": "ME4 4FL",
    "wof:placetype": "postalcode"
  },
  "geometry": {"coordinates":[0.533525,51.380128],"type":"Point"}
}
