{
  "type": "Feature",
  "properties": {
    "iso:country":"GB",
    "wof:name":"ME4 4FL",
    "wof:placetype":"postalcode"
},
  "geometry": {"coordinates":[0.53352532943939,51.38012784264397],"type":"Point"}
}