{
  "type": "Feature",
  "properties": {
    "iso:country": "GB",
    "wof:name": "ME4 4FL",
    "wof:placetype": "postalcode"
  },
  "geometry": {"coordinates":[0.533525,51.380128],"type":"Point"}
}
