{
  "type": "Feature",
  "properties": {
    "iso:country":"GB",
    "wof:name":"PO14 3JW",
    "wof:placetype":"postalcode"
},
  "geometry": {"coordinates":[-1.23065920176028,50.81788870195427],"type":"Point"}
}