{
  "type": "Feature",
  "properties": {
    "iso:country":"GB",
    "wof:name":"IP28 8PT",
    "wof:placetype":"postalcode"
},
  "geometry": {"coordinates":[0.46099113185542,52.34775096075958],"type":"Point"}
}