{
  "type": "Feature",
  "properties": {
    "iso:country":"GB",
    "wof:name":"PE22 8PE",
    "wof:placetype":"postalcode"
},
  "geometry": {"coordinates":[0.1652878566967,53.07777298518985],"type":"Point"}
}