{
  "type": "Feature",
  "properties": {
    "date:inception_lower": "1982-12-01",
    "date:inception_upper": "1982-12-01",
    "iso:country": "GB",
    "wof:name": "KY16 9UF",
    "wof:placetype": "postalcode"
  },
  "geometry": {"coordinates":[-2.83847,56.33317],"type":"Point"}
}
