{
  "type": "Feature",
  "properties": {
    "iso:country":"GB",
    "wof:name":"NG14 6DR",
    "wof:placetype":"postalcode"
},
  "geometry": {"coordinates":[-1.05964377083257,53.02536424505511],"type":"Point"}
}