{
  "type": "Feature",
  "properties": {
    "date:inception_lower":"1980-01-01",
    "date:inception_upper":"1980-01-31",
    "iso:country":"GB",
    "wof:name":"NG14 6DR",
    "wof:placetype":"postalcode"
},
  "geometry": {"coordinates":[-1.059644,53.025364],"type":"Point"}
}