{
  "type": "Feature",
  "properties": {
    "date:inception_lower":"1980-01-01",
    "date:inception_upper":"1980-01-31",
    "iso:country":"GB",
    "wof:name":"LE2 6TY",
    "wof:placetype":"postalcode"
},
  "geometry": {"coordinates":[-1.13083,52.59341],"type":"Point"}
}