{
  "type": "Feature",
  "properties": {
    "iso:country":"GB",
    "wof:name":"LE2 6TY",
    "wof:placetype":"postalcode"
},
  "geometry": {"coordinates":[-1.13083033973676,52.59340959588695],"type":"Point"}
}