{
  "type": "Feature",
  "properties": {
    "iso:country":"GB",
    "wof:name":"PO9 4HU",
    "wof:placetype":"postalcode"
},
  "geometry": {"coordinates":[-1.00204823726875,50.87804588787638],"type":"Point"}
}