{
  "type": "Feature",
  "properties": {
    "iso:country":"GB",
    "wof:name":"EX1 1GJ",
    "wof:placetype":"postalcode"
},
  "geometry": {"coordinates":[-3.52801763527838,50.72336787476485],"type":"Point"}
}