{
  "type": "Feature",
  "properties": {
    "iso:country":"GB",
    "wof:name":"IG1 1JY",
    "wof:placetype":"postalcode"
},
  "geometry": {"coordinates":[0.07966489314296,51.55631338380094],"type":"Point"}
}