{
  "type": "Feature",
  "properties": {
    "iso:country":"GB",
    "wof:name":"RM5 3BB",
    "wof:placetype":"postalcode"
},
  "geometry": {"coordinates":[0.16768915733149,51.58989081460316],"type":"Point"}
}