{
  "type": "Feature",
  "properties": {
    "iso:country":"GB",
    "wof:name":"B78 2PL",
    "wof:placetype":"postalcode"
},
  "geometry": {"coordinates":[-1.68186343639205,52.57294054415303],"type":"Point"}
}