{
  "type": "Feature",
  "properties": {
    "date:inception_lower":"1992-01-01",
    "date:inception_upper":"1992-01-31",
    "iso:country":"GB",
    "wof:name":"B78 2PL",
    "wof:placetype":"postalcode"
},
  "geometry": {"coordinates":[-1.681863,52.572941],"type":"Point"}
}