{
  "type": "Feature",
  "properties": {
    "iso:country":"GB",
    "wof:name":"NG20 9NF",
    "wof:placetype":"postalcode"
},
  "geometry": {"coordinates":[-1.16936011056171,53.22635312087097],"type":"Point"}
}