{
  "type": "Feature",
  "properties": {
    "date:inception_lower": "1980-01-01",
    "date:inception_upper": "1980-01-01",
    "iso:country": "GB",
    "wof:name": "NG20 9NF",
    "wof:placetype": "postalcode"
  },
  "geometry": {"coordinates":[-1.16936,53.226353],"type":"Point"}
}
