{
  "type": "Feature",
  "properties": {
    "iso:country":"GB",
    "wof:name":"LE6 0GU",
    "wof:placetype":"postalcode"
},
  "geometry": {"coordinates":[-1.22833830375074,52.65800335138758],"type":"Point"}
}