{
  "type": "Feature",
  "properties": {
    "iso:country": "GB",
    "wof:name": "NP44 3EY",
    "wof:placetype": "postalcode"
  },
  "geometry": {"coordinates":[-3.014301,51.640002],"type":"Point"}
}
