{
  "type": "Feature",
  "properties": {
    "date:inception_lower":"1980-01-01",
    "date:inception_upper":"1980-01-31",
    "iso:country":"GB",
    "wof:name":"NP44 3EY",
    "wof:placetype":"postalcode"
},
  "geometry": {"coordinates":[-3.014301,51.640002],"type":"Point"}
}