{
  "type": "Feature",
  "properties": {
    "iso:country":"GB",
    "wof:name":"NE46 2NT",
    "wof:placetype":"postalcode"
},
  "geometry": {"coordinates":[-2.16320690490263,54.95518773255358],"type":"Point"}
}