{
  "type": "Feature",
  "properties": {
    "iso:country": "GB",
    "wof:name": "NE46 2NT",
    "wof:placetype": "postalcode"
  },
  "geometry": {"coordinates":[-2.163207,54.955188],"type":"Point"}
}
