{
  "type": "Feature",
  "properties": {
    "date:inception_lower": "1995-01-01",
    "date:inception_upper": "1995-01-01",
    "iso:country": "GB",
    "wof:name": "BD22 9EF",
    "wof:placetype": "postalcode"
  },
  "geometry": {"coordinates":[-1.934019,53.834976],"type":"Point"}
}
