{
  "type": "Feature",
  "properties": {
    "iso:country":"GB",
    "wof:name":"NR10 3FU",
    "wof:placetype":"postalcode"
},
  "geometry": {"coordinates":[1.29184550199753,52.7285851964125],"type":"Point"}
}