{
  "type": "Feature",
  "properties": {
    "date:inception_lower": "1980-01-01",
    "date:inception_upper": "1980-01-01",
    "iso:country": "GB",
    "wof:name": "YO21 1NA",
    "wof:placetype": "postalcode"
  },
  "geometry": {"coordinates":[-0.635872,54.479044],"type":"Point"}
}
