{
  "type": "Feature",
  "properties": {
    "date:inception_lower":"1980-01-01",
    "date:inception_upper":"1980-01-31",
    "iso:country":"GB",
    "wof:name":"DY14 8DT",
    "wof:placetype":"postalcode"
},
  "geometry": {"coordinates":[-2.488258,52.377986],"type":"Point"}
}