{
  "type": "Feature",
  "properties": {
    "iso:country":"GB",
    "wof:name":"DY14 8DT",
    "wof:placetype":"postalcode"
},
  "geometry": {"coordinates":[-2.48825763756949,52.37798565625163],"type":"Point"}
}