{
  "type": "Feature",
  "properties": {
    "iso:country": "GB",
    "wof:name": "DN22 9BD",
    "wof:placetype": "postalcode"
  },
  "geometry": {"coordinates":[-0.880896,53.370108],"type":"Point"}
}
