{
  "type": "Feature",
  "properties": {
    "date:inception_lower": "2009-11-01",
    "date:inception_upper": "2009-11-01",
    "iso:country": "GB",
    "wof:name": "DN22 9BD",
    "wof:placetype": "postalcode"
  },
  "geometry": {"coordinates":[-0.86835,53.365989],"type":"Point"}
}
