{
  "type": "Feature",
  "properties": {
    "iso:country": "GB",
    "wof:name": "TS13 5DX",
    "wof:placetype": "postalcode"
  },
  "geometry": {"coordinates":[-0.826127,54.545913],"type":"Point"}
}
