{
  "type": "Feature",
  "properties": {
    "iso:country": "GB",
    "wof:name": "M28 3UN",
    "wof:placetype": "postalcode"
  },
  "geometry": {"coordinates":[-2.409078,53.518192],"type":"Point"}
}
