{
  "type": "Feature",
  "properties": {
    "iso:country":"GB",
    "wof:name":"M28 3UN",
    "wof:placetype":"postalcode"
},
  "geometry": {"coordinates":[-2.40908027172568,53.51817540273873],"type":"Point"}
}