{
  "type": "Feature",
  "properties": {
    "iso:country": "GB",
    "wof:name": "TQ9 7FF",
    "wof:placetype": "postalcode"
  },
  "geometry": {"coordinates":[-3.682465,50.344378],"type":"Point"}
}
