{
  "type": "Feature",
  "properties": {
    "date:inception_lower": "2013-03-01",
    "date:inception_upper": "2013-03-01",
    "iso:country": "GB",
    "wof:name": "L5 1AB",
    "wof:placetype": "postalcode"
  },
  "geometry": {"coordinates":[-2.961462,53.427888],"type":"Point"}
}
