{
  "type": "Feature",
  "properties": {
    "iso:country":"GB",
    "wof:name":"L5 1AB",
    "wof:placetype":"postalcode"
},
  "geometry": {"coordinates":[-2.96146253573887,53.4278884740465],"type":"Point"}
}