{
  "type": "Feature",
  "properties": {
    "iso:country":"GB",
    "wof:name":"RM5 3LD",
    "wof:placetype":"postalcode"
},
  "geometry": {"coordinates":[0.16562723241822,51.5969252687977],"type":"Point"}
}