{
  "type": "Feature",
  "properties": {
    "iso:country":"GB",
    "wof:name":"TA21 9LL",
    "wof:placetype":"postalcode"
},
  "geometry": {"coordinates":[-3.16680307662181,50.96017062164116],"type":"Point"}
}