{
  "type": "Feature",
  "properties": {
    "date:inception_lower": "1980-01-01",
    "date:inception_upper": "1980-01-01",
    "iso:country": "GB",
    "wof:name": "TA21 9LL",
    "wof:placetype": "postalcode"
  },
  "geometry": {"coordinates":[-3.166803,50.960171],"type":"Point"}
}
