{
  "type": "Feature",
  "properties": {
    "iso:country": "GB",
    "wof:name": "TS2 1RN",
    "wof:placetype": "postalcode"
  },
  "geometry": {"coordinates":[-1.249607,54.587128],"type":"Point"}
}
