{
  "type": "Feature",
  "properties": {
    "iso:country":"GB",
    "wof:name":"TS2 1RN",
    "wof:placetype":"postalcode"
},
  "geometry": {"coordinates":[-1.2494528250319,54.58714119448558],"type":"Point"}
}