{
  "type": "Feature",
  "properties": {
    "date:inception_lower":"1988-03-01",
    "date:inception_upper":"1988-03-31",
    "iso:country":"GB",
    "wof:name":"TS2 1RN",
    "wof:placetype":"postalcode"
},
  "geometry": {"coordinates":[-1.249607,54.587128],"type":"Point"}
}