{
  "type": "Feature",
  "properties": {
    "iso:country":"GB",
    "wof:name":"DN35 9HR",
    "wof:placetype":"postalcode"
},
  "geometry": {"coordinates":[-0.04508884430755,53.55375945490141],"type":"Point"}
}