{
  "type": "Feature",
  "properties": {
    "iso:country":"GB",
    "wof:name":"EX20 3HZ",
    "wof:placetype":"postalcode"
},
  "geometry": {"coordinates":[-4.07271466086115,50.82002757103362],"type":"Point"}
}