{
  "type": "Feature",
  "properties": {
    "date:inception_lower": "1980-01-01",
    "date:inception_upper": "1980-01-01",
    "iso:country": "GB",
    "wof:name": "EX20 3HZ",
    "wof:placetype": "postalcode"
  },
  "geometry": {"coordinates":[-4.072715,50.820028],"type":"Point"}
}
