{
  "type": "Feature",
  "properties": {
    "iso:country": "GB",
    "wof:name": "EX20 3HZ",
    "wof:placetype": "postalcode"
  },
  "geometry": {"coordinates":[-4.072715,50.820028],"type":"Point"}
}
