{
  "type": "Feature",
  "properties": {
    "iso:country":"GB",
    "wof:name":"CH4 9FL",
    "wof:placetype":"postalcode"
},
  "geometry": {"coordinates":[-2.93090202894304,53.12388615998399],"type":"Point"}
}