{
  "type": "Feature",
  "properties": {
    "iso:country": "GB",
    "wof:name": "CH4 9FL",
    "wof:placetype": "postalcode"
  },
  "geometry": {"coordinates":[-2.930902,53.123886],"type":"Point"}
}
