{
  "type": "Feature",
  "properties": {
    "date:inception_lower":"2009-04-01",
    "date:inception_upper":"2009-04-30",
    "iso:country":"GB",
    "wof:name":"CH4 9FL",
    "wof:placetype":"postalcode"
},
  "geometry": {"coordinates":[-2.930902,53.123886],"type":"Point"}
}