{
  "type": "Feature",
  "properties": {
    "iso:country":"GB",
    "wof:name":"CA1 3NU",
    "wof:placetype":"postalcode"
},
  "geometry": {"coordinates":[-2.90581328905205,54.88294927313241],"type":"Point"}
}