{
  "type": "Feature",
  "properties": {
    "iso:country": "GB",
    "wof:name": "BA10 0EQ",
    "wof:placetype": "postalcode"
  },
  "geometry": {"coordinates":[-2.452852,51.112361],"type":"Point"}
}
