{
  "type": "Feature",
  "properties": {
    "date:inception_lower":"1980-01-01",
    "date:inception_upper":"1980-01-31",
    "iso:country":"GB",
    "wof:name":"BA10 0EQ",
    "wof:placetype":"postalcode"
},
  "geometry": {"coordinates":[-2.452852,51.112361],"type":"Point"}
}