{
  "type": "Feature",
  "properties": {
    "iso:country":"GB",
    "wof:name":"TR20 8XB",
    "wof:placetype":"postalcode"
},
  "geometry": {"coordinates":[-5.54538903623429,50.15221127910518],"type":"Point"}
}