{
  "type": "Feature",
  "properties": {
    "date:inception_lower":"1980-01-01",
    "date:inception_upper":"1980-01-31",
    "iso:country":"GB",
    "wof:name":"TR20 8XB",
    "wof:placetype":"postalcode"
},
  "geometry": {"coordinates":[-5.546766,50.152675],"type":"Point"}
}