{
  "type": "Feature",
  "properties": {
    "iso:country":"GB",
    "wof:name":"B98 9BS",
    "wof:placetype":"postalcode"
},
  "geometry": {"coordinates":[-1.88891148528253,52.33158308753653],"type":"Point"}
}