{
  "type": "Feature",
  "properties": {
    "iso:country": "GB",
    "wof:name": "BB5 2HB",
    "wof:placetype": "postalcode"
  },
  "geometry": {"coordinates":[-2.362854,53.748844],"type":"Point"}
}
