{
  "type": "Feature",
  "properties": {
    "iso:country":"GB",
    "wof:name":"CW6 9GZ",
    "wof:placetype":"postalcode"
},
  "geometry": {"coordinates":[-2.58776698591123,53.13148670807698],"type":"Point"}
}