{
  "type": "Feature",
  "properties": {
    "iso:country": "GB",
    "wof:name": "CW6 9GZ",
    "wof:placetype": "postalcode"
  },
  "geometry": {"coordinates":[-2.587767,53.131487],"type":"Point"}
}
