{
  "type": "Feature",
  "properties": {
    "date:inception_lower":"2014-07-01",
    "date:inception_upper":"2014-07-31",
    "iso:country":"GB",
    "wof:name":"CW6 9GZ",
    "wof:placetype":"postalcode"
},
  "geometry": {"coordinates":[-2.587767,53.131487],"type":"Point"}
}