{
  "type": "Feature",
  "properties": {
    "iso:country":"GB",
    "wof:name":"DH6 2SZ",
    "wof:placetype":"postalcode"
},
  "geometry": {"coordinates":[-1.40096430335431,54.79020603326619],"type":"Point"}
}