{
  "type": "Feature",
  "properties": {
    "iso:country": "GB",
    "wof:name": "DH6 2SZ",
    "wof:placetype": "postalcode"
  },
  "geometry": {"coordinates":[-1.400964,54.790206],"type":"Point"}
}
