{
  "type": "Feature",
  "properties": {
    "date:inception_lower": "2020-08-01",
    "date:inception_upper": "2020-08-01",
    "iso:country": "GB",
    "wof:name": "G74 4GQ",
    "wof:placetype": "postalcode"
  },
  "geometry": {"coordinates":[-4.18119,55.775768],"type":"Point"}
}
