{
  "type": "Feature",
  "properties": {
    "date:inception_lower": "1980-01-01",
    "date:inception_upper": "1980-01-01",
    "iso:country": "GB",
    "wof:name": "CV5 6HT",
    "wof:placetype": "postalcode"
  },
  "geometry": {"coordinates":[-1.52853,52.406409],"type":"Point"}
}
