{
  "type": "Feature",
  "properties": {
    "iso:country":"GB",
    "wof:name":"CV5 6HT",
    "wof:placetype":"postalcode"
},
  "geometry": {"coordinates":[-1.52858240436048,52.40645610869818],"type":"Point"}
}