{
  "type": "Feature",
  "properties": {
    "iso:country": "GB",
    "wof:name": "CV5 6HT",
    "wof:placetype": "postalcode"
  },
  "geometry": {"coordinates":[-1.528582,52.406456],"type":"Point"}
}
