{
  "type": "Feature",
  "properties": {
    "date:inception_lower":"2005-09-01",
    "date:inception_upper":"2005-09-30",
    "iso:country":"GB",
    "wof:name":"EH24 9ER",
    "wof:placetype":"postalcode"
},
  "geometry": {"coordinates":[-3.142651,55.848591],"type":"Point"}
}