{
  "type": "Feature",
  "properties": {
    "date:inception_lower": "1980-01-01",
    "date:inception_upper": "1980-01-01",
    "iso:country": "GB",
    "wof:name": "BA2 7DG",
    "wof:placetype": "postalcode"
  },
  "geometry": {"coordinates":[-2.344713,51.342384],"type":"Point"}
}
