{
  "type": "Feature",
  "properties": {
    "iso:country":"GB",
    "wof:name":"BA2 7DG",
    "wof:placetype":"postalcode"
},
  "geometry": {"coordinates":[-2.34471266501333,51.34238396494261],"type":"Point"}
}