{
  "type": "Feature",
  "properties": {
    "iso:country":"GB",
    "wof:name":"SE9 4RG",
    "wof:placetype":"postalcode"
},
  "geometry": {"coordinates":[0.03999121092253,51.44043702498226],"type":"Point"}
}