{
  "type": "Feature",
  "properties": {
    "iso:country": "GB",
    "wof:name": "SE9 4RG",
    "wof:placetype": "postalcode"
  },
  "geometry": {"coordinates":[0.039991,51.440437],"type":"Point"}
}
