{
  "type": "Feature",
  "properties": {
    "iso:country":"GB",
    "wof:name":"LN1 2WU",
    "wof:placetype":"postalcode"
},
  "geometry": {"coordinates":[-0.66836241761865,53.27236620680851],"type":"Point"}
}