{
  "type": "Feature",
  "properties": {
    "iso:country": "GB",
    "wof:name": "LN1 2WU",
    "wof:placetype": "postalcode"
  },
  "geometry": {"coordinates":[-0.668362,53.272366],"type":"Point"}
}
