{
  "type": "Feature",
  "properties": {
    "iso:country":"GB",
    "wof:name":"TS23 2TH",
    "wof:placetype":"postalcode"
},
  "geometry": {"coordinates":[-1.29580296536879,54.61825391398884],"type":"Point"}
}