{
  "type": "Feature",
  "properties": {
    "iso:country":"GB",
    "wof:name":"NE24 1JE",
    "wof:placetype":"postalcode"
},
  "geometry": {"coordinates":[-1.51511268453845,55.13009304018203],"type":"Point"}
}