{
  "type": "Feature",
  "properties": {
    "date:inception_lower": "1999-06-01",
    "date:inception_upper": "1999-06-01",
    "iso:country": "GB",
    "wof:name": "NP26 3PA",
    "wof:placetype": "postalcode"
  },
  "geometry": {"coordinates":[-2.816011,51.581512],"type":"Point"}
}
