{
  "type": "Feature",
  "properties": {
    "iso:country":"GB",
    "wof:name":"BR2 0HH",
    "wof:placetype":"postalcode"
},
  "geometry": {"coordinates":[0.00118561940656,51.40230206460615],"type":"Point"}
}