{
  "type": "Feature",
  "properties": {
    "date:inception_lower": "1980-01-01",
    "date:inception_upper": "1980-01-01",
    "iso:country": "GB",
    "wof:name": "BR2 0HH",
    "wof:placetype": "postalcode"
  },
  "geometry": {"coordinates":[0.001186,51.402302],"type":"Point"}
}
