{
  "type": "Feature",
  "properties": {
    "iso:country": "GB",
    "wof:name": "TD12 4DW",
    "wof:placetype": "postalcode"
  },
  "geometry": {"coordinates":[-2.253751,55.651768],"type":"Point"}
}
