{
  "type": "Feature",
  "properties": {
    "date:inception_lower": "2021-03-01",
    "date:inception_upper": "2021-03-01",
    "iso:country": "GB",
    "wof:name": "PR2 0AL",
    "wof:placetype": "postalcode"
  },
  "geometry": {"coordinates":[-2.708369,53.754266],"type":"Point"}
}
