{
  "type": "Feature",
  "properties": {
    "iso:country":"GB",
    "wof:name":"NG10 5LX",
    "wof:placetype":"postalcode"
},
  "geometry": {"coordinates":[-1.29078406705996,52.91540811695825],"type":"Point"}
}