{
  "type": "Feature",
  "properties": {
    "date:inception_lower": "1980-01-01",
    "date:inception_upper": "1980-01-01",
    "iso:country": "GB",
    "wof:name": "NG10 5LX",
    "wof:placetype": "postalcode"
  },
  "geometry": {"coordinates":[-1.290784,52.915408],"type":"Point"}
}
