{
  "type": "Feature",
  "properties": {
    "iso:country":"GB",
    "wof:name":"CR4 2AJ",
    "wof:placetype":"postalcode"
},
  "geometry": {"coordinates":[-0.15178718346677,51.41694572049494],"type":"Point"}
}