{
  "type": "Feature",
  "properties": {
    "iso:country":"GB",
    "wof:name":"GU3 2DG",
    "wof:placetype":"postalcode"
},
  "geometry": {"coordinates":[-0.67238466835113,51.25456659779945],"type":"Point"}
}