{
  "type": "Feature",
  "properties": {
    "iso:country":"GB",
    "wof:name":"HD9 1LP",
    "wof:placetype":"postalcode"
},
  "geometry": {"coordinates":[-1.76675106311434,53.57661501827926],"type":"Point"}
}