{
  "type": "Feature",
  "properties": {
    "date:inception_lower":"2001-06-01",
    "date:inception_upper":"2001-06-30",
    "iso:country":"GB",
    "wof:name":"HD9 1LP",
    "wof:placetype":"postalcode"
},
  "geometry": {"coordinates":[-1.766751,53.576615],"type":"Point"}
}