{
  "type": "Feature",
  "properties": {
    "iso:country": "GB",
    "wof:name": "NE12 6PF",
    "wof:placetype": "postalcode"
  },
  "geometry": {"coordinates":[-1.568263,55.041321],"type":"Point"}
}
