{
  "type": "Feature",
  "properties": {
    "date:inception_lower":"1999-06-01",
    "date:inception_upper":"1999-06-30",
    "iso:country":"GB",
    "wof:name":"NE12 6PF",
    "wof:placetype":"postalcode"
},
  "geometry": {"coordinates":[-1.568263,55.041321],"type":"Point"}
}