{
  "type": "Feature",
  "properties": {
    "iso:country":"GB",
    "wof:name":"NG19 6SQ",
    "wof:placetype":"postalcode"
},
  "geometry": {"coordinates":[-1.21109693857289,53.14942905724956],"type":"Point"}
}