{
  "type": "Feature",
  "properties": {
    "date:inception_lower": "1980-01-01",
    "date:inception_upper": "1980-01-01",
    "iso:country": "GB",
    "wof:name": "GU8 4QN",
    "wof:placetype": "postalcode"
  },
  "geometry": {"coordinates":[-0.635813,51.112568],"type":"Point"}
}
