{
  "type": "Feature",
  "properties": {
    "iso:country":"GB",
    "wof:name":"GU8 4QN",
    "wof:placetype":"postalcode"
},
  "geometry": {"coordinates":[-0.63581315759317,51.11256829531533],"type":"Point"}
}