{
  "type": "Feature",
  "properties": {
    "iso:country":"GB",
    "wof:name":"DN19 7UD",
    "wof:placetype":"postalcode"
},
  "geometry": {"coordinates":[-0.33486178665704,53.68253072239053],"type":"Point"}
}