{
  "type": "Feature",
  "properties": {
    "date:inception_lower": "1999-12-01",
    "date:inception_upper": "1999-12-01",
    "iso:country": "GB",
    "wof:name": "DN19 7UD",
    "wof:placetype": "postalcode"
  },
  "geometry": {"coordinates":[-0.334862,53.682531],"type":"Point"}
}
