{
  "type": "Feature",
  "properties": {
    "iso:country":"GB",
    "wof:name":"HP8 4QT",
    "wof:placetype":"postalcode"
},
  "geometry": {"coordinates":[-0.57111254764603,51.62715212486403],"type":"Point"}
}