{
  "type": "Feature",
  "properties": {
    "iso:country": "GB",
    "wof:name": "HP8 4QT",
    "wof:placetype": "postalcode"
  },
  "geometry": {"coordinates":[-0.571113,51.627152],"type":"Point"}
}
