{
  "type": "Feature",
  "properties": {
    "iso:country":"GB",
    "wof:name":"IP26 5HN",
    "wof:placetype":"postalcode"
},
  "geometry": {"coordinates":[0.66343901319536,52.51412684207759],"type":"Point"}
}