{
  "type": "Feature",
  "properties": {
    "iso:country": "GB",
    "wof:name": "IP26 5HN",
    "wof:placetype": "postalcode"
  },
  "geometry": {"coordinates":[0.663439,52.514127],"type":"Point"}
}
