{
  "type": "Feature",
  "properties": {
    "iso:country":"GB",
    "wof:name":"LS19 7AS",
    "wof:placetype":"postalcode"
},
  "geometry": {"coordinates":[-1.66959721224211,53.86686427457696],"type":"Point"}
}