{
  "type": "Feature",
  "properties": {
    "iso:country": "GB",
    "wof:name": "SK9 3PW",
    "wof:placetype": "postalcode"
  },
  "geometry": {"coordinates":[-2.210753,53.35029],"type":"Point"}
}
