{
  "type": "Feature",
  "properties": {
    "iso:country": "GB",
    "wof:name": "HU16 5AA",
    "wof:placetype": "postalcode"
  },
  "geometry": {"coordinates":[-0.421576,53.780985],"type":"Point"}
}
