{
  "type": "Feature",
  "properties": {
    "iso:country":"GB",
    "wof:name":"SK1 1PN",
    "wof:placetype":"postalcode"
},
  "geometry": {"coordinates":[-2.15887006754768,53.41184340145685],"type":"Point"}
}