{
  "type": "Feature",
  "properties": {
    "iso:country": "GB",
    "wof:name": "CF64 1DU",
    "wof:placetype": "postalcode"
  },
  "geometry": {"coordinates":[-3.172406,51.443497],"type":"Point"}
}
