{
  "type": "Feature",
  "properties": {
    "date:inception_lower": "1999-12-01",
    "date:inception_upper": "1999-12-01",
    "iso:country": "GB",
    "wof:name": "CF64 1DU",
    "wof:placetype": "postalcode"
  },
  "geometry": {"coordinates":[-3.172406,51.443497],"type":"Point"}
}
