{
  "type": "Feature",
  "properties": {
    "iso:country":"GB",
    "wof:name":"CF64 1DU",
    "wof:placetype":"postalcode"
},
  "geometry": {"coordinates":[-3.17240566267329,51.44349706199419],"type":"Point"}
}