{
  "type": "Feature",
  "properties": {
    "iso:country":"GB",
    "wof:name":"CV33 9EG",
    "wof:placetype":"postalcode"
},
  "geometry": {"coordinates":[-1.44066388189992,52.30400667283723],"type":"Point"}
}