{
  "type": "Feature",
  "properties": {
    "date:inception_lower": "1980-01-01",
    "date:inception_upper": "1980-01-01",
    "iso:country": "GB",
    "wof:name": "CV33 9EG",
    "wof:placetype": "postalcode"
  },
  "geometry": {"coordinates":[-1.440664,52.304007],"type":"Point"}
}
