{
  "type": "Feature",
  "properties": {
    "iso:country":"GB",
    "wof:name":"WA4 4NE",
    "wof:placetype":"postalcode"
},
  "geometry": {"coordinates":[-2.57701745877047,53.33948933865512],"type":"Point"}
}