{
  "type": "Feature",
  "properties": {
    "iso:country":"GB",
    "wof:name":"DN18 6EF",
    "wof:placetype":"postalcode"
},
  "geometry": {"coordinates":[-0.38845250162102,53.64079874826777],"type":"Point"}
}