{
  "type": "Feature",
  "properties": {
    "iso:country":"GB",
    "wof:name":"OX7 7AP",
    "wof:placetype":"postalcode"
},
  "geometry": {"coordinates":[-1.38444972926125,51.96890785430393],"type":"Point"}
}