{
  "type": "Feature",
  "properties": {
    "date:inception_lower":"1991-09-01",
    "date:inception_upper":"1991-09-30",
    "iso:country":"GB",
    "wof:name":"OX7 7AP",
    "wof:placetype":"postalcode"
},
  "geometry": {"coordinates":[-1.38445,51.968908],"type":"Point"}
}