{
  "type": "Feature",
  "properties": {
    "iso:country": "GB",
    "wof:name": "OX7 7AP",
    "wof:placetype": "postalcode"
  },
  "geometry": {"coordinates":[-1.38445,51.968908],"type":"Point"}
}
