{
  "type": "Feature",
  "properties": {
    "iso:country":"GB",
    "wof:name":"NP13 2BS",
    "wof:placetype":"postalcode"
},
  "geometry": {"coordinates":[-3.14700665431302,51.70761144670512],"type":"Point"}
}