{
  "type": "Feature",
  "properties": {
    "date:inception_lower": "1999-06-01",
    "date:inception_upper": "1999-06-01",
    "iso:country": "GB",
    "wof:name": "NP13 2BS",
    "wof:placetype": "postalcode"
  },
  "geometry": {"coordinates":[-3.147015,51.707614],"type":"Point"}
}
