{
  "type": "Feature",
  "properties": {
    "iso:country": "GB",
    "wof:name": "BB18 6TQ",
    "wof:placetype": "postalcode"
  },
  "geometry": {"coordinates":[-2.152543,53.899056],"type":"Point"}
}
