{
  "type": "Feature",
  "properties": {
    "iso:country":"GB",
    "wof:name":"B75 7NA",
    "wof:placetype":"postalcode"
},
  "geometry": {"coordinates":[-1.78553595680324,52.56644905073939],"type":"Point"}
}