{
  "type": "Feature",
  "properties": {
    "iso:country":"GB",
    "wof:name":"S3 7LG",
    "wof:placetype":"postalcode"
},
  "geometry": {"coordinates":[-1.47831544232233,53.38807882222593],"type":"Point"}
}