{
  "type": "Feature",
  "properties": {
    "date:inception_lower": "2009-10-01",
    "date:inception_upper": "2009-10-01",
    "iso:country": "GB",
    "wof:name": "S3 7LG",
    "wof:placetype": "postalcode"
  },
  "geometry": {"coordinates":[-1.479346,53.387418],"type":"Point"}
}
