{
  "type": "Feature",
  "properties": {
    "iso:country":"GB",
    "wof:name":"BH23 7HP",
    "wof:placetype":"postalcode"
},
  "geometry": {"coordinates":[-1.76520502613045,50.74901128419157],"type":"Point"}
}