{
  "type": "Feature",
  "properties": {
    "iso:country":"GB",
    "wof:name":"UB1 3AA",
    "wof:placetype":"postalcode"
},
  "geometry": {"coordinates":[-0.35577180787059,51.51795639711427],"type":"Point"}
}