{
  "type": "Feature",
  "properties": {
    "date:inception_lower": "2008-11-01",
    "date:inception_upper": "2008-11-01",
    "iso:country": "GB",
    "wof:name": "UB1 3AA",
    "wof:placetype": "postalcode"
  },
  "geometry": {"coordinates":[-0.355772,51.517956],"type":"Point"}
}
