{
  "type": "Feature",
  "properties": {
    "iso:country":"GB",
    "wof:name":"CT1 2SQ",
    "wof:placetype":"postalcode"
},
  "geometry": {"coordinates":[1.08067355764647,51.27836074968383],"type":"Point"}
}