{
  "type": "Feature",
  "properties": {
    "iso:country":"GB",
    "wof:name":"TR18 2HX",
    "wof:placetype":"postalcode"
},
  "geometry": {"coordinates":[-5.53414572258974,50.1209042525145],"type":"Point"}
}