{
  "type": "Feature",
  "properties": {
    "iso:country": "GB",
    "wof:name": "LL55 2RG",
    "wof:placetype": "postalcode"
  },
  "geometry": {"coordinates":[-4.268508,53.138758],"type":"Point"}
}
