{
  "type": "Feature",
  "properties": {
    "iso:country":"GB",
    "wof:name":"LL55 2RG",
    "wof:placetype":"postalcode"
},
  "geometry": {"coordinates":[-4.26850824281207,53.13875825584448],"type":"Point"}
}