{
  "type": "Feature",
  "properties": {
    "iso:country":"GB",
    "wof:name":"RG8 7PG",
    "wof:placetype":"postalcode"
},
  "geometry": {"coordinates":[-1.07640416433756,51.50656426460662],"type":"Point"}
}