{
  "type": "Feature",
  "properties": {
    "iso:country": "GB",
    "wof:name": "RG8 7PG",
    "wof:placetype": "postalcode"
  },
  "geometry": {"coordinates":[-1.076404,51.506564],"type":"Point"}
}
