{
  "type": "Feature",
  "properties": {
    "iso:country":"GB",
    "wof:name":"LA6 3ND",
    "wof:placetype":"postalcode"
},
  "geometry": {"coordinates":[-2.53239891808739,54.14295048858524],"type":"Point"}
}