{
  "type": "Feature",
  "properties": {
    "date:inception_lower": "1993-01-01",
    "date:inception_upper": "1993-01-01",
    "iso:country": "GB",
    "wof:name": "ST14 8AQ",
    "wof:placetype": "postalcode"
  },
  "geometry": {"coordinates":[-1.863363,52.89623],"type":"Point"}
}
