{
  "type": "Feature",
  "properties": {
    "iso:country": "GB",
    "wof:name": "ST14 8AQ",
    "wof:placetype": "postalcode"
  },
  "geometry": {"coordinates":[-1.863363,52.89623],"type":"Point"}
}
