{
  "type": "Feature",
  "properties": {
    "iso:country": "GB",
    "wof:name": "RG30 2QH",
    "wof:placetype": "postalcode"
  },
  "geometry": {"coordinates":[-1.010365,51.457497],"type":"Point"}
}
