{
  "type": "Feature",
  "properties": {
    "iso:country":"GB",
    "wof:name":"CV12 9JS",
    "wof:placetype":"postalcode"
},
  "geometry": {"coordinates":[-1.41669601369301,52.47715917377712],"type":"Point"}
}