{
  "type": "Feature",
  "properties": {
    "date:inception_lower":"1988-03-01",
    "date:inception_upper":"1988-03-31",
    "iso:country":"GB",
    "wof:name":"SN5 6HP",
    "wof:placetype":"postalcode"
},
  "geometry": {"coordinates":[-1.848573,51.556038],"type":"Point"}
}