{
  "type": "Feature",
  "properties": {
    "iso:country": "GB",
    "wof:name": "SN5 6HP",
    "wof:placetype": "postalcode"
  },
  "geometry": {"coordinates":[-1.848573,51.556038],"type":"Point"}
}
