{
  "type": "Feature",
  "properties": {
    "iso:country":"GB",
    "wof:name":"SN5 6HP",
    "wof:placetype":"postalcode"
},
  "geometry": {"coordinates":[-1.84857336419816,51.55603794904632],"type":"Point"}
}