{
  "type": "Feature",
  "properties": {
    "date:inception_lower": "1980-01-01",
    "date:inception_upper": "1980-01-01",
    "iso:country": "GB",
    "wof:name": "LN2 2SZ",
    "wof:placetype": "postalcode"
  },
  "geometry": {"coordinates":[-0.484226,53.270177],"type":"Point"}
}
