{
  "type": "Feature",
  "properties": {
    "iso:country": "GB",
    "wof:name": "LN2 2SZ",
    "wof:placetype": "postalcode"
  },
  "geometry": {"coordinates":[-0.484226,53.270177],"type":"Point"}
}
