{
  "type": "Feature",
  "properties": {
    "iso:country":"GB",
    "wof:name":"PE2 5PL",
    "wof:placetype":"postalcode"
},
  "geometry": {"coordinates":[-0.27002078177003,52.54734455588233],"type":"Point"}
}