{
  "type": "Feature",
  "properties": {
    "date:inception_lower":"1980-01-01",
    "date:inception_upper":"1980-01-31",
    "iso:country":"GB",
    "wof:name":"PR4 4LJ",
    "wof:placetype":"postalcode"
},
  "geometry": {"coordinates":[-2.706904,53.72304],"type":"Point"}
}