{
  "type": "Feature",
  "properties": {
    "iso:country":"GB",
    "wof:name":"PR4 4LJ",
    "wof:placetype":"postalcode"
},
  "geometry": {"coordinates":[-2.70698305011392,53.7230147954476],"type":"Point"}
}