{
  "type": "Feature",
  "properties": {
    "date:inception_lower": "2016-06-01",
    "date:inception_upper": "2016-06-01",
    "iso:country": "GB",
    "wof:name": "B36 0LP",
    "wof:placetype": "postalcode"
  },
  "geometry": {"coordinates":[-1.737156,52.491804],"type":"Point"}
}
