{
  "type": "Feature",
  "properties": {
    "iso:country": "GB",
    "wof:name": "B36 0LP",
    "wof:placetype": "postalcode"
  },
  "geometry": {"coordinates":[-1.737156,52.491804],"type":"Point"}
}
