{
  "type": "Feature",
  "properties": {
    "iso:country": "GB",
    "wof:name": "TN17 2QD",
    "wof:placetype": "postalcode"
  },
  "geometry": {"coordinates":[0.502725,51.110655],"type":"Point"}
}
