{
  "type": "Feature",
  "properties": {
    "date:inception_lower": "1995-07-01",
    "date:inception_upper": "1995-07-01",
    "iso:country": "GB",
    "wof:name": "CM1 1SR",
    "wof:placetype": "postalcode"
  },
  "geometry": {"coordinates":[0.47121,51.742233],"type":"Point"}
}
