{
  "type": "Feature",
  "properties": {
    "iso:country": "GB",
    "wof:name": "SS1 2YP",
    "wof:placetype": "postalcode"
  },
  "geometry": {"coordinates":[0.73426,51.530208],"type":"Point"}
}
