{
  "type": "Feature",
  "properties": {
    "iso:country":"GB",
    "wof:name":"SS1 2YP",
    "wof:placetype":"postalcode"
},
  "geometry": {"coordinates":[0.73426026701895,51.53020803267959],"type":"Point"}
}