{
  "type": "Feature",
  "properties": {
    "iso:country":"GB",
    "wof:name":"PO30 1PB",
    "wof:placetype":"postalcode"
},
  "geometry": {"coordinates":[-1.32099698163989,50.68768568402565],"type":"Point"}
}