{
  "type": "Feature",
  "properties": {
    "date:inception_lower":"1980-01-01",
    "date:inception_upper":"1980-01-31",
    "iso:country":"GB",
    "wof:name":"PO30 1PB",
    "wof:placetype":"postalcode"
},
  "geometry": {"coordinates":[-1.320997,50.687686],"type":"Point"}
}