{
  "type": "Feature",
  "properties": {
    "iso:country": "GB",
    "wof:name": "PO30 1PB",
    "wof:placetype": "postalcode"
  },
  "geometry": {"coordinates":[-1.320997,50.687686],"type":"Point"}
}
