{
  "type": "Feature",
  "properties": {
    "iso:country":"GB",
    "wof:name":"PL13 1ES",
    "wof:placetype":"postalcode"
},
  "geometry": {"coordinates":[-4.4495806074832,50.36026203428204],"type":"Point"}
}