{
  "type": "Feature",
  "properties": {
    "date:inception_lower":"1980-01-01",
    "date:inception_upper":"1980-01-31",
    "iso:country":"GB",
    "wof:name":"BL9 5NH",
    "wof:placetype":"postalcode"
},
  "geometry": {"coordinates":[-2.305276,53.64008],"type":"Point"}
}