{
  "type": "Feature",
  "properties": {
    "iso:country":"GB",
    "wof:name":"BL9 5NH",
    "wof:placetype":"postalcode"
},
  "geometry": {"coordinates":[-2.30527623017434,53.64007976065875],"type":"Point"}
}