{
  "type": "Feature",
  "properties": {
    "iso:country": "GB",
    "wof:name": "BL9 5NH",
    "wof:placetype": "postalcode"
  },
  "geometry": {"coordinates":[-2.305276,53.64008],"type":"Point"}
}
