{
  "type": "Feature",
  "properties": {
    "iso:country":"GB",
    "wof:name":"PR3 2BT",
    "wof:placetype":"postalcode"
},
  "geometry": {"coordinates":[-2.67179394267251,53.82281532680084],"type":"Point"}
}