{
  "type": "Feature",
  "properties": {
    "iso:country":"GB",
    "wof:name":"N10 1QY",
    "wof:placetype":"postalcode"
},
  "geometry": {"coordinates":[-0.14900755150404,51.59447689469953],"type":"Point"}
}