{
  "type": "Feature",
  "properties": {
    "iso:country": "GB",
    "wof:name": "CB7 5JD",
    "wof:placetype": "postalcode"
  },
  "geometry": {"coordinates":[0.34195,52.33519],"type":"Point"}
}
