{
  "type": "Feature",
  "properties": {
    "iso:country":"GB",
    "wof:name":"CB7 5JD",
    "wof:placetype":"postalcode"
},
  "geometry": {"coordinates":[0.34194968521139,52.33519047639791],"type":"Point"}
}