{
  "type": "Feature",
  "properties": {
    "iso:country":"GB",
    "wof:name":"GL53 7DY",
    "wof:placetype":"postalcode"
},
  "geometry": {"coordinates":[-2.0728840994272,51.88237354854023],"type":"Point"}
}