{
  "type": "Feature",
  "properties": {
    "iso:country":"GB",
    "wof:name":"M33 3PW",
    "wof:placetype":"postalcode"
},
  "geometry": {"coordinates":[-2.31303164894063,53.40857225971027],"type":"Point"}
}