{
  "type": "Feature",
  "properties": {
    "iso:country": "GB",
    "wof:name": "EX38 7AE",
    "wof:placetype": "postalcode"
  },
  "geometry": {"coordinates":[-4.148512,50.953381],"type":"Point"}
}
