{
  "type": "Feature",
  "properties": {
    "iso:country": "GB",
    "wof:name": "YO26 7LF",
    "wof:placetype": "postalcode"
  },
  "geometry": {"coordinates":[-1.240141,53.953105],"type":"Point"}
}
