{
  "type": "Feature",
  "properties": {
    "iso:country": "GB",
    "wof:name": "CM1 4JQ",
    "wof:placetype": "postalcode"
  },
  "geometry": {"coordinates":[0.460166,51.746664],"type":"Point"}
}
