{
  "type": "Feature",
  "properties": {
    "iso:country": "GB",
    "wof:name": "TS11 6NE",
    "wof:placetype": "postalcode"
  },
  "geometry": {"coordinates":[-1.034194,54.594171],"type":"Point"}
}
