{
  "type": "Feature",
  "properties": {
    "iso:country":"GB",
    "wof:name":"TS11 6NE",
    "wof:placetype":"postalcode"
},
  "geometry": {"coordinates":[-1.03419357519481,54.59417124094065],"type":"Point"}
}