{
  "type": "Feature",
  "properties": {
    "iso:country": "GB",
    "wof:name": "TQ10 9EJ",
    "wof:placetype": "postalcode"
  },
  "geometry": {"coordinates":[-3.813754,50.408977],"type":"Point"}
}
