{
  "type": "Feature",
  "properties": {
    "date:inception_lower": "1996-12-01",
    "date:inception_upper": "1996-12-01",
    "iso:country": "GB",
    "wof:name": "TQ10 9EJ",
    "wof:placetype": "postalcode"
  },
  "geometry": {"coordinates":[-3.813754,50.408977],"type":"Point"}
}
