{
  "type": "Feature",
  "properties": {
    "iso:country":"GB",
    "wof:name":"BH12 1RA",
    "wof:placetype":"postalcode"
},
  "geometry": {"coordinates":[-1.91503804116813,50.73609608701522],"type":"Point"}
}