{
  "type": "Feature",
  "properties": {
    "date:inception_lower": "2005-08-01",
    "date:inception_upper": "2005-08-01",
    "iso:country": "GB",
    "wof:name": "BH12 1RA",
    "wof:placetype": "postalcode"
  },
  "geometry": {"coordinates":[-1.915038,50.736096],"type":"Point"}
}
