{
  "type": "Feature",
  "properties": {
    "iso:country":"GB",
    "wof:name":"OX11 7EP",
    "wof:placetype":"postalcode"
},
  "geometry": {"coordinates":[-1.25580450275202,51.61181744322391],"type":"Point"}
}