{
  "type": "Feature",
  "properties": {
    "iso:country": "GB",
    "wof:name": "OX11 7EP",
    "wof:placetype": "postalcode"
  },
  "geometry": {"coordinates":[-1.255804,51.611817],"type":"Point"}
}
