{
  "type": "Feature",
  "properties": {
    "iso:country":"GB",
    "wof:name":"PL21 0TA",
    "wof:placetype":"postalcode"
},
  "geometry": {"coordinates":[-3.89341783651798,50.34938945571144],"type":"Point"}
}