{
  "type": "Feature",
  "properties": {
    "iso:country":"GB",
    "wof:name":"LE8 6NP",
    "wof:placetype":"postalcode"
},
  "geometry": {"coordinates":[-1.18045471135266,52.5708386645371],"type":"Point"}
}