{
  "type": "Feature",
  "properties": {
    "iso:country":"GB",
    "wof:name":"WV4 6HR",
    "wof:placetype":"postalcode"
},
  "geometry": {"coordinates":[-2.10603869738151,52.56354751729545],"type":"Point"}
}