{
  "type": "Feature",
  "properties": {
    "iso:country":"GB",
    "wof:name":"BS48 3SH",
    "wof:placetype":"postalcode"
},
  "geometry": {"coordinates":[-2.66546617677378,51.40731474640801],"type":"Point"}
}