{
  "type": "Feature",
  "properties": {
    "iso:country": "GB",
    "wof:name": "BS48 3SH",
    "wof:placetype": "postalcode"
  },
  "geometry": {"coordinates":[-2.665398,51.407349],"type":"Point"}
}
