{
  "type": "Feature",
  "properties": {
    "date:inception_lower": "2014-03-01",
    "date:inception_upper": "2014-03-01",
    "iso:country": "GB",
    "wof:name": "NE9 7RG",
    "wof:placetype": "postalcode"
  },
  "geometry": {"coordinates":[-1.557016,54.921656],"type":"Point"}
}
