{
  "type": "Feature",
  "properties": {
    "iso:country": "GB",
    "wof:name": "NE9 7RG",
    "wof:placetype": "postalcode"
  },
  "geometry": {"coordinates":[-1.557016,54.921656],"type":"Point"}
}
