{
  "type": "Feature",
  "properties": {
    "date:inception_lower": "1980-01-01",
    "date:inception_upper": "1980-01-01",
    "iso:country": "GB",
    "wof:name": "SA10 6HE",
    "wof:placetype": "postalcode"
  },
  "geometry": {"coordinates":[-3.845294,51.661039],"type":"Point"}
}
