{
  "type": "Feature",
  "properties": {
    "iso:country":"GB",
    "wof:name":"SA10 6HE",
    "wof:placetype":"postalcode"
},
  "geometry": {"coordinates":[-3.84529433492026,51.66103860103656],"type":"Point"}
}