{
  "type": "Feature",
  "properties": {
    "iso:country":"GB",
    "wof:name":"TR27 4LW",
    "wof:placetype":"postalcode"
},
  "geometry": {"coordinates":[-5.41208157501654,50.19018841922647],"type":"Point"}
}