{
  "type": "Feature",
  "properties": {
    "iso:country": "GB",
    "wof:name": "YO62 5GZ",
    "wof:placetype": "postalcode"
  },
  "geometry": {"coordinates":[-1.066217,54.344718],"type":"Point"}
}
