{
  "type": "Feature",
  "properties": {
    "date:inception_lower":"2009-07-01",
    "date:inception_upper":"2009-07-31",
    "iso:country":"GB",
    "wof:name":"YO62 5GZ",
    "wof:placetype":"postalcode"
},
  "geometry": {"coordinates":[-1.066217,54.344718],"type":"Point"}
}