{
  "type": "Feature",
  "properties": {
    "iso:country":"GB",
    "wof:name":"LL22 8PD",
    "wof:placetype":"postalcode"
},
  "geometry": {"coordinates":[-3.59757508112461,53.24333719702536],"type":"Point"}
}