{
  "type": "Feature",
  "properties": {
    "iso:country": "GB",
    "wof:name": "LL22 8PD",
    "wof:placetype": "postalcode"
  },
  "geometry": {"coordinates":[-3.597575,53.243337],"type":"Point"}
}
