{
  "type": "Feature",
  "properties": {
    "iso:country": "GB",
    "wof:name": "EH22 3JF",
    "wof:placetype": "postalcode"
  },
  "geometry": {"coordinates":[-3.085258,55.884338],"type":"Point"}
}
