{
  "type": "Feature",
  "properties": {
    "iso:country":"GB",
    "wof:name":"EH22 3JF",
    "wof:placetype":"postalcode"
},
  "geometry": {"coordinates":[-3.08525403279077,55.88434259040561],"type":"Point"}
}