{
  "type": "Feature",
  "properties": {
    "iso:country":"GB",
    "wof:name":"BD9 5DB",
    "wof:placetype":"postalcode"
},
  "geometry": {"coordinates":[-1.79018648225093,53.80909144472558],"type":"Point"}
}