{
  "type": "Feature",
  "properties": {
    "iso:country":"GB",
    "wof:name":"LS23 6JS",
    "wof:placetype":"postalcode"
},
  "geometry": {"coordinates":[-1.35184140824745,53.89395374845562],"type":"Point"}
}