{
  "type": "Feature",
  "properties": {
    "iso:country": "GB",
    "wof:name": "CV21 2QE",
    "wof:placetype": "postalcode"
  },
  "geometry": {"coordinates":[-1.260273,52.373669],"type":"Point"}
}
