{
  "type": "Feature",
  "properties": {
    "iso:country": "GB",
    "wof:name": "CV21 2QE",
    "wof:placetype": "postalcode"
  },
  "geometry": {"coordinates":[-1.260299,52.373751],"type":"Point"}
}
