{
  "type": "Feature",
  "properties": {
    "iso:country":"GB",
    "wof:name":"NN5 6DN",
    "wof:placetype":"postalcode"
},
  "geometry": {"coordinates":[-0.93507504578041,52.24923969330393],"type":"Point"}
}