{
  "type": "Feature",
  "properties": {
    "iso:country": "GB",
    "wof:name": "KT23 4EZ",
    "wof:placetype": "postalcode"
  },
  "geometry": {"coordinates":[-0.378908,51.274033],"type":"Point"}
}
