{
  "type": "Feature",
  "properties": {
    "date:inception_lower":"1980-01-01",
    "date:inception_upper":"1980-01-31",
    "iso:country":"GB",
    "wof:name":"KT23 4EZ",
    "wof:placetype":"postalcode"
},
  "geometry": {"coordinates":[-0.378908,51.274033],"type":"Point"}
}