{
  "type": "Feature",
  "properties": {
    "iso:country":"GB",
    "wof:name":"SW4 0PT",
    "wof:placetype":"postalcode"
},
  "geometry": {"coordinates":[-0.15072233344858,51.46540800070315],"type":"Point"}
}