{
  "type": "Feature",
  "properties": {
    "iso:country":"GB",
    "wof:name":"SM4 4NW",
    "wof:placetype":"postalcode"
},
  "geometry": {"coordinates":[-0.22636946653118,51.3883507316807],"type":"Point"}
}