{
  "type": "Feature",
  "properties": {
    "iso:country": "GB",
    "wof:name": "SM4 4NW",
    "wof:placetype": "postalcode"
  },
  "geometry": {"coordinates":[-0.226369,51.388351],"type":"Point"}
}
