{
  "type": "Feature",
  "properties": {
    "date:inception_lower": "1990-02-01",
    "date:inception_upper": "1990-02-01",
    "iso:country": "GB",
    "wof:name": "TR1 3BL",
    "wof:placetype": "postalcode"
  },
  "geometry": {"coordinates":[-5.055978,50.263065],"type":"Point"}
}
