{
  "type": "Feature",
  "properties": {
    "iso:country": "GB",
    "wof:name": "PL21 9JE",
    "wof:placetype": "postalcode"
  },
  "geometry": {"coordinates":[-3.934045,50.391308],"type":"Point"}
}
