{
  "type": "Feature",
  "properties": {
    "iso:country":"GB",
    "wof:name":"L23 6TR",
    "wof:placetype":"postalcode"
},
  "geometry": {"coordinates":[-3.05439018108822,53.49503322424669],"type":"Point"}
}