{
  "type": "Feature",
  "properties": {
    "iso:country":"GB",
    "wof:name":"DH7 9TN",
    "wof:placetype":"postalcode"
},
  "geometry": {"coordinates":[-1.65983076042044,54.80151475978531],"type":"Point"}
}