{
  "type": "Feature",
  "properties": {
    "iso:country": "GB",
    "wof:name": "RH17 5PS",
    "wof:placetype": "postalcode"
  },
  "geometry": {"coordinates":[-0.200051,50.995032],"type":"Point"}
}
