{
  "type": "Feature",
  "properties": {
    "iso:country": "GB",
    "wof:name": "PL2 1JB",
    "wof:placetype": "postalcode"
  },
  "geometry": {"coordinates":[-4.171486,50.382906],"type":"Point"}
}
