{
  "type": "Feature",
  "properties": {
    "iso:country":"GB",
    "wof:name":"PL2 1JB",
    "wof:placetype":"postalcode"
},
  "geometry": {"coordinates":[-4.17148632894218,50.38290640896608],"type":"Point"}
}