{
  "type": "Feature",
  "properties": {
    "iso:country":"GB",
    "wof:name":"CT17 9LG",
    "wof:placetype":"postalcode"
},
  "geometry": {"coordinates":[1.28869458709369,51.11720796586545],"type":"Point"}
}