{
  "type": "Feature",
  "properties": {
    "iso:country":"GB",
    "wof:name":"B34 6TY",
    "wof:placetype":"postalcode"
},
  "geometry": {"coordinates":[-1.77999081486759,52.49516698497671],"type":"Point"}
}