{
  "type": "Feature",
  "properties": {
    "iso:country":"GB",
    "wof:name":"DN14 7EJ",
    "wof:placetype":"postalcode"
},
  "geometry": {"coordinates":[-0.87482111714947,53.7400548394203],"type":"Point"}
}