{
  "type": "Feature",
  "properties": {
    "iso:country":"GB",
    "wof:name":"SE14 5HD",
    "wof:placetype":"postalcode"
},
  "geometry": {"coordinates":[-0.04762293391868,51.47423088484943],"type":"Point"}
}