{
  "type": "Feature",
  "properties": {
    "date:inception_lower": "1998-12-01",
    "date:inception_upper": "1998-12-01",
    "iso:country": "GB",
    "wof:name": "CB1 7AJ",
    "wof:placetype": "postalcode"
  },
  "geometry": {"coordinates":[0.14277,52.188057],"type":"Point"}
}
