{
  "type": "Feature",
  "properties": {
    "date:inception_lower": "1991-01-01",
    "date:inception_upper": "1991-01-01",
    "iso:country": "GB",
    "wof:name": "LS27 7UN",
    "wof:placetype": "postalcode"
  },
  "geometry": {"coordinates":[-1.604895,53.758301],"type":"Point"}
}
