{
  "type": "Feature",
  "properties": {
    "iso:country": "GB",
    "wof:name": "LS27 7UN",
    "wof:placetype": "postalcode"
  },
  "geometry": {"coordinates":[-1.604895,53.758301],"type":"Point"}
}
