{
  "type": "Feature",
  "properties": {
    "date:inception_lower": "2001-06-01",
    "date:inception_upper": "2001-06-01",
    "iso:country": "GB",
    "wof:name": "DE72 3TR",
    "wof:placetype": "postalcode"
  },
  "geometry": {"coordinates":[-1.390576,52.888625],"type":"Point"}
}
