{
  "type": "Feature",
  "properties": {
    "iso:country":"GB",
    "wof:name":"SW16 2JJ",
    "wof:placetype":"postalcode"
},
  "geometry": {"coordinates":[-0.1154993053686,51.43414631538575],"type":"Point"}
}