{
  "type": "Feature",
  "properties": {
    "date:inception_lower": "1980-01-01",
    "date:inception_upper": "1980-01-01",
    "iso:country": "GB",
    "wof:name": "SW16 2JJ",
    "wof:placetype": "postalcode"
  },
  "geometry": {"coordinates":[-0.115415,51.434172],"type":"Point"}
}
