{
  "type": "Feature",
  "properties": {
    "iso:country":"GB",
    "wof:name":"SO53 3SD",
    "wof:placetype":"postalcode"
},
  "geometry": {"coordinates":[-1.38828249000192,50.9701650495976],"type":"Point"}
}