{
  "type": "Feature",
  "properties": {
    "date:inception_lower": "1994-12-01",
    "date:inception_upper": "1994-12-01",
    "iso:country": "GB",
    "wof:name": "SO53 3SD",
    "wof:placetype": "postalcode"
  },
  "geometry": {"coordinates":[-1.388286,50.970175],"type":"Point"}
}
