{
  "type": "Feature",
  "properties": {
    "iso:country":"GB",
    "wof:name":"B27 6SB",
    "wof:placetype":"postalcode"
},
  "geometry": {"coordinates":[-1.8094966120904,52.45003445015151],"type":"Point"}
}