{
  "type": "Feature",
  "properties": {
    "iso:country":"GB",
    "wof:name":"S10 3EW",
    "wof:placetype":"postalcode"
},
  "geometry": {"coordinates":[-1.5104026224654,53.37225973083268],"type":"Point"}
}