{
  "type": "Feature",
  "properties": {
    "date:inception_lower": "1980-01-01",
    "date:inception_upper": "1980-01-01",
    "iso:country": "GB",
    "wof:name": "S10 3EW",
    "wof:placetype": "postalcode"
  },
  "geometry": {"coordinates":[-1.510403,53.37226],"type":"Point"}
}
