{
  "type": "Feature",
  "properties": {
    "iso:country":"GB",
    "wof:name":"IV24 3AP",
    "wof:placetype":"postalcode"
},
  "geometry": {"coordinates":[-4.3336935626857,57.89253396368004],"type":"Point"}
}