{
  "type": "Feature",
  "properties": {
    "iso:country":"GB",
    "wof:name":"SN5 4FG",
    "wof:placetype":"postalcode"
},
  "geometry": {"coordinates":[-1.88694905968662,51.58769471593479],"type":"Point"}
}