{
  "type": "Feature",
  "properties": {
    "date:inception_lower":"2008-01-01",
    "date:inception_upper":"2008-01-31",
    "iso:country":"GB",
    "wof:name":"SN5 4FG",
    "wof:placetype":"postalcode"
},
  "geometry": {"coordinates":[-1.886949,51.587695],"type":"Point"}
}