{
  "type": "Feature",
  "properties": {
    "iso:country": "GB",
    "wof:name": "SN5 4FG",
    "wof:placetype": "postalcode"
  },
  "geometry": {"coordinates":[-1.886949,51.587695],"type":"Point"}
}
