{
  "type": "Feature",
  "properties": {
    "iso:country":"GB",
    "wof:name":"HS2 0LW",
    "wof:placetype":"postalcode"
},
  "geometry": {"coordinates":[-6.33571863569526,58.25640473699902],"type":"Point"}
}