{
  "type": "Feature",
  "properties": {
    "iso:country": "GB",
    "wof:name": "HS2 0LW",
    "wof:placetype": "postalcode"
  },
  "geometry": {"coordinates":[-6.335772,58.256337],"type":"Point"}
}
