{
  "type": "Feature",
  "properties": {
    "iso:country":"GB",
    "wof:name":"TR15 3NB",
    "wof:placetype":"postalcode"
},
  "geometry": {"coordinates":[-5.25638528552233,50.2290451891049],"type":"Point"}
}