{
  "type": "Feature",
  "properties": {
    "iso:country":"GB",
    "wof:name":"WN7 5SH",
    "wof:placetype":"postalcode"
},
  "geometry": {"coordinates":[-2.52707840368448,53.50471582109871],"type":"Point"}
}