{
  "type": "Feature",
  "properties": {
    "date:inception_lower": "1984-10-01",
    "date:inception_upper": "1984-10-01",
    "iso:country": "GB",
    "wof:name": "WN7 5SH",
    "wof:placetype": "postalcode"
  },
  "geometry": {"coordinates":[-2.526882,53.504751],"type":"Point"}
}
