{
  "type": "Feature",
  "properties": {
    "date:inception_lower": "1980-01-01",
    "date:inception_upper": "1980-01-01",
    "iso:country": "GB",
    "wof:name": "CB11 3LB",
    "wof:placetype": "postalcode"
  },
  "geometry": {"coordinates":[0.26338,51.979193],"type":"Point"}
}
