{
  "type": "Feature",
  "properties": {
    "iso:country":"GB",
    "wof:name":"CB11 3LB",
    "wof:placetype":"postalcode"
},
  "geometry": {"coordinates":[0.26338029442589,51.97919316389351],"type":"Point"}
}