{
  "type": "Feature",
  "properties": {
    "iso:country":"GB",
    "wof:name":"NE29 7AF",
    "wof:placetype":"postalcode"
},
  "geometry": {"coordinates":[-1.47367964875167,55.00339575746335],"type":"Point"}
}