{
  "type": "Feature",
  "properties": {
    "date:inception_lower": "1984-10-01",
    "date:inception_upper": "1984-10-01",
    "iso:country": "GB",
    "wof:name": "L4 1YB",
    "wof:placetype": "postalcode"
  },
  "geometry": {"coordinates":[-2.97995,53.434021],"type":"Point"}
}
