{
  "type": "Feature",
  "properties": {
    "date:inception_lower": "1980-01-01",
    "date:inception_upper": "1980-01-01",
    "iso:country": "GB",
    "wof:name": "ML10 6TD",
    "wof:placetype": "postalcode"
  },
  "geometry": {"coordinates":[-4.030644,55.699337],"type":"Point"}
}
