{
  "type": "Feature",
  "properties": {
    "iso:country": "GB",
    "wof:name": "LS21 3NQ",
    "wof:placetype": "postalcode"
  },
  "geometry": {"coordinates":[-1.699012,53.904322],"type":"Point"}
}
