{
  "type": "Feature",
  "properties": {
    "iso:country":"GB",
    "wof:name":"LS21 3NQ",
    "wof:placetype":"postalcode"
},
  "geometry": {"coordinates":[-1.69901211547099,53.90432208964366],"type":"Point"}
}