{
  "type": "Feature",
  "properties": {
    "iso:country":"GB",
    "wof:name":"BH8 0PG",
    "wof:placetype":"postalcode"
},
  "geometry": {"coordinates":[-1.84504734772346,50.75402751224865],"type":"Point"}
}