{
  "type": "Feature",
  "properties": {
    "date:inception_lower":"1985-04-01",
    "date:inception_upper":"1985-04-30",
    "iso:country":"GB",
    "wof:name":"BH8 0PG",
    "wof:placetype":"postalcode"
},
  "geometry": {"coordinates":[-1.845047,50.754028],"type":"Point"}
}