{
  "type": "Feature",
  "properties": {
    "iso:country": "GB",
    "wof:name": "BH8 0PG",
    "wof:placetype": "postalcode"
  },
  "geometry": {"coordinates":[-1.845047,50.754028],"type":"Point"}
}
