{
  "type": "Feature",
  "properties": {
    "date:inception_lower": "2013-03-01",
    "date:inception_upper": "2013-03-01",
    "iso:country": "GB",
    "wof:name": "TS17 8FW",
    "wof:placetype": "postalcode"
  },
  "geometry": {"coordinates":[-1.292706,54.547652],"type":"Point"}
}
