{
  "type": "Feature",
  "properties": {
    "iso:country":"GB",
    "wof:name":"BS37 6LG",
    "wof:placetype":"postalcode"
},
  "geometry": {"coordinates":[-2.38653724808518,51.53695749585685],"type":"Point"}
}