{
  "type": "Feature",
  "properties": {
    "date:inception_lower": "2008-02-01",
    "date:inception_upper": "2008-02-01",
    "iso:country": "GB",
    "wof:name": "WA10 1GH",
    "wof:placetype": "postalcode"
  },
  "geometry": {"coordinates":[-2.730351,53.454047],"type":"Point"}
}
