{
  "type": "Feature",
  "properties": {
    "iso:country":"GB",
    "wof:name":"WA10 1GH",
    "wof:placetype":"postalcode"
},
  "geometry": {"coordinates":[-2.7303507778229,53.45404693227467],"type":"Point"}
}