{
  "type": "Feature",
  "properties": {
    "date:inception_lower": "1980-01-01",
    "date:inception_upper": "1980-01-01",
    "iso:country": "GB",
    "wof:name": "SN3 2AR",
    "wof:placetype": "postalcode"
  },
  "geometry": {"coordinates":[-1.743655,51.55074],"type":"Point"}
}
