{
  "type": "Feature",
  "properties": {
    "iso:country":"GB",
    "wof:name":"CH8 7RX",
    "wof:placetype":"postalcode"
},
  "geometry": {"coordinates":[-3.21752381358673,53.26797107450475],"type":"Point"}
}