{
  "type": "Feature",
  "properties": {
    "iso:country":"GB",
    "wof:name":"SW15 2RE",
    "wof:placetype":"postalcode"
},
  "geometry": {"coordinates":[-0.20758679284389,51.45740652656647],"type":"Point"}
}