{
  "type": "Feature",
  "properties": {
    "date:inception_lower":"1990-02-01",
    "date:inception_upper":"1990-02-28",
    "iso:country":"GB",
    "wof:name":"SW15 2RE",
    "wof:placetype":"postalcode"
},
  "geometry": {"coordinates":[-0.207587,51.457407],"type":"Point"}
}