{
  "type": "Feature",
  "properties": {
    "iso:country":"GB",
    "wof:name":"CW9 5RF",
    "wof:placetype":"postalcode"
},
  "geometry": {"coordinates":[-2.50828744613411,53.26204883782418],"type":"Point"}
}