{
  "type": "Feature",
  "properties": {
    "iso:country": "GB",
    "wof:name": "DH6 5LD",
    "wof:placetype": "postalcode"
  },
  "geometry": {"coordinates":[-1.536428,54.708922],"type":"Point"}
}
