{
  "type": "Feature",
  "properties": {
    "iso:country":"GB",
    "wof:name":"AB54 8HH",
    "wof:placetype":"postalcode"
},
  "geometry": {"coordinates":[-2.77818455036991,57.44740927969331],"type":"Point"}
}