{
  "type": "Feature",
  "properties": {
    "iso:country":"GB",
    "wof:name":"NE26 3LT",
    "wof:placetype":"postalcode"
},
  "geometry": {"coordinates":[-1.45813922346411,55.04403531917452],"type":"Point"}
}