{
  "type": "Feature",
  "properties": {
    "iso:country":"GB",
    "wof:name":"CF23 9JQ",
    "wof:placetype":"postalcode"
},
  "geometry": {"coordinates":[-3.15409756947192,51.50945457299619],"type":"Point"}
}