{
  "type": "Feature",
  "properties": {
    "date:inception_lower":"2006-04-01",
    "date:inception_upper":"2006-04-30",
    "iso:country":"GB",
    "wof:name":"IP13 7LZ",
    "wof:placetype":"postalcode"
},
  "geometry": {"coordinates":[1.289907,52.256593],"type":"Point"}
}