{
  "type": "Feature",
  "properties": {
    "date:inception_lower":"1980-01-01",
    "date:inception_upper":"1980-01-31",
    "iso:country":"GB",
    "wof:name":"NN2 8JT",
    "wof:placetype":"postalcode"
},
  "geometry": {"coordinates":[-0.895879,52.269199],"type":"Point"}
}