{
  "type": "Feature",
  "properties": {
    "iso:country":"GB",
    "wof:name":"NN18 0BD",
    "wof:placetype":"postalcode"
},
  "geometry": {"coordinates":[-0.72607303964654,52.49022401988584],"type":"Point"}
}