{
  "type": "Feature",
  "properties": {
    "date:inception_lower":"1980-01-01",
    "date:inception_upper":"1980-01-31",
    "iso:country":"GB",
    "wof:name":"NN18 0BD",
    "wof:placetype":"postalcode"
},
  "geometry": {"coordinates":[-0.726073,52.490224],"type":"Point"}
}