{
  "type": "Feature",
  "properties": {
    "date:inception_lower": "1991-09-01",
    "date:inception_upper": "1991-09-01",
    "iso:country": "GB",
    "wof:name": "IP33 3TA",
    "wof:placetype": "postalcode"
  },
  "geometry": {"coordinates":[0.693526,52.250176],"type":"Point"}
}
