{
  "type": "Feature",
  "properties": {
    "iso:country":"GB",
    "wof:name":"SK7 3LH",
    "wof:placetype":"postalcode"
},
  "geometry": {"coordinates":[-2.17017823296148,53.37674538262763],"type":"Point"}
}