{
  "type": "Feature",
  "properties": {
    "date:inception_lower":"1980-01-01",
    "date:inception_upper":"1980-01-31",
    "iso:country":"GB",
    "wof:name":"SK7 3LH",
    "wof:placetype":"postalcode"
},
  "geometry": {"coordinates":[-2.170178,53.376745],"type":"Point"}
}