{
  "type": "Feature",
  "properties": {
    "iso:country": "GB",
    "wof:name": "YO18 8AQ",
    "wof:placetype": "postalcode"
  },
  "geometry": {"coordinates":[-0.782932,54.248271],"type":"Point"}
}
