{
  "type": "Feature",
  "properties": {
    "date:inception_lower":"1980-01-01",
    "date:inception_upper":"1980-01-31",
    "iso:country":"GB",
    "wof:name":"YO18 8AQ",
    "wof:placetype":"postalcode"
},
  "geometry": {"coordinates":[-0.782932,54.248271],"type":"Point"}
}