{
  "type": "Feature",
  "properties": {
    "iso:country":"GB",
    "wof:name":"NE21 4NB",
    "wof:placetype":"postalcode"
},
  "geometry": {"coordinates":[-1.74093670416169,54.97190735674529],"type":"Point"}
}