{
  "type": "Feature",
  "properties": {
    "iso:country":"GB",
    "wof:name":"MK43 0UB",
    "wof:placetype":"postalcode"
},
  "geometry": {"coordinates":[-0.57742522222107,52.01508229247894],"type":"Point"}
}