{
  "type": "Feature",
  "properties": {
    "date:inception_lower": "1994-05-01",
    "date:inception_upper": "1994-05-01",
    "iso:country": "GB",
    "wof:name": "M46 0DZ",
    "wof:placetype": "postalcode"
  },
  "geometry": {"coordinates":[-2.492717,53.525437],"type":"Point"}
}
