{
  "type": "Feature",
  "properties": {
    "iso:country":"GB",
    "wof:name":"DT1 1QZ",
    "wof:placetype":"postalcode"
},
  "geometry": {"coordinates":[-2.43998834065373,50.70909099666883],"type":"Point"}
}