{
  "type": "Feature",
  "properties": {
    "iso:country": "GB",
    "wof:name": "DT1 1QZ",
    "wof:placetype": "postalcode"
  },
  "geometry": {"coordinates":[-2.439988,50.709091],"type":"Point"}
}
