{
  "type": "Feature",
  "properties": {
    "iso:country":"GB",
    "wof:name":"NE34 6BB",
    "wof:placetype":"postalcode"
},
  "geometry": {"coordinates":[-1.41511255694263,54.97563927228764],"type":"Point"}
}