{
  "type": "Feature",
  "properties": {
    "iso:country": "GB",
    "wof:name": "NE34 6BB",
    "wof:placetype": "postalcode"
  },
  "geometry": {"coordinates":[-1.415113,54.975639],"type":"Point"}
}
