{
  "type": "Feature",
  "properties": {
    "iso:country":"GB",
    "wof:name":"BH23 4EE",
    "wof:placetype":"postalcode"
},
  "geometry": {"coordinates":[-1.73247392309452,50.73447168441476],"type":"Point"}
}