{
  "type": "Feature",
  "properties": {
    "iso:country":"GB",
    "wof:name":"DL8 5EX",
    "wof:placetype":"postalcode"
},
  "geometry": {"coordinates":[-1.82123045478507,54.30695455818029],"type":"Point"}
}