{
  "type": "Feature",
  "properties": {
    "iso:country":"GB",
    "wof:name":"HR4 9XH",
    "wof:placetype":"postalcode"
},
  "geometry": {"coordinates":[-2.73569341446398,52.06487613306368],"type":"Point"}
}