{
  "type": "Feature",
  "properties": {
    "iso:country": "GB",
    "wof:name": "HR4 9XH",
    "wof:placetype": "postalcode"
  },
  "geometry": {"coordinates":[-2.735693,52.064876],"type":"Point"}
}
