{
  "type": "Feature",
  "properties": {
    "iso:country": "GB",
    "wof:name": "DY13 0TS",
    "wof:placetype": "postalcode"
  },
  "geometry": {"coordinates":[-2.310304,52.326691],"type":"Point"}
}
