{
  "type": "Feature",
  "properties": {
    "iso:country":"GB",
    "wof:name":"DY13 0TS",
    "wof:placetype":"postalcode"
},
  "geometry": {"coordinates":[-2.31030753293218,52.32667782900393],"type":"Point"}
}