{
  "type": "Feature",
  "properties": {
    "iso:country": "GB",
    "wof:name": "KA1 1SR",
    "wof:placetype": "postalcode"
  },
  "geometry": {"coordinates":[-4.50721,55.600211],"type":"Point"}
}
