{
  "type": "Feature",
  "properties": {
    "date:inception_lower": "2020-11-01",
    "date:inception_upper": "2020-11-01",
    "iso:country": "GB",
    "wof:name": "MK17 8WW",
    "wof:placetype": "postalcode"
  },
  "geometry": {"coordinates":[-0.673081,52.030424],"type":"Point"}
}
