{
  "type": "Feature",
  "properties": {
    "date:inception_lower": "2005-12-01",
    "date:inception_upper": "2005-12-01",
    "iso:country": "GB",
    "wof:name": "B16 8FQ",
    "wof:placetype": "postalcode"
  },
  "geometry": {"coordinates":[-1.918577,52.476389],"type":"Point"}
}
