{
  "type": "Feature",
  "properties": {
    "iso:country":"GB",
    "wof:name":"SY4 3QP",
    "wof:placetype":"postalcode"
},
  "geometry": {"coordinates":[-2.78224591674757,52.77441159046985],"type":"Point"}
}