{
  "type": "Feature",
  "properties": {
    "iso:country": "GB",
    "wof:name": "SY4 3QP",
    "wof:placetype": "postalcode"
  },
  "geometry": {"coordinates":[-2.782246,52.774412],"type":"Point"}
}
