{
  "type": "Feature",
  "properties": {
    "iso:country":"GB",
    "wof:name":"TQ1 2DE",
    "wof:placetype":"postalcode"
},
  "geometry": {"coordinates":[-3.52445551994026,50.46167715261169],"type":"Point"}
}