{
  "type": "Feature",
  "properties": {
    "iso:country":"GB",
    "wof:name":"S18 1PJ",
    "wof:placetype":"postalcode"
},
  "geometry": {"coordinates":[-1.47918566358126,53.30313897446666],"type":"Point"}
}