{
  "type": "Feature",
  "properties": {
    "iso:country": "GB",
    "wof:name": "NE11 9FJ",
    "wof:placetype": "postalcode"
  },
  "geometry": {"coordinates":[-1.639988,54.952589],"type":"Point"}
}
