{
  "type": "Feature",
  "properties": {
    "iso:country": "GB",
    "wof:name": "DG1 3TS",
    "wof:placetype": "postalcode"
  },
  "geometry": {"coordinates":[-3.573289,55.090543],"type":"Point"}
}
