{
  "type": "Feature",
  "properties": {
    "iso:country": "GB",
    "wof:name": "DD10 0DR",
    "wof:placetype": "postalcode"
  },
  "geometry": {"coordinates":[-2.450804,56.783622],"type":"Point"}
}
