{
  "type": "Feature",
  "properties": {
    "iso:country":"GB",
    "wof:name":"CW8 2TH",
    "wof:placetype":"postalcode"
},
  "geometry": {"coordinates":[-2.62654632987626,53.24091014121392],"type":"Point"}
}