{
  "type": "Feature",
  "properties": {
    "iso:country": "GB",
    "wof:name": "L36 6LX",
    "wof:placetype": "postalcode"
  },
  "geometry": {"coordinates":[-2.820747,53.409289],"type":"Point"}
}
