{
  "type": "Feature",
  "properties": {
    "iso:country":"GB",
    "wof:name":"L36 6LX",
    "wof:placetype":"postalcode"
},
  "geometry": {"coordinates":[-2.82074675475508,53.40928910405997],"type":"Point"}
}