{
  "type": "Feature",
  "properties": {
    "date:inception_lower":"2003-08-01",
    "date:inception_upper":"2003-08-31",
    "iso:country":"GB",
    "wof:name":"BH15 2AA",
    "wof:placetype":"postalcode"
},
  "geometry": {"coordinates":[-1.990767,50.726522],"type":"Point"}
}