{
  "type": "Feature",
  "properties": {
    "iso:country": "GB",
    "wof:name": "SK8 3LW",
    "wof:placetype": "postalcode"
  },
  "geometry": {"coordinates":[-2.227705,53.362897],"type":"Point"}
}
