{
  "type": "Feature",
  "properties": {
    "iso:country":"GB",
    "wof:name":"SK8 3LW",
    "wof:placetype":"postalcode"
},
  "geometry": {"coordinates":[-2.22770531567996,53.36289679980896],"type":"Point"}
}