{
  "type": "Feature",
  "properties": {
    "iso:country":"GB",
    "wof:name":"NG11 9GJ",
    "wof:placetype":"postalcode"
},
  "geometry": {"coordinates":[-1.18202520442282,52.89815060755834],"type":"Point"}
}