{
  "type": "Feature",
  "properties": {
    "iso:country":"GB",
    "wof:name":"E14 3NH",
    "wof:placetype":"postalcode"
},
  "geometry": {"coordinates":[-0.01295161863208,51.49766789594003],"type":"Point"}
}