{
  "type": "Feature",
  "properties": {
    "date:inception_lower":"1994-12-01",
    "date:inception_upper":"1994-12-31",
    "iso:country":"GB",
    "wof:name":"E14 3NH",
    "wof:placetype":"postalcode"
},
  "geometry": {"coordinates":[-0.012778,51.498053],"type":"Point"}
}