{
  "type": "Feature",
  "properties": {
    "iso:country":"GB",
    "wof:name":"N1 9QN",
    "wof:placetype":"postalcode"
},
  "geometry": {"coordinates":[-0.11664088850372,51.53435093123527],"type":"Point"}
}