{
  "type": "Feature",
  "properties": {
    "iso:country": "GB",
    "wof:name": "N1 9QN",
    "wof:placetype": "postalcode"
  },
  "geometry": {"coordinates":[-0.116641,51.534351],"type":"Point"}
}
