{
  "type": "Feature",
  "properties": {
    "iso:country": "GB",
    "wof:name": "G77 5GS",
    "wof:placetype": "postalcode"
  },
  "geometry": {"coordinates":[-4.349509,55.763775],"type":"Point"}
}
