{
  "type": "Feature",
  "properties": {
    "date:inception_lower": "2019-12-01",
    "date:inception_upper": "2019-12-01",
    "iso:country": "GB",
    "wof:name": "G77 5GS",
    "wof:placetype": "postalcode"
  },
  "geometry": {"coordinates":[-4.348231,55.763728],"type":"Point"}
}
