{
  "type": "Feature",
  "properties": {
    "date:inception_lower":"1980-01-01",
    "date:inception_upper":"1980-01-31",
    "iso:country":"GB",
    "wof:name":"RM5 3RP",
    "wof:placetype":"postalcode"
},
  "geometry": {"coordinates":[0.169607,51.600746],"type":"Point"}
}