{
  "type": "Feature",
  "properties": {
    "iso:country": "GB",
    "wof:name": "RM5 3RP",
    "wof:placetype": "postalcode"
  },
  "geometry": {"coordinates":[0.169607,51.600746],"type":"Point"}
}
