{
  "type": "Feature",
  "properties": {
    "iso:country":"GB",
    "wof:name":"SR8 5BN",
    "wof:placetype":"postalcode"
},
  "geometry": {"coordinates":[-1.34027249597798,54.76500725216301],"type":"Point"}
}