{
  "type": "Feature",
  "properties": {
    "iso:country": "GB",
    "wof:name": "SR8 5BN",
    "wof:placetype": "postalcode"
  },
  "geometry": {"coordinates":[-1.340272,54.765007],"type":"Point"}
}
