{
  "type": "Feature",
  "properties": {
    "date:inception_lower": "1992-08-01",
    "date:inception_upper": "1992-08-01",
    "iso:country": "GB",
    "wof:name": "SN2 1EL",
    "wof:placetype": "postalcode"
  },
  "geometry": {"coordinates":[-1.793675,51.565755],"type":"Point"}
}
