{
  "type": "Feature",
  "properties": {
    "iso:country":"GB",
    "wof:name":"CT1 9SB",
    "wof:placetype":"postalcode"
},
  "geometry": {"coordinates":[1.09309142286073,51.28345686080868],"type":"Point"}
}