{
  "type": "Feature",
  "properties": {
    "iso:country":"GB",
    "wof:name":"CA2 4UJ",
    "wof:placetype":"postalcode"
},
  "geometry": {"coordinates":[-2.92405578378263,54.85047752950817],"type":"Point"}
}