{
  "type": "Feature",
  "properties": {
    "iso:country":"GB",
    "wof:name":"TD9 0LH",
    "wof:placetype":"postalcode"
},
  "geometry": {"coordinates":[-2.94872928046305,55.33351518165679],"type":"Point"}
}