{
  "type": "Feature",
  "properties": {
    "date:inception_lower":"2015-09-01",
    "date:inception_upper":"2015-09-30",
    "iso:country":"GB",
    "wof:name":"PR9 9DQ",
    "wof:placetype":"postalcode"
},
  "geometry": {"coordinates":[-2.968197,53.667509],"type":"Point"}
}