{
  "type": "Feature",
  "properties": {
    "iso:country":"GB",
    "wof:name":"PR9 9DQ",
    "wof:placetype":"postalcode"
},
  "geometry": {"coordinates":[-2.96819704205334,53.66750901529301],"type":"Point"}
}