{
  "type": "Feature",
  "properties": {
    "date:inception_lower": "1980-01-01",
    "date:inception_upper": "1980-01-01",
    "iso:country": "GB",
    "wof:name": "KT10 9TT",
    "wof:placetype": "postalcode"
  },
  "geometry": {"coordinates":[-0.359083,51.370708],"type":"Point"}
}
