{
  "type": "Feature",
  "properties": {
    "iso:country":"GB",
    "wof:name":"G32 8HH",
    "wof:placetype":"postalcode"
},
  "geometry": {"coordinates":[-4.16415664633053,55.84216604009359],"type":"Point"}
}