{
  "type": "Feature",
  "properties": {
    "date:inception_lower": "2022-12-01",
    "date:inception_upper": "2022-12-01",
    "iso:country": "GB",
    "wof:name": "TW18 4JT",
    "wof:placetype": "postalcode"
  },
  "geometry": {"coordinates":[-0.494707,51.437498],"type":"Point"}
}
