{
  "type": "Feature",
  "properties": {
    "iso:country": "GB",
    "wof:name": "BA12 7QZ",
    "wof:placetype": "postalcode"
  },
  "geometry": {"coordinates":[-2.249692,51.198369],"type":"Point"}
}
