{
  "type": "Feature",
  "properties": {
    "iso:country":"GB",
    "wof:name":"PL26 7BY",
    "wof:placetype":"postalcode"
},
  "geometry": {"coordinates":[-4.81829302204314,50.31924330796328],"type":"Point"}
}