{
  "type": "Feature",
  "properties": {
    "iso:country":"GB",
    "wof:name":"RM5 3AA",
    "wof:placetype":"postalcode"
},
  "geometry": {"coordinates":[0.17211086512448,51.5851327958075],"type":"Point"}
}