{
  "type": "Feature",
  "properties": {
    "iso:country":"GB",
    "wof:name":"CO12 3DE",
    "wof:placetype":"postalcode"
},
  "geometry": {"coordinates":[1.28705924148052,51.94631873402827],"type":"Point"}
}