{
  "type": "Feature",
  "properties": {
    "date:inception_lower":"1997-06-01",
    "date:inception_upper":"1997-06-30",
    "iso:country":"GB",
    "wof:name":"LN5 9PF",
    "wof:placetype":"postalcode"
},
  "geometry": {"coordinates":[-0.642507,53.130273],"type":"Point"}
}