{
  "type": "Feature",
  "properties": {
    "iso:country":"GB",
    "wof:name":"NW6 6PX",
    "wof:placetype":"postalcode"
},
  "geometry": {"coordinates":[-0.19834667730273,51.53812512113917],"type":"Point"}
}