{
  "type": "Feature",
  "properties": {
    "iso:country":"GB",
    "wof:name":"EX7 9AG",
    "wof:placetype":"postalcode"
},
  "geometry": {"coordinates":[-3.47378424487946,50.58101791010115],"type":"Point"}
}