{
  "type": "Feature",
  "properties": {
    "iso:country": "GB",
    "wof:name": "ME13 0HJ",
    "wof:placetype": "postalcode"
  },
  "geometry": {"coordinates":[0.840266,51.270269],"type":"Point"}
}
