{
  "type": "Feature",
  "properties": {
    "iso:country":"GB",
    "wof:name":"ME13 0HJ",
    "wof:placetype":"postalcode"
},
  "geometry": {"coordinates":[0.84026566735001,51.27026894374133],"type":"Point"}
}