{
  "type": "Feature",
  "properties": {
    "iso:country":"GB",
    "wof:name":"BA11 4DA",
    "wof:placetype":"postalcode"
},
  "geometry": {"coordinates":[-2.33248019861243,51.21927616577889],"type":"Point"}
}