{
  "type": "Feature",
  "properties": {
    "iso:country": "GB",
    "wof:name": "LA18 4HT",
    "wof:placetype": "postalcode"
  },
  "geometry": {"coordinates":[-3.28623,54.196873],"type":"Point"}
}
