{
  "type": "Feature",
  "properties": {
    "date:inception_lower": "1980-01-01",
    "date:inception_upper": "1980-01-01",
    "iso:country": "GB",
    "wof:name": "LA18 4HT",
    "wof:placetype": "postalcode"
  },
  "geometry": {"coordinates":[-3.28623,54.196873],"type":"Point"}
}
