{
  "type": "Feature",
  "properties": {
    "iso:country":"GB",
    "wof:name":"LA18 4HT",
    "wof:placetype":"postalcode"
},
  "geometry": {"coordinates":[-3.28622983137698,54.19687333499343],"type":"Point"}
}