{
  "type": "Feature",
  "properties": {
    "iso:country":"GB",
    "wof:name":"BH11 8LZ",
    "wof:placetype":"postalcode"
},
  "geometry": {"coordinates":[-1.92288242573523,50.75713528567951],"type":"Point"}
}