{
  "type": "Feature",
  "properties": {
    "iso:country":"GB",
    "wof:name":"WS15 1SR",
    "wof:placetype":"postalcode"
},
  "geometry": {"coordinates":[-1.90936780169207,52.74821801232947],"type":"Point"}
}