{
  "type": "Feature",
  "properties": {
    "date:inception_lower": "2015-01-01",
    "date:inception_upper": "2015-01-01",
    "iso:country": "GB",
    "wof:name": "WS15 1SR",
    "wof:placetype": "postalcode"
  },
  "geometry": {"coordinates":[-1.909368,52.748218],"type":"Point"}
}
