{
  "type": "Feature",
  "properties": {
    "iso:country": "GB",
    "wof:name": "WS15 1SR",
    "wof:placetype": "postalcode"
  },
  "geometry": {"coordinates":[-1.909368,52.748218],"type":"Point"}
}
