{
  "type": "Feature",
  "properties": {
    "iso:country":"GB",
    "wof:name":"SN7 8FD",
    "wof:placetype":"postalcode"
},
  "geometry": {"coordinates":[-1.51236217834844,51.63737648533716],"type":"Point"}
}