{
  "type": "Feature",
  "properties": {
    "iso:country": "GB",
    "wof:name": "SN7 8FD",
    "wof:placetype": "postalcode"
  },
  "geometry": {"coordinates":[-1.512362,51.637376],"type":"Point"}
}
