{
  "type": "Feature",
  "properties": {
    "iso:country":"GB",
    "wof:name":"GL20 7PS",
    "wof:placetype":"postalcode"
},
  "geometry": {"coordinates":[-2.05246023768789,52.03344721087618],"type":"Point"}
}