{
  "type": "Feature",
  "properties": {
    "iso:country": "GB",
    "wof:name": "BS5 6XT",
    "wof:placetype": "postalcode"
  },
  "geometry": {"coordinates":[-2.562901,51.475299],"type":"Point"}
}
