{
  "type": "Feature",
  "properties": {
    "date:inception_lower":"1980-01-01",
    "date:inception_upper":"1980-01-31",
    "iso:country":"GB",
    "wof:name":"BS5 6XT",
    "wof:placetype":"postalcode"
},
  "geometry": {"coordinates":[-2.562901,51.475299],"type":"Point"}
}