{
  "type": "Feature",
  "properties": {
    "iso:country":"GB",
    "wof:name":"DY8 4QY",
    "wof:placetype":"postalcode"
},
  "geometry": {"coordinates":[-2.16786617377055,52.4635709274506],"type":"Point"}
}