{
  "type": "Feature",
  "properties": {
    "iso:country":"GB",
    "wof:name":"W1T 2RJ",
    "wof:placetype":"postalcode"
},
  "geometry": {"coordinates":[-0.13491806986713,51.52038084964054],"type":"Point"}
}