{
  "type": "Feature",
  "properties": {
    "iso:country": "GB",
    "wof:name": "NR24 2AX",
    "wof:placetype": "postalcode"
  },
  "geometry": {"coordinates":[1.111052,52.857916],"type":"Point"}
}
