{
  "type": "Feature",
  "properties": {
    "iso:country":"GB",
    "wof:name":"TS10 2AG",
    "wof:placetype":"postalcode"
},
  "geometry": {"coordinates":[-1.06648840304995,54.61540949332106],"type":"Point"}
}