{
  "type": "Feature",
  "properties": {
    "iso:country":"GB",
    "wof:name":"WF12 7LE",
    "wof:placetype":"postalcode"
},
  "geometry": {"coordinates":[-1.61284131180934,53.69407937410547],"type":"Point"}
}