{
  "type": "Feature",
  "properties": {
    "iso:country": "GB",
    "wof:name": "PL2 2DN",
    "wof:placetype": "postalcode"
  },
  "geometry": {"coordinates":[-4.175961,50.38938],"type":"Point"}
}
