{
  "type": "Feature",
  "properties": {
    "iso:country":"GB",
    "wof:name":"B97 4RA",
    "wof:placetype":"postalcode"
},
  "geometry": {"coordinates":[-1.94478005876482,52.30651263886869],"type":"Point"}
}