{
  "type": "Feature",
  "properties": {
    "date:inception_lower": "2021-02-01",
    "date:inception_upper": "2021-02-01",
    "iso:country": "GB",
    "wof:name": "TN23 1FA",
    "wof:placetype": "postalcode"
  },
  "geometry": {"coordinates":[0.870284,51.146989],"type":"Point"}
}
