{
  "type": "Feature",
  "properties": {
    "iso:country": "GB",
    "wof:name": "CH65 9JN",
    "wof:placetype": "postalcode"
  },
  "geometry": {"coordinates":[-2.891403,53.26371],"type":"Point"}
}
