{
  "type": "Feature",
  "properties": {
    "iso:country":"GB",
    "wof:name":"CH65 9JN",
    "wof:placetype":"postalcode"
},
  "geometry": {"coordinates":[-2.89140325497785,53.26370952298056],"type":"Point"}
}