{
  "type": "Feature",
  "properties": {
    "iso:country": "GB",
    "wof:name": "B44 0EP",
    "wof:placetype": "postalcode"
  },
  "geometry": {"coordinates":[-1.878168,52.540681],"type":"Point"}
}
