{
  "type": "Feature",
  "properties": {
    "iso:country":"GB",
    "wof:name":"B44 0EP",
    "wof:placetype":"postalcode"
},
  "geometry": {"coordinates":[-1.87816781696386,52.54068062293864],"type":"Point"}
}