{
  "type": "Feature",
  "properties": {
    "iso:country":"GB",
    "wof:name":"DE73 6PW",
    "wof:placetype":"postalcode"
},
  "geometry": {"coordinates":[-1.42991130848397,52.87207257557939],"type":"Point"}
}