{
  "type": "Feature",
  "properties": {
    "iso:country": "GB",
    "wof:name": "DE73 6PW",
    "wof:placetype": "postalcode"
  },
  "geometry": {"coordinates":[-1.429911,52.872073],"type":"Point"}
}
