{
  "type": "Feature",
  "properties": {
    "iso:country": "GB",
    "wof:name": "BS23 2JB",
    "wof:placetype": "postalcode"
  },
  "geometry": {"coordinates":[-2.986037,51.353801],"type":"Point"}
}
