{
  "type": "Feature",
  "properties": {
    "date:inception_lower": "2020-08-01",
    "date:inception_upper": "2020-08-01",
    "iso:country": "GB",
    "wof:name": "NG13 9LL",
    "wof:placetype": "postalcode"
  },
  "geometry": {"coordinates":[-0.859504,52.942242],"type":"Point"}
}
