{
  "type": "Feature",
  "properties": {
    "iso:country":"GB",
    "wof:name":"YO41 1EU",
    "wof:placetype":"postalcode"
},
  "geometry": {"coordinates":[-0.9186567530317,53.98823089463574],"type":"Point"}
}