{
  "type": "Feature",
  "properties": {
    "iso:country": "GB",
    "wof:name": "YO41 1EU",
    "wof:placetype": "postalcode"
  },
  "geometry": {"coordinates":[-0.918657,53.988231],"type":"Point"}
}
