{
  "type": "Feature",
  "properties": {
    "date:inception_lower": "1998-06-01",
    "date:inception_upper": "1998-06-01",
    "iso:country": "GB",
    "wof:name": "YO41 1EU",
    "wof:placetype": "postalcode"
  },
  "geometry": {"coordinates":[-0.918657,53.988231],"type":"Point"}
}
