{
  "type": "Feature",
  "properties": {
    "iso:country":"GB",
    "wof:name":"CA2 4HP",
    "wof:placetype":"postalcode"
},
  "geometry": {"coordinates":[-2.92528434909422,54.87896515815292],"type":"Point"}
}