{
  "type": "Feature",
  "properties": {
    "iso:country":"GB",
    "wof:name":"ST6 8RU",
    "wof:placetype":"postalcode"
},
  "geometry": {"coordinates":[-2.14125997122083,53.07309553639396],"type":"Point"}
}