{
  "type": "Feature",
  "properties": {
    "iso:country": "GB",
    "wof:name": "ST6 8RU",
    "wof:placetype": "postalcode"
  },
  "geometry": {"coordinates":[-2.14126,53.073096],"type":"Point"}
}
