{
  "type": "Feature",
  "properties": {
    "iso:country":"GB",
    "wof:name":"SS9 3EU",
    "wof:placetype":"postalcode"
},
  "geometry": {"coordinates":[0.65636662227138,51.55099300250205],"type":"Point"}
}