{
  "type": "Feature",
  "properties": {
    "iso:country":"GB",
    "wof:name":"AB31 5UB",
    "wof:placetype":"postalcode"
},
  "geometry": {"coordinates":[-2.50360531992141,57.05211613714294],"type":"Point"}
}