{
  "type": "Feature",
  "properties": {
    "iso:country":"GB",
    "wof:name":"WA14 4NH",
    "wof:placetype":"postalcode"
},
  "geometry": {"coordinates":[-2.36641242554458,53.39034419521823],"type":"Point"}
}