{
  "type": "Feature",
  "properties": {
    "iso:country": "GB",
    "wof:name": "SO31 5GT",
    "wof:placetype": "postalcode"
  },
  "geometry": {"coordinates":[-1.343023,50.879436],"type":"Point"}
}
