{
  "type": "Feature",
  "properties": {
    "iso:country":"GB",
    "wof:name":"SO31 5GT",
    "wof:placetype":"postalcode"
},
  "geometry": {"coordinates":[-1.34303292717257,50.87944613812567],"type":"Point"}
}