{
  "type": "Feature",
  "properties": {
    "iso:country":"GB",
    "wof:name":"DH1 2UF",
    "wof:placetype":"postalcode"
},
  "geometry": {"coordinates":[-1.51678408578216,54.78689396788397],"type":"Point"}
}