{
  "type": "Feature",
  "properties": {
    "date:inception_lower": "1980-01-01",
    "date:inception_upper": "1980-01-01",
    "iso:country": "GB",
    "wof:name": "DH1 2UF",
    "wof:placetype": "postalcode"
  },
  "geometry": {"coordinates":[-1.516784,54.786894],"type":"Point"}
}
