{
  "type": "Feature",
  "properties": {
    "date:inception_lower": "1980-01-01",
    "date:inception_upper": "1980-01-01",
    "iso:country": "GB",
    "wof:name": "GL16 7LJ",
    "wof:placetype": "postalcode"
  },
  "geometry": {"coordinates":[-2.603479,51.780161],"type":"Point"}
}
