{
  "type": "Feature",
  "properties": {
    "iso:country":"GB",
    "wof:name":"W1C 2AE",
    "wof:placetype":"postalcode"
},
  "geometry": {"coordinates":[-0.14783530310923,51.5142907869611],"type":"Point"}
}