{
  "type": "Feature",
  "properties": {
    "iso:country":"GB",
    "wof:name":"HU7 4EU",
    "wof:placetype":"postalcode"
},
  "geometry": {"coordinates":[-0.33900832226001,53.79448556617145],"type":"Point"}
}