{
  "type": "Feature",
  "properties": {
    "date:inception_lower": "1994-05-01",
    "date:inception_upper": "1994-05-01",
    "iso:country": "GB",
    "wof:name": "M20 5GH",
    "wof:placetype": "postalcode"
  },
  "geometry": {"coordinates":[-2.23282,53.402545],"type":"Point"}
}
