{
  "type": "Feature",
  "properties": {
    "iso:country":"GB",
    "wof:name":"M20 5GH",
    "wof:placetype":"postalcode"
},
  "geometry": {"coordinates":[-2.23282044736483,53.40254464419401],"type":"Point"}
}