{
  "type": "Feature",
  "properties": {
    "iso:country": "GB",
    "wof:name": "TD1 3NQ",
    "wof:placetype": "postalcode"
  },
  "geometry": {"coordinates":[-2.789237,55.604564],"type":"Point"}
}
