{
  "type": "Feature",
  "properties": {
    "iso:country":"GB",
    "wof:name":"TD1 3NQ",
    "wof:placetype":"postalcode"
},
  "geometry": {"coordinates":[-2.78923717912798,55.60456404673211],"type":"Point"}
}