{
  "type": "Feature",
  "properties": {
    "iso:country":"GB",
    "wof:name":"BN22 0BB",
    "wof:placetype":"postalcode"
},
  "geometry": {"coordinates":[0.26613388473822,50.80088907671448],"type":"Point"}
}