{
  "type": "Feature",
  "properties": {
    "date:inception_lower": "1985-04-01",
    "date:inception_upper": "1985-04-01",
    "iso:country": "GB",
    "wof:name": "WV10 7TT",
    "wof:placetype": "postalcode"
  },
  "geometry": {"coordinates":[-2.095142,52.647674],"type":"Point"}
}
