{
  "type": "Feature",
  "properties": {
    "iso:country":"GB",
    "wof:name":"WV10 7TT",
    "wof:placetype":"postalcode"
},
  "geometry": {"coordinates":[-2.09514252652454,52.64767406692769],"type":"Point"}
}