{
  "type": "Feature",
  "properties": {
    "date:inception_lower": "2022-06-01",
    "date:inception_upper": "2022-06-01",
    "iso:country": "GB",
    "wof:name": "CT14 0FJ",
    "wof:placetype": "postalcode"
  },
  "geometry": {"coordinates":[1.301307,51.227005],"type":"Point"}
}
