{
  "type": "Feature",
  "properties": {
    "date:inception_lower": "2002-05-01",
    "date:inception_upper": "2002-05-01",
    "iso:country": "GB",
    "wof:name": "MK4 3EZ",
    "wof:placetype": "postalcode"
  },
  "geometry": {"coordinates":[-0.788348,51.995349],"type":"Point"}
}
