{
  "type": "Feature",
  "properties": {
    "iso:country":"GB",
    "wof:name":"MK4 3EZ",
    "wof:placetype":"postalcode"
},
  "geometry": {"coordinates":[-0.78834765404613,51.99534891708783],"type":"Point"}
}