{
  "type": "Feature",
  "properties": {
    "iso:country": "GB",
    "wof:name": "S9 3RD",
    "wof:placetype": "postalcode"
  },
  "geometry": {"coordinates":[-1.432957,53.393409],"type":"Point"}
}
