{
  "type": "Feature",
  "properties": {
    "date:inception_lower":"1980-01-01",
    "date:inception_upper":"1980-01-31",
    "iso:country":"GB",
    "wof:name":"S9 3RD",
    "wof:placetype":"postalcode"
},
  "geometry": {"coordinates":[-1.432957,53.393409],"type":"Point"}
}