{
  "type": "Feature",
  "properties": {
    "iso:country":"GB",
    "wof:name":"AL5 4QJ",
    "wof:placetype":"postalcode"
},
  "geometry": {"coordinates":[-0.34839872903974,51.82235094408188],"type":"Point"}
}