{
  "type": "Feature",
  "properties": {
    "iso:country":"GB",
    "wof:name":"SO45 1YY",
    "wof:placetype":"postalcode"
},
  "geometry": {"coordinates":[-1.37405057391324,50.81343110479131],"type":"Point"}
}