{
  "type": "Feature",
  "properties": {
    "iso:country":"GB",
    "wof:name":"M28 2QT",
    "wof:placetype":"postalcode"
},
  "geometry": {"coordinates":[-2.39107503179056,53.50532827768498],"type":"Point"}
}