{
  "type": "Feature",
  "properties": {
    "iso:country":"GB",
    "wof:name":"OL15 8JB",
    "wof:placetype":"postalcode"
},
  "geometry": {"coordinates":[-2.10003465135872,53.64232412842885],"type":"Point"}
}