{
  "type": "Feature",
  "properties": {
    "iso:country":"GB",
    "wof:name":"WD6 5BB",
    "wof:placetype":"postalcode"
},
  "geometry": {"coordinates":[-0.27611662381039,51.67183908835202],"type":"Point"}
}