{
  "type": "Feature",
  "properties": {
    "iso:country":"GB",
    "wof:name":"WV10 6EX",
    "wof:placetype":"postalcode"
},
  "geometry": {"coordinates":[-2.13050927575336,52.62696395248861],"type":"Point"}
}