{
  "type": "Feature",
  "properties": {
    "iso:country":"GB",
    "wof:name":"BR1 5RN",
    "wof:placetype":"postalcode"
},
  "geometry": {"coordinates":[-0.00578171233731,51.42754673245127],"type":"Point"}
}