{
  "type": "Feature",
  "properties": {
    "iso:country":"GB",
    "wof:name":"CR7 7DA",
    "wof:placetype":"postalcode"
},
  "geometry": {"coordinates":[-0.1054872710741,51.39828397379353],"type":"Point"}
}