{
  "type": "Feature",
  "properties": {
    "date:inception_lower":"1990-07-01",
    "date:inception_upper":"1990-07-31",
    "iso:country":"GB",
    "wof:name":"CR7 7DA",
    "wof:placetype":"postalcode"
},
  "geometry": {"coordinates":[-0.105487,51.398284],"type":"Point"}
}