{
  "type": "Feature",
  "properties": {
    "date:inception_lower":"1980-01-01",
    "date:inception_upper":"1980-01-31",
    "iso:country":"GB",
    "wof:name":"RG22 5LX",
    "wof:placetype":"postalcode"
},
  "geometry": {"coordinates":[-1.141272,51.239252],"type":"Point"}
}