{
  "type": "Feature",
  "properties": {
    "iso:country":"GB",
    "wof:name":"B42 2BJ",
    "wof:placetype":"postalcode"
},
  "geometry": {"coordinates":[-1.92593705115289,52.54223932639891],"type":"Point"}
}