{
  "type": "Feature",
  "properties": {
    "iso:country": "GB",
    "wof:name": "CF35 6EF",
    "wof:placetype": "postalcode"
  },
  "geometry": {"coordinates":[-3.526208,51.573254],"type":"Point"}
}
