{
  "type": "Feature",
  "properties": {
    "iso:country": "GB",
    "wof:name": "CT2 7HL",
    "wof:placetype": "postalcode"
  },
  "geometry": {"coordinates":[1.073435,51.286562],"type":"Point"}
}
