{
  "type": "Feature",
  "properties": {
    "iso:country":"GB",
    "wof:name":"OL7 9NJ",
    "wof:placetype":"postalcode"
},
  "geometry": {"coordinates":[-2.10659242716117,53.50184928843081],"type":"Point"}
}