{
  "type": "Feature",
  "properties": {
    "date:inception_lower":"1980-01-01",
    "date:inception_upper":"1980-01-31",
    "iso:country":"GB",
    "wof:name":"OL7 9NJ",
    "wof:placetype":"postalcode"
},
  "geometry": {"coordinates":[-2.106592,53.501849],"type":"Point"}
}