{
  "type": "Feature",
  "properties": {
    "iso:country": "GB",
    "wof:name": "OL7 9NJ",
    "wof:placetype": "postalcode"
  },
  "geometry": {"coordinates":[-2.106592,53.501849],"type":"Point"}
}
