{
  "type": "Feature",
  "properties": {
    "date:inception_lower": "1980-01-01",
    "date:inception_upper": "1980-01-01",
    "iso:country": "GB",
    "wof:name": "WN6 9QF",
    "wof:placetype": "postalcode"
  },
  "geometry": {"coordinates":[-2.756964,53.599739],"type":"Point"}
}
