{
  "type": "Feature",
  "properties": {
    "iso:country":"GB",
    "wof:name":"WN6 9QF",
    "wof:placetype":"postalcode"
},
  "geometry": {"coordinates":[-2.7569644129443,53.5997391450442],"type":"Point"}
}