{
  "type": "Feature",
  "properties": {
    "iso:country":"GB",
    "wof:name":"PH22 1RP",
    "wof:placetype":"postalcode"
},
  "geometry": {"coordinates":[-3.82951365937021,57.19589550763742],"type":"Point"}
}