{
  "type": "Feature",
  "properties": {
    "date:inception_lower": "1980-01-01",
    "date:inception_upper": "1980-01-01",
    "iso:country": "GB",
    "wof:name": "PH22 1RP",
    "wof:placetype": "postalcode"
  },
  "geometry": {"coordinates":[-3.829514,57.195896],"type":"Point"}
}
