{
  "type": "Feature",
  "properties": {
    "iso:country":"GB",
    "wof:name":"M32 8GS",
    "wof:placetype":"postalcode"
},
  "geometry": {"coordinates":[-2.28703751465077,53.45319382914347],"type":"Point"}
}