{
  "type": "Feature",
  "properties": {
    "iso:country":"GB",
    "wof:name":"PO39 0LD",
    "wof:placetype":"postalcode"
},
  "geometry": {"coordinates":[-1.5352461233913,50.68227945884952],"type":"Point"}
}