{
  "type": "Feature",
  "properties": {
    "date:inception_lower": "1992-08-01",
    "date:inception_upper": "1992-08-01",
    "iso:country": "GB",
    "wof:name": "PO39 0LD",
    "wof:placetype": "postalcode"
  },
  "geometry": {"coordinates":[-1.534697,50.682474],"type":"Point"}
}
