{
  "type": "Feature",
  "properties": {
    "iso:country": "GB",
    "wof:name": "NP11 6GW",
    "wof:placetype": "postalcode"
  },
  "geometry": {"coordinates":[-3.104605,51.615009],"type":"Point"}
}
