{
  "type": "Feature",
  "properties": {
    "date:inception_lower": "1980-01-01",
    "date:inception_upper": "1980-01-01",
    "iso:country": "GB",
    "wof:name": "SA44 5SL",
    "wof:placetype": "postalcode"
  },
  "geometry": {"coordinates":[-4.417535,52.100008],"type":"Point"}
}
