{
  "type": "Feature",
  "properties": {
    "iso:country":"GB",
    "wof:name":"KY4 9NY",
    "wof:placetype":"postalcode"
},
  "geometry": {"coordinates":[-3.35987687816459,56.10019040318655],"type":"Point"}
}