{
  "type": "Feature",
  "properties": {
    "date:inception_lower": "1980-01-01",
    "date:inception_upper": "1980-01-01",
    "iso:country": "GB",
    "wof:name": "KY4 9NY",
    "wof:placetype": "postalcode"
  },
  "geometry": {"coordinates":[-3.359877,56.10019],"type":"Point"}
}
