{
  "type": "Feature",
  "properties": {
    "iso:country": "GB",
    "wof:name": "KY4 9NY",
    "wof:placetype": "postalcode"
  },
  "geometry": {"coordinates":[-3.359877,56.10019],"type":"Point"}
}
