{
  "type": "Feature",
  "properties": {
    "iso:country":"GB",
    "wof:name":"KA21 5BY",
    "wof:placetype":"postalcode"
},
  "geometry": {"coordinates":[-4.79299480151137,55.6347254681037],"type":"Point"}
}