{
  "type": "Feature",
  "properties": {
    "date:inception_lower": "1980-01-01",
    "date:inception_upper": "1980-01-01",
    "iso:country": "GB",
    "wof:name": "DY5 3EQ",
    "wof:placetype": "postalcode"
  },
  "geometry": {"coordinates":[-2.124933,52.481574],"type":"Point"}
}
