{
  "type": "Feature",
  "properties": {
    "iso:country": "GB",
    "wof:name": "AL5 2AY",
    "wof:placetype": "postalcode"
  },
  "geometry": {"coordinates":[-0.371386,51.796901],"type":"Point"}
}
