{
  "type": "Feature",
  "properties": {
    "iso:country":"GB",
    "wof:name":"AL5 2AY",
    "wof:placetype":"postalcode"
},
  "geometry": {"coordinates":[-0.37138623811177,51.79690091850591],"type":"Point"}
}