{
  "type": "Feature",
  "properties": {
    "iso:country":"GB",
    "wof:name":"CF39 8TH",
    "wof:placetype":"postalcode"
},
  "geometry": {"coordinates":[-3.47524923362178,51.58600931398035],"type":"Point"}
}