{
  "type": "Feature",
  "properties": {
    "iso:country": "GB",
    "wof:name": "CF39 8TH",
    "wof:placetype": "postalcode"
  },
  "geometry": {"coordinates":[-3.475249,51.586009],"type":"Point"}
}
