{
  "type": "Feature",
  "properties": {
    "date:inception_lower": "1980-01-01",
    "date:inception_upper": "1980-01-01",
    "iso:country": "GB",
    "wof:name": "CF39 8TH",
    "wof:placetype": "postalcode"
  },
  "geometry": {"coordinates":[-3.475249,51.586009],"type":"Point"}
}
