{
  "type": "Feature",
  "properties": {
    "iso:country": "GB",
    "wof:name": "DT6 4DZ",
    "wof:placetype": "postalcode"
  },
  "geometry": {"coordinates":[-2.748735,50.727067],"type":"Point"}
}
