{
  "type": "Feature",
  "properties": {
    "iso:country":"GB",
    "wof:name":"DT6 4DZ",
    "wof:placetype":"postalcode"
},
  "geometry": {"coordinates":[-2.7487350743298,50.72706669232417],"type":"Point"}
}