{
  "type": "Feature",
  "properties": {
    "iso:country":"GB",
    "wof:name":"NR27 9JG",
    "wof:placetype":"postalcode"
},
  "geometry": {"coordinates":[1.29334427103194,52.92654298470848],"type":"Point"}
}