{
  "type": "Feature",
  "properties": {
    "date:inception_lower":"1980-01-01",
    "date:inception_upper":"1980-01-31",
    "iso:country":"GB",
    "wof:name":"NR27 9JG",
    "wof:placetype":"postalcode"
},
  "geometry": {"coordinates":[1.293344,52.926543],"type":"Point"}
}