{
  "type": "Feature",
  "properties": {
    "iso:country":"GB",
    "wof:name":"S2 1UB",
    "wof:placetype":"postalcode"
},
  "geometry": {"coordinates":[-1.43957917070485,53.37236189074856],"type":"Point"}
}