{
  "type": "Feature",
  "properties": {
    "date:inception_lower": "1980-01-01",
    "date:inception_upper": "1980-01-01",
    "iso:country": "GB",
    "wof:name": "CH4 7EU",
    "wof:placetype": "postalcode"
  },
  "geometry": {"coordinates":[-2.884171,53.177621],"type":"Point"}
}
