{
  "type": "Feature",
  "properties": {
    "iso:country":"GB",
    "wof:name":"CH4 7EU",
    "wof:placetype":"postalcode"
},
  "geometry": {"coordinates":[-2.88417068552478,53.17762054728552],"type":"Point"}
}