{
  "type": "Feature",
  "properties": {
    "iso:country":"GB",
    "wof:name":"CR9 1LT",
    "wof:placetype":"postalcode"
},
  "geometry": {"coordinates":[-0.09880964502907,51.36620664664366],"type":"Point"}
}