{
  "type": "Feature",
  "properties": {
    "iso:country":"GB",
    "wof:name":"LL17 0LQ",
    "wof:placetype":"postalcode"
},
  "geometry": {"coordinates":[-3.46934713312019,53.25368018410587],"type":"Point"}
}