{
  "type": "Feature",
  "properties": {
    "date:inception_lower": "1996-06-01",
    "date:inception_upper": "1996-06-01",
    "iso:country": "GB",
    "wof:name": "LL17 0LQ",
    "wof:placetype": "postalcode"
  },
  "geometry": {"coordinates":[-3.469347,53.25368],"type":"Point"}
}
