{
  "type": "Feature",
  "properties": {
    "iso:country": "GB",
    "wof:name": "NN15 5UP",
    "wof:placetype": "postalcode"
  },
  "geometry": {"coordinates":[-0.698526,52.398004],"type":"Point"}
}
