{
  "type": "Feature",
  "properties": {
    "date:inception_lower":"1980-01-01",
    "date:inception_upper":"1980-01-31",
    "iso:country":"GB",
    "wof:name":"B17 0LY",
    "wof:placetype":"postalcode"
},
  "geometry": {"coordinates":[-1.948024,52.454995],"type":"Point"}
}