{
  "type": "Feature",
  "properties": {
    "iso:country":"GB",
    "wof:name":"BH22 8NE",
    "wof:placetype":"postalcode"
},
  "geometry": {"coordinates":[-1.87899456745828,50.79421951611406],"type":"Point"}
}