{
  "type": "Feature",
  "properties": {
    "iso:country":"GB",
    "wof:name":"NW1 9EJ",
    "wof:placetype":"postalcode"
},
  "geometry": {"coordinates":[-0.13626385267318,51.54319819245757],"type":"Point"}
}