{
  "type": "Feature",
  "properties": {
    "date:inception_lower":"1980-01-01",
    "date:inception_upper":"1980-01-31",
    "iso:country":"GB",
    "wof:name":"NW1 9EJ",
    "wof:placetype":"postalcode"
},
  "geometry": {"coordinates":[-0.136264,51.543198],"type":"Point"}
}