{
  "type": "Feature",
  "properties": {
    "date:inception_lower": "1988-03-01",
    "date:inception_upper": "1988-03-01",
    "iso:country": "GB",
    "wof:name": "PO9 3DA",
    "wof:placetype": "postalcode"
  },
  "geometry": {"coordinates":[-0.994399,50.860319],"type":"Point"}
}
