{
  "type": "Feature",
  "properties": {
    "iso:country":"GB",
    "wof:name":"UB6 8TE",
    "wof:placetype":"postalcode"
},
  "geometry": {"coordinates":[-0.32313530555375,51.53300609547986],"type":"Point"}
}