{
  "type": "Feature",
  "properties": {
    "iso:country":"GB",
    "wof:name":"YO25 9EP",
    "wof:placetype":"postalcode"
},
  "geometry": {"coordinates":[-0.6339429974952,53.96882049410704],"type":"Point"}
}