{
  "type": "Feature",
  "properties": {
    "date:inception_lower":"1980-01-01",
    "date:inception_upper":"1980-01-31",
    "iso:country":"GB",
    "wof:name":"NE23 6LW",
    "wof:placetype":"postalcode"
},
  "geometry": {"coordinates":[-1.579425,55.07079],"type":"Point"}
}