{
  "type": "Feature",
  "properties": {
    "iso:country":"GB",
    "wof:name":"NE23 6LW",
    "wof:placetype":"postalcode"
},
  "geometry": {"coordinates":[-1.57942477926777,55.07078997744408],"type":"Point"}
}