{
  "type": "Feature",
  "properties": {
    "iso:country": "GB",
    "wof:name": "NE23 6LW",
    "wof:placetype": "postalcode"
  },
  "geometry": {"coordinates":[-1.579425,55.07079],"type":"Point"}
}
