{
  "type": "Feature",
  "properties": {
    "iso:country": "GB",
    "wof:name": "DT11 8UX",
    "wof:placetype": "postalcode"
  },
  "geometry": {"coordinates":[-2.134031,50.885209],"type":"Point"}
}
