{
  "type": "Feature",
  "properties": {
    "iso:country":"GB",
    "wof:name":"DT11 8UX",
    "wof:placetype":"postalcode"
},
  "geometry": {"coordinates":[-2.13403127895395,50.88520870029081],"type":"Point"}
}