{
  "type": "Feature",
  "properties": {
    "iso:country":"GB",
    "wof:name":"DL8 3HG",
    "wof:placetype":"postalcode"
},
  "geometry": {"coordinates":[-2.07942156406923,54.31531054482885],"type":"Point"}
}