{
  "type": "Feature",
  "properties": {
    "iso:country": "GB",
    "wof:name": "DL8 3HG",
    "wof:placetype": "postalcode"
  },
  "geometry": {"coordinates":[-2.079422,54.315311],"type":"Point"}
}
