{
  "type": "Feature",
  "properties": {
    "date:inception_lower": "1980-01-01",
    "date:inception_upper": "1980-01-01",
    "iso:country": "GB",
    "wof:name": "HA5 5NH",
    "wof:placetype": "postalcode"
  },
  "geometry": {"coordinates":[-0.37395,51.590869],"type":"Point"}
}
