{
  "type": "Feature",
  "properties": {
    "iso:country":"GB",
    "wof:name":"DG9 9HP",
    "wof:placetype":"postalcode"
},
  "geometry": {"coordinates":[-4.88914475719211,54.64806632876101],"type":"Point"}
}