{
  "type": "Feature",
  "properties": {
    "iso:country":"GB",
    "wof:name":"M27 0AG",
    "wof:placetype":"postalcode"
},
  "geometry": {"coordinates":[-2.35028935413791,53.50324367310576],"type":"Point"}
}