{
  "type": "Feature",
  "properties": {
    "iso:country":"GB",
    "wof:name":"TW1 2DG",
    "wof:placetype":"postalcode"
},
  "geometry": {"coordinates":[-0.31555301471602,51.45714599019698],"type":"Point"}
}