{
  "type": "Feature",
  "properties": {
    "iso:country": "GB",
    "wof:name": "TW1 2DG",
    "wof:placetype": "postalcode"
  },
  "geometry": {"coordinates":[-0.315553,51.457146],"type":"Point"}
}
