{
  "type": "Feature",
  "properties": {
    "date:inception_lower":"1980-01-01",
    "date:inception_upper":"1980-01-31",
    "iso:country":"GB",
    "wof:name":"TS8 0RP",
    "wof:placetype":"postalcode"
},
  "geometry": {"coordinates":[-1.231256,54.529519],"type":"Point"}
}