{
  "type": "Feature",
  "properties": {
    "iso:country": "GB",
    "wof:name": "TS8 0RP",
    "wof:placetype": "postalcode"
  },
  "geometry": {"coordinates":[-1.231256,54.529519],"type":"Point"}
}
