{
  "type": "Feature",
  "properties": {
    "iso:country":"GB",
    "wof:name":"TS8 0RP",
    "wof:placetype":"postalcode"
},
  "geometry": {"coordinates":[-1.23125620785549,54.52951872751982],"type":"Point"}
}