{
  "type": "Feature",
  "properties": {
    "iso:country":"GB",
    "wof:name":"YO43 4NE",
    "wof:placetype":"postalcode"
},
  "geometry": {"coordinates":[-0.6332767931895,53.86190299960946],"type":"Point"}
}