{
  "type": "Feature",
  "properties": {
    "date:inception_lower":"1998-06-01",
    "date:inception_upper":"1998-06-30",
    "iso:country":"GB",
    "wof:name":"SL6 4BD",
    "wof:placetype":"postalcode"
},
  "geometry": {"coordinates":[-0.742402,51.512011],"type":"Point"}
}