{
  "type": "Feature",
  "properties": {
    "iso:country":"GB",
    "wof:name":"NP44 3QX",
    "wof:placetype":"postalcode"
},
  "geometry": {"coordinates":[-3.02123535488805,51.65021053085798],"type":"Point"}
}