{
  "type": "Feature",
  "properties": {
    "iso:country":"GB",
    "wof:name":"TA24 5BE",
    "wof:placetype":"postalcode"
},
  "geometry": {"coordinates":[-3.47114609214404,51.20736006139694],"type":"Point"}
}