{
  "type": "Feature",
  "properties": {
    "iso:country":"GB",
    "wof:name":"G74 2LD",
    "wof:placetype":"postalcode"
},
  "geometry": {"coordinates":[-4.14714642025102,55.75581769559054],"type":"Point"}
}