{
  "type": "Feature",
  "properties": {
    "iso:country":"GB",
    "wof:name":"TD5 8QG",
    "wof:placetype":"postalcode"
},
  "geometry": {"coordinates":[-2.36396600297021,55.51768077954611],"type":"Point"}
}