{
  "type": "Feature",
  "properties": {
    "iso:country": "GB",
    "wof:name": "TD5 8QG",
    "wof:placetype": "postalcode"
  },
  "geometry": {"coordinates":[-2.363877,55.517654],"type":"Point"}
}
