{
  "type": "Feature",
  "properties": {
    "date:inception_lower": "1980-01-01",
    "date:inception_upper": "1980-01-01",
    "iso:country": "GB",
    "wof:name": "SY24 5DY",
    "wof:placetype": "postalcode"
  },
  "geometry": {"coordinates":[-3.983762,52.484569],"type":"Point"}
}
