{
  "type": "Feature",
  "properties": {
    "iso:country":"GB",
    "wof:name":"SY24 5DY",
    "wof:placetype":"postalcode"
},
  "geometry": {"coordinates":[-3.98376191833065,52.48456932848764],"type":"Point"}
}