{
  "type": "Feature",
  "properties": {
    "iso:country": "GB",
    "wof:name": "G33 3JJ",
    "wof:placetype": "postalcode"
  },
  "geometry": {"coordinates":[-4.165511,55.867369],"type":"Point"}
}
