{
  "type": "Feature",
  "properties": {
    "iso:country":"GB",
    "wof:name":"CM1 4LT",
    "wof:placetype":"postalcode"
},
  "geometry": {"coordinates":[0.39588552843476,51.7507897182366],"type":"Point"}
}