{
  "type": "Feature",
  "properties": {
    "iso:country": "GB",
    "wof:name": "KA5 5JL",
    "wof:placetype": "postalcode"
  },
  "geometry": {"coordinates":[-4.371755,55.507922],"type":"Point"}
}
