{
  "type": "Feature",
  "properties": {
    "iso:country":"GB",
    "wof:name":"KA5 5JL",
    "wof:placetype":"postalcode"
},
  "geometry": {"coordinates":[-4.36974045660693,55.50364676128149],"type":"Point"}
}