{
  "type": "Feature",
  "properties": {
    "iso:country":"GB",
    "wof:name":"WD4 9AP",
    "wof:placetype":"postalcode"
},
  "geometry": {"coordinates":[-0.47587370529686,51.68967147261072],"type":"Point"}
}