{
  "type": "Feature",
  "properties": {
    "iso:country":"GB",
    "wof:name":"S40 4AH",
    "wof:placetype":"postalcode"
},
  "geometry": {"coordinates":[-1.44735402818584,53.23948046085462],"type":"Point"}
}