{
  "type": "Feature",
  "properties": {
    "date:inception_lower": "2009-03-01",
    "date:inception_upper": "2009-03-01",
    "iso:country": "GB",
    "wof:name": "G21 4PA",
    "wof:placetype": "postalcode"
  },
  "geometry": {"coordinates":[-4.212822,55.8792],"type":"Point"}
}
