{
  "type": "Feature",
  "properties": {
    "iso:country":"GB",
    "wof:name":"NE46 3AR",
    "wof:placetype":"postalcode"
},
  "geometry": {"coordinates":[-2.12310296641936,54.97393534049525],"type":"Point"}
}