{
  "type": "Feature",
  "properties": {
    "date:inception_lower": "2020-07-01",
    "date:inception_upper": "2020-07-01",
    "iso:country": "GB",
    "wof:name": "M32 0NW",
    "wof:placetype": "postalcode"
  },
  "geometry": {"coordinates":[-2.297812,53.452106],"type":"Point"}
}
