{
  "type": "Feature",
  "properties": {
    "iso:country":"GB",
    "wof:name":"EN8 0AY",
    "wof:placetype":"postalcode"
},
  "geometry": {"coordinates":[-0.03187019478372,51.71301581414446],"type":"Point"}
}