{
  "type": "Feature",
  "properties": {
    "iso:country":"GB",
    "wof:name":"PA2 6TP",
    "wof:placetype":"postalcode"
},
  "geometry": {"coordinates":[-4.41627095042463,55.83589786037686],"type":"Point"}
}