{
  "type": "Feature",
  "properties": {
    "iso:country":"GB",
    "wof:name":"FY8 1PU",
    "wof:placetype":"postalcode"
},
  "geometry": {"coordinates":[-3.02399295304695,53.75010767384581],"type":"Point"}
}