{
  "type": "Feature",
  "properties": {
    "date:inception_lower": "1980-01-01",
    "date:inception_upper": "1980-01-01",
    "iso:country": "GB",
    "wof:name": "FY8 1PU",
    "wof:placetype": "postalcode"
  },
  "geometry": {"coordinates":[-3.02399,53.750123],"type":"Point"}
}
