{
  "type": "Feature",
  "properties": {
    "iso:country":"GB",
    "wof:name":"CT14 7RG",
    "wof:placetype":"postalcode"
},
  "geometry": {"coordinates":[1.38396491103222,51.2033520027855],"type":"Point"}
}