{
  "type": "Feature",
  "properties": {
    "iso:country": "GB",
    "wof:name": "KT10 0TX",
    "wof:placetype": "postalcode"
  },
  "geometry": {"coordinates":[-0.324546,51.358106],"type":"Point"}
}
