{
  "type": "Feature",
  "properties": {
    "iso:country": "GB",
    "wof:name": "KY8 6HL",
    "wof:placetype": "postalcode"
  },
  "geometry": {"coordinates":[-2.949396,56.213528],"type":"Point"}
}
