{
  "type": "Feature",
  "properties": {
    "iso:country":"GB",
    "wof:name":"KY8 6HL",
    "wof:placetype":"postalcode"
},
  "geometry": {"coordinates":[-2.94927107120478,56.21370894769792],"type":"Point"}
}