{
  "type": "Feature",
  "properties": {
    "date:inception_lower": "1980-01-01",
    "date:inception_upper": "1980-01-01",
    "iso:country": "GB",
    "wof:name": "KY8 6HL",
    "wof:placetype": "postalcode"
  },
  "geometry": {"coordinates":[-2.949396,56.213528],"type":"Point"}
}
