{
  "type": "Feature",
  "properties": {
    "iso:country": "GB",
    "wof:name": "L1 9BQ",
    "wof:placetype": "postalcode"
  },
  "geometry": {"coordinates":[-2.96976,53.402319],"type":"Point"}
}
