{
  "type": "Feature",
  "properties": {
    "iso:country":"GB",
    "wof:name":"TS21 2ES",
    "wof:placetype":"postalcode"
},
  "geometry": {"coordinates":[-1.50269224901263,54.64885547499157],"type":"Point"}
}