{
  "type": "Feature",
  "properties": {
    "iso:country": "GB",
    "wof:name": "TS21 2ES",
    "wof:placetype": "postalcode"
  },
  "geometry": {"coordinates":[-1.502692,54.648855],"type":"Point"}
}
