{
  "type": "Feature",
  "properties": {
    "iso:country": "GB",
    "wof:name": "BL1 3JH",
    "wof:placetype": "postalcode"
  },
  "geometry": {"coordinates":[-2.443856,53.592853],"type":"Point"}
}
