{
  "type": "Feature",
  "properties": {
    "iso:country": "GB",
    "wof:name": "SN13 0QP",
    "wof:placetype": "postalcode"
  },
  "geometry": {"coordinates":[-2.206916,51.431393],"type":"Point"}
}
