{
  "type": "Feature",
  "properties": {
    "iso:country":"GB",
    "wof:name":"SN13 0QP",
    "wof:placetype":"postalcode"
},
  "geometry": {"coordinates":[-2.20691637734706,51.4313933544397],"type":"Point"}
}