{
  "type": "Feature",
  "properties": {
    "iso:country":"GB",
    "wof:name":"PA28 6LW",
    "wof:placetype":"postalcode"
},
  "geometry": {"coordinates":[-5.61290349227074,55.41954919948862],"type":"Point"}
}