{
  "type": "Feature",
  "properties": {
    "date:inception_lower": "1980-01-01",
    "date:inception_upper": "1980-01-01",
    "iso:country": "GB",
    "wof:name": "NE8 4EU",
    "wof:placetype": "postalcode"
  },
  "geometry": {"coordinates":[-1.600192,54.952565],"type":"Point"}
}
