{
  "type": "Feature",
  "properties": {
    "iso:country":"GB",
    "wof:name":"IV25 3RG",
    "wof:placetype":"postalcode"
},
  "geometry": {"coordinates":[-4.11380758727435,57.87807514146854],"type":"Point"}
}