{
  "type": "Feature",
  "properties": {
    "date:inception_lower": "1980-01-01",
    "date:inception_upper": "1980-01-01",
    "iso:country": "GB",
    "wof:name": "IV25 3RG",
    "wof:placetype": "postalcode"
  },
  "geometry": {"coordinates":[-4.113808,57.878075],"type":"Point"}
}
