{
  "type": "Feature",
  "properties": {
    "date:inception_lower": "1980-01-01",
    "date:inception_upper": "1980-01-01",
    "iso:country": "GB",
    "wof:name": "GL17 9BE",
    "wof:placetype": "postalcode"
  },
  "geometry": {"coordinates":[-2.532586,51.855646],"type":"Point"}
}
