{
  "type": "Feature",
  "properties": {
    "iso:country":"GB",
    "wof:name":"GL17 9BE",
    "wof:placetype":"postalcode"
},
  "geometry": {"coordinates":[-2.53258620352784,51.85564648150413],"type":"Point"}
}