{
  "type": "Feature",
  "properties": {
    "iso:country":"GB",
    "wof:name":"BH19 2JF",
    "wof:placetype":"postalcode"
},
  "geometry": {"coordinates":[-1.95829155556327,50.60179475838569],"type":"Point"}
}