{
  "type": "Feature",
  "properties": {
    "iso:country": "GB",
    "wof:name": "MK18 4RF",
    "wof:placetype": "postalcode"
  },
  "geometry": {"coordinates":[-1.050268,51.988725],"type":"Point"}
}
