{
  "type": "Feature",
  "properties": {
    "date:inception_lower":"2012-02-01",
    "date:inception_upper":"2012-02-29",
    "iso:country":"GB",
    "wof:name":"MK18 4RF",
    "wof:placetype":"postalcode"
},
  "geometry": {"coordinates":[-1.050268,51.988725],"type":"Point"}
}