{
  "type": "Feature",
  "properties": {
    "iso:country":"GB",
    "wof:name":"MK18 4RF",
    "wof:placetype":"postalcode"
},
  "geometry": {"coordinates":[-1.05026839846762,51.98872458577416],"type":"Point"}
}