{
  "type": "Feature",
  "properties": {
    "iso:country":"GB",
    "wof:name":"SL1 2NY",
    "wof:placetype":"postalcode"
},
  "geometry": {"coordinates":[-0.61113193273533,51.50923521075578],"type":"Point"}
}