{
  "type": "Feature",
  "properties": {
    "iso:country": "GB",
    "wof:name": "SL1 2NY",
    "wof:placetype": "postalcode"
  },
  "geometry": {"coordinates":[-0.611132,51.509235],"type":"Point"}
}
