{
  "type": "Feature",
  "properties": {
    "iso:country":"GB",
    "wof:name":"WF13 2AS",
    "wof:placetype":"postalcode"
},
  "geometry": {"coordinates":[-1.636233656461,53.69651652658693],"type":"Point"}
}