{
  "type": "Feature",
  "properties": {
    "iso:country": "GB",
    "wof:name": "WF13 2AS",
    "wof:placetype": "postalcode"
  },
  "geometry": {"coordinates":[-1.636234,53.696517],"type":"Point"}
}
