{
  "type": "Feature",
  "properties": {
    "date:inception_lower": "1980-01-01",
    "date:inception_upper": "1980-01-01",
    "iso:country": "GB",
    "wof:name": "WF13 2AS",
    "wof:placetype": "postalcode"
  },
  "geometry": {"coordinates":[-1.636234,53.696517],"type":"Point"}
}
