{
  "type": "Feature",
  "properties": {
    "iso:country":"GB",
    "wof:name":"PH1 2JZ",
    "wof:placetype":"postalcode"
},
  "geometry": {"coordinates":[-3.47186893686369,56.40673825579689],"type":"Point"}
}