{
  "type": "Feature",
  "properties": {
    "iso:country": "GB",
    "wof:name": "PH1 2JZ",
    "wof:placetype": "postalcode"
  },
  "geometry": {"coordinates":[-3.471869,56.406738],"type":"Point"}
}
