{
  "type": "Feature",
  "properties": {
    "iso:country":"GB",
    "wof:name":"IP13 7BA",
    "wof:placetype":"postalcode"
},
  "geometry": {"coordinates":[1.26510703535088,52.20071798410966],"type":"Point"}
}