{
  "type": "Feature",
  "properties": {
    "iso:country":"GB",
    "wof:name":"OL9 0LS",
    "wof:placetype":"postalcode"
},
  "geometry": {"coordinates":[-2.15363562749897,53.54532870318025],"type":"Point"}
}