{
  "type": "Feature",
  "properties": {
    "iso:country":"GB",
    "wof:name":"SS6 9AB",
    "wof:placetype":"postalcode"
},
  "geometry": {"coordinates":[0.597915475931,51.59024571663895],"type":"Point"}
}