{
  "type": "Feature",
  "properties": {
    "date:inception_lower":"1980-01-01",
    "date:inception_upper":"1980-01-31",
    "iso:country":"GB",
    "wof:name":"SS6 9AB",
    "wof:placetype":"postalcode"
},
  "geometry": {"coordinates":[0.597943,51.59026],"type":"Point"}
}