{
  "type": "Feature",
  "properties": {
    "iso:country":"GB",
    "wof:name":"B95 5EA",
    "wof:placetype":"postalcode"
},
  "geometry": {"coordinates":[-1.75959004420983,52.30039270422075],"type":"Point"}
}