{
  "type": "Feature",
  "properties": {
    "date:inception_lower": "1992-01-01",
    "date:inception_upper": "1992-01-01",
    "iso:country": "GB",
    "wof:name": "B95 5EA",
    "wof:placetype": "postalcode"
  },
  "geometry": {"coordinates":[-1.759581,52.300408],"type":"Point"}
}
