{
  "type": "Feature",
  "properties": {
    "iso:country":"GB",
    "wof:name":"KT10 9HQ",
    "wof:placetype":"postalcode"
},
  "geometry": {"coordinates":[-0.35789030809477,51.35185179147032],"type":"Point"}
}