{
  "type": "Feature",
  "properties": {
    "iso:country":"GB",
    "wof:name":"CO2 7AP",
    "wof:placetype":"postalcode"
},
  "geometry": {"coordinates":[0.89366470015487,51.88202415583613],"type":"Point"}
}