{
  "type": "Feature",
  "properties": {
    "iso:country": "GB",
    "wof:name": "GU5 9EE",
    "wof:placetype": "postalcode"
  },
  "geometry": {"coordinates":[-0.484511,51.196843],"type":"Point"}
}
