{
  "type": "Feature",
  "properties": {
    "date:inception_lower":"1980-01-01",
    "date:inception_upper":"1980-01-31",
    "iso:country":"GB",
    "wof:name":"GU5 9EE",
    "wof:placetype":"postalcode"
},
  "geometry": {"coordinates":[-0.484511,51.196843],"type":"Point"}
}