{
  "type": "Feature",
  "properties": {
    "iso:country": "GB",
    "wof:name": "IV30 6XF",
    "wof:placetype": "postalcode"
  },
  "geometry": {"coordinates":[-3.317885,57.632868],"type":"Point"}
}
