{
  "type": "Feature",
  "properties": {
    "date:inception_lower": "1980-01-01",
    "date:inception_upper": "1980-01-01",
    "iso:country": "GB",
    "wof:name": "DN2 4EY",
    "wof:placetype": "postalcode"
  },
  "geometry": {"coordinates":[-1.116597,53.536154],"type":"Point"}
}
