{
  "type": "Feature",
  "properties": {
    "iso:country":"GB",
    "wof:name":"PH10 7DE",
    "wof:placetype":"postalcode"
},
  "geometry": {"coordinates":[-3.32942873593792,56.59454984663616],"type":"Point"}
}