{
  "type": "Feature",
  "properties": {
    "date:inception_lower": "1980-01-01",
    "date:inception_upper": "1980-01-01",
    "iso:country": "GB",
    "wof:name": "G72 9NN",
    "wof:placetype": "postalcode"
  },
  "geometry": {"coordinates":[-4.103644,55.804751],"type":"Point"}
}
