{
  "type": "Feature",
  "properties": {
    "iso:country":"GB",
    "wof:name":"S66 2RR",
    "wof:placetype":"postalcode"
},
  "geometry": {"coordinates":[-1.28080990075229,53.42794273324755],"type":"Point"}
}