{
  "type": "Feature",
  "properties": {
    "iso:country":"GB",
    "wof:name":"CB10 2PD",
    "wof:placetype":"postalcode"
},
  "geometry": {"coordinates":[0.37850968917802,52.01657163118146],"type":"Point"}
}