{
  "type": "Feature",
  "properties": {
    "date:inception_lower": "2013-02-01",
    "date:inception_upper": "2013-02-01",
    "iso:country": "GB",
    "wof:name": "EC4R 3TA",
    "wof:placetype": "postalcode"
  },
  "geometry": {"coordinates":[-0.092559,51.510608],"type":"Point"}
}
