{
  "type": "Feature",
  "properties": {
    "iso:country":"GB",
    "wof:name":"EC4R 3TA",
    "wof:placetype":"postalcode"
},
  "geometry": {"coordinates":[-0.09255903343046,51.51060817318471],"type":"Point"}
}