{
  "type": "Feature",
  "properties": {
    "iso:country":"GB",
    "wof:name":"B69 1XG",
    "wof:placetype":"postalcode"
},
  "geometry": {"coordinates":[-2.05931295007373,52.5046785764887],"type":"Point"}
}