{
  "type": "Feature",
  "properties": {
    "date:inception_lower":"1980-01-01",
    "date:inception_upper":"1980-01-31",
    "iso:country":"GB",
    "wof:name":"B69 1XG",
    "wof:placetype":"postalcode"
},
  "geometry": {"coordinates":[-2.059313,52.504679],"type":"Point"}
}