{
  "type": "Feature",
  "properties": {
    "iso:country": "GB",
    "wof:name": "B69 1XG",
    "wof:placetype": "postalcode"
  },
  "geometry": {"coordinates":[-2.059313,52.504679],"type":"Point"}
}
