{
  "type": "Feature",
  "properties": {
    "iso:country":"GB",
    "wof:name":"SK23 6DJ",
    "wof:placetype":"postalcode"
},
  "geometry": {"coordinates":[-1.93797768579971,53.34070782999511],"type":"Point"}
}