{
  "type": "Feature",
  "properties": {
    "iso:country": "GB",
    "wof:name": "WA11 0DS",
    "wof:placetype": "postalcode"
  },
  "geometry": {"coordinates":[-2.691486,53.462566],"type":"Point"}
}
