{
  "type": "Feature",
  "properties": {
    "iso:country":"GB",
    "wof:name":"DD9 7PP",
    "wof:placetype":"postalcode"
},
  "geometry": {"coordinates":[-2.59666971208771,56.73261973306486],"type":"Point"}
}