{
  "type": "Feature",
  "properties": {
    "iso:country":"GB",
    "wof:name":"ME20 6DA",
    "wof:placetype":"postalcode"
},
  "geometry": {"coordinates":[0.46245904490437,51.29764395055121],"type":"Point"}
}