{
  "type": "Feature",
  "properties": {
    "date:inception_lower": "1980-01-01",
    "date:inception_upper": "1980-01-01",
    "iso:country": "GB",
    "wof:name": "ME20 6DA",
    "wof:placetype": "postalcode"
  },
  "geometry": {"coordinates":[0.462459,51.297644],"type":"Point"}
}
