{
  "type": "Feature",
  "properties": {
    "iso:country":"GB",
    "wof:name":"CF15 9PJ",
    "wof:placetype":"postalcode"
},
  "geometry": {"coordinates":[-3.29279489252863,51.53192610447203],"type":"Point"}
}