{
  "type": "Feature",
  "properties": {
    "date:inception_lower": "1980-01-01",
    "date:inception_upper": "1980-01-01",
    "iso:country": "GB",
    "wof:name": "WF7 5JN",
    "wof:placetype": "postalcode"
  },
  "geometry": {"coordinates":[-1.367117,53.672136],"type":"Point"}
}
