{
  "type": "Feature",
  "properties": {
    "iso:country": "GB",
    "wof:name": "WF7 5JN",
    "wof:placetype": "postalcode"
  },
  "geometry": {"coordinates":[-1.367117,53.672136],"type":"Point"}
}
