{
  "type": "Feature",
  "properties": {
    "iso:country": "GB",
    "wof:name": "E7 8BE",
    "wof:placetype": "postalcode"
  },
  "geometry": {"coordinates":[0.027028,51.546327],"type":"Point"}
}
