{
  "type": "Feature",
  "properties": {
    "iso:country":"GB",
    "wof:name":"E7 8BE",
    "wof:placetype":"postalcode"
},
  "geometry": {"coordinates":[0.02702749536631,51.54632655995849],"type":"Point"}
}