{
  "type": "Feature",
  "properties": {
    "date:inception_lower":"1980-01-01",
    "date:inception_upper":"1980-01-31",
    "iso:country":"GB",
    "wof:name":"M16 9HN",
    "wof:placetype":"postalcode"
},
  "geometry": {"coordinates":[-2.268628,53.463906],"type":"Point"}
}