{
  "type": "Feature",
  "properties": {
    "iso:country":"GB",
    "wof:name":"M16 9HN",
    "wof:placetype":"postalcode"
},
  "geometry": {"coordinates":[-2.26862829298998,53.46390602268813],"type":"Point"}
}