{
  "type": "Feature",
  "properties": {
    "date:inception_lower": "1990-07-01",
    "date:inception_upper": "1990-07-01",
    "iso:country": "GB",
    "wof:name": "BD23 5AG",
    "wof:placetype": "postalcode"
  },
  "geometry": {"coordinates":[-1.996699,54.071443],"type":"Point"}
}
