{
  "type": "Feature",
  "properties": {
    "iso:country":"GB",
    "wof:name":"EH25 9PT",
    "wof:placetype":"postalcode"
},
  "geometry": {"coordinates":[-3.16371033846721,55.85631872808469],"type":"Point"}
}