{
  "type": "Feature",
  "properties": {
    "iso:country": "GB",
    "wof:name": "EH25 9PT",
    "wof:placetype": "postalcode"
  },
  "geometry": {"coordinates":[-3.16371,55.856319],"type":"Point"}
}
