{
  "type": "Feature",
  "properties": {
    "iso:country": "GB",
    "wof:name": "RM3 8FF",
    "wof:placetype": "postalcode"
  },
  "geometry": {"coordinates":[0.212934,51.603237],"type":"Point"}
}
