{
  "type": "Feature",
  "properties": {
    "iso:country":"GB",
    "wof:name":"SA17 4TW",
    "wof:placetype":"postalcode"
},
  "geometry": {"coordinates":[-4.30071541743011,51.73509160102095],"type":"Point"}
}