{
  "type": "Feature",
  "properties": {
    "date:inception_lower": "1980-01-01",
    "date:inception_upper": "1980-01-01",
    "iso:country": "GB",
    "wof:name": "EX32 0AD",
    "wof:placetype": "postalcode"
  },
  "geometry": {"coordinates":[-4.046751,51.052807],"type":"Point"}
}
