{
  "type": "Feature",
  "properties": {
    "iso:country":"GB",
    "wof:name":"EX32 0AD",
    "wof:placetype":"postalcode"
},
  "geometry": {"coordinates":[-4.04675121940125,51.05280653378073],"type":"Point"}
}