{
  "type": "Feature",
  "properties": {
    "iso:country":"GB",
    "wof:name":"BA2 0NY",
    "wof:placetype":"postalcode"
},
  "geometry": {"coordinates":[-2.4574882236579,51.32252137600447],"type":"Point"}
}