{
  "type": "Feature",
  "properties": {
    "iso:country": "GB",
    "wof:name": "DL14 0LP",
    "wof:placetype": "postalcode"
  },
  "geometry": {"coordinates":[-1.705653,54.654101],"type":"Point"}
}
