{
  "type": "Feature",
  "properties": {
    "iso:country":"GB",
    "wof:name":"BS15 9SX",
    "wof:placetype":"postalcode"
},
  "geometry": {"coordinates":[-2.5035662169633,51.45191183499274],"type":"Point"}
}