{
  "type": "Feature",
  "properties": {
    "iso:country":"GB",
    "wof:name":"EX12 2QW",
    "wof:placetype":"postalcode"
},
  "geometry": {"coordinates":[-3.07299311058212,50.70373199448518],"type":"Point"}
}