{
  "type": "Feature",
  "properties": {
    "iso:country": "GB",
    "wof:name": "BS15 9PB",
    "wof:placetype": "postalcode"
  },
  "geometry": {"coordinates":[-2.488214,51.460211],"type":"Point"}
}
