{
  "type": "Feature",
  "properties": {
    "iso:country":"GB",
    "wof:name":"BS15 9PB",
    "wof:placetype":"postalcode"
},
  "geometry": {"coordinates":[-2.48825659236404,51.46023990547977],"type":"Point"}
}