{
  "type": "Feature",
  "properties": {
    "iso:country":"GB",
    "wof:name":"NR9 5JB",
    "wof:placetype":"postalcode"
},
  "geometry": {"coordinates":[1.15593754100775,52.6544825417043],"type":"Point"}
}