{
  "type": "Feature",
  "properties": {
    "iso:country":"GB",
    "wof:name":"DT2 9LA",
    "wof:placetype":"postalcode"
},
  "geometry": {"coordinates":[-2.50369810987911,50.6991657907012],"type":"Point"}
}