{
  "type": "Feature",
  "properties": {
    "date:inception_lower":"1980-01-01",
    "date:inception_upper":"1980-01-31",
    "iso:country":"GB",
    "wof:name":"DT2 9LA",
    "wof:placetype":"postalcode"
},
  "geometry": {"coordinates":[-2.503711,50.699183],"type":"Point"}
}