{
  "type": "Feature",
  "properties": {
    "iso:country": "GB",
    "wof:name": "GL56 9SG",
    "wof:placetype": "postalcode"
  },
  "geometry": {"coordinates":[-1.675118,52.043891],"type":"Point"}
}
