{
  "type": "Feature",
  "properties": {
    "iso:country":"GB",
    "wof:name":"GL56 9SG",
    "wof:placetype":"postalcode"
},
  "geometry": {"coordinates":[-1.67511776276769,52.04389057484918],"type":"Point"}
}