{
  "type": "Feature",
  "properties": {
    "iso:country":"GB",
    "wof:name":"MK13 7LX",
    "wof:placetype":"postalcode"
},
  "geometry": {"coordinates":[-0.77368803475257,52.0563550398964],"type":"Point"}
}