{
  "type": "Feature",
  "properties": {
    "iso:country":"GB",
    "wof:name":"SK9 7JS",
    "wof:placetype":"postalcode"
},
  "geometry": {"coordinates":[-2.23641413427893,53.3020085006693],"type":"Point"}
}