{
  "type": "Feature",
  "properties": {
    "iso:country": "GB",
    "wof:name": "SK9 7JS",
    "wof:placetype": "postalcode"
  },
  "geometry": {"coordinates":[-2.236414,53.302008],"type":"Point"}
}
