{
  "type": "Feature",
  "properties": {
    "iso:country": "GB",
    "wof:name": "TF1 1JD",
    "wof:placetype": "postalcode"
  },
  "geometry": {"coordinates":[-2.511452,52.696114],"type":"Point"}
}
