{
  "type": "Feature",
  "properties": {
    "iso:country":"GB",
    "wof:name":"TF1 1JD",
    "wof:placetype":"postalcode"
},
  "geometry": {"coordinates":[-2.5114516291911,52.6961142534184],"type":"Point"}
}