{
  "type": "Feature",
  "properties": {
    "date:inception_lower": "1980-01-01",
    "date:inception_upper": "1980-01-01",
    "iso:country": "GB",
    "wof:name": "TF1 1JD",
    "wof:placetype": "postalcode"
  },
  "geometry": {"coordinates":[-2.511452,52.696114],"type":"Point"}
}
