{
  "type": "Feature",
  "properties": {
    "iso:country": "GB",
    "wof:name": "TA5 1EE",
    "wof:placetype": "postalcode"
  },
  "geometry": {"coordinates":[-3.218277,51.180781],"type":"Point"}
}
