{
  "type": "Feature",
  "properties": {
    "iso:country": "GB",
    "wof:name": "HP2 6EZ",
    "wof:placetype": "postalcode"
  },
  "geometry": {"coordinates":[-0.491131,51.794379],"type":"Point"}
}
