{
  "type": "Feature",
  "properties": {
    "date:inception_lower":"1980-01-01",
    "date:inception_upper":"1980-01-31",
    "iso:country":"GB",
    "wof:name":"HP2 6EZ",
    "wof:placetype":"postalcode"
},
  "geometry": {"coordinates":[-0.491131,51.794379],"type":"Point"}
}