{
  "type": "Feature",
  "properties": {
    "iso:country":"GB",
    "wof:name":"HP2 6EZ",
    "wof:placetype":"postalcode"
},
  "geometry": {"coordinates":[-0.49138167138491,51.79407778225058],"type":"Point"}
}