{
  "type": "Feature",
  "properties": {
    "iso:country": "GB",
    "wof:name": "DL4 1HE",
    "wof:placetype": "postalcode"
  },
  "geometry": {"coordinates":[-1.647394,54.625215],"type":"Point"}
}
