{
  "type": "Feature",
  "properties": {
    "iso:country":"GB",
    "wof:name":"DL4 1HE",
    "wof:placetype":"postalcode"
},
  "geometry": {"coordinates":[-1.64739369393229,54.62521538011647],"type":"Point"}
}