{
  "type": "Feature",
  "properties": {
    "date:inception_lower":"2015-06-01",
    "date:inception_upper":"2015-06-30",
    "iso:country":"GB",
    "wof:name":"NR6 5AP",
    "wof:placetype":"postalcode"
},
  "geometry": {"coordinates":[1.258418,52.644269],"type":"Point"}
}