{
  "type": "Feature",
  "properties": {
    "date:inception_lower": "2022-05-01",
    "date:inception_upper": "2022-05-01",
    "iso:country": "GB",
    "wof:name": "SG19 3FB",
    "wof:placetype": "postalcode"
  },
  "geometry": {"coordinates":[-0.197642,52.156451],"type":"Point"}
}
