{
  "type": "Feature",
  "properties": {
    "date:inception_lower": "1999-06-01",
    "date:inception_upper": "1999-06-01",
    "iso:country": "GB",
    "wof:name": "CH62 5DN",
    "wof:placetype": "postalcode"
  },
  "geometry": {"coordinates":[-2.995744,53.351768],"type":"Point"}
}
