{
  "type": "Feature",
  "properties": {
    "iso:country":"GB",
    "wof:name":"DL6 3SD",
    "wof:placetype":"postalcode"
},
  "geometry": {"coordinates":[-1.40482058907251,54.30361554025641],"type":"Point"}
}