{
  "type": "Feature",
  "properties": {
    "date:inception_lower": "2005-11-01",
    "date:inception_upper": "2005-11-01",
    "iso:country": "GB",
    "wof:name": "EN11 1AP",
    "wof:placetype": "postalcode"
  },
  "geometry": {"coordinates":[-0.010276,51.759754],"type":"Point"}
}
