{
  "type": "Feature",
  "properties": {
    "date:inception_lower": "2019-06-01",
    "date:inception_upper": "2019-06-01",
    "iso:country": "GB",
    "wof:name": "PE28 9RD",
    "wof:placetype": "postalcode"
  },
  "geometry": {"coordinates":[-0.088715,52.301706],"type":"Point"}
}
