{
  "type": "Feature",
  "properties": {
    "iso:country": "GB",
    "wof:name": "PE28 9RD",
    "wof:placetype": "postalcode"
  },
  "geometry": {"coordinates":[-0.088686,52.301697],"type":"Point"}
}
