{
  "type": "Feature",
  "properties": {
    "iso:country": "GB",
    "wof:name": "NR6 7NN",
    "wof:placetype": "postalcode"
  },
  "geometry": {"coordinates":[1.304165,52.658776],"type":"Point"}
}
