{
  "type": "Feature",
  "properties": {
    "iso:country":"GB",
    "wof:name":"LL13 0NS",
    "wof:placetype":"postalcode"
},
  "geometry": {"coordinates":[-2.97773935521342,53.03643924246364],"type":"Point"}
}