{
  "type": "Feature",
  "properties": {
    "date:inception_lower": "2020-04-01",
    "date:inception_upper": "2020-04-01",
    "iso:country": "GB",
    "wof:name": "CW2 6GX",
    "wof:placetype": "postalcode"
  },
  "geometry": {"coordinates":[-2.435668,53.089234],"type":"Point"}
}
