{
  "type": "Feature",
  "properties": {
    "date:inception_lower": "2024-03-01",
    "date:inception_upper": "2024-03-01",
    "iso:country": "GB",
    "wof:name": "CO11 2GP",
    "wof:placetype": "postalcode"
  },
  "geometry": {"coordinates":[1.052251,51.936128],"type":"Point"}
}
