{
  "type": "Feature",
  "properties": {
    "iso:country": "GB",
    "wof:name": "SN25 2TA",
    "wof:placetype": "postalcode"
  },
  "geometry": {"coordinates":[-1.816232,51.611075],"type":"Point"}
}
