{
  "type": "Feature",
  "properties": {
    "iso:country":"GB",
    "wof:name":"EH25 9LL",
    "wof:placetype":"postalcode"
},
  "geometry": {"coordinates":[-3.1634901191926,55.85803705495354],"type":"Point"}
}