{
  "type": "Feature",
  "properties": {
    "iso:country": "GB",
    "wof:name": "EH25 9LL",
    "wof:placetype": "postalcode"
  },
  "geometry": {"coordinates":[-3.16349,55.858037],"type":"Point"}
}
