{
  "type": "Feature",
  "properties": {
    "iso:country":"GB",
    "wof:name":"CH48 3JE",
    "wof:placetype":"postalcode"
},
  "geometry": {"coordinates":[-3.17470005469019,53.36361462949638],"type":"Point"}
}