{
  "type": "Feature",
  "properties": {
    "date:inception_lower":"1980-01-01",
    "date:inception_upper":"1980-01-31",
    "iso:country":"GB",
    "wof:name":"BL9 0TR",
    "wof:placetype":"postalcode"
},
  "geometry": {"coordinates":[-2.301689,53.586699],"type":"Point"}
}