{
  "type": "Feature",
  "properties": {
    "iso:country":"GB",
    "wof:name":"BL9 0TR",
    "wof:placetype":"postalcode"
},
  "geometry": {"coordinates":[-2.30168861187197,53.58669853453851],"type":"Point"}
}