{
  "type": "Feature",
  "properties": {
    "date:inception_lower": "1980-01-01",
    "date:inception_upper": "1980-01-01",
    "iso:country": "GB",
    "wof:name": "SS14 1SE",
    "wof:placetype": "postalcode"
  },
  "geometry": {"coordinates":[0.494304,51.567484],"type":"Point"}
}
