{
  "type": "Feature",
  "properties": {
    "iso:country":"GB",
    "wof:name":"SS14 1SE",
    "wof:placetype":"postalcode"
},
  "geometry": {"coordinates":[0.49430360963667,51.56748396804876],"type":"Point"}
}