{
  "type": "Feature",
  "properties": {
    "iso:country": "GB",
    "wof:name": "EH16 6LG",
    "wof:placetype": "postalcode"
  },
  "geometry": {"coordinates":[-3.167714,55.915217],"type":"Point"}
}
