{
  "type": "Feature",
  "properties": {
    "iso:country":"GB",
    "wof:name":"NE15 9SE",
    "wof:placetype":"postalcode"
},
  "geometry": {"coordinates":[-1.72461368369224,54.98999673156868],"type":"Point"}
}