{
  "type": "Feature",
  "properties": {
    "date:inception_lower": "1980-01-01",
    "date:inception_upper": "1980-01-01",
    "iso:country": "GB",
    "wof:name": "NE15 9SE",
    "wof:placetype": "postalcode"
  },
  "geometry": {"coordinates":[-1.724614,54.989997],"type":"Point"}
}
