{
  "type": "Feature",
  "properties": {
    "iso:country": "GB",
    "wof:name": "NE15 9SE",
    "wof:placetype": "postalcode"
  },
  "geometry": {"coordinates":[-1.724614,54.989997],"type":"Point"}
}
