{
  "type": "Feature",
  "properties": {
    "date:inception_lower":"1980-01-01",
    "date:inception_upper":"1980-01-31",
    "iso:country":"GB",
    "wof:name":"LL18 1NG",
    "wof:placetype":"postalcode"
},
  "geometry": {"coordinates":[-3.500981,53.315458],"type":"Point"}
}