{
  "type": "Feature",
  "properties": {
    "iso:country": "GB",
    "wof:name": "ST12 9FE",
    "wof:placetype": "postalcode"
  },
  "geometry": {"coordinates":[-2.16883,52.955786],"type":"Point"}
}
