{
  "type": "Feature",
  "properties": {
    "iso:country":"GB",
    "wof:name":"DA2 6FX",
    "wof:placetype":"postalcode"
},
  "geometry": {"coordinates":[0.24423810760776,51.44748667047514],"type":"Point"}
}