{
  "type": "Feature",
  "properties": {
    "iso:country":"GB",
    "wof:name":"NG9 2HL",
    "wof:placetype":"postalcode"
},
  "geometry": {"coordinates":[-1.21410134237373,52.93125974497535],"type":"Point"}
}