{
  "type": "Feature",
  "properties": {
    "iso:country":"GB",
    "wof:name":"BD18 4AR",
    "wof:placetype":"postalcode"
},
  "geometry": {"coordinates":[-1.81082338707417,53.82949238868866],"type":"Point"}
}