{
  "type": "Feature",
  "properties": {
    "iso:country": "GB",
    "wof:name": "CA7 3BD",
    "wof:placetype": "postalcode"
  },
  "geometry": {"coordinates":[-3.321375,54.764893],"type":"Point"}
}
