{
  "type": "Feature",
  "properties": {
    "iso:country":"GB",
    "wof:name":"CA7 3BD",
    "wof:placetype":"postalcode"
},
  "geometry": {"coordinates":[-3.3213751353472,54.76489328791035],"type":"Point"}
}