{
  "type": "Feature",
  "properties": {
    "iso:country": "GB",
    "wof:name": "SG11 1UX",
    "wof:placetype": "postalcode"
  },
  "geometry": {"coordinates":[0.012186,51.891998],"type":"Point"}
}
