{
  "type": "Feature",
  "properties": {
    "iso:country":"GB",
    "wof:name":"SG11 1UX",
    "wof:placetype":"postalcode"
},
  "geometry": {"coordinates":[0.01205267805231,51.89225257962222],"type":"Point"}
}