{
  "type": "Feature",
  "properties": {
    "iso:country": "GB",
    "wof:name": "PO21 5PW",
    "wof:placetype": "postalcode"
  },
  "geometry": {"coordinates":[-0.696376,50.788233],"type":"Point"}
}
