{
  "type": "Feature",
  "properties": {
    "iso:country":"GB",
    "wof:name":"HD3 4TH",
    "wof:placetype":"postalcode"
},
  "geometry": {"coordinates":[-1.84066994405808,53.64692534665951],"type":"Point"}
}