{
  "type": "Feature",
  "properties": {
    "iso:country":"GB",
    "wof:name":"PR4 5LH",
    "wof:placetype":"postalcode"
},
  "geometry": {"coordinates":[-2.81296716435592,53.71065753085998],"type":"Point"}
}