{
  "type": "Feature",
  "properties": {
    "iso:country":"GB",
    "wof:name":"TS22 5PU",
    "wof:placetype":"postalcode"
},
  "geometry": {"coordinates":[-1.26086184083858,54.63903028237846],"type":"Point"}
}