{
  "type": "Feature",
  "properties": {
    "iso:country":"GB",
    "wof:name":"NG34 9EQ",
    "wof:placetype":"postalcode"
},
  "geometry": {"coordinates":[-0.40025073874803,53.0456805965951],"type":"Point"}
}