{
  "type": "Feature",
  "properties": {
    "iso:country": "GB",
    "wof:name": "NG34 9EQ",
    "wof:placetype": "postalcode"
  },
  "geometry": {"coordinates":[-0.400251,53.045681],"type":"Point"}
}
