{
  "type": "Feature",
  "properties": {
    "iso:country":"GB",
    "wof:name":"AB35 5XA",
    "wof:placetype":"postalcode"
},
  "geometry": {"coordinates":[-3.05590642921125,57.05553191760422],"type":"Point"}
}