{
  "type": "Feature",
  "properties": {
    "date:inception_lower": "1990-08-01",
    "date:inception_upper": "1990-08-01",
    "iso:country": "GB",
    "wof:name": "AB35 5XA",
    "wof:placetype": "postalcode"
  },
  "geometry": {"coordinates":[-3.055906,57.055532],"type":"Point"}
}
