{
  "type": "Feature",
  "properties": {
    "date:inception_lower": "1999-12-01",
    "date:inception_upper": "1999-12-01",
    "iso:country": "GB",
    "wof:name": "IP22 5SF",
    "wof:placetype": "postalcode"
  },
  "geometry": {"coordinates":[1.092565,52.374802],"type":"Point"}
}
