{
  "type": "Feature",
  "properties": {
    "iso:country":"GB",
    "wof:name":"IP22 5SF",
    "wof:placetype":"postalcode"
},
  "geometry": {"coordinates":[1.0923078423048,52.37487804045048],"type":"Point"}
}