{
  "type": "Feature",
  "properties": {
    "date:inception_lower": "1980-01-01",
    "date:inception_upper": "1980-01-01",
    "iso:country": "GB",
    "wof:name": "PH10 7BB",
    "wof:placetype": "postalcode"
  },
  "geometry": {"coordinates":[-3.34071,56.602228],"type":"Point"}
}
