{
  "type": "Feature",
  "properties": {
    "iso:country":"GB",
    "wof:name":"NR29 5LH",
    "wof:placetype":"postalcode"
},
  "geometry": {"coordinates":[1.57649707038383,52.72062999286822],"type":"Point"}
}