{
  "type": "Feature",
  "properties": {
    "iso:country":"GB",
    "wof:name":"CA28 6SQ",
    "wof:placetype":"postalcode"
},
  "geometry": {"coordinates":[-3.56641257162804,54.5497652496222],"type":"Point"}
}