{
  "type": "Feature",
  "properties": {
    "date:inception_lower": "1980-01-01",
    "date:inception_upper": "1980-01-01",
    "iso:country": "GB",
    "wof:name": "CA28 6SQ",
    "wof:placetype": "postalcode"
  },
  "geometry": {"coordinates":[-3.566413,54.549765],"type":"Point"}
}
