{
  "type": "Feature",
  "properties": {
    "date:inception_lower": "1980-01-01",
    "date:inception_upper": "1980-01-01",
    "iso:country": "GB",
    "wof:name": "LA12 0LQ",
    "wof:placetype": "postalcode"
  },
  "geometry": {"coordinates":[-3.14635,54.172293],"type":"Point"}
}
