{
  "type": "Feature",
  "properties": {
    "iso:country":"GB",
    "wof:name":"LA12 0LQ",
    "wof:placetype":"postalcode"
},
  "geometry": {"coordinates":[-3.14634964768699,54.17229282351578],"type":"Point"}
}