{
  "type": "Feature",
  "properties": {
    "iso:country":"GB",
    "wof:name":"TF11 8NW",
    "wof:placetype":"postalcode"
},
  "geometry": {"coordinates":[-2.28766481940862,52.71411106821817],"type":"Point"}
}