{
  "type": "Feature",
  "properties": {
    "iso:country": "GB",
    "wof:name": "TF11 8NW",
    "wof:placetype": "postalcode"
  },
  "geometry": {"coordinates":[-2.287665,52.714111],"type":"Point"}
}
