{
  "type": "Feature",
  "properties": {
    "date:inception_lower": "1998-12-01",
    "date:inception_upper": "1998-12-01",
    "iso:country": "GB",
    "wof:name": "TF11 8NW",
    "wof:placetype": "postalcode"
  },
  "geometry": {"coordinates":[-2.287665,52.714111],"type":"Point"}
}
