{
  "type": "Feature",
  "properties": {
    "date:inception_lower": "2020-12-01",
    "date:inception_upper": "2020-12-01",
    "iso:country": "GB",
    "wof:name": "SS3 9XE",
    "wof:placetype": "postalcode"
  },
  "geometry": {"coordinates":[0.841688,51.589681],"type":"Point"}
}
