{
  "type": "Feature",
  "properties": {
    "iso:country":"GB",
    "wof:name":"BB2 5HU",
    "wof:placetype":"postalcode"
},
  "geometry": {"coordinates":[-2.53536483768941,53.72519011189119],"type":"Point"}
}