{
  "type": "Feature",
  "properties": {
    "date:inception_lower":"2007-10-01",
    "date:inception_upper":"2007-10-31",
    "iso:country":"GB",
    "wof:name":"HA4 6DQ",
    "wof:placetype":"postalcode"
},
  "geometry": {"coordinates":[-0.409399,51.551976],"type":"Point"}
}