{
  "type": "Feature",
  "properties": {
    "iso:country":"GB",
    "wof:name":"WS2 7EQ",
    "wof:placetype":"postalcode"
},
  "geometry": {"coordinates":[-2.00350050646605,52.60302443615181],"type":"Point"}
}