{
  "type": "Feature",
  "properties": {
    "iso:country": "GB",
    "wof:name": "WS2 7EQ",
    "wof:placetype": "postalcode"
  },
  "geometry": {"coordinates":[-2.0035,52.603024],"type":"Point"}
}
