{
  "type": "Feature",
  "properties": {
    "iso:country":"GB",
    "wof:name":"SM6 8ED",
    "wof:placetype":"postalcode"
},
  "geometry": {"coordinates":[-0.13841640141713,51.36903694851276],"type":"Point"}
}