{
  "type": "Feature",
  "properties": {
    "iso:country":"GB",
    "wof:name":"PE6 9BH",
    "wof:placetype":"postalcode"
},
  "geometry": {"coordinates":[-0.30151427994001,52.6597990372327],"type":"Point"}
}