{
  "type": "Feature",
  "properties": {
    "iso:country":"GB",
    "wof:name":"PL17 7NW",
    "wof:placetype":"postalcode"
},
  "geometry": {"coordinates":[-4.36189311038703,50.5171249786631],"type":"Point"}
}