{
  "type": "Feature",
  "properties": {
    "date:inception_lower": "1995-01-01",
    "date:inception_upper": "1995-01-01",
    "iso:country": "GB",
    "wof:name": "PL17 7NW",
    "wof:placetype": "postalcode"
  },
  "geometry": {"coordinates":[-4.361893,50.517125],"type":"Point"}
}
