{
  "type": "Feature",
  "properties": {
    "iso:country":"GB",
    "wof:name":"SM1 3QS",
    "wof:placetype":"postalcode"
},
  "geometry": {"coordinates":[-0.17518675984099,51.3696064745968],"type":"Point"}
}