{
  "type": "Feature",
  "properties": {
    "iso:country":"GB",
    "wof:name":"SE18 5RP",
    "wof:placetype":"postalcode"
},
  "geometry": {"coordinates":[0.06000992668322,51.49068945240981],"type":"Point"}
}