{
  "type": "Feature",
  "properties": {
    "iso:country":"GB",
    "wof:name":"ML6 8LX",
    "wof:placetype":"postalcode"
},
  "geometry": {"coordinates":[-3.9446701876435,55.8668613923078],"type":"Point"}
}