{
  "type": "Feature",
  "properties": {
    "iso:country":"GB",
    "wof:name":"YO25 8JY",
    "wof:placetype":"postalcode"
},
  "geometry": {"coordinates":[-0.33015807127691,53.96206134820728],"type":"Point"}
}