{
  "type": "Feature",
  "properties": {
    "date:inception_lower":"1980-01-01",
    "date:inception_upper":"1980-01-31",
    "iso:country":"GB",
    "wof:name":"YO25 8JY",
    "wof:placetype":"postalcode"
},
  "geometry": {"coordinates":[-0.330158,53.962061],"type":"Point"}
}