{
  "type": "Feature",
  "properties": {
    "iso:country":"GB",
    "wof:name":"NE9 6RE",
    "wof:placetype":"postalcode"
},
  "geometry": {"coordinates":[-1.58457973838452,54.93880896205418],"type":"Point"}
}