{
  "type": "Feature",
  "properties": {
    "iso:country":"GB",
    "wof:name":"G84 8LP",
    "wof:placetype":"postalcode"
},
  "geometry": {"coordinates":[-4.76784061461516,56.02123006422892],"type":"Point"}
}