{
  "type": "Feature",
  "properties": {
    "iso:country": "GB",
    "wof:name": "G84 8LP",
    "wof:placetype": "postalcode"
  },
  "geometry": {"coordinates":[-4.767821,56.021223],"type":"Point"}
}
