{
  "type": "Feature",
  "properties": {
    "date:inception_lower": "1980-01-01",
    "date:inception_upper": "1980-01-01",
    "iso:country": "GB",
    "wof:name": "G84 8LP",
    "wof:placetype": "postalcode"
  },
  "geometry": {"coordinates":[-4.767821,56.021223],"type":"Point"}
}
