{
  "type": "Feature",
  "properties": {
    "iso:country":"GB",
    "wof:name":"FY1 3DZ",
    "wof:placetype":"postalcode"
},
  "geometry": {"coordinates":[-3.04608188249016,53.81937044665184],"type":"Point"}
}