{
  "type": "Feature",
  "properties": {
    "iso:country": "GB",
    "wof:name": "FY1 3DZ",
    "wof:placetype": "postalcode"
  },
  "geometry": {"coordinates":[-3.046082,53.81937],"type":"Point"}
}
