{
  "type": "Feature",
  "properties": {
    "iso:country":"GB",
    "wof:name":"DG1 3BQ",
    "wof:placetype":"postalcode"
},
  "geometry": {"coordinates":[-3.59396105553141,55.07085707259841],"type":"Point"}
}