{
  "type": "Feature",
  "properties": {
    "iso:country":"GB",
    "wof:name":"TS19 0XH",
    "wof:placetype":"postalcode"
},
  "geometry": {"coordinates":[-1.34841814604439,54.57595023435128],"type":"Point"}
}