{
  "type": "Feature",
  "properties": {
    "iso:country": "GB",
    "wof:name": "RG10 9JN",
    "wof:placetype": "postalcode"
  },
  "geometry": {"coordinates":[-0.8581,51.480508],"type":"Point"}
}
