{
  "type": "Feature",
  "properties": {
    "iso:country": "GB",
    "wof:name": "ST20 0GQ",
    "wof:placetype": "postalcode"
  },
  "geometry": {"coordinates":[-2.258878,52.790154],"type":"Point"}
}
