{
  "type": "Feature",
  "properties": {
    "iso:country":"GB",
    "wof:name":"CW1 6FN",
    "wof:placetype":"postalcode"
},
  "geometry": {"coordinates":[-2.41693388647427,53.09594592387825],"type":"Point"}
}