{
  "type": "Feature",
  "properties": {
    "iso:country":"GB",
    "wof:name":"BR7 5EU",
    "wof:placetype":"postalcode"
},
  "geometry": {"coordinates":[0.04422570865565,51.41893330688252],"type":"Point"}
}