{
  "type": "Feature",
  "properties": {
    "iso:country": "GB",
    "wof:name": "BR7 5EU",
    "wof:placetype": "postalcode"
  },
  "geometry": {"coordinates":[0.044226,51.418933],"type":"Point"}
}
