{
  "type": "Feature",
  "properties": {
    "iso:country":"GB",
    "wof:name":"HD1 3QG",
    "wof:placetype":"postalcode"
},
  "geometry": {"coordinates":[-1.79044555634,53.63492972290273],"type":"Point"}
}