{
  "type": "Feature",
  "properties": {
    "iso:country": "GB",
    "wof:name": "BR8 7DJ",
    "wof:placetype": "postalcode"
  },
  "geometry": {"coordinates":[0.161966,51.39735],"type":"Point"}
}
