{
  "type": "Feature",
  "properties": {
    "date:inception_lower":"2018-04-01",
    "date:inception_upper":"2018-04-30",
    "iso:country":"GB",
    "wof:name":"TQ7 2NL",
    "wof:placetype":"postalcode"
},
  "geometry": {"coordinates":[-3.710505,50.23298],"type":"Point"}
}