{
  "type": "Feature",
  "properties": {
    "date:inception_lower": "2018-04-01",
    "date:inception_upper": "2018-04-01",
    "iso:country": "GB",
    "wof:name": "TQ7 2NL",
    "wof:placetype": "postalcode"
  },
  "geometry": {"coordinates":[-3.710529,50.232872],"type":"Point"}
}
