{
  "type": "Feature",
  "properties": {
    "date:inception_lower":"1980-01-01",
    "date:inception_upper":"1980-01-31",
    "iso:country":"GB",
    "wof:name":"HP14 3BD",
    "wof:placetype":"postalcode"
},
  "geometry": {"coordinates":[-0.8309,51.637948],"type":"Point"}
}