{
  "type": "Feature",
  "properties": {
    "iso:country":"GB",
    "wof:name":"HP14 3BD",
    "wof:placetype":"postalcode"
},
  "geometry": {"coordinates":[-0.83089984173029,51.63794756588895],"type":"Point"}
}