{
  "type": "Feature",
  "properties": {
    "iso:country": "GB",
    "wof:name": "E3 2QZ",
    "wof:placetype": "postalcode"
  },
  "geometry": {"coordinates":[-0.026591,51.535119],"type":"Point"}
}
