{
  "type": "Feature",
  "properties": {
    "iso:country":"GB",
    "wof:name":"EX14 3JQ",
    "wof:placetype":"postalcode"
},
  "geometry": {"coordinates":[-3.27900453043397,50.81055016700584],"type":"Point"}
}