{
  "type": "Feature",
  "properties": {
    "iso:country":"GB",
    "wof:name":"TS3 8TG",
    "wof:placetype":"postalcode"
},
  "geometry": {"coordinates":[-1.19407326476278,54.57289123601981],"type":"Point"}
}