{
  "type": "Feature",
  "properties": {
    "date:inception_lower": "1996-12-01",
    "date:inception_upper": "1996-12-01",
    "iso:country": "GB",
    "wof:name": "TS3 8TG",
    "wof:placetype": "postalcode"
  },
  "geometry": {"coordinates":[-1.194087,54.572904],"type":"Point"}
}
