{
  "type": "Feature",
  "properties": {
    "iso:country":"GB",
    "wof:name":"IP13 7LF",
    "wof:placetype":"postalcode"
},
  "geometry": {"coordinates":[1.31266397078142,52.19697182466101],"type":"Point"}
}