{
  "type": "Feature",
  "properties": {
    "date:inception_lower":"2007-02-01",
    "date:inception_upper":"2007-02-28",
    "iso:country":"GB",
    "wof:name":"AB51 3SS",
    "wof:placetype":"postalcode"
},
  "geometry": {"coordinates":[-2.389769,57.283342],"type":"Point"}
}