{
  "type": "Feature",
  "properties": {
    "iso:country":"GB",
    "wof:name":"SM6 7JP",
    "wof:placetype":"postalcode"
},
  "geometry": {"coordinates":[-0.15782545875034,51.37226637891198],"type":"Point"}
}