{
  "type": "Feature",
  "properties": {
    "iso:country":"GB",
    "wof:name":"LE3 6UH",
    "wof:placetype":"postalcode"
},
  "geometry": {"coordinates":[-1.19718408380347,52.63641840681084],"type":"Point"}
}