{
  "type": "Feature",
  "properties": {
    "date:inception_lower": "1993-01-01",
    "date:inception_upper": "1993-01-01",
    "iso:country": "GB",
    "wof:name": "LE3 6UH",
    "wof:placetype": "postalcode"
  },
  "geometry": {"coordinates":[-1.197184,52.636418],"type":"Point"}
}
