{
  "type": "Feature",
  "properties": {
    "date:inception_lower": "2016-09-01",
    "date:inception_upper": "2016-09-01",
    "iso:country": "GB",
    "wof:name": "ST7 1GH",
    "wof:placetype": "postalcode"
  },
  "geometry": {"coordinates":[-2.262293,53.085608],"type":"Point"}
}
