{
  "type": "Feature",
  "properties": {
    "iso:country":"GB",
    "wof:name":"SL3 8SU",
    "wof:placetype":"postalcode"
},
  "geometry": {"coordinates":[-0.5420396814602,51.49782211205877],"type":"Point"}
}