{
  "type": "Feature",
  "properties": {
    "iso:country":"GB",
    "wof:name":"ME14 5SF",
    "wof:placetype":"postalcode"
},
  "geometry": {"coordinates":[0.53773054793642,51.27162723300718],"type":"Point"}
}