{
  "type": "Feature",
  "properties": {
    "iso:country":"GB",
    "wof:name":"UB6 9TR",
    "wof:placetype":"postalcode"
},
  "geometry": {"coordinates":[-0.36920458859334,51.53370049186946],"type":"Point"}
}