{
  "type": "Feature",
  "properties": {
    "date:inception_lower":"1980-01-01",
    "date:inception_upper":"1980-01-31",
    "iso:country":"GB",
    "wof:name":"SG18 9BH",
    "wof:placetype":"postalcode"
},
  "geometry": {"coordinates":[-0.293714,52.099756],"type":"Point"}
}