{
  "type": "Feature",
  "properties": {
    "iso:country":"GB",
    "wof:name":"NR12 8BS",
    "wof:placetype":"postalcode"
},
  "geometry": {"coordinates":[1.47551909982295,52.72601029320894],"type":"Point"}
}