{
  "type": "Feature",
  "properties": {
    "iso:country":"GB",
    "wof:name":"NG7 6HA",
    "wof:placetype":"postalcode"
},
  "geometry": {"coordinates":[-1.16787212107516,52.96879989185895],"type":"Point"}
}