{
  "type": "Feature",
  "properties": {
    "iso:country": "GB",
    "wof:name": "NG7 6HA",
    "wof:placetype": "postalcode"
  },
  "geometry": {"coordinates":[-1.167872,52.9688],"type":"Point"}
}
