{
  "type": "Feature",
  "properties": {
    "iso:country":"GB",
    "wof:name":"RH11 8NX",
    "wof:placetype":"postalcode"
},
  "geometry": {"coordinates":[-0.21372860953595,51.10229562954122],"type":"Point"}
}