{
  "type": "Feature",
  "properties": {
    "iso:country": "GB",
    "wof:name": "BH24 2DR",
    "wof:placetype": "postalcode"
  },
  "geometry": {"coordinates":[-1.846216,50.825673],"type":"Point"}
}
