{
  "type": "Feature",
  "properties": {
    "iso:country":"GB",
    "wof:name":"BH24 2DR",
    "wof:placetype":"postalcode"
},
  "geometry": {"coordinates":[-1.84621629216919,50.82567285617816],"type":"Point"}
}