{
  "type": "Feature",
  "properties": {
    "iso:country": "GB",
    "wof:name": "ML9 1DY",
    "wof:placetype": "postalcode"
  },
  "geometry": {"coordinates":[-3.980767,55.74737],"type":"Point"}
}
