{
  "type": "Feature",
  "properties": {
    "iso:country": "GB",
    "wof:name": "GU23 6AY",
    "wof:placetype": "postalcode"
  },
  "geometry": {"coordinates":[-0.491121,51.300739],"type":"Point"}
}
