{
  "type": "Feature",
  "properties": {
    "iso:country":"GB",
    "wof:name":"GU23 6AY",
    "wof:placetype":"postalcode"
},
  "geometry": {"coordinates":[-0.49108487167529,51.30074970799199],"type":"Point"}
}