{
  "type": "Feature",
  "properties": {
    "iso:country":"GB",
    "wof:name":"IP17 1JF",
    "wof:placetype":"postalcode"
},
  "geometry": {"coordinates":[1.44594452198443,52.19959994177999],"type":"Point"}
}