{
  "type": "Feature",
  "properties": {
    "date:inception_lower": "1980-01-01",
    "date:inception_upper": "1980-01-01",
    "iso:country": "GB",
    "wof:name": "IP17 1JF",
    "wof:placetype": "postalcode"
  },
  "geometry": {"coordinates":[1.445931,52.199602],"type":"Point"}
}
