{
  "type": "Feature",
  "properties": {
    "date:inception_lower":"1980-01-01",
    "date:inception_upper":"1980-01-31",
    "iso:country":"GB",
    "wof:name":"NP7 8HS",
    "wof:placetype":"postalcode"
},
  "geometry": {"coordinates":[-2.885108,51.905841],"type":"Point"}
}