{
  "type": "Feature",
  "properties": {
    "iso:country":"GB",
    "wof:name":"NP7 8HS",
    "wof:placetype":"postalcode"
},
  "geometry": {"coordinates":[-2.88510843035898,51.90584101515202],"type":"Point"}
}