{
  "type": "Feature",
  "properties": {
    "iso:country": "GB",
    "wof:name": "NP7 8HS",
    "wof:placetype": "postalcode"
  },
  "geometry": {"coordinates":[-2.885108,51.905841],"type":"Point"}
}
