{
  "type": "Feature",
  "properties": {
    "iso:country":"GB",
    "wof:name":"EC2M 3BN",
    "wof:placetype":"postalcode"
},
  "geometry": {"coordinates":[-0.07937192262348,51.52090528159202],"type":"Point"}
}