{
  "type": "Feature",
  "properties": {
    "date:inception_lower":"2014-03-01",
    "date:inception_upper":"2014-03-31",
    "iso:country":"GB",
    "wof:name":"EC2M 3BN",
    "wof:placetype":"postalcode"
},
  "geometry": {"coordinates":[-0.079241,51.520644],"type":"Point"}
}