{
  "type": "Feature",
  "properties": {
    "iso:country":"GB",
    "wof:name":"LE17 5QQ",
    "wof:placetype":"postalcode"
},
  "geometry": {"coordinates":[-1.11585335352403,52.51672990954147],"type":"Point"}
}