{
  "type": "Feature",
  "properties": {
    "date:inception_lower":"1980-01-01",
    "date:inception_upper":"1980-01-31",
    "iso:country":"GB",
    "wof:name":"LE17 5QQ",
    "wof:placetype":"postalcode"
},
  "geometry": {"coordinates":[-1.115853,52.51673],"type":"Point"}
}