{
  "type": "Feature",
  "properties": {
    "iso:country": "GB",
    "wof:name": "WV3 9SE",
    "wof:placetype": "postalcode"
  },
  "geometry": {"coordinates":[-2.14635,52.583866],"type":"Point"}
}
