{
  "type": "Feature",
  "properties": {
    "iso:country":"GB",
    "wof:name":"WV3 9SE",
    "wof:placetype":"postalcode"
},
  "geometry": {"coordinates":[-2.14635009355132,52.58386641340901],"type":"Point"}
}