{
  "type": "Feature",
  "properties": {
    "iso:country": "GB",
    "wof:name": "NN18 9FQ",
    "wof:placetype": "postalcode"
  },
  "geometry": {"coordinates":[-0.732565,52.477076],"type":"Point"}
}
