{
  "type": "Feature",
  "properties": {
    "date:inception_lower": "2014-12-01",
    "date:inception_upper": "2014-12-01",
    "iso:country": "GB",
    "wof:name": "MK18 3FQ",
    "wof:placetype": "postalcode"
  },
  "geometry": {"coordinates":[-0.889806,51.943058],"type":"Point"}
}
