{
  "type": "Feature",
  "properties": {
    "iso:country":"GB",
    "wof:name":"MK18 3FQ",
    "wof:placetype":"postalcode"
},
  "geometry": {"coordinates":[-0.88980599815072,51.9430582260769],"type":"Point"}
}