{
  "type": "Feature",
  "properties": {
    "iso:country":"GB",
    "wof:name":"SP4 9HR",
    "wof:placetype":"postalcode"
},
  "geometry": {"coordinates":[-1.75564980724837,51.19224009762782],"type":"Point"}
}