{
  "type": "Feature",
  "properties": {
    "iso:country":"GB",
    "wof:name":"BN1 6EB",
    "wof:placetype":"postalcode"
},
  "geometry": {"coordinates":[-0.13786636501151,50.83878744658215],"type":"Point"}
}