{
  "type": "Feature",
  "properties": {
    "iso:country":"GB",
    "wof:name":"AB39 2LX",
    "wof:placetype":"postalcode"
},
  "geometry": {"coordinates":[-2.22456735811917,56.9630862432879],"type":"Point"}
}