{
  "type": "Feature",
  "properties": {
    "date:inception_lower": "1996-06-01",
    "date:inception_upper": "1996-06-01",
    "iso:country": "GB",
    "wof:name": "AB39 2LX",
    "wof:placetype": "postalcode"
  },
  "geometry": {"coordinates":[-2.224567,56.963086],"type":"Point"}
}
