{
  "type": "Feature",
  "properties": {
    "iso:country":"GB",
    "wof:name":"SE7 7DB",
    "wof:placetype":"postalcode"
},
  "geometry": {"coordinates":[0.03459844482233,51.47773393139646],"type":"Point"}
}