{
  "type": "Feature",
  "properties": {
    "iso:country":"GB",
    "wof:name":"OX15 4FW",
    "wof:placetype":"postalcode"
},
  "geometry": {"coordinates":[-1.36978586170961,52.02535566794599],"type":"Point"}
}