{
  "type": "Feature",
  "properties": {
    "iso:country":"GB",
    "wof:name":"TR11 5DF",
    "wof:placetype":"postalcode"
},
  "geometry": {"coordinates":[-5.10363037132559,50.149424403578],"type":"Point"}
}