{
  "type": "Feature",
  "properties": {
    "date:inception_lower": "1980-01-01",
    "date:inception_upper": "1980-01-01",
    "iso:country": "GB",
    "wof:name": "TR11 5DF",
    "wof:placetype": "postalcode"
  },
  "geometry": {"coordinates":[-5.103747,50.149401],"type":"Point"}
}
