{
  "type": "Feature",
  "properties": {
    "iso:country":"GB",
    "wof:name":"SK10 4LP",
    "wof:placetype":"postalcode"
},
  "geometry": {"coordinates":[-2.16221851823127,53.3193280218041],"type":"Point"}
}