{
  "type": "Feature",
  "properties": {
    "iso:country":"GB",
    "wof:name":"EX4 6QH",
    "wof:placetype":"postalcode"
},
  "geometry": {"coordinates":[-3.52328148646566,50.73022879514544],"type":"Point"}
}