{
  "type": "Feature",
  "properties": {
    "iso:country":"GB",
    "wof:name":"PR4 2WT",
    "wof:placetype":"postalcode"
},
  "geometry": {"coordinates":[-2.92008783986371,53.77468880251913],"type":"Point"}
}