{
  "type": "Feature",
  "properties": {
    "iso:country": "GB",
    "wof:name": "PR4 2WT",
    "wof:placetype": "postalcode"
  },
  "geometry": {"coordinates":[-2.920088,53.774689],"type":"Point"}
}
