{
  "type": "Feature",
  "properties": {
    "date:inception_lower": "1980-01-01",
    "date:inception_upper": "1980-01-01",
    "iso:country": "GB",
    "wof:name": "NW9 6DS",
    "wof:placetype": "postalcode"
  },
  "geometry": {"coordinates":[-0.246396,51.590937],"type":"Point"}
}
