{
  "type": "Feature",
  "properties": {
    "iso:country":"GB",
    "wof:name":"NW9 6DS",
    "wof:placetype":"postalcode"
},
  "geometry": {"coordinates":[-0.24639587472914,51.590936676202],"type":"Point"}
}