{
  "type": "Feature",
  "properties": {
    "iso:country":"GB",
    "wof:name":"EX6 7LL",
    "wof:placetype":"postalcode"
},
  "geometry": {"coordinates":[-3.67775501540371,50.66578292568737],"type":"Point"}
}