{
  "type": "Feature",
  "properties": {
    "date:inception_lower": "1980-01-01",
    "date:inception_upper": "1980-01-01",
    "iso:country": "GB",
    "wof:name": "EX6 7LL",
    "wof:placetype": "postalcode"
  },
  "geometry": {"coordinates":[-3.677755,50.665783],"type":"Point"}
}
