{
  "type": "Feature",
  "properties": {
    "iso:country":"GB",
    "wof:name":"CA4 9PD",
    "wof:placetype":"postalcode"
},
  "geometry": {"coordinates":[-2.77025167828454,54.80543115546742],"type":"Point"}
}