{
  "type": "Feature",
  "properties": {
    "iso:country": "GB",
    "wof:name": "CA4 9PD",
    "wof:placetype": "postalcode"
  },
  "geometry": {"coordinates":[-2.770502,54.805239],"type":"Point"}
}
