{
  "type": "Feature",
  "properties": {
    "iso:country": "GB",
    "wof:name": "WA2 9UF",
    "wof:placetype": "postalcode"
  },
  "geometry": {"coordinates":[-2.584921,53.417635],"type":"Point"}
}
