{
  "type": "Feature",
  "properties": {
    "date:inception_lower": "1980-01-01",
    "date:inception_upper": "1980-01-01",
    "iso:country": "GB",
    "wof:name": "LE15 7EH",
    "wof:placetype": "postalcode"
  },
  "geometry": {"coordinates":[-0.765322,52.690083],"type":"Point"}
}
