{
  "type": "Feature",
  "properties": {
    "date:inception_lower":"1980-01-01",
    "date:inception_upper":"1980-01-31",
    "iso:country":"GB",
    "wof:name":"LL11 6PN",
    "wof:placetype":"postalcode"
},
  "geometry": {"coordinates":[-3.044152,53.056279],"type":"Point"}
}