{
  "type": "Feature",
  "properties": {
    "iso:country":"GB",
    "wof:name":"LL11 6PN",
    "wof:placetype":"postalcode"
},
  "geometry": {"coordinates":[-3.04415143311085,53.05626287219462],"type":"Point"}
}