{
  "type": "Feature",
  "properties": {
    "iso:country": "GB",
    "wof:name": "NN18 9BY",
    "wof:placetype": "postalcode"
  },
  "geometry": {"coordinates":[-0.734908,52.478036],"type":"Point"}
}
