{
  "type": "Feature",
  "properties": {
    "iso:country":"GB",
    "wof:name":"DL17 0RB",
    "wof:placetype":"postalcode"
},
  "geometry": {"coordinates":[-1.54800054612328,54.66057190950185],"type":"Point"}
}