{
  "type": "Feature",
  "properties": {
    "iso:country": "GB",
    "wof:name": "CH60 2SY",
    "wof:placetype": "postalcode"
  },
  "geometry": {"coordinates":[-3.079457,53.329268],"type":"Point"}
}
