{
  "type": "Feature",
  "properties": {
    "iso:country":"GB",
    "wof:name":"FK3 8LD",
    "wof:placetype":"postalcode"
},
  "geometry": {"coordinates":[-3.72245253315215,56.01558871907373],"type":"Point"}
}