{
  "type": "Feature",
  "properties": {
    "iso:country": "GB",
    "wof:name": "FK3 8LD",
    "wof:placetype": "postalcode"
  },
  "geometry": {"coordinates":[-3.722452,56.015589],"type":"Point"}
}
