{
  "type": "Feature",
  "properties": {
    "date:inception_lower": "1983-07-01",
    "date:inception_upper": "1983-07-01",
    "iso:country": "GB",
    "wof:name": "FK3 8LD",
    "wof:placetype": "postalcode"
  },
  "geometry": {"coordinates":[-3.722452,56.015589],"type":"Point"}
}
