{
  "type": "Feature",
  "properties": {
    "iso:country":"GB",
    "wof:name":"CO7 9PU",
    "wof:placetype":"postalcode"
},
  "geometry": {"coordinates":[0.95783462082255,51.86711676258627],"type":"Point"}
}