{
  "type": "Feature",
  "properties": {
    "iso:country":"GB",
    "wof:name":"SO51 7AA",
    "wof:placetype":"postalcode"
},
  "geometry": {"coordinates":[-1.4851587403366,51.00848968121494],"type":"Point"}
}