{
  "type": "Feature",
  "properties": {
    "date:inception_lower":"2003-09-01",
    "date:inception_upper":"2003-09-30",
    "iso:country":"GB",
    "wof:name":"SO51 7AA",
    "wof:placetype":"postalcode"
},
  "geometry": {"coordinates":[-1.485159,51.00849],"type":"Point"}
}