{
  "type": "Feature",
  "properties": {
    "iso:country": "GB",
    "wof:name": "SO51 7AA",
    "wof:placetype": "postalcode"
  },
  "geometry": {"coordinates":[-1.485159,51.00849],"type":"Point"}
}
