{
  "type": "Feature",
  "properties": {
    "iso:country": "GB",
    "wof:name": "EN1 2PD",
    "wof:placetype": "postalcode"
  },
  "geometry": {"coordinates":[-0.075375,51.646024],"type":"Point"}
}
