{
  "type": "Feature",
  "properties": {
    "iso:country": "GB",
    "wof:name": "CF44 0EQ",
    "wof:placetype": "postalcode"
  },
  "geometry": {"coordinates":[-3.424443,51.705605],"type":"Point"}
}
