{
  "type": "Feature",
  "properties": {
    "iso:country":"GB",
    "wof:name":"CF44 0EQ",
    "wof:placetype":"postalcode"
},
  "geometry": {"coordinates":[-3.42455305138153,51.70578709020749],"type":"Point"}
}