{
  "type": "Feature",
  "properties": {
    "date:inception_lower": "1980-01-01",
    "date:inception_upper": "1980-01-01",
    "iso:country": "GB",
    "wof:name": "HR8 1RS",
    "wof:placetype": "postalcode"
  },
  "geometry": {"coordinates":[-2.369984,52.006139],"type":"Point"}
}
