{
  "type": "Feature",
  "properties": {
    "iso:country":"GB",
    "wof:name":"HR8 1RS",
    "wof:placetype":"postalcode"
},
  "geometry": {"coordinates":[-2.36998400893646,52.00613895085615],"type":"Point"}
}