{
  "type": "Feature",
  "properties": {
    "iso:country": "GB",
    "wof:name": "WF3 1DH",
    "wof:placetype": "postalcode"
  },
  "geometry": {"coordinates":[-1.583458,53.720469],"type":"Point"}
}
