{
  "type": "Feature",
  "properties": {
    "iso:country":"GB",
    "wof:name":"PR1 4HR",
    "wof:placetype":"postalcode"
},
  "geometry": {"coordinates":[-2.68927171580103,53.75758791029745],"type":"Point"}
}