{
  "type": "Feature",
  "properties": {
    "iso:country":"GB",
    "wof:name":"LL11 5HR",
    "wof:placetype":"postalcode"
},
  "geometry": {"coordinates":[-3.08952210409401,53.10403962139669],"type":"Point"}
}