{
  "type": "Feature",
  "properties": {
    "iso:country":"GB",
    "wof:name":"DA14 6LY",
    "wof:placetype":"postalcode"
},
  "geometry": {"coordinates":[0.11016931768811,51.41422119470991],"type":"Point"}
}