{
  "type": "Feature",
  "properties": {
    "iso:country": "GB",
    "wof:name": "DA14 6LY",
    "wof:placetype": "postalcode"
  },
  "geometry": {"coordinates":[0.110169,51.414221],"type":"Point"}
}
