{
  "type": "Feature",
  "properties": {
    "iso:country":"GB",
    "wof:name":"PA7 5JQ",
    "wof:placetype":"postalcode"
},
  "geometry": {"coordinates":[-4.50444244209833,55.90704457444763],"type":"Point"}
}