{
  "type": "Feature",
  "properties": {
    "date:inception_lower":"1999-12-01",
    "date:inception_upper":"1999-12-31",
    "iso:country":"GB",
    "wof:name":"PA7 5JQ",
    "wof:placetype":"postalcode"
},
  "geometry": {"coordinates":[-4.504442,55.907045],"type":"Point"}
}