{
  "type": "Feature",
  "properties": {
    "iso:country":"GB",
    "wof:name":"CH47 2BZ",
    "wof:placetype":"postalcode"
},
  "geometry": {"coordinates":[-3.17966023162372,53.39627715997575],"type":"Point"}
}