{
  "type": "Feature",
  "properties": {
    "date:inception_lower": "1980-01-01",
    "date:inception_upper": "1980-01-01",
    "iso:country": "GB",
    "wof:name": "DA6 7NL",
    "wof:placetype": "postalcode"
  },
  "geometry": {"coordinates":[0.145095,51.452149],"type":"Point"}
}
