{
  "type": "Feature",
  "properties": {
    "iso:country":"GB",
    "wof:name":"DA6 7NL",
    "wof:placetype":"postalcode"
},
  "geometry": {"coordinates":[0.14509446945934,51.45214889210703],"type":"Point"}
}