{
  "type": "Feature",
  "properties": {
    "iso:country": "GB",
    "wof:name": "NN3 9BG",
    "wof:placetype": "postalcode"
  },
  "geometry": {"coordinates":[-0.826482,52.256104],"type":"Point"}
}
