{
  "type": "Feature",
  "properties": {
    "iso:country":"GB",
    "wof:name":"NN3 9BG",
    "wof:placetype":"postalcode"
},
  "geometry": {"coordinates":[-0.82648199879932,52.25610425779247],"type":"Point"}
}