{
  "type": "Feature",
  "properties": {
    "date:inception_lower": "1980-01-01",
    "date:inception_upper": "1980-01-01",
    "iso:country": "GB",
    "wof:name": "HR2 8NX",
    "wof:placetype": "postalcode"
  },
  "geometry": {"coordinates":[-2.734843,51.926764],"type":"Point"}
}
