{
  "type": "Feature",
  "properties": {
    "iso:country":"GB",
    "wof:name":"HR2 8NX",
    "wof:placetype":"postalcode"
},
  "geometry": {"coordinates":[-2.73484288005057,51.92676356608245],"type":"Point"}
}