{
  "type": "Feature",
  "properties": {
    "iso:country":"GB",
    "wof:name":"DY14 9LA",
    "wof:placetype":"postalcode"
},
  "geometry": {"coordinates":[-2.47859525638978,52.33894469497481],"type":"Point"}
}