{
  "type": "Feature",
  "properties": {
    "iso:country": "GB",
    "wof:name": "DY14 9LA",
    "wof:placetype": "postalcode"
  },
  "geometry": {"coordinates":[-2.478595,52.338945],"type":"Point"}
}
