{
  "type": "Feature",
  "properties": {
    "date:inception_lower": "1980-01-01",
    "date:inception_upper": "1980-01-01",
    "iso:country": "GB",
    "wof:name": "DY14 9LA",
    "wof:placetype": "postalcode"
  },
  "geometry": {"coordinates":[-2.478595,52.338945],"type":"Point"}
}
