{
  "type": "Feature",
  "properties": {
    "iso:country": "GB",
    "wof:name": "EX38 7HH",
    "wof:placetype": "postalcode"
  },
  "geometry": {"coordinates":[-4.129585,50.985979],"type":"Point"}
}
