{
  "type": "Feature",
  "properties": {
    "iso:country":"GB",
    "wof:name":"L8 1TP",
    "wof:placetype":"postalcode"
},
  "geometry": {"coordinates":[-2.96277404522586,53.39335151379759],"type":"Point"}
}