{
  "type": "Feature",
  "properties": {
    "iso:country":"GB",
    "wof:name":"CB9 7HE",
    "wof:placetype":"postalcode"
},
  "geometry": {"coordinates":[0.45156130677595,52.10613257363404],"type":"Point"}
}