{
  "type": "Feature",
  "properties": {
    "iso:country":"GB",
    "wof:name":"E15 3BD",
    "wof:placetype":"postalcode"
},
  "geometry": {"coordinates":[0.00520319389463,51.53216052470926],"type":"Point"}
}