{
  "type": "Feature",
  "properties": {
    "iso:country":"GB",
    "wof:name":"HU7 4UZ",
    "wof:placetype":"postalcode"
},
  "geometry": {"coordinates":[-0.30248107625016,53.7767687887658],"type":"Point"}
}