{
  "type": "Feature",
  "properties": {
    "iso:country":"GB",
    "wof:name":"BS16 9ER",
    "wof:placetype":"postalcode"
},
  "geometry": {"coordinates":[-2.48238274222093,51.48468535403273],"type":"Point"}
}