{
  "type": "Feature",
  "properties": {
    "iso:country": "GB",
    "wof:name": "TQ4 5XY",
    "wof:placetype": "postalcode"
  },
  "geometry": {"coordinates":[-3.580532,50.429595],"type":"Point"}
}
