{
  "type": "Feature",
  "properties": {
    "date:inception_lower":"2013-09-01",
    "date:inception_upper":"2013-09-30",
    "iso:country":"GB",
    "wof:name":"TQ4 5XY",
    "wof:placetype":"postalcode"
},
  "geometry": {"coordinates":[-3.580532,50.429595],"type":"Point"}
}