{
  "type": "Feature",
  "properties": {
    "iso:country": "GB",
    "wof:name": "PL14 5FL",
    "wof:placetype": "postalcode"
  },
  "geometry": {"coordinates":[-4.469857,50.488887],"type":"Point"}
}
