{
  "type": "Feature",
  "properties": {
    "iso:country":"GB",
    "wof:name":"KT12 3SL",
    "wof:placetype":"postalcode"
},
  "geometry": {"coordinates":[-0.39531831464382,51.3772345691953],"type":"Point"}
}