{
  "type": "Feature",
  "properties": {
    "iso:country": "GB",
    "wof:name": "KT12 3SL",
    "wof:placetype": "postalcode"
  },
  "geometry": {"coordinates":[-0.395318,51.377235],"type":"Point"}
}
