{
  "type": "Feature",
  "properties": {
    "iso:country":"GB",
    "wof:name":"TS5 6LE",
    "wof:placetype":"postalcode"
},
  "geometry": {"coordinates":[-1.23750106998288,54.56257681346226],"type":"Point"}
}