{
  "type": "Feature",
  "properties": {
    "iso:country":"GB",
    "wof:name":"NN29 7NY",
    "wof:placetype":"postalcode"
},
  "geometry": {"coordinates":[-0.67563740751015,52.22316634580209],"type":"Point"}
}