{
  "type": "Feature",
  "properties": {
    "iso:country": "GB",
    "wof:name": "DH5 8JS",
    "wof:placetype": "postalcode"
  },
  "geometry": {"coordinates":[-1.47009,54.834229],"type":"Point"}
}
