{
  "type": "Feature",
  "properties": {
    "iso:country":"GB",
    "wof:name":"M40 3GP",
    "wof:placetype":"postalcode"
},
  "geometry": {"coordinates":[-2.16144480564655,53.51548600009407],"type":"Point"}
}