{
  "type": "Feature",
  "properties": {
    "iso:country":"GB",
    "wof:name":"BS21 7TB",
    "wof:placetype":"postalcode"
},
  "geometry": {"coordinates":[-2.85907334025259,51.43735561963619],"type":"Point"}
}