{
  "type": "Feature",
  "properties": {
    "date:inception_lower":"2007-07-01",
    "date:inception_upper":"2007-07-31",
    "iso:country":"GB",
    "wof:name":"DD10 9FJ",
    "wof:placetype":"postalcode"
},
  "geometry": {"coordinates":[-2.478213,56.724084],"type":"Point"}
}