{
  "type": "Feature",
  "properties": {
    "iso:country":"GB",
    "wof:name":"DD10 9FJ",
    "wof:placetype":"postalcode"
},
  "geometry": {"coordinates":[-2.47821260476544,56.72408402808676],"type":"Point"}
}