{
  "type": "Feature",
  "properties": {
    "iso:country":"GB",
    "wof:name":"DN3 2DW",
    "wof:placetype":"postalcode"
},
  "geometry": {"coordinates":[-1.056656502329,53.54197895562807],"type":"Point"}
}