{
  "type": "Feature",
  "properties": {
    "iso:country":"GB",
    "wof:name":"NE63 8QQ",
    "wof:placetype":"postalcode"
},
  "geometry": {"coordinates":[-1.58505784065777,55.18472538978263],"type":"Point"}
}