{
  "type": "Feature",
  "properties": {
    "date:inception_lower": "1980-01-01",
    "date:inception_upper": "1980-01-01",
    "iso:country": "GB",
    "wof:name": "TS6 7LD",
    "wof:placetype": "postalcode"
  },
  "geometry": {"coordinates":[-1.148807,54.57384],"type":"Point"}
}
