{
  "type": "Feature",
  "properties": {
    "iso:country": "GB",
    "wof:name": "PA22 3AP",
    "wof:placetype": "postalcode"
  },
  "geometry": {"coordinates":[-5.15252,55.923782],"type":"Point"}
}
