{
  "type": "Feature",
  "properties": {
    "iso:country":"GB",
    "wof:name":"PA22 3AP",
    "wof:placetype":"postalcode"
},
  "geometry": {"coordinates":[-5.15252023822776,55.92378210680482],"type":"Point"}
}