{
  "type": "Feature",
  "properties": {
    "iso:country": "GB",
    "wof:name": "CT1 1RT",
    "wof:placetype": "postalcode"
  },
  "geometry": {"coordinates":[1.10265,51.274394],"type":"Point"}
}
