{
  "type": "Feature",
  "properties": {
    "iso:country":"GB",
    "wof:name":"CT1 1RT",
    "wof:placetype":"postalcode"
},
  "geometry": {"coordinates":[1.10273737653738,51.27442264256797],"type":"Point"}
}