{
  "type": "Feature",
  "properties": {
    "iso:country": "GB",
    "wof:name": "DD3 6HW",
    "wof:placetype": "postalcode"
  },
  "geometry": {"coordinates":[-2.986922,56.467528],"type":"Point"}
}
