{
  "type": "Feature",
  "properties": {
    "iso:country":"GB",
    "wof:name":"DD3 6HW",
    "wof:placetype":"postalcode"
},
  "geometry": {"coordinates":[-2.98692202627502,56.46752826261578],"type":"Point"}
}