{
  "type": "Feature",
  "properties": {
    "iso:country": "GB",
    "wof:name": "EH1 2JP",
    "wof:placetype": "postalcode"
  },
  "geometry": {"coordinates":[-3.194746,55.94824],"type":"Point"}
}
