{
  "type": "Feature",
  "properties": {
    "iso:country":"GB",
    "wof:name":"CT5 4DA",
    "wof:placetype":"postalcode"
},
  "geometry": {"coordinates":[1.01487071933712,51.34960221917847],"type":"Point"}
}