{
  "type": "Feature",
  "properties": {
    "date:inception_lower": "1980-01-01",
    "date:inception_upper": "1980-01-01",
    "iso:country": "GB",
    "wof:name": "CT5 4DA",
    "wof:placetype": "postalcode"
  },
  "geometry": {"coordinates":[1.014871,51.349602],"type":"Point"}
}
