{
  "type": "Feature",
  "properties": {
    "iso:country":"GB",
    "wof:name":"NR17 1GA",
    "wof:placetype":"postalcode"
},
  "geometry": {"coordinates":[0.99962983590713,52.51300231573264],"type":"Point"}
}