{
  "type": "Feature",
  "properties": {
    "date:inception_lower":"2008-03-01",
    "date:inception_upper":"2008-03-31",
    "iso:country":"GB",
    "wof:name":"NR17 1GA",
    "wof:placetype":"postalcode"
},
  "geometry": {"coordinates":[0.99963,52.513002],"type":"Point"}
}