{
  "type": "Feature",
  "properties": {
    "iso:country": "GB",
    "wof:name": "NR17 1GA",
    "wof:placetype": "postalcode"
  },
  "geometry": {"coordinates":[0.99963,52.513002],"type":"Point"}
}
