{
  "type": "Feature",
  "properties": {
    "iso:country": "GB",
    "wof:name": "TW19 7BQ",
    "wof:placetype": "postalcode"
  },
  "geometry": {"coordinates":[-0.463892,51.451297],"type":"Point"}
}
