{
  "type": "Feature",
  "properties": {
    "date:inception_lower": "1980-01-01",
    "date:inception_upper": "1980-01-01",
    "iso:country": "GB",
    "wof:name": "TW19 7BQ",
    "wof:placetype": "postalcode"
  },
  "geometry": {"coordinates":[-0.463822,51.451467],"type":"Point"}
}
