{
  "type": "Feature",
  "properties": {
    "date:inception_lower": "1980-01-01",
    "date:inception_upper": "1980-01-01",
    "iso:country": "GB",
    "wof:name": "BR6 9QT",
    "wof:placetype": "postalcode"
  },
  "geometry": {"coordinates":[0.090463,51.368099],"type":"Point"}
}
