{
  "type": "Feature",
  "properties": {
    "iso:country":"GB",
    "wof:name":"BR6 9QT",
    "wof:placetype":"postalcode"
},
  "geometry": {"coordinates":[0.09046305443986,51.36809883285796],"type":"Point"}
}