{
  "type": "Feature",
  "properties": {
    "date:inception_lower": "1994-05-01",
    "date:inception_upper": "1994-05-01",
    "iso:country": "GB",
    "wof:name": "M33 6JA",
    "wof:placetype": "postalcode"
  },
  "geometry": {"coordinates":[-2.330726,53.430448],"type":"Point"}
}
