{
  "type": "Feature",
  "properties": {
    "date:inception_lower": "2019-04-01",
    "date:inception_upper": "2019-04-01",
    "iso:country": "GB",
    "wof:name": "TF11 8GS",
    "wof:placetype": "postalcode"
  },
  "geometry": {"coordinates":[-2.361545,52.666008],"type":"Point"}
}
