{
  "type": "Feature",
  "properties": {
    "iso:country":"GB",
    "wof:name":"BN3 2EB",
    "wof:placetype":"postalcode"
},
  "geometry": {"coordinates":[-0.17153702251619,50.82764650579403],"type":"Point"}
}