{
  "type": "Feature",
  "properties": {
    "date:inception_lower": "1980-01-01",
    "date:inception_upper": "1980-01-01",
    "iso:country": "GB",
    "wof:name": "SE10 8AG",
    "wof:placetype": "postalcode"
  },
  "geometry": {"coordinates":[-0.010222,51.472334],"type":"Point"}
}
