{
  "type": "Feature",
  "properties": {
    "iso:country": "GB",
    "wof:name": "SE10 8AG",
    "wof:placetype": "postalcode"
  },
  "geometry": {"coordinates":[-0.010222,51.472334],"type":"Point"}
}
