{
  "type": "Feature",
  "properties": {
    "iso:country":"GB",
    "wof:name":"SE10 8AG",
    "wof:placetype":"postalcode"
},
  "geometry": {"coordinates":[-0.01022243300257,51.47233414797802],"type":"Point"}
}