{
  "type": "Feature",
  "properties": {
    "iso:country":"GB",
    "wof:name":"SY4 4ED",
    "wof:placetype":"postalcode"
},
  "geometry": {"coordinates":[-2.68107660104821,52.76311537594935],"type":"Point"}
}