{
  "type": "Feature",
  "properties": {
    "iso:country": "GB",
    "wof:name": "LA22 0DY",
    "wof:placetype": "postalcode"
  },
  "geometry": {"coordinates":[-2.965141,54.427178],"type":"Point"}
}
