{
  "type": "Feature",
  "properties": {
    "iso:country":"GB",
    "wof:name":"LA22 0DY",
    "wof:placetype":"postalcode"
},
  "geometry": {"coordinates":[-2.96514158643892,54.42730518620134],"type":"Point"}
}