{
  "type": "Feature",
  "properties": {
    "iso:country":"GB",
    "wof:name":"G72 9XE",
    "wof:placetype":"postalcode"
},
  "geometry": {"coordinates":[-4.10420905738705,55.78919336475422],"type":"Point"}
}