{
  "type": "Feature",
  "properties": {
    "iso:country":"GB",
    "wof:name":"DD5 1DA",
    "wof:placetype":"postalcode"
},
  "geometry": {"coordinates":[-2.8874138904035,56.4711186260306],"type":"Point"}
}