{
  "type": "Feature",
  "properties": {
    "date:inception_lower": "1986-03-01",
    "date:inception_upper": "1986-03-01",
    "iso:country": "GB",
    "wof:name": "DD5 1DA",
    "wof:placetype": "postalcode"
  },
  "geometry": {"coordinates":[-2.887414,56.471119],"type":"Point"}
}
