{
  "type": "Feature",
  "properties": {
    "iso:country":"GB",
    "wof:name":"KA11 1RS",
    "wof:placetype":"postalcode"
},
  "geometry": {"coordinates":[-4.62988502031768,55.62887666729328],"type":"Point"}
}