{
  "type": "Feature",
  "properties": {
    "iso:country":"GB",
    "wof:name":"WV6 9DF",
    "wof:placetype":"postalcode"
},
  "geometry": {"coordinates":[-2.16626816820604,52.6133175907764],"type":"Point"}
}