{
  "type": "Feature",
  "properties": {
    "date:inception_lower": "2000-10-01",
    "date:inception_upper": "2000-10-01",
    "iso:country": "GB",
    "wof:name": "W1H 1NN",
    "wof:placetype": "postalcode"
  },
  "geometry": {"coordinates":[-0.163275,51.519929],"type":"Point"}
}
