{
  "type": "Feature",
  "properties": {
    "date:inception_lower":"1980-01-01",
    "date:inception_upper":"1980-01-31",
    "iso:country":"GB",
    "wof:name":"RH18 5AJ",
    "wof:placetype":"postalcode"
},
  "geometry": {"coordinates":[0.034721,51.095723],"type":"Point"}
}