{
  "type": "Feature",
  "properties": {
    "iso:country": "GB",
    "wof:name": "RH18 5AJ",
    "wof:placetype": "postalcode"
  },
  "geometry": {"coordinates":[0.034721,51.095723],"type":"Point"}
}
