{
  "type": "Feature",
  "properties": {
    "iso:country": "GB",
    "wof:name": "EX31 1JL",
    "wof:placetype": "postalcode"
  },
  "geometry": {"coordinates":[-4.063109,51.083096],"type":"Point"}
}
