{
  "type": "Feature",
  "properties": {
    "iso:country":"GB",
    "wof:name":"EX31 1JL",
    "wof:placetype":"postalcode"
},
  "geometry": {"coordinates":[-4.06310894886349,51.08309619910263],"type":"Point"}
}