{
  "type": "Feature",
  "properties": {
    "date:inception_lower": "1998-06-01",
    "date:inception_upper": "1998-06-01",
    "iso:country": "GB",
    "wof:name": "GU21 2QL",
    "wof:placetype": "postalcode"
  },
  "geometry": {"coordinates":[-0.61462,51.312716],"type":"Point"}
}
