{
  "type": "Feature",
  "properties": {
    "iso:country":"GB",
    "wof:name":"G3 8PR",
    "wof:placetype":"postalcode"
},
  "geometry": {"coordinates":[-4.29439466447356,55.86403562035925],"type":"Point"}
}