{
  "type": "Feature",
  "properties": {
    "iso:country":"GB",
    "wof:name":"NN2 7AD",
    "wof:placetype":"postalcode"
},
  "geometry": {"coordinates":[-0.89356622454243,52.26908714377882],"type":"Point"}
}