{
  "type": "Feature",
  "properties": {
    "iso:country":"GB",
    "wof:name":"YO24 1BY",
    "wof:placetype":"postalcode"
},
  "geometry": {"coordinates":[-1.10139217904168,53.95037713786811],"type":"Point"}
}