{
  "type": "Feature",
  "properties": {
    "iso:country":"GB",
    "wof:name":"HU8 0PF",
    "wof:placetype":"postalcode"
},
  "geometry": {"coordinates":[-0.29893461313127,53.77890289197273],"type":"Point"}
}