{
  "type": "Feature",
  "properties": {
    "date:inception_lower": "1980-01-01",
    "date:inception_upper": "1980-01-01",
    "iso:country": "GB",
    "wof:name": "EN11 0RJ",
    "wof:placetype": "postalcode"
  },
  "geometry": {"coordinates":[-0.007861,51.768526],"type":"Point"}
}
