{
  "type": "Feature",
  "properties": {
    "iso:country":"GB",
    "wof:name":"EN11 0RJ",
    "wof:placetype":"postalcode"
},
  "geometry": {"coordinates":[-0.00786109001505,51.76852559439418],"type":"Point"}
}