{
  "type": "Feature",
  "properties": {
    "date:inception_lower": "1995-12-01",
    "date:inception_upper": "1995-12-01",
    "iso:country": "GB",
    "wof:name": "GL4 5WJ",
    "wof:placetype": "postalcode"
  },
  "geometry": {"coordinates":[-2.19129,51.845243],"type":"Point"}
}
