{
  "type": "Feature",
  "properties": {
    "iso:country": "GB",
    "wof:name": "GL4 5WJ",
    "wof:placetype": "postalcode"
  },
  "geometry": {"coordinates":[-2.19129,51.845243],"type":"Point"}
}
