{
  "type": "Feature",
  "properties": {
    "iso:country":"GB",
    "wof:name":"HP22 4LX",
    "wof:placetype":"postalcode"
},
  "geometry": {"coordinates":[-0.77021916412313,51.87223214661194],"type":"Point"}
}