{
  "type": "Feature",
  "properties": {
    "date:inception_lower":"1980-01-01",
    "date:inception_upper":"1980-01-31",
    "iso:country":"GB",
    "wof:name":"SL9 8SA",
    "wof:placetype":"postalcode"
},
  "geometry": {"coordinates":[-0.563061,51.59801],"type":"Point"}
}