{
  "type": "Feature",
  "properties": {
    "iso:country":"GB",
    "wof:name":"W1H 1EW",
    "wof:placetype":"postalcode"
},
  "geometry": {"coordinates":[-0.15989270837662,51.52015482334803],"type":"Point"}
}