{
  "type": "Feature",
  "properties": {
    "iso:country":"GB",
    "wof:name":"NN7 4PP",
    "wof:placetype":"postalcode"
},
  "geometry": {"coordinates":[-1.08778182128602,52.23280662591794],"type":"Point"}
}