{
  "type": "Feature",
  "properties": {
    "iso:country":"GB",
    "wof:name":"G81 2DN",
    "wof:placetype":"postalcode"
},
  "geometry": {"coordinates":[-4.40355655984185,55.91191412967066],"type":"Point"}
}