{
  "type": "Feature",
  "properties": {
    "date:inception_lower":"2014-01-01",
    "date:inception_upper":"2014-01-31",
    "iso:country":"GB",
    "wof:name":"G81 2DN",
    "wof:placetype":"postalcode"
},
  "geometry": {"coordinates":[-4.403557,55.911914],"type":"Point"}
}