{
  "type": "Feature",
  "properties": {
    "iso:country": "GB",
    "wof:name": "G81 2DN",
    "wof:placetype": "postalcode"
  },
  "geometry": {"coordinates":[-4.403557,55.911914],"type":"Point"}
}
