{
  "type": "Feature",
  "properties": {
    "date:inception_lower": "2018-04-01",
    "date:inception_upper": "2018-04-01",
    "iso:country": "GB",
    "wof:name": "PR6 9FU",
    "wof:placetype": "postalcode"
  },
  "geometry": {"coordinates":[-2.596594,53.612868],"type":"Point"}
}
