{
  "type": "Feature",
  "properties": {
    "iso:country": "GB",
    "wof:name": "SS5 5BG",
    "wof:placetype": "postalcode"
  },
  "geometry": {"coordinates":[0.661682,51.609384],"type":"Point"}
}
