{
  "type": "Feature",
  "properties": {
    "iso:country":"GB",
    "wof:name":"SS5 5BG",
    "wof:placetype":"postalcode"
},
  "geometry": {"coordinates":[0.66168185078358,51.60938448799534],"type":"Point"}
}