{
  "type": "Feature",
  "properties": {
    "iso:country":"GB",
    "wof:name":"WV4 5QB",
    "wof:placetype":"postalcode"
},
  "geometry": {"coordinates":[-2.15133754072538,52.55788852380019],"type":"Point"}
}