{
  "type": "Feature",
  "properties": {
    "iso:country": "GB",
    "wof:name": "RH10 7JT",
    "wof:placetype": "postalcode"
  },
  "geometry": {"coordinates":[-0.153419,51.103472],"type":"Point"}
}
