{
  "type": "Feature",
  "properties": {
    "iso:country":"GB",
    "wof:name":"RH10 7JT",
    "wof:placetype":"postalcode"
},
  "geometry": {"coordinates":[-0.15341877302248,51.10347195904014],"type":"Point"}
}