{
  "type": "Feature",
  "properties": {
    "iso:country":"GB",
    "wof:name":"LA3 3NF",
    "wof:placetype":"postalcode"
},
  "geometry": {"coordinates":[-2.86941525554348,54.0571673710912],"type":"Point"}
}