{
  "type": "Feature",
  "properties": {
    "date:inception_lower": "1993-08-01",
    "date:inception_upper": "1993-08-01",
    "iso:country": "GB",
    "wof:name": "LA3 3NF",
    "wof:placetype": "postalcode"
  },
  "geometry": {"coordinates":[-2.869415,54.057167],"type":"Point"}
}
