{
  "type": "Feature",
  "properties": {
    "iso:country": "GB",
    "wof:name": "EX13 5UL",
    "wof:placetype": "postalcode"
  },
  "geometry": {"coordinates":[-2.930835,50.782652],"type":"Point"}
}
