{
  "type": "Feature",
  "properties": {
    "iso:country":"GB",
    "wof:name":"NP11 5EL",
    "wof:placetype":"postalcode"
},
  "geometry": {"coordinates":[-3.13722586996034,51.68348325753968],"type":"Point"}
}