{
  "type": "Feature",
  "properties": {
    "iso:country":"GB",
    "wof:name":"ST16 3FP",
    "wof:placetype":"postalcode"
},
  "geometry": {"coordinates":[-2.12209406265366,52.8194221207766],"type":"Point"}
}