{
  "type": "Feature",
  "properties": {
    "date:inception_lower": "1998-12-01",
    "date:inception_upper": "1998-12-01",
    "iso:country": "GB",
    "wof:name": "ST16 3FP",
    "wof:placetype": "postalcode"
  },
  "geometry": {"coordinates":[-2.122094,52.819422],"type":"Point"}
}
