{
  "type": "Feature",
  "properties": {
    "iso:country":"GB",
    "wof:name":"PH1 4HJ",
    "wof:placetype":"postalcode"
},
  "geometry": {"coordinates":[-3.4711378572767,56.53467739196879],"type":"Point"}
}