{
  "type": "Feature",
  "properties": {
    "date:inception_lower": "1980-01-01",
    "date:inception_upper": "1980-01-01",
    "iso:country": "GB",
    "wof:name": "PH1 4HJ",
    "wof:placetype": "postalcode"
  },
  "geometry": {"coordinates":[-3.471136,56.534668],"type":"Point"}
}
