{
  "type": "Feature",
  "properties": {
    "iso:country":"GB",
    "wof:name":"SO42 7WA",
    "wof:placetype":"postalcode"
},
  "geometry": {"coordinates":[-1.4696497312537,50.81449811124597],"type":"Point"}
}