{
  "type": "Feature",
  "properties": {
    "date:inception_lower": "1986-01-01",
    "date:inception_upper": "1986-01-01",
    "iso:country": "GB",
    "wof:name": "SO42 7WA",
    "wof:placetype": "postalcode"
  },
  "geometry": {"coordinates":[-1.469068,50.814433],"type":"Point"}
}
