{
  "type": "Feature",
  "properties": {
    "date:inception_lower": "2019-09-01",
    "date:inception_upper": "2019-09-01",
    "iso:country": "GB",
    "wof:name": "SA1 1LA",
    "wof:placetype": "postalcode"
  },
  "geometry": {"coordinates":[-3.942347,51.624201],"type":"Point"}
}
