{
  "type": "Feature",
  "properties": {
    "iso:country": "GB",
    "wof:name": "CT1 3JL",
    "wof:placetype": "postalcode"
  },
  "geometry": {"coordinates":[1.080748,51.27047],"type":"Point"}
}
