{
  "type": "Feature",
  "properties": {
    "date:inception_lower": "1984-02-01",
    "date:inception_upper": "1984-02-01",
    "iso:country": "GB",
    "wof:name": "CT1 3JL",
    "wof:placetype": "postalcode"
  },
  "geometry": {"coordinates":[1.080748,51.27047],"type":"Point"}
}
