{
  "type": "Feature",
  "properties": {
    "iso:country":"GB",
    "wof:name":"PE30 3XG",
    "wof:placetype":"postalcode"
},
  "geometry": {"coordinates":[0.43543130373204,52.78956914034268],"type":"Point"}
}