{
  "type": "Feature",
  "properties": {
    "date:inception_lower":"1995-01-01",
    "date:inception_upper":"1995-01-31",
    "iso:country":"GB",
    "wof:name":"PE30 3XG",
    "wof:placetype":"postalcode"
},
  "geometry": {"coordinates":[0.435431,52.789569],"type":"Point"}
}