{
  "type": "Feature",
  "properties": {
    "iso:country":"GB",
    "wof:name":"L15 5BT",
    "wof:placetype":"postalcode"
},
  "geometry": {"coordinates":[-2.92038568414242,53.39073753032856],"type":"Point"}
}