{
  "type": "Feature",
  "properties": {
    "date:inception_lower": "2003-10-01",
    "date:inception_upper": "2003-10-01",
    "iso:country": "GB",
    "wof:name": "CT5 4UB",
    "wof:placetype": "postalcode"
  },
  "geometry": {"coordinates":[1.008171,51.342714],"type":"Point"}
}
