{
  "type": "Feature",
  "properties": {
    "iso:country":"GB",
    "wof:name":"CT5 4UB",
    "wof:placetype":"postalcode"
},
  "geometry": {"coordinates":[1.00817130342289,51.34271395061861],"type":"Point"}
}