{
  "type": "Feature",
  "properties": {
    "iso:country": "GB",
    "wof:name": "DD2 5HB",
    "wof:placetype": "postalcode"
  },
  "geometry": {"coordinates":[-3.124377,56.457464],"type":"Point"}
}
