{
  "type": "Feature",
  "properties": {
    "iso:country": "GB",
    "wof:name": "SY22 6NS",
    "wof:placetype": "postalcode"
  },
  "geometry": {"coordinates":[-3.075085,52.759191],"type":"Point"}
}
