{
  "type": "Feature",
  "properties": {
    "iso:country":"GB",
    "wof:name":"SY22 6NS",
    "wof:placetype":"postalcode"
},
  "geometry": {"coordinates":[-3.07508493555871,52.75919118753543],"type":"Point"}
}