{
  "type": "Feature",
  "properties": {
    "iso:country":"GB",
    "wof:name":"TS8 9DH",
    "wof:placetype":"postalcode"
},
  "geometry": {"coordinates":[-1.21854085776251,54.53750770909951],"type":"Point"}
}