{
  "type": "Feature",
  "properties": {
    "iso:country": "GB",
    "wof:name": "TS8 9DH",
    "wof:placetype": "postalcode"
  },
  "geometry": {"coordinates":[-1.218541,54.537508],"type":"Point"}
}
