{
  "type": "Feature",
  "properties": {
    "iso:country":"GB",
    "wof:name":"BS36 2JZ",
    "wof:placetype":"postalcode"
},
  "geometry": {"coordinates":[-2.47150325894202,51.5342908654811],"type":"Point"}
}