{
  "type": "Feature",
  "properties": {
    "iso:country": "GB",
    "wof:name": "BS36 2JZ",
    "wof:placetype": "postalcode"
  },
  "geometry": {"coordinates":[-2.471503,51.534291],"type":"Point"}
}
