{
  "type": "Feature",
  "properties": {
    "iso:country": "GB",
    "wof:name": "CB2 9GG",
    "wof:placetype": "postalcode"
  },
  "geometry": {"coordinates":[0.10273,52.167943],"type":"Point"}
}
