{
  "type": "Feature",
  "properties": {
    "iso:country":"GB",
    "wof:name":"AB10 7LQ",
    "wof:placetype":"postalcode"
},
  "geometry": {"coordinates":[-2.12867418120164,57.12847610495231],"type":"Point"}
}