{
  "type": "Feature",
  "properties": {
    "date:inception_lower":"1996-06-01",
    "date:inception_upper":"1996-06-30",
    "iso:country":"GB",
    "wof:name":"AB10 7LQ",
    "wof:placetype":"postalcode"
},
  "geometry": {"coordinates":[-2.128674,57.128476],"type":"Point"}
}