{
  "type": "Feature",
  "properties": {
    "iso:country":"GB",
    "wof:name":"DT2 8EJ",
    "wof:placetype":"postalcode"
},
  "geometry": {"coordinates":[-2.38561129305876,50.67713455809481],"type":"Point"}
}