{
  "type": "Feature",
  "properties": {
    "iso:country": "GB",
    "wof:name": "WN1 3RD",
    "wof:placetype": "postalcode"
  },
  "geometry": {"coordinates":[-2.618741,53.54468],"type":"Point"}
}
