{
  "type": "Feature",
  "properties": {
    "iso:country":"GB",
    "wof:name":"WN1 3RD",
    "wof:placetype":"postalcode"
},
  "geometry": {"coordinates":[-2.6187409972287,53.5446797378854],"type":"Point"}
}