{
  "type": "Feature",
  "properties": {
    "iso:country": "GB",
    "wof:name": "NE5 1NQ",
    "wof:placetype": "postalcode"
  },
  "geometry": {"coordinates":[-1.723142,55.015352],"type":"Point"}
}
