{
  "type": "Feature",
  "properties": {
    "iso:country":"GB",
    "wof:name":"NE5 1NQ",
    "wof:placetype":"postalcode"
},
  "geometry": {"coordinates":[-1.7231421376663,55.01535241174209],"type":"Point"}
}