{
  "type": "Feature",
  "properties": {
    "iso:country": "GB",
    "wof:name": "DE3 9DB",
    "wof:placetype": "postalcode"
  },
  "geometry": {"coordinates":[-1.542849,52.918955],"type":"Point"}
}
