{
  "type": "Feature",
  "properties": {
    "iso:country":"GB",
    "wof:name":"SE17 2HJ",
    "wof:placetype":"postalcode"
},
  "geometry": {"coordinates":[-0.09207969782375,51.48620349840676],"type":"Point"}
}