{
  "type": "Feature",
  "properties": {
    "date:inception_lower":"1980-01-01",
    "date:inception_upper":"1980-01-31",
    "iso:country":"GB",
    "wof:name":"WS15 1AR",
    "wof:placetype":"postalcode"
},
  "geometry": {"coordinates":[-1.930878,52.748268],"type":"Point"}
}