{
  "type": "Feature",
  "properties": {
    "iso:country": "GB",
    "wof:name": "WS15 1AR",
    "wof:placetype": "postalcode"
  },
  "geometry": {"coordinates":[-1.930878,52.748268],"type":"Point"}
}
