{
  "type": "Feature",
  "properties": {
    "date:inception_lower":"2001-12-01",
    "date:inception_upper":"2001-12-31",
    "iso:country":"GB",
    "wof:name":"L35 0LX",
    "wof:placetype":"postalcode"
},
  "geometry": {"coordinates":[-2.769479,53.412633],"type":"Point"}
}