{
  "type": "Feature",
  "properties": {
    "iso:country":"GB",
    "wof:name":"L35 0LX",
    "wof:placetype":"postalcode"
},
  "geometry": {"coordinates":[-2.76947888417398,53.41263281755526],"type":"Point"}
}