{
  "type": "Feature",
  "properties": {
    "date:inception_lower": "1998-12-01",
    "date:inception_upper": "1998-12-01",
    "iso:country": "GB",
    "wof:name": "EX24 6RU",
    "wof:placetype": "postalcode"
  },
  "geometry": {"coordinates":[-3.09833,50.74104],"type":"Point"}
}
