{
  "type": "Feature",
  "properties": {
    "date:inception_lower": "2021-07-01",
    "date:inception_upper": "2021-07-01",
    "iso:country": "GB",
    "wof:name": "NG12 4JD",
    "wof:placetype": "postalcode"
  },
  "geometry": {"coordinates":[-1.126743,52.90665],"type":"Point"}
}
