{
  "type": "Feature",
  "properties": {
    "date:inception_lower": "1980-01-01",
    "date:inception_upper": "1980-01-01",
    "iso:country": "GB",
    "wof:name": "OX11 0JW",
    "wof:placetype": "postalcode"
  },
  "geometry": {"coordinates":[-1.309697,51.600647],"type":"Point"}
}
