{
  "type": "Feature",
  "properties": {
    "iso:country":"GB",
    "wof:name":"TS17 9EA",
    "wof:placetype":"postalcode"
},
  "geometry": {"coordinates":[-1.2888036625037,54.53913633074194],"type":"Point"}
}