{
  "type": "Feature",
  "properties": {
    "iso:country":"GB",
    "wof:name":"LN6 0RE",
    "wof:placetype":"postalcode"
},
  "geometry": {"coordinates":[-0.59607638660396,53.21389607073753],"type":"Point"}
}