{
  "type": "Feature",
  "properties": {
    "date:inception_lower": "1993-08-01",
    "date:inception_upper": "1993-08-01",
    "iso:country": "GB",
    "wof:name": "LN6 0RE",
    "wof:placetype": "postalcode"
  },
  "geometry": {"coordinates":[-0.596075,53.213927],"type":"Point"}
}
