{
  "type": "Feature",
  "properties": {
    "date:inception_lower": "2003-07-01",
    "date:inception_upper": "2003-07-01",
    "iso:country": "GB",
    "wof:name": "TN27 8RH",
    "wof:placetype": "postalcode"
  },
  "geometry": {"coordinates":[0.731315,51.161714],"type":"Point"}
}
