{
  "type": "Feature",
  "properties": {
    "iso:country": "GB",
    "wof:name": "MK10 7GT",
    "wof:placetype": "postalcode"
  },
  "geometry": {"coordinates":[-0.682699,52.048398],"type":"Point"}
}
