{
  "type": "Feature",
  "properties": {
    "date:inception_lower": "2015-11-01",
    "date:inception_upper": "2015-11-01",
    "iso:country": "GB",
    "wof:name": "MK10 7GT",
    "wof:placetype": "postalcode"
  },
  "geometry": {"coordinates":[-0.681259,52.049254],"type":"Point"}
}
