{
  "type": "Feature",
  "properties": {
    "iso:country":"GB",
    "wof:name":"MK10 7GT",
    "wof:placetype":"postalcode"
},
  "geometry": {"coordinates":[-0.68323203063021,52.04785354682294],"type":"Point"}
}