{
  "type": "Feature",
  "properties": {
    "iso:country": "GB",
    "wof:name": "MK10 7GT",
    "wof:placetype": "postalcode"
  },
  "geometry": {"coordinates":[-0.681259,52.049254],"type":"Point"}
}
