{
  "type": "Feature",
  "properties": {
    "iso:country":"GB",
    "wof:name":"IV30 6FB",
    "wof:placetype":"postalcode"
},
  "geometry": {"coordinates":[-3.28958117646428,57.64234030841523],"type":"Point"}
}