{
  "type": "Feature",
  "properties": {
    "iso:country":"GB",
    "wof:name":"IP12 2EZ",
    "wof:placetype":"postalcode"
},
  "geometry": {"coordinates":[1.55249093437398,52.13644212381998],"type":"Point"}
}