{
  "type": "Feature",
  "properties": {
    "iso:country":"GB",
    "wof:name":"EX35 6EH",
    "wof:placetype":"postalcode"
},
  "geometry": {"coordinates":[-3.83038386797292,51.23029420040686],"type":"Point"}
}