{
  "type": "Feature",
  "properties": {
    "iso:country": "GB",
    "wof:name": "EX35 6EH",
    "wof:placetype": "postalcode"
  },
  "geometry": {"coordinates":[-3.830384,51.230294],"type":"Point"}
}
