{
  "type": "Feature",
  "properties": {
    "date:inception_lower": "1980-01-01",
    "date:inception_upper": "1980-01-01",
    "iso:country": "GB",
    "wof:name": "EX35 6EH",
    "wof:placetype": "postalcode"
  },
  "geometry": {"coordinates":[-3.830384,51.230294],"type":"Point"}
}
