{
  "type": "Feature",
  "properties": {
    "iso:country": "GB",
    "wof:name": "BN11 3JE",
    "wof:placetype": "postalcode"
  },
  "geometry": {"coordinates":[-0.383376,50.810476],"type":"Point"}
}
