{
  "type": "Feature",
  "properties": {
    "iso:country":"GB",
    "wof:name":"CM3 1RB",
    "wof:placetype":"postalcode"
},
  "geometry": {"coordinates":[0.45976288636895,51.7917637136381],"type":"Point"}
}