{
  "type": "Feature",
  "properties": {
    "iso:country": "GB",
    "wof:name": "CM3 1RB",
    "wof:placetype": "postalcode"
  },
  "geometry": {"coordinates":[0.459763,51.791764],"type":"Point"}
}
