{
  "type": "Feature",
  "properties": {
    "iso:country":"GB",
    "wof:name":"DG9 7ND",
    "wof:placetype":"postalcode"
},
  "geometry": {"coordinates":[-5.03745974429219,54.90158714661191],"type":"Point"}
}