{
  "type": "Feature",
  "properties": {
    "date:inception_lower": "1980-01-01",
    "date:inception_upper": "1980-01-01",
    "iso:country": "GB",
    "wof:name": "AL3 6RW",
    "wof:placetype": "postalcode"
  },
  "geometry": {"coordinates":[-0.399508,51.781677],"type":"Point"}
}
