{
  "type": "Feature",
  "properties": {
    "iso:country":"GB",
    "wof:name":"AL3 6RW",
    "wof:placetype":"postalcode"
},
  "geometry": {"coordinates":[-0.39950782861105,51.78167723971432],"type":"Point"}
}