{
  "type": "Feature",
  "properties": {
    "iso:country":"GB",
    "wof:name":"GL55 6AS",
    "wof:placetype":"postalcode"
},
  "geometry": {"coordinates":[-1.78297029287912,52.0496495752514],"type":"Point"}
}