{
  "type": "Feature",
  "properties": {
    "date:inception_lower":"1980-01-01",
    "date:inception_upper":"1980-01-31",
    "iso:country":"GB",
    "wof:name":"L32 4SD",
    "wof:placetype":"postalcode"
},
  "geometry": {"coordinates":[-2.899697,53.473563],"type":"Point"}
}