{
  "type": "Feature",
  "properties": {
    "iso:country": "GB",
    "wof:name": "L32 4SD",
    "wof:placetype": "postalcode"
  },
  "geometry": {"coordinates":[-2.899697,53.473563],"type":"Point"}
}
