{
  "type": "Feature",
  "properties": {
    "iso:country":"GB",
    "wof:name":"L32 4SD",
    "wof:placetype":"postalcode"
},
  "geometry": {"coordinates":[-2.8996981623713,53.47354754253189],"type":"Point"}
}