{
  "type": "Feature",
  "properties": {
    "iso:country":"GB",
    "wof:name":"N18 2GZ",
    "wof:placetype":"postalcode"
},
  "geometry": {"coordinates":[-0.06615839473178,51.61702500757743],"type":"Point"}
}