{
  "type": "Feature",
  "properties": {
    "date:inception_lower": "2000-12-01",
    "date:inception_upper": "2000-12-01",
    "iso:country": "GB",
    "wof:name": "ME12 4EE",
    "wof:placetype": "postalcode"
  },
  "geometry": {"coordinates":[0.844143,51.414585],"type":"Point"}
}
