{
  "type": "Feature",
  "properties": {
    "iso:country":"GB",
    "wof:name":"ME12 4EE",
    "wof:placetype":"postalcode"
},
  "geometry": {"coordinates":[0.84414305459989,51.41458458315133],"type":"Point"}
}