{
  "type": "Feature",
  "properties": {
    "iso:country":"GB",
    "wof:name":"DA12 4RS",
    "wof:placetype":"postalcode"
},
  "geometry": {"coordinates":[0.39460858217208,51.41778261367357],"type":"Point"}
}