{
  "type": "Feature",
  "properties": {
    "date:inception_lower": "2021-09-01",
    "date:inception_upper": "2021-09-01",
    "iso:country": "GB",
    "wof:name": "SE1 5UH",
    "wof:placetype": "postalcode"
  },
  "geometry": {"coordinates":[-0.064148,51.487357],"type":"Point"}
}
