{
  "type": "Feature",
  "properties": {
    "date:inception_lower": "1992-01-01",
    "date:inception_upper": "1992-01-01",
    "iso:country": "GB",
    "wof:name": "CR0 7XQ",
    "wof:placetype": "postalcode"
  },
  "geometry": {"coordinates":[-0.046388,51.388501],"type":"Point"}
}
