{
  "type": "Feature",
  "properties": {
    "date:inception_lower": "1996-06-01",
    "date:inception_upper": "1996-06-01",
    "iso:country": "GB",
    "wof:name": "CF62 8HD",
    "wof:placetype": "postalcode"
  },
  "geometry": {"coordinates":[-3.27832,51.406781],"type":"Point"}
}
