{
  "type": "Feature",
  "properties": {
    "iso:country": "GB",
    "wof:name": "CF62 8HD",
    "wof:placetype": "postalcode"
  },
  "geometry": {"coordinates":[-3.27832,51.406781],"type":"Point"}
}
