{
  "type": "Feature",
  "properties": {
    "date:inception_lower": "1980-01-01",
    "date:inception_upper": "1980-01-01",
    "iso:country": "GB",
    "wof:name": "EX5 2DS",
    "wof:placetype": "postalcode"
  },
  "geometry": {"coordinates":[-3.433007,50.735365],"type":"Point"}
}
