{
  "type": "Feature",
  "properties": {
    "iso:country":"GB",
    "wof:name":"EX5 2DS",
    "wof:placetype":"postalcode"
},
  "geometry": {"coordinates":[-3.43291981428086,50.73528669490195],"type":"Point"}
}