{
  "type": "Feature",
  "properties": {
    "iso:country": "GB",
    "wof:name": "PE19 6YN",
    "wof:placetype": "postalcode"
  },
  "geometry": {"coordinates":[-0.223043,52.258805],"type":"Point"}
}
