{
  "type": "Feature",
  "properties": {
    "date:inception_lower":"2001-06-01",
    "date:inception_upper":"2001-06-30",
    "iso:country":"GB",
    "wof:name":"NE28 0RZ",
    "wof:placetype":"postalcode"
},
  "geometry": {"coordinates":[-1.480448,54.990134],"type":"Point"}
}