{
  "type": "Feature",
  "properties": {
    "iso:country":"GB",
    "wof:name":"NE28 0RZ",
    "wof:placetype":"postalcode"
},
  "geometry": {"coordinates":[-1.48044838513938,54.99013411752006],"type":"Point"}
}