{
  "type": "Feature",
  "properties": {
    "iso:country":"GB",
    "wof:name":"BB1 4HF",
    "wof:placetype":"postalcode"
},
  "geometry": {"coordinates":[-2.41961999186474,53.76617893026981],"type":"Point"}
}