{
  "type": "Feature",
  "properties": {
    "iso:country":"GB",
    "wof:name":"M16 0DZ",
    "wof:placetype":"postalcode"
},
  "geometry": {"coordinates":[-2.27367342232172,53.44974666359678],"type":"Point"}
}