{
  "type": "Feature",
  "properties": {
    "iso:country":"GB",
    "wof:name":"DN36 4GH",
    "wof:placetype":"postalcode"
},
  "geometry": {"coordinates":[-0.05584801946778,53.52982405878665],"type":"Point"}
}