{
  "type": "Feature",
  "properties": {
    "date:inception_lower":"1980-01-01",
    "date:inception_upper":"1980-01-31",
    "iso:country":"GB",
    "wof:name":"BS14 0QZ",
    "wof:placetype":"postalcode"
},
  "geometry": {"coordinates":[-2.550473,51.394945],"type":"Point"}
}