{
  "type": "Feature",
  "properties": {
    "iso:country":"GB",
    "wof:name":"BS14 0QZ",
    "wof:placetype":"postalcode"
},
  "geometry": {"coordinates":[-2.55047259697014,51.39494544726432],"type":"Point"}
}