{
  "type": "Feature",
  "properties": {
    "iso:country": "GB",
    "wof:name": "BS14 0QZ",
    "wof:placetype": "postalcode"
  },
  "geometry": {"coordinates":[-2.550473,51.394945],"type":"Point"}
}
