{
  "type": "Feature",
  "properties": {
    "date:inception_lower": "2022-10-01",
    "date:inception_upper": "2022-10-01",
    "iso:country": "GB",
    "wof:name": "RG19 8FT",
    "wof:placetype": "postalcode"
  },
  "geometry": {"coordinates":[-1.255657,51.356858],"type":"Point"}
}
