{
  "type": "Feature",
  "properties": {
    "iso:country": "GB",
    "wof:name": "CO10 0FL",
    "wof:placetype": "postalcode"
  },
  "geometry": {"coordinates":[0.749883,52.020409],"type":"Point"}
}
