{
  "type": "Feature",
  "properties": {
    "iso:country": "GB",
    "wof:name": "DH2 2BL",
    "wof:placetype": "postalcode"
  },
  "geometry": {"coordinates":[-1.587611,54.8576],"type":"Point"}
}
