{
  "type": "Feature",
  "properties": {
    "iso:country":"GB",
    "wof:name":"EX34 8AW",
    "wof:placetype":"postalcode"
},
  "geometry": {"coordinates":[-4.12702337432264,51.20911585223113],"type":"Point"}
}