{
  "type": "Feature",
  "properties": {
    "date:inception_lower":"1980-01-01",
    "date:inception_upper":"1980-01-31",
    "iso:country":"GB",
    "wof:name":"EX34 8AW",
    "wof:placetype":"postalcode"
},
  "geometry": {"coordinates":[-4.127023,51.209116],"type":"Point"}
}