{
  "type": "Feature",
  "properties": {
    "iso:country": "GB",
    "wof:name": "EX34 8AW",
    "wof:placetype": "postalcode"
  },
  "geometry": {"coordinates":[-4.126929,51.209037],"type":"Point"}
}
