{
  "type": "Feature",
  "properties": {
    "iso:country":"GB",
    "wof:name":"GL4 4PF",
    "wof:placetype":"postalcode"
},
  "geometry": {"coordinates":[-2.22246893814556,51.84787615430049],"type":"Point"}
}