{
  "type": "Feature",
  "properties": {
    "iso:country": "GB",
    "wof:name": "GL4 4PF",
    "wof:placetype": "postalcode"
  },
  "geometry": {"coordinates":[-2.222469,51.847876],"type":"Point"}
}
