{
  "type": "Feature",
  "properties": {
    "iso:country":"GB",
    "wof:name":"TS6 7RD",
    "wof:placetype":"postalcode"
},
  "geometry": {"coordinates":[-1.1434752692452,54.5669538178379],"type":"Point"}
}