{
  "type": "Feature",
  "properties": {
    "iso:country": "GB",
    "wof:name": "TS6 7RD",
    "wof:placetype": "postalcode"
  },
  "geometry": {"coordinates":[-1.143475,54.566954],"type":"Point"}
}
