{
  "type": "Feature",
  "properties": {
    "iso:country":"GB",
    "wof:name":"EN5 5DN",
    "wof:placetype":"postalcode"
},
  "geometry": {"coordinates":[-0.18475182960793,51.64886310700239],"type":"Point"}
}