{
  "type": "Feature",
  "properties": {
    "iso:country":"GB",
    "wof:name":"HG2 8AY",
    "wof:placetype":"postalcode"
},
  "geometry": {"coordinates":[-1.53520080643847,53.98057412053316],"type":"Point"}
}