{
  "type": "Feature",
  "properties": {
    "date:inception_lower": "1980-01-01",
    "date:inception_upper": "1980-01-01",
    "iso:country": "GB",
    "wof:name": "ST16 1HJ",
    "wof:placetype": "postalcode"
  },
  "geometry": {"coordinates":[-2.150396,52.812369],"type":"Point"}
}
