{
  "type": "Feature",
  "properties": {
    "iso:country": "GB",
    "wof:name": "B64 5HU",
    "wof:placetype": "postalcode"
  },
  "geometry": {"coordinates":[-2.076528,52.475119],"type":"Point"}
}
