{
  "type": "Feature",
  "properties": {
    "date:inception_lower": "2007-05-01",
    "date:inception_upper": "2007-05-01",
    "iso:country": "GB",
    "wof:name": "B64 5HU",
    "wof:placetype": "postalcode"
  },
  "geometry": {"coordinates":[-2.077537,52.474702],"type":"Point"}
}
