{
  "type": "Feature",
  "properties": {
    "iso:country":"GB",
    "wof:name":"B64 5HU",
    "wof:placetype":"postalcode"
},
  "geometry": {"coordinates":[-2.07652775833498,52.47511870964063],"type":"Point"}
}