{
  "type": "Feature",
  "properties": {
    "iso:country":"GB",
    "wof:name":"MK43 7QA",
    "wof:placetype":"postalcode"
},
  "geometry": {"coordinates":[-0.55260600699227,52.18972250356655],"type":"Point"}
}