{
  "type": "Feature",
  "properties": {
    "date:inception_lower": "1983-03-01",
    "date:inception_upper": "1983-03-01",
    "iso:country": "GB",
    "wof:name": "MK43 7QA",
    "wof:placetype": "postalcode"
  },
  "geometry": {"coordinates":[-0.552606,52.189722],"type":"Point"}
}
