{
  "type": "Feature",
  "properties": {
    "iso:country": "GB",
    "wof:name": "MK43 7QA",
    "wof:placetype": "postalcode"
  },
  "geometry": {"coordinates":[-0.552606,52.189722],"type":"Point"}
}
