{
  "type": "Feature",
  "properties": {
    "date:inception_lower": "2009-11-01",
    "date:inception_upper": "2009-11-01",
    "iso:country": "GB",
    "wof:name": "TR26 2FT",
    "wof:placetype": "postalcode"
  },
  "geometry": {"coordinates":[-5.496886,50.205495],"type":"Point"}
}
