{
  "type": "Feature",
  "properties": {
    "iso:country":"GB",
    "wof:name":"TR26 2FT",
    "wof:placetype":"postalcode"
},
  "geometry": {"coordinates":[-5.49688610989947,50.20549460471599],"type":"Point"}
}