{
  "type": "Feature",
  "properties": {
    "date:inception_lower": "1980-01-01",
    "date:inception_upper": "1980-01-01",
    "iso:country": "GB",
    "wof:name": "L9 6DG",
    "wof:placetype": "postalcode"
  },
  "geometry": {"coordinates":[-2.923225,53.455885],"type":"Point"}
}
