{
  "type": "Feature",
  "properties": {
    "iso:country":"GB",
    "wof:name":"L9 6DG",
    "wof:placetype":"postalcode"
},
  "geometry": {"coordinates":[-2.923224943251,53.45588483081507],"type":"Point"}
}