{
  "type": "Feature",
  "properties": {
    "iso:country": "GB",
    "wof:name": "L9 6DG",
    "wof:placetype": "postalcode"
  },
  "geometry": {"coordinates":[-2.923225,53.455885],"type":"Point"}
}
