{
  "type": "Feature",
  "properties": {
    "iso:country": "GB",
    "wof:name": "CF44 0YX",
    "wof:placetype": "postalcode"
  },
  "geometry": {"coordinates":[-3.530485,51.775004],"type":"Point"}
}
