{
  "type": "Feature",
  "properties": {
    "iso:country":"GB",
    "wof:name":"CF44 0YX",
    "wof:placetype":"postalcode"
},
  "geometry": {"coordinates":[-3.53048510854131,51.77500447459751],"type":"Point"}
}