{
  "type": "Feature",
  "properties": {
    "date:inception_lower": "2017-05-01",
    "date:inception_upper": "2017-05-01",
    "iso:country": "GB",
    "wof:name": "DN36 4BW",
    "wof:placetype": "postalcode"
  },
  "geometry": {"coordinates":[-0.055472,53.521042],"type":"Point"}
}
