{
  "type": "Feature",
  "properties": {
    "date:inception_lower": "1980-01-01",
    "date:inception_upper": "1980-01-01",
    "iso:country": "GB",
    "wof:name": "NR18 9JD",
    "wof:placetype": "postalcode"
  },
  "geometry": {"coordinates":[1.105366,52.565785],"type":"Point"}
}
