{
  "type": "Feature",
  "properties": {
    "iso:country":"GB",
    "wof:name":"NR18 9JD",
    "wof:placetype":"postalcode"
},
  "geometry": {"coordinates":[1.10496423422741,52.56561917670498],"type":"Point"}
}