{
  "type": "Feature",
  "properties": {
    "iso:country": "GB",
    "wof:name": "WR14 4LG",
    "wof:placetype": "postalcode"
  },
  "geometry": {"coordinates":[-2.335208,52.0819],"type":"Point"}
}
