{
  "type": "Feature",
  "properties": {
    "date:inception_lower": "2017-08-01",
    "date:inception_upper": "2017-08-01",
    "iso:country": "GB",
    "wof:name": "SO31 8LX",
    "wof:placetype": "postalcode"
  },
  "geometry": {"coordinates":[-1.323289,50.892498],"type":"Point"}
}
