{
  "type": "Feature",
  "properties": {
    "date:inception_lower": "2022-06-01",
    "date:inception_upper": "2022-06-01",
    "iso:country": "GB",
    "wof:name": "LL23 7DH",
    "wof:placetype": "postalcode"
  },
  "geometry": {"coordinates":[-3.599647,52.916429],"type":"Point"}
}
