{
  "type": "Feature",
  "properties": {
    "iso:country":"GB",
    "wof:name":"AL4 8PB",
    "wof:placetype":"postalcode"
},
  "geometry": {"coordinates":[-0.29070660194504,51.80891989641717],"type":"Point"}
}