{
  "type": "Feature",
  "properties": {
    "iso:country":"GB",
    "wof:name":"RH12 4GX",
    "wof:placetype":"postalcode"
},
  "geometry": {"coordinates":[-0.29468572001087,51.07867502125573],"type":"Point"}
}