{
  "type": "Feature",
  "properties": {
    "date:inception_lower": "1997-12-01",
    "date:inception_upper": "1997-12-01",
    "iso:country": "GB",
    "wof:name": "SK13 1PJ",
    "wof:placetype": "postalcode"
  },
  "geometry": {"coordinates":[-1.979866,53.462156],"type":"Point"}
}
