{
  "type": "Feature",
  "properties": {
    "iso:country":"GB",
    "wof:name":"TW19 7PN",
    "wof:placetype":"postalcode"
},
  "geometry": {"coordinates":[-0.48227003323985,51.45650909994501],"type":"Point"}
}