{
  "type": "Feature",
  "properties": {
    "iso:country": "GB",
    "wof:name": "CV47 2UU",
    "wof:placetype": "postalcode"
  },
  "geometry": {"coordinates":[-1.3955,52.244464],"type":"Point"}
}
