{
  "type": "Feature",
  "properties": {
    "date:inception_lower": "1980-01-01",
    "date:inception_upper": "1980-01-01",
    "iso:country": "GB",
    "wof:name": "RH12 4NS",
    "wof:placetype": "postalcode"
  },
  "geometry": {"coordinates":[-0.28763,51.076104],"type":"Point"}
}
