{
  "type": "Feature",
  "properties": {
    "iso:country":"GB",
    "wof:name":"RH12 4NS",
    "wof:placetype":"postalcode"
},
  "geometry": {"coordinates":[-0.28765762144318,51.07608123043931],"type":"Point"}
}