{
  "type": "Feature",
  "properties": {
    "iso:country":"GB",
    "wof:name":"WN7 2DB",
    "wof:placetype":"postalcode"
},
  "geometry": {"coordinates":[-2.5074928193013,53.49457168982087],"type":"Point"}
}