{
  "type": "Feature",
  "properties": {
    "iso:country":"GB",
    "wof:name":"AB23 8YF",
    "wof:placetype":"postalcode"
},
  "geometry": {"coordinates":[-2.05669432379404,57.25028434080446],"type":"Point"}
}