{
  "type": "Feature",
  "properties": {
    "iso:country":"GB",
    "wof:name":"GL56 0JU",
    "wof:placetype":"postalcode"
},
  "geometry": {"coordinates":[-1.68763192298965,51.98884734936461],"type":"Point"}
}