{
  "type": "Feature",
  "properties": {
    "iso:country": "GB",
    "wof:name": "GL56 0JU",
    "wof:placetype": "postalcode"
  },
  "geometry": {"coordinates":[-1.687632,51.988847],"type":"Point"}
}
