{
  "type": "Feature",
  "properties": {
    "date:inception_lower":"2008-04-01",
    "date:inception_upper":"2008-04-30",
    "iso:country":"GB",
    "wof:name":"GL56 0JU",
    "wof:placetype":"postalcode"
},
  "geometry": {"coordinates":[-1.687632,51.988847],"type":"Point"}
}