{
  "type": "Feature",
  "properties": {
    "date:inception_lower":"2004-06-01",
    "date:inception_upper":"2004-06-30",
    "iso:country":"GB",
    "wof:name":"CF31 5BE",
    "wof:placetype":"postalcode"
},
  "geometry": {"coordinates":[-3.590192,51.501654],"type":"Point"}
}