{
  "type": "Feature",
  "properties": {
    "iso:country": "GB",
    "wof:name": "CF31 5BE",
    "wof:placetype": "postalcode"
  },
  "geometry": {"coordinates":[-3.590192,51.501654],"type":"Point"}
}
