{
  "type": "Feature",
  "properties": {
    "date:inception_lower": "2018-09-01",
    "date:inception_upper": "2018-09-01",
    "iso:country": "GB",
    "wof:name": "WA14 5AA",
    "wof:placetype": "postalcode"
  },
  "geometry": {"coordinates":[-2.350778,53.403576],"type":"Point"}
}
