{
  "type": "Feature",
  "properties": {
    "iso:country":"GB",
    "wof:name":"B96 6DB",
    "wof:placetype":"postalcode"
},
  "geometry": {"coordinates":[-1.94041322375784,52.25977915271029],"type":"Point"}
}