{
  "type": "Feature",
  "properties": {
    "date:inception_lower": "1980-01-01",
    "date:inception_upper": "1980-01-01",
    "iso:country": "GB",
    "wof:name": "B96 6DB",
    "wof:placetype": "postalcode"
  },
  "geometry": {"coordinates":[-1.940406,52.259793],"type":"Point"}
}
