{
  "type": "Feature",
  "properties": {
    "iso:country": "GB",
    "wof:name": "B96 6DB",
    "wof:placetype": "postalcode"
  },
  "geometry": {"coordinates":[-1.939907,52.260045],"type":"Point"}
}
