{
  "type": "Feature",
  "properties": {
    "date:inception_lower":"2016-08-01",
    "date:inception_upper":"2016-08-31",
    "iso:country":"GB",
    "wof:name":"HU15 2FX",
    "wof:placetype":"postalcode"
},
  "geometry": {"coordinates":[-0.682826,53.770308],"type":"Point"}
}