{
  "type": "Feature",
  "properties": {
    "iso:country":"GB",
    "wof:name":"HU15 2FX",
    "wof:placetype":"postalcode"
},
  "geometry": {"coordinates":[-0.68259471090884,53.77022197482811],"type":"Point"}
}