{
  "type": "Feature",
  "properties": {
    "iso:country":"GB",
    "wof:name":"N2 0RL",
    "wof:placetype":"postalcode"
},
  "geometry": {"coordinates":[-0.1734067521465,51.58045338327088],"type":"Point"}
}