{
  "type": "Feature",
  "properties": {
    "date:inception_lower": "1980-01-01",
    "date:inception_upper": "1980-01-01",
    "iso:country": "GB",
    "wof:name": "HR3 6LZ",
    "wof:placetype": "postalcode"
  },
  "geometry": {"coordinates":[-3.042247,52.134787],"type":"Point"}
}
