{
  "type": "Feature",
  "properties": {
    "date:inception_lower": "2010-08-01",
    "date:inception_upper": "2010-08-01",
    "iso:country": "GB",
    "wof:name": "G31 4BG",
    "wof:placetype": "postalcode"
  },
  "geometry": {"coordinates":[-4.212206,55.855965],"type":"Point"}
}
