{
  "type": "Feature",
  "properties": {
    "iso:country": "GB",
    "wof:name": "LL14 4ED",
    "wof:placetype": "postalcode"
  },
  "geometry": {"coordinates":[-3.026714,53.028862],"type":"Point"}
}
