{
  "type": "Feature",
  "properties": {
    "iso:country":"GB",
    "wof:name":"HD7 4AE",
    "wof:placetype":"postalcode"
},
  "geometry": {"coordinates":[-1.85257722534171,53.63767374041689],"type":"Point"}
}