{
  "type": "Feature",
  "properties": {
    "iso:country": "GB",
    "wof:name": "SA14 8DT",
    "wof:placetype": "postalcode"
  },
  "geometry": {"coordinates":[-4.137584,51.703669],"type":"Point"}
}
