{
  "type": "Feature",
  "properties": {
    "iso:country":"GB",
    "wof:name":"PE8 6BA",
    "wof:placetype":"postalcode"
},
  "geometry": {"coordinates":[-0.43951818153665,52.60605377521555],"type":"Point"}
}