{
  "type": "Feature",
  "properties": {
    "date:inception_lower": "1980-01-01",
    "date:inception_upper": "1980-01-01",
    "iso:country": "GB",
    "wof:name": "PE8 6BA",
    "wof:placetype": "postalcode"
  },
  "geometry": {"coordinates":[-0.439518,52.606054],"type":"Point"}
}
