{
  "type": "Feature",
  "properties": {
    "iso:country":"GB",
    "wof:name":"BH10 4HF",
    "wof:placetype":"postalcode"
},
  "geometry": {"coordinates":[-1.89097327732051,50.74970896649183],"type":"Point"}
}