{
  "type": "Feature",
  "properties": {
    "iso:country": "GB",
    "wof:name": "NN8 1EW",
    "wof:placetype": "postalcode"
  },
  "geometry": {"coordinates":[-0.684092,52.305581],"type":"Point"}
}
