{
  "type": "Feature",
  "properties": {
    "iso:country":"GB",
    "wof:name":"NN8 1EW",
    "wof:placetype":"postalcode"
},
  "geometry": {"coordinates":[-0.68409215924451,52.30558140483731],"type":"Point"}
}