{
  "type": "Feature",
  "properties": {
    "date:inception_lower": "1980-01-01",
    "date:inception_upper": "1980-01-01",
    "iso:country": "GB",
    "wof:name": "NN8 1EW",
    "wof:placetype": "postalcode"
  },
  "geometry": {"coordinates":[-0.684092,52.305581],"type":"Point"}
}
