{
  "type": "Feature",
  "properties": {
    "date:inception_lower": "1993-01-01",
    "date:inception_upper": "1993-01-01",
    "iso:country": "GB",
    "wof:name": "SA6 8LP",
    "wof:placetype": "postalcode"
  },
  "geometry": {"coordinates":[-3.932492,51.653116],"type":"Point"}
}
