{
  "type": "Feature",
  "properties": {
    "iso:country":"GB",
    "wof:name":"BA12 6PL",
    "wof:placetype":"postalcode"
},
  "geometry": {"coordinates":[-2.31758442982771,51.08332207589977],"type":"Point"}
}