{
  "type": "Feature",
  "properties": {
    "iso:country": "GB",
    "wof:name": "BA12 6PL",
    "wof:placetype": "postalcode"
  },
  "geometry": {"coordinates":[-2.317584,51.083322],"type":"Point"}
}
