{
  "type": "Feature",
  "properties": {
    "iso:country": "GB",
    "wof:name": "IP23 7QP",
    "wof:placetype": "postalcode"
  },
  "geometry": {"coordinates":[1.20694,52.284834],"type":"Point"}
}
