{
  "type": "Feature",
  "properties": {
    "iso:country": "GB",
    "wof:name": "PE22 7PA",
    "wof:placetype": "postalcode"
  },
  "geometry": {"coordinates":[-0.062991,53.148543],"type":"Point"}
}
