{
  "type": "Feature",
  "properties": {
    "date:inception_lower": "1980-01-01",
    "date:inception_upper": "1980-01-01",
    "iso:country": "GB",
    "wof:name": "PE22 7PA",
    "wof:placetype": "postalcode"
  },
  "geometry": {"coordinates":[-0.062991,53.148543],"type":"Point"}
}
