{
  "type": "Feature",
  "properties": {
    "date:inception_lower": "2021-04-01",
    "date:inception_upper": "2021-04-01",
    "iso:country": "GB",
    "wof:name": "CO11 2FS",
    "wof:placetype": "postalcode"
  },
  "geometry": {"coordinates":[1.048927,51.934748],"type":"Point"}
}
