{
  "type": "Feature",
  "properties": {
    "iso:country":"GB",
    "wof:name":"W7 2JL",
    "wof:placetype":"postalcode"
},
  "geometry": {"coordinates":[-0.32622305693524,51.50463453206581],"type":"Point"}
}