{
  "type": "Feature",
  "properties": {
    "iso:country": "GB",
    "wof:name": "DE55 6GF",
    "wof:placetype": "postalcode"
  },
  "geometry": {"coordinates":[-1.417088,53.134391],"type":"Point"}
}
