{
  "type": "Feature",
  "properties": {
    "iso:country":"GB",
    "wof:name":"DE55 6GF",
    "wof:placetype":"postalcode"
},
  "geometry": {"coordinates":[-1.41710442205763,53.13441672034569],"type":"Point"}
}