{
  "type": "Feature",
  "properties": {
    "iso:country":"GB",
    "wof:name":"SW5 9DB",
    "wof:placetype":"postalcode"
},
  "geometry": {"coordinates":[-0.19347435713525,51.49036325581186],"type":"Point"}
}