{
  "type": "Feature",
  "properties": {
    "date:inception_lower":"1980-01-01",
    "date:inception_upper":"1980-01-31",
    "iso:country":"GB",
    "wof:name":"PE12 9PJ",
    "wof:placetype":"postalcode"
},
  "geometry": {"coordinates":[0.174794,52.839531],"type":"Point"}
}