{
  "type": "Feature",
  "properties": {
    "iso:country":"GB",
    "wof:name":"WA7 2RR",
    "wof:placetype":"postalcode"
},
  "geometry": {"coordinates":[-2.70401583415401,53.31761166537223],"type":"Point"}
}