{
  "type": "Feature",
  "properties": {
    "iso:country": "GB",
    "wof:name": "WA7 2RR",
    "wof:placetype": "postalcode"
  },
  "geometry": {"coordinates":[-2.704016,53.317612],"type":"Point"}
}
