{
  "type": "Feature",
  "properties": {
    "iso:country": "GB",
    "wof:name": "GL11 5HD",
    "wof:placetype": "postalcode"
  },
  "geometry": {"coordinates":[-2.344062,51.687713],"type":"Point"}
}
