{
  "type": "Feature",
  "properties": {
    "iso:country":"GB",
    "wof:name":"RM18 8TE",
    "wof:placetype":"postalcode"
},
  "geometry": {"coordinates":[0.42319787600755,51.48183889064411],"type":"Point"}
}