{
  "type": "Feature",
  "properties": {
    "iso:country": "GB",
    "wof:name": "RM18 8TE",
    "wof:placetype": "postalcode"
  },
  "geometry": {"coordinates":[0.423198,51.481839],"type":"Point"}
}
