{
  "type": "Feature",
  "properties": {
    "iso:country":"GB",
    "wof:name":"LN7 6SX",
    "wof:placetype":"postalcode"
},
  "geometry": {"coordinates":[-0.32255273536957,53.45583422927034],"type":"Point"}
}