{
  "type": "Feature",
  "properties": {
    "iso:country":"GB",
    "wof:name":"LE5 6XF",
    "wof:placetype":"postalcode"
},
  "geometry": {"coordinates":[-1.05999275609234,52.62339001878885],"type":"Point"}
}