{
  "type": "Feature",
  "properties": {
    "iso:country": "GB",
    "wof:name": "YO17 8DG",
    "wof:placetype": "postalcode"
  },
  "geometry": {"coordinates":[-0.610824,54.110563],"type":"Point"}
}
