{
  "type": "Feature",
  "properties": {
    "iso:country": "GB",
    "wof:name": "EX1 2QU",
    "wof:placetype": "postalcode"
  },
  "geometry": {"coordinates":[-3.506862,50.722825],"type":"Point"}
}
