{
  "type": "Feature",
  "properties": {
    "iso:country":"GB",
    "wof:name":"EX1 2QU",
    "wof:placetype":"postalcode"
},
  "geometry": {"coordinates":[-3.50686203884463,50.72282491153705],"type":"Point"}
}