{
  "type": "Feature",
  "properties": {
    "date:inception_lower": "1980-01-01",
    "date:inception_upper": "1980-01-01",
    "iso:country": "GB",
    "wof:name": "GU5 9NU",
    "wof:placetype": "postalcode"
  },
  "geometry": {"coordinates":[-0.441711,51.219482],"type":"Point"}
}
