{
  "type": "Feature",
  "properties": {
    "iso:country": "GB",
    "wof:name": "LS19 6BX",
    "wof:placetype": "postalcode"
  },
  "geometry": {"coordinates":[-1.691277,53.853099],"type":"Point"}
}
