{
  "type": "Feature",
  "properties": {
    "date:inception_lower":"1980-01-01",
    "date:inception_upper":"1980-01-31",
    "iso:country":"GB",
    "wof:name":"LS19 6BX",
    "wof:placetype":"postalcode"
},
  "geometry": {"coordinates":[-1.691277,53.853099],"type":"Point"}
}