{
  "type": "Feature",
  "properties": {
    "iso:country":"GB",
    "wof:name":"LS19 6BX",
    "wof:placetype":"postalcode"
},
  "geometry": {"coordinates":[-1.69127688784525,53.85309855630162],"type":"Point"}
}