{
  "type": "Feature",
  "properties": {
    "iso:country":"GB",
    "wof:name":"NR31 7AY",
    "wof:placetype":"postalcode"
},
  "geometry": {"coordinates":[1.72498464036294,52.57395430234719],"type":"Point"}
}