{
  "type": "Feature",
  "properties": {
    "iso:country": "GB",
    "wof:name": "SK17 0DG",
    "wof:placetype": "postalcode"
  },
  "geometry": {"coordinates":[-1.781004,53.169556],"type":"Point"}
}
