{
  "type": "Feature",
  "properties": {
    "iso:country":"GB",
    "wof:name":"TD2 6RW",
    "wof:placetype":"postalcode"
},
  "geometry": {"coordinates":[-2.75673524641462,55.7184529946128],"type":"Point"}
}