{
  "type": "Feature",
  "properties": {
    "iso:country": "GB",
    "wof:name": "TD2 6RW",
    "wof:placetype": "postalcode"
  },
  "geometry": {"coordinates":[-2.756735,55.718453],"type":"Point"}
}
