{
  "type": "Feature",
  "properties": {
    "iso:country":"GB",
    "wof:name":"M16 9QA",
    "wof:placetype":"postalcode"
},
  "geometry": {"coordinates":[-2.26992340297647,53.4591212232742],"type":"Point"}
}