{
  "type": "Feature",
  "properties": {
    "date:inception_lower": "1980-01-01",
    "date:inception_upper": "1980-01-01",
    "iso:country": "GB",
    "wof:name": "HG4 2HJ",
    "wof:placetype": "postalcode"
  },
  "geometry": {"coordinates":[-1.541792,54.142674],"type":"Point"}
}
