{
  "type": "Feature",
  "properties": {
    "iso:country":"GB",
    "wof:name":"HG4 2HJ",
    "wof:placetype":"postalcode"
},
  "geometry": {"coordinates":[-1.541792373012,54.14267365422332],"type":"Point"}
}