{
  "type": "Feature",
  "properties": {
    "iso:country": "GB",
    "wof:name": "HG4 2HJ",
    "wof:placetype": "postalcode"
  },
  "geometry": {"coordinates":[-1.541792,54.142674],"type":"Point"}
}
