{
  "type": "Feature",
  "properties": {
    "iso:country":"GB",
    "wof:name":"E12 6JL",
    "wof:placetype":"postalcode"
},
  "geometry": {"coordinates":[0.06498575451037,51.5462670393281],"type":"Point"}
}