{
  "type": "Feature",
  "properties": {
    "iso:country":"GB",
    "wof:name":"CW3 9AP",
    "wof:placetype":"postalcode"
},
  "geometry": {"coordinates":[-2.36748336146522,53.03399417251863],"type":"Point"}
}