{
  "type": "Feature",
  "properties": {
    "iso:country":"GB",
    "wof:name":"DH1 2PR",
    "wof:placetype":"postalcode"
},
  "geometry": {"coordinates":[-1.53660512980415,54.75333441360867],"type":"Point"}
}