{
  "type": "Feature",
  "properties": {
    "iso:country": "GB",
    "wof:name": "SA5 9ET",
    "wof:placetype": "postalcode"
  },
  "geometry": {"coordinates":[-3.949543,51.647897],"type":"Point"}
}
