{
  "type": "Feature",
  "properties": {
    "iso:country":"GB",
    "wof:name":"KA27 8PD",
    "wof:placetype":"postalcode"
},
  "geometry": {"coordinates":[-5.2910463104885,55.46173654573222],"type":"Point"}
}