{
  "type": "Feature",
  "properties": {
    "date:inception_lower":"1980-01-01",
    "date:inception_upper":"1980-01-31",
    "iso:country":"GB",
    "wof:name":"KA27 8PD",
    "wof:placetype":"postalcode"
},
  "geometry": {"coordinates":[-5.292162,55.462973],"type":"Point"}
}