{
  "type": "Feature",
  "properties": {
    "iso:country": "GB",
    "wof:name": "KA27 8PD",
    "wof:placetype": "postalcode"
  },
  "geometry": {"coordinates":[-5.292162,55.462973],"type":"Point"}
}
