{
  "type": "Feature",
  "properties": {
    "iso:country":"GB",
    "wof:name":"BB4 8SW",
    "wof:placetype":"postalcode"
},
  "geometry": {"coordinates":[-2.29195614347303,53.70206854727572],"type":"Point"}
}