{
  "type": "Feature",
  "properties": {
    "iso:country":"GB",
    "wof:name":"TN4 9DP",
    "wof:placetype":"postalcode"
},
  "geometry": {"coordinates":[0.2746789483698,51.15156837241109],"type":"Point"}
}