{
  "type": "Feature",
  "properties": {
    "iso:country":"GB",
    "wof:name":"CB21 5LF",
    "wof:placetype":"postalcode"
},
  "geometry": {"coordinates":[0.24673109305634,52.20571188858839],"type":"Point"}
}