{
  "type": "Feature",
  "properties": {
    "iso:country": "GB",
    "wof:name": "CB21 5LF",
    "wof:placetype": "postalcode"
  },
  "geometry": {"coordinates":[0.246731,52.205712],"type":"Point"}
}
