{
  "type": "Feature",
  "properties": {
    "date:inception_lower":"2006-09-01",
    "date:inception_upper":"2006-09-30",
    "iso:country":"GB",
    "wof:name":"CB21 5LF",
    "wof:placetype":"postalcode"
},
  "geometry": {"coordinates":[0.246731,52.205712],"type":"Point"}
}