{
  "type": "Feature",
  "properties": {
    "iso:country":"GB",
    "wof:name":"BS21 6RU",
    "wof:placetype":"postalcode"
},
  "geometry": {"coordinates":[-2.79103558487937,51.4438590758296],"type":"Point"}
}