{
  "type": "Feature",
  "properties": {
    "date:inception_lower": "1980-01-01",
    "date:inception_upper": "1980-01-01",
    "iso:country": "GB",
    "wof:name": "BS21 6RU",
    "wof:placetype": "postalcode"
  },
  "geometry": {"coordinates":[-2.791036,51.443859],"type":"Point"}
}
