{
  "type": "Feature",
  "properties": {
    "iso:country":"GB",
    "wof:name":"SO30 4RN",
    "wof:placetype":"postalcode"
},
  "geometry": {"coordinates":[-1.3136608732384,50.9127294100284],"type":"Point"}
}