{
  "type": "Feature",
  "properties": {
    "iso:country": "GB",
    "wof:name": "CW7 2EY",
    "wof:placetype": "postalcode"
  },
  "geometry": {"coordinates":[-2.539803,53.190916],"type":"Point"}
}
