{
  "type": "Feature",
  "properties": {
    "date:inception_lower":"1981-06-01",
    "date:inception_upper":"1981-06-30",
    "iso:country":"GB",
    "wof:name":"CW7 2EY",
    "wof:placetype":"postalcode"
},
  "geometry": {"coordinates":[-2.539803,53.190916],"type":"Point"}
}