{
  "type": "Feature",
  "properties": {
    "iso:country": "GB",
    "wof:name": "PE4 7PX",
    "wof:placetype": "postalcode"
  },
  "geometry": {"coordinates":[-0.249383,52.608215],"type":"Point"}
}
