{
  "type": "Feature",
  "properties": {
    "date:inception_lower": "1980-01-01",
    "date:inception_upper": "1980-01-01",
    "iso:country": "GB",
    "wof:name": "EH22 5NR",
    "wof:placetype": "postalcode"
  },
  "geometry": {"coordinates":[-3.04312,55.871498],"type":"Point"}
}
