{
  "type": "Feature",
  "properties": {
    "iso:country":"GB",
    "wof:name":"NW3 3RU",
    "wof:placetype":"postalcode"
},
  "geometry": {"coordinates":[-0.16192612030681,51.54339623548088],"type":"Point"}
}