{
  "type": "Feature",
  "properties": {
    "date:inception_lower": "1980-01-01",
    "date:inception_upper": "1980-01-01",
    "iso:country": "GB",
    "wof:name": "WF5 0NT",
    "wof:placetype": "postalcode"
  },
  "geometry": {"coordinates":[-1.560769,53.677092],"type":"Point"}
}
