{
  "type": "Feature",
  "properties": {
    "iso:country": "GB",
    "wof:name": "WF5 0NT",
    "wof:placetype": "postalcode"
  },
  "geometry": {"coordinates":[-1.560769,53.677092],"type":"Point"}
}
