{
  "type": "Feature",
  "properties": {
    "iso:country":"GB",
    "wof:name":"WF5 0NT",
    "wof:placetype":"postalcode"
},
  "geometry": {"coordinates":[-1.5607695450571,53.67709194181737],"type":"Point"}
}