{
  "type": "Feature",
  "properties": {
    "iso:country":"GB",
    "wof:name":"TN24 0DF",
    "wof:placetype":"postalcode"
},
  "geometry": {"coordinates":[0.88669692465417,51.13186043181407],"type":"Point"}
}