{
  "type": "Feature",
  "properties": {
    "iso:country":"GB",
    "wof:name":"CT4 7EA",
    "wof:placetype":"postalcode"
},
  "geometry": {"coordinates":[0.95182095065932,51.20970924340108],"type":"Point"}
}