{
  "type": "Feature",
  "properties": {
    "date:inception_lower": "1980-01-01",
    "date:inception_upper": "1980-01-01",
    "iso:country": "GB",
    "wof:name": "CT4 7EA",
    "wof:placetype": "postalcode"
  },
  "geometry": {"coordinates":[0.951821,51.209709],"type":"Point"}
}
