{
  "type": "Feature",
  "properties": {
    "iso:country":"GB",
    "wof:name":"NE22 6BN",
    "wof:placetype":"postalcode"
},
  "geometry": {"coordinates":[-1.60856256987225,55.13713237595519],"type":"Point"}
}