{
  "type": "Feature",
  "properties": {
    "date:inception_lower":"2014-11-01",
    "date:inception_upper":"2014-11-30",
    "iso:country":"GB",
    "wof:name":"NE22 6BN",
    "wof:placetype":"postalcode"
},
  "geometry": {"coordinates":[-1.608563,55.137132],"type":"Point"}
}