{
  "type": "Feature",
  "properties": {
    "iso:country":"GB",
    "wof:name":"N9 9SQ",
    "wof:placetype":"postalcode"
},
  "geometry": {"coordinates":[-0.06542446473514,51.62307382436656],"type":"Point"}
}