{
  "type": "Feature",
  "properties": {
    "iso:country":"GB",
    "wof:name":"ST15 8FQ",
    "wof:placetype":"postalcode"
},
  "geometry": {"coordinates":[-2.12990988421313,52.89250653732277],"type":"Point"}
}