{
  "type": "Feature",
  "properties": {
    "date:inception_lower": "1992-01-01",
    "date:inception_upper": "1992-01-01",
    "iso:country": "GB",
    "wof:name": "ST15 8FQ",
    "wof:placetype": "postalcode"
  },
  "geometry": {"coordinates":[-2.12991,52.892507],"type":"Point"}
}
