{
  "type": "Feature",
  "properties": {
    "date:inception_lower": "2023-09-01",
    "date:inception_upper": "2023-09-01",
    "iso:country": "GB",
    "wof:name": "LE2 1AT",
    "wof:placetype": "postalcode"
  },
  "geometry": {"coordinates":[-1.10463,52.621821],"type":"Point"}
}
