{
  "type": "Feature",
  "properties": {
    "date:inception_lower":"1980-01-01",
    "date:inception_upper":"1980-01-31",
    "iso:country":"GB",
    "wof:name":"E4 7SP",
    "wof:placetype":"postalcode"
},
  "geometry": {"coordinates":[-0.016646,51.629499],"type":"Point"}
}