{
  "type": "Feature",
  "properties": {
    "iso:country": "GB",
    "wof:name": "WC2R 0EW",
    "wof:placetype": "postalcode"
  },
  "geometry": {"coordinates":[-0.120721,51.51055],"type":"Point"}
}
