{
  "type": "Feature",
  "properties": {
    "iso:country":"GB",
    "wof:name":"WC2R 0EW",
    "wof:placetype":"postalcode"
},
  "geometry": {"coordinates":[-0.12072103137762,51.51055022731922],"type":"Point"}
}