{
  "type": "Feature",
  "properties": {
    "date:inception_lower": "1980-01-01",
    "date:inception_upper": "1980-01-01",
    "iso:country": "GB",
    "wof:name": "WC2R 0EW",
    "wof:placetype": "postalcode"
  },
  "geometry": {"coordinates":[-0.120721,51.51055],"type":"Point"}
}
