{
  "type": "Feature",
  "properties": {
    "iso:country": "GB",
    "wof:name": "NR29 5BX",
    "wof:placetype": "postalcode"
  },
  "geometry": {"coordinates":[1.550171,52.729625],"type":"Point"}
}
