{
  "type": "Feature",
  "properties": {
    "date:inception_lower": "1980-01-01",
    "date:inception_upper": "1980-01-01",
    "iso:country": "GB",
    "wof:name": "NR29 5BX",
    "wof:placetype": "postalcode"
  },
  "geometry": {"coordinates":[1.549651,52.730154],"type":"Point"}
}
