{
  "type": "Feature",
  "properties": {
    "iso:country":"GB",
    "wof:name":"BH12 3AR",
    "wof:placetype":"postalcode"
},
  "geometry": {"coordinates":[-1.93763979207672,50.73629016516758],"type":"Point"}
}