{
  "type": "Feature",
  "properties": {
    "iso:country":"GB",
    "wof:name":"TQ3 1JD",
    "wof:placetype":"postalcode"
},
  "geometry": {"coordinates":[-3.56190840014265,50.45108942172551],"type":"Point"}
}