{
  "type": "Feature",
  "properties": {
    "date:inception_lower":"2002-10-01",
    "date:inception_upper":"2002-10-31",
    "iso:country":"GB",
    "wof:name":"CM6 3FY",
    "wof:placetype":"postalcode"
},
  "geometry": {"coordinates":[0.417406,51.861221],"type":"Point"}
}