{
  "type": "Feature",
  "properties": {
    "iso:country": "GB",
    "wof:name": "IP12 4LA",
    "wof:placetype": "postalcode"
  },
  "geometry": {"coordinates":[1.301681,52.098947],"type":"Point"}
}
