{
  "type": "Feature",
  "properties": {
    "iso:country":"GB",
    "wof:name":"B71 3NQ",
    "wof:placetype":"postalcode"
},
  "geometry": {"coordinates":[-1.98410411883679,52.54681016525724],"type":"Point"}
}