{
  "type": "Feature",
  "properties": {
    "iso:country": "GB",
    "wof:name": "EH2 9AL",
    "wof:placetype": "postalcode"
  },
  "geometry": {"coordinates":[-3.232955,55.943214],"type":"Point"}
}
