{
  "type": "Feature",
  "properties": {
    "iso:country":"GB",
    "wof:name":"ST7 2HJ",
    "wof:placetype":"postalcode"
},
  "geometry": {"coordinates":[-2.31969553453317,53.09920441118787],"type":"Point"}
}