{
  "type": "Feature",
  "properties": {
    "date:inception_lower":"2012-09-01",
    "date:inception_upper":"2012-09-30",
    "iso:country":"GB",
    "wof:name":"LS17 8FT",
    "wof:placetype":"postalcode"
},
  "geometry": {"coordinates":[-1.478086,53.853152],"type":"Point"}
}