{
  "type": "Feature",
  "properties": {
    "iso:country":"GB",
    "wof:name":"LS17 8FT",
    "wof:placetype":"postalcode"
},
  "geometry": {"coordinates":[-1.47808565656452,53.85315215073184],"type":"Point"}
}