{
  "type": "Feature",
  "properties": {
    "iso:country":"GB",
    "wof:name":"NE66 4AR",
    "wof:placetype":"postalcode"
},
  "geometry": {"coordinates":[-1.89019896030975,55.42396966357496],"type":"Point"}
}