{
  "type": "Feature",
  "properties": {
    "iso:country":"GB",
    "wof:name":"DN18 5RB",
    "wof:placetype":"postalcode"
},
  "geometry": {"coordinates":[-0.43235471543536,53.69289851897964],"type":"Point"}
}