{
  "type": "Feature",
  "properties": {
    "iso:country": "GB",
    "wof:name": "DN18 5RB",
    "wof:placetype": "postalcode"
  },
  "geometry": {"coordinates":[-0.432355,53.692899],"type":"Point"}
}
