{
  "type": "Feature",
  "properties": {
    "iso:country":"GB",
    "wof:name":"NG15 9BU",
    "wof:placetype":"postalcode"
},
  "geometry": {"coordinates":[-1.15794939903279,53.08244585823126],"type":"Point"}
}