{
  "type": "Feature",
  "properties": {
    "date:inception_lower":"1987-10-01",
    "date:inception_upper":"1987-10-31",
    "iso:country":"GB",
    "wof:name":"M5 3AW",
    "wof:placetype":"postalcode"
},
  "geometry": {"coordinates":[-2.282555,53.469761],"type":"Point"}
}