{
  "type": "Feature",
  "properties": {
    "date:inception_lower": "1998-12-01",
    "date:inception_upper": "1998-12-01",
    "iso:country": "GB",
    "wof:name": "TR4 8PR",
    "wof:placetype": "postalcode"
  },
  "geometry": {"coordinates":[-5.12627,50.26176],"type":"Point"}
}
