{
  "type": "Feature",
  "properties": {
    "iso:country": "GB",
    "wof:name": "TR4 8PR",
    "wof:placetype": "postalcode"
  },
  "geometry": {"coordinates":[-5.12627,50.26176],"type":"Point"}
}
