{
  "type": "Feature",
  "properties": {
    "date:inception_lower": "1980-01-01",
    "date:inception_upper": "1980-01-01",
    "iso:country": "GB",
    "wof:name": "ME15 9AH",
    "wof:placetype": "postalcode"
  },
  "geometry": {"coordinates":[0.534818,51.254404],"type":"Point"}
}
