{
  "type": "Feature",
  "properties": {
    "date:inception_lower": "2020-11-01",
    "date:inception_upper": "2020-11-01",
    "iso:country": "GB",
    "wof:name": "EH54 6GN",
    "wof:placetype": "postalcode"
  },
  "geometry": {"coordinates":[-3.513997,55.897073],"type":"Point"}
}
