{
  "type": "Feature",
  "properties": {
    "iso:country": "GB",
    "wof:name": "YO8 9AP",
    "wof:placetype": "postalcode"
  },
  "geometry": {"coordinates":[-1.086911,53.775996],"type":"Point"}
}
