{
  "type": "Feature",
  "properties": {
    "iso:country":"GB",
    "wof:name":"YO8 9AP",
    "wof:placetype":"postalcode"
},
  "geometry": {"coordinates":[-1.08691106579891,53.77599570442296],"type":"Point"}
}