{
  "type": "Feature",
  "properties": {
    "iso:country":"GB",
    "wof:name":"E8 1FG",
    "wof:placetype":"postalcode"
},
  "geometry": {"coordinates":[-0.06872185668389,51.54776204637833],"type":"Point"}
}