{
  "type": "Feature",
  "properties": {
    "iso:country":"GB",
    "wof:name":"CF36 5HT",
    "wof:placetype":"postalcode"
},
  "geometry": {"coordinates":[-3.69476517287739,51.4837959324469],"type":"Point"}
}