{
  "type": "Feature",
  "properties": {
    "date:inception_lower": "1980-01-01",
    "date:inception_upper": "1980-01-01",
    "iso:country": "GB",
    "wof:name": "CF36 5HT",
    "wof:placetype": "postalcode"
  },
  "geometry": {"coordinates":[-3.694765,51.483796],"type":"Point"}
}
