{
  "type": "Feature",
  "properties": {
    "iso:country": "GB",
    "wof:name": "OX33 1UX",
    "wof:placetype": "postalcode"
  },
  "geometry": {"coordinates":[-1.127256,51.743309],"type":"Point"}
}
