{
  "type": "Feature",
  "properties": {
    "iso:country":"GB",
    "wof:name":"HD1 5EB",
    "wof:placetype":"postalcode"
},
  "geometry": {"coordinates":[-1.78543379691177,53.65699588352552],"type":"Point"}
}