{
  "type": "Feature",
  "properties": {
    "iso:country": "GB",
    "wof:name": "HD1 5EB",
    "wof:placetype": "postalcode"
  },
  "geometry": {"coordinates":[-1.785814,53.65694],"type":"Point"}
}
