{
  "type": "Feature",
  "properties": {
    "iso:country": "GB",
    "wof:name": "CO15 2DN",
    "wof:placetype": "postalcode"
  },
  "geometry": {"coordinates":[1.118275,51.787594],"type":"Point"}
}
