{
  "type": "Feature",
  "properties": {
    "date:inception_lower": "1980-01-01",
    "date:inception_upper": "1980-01-01",
    "iso:country": "GB",
    "wof:name": "ST14 8LL",
    "wof:placetype": "postalcode"
  },
  "geometry": {"coordinates":[-1.798863,52.871418],"type":"Point"}
}
