{
  "type": "Feature",
  "properties": {
    "iso:country":"GB",
    "wof:name":"ST14 8LL",
    "wof:placetype":"postalcode"
},
  "geometry": {"coordinates":[-1.79886336688577,52.87141787129044],"type":"Point"}
}