{
  "type": "Feature",
  "properties": {
    "iso:country":"GB",
    "wof:name":"L35 4LP",
    "wof:placetype":"postalcode"
},
  "geometry": {"coordinates":[-2.76381279376119,53.41630965383165],"type":"Point"}
}