{
  "type": "Feature",
  "properties": {
    "date:inception_lower": "1980-01-01",
    "date:inception_upper": "1980-01-01",
    "iso:country": "GB",
    "wof:name": "HD7 6LE",
    "wof:placetype": "postalcode"
  },
  "geometry": {"coordinates":[-1.915211,53.604954],"type":"Point"}
}
