{
  "type": "Feature",
  "properties": {
    "iso:country": "GB",
    "wof:name": "CV6 7BZ",
    "wof:placetype": "postalcode"
  },
  "geometry": {"coordinates":[-1.476742,52.437074],"type":"Point"}
}
