{
  "type": "Feature",
  "properties": {
    "iso:country":"GB",
    "wof:name":"CV6 7BZ",
    "wof:placetype":"postalcode"
},
  "geometry": {"coordinates":[-1.47674173496147,52.43707434800353],"type":"Point"}
}