{
  "type": "Feature",
  "properties": {
    "iso:country":"GB",
    "wof:name":"S41 7PA",
    "wof:placetype":"postalcode"
},
  "geometry": {"coordinates":[-1.43081274333449,53.24056223668335],"type":"Point"}
}