{
  "type": "Feature",
  "properties": {
    "iso:country":"GB",
    "wof:name":"EX8 1JW",
    "wof:placetype":"postalcode"
},
  "geometry": {"coordinates":[-3.40710399971409,50.61948908639364],"type":"Point"}
}