{
  "type": "Feature",
  "properties": {
    "iso:country":"GB",
    "wof:name":"TF10 7TN",
    "wof:placetype":"postalcode"
},
  "geometry": {"coordinates":[-2.36911414375843,52.77064570528064],"type":"Point"}
}