{
  "type": "Feature",
  "properties": {
    "iso:country":"GB",
    "wof:name":"S18 1PA",
    "wof:placetype":"postalcode"
},
  "geometry": {"coordinates":[-1.48009399211299,53.30866206093264],"type":"Point"}
}