{
  "type": "Feature",
  "properties": {
    "iso:country": "GB",
    "wof:name": "YO22 5DF",
    "wof:placetype": "postalcode"
  },
  "geometry": {"coordinates":[-0.660597,54.453544],"type":"Point"}
}
