{
  "type": "Feature",
  "properties": {
    "iso:country":"GB",
    "wof:name":"YO22 5DF",
    "wof:placetype":"postalcode"
},
  "geometry": {"coordinates":[-0.66059695163926,54.4535435538798],"type":"Point"}
}