{
  "type": "Feature",
  "properties": {
    "date:inception_lower":"1980-01-01",
    "date:inception_upper":"1980-01-31",
    "iso:country":"GB",
    "wof:name":"YO22 5DF",
    "wof:placetype":"postalcode"
},
  "geometry": {"coordinates":[-0.660597,54.453544],"type":"Point"}
}