{
  "type": "Feature",
  "properties": {
    "iso:country":"GB",
    "wof:name":"CW5 6HG",
    "wof:placetype":"postalcode"
},
  "geometry": {"coordinates":[-2.51116181360418,53.07424715386198],"type":"Point"}
}