{
  "type": "Feature",
  "properties": {
    "iso:country": "GB",
    "wof:name": "CW5 6HG",
    "wof:placetype": "postalcode"
  },
  "geometry": {"coordinates":[-2.511162,53.074247],"type":"Point"}
}
