{
  "type": "Feature",
  "properties": {
    "date:inception_lower": "1993-08-01",
    "date:inception_upper": "1993-08-01",
    "iso:country": "GB",
    "wof:name": "WS4 2BS",
    "wof:placetype": "postalcode"
  },
  "geometry": {"coordinates":[-1.977991,52.593502],"type":"Point"}
}
