{
  "type": "Feature",
  "properties": {
    "iso:country":"GB",
    "wof:name":"WS4 2BS",
    "wof:placetype":"postalcode"
},
  "geometry": {"coordinates":[-1.97799075355734,52.59350232600811],"type":"Point"}
}