{
  "type": "Feature",
  "properties": {
    "iso:country":"GB",
    "wof:name":"HA7 3SE",
    "wof:placetype":"postalcode"
},
  "geometry": {"coordinates":[-0.32118105612968,51.61469048785102],"type":"Point"}
}