{
  "type": "Feature",
  "properties": {
    "iso:country":"GB",
    "wof:name":"B25 8PB",
    "wof:placetype":"postalcode"
},
  "geometry": {"coordinates":[-1.82368603914286,52.46722732311206],"type":"Point"}
}