{
  "type": "Feature",
  "properties": {
    "date:inception_lower": "1980-01-01",
    "date:inception_upper": "1980-01-01",
    "iso:country": "GB",
    "wof:name": "NW1 1TT",
    "wof:placetype": "postalcode"
  },
  "geometry": {"coordinates":[-0.134183,51.535539],"type":"Point"}
}
