{
  "type": "Feature",
  "properties": {
    "iso:country":"GB",
    "wof:name":"NW1 1TT",
    "wof:placetype":"postalcode"
},
  "geometry": {"coordinates":[-0.13418314017352,51.53553949796166],"type":"Point"}
}