{
  "type": "Feature",
  "properties": {
    "iso:country":"GB",
    "wof:name":"LA9 6HJ",
    "wof:placetype":"postalcode"
},
  "geometry": {"coordinates":[-2.73200900378805,54.33586169313431],"type":"Point"}
}