{
  "type": "Feature",
  "properties": {
    "iso:country":"GB",
    "wof:name":"B32 2NR",
    "wof:placetype":"postalcode"
},
  "geometry": {"coordinates":[-1.97736758353463,52.45463536972474],"type":"Point"}
}