{
  "type": "Feature",
  "properties": {
    "iso:country":"GB",
    "wof:name":"PO7 6JY",
    "wof:placetype":"postalcode"
},
  "geometry": {"coordinates":[-1.06389149870393,50.91714551958925],"type":"Point"}
}