{
  "type": "Feature",
  "properties": {
    "iso:country":"GB",
    "wof:name":"B68 9RU",
    "wof:placetype":"postalcode"
},
  "geometry": {"coordinates":[-1.99720199549788,52.49413037997839],"type":"Point"}
}