{
  "type": "Feature",
  "properties": {
    "iso:country": "GB",
    "wof:name": "S17 4RL",
    "wof:placetype": "postalcode"
  },
  "geometry": {"coordinates":[-1.49721,53.322066],"type":"Point"}
}
