{
  "type": "Feature",
  "properties": {
    "iso:country":"GB",
    "wof:name":"S17 4RL",
    "wof:placetype":"postalcode"
},
  "geometry": {"coordinates":[-1.49719576598944,53.32204771748631],"type":"Point"}
}