{
  "type": "Feature",
  "properties": {
    "iso:country":"GB",
    "wof:name":"NR14 6FP",
    "wof:placetype":"postalcode"
},
  "geometry": {"coordinates":[1.49580574142361,52.51577787059492],"type":"Point"}
}