{
  "type": "Feature",
  "properties": {
    "iso:country":"GB",
    "wof:name":"BS2 9TJ",
    "wof:placetype":"postalcode"
},
  "geometry": {"coordinates":[-2.57287361111019,51.46796728532777],"type":"Point"}
}