{
  "type": "Feature",
  "properties": {
    "iso:country":"GB",
    "wof:name":"DT2 0HY",
    "wof:placetype":"postalcode"
},
  "geometry": {"coordinates":[-2.58149574228725,50.79565512262052],"type":"Point"}
}