{
  "type": "Feature",
  "properties": {
    "date:inception_lower": "1980-01-01",
    "date:inception_upper": "1980-01-01",
    "iso:country": "GB",
    "wof:name": "NR30 3JF",
    "wof:placetype": "postalcode"
  },
  "geometry": {"coordinates":[1.7379,52.599227],"type":"Point"}
}
