{
  "type": "Feature",
  "properties": {
    "iso:country":"GB",
    "wof:name":"NR30 3JF",
    "wof:placetype":"postalcode"
},
  "geometry": {"coordinates":[1.73789976493956,52.59922697510874],"type":"Point"}
}