{
  "type": "Feature",
  "properties": {
    "iso:country": "GB",
    "wof:name": "NR30 3JF",
    "wof:placetype": "postalcode"
  },
  "geometry": {"coordinates":[1.7379,52.599227],"type":"Point"}
}
