{
  "type": "Feature",
  "properties": {
    "date:inception_lower": "2019-03-01",
    "date:inception_upper": "2019-03-01",
    "iso:country": "GB",
    "wof:name": "BH4 0GU",
    "wof:placetype": "postalcode"
  },
  "geometry": {"coordinates":[-1.90239,50.721911],"type":"Point"}
}
