{
  "type": "Feature",
  "properties": {
    "iso:country":"GB",
    "wof:name":"NE12 7AW",
    "wof:placetype":"postalcode"
},
  "geometry": {"coordinates":[-1.56446718519385,55.02771165424359],"type":"Point"}
}