{
  "type": "Feature",
  "properties": {
    "iso:country": "GB",
    "wof:name": "CF32 0QL",
    "wof:placetype": "postalcode"
  },
  "geometry": {"coordinates":[-3.63436,51.46363],"type":"Point"}
}
