{
  "type": "Feature",
  "properties": {
    "iso:country":"GB",
    "wof:name":"BN11 3AY",
    "wof:placetype":"postalcode"
},
  "geometry": {"coordinates":[-0.3704484577661,50.8099816576756],"type":"Point"}
}