{
  "type": "Feature",
  "properties": {
    "date:inception_lower":"1980-01-01",
    "date:inception_upper":"1980-01-31",
    "iso:country":"GB",
    "wof:name":"SW16 2JQ",
    "wof:placetype":"postalcode"
},
  "geometry": {"coordinates":[-0.115588,51.435479],"type":"Point"}
}