{
  "type": "Feature",
  "properties": {
    "iso:country":"GB",
    "wof:name":"SW16 2JQ",
    "wof:placetype":"postalcode"
},
  "geometry": {"coordinates":[-0.11558834922741,51.43547865819836],"type":"Point"}
}