{
  "type": "Feature",
  "properties": {
    "iso:country":"GB",
    "wof:name":"WD23 2DY",
    "wof:placetype":"postalcode"
},
  "geometry": {"coordinates":[-0.37444078412659,51.66505830592575],"type":"Point"}
}