{
  "type": "Feature",
  "properties": {
    "date:inception_lower": "1980-01-01",
    "date:inception_upper": "1980-01-01",
    "iso:country": "GB",
    "wof:name": "KT18 5AJ",
    "wof:placetype": "postalcode"
  },
  "geometry": {"coordinates":[-0.266022,51.331706],"type":"Point"}
}
