{
  "type": "Feature",
  "properties": {
    "iso:country": "GB",
    "wof:name": "TS20 2AH",
    "wof:placetype": "postalcode"
  },
  "geometry": {"coordinates":[-1.310478,54.574476],"type":"Point"}
}
