{
  "type": "Feature",
  "properties": {
    "iso:country":"GB",
    "wof:name":"M8 5UP",
    "wof:placetype":"postalcode"
},
  "geometry": {"coordinates":[-2.23208511616652,53.51320338551388],"type":"Point"}
}