{
  "type": "Feature",
  "properties": {
    "iso:country":"GB",
    "wof:name":"PR4 5NJ",
    "wof:placetype":"postalcode"
},
  "geometry": {"coordinates":[-2.78514509602695,53.73233422630571],"type":"Point"}
}