{
  "type": "Feature",
  "properties": {
    "iso:country":"GB",
    "wof:name":"ST5 5HJ",
    "wof:placetype":"postalcode"
},
  "geometry": {"coordinates":[-2.29138047206583,52.98666131499875],"type":"Point"}
}