{
  "type": "Feature",
  "properties": {
    "iso:country": "GB",
    "wof:name": "ST5 5HJ",
    "wof:placetype": "postalcode"
  },
  "geometry": {"coordinates":[-2.29138,52.986661],"type":"Point"}
}
