{
  "type": "Feature",
  "properties": {
    "date:inception_lower": "1980-01-01",
    "date:inception_upper": "1980-01-01",
    "iso:country": "GB",
    "wof:name": "IP13 0EL",
    "wof:placetype": "postalcode"
  },
  "geometry": {"coordinates":[1.3197,52.185729],"type":"Point"}
}
