{
  "type": "Feature",
  "properties": {
    "iso:country":"GB",
    "wof:name":"IP13 0EL",
    "wof:placetype":"postalcode"
},
  "geometry": {"coordinates":[1.31984270406289,52.18568009257229],"type":"Point"}
}