{
  "type": "Feature",
  "properties": {
    "iso:country":"GB",
    "wof:name":"CO12 3AS",
    "wof:placetype":"postalcode"
},
  "geometry": {"coordinates":[1.28244746372081,51.93857749102342],"type":"Point"}
}