{
  "type": "Feature",
  "properties": {
    "iso:country": "GB",
    "wof:name": "NE38 9JH",
    "wof:placetype": "postalcode"
  },
  "geometry": {"coordinates":[-1.559985,54.878325],"type":"Point"}
}
