{
  "type": "Feature",
  "properties": {
    "iso:country": "GB",
    "wof:name": "KT24 5HF",
    "wof:placetype": "postalcode"
  },
  "geometry": {"coordinates":[-0.42354,51.292394],"type":"Point"}
}
