{
  "type": "Feature",
  "properties": {
    "iso:country":"GB",
    "wof:name":"KT24 5HF",
    "wof:placetype":"postalcode"
},
  "geometry": {"coordinates":[-0.42356301592674,51.2923964144311],"type":"Point"}
}