{
  "type": "Feature",
  "properties": {
    "date:inception_lower": "1993-01-01",
    "date:inception_upper": "1993-01-01",
    "iso:country": "GB",
    "wof:name": "CF63 4HF",
    "wof:placetype": "postalcode"
  },
  "geometry": {"coordinates":[-3.26994,51.40529],"type":"Point"}
}
