{
  "type": "Feature",
  "properties": {
    "iso:country":"GB",
    "wof:name":"CF63 4HF",
    "wof:placetype":"postalcode"
},
  "geometry": {"coordinates":[-3.2699399383013,51.4052896162514],"type":"Point"}
}