{
  "type": "Feature",
  "properties": {
    "iso:country":"GB",
    "wof:name":"SW3 5LA",
    "wof:placetype":"postalcode"
},
  "geometry": {"coordinates":[-0.1710721854386,51.48539386124129],"type":"Point"}
}