{
  "type": "Feature",
  "properties": {
    "date:inception_lower": "2020-05-01",
    "date:inception_upper": "2020-05-01",
    "iso:country": "GB",
    "wof:name": "WV9 5FD",
    "wof:placetype": "postalcode"
  },
  "geometry": {"coordinates":[-2.137299,52.664081],"type":"Point"}
}
