{
  "type": "Feature",
  "properties": {
    "iso:country": "GB",
    "wof:name": "NN16 0BL",
    "wof:placetype": "postalcode"
  },
  "geometry": {"coordinates":[-0.727361,52.400134],"type":"Point"}
}
