{
  "type": "Feature",
  "properties": {
    "iso:country":"GB",
    "wof:name":"CF33 6EG",
    "wof:placetype":"postalcode"
},
  "geometry": {"coordinates":[-3.68114234190666,51.53550906805236],"type":"Point"}
}