{
  "type": "Feature",
  "properties": {
    "date:inception_lower":"1996-12-01",
    "date:inception_upper":"1996-12-31",
    "iso:country":"GB",
    "wof:name":"CF33 6EG",
    "wof:placetype":"postalcode"
},
  "geometry": {"coordinates":[-3.681142,51.535509],"type":"Point"}
}