{
  "type": "Feature",
  "properties": {
    "iso:country":"GB",
    "wof:name":"M40 1LT",
    "wof:placetype":"postalcode"
},
  "geometry": {"coordinates":[-2.17602001372169,53.49907953318137],"type":"Point"}
}