{
  "type": "Feature",
  "properties": {
    "iso:country":"GB",
    "wof:name":"WA16 8HX",
    "wof:placetype":"postalcode"
},
  "geometry": {"coordinates":[-2.36547480963843,53.30371408018512],"type":"Point"}
}