{
  "type": "Feature",
  "properties": {
    "date:inception_lower":"1980-01-01",
    "date:inception_upper":"1980-01-31",
    "iso:country":"GB",
    "wof:name":"CM7 5TA",
    "wof:placetype":"postalcode"
},
  "geometry": {"coordinates":[0.548478,51.89645],"type":"Point"}
}