{
  "type": "Feature",
  "properties": {
    "iso:country":"GB",
    "wof:name":"CM7 5TA",
    "wof:placetype":"postalcode"
},
  "geometry": {"coordinates":[0.54847796781208,51.89644987195822],"type":"Point"}
}