{
  "type": "Feature",
  "properties": {
    "iso:country":"GB",
    "wof:name":"PL19 9DT",
    "wof:placetype":"postalcode"
},
  "geometry": {"coordinates":[-4.14539452448728,50.53766944993068],"type":"Point"}
}