{
  "type": "Feature",
  "properties": {
    "iso:country": "GB",
    "wof:name": "DD11 2EA",
    "wof:placetype": "postalcode"
  },
  "geometry": {"coordinates":[-2.605193,56.558748],"type":"Point"}
}
