{
  "type": "Feature",
  "properties": {
    "iso:country":"GB",
    "wof:name":"B79 7RJ",
    "wof:placetype":"postalcode"
},
  "geometry": {"coordinates":[-1.69758973089737,52.63557769433025],"type":"Point"}
}