{
  "type": "Feature",
  "properties": {
    "date:inception_lower": "1980-01-01",
    "date:inception_upper": "1980-01-01",
    "iso:country": "GB",
    "wof:name": "B79 7RJ",
    "wof:placetype": "postalcode"
  },
  "geometry": {"coordinates":[-1.697493,52.635837],"type":"Point"}
}
