{
  "type": "Feature",
  "properties": {
    "iso:country":"GB",
    "wof:name":"OL9 8DT",
    "wof:placetype":"postalcode"
},
  "geometry": {"coordinates":[-2.15982880720673,53.52285865184233],"type":"Point"}
}