{
  "type": "Feature",
  "properties": {
    "iso:country":"GB",
    "wof:name":"SN10 2RL",
    "wof:placetype":"postalcode"
},
  "geometry": {"coordinates":[-1.96777628995379,51.36456650498102],"type":"Point"}
}