{
  "type": "Feature",
  "properties": {
    "iso:country": "GB",
    "wof:name": "NE29 0JF",
    "wof:placetype": "postalcode"
  },
  "geometry": {"coordinates":[-1.457174,55.008886],"type":"Point"}
}
