{
  "type": "Feature",
  "properties": {
    "iso:country":"GB",
    "wof:name":"NE29 0JF",
    "wof:placetype":"postalcode"
},
  "geometry": {"coordinates":[-1.45717445569312,55.00888578893578],"type":"Point"}
}