{
  "type": "Feature",
  "properties": {
    "date:inception_lower":"1980-01-01",
    "date:inception_upper":"1980-01-31",
    "iso:country":"GB",
    "wof:name":"NE29 0JF",
    "wof:placetype":"postalcode"
},
  "geometry": {"coordinates":[-1.457174,55.008886],"type":"Point"}
}