{
  "type": "Feature",
  "properties": {
    "iso:country": "GB",
    "wof:name": "SY23 2BF",
    "wof:placetype": "postalcode"
  },
  "geometry": {"coordinates":[-4.078128,52.417158],"type":"Point"}
}
