{
  "type": "Feature",
  "properties": {
    "date:inception_lower":"2014-07-01",
    "date:inception_upper":"2014-07-31",
    "iso:country":"GB",
    "wof:name":"SY23 2BF",
    "wof:placetype":"postalcode"
},
  "geometry": {"coordinates":[-4.078128,52.417158],"type":"Point"}
}