{
  "type": "Feature",
  "properties": {
    "iso:country":"GB",
    "wof:name":"IG10 4NG",
    "wof:placetype":"postalcode"
},
  "geometry": {"coordinates":[0.05127492196384,51.64123594326511],"type":"Point"}
}