{
  "type": "Feature",
  "properties": {
    "date:inception_lower":"1980-01-01",
    "date:inception_upper":"1980-01-31",
    "iso:country":"GB",
    "wof:name":"IG10 4NG",
    "wof:placetype":"postalcode"
},
  "geometry": {"coordinates":[0.051275,51.641236],"type":"Point"}
}