{
  "type": "Feature",
  "properties": {
    "iso:country":"GB",
    "wof:name":"FY4 5DX",
    "wof:placetype":"postalcode"
},
  "geometry": {"coordinates":[-3.01308919696892,53.77845997491411],"type":"Point"}
}