{
  "type": "Feature",
  "properties": {
    "date:inception_lower": "1996-12-01",
    "date:inception_upper": "1996-12-01",
    "iso:country": "GB",
    "wof:name": "WA4 5FF",
    "wof:placetype": "postalcode"
  },
  "geometry": {"coordinates":[-2.572863,53.344399],"type":"Point"}
}
