{
  "type": "Feature",
  "properties": {
    "iso:country": "GB",
    "wof:name": "WA4 5FF",
    "wof:placetype": "postalcode"
  },
  "geometry": {"coordinates":[-2.572863,53.344399],"type":"Point"}
}
