{
  "type": "Feature",
  "properties": {
    "iso:country":"GB",
    "wof:name":"IG1 4DP",
    "wof:placetype":"postalcode"
},
  "geometry": {"coordinates":[0.07054192239594,51.55904666219242],"type":"Point"}
}