{
  "type": "Feature",
  "properties": {
    "iso:country":"GB",
    "wof:name":"SO22 6DF",
    "wof:placetype":"postalcode"
},
  "geometry": {"coordinates":[-1.33107307843218,51.07324538897443],"type":"Point"}
}