{
  "type": "Feature",
  "properties": {
    "iso:country": "GB",
    "wof:name": "SO14 3AJ",
    "wof:placetype": "postalcode"
  },
  "geometry": {"coordinates":[-1.394461,50.896864],"type":"Point"}
}
