{
  "type": "Feature",
  "properties": {
    "iso:country":"GB",
    "wof:name":"CM16 4LR",
    "wof:placetype":"postalcode"
},
  "geometry": {"coordinates":[0.11156450261791,51.69826828343733],"type":"Point"}
}