{
  "type": "Feature",
  "properties": {
    "iso:country": "GB",
    "wof:name": "SM6 9RD",
    "wof:placetype": "postalcode"
  },
  "geometry": {"coordinates":[-0.13287,51.352177],"type":"Point"}
}
