{
  "type": "Feature",
  "properties": {
    "iso:country": "GB",
    "wof:name": "KT18 6LZ",
    "wof:placetype": "postalcode"
  },
  "geometry": {"coordinates":[-0.271844,51.27431],"type":"Point"}
}
