{
  "type": "Feature",
  "properties": {
    "iso:country":"GB",
    "wof:name":"KT18 6LZ",
    "wof:placetype":"postalcode"
},
  "geometry": {"coordinates":[-0.27105683116358,51.27454260317829],"type":"Point"}
}