{
  "type": "Feature",
  "properties": {
    "iso:country":"GB",
    "wof:name":"SO53 3BA",
    "wof:placetype":"postalcode"
},
  "geometry": {"coordinates":[-1.37899583741029,50.9745133466515],"type":"Point"}
}