{
  "type": "Feature",
  "properties": {
    "iso:country": "GB",
    "wof:name": "SE6 4HP",
    "wof:placetype": "postalcode"
  },
  "geometry": {"coordinates":[-0.019622,51.447134],"type":"Point"}
}
