{
  "type": "Feature",
  "properties": {
    "iso:country":"GB",
    "wof:name":"SE6 4HP",
    "wof:placetype":"postalcode"
},
  "geometry": {"coordinates":[-0.01962205030276,51.44713381965665],"type":"Point"}
}