{
  "type": "Feature",
  "properties": {
    "iso:country":"GB",
    "wof:name":"GL53 9JD",
    "wof:placetype":"postalcode"
},
  "geometry": {"coordinates":[-2.06237457695575,51.87824380759609],"type":"Point"}
}