{
  "type": "Feature",
  "properties": {
    "iso:country":"GB",
    "wof:name":"E14 4HD",
    "wof:placetype":"postalcode"
},
  "geometry": {"coordinates":[-0.02613446508677,51.50633463829357],"type":"Point"}
}