{
  "type": "Feature",
  "properties": {
    "iso:country":"GB",
    "wof:name":"PE38 9HE",
    "wof:placetype":"postalcode"
},
  "geometry": {"coordinates":[0.36932967065504,52.60767590509271],"type":"Point"}
}