{
  "type": "Feature",
  "properties": {
    "iso:country": "GB",
    "wof:name": "PE38 9HE",
    "wof:placetype": "postalcode"
  },
  "geometry": {"coordinates":[0.36933,52.607676],"type":"Point"}
}
