{
  "type": "Feature",
  "properties": {
    "iso:country": "GB",
    "wof:name": "AL5 2QG",
    "wof:placetype": "postalcode"
  },
  "geometry": {"coordinates":[-0.361889,51.817413],"type":"Point"}
}
