{
  "type": "Feature",
  "properties": {
    "iso:country":"GB",
    "wof:name":"BH9 2NZ",
    "wof:placetype":"postalcode"
},
  "geometry": {"coordinates":[-1.88097073071741,50.74222633001215],"type":"Point"}
}