{
  "type": "Feature",
  "properties": {
    "iso:country":"GB",
    "wof:name":"BL6 5LX",
    "wof:placetype":"postalcode"
},
  "geometry": {"coordinates":[-2.58754626682439,53.59577460498471],"type":"Point"}
}