{
  "type": "Feature",
  "properties": {
    "date:inception_lower": "1981-06-01",
    "date:inception_upper": "1981-06-01",
    "iso:country": "GB",
    "wof:name": "BL6 5LX",
    "wof:placetype": "postalcode"
  },
  "geometry": {"coordinates":[-2.587546,53.595775],"type":"Point"}
}
