{
  "type": "Feature",
  "properties": {
    "iso:country": "GB",
    "wof:name": "BL6 5LX",
    "wof:placetype": "postalcode"
  },
  "geometry": {"coordinates":[-2.587546,53.595775],"type":"Point"}
}
