{
  "type": "Feature",
  "properties": {
    "iso:country":"GB",
    "wof:name":"SE28 0LT",
    "wof:placetype":"postalcode"
},
  "geometry": {"coordinates":[0.09171107371635,51.50096455924174],"type":"Point"}
}