{
  "type": "Feature",
  "properties": {
    "date:inception_lower": "2007-09-01",
    "date:inception_upper": "2007-09-01",
    "iso:country": "GB",
    "wof:name": "SA1 7FG",
    "wof:placetype": "postalcode"
  },
  "geometry": {"coordinates":[-3.929996,51.639282],"type":"Point"}
}
