{
  "type": "Feature",
  "properties": {
    "date:inception_lower": "2019-01-01",
    "date:inception_upper": "2019-01-01",
    "iso:country": "GB",
    "wof:name": "IP30 9TB",
    "wof:placetype": "postalcode"
  },
  "geometry": {"coordinates":[0.909978,52.23974],"type":"Point"}
}
