{
  "type": "Feature",
  "properties": {
    "date:inception_lower":"2019-01-01",
    "date:inception_upper":"2019-01-31",
    "iso:country":"GB",
    "wof:name":"IP30 9TB",
    "wof:placetype":"postalcode"
},
  "geometry": {"coordinates":[0.910334,52.239812],"type":"Point"}
}