{
  "type": "Feature",
  "properties": {
    "iso:country": "GB",
    "wof:name": "IP30 9TB",
    "wof:placetype": "postalcode"
  },
  "geometry": {"coordinates":[0.910334,52.239812],"type":"Point"}
}
