{
  "type": "Feature",
  "properties": {
    "date:inception_lower": "2018-03-01",
    "date:inception_upper": "2018-03-01",
    "iso:country": "GB",
    "wof:name": "DE6 9DR",
    "wof:placetype": "postalcode"
  },
  "geometry": {"coordinates":[-1.712007,53.006357],"type":"Point"}
}
