{
  "type": "Feature",
  "properties": {
    "iso:country":"GB",
    "wof:name":"GL10 3PX",
    "wof:placetype":"postalcode"
},
  "geometry": {"coordinates":[-2.26409503056846,51.72488239648474],"type":"Point"}
}