{
  "type": "Feature",
  "properties": {
    "iso:country": "GB",
    "wof:name": "GL10 3PX",
    "wof:placetype": "postalcode"
  },
  "geometry": {"coordinates":[-2.264095,51.724882],"type":"Point"}
}
