{
  "type": "Feature",
  "properties": {
    "date:inception_lower":"1980-01-01",
    "date:inception_upper":"1980-01-31",
    "iso:country":"GB",
    "wof:name":"GL10 3PX",
    "wof:placetype":"postalcode"
},
  "geometry": {"coordinates":[-2.264095,51.724882],"type":"Point"}
}