{
  "type": "Feature",
  "properties": {
    "iso:country":"GB",
    "wof:name":"BR1 2QF",
    "wof:placetype":"postalcode"
},
  "geometry": {"coordinates":[0.03613672995446,51.40358843245538],"type":"Point"}
}