{
  "type": "Feature",
  "properties": {
    "iso:country":"GB",
    "wof:name":"KY12 9YG",
    "wof:placetype":"postalcode"
},
  "geometry": {"coordinates":[-3.4769013632432,56.07963456608596],"type":"Point"}
}