{
  "type": "Feature",
  "properties": {
    "iso:country": "GB",
    "wof:name": "KY12 9YG",
    "wof:placetype": "postalcode"
  },
  "geometry": {"coordinates":[-3.476901,56.079635],"type":"Point"}
}
