{
  "type": "Feature",
  "properties": {
    "iso:country": "GB",
    "wof:name": "PO19 5DW",
    "wof:placetype": "postalcode"
  },
  "geometry": {"coordinates":[-0.782852,50.850229],"type":"Point"}
}
