{
  "type": "Feature",
  "properties": {
    "date:inception_lower":"1980-01-01",
    "date:inception_upper":"1980-01-31",
    "iso:country":"GB",
    "wof:name":"L35 0LN",
    "wof:placetype":"postalcode"
},
  "geometry": {"coordinates":[-2.770395,53.416717],"type":"Point"}
}