{
  "type": "Feature",
  "properties": {
    "iso:country":"GB",
    "wof:name":"ME15 8AJ",
    "wof:placetype":"postalcode"
},
  "geometry": {"coordinates":[0.55056275940078,51.25247034879143],"type":"Point"}
}