{
  "type": "Feature",
  "properties": {
    "iso:country":"GB",
    "wof:name":"PL9 9BP",
    "wof:placetype":"postalcode"
},
  "geometry": {"coordinates":[-4.08648027242475,50.35790284201567],"type":"Point"}
}