{
  "type": "Feature",
  "properties": {
    "iso:country": "GB",
    "wof:name": "PL9 9BP",
    "wof:placetype": "postalcode"
  },
  "geometry": {"coordinates":[-4.08644,50.357925],"type":"Point"}
}
