{
  "type": "Feature",
  "properties": {
    "iso:country":"GB",
    "wof:name":"MK5 7LR",
    "wof:placetype":"postalcode"
},
  "geometry": {"coordinates":[-0.79329172899625,52.00811318169514],"type":"Point"}
}