{
  "type": "Feature",
  "properties": {
    "iso:country":"GB",
    "wof:name":"UB9 6NJ",
    "wof:placetype":"postalcode"
},
  "geometry": {"coordinates":[-0.4733962302064,51.60328043780726],"type":"Point"}
}