{
  "type": "Feature",
  "properties": {
    "iso:country":"GB",
    "wof:name":"HU17 0QH",
    "wof:placetype":"postalcode"
},
  "geometry": {"coordinates":[-0.41007487253309,53.84269487875019],"type":"Point"}
}