{
  "type": "Feature",
  "properties": {
    "date:inception_lower": "2005-08-01",
    "date:inception_upper": "2005-08-01",
    "iso:country": "GB",
    "wof:name": "S72 7NA",
    "wof:placetype": "postalcode"
  },
  "geometry": {"coordinates":[-1.378951,53.5724],"type":"Point"}
}
