{
  "type": "Feature",
  "properties": {
    "iso:country":"GB",
    "wof:name":"S72 7NA",
    "wof:placetype":"postalcode"
},
  "geometry": {"coordinates":[-1.3789506773674,53.57239993405508],"type":"Point"}
}