{
  "type": "Feature",
  "properties": {
    "iso:country": "GB",
    "wof:name": "S72 7NA",
    "wof:placetype": "postalcode"
  },
  "geometry": {"coordinates":[-1.378951,53.5724],"type":"Point"}
}
