{
  "type": "Feature",
  "properties": {
    "iso:country": "GB",
    "wof:name": "G11 7LL",
    "wof:placetype": "postalcode"
  },
  "geometry": {"coordinates":[-4.31751,55.877003],"type":"Point"}
}
