{
  "type": "Feature",
  "properties": {
    "iso:country":"GB",
    "wof:name":"PE21 6PY",
    "wof:placetype":"postalcode"
},
  "geometry": {"coordinates":[-0.02561551018057,52.98060623233043],"type":"Point"}
}