{
  "type": "Feature",
  "properties": {
    "date:inception_lower":"2009-12-01",
    "date:inception_upper":"2009-12-31",
    "iso:country":"GB",
    "wof:name":"PR8 4BN",
    "wof:placetype":"postalcode"
},
  "geometry": {"coordinates":[-3.003482,53.630228],"type":"Point"}
}