{
  "type": "Feature",
  "properties": {
    "iso:country": "GB",
    "wof:name": "PR8 4BN",
    "wof:placetype": "postalcode"
  },
  "geometry": {"coordinates":[-3.003482,53.630228],"type":"Point"}
}
