{
  "type": "Feature",
  "properties": {
    "iso:country":"GB",
    "wof:name":"PR8 4BN",
    "wof:placetype":"postalcode"
},
  "geometry": {"coordinates":[-3.00353091014919,53.63024797438887],"type":"Point"}
}