{
  "type": "Feature",
  "properties": {
    "date:inception_lower":"1991-01-01",
    "date:inception_upper":"1991-01-31",
    "iso:country":"GB",
    "wof:name":"PE15 0UU",
    "wof:placetype":"postalcode"
},
  "geometry": {"coordinates":[-0.024464,52.496899],"type":"Point"}
}