{
  "type": "Feature",
  "properties": {
    "iso:country":"GB",
    "wof:name":"PE15 0UU",
    "wof:placetype":"postalcode"
},
  "geometry": {"coordinates":[-0.02446431609067,52.49689909419986],"type":"Point"}
}