{
  "type": "Feature",
  "properties": {
    "iso:country": "GB",
    "wof:name": "PE15 0UU",
    "wof:placetype": "postalcode"
  },
  "geometry": {"coordinates":[-0.024464,52.496899],"type":"Point"}
}
