{
  "type": "Feature",
  "properties": {
    "iso:country": "GB",
    "wof:name": "B98 7RA",
    "wof:placetype": "postalcode"
  },
  "geometry": {"coordinates":[-1.924085,52.289761],"type":"Point"}
}
