{
  "type": "Feature",
  "properties": {
    "iso:country":"GB",
    "wof:name":"B98 7RA",
    "wof:placetype":"postalcode"
},
  "geometry": {"coordinates":[-1.92408487011979,52.28976137433185],"type":"Point"}
}