{
  "type": "Feature",
  "properties": {
    "date:inception_lower": "1980-01-01",
    "date:inception_upper": "1980-01-01",
    "iso:country": "GB",
    "wof:name": "B98 7RA",
    "wof:placetype": "postalcode"
  },
  "geometry": {"coordinates":[-1.924085,52.289761],"type":"Point"}
}
