{
  "type": "Feature",
  "properties": {
    "iso:country":"GB",
    "wof:name":"BA5 1DP",
    "wof:placetype":"postalcode"
},
  "geometry": {"coordinates":[-2.69828117959885,51.22632378413387],"type":"Point"}
}