{
  "type": "Feature",
  "properties": {
    "iso:country": "GB",
    "wof:name": "BA5 1DP",
    "wof:placetype": "postalcode"
  },
  "geometry": {"coordinates":[-2.698281,51.226324],"type":"Point"}
}
