{
  "type": "Feature",
  "properties": {
    "iso:country":"GB",
    "wof:name":"SK8 7EN",
    "wof:placetype":"postalcode"
},
  "geometry": {"coordinates":[-2.18188384280563,53.36524064854173],"type":"Point"}
}