{
  "type": "Feature",
  "properties": {
    "iso:country": "GB",
    "wof:name": "E6 5UD",
    "wof:placetype": "postalcode"
  },
  "geometry": {"coordinates":[0.048932,51.518626],"type":"Point"}
}
