{
  "type": "Feature",
  "properties": {
    "iso:country":"GB",
    "wof:name":"E6 5UD",
    "wof:placetype":"postalcode"
},
  "geometry": {"coordinates":[0.0489318741044,51.51862617506594],"type":"Point"}
}