{
  "type": "Feature",
  "properties": {
    "iso:country": "GB",
    "wof:name": "RG6 3BZ",
    "wof:placetype": "postalcode"
  },
  "geometry": {"coordinates":[-0.917122,51.432683],"type":"Point"}
}
