{
  "type": "Feature",
  "properties": {
    "iso:country":"GB",
    "wof:name":"RG6 3BZ",
    "wof:placetype":"postalcode"
},
  "geometry": {"coordinates":[-0.91712244044944,51.43268283115211],"type":"Point"}
}