{
  "type": "Feature",
  "properties": {
    "iso:country":"GB",
    "wof:name":"M24 2HB",
    "wof:placetype":"postalcode"
},
  "geometry": {"coordinates":[-2.18794567118663,53.5504569208975],"type":"Point"}
}