{
  "type": "Feature",
  "properties": {
    "date:inception_lower": "1999-06-01",
    "date:inception_upper": "1999-06-01",
    "iso:country": "GB",
    "wof:name": "CH46 6EH",
    "wof:placetype": "postalcode"
  },
  "geometry": {"coordinates":[-3.128865,53.397137],"type":"Point"}
}
