{
  "type": "Feature",
  "properties": {
    "iso:country":"GB",
    "wof:name":"CH46 6EH",
    "wof:placetype":"postalcode"
},
  "geometry": {"coordinates":[-3.12886513235427,53.39713689327021],"type":"Point"}
}