{
  "type": "Feature",
  "properties": {
    "iso:country":"GB",
    "wof:name":"DA16 2AA",
    "wof:placetype":"postalcode"
},
  "geometry": {"coordinates":[0.10518595151332,51.46162251399673],"type":"Point"}
}