{
  "type": "Feature",
  "properties": {
    "iso:country":"GB",
    "wof:name":"GU31 5LF",
    "wof:placetype":"postalcode"
},
  "geometry": {"coordinates":[-0.87538788604478,50.97126399833929],"type":"Point"}
}