{
  "type": "Feature",
  "properties": {
    "iso:country":"GB",
    "wof:name":"BA2 6AL",
    "wof:placetype":"postalcode"
},
  "geometry": {"coordinates":[-2.34934926415233,51.37626000358188],"type":"Point"}
}