{
  "type": "Feature",
  "properties": {
    "date:inception_lower": "1980-01-01",
    "date:inception_upper": "1980-01-01",
    "iso:country": "GB",
    "wof:name": "G64 3EJ",
    "wof:placetype": "postalcode"
  },
  "geometry": {"coordinates":[-4.224645,55.913965],"type":"Point"}
}
