{
  "type": "Feature",
  "properties": {
    "iso:country":"GB",
    "wof:name":"G64 3EJ",
    "wof:placetype":"postalcode"
},
  "geometry": {"coordinates":[-4.22464458539473,55.91396528390686],"type":"Point"}
}