{
  "type": "Feature",
  "properties": {
    "iso:country": "GB",
    "wof:name": "BA4 4JT",
    "wof:placetype": "postalcode"
  },
  "geometry": {"coordinates":[-2.534477,51.207453],"type":"Point"}
}
