{
  "type": "Feature",
  "properties": {
    "iso:country":"GB",
    "wof:name":"BA4 4JT",
    "wof:placetype":"postalcode"
},
  "geometry": {"coordinates":[-2.53447689713061,51.20745840220379],"type":"Point"}
}