{
  "type": "Feature",
  "properties": {
    "iso:country":"GB",
    "wof:name":"NE30 3UL",
    "wof:placetype":"postalcode"
},
  "geometry": {"coordinates":[-1.45407294286454,55.02887534761471],"type":"Point"}
}