{
  "type": "Feature",
  "properties": {
    "iso:country":"GB",
    "wof:name":"RG2 9DE",
    "wof:placetype":"postalcode"
},
  "geometry": {"coordinates":[-0.94683901057893,51.40907096874662],"type":"Point"}
}