{
  "type": "Feature",
  "properties": {
    "iso:country":"GB",
    "wof:name":"MK45 4AB",
    "wof:placetype":"postalcode"
},
  "geometry": {"coordinates":[-0.42239970710936,52.02769249057094],"type":"Point"}
}