{
  "type": "Feature",
  "properties": {
    "iso:country": "GB",
    "wof:name": "MK45 4AB",
    "wof:placetype": "postalcode"
  },
  "geometry": {"coordinates":[-0.422455,52.027929],"type":"Point"}
}
