{
  "type": "Feature",
  "properties": {
    "iso:country":"GB",
    "wof:name":"SK5 7HT",
    "wof:placetype":"postalcode"
},
  "geometry": {"coordinates":[-2.1544357500508,53.42943080219035],"type":"Point"}
}