{
  "type": "Feature",
  "properties": {
    "date:inception_lower": "1980-01-01",
    "date:inception_upper": "1980-01-01",
    "iso:country": "GB",
    "wof:name": "L12 9EH",
    "wof:placetype": "postalcode"
  },
  "geometry": {"coordinates":[-2.897474,53.426688],"type":"Point"}
}
