{
  "type": "Feature",
  "properties": {
    "iso:country":"GB",
    "wof:name":"L12 9EH",
    "wof:placetype":"postalcode"
},
  "geometry": {"coordinates":[-2.89747402776725,53.4266876757278],"type":"Point"}
}