{
  "type": "Feature",
  "properties": {
    "iso:country": "GB",
    "wof:name": "L12 9EH",
    "wof:placetype": "postalcode"
  },
  "geometry": {"coordinates":[-2.897474,53.426688],"type":"Point"}
}
