{
  "type": "Feature",
  "properties": {
    "iso:country":"GB",
    "wof:name":"BB6 8BL",
    "wof:placetype":"postalcode"
},
  "geometry": {"coordinates":[-2.45425913374224,53.82421424816145],"type":"Point"}
}