{
  "type": "Feature",
  "properties": {
    "iso:country":"GB",
    "wof:name":"PO7 8RN",
    "wof:placetype":"postalcode"
},
  "geometry": {"coordinates":[-1.00503339160909,50.88938417188202],"type":"Point"}
}