{
  "type": "Feature",
  "properties": {
    "iso:country":"GB",
    "wof:name":"NE3 5TE",
    "wof:placetype":"postalcode"
},
  "geometry": {"coordinates":[-1.6191932424005,55.02704136879177],"type":"Point"}
}