{
  "type": "Feature",
  "properties": {
    "iso:country":"GB",
    "wof:name":"HR1 1PT",
    "wof:placetype":"postalcode"
},
  "geometry": {"coordinates":[-2.68765835447016,52.06117439369839],"type":"Point"}
}