{
  "type": "Feature",
  "properties": {
    "iso:country":"GB",
    "wof:name":"NP7 5HD",
    "wof:placetype":"postalcode"
},
  "geometry": {"coordinates":[-3.01758975350099,51.82216729738565],"type":"Point"}
}