{
  "type": "Feature",
  "properties": {
    "date:inception_lower": "1980-01-01",
    "date:inception_upper": "1980-01-01",
    "iso:country": "GB",
    "wof:name": "NP7 5HD",
    "wof:placetype": "postalcode"
  },
  "geometry": {"coordinates":[-3.01759,51.822167],"type":"Point"}
}
