{
  "type": "Feature",
  "properties": {
    "iso:country": "GB",
    "wof:name": "RG42 3DT",
    "wof:placetype": "postalcode"
  },
  "geometry": {"coordinates":[-0.734223,51.425825],"type":"Point"}
}
