{
  "type": "Feature",
  "properties": {
    "iso:country":"GB",
    "wof:name":"ST6 3DQ",
    "wof:placetype":"postalcode"
},
  "geometry": {"coordinates":[-2.19195845546614,53.03870408857125],"type":"Point"}
}