{
  "type": "Feature",
  "properties": {
    "iso:country":"GB",
    "wof:name":"NW1 8BB",
    "wof:placetype":"postalcode"
},
  "geometry": {"coordinates":[-0.15329042205259,51.54368326382643],"type":"Point"}
}