{
  "type": "Feature",
  "properties": {
    "iso:country": "GB",
    "wof:name": "NW1 8BB",
    "wof:placetype": "postalcode"
  },
  "geometry": {"coordinates":[-0.153265,51.543685],"type":"Point"}
}
