{
  "type": "Feature",
  "properties": {
    "iso:country": "GB",
    "wof:name": "SP4 6FR",
    "wof:placetype": "postalcode"
  },
  "geometry": {"coordinates":[-1.789123,51.100658],"type":"Point"}
}
