{
  "type": "Feature",
  "properties": {
    "iso:country":"GB",
    "wof:name":"SP4 6FR",
    "wof:placetype":"postalcode"
},
  "geometry": {"coordinates":[-1.78912312700434,51.10065843611176],"type":"Point"}
}