{
  "type": "Feature",
  "properties": {
    "iso:country":"GB",
    "wof:name":"ST6 7BD",
    "wof:placetype":"postalcode"
},
  "geometry": {"coordinates":[-2.19733981305183,53.05772520878399],"type":"Point"}
}