{
  "type": "Feature",
  "properties": {
    "iso:country":"GB",
    "wof:name":"B15 1HD",
    "wof:placetype":"postalcode"
},
  "geometry": {"coordinates":[-1.91431997511928,52.47284732540443],"type":"Point"}
}