{
  "type": "Feature",
  "properties": {
    "iso:country": "GB",
    "wof:name": "SP2 8AU",
    "wof:placetype": "postalcode"
  },
  "geometry": {"coordinates":[-1.786138,51.054254],"type":"Point"}
}
