{
  "type": "Feature",
  "properties": {
    "iso:country":"GB",
    "wof:name":"SP2 8AU",
    "wof:placetype":"postalcode"
},
  "geometry": {"coordinates":[-1.78613778404542,51.05425362973958],"type":"Point"}
}