{
  "type": "Feature",
  "properties": {
    "iso:country":"GB",
    "wof:name":"GL11 4DB",
    "wof:placetype":"postalcode"
},
  "geometry": {"coordinates":[-2.3582226507367,51.68939650370557],"type":"Point"}
}