{
  "type": "Feature",
  "properties": {
    "iso:country": "GB",
    "wof:name": "PE24 4PG",
    "wof:placetype": "postalcode"
  },
  "geometry": {"coordinates":[0.241102,53.112504],"type":"Point"}
}
