{
  "type": "Feature",
  "properties": {
    "iso:country":"GB",
    "wof:name":"PE24 4PG",
    "wof:placetype":"postalcode"
},
  "geometry": {"coordinates":[0.24110186393025,53.11250353852588],"type":"Point"}
}