{
  "type": "Feature",
  "properties": {
    "iso:country":"GB",
    "wof:name":"TQ6 9RW",
    "wof:placetype":"postalcode"
},
  "geometry": {"coordinates":[-3.58564257164584,50.34312136024116],"type":"Point"}
}