{
  "type": "Feature",
  "properties": {
    "date:inception_lower": "2001-06-01",
    "date:inception_upper": "2001-06-01",
    "iso:country": "GB",
    "wof:name": "TQ6 9RW",
    "wof:placetype": "postalcode"
  },
  "geometry": {"coordinates":[-3.585631,50.343096],"type":"Point"}
}
