{
  "type": "Feature",
  "properties": {
    "iso:country":"GB",
    "wof:name":"NE29 7BT",
    "wof:placetype":"postalcode"
},
  "geometry": {"coordinates":[-1.46704792955164,55.00598191281477],"type":"Point"}
}