{
  "type": "Feature",
  "properties": {
    "iso:country": "GB",
    "wof:name": "SA44 5UY",
    "wof:placetype": "postalcode"
  },
  "geometry": {"coordinates":[-4.397309,52.019066],"type":"Point"}
}
