{
  "type": "Feature",
  "properties": {
    "iso:country":"GB",
    "wof:name":"WA9 1EN",
    "wof:placetype":"postalcode"
},
  "geometry": {"coordinates":[-2.71247443908685,53.45757959480655],"type":"Point"}
}