{
  "type": "Feature",
  "properties": {
    "iso:country": "GB",
    "wof:name": "CW9 5QN",
    "wof:placetype": "postalcode"
  },
  "geometry": {"coordinates":[-2.501223,53.25789],"type":"Point"}
}
