{
  "type": "Feature",
  "properties": {
    "iso:country": "GB",
    "wof:name": "DE21 6NZ",
    "wof:placetype": "postalcode"
  },
  "geometry": {"coordinates":[-1.436412,52.917302],"type":"Point"}
}
