{
  "type": "Feature",
  "properties": {
    "date:inception_lower": "1999-06-01",
    "date:inception_upper": "1999-06-01",
    "iso:country": "GB",
    "wof:name": "NP11 7JR",
    "wof:placetype": "postalcode"
  },
  "geometry": {"coordinates":[-3.185974,51.626707],"type":"Point"}
}
