{
  "type": "Feature",
  "properties": {
    "iso:country":"GB",
    "wof:name":"NP11 7JR",
    "wof:placetype":"postalcode"
},
  "geometry": {"coordinates":[-3.18592773496179,51.62693849722014],"type":"Point"}
}