{
  "type": "Feature",
  "properties": {
    "iso:country": "GB",
    "wof:name": "AB15 9RR",
    "wof:placetype": "postalcode"
  },
  "geometry": {"coordinates":[-2.180972,57.118791],"type":"Point"}
}
