{
  "type": "Feature",
  "properties": {
    "iso:country":"GB",
    "wof:name":"AB15 9RR",
    "wof:placetype":"postalcode"
},
  "geometry": {"coordinates":[-2.18097234615841,57.11879058894953],"type":"Point"}
}