{
  "type": "Feature",
  "properties": {
    "iso:country":"GB",
    "wof:name":"BD2 1HZ",
    "wof:placetype":"postalcode"
},
  "geometry": {"coordinates":[-1.73750000565276,53.8223529220304],"type":"Point"}
}