{
  "type": "Feature",
  "properties": {
    "iso:country":"GB",
    "wof:name":"NG19 9DN",
    "wof:placetype":"postalcode"
},
  "geometry": {"coordinates":[-1.17666109783163,53.16977228059736],"type":"Point"}
}