{
  "type": "Feature",
  "properties": {
    "iso:country": "GB",
    "wof:name": "NG19 9DN",
    "wof:placetype": "postalcode"
  },
  "geometry": {"coordinates":[-1.176661,53.169772],"type":"Point"}
}
