{
  "type": "Feature",
  "properties": {
    "iso:country":"GB",
    "wof:name":"AB15 6JR",
    "wof:placetype":"postalcode"
},
  "geometry": {"coordinates":[-2.16586621115861,57.1491652113009],"type":"Point"}
}