{
  "type": "Feature",
  "properties": {
    "iso:country":"GB",
    "wof:name":"UB7 8DD",
    "wof:placetype":"postalcode"
},
  "geometry": {"coordinates":[-0.46467638647808,51.52011569736852],"type":"Point"}
}