{
  "type": "Feature",
  "properties": {
    "iso:country": "GB",
    "wof:name": "SN3 2BN",
    "wof:placetype": "postalcode"
  },
  "geometry": {"coordinates":[-1.752254,51.552835],"type":"Point"}
}
