{
  "type": "Feature",
  "properties": {
    "date:inception_lower": "2007-08-01",
    "date:inception_upper": "2007-08-01",
    "iso:country": "GB",
    "wof:name": "SN3 2BN",
    "wof:placetype": "postalcode"
  },
  "geometry": {"coordinates":[-1.752254,51.552835],"type":"Point"}
}
