{
  "type": "Feature",
  "properties": {
    "iso:country":"GB",
    "wof:name":"PL2 3QJ",
    "wof:placetype":"postalcode"
},
  "geometry": {"coordinates":[-4.15035541119992,50.39311203145285],"type":"Point"}
}