{
  "type": "Feature",
  "properties": {
    "iso:country":"GB",
    "wof:name":"LD1 6ED",
    "wof:placetype":"postalcode"
},
  "geometry": {"coordinates":[-3.38693059809946,52.26961717300916],"type":"Point"}
}