{
  "type": "Feature",
  "properties": {
    "iso:country": "GB",
    "wof:name": "LD1 6ED",
    "wof:placetype": "postalcode"
  },
  "geometry": {"coordinates":[-3.386931,52.269617],"type":"Point"}
}
