{
  "type": "Feature",
  "properties": {
    "date:inception_lower": "1980-01-01",
    "date:inception_upper": "1980-01-01",
    "iso:country": "GB",
    "wof:name": "TN29 9UE",
    "wof:placetype": "postalcode"
  },
  "geometry": {"coordinates":[0.852986,51.009068],"type":"Point"}
}
