{
  "type": "Feature",
  "properties": {
    "iso:country":"GB",
    "wof:name":"NG2 4AZ",
    "wof:placetype":"postalcode"
},
  "geometry": {"coordinates":[-1.12038509287704,52.95057795106248],"type":"Point"}
}