{
  "type": "Feature",
  "properties": {
    "iso:country": "GB",
    "wof:name": "NG2 4AZ",
    "wof:placetype": "postalcode"
  },
  "geometry": {"coordinates":[-1.120385,52.950578],"type":"Point"}
}
