{
  "type": "Feature",
  "properties": {
    "date:inception_lower":"2008-04-01",
    "date:inception_upper":"2008-04-30",
    "iso:country":"GB",
    "wof:name":"SM3 8JZ",
    "wof:placetype":"postalcode"
},
  "geometry": {"coordinates":[-0.229438,51.371032],"type":"Point"}
}