{
  "type": "Feature",
  "properties": {
    "iso:country":"GB",
    "wof:name":"SM3 8JZ",
    "wof:placetype":"postalcode"
},
  "geometry": {"coordinates":[-0.22943807913663,51.37103244147056],"type":"Point"}
}