{
  "type": "Feature",
  "properties": {
    "iso:country":"GB",
    "wof:name":"DD2 3FB",
    "wof:placetype":"postalcode"
},
  "geometry": {"coordinates":[-3.00822380793327,56.47207394640181],"type":"Point"}
}