{
  "type": "Feature",
  "properties": {
    "iso:country":"GB",
    "wof:name":"LN6 0FN",
    "wof:placetype":"postalcode"
},
  "geometry": {"coordinates":[-0.61496649318446,53.21743424996961],"type":"Point"}
}