{
  "type": "Feature",
  "properties": {
    "iso:country": "GB",
    "wof:name": "LN6 0FN",
    "wof:placetype": "postalcode"
  },
  "geometry": {"coordinates":[-0.614966,53.217434],"type":"Point"}
}
