{
  "type": "Feature",
  "properties": {
    "date:inception_lower": "1994-12-01",
    "date:inception_upper": "1994-12-01",
    "iso:country": "GB",
    "wof:name": "LN6 0FN",
    "wof:placetype": "postalcode"
  },
  "geometry": {"coordinates":[-0.614966,53.217434],"type":"Point"}
}
