{
  "type": "Feature",
  "properties": {
    "iso:country": "GB",
    "wof:name": "EX8 3LQ",
    "wof:placetype": "postalcode"
  },
  "geometry": {"coordinates":[-3.403909,50.634196],"type":"Point"}
}
