{
  "type": "Feature",
  "properties": {
    "iso:country":"GB",
    "wof:name":"IV30 6TA",
    "wof:placetype":"postalcode"
},
  "geometry": {"coordinates":[-3.29224783132774,57.64195375209857],"type":"Point"}
}