{
  "type": "Feature",
  "properties": {
    "iso:country": "GB",
    "wof:name": "LE16 9QY",
    "wof:placetype": "postalcode"
  },
  "geometry": {"coordinates":[-0.931863,52.483297],"type":"Point"}
}
