{
  "type": "Feature",
  "properties": {
    "iso:country":"GB",
    "wof:name":"BD9 4NL",
    "wof:placetype":"postalcode"
},
  "geometry": {"coordinates":[-1.77487042455014,53.81072648196348],"type":"Point"}
}