{
  "type": "Feature",
  "properties": {
    "iso:country": "GB",
    "wof:name": "TR26 2NU",
    "wof:placetype": "postalcode"
  },
  "geometry": {"coordinates":[-5.457441,50.196196],"type":"Point"}
}
