{
  "type": "Feature",
  "properties": {
    "iso:country":"GB",
    "wof:name":"TR26 2NU",
    "wof:placetype":"postalcode"
},
  "geometry": {"coordinates":[-5.45744116906701,50.19619575268715],"type":"Point"}
}