{
  "type": "Feature",
  "properties": {
    "date:inception_lower": "1999-06-01",
    "date:inception_upper": "1999-06-01",
    "iso:country": "GB",
    "wof:name": "CF23 6AQ",
    "wof:placetype": "postalcode"
  },
  "geometry": {"coordinates":[-3.172106,51.507874],"type":"Point"}
}
