{
  "type": "Feature",
  "properties": {
    "iso:country":"GB",
    "wof:name":"CF23 6AQ",
    "wof:placetype":"postalcode"
},
  "geometry": {"coordinates":[-3.17178297495629,51.50794838830361],"type":"Point"}
}