{
  "type": "Feature",
  "properties": {
    "iso:country": "GB",
    "wof:name": "HP5 1RL",
    "wof:placetype": "postalcode"
  },
  "geometry": {"coordinates":[-0.598889,51.699538],"type":"Point"}
}
