{
  "type": "Feature",
  "properties": {
    "iso:country": "GB",
    "wof:name": "NR31 6JA",
    "wof:placetype": "postalcode"
  },
  "geometry": {"coordinates":[1.723915,52.571019],"type":"Point"}
}
