{
  "type": "Feature",
  "properties": {
    "iso:country":"GB",
    "wof:name":"NR31 6JA",
    "wof:placetype":"postalcode"
},
  "geometry": {"coordinates":[1.72418366320412,52.57025568833809],"type":"Point"}
}