{
  "type": "Feature",
  "properties": {
    "iso:country":"GB",
    "wof:name":"HU6 8JS",
    "wof:placetype":"postalcode"
},
  "geometry": {"coordinates":[-0.3854899437497,53.7772681350642],"type":"Point"}
}