{
  "type": "Feature",
  "properties": {
    "iso:country":"GB",
    "wof:name":"WD3 3EE",
    "wof:placetype":"postalcode"
},
  "geometry": {"coordinates":[-0.43744311429416,51.64778553694665],"type":"Point"}
}