{
  "type": "Feature",
  "properties": {
    "date:inception_lower": "2020-12-01",
    "date:inception_upper": "2020-12-01",
    "iso:country": "GB",
    "wof:name": "RH2 7LP",
    "wof:placetype": "postalcode"
  },
  "geometry": {"coordinates":[-0.196274,51.225571],"type":"Point"}
}
