{
  "type": "Feature",
  "properties": {
    "iso:country":"GB",
    "wof:name":"SE20 7RG",
    "wof:placetype":"postalcode"
},
  "geometry": {"coordinates":[-0.0570580399582,51.40838118080546],"type":"Point"}
}