{
  "type": "Feature",
  "properties": {
    "date:inception_lower": "1980-01-01",
    "date:inception_upper": "1980-01-01",
    "iso:country": "GB",
    "wof:name": "HU15 1ND",
    "wof:placetype": "postalcode"
  },
  "geometry": {"coordinates":[-0.548668,53.733529],"type":"Point"}
}
