{
  "type": "Feature",
  "properties": {
    "iso:country":"GB",
    "wof:name":"PL10 1BQ",
    "wof:placetype":"postalcode"
},
  "geometry": {"coordinates":[-4.21771740962244,50.34928481340791],"type":"Point"}
}