{
  "type": "Feature",
  "properties": {
    "date:inception_lower":"1980-01-01",
    "date:inception_upper":"1980-01-31",
    "iso:country":"GB",
    "wof:name":"PL10 1BQ",
    "wof:placetype":"postalcode"
},
  "geometry": {"coordinates":[-4.217717,50.349285],"type":"Point"}
}