{
  "type": "Feature",
  "properties": {
    "iso:country":"GB",
    "wof:name":"CT10 2BL",
    "wof:placetype":"postalcode"
},
  "geometry": {"coordinates":[1.432111850985,51.36128216640323],"type":"Point"}
}