{
  "type": "Feature",
  "properties": {
    "iso:country":"GB",
    "wof:name":"NE65 7RG",
    "wof:placetype":"postalcode"
},
  "geometry": {"coordinates":[-1.90039855305227,55.30697665262689],"type":"Point"}
}