{
  "type": "Feature",
  "properties": {
    "date:inception_lower": "2013-09-01",
    "date:inception_upper": "2013-09-01",
    "iso:country": "GB",
    "wof:name": "BS37 7BE",
    "wof:placetype": "postalcode"
  },
  "geometry": {"coordinates":[-2.433042,51.549976],"type":"Point"}
}
