{
  "type": "Feature",
  "properties": {
    "iso:country":"GB",
    "wof:name":"BS30 6RH",
    "wof:placetype":"postalcode"
},
  "geometry": {"coordinates":[-2.47383686497942,51.43550022612568],"type":"Point"}
}