{
  "type": "Feature",
  "properties": {
    "iso:country":"GB",
    "wof:name":"CR2 0PL",
    "wof:placetype":"postalcode"
},
  "geometry": {"coordinates":[-0.0939349451311,51.34798001241724],"type":"Point"}
}