{
  "type": "Feature",
  "properties": {
    "iso:country": "GB",
    "wof:name": "CR2 0PL",
    "wof:placetype": "postalcode"
  },
  "geometry": {"coordinates":[-0.093909,51.347979],"type":"Point"}
}
