{
  "type": "Feature",
  "properties": {
    "iso:country":"GB",
    "wof:name":"HG1 4JX",
    "wof:placetype":"postalcode"
},
  "geometry": {"coordinates":[-1.52237877879987,54.00709168142202],"type":"Point"}
}