{
  "type": "Feature",
  "properties": {
    "iso:country": "GB",
    "wof:name": "CO7 7QS",
    "wof:placetype": "postalcode"
  },
  "geometry": {"coordinates":[0.949003,51.917955],"type":"Point"}
}
