{
  "type": "Feature",
  "properties": {
    "iso:country":"GB",
    "wof:name":"CO7 7QS",
    "wof:placetype":"postalcode"
},
  "geometry": {"coordinates":[0.94900336559353,51.91795511249805],"type":"Point"}
}