{
  "type": "Feature",
  "properties": {
    "date:inception_lower":"1980-01-01",
    "date:inception_upper":"1980-01-31",
    "iso:country":"GB",
    "wof:name":"CO7 7QS",
    "wof:placetype":"postalcode"
},
  "geometry": {"coordinates":[0.949003,51.917955],"type":"Point"}
}