{
  "type": "Feature",
  "properties": {
    "iso:country":"GB",
    "wof:name":"M13 0PY",
    "wof:placetype":"postalcode"
},
  "geometry": {"coordinates":[-2.19971140790836,53.44968661410903],"type":"Point"}
}