{
  "type": "Feature",
  "properties": {
    "iso:country":"GB",
    "wof:name":"HR9 6EE",
    "wof:placetype":"postalcode"
},
  "geometry": {"coordinates":[-2.61081441267054,51.92288736241925],"type":"Point"}
}