{
  "type": "Feature",
  "properties": {
    "date:inception_lower": "1995-07-01",
    "date:inception_upper": "1995-07-01",
    "iso:country": "GB",
    "wof:name": "HR9 6EE",
    "wof:placetype": "postalcode"
  },
  "geometry": {"coordinates":[-2.610814,51.922887],"type":"Point"}
}
