{
  "type": "Feature",
  "properties": {
    "date:inception_lower": "1980-01-01",
    "date:inception_upper": "1980-01-01",
    "iso:country": "GB",
    "wof:name": "HR7 4LU",
    "wof:placetype": "postalcode"
  },
  "geometry": {"coordinates":[-2.517604,52.218097],"type":"Point"}
}
