{
  "type": "Feature",
  "properties": {
    "date:inception_lower": "1985-04-01",
    "date:inception_upper": "1985-04-01",
    "iso:country": "GB",
    "wof:name": "RH12 1AH",
    "wof:placetype": "postalcode"
  },
  "geometry": {"coordinates":[-0.333515,51.063278],"type":"Point"}
}
