{
  "type": "Feature",
  "properties": {
    "date:inception_lower": "1994-05-01",
    "date:inception_upper": "1994-05-01",
    "iso:country": "GB",
    "wof:name": "PR1 7HA",
    "wof:placetype": "postalcode"
  },
  "geometry": {"coordinates":[-2.712432,53.767384],"type":"Point"}
}
