{
  "type": "Feature",
  "properties": {
    "iso:country": "GB",
    "wof:name": "UB8 1NW",
    "wof:placetype": "postalcode"
  },
  "geometry": {"coordinates":[-0.472104,51.546903],"type":"Point"}
}
