{
  "type": "Feature",
  "properties": {
    "iso:country":"GB",
    "wof:name":"UB8 1NW",
    "wof:placetype":"postalcode"
},
  "geometry": {"coordinates":[-0.47215542264426,51.54686601922478],"type":"Point"}
}