{
  "type": "Feature",
  "properties": {
    "iso:country":"GB",
    "wof:name":"RG22 6DU",
    "wof:placetype":"postalcode"
},
  "geometry": {"coordinates":[-1.11058092053874,51.25446204138132],"type":"Point"}
}