{
  "type": "Feature",
  "properties": {
    "date:inception_lower":"1980-01-01",
    "date:inception_upper":"1980-01-31",
    "iso:country":"GB",
    "wof:name":"WF2 0RU",
    "wof:placetype":"postalcode"
},
  "geometry": {"coordinates":[-1.548122,53.701771],"type":"Point"}
}