{
  "type": "Feature",
  "properties": {
    "iso:country":"GB",
    "wof:name":"WF2 0RU",
    "wof:placetype":"postalcode"
},
  "geometry": {"coordinates":[-1.5481223079944,53.70177146529533],"type":"Point"}
}