{
  "type": "Feature",
  "properties": {
    "iso:country":"GB",
    "wof:name":"EH16 6EH",
    "wof:placetype":"postalcode"
},
  "geometry": {"coordinates":[-3.15893885745291,55.90798564116778],"type":"Point"}
}