{
  "type": "Feature",
  "properties": {
    "date:inception_lower": "2018-10-01",
    "date:inception_upper": "2018-10-01",
    "iso:country": "GB",
    "wof:name": "BA5 1GG",
    "wof:placetype": "postalcode"
  },
  "geometry": {"coordinates":[-2.663003,51.226632],"type":"Point"}
}
