{
  "type": "Feature",
  "properties": {
    "iso:country":"GB",
    "wof:name":"SO16 6BP",
    "wof:placetype":"postalcode"
},
  "geometry": {"coordinates":[-1.43986989557047,50.93075821223795],"type":"Point"}
}