{
  "type": "Feature",
  "properties": {
    "iso:country":"GB",
    "wof:name":"NW3 3DU",
    "wof:placetype":"postalcode"
},
  "geometry": {"coordinates":[-0.16234435841494,51.54196399687501],"type":"Point"}
}