{
  "type": "Feature",
  "properties": {
    "date:inception_lower": "1980-01-01",
    "date:inception_upper": "1980-01-01",
    "iso:country": "GB",
    "wof:name": "LE2 2FT",
    "wof:placetype": "postalcode"
  },
  "geometry": {"coordinates":[-1.013499,52.595952],"type":"Point"}
}
