{
  "type": "Feature",
  "properties": {
    "iso:country":"GB",
    "wof:name":"LE2 2FT",
    "wof:placetype":"postalcode"
},
  "geometry": {"coordinates":[-1.01349923405771,52.59595185858568],"type":"Point"}
}