{
  "type": "Feature",
  "properties": {
    "iso:country":"GB",
    "wof:name":"G76 7QE",
    "wof:placetype":"postalcode"
},
  "geometry": {"coordinates":[-4.287666112156,55.79089424080956],"type":"Point"}
}