{
  "type": "Feature",
  "properties": {
    "iso:country":"GB",
    "wof:name":"B19 3EH",
    "wof:placetype":"postalcode"
},
  "geometry": {"coordinates":[-1.90679075813268,52.48986863185267],"type":"Point"}
}