{
  "type": "Feature",
  "properties": {
    "iso:country":"GB",
    "wof:name":"TA3 7BQ",
    "wof:placetype":"postalcode"
},
  "geometry": {"coordinates":[-3.07759519886548,50.98910289529104],"type":"Point"}
}