{
  "type": "Feature",
  "properties": {
    "iso:country": "GB",
    "wof:name": "TA3 7BQ",
    "wof:placetype": "postalcode"
  },
  "geometry": {"coordinates":[-3.077595,50.989103],"type":"Point"}
}
