{
  "type": "Feature",
  "properties": {
    "iso:country": "GB",
    "wof:name": "BA11 5HB",
    "wof:placetype": "postalcode"
  },
  "geometry": {"coordinates":[-2.344374,51.176494],"type":"Point"}
}
