{
  "type": "Feature",
  "properties": {
    "iso:country":"GB",
    "wof:name":"BA11 5HB",
    "wof:placetype":"postalcode"
},
  "geometry": {"coordinates":[-2.34437446251165,51.17649394129681],"type":"Point"}
}