{
  "type": "Feature",
  "properties": {
    "date:inception_lower":"1980-01-01",
    "date:inception_upper":"1980-01-31",
    "iso:country":"GB",
    "wof:name":"BA11 5HB",
    "wof:placetype":"postalcode"
},
  "geometry": {"coordinates":[-2.344374,51.176494],"type":"Point"}
}