{
  "type": "Feature",
  "properties": {
    "date:inception_lower": "2012-03-01",
    "date:inception_upper": "2012-03-01",
    "iso:country": "GB",
    "wof:name": "BS39 7AN",
    "wof:placetype": "postalcode"
  },
  "geometry": {"coordinates":[-2.508152,51.308649],"type":"Point"}
}
