{
  "type": "Feature",
  "properties": {
    "iso:country":"GB",
    "wof:name":"BS39 7AN",
    "wof:placetype":"postalcode"
},
  "geometry": {"coordinates":[-2.50728707058896,51.30842380077854],"type":"Point"}
}