{
  "type": "Feature",
  "properties": {
    "iso:country": "GB",
    "wof:name": "TA9 3GA",
    "wof:placetype": "postalcode"
  },
  "geometry": {"coordinates":[-2.973026,51.223561],"type":"Point"}
}
