{
  "type": "Feature",
  "properties": {
    "iso:country":"GB",
    "wof:name":"CR4 3NT",
    "wof:placetype":"postalcode"
},
  "geometry": {"coordinates":[-0.16513007505102,51.40373838810836],"type":"Point"}
}