{
  "type": "Feature",
  "properties": {
    "iso:country":"GB",
    "wof:name":"RG24 8AR",
    "wof:placetype":"postalcode"
},
  "geometry": {"coordinates":[-1.04673699313892,51.2796590893932],"type":"Point"}
}