{
  "type": "Feature",
  "properties": {
    "date:inception_lower":"1980-01-01",
    "date:inception_upper":"1980-01-31",
    "iso:country":"GB",
    "wof:name":"EX17 5EF",
    "wof:placetype":"postalcode"
},
  "geometry": {"coordinates":[-3.835453,50.743088],"type":"Point"}
}