{
  "type": "Feature",
  "properties": {
    "iso:country": "GB",
    "wof:name": "KW14 8JJ",
    "wof:placetype": "postalcode"
  },
  "geometry": {"coordinates":[-3.504818,58.594099],"type":"Point"}
}
