{
  "type": "Feature",
  "properties": {
    "date:inception_lower": "1980-01-01",
    "date:inception_upper": "1980-01-01",
    "iso:country": "GB",
    "wof:name": "KW14 8JJ",
    "wof:placetype": "postalcode"
  },
  "geometry": {"coordinates":[-3.504818,58.594099],"type":"Point"}
}
