{
  "type": "Feature",
  "properties": {
    "iso:country": "GB",
    "wof:name": "NP25 4SY",
    "wof:placetype": "postalcode"
  },
  "geometry": {"coordinates":[-2.687546,51.734073],"type":"Point"}
}
