{
  "type": "Feature",
  "properties": {
    "iso:country":"GB",
    "wof:name":"EX22 6FG",
    "wof:placetype":"postalcode"
},
  "geometry": {"coordinates":[-4.35771350366354,50.8177974051861],"type":"Point"}
}