{
  "type": "Feature",
  "properties": {
    "date:inception_lower":"2011-05-01",
    "date:inception_upper":"2011-05-31",
    "iso:country":"GB",
    "wof:name":"EX22 6FG",
    "wof:placetype":"postalcode"
},
  "geometry": {"coordinates":[-4.357713,50.817797],"type":"Point"}
}