{
  "type": "Feature",
  "properties": {
    "date:inception_lower": "2004-09-01",
    "date:inception_upper": "2004-09-01",
    "iso:country": "GB",
    "wof:name": "SE17 1RS",
    "wof:placetype": "postalcode"
  },
  "geometry": {"coordinates":[-0.096813,51.490822],"type":"Point"}
}
