{
  "type": "Feature",
  "properties": {
    "iso:country":"GB",
    "wof:name":"EH32 9RE",
    "wof:placetype":"postalcode"
},
  "geometry": {"coordinates":[-2.96699355621808,55.96116412629218],"type":"Point"}
}