{
  "type": "Feature",
  "properties": {
    "iso:country":"GB",
    "wof:name":"BN26 6AJ",
    "wof:placetype":"postalcode"
},
  "geometry": {"coordinates":[0.24443127102627,50.82185986336767],"type":"Point"}
}