{
  "type": "Feature",
  "properties": {
    "iso:country": "GB",
    "wof:name": "DN32 8BD",
    "wof:placetype": "postalcode"
  },
  "geometry": {"coordinates":[-0.067187,53.563117],"type":"Point"}
}
