{
  "type": "Feature",
  "properties": {
    "date:inception_lower":"1980-01-01",
    "date:inception_upper":"1980-01-31",
    "iso:country":"GB",
    "wof:name":"DN32 8BD",
    "wof:placetype":"postalcode"
},
  "geometry": {"coordinates":[-0.067187,53.563117],"type":"Point"}
}