{
  "type": "Feature",
  "properties": {
    "iso:country":"GB",
    "wof:name":"DN32 8BD",
    "wof:placetype":"postalcode"
},
  "geometry": {"coordinates":[-0.06718664802967,53.56311747109378],"type":"Point"}
}