{
  "type": "Feature",
  "properties": {
    "iso:country":"GB",
    "wof:name":"DA8 1SP",
    "wof:placetype":"postalcode"
},
  "geometry": {"coordinates":[0.17914556406162,51.48108066318098],"type":"Point"}
}