{
  "type": "Feature",
  "properties": {
    "iso:country": "GB",
    "wof:name": "DA8 1SP",
    "wof:placetype": "postalcode"
  },
  "geometry": {"coordinates":[0.179146,51.481081],"type":"Point"}
}
