{
  "type": "Feature",
  "properties": {
    "date:inception_lower": "1980-01-01",
    "date:inception_upper": "1980-01-01",
    "iso:country": "GB",
    "wof:name": "DD2 3BX",
    "wof:placetype": "postalcode"
  },
  "geometry": {"coordinates":[-3.009419,56.472288],"type":"Point"}
}
