{
  "type": "Feature",
  "properties": {
    "iso:country":"GB",
    "wof:name":"DH8 7EU",
    "wof:placetype":"postalcode"
},
  "geometry": {"coordinates":[-1.8205338760194,54.84405871950407],"type":"Point"}
}