{
  "type": "Feature",
  "properties": {
    "iso:country": "GB",
    "wof:name": "DH8 7EU",
    "wof:placetype": "postalcode"
  },
  "geometry": {"coordinates":[-1.820534,54.844059],"type":"Point"}
}
