{
  "type": "Feature",
  "properties": {
    "date:inception_lower": "1980-01-01",
    "date:inception_upper": "1980-01-01",
    "iso:country": "GB",
    "wof:name": "DH8 7EU",
    "wof:placetype": "postalcode"
  },
  "geometry": {"coordinates":[-1.820534,54.844059],"type":"Point"}
}
