{
  "type": "Feature",
  "properties": {
    "iso:country": "GB",
    "wof:name": "EN3 5SH",
    "wof:placetype": "postalcode"
  },
  "geometry": {"coordinates":[-0.043754,51.668055],"type":"Point"}
}
