{
  "type": "Feature",
  "properties": {
    "iso:country":"GB",
    "wof:name":"CF46 6PS",
    "wof:placetype":"postalcode"
},
  "geometry": {"coordinates":[-3.27301975028432,51.64981845878375],"type":"Point"}
}