{
  "type": "Feature",
  "properties": {
    "iso:country":"GB",
    "wof:name":"BH17 7LJ",
    "wof:placetype":"postalcode"
},
  "geometry": {"coordinates":[-1.98396056390555,50.74492957133331],"type":"Point"}
}