{
  "type": "Feature",
  "properties": {
    "date:inception_lower": "1980-01-01",
    "date:inception_upper": "1980-01-01",
    "iso:country": "GB",
    "wof:name": "BH17 7LJ",
    "wof:placetype": "postalcode"
  },
  "geometry": {"coordinates":[-1.983961,50.74493],"type":"Point"}
}
