{
  "type": "Feature",
  "properties": {
    "iso:country":"GB",
    "wof:name":"OX2 6JT",
    "wof:placetype":"postalcode"
},
  "geometry": {"coordinates":[-1.26136302261072,51.76840079912544],"type":"Point"}
}