{
  "type": "Feature",
  "properties": {
    "iso:country": "GB",
    "wof:name": "OX2 6JT",
    "wof:placetype": "postalcode"
  },
  "geometry": {"coordinates":[-1.261389,51.768581],"type":"Point"}
}
