{
  "type": "Feature",
  "properties": {
    "iso:country": "GB",
    "wof:name": "NP8 1HU",
    "wof:placetype": "postalcode"
  },
  "geometry": {"coordinates":[-3.148492,51.851784],"type":"Point"}
}
