{
  "type": "Feature",
  "properties": {
    "iso:country":"GB",
    "wof:name":"GL7 7DN",
    "wof:placetype":"postalcode"
},
  "geometry": {"coordinates":[-1.96915559372574,51.7725947142688],"type":"Point"}
}