{
  "type": "Feature",
  "properties": {
    "iso:country":"GB",
    "wof:name":"SO19 9EL",
    "wof:placetype":"postalcode"
},
  "geometry": {"coordinates":[-1.37903863392214,50.89325782006483],"type":"Point"}
}