{
  "type": "Feature",
  "properties": {
    "iso:country": "GB",
    "wof:name": "DL1 5EP",
    "wof:placetype": "postalcode"
  },
  "geometry": {"coordinates":[-1.550602,54.518724],"type":"Point"}
}
