{
  "type": "Feature",
  "properties": {
    "iso:country":"GB",
    "wof:name":"TD5 7EE",
    "wof:placetype":"postalcode"
},
  "geometry": {"coordinates":[-2.43772126369499,55.60201904727354],"type":"Point"}
}