{
  "type": "Feature",
  "properties": {
    "iso:country":"GB",
    "wof:name":"N22 6XR",
    "wof:placetype":"postalcode"
},
  "geometry": {"coordinates":[-0.10226474941911,51.59293007236457],"type":"Point"}
}