{
  "type": "Feature",
  "properties": {
    "iso:country":"GB",
    "wof:name":"SR8 1HZ",
    "wof:placetype":"postalcode"
},
  "geometry": {"coordinates":[-1.34706156585822,54.75358591759935],"type":"Point"}
}