{
  "type": "Feature",
  "properties": {
    "date:inception_lower":"1998-12-01",
    "date:inception_upper":"1998-12-31",
    "iso:country":"GB",
    "wof:name":"RG21 3PS",
    "wof:placetype":"postalcode"
},
  "geometry": {"coordinates":[-1.086858,51.258964],"type":"Point"}
}