{
  "type": "Feature",
  "properties": {
    "iso:country":"GB",
    "wof:name":"PR5 4TX",
    "wof:placetype":"postalcode"
},
  "geometry": {"coordinates":[-2.67366900106376,53.73419042452338],"type":"Point"}
}