{
  "type": "Feature",
  "properties": {
    "iso:country":"GB",
    "wof:name":"PE24 5JJ",
    "wof:placetype":"postalcode"
},
  "geometry": {"coordinates":[0.24240656556334,53.16396973069892],"type":"Point"}
}