{
  "type": "Feature",
  "properties": {
    "iso:country":"GB",
    "wof:name":"NP4 9JU",
    "wof:placetype":"postalcode"
},
  "geometry": {"coordinates":[-3.08003354075382,51.77163617809168],"type":"Point"}
}