{
  "type": "Feature",
  "properties": {
    "iso:country": "GB",
    "wof:name": "NP4 9JU",
    "wof:placetype": "postalcode"
  },
  "geometry": {"coordinates":[-3.080033,51.771636],"type":"Point"}
}
