{
  "type": "Feature",
  "properties": {
    "iso:country":"GB",
    "wof:name":"CV37 7HX",
    "wof:placetype":"postalcode"
},
  "geometry": {"coordinates":[-1.68525429342743,52.1824984459192],"type":"Point"}
}