{
  "type": "Feature",
  "properties": {
    "date:inception_lower": "1980-01-01",
    "date:inception_upper": "1980-01-01",
    "iso:country": "GB",
    "wof:name": "SL2 1HR",
    "wof:placetype": "postalcode"
  },
  "geometry": {"coordinates":[-0.62126,51.53223],"type":"Point"}
}
