{
  "type": "Feature",
  "properties": {
    "iso:country":"GB",
    "wof:name":"SL2 1HR",
    "wof:placetype":"postalcode"
},
  "geometry": {"coordinates":[-0.6212596729316,51.53223036989966],"type":"Point"}
}