{
  "type": "Feature",
  "properties": {
    "iso:country":"GB",
    "wof:name":"SR3 2TP",
    "wof:placetype":"postalcode"
},
  "geometry": {"coordinates":[-1.40576665994477,54.85934539868777],"type":"Point"}
}