{
  "type": "Feature",
  "properties": {
    "iso:country":"GB",
    "wof:name":"IP5 2GZ",
    "wof:placetype":"postalcode"
},
  "geometry": {"coordinates":[1.24631336332417,52.05809672183089],"type":"Point"}
}