{
  "type": "Feature",
  "properties": {
    "iso:country": "GB",
    "wof:name": "CM1 4FS",
    "wof:placetype": "postalcode"
  },
  "geometry": {"coordinates":[0.460828,51.745587],"type":"Point"}
}
