{
  "type": "Feature",
  "properties": {
    "iso:country":"GB",
    "wof:name":"LS23 6DQ",
    "wof:placetype":"postalcode"
},
  "geometry": {"coordinates":[-1.3483766034563,53.90050521580856],"type":"Point"}
}