{
  "type": "Feature",
  "properties": {
    "iso:country": "GB",
    "wof:name": "LS23 6DQ",
    "wof:placetype": "postalcode"
  },
  "geometry": {"coordinates":[-1.348377,53.900505],"type":"Point"}
}
