{
  "type": "Feature",
  "properties": {
    "iso:country": "GB",
    "wof:name": "HD6 4HH",
    "wof:placetype": "postalcode"
  },
  "geometry": {"coordinates":[-1.75415,53.69989],"type":"Point"}
}
