{
  "type": "Feature",
  "properties": {
    "iso:country":"GB",
    "wof:name":"HD6 4HH",
    "wof:placetype":"postalcode"
},
  "geometry": {"coordinates":[-1.75415051500926,53.69989022858505],"type":"Point"}
}