{
  "type": "Feature",
  "properties": {
    "iso:country":"GB",
    "wof:name":"PE38 9AG",
    "wof:placetype":"postalcode"
},
  "geometry": {"coordinates":[0.38109972931166,52.60110957058073],"type":"Point"}
}