{
  "type": "Feature",
  "properties": {
    "iso:country":"GB",
    "wof:name":"CB9 7PH",
    "wof:placetype":"postalcode"
},
  "geometry": {"coordinates":[0.4916895855687,52.09218872247352],"type":"Point"}
}