{
  "type": "Feature",
  "properties": {
    "iso:country":"GB",
    "wof:name":"LS9 7QD",
    "wof:placetype":"postalcode"
},
  "geometry": {"coordinates":[-1.52420993740697,53.8006830632619],"type":"Point"}
}