{
  "type": "Feature",
  "properties": {
    "iso:country": "GB",
    "wof:name": "LS9 7QD",
    "wof:placetype": "postalcode"
  },
  "geometry": {"coordinates":[-1.52421,53.800683],"type":"Point"}
}
