{
  "type": "Feature",
  "properties": {
    "iso:country":"GB",
    "wof:name":"DY5 3QL",
    "wof:placetype":"postalcode"
},
  "geometry": {"coordinates":[-2.13293361953729,52.47646209786107],"type":"Point"}
}