{
  "type": "Feature",
  "properties": {
    "date:inception_lower": "1980-01-01",
    "date:inception_upper": "1980-01-01",
    "iso:country": "GB",
    "wof:name": "EN10 7LZ",
    "wof:placetype": "postalcode"
  },
  "geometry": {"coordinates":[-0.020753,51.749149],"type":"Point"}
}
