{
  "type": "Feature",
  "properties": {
    "iso:country":"GB",
    "wof:name":"EN10 7LZ",
    "wof:placetype":"postalcode"
},
  "geometry": {"coordinates":[-0.02075273855586,51.74914914480281],"type":"Point"}
}