{
  "type": "Feature",
  "properties": {
    "iso:country":"GB",
    "wof:name":"CR7 7HN",
    "wof:placetype":"postalcode"
},
  "geometry": {"coordinates":[-0.10815656283873,51.38829123692454],"type":"Point"}
}