{
  "type": "Feature",
  "properties": {
    "iso:country":"GB",
    "wof:name":"BL3 1AS",
    "wof:placetype":"postalcode"
},
  "geometry": {"coordinates":[-2.39202597873627,53.56910692382965],"type":"Point"}
}