{
  "type": "Feature",
  "properties": {
    "date:inception_lower":"2004-07-01",
    "date:inception_upper":"2004-07-31",
    "iso:country":"GB",
    "wof:name":"BL3 1AS",
    "wof:placetype":"postalcode"
},
  "geometry": {"coordinates":[-2.392026,53.569107],"type":"Point"}
}