{
  "type": "Feature",
  "properties": {
    "iso:country": "GB",
    "wof:name": "BL3 1AS",
    "wof:placetype": "postalcode"
  },
  "geometry": {"coordinates":[-2.392026,53.569107],"type":"Point"}
}
