{
  "type": "Feature",
  "properties": {
    "date:inception_lower": "2023-11-01",
    "date:inception_upper": "2023-11-01",
    "iso:country": "GB",
    "wof:name": "YO30 2BF",
    "wof:placetype": "postalcode"
  },
  "geometry": {"coordinates":[-1.215851,54.034702],"type":"Point"}
}
