{
  "type": "Feature",
  "properties": {
    "iso:country":"GB",
    "wof:name":"DN9 3DU",
    "wof:placetype":"postalcode"
},
  "geometry": {"coordinates":[-0.9595415018411,53.50160492013093],"type":"Point"}
}