{
  "type": "Feature",
  "properties": {
    "date:inception_lower":"1980-01-01",
    "date:inception_upper":"1980-01-31",
    "iso:country":"GB",
    "wof:name":"DN9 3DU",
    "wof:placetype":"postalcode"
},
  "geometry": {"coordinates":[-0.959545,53.501626],"type":"Point"}
}