{
  "type": "Feature",
  "properties": {
    "iso:country": "GB",
    "wof:name": "DN9 3DU",
    "wof:placetype": "postalcode"
  },
  "geometry": {"coordinates":[-0.959545,53.501626],"type":"Point"}
}
