{
  "type": "Feature",
  "properties": {
    "iso:country": "GB",
    "wof:name": "AL2 3LQ",
    "wof:placetype": "postalcode"
  },
  "geometry": {"coordinates":[-0.362218,51.708077],"type":"Point"}
}
