{
  "type": "Feature",
  "properties": {
    "iso:country":"GB",
    "wof:name":"AL2 3LQ",
    "wof:placetype":"postalcode"
},
  "geometry": {"coordinates":[-0.36221776047981,51.70807717830062],"type":"Point"}
}