{
  "type": "Feature",
  "properties": {
    "iso:country": "GB",
    "wof:name": "MK41 0DH",
    "wof:placetype": "postalcode"
  },
  "geometry": {"coordinates":[-0.428463,52.154012],"type":"Point"}
}
