{
  "type": "Feature",
  "properties": {
    "date:inception_lower":"1980-01-01",
    "date:inception_upper":"1980-01-31",
    "iso:country":"GB",
    "wof:name":"MK41 0DH",
    "wof:placetype":"postalcode"
},
  "geometry": {"coordinates":[-0.428463,52.154012],"type":"Point"}
}