{
  "type": "Feature",
  "properties": {
    "iso:country":"GB",
    "wof:name":"OL12 6TP",
    "wof:placetype":"postalcode"
},
  "geometry": {"coordinates":[-2.16268503366867,53.6185623088137],"type":"Point"}
}