{
  "type": "Feature",
  "properties": {
    "iso:country":"GB",
    "wof:name":"TW1 2AR",
    "wof:placetype":"postalcode"
},
  "geometry": {"coordinates":[-0.31524465945371,51.45496539967027],"type":"Point"}
}