{
  "type": "Feature",
  "properties": {
    "iso:country":"GB",
    "wof:name":"LN2 4RX",
    "wof:placetype":"postalcode"
},
  "geometry": {"coordinates":[-0.50290386306603,53.24632953182031],"type":"Point"}
}