{
  "type": "Feature",
  "properties": {
    "date:inception_lower": "1980-01-01",
    "date:inception_upper": "1980-01-01",
    "iso:country": "GB",
    "wof:name": "KT17 3JN",
    "wof:placetype": "postalcode"
  },
  "geometry": {"coordinates":[-0.247396,51.337949],"type":"Point"}
}
