{
  "type": "Feature",
  "properties": {
    "iso:country": "GB",
    "wof:name": "DT6 4PD",
    "wof:placetype": "postalcode"
  },
  "geometry": {"coordinates":[-2.700656,50.740828],"type":"Point"}
}
