{
  "type": "Feature",
  "properties": {
    "iso:country":"GB",
    "wof:name":"DT6 4PD",
    "wof:placetype":"postalcode"
},
  "geometry": {"coordinates":[-2.70068436976064,50.74084563435413],"type":"Point"}
}