{
  "type": "Feature",
  "properties": {
    "iso:country":"GB",
    "wof:name":"FY1 4AR",
    "wof:placetype":"postalcode"
},
  "geometry": {"coordinates":[-3.04503120341093,53.81011258578634],"type":"Point"}
}