{
  "type": "Feature",
  "properties": {
    "iso:country": "GB",
    "wof:name": "G64 1TR",
    "wof:placetype": "postalcode"
  },
  "geometry": {"coordinates":[-4.21557,55.902733],"type":"Point"}
}
