{
  "type": "Feature",
  "properties": {
    "iso:country":"GB",
    "wof:name":"SK10 2NY",
    "wof:placetype":"postalcode"
},
  "geometry": {"coordinates":[-2.11356049394337,53.27187897701904],"type":"Point"}
}