{
  "type": "Feature",
  "properties": {
    "date:inception_lower": "2016-03-01",
    "date:inception_upper": "2016-03-01",
    "iso:country": "GB",
    "wof:name": "CH4 0TQ",
    "wof:placetype": "postalcode"
  },
  "geometry": {"coordinates":[-2.977391,53.16399],"type":"Point"}
}
