{
  "type": "Feature",
  "properties": {
    "iso:country":"GB",
    "wof:name":"CH4 0TQ",
    "wof:placetype":"postalcode"
},
  "geometry": {"coordinates":[-2.97789160564705,53.16364665933451],"type":"Point"}
}