{
  "type": "Feature",
  "properties": {
    "iso:country": "GB",
    "wof:name": "GU5 0EX",
    "wof:placetype": "postalcode"
  },
  "geometry": {"coordinates":[-0.557458,51.19058],"type":"Point"}
}
