{
  "type": "Feature",
  "properties": {
    "date:inception_lower": "2019-10-01",
    "date:inception_upper": "2019-10-01",
    "iso:country": "GB",
    "wof:name": "GU5 0EX",
    "wof:placetype": "postalcode"
  },
  "geometry": {"coordinates":[-0.557401,51.190597],"type":"Point"}
}
