{
  "type": "Feature",
  "properties": {
    "iso:country": "GB",
    "wof:name": "GU5 0EX",
    "wof:placetype": "postalcode"
  },
  "geometry": {"coordinates":[-0.557531,51.190536],"type":"Point"}
}
