{
  "type": "Feature",
  "properties": {
    "date:inception_lower":"1980-01-01",
    "date:inception_upper":"1980-01-31",
    "iso:country":"GB",
    "wof:name":"SY7 9HL",
    "wof:placetype":"postalcode"
},
  "geometry": {"coordinates":[-2.668365,52.475448],"type":"Point"}
}