{
  "type": "Feature",
  "properties": {
    "iso:country":"GB",
    "wof:name":"CV32 4AP",
    "wof:placetype":"postalcode"
},
  "geometry": {"coordinates":[-1.53285161542327,52.29020233807579],"type":"Point"}
}