{
  "type": "Feature",
  "properties": {
    "date:inception_lower": "2008-11-01",
    "date:inception_upper": "2008-11-01",
    "iso:country": "GB",
    "wof:name": "CV32 4AP",
    "wof:placetype": "postalcode"
  },
  "geometry": {"coordinates":[-1.532678,52.290343],"type":"Point"}
}
