{
  "type": "Feature",
  "properties": {
    "iso:country": "GB",
    "wof:name": "RH4 9LN",
    "wof:placetype": "postalcode"
  },
  "geometry": {"coordinates":[-0.32998,51.233193],"type":"Point"}
}
