{
  "type": "Feature",
  "properties": {
    "iso:country": "GB",
    "wof:name": "CF44 9PE",
    "wof:placetype": "postalcode"
  },
  "geometry": {"coordinates":[-3.505549,51.738694],"type":"Point"}
}
