{
  "type": "Feature",
  "properties": {
    "iso:country":"GB",
    "wof:name":"LL54 6AS",
    "wof:placetype":"postalcode"
},
  "geometry": {"coordinates":[-4.25339205736141,53.05533066447396],"type":"Point"}
}