{
  "type": "Feature",
  "properties": {
    "iso:country": "GB",
    "wof:name": "PE19 2TH",
    "wof:placetype": "postalcode"
  },
  "geometry": {"coordinates":[-0.269454,52.222495],"type":"Point"}
}
