{
  "type": "Feature",
  "properties": {
    "iso:country":"GB",
    "wof:name":"PE19 2TH",
    "wof:placetype":"postalcode"
},
  "geometry": {"coordinates":[-0.26945360056207,52.22249517338093],"type":"Point"}
}