{
  "type": "Feature",
  "properties": {
    "date:inception_lower":"1980-01-01",
    "date:inception_upper":"1980-01-31",
    "iso:country":"GB",
    "wof:name":"PE19 2TH",
    "wof:placetype":"postalcode"
},
  "geometry": {"coordinates":[-0.269454,52.222495],"type":"Point"}
}