{
  "type": "Feature",
  "properties": {
    "iso:country":"GB",
    "wof:name":"B92 0JA",
    "wof:placetype":"postalcode"
},
  "geometry": {"coordinates":[-1.72070601819577,52.4066520694994],"type":"Point"}
}