{
  "type": "Feature",
  "properties": {
    "iso:country":"GB",
    "wof:name":"SG11 1JH",
    "wof:placetype":"postalcode"
},
  "geometry": {"coordinates":[-0.05836379525203,51.89320189530142],"type":"Point"}
}