{
  "type": "Feature",
  "properties": {
    "iso:country": "GB",
    "wof:name": "SG11 1JH",
    "wof:placetype": "postalcode"
  },
  "geometry": {"coordinates":[-0.058364,51.893202],"type":"Point"}
}
