{
  "type": "Feature",
  "properties": {
    "iso:country": "GB",
    "wof:name": "RG31 6YR",
    "wof:placetype": "postalcode"
  },
  "geometry": {"coordinates":[-1.050002,51.477733],"type":"Point"}
}
