{
  "type": "Feature",
  "properties": {
    "iso:country":"GB",
    "wof:name":"RG31 6YR",
    "wof:placetype":"postalcode"
},
  "geometry": {"coordinates":[-1.05000166499183,51.47773271048326],"type":"Point"}
}