{
  "type": "Feature",
  "properties": {
    "iso:country":"GB",
    "wof:name":"NN4 8UQ",
    "wof:placetype":"postalcode"
},
  "geometry": {"coordinates":[-0.92197635543291,52.22700365046235],"type":"Point"}
}