{
  "type": "Feature",
  "properties": {
    "iso:country": "GB",
    "wof:name": "NN4 8UQ",
    "wof:placetype": "postalcode"
  },
  "geometry": {"coordinates":[-0.921976,52.227004],"type":"Point"}
}
