{
  "type": "Feature",
  "properties": {
    "iso:country": "GB",
    "wof:name": "TN4 9LA",
    "wof:placetype": "postalcode"
  },
  "geometry": {"coordinates":[0.271609,51.146124],"type":"Point"}
}
