{
  "type": "Feature",
  "properties": {
    "iso:country":"GB",
    "wof:name":"SM4 6BN",
    "wof:placetype":"postalcode"
},
  "geometry": {"coordinates":[-0.18413347696531,51.38676856509315],"type":"Point"}
}