{
  "type": "Feature",
  "properties": {
    "iso:country":"GB",
    "wof:name":"TN16 3DR",
    "wof:placetype":"postalcode"
},
  "geometry": {"coordinates":[0.02400719126118,51.3202994282078],"type":"Point"}
}