{
  "type": "Feature",
  "properties": {
    "date:inception_lower": "2008-11-01",
    "date:inception_upper": "2008-11-01",
    "iso:country": "GB",
    "wof:name": "G40 2AG",
    "wof:placetype": "postalcode"
  },
  "geometry": {"coordinates":[-4.229164,55.856364],"type":"Point"}
}
