{
  "type": "Feature",
  "properties": {
    "iso:country": "GB",
    "wof:name": "NE28 8HR",
    "wof:placetype": "postalcode"
  },
  "geometry": {"coordinates":[-1.531801,54.99169],"type":"Point"}
}
