{
  "type": "Feature",
  "properties": {
    "date:inception_lower": "1980-01-01",
    "date:inception_upper": "1980-01-01",
    "iso:country": "GB",
    "wof:name": "NE28 8HR",
    "wof:placetype": "postalcode"
  },
  "geometry": {"coordinates":[-1.531801,54.99169],"type":"Point"}
}
