{
  "type": "Feature",
  "properties": {
    "date:inception_lower": "1998-06-01",
    "date:inception_upper": "1998-06-01",
    "iso:country": "GB",
    "wof:name": "YO1 7EF",
    "wof:placetype": "postalcode"
  },
  "geometry": {"coordinates":[-1.0841,53.962084],"type":"Point"}
}
