{
  "type": "Feature",
  "properties": {
    "iso:country":"GB",
    "wof:name":"YO1 7EF",
    "wof:placetype":"postalcode"
},
  "geometry": {"coordinates":[-1.08410001003185,53.96208386793534],"type":"Point"}
}