{
  "type": "Feature",
  "properties": {
    "date:inception_lower": "1980-01-01",
    "date:inception_upper": "1980-01-01",
    "iso:country": "GB",
    "wof:name": "TF2 8DU",
    "wof:placetype": "postalcode"
  },
  "geometry": {"coordinates":[-2.438783,52.715194],"type":"Point"}
}
