{
  "type": "Feature",
  "properties": {
    "date:inception_lower": "1991-01-01",
    "date:inception_upper": "1991-01-01",
    "iso:country": "GB",
    "wof:name": "FY1 3RX",
    "wof:placetype": "postalcode"
  },
  "geometry": {"coordinates":[-3.041093,53.823405],"type":"Point"}
}
