{
  "type": "Feature",
  "properties": {
    "iso:country":"GB",
    "wof:name":"SY6 6DD",
    "wof:placetype":"postalcode"
},
  "geometry": {"coordinates":[-2.81047805097044,52.53510793096528],"type":"Point"}
}