{
  "type": "Feature",
  "properties": {
    "iso:country": "GB",
    "wof:name": "KT8 9GL",
    "wof:placetype": "postalcode"
  },
  "geometry": {"coordinates":[-0.354566,51.405733],"type":"Point"}
}
