{
  "type": "Feature",
  "properties": {
    "iso:country":"GB",
    "wof:name":"M29 8JA",
    "wof:placetype":"postalcode"
},
  "geometry": {"coordinates":[-2.47299441549468,53.51257338311306],"type":"Point"}
}