{
  "type": "Feature",
  "properties": {
    "iso:country":"GB",
    "wof:name":"LE12 8RL",
    "wof:placetype":"postalcode"
},
  "geometry": {"coordinates":[-1.21768793899207,52.72373930119533],"type":"Point"}
}