{
  "type": "Feature",
  "properties": {
    "iso:country":"GB",
    "wof:name":"TS9 6JT",
    "wof:placetype":"postalcode"
},
  "geometry": {"coordinates":[-1.13967408622501,54.48739023646574],"type":"Point"}
}