{
  "type": "Feature",
  "properties": {
    "iso:country":"GB",
    "wof:name":"S18 1TF",
    "wof:placetype":"postalcode"
},
  "geometry": {"coordinates":[-1.48588017206267,53.29798145624427],"type":"Point"}
}