{
  "type": "Feature",
  "properties": {
    "date:inception_lower": "2023-09-01",
    "date:inception_upper": "2023-09-01",
    "iso:country": "GB",
    "wof:name": "CO4 6EX",
    "wof:placetype": "postalcode"
  },
  "geometry": {"coordinates":[0.889831,51.9194],"type":"Point"}
}
