{
  "type": "Feature",
  "properties": {
    "date:inception_lower": "2003-02-01",
    "date:inception_upper": "2003-02-01",
    "iso:country": "GB",
    "wof:name": "OX29 7WJ",
    "wof:placetype": "postalcode"
  },
  "geometry": {"coordinates":[-1.527204,51.790009],"type":"Point"}
}
