{
  "type": "Feature",
  "properties": {
    "iso:country":"GB",
    "wof:name":"OX29 7WJ",
    "wof:placetype":"postalcode"
},
  "geometry": {"coordinates":[-1.52698377582217,51.78884816554708],"type":"Point"}
}