{
  "type": "Feature",
  "properties": {
    "iso:country":"GB",
    "wof:name":"M23 9QR",
    "wof:placetype":"postalcode"
},
  "geometry": {"coordinates":[-2.29983057704449,53.40522645454345],"type":"Point"}
}