{
  "type": "Feature",
  "properties": {
    "iso:country":"GB",
    "wof:name":"AB24 4RN",
    "wof:placetype":"postalcode"
},
  "geometry": {"coordinates":[-2.11846155148439,57.163187587771],"type":"Point"}
}