{
  "type": "Feature",
  "properties": {
    "iso:country":"GB",
    "wof:name":"DD4 8BL",
    "wof:placetype":"postalcode"
},
  "geometry": {"coordinates":[-2.94538713327683,56.485146632126],"type":"Point"}
}