{
  "type": "Feature",
  "properties": {
    "date:inception_lower": "1980-01-01",
    "date:inception_upper": "1980-01-01",
    "iso:country": "GB",
    "wof:name": "DD4 8BL",
    "wof:placetype": "postalcode"
  },
  "geometry": {"coordinates":[-2.945387,56.485147],"type":"Point"}
}
