{
  "type": "Feature",
  "properties": {
    "iso:country":"GB",
    "wof:name":"SS17 7DX",
    "wof:placetype":"postalcode"
},
  "geometry": {"coordinates":[0.44450581651259,51.52043639798032],"type":"Point"}
}