{
  "type": "Feature",
  "properties": {
    "iso:country":"GB",
    "wof:name":"BN13 1SN",
    "wof:placetype":"postalcode"
},
  "geometry": {"coordinates":[-0.40086573422409,50.82371252588135],"type":"Point"}
}