{
  "type": "Feature",
  "properties": {
    "iso:country":"GB",
    "wof:name":"PL1 3LP",
    "wof:placetype":"postalcode"
},
  "geometry": {"coordinates":[-4.15772898833761,50.36741337765858],"type":"Point"}
}