{
  "type": "Feature",
  "properties": {
    "iso:country":"GB",
    "wof:name":"CO9 2TL",
    "wof:placetype":"postalcode"
},
  "geometry": {"coordinates":[0.65279767458352,51.94689698299163],"type":"Point"}
}