{
  "type": "Feature",
  "properties": {
    "iso:country":"GB",
    "wof:name":"GL19 4EF",
    "wof:placetype":"postalcode"
},
  "geometry": {"coordinates":[-2.20730381817558,51.97511533895909],"type":"Point"}
}