{
  "type": "Feature",
  "properties": {
    "date:inception_lower": "2013-07-01",
    "date:inception_upper": "2013-07-01",
    "iso:country": "GB",
    "wof:name": "HA7 9HL",
    "wof:placetype": "postalcode"
  },
  "geometry": {"coordinates":[-0.295623,51.604467],"type":"Point"}
}
