{
  "type": "Feature",
  "properties": {
    "iso:country":"GB",
    "wof:name":"HD6 2JF",
    "wof:placetype":"postalcode"
},
  "geometry": {"coordinates":[-1.79225080360015,53.71081092414307],"type":"Point"}
}