{
  "type": "Feature",
  "properties": {
    "iso:country": "GB",
    "wof:name": "WV16 6HH",
    "wof:placetype": "postalcode"
  },
  "geometry": {"coordinates":[-2.39362,52.456885],"type":"Point"}
}
