{
  "type": "Feature",
  "properties": {
    "iso:country":"GB",
    "wof:name":"WV16 6HH",
    "wof:placetype":"postalcode"
},
  "geometry": {"coordinates":[-2.39362026157058,52.45688547267162],"type":"Point"}
}