{
  "type": "Feature",
  "properties": {
    "iso:country":"GB",
    "wof:name":"SO40 2NS",
    "wof:placetype":"postalcode"
},
  "geometry": {"coordinates":[-1.58732390677675,50.92366556934358],"type":"Point"}
}