{
  "type": "Feature",
  "properties": {
    "date:inception_lower": "1980-01-01",
    "date:inception_upper": "1980-01-01",
    "iso:country": "GB",
    "wof:name": "LA3 1NL",
    "wof:placetype": "postalcode"
  },
  "geometry": {"coordinates":[-2.890576,54.058702],"type":"Point"}
}
