{
  "type": "Feature",
  "properties": {
    "iso:country":"GB",
    "wof:name":"DL3 9DH",
    "wof:placetype":"postalcode"
},
  "geometry": {"coordinates":[-1.59436233098244,54.53007636403878],"type":"Point"}
}