{
  "type": "Feature",
  "properties": {
    "iso:country": "GB",
    "wof:name": "NR33 7QS",
    "wof:placetype": "postalcode"
  },
  "geometry": {"coordinates":[1.724802,52.443274],"type":"Point"}
}
