{
  "type": "Feature",
  "properties": {
    "iso:country":"GB",
    "wof:name":"S73 8NF",
    "wof:placetype":"postalcode"
},
  "geometry": {"coordinates":[-1.41213585338683,53.52823641074109],"type":"Point"}
}