{
  "type": "Feature",
  "properties": {
    "iso:country": "GB",
    "wof:name": "S73 8NF",
    "wof:placetype": "postalcode"
  },
  "geometry": {"coordinates":[-1.412136,53.528236],"type":"Point"}
}
