{
  "type": "Feature",
  "properties": {
    "iso:country":"GB",
    "wof:name":"W5 4LD",
    "wof:placetype":"postalcode"
},
  "geometry": {"coordinates":[-0.30340781680931,51.50013428026641],"type":"Point"}
}