{
  "type": "Feature",
  "properties": {
    "iso:country":"GB",
    "wof:name":"CH5 2HR",
    "wof:placetype":"postalcode"
},
  "geometry": {"coordinates":[-3.00109749428984,53.21853101932354],"type":"Point"}
}