{
  "type": "Feature",
  "properties": {
    "date:inception_lower": "1990-02-01",
    "date:inception_upper": "1990-02-01",
    "iso:country": "GB",
    "wof:name": "CH5 2HR",
    "wof:placetype": "postalcode"
  },
  "geometry": {"coordinates":[-3.001139,53.218403],"type":"Point"}
}
