{
  "type": "Feature",
  "properties": {
    "date:inception_lower": "2020-06-01",
    "date:inception_upper": "2020-06-01",
    "iso:country": "GB",
    "wof:name": "SG14 1FL",
    "wof:placetype": "postalcode"
  },
  "geometry": {"coordinates":[-0.078815,51.797014],"type":"Point"}
}
