{
  "type": "Feature",
  "properties": {
    "date:inception_lower": "2020-12-01",
    "date:inception_upper": "2020-12-01",
    "iso:country": "GB",
    "wof:name": "RG17 0QT",
    "wof:placetype": "postalcode"
  },
  "geometry": {"coordinates":[-1.538735,51.435902],"type":"Point"}
}
