{
  "type": "Feature",
  "properties": {
    "iso:country":"GB",
    "wof:name":"NE12 5XT",
    "wof:placetype":"postalcode"
},
  "geometry": {"coordinates":[-1.57782368553326,55.04286446264004],"type":"Point"}
}