{
  "type": "Feature",
  "properties": {
    "iso:country":"GB",
    "wof:name":"TA9 4RA",
    "wof:placetype":"postalcode"
},
  "geometry": {"coordinates":[-2.94968185777909,51.21856445412825],"type":"Point"}
}