{
  "type": "Feature",
  "properties": {
    "iso:country":"GB",
    "wof:name":"DA6 7HG",
    "wof:placetype":"postalcode"
},
  "geometry": {"coordinates":[0.14201445284009,51.45522684369266],"type":"Point"}
}