{
  "type": "Feature",
  "properties": {
    "iso:country": "GB",
    "wof:name": "DA17 6JB",
    "wof:placetype": "postalcode"
  },
  "geometry": {"coordinates":[0.152569,51.487408],"type":"Point"}
}
