{
  "type": "Feature",
  "properties": {
    "date:inception_lower": "1980-01-01",
    "date:inception_upper": "1980-01-01",
    "iso:country": "GB",
    "wof:name": "TD15 2UG",
    "wof:placetype": "postalcode"
  },
  "geometry": {"coordinates":[-1.978999,55.64857],"type":"Point"}
}
