{
  "type": "Feature",
  "properties": {
    "iso:country":"GB",
    "wof:name":"TD15 2UG",
    "wof:placetype":"postalcode"
},
  "geometry": {"coordinates":[-1.97899931086709,55.64857006806728],"type":"Point"}
}