{
  "type": "Feature",
  "properties": {
    "date:inception_lower": "1980-01-01",
    "date:inception_upper": "1980-01-01",
    "iso:country": "GB",
    "wof:name": "HG3 2TW",
    "wof:placetype": "postalcode"
  },
  "geometry": {"coordinates":[-1.55985,54.004448],"type":"Point"}
}
