{
  "type": "Feature",
  "properties": {
    "iso:country":"GB",
    "wof:name":"B8 3RD",
    "wof:placetype":"postalcode"
},
  "geometry": {"coordinates":[-1.82916122428763,52.48641994642265],"type":"Point"}
}