{
  "type": "Feature",
  "properties": {
    "iso:country": "GB",
    "wof:name": "B8 3RD",
    "wof:placetype": "postalcode"
  },
  "geometry": {"coordinates":[-1.829161,52.48642],"type":"Point"}
}
