{
  "type": "Feature",
  "properties": {
    "date:inception_lower": "2022-02-01",
    "date:inception_upper": "2022-02-01",
    "iso:country": "GB",
    "wof:name": "SP8 4YU",
    "wof:placetype": "postalcode"
  },
  "geometry": {"coordinates":[-2.271955,51.039936],"type":"Point"}
}
