{
  "type": "Feature",
  "properties": {
    "date:inception_lower": "1991-09-01",
    "date:inception_upper": "1991-09-01",
    "iso:country": "GB",
    "wof:name": "B60 3PR",
    "wof:placetype": "postalcode"
  },
  "geometry": {"coordinates":[-2.069641,52.318866],"type":"Point"}
}
