{
  "type": "Feature",
  "properties": {
    "date:inception_lower":"1995-07-01",
    "date:inception_upper":"1995-07-31",
    "iso:country":"GB",
    "wof:name":"RG18 4NX",
    "wof:placetype":"postalcode"
},
  "geometry": {"coordinates":[-1.23908,51.41197],"type":"Point"}
}