{
  "type": "Feature",
  "properties": {
    "iso:country": "GB",
    "wof:name": "RG18 4NX",
    "wof:placetype": "postalcode"
  },
  "geometry": {"coordinates":[-1.23908,51.41197],"type":"Point"}
}
