{
  "type": "Feature",
  "properties": {
    "iso:country": "GB",
    "wof:name": "GL2 0JR",
    "wof:placetype": "postalcode"
  },
  "geometry": {"coordinates":[-2.209134,51.874316],"type":"Point"}
}
