{
  "type": "Feature",
  "properties": {
    "iso:country":"GB",
    "wof:name":"TN15 6JD",
    "wof:placetype":"postalcode"
},
  "geometry": {"coordinates":[0.2697777669791,51.33962521019494],"type":"Point"}
}