{
  "type": "Feature",
  "properties": {
    "date:inception_lower": "1980-01-01",
    "date:inception_upper": "1980-01-01",
    "iso:country": "GB",
    "wof:name": "CR0 8NJ",
    "wof:placetype": "postalcode"
  },
  "geometry": {"coordinates":[-0.029011,51.369415],"type":"Point"}
}
