{
  "type": "Feature",
  "properties": {
    "iso:country": "GB",
    "wof:name": "CR0 8NJ",
    "wof:placetype": "postalcode"
  },
  "geometry": {"coordinates":[-0.029011,51.369415],"type":"Point"}
}
