{
  "type": "Feature",
  "properties": {
    "iso:country":"GB",
    "wof:name":"NG18 3JH",
    "wof:placetype":"postalcode"
},
  "geometry": {"coordinates":[-1.16712836512327,53.13980796903519],"type":"Point"}
}