{
  "type": "Feature",
  "properties": {
    "date:inception_lower": "1999-06-01",
    "date:inception_upper": "1999-06-01",
    "iso:country": "GB",
    "wof:name": "NP24 6NQ",
    "wof:placetype": "postalcode"
  },
  "geometry": {"coordinates":[-3.237107,51.718512],"type":"Point"}
}
