{
  "type": "Feature",
  "properties": {
    "iso:country": "GB",
    "wof:name": "NP24 6NQ",
    "wof:placetype": "postalcode"
  },
  "geometry": {"coordinates":[-3.237107,51.718512],"type":"Point"}
}
