{
  "type": "Feature",
  "properties": {
    "iso:country":"GB",
    "wof:name":"WA7 6NR",
    "wof:placetype":"postalcode"
},
  "geometry": {"coordinates":[-2.66540734730036,53.334975052346],"type":"Point"}
}