{
  "type": "Feature",
  "properties": {
    "iso:country": "GB",
    "wof:name": "WA7 6NR",
    "wof:placetype": "postalcode"
  },
  "geometry": {"coordinates":[-2.665407,53.334975],"type":"Point"}
}
