{
  "type": "Feature",
  "properties": {
    "iso:country":"GB",
    "wof:name":"LA12 7DA",
    "wof:placetype":"postalcode"
},
  "geometry": {"coordinates":[-3.09760626376237,54.20016907916163],"type":"Point"}
}