{
  "type": "Feature",
  "properties": {
    "iso:country":"GB",
    "wof:name":"RG20 9QS",
    "wof:placetype":"postalcode"
},
  "geometry": {"coordinates":[-1.37290293788092,51.34360671784006],"type":"Point"}
}