{
  "type": "Feature",
  "properties": {
    "date:inception_lower": "1995-07-01",
    "date:inception_upper": "1995-07-01",
    "iso:country": "GB",
    "wof:name": "RG20 9QS",
    "wof:placetype": "postalcode"
  },
  "geometry": {"coordinates":[-1.372903,51.343607],"type":"Point"}
}
