{
  "type": "Feature",
  "properties": {
    "iso:country":"GB",
    "wof:name":"CW10 0EX",
    "wof:placetype":"postalcode"
},
  "geometry": {"coordinates":[-2.43493162731708,53.17904796858125],"type":"Point"}
}