{
  "type": "Feature",
  "properties": {
    "date:inception_lower": "1996-12-01",
    "date:inception_upper": "1996-12-01",
    "iso:country": "GB",
    "wof:name": "SK22 4JG",
    "wof:placetype": "postalcode"
  },
  "geometry": {"coordinates":[-1.987983,53.367383],"type":"Point"}
}
