{
  "type": "Feature",
  "properties": {
    "iso:country":"GB",
    "wof:name":"DN21 3LJ",
    "wof:placetype":"postalcode"
},
  "geometry": {"coordinates":[-0.72864695202461,53.43847140668086],"type":"Point"}
}