{
  "type": "Feature",
  "properties": {
    "iso:country": "GB",
    "wof:name": "PE28 4WS",
    "wof:placetype": "postalcode"
  },
  "geometry": {"coordinates":[-0.259276,52.371025],"type":"Point"}
}
