{
  "type": "Feature",
  "properties": {
    "date:inception_lower": "2018-04-01",
    "date:inception_upper": "2018-04-01",
    "iso:country": "GB",
    "wof:name": "CO3 8BD",
    "wof:placetype": "postalcode"
  },
  "geometry": {"coordinates":[0.823149,51.886359],"type":"Point"}
}
