{
  "type": "Feature",
  "properties": {
    "iso:country": "GB",
    "wof:name": "CO3 8BD",
    "wof:placetype": "postalcode"
  },
  "geometry": {"coordinates":[0.823149,51.886359],"type":"Point"}
}
