{
  "type": "Feature",
  "properties": {
    "date:inception_lower": "2004-08-01",
    "date:inception_upper": "2004-08-01",
    "iso:country": "GB",
    "wof:name": "TS12 2EG",
    "wof:placetype": "postalcode"
  },
  "geometry": {"coordinates":[-0.984718,54.560981],"type":"Point"}
}
