{
  "type": "Feature",
  "properties": {
    "iso:country":"GB",
    "wof:name":"SG8 7DB",
    "wof:placetype":"postalcode"
},
  "geometry": {"coordinates":[-0.01901208053228,52.05020315825629],"type":"Point"}
}