{
  "type": "Feature",
  "properties": {
    "iso:country":"GB",
    "wof:name":"DA5 1HJ",
    "wof:placetype":"postalcode"
},
  "geometry": {"coordinates":[0.14005951878735,51.4491293709282],"type":"Point"}
}