{
  "type": "Feature",
  "properties": {
    "iso:country": "GB",
    "wof:name": "WF9 3PW",
    "wof:placetype": "postalcode"
  },
  "geometry": {"coordinates":[-1.324346,53.590306],"type":"Point"}
}
