{
  "type": "Feature",
  "properties": {
    "iso:country":"GB",
    "wof:name":"CF38 1NU",
    "wof:placetype":"postalcode"
},
  "geometry": {"coordinates":[-3.31296791148634,51.56660864995332],"type":"Point"}
}