{
  "type": "Feature",
  "properties": {
    "date:inception_lower": "1980-01-01",
    "date:inception_upper": "1980-01-01",
    "iso:country": "GB",
    "wof:name": "CF38 1NU",
    "wof:placetype": "postalcode"
  },
  "geometry": {"coordinates":[-3.312968,51.566609],"type":"Point"}
}
