{
  "type": "Feature",
  "properties": {
    "iso:country":"GB",
    "wof:name":"PO7 5HP",
    "wof:placetype":"postalcode"
},
  "geometry": {"coordinates":[-1.03504865177696,50.86724429539908],"type":"Point"}
}