{
  "type": "Feature",
  "properties": {
    "iso:country": "GB",
    "wof:name": "GU7 1QD",
    "wof:placetype": "postalcode"
  },
  "geometry": {"coordinates":[-0.613039,51.180365],"type":"Point"}
}
