{
  "type": "Feature",
  "properties": {
    "iso:country": "GB",
    "wof:name": "EX32 7NY",
    "wof:placetype": "postalcode"
  },
  "geometry": {"coordinates":[-3.966558,51.086407],"type":"Point"}
}
