{
  "type": "Feature",
  "properties": {
    "iso:country":"GB",
    "wof:name":"EX32 7NY",
    "wof:placetype":"postalcode"
},
  "geometry": {"coordinates":[-3.96655783082627,51.08640676012431],"type":"Point"}
}