{
  "type": "Feature",
  "properties": {
    "iso:country":"GB",
    "wof:name":"CM13 3HU",
    "wof:placetype":"postalcode"
},
  "geometry": {"coordinates":[0.28433686419279,51.59327156328411],"type":"Point"}
}