{
  "type": "Feature",
  "properties": {
    "iso:country":"GB",
    "wof:name":"TA4 3QW",
    "wof:placetype":"postalcode"
},
  "geometry": {"coordinates":[-3.26003803802742,51.09516153472167],"type":"Point"}
}