{
  "type": "Feature",
  "properties": {
    "iso:country": "GB",
    "wof:name": "TA4 3QW",
    "wof:placetype": "postalcode"
  },
  "geometry": {"coordinates":[-3.260049,51.095157],"type":"Point"}
}
