{
  "type": "Feature",
  "properties": {
    "iso:country": "GB",
    "wof:name": "BA22 8NN",
    "wof:placetype": "postalcode"
  },
  "geometry": {"coordinates":[-2.684392,51.000279],"type":"Point"}
}
