{
  "type": "Feature",
  "properties": {
    "iso:country": "GB",
    "wof:name": "NG8 1NA",
    "wof:placetype": "postalcode"
  },
  "geometry": {"coordinates":[-1.1932,52.956794],"type":"Point"}
}
