{
  "type": "Feature",
  "properties": {
    "date:inception_lower": "1980-01-01",
    "date:inception_upper": "1980-01-01",
    "iso:country": "GB",
    "wof:name": "NG8 1NA",
    "wof:placetype": "postalcode"
  },
  "geometry": {"coordinates":[-1.1932,52.956794],"type":"Point"}
}
