{
  "type": "Feature",
  "properties": {
    "iso:country":"GB",
    "wof:name":"NG8 1NA",
    "wof:placetype":"postalcode"
},
  "geometry": {"coordinates":[-1.19339157643653,52.95691187289117],"type":"Point"}
}