{
  "type": "Feature",
  "properties": {
    "iso:country":"GB",
    "wof:name":"BH9 3DB",
    "wof:placetype":"postalcode"
},
  "geometry": {"coordinates":[-1.86674690859062,50.75037629000835],"type":"Point"}
}