{
  "type": "Feature",
  "properties": {
    "date:inception_lower":"2004-01-01",
    "date:inception_upper":"2004-01-31",
    "iso:country":"GB",
    "wof:name":"WA5 8GB",
    "wof:placetype":"postalcode"
},
  "geometry": {"coordinates":[-2.631008,53.399378],"type":"Point"}
}