{
  "type": "Feature",
  "properties": {
    "iso:country": "GB",
    "wof:name": "WS10 7WL",
    "wof:placetype": "postalcode"
  },
  "geometry": {"coordinates":[-2.030082,52.54483],"type":"Point"}
}
