{
  "type": "Feature",
  "properties": {
    "iso:country":"GB",
    "wof:name":"WS10 7WL",
    "wof:placetype":"postalcode"
},
  "geometry": {"coordinates":[-2.0300821712653,52.54482953940695],"type":"Point"}
}