{
  "type": "Feature",
  "properties": {
    "iso:country":"GB",
    "wof:name":"HU12 9AG",
    "wof:placetype":"postalcode"
},
  "geometry": {"coordinates":[-0.09233054307906,53.7808544025251],"type":"Point"}
}