{
  "type": "Feature",
  "properties": {
    "iso:country":"GB",
    "wof:name":"G41 1EE",
    "wof:placetype":"postalcode"
},
  "geometry": {"coordinates":[-4.28315546106049,55.85171612367436],"type":"Point"}
}