{
  "type": "Feature",
  "properties": {
    "iso:country": "GB",
    "wof:name": "NR26 8JJ",
    "wof:placetype": "postalcode"
  },
  "geometry": {"coordinates":[1.211422,52.940013],"type":"Point"}
}
