{
  "type": "Feature",
  "properties": {
    "iso:country":"GB",
    "wof:name":"NR26 8JJ",
    "wof:placetype":"postalcode"
},
  "geometry": {"coordinates":[1.2113752493058,52.93999407363848],"type":"Point"}
}