{
  "type": "Feature",
  "properties": {
    "iso:country": "GB",
    "wof:name": "SE1 7XP",
    "wof:placetype": "postalcode"
  },
  "geometry": {"coordinates":[-0.105932,51.49846],"type":"Point"}
}
