{
  "type": "Feature",
  "properties": {
    "date:inception_lower":"1980-01-01",
    "date:inception_upper":"1980-01-31",
    "iso:country":"GB",
    "wof:name":"M4 5EA",
    "wof:placetype":"postalcode"
},
  "geometry": {"coordinates":[-2.229267,53.485704],"type":"Point"}
}