{
  "type": "Feature",
  "properties": {
    "iso:country":"GB",
    "wof:name":"B14 7QU",
    "wof:placetype":"postalcode"
},
  "geometry": {"coordinates":[-1.89475927026383,52.43384194525989],"type":"Point"}
}