{
  "type": "Feature",
  "properties": {
    "iso:country": "GB",
    "wof:name": "HP3 8RR",
    "wof:placetype": "postalcode"
  },
  "geometry": {"coordinates":[-0.440445,51.729176],"type":"Point"}
}
