{
  "type": "Feature",
  "properties": {
    "iso:country":"GB",
    "wof:name":"HP3 8RR",
    "wof:placetype":"postalcode"
},
  "geometry": {"coordinates":[-0.44044478758371,51.72917552390064],"type":"Point"}
}