{
  "type": "Feature",
  "properties": {
    "date:inception_lower": "1980-01-01",
    "date:inception_upper": "1980-01-01",
    "iso:country": "GB",
    "wof:name": "HP3 8RR",
    "wof:placetype": "postalcode"
  },
  "geometry": {"coordinates":[-0.440445,51.729176],"type":"Point"}
}
