{
  "type": "Feature",
  "properties": {
    "date:inception_lower": "1998-06-01",
    "date:inception_upper": "1998-06-01",
    "iso:country": "GB",
    "wof:name": "YO32 4AF",
    "wof:placetype": "postalcode"
  },
  "geometry": {"coordinates":[-1.076759,53.988048],"type":"Point"}
}
