{
  "type": "Feature",
  "properties": {
    "iso:country":"GB",
    "wof:name":"YO32 4AF",
    "wof:placetype":"postalcode"
},
  "geometry": {"coordinates":[-1.07675890097437,53.98804809193834],"type":"Point"}
}