{
  "type": "Feature",
  "properties": {
    "iso:country": "GB",
    "wof:name": "LU2 8NX",
    "wof:placetype": "postalcode"
  },
  "geometry": {"coordinates":[-0.354824,51.889051],"type":"Point"}
}
