{
  "type": "Feature",
  "properties": {
    "iso:country":"GB",
    "wof:name":"LU2 8NX",
    "wof:placetype":"postalcode"
},
  "geometry": {"coordinates":[-0.35486256292265,51.88905272850135],"type":"Point"}
}