{
  "type": "Feature",
  "properties": {
    "iso:country": "GB",
    "wof:name": "N4 3SA",
    "wof:placetype": "postalcode"
  },
  "geometry": {"coordinates":[-0.111117,51.569558],"type":"Point"}
}
