{
  "type": "Feature",
  "properties": {
    "iso:country":"GB",
    "wof:name":"BS37 4BZ",
    "wof:placetype":"postalcode"
},
  "geometry": {"coordinates":[-2.42533583508705,51.54005111207073],"type":"Point"}
}