{
  "type": "Feature",
  "properties": {
    "iso:country": "GB",
    "wof:name": "BS37 4BZ",
    "wof:placetype": "postalcode"
  },
  "geometry": {"coordinates":[-2.425336,51.540051],"type":"Point"}
}
