{
  "type": "Feature",
  "properties": {
    "iso:country":"GB",
    "wof:name":"AL4 0AG",
    "wof:placetype":"postalcode"
},
  "geometry": {"coordinates":[-0.295038398574,51.74753170061626],"type":"Point"}
}