{
  "type": "Feature",
  "properties": {
    "date:inception_lower": "2000-06-01",
    "date:inception_upper": "2000-06-01",
    "iso:country": "GB",
    "wof:name": "AL4 0AG",
    "wof:placetype": "postalcode"
  },
  "geometry": {"coordinates":[-0.295038,51.747532],"type":"Point"}
}
