{
  "type": "Feature",
  "properties": {
    "iso:country":"GB",
    "wof:name":"W1W 5NU",
    "wof:placetype":"postalcode"
},
  "geometry": {"coordinates":[-0.14242343623885,51.52049095791341],"type":"Point"}
}