{
  "type": "Feature",
  "properties": {
    "iso:country": "GB",
    "wof:name": "TN25 4PS",
    "wof:placetype": "postalcode"
  },
  "geometry": {"coordinates":[0.894842,51.170407],"type":"Point"}
}
