{
  "type": "Feature",
  "properties": {
    "iso:country":"GB",
    "wof:name":"RH6 7EZ",
    "wof:placetype":"postalcode"
},
  "geometry": {"coordinates":[-0.16782103090352,51.17162266227843],"type":"Point"}
}