{
  "type": "Feature",
  "properties": {
    "iso:country":"GB",
    "wof:name":"LU3 1PH",
    "wof:placetype":"postalcode"
},
  "geometry": {"coordinates":[-0.43563899038741,51.90006309199124],"type":"Point"}
}