{
  "type": "Feature",
  "properties": {
    "iso:country":"GB",
    "wof:name":"GL54 4NH",
    "wof:placetype":"postalcode"
},
  "geometry": {"coordinates":[-1.90467279961013,51.79538848101938],"type":"Point"}
}