{
  "type": "Feature",
  "properties": {
    "iso:country":"GB",
    "wof:name":"SG1 5PA",
    "wof:placetype":"postalcode"
},
  "geometry": {"coordinates":[-0.18141440991836,51.91308895866162],"type":"Point"}
}