{
  "type": "Feature",
  "properties": {
    "date:inception_lower": "1980-01-01",
    "date:inception_upper": "1980-01-01",
    "iso:country": "GB",
    "wof:name": "SG1 5PA",
    "wof:placetype": "postalcode"
  },
  "geometry": {"coordinates":[-0.181414,51.913089],"type":"Point"}
}
