{
  "type": "Feature",
  "properties": {
    "iso:country":"GB",
    "wof:name":"SN5 6HB",
    "wof:placetype":"postalcode"
},
  "geometry": {"coordinates":[-1.84573512557379,51.55934308744935],"type":"Point"}
}