{
  "type": "Feature",
  "properties": {
    "iso:country":"GB",
    "wof:name":"WS7 1AN",
    "wof:placetype":"postalcode"
},
  "geometry": {"coordinates":[-1.93532865354402,52.68377053663857],"type":"Point"}
}