{
  "type": "Feature",
  "properties": {
    "iso:country":"GB",
    "wof:name":"BS4 4PL",
    "wof:placetype":"postalcode"
},
  "geometry": {"coordinates":[-2.54874024544948,51.43992997123785],"type":"Point"}
}