{
  "type": "Feature",
  "properties": {
    "iso:country":"GB",
    "wof:name":"HG3 3SQ",
    "wof:placetype":"postalcode"
},
  "geometry": {"coordinates":[-1.49766658656092,54.06997681056684],"type":"Point"}
}