{
  "type": "Feature",
  "properties": {
    "iso:country":"GB",
    "wof:name":"IP7 6QY",
    "wof:placetype":"postalcode"
},
  "geometry": {"coordinates":[0.94232693055287,52.08715618082147],"type":"Point"}
}