{
  "type": "Feature",
  "properties": {
    "date:inception_lower": "1980-01-01",
    "date:inception_upper": "1980-01-01",
    "iso:country": "GB",
    "wof:name": "SY8 3QU",
    "wof:placetype": "postalcode"
  },
  "geometry": {"coordinates":[-2.572016,52.374288],"type":"Point"}
}
