{
  "type": "Feature",
  "properties": {
    "iso:country": "GB",
    "wof:name": "SY8 3QU",
    "wof:placetype": "postalcode"
  },
  "geometry": {"coordinates":[-2.572572,52.375099],"type":"Point"}
}
