{
  "type": "Feature",
  "properties": {
    "iso:country":"GB",
    "wof:name":"TN38 0YN",
    "wof:placetype":"postalcode"
},
  "geometry": {"coordinates":[0.54960967941009,50.85259912958017],"type":"Point"}
}