{
  "type": "Feature",
  "properties": {
    "iso:country": "GB",
    "wof:name": "W1G 9TG",
    "wof:placetype": "postalcode"
  },
  "geometry": {"coordinates":[-0.148208,51.519305],"type":"Point"}
}
