{
  "type": "Feature",
  "properties": {
    "date:inception_lower": "1980-01-01",
    "date:inception_upper": "1980-01-01",
    "iso:country": "GB",
    "wof:name": "NE24 5SN",
    "wof:placetype": "postalcode"
  },
  "geometry": {"coordinates":[-1.526814,55.120632],"type":"Point"}
}
