{
  "type": "Feature",
  "properties": {
    "iso:country":"GB",
    "wof:name":"LU2 9NW",
    "wof:placetype":"postalcode"
},
  "geometry": {"coordinates":[-0.37190635539508,51.88347212885895],"type":"Point"}
}