{
  "type": "Feature",
  "properties": {
    "date:inception_lower":"2000-06-01",
    "date:inception_upper":"2000-06-30",
    "iso:country":"GB",
    "wof:name":"LU2 9NW",
    "wof:placetype":"postalcode"
},
  "geometry": {"coordinates":[-0.371906,51.883472],"type":"Point"}
}