{
  "type": "Feature",
  "properties": {
    "iso:country":"GB",
    "wof:name":"NR27 0LF",
    "wof:placetype":"postalcode"
},
  "geometry": {"coordinates":[1.33743554899874,52.90619147609224],"type":"Point"}
}