{
  "type": "Feature",
  "properties": {
    "date:inception_lower":"1980-01-01",
    "date:inception_upper":"1980-01-31",
    "iso:country":"GB",
    "wof:name":"NR27 0LF",
    "wof:placetype":"postalcode"
},
  "geometry": {"coordinates":[1.337462,52.906301],"type":"Point"}
}