{
  "type": "Feature",
  "properties": {
    "date:inception_lower": "1980-01-01",
    "date:inception_upper": "1980-01-01",
    "iso:country": "GB",
    "wof:name": "NP4 9PF",
    "wof:placetype": "postalcode"
  },
  "geometry": {"coordinates":[-3.079375,51.778071],"type":"Point"}
}
