{
  "type": "Feature",
  "properties": {
    "iso:country":"GB",
    "wof:name":"NP4 9PF",
    "wof:placetype":"postalcode"
},
  "geometry": {"coordinates":[-3.07937548696402,51.77807108375181],"type":"Point"}
}