{
  "type": "Feature",
  "properties": {
    "date:inception_lower":"1980-01-01",
    "date:inception_upper":"1980-01-31",
    "iso:country":"GB",
    "wof:name":"BD17 5DX",
    "wof:placetype":"postalcode"
},
  "geometry": {"coordinates":[-1.788445,53.847404],"type":"Point"}
}