{
  "type": "Feature",
  "properties": {
    "iso:country": "GB",
    "wof:name": "KY8 5TU",
    "wof:placetype": "postalcode"
  },
  "geometry": {"coordinates":[-3.046617,56.210471],"type":"Point"}
}
