{
  "type": "Feature",
  "properties": {
    "iso:country":"GB",
    "wof:name":"E4 8BS",
    "wof:placetype":"postalcode"
},
  "geometry": {"coordinates":[-0.01587675417233,51.62625747642664],"type":"Point"}
}