{
  "type": "Feature",
  "properties": {
    "date:inception_lower": "1980-01-01",
    "date:inception_upper": "1980-01-01",
    "iso:country": "GB",
    "wof:name": "SM1 4QH",
    "wof:placetype": "postalcode"
  },
  "geometry": {"coordinates":[-0.184451,51.366036],"type":"Point"}
}
