{
  "type": "Feature",
  "properties": {
    "date:inception_lower": "1987-04-01",
    "date:inception_upper": "1987-04-01",
    "iso:country": "GB",
    "wof:name": "SL7 3QY",
    "wof:placetype": "postalcode"
  },
  "geometry": {"coordinates":[-0.783645,51.591529],"type":"Point"}
}
