{
  "type": "Feature",
  "properties": {
    "iso:country":"GB",
    "wof:name":"SL7 3QY",
    "wof:placetype":"postalcode"
},
  "geometry": {"coordinates":[-0.78364513623798,51.59152881248838],"type":"Point"}
}