{
  "type": "Feature",
  "properties": {
    "iso:country": "GB",
    "wof:name": "SL7 3QY",
    "wof:placetype": "postalcode"
  },
  "geometry": {"coordinates":[-0.783645,51.591529],"type":"Point"}
}
