{
  "type": "Feature",
  "properties": {
    "iso:country": "GB",
    "wof:name": "TQ7 1QP",
    "wof:placetype": "postalcode"
  },
  "geometry": {"coordinates":[-3.773412,50.283188],"type":"Point"}
}
