{
  "type": "Feature",
  "properties": {
    "iso:country": "GB",
    "wof:name": "LL32 8ET",
    "wof:placetype": "postalcode"
  },
  "geometry": {"coordinates":[-3.841763,53.286822],"type":"Point"}
}
