{
  "type": "Feature",
  "properties": {
    "iso:country":"GB",
    "wof:name":"LL32 8ET",
    "wof:placetype":"postalcode"
},
  "geometry": {"coordinates":[-3.84176315728733,53.28682235249702],"type":"Point"}
}