{
  "type": "Feature",
  "properties": {
    "iso:country":"GB",
    "wof:name":"YO32 5RW",
    "wof:placetype":"postalcode"
},
  "geometry": {"coordinates":[-1.04457649560597,54.03476801386474],"type":"Point"}
}