{
  "type": "Feature",
  "properties": {
    "iso:country": "GB",
    "wof:name": "YO32 5RW",
    "wof:placetype": "postalcode"
  },
  "geometry": {"coordinates":[-1.044586,54.034776],"type":"Point"}
}
