{
  "type": "Feature",
  "properties": {
    "iso:country":"GB",
    "wof:name":"GL1 4EL",
    "wof:placetype":"postalcode"
},
  "geometry": {"coordinates":[-2.23819749278198,51.86012694340567],"type":"Point"}
}