{
  "type": "Feature",
  "properties": {
    "date:inception_lower": "1993-08-01",
    "date:inception_upper": "1993-08-01",
    "iso:country": "GB",
    "wof:name": "LL53 6ND",
    "wof:placetype": "postalcode"
  },
  "geometry": {"coordinates":[-4.521942,52.933569],"type":"Point"}
}
