{
  "type": "Feature",
  "properties": {
    "iso:country":"GB",
    "wof:name":"LL53 6ND",
    "wof:placetype":"postalcode"
},
  "geometry": {"coordinates":[-4.52194218104406,52.93356894462256],"type":"Point"}
}