{
  "type": "Feature",
  "properties": {
    "iso:country":"GB",
    "wof:name":"WD3 3EN",
    "wof:placetype":"postalcode"
},
  "geometry": {"coordinates":[-0.45009223750267,51.64858260079825],"type":"Point"}
}