{
  "type": "Feature",
  "properties": {
    "iso:country":"GB",
    "wof:name":"HD8 0QN",
    "wof:placetype":"postalcode"
},
  "geometry": {"coordinates":[-1.71354524378609,53.61686599610367],"type":"Point"}
}