{
  "type": "Feature",
  "properties": {
    "iso:country": "GB",
    "wof:name": "HD8 0QN",
    "wof:placetype": "postalcode"
  },
  "geometry": {"coordinates":[-1.713545,53.616866],"type":"Point"}
}
