{
  "type": "Feature",
  "properties": {
    "iso:country":"GB",
    "wof:name":"RG42 5JR",
    "wof:placetype":"postalcode"
},
  "geometry": {"coordinates":[-0.78283585554103,51.43418916758893],"type":"Point"}
}