{
  "type": "Feature",
  "properties": {
    "date:inception_lower": "1995-07-01",
    "date:inception_upper": "1995-07-01",
    "iso:country": "GB",
    "wof:name": "RG42 5JR",
    "wof:placetype": "postalcode"
  },
  "geometry": {"coordinates":[-0.78312,51.434203],"type":"Point"}
}
