{
  "type": "Feature",
  "properties": {
    "iso:country": "GB",
    "wof:name": "RG42 5JR",
    "wof:placetype": "postalcode"
  },
  "geometry": {"coordinates":[-0.78312,51.434203],"type":"Point"}
}
