{
  "type": "Feature",
  "properties": {
    "date:inception_lower": "1999-06-01",
    "date:inception_upper": "1999-06-01",
    "iso:country": "GB",
    "wof:name": "CH41 3RZ",
    "wof:placetype": "postalcode"
  },
  "geometry": {"coordinates":[-3.03075,53.395993],"type":"Point"}
}
