{
  "type": "Feature",
  "properties": {
    "iso:country":"GB",
    "wof:name":"CH7 6GD",
    "wof:placetype":"postalcode"
},
  "geometry": {"coordinates":[-3.08894697954122,53.20359333833348],"type":"Point"}
}