{
  "type": "Feature",
  "properties": {
    "iso:country":"GB",
    "wof:name":"NP13 1NR",
    "wof:placetype":"postalcode"
},
  "geometry": {"coordinates":[-3.13873384499695,51.73433385660213],"type":"Point"}
}