{
  "type": "Feature",
  "properties": {
    "date:inception_lower": "1999-06-01",
    "date:inception_upper": "1999-06-01",
    "iso:country": "GB",
    "wof:name": "NP13 1NR",
    "wof:placetype": "postalcode"
  },
  "geometry": {"coordinates":[-3.138734,51.734334],"type":"Point"}
}
