{
  "type": "Feature",
  "properties": {
    "iso:country": "GB",
    "wof:name": "BN3 3AW",
    "wof:placetype": "postalcode"
  },
  "geometry": {"coordinates":[-0.162248,50.827716],"type":"Point"}
}
