{
  "type": "Feature",
  "properties": {
    "iso:country":"GB",
    "wof:name":"BN2 1QH",
    "wof:placetype":"postalcode"
},
  "geometry": {"coordinates":[-0.13168872419117,50.82062981544689],"type":"Point"}
}