{
  "type": "Feature",
  "properties": {
    "iso:country":"GB",
    "wof:name":"M25 3EL",
    "wof:placetype":"postalcode"
},
  "geometry": {"coordinates":[-2.28300321834725,53.53709261674241],"type":"Point"}
}