{
  "type": "Feature",
  "properties": {
    "date:inception_lower": "2016-01-01",
    "date:inception_upper": "2016-01-01",
    "iso:country": "GB",
    "wof:name": "M25 3EL",
    "wof:placetype": "postalcode"
  },
  "geometry": {"coordinates":[-2.285866,53.532356],"type":"Point"}
}
