{
  "type": "Feature",
  "properties": {
    "date:inception_lower":"2016-01-01",
    "date:inception_upper":"2016-01-31",
    "iso:country":"GB",
    "wof:name":"M25 3EL",
    "wof:placetype":"postalcode"
},
  "geometry": {"coordinates":[-2.283003,53.537093],"type":"Point"}
}