{
  "type": "Feature",
  "properties": {
    "iso:country":"GB",
    "wof:name":"RH11 7GP",
    "wof:placetype":"postalcode"
},
  "geometry": {"coordinates":[-0.21058606895097,51.12929846466093],"type":"Point"}
}