{
  "type": "Feature",
  "properties": {
    "iso:country":"GB",
    "wof:name":"SG2 8JL",
    "wof:placetype":"postalcode"
},
  "geometry": {"coordinates":[-0.16591634938653,51.88093603150758],"type":"Point"}
}