{
  "type": "Feature",
  "properties": {
    "iso:country":"GB",
    "wof:name":"SA67 8JE",
    "wof:placetype":"postalcode"
},
  "geometry": {"coordinates":[-4.69586244977286,51.76345958210722],"type":"Point"}
}