{
  "type": "Feature",
  "properties": {
    "iso:country":"GB",
    "wof:name":"SL4 3TQ",
    "wof:placetype":"postalcode"
},
  "geometry": {"coordinates":[-0.62942606043067,51.4748669466298],"type":"Point"}
}