{
  "type": "Feature",
  "properties": {
    "date:inception_lower": "2002-06-01",
    "date:inception_upper": "2002-06-01",
    "iso:country": "GB",
    "wof:name": "SL4 3TQ",
    "wof:placetype": "postalcode"
  },
  "geometry": {"coordinates":[-0.629426,51.474867],"type":"Point"}
}
