{
  "type": "Feature",
  "properties": {
    "iso:country":"GB",
    "wof:name":"BB7 9DJ",
    "wof:placetype":"postalcode"
},
  "geometry": {"coordinates":[-2.33626049090233,53.83088585902352],"type":"Point"}
}