{
  "type": "Feature",
  "properties": {
    "iso:country":"GB",
    "wof:name":"PR4 4BE",
    "wof:placetype":"postalcode"
},
  "geometry": {"coordinates":[-2.74929059196694,53.72611025469362],"type":"Point"}
}