{
  "type": "Feature",
  "properties": {
    "iso:country": "GB",
    "wof:name": "PR4 4BE",
    "wof:placetype": "postalcode"
  },
  "geometry": {"coordinates":[-2.749291,53.72611],"type":"Point"}
}
