{
  "type": "Feature",
  "properties": {
    "iso:country": "GB",
    "wof:name": "SK10 4QH",
    "wof:placetype": "postalcode"
  },
  "geometry": {"coordinates":[-2.178385,53.301112],"type":"Point"}
}
