{
  "type": "Feature",
  "properties": {
    "iso:country":"GB",
    "wof:name":"LS14 1JL",
    "wof:placetype":"postalcode"
},
  "geometry": {"coordinates":[-1.47851556844352,53.82343966830194],"type":"Point"}
}