{
  "type": "Feature",
  "properties": {
    "iso:country":"GB",
    "wof:name":"HU3 3HY",
    "wof:placetype":"postalcode"
},
  "geometry": {"coordinates":[-0.36875833907717,53.74027620560649],"type":"Point"}
}