{
  "type": "Feature",
  "properties": {
    "iso:country":"GB",
    "wof:name":"E2 9PF",
    "wof:placetype":"postalcode"
},
  "geometry": {"coordinates":[-0.05330890121263,51.52871282429983],"type":"Point"}
}