{
  "type": "Feature",
  "properties": {
    "iso:country": "GB",
    "wof:name": "PA23 7DX",
    "wof:placetype": "postalcode"
  },
  "geometry": {"coordinates":[-4.926827,55.948251],"type":"Point"}
}
