{
  "type": "Feature",
  "properties": {
    "iso:country":"GB",
    "wof:name":"PA23 7DX",
    "wof:placetype":"postalcode"
},
  "geometry": {"coordinates":[-4.92682723500279,55.94825131768625],"type":"Point"}
}