{
  "type": "Feature",
  "properties": {
    "date:inception_lower": "1997-06-01",
    "date:inception_upper": "1997-06-01",
    "iso:country": "GB",
    "wof:name": "PA23 7DX",
    "wof:placetype": "postalcode"
  },
  "geometry": {"coordinates":[-4.926827,55.948251],"type":"Point"}
}
