{
  "type": "Feature",
  "properties": {
    "iso:country":"GB",
    "wof:name":"NN15 5FE",
    "wof:placetype":"postalcode"
},
  "geometry": {"coordinates":[-0.6858389785443,52.36594693432659],"type":"Point"}
}