{
  "type": "Feature",
  "properties": {
    "date:inception_lower": "2010-03-01",
    "date:inception_upper": "2010-03-01",
    "iso:country": "GB",
    "wof:name": "NN15 5FE",
    "wof:placetype": "postalcode"
  },
  "geometry": {"coordinates":[-0.685898,52.365948],"type":"Point"}
}
