{
  "type": "Feature",
  "properties": {
    "date:inception_lower": "1980-01-01",
    "date:inception_upper": "1980-01-01",
    "iso:country": "GB",
    "wof:name": "NG16 3DG",
    "wof:placetype": "postalcode"
  },
  "geometry": {"coordinates":[-1.305868,53.022057],"type":"Point"}
}
