{
  "type": "Feature",
  "properties": {
    "iso:country":"GB",
    "wof:name":"M27 5LY",
    "wof:placetype":"postalcode"
},
  "geometry": {"coordinates":[-2.32442429717607,53.50204935040915],"type":"Point"}
}