{
  "type": "Feature",
  "properties": {
    "iso:country": "GB",
    "wof:name": "M27 5LY",
    "wof:placetype": "postalcode"
  },
  "geometry": {"coordinates":[-2.324424,53.502049],"type":"Point"}
}
