{
  "type": "Feature",
  "properties": {
    "iso:country":"GB",
    "wof:name":"NG9 8GX",
    "wof:placetype":"postalcode"
},
  "geometry": {"coordinates":[-1.27345054384971,52.94344046010994],"type":"Point"}
}