{
  "type": "Feature",
  "properties": {
    "date:inception_lower": "1980-01-01",
    "date:inception_upper": "1980-01-01",
    "iso:country": "GB",
    "wof:name": "NG9 8GX",
    "wof:placetype": "postalcode"
  },
  "geometry": {"coordinates":[-1.27345,52.94344],"type":"Point"}
}
