{
  "type": "Feature",
  "properties": {
    "iso:country":"GB",
    "wof:name":"BB7 9LP",
    "wof:placetype":"postalcode"
},
  "geometry": {"coordinates":[-2.42383912828201,53.81451075088577],"type":"Point"}
}