{
  "type": "Feature",
  "properties": {
    "iso:country":"GB",
    "wof:name":"DH1 1JD",
    "wof:placetype":"postalcode"
},
  "geometry": {"coordinates":[-1.55609341288038,54.77990871758008],"type":"Point"}
}