{
  "type": "Feature",
  "properties": {
    "iso:country":"GB",
    "wof:name":"G22 7QW",
    "wof:placetype":"postalcode"
},
  "geometry": {"coordinates":[-4.25653305493222,55.89626387904399],"type":"Point"}
}