{
  "type": "Feature",
  "properties": {
    "date:inception_lower":"1980-01-01",
    "date:inception_upper":"1980-01-31",
    "iso:country":"GB",
    "wof:name":"G22 7QW",
    "wof:placetype":"postalcode"
},
  "geometry": {"coordinates":[-4.256533,55.896264],"type":"Point"}
}