{
  "type": "Feature",
  "properties": {
    "date:inception_lower": "1980-01-01",
    "date:inception_upper": "1980-01-01",
    "iso:country": "GB",
    "wof:name": "SP5 2LJ",
    "wof:placetype": "postalcode"
  },
  "geometry": {"coordinates":[-1.715557,50.981851],"type":"Point"}
}
