{
  "type": "Feature",
  "properties": {
    "iso:country":"GB",
    "wof:name":"SP5 2LJ",
    "wof:placetype":"postalcode"
},
  "geometry": {"coordinates":[-1.71555736379689,50.98185076009637],"type":"Point"}
}