{
  "type": "Feature",
  "properties": {
    "iso:country":"GB",
    "wof:name":"BB4 4PQ",
    "wof:placetype":"postalcode"
},
  "geometry": {"coordinates":[-2.33603271133589,53.69800713433914],"type":"Point"}
}