{
  "type": "Feature",
  "properties": {
    "iso:country": "GB",
    "wof:name": "BB4 4PQ",
    "wof:placetype": "postalcode"
  },
  "geometry": {"coordinates":[-2.336033,53.698007],"type":"Point"}
}
