{
  "type": "Feature",
  "properties": {
    "iso:country":"GB",
    "wof:name":"NG6 8UY",
    "wof:placetype":"postalcode"
},
  "geometry": {"coordinates":[-1.21258486288298,53.00660821650986],"type":"Point"}
}