{
  "type": "Feature",
  "properties": {
    "iso:country": "GB",
    "wof:name": "SA32 7EB",
    "wof:placetype": "postalcode"
  },
  "geometry": {"coordinates":[-4.264108,51.962733],"type":"Point"}
}
