{
  "type": "Feature",
  "properties": {
    "iso:country":"GB",
    "wof:name":"NR30 1JL",
    "wof:placetype":"postalcode"
},
  "geometry": {"coordinates":[1.72240882787234,52.60955571383338],"type":"Point"}
}