{
  "type": "Feature",
  "properties": {
    "iso:country": "GB",
    "wof:name": "NR30 1JL",
    "wof:placetype": "postalcode"
  },
  "geometry": {"coordinates":[1.722432,52.609582],"type":"Point"}
}
