{
  "type": "Feature",
  "properties": {
    "date:inception_lower": "2019-03-01",
    "date:inception_upper": "2019-03-01",
    "iso:country": "GB",
    "wof:name": "TS8 9GN",
    "wof:placetype": "postalcode"
  },
  "geometry": {"coordinates":[-1.227901,54.520513],"type":"Point"}
}
