{
  "type": "Feature",
  "properties": {
    "iso:country": "GB",
    "wof:name": "WR9 8HJ",
    "wof:placetype": "postalcode"
  },
  "geometry": {"coordinates":[-2.144454,52.267275],"type":"Point"}
}
