{
  "type": "Feature",
  "properties": {
    "date:inception_lower": "1988-03-01",
    "date:inception_upper": "1988-03-01",
    "iso:country": "GB",
    "wof:name": "WR9 8HJ",
    "wof:placetype": "postalcode"
  },
  "geometry": {"coordinates":[-2.144454,52.267275],"type":"Point"}
}
