{
  "type": "Feature",
  "properties": {
    "iso:country": "GB",
    "wof:name": "TN17 1HL",
    "wof:placetype": "postalcode"
  },
  "geometry": {"coordinates":[0.437421,51.098525],"type":"Point"}
}
