{
  "type": "Feature",
  "properties": {
    "iso:country":"GB",
    "wof:name":"ML6 0AE",
    "wof:placetype":"postalcode"
},
  "geometry": {"coordinates":[-3.98285188769629,55.864679269684],"type":"Point"}
}