{
  "type": "Feature",
  "properties": {
    "date:inception_lower": "2008-11-01",
    "date:inception_upper": "2008-11-01",
    "iso:country": "GB",
    "wof:name": "ML6 0AE",
    "wof:placetype": "postalcode"
  },
  "geometry": {"coordinates":[-3.982717,55.86474],"type":"Point"}
}
