{
  "type": "Feature",
  "properties": {
    "iso:country":"GB",
    "wof:name":"AB33 8QY",
    "wof:placetype":"postalcode"
},
  "geometry": {"coordinates":[-2.87937512215806,57.2368880265742],"type":"Point"}
}