{
  "type": "Feature",
  "properties": {
    "iso:country": "GB",
    "wof:name": "AB33 8QY",
    "wof:placetype": "postalcode"
  },
  "geometry": {"coordinates":[-2.879375,57.236888],"type":"Point"}
}
