{
  "type": "Feature",
  "properties": {
    "date:inception_lower":"1980-01-01",
    "date:inception_upper":"1980-01-31",
    "iso:country":"GB",
    "wof:name":"TW18 2JZ",
    "wof:placetype":"postalcode"
},
  "geometry": {"coordinates":[-0.50797,51.424917],"type":"Point"}
}