{
  "type": "Feature",
  "properties": {
    "date:inception_lower": "1995-12-01",
    "date:inception_upper": "1995-12-01",
    "iso:country": "GB",
    "wof:name": "LE7 1GF",
    "wof:placetype": "postalcode"
  },
  "geometry": {"coordinates":[-1.089584,52.695927],"type":"Point"}
}
