{
  "type": "Feature",
  "properties": {
    "iso:country":"GB",
    "wof:name":"ME8 8JN",
    "wof:placetype":"postalcode"
},
  "geometry": {"coordinates":[0.61019510014439,51.35860407718138],"type":"Point"}
}