{
  "type": "Feature",
  "properties": {
    "date:inception_lower": "1980-01-01",
    "date:inception_upper": "1980-01-01",
    "iso:country": "GB",
    "wof:name": "ME8 8JN",
    "wof:placetype": "postalcode"
  },
  "geometry": {"coordinates":[0.610195,51.358604],"type":"Point"}
}
