{
  "type": "Feature",
  "properties": {
    "iso:country": "GB",
    "wof:name": "ME8 8JN",
    "wof:placetype": "postalcode"
  },
  "geometry": {"coordinates":[0.610195,51.358604],"type":"Point"}
}
