{
  "type": "Feature",
  "properties": {
    "iso:country":"GB",
    "wof:name":"B29 7NQ",
    "wof:placetype":"postalcode"
},
  "geometry": {"coordinates":[-1.91414406425968,52.44210141587403],"type":"Point"}
}