{
  "type": "Feature",
  "properties": {
    "iso:country":"GB",
    "wof:name":"N3 1NG",
    "wof:placetype":"postalcode"
},
  "geometry": {"coordinates":[-0.18265442499005,51.60912966780653],"type":"Point"}
}