{
  "type": "Feature",
  "properties": {
    "iso:country":"GB",
    "wof:name":"CM14 5TS",
    "wof:placetype":"postalcode"
},
  "geometry": {"coordinates":[0.26771276618813,51.66731758598574],"type":"Point"}
}