{
  "type": "Feature",
  "properties": {
    "date:inception_lower":"1980-01-01",
    "date:inception_upper":"1980-01-31",
    "iso:country":"GB",
    "wof:name":"SA15 5HF",
    "wof:placetype":"postalcode"
},
  "geometry": {"coordinates":[-4.17797,51.773951],"type":"Point"}
}