{
  "type": "Feature",
  "properties": {
    "iso:country": "GB",
    "wof:name": "DE11 9HF",
    "wof:placetype": "postalcode"
  },
  "geometry": {"coordinates":[-1.581723,52.75389],"type":"Point"}
}
