{
  "type": "Feature",
  "properties": {
    "date:inception_lower":"1999-06-01",
    "date:inception_upper":"1999-06-30",
    "iso:country":"GB",
    "wof:name":"CH66 2XE",
    "wof:placetype":"postalcode"
},
  "geometry": {"coordinates":[-2.920218,53.255284],"type":"Point"}
}