{
  "type": "Feature",
  "properties": {
    "iso:country": "GB",
    "wof:name": "NE1 2NH",
    "wof:placetype": "postalcode"
  },
  "geometry": {"coordinates":[-1.602995,54.97059],"type":"Point"}
}
