{
  "type": "Feature",
  "properties": {
    "iso:country":"GB",
    "wof:name":"NE1 2NH",
    "wof:placetype":"postalcode"
},
  "geometry": {"coordinates":[-1.60296675066977,54.97050211595135],"type":"Point"}
}