{
  "type": "Feature",
  "properties": {
    "date:inception_lower": "1980-01-01",
    "date:inception_upper": "1980-01-01",
    "iso:country": "GB",
    "wof:name": "TR10 9AQ",
    "wof:placetype": "postalcode"
  },
  "geometry": {"coordinates":[-5.162553,50.165474],"type":"Point"}
}
