{
  "type": "Feature",
  "properties": {
    "date:inception_lower": "1980-01-01",
    "date:inception_upper": "1980-01-01",
    "iso:country": "GB",
    "wof:name": "GU22 8QX",
    "wof:placetype": "postalcode"
  },
  "geometry": {"coordinates":[-0.512531,51.325124],"type":"Point"}
}
