{
  "type": "Feature",
  "properties": {
    "date:inception_lower": "2014-10-01",
    "date:inception_upper": "2014-10-01",
    "iso:country": "GB",
    "wof:name": "LA11 7RY",
    "wof:placetype": "postalcode"
  },
  "geometry": {"coordinates":[-2.942232,54.177542],"type":"Point"}
}
