{
  "type": "Feature",
  "properties": {
    "iso:country":"GB",
    "wof:name":"LA11 7RY",
    "wof:placetype":"postalcode"
},
  "geometry": {"coordinates":[-2.94192127785221,54.17735509871982],"type":"Point"}
}