{
  "type": "Feature",
  "properties": {
    "date:inception_lower": "2016-10-01",
    "date:inception_upper": "2016-10-01",
    "iso:country": "GB",
    "wof:name": "PL25 9ZU",
    "wof:placetype": "postalcode"
  },
  "geometry": {"coordinates":[-4.758797,50.341357],"type":"Point"}
}
