{
  "type": "Feature",
  "properties": {
    "iso:country":"GB",
    "wof:name":"L40 8HH",
    "wof:placetype":"postalcode"
},
  "geometry": {"coordinates":[-2.91403561503019,53.59654776928576],"type":"Point"}
}