{
  "type": "Feature",
  "properties": {
    "iso:country":"GB",
    "wof:name":"N11 3FL",
    "wof:placetype":"postalcode"
},
  "geometry": {"coordinates":[-0.14684050141887,51.61330869906035],"type":"Point"}
}