{
  "type": "Feature",
  "properties": {
    "iso:country": "GB",
    "wof:name": "N11 3FL",
    "wof:placetype": "postalcode"
  },
  "geometry": {"coordinates":[-0.14684,51.613309],"type":"Point"}
}
