{
  "type": "Feature",
  "properties": {
    "iso:country": "GB",
    "wof:name": "SK6 5PP",
    "wof:placetype": "postalcode"
  },
  "geometry": {"coordinates":[-2.025735,53.392774],"type":"Point"}
}
