{
  "type": "Feature",
  "properties": {
    "iso:country":"GB",
    "wof:name":"BN1 8FH",
    "wof:placetype":"postalcode"
},
  "geometry": {"coordinates":[-0.12523781022328,50.86186923160427],"type":"Point"}
}