{
  "type": "Feature",
  "properties": {
    "iso:country": "GB",
    "wof:name": "TN30 7ET",
    "wof:placetype": "postalcode"
  },
  "geometry": {"coordinates":[0.726248,51.010891],"type":"Point"}
}
