{
  "type": "Feature",
  "properties": {
    "iso:country": "GB",
    "wof:name": "DY1 3HG",
    "wof:placetype": "postalcode"
  },
  "geometry": {"coordinates":[-2.095641,52.519926],"type":"Point"}
}
