{
  "type": "Feature",
  "properties": {
    "iso:country":"GB",
    "wof:name":"DY1 3HG",
    "wof:placetype":"postalcode"
},
  "geometry": {"coordinates":[-2.0956466271069,52.51991957786823],"type":"Point"}
}