{
  "type": "Feature",
  "properties": {
    "date:inception_lower": "1995-12-01",
    "date:inception_upper": "1995-12-01",
    "iso:country": "GB",
    "wof:name": "RH6 9HB",
    "wof:placetype": "postalcode"
  },
  "geometry": {"coordinates":[-0.160137,51.171682],"type":"Point"}
}
