{
  "type": "Feature",
  "properties": {
    "iso:country":"GB",
    "wof:name":"PO30 2NU",
    "wof:placetype":"postalcode"
},
  "geometry": {"coordinates":[-1.24649154020851,50.68601401152616],"type":"Point"}
}