{
  "type": "Feature",
  "properties": {
    "iso:country": "GB",
    "wof:name": "PO30 2NU",
    "wof:placetype": "postalcode"
  },
  "geometry": {"coordinates":[-1.246482,50.686002],"type":"Point"}
}
