{
  "type": "Feature",
  "properties": {
    "iso:country":"GB",
    "wof:name":"NG34 8DG",
    "wof:placetype":"postalcode"
},
  "geometry": {"coordinates":[-0.4634724054888,53.03769476549068],"type":"Point"}
}