{
  "type": "Feature",
  "properties": {
    "iso:country":"GB",
    "wof:name":"SM6 7AZ",
    "wof:placetype":"postalcode"
},
  "geometry": {"coordinates":[-0.1576003230609,51.37966381204111],"type":"Point"}
}