{
  "type": "Feature",
  "properties": {
    "iso:country":"GB",
    "wof:name":"GL3 3BZ",
    "wof:placetype":"postalcode"
},
  "geometry": {"coordinates":[-2.19069389488789,51.86220961726178],"type":"Point"}
}