{
  "type": "Feature",
  "properties": {
    "iso:country": "GB",
    "wof:name": "GL3 3BZ",
    "wof:placetype": "postalcode"
  },
  "geometry": {"coordinates":[-2.190694,51.86221],"type":"Point"}
}
