{
  "type": "Feature",
  "properties": {
    "iso:country":"GB",
    "wof:name":"NE2 1DF",
    "wof:placetype":"postalcode"
},
  "geometry": {"coordinates":[-1.60491614765827,54.98038436302665],"type":"Point"}
}