{
  "type": "Feature",
  "properties": {
    "iso:country":"GB",
    "wof:name":"TD1 3NP",
    "wof:placetype":"postalcode"
},
  "geometry": {"coordinates":[-2.79873727062702,55.59795203725344],"type":"Point"}
}