{
  "type": "Feature",
  "properties": {
    "iso:country": "GB",
    "wof:name": "LA20 6HQ",
    "wof:placetype": "postalcode"
  },
  "geometry": {"coordinates":[-3.211474,54.277047],"type":"Point"}
}
