{
  "type": "Feature",
  "properties": {
    "iso:country":"GB",
    "wof:name":"LA20 6HQ",
    "wof:placetype":"postalcode"
},
  "geometry": {"coordinates":[-3.21147338298393,54.27705684774275],"type":"Point"}
}