{
  "type": "Feature",
  "properties": {
    "date:inception_lower": "1980-01-01",
    "date:inception_upper": "1980-01-01",
    "iso:country": "GB",
    "wof:name": "GL15 6QQ",
    "wof:placetype": "postalcode"
  },
  "geometry": {"coordinates":[-2.661781,51.753421],"type":"Point"}
}
