{
  "type": "Feature",
  "properties": {
    "iso:country":"GB",
    "wof:name":"GL15 6QQ",
    "wof:placetype":"postalcode"
},
  "geometry": {"coordinates":[-2.66207908490855,51.75319106931492],"type":"Point"}
}