{
  "type": "Feature",
  "properties": {
    "iso:country":"GB",
    "wof:name":"SO40 7GU",
    "wof:placetype":"postalcode"
},
  "geometry": {"coordinates":[-1.55073293436582,50.91013189669166],"type":"Point"}
}