{
  "type": "Feature",
  "properties": {
    "date:inception_lower": "1994-12-01",
    "date:inception_upper": "1994-12-01",
    "iso:country": "GB",
    "wof:name": "SO40 7GU",
    "wof:placetype": "postalcode"
  },
  "geometry": {"coordinates":[-1.550733,50.910132],"type":"Point"}
}
