{
  "type": "Feature",
  "properties": {
    "iso:country":"GB",
    "wof:name":"OX9 3TU",
    "wof:placetype":"postalcode"
},
  "geometry": {"coordinates":[-0.97395941820332,51.75056322076844],"type":"Point"}
}