{
  "type": "Feature",
  "properties": {
    "date:inception_lower": "1980-01-01",
    "date:inception_upper": "1980-01-01",
    "iso:country": "GB",
    "wof:name": "OX9 3TU",
    "wof:placetype": "postalcode"
  },
  "geometry": {"coordinates":[-0.973959,51.750563],"type":"Point"}
}
