{
  "type": "Feature",
  "properties": {
    "iso:country":"GB",
    "wof:name":"CM7 4BT",
    "wof:placetype":"postalcode"
},
  "geometry": {"coordinates":[0.48769617231851,51.95259830708204],"type":"Point"}
}