{
  "type": "Feature",
  "properties": {
    "date:inception_lower": "1980-01-01",
    "date:inception_upper": "1980-01-01",
    "iso:country": "GB",
    "wof:name": "FY5 3SW",
    "wof:placetype": "postalcode"
  },
  "geometry": {"coordinates":[-3.03166,53.866702],"type":"Point"}
}
