{
  "type": "Feature",
  "properties": {
    "iso:country": "GB",
    "wof:name": "BA21 5RA",
    "wof:placetype": "postalcode"
  },
  "geometry": {"coordinates":[-2.621614,50.955326],"type":"Point"}
}
