{
  "type": "Feature",
  "properties": {
    "iso:country":"GB",
    "wof:name":"BA21 5RA",
    "wof:placetype":"postalcode"
},
  "geometry": {"coordinates":[-2.62161445741315,50.95532648346202],"type":"Point"}
}