{
  "type": "Feature",
  "properties": {
    "iso:country":"GB",
    "wof:name":"WD3 3JF",
    "wof:placetype":"postalcode"
},
  "geometry": {"coordinates":[-0.45790733242911,51.65894532465106],"type":"Point"}
}