{
  "type": "Feature",
  "properties": {
    "iso:country":"GB",
    "wof:name":"M40 9DA",
    "wof:placetype":"postalcode"
},
  "geometry": {"coordinates":[-2.19635677027656,53.50903394221],"type":"Point"}
}