{
  "type": "Feature",
  "properties": {
    "date:inception_lower": "2002-07-01",
    "date:inception_upper": "2002-07-01",
    "iso:country": "GB",
    "wof:name": "NN13 7AU",
    "wof:placetype": "postalcode"
  },
  "geometry": {"coordinates":[-1.142709,52.034712],"type":"Point"}
}
