{
  "type": "Feature",
  "properties": {
    "iso:country":"GB",
    "wof:name":"NE8 2AN",
    "wof:placetype":"postalcode"
},
  "geometry": {"coordinates":[-1.60495312107676,54.96546727966068],"type":"Point"}
}