{
  "type": "Feature",
  "properties": {
    "iso:country":"GB",
    "wof:name":"SS13 1QU",
    "wof:placetype":"postalcode"
},
  "geometry": {"coordinates":[0.50684686457129,51.58248720577835],"type":"Point"}
}