{
  "type": "Feature",
  "properties": {
    "iso:country": "GB",
    "wof:name": "SS13 1QU",
    "wof:placetype": "postalcode"
  },
  "geometry": {"coordinates":[0.506847,51.582487],"type":"Point"}
}
