{
  "type": "Feature",
  "properties": {
    "iso:country":"GB",
    "wof:name":"B15 1LA",
    "wof:placetype":"postalcode"
},
  "geometry": {"coordinates":[-1.91692610337483,52.47264240892034],"type":"Point"}
}