{
  "type": "Feature",
  "properties": {
    "iso:country":"GB",
    "wof:name":"SE23 3SX",
    "wof:placetype":"postalcode"
},
  "geometry": {"coordinates":[-0.05189293435198,51.44261168762485],"type":"Point"}
}