{
  "type": "Feature",
  "properties": {
    "iso:country":"GB",
    "wof:name":"BS8 2PU",
    "wof:placetype":"postalcode"
},
  "geometry": {"coordinates":[-2.61238163365731,51.46509701898523],"type":"Point"}
}