{
  "type": "Feature",
  "properties": {
    "iso:country":"GB",
    "wof:name":"KY12 8BE",
    "wof:placetype":"postalcode"
},
  "geometry": {"coordinates":[-3.46837494614392,56.07345531280526],"type":"Point"}
}