{
  "type": "Feature",
  "properties": {
    "iso:country": "GB",
    "wof:name": "KY12 8BE",
    "wof:placetype": "postalcode"
  },
  "geometry": {"coordinates":[-3.468375,56.073455],"type":"Point"}
}
