{
  "type": "Feature",
  "properties": {
    "iso:country":"GB",
    "wof:name":"DY8 4YW",
    "wof:placetype":"postalcode"
},
  "geometry": {"coordinates":[-2.1563532717042,52.47103942814648],"type":"Point"}
}