{
  "type": "Feature",
  "properties": {
    "iso:country": "GB",
    "wof:name": "HU11 4AX",
    "wof:placetype": "postalcode"
  },
  "geometry": {"coordinates":[-0.257036,53.780971],"type":"Point"}
}
