{
  "type": "Feature",
  "properties": {
    "date:inception_lower": "1980-01-01",
    "date:inception_upper": "1980-01-01",
    "iso:country": "GB",
    "wof:name": "NE3 5TP",
    "wof:placetype": "postalcode"
  },
  "geometry": {"coordinates":[-1.630885,55.027976],"type":"Point"}
}
