{
  "type": "Feature",
  "properties": {
    "iso:country":"GB",
    "wof:name":"NE3 5TP",
    "wof:placetype":"postalcode"
},
  "geometry": {"coordinates":[-1.63088551790263,55.02797598060826],"type":"Point"}
}