{
  "type": "Feature",
  "properties": {
    "iso:country":"GB",
    "wof:name":"SY8 1LZ",
    "wof:placetype":"postalcode"
},
  "geometry": {"coordinates":[-2.69857498074559,52.36374951510974],"type":"Point"}
}