{
  "type": "Feature",
  "properties": {
    "date:inception_lower": "1980-01-01",
    "date:inception_upper": "1980-01-01",
    "iso:country": "GB",
    "wof:name": "SY8 1LZ",
    "wof:placetype": "postalcode"
  },
  "geometry": {"coordinates":[-2.698575,52.36375],"type":"Point"}
}
