{
  "type": "Feature",
  "properties": {
    "date:inception_lower": "2014-01-01",
    "date:inception_upper": "2014-01-01",
    "iso:country": "GB",
    "wof:name": "RH2 0JR",
    "wof:placetype": "postalcode"
  },
  "geometry": {"coordinates":[-0.202307,51.242302],"type":"Point"}
}
