{
  "type": "Feature",
  "properties": {
    "date:inception_lower": "2003-04-01",
    "date:inception_upper": "2003-04-01",
    "iso:country": "GB",
    "wof:name": "CO4 9EW",
    "wof:placetype": "postalcode"
  },
  "geometry": {"coordinates":[0.910366,51.918279],"type":"Point"}
}
