{
  "type": "Feature",
  "properties": {
    "iso:country":"GB",
    "wof:name":"CO4 9EW",
    "wof:placetype":"postalcode"
},
  "geometry": {"coordinates":[0.91036617482981,51.918278919675],"type":"Point"}
}