{
  "type": "Feature",
  "properties": {
    "iso:country":"GB",
    "wof:name":"WF3 1UD",
    "wof:placetype":"postalcode"
},
  "geometry": {"coordinates":[-1.5708878480852,53.72717475546882],"type":"Point"}
}