{
  "type": "Feature",
  "properties": {
    "iso:country": "GB",
    "wof:name": "WF3 1UD",
    "wof:placetype": "postalcode"
  },
  "geometry": {"coordinates":[-1.570888,53.727175],"type":"Point"}
}
