{
  "type": "Feature",
  "properties": {
    "date:inception_lower": "1993-01-01",
    "date:inception_upper": "1993-01-01",
    "iso:country": "GB",
    "wof:name": "WF3 1UD",
    "wof:placetype": "postalcode"
  },
  "geometry": {"coordinates":[-1.570888,53.727175],"type":"Point"}
}
