{
  "type": "Feature",
  "properties": {
    "iso:country":"GB",
    "wof:name":"CR0 6RJ",
    "wof:placetype":"postalcode"
},
  "geometry": {"coordinates":[-0.06692625736906,51.38304992650253],"type":"Point"}
}