{
  "type": "Feature",
  "properties": {
    "date:inception_lower": "1980-01-01",
    "date:inception_upper": "1980-01-01",
    "iso:country": "GB",
    "wof:name": "CR0 6RJ",
    "wof:placetype": "postalcode"
  },
  "geometry": {"coordinates":[-0.066926,51.38305],"type":"Point"}
}
