{
  "type": "Feature",
  "properties": {
    "iso:country": "GB",
    "wof:name": "CR0 6RJ",
    "wof:placetype": "postalcode"
  },
  "geometry": {"coordinates":[-0.066926,51.38305],"type":"Point"}
}
