{
  "type": "Feature",
  "properties": {
    "date:inception_lower": "1980-01-01",
    "date:inception_upper": "1980-01-01",
    "iso:country": "GB",
    "wof:name": "EH48 1LX",
    "wof:placetype": "postalcode"
  },
  "geometry": {"coordinates":[-3.612345,55.901373],"type":"Point"}
}
