{
  "type": "Feature",
  "properties": {
    "iso:country":"GB",
    "wof:name":"EH48 1LX",
    "wof:placetype":"postalcode"
},
  "geometry": {"coordinates":[-3.61234511321157,55.90137308660189],"type":"Point"}
}