{
  "type": "Feature",
  "properties": {
    "iso:country":"GB",
    "wof:name":"CR0 8HS",
    "wof:placetype":"postalcode"
},
  "geometry": {"coordinates":[-0.03201389044821,51.37444709448283],"type":"Point"}
}