{
  "type": "Feature",
  "properties": {
    "iso:country": "GB",
    "wof:name": "CR0 8HS",
    "wof:placetype": "postalcode"
  },
  "geometry": {"coordinates":[-0.032014,51.374447],"type":"Point"}
}
