{
  "type": "Feature",
  "properties": {
    "date:inception_lower":"1980-01-01",
    "date:inception_upper":"1980-01-31",
    "iso:country":"GB",
    "wof:name":"CR4 1AB",
    "wof:placetype":"postalcode"
},
  "geometry": {"coordinates":[-0.145466,51.411792],"type":"Point"}
}