{
  "type": "Feature",
  "properties": {
    "date:inception_lower": "1990-02-01",
    "date:inception_upper": "1990-02-01",
    "iso:country": "GB",
    "wof:name": "BR6 7PW",
    "wof:placetype": "postalcode"
  },
  "geometry": {"coordinates":[0.147273,51.357458],"type":"Point"}
}
