{
  "type": "Feature",
  "properties": {
    "iso:country": "GB",
    "wof:name": "BR6 7PW",
    "wof:placetype": "postalcode"
  },
  "geometry": {"coordinates":[0.147246,51.357458],"type":"Point"}
}
