{
  "type": "Feature",
  "properties": {
    "iso:country":"GB",
    "wof:name":"BR6 7PW",
    "wof:placetype":"postalcode"
},
  "geometry": {"coordinates":[0.1472460368897,51.35745810972302],"type":"Point"}
}