{
  "type": "Feature",
  "properties": {
    "iso:country": "GB",
    "wof:name": "BR6 7PW",
    "wof:placetype": "postalcode"
  },
  "geometry": {"coordinates":[0.146733,51.356965],"type":"Point"}
}
