{
  "type": "Feature",
  "properties": {
    "iso:country":"GB",
    "wof:name":"N17 0DX",
    "wof:placetype":"postalcode"
},
  "geometry": {"coordinates":[-0.06047947824212,51.60826257787337],"type":"Point"}
}