{
  "type": "Feature",
  "properties": {
    "iso:country":"GB",
    "wof:name":"LE67 4HD",
    "wof:placetype":"postalcode"
},
  "geometry": {"coordinates":[-1.33904485134525,52.7185802406983],"type":"Point"}
}