{
  "type": "Feature",
  "properties": {
    "date:inception_lower":"1980-01-01",
    "date:inception_upper":"1980-01-31",
    "iso:country":"GB",
    "wof:name":"N17 7LU",
    "wof:placetype":"postalcode"
},
  "geometry": {"coordinates":[-0.087752,51.606759],"type":"Point"}
}