{
  "type": "Feature",
  "properties": {
    "iso:country": "GB",
    "wof:name": "AL1 5QG",
    "wof:placetype": "postalcode"
  },
  "geometry": {"coordinates":[-0.312456,51.742739],"type":"Point"}
}
