{
  "type": "Feature",
  "properties": {
    "iso:country":"GB",
    "wof:name":"AL1 5QG",
    "wof:placetype":"postalcode"
},
  "geometry": {"coordinates":[-0.31245563056876,51.74273857503284],"type":"Point"}
}