{
  "type": "Feature",
  "properties": {
    "date:inception_lower": "1980-01-01",
    "date:inception_upper": "1980-01-01",
    "iso:country": "GB",
    "wof:name": "NN14 1PN",
    "wof:placetype": "postalcode"
  },
  "geometry": {"coordinates":[-0.773396,52.378414],"type":"Point"}
}
