{
  "type": "Feature",
  "properties": {
    "iso:country": "GB",
    "wof:name": "CF48 4DY",
    "wof:placetype": "postalcode"
  },
  "geometry": {"coordinates":[-3.346543,51.711491],"type":"Point"}
}
