{
  "type": "Feature",
  "properties": {
    "date:inception_lower": "1994-12-01",
    "date:inception_upper": "1994-12-01",
    "iso:country": "GB",
    "wof:name": "CF48 4DY",
    "wof:placetype": "postalcode"
  },
  "geometry": {"coordinates":[-3.346543,51.711491],"type":"Point"}
}
