{
  "type": "Feature",
  "properties": {
    "iso:country":"GB",
    "wof:name":"CF48 4DY",
    "wof:placetype":"postalcode"
},
  "geometry": {"coordinates":[-3.34654255186734,51.7114909197587],"type":"Point"}
}