{
  "type": "Feature",
  "properties": {
    "iso:country":"GB",
    "wof:name":"EX16 8RW",
    "wof:placetype":"postalcode"
},
  "geometry": {"coordinates":[-3.51186152967047,50.8577569156533],"type":"Point"}
}