{
  "type": "Feature",
  "properties": {
    "iso:country":"GB",
    "wof:name":"LL61 6EJ",
    "wof:placetype":"postalcode"
},
  "geometry": {"coordinates":[-4.22909649122509,53.19215321089997],"type":"Point"}
}