{
  "type": "Feature",
  "properties": {
    "date:inception_lower": "1986-07-01",
    "date:inception_upper": "1986-07-01",
    "iso:country": "GB",
    "wof:name": "TD15 1HH",
    "wof:placetype": "postalcode"
  },
  "geometry": {"coordinates":[-1.999655,55.767544],"type":"Point"}
}
