{
  "type": "Feature",
  "properties": {
    "date:inception_lower":"2002-06-01",
    "date:inception_upper":"2002-06-30",
    "iso:country":"GB",
    "wof:name":"PO20 3RE",
    "wof:placetype":"postalcode"
},
  "geometry": {"coordinates":[-0.665153,50.838429],"type":"Point"}
}