{
  "type": "Feature",
  "properties": {
    "iso:country": "GB",
    "wof:name": "PO20 3RE",
    "wof:placetype": "postalcode"
  },
  "geometry": {"coordinates":[-0.665153,50.838429],"type":"Point"}
}
