{
  "type": "Feature",
  "properties": {
    "date:inception_lower": "1980-01-01",
    "date:inception_upper": "1980-01-01",
    "iso:country": "GB",
    "wof:name": "M19 3FL",
    "wof:placetype": "postalcode"
  },
  "geometry": {"coordinates":[-2.185357,53.448505],"type":"Point"}
}
