{
  "type": "Feature",
  "properties": {
    "iso:country": "GB",
    "wof:name": "M19 3FL",
    "wof:placetype": "postalcode"
  },
  "geometry": {"coordinates":[-2.185357,53.448505],"type":"Point"}
}
