{
  "type": "Feature",
  "properties": {
    "iso:country":"GB",
    "wof:name":"SL9 8EU",
    "wof:placetype":"postalcode"
},
  "geometry": {"coordinates":[-0.55154369581251,51.58834587999772],"type":"Point"}
}