{
  "type": "Feature",
  "properties": {
    "iso:country":"GB",
    "wof:name":"CM15 8QU",
    "wof:placetype":"postalcode"
},
  "geometry": {"coordinates":[0.32465631297524,51.6335596328635],"type":"Point"}
}