{
  "type": "Feature",
  "properties": {
    "date:inception_lower":"1980-01-01",
    "date:inception_upper":"1980-01-31",
    "iso:country":"GB",
    "wof:name":"CM15 8QU",
    "wof:placetype":"postalcode"
},
  "geometry": {"coordinates":[0.324727,51.633552],"type":"Point"}
}