{
  "type": "Feature",
  "properties": {
    "iso:country": "GB",
    "wof:name": "BS10 5NG",
    "wof:placetype": "postalcode"
  },
  "geometry": {"coordinates":[-2.590435,51.502263],"type":"Point"}
}
