{
  "type": "Feature",
  "properties": {
    "iso:country":"GB",
    "wof:name":"BD16 4RF",
    "wof:placetype":"postalcode"
},
  "geometry": {"coordinates":[-1.81976538622742,53.84525295202096],"type":"Point"}
}