{
  "type": "Feature",
  "properties": {
    "date:inception_lower":"1980-01-01",
    "date:inception_upper":"1980-01-31",
    "iso:country":"GB",
    "wof:name":"BD16 4RF",
    "wof:placetype":"postalcode"
},
  "geometry": {"coordinates":[-1.819765,53.845253],"type":"Point"}
}