{
  "type": "Feature",
  "properties": {
    "iso:country":"GB",
    "wof:name":"G66 5LP",
    "wof:placetype":"postalcode"
},
  "geometry": {"coordinates":[-4.0950399006863,55.93258646949417],"type":"Point"}
}