{
  "type": "Feature",
  "properties": {
    "iso:country": "GB",
    "wof:name": "NW10 9UP",
    "wof:placetype": "postalcode"
  },
  "geometry": {"coordinates":[-0.247056,51.544142],"type":"Point"}
}
