{
  "type": "Feature",
  "properties": {
    "date:inception_lower":"1980-01-01",
    "date:inception_upper":"1980-01-31",
    "iso:country":"GB",
    "wof:name":"NW10 9UP",
    "wof:placetype":"postalcode"
},
  "geometry": {"coordinates":[-0.247056,51.544142],"type":"Point"}
}