{
  "type": "Feature",
  "properties": {
    "iso:country":"GB",
    "wof:name":"NW10 9UP",
    "wof:placetype":"postalcode"
},
  "geometry": {"coordinates":[-0.24705614280959,51.54414155506409],"type":"Point"}
}