{
  "type": "Feature",
  "properties": {
    "iso:country": "GB",
    "wof:name": "GL14 2NE",
    "wof:placetype": "postalcode"
  },
  "geometry": {"coordinates":[-2.506266,51.826272],"type":"Point"}
}
