{
  "type": "Feature",
  "properties": {
    "iso:country":"GB",
    "wof:name":"GL14 2NE",
    "wof:placetype":"postalcode"
},
  "geometry": {"coordinates":[-2.50626639286887,51.82627219592088],"type":"Point"}
}