{
  "type": "Feature",
  "properties": {
    "iso:country":"GB",
    "wof:name":"S80 3PA",
    "wof:placetype":"postalcode"
},
  "geometry": {"coordinates":[-1.0279152791929,53.26514165999014],"type":"Point"}
}