{
  "type": "Feature",
  "properties": {
    "iso:country": "GB",
    "wof:name": "S80 3PA",
    "wof:placetype": "postalcode"
  },
  "geometry": {"coordinates":[-1.027915,53.265142],"type":"Point"}
}
