{
  "type": "Feature",
  "properties": {
    "iso:country":"GB",
    "wof:name":"PR3 3JD",
    "wof:placetype":"postalcode"
},
  "geometry": {"coordinates":[-2.59931368722972,53.829994452502],"type":"Point"}
}