{
  "type": "Feature",
  "properties": {
    "date:inception_lower": "1980-01-01",
    "date:inception_upper": "1980-01-01",
    "iso:country": "GB",
    "wof:name": "PR3 3JD",
    "wof:placetype": "postalcode"
  },
  "geometry": {"coordinates":[-2.599328,53.82999],"type":"Point"}
}
