{
  "type": "Feature",
  "properties": {
    "iso:country":"GB",
    "wof:name":"TF4 3EH",
    "wof:placetype":"postalcode"
},
  "geometry": {"coordinates":[-2.4681709732438,52.65602812462603],"type":"Point"}
}