{
  "type": "Feature",
  "properties": {
    "iso:country": "GB",
    "wof:name": "SK6 7PU",
    "wof:placetype": "postalcode"
  },
  "geometry": {"coordinates":[-2.069701,53.391543],"type":"Point"}
}
