{
  "type": "Feature",
  "properties": {
    "iso:country":"GB",
    "wof:name":"SK6 7PU",
    "wof:placetype":"postalcode"
},
  "geometry": {"coordinates":[-2.0697014264448,53.39154288048937],"type":"Point"}
}