{
  "type": "Feature",
  "properties": {
    "iso:country":"GB",
    "wof:name":"NG20 8PX",
    "wof:placetype":"postalcode"
},
  "geometry": {"coordinates":[-1.22409119253595,53.20745829039046],"type":"Point"}
}