{
  "type": "Feature",
  "properties": {
    "iso:country":"GB",
    "wof:name":"TW7 7PB",
    "wof:placetype":"postalcode"
},
  "geometry": {"coordinates":[-0.34863801610517,51.46212182169745],"type":"Point"}
}