{
  "type": "Feature",
  "properties": {
    "iso:country":"GB",
    "wof:name":"NE63 0DQ",
    "wof:placetype":"postalcode"
},
  "geometry": {"coordinates":[-1.56120446350559,55.1673888663069],"type":"Point"}
}