{
  "type": "Feature",
  "properties": {
    "iso:country":"GB",
    "wof:name":"B69 1SL",
    "wof:placetype":"postalcode"
},
  "geometry": {"coordinates":[-2.05415647698434,52.50455520113218],"type":"Point"}
}