{
  "type": "Feature",
  "properties": {
    "iso:country":"GB",
    "wof:name":"BB10 2AG",
    "wof:placetype":"postalcode"
},
  "geometry": {"coordinates":[-2.24175160008182,53.80912021770126],"type":"Point"}
}