{
  "type": "Feature",
  "properties": {
    "iso:country": "GB",
    "wof:name": "G45 0JP",
    "wof:placetype": "postalcode"
  },
  "geometry": {"coordinates":[-4.226725,55.799721],"type":"Point"}
}
