{
  "type": "Feature",
  "properties": {
    "date:inception_lower": "2021-07-01",
    "date:inception_upper": "2021-07-01",
    "iso:country": "GB",
    "wof:name": "LE7 9WU",
    "wof:placetype": "postalcode"
  },
  "geometry": {"coordinates":[-0.874371,52.599449],"type":"Point"}
}
