{
  "type": "Feature",
  "properties": {
    "iso:country":"GB",
    "wof:name":"RM17 5NS",
    "wof:placetype":"postalcode"
},
  "geometry": {"coordinates":[0.33802819174919,51.48627540316433],"type":"Point"}
}