{
  "type": "Feature",
  "properties": {
    "iso:country": "GB",
    "wof:name": "MK4 3AP",
    "wof:placetype": "postalcode"
  },
  "geometry": {"coordinates":[-0.777764,51.99675],"type":"Point"}
}
