{
  "type": "Feature",
  "properties": {
    "date:inception_lower":"1994-12-01",
    "date:inception_upper":"1994-12-31",
    "iso:country":"GB",
    "wof:name":"MK4 3AP",
    "wof:placetype":"postalcode"
},
  "geometry": {"coordinates":[-0.777764,51.99675],"type":"Point"}
}