{
  "type": "Feature",
  "properties": {
    "iso:country":"GB",
    "wof:name":"RG42 3DZ",
    "wof:placetype":"postalcode"
},
  "geometry": {"coordinates":[-0.73417190008232,51.42413329012049],"type":"Point"}
}