{
  "type": "Feature",
  "properties": {
    "iso:country":"GB",
    "wof:name":"LS7 4LP",
    "wof:placetype":"postalcode"
},
  "geometry": {"coordinates":[-1.53098245542296,53.82646040795233],"type":"Point"}
}