{
  "type": "Feature",
  "properties": {
    "iso:country": "GB",
    "wof:name": "LS7 4LP",
    "wof:placetype": "postalcode"
  },
  "geometry": {"coordinates":[-1.530982,53.82646],"type":"Point"}
}
