{
  "type": "Feature",
  "properties": {
    "iso:country":"GB",
    "wof:name":"PL14 6LE",
    "wof:placetype":"postalcode"
},
  "geometry": {"coordinates":[-4.53922734837223,50.45491528396354],"type":"Point"}
}