{
  "type": "Feature",
  "properties": {
    "iso:country":"GB",
    "wof:name":"G75 9HR",
    "wof:placetype":"postalcode"
},
  "geometry": {"coordinates":[-4.195827323163,55.74547533578836],"type":"Point"}
}