{
  "type": "Feature",
  "properties": {
    "date:inception_lower":"1980-01-01",
    "date:inception_upper":"1980-01-31",
    "iso:country":"GB",
    "wof:name":"G75 9HR",
    "wof:placetype":"postalcode"
},
  "geometry": {"coordinates":[-4.195827,55.745475],"type":"Point"}
}