{
  "type": "Feature",
  "properties": {
    "date:inception_lower": "2002-06-01",
    "date:inception_upper": "2002-06-01",
    "iso:country": "GB",
    "wof:name": "PO20 2AY",
    "wof:placetype": "postalcode"
  },
  "geometry": {"coordinates":[-0.722514,50.839017],"type":"Point"}
}
