{
  "type": "Feature",
  "properties": {
    "iso:country": "GB",
    "wof:name": "NR29 3TH",
    "wof:placetype": "postalcode"
  },
  "geometry": {"coordinates":[1.716261,52.662963],"type":"Point"}
}
