{
  "type": "Feature",
  "properties": {
    "iso:country":"GB",
    "wof:name":"GL2 0LB",
    "wof:placetype":"postalcode"
},
  "geometry": {"coordinates":[-2.20608319134354,51.87412356278683],"type":"Point"}
}