{
  "type": "Feature",
  "properties": {
    "iso:country":"GB",
    "wof:name":"BD22 0PP",
    "wof:placetype":"postalcode"
},
  "geometry": {"coordinates":[-1.94984249324466,53.8665439695602],"type":"Point"}
}