{
  "type": "Feature",
  "properties": {
    "date:inception_lower": "2011-06-01",
    "date:inception_upper": "2011-06-01",
    "iso:country": "GB",
    "wof:name": "NN17 2GB",
    "wof:placetype": "postalcode"
  },
  "geometry": {"coordinates":[-0.718919,52.500216],"type":"Point"}
}
