{
  "type": "Feature",
  "properties": {
    "iso:country":"GB",
    "wof:name":"NE48 2SY",
    "wof:placetype":"postalcode"
},
  "geometry": {"coordinates":[-2.17619387384729,55.17836558050605],"type":"Point"}
}