{
  "type": "Feature",
  "properties": {
    "iso:country":"GB",
    "wof:name":"PR3 2TY",
    "wof:placetype":"postalcode"
},
  "geometry": {"coordinates":[-2.58549026241542,53.84216962925396],"type":"Point"}
}