{
  "type": "Feature",
  "properties": {
    "iso:country":"GB",
    "wof:name":"BS23 2UT",
    "wof:placetype":"postalcode"
},
  "geometry": {"coordinates":[-2.95636412826336,51.35017188674492],"type":"Point"}
}