{
  "type": "Feature",
  "properties": {
    "iso:country": "GB",
    "wof:name": "BS23 2UT",
    "wof:placetype": "postalcode"
  },
  "geometry": {"coordinates":[-2.956414,51.350222],"type":"Point"}
}
