{
  "type": "Feature",
  "properties": {
    "iso:country":"GB",
    "wof:name":"M24 2LS",
    "wof:placetype":"postalcode"
},
  "geometry": {"coordinates":[-2.18966413448964,53.55334845037707],"type":"Point"}
}