{
  "type": "Feature",
  "properties": {
    "date:inception_lower": "1995-12-01",
    "date:inception_upper": "1995-12-01",
    "iso:country": "GB",
    "wof:name": "DE12 7LA",
    "wof:placetype": "postalcode"
  },
  "geometry": {"coordinates":[-1.505728,52.709458],"type":"Point"}
}
