{
  "type": "Feature",
  "properties": {
    "iso:country":"GB",
    "wof:name":"DE12 7LA",
    "wof:placetype":"postalcode"
},
  "geometry": {"coordinates":[-1.50572822741678,52.70945816497697],"type":"Point"}
}