{
  "type": "Feature",
  "properties": {
    "date:inception_lower": "1980-01-01",
    "date:inception_upper": "1980-01-01",
    "iso:country": "GB",
    "wof:name": "IG9 5HW",
    "wof:placetype": "postalcode"
  },
  "geometry": {"coordinates":[0.029358,51.622957],"type":"Point"}
}
