{
  "type": "Feature",
  "properties": {
    "date:inception_lower":"1992-05-01",
    "date:inception_upper":"1992-05-31",
    "iso:country":"GB",
    "wof:name":"PH3 1QF",
    "wof:placetype":"postalcode"
},
  "geometry": {"coordinates":[-3.708696,56.297176],"type":"Point"}
}