{
  "type": "Feature",
  "properties": {
    "iso:country":"GB",
    "wof:name":"TR27 5BD",
    "wof:placetype":"postalcode"
},
  "geometry": {"coordinates":[-5.40141817304894,50.19945286305032],"type":"Point"}
}