{
  "type": "Feature",
  "properties": {
    "date:inception_lower": "1998-06-01",
    "date:inception_upper": "1998-06-01",
    "iso:country": "GB",
    "wof:name": "RH11 8XX",
    "wof:placetype": "postalcode"
  },
  "geometry": {"coordinates":[-0.198724,51.1102],"type":"Point"}
}
