{
  "type": "Feature",
  "properties": {
    "iso:country":"GB",
    "wof:name":"FK7 8HX",
    "wof:placetype":"postalcode"
},
  "geometry": {"coordinates":[-3.91259843074164,56.08932365630334],"type":"Point"}
}