{
  "type": "Feature",
  "properties": {
    "iso:country":"GB",
    "wof:name":"CR7 7LN",
    "wof:placetype":"postalcode"
},
  "geometry": {"coordinates":[-0.11285793748625,51.39628962604024],"type":"Point"}
}