{
  "type": "Feature",
  "properties": {
    "date:inception_lower": "1990-07-01",
    "date:inception_upper": "1990-07-01",
    "iso:country": "GB",
    "wof:name": "CR7 7LN",
    "wof:placetype": "postalcode"
  },
  "geometry": {"coordinates":[-0.112858,51.39629],"type":"Point"}
}
