{
  "type": "Feature",
  "properties": {
    "iso:country":"GB",
    "wof:name":"ME3 9UA",
    "wof:placetype":"postalcode"
},
  "geometry": {"coordinates":[0.63588455318702,51.45592517488514],"type":"Point"}
}