{
  "type": "Feature",
  "properties": {
    "iso:country": "GB",
    "wof:name": "ME3 9UA",
    "wof:placetype": "postalcode"
  },
  "geometry": {"coordinates":[0.635885,51.455925],"type":"Point"}
}
