{
  "type": "Feature",
  "properties": {
    "iso:country": "GB",
    "wof:name": "DY7 6SN",
    "wof:placetype": "postalcode"
  },
  "geometry": {"coordinates":[-2.172093,52.468087],"type":"Point"}
}
