{
  "type": "Feature",
  "properties": {
    "iso:country":"GB",
    "wof:name":"DY7 6SN",
    "wof:placetype":"postalcode"
},
  "geometry": {"coordinates":[-2.17209333994127,52.46808680904388],"type":"Point"}
}