{
  "type": "Feature",
  "properties": {
    "iso:country":"GB",
    "wof:name":"N19 4BW",
    "wof:placetype":"postalcode"
},
  "geometry": {"coordinates":[-0.12542048951788,51.56806944638277],"type":"Point"}
}