{
  "type": "Feature",
  "properties": {
    "date:inception_lower": "1982-03-01",
    "date:inception_upper": "1982-03-01",
    "iso:country": "GB",
    "wof:name": "N19 4BW",
    "wof:placetype": "postalcode"
  },
  "geometry": {"coordinates":[-0.12542,51.568069],"type":"Point"}
}
