{
  "type": "Feature",
  "properties": {
    "iso:country": "GB",
    "wof:name": "ST1 5RU",
    "wof:placetype": "postalcode"
  },
  "geometry": {"coordinates":[-2.199535,53.025828],"type":"Point"}
}
