{
  "type": "Feature",
  "properties": {
    "date:inception_lower": "2006-07-01",
    "date:inception_upper": "2006-07-01",
    "iso:country": "GB",
    "wof:name": "ST1 5RU",
    "wof:placetype": "postalcode"
  },
  "geometry": {"coordinates":[-2.199535,53.025828],"type":"Point"}
}
