{
  "type": "Feature",
  "properties": {
    "date:inception_lower": "2002-06-01",
    "date:inception_upper": "2002-06-01",
    "iso:country": "GB",
    "wof:name": "DE14 1DH",
    "wof:placetype": "postalcode"
  },
  "geometry": {"coordinates":[-1.620665,52.821577],"type":"Point"}
}
