{
  "type": "Feature",
  "properties": {
    "iso:country":"GB",
    "wof:name":"KA3 5BD",
    "wof:placetype":"postalcode"
},
  "geometry": {"coordinates":[-4.5168236976386,55.68201588762602],"type":"Point"}
}