{
  "type": "Feature",
  "properties": {
    "date:inception_lower":"1980-01-01",
    "date:inception_upper":"1980-01-31",
    "iso:country":"GB",
    "wof:name":"PL31 2AF",
    "wof:placetype":"postalcode"
},
  "geometry": {"coordinates":[-4.711923,50.46978],"type":"Point"}
}