{
  "type": "Feature",
  "properties": {
    "iso:country":"GB",
    "wof:name":"DG11 2LS",
    "wof:placetype":"postalcode"
},
  "geometry": {"coordinates":[-3.25161644058697,55.2322145905598],"type":"Point"}
}