{
  "type": "Feature",
  "properties": {
    "iso:country": "GB",
    "wof:name": "WA10 4NU",
    "wof:placetype": "postalcode"
  },
  "geometry": {"coordinates":[-2.755142,53.450943],"type":"Point"}
}
