{
  "type": "Feature",
  "properties": {
    "iso:country":"GB",
    "wof:name":"HR2 7JE",
    "wof:placetype":"postalcode"
},
  "geometry": {"coordinates":[-2.72231530307192,52.04942284346021],"type":"Point"}
}