{
  "type": "Feature",
  "properties": {
    "date:inception_lower": "2023-02-01",
    "date:inception_upper": "2023-02-01",
    "iso:country": "GB",
    "wof:name": "SG17 5SR",
    "wof:placetype": "postalcode"
  },
  "geometry": {"coordinates":[-0.33631,52.020764],"type":"Point"}
}
