{
  "type": "Feature",
  "properties": {
    "iso:country": "GB",
    "wof:name": "GL15 6PU",
    "wof:placetype": "postalcode"
  },
  "geometry": {"coordinates":[-2.620331,51.696316],"type":"Point"}
}
