{
  "type": "Feature",
  "properties": {
    "iso:country":"GB",
    "wof:name":"GL15 6PU",
    "wof:placetype":"postalcode"
},
  "geometry": {"coordinates":[-2.62033123644793,51.69631553968884],"type":"Point"}
}