{
  "type": "Feature",
  "properties": {
    "iso:country":"GB",
    "wof:name":"BH22 9BN",
    "wof:placetype":"postalcode"
},
  "geometry": {"coordinates":[-1.8881369571421,50.80393158327058],"type":"Point"}
}