{
  "type": "Feature",
  "properties": {
    "iso:country":"GB",
    "wof:name":"S75 1DT",
    "wof:placetype":"postalcode"
},
  "geometry": {"coordinates":[-1.49212678270576,53.5628486889465],"type":"Point"}
}