{
  "type": "Feature",
  "properties": {
    "date:inception_lower": "2017-11-01",
    "date:inception_upper": "2017-11-01",
    "iso:country": "GB",
    "wof:name": "WD19 7SE",
    "wof:placetype": "postalcode"
  },
  "geometry": {"coordinates":[-0.390998,51.625618],"type":"Point"}
}
