{
  "type": "Feature",
  "properties": {
    "iso:country":"GB",
    "wof:name":"SO23 7ET",
    "wof:placetype":"postalcode"
},
  "geometry": {"coordinates":[-1.31073186650853,51.0781539398188],"type":"Point"}
}