{
  "type": "Feature",
  "properties": {
    "iso:country":"GB",
    "wof:name":"PH26 3LE",
    "wof:placetype":"postalcode"
},
  "geometry": {"coordinates":[-3.61213098719527,57.33324512658646],"type":"Point"}
}