{
  "type": "Feature",
  "properties": {
    "date:inception_lower": "1980-01-01",
    "date:inception_upper": "1980-01-01",
    "iso:country": "GB",
    "wof:name": "PH26 3LE",
    "wof:placetype": "postalcode"
  },
  "geometry": {"coordinates":[-3.612131,57.333245],"type":"Point"}
}
