{
  "type": "Feature",
  "properties": {
    "iso:country":"GB",
    "wof:name":"EC1V 7HU",
    "wof:placetype":"postalcode"
},
  "geometry": {"coordinates":[-0.10386434650994,51.52848881100665],"type":"Point"}
}