{
  "type": "Feature",
  "properties": {
    "iso:country":"GB",
    "wof:name":"CF10 5FZ",
    "wof:placetype":"postalcode"
},
  "geometry": {"coordinates":[-3.17165091993964,51.46347573918293],"type":"Point"}
}