{
  "type": "Feature",
  "properties": {
    "iso:country": "GB",
    "wof:name": "CF10 5FZ",
    "wof:placetype": "postalcode"
  },
  "geometry": {"coordinates":[-3.171651,51.463476],"type":"Point"}
}
