{
  "type": "Feature",
  "properties": {
    "date:inception_lower": "2013-09-01",
    "date:inception_upper": "2013-09-01",
    "iso:country": "GB",
    "wof:name": "NE34 8PF",
    "wof:placetype": "postalcode"
  },
  "geometry": {"coordinates":[-1.413775,54.966664],"type":"Point"}
}
