{
  "type": "Feature",
  "properties": {
    "iso:country":"GB",
    "wof:name":"NE34 8PF",
    "wof:placetype":"postalcode"
},
  "geometry": {"coordinates":[-1.41377466330697,54.96666445010115],"type":"Point"}
}