{
  "type": "Feature",
  "properties": {
    "iso:country":"GB",
    "wof:name":"ST3 2BY",
    "wof:placetype":"postalcode"
},
  "geometry": {"coordinates":[-2.16409773478338,52.98722000744904],"type":"Point"}
}