{
  "type": "Feature",
  "properties": {
    "iso:country":"GB",
    "wof:name":"B44 9JY",
    "wof:placetype":"postalcode"
},
  "geometry": {"coordinates":[-1.89005578705448,52.55682902690845],"type":"Point"}
}