{
  "type": "Feature",
  "properties": {
    "iso:country":"GB",
    "wof:name":"W1U 3PQ",
    "wof:placetype":"postalcode"
},
  "geometry": {"coordinates":[-0.15221772807106,51.51640120467345],"type":"Point"}
}