{
  "type": "Feature",
  "properties": {
    "date:inception_lower":"1980-01-01",
    "date:inception_upper":"1980-01-31",
    "iso:country":"GB",
    "wof:name":"EX17 3AR",
    "wof:placetype":"postalcode"
},
  "geometry": {"coordinates":[-3.653563,50.789455],"type":"Point"}
}