{
  "type": "Feature",
  "properties": {
    "iso:country":"GB",
    "wof:name":"BS15 3QX",
    "wof:placetype":"postalcode"
},
  "geometry": {"coordinates":[-2.51129666168516,51.44826373082438],"type":"Point"}
}