{
  "type": "Feature",
  "properties": {
    "iso:country": "GB",
    "wof:name": "BS15 3QX",
    "wof:placetype": "postalcode"
  },
  "geometry": {"coordinates":[-2.511297,51.448264],"type":"Point"}
}
