{
  "type": "Feature",
  "properties": {
    "iso:country":"GB",
    "wof:name":"W1G 9LU",
    "wof:placetype":"postalcode"
},
  "geometry": {"coordinates":[-0.1448403190078,51.5184789200874],"type":"Point"}
}