{
  "type": "Feature",
  "properties": {
    "iso:country": "GB",
    "wof:name": "E10 7JE",
    "wof:placetype": "postalcode"
  },
  "geometry": {"coordinates":[-0.020794,51.569679],"type":"Point"}
}
