{
  "type": "Feature",
  "properties": {
    "iso:country":"GB",
    "wof:name":"E17 3LL",
    "wof:placetype":"postalcode"
},
  "geometry": {"coordinates":[-0.00393747412528,51.58851121367629],"type":"Point"}
}