{
  "type": "Feature",
  "properties": {
    "iso:country":"GB",
    "wof:name":"PO33 4AT",
    "wof:placetype":"postalcode"
},
  "geometry": {"coordinates":[-1.17418118388097,50.69263769713807],"type":"Point"}
}