{
  "type": "Feature",
  "properties": {
    "iso:country":"GB",
    "wof:name":"B24 8AD",
    "wof:placetype":"postalcode"
},
  "geometry": {"coordinates":[-1.8427051871338,52.52067235148753],"type":"Point"}
}