{
  "type": "Feature",
  "properties": {
    "date:inception_lower":"1986-07-01",
    "date:inception_upper":"1986-07-31",
    "iso:country":"GB",
    "wof:name":"S74 9TL",
    "wof:placetype":"postalcode"
},
  "geometry": {"coordinates":[-1.443799,53.508739],"type":"Point"}
}