{
  "type": "Feature",
  "properties": {
    "iso:country":"GB",
    "wof:name":"S74 9TL",
    "wof:placetype":"postalcode"
},
  "geometry": {"coordinates":[-1.44379887322052,53.5087389497802],"type":"Point"}
}