{
  "type": "Feature",
  "properties": {
    "iso:country":"GB",
    "wof:name":"N14 4ST",
    "wof:placetype":"postalcode"
},
  "geometry": {"coordinates":[-0.12289229046635,51.64412270935494],"type":"Point"}
}