{
  "type": "Feature",
  "properties": {
    "iso:country":"GB",
    "wof:name":"HR6 8JS",
    "wof:placetype":"postalcode"
},
  "geometry": {"coordinates":[-2.73943296448122,52.21865594859965],"type":"Point"}
}