{
  "type": "Feature",
  "properties": {
    "iso:country":"GB",
    "wof:name":"CO6 2HU",
    "wof:placetype":"postalcode"
},
  "geometry": {"coordinates":[0.71303255695071,51.93823910815536],"type":"Point"}
}