{
  "type": "Feature",
  "properties": {
    "iso:country":"GB",
    "wof:name":"HD7 5HJ",
    "wof:placetype":"postalcode"
},
  "geometry": {"coordinates":[-1.88052997755227,53.6204115088379],"type":"Point"}
}