{
  "type": "Feature",
  "properties": {
    "iso:country":"GB",
    "wof:name":"PR1 4HD",
    "wof:placetype":"postalcode"
},
  "geometry": {"coordinates":[-2.68886930514794,53.75709587270111],"type":"Point"}
}