{
  "type": "Feature",
  "properties": {
    "date:inception_lower": "1980-01-01",
    "date:inception_upper": "1980-01-01",
    "iso:country": "GB",
    "wof:name": "UB9 4HJ",
    "wof:placetype": "postalcode"
  },
  "geometry": {"coordinates":[-0.511619,51.560225],"type":"Point"}
}
