{
  "type": "Feature",
  "properties": {
    "iso:country": "GB",
    "wof:name": "UB9 4HJ",
    "wof:placetype": "postalcode"
  },
  "geometry": {"coordinates":[-0.512283,51.562877],"type":"Point"}
}
