{
  "type": "Feature",
  "properties": {
    "iso:country":"GB",
    "wof:name":"UB9 4HJ",
    "wof:placetype":"postalcode"
},
  "geometry": {"coordinates":[-0.51230349518392,51.5628752340211],"type":"Point"}
}