{
  "type": "Feature",
  "properties": {
    "iso:country":"GB",
    "wof:name":"PE1 1LR",
    "wof:placetype":"postalcode"
},
  "geometry": {"coordinates":[-0.24505484993326,52.57277204065254],"type":"Point"}
}