{
  "type": "Feature",
  "properties": {
    "iso:country":"GB",
    "wof:name":"LN6 7GJ",
    "wof:placetype":"postalcode"
},
  "geometry": {"coordinates":[-0.5505268517589,53.23010747783218],"type":"Point"}
}