{
  "type": "Feature",
  "properties": {
    "iso:country": "GB",
    "wof:name": "LN6 7GJ",
    "wof:placetype": "postalcode"
  },
  "geometry": {"coordinates":[-0.550527,53.230107],"type":"Point"}
}
