{
  "type": "Feature",
  "properties": {
    "iso:country":"GB",
    "wof:name":"SK4 5HZ",
    "wof:placetype":"postalcode"
},
  "geometry": {"coordinates":[-2.16672474941107,53.43149060346178],"type":"Point"}
}