{
  "type": "Feature",
  "properties": {
    "iso:country":"GB",
    "wof:name":"BN25 3NP",
    "wof:placetype":"postalcode"
},
  "geometry": {"coordinates":[0.11519185125067,50.77682388185073],"type":"Point"}
}