{
  "type": "Feature",
  "properties": {
    "iso:country": "GB",
    "wof:name": "DE14 1QA",
    "wof:placetype": "postalcode"
  },
  "geometry": {"coordinates":[-1.63049,52.814443],"type":"Point"}
}
