{
  "type": "Feature",
  "properties": {
    "iso:country": "GB",
    "wof:name": "SN2 5NJ",
    "wof:placetype": "postalcode"
  },
  "geometry": {"coordinates":[-1.784705,51.595599],"type":"Point"}
}
