{
  "type": "Feature",
  "properties": {
    "iso:country":"GB",
    "wof:name":"PE14 0SE",
    "wof:placetype":"postalcode"
},
  "geometry": {"coordinates":[0.14742416009836,52.64835909588383],"type":"Point"}
}