{
  "type": "Feature",
  "properties": {
    "date:inception_lower": "1980-01-01",
    "date:inception_upper": "1980-01-01",
    "iso:country": "GB",
    "wof:name": "HU5 5ST",
    "wof:placetype": "postalcode"
  },
  "geometry": {"coordinates":[-0.399009,53.766582],"type":"Point"}
}
