{
  "type": "Feature",
  "properties": {
    "iso:country":"GB",
    "wof:name":"HU5 5ST",
    "wof:placetype":"postalcode"
},
  "geometry": {"coordinates":[-0.3990087992832,53.76658165754434],"type":"Point"}
}