{
  "type": "Feature",
  "properties": {
    "iso:country":"GB",
    "wof:name":"B44 9DU",
    "wof:placetype":"postalcode"
},
  "geometry": {"coordinates":[-1.89946592737893,52.55046356710174],"type":"Point"}
}