{
  "type": "Feature",
  "properties": {
    "iso:country":"GB",
    "wof:name":"DD7 7BZ",
    "wof:placetype":"postalcode"
},
  "geometry": {"coordinates":[-2.72020414571486,56.50179547844299],"type":"Point"}
}