{
  "type": "Feature",
  "properties": {
    "iso:country":"GB",
    "wof:name":"DG9 8JG",
    "wof:placetype":"postalcode"
},
  "geometry": {"coordinates":[-5.07500284611925,54.85665042595705],"type":"Point"}
}