{
  "type": "Feature",
  "properties": {
    "iso:country":"GB",
    "wof:name":"CT3 4EJ",
    "wof:placetype":"postalcode"
},
  "geometry": {"coordinates":[1.19555360245326,51.36058573283493],"type":"Point"}
}