{
  "type": "Feature",
  "properties": {
    "date:inception_lower": "1980-01-01",
    "date:inception_upper": "1980-01-01",
    "iso:country": "GB",
    "wof:name": "CT3 4EJ",
    "wof:placetype": "postalcode"
  },
  "geometry": {"coordinates":[1.194996,51.360625],"type":"Point"}
}
