{
  "type": "Feature",
  "properties": {
    "iso:country":"GB",
    "wof:name":"CF40 1PF",
    "wof:placetype":"postalcode"
},
  "geometry": {"coordinates":[-3.44198054889863,51.60933439313855],"type":"Point"}
}