{
  "type": "Feature",
  "properties": {
    "date:inception_lower":"1987-04-01",
    "date:inception_upper":"1987-04-30",
    "iso:country":"GB",
    "wof:name":"HP6 5DP",
    "wof:placetype":"postalcode"
},
  "geometry": {"coordinates":[-0.602193,51.674491],"type":"Point"}
}