{
  "type": "Feature",
  "properties": {
    "iso:country":"GB",
    "wof:name":"LS18 4NP",
    "wof:placetype":"postalcode"
},
  "geometry": {"coordinates":[-1.63798442269824,53.8331223447534],"type":"Point"}
}