{
  "type": "Feature",
  "properties": {
    "iso:country": "GB",
    "wof:name": "E14 6EF",
    "wof:placetype": "postalcode"
  },
  "geometry": {"coordinates":[-0.017565,51.514194],"type":"Point"}
}
