{
  "type": "Feature",
  "properties": {
    "date:inception_lower": "2022-10-01",
    "date:inception_upper": "2022-10-01",
    "iso:country": "GB",
    "wof:name": "YO10 5FY",
    "wof:placetype": "postalcode"
  },
  "geometry": {"coordinates":[-1.035222,53.946458],"type":"Point"}
}
