{
  "type": "Feature",
  "properties": {
    "iso:country": "GB",
    "wof:name": "DE45 1HB",
    "wof:placetype": "postalcode"
  },
  "geometry": {"coordinates":[-1.673894,53.213186],"type":"Point"}
}
