{
  "type": "Feature",
  "properties": {
    "iso:country":"GB",
    "wof:name":"DE45 1HB",
    "wof:placetype":"postalcode"
},
  "geometry": {"coordinates":[-1.67389533818623,53.21316856356578],"type":"Point"}
}