{
  "type": "Feature",
  "properties": {
    "date:inception_lower":"1983-07-01",
    "date:inception_upper":"1983-07-31",
    "iso:country":"GB",
    "wof:name":"OL4 3BN",
    "wof:placetype":"postalcode"
},
  "geometry": {"coordinates":[-2.073517,53.53815],"type":"Point"}
}