{
  "type": "Feature",
  "properties": {
    "iso:country":"GB",
    "wof:name":"OL4 3BN",
    "wof:placetype":"postalcode"
},
  "geometry": {"coordinates":[-2.0734585232188,53.53813342736248],"type":"Point"}
}