{
  "type": "Feature",
  "properties": {
    "date:inception_lower":"2000-12-01",
    "date:inception_upper":"2000-12-31",
    "iso:country":"GB",
    "wof:name":"PA17 5EB",
    "wof:placetype":"postalcode"
},
  "geometry": {"coordinates":[-4.890386,55.867905],"type":"Point"}
}