{
  "type": "Feature",
  "properties": {
    "iso:country":"GB",
    "wof:name":"PA17 5EB",
    "wof:placetype":"postalcode"
},
  "geometry": {"coordinates":[-4.89038610941022,55.86790498877707],"type":"Point"}
}