{
  "type": "Feature",
  "properties": {
    "iso:country": "GB",
    "wof:name": "PA17 5EB",
    "wof:placetype": "postalcode"
  },
  "geometry": {"coordinates":[-4.890386,55.867905],"type":"Point"}
}
