{
  "type": "Feature",
  "properties": {
    "iso:country": "GB",
    "wof:name": "KT12 4PL",
    "wof:placetype": "postalcode"
  },
  "geometry": {"coordinates":[-0.386669,51.371082],"type":"Point"}
}
