{
  "type": "Feature",
  "properties": {
    "iso:country":"GB",
    "wof:name":"KT12 4PL",
    "wof:placetype":"postalcode"
},
  "geometry": {"coordinates":[-0.38666903428537,51.37108186935651],"type":"Point"}
}