{
  "type": "Feature",
  "properties": {
    "iso:country": "GB",
    "wof:name": "HD5 9PH",
    "wof:placetype": "postalcode"
  },
  "geometry": {"coordinates":[-1.756005,53.656859],"type":"Point"}
}
