{
  "type": "Feature",
  "properties": {
    "iso:country":"GB",
    "wof:name":"DL14 6LH",
    "wof:placetype":"postalcode"
},
  "geometry": {"coordinates":[-1.68734005370804,54.65121580393037],"type":"Point"}
}