{
  "type": "Feature",
  "properties": {
    "date:inception_lower": "1986-07-01",
    "date:inception_upper": "1986-07-01",
    "iso:country": "GB",
    "wof:name": "CF48 1YE",
    "wof:placetype": "postalcode"
  },
  "geometry": {"coordinates":[-3.384066,51.746302],"type":"Point"}
}
