{
  "type": "Feature",
  "properties": {
    "iso:country":"GB",
    "wof:name":"CF48 1YE",
    "wof:placetype":"postalcode"
},
  "geometry": {"coordinates":[-3.3840661823389,51.74630230736295],"type":"Point"}
}