{
  "type": "Feature",
  "properties": {
    "iso:country":"GB",
    "wof:name":"AB12 5YX",
    "wof:placetype":"postalcode"
},
  "geometry": {"coordinates":[-2.20756514651677,57.06967461601384],"type":"Point"}
}