{
  "type": "Feature",
  "properties": {
    "date:inception_lower": "1980-01-01",
    "date:inception_upper": "1980-01-01",
    "iso:country": "GB",
    "wof:name": "CA6 4PG",
    "wof:placetype": "postalcode"
  },
  "geometry": {"coordinates":[-2.789608,54.953784],"type":"Point"}
}
