{
  "type": "Feature",
  "properties": {
    "iso:country":"GB",
    "wof:name":"IP24 3RL",
    "wof:placetype":"postalcode"
},
  "geometry": {"coordinates":[0.73223599767689,52.40443039012106],"type":"Point"}
}