{
  "type": "Feature",
  "properties": {
    "iso:country": "GB",
    "wof:name": "IP24 3RL",
    "wof:placetype": "postalcode"
  },
  "geometry": {"coordinates":[0.732236,52.40443],"type":"Point"}
}
