{
  "type": "Feature",
  "properties": {
    "iso:country":"GB",
    "wof:name":"WN2 5PU",
    "wof:placetype":"postalcode"
},
  "geometry": {"coordinates":[-2.58897911424491,53.51301977171004],"type":"Point"}
}