{
  "type": "Feature",
  "properties": {
    "iso:country": "GB",
    "wof:name": "WN2 5PU",
    "wof:placetype": "postalcode"
  },
  "geometry": {"coordinates":[-2.588979,53.51302],"type":"Point"}
}
