{
  "type": "Feature",
  "properties": {
    "date:inception_lower": "2023-01-01",
    "date:inception_upper": "2023-01-01",
    "iso:country": "GB",
    "wof:name": "TR1 3GP",
    "wof:placetype": "postalcode"
  },
  "geometry": {"coordinates":[-5.066415,50.263148],"type":"Point"}
}
