{
  "type": "Feature",
  "properties": {
    "date:inception_lower": "1980-01-01",
    "date:inception_upper": "1980-01-01",
    "iso:country": "GB",
    "wof:name": "L37 0AN",
    "wof:placetype": "postalcode"
  },
  "geometry": {"coordinates":[-3.046833,53.572608],"type":"Point"}
}
