{
  "type": "Feature",
  "properties": {
    "iso:country":"GB",
    "wof:name":"L37 0AN",
    "wof:placetype":"postalcode"
},
  "geometry": {"coordinates":[-3.04685076253578,53.57260089168334],"type":"Point"}
}