{
  "type": "Feature",
  "properties": {
    "date:inception_lower": "1980-01-01",
    "date:inception_upper": "1980-01-01",
    "iso:country": "GB",
    "wof:name": "LL73 8PD",
    "wof:placetype": "postalcode"
  },
  "geometry": {"coordinates":[-4.242819,53.33813],"type":"Point"}
}
