{
  "type": "Feature",
  "properties": {
    "iso:country":"GB",
    "wof:name":"LL73 8PD",
    "wof:placetype":"postalcode"
},
  "geometry": {"coordinates":[-4.24281912332414,53.33812957711396],"type":"Point"}
}