{
  "type": "Feature",
  "properties": {
    "iso:country":"GB",
    "wof:name":"SK7 5ED",
    "wof:placetype":"postalcode"
},
  "geometry": {"coordinates":[-2.12726381826924,53.3769876973515],"type":"Point"}
}