{
  "type": "Feature",
  "properties": {
    "date:inception_lower": "1980-01-01",
    "date:inception_upper": "1980-01-01",
    "iso:country": "GB",
    "wof:name": "SK7 5ED",
    "wof:placetype": "postalcode"
  },
  "geometry": {"coordinates":[-2.126812,53.376906],"type":"Point"}
}
