{
  "type": "Feature",
  "properties": {
    "iso:country": "GB",
    "wof:name": "CW6 9NZ",
    "wof:placetype": "postalcode"
  },
  "geometry": {"coordinates":[-2.671546,53.132841],"type":"Point"}
}
