{
  "type": "Feature",
  "properties": {
    "date:inception_lower": "2000-06-01",
    "date:inception_upper": "2000-06-01",
    "iso:country": "GB",
    "wof:name": "CW6 9NZ",
    "wof:placetype": "postalcode"
  },
  "geometry": {"coordinates":[-2.671546,53.132841],"type":"Point"}
}
