{
  "type": "Feature",
  "properties": {
    "iso:country":"GB",
    "wof:name":"SN11 0QP",
    "wof:placetype":"postalcode"
},
  "geometry": {"coordinates":[-2.00189304930696,51.4316573282338],"type":"Point"}
}