{
  "type": "Feature",
  "properties": {
    "iso:country": "GB",
    "wof:name": "SN11 0QP",
    "wof:placetype": "postalcode"
  },
  "geometry": {"coordinates":[-2.001893,51.431657],"type":"Point"}
}
