{
  "type": "Feature",
  "properties": {
    "iso:country":"GB",
    "wof:name":"BH12 4AA",
    "wof:placetype":"postalcode"
},
  "geometry": {"coordinates":[-1.92004108972417,50.73559602506766],"type":"Point"}
}