{
  "type": "Feature",
  "properties": {
    "iso:country": "GB",
    "wof:name": "RH11 9EJ",
    "wof:placetype": "postalcode"
  },
  "geometry": {"coordinates":[-0.210221,51.101037],"type":"Point"}
}
