{
  "type": "Feature",
  "properties": {
    "iso:country": "GB",
    "wof:name": "WA14 1LJ",
    "wof:placetype": "postalcode"
  },
  "geometry": {"coordinates":[-2.344537,53.396207],"type":"Point"}
}
