{
  "type": "Feature",
  "properties": {
    "iso:country":"GB",
    "wof:name":"PL27 7EH",
    "wof:placetype":"postalcode"
},
  "geometry": {"coordinates":[-4.8415790141385,50.51543742515058],"type":"Point"}
}