{
  "type": "Feature",
  "properties": {
    "iso:country":"GB",
    "wof:name":"CB9 9NP",
    "wof:placetype":"postalcode"
},
  "geometry": {"coordinates":[0.43536782271103,52.09170258620776],"type":"Point"}
}