{
  "type": "Feature",
  "properties": {
    "date:inception_lower": "2018-01-01",
    "date:inception_upper": "2018-01-01",
    "iso:country": "GB",
    "wof:name": "CH5 4AH",
    "wof:placetype": "postalcode"
  },
  "geometry": {"coordinates":[-3.062868,53.221877],"type":"Point"}
}
