{
  "type": "Feature",
  "properties": {
    "date:inception_lower": "1980-01-01",
    "date:inception_upper": "1980-01-01",
    "iso:country": "GB",
    "wof:name": "NE47 7HB",
    "wof:placetype": "postalcode"
  },
  "geometry": {"coordinates":[-2.393098,54.984819],"type":"Point"}
}
