{
  "type": "Feature",
  "properties": {
    "iso:country":"GB",
    "wof:name":"NE47 7HB",
    "wof:placetype":"postalcode"
},
  "geometry": {"coordinates":[-2.39309771110048,54.98481932583113],"type":"Point"}
}