{
  "type": "Feature",
  "properties": {
    "iso:country": "GB",
    "wof:name": "NE47 7HB",
    "wof:placetype": "postalcode"
  },
  "geometry": {"coordinates":[-2.393098,54.984819],"type":"Point"}
}
