{
  "type": "Feature",
  "properties": {
    "iso:country":"GB",
    "wof:name":"BA2 0DS",
    "wof:placetype":"postalcode"
},
  "geometry": {"coordinates":[-2.44090234359466,51.33035392697594],"type":"Point"}
}