{
  "type": "Feature",
  "properties": {
    "iso:country": "GB",
    "wof:name": "TS23 4EG",
    "wof:placetype": "postalcode"
  },
  "geometry": {"coordinates":[-1.261499,54.602101],"type":"Point"}
}
