{
  "type": "Feature",
  "properties": {
    "iso:country":"GB",
    "wof:name":"TS3 8QB",
    "wof:placetype":"postalcode"
},
  "geometry": {"coordinates":[-1.19698821582579,54.56152396623146],"type":"Point"}
}