{
  "type": "Feature",
  "properties": {
    "date:inception_lower": "1980-01-01",
    "date:inception_upper": "1980-01-01",
    "iso:country": "GB",
    "wof:name": "TS3 8QB",
    "wof:placetype": "postalcode"
  },
  "geometry": {"coordinates":[-1.196988,54.561524],"type":"Point"}
}
