{
  "type": "Feature",
  "properties": {
    "date:inception_lower": "2014-11-01",
    "date:inception_upper": "2014-11-01",
    "iso:country": "GB",
    "wof:name": "PO19 8FQ",
    "wof:placetype": "postalcode"
  },
  "geometry": {"coordinates":[-0.784944,50.820924],"type":"Point"}
}
