{
  "type": "Feature",
  "properties": {
    "iso:country":"GB",
    "wof:name":"SY16 4PA",
    "wof:placetype":"postalcode"
},
  "geometry": {"coordinates":[-3.25656475822251,52.490799632107],"type":"Point"}
}