{
  "type": "Feature",
  "properties": {
    "date:inception_lower": "1980-01-01",
    "date:inception_upper": "1980-01-01",
    "iso:country": "GB",
    "wof:name": "SY16 4PA",
    "wof:placetype": "postalcode"
  },
  "geometry": {"coordinates":[-3.253522,52.49198],"type":"Point"}
}
