{
  "type": "Feature",
  "properties": {
    "iso:country":"GB",
    "wof:name":"CV5 8GZ",
    "wof:placetype":"postalcode"
},
  "geometry": {"coordinates":[-1.54651135578733,52.41408690020718],"type":"Point"}
}