{
  "type": "Feature",
  "properties": {
    "date:inception_lower": "2002-12-01",
    "date:inception_upper": "2002-12-01",
    "iso:country": "GB",
    "wof:name": "WS14 0HB",
    "wof:placetype": "postalcode"
  },
  "geometry": {"coordinates":[-1.838371,52.633678],"type":"Point"}
}
