{
  "type": "Feature",
  "properties": {
    "iso:country": "GB",
    "wof:name": "WS14 0HB",
    "wof:placetype": "postalcode"
  },
  "geometry": {"coordinates":[-1.838371,52.633678],"type":"Point"}
}
