{
  "type": "Feature",
  "properties": {
    "iso:country":"GB",
    "wof:name":"WS14 0HB",
    "wof:placetype":"postalcode"
},
  "geometry": {"coordinates":[-1.83837059620984,52.63367753003875],"type":"Point"}
}