{
  "type": "Feature",
  "properties": {
    "iso:country":"GB",
    "wof:name":"S5 7SS",
    "wof:placetype":"postalcode"
},
  "geometry": {"coordinates":[-1.46311136672743,53.42417283997871],"type":"Point"}
}