{
  "type": "Feature",
  "properties": {
    "iso:country":"GB",
    "wof:name":"LE67 9WP",
    "wof:placetype":"postalcode"
},
  "geometry": {"coordinates":[-1.27696731003949,52.68554915788348],"type":"Point"}
}