{
  "type": "Feature",
  "properties": {
    "iso:country":"GB",
    "wof:name":"NR3 4TN",
    "wof:placetype":"postalcode"
},
  "geometry": {"coordinates":[1.30299113947441,52.64380708395228],"type":"Point"}
}