{
  "type": "Feature",
  "properties": {
    "iso:country": "GB",
    "wof:name": "HU2 8AR",
    "wof:placetype": "postalcode"
  },
  "geometry": {"coordinates":[-0.336321,53.750366],"type":"Point"}
}
