{
  "type": "Feature",
  "properties": {
    "iso:country": "GB",
    "wof:name": "HP20 1XT",
    "wof:placetype": "postalcode"
  },
  "geometry": {"coordinates":[-0.79501,51.825616],"type":"Point"}
}
