{
  "type": "Feature",
  "properties": {
    "date:inception_lower": "2017-05-01",
    "date:inception_upper": "2017-05-01",
    "iso:country": "GB",
    "wof:name": "CB24 1AH",
    "wof:placetype": "postalcode"
  },
  "geometry": {"coordinates":[0.048321,52.288295],"type":"Point"}
}
