{
  "type": "Feature",
  "properties": {
    "date:inception_lower":"2001-06-01",
    "date:inception_upper":"2001-06-30",
    "iso:country":"GB",
    "wof:name":"NE12 8UX",
    "wof:placetype":"postalcode"
},
  "geometry": {"coordinates":[-1.597926,55.012263],"type":"Point"}
}