{
  "type": "Feature",
  "properties": {
    "iso:country": "GB",
    "wof:name": "TQ12 1PT",
    "wof:placetype": "postalcode"
  },
  "geometry": {"coordinates":[-3.621056,50.533841],"type":"Point"}
}
