{
  "type": "Feature",
  "properties": {
    "iso:country":"GB",
    "wof:name":"LE9 8FJ",
    "wof:placetype":"postalcode"
},
  "geometry": {"coordinates":[-1.34369843196844,52.57503805012168],"type":"Point"}
}