{
  "type": "Feature",
  "properties": {
    "date:inception_lower": "2005-01-01",
    "date:inception_upper": "2005-01-01",
    "iso:country": "GB",
    "wof:name": "RM19 1PR",
    "wof:placetype": "postalcode"
  },
  "geometry": {"coordinates":[0.247784,51.479524],"type":"Point"}
}
