{
  "type": "Feature",
  "properties": {
    "iso:country":"GB",
    "wof:name":"S41 8DL",
    "wof:placetype":"postalcode"
},
  "geometry": {"coordinates":[-1.4502506497314,53.25665366604241],"type":"Point"}
}