{
  "type": "Feature",
  "properties": {
    "date:inception_lower": "1987-04-01",
    "date:inception_upper": "1987-04-01",
    "iso:country": "GB",
    "wof:name": "S41 8DL",
    "wof:placetype": "postalcode"
  },
  "geometry": {"coordinates":[-1.450235,53.256663],"type":"Point"}
}
