{
  "type": "Feature",
  "properties": {
    "iso:country": "GB",
    "wof:name": "S41 8DL",
    "wof:placetype": "postalcode"
  },
  "geometry": {"coordinates":[-1.450235,53.256663],"type":"Point"}
}
