{
  "type": "Feature",
  "properties": {
    "iso:country":"GB",
    "wof:name":"PL15 7PD",
    "wof:placetype":"postalcode"
},
  "geometry": {"coordinates":[-4.45269986630573,50.57012180234017],"type":"Point"}
}