{
  "type": "Feature",
  "properties": {
    "iso:country": "GB",
    "wof:name": "PL15 7PD",
    "wof:placetype": "postalcode"
  },
  "geometry": {"coordinates":[-4.4527,50.570122],"type":"Point"}
}
