{
  "type": "Feature",
  "properties": {
    "iso:country":"GB",
    "wof:name":"DA12 5JT",
    "wof:placetype":"postalcode"
},
  "geometry": {"coordinates":[0.37543956370808,51.41840663834221],"type":"Point"}
}