{
  "type": "Feature",
  "properties": {
    "iso:country": "GB",
    "wof:name": "DG7 1HF",
    "wof:placetype": "postalcode"
  },
  "geometry": {"coordinates":[-3.934942,54.936003],"type":"Point"}
}
