{
  "type": "Feature",
  "properties": {
    "date:inception_lower": "2022-07-01",
    "date:inception_upper": "2022-07-01",
    "iso:country": "GB",
    "wof:name": "NG11 6RS",
    "wof:placetype": "postalcode"
  },
  "geometry": {"coordinates":[-1.156011,52.88873],"type":"Point"}
}
