{
  "type": "Feature",
  "properties": {
    "date:inception_lower": "1980-01-01",
    "date:inception_upper": "1980-01-01",
    "iso:country": "GB",
    "wof:name": "B45 8RZ",
    "wof:placetype": "postalcode"
  },
  "geometry": {"coordinates":[-2.001498,52.386259],"type":"Point"}
}
