{
  "type": "Feature",
  "properties": {
    "iso:country": "GB",
    "wof:name": "CH4 8RW",
    "wof:placetype": "postalcode"
  },
  "geometry": {"coordinates":[-2.935828,53.178617],"type":"Point"}
}
