{
  "type": "Feature",
  "properties": {
    "iso:country":"GB",
    "wof:name":"CH4 8RW",
    "wof:placetype":"postalcode"
},
  "geometry": {"coordinates":[-2.93481064230445,53.17795295319099],"type":"Point"}
}