{
  "type": "Feature",
  "properties": {
    "date:inception_lower":"2018-09-01",
    "date:inception_upper":"2018-09-30",
    "iso:country":"GB",
    "wof:name":"CM3 3AA",
    "wof:placetype":"postalcode"
},
  "geometry": {"coordinates":[0.550665,51.7654],"type":"Point"}
}