{
  "type": "Feature",
  "properties": {
    "iso:country":"GB",
    "wof:name":"CM3 3AA",
    "wof:placetype":"postalcode"
},
  "geometry": {"coordinates":[0.55059361958389,51.76535724428302],"type":"Point"}
}