{
  "type": "Feature",
  "properties": {
    "date:inception_lower": "1980-01-01",
    "date:inception_upper": "1980-01-01",
    "iso:country": "GB",
    "wof:name": "DA15 9NP",
    "wof:placetype": "postalcode"
  },
  "geometry": {"coordinates":[0.116031,51.448379],"type":"Point"}
}
