{
  "type": "Feature",
  "properties": {
    "date:inception_lower":"1980-01-01",
    "date:inception_upper":"1980-01-31",
    "iso:country":"GB",
    "wof:name":"PE12 0RZ",
    "wof:placetype":"postalcode"
},
  "geometry": {"coordinates":[-0.035087,52.707057],"type":"Point"}
}