{
  "type": "Feature",
  "properties": {
    "iso:country":"GB",
    "wof:name":"GU1 4HP",
    "wof:placetype":"postalcode"
},
  "geometry": {"coordinates":[-0.57107956455836,51.24038881426824],"type":"Point"}
}