{
  "type": "Feature",
  "properties": {
    "iso:country":"GB",
    "wof:name":"N11 3GW",
    "wof:placetype":"postalcode"
},
  "geometry": {"coordinates":[-0.158012811178,51.61348454327182],"type":"Point"}
}