{
  "type": "Feature",
  "properties": {
    "iso:country":"GB",
    "wof:name":"DE45 1LG",
    "wof:placetype":"postalcode"
},
  "geometry": {"coordinates":[-1.67077001090319,53.17741108629596],"type":"Point"}
}