{
  "type": "Feature",
  "properties": {
    "iso:country": "GB",
    "wof:name": "DE45 1LG",
    "wof:placetype": "postalcode"
  },
  "geometry": {"coordinates":[-1.67077,53.177411],"type":"Point"}
}
