{
  "type": "Feature",
  "properties": {
    "date:inception_lower": "1980-01-01",
    "date:inception_upper": "1980-01-01",
    "iso:country": "GB",
    "wof:name": "WD6 5LY",
    "wof:placetype": "postalcode"
  },
  "geometry": {"coordinates":[-0.270999,51.668864],"type":"Point"}
}
