{
  "type": "Feature",
  "properties": {
    "iso:country":"GB",
    "wof:name":"WD6 5LY",
    "wof:placetype":"postalcode"
},
  "geometry": {"coordinates":[-0.27117003309238,51.66919462746056],"type":"Point"}
}