{
  "type": "Feature",
  "properties": {
    "iso:country":"GB",
    "wof:name":"BR7 5RN",
    "wof:placetype":"postalcode"
},
  "geometry": {"coordinates":[0.06523330572806,51.40668535825105],"type":"Point"}
}