{
  "type": "Feature",
  "properties": {
    "iso:country":"GB",
    "wof:name":"WR1 3DG",
    "wof:placetype":"postalcode"
},
  "geometry": {"coordinates":[-2.22642576359519,52.19832512282131],"type":"Point"}
}