{
  "type": "Feature",
  "properties": {
    "iso:country": "GB",
    "wof:name": "WR1 3DG",
    "wof:placetype": "postalcode"
  },
  "geometry": {"coordinates":[-2.226426,52.198325],"type":"Point"}
}
