{
  "type": "Feature",
  "properties": {
    "iso:country":"GB",
    "wof:name":"WF14 9FD",
    "wof:placetype":"postalcode"
},
  "geometry": {"coordinates":[-1.71265152579397,53.68395186514424],"type":"Point"}
}