{
  "type": "Feature",
  "properties": {
    "date:inception_lower":"2012-09-01",
    "date:inception_upper":"2012-09-30",
    "iso:country":"GB",
    "wof:name":"WF14 9FD",
    "wof:placetype":"postalcode"
},
  "geometry": {"coordinates":[-1.712651,53.683952],"type":"Point"}
}