{
  "type": "Feature",
  "properties": {
    "iso:country": "GB",
    "wof:name": "PR4 5QL",
    "wof:placetype": "postalcode"
  },
  "geometry": {"coordinates":[-2.788174,53.711138],"type":"Point"}
}
