{
  "type": "Feature",
  "properties": {
    "iso:country":"GB",
    "wof:name":"GL15 6PP",
    "wof:placetype":"postalcode"
},
  "geometry": {"coordinates":[-2.60098864205787,51.68444872051317],"type":"Point"}
}