{
  "type": "Feature",
  "properties": {
    "iso:country":"GB",
    "wof:name":"TD6 0SJ",
    "wof:placetype":"postalcode"
},
  "geometry": {"coordinates":[-2.67243539020456,55.57684814041446],"type":"Point"}
}