{
  "type": "Feature",
  "properties": {
    "date:inception_lower": "1996-06-01",
    "date:inception_upper": "1996-06-01",
    "iso:country": "GB",
    "wof:name": "TD6 0SJ",
    "wof:placetype": "postalcode"
  },
  "geometry": {"coordinates":[-2.672435,55.576848],"type":"Point"}
}
