{
  "type": "Feature",
  "properties": {
    "iso:country":"GB",
    "wof:name":"SP4 8QH",
    "wof:placetype":"postalcode"
},
  "geometry": {"coordinates":[-1.79720753140117,51.19190577647905],"type":"Point"}
}