{
  "type": "Feature",
  "properties": {
    "date:inception_lower": "1980-01-01",
    "date:inception_upper": "1980-01-01",
    "iso:country": "GB",
    "wof:name": "SP4 8QH",
    "wof:placetype": "postalcode"
  },
  "geometry": {"coordinates":[-1.797207,51.191906],"type":"Point"}
}
