{
  "type": "Feature",
  "properties": {
    "iso:country": "GB",
    "wof:name": "SP4 8QH",
    "wof:placetype": "postalcode"
  },
  "geometry": {"coordinates":[-1.797207,51.191906],"type":"Point"}
}
