{
  "type": "Feature",
  "properties": {
    "date:inception_lower":"1980-01-01",
    "date:inception_upper":"1980-01-31",
    "iso:country":"GB",
    "wof:name":"KY2 6UF",
    "wof:placetype":"postalcode"
},
  "geometry": {"coordinates":[-3.205533,56.126647],"type":"Point"}
}