{
  "type": "Feature",
  "properties": {
    "iso:country":"GB",
    "wof:name":"KY2 6UF",
    "wof:placetype":"postalcode"
},
  "geometry": {"coordinates":[-3.20553295594511,56.12664717121574],"type":"Point"}
}