{
  "type": "Feature",
  "properties": {
    "iso:country":"GB",
    "wof:name":"CT3 1UZ",
    "wof:placetype":"postalcode"
},
  "geometry": {"coordinates":[1.16311359907514,51.27177126605077],"type":"Point"}
}