{
  "type": "Feature",
  "properties": {
    "iso:country":"GB",
    "wof:name":"KW16 3EX",
    "wof:placetype":"postalcode"
},
  "geometry": {"coordinates":[-3.28394519420066,58.98090381076211],"type":"Point"}
}