{
  "type": "Feature",
  "properties": {
    "date:inception_lower": "2011-05-01",
    "date:inception_upper": "2011-05-01",
    "iso:country": "GB",
    "wof:name": "AB30 1ZQ",
    "wof:placetype": "postalcode"
  },
  "geometry": {"coordinates":[-2.450377,56.897604],"type":"Point"}
}
