{
  "type": "Feature",
  "properties": {
    "iso:country":"GB",
    "wof:name":"NW3 4SS",
    "wof:placetype":"postalcode"
},
  "geometry": {"coordinates":[-0.15933622714673,51.54467751910988],"type":"Point"}
}