{
  "type": "Feature",
  "properties": {
    "iso:country":"GB",
    "wof:name":"CF24 3AJ",
    "wof:placetype":"postalcode"
},
  "geometry": {"coordinates":[-3.17106070649774,51.48708543040023],"type":"Point"}
}