{
  "type": "Feature",
  "properties": {
    "date:inception_lower":"1999-06-01",
    "date:inception_upper":"1999-06-30",
    "iso:country":"GB",
    "wof:name":"CF24 3AJ",
    "wof:placetype":"postalcode"
},
  "geometry": {"coordinates":[-3.171061,51.487085],"type":"Point"}
}