{
  "type": "Feature",
  "properties": {
    "date:inception_lower": "1993-08-01",
    "date:inception_upper": "1993-08-01",
    "iso:country": "GB",
    "wof:name": "NN3 9DS",
    "wof:placetype": "postalcode"
  },
  "geometry": {"coordinates":[-0.81122,52.253209],"type":"Point"}
}
