{
  "type": "Feature",
  "properties": {
    "iso:country":"GB",
    "wof:name":"NN3 9DS",
    "wof:placetype":"postalcode"
},
  "geometry": {"coordinates":[-0.81122018262952,52.25320940528923],"type":"Point"}
}