{
  "type": "Feature",
  "properties": {
    "iso:country":"GB",
    "wof:name":"EN1 3LP",
    "wof:placetype":"postalcode"
},
  "geometry": {"coordinates":[-0.07367063812332,51.6620206597857],"type":"Point"}
}