{
  "type": "Feature",
  "properties": {
    "iso:country":"GB",
    "wof:name":"LS10 4BW",
    "wof:placetype":"postalcode"
},
  "geometry": {"coordinates":[-1.54425107273853,53.74745256773743],"type":"Point"}
}