{
  "type": "Feature",
  "properties": {
    "date:inception_lower": "2020-07-01",
    "date:inception_upper": "2020-07-01",
    "iso:country": "GB",
    "wof:name": "NW2 2DZ",
    "wof:placetype": "postalcode"
  },
  "geometry": {"coordinates":[-0.196539,51.561328],"type":"Point"}
}
