{
  "type": "Feature",
  "properties": {
    "date:inception_lower": "1993-08-01",
    "date:inception_upper": "1993-08-01",
    "iso:country": "GB",
    "wof:name": "NW3 2BP",
    "wof:placetype": "postalcode"
  },
  "geometry": {"coordinates":[-0.153733,51.544149],"type":"Point"}
}
