{
  "type": "Feature",
  "properties": {
    "iso:country":"GB",
    "wof:name":"NW3 2BP",
    "wof:placetype":"postalcode"
},
  "geometry": {"coordinates":[-0.15373306921179,51.54414884559944],"type":"Point"}
}