{
  "type": "Feature",
  "properties": {
    "iso:country":"GB",
    "wof:name":"NN2 8SF",
    "wof:placetype":"postalcode"
},
  "geometry": {"coordinates":[-0.89693246188554,52.28579635370804],"type":"Point"}
}