{
  "type": "Feature",
  "properties": {
    "date:inception_lower": "1992-01-01",
    "date:inception_upper": "1992-01-01",
    "iso:country": "GB",
    "wof:name": "LU7 0UJ",
    "wof:placetype": "postalcode"
  },
  "geometry": {"coordinates":[-0.746971,51.914813],"type":"Point"}
}
