{
  "type": "Feature",
  "properties": {
    "iso:country":"GB",
    "wof:name":"LU7 0UJ",
    "wof:placetype":"postalcode"
},
  "geometry": {"coordinates":[-0.74697111510419,51.9148127768697],"type":"Point"}
}