{
  "type": "Feature",
  "properties": {
    "iso:country":"GB",
    "wof:name":"SO50 6AW",
    "wof:placetype":"postalcode"
},
  "geometry": {"coordinates":[-1.33688075120606,50.97137741182562],"type":"Point"}
}