{
  "type": "Feature",
  "properties": {
    "date:inception_lower": "1980-01-01",
    "date:inception_upper": "1980-01-01",
    "iso:country": "GB",
    "wof:name": "SY1 1JD",
    "wof:placetype": "postalcode"
  },
  "geometry": {"coordinates":[-2.756824,52.707024],"type":"Point"}
}
