{
  "type": "Feature",
  "properties": {
    "iso:country":"GB",
    "wof:name":"SY1 1JD",
    "wof:placetype":"postalcode"
},
  "geometry": {"coordinates":[-2.7568107842148,52.70700952003838],"type":"Point"}
}