{
  "type": "Feature",
  "properties": {
    "iso:country": "GB",
    "wof:name": "PO10 7GP",
    "wof:placetype": "postalcode"
  },
  "geometry": {"coordinates":[-0.934308,50.864165],"type":"Point"}
}
