{
  "type": "Feature",
  "properties": {
    "iso:country":"GB",
    "wof:name":"PO10 7GP",
    "wof:placetype":"postalcode"
},
  "geometry": {"coordinates":[-0.93430808497803,50.86416492321761],"type":"Point"}
}