{
  "type": "Feature",
  "properties": {
    "iso:country":"GB",
    "wof:name":"BD10 8PT",
    "wof:placetype":"postalcode"
},
  "geometry": {"coordinates":[-1.7342871140814,53.83798486389653],"type":"Point"}
}