{
  "type": "Feature",
  "properties": {
    "iso:country":"GB",
    "wof:name":"HU12 9LR",
    "wof:placetype":"postalcode"
},
  "geometry": {"coordinates":[-0.17619676630612,53.72080696935944],"type":"Point"}
}