{
  "type": "Feature",
  "properties": {
    "iso:country": "GB",
    "wof:name": "LS15 4BH",
    "wof:placetype": "postalcode"
  },
  "geometry": {"coordinates":[-1.429023,53.825668],"type":"Point"}
}
