{
  "type": "Feature",
  "properties": {
    "date:inception_lower": "1998-06-01",
    "date:inception_upper": "1998-06-01",
    "iso:country": "GB",
    "wof:name": "M17 8DA",
    "wof:placetype": "postalcode"
  },
  "geometry": {"coordinates":[-2.347275,53.466544],"type":"Point"}
}
