{
  "type": "Feature",
  "properties": {
    "iso:country":"GB",
    "wof:name":"M17 8DA",
    "wof:placetype":"postalcode"
},
  "geometry": {"coordinates":[-2.3472755183016,53.46654353518355],"type":"Point"}
}