{
  "type": "Feature",
  "properties": {
    "iso:country":"GB",
    "wof:name":"G44 5TR",
    "wof:placetype":"postalcode"
},
  "geometry": {"coordinates":[-4.25872407411123,55.81422199551962],"type":"Point"}
}