{
  "type": "Feature",
  "properties": {
    "date:inception_lower":"1994-05-01",
    "date:inception_upper":"1994-05-31",
    "iso:country":"GB",
    "wof:name":"NR11 8LU",
    "wof:placetype":"postalcode"
},
  "geometry": {"coordinates":[1.41976,52.88399],"type":"Point"}
}