{
  "type": "Feature",
  "properties": {
    "iso:country":"GB",
    "wof:name":"CB22 3AA",
    "wof:placetype":"postalcode"
},
  "geometry": {"coordinates":[0.15800842952882,52.16675139902388],"type":"Point"}
}