{
  "type": "Feature",
  "properties": {
    "iso:country": "GB",
    "wof:name": "CM2 8JX",
    "wof:placetype": "postalcode"
  },
  "geometry": {"coordinates":[0.465376,51.696005],"type":"Point"}
}
