{
  "type": "Feature",
  "properties": {
    "iso:country":"GB",
    "wof:name":"CM2 8JX",
    "wof:placetype":"postalcode"
},
  "geometry": {"coordinates":[0.46537570391663,51.69600529298197],"type":"Point"}
}