{
  "type": "Feature",
  "properties": {
    "iso:country":"GB",
    "wof:name":"DH9 6PX",
    "wof:placetype":"postalcode"
},
  "geometry": {"coordinates":[-1.69845601730487,54.86622931412808],"type":"Point"}
}