{
  "type": "Feature",
  "properties": {
    "iso:country": "GB",
    "wof:name": "DH9 6PX",
    "wof:placetype": "postalcode"
  },
  "geometry": {"coordinates":[-1.698456,54.866229],"type":"Point"}
}
