{
  "type": "Feature",
  "properties": {
    "iso:country":"GB",
    "wof:name":"SW1A 1LY",
    "wof:placetype":"postalcode"
},
  "geometry": {"coordinates":[-0.13950980983966,51.50638949020252],"type":"Point"}
}