{
  "type": "Feature",
  "properties": {
    "date:inception_lower":"1980-01-01",
    "date:inception_upper":"1980-01-31",
    "iso:country":"GB",
    "wof:name":"B29 6PY",
    "wof:placetype":"postalcode"
},
  "geometry": {"coordinates":[-1.951673,52.442042],"type":"Point"}
}