{
  "type": "Feature",
  "properties": {
    "date:inception_lower": "2024-01-01",
    "date:inception_upper": "2024-01-01",
    "iso:country": "GB",
    "wof:name": "NN1 2FQ",
    "wof:placetype": "postalcode"
  },
  "geometry": {"coordinates":[-0.898497,52.241043],"type":"Point"}
}
