{
  "type": "Feature",
  "properties": {
    "date:inception_lower": "1980-01-01",
    "date:inception_upper": "1980-01-01",
    "iso:country": "GB",
    "wof:name": "GL3 2RT",
    "wof:placetype": "postalcode"
  },
  "geometry": {"coordinates":[-2.19009,51.88431],"type":"Point"}
}
