{
  "type": "Feature",
  "properties": {
    "iso:country":"GB",
    "wof:name":"M9 7DJ",
    "wof:placetype":"postalcode"
},
  "geometry": {"coordinates":[-2.19475725465706,53.521907946867],"type":"Point"}
}