{
  "type": "Feature",
  "properties": {
    "iso:country":"GB",
    "wof:name":"DD8 3NL",
    "wof:placetype":"postalcode"
},
  "geometry": {"coordinates":[-2.87810559632783,56.66460699703917],"type":"Point"}
}