{
  "type": "Feature",
  "properties": {
    "iso:country": "GB",
    "wof:name": "DD8 3NL",
    "wof:placetype": "postalcode"
  },
  "geometry": {"coordinates":[-2.878106,56.664607],"type":"Point"}
}
