{
  "type": "Feature",
  "properties": {
    "date:inception_lower": "1980-01-01",
    "date:inception_upper": "1980-01-01",
    "iso:country": "GB",
    "wof:name": "DD8 3NL",
    "wof:placetype": "postalcode"
  },
  "geometry": {"coordinates":[-2.878106,56.664607],"type":"Point"}
}
