{
  "type": "Feature",
  "properties": {
    "date:inception_lower": "2019-06-01",
    "date:inception_upper": "2019-06-01",
    "iso:country": "GB",
    "wof:name": "SW8 1GX",
    "wof:placetype": "postalcode"
  },
  "geometry": {"coordinates":[-0.124204,51.483036],"type":"Point"}
}
