{
  "type": "Feature",
  "properties": {
    "date:inception_lower":"1995-12-01",
    "date:inception_upper":"1995-12-31",
    "iso:country":"GB",
    "wof:name":"LS22 7FE",
    "wof:placetype":"postalcode"
},
  "geometry": {"coordinates":[-1.378408,53.934099],"type":"Point"}
}