{
  "type": "Feature",
  "properties": {
    "iso:country":"GB",
    "wof:name":"PL29 3TT",
    "wof:placetype":"postalcode"
},
  "geometry": {"coordinates":[-4.82945136721863,50.56596141806881],"type":"Point"}
}