{
  "type": "Feature",
  "properties": {
    "date:inception_lower": "1980-01-01",
    "date:inception_upper": "1980-01-01",
    "iso:country": "GB",
    "wof:name": "PL29 3TT",
    "wof:placetype": "postalcode"
  },
  "geometry": {"coordinates":[-4.829451,50.565961],"type":"Point"}
}
