{
  "type": "Feature",
  "properties": {
    "date:inception_lower": "1999-06-01",
    "date:inception_upper": "1999-06-01",
    "iso:country": "GB",
    "wof:name": "AB45 1HZ",
    "wof:placetype": "postalcode"
  },
  "geometry": {"coordinates":[-2.522382,57.668292],"type":"Point"}
}
