{
  "type": "Feature",
  "properties": {
    "iso:country": "GB",
    "wof:name": "AB45 1HZ",
    "wof:placetype": "postalcode"
  },
  "geometry": {"coordinates":[-2.522401,57.668409],"type":"Point"}
}
