{
  "type": "Feature",
  "properties": {
    "iso:country":"GB",
    "wof:name":"PH2 7RY",
    "wof:placetype":"postalcode"
},
  "geometry": {"coordinates":[-3.24204872033447,56.43341325118037],"type":"Point"}
}