{
  "type": "Feature",
  "properties": {
    "iso:country": "GB",
    "wof:name": "PH2 7RY",
    "wof:placetype": "postalcode"
  },
  "geometry": {"coordinates":[-3.242049,56.433413],"type":"Point"}
}
