{
  "type": "Feature",
  "properties": {
    "iso:country": "GB",
    "wof:name": "CW12 4ZQ",
    "wof:placetype": "postalcode"
  },
  "geometry": {"coordinates":[-2.232826,53.169475],"type":"Point"}
}
