{
  "type": "Feature",
  "properties": {
    "date:inception_lower": "1980-01-01",
    "date:inception_upper": "1980-01-01",
    "iso:country": "GB",
    "wof:name": "E14 0DE",
    "wof:placetype": "postalcode"
  },
  "geometry": {"coordinates":[-0.019683,51.509941],"type":"Point"}
}
