{
  "type": "Feature",
  "properties": {
    "iso:country": "GB",
    "wof:name": "E14 0DE",
    "wof:placetype": "postalcode"
  },
  "geometry": {"coordinates":[-0.019501,51.510145],"type":"Point"}
}
