{
  "type": "Feature",
  "properties": {
    "iso:country":"GB",
    "wof:name":"E14 0DE",
    "wof:placetype":"postalcode"
},
  "geometry": {"coordinates":[-0.01974594550515,51.50977004561423],"type":"Point"}
}