{
  "type": "Feature",
  "properties": {
    "iso:country":"GB",
    "wof:name":"WF8 3BJ",
    "wof:placetype":"postalcode"
},
  "geometry": {"coordinates":[-1.26693831208728,53.67492652165563],"type":"Point"}
}