{
  "type": "Feature",
  "properties": {
    "date:inception_lower": "1980-01-01",
    "date:inception_upper": "1980-01-01",
    "iso:country": "GB",
    "wof:name": "WF8 3BJ",
    "wof:placetype": "postalcode"
  },
  "geometry": {"coordinates":[-1.266938,53.674927],"type":"Point"}
}
