{
  "type": "Feature",
  "properties": {
    "iso:country":"GB",
    "wof:name":"OL10 3JU",
    "wof:placetype":"postalcode"
},
  "geometry": {"coordinates":[-2.24353783255249,53.59322182583059],"type":"Point"}
}