{
  "type": "Feature",
  "properties": {
    "iso:country": "GB",
    "wof:name": "OL10 3JU",
    "wof:placetype": "postalcode"
  },
  "geometry": {"coordinates":[-2.24349,53.593184],"type":"Point"}
}
