{
  "type": "Feature",
  "properties": {
    "date:inception_lower": "1980-01-01",
    "date:inception_upper": "1980-01-01",
    "iso:country": "GB",
    "wof:name": "OL10 3JU",
    "wof:placetype": "postalcode"
  },
  "geometry": {"coordinates":[-2.243535,53.593238],"type":"Point"}
}
