{
  "type": "Feature",
  "properties": {
    "iso:country": "GB",
    "wof:name": "LN6 9YR",
    "wof:placetype": "postalcode"
  },
  "geometry": {"coordinates":[-0.657028,53.152025],"type":"Point"}
}
