{
  "type": "Feature",
  "properties": {
    "iso:country":"GB",
    "wof:name":"LN6 9YR",
    "wof:placetype":"postalcode"
},
  "geometry": {"coordinates":[-0.65703033262345,53.15200406327949],"type":"Point"}
}