{
  "type": "Feature",
  "properties": {
    "date:inception_lower": "2013-07-01",
    "date:inception_upper": "2013-07-01",
    "iso:country": "GB",
    "wof:name": "LN6 9YR",
    "wof:placetype": "postalcode"
  },
  "geometry": {"coordinates":[-0.656848,53.152041],"type":"Point"}
}
