{
  "type": "Feature",
  "properties": {
    "iso:country":"GB",
    "wof:name":"OL4 3LT",
    "wof:placetype":"postalcode"
},
  "geometry": {"coordinates":[-2.06737636216908,53.54670291290189],"type":"Point"}
}