{
  "type": "Feature",
  "properties": {
    "iso:country":"GB",
    "wof:name":"ST13 7BD",
    "wof:placetype":"postalcode"
},
  "geometry": {"coordinates":[-2.0435450007456,53.06135100480794],"type":"Point"}
}