{
  "type": "Feature",
  "properties": {
    "iso:country": "GB",
    "wof:name": "ST13 7BD",
    "wof:placetype": "postalcode"
  },
  "geometry": {"coordinates":[-2.043545,53.061351],"type":"Point"}
}
