{
  "type": "Feature",
  "properties": {
    "iso:country":"GB",
    "wof:name":"NN8 2QN",
    "wof:placetype":"postalcode"
},
  "geometry": {"coordinates":[-0.69468278790607,52.28759138696444],"type":"Point"}
}