{
  "type": "Feature",
  "properties": {
    "date:inception_lower": "2005-06-01",
    "date:inception_upper": "2005-06-01",
    "iso:country": "GB",
    "wof:name": "NN8 2QN",
    "wof:placetype": "postalcode"
  },
  "geometry": {"coordinates":[-0.694683,52.287591],"type":"Point"}
}
