{
  "type": "Feature",
  "properties": {
    "date:inception_lower": "2017-02-01",
    "date:inception_upper": "2017-02-01",
    "iso:country": "GB",
    "wof:name": "YO42 4AD",
    "wof:placetype": "postalcode"
  },
  "geometry": {"coordinates":[-0.853379,53.88739],"type":"Point"}
}
