{
  "type": "Feature",
  "properties": {
    "iso:country": "GB",
    "wof:name": "CW2 8TF",
    "wof:placetype": "postalcode"
  },
  "geometry": {"coordinates":[-2.482327,53.099859],"type":"Point"}
}
