{
  "type": "Feature",
  "properties": {
    "date:inception_lower": "2021-04-01",
    "date:inception_upper": "2021-04-01",
    "iso:country": "GB",
    "wof:name": "AL4 0PW",
    "wof:placetype": "postalcode"
  },
  "geometry": {"coordinates":[-0.297567,51.759777],"type":"Point"}
}
