{
  "type": "Feature",
  "properties": {
    "iso:country":"GB",
    "wof:name":"TA24 7EB",
    "wof:placetype":"postalcode"
},
  "geometry": {"coordinates":[-3.54264510011225,51.14069366772788],"type":"Point"}
}