{
  "type": "Feature",
  "properties": {
    "iso:country": "GB",
    "wof:name": "TA24 7EB",
    "wof:placetype": "postalcode"
  },
  "geometry": {"coordinates":[-3.542645,51.140694],"type":"Point"}
}
