{
  "type": "Feature",
  "properties": {
    "iso:country":"GB",
    "wof:name":"SO40 8BQ",
    "wof:placetype":"postalcode"
},
  "geometry": {"coordinates":[-1.50072816348481,50.91500962426446],"type":"Point"}
}