{
  "type": "Feature",
  "properties": {
    "iso:country": "GB",
    "wof:name": "RH5 6LW",
    "wof:placetype": "postalcode"
  },
  "geometry": {"coordinates":[-0.394169,51.19107],"type":"Point"}
}
