{
  "type": "Feature",
  "properties": {
    "iso:country":"GB",
    "wof:name":"RH5 6LW",
    "wof:placetype":"postalcode"
},
  "geometry": {"coordinates":[-0.39415457775369,51.19179200288191],"type":"Point"}
}