{
  "type": "Feature",
  "properties": {
    "iso:country":"GB",
    "wof:name":"TA6 6ES",
    "wof:placetype":"postalcode"
},
  "geometry": {"coordinates":[-3.00612808496772,51.11484334897089],"type":"Point"}
}