{
  "type": "Feature",
  "properties": {
    "date:inception_lower":"1994-12-01",
    "date:inception_upper":"1994-12-31",
    "iso:country":"GB",
    "wof:name":"TA6 6ES",
    "wof:placetype":"postalcode"
},
  "geometry": {"coordinates":[-3.006128,51.114843],"type":"Point"}
}