{
  "type": "Feature",
  "properties": {
    "iso:country":"GB",
    "wof:name":"PA20 0NJ",
    "wof:placetype":"postalcode"
},
  "geometry": {"coordinates":[-5.06329290993795,55.84912929565324],"type":"Point"}
}