{
  "type": "Feature",
  "properties": {
    "iso:country": "GB",
    "wof:name": "PA20 0NJ",
    "wof:placetype": "postalcode"
  },
  "geometry": {"coordinates":[-5.0635,55.849529],"type":"Point"}
}
