{
  "type": "Feature",
  "properties": {
    "iso:country": "GB",
    "wof:name": "NN7 1NN",
    "wof:placetype": "postalcode"
  },
  "geometry": {"coordinates":[-0.757064,52.23681],"type":"Point"}
}
