{
  "type": "Feature",
  "properties": {
    "iso:country":"GB",
    "wof:name":"NN7 1NN",
    "wof:placetype":"postalcode"
},
  "geometry": {"coordinates":[-0.75706433061955,52.23680987610668],"type":"Point"}
}