{
  "type": "Feature",
  "properties": {
    "iso:country":"GB",
    "wof:name":"WA5 1NW",
    "wof:placetype":"postalcode"
},
  "geometry": {"coordinates":[-2.6135655930567,53.39439003133821],"type":"Point"}
}