{
  "type": "Feature",
  "properties": {
    "date:inception_lower":"1980-01-01",
    "date:inception_upper":"1980-01-31",
    "iso:country":"GB",
    "wof:name":"ST16 3DN",
    "wof:placetype":"postalcode"
},
  "geometry": {"coordinates":[-2.117424,52.821054],"type":"Point"}
}