{
  "type": "Feature",
  "properties": {
    "iso:country":"GB",
    "wof:name":"CM1 2GR",
    "wof:placetype":"postalcode"
},
  "geometry": {"coordinates":[0.44824811777811,51.73953915949932],"type":"Point"}
}