{
  "type": "Feature",
  "properties": {
    "iso:country": "GB",
    "wof:name": "HX3 5QD",
    "wof:placetype": "postalcode"
  },
  "geometry": {"coordinates":[-1.876455,53.737298],"type":"Point"}
}
