{
  "type": "Feature",
  "properties": {
    "iso:country":"GB",
    "wof:name":"HX3 5QD",
    "wof:placetype":"postalcode"
},
  "geometry": {"coordinates":[-1.87645499733379,53.73729815610389],"type":"Point"}
}