{
  "type": "Feature",
  "properties": {
    "iso:country": "GB",
    "wof:name": "DN22 9ET",
    "wof:placetype": "postalcode"
  },
  "geometry": {"coordinates":[-0.824333,53.386122],"type":"Point"}
}
