{
  "type": "Feature",
  "properties": {
    "iso:country":"GB",
    "wof:name":"DN22 9ET",
    "wof:placetype":"postalcode"
},
  "geometry": {"coordinates":[-0.82342749141094,53.3900024634931],"type":"Point"}
}