{
  "type": "Feature",
  "properties": {
    "iso:country": "GB",
    "wof:name": "OX10 9JQ",
    "wof:placetype": "postalcode"
  },
  "geometry": {"coordinates":[-1.148397,51.547922],"type":"Point"}
}
