{
  "type": "Feature",
  "properties": {
    "iso:country":"GB",
    "wof:name":"OX10 9JQ",
    "wof:placetype":"postalcode"
},
  "geometry": {"coordinates":[-1.14839665045712,51.54792194904855],"type":"Point"}
}