{
  "type": "Feature",
  "properties": {
    "date:inception_lower": "1980-01-01",
    "date:inception_upper": "1980-01-01",
    "iso:country": "GB",
    "wof:name": "OX10 9JQ",
    "wof:placetype": "postalcode"
  },
  "geometry": {"coordinates":[-1.148397,51.547922],"type":"Point"}
}
