{
  "type": "Feature",
  "properties": {
    "iso:country":"GB",
    "wof:name":"CO15 1RA",
    "wof:placetype":"postalcode"
},
  "geometry": {"coordinates":[1.15172834025635,51.78777756060442],"type":"Point"}
}