{
  "type": "Feature",
  "properties": {
    "iso:country": "GB",
    "wof:name": "CO15 1RA",
    "wof:placetype": "postalcode"
  },
  "geometry": {"coordinates":[1.151728,51.787778],"type":"Point"}
}
