{
  "type": "Feature",
  "properties": {
    "iso:country": "GB",
    "wof:name": "SS7 1TW",
    "wof:placetype": "postalcode"
  },
  "geometry": {"coordinates":[0.583347,51.56276],"type":"Point"}
}
