{
  "type": "Feature",
  "properties": {
    "iso:country":"GB",
    "wof:name":"SS7 1TW",
    "wof:placetype":"postalcode"
},
  "geometry": {"coordinates":[0.58334722767608,51.56275975534294],"type":"Point"}
}