{
  "type": "Feature",
  "properties": {
    "iso:country":"GB",
    "wof:name":"EX7 9NH",
    "wof:placetype":"postalcode"
},
  "geometry": {"coordinates":[-3.47648393695767,50.58243165567658],"type":"Point"}
}