{
  "type": "Feature",
  "properties": {
    "iso:country":"GB",
    "wof:name":"PO16 0AD",
    "wof:placetype":"postalcode"
},
  "geometry": {"coordinates":[-1.17937085594878,50.85270972172746],"type":"Point"}
}