{
  "type": "Feature",
  "properties": {
    "date:inception_lower": "2000-12-01",
    "date:inception_upper": "2000-12-01",
    "iso:country": "GB",
    "wof:name": "W1F 8GZ",
    "wof:placetype": "postalcode"
  },
  "geometry": {"coordinates":[-0.135622,51.515149],"type":"Point"}
}
