{
  "type": "Feature",
  "properties": {
    "date:inception_lower": "1980-01-01",
    "date:inception_upper": "1980-01-01",
    "iso:country": "GB",
    "wof:name": "B35 6HH",
    "wof:placetype": "postalcode"
  },
  "geometry": {"coordinates":[-1.791243,52.523299],"type":"Point"}
}
