{
  "type": "Feature",
  "properties": {
    "date:inception_lower": "2007-02-01",
    "date:inception_upper": "2007-02-01",
    "iso:country": "GB",
    "wof:name": "LE67 1GW",
    "wof:placetype": "postalcode"
  },
  "geometry": {"coordinates":[-1.349509,52.675928],"type":"Point"}
}
