{
  "type": "Feature",
  "properties": {
    "iso:country": "GB",
    "wof:name": "WV11 2RN",
    "wof:placetype": "postalcode"
  },
  "geometry": {"coordinates":[-2.035296,52.636585],"type":"Point"}
}
