{
  "type": "Feature",
  "properties": {
    "date:inception_lower": "2018-03-01",
    "date:inception_upper": "2018-03-01",
    "iso:country": "GB",
    "wof:name": "WV11 2RN",
    "wof:placetype": "postalcode"
  },
  "geometry": {"coordinates":[-2.0354,52.636639],"type":"Point"}
}
