{
  "type": "Feature",
  "properties": {
    "iso:country":"GB",
    "wof:name":"CB7 4DW",
    "wof:placetype":"postalcode"
},
  "geometry": {"coordinates":[0.26292199526288,52.39791202853296],"type":"Point"}
}