{
  "type": "Feature",
  "properties": {
    "date:inception_lower": "1990-02-01",
    "date:inception_upper": "1990-02-01",
    "iso:country": "GB",
    "wof:name": "HR2 6EX",
    "wof:placetype": "postalcode"
  },
  "geometry": {"coordinates":[-2.705861,52.037987],"type":"Point"}
}
