{
  "type": "Feature",
  "properties": {
    "iso:country":"GB",
    "wof:name":"HR2 6EX",
    "wof:placetype":"postalcode"
},
  "geometry": {"coordinates":[-2.70586106176104,52.03798739950112],"type":"Point"}
}