{
  "type": "Feature",
  "properties": {
    "iso:country": "GB",
    "wof:name": "HR2 6EX",
    "wof:placetype": "postalcode"
  },
  "geometry": {"coordinates":[-2.705861,52.037987],"type":"Point"}
}
