{
  "type": "Feature",
  "properties": {
    "iso:country":"GB",
    "wof:name":"PE2 9PJ",
    "wof:placetype":"postalcode"
},
  "geometry": {"coordinates":[-0.25288067620694,52.56485889327304],"type":"Point"}
}