{
  "type": "Feature",
  "properties": {
    "iso:country": "GB",
    "wof:name": "DT5 2JP",
    "wof:placetype": "postalcode"
  },
  "geometry": {"coordinates":[-2.444251,50.548633],"type":"Point"}
}
