{
  "type": "Feature",
  "properties": {
    "iso:country":"GB",
    "wof:name":"DT5 2JP",
    "wof:placetype":"postalcode"
},
  "geometry": {"coordinates":[-2.44425103988787,50.54863311031063],"type":"Point"}
}