{
  "type": "Feature",
  "properties": {
    "iso:country":"GB",
    "wof:name":"M21 8XT",
    "wof:placetype":"postalcode"
},
  "geometry": {"coordinates":[-2.26981402520513,53.43950853931568],"type":"Point"}
}