{
  "type": "Feature",
  "properties": {
    "iso:country":"GB",
    "wof:name":"RG1 7BH",
    "wof:placetype":"postalcode"
},
  "geometry": {"coordinates":[-0.9805677937339,51.45700811519815],"type":"Point"}
}