{
  "type": "Feature",
  "properties": {
    "date:inception_lower": "1990-02-01",
    "date:inception_upper": "1990-02-01",
    "iso:country": "GB",
    "wof:name": "RG1 7BH",
    "wof:placetype": "postalcode"
  },
  "geometry": {"coordinates":[-0.980568,51.457008],"type":"Point"}
}
