{
  "type": "Feature",
  "properties": {
    "iso:country":"GB",
    "wof:name":"PO37 7BS",
    "wof:placetype":"postalcode"
},
  "geometry": {"coordinates":[-1.18124504889547,50.64222816760282],"type":"Point"}
}