{
  "type": "Feature",
  "properties": {
    "iso:country": "GB",
    "wof:name": "PO37 7BS",
    "wof:placetype": "postalcode"
  },
  "geometry": {"coordinates":[-1.181245,50.642228],"type":"Point"}
}
