{
  "type": "Feature",
  "properties": {
    "iso:country":"GB",
    "wof:name":"W1T 5LQ",
    "wof:placetype":"postalcode"
},
  "geometry": {"coordinates":[-0.13882931851504,51.5241478845996],"type":"Point"}
}