{
  "type": "Feature",
  "properties": {
    "date:inception_lower": "2000-12-01",
    "date:inception_upper": "2000-12-01",
    "iso:country": "GB",
    "wof:name": "W1T 5LQ",
    "wof:placetype": "postalcode"
  },
  "geometry": {"coordinates":[-0.138829,51.524148],"type":"Point"}
}
