{
  "type": "Feature",
  "properties": {
    "iso:country": "GB",
    "wof:name": "W1T 5LQ",
    "wof:placetype": "postalcode"
  },
  "geometry": {"coordinates":[-0.138829,51.524148],"type":"Point"}
}
