{
  "type": "Feature",
  "properties": {
    "iso:country":"GB",
    "wof:name":"SN3 3HE",
    "wof:placetype":"postalcode"
},
  "geometry": {"coordinates":[-1.75591776146956,51.56350672185857],"type":"Point"}
}