{
  "type": "Feature",
  "properties": {
    "iso:country":"GB",
    "wof:name":"W1H 7JB",
    "wof:placetype":"postalcode"
},
  "geometry": {"coordinates":[-0.15857818265236,51.51486460074934],"type":"Point"}
}