{
  "type": "Feature",
  "properties": {
    "date:inception_lower": "2007-03-01",
    "date:inception_upper": "2007-03-01",
    "iso:country": "GB",
    "wof:name": "ML3 3XD",
    "wof:placetype": "postalcode"
  },
  "geometry": {"coordinates":[-4.049982,55.779568],"type":"Point"}
}
