{
  "type": "Feature",
  "properties": {
    "iso:country":"GB",
    "wof:name":"ML3 3XD",
    "wof:placetype":"postalcode"
},
  "geometry": {"coordinates":[-4.04998173849615,55.77956798756609],"type":"Point"}
}