{
  "type": "Feature",
  "properties": {
    "iso:country": "GB",
    "wof:name": "NR34 7UW",
    "wof:placetype": "postalcode"
  },
  "geometry": {"coordinates":[1.64909,52.433216],"type":"Point"}
}
