{
  "type": "Feature",
  "properties": {
    "date:inception_lower":"1980-01-01",
    "date:inception_upper":"1980-01-31",
    "iso:country":"GB",
    "wof:name":"NR34 7UW",
    "wof:placetype":"postalcode"
},
  "geometry": {"coordinates":[1.64909,52.433216],"type":"Point"}
}