{
  "type": "Feature",
  "properties": {
    "iso:country": "GB",
    "wof:name": "HA8 0RL",
    "wof:placetype": "postalcode"
  },
  "geometry": {"coordinates":[-0.256935,51.606381],"type":"Point"}
}
