{
  "type": "Feature",
  "properties": {
    "date:inception_lower":"1980-01-01",
    "date:inception_upper":"1980-01-31",
    "iso:country":"GB",
    "wof:name":"HA8 0RL",
    "wof:placetype":"postalcode"
},
  "geometry": {"coordinates":[-0.256935,51.606381],"type":"Point"}
}