{
  "type": "Feature",
  "properties": {
    "iso:country": "GB",
    "wof:name": "HA8 0RL",
    "wof:placetype": "postalcode"
  },
  "geometry": {"coordinates":[-0.25653,51.606531],"type":"Point"}
}
