{
  "type": "Feature",
  "properties": {
    "iso:country": "GB",
    "wof:name": "CR4 2BY",
    "wof:placetype": "postalcode"
  },
  "geometry": {"coordinates":[-0.160717,51.419128],"type":"Point"}
}
