{
  "type": "Feature",
  "properties": {
    "iso:country":"GB",
    "wof:name":"CR4 2BY",
    "wof:placetype":"postalcode"
},
  "geometry": {"coordinates":[-0.16071691791925,51.41912752638638],"type":"Point"}
}