{
  "type": "Feature",
  "properties": {
    "iso:country":"GB",
    "wof:name":"ZE1 0HW",
    "wof:placetype":"postalcode"
},
  "geometry": {"coordinates":[-1.15313721910292,60.15617830618039],"type":"Point"}
}