{
  "type": "Feature",
  "properties": {
    "date:inception_lower":"1996-12-01",
    "date:inception_upper":"1996-12-31",
    "iso:country":"GB",
    "wof:name":"MK45 2FL",
    "wof:placetype":"postalcode"
},
  "geometry": {"coordinates":[-0.4285,52.024305],"type":"Point"}
}