{
  "type": "Feature",
  "properties": {
    "iso:country":"GB",
    "wof:name":"MK45 2FL",
    "wof:placetype":"postalcode"
},
  "geometry": {"coordinates":[-0.42820001097137,52.02439821244186],"type":"Point"}
}