{
  "type": "Feature",
  "properties": {
    "date:inception_lower": "2006-10-01",
    "date:inception_upper": "2006-10-01",
    "iso:country": "GB",
    "wof:name": "SY23 2AD",
    "wof:placetype": "postalcode"
  },
  "geometry": {"coordinates":[-4.078568,52.417114],"type":"Point"}
}
