{
  "type": "Feature",
  "properties": {
    "iso:country":"GB",
    "wof:name":"SY23 2AD",
    "wof:placetype":"postalcode"
},
  "geometry": {"coordinates":[-4.0785676194513,52.41711401089935],"type":"Point"}
}