{
  "type": "Feature",
  "properties": {
    "iso:country":"GB",
    "wof:name":"YO12 4SD",
    "wof:placetype":"postalcode"
},
  "geometry": {"coordinates":[-0.4435210600921,54.19780734244519],"type":"Point"}
}