{
  "type": "Feature",
  "properties": {
    "iso:country":"GB",
    "wof:name":"BS15 3HA",
    "wof:placetype":"postalcode"
},
  "geometry": {"coordinates":[-2.51506738021867,51.4470333488011],"type":"Point"}
}