{
  "type": "Feature",
  "properties": {
    "date:inception_lower": "1980-01-01",
    "date:inception_upper": "1980-01-01",
    "iso:country": "GB",
    "wof:name": "BS16 6TX",
    "wof:placetype": "postalcode"
  },
  "geometry": {"coordinates":[-2.487355,51.497217],"type":"Point"}
}
