{
  "type": "Feature",
  "properties": {
    "date:inception_lower": "1980-01-01",
    "date:inception_upper": "1980-01-01",
    "iso:country": "GB",
    "wof:name": "SG6 2BP",
    "wof:placetype": "postalcode"
  },
  "geometry": {"coordinates":[-0.216382,51.969652],"type":"Point"}
}
