{
  "type": "Feature",
  "properties": {
    "iso:country":"GB",
    "wof:name":"CH41 9DN",
    "wof:placetype":"postalcode"
},
  "geometry": {"coordinates":[-3.01984534159077,53.38336718842488],"type":"Point"}
}