{
  "type": "Feature",
  "properties": {
    "iso:country":"GB",
    "wof:name":"N22 7UG",
    "wof:placetype":"postalcode"
},
  "geometry": {"coordinates":[-0.13424957780642,51.59841569222203],"type":"Point"}
}