{
  "type": "Feature",
  "properties": {
    "iso:country": "GB",
    "wof:name": "N22 7UG",
    "wof:placetype": "postalcode"
  },
  "geometry": {"coordinates":[-0.13425,51.598416],"type":"Point"}
}
