{
  "type": "Feature",
  "properties": {
    "iso:country":"GB",
    "wof:name":"SY5 7HB",
    "wof:placetype":"postalcode"
},
  "geometry": {"coordinates":[-2.72275137024182,52.60647256288875],"type":"Point"}
}