{
  "type": "Feature",
  "properties": {
    "iso:country": "GB",
    "wof:name": "SY5 7HB",
    "wof:placetype": "postalcode"
  },
  "geometry": {"coordinates":[-2.722751,52.606473],"type":"Point"}
}
