{
  "type": "Feature",
  "properties": {
    "iso:country": "GB",
    "wof:name": "CM1 6HY",
    "wof:placetype": "postalcode"
  },
  "geometry": {"coordinates":[0.493354,51.744778],"type":"Point"}
}
