{
  "type": "Feature",
  "properties": {
    "iso:country":"GB",
    "wof:name":"CM1 6HY",
    "wof:placetype":"postalcode"
},
  "geometry": {"coordinates":[0.49335421219175,51.74477768362291],"type":"Point"}
}