{
  "type": "Feature",
  "properties": {
    "iso:country":"GB",
    "wof:name":"FK4 1HS",
    "wof:placetype":"postalcode"
},
  "geometry": {"coordinates":[-3.93741824685278,55.99039904414965],"type":"Point"}
}