{
  "type": "Feature",
  "properties": {
    "iso:country": "GB",
    "wof:name": "BN23 6QW",
    "wof:placetype": "postalcode"
  },
  "geometry": {"coordinates":[0.286025,50.797843],"type":"Point"}
}
