{
  "type": "Feature",
  "properties": {
    "iso:country":"GB",
    "wof:name":"BN23 6QW",
    "wof:placetype":"postalcode"
},
  "geometry": {"coordinates":[0.28597959508325,50.79749776224624],"type":"Point"}
}