{
  "type": "Feature",
  "properties": {
    "iso:country":"GB",
    "wof:name":"GU32 3LS",
    "wof:placetype":"postalcode"
},
  "geometry": {"coordinates":[-0.94750854723639,50.99787954768257],"type":"Point"}
}