{
  "type": "Feature",
  "properties": {
    "iso:country": "GB",
    "wof:name": "GU32 3LS",
    "wof:placetype": "postalcode"
  },
  "geometry": {"coordinates":[-0.94754,50.997622],"type":"Point"}
}
