{
  "type": "Feature",
  "properties": {
    "iso:country":"GB",
    "wof:name":"HA3 8DS",
    "wof:placetype":"postalcode"
},
  "geometry": {"coordinates":[-0.30285629624157,51.58823271141164],"type":"Point"}
}