{
  "type": "Feature",
  "properties": {
    "iso:country":"GB",
    "wof:name":"CF5 6BP",
    "wof:placetype":"postalcode"
},
  "geometry": {"coordinates":[-3.27543458561498,51.4565116767827],"type":"Point"}
}