{
  "type": "Feature",
  "properties": {
    "iso:country": "GB",
    "wof:name": "CF5 6BP",
    "wof:placetype": "postalcode"
  },
  "geometry": {"coordinates":[-3.275445,51.456512],"type":"Point"}
}
