{
  "type": "Feature",
  "properties": {
    "iso:country":"GB",
    "wof:name":"EX2 5LH",
    "wof:placetype":"postalcode"
},
  "geometry": {"coordinates":[-3.49642252660893,50.71710478578553],"type":"Point"}
}