{
  "type": "Feature",
  "properties": {
    "iso:country":"GB",
    "wof:name":"SN6 7NB",
    "wof:placetype":"postalcode"
},
  "geometry": {"coordinates":[-1.70479887515442,51.63808940391063],"type":"Point"}
}