{
  "type": "Feature",
  "properties": {
    "iso:country": "GB",
    "wof:name": "SN6 7NB",
    "wof:placetype": "postalcode"
  },
  "geometry": {"coordinates":[-1.704799,51.638089],"type":"Point"}
}
