{
  "type": "Feature",
  "properties": {
    "date:inception_lower": "1999-06-01",
    "date:inception_upper": "1999-06-01",
    "iso:country": "GB",
    "wof:name": "PE10 0QJ",
    "wof:placetype": "postalcode"
  },
  "geometry": {"coordinates":[-0.375043,52.739156],"type":"Point"}
}
