{
  "type": "Feature",
  "properties": {
    "iso:country":"GB",
    "wof:name":"PE10 0QJ",
    "wof:placetype":"postalcode"
},
  "geometry": {"coordinates":[-0.37504321019484,52.7391559979318],"type":"Point"}
}