{
  "type": "Feature",
  "properties": {
    "iso:country": "GB",
    "wof:name": "OX12 0FW",
    "wof:placetype": "postalcode"
  },
  "geometry": {"coordinates":[-1.414801,51.632411],"type":"Point"}
}
