{
  "type": "Feature",
  "properties": {
    "iso:country": "GB",
    "wof:name": "NE24 3SJ",
    "wof:placetype": "postalcode"
  },
  "geometry": {"coordinates":[-1.512163,55.113466],"type":"Point"}
}
