{
  "type": "Feature",
  "properties": {
    "iso:country":"GB",
    "wof:name":"RH11 0NY",
    "wof:placetype":"postalcode"
},
  "geometry": {"coordinates":[-0.21085314343588,51.13718038250602],"type":"Point"}
}