{
  "type": "Feature",
  "properties": {
    "date:inception_lower":"1980-01-01",
    "date:inception_upper":"1980-01-31",
    "iso:country":"GB",
    "wof:name":"HX6 3QA",
    "wof:placetype":"postalcode"
},
  "geometry": {"coordinates":[-1.912895,53.702843],"type":"Point"}
}