{
  "type": "Feature",
  "properties": {
    "iso:country":"GB",
    "wof:name":"HX6 3QA",
    "wof:placetype":"postalcode"
},
  "geometry": {"coordinates":[-1.91289461826496,53.70284285227861],"type":"Point"}
}