{
  "type": "Feature",
  "properties": {
    "iso:country":"GB",
    "wof:name":"FK8 3XH",
    "wof:placetype":"postalcode"
},
  "geometry": {"coordinates":[-4.42193664071011,56.15006802586977],"type":"Point"}
}