{
  "type": "Feature",
  "properties": {
    "iso:country":"GB",
    "wof:name":"HA0 1UA",
    "wof:placetype":"postalcode"
},
  "geometry": {"coordinates":[-0.29497966595176,51.54219505984147],"type":"Point"}
}