{
  "type": "Feature",
  "properties": {
    "iso:country":"GB",
    "wof:name":"LL65 1SF",
    "wof:placetype":"postalcode"
},
  "geometry": {"coordinates":[-4.63615684226172,53.30923175380267],"type":"Point"}
}