{
  "type": "Feature",
  "properties": {
    "iso:country":"GB",
    "wof:name":"EH29 9EP",
    "wof:placetype":"postalcode"
},
  "geometry": {"coordinates":[-3.41245791845551,55.9576715470326],"type":"Point"}
}