{
  "type": "Feature",
  "properties": {
    "iso:country":"GB",
    "wof:name":"SE9 4DB",
    "wof:placetype":"postalcode"
},
  "geometry": {"coordinates":[0.0398867272931,51.42711146860714],"type":"Point"}
}