{
  "type": "Feature",
  "properties": {
    "iso:country":"GB",
    "wof:name":"EH26 0AN",
    "wof:placetype":"postalcode"
},
  "geometry": {"coordinates":[-3.23067307889362,55.83438010043778],"type":"Point"}
}