{
  "type": "Feature",
  "properties": {
    "iso:country":"GB",
    "wof:name":"SA33 4BZ",
    "wof:placetype":"postalcode"
},
  "geometry": {"coordinates":[-4.49312568429803,51.82698545076816],"type":"Point"}
}