{
  "type": "Feature",
  "properties": {
    "iso:country": "GB",
    "wof:name": "SA33 4BZ",
    "wof:placetype": "postalcode"
  },
  "geometry": {"coordinates":[-4.493126,51.826985],"type":"Point"}
}
