{
  "type": "Feature",
  "properties": {
    "iso:country": "GB",
    "wof:name": "NG24 3AX",
    "wof:placetype": "postalcode"
  },
  "geometry": {"coordinates":[-0.787945,53.060357],"type":"Point"}
}
