{
  "type": "Feature",
  "properties": {
    "iso:country":"GB",
    "wof:name":"L23 6UW",
    "wof:placetype":"postalcode"
},
  "geometry": {"coordinates":[-3.04839420295359,53.49456462802333],"type":"Point"}
}