{
  "type": "Feature",
  "properties": {
    "iso:country":"GB",
    "wof:name":"SA71 5QQ",
    "wof:placetype":"postalcode"
},
  "geometry": {"coordinates":[-4.91244025403352,51.67038306685913],"type":"Point"}
}