{
  "type": "Feature",
  "properties": {
    "iso:country":"GB",
    "wof:name":"SE22 9NH",
    "wof:placetype":"postalcode"
},
  "geometry": {"coordinates":[-0.07045645961895,51.45522971127431],"type":"Point"}
}