{
  "type": "Feature",
  "properties": {
    "date:inception_lower": "1999-12-01",
    "date:inception_upper": "1999-12-01",
    "iso:country": "GB",
    "wof:name": "SO50 7LU",
    "wof:placetype": "postalcode"
  },
  "geometry": {"coordinates":[-1.291483,50.951473],"type":"Point"}
}
