{
  "type": "Feature",
  "properties": {
    "iso:country":"GB",
    "wof:name":"SO50 7LU",
    "wof:placetype":"postalcode"
},
  "geometry": {"coordinates":[-1.29150852076408,50.95148063682029],"type":"Point"}
}