{
  "type": "Feature",
  "properties": {
    "iso:country": "GB",
    "wof:name": "LL30 1UX",
    "wof:placetype": "postalcode"
  },
  "geometry": {"coordinates":[-3.815655,53.315721],"type":"Point"}
}
