{
  "type": "Feature",
  "properties": {
    "date:inception_lower":"1993-01-01",
    "date:inception_upper":"1993-01-31",
    "iso:country":"GB",
    "wof:name":"LL30 1UX",
    "wof:placetype":"postalcode"
},
  "geometry": {"coordinates":[-3.815655,53.315721],"type":"Point"}
}