{
  "type": "Feature",
  "properties": {
    "iso:country":"GB",
    "wof:name":"LL30 1UX",
    "wof:placetype":"postalcode"
},
  "geometry": {"coordinates":[-3.8156551190592,53.31572112060301],"type":"Point"}
}