{
  "type": "Feature",
  "properties": {
    "iso:country":"GB",
    "wof:name":"IP17 3PP",
    "wof:placetype":"postalcode"
},
  "geometry": {"coordinates":[1.52959324118853,52.27716770521966],"type":"Point"}
}