{
  "type": "Feature",
  "properties": {
    "iso:country":"GB",
    "wof:name":"CF35 5LU",
    "wof:placetype":"postalcode"
},
  "geometry": {"coordinates":[-3.50281565252379,51.51808398542268],"type":"Point"}
}