{
  "type": "Feature",
  "properties": {
    "iso:country": "GB",
    "wof:name": "CF35 5LU",
    "wof:placetype": "postalcode"
  },
  "geometry": {"coordinates":[-3.502816,51.518084],"type":"Point"}
}
