{
  "type": "Feature",
  "properties": {
    "iso:country":"GB",
    "wof:name":"B20 2FE",
    "wof:placetype":"postalcode"
},
  "geometry": {"coordinates":[-1.92991033530708,52.51000399459573],"type":"Point"}
}