{
  "type": "Feature",
  "properties": {
    "iso:country":"GB",
    "wof:name":"IG10 3SY",
    "wof:placetype":"postalcode"
},
  "geometry": {"coordinates":[0.08382156031649,51.64750613581887],"type":"Point"}
}