{
  "type": "Feature",
  "properties": {
    "iso:country": "GB",
    "wof:name": "IG10 3SY",
    "wof:placetype": "postalcode"
  },
  "geometry": {"coordinates":[0.083822,51.647506],"type":"Point"}
}
