{
  "type": "Feature",
  "properties": {
    "iso:country":"GB",
    "wof:name":"TN25 6EJ",
    "wof:placetype":"postalcode"
},
  "geometry": {"coordinates":[0.98864680157816,51.10855603745934],"type":"Point"}
}