{
  "type": "Feature",
  "properties": {
    "iso:country": "GB",
    "wof:name": "TN25 6EJ",
    "wof:placetype": "postalcode"
  },
  "geometry": {"coordinates":[0.988647,51.108556],"type":"Point"}
}
