{
  "type": "Feature",
  "properties": {
    "iso:country":"GB",
    "wof:name":"FK15 0BN",
    "wof:placetype":"postalcode"
},
  "geometry": {"coordinates":[-3.95986210809333,56.19284314464413],"type":"Point"}
}