{
  "type": "Feature",
  "properties": {
    "date:inception_lower": "1980-01-01",
    "date:inception_upper": "1980-01-01",
    "iso:country": "GB",
    "wof:name": "SA2 8JJ",
    "wof:placetype": "postalcode"
  },
  "geometry": {"coordinates":[-3.999939,51.616076],"type":"Point"}
}
