{
  "type": "Feature",
  "properties": {
    "iso:country": "GB",
    "wof:name": "HP22 5PE",
    "wof:placetype": "postalcode"
  },
  "geometry": {"coordinates":[-0.735954,51.781487],"type":"Point"}
}
