{
  "type": "Feature",
  "properties": {
    "iso:country":"GB",
    "wof:name":"HP22 5PE",
    "wof:placetype":"postalcode"
},
  "geometry": {"coordinates":[-0.73595372601492,51.78148675761292],"type":"Point"}
}