{
  "type": "Feature",
  "properties": {
    "date:inception_lower": "2022-07-01",
    "date:inception_upper": "2022-07-01",
    "iso:country": "GB",
    "wof:name": "HP23 4FQ",
    "wof:placetype": "postalcode"
  },
  "geometry": {"coordinates":[-0.681796,51.791024],"type":"Point"}
}
