{
  "type": "Feature",
  "properties": {
    "iso:country": "GB",
    "wof:name": "IG10 1LX",
    "wof:placetype": "postalcode"
  },
  "geometry": {"coordinates":[0.066496,51.656583],"type":"Point"}
}
