{
  "type": "Feature",
  "properties": {
    "date:inception_lower":"2004-07-01",
    "date:inception_upper":"2004-07-31",
    "iso:country":"GB",
    "wof:name":"IG10 1LX",
    "wof:placetype":"postalcode"
},
  "geometry": {"coordinates":[0.066398,51.656609],"type":"Point"}
}