{
  "type": "Feature",
  "properties": {
    "iso:country":"GB",
    "wof:name":"NG13 9AN",
    "wof:placetype":"postalcode"
},
  "geometry": {"coordinates":[-0.8967308977624,52.95436720918586],"type":"Point"}
}