{
  "type": "Feature",
  "properties": {
    "date:inception_lower": "1998-06-01",
    "date:inception_upper": "1998-06-01",
    "iso:country": "GB",
    "wof:name": "LE9 7BT",
    "wof:placetype": "postalcode"
  },
  "geometry": {"coordinates":[-1.303948,52.577688],"type":"Point"}
}
