{
  "type": "Feature",
  "properties": {
    "iso:country":"GB",
    "wof:name":"LE9 7BT",
    "wof:placetype":"postalcode"
},
  "geometry": {"coordinates":[-1.30394759774812,52.5776879525259],"type":"Point"}
}