{
  "type": "Feature",
  "properties": {
    "iso:country":"GB",
    "wof:name":"BD7 4AL",
    "wof:placetype":"postalcode"
},
  "geometry": {"coordinates":[-1.80395017339509,53.77534686120761],"type":"Point"}
}