{
  "type": "Feature",
  "properties": {
    "date:inception_lower":"1986-07-01",
    "date:inception_upper":"1986-07-31",
    "iso:country":"GB",
    "wof:name":"LE10 1UW",
    "wof:placetype":"postalcode"
},
  "geometry": {"coordinates":[-1.370772,52.556773],"type":"Point"}
}