{
  "type": "Feature",
  "properties": {
    "iso:country":"GB",
    "wof:name":"LE10 1UW",
    "wof:placetype":"postalcode"
},
  "geometry": {"coordinates":[-1.37077169872477,52.55677348802251],"type":"Point"}
}