{
  "type": "Feature",
  "properties": {
    "iso:country":"GB",
    "wof:name":"NG11 8DJ",
    "wof:placetype":"postalcode"
},
  "geometry": {"coordinates":[-1.17997260236773,52.90687431517281],"type":"Point"}
}