{
  "type": "Feature",
  "properties": {
    "iso:country":"GB",
    "wof:name":"SR4 0PY",
    "wof:placetype":"postalcode"
},
  "geometry": {"coordinates":[-1.45128417559042,54.90536349908228],"type":"Point"}
}