{
  "type": "Feature",
  "properties": {
    "iso:country":"GB",
    "wof:name":"NN8 3JZ",
    "wof:placetype":"postalcode"
},
  "geometry": {"coordinates":[-0.71317328778755,52.29862822234347],"type":"Point"}
}