{
  "type": "Feature",
  "properties": {
    "iso:country":"GB",
    "wof:name":"CV2 2HZ",
    "wof:placetype":"postalcode"
},
  "geometry": {"coordinates":[-1.4420331072716,52.41555517237797],"type":"Point"}
}