{
  "type": "Feature",
  "properties": {
    "iso:country":"GB",
    "wof:name":"M4 5WD",
    "wof:placetype":"postalcode"
},
  "geometry": {"coordinates":[-2.23229897863746,53.48615679142533],"type":"Point"}
}