{
  "type": "Feature",
  "properties": {
    "date:inception_lower": "1980-01-01",
    "date:inception_upper": "1980-01-01",
    "iso:country": "GB",
    "wof:name": "PA20 9JS",
    "wof:placetype": "postalcode"
  },
  "geometry": {"coordinates":[-5.039517,55.843097],"type":"Point"}
}
