{
  "type": "Feature",
  "properties": {
    "iso:country":"GB",
    "wof:name":"PA20 9JS",
    "wof:placetype":"postalcode"
},
  "geometry": {"coordinates":[-5.03953415885585,55.84303073799585],"type":"Point"}
}