{
  "type": "Feature",
  "properties": {
    "iso:country":"GB",
    "wof:name":"KT19 0EJ",
    "wof:placetype":"postalcode"
},
  "geometry": {"coordinates":[-0.26339786196618,51.36202658912504],"type":"Point"}
}