{
  "type": "Feature",
  "properties": {
    "iso:country":"GB",
    "wof:name":"ML1 5BX",
    "wof:placetype":"postalcode"
},
  "geometry": {"coordinates":[-3.95156746863398,55.81573392067256],"type":"Point"}
}