{
  "type": "Feature",
  "properties": {
    "iso:country":"GB",
    "wof:name":"BS4 4AW",
    "wof:placetype":"postalcode"
},
  "geometry": {"coordinates":[-2.54385751410555,51.45279279138774],"type":"Point"}
}