{
  "type": "Feature",
  "properties": {
    "iso:country":"GB",
    "wof:name":"DT4 7SZ",
    "wof:placetype":"postalcode"
},
  "geometry": {"coordinates":[-2.45065013358577,50.62018328349092],"type":"Point"}
}