{
  "type": "Feature",
  "properties": {
    "date:inception_lower": "2007-11-01",
    "date:inception_upper": "2007-11-01",
    "iso:country": "GB",
    "wof:name": "NG13 8YJ",
    "wof:placetype": "postalcode"
  },
  "geometry": {"coordinates":[-0.961393,52.946284],"type":"Point"}
}
