{
  "type": "Feature",
  "properties": {
    "iso:country":"GB",
    "wof:name":"ST16 3HB",
    "wof:placetype":"postalcode"
},
  "geometry": {"coordinates":[-2.11575004342691,52.81643500474527],"type":"Point"}
}