{
  "type": "Feature",
  "properties": {
    "iso:country":"GB",
    "wof:name":"CH45 3LF",
    "wof:placetype":"postalcode"
},
  "geometry": {"coordinates":[-3.06588558367183,53.424449130215],"type":"Point"}
}