{
  "type": "Feature",
  "properties": {
    "iso:country":"GB",
    "wof:name":"G41 1AJ",
    "wof:placetype":"postalcode"
},
  "geometry": {"coordinates":[-4.26534148056125,55.84211433082152],"type":"Point"}
}