{
  "type": "Feature",
  "properties": {
    "date:inception_lower": "2003-10-01",
    "date:inception_upper": "2003-10-01",
    "iso:country": "GB",
    "wof:name": "BA11 3NF",
    "wof:placetype": "postalcode"
  },
  "geometry": {"coordinates":[-2.33754,51.235672],"type":"Point"}
}
