{
  "type": "Feature",
  "properties": {
    "iso:country":"GB",
    "wof:name":"CH48 1PH",
    "wof:placetype":"postalcode"
},
  "geometry": {"coordinates":[-3.13544750098576,53.37209378545256],"type":"Point"}
}