{
  "type": "Feature",
  "properties": {
    "date:inception_lower": "1980-01-01",
    "date:inception_upper": "1980-01-01",
    "iso:country": "GB",
    "wof:name": "DH9 6LG",
    "wof:placetype": "postalcode"
  },
  "geometry": {"coordinates":[-1.695337,54.862483],"type":"Point"}
}
