{
  "type": "Feature",
  "properties": {
    "iso:country":"GB",
    "wof:name":"DH9 6LG",
    "wof:placetype":"postalcode"
},
  "geometry": {"coordinates":[-1.69533697516071,54.86248319589011],"type":"Point"}
}