{
  "type": "Feature",
  "properties": {
    "iso:country": "GB",
    "wof:name": "DH9 6LG",
    "wof:placetype": "postalcode"
  },
  "geometry": {"coordinates":[-1.695337,54.862483],"type":"Point"}
}
