{
  "type": "Feature",
  "properties": {
    "iso:country": "GB",
    "wof:name": "TW7 4BX",
    "wof:placetype": "postalcode"
  },
  "geometry": {"coordinates":[-0.337878,51.474982],"type":"Point"}
}
