{
  "type": "Feature",
  "properties": {
    "iso:country": "GB",
    "wof:name": "G33 4SP",
    "wof:placetype": "postalcode"
  },
  "geometry": {"coordinates":[-4.132301,55.856271],"type":"Point"}
}
