{
  "type": "Feature",
  "properties": {
    "iso:country":"GB",
    "wof:name":"BS31 1BZ",
    "wof:placetype":"postalcode"
},
  "geometry": {"coordinates":[-2.49851032021737,51.41185769200668],"type":"Point"}
}