{
  "type": "Feature",
  "properties": {
    "date:inception_lower":"1997-12-01",
    "date:inception_upper":"1997-12-31",
    "iso:country":"GB",
    "wof:name":"BS31 1BZ",
    "wof:placetype":"postalcode"
},
  "geometry": {"coordinates":[-2.49851,51.411858],"type":"Point"}
}