{
  "type": "Feature",
  "properties": {
    "iso:country": "GB",
    "wof:name": "CO2 7HY",
    "wof:placetype": "postalcode"
  },
  "geometry": {"coordinates":[0.888041,51.87727],"type":"Point"}
}
