{
  "type": "Feature",
  "properties": {
    "date:inception_lower":"2014-05-01",
    "date:inception_upper":"2014-05-31",
    "iso:country":"GB",
    "wof:name":"CO2 7HY",
    "wof:placetype":"postalcode"
},
  "geometry": {"coordinates":[0.888041,51.87727],"type":"Point"}
}