{
  "type": "Feature",
  "properties": {
    "iso:country":"GB",
    "wof:name":"LE67 4DB",
    "wof:placetype":"postalcode"
},
  "geometry": {"coordinates":[-1.35083403564469,52.72225022597409],"type":"Point"}
}