{
  "type": "Feature",
  "properties": {
    "iso:country":"GB",
    "wof:name":"SW8 1DR",
    "wof:placetype":"postalcode"
},
  "geometry": {"coordinates":[-0.12018348900963,51.47913960963911],"type":"Point"}
}