{
  "type": "Feature",
  "properties": {
    "date:inception_lower": "1992-08-01",
    "date:inception_upper": "1992-08-01",
    "iso:country": "GB",
    "wof:name": "LE65 2TA",
    "wof:placetype": "postalcode"
  },
  "geometry": {"coordinates":[-1.49168,52.766258],"type":"Point"}
}
