{
  "type": "Feature",
  "properties": {
    "iso:country": "GB",
    "wof:name": "LE65 2TA",
    "wof:placetype": "postalcode"
  },
  "geometry": {"coordinates":[-1.49168,52.766258],"type":"Point"}
}
