{
  "type": "Feature",
  "properties": {
    "iso:country": "GB",
    "wof:name": "L21 9NY",
    "wof:placetype": "postalcode"
  },
  "geometry": {"coordinates":[-3.003069,53.478675],"type":"Point"}
}
