{
  "type": "Feature",
  "properties": {
    "iso:country":"GB",
    "wof:name":"L21 9NY",
    "wof:placetype":"postalcode"
},
  "geometry": {"coordinates":[-3.00306878560344,53.47867493871889],"type":"Point"}
}