{
  "type": "Feature",
  "properties": {
    "iso:country":"GB",
    "wof:name":"LS6 1PB",
    "wof:placetype":"postalcode"
},
  "geometry": {"coordinates":[-1.56946158425693,53.80893417323999],"type":"Point"}
}