{
  "type": "Feature",
  "properties": {
    "iso:country": "GB",
    "wof:name": "SY21 7LJ",
    "wof:placetype": "postalcode"
  },
  "geometry": {"coordinates":[-3.152098,52.660958],"type":"Point"}
}
