{
  "type": "Feature",
  "properties": {
    "iso:country":"GB",
    "wof:name":"EX9 6AG",
    "wof:placetype":"postalcode"
},
  "geometry": {"coordinates":[-3.34406318866082,50.63113350046424],"type":"Point"}
}