{
  "type": "Feature",
  "properties": {
    "iso:country": "GB",
    "wof:name": "HD9 7SW",
    "wof:placetype": "postalcode"
  },
  "geometry": {"coordinates":[-1.773496,53.586279],"type":"Point"}
}
