{
  "type": "Feature",
  "properties": {
    "iso:country":"GB",
    "wof:name":"CF31 3PF",
    "wof:placetype":"postalcode"
},
  "geometry": {"coordinates":[-3.58331950201103,51.50000240776474],"type":"Point"}
}