{
  "type": "Feature",
  "properties": {
    "date:inception_lower": "1980-01-01",
    "date:inception_upper": "1980-01-01",
    "iso:country": "GB",
    "wof:name": "NE68 7TN",
    "wof:placetype": "postalcode"
  },
  "geometry": {"coordinates":[-1.655583,55.580131],"type":"Point"}
}
