{
  "type": "Feature",
  "properties": {
    "iso:country":"GB",
    "wof:name":"NE68 7TN",
    "wof:placetype":"postalcode"
},
  "geometry": {"coordinates":[-1.6556579996369,55.58014261566655],"type":"Point"}
}