{
  "type": "Feature",
  "properties": {
    "iso:country": "GB",
    "wof:name": "BA20 2LW",
    "wof:placetype": "postalcode"
  },
  "geometry": {"coordinates":[-2.645995,50.929027],"type":"Point"}
}
