{
  "type": "Feature",
  "properties": {
    "iso:country":"GB",
    "wof:name":"BA20 2LW",
    "wof:placetype":"postalcode"
},
  "geometry": {"coordinates":[-2.64589515892409,50.92907162849008],"type":"Point"}
}