{
  "type": "Feature",
  "properties": {
    "date:inception_lower": "1980-01-01",
    "date:inception_upper": "1980-01-01",
    "iso:country": "GB",
    "wof:name": "DL10 6PY",
    "wof:placetype": "postalcode"
  },
  "geometry": {"coordinates":[-1.653619,54.446385],"type":"Point"}
}
