{
  "type": "Feature",
  "properties": {
    "iso:country":"GB",
    "wof:name":"DL10 6PY",
    "wof:placetype":"postalcode"
},
  "geometry": {"coordinates":[-1.65361855992569,54.44638503454971],"type":"Point"}
}