{
  "type": "Feature",
  "properties": {
    "iso:country": "GB",
    "wof:name": "NR10 4EH",
    "wof:placetype": "postalcode"
  },
  "geometry": {"coordinates":[1.112301,52.763078],"type":"Point"}
}
