{
  "type": "Feature",
  "properties": {
    "date:inception_lower":"1996-12-01",
    "date:inception_upper":"1996-12-31",
    "iso:country":"GB",
    "wof:name":"NR10 4EH",
    "wof:placetype":"postalcode"
},
  "geometry": {"coordinates":[1.112301,52.763078],"type":"Point"}
}