{
  "type": "Feature",
  "properties": {
    "date:inception_lower":"2017-05-01",
    "date:inception_upper":"2017-05-31",
    "iso:country":"GB",
    "wof:name":"PR5 6QH",
    "wof:placetype":"postalcode"
},
  "geometry": {"coordinates":[-2.660795,53.736067],"type":"Point"}
}