{
  "type": "Feature",
  "properties": {
    "iso:country": "GB",
    "wof:name": "PR5 6QH",
    "wof:placetype": "postalcode"
  },
  "geometry": {"coordinates":[-2.660795,53.736067],"type":"Point"}
}
