{
  "type": "Feature",
  "properties": {
    "iso:country": "GB",
    "wof:name": "ME19 6FY",
    "wof:placetype": "postalcode"
  },
  "geometry": {"coordinates":[0.43415,51.296186],"type":"Point"}
}
