{
  "type": "Feature",
  "properties": {
    "iso:country":"GB",
    "wof:name":"ME19 6FY",
    "wof:placetype":"postalcode"
},
  "geometry": {"coordinates":[0.43414978792757,51.29618555509163],"type":"Point"}
}