{
  "type": "Feature",
  "properties": {
    "date:inception_lower": "1980-01-01",
    "date:inception_upper": "1980-01-01",
    "iso:country": "GB",
    "wof:name": "SA31 3HW",
    "wof:placetype": "postalcode"
  },
  "geometry": {"coordinates":[-4.332073,51.851145],"type":"Point"}
}
