{
  "type": "Feature",
  "properties": {
    "iso:country": "GB",
    "wof:name": "SA31 3HW",
    "wof:placetype": "postalcode"
  },
  "geometry": {"coordinates":[-4.332073,51.851145],"type":"Point"}
}
