{
  "type": "Feature",
  "properties": {
    "date:inception_lower": "1980-01-01",
    "date:inception_upper": "1980-01-01",
    "iso:country": "GB",
    "wof:name": "FK14 7HB",
    "wof:placetype": "postalcode"
  },
  "geometry": {"coordinates":[-3.67693,56.163281],"type":"Point"}
}
