{
  "type": "Feature",
  "properties": {
    "iso:country":"GB",
    "wof:name":"SS16 4JE",
    "wof:placetype":"postalcode"
},
  "geometry": {"coordinates":[0.48547253878432,51.56299491057632],"type":"Point"}
}