{
  "type": "Feature",
  "properties": {
    "date:inception_lower": "2023-05-01",
    "date:inception_upper": "2023-05-01",
    "iso:country": "GB",
    "wof:name": "LS29 6SQ",
    "wof:placetype": "postalcode"
  },
  "geometry": {"coordinates":[-1.751029,53.890498],"type":"Point"}
}
