{
  "type": "Feature",
  "properties": {
    "date:inception_lower": "1980-01-01",
    "date:inception_upper": "1980-01-01",
    "iso:country": "GB",
    "wof:name": "DN14 8NY",
    "wof:placetype": "postalcode"
  },
  "geometry": {"coordinates":[-0.94802,53.684417],"type":"Point"}
}
