{
  "type": "Feature",
  "properties": {
    "iso:country": "GB",
    "wof:name": "DN14 8NY",
    "wof:placetype": "postalcode"
  },
  "geometry": {"coordinates":[-0.94802,53.684417],"type":"Point"}
}
