{
  "type": "Feature",
  "properties": {
    "iso:country": "GB",
    "wof:name": "SN10 5PP",
    "wof:placetype": "postalcode"
  },
  "geometry": {"coordinates":[-2.016813,51.323558],"type":"Point"}
}
