{
  "type": "Feature",
  "properties": {
    "date:inception_lower": "1980-01-01",
    "date:inception_upper": "1980-01-01",
    "iso:country": "GB",
    "wof:name": "BD11 1LR",
    "wof:placetype": "postalcode"
  },
  "geometry": {"coordinates":[-1.658144,53.758887],"type":"Point"}
}
