{
  "type": "Feature",
  "properties": {
    "iso:country": "GB",
    "wof:name": "BD11 1LR",
    "wof:placetype": "postalcode"
  },
  "geometry": {"coordinates":[-1.658144,53.758887],"type":"Point"}
}
