{
  "type": "Feature",
  "properties": {
    "date:inception_lower":"2014-04-01",
    "date:inception_upper":"2014-04-30",
    "iso:country":"GB",
    "wof:name":"KT20 6BF",
    "wof:placetype":"postalcode"
},
  "geometry": {"coordinates":[-0.220663,51.299372],"type":"Point"}
}