{
  "type": "Feature",
  "properties": {
    "iso:country":"GB",
    "wof:name":"PO20 9AQ",
    "wof:placetype":"postalcode"
},
  "geometry": {"coordinates":[-0.80218589839689,50.7308765483444],"type":"Point"}
}