{
  "type": "Feature",
  "properties": {
    "iso:country": "GB",
    "wof:name": "NG19 0EF",
    "wof:placetype": "postalcode"
  },
  "geometry": {"coordinates":[-1.167167,53.150937],"type":"Point"}
}
