{
  "type": "Feature",
  "properties": {
    "iso:country":"GB",
    "wof:name":"NG19 0EF",
    "wof:placetype":"postalcode"
},
  "geometry": {"coordinates":[-1.16716729641428,53.15093688148821],"type":"Point"}
}