{
  "type": "Feature",
  "properties": {
    "iso:country": "GB",
    "wof:name": "MK43 8QX",
    "wof:placetype": "postalcode"
  },
  "geometry": {"coordinates":[-0.532981,52.141926],"type":"Point"}
}
