{
  "type": "Feature",
  "properties": {
    "iso:country":"GB",
    "wof:name":"WN8 6RH",
    "wof:placetype":"postalcode"
},
  "geometry": {"coordinates":[-2.77042368104404,53.55796443863707],"type":"Point"}
}