{
  "type": "Feature",
  "properties": {
    "iso:country": "GB",
    "wof:name": "L30 1RW",
    "wof:placetype": "postalcode"
  },
  "geometry": {"coordinates":[-2.964821,53.479817],"type":"Point"}
}
