{
  "type": "Feature",
  "properties": {
    "iso:country": "GB",
    "wof:name": "W9 3PE",
    "wof:placetype": "postalcode"
  },
  "geometry": {"coordinates":[-0.200152,51.525249],"type":"Point"}
}
