{
  "type": "Feature",
  "properties": {
    "date:inception_lower": "1980-01-01",
    "date:inception_upper": "1980-01-01",
    "iso:country": "GB",
    "wof:name": "LS20 8HS",
    "wof:placetype": "postalcode"
  },
  "geometry": {"coordinates":[-1.723787,53.870818],"type":"Point"}
}
