{
  "type": "Feature",
  "properties": {
    "iso:country": "GB",
    "wof:name": "EH28 8RE",
    "wof:placetype": "postalcode"
  },
  "geometry": {"coordinates":[-3.379119,55.92101],"type":"Point"}
}
