{
  "type": "Feature",
  "properties": {
    "iso:country":"GB",
    "wof:name":"EH28 8RE",
    "wof:placetype":"postalcode"
},
  "geometry": {"coordinates":[-3.37911884162785,55.92101003024965],"type":"Point"}
}