{
  "type": "Feature",
  "properties": {
    "iso:country": "GB",
    "wof:name": "TN21 8HD",
    "wof:placetype": "postalcode"
  },
  "geometry": {"coordinates":[0.255001,50.969451],"type":"Point"}
}
