{
  "type": "Feature",
  "properties": {
    "date:inception_lower":"1980-01-01",
    "date:inception_upper":"1980-01-31",
    "iso:country":"GB",
    "wof:name":"TN21 8HD",
    "wof:placetype":"postalcode"
},
  "geometry": {"coordinates":[0.255001,50.969451],"type":"Point"}
}