{
  "type": "Feature",
  "properties": {
    "iso:country":"GB",
    "wof:name":"TN21 8HD",
    "wof:placetype":"postalcode"
},
  "geometry": {"coordinates":[0.25500056780135,50.96945139648735],"type":"Point"}
}