{
  "type": "Feature",
  "properties": {
    "iso:country":"GB",
    "wof:name":"NN15 7ND",
    "wof:placetype":"postalcode"
},
  "geometry": {"coordinates":[-0.71623687770665,52.39396332307717],"type":"Point"}
}