{
  "type": "Feature",
  "properties": {
    "iso:country": "GB",
    "wof:name": "NN15 7ND",
    "wof:placetype": "postalcode"
  },
  "geometry": {"coordinates":[-0.716237,52.393963],"type":"Point"}
}
