{
  "type": "Feature",
  "properties": {
    "iso:country":"GB",
    "wof:name":"B90 4ND",
    "wof:placetype":"postalcode"
},
  "geometry": {"coordinates":[-1.80359535975957,52.39721721379649],"type":"Point"}
}