{
  "type": "Feature",
  "properties": {
    "iso:country": "GB",
    "wof:name": "B90 4ND",
    "wof:placetype": "postalcode"
  },
  "geometry": {"coordinates":[-1.804344,52.397488],"type":"Point"}
}
