{
  "type": "Feature",
  "properties": {
    "iso:country":"GB",
    "wof:name":"UB6 9QG",
    "wof:placetype":"postalcode"
},
  "geometry": {"coordinates":[-0.36153834147721,51.52876484271664],"type":"Point"}
}