{
  "type": "Feature",
  "properties": {
    "iso:country":"GB",
    "wof:name":"PH2 6HX",
    "wof:placetype":"postalcode"
},
  "geometry": {"coordinates":[-3.31395489120601,56.48182008480225],"type":"Point"}
}