{
  "type": "Feature",
  "properties": {
    "iso:country": "GB",
    "wof:name": "PH2 6HX",
    "wof:placetype": "postalcode"
  },
  "geometry": {"coordinates":[-3.308939,56.478557],"type":"Point"}
}
