{
  "type": "Feature",
  "properties": {
    "iso:country": "GB",
    "wof:name": "LE1 5WN",
    "wof:placetype": "postalcode"
  },
  "geometry": {"coordinates":[-1.140666,52.633181],"type":"Point"}
}
