{
  "type": "Feature",
  "properties": {
    "iso:country":"GB",
    "wof:name":"LE1 5WN",
    "wof:placetype":"postalcode"
},
  "geometry": {"coordinates":[-1.14066649625474,52.63318127197562],"type":"Point"}
}