{
  "type": "Feature",
  "properties": {
    "iso:country":"GB",
    "wof:name":"SS9 2XG",
    "wof:placetype":"postalcode"
},
  "geometry": {"coordinates":[0.62978349716593,51.54480198666397],"type":"Point"}
}