{
  "type": "Feature",
  "properties": {
    "iso:country":"GB",
    "wof:name":"PO19 6DW",
    "wof:placetype":"postalcode"
},
  "geometry": {"coordinates":[-0.77898067126466,50.84889345430356],"type":"Point"}
}