{
  "type": "Feature",
  "properties": {
    "date:inception_lower":"2015-02-01",
    "date:inception_upper":"2015-02-28",
    "iso:country":"GB",
    "wof:name":"PO19 6DW",
    "wof:placetype":"postalcode"
},
  "geometry": {"coordinates":[-0.779118,50.848886],"type":"Point"}
}