{
  "type": "Feature",
  "properties": {
    "iso:country": "GB",
    "wof:name": "PO19 6DW",
    "wof:placetype": "postalcode"
  },
  "geometry": {"coordinates":[-0.779118,50.848886],"type":"Point"}
}
