{
  "type": "Feature",
  "properties": {
    "date:inception_lower":"1980-01-01",
    "date:inception_upper":"1980-01-31",
    "iso:country":"GB",
    "wof:name":"OL14 8RR",
    "wof:placetype":"postalcode"
},
  "geometry": {"coordinates":[-2.061178,53.73686],"type":"Point"}
}