{
  "type": "Feature",
  "properties": {
    "iso:country":"GB",
    "wof:name":"E3 2ZD",
    "wof:placetype":"postalcode"
},
  "geometry": {"coordinates":[-0.01933311805175,51.53124649134682],"type":"Point"}
}