{
  "type": "Feature",
  "properties": {
    "date:inception_lower":"1998-06-01",
    "date:inception_upper":"1998-06-30",
    "iso:country":"GB",
    "wof:name":"YO32 2FG",
    "wof:placetype":"postalcode"
},
  "geometry": {"coordinates":[-1.079881,54.015926],"type":"Point"}
}