{
  "type": "Feature",
  "properties": {
    "iso:country":"GB",
    "wof:name":"YO32 2FG",
    "wof:placetype":"postalcode"
},
  "geometry": {"coordinates":[-1.0798810206012,54.01592585492256],"type":"Point"}
}