{
  "type": "Feature",
  "properties": {
    "iso:country":"GB",
    "wof:name":"DH9 8JY",
    "wof:placetype":"postalcode"
},
  "geometry": {"coordinates":[-1.74090037176814,54.86088142355566],"type":"Point"}
}