{
  "type": "Feature",
  "properties": {
    "iso:country": "GB",
    "wof:name": "SY12 0AR",
    "wof:placetype": "postalcode"
  },
  "geometry": {"coordinates":[-2.893293,52.907697],"type":"Point"}
}
