{
  "type": "Feature",
  "properties": {
    "iso:country":"GB",
    "wof:name":"HR4 8DB",
    "wof:placetype":"postalcode"
},
  "geometry": {"coordinates":[-2.72729577901079,52.10734657453538],"type":"Point"}
}