{
  "type": "Feature",
  "properties": {
    "iso:country": "GB",
    "wof:name": "HR4 8DB",
    "wof:placetype": "postalcode"
  },
  "geometry": {"coordinates":[-2.727296,52.107347],"type":"Point"}
}
