{
  "type": "Feature",
  "properties": {
    "iso:country": "GB",
    "wof:name": "PH2 0NP",
    "wof:placetype": "postalcode"
  },
  "geometry": {"coordinates":[-3.437345,56.383827],"type":"Point"}
}
