{
  "type": "Feature",
  "properties": {
    "iso:country":"GB",
    "wof:name":"PH2 0NP",
    "wof:placetype":"postalcode"
},
  "geometry": {"coordinates":[-3.43734520560038,56.3838266279563],"type":"Point"}
}