{
  "type": "Feature",
  "properties": {
    "iso:country": "GB",
    "wof:name": "L11 4RG",
    "wof:placetype": "postalcode"
  },
  "geometry": {"coordinates":[-2.902256,53.451371],"type":"Point"}
}
