{
  "type": "Feature",
  "properties": {
    "iso:country":"GB",
    "wof:name":"IV1 1JT",
    "wof:placetype":"postalcode"
},
  "geometry": {"coordinates":[-4.22481697492256,57.47967207798023],"type":"Point"}
}