{
  "type": "Feature",
  "properties": {
    "date:inception_lower": "1980-01-01",
    "date:inception_upper": "1980-01-01",
    "iso:country": "GB",
    "wof:name": "GL54 1LR",
    "wof:placetype": "postalcode"
  },
  "geometry": {"coordinates":[-1.719634,51.926801],"type":"Point"}
}
