{
  "type": "Feature",
  "properties": {
    "iso:country": "GB",
    "wof:name": "GL54 1LR",
    "wof:placetype": "postalcode"
  },
  "geometry": {"coordinates":[-1.719634,51.926801],"type":"Point"}
}
