{
  "type": "Feature",
  "properties": {
    "date:inception_lower": "2001-12-01",
    "date:inception_upper": "2001-12-01",
    "iso:country": "GB",
    "wof:name": "LN4 2DG",
    "wof:placetype": "postalcode"
  },
  "geometry": {"coordinates":[-0.529821,53.18771],"type":"Point"}
}
