{
  "type": "Feature",
  "properties": {
    "iso:country":"GB",
    "wof:name":"CH7 6DJ",
    "wof:placetype":"postalcode"
},
  "geometry": {"coordinates":[-3.13491845259268,53.20617566489567],"type":"Point"}
}