{
  "type": "Feature",
  "properties": {
    "iso:country": "GB",
    "wof:name": "CH7 6DJ",
    "wof:placetype": "postalcode"
  },
  "geometry": {"coordinates":[-3.134918,53.206176],"type":"Point"}
}
