{
  "type": "Feature",
  "properties": {
    "date:inception_lower":"1999-12-01",
    "date:inception_upper":"1999-12-31",
    "iso:country":"GB",
    "wof:name":"CH7 6DJ",
    "wof:placetype":"postalcode"
},
  "geometry": {"coordinates":[-3.134918,53.206176],"type":"Point"}
}