{
  "type": "Feature",
  "properties": {
    "iso:country":"GB",
    "wof:name":"W10 5SH",
    "wof:placetype":"postalcode"
},
  "geometry": {"coordinates":[-0.21179214734694,51.5221445114034],"type":"Point"}
}