{
  "type": "Feature",
  "properties": {
    "date:inception_lower": "2021-06-01",
    "date:inception_upper": "2021-06-01",
    "iso:country": "GB",
    "wof:name": "DN15 7ND",
    "wof:placetype": "postalcode"
  },
  "geometry": {"coordinates":[-0.655823,53.595571],"type":"Point"}
}
