{
  "type": "Feature",
  "properties": {
    "iso:country": "GB",
    "wof:name": "SN10 5TW",
    "wof:placetype": "postalcode"
  },
  "geometry": {"coordinates":[-2.036799,51.282219],"type":"Point"}
}
