{
  "type": "Feature",
  "properties": {
    "date:inception_lower": "1987-04-01",
    "date:inception_upper": "1987-04-01",
    "iso:country": "GB",
    "wof:name": "LE10 0YH",
    "wof:placetype": "postalcode"
  },
  "geometry": {"coordinates":[-1.40209,52.542345],"type":"Point"}
}
