{
  "type": "Feature",
  "properties": {
    "iso:country":"GB",
    "wof:name":"LE10 0YH",
    "wof:placetype":"postalcode"
},
  "geometry": {"coordinates":[-1.40209024989488,52.54234498375],"type":"Point"}
}