{
  "type": "Feature",
  "properties": {
    "iso:country": "GB",
    "wof:name": "GU9 9QT",
    "wof:placetype": "postalcode"
  },
  "geometry": {"coordinates":[-0.785835,51.221942],"type":"Point"}
}
