{
  "type": "Feature",
  "properties": {
    "iso:country":"GB",
    "wof:name":"GU9 9QT",
    "wof:placetype":"postalcode"
},
  "geometry": {"coordinates":[-0.78583514069213,51.22194212245083],"type":"Point"}
}