{
  "type": "Feature",
  "properties": {
    "iso:country":"GB",
    "wof:name":"HU5 5UL",
    "wof:placetype":"postalcode"
},
  "geometry": {"coordinates":[-0.39774000911531,53.75288334484014],"type":"Point"}
}