{
  "type": "Feature",
  "properties": {
    "date:inception_lower": "1980-01-01",
    "date:inception_upper": "1980-01-01",
    "iso:country": "GB",
    "wof:name": "HU5 5UL",
    "wof:placetype": "postalcode"
  },
  "geometry": {"coordinates":[-0.39774,53.752883],"type":"Point"}
}
