{
  "type": "Feature",
  "properties": {
    "iso:country": "GB",
    "wof:name": "HU5 5UL",
    "wof:placetype": "postalcode"
  },
  "geometry": {"coordinates":[-0.39774,53.752883],"type":"Point"}
}
