{
  "type": "Feature",
  "properties": {
    "iso:country":"GB",
    "wof:name":"RG5 4DJ",
    "wof:placetype":"postalcode"
},
  "geometry": {"coordinates":[-0.897006899248,51.44123548289602],"type":"Point"}
}