{
  "type": "Feature",
  "properties": {
    "iso:country":"GB",
    "wof:name":"KY1 2UD",
    "wof:placetype":"postalcode"
},
  "geometry": {"coordinates":[-3.12200648844556,56.12605946583518],"type":"Point"}
}