{
  "type": "Feature",
  "properties": {
    "iso:country": "GB",
    "wof:name": "KY1 2UD",
    "wof:placetype": "postalcode"
  },
  "geometry": {"coordinates":[-3.122006,56.126059],"type":"Point"}
}
