{
  "type": "Feature",
  "properties": {
    "date:inception_lower":"1980-01-01",
    "date:inception_upper":"1980-01-31",
    "iso:country":"GB",
    "wof:name":"KY1 2UD",
    "wof:placetype":"postalcode"
},
  "geometry": {"coordinates":[-3.122006,56.126059],"type":"Point"}
}