{
  "type": "Feature",
  "properties": {
    "iso:country":"GB",
    "wof:name":"BL4 7UQ",
    "wof:placetype":"postalcode"
},
  "geometry": {"coordinates":[-2.40670518346459,53.54888795674225],"type":"Point"}
}