{
  "type": "Feature",
  "properties": {
    "iso:country": "GB",
    "wof:name": "BL4 7UQ",
    "wof:placetype": "postalcode"
  },
  "geometry": {"coordinates":[-2.406705,53.548888],"type":"Point"}
}
