{
  "type": "Feature",
  "properties": {
    "iso:country":"GB",
    "wof:name":"PE36 5LS",
    "wof:placetype":"postalcode"
},
  "geometry": {"coordinates":[0.54517028012402,52.89941072001923],"type":"Point"}
}