{
  "type": "Feature",
  "properties": {
    "iso:country":"GB",
    "wof:name":"LS11 7JP",
    "wof:placetype":"postalcode"
},
  "geometry": {"coordinates":[-1.56337375174841,53.77220500579492],"type":"Point"}
}