{
  "type": "Feature",
  "properties": {
    "iso:country":"GB",
    "wof:name":"NR21 0LH",
    "wof:placetype":"postalcode"
},
  "geometry": {"coordinates":[0.84595089076497,52.86807721459861],"type":"Point"}
}