{
  "type": "Feature",
  "properties": {
    "iso:country":"GB",
    "wof:name":"AL4 8NZ",
    "wof:placetype":"postalcode"
},
  "geometry": {"coordinates":[-0.29200948148498,51.80745516061442],"type":"Point"}
}