{
  "type": "Feature",
  "properties": {
    "iso:country": "GB",
    "wof:name": "AL4 8NZ",
    "wof:placetype": "postalcode"
  },
  "geometry": {"coordinates":[-0.292009,51.807455],"type":"Point"}
}
