{
  "type": "Feature",
  "properties": {
    "iso:country": "GB",
    "wof:name": "G71 6PD",
    "wof:placetype": "postalcode"
  },
  "geometry": {"coordinates":[-4.053909,55.820852],"type":"Point"}
}
