{
  "type": "Feature",
  "properties": {
    "iso:country":"GB",
    "wof:name":"NG12 2AA",
    "wof:placetype":"postalcode"
},
  "geometry": {"coordinates":[-1.0410150933779,52.94694370222688],"type":"Point"}
}