{
  "type": "Feature",
  "properties": {
    "iso:country":"GB",
    "wof:name":"G64 2AD",
    "wof:placetype":"postalcode"
},
  "geometry": {"coordinates":[-4.23064073923991,55.90273943862923],"type":"Point"}
}