{
  "type": "Feature",
  "properties": {
    "iso:country":"GB",
    "wof:name":"LS26 8BD",
    "wof:placetype":"postalcode"
},
  "geometry": {"coordinates":[-1.38803859794689,53.76280105016107],"type":"Point"}
}