{
  "type": "Feature",
  "properties": {
    "date:inception_lower": "1980-01-01",
    "date:inception_upper": "1980-01-01",
    "iso:country": "GB",
    "wof:name": "LL14 3SU",
    "wof:placetype": "postalcode"
  },
  "geometry": {"coordinates":[-3.088774,52.979772],"type":"Point"}
}
