{
  "type": "Feature",
  "properties": {
    "iso:country": "GB",
    "wof:name": "LL14 3SU",
    "wof:placetype": "postalcode"
  },
  "geometry": {"coordinates":[-3.08914,52.979475],"type":"Point"}
}
