{
  "type": "Feature",
  "properties": {
    "iso:country":"GB",
    "wof:name":"HA8 7NN",
    "wof:placetype":"postalcode"
},
  "geometry": {"coordinates":[-0.27992439458306,51.61252859732372],"type":"Point"}
}