{
  "type": "Feature",
  "properties": {
    "iso:country":"GB",
    "wof:name":"IP26 5AT",
    "wof:placetype":"postalcode"
},
  "geometry": {"coordinates":[0.62635470633186,52.54476565489553],"type":"Point"}
}