{
  "type": "Feature",
  "properties": {
    "iso:country":"GB",
    "wof:name":"KT10 9QU",
    "wof:placetype":"postalcode"
},
  "geometry": {"coordinates":[-0.36572650531808,51.3689391778008],"type":"Point"}
}