{
  "type": "Feature",
  "properties": {
    "date:inception_lower":"1996-06-01",
    "date:inception_upper":"1996-06-30",
    "iso:country":"GB",
    "wof:name":"KT10 9QU",
    "wof:placetype":"postalcode"
},
  "geometry": {"coordinates":[-0.365726,51.368939],"type":"Point"}
}