{
  "type": "Feature",
  "properties": {
    "iso:country": "GB",
    "wof:name": "B10 9HY",
    "wof:placetype": "postalcode"
  },
  "geometry": {"coordinates":[-1.839821,52.466702],"type":"Point"}
}
