{
  "type": "Feature",
  "properties": {
    "iso:country":"GB",
    "wof:name":"TS19 0HW",
    "wof:placetype":"postalcode"
},
  "geometry": {"coordinates":[-1.32054926764617,54.57734280797189],"type":"Point"}
}