{
  "type": "Feature",
  "properties": {
    "date:inception_lower": "2016-11-01",
    "date:inception_upper": "2016-11-01",
    "iso:country": "GB",
    "wof:name": "TR3 7FH",
    "wof:placetype": "postalcode"
  },
  "geometry": {"coordinates":[-5.14475,50.196462],"type":"Point"}
}
