{
  "type": "Feature",
  "properties": {
    "iso:country": "GB",
    "wof:name": "SA6 5BB",
    "wof:placetype": "postalcode"
  },
  "geometry": {"coordinates":[-3.90081,51.691191],"type":"Point"}
}
