{
  "type": "Feature",
  "properties": {
    "date:inception_lower": "2017-09-01",
    "date:inception_upper": "2017-09-01",
    "iso:country": "GB",
    "wof:name": "SA6 5BB",
    "wof:placetype": "postalcode"
  },
  "geometry": {"coordinates":[-3.90081,51.691191],"type":"Point"}
}
