{
  "type": "Feature",
  "properties": {
    "iso:country":"GB",
    "wof:name":"BN3 4HQ",
    "wof:placetype":"postalcode"
},
  "geometry": {"coordinates":[-0.18913023818476,50.82765110151954],"type":"Point"}
}