{
  "type": "Feature",
  "properties": {
    "iso:country": "GB",
    "wof:name": "NG11 6DX",
    "wof:placetype": "postalcode"
  },
  "geometry": {"coordinates":[-1.148573,52.891319],"type":"Point"}
}
