{
  "type": "Feature",
  "properties": {
    "date:inception_lower": "1980-01-01",
    "date:inception_upper": "1980-01-01",
    "iso:country": "GB",
    "wof:name": "NG11 6DX",
    "wof:placetype": "postalcode"
  },
  "geometry": {"coordinates":[-1.148544,52.89131],"type":"Point"}
}
