{
  "type": "Feature",
  "properties": {
    "iso:country":"GB",
    "wof:name":"SE25 4DR",
    "wof:placetype":"postalcode"
},
  "geometry": {"coordinates":[-0.07374392278597,51.40584192317182],"type":"Point"}
}