{
  "type": "Feature",
  "properties": {
    "date:inception_lower": "2000-12-01",
    "date:inception_upper": "2000-12-01",
    "iso:country": "GB",
    "wof:name": "WD23 4RF",
    "wof:placetype": "postalcode"
  },
  "geometry": {"coordinates":[-0.348838,51.642635],"type":"Point"}
}
