{
  "type": "Feature",
  "properties": {
    "iso:country":"GB",
    "wof:name":"AB34 4TJ",
    "wof:placetype":"postalcode"
},
  "geometry": {"coordinates":[-2.81083875395467,57.14260208787433],"type":"Point"}
}