{
  "type": "Feature",
  "properties": {
    "iso:country":"GB",
    "wof:name":"BN26 5HS",
    "wof:placetype":"postalcode"
},
  "geometry": {"coordinates":[0.23119337757775,50.81997329418294],"type":"Point"}
}