{
  "type": "Feature",
  "properties": {
    "iso:country": "GB",
    "wof:name": "BN26 5HS",
    "wof:placetype": "postalcode"
  },
  "geometry": {"coordinates":[0.231193,50.819973],"type":"Point"}
}
