{
  "type": "Feature",
  "properties": {
    "iso:country":"GB",
    "wof:name":"SL2 5JD",
    "wof:placetype":"postalcode"
},
  "geometry": {"coordinates":[-0.57962097236706,51.51745431584258],"type":"Point"}
}