{
  "type": "Feature",
  "properties": {
    "iso:country":"GB",
    "wof:name":"SN8 2PG",
    "wof:placetype":"postalcode"
},
  "geometry": {"coordinates":[-1.60360846138582,51.44349543209448],"type":"Point"}
}