{
  "type": "Feature",
  "properties": {
    "iso:country": "GB",
    "wof:name": "SN8 2PG",
    "wof:placetype": "postalcode"
  },
  "geometry": {"coordinates":[-1.603608,51.443495],"type":"Point"}
}
