{
  "type": "Feature",
  "properties": {
    "iso:country": "GB",
    "wof:name": "TF1 1LP",
    "wof:placetype": "postalcode"
  },
  "geometry": {"coordinates":[-2.518206,52.700454],"type":"Point"}
}
