{
  "type": "Feature",
  "properties": {
    "iso:country":"GB",
    "wof:name":"BR1 1SB",
    "wof:placetype":"postalcode"
},
  "geometry": {"coordinates":[0.01522481844299,51.40769097030856],"type":"Point"}
}