{
  "type": "Feature",
  "properties": {
    "date:inception_lower":"1999-06-01",
    "date:inception_upper":"1999-06-30",
    "iso:country":"GB",
    "wof:name":"BR1 1SB",
    "wof:placetype":"postalcode"
},
  "geometry": {"coordinates":[0.015164,51.407683],"type":"Point"}
}