{
  "type": "Feature",
  "properties": {
    "iso:country":"GB",
    "wof:name":"GU31 5QA",
    "wof:placetype":"postalcode"
},
  "geometry": {"coordinates":[-0.88301881755893,50.97020413408861],"type":"Point"}
}