{
  "type": "Feature",
  "properties": {
    "iso:country": "GB",
    "wof:name": "GU31 5QA",
    "wof:placetype": "postalcode"
  },
  "geometry": {"coordinates":[-0.883019,50.970204],"type":"Point"}
}
