{
  "type": "Feature",
  "properties": {
    "iso:country":"GB",
    "wof:name":"EN9 3XT",
    "wof:placetype":"postalcode"
},
  "geometry": {"coordinates":[-0.00552570754428,51.67777083560481],"type":"Point"}
}