{
  "type": "Feature",
  "properties": {
    "date:inception_lower": "2000-12-01",
    "date:inception_upper": "2000-12-01",
    "iso:country": "GB",
    "wof:name": "EN9 3XT",
    "wof:placetype": "postalcode"
  },
  "geometry": {"coordinates":[-0.005526,51.677771],"type":"Point"}
}
