{
  "type": "Feature",
  "properties": {
    "iso:country":"GB",
    "wof:name":"AB39 2LA",
    "wof:placetype":"postalcode"
},
  "geometry": {"coordinates":[-2.20448794434124,56.96002147601496],"type":"Point"}
}