{
  "type": "Feature",
  "properties": {
    "iso:country":"GB",
    "wof:name":"RM18 7RU",
    "wof:placetype":"postalcode"
},
  "geometry": {"coordinates":[0.36235460600365,51.46643434715085],"type":"Point"}
}