{
  "type": "Feature",
  "properties": {
    "iso:country":"GB",
    "wof:name":"DH4 5HS",
    "wof:placetype":"postalcode"
},
  "geometry": {"coordinates":[-1.4835543503326,54.84784771977547],"type":"Point"}
}