{
  "type": "Feature",
  "properties": {
    "iso:country":"GB",
    "wof:name":"B75 5RL",
    "wof:placetype":"postalcode"
},
  "geometry": {"coordinates":[-1.80207230191422,52.58982437584753],"type":"Point"}
}