{
  "type": "Feature",
  "properties": {
    "iso:country": "GB",
    "wof:name": "B75 5RL",
    "wof:placetype": "postalcode"
  },
  "geometry": {"coordinates":[-1.802072,52.589824],"type":"Point"}
}
