{
  "type": "Feature",
  "properties": {
    "iso:country":"GB",
    "wof:name":"CM1 2BZ",
    "wof:placetype":"postalcode"
},
  "geometry": {"coordinates":[0.45457622322174,51.74751880087743],"type":"Point"}
}