{
  "type": "Feature",
  "properties": {
    "iso:country": "GB",
    "wof:name": "CM1 2BZ",
    "wof:placetype": "postalcode"
  },
  "geometry": {"coordinates":[0.454576,51.747519],"type":"Point"}
}
