{
  "type": "Feature",
  "properties": {
    "iso:country":"GB",
    "wof:name":"SY16 2LA",
    "wof:placetype":"postalcode"
},
  "geometry": {"coordinates":[-3.31007094461148,52.5184403859316],"type":"Point"}
}