{
  "type": "Feature",
  "properties": {
    "iso:country": "GB",
    "wof:name": "EH48 1PX",
    "wof:placetype": "postalcode"
  },
  "geometry": {"coordinates":[-3.637755,55.901761],"type":"Point"}
}
