{
  "type": "Feature",
  "properties": {
    "iso:country":"GB",
    "wof:name":"EH48 1PX",
    "wof:placetype":"postalcode"
},
  "geometry": {"coordinates":[-3.63785592342338,55.90171927314815],"type":"Point"}
}