{
  "type": "Feature",
  "properties": {
    "date:inception_lower": "2011-07-01",
    "date:inception_upper": "2011-07-01",
    "iso:country": "GB",
    "wof:name": "EH48 1PX",
    "wof:placetype": "postalcode"
  },
  "geometry": {"coordinates":[-3.637849,55.901715],"type":"Point"}
}
