{
  "type": "Feature",
  "properties": {
    "iso:country": "GB",
    "wof:name": "OL11 2AY",
    "wof:placetype": "postalcode"
  },
  "geometry": {"coordinates":[-2.151337,53.590981],"type":"Point"}
}
