{
  "type": "Feature",
  "properties": {
    "date:inception_lower": "2017-12-01",
    "date:inception_upper": "2017-12-01",
    "iso:country": "GB",
    "wof:name": "OL11 2AY",
    "wof:placetype": "postalcode"
  },
  "geometry": {"coordinates":[-2.151126,53.590991],"type":"Point"}
}
