{
  "type": "Feature",
  "properties": {
    "date:inception_lower": "1993-01-01",
    "date:inception_upper": "1993-01-01",
    "iso:country": "GB",
    "wof:name": "YO11 3YT",
    "wof:placetype": "postalcode"
  },
  "geometry": {"coordinates":[-0.410909,54.235906],"type":"Point"}
}
