{
  "type": "Feature",
  "properties": {
    "iso:country":"GB",
    "wof:name":"BB11 2BQ",
    "wof:placetype":"postalcode"
},
  "geometry": {"coordinates":[-2.24344680440895,53.78720409189177],"type":"Point"}
}