{
  "type": "Feature",
  "properties": {
    "date:inception_lower": "2019-09-01",
    "date:inception_upper": "2019-09-01",
    "iso:country": "GB",
    "wof:name": "LE7 3AH",
    "wof:placetype": "postalcode"
  },
  "geometry": {"coordinates":[-1.04795,52.702848],"type":"Point"}
}
