{
  "type": "Feature",
  "properties": {
    "iso:country":"GB",
    "wof:name":"NW10 9RG",
    "wof:placetype":"postalcode"
},
  "geometry": {"coordinates":[-0.24902639626155,51.54203079830081],"type":"Point"}
}