{
  "type": "Feature",
  "properties": {
    "iso:country": "GB",
    "wof:name": "NN8 4HE",
    "wof:placetype": "postalcode"
  },
  "geometry": {"coordinates":[-0.684867,52.312099],"type":"Point"}
}
