{
  "type": "Feature",
  "properties": {
    "iso:country":"GB",
    "wof:name":"NN8 4HE",
    "wof:placetype":"postalcode"
},
  "geometry": {"coordinates":[-0.68486706317727,52.31209938473401],"type":"Point"}
}