{
  "type": "Feature",
  "properties": {
    "iso:country":"GB",
    "wof:name":"PE29 9GU",
    "wof:placetype":"postalcode"
},
  "geometry": {"coordinates":[-0.18395967539979,52.34065221033659],"type":"Point"}
}