{
  "type": "Feature",
  "properties": {
    "date:inception_lower": "1984-10-01",
    "date:inception_upper": "1984-10-01",
    "iso:country": "GB",
    "wof:name": "YO11 3NB",
    "wof:placetype": "postalcode"
  },
  "geometry": {"coordinates":[-0.38861,54.243088],"type":"Point"}
}
