{
  "type": "Feature",
  "properties": {
    "date:inception_lower": "2005-11-01",
    "date:inception_upper": "2005-11-01",
    "iso:country": "GB",
    "wof:name": "CA22 2SX",
    "wof:placetype": "postalcode"
  },
  "geometry": {"coordinates":[-3.54521,54.504623],"type":"Point"}
}
