{
  "type": "Feature",
  "properties": {
    "iso:country":"GB",
    "wof:name":"CA22 2SX",
    "wof:placetype":"postalcode"
},
  "geometry": {"coordinates":[-3.54505329310181,54.5045790788883],"type":"Point"}
}