{
  "type": "Feature",
  "properties": {
    "iso:country":"GB",
    "wof:name":"EN6 1BB",
    "wof:placetype":"postalcode"
},
  "geometry": {"coordinates":[-0.19129290001191,51.69732424068464],"type":"Point"}
}