{
  "type": "Feature",
  "properties": {
    "iso:country": "GB",
    "wof:name": "WN5 8UL",
    "wof:placetype": "postalcode"
  },
  "geometry": {"coordinates":[-2.715744,53.53373],"type":"Point"}
}
