{
  "type": "Feature",
  "properties": {
    "iso:country":"GB",
    "wof:name":"HU6 7RB",
    "wof:placetype":"postalcode"
},
  "geometry": {"coordinates":[-0.35474513058028,53.76867907890023],"type":"Point"}
}