{
  "type": "Feature",
  "properties": {
    "iso:country": "GB",
    "wof:name": "HU6 7RB",
    "wof:placetype": "postalcode"
  },
  "geometry": {"coordinates":[-0.354745,53.768679],"type":"Point"}
}
