{
  "type": "Feature",
  "properties": {
    "iso:country":"GB",
    "wof:name":"DE22 2FZ",
    "wof:placetype":"postalcode"
},
  "geometry": {"coordinates":[-1.49183483803006,52.95716843478288],"type":"Point"}
}