{
  "type": "Feature",
  "properties": {
    "iso:country":"GB",
    "wof:name":"LS26 8LY",
    "wof:placetype":"postalcode"
},
  "geometry": {"coordinates":[-1.44498857717524,53.75441353931247],"type":"Point"}
}