{
  "type": "Feature",
  "properties": {
    "date:inception_lower": "1997-12-01",
    "date:inception_upper": "1997-12-01",
    "iso:country": "GB",
    "wof:name": "DY4 0PU",
    "wof:placetype": "postalcode"
  },
  "geometry": {"coordinates":[-2.033066,52.539648],"type":"Point"}
}
