{
  "type": "Feature",
  "properties": {
    "iso:country": "GB",
    "wof:name": "DY4 0PU",
    "wof:placetype": "postalcode"
  },
  "geometry": {"coordinates":[-2.033095,52.538416],"type":"Point"}
}
