{
  "type": "Feature",
  "properties": {
    "date:inception_lower": "2022-09-01",
    "date:inception_upper": "2022-09-01",
    "iso:country": "GB",
    "wof:name": "DE6 4PT",
    "wof:placetype": "postalcode"
  },
  "geometry": {"coordinates":[-1.567891,52.945756],"type":"Point"}
}
