{
  "type": "Feature",
  "properties": {
    "date:inception_lower": "2005-08-01",
    "date:inception_upper": "2005-08-01",
    "iso:country": "GB",
    "wof:name": "SP5 3LN",
    "wof:placetype": "postalcode"
  },
  "geometry": {"coordinates":[-1.746189,50.978342],"type":"Point"}
}
