{
  "type": "Feature",
  "properties": {
    "iso:country":"GB",
    "wof:name":"SP5 3LN",
    "wof:placetype":"postalcode"
},
  "geometry": {"coordinates":[-1.74618950287125,50.97834232767124],"type":"Point"}
}