{
  "type": "Feature",
  "properties": {
    "iso:country":"GB",
    "wof:name":"SS9 2QT",
    "wof:placetype":"postalcode"
},
  "geometry": {"coordinates":[0.62590354224465,51.54705636849463],"type":"Point"}
}