{
  "type": "Feature",
  "properties": {
    "iso:country": "GB",
    "wof:name": "TQ6 9TD",
    "wof:placetype": "postalcode"
  },
  "geometry": {"coordinates":[-3.593822,50.354027],"type":"Point"}
}
