{
  "type": "Feature",
  "properties": {
    "date:inception_lower":"1984-10-01",
    "date:inception_upper":"1984-10-31",
    "iso:country":"GB",
    "wof:name":"TQ6 9TD",
    "wof:placetype":"postalcode"
},
  "geometry": {"coordinates":[-3.593822,50.354027],"type":"Point"}
}