{
  "type": "Feature",
  "properties": {
    "iso:country":"GB",
    "wof:name":"HA4 6HF",
    "wof:placetype":"postalcode"
},
  "geometry": {"coordinates":[-0.42266073699285,51.56682110594951],"type":"Point"}
}