{
  "type": "Feature",
  "properties": {
    "iso:country": "GB",
    "wof:name": "WS14 0DH",
    "wof:placetype": "postalcode"
  },
  "geometry": {"coordinates":[-1.851663,52.639727],"type":"Point"}
}
