{
  "type": "Feature",
  "properties": {
    "iso:country":"GB",
    "wof:name":"PE16 6LA",
    "wof:placetype":"postalcode"
},
  "geometry": {"coordinates":[0.05060208580362,52.45333495513146],"type":"Point"}
}