{
  "type": "Feature",
  "properties": {
    "iso:country":"GB",
    "wof:name":"EH11 2HG",
    "wof:placetype":"postalcode"
},
  "geometry": {"coordinates":[-3.22438880493179,55.94323148649607],"type":"Point"}
}