{
  "type": "Feature",
  "properties": {
    "iso:country": "GB",
    "wof:name": "CF48 1DA",
    "wof:placetype": "postalcode"
  },
  "geometry": {"coordinates":[-3.387913,51.749413],"type":"Point"}
}
