{
  "type": "Feature",
  "properties": {
    "iso:country":"GB",
    "wof:name":"CF48 1DA",
    "wof:placetype":"postalcode"
},
  "geometry": {"coordinates":[-3.38791325126093,51.74941301208092],"type":"Point"}
}