{
  "type": "Feature",
  "properties": {
    "iso:country":"GB",
    "wof:name":"BR8 7LG",
    "wof:placetype":"postalcode"
},
  "geometry": {"coordinates":[0.18060529320682,51.40778757288052],"type":"Point"}
}