{
  "type": "Feature",
  "properties": {
    "iso:country": "GB",
    "wof:name": "RG40 3BG",
    "wof:placetype": "postalcode"
  },
  "geometry": {"coordinates":[-0.811479,51.391456],"type":"Point"}
}
