{
  "type": "Feature",
  "properties": {
    "iso:country":"GB",
    "wof:name":"RG40 3BG",
    "wof:placetype":"postalcode"
},
  "geometry": {"coordinates":[-0.81147938837456,51.39145618290507],"type":"Point"}
}