{
  "type": "Feature",
  "properties": {
    "iso:country": "GB",
    "wof:name": "BB11 3AZ",
    "wof:placetype": "postalcode"
  },
  "geometry": {"coordinates":[-2.234788,53.785954],"type":"Point"}
}
