{
  "type": "Feature",
  "properties": {
    "date:inception_lower": "1993-01-01",
    "date:inception_upper": "1993-01-01",
    "iso:country": "GB",
    "wof:name": "WF4 4LG",
    "wof:placetype": "postalcode"
  },
  "geometry": {"coordinates":[-1.573111,53.611044],"type":"Point"}
}
