{
  "type": "Feature",
  "properties": {
    "iso:country": "GB",
    "wof:name": "WF4 4LG",
    "wof:placetype": "postalcode"
  },
  "geometry": {"coordinates":[-1.563159,53.607297],"type":"Point"}
}
