{
  "type": "Feature",
  "properties": {
    "iso:country":"GB",
    "wof:name":"W3 9SQ",
    "wof:placetype":"postalcode"
},
  "geometry": {"coordinates":[-0.28315990188814,51.50985712257217],"type":"Point"}
}