{
  "type": "Feature",
  "properties": {
    "iso:country":"GB",
    "wof:name":"SE6 1NN",
    "wof:placetype":"postalcode"
},
  "geometry": {"coordinates":[0.00060793098465,51.44110686238212],"type":"Point"}
}