{
  "type": "Feature",
  "properties": {
    "iso:country": "GB",
    "wof:name": "WC2B 5PR",
    "wof:placetype": "postalcode"
  },
  "geometry": {"coordinates":[-0.123607,51.516082],"type":"Point"}
}
