{
  "type": "Feature",
  "properties": {
    "iso:country": "GB",
    "wof:name": "ME12 4QR",
    "wof:placetype": "postalcode"
  },
  "geometry": {"coordinates":[0.924251,51.396],"type":"Point"}
}
