{
  "type": "Feature",
  "properties": {
    "iso:country":"GB",
    "wof:name":"ME12 4QR",
    "wof:placetype":"postalcode"
},
  "geometry": {"coordinates":[0.92425116545505,51.39599970826714],"type":"Point"}
}