{
  "type": "Feature",
  "properties": {
    "iso:country":"GB",
    "wof:name":"TS14 8AD",
    "wof:placetype":"postalcode"
},
  "geometry": {"coordinates":[-1.06474541736846,54.53131197220709],"type":"Point"}
}