{
  "type": "Feature",
  "properties": {
    "iso:country":"GB",
    "wof:name":"TW20 0QA",
    "wof:placetype":"postalcode"
},
  "geometry": {"coordinates":[-0.57742670510702,51.43053685274442],"type":"Point"}
}