{
  "type": "Feature",
  "properties": {
    "iso:country": "GB",
    "wof:name": "DL3 8AT",
    "wof:placetype": "postalcode"
  },
  "geometry": {"coordinates":[-1.593248,54.522488],"type":"Point"}
}
