{
  "type": "Feature",
  "properties": {
    "iso:country":"GB",
    "wof:name":"DL3 8AT",
    "wof:placetype":"postalcode"
},
  "geometry": {"coordinates":[-1.59324789481109,54.52248765149598],"type":"Point"}
}