{
  "type": "Feature",
  "properties": {
    "iso:country":"GB",
    "wof:name":"PE14 0RT",
    "wof:placetype":"postalcode"
},
  "geometry": {"coordinates":[0.12982329389792,52.64026993318382],"type":"Point"}
}