{
  "type": "Feature",
  "properties": {
    "date:inception_lower": "2023-10-01",
    "date:inception_upper": "2023-10-01",
    "iso:country": "GB",
    "wof:name": "B98 8BB",
    "wof:placetype": "postalcode"
  },
  "geometry": {"coordinates":[-1.912081,52.313547],"type":"Point"}
}
