{
  "type": "Feature",
  "properties": {
    "date:inception_lower": "1980-01-01",
    "date:inception_upper": "1980-01-01",
    "iso:country": "GB",
    "wof:name": "MK14 6HJ",
    "wof:placetype": "postalcode"
  },
  "geometry": {"coordinates":[-0.750935,52.059488],"type":"Point"}
}
