{
  "type": "Feature",
  "properties": {
    "iso:country":"GB",
    "wof:name":"MK14 6HJ",
    "wof:placetype":"postalcode"
},
  "geometry": {"coordinates":[-0.75093519892061,52.05948778603482],"type":"Point"}
}