{
  "type": "Feature",
  "properties": {
    "iso:country":"GB",
    "wof:name":"LU2 9HS",
    "wof:placetype":"postalcode"
},
  "geometry": {"coordinates":[-0.38299078684151,51.88919084871271],"type":"Point"}
}