{
  "type": "Feature",
  "properties": {
    "iso:country": "GB",
    "wof:name": "LU2 9HS",
    "wof:placetype": "postalcode"
  },
  "geometry": {"coordinates":[-0.382991,51.889191],"type":"Point"}
}
