{
  "type": "Feature",
  "properties": {
    "iso:country":"GB",
    "wof:name":"LS25 7LQ",
    "wof:placetype":"postalcode"
},
  "geometry": {"coordinates":[-1.38074927065564,53.76334786575882],"type":"Point"}
}