{
  "type": "Feature",
  "properties": {
    "iso:country":"GB",
    "wof:name":"LS12 5QP",
    "wof:placetype":"postalcode"
},
  "geometry": {"coordinates":[-1.62327317350955,53.77581451483664],"type":"Point"}
}