{
  "type": "Feature",
  "properties": {
    "date:inception_lower": "1980-01-01",
    "date:inception_upper": "1980-01-01",
    "iso:country": "GB",
    "wof:name": "LS15 0NE",
    "wof:placetype": "postalcode"
  },
  "geometry": {"coordinates":[-1.450303,53.796889],"type":"Point"}
}
