{
  "type": "Feature",
  "properties": {
    "iso:country":"GB",
    "wof:name":"LS15 0NE",
    "wof:placetype":"postalcode"
},
  "geometry": {"coordinates":[-1.45030346607093,53.79688887522173],"type":"Point"}
}