{
  "type": "Feature",
  "properties": {
    "iso:country":"GB",
    "wof:name":"TW3 4BE",
    "wof:placetype":"postalcode"
},
  "geometry": {"coordinates":[-0.36165607073316,51.47646736615579],"type":"Point"}
}