{
  "type": "Feature",
  "properties": {
    "iso:country":"GB",
    "wof:name":"TN23 1JS",
    "wof:placetype":"postalcode"
},
  "geometry": {"coordinates":[0.86633414683562,51.15067422914188],"type":"Point"}
}