{
  "type": "Feature",
  "properties": {
    "iso:country": "GB",
    "wof:name": "G74 3HX",
    "wof:placetype": "postalcode"
  },
  "geometry": {"coordinates":[-4.149567,55.772869],"type":"Point"}
}
