{
  "type": "Feature",
  "properties": {
    "iso:country":"GB",
    "wof:name":"G74 3HX",
    "wof:placetype":"postalcode"
},
  "geometry": {"coordinates":[-4.14956699841151,55.77286928694414],"type":"Point"}
}