{
  "type": "Feature",
  "properties": {
    "iso:country":"GB",
    "wof:name":"NE61 6XG",
    "wof:placetype":"postalcode"
},
  "geometry": {"coordinates":[-1.64502032969961,55.18268600777668],"type":"Point"}
}