{
  "type": "Feature",
  "properties": {
    "date:inception_lower":"1980-01-01",
    "date:inception_upper":"1980-01-31",
    "iso:country":"GB",
    "wof:name":"W6 0XF",
    "wof:placetype":"postalcode"
},
  "geometry": {"coordinates":[-0.244279,51.497269],"type":"Point"}
}