{
  "type": "Feature",
  "properties": {
    "iso:country": "GB",
    "wof:name": "W6 0XF",
    "wof:placetype": "postalcode"
  },
  "geometry": {"coordinates":[-0.244279,51.497269],"type":"Point"}
}
