{
  "type": "Feature",
  "properties": {
    "iso:country":"GB",
    "wof:name":"WD3 8EF",
    "wof:placetype":"postalcode"
},
  "geometry": {"coordinates":[-0.49459793973031,51.63765184320405],"type":"Point"}
}