{
  "type": "Feature",
  "properties": {
    "iso:country":"GB",
    "wof:name":"BL6 5DN",
    "wof:placetype":"postalcode"
},
  "geometry": {"coordinates":[-2.58054084207693,53.5950627750447],"type":"Point"}
}