{
  "type": "Feature",
  "properties": {
    "iso:country": "GB",
    "wof:name": "BL6 5DN",
    "wof:placetype": "postalcode"
  },
  "geometry": {"coordinates":[-2.580541,53.595063],"type":"Point"}
}
