{
  "type": "Feature",
  "properties": {
    "iso:country": "GB",
    "wof:name": "NR5 8EU",
    "wof:placetype": "postalcode"
  },
  "geometry": {"coordinates":[1.241352,52.632378],"type":"Point"}
}
