{
  "type": "Feature",
  "properties": {
    "date:inception_lower": "1980-01-01",
    "date:inception_upper": "1980-01-01",
    "iso:country": "GB",
    "wof:name": "SN8 1PZ",
    "wof:placetype": "postalcode"
  },
  "geometry": {"coordinates":[-1.788239,51.415875],"type":"Point"}
}
