{
  "type": "Feature",
  "properties": {
    "iso:country":"GB",
    "wof:name":"SN8 1PZ",
    "wof:placetype":"postalcode"
},
  "geometry": {"coordinates":[-1.78823866837468,51.41587514870732],"type":"Point"}
}