{
  "type": "Feature",
  "properties": {
    "iso:country":"GB",
    "wof:name":"HG1 4NL",
    "wof:placetype":"postalcode"
},
  "geometry": {"coordinates":[-1.50887286954203,53.99823828741697],"type":"Point"}
}