{
  "type": "Feature",
  "properties": {
    "iso:country": "GB",
    "wof:name": "HG1 4NL",
    "wof:placetype": "postalcode"
  },
  "geometry": {"coordinates":[-1.508873,53.998238],"type":"Point"}
}
