{
  "type": "Feature",
  "properties": {
    "iso:country": "GB",
    "wof:name": "GU12 6SW",
    "wof:placetype": "postalcode"
  },
  "geometry": {"coordinates":[-0.721248,51.252053],"type":"Point"}
}
