{
  "type": "Feature",
  "properties": {
    "iso:country":"GB",
    "wof:name":"DN22 7LB",
    "wof:placetype":"postalcode"
},
  "geometry": {"coordinates":[-0.94870353026778,53.32822972152034],"type":"Point"}
}