{
  "type": "Feature",
  "properties": {
    "iso:country": "GB",
    "wof:name": "DN22 7LB",
    "wof:placetype": "postalcode"
  },
  "geometry": {"coordinates":[-0.948703,53.32823],"type":"Point"}
}
