{
  "type": "Feature",
  "properties": {
    "iso:country":"GB",
    "wof:name":"CF62 3DX",
    "wof:placetype":"postalcode"
},
  "geometry": {"coordinates":[-3.35485421319878,51.38932153587258],"type":"Point"}
}