{
  "type": "Feature",
  "properties": {
    "date:inception_lower": "1980-01-01",
    "date:inception_upper": "1980-01-01",
    "iso:country": "GB",
    "wof:name": "CF47 9RT",
    "wof:placetype": "postalcode"
  },
  "geometry": {"coordinates":[-3.378772,51.760347],"type":"Point"}
}
