{
  "type": "Feature",
  "properties": {
    "iso:country":"GB",
    "wof:name":"CF47 9RT",
    "wof:placetype":"postalcode"
},
  "geometry": {"coordinates":[-3.37877221958049,51.76034661066242],"type":"Point"}
}