{
  "type": "Feature",
  "properties": {
    "iso:country":"GB",
    "wof:name":"WV6 7DE",
    "wof:placetype":"postalcode"
},
  "geometry": {"coordinates":[-2.26453388974141,52.58785039674701],"type":"Point"}
}