{
  "type": "Feature",
  "properties": {
    "iso:country": "GB",
    "wof:name": "WV6 7DE",
    "wof:placetype": "postalcode"
  },
  "geometry": {"coordinates":[-2.264534,52.58785],"type":"Point"}
}
