{
  "type": "Feature",
  "properties": {
    "iso:country":"GB",
    "wof:name":"DH9 7RF",
    "wof:placetype":"postalcode"
},
  "geometry": {"coordinates":[-1.70681784202335,54.86690577311438],"type":"Point"}
}