{
  "type": "Feature",
  "properties": {
    "date:inception_lower": "1991-09-01",
    "date:inception_upper": "1991-09-01",
    "iso:country": "GB",
    "wof:name": "SA14 8DG",
    "wof:placetype": "postalcode"
  },
  "geometry": {"coordinates":[-4.141669,51.701598],"type":"Point"}
}
