{
  "type": "Feature",
  "properties": {
    "iso:country":"GB",
    "wof:name":"SA14 8DG",
    "wof:placetype":"postalcode"
},
  "geometry": {"coordinates":[-4.14166915943905,51.70159835190672],"type":"Point"}
}