{
  "type": "Feature",
  "properties": {
    "iso:country":"GB",
    "wof:name":"ME15 0QF",
    "wof:placetype":"postalcode"
},
  "geometry": {"coordinates":[0.50827997657238,51.23474944416452],"type":"Point"}
}