{
  "type": "Feature",
  "properties": {
    "iso:country":"GB",
    "wof:name":"YO25 3DP",
    "wof:placetype":"postalcode"
},
  "geometry": {"coordinates":[-0.3602843215171,54.11983296725503],"type":"Point"}
}