{
  "type": "Feature",
  "properties": {
    "iso:country": "GB",
    "wof:name": "YO25 3DP",
    "wof:placetype": "postalcode"
  },
  "geometry": {"coordinates":[-0.360284,54.119833],"type":"Point"}
}
