{
  "type": "Feature",
  "properties": {
    "iso:country":"GB",
    "wof:name":"PR25 4GH",
    "wof:placetype":"postalcode"
},
  "geometry": {"coordinates":[-2.68498251902923,53.70185838810031],"type":"Point"}
}