{
  "type": "Feature",
  "properties": {
    "iso:country":"GB",
    "wof:name":"MK18 2HZ",
    "wof:placetype":"postalcode"
},
  "geometry": {"coordinates":[-0.92902098674448,51.96535080452853],"type":"Point"}
}