{
  "type": "Feature",
  "properties": {
    "iso:country": "GB",
    "wof:name": "MK18 2HZ",
    "wof:placetype": "postalcode"
  },
  "geometry": {"coordinates":[-0.929021,51.965351],"type":"Point"}
}
