{
  "type": "Feature",
  "properties": {
    "iso:country":"GB",
    "wof:name":"DE11 7EW",
    "wof:placetype":"postalcode"
},
  "geometry": {"coordinates":[-1.52980947687124,52.76735046430178],"type":"Point"}
}