{
  "type": "Feature",
  "properties": {
    "date:inception_lower":"2006-03-01",
    "date:inception_upper":"2006-03-31",
    "iso:country":"GB",
    "wof:name":"DE11 7EW",
    "wof:placetype":"postalcode"
},
  "geometry": {"coordinates":[-1.529809,52.76735],"type":"Point"}
}