{
  "type": "Feature",
  "properties": {
    "iso:country":"GB",
    "wof:name":"GU25 4QZ",
    "wof:placetype":"postalcode"
},
  "geometry": {"coordinates":[-0.57835758556464,51.39450736588492],"type":"Point"}
}