{
  "type": "Feature",
  "properties": {
    "iso:country": "GB",
    "wof:name": "TR8 5UE",
    "wof:placetype": "postalcode"
  },
  "geometry": {"coordinates":[-4.932847,50.36134],"type":"Point"}
}
