{
  "type": "Feature",
  "properties": {
    "iso:country":"GB",
    "wof:name":"TR8 5UE",
    "wof:placetype":"postalcode"
},
  "geometry": {"coordinates":[-4.93284685205469,50.3613399152364],"type":"Point"}
}