{
  "type": "Feature",
  "properties": {
    "iso:country": "GB",
    "wof:name": "NR16 1BW",
    "wof:placetype": "postalcode"
  },
  "geometry": {"coordinates":[1.152468,52.505483],"type":"Point"}
}
