{
  "type": "Feature",
  "properties": {
    "iso:country":"GB",
    "wof:name":"NR16 1BW",
    "wof:placetype":"postalcode"
},
  "geometry": {"coordinates":[1.15246754362817,52.50548303235557],"type":"Point"}
}