{
  "type": "Feature",
  "properties": {
    "date:inception_lower":"2006-08-01",
    "date:inception_upper":"2006-08-31",
    "iso:country":"GB",
    "wof:name":"NR16 1BW",
    "wof:placetype":"postalcode"
},
  "geometry": {"coordinates":[1.152468,52.505483],"type":"Point"}
}