{
  "type": "Feature",
  "properties": {
    "iso:country": "GB",
    "wof:name": "EX31 3WN",
    "wof:placetype": "postalcode"
  },
  "geometry": {"coordinates":[-4.097018,51.06801],"type":"Point"}
}
