{
  "type": "Feature",
  "properties": {
    "date:inception_lower": "2017-04-01",
    "date:inception_upper": "2017-04-01",
    "iso:country": "GB",
    "wof:name": "EX31 3WN",
    "wof:placetype": "postalcode"
  },
  "geometry": {"coordinates":[-4.097018,51.06801],"type":"Point"}
}
