{
  "type": "Feature",
  "properties": {
    "iso:country":"GB",
    "wof:name":"SK6 6PW",
    "wof:placetype":"postalcode"
},
  "geometry": {"coordinates":[-2.06531012010807,53.40095639958143],"type":"Point"}
}