{
  "type": "Feature",
  "properties": {
    "date:inception_lower":"1980-01-01",
    "date:inception_upper":"1980-01-31",
    "iso:country":"GB",
    "wof:name":"CH5 1HJ",
    "wof:placetype":"postalcode"
},
  "geometry": {"coordinates":[-3.04623,53.212109],"type":"Point"}
}