{
  "type": "Feature",
  "properties": {
    "iso:country": "GB",
    "wof:name": "CH5 1HJ",
    "wof:placetype": "postalcode"
  },
  "geometry": {"coordinates":[-3.04623,53.212109],"type":"Point"}
}
