{
  "type": "Feature",
  "properties": {
    "iso:country":"GB",
    "wof:name":"CH5 1HJ",
    "wof:placetype":"postalcode"
},
  "geometry": {"coordinates":[-3.04641157823825,53.21215480463629],"type":"Point"}
}