{
  "type": "Feature",
  "properties": {
    "iso:country":"GB",
    "wof:name":"KT6 6EX",
    "wof:placetype":"postalcode"
},
  "geometry": {"coordinates":[-0.29852675047466,51.3908685082186],"type":"Point"}
}