{
  "type": "Feature",
  "properties": {
    "iso:country":"GB",
    "wof:name":"FY8 4FZ",
    "wof:placetype":"postalcode"
},
  "geometry": {"coordinates":[-2.98801605091791,53.75312422099397],"type":"Point"}
}