{
  "type": "Feature",
  "properties": {
    "iso:country":"GB",
    "wof:name":"CO1 1EH",
    "wof:placetype":"postalcode"
},
  "geometry": {"coordinates":[0.89647973138031,51.89235144866328],"type":"Point"}
}