{
  "type": "Feature",
  "properties": {
    "iso:country": "GB",
    "wof:name": "CO1 1EH",
    "wof:placetype": "postalcode"
  },
  "geometry": {"coordinates":[0.89648,51.892351],"type":"Point"}
}
