{
  "type": "Feature",
  "properties": {
    "iso:country":"GB",
    "wof:name":"DA1 5DS",
    "wof:placetype":"postalcode"
},
  "geometry": {"coordinates":[0.23900797215775,51.45207424242999],"type":"Point"}
}