{
  "type": "Feature",
  "properties": {
    "iso:country": "GB",
    "wof:name": "DD10 9EH",
    "wof:placetype": "postalcode"
  },
  "geometry": {"coordinates":[-2.489083,56.7382],"type":"Point"}
}
