{
  "type": "Feature",
  "properties": {
    "iso:country":"GB",
    "wof:name":"DD10 9EH",
    "wof:placetype":"postalcode"
},
  "geometry": {"coordinates":[-2.48908263567411,56.73820020490377],"type":"Point"}
}