{
  "type": "Feature",
  "properties": {
    "iso:country": "GB",
    "wof:name": "CH66 1UP",
    "wof:placetype": "postalcode"
  },
  "geometry": {"coordinates":[-2.910311,53.289948],"type":"Point"}
}
