{
  "type": "Feature",
  "properties": {
    "iso:country":"GB",
    "wof:name":"RH13 0RX",
    "wof:placetype":"postalcode"
},
  "geometry": {"coordinates":[-0.40177848378348,51.0710065459181],"type":"Point"}
}