{
  "type": "Feature",
  "properties": {
    "date:inception_lower": "1987-10-01",
    "date:inception_upper": "1987-10-01",
    "iso:country": "GB",
    "wof:name": "OL3 6HU",
    "wof:placetype": "postalcode"
  },
  "geometry": {"coordinates":[-2.00473,53.543657],"type":"Point"}
}
