{
  "type": "Feature",
  "properties": {
    "iso:country":"GB",
    "wof:name":"PR7 6ND",
    "wof:placetype":"postalcode"
},
  "geometry": {"coordinates":[-2.73544711648926,53.65455000190062],"type":"Point"}
}