{
  "type": "Feature",
  "properties": {
    "date:inception_lower": "1980-01-01",
    "date:inception_upper": "1980-01-01",
    "iso:country": "GB",
    "wof:name": "CW9 5LN",
    "wof:placetype": "postalcode"
  },
  "geometry": {"coordinates":[-2.508174,53.266355],"type":"Point"}
}
