{
  "type": "Feature",
  "properties": {
    "iso:country":"GB",
    "wof:name":"CW9 5LN",
    "wof:placetype":"postalcode"
},
  "geometry": {"coordinates":[-2.50817361427737,53.26635498874987],"type":"Point"}
}