{
  "type": "Feature",
  "properties": {
    "iso:country":"GB",
    "wof:name":"CF14 4HL",
    "wof:placetype":"postalcode"
},
  "geometry": {"coordinates":[-3.19174063930717,51.51846558208306],"type":"Point"}
}