{
  "type": "Feature",
  "properties": {
    "iso:country":"GB",
    "wof:name":"B15 2SW",
    "wof:placetype":"postalcode"
},
  "geometry": {"coordinates":[-1.94353096848986,52.44728828897539],"type":"Point"}
}