{
  "type": "Feature",
  "properties": {
    "date:inception_lower": "1980-01-01",
    "date:inception_upper": "1980-01-01",
    "iso:country": "GB",
    "wof:name": "B15 2SW",
    "wof:placetype": "postalcode"
  },
  "geometry": {"coordinates":[-1.943531,52.447288],"type":"Point"}
}
