{
  "type": "Feature",
  "properties": {
    "iso:country": "GB",
    "wof:name": "SK2 5JP",
    "wof:placetype": "postalcode"
  },
  "geometry": {"coordinates":[-2.107754,53.389366],"type":"Point"}
}
