{
  "type": "Feature",
  "properties": {
    "iso:country":"GB",
    "wof:name":"SK2 5JP",
    "wof:placetype":"postalcode"
},
  "geometry": {"coordinates":[-2.1077539946568,53.38936625056299],"type":"Point"}
}