{
  "type": "Feature",
  "properties": {
    "iso:country":"GB",
    "wof:name":"EH48 3SH",
    "wof:placetype":"postalcode"
},
  "geometry": {"coordinates":[-3.76737978206016,55.88431843707468],"type":"Point"}
}