{
  "type": "Feature",
  "properties": {
    "date:inception_lower": "1980-01-01",
    "date:inception_upper": "1980-01-01",
    "iso:country": "GB",
    "wof:name": "TF3 1EZ",
    "wof:placetype": "postalcode"
  },
  "geometry": {"coordinates":[-2.455539,52.651097],"type":"Point"}
}
