{
  "type": "Feature",
  "properties": {
    "iso:country":"GB",
    "wof:name":"TF3 1EZ",
    "wof:placetype":"postalcode"
},
  "geometry": {"coordinates":[-2.4555391052662,52.65109704896989],"type":"Point"}
}