{
  "type": "Feature",
  "properties": {
    "iso:country":"GB",
    "wof:name":"IG4 5HN",
    "wof:placetype":"postalcode"
},
  "geometry": {"coordinates":[0.05223452236353,51.57988059466368],"type":"Point"}
}