{
  "type": "Feature",
  "properties": {
    "iso:country": "GB",
    "wof:name": "BS4 4HX",
    "wof:placetype": "postalcode"
  },
  "geometry": {"coordinates":[-2.540888,51.454812],"type":"Point"}
}
