{
  "type": "Feature",
  "properties": {
    "iso:country":"GB",
    "wof:name":"BS4 4HX",
    "wof:placetype":"postalcode"
},
  "geometry": {"coordinates":[-2.54088796537033,51.45481166659403],"type":"Point"}
}