{
  "type": "Feature",
  "properties": {
    "date:inception_lower":"1994-05-01",
    "date:inception_upper":"1994-05-31",
    "iso:country":"GB",
    "wof:name":"BS4 4HX",
    "wof:placetype":"postalcode"
},
  "geometry": {"coordinates":[-2.540888,51.454812],"type":"Point"}
}