{
  "type": "Feature",
  "properties": {
    "date:inception_lower":"1999-06-01",
    "date:inception_upper":"1999-06-30",
    "iso:country":"GB",
    "wof:name":"CH48 7EG",
    "wof:placetype":"postalcode"
},
  "geometry": {"coordinates":[-3.170851,53.373954],"type":"Point"}
}