{
  "type": "Feature",
  "properties": {
    "iso:country":"GB",
    "wof:name":"ME13 8BU",
    "wof:placetype":"postalcode"
},
  "geometry": {"coordinates":[0.90241835725582,51.31410180687968],"type":"Point"}
}