{
  "type": "Feature",
  "properties": {
    "iso:country": "GB",
    "wof:name": "ME13 8BU",
    "wof:placetype": "postalcode"
  },
  "geometry": {"coordinates":[0.902418,51.314102],"type":"Point"}
}
