{
  "type": "Feature",
  "properties": {
    "iso:country":"GB",
    "wof:name":"KA12 9HG",
    "wof:placetype":"postalcode"
},
  "geometry": {"coordinates":[-4.66109313257327,55.62707063930985],"type":"Point"}
}