{
  "type": "Feature",
  "properties": {
    "iso:country":"GB",
    "wof:name":"TD9 0AR",
    "wof:placetype":"postalcode"
},
  "geometry": {"coordinates":[-2.78969412595686,55.42017452304423],"type":"Point"}
}