{
  "type": "Feature",
  "properties": {
    "iso:country":"GB",
    "wof:name":"NR31 7AR",
    "wof:placetype":"postalcode"
},
  "geometry": {"coordinates":[1.72355915359869,52.57420607271932],"type":"Point"}
}