{
  "type": "Feature",
  "properties": {
    "iso:country":"GB",
    "wof:name":"NR21 8EY",
    "wof:placetype":"postalcode"
},
  "geometry": {"coordinates":[0.85674727787908,52.83631739945744],"type":"Point"}
}