{
  "type": "Feature",
  "properties": {
    "iso:country": "GB",
    "wof:name": "NR21 8EY",
    "wof:placetype": "postalcode"
  },
  "geometry": {"coordinates":[0.856765,52.836343],"type":"Point"}
}
