{
  "type": "Feature",
  "properties": {
    "date:inception_lower": "1980-01-01",
    "date:inception_upper": "1980-01-01",
    "iso:country": "GB",
    "wof:name": "SK14 2SF",
    "wof:placetype": "postalcode"
  },
  "geometry": {"coordinates":[-2.065383,53.44829],"type":"Point"}
}
