{
  "type": "Feature",
  "properties": {
    "iso:country":"GB",
    "wof:name":"L35 7LQ",
    "wof:placetype":"postalcode"
},
  "geometry": {"coordinates":[-2.78755024676042,53.42743633328655],"type":"Point"}
}