{
  "type": "Feature",
  "properties": {
    "iso:country": "GB",
    "wof:name": "L35 7LQ",
    "wof:placetype": "postalcode"
  },
  "geometry": {"coordinates":[-2.78755,53.427436],"type":"Point"}
}
