{
  "type": "Feature",
  "properties": {
    "iso:country":"GB",
    "wof:name":"N19 3RB",
    "wof:placetype":"postalcode"
},
  "geometry": {"coordinates":[-0.13359478014351,51.56824471231293],"type":"Point"}
}