{
  "type": "Feature",
  "properties": {
    "date:inception_lower":"1980-01-01",
    "date:inception_upper":"1980-01-31",
    "iso:country":"GB",
    "wof:name":"N19 3RB",
    "wof:placetype":"postalcode"
},
  "geometry": {"coordinates":[-0.133595,51.568245],"type":"Point"}
}