{
  "type": "Feature",
  "properties": {
    "date:inception_lower": "1980-01-01",
    "date:inception_upper": "1980-01-01",
    "iso:country": "GB",
    "wof:name": "MK45 4DR",
    "wof:placetype": "postalcode"
  },
  "geometry": {"coordinates":[-0.42455,52.007562],"type":"Point"}
}
