{
  "type": "Feature",
  "properties": {
    "iso:country":"GB",
    "wof:name":"MK45 4DR",
    "wof:placetype":"postalcode"
},
  "geometry": {"coordinates":[-0.42455009807356,52.00756234925073],"type":"Point"}
}