{
  "type": "Feature",
  "properties": {
    "date:inception_lower": "2020-01-01",
    "date:inception_upper": "2020-01-01",
    "iso:country": "GB",
    "wof:name": "IP9 1QS",
    "wof:placetype": "postalcode"
  },
  "geometry": {"coordinates":[1.273693,51.962806],"type":"Point"}
}
