{
  "type": "Feature",
  "properties": {
    "date:inception_lower": "2011-06-01",
    "date:inception_upper": "2011-06-01",
    "iso:country": "GB",
    "wof:name": "M24 1PJ",
    "wof:placetype": "postalcode"
  },
  "geometry": {"coordinates":[-2.184586,53.534472],"type":"Point"}
}
