{
  "type": "Feature",
  "properties": {
    "iso:country":"GB",
    "wof:name":"HR4 9SA",
    "wof:placetype":"postalcode"
},
  "geometry": {"coordinates":[-2.72161568709403,52.06663548031618],"type":"Point"}
}