{
  "type": "Feature",
  "properties": {
    "iso:country":"GB",
    "wof:name":"CF32 9SA",
    "wof:placetype":"postalcode"
},
  "geometry": {"coordinates":[-3.58276318535613,51.5371567237923],"type":"Point"}
}