{
  "type": "Feature",
  "properties": {
    "iso:country":"GB",
    "wof:name":"HR7 4RW",
    "wof:placetype":"postalcode"
},
  "geometry": {"coordinates":[-2.61804065325312,52.16162612193583],"type":"Point"}
}