{
  "type": "Feature",
  "properties": {
    "iso:country":"GB",
    "wof:name":"EX7 0BS",
    "wof:placetype":"postalcode"
},
  "geometry": {"coordinates":[-3.46314904843023,50.58241111879222],"type":"Point"}
}