{
  "type": "Feature",
  "properties": {
    "iso:country":"GB",
    "wof:name":"NN7 2BS",
    "wof:placetype":"postalcode"
},
  "geometry": {"coordinates":[-0.81632615681815,52.18793331857653],"type":"Point"}
}