{
  "type": "Feature",
  "properties": {
    "date:inception_lower": "2006-07-01",
    "date:inception_upper": "2006-07-01",
    "iso:country": "GB",
    "wof:name": "SN25 2LL",
    "wof:placetype": "postalcode"
  },
  "geometry": {"coordinates":[-1.832732,51.604318],"type":"Point"}
}
