{
  "type": "Feature",
  "properties": {
    "iso:country": "GB",
    "wof:name": "SN25 2LL",
    "wof:placetype": "postalcode"
  },
  "geometry": {"coordinates":[-1.832732,51.604318],"type":"Point"}
}
