{
  "type": "Feature",
  "properties": {
    "iso:country":"GB",
    "wof:name":"WA16 7EQ",
    "wof:placetype":"postalcode"
},
  "geometry": {"coordinates":[-2.33861188774461,53.30343386504554],"type":"Point"}
}