{
  "type": "Feature",
  "properties": {
    "date:inception_lower":"1980-01-01",
    "date:inception_upper":"1980-01-31",
    "iso:country":"GB",
    "wof:name":"WA16 7EQ",
    "wof:placetype":"postalcode"
},
  "geometry": {"coordinates":[-2.338612,53.303434],"type":"Point"}
}