{
  "type": "Feature",
  "properties": {
    "iso:country":"GB",
    "wof:name":"SL3 9QZ",
    "wof:placetype":"postalcode"
},
  "geometry": {"coordinates":[-0.56643455230088,51.47976091153809],"type":"Point"}
}