{
  "type": "Feature",
  "properties": {
    "date:inception_lower":"1985-04-01",
    "date:inception_upper":"1985-04-30",
    "iso:country":"GB",
    "wof:name":"SL3 9QZ",
    "wof:placetype":"postalcode"
},
  "geometry": {"coordinates":[-0.566435,51.479761],"type":"Point"}
}