{
  "type": "Feature",
  "properties": {
    "iso:country":"GB",
    "wof:name":"M41 7AU",
    "wof:placetype":"postalcode"
},
  "geometry": {"coordinates":[-2.36210967158061,53.4537807191927],"type":"Point"}
}