{
  "type": "Feature",
  "properties": {
    "iso:country":"GB",
    "wof:name":"SE20 8SG",
    "wof:placetype":"postalcode"
},
  "geometry": {"coordinates":[-0.0674277246153,51.40764438708895],"type":"Point"}
}