{
  "type": "Feature",
  "properties": {
    "iso:country": "GB",
    "wof:name": "SE20 8SG",
    "wof:placetype": "postalcode"
  },
  "geometry": {"coordinates":[-0.067428,51.407644],"type":"Point"}
}
