{
  "type": "Feature",
  "properties": {
    "date:inception_lower":"2005-01-01",
    "date:inception_upper":"2005-01-31",
    "iso:country":"GB",
    "wof:name":"KT22 9QE",
    "wof:placetype":"postalcode"
},
  "geometry": {"coordinates":[-0.363546,51.29142],"type":"Point"}
}