{
  "type": "Feature",
  "properties": {
    "iso:country": "GB",
    "wof:name": "KT22 9QE",
    "wof:placetype": "postalcode"
  },
  "geometry": {"coordinates":[-0.363546,51.29142],"type":"Point"}
}
