{
  "type": "Feature",
  "properties": {
    "iso:country":"GB",
    "wof:name":"SO19 6NP",
    "wof:placetype":"postalcode"
},
  "geometry": {"coordinates":[-1.3336679875665,50.90521062314766],"type":"Point"}
}