{
  "type": "Feature",
  "properties": {
    "iso:country":"GB",
    "wof:name":"W1K 7HF",
    "wof:placetype":"postalcode"
},
  "geometry": {"coordinates":[-0.15560849136851,51.51060046228775],"type":"Point"}
}