{
  "type": "Feature",
  "properties": {
    "date:inception_lower": "2001-12-01",
    "date:inception_upper": "2001-12-01",
    "iso:country": "GB",
    "wof:name": "SW12 9EE",
    "wof:placetype": "postalcode"
  },
  "geometry": {"coordinates":[-0.148156,51.452059],"type":"Point"}
}
