{
  "type": "Feature",
  "properties": {
    "date:inception_lower":"2001-12-01",
    "date:inception_upper":"2001-12-31",
    "iso:country":"GB",
    "wof:name":"SW12 9EE",
    "wof:placetype":"postalcode"
},
  "geometry": {"coordinates":[-0.148197,51.452032],"type":"Point"}
}