{
  "type": "Feature",
  "properties": {
    "iso:country":"GB",
    "wof:name":"SW12 9EE",
    "wof:placetype":"postalcode"
},
  "geometry": {"coordinates":[-0.148197239544,51.45203215905111],"type":"Point"}
}