{
  "type": "Feature",
  "properties": {
    "iso:country":"GB",
    "wof:name":"SN6 6PH",
    "wof:placetype":"postalcode"
},
  "geometry": {"coordinates":[-1.92597038096305,51.64601622452566],"type":"Point"}
}