{
  "type": "Feature",
  "properties": {
    "iso:country":"GB",
    "wof:name":"W1K 5QZ",
    "wof:placetype":"postalcode"
},
  "geometry": {"coordinates":[-0.14831843357305,51.51374987295407],"type":"Point"}
}