{
  "type": "Feature",
  "properties": {
    "iso:country":"GB",
    "wof:name":"S75 3RW",
    "wof:placetype":"postalcode"
},
  "geometry": {"coordinates":[-1.52676281227122,53.54371050268644],"type":"Point"}
}