{
  "type": "Feature",
  "properties": {
    "iso:country":"GB",
    "wof:name":"CV13 0JD",
    "wof:placetype":"postalcode"
},
  "geometry": {"coordinates":[-1.34963628958622,52.65740031029348],"type":"Point"}
}