{
  "type": "Feature",
  "properties": {
    "iso:country": "GB",
    "wof:name": "NG14 6RA",
    "wof:placetype": "postalcode"
  },
  "geometry": {"coordinates":[-1.057723,53.033467],"type":"Point"}
}
