{
  "type": "Feature",
  "properties": {
    "iso:country":"GB",
    "wof:name":"B64 6RU",
    "wof:placetype":"postalcode"
},
  "geometry": {"coordinates":[-2.05171737974035,52.4725610809093],"type":"Point"}
}