{
  "type": "Feature",
  "properties": {
    "iso:country":"GB",
    "wof:name":"WD25 9SZ",
    "wof:placetype":"postalcode"
},
  "geometry": {"coordinates":[-0.38345543058545,51.68397604461366],"type":"Point"}
}