{
  "type": "Feature",
  "properties": {
    "iso:country":"GB",
    "wof:name":"DE21 7RF",
    "wof:placetype":"postalcode"
},
  "geometry": {"coordinates":[-1.39422140554946,52.92248863691295],"type":"Point"}
}