{
  "type": "Feature",
  "properties": {
    "iso:country": "GB",
    "wof:name": "DE21 7RF",
    "wof:placetype": "postalcode"
  },
  "geometry": {"coordinates":[-1.394221,52.922489],"type":"Point"}
}
