{
  "type": "Feature",
  "properties": {
    "date:inception_lower":"1980-01-01",
    "date:inception_upper":"1980-01-31",
    "iso:country":"GB",
    "wof:name":"G61 2EL",
    "wof:placetype":"postalcode"
},
  "geometry": {"coordinates":[-4.322396,55.91811],"type":"Point"}
}