{
  "type": "Feature",
  "properties": {
    "date:inception_lower": "1980-01-01",
    "date:inception_upper": "1980-01-01",
    "iso:country": "GB",
    "wof:name": "BD17 5QS",
    "wof:placetype": "postalcode"
  },
  "geometry": {"coordinates":[-1.769728,53.842876],"type":"Point"}
}
