{
  "type": "Feature",
  "properties": {
    "iso:country":"GB",
    "wof:name":"HU5 5RU",
    "wof:placetype":"postalcode"
},
  "geometry": {"coordinates":[-0.3992384215374,53.75934852936739],"type":"Point"}
}