{
  "type": "Feature",
  "properties": {
    "iso:country":"GB",
    "wof:name":"RG17 7TD",
    "wof:placetype":"postalcode"
},
  "geometry": {"coordinates":[-1.54606005669133,51.46327519640713],"type":"Point"}
}