{
  "type": "Feature",
  "properties": {
    "iso:country": "GB",
    "wof:name": "RG17 7TD",
    "wof:placetype": "postalcode"
  },
  "geometry": {"coordinates":[-1.54606,51.463275],"type":"Point"}
}
