{
  "type": "Feature",
  "properties": {
    "iso:country":"GB",
    "wof:name":"DA7 4HW",
    "wof:placetype":"postalcode"
},
  "geometry": {"coordinates":[0.1472088907812,51.45794659524231],"type":"Point"}
}