{
  "type": "Feature",
  "properties": {
    "iso:country":"GB",
    "wof:name":"PO15 5RZ",
    "wof:placetype":"postalcode"
},
  "geometry": {"coordinates":[-1.24293940777995,50.85821109119012],"type":"Point"}
}