{
  "type": "Feature",
  "properties": {
    "iso:country":"GB",
    "wof:name":"EX21 5LS",
    "wof:placetype":"postalcode"
},
  "geometry": {"coordinates":[-4.15383506068987,50.81835068347906],"type":"Point"}
}