{
  "type": "Feature",
  "properties": {
    "date:inception_lower": "1980-01-01",
    "date:inception_upper": "1980-01-01",
    "iso:country": "GB",
    "wof:name": "EX21 5LS",
    "wof:placetype": "postalcode"
  },
  "geometry": {"coordinates":[-4.153484,50.818512],"type":"Point"}
}
