{
  "type": "Feature",
  "properties": {
    "iso:country": "GB",
    "wof:name": "TQ10 9HB",
    "wof:placetype": "postalcode"
  },
  "geometry": {"coordinates":[-3.851313,50.403061],"type":"Point"}
}
