{
  "type": "Feature",
  "properties": {
    "date:inception_lower":"1980-01-01",
    "date:inception_upper":"1980-01-31",
    "iso:country":"GB",
    "wof:name":"TQ10 9HB",
    "wof:placetype":"postalcode"
},
  "geometry": {"coordinates":[-3.851313,50.403061],"type":"Point"}
}