{
  "type": "Feature",
  "properties": {
    "iso:country":"GB",
    "wof:name":"TA6 3PW",
    "wof:placetype":"postalcode"
},
  "geometry": {"coordinates":[-3.010671733985,51.12795995456767],"type":"Point"}
}