{
  "type": "Feature",
  "properties": {
    "date:inception_lower": "1980-01-01",
    "date:inception_upper": "1980-01-01",
    "iso:country": "GB",
    "wof:name": "SG9 0JT",
    "wof:placetype": "postalcode"
  },
  "geometry": {"coordinates":[0.104778,51.930556],"type":"Point"}
}
