{
  "type": "Feature",
  "properties": {
    "iso:country": "GB",
    "wof:name": "SG9 0JT",
    "wof:placetype": "postalcode"
  },
  "geometry": {"coordinates":[0.104938,51.930211],"type":"Point"}
}
