{
  "type": "Feature",
  "properties": {
    "iso:country":"GB",
    "wof:name":"SG9 0JT",
    "wof:placetype":"postalcode"
},
  "geometry": {"coordinates":[0.1049374571458,51.93021142527159],"type":"Point"}
}