{
  "type": "Feature",
  "properties": {
    "iso:country":"GB",
    "wof:name":"BS4 4LG",
    "wof:placetype":"postalcode"
},
  "geometry": {"coordinates":[-2.54922371384523,51.4346585980118],"type":"Point"}
}