{
  "type": "Feature",
  "properties": {
    "iso:country": "GB",
    "wof:name": "BS4 4LG",
    "wof:placetype": "postalcode"
  },
  "geometry": {"coordinates":[-2.549224,51.434659],"type":"Point"}
}
