{
  "type": "Feature",
  "properties": {
    "date:inception_lower": "1984-10-01",
    "date:inception_upper": "1984-10-01",
    "iso:country": "GB",
    "wof:name": "BS4 4LG",
    "wof:placetype": "postalcode"
  },
  "geometry": {"coordinates":[-2.549224,51.434659],"type":"Point"}
}
