{
  "type": "Feature",
  "properties": {
    "iso:country":"GB",
    "wof:name":"EH3 6BJ",
    "wof:placetype":"postalcode"
},
  "geometry": {"coordinates":[-3.20744361082115,55.95386684646122],"type":"Point"}
}