{
  "type": "Feature",
  "properties": {
    "date:inception_lower": "1980-01-01",
    "date:inception_upper": "1980-01-01",
    "iso:country": "GB",
    "wof:name": "EH3 6BJ",
    "wof:placetype": "postalcode"
  },
  "geometry": {"coordinates":[-3.207444,55.953867],"type":"Point"}
}
