{
  "type": "Feature",
  "properties": {
    "date:inception_lower": "1985-04-01",
    "date:inception_upper": "1985-04-01",
    "iso:country": "GB",
    "wof:name": "TR15 3QA",
    "wof:placetype": "postalcode"
  },
  "geometry": {"coordinates":[-5.270642,50.229265],"type":"Point"}
}
