{
  "type": "Feature",
  "properties": {
    "iso:country":"GB",
    "wof:name":"TQ10 9NG",
    "wof:placetype":"postalcode"
},
  "geometry": {"coordinates":[-3.8305924140582,50.3886655613007],"type":"Point"}
}