{
  "type": "Feature",
  "properties": {
    "iso:country": "GB",
    "wof:name": "TQ10 9NG",
    "wof:placetype": "postalcode"
  },
  "geometry": {"coordinates":[-3.824984,50.385987],"type":"Point"}
}
