{
  "type": "Feature",
  "properties": {
    "iso:country": "GB",
    "wof:name": "DL8 3DZ",
    "wof:placetype": "postalcode"
  },
  "geometry": {"coordinates":[-2.104982,54.31415],"type":"Point"}
}
