{
  "type": "Feature",
  "properties": {
    "iso:country":"GB",
    "wof:name":"DL8 3DZ",
    "wof:placetype":"postalcode"
},
  "geometry": {"coordinates":[-2.10498154991584,54.31414958432367],"type":"Point"}
}