{
  "type": "Feature",
  "properties": {
    "iso:country":"GB",
    "wof:name":"RG12 0TS",
    "wof:placetype":"postalcode"
},
  "geometry": {"coordinates":[-0.73606593840433,51.39456976030561],"type":"Point"}
}