{
  "type": "Feature",
  "properties": {
    "date:inception_lower": "1995-07-01",
    "date:inception_upper": "1995-07-01",
    "iso:country": "GB",
    "wof:name": "RG12 0TS",
    "wof:placetype": "postalcode"
  },
  "geometry": {"coordinates":[-0.736066,51.39457],"type":"Point"}
}
