{
  "type": "Feature",
  "properties": {
    "iso:country": "GB",
    "wof:name": "S64 9QE",
    "wof:placetype": "postalcode"
  },
  "geometry": {"coordinates":[-1.287156,53.493032],"type":"Point"}
}
