{
  "type": "Feature",
  "properties": {
    "iso:country":"GB",
    "wof:name":"S64 9QE",
    "wof:placetype":"postalcode"
},
  "geometry": {"coordinates":[-1.28715555431465,53.49303174092774],"type":"Point"}
}