{
  "type": "Feature",
  "properties": {
    "iso:country": "GB",
    "wof:name": "TS23 2DR",
    "wof:placetype": "postalcode"
  },
  "geometry": {"coordinates":[-1.288945,54.611009],"type":"Point"}
}
