{
  "type": "Feature",
  "properties": {
    "iso:country":"GB",
    "wof:name":"TS23 2DR",
    "wof:placetype":"postalcode"
},
  "geometry": {"coordinates":[-1.28892980207312,54.61099723688002],"type":"Point"}
}