{
  "type": "Feature",
  "properties": {
    "date:inception_lower": "1980-01-01",
    "date:inception_upper": "1980-01-01",
    "iso:country": "GB",
    "wof:name": "TS23 2DR",
    "wof:placetype": "postalcode"
  },
  "geometry": {"coordinates":[-1.288945,54.611009],"type":"Point"}
}
