{
  "type": "Feature",
  "properties": {
    "iso:country":"GB",
    "wof:name":"TN12 9QW",
    "wof:placetype":"postalcode"
},
  "geometry": {"coordinates":[0.48756859781277,51.17478973775228],"type":"Point"}
}