{
  "type": "Feature",
  "properties": {
    "date:inception_lower": "2016-07-01",
    "date:inception_upper": "2016-07-01",
    "iso:country": "GB",
    "wof:name": "SW4 7EW",
    "wof:placetype": "postalcode"
  },
  "geometry": {"coordinates":[-0.135594,51.460753],"type":"Point"}
}
