{
  "type": "Feature",
  "properties": {
    "iso:country":"GB",
    "wof:name":"TQ4 7DY",
    "wof:placetype":"postalcode"
},
  "geometry": {"coordinates":[-3.58710663853649,50.42282274973597],"type":"Point"}
}