{
  "type": "Feature",
  "properties": {
    "date:inception_lower": "1996-06-01",
    "date:inception_upper": "1996-06-01",
    "iso:country": "GB",
    "wof:name": "AB51 3WX",
    "wof:placetype": "postalcode"
  },
  "geometry": {"coordinates":[-2.389393,57.280774],"type":"Point"}
}
