{
  "type": "Feature",
  "properties": {
    "iso:country":"GB",
    "wof:name":"AB51 3WX",
    "wof:placetype":"postalcode"
},
  "geometry": {"coordinates":[-2.38939349649287,57.2807741400913],"type":"Point"}
}