{
  "type": "Feature",
  "properties": {
    "iso:country":"GB",
    "wof:name":"SW11 1BH",
    "wof:placetype":"postalcode"
},
  "geometry": {"coordinates":[-0.16309956351415,51.45941569750179],"type":"Point"}
}