{
  "type": "Feature",
  "properties": {
    "date:inception_lower": "2012-02-01",
    "date:inception_upper": "2012-02-01",
    "iso:country": "GB",
    "wof:name": "HP20 2FW",
    "wof:placetype": "postalcode"
  },
  "geometry": {"coordinates":[-0.805443,51.826748],"type":"Point"}
}
