{
  "type": "Feature",
  "properties": {
    "date:inception_lower": "1980-01-01",
    "date:inception_upper": "1980-01-01",
    "iso:country": "GB",
    "wof:name": "FK2 7BY",
    "wof:placetype": "postalcode"
  },
  "geometry": {"coordinates":[-3.784751,56.007693],"type":"Point"}
}
