{
  "type": "Feature",
  "properties": {
    "iso:country":"GB",
    "wof:name":"FK2 7BY",
    "wof:placetype":"postalcode"
},
  "geometry": {"coordinates":[-3.78475113253053,56.00769338949084],"type":"Point"}
}