{
  "type": "Feature",
  "properties": {
    "iso:country": "GB",
    "wof:name": "FK2 7BY",
    "wof:placetype": "postalcode"
  },
  "geometry": {"coordinates":[-3.784751,56.007693],"type":"Point"}
}
