{
  "type": "Feature",
  "properties": {
    "date:inception_lower": "1980-01-01",
    "date:inception_upper": "1980-01-01",
    "iso:country": "GB",
    "wof:name": "RH6 7ET",
    "wof:placetype": "postalcode"
  },
  "geometry": {"coordinates":[-0.172255,51.170583],"type":"Point"}
}
