{
  "type": "Feature",
  "properties": {
    "iso:country":"GB",
    "wof:name":"KA15 1DU",
    "wof:placetype":"postalcode"
},
  "geometry": {"coordinates":[-4.63295517995153,55.74960846642266],"type":"Point"}
}