{
  "type": "Feature",
  "properties": {
    "iso:country":"GB",
    "wof:name":"WA15 9QR",
    "wof:placetype":"postalcode"
},
  "geometry": {"coordinates":[-2.34609164117614,53.38397800443649],"type":"Point"}
}