{
  "type": "Feature",
  "properties": {
    "iso:country": "GB",
    "wof:name": "HR6 9PN",
    "wof:placetype": "postalcode"
  },
  "geometry": {"coordinates":[-2.823621,52.278254],"type":"Point"}
}
