{
  "type": "Feature",
  "properties": {
    "iso:country":"GB",
    "wof:name":"HR6 9PN",
    "wof:placetype":"postalcode"
},
  "geometry": {"coordinates":[-2.82362075509364,52.278254017317],"type":"Point"}
}