{
  "type": "Feature",
  "properties": {
    "date:inception_lower": "2008-09-01",
    "date:inception_upper": "2008-09-01",
    "iso:country": "GB",
    "wof:name": "B5 7SU",
    "wof:placetype": "postalcode"
  },
  "geometry": {"coordinates":[-1.905115,52.45406],"type":"Point"}
}
