{
  "type": "Feature",
  "properties": {
    "iso:country":"GB",
    "wof:name":"WN7 1JB",
    "wof:placetype":"postalcode"
},
  "geometry": {"coordinates":[-2.50332567118147,53.50289470042902],"type":"Point"}
}