{
  "type": "Feature",
  "properties": {
    "date:inception_lower":"1993-01-01",
    "date:inception_upper":"1993-01-31",
    "iso:country":"GB",
    "wof:name":"LL18 5TU",
    "wof:placetype":"postalcode"
},
  "geometry": {"coordinates":[-3.514168,53.29573],"type":"Point"}
}