{
  "type": "Feature",
  "properties": {
    "iso:country":"GB",
    "wof:name":"LL18 5TU",
    "wof:placetype":"postalcode"
},
  "geometry": {"coordinates":[-3.51512736175013,53.29611342626153],"type":"Point"}
}