{
  "type": "Feature",
  "properties": {
    "iso:country": "GB",
    "wof:name": "LL18 5TU",
    "wof:placetype": "postalcode"
  },
  "geometry": {"coordinates":[-3.514168,53.29573],"type":"Point"}
}
