{
  "type": "Feature",
  "properties": {
    "iso:country":"GB",
    "wof:name":"CW7 2RE",
    "wof:placetype":"postalcode"
},
  "geometry": {"coordinates":[-2.54691190043024,53.1885191266584],"type":"Point"}
}