{
  "type": "Feature",
  "properties": {
    "iso:country":"GB",
    "wof:name":"LS2 9NS",
    "wof:placetype":"postalcode"
},
  "geometry": {"coordinates":[-1.55174359225047,53.80144519602828],"type":"Point"}
}