{
  "type": "Feature",
  "properties": {
    "date:inception_lower": "1980-01-01",
    "date:inception_upper": "1980-01-01",
    "iso:country": "GB",
    "wof:name": "BN21 1TS",
    "wof:placetype": "postalcode"
  },
  "geometry": {"coordinates":[0.263971,50.781392],"type":"Point"}
}
