{
  "type": "Feature",
  "properties": {
    "iso:country":"GB",
    "wof:name":"UB2 5LL",
    "wof:placetype":"postalcode"
},
  "geometry": {"coordinates":[-0.40090949348716,51.50161204543729],"type":"Point"}
}