{
  "type": "Feature",
  "properties": {
    "date:inception_lower": "2021-06-01",
    "date:inception_upper": "2021-06-01",
    "iso:country": "GB",
    "wof:name": "SE14 6FL",
    "wof:placetype": "postalcode"
  },
  "geometry": {"coordinates":[-0.032956,51.479499],"type":"Point"}
}
