{
  "type": "Feature",
  "properties": {
    "iso:country":"GB",
    "wof:name":"PL3 4QP",
    "wof:placetype":"postalcode"
},
  "geometry": {"coordinates":[-4.14409804117595,50.39444183156598],"type":"Point"}
}