{
  "type": "Feature",
  "properties": {
    "iso:country":"GB",
    "wof:name":"SE4 1AN",
    "wof:placetype":"postalcode"
},
  "geometry": {"coordinates":[-0.03568003764662,51.44921155005528],"type":"Point"}
}