{
  "type": "Feature",
  "properties": {
    "iso:country":"GB",
    "wof:name":"UB2 4JW",
    "wof:placetype":"postalcode"
},
  "geometry": {"coordinates":[-0.36884734674749,51.49164770844732],"type":"Point"}
}