{
  "type": "Feature",
  "properties": {
    "date:inception_lower": "1980-01-01",
    "date:inception_upper": "1980-01-01",
    "iso:country": "GB",
    "wof:name": "UB2 4JW",
    "wof:placetype": "postalcode"
  },
  "geometry": {"coordinates":[-0.368847,51.491648],"type":"Point"}
}
