{
  "type": "Feature",
  "properties": {
    "iso:country": "GB",
    "wof:name": "BS37 5HA",
    "wof:placetype": "postalcode"
  },
  "geometry": {"coordinates":[-2.424986,51.547407],"type":"Point"}
}
