{
  "type": "Feature",
  "properties": {
    "date:inception_lower":"1997-12-01",
    "date:inception_upper":"1997-12-31",
    "iso:country":"GB",
    "wof:name":"BS37 5HA",
    "wof:placetype":"postalcode"
},
  "geometry": {"coordinates":[-2.424986,51.547407],"type":"Point"}
}