{
  "type": "Feature",
  "properties": {
    "iso:country":"GB",
    "wof:name":"W8 6EX",
    "wof:placetype":"postalcode"
},
  "geometry": {"coordinates":[-0.19886088927964,51.49769403989927],"type":"Point"}
}