{
  "type": "Feature",
  "properties": {
    "iso:country":"GB",
    "wof:name":"PR4 0ZH",
    "wof:placetype":"postalcode"
},
  "geometry": {"coordinates":[-2.81509065438925,53.78518309972536],"type":"Point"}
}