{
  "type": "Feature",
  "properties": {
    "date:inception_lower": "1980-01-01",
    "date:inception_upper": "1980-01-01",
    "iso:country": "GB",
    "wof:name": "PR4 0ZH",
    "wof:placetype": "postalcode"
  },
  "geometry": {"coordinates":[-2.815091,53.785183],"type":"Point"}
}
