{
  "type": "Feature",
  "properties": {
    "iso:country":"GB",
    "wof:name":"RG20 8AB",
    "wof:placetype":"postalcode"
},
  "geometry": {"coordinates":[-1.29455866243825,51.50411332324042],"type":"Point"}
}