{
  "type": "Feature",
  "properties": {
    "iso:country": "GB",
    "wof:name": "RG20 8AB",
    "wof:placetype": "postalcode"
  },
  "geometry": {"coordinates":[-1.294559,51.504113],"type":"Point"}
}
