{
  "type": "Feature",
  "properties": {
    "date:inception_lower": "1998-06-01",
    "date:inception_upper": "1998-06-01",
    "iso:country": "GB",
    "wof:name": "E8 1LX",
    "wof:placetype": "postalcode"
  },
  "geometry": {"coordinates":[-0.060173,51.549015],"type":"Point"}
}
