{
  "type": "Feature",
  "properties": {
    "iso:country":"GB",
    "wof:name":"E8 1LX",
    "wof:placetype":"postalcode"
},
  "geometry": {"coordinates":[-0.06017336690547,51.54901485557177],"type":"Point"}
}