{
  "type": "Feature",
  "properties": {
    "date:inception_lower":"1999-06-01",
    "date:inception_upper":"1999-06-30",
    "iso:country":"GB",
    "wof:name":"GU17 0AW",
    "wof:placetype":"postalcode"
},
  "geometry": {"coordinates":[-0.805204,51.328313],"type":"Point"}
}