{
  "type": "Feature",
  "properties": {
    "iso:country": "GB",
    "wof:name": "GU17 0AW",
    "wof:placetype": "postalcode"
  },
  "geometry": {"coordinates":[-0.805204,51.328313],"type":"Point"}
}
