{
  "type": "Feature",
  "properties": {
    "iso:country": "GB",
    "wof:name": "LA6 2RX",
    "wof:placetype": "postalcode"
  },
  "geometry": {"coordinates":[-2.578697,54.210395],"type":"Point"}
}
