{
  "type": "Feature",
  "properties": {
    "iso:country":"GB",
    "wof:name":"LA6 2RX",
    "wof:placetype":"postalcode"
},
  "geometry": {"coordinates":[-2.57869744512606,54.2103948842754],"type":"Point"}
}