{
  "type": "Feature",
  "properties": {
    "date:inception_lower": "2002-05-01",
    "date:inception_upper": "2002-05-01",
    "iso:country": "GB",
    "wof:name": "CH2 3PB",
    "wof:placetype": "postalcode"
  },
  "geometry": {"coordinates":[-2.868208,53.203636],"type":"Point"}
}
