{
  "type": "Feature",
  "properties": {
    "iso:country": "GB",
    "wof:name": "TF7 4JQ",
    "wof:placetype": "postalcode"
  },
  "geometry": {"coordinates":[-2.435641,52.634577],"type":"Point"}
}
