{
  "type": "Feature",
  "properties": {
    "date:inception_lower":"1980-01-01",
    "date:inception_upper":"1980-01-31",
    "iso:country":"GB",
    "wof:name":"TF7 4JQ",
    "wof:placetype":"postalcode"
},
  "geometry": {"coordinates":[-2.435641,52.634577],"type":"Point"}
}