{
  "type": "Feature",
  "properties": {
    "iso:country":"GB",
    "wof:name":"TF7 4JQ",
    "wof:placetype":"postalcode"
},
  "geometry": {"coordinates":[-2.43564136772248,52.63457678014666],"type":"Point"}
}