{
  "type": "Feature",
  "properties": {
    "date:inception_lower": "2007-02-01",
    "date:inception_upper": "2007-02-01",
    "iso:country": "GB",
    "wof:name": "N22 5AF",
    "wof:placetype": "postalcode"
  },
  "geometry": {"coordinates":[-0.108467,51.604882],"type":"Point"}
}
