{
  "type": "Feature",
  "properties": {
    "iso:country":"GB",
    "wof:name":"N22 5AF",
    "wof:placetype":"postalcode"
},
  "geometry": {"coordinates":[-0.10846709797536,51.60488221564969],"type":"Point"}
}