{
  "type": "Feature",
  "properties": {
    "iso:country":"GB",
    "wof:name":"IP11 2LF",
    "wof:placetype":"postalcode"
},
  "geometry": {"coordinates":[1.32911770113174,51.96295377411226],"type":"Point"}
}