{
  "type": "Feature",
  "properties": {
    "date:inception_lower":"1980-01-01",
    "date:inception_upper":"1980-01-31",
    "iso:country":"GB",
    "wof:name":"PH2 7ES",
    "wof:placetype":"postalcode"
},
  "geometry": {"coordinates":[-3.417805,56.402813],"type":"Point"}
}