{
  "type": "Feature",
  "properties": {
    "iso:country":"GB",
    "wof:name":"HR9 5SB",
    "wof:placetype":"postalcode"
},
  "geometry": {"coordinates":[-2.59870553601837,51.88166310687225],"type":"Point"}
}