{
  "type": "Feature",
  "properties": {
    "date:inception_lower":"1980-01-01",
    "date:inception_upper":"1980-01-31",
    "iso:country":"GB",
    "wof:name":"HR9 5SB",
    "wof:placetype":"postalcode"
},
  "geometry": {"coordinates":[-2.598705,51.881663],"type":"Point"}
}