{
  "type": "Feature",
  "properties": {
    "iso:country": "GB",
    "wof:name": "HR9 5SB",
    "wof:placetype": "postalcode"
  },
  "geometry": {"coordinates":[-2.598705,51.881663],"type":"Point"}
}
