{
  "type": "Feature",
  "properties": {
    "iso:country":"GB",
    "wof:name":"UB6 8SA",
    "wof:placetype":"postalcode"
},
  "geometry": {"coordinates":[-0.34616252851053,51.5309680082304],"type":"Point"}
}