{
  "type": "Feature",
  "properties": {
    "iso:country": "GB",
    "wof:name": "UB6 8SA",
    "wof:placetype": "postalcode"
  },
  "geometry": {"coordinates":[-0.346162,51.530968],"type":"Point"}
}
