{
  "type": "Feature",
  "properties": {
    "iso:country": "GB",
    "wof:name": "EH23 4HZ",
    "wof:placetype": "postalcode"
  },
  "geometry": {"coordinates":[-3.045502,55.83763],"type":"Point"}
}
