{
  "type": "Feature",
  "properties": {
    "iso:country": "GB",
    "wof:name": "SA4 4XW",
    "wof:placetype": "postalcode"
  },
  "geometry": {"coordinates":[-4.05061,51.67332],"type":"Point"}
}
