{
  "type": "Feature",
  "properties": {
    "iso:country":"GB",
    "wof:name":"SA4 4XW",
    "wof:placetype":"postalcode"
},
  "geometry": {"coordinates":[-4.05089820358816,51.67342657302391],"type":"Point"}
}