{
  "type": "Feature",
  "properties": {
    "iso:country":"GB",
    "wof:name":"BL2 6EY",
    "wof:placetype":"postalcode"
},
  "geometry": {"coordinates":[-2.39415422327748,53.57226382910777],"type":"Point"}
}