{
  "type": "Feature",
  "properties": {
    "iso:country":"GB",
    "wof:name":"CO5 8LF",
    "wof:placetype":"postalcode"
},
  "geometry": {"coordinates":[0.90952015091894,51.7823156268555],"type":"Point"}
}