{
  "type": "Feature",
  "properties": {
    "iso:country":"GB",
    "wof:name":"SY3 9EX",
    "wof:placetype":"postalcode"
},
  "geometry": {"coordinates":[-2.75954725113773,52.69157445382498],"type":"Point"}
}