{
  "type": "Feature",
  "properties": {
    "date:inception_lower": "1993-01-01",
    "date:inception_upper": "1993-01-01",
    "iso:country": "GB",
    "wof:name": "SY3 9EX",
    "wof:placetype": "postalcode"
  },
  "geometry": {"coordinates":[-2.759944,52.691523],"type":"Point"}
}
