{
  "type": "Feature",
  "properties": {
    "date:inception_lower": "1995-07-01",
    "date:inception_upper": "1995-07-01",
    "iso:country": "GB",
    "wof:name": "S73 9NR",
    "wof:placetype": "postalcode"
  },
  "geometry": {"coordinates":[-1.387387,53.537236],"type":"Point"}
}
