{
  "type": "Feature",
  "properties": {
    "iso:country": "GB",
    "wof:name": "SA16 0RN",
    "wof:placetype": "postalcode"
  },
  "geometry": {"coordinates":[-4.239957,51.690096],"type":"Point"}
}
