{
  "type": "Feature",
  "properties": {
    "iso:country":"GB",
    "wof:name":"SA16 0RN",
    "wof:placetype":"postalcode"
},
  "geometry": {"coordinates":[-4.23993346861396,51.69008881986222],"type":"Point"}
}