{
  "type": "Feature",
  "properties": {
    "iso:country":"GB",
    "wof:name":"EX15 3AE",
    "wof:placetype":"postalcode"
},
  "geometry": {"coordinates":[-3.32836603291963,50.90687941658211],"type":"Point"}
}