{
  "type": "Feature",
  "properties": {
    "date:inception_lower": "1993-08-01",
    "date:inception_upper": "1993-08-01",
    "iso:country": "GB",
    "wof:name": "SG5 3NE",
    "wof:placetype": "postalcode"
  },
  "geometry": {"coordinates":[-0.361394,51.99387],"type":"Point"}
}
