{
  "type": "Feature",
  "properties": {
    "iso:country":"GB",
    "wof:name":"SG5 3NE",
    "wof:placetype":"postalcode"
},
  "geometry": {"coordinates":[-0.36139413042423,51.9938697571158],"type":"Point"}
}