{
  "type": "Feature",
  "properties": {
    "iso:country":"GB",
    "wof:name":"GL1 5NE",
    "wof:placetype":"postalcode"
},
  "geometry": {"coordinates":[-2.25612360033737,51.84608135932408],"type":"Point"}
}