{
  "type": "Feature",
  "properties": {
    "iso:country":"GB",
    "wof:name":"TS23 3SB",
    "wof:placetype":"postalcode"
},
  "geometry": {"coordinates":[-1.28429467667524,54.62367749100738],"type":"Point"}
}