{
  "type": "Feature",
  "properties": {
    "iso:country":"GB",
    "wof:name":"CB23 7PA",
    "wof:placetype":"postalcode"
},
  "geometry": {"coordinates":[-0.02262274435652,52.21103733880398],"type":"Point"}
}