{
  "type": "Feature",
  "properties": {
    "iso:country":"GB",
    "wof:name":"LS16 8AA",
    "wof:placetype":"postalcode"
},
  "geometry": {"coordinates":[-1.59151039398889,53.84810894410134],"type":"Point"}
}