{
  "type": "Feature",
  "properties": {
    "date:inception_lower":"1980-01-01",
    "date:inception_upper":"1980-01-31",
    "iso:country":"GB",
    "wof:name":"S73 0QG",
    "wof:placetype":"postalcode"
},
  "geometry": {"coordinates":[-1.415563,53.507202],"type":"Point"}
}