{
  "type": "Feature",
  "properties": {
    "iso:country":"GB",
    "wof:name":"S73 0QG",
    "wof:placetype":"postalcode"
},
  "geometry": {"coordinates":[-1.4155630168095,53.50720210087795],"type":"Point"}
}