{
  "type": "Feature",
  "properties": {
    "iso:country": "GB",
    "wof:name": "CB21 4AQ",
    "wof:placetype": "postalcode"
  },
  "geometry": {"coordinates":[0.269695,52.150299],"type":"Point"}
}
