{
  "type": "Feature",
  "properties": {
    "iso:country": "GB",
    "wof:name": "RG7 1XP",
    "wof:placetype": "postalcode"
  },
  "geometry": {"coordinates":[-0.946584,51.365071],"type":"Point"}
}
