{
  "type": "Feature",
  "properties": {
    "iso:country":"GB",
    "wof:name":"DE74 2PF",
    "wof:placetype":"postalcode"
},
  "geometry": {"coordinates":[-1.33192637443569,52.84335282368599],"type":"Point"}
}