{
  "type": "Feature",
  "properties": {
    "iso:country": "GB",
    "wof:name": "FK7 7DF",
    "wof:placetype": "postalcode"
  },
  "geometry": {"coordinates":[-3.864879,56.080097],"type":"Point"}
}
