{
  "type": "Feature",
  "properties": {
    "iso:country":"GB",
    "wof:name":"FK7 7DF",
    "wof:placetype":"postalcode"
},
  "geometry": {"coordinates":[-3.86487934903836,56.08009700221713],"type":"Point"}
}