{
  "type": "Feature",
  "properties": {
    "iso:country":"GB",
    "wof:name":"SN3 3AR",
    "wof:placetype":"postalcode"
},
  "geometry": {"coordinates":[-1.76040589600594,51.56045888895466],"type":"Point"}
}