{
  "type": "Feature",
  "properties": {
    "iso:country":"GB",
    "wof:name":"DH4 4QW",
    "wof:placetype":"postalcode"
},
  "geometry": {"coordinates":[-1.49338636933929,54.86733586563337],"type":"Point"}
}