{
  "type": "Feature",
  "properties": {
    "date:inception_lower":"1980-01-01",
    "date:inception_upper":"1980-01-31",
    "iso:country":"GB",
    "wof:name":"LA11 7AH",
    "wof:placetype":"postalcode"
},
  "geometry": {"coordinates":[-2.923832,54.181009],"type":"Point"}
}