{
  "type": "Feature",
  "properties": {
    "iso:country": "GB",
    "wof:name": "LA11 7AH",
    "wof:placetype": "postalcode"
  },
  "geometry": {"coordinates":[-2.923832,54.181009],"type":"Point"}
}
