{
  "type": "Feature",
  "properties": {
    "iso:country":"GB",
    "wof:name":"LA11 7AH",
    "wof:placetype":"postalcode"
},
  "geometry": {"coordinates":[-2.92383202556855,54.18100945284452],"type":"Point"}
}