{
  "type": "Feature",
  "properties": {
    "date:inception_lower": "2022-03-01",
    "date:inception_upper": "2022-03-01",
    "iso:country": "GB",
    "wof:name": "ST7 2EX",
    "wof:placetype": "postalcode"
  },
  "geometry": {"coordinates":[-2.323462,53.099624],"type":"Point"}
}
