{
  "type": "Feature",
  "properties": {
    "iso:country":"GB",
    "wof:name":"CV32 5ES",
    "wof:placetype":"postalcode"
},
  "geometry": {"coordinates":[-1.53859399697329,52.28925394403073],"type":"Point"}
}