{
  "type": "Feature",
  "properties": {
    "iso:country":"GB",
    "wof:name":"IP9 2DB",
    "wof:placetype":"postalcode"
},
  "geometry": {"coordinates":[1.08486219886092,51.98874178014422],"type":"Point"}
}