{
  "type": "Feature",
  "properties": {
    "iso:country": "GB",
    "wof:name": "IP9 2DB",
    "wof:placetype": "postalcode"
  },
  "geometry": {"coordinates":[1.084446,51.988829],"type":"Point"}
}
