{
  "type": "Feature",
  "properties": {
    "iso:country":"GB",
    "wof:name":"SK10 2EU",
    "wof:placetype":"postalcode"
},
  "geometry": {"coordinates":[-2.12555977967303,53.2679568096206],"type":"Point"}
}