{
  "type": "Feature",
  "properties": {
    "iso:country":"GB",
    "wof:name":"RG45 7LP",
    "wof:placetype":"postalcode"
},
  "geometry": {"coordinates":[-0.80179240882018,51.36778031410986],"type":"Point"}
}