{
  "type": "Feature",
  "properties": {
    "iso:country":"GB",
    "wof:name":"PL26 7PT",
    "wof:placetype":"postalcode"
},
  "geometry": {"coordinates":[-4.89825054543275,50.37281349744086],"type":"Point"}
}