{
  "type": "Feature",
  "properties": {
    "iso:country":"GB",
    "wof:name":"TS21 1QE",
    "wof:placetype":"postalcode"
},
  "geometry": {"coordinates":[-1.39096597057753,54.58905001978349],"type":"Point"}
}