{
  "type": "Feature",
  "properties": {
    "iso:country":"GB",
    "wof:name":"NN3 8UP",
    "wof:placetype":"postalcode"
},
  "geometry": {"coordinates":[-0.83623178483505,52.27318427932074],"type":"Point"}
}