{
  "type": "Feature",
  "properties": {
    "iso:country": "GB",
    "wof:name": "CF44 9EN",
    "wof:placetype": "postalcode"
  },
  "geometry": {"coordinates":[-3.487087,51.732644],"type":"Point"}
}
