{
  "type": "Feature",
  "properties": {
    "date:inception_lower":"2002-08-01",
    "date:inception_upper":"2002-08-31",
    "iso:country":"GB",
    "wof:name":"DE15 0JZ",
    "wof:placetype":"postalcode"
},
  "geometry": {"coordinates":[-1.612513,52.807176],"type":"Point"}
}