{
  "type": "Feature",
  "properties": {
    "iso:country":"GB",
    "wof:name":"SM5 2BA",
    "wof:placetype":"postalcode"
},
  "geometry": {"coordinates":[-0.16295806788436,51.37936125617362],"type":"Point"}
}