{
  "type": "Feature",
  "properties": {
    "date:inception_lower":"1980-01-01",
    "date:inception_upper":"1980-01-31",
    "iso:country":"GB",
    "wof:name":"OL15 8DY",
    "wof:placetype":"postalcode"
},
  "geometry": {"coordinates":[-2.102736,53.646007],"type":"Point"}
}