{
  "type": "Feature",
  "properties": {
    "date:inception_lower":"2011-02-01",
    "date:inception_upper":"2011-02-28",
    "iso:country":"GB",
    "wof:name":"SN2 5DN",
    "wof:placetype":"postalcode"
},
  "geometry": {"coordinates":[-1.778176,51.593456],"type":"Point"}
}