{
  "type": "Feature",
  "properties": {
    "iso:country":"GB",
    "wof:name":"SN2 5DN",
    "wof:placetype":"postalcode"
},
  "geometry": {"coordinates":[-1.77817613326299,51.59345610913543],"type":"Point"}
}