{
  "type": "Feature",
  "properties": {
    "iso:country": "GB",
    "wof:name": "SN2 5DN",
    "wof:placetype": "postalcode"
  },
  "geometry": {"coordinates":[-1.778176,51.593456],"type":"Point"}
}
