{
  "type": "Feature",
  "properties": {
    "date:inception_lower":"2005-11-01",
    "date:inception_upper":"2005-11-30",
    "iso:country":"GB",
    "wof:name":"GL3 4AG",
    "wof:placetype":"postalcode"
},
  "geometry": {"coordinates":[-2.16611,51.838871],"type":"Point"}
}