{
  "type": "Feature",
  "properties": {
    "date:inception_lower": "1994-09-01",
    "date:inception_upper": "1994-09-01",
    "iso:country": "GB",
    "wof:name": "DG2 0NW",
    "wof:placetype": "postalcode"
  },
  "geometry": {"coordinates":[-3.628228,55.077],"type":"Point"}
}
