{
  "type": "Feature",
  "properties": {
    "iso:country":"GB",
    "wof:name":"B74 2SE",
    "wof:placetype":"postalcode"
},
  "geometry": {"coordinates":[-1.83365458308274,52.57580381929043],"type":"Point"}
}