{
  "type": "Feature",
  "properties": {
    "iso:country": "GB",
    "wof:name": "CT3 4JS",
    "wof:placetype": "postalcode"
  },
  "geometry": {"coordinates":[1.152277,51.333984],"type":"Point"}
}
