{
  "type": "Feature",
  "properties": {
    "date:inception_lower": "1980-01-01",
    "date:inception_upper": "1980-01-01",
    "iso:country": "GB",
    "wof:name": "LA9 4SJ",
    "wof:placetype": "postalcode"
  },
  "geometry": {"coordinates":[-2.751861,54.33388],"type":"Point"}
}
