{
  "type": "Feature",
  "properties": {
    "iso:country":"GB",
    "wof:name":"CV37 6UW",
    "wof:placetype":"postalcode"
},
  "geometry": {"coordinates":[-1.702602082444,52.1997960433003],"type":"Point"}
}