{
  "type": "Feature",
  "properties": {
    "iso:country":"GB",
    "wof:name":"LS16 8PB",
    "wof:placetype":"postalcode"
},
  "geometry": {"coordinates":[-1.5744400658143,53.84067953129249],"type":"Point"}
}