{
  "type": "Feature",
  "properties": {
    "date:inception_lower":"2001-06-01",
    "date:inception_upper":"2001-06-30",
    "iso:country":"GB",
    "wof:name":"LS16 8PB",
    "wof:placetype":"postalcode"
},
  "geometry": {"coordinates":[-1.574445,53.840695],"type":"Point"}
}