{
  "type": "Feature",
  "properties": {
    "iso:country":"GB",
    "wof:name":"NW5 4JU",
    "wof:placetype":"postalcode"
},
  "geometry": {"coordinates":[-0.15773924374786,51.55208020672641],"type":"Point"}
}