{
  "type": "Feature",
  "properties": {
    "iso:country":"GB",
    "wof:name":"WR13 6PS",
    "wof:placetype":"postalcode"
},
  "geometry": {"coordinates":[-2.34449993558786,52.08705132737495],"type":"Point"}
}