{
  "type": "Feature",
  "properties": {
    "date:inception_lower": "1980-01-01",
    "date:inception_upper": "1980-01-01",
    "iso:country": "GB",
    "wof:name": "WR13 6PS",
    "wof:placetype": "postalcode"
  },
  "geometry": {"coordinates":[-2.3445,52.087051],"type":"Point"}
}
