{
  "type": "Feature",
  "properties": {
    "iso:country":"GB",
    "wof:name":"RH1 1JG",
    "wof:placetype":"postalcode"
},
  "geometry": {"coordinates":[-0.17161050553754,51.24431757195804],"type":"Point"}
}