{
  "type": "Feature",
  "properties": {
    "date:inception_lower":"1980-01-01",
    "date:inception_upper":"1980-01-31",
    "iso:country":"GB",
    "wof:name":"CO15 3QE",
    "wof:placetype":"postalcode"
},
  "geometry": {"coordinates":[1.152995,51.79824],"type":"Point"}
}