{
  "type": "Feature",
  "properties": {
    "iso:country": "GB",
    "wof:name": "CO15 3QE",
    "wof:placetype": "postalcode"
  },
  "geometry": {"coordinates":[1.152995,51.79824],"type":"Point"}
}
