{
  "type": "Feature",
  "properties": {
    "iso:country":"GB",
    "wof:name":"N17 6AP",
    "wof:placetype":"postalcode"
},
  "geometry": {"coordinates":[-0.0946609754988,51.59074760330232],"type":"Point"}
}