{
  "type": "Feature",
  "properties": {
    "iso:country":"GB",
    "wof:name":"N7 9DH",
    "wof:placetype":"postalcode"
},
  "geometry": {"coordinates":[-0.11922606692948,51.54439206199104],"type":"Point"}
}