{
  "type": "Feature",
  "properties": {
    "iso:country":"GB",
    "wof:name":"EX1 3UX",
    "wof:placetype":"postalcode"
},
  "geometry": {"coordinates":[-3.46452314818185,50.74760134107235],"type":"Point"}
}