{
  "type": "Feature",
  "properties": {
    "iso:country": "GB",
    "wof:name": "EX1 3UX",
    "wof:placetype": "postalcode"
  },
  "geometry": {"coordinates":[-3.464537,50.747591],"type":"Point"}
}
