{
  "type": "Feature",
  "properties": {
    "iso:country":"GB",
    "wof:name":"BS7 0JW",
    "wof:placetype":"postalcode"
},
  "geometry": {"coordinates":[-2.57754387775613,51.49578234102698],"type":"Point"}
}