{
  "type": "Feature",
  "properties": {
    "iso:country":"GB",
    "wof:name":"NP19 4LG",
    "wof:placetype":"postalcode"
},
  "geometry": {"coordinates":[-2.95416376286497,51.58116206704417],"type":"Point"}
}