{
  "type": "Feature",
  "properties": {
    "iso:country": "GB",
    "wof:name": "NP19 4LG",
    "wof:placetype": "postalcode"
  },
  "geometry": {"coordinates":[-2.954164,51.581162],"type":"Point"}
}
