{
  "type": "Feature",
  "properties": {
    "date:inception_lower":"1999-06-01",
    "date:inception_upper":"1999-06-30",
    "iso:country":"GB",
    "wof:name":"NP19 4LG",
    "wof:placetype":"postalcode"
},
  "geometry": {"coordinates":[-2.954164,51.581162],"type":"Point"}
}