{
  "type": "Feature",
  "properties": {
    "iso:country":"GB",
    "wof:name":"DD11 4SB",
    "wof:placetype":"postalcode"
},
  "geometry": {"coordinates":[-2.67053234982844,56.62440106714283],"type":"Point"}
}