{
  "type": "Feature",
  "properties": {
    "iso:country": "GB",
    "wof:name": "LS22 5BL",
    "wof:placetype": "postalcode"
  },
  "geometry": {"coordinates":[-1.413272,53.908084],"type":"Point"}
}
