{
  "type": "Feature",
  "properties": {
    "iso:country": "GB",
    "wof:name": "HR6 8BL",
    "wof:placetype": "postalcode"
  },
  "geometry": {"coordinates":[-2.738425,52.23204],"type":"Point"}
}
