{
  "type": "Feature",
  "properties": {
    "iso:country":"GB",
    "wof:name":"HR6 8BL",
    "wof:placetype":"postalcode"
},
  "geometry": {"coordinates":[-2.73842546569948,52.2320401727346],"type":"Point"}
}