{
  "type": "Feature",
  "properties": {
    "iso:country":"GB",
    "wof:name":"DA11 7PB",
    "wof:placetype":"postalcode"
},
  "geometry": {"coordinates":[0.36410625579021,51.41702605952167],"type":"Point"}
}