{
  "type": "Feature",
  "properties": {
    "date:inception_lower": "1980-01-01",
    "date:inception_upper": "1980-01-01",
    "iso:country": "GB",
    "wof:name": "DD4 6PS",
    "wof:placetype": "postalcode"
  },
  "geometry": {"coordinates":[-2.955956,56.47149],"type":"Point"}
}
