{
  "type": "Feature",
  "properties": {
    "iso:country": "GB",
    "wof:name": "DD4 6PS",
    "wof:placetype": "postalcode"
  },
  "geometry": {"coordinates":[-2.955956,56.47149],"type":"Point"}
}
