{
  "type": "Feature",
  "properties": {
    "date:inception_lower": "1992-08-01",
    "date:inception_upper": "1992-08-01",
    "iso:country": "GB",
    "wof:name": "SW20 8JD",
    "wof:placetype": "postalcode"
  },
  "geometry": {"coordinates":[-0.222319,51.413603],"type":"Point"}
}
