{
  "type": "Feature",
  "properties": {
    "iso:country": "GB",
    "wof:name": "SW20 8JD",
    "wof:placetype": "postalcode"
  },
  "geometry": {"coordinates":[-0.222376,51.413631],"type":"Point"}
}
