{
  "type": "Feature",
  "properties": {
    "iso:country":"GB",
    "wof:name":"SW20 8JD",
    "wof:placetype":"postalcode"
},
  "geometry": {"coordinates":[-0.2224554844351,51.41368644356879],"type":"Point"}
}