{
  "type": "Feature",
  "properties": {
    "iso:country":"GB",
    "wof:name":"SA43 1JJ",
    "wof:placetype":"postalcode"
},
  "geometry": {"coordinates":[-4.66122867030915,52.0832985941213],"type":"Point"}
}