{
  "type": "Feature",
  "properties": {
    "date:inception_lower":"1980-01-01",
    "date:inception_upper":"1980-01-31",
    "iso:country":"GB",
    "wof:name":"SA43 1JJ",
    "wof:placetype":"postalcode"
},
  "geometry": {"coordinates":[-4.661229,52.083299],"type":"Point"}
}