{
  "type": "Feature",
  "properties": {
    "iso:country":"GB",
    "wof:name":"PL17 7NT",
    "wof:placetype":"postalcode"
},
  "geometry": {"coordinates":[-4.4044615261606,50.53418808692596],"type":"Point"}
}