{
  "type": "Feature",
  "properties": {
    "date:inception_lower": "2006-02-01",
    "date:inception_upper": "2006-02-01",
    "iso:country": "GB",
    "wof:name": "B23 6GD",
    "wof:placetype": "postalcode"
  },
  "geometry": {"coordinates":[-1.85421,52.522404],"type":"Point"}
}
