{
  "type": "Feature",
  "properties": {
    "iso:country":"GB",
    "wof:name":"NG2 4FU",
    "wof:placetype":"postalcode"
},
  "geometry": {"coordinates":[-1.12331205414301,52.95083329857808],"type":"Point"}
}