{
  "type": "Feature",
  "properties": {
    "iso:country": "GB",
    "wof:name": "GU15 4PA",
    "wof:placetype": "postalcode"
  },
  "geometry": {"coordinates":[-0.77487,51.342531],"type":"Point"}
}
