{
  "type": "Feature",
  "properties": {
    "iso:country":"GB",
    "wof:name":"HG2 9HU",
    "wof:placetype":"postalcode"
},
  "geometry": {"coordinates":[-1.53083084324683,53.96915165570123],"type":"Point"}
}