{
  "type": "Feature",
  "properties": {
    "iso:country": "GB",
    "wof:name": "KT18 5JP",
    "wof:placetype": "postalcode"
  },
  "geometry": {"coordinates":[-0.25464,51.32259],"type":"Point"}
}
