{
  "type": "Feature",
  "properties": {
    "iso:country": "GB",
    "wof:name": "G67 2JU",
    "wof:placetype": "postalcode"
  },
  "geometry": {"coordinates":[-3.982028,55.947901],"type":"Point"}
}
