{
  "type": "Feature",
  "properties": {
    "iso:country":"GB",
    "wof:name":"G67 2JU",
    "wof:placetype":"postalcode"
},
  "geometry": {"coordinates":[-3.98202769159524,55.94790143524052],"type":"Point"}
}