{
  "type": "Feature",
  "properties": {
    "date:inception_lower": "1980-01-01",
    "date:inception_upper": "1980-01-01",
    "iso:country": "GB",
    "wof:name": "G67 2JU",
    "wof:placetype": "postalcode"
  },
  "geometry": {"coordinates":[-3.982028,55.947901],"type":"Point"}
}
