{
  "type": "Feature",
  "properties": {
    "iso:country": "GB",
    "wof:name": "DE24 8NB",
    "wof:placetype": "postalcode"
  },
  "geometry": {"coordinates":[-1.453266,52.902773],"type":"Point"}
}
