{
  "type": "Feature",
  "properties": {
    "date:inception_lower": "1980-01-01",
    "date:inception_upper": "1980-01-01",
    "iso:country": "GB",
    "wof:name": "PO2 9HU",
    "wof:placetype": "postalcode"
  },
  "geometry": {"coordinates":[-1.076366,50.823694],"type":"Point"}
}
