{
  "type": "Feature",
  "properties": {
    "iso:country": "GB",
    "wof:name": "ST19 9LR",
    "wof:placetype": "postalcode"
  },
  "geometry": {"coordinates":[-2.163855,52.687978],"type":"Point"}
}
