{
  "type": "Feature",
  "properties": {
    "date:inception_lower":"1983-07-01",
    "date:inception_upper":"1983-07-31",
    "iso:country":"GB",
    "wof:name":"SK9 5QN",
    "wof:placetype":"postalcode"
},
  "geometry": {"coordinates":[-2.236062,53.325155],"type":"Point"}
}