{
  "type": "Feature",
  "properties": {
    "iso:country": "GB",
    "wof:name": "SK9 5QN",
    "wof:placetype": "postalcode"
  },
  "geometry": {"coordinates":[-2.236062,53.325155],"type":"Point"}
}
