{
  "type": "Feature",
  "properties": {
    "iso:country":"GB",
    "wof:name":"CH47 3AQ",
    "wof:placetype":"postalcode"
},
  "geometry": {"coordinates":[-3.17408825725711,53.39819284064622],"type":"Point"}
}