{
  "type": "Feature",
  "properties": {
    "iso:country": "GB",
    "wof:name": "CH47 3AQ",
    "wof:placetype": "postalcode"
  },
  "geometry": {"coordinates":[-3.174088,53.398193],"type":"Point"}
}
