{
  "type": "Feature",
  "properties": {
    "iso:country": "GB",
    "wof:name": "TN6 1UG",
    "wof:placetype": "postalcode"
  },
  "geometry": {"coordinates":[0.14652,51.047842],"type":"Point"}
}
