{
  "type": "Feature",
  "properties": {
    "date:inception_lower":"2010-08-01",
    "date:inception_upper":"2010-08-31",
    "iso:country":"GB",
    "wof:name":"B77 2TP",
    "wof:placetype":"postalcode"
},
  "geometry": {"coordinates":[-1.678653,52.612514],"type":"Point"}
}