{
  "type": "Feature",
  "properties": {
    "iso:country": "GB",
    "wof:name": "B77 2TP",
    "wof:placetype": "postalcode"
  },
  "geometry": {"coordinates":[-1.678653,52.612514],"type":"Point"}
}
