{
  "type": "Feature",
  "properties": {
    "iso:country":"GB",
    "wof:name":"SG6 2EG",
    "wof:placetype":"postalcode"
},
  "geometry": {"coordinates":[-0.21862486961346,51.97322887844962],"type":"Point"}
}