{
  "type": "Feature",
  "properties": {
    "iso:country":"GB",
    "wof:name":"TS7 0QA",
    "wof:placetype":"postalcode"
},
  "geometry": {"coordinates":[-1.18040177127733,54.52337024380908],"type":"Point"}
}