{
  "type": "Feature",
  "properties": {
    "date:inception_lower":"2001-12-01",
    "date:inception_upper":"2001-12-31",
    "iso:country":"GB",
    "wof:name":"FK9 5GE",
    "wof:placetype":"postalcode"
},
  "geometry": {"coordinates":[-3.944078,56.137757],"type":"Point"}
}