{
  "type": "Feature",
  "properties": {
    "iso:country":"GB",
    "wof:name":"FK9 5GE",
    "wof:placetype":"postalcode"
},
  "geometry": {"coordinates":[-3.94405366625962,56.13776352490922],"type":"Point"}
}