{
  "type": "Feature",
  "properties": {
    "date:inception_lower": "2022-10-01",
    "date:inception_upper": "2022-10-01",
    "iso:country": "GB",
    "wof:name": "OL9 9GN",
    "wof:placetype": "postalcode"
  },
  "geometry": {"coordinates":[-2.152886,53.539027],"type":"Point"}
}
