{
  "type": "Feature",
  "properties": {
    "date:inception_lower": "1999-06-01",
    "date:inception_upper": "1999-06-01",
    "iso:country": "GB",
    "wof:name": "KT24 6ES",
    "wof:placetype": "postalcode"
  },
  "geometry": {"coordinates":[-0.455042,51.2409],"type":"Point"}
}
