{
  "type": "Feature",
  "properties": {
    "date:inception_lower": "1980-01-01",
    "date:inception_upper": "1980-01-01",
    "iso:country": "GB",
    "wof:name": "SN12 8HJ",
    "wof:placetype": "postalcode"
  },
  "geometry": {"coordinates":[-2.181096,51.395155],"type":"Point"}
}
