{
  "type": "Feature",
  "properties": {
    "iso:country": "GB",
    "wof:name": "DH3 4NQ",
    "wof:placetype": "postalcode"
  },
  "geometry": {"coordinates":[-1.542088,54.838826],"type":"Point"}
}
