{
  "type": "Feature",
  "properties": {
    "iso:country":"GB",
    "wof:name":"WD3 9UJ",
    "wof:placetype":"postalcode"
},
  "geometry": {"coordinates":[-0.51819928224626,51.61937466278599],"type":"Point"}
}