{
  "type": "Feature",
  "properties": {
    "iso:country": "GB",
    "wof:name": "WD3 9UJ",
    "wof:placetype": "postalcode"
  },
  "geometry": {"coordinates":[-0.518199,51.619375],"type":"Point"}
}
