{
  "type": "Feature",
  "properties": {
    "iso:country": "GB",
    "wof:name": "LA4 5SZ",
    "wof:placetype": "postalcode"
  },
  "geometry": {"coordinates":[-2.857278,54.069397],"type":"Point"}
}
