{
  "type": "Feature",
  "properties": {
    "date:inception_lower":"1980-01-01",
    "date:inception_upper":"1980-01-31",
    "iso:country":"GB",
    "wof:name":"LA4 5SZ",
    "wof:placetype":"postalcode"
},
  "geometry": {"coordinates":[-2.857278,54.069397],"type":"Point"}
}