{
  "type": "Feature",
  "properties": {
    "iso:country":"GB",
    "wof:name":"LA4 5SZ",
    "wof:placetype":"postalcode"
},
  "geometry": {"coordinates":[-2.85727780190691,54.0693971278241],"type":"Point"}
}