{
  "type": "Feature",
  "properties": {
    "iso:country":"GB",
    "wof:name":"TA5 2QF",
    "wof:placetype":"postalcode"
},
  "geometry": {"coordinates":[-3.07772222482835,51.16166690948942],"type":"Point"}
}