{
  "type": "Feature",
  "properties": {
    "date:inception_lower": "1980-01-01",
    "date:inception_upper": "1980-01-01",
    "iso:country": "GB",
    "wof:name": "OL11 2HN",
    "wof:placetype": "postalcode"
  },
  "geometry": {"coordinates":[-2.148535,53.601395],"type":"Point"}
}
