{
  "type": "Feature",
  "properties": {
    "iso:country": "GB",
    "wof:name": "OL11 2HN",
    "wof:placetype": "postalcode"
  },
  "geometry": {"coordinates":[-2.148535,53.601395],"type":"Point"}
}
