{
  "type": "Feature",
  "properties": {
    "iso:country": "GB",
    "wof:name": "BS6 5DJ",
    "wof:placetype": "postalcode"
  },
  "geometry": {"coordinates":[-2.589288,51.46928],"type":"Point"}
}
