{
  "type": "Feature",
  "properties": {
    "iso:country":"GB",
    "wof:name":"BS6 5DJ",
    "wof:placetype":"postalcode"
},
  "geometry": {"coordinates":[-2.58928782996058,51.46927961247154],"type":"Point"}
}