{
  "type": "Feature",
  "properties": {
    "iso:country": "GB",
    "wof:name": "PO2 7PB",
    "wof:placetype": "postalcode"
  },
  "geometry": {"coordinates":[-1.078542,50.810555],"type":"Point"}
}
