{
  "type": "Feature",
  "properties": {
    "date:inception_lower":"1995-12-01",
    "date:inception_upper":"1995-12-31",
    "iso:country":"GB",
    "wof:name":"CW2 7UQ",
    "wof:placetype":"postalcode"
},
  "geometry": {"coordinates":[-2.463152,53.098562],"type":"Point"}
}