{
  "type": "Feature",
  "properties": {
    "iso:country": "GB",
    "wof:name": "CW2 7UQ",
    "wof:placetype": "postalcode"
  },
  "geometry": {"coordinates":[-2.463152,53.098562],"type":"Point"}
}
