{
  "type": "Feature",
  "properties": {
    "iso:country":"GB",
    "wof:name":"CW2 7UQ",
    "wof:placetype":"postalcode"
},
  "geometry": {"coordinates":[-2.46315172367407,53.09856158427317],"type":"Point"}
}