{
  "type": "Feature",
  "properties": {
    "iso:country":"GB",
    "wof:name":"EC4R 9AF",
    "wof:placetype":"postalcode"
},
  "geometry": {"coordinates":[-0.08654034925657,51.5104831558273],"type":"Point"}
}