{
  "type": "Feature",
  "properties": {
    "date:inception_lower": "1999-12-01",
    "date:inception_upper": "1999-12-01",
    "iso:country": "GB",
    "wof:name": "EC4R 9AF",
    "wof:placetype": "postalcode"
  },
  "geometry": {"coordinates":[-0.08654,51.510483],"type":"Point"}
}
