{
  "type": "Feature",
  "properties": {
    "iso:country":"GB",
    "wof:name":"W3 7NJ",
    "wof:placetype":"postalcode"
},
  "geometry": {"coordinates":[-0.25587011612911,51.5165404925437],"type":"Point"}
}