{
  "type": "Feature",
  "properties": {
    "iso:country":"GB",
    "wof:name":"DA5 1BN",
    "wof:placetype":"postalcode"
},
  "geometry": {"coordinates":[0.12806222992616,51.44709057986925],"type":"Point"}
}