{
  "type": "Feature",
  "properties": {
    "date:inception_lower": "2016-06-01",
    "date:inception_upper": "2016-06-01",
    "iso:country": "GB",
    "wof:name": "ML3 6LT",
    "wof:placetype": "postalcode"
  },
  "geometry": {"coordinates":[-4.040801,55.779861],"type":"Point"}
}
