{
  "type": "Feature",
  "properties": {
    "date:inception_lower":"2003-03-01",
    "date:inception_upper":"2003-03-31",
    "iso:country":"GB",
    "wof:name":"EX18 7LH",
    "wof:placetype":"postalcode"
},
  "geometry": {"coordinates":[-3.950751,50.90533],"type":"Point"}
}