{
  "type": "Feature",
  "properties": {
    "iso:country":"GB",
    "wof:name":"EX18 7LH",
    "wof:placetype":"postalcode"
},
  "geometry": {"coordinates":[-3.95075100954649,50.90533034872082],"type":"Point"}
}