{
  "type": "Feature",
  "properties": {
    "date:inception_lower": "2003-03-01",
    "date:inception_upper": "2003-03-01",
    "iso:country": "GB",
    "wof:name": "EX18 7LH",
    "wof:placetype": "postalcode"
  },
  "geometry": {"coordinates":[-3.950773,50.905333],"type":"Point"}
}
