{
  "type": "Feature",
  "properties": {
    "iso:country":"GB",
    "wof:name":"HX2 8TU",
    "wof:placetype":"postalcode"
},
  "geometry": {"coordinates":[-1.89547158219577,53.74097434372709],"type":"Point"}
}