{
  "type": "Feature",
  "properties": {
    "iso:country":"GB",
    "wof:name":"BD17 7LG",
    "wof:placetype":"postalcode"
},
  "geometry": {"coordinates":[-1.74595290774635,53.85388275313496],"type":"Point"}
}