{
  "type": "Feature",
  "properties": {
    "iso:country":"GB",
    "wof:name":"FK1 1SX",
    "wof:placetype":"postalcode"
},
  "geometry": {"coordinates":[-3.76956842302413,55.99836881901557],"type":"Point"}
}