{
  "type": "Feature",
  "properties": {
    "iso:country": "GB",
    "wof:name": "FK1 1SX",
    "wof:placetype": "postalcode"
  },
  "geometry": {"coordinates":[-3.769568,55.998369],"type":"Point"}
}
