{
  "type": "Feature",
  "properties": {
    "iso:country":"GB",
    "wof:name":"NP16 6HJ",
    "wof:placetype":"postalcode"
},
  "geometry": {"coordinates":[-2.71599211178017,51.68770606179028],"type":"Point"}
}