{
  "type": "Feature",
  "properties": {
    "iso:country":"GB",
    "wof:name":"NR21 0QL",
    "wof:placetype":"postalcode"
},
  "geometry": {"coordinates":[0.97269160646523,52.87715503507631],"type":"Point"}
}