{
  "type": "Feature",
  "properties": {
    "iso:country":"GB",
    "wof:name":"NR2 2PR",
    "wof:placetype":"postalcode"
},
  "geometry": {"coordinates":[1.27997992604338,52.62754792033878],"type":"Point"}
}