{
  "type": "Feature",
  "properties": {
    "date:inception_lower": "1980-01-01",
    "date:inception_upper": "1980-01-01",
    "iso:country": "GB",
    "wof:name": "NR2 2PR",
    "wof:placetype": "postalcode"
  },
  "geometry": {"coordinates":[1.27998,52.627548],"type":"Point"}
}
