{
  "type": "Feature",
  "properties": {
    "date:inception_lower": "1991-01-01",
    "date:inception_upper": "1991-01-01",
    "iso:country": "GB",
    "wof:name": "BS11 0BE",
    "wof:placetype": "postalcode"
  },
  "geometry": {"coordinates":[-2.676392,51.491963],"type":"Point"}
}
