{
  "type": "Feature",
  "properties": {
    "date:inception_lower":"2001-12-01",
    "date:inception_upper":"2001-12-31",
    "iso:country":"GB",
    "wof:name":"W1H 2AG",
    "wof:placetype":"postalcode"
},
  "geometry": {"coordinates":[-0.1602,51.518964],"type":"Point"}
}