{
  "type": "Feature",
  "properties": {
    "date:inception_lower": "2004-08-01",
    "date:inception_upper": "2004-08-01",
    "iso:country": "GB",
    "wof:name": "DT4 0UB",
    "wof:placetype": "postalcode"
  },
  "geometry": {"coordinates":[-2.459098,50.611227],"type":"Point"}
}
