{
  "type": "Feature",
  "properties": {
    "date:inception_lower": "1980-01-01",
    "date:inception_upper": "1980-01-01",
    "iso:country": "GB",
    "wof:name": "TN25 7DY",
    "wof:placetype": "postalcode"
  },
  "geometry": {"coordinates":[0.945861,51.09249],"type":"Point"}
}
