{
  "type": "Feature",
  "properties": {
    "date:inception_lower":"1980-01-01",
    "date:inception_upper":"1980-01-31",
    "iso:country":"GB",
    "wof:name":"KA26 0NF",
    "wof:placetype":"postalcode"
},
  "geometry": {"coordinates":[-5.001864,55.099961],"type":"Point"}
}