{
  "type": "Feature",
  "properties": {
    "iso:country":"GB",
    "wof:name":"KA26 0NF",
    "wof:placetype":"postalcode"
},
  "geometry": {"coordinates":[-5.00300651455446,55.09982799387114],"type":"Point"}
}