{
  "type": "Feature",
  "properties": {
    "iso:country": "GB",
    "wof:name": "NG21 9BN",
    "wof:placetype": "postalcode"
  },
  "geometry": {"coordinates":[-1.100816,53.174761],"type":"Point"}
}
