{
  "type": "Feature",
  "properties": {
    "iso:country":"GB",
    "wof:name":"NG21 9BN",
    "wof:placetype":"postalcode"
},
  "geometry": {"coordinates":[-1.10081634576782,53.17476141838677],"type":"Point"}
}