{
  "type": "Feature",
  "properties": {
    "iso:country": "GB",
    "wof:name": "WF3 4PX",
    "wof:placetype": "postalcode"
  },
  "geometry": {"coordinates":[-1.480623,53.715511],"type":"Point"}
}
