{
  "type": "Feature",
  "properties": {
    "iso:country":"GB",
    "wof:name":"S5 8AG",
    "wof:placetype":"postalcode"
},
  "geometry": {"coordinates":[-1.48372443353332,53.42693329197417],"type":"Point"}
}