{
  "type": "Feature",
  "properties": {
    "iso:country": "GB",
    "wof:name": "TN22 5TW",
    "wof:placetype": "postalcode"
  },
  "geometry": {"coordinates":[0.105184,50.957094],"type":"Point"}
}
