{
  "type": "Feature",
  "properties": {
    "iso:country":"GB",
    "wof:name":"TN22 5TW",
    "wof:placetype":"postalcode"
},
  "geometry": {"coordinates":[0.10518375342471,50.95709428766418],"type":"Point"}
}