{
  "type": "Feature",
  "properties": {
    "date:inception_lower":"1985-04-01",
    "date:inception_upper":"1985-04-30",
    "iso:country":"GB",
    "wof:name":"TN22 5TW",
    "wof:placetype":"postalcode"
},
  "geometry": {"coordinates":[0.105184,50.957094],"type":"Point"}
}