{
  "type": "Feature",
  "properties": {
    "iso:country":"GB",
    "wof:name":"TS5 4DX",
    "wof:placetype":"postalcode"
},
  "geometry": {"coordinates":[-1.25569602081305,54.56721953290881],"type":"Point"}
}