{
  "type": "Feature",
  "properties": {
    "date:inception_lower": "1980-01-01",
    "date:inception_upper": "1980-01-01",
    "iso:country": "GB",
    "wof:name": "LA4 4HY",
    "wof:placetype": "postalcode"
  },
  "geometry": {"coordinates":[-2.876716,54.065179],"type":"Point"}
}
