{
  "type": "Feature",
  "properties": {
    "iso:country":"GB",
    "wof:name":"LA4 4HY",
    "wof:placetype":"postalcode"
},
  "geometry": {"coordinates":[-2.87669292178501,54.06542832333756],"type":"Point"}
}