{
  "type": "Feature",
  "properties": {
    "iso:country":"GB",
    "wof:name":"SW9 8DA",
    "wof:placetype":"postalcode"
},
  "geometry": {"coordinates":[-0.11652343519963,51.46275931934622],"type":"Point"}
}