{
  "type": "Feature",
  "properties": {
    "date:inception_lower": "1980-01-01",
    "date:inception_upper": "1980-01-01",
    "iso:country": "GB",
    "wof:name": "SW9 8DA",
    "wof:placetype": "postalcode"
  },
  "geometry": {"coordinates":[-0.116712,51.462726],"type":"Point"}
}
