{
  "type": "Feature",
  "properties": {
    "iso:country":"GB",
    "wof:name":"TR18 2PX",
    "wof:placetype":"postalcode"
},
  "geometry": {"coordinates":[-5.54147398286067,50.12141841965485],"type":"Point"}
}