{
  "type": "Feature",
  "properties": {
    "iso:country":"GB",
    "wof:name":"DG9 1AB",
    "wof:placetype":"postalcode"
},
  "geometry": {"coordinates":[-5.02362675274569,54.90353278023106],"type":"Point"}
}