{
  "type": "Feature",
  "properties": {
    "date:inception_lower":"2010-06-01",
    "date:inception_upper":"2010-06-30",
    "iso:country":"GB",
    "wof:name":"DG9 1AB",
    "wof:placetype":"postalcode"
},
  "geometry": {"coordinates":[-5.023627,54.903533],"type":"Point"}
}