{
  "type": "Feature",
  "properties": {
    "iso:country":"GB",
    "wof:name":"BD10 9QU",
    "wof:placetype":"postalcode"
},
  "geometry": {"coordinates":[-1.72360611156132,53.83306233691845],"type":"Point"}
}