{
  "type": "Feature",
  "properties": {
    "date:inception_lower":"1980-01-01",
    "date:inception_upper":"1980-01-31",
    "iso:country":"GB",
    "wof:name":"NE24 3QA",
    "wof:placetype":"postalcode"
},
  "geometry": {"coordinates":[-1.505317,55.109296],"type":"Point"}
}