{
  "type": "Feature",
  "properties": {
    "iso:country": "GB",
    "wof:name": "DN41 7AB",
    "wof:placetype": "postalcode"
  },
  "geometry": {"coordinates":[-0.176826,53.579996],"type":"Point"}
}
