{
  "type": "Feature",
  "properties": {
    "date:inception_lower": "2017-11-01",
    "date:inception_upper": "2017-11-01",
    "iso:country": "GB",
    "wof:name": "TR16 6EL",
    "wof:placetype": "postalcode"
  },
  "geometry": {"coordinates":[-5.238922,50.206126],"type":"Point"}
}
