{
  "type": "Feature",
  "properties": {
    "iso:country": "GB",
    "wof:name": "SM6 9PT",
    "wof:placetype": "postalcode"
  },
  "geometry": {"coordinates":[-0.144231,51.35386],"type":"Point"}
}
