{
  "type": "Feature",
  "properties": {
    "iso:country":"GB",
    "wof:name":"SM6 9PT",
    "wof:placetype":"postalcode"
},
  "geometry": {"coordinates":[-0.14423070081549,51.35385957019951],"type":"Point"}
}