{
  "type": "Feature",
  "properties": {
    "iso:country":"GB",
    "wof:name":"YO8 3RQ",
    "wof:placetype":"postalcode"
},
  "geometry": {"coordinates":[-1.11931747808236,53.78788688603618],"type":"Point"}
}