{
  "type": "Feature",
  "properties": {
    "date:inception_lower": "1998-06-01",
    "date:inception_upper": "1998-06-01",
    "iso:country": "GB",
    "wof:name": "YO8 3RQ",
    "wof:placetype": "postalcode"
  },
  "geometry": {"coordinates":[-1.119317,53.787887],"type":"Point"}
}
