{
  "type": "Feature",
  "properties": {
    "iso:country": "GB",
    "wof:name": "YO8 3RQ",
    "wof:placetype": "postalcode"
  },
  "geometry": {"coordinates":[-1.119317,53.787887],"type":"Point"}
}
