{
  "type": "Feature",
  "properties": {
    "iso:country": "GB",
    "wof:name": "HU7 4ZH",
    "wof:placetype": "postalcode"
  },
  "geometry": {"coordinates":[-0.30813,53.791771],"type":"Point"}
}
