{
  "type": "Feature",
  "properties": {
    "iso:country":"GB",
    "wof:name":"TR26 1RG",
    "wof:placetype":"postalcode"
},
  "geometry": {"coordinates":[-5.48569568094387,50.21292951708247],"type":"Point"}
}