{
  "type": "Feature",
  "properties": {
    "iso:country": "GB",
    "wof:name": "TR26 1RG",
    "wof:placetype": "postalcode"
  },
  "geometry": {"coordinates":[-5.485696,50.21293],"type":"Point"}
}
