{
  "type": "Feature",
  "properties": {
    "date:inception_lower": "1980-01-01",
    "date:inception_upper": "1980-01-01",
    "iso:country": "GB",
    "wof:name": "TR26 1RG",
    "wof:placetype": "postalcode"
  },
  "geometry": {"coordinates":[-5.485696,50.21293],"type":"Point"}
}
