{
  "type": "Feature",
  "properties": {
    "iso:country":"GB",
    "wof:name":"RM10 8ET",
    "wof:placetype":"postalcode"
},
  "geometry": {"coordinates":[0.15999159778051,51.54691225402494],"type":"Point"}
}