{
  "type": "Feature",
  "properties": {
    "iso:country":"GB",
    "wof:name":"BD18 4AH",
    "wof:placetype":"postalcode"
},
  "geometry": {"coordinates":[-1.80845326640693,53.82948863330969],"type":"Point"}
}