{
  "type": "Feature",
  "properties": {
    "iso:country":"GB",
    "wof:name":"NN14 6ST",
    "wof:placetype":"postalcode"
},
  "geometry": {"coordinates":[-0.79086266170964,52.42039121532515],"type":"Point"}
}