{
  "type": "Feature",
  "properties": {
    "iso:country":"GB",
    "wof:name":"DH8 8AG",
    "wof:placetype":"postalcode"
},
  "geometry": {"coordinates":[-1.85485158897944,54.84483241185301],"type":"Point"}
}