{
  "type": "Feature",
  "properties": {
    "iso:country":"GB",
    "wof:name":"SN2 1EY",
    "wof:placetype":"postalcode"
},
  "geometry": {"coordinates":[-1.7842419136074,51.57151052189025],"type":"Point"}
}