{
  "type": "Feature",
  "properties": {
    "date:inception_lower": "1980-01-01",
    "date:inception_upper": "1980-01-01",
    "iso:country": "GB",
    "wof:name": "PE32 2ER",
    "wof:placetype": "postalcode"
  },
  "geometry": {"coordinates":[0.730959,52.666232],"type":"Point"}
}
