{
  "type": "Feature",
  "properties": {
    "iso:country":"GB",
    "wof:name":"EX5 4JY",
    "wof:placetype":"postalcode"
},
  "geometry": {"coordinates":[-3.47910828506522,50.81903881653287],"type":"Point"}
}