{
  "type": "Feature",
  "properties": {
    "iso:country":"GB",
    "wof:name":"GL16 8HA",
    "wof:placetype":"postalcode"
},
  "geometry": {"coordinates":[-2.61727716773822,51.79289720627249],"type":"Point"}
}