{
  "type": "Feature",
  "properties": {
    "iso:country": "GB",
    "wof:name": "GU14 7EY",
    "wof:placetype": "postalcode"
  },
  "geometry": {"coordinates":[-0.743221,51.289672],"type":"Point"}
}
