{
  "type": "Feature",
  "properties": {
    "date:inception_lower": "2021-04-01",
    "date:inception_upper": "2021-04-01",
    "iso:country": "GB",
    "wof:name": "YO7 3FU",
    "wof:placetype": "postalcode"
  },
  "geometry": {"coordinates":[-1.360374,54.221077],"type":"Point"}
}
