{
  "type": "Feature",
  "properties": {
    "iso:country":"GB",
    "wof:name":"G71 7NH",
    "wof:placetype":"postalcode"
},
  "geometry": {"coordinates":[-4.0754386012286,55.81775840930852],"type":"Point"}
}