{
  "type": "Feature",
  "properties": {
    "date:inception_lower": "1980-01-01",
    "date:inception_upper": "1980-01-01",
    "iso:country": "GB",
    "wof:name": "G71 7NH",
    "wof:placetype": "postalcode"
  },
  "geometry": {"coordinates":[-4.075439,55.817758],"type":"Point"}
}
