{
  "type": "Feature",
  "properties": {
    "iso:country":"GB",
    "wof:name":"B60 2TA",
    "wof:placetype":"postalcode"
},
  "geometry": {"coordinates":[-2.04007530374782,52.33049541287961],"type":"Point"}
}