{
  "type": "Feature",
  "properties": {
    "date:inception_lower": "2001-06-01",
    "date:inception_upper": "2001-06-01",
    "iso:country": "GB",
    "wof:name": "B60 2TA",
    "wof:placetype": "postalcode"
  },
  "geometry": {"coordinates":[-2.040075,52.330495],"type":"Point"}
}
