{
  "type": "Feature",
  "properties": {
    "iso:country":"GB",
    "wof:name":"MK6 2LZ",
    "wof:placetype":"postalcode"
},
  "geometry": {"coordinates":[-0.75350669245271,52.02997911106686],"type":"Point"}
}