{
  "type": "Feature",
  "properties": {
    "iso:country":"GB",
    "wof:name":"ST10 4LY",
    "wof:placetype":"postalcode"
},
  "geometry": {"coordinates":[-1.97936004277067,52.95043114488298],"type":"Point"}
}