{
  "type": "Feature",
  "properties": {
    "iso:country":"GB",
    "wof:name":"M33 3DH",
    "wof:placetype":"postalcode"
},
  "geometry": {"coordinates":[-2.31853553076256,53.41839119698994],"type":"Point"}
}