{
  "type": "Feature",
  "properties": {
    "date:inception_lower":"1980-01-01",
    "date:inception_upper":"1980-01-31",
    "iso:country":"GB",
    "wof:name":"M33 3DH",
    "wof:placetype":"postalcode"
},
  "geometry": {"coordinates":[-2.318535,53.418391],"type":"Point"}
}