{
  "type": "Feature",
  "properties": {
    "iso:country": "GB",
    "wof:name": "M33 3DH",
    "wof:placetype": "postalcode"
  },
  "geometry": {"coordinates":[-2.318535,53.418391],"type":"Point"}
}
