{
  "type": "Feature",
  "properties": {
    "date:inception_lower": "2021-05-01",
    "date:inception_upper": "2021-05-01",
    "iso:country": "GB",
    "wof:name": "TD11 3FH",
    "wof:placetype": "postalcode"
  },
  "geometry": {"coordinates":[-2.258175,55.719379],"type":"Point"}
}
