{
  "type": "Feature",
  "properties": {
    "iso:country":"GB",
    "wof:name":"M20 4WT",
    "wof:placetype":"postalcode"
},
  "geometry": {"coordinates":[-2.22011738900911,53.43286916230497],"type":"Point"}
}