{
  "type": "Feature",
  "properties": {
    "iso:country":"GB",
    "wof:name":"DT3 5DZ",
    "wof:placetype":"postalcode"
},
  "geometry": {"coordinates":[-2.47217543731484,50.65087156540207],"type":"Point"}
}