{
  "type": "Feature",
  "properties": {
    "iso:country":"GB",
    "wof:name":"RG7 4TE",
    "wof:placetype":"postalcode"
},
  "geometry": {"coordinates":[-1.21183860748359,51.37648853912918],"type":"Point"}
}