{
  "type": "Feature",
  "properties": {
    "date:inception_lower": "1980-01-01",
    "date:inception_upper": "1980-01-01",
    "iso:country": "GB",
    "wof:name": "RG7 4TE",
    "wof:placetype": "postalcode"
  },
  "geometry": {"coordinates":[-1.211732,51.376533],"type":"Point"}
}
