{
  "type": "Feature",
  "properties": {
    "iso:country":"GB",
    "wof:name":"SW4 9LE",
    "wof:placetype":"postalcode"
},
  "geometry": {"coordinates":[-0.13968016656843,51.45230197798666],"type":"Point"}
}