{
  "type": "Feature",
  "properties": {
    "iso:country":"GB",
    "wof:name":"NG34 0AN",
    "wof:placetype":"postalcode"
},
  "geometry": {"coordinates":[-0.3758077648132,52.9438324515542],"type":"Point"}
}