{
  "type": "Feature",
  "properties": {
    "iso:country": "GB",
    "wof:name": "DE73 6NG",
    "wof:placetype": "postalcode"
  },
  "geometry": {"coordinates":[-1.429354,52.865849],"type":"Point"}
}
