{
  "type": "Feature",
  "properties": {
    "date:inception_lower": "1980-01-01",
    "date:inception_upper": "1980-01-01",
    "iso:country": "GB",
    "wof:name": "IP30 9RF",
    "wof:placetype": "postalcode"
  },
  "geometry": {"coordinates":[0.889276,52.221687],"type":"Point"}
}
