{
  "type": "Feature",
  "properties": {
    "iso:country": "GB",
    "wof:name": "TA2 6AP",
    "wof:placetype": "postalcode"
  },
  "geometry": {"coordinates":[-3.126432,51.031824],"type":"Point"}
}
