{
  "type": "Feature",
  "properties": {
    "iso:country": "GB",
    "wof:name": "SM7 1EZ",
    "wof:placetype": "postalcode"
  },
  "geometry": {"coordinates":[-0.215633,51.319232],"type":"Point"}
}
