{
  "type": "Feature",
  "properties": {
    "date:inception_lower":"2014-01-01",
    "date:inception_upper":"2014-01-31",
    "iso:country":"GB",
    "wof:name":"CA2 6RH",
    "wof:placetype":"postalcode"
},
  "geometry": {"coordinates":[-2.963662,54.878359],"type":"Point"}
}