{
  "type": "Feature",
  "properties": {
    "iso:country": "GB",
    "wof:name": "CA2 6RH",
    "wof:placetype": "postalcode"
  },
  "geometry": {"coordinates":[-2.963662,54.878359],"type":"Point"}
}
