{
  "type": "Feature",
  "properties": {
    "iso:country": "GB",
    "wof:name": "EX24 6QG",
    "wof:placetype": "postalcode"
  },
  "geometry": {"coordinates":[-3.05909,50.728383],"type":"Point"}
}
