{
  "type": "Feature",
  "properties": {
    "iso:country":"GB",
    "wof:name":"B38 9SF",
    "wof:placetype":"postalcode"
},
  "geometry": {"coordinates":[-1.94358076816495,52.39653949275843],"type":"Point"}
}