{
  "type": "Feature",
  "properties": {
    "iso:country":"GB",
    "wof:name":"DE7 8DH",
    "wof:placetype":"postalcode"
},
  "geometry": {"coordinates":[-1.30890652339491,52.97837790901651],"type":"Point"}
}