{
  "type": "Feature",
  "properties": {
    "iso:country": "GB",
    "wof:name": "DE7 8DH",
    "wof:placetype": "postalcode"
  },
  "geometry": {"coordinates":[-1.308906,52.978378],"type":"Point"}
}
