{
  "type": "Feature",
  "properties": {
    "iso:country":"GB",
    "wof:name":"HP4 1QZ",
    "wof:placetype":"postalcode"
},
  "geometry": {"coordinates":[-0.56473815037291,51.83755349218195],"type":"Point"}
}