{
  "type": "Feature",
  "properties": {
    "date:inception_lower": "1980-01-01",
    "date:inception_upper": "1980-01-01",
    "iso:country": "GB",
    "wof:name": "HP4 1QZ",
    "wof:placetype": "postalcode"
  },
  "geometry": {"coordinates":[-0.565105,51.837423],"type":"Point"}
}
