{
  "type": "Feature",
  "properties": {
    "iso:country":"GB",
    "wof:name":"OX4 4SF",
    "wof:placetype":"postalcode"
},
  "geometry": {"coordinates":[-1.23377110282092,51.72556068121649],"type":"Point"}
}