{
  "type": "Feature",
  "properties": {
    "iso:country": "GB",
    "wof:name": "OX4 4SF",
    "wof:placetype": "postalcode"
  },
  "geometry": {"coordinates":[-1.232167,51.726005],"type":"Point"}
}
