{
  "type": "Feature",
  "properties": {
    "date:inception_lower": "1980-01-01",
    "date:inception_upper": "1980-01-01",
    "iso:country": "GB",
    "wof:name": "GL11 4NH",
    "wof:placetype": "postalcode"
  },
  "geometry": {"coordinates":[-2.34766,51.679619],"type":"Point"}
}
