{
  "type": "Feature",
  "properties": {
    "iso:country":"GB",
    "wof:name":"EH49 7JU",
    "wof:placetype":"postalcode"
},
  "geometry": {"coordinates":[-3.59052004686853,55.97929650024104],"type":"Point"}
}