{
  "type": "Feature",
  "properties": {
    "iso:country":"GB",
    "wof:name":"TQ13 9XT",
    "wof:placetype":"postalcode"
},
  "geometry": {"coordinates":[-3.73921179206569,50.57921736563849],"type":"Point"}
}