{
  "type": "Feature",
  "properties": {
    "iso:country": "GB",
    "wof:name": "CM1 1RS",
    "wof:placetype": "postalcode"
  },
  "geometry": {"coordinates":[0.470089,51.738695],"type":"Point"}
}
