{
  "type": "Feature",
  "properties": {
    "iso:country":"GB",
    "wof:name":"TW4 5EP",
    "wof:placetype":"postalcode"
},
  "geometry": {"coordinates":[-0.3803343425409,51.46016299628836],"type":"Point"}
}