{
  "type": "Feature",
  "properties": {
    "iso:country": "GB",
    "wof:name": "ML9 3DP",
    "wof:placetype": "postalcode"
  },
  "geometry": {"coordinates":[-3.911683,55.707988],"type":"Point"}
}
