{
  "type": "Feature",
  "properties": {
    "iso:country":"GB",
    "wof:name":"ML9 3DP",
    "wof:placetype":"postalcode"
},
  "geometry": {"coordinates":[-3.91168316552943,55.70798798607625],"type":"Point"}
}