{
  "type": "Feature",
  "properties": {
    "iso:country":"GB",
    "wof:name":"CF15 9NA",
    "wof:placetype":"postalcode"
},
  "geometry": {"coordinates":[-3.27236292973719,51.53905532125656],"type":"Point"}
}