{
  "type": "Feature",
  "properties": {
    "iso:country": "GB",
    "wof:name": "CF15 9NA",
    "wof:placetype": "postalcode"
  },
  "geometry": {"coordinates":[-3.272077,51.53879],"type":"Point"}
}
