{
  "type": "Feature",
  "properties": {
    "iso:country":"GB",
    "wof:name":"TN8 6LT",
    "wof:placetype":"postalcode"
},
  "geometry": {"coordinates":[0.09245781503824,51.21188922575053],"type":"Point"}
}