{
  "type": "Feature",
  "properties": {
    "date:inception_lower": "1980-01-01",
    "date:inception_upper": "1980-01-01",
    "iso:country": "GB",
    "wof:name": "TN8 6LT",
    "wof:placetype": "postalcode"
  },
  "geometry": {"coordinates":[0.092484,51.211887],"type":"Point"}
}
