{
  "type": "Feature",
  "properties": {
    "iso:country":"GB",
    "wof:name":"ML4 1JW",
    "wof:placetype":"postalcode"
},
  "geometry": {"coordinates":[-4.02447788543945,55.82679526194667],"type":"Point"}
}