{
  "type": "Feature",
  "properties": {
    "iso:country":"GB",
    "wof:name":"EN1 3AG",
    "wof:placetype":"postalcode"
},
  "geometry": {"coordinates":[-0.06509382652525,51.66071963241445],"type":"Point"}
}