{
  "type": "Feature",
  "properties": {
    "iso:country": "GB",
    "wof:name": "NR26 8TA",
    "wof:placetype": "postalcode"
  },
  "geometry": {"coordinates":[1.187204,52.94328],"type":"Point"}
}
