{
  "type": "Feature",
  "properties": {
    "iso:country":"GB",
    "wof:name":"NR26 8TA",
    "wof:placetype":"postalcode"
},
  "geometry": {"coordinates":[1.18720373636527,52.94328034008773],"type":"Point"}
}