{
  "type": "Feature",
  "properties": {
    "iso:country":"GB",
    "wof:name":"LS21 3JG",
    "wof:placetype":"postalcode"
},
  "geometry": {"coordinates":[-1.69186123151858,53.90188623989739],"type":"Point"}
}