{
  "type": "Feature",
  "properties": {
    "iso:country": "GB",
    "wof:name": "LS21 3JG",
    "wof:placetype": "postalcode"
  },
  "geometry": {"coordinates":[-1.691861,53.901886],"type":"Point"}
}
