{
  "type": "Feature",
  "properties": {
    "iso:country": "GB",
    "wof:name": "SG5 3YG",
    "wof:placetype": "postalcode"
  },
  "geometry": {"coordinates":[-0.279254,51.971622],"type":"Point"}
}
