{
  "type": "Feature",
  "properties": {
    "iso:country":"GB",
    "wof:name":"SG5 3YG",
    "wof:placetype":"postalcode"
},
  "geometry": {"coordinates":[-0.27933972814998,51.97161404377161],"type":"Point"}
}