{
  "type": "Feature",
  "properties": {
    "date:inception_lower": "2007-09-01",
    "date:inception_upper": "2007-09-01",
    "iso:country": "GB",
    "wof:name": "CV31 3LH",
    "wof:placetype": "postalcode"
  },
  "geometry": {"coordinates":[-1.540957,52.277977],"type":"Point"}
}
