{
  "type": "Feature",
  "properties": {
    "iso:country":"GB",
    "wof:name":"CV31 3LH",
    "wof:placetype":"postalcode"
},
  "geometry": {"coordinates":[-1.54099762791643,52.27797144929501],"type":"Point"}
}