{
  "type": "Feature",
  "properties": {
    "iso:country":"GB",
    "wof:name":"G61 2DF",
    "wof:placetype":"postalcode"
},
  "geometry": {"coordinates":[-4.32856139418728,55.91576430868958],"type":"Point"}
}