{
  "type": "Feature",
  "properties": {
    "iso:country":"GB",
    "wof:name":"NG9 8GQ",
    "wof:placetype":"postalcode"
},
  "geometry": {"coordinates":[-1.27284754351247,52.93946343630563],"type":"Point"}
}