{
  "type": "Feature",
  "properties": {
    "iso:country":"GB",
    "wof:name":"OX26 6RW",
    "wof:placetype":"postalcode"
},
  "geometry": {"coordinates":[-1.14981518320783,51.90047396373169],"type":"Point"}
}