{
  "type": "Feature",
  "properties": {
    "iso:country":"GB",
    "wof:name":"PE9 3TB",
    "wof:placetype":"postalcode"
},
  "geometry": {"coordinates":[-0.55074735325823,52.63112985955163],"type":"Point"}
}