{
  "type": "Feature",
  "properties": {
    "iso:country": "GB",
    "wof:name": "PE9 3TB",
    "wof:placetype": "postalcode"
  },
  "geometry": {"coordinates":[-0.550747,52.63113],"type":"Point"}
}
