{
  "type": "Feature",
  "properties": {
    "iso:country":"GB",
    "wof:name":"SR5 4QJ",
    "wof:placetype":"postalcode"
},
  "geometry": {"coordinates":[-1.46133971122937,54.9290157678733],"type":"Point"}
}