{
  "type": "Feature",
  "properties": {
    "iso:country":"GB",
    "wof:name":"KT6 5JB",
    "wof:placetype":"postalcode"
},
  "geometry": {"coordinates":[-0.31696271168935,51.38316740092375],"type":"Point"}
}