{
  "type": "Feature",
  "properties": {
    "iso:country":"GB",
    "wof:name":"CV2 1NR",
    "wof:placetype":"postalcode"
},
  "geometry": {"coordinates":[-1.45324270424878,52.45787010702649],"type":"Point"}
}