{
  "type": "Feature",
  "properties": {
    "date:inception_lower": "1980-01-01",
    "date:inception_upper": "1980-01-01",
    "iso:country": "GB",
    "wof:name": "CV2 1NR",
    "wof:placetype": "postalcode"
  },
  "geometry": {"coordinates":[-1.452743,52.458344],"type":"Point"}
}
