{
  "type": "Feature",
  "properties": {
    "iso:country":"GB",
    "wof:name":"EH21 8BA",
    "wof:placetype":"postalcode"
},
  "geometry": {"coordinates":[-3.01621275550307,55.93530374926052],"type":"Point"}
}