{
  "type": "Feature",
  "properties": {
    "iso:country": "GB",
    "wof:name": "EH21 8BA",
    "wof:placetype": "postalcode"
  },
  "geometry": {"coordinates":[-3.016213,55.935304],"type":"Point"}
}
