{
  "type": "Feature",
  "properties": {
    "iso:country":"GB",
    "wof:name":"HU7 4SH",
    "wof:placetype":"postalcode"
},
  "geometry": {"coordinates":[-0.31063385998641,53.78462361077084],"type":"Point"}
}