{
  "type": "Feature",
  "properties": {
    "iso:country":"GB",
    "wof:name":"CF42 5ES",
    "wof:placetype":"postalcode"
},
  "geometry": {"coordinates":[-3.52839325918619,51.67314493329358],"type":"Point"}
}