{
  "type": "Feature",
  "properties": {
    "iso:country": "GB",
    "wof:name": "SE15 3LF",
    "wof:placetype": "postalcode"
  },
  "geometry": {"coordinates":[-0.05961,51.463216],"type":"Point"}
}
