{
  "type": "Feature",
  "properties": {
    "iso:country": "GB",
    "wof:name": "MK19 7LH",
    "wof:placetype": "postalcode"
  },
  "geometry": {"coordinates":[-0.828206,52.1137],"type":"Point"}
}
