{
  "type": "Feature",
  "properties": {
    "iso:country":"GB",
    "wof:name":"NE29 8LE",
    "wof:placetype":"postalcode"
},
  "geometry": {"coordinates":[-1.47558007220641,55.01831217501221],"type":"Point"}
}