{
  "type": "Feature",
  "properties": {
    "iso:country":"GB",
    "wof:name":"KA8 9RP",
    "wof:placetype":"postalcode"
},
  "geometry": {"coordinates":[-4.59761174374525,55.47215526410007],"type":"Point"}
}