{
  "type": "Feature",
  "properties": {
    "iso:country": "GB",
    "wof:name": "SR1 2HJ",
    "wof:placetype": "postalcode"
  },
  "geometry": {"coordinates":[-1.37324,54.905516],"type":"Point"}
}
