{
  "type": "Feature",
  "properties": {
    "iso:country":"GB",
    "wof:name":"SR1 2HJ",
    "wof:placetype":"postalcode"
},
  "geometry": {"coordinates":[-1.37324034701906,54.90551642149504],"type":"Point"}
}