{
  "type": "Feature",
  "properties": {
    "date:inception_lower": "1980-01-01",
    "date:inception_upper": "1980-01-01",
    "iso:country": "GB",
    "wof:name": "DE11 9EY",
    "wof:placetype": "postalcode"
  },
  "geometry": {"coordinates":[-1.565401,52.767611],"type":"Point"}
}
