{
  "type": "Feature",
  "properties": {
    "iso:country":"GB",
    "wof:name":"TQ7 1PE",
    "wof:placetype":"postalcode"
},
  "geometry": {"coordinates":[-3.77818450341001,50.28506673337051],"type":"Point"}
}