{
  "type": "Feature",
  "properties": {
    "iso:country":"GB",
    "wof:name":"PO37 7EZ",
    "wof:placetype":"postalcode"
},
  "geometry": {"coordinates":[-1.17378457253299,50.64103341872898],"type":"Point"}
}