{
  "type": "Feature",
  "properties": {
    "date:inception_lower":"1980-01-01",
    "date:inception_upper":"1980-01-31",
    "iso:country":"GB",
    "wof:name":"SG11 1PZ",
    "wof:placetype":"postalcode"
},
  "geometry": {"coordinates":[0.014576,51.885627],"type":"Point"}
}