{
  "type": "Feature",
  "properties": {
    "date:inception_lower": "2007-01-01",
    "date:inception_upper": "2007-01-01",
    "iso:country": "GB",
    "wof:name": "KA9 1QB",
    "wof:placetype": "postalcode"
  },
  "geometry": {"coordinates":[-4.615159,55.497984],"type":"Point"}
}
