{
  "type": "Feature",
  "properties": {
    "iso:country":"GB",
    "wof:name":"KA9 1QB",
    "wof:placetype":"postalcode"
},
  "geometry": {"coordinates":[-4.61500814285723,55.49850829929152],"type":"Point"}
}