{
  "type": "Feature",
  "properties": {
    "date:inception_lower": "2019-12-01",
    "date:inception_upper": "2019-12-01",
    "iso:country": "GB",
    "wof:name": "EH47 0TB",
    "wof:placetype": "postalcode"
  },
  "geometry": {"coordinates":[-3.703131,55.868614],"type":"Point"}
}
