{
  "type": "Feature",
  "properties": {
    "date:inception_lower": "1980-01-01",
    "date:inception_upper": "1980-01-01",
    "iso:country": "GB",
    "wof:name": "DA16 2BD",
    "wof:placetype": "postalcode"
  },
  "geometry": {"coordinates":[0.112161,51.46022],"type":"Point"}
}
