{
  "type": "Feature",
  "properties": {
    "iso:country":"GB",
    "wof:name":"DA16 2BD",
    "wof:placetype":"postalcode"
},
  "geometry": {"coordinates":[0.11216095558417,51.46022005632796],"type":"Point"}
}