{
  "type": "Feature",
  "properties": {
    "iso:country": "GB",
    "wof:name": "DA14 5BG",
    "wof:placetype": "postalcode"
  },
  "geometry": {"coordinates":[0.131377,51.414422],"type":"Point"}
}
