{
  "type": "Feature",
  "properties": {
    "iso:country": "GB",
    "wof:name": "L4 5RS",
    "wof:placetype": "postalcode"
  },
  "geometry": {"coordinates":[-2.970682,53.446762],"type":"Point"}
}
