{
  "type": "Feature",
  "properties": {
    "date:inception_lower": "1980-01-01",
    "date:inception_upper": "1980-01-01",
    "iso:country": "GB",
    "wof:name": "L4 5RS",
    "wof:placetype": "postalcode"
  },
  "geometry": {"coordinates":[-2.970682,53.446762],"type":"Point"}
}
