{
  "type": "Feature",
  "properties": {
    "iso:country":"GB",
    "wof:name":"N22 5DT",
    "wof:placetype":"postalcode"
},
  "geometry": {"coordinates":[-0.09680562171066,51.59919033775645],"type":"Point"}
}