{
  "type": "Feature",
  "properties": {
    "iso:country":"GB",
    "wof:name":"TR26 1HR",
    "wof:placetype":"postalcode"
},
  "geometry": {"coordinates":[-5.48072501817678,50.21494098625556],"type":"Point"}
}