{
  "type": "Feature",
  "properties": {
    "iso:country":"GB",
    "wof:name":"CM2 8NY",
    "wof:placetype":"postalcode"
},
  "geometry": {"coordinates":[0.47199482609001,51.70168467287276],"type":"Point"}
}