{
  "type": "Feature",
  "properties": {
    "iso:country": "GB",
    "wof:name": "SA6 8HR",
    "wof:placetype": "postalcode"
  },
  "geometry": {"coordinates":[-3.925788,51.652525],"type":"Point"}
}
