{
  "type": "Feature",
  "properties": {
    "iso:country":"GB",
    "wof:name":"SA6 8HR",
    "wof:placetype":"postalcode"
},
  "geometry": {"coordinates":[-3.92578779251383,51.65252488853036],"type":"Point"}
}