{
  "type": "Feature",
  "properties": {
    "date:inception_lower":"1980-01-01",
    "date:inception_upper":"1980-01-31",
    "iso:country":"GB",
    "wof:name":"SW7 2SG",
    "wof:placetype":"postalcode"
},
  "geometry": {"coordinates":[-0.170142,51.494965],"type":"Point"}
}