{
  "type": "Feature",
  "properties": {
    "iso:country":"GB",
    "wof:name":"HU9 3BB",
    "wof:placetype":"postalcode"
},
  "geometry": {"coordinates":[-0.30269131803087,53.75952151850492],"type":"Point"}
}