{
  "type": "Feature",
  "properties": {
    "iso:country": "GB",
    "wof:name": "HU9 3BB",
    "wof:placetype": "postalcode"
  },
  "geometry": {"coordinates":[-0.302691,53.759522],"type":"Point"}
}
