{
  "type": "Feature",
  "properties": {
    "date:inception_lower":"1980-01-01",
    "date:inception_upper":"1980-01-31",
    "iso:country":"GB",
    "wof:name":"HU9 3BB",
    "wof:placetype":"postalcode"
},
  "geometry": {"coordinates":[-0.302691,53.759522],"type":"Point"}
}