{
  "type": "Feature",
  "properties": {
    "date:inception_lower":"1999-06-01",
    "date:inception_upper":"1999-06-30",
    "iso:country":"GB",
    "wof:name":"CH66 5PD",
    "wof:placetype":"postalcode"
},
  "geometry": {"coordinates":[-2.953402,53.2875],"type":"Point"}
}