{
  "type": "Feature",
  "properties": {
    "iso:country":"GB",
    "wof:name":"SO16 0XW",
    "wof:placetype":"postalcode"
},
  "geometry": {"coordinates":[-1.46776175454013,50.95182292758073],"type":"Point"}
}