{
  "type": "Feature",
  "properties": {
    "date:inception_lower":"1994-12-01",
    "date:inception_upper":"1994-12-31",
    "iso:country":"GB",
    "wof:name":"SO16 0XW",
    "wof:placetype":"postalcode"
},
  "geometry": {"coordinates":[-1.467762,50.951823],"type":"Point"}
}