{
  "type": "Feature",
  "properties": {
    "date:inception_lower": "1980-01-01",
    "date:inception_upper": "1980-01-01",
    "iso:country": "GB",
    "wof:name": "BN23 8AY",
    "wof:placetype": "postalcode"
  },
  "geometry": {"coordinates":[0.296482,50.812262],"type":"Point"}
}
