{
  "type": "Feature",
  "properties": {
    "iso:country": "GB",
    "wof:name": "NE6 3UR",
    "wof:placetype": "postalcode"
  },
  "geometry": {"coordinates":[-1.542885,54.969456],"type":"Point"}
}
