{
  "type": "Feature",
  "properties": {
    "date:inception_lower": "1980-01-01",
    "date:inception_upper": "1980-01-01",
    "iso:country": "GB",
    "wof:name": "NN18 9JP",
    "wof:placetype": "postalcode"
  },
  "geometry": {"coordinates":[-0.721288,52.473414],"type":"Point"}
}
