{
  "type": "Feature",
  "properties": {
    "iso:country":"GB",
    "wof:name":"PL4 8LX",
    "wof:placetype":"postalcode"
},
  "geometry": {"coordinates":[-4.13449309078161,50.37638700681309],"type":"Point"}
}