{
  "type": "Feature",
  "properties": {
    "date:inception_lower": "1980-01-01",
    "date:inception_upper": "1980-01-01",
    "iso:country": "GB",
    "wof:name": "N18 2BD",
    "wof:placetype": "postalcode"
  },
  "geometry": {"coordinates":[-0.055375,51.609752],"type":"Point"}
}
