{
  "type": "Feature",
  "properties": {
    "iso:country":"GB",
    "wof:name":"N18 2BD",
    "wof:placetype":"postalcode"
},
  "geometry": {"coordinates":[-0.05537548026794,51.60975181162825],"type":"Point"}
}