{
  "type": "Feature",
  "properties": {
    "date:inception_lower": "2013-04-01",
    "date:inception_upper": "2013-04-01",
    "iso:country": "GB",
    "wof:name": "BD12 0QA",
    "wof:placetype": "postalcode"
  },
  "geometry": {"coordinates":[-1.761777,53.755476],"type":"Point"}
}
