{
  "type": "Feature",
  "properties": {
    "iso:country": "GB",
    "wof:name": "BD12 0QA",
    "wof:placetype": "postalcode"
  },
  "geometry": {"coordinates":[-1.761641,53.755467],"type":"Point"}
}
