{
  "type": "Feature",
  "properties": {
    "iso:country":"GB",
    "wof:name":"SN3 6HQ",
    "wof:placetype":"postalcode"
},
  "geometry": {"coordinates":[-1.72832995907682,51.54735155775528],"type":"Point"}
}