{
  "type": "Feature",
  "properties": {
    "iso:country": "GB",
    "wof:name": "SN3 6HQ",
    "wof:placetype": "postalcode"
  },
  "geometry": {"coordinates":[-1.72833,51.547352],"type":"Point"}
}
