{
  "type": "Feature",
  "properties": {
    "iso:country":"GB",
    "wof:name":"RH1 4LG",
    "wof:placetype":"postalcode"
},
  "geometry": {"coordinates":[-0.10466113549661,51.23968231297276],"type":"Point"}
}