{
  "type": "Feature",
  "properties": {
    "iso:country": "GB",
    "wof:name": "RH1 4LG",
    "wof:placetype": "postalcode"
  },
  "geometry": {"coordinates":[-0.104661,51.239682],"type":"Point"}
}
