{
  "type": "Feature",
  "properties": {
    "date:inception_lower": "1980-01-01",
    "date:inception_upper": "1980-01-01",
    "iso:country": "GB",
    "wof:name": "TN1 1SF",
    "wof:placetype": "postalcode"
  },
  "geometry": {"coordinates":[0.26517,51.129098],"type":"Point"}
}
