{
  "type": "Feature",
  "properties": {
    "iso:country": "GB",
    "wof:name": "TN1 1SF",
    "wof:placetype": "postalcode"
  },
  "geometry": {"coordinates":[0.26517,51.129098],"type":"Point"}
}
