{
  "type": "Feature",
  "properties": {
    "iso:country":"GB",
    "wof:name":"TN1 1SF",
    "wof:placetype":"postalcode"
},
  "geometry": {"coordinates":[0.26517036070683,51.12909831290355],"type":"Point"}
}