{
  "type": "Feature",
  "properties": {
    "iso:country":"GB",
    "wof:name":"PE34 3PZ",
    "wof:placetype":"postalcode"
},
  "geometry": {"coordinates":[0.38907561919836,52.62147718914681],"type":"Point"}
}