{
  "type": "Feature",
  "properties": {
    "iso:country":"GB",
    "wof:name":"PL5 3NY",
    "wof:placetype":"postalcode"
},
  "geometry": {"coordinates":[-4.15910586549395,50.40299656468205],"type":"Point"}
}