{
  "type": "Feature",
  "properties": {
    "date:inception_lower": "1980-01-01",
    "date:inception_upper": "1980-01-01",
    "iso:country": "GB",
    "wof:name": "NE3 5SY",
    "wof:placetype": "postalcode"
  },
  "geometry": {"coordinates":[-1.620377,55.027593],"type":"Point"}
}
