{
  "type": "Feature",
  "properties": {
    "iso:country":"GB",
    "wof:name":"SG19 3HU",
    "wof:placetype":"postalcode"
},
  "geometry": {"coordinates":[-0.12802353252894,52.14103952252551],"type":"Point"}
}