{
  "type": "Feature",
  "properties": {
    "iso:country":"GB",
    "wof:name":"CW12 3GX",
    "wof:placetype":"postalcode"
},
  "geometry": {"coordinates":[-2.18815424198057,53.15465069407961],"type":"Point"}
}