{
  "type": "Feature",
  "properties": {
    "iso:country": "GB",
    "wof:name": "CW12 3GX",
    "wof:placetype": "postalcode"
  },
  "geometry": {"coordinates":[-2.188154,53.154651],"type":"Point"}
}
