{
  "type": "Feature",
  "properties": {
    "iso:country": "GB",
    "wof:name": "OX11 7PT",
    "wof:placetype": "postalcode"
  },
  "geometry": {"coordinates":[-1.235439,51.615418],"type":"Point"}
}
