{
  "type": "Feature",
  "properties": {
    "iso:country":"GB",
    "wof:name":"EX2 7JU",
    "wof:placetype":"postalcode"
},
  "geometry": {"coordinates":[-3.47956850543251,50.70371313122786],"type":"Point"}
}