{
  "type": "Feature",
  "properties": {
    "iso:country":"GB",
    "wof:name":"DG2 9JY",
    "wof:placetype":"postalcode"
},
  "geometry": {"coordinates":[-3.63503018513747,55.07785274424634],"type":"Point"}
}