{
  "type": "Feature",
  "properties": {
    "iso:country":"GB",
    "wof:name":"PR3 0XD",
    "wof:placetype":"postalcode"
},
  "geometry": {"coordinates":[-2.85154765523696,53.84886291447641],"type":"Point"}
}