{
  "type": "Feature",
  "properties": {
    "iso:country":"GB",
    "wof:name":"RG1 6NH",
    "wof:placetype":"postalcode"
},
  "geometry": {"coordinates":[-0.98657301312302,51.45100864844107],"type":"Point"}
}