{
  "type": "Feature",
  "properties": {
    "date:inception_lower": "2013-12-01",
    "date:inception_upper": "2013-12-01",
    "iso:country": "GB",
    "wof:name": "PE8 4FE",
    "wof:placetype": "postalcode"
  },
  "geometry": {"coordinates":[-0.465499,52.487114],"type":"Point"}
}
