{
  "type": "Feature",
  "properties": {
    "iso:country":"GB",
    "wof:name":"BL7 9TL",
    "wof:placetype":"postalcode"
},
  "geometry": {"coordinates":[-2.44324983657174,53.63164857315934],"type":"Point"}
}