{
  "type": "Feature",
  "properties": {
    "iso:country":"GB",
    "wof:name":"OX18 2DA",
    "wof:placetype":"postalcode"
},
  "geometry": {"coordinates":[-1.50790658304952,51.72328739833777],"type":"Point"}
}