{
  "type": "Feature",
  "properties": {
    "date:inception_lower": "1991-09-01",
    "date:inception_upper": "1991-09-01",
    "iso:country": "GB",
    "wof:name": "OX18 2DA",
    "wof:placetype": "postalcode"
  },
  "geometry": {"coordinates":[-1.507907,51.723287],"type":"Point"}
}
