{
  "type": "Feature",
  "properties": {
    "iso:country":"GB",
    "wof:name":"CM2 9ER",
    "wof:placetype":"postalcode"
},
  "geometry": {"coordinates":[0.47509187993921,51.71785195384763],"type":"Point"}
}