{
  "type": "Feature",
  "properties": {
    "iso:country": "GB",
    "wof:name": "N5 1LQ",
    "wof:placetype": "postalcode"
  },
  "geometry": {"coordinates":[-0.104134,51.559472],"type":"Point"}
}
