{
  "type": "Feature",
  "properties": {
    "iso:country":"GB",
    "wof:name":"N5 1LQ",
    "wof:placetype":"postalcode"
},
  "geometry": {"coordinates":[-0.1041339780311,51.5594723536754],"type":"Point"}
}