{
  "type": "Feature",
  "properties": {
    "iso:country":"GB",
    "wof:name":"NN6 6NA",
    "wof:placetype":"postalcode"
},
  "geometry": {"coordinates":[-1.12437017730911,52.37427930547363],"type":"Point"}
}