{
  "type": "Feature",
  "properties": {
    "iso:country":"GB",
    "wof:name":"CM18 7NS",
    "wof:placetype":"postalcode"
},
  "geometry": {"coordinates":[0.08930211559778,51.75121858324234],"type":"Point"}
}