{
  "type": "Feature",
  "properties": {
    "iso:country":"GB",
    "wof:name":"ZE2 9BZ",
    "wof:placetype":"postalcode"
},
  "geometry": {"coordinates":[-1.0160380426128,60.71634327695993],"type":"Point"}
}