{
  "type": "Feature",
  "properties": {
    "iso:country":"GB",
    "wof:name":"CM15 8NJ",
    "wof:placetype":"postalcode"
},
  "geometry": {"coordinates":[0.32680280715386,51.62975804638589],"type":"Point"}
}