{
  "type": "Feature",
  "properties": {
    "iso:country":"GB",
    "wof:name":"AB55 6LT",
    "wof:placetype":"postalcode"
},
  "geometry": {"coordinates":[-2.89562456497384,57.58652978801218],"type":"Point"}
}