{
  "type": "Feature",
  "properties": {
    "iso:country": "GB",
    "wof:name": "TQ11 0BX",
    "wof:placetype": "postalcode"
  },
  "geometry": {"coordinates":[-3.773423,50.481056],"type":"Point"}
}
