{
  "type": "Feature",
  "properties": {
    "iso:country":"GB",
    "wof:name":"CM2 7HR",
    "wof:placetype":"postalcode"
},
  "geometry": {"coordinates":[0.49728574076792,51.71650982619916],"type":"Point"}
}