{
  "type": "Feature",
  "properties": {
    "iso:country":"GB",
    "wof:name":"PE12 6SS",
    "wof:placetype":"postalcode"
},
  "geometry": {"coordinates":[-0.0101439875213,52.77436856600895],"type":"Point"}
}