{
  "type": "Feature",
  "properties": {
    "iso:country": "GB",
    "wof:name": "ME4 3AW",
    "wof:placetype": "postalcode"
  },
  "geometry": {"coordinates":[0.535993,51.406552],"type":"Point"}
}
