{
  "type": "Feature",
  "properties": {
    "iso:country":"GB",
    "wof:name":"G72 8UN",
    "wof:placetype":"postalcode"
},
  "geometry": {"coordinates":[-4.14193617624717,55.81017399250226],"type":"Point"}
}