{
  "type": "Feature",
  "properties": {
    "date:inception_lower":"1981-06-01",
    "date:inception_upper":"1981-06-30",
    "iso:country":"GB",
    "wof:name":"M3 4FG",
    "wof:placetype":"postalcode"
},
  "geometry": {"coordinates":[-2.251941,53.476877],"type":"Point"}
}