{
  "type": "Feature",
  "properties": {
    "iso:country": "GB",
    "wof:name": "M3 4FG",
    "wof:placetype": "postalcode"
  },
  "geometry": {"coordinates":[-2.251941,53.476877],"type":"Point"}
}
