{
  "type": "Feature",
  "properties": {
    "iso:country":"GB",
    "wof:name":"M3 4FG",
    "wof:placetype":"postalcode"
},
  "geometry": {"coordinates":[-2.25194075218926,53.47687682435213],"type":"Point"}
}