{
  "type": "Feature",
  "properties": {
    "iso:country": "GB",
    "wof:name": "BH21 6RP",
    "wof:placetype": "postalcode"
  },
  "geometry": {"coordinates":[-1.878303,50.858551],"type":"Point"}
}
