{
  "type": "Feature",
  "properties": {
    "iso:country":"GB",
    "wof:name":"GL7 5QW",
    "wof:placetype":"postalcode"
},
  "geometry": {"coordinates":[-1.85832182970439,51.6728919590497],"type":"Point"}
}