{
  "type": "Feature",
  "properties": {
    "iso:country":"GB",
    "wof:name":"GU9 9LW",
    "wof:placetype":"postalcode"
},
  "geometry": {"coordinates":[-0.76272383115091,51.2315197313438],"type":"Point"}
}