{
  "type": "Feature",
  "properties": {
    "iso:country": "GB",
    "wof:name": "GU9 9LW",
    "wof:placetype": "postalcode"
  },
  "geometry": {"coordinates":[-0.762724,51.23152],"type":"Point"}
}
