{
  "type": "Feature",
  "properties": {
    "iso:country": "GB",
    "wof:name": "S64 8QX",
    "wof:placetype": "postalcode"
  },
  "geometry": {"coordinates":[-1.317974,53.476457],"type":"Point"}
}
