{
  "type": "Feature",
  "properties": {
    "iso:country":"GB",
    "wof:name":"NR30 5TQ",
    "wof:placetype":"postalcode"
},
  "geometry": {"coordinates":[1.71448832332888,52.64894962324923],"type":"Point"}
}