{
  "type": "Feature",
  "properties": {
    "iso:country": "GB",
    "wof:name": "NR30 5TQ",
    "wof:placetype": "postalcode"
  },
  "geometry": {"coordinates":[1.714488,52.64895],"type":"Point"}
}
