{
  "type": "Feature",
  "properties": {
    "iso:country":"GB",
    "wof:name":"TN1 1DH",
    "wof:placetype":"postalcode"
},
  "geometry": {"coordinates":[0.25953417288627,51.12695000852391],"type":"Point"}
}