{
  "type": "Feature",
  "properties": {
    "date:inception_lower": "2004-11-01",
    "date:inception_upper": "2004-11-01",
    "iso:country": "GB",
    "wof:name": "LD1 6AX",
    "wof:placetype": "postalcode"
  },
  "geometry": {"coordinates":[-3.385453,52.239623],"type":"Point"}
}
