{
  "type": "Feature",
  "properties": {
    "iso:country": "GB",
    "wof:name": "CH66 1JP",
    "wof:placetype": "postalcode"
  },
  "geometry": {"coordinates":[-2.93003,53.291674],"type":"Point"}
}
