{
  "type": "Feature",
  "properties": {
    "date:inception_lower": "1999-06-01",
    "date:inception_upper": "1999-06-01",
    "iso:country": "GB",
    "wof:name": "CH66 1JP",
    "wof:placetype": "postalcode"
  },
  "geometry": {"coordinates":[-2.93003,53.291674],"type":"Point"}
}
