{
  "type": "Feature",
  "properties": {
    "iso:country":"GB",
    "wof:name":"SE6 3TB",
    "wof:placetype":"postalcode"
},
  "geometry": {"coordinates":[-0.02270518441788,51.43606184429164],"type":"Point"}
}