{
  "type": "Feature",
  "properties": {
    "iso:country":"GB",
    "wof:name":"W1K 2HR",
    "wof:placetype":"postalcode"
},
  "geometry": {"coordinates":[-0.1503804110741,51.51087783146112],"type":"Point"}
}