{
  "type": "Feature",
  "properties": {
    "iso:country":"GB",
    "wof:name":"DL6 3TH",
    "wof:placetype":"postalcode"
},
  "geometry": {"coordinates":[-1.36969492980623,54.31539937047042],"type":"Point"}
}