{
  "type": "Feature",
  "properties": {
    "iso:country":"GB",
    "wof:name":"NP20 4LN",
    "wof:placetype":"postalcode"
},
  "geometry": {"coordinates":[-3.01281805819445,51.58447390329231],"type":"Point"}
}