{
  "type": "Feature",
  "properties": {
    "iso:country": "GB",
    "wof:name": "ST1 6AZ",
    "wof:placetype": "postalcode"
  },
  "geometry": {"coordinates":[-2.170433,53.033837],"type":"Point"}
}
