{
  "type": "Feature",
  "properties": {
    "iso:country": "GB",
    "wof:name": "TD1 2NF",
    "wof:placetype": "postalcode"
  },
  "geometry": {"coordinates":[-2.865526,55.652975],"type":"Point"}
}
