{
  "type": "Feature",
  "properties": {
    "iso:country": "GB",
    "wof:name": "AB56 4TU",
    "wof:placetype": "postalcode"
  },
  "geometry": {"coordinates":[-2.814132,57.692574],"type":"Point"}
}
