{
  "type": "Feature",
  "properties": {
    "iso:country":"GB",
    "wof:name":"AB56 4TU",
    "wof:placetype":"postalcode"
},
  "geometry": {"coordinates":[-2.81413236370951,57.69257396699653],"type":"Point"}
}