{
  "type": "Feature",
  "properties": {
    "iso:country":"GB",
    "wof:name":"TS25 1HQ",
    "wof:placetype":"postalcode"
},
  "geometry": {"coordinates":[-1.21575219176455,54.65871570673139],"type":"Point"}
}