{
  "type": "Feature",
  "properties": {
    "iso:country": "GB",
    "wof:name": "TS25 1HQ",
    "wof:placetype": "postalcode"
  },
  "geometry": {"coordinates":[-1.215752,54.658716],"type":"Point"}
}
