{
  "type": "Feature",
  "properties": {
    "date:inception_lower": "1995-07-01",
    "date:inception_upper": "1995-07-01",
    "iso:country": "GB",
    "wof:name": "RG30 3SB",
    "wof:placetype": "postalcode"
  },
  "geometry": {"coordinates":[-1.04945,51.411396],"type":"Point"}
}
