{
  "type": "Feature",
  "properties": {
    "date:inception_lower": "1980-01-01",
    "date:inception_upper": "1980-01-01",
    "iso:country": "GB",
    "wof:name": "B79 9JJ",
    "wof:placetype": "postalcode"
  },
  "geometry": {"coordinates":[-1.689034,52.706511],"type":"Point"}
}
