{
  "type": "Feature",
  "properties": {
    "iso:country":"GB",
    "wof:name":"B79 9JJ",
    "wof:placetype":"postalcode"
},
  "geometry": {"coordinates":[-1.68903387769238,52.70651127590071],"type":"Point"}
}