{
  "type": "Feature",
  "properties": {
    "iso:country": "GB",
    "wof:name": "TN24 0NA",
    "wof:placetype": "postalcode"
  },
  "geometry": {"coordinates":[0.912754,51.139724],"type":"Point"}
}
