{
  "type": "Feature",
  "properties": {
    "iso:country": "GB",
    "wof:name": "SY20 8SJ",
    "wof:placetype": "postalcode"
  },
  "geometry": {"coordinates":[-3.736118,52.57279],"type":"Point"}
}
