{
  "type": "Feature",
  "properties": {
    "iso:country":"GB",
    "wof:name":"SY20 8SJ",
    "wof:placetype":"postalcode"
},
  "geometry": {"coordinates":[-3.73611799264868,52.57279010990712],"type":"Point"}
}