{
  "type": "Feature",
  "properties": {
    "iso:country":"GB",
    "wof:name":"PR4 5SA",
    "wof:placetype":"postalcode"
},
  "geometry": {"coordinates":[-2.75793782850462,53.72824899841109],"type":"Point"}
}