{
  "type": "Feature",
  "properties": {
    "date:inception_lower": "1980-01-01",
    "date:inception_upper": "1980-01-01",
    "iso:country": "GB",
    "wof:name": "PR4 5SA",
    "wof:placetype": "postalcode"
  },
  "geometry": {"coordinates":[-2.758134,53.72839],"type":"Point"}
}
