{
  "type": "Feature",
  "properties": {
    "date:inception_lower": "1999-06-01",
    "date:inception_upper": "1999-06-01",
    "iso:country": "GB",
    "wof:name": "NP20 5JT",
    "wof:placetype": "postalcode"
  },
  "geometry": {"coordinates":[-2.995261,51.593463],"type":"Point"}
}
