{
  "type": "Feature",
  "properties": {
    "iso:country": "GB",
    "wof:name": "SY19 7EB",
    "wof:placetype": "postalcode"
  },
  "geometry": {"coordinates":[-3.658947,52.618707],"type":"Point"}
}
