{
  "type": "Feature",
  "properties": {
    "date:inception_lower":"1993-08-01",
    "date:inception_upper":"1993-08-31",
    "iso:country":"GB",
    "wof:name":"SY19 7EB",
    "wof:placetype":"postalcode"
},
  "geometry": {"coordinates":[-3.658947,52.618707],"type":"Point"}
}