{
  "type": "Feature",
  "properties": {
    "iso:country":"GB",
    "wof:name":"SY19 7EB",
    "wof:placetype":"postalcode"
},
  "geometry": {"coordinates":[-3.65894728316467,52.61870679604517],"type":"Point"}
}