{
  "type": "Feature",
  "properties": {
    "iso:country":"GB",
    "wof:name":"PO16 8AN",
    "wof:placetype":"postalcode"
},
  "geometry": {"coordinates":[-1.15457730832982,50.85056341063579],"type":"Point"}
}