{
  "type": "Feature",
  "properties": {
    "iso:country":"GB",
    "wof:name":"NP8 1HD",
    "wof:placetype":"postalcode"
},
  "geometry": {"coordinates":[-3.10397927822972,51.85485362123736],"type":"Point"}
}