{
  "type": "Feature",
  "properties": {
    "iso:country":"GB",
    "wof:name":"CF44 8RL",
    "wof:placetype":"postalcode"
},
  "geometry": {"coordinates":[-3.46926436309146,51.72070222446219],"type":"Point"}
}