{
  "type": "Feature",
  "properties": {
    "date:inception_lower": "2008-01-01",
    "date:inception_upper": "2008-01-01",
    "iso:country": "GB",
    "wof:name": "ST19 9ER",
    "wof:placetype": "postalcode"
  },
  "geometry": {"coordinates":[-2.245021,52.69155],"type":"Point"}
}
