{
  "type": "Feature",
  "properties": {
    "iso:country":"GB",
    "wof:name":"ST19 9ER",
    "wof:placetype":"postalcode"
},
  "geometry": {"coordinates":[-2.24502446857705,52.69153506711483],"type":"Point"}
}