{
  "type": "Feature",
  "properties": {
    "date:inception_lower":"2008-01-01",
    "date:inception_upper":"2008-01-31",
    "iso:country":"GB",
    "wof:name":"ST19 9ER",
    "wof:placetype":"postalcode"
},
  "geometry": {"coordinates":[-2.244977,52.691631],"type":"Point"}
}