{
  "type": "Feature",
  "properties": {
    "iso:country": "GB",
    "wof:name": "ST19 9ER",
    "wof:placetype": "postalcode"
  },
  "geometry": {"coordinates":[-2.244977,52.691631],"type":"Point"}
}
