{
  "type": "Feature",
  "properties": {
    "iso:country":"GB",
    "wof:name":"HU8 7EB",
    "wof:placetype":"postalcode"
},
  "geometry": {"coordinates":[-0.32540193321176,53.75148101741659],"type":"Point"}
}