{
  "type": "Feature",
  "properties": {
    "iso:country": "GB",
    "wof:name": "NP20 7AA",
    "wof:placetype": "postalcode"
  },
  "geometry": {"coordinates":[-3.031971,51.61442],"type":"Point"}
}
