{
  "type": "Feature",
  "properties": {
    "iso:country": "GB",
    "wof:name": "KA6 7HL",
    "wof:placetype": "postalcode"
  },
  "geometry": {"coordinates":[-4.468356,55.400173],"type":"Point"}
}
