{
  "type": "Feature",
  "properties": {
    "iso:country":"GB",
    "wof:name":"KA6 7HL",
    "wof:placetype":"postalcode"
},
  "geometry": {"coordinates":[-4.46835597258987,55.40017308404119],"type":"Point"}
}