{
  "type": "Feature",
  "properties": {
    "date:inception_lower":"1980-01-01",
    "date:inception_upper":"1980-01-31",
    "iso:country":"GB",
    "wof:name":"DY5 3UN",
    "wof:placetype":"postalcode"
},
  "geometry": {"coordinates":[-2.137816,52.484197],"type":"Point"}
}