{
  "type": "Feature",
  "properties": {
    "iso:country":"GB",
    "wof:name":"DY5 3UN",
    "wof:placetype":"postalcode"
},
  "geometry": {"coordinates":[-2.13781639858486,52.48419685905605],"type":"Point"}
}