{
  "type": "Feature",
  "properties": {
    "iso:country":"GB",
    "wof:name":"CR0 8EU",
    "wof:placetype":"postalcode"
},
  "geometry": {"coordinates":[-0.02800749494655,51.3740559816627],"type":"Point"}
}