{
  "type": "Feature",
  "properties": {
    "iso:country": "GB",
    "wof:name": "NG8 1AU",
    "wof:placetype": "postalcode"
  },
  "geometry": {"coordinates":[-1.189829,52.953202],"type":"Point"}
}
