{
  "type": "Feature",
  "properties": {
    "date:inception_lower":"1999-06-01",
    "date:inception_upper":"1999-06-30",
    "iso:country":"GB",
    "wof:name":"BD6 3XD",
    "wof:placetype":"postalcode"
},
  "geometry": {"coordinates":[-1.81711,53.770955],"type":"Point"}
}