{
  "type": "Feature",
  "properties": {
    "iso:country": "GB",
    "wof:name": "CF32 9PZ",
    "wof:placetype": "postalcode"
  },
  "geometry": {"coordinates":[-3.583824,51.541971],"type":"Point"}
}
