{
  "type": "Feature",
  "properties": {
    "iso:country": "GB",
    "wof:name": "AL2 2JZ",
    "wof:placetype": "postalcode"
  },
  "geometry": {"coordinates":[-0.332851,51.712799],"type":"Point"}
}
