{
  "type": "Feature",
  "properties": {
    "date:inception_lower": "1981-09-01",
    "date:inception_upper": "1981-09-01",
    "iso:country": "GB",
    "wof:name": "MK13 0PN",
    "wof:placetype": "postalcode"
  },
  "geometry": {"coordinates":[-0.792519,52.052281],"type":"Point"}
}
