{
  "type": "Feature",
  "properties": {
    "iso:country": "GB",
    "wof:name": "MK13 0PN",
    "wof:placetype": "postalcode"
  },
  "geometry": {"coordinates":[-0.792305,52.052099],"type":"Point"}
}
