{
  "type": "Feature",
  "properties": {
    "iso:country":"GB",
    "wof:name":"DE5 9SS",
    "wof:placetype":"postalcode"
},
  "geometry": {"coordinates":[-1.37835971058592,53.03191493508314],"type":"Point"}
}