{
  "type": "Feature",
  "properties": {
    "iso:country": "GB",
    "wof:name": "CW8 1SZ",
    "wof:placetype": "postalcode"
  },
  "geometry": {"coordinates":[-2.532189,53.243344],"type":"Point"}
}
