{
  "type": "Feature",
  "properties": {
    "date:inception_lower": "2001-06-01",
    "date:inception_upper": "2001-06-01",
    "iso:country": "GB",
    "wof:name": "B23 5JG",
    "wof:placetype": "postalcode"
  },
  "geometry": {"coordinates":[-1.865197,52.534527],"type":"Point"}
}
