{
  "type": "Feature",
  "properties": {
    "iso:country":"GB",
    "wof:name":"B23 5JG",
    "wof:placetype":"postalcode"
},
  "geometry": {"coordinates":[-1.86519681191766,52.53452650711208],"type":"Point"}
}