{
  "type": "Feature",
  "properties": {
    "iso:country":"GB",
    "wof:name":"BA6 8RH",
    "wof:placetype":"postalcode"
},
  "geometry": {"coordinates":[-2.66126058327607,51.11325639380871],"type":"Point"}
}