{
  "type": "Feature",
  "properties": {
    "iso:country":"GB",
    "wof:name":"WR11 1AW",
    "wof:placetype":"postalcode"
},
  "geometry": {"coordinates":[-1.94017066851964,52.09068709958323],"type":"Point"}
}