{
  "type": "Feature",
  "properties": {
    "iso:country": "GB",
    "wof:name": "HA4 0HR",
    "wof:placetype": "postalcode"
  },
  "geometry": {"coordinates":[-0.390831,51.560283],"type":"Point"}
}
