{
  "type": "Feature",
  "properties": {
    "iso:country":"GB",
    "wof:name":"HA4 0HR",
    "wof:placetype":"postalcode"
},
  "geometry": {"coordinates":[-0.39083135661341,51.56028329195051],"type":"Point"}
}