{
  "type": "Feature",
  "properties": {
    "iso:country":"GB",
    "wof:name":"W1W 7QF",
    "wof:placetype":"postalcode"
},
  "geometry": {"coordinates":[-0.14033540435141,51.51831765713774],"type":"Point"}
}