{
  "type": "Feature",
  "properties": {
    "iso:country":"GB",
    "wof:name":"IP16 4UE",
    "wof:placetype":"postalcode"
},
  "geometry": {"coordinates":[1.61985570115587,52.21231387914575],"type":"Point"}
}