{
  "type": "Feature",
  "properties": {
    "iso:country":"GB",
    "wof:name":"TS17 9HA",
    "wof:placetype":"postalcode"
},
  "geometry": {"coordinates":[-1.28894166501987,54.53831033146731],"type":"Point"}
}