{
  "type": "Feature",
  "properties": {
    "iso:country":"GB",
    "wof:name":"ME10 1LX",
    "wof:placetype":"postalcode"
},
  "geometry": {"coordinates":[0.70878954368851,51.34751473340844],"type":"Point"}
}