{
  "type": "Feature",
  "properties": {
    "iso:country": "GB",
    "wof:name": "ME10 1LX",
    "wof:placetype": "postalcode"
  },
  "geometry": {"coordinates":[0.70879,51.347515],"type":"Point"}
}
