{
  "type": "Feature",
  "properties": {
    "iso:country": "GB",
    "wof:name": "LA1 4BQ",
    "wof:placetype": "postalcode"
  },
  "geometry": {"coordinates":[-2.786964,54.037594],"type":"Point"}
}
