{
  "type": "Feature",
  "properties": {
    "iso:country":"GB",
    "wof:name":"LA1 4BQ",
    "wof:placetype":"postalcode"
},
  "geometry": {"coordinates":[-2.78696393331347,54.03759351667492],"type":"Point"}
}