{
  "type": "Feature",
  "properties": {
    "date:inception_lower": "2018-05-01",
    "date:inception_upper": "2018-05-01",
    "iso:country": "GB",
    "wof:name": "AL9 7ES",
    "wof:placetype": "postalcode"
  },
  "geometry": {"coordinates":[-0.204463,51.723006],"type":"Point"}
}
