{
  "type": "Feature",
  "properties": {
    "iso:country":"GB",
    "wof:name":"NP25 4RD",
    "wof:placetype":"postalcode"
},
  "geometry": {"coordinates":[-2.72170410523994,51.72303392705529],"type":"Point"}
}