{
  "type": "Feature",
  "properties": {
    "date:inception_lower": "2012-12-01",
    "date:inception_upper": "2012-12-01",
    "iso:country": "GB",
    "wof:name": "NP25 4RD",
    "wof:placetype": "postalcode"
  },
  "geometry": {"coordinates":[-2.721795,51.723028],"type":"Point"}
}
