{
  "type": "Feature",
  "properties": {
    "iso:country": "GB",
    "wof:name": "EX15 2EZ",
    "wof:placetype": "postalcode"
  },
  "geometry": {"coordinates":[-3.368639,50.89504],"type":"Point"}
}
