{
  "type": "Feature",
  "properties": {
    "iso:country":"GB",
    "wof:name":"EX15 2EZ",
    "wof:placetype":"postalcode"
},
  "geometry": {"coordinates":[-3.36859784302179,50.89505654203735],"type":"Point"}
}