{
  "type": "Feature",
  "properties": {
    "iso:country":"GB",
    "wof:name":"G43 2AH",
    "wof:placetype":"postalcode"
},
  "geometry": {"coordinates":[-4.29459551045287,55.81323410055697],"type":"Point"}
}