{
  "type": "Feature",
  "properties": {
    "date:inception_lower": "1980-01-01",
    "date:inception_upper": "1980-01-01",
    "iso:country": "GB",
    "wof:name": "N1 5TH",
    "wof:placetype": "postalcode"
  },
  "geometry": {"coordinates":[-0.082127,51.539034],"type":"Point"}
}
