{
  "type": "Feature",
  "properties": {
    "iso:country":"GB",
    "wof:name":"PL8 1AP",
    "wof:placetype":"postalcode"
},
  "geometry": {"coordinates":[-4.0363982465504,50.31611297534498],"type":"Point"}
}