{
  "type": "Feature",
  "properties": {
    "date:inception_lower": "1993-01-01",
    "date:inception_upper": "1993-01-01",
    "iso:country": "GB",
    "wof:name": "CF41 7QW",
    "wof:placetype": "postalcode"
  },
  "geometry": {"coordinates":[-3.4774,51.64737],"type":"Point"}
}
