{
  "type": "Feature",
  "properties": {
    "iso:country":"GB",
    "wof:name":"CF41 7QW",
    "wof:placetype":"postalcode"
},
  "geometry": {"coordinates":[-3.4773997450332,51.64737040700235],"type":"Point"}
}