{
  "type": "Feature",
  "properties": {
    "iso:country":"GB",
    "wof:name":"M11 1EE",
    "wof:placetype":"postalcode"
},
  "geometry": {"coordinates":[-2.16841203858294,53.47369817478208],"type":"Point"}
}