{
  "type": "Feature",
  "properties": {
    "date:inception_lower": "1980-01-01",
    "date:inception_upper": "1980-01-01",
    "iso:country": "GB",
    "wof:name": "M11 1EE",
    "wof:placetype": "postalcode"
  },
  "geometry": {"coordinates":[-2.168412,53.473698],"type":"Point"}
}
