{
  "type": "Feature",
  "properties": {
    "iso:country": "GB",
    "wof:name": "LL11 6ND",
    "wof:placetype": "postalcode"
  },
  "geometry": {"coordinates":[-3.033672,53.066647],"type":"Point"}
}
