{
  "type": "Feature",
  "properties": {
    "iso:country":"GB",
    "wof:name":"TQ6 9BD",
    "wof:placetype":"postalcode"
},
  "geometry": {"coordinates":[-3.57767246571061,50.35028999863226],"type":"Point"}
}