{
  "type": "Feature",
  "properties": {
    "date:inception_lower": "1981-06-01",
    "date:inception_upper": "1981-06-01",
    "iso:country": "GB",
    "wof:name": "NW5 4AB",
    "wof:placetype": "postalcode"
  },
  "geometry": {"coordinates":[-0.152216,51.553819],"type":"Point"}
}
