{
  "type": "Feature",
  "properties": {
    "date:inception_lower": "1980-01-01",
    "date:inception_upper": "1980-01-01",
    "iso:country": "GB",
    "wof:name": "B6 6PD",
    "wof:placetype": "postalcode"
  },
  "geometry": {"coordinates":[-1.889347,52.510162],"type":"Point"}
}
