{
  "type": "Feature",
  "properties": {
    "iso:country":"GB",
    "wof:name":"OL9 8NS",
    "wof:placetype":"postalcode"
},
  "geometry": {"coordinates":[-2.14229570898786,53.53443988498639],"type":"Point"}
}