{
  "type": "Feature",
  "properties": {
    "iso:country": "GB",
    "wof:name": "OL9 8NS",
    "wof:placetype": "postalcode"
  },
  "geometry": {"coordinates":[-2.142296,53.53444],"type":"Point"}
}
