{
  "type": "Feature",
  "properties": {
    "iso:country":"GB",
    "wof:name":"TA6 6NE",
    "wof:placetype":"postalcode"
},
  "geometry": {"coordinates":[-3.01917842319276,51.09437156326102],"type":"Point"}
}