{
  "type": "Feature",
  "properties": {
    "iso:country": "GB",
    "wof:name": "G46 8PJ",
    "wof:placetype": "postalcode"
  },
  "geometry": {"coordinates":[-4.320454,55.809185],"type":"Point"}
}
