{
  "type": "Feature",
  "properties": {
    "iso:country":"GB",
    "wof:name":"G46 8PJ",
    "wof:placetype":"postalcode"
},
  "geometry": {"coordinates":[-4.32046745606178,55.8091893238449],"type":"Point"}
}