{
  "type": "Feature",
  "properties": {
    "iso:country": "GB",
    "wof:name": "PR1 9UR",
    "wof:placetype": "postalcode"
  },
  "geometry": {"coordinates":[-2.7094,53.733346],"type":"Point"}
}
