{
  "type": "Feature",
  "properties": {
    "iso:country":"GB",
    "wof:name":"PR1 9UR",
    "wof:placetype":"postalcode"
},
  "geometry": {"coordinates":[-2.709399961087,53.73334600108475],"type":"Point"}
}