{
  "type": "Feature",
  "properties": {
    "date:inception_lower":"1980-01-01",
    "date:inception_upper":"1980-01-31",
    "iso:country":"GB",
    "wof:name":"PR1 9UR",
    "wof:placetype":"postalcode"
},
  "geometry": {"coordinates":[-2.7094,53.733346],"type":"Point"}
}