{
  "type": "Feature",
  "properties": {
    "iso:country":"GB",
    "wof:name":"LL65 1NS",
    "wof:placetype":"postalcode"
},
  "geometry": {"coordinates":[-4.6427959711141,53.31050539160346],"type":"Point"}
}