{
  "type": "Feature",
  "properties": {
    "iso:country":"GB",
    "wof:name":"BS2 0HS",
    "wof:placetype":"postalcode"
},
  "geometry": {"coordinates":[-2.58189833949611,51.45538850239783],"type":"Point"}
}