{
  "type": "Feature",
  "properties": {
    "iso:country":"GB",
    "wof:name":"M25 1AW",
    "wof:placetype":"postalcode"
},
  "geometry": {"coordinates":[-2.28338225466702,53.53059311495502],"type":"Point"}
}