{
  "type": "Feature",
  "properties": {
    "iso:country": "GB",
    "wof:name": "AB12 5BL",
    "wof:placetype": "postalcode"
  },
  "geometry": {"coordinates":[-2.099517,57.121155],"type":"Point"}
}
