{
  "type": "Feature",
  "properties": {
    "iso:country":"GB",
    "wof:name":"AB12 5BL",
    "wof:placetype":"postalcode"
},
  "geometry": {"coordinates":[-2.09951679594061,57.12115455370831],"type":"Point"}
}