{
  "type": "Feature",
  "properties": {
    "iso:country":"GB",
    "wof:name":"WR5 1NJ",
    "wof:placetype":"postalcode"
},
  "geometry": {"coordinates":[-2.18914032480571,52.19347310515056],"type":"Point"}
}