{
  "type": "Feature",
  "properties": {
    "iso:country": "GB",
    "wof:name": "WR5 1NJ",
    "wof:placetype": "postalcode"
  },
  "geometry": {"coordinates":[-2.18914,52.193473],"type":"Point"}
}
