{
  "type": "Feature",
  "properties": {
    "iso:country":"GB",
    "wof:name":"DA13 9NL",
    "wof:placetype":"postalcode"
},
  "geometry": {"coordinates":[0.31685820514875,51.41189042820296],"type":"Point"}
}