{
  "type": "Feature",
  "properties": {
    "iso:country":"GB",
    "wof:name":"YO8 4QE",
    "wof:placetype":"postalcode"
},
  "geometry": {"coordinates":[-1.07144201962691,53.78178227061989],"type":"Point"}
}