{
  "type": "Feature",
  "properties": {
    "iso:country":"GB",
    "wof:name":"CH45 1JP",
    "wof:placetype":"postalcode"
},
  "geometry": {"coordinates":[-3.04151549595236,53.42976092225109],"type":"Point"}
}