{
  "type": "Feature",
  "properties": {
    "iso:country": "GB",
    "wof:name": "TS25 1JY",
    "wof:placetype": "postalcode"
  },
  "geometry": {"coordinates":[-1.219283,54.663762],"type":"Point"}
}
