{
  "type": "Feature",
  "properties": {
    "iso:country":"GB",
    "wof:name":"TS25 1JY",
    "wof:placetype":"postalcode"
},
  "geometry": {"coordinates":[-1.21928279196262,54.66376219923085],"type":"Point"}
}