{
  "type": "Feature",
  "properties": {
    "iso:country":"GB",
    "wof:name":"HD8 9PU",
    "wof:placetype":"postalcode"
},
  "geometry": {"coordinates":[-1.61209732637751,53.59861281915573],"type":"Point"}
}