{
  "type": "Feature",
  "properties": {
    "date:inception_lower": "2003-01-01",
    "date:inception_upper": "2003-01-01",
    "iso:country": "GB",
    "wof:name": "N9 0FS",
    "wof:placetype": "postalcode"
  },
  "geometry": {"coordinates":[-0.046757,51.622783],"type":"Point"}
}
