{
  "type": "Feature",
  "properties": {
    "iso:country":"GB",
    "wof:name":"SW1P 3NP",
    "wof:placetype":"postalcode"
},
  "geometry": {"coordinates":[-0.12962152411134,51.49872344508872],"type":"Point"}
}