{
  "type": "Feature",
  "properties": {
    "iso:country": "GB",
    "wof:name": "HG1 4FH",
    "wof:placetype": "postalcode"
  },
  "geometry": {"coordinates":[-1.534438,54.004386],"type":"Point"}
}
