{
  "type": "Feature",
  "properties": {
    "iso:country":"GB",
    "wof:name":"HA9 9AW",
    "wof:placetype":"postalcode"
},
  "geometry": {"coordinates":[-0.27638017857886,51.56309116440254],"type":"Point"}
}