{
  "type": "Feature",
  "properties": {
    "date:inception_lower": "1980-01-01",
    "date:inception_upper": "1980-01-01",
    "iso:country": "GB",
    "wof:name": "BS24 8RZ",
    "wof:placetype": "postalcode"
  },
  "geometry": {"coordinates":[-2.944928,51.340523],"type":"Point"}
}
