{
  "type": "Feature",
  "properties": {
    "iso:country":"GB",
    "wof:name":"BS24 8RZ",
    "wof:placetype":"postalcode"
},
  "geometry": {"coordinates":[-2.94508189346043,51.34061509027807],"type":"Point"}
}