{
  "type": "Feature",
  "properties": {
    "iso:country":"GB",
    "wof:name":"RG27 0RF",
    "wof:placetype":"postalcode"
},
  "geometry": {"coordinates":[-0.92030888095588,51.34076012871377],"type":"Point"}
}