{
  "type": "Feature",
  "properties": {
    "iso:country": "GB",
    "wof:name": "RG27 0RF",
    "wof:placetype": "postalcode"
  },
  "geometry": {"coordinates":[-0.919658,51.340818],"type":"Point"}
}
