{
  "type": "Feature",
  "properties": {
    "iso:country":"GB",
    "wof:name":"TF1 3LD",
    "wof:placetype":"postalcode"
},
  "geometry": {"coordinates":[-2.52205007984229,52.71255517076876],"type":"Point"}
}