{
  "type": "Feature",
  "properties": {
    "date:inception_lower": "1980-01-01",
    "date:inception_upper": "1980-01-01",
    "iso:country": "GB",
    "wof:name": "TF1 3LD",
    "wof:placetype": "postalcode"
  },
  "geometry": {"coordinates":[-2.52205,52.712555],"type":"Point"}
}
