{
  "type": "Feature",
  "properties": {
    "iso:country":"GB",
    "wof:name":"N1 1DR",
    "wof:placetype":"postalcode"
},
  "geometry": {"coordinates":[-0.11749551608615,51.54159461828792],"type":"Point"}
}