{
  "type": "Feature",
  "properties": {
    "iso:country": "GB",
    "wof:name": "OX16 9PL",
    "wof:placetype": "postalcode"
  },
  "geometry": {"coordinates":[-1.342026,52.05784],"type":"Point"}
}
