{
  "type": "Feature",
  "properties": {
    "date:inception_lower": "1980-01-01",
    "date:inception_upper": "1980-01-01",
    "iso:country": "GB",
    "wof:name": "OX16 9PL",
    "wof:placetype": "postalcode"
  },
  "geometry": {"coordinates":[-1.342026,52.05784],"type":"Point"}
}
