{
  "type": "Feature",
  "properties": {
    "iso:country": "GB",
    "wof:name": "SA61 1HH",
    "wof:placetype": "postalcode"
  },
  "geometry": {"coordinates":[-4.987251,51.794625],"type":"Point"}
}
