{
  "type": "Feature",
  "properties": {
    "iso:country":"GB",
    "wof:name":"SA61 1HH",
    "wof:placetype":"postalcode"
},
  "geometry": {"coordinates":[-4.98725131152455,51.79462468826178],"type":"Point"}
}