{
  "type": "Feature",
  "properties": {
    "iso:country":"GB",
    "wof:name":"PE6 8NF",
    "wof:placetype":"postalcode"
},
  "geometry": {"coordinates":[-0.29808732910019,52.67379337123712],"type":"Point"}
}