{
  "type": "Feature",
  "properties": {
    "iso:country": "GB",
    "wof:name": "PE6 8NF",
    "wof:placetype": "postalcode"
  },
  "geometry": {"coordinates":[-0.298087,52.673793],"type":"Point"}
}
