{
  "type": "Feature",
  "properties": {
    "iso:country": "GB",
    "wof:name": "CA13 9HX",
    "wof:placetype": "postalcode"
  },
  "geometry": {"coordinates":[-3.358407,54.663942],"type":"Point"}
}
