{
  "type": "Feature",
  "properties": {
    "iso:country":"GB",
    "wof:name":"CA13 0UW",
    "wof:placetype":"postalcode"
},
  "geometry": {"coordinates":[-3.44691060904948,54.63266454559973],"type":"Point"}
}