{
  "type": "Feature",
  "properties": {
    "iso:country": "GB",
    "wof:name": "CA13 0UW",
    "wof:placetype": "postalcode"
  },
  "geometry": {"coordinates":[-3.446911,54.632665],"type":"Point"}
}
