{
  "type": "Feature",
  "properties": {
    "iso:country": "GB",
    "wof:name": "EX17 3QJ",
    "wof:placetype": "postalcode"
  },
  "geometry": {"coordinates":[-3.667034,50.774892],"type":"Point"}
}
