{
  "type": "Feature",
  "properties": {
    "date:inception_lower": "2006-08-01",
    "date:inception_upper": "2006-08-01",
    "iso:country": "GB",
    "wof:name": "PA5 8PZ",
    "wof:placetype": "postalcode"
  },
  "geometry": {"coordinates":[-4.514992,55.833464],"type":"Point"}
}
