{
  "type": "Feature",
  "properties": {
    "iso:country":"GB",
    "wof:name":"PA5 8PZ",
    "wof:placetype":"postalcode"
},
  "geometry": {"coordinates":[-4.51508987177943,55.83349375668805],"type":"Point"}
}