{
  "type": "Feature",
  "properties": {
    "iso:country":"GB",
    "wof:name":"OL12 9PF",
    "wof:placetype":"postalcode"
},
  "geometry": {"coordinates":[-2.13493853591986,53.64974101244376],"type":"Point"}
}