{
  "type": "Feature",
  "properties": {
    "iso:country":"GB",
    "wof:name":"HP12 3EJ",
    "wof:placetype":"postalcode"
},
  "geometry": {"coordinates":[-0.77557753842587,51.62957001131883],"type":"Point"}
}