{
  "type": "Feature",
  "properties": {
    "iso:country":"GB",
    "wof:name":"NE29 7QN",
    "wof:placetype":"postalcode"
},
  "geometry": {"coordinates":[-1.46455065977159,55.00683363756485],"type":"Point"}
}