{
  "type": "Feature",
  "properties": {
    "iso:country": "GB",
    "wof:name": "NE29 7QN",
    "wof:placetype": "postalcode"
  },
  "geometry": {"coordinates":[-1.464551,55.006834],"type":"Point"}
}
