{
  "type": "Feature",
  "properties": {
    "iso:country":"GB",
    "wof:name":"DL12 9PP",
    "wof:placetype":"postalcode"
},
  "geometry": {"coordinates":[-1.98108216933787,54.56910994890577],"type":"Point"}
}