{
  "type": "Feature",
  "properties": {
    "iso:country":"GB",
    "wof:name":"B69 2JD",
    "wof:placetype":"postalcode"
},
  "geometry": {"coordinates":[-2.04430498926171,52.50892842126355],"type":"Point"}
}