{
  "type": "Feature",
  "properties": {
    "iso:country": "GB",
    "wof:name": "DD10 0BG",
    "wof:placetype": "postalcode"
  },
  "geometry": {"coordinates":[-2.416544,56.774282],"type":"Point"}
}
