{
  "type": "Feature",
  "properties": {
    "iso:country":"GB",
    "wof:name":"TS5 4AT",
    "wof:placetype":"postalcode"
},
  "geometry": {"coordinates":[-1.26054907540017,54.56741104134981],"type":"Point"}
}