{
  "type": "Feature",
  "properties": {
    "iso:country": "GB",
    "wof:name": "PO1 3DR",
    "wof:placetype": "postalcode"
  },
  "geometry": {"coordinates":[-1.104472,50.797223],"type":"Point"}
}
