{
  "type": "Feature",
  "properties": {
    "date:inception_lower": "1995-01-01",
    "date:inception_upper": "1995-01-01",
    "iso:country": "GB",
    "wof:name": "IP31 3QS",
    "wof:placetype": "postalcode"
  },
  "geometry": {"coordinates":[0.812434,52.256035],"type":"Point"}
}
