{
  "type": "Feature",
  "properties": {
    "iso:country":"GB",
    "wof:name":"NE8 2BA",
    "wof:placetype":"postalcode"
},
  "geometry": {"coordinates":[-1.6030601028103,54.96578462614107],"type":"Point"}
}