{
  "type": "Feature",
  "properties": {
    "date:inception_lower": "2022-05-01",
    "date:inception_upper": "2022-05-01",
    "iso:country": "GB",
    "wof:name": "GU19 5FR",
    "wof:placetype": "postalcode"
  },
  "geometry": {"coordinates":[-0.693058,51.35714],"type":"Point"}
}
