{
  "type": "Feature",
  "properties": {
    "iso:country":"GB",
    "wof:name":"SG1 5EH",
    "wof:placetype":"postalcode"
},
  "geometry": {"coordinates":[-0.19124655012821,51.91300669123595],"type":"Point"}
}