{
  "type": "Feature",
  "properties": {
    "iso:country":"GB",
    "wof:name":"SY3 7PP",
    "wof:placetype":"postalcode"
},
  "geometry": {"coordinates":[-2.74046976405405,52.69995684119733],"type":"Point"}
}