{
  "type": "Feature",
  "properties": {
    "iso:country": "GB",
    "wof:name": "SY3 7PP",
    "wof:placetype": "postalcode"
  },
  "geometry": {"coordinates":[-2.74047,52.699957],"type":"Point"}
}
