{
  "type": "Feature",
  "properties": {
    "iso:country":"GB",
    "wof:name":"SK17 7TB",
    "wof:placetype":"postalcode"
},
  "geometry": {"coordinates":[-1.89843927647777,53.25560262842668],"type":"Point"}
}