{
  "type": "Feature",
  "properties": {
    "iso:country": "GB",
    "wof:name": "NR22 6EF",
    "wof:placetype": "postalcode"
  },
  "geometry": {"coordinates":[0.876223,52.894818],"type":"Point"}
}
