{
  "type": "Feature",
  "properties": {
    "date:inception_lower": "1980-01-01",
    "date:inception_upper": "1980-01-01",
    "iso:country": "GB",
    "wof:name": "DL2 3PF",
    "wof:placetype": "postalcode"
  },
  "geometry": {"coordinates":[-1.792996,54.579836],"type":"Point"}
}
