{
  "type": "Feature",
  "properties": {
    "iso:country": "GB",
    "wof:name": "BH21 5LF",
    "wof:placetype": "postalcode"
  },
  "geometry": {"coordinates":[-2.034035,50.891245],"type":"Point"}
}
