{
  "type": "Feature",
  "properties": {
    "iso:country":"GB",
    "wof:name":"BH21 5LF",
    "wof:placetype":"postalcode"
},
  "geometry": {"coordinates":[-2.03404231390548,50.89125186653261],"type":"Point"}
}