{
  "type": "Feature",
  "properties": {
    "date:inception_lower": "1980-01-01",
    "date:inception_upper": "1980-01-01",
    "iso:country": "GB",
    "wof:name": "BH21 5LF",
    "wof:placetype": "postalcode"
  },
  "geometry": {"coordinates":[-2.034035,50.891245],"type":"Point"}
}
