{
  "type": "Feature",
  "properties": {
    "date:inception_lower": "1999-06-01",
    "date:inception_upper": "1999-06-01",
    "iso:country": "GB",
    "wof:name": "CF10 5GP",
    "wof:placetype": "postalcode"
  },
  "geometry": {"coordinates":[-3.17948,51.472884],"type":"Point"}
}
