{
  "type": "Feature",
  "properties": {
    "iso:country":"GB",
    "wof:name":"CF10 5GP",
    "wof:placetype":"postalcode"
},
  "geometry": {"coordinates":[-3.17947988514989,51.47288372091153],"type":"Point"}
}