{
  "type": "Feature",
  "properties": {
    "iso:country":"GB",
    "wof:name":"PL9 9JT",
    "wof:placetype":"postalcode"
},
  "geometry": {"coordinates":[-4.08749416325621,50.35633761202627],"type":"Point"}
}