{
  "type": "Feature",
  "properties": {
    "iso:country": "GB",
    "wof:name": "PL9 9JT",
    "wof:placetype": "postalcode"
  },
  "geometry": {"coordinates":[-4.087494,50.356338],"type":"Point"}
}
