{
  "type": "Feature",
  "properties": {
    "iso:country":"GB",
    "wof:name":"HA4 7UZ",
    "wof:placetype":"postalcode"
},
  "geometry": {"coordinates":[-0.41368296490882,51.58432466491207],"type":"Point"}
}