{
  "type": "Feature",
  "properties": {
    "date:inception_lower": "2022-07-01",
    "date:inception_upper": "2022-07-01",
    "iso:country": "GB",
    "wof:name": "CV34 8BS",
    "wof:placetype": "postalcode"
  },
  "geometry": {"coordinates":[-1.558775,52.271068],"type":"Point"}
}
