{
  "type": "Feature",
  "properties": {
    "date:inception_lower": "1992-01-01",
    "date:inception_upper": "1992-01-01",
    "iso:country": "GB",
    "wof:name": "BA14 8QX",
    "wof:placetype": "postalcode"
  },
  "geometry": {"coordinates":[-2.203373,51.32662],"type":"Point"}
}
