{
  "type": "Feature",
  "properties": {
    "iso:country":"GB",
    "wof:name":"BA14 8QX",
    "wof:placetype":"postalcode"
},
  "geometry": {"coordinates":[-2.20337264253139,51.32661971357625],"type":"Point"}
}