{
  "type": "Feature",
  "properties": {
    "iso:country": "GB",
    "wof:name": "BA14 8QX",
    "wof:placetype": "postalcode"
  },
  "geometry": {"coordinates":[-2.203373,51.32662],"type":"Point"}
}
