{
  "type": "Feature",
  "properties": {
    "iso:country":"GB",
    "wof:name":"SW16 1TL",
    "wof:placetype":"postalcode"
},
  "geometry": {"coordinates":[-0.13947601580585,51.42722734337838],"type":"Point"}
}