{
  "type": "Feature",
  "properties": {
    "iso:country": "GB",
    "wof:name": "OL15 9NX",
    "wof:placetype": "postalcode"
  },
  "geometry": {"coordinates":[-2.099578,53.653973],"type":"Point"}
}
