{
  "type": "Feature",
  "properties": {
    "date:inception_lower": "1980-01-01",
    "date:inception_upper": "1980-01-01",
    "iso:country": "GB",
    "wof:name": "OL15 9NX",
    "wof:placetype": "postalcode"
  },
  "geometry": {"coordinates":[-2.099578,53.653973],"type":"Point"}
}
