{
  "type": "Feature",
  "properties": {
    "iso:country":"GB",
    "wof:name":"SS1 2SF",
    "wof:placetype":"postalcode"
},
  "geometry": {"coordinates":[0.73188711887131,51.53560561846996],"type":"Point"}
}