{
  "type": "Feature",
  "properties": {
    "iso:country": "GB",
    "wof:name": "SS1 2SF",
    "wof:placetype": "postalcode"
  },
  "geometry": {"coordinates":[0.731917,51.535609],"type":"Point"}
}
