{
  "type": "Feature",
  "properties": {
    "iso:country":"GB",
    "wof:name":"SK6 2AY",
    "wof:placetype":"postalcode"
},
  "geometry": {"coordinates":[-2.11607026991583,53.42294865972067],"type":"Point"}
}