{
  "type": "Feature",
  "properties": {
    "date:inception_lower": "1987-04-01",
    "date:inception_upper": "1987-04-01",
    "iso:country": "GB",
    "wof:name": "IP4 4ED",
    "wof:placetype": "postalcode"
  },
  "geometry": {"coordinates":[1.176203,52.060521],"type":"Point"}
}
