{
  "type": "Feature",
  "properties": {
    "iso:country":"GB",
    "wof:name":"IP4 4ED",
    "wof:placetype":"postalcode"
},
  "geometry": {"coordinates":[1.17620272180797,52.06052147221271],"type":"Point"}
}