{
  "type": "Feature",
  "properties": {
    "date:inception_lower":"2000-12-01",
    "date:inception_upper":"2000-12-31",
    "iso:country":"GB",
    "wof:name":"SE1 3LY",
    "wof:placetype":"postalcode"
},
  "geometry": {"coordinates":[-0.0781,51.500435],"type":"Point"}
}