{
  "type": "Feature",
  "properties": {
    "iso:country":"GB",
    "wof:name":"SE1 3LY",
    "wof:placetype":"postalcode"
},
  "geometry": {"coordinates":[-0.07810025655245,51.50043531825286],"type":"Point"}
}