{
  "type": "Feature",
  "properties": {
    "date:inception_lower": "2003-02-01",
    "date:inception_upper": "2003-02-01",
    "iso:country": "GB",
    "wof:name": "CH43 7PX",
    "wof:placetype": "postalcode"
  },
  "geometry": {"coordinates":[-3.069418,53.3907],"type":"Point"}
}
