{
  "type": "Feature",
  "properties": {
    "iso:country":"GB",
    "wof:name":"TQ5 0PF",
    "wof:placetype":"postalcode"
},
  "geometry": {"coordinates":[-3.56531535260482,50.39852007655732],"type":"Point"}
}