{
  "type": "Feature",
  "properties": {
    "iso:country": "GB",
    "wof:name": "NR20 5JU",
    "wof:placetype": "postalcode"
  },
  "geometry": {"coordinates":[0.945177,52.755127],"type":"Point"}
}
