{
  "type": "Feature",
  "properties": {
    "iso:country":"GB",
    "wof:name":"OX9 3JG",
    "wof:placetype":"postalcode"
},
  "geometry": {"coordinates":[-0.96889709124903,51.74321789587861],"type":"Point"}
}