{
  "type": "Feature",
  "properties": {
    "iso:country": "GB",
    "wof:name": "LL53 7NY",
    "wof:placetype": "postalcode"
  },
  "geometry": {"coordinates":[-4.489854,52.858321],"type":"Point"}
}
