{
  "type": "Feature",
  "properties": {
    "iso:country":"GB",
    "wof:name":"HD2 2HR",
    "wof:placetype":"postalcode"
},
  "geometry": {"coordinates":[-1.79347693306103,53.67694576903987],"type":"Point"}
}