{
  "type": "Feature",
  "properties": {
    "iso:country":"GB",
    "wof:name":"TQ2 6ED",
    "wof:placetype":"postalcode"
},
  "geometry": {"coordinates":[-3.55291381341504,50.46763233228742],"type":"Point"}
}