{
  "type": "Feature",
  "properties": {
    "iso:country":"GB",
    "wof:name":"NR7 9NF",
    "wof:placetype":"postalcode"
},
  "geometry": {"coordinates":[1.33740879477357,52.63949608610369],"type":"Point"}
}