{
  "type": "Feature",
  "properties": {
    "iso:country":"GB",
    "wof:name":"DG2 0QH",
    "wof:placetype":"postalcode"
},
  "geometry": {"coordinates":[-3.62136756937687,55.08010253792697],"type":"Point"}
}