{
  "type": "Feature",
  "properties": {
    "date:inception_lower": "2022-03-01",
    "date:inception_upper": "2022-03-01",
    "iso:country": "GB",
    "wof:name": "DL15 8FE",
    "wof:placetype": "postalcode"
  },
  "geometry": {"coordinates":[-1.755444,54.693537],"type":"Point"}
}
