{
  "type": "Feature",
  "properties": {
    "iso:country":"GB",
    "wof:name":"CF32 7EL",
    "wof:placetype":"postalcode"
},
  "geometry": {"coordinates":[-3.54317389343061,51.60590729380188],"type":"Point"}
}