{
  "type": "Feature",
  "properties": {
    "iso:country": "GB",
    "wof:name": "BR5 3SA",
    "wof:placetype": "postalcode"
  },
  "geometry": {"coordinates":[0.109595,51.40049],"type":"Point"}
}
