{
  "type": "Feature",
  "properties": {
    "iso:country":"GB",
    "wof:name":"BR5 3SA",
    "wof:placetype":"postalcode"
},
  "geometry": {"coordinates":[0.10959472879913,51.40049030687113],"type":"Point"}
}