{
  "type": "Feature",
  "properties": {
    "iso:country":"GB",
    "wof:name":"BR1 2NB",
    "wof:placetype":"postalcode"
},
  "geometry": {"coordinates":[0.03896531188261,51.40253204454996],"type":"Point"}
}