{
  "type": "Feature",
  "properties": {
    "iso:country":"GB",
    "wof:name":"WD3 4AW",
    "wof:placetype":"postalcode"
},
  "geometry": {"coordinates":[-0.46829463809141,51.65574523576484],"type":"Point"}
}