{
  "type": "Feature",
  "properties": {
    "date:inception_lower": "2007-01-01",
    "date:inception_upper": "2007-01-01",
    "iso:country": "GB",
    "wof:name": "MK18 1HN",
    "wof:placetype": "postalcode"
  },
  "geometry": {"coordinates":[-0.976416,52.015567],"type":"Point"}
}
