{
  "type": "Feature",
  "properties": {
    "iso:country": "GB",
    "wof:name": "MK18 1HN",
    "wof:placetype": "postalcode"
  },
  "geometry": {"coordinates":[-0.976416,52.015567],"type":"Point"}
}
