{
  "type": "Feature",
  "properties": {
    "date:inception_lower": "1980-01-01",
    "date:inception_upper": "1980-01-01",
    "iso:country": "GB",
    "wof:name": "NR7 9LE",
    "wof:placetype": "postalcode"
  },
  "geometry": {"coordinates":[1.343875,52.643631],"type":"Point"}
}
