{
  "type": "Feature",
  "properties": {
    "iso:country":"GB",
    "wof:name":"NR7 9LE",
    "wof:placetype":"postalcode"
},
  "geometry": {"coordinates":[1.34387464128939,52.64363060723782],"type":"Point"}
}