{
  "type": "Feature",
  "properties": {
    "iso:country":"GB",
    "wof:name":"RM14 1XS",
    "wof:placetype":"postalcode"
},
  "geometry": {"coordinates":[0.2680705431702,51.56410823689833],"type":"Point"}
}