{
  "type": "Feature",
  "properties": {
    "iso:country":"GB",
    "wof:name":"S1 2BW",
    "wof:placetype":"postalcode"
},
  "geometry": {"coordinates":[-1.46371358142462,53.37867490651829],"type":"Point"}
}