{
  "type": "Feature",
  "properties": {
    "date:inception_lower": "1980-01-01",
    "date:inception_upper": "1980-01-01",
    "iso:country": "GB",
    "wof:name": "S1 2BW",
    "wof:placetype": "postalcode"
  },
  "geometry": {"coordinates":[-1.463714,53.378675],"type":"Point"}
}
