{
  "type": "Feature",
  "properties": {
    "iso:country": "GB",
    "wof:name": "CV36 4HL",
    "wof:placetype": "postalcode"
  },
  "geometry": {"coordinates":[-1.629647,52.060857],"type":"Point"}
}
