{
  "type": "Feature",
  "properties": {
    "iso:country": "GB",
    "wof:name": "BD12 7HJ",
    "wof:placetype": "postalcode"
  },
  "geometry": {"coordinates":[-1.741028,53.750241],"type":"Point"}
}
