{
  "type": "Feature",
  "properties": {
    "iso:country":"GB",
    "wof:name":"SP4 6LX",
    "wof:placetype":"postalcode"
},
  "geometry": {"coordinates":[-1.72997994911654,51.11827834159241],"type":"Point"}
}