{
  "type": "Feature",
  "properties": {
    "iso:country":"GB",
    "wof:name":"FK13 6PQ",
    "wof:placetype":"postalcode"
},
  "geometry": {"coordinates":[-3.72868205928849,56.15632261033543],"type":"Point"}
}