{
  "type": "Feature",
  "properties": {
    "iso:country":"GB",
    "wof:name":"CM3 1AS",
    "wof:placetype":"postalcode"
},
  "geometry": {"coordinates":[0.45714917362381,51.79490296935636],"type":"Point"}
}