{
  "type": "Feature",
  "properties": {
    "iso:country":"GB",
    "wof:name":"CH42 8PY",
    "wof:placetype":"postalcode"
},
  "geometry": {"coordinates":[-3.04816659005525,53.37219117111052],"type":"Point"}
}