{
  "type": "Feature",
  "properties": {
    "iso:country":"GB",
    "wof:name":"DT2 0LL",
    "wof:placetype":"postalcode"
},
  "geometry": {"coordinates":[-2.57570787846266,50.83383051625011],"type":"Point"}
}