{
  "type": "Feature",
  "properties": {
    "iso:country": "GB",
    "wof:name": "DT2 0LL",
    "wof:placetype": "postalcode"
  },
  "geometry": {"coordinates":[-2.575708,50.833831],"type":"Point"}
}
