{
  "type": "Feature",
  "properties": {
    "date:inception_lower": "1980-01-01",
    "date:inception_upper": "1980-01-01",
    "iso:country": "GB",
    "wof:name": "CM24 8HY",
    "wof:placetype": "postalcode"
  },
  "geometry": {"coordinates":[0.186829,51.907172],"type":"Point"}
}
