{
  "type": "Feature",
  "properties": {
    "iso:country": "GB",
    "wof:name": "CM24 8HY",
    "wof:placetype": "postalcode"
  },
  "geometry": {"coordinates":[0.186829,51.907172],"type":"Point"}
}
