{
  "type": "Feature",
  "properties": {
    "iso:country":"GB",
    "wof:name":"BR6 9LA",
    "wof:placetype":"postalcode"
},
  "geometry": {"coordinates":[0.09086010457804,51.36325351994064],"type":"Point"}
}