{
  "type": "Feature",
  "properties": {
    "date:inception_lower": "2022-02-01",
    "date:inception_upper": "2022-02-01",
    "iso:country": "GB",
    "wof:name": "BR6 9LA",
    "wof:placetype": "postalcode"
  },
  "geometry": {"coordinates":[0.090873,51.363264],"type":"Point"}
}
