{
  "type": "Feature",
  "properties": {
    "iso:country":"GB",
    "wof:name":"EX2 9ES",
    "wof:placetype":"postalcode"
},
  "geometry": {"coordinates":[-3.53805841021064,50.7124258454479],"type":"Point"}
}