{
  "type": "Feature",
  "properties": {
    "iso:country": "GB",
    "wof:name": "LA3 2PW",
    "wof:placetype": "postalcode"
  },
  "geometry": {"coordinates":[-2.89887,54.045914],"type":"Point"}
}
