{
  "type": "Feature",
  "properties": {
    "date:inception_lower": "1980-01-01",
    "date:inception_upper": "1980-01-01",
    "iso:country": "GB",
    "wof:name": "B45 0JG",
    "wof:placetype": "postalcode"
  },
  "geometry": {"coordinates":[-2.004211,52.40464],"type":"Point"}
}
