{
  "type": "Feature",
  "properties": {
    "iso:country":"GB",
    "wof:name":"B45 0JG",
    "wof:placetype":"postalcode"
},
  "geometry": {"coordinates":[-2.00420385410296,52.40469775666977],"type":"Point"}
}