{
  "type": "Feature",
  "properties": {
    "iso:country":"GB",
    "wof:name":"TS23 2QG",
    "wof:placetype":"postalcode"
},
  "geometry": {"coordinates":[-1.2894535904433,54.6031457018725],"type":"Point"}
}