{
  "type": "Feature",
  "properties": {
    "date:inception_lower":"1997-12-01",
    "date:inception_upper":"1997-12-31",
    "iso:country":"GB",
    "wof:name":"SW4 6EJ",
    "wof:placetype":"postalcode"
},
  "geometry": {"coordinates":[-0.132561,51.464158],"type":"Point"}
}