{
  "type": "Feature",
  "properties": {
    "iso:country":"GB",
    "wof:name":"SW4 6EJ",
    "wof:placetype":"postalcode"
},
  "geometry": {"coordinates":[-0.1325612298746,51.46415793116325],"type":"Point"}
}