{
  "type": "Feature",
  "properties": {
    "date:inception_lower":"2007-11-01",
    "date:inception_upper":"2007-11-30",
    "iso:country":"GB",
    "wof:name":"UB6 0FD",
    "wof:placetype":"postalcode"
},
  "geometry": {"coordinates":[-0.351691,51.545164],"type":"Point"}
}