{
  "type": "Feature",
  "properties": {
    "iso:country": "GB",
    "wof:name": "UB6 0FD",
    "wof:placetype": "postalcode"
  },
  "geometry": {"coordinates":[-0.351691,51.545164],"type":"Point"}
}
