{
  "type": "Feature",
  "properties": {
    "iso:country":"GB",
    "wof:name":"TS16 0RN",
    "wof:placetype":"postalcode"
},
  "geometry": {"coordinates":[-1.35379818870382,54.51647602678783],"type":"Point"}
}