{
  "type": "Feature",
  "properties": {
    "iso:country": "GB",
    "wof:name": "IG10 1TZ",
    "wof:placetype": "postalcode"
  },
  "geometry": {"coordinates":[0.064524,51.648191],"type":"Point"}
}
