{
  "type": "Feature",
  "properties": {
    "iso:country":"GB",
    "wof:name":"IG10 1TZ",
    "wof:placetype":"postalcode"
},
  "geometry": {"coordinates":[0.06461653819436,51.64826807973999],"type":"Point"}
}