{
  "type": "Feature",
  "properties": {
    "iso:country":"GB",
    "wof:name":"RM17 5AZ",
    "wof:placetype":"postalcode"
},
  "geometry": {"coordinates":[0.32226437105411,51.48532068790753],"type":"Point"}
}