{
  "type": "Feature",
  "properties": {
    "iso:country":"GB",
    "wof:name":"N10 2AN",
    "wof:placetype":"postalcode"
},
  "geometry": {"coordinates":[-0.13652728628786,51.59709402555354],"type":"Point"}
}