{
  "type": "Feature",
  "properties": {
    "iso:country":"GB",
    "wof:name":"TN12 7EQ",
    "wof:placetype":"postalcode"
},
  "geometry": {"coordinates":[0.36709112417783,51.15783729971906],"type":"Point"}
}