{
  "type": "Feature",
  "properties": {
    "iso:country": "GB",
    "wof:name": "SG19 2AJ",
    "wof:placetype": "postalcode"
  },
  "geometry": {"coordinates":[-0.303454,52.152406],"type":"Point"}
}
