{
  "type": "Feature",
  "properties": {
    "iso:country":"GB",
    "wof:name":"W11 2NT",
    "wof:placetype":"postalcode"
},
  "geometry": {"coordinates":[-0.20784439784753,51.51181491275979],"type":"Point"}
}