{
  "type": "Feature",
  "properties": {
    "iso:country":"GB",
    "wof:name":"IP22 4PP",
    "wof:placetype":"postalcode"
},
  "geometry": {"coordinates":[1.11501900314697,52.37394840203886],"type":"Point"}
}