{
  "type": "Feature",
  "properties": {
    "date:inception_lower": "2024-02-01",
    "date:inception_upper": "2024-02-01",
    "iso:country": "GB",
    "wof:name": "B69 3GA",
    "wof:placetype": "postalcode"
  },
  "geometry": {"coordinates":[-2.032222,52.515052],"type":"Point"}
}
