{
  "type": "Feature",
  "properties": {
    "iso:country":"GB",
    "wof:name":"SY10 8QG",
    "wof:placetype":"postalcode"
},
  "geometry": {"coordinates":[-3.04069176212862,52.78409437801758],"type":"Point"}
}