{
  "type": "Feature",
  "properties": {
    "iso:country":"GB",
    "wof:name":"SW10 0TU",
    "wof:placetype":"postalcode"
},
  "geometry": {"coordinates":[-0.18339086051845,51.48094521494983],"type":"Point"}
}