{
  "type": "Feature",
  "properties": {
    "iso:country": "GB",
    "wof:name": "SW10 0TU",
    "wof:placetype": "postalcode"
  },
  "geometry": {"coordinates":[-0.183367,51.480946],"type":"Point"}
}
