{
  "type": "Feature",
  "properties": {
    "iso:country":"GB",
    "wof:name":"TR24 0QQ",
    "wof:placetype":"postalcode"
},
  "geometry": {"coordinates":[-6.32993566788241,49.94810406114618],"type":"Point"}
}