{
  "type": "Feature",
  "properties": {
    "date:inception_lower":"1980-01-01",
    "date:inception_upper":"1980-01-31",
    "iso:country":"GB",
    "wof:name":"CV37 8PN",
    "wof:placetype":"postalcode"
},
  "geometry": {"coordinates":[-1.788863,52.176283],"type":"Point"}
}