{
  "type": "Feature",
  "properties": {
    "iso:country":"GB",
    "wof:name":"NN3 7PL",
    "wof:placetype":"postalcode"
},
  "geometry": {"coordinates":[-0.85732272282044,52.28854856480081],"type":"Point"}
}