{
  "type": "Feature",
  "properties": {
    "iso:country":"GB",
    "wof:name":"NP7 9RF",
    "wof:placetype":"postalcode"
},
  "geometry": {"coordinates":[-3.06437859355547,51.81832733760241],"type":"Point"}
}