{
  "type": "Feature",
  "properties": {
    "iso:country": "GB",
    "wof:name": "ME17 1FR",
    "wof:placetype": "postalcode"
  },
  "geometry": {"coordinates":[0.666865,51.243051],"type":"Point"}
}
