{
  "type": "Feature",
  "properties": {
    "iso:country":"GB",
    "wof:name":"ME17 1FR",
    "wof:placetype":"postalcode"
},
  "geometry": {"coordinates":[0.66686537145508,51.24305071394285],"type":"Point"}
}