{
  "type": "Feature",
  "properties": {
    "iso:country":"GB",
    "wof:name":"SP8 5AZ",
    "wof:placetype":"postalcode"
},
  "geometry": {"coordinates":[-2.32856575402563,51.07767161586186],"type":"Point"}
}