{
  "type": "Feature",
  "properties": {
    "date:inception_lower": "1980-01-01",
    "date:inception_upper": "1980-01-01",
    "iso:country": "GB",
    "wof:name": "SP8 5AZ",
    "wof:placetype": "postalcode"
  },
  "geometry": {"coordinates":[-2.327815,51.076939],"type":"Point"}
}
