{
  "type": "Feature",
  "properties": {
    "iso:country":"GB",
    "wof:name":"BH1 2JJ",
    "wof:placetype":"postalcode"
},
  "geometry": {"coordinates":[-1.87432170111448,50.72181503076123],"type":"Point"}
}