{
  "type": "Feature",
  "properties": {
    "iso:country": "GB",
    "wof:name": "LE2 5PU",
    "wof:placetype": "postalcode"
  },
  "geometry": {"coordinates":[-1.081072,52.590274],"type":"Point"}
}
