{
  "type": "Feature",
  "properties": {
    "iso:country":"GB",
    "wof:name":"LE2 5PU",
    "wof:placetype":"postalcode"
},
  "geometry": {"coordinates":[-1.08107229993989,52.59027413185633],"type":"Point"}
}