{
  "type": "Feature",
  "properties": {
    "date:inception_lower": "1980-01-01",
    "date:inception_upper": "1980-01-01",
    "iso:country": "GB",
    "wof:name": "TD1 3EF",
    "wof:placetype": "postalcode"
  },
  "geometry": {"coordinates":[-2.791307,55.607255],"type":"Point"}
}
