{
  "type": "Feature",
  "properties": {
    "date:inception_lower": "2013-11-01",
    "date:inception_upper": "2013-11-01",
    "iso:country": "GB",
    "wof:name": "LE65 1GA",
    "wof:placetype": "postalcode"
  },
  "geometry": {"coordinates":[-1.458404,52.745705],"type":"Point"}
}
