{
  "type": "Feature",
  "properties": {
    "iso:country": "GB",
    "wof:name": "LE65 1GA",
    "wof:placetype": "postalcode"
  },
  "geometry": {"coordinates":[-1.458404,52.745705],"type":"Point"}
}
