{
  "type": "Feature",
  "properties": {
    "iso:country":"GB",
    "wof:name":"LE65 1GA",
    "wof:placetype":"postalcode"
},
  "geometry": {"coordinates":[-1.45840355262927,52.74570473231228],"type":"Point"}
}