{
  "type": "Feature",
  "properties": {
    "iso:country":"GB",
    "wof:name":"DG8 0BH",
    "wof:placetype":"postalcode"
},
  "geometry": {"coordinates":[-4.6085239460464,54.91075069343027],"type":"Point"}
}