{
  "type": "Feature",
  "properties": {
    "iso:country":"GB",
    "wof:name":"NE34 7NL",
    "wof:placetype":"postalcode"
},
  "geometry": {"coordinates":[-1.4049502353141,54.9697938012415],"type":"Point"}
}