{
  "type": "Feature",
  "properties": {
    "iso:country": "GB",
    "wof:name": "NE34 7NL",
    "wof:placetype": "postalcode"
  },
  "geometry": {"coordinates":[-1.40495,54.969794],"type":"Point"}
}
