{
  "type": "Feature",
  "properties": {
    "date:inception_lower":"1980-01-01",
    "date:inception_upper":"1980-01-31",
    "iso:country":"GB",
    "wof:name":"RG24 9PR",
    "wof:placetype":"postalcode"
},
  "geometry": {"coordinates":[-1.082042,51.290138],"type":"Point"}
}