{
  "type": "Feature",
  "properties": {
    "iso:country":"GB",
    "wof:name":"RG24 9PR",
    "wof:placetype":"postalcode"
},
  "geometry": {"coordinates":[-1.08204225395045,51.2901381141998],"type":"Point"}
}