{
  "type": "Feature",
  "properties": {
    "date:inception_lower":"1980-01-01",
    "date:inception_upper":"1980-01-31",
    "iso:country":"GB",
    "wof:name":"LA14 4JD",
    "wof:placetype":"postalcode"
},
  "geometry": {"coordinates":[-3.221209,54.135128],"type":"Point"}
}