{
  "type": "Feature",
  "properties": {
    "iso:country":"GB",
    "wof:name":"LA14 4JD",
    "wof:placetype":"postalcode"
},
  "geometry": {"coordinates":[-3.22120910173915,54.13512822190617],"type":"Point"}
}