{
  "type": "Feature",
  "properties": {
    "iso:country": "GB",
    "wof:name": "LA14 4JD",
    "wof:placetype": "postalcode"
  },
  "geometry": {"coordinates":[-3.221209,54.135128],"type":"Point"}
}
