{
  "type": "Feature",
  "properties": {
    "iso:country":"GB",
    "wof:name":"NG10 1ES",
    "wof:placetype":"postalcode"
},
  "geometry": {"coordinates":[-1.26799604289891,52.89362321825844],"type":"Point"}
}