{
  "type": "Feature",
  "properties": {
    "iso:country": "GB",
    "wof:name": "NG10 1ES",
    "wof:placetype": "postalcode"
  },
  "geometry": {"coordinates":[-1.267996,52.893623],"type":"Point"}
}
