{
  "type": "Feature",
  "properties": {
    "iso:country":"GB",
    "wof:name":"WF8 3RH",
    "wof:placetype":"postalcode"
},
  "geometry": {"coordinates":[-1.30923578047138,53.68311454963855],"type":"Point"}
}