{
  "type": "Feature",
  "properties": {
    "iso:country":"GB",
    "wof:name":"RM9 6JD",
    "wof:placetype":"postalcode"
},
  "geometry": {"coordinates":[0.13879950635999,51.53820882749815],"type":"Point"}
}