{
  "type": "Feature",
  "properties": {
    "date:inception_lower": "1980-01-01",
    "date:inception_upper": "1980-01-01",
    "iso:country": "GB",
    "wof:name": "RM9 6JD",
    "wof:placetype": "postalcode"
  },
  "geometry": {"coordinates":[0.1388,51.538209],"type":"Point"}
}
