{
  "type": "Feature",
  "properties": {
    "iso:country":"GB",
    "wof:name":"RH10 1RP",
    "wof:placetype":"postalcode"
},
  "geometry": {"coordinates":[-0.16811707146254,51.12334397269451],"type":"Point"}
}