{
  "type": "Feature",
  "properties": {
    "iso:country": "GB",
    "wof:name": "BH25 7QW",
    "wof:placetype": "postalcode"
  },
  "geometry": {"coordinates":[-1.670827,50.738531],"type":"Point"}
}
