{
  "type": "Feature",
  "properties": {
    "date:inception_lower": "2005-07-01",
    "date:inception_upper": "2005-07-01",
    "iso:country": "GB",
    "wof:name": "OX1 1HD",
    "wof:placetype": "postalcode"
  },
  "geometry": {"coordinates":[-1.264091,51.751263],"type":"Point"}
}
