{
  "type": "Feature",
  "properties": {
    "iso:country": "GB",
    "wof:name": "OX1 1HD",
    "wof:placetype": "postalcode"
  },
  "geometry": {"coordinates":[-1.264091,51.751263],"type":"Point"}
}
