{
  "type": "Feature",
  "properties": {
    "iso:country":"GB",
    "wof:name":"OX1 1HD",
    "wof:placetype":"postalcode"
},
  "geometry": {"coordinates":[-1.26409069255235,51.75126262229409],"type":"Point"}
}