{
  "type": "Feature",
  "properties": {
    "iso:country":"GB",
    "wof:name":"CB22 3DF",
    "wof:placetype":"postalcode"
},
  "geometry": {"coordinates":[0.1760335602009,52.1288783202823],"type":"Point"}
}