{
  "type": "Feature",
  "properties": {
    "iso:country": "GB",
    "wof:name": "BH10 6AU",
    "wof:placetype": "postalcode"
  },
  "geometry": {"coordinates":[-1.88231,50.756499],"type":"Point"}
}
