{
  "type": "Feature",
  "properties": {
    "iso:country": "GB",
    "wof:name": "CV11 6ZA",
    "wof:placetype": "postalcode"
  },
  "geometry": {"coordinates":[-1.404161,52.496093],"type":"Point"}
}
