{
  "type": "Feature",
  "properties": {
    "iso:country":"GB",
    "wof:name":"CV11 6ZA",
    "wof:placetype":"postalcode"
},
  "geometry": {"coordinates":[-1.40416106217327,52.49609275988784],"type":"Point"}
}