{
  "type": "Feature",
  "properties": {
    "iso:country": "GB",
    "wof:name": "PE21 9DR",
    "wof:placetype": "postalcode"
  },
  "geometry": {"coordinates":[-0.015086,52.988037],"type":"Point"}
}
