{
  "type": "Feature",
  "properties": {
    "iso:country": "GB",
    "wof:name": "LN6 7LE",
    "wof:placetype": "postalcode"
  },
  "geometry": {"coordinates":[-0.5767,53.201606],"type":"Point"}
}
