{
  "type": "Feature",
  "properties": {
    "iso:country":"GB",
    "wof:name":"LN6 7LE",
    "wof:placetype":"postalcode"
},
  "geometry": {"coordinates":[-0.57655204409575,53.20157342283244],"type":"Point"}
}