{
  "type": "Feature",
  "properties": {
    "date:inception_lower": "1994-05-01",
    "date:inception_upper": "1994-05-01",
    "iso:country": "GB",
    "wof:name": "M43 7LA",
    "wof:placetype": "postalcode"
  },
  "geometry": {"coordinates":[-2.133325,53.488636],"type":"Point"}
}
