{
  "type": "Feature",
  "properties": {
    "date:inception_lower": "2016-06-01",
    "date:inception_upper": "2016-06-01",
    "iso:country": "GB",
    "wof:name": "EH49 9BB",
    "wof:placetype": "postalcode"
  },
  "geometry": {"coordinates":[-3.628545,55.98217],"type":"Point"}
}
