{
  "type": "Feature",
  "properties": {
    "date:inception_lower": "1997-06-01",
    "date:inception_upper": "1997-06-01",
    "iso:country": "GB",
    "wof:name": "IP5 3QS",
    "wof:placetype": "postalcode"
  },
  "geometry": {"coordinates":[1.269397,52.0671],"type":"Point"}
}
