{
  "type": "Feature",
  "properties": {
    "iso:country":"GB",
    "wof:name":"IP5 3QS",
    "wof:placetype":"postalcode"
},
  "geometry": {"coordinates":[1.26939726209651,52.06709975111648],"type":"Point"}
}