{
  "type": "Feature",
  "properties": {
    "iso:country":"GB",
    "wof:name":"B26 2EH",
    "wof:placetype":"postalcode"
},
  "geometry": {"coordinates":[-1.79154995515431,52.47402550575088],"type":"Point"}
}