{
  "type": "Feature",
  "properties": {
    "date:inception_lower": "1980-01-01",
    "date:inception_upper": "1980-01-01",
    "iso:country": "GB",
    "wof:name": "B26 2EH",
    "wof:placetype": "postalcode"
  },
  "geometry": {"coordinates":[-1.79155,52.474026],"type":"Point"}
}
