{
  "type": "Feature",
  "properties": {
    "date:inception_lower": "2016-07-01",
    "date:inception_upper": "2016-07-01",
    "iso:country": "GB",
    "wof:name": "PR2 3NF",
    "wof:placetype": "postalcode"
  },
  "geometry": {"coordinates":[-2.720216,53.798677],"type":"Point"}
}
