{
  "type": "Feature",
  "properties": {
    "date:inception_lower": "1999-06-01",
    "date:inception_upper": "1999-06-01",
    "iso:country": "GB",
    "wof:name": "CH43 5SW",
    "wof:placetype": "postalcode"
  },
  "geometry": {"coordinates":[-3.045324,53.380099],"type":"Point"}
}
