{
  "type": "Feature",
  "properties": {
    "iso:country":"GB",
    "wof:name":"BD4 7LN",
    "wof:placetype":"postalcode"
},
  "geometry": {"coordinates":[-1.74025693022517,53.77934245178081],"type":"Point"}
}