{
  "type": "Feature",
  "properties": {
    "iso:country": "GB",
    "wof:name": "PE15 9DQ",
    "wof:placetype": "postalcode"
  },
  "geometry": {"coordinates":[0.095916,52.544982],"type":"Point"}
}
