{
  "type": "Feature",
  "properties": {
    "iso:country":"GB",
    "wof:name":"LN1 2UU",
    "wof:placetype":"postalcode"
},
  "geometry": {"coordinates":[-0.55218448309502,53.29773823326371],"type":"Point"}
}