{
  "type": "Feature",
  "properties": {
    "date:inception_lower": "2018-06-01",
    "date:inception_upper": "2018-06-01",
    "iso:country": "GB",
    "wof:name": "KT8 0AJ",
    "wof:placetype": "postalcode"
  },
  "geometry": {"coordinates":[-0.351995,51.391857],"type":"Point"}
}
