{
  "type": "Feature",
  "properties": {
    "iso:country": "GB",
    "wof:name": "SN13 0BU",
    "wof:placetype": "postalcode"
  },
  "geometry": {"coordinates":[-2.213895,51.43262],"type":"Point"}
}
