{
  "type": "Feature",
  "properties": {
    "date:inception_lower":"1980-01-01",
    "date:inception_upper":"1980-01-31",
    "iso:country":"GB",
    "wof:name":"CF32 0TD",
    "wof:placetype":"postalcode"
},
  "geometry": {"coordinates":[-3.598123,51.467259],"type":"Point"}
}