{
  "type": "Feature",
  "properties": {
    "iso:country":"GB",
    "wof:name":"CF32 0TD",
    "wof:placetype":"postalcode"
},
  "geometry": {"coordinates":[-3.59812308327673,51.46725853912177],"type":"Point"}
}