{
  "type": "Feature",
  "properties": {
    "iso:country":"GB",
    "wof:name":"OX2 9DF",
    "wof:placetype":"postalcode"
},
  "geometry": {"coordinates":[-1.31246725781135,51.7488850446229],"type":"Point"}
}