{
  "type": "Feature",
  "properties": {
    "iso:country":"GB",
    "wof:name":"TS24 0TH",
    "wof:placetype":"postalcode"
},
  "geometry": {"coordinates":[-1.20851877665901,54.70308200557745],"type":"Point"}
}