{
  "type": "Feature",
  "properties": {
    "date:inception_lower": "1984-02-01",
    "date:inception_upper": "1984-02-01",
    "iso:country": "GB",
    "wof:name": "TS24 0TH",
    "wof:placetype": "postalcode"
  },
  "geometry": {"coordinates":[-1.208519,54.703082],"type":"Point"}
}
