{
  "type": "Feature",
  "properties": {
    "iso:country":"GB",
    "wof:name":"WA7 4LZ",
    "wof:placetype":"postalcode"
},
  "geometry": {"coordinates":[-2.7393138057718,53.31974417329697],"type":"Point"}
}