{
  "type": "Feature",
  "properties": {
    "iso:country":"GB",
    "wof:name":"W11 3QP",
    "wof:placetype":"postalcode"
},
  "geometry": {"coordinates":[-0.19827104519994,51.50899748824953],"type":"Point"}
}