{
  "type": "Feature",
  "properties": {
    "iso:country":"GB",
    "wof:name":"AB13 0ER",
    "wof:placetype":"postalcode"
},
  "geometry": {"coordinates":[-2.25585877356503,57.11593814459996],"type":"Point"}
}