{
  "type": "Feature",
  "properties": {
    "iso:country": "GB",
    "wof:name": "HU9 1TD",
    "wof:placetype": "postalcode"
  },
  "geometry": {"coordinates":[-0.328015,53.742214],"type":"Point"}
}
