{
  "type": "Feature",
  "properties": {
    "date:inception_lower":"2009-09-01",
    "date:inception_upper":"2009-09-30",
    "iso:country":"GB",
    "wof:name":"HU9 1TD",
    "wof:placetype":"postalcode"
},
  "geometry": {"coordinates":[-0.328015,53.742214],"type":"Point"}
}