{
  "type": "Feature",
  "properties": {
    "iso:country":"GB",
    "wof:name":"HU9 1TD",
    "wof:placetype":"postalcode"
},
  "geometry": {"coordinates":[-0.32801464530287,53.74221369171374],"type":"Point"}
}