{
  "type": "Feature",
  "properties": {
    "date:inception_lower": "2018-04-01",
    "date:inception_upper": "2018-04-01",
    "iso:country": "GB",
    "wof:name": "DN6 0FH",
    "wof:placetype": "postalcode"
  },
  "geometry": {"coordinates":[-1.156462,53.618948],"type":"Point"}
}
