{
  "type": "Feature",
  "properties": {
    "iso:country": "GB",
    "wof:name": "DN6 0FH",
    "wof:placetype": "postalcode"
  },
  "geometry": {"coordinates":[-1.156462,53.618948],"type":"Point"}
}
