{
  "type": "Feature",
  "properties": {
    "iso:country": "GB",
    "wof:name": "NN12 8SD",
    "wof:placetype": "postalcode"
  },
  "geometry": {"coordinates":[-1.089024,52.12482],"type":"Point"}
}
