{
  "type": "Feature",
  "properties": {
    "date:inception_lower":"1980-01-01",
    "date:inception_upper":"1980-01-31",
    "iso:country":"GB",
    "wof:name":"NN12 8SD",
    "wof:placetype":"postalcode"
},
  "geometry": {"coordinates":[-1.089024,52.12482],"type":"Point"}
}