{
  "type": "Feature",
  "properties": {
    "iso:country": "GB",
    "wof:name": "HG3 4HY",
    "wof:placetype": "postalcode"
  },
  "geometry": {"coordinates":[-1.691472,54.057984],"type":"Point"}
}
