{
  "type": "Feature",
  "properties": {
    "date:inception_lower":"1981-06-01",
    "date:inception_upper":"1981-06-30",
    "iso:country":"GB",
    "wof:name":"PR4 3JS",
    "wof:placetype":"postalcode"
},
  "geometry": {"coordinates":[-2.871411,53.792337],"type":"Point"}
}