{
  "type": "Feature",
  "properties": {
    "iso:country":"GB",
    "wof:name":"PR4 3JS",
    "wof:placetype":"postalcode"
},
  "geometry": {"coordinates":[-2.87148881028206,53.79240840447772],"type":"Point"}
}