{
  "type": "Feature",
  "properties": {
    "iso:country":"GB",
    "wof:name":"NP23 7RE",
    "wof:placetype":"postalcode"
},
  "geometry": {"coordinates":[-3.1849428969957,51.74372262691719],"type":"Point"}
}