{
  "type": "Feature",
  "properties": {
    "iso:country":"GB",
    "wof:name":"LD6 5NE",
    "wof:placetype":"postalcode"
},
  "geometry": {"coordinates":[-3.42368010476287,52.36037445367059],"type":"Point"}
}