{
  "type": "Feature",
  "properties": {
    "iso:country": "GB",
    "wof:name": "CM9 8LB",
    "wof:placetype": "postalcode"
  },
  "geometry": {"coordinates":[0.737726,51.771569],"type":"Point"}
}
