{
  "type": "Feature",
  "properties": {
    "iso:country":"GB",
    "wof:name":"GL7 1JP",
    "wof:placetype":"postalcode"
},
  "geometry": {"coordinates":[-1.95165639561374,51.71040646681934],"type":"Point"}
}