{
  "type": "Feature",
  "properties": {
    "date:inception_lower":"2013-04-01",
    "date:inception_upper":"2013-04-30",
    "iso:country":"GB",
    "wof:name":"GL7 1JP",
    "wof:placetype":"postalcode"
},
  "geometry": {"coordinates":[-1.951656,51.710406],"type":"Point"}
}