{
  "type": "Feature",
  "properties": {
    "date:inception_lower": "1990-07-01",
    "date:inception_upper": "1990-07-01",
    "iso:country": "GB",
    "wof:name": "SG12 0PP",
    "wof:placetype": "postalcode"
  },
  "geometry": {"coordinates":[-0.070114,51.824489],"type":"Point"}
}
