{
  "type": "Feature",
  "properties": {
    "iso:country":"GB",
    "wof:name":"SG12 0PP",
    "wof:placetype":"postalcode"
},
  "geometry": {"coordinates":[-0.07011386202804,51.8244886226699],"type":"Point"}
}