{
  "type": "Feature",
  "properties": {
    "iso:country":"GB",
    "wof:name":"CF83 8NA",
    "wof:placetype":"postalcode"
},
  "geometry": {"coordinates":[-3.14309354675992,51.59594644937077],"type":"Point"}
}