{
  "type": "Feature",
  "properties": {
    "date:inception_lower": "1999-06-01",
    "date:inception_upper": "1999-06-01",
    "iso:country": "GB",
    "wof:name": "CF83 8NA",
    "wof:placetype": "postalcode"
  },
  "geometry": {"coordinates":[-3.143094,51.595946],"type":"Point"}
}
