{
  "type": "Feature",
  "properties": {
    "iso:country": "GB",
    "wof:name": "CH6 5AE",
    "wof:placetype": "postalcode"
  },
  "geometry": {"coordinates":[-3.135157,53.249178],"type":"Point"}
}
