{
  "type": "Feature",
  "properties": {
    "iso:country":"GB",
    "wof:name":"CH6 5AE",
    "wof:placetype":"postalcode"
},
  "geometry": {"coordinates":[-3.13515719596683,53.24917828228165],"type":"Point"}
}