{
  "type": "Feature",
  "properties": {
    "iso:country":"GB",
    "wof:name":"CH5 4QN",
    "wof:placetype":"postalcode"
},
  "geometry": {"coordinates":[-3.05351210136519,53.21531038463758],"type":"Point"}
}