{
  "type": "Feature",
  "properties": {
    "iso:country": "GB",
    "wof:name": "CH5 4QN",
    "wof:placetype": "postalcode"
  },
  "geometry": {"coordinates":[-3.053512,53.21531],"type":"Point"}
}
