{
  "type": "Feature",
  "properties": {
    "iso:country":"GB",
    "wof:name":"SE13 7SY",
    "wof:placetype":"postalcode"
},
  "geometry": {"coordinates":[-0.02102416100656,51.46729220875339],"type":"Point"}
}