{
  "type": "Feature",
  "properties": {
    "date:inception_lower": "2004-09-01",
    "date:inception_upper": "2004-09-01",
    "iso:country": "GB",
    "wof:name": "DE73 8FX",
    "wof:placetype": "postalcode"
  },
  "geometry": {"coordinates":[-1.437038,52.82421],"type":"Point"}
}
