{
  "type": "Feature",
  "properties": {
    "iso:country":"GB",
    "wof:name":"LL31 9EH",
    "wof:placetype":"postalcode"
},
  "geometry": {"coordinates":[-3.80457390552776,53.28471207321955],"type":"Point"}
}