{
  "type": "Feature",
  "properties": {
    "iso:country":"GB",
    "wof:name":"WF9 3NY",
    "wof:placetype":"postalcode"
},
  "geometry": {"coordinates":[-1.31867830346569,53.59142416030748],"type":"Point"}
}