{
  "type": "Feature",
  "properties": {
    "iso:country": "GB",
    "wof:name": "WF9 3NY",
    "wof:placetype": "postalcode"
  },
  "geometry": {"coordinates":[-1.318678,53.591424],"type":"Point"}
}
