{
  "type": "Feature",
  "properties": {
    "date:inception_lower": "1980-01-01",
    "date:inception_upper": "1980-01-01",
    "iso:country": "GB",
    "wof:name": "RH19 1AH",
    "wof:placetype": "postalcode"
  },
  "geometry": {"coordinates":[-0.008197,51.124263],"type":"Point"}
}
