{
  "type": "Feature",
  "properties": {
    "date:inception_lower": "1999-06-01",
    "date:inception_upper": "1999-06-01",
    "iso:country": "GB",
    "wof:name": "BL4 0PL",
    "wof:placetype": "postalcode"
  },
  "geometry": {"coordinates":[-2.43184,53.543506],"type":"Point"}
}
