{
  "type": "Feature",
  "properties": {
    "iso:country":"GB",
    "wof:name":"BL4 0PL",
    "wof:placetype":"postalcode"
},
  "geometry": {"coordinates":[-2.43183991611074,53.54350561768677],"type":"Point"}
}