{
  "type": "Feature",
  "properties": {
    "date:inception_lower": "1980-01-01",
    "date:inception_upper": "1980-01-01",
    "iso:country": "GB",
    "wof:name": "NG22 9JT",
    "wof:placetype": "postalcode"
  },
  "geometry": {"coordinates":[-0.984937,53.209096],"type":"Point"}
}
