{
  "type": "Feature",
  "properties": {
    "iso:country": "GB",
    "wof:name": "LL13 0EH",
    "wof:placetype": "postalcode"
  },
  "geometry": {"coordinates":[-2.934168,52.967687],"type":"Point"}
}
