{
  "type": "Feature",
  "properties": {
    "iso:country": "GB",
    "wof:name": "RG14 6RY",
    "wof:placetype": "postalcode"
  },
  "geometry": {"coordinates":[-1.34931,51.374338],"type":"Point"}
}
