{
  "type": "Feature",
  "properties": {
    "date:inception_lower": "2000-06-01",
    "date:inception_upper": "2000-06-01",
    "iso:country": "GB",
    "wof:name": "GL15 4QD",
    "wof:placetype": "postalcode"
  },
  "geometry": {"coordinates":[-2.544933,51.753883],"type":"Point"}
}
