{
  "type": "Feature",
  "properties": {
    "date:inception_lower": "2022-02-01",
    "date:inception_upper": "2022-02-01",
    "iso:country": "GB",
    "wof:name": "HP10 9FZ",
    "wof:placetype": "postalcode"
  },
  "geometry": {"coordinates":[-0.73751,51.614181],"type":"Point"}
}
