{
  "type": "Feature",
  "properties": {
    "iso:country": "GB",
    "wof:name": "NE61 9GJ",
    "wof:placetype": "postalcode"
  },
  "geometry": {"coordinates":[-1.69196,55.167865],"type":"Point"}
}
