{
  "type": "Feature",
  "properties": {
    "iso:country":"GB",
    "wof:name":"UB4 9YQ",
    "wof:placetype":"postalcode"
},
  "geometry": {"coordinates":[-0.38959632252909,51.52213042621806],"type":"Point"}
}