{
  "type": "Feature",
  "properties": {
    "date:inception_lower": "1999-12-01",
    "date:inception_upper": "1999-12-01",
    "iso:country": "GB",
    "wof:name": "UB4 9YQ",
    "wof:placetype": "postalcode"
  },
  "geometry": {"coordinates":[-0.389596,51.52213],"type":"Point"}
}
