{
  "type": "Feature",
  "properties": {
    "date:inception_lower": "1984-02-01",
    "date:inception_upper": "1984-02-01",
    "iso:country": "GB",
    "wof:name": "B98 7YJ",
    "wof:placetype": "postalcode"
  },
  "geometry": {"coordinates":[-1.9425,52.288639],"type":"Point"}
}
