{
  "type": "Feature",
  "properties": {
    "date:inception_lower": "1980-01-01",
    "date:inception_upper": "1980-01-01",
    "iso:country": "GB",
    "wof:name": "TR16 6SX",
    "wof:placetype": "postalcode"
  },
  "geometry": {"coordinates":[-5.211948,50.210024],"type":"Point"}
}
