{
  "type": "Feature",
  "properties": {
    "iso:country":"GB",
    "wof:name":"SE15 1EU",
    "wof:placetype":"postalcode"
},
  "geometry": {"coordinates":[-0.05031530441826,51.48335827316737],"type":"Point"}
}