{
  "type": "Feature",
  "properties": {
    "date:inception_lower": "1980-01-01",
    "date:inception_upper": "1980-01-01",
    "iso:country": "GB",
    "wof:name": "SE15 1EU",
    "wof:placetype": "postalcode"
  },
  "geometry": {"coordinates":[-0.050315,51.483358],"type":"Point"}
}
