{
  "type": "Feature",
  "properties": {
    "date:inception_lower": "1980-01-01",
    "date:inception_upper": "1980-01-01",
    "iso:country": "GB",
    "wof:name": "NW5 2HF",
    "wof:placetype": "postalcode"
  },
  "geometry": {"coordinates":[-0.140406,51.552319],"type":"Point"}
}
