{
  "type": "Feature",
  "properties": {
    "iso:country": "GB",
    "wof:name": "PO10 8LY",
    "wof:placetype": "postalcode"
  },
  "geometry": {"coordinates":[-0.911698,50.849001],"type":"Point"}
}
