{
  "type": "Feature",
  "properties": {
    "date:inception_lower": "1998-06-01",
    "date:inception_upper": "1998-06-01",
    "iso:country": "GB",
    "wof:name": "KT22 7EU",
    "wof:placetype": "postalcode"
  },
  "geometry": {"coordinates":[-0.32333,51.298682],"type":"Point"}
}
