{
  "type": "Feature",
  "properties": {
    "date:inception_lower":"2002-05-01",
    "date:inception_upper":"2002-05-31",
    "iso:country":"GB",
    "wof:name":"NP23 5WS",
    "wof:placetype":"postalcode"
},
  "geometry": {"coordinates":[-3.222313,51.793099],"type":"Point"}
}