{
  "type": "Feature",
  "properties": {
    "iso:country": "GB",
    "wof:name": "NP23 5WS",
    "wof:placetype": "postalcode"
  },
  "geometry": {"coordinates":[-3.222313,51.793099],"type":"Point"}
}
