{
  "type": "Feature",
  "properties": {
    "iso:country":"GB",
    "wof:name":"NP23 5WS",
    "wof:placetype":"postalcode"
},
  "geometry": {"coordinates":[-3.22231316741146,51.79309891767659],"type":"Point"}
}