{
  "type": "Feature",
  "properties": {
    "iso:country": "GB",
    "wof:name": "W7 1QN",
    "wof:placetype": "postalcode"
  },
  "geometry": {"coordinates":[-0.330652,51.517494],"type":"Point"}
}
