{
  "type": "Feature",
  "properties": {
    "iso:country":"GB",
    "wof:name":"W7 1QN",
    "wof:placetype":"postalcode"
},
  "geometry": {"coordinates":[-0.33065215270686,51.51749370064354],"type":"Point"}
}