{
  "type": "Feature",
  "properties": {
    "iso:country":"GB",
    "wof:name":"WV12 4BF",
    "wof:placetype":"postalcode"
},
  "geometry": {"coordinates":[-2.04066205589603,52.60006878063295],"type":"Point"}
}