{
  "type": "Feature",
  "properties": {
    "iso:country": "GB",
    "wof:name": "WV12 4BF",
    "wof:placetype": "postalcode"
  },
  "geometry": {"coordinates":[-2.040662,52.600069],"type":"Point"}
}
