{
  "type": "Feature",
  "properties": {
    "date:inception_lower":"2014-06-01",
    "date:inception_upper":"2014-06-30",
    "iso:country":"GB",
    "wof:name":"WV12 4BF",
    "wof:placetype":"postalcode"
},
  "geometry": {"coordinates":[-2.040662,52.600069],"type":"Point"}
}