{
  "type": "Feature",
  "properties": {
    "iso:country":"GB",
    "wof:name":"GL3 2JR",
    "wof:placetype":"postalcode"
},
  "geometry": {"coordinates":[-2.16829417626145,51.87964123410336],"type":"Point"}
}