{
  "type": "Feature",
  "properties": {
    "iso:country":"GB",
    "wof:name":"PE1 3AF",
    "wof:placetype":"postalcode"
},
  "geometry": {"coordinates":[-0.24292307027939,52.58438365141937],"type":"Point"}
}