{
  "type": "Feature",
  "properties": {
    "iso:country":"GB",
    "wof:name":"CT13 9DJ",
    "wof:placetype":"postalcode"
},
  "geometry": {"coordinates":[1.33638321419356,51.27656402824994],"type":"Point"}
}