{
  "type": "Feature",
  "properties": {
    "iso:country":"GB",
    "wof:name":"WR1 1NR",
    "wof:placetype":"postalcode"
},
  "geometry": {"coordinates":[-2.21706669762191,52.19928672268079],"type":"Point"}
}