{
  "type": "Feature",
  "properties": {
    "date:inception_lower": "1980-01-01",
    "date:inception_upper": "1980-01-01",
    "iso:country": "GB",
    "wof:name": "WR1 1NR",
    "wof:placetype": "postalcode"
  },
  "geometry": {"coordinates":[-2.21715,52.199272],"type":"Point"}
}
