{
  "type": "Feature",
  "properties": {
    "date:inception_lower": "1980-01-01",
    "date:inception_upper": "1980-01-01",
    "iso:country": "GB",
    "wof:name": "GL6 9JX",
    "wof:placetype": "postalcode"
  },
  "geometry": {"coordinates":[-2.180849,51.707808],"type":"Point"}
}
