{
  "type": "Feature",
  "properties": {
    "iso:country": "GB",
    "wof:name": "GL6 9JX",
    "wof:placetype": "postalcode"
  },
  "geometry": {"coordinates":[-2.180565,51.707993],"type":"Point"}
}
