{
  "type": "Feature",
  "properties": {
    "iso:country":"GB",
    "wof:name":"LA9 5BZ",
    "wof:placetype":"postalcode"
},
  "geometry": {"coordinates":[-2.74806877781867,54.31910951337112],"type":"Point"}
}