{
  "type": "Feature",
  "properties": {
    "date:inception_lower": "1981-06-01",
    "date:inception_upper": "1981-06-01",
    "iso:country": "GB",
    "wof:name": "LS12 3TJ",
    "wof:placetype": "postalcode"
  },
  "geometry": {"coordinates":[-1.600082,53.79394],"type":"Point"}
}
