{
  "type": "Feature",
  "properties": {
    "iso:country": "GB",
    "wof:name": "LE4 6GH",
    "wof:placetype": "postalcode"
  },
  "geometry": {"coordinates":[-1.107978,52.650084],"type":"Point"}
}
