{
  "type": "Feature",
  "properties": {
    "iso:country":"GB",
    "wof:name":"LE4 6GH",
    "wof:placetype":"postalcode"
},
  "geometry": {"coordinates":[-1.10797830179757,52.65008367325127],"type":"Point"}
}