{
  "type": "Feature",
  "properties": {
    "date:inception_lower": "1980-01-01",
    "date:inception_upper": "1980-01-01",
    "iso:country": "GB",
    "wof:name": "WF17 0ET",
    "wof:placetype": "postalcode"
  },
  "geometry": {"coordinates":[-1.630944,53.717802],"type":"Point"}
}
