{
  "type": "Feature",
  "properties": {
    "iso:country":"GB",
    "wof:name":"BN1 6EL",
    "wof:placetype":"postalcode"
},
  "geometry": {"coordinates":[-0.13548855934107,50.84142951940996],"type":"Point"}
}