{
  "type": "Feature",
  "properties": {
    "iso:country":"GB",
    "wof:name":"PA2 6HN",
    "wof:placetype":"postalcode"
},
  "geometry": {"coordinates":[-4.42808626329117,55.83020945432892],"type":"Point"}
}