{
  "type": "Feature",
  "properties": {
    "iso:country": "GB",
    "wof:name": "TN22 4LZ",
    "wof:placetype": "postalcode"
  },
  "geometry": {"coordinates":[0.139639,50.989834],"type":"Point"}
}
