{
  "type": "Feature",
  "properties": {
    "iso:country": "GB",
    "wof:name": "CB22 7QY",
    "wof:placetype": "postalcode"
  },
  "geometry": {"coordinates":[0.0355,52.126425],"type":"Point"}
}
