{
  "type": "Feature",
  "properties": {
    "date:inception_lower": "2006-09-01",
    "date:inception_upper": "2006-09-01",
    "iso:country": "GB",
    "wof:name": "CB22 7QY",
    "wof:placetype": "postalcode"
  },
  "geometry": {"coordinates":[0.0355,52.126425],"type":"Point"}
}
