{
  "type": "Feature",
  "properties": {
    "iso:country": "GB",
    "wof:name": "BD23 2UL",
    "wof:placetype": "postalcode"
  },
  "geometry": {"coordinates":[-2.018511,53.957932],"type":"Point"}
}
