{
  "type": "Feature",
  "properties": {
    "date:inception_lower": "2000-06-01",
    "date:inception_upper": "2000-06-01",
    "iso:country": "GB",
    "wof:name": "BD23 2UL",
    "wof:placetype": "postalcode"
  },
  "geometry": {"coordinates":[-2.018511,53.957932],"type":"Point"}
}
