{
  "type": "Feature",
  "properties": {
    "iso:country":"GB",
    "wof:name":"MK46 5QG",
    "wof:placetype":"postalcode"
},
  "geometry": {"coordinates":[-0.70250971598018,52.15655397187637],"type":"Point"}
}