{
  "type": "Feature",
  "properties": {
    "iso:country":"GB",
    "wof:name":"WA15 6EX",
    "wof:placetype":"postalcode"
},
  "geometry": {"coordinates":[-2.32669712780506,53.40550647392607],"type":"Point"}
}