{
  "type": "Feature",
  "properties": {
    "iso:country":"GB",
    "wof:name":"TW18 1DN",
    "wof:placetype":"postalcode"
},
  "geometry": {"coordinates":[-0.48968767038146,51.42844116601607],"type":"Point"}
}