{
  "type": "Feature",
  "properties": {
    "iso:country":"GB",
    "wof:name":"PE8 6AX",
    "wof:placetype":"postalcode"
},
  "geometry": {"coordinates":[-0.44100918460982,52.60523727952032],"type":"Point"}
}