{
  "type": "Feature",
  "properties": {
    "iso:country":"GB",
    "wof:name":"IP6 9SY",
    "wof:placetype":"postalcode"
},
  "geometry": {"coordinates":[1.1371813378835,52.16546425538096],"type":"Point"}
}