{
  "type": "Feature",
  "properties": {
    "iso:country": "GB",
    "wof:name": "DD10 8NH",
    "wof:placetype": "postalcode"
  },
  "geometry": {"coordinates":[-2.465385,56.714834],"type":"Point"}
}
