{
  "type": "Feature",
  "properties": {
    "iso:country":"GB",
    "wof:name":"DD10 8NH",
    "wof:placetype":"postalcode"
},
  "geometry": {"coordinates":[-2.46538540710922,56.71483442903123],"type":"Point"}
}