{
  "type": "Feature",
  "properties": {
    "date:inception_lower":"1980-01-01",
    "date:inception_upper":"1980-01-31",
    "iso:country":"GB",
    "wof:name":"L26 1TQ",
    "wof:placetype":"postalcode"
},
  "geometry": {"coordinates":[-2.840869,53.357895],"type":"Point"}
}