{
  "type": "Feature",
  "properties": {
    "iso:country":"GB",
    "wof:name":"L26 1TQ",
    "wof:placetype":"postalcode"
},
  "geometry": {"coordinates":[-2.84086927451494,53.35789458204477],"type":"Point"}
}