{
  "type": "Feature",
  "properties": {
    "iso:country":"GB",
    "wof:name":"SS8 9QN",
    "wof:placetype":"postalcode"
},
  "geometry": {"coordinates":[0.57363481157075,51.52849240606573],"type":"Point"}
}