{
  "type": "Feature",
  "properties": {
    "iso:country":"GB",
    "wof:name":"KA2 0AB",
    "wof:placetype":"postalcode"
},
  "geometry": {"coordinates":[-4.52315172773455,55.60067602025698],"type":"Point"}
}