{
  "type": "Feature",
  "properties": {
    "iso:country": "GB",
    "wof:name": "KA2 0AB",
    "wof:placetype": "postalcode"
  },
  "geometry": {"coordinates":[-4.523152,55.600676],"type":"Point"}
}
