{
  "type": "Feature",
  "properties": {
    "date:inception_lower": "2017-02-01",
    "date:inception_upper": "2017-02-01",
    "iso:country": "GB",
    "wof:name": "NN5 6GT",
    "wof:placetype": "postalcode"
  },
  "geometry": {"coordinates":[-0.936688,52.243686],"type":"Point"}
}
