{
  "type": "Feature",
  "properties": {
    "iso:country": "GB",
    "wof:name": "NN5 6GT",
    "wof:placetype": "postalcode"
  },
  "geometry": {"coordinates":[-0.936614,52.243713],"type":"Point"}
}
