{
  "type": "Feature",
  "properties": {
    "iso:country":"GB",
    "wof:name":"WN7 2XB",
    "wof:placetype":"postalcode"
},
  "geometry": {"coordinates":[-2.4861254471535,53.50305580548889],"type":"Point"}
}