{
  "type": "Feature",
  "properties": {
    "date:inception_lower":"1980-01-01",
    "date:inception_upper":"1980-01-31",
    "iso:country":"GB",
    "wof:name":"WN7 2XB",
    "wof:placetype":"postalcode"
},
  "geometry": {"coordinates":[-2.486125,53.503056],"type":"Point"}
}