{
  "type": "Feature",
  "properties": {
    "date:inception_lower": "2021-08-01",
    "date:inception_upper": "2021-08-01",
    "iso:country": "GB",
    "wof:name": "GL7 1ZR",
    "wof:placetype": "postalcode"
  },
  "geometry": {"coordinates":[-1.959759,51.702852],"type":"Point"}
}
