{
  "type": "Feature",
  "properties": {
    "iso:country": "GB",
    "wof:name": "KA9 1AA",
    "wof:placetype": "postalcode"
  },
  "geometry": {"coordinates":[-4.610737,55.501206],"type":"Point"}
}
