{
  "type": "Feature",
  "properties": {
    "iso:country":"GB",
    "wof:name":"KA9 1AA",
    "wof:placetype":"postalcode"
},
  "geometry": {"coordinates":[-4.61073713285924,55.50120622692676],"type":"Point"}
}