{
  "type": "Feature",
  "properties": {
    "iso:country": "GB",
    "wof:name": "SG9 9SG",
    "wof:placetype": "postalcode"
  },
  "geometry": {"coordinates":[-0.023406,51.942292],"type":"Point"}
}
