{
  "type": "Feature",
  "properties": {
    "date:inception_lower": "1994-05-01",
    "date:inception_upper": "1994-05-01",
    "iso:country": "GB",
    "wof:name": "SG9 9SG",
    "wof:placetype": "postalcode"
  },
  "geometry": {"coordinates":[-0.023406,51.942292],"type":"Point"}
}
