{
  "type": "Feature",
  "properties": {
    "iso:country":"GB",
    "wof:name":"SG9 9SG",
    "wof:placetype":"postalcode"
},
  "geometry": {"coordinates":[-0.02340649916075,51.94229216677913],"type":"Point"}
}