{
  "type": "Feature",
  "properties": {
    "date:inception_lower":"1980-01-01",
    "date:inception_upper":"1980-01-31",
    "iso:country":"GB",
    "wof:name":"DE12 7HX",
    "wof:placetype":"postalcode"
},
  "geometry": {"coordinates":[-1.5089,52.705075],"type":"Point"}
}