{
  "type": "Feature",
  "properties": {
    "iso:country":"GB",
    "wof:name":"DE12 7HX",
    "wof:placetype":"postalcode"
},
  "geometry": {"coordinates":[-1.50890049617613,52.70507537668961],"type":"Point"}
}