{
  "type": "Feature",
  "properties": {
    "iso:country": "GB",
    "wof:name": "WV14 0HZ",
    "wof:placetype": "postalcode"
  },
  "geometry": {"coordinates":[-2.081451,52.565949],"type":"Point"}
}
