{
  "type": "Feature",
  "properties": {
    "iso:country":"GB",
    "wof:name":"NG22 9TF",
    "wof:placetype":"postalcode"
},
  "geometry": {"coordinates":[-0.99982621389263,53.20629986914793],"type":"Point"}
}