{
  "type": "Feature",
  "properties": {
    "iso:country":"GB",
    "wof:name":"YO25 6UH",
    "wof:placetype":"postalcode"
},
  "geometry": {"coordinates":[-0.43967562563729,54.00625684644289],"type":"Point"}
}