{
  "type": "Feature",
  "properties": {
    "iso:country": "GB",
    "wof:name": "YO25 6UH",
    "wof:placetype": "postalcode"
  },
  "geometry": {"coordinates":[-0.439676,54.006257],"type":"Point"}
}
