{
  "type": "Feature",
  "properties": {
    "iso:country":"GB",
    "wof:name":"S64 9JR",
    "wof:placetype":"postalcode"
},
  "geometry": {"coordinates":[-1.29084896655509,53.50294117242053],"type":"Point"}
}