{
  "type": "Feature",
  "properties": {
    "iso:country": "GB",
    "wof:name": "S64 9JR",
    "wof:placetype": "postalcode"
  },
  "geometry": {"coordinates":[-1.290849,53.502941],"type":"Point"}
}
