{
  "type": "Feature",
  "properties": {
    "date:inception_lower": "1980-01-01",
    "date:inception_upper": "1980-01-01",
    "iso:country": "GB",
    "wof:name": "DT2 8LJ",
    "wof:placetype": "postalcode"
  },
  "geometry": {"coordinates":[-2.264811,50.671644],"type":"Point"}
}
