{
  "type": "Feature",
  "properties": {
    "date:inception_lower": "2019-02-01",
    "date:inception_upper": "2019-02-01",
    "iso:country": "GB",
    "wof:name": "LL22 8FN",
    "wof:placetype": "postalcode"
  },
  "geometry": {"coordinates":[-3.60071,53.288693],"type":"Point"}
}
