{
  "type": "Feature",
  "properties": {
    "iso:country": "GB",
    "wof:name": "LL22 8FN",
    "wof:placetype": "postalcode"
  },
  "geometry": {"coordinates":[-3.600852,53.288484],"type":"Point"}
}
