{
  "type": "Feature",
  "properties": {
    "iso:country": "GB",
    "wof:name": "GL20 6JP",
    "wof:placetype": "postalcode"
  },
  "geometry": {"coordinates":[-2.15015,52.031942],"type":"Point"}
}
