{
  "type": "Feature",
  "properties": {
    "date:inception_lower":"1995-12-01",
    "date:inception_upper":"1995-12-31",
    "iso:country":"GB",
    "wof:name":"WA8 9ZP",
    "wof:placetype":"postalcode"
},
  "geometry": {"coordinates":[-2.741281,53.379517],"type":"Point"}
}