{
  "type": "Feature",
  "properties": {
    "iso:country":"GB",
    "wof:name":"WA8 9ZP",
    "wof:placetype":"postalcode"
},
  "geometry": {"coordinates":[-2.74128112305685,53.37951679624754],"type":"Point"}
}