{
  "type": "Feature",
  "properties": {
    "iso:country":"GB",
    "wof:name":"KT12 4PE",
    "wof:placetype":"postalcode"
},
  "geometry": {"coordinates":[-0.39042857160743,51.36916423116579],"type":"Point"}
}