{
  "type": "Feature",
  "properties": {
    "iso:country": "GB",
    "wof:name": "NN8 2EB",
    "wof:placetype": "postalcode"
  },
  "geometry": {"coordinates":[-0.678022,52.285815],"type":"Point"}
}
