{
  "type": "Feature",
  "properties": {
    "iso:country":"GB",
    "wof:name":"NN8 2EB",
    "wof:placetype":"postalcode"
},
  "geometry": {"coordinates":[-0.67802190552996,52.2858146960338],"type":"Point"}
}