{
  "type": "Feature",
  "properties": {
    "iso:country":"GB",
    "wof:name":"WN6 0TL",
    "wof:placetype":"postalcode"
},
  "geometry": {"coordinates":[-2.66003797593825,53.58198578746907],"type":"Point"}
}