{
  "type": "Feature",
  "properties": {
    "date:inception_lower": "1981-09-01",
    "date:inception_upper": "1981-09-01",
    "iso:country": "GB",
    "wof:name": "WN6 0TL",
    "wof:placetype": "postalcode"
  },
  "geometry": {"coordinates":[-2.660038,53.581986],"type":"Point"}
}
