{
  "type": "Feature",
  "properties": {
    "iso:country":"GB",
    "wof:name":"TA21 8PP",
    "wof:placetype":"postalcode"
},
  "geometry": {"coordinates":[-3.22478147839364,50.97518819722935],"type":"Point"}
}