{
  "type": "Feature",
  "properties": {
    "iso:country":"GB",
    "wof:name":"GU9 9EA",
    "wof:placetype":"postalcode"
},
  "geometry": {"coordinates":[-0.78106075187203,51.23842937099845],"type":"Point"}
}