{
  "type": "Feature",
  "properties": {
    "iso:country":"GB",
    "wof:name":"EX6 7RE",
    "wof:placetype":"postalcode"
},
  "geometry": {"coordinates":[-3.6217089462332,50.66466993834346],"type":"Point"}
}