{
  "type": "Feature",
  "properties": {
    "iso:country":"GB",
    "wof:name":"NG7 2AQ",
    "wof:placetype":"postalcode"
},
  "geometry": {"coordinates":[-1.17949462942478,52.95499191875536],"type":"Point"}
}