{
  "type": "Feature",
  "properties": {
    "iso:country":"GB",
    "wof:name":"HR9 9BP",
    "wof:placetype":"postalcode"
},
  "geometry": {"coordinates":[-2.57164704737501,51.91198936540158],"type":"Point"}
}