{
  "type": "Feature",
  "properties": {
    "iso:country": "GB",
    "wof:name": "HR9 9BP",
    "wof:placetype": "postalcode"
  },
  "geometry": {"coordinates":[-2.571647,51.911989],"type":"Point"}
}
