{
  "type": "Feature",
  "properties": {
    "date:inception_lower": "1991-09-01",
    "date:inception_upper": "1991-09-01",
    "iso:country": "GB",
    "wof:name": "B16 9BZ",
    "wof:placetype": "postalcode"
  },
  "geometry": {"coordinates":[-1.951841,52.477345],"type":"Point"}
}
