{
  "type": "Feature",
  "properties": {
    "date:inception_lower": "1982-03-01",
    "date:inception_upper": "1982-03-01",
    "iso:country": "GB",
    "wof:name": "E15 3JF",
    "wof:placetype": "postalcode"
  },
  "geometry": {"coordinates":[0.007132,51.533072],"type":"Point"}
}
