{
  "type": "Feature",
  "properties": {
    "iso:country":"GB",
    "wof:name":"PL9 9SJ",
    "wof:placetype":"postalcode"
},
  "geometry": {"coordinates":[-4.12741272763424,50.35991318686376],"type":"Point"}
}