{
  "type": "Feature",
  "properties": {
    "date:inception_lower":"1986-07-01",
    "date:inception_upper":"1986-07-31",
    "iso:country":"GB",
    "wof:name":"EX39 6DD",
    "wof:placetype":"postalcode"
},
  "geometry": {"coordinates":[-4.481108,50.993257],"type":"Point"}
}