{
  "type": "Feature",
  "properties": {
    "iso:country":"GB",
    "wof:name":"EX39 6DD",
    "wof:placetype":"postalcode"
},
  "geometry": {"coordinates":[-4.48110814046922,50.99325734278147],"type":"Point"}
}