{
  "type": "Feature",
  "properties": {
    "iso:country":"GB",
    "wof:name":"B11 2QB",
    "wof:placetype":"postalcode"
},
  "geometry": {"coordinates":[-1.85918535251308,52.4595434332509],"type":"Point"}
}