{
  "type": "Feature",
  "properties": {
    "iso:country":"GB",
    "wof:name":"IV1 1LP",
    "wof:placetype":"postalcode"
},
  "geometry": {"coordinates":[-4.22553104267253,57.4798930947974],"type":"Point"}
}