{
  "type": "Feature",
  "properties": {
    "iso:country": "GB",
    "wof:name": "IV1 1LP",
    "wof:placetype": "postalcode"
  },
  "geometry": {"coordinates":[-4.225531,57.479893],"type":"Point"}
}
