{
  "type": "Feature",
  "properties": {
    "date:inception_lower":"1985-04-01",
    "date:inception_upper":"1985-04-30",
    "iso:country":"GB",
    "wof:name":"RH13 5PS",
    "wof:placetype":"postalcode"
},
  "geometry": {"coordinates":[-0.311022,51.068759],"type":"Point"}
}