{
  "type": "Feature",
  "properties": {
    "iso:country":"GB",
    "wof:name":"LA1 1HL",
    "wof:placetype":"postalcode"
},
  "geometry": {"coordinates":[-2.80432348019775,54.05252429429218],"type":"Point"}
}