{
  "type": "Feature",
  "properties": {
    "date:inception_lower": "2009-08-01",
    "date:inception_upper": "2009-08-01",
    "iso:country": "GB",
    "wof:name": "B46 2BF",
    "wof:placetype": "postalcode"
  },
  "geometry": {"coordinates":[-1.668308,52.515476],"type":"Point"}
}
