{
  "type": "Feature",
  "properties": {
    "iso:country":"GB",
    "wof:name":"B46 2BF",
    "wof:placetype":"postalcode"
},
  "geometry": {"coordinates":[-1.66830853544281,52.51547591067904],"type":"Point"}
}