{
  "type": "Feature",
  "properties": {
    "iso:country": "GB",
    "wof:name": "B46 2BF",
    "wof:placetype": "postalcode"
  },
  "geometry": {"coordinates":[-1.668308,52.515476],"type":"Point"}
}
