{
  "type": "Feature",
  "properties": {
    "date:inception_lower": "1980-01-01",
    "date:inception_upper": "1980-01-01",
    "iso:country": "GB",
    "wof:name": "LL16 3NF",
    "wof:placetype": "postalcode"
  },
  "geometry": {"coordinates":[-3.420025,53.182394],"type":"Point"}
}
