{
  "type": "Feature",
  "properties": {
    "iso:country":"GB",
    "wof:name":"LL16 3NF",
    "wof:placetype":"postalcode"
},
  "geometry": {"coordinates":[-3.4200224957746,53.18235218572143],"type":"Point"}
}