{
  "type": "Feature",
  "properties": {
    "iso:country":"GB",
    "wof:name":"LA14 3QE",
    "wof:placetype":"postalcode"
},
  "geometry": {"coordinates":[-3.246910071199,54.11074953573702],"type":"Point"}
}