{
  "type": "Feature",
  "properties": {
    "date:inception_lower": "1990-02-01",
    "date:inception_upper": "1990-02-01",
    "iso:country": "GB",
    "wof:name": "TQ3 3TG",
    "wof:placetype": "postalcode"
  },
  "geometry": {"coordinates":[-3.583535,50.441524],"type":"Point"}
}
