{
  "type": "Feature",
  "properties": {
    "iso:country":"GB",
    "wof:name":"TQ3 3TG",
    "wof:placetype":"postalcode"
},
  "geometry": {"coordinates":[-3.58353537907031,50.4415244914467],"type":"Point"}
}