{
  "type": "Feature",
  "properties": {
    "iso:country": "GB",
    "wof:name": "GU10 1EP",
    "wof:placetype": "postalcode"
  },
  "geometry": {"coordinates":[-0.733592,51.226784],"type":"Point"}
}
