{
  "type": "Feature",
  "properties": {
    "iso:country":"GB",
    "wof:name":"GU10 1EP",
    "wof:placetype":"postalcode"
},
  "geometry": {"coordinates":[-0.73359213400473,51.22678394413742],"type":"Point"}
}