{
  "type": "Feature",
  "properties": {
    "date:inception_lower":"2000-12-01",
    "date:inception_upper":"2000-12-31",
    "iso:country":"GB",
    "wof:name":"W1B 5QE",
    "wof:placetype":"postalcode"
},
  "geometry": {"coordinates":[-0.139893,51.513266],"type":"Point"}
}