{
  "type": "Feature",
  "properties": {
    "iso:country": "GB",
    "wof:name": "PL17 8BU",
    "wof:placetype": "postalcode"
  },
  "geometry": {"coordinates":[-4.312286,50.521602],"type":"Point"}
}
