{
  "type": "Feature",
  "properties": {
    "iso:country":"GB",
    "wof:name":"PL17 8BU",
    "wof:placetype":"postalcode"
},
  "geometry": {"coordinates":[-4.31228567032214,50.52160220196807],"type":"Point"}
}