{
  "type": "Feature",
  "properties": {
    "date:inception_lower":"2007-07-01",
    "date:inception_upper":"2007-07-31",
    "iso:country":"GB",
    "wof:name":"PL17 8BU",
    "wof:placetype":"postalcode"
},
  "geometry": {"coordinates":[-4.312286,50.521602],"type":"Point"}
}