{
  "type": "Feature",
  "properties": {
    "date:inception_lower": "1999-12-01",
    "date:inception_upper": "1999-12-01",
    "iso:country": "GB",
    "wof:name": "PH3 1QR",
    "wof:placetype": "postalcode"
  },
  "geometry": {"coordinates":[-3.694702,56.297916],"type":"Point"}
}
