{
  "type": "Feature",
  "properties": {
    "iso:country": "GB",
    "wof:name": "EH10 6JU",
    "wof:placetype": "postalcode"
  },
  "geometry": {"coordinates":[-3.206436,55.914772],"type":"Point"}
}
