{
  "type": "Feature",
  "properties": {
    "iso:country":"GB",
    "wof:name":"EH10 6JU",
    "wof:placetype":"postalcode"
},
  "geometry": {"coordinates":[-3.20643590209626,55.9147717578029],"type":"Point"}
}