{
  "type": "Feature",
  "properties": {
    "date:inception_lower":"1980-01-01",
    "date:inception_upper":"1980-01-31",
    "iso:country":"GB",
    "wof:name":"NP44 2NT",
    "wof:placetype":"postalcode"
},
  "geometry": {"coordinates":[-3.009004,51.663084],"type":"Point"}
}