{
  "type": "Feature",
  "properties": {
    "iso:country":"GB",
    "wof:name":"NP44 2NT",
    "wof:placetype":"postalcode"
},
  "geometry": {"coordinates":[-3.00900392707918,51.66308427890813],"type":"Point"}
}