{
  "type": "Feature",
  "properties": {
    "iso:country":"GB",
    "wof:name":"SW14 8SZ",
    "wof:placetype":"postalcode"
},
  "geometry": {"coordinates":[-0.25433371029379,51.46660975847027],"type":"Point"}
}