{
  "type": "Feature",
  "properties": {
    "iso:country": "GB",
    "wof:name": "SW14 8SZ",
    "wof:placetype": "postalcode"
  },
  "geometry": {"coordinates":[-0.254334,51.46661],"type":"Point"}
}
