{
  "type": "Feature",
  "properties": {
    "iso:country":"GB",
    "wof:name":"DL5 6QB",
    "wof:placetype":"postalcode"
},
  "geometry": {"coordinates":[-1.5990880055421,54.60763980071818],"type":"Point"}
}