{
  "type": "Feature",
  "properties": {
    "date:inception_lower": "1980-01-01",
    "date:inception_upper": "1980-01-01",
    "iso:country": "GB",
    "wof:name": "IP18 6NG",
    "wof:placetype": "postalcode"
  },
  "geometry": {"coordinates":[1.669728,52.334479],"type":"Point"}
}
