{
  "type": "Feature",
  "properties": {
    "iso:country":"GB",
    "wof:name":"IP18 6NG",
    "wof:placetype":"postalcode"
},
  "geometry": {"coordinates":[1.66972790167867,52.33447873478362],"type":"Point"}
}