{
  "type": "Feature",
  "properties": {
    "iso:country": "GB",
    "wof:name": "IP18 6NG",
    "wof:placetype": "postalcode"
  },
  "geometry": {"coordinates":[1.669728,52.334479],"type":"Point"}
}
