{
  "type": "Feature",
  "properties": {
    "date:inception_lower": "1980-01-01",
    "date:inception_upper": "1980-01-01",
    "iso:country": "GB",
    "wof:name": "LA12 7AB",
    "wof:placetype": "postalcode"
  },
  "geometry": {"coordinates":[-3.095089,54.194844],"type":"Point"}
}
