{
  "type": "Feature",
  "properties": {
    "iso:country": "GB",
    "wof:name": "LA12 7AB",
    "wof:placetype": "postalcode"
  },
  "geometry": {"coordinates":[-3.09515,54.194826],"type":"Point"}
}
