{
  "type": "Feature",
  "properties": {
    "iso:country":"GB",
    "wof:name":"G21 4YW",
    "wof:placetype":"postalcode"
},
  "geometry": {"coordinates":[-4.21652629048509,55.88303356430711],"type":"Point"}
}