{
  "type": "Feature",
  "properties": {
    "date:inception_lower": "2023-07-01",
    "date:inception_upper": "2023-07-01",
    "iso:country": "GB",
    "wof:name": "NG5 4FA",
    "wof:placetype": "postalcode"
  },
  "geometry": {"coordinates":[-1.147138,52.979622],"type":"Point"}
}
