{
  "type": "Feature",
  "properties": {
    "date:inception_lower": "1984-10-01",
    "date:inception_upper": "1984-10-01",
    "iso:country": "GB",
    "wof:name": "LS17 9EH",
    "wof:placetype": "postalcode"
  },
  "geometry": {"coordinates":[-1.453228,53.894152],"type":"Point"}
}
