{
  "type": "Feature",
  "properties": {
    "iso:country": "GB",
    "wof:name": "L26 7WE",
    "wof:placetype": "postalcode"
  },
  "geometry": {"coordinates":[-2.836393,53.370232],"type":"Point"}
}
