{
  "type": "Feature",
  "properties": {
    "iso:country":"GB",
    "wof:name":"L26 7WE",
    "wof:placetype":"postalcode"
},
  "geometry": {"coordinates":[-2.83639296401484,53.37023183011858],"type":"Point"}
}