{
  "type": "Feature",
  "properties": {
    "date:inception_lower":"1980-01-01",
    "date:inception_upper":"1980-01-31",
    "iso:country":"GB",
    "wof:name":"TA24 6PR",
    "wof:placetype":"postalcode"
},
  "geometry": {"coordinates":[-3.440777,51.188386],"type":"Point"}
}