{
  "type": "Feature",
  "properties": {
    "iso:country":"GB",
    "wof:name":"SP11 0NX",
    "wof:placetype":"postalcode"
},
  "geometry": {"coordinates":[-1.4139861043342,51.27093129602895],"type":"Point"}
}