{
  "type": "Feature",
  "properties": {
    "iso:country": "GB",
    "wof:name": "KA7 2DH",
    "wof:placetype": "postalcode"
  },
  "geometry": {"coordinates":[-4.635081,55.45726],"type":"Point"}
}
