{
  "type": "Feature",
  "properties": {
    "iso:country":"GB",
    "wof:name":"KA7 2DH",
    "wof:placetype":"postalcode"
},
  "geometry": {"coordinates":[-4.63520598011532,55.4569151180565],"type":"Point"}
}