{
  "type": "Feature",
  "properties": {
    "iso:country": "GB",
    "wof:name": "CF48 1RE",
    "wof:placetype": "postalcode"
  },
  "geometry": {"coordinates":[-3.410144,51.74271],"type":"Point"}
}
