{
  "type": "Feature",
  "properties": {
    "iso:country":"GB",
    "wof:name":"DD7 7RS",
    "wof:placetype":"postalcode"
},
  "geometry": {"coordinates":[-2.74718078089892,56.49568852753891],"type":"Point"}
}