{
  "type": "Feature",
  "properties": {
    "iso:country": "GB",
    "wof:name": "SK14 4AN",
    "wof:placetype": "postalcode"
  },
  "geometry": {"coordinates":[-2.06912,53.459047],"type":"Point"}
}
