{
  "type": "Feature",
  "properties": {
    "iso:country":"GB",
    "wof:name":"PE4 7YW",
    "wof:placetype":"postalcode"
},
  "geometry": {"coordinates":[-0.25482341457656,52.60994085491888],"type":"Point"}
}