{
  "type": "Feature",
  "properties": {
    "date:inception_lower":"1992-01-01",
    "date:inception_upper":"1992-01-31",
    "iso:country":"GB",
    "wof:name":"PE4 7YW",
    "wof:placetype":"postalcode"
},
  "geometry": {"coordinates":[-0.254823,52.609941],"type":"Point"}
}