{
  "type": "Feature",
  "properties": {
    "iso:country": "GB",
    "wof:name": "PE4 7YW",
    "wof:placetype": "postalcode"
  },
  "geometry": {"coordinates":[-0.254823,52.609941],"type":"Point"}
}
