{
  "type": "Feature",
  "properties": {
    "iso:country": "GB",
    "wof:name": "CB3 9BG",
    "wof:placetype": "postalcode"
  },
  "geometry": {"coordinates":[0.102575,52.200915],"type":"Point"}
}
