{
  "type": "Feature",
  "properties": {
    "iso:country":"GB",
    "wof:name":"NE1 5DY",
    "wof:placetype":"postalcode"
},
  "geometry": {"coordinates":[-1.619792737144,54.97025929443225],"type":"Point"}
}