{
  "type": "Feature",
  "properties": {
    "iso:country": "GB",
    "wof:name": "GU51 3RR",
    "wof:placetype": "postalcode"
  },
  "geometry": {"coordinates":[-0.841498,51.27833],"type":"Point"}
}
