{
  "type": "Feature",
  "properties": {
    "iso:country":"GB",
    "wof:name":"GU51 3RR",
    "wof:placetype":"postalcode"
},
  "geometry": {"coordinates":[-0.84149820294372,51.27833014228185],"type":"Point"}
}