{
  "type": "Feature",
  "properties": {
    "date:inception_lower": "2001-06-01",
    "date:inception_upper": "2001-06-01",
    "iso:country": "GB",
    "wof:name": "GU51 3RR",
    "wof:placetype": "postalcode"
  },
  "geometry": {"coordinates":[-0.841452,51.278365],"type":"Point"}
}
