{
  "type": "Feature",
  "properties": {
    "iso:country":"GB",
    "wof:name":"BA12 9PG",
    "wof:placetype":"postalcode"
},
  "geometry": {"coordinates":[-2.18750164235817,51.19697487390172],"type":"Point"}
}