{
  "type": "Feature",
  "properties": {
    "date:inception_lower":"1980-01-01",
    "date:inception_upper":"1980-01-31",
    "iso:country":"GB",
    "wof:name":"BA12 9PG",
    "wof:placetype":"postalcode"
},
  "geometry": {"coordinates":[-2.187502,51.196975],"type":"Point"}
}