{
  "type": "Feature",
  "properties": {
    "iso:country":"GB",
    "wof:name":"W3 8QF",
    "wof:placetype":"postalcode"
},
  "geometry": {"coordinates":[-0.27725652256022,51.50513949736183],"type":"Point"}
}