{
  "type": "Feature",
  "properties": {
    "iso:country": "GB",
    "wof:name": "W3 8QF",
    "wof:placetype": "postalcode"
  },
  "geometry": {"coordinates":[-0.277285,51.505158],"type":"Point"}
}
