{
  "type": "Feature",
  "properties": {
    "iso:country":"GB",
    "wof:name":"KY15 5TL",
    "wof:placetype":"postalcode"
},
  "geometry": {"coordinates":[-2.94629876850283,56.32268085284769],"type":"Point"}
}