{
  "type": "Feature",
  "properties": {
    "iso:country":"GB",
    "wof:name":"KA11 2DS",
    "wof:placetype":"postalcode"
},
  "geometry": {"coordinates":[-4.61989701060734,55.62943208703213],"type":"Point"}
}