{
  "type": "Feature",
  "properties": {
    "iso:country": "GB",
    "wof:name": "KA11 2DS",
    "wof:placetype": "postalcode"
  },
  "geometry": {"coordinates":[-4.619897,55.629432],"type":"Point"}
}
