{
  "type": "Feature",
  "properties": {
    "date:inception_lower": "1992-10-01",
    "date:inception_upper": "1992-10-01",
    "iso:country": "GB",
    "wof:name": "KA11 2DS",
    "wof:placetype": "postalcode"
  },
  "geometry": {"coordinates":[-4.619897,55.629432],"type":"Point"}
}
