{
  "type": "Feature",
  "properties": {
    "date:inception_lower": "2001-12-01",
    "date:inception_upper": "2001-12-01",
    "iso:country": "GB",
    "wof:name": "EN3 6FF",
    "wof:placetype": "postalcode"
  },
  "geometry": {"coordinates":[-0.027456,51.674715],"type":"Point"}
}
