{
  "type": "Feature",
  "properties": {
    "iso:country":"GB",
    "wof:name":"TF2 8EY",
    "wof:placetype":"postalcode"
},
  "geometry": {"coordinates":[-2.43558965883699,52.72002430602134],"type":"Point"}
}