{
  "type": "Feature",
  "properties": {
    "iso:country":"GB",
    "wof:name":"RH8 0TT",
    "wof:placetype":"postalcode"
},
  "geometry": {"coordinates":[0.03657878488544,51.25026858395703],"type":"Point"}
}