{
  "type": "Feature",
  "properties": {
    "iso:country":"GB",
    "wof:name":"G20 8NF",
    "wof:placetype":"postalcode"
},
  "geometry": {"coordinates":[-4.28434134244378,55.8863409690802],"type":"Point"}
}