{
  "type": "Feature",
  "properties": {
    "iso:country":"GB",
    "wof:name":"BS15 4HR",
    "wof:placetype":"postalcode"
},
  "geometry": {"coordinates":[-2.49185267417731,51.46269755769084],"type":"Point"}
}