{
  "type": "Feature",
  "properties": {
    "iso:country":"GB",
    "wof:name":"AL5 5LR",
    "wof:placetype":"postalcode"
},
  "geometry": {"coordinates":[-0.34874270336168,51.81254566449752],"type":"Point"}
}