{
  "type": "Feature",
  "properties": {
    "iso:country": "GB",
    "wof:name": "S60 5JP",
    "wof:placetype": "postalcode"
  },
  "geometry": {"coordinates":[-1.360544,53.399866],"type":"Point"}
}
