{
  "type": "Feature",
  "properties": {
    "iso:country":"GB",
    "wof:name":"LS10 4WN",
    "wof:placetype":"postalcode"
},
  "geometry": {"coordinates":[-1.5299183369612,53.74500640540017],"type":"Point"}
}