{
  "type": "Feature",
  "properties": {
    "iso:country":"GB",
    "wof:name":"LL55 1LW",
    "wof:placetype":"postalcode"
},
  "geometry": {"coordinates":[-4.26355965535083,53.15155663245815],"type":"Point"}
}