{
  "type": "Feature",
  "properties": {
    "iso:country": "GB",
    "wof:name": "NP12 1WJ",
    "wof:placetype": "postalcode"
  },
  "geometry": {"coordinates":[-3.203856,51.668397],"type":"Point"}
}
