{
  "type": "Feature",
  "properties": {
    "date:inception_lower": "2014-11-01",
    "date:inception_upper": "2014-11-01",
    "iso:country": "GB",
    "wof:name": "SE1 5XY",
    "wof:placetype": "postalcode"
  },
  "geometry": {"coordinates":[-0.071631,51.485484],"type":"Point"}
}
