{
  "type": "Feature",
  "properties": {
    "iso:country":"GB",
    "wof:name":"SE1 5XY",
    "wof:placetype":"postalcode"
},
  "geometry": {"coordinates":[-0.07168538610709,51.48549219960912],"type":"Point"}
}