{
  "type": "Feature",
  "properties": {
    "date:inception_lower": "2014-11-01",
    "date:inception_upper": "2014-11-01",
    "iso:country": "GB",
    "wof:name": "SE1 5XY",
    "wof:placetype": "postalcode"
  },
  "geometry": {"coordinates":[-0.071685,51.485492],"type":"Point"}
}
