{
  "type": "Feature",
  "properties": {
    "iso:country": "GB",
    "wof:name": "SS17 8BP",
    "wof:placetype": "postalcode"
  },
  "geometry": {"coordinates":[0.438707,51.529272],"type":"Point"}
}
