{
  "type": "Feature",
  "properties": {
    "date:inception_lower":"1980-01-01",
    "date:inception_upper":"1980-01-31",
    "iso:country":"GB",
    "wof:name":"SS17 8BP",
    "wof:placetype":"postalcode"
},
  "geometry": {"coordinates":[0.438707,51.529272],"type":"Point"}
}