{
  "type": "Feature",
  "properties": {
    "date:inception_lower":"1998-12-01",
    "date:inception_upper":"1998-12-31",
    "iso:country":"GB",
    "wof:name":"DY5 3FW",
    "wof:placetype":"postalcode"
},
  "geometry": {"coordinates":[-2.14101,52.471945],"type":"Point"}
}