{
  "type": "Feature",
  "properties": {
    "iso:country": "GB",
    "wof:name": "WA8 7ND",
    "wof:placetype": "postalcode"
  },
  "geometry": {"coordinates":[-2.734273,53.365376],"type":"Point"}
}
