{
  "type": "Feature",
  "properties": {
    "iso:country":"GB",
    "wof:name":"CH7 6SR",
    "wof:placetype":"postalcode"
},
  "geometry": {"coordinates":[-3.13346792457583,53.18979288467141],"type":"Point"}
}