{
  "type": "Feature",
  "properties": {
    "iso:country": "GB",
    "wof:name": "CH7 6SR",
    "wof:placetype": "postalcode"
  },
  "geometry": {"coordinates":[-3.133468,53.189793],"type":"Point"}
}
