{
  "type": "Feature",
  "properties": {
    "iso:country":"GB",
    "wof:name":"TN19 7LJ",
    "wof:placetype":"postalcode"
},
  "geometry": {"coordinates":[0.33809048763857,50.9851662374891],"type":"Point"}
}