{
  "type": "Feature",
  "properties": {
    "date:inception_lower": "1980-01-01",
    "date:inception_upper": "1980-01-01",
    "iso:country": "GB",
    "wof:name": "BN12 4AY",
    "wof:placetype": "postalcode"
  },
  "geometry": {"coordinates":[-0.410151,50.812545],"type":"Point"}
}
