{
  "type": "Feature",
  "properties": {
    "iso:country": "GB",
    "wof:name": "BN12 4AY",
    "wof:placetype": "postalcode"
  },
  "geometry": {"coordinates":[-0.410047,50.812569],"type":"Point"}
}
