{
  "type": "Feature",
  "properties": {
    "iso:country":"GB",
    "wof:name":"ST17 9LG",
    "wof:placetype":"postalcode"
},
  "geometry": {"coordinates":[-2.11587735648876,52.78069272287487],"type":"Point"}
}