{
  "type": "Feature",
  "properties": {
    "date:inception_lower": "1980-01-01",
    "date:inception_upper": "1980-01-01",
    "iso:country": "GB",
    "wof:name": "NN8 1HP",
    "wof:placetype": "postalcode"
  },
  "geometry": {"coordinates":[-0.685088,52.302167],"type":"Point"}
}
