{
  "type": "Feature",
  "properties": {
    "iso:country":"GB",
    "wof:name":"NG34 9PB",
    "wof:placetype":"postalcode"
},
  "geometry": {"coordinates":[-0.36519542152611,53.01330704683452],"type":"Point"}
}