{
  "type": "Feature",
  "properties": {
    "iso:country": "GB",
    "wof:name": "SA8 3JJ",
    "wof:placetype": "postalcode"
  },
  "geometry": {"coordinates":[-3.817616,51.725195],"type":"Point"}
}
