{
  "type": "Feature",
  "properties": {
    "iso:country":"GB",
    "wof:name":"SA8 3JJ",
    "wof:placetype":"postalcode"
},
  "geometry": {"coordinates":[-3.81760089800401,51.72518942192544],"type":"Point"}
}