{
  "type": "Feature",
  "properties": {
    "iso:country":"GB",
    "wof:name":"LA9 4DP",
    "wof:placetype":"postalcode"
},
  "geometry": {"coordinates":[-2.748152424373,54.32795260505471],"type":"Point"}
}