{
  "type": "Feature",
  "properties": {
    "iso:country": "GB",
    "wof:name": "LA9 4DP",
    "wof:placetype": "postalcode"
  },
  "geometry": {"coordinates":[-2.748082,54.328196],"type":"Point"}
}
