{
  "type": "Feature",
  "properties": {
    "date:inception_lower": "2004-01-01",
    "date:inception_upper": "2004-01-01",
    "iso:country": "GB",
    "wof:name": "LA9 4DP",
    "wof:placetype": "postalcode"
  },
  "geometry": {"coordinates":[-2.748282,54.328231],"type":"Point"}
}
