{
  "type": "Feature",
  "properties": {
    "iso:country":"GB",
    "wof:name":"EH48 3DD",
    "wof:placetype":"postalcode"
},
  "geometry": {"coordinates":[-3.70254704576672,55.92958868456246],"type":"Point"}
}