{
  "type": "Feature",
  "properties": {
    "date:inception_lower":"2008-01-01",
    "date:inception_upper":"2008-01-31",
    "iso:country":"GB",
    "wof:name":"MK19 7AX",
    "wof:placetype":"postalcode"
},
  "geometry": {"coordinates":[-0.824279,52.112075],"type":"Point"}
}