{
  "type": "Feature",
  "properties": {
    "iso:country": "GB",
    "wof:name": "MK19 7AX",
    "wof:placetype": "postalcode"
  },
  "geometry": {"coordinates":[-0.824279,52.112075],"type":"Point"}
}
