{
  "type": "Feature",
  "properties": {
    "iso:country":"GB",
    "wof:name":"CF10 5HZ",
    "wof:placetype":"postalcode"
},
  "geometry": {"coordinates":[-3.17164069950165,51.47150563774063],"type":"Point"}
}