{
  "type": "Feature",
  "properties": {
    "date:inception_lower":"1999-06-01",
    "date:inception_upper":"1999-06-30",
    "iso:country":"GB",
    "wof:name":"CF10 5HZ",
    "wof:placetype":"postalcode"
},
  "geometry": {"coordinates":[-3.171641,51.471506],"type":"Point"}
}