{
  "type": "Feature",
  "properties": {
    "date:inception_lower": "1980-01-01",
    "date:inception_upper": "1980-01-01",
    "iso:country": "GB",
    "wof:name": "DH8 0QU",
    "wof:placetype": "postalcode"
  },
  "geometry": {"coordinates":[-1.851623,54.871833],"type":"Point"}
}
