{
  "type": "Feature",
  "properties": {
    "iso:country":"GB",
    "wof:name":"DH8 0QU",
    "wof:placetype":"postalcode"
},
  "geometry": {"coordinates":[-1.85162267074016,54.87183257392726],"type":"Point"}
}