{
  "type": "Feature",
  "properties": {
    "date:inception_lower": "1980-01-01",
    "date:inception_upper": "1980-01-01",
    "iso:country": "GB",
    "wof:name": "TN25 6HF",
    "wof:placetype": "postalcode"
  },
  "geometry": {"coordinates":[1.01569,51.108923],"type":"Point"}
}
