{
  "type": "Feature",
  "properties": {
    "date:inception_lower": "1981-06-01",
    "date:inception_upper": "1981-06-01",
    "iso:country": "GB",
    "wof:name": "HP18 0SN",
    "wof:placetype": "postalcode"
  },
  "geometry": {"coordinates":[-1.017222,51.88234],"type":"Point"}
}
