{
  "type": "Feature",
  "properties": {
    "iso:country":"GB",
    "wof:name":"M26 4BW",
    "wof:placetype":"postalcode"
},
  "geometry": {"coordinates":[-2.33407869485357,53.5640786535955],"type":"Point"}
}