{
  "type": "Feature",
  "properties": {
    "iso:country":"GB",
    "wof:name":"CV23 9QJ",
    "wof:placetype":"postalcode"
},
  "geometry": {"coordinates":[-1.41255309053046,52.32701138116776],"type":"Point"}
}