{
  "type": "Feature",
  "properties": {
    "date:inception_lower": "1980-01-01",
    "date:inception_upper": "1980-01-01",
    "iso:country": "GB",
    "wof:name": "CV23 9QJ",
    "wof:placetype": "postalcode"
  },
  "geometry": {"coordinates":[-1.412553,52.327011],"type":"Point"}
}
