{
  "type": "Feature",
  "properties": {
    "date:inception_lower": "2020-02-01",
    "date:inception_upper": "2020-02-01",
    "iso:country": "GB",
    "wof:name": "SO14 5DJ",
    "wof:placetype": "postalcode"
  },
  "geometry": {"coordinates":[-1.389151,50.901009],"type":"Point"}
}
