{
  "type": "Feature",
  "properties": {
    "iso:country":"GB",
    "wof:name":"FK3 9XE",
    "wof:placetype":"postalcode"
},
  "geometry": {"coordinates":[-3.67554731046824,56.00380724569867],"type":"Point"}
}