{
  "type": "Feature",
  "properties": {
    "date:inception_lower": "1984-10-01",
    "date:inception_upper": "1984-10-01",
    "iso:country": "GB",
    "wof:name": "TA11 6LW",
    "wof:placetype": "postalcode"
  },
  "geometry": {"coordinates":[-2.730447,51.055],"type":"Point"}
}
