{
  "type": "Feature",
  "properties": {
    "iso:country":"GB",
    "wof:name":"TA11 6LW",
    "wof:placetype":"postalcode"
},
  "geometry": {"coordinates":[-2.7304138623257,51.05498852920216],"type":"Point"}
}