{
  "type": "Feature",
  "properties": {
    "iso:country":"GB",
    "wof:name":"DE4 4FP",
    "wof:placetype":"postalcode"
},
  "geometry": {"coordinates":[-1.57311029678741,53.08722903826096],"type":"Point"}
}