{
  "type": "Feature",
  "properties": {
    "iso:country":"GB",
    "wof:name":"CT16 2AA",
    "wof:placetype":"postalcode"
},
  "geometry": {"coordinates":[1.30026981454415,51.13562754790277],"type":"Point"}
}