{
  "type": "Feature",
  "properties": {
    "iso:country":"GB",
    "wof:name":"TN4 9EW",
    "wof:placetype":"postalcode"
},
  "geometry": {"coordinates":[0.26800061831011,51.14893709505434],"type":"Point"}
}