{
  "type": "Feature",
  "properties": {
    "date:inception_lower": "1983-01-01",
    "date:inception_upper": "1983-01-01",
    "iso:country": "GB",
    "wof:name": "DY4 8QR",
    "wof:placetype": "postalcode"
  },
  "geometry": {"coordinates":[-2.068882,52.528596],"type":"Point"}
}
