{
  "type": "Feature",
  "properties": {
    "iso:country":"GB",
    "wof:name":"PL28 8NT",
    "wof:placetype":"postalcode"
},
  "geometry": {"coordinates":[-4.99184595694785,50.52709645776723],"type":"Point"}
}