{
  "type": "Feature",
  "properties": {
    "date:inception_lower":"1994-05-01",
    "date:inception_upper":"1994-05-31",
    "iso:country":"GB",
    "wof:name":"SA12 9UU",
    "wof:placetype":"postalcode"
},
  "geometry": {"coordinates":[-3.736437,51.653927],"type":"Point"}
}