{
  "type": "Feature",
  "properties": {
    "date:inception_lower": "1994-05-01",
    "date:inception_upper": "1994-05-01",
    "iso:country": "GB",
    "wof:name": "SA12 9UU",
    "wof:placetype": "postalcode"
  },
  "geometry": {"coordinates":[-3.736392,51.653865],"type":"Point"}
}
