{
  "type": "Feature",
  "properties": {
    "date:inception_lower": "1999-06-01",
    "date:inception_upper": "1999-06-01",
    "iso:country": "GB",
    "wof:name": "CF15 9SB",
    "wof:placetype": "postalcode"
  },
  "geometry": {"coordinates":[-3.325827,51.528041],"type":"Point"}
}
