{
  "type": "Feature",
  "properties": {
    "iso:country":"GB",
    "wof:name":"CF15 9SB",
    "wof:placetype":"postalcode"
},
  "geometry": {"coordinates":[-3.32582687165378,51.52804150072399],"type":"Point"}
}