{
  "type": "Feature",
  "properties": {
    "iso:country": "GB",
    "wof:name": "WD25 8AW",
    "wof:placetype": "postalcode"
  },
  "geometry": {"coordinates":[-0.354379,51.672967],"type":"Point"}
}
