{
  "type": "Feature",
  "properties": {
    "date:inception_lower": "2000-10-01",
    "date:inception_upper": "2000-10-01",
    "iso:country": "GB",
    "wof:name": "WD25 8AW",
    "wof:placetype": "postalcode"
  },
  "geometry": {"coordinates":[-0.354379,51.672967],"type":"Point"}
}
