{
  "type": "Feature",
  "properties": {
    "iso:country":"GB",
    "wof:name":"M41 9DF",
    "wof:placetype":"postalcode"
},
  "geometry": {"coordinates":[-2.36081404266214,53.44661179265003],"type":"Point"}
}