{
  "type": "Feature",
  "properties": {
    "iso:country": "GB",
    "wof:name": "WN3 4DR",
    "wof:placetype": "postalcode"
  },
  "geometry": {"coordinates":[-2.638842,53.544679],"type":"Point"}
}
