{
  "type": "Feature",
  "properties": {
    "iso:country":"GB",
    "wof:name":"WN3 4DR",
    "wof:placetype":"postalcode"
},
  "geometry": {"coordinates":[-2.63884230960727,53.5446638932152],"type":"Point"}
}