{
  "type": "Feature",
  "properties": {
    "date:inception_lower": "2006-03-01",
    "date:inception_upper": "2006-03-01",
    "iso:country": "GB",
    "wof:name": "WN3 4DR",
    "wof:placetype": "postalcode"
  },
  "geometry": {"coordinates":[-2.639387,53.544793],"type":"Point"}
}
