{
  "type": "Feature",
  "properties": {
    "date:inception_lower":"1994-05-01",
    "date:inception_upper":"1994-05-31",
    "iso:country":"GB",
    "wof:name":"M34 7XA",
    "wof:placetype":"postalcode"
},
  "geometry": {"coordinates":[-2.109202,53.438038],"type":"Point"}
}