{
  "type": "Feature",
  "properties": {
    "iso:country":"GB",
    "wof:name":"M34 7XA",
    "wof:placetype":"postalcode"
},
  "geometry": {"coordinates":[-2.10920206440277,53.43803788044625],"type":"Point"}
}