{
  "type": "Feature",
  "properties": {
    "date:inception_lower": "1990-08-01",
    "date:inception_upper": "1990-08-01",
    "iso:country": "GB",
    "wof:name": "AB44 1TP",
    "wof:placetype": "postalcode"
  },
  "geometry": {"coordinates":[-2.495952,57.671334],"type":"Point"}
}
