{
  "type": "Feature",
  "properties": {
    "iso:country": "GB",
    "wof:name": "EH54 6AS",
    "wof:placetype": "postalcode"
  },
  "geometry": {"coordinates":[-3.515839,55.894188],"type":"Point"}
}
