{
  "type": "Feature",
  "properties": {
    "iso:country":"GB",
    "wof:name":"NG5 1GD",
    "wof:placetype":"postalcode"
},
  "geometry": {"coordinates":[-1.16102517437764,52.98097745487316],"type":"Point"}
}