{
  "type": "Feature",
  "properties": {
    "iso:country":"GB",
    "wof:name":"SL6 7LU",
    "wof:placetype":"postalcode"
},
  "geometry": {"coordinates":[-0.72687688899389,51.52614044023606],"type":"Point"}
}