{
  "type": "Feature",
  "properties": {
    "date:inception_lower": "1992-01-01",
    "date:inception_upper": "1992-01-01",
    "iso:country": "GB",
    "wof:name": "SL6 7LU",
    "wof:placetype": "postalcode"
  },
  "geometry": {"coordinates":[-0.726877,51.52614],"type":"Point"}
}
