{
  "type": "Feature",
  "properties": {
    "iso:country":"GB",
    "wof:name":"SO40 7QJ",
    "wof:placetype":"postalcode"
},
  "geometry": {"coordinates":[-1.50169897735265,50.90934853050824],"type":"Point"}
}