{
  "type": "Feature",
  "properties": {
    "iso:country": "GB",
    "wof:name": "DA5 3JS",
    "wof:placetype": "postalcode"
  },
  "geometry": {"coordinates":[0.137739,51.43981],"type":"Point"}
}
