{
  "type": "Feature",
  "properties": {
    "iso:country":"GB",
    "wof:name":"RG41 3UL",
    "wof:placetype":"postalcode"
},
  "geometry": {"coordinates":[-0.86423701912951,51.41775935028694],"type":"Point"}
}