{
  "type": "Feature",
  "properties": {
    "iso:country":"GB",
    "wof:name":"YO32 4DY",
    "wof:placetype":"postalcode"
},
  "geometry": {"coordinates":[-1.07399478575934,53.99577450891435],"type":"Point"}
}