{
  "type": "Feature",
  "properties": {
    "iso:country": "GB",
    "wof:name": "YO32 4DY",
    "wof:placetype": "postalcode"
  },
  "geometry": {"coordinates":[-1.073995,53.995775],"type":"Point"}
}
