{
  "type": "Feature",
  "properties": {
    "iso:country":"GB",
    "wof:name":"GL52 5GB",
    "wof:placetype":"postalcode"
},
  "geometry": {"coordinates":[-2.04897866209159,51.90275027734328],"type":"Point"}
}