{
  "type": "Feature",
  "properties": {
    "date:inception_lower": "1980-01-01",
    "date:inception_upper": "1980-01-01",
    "iso:country": "GB",
    "wof:name": "SA33 5PT",
    "wof:placetype": "postalcode"
  },
  "geometry": {"coordinates":[-4.471645,51.885776],"type":"Point"}
}
