{
  "type": "Feature",
  "properties": {
    "date:inception_lower": "1980-01-01",
    "date:inception_upper": "1980-01-01",
    "iso:country": "GB",
    "wof:name": "MK18 5AY",
    "wof:placetype": "postalcode"
  },
  "geometry": {"coordinates":[-0.975957,52.060039],"type":"Point"}
}
