{
  "type": "Feature",
  "properties": {
    "date:inception_lower":"1997-12-01",
    "date:inception_upper":"1997-12-31",
    "iso:country":"GB",
    "wof:name":"NG17 2SF",
    "wof:placetype":"postalcode"
},
  "geometry": {"coordinates":[-1.307282,53.124588],"type":"Point"}
}