{
  "type": "Feature",
  "properties": {
    "iso:country": "GB",
    "wof:name": "NG17 2SF",
    "wof:placetype": "postalcode"
  },
  "geometry": {"coordinates":[-1.307282,53.124588],"type":"Point"}
}
