{
  "type": "Feature",
  "properties": {
    "iso:country":"GB",
    "wof:name":"NG17 2SF",
    "wof:placetype":"postalcode"
},
  "geometry": {"coordinates":[-1.30728163420712,53.12458788110851],"type":"Point"}
}