{
  "type": "Feature",
  "properties": {
    "iso:country":"GB",
    "wof:name":"NG1 2NR",
    "wof:placetype":"postalcode"
},
  "geometry": {"coordinates":[-1.14954939373205,52.95250714769172],"type":"Point"}
}