{
  "type": "Feature",
  "properties": {
    "iso:country": "GB",
    "wof:name": "AB12 4TL",
    "wof:placetype": "postalcode"
  },
  "geometry": {"coordinates":[-2.138955,57.059691],"type":"Point"}
}
