{
  "type": "Feature",
  "properties": {
    "iso:country": "GB",
    "wof:name": "CH7 4NQ",
    "wof:placetype": "postalcode"
  },
  "geometry": {"coordinates":[-3.119953,53.119156],"type":"Point"}
}
