{
  "type": "Feature",
  "properties": {
    "date:inception_lower":"1980-01-01",
    "date:inception_upper":"1980-01-31",
    "iso:country":"GB",
    "wof:name":"CH7 4NQ",
    "wof:placetype":"postalcode"
},
  "geometry": {"coordinates":[-3.119953,53.119156],"type":"Point"}
}