{
  "type": "Feature",
  "properties": {
    "iso:country":"GB",
    "wof:name":"NE3 2XA",
    "wof:placetype":"postalcode"
},
  "geometry": {"coordinates":[-1.67137486733645,55.01591568128821],"type":"Point"}
}