{
  "type": "Feature",
  "properties": {
    "date:inception_lower":"1980-01-01",
    "date:inception_upper":"1980-01-31",
    "iso:country":"GB",
    "wof:name":"NE3 2XA",
    "wof:placetype":"postalcode"
},
  "geometry": {"coordinates":[-1.671375,55.015916],"type":"Point"}
}