{
  "type": "Feature",
  "properties": {
    "iso:country": "GB",
    "wof:name": "NR1 1TU",
    "wof:placetype": "postalcode"
  },
  "geometry": {"coordinates":[1.321053,52.624415],"type":"Point"}
}
