{
  "type": "Feature",
  "properties": {
    "iso:country":"GB",
    "wof:name":"NR1 1TU",
    "wof:placetype":"postalcode"
},
  "geometry": {"coordinates":[1.32105267108454,52.6244149869833],"type":"Point"}
}