{
  "type": "Feature",
  "properties": {
    "iso:country":"GB",
    "wof:name":"N2 8ES",
    "wof:placetype":"postalcode"
},
  "geometry": {"coordinates":[-0.1720363727719,51.59481983395717],"type":"Point"}
}