{
  "type": "Feature",
  "properties": {
    "date:inception_lower": "1980-01-01",
    "date:inception_upper": "1980-01-01",
    "iso:country": "GB",
    "wof:name": "GU14 7JT",
    "wof:placetype": "postalcode"
  },
  "geometry": {"coordinates":[-0.753507,51.293136],"type":"Point"}
}
