{
  "type": "Feature",
  "properties": {
    "date:inception_lower": "2020-02-01",
    "date:inception_upper": "2020-02-01",
    "iso:country": "GB",
    "wof:name": "CH66 1UQ",
    "wof:placetype": "postalcode"
  },
  "geometry": {"coordinates":[-2.910095,53.292484],"type":"Point"}
}
