{
  "type": "Feature",
  "properties": {
    "date:inception_lower":"2010-02-01",
    "date:inception_upper":"2010-02-28",
    "iso:country":"GB",
    "wof:name":"YO11 2EU",
    "wof:placetype":"postalcode"
},
  "geometry": {"coordinates":[-0.399189,54.280216],"type":"Point"}
}