{
  "type": "Feature",
  "properties": {
    "iso:country":"GB",
    "wof:name":"YO11 2EU",
    "wof:placetype":"postalcode"
},
  "geometry": {"coordinates":[-0.39918915045769,54.28021633952381],"type":"Point"}
}