{
  "type": "Feature",
  "properties": {
    "iso:country":"GB",
    "wof:name":"SE24 0LA",
    "wof:placetype":"postalcode"
},
  "geometry": {"coordinates":[-0.10716701390409,51.45577424116215],"type":"Point"}
}