{
  "type": "Feature",
  "properties": {
    "date:inception_lower": "2020-02-01",
    "date:inception_upper": "2020-02-01",
    "iso:country": "GB",
    "wof:name": "RG25 2FL",
    "wof:placetype": "postalcode"
  },
  "geometry": {"coordinates":[-1.198363,51.214019],"type":"Point"}
}
