{
  "type": "Feature",
  "properties": {
    "iso:country": "GB",
    "wof:name": "RG25 2FL",
    "wof:placetype": "postalcode"
  },
  "geometry": {"coordinates":[-1.198405,51.214064],"type":"Point"}
}
