{
  "type": "Feature",
  "properties": {
    "iso:country": "GB",
    "wof:name": "BS31 3DY",
    "wof:placetype": "postalcode"
  },
  "geometry": {"coordinates":[-2.463915,51.400419],"type":"Point"}
}
