{
  "type": "Feature",
  "properties": {
    "iso:country":"GB",
    "wof:name":"WV11 3UH",
    "wof:placetype":"postalcode"
},
  "geometry": {"coordinates":[-2.06850523018267,52.59857257499114],"type":"Point"}
}