{
  "type": "Feature",
  "properties": {
    "iso:country": "GB",
    "wof:name": "RG2 6AW",
    "wof:placetype": "postalcode"
  },
  "geometry": {"coordinates":[-0.99581,51.42718],"type":"Point"}
}
