{
  "type": "Feature",
  "properties": {
    "iso:country": "GB",
    "wof:name": "PR4 4TE",
    "wof:placetype": "postalcode"
  },
  "geometry": {"coordinates":[-2.775159,53.698916],"type":"Point"}
}
