{
  "type": "Feature",
  "properties": {
    "iso:country":"GB",
    "wof:name":"NG10 2AF",
    "wof:placetype":"postalcode"
},
  "geometry": {"coordinates":[-1.26426922574621,52.89777134121463],"type":"Point"}
}