{
  "type": "Feature",
  "properties": {
    "iso:country":"GB",
    "wof:name":"SW15 3JL",
    "wof:placetype":"postalcode"
},
  "geometry": {"coordinates":[-0.21872883611063,51.45220781999151],"type":"Point"}
}