{
  "type": "Feature",
  "properties": {
    "iso:country":"GB",
    "wof:name":"E3 3SR",
    "wof:placetype":"postalcode"
},
  "geometry": {"coordinates":[-0.0289072992261,51.53022973343165],"type":"Point"}
}