{
  "type": "Feature",
  "properties": {
    "iso:country":"GB",
    "wof:name":"RG28 7RN",
    "wof:placetype":"postalcode"
},
  "geometry": {"coordinates":[-1.36988930259116,51.23029248126458],"type":"Point"}
}