{
  "type": "Feature",
  "properties": {
    "date:inception_lower":"1980-01-01",
    "date:inception_upper":"1980-01-31",
    "iso:country":"GB",
    "wof:name":"LE13 1ES",
    "wof:placetype":"postalcode"
},
  "geometry": {"coordinates":[-0.874802,52.758614],"type":"Point"}
}