{
  "type": "Feature",
  "properties": {
    "iso:country": "GB",
    "wof:name": "B29 7QN",
    "wof:placetype": "postalcode"
  },
  "geometry": {"coordinates":[-1.917981,52.440545],"type":"Point"}
}
