{
  "type": "Feature",
  "properties": {
    "iso:country":"GB",
    "wof:name":"BN26 5XS",
    "wof:placetype":"postalcode"
},
  "geometry": {"coordinates":[0.15351984852297,50.8086350331611],"type":"Point"}
}