{
  "type": "Feature",
  "properties": {
    "iso:country":"GB",
    "wof:name":"EC3N 4TH",
    "wof:placetype":"postalcode"
},
  "geometry": {"coordinates":[-0.07637944809974,51.51050578531355],"type":"Point"}
}