{
  "type": "Feature",
  "properties": {
    "date:inception_lower": "2016-11-01",
    "date:inception_upper": "2016-11-01",
    "iso:country": "GB",
    "wof:name": "WS10 7EY",
    "wof:placetype": "postalcode"
  },
  "geometry": {"coordinates":[-2.022281,52.553522],"type":"Point"}
}
