{
  "type": "Feature",
  "properties": {
    "iso:country":"GB",
    "wof:name":"WS10 7EY",
    "wof:placetype":"postalcode"
},
  "geometry": {"coordinates":[-2.02241859178193,52.55303000130311],"type":"Point"}
}