{
  "type": "Feature",
  "properties": {
    "date:inception_lower": "1980-01-01",
    "date:inception_upper": "1980-01-01",
    "iso:country": "GB",
    "wof:name": "CF38 1EP",
    "wof:placetype": "postalcode"
  },
  "geometry": {"coordinates":[-3.324808,51.571999],"type":"Point"}
}
