{
  "type": "Feature",
  "properties": {
    "iso:country":"GB",
    "wof:name":"CF38 1EP",
    "wof:placetype":"postalcode"
},
  "geometry": {"coordinates":[-3.32532353085556,51.57174797000033],"type":"Point"}
}