{
  "type": "Feature",
  "properties": {
    "date:inception_lower": "2002-06-01",
    "date:inception_upper": "2002-06-01",
    "iso:country": "GB",
    "wof:name": "DE23 1PW",
    "wof:placetype": "postalcode"
  },
  "geometry": {"coordinates":[-1.50357,52.890382],"type":"Point"}
}
