{
  "type": "Feature",
  "properties": {
    "iso:country":"GB",
    "wof:name":"DE23 1PW",
    "wof:placetype":"postalcode"
},
  "geometry": {"coordinates":[-1.50356979681605,52.89038201662975],"type":"Point"}
}