{
  "type": "Feature",
  "properties": {
    "iso:country": "GB",
    "wof:name": "LS17 8JS",
    "wof:placetype": "postalcode"
  },
  "geometry": {"coordinates":[-1.47543,53.854021],"type":"Point"}
}
