{
  "type": "Feature",
  "properties": {
    "iso:country":"GB",
    "wof:name":"LS17 8JS",
    "wof:placetype":"postalcode"
},
  "geometry": {"coordinates":[-1.47542965727049,53.85402139854731],"type":"Point"}
}