{
  "type": "Feature",
  "properties": {
    "date:inception_lower": "1980-01-01",
    "date:inception_upper": "1980-01-01",
    "iso:country": "GB",
    "wof:name": "KY11 1AX",
    "wof:placetype": "postalcode"
  },
  "geometry": {"coordinates":[-3.400338,56.029633],"type":"Point"}
}
