{
  "type": "Feature",
  "properties": {
    "iso:country": "GB",
    "wof:name": "KY11 1AX",
    "wof:placetype": "postalcode"
  },
  "geometry": {"coordinates":[-3.400338,56.029633],"type":"Point"}
}
