{
  "type": "Feature",
  "properties": {
    "iso:country":"GB",
    "wof:name":"LD7 1TE",
    "wof:placetype":"postalcode"
},
  "geometry": {"coordinates":[-3.11378242017534,52.34887699938255],"type":"Point"}
}