{
  "type": "Feature",
  "properties": {
    "date:inception_lower": "1980-01-01",
    "date:inception_upper": "1980-01-01",
    "iso:country": "GB",
    "wof:name": "LD7 1TE",
    "wof:placetype": "postalcode"
  },
  "geometry": {"coordinates":[-3.113367,52.348705],"type":"Point"}
}
