{
  "type": "Feature",
  "properties": {
    "iso:country": "GB",
    "wof:name": "OX10 0JA",
    "wof:placetype": "postalcode"
  },
  "geometry": {"coordinates":[-1.130514,51.600886],"type":"Point"}
}
