{
  "type": "Feature",
  "properties": {
    "date:inception_lower": "2023-12-01",
    "date:inception_upper": "2023-12-01",
    "iso:country": "GB",
    "wof:name": "NE67 5FA",
    "wof:placetype": "postalcode"
  },
  "geometry": {"coordinates":[-1.63322,55.554163],"type":"Point"}
}
