{
  "type": "Feature",
  "properties": {
    "date:inception_lower": "2016-06-01",
    "date:inception_upper": "2016-06-01",
    "iso:country": "GB",
    "wof:name": "GL52 7ZE",
    "wof:placetype": "postalcode"
  },
  "geometry": {"coordinates":[-2.0712,51.951784],"type":"Point"}
}
