{
  "type": "Feature",
  "properties": {
    "iso:country": "GB",
    "wof:name": "B92 0BD",
    "wof:placetype": "postalcode"
  },
  "geometry": {"coordinates":[-1.69889,52.426287],"type":"Point"}
}
