{
  "type": "Feature",
  "properties": {
    "iso:country":"GB",
    "wof:name":"B92 0BD",
    "wof:placetype":"postalcode"
},
  "geometry": {"coordinates":[-1.69889035068914,52.42628686220801],"type":"Point"}
}