{
  "type": "Feature",
  "properties": {
    "iso:country":"GB",
    "wof:name":"LS11 5SX",
    "wof:placetype":"postalcode"
},
  "geometry": {"coordinates":[-1.54521073064999,53.77233526412336],"type":"Point"}
}