{
  "type": "Feature",
  "properties": {
    "iso:country":"GB",
    "wof:name":"L2 0RG",
    "wof:placetype":"postalcode"
},
  "geometry": {"coordinates":[-2.99389398760646,53.40587872819138],"type":"Point"}
}