{
  "type": "Feature",
  "properties": {
    "date:inception_lower":"1980-01-01",
    "date:inception_upper":"1980-01-31",
    "iso:country":"GB",
    "wof:name":"L2 0RG",
    "wof:placetype":"postalcode"
},
  "geometry": {"coordinates":[-2.993894,53.405879],"type":"Point"}
}