{
  "type": "Feature",
  "properties": {
    "date:inception_lower": "2017-08-01",
    "date:inception_upper": "2017-08-01",
    "iso:country": "GB",
    "wof:name": "GU11 4AR",
    "wof:placetype": "postalcode"
  },
  "geometry": {"coordinates":[-0.760917,51.255445],"type":"Point"}
}
