{
  "type": "Feature",
  "properties": {
    "iso:country":"GB",
    "wof:name":"M24 0BG",
    "wof:placetype":"postalcode"
},
  "geometry": {"coordinates":[-2.19878552698756,53.54788668212671],"type":"Point"}
}