{
  "type": "Feature",
  "properties": {
    "date:inception_lower":"2013-07-01",
    "date:inception_upper":"2013-07-31",
    "iso:country":"GB",
    "wof:name":"M24 0BG",
    "wof:placetype":"postalcode"
},
  "geometry": {"coordinates":[-2.198785,53.547887],"type":"Point"}
}