{
  "type": "Feature",
  "properties": {
    "iso:country":"GB",
    "wof:name":"DT10 2RF",
    "wof:placetype":"postalcode"
},
  "geometry": {"coordinates":[-2.38055172852224,50.95903194996384],"type":"Point"}
}