{
  "type": "Feature",
  "properties": {
    "iso:country":"GB",
    "wof:name":"BD5 0SU",
    "wof:placetype":"postalcode"
},
  "geometry": {"coordinates":[-1.75760777924914,53.78362108119371],"type":"Point"}
}