{
  "type": "Feature",
  "properties": {
    "iso:country":"GB",
    "wof:name":"IP30 9TF",
    "wof:placetype":"postalcode"
},
  "geometry": {"coordinates":[0.86528367877691,52.20680377697262],"type":"Point"}
}