{
  "type": "Feature",
  "properties": {
    "iso:country": "GB",
    "wof:name": "IP30 9TF",
    "wof:placetype": "postalcode"
  },
  "geometry": {"coordinates":[0.865284,52.206804],"type":"Point"}
}
