{
  "type": "Feature",
  "properties": {
    "iso:country": "GB",
    "wof:name": "SR6 7BE",
    "wof:placetype": "postalcode"
  },
  "geometry": {"coordinates":[-1.370101,54.954782],"type":"Point"}
}
