{
  "type": "Feature",
  "properties": {
    "iso:country":"GB",
    "wof:name":"SR6 7BE",
    "wof:placetype":"postalcode"
},
  "geometry": {"coordinates":[-1.37010073817394,54.95478184355393],"type":"Point"}
}