{
  "type": "Feature",
  "properties": {
    "iso:country": "GB",
    "wof:name": "L25 5LS",
    "wof:placetype": "postalcode"
  },
  "geometry": {"coordinates":[-2.856733,53.377234],"type":"Point"}
}
