{
  "type": "Feature",
  "properties": {
    "iso:country":"GB",
    "wof:name":"L25 5LS",
    "wof:placetype":"postalcode"
},
  "geometry": {"coordinates":[-2.85673347410528,53.37723369396019],"type":"Point"}
}