{
  "type": "Feature",
  "properties": {
    "iso:country":"GB",
    "wof:name":"CF72 8JY",
    "wof:placetype":"postalcode"
},
  "geometry": {"coordinates":[-3.38029564798023,51.49104032213062],"type":"Point"}
}