{
  "type": "Feature",
  "properties": {
    "iso:country": "GB",
    "wof:name": "CF72 8JY",
    "wof:placetype": "postalcode"
  },
  "geometry": {"coordinates":[-3.380296,51.49104],"type":"Point"}
}
