{
  "type": "Feature",
  "properties": {
    "date:inception_lower": "2000-06-01",
    "date:inception_upper": "2000-06-01",
    "iso:country": "GB",
    "wof:name": "OX16 4SQ",
    "wof:placetype": "postalcode"
  },
  "geometry": {"coordinates":[-1.324013,52.062683],"type":"Point"}
}
