{
  "type": "Feature",
  "properties": {
    "iso:country":"GB",
    "wof:name":"OX16 4SQ",
    "wof:placetype":"postalcode"
},
  "geometry": {"coordinates":[-1.32401285621276,52.06268349434023],"type":"Point"}
}