{
  "type": "Feature",
  "properties": {
    "iso:country":"GB",
    "wof:name":"SO24 0BB",
    "wof:placetype":"postalcode"
},
  "geometry": {"coordinates":[-1.09664083824065,51.06903458704182],"type":"Point"}
}