{
  "type": "Feature",
  "properties": {
    "iso:country":"GB",
    "wof:name":"CW8 2TT",
    "wof:placetype":"postalcode"
},
  "geometry": {"coordinates":[-2.61314210672438,53.25289919498852],"type":"Point"}
}