{
  "type": "Feature",
  "properties": {
    "iso:country": "GB",
    "wof:name": "CW8 2TT",
    "wof:placetype": "postalcode"
  },
  "geometry": {"coordinates":[-2.613142,53.252899],"type":"Point"}
}
