{
  "type": "Feature",
  "properties": {
    "iso:country":"GB",
    "wof:name":"DD2 2BP",
    "wof:placetype":"postalcode"
},
  "geometry": {"coordinates":[-2.99813123527701,56.46419521922994],"type":"Point"}
}