{
  "type": "Feature",
  "properties": {
    "date:inception_lower": "1980-01-01",
    "date:inception_upper": "1980-01-01",
    "iso:country": "GB",
    "wof:name": "DD2 2BP",
    "wof:placetype": "postalcode"
  },
  "geometry": {"coordinates":[-2.998131,56.464195],"type":"Point"}
}
