{
  "type": "Feature",
  "properties": {
    "iso:country": "GB",
    "wof:name": "BN17 5DD",
    "wof:placetype": "postalcode"
  },
  "geometry": {"coordinates":[-0.550486,50.81099],"type":"Point"}
}
