{
  "type": "Feature",
  "properties": {
    "iso:country":"GB",
    "wof:name":"BN17 5DD",
    "wof:placetype":"postalcode"
},
  "geometry": {"coordinates":[-0.54999480718933,50.81065157969554],"type":"Point"}
}