{
  "type": "Feature",
  "properties": {
    "iso:country":"GB",
    "wof:name":"SS12 0QQ",
    "wof:placetype":"postalcode"
},
  "geometry": {"coordinates":[0.52003375522926,51.61000296019398],"type":"Point"}
}