{
  "type": "Feature",
  "properties": {
    "iso:country":"GB",
    "wof:name":"SW6 4RA",
    "wof:placetype":"postalcode"
},
  "geometry": {"coordinates":[-0.20522139555352,51.47147058187305],"type":"Point"}
}