{
  "type": "Feature",
  "properties": {
    "iso:country":"GB",
    "wof:name":"DN32 9LT",
    "wof:placetype":"postalcode"
},
  "geometry": {"coordinates":[-0.07566870296794,53.55788733845579],"type":"Point"}
}