{
  "type": "Feature",
  "properties": {
    "iso:country":"GB",
    "wof:name":"DN14 8DX",
    "wof:placetype":"postalcode"
},
  "geometry": {"coordinates":[-0.82632082754242,53.64794124366411],"type":"Point"}
}