{
  "type": "Feature",
  "properties": {
    "iso:country":"GB",
    "wof:name":"OL2 6HQ",
    "wof:placetype":"postalcode"
},
  "geometry": {"coordinates":[-2.10459035711651,53.55803732759232],"type":"Point"}
}