{
  "type": "Feature",
  "properties": {
    "iso:country":"GB",
    "wof:name":"TR12 6DD",
    "wof:placetype":"postalcode"
},
  "geometry": {"coordinates":[-5.17860323723241,50.08190323216262],"type":"Point"}
}