{
  "type": "Feature",
  "properties": {
    "date:inception_lower":"1980-01-01",
    "date:inception_upper":"1980-01-31",
    "iso:country":"GB",
    "wof:name":"TR12 6DD",
    "wof:placetype":"postalcode"
},
  "geometry": {"coordinates":[-5.178654,50.081891],"type":"Point"}
}