{
  "type": "Feature",
  "properties": {
    "iso:country":"GB",
    "wof:name":"NE25 0QU",
    "wof:placetype":"postalcode"
},
  "geometry": {"coordinates":[-1.5383192593957,55.07879160522418],"type":"Point"}
}