{
  "type": "Feature",
  "properties": {
    "date:inception_lower":"2015-11-01",
    "date:inception_upper":"2015-11-30",
    "iso:country":"GB",
    "wof:name":"NE25 0QU",
    "wof:placetype":"postalcode"
},
  "geometry": {"coordinates":[-1.537703,55.079182],"type":"Point"}
}