{
  "type": "Feature",
  "properties": {
    "iso:country":"GB",
    "wof:name":"LE13 0PD",
    "wof:placetype":"postalcode"
},
  "geometry": {"coordinates":[-0.89499925958266,52.7732781062023],"type":"Point"}
}