{
  "type": "Feature",
  "properties": {
    "iso:country":"GB",
    "wof:name":"SN3 2GS",
    "wof:placetype":"postalcode"
},
  "geometry": {"coordinates":[-1.74067633647881,51.5597156672868],"type":"Point"}
}