{
  "type": "Feature",
  "properties": {
    "iso:country": "GB",
    "wof:name": "SN3 2GS",
    "wof:placetype": "postalcode"
  },
  "geometry": {"coordinates":[-1.740676,51.559716],"type":"Point"}
}
