{
  "type": "Feature",
  "properties": {
    "date:inception_lower": "1980-01-01",
    "date:inception_upper": "1980-01-01",
    "iso:country": "GB",
    "wof:name": "SE16 4NU",
    "wof:placetype": "postalcode"
  },
  "geometry": {"coordinates":[-0.05932,51.498894],"type":"Point"}
}
