{
  "type": "Feature",
  "properties": {
    "iso:country": "GB",
    "wof:name": "SE16 4NU",
    "wof:placetype": "postalcode"
  },
  "geometry": {"coordinates":[-0.05932,51.498894],"type":"Point"}
}
