{
  "type": "Feature",
  "properties": {
    "iso:country":"GB",
    "wof:name":"SE16 4NU",
    "wof:placetype":"postalcode"
},
  "geometry": {"coordinates":[-0.05931990329515,51.49889404605793],"type":"Point"}
}