{
  "type": "Feature",
  "properties": {
    "date:inception_lower":"1980-01-01",
    "date:inception_upper":"1980-01-31",
    "iso:country":"GB",
    "wof:name":"EH20 9NU",
    "wof:placetype":"postalcode"
},
  "geometry": {"coordinates":[-3.178396,55.88389],"type":"Point"}
}