{
  "type": "Feature",
  "properties": {
    "iso:country":"GB",
    "wof:name":"DN11 9AX",
    "wof:placetype":"postalcode"
},
  "geometry": {"coordinates":[-1.14128921312755,53.46712040410709],"type":"Point"}
}