{
  "type": "Feature",
  "properties": {
    "date:inception_lower": "1980-01-01",
    "date:inception_upper": "1980-01-01",
    "iso:country": "GB",
    "wof:name": "DN11 9AX",
    "wof:placetype": "postalcode"
  },
  "geometry": {"coordinates":[-1.141289,53.46712],"type":"Point"}
}
