{
  "type": "Feature",
  "properties": {
    "iso:country":"GB",
    "wof:name":"DH5 0HH",
    "wof:placetype":"postalcode"
},
  "geometry": {"coordinates":[-1.44225856571172,54.81130558114501],"type":"Point"}
}