{
  "type": "Feature",
  "properties": {
    "date:inception_lower":"1980-01-01",
    "date:inception_upper":"1980-01-31",
    "iso:country":"GB",
    "wof:name":"DH5 0HH",
    "wof:placetype":"postalcode"
},
  "geometry": {"coordinates":[-1.442259,54.811306],"type":"Point"}
}