{
  "type": "Feature",
  "properties": {
    "date:inception_lower": "1980-01-01",
    "date:inception_upper": "1980-01-01",
    "iso:country": "GB",
    "wof:name": "TA5 2RB",
    "wof:placetype": "postalcode"
  },
  "geometry": {"coordinates":[-3.061498,51.177827],"type":"Point"}
}
