{
  "type": "Feature",
  "properties": {
    "iso:country": "GB",
    "wof:name": "TA5 2RB",
    "wof:placetype": "postalcode"
  },
  "geometry": {"coordinates":[-3.06077,51.177249],"type":"Point"}
}
