{
  "type": "Feature",
  "properties": {
    "iso:country":"GB",
    "wof:name":"SA72 6LG",
    "wof:placetype":"postalcode"
},
  "geometry": {"coordinates":[-4.93386522073383,51.69011266316107],"type":"Point"}
}