{
  "type": "Feature",
  "properties": {
    "date:inception_lower": "1980-01-01",
    "date:inception_upper": "1980-01-01",
    "iso:country": "GB",
    "wof:name": "SA72 6LG",
    "wof:placetype": "postalcode"
  },
  "geometry": {"coordinates":[-4.933865,51.690113],"type":"Point"}
}
