{
  "type": "Feature",
  "properties": {
    "iso:country":"GB",
    "wof:name":"PH2 8BS",
    "wof:placetype":"postalcode"
},
  "geometry": {"coordinates":[-3.43253766478519,56.38605669313577],"type":"Point"}
}