{
  "type": "Feature",
  "properties": {
    "iso:country": "GB",
    "wof:name": "CF15 9NN",
    "wof:placetype": "postalcode"
  },
  "geometry": {"coordinates":[-3.328947,51.526783],"type":"Point"}
}
