{
  "type": "Feature",
  "properties": {
    "date:inception_lower": "1980-01-01",
    "date:inception_upper": "1980-01-01",
    "iso:country": "GB",
    "wof:name": "L31 0AB",
    "wof:placetype": "postalcode"
  },
  "geometry": {"coordinates":[-2.944409,53.516095],"type":"Point"}
}
