{
  "type": "Feature",
  "properties": {
    "iso:country": "GB",
    "wof:name": "L31 0AB",
    "wof:placetype": "postalcode"
  },
  "geometry": {"coordinates":[-2.944244,53.516044],"type":"Point"}
}
