{
  "type": "Feature",
  "properties": {
    "iso:country":"GB",
    "wof:name":"L31 0AB",
    "wof:placetype":"postalcode"
},
  "geometry": {"coordinates":[-2.94424397296594,53.51604423324398],"type":"Point"}
}