{
  "type": "Feature",
  "properties": {
    "iso:country":"GB",
    "wof:name":"LE17 5NN",
    "wof:placetype":"postalcode"
},
  "geometry": {"coordinates":[-1.16971545993757,52.51052114841361],"type":"Point"}
}