{
  "type": "Feature",
  "properties": {
    "iso:country":"GB",
    "wof:name":"BS11 9BT",
    "wof:placetype":"postalcode"
},
  "geometry": {"coordinates":[-2.70508811761535,51.51271722277142],"type":"Point"}
}