{
  "type": "Feature",
  "properties": {
    "iso:country":"GB",
    "wof:name":"WS2 9BT",
    "wof:placetype":"postalcode"
},
  "geometry": {"coordinates":[-1.98975802216328,52.58530521282577],"type":"Point"}
}