{
  "type": "Feature",
  "properties": {
    "date:inception_lower":"1999-12-01",
    "date:inception_upper":"1999-12-31",
    "iso:country":"GB",
    "wof:name":"B97 6TS",
    "wof:placetype":"postalcode"
},
  "geometry": {"coordinates":[-1.96679,52.312508],"type":"Point"}
}