{
  "type": "Feature",
  "properties": {
    "iso:country": "GB",
    "wof:name": "B97 6TS",
    "wof:placetype": "postalcode"
  },
  "geometry": {"coordinates":[-1.96679,52.312508],"type":"Point"}
}
