{
  "type": "Feature",
  "properties": {
    "iso:country":"GB",
    "wof:name":"B97 6TS",
    "wof:placetype":"postalcode"
},
  "geometry": {"coordinates":[-1.9667899933264,52.31250831405735],"type":"Point"}
}