{
  "type": "Feature",
  "properties": {
    "iso:country":"GB",
    "wof:name":"BH9 3PL",
    "wof:placetype":"postalcode"
},
  "geometry": {"coordinates":[-1.85499209485128,50.76082071275622],"type":"Point"}
}