{
  "type": "Feature",
  "properties": {
    "iso:country":"GB",
    "wof:name":"GL6 6UR",
    "wof:placetype":"postalcode"
},
  "geometry": {"coordinates":[-2.20036592530509,51.7872357525019],"type":"Point"}
}