{
  "type": "Feature",
  "properties": {
    "date:inception_lower": "1980-01-01",
    "date:inception_upper": "1980-01-01",
    "iso:country": "GB",
    "wof:name": "GL6 6UR",
    "wof:placetype": "postalcode"
  },
  "geometry": {"coordinates":[-2.200366,51.787236],"type":"Point"}
}
