{
  "type": "Feature",
  "properties": {
    "iso:country":"GB",
    "wof:name":"BD22 7BJ",
    "wof:placetype":"postalcode"
},
  "geometry": {"coordinates":[-1.91966658794356,53.85377385336808],"type":"Point"}
}