{
  "type": "Feature",
  "properties": {
    "iso:country": "GB",
    "wof:name": "BD22 7BJ",
    "wof:placetype": "postalcode"
  },
  "geometry": {"coordinates":[-1.919667,53.853774],"type":"Point"}
}
