{
  "type": "Feature",
  "properties": {
    "date:inception_lower":"1995-12-01",
    "date:inception_upper":"1995-12-31",
    "iso:country":"GB",
    "wof:name":"BH9 2BH",
    "wof:placetype":"postalcode"
},
  "geometry": {"coordinates":[-1.874291,50.75462],"type":"Point"}
}