{
  "type": "Feature",
  "properties": {
    "iso:country": "GB",
    "wof:name": "BH9 2BH",
    "wof:placetype": "postalcode"
  },
  "geometry": {"coordinates":[-1.874291,50.75462],"type":"Point"}
}
