{
  "type": "Feature",
  "properties": {
    "iso:country":"GB",
    "wof:name":"BH9 2BH",
    "wof:placetype":"postalcode"
},
  "geometry": {"coordinates":[-1.87429076320129,50.75462017461159],"type":"Point"}
}