{
  "type": "Feature",
  "properties": {
    "iso:country":"GB",
    "wof:name":"GL7 5XN",
    "wof:placetype":"postalcode"
},
  "geometry": {"coordinates":[-1.93050071851558,51.67005251779789],"type":"Point"}
}