{
  "type": "Feature",
  "properties": {
    "iso:country":"GB",
    "wof:name":"NE24 2BT",
    "wof:placetype":"postalcode"
},
  "geometry": {"coordinates":[-1.50566453827356,55.12683808878569],"type":"Point"}
}