{
  "type": "Feature",
  "properties": {
    "iso:country":"GB",
    "wof:name":"HU15 1QQ",
    "wof:placetype":"postalcode"
},
  "geometry": {"coordinates":[-0.5755355408647,53.75223363193852],"type":"Point"}
}