{
  "type": "Feature",
  "properties": {
    "iso:country":"GB",
    "wof:name":"AL3 7DQ",
    "wof:placetype":"postalcode"
},
  "geometry": {"coordinates":[-0.40552738782136,51.79597512085792],"type":"Point"}
}