{
  "type": "Feature",
  "properties": {
    "iso:country": "GB",
    "wof:name": "AL3 7DQ",
    "wof:placetype": "postalcode"
  },
  "geometry": {"coordinates":[-0.405465,51.795856],"type":"Point"}
}
