{
  "type": "Feature",
  "properties": {
    "iso:country": "GB",
    "wof:name": "NE5 2EP",
    "wof:placetype": "postalcode"
  },
  "geometry": {"coordinates":[-1.66893,54.980432],"type":"Point"}
}
