{
  "type": "Feature",
  "properties": {
    "iso:country":"GB",
    "wof:name":"NE5 2EP",
    "wof:placetype":"postalcode"
},
  "geometry": {"coordinates":[-1.6689301855977,54.98043151125606],"type":"Point"}
}