{
  "type": "Feature",
  "properties": {
    "date:inception_lower": "1980-01-01",
    "date:inception_upper": "1980-01-01",
    "iso:country": "GB",
    "wof:name": "DL1 2SF",
    "wof:placetype": "postalcode"
  },
  "geometry": {"coordinates":[-1.514676,54.541172],"type":"Point"}
}
