{
  "type": "Feature",
  "properties": {
    "iso:country":"GB",
    "wof:name":"DL6 1PH",
    "wof:placetype":"postalcode"
},
  "geometry": {"coordinates":[-1.43398726902699,54.33392625889459],"type":"Point"}
}