{
  "type": "Feature",
  "properties": {
    "date:inception_lower": "1980-01-01",
    "date:inception_upper": "1980-01-01",
    "iso:country": "GB",
    "wof:name": "HG4 4BP",
    "wof:placetype": "postalcode"
  },
  "geometry": {"coordinates":[-1.654814,54.232242],"type":"Point"}
}
