{
  "type": "Feature",
  "properties": {
    "iso:country":"GB",
    "wof:name":"CF11 6SD",
    "wof:placetype":"postalcode"
},
  "geometry": {"coordinates":[-3.18923195806939,51.47416096478698],"type":"Point"}
}