{
  "type": "Feature",
  "properties": {
    "iso:country": "GB",
    "wof:name": "CF11 6SD",
    "wof:placetype": "postalcode"
  },
  "geometry": {"coordinates":[-3.189232,51.474161],"type":"Point"}
}
