{
  "type": "Feature",
  "properties": {
    "iso:country":"GB",
    "wof:name":"SW2 2AZ",
    "wof:placetype":"postalcode"
},
  "geometry": {"coordinates":[-0.11916963076178,51.448467580092],"type":"Point"}
}