{
  "type": "Feature",
  "properties": {
    "date:inception_lower": "1980-01-01",
    "date:inception_upper": "1980-01-01",
    "iso:country": "GB",
    "wof:name": "S42 7EU",
    "wof:placetype": "postalcode"
  },
  "geometry": {"coordinates":[-1.498773,53.220553],"type":"Point"}
}
