{
  "type": "Feature",
  "properties": {
    "iso:country":"GB",
    "wof:name":"S42 7EU",
    "wof:placetype":"postalcode"
},
  "geometry": {"coordinates":[-1.4987740901161,53.22054327706789],"type":"Point"}
}