{
  "type": "Feature",
  "properties": {
    "date:inception_lower":"2005-04-01",
    "date:inception_upper":"2005-04-30",
    "iso:country":"GB",
    "wof:name":"NP25 3BQ",
    "wof:placetype":"postalcode"
},
  "geometry": {"coordinates":[-2.71448,51.812028],"type":"Point"}
}