{
  "type": "Feature",
  "properties": {
    "iso:country":"GB",
    "wof:name":"NP25 3BQ",
    "wof:placetype":"postalcode"
},
  "geometry": {"coordinates":[-2.71447988817469,51.81202817339667],"type":"Point"}
}