{
  "type": "Feature",
  "properties": {
    "iso:country":"GB",
    "wof:name":"NE61 1TW",
    "wof:placetype":"postalcode"
},
  "geometry": {"coordinates":[-1.6831219478543,55.16629268089704],"type":"Point"}
}