{
  "type": "Feature",
  "properties": {
    "date:inception_lower":"1995-12-01",
    "date:inception_upper":"1995-12-31",
    "iso:country":"GB",
    "wof:name":"SK6 3BL",
    "wof:placetype":"postalcode"
},
  "geometry": {"coordinates":[-2.099366,53.416213],"type":"Point"}
}