{
  "type": "Feature",
  "properties": {
    "iso:country":"GB",
    "wof:name":"HR9 5RG",
    "wof:placetype":"postalcode"
},
  "geometry": {"coordinates":[-2.58712442152517,51.87702818862947],"type":"Point"}
}