{
  "type": "Feature",
  "properties": {
    "iso:country": "GB",
    "wof:name": "HR9 5RG",
    "wof:placetype": "postalcode"
  },
  "geometry": {"coordinates":[-2.587126,51.877036],"type":"Point"}
}
