{
  "type": "Feature",
  "properties": {
    "date:inception_lower": "1980-01-01",
    "date:inception_upper": "1980-01-01",
    "iso:country": "GB",
    "wof:name": "HR9 5RG",
    "wof:placetype": "postalcode"
  },
  "geometry": {"coordinates":[-2.587126,51.877036],"type":"Point"}
}
