{
  "type": "Feature",
  "properties": {
    "iso:country":"GB",
    "wof:name":"LS18 5PH",
    "wof:placetype":"postalcode"
},
  "geometry": {"coordinates":[-1.63314287005034,53.84640981188068],"type":"Point"}
}