{
  "type": "Feature",
  "properties": {
    "date:inception_lower":"1980-01-01",
    "date:inception_upper":"1980-01-31",
    "iso:country":"GB",
    "wof:name":"LS18 5PH",
    "wof:placetype":"postalcode"
},
  "geometry": {"coordinates":[-1.633143,53.84641],"type":"Point"}
}