{
  "type": "Feature",
  "properties": {
    "iso:country": "GB",
    "wof:name": "CH8 8AP",
    "wof:placetype": "postalcode"
  },
  "geometry": {"coordinates":[-3.230462,53.261105],"type":"Point"}
}
