{
  "type": "Feature",
  "properties": {
    "iso:country":"GB",
    "wof:name":"CH8 8AP",
    "wof:placetype":"postalcode"
},
  "geometry": {"coordinates":[-3.2304616925597,53.26110520449905],"type":"Point"}
}