{
  "type": "Feature",
  "properties": {
    "iso:country":"GB",
    "wof:name":"B94 6AQ",
    "wof:placetype":"postalcode"
},
  "geometry": {"coordinates":[-1.83525033482652,52.36991756404866],"type":"Point"}
}