{
  "type": "Feature",
  "properties": {
    "date:inception_lower": "1980-01-01",
    "date:inception_upper": "1980-01-01",
    "iso:country": "GB",
    "wof:name": "B94 6AQ",
    "wof:placetype": "postalcode"
  },
  "geometry": {"coordinates":[-1.83525,52.369918],"type":"Point"}
}
