{
  "type": "Feature",
  "properties": {
    "iso:country": "GB",
    "wof:name": "L1 0AR",
    "wof:placetype": "postalcode"
  },
  "geometry": {"coordinates":[-2.981961,53.396565],"type":"Point"}
}
