{
  "type": "Feature",
  "properties": {
    "iso:country":"GB",
    "wof:name":"HD1 4TW",
    "wof:placetype":"postalcode"
},
  "geometry": {"coordinates":[-1.81000648665488,53.64019346068532],"type":"Point"}
}