{
  "type": "Feature",
  "properties": {
    "date:inception_lower": "2022-06-01",
    "date:inception_upper": "2022-06-01",
    "iso:country": "GB",
    "wof:name": "GU14 7TF",
    "wof:placetype": "postalcode"
  },
  "geometry": {"coordinates":[-0.754021,51.286846],"type":"Point"}
}
