{
  "type": "Feature",
  "properties": {
    "iso:country":"GB",
    "wof:name":"KT10 0BD",
    "wof:placetype":"postalcode"
},
  "geometry": {"coordinates":[-0.33220175610198,51.37628123122202],"type":"Point"}
}