{
  "type": "Feature",
  "properties": {
    "iso:country":"GB",
    "wof:name":"CF82 7AQ",
    "wof:placetype":"postalcode"
},
  "geometry": {"coordinates":[-3.23856429878818,51.64253505795926],"type":"Point"}
}