{
  "type": "Feature",
  "properties": {
    "date:inception_lower": "1999-06-01",
    "date:inception_upper": "1999-06-01",
    "iso:country": "GB",
    "wof:name": "CH61 4UF",
    "wof:placetype": "postalcode"
  },
  "geometry": {"coordinates":[-3.120698,53.35474],"type":"Point"}
}
