{
  "type": "Feature",
  "properties": {
    "iso:country": "GB",
    "wof:name": "CH61 4UF",
    "wof:placetype": "postalcode"
  },
  "geometry": {"coordinates":[-3.120698,53.35474],"type":"Point"}
}
