{
  "type": "Feature",
  "properties": {
    "iso:country":"GB",
    "wof:name":"TN13 2AH",
    "wof:placetype":"postalcode"
},
  "geometry": {"coordinates":[0.167605874399,51.28393284554323],"type":"Point"}
}