{
  "type": "Feature",
  "properties": {
    "iso:country":"GB",
    "wof:name":"LA14 5UG",
    "wof:placetype":"postalcode"
},
  "geometry": {"coordinates":[-3.23775203935024,54.12220509241744],"type":"Point"}
}