{
  "type": "Feature",
  "properties": {
    "iso:country": "GB",
    "wof:name": "SA11 2JB",
    "wof:placetype": "postalcode"
  },
  "geometry": {"coordinates":[-3.823137,51.632061],"type":"Point"}
}
