{
  "type": "Feature",
  "properties": {
    "iso:country":"GB",
    "wof:name":"SA11 2JB",
    "wof:placetype":"postalcode"
},
  "geometry": {"coordinates":[-3.82313685716962,51.63206095379392],"type":"Point"}
}