{
  "type": "Feature",
  "properties": {
    "iso:country":"GB",
    "wof:name":"DN20 8LP",
    "wof:placetype":"postalcode"
},
  "geometry": {"coordinates":[-0.49571437633529,53.55113425959189],"type":"Point"}
}