{
  "type": "Feature",
  "properties": {
    "iso:country":"GB",
    "wof:name":"W1W 6SQ",
    "wof:placetype":"postalcode"
},
  "geometry": {"coordinates":[-0.14087474880698,51.51958515686274],"type":"Point"}
}