{
  "type": "Feature",
  "properties": {
    "date:inception_lower": "2021-01-01",
    "date:inception_upper": "2021-01-01",
    "iso:country": "GB",
    "wof:name": "NG20 0EH",
    "wof:placetype": "postalcode"
  },
  "geometry": {"coordinates":[-1.165345,53.193174],"type":"Point"}
}
