{
  "type": "Feature",
  "properties": {
    "date:inception_lower": "1999-06-01",
    "date:inception_upper": "1999-06-01",
    "iso:country": "GB",
    "wof:name": "ME1 1BH",
    "wof:placetype": "postalcode"
  },
  "geometry": {"coordinates":[0.490655,51.379312],"type":"Point"}
}
