{
  "type": "Feature",
  "properties": {
    "iso:country":"GB",
    "wof:name":"NR21 7JR",
    "wof:placetype":"postalcode"
},
  "geometry": {"coordinates":[0.73991166207092,52.79310491399403],"type":"Point"}
}