{
  "type": "Feature",
  "properties": {
    "date:inception_lower": "1981-06-01",
    "date:inception_upper": "1981-06-01",
    "iso:country": "GB",
    "wof:name": "NR21 7JR",
    "wof:placetype": "postalcode"
  },
  "geometry": {"coordinates":[0.739912,52.793105],"type":"Point"}
}
