{
  "type": "Feature",
  "properties": {
    "iso:country":"GB",
    "wof:name":"B11 1QE",
    "wof:placetype":"postalcode"
},
  "geometry": {"coordinates":[-1.86223055903745,52.45995156200994],"type":"Point"}
}