{
  "type": "Feature",
  "properties": {
    "iso:country": "GB",
    "wof:name": "B11 1QE",
    "wof:placetype": "postalcode"
  },
  "geometry": {"coordinates":[-1.862231,52.459952],"type":"Point"}
}
