{
  "type": "Feature",
  "properties": {
    "iso:country": "GB",
    "wof:name": "B69 3EY",
    "wof:placetype": "postalcode"
  },
  "geometry": {"coordinates":[-2.025726,52.510103],"type":"Point"}
}
