{
  "type": "Feature",
  "properties": {
    "date:inception_lower":"1980-01-01",
    "date:inception_upper":"1980-01-31",
    "iso:country":"GB",
    "wof:name":"B69 3EY",
    "wof:placetype":"postalcode"
},
  "geometry": {"coordinates":[-2.025726,52.510103],"type":"Point"}
}