{
  "type": "Feature",
  "properties": {
    "iso:country": "GB",
    "wof:name": "DG8 9JE",
    "wof:placetype": "postalcode"
  },
  "geometry": {"coordinates":[-4.443975,54.869273],"type":"Point"}
}
