{
  "type": "Feature",
  "properties": {
    "date:inception_lower":"1980-01-01",
    "date:inception_upper":"1980-01-31",
    "iso:country":"GB",
    "wof:name":"DG8 9JE",
    "wof:placetype":"postalcode"
},
  "geometry": {"coordinates":[-4.443975,54.869273],"type":"Point"}
}