{
  "type": "Feature",
  "properties": {
    "iso:country":"GB",
    "wof:name":"WD3 5LX",
    "wof:placetype":"postalcode"
},
  "geometry": {"coordinates":[-0.51163599236695,51.66279465280186],"type":"Point"}
}