{
  "type": "Feature",
  "properties": {
    "iso:country": "GB",
    "wof:name": "WD3 5LX",
    "wof:placetype": "postalcode"
  },
  "geometry": {"coordinates":[-0.511636,51.662795],"type":"Point"}
}
