{
  "type": "Feature",
  "properties": {
    "date:inception_lower": "2000-12-01",
    "date:inception_upper": "2000-12-01",
    "iso:country": "GB",
    "wof:name": "YO31 8JH",
    "wof:placetype": "postalcode"
  },
  "geometry": {"coordinates":[-1.07393,53.970904],"type":"Point"}
}
