{
  "type": "Feature",
  "properties": {
    "iso:country":"GB",
    "wof:name":"TD7 4AR",
    "wof:placetype":"postalcode"
},
  "geometry": {"coordinates":[-2.83892842856912,55.54557578271691],"type":"Point"}
}