{
  "type": "Feature",
  "properties": {
    "iso:country":"GB",
    "wof:name":"G21 3NR",
    "wof:placetype":"postalcode"
},
  "geometry": {"coordinates":[-4.20980269744975,55.8904881466914],"type":"Point"}
}