{
  "type": "Feature",
  "properties": {
    "iso:country": "GB",
    "wof:name": "NG34 9RY",
    "wof:placetype": "postalcode"
  },
  "geometry": {"coordinates":[-0.299162,52.985932],"type":"Point"}
}
