{
  "type": "Feature",
  "properties": {
    "iso:country":"GB",
    "wof:name":"NG34 9RY",
    "wof:placetype":"postalcode"
},
  "geometry": {"coordinates":[-0.29916168131756,52.98593161692341],"type":"Point"}
}