{
  "type": "Feature",
  "properties": {
    "iso:country":"GB",
    "wof:name":"RG5 4NW",
    "wof:placetype":"postalcode"
},
  "geometry": {"coordinates":[-0.88809523287603,51.45212146087988],"type":"Point"}
}