{
  "type": "Feature",
  "properties": {
    "iso:country": "GB",
    "wof:name": "RG5 4NW",
    "wof:placetype": "postalcode"
  },
  "geometry": {"coordinates":[-0.888095,51.452121],"type":"Point"}
}
