{
  "type": "Feature",
  "properties": {
    "iso:country":"GB",
    "wof:name":"ST14 8QJ",
    "wof:placetype":"postalcode"
},
  "geometry": {"coordinates":[-1.90895248859373,52.86241984544695],"type":"Point"}
}