{
  "type": "Feature",
  "properties": {
    "iso:country": "GB",
    "wof:name": "ST14 8QJ",
    "wof:placetype": "postalcode"
  },
  "geometry": {"coordinates":[-1.909024,52.862365],"type":"Point"}
}
