{
  "type": "Feature",
  "properties": {
    "iso:country":"GB",
    "wof:name":"SA4 4YQ",
    "wof:placetype":"postalcode"
},
  "geometry": {"coordinates":[-4.0498322411243,51.67480305983631],"type":"Point"}
}