{
  "type": "Feature",
  "properties": {
    "iso:country": "GB",
    "wof:name": "PE12 9HB",
    "wof:placetype": "postalcode"
  },
  "geometry": {"coordinates":[0.118301,52.785244],"type":"Point"}
}
