{
  "type": "Feature",
  "properties": {
    "iso:country":"GB",
    "wof:name":"PE12 9HB",
    "wof:placetype":"postalcode"
},
  "geometry": {"coordinates":[0.11830094197935,52.78524436913143],"type":"Point"}
}