{
  "type": "Feature",
  "properties": {
    "iso:country":"GB",
    "wof:name":"MK16 0FL",
    "wof:placetype":"postalcode"
},
  "geometry": {"coordinates":[-0.72252112896799,52.08453822891087],"type":"Point"}
}