{
  "type": "Feature",
  "properties": {
    "iso:country": "GB",
    "wof:name": "MK16 0FL",
    "wof:placetype": "postalcode"
  },
  "geometry": {"coordinates":[-0.722521,52.084538],"type":"Point"}
}
