{
  "type": "Feature",
  "properties": {
    "date:inception_lower":"2014-08-01",
    "date:inception_upper":"2014-08-31",
    "iso:country":"GB",
    "wof:name":"MK16 0FL",
    "wof:placetype":"postalcode"
},
  "geometry": {"coordinates":[-0.722521,52.084538],"type":"Point"}
}