{
  "type": "Feature",
  "properties": {
    "iso:country":"GB",
    "wof:name":"B64 6PG",
    "wof:placetype":"postalcode"
},
  "geometry": {"coordinates":[-2.05457217632751,52.47159786524788],"type":"Point"}
}