{
  "type": "Feature",
  "properties": {
    "date:inception_lower":"2012-02-01",
    "date:inception_upper":"2012-02-29",
    "iso:country":"GB",
    "wof:name":"B64 6PG",
    "wof:placetype":"postalcode"
},
  "geometry": {"coordinates":[-2.054572,52.471598],"type":"Point"}
}