{
  "type": "Feature",
  "properties": {
    "iso:country":"GB",
    "wof:name":"EX16 8RP",
    "wof:placetype":"postalcode"
},
  "geometry": {"coordinates":[-3.51215296131996,50.85095435838117],"type":"Point"}
}