{
  "type": "Feature",
  "properties": {
    "iso:country":"GB",
    "wof:name":"CO14 8TB",
    "wof:placetype":"postalcode"
},
  "geometry": {"coordinates":[1.25073586707169,51.84876865391425],"type":"Point"}
}