{
  "type": "Feature",
  "properties": {
    "iso:country": "GB",
    "wof:name": "WR8 0LE",
    "wof:placetype": "postalcode"
  },
  "geometry": {"coordinates":[-2.216542,52.061292],"type":"Point"}
}
