{
  "type": "Feature",
  "properties": {
    "iso:country":"GB",
    "wof:name":"WR8 0LE",
    "wof:placetype":"postalcode"
},
  "geometry": {"coordinates":[-2.21654218702978,52.06129235700786],"type":"Point"}
}