{
  "type": "Feature",
  "properties": {
    "iso:country":"GB",
    "wof:name":"LS28 9BY",
    "wof:placetype":"postalcode"
},
  "geometry": {"coordinates":[-1.65052977073328,53.7972255724815],"type":"Point"}
}