{
  "type": "Feature",
  "properties": {
    "iso:country":"GB",
    "wof:name":"IP3 8EJ",
    "wof:placetype":"postalcode"
},
  "geometry": {"coordinates":[1.17264015628253,52.04978877817564],"type":"Point"}
}