{
  "type": "Feature",
  "properties": {
    "iso:country":"GB",
    "wof:name":"LN11 7DZ",
    "wof:placetype":"postalcode"
},
  "geometry": {"coordinates":[0.06719766903352,53.38564308305119],"type":"Point"}
}