{
  "type": "Feature",
  "properties": {
    "iso:country": "GB",
    "wof:name": "LN11 7DZ",
    "wof:placetype": "postalcode"
  },
  "geometry": {"coordinates":[0.067198,53.385643],"type":"Point"}
}
