{
  "type": "Feature",
  "properties": {
    "iso:country": "GB",
    "wof:name": "BH22 0LJ",
    "wof:placetype": "postalcode"
  },
  "geometry": {"coordinates":[-1.891577,50.831929],"type":"Point"}
}
