{
  "type": "Feature",
  "properties": {
    "iso:country":"GB",
    "wof:name":"BH22 0LJ",
    "wof:placetype":"postalcode"
},
  "geometry": {"coordinates":[-1.89157749866783,50.83192854590816],"type":"Point"}
}