{
  "type": "Feature",
  "properties": {
    "iso:country":"GB",
    "wof:name":"HP20 2AY",
    "wof:placetype":"postalcode"
},
  "geometry": {"coordinates":[-0.80602625517507,51.82717642554983],"type":"Point"}
}