{
  "type": "Feature",
  "properties": {
    "iso:country": "GB",
    "wof:name": "DL8 3JB",
    "wof:placetype": "postalcode"
  },
  "geometry": {"coordinates":[-2.073744,54.321138],"type":"Point"}
}
