{
  "type": "Feature",
  "properties": {
    "iso:country":"GB",
    "wof:name":"SL1 9JF",
    "wof:placetype":"postalcode"
},
  "geometry": {"coordinates":[-0.62439226561599,51.50673880620182],"type":"Point"}
}