{
  "type": "Feature",
  "properties": {
    "date:inception_lower":"1987-10-01",
    "date:inception_upper":"1987-10-31",
    "iso:country":"GB",
    "wof:name":"SL1 9JF",
    "wof:placetype":"postalcode"
},
  "geometry": {"coordinates":[-0.624392,51.506739],"type":"Point"}
}