{
  "type": "Feature",
  "properties": {
    "iso:country": "GB",
    "wof:name": "SL1 9JF",
    "wof:placetype": "postalcode"
  },
  "geometry": {"coordinates":[-0.624392,51.506739],"type":"Point"}
}
