{
  "type": "Feature",
  "properties": {
    "iso:country":"GB",
    "wof:name":"WA5 9UT",
    "wof:placetype":"postalcode"
},
  "geometry": {"coordinates":[-2.62317862895218,53.41007945140286],"type":"Point"}
}