{
  "type": "Feature",
  "properties": {
    "iso:country":"GB",
    "wof:name":"CO3 0LE",
    "wof:placetype":"postalcode"
},
  "geometry": {"coordinates":[0.84970762040269,51.8761006751539],"type":"Point"}
}