{
  "type": "Feature",
  "properties": {
    "iso:country": "GB",
    "wof:name": "NR21 8BE",
    "wof:placetype": "postalcode"
  },
  "geometry": {"coordinates":[0.855578,52.829348],"type":"Point"}
}
