{
  "type": "Feature",
  "properties": {
    "iso:country":"GB",
    "wof:name":"RH2 8EL",
    "wof:placetype":"postalcode"
},
  "geometry": {"coordinates":[-0.20327309229122,51.22045534948442],"type":"Point"}
}