{
  "type": "Feature",
  "properties": {
    "iso:country": "GB",
    "wof:name": "RH2 8EL",
    "wof:placetype": "postalcode"
  },
  "geometry": {"coordinates":[-0.203273,51.220455],"type":"Point"}
}
