{
  "type": "Feature",
  "properties": {
    "iso:country":"GB",
    "wof:name":"KA22 8JH",
    "wof:placetype":"postalcode"
},
  "geometry": {"coordinates":[-4.80856028794092,55.64527367052249],"type":"Point"}
}