{
  "type": "Feature",
  "properties": {
    "iso:country":"GB",
    "wof:name":"SW7 5PS",
    "wof:placetype":"postalcode"
},
  "geometry": {"coordinates":[-0.18069671154577,51.49833989133177],"type":"Point"}
}