{
  "type": "Feature",
  "properties": {
    "iso:country":"GB",
    "wof:name":"CT13 0AZ",
    "wof:placetype":"postalcode"
},
  "geometry": {"coordinates":[1.33125738065526,51.27113315642161],"type":"Point"}
}