{
  "type": "Feature",
  "properties": {
    "iso:country":"GB",
    "wof:name":"KT18 7DY",
    "wof:placetype":"postalcode"
},
  "geometry": {"coordinates":[-0.27545381308378,51.32059592398181],"type":"Point"}
}