{
  "type": "Feature",
  "properties": {
    "iso:country":"GB",
    "wof:name":"WN6 7PX",
    "wof:placetype":"postalcode"
},
  "geometry": {"coordinates":[-2.65094943409277,53.55868355689426],"type":"Point"}
}