{
  "type": "Feature",
  "properties": {
    "iso:country":"GB",
    "wof:name":"PL26 7DX",
    "wof:placetype":"postalcode"
},
  "geometry": {"coordinates":[-4.8261024334461,50.32347028735047],"type":"Point"}
}