{
  "type": "Feature",
  "properties": {
    "date:inception_lower":"1980-01-01",
    "date:inception_upper":"1980-01-31",
    "iso:country":"GB",
    "wof:name":"PL26 7DX",
    "wof:placetype":"postalcode"
},
  "geometry": {"coordinates":[-4.826402,50.32328],"type":"Point"}
}