{
  "type": "Feature",
  "properties": {
    "iso:country": "GB",
    "wof:name": "NR30 2PR",
    "wof:placetype": "postalcode"
  },
  "geometry": {"coordinates":[1.729348,52.601943],"type":"Point"}
}
