{
  "type": "Feature",
  "properties": {
    "iso:country": "GB",
    "wof:name": "NR30 2PR",
    "wof:placetype": "postalcode"
  },
  "geometry": {"coordinates":[1.729312,52.601872],"type":"Point"}
}
