{
  "type": "Feature",
  "properties": {
    "iso:country": "GB",
    "wof:name": "EH17 7PR",
    "wof:placetype": "postalcode"
  },
  "geometry": {"coordinates":[-3.151786,55.916535],"type":"Point"}
}
