{
  "type": "Feature",
  "properties": {
    "date:inception_lower": "2019-02-01",
    "date:inception_upper": "2019-02-01",
    "iso:country": "GB",
    "wof:name": "TW7 6XW",
    "wof:placetype": "postalcode"
  },
  "geometry": {"coordinates":[-0.323648,51.468575],"type":"Point"}
}
