{
  "type": "Feature",
  "properties": {
    "iso:country": "GB",
    "wof:name": "KT24 5DG",
    "wof:placetype": "postalcode"
  },
  "geometry": {"coordinates":[-0.429453,51.277404],"type":"Point"}
}
