{
  "type": "Feature",
  "properties": {
    "iso:country":"GB",
    "wof:name":"G41 1BB",
    "wof:placetype":"postalcode"
},
  "geometry": {"coordinates":[-4.28083236578362,55.85160643767335],"type":"Point"}
}