{
  "type": "Feature",
  "properties": {
    "iso:country": "GB",
    "wof:name": "G41 1BB",
    "wof:placetype": "postalcode"
  },
  "geometry": {"coordinates":[-4.278429,55.852005],"type":"Point"}
}
