{
  "type": "Feature",
  "properties": {
    "iso:country":"GB",
    "wof:name":"TR19 6AE",
    "wof:placetype":"postalcode"
},
  "geometry": {"coordinates":[-5.584807171297,50.10060004748203],"type":"Point"}
}