{
  "type": "Feature",
  "properties": {
    "iso:country":"GB",
    "wof:name":"TN25 4JX",
    "wof:placetype":"postalcode"
},
  "geometry": {"coordinates":[0.84738339379306,51.19103629486296],"type":"Point"}
}