{
  "type": "Feature",
  "properties": {
    "iso:country":"GB",
    "wof:name":"CV8 3BY",
    "wof:placetype":"postalcode"
},
  "geometry": {"coordinates":[-1.51302430773096,52.35220019546936],"type":"Point"}
}