{
  "type": "Feature",
  "properties": {
    "iso:country": "GB",
    "wof:name": "CV8 3BY",
    "wof:placetype": "postalcode"
  },
  "geometry": {"coordinates":[-1.513014,52.352217],"type":"Point"}
}
