{
  "type": "Feature",
  "properties": {
    "iso:country":"GB",
    "wof:name":"CF44 0HT",
    "wof:placetype":"postalcode"
},
  "geometry": {"coordinates":[-3.4191744263874,51.71149903959031],"type":"Point"}
}