{
  "type": "Feature",
  "properties": {
    "iso:country": "GB",
    "wof:name": "CF44 0HT",
    "wof:placetype": "postalcode"
  },
  "geometry": {"coordinates":[-3.419174,51.711499],"type":"Point"}
}
