{
  "type": "Feature",
  "properties": {
    "iso:country": "GB",
    "wof:name": "L36 1TZ",
    "wof:placetype": "postalcode"
  },
  "geometry": {"coordinates":[-2.820394,53.418334],"type":"Point"}
}
