{
  "type": "Feature",
  "properties": {
    "iso:country":"GB",
    "wof:name":"L36 1TZ",
    "wof:placetype":"postalcode"
},
  "geometry": {"coordinates":[-2.82039434337565,53.41833426134371],"type":"Point"}
}