{
  "type": "Feature",
  "properties": {
    "iso:country": "GB",
    "wof:name": "YO8 3UH",
    "wof:placetype": "postalcode"
  },
  "geometry": {"coordinates":[-1.133063,53.830178],"type":"Point"}
}
