{
  "type": "Feature",
  "properties": {
    "iso:country":"GB",
    "wof:name":"YO8 3UH",
    "wof:placetype":"postalcode"
},
  "geometry": {"coordinates":[-1.1330626148139,53.83017785708341],"type":"Point"}
}