{
  "type": "Feature",
  "properties": {
    "iso:country":"GB",
    "wof:name":"M46 0EJ",
    "wof:placetype":"postalcode"
},
  "geometry": {"coordinates":[-2.49590642953255,53.52469583010122],"type":"Point"}
}