{
  "type": "Feature",
  "properties": {
    "date:inception_lower": "2011-05-01",
    "date:inception_upper": "2011-05-01",
    "iso:country": "GB",
    "wof:name": "M46 0EJ",
    "wof:placetype": "postalcode"
  },
  "geometry": {"coordinates":[-2.495906,53.524696],"type":"Point"}
}
