{
  "type": "Feature",
  "properties": {
    "iso:country":"GB",
    "wof:name":"HU5 4AX",
    "wof:placetype":"postalcode"
},
  "geometry": {"coordinates":[-0.37331503364721,53.76912126342348],"type":"Point"}
}