{
  "type": "Feature",
  "properties": {
    "iso:country":"GB",
    "wof:name":"UB4 0JW",
    "wof:placetype":"postalcode"
},
  "geometry": {"coordinates":[-0.39360902656104,51.51500964435545],"type":"Point"}
}