{
  "type": "Feature",
  "properties": {
    "date:inception_lower": "1980-01-01",
    "date:inception_upper": "1980-01-01",
    "iso:country": "GB",
    "wof:name": "UB4 0JW",
    "wof:placetype": "postalcode"
  },
  "geometry": {"coordinates":[-0.393609,51.51501],"type":"Point"}
}
