{
  "type": "Feature",
  "properties": {
    "iso:country":"GB",
    "wof:name":"DE7 6GE",
    "wof:placetype":"postalcode"
},
  "geometry": {"coordinates":[-1.38457188778331,52.97572813561242],"type":"Point"}
}