{
  "type": "Feature",
  "properties": {
    "iso:country":"GB",
    "wof:name":"NG17 3BL",
    "wof:placetype":"postalcode"
},
  "geometry": {"coordinates":[-1.25412783061575,53.13919790712984],"type":"Point"}
}