{
  "type": "Feature",
  "properties": {
    "iso:country":"GB",
    "wof:name":"B19 3JG",
    "wof:placetype":"postalcode"
},
  "geometry": {"coordinates":[-1.90481618686,52.49037949126541],"type":"Point"}
}