{
  "type": "Feature",
  "properties": {
    "iso:country":"GB",
    "wof:name":"NN3 6JG",
    "wof:placetype":"postalcode"
},
  "geometry": {"coordinates":[-0.8533226771907,52.27027662887173],"type":"Point"}
}