{
  "type": "Feature",
  "properties": {
    "iso:country":"GB",
    "wof:name":"M45 7WP",
    "wof:placetype":"postalcode"
},
  "geometry": {"coordinates":[-2.30631281902203,53.55353778851232],"type":"Point"}
}