{
  "type": "Feature",
  "properties": {
    "iso:country":"GB",
    "wof:name":"HP4 3RH",
    "wof:placetype":"postalcode"
},
  "geometry": {"coordinates":[-0.59256665839258,51.76942746732058],"type":"Point"}
}