{
  "type": "Feature",
  "properties": {
    "iso:country": "GB",
    "wof:name": "YO17 8QJ",
    "wof:placetype": "postalcode"
  },
  "geometry": {"coordinates":[-0.531456,54.162607],"type":"Point"}
}
