{
  "type": "Feature",
  "properties": {
    "iso:country":"GB",
    "wof:name":"YO17 8QJ",
    "wof:placetype":"postalcode"
},
  "geometry": {"coordinates":[-0.53144314005393,54.16258939179846],"type":"Point"}
}