{
  "type": "Feature",
  "properties": {
    "date:inception_lower":"1980-01-01",
    "date:inception_upper":"1980-01-31",
    "iso:country":"GB",
    "wof:name":"YO17 8QJ",
    "wof:placetype":"postalcode"
},
  "geometry": {"coordinates":[-0.531456,54.162607],"type":"Point"}
}