{
  "type": "Feature",
  "properties": {
    "iso:country":"GB",
    "wof:name":"S75 3EH",
    "wof:placetype":"postalcode"
},
  "geometry": {"coordinates":[-1.50992340553281,53.53177797490192],"type":"Point"}
}