{
  "type": "Feature",
  "properties": {
    "iso:country":"GB",
    "wof:name":"DG2 0YA",
    "wof:placetype":"postalcode"
},
  "geometry": {"coordinates":[-3.6379219549297,55.154699797285],"type":"Point"}
}