{
  "type": "Feature",
  "properties": {
    "iso:country": "GB",
    "wof:name": "HP12 3QQ",
    "wof:placetype": "postalcode"
  },
  "geometry": {"coordinates":[-0.772286,51.631082],"type":"Point"}
}
