{
  "type": "Feature",
  "properties": {
    "iso:country":"GB",
    "wof:name":"BD20 0EE",
    "wof:placetype":"postalcode"
},
  "geometry": {"coordinates":[-1.93683922730492,53.90816945079639],"type":"Point"}
}