{
  "type": "Feature",
  "properties": {
    "iso:country": "GB",
    "wof:name": "BD20 0EE",
    "wof:placetype": "postalcode"
  },
  "geometry": {"coordinates":[-1.936839,53.908169],"type":"Point"}
}
