{
  "type": "Feature",
  "properties": {
    "iso:country":"GB",
    "wof:name":"ST14 8RQ",
    "wof:placetype":"postalcode"
},
  "geometry": {"coordinates":[-1.88078361020721,52.8541786724122],"type":"Point"}
}