{
  "type": "Feature",
  "properties": {
    "date:inception_lower": "1980-01-01",
    "date:inception_upper": "1980-01-01",
    "iso:country": "GB",
    "wof:name": "ST14 8RQ",
    "wof:placetype": "postalcode"
  },
  "geometry": {"coordinates":[-1.880765,52.854223],"type":"Point"}
}
