{
  "type": "Feature",
  "properties": {
    "iso:country": "GB",
    "wof:name": "HG3 3LF",
    "wof:placetype": "postalcode"
  },
  "geometry": {"coordinates":[-1.638443,54.079568],"type":"Point"}
}
