{
  "type": "Feature",
  "properties": {
    "date:inception_lower": "1980-01-01",
    "date:inception_upper": "1980-01-01",
    "iso:country": "GB",
    "wof:name": "MK42 9SB",
    "wof:placetype": "postalcode"
  },
  "geometry": {"coordinates":[-0.461551,52.121945],"type":"Point"}
}
