{
  "type": "Feature",
  "properties": {
    "date:inception_lower": "1980-01-01",
    "date:inception_upper": "1980-01-01",
    "iso:country": "GB",
    "wof:name": "TN15 6XX",
    "wof:placetype": "postalcode"
  },
  "geometry": {"coordinates":[0.247486,51.331548],"type":"Point"}
}
