{
  "type": "Feature",
  "properties": {
    "date:inception_lower": "1980-01-01",
    "date:inception_upper": "1980-01-01",
    "iso:country": "GB",
    "wof:name": "CV2 3DU",
    "wof:placetype": "postalcode"
  },
  "geometry": {"coordinates":[-1.466784,52.416299],"type":"Point"}
}
