{
  "type": "Feature",
  "properties": {
    "iso:country": "GB",
    "wof:name": "TD5 7BN",
    "wof:placetype": "postalcode"
  },
  "geometry": {"coordinates":[-2.427444,55.598335],"type":"Point"}
}
