{
  "type": "Feature",
  "properties": {
    "iso:country": "GB",
    "wof:name": "WD19 4GY",
    "wof:placetype": "postalcode"
  },
  "geometry": {"coordinates":[-0.377562,51.642432],"type":"Point"}
}
