{
  "type": "Feature",
  "properties": {
    "date:inception_lower": "2002-06-01",
    "date:inception_upper": "2002-06-01",
    "iso:country": "GB",
    "wof:name": "GU8 4GH",
    "wof:placetype": "postalcode"
  },
  "geometry": {"coordinates":[-0.632437,51.113203],"type":"Point"}
}
