{
  "type": "Feature",
  "properties": {
    "iso:country":"GB",
    "wof:name":"DY4 9QL",
    "wof:placetype":"postalcode"
},
  "geometry": {"coordinates":[-2.06479810309022,52.53780345572178],"type":"Point"}
}