{
  "type": "Feature",
  "properties": {
    "date:inception_lower": "1980-01-01",
    "date:inception_upper": "1980-01-01",
    "iso:country": "GB",
    "wof:name": "NE9 7AF",
    "wof:placetype": "postalcode"
  },
  "geometry": {"coordinates":[-1.58646,54.92291],"type":"Point"}
}
