{
  "type": "Feature",
  "properties": {
    "iso:country":"GB",
    "wof:name":"L23 5RG",
    "wof:placetype":"postalcode"
},
  "geometry": {"coordinates":[-3.03054510638168,53.48828388691965],"type":"Point"}
}