{
  "type": "Feature",
  "properties": {
    "iso:country": "GB",
    "wof:name": "L23 5RG",
    "wof:placetype": "postalcode"
  },
  "geometry": {"coordinates":[-3.030557,53.488273],"type":"Point"}
}
