{
  "type": "Feature",
  "properties": {
    "date:inception_lower": "1980-01-01",
    "date:inception_upper": "1980-01-01",
    "iso:country": "GB",
    "wof:name": "YO22 5JB",
    "wof:placetype": "postalcode"
  },
  "geometry": {"coordinates":[-0.633675,54.433349],"type":"Point"}
}
