{
  "type": "Feature",
  "properties": {
    "iso:country": "GB",
    "wof:name": "YO22 5JB",
    "wof:placetype": "postalcode"
  },
  "geometry": {"coordinates":[-0.633565,54.429258],"type":"Point"}
}
