{
  "type": "Feature",
  "properties": {
    "iso:country":"GB",
    "wof:name":"PR1 3JE",
    "wof:placetype":"postalcode"
},
  "geometry": {"coordinates":[-2.70441557964146,53.75345514385744],"type":"Point"}
}