{
  "type": "Feature",
  "properties": {
    "iso:country": "GB",
    "wof:name": "PR1 3JE",
    "wof:placetype": "postalcode"
  },
  "geometry": {"coordinates":[-2.70342,53.753989],"type":"Point"}
}
