{
  "type": "Feature",
  "properties": {
    "iso:country":"GB",
    "wof:name":"G78 1DD",
    "wof:placetype":"postalcode"
},
  "geometry": {"coordinates":[-4.38275368316851,55.80779994502967],"type":"Point"}
}