{
  "type": "Feature",
  "properties": {
    "iso:country":"GB",
    "wof:name":"CA2 5PW",
    "wof:placetype":"postalcode"
},
  "geometry": {"coordinates":[-2.94859211829529,54.88787093711477],"type":"Point"}
}