{
  "type": "Feature",
  "properties": {
    "date:inception_lower": "1980-01-01",
    "date:inception_upper": "1980-01-01",
    "iso:country": "GB",
    "wof:name": "CA2 5PW",
    "wof:placetype": "postalcode"
  },
  "geometry": {"coordinates":[-2.948592,54.887871],"type":"Point"}
}
