{
  "type": "Feature",
  "properties": {
    "iso:country":"GB",
    "wof:name":"TF2 8SU",
    "wof:placetype":"postalcode"
},
  "geometry": {"coordinates":[-2.41828453781054,52.71557383793105],"type":"Point"}
}