{
  "type": "Feature",
  "properties": {
    "iso:country":"GB",
    "wof:name":"SE3 7JY",
    "wof:placetype":"postalcode"
},
  "geometry": {"coordinates":[0.02060401584473,51.47520617961121],"type":"Point"}
}