{
  "type": "Feature",
  "properties": {
    "date:inception_lower": "1990-07-01",
    "date:inception_upper": "1990-07-01",
    "iso:country": "GB",
    "wof:name": "BA21 3TF",
    "wof:placetype": "postalcode"
  },
  "geometry": {"coordinates":[-2.668943,50.94966],"type":"Point"}
}
