{
  "type": "Feature",
  "properties": {
    "iso:country":"GB",
    "wof:name":"BA21 3TF",
    "wof:placetype":"postalcode"
},
  "geometry": {"coordinates":[-2.66894324883269,50.94966043857691],"type":"Point"}
}