{
  "type": "Feature",
  "properties": {
    "iso:country":"GB",
    "wof:name":"PL3 5RR",
    "wof:placetype":"postalcode"
},
  "geometry": {"coordinates":[-4.13393527529599,50.398424410407],"type":"Point"}
}