{
  "type": "Feature",
  "properties": {
    "iso:country": "GB",
    "wof:name": "PL3 5RR",
    "wof:placetype": "postalcode"
  },
  "geometry": {"coordinates":[-4.133935,50.398424],"type":"Point"}
}
