{
  "type": "Feature",
  "properties": {
    "iso:country":"GB",
    "wof:name":"LA8 8EQ",
    "wof:placetype":"postalcode"
},
  "geometry": {"coordinates":[-2.7964102937483,54.2550157351311],"type":"Point"}
}