{
  "type": "Feature",
  "properties": {
    "date:inception_lower": "1980-01-01",
    "date:inception_upper": "1980-01-01",
    "iso:country": "GB",
    "wof:name": "LA8 8EQ",
    "wof:placetype": "postalcode"
  },
  "geometry": {"coordinates":[-2.79641,54.255016],"type":"Point"}
}
