{
  "type": "Feature",
  "properties": {
    "iso:country": "GB",
    "wof:name": "LA8 8EQ",
    "wof:placetype": "postalcode"
  },
  "geometry": {"coordinates":[-2.79641,54.255016],"type":"Point"}
}
