{
  "type": "Feature",
  "properties": {
    "iso:country":"GB",
    "wof:name":"IP6 0PP",
    "wof:placetype":"postalcode"
},
  "geometry": {"coordinates":[1.09623193464388,52.1317953872403],"type":"Point"}
}