{
  "type": "Feature",
  "properties": {
    "iso:country":"GB",
    "wof:name":"DL3 9NN",
    "wof:placetype":"postalcode"
},
  "geometry": {"coordinates":[-1.57499325717041,54.52780810272356],"type":"Point"}
}