{
  "type": "Feature",
  "properties": {
    "iso:country":"GB",
    "wof:name":"GU15 1AG",
    "wof:placetype":"postalcode"
},
  "geometry": {"coordinates":[-0.70662661368774,51.3313932673281],"type":"Point"}
}