{
  "type": "Feature",
  "properties": {
    "iso:country": "GB",
    "wof:name": "M41 6LN",
    "wof:placetype": "postalcode"
  },
  "geometry": {"coordinates":[-2.386193,53.447575],"type":"Point"}
}
