{
  "type": "Feature",
  "properties": {
    "iso:country": "GB",
    "wof:name": "S3 7RH",
    "wof:placetype": "postalcode"
  },
  "geometry": {"coordinates":[-1.486084,53.380984],"type":"Point"}
}
