{
  "type": "Feature",
  "properties": {
    "date:inception_lower":"1980-01-01",
    "date:inception_upper":"1980-01-31",
    "iso:country":"GB",
    "wof:name":"LL55 1UT",
    "wof:placetype":"postalcode"
},
  "geometry": {"coordinates":[-4.217411,53.164716],"type":"Point"}
}