{
  "type": "Feature",
  "properties": {
    "iso:country":"GB",
    "wof:name":"LL55 1UT",
    "wof:placetype":"postalcode"
},
  "geometry": {"coordinates":[-4.21741080206612,53.16471572701392],"type":"Point"}
}