{
  "type": "Feature",
  "properties": {
    "iso:country":"GB",
    "wof:name":"SL6 9QW",
    "wof:placetype":"postalcode"
},
  "geometry": {"coordinates":[-0.70702637429611,51.55873486255206],"type":"Point"}
}