{
  "type": "Feature",
  "properties": {
    "iso:country":"GB",
    "wof:name":"AL10 0RF",
    "wof:placetype":"postalcode"
},
  "geometry": {"coordinates":[-0.22939783628108,51.77094757608867],"type":"Point"}
}