{
  "type": "Feature",
  "properties": {
    "iso:country": "GB",
    "wof:name": "LE2 7PR",
    "wof:placetype": "postalcode"
  },
  "geometry": {"coordinates":[-1.143748,52.614567],"type":"Point"}
}
