{
  "type": "Feature",
  "properties": {
    "date:inception_lower": "1980-01-01",
    "date:inception_upper": "1980-01-01",
    "iso:country": "GB",
    "wof:name": "TD9 0TD",
    "wof:placetype": "postalcode"
  },
  "geometry": {"coordinates":[-2.782836,55.179376],"type":"Point"}
}
