{
  "type": "Feature",
  "properties": {
    "iso:country":"GB",
    "wof:name":"TD9 0TD",
    "wof:placetype":"postalcode"
},
  "geometry": {"coordinates":[-2.78283563131861,55.1793757332654],"type":"Point"}
}