{
  "type": "Feature",
  "properties": {
    "iso:country":"GB",
    "wof:name":"TQ12 4RJ",
    "wof:placetype":"postalcode"
},
  "geometry": {"coordinates":[-3.55977075165353,50.53337409263134],"type":"Point"}
}