{
  "type": "Feature",
  "properties": {
    "iso:country":"GB",
    "wof:name":"NW6 5EY",
    "wof:placetype":"postalcode"
},
  "geometry": {"coordinates":[-0.19268130196008,51.53189615800017],"type":"Point"}
}