{
  "type": "Feature",
  "properties": {
    "iso:country":"GB",
    "wof:name":"ZE1 0BT",
    "wof:placetype":"postalcode"
},
  "geometry": {"coordinates":[-1.14583390437447,60.15161486008011],"type":"Point"}
}