{
  "type": "Feature",
  "properties": {
    "iso:country":"GB",
    "wof:name":"IV3 5DQ",
    "wof:placetype":"postalcode"
},
  "geometry": {"coordinates":[-4.23173912765618,57.47747410175165],"type":"Point"}
}