{
  "type": "Feature",
  "properties": {
    "iso:country": "GB",
    "wof:name": "NN14 6EZ",
    "wof:placetype": "postalcode"
  },
  "geometry": {"coordinates":[-0.797919,52.424797],"type":"Point"}
}
