{
  "type": "Feature",
  "properties": {
    "iso:country":"GB",
    "wof:name":"NN14 6EZ",
    "wof:placetype":"postalcode"
},
  "geometry": {"coordinates":[-0.79791893327715,52.42479659698914],"type":"Point"}
}