{
  "type": "Feature",
  "properties": {
    "iso:country":"GB",
    "wof:name":"TA7 8JD",
    "wof:placetype":"postalcode"
},
  "geometry": {"coordinates":[-2.93915611314608,51.16288879257861],"type":"Point"}
}