{
  "type": "Feature",
  "properties": {
    "date:inception_lower":"1980-01-01",
    "date:inception_upper":"1980-01-31",
    "iso:country":"GB",
    "wof:name":"TA7 8JD",
    "wof:placetype":"postalcode"
},
  "geometry": {"coordinates":[-2.939156,51.162889],"type":"Point"}
}