{
  "type": "Feature",
  "properties": {
    "date:inception_lower": "1980-01-01",
    "date:inception_upper": "1980-01-01",
    "iso:country": "GB",
    "wof:name": "BA4 4HQ",
    "wof:placetype": "postalcode"
  },
  "geometry": {"coordinates":[-2.646157,51.163148],"type":"Point"}
}
