{
  "type": "Feature",
  "properties": {
    "iso:country":"GB",
    "wof:name":"BA4 4HQ",
    "wof:placetype":"postalcode"
},
  "geometry": {"coordinates":[-2.64615687126929,51.16314834798438],"type":"Point"}
}