{
  "type": "Feature",
  "properties": {
    "date:inception_lower":"1980-01-01",
    "date:inception_upper":"1980-01-31",
    "iso:country":"GB",
    "wof:name":"LL18 3NQ",
    "wof:placetype":"postalcode"
},
  "geometry": {"coordinates":[-3.479218,53.322931],"type":"Point"}
}