{
  "type": "Feature",
  "properties": {
    "iso:country":"GB",
    "wof:name":"LL18 3NQ",
    "wof:placetype":"postalcode"
},
  "geometry": {"coordinates":[-3.47921786200208,53.322930667151],"type":"Point"}
}