{
  "type": "Feature",
  "properties": {
    "date:inception_lower": "1980-01-01",
    "date:inception_upper": "1980-01-01",
    "iso:country": "GB",
    "wof:name": "W9 1DW",
    "wof:placetype": "postalcode"
  },
  "geometry": {"coordinates":[-0.182467,51.526741],"type":"Point"}
}
