{
  "type": "Feature",
  "properties": {
    "iso:country":"GB",
    "wof:name":"W9 1DW",
    "wof:placetype":"postalcode"
},
  "geometry": {"coordinates":[-0.1826877687728,51.52687685879754],"type":"Point"}
}