{
  "type": "Feature",
  "properties": {
    "iso:country":"GB",
    "wof:name":"CV37 7HE",
    "wof:placetype":"postalcode"
},
  "geometry": {"coordinates":[-1.68652427794703,52.18492924410545],"type":"Point"}
}