{
  "type": "Feature",
  "properties": {
    "iso:country":"GB",
    "wof:name":"HX7 7NQ",
    "wof:placetype":"postalcode"
},
  "geometry": {"coordinates":[-2.02016198628394,53.75026664133824],"type":"Point"}
}