{
  "type": "Feature",
  "properties": {
    "iso:country":"GB",
    "wof:name":"NW11 6NN",
    "wof:placetype":"postalcode"
},
  "geometry": {"coordinates":[-0.18179740974333,51.58249905452503],"type":"Point"}
}