{
  "type": "Feature",
  "properties": {
    "date:inception_lower": "2023-06-01",
    "date:inception_upper": "2023-06-01",
    "iso:country": "GB",
    "wof:name": "SN1 7ET",
    "wof:placetype": "postalcode"
  },
  "geometry": {"coordinates":[-1.81233,51.549135],"type":"Point"}
}
