{
  "type": "Feature",
  "properties": {
    "iso:country":"GB",
    "wof:name":"EX2 5JL",
    "wof:placetype":"postalcode"
},
  "geometry": {"coordinates":[-3.48974958131833,50.70814302832818],"type":"Point"}
}