{
  "type": "Feature",
  "properties": {
    "date:inception_lower": "2022-06-01",
    "date:inception_upper": "2022-06-01",
    "iso:country": "GB",
    "wof:name": "ME8 7FG",
    "wof:placetype": "postalcode"
  },
  "geometry": {"coordinates":[0.611233,51.37406],"type":"Point"}
}
