{
  "type": "Feature",
  "properties": {
    "date:inception_lower":"1980-01-01",
    "date:inception_upper":"1980-01-31",
    "iso:country":"GB",
    "wof:name":"GU21 2SU",
    "wof:placetype":"postalcode"
},
  "geometry": {"coordinates":[-0.624579,51.316988],"type":"Point"}
}