{
  "type": "Feature",
  "properties": {
    "iso:country": "GB",
    "wof:name": "GU21 2SU",
    "wof:placetype": "postalcode"
  },
  "geometry": {"coordinates":[-0.624579,51.316988],"type":"Point"}
}
