{
  "type": "Feature",
  "properties": {
    "iso:country": "GB",
    "wof:name": "SW16 2BG",
    "wof:placetype": "postalcode"
  },
  "geometry": {"coordinates":[-0.11918,51.429304],"type":"Point"}
}
