{
  "type": "Feature",
  "properties": {
    "iso:country":"GB",
    "wof:name":"SW16 2BG",
    "wof:placetype":"postalcode"
},
  "geometry": {"coordinates":[-0.11917985787508,51.42930444186832],"type":"Point"}
}