{
  "type": "Feature",
  "properties": {
    "date:inception_lower": "2014-08-01",
    "date:inception_upper": "2014-08-01",
    "iso:country": "GB",
    "wof:name": "SW16 2BG",
    "wof:placetype": "postalcode"
  },
  "geometry": {"coordinates":[-0.11918,51.429304],"type":"Point"}
}
