{
  "type": "Feature",
  "properties": {
    "date:inception_lower": "2020-01-01",
    "date:inception_upper": "2020-01-01",
    "iso:country": "GB",
    "wof:name": "TN22 5FT",
    "wof:placetype": "postalcode"
  },
  "geometry": {"coordinates":[0.094839,50.95698],"type":"Point"}
}
