{
  "type": "Feature",
  "properties": {
    "iso:country":"GB",
    "wof:name":"CT18 7HE",
    "wof:placetype":"postalcode"
},
  "geometry": {"coordinates":[1.21208215646149,51.10616169795005],"type":"Point"}
}