{
  "type": "Feature",
  "properties": {
    "date:inception_lower": "1980-01-01",
    "date:inception_upper": "1980-01-01",
    "iso:country": "GB",
    "wof:name": "CO3 3RB",
    "wof:placetype": "postalcode"
  },
  "geometry": {"coordinates":[0.877572,51.888301],"type":"Point"}
}
