{
  "type": "Feature",
  "properties": {
    "date:inception_lower": "1980-01-01",
    "date:inception_upper": "1980-01-01",
    "iso:country": "GB",
    "wof:name": "HA6 2XA",
    "wof:placetype": "postalcode"
  },
  "geometry": {"coordinates":[-0.434422,51.605384],"type":"Point"}
}
