{
  "type": "Feature",
  "properties": {
    "iso:country":"GB",
    "wof:name":"HA6 2XA",
    "wof:placetype":"postalcode"
},
  "geometry": {"coordinates":[-0.43442250472387,51.60538383040241],"type":"Point"}
}