{
  "type": "Feature",
  "properties": {
    "iso:country":"GB",
    "wof:name":"OX1 4TN",
    "wof:placetype":"postalcode"
},
  "geometry": {"coordinates":[-1.25185947101387,51.73401211339598],"type":"Point"}
}