{
  "type": "Feature",
  "properties": {
    "iso:country": "GB",
    "wof:name": "RG27 9SE",
    "wof:placetype": "postalcode"
  },
  "geometry": {"coordinates":[-0.949133,51.283761],"type":"Point"}
}
