{
  "type": "Feature",
  "properties": {
    "date:inception_lower": "1987-04-01",
    "date:inception_upper": "1987-04-01",
    "iso:country": "GB",
    "wof:name": "RG27 9SE",
    "wof:placetype": "postalcode"
  },
  "geometry": {"coordinates":[-0.949133,51.283761],"type":"Point"}
}
