{
  "type": "Feature",
  "properties": {
    "iso:country":"GB",
    "wof:name":"AB42 3AJ",
    "wof:placetype":"postalcode"
},
  "geometry": {"coordinates":[-1.81093210767049,57.47556777339388],"type":"Point"}
}