{
  "type": "Feature",
  "properties": {
    "date:inception_lower": "1996-06-01",
    "date:inception_upper": "1996-06-01",
    "iso:country": "GB",
    "wof:name": "AB42 3AJ",
    "wof:placetype": "postalcode"
  },
  "geometry": {"coordinates":[-1.810932,57.475568],"type":"Point"}
}
