{
  "type": "Feature",
  "properties": {
    "iso:country":"GB",
    "wof:name":"S63 8HT",
    "wof:placetype":"postalcode"
},
  "geometry": {"coordinates":[-1.31430988128256,53.52151356183289],"type":"Point"}
}