{
  "type": "Feature",
  "properties": {
    "iso:country":"GB",
    "wof:name":"IP33 3DZ",
    "wof:placetype":"postalcode"
},
  "geometry": {"coordinates":[0.70278857544466,52.2460983866742],"type":"Point"}
}