{
  "type": "Feature",
  "properties": {
    "date:inception_lower": "2018-05-01",
    "date:inception_upper": "2018-05-01",
    "iso:country": "GB",
    "wof:name": "WN1 1DP",
    "wof:placetype": "postalcode"
  },
  "geometry": {"coordinates":[-2.633861,53.544606],"type":"Point"}
}
