{
  "type": "Feature",
  "properties": {
    "date:inception_lower":"1980-01-01",
    "date:inception_upper":"1980-01-31",
    "iso:country":"GB",
    "wof:name":"CW3 0HP",
    "wof:placetype":"postalcode"
},
  "geometry": {"coordinates":[-2.499659,52.994751],"type":"Point"}
}