{
  "type": "Feature",
  "properties": {
    "iso:country":"GB",
    "wof:name":"CW3 0HP",
    "wof:placetype":"postalcode"
},
  "geometry": {"coordinates":[-2.49965890410135,52.99475054485122],"type":"Point"}
}