{
  "type": "Feature",
  "properties": {
    "iso:country":"GB",
    "wof:name":"WA6 9QG",
    "wof:placetype":"postalcode"
},
  "geometry": {"coordinates":[-2.76297194470603,53.26668623568164],"type":"Point"}
}