{
  "type": "Feature",
  "properties": {
    "iso:country": "GB",
    "wof:name": "WA6 9QG",
    "wof:placetype": "postalcode"
  },
  "geometry": {"coordinates":[-2.762972,53.266686],"type":"Point"}
}
