{
  "type": "Feature",
  "properties": {
    "iso:country":"GB",
    "wof:name":"NE10 0PP",
    "wof:placetype":"postalcode"
},
  "geometry": {"coordinates":[-1.5597307371755,54.95025102726191],"type":"Point"}
}