{
  "type": "Feature",
  "properties": {
    "iso:country":"GB",
    "wof:name":"DN17 1SH",
    "wof:placetype":"postalcode"
},
  "geometry": {"coordinates":[-0.67655338915081,53.57756921869219],"type":"Point"}
}