{
  "type": "Feature",
  "properties": {
    "date:inception_lower":"1983-07-01",
    "date:inception_upper":"1983-07-31",
    "iso:country":"GB",
    "wof:name":"DN17 1SH",
    "wof:placetype":"postalcode"
},
  "geometry": {"coordinates":[-0.676553,53.577569],"type":"Point"}
}