{
  "type": "Feature",
  "properties": {
    "iso:country":"GB",
    "wof:name":"B13 0RS",
    "wof:placetype":"postalcode"
},
  "geometry": {"coordinates":[-1.8812612299086,52.42665514259163],"type":"Point"}
}