{
  "type": "Feature",
  "properties": {
    "iso:country":"GB",
    "wof:name":"WA13 9AP",
    "wof:placetype":"postalcode"
},
  "geometry": {"coordinates":[-2.480973006526,53.38214424689173],"type":"Point"}
}