{
  "type": "Feature",
  "properties": {
    "iso:country":"GB",
    "wof:name":"CV32 7EX",
    "wof:placetype":"postalcode"
},
  "geometry": {"coordinates":[-1.5215604022082,52.31081689799232],"type":"Point"}
}