{
  "type": "Feature",
  "properties": {
    "iso:country":"GB",
    "wof:name":"PO2 7LP",
    "wof:placetype":"postalcode"
},
  "geometry": {"coordinates":[-1.07936002853505,50.81152353419684],"type":"Point"}
}