{
  "type": "Feature",
  "properties": {
    "iso:country": "GB",
    "wof:name": "PO2 7LP",
    "wof:placetype": "postalcode"
  },
  "geometry": {"coordinates":[-1.07936,50.811524],"type":"Point"}
}
