{
  "type": "Feature",
  "properties": {
    "iso:country":"GB",
    "wof:name":"DY10 2NJ",
    "wof:placetype":"postalcode"
},
  "geometry": {"coordinates":[-2.24651555117546,52.39384096555962],"type":"Point"}
}