{
  "type": "Feature",
  "properties": {
    "date:inception_lower":"1985-04-01",
    "date:inception_upper":"1985-04-30",
    "iso:country":"GB",
    "wof:name":"NR5 9BU",
    "wof:placetype":"postalcode"
},
  "geometry": {"coordinates":[1.234174,52.64032],"type":"Point"}
}