{
  "type": "Feature",
  "properties": {
    "iso:country":"GB",
    "wof:name":"NW10 0JA",
    "wof:placetype":"postalcode"
},
  "geometry": {"coordinates":[-0.25234987098186,51.5554069894277],"type":"Point"}
}