{
  "type": "Feature",
  "properties": {
    "date:inception_lower":"1998-06-01",
    "date:inception_upper":"1998-06-30",
    "iso:country":"GB",
    "wof:name":"SA31 3NE",
    "wof:placetype":"postalcode"
},
  "geometry": {"coordinates":[-4.327318,51.84918],"type":"Point"}
}