{
  "type": "Feature",
  "properties": {
    "iso:country":"GB",
    "wof:name":"SY13 1LP",
    "wof:placetype":"postalcode"
},
  "geometry": {"coordinates":[-2.68838481433923,52.97338348129087],"type":"Point"}
}