{
  "type": "Feature",
  "properties": {
    "iso:country":"GB",
    "wof:name":"ST6 5TA",
    "wof:placetype":"postalcode"
},
  "geometry": {"coordinates":[-2.21054216698029,53.05728905310395],"type":"Point"}
}