{
  "type": "Feature",
  "properties": {
    "iso:country": "GB",
    "wof:name": "PO8 0WP",
    "wof:placetype": "postalcode"
  },
  "geometry": {"coordinates":[-0.991229,50.942576],"type":"Point"}
}
