{
  "type": "Feature",
  "properties": {
    "date:inception_lower": "2004-09-01",
    "date:inception_upper": "2004-09-01",
    "iso:country": "GB",
    "wof:name": "OX28 6WY",
    "wof:placetype": "postalcode"
  },
  "geometry": {"coordinates":[-1.485118,51.776948],"type":"Point"}
}
