{
  "type": "Feature",
  "properties": {
    "iso:country":"GB",
    "wof:name":"SO50 9DP",
    "wof:placetype":"postalcode"
},
  "geometry": {"coordinates":[-1.35713432565909,50.97129275414709],"type":"Point"}
}