{
  "type": "Feature",
  "properties": {
    "date:inception_lower": "2012-12-01",
    "date:inception_upper": "2012-12-01",
    "iso:country": "GB",
    "wof:name": "HX2 6XH",
    "wof:placetype": "postalcode"
  },
  "geometry": {"coordinates":[-1.954608,53.749664],"type":"Point"}
}
