{
  "type": "Feature",
  "properties": {
    "iso:country": "GB",
    "wof:name": "HX2 6XH",
    "wof:placetype": "postalcode"
  },
  "geometry": {"coordinates":[-1.954608,53.749664],"type":"Point"}
}
