{
  "type": "Feature",
  "properties": {
    "iso:country": "GB",
    "wof:name": "GL1 1AP",
    "wof:placetype": "postalcode"
  },
  "geometry": {"coordinates":[-2.238826,51.863623],"type":"Point"}
}
