{
  "type": "Feature",
  "properties": {
    "date:inception_lower": "2022-11-01",
    "date:inception_upper": "2022-11-01",
    "iso:country": "GB",
    "wof:name": "CR2 9FB",
    "wof:placetype": "postalcode"
  },
  "geometry": {"coordinates":[-0.093011,51.331193],"type":"Point"}
}
