{
  "type": "Feature",
  "properties": {
    "iso:country":"GB",
    "wof:name":"PO21 4XF",
    "wof:placetype":"postalcode"
},
  "geometry": {"coordinates":[-0.73276900596885,50.77078251665096],"type":"Point"}
}