{
  "type": "Feature",
  "properties": {
    "iso:country":"GB",
    "wof:name":"LS12 5DH",
    "wof:placetype":"postalcode"
},
  "geometry": {"coordinates":[-1.6197268016533,53.77701671408006],"type":"Point"}
}