{
  "type": "Feature",
  "properties": {
    "date:inception_lower": "1980-01-01",
    "date:inception_upper": "1980-01-01",
    "iso:country": "GB",
    "wof:name": "LS12 5DH",
    "wof:placetype": "postalcode"
  },
  "geometry": {"coordinates":[-1.619727,53.777017],"type":"Point"}
}
