{
  "type": "Feature",
  "properties": {
    "iso:country":"GB",
    "wof:name":"DN19 7AA",
    "wof:placetype":"postalcode"
},
  "geometry": {"coordinates":[-0.3796790093915,53.67670017523974],"type":"Point"}
}