{
  "type": "Feature",
  "properties": {
    "iso:country":"GB",
    "wof:name":"PO4 9PL",
    "wof:placetype":"postalcode"
},
  "geometry": {"coordinates":[-1.05908953828282,50.78405074983964],"type":"Point"}
}