{
  "type": "Feature",
  "properties": {
    "iso:country": "GB",
    "wof:name": "DN7 4AB",
    "wof:placetype": "postalcode"
  },
  "geometry": {"coordinates":[-1.020878,53.583768],"type":"Point"}
}
