{
  "type": "Feature",
  "properties": {
    "iso:country":"GB",
    "wof:name":"DN7 4AB",
    "wof:placetype":"postalcode"
},
  "geometry": {"coordinates":[-1.02087801759319,53.58376753009608],"type":"Point"}
}