{
  "type": "Feature",
  "properties": {
    "iso:country": "GB",
    "wof:name": "PO18 0SN",
    "wof:placetype": "postalcode"
  },
  "geometry": {"coordinates":[-0.74659,50.850582],"type":"Point"}
}
