{
  "type": "Feature",
  "properties": {
    "date:inception_lower":"2008-08-01",
    "date:inception_upper":"2008-08-31",
    "iso:country":"GB",
    "wof:name":"PO18 0SN",
    "wof:placetype":"postalcode"
},
  "geometry": {"coordinates":[-0.74659,50.850582],"type":"Point"}
}