{
  "type": "Feature",
  "properties": {
    "iso:country":"GB",
    "wof:name":"PO18 0SN",
    "wof:placetype":"postalcode"
},
  "geometry": {"coordinates":[-0.74658983302479,50.85058250157955],"type":"Point"}
}