{
  "type": "Feature",
  "properties": {
    "iso:country": "GB",
    "wof:name": "YO10 3ER",
    "wof:placetype": "postalcode"
  },
  "geometry": {"coordinates":[-1.066055,53.955878],"type":"Point"}
}
