{
  "type": "Feature",
  "properties": {
    "date:inception_lower": "1980-10-01",
    "date:inception_upper": "1980-10-01",
    "iso:country": "GB",
    "wof:name": "KY7 5LY",
    "wof:placetype": "postalcode"
  },
  "geometry": {"coordinates":[-3.176265,56.197563],"type":"Point"}
}
