{
  "type": "Feature",
  "properties": {
    "iso:country":"GB",
    "wof:name":"SE22 9QH",
    "wof:placetype":"postalcode"
},
  "geometry": {"coordinates":[-0.06680292188505,51.4613025181667],"type":"Point"}
}