{
  "type": "Feature",
  "properties": {
    "iso:country":"GB",
    "wof:name":"BS23 3XY",
    "wof:placetype":"postalcode"
},
  "geometry": {"coordinates":[-2.96119502682482,51.33536750111187],"type":"Point"}
}