{
  "type": "Feature",
  "properties": {
    "date:inception_lower": "2023-04-01",
    "date:inception_upper": "2023-04-01",
    "iso:country": "GB",
    "wof:name": "RG23 7QU",
    "wof:placetype": "postalcode"
  },
  "geometry": {"coordinates":[-1.153526,51.230151],"type":"Point"}
}
