{
  "type": "Feature",
  "properties": {
    "iso:country":"GB",
    "wof:name":"YO61 1LL",
    "wof:placetype":"postalcode"
},
  "geometry": {"coordinates":[-1.10892658508257,54.10361480174014],"type":"Point"}
}