{
  "type": "Feature",
  "properties": {
    "iso:country": "GB",
    "wof:name": "YO61 1LL",
    "wof:placetype": "postalcode"
  },
  "geometry": {"coordinates":[-1.108927,54.103615],"type":"Point"}
}
