{
  "type": "Feature",
  "properties": {
    "date:inception_lower": "1998-06-01",
    "date:inception_upper": "1998-06-01",
    "iso:country": "GB",
    "wof:name": "YO61 1LL",
    "wof:placetype": "postalcode"
  },
  "geometry": {"coordinates":[-1.108927,54.103615],"type":"Point"}
}
