{
  "type": "Feature",
  "properties": {
    "iso:country":"GB",
    "wof:name":"WA9 4UF",
    "wof:placetype":"postalcode"
},
  "geometry": {"coordinates":[-2.71036075849619,53.41485989490743],"type":"Point"}
}