{
  "type": "Feature",
  "properties": {
    "iso:country": "GB",
    "wof:name": "WA9 4UF",
    "wof:placetype": "postalcode"
  },
  "geometry": {"coordinates":[-2.710361,53.41486],"type":"Point"}
}
