{
  "type": "Feature",
  "properties": {
    "iso:country":"GB",
    "wof:name":"RG40 1UY",
    "wof:placetype":"postalcode"
},
  "geometry": {"coordinates":[-0.82340868438208,51.41499179253797],"type":"Point"}
}