{
  "type": "Feature",
  "properties": {
    "iso:country": "GB",
    "wof:name": "DN21 2RQ",
    "wof:placetype": "postalcode"
  },
  "geometry": {"coordinates":[-0.776774,53.406011],"type":"Point"}
}
