{
  "type": "Feature",
  "properties": {
    "iso:country":"GB",
    "wof:name":"DN21 2RQ",
    "wof:placetype":"postalcode"
},
  "geometry": {"coordinates":[-0.77677434856751,53.40601078087975],"type":"Point"}
}