{
  "type": "Feature",
  "properties": {
    "date:inception_lower": "2016-09-01",
    "date:inception_upper": "2016-09-01",
    "iso:country": "GB",
    "wof:name": "CH3 9FN",
    "wof:placetype": "postalcode"
  },
  "geometry": {"coordinates":[-2.775982,53.119745],"type":"Point"}
}
