{
  "type": "Feature",
  "properties": {
    "date:inception_lower":"1980-01-01",
    "date:inception_upper":"1980-01-31",
    "iso:country":"GB",
    "wof:name":"N3 1BY",
    "wof:placetype":"postalcode"
},
  "geometry": {"coordinates":[-0.200827,51.602534],"type":"Point"}
}