{
  "type": "Feature",
  "properties": {
    "iso:country":"GB",
    "wof:name":"N3 1BY",
    "wof:placetype":"postalcode"
},
  "geometry": {"coordinates":[-0.20097235768552,51.60242481298171],"type":"Point"}
}