{
  "type": "Feature",
  "properties": {
    "iso:country":"GB",
    "wof:name":"SE16 4JL",
    "wof:placetype":"postalcode"
},
  "geometry": {"coordinates":[-0.05550860503347,51.50008987923419],"type":"Point"}
}