{
  "type": "Feature",
  "properties": {
    "date:inception_lower":"1985-04-01",
    "date:inception_upper":"1985-04-30",
    "iso:country":"GB",
    "wof:name":"SE16 4JL",
    "wof:placetype":"postalcode"
},
  "geometry": {"coordinates":[-0.055509,51.50009],"type":"Point"}
}