{
  "type": "Feature",
  "properties": {
    "iso:country":"GB",
    "wof:name":"NE20 9LR",
    "wof:placetype":"postalcode"
},
  "geometry": {"coordinates":[-1.76546831480954,55.03793355864851],"type":"Point"}
}