{
  "type": "Feature",
  "properties": {
    "iso:country": "GB",
    "wof:name": "PL23 1HQ",
    "wof:placetype": "postalcode"
  },
  "geometry": {"coordinates":[-4.651894,50.336644],"type":"Point"}
}
