{
  "type": "Feature",
  "properties": {
    "date:inception_lower": "1980-01-01",
    "date:inception_upper": "1980-01-01",
    "iso:country": "GB",
    "wof:name": "PL23 1HQ",
    "wof:placetype": "postalcode"
  },
  "geometry": {"coordinates":[-4.651894,50.336644],"type":"Point"}
}
