{
  "type": "Feature",
  "properties": {
    "iso:country":"GB",
    "wof:name":"GU51 2XH",
    "wof:placetype":"postalcode"
},
  "geometry": {"coordinates":[-0.8251932650579,51.29532482330768],"type":"Point"}
}