{
  "type": "Feature",
  "properties": {
    "date:inception_lower": "1996-06-01",
    "date:inception_upper": "1996-06-01",
    "iso:country": "GB",
    "wof:name": "OL1 2JP",
    "wof:placetype": "postalcode"
  },
  "geometry": {"coordinates":[-2.117329,53.551788],"type":"Point"}
}
