{
  "type": "Feature",
  "properties": {
    "iso:country": "GB",
    "wof:name": "OL1 2JP",
    "wof:placetype": "postalcode"
  },
  "geometry": {"coordinates":[-2.117329,53.551788],"type":"Point"}
}
