{
  "type": "Feature",
  "properties": {
    "date:inception_lower": "2016-07-01",
    "date:inception_upper": "2016-07-01",
    "iso:country": "GB",
    "wof:name": "WR9 7LT",
    "wof:placetype": "postalcode"
  },
  "geometry": {"coordinates":[-2.168465,52.252172],"type":"Point"}
}
