{
  "type": "Feature",
  "properties": {
    "iso:country":"GB",
    "wof:name":"HA7 2QW",
    "wof:placetype":"postalcode"
},
  "geometry": {"coordinates":[-0.31334420803833,51.61452420244571],"type":"Point"}
}