{
  "type": "Feature",
  "properties": {
    "iso:country": "GB",
    "wof:name": "PA16 7NW",
    "wof:placetype": "postalcode"
  },
  "geometry": {"coordinates":[-4.794793,55.946672],"type":"Point"}
}
