{
  "type": "Feature",
  "properties": {
    "date:inception_lower": "2009-08-01",
    "date:inception_upper": "2009-08-01",
    "iso:country": "GB",
    "wof:name": "PA16 7NW",
    "wof:placetype": "postalcode"
  },
  "geometry": {"coordinates":[-4.794793,55.946672],"type":"Point"}
}
