{
  "type": "Feature",
  "properties": {
    "iso:country":"GB",
    "wof:name":"PA16 7NW",
    "wof:placetype":"postalcode"
},
  "geometry": {"coordinates":[-4.79479284190402,55.9466718488049],"type":"Point"}
}