{
  "type": "Feature",
  "properties": {
    "iso:country": "GB",
    "wof:name": "SO16 8JN",
    "wof:placetype": "postalcode"
  },
  "geometry": {"coordinates":[-1.463566,50.950266],"type":"Point"}
}
