{
  "type": "Feature",
  "properties": {
    "date:inception_lower": "1980-01-01",
    "date:inception_upper": "1980-01-01",
    "iso:country": "GB",
    "wof:name": "TW12 1NL",
    "wof:placetype": "postalcode"
  },
  "geometry": {"coordinates":[-0.355011,51.4284],"type":"Point"}
}
