{
  "type": "Feature",
  "properties": {
    "iso:country":"GB",
    "wof:name":"RG7 2ED",
    "wof:placetype":"postalcode"
},
  "geometry": {"coordinates":[-1.02310508606795,51.35550994799387],"type":"Point"}
}