{
  "type": "Feature",
  "properties": {
    "iso:country": "GB",
    "wof:name": "RG7 2ED",
    "wof:placetype": "postalcode"
  },
  "geometry": {"coordinates":[-1.023086,51.355511],"type":"Point"}
}
