{
  "type": "Feature",
  "properties": {
    "iso:country":"GB",
    "wof:name":"SO50 9BH",
    "wof:placetype":"postalcode"
},
  "geometry": {"coordinates":[-1.35497605089532,50.97390664089139],"type":"Point"}
}