{
  "type": "Feature",
  "properties": {
    "iso:country": "GB",
    "wof:name": "SO50 9BH",
    "wof:placetype": "postalcode"
  },
  "geometry": {"coordinates":[-1.354966,50.97389],"type":"Point"}
}
