{
  "type": "Feature",
  "properties": {
    "iso:country":"GB",
    "wof:name":"GL5 1SX",
    "wof:placetype":"postalcode"
},
  "geometry": {"coordinates":[-2.20823911941918,51.75286720924205],"type":"Point"}
}