{
  "type": "Feature",
  "properties": {
    "date:inception_lower": "1980-01-01",
    "date:inception_upper": "1980-01-01",
    "iso:country": "GB",
    "wof:name": "PE21 9HA",
    "wof:placetype": "postalcode"
  },
  "geometry": {"coordinates":[-0.027191,52.987546],"type":"Point"}
}
