{
  "type": "Feature",
  "properties": {
    "iso:country": "GB",
    "wof:name": "PE21 9HA",
    "wof:placetype": "postalcode"
  },
  "geometry": {"coordinates":[-0.027191,52.987546],"type":"Point"}
}
