{
  "type": "Feature",
  "properties": {
    "iso:country":"GB",
    "wof:name":"W1T 6BE",
    "wof:placetype":"postalcode"
},
  "geometry": {"coordinates":[-0.14103283279524,51.52349040501527],"type":"Point"}
}