{
  "type": "Feature",
  "properties": {
    "iso:country": "GB",
    "wof:name": "CM6 1WL",
    "wof:placetype": "postalcode"
  },
  "geometry": {"coordinates":[0.344935,51.874425],"type":"Point"}
}
