{
  "type": "Feature",
  "properties": {
    "iso:country":"GB",
    "wof:name":"B90 2JP",
    "wof:placetype":"postalcode"
},
  "geometry": {"coordinates":[-1.8394525387722,52.40599164910596],"type":"Point"}
}