{
  "type": "Feature",
  "properties": {
    "iso:country":"GB",
    "wof:name":"LA3 3PS",
    "wof:placetype":"postalcode"
},
  "geometry": {"coordinates":[-2.8338591515864,54.0575630089442],"type":"Point"}
}