{
  "type": "Feature",
  "properties": {
    "iso:country": "GB",
    "wof:name": "LA3 3PS",
    "wof:placetype": "postalcode"
  },
  "geometry": {"coordinates":[-2.833623,54.057368],"type":"Point"}
}
