{
  "type": "Feature",
  "properties": {
    "date:inception_lower": "1985-10-01",
    "date:inception_upper": "1985-10-01",
    "iso:country": "GB",
    "wof:name": "LA3 3PS",
    "wof:placetype": "postalcode"
  },
  "geometry": {"coordinates":[-2.833623,54.057368],"type":"Point"}
}
