{
  "type": "Feature",
  "properties": {
    "iso:country": "GB",
    "wof:name": "NE15 8QE",
    "wof:placetype": "postalcode"
  },
  "geometry": {"coordinates":[-1.765981,54.982175],"type":"Point"}
}
