{
  "type": "Feature",
  "properties": {
    "iso:country":"GB",
    "wof:name":"NE15 8QE",
    "wof:placetype":"postalcode"
},
  "geometry": {"coordinates":[-1.76598059019688,54.98217539066543],"type":"Point"}
}