{
  "type": "Feature",
  "properties": {
    "iso:country":"GB",
    "wof:name":"WA12 8ES",
    "wof:placetype":"postalcode"
},
  "geometry": {"coordinates":[-2.6306109243936,53.44570747145885],"type":"Point"}
}