{
  "type": "Feature",
  "properties": {
    "iso:country":"GB",
    "wof:name":"CF14 3PH",
    "wof:placetype":"postalcode"
},
  "geometry": {"coordinates":[-3.18690600213599,51.50103439348871],"type":"Point"}
}