{
  "type": "Feature",
  "properties": {
    "date:inception_lower":"2004-06-01",
    "date:inception_upper":"2004-06-30",
    "iso:country":"GB",
    "wof:name":"CF14 3PH",
    "wof:placetype":"postalcode"
},
  "geometry": {"coordinates":[-3.186906,51.501034],"type":"Point"}
}