{
  "type": "Feature",
  "properties": {
    "iso:country":"GB",
    "wof:name":"BH14 0NU",
    "wof:placetype":"postalcode"
},
  "geometry": {"coordinates":[-1.95192059706282,50.72546973831733],"type":"Point"}
}