{
  "type": "Feature",
  "properties": {
    "iso:country": "GB",
    "wof:name": "BH14 0NU",
    "wof:placetype": "postalcode"
  },
  "geometry": {"coordinates":[-1.951921,50.72547],"type":"Point"}
}
