{
  "type": "Feature",
  "properties": {
    "iso:country":"GB",
    "wof:name":"SR7 9PT",
    "wof:placetype":"postalcode"
},
  "geometry": {"coordinates":[-1.39329636721763,54.81728955886221],"type":"Point"}
}