{
  "type": "Feature",
  "properties": {
    "date:inception_lower":"1985-10-01",
    "date:inception_upper":"1985-10-31",
    "iso:country":"GB",
    "wof:name":"PE30 3TU",
    "wof:placetype":"postalcode"
},
  "geometry": {"coordinates":[0.445678,52.773128],"type":"Point"}
}