{
  "type": "Feature",
  "properties": {
    "iso:country":"GB",
    "wof:name":"CV5 8EB",
    "wof:placetype":"postalcode"
},
  "geometry": {"coordinates":[-1.53776197942064,52.40579110141744],"type":"Point"}
}