{
  "type": "Feature",
  "properties": {
    "date:inception_lower": "2001-12-01",
    "date:inception_upper": "2001-12-01",
    "iso:country": "GB",
    "wof:name": "CV5 8EB",
    "wof:placetype": "postalcode"
  },
  "geometry": {"coordinates":[-1.537762,52.405791],"type":"Point"}
}
