{
  "type": "Feature",
  "properties": {
    "iso:country": "GB",
    "wof:name": "CV5 8EB",
    "wof:placetype": "postalcode"
  },
  "geometry": {"coordinates":[-1.537762,52.405791],"type":"Point"}
}
