{
  "type": "Feature",
  "properties": {
    "date:inception_lower": "1980-01-01",
    "date:inception_upper": "1980-01-01",
    "iso:country": "GB",
    "wof:name": "NE46 2HQ",
    "wof:placetype": "postalcode"
  },
  "geometry": {"coordinates":[-2.104947,54.966808],"type":"Point"}
}
