{
  "type": "Feature",
  "properties": {
    "date:inception_lower": "1980-01-01",
    "date:inception_upper": "1980-01-01",
    "iso:country": "GB",
    "wof:name": "NG11 9DG",
    "wof:placetype": "postalcode"
  },
  "geometry": {"coordinates":[-1.181387,52.896519],"type":"Point"}
}
