{
  "type": "Feature",
  "properties": {
    "iso:country":"GB",
    "wof:name":"SW11 6EQ",
    "wof:placetype":"postalcode"
},
  "geometry": {"coordinates":[-0.16530360165625,51.45363202549495],"type":"Point"}
}