{
  "type": "Feature",
  "properties": {
    "iso:country": "GB",
    "wof:name": "YO26 8BG",
    "wof:placetype": "postalcode"
  },
  "geometry": {"coordinates":[-1.324619,54.005263],"type":"Point"}
}
