{
  "type": "Feature",
  "properties": {
    "date:inception_lower": "1999-12-01",
    "date:inception_upper": "1999-12-01",
    "iso:country": "GB",
    "wof:name": "YO26 8BG",
    "wof:placetype": "postalcode"
  },
  "geometry": {"coordinates":[-1.324619,54.005263],"type":"Point"}
}
