{
  "type": "Feature",
  "properties": {
    "iso:country":"GB",
    "wof:name":"YO26 8BG",
    "wof:placetype":"postalcode"
},
  "geometry": {"coordinates":[-1.32461869515803,54.00526292323635],"type":"Point"}
}