{
  "type": "Feature",
  "properties": {
    "date:inception_lower": "2009-10-01",
    "date:inception_upper": "2009-10-01",
    "iso:country": "GB",
    "wof:name": "BS31 2EP",
    "wof:placetype": "postalcode"
  },
  "geometry": {"coordinates":[-2.500226,51.418844],"type":"Point"}
}
