{
  "type": "Feature",
  "properties": {
    "iso:country":"GB",
    "wof:name":"DH4 4PB",
    "wof:placetype":"postalcode"
},
  "geometry": {"coordinates":[-1.49890694229871,54.86317105809132],"type":"Point"}
}