{
  "type": "Feature",
  "properties": {
    "iso:country":"GB",
    "wof:name":"WF2 7RJ",
    "wof:placetype":"postalcode"
},
  "geometry": {"coordinates":[-1.49785136889102,53.67096650483554],"type":"Point"}
}