{
  "type": "Feature",
  "properties": {
    "iso:country": "GB",
    "wof:name": "B98 0AB",
    "wof:placetype": "postalcode"
  },
  "geometry": {"coordinates":[-1.893755,52.29453],"type":"Point"}
}
