{
  "type": "Feature",
  "properties": {
    "iso:country":"GB",
    "wof:name":"NG31 8DG",
    "wof:placetype":"postalcode"
},
  "geometry": {"coordinates":[-0.64071401492241,52.9210865863165],"type":"Point"}
}