{
  "type": "Feature",
  "properties": {
    "iso:country":"GB",
    "wof:name":"PE12 9JN",
    "wof:placetype":"postalcode"
},
  "geometry": {"coordinates":[0.11327476527221,52.79016224937012],"type":"Point"}
}