{
  "type": "Feature",
  "properties": {
    "iso:country": "GB",
    "wof:name": "NR33 9AE",
    "wof:placetype": "postalcode"
  },
  "geometry": {"coordinates":[1.7152,52.466459],"type":"Point"}
}
