{
  "type": "Feature",
  "properties": {
    "date:inception_lower": "1980-01-01",
    "date:inception_upper": "1980-01-01",
    "iso:country": "GB",
    "wof:name": "NR33 9AE",
    "wof:placetype": "postalcode"
  },
  "geometry": {"coordinates":[1.7152,52.466459],"type":"Point"}
}
