{
  "type": "Feature",
  "properties": {
    "iso:country":"GB",
    "wof:name":"TS18 3PN",
    "wof:placetype":"postalcode"
},
  "geometry": {"coordinates":[-1.32568179925586,54.55600040725322],"type":"Point"}
}