{
  "type": "Feature",
  "properties": {
    "iso:country": "GB",
    "wof:name": "HD3 3JB",
    "wof:placetype": "postalcode"
  },
  "geometry": {"coordinates":[-1.822993,53.65979],"type":"Point"}
}
