{
  "type": "Feature",
  "properties": {
    "iso:country":"GB",
    "wof:name":"HD3 3JB",
    "wof:placetype":"postalcode"
},
  "geometry": {"coordinates":[-1.82299262790281,53.65978961617952],"type":"Point"}
}