{
  "type": "Feature",
  "properties": {
    "iso:country":"GB",
    "wof:name":"TD12 4DG",
    "wof:placetype":"postalcode"
},
  "geometry": {"coordinates":[-2.25218919682496,55.65112454981718],"type":"Point"}
}