{
  "type": "Feature",
  "properties": {
    "iso:country": "GB",
    "wof:name": "TD12 4DG",
    "wof:placetype": "postalcode"
  },
  "geometry": {"coordinates":[-2.25218,55.651096],"type":"Point"}
}
