{
  "type": "Feature",
  "properties": {
    "iso:country":"GB",
    "wof:name":"KT12 5EB",
    "wof:placetype":"postalcode"
},
  "geometry": {"coordinates":[-0.42814933926389,51.35882250430799],"type":"Point"}
}