{
  "type": "Feature",
  "properties": {
    "iso:country": "GB",
    "wof:name": "DA13 9JG",
    "wof:placetype": "postalcode"
  },
  "geometry": {"coordinates":[0.35201,51.403546],"type":"Point"}
}
