{
  "type": "Feature",
  "properties": {
    "iso:country": "GB",
    "wof:name": "WA11 8NZ",
    "wof:placetype": "postalcode"
  },
  "geometry": {"coordinates":[-2.784274,53.509399],"type":"Point"}
}
