{
  "type": "Feature",
  "properties": {
    "iso:country":"GB",
    "wof:name":"DL2 1DT",
    "wof:placetype":"postalcode"
},
  "geometry": {"coordinates":[-1.46847072963579,54.50519823545457],"type":"Point"}
}