{
  "type": "Feature",
  "properties": {
    "iso:country":"GB",
    "wof:name":"ST18 0NN",
    "wof:placetype":"postalcode"
},
  "geometry": {"coordinates":[-1.9875309494563,52.79182398477781],"type":"Point"}
}