{
  "type": "Feature",
  "properties": {
    "iso:country": "GB",
    "wof:name": "ST18 0NN",
    "wof:placetype": "postalcode"
  },
  "geometry": {"coordinates":[-1.987531,52.791824],"type":"Point"}
}
