{
  "type": "Feature",
  "properties": {
    "date:inception_lower": "1980-01-01",
    "date:inception_upper": "1980-01-01",
    "iso:country": "GB",
    "wof:name": "ST18 0NN",
    "wof:placetype": "postalcode"
  },
  "geometry": {"coordinates":[-1.987531,52.791824],"type":"Point"}
}
