{
  "type": "Feature",
  "properties": {
    "date:inception_lower": "1980-01-01",
    "date:inception_upper": "1980-01-01",
    "iso:country": "GB",
    "wof:name": "WV11 3QW",
    "wof:placetype": "postalcode"
  },
  "geometry": {"coordinates":[-2.07396,52.597704],"type":"Point"}
}
