{
  "type": "Feature",
  "properties": {
    "iso:country":"GB",
    "wof:name":"WV11 3QW",
    "wof:placetype":"postalcode"
},
  "geometry": {"coordinates":[-2.07399572519448,52.59759836393754],"type":"Point"}
}