{
  "type": "Feature",
  "properties": {
    "iso:country": "GB",
    "wof:name": "WV11 3QW",
    "wof:placetype": "postalcode"
  },
  "geometry": {"coordinates":[-2.07396,52.597704],"type":"Point"}
}
