{
  "type": "Feature",
  "properties": {
    "iso:country":"GB",
    "wof:name":"NE25 9AT",
    "wof:placetype":"postalcode"
},
  "geometry": {"coordinates":[-1.46612303864534,55.04620030980799],"type":"Point"}
}