{
  "type": "Feature",
  "properties": {
    "iso:country":"GB",
    "wof:name":"E7 8DS",
    "wof:placetype":"postalcode"
},
  "geometry": {"coordinates":[0.03444060575336,51.54438171381098],"type":"Point"}
}