{
  "type": "Feature",
  "properties": {
    "date:inception_lower": "1980-01-01",
    "date:inception_upper": "1980-01-01",
    "iso:country": "GB",
    "wof:name": "E7 8DS",
    "wof:placetype": "postalcode"
  },
  "geometry": {"coordinates":[0.034441,51.544382],"type":"Point"}
}
