{
  "type": "Feature",
  "properties": {
    "date:inception_lower": "2016-02-01",
    "date:inception_upper": "2016-02-01",
    "iso:country": "GB",
    "wof:name": "DY5 1LY",
    "wof:placetype": "postalcode"
  },
  "geometry": {"coordinates":[-2.117071,52.487704],"type":"Point"}
}
