{
  "type": "Feature",
  "properties": {
    "date:inception_lower": "1980-01-01",
    "date:inception_upper": "1980-01-01",
    "iso:country": "GB",
    "wof:name": "NG16 5AE",
    "wof:placetype": "postalcode"
  },
  "geometry": {"coordinates":[-1.308319,53.031844],"type":"Point"}
}
