{
  "type": "Feature",
  "properties": {
    "iso:country":"GB",
    "wof:name":"NG16 5AE",
    "wof:placetype":"postalcode"
},
  "geometry": {"coordinates":[-1.30941255559956,53.03257755115666],"type":"Point"}
}