{
  "type": "Feature",
  "properties": {
    "iso:country": "GB",
    "wof:name": "NG16 5AE",
    "wof:placetype": "postalcode"
  },
  "geometry": {"coordinates":[-1.309413,53.032578],"type":"Point"}
}
