{
  "type": "Feature",
  "properties": {
    "iso:country":"GB",
    "wof:name":"NG2 5FF",
    "wof:placetype":"postalcode"
},
  "geometry": {"coordinates":[-1.13355772261919,52.93789157115708],"type":"Point"}
}