{
  "type": "Feature",
  "properties": {
    "date:inception_lower":"1985-10-01",
    "date:inception_upper":"1985-10-31",
    "iso:country":"GB",
    "wof:name":"W10 4BA",
    "wof:placetype":"postalcode"
},
  "geometry": {"coordinates":[-0.209448,51.532288],"type":"Point"}
}