{
  "type": "Feature",
  "properties": {
    "iso:country": "GB",
    "wof:name": "W10 4BA",
    "wof:placetype": "postalcode"
  },
  "geometry": {"coordinates":[-0.209448,51.532288],"type":"Point"}
}
