{
  "type": "Feature",
  "properties": {
    "iso:country":"GB",
    "wof:name":"SE9 5RL",
    "wof:placetype":"postalcode"
},
  "geometry": {"coordinates":[0.04160591825682,51.44534596870353],"type":"Point"}
}