{
  "type": "Feature",
  "properties": {
    "iso:country":"GB",
    "wof:name":"BS7 8NN",
    "wof:placetype":"postalcode"
},
  "geometry": {"coordinates":[-2.59037970147594,51.4757930372954],"type":"Point"}
}