{
  "type": "Feature",
  "properties": {
    "iso:country": "GB",
    "wof:name": "LL28 5AQ",
    "wof:placetype": "postalcode"
  },
  "geometry": {"coordinates":[-3.795839,53.219136],"type":"Point"}
}
