{
  "type": "Feature",
  "properties": {
    "iso:country":"GB",
    "wof:name":"LL28 5AQ",
    "wof:placetype":"postalcode"
},
  "geometry": {"coordinates":[-3.79583891866535,53.21913582409876],"type":"Point"}
}