{
  "type": "Feature",
  "properties": {
    "iso:country": "GB",
    "wof:name": "OX12 7AS",
    "wof:placetype": "postalcode"
  },
  "geometry": {"coordinates":[-1.418558,51.589556],"type":"Point"}
}
