{
  "type": "Feature",
  "properties": {
    "iso:country": "GB",
    "wof:name": "SN4 0FS",
    "wof:placetype": "postalcode"
  },
  "geometry": {"coordinates":[-1.79285,51.509153],"type":"Point"}
}
