{
  "type": "Feature",
  "properties": {
    "iso:country": "GB",
    "wof:name": "G43 1AQ",
    "wof:placetype": "postalcode"
  },
  "geometry": {"coordinates":[-4.335531,55.820044],"type":"Point"}
}
