{
  "type": "Feature",
  "properties": {
    "iso:country":"GB",
    "wof:name":"TS3 0NF",
    "wof:placetype":"postalcode"
},
  "geometry": {"coordinates":[-1.18745705659311,54.55088252986828],"type":"Point"}
}