{
  "type": "Feature",
  "properties": {
    "iso:country":"GB",
    "wof:name":"SG8 9QB",
    "wof:placetype":"postalcode"
},
  "geometry": {"coordinates":[-0.05491338558628,52.01708169922912],"type":"Point"}
}