{
  "type": "Feature",
  "properties": {
    "iso:country": "GB",
    "wof:name": "SG8 9QB",
    "wof:placetype": "postalcode"
  },
  "geometry": {"coordinates":[-0.055054,52.016878],"type":"Point"}
}
