{
  "type": "Feature",
  "properties": {
    "iso:country": "GB",
    "wof:name": "PR8 2SW",
    "wof:placetype": "postalcode"
  },
  "geometry": {"coordinates":[-3.016604,53.64325],"type":"Point"}
}
