{
  "type": "Feature",
  "properties": {
    "date:inception_lower":"1986-07-01",
    "date:inception_upper":"1986-07-31",
    "iso:country":"GB",
    "wof:name":"PR8 2SW",
    "wof:placetype":"postalcode"
},
  "geometry": {"coordinates":[-3.016604,53.64325],"type":"Point"}
}