{
  "type": "Feature",
  "properties": {
    "date:inception_lower":"1980-01-01",
    "date:inception_upper":"1980-01-31",
    "iso:country":"GB",
    "wof:name":"G82 1RQ",
    "wof:placetype":"postalcode"
},
  "geometry": {"coordinates":[-4.555657,55.942486],"type":"Point"}
}