{
  "type": "Feature",
  "properties": {
    "iso:country": "GB",
    "wof:name": "G82 1RQ",
    "wof:placetype": "postalcode"
  },
  "geometry": {"coordinates":[-4.555657,55.942486],"type":"Point"}
}
