{
  "type": "Feature",
  "properties": {
    "iso:country":"GB",
    "wof:name":"PE7 1FN",
    "wof:placetype":"postalcode"
},
  "geometry": {"coordinates":[-0.12789105532607,52.5601251821953],"type":"Point"}
}