{
  "type": "Feature",
  "properties": {
    "iso:country":"GB",
    "wof:name":"BL1 3AZ",
    "wof:placetype":"postalcode"
},
  "geometry": {"coordinates":[-2.44732700534154,53.58536151568698],"type":"Point"}
}