{
  "type": "Feature",
  "properties": {
    "iso:country":"GB",
    "wof:name":"RM20 3JJ",
    "wof:placetype":"postalcode"
},
  "geometry": {"coordinates":[0.27697412495701,51.47744080893876],"type":"Point"}
}