{
  "type": "Feature",
  "properties": {
    "iso:country":"GB",
    "wof:name":"DA1 4NF",
    "wof:placetype":"postalcode"
},
  "geometry": {"coordinates":[0.19095111179536,51.45514071448726],"type":"Point"}
}