{
  "type": "Feature",
  "properties": {
    "iso:country": "GB",
    "wof:name": "DA1 4NF",
    "wof:placetype": "postalcode"
  },
  "geometry": {"coordinates":[0.190951,51.455141],"type":"Point"}
}
