{
  "type": "Feature",
  "properties": {
    "iso:country":"GB",
    "wof:name":"SK9 4AW",
    "wof:placetype":"postalcode"
},
  "geometry": {"coordinates":[-2.23326705604298,53.33299876324831],"type":"Point"}
}