{
  "type": "Feature",
  "properties": {
    "iso:country": "GB",
    "wof:name": "SK9 4AW",
    "wof:placetype": "postalcode"
  },
  "geometry": {"coordinates":[-2.233267,53.332999],"type":"Point"}
}
