{
  "type": "Feature",
  "properties": {
    "iso:country":"GB",
    "wof:name":"TN2 4RX",
    "wof:placetype":"postalcode"
},
  "geometry": {"coordinates":[0.29963041438706,51.14319296829505],"type":"Point"}
}