{
  "type": "Feature",
  "properties": {
    "date:inception_lower": "1980-01-01",
    "date:inception_upper": "1980-01-01",
    "iso:country": "GB",
    "wof:name": "TN2 4RX",
    "wof:placetype": "postalcode"
  },
  "geometry": {"coordinates":[0.29963,51.143193],"type":"Point"}
}
