{
  "type": "Feature",
  "properties": {
    "date:inception_lower": "1980-01-01",
    "date:inception_upper": "1980-01-01",
    "iso:country": "GB",
    "wof:name": "WN3 5QE",
    "wof:placetype": "postalcode"
  },
  "geometry": {"coordinates":[-2.647843,53.523322],"type":"Point"}
}
