{
  "type": "Feature",
  "properties": {
    "date:inception_lower": "1980-01-01",
    "date:inception_upper": "1980-01-01",
    "iso:country": "GB",
    "wof:name": "G31 1RW",
    "wof:placetype": "postalcode"
  },
  "geometry": {"coordinates":[-4.221258,55.857271],"type":"Point"}
}
