{
  "type": "Feature",
  "properties": {
    "iso:country": "GB",
    "wof:name": "G63 0ER",
    "wof:placetype": "postalcode"
  },
  "geometry": {"coordinates":[-4.446173,56.04342],"type":"Point"}
}
