{
  "type": "Feature",
  "properties": {
    "iso:country": "GB",
    "wof:name": "S70 6PE",
    "wof:placetype": "postalcode"
  },
  "geometry": {"coordinates":[-1.507103,53.551208],"type":"Point"}
}
