{
  "type": "Feature",
  "properties": {
    "date:inception_lower": "1980-01-01",
    "date:inception_upper": "1980-01-01",
    "iso:country": "GB",
    "wof:name": "BB7 4TF",
    "wof:placetype": "postalcode"
  },
  "geometry": {"coordinates":[-2.390099,53.897018],"type":"Point"}
}
