{
  "type": "Feature",
  "properties": {
    "iso:country":"GB",
    "wof:name":"BB7 4TF",
    "wof:placetype":"postalcode"
},
  "geometry": {"coordinates":[-2.39009937994979,53.89701765755374],"type":"Point"}
}