{
  "type": "Feature",
  "properties": {
    "date:inception_lower": "1996-06-01",
    "date:inception_upper": "1996-06-01",
    "iso:country": "GB",
    "wof:name": "AB21 0EQ",
    "wof:placetype": "postalcode"
  },
  "geometry": {"coordinates":[-2.214671,57.217532],"type":"Point"}
}
