{
  "type": "Feature",
  "properties": {
    "iso:country":"GB",
    "wof:name":"AB21 0EQ",
    "wof:placetype":"postalcode"
},
  "geometry": {"coordinates":[-2.21467095613907,57.21753245284739],"type":"Point"}
}