{
  "type": "Feature",
  "properties": {
    "date:inception_lower": "1980-01-01",
    "date:inception_upper": "1980-01-01",
    "iso:country": "GB",
    "wof:name": "PA12 4JY",
    "wof:placetype": "postalcode"
  },
  "geometry": {"coordinates":[-4.61381,55.775279],"type":"Point"}
}
