{
  "type": "Feature",
  "properties": {
    "iso:country":"GB",
    "wof:name":"PA12 4JY",
    "wof:placetype":"postalcode"
},
  "geometry": {"coordinates":[-4.61464989970797,55.78040753049324],"type":"Point"}
}