{
  "type": "Feature",
  "properties": {
    "iso:country":"GB",
    "wof:name":"PE29 2HE",
    "wof:placetype":"postalcode"
},
  "geometry": {"coordinates":[-0.17526348915296,52.31725761842428],"type":"Point"}
}