{
  "type": "Feature",
  "properties": {
    "iso:country":"GB",
    "wof:name":"B70 0HE",
    "wof:placetype":"postalcode"
},
  "geometry": {"coordinates":[-2.02754633286357,52.52218466393277],"type":"Point"}
}