{
  "type": "Feature",
  "properties": {
    "date:inception_lower": "1986-04-01",
    "date:inception_upper": "1986-04-01",
    "iso:country": "GB",
    "wof:name": "TN15 8EH",
    "wof:placetype": "postalcode"
  },
  "geometry": {"coordinates":[0.310538,51.296721],"type":"Point"}
}
