{
  "type": "Feature",
  "properties": {
    "iso:country": "GB",
    "wof:name": "TN15 8EH",
    "wof:placetype": "postalcode"
  },
  "geometry": {"coordinates":[0.310538,51.296721],"type":"Point"}
}
