{
  "type": "Feature",
  "properties": {
    "date:inception_lower": "1980-01-01",
    "date:inception_upper": "1980-01-01",
    "iso:country": "GB",
    "wof:name": "B8 1DU",
    "wof:placetype": "postalcode"
  },
  "geometry": {"coordinates":[-1.860617,52.486362],"type":"Point"}
}
