{
  "type": "Feature",
  "properties": {
    "iso:country":"GB",
    "wof:name":"B8 1DU",
    "wof:placetype":"postalcode"
},
  "geometry": {"coordinates":[-1.8606166893338,52.48636222185565],"type":"Point"}
}