{
  "type": "Feature",
  "properties": {
    "iso:country":"GB",
    "wof:name":"DD9 7DJ",
    "wof:placetype":"postalcode"
},
  "geometry": {"coordinates":[-2.65108166314941,56.72893345807439],"type":"Point"}
}