{
  "type": "Feature",
  "properties": {
    "iso:country":"GB",
    "wof:name":"M31 4PD",
    "wof:placetype":"postalcode"
},
  "geometry": {"coordinates":[-2.43335874819511,53.41884748027269],"type":"Point"}
}