{
  "type": "Feature",
  "properties": {
    "iso:country":"GB",
    "wof:name":"BS5 0PR",
    "wof:placetype":"postalcode"
},
  "geometry": {"coordinates":[-2.57336791412828,51.46146392809316],"type":"Point"}
}