{
  "type": "Feature",
  "properties": {
    "iso:country":"GB",
    "wof:name":"HA9 9HL",
    "wof:placetype":"postalcode"
},
  "geometry": {"coordinates":[-0.27347901783572,51.56807520242215],"type":"Point"}
}