{
  "type": "Feature",
  "properties": {
    "iso:country":"GB",
    "wof:name":"TW18 1PH",
    "wof:placetype":"postalcode"
},
  "geometry": {"coordinates":[-0.48343280722248,51.42488939448936],"type":"Point"}
}