{
  "type": "Feature",
  "properties": {
    "date:inception_lower": "1980-01-01",
    "date:inception_upper": "1980-01-01",
    "iso:country": "GB",
    "wof:name": "SY4 5RW",
    "wof:placetype": "postalcode"
  },
  "geometry": {"coordinates":[-2.707325,52.859435],"type":"Point"}
}
