{
  "type": "Feature",
  "properties": {
    "iso:country":"GB",
    "wof:name":"SY4 5RW",
    "wof:placetype":"postalcode"
},
  "geometry": {"coordinates":[-2.70777188863129,52.85930098798238],"type":"Point"}
}