{
  "type": "Feature",
  "properties": {
    "iso:country":"GB",
    "wof:name":"LN3 4JH",
    "wof:placetype":"postalcode"
},
  "geometry": {"coordinates":[-0.45295300438264,53.24212285986202],"type":"Point"}
}