{
  "type": "Feature",
  "properties": {
    "iso:country": "GB",
    "wof:name": "LN3 4JH",
    "wof:placetype": "postalcode"
  },
  "geometry": {"coordinates":[-0.452953,53.242123],"type":"Point"}
}
