{
  "type": "Feature",
  "properties": {
    "iso:country":"GB",
    "wof:name":"DA1 5QS",
    "wof:placetype":"postalcode"
},
  "geometry": {"coordinates":[0.22770710597725,51.45794620090614],"type":"Point"}
}