{
  "type": "Feature",
  "properties": {
    "iso:country": "GB",
    "wof:name": "CF10 4QL",
    "wof:placetype": "postalcode"
  },
  "geometry": {"coordinates":[-3.171179,51.475422],"type":"Point"}
}
