{
  "type": "Feature",
  "properties": {
    "iso:country":"GB",
    "wof:name":"CF10 4QL",
    "wof:placetype":"postalcode"
},
  "geometry": {"coordinates":[-3.17117949217139,51.47542173328681],"type":"Point"}
}