{
  "type": "Feature",
  "properties": {
    "iso:country":"GB",
    "wof:name":"BS8 2LR",
    "wof:placetype":"postalcode"
},
  "geometry": {"coordinates":[-2.60808370332624,51.46015601292756],"type":"Point"}
}