{
  "type": "Feature",
  "properties": {
    "date:inception_lower": "1980-01-01",
    "date:inception_upper": "1980-01-01",
    "iso:country": "GB",
    "wof:name": "SY5 0LJ",
    "wof:placetype": "postalcode"
  },
  "geometry": {"coordinates":[-2.928301,52.632168],"type":"Point"}
}
