{
  "type": "Feature",
  "properties": {
    "iso:country":"GB",
    "wof:name":"CT14 7DJ",
    "wof:placetype":"postalcode"
},
  "geometry": {"coordinates":[1.40109977214675,51.2194060937541],"type":"Point"}
}