{
  "type": "Feature",
  "properties": {
    "iso:country": "GB",
    "wof:name": "CT14 7DJ",
    "wof:placetype": "postalcode"
  },
  "geometry": {"coordinates":[1.401119,51.219469],"type":"Point"}
}
