{
  "type": "Feature",
  "properties": {
    "date:inception_lower":"2010-10-01",
    "date:inception_upper":"2010-10-31",
    "iso:country":"GB",
    "wof:name":"NN7 2GD",
    "wof:placetype":"postalcode"
},
  "geometry": {"coordinates":[-0.898166,52.156143],"type":"Point"}
}