{
  "type": "Feature",
  "properties": {
    "date:inception_lower": "2022-03-01",
    "date:inception_upper": "2022-03-01",
    "iso:country": "GB",
    "wof:name": "IP30 9YY",
    "wof:placetype": "postalcode"
  },
  "geometry": {"coordinates":[0.897119,52.224489],"type":"Point"}
}
