{
  "type": "Feature",
  "properties": {
    "iso:country":"GB",
    "wof:name":"SW16 6LN",
    "wof:placetype":"postalcode"
},
  "geometry": {"coordinates":[-0.13599542064915,51.42650658627556],"type":"Point"}
}