{
  "type": "Feature",
  "properties": {
    "date:inception_lower": "2018-01-01",
    "date:inception_upper": "2018-01-01",
    "iso:country": "GB",
    "wof:name": "DL17 0GY",
    "wof:placetype": "postalcode"
  },
  "geometry": {"coordinates":[-1.559843,54.655871],"type":"Point"}
}
