{
  "type": "Feature",
  "properties": {
    "iso:country":"GB",
    "wof:name":"GU34 5BU",
    "wof:placetype":"postalcode"
},
  "geometry": {"coordinates":[-1.04257199819992,51.11078751777227],"type":"Point"}
}