{
  "type": "Feature",
  "properties": {
    "iso:country":"GB",
    "wof:name":"AB31 4LD",
    "wof:placetype":"postalcode"
},
  "geometry": {"coordinates":[-2.64151239606364,57.13419500743712],"type":"Point"}
}