{
  "type": "Feature",
  "properties": {
    "iso:country":"GB",
    "wof:name":"BS21 7ND",
    "wof:placetype":"postalcode"
},
  "geometry": {"coordinates":[-2.85571932586661,51.44110275445077],"type":"Point"}
}