{
  "type": "Feature",
  "properties": {
    "date:inception_lower":"1980-01-01",
    "date:inception_upper":"1980-01-31",
    "iso:country":"GB",
    "wof:name":"TA18 8NX",
    "wof:placetype":"postalcode"
},
  "geometry": {"coordinates":[-2.768381,50.870346],"type":"Point"}
}