{
  "type": "Feature",
  "properties": {
    "iso:country":"GB",
    "wof:name":"TA18 8NX",
    "wof:placetype":"postalcode"
},
  "geometry": {"coordinates":[-2.76838115254566,50.87034559994385],"type":"Point"}
}