{
  "type": "Feature",
  "properties": {
    "date:inception_lower": "1992-01-01",
    "date:inception_upper": "1992-01-01",
    "iso:country": "GB",
    "wof:name": "SS0 0AP",
    "wof:placetype": "postalcode"
  },
  "geometry": {"coordinates":[0.68024,51.560046],"type":"Point"}
}
