{
  "type": "Feature",
  "properties": {
    "iso:country":"GB",
    "wof:name":"B77 2JU",
    "wof:placetype":"postalcode"
},
  "geometry": {"coordinates":[-1.6726599157393,52.61604864279948],"type":"Point"}
}