{
  "type": "Feature",
  "properties": {
    "date:inception_lower": "1992-08-01",
    "date:inception_upper": "1992-08-01",
    "iso:country": "GB",
    "wof:name": "B77 2JU",
    "wof:placetype": "postalcode"
  },
  "geometry": {"coordinates":[-1.67266,52.616049],"type":"Point"}
}
