{
  "type": "Feature",
  "properties": {
    "iso:country":"GB",
    "wof:name":"EX4 4DW",
    "wof:placetype":"postalcode"
},
  "geometry": {"coordinates":[-3.54024340683229,50.72765864166972],"type":"Point"}
}