{
  "type": "Feature",
  "properties": {
    "iso:country": "GB",
    "wof:name": "EX4 4DW",
    "wof:placetype": "postalcode"
  },
  "geometry": {"coordinates":[-3.540243,50.727659],"type":"Point"}
}
