{
  "type": "Feature",
  "properties": {
    "iso:country":"GB",
    "wof:name":"AL4 0FG",
    "wof:placetype":"postalcode"
},
  "geometry": {"coordinates":[-0.29900790871271,51.74675296328999],"type":"Point"}
}