{
  "type": "Feature",
  "properties": {
    "iso:country": "GB",
    "wof:name": "TW15 1HN",
    "wof:placetype": "postalcode"
  },
  "geometry": {"coordinates":[-0.450591,51.427994],"type":"Point"}
}
