{
  "type": "Feature",
  "properties": {
    "iso:country":"GB",
    "wof:name":"TW15 1HN",
    "wof:placetype":"postalcode"
},
  "geometry": {"coordinates":[-0.45059059242598,51.42799386731345],"type":"Point"}
}