{
  "type": "Feature",
  "properties": {
    "iso:country":"GB",
    "wof:name":"E17 9RQ",
    "wof:placetype":"postalcode"
},
  "geometry": {"coordinates":[-0.01321994927573,51.58420842239864],"type":"Point"}
}