{
  "type": "Feature",
  "properties": {
    "iso:country": "GB",
    "wof:name": "OL5 0PS",
    "wof:placetype": "postalcode"
  },
  "geometry": {"coordinates":[-2.045377,53.523182],"type":"Point"}
}
