{
  "type": "Feature",
  "properties": {
    "date:inception_lower":"1980-01-01",
    "date:inception_upper":"1980-01-31",
    "iso:country":"GB",
    "wof:name":"HR1 3PN",
    "wof:placetype":"postalcode"
},
  "geometry": {"coordinates":[-2.612388,52.137545],"type":"Point"}
}