{
  "type": "Feature",
  "properties": {
    "iso:country":"GB",
    "wof:name":"HR1 3PN",
    "wof:placetype":"postalcode"
},
  "geometry": {"coordinates":[-2.60788461295467,52.13404183916244],"type":"Point"}
}