{
  "type": "Feature",
  "properties": {
    "iso:country": "GB",
    "wof:name": "HR1 3PN",
    "wof:placetype": "postalcode"
  },
  "geometry": {"coordinates":[-2.612388,52.137545],"type":"Point"}
}
