{
  "type": "Feature",
  "properties": {
    "iso:country":"GB",
    "wof:name":"AL2 3QN",
    "wof:placetype":"postalcode"
},
  "geometry": {"coordinates":[-0.36653436573443,51.71119454622995],"type":"Point"}
}