{
  "type": "Feature",
  "properties": {
    "date:inception_lower": "1980-01-01",
    "date:inception_upper": "1980-01-01",
    "iso:country": "GB",
    "wof:name": "IG1 2UF",
    "wof:placetype": "postalcode"
  },
  "geometry": {"coordinates":[0.081271,51.550736],"type":"Point"}
}
