{
  "type": "Feature",
  "properties": {
    "iso:country":"GB",
    "wof:name":"SY5 9PX",
    "wof:placetype":"postalcode"
},
  "geometry": {"coordinates":[-2.87300046693725,52.67900722298202],"type":"Point"}
}