{
  "type": "Feature",
  "properties": {
    "iso:country":"GB",
    "wof:name":"SE18 4GJ",
    "wof:placetype":"postalcode"
},
  "geometry": {"coordinates":[0.0465563152477,51.47398265480251],"type":"Point"}
}