{
  "type": "Feature",
  "properties": {
    "date:inception_lower":"2007-01-01",
    "date:inception_upper":"2007-01-31",
    "iso:country":"GB",
    "wof:name":"SE18 4GJ",
    "wof:placetype":"postalcode"
},
  "geometry": {"coordinates":[0.046556,51.473983],"type":"Point"}
}