{
  "type": "Feature",
  "properties": {
    "iso:country": "GB",
    "wof:name": "SE18 4GJ",
    "wof:placetype": "postalcode"
  },
  "geometry": {"coordinates":[0.046556,51.473983],"type":"Point"}
}
