{
  "type": "Feature",
  "properties": {
    "iso:country":"GB",
    "wof:name":"HS2 0BG",
    "wof:placetype":"postalcode"
},
  "geometry": {"coordinates":[-6.31702533044083,58.21063557000802],"type":"Point"}
}