{
  "type": "Feature",
  "properties": {
    "iso:country": "GB",
    "wof:name": "HS2 0BG",
    "wof:placetype": "postalcode"
  },
  "geometry": {"coordinates":[-6.317025,58.210636],"type":"Point"}
}
