{
  "type": "Feature",
  "properties": {
    "iso:country":"GB",
    "wof:name":"DH2 1SB",
    "wof:placetype":"postalcode"
},
  "geometry": {"coordinates":[-1.60706755519352,54.88155070022051],"type":"Point"}
}