{
  "type": "Feature",
  "properties": {
    "iso:country":"GB",
    "wof:name":"AB53 8NU",
    "wof:placetype":"postalcode"
},
  "geometry": {"coordinates":[-2.29970548954796,57.48777532721395],"type":"Point"}
}