{
  "type": "Feature",
  "properties": {
    "iso:country":"GB",
    "wof:name":"CA15 7QX",
    "wof:placetype":"postalcode"
},
  "geometry": {"coordinates":[-3.48058356723607,54.70701660877974],"type":"Point"}
}