{
  "type": "Feature",
  "properties": {
    "iso:country":"GB",
    "wof:name":"WF7 6JG",
    "wof:placetype":"postalcode"
},
  "geometry": {"coordinates":[-1.35668740492779,53.6820843898283],"type":"Point"}
}