{
  "type": "Feature",
  "properties": {
    "date:inception_lower": "1980-01-01",
    "date:inception_upper": "1980-01-01",
    "iso:country": "GB",
    "wof:name": "WF7 6JG",
    "wof:placetype": "postalcode"
  },
  "geometry": {"coordinates":[-1.356826,53.682103],"type":"Point"}
}
