{
  "type": "Feature",
  "properties": {
    "iso:country":"GB",
    "wof:name":"HP7 0LE",
    "wof:placetype":"postalcode"
},
  "geometry": {"coordinates":[-0.62810759483877,51.65300899431731],"type":"Point"}
}