{
  "type": "Feature",
  "properties": {
    "date:inception_lower": "1992-08-01",
    "date:inception_upper": "1992-08-01",
    "iso:country": "GB",
    "wof:name": "SS5 5LY",
    "wof:placetype": "postalcode"
  },
  "geometry": {"coordinates":[0.649384,51.618995],"type":"Point"}
}
