{
  "type": "Feature",
  "properties": {
    "iso:country":"GB",
    "wof:name":"SS5 5LY",
    "wof:placetype":"postalcode"
},
  "geometry": {"coordinates":[0.6491395568729,51.61897658981993],"type":"Point"}
}