{
  "type": "Feature",
  "properties": {
    "iso:country":"GB",
    "wof:name":"N3 3SP",
    "wof:placetype":"postalcode"
},
  "geometry": {"coordinates":[-0.20526331816504,51.59614192755005],"type":"Point"}
}