{
  "type": "Feature",
  "properties": {
    "iso:country":"GB",
    "wof:name":"E8 3HB",
    "wof:placetype":"postalcode"
},
  "geometry": {"coordinates":[-0.06273018274226,51.54077496140943],"type":"Point"}
}