{
  "type": "Feature",
  "properties": {
    "iso:country":"GB",
    "wof:name":"SE18 6LF",
    "wof:placetype":"postalcode"
},
  "geometry": {"coordinates":[0.06792662557796,51.4911885882299],"type":"Point"}
}