{
  "type": "Feature",
  "properties": {
    "iso:country": "GB",
    "wof:name": "BD7 4QY",
    "wof:placetype": "postalcode"
  },
  "geometry": {"coordinates":[-1.794762,53.776913],"type":"Point"}
}
