{
  "type": "Feature",
  "properties": {
    "iso:country":"GB",
    "wof:name":"TR3 7JY",
    "wof:placetype":"postalcode"
},
  "geometry": {"coordinates":[-5.12513939957183,50.2082740517541],"type":"Point"}
}