{
  "type": "Feature",
  "properties": {
    "iso:country":"GB",
    "wof:name":"DE7 8JT",
    "wof:placetype":"postalcode"
},
  "geometry": {"coordinates":[-1.30020042039199,52.98074514411381],"type":"Point"}
}