{
  "type": "Feature",
  "properties": {
    "iso:country":"GB",
    "wof:name":"PO15 6QW",
    "wof:placetype":"postalcode"
},
  "geometry": {"coordinates":[-1.20906731302372,50.85825631510409],"type":"Point"}
}