{
  "type": "Feature",
  "properties": {
    "date:inception_lower": "2004-05-01",
    "date:inception_upper": "2004-05-01",
    "iso:country": "GB",
    "wof:name": "RG10 9TY",
    "wof:placetype": "postalcode"
  },
  "geometry": {"coordinates":[-0.881468,51.472443],"type":"Point"}
}
