{
  "type": "Feature",
  "properties": {
    "iso:country":"GB",
    "wof:name":"RG10 9TY",
    "wof:placetype":"postalcode"
},
  "geometry": {"coordinates":[-0.88146777083616,51.47244307838944],"type":"Point"}
}