{
  "type": "Feature",
  "properties": {
    "iso:country":"GB",
    "wof:name":"YO30 7AT",
    "wof:placetype":"postalcode"
},
  "geometry": {"coordinates":[-1.08640435342421,53.96962440720774],"type":"Point"}
}