{
  "type": "Feature",
  "properties": {
    "iso:country": "GB",
    "wof:name": "KT22 9HH",
    "wof:placetype": "postalcode"
  },
  "geometry": {"coordinates":[-0.359738,51.285189],"type":"Point"}
}
