{
  "type": "Feature",
  "properties": {
    "iso:country":"GB",
    "wof:name":"KT22 9HH",
    "wof:placetype":"postalcode"
},
  "geometry": {"coordinates":[-0.35973834646877,51.28518895625801],"type":"Point"}
}