{
  "type": "Feature",
  "properties": {
    "date:inception_lower": "1980-01-01",
    "date:inception_upper": "1980-01-01",
    "iso:country": "GB",
    "wof:name": "KT22 9HH",
    "wof:placetype": "postalcode"
  },
  "geometry": {"coordinates":[-0.359738,51.285189],"type":"Point"}
}
