{
  "type": "Feature",
  "properties": {
    "iso:country":"GB",
    "wof:name":"GL12 7JS",
    "wof:placetype":"postalcode"
},
  "geometry": {"coordinates":[-2.34505680152437,51.6359380004745],"type":"Point"}
}