{
  "type": "Feature",
  "properties": {
    "iso:country": "GB",
    "wof:name": "NN10 9YG",
    "wof:placetype": "postalcode"
  },
  "geometry": {"coordinates":[-0.601169,52.289137],"type":"Point"}
}
