{
  "type": "Feature",
  "properties": {
    "date:inception_lower": "1980-01-01",
    "date:inception_upper": "1980-01-01",
    "iso:country": "GB",
    "wof:name": "NN10 9YG",
    "wof:placetype": "postalcode"
  },
  "geometry": {"coordinates":[-0.601169,52.289137],"type":"Point"}
}
