{
  "type": "Feature",
  "properties": {
    "iso:country":"GB",
    "wof:name":"NN10 9YG",
    "wof:placetype":"postalcode"
},
  "geometry": {"coordinates":[-0.60116861610917,52.28913719217526],"type":"Point"}
}