{
  "type": "Feature",
  "properties": {
    "iso:country":"GB",
    "wof:name":"SE5 7QH",
    "wof:placetype":"postalcode"
},
  "geometry": {"coordinates":[-0.08880464950001,51.47806580893707],"type":"Point"}
}