{
  "type": "Feature",
  "properties": {
    "iso:country":"GB",
    "wof:name":"LN3 5DF",
    "wof:placetype":"postalcode"
},
  "geometry": {"coordinates":[-0.40397449498033,53.27204234995913],"type":"Point"}
}