{
  "type": "Feature",
  "properties": {
    "iso:country":"GB",
    "wof:name":"WV6 0DD",
    "wof:placetype":"postalcode"
},
  "geometry": {"coordinates":[-2.15364094127415,52.59228060690533],"type":"Point"}
}