{
  "type": "Feature",
  "properties": {
    "iso:country": "GB",
    "wof:name": "SP4 6GY",
    "wof:placetype": "postalcode"
  },
  "geometry": {"coordinates":[-1.785631,51.105979],"type":"Point"}
}
