{
  "type": "Feature",
  "properties": {
    "date:inception_lower":"2015-09-01",
    "date:inception_upper":"2015-09-30",
    "iso:country":"GB",
    "wof:name":"SP4 6GY",
    "wof:placetype":"postalcode"
},
  "geometry": {"coordinates":[-1.785631,51.105979],"type":"Point"}
}