{
  "type": "Feature",
  "properties": {
    "iso:country":"GB",
    "wof:name":"BD20 9HJ",
    "wof:placetype":"postalcode"
},
  "geometry": {"coordinates":[-1.96533655267518,53.92390061880622],"type":"Point"}
}