{
  "type": "Feature",
  "properties": {
    "iso:country":"GB",
    "wof:name":"KA6 7TZ",
    "wof:placetype":"postalcode"
},
  "geometry": {"coordinates":[-4.40004585086405,55.31107409096141],"type":"Point"}
}