{
  "type": "Feature",
  "properties": {
    "iso:country":"GB",
    "wof:name":"NW11 0DH",
    "wof:placetype":"postalcode"
},
  "geometry": {"coordinates":[-0.20146137025066,51.58456455475803],"type":"Point"}
}