{
  "type": "Feature",
  "properties": {
    "iso:country":"GB",
    "wof:name":"HA5 3BJ",
    "wof:placetype":"postalcode"
},
  "geometry": {"coordinates":[-0.3768237924772,51.59429655614515],"type":"Point"}
}