{
  "type": "Feature",
  "properties": {
    "iso:country": "GB",
    "wof:name": "AB42 4QN",
    "wof:placetype": "postalcode"
  },
  "geometry": {"coordinates":[-2.156324,57.534151],"type":"Point"}
}
