{
  "type": "Feature",
  "properties": {
    "iso:country":"GB",
    "wof:name":"TW1 1RH",
    "wof:placetype":"postalcode"
},
  "geometry": {"coordinates":[-0.32139781936214,51.45516156709652],"type":"Point"}
}