{
  "type": "Feature",
  "properties": {
    "iso:country":"GB",
    "wof:name":"SG10 6DA",
    "wof:placetype":"postalcode"
},
  "geometry": {"coordinates":[0.07254712027511,51.85637537329908],"type":"Point"}
}