{
  "type": "Feature",
  "properties": {
    "iso:country": "GB",
    "wof:name": "SG10 6DA",
    "wof:placetype": "postalcode"
  },
  "geometry": {"coordinates":[0.072547,51.856375],"type":"Point"}
}
