{
  "type": "Feature",
  "properties": {
    "iso:country":"GB",
    "wof:name":"LE12 5HZ",
    "wof:placetype":"postalcode"
},
  "geometry": {"coordinates":[-1.25364313109633,52.79107036191055],"type":"Point"}
}