{
  "type": "Feature",
  "properties": {
    "date:inception_lower": "2019-09-01",
    "date:inception_upper": "2019-09-01",
    "iso:country": "GB",
    "wof:name": "AL4 0LD",
    "wof:placetype": "postalcode"
  },
  "geometry": {"coordinates":[-0.299925,51.759901],"type":"Point"}
}
