{
  "type": "Feature",
  "properties": {
    "iso:country": "GB",
    "wof:name": "AL4 0LD",
    "wof:placetype": "postalcode"
  },
  "geometry": {"coordinates":[-0.299925,51.759901],"type":"Point"}
}
