{
  "type": "Feature",
  "properties": {
    "iso:country": "GB",
    "wof:name": "AL4 0LD",
    "wof:placetype": "postalcode"
  },
  "geometry": {"coordinates":[-0.300341,51.760401],"type":"Point"}
}
