{
  "type": "Feature",
  "properties": {
    "date:inception_lower": "1980-01-01",
    "date:inception_upper": "1980-01-01",
    "iso:country": "GB",
    "wof:name": "S2 4AN",
    "wof:placetype": "postalcode"
  },
  "geometry": {"coordinates":[-1.470346,53.373527],"type":"Point"}
}
