{
  "type": "Feature",
  "properties": {
    "date:inception_lower": "1980-01-01",
    "date:inception_upper": "1980-01-01",
    "iso:country": "GB",
    "wof:name": "EX4 9HW",
    "wof:placetype": "postalcode"
  },
  "geometry": {"coordinates":[-3.472897,50.744771],"type":"Point"}
}
