{
  "type": "Feature",
  "properties": {
    "iso:country":"GB",
    "wof:name":"EX4 9HW",
    "wof:placetype":"postalcode"
},
  "geometry": {"coordinates":[-3.47289674082751,50.74477089936866],"type":"Point"}
}