{
  "type": "Feature",
  "properties": {
    "iso:country": "GB",
    "wof:name": "TQ7 4HL",
    "wof:placetype": "postalcode"
  },
  "geometry": {"coordinates":[-3.894982,50.297926],"type":"Point"}
}
