{
  "type": "Feature",
  "properties": {
    "date:inception_lower": "2009-09-01",
    "date:inception_upper": "2009-09-01",
    "iso:country": "GB",
    "wof:name": "BN1 4ZB",
    "wof:placetype": "postalcode"
  },
  "geometry": {"coordinates":[-0.139206,50.831524],"type":"Point"}
}
