{
  "type": "Feature",
  "properties": {
    "iso:country":"GB",
    "wof:name":"AB44 1YA",
    "wof:placetype":"postalcode"
},
  "geometry": {"coordinates":[-2.49614301384544,57.6668868907027],"type":"Point"}
}