{
  "type": "Feature",
  "properties": {
    "date:inception_lower":"1990-08-01",
    "date:inception_upper":"1990-08-31",
    "iso:country":"GB",
    "wof:name":"AB44 1YA",
    "wof:placetype":"postalcode"
},
  "geometry": {"coordinates":[-2.496143,57.666887],"type":"Point"}
}