{
  "type": "Feature",
  "properties": {
    "iso:country":"GB",
    "wof:name":"NW8 7QE",
    "wof:placetype":"postalcode"
},
  "geometry": {"coordinates":[-0.16395644784885,51.53666571082818],"type":"Point"}
}