{
  "type": "Feature",
  "properties": {
    "iso:country":"GB",
    "wof:name":"W1G 8TG",
    "wof:placetype":"postalcode"
},
  "geometry": {"coordinates":[-0.14912155130825,51.51882532254326],"type":"Point"}
}