{
  "type": "Feature",
  "properties": {
    "iso:country":"GB",
    "wof:name":"TN5 6NL",
    "wof:placetype":"postalcode"
},
  "geometry": {"coordinates":[0.33651990933867,51.0336021648781],"type":"Point"}
}