{
  "type": "Feature",
  "properties": {
    "iso:country":"GB",
    "wof:name":"AB23 8JZ",
    "wof:placetype":"postalcode"
},
  "geometry": {"coordinates":[-2.09463751881024,57.18925848135975],"type":"Point"}
}