{
  "type": "Feature",
  "properties": {
    "date:inception_lower":"1990-12-01",
    "date:inception_upper":"1990-12-31",
    "iso:country":"GB",
    "wof:name":"AB23 8JZ",
    "wof:placetype":"postalcode"
},
  "geometry": {"coordinates":[-2.094637,57.189258],"type":"Point"}
}