{
  "type": "Feature",
  "properties": {
    "iso:country":"GB",
    "wof:name":"RG17 7LG",
    "wof:placetype":"postalcode"
},
  "geometry": {"coordinates":[-1.53243597048532,51.50197530731254],"type":"Point"}
}