{
  "type": "Feature",
  "properties": {
    "iso:country":"GB",
    "wof:name":"SK23 7HD",
    "wof:placetype":"postalcode"
},
  "geometry": {"coordinates":[-1.97627873348778,53.30805667185405],"type":"Point"}
}