{
  "type": "Feature",
  "properties": {
    "iso:country":"GB",
    "wof:name":"NR18 0LQ",
    "wof:placetype":"postalcode"
},
  "geometry": {"coordinates":[1.11274565822093,52.57671025830497],"type":"Point"}
}