{
  "type": "Feature",
  "properties": {
    "iso:country":"GB",
    "wof:name":"BB5 4DY",
    "wof:placetype":"postalcode"
},
  "geometry": {"coordinates":[-2.38426676254838,53.75720160541781],"type":"Point"}
}