{
  "type": "Feature",
  "properties": {
    "iso:country":"GB",
    "wof:name":"TR13 0PJ",
    "wof:placetype":"postalcode"
},
  "geometry": {"coordinates":[-5.24611681357726,50.11293210671695],"type":"Point"}
}