{
  "type": "Feature",
  "properties": {
    "iso:country":"GB",
    "wof:name":"B14 5PJ",
    "wof:placetype":"postalcode"
},
  "geometry": {"coordinates":[-1.90263599788397,52.40362411020076],"type":"Point"}
}