{
  "type": "Feature",
  "properties": {
    "date:inception_lower": "2019-01-01",
    "date:inception_upper": "2019-01-01",
    "iso:country": "GB",
    "wof:name": "PE14 8ET",
    "wof:placetype": "postalcode"
  },
  "geometry": {"coordinates":[0.245829,52.661174],"type":"Point"}
}
