{
  "type": "Feature",
  "properties": {
    "iso:country":"GB",
    "wof:name":"EX12 3DQ",
    "wof:placetype":"postalcode"
},
  "geometry": {"coordinates":[-3.13033962700318,50.69344144436447],"type":"Point"}
}