{
  "type": "Feature",
  "properties": {
    "iso:country": "GB",
    "wof:name": "HU3 5BW",
    "wof:placetype": "postalcode"
  },
  "geometry": {"coordinates":[-0.384657,53.738265],"type":"Point"}
}
