{
  "type": "Feature",
  "properties": {
    "iso:country": "GB",
    "wof:name": "NP26 3DR",
    "wof:placetype": "postalcode"
  },
  "geometry": {"coordinates":[-2.829921,51.561561],"type":"Point"}
}
