{
  "type": "Feature",
  "properties": {
    "iso:country":"GB",
    "wof:name":"NP26 3DR",
    "wof:placetype":"postalcode"
},
  "geometry": {"coordinates":[-2.82992062160283,51.56156090125921],"type":"Point"}
}