{
  "type": "Feature",
  "properties": {
    "date:inception_lower":"1980-01-01",
    "date:inception_upper":"1980-01-31",
    "iso:country":"GB",
    "wof:name":"CM9 6QS",
    "wof:placetype":"postalcode"
},
  "geometry": {"coordinates":[0.610639,51.755513],"type":"Point"}
}