{
  "type": "Feature",
  "properties": {
    "iso:country":"GB",
    "wof:name":"CM9 6QS",
    "wof:placetype":"postalcode"
},
  "geometry": {"coordinates":[0.61063894531812,51.75551280482419],"type":"Point"}
}