{
  "type": "Feature",
  "properties": {
    "iso:country": "GB",
    "wof:name": "CM9 6QS",
    "wof:placetype": "postalcode"
  },
  "geometry": {"coordinates":[0.610639,51.755513],"type":"Point"}
}
