{
  "type": "Feature",
  "properties": {
    "iso:country":"GB",
    "wof:name":"SK11 8XA",
    "wof:placetype":"postalcode"
},
  "geometry": {"coordinates":[-2.15497913369852,53.25203896745632],"type":"Point"}
}