{
  "type": "Feature",
  "properties": {
    "iso:country": "GB",
    "wof:name": "SK11 8XA",
    "wof:placetype": "postalcode"
  },
  "geometry": {"coordinates":[-2.154979,53.252039],"type":"Point"}
}
