{
  "type": "Feature",
  "properties": {
    "iso:country":"GB",
    "wof:name":"DE21 4PE",
    "wof:placetype":"postalcode"
},
  "geometry": {"coordinates":[-1.43285155936203,52.93938149946451],"type":"Point"}
}