{
  "type": "Feature",
  "properties": {
    "date:inception_lower": "2020-02-01",
    "date:inception_upper": "2020-02-01",
    "iso:country": "GB",
    "wof:name": "ME13 8GU",
    "wof:placetype": "postalcode"
  },
  "geometry": {"coordinates":[0.908829,51.311284],"type":"Point"}
}
