{
  "type": "Feature",
  "properties": {
    "iso:country":"GB",
    "wof:name":"SK3 0RW",
    "wof:placetype":"postalcode"
},
  "geometry": {"coordinates":[-2.18807362509475,53.398956262708],"type":"Point"}
}