{
  "type": "Feature",
  "properties": {
    "iso:country":"GB",
    "wof:name":"S80 1RY",
    "wof:placetype":"postalcode"
},
  "geometry": {"coordinates":[-1.12835622918109,53.30700682752744],"type":"Point"}
}