{
  "type": "Feature",
  "properties": {
    "iso:country": "GB",
    "wof:name": "TS17 9QN",
    "wof:placetype": "postalcode"
  },
  "geometry": {"coordinates":[-1.287661,54.537305],"type":"Point"}
}
