{
  "type": "Feature",
  "properties": {
    "iso:country":"GB",
    "wof:name":"BL6 4BT",
    "wof:placetype":"postalcode"
},
  "geometry": {"coordinates":[-2.5054853820878,53.57158431842819],"type":"Point"}
}