{
  "type": "Feature",
  "properties": {
    "iso:country": "GB",
    "wof:name": "PO12 3HE",
    "wof:placetype": "postalcode"
  },
  "geometry": {"coordinates":[-1.140498,50.800389],"type":"Point"}
}
