{
  "type": "Feature",
  "properties": {
    "iso:country": "GB",
    "wof:name": "PE21 8GE",
    "wof:placetype": "postalcode"
  },
  "geometry": {"coordinates":[-0.027922,52.969709],"type":"Point"}
}
