{
  "type": "Feature",
  "properties": {
    "date:inception_lower":"2009-04-01",
    "date:inception_upper":"2009-04-30",
    "iso:country":"GB",
    "wof:name":"PE21 8GE",
    "wof:placetype":"postalcode"
},
  "geometry": {"coordinates":[-0.027922,52.969709],"type":"Point"}
}