{
  "type": "Feature",
  "properties": {
    "iso:country":"GB",
    "wof:name":"ME10 4JU",
    "wof:placetype":"postalcode"
},
  "geometry": {"coordinates":[0.74941146942889,51.33347260036055],"type":"Point"}
}