{
  "type": "Feature",
  "properties": {
    "iso:country":"GB",
    "wof:name":"OX7 3TA",
    "wof:placetype":"postalcode"
},
  "geometry": {"coordinates":[-1.47783373462415,51.87183439398683],"type":"Point"}
}