{
  "type": "Feature",
  "properties": {
    "iso:country":"GB",
    "wof:name":"LS19 7AQ",
    "wof:placetype":"postalcode"
},
  "geometry": {"coordinates":[-1.6753879220054,53.86332984311658],"type":"Point"}
}