{
  "type": "Feature",
  "properties": {
    "iso:country": "GB",
    "wof:name": "DN6 0BF",
    "wof:placetype": "postalcode"
  },
  "geometry": {"coordinates":[-1.152341,53.618659],"type":"Point"}
}
