{
  "type": "Feature",
  "properties": {
    "iso:country":"GB",
    "wof:name":"SW17 9HP",
    "wof:placetype":"postalcode"
},
  "geometry": {"coordinates":[-0.16228149112367,51.41884632083416],"type":"Point"}
}