{
  "type": "Feature",
  "properties": {
    "iso:country":"GB",
    "wof:name":"ME7 2RE",
    "wof:placetype":"postalcode"
},
  "geometry": {"coordinates":[0.56699331605138,51.3903353456922],"type":"Point"}
}