{
  "type": "Feature",
  "properties": {
    "iso:country": "GB",
    "wof:name": "N17 6DB",
    "wof:placetype": "postalcode"
  },
  "geometry": {"coordinates":[-0.083081,51.589768],"type":"Point"}
}
