{
  "type": "Feature",
  "properties": {
    "iso:country":"GB",
    "wof:name":"N17 6DB",
    "wof:placetype":"postalcode"
},
  "geometry": {"coordinates":[-0.08308071277938,51.5897676900865],"type":"Point"}
}