{
  "type": "Feature",
  "properties": {
    "iso:country":"GB",
    "wof:name":"WA13 0LU",
    "wof:placetype":"postalcode"
},
  "geometry": {"coordinates":[-2.46422264817832,53.37634997439662],"type":"Point"}
}