{
  "type": "Feature",
  "properties": {
    "date:inception_lower":"2007-07-01",
    "date:inception_upper":"2007-07-31",
    "iso:country":"GB",
    "wof:name":"WA13 0LU",
    "wof:placetype":"postalcode"
},
  "geometry": {"coordinates":[-2.464223,53.37635],"type":"Point"}
}