{
  "type": "Feature",
  "properties": {
    "iso:country": "GB",
    "wof:name": "WA13 0LU",
    "wof:placetype": "postalcode"
  },
  "geometry": {"coordinates":[-2.464223,53.37635],"type":"Point"}
}
