{
  "type": "Feature",
  "properties": {
    "iso:country":"GB",
    "wof:name":"PE3 6JQ",
    "wof:placetype":"postalcode"
},
  "geometry": {"coordinates":[-0.26110157229296,52.5726221876205],"type":"Point"}
}