{
  "type": "Feature",
  "properties": {
    "date:inception_lower":"1980-01-01",
    "date:inception_upper":"1980-01-31",
    "iso:country":"GB",
    "wof:name":"CM20 3LY",
    "wof:placetype":"postalcode"
},
  "geometry": {"coordinates":[0.112341,51.771139],"type":"Point"}
}