{
  "type": "Feature",
  "properties": {
    "iso:country": "GB",
    "wof:name": "SR8 1HF",
    "wof:placetype": "postalcode"
  },
  "geometry": {"coordinates":[-1.347036,54.751303],"type":"Point"}
}
