{
  "type": "Feature",
  "properties": {
    "iso:country": "GB",
    "wof:name": "MK17 0FP",
    "wof:placetype": "postalcode"
  },
  "geometry": {"coordinates":[-0.869958,51.973108],"type":"Point"}
}
