{
  "type": "Feature",
  "properties": {
    "iso:country":"GB",
    "wof:name":"L30 5QL",
    "wof:placetype":"postalcode"
},
  "geometry": {"coordinates":[-2.97212721858617,53.48959143685368],"type":"Point"}
}