{
  "type": "Feature",
  "properties": {
    "iso:country":"GB",
    "wof:name":"TR26 1LF",
    "wof:placetype":"postalcode"
},
  "geometry": {"coordinates":[-5.47989909347181,50.21341836571483],"type":"Point"}
}