{
  "type": "Feature",
  "properties": {
    "date:inception_lower":"1980-01-01",
    "date:inception_upper":"1980-01-31",
    "iso:country":"GB",
    "wof:name":"BN18 0RB",
    "wof:placetype":"postalcode"
},
  "geometry": {"coordinates":[-0.634594,50.866521],"type":"Point"}
}