{
  "type": "Feature",
  "properties": {
    "iso:country": "GB",
    "wof:name": "B75 7HG",
    "wof:placetype": "postalcode"
  },
  "geometry": {"coordinates":[-1.792951,52.567694],"type":"Point"}
}
