{
  "type": "Feature",
  "properties": {
    "iso:country":"GB",
    "wof:name":"B75 7HG",
    "wof:placetype":"postalcode"
},
  "geometry": {"coordinates":[-1.79295089033203,52.56769383965568],"type":"Point"}
}