{
  "type": "Feature",
  "properties": {
    "date:inception_lower": "2024-03-01",
    "date:inception_upper": "2024-03-01",
    "iso:country": "GB",
    "wof:name": "RH11 9WA",
    "wof:placetype": "postalcode"
  },
  "geometry": {"coordinates":[-0.18551,51.084663],"type":"Point"}
}
