{
  "type": "Feature",
  "properties": {
    "iso:country": "GB",
    "wof:name": "PE6 9BG",
    "wof:placetype": "postalcode"
  },
  "geometry": {"coordinates":[-0.299478,52.662737],"type":"Point"}
}
