{
  "type": "Feature",
  "properties": {
    "iso:country":"GB",
    "wof:name":"PE6 9BG",
    "wof:placetype":"postalcode"
},
  "geometry": {"coordinates":[-0.29947805688244,52.66273677388659],"type":"Point"}
}