{
  "type": "Feature",
  "properties": {
    "iso:country":"GB",
    "wof:name":"KT1 1QY",
    "wof:placetype":"postalcode"
},
  "geometry": {"coordinates":[-0.30158903837397,51.41102912933486],"type":"Point"}
}