{
  "type": "Feature",
  "properties": {
    "iso:country": "GB",
    "wof:name": "TR7 2TA",
    "wof:placetype": "postalcode"
  },
  "geometry": {"coordinates":[-5.061227,50.411435],"type":"Point"}
}
