{
  "type": "Feature",
  "properties": {
    "iso:country":"GB",
    "wof:name":"TR7 2TA",
    "wof:placetype":"postalcode"
},
  "geometry": {"coordinates":[-5.06122721143775,50.41143529237632],"type":"Point"}
}