{
  "type": "Feature",
  "properties": {
    "date:inception_lower":"1994-12-01",
    "date:inception_upper":"1994-12-31",
    "iso:country":"GB",
    "wof:name":"TR15 2XG",
    "wof:placetype":"postalcode"
},
  "geometry": {"coordinates":[-5.224648,50.227574],"type":"Point"}
}