{
  "type": "Feature",
  "properties": {
    "iso:country":"GB",
    "wof:name":"TR15 2XG",
    "wof:placetype":"postalcode"
},
  "geometry": {"coordinates":[-5.22464831959525,50.22757425205278],"type":"Point"}
}