{
  "type": "Feature",
  "properties": {
    "iso:country": "GB",
    "wof:name": "TR15 2XG",
    "wof:placetype": "postalcode"
  },
  "geometry": {"coordinates":[-5.224648,50.227574],"type":"Point"}
}
