{
  "type": "Feature",
  "properties": {
    "iso:country":"GB",
    "wof:name":"DE24 8JW",
    "wof:placetype":"postalcode"
},
  "geometry": {"coordinates":[-1.44714764636877,52.89174205184528],"type":"Point"}
}