{
  "type": "Feature",
  "properties": {
    "iso:country": "GB",
    "wof:name": "CM9 8LY",
    "wof:placetype": "postalcode"
  },
  "geometry": {"coordinates":[0.731335,51.74667],"type":"Point"}
}
