{
  "type": "Feature",
  "properties": {
    "iso:country": "GB",
    "wof:name": "CM9 8LY",
    "wof:placetype": "postalcode"
  },
  "geometry": {"coordinates":[0.73162,51.746349],"type":"Point"}
}
