{
  "type": "Feature",
  "properties": {
    "iso:country":"GB",
    "wof:name":"CM9 8LY",
    "wof:placetype":"postalcode"
},
  "geometry": {"coordinates":[0.73130729988258,51.74666267334998],"type":"Point"}
}