{
  "type": "Feature",
  "properties": {
    "iso:country":"GB",
    "wof:name":"NE63 9SL",
    "wof:placetype":"postalcode"
},
  "geometry": {"coordinates":[-1.54087185835166,55.17319987793113],"type":"Point"}
}