{
  "type": "Feature",
  "properties": {
    "date:inception_lower": "1980-01-01",
    "date:inception_upper": "1980-01-01",
    "iso:country": "GB",
    "wof:name": "NE63 9SL",
    "wof:placetype": "postalcode"
  },
  "geometry": {"coordinates":[-1.540872,55.1732],"type":"Point"}
}
