{
  "type": "Feature",
  "properties": {
    "iso:country": "GB",
    "wof:name": "E16 1YU",
    "wof:placetype": "postalcode"
  },
  "geometry": {"coordinates":[0.012157,51.516594],"type":"Point"}
}
