{
  "type": "Feature",
  "properties": {
    "iso:country":"GB",
    "wof:name":"TA18 7RD",
    "wof:placetype":"postalcode"
},
  "geometry": {"coordinates":[-2.75185656852927,50.89439148852159],"type":"Point"}
}