{
  "type": "Feature",
  "properties": {
    "iso:country":"GB",
    "wof:name":"EN7 5QQ",
    "wof:placetype":"postalcode"
},
  "geometry": {"coordinates":[-0.06376030002934,51.70589327226291],"type":"Point"}
}