{
  "type": "Feature",
  "properties": {
    "iso:country": "GB",
    "wof:name": "OX16 1GW",
    "wof:placetype": "postalcode"
  },
  "geometry": {"coordinates":[-1.363386,52.079835],"type":"Point"}
}
