{
  "type": "Feature",
  "properties": {
    "date:inception_lower": "2022-04-01",
    "date:inception_upper": "2022-04-01",
    "iso:country": "GB",
    "wof:name": "CR3 5GF",
    "wof:placetype": "postalcode"
  },
  "geometry": {"coordinates":[-0.086671,51.296215],"type":"Point"}
}
