{
  "type": "Feature",
  "properties": {
    "iso:country": "GB",
    "wof:name": "EX8 2LD",
    "wof:placetype": "postalcode"
  },
  "geometry": {"coordinates":[-3.392894,50.623203],"type":"Point"}
}
