{
  "type": "Feature",
  "properties": {
    "iso:country":"GB",
    "wof:name":"EX8 2LD",
    "wof:placetype":"postalcode"
},
  "geometry": {"coordinates":[-3.39289369126662,50.62320327141464],"type":"Point"}
}