{
  "type": "Feature",
  "properties": {
    "date:inception_lower":"1998-12-01",
    "date:inception_upper":"1998-12-31",
    "iso:country":"GB",
    "wof:name":"EX8 2LD",
    "wof:placetype":"postalcode"
},
  "geometry": {"coordinates":[-3.392894,50.623203],"type":"Point"}
}