{
  "type": "Feature",
  "properties": {
    "iso:country":"GB",
    "wof:name":"HD1 6AR",
    "wof:placetype":"postalcode"
},
  "geometry": {"coordinates":[-1.7805013861451,53.65109968902748],"type":"Point"}
}