{
  "type": "Feature",
  "properties": {
    "iso:country":"GB",
    "wof:name":"OX11 9QG",
    "wof:placetype":"postalcode"
},
  "geometry": {"coordinates":[-1.23650083840065,51.57103395555112],"type":"Point"}
}