{
  "type": "Feature",
  "properties": {
    "iso:country":"GB",
    "wof:name":"DN2 4PW",
    "wof:placetype":"postalcode"
},
  "geometry": {"coordinates":[-1.09538190877001,53.5432578446796],"type":"Point"}
}