{
  "type": "Feature",
  "properties": {
    "iso:country": "GB",
    "wof:name": "SA44 5XB",
    "wof:placetype": "postalcode"
  },
  "geometry": {"coordinates":[-4.391458,52.016227],"type":"Point"}
}
