{
  "type": "Feature",
  "properties": {
    "iso:country":"GB",
    "wof:name":"HP4 2EQ",
    "wof:placetype":"postalcode"
},
  "geometry": {"coordinates":[-0.5553070766213,51.75894073322644],"type":"Point"}
}