{
  "type": "Feature",
  "properties": {
    "iso:country":"GB",
    "wof:name":"TD5 8AD",
    "wof:placetype":"postalcode"
},
  "geometry": {"coordinates":[-2.3586044449719,55.5219467191908],"type":"Point"}
}