{
  "type": "Feature",
  "properties": {
    "iso:country":"GB",
    "wof:name":"TW7 5HU",
    "wof:placetype":"postalcode"
},
  "geometry": {"coordinates":[-0.33206174856741,51.48047439170141],"type":"Point"}
}