{
  "type": "Feature",
  "properties": {
    "iso:country": "GB",
    "wof:name": "SG2 9GG",
    "wof:placetype": "postalcode"
  },
  "geometry": {"coordinates":[-0.175928,51.892519],"type":"Point"}
}
