{
  "type": "Feature",
  "properties": {
    "date:inception_lower": "1999-06-01",
    "date:inception_upper": "1999-06-01",
    "iso:country": "GB",
    "wof:name": "SG2 9GG",
    "wof:placetype": "postalcode"
  },
  "geometry": {"coordinates":[-0.175928,51.892519],"type":"Point"}
}
