{
  "type": "Feature",
  "properties": {
    "iso:country": "GB",
    "wof:name": "CM20 1AY",
    "wof:placetype": "postalcode"
  },
  "geometry": {"coordinates":[0.093885,51.77637],"type":"Point"}
}
