{
  "type": "Feature",
  "properties": {
    "date:inception_lower":"2009-12-01",
    "date:inception_upper":"2009-12-31",
    "iso:country":"GB",
    "wof:name":"CM20 1AY",
    "wof:placetype":"postalcode"
},
  "geometry": {"coordinates":[0.093885,51.77637],"type":"Point"}
}