{
  "type": "Feature",
  "properties": {
    "iso:country":"GB",
    "wof:name":"BA1 7ND",
    "wof:placetype":"postalcode"
},
  "geometry": {"coordinates":[-2.3155865638066,51.4055607905248],"type":"Point"}
}