{
  "type": "Feature",
  "properties": {
    "iso:country": "GB",
    "wof:name": "BL9 6RR",
    "wof:placetype": "postalcode"
  },
  "geometry": {"coordinates":[-2.294509,53.62089],"type":"Point"}
}
