{
  "type": "Feature",
  "properties": {
    "iso:country":"GB",
    "wof:name":"BL9 6RR",
    "wof:placetype":"postalcode"
},
  "geometry": {"coordinates":[-2.29450952606329,53.62088988951177],"type":"Point"}
}