{
  "type": "Feature",
  "properties": {
    "date:inception_lower":"2005-04-01",
    "date:inception_upper":"2005-04-30",
    "iso:country":"GB",
    "wof:name":"NR32 4XJ",
    "wof:placetype":"postalcode"
},
  "geometry": {"coordinates":[1.725395,52.496289],"type":"Point"}
}