{
  "type": "Feature",
  "properties": {
    "iso:country": "GB",
    "wof:name": "HG3 1FF",
    "wof:placetype": "postalcode"
  },
  "geometry": {"coordinates":[-1.569339,53.97989],"type":"Point"}
}
