{
  "type": "Feature",
  "properties": {
    "iso:country":"GB",
    "wof:name":"BB4 7BZ",
    "wof:placetype":"postalcode"
},
  "geometry": {"coordinates":[-2.25196824786271,53.68955804280231],"type":"Point"}
}