{
  "type": "Feature",
  "properties": {
    "iso:country": "GB",
    "wof:name": "SW15 2JN",
    "wof:placetype": "postalcode"
  },
  "geometry": {"coordinates":[-0.210699,51.458057],"type":"Point"}
}
