{
  "type": "Feature",
  "properties": {
    "iso:country":"GB",
    "wof:name":"SW15 2JN",
    "wof:placetype":"postalcode"
},
  "geometry": {"coordinates":[-0.21069933183858,51.45805656937089],"type":"Point"}
}