{
  "type": "Feature",
  "properties": {
    "date:inception_lower":"1980-01-01",
    "date:inception_upper":"1980-01-31",
    "iso:country":"GB",
    "wof:name":"ST4 3QJ",
    "wof:placetype":"postalcode"
},
  "geometry": {"coordinates":[-2.164207,52.996317],"type":"Point"}
}