{
  "type": "Feature",
  "properties": {
    "iso:country": "GB",
    "wof:name": "ST4 3QJ",
    "wof:placetype": "postalcode"
  },
  "geometry": {"coordinates":[-2.164207,52.996317],"type":"Point"}
}
