{
  "type": "Feature",
  "properties": {
    "iso:country":"GB",
    "wof:name":"BS16 1FT",
    "wof:placetype":"postalcode"
},
  "geometry": {"coordinates":[-2.56090916819472,51.49954964895885],"type":"Point"}
}