{
  "type": "Feature",
  "properties": {
    "date:inception_lower":"2010-01-01",
    "date:inception_upper":"2010-01-31",
    "iso:country":"GB",
    "wof:name":"BS16 1FT",
    "wof:placetype":"postalcode"
},
  "geometry": {"coordinates":[-2.560909,51.49955],"type":"Point"}
}