{
  "type": "Feature",
  "properties": {
    "iso:country": "GB",
    "wof:name": "BS16 1FT",
    "wof:placetype": "postalcode"
  },
  "geometry": {"coordinates":[-2.560909,51.49955],"type":"Point"}
}
