{
  "type": "Feature",
  "properties": {
    "iso:country":"GB",
    "wof:name":"PA1 3QA",
    "wof:placetype":"postalcode"
},
  "geometry": {"coordinates":[-4.41592397828217,55.84677998985946],"type":"Point"}
}