{
  "type": "Feature",
  "properties": {
    "date:inception_lower": "2007-07-01",
    "date:inception_upper": "2007-07-01",
    "iso:country": "GB",
    "wof:name": "NP7 6NJ",
    "wof:placetype": "postalcode"
  },
  "geometry": {"coordinates":[-3.005176,51.838746],"type":"Point"}
}
