{
  "type": "Feature",
  "properties": {
    "iso:country":"GB",
    "wof:name":"HA7 4XS",
    "wof:placetype":"postalcode"
},
  "geometry": {"coordinates":[-0.29691942960469,51.62229911167132],"type":"Point"}
}