{
  "type": "Feature",
  "properties": {
    "iso:country":"GB",
    "wof:name":"E3 3LG",
    "wof:placetype":"postalcode"
},
  "geometry": {"coordinates":[-0.01653727105739,51.51960773959981],"type":"Point"}
}