{
  "type": "Feature",
  "properties": {
    "iso:country": "GB",
    "wof:name": "E3 3LG",
    "wof:placetype": "postalcode"
  },
  "geometry": {"coordinates":[-0.016537,51.519608],"type":"Point"}
}
