{
  "type": "Feature",
  "properties": {
    "iso:country":"GB",
    "wof:name":"BD4 7JE",
    "wof:placetype":"postalcode"
},
  "geometry": {"coordinates":[-1.73645302614504,53.7809609897708],"type":"Point"}
}