{
  "type": "Feature",
  "properties": {
    "date:inception_lower":"1980-01-01",
    "date:inception_upper":"1980-01-31",
    "iso:country":"GB",
    "wof:name":"TQ4 6AD",
    "wof:placetype":"postalcode"
},
  "geometry": {"coordinates":[-3.562736,50.4356],"type":"Point"}
}