{
  "type": "Feature",
  "properties": {
    "iso:country":"GB",
    "wof:name":"TQ4 6AD",
    "wof:placetype":"postalcode"
},
  "geometry": {"coordinates":[-3.56273622713156,50.43560009449178],"type":"Point"}
}