{
  "type": "Feature",
  "properties": {
    "iso:country": "GB",
    "wof:name": "TQ4 6AD",
    "wof:placetype": "postalcode"
  },
  "geometry": {"coordinates":[-3.562736,50.4356],"type":"Point"}
}
