{
  "type": "Feature",
  "properties": {
    "date:inception_lower": "1996-06-01",
    "date:inception_upper": "1996-06-01",
    "iso:country": "GB",
    "wof:name": "WA2 0GX",
    "wof:placetype": "postalcode"
  },
  "geometry": {"coordinates":[-2.563797,53.41317],"type":"Point"}
}
