{
  "type": "Feature",
  "properties": {
    "iso:country":"GB",
    "wof:name":"WA2 0GX",
    "wof:placetype":"postalcode"
},
  "geometry": {"coordinates":[-2.56379753629025,53.41317015758003],"type":"Point"}
}