{
  "type": "Feature",
  "properties": {
    "iso:country":"GB",
    "wof:name":"LE5 2GT",
    "wof:placetype":"postalcode"
},
  "geometry": {"coordinates":[-1.06814479053767,52.63463801575386],"type":"Point"}
}