{
  "type": "Feature",
  "properties": {
    "date:inception_lower":"1980-01-01",
    "date:inception_upper":"1980-01-31",
    "iso:country":"GB",
    "wof:name":"LE5 2GT",
    "wof:placetype":"postalcode"
},
  "geometry": {"coordinates":[-1.068145,52.634638],"type":"Point"}
}