{
  "type": "Feature",
  "properties": {
    "iso:country":"GB",
    "wof:name":"TN12 7NN",
    "wof:placetype":"postalcode"
},
  "geometry": {"coordinates":[0.40245667834096,51.15309582837435],"type":"Point"}
}