{
  "type": "Feature",
  "properties": {
    "iso:country": "GB",
    "wof:name": "WF5 0LT",
    "wof:placetype": "postalcode"
  },
  "geometry": {"coordinates":[-1.561984,53.67093],"type":"Point"}
}
