{
  "type": "Feature",
  "properties": {
    "iso:country":"GB",
    "wof:name":"SO31 7FB",
    "wof:placetype":"postalcode"
},
  "geometry": {"coordinates":[-1.28577398661302,50.87693376534766],"type":"Point"}
}