{
  "type": "Feature",
  "properties": {
    "iso:country":"GB",
    "wof:name":"NP4 8RB",
    "wof:placetype":"postalcode"
},
  "geometry": {"coordinates":[-3.01160143082604,51.72449177708398],"type":"Point"}
}