{
  "type": "Feature",
  "properties": {
    "iso:country": "GB",
    "wof:name": "G31 5JX",
    "wof:placetype": "postalcode"
  },
  "geometry": {"coordinates":[-4.18311,55.852589],"type":"Point"}
}
