{
  "type": "Feature",
  "properties": {
    "iso:country":"GB",
    "wof:name":"CF42 5HL",
    "wof:placetype":"postalcode"
},
  "geometry": {"coordinates":[-3.52732165209901,51.67052424031986],"type":"Point"}
}