{
  "type": "Feature",
  "properties": {
    "iso:country": "GB",
    "wof:name": "YO14 0BX",
    "wof:placetype": "postalcode"
  },
  "geometry": {"coordinates":[-0.297256,54.20906],"type":"Point"}
}
