{
  "type": "Feature",
  "properties": {
    "iso:country":"GB",
    "wof:name":"YO14 0BX",
    "wof:placetype":"postalcode"
},
  "geometry": {"coordinates":[-0.29725576272502,54.20906001469523],"type":"Point"}
}