{
  "type": "Feature",
  "properties": {
    "iso:country":"GB",
    "wof:name":"DH6 4AY",
    "wof:placetype":"postalcode"
},
  "geometry": {"coordinates":[-1.49835326176509,54.71050463998456],"type":"Point"}
}