{
  "type": "Feature",
  "properties": {
    "iso:country": "GB",
    "wof:name": "HP9 2NU",
    "wof:placetype": "postalcode"
  },
  "geometry": {"coordinates":[-0.643708,51.6185],"type":"Point"}
}
