{
  "type": "Feature",
  "properties": {
    "iso:country":"GB",
    "wof:name":"CW8 3BT",
    "wof:placetype":"postalcode"
},
  "geometry": {"coordinates":[-2.56375389054739,53.25733189111606],"type":"Point"}
}