{
  "type": "Feature",
  "properties": {
    "iso:country": "GB",
    "wof:name": "E5 9GF",
    "wof:placetype": "postalcode"
  },
  "geometry": {"coordinates":[-0.050432,51.565004],"type":"Point"}
}
