{
  "type": "Feature",
  "properties": {
    "iso:country":"GB",
    "wof:name":"E5 9GF",
    "wof:placetype":"postalcode"
},
  "geometry": {"coordinates":[-0.0504317738217,51.56500400088851],"type":"Point"}
}