{
  "type": "Feature",
  "properties": {
    "iso:country": "GB",
    "wof:name": "CV32 7JE",
    "wof:placetype": "postalcode"
  },
  "geometry": {"coordinates":[-1.511291,52.309972],"type":"Point"}
}
