{
  "type": "Feature",
  "properties": {
    "iso:country":"GB",
    "wof:name":"CV32 7JE",
    "wof:placetype":"postalcode"
},
  "geometry": {"coordinates":[-1.51133148178875,52.309965921817],"type":"Point"}
}