{
  "type": "Feature",
  "properties": {
    "iso:country": "GB",
    "wof:name": "EH22 5PW",
    "wof:placetype": "postalcode"
  },
  "geometry": {"coordinates":[-3.043131,55.868762],"type":"Point"}
}
