{
  "type": "Feature",
  "properties": {
    "date:inception_lower": "1980-01-01",
    "date:inception_upper": "1980-01-01",
    "iso:country": "GB",
    "wof:name": "BA6 9DA",
    "wof:placetype": "postalcode"
  },
  "geometry": {"coordinates":[-2.715593,51.151405],"type":"Point"}
}
