{
  "type": "Feature",
  "properties": {
    "iso:country":"GB",
    "wof:name":"BA6 9DA",
    "wof:placetype":"postalcode"
},
  "geometry": {"coordinates":[-2.71559333219228,51.15140494994888],"type":"Point"}
}