{
  "type": "Feature",
  "properties": {
    "iso:country":"GB",
    "wof:name":"LA6 3LH",
    "wof:placetype":"postalcode"
},
  "geometry": {"coordinates":[-2.53420144206437,54.14265489897571],"type":"Point"}
}