{
  "type": "Feature",
  "properties": {
    "iso:country":"GB",
    "wof:name":"SA14 7DW",
    "wof:placetype":"postalcode"
},
  "geometry": {"coordinates":[-4.11223163992909,51.81301795454562],"type":"Point"}
}