{
  "type": "Feature",
  "properties": {
    "iso:country": "GB",
    "wof:name": "SA14 7DW",
    "wof:placetype": "postalcode"
  },
  "geometry": {"coordinates":[-4.112232,51.813018],"type":"Point"}
}
