{
  "type": "Feature",
  "properties": {
    "iso:country":"GB",
    "wof:name":"BR1 3PN",
    "wof:placetype":"postalcode"
},
  "geometry": {"coordinates":[0.01770743459705,51.41247740105837],"type":"Point"}
}