{
  "type": "Feature",
  "properties": {
    "date:inception_lower": "1998-12-01",
    "date:inception_upper": "1998-12-01",
    "iso:country": "GB",
    "wof:name": "M44 5XP",
    "wof:placetype": "postalcode"
  },
  "geometry": {"coordinates":[-2.43403,53.427124],"type":"Point"}
}
