{
  "type": "Feature",
  "properties": {
    "iso:country":"GB",
    "wof:name":"M44 5XP",
    "wof:placetype":"postalcode"
},
  "geometry": {"coordinates":[-2.43402989241979,53.42712353929046],"type":"Point"}
}