{
  "type": "Feature",
  "properties": {
    "iso:country":"GB",
    "wof:name":"KT18 6PN",
    "wof:placetype":"postalcode"
},
  "geometry": {"coordinates":[-0.28069549538266,51.27519713667252],"type":"Point"}
}