{
  "type": "Feature",
  "properties": {
    "iso:country":"GB",
    "wof:name":"CM0 7XG",
    "wof:placetype":"postalcode"
},
  "geometry": {"coordinates":[0.82955469903262,51.66227860174658],"type":"Point"}
}