{
  "type": "Feature",
  "properties": {
    "iso:country":"GB",
    "wof:name":"DD8 2QF",
    "wof:placetype":"postalcode"
},
  "geometry": {"coordinates":[-2.76512728829695,56.62617317133611],"type":"Point"}
}