{
  "type": "Feature",
  "properties": {
    "iso:country":"GB",
    "wof:name":"SE9 6AZ",
    "wof:placetype":"postalcode"
},
  "geometry": {"coordinates":[0.03373718400583,51.45480829483802],"type":"Point"}
}