{
  "type": "Feature",
  "properties": {
    "date:inception_lower": "2010-09-01",
    "date:inception_upper": "2010-09-01",
    "iso:country": "GB",
    "wof:name": "SE9 6AZ",
    "wof:placetype": "postalcode"
  },
  "geometry": {"coordinates":[0.033737,51.454808],"type":"Point"}
}
