{
  "type": "Feature",
  "properties": {
    "iso:country": "GB",
    "wof:name": "SE18 9LS",
    "wof:placetype": "postalcode"
  },
  "geometry": {"coordinates":[0.084874,51.490736],"type":"Point"}
}
