{
  "type": "Feature",
  "properties": {
    "iso:country":"GB",
    "wof:name":"CV10 0EH",
    "wof:placetype":"postalcode"
},
  "geometry": {"coordinates":[-1.46671745065003,52.53266575078815],"type":"Point"}
}