{
  "type": "Feature",
  "properties": {
    "date:inception_lower": "2010-02-01",
    "date:inception_upper": "2010-02-01",
    "iso:country": "GB",
    "wof:name": "CM16 6FJ",
    "wof:placetype": "postalcode"
  },
  "geometry": {"coordinates":[0.150987,51.722162],"type":"Point"}
}
