{
  "type": "Feature",
  "properties": {
    "iso:country": "GB",
    "wof:name": "CM16 6FJ",
    "wof:placetype": "postalcode"
  },
  "geometry": {"coordinates":[0.150987,51.722162],"type":"Point"}
}
