{
  "type": "Feature",
  "properties": {
    "iso:country": "GB",
    "wof:name": "PE21 7DX",
    "wof:placetype": "postalcode"
  },
  "geometry": {"coordinates":[-0.038469,52.948093],"type":"Point"}
}
