{
  "type": "Feature",
  "properties": {
    "iso:country":"GB",
    "wof:name":"PE21 7DX",
    "wof:placetype":"postalcode"
},
  "geometry": {"coordinates":[-0.03846869275338,52.94809302705508],"type":"Point"}
}