{
  "type": "Feature",
  "properties": {
    "iso:country": "GB",
    "wof:name": "DN15 8EJ",
    "wof:placetype": "postalcode"
  },
  "geometry": {"coordinates":[-0.67641,53.600049],"type":"Point"}
}
