{
  "type": "Feature",
  "properties": {
    "date:inception_lower":"1991-01-01",
    "date:inception_upper":"1991-01-31",
    "iso:country":"GB",
    "wof:name":"DN15 8EJ",
    "wof:placetype":"postalcode"
},
  "geometry": {"coordinates":[-0.67641,53.600049],"type":"Point"}
}