{
  "type": "Feature",
  "properties": {
    "date:inception_lower": "1980-01-01",
    "date:inception_upper": "1980-01-01",
    "iso:country": "GB",
    "wof:name": "PL26 8EH",
    "wof:placetype": "postalcode"
  },
  "geometry": {"coordinates":[-4.884495,50.38045],"type":"Point"}
}
