{
  "type": "Feature",
  "properties": {
    "iso:country": "GB",
    "wof:name": "OX29 4BT",
    "wof:placetype": "postalcode"
  },
  "geometry": {"coordinates":[-1.361124,51.775576],"type":"Point"}
}
