{
  "type": "Feature",
  "properties": {
    "iso:country":"GB",
    "wof:name":"DT4 8HQ",
    "wof:placetype":"postalcode"
},
  "geometry": {"coordinates":[-2.45449439986558,50.61131934078715],"type":"Point"}
}