{
  "type": "Feature",
  "properties": {
    "iso:country":"GB",
    "wof:name":"UB4 9LL",
    "wof:placetype":"postalcode"
},
  "geometry": {"coordinates":[-0.39736434241298,51.52997011086232],"type":"Point"}
}