{
  "type": "Feature",
  "properties": {
    "iso:country":"GB",
    "wof:name":"CB4 1PA",
    "wof:placetype":"postalcode"
},
  "geometry": {"coordinates":[0.14707603215831,52.21817814635438],"type":"Point"}
}