{
  "type": "Feature",
  "properties": {
    "iso:country":"GB",
    "wof:name":"PE20 2PH",
    "wof:placetype":"postalcode"
},
  "geometry": {"coordinates":[-0.12097043782688,52.9083572305678],"type":"Point"}
}