{
  "type": "Feature",
  "properties": {
    "date:inception_lower": "1980-01-01",
    "date:inception_upper": "1980-01-01",
    "iso:country": "GB",
    "wof:name": "PE20 2PH",
    "wof:placetype": "postalcode"
  },
  "geometry": {"coordinates":[-0.12097,52.908357],"type":"Point"}
}
