{
  "type": "Feature",
  "properties": {
    "iso:country": "GB",
    "wof:name": "TF1 5TG",
    "wof:placetype": "postalcode"
  },
  "geometry": {"coordinates":[-2.469666,52.705861],"type":"Point"}
}
