{
  "type": "Feature",
  "properties": {
    "date:inception_lower":"2014-11-01",
    "date:inception_upper":"2014-11-30",
    "iso:country":"GB",
    "wof:name":"TF1 5TG",
    "wof:placetype":"postalcode"
},
  "geometry": {"coordinates":[-2.469666,52.705861],"type":"Point"}
}