{
  "type": "Feature",
  "properties": {
    "iso:country":"GB",
    "wof:name":"TF1 5TG",
    "wof:placetype":"postalcode"
},
  "geometry": {"coordinates":[-2.46966642343972,52.70586127061149],"type":"Point"}
}