{
  "type": "Feature",
  "properties": {
    "iso:country": "GB",
    "wof:name": "PO38 1NR",
    "wof:placetype": "postalcode"
  },
  "geometry": {"coordinates":[-1.194066,50.599565],"type":"Point"}
}
