{
  "type": "Feature",
  "properties": {
    "date:inception_lower":"1980-01-01",
    "date:inception_upper":"1980-01-31",
    "iso:country":"GB",
    "wof:name":"PO38 1NR",
    "wof:placetype":"postalcode"
},
  "geometry": {"coordinates":[-1.194066,50.599565],"type":"Point"}
}