{
  "type": "Feature",
  "properties": {
    "iso:country":"GB",
    "wof:name":"PO38 1NR",
    "wof:placetype":"postalcode"
},
  "geometry": {"coordinates":[-1.19406622431215,50.599564808092],"type":"Point"}
}