{
  "type": "Feature",
  "properties": {
    "iso:country":"GB",
    "wof:name":"E17 7AP",
    "wof:placetype":"postalcode"
},
  "geometry": {"coordinates":[-0.03707544954389,51.58231678130168],"type":"Point"}
}