{
  "type": "Feature",
  "properties": {
    "date:inception_lower": "2002-11-01",
    "date:inception_upper": "2002-11-01",
    "iso:country": "GB",
    "wof:name": "SO41 3NE",
    "wof:placetype": "postalcode"
  },
  "geometry": {"coordinates":[-1.545789,50.752923],"type":"Point"}
}
