{
  "type": "Feature",
  "properties": {
    "iso:country":"GB",
    "wof:name":"SO41 3NE",
    "wof:placetype":"postalcode"
},
  "geometry": {"coordinates":[-1.54578867428155,50.7529229191568],"type":"Point"}
}