{
  "type": "Feature",
  "properties": {
    "iso:country":"GB",
    "wof:name":"NG5 8LJ",
    "wof:placetype":"postalcode"
},
  "geometry": {"coordinates":[-1.12290074490753,53.01382853923413],"type":"Point"}
}