{
  "type": "Feature",
  "properties": {
    "iso:country":"GB",
    "wof:name":"BH5 1NB",
    "wof:placetype":"postalcode"
},
  "geometry": {"coordinates":[-1.83358256542705,50.72498347355388],"type":"Point"}
}