{
  "type": "Feature",
  "properties": {
    "iso:country": "GB",
    "wof:name": "DT2 7AL",
    "wof:placetype": "postalcode"
  },
  "geometry": {"coordinates":[-2.481922,50.813762],"type":"Point"}
}
