{
  "type": "Feature",
  "properties": {
    "iso:country":"GB",
    "wof:name":"DT2 7AL",
    "wof:placetype":"postalcode"
},
  "geometry": {"coordinates":[-2.48192160802513,50.8137616614107],"type":"Point"}
}