{
  "type": "Feature",
  "properties": {
    "date:inception_lower": "1980-01-01",
    "date:inception_upper": "1980-01-01",
    "iso:country": "GB",
    "wof:name": "DT2 7AL",
    "wof:placetype": "postalcode"
  },
  "geometry": {"coordinates":[-2.482945,50.813874],"type":"Point"}
}
