{
  "type": "Feature",
  "properties": {
    "iso:country": "GB",
    "wof:name": "ST16 3SL",
    "wof:placetype": "postalcode"
  },
  "geometry": {"coordinates":[-2.089195,52.811028],"type":"Point"}
}
