{
  "type": "Feature",
  "properties": {
    "iso:country":"GB",
    "wof:name":"ST16 3SL",
    "wof:placetype":"postalcode"
},
  "geometry": {"coordinates":[-2.08919458394907,52.81102836001445],"type":"Point"}
}