{
  "type": "Feature",
  "properties": {
    "date:inception_lower": "2003-04-01",
    "date:inception_upper": "2003-04-01",
    "iso:country": "GB",
    "wof:name": "CV12 0PE",
    "wof:placetype": "postalcode"
  },
  "geometry": {"coordinates":[-1.511302,52.468956],"type":"Point"}
}
