{
  "type": "Feature",
  "properties": {
    "iso:country":"GB",
    "wof:name":"CV12 0PE",
    "wof:placetype":"postalcode"
},
  "geometry": {"coordinates":[-1.51132503928832,52.4689751974039],"type":"Point"}
}