{
  "type": "Feature",
  "properties": {
    "date:inception_lower": "1980-01-01",
    "date:inception_upper": "1980-01-01",
    "iso:country": "GB",
    "wof:name": "TN39 4NS",
    "wof:placetype": "postalcode"
  },
  "geometry": {"coordinates":[0.437157,50.85056],"type":"Point"}
}
