{
  "type": "Feature",
  "properties": {
    "date:inception_lower": "1992-08-01",
    "date:inception_upper": "1992-08-01",
    "iso:country": "GB",
    "wof:name": "TA8 1RF",
    "wof:placetype": "postalcode"
  },
  "geometry": {"coordinates":[-2.989813,51.233973],"type":"Point"}
}
