{
  "type": "Feature",
  "properties": {
    "iso:country":"GB",
    "wof:name":"SN11 9HE",
    "wof:placetype":"postalcode"
},
  "geometry": {"coordinates":[-2.02249301918012,51.46291874212231],"type":"Point"}
}