{
  "type": "Feature",
  "properties": {
    "date:inception_lower": "1980-01-01",
    "date:inception_upper": "1980-01-01",
    "iso:country": "GB",
    "wof:name": "SN11 9HE",
    "wof:placetype": "postalcode"
  },
  "geometry": {"coordinates":[-2.022486,51.462917],"type":"Point"}
}
