{
  "type": "Feature",
  "properties": {
    "iso:country": "GB",
    "wof:name": "PA45 7QL",
    "wof:placetype": "postalcode"
  },
  "geometry": {"coordinates":[-6.140284,55.815246],"type":"Point"}
}
