{
  "type": "Feature",
  "properties": {
    "iso:country":"GB",
    "wof:name":"PA45 7QL",
    "wof:placetype":"postalcode"
},
  "geometry": {"coordinates":[-6.14028397531285,55.8152463922933],"type":"Point"}
}