{
  "type": "Feature",
  "properties": {
    "date:inception_lower": "1986-07-01",
    "date:inception_upper": "1986-07-01",
    "iso:country": "GB",
    "wof:name": "ST7 2PA",
    "wof:placetype": "postalcode"
  },
  "geometry": {"coordinates":[-2.304821,53.095091],"type":"Point"}
}
