{
  "type": "Feature",
  "properties": {
    "iso:country": "GB",
    "wof:name": "ST7 2PA",
    "wof:placetype": "postalcode"
  },
  "geometry": {"coordinates":[-2.304821,53.095091],"type":"Point"}
}
