{
  "type": "Feature",
  "properties": {
    "iso:country":"GB",
    "wof:name":"ST7 2PA",
    "wof:placetype":"postalcode"
},
  "geometry": {"coordinates":[-2.30523207632502,53.09404673558128],"type":"Point"}
}