{
  "type": "Feature",
  "properties": {
    "iso:country":"GB",
    "wof:name":"BH12 4QN",
    "wof:placetype":"postalcode"
},
  "geometry": {"coordinates":[-1.94888484138057,50.74220377655392],"type":"Point"}
}