{
  "type": "Feature",
  "properties": {
    "date:inception_lower":"1995-07-01",
    "date:inception_upper":"1995-07-31",
    "iso:country":"GB",
    "wof:name":"BH12 4QN",
    "wof:placetype":"postalcode"
},
  "geometry": {"coordinates":[-1.948885,50.742204],"type":"Point"}
}