{
  "type": "Feature",
  "properties": {
    "date:inception_lower": "1980-01-01",
    "date:inception_upper": "1980-01-01",
    "iso:country": "GB",
    "wof:name": "WA7 3EX",
    "wof:placetype": "postalcode"
  },
  "geometry": {"coordinates":[-2.678646,53.312824],"type":"Point"}
}
