{
  "type": "Feature",
  "properties": {
    "iso:country": "GB",
    "wof:name": "CV22 5RG",
    "wof:placetype": "postalcode"
  },
  "geometry": {"coordinates":[-1.268695,52.354555],"type":"Point"}
}
