{
  "type": "Feature",
  "properties": {
    "iso:country":"GB",
    "wof:name":"HU8 9AG",
    "wof:placetype":"postalcode"
},
  "geometry": {"coordinates":[-0.29820090094806,53.76440191029781],"type":"Point"}
}