{
  "type": "Feature",
  "properties": {
    "date:inception_lower":"1987-10-01",
    "date:inception_upper":"1987-10-31",
    "iso:country":"GB",
    "wof:name":"TF3 5DH",
    "wof:placetype":"postalcode"
},
  "geometry": {"coordinates":[-2.466254,52.681441],"type":"Point"}
}