{
  "type": "Feature",
  "properties": {
    "iso:country":"GB",
    "wof:name":"LS9 6DP",
    "wof:placetype":"postalcode"
},
  "geometry": {"coordinates":[-1.51056434804301,53.80687487548259],"type":"Point"}
}