{
  "type": "Feature",
  "properties": {
    "date:inception_lower":"2014-04-01",
    "date:inception_upper":"2014-04-30",
    "iso:country":"GB",
    "wof:name":"CW5 7RY",
    "wof:placetype":"postalcode"
},
  "geometry": {"coordinates":[-2.501592,53.059923],"type":"Point"}
}