{
  "type": "Feature",
  "properties": {
    "iso:country":"GB",
    "wof:name":"CW5 7RY",
    "wof:placetype":"postalcode"
},
  "geometry": {"coordinates":[-2.50159180116523,53.0599232215646],"type":"Point"}
}