{
  "type": "Feature",
  "properties": {
    "iso:country": "GB",
    "wof:name": "CW5 7RY",
    "wof:placetype": "postalcode"
  },
  "geometry": {"coordinates":[-2.501592,53.059923],"type":"Point"}
}
