{
  "type": "Feature",
  "properties": {
    "iso:country": "GB",
    "wof:name": "PR3 0EB",
    "wof:placetype": "postalcode"
  },
  "geometry": {"coordinates":[-2.764215,53.875441],"type":"Point"}
}
