{
  "type": "Feature",
  "properties": {
    "iso:country":"GB",
    "wof:name":"PO5 4EX",
    "wof:placetype":"postalcode"
},
  "geometry": {"coordinates":[-1.09576368637652,50.79262309059193],"type":"Point"}
}