{
  "type": "Feature",
  "properties": {
    "iso:country": "GB",
    "wof:name": "PO5 4EX",
    "wof:placetype": "postalcode"
  },
  "geometry": {"coordinates":[-1.095764,50.792623],"type":"Point"}
}
