{
  "type": "Feature",
  "properties": {
    "date:inception_lower": "1998-06-01",
    "date:inception_upper": "1998-06-01",
    "iso:country": "GB",
    "wof:name": "PO5 4EX",
    "wof:placetype": "postalcode"
  },
  "geometry": {"coordinates":[-1.095764,50.792623],"type":"Point"}
}
