{
  "type": "Feature",
  "properties": {
    "date:inception_lower": "2012-12-01",
    "date:inception_upper": "2012-12-01",
    "iso:country": "GB",
    "wof:name": "BS16 4DX",
    "wof:placetype": "postalcode"
  },
  "geometry": {"coordinates":[-2.50845,51.471834],"type":"Point"}
}
