{
  "type": "Feature",
  "properties": {
    "iso:country":"GB",
    "wof:name":"BS16 4DX",
    "wof:placetype":"postalcode"
},
  "geometry": {"coordinates":[-2.50846479104933,51.47183405568872],"type":"Point"}
}