{
  "type": "Feature",
  "properties": {
    "iso:country": "GB",
    "wof:name": "GL6 6HB",
    "wof:placetype": "postalcode"
  },
  "geometry": {"coordinates":[-2.253531,51.751609],"type":"Point"}
}
