{
  "type": "Feature",
  "properties": {
    "iso:country":"GB",
    "wof:name":"GL6 6HB",
    "wof:placetype":"postalcode"
},
  "geometry": {"coordinates":[-2.25353132382542,51.75160930210754],"type":"Point"}
}