{
  "type": "Feature",
  "properties": {
    "iso:country":"GB",
    "wof:name":"PL15 7HT",
    "wof:placetype":"postalcode"
},
  "geometry": {"coordinates":[-4.40975109397426,50.62902378252388],"type":"Point"}
}