{
  "type": "Feature",
  "properties": {
    "date:inception_lower": "1980-01-01",
    "date:inception_upper": "1980-01-01",
    "iso:country": "GB",
    "wof:name": "EH48 4HD",
    "wof:placetype": "postalcode"
  },
  "geometry": {"coordinates":[-3.638867,55.903692],"type":"Point"}
}
