{
  "type": "Feature",
  "properties": {
    "iso:country":"GB",
    "wof:name":"WS13 8TQ",
    "wof:placetype":"postalcode"
},
  "geometry": {"coordinates":[-1.77265156183201,52.71294868899898],"type":"Point"}
}