{
  "type": "Feature",
  "properties": {
    "date:inception_lower":"2004-04-01",
    "date:inception_upper":"2004-04-30",
    "iso:country":"GB",
    "wof:name":"WS13 8TQ",
    "wof:placetype":"postalcode"
},
  "geometry": {"coordinates":[-1.772652,52.712949],"type":"Point"}
}