{
  "type": "Feature",
  "properties": {
    "iso:country":"GB",
    "wof:name":"G82 4NR",
    "wof:placetype":"postalcode"
},
  "geometry": {"coordinates":[-4.58596325904704,55.96967810656259],"type":"Point"}
}