{
  "type": "Feature",
  "properties": {
    "iso:country":"GB",
    "wof:name":"G77 6UD",
    "wof:placetype":"postalcode"
},
  "geometry": {"coordinates":[-4.34575900561247,55.77780937669593],"type":"Point"}
}