{
  "type": "Feature",
  "properties": {
    "date:inception_lower": "1989-07-01",
    "date:inception_upper": "1989-07-01",
    "iso:country": "GB",
    "wof:name": "G77 6UD",
    "wof:placetype": "postalcode"
  },
  "geometry": {"coordinates":[-4.345759,55.777809],"type":"Point"}
}
