{
  "type": "Feature",
  "properties": {
    "iso:country": "GB",
    "wof:name": "G77 6UD",
    "wof:placetype": "postalcode"
  },
  "geometry": {"coordinates":[-4.345759,55.777809],"type":"Point"}
}
