{
  "type": "Feature",
  "properties": {
    "iso:country":"GB",
    "wof:name":"L69 3GJ",
    "wof:placetype":"postalcode"
},
  "geometry": {"coordinates":[-2.96541334149826,53.40631020407375],"type":"Point"}
}