{
  "type": "Feature",
  "properties": {
    "iso:country": "GB",
    "wof:name": "L69 3GJ",
    "wof:placetype": "postalcode"
  },
  "geometry": {"coordinates":[-2.965428,53.406318],"type":"Point"}
}
