{
  "type": "Feature",
  "properties": {
    "iso:country": "GB",
    "wof:name": "BR3 4EQ",
    "wof:placetype": "postalcode"
  },
  "geometry": {"coordinates":[-0.051029,51.401366],"type":"Point"}
}
