{
  "type": "Feature",
  "properties": {
    "iso:country":"GB",
    "wof:name":"BR3 4EQ",
    "wof:placetype":"postalcode"
},
  "geometry": {"coordinates":[-0.0510295062877,51.40136563875144],"type":"Point"}
}