{
  "type": "Feature",
  "properties": {
    "iso:country":"GB",
    "wof:name":"SL2 2HH",
    "wof:placetype":"postalcode"
},
  "geometry": {"coordinates":[-0.63527317608016,51.53608990879576],"type":"Point"}
}