{
  "type": "Feature",
  "properties": {
    "date:inception_lower": "1980-01-01",
    "date:inception_upper": "1980-01-01",
    "iso:country": "GB",
    "wof:name": "SL2 2HH",
    "wof:placetype": "postalcode"
  },
  "geometry": {"coordinates":[-0.635273,51.53609],"type":"Point"}
}
