{
  "type": "Feature",
  "properties": {
    "date:inception_lower":"1980-01-01",
    "date:inception_upper":"1980-01-31",
    "iso:country":"GB",
    "wof:name":"NN16 9AJ",
    "wof:placetype":"postalcode"
},
  "geometry": {"coordinates":[-0.729855,52.413611],"type":"Point"}
}