{
  "type": "Feature",
  "properties": {
    "iso:country":"GB",
    "wof:name":"SY1 1RG",
    "wof:placetype":"postalcode"
},
  "geometry": {"coordinates":[-2.75835208317726,52.70797955882257],"type":"Point"}
}