{
  "type": "Feature",
  "properties": {
    "iso:country":"GB",
    "wof:name":"WA2 0PT",
    "wof:placetype":"postalcode"
},
  "geometry": {"coordinates":[-2.55412476165361,53.41208287956393],"type":"Point"}
}