{
  "type": "Feature",
  "properties": {
    "iso:country":"GB",
    "wof:name":"CH60 9HT",
    "wof:placetype":"postalcode"
},
  "geometry": {"coordinates":[-3.11601531168662,53.32964169740746],"type":"Point"}
}