{
  "type": "Feature",
  "properties": {
    "iso:country":"GB",
    "wof:name":"TR15 3BW",
    "wof:placetype":"postalcode"
},
  "geometry": {"coordinates":[-5.2407811911192,50.22621634098529],"type":"Point"}
}