{
  "type": "Feature",
  "properties": {
    "iso:country":"GB",
    "wof:name":"OX11 9NY",
    "wof:placetype":"postalcode"
},
  "geometry": {"coordinates":[-1.23434523011757,51.56621843526164],"type":"Point"}
}