{
  "type": "Feature",
  "properties": {
    "date:inception_lower": "2018-12-01",
    "date:inception_upper": "2018-12-01",
    "iso:country": "GB",
    "wof:name": "CV35 0FH",
    "wof:placetype": "postalcode"
  },
  "geometry": {"coordinates":[-1.506553,52.197743],"type":"Point"}
}
