{
  "type": "Feature",
  "properties": {
    "iso:country":"GB",
    "wof:name":"SO18 5FQ",
    "wof:placetype":"postalcode"
},
  "geometry": {"coordinates":[-1.34604721252394,50.91696183901077],"type":"Point"}
}