{
  "type": "Feature",
  "properties": {
    "date:inception_lower":"1980-01-01",
    "date:inception_upper":"1980-01-31",
    "iso:country":"GB",
    "wof:name":"MK44 3SN",
    "wof:placetype":"postalcode"
},
  "geometry": {"coordinates":[-0.412073,52.117135],"type":"Point"}
}