{
  "type": "Feature",
  "properties": {
    "iso:country":"GB",
    "wof:name":"MK44 3SN",
    "wof:placetype":"postalcode"
},
  "geometry": {"coordinates":[-0.4120725744027,52.117135306055],"type":"Point"}
}