{
  "type": "Feature",
  "properties": {
    "iso:country":"GB",
    "wof:name":"CT2 8HU",
    "wof:placetype":"postalcode"
},
  "geometry": {"coordinates":[1.05946179108201,51.29171668213684],"type":"Point"}
}