{
  "type": "Feature",
  "properties": {
    "date:inception_lower": "2022-09-01",
    "date:inception_upper": "2022-09-01",
    "iso:country": "GB",
    "wof:name": "ME3 9YB",
    "wof:placetype": "postalcode"
  },
  "geometry": {"coordinates":[0.5691,51.425365],"type":"Point"}
}
