{
  "type": "Feature",
  "properties": {
    "date:inception_lower": "1980-01-01",
    "date:inception_upper": "1980-01-01",
    "iso:country": "GB",
    "wof:name": "B32 2BU",
    "wof:placetype": "postalcode"
  },
  "geometry": {"coordinates":[-1.978352,52.456757],"type":"Point"}
}
