{
  "type": "Feature",
  "properties": {
    "date:inception_lower": "2010-05-01",
    "date:inception_upper": "2010-05-01",
    "iso:country": "GB",
    "wof:name": "SY4 3JR",
    "wof:placetype": "postalcode"
  },
  "geometry": {"coordinates":[-2.720503,52.8146],"type":"Point"}
}
