{
  "type": "Feature",
  "properties": {
    "iso:country":"GB",
    "wof:name":"SY4 3JR",
    "wof:placetype":"postalcode"
},
  "geometry": {"coordinates":[-2.72050264445997,52.81460000106056],"type":"Point"}
}