{
  "type": "Feature",
  "properties": {
    "iso:country": "GB",
    "wof:name": "SY4 3JR",
    "wof:placetype": "postalcode"
  },
  "geometry": {"coordinates":[-2.720503,52.8146],"type":"Point"}
}
