{
  "type": "Feature",
  "properties": {
    "iso:country":"GB",
    "wof:name":"WA15 7UG",
    "wof:placetype":"postalcode"
},
  "geometry": {"coordinates":[-2.31899577722951,53.39747353006689],"type":"Point"}
}