{
  "type": "Feature",
  "properties": {
    "date:inception_lower": "2007-02-01",
    "date:inception_upper": "2007-02-01",
    "iso:country": "GB",
    "wof:name": "DN4 9EU",
    "wof:placetype": "postalcode"
  },
  "geometry": {"coordinates":[-1.157353,53.493455],"type":"Point"}
}
