{
  "type": "Feature",
  "properties": {
    "iso:country":"GB",
    "wof:name":"DN4 9EU",
    "wof:placetype":"postalcode"
},
  "geometry": {"coordinates":[-1.15735312486624,53.49345481935097],"type":"Point"}
}