{
  "type": "Feature",
  "properties": {
    "iso:country":"GB",
    "wof:name":"B26 2NP",
    "wof:placetype":"postalcode"
},
  "geometry": {"coordinates":[-1.79331520680876,52.46488578011525],"type":"Point"}
}