{
  "type": "Feature",
  "properties": {
    "iso:country": "GB",
    "wof:name": "B26 2NP",
    "wof:placetype": "postalcode"
  },
  "geometry": {"coordinates":[-1.793315,52.464886],"type":"Point"}
}
