{
  "type": "Feature",
  "properties": {
    "date:inception_lower": "2021-07-01",
    "date:inception_upper": "2021-07-01",
    "iso:country": "GB",
    "wof:name": "NW10 6FP",
    "wof:placetype": "postalcode"
  },
  "geometry": {"coordinates":[-0.249069,51.527142],"type":"Point"}
}
