{
  "type": "Feature",
  "properties": {
    "iso:country":"GB",
    "wof:name":"SP2 9BJ",
    "wof:placetype":"postalcode"
},
  "geometry": {"coordinates":[-1.82097482848073,51.07752981382578],"type":"Point"}
}