{
  "type": "Feature",
  "properties": {
    "iso:country": "GB",
    "wof:name": "SP2 9BJ",
    "wof:placetype": "postalcode"
  },
  "geometry": {"coordinates":[-1.820975,51.07753],"type":"Point"}
}
