{
  "type": "Feature",
  "properties": {
    "iso:country":"GB",
    "wof:name":"BN7 9TL",
    "wof:placetype":"postalcode"
},
  "geometry": {"coordinates":[0.01201510285296,50.87332556580501],"type":"Point"}
}