{
  "type": "Feature",
  "properties": {
    "date:inception_lower":"1980-01-01",
    "date:inception_upper":"1980-01-31",
    "iso:country":"GB",
    "wof:name":"IP28 6JL",
    "wof:placetype":"postalcode"
},
  "geometry": {"coordinates":[0.693937,52.277227],"type":"Point"}
}