{
  "type": "Feature",
  "properties": {
    "iso:country":"GB",
    "wof:name":"IP28 6JL",
    "wof:placetype":"postalcode"
},
  "geometry": {"coordinates":[0.69393652583183,52.27722700811427],"type":"Point"}
}