{
  "type": "Feature",
  "properties": {
    "date:inception_lower": "1992-01-01",
    "date:inception_upper": "1992-01-01",
    "iso:country": "GB",
    "wof:name": "SS5 6PJ",
    "wof:placetype": "postalcode"
  },
  "geometry": {"coordinates":[0.615621,51.629765],"type":"Point"}
}
