{
  "type": "Feature",
  "properties": {
    "iso:country": "GB",
    "wof:name": "SS5 6PJ",
    "wof:placetype": "postalcode"
  },
  "geometry": {"coordinates":[0.615621,51.629765],"type":"Point"}
}
