{
  "type": "Feature",
  "properties": {
    "iso:country":"GB",
    "wof:name":"AB33 8UD",
    "wof:placetype":"postalcode"
},
  "geometry": {"coordinates":[-2.6954538659904,57.23193245499117],"type":"Point"}
}