{
  "type": "Feature",
  "properties": {
    "date:inception_lower": "1996-06-01",
    "date:inception_upper": "1996-06-01",
    "iso:country": "GB",
    "wof:name": "AB33 8UD",
    "wof:placetype": "postalcode"
  },
  "geometry": {"coordinates":[-2.695454,57.231932],"type":"Point"}
}
