{
  "type": "Feature",
  "properties": {
    "date:inception_lower": "2016-10-01",
    "date:inception_upper": "2016-10-01",
    "iso:country": "GB",
    "wof:name": "EH11 1FL",
    "wof:placetype": "postalcode"
  },
  "geometry": {"coordinates":[-3.214553,55.941016],"type":"Point"}
}
