{
  "type": "Feature",
  "properties": {
    "date:inception_lower": "1986-05-01",
    "date:inception_upper": "1986-05-01",
    "iso:country": "GB",
    "wof:name": "TD6 9RF",
    "wof:placetype": "postalcode"
  },
  "geometry": {"coordinates":[-2.721961,55.596245],"type":"Point"}
}
