{
  "type": "Feature",
  "properties": {
    "iso:country": "GB",
    "wof:name": "TD6 9RF",
    "wof:placetype": "postalcode"
  },
  "geometry": {"coordinates":[-2.721961,55.596245],"type":"Point"}
}
