{
  "type": "Feature",
  "properties": {
    "iso:country": "GB",
    "wof:name": "PO33 2TL",
    "wof:placetype": "postalcode"
  },
  "geometry": {"coordinates":[-1.164939,50.72277],"type":"Point"}
}
