{
  "type": "Feature",
  "properties": {
    "iso:country":"GB",
    "wof:name":"PO33 2TL",
    "wof:placetype":"postalcode"
},
  "geometry": {"coordinates":[-1.16493923424524,50.72276996366057],"type":"Point"}
}