{
  "type": "Feature",
  "properties": {
    "date:inception_lower": "1980-01-01",
    "date:inception_upper": "1980-01-01",
    "iso:country": "GB",
    "wof:name": "RH7 6DZ",
    "wof:placetype": "postalcode"
  },
  "geometry": {"coordinates":[-0.009046,51.180593],"type":"Point"}
}
