{
  "type": "Feature",
  "properties": {
    "iso:country":"GB",
    "wof:name":"RH7 6DZ",
    "wof:placetype":"postalcode"
},
  "geometry": {"coordinates":[-0.00904639261055,51.18059296654876],"type":"Point"}
}