{
  "type": "Feature",
  "properties": {
    "date:inception_lower": "1980-01-01",
    "date:inception_upper": "1980-01-01",
    "iso:country": "GB",
    "wof:name": "GL5 5PH",
    "wof:placetype": "postalcode"
  },
  "geometry": {"coordinates":[-2.235658,51.724206],"type":"Point"}
}
