{
  "type": "Feature",
  "properties": {
    "iso:country":"GB",
    "wof:name":"GL5 5PH",
    "wof:placetype":"postalcode"
},
  "geometry": {"coordinates":[-2.23565760207373,51.72420565287387],"type":"Point"}
}