{
  "type": "Feature",
  "properties": {
    "iso:country":"GB",
    "wof:name":"PL19 0LT",
    "wof:placetype":"postalcode"
},
  "geometry": {"coordinates":[-4.14900692163211,50.6121190502786],"type":"Point"}
}