{
  "type": "Feature",
  "properties": {
    "date:inception_lower": "1995-07-01",
    "date:inception_upper": "1995-07-01",
    "iso:country": "GB",
    "wof:name": "RG41 2RN",
    "wof:placetype": "postalcode"
  },
  "geometry": {"coordinates":[-0.847239,51.408017],"type":"Point"}
}
