{
  "type": "Feature",
  "properties": {
    "iso:country":"GB",
    "wof:name":"RG41 2RN",
    "wof:placetype":"postalcode"
},
  "geometry": {"coordinates":[-0.84723930535876,51.40801696315991],"type":"Point"}
}