{
  "type": "Feature",
  "properties": {
    "date:inception_lower": "2020-11-01",
    "date:inception_upper": "2020-11-01",
    "iso:country": "GB",
    "wof:name": "CO7 7GE",
    "wof:placetype": "postalcode"
  },
  "geometry": {"coordinates":[0.993725,51.879243],"type":"Point"}
}
