{
  "type": "Feature",
  "properties": {
    "iso:country": "GB",
    "wof:name": "BA12 7AG",
    "wof:placetype": "postalcode"
  },
  "geometry": {"coordinates":[-2.139442,51.172701],"type":"Point"}
}
