{
  "type": "Feature",
  "properties": {
    "iso:country":"GB",
    "wof:name":"BA12 7AG",
    "wof:placetype":"postalcode"
},
  "geometry": {"coordinates":[-2.13944190830131,51.17270089603829],"type":"Point"}
}