{
  "type": "Feature",
  "properties": {
    "iso:country":"GB",
    "wof:name":"KA7 2AR",
    "wof:placetype":"postalcode"
},
  "geometry": {"coordinates":[-4.63642513801971,55.45835403089059],"type":"Point"}
}