{
  "type": "Feature",
  "properties": {
    "iso:country":"GB",
    "wof:name":"TS14 8HE",
    "wof:placetype":"postalcode"
},
  "geometry": {"coordinates":[-1.10440805354151,54.52593214334353],"type":"Point"}
}