{
  "type": "Feature",
  "properties": {
    "iso:country":"GB",
    "wof:name":"G31 1ST",
    "wof:placetype":"postalcode"
},
  "geometry": {"coordinates":[-4.22362134314411,55.85779483593093],"type":"Point"}
}