{
  "type": "Feature",
  "properties": {
    "date:inception_lower": "1980-01-01",
    "date:inception_upper": "1980-01-01",
    "iso:country": "GB",
    "wof:name": "G31 1ST",
    "wof:placetype": "postalcode"
  },
  "geometry": {"coordinates":[-4.223621,55.857795],"type":"Point"}
}
