{
  "type": "Feature",
  "properties": {
    "iso:country":"GB",
    "wof:name":"CR5 3EA",
    "wof:placetype":"postalcode"
},
  "geometry": {"coordinates":[-0.14423966464592,51.31026284579338],"type":"Point"}
}