{
  "type": "Feature",
  "properties": {
    "iso:country":"GB",
    "wof:name":"CO9 1YB",
    "wof:placetype":"postalcode"
},
  "geometry": {"coordinates":[0.64131153709631,51.93593201187863],"type":"Point"}
}