{
  "type": "Feature",
  "properties": {
    "iso:country": "GB",
    "wof:name": "PL25 4PH",
    "wof:placetype": "postalcode"
  },
  "geometry": {"coordinates":[-4.785002,50.346492],"type":"Point"}
}
