{
  "type": "Feature",
  "properties": {
    "iso:country":"GB",
    "wof:name":"S81 8LL",
    "wof:placetype":"postalcode"
},
  "geometry": {"coordinates":[-1.1700988407863,53.32369130836186],"type":"Point"}
}