{
  "type": "Feature",
  "properties": {
    "date:inception_lower": "2006-01-01",
    "date:inception_upper": "2006-01-01",
    "iso:country": "GB",
    "wof:name": "DN7 4BF",
    "wof:placetype": "postalcode"
  },
  "geometry": {"coordinates":[-1.019055,53.58031],"type":"Point"}
}
