{
  "type": "Feature",
  "properties": {
    "iso:country":"GB",
    "wof:name":"DN7 4BF",
    "wof:placetype":"postalcode"
},
  "geometry": {"coordinates":[-1.01905475604862,53.58030993868413],"type":"Point"}
}