{
  "type": "Feature",
  "properties": {
    "date:inception_lower": "1995-07-01",
    "date:inception_upper": "1995-07-01",
    "iso:country": "GB",
    "wof:name": "CF83 1AQ",
    "wof:placetype": "postalcode"
  },
  "geometry": {"coordinates":[-3.229265,51.576022],"type":"Point"}
}
