{
  "type": "Feature",
  "properties": {
    "iso:country":"GB",
    "wof:name":"WA2 8EF",
    "wof:placetype":"postalcode"
},
  "geometry": {"coordinates":[-2.57704533759518,53.40602377785618],"type":"Point"}
}