{
  "type": "Feature",
  "properties": {
    "iso:country":"GB",
    "wof:name":"SS8 9FG",
    "wof:placetype":"postalcode"
},
  "geometry": {"coordinates":[0.57479592747702,51.53373708528747],"type":"Point"}
}