{
  "type": "Feature",
  "properties": {
    "date:inception_lower": "1990-02-01",
    "date:inception_upper": "1990-02-01",
    "iso:country": "GB",
    "wof:name": "SS8 9FG",
    "wof:placetype": "postalcode"
  },
  "geometry": {"coordinates":[0.574737,51.533742],"type":"Point"}
}
