{
  "type": "Feature",
  "properties": {
    "date:inception_lower": "1980-01-01",
    "date:inception_upper": "1980-01-01",
    "iso:country": "GB",
    "wof:name": "NE48 2AE",
    "wof:placetype": "postalcode"
  },
  "geometry": {"coordinates":[-2.253976,55.144086],"type":"Point"}
}
