{
  "type": "Feature",
  "properties": {
    "iso:country":"GB",
    "wof:name":"NE48 2AE",
    "wof:placetype":"postalcode"
},
  "geometry": {"coordinates":[-2.25407680178554,55.14400055881516],"type":"Point"}
}