{
  "type": "Feature",
  "properties": {
    "iso:country": "GB",
    "wof:name": "TF3 5HD",
    "wof:placetype": "postalcode"
  },
  "geometry": {"coordinates":[-2.476854,52.685003],"type":"Point"}
}
