{
  "type": "Feature",
  "properties": {
    "date:inception_lower":"1992-08-01",
    "date:inception_upper":"1992-08-31",
    "iso:country":"GB",
    "wof:name":"TF3 5HD",
    "wof:placetype":"postalcode"
},
  "geometry": {"coordinates":[-2.476854,52.685003],"type":"Point"}
}