{
  "type": "Feature",
  "properties": {
    "iso:country":"GB",
    "wof:name":"TF3 5HD",
    "wof:placetype":"postalcode"
},
  "geometry": {"coordinates":[-2.47685383455353,52.68500340629517],"type":"Point"}
}