{
  "type": "Feature",
  "properties": {
    "iso:country":"GB",
    "wof:name":"SG13 8SL",
    "wof:placetype":"postalcode"
},
  "geometry": {"coordinates":[-0.06978743597073,51.78526832311784],"type":"Point"}
}