{
  "type": "Feature",
  "properties": {
    "date:inception_lower":"1991-01-01",
    "date:inception_upper":"1991-01-31",
    "iso:country":"GB",
    "wof:name":"ST10 4LD",
    "wof:placetype":"postalcode"
},
  "geometry": {"coordinates":[-1.981384,52.950827],"type":"Point"}
}