{
  "type": "Feature",
  "properties": {
    "iso:country":"GB",
    "wof:name":"ST10 4LD",
    "wof:placetype":"postalcode"
},
  "geometry": {"coordinates":[-1.98138401030996,52.95082700116583],"type":"Point"}
}