{
  "type": "Feature",
  "properties": {
    "date:inception_lower": "2023-04-01",
    "date:inception_upper": "2023-04-01",
    "iso:country": "GB",
    "wof:name": "G75 7AH",
    "wof:placetype": "postalcode"
  },
  "geometry": {"coordinates":[-4.228716,55.742128],"type":"Point"}
}
