{
  "type": "Feature",
  "properties": {
    "iso:country": "GB",
    "wof:name": "NE33 2PU",
    "wof:placetype": "postalcode"
  },
  "geometry": {"coordinates":[-1.429491,54.997311],"type":"Point"}
}
