{
  "type": "Feature",
  "properties": {
    "date:inception_lower":"1994-12-01",
    "date:inception_upper":"1994-12-31",
    "iso:country":"GB",
    "wof:name":"NE33 2PU",
    "wof:placetype":"postalcode"
},
  "geometry": {"coordinates":[-1.429491,54.997311],"type":"Point"}
}