{
  "type": "Feature",
  "properties": {
    "iso:country":"GB",
    "wof:name":"BA1 1DX",
    "wof:placetype":"postalcode"
},
  "geometry": {"coordinates":[-2.36102893426075,51.3834359091253],"type":"Point"}
}