{
  "type": "Feature",
  "properties": {
    "iso:country": "GB",
    "wof:name": "SE5 8FF",
    "wof:placetype": "postalcode"
  },
  "geometry": {"coordinates":[-0.081536,51.473929],"type":"Point"}
}
