{
  "type": "Feature",
  "properties": {
    "iso:country": "GB",
    "wof:name": "SL3 0QR",
    "wof:placetype": "postalcode"
  },
  "geometry": {"coordinates":[-0.512651,51.473012],"type":"Point"}
}
