{
  "type": "Feature",
  "properties": {
    "date:inception_lower": "1991-09-01",
    "date:inception_upper": "1991-09-01",
    "iso:country": "GB",
    "wof:name": "SL3 0QR",
    "wof:placetype": "postalcode"
  },
  "geometry": {"coordinates":[-0.512651,51.473012],"type":"Point"}
}
