{
  "type": "Feature",
  "properties": {
    "iso:country": "GB",
    "wof:name": "DE74 2FR",
    "wof:placetype": "postalcode"
  },
  "geometry": {"coordinates":[-1.272808,52.840193],"type":"Point"}
}
