{
  "type": "Feature",
  "properties": {
    "iso:country":"GB",
    "wof:name":"DE74 2FR",
    "wof:placetype":"postalcode"
},
  "geometry": {"coordinates":[-1.27265071474758,52.84018188211452],"type":"Point"}
}