{
  "type": "Feature",
  "properties": {
    "iso:country":"GB",
    "wof:name":"CO6 4TB",
    "wof:placetype":"postalcode"
},
  "geometry": {"coordinates":[0.930294965057,51.99151355055294],"type":"Point"}
}