{
  "type": "Feature",
  "properties": {
    "iso:country": "GB",
    "wof:name": "NE33 2RY",
    "wof:placetype": "postalcode"
  },
  "geometry": {"coordinates":[-1.424611,54.996443],"type":"Point"}
}
