{
  "type": "Feature",
  "properties": {
    "iso:country":"GB",
    "wof:name":"NE33 2RY",
    "wof:placetype":"postalcode"
},
  "geometry": {"coordinates":[-1.42461084591002,54.99644297478708],"type":"Point"}
}