{
  "type": "Feature",
  "properties": {
    "date:inception_lower": "2021-08-01",
    "date:inception_upper": "2021-08-01",
    "iso:country": "GB",
    "wof:name": "YO22 4FQ",
    "wof:placetype": "postalcode"
  },
  "geometry": {"coordinates":[-0.580537,54.449265],"type":"Point"}
}
