{
  "type": "Feature",
  "properties": {
    "date:inception_lower": "1980-01-01",
    "date:inception_upper": "1980-01-01",
    "iso:country": "GB",
    "wof:name": "NR12 7AQ",
    "wof:placetype": "postalcode"
  },
  "geometry": {"coordinates":[1.376094,52.724353],"type":"Point"}
}
