{
  "type": "Feature",
  "properties": {
    "iso:country":"GB",
    "wof:name":"FK1 2QZ",
    "wof:placetype":"postalcode"
},
  "geometry": {"coordinates":[-3.77152509404613,55.98611036741028],"type":"Point"}
}