{
  "type": "Feature",
  "properties": {
    "date:inception_lower": "1980-01-01",
    "date:inception_upper": "1980-01-01",
    "iso:country": "GB",
    "wof:name": "KT23 4HW",
    "wof:placetype": "postalcode"
  },
  "geometry": {"coordinates":[-0.389568,51.265442],"type":"Point"}
}
