{
  "type": "Feature",
  "properties": {
    "iso:country":"GB",
    "wof:name":"KT23 4HW",
    "wof:placetype":"postalcode"
},
  "geometry": {"coordinates":[-0.38956801512811,51.26544167973227],"type":"Point"}
}