{
  "type": "Feature",
  "properties": {
    "date:inception_lower": "1980-01-01",
    "date:inception_upper": "1980-01-01",
    "iso:country": "GB",
    "wof:name": "DD6 9BY",
    "wof:placetype": "postalcode"
  },
  "geometry": {"coordinates":[-2.87939,56.447726],"type":"Point"}
}
