{
  "type": "Feature",
  "properties": {
    "iso:country":"GB",
    "wof:name":"RM7 9DA",
    "wof:placetype":"postalcode"
},
  "geometry": {"coordinates":[0.16939851565473,51.57304268760897],"type":"Point"}
}