{
  "type": "Feature",
  "properties": {
    "date:inception_lower": "1980-01-01",
    "date:inception_upper": "1980-01-01",
    "iso:country": "GB",
    "wof:name": "CT19 5HH",
    "wof:placetype": "postalcode"
  },
  "geometry": {"coordinates":[1.167746,51.084435],"type":"Point"}
}
