{
  "type": "Feature",
  "properties": {
    "iso:country": "GB",
    "wof:name": "CT19 5HH",
    "wof:placetype": "postalcode"
  },
  "geometry": {"coordinates":[1.167746,51.084435],"type":"Point"}
}
