{
  "type": "Feature",
  "properties": {
    "iso:country":"GB",
    "wof:name":"CF15 8FX",
    "wof:placetype":"postalcode"
},
  "geometry": {"coordinates":[-3.24346249186139,51.51086093355556],"type":"Point"}
}