{
  "type": "Feature",
  "properties": {
    "iso:country":"GB",
    "wof:name":"BR6 8NQ",
    "wof:placetype":"postalcode"
},
  "geometry": {"coordinates":[0.05014841298295,51.36420696562773],"type":"Point"}
}