{
  "type": "Feature",
  "properties": {
    "date:inception_lower":"1980-01-01",
    "date:inception_upper":"1980-01-31",
    "iso:country":"GB",
    "wof:name":"BR6 8NQ",
    "wof:placetype":"postalcode"
},
  "geometry": {"coordinates":[0.050148,51.364207],"type":"Point"}
}