{
  "type": "Feature",
  "properties": {
    "iso:country":"GB",
    "wof:name":"PL6 7DF",
    "wof:placetype":"postalcode"
},
  "geometry": {"coordinates":[-4.11358717138389,50.43855981753347],"type":"Point"}
}