{
  "type": "Feature",
  "properties": {
    "date:inception_lower": "1980-01-01",
    "date:inception_upper": "1980-01-01",
    "iso:country": "GB",
    "wof:name": "PL6 7DF",
    "wof:placetype": "postalcode"
  },
  "geometry": {"coordinates":[-4.113587,50.43856],"type":"Point"}
}
