{
  "type": "Feature",
  "properties": {
    "date:inception_lower": "1983-03-01",
    "date:inception_upper": "1983-03-01",
    "iso:country": "GB",
    "wof:name": "E14 7BW",
    "wof:placetype": "postalcode"
  },
  "geometry": {"coordinates":[-0.02849,51.516518],"type":"Point"}
}
