{
  "type": "Feature",
  "properties": {
    "iso:country":"GB",
    "wof:name":"E14 7BW",
    "wof:placetype":"postalcode"
},
  "geometry": {"coordinates":[-0.02849040756442,51.51651796675412],"type":"Point"}
}