{
  "type": "Feature",
  "properties": {
    "iso:country":"GB",
    "wof:name":"RG21 4BP",
    "wof:placetype":"postalcode"
},
  "geometry": {"coordinates":[-1.07671803563911,51.26385743265419],"type":"Point"}
}