{
  "type": "Feature",
  "properties": {
    "date:inception_lower":"1980-01-01",
    "date:inception_upper":"1980-01-31",
    "iso:country":"GB",
    "wof:name":"ST4 2BQ",
    "wof:placetype":"postalcode"
},
  "geometry": {"coordinates":[-2.176542,53.010547],"type":"Point"}
}