{
  "type": "Feature",
  "properties": {
    "iso:country":"GB",
    "wof:name":"ST4 2BQ",
    "wof:placetype":"postalcode"
},
  "geometry": {"coordinates":[-2.1765417866433,53.01054704970455],"type":"Point"}
}