{
  "type": "Feature",
  "properties": {
    "iso:country":"GB",
    "wof:name":"DA3 7HE",
    "wof:placetype":"postalcode"
},
  "geometry": {"coordinates":[0.33588697856576,51.39388580246714],"type":"Point"}
}