{
  "type": "Feature",
  "properties": {
    "iso:country":"GB",
    "wof:name":"TW7 5BT",
    "wof:placetype":"postalcode"
},
  "geometry": {"coordinates":[-0.3213510871385,51.4803665217146],"type":"Point"}
}