{
  "type": "Feature",
  "properties": {
    "date:inception_lower": "1980-01-01",
    "date:inception_upper": "1980-01-01",
    "iso:country": "GB",
    "wof:name": "EX23 8LN",
    "wof:placetype": "postalcode"
  },
  "geometry": {"coordinates":[-4.548529,50.825713],"type":"Point"}
}
