{
  "type": "Feature",
  "properties": {
    "iso:country":"GB",
    "wof:name":"EX23 8LN",
    "wof:placetype":"postalcode"
},
  "geometry": {"coordinates":[-4.54849574403404,50.82571894787738],"type":"Point"}
}