{
  "type": "Feature",
  "properties": {
    "iso:country":"GB",
    "wof:name":"TA14 6SX",
    "wof:placetype":"postalcode"
},
  "geometry": {"coordinates":[-2.75180113234819,50.93860808848712],"type":"Point"}
}