{
  "type": "Feature",
  "properties": {
    "date:inception_lower":"1980-01-01",
    "date:inception_upper":"1980-01-31",
    "iso:country":"GB",
    "wof:name":"TA14 6SX",
    "wof:placetype":"postalcode"
},
  "geometry": {"coordinates":[-2.751801,50.938608],"type":"Point"}
}