{
  "type": "Feature",
  "properties": {
    "date:inception_lower": "1999-12-01",
    "date:inception_upper": "1999-12-01",
    "iso:country": "GB",
    "wof:name": "SM6 7EX",
    "wof:placetype": "postalcode"
  },
  "geometry": {"coordinates":[-0.15165,51.373986],"type":"Point"}
}
