{
  "type": "Feature",
  "properties": {
    "iso:country":"GB",
    "wof:name":"PH3 1LD",
    "wof:placetype":"postalcode"
},
  "geometry": {"coordinates":[-3.73615004200959,56.33023878867935],"type":"Point"}
}