{
  "type": "Feature",
  "properties": {
    "iso:country":"GB",
    "wof:name":"GL12 7AS",
    "wof:placetype":"postalcode"
},
  "geometry": {"coordinates":[-2.35857314890061,51.63856788966194],"type":"Point"}
}