{
  "type": "Feature",
  "properties": {
    "iso:country": "GB",
    "wof:name": "EH32 0LA",
    "wof:placetype": "postalcode"
  },
  "geometry": {"coordinates":[-2.895215,55.975678],"type":"Point"}
}
