{
  "type": "Feature",
  "properties": {
    "iso:country":"GB",
    "wof:name":"EH32 0LA",
    "wof:placetype":"postalcode"
},
  "geometry": {"coordinates":[-2.8952149439117,55.97567840540101],"type":"Point"}
}