{
  "type": "Feature",
  "properties": {
    "iso:country": "GB",
    "wof:name": "WF13 2AB",
    "wof:placetype": "postalcode"
  },
  "geometry": {"coordinates":[-1.632145,53.696423],"type":"Point"}
}
