{
  "type": "Feature",
  "properties": {
    "iso:country":"GB",
    "wof:name":"TD13 5YB",
    "wof:placetype":"postalcode"
},
  "geometry": {"coordinates":[-2.36538177726529,55.93068794490552],"type":"Point"}
}