{
  "type": "Feature",
  "properties": {
    "iso:country":"GB",
    "wof:name":"GL7 4FD",
    "wof:placetype":"postalcode"
},
  "geometry": {"coordinates":[-1.77223135989528,51.67088659953771],"type":"Point"}
}