{
  "type": "Feature",
  "properties": {
    "iso:country": "GB",
    "wof:name": "GL7 4FD",
    "wof:placetype": "postalcode"
  },
  "geometry": {"coordinates":[-1.772161,51.670944],"type":"Point"}
}
