{
  "type": "Feature",
  "properties": {
    "iso:country":"GB",
    "wof:name":"EN9 3RD",
    "wof:placetype":"postalcode"
},
  "geometry": {"coordinates":[0.04233236682761,51.67990684462696],"type":"Point"}
}