{
  "type": "Feature",
  "properties": {
    "iso:country": "GB",
    "wof:name": "WR4 0DR",
    "wof:placetype": "postalcode"
  },
  "geometry": {"coordinates":[-2.179273,52.209743],"type":"Point"}
}
