{
  "type": "Feature",
  "properties": {
    "iso:country":"GB",
    "wof:name":"WR4 0DR",
    "wof:placetype":"postalcode"
},
  "geometry": {"coordinates":[-2.17927260391397,52.20974316561679],"type":"Point"}
}