{
  "type": "Feature",
  "properties": {
    "iso:country": "GB",
    "wof:name": "DE1 3RG",
    "wof:placetype": "postalcode"
  },
  "geometry": {"coordinates":[-1.470371,52.931428],"type":"Point"}
}
