{
  "type": "Feature",
  "properties": {
    "iso:country": "GB",
    "wof:name": "BL8 3LW",
    "wof:placetype": "postalcode"
  },
  "geometry": {"coordinates":[-2.334418,53.614691],"type":"Point"}
}
