{
  "type": "Feature",
  "properties": {
    "date:inception_lower": "1990-02-01",
    "date:inception_upper": "1990-02-01",
    "iso:country": "GB",
    "wof:name": "BL8 3LW",
    "wof:placetype": "postalcode"
  },
  "geometry": {"coordinates":[-2.334418,53.614691],"type":"Point"}
}
