{
  "type": "Feature",
  "properties": {
    "iso:country":"GB",
    "wof:name":"BL1 2AN",
    "wof:placetype":"postalcode"
},
  "geometry": {"coordinates":[-2.42931288199215,53.58007947568161],"type":"Point"}
}