{
  "type": "Feature",
  "properties": {
    "iso:country": "GB",
    "wof:name": "WS15 1ST",
    "wof:placetype": "postalcode"
  },
  "geometry": {"coordinates":[-1.929388,52.750721],"type":"Point"}
}
