{
  "type": "Feature",
  "properties": {
    "iso:country": "GB",
    "wof:name": "SR7 8RS",
    "wof:placetype": "postalcode"
  },
  "geometry": {"coordinates":[-1.355333,54.802122],"type":"Point"}
}
