{
  "type": "Feature",
  "properties": {
    "iso:country":"GB",
    "wof:name":"TW14 8DZ",
    "wof:placetype":"postalcode"
},
  "geometry": {"coordinates":[-0.44225207582141,51.4485836216444],"type":"Point"}
}