{
  "type": "Feature",
  "properties": {
    "date:inception_lower": "1980-01-01",
    "date:inception_upper": "1980-01-01",
    "iso:country": "GB",
    "wof:name": "FK4 1AL",
    "wof:placetype": "postalcode"
  },
  "geometry": {"coordinates":[-3.881659,56.00299],"type":"Point"}
}
