{
  "type": "Feature",
  "properties": {
    "iso:country":"GB",
    "wof:name":"FK4 1AL",
    "wof:placetype":"postalcode"
},
  "geometry": {"coordinates":[-3.88165885218747,56.00299029498763],"type":"Point"}
}