{
  "type": "Feature",
  "properties": {
    "iso:country": "GB",
    "wof:name": "BL5 3NH",
    "wof:placetype": "postalcode"
  },
  "geometry": {"coordinates":[-2.551613,53.57236],"type":"Point"}
}
