{
  "type": "Feature",
  "properties": {
    "iso:country":"GB",
    "wof:name":"RG4 8EA",
    "wof:placetype":"postalcode"
},
  "geometry": {"coordinates":[-0.96493505289699,51.46599791279311],"type":"Point"}
}