{
  "type": "Feature",
  "properties": {
    "iso:country":"GB",
    "wof:name":"PO2 8HP",
    "wof:placetype":"postalcode"
},
  "geometry": {"coordinates":[-1.08195993556173,50.81574363310094],"type":"Point"}
}