{
  "type": "Feature",
  "properties": {
    "iso:country":"GB",
    "wof:name":"CT1 3EY",
    "wof:placetype":"postalcode"
},
  "geometry": {"coordinates":[1.09302750141667,51.26948985523865],"type":"Point"}
}