{
  "type": "Feature",
  "properties": {
    "date:inception_lower":"1980-01-01",
    "date:inception_upper":"1980-01-31",
    "iso:country":"GB",
    "wof:name":"GU9 0AD",
    "wof:placetype":"postalcode"
},
  "geometry": {"coordinates":[-0.803899,51.217803],"type":"Point"}
}