{
  "type": "Feature",
  "properties": {
    "iso:country":"GB",
    "wof:name":"GU9 0AD",
    "wof:placetype":"postalcode"
},
  "geometry": {"coordinates":[-0.80389952035473,51.21780280938889],"type":"Point"}
}