{
  "type": "Feature",
  "properties": {
    "date:inception_lower": "1996-12-01",
    "date:inception_upper": "1996-12-01",
    "iso:country": "GB",
    "wof:name": "E4 8YD",
    "wof:placetype": "postalcode"
  },
  "geometry": {"coordinates":[-0.025041,51.607851],"type":"Point"}
}
