{
  "type": "Feature",
  "properties": {
    "iso:country": "GB",
    "wof:name": "E4 8YD",
    "wof:placetype": "postalcode"
  },
  "geometry": {"coordinates":[-0.025041,51.607851],"type":"Point"}
}
