{
  "type": "Feature",
  "properties": {
    "iso:country":"GB",
    "wof:name":"SW11 6RZ",
    "wof:placetype":"postalcode"
},
  "geometry": {"coordinates":[-0.1623223145705,51.45726328813895],"type":"Point"}
}