{
  "type": "Feature",
  "properties": {
    "iso:country": "GB",
    "wof:name": "BN15 9NW",
    "wof:placetype": "postalcode"
  },
  "geometry": {"coordinates":[-0.330851,50.832553],"type":"Point"}
}
