{
  "type": "Feature",
  "properties": {
    "iso:country":"GB",
    "wof:name":"SW15 2RT",
    "wof:placetype":"postalcode"
},
  "geometry": {"coordinates":[-0.20633200876869,51.45783696147075],"type":"Point"}
}