{
  "type": "Feature",
  "properties": {
    "iso:country":"GB",
    "wof:name":"SN3 3RA",
    "wof:placetype":"postalcode"
},
  "geometry": {"coordinates":[-1.74626047554721,51.56979821084468],"type":"Point"}
}