{
  "type": "Feature",
  "properties": {
    "date:inception_lower": "1995-01-01",
    "date:inception_upper": "1995-01-01",
    "iso:country": "GB",
    "wof:name": "SN3 3RA",
    "wof:placetype": "postalcode"
  },
  "geometry": {"coordinates":[-1.74626,51.569798],"type":"Point"}
}
