{
  "type": "Feature",
  "properties": {
    "date:inception_lower": "1993-02-01",
    "date:inception_upper": "1993-02-01",
    "iso:country": "GB",
    "wof:name": "DD10 9HN",
    "wof:placetype": "postalcode"
  },
  "geometry": {"coordinates":[-2.483441,56.7431],"type":"Point"}
}
