{
  "type": "Feature",
  "properties": {
    "date:inception_lower": "1980-01-01",
    "date:inception_upper": "1980-01-01",
    "iso:country": "GB",
    "wof:name": "FY2 9TS",
    "wof:placetype": "postalcode"
  },
  "geometry": {"coordinates":[-3.046007,53.838301],"type":"Point"}
}
