{
  "type": "Feature",
  "properties": {
    "iso:country":"GB",
    "wof:name":"TR8 4WD",
    "wof:placetype":"postalcode"
},
  "geometry": {"coordinates":[-5.03005994504177,50.40172723882119],"type":"Point"}
}