{
  "type": "Feature",
  "properties": {
    "date:inception_lower": "2014-06-01",
    "date:inception_upper": "2014-06-01",
    "iso:country": "GB",
    "wof:name": "TR8 4WD",
    "wof:placetype": "postalcode"
  },
  "geometry": {"coordinates":[-5.03006,50.401727],"type":"Point"}
}
