{
  "type": "Feature",
  "properties": {
    "iso:country":"GB",
    "wof:name":"TN5 6UQ",
    "wof:placetype":"postalcode"
},
  "geometry": {"coordinates":[0.33297493198045,51.06694976552073],"type":"Point"}
}