{
  "type": "Feature",
  "properties": {
    "iso:country":"GB",
    "wof:name":"HU19 2PJ",
    "wof:placetype":"postalcode"
},
  "geometry": {"coordinates":[0.03955167232298,53.71976443357946],"type":"Point"}
}