{
  "type": "Feature",
  "properties": {
    "iso:country": "GB",
    "wof:name": "EN6 1QD",
    "wof:placetype": "postalcode"
  },
  "geometry": {"coordinates":[-0.190477,51.697096],"type":"Point"}
}
