{
  "type": "Feature",
  "properties": {
    "iso:country":"GB",
    "wof:name":"EN6 1QD",
    "wof:placetype":"postalcode"
},
  "geometry": {"coordinates":[-0.19047719785309,51.69709586573239],"type":"Point"}
}