{
  "type": "Feature",
  "properties": {
    "iso:country":"GB",
    "wof:name":"SS14 2SX",
    "wof:placetype":"postalcode"
},
  "geometry": {"coordinates":[0.4802358157912,51.58103832177768],"type":"Point"}
}