{
  "type": "Feature",
  "properties": {
    "iso:country": "GB",
    "wof:name": "TA12 6NL",
    "wof:placetype": "postalcode"
  },
  "geometry": {"coordinates":[-2.758622,50.970307],"type":"Point"}
}
