{
  "type": "Feature",
  "properties": {
    "iso:country":"GB",
    "wof:name":"HD4 6UH",
    "wof:placetype":"postalcode"
},
  "geometry": {"coordinates":[-1.75091952908525,53.6107656025578],"type":"Point"}
}