{
  "type": "Feature",
  "properties": {
    "date:inception_lower":"1980-01-01",
    "date:inception_upper":"1980-01-31",
    "iso:country":"GB",
    "wof:name":"LA2 0DY",
    "wof:placetype":"postalcode"
},
  "geometry": {"coordinates":[-2.83858,53.969601],"type":"Point"}
}