{
  "type": "Feature",
  "properties": {
    "iso:country":"GB",
    "wof:name":"LA2 0DY",
    "wof:placetype":"postalcode"
},
  "geometry": {"coordinates":[-2.83858050500222,53.96960127930264],"type":"Point"}
}