{
  "type": "Feature",
  "properties": {
    "iso:country":"GB",
    "wof:name":"HU13 0LL",
    "wof:placetype":"postalcode"
},
  "geometry": {"coordinates":[-0.45406377770855,53.73159990852074],"type":"Point"}
}