{
  "type": "Feature",
  "properties": {
    "date:inception_lower": "1997-12-01",
    "date:inception_upper": "1997-12-01",
    "iso:country": "GB",
    "wof:name": "HU13 0LL",
    "wof:placetype": "postalcode"
  },
  "geometry": {"coordinates":[-0.454064,53.7316],"type":"Point"}
}
