{
  "type": "Feature",
  "properties": {
    "date:inception_lower": "2024-01-01",
    "date:inception_upper": "2024-01-01",
    "iso:country": "GB",
    "wof:name": "BS3 1GE",
    "wof:placetype": "postalcode"
  },
  "geometry": {"coordinates":[-2.597475,51.442288],"type":"Point"}
}
