{
  "type": "Feature",
  "properties": {
    "iso:country":"GB",
    "wof:name":"EH6 8BA",
    "wof:placetype":"postalcode"
},
  "geometry": {"coordinates":[-3.15972864007614,55.96925000500845],"type":"Point"}
}