{
  "type": "Feature",
  "properties": {
    "iso:country": "GB",
    "wof:name": "AB56 5EU",
    "wof:placetype": "postalcode"
  },
  "geometry": {"coordinates":[-3.005618,57.618777],"type":"Point"}
}
