{
  "type": "Feature",
  "properties": {
    "iso:country":"GB",
    "wof:name":"TS6 6QJ",
    "wof:placetype":"postalcode"
},
  "geometry": {"coordinates":[-1.17004131776406,54.57713253812536],"type":"Point"}
}