{
  "type": "Feature",
  "properties": {
    "iso:country": "GB",
    "wof:name": "TS6 6QJ",
    "wof:placetype": "postalcode"
  },
  "geometry": {"coordinates":[-1.170041,54.577133],"type":"Point"}
}
