{
  "type": "Feature",
  "properties": {
    "iso:country":"GB",
    "wof:name":"RH12 5JG",
    "wof:placetype":"postalcode"
},
  "geometry": {"coordinates":[-0.30169701873535,51.08564770022218],"type":"Point"}
}