{
  "type": "Feature",
  "properties": {
    "date:inception_lower": "1980-01-01",
    "date:inception_upper": "1980-01-01",
    "iso:country": "GB",
    "wof:name": "BS5 7NN",
    "wof:placetype": "postalcode"
  },
  "geometry": {"coordinates":[-2.537689,51.460635],"type":"Point"}
}
