{
  "type": "Feature",
  "properties": {
    "iso:country":"GB",
    "wof:name":"NG8 1AB",
    "wof:placetype":"postalcode"
},
  "geometry": {"coordinates":[-1.19041768756305,52.95035630902195],"type":"Point"}
}