{
  "type": "Feature",
  "properties": {
    "iso:country": "GB",
    "wof:name": "SW16 3LZ",
    "wof:placetype": "postalcode"
  },
  "geometry": {"coordinates":[-0.11444,51.413743],"type":"Point"}
}
