{
  "type": "Feature",
  "properties": {
    "iso:country":"GB",
    "wof:name":"HR4 8LH",
    "wof:placetype":"postalcode"
},
  "geometry": {"coordinates":[-2.7849796850649,52.10201362298347],"type":"Point"}
}