{
  "type": "Feature",
  "properties": {
    "iso:country": "GB",
    "wof:name": "HR4 8LH",
    "wof:placetype": "postalcode"
  },
  "geometry": {"coordinates":[-2.78498,52.102014],"type":"Point"}
}
