{
  "type": "Feature",
  "properties": {
    "iso:country": "GB",
    "wof:name": "CM19 4HU",
    "wof:placetype": "postalcode"
  },
  "geometry": {"coordinates":[0.077272,51.757777],"type":"Point"}
}
