{
  "type": "Feature",
  "properties": {
    "iso:country":"GB",
    "wof:name":"NG11 7BZ",
    "wof:placetype":"postalcode"
},
  "geometry": {"coordinates":[-1.16039006267403,52.92073431619091],"type":"Point"}
}