{
  "type": "Feature",
  "properties": {
    "date:inception_lower": "1980-01-01",
    "date:inception_upper": "1980-01-01",
    "iso:country": "GB",
    "wof:name": "NG11 7BZ",
    "wof:placetype": "postalcode"
  },
  "geometry": {"coordinates":[-1.16039,52.920734],"type":"Point"}
}
