{
  "type": "Feature",
  "properties": {
    "iso:country":"GB",
    "wof:name":"TW11 0RW",
    "wof:placetype":"postalcode"
},
  "geometry": {"coordinates":[-0.34713706639389,51.43113991699563],"type":"Point"}
}