{
  "type": "Feature",
  "properties": {
    "iso:country":"GB",
    "wof:name":"NR14 7FB",
    "wof:placetype":"postalcode"
},
  "geometry": {"coordinates":[1.42723730012669,52.60715919813823],"type":"Point"}
}