{
  "type": "Feature",
  "properties": {
    "iso:country": "GB",
    "wof:name": "NR14 7FB",
    "wof:placetype": "postalcode"
  },
  "geometry": {"coordinates":[1.427237,52.607159],"type":"Point"}
}
