{
  "type": "Feature",
  "properties": {
    "date:inception_lower":"2012-08-01",
    "date:inception_upper":"2012-08-31",
    "iso:country":"GB",
    "wof:name":"NR14 7FB",
    "wof:placetype":"postalcode"
},
  "geometry": {"coordinates":[1.427237,52.607159],"type":"Point"}
}