{
  "type": "Feature",
  "properties": {
    "iso:country": "GB",
    "wof:name": "EX5 2FL",
    "wof:placetype": "postalcode"
  },
  "geometry": {"coordinates":[-3.425143,50.739114],"type":"Point"}
}
