{
  "type": "Feature",
  "properties": {
    "iso:country": "GB",
    "wof:name": "CW12 4ZA",
    "wof:placetype": "postalcode"
  },
  "geometry": {"coordinates":[-2.251995,53.173121],"type":"Point"}
}
