{
  "type": "Feature",
  "properties": {
    "date:inception_lower": "1980-01-01",
    "date:inception_upper": "1980-01-01",
    "iso:country": "GB",
    "wof:name": "TS17 6BE",
    "wof:placetype": "postalcode"
  },
  "geometry": {"coordinates":[-1.304607,54.558703],"type":"Point"}
}
