{
  "type": "Feature",
  "properties": {
    "iso:country":"GB",
    "wof:name":"SR7 8RG",
    "wof:placetype":"postalcode"
},
  "geometry": {"coordinates":[-1.363601576329,54.81746109466993],"type":"Point"}
}