{
  "type": "Feature",
  "properties": {
    "date:inception_lower":"1992-08-01",
    "date:inception_upper":"1992-08-31",
    "iso:country":"GB",
    "wof:name":"HP27 9SS",
    "wof:placetype":"postalcode"
},
  "geometry": {"coordinates":[-0.863108,51.741973],"type":"Point"}
}