{
  "type": "Feature",
  "properties": {
    "iso:country": "GB",
    "wof:name": "HP27 9SS",
    "wof:placetype": "postalcode"
  },
  "geometry": {"coordinates":[-0.863108,51.741973],"type":"Point"}
}
