{
  "type": "Feature",
  "properties": {
    "date:inception_lower":"1995-07-01",
    "date:inception_upper":"1995-07-31",
    "iso:country":"GB",
    "wof:name":"PO40 9SG",
    "wof:placetype":"postalcode"
},
  "geometry": {"coordinates":[-1.530288,50.694543],"type":"Point"}
}