{
  "type": "Feature",
  "properties": {
    "date:inception_lower": "1980-01-01",
    "date:inception_upper": "1980-01-01",
    "iso:country": "GB",
    "wof:name": "PO2 9QL",
    "wof:placetype": "postalcode"
  },
  "geometry": {"coordinates":[-1.071936,50.82945],"type":"Point"}
}
