{
  "type": "Feature",
  "properties": {
    "iso:country":"GB",
    "wof:name":"DY9 9SR",
    "wof:placetype":"postalcode"
},
  "geometry": {"coordinates":[-2.11778609212474,52.39477678327224],"type":"Point"}
}