{
  "type": "Feature",
  "properties": {
    "date:inception_lower": "1980-01-01",
    "date:inception_upper": "1980-01-01",
    "iso:country": "GB",
    "wof:name": "DY9 9SR",
    "wof:placetype": "postalcode"
  },
  "geometry": {"coordinates":[-2.117786,52.394777],"type":"Point"}
}
