{
  "type": "Feature",
  "properties": {
    "date:inception_lower": "2010-10-01",
    "date:inception_upper": "2010-10-01",
    "iso:country": "GB",
    "wof:name": "MK3 6FA",
    "wof:placetype": "postalcode"
  },
  "geometry": {"coordinates":[-0.744759,51.993049],"type":"Point"}
}
