{
  "type": "Feature",
  "properties": {
    "iso:country":"GB",
    "wof:name":"TF11 8JX",
    "wof:placetype":"postalcode"
},
  "geometry": {"coordinates":[-2.2935514249419,52.69574876248001],"type":"Point"}
}