{
  "type": "Feature",
  "properties": {
    "date:inception_lower": "1980-01-01",
    "date:inception_upper": "1980-01-01",
    "iso:country": "GB",
    "wof:name": "TF11 8JX",
    "wof:placetype": "postalcode"
  },
  "geometry": {"coordinates":[-2.293549,52.695764],"type":"Point"}
}
