{
  "type": "Feature",
  "properties": {
    "iso:country": "GB",
    "wof:name": "TF11 8JX",
    "wof:placetype": "postalcode"
  },
  "geometry": {"coordinates":[-2.293637,52.695763],"type":"Point"}
}
