{
  "type": "Feature",
  "properties": {
    "date:inception_lower": "2020-04-01",
    "date:inception_upper": "2020-04-01",
    "iso:country": "GB",
    "wof:name": "N7 9HT",
    "wof:placetype": "postalcode"
  },
  "geometry": {"coordinates":[-0.118374,51.545892],"type":"Point"}
}
