{
  "type": "Feature",
  "properties": {
    "iso:country": "GB",
    "wof:name": "IG7 6PA",
    "wof:placetype": "postalcode"
  },
  "geometry": {"coordinates":[0.073891,51.61931],"type":"Point"}
}
