{
  "type": "Feature",
  "properties": {
    "iso:country":"GB",
    "wof:name":"IG7 6PA",
    "wof:placetype":"postalcode"
},
  "geometry": {"coordinates":[0.0738907980972,51.61931030530681],"type":"Point"}
}