{
  "type": "Feature",
  "properties": {
    "date:inception_lower":"1980-01-01",
    "date:inception_upper":"1980-01-31",
    "iso:country":"GB",
    "wof:name":"IG7 6PA",
    "wof:placetype":"postalcode"
},
  "geometry": {"coordinates":[0.073891,51.61931],"type":"Point"}
}