{
  "type": "Feature",
  "properties": {
    "date:inception_lower": "1980-01-01",
    "date:inception_upper": "1980-01-01",
    "iso:country": "GB",
    "wof:name": "CB11 3SY",
    "wof:placetype": "postalcode"
  },
  "geometry": {"coordinates":[0.215995,51.971885],"type":"Point"}
}
