{
  "type": "Feature",
  "properties": {
    "date:inception_lower":"1981-06-01",
    "date:inception_upper":"1981-06-30",
    "iso:country":"GB",
    "wof:name":"HP10 8JU",
    "wof:placetype":"postalcode"
},
  "geometry": {"coordinates":[-0.704416,51.638392],"type":"Point"}
}