{
  "type": "Feature",
  "properties": {
    "iso:country":"GB",
    "wof:name":"LA21 8DG",
    "wof:placetype":"postalcode"
},
  "geometry": {"coordinates":[-3.06728756835039,54.4034196257827],"type":"Point"}
}