{
  "type": "Feature",
  "properties": {
    "iso:country": "GB",
    "wof:name": "E1W 2AE",
    "wof:placetype": "postalcode"
  },
  "geometry": {"coordinates":[-0.066049,51.508458],"type":"Point"}
}
