{
  "type": "Feature",
  "properties": {
    "date:inception_lower": "2008-09-01",
    "date:inception_upper": "2008-09-01",
    "iso:country": "GB",
    "wof:name": "LS27 8QW",
    "wof:placetype": "postalcode"
  },
  "geometry": {"coordinates":[-1.598045,53.744966],"type":"Point"}
}
