{
  "type": "Feature",
  "properties": {
    "iso:country":"GB",
    "wof:name":"LS27 8QW",
    "wof:placetype":"postalcode"
},
  "geometry": {"coordinates":[-1.598045196051,53.74496646028494],"type":"Point"}
}