{
  "type": "Feature",
  "properties": {
    "iso:country": "GB",
    "wof:name": "LS27 8QW",
    "wof:placetype": "postalcode"
  },
  "geometry": {"coordinates":[-1.598045,53.744966],"type":"Point"}
}
