{
  "type": "Feature",
  "properties": {
    "date:inception_lower": "2006-02-01",
    "date:inception_upper": "2006-02-01",
    "iso:country": "GB",
    "wof:name": "BB3 3BD",
    "wof:placetype": "postalcode"
  },
  "geometry": {"coordinates":[-2.458584,53.698535],"type":"Point"}
}
