{
  "type": "Feature",
  "properties": {
    "iso:country":"GB",
    "wof:name":"B62 0HJ",
    "wof:placetype":"postalcode"
},
  "geometry": {"coordinates":[-2.02656327618815,52.43258193870375],"type":"Point"}
}