{
  "type": "Feature",
  "properties": {
    "iso:country":"GB",
    "wof:name":"BD10 0UJ",
    "wof:placetype":"postalcode"
},
  "geometry": {"coordinates":[-1.71327074188137,53.83574347347889],"type":"Point"}
}