{
  "type": "Feature",
  "properties": {
    "date:inception_lower":"1994-12-01",
    "date:inception_upper":"1994-12-31",
    "iso:country":"GB",
    "wof:name":"BD10 0UJ",
    "wof:placetype":"postalcode"
},
  "geometry": {"coordinates":[-1.713271,53.835743],"type":"Point"}
}