{
  "type": "Feature",
  "properties": {
    "iso:country": "GB",
    "wof:name": "BD10 0UJ",
    "wof:placetype": "postalcode"
  },
  "geometry": {"coordinates":[-1.713271,53.835743],"type":"Point"}
}
