{
  "type": "Feature",
  "properties": {
    "iso:country":"GB",
    "wof:name":"NP44 8HU",
    "wof:placetype":"postalcode"
},
  "geometry": {"coordinates":[-3.00640017820768,51.64541126646475],"type":"Point"}
}