{
  "type": "Feature",
  "properties": {
    "date:inception_lower": "1980-01-01",
    "date:inception_upper": "1980-01-01",
    "iso:country": "GB",
    "wof:name": "NP44 8HU",
    "wof:placetype": "postalcode"
  },
  "geometry": {"coordinates":[-3.0064,51.645411],"type":"Point"}
}
