{
  "type": "Feature",
  "properties": {
    "iso:country": "GB",
    "wof:name": "DL3 0HJ",
    "wof:placetype": "postalcode"
  },
  "geometry": {"coordinates":[-1.555514,54.545883],"type":"Point"}
}
