{
  "type": "Feature",
  "properties": {
    "iso:country":"GB",
    "wof:name":"HA0 2LH",
    "wof:placetype":"postalcode"
},
  "geometry": {"coordinates":[-0.31709771823631,51.55284651712316],"type":"Point"}
}