{
  "type": "Feature",
  "properties": {
    "date:inception_lower": "1980-01-01",
    "date:inception_upper": "1980-01-01",
    "iso:country": "GB",
    "wof:name": "HA0 2LH",
    "wof:placetype": "postalcode"
  },
  "geometry": {"coordinates":[-0.317098,51.552847],"type":"Point"}
}
