{
  "type": "Feature",
  "properties": {
    "iso:country":"GB",
    "wof:name":"SE7 7QL",
    "wof:placetype":"postalcode"
},
  "geometry": {"coordinates":[0.02653420496954,51.48683936583675],"type":"Point"}
}