{
  "type": "Feature",
  "properties": {
    "iso:country": "GB",
    "wof:name": "LS12 5DL",
    "wof:placetype": "postalcode"
  },
  "geometry": {"coordinates":[-1.621516,53.792356],"type":"Point"}
}
