{
  "type": "Feature",
  "properties": {
    "iso:country":"GB",
    "wof:name":"BN3 2DE",
    "wof:placetype":"postalcode"
},
  "geometry": {"coordinates":[-0.17876585931494,50.82761567928311],"type":"Point"}
}