{
  "type": "Feature",
  "properties": {
    "iso:country":"GB",
    "wof:name":"SA62 5RS",
    "wof:placetype":"postalcode"
},
  "geometry": {"coordinates":[-4.88157019283302,51.94017264696019],"type":"Point"}
}