{
  "type": "Feature",
  "properties": {
    "date:inception_lower": "1980-01-01",
    "date:inception_upper": "1980-01-01",
    "iso:country": "GB",
    "wof:name": "SA62 5RS",
    "wof:placetype": "postalcode"
  },
  "geometry": {"coordinates":[-4.88157,51.940173],"type":"Point"}
}
