{
  "type": "Feature",
  "properties": {
    "date:inception_lower": "2019-03-01",
    "date:inception_upper": "2019-03-01",
    "iso:country": "GB",
    "wof:name": "SK6 2BD",
    "wof:placetype": "postalcode"
  },
  "geometry": {"coordinates":[-2.113227,53.423723],"type":"Point"}
}
