{
  "type": "Feature",
  "properties": {
    "iso:country":"GB",
    "wof:name":"AB45 1FH",
    "wof:placetype":"postalcode"
},
  "geometry": {"coordinates":[-2.53674833157684,57.66623602995404],"type":"Point"}
}