{
  "type": "Feature",
  "properties": {
    "date:inception_lower": "1996-06-01",
    "date:inception_upper": "1996-06-01",
    "iso:country": "GB",
    "wof:name": "AB45 1FH",
    "wof:placetype": "postalcode"
  },
  "geometry": {"coordinates":[-2.536748,57.666236],"type":"Point"}
}
