{
  "type": "Feature",
  "properties": {
    "iso:country": "GB",
    "wof:name": "BD2 3QB",
    "wof:placetype": "postalcode"
  },
  "geometry": {"coordinates":[-1.710857,53.808837],"type":"Point"}
}
