{
  "type": "Feature",
  "properties": {
    "iso:country":"GB",
    "wof:name":"BD2 3QB",
    "wof:placetype":"postalcode"
},
  "geometry": {"coordinates":[-1.71085744826436,53.80883674445644],"type":"Point"}
}