{
  "type": "Feature",
  "properties": {
    "iso:country":"GB",
    "wof:name":"SP4 6EL",
    "wof:placetype":"postalcode"
},
  "geometry": {"coordinates":[-1.74930436730409,51.11147834945636],"type":"Point"}
}