{
  "type": "Feature",
  "properties": {
    "iso:country":"GB",
    "wof:name":"LS12 4QQ",
    "wof:placetype":"postalcode"
},
  "geometry": {"coordinates":[-1.60960269092067,53.79204815239174],"type":"Point"}
}