{
  "type": "Feature",
  "properties": {
    "date:inception_lower": "1990-02-01",
    "date:inception_upper": "1990-02-01",
    "iso:country": "GB",
    "wof:name": "SG2 7BH",
    "wof:placetype": "postalcode"
  },
  "geometry": {"coordinates":[-0.159629,51.909297],"type":"Point"}
}
