{
  "type": "Feature",
  "properties": {
    "iso:country":"GB",
    "wof:name":"SG2 7BH",
    "wof:placetype":"postalcode"
},
  "geometry": {"coordinates":[-0.15962898529418,51.90929739385886],"type":"Point"}
}