{
  "type": "Feature",
  "properties": {
    "date:inception_lower": "1980-01-01",
    "date:inception_upper": "1980-01-01",
    "iso:country": "GB",
    "wof:name": "GL50 3AH",
    "wof:placetype": "postalcode"
  },
  "geometry": {"coordinates":[-2.083773,51.898072],"type":"Point"}
}
