{
  "type": "Feature",
  "properties": {
    "iso:country":"GB",
    "wof:name":"GL50 3AH",
    "wof:placetype":"postalcode"
},
  "geometry": {"coordinates":[-2.08376571361405,51.8980103863513],"type":"Point"}
}