{
  "type": "Feature",
  "properties": {
    "iso:country": "GB",
    "wof:name": "GL50 3AH",
    "wof:placetype": "postalcode"
  },
  "geometry": {"coordinates":[-2.083766,51.89801],"type":"Point"}
}
