{
  "type": "Feature",
  "properties": {
    "iso:country": "GB",
    "wof:name": "DH1 4NJ",
    "wof:placetype": "postalcode"
  },
  "geometry": {"coordinates":[-1.58849,54.78448],"type":"Point"}
}
