{
  "type": "Feature",
  "properties": {
    "iso:country":"GB",
    "wof:name":"DH1 4NJ",
    "wof:placetype":"postalcode"
},
  "geometry": {"coordinates":[-1.58847895967666,54.78447115363397],"type":"Point"}
}