{
  "type": "Feature",
  "properties": {
    "iso:country":"GB",
    "wof:name":"SY13 2DS",
    "wof:placetype":"postalcode"
},
  "geometry": {"coordinates":[-2.67052034286122,52.89771371368229],"type":"Point"}
}