{
  "type": "Feature",
  "properties": {
    "iso:country": "GB",
    "wof:name": "SY13 2DS",
    "wof:placetype": "postalcode"
  },
  "geometry": {"coordinates":[-2.67052,52.897714],"type":"Point"}
}
