{
  "type": "Feature",
  "properties": {
    "iso:country":"GB",
    "wof:name":"CT6 5RB",
    "wof:placetype":"postalcode"
},
  "geometry": {"coordinates":[1.12594588258092,51.36861754106663],"type":"Point"}
}