{
  "type": "Feature",
  "properties": {
    "date:inception_lower": "1980-01-01",
    "date:inception_upper": "1980-01-01",
    "iso:country": "GB",
    "wof:name": "SE18 6XN",
    "wof:placetype": "postalcode"
  },
  "geometry": {"coordinates":[0.063356,51.483797],"type":"Point"}
}
