{
  "type": "Feature",
  "properties": {
    "iso:country":"GB",
    "wof:name":"SE18 6XN",
    "wof:placetype":"postalcode"
},
  "geometry": {"coordinates":[0.06332884158595,51.4837965781679],"type":"Point"}
}