{
  "type": "Feature",
  "properties": {
    "date:inception_lower": "1980-01-01",
    "date:inception_upper": "1980-01-01",
    "iso:country": "GB",
    "wof:name": "NP4 0JB",
    "wof:placetype": "postalcode"
  },
  "geometry": {"coordinates":[-3.008624,51.705557],"type":"Point"}
}
