{
  "type": "Feature",
  "properties": {
    "iso:country": "GB",
    "wof:name": "NP4 0JB",
    "wof:placetype": "postalcode"
  },
  "geometry": {"coordinates":[-3.008617,51.705554],"type":"Point"}
}
