{
  "type": "Feature",
  "properties": {
    "iso:country":"GB",
    "wof:name":"G65 9HQ",
    "wof:placetype":"postalcode"
},
  "geometry": {"coordinates":[-4.04296868357822,55.96100613505502],"type":"Point"}
}