{
  "type": "Feature",
  "properties": {
    "date:inception_lower": "1996-12-01",
    "date:inception_upper": "1996-12-01",
    "iso:country": "GB",
    "wof:name": "G34 9HJ",
    "wof:placetype": "postalcode"
  },
  "geometry": {"coordinates":[-4.116711,55.868106],"type":"Point"}
}
