{
  "type": "Feature",
  "properties": {
    "date:inception_lower":"1992-01-01",
    "date:inception_upper":"1992-01-31",
    "iso:country":"GB",
    "wof:name":"ST16 1HW",
    "wof:placetype":"postalcode"
},
  "geometry": {"coordinates":[-2.143335,52.812566],"type":"Point"}
}