{
  "type": "Feature",
  "properties": {
    "iso:country": "GB",
    "wof:name": "HR2 9QR",
    "wof:placetype": "postalcode"
  },
  "geometry": {"coordinates":[-2.815704,52.035147],"type":"Point"}
}
