{
  "type": "Feature",
  "properties": {
    "iso:country":"GB",
    "wof:name":"HR2 9QR",
    "wof:placetype":"postalcode"
},
  "geometry": {"coordinates":[-2.81570399036046,52.03514711641981],"type":"Point"}
}