{
  "type": "Feature",
  "properties": {
    "iso:country": "GB",
    "wof:name": "CB8 7DY",
    "wof:placetype": "postalcode"
  },
  "geometry": {"coordinates":[0.410276,52.253803],"type":"Point"}
}
