{
  "type": "Feature",
  "properties": {
    "iso:country":"GB",
    "wof:name":"WA10 4ES",
    "wof:placetype":"postalcode"
},
  "geometry": {"coordinates":[-2.75719994546179,53.45481455516275],"type":"Point"}
}