{
  "type": "Feature",
  "properties": {
    "date:inception_lower": "1980-01-01",
    "date:inception_upper": "1980-01-01",
    "iso:country": "GB",
    "wof:name": "WA10 4ES",
    "wof:placetype": "postalcode"
  },
  "geometry": {"coordinates":[-2.7572,53.454815],"type":"Point"}
}
