{
  "type": "Feature",
  "properties": {
    "date:inception_lower": "2008-06-01",
    "date:inception_upper": "2008-06-01",
    "iso:country": "GB",
    "wof:name": "BL11 1AF",
    "wof:placetype": "postalcode"
  },
  "geometry": {"coordinates":[-2.425139,53.572023],"type":"Point"}
}
