{
  "type": "Feature",
  "properties": {
    "iso:country":"GB",
    "wof:name":"SS3 9EF",
    "wof:placetype":"postalcode"
},
  "geometry": {"coordinates":[0.77970688739575,51.53133389518295],"type":"Point"}
}