{
  "type": "Feature",
  "properties": {
    "iso:country":"GB",
    "wof:name":"SO51 5AY",
    "wof:placetype":"postalcode"
},
  "geometry": {"coordinates":[-1.48095840779811,50.98892181466452],"type":"Point"}
}