{
  "type": "Feature",
  "properties": {
    "iso:country": "GB",
    "wof:name": "B8 2PY",
    "wof:placetype": "postalcode"
  },
  "geometry": {"coordinates":[-1.82078,52.486776],"type":"Point"}
}
