{
  "type": "Feature",
  "properties": {
    "date:inception_lower": "1980-01-01",
    "date:inception_upper": "1980-01-01",
    "iso:country": "GB",
    "wof:name": "FK4 1EX",
    "wof:placetype": "postalcode"
  },
  "geometry": {"coordinates":[-3.899951,56.002845],"type":"Point"}
}
