{
  "type": "Feature",
  "properties": {
    "iso:country": "GB",
    "wof:name": "SR1 3BN",
    "wof:placetype": "postalcode"
  },
  "geometry": {"coordinates":[-1.382775,54.907056],"type":"Point"}
}
