{
  "type": "Feature",
  "properties": {
    "iso:country":"GB",
    "wof:name":"B33 8EA",
    "wof:placetype":"postalcode"
},
  "geometry": {"coordinates":[-1.80516316458542,52.48178005525261],"type":"Point"}
}