{
  "type": "Feature",
  "properties": {
    "date:inception_lower":"2000-10-01",
    "date:inception_upper":"2000-10-31",
    "iso:country":"GB",
    "wof:name":"WD19 6JP",
    "wof:placetype":"postalcode"
},
  "geometry": {"coordinates":[-0.395391,51.624567],"type":"Point"}
}