{
  "type": "Feature",
  "properties": {
    "iso:country":"GB",
    "wof:name":"WD19 6JP",
    "wof:placetype":"postalcode"
},
  "geometry": {"coordinates":[-0.39539153959182,51.62456747252202],"type":"Point"}
}