{
  "type": "Feature",
  "properties": {
    "iso:country":"GB",
    "wof:name":"YO42 1UF",
    "wof:placetype":"postalcode"
},
  "geometry": {"coordinates":[-0.74461212661054,53.94123780839305],"type":"Point"}
}