{
  "type": "Feature",
  "properties": {
    "iso:country": "GB",
    "wof:name": "SS6 7SJ",
    "wof:placetype": "postalcode"
  },
  "geometry": {"coordinates":[0.599606,51.578634],"type":"Point"}
}
