{
  "type": "Feature",
  "properties": {
    "iso:country":"GB",
    "wof:name":"SL5 9DL",
    "wof:placetype":"postalcode"
},
  "geometry": {"coordinates":[-0.67185664875797,51.40355327486272],"type":"Point"}
}