{
  "type": "Feature",
  "properties": {
    "iso:country":"GB",
    "wof:name":"AB21 0NZ",
    "wof:placetype":"postalcode"
},
  "geometry": {"coordinates":[-2.19420704568079,57.2650224327855],"type":"Point"}
}