{
  "type": "Feature",
  "properties": {
    "iso:country": "GB",
    "wof:name": "AB21 0NZ",
    "wof:placetype": "postalcode"
  },
  "geometry": {"coordinates":[-2.194207,57.265022],"type":"Point"}
}
