{
  "type": "Feature",
  "properties": {
    "date:inception_lower": "1980-01-01",
    "date:inception_upper": "1980-01-01",
    "iso:country": "GB",
    "wof:name": "SK14 5BA",
    "wof:placetype": "postalcode"
  },
  "geometry": {"coordinates":[-2.077338,53.440004],"type":"Point"}
}
