{
  "type": "Feature",
  "properties": {
    "date:inception_lower": "1994-12-01",
    "date:inception_upper": "1994-12-01",
    "iso:country": "GB",
    "wof:name": "SO31 8FX",
    "wof:placetype": "postalcode"
  },
  "geometry": {"coordinates":[-1.317969,50.888484],"type":"Point"}
}
