{
  "type": "Feature",
  "properties": {
    "iso:country":"GB",
    "wof:name":"DN22 0QJ",
    "wof:placetype":"postalcode"
},
  "geometry": {"coordinates":[-0.94395644940876,53.28148025797573],"type":"Point"}
}