{
  "type": "Feature",
  "properties": {
    "iso:country": "GB",
    "wof:name": "DN22 0QJ",
    "wof:placetype": "postalcode"
  },
  "geometry": {"coordinates":[-0.943956,53.28148],"type":"Point"}
}
