{
  "type": "Feature",
  "properties": {
    "iso:country": "GB",
    "wof:name": "PA16 0EW",
    "wof:placetype": "postalcode"
  },
  "geometry": {"coordinates":[-4.860518,55.909323],"type":"Point"}
}
