{
  "type": "Feature",
  "properties": {
    "date:inception_lower": "1986-05-01",
    "date:inception_upper": "1986-05-01",
    "iso:country": "GB",
    "wof:name": "PA16 0EW",
    "wof:placetype": "postalcode"
  },
  "geometry": {"coordinates":[-4.860513,55.909318],"type":"Point"}
}
