{
  "type": "Feature",
  "properties": {
    "iso:country":"GB",
    "wof:name":"NW8 6NA",
    "wof:placetype":"postalcode"
},
  "geometry": {"coordinates":[-0.17560489864297,51.53852902570633],"type":"Point"}
}