{
  "type": "Feature",
  "properties": {
    "iso:country":"GB",
    "wof:name":"S75 6DT",
    "wof:placetype":"postalcode"
},
  "geometry": {"coordinates":[-1.49656107530679,53.58230033876796],"type":"Point"}
}