{
  "type": "Feature",
  "properties": {
    "iso:country":"GB",
    "wof:name":"WA12 9EU",
    "wof:placetype":"postalcode"
},
  "geometry": {"coordinates":[-2.64893696901871,53.4567462249163],"type":"Point"}
}