{
  "type": "Feature",
  "properties": {
    "iso:country":"GB",
    "wof:name":"WN6 0RY",
    "wof:placetype":"postalcode"
},
  "geometry": {"coordinates":[-2.68771354530758,53.58874197901419],"type":"Point"}
}