{
  "type": "Feature",
  "properties": {
    "date:inception_lower": "1981-06-01",
    "date:inception_upper": "1981-06-01",
    "iso:country": "GB",
    "wof:name": "WN6 0RY",
    "wof:placetype": "postalcode"
  },
  "geometry": {"coordinates":[-2.687713,53.588742],"type":"Point"}
}
