{
  "type": "Feature",
  "properties": {
    "iso:country": "GB",
    "wof:name": "WN6 0RY",
    "wof:placetype": "postalcode"
  },
  "geometry": {"coordinates":[-2.687713,53.588742],"type":"Point"}
}
