{
  "type": "Feature",
  "properties": {
    "date:inception_lower":"1980-01-01",
    "date:inception_upper":"1980-01-31",
    "iso:country":"GB",
    "wof:name":"CM3 4NG",
    "wof:placetype":"postalcode"
},
  "geometry": {"coordinates":[0.574529,51.717324],"type":"Point"}
}