{
  "type": "Feature",
  "properties": {
    "iso:country": "GB",
    "wof:name": "CM3 4NG",
    "wof:placetype": "postalcode"
  },
  "geometry": {"coordinates":[0.574529,51.717324],"type":"Point"}
}
