{
  "type": "Feature",
  "properties": {
    "iso:country":"GB",
    "wof:name":"CM3 4NG",
    "wof:placetype":"postalcode"
},
  "geometry": {"coordinates":[0.57452938947626,51.71732410570784],"type":"Point"}
}