{
  "type": "Feature",
  "properties": {
    "iso:country":"GB",
    "wof:name":"HS8 5RS",
    "wof:placetype":"postalcode"
},
  "geometry": {"coordinates":[-7.36878016246484,57.32278990979158],"type":"Point"}
}