{
  "type": "Feature",
  "properties": {
    "date:inception_lower":"1995-07-01",
    "date:inception_upper":"1995-07-31",
    "iso:country":"GB",
    "wof:name":"HS8 5RS",
    "wof:placetype":"postalcode"
},
  "geometry": {"coordinates":[-7.368038,57.323867],"type":"Point"}
}