{
  "type": "Feature",
  "properties": {
    "iso:country": "GB",
    "wof:name": "HS8 5RS",
    "wof:placetype": "postalcode"
  },
  "geometry": {"coordinates":[-7.368038,57.323867],"type":"Point"}
}
