{
  "type": "Feature",
  "properties": {
    "date:inception_lower":"1991-09-01",
    "date:inception_upper":"1991-09-30",
    "iso:country":"GB",
    "wof:name":"OX20 1PF",
    "wof:placetype":"postalcode"
},
  "geometry": {"coordinates":[-1.344061,51.847615],"type":"Point"}
}