{
  "type": "Feature",
  "properties": {
    "iso:country":"GB",
    "wof:name":"OX20 1PF",
    "wof:placetype":"postalcode"
},
  "geometry": {"coordinates":[-1.34407815928753,51.84760854113708],"type":"Point"}
}