{
  "type": "Feature",
  "properties": {
    "date:inception_lower": "1980-01-01",
    "date:inception_upper": "1980-01-01",
    "iso:country": "GB",
    "wof:name": "ME16 0EN",
    "wof:placetype": "postalcode"
  },
  "geometry": {"coordinates":[0.504986,51.279851],"type":"Point"}
}
