{
  "type": "Feature",
  "properties": {
    "iso:country":"GB",
    "wof:name":"BS4 2DY",
    "wof:placetype":"postalcode"
},
  "geometry": {"coordinates":[-2.5748876725425,51.43807821434814],"type":"Point"}
}