{
  "type": "Feature",
  "properties": {
    "iso:country":"GB",
    "wof:name":"NP12 1SJ",
    "wof:placetype":"postalcode"
},
  "geometry": {"coordinates":[-3.20651495411033,51.66232682320772],"type":"Point"}
}