{
  "type": "Feature",
  "properties": {
    "iso:country": "GB",
    "wof:name": "NP12 1SJ",
    "wof:placetype": "postalcode"
  },
  "geometry": {"coordinates":[-3.206515,51.662327],"type":"Point"}
}
