{
  "type": "Feature",
  "properties": {
    "iso:country":"GB",
    "wof:name":"CW12 2HE",
    "wof:placetype":"postalcode"
},
  "geometry": {"coordinates":[-2.19352148907601,53.16766704759523],"type":"Point"}
}