{
  "type": "Feature",
  "properties": {
    "iso:country": "GB",
    "wof:name": "BL1 8GD",
    "wof:placetype": "postalcode"
  },
  "geometry": {"coordinates":[-2.417289,53.593935],"type":"Point"}
}
