{
  "type": "Feature",
  "properties": {
    "date:inception_lower": "1993-01-01",
    "date:inception_upper": "1993-01-01",
    "iso:country": "GB",
    "wof:name": "BB5 3TH",
    "wof:placetype": "postalcode"
  },
  "geometry": {"coordinates":[-2.380282,53.739265],"type":"Point"}
}
