{
  "type": "Feature",
  "properties": {
    "iso:country":"GB",
    "wof:name":"BB5 3TH",
    "wof:placetype":"postalcode"
},
  "geometry": {"coordinates":[-2.38028251999777,53.73926510444997],"type":"Point"}
}