{
  "type": "Feature",
  "properties": {
    "iso:country": "GB",
    "wof:name": "WD19 4NF",
    "wof:placetype": "postalcode"
  },
  "geometry": {"coordinates":[-0.38953,51.638317],"type":"Point"}
}
