{
  "type": "Feature",
  "properties": {
    "iso:country":"GB",
    "wof:name":"WD19 4NF",
    "wof:placetype":"postalcode"
},
  "geometry": {"coordinates":[-0.38953044142496,51.63831703152307],"type":"Point"}
}