{
  "type": "Feature",
  "properties": {
    "date:inception_lower": "1980-01-01",
    "date:inception_upper": "1980-01-01",
    "iso:country": "GB",
    "wof:name": "BS3 2AQ",
    "wof:placetype": "postalcode"
  },
  "geometry": {"coordinates":[-2.613614,51.440856],"type":"Point"}
}
