{
  "type": "Feature",
  "properties": {
    "iso:country":"GB",
    "wof:name":"BS3 2AQ",
    "wof:placetype":"postalcode"
},
  "geometry": {"coordinates":[-2.61358201258815,51.44083126656932],"type":"Point"}
}