{
  "type": "Feature",
  "properties": {
    "iso:country": "GB",
    "wof:name": "TN15 6HE",
    "wof:placetype": "postalcode"
  },
  "geometry": {"coordinates":[0.257668,51.347099],"type":"Point"}
}
