{
  "type": "Feature",
  "properties": {
    "iso:country":"GB",
    "wof:name":"EH33 1PH",
    "wof:placetype":"postalcode"
},
  "geometry": {"coordinates":[-2.90940318638724,55.94046051902205],"type":"Point"}
}