{
  "type": "Feature",
  "properties": {
    "date:inception_lower": "1980-01-01",
    "date:inception_upper": "1980-01-01",
    "iso:country": "GB",
    "wof:name": "RG25 2LA",
    "wof:placetype": "postalcode"
  },
  "geometry": {"coordinates":[-1.04257,51.246813],"type":"Point"}
}
