{
  "type": "Feature",
  "properties": {
    "iso:country": "GB",
    "wof:name": "RG25 2LA",
    "wof:placetype": "postalcode"
  },
  "geometry": {"coordinates":[-1.042588,51.246813],"type":"Point"}
}
