{
  "type": "Feature",
  "properties": {
    "iso:country": "GB",
    "wof:name": "BN26 6HJ",
    "wof:placetype": "postalcode"
  },
  "geometry": {"coordinates":[0.25238,50.821513],"type":"Point"}
}
