{
  "type": "Feature",
  "properties": {
    "iso:country": "GB",
    "wof:name": "TA7 0LP",
    "wof:placetype": "postalcode"
  },
  "geometry": {"coordinates":[-2.932802,51.104526],"type":"Point"}
}
