{
  "type": "Feature",
  "properties": {
    "iso:country":"GB",
    "wof:name":"TF3 1EP",
    "wof:placetype":"postalcode"
},
  "geometry": {"coordinates":[-2.44707816688173,52.65486903174152],"type":"Point"}
}