{
  "type": "Feature",
  "properties": {
    "iso:country": "GB",
    "wof:name": "TF3 1EP",
    "wof:placetype": "postalcode"
  },
  "geometry": {"coordinates":[-2.447078,52.654869],"type":"Point"}
}
