{
  "type": "Feature",
  "properties": {
    "iso:country":"GB",
    "wof:name":"PO11 0RB",
    "wof:placetype":"postalcode"
},
  "geometry": {"coordinates":[-0.9871583472516,50.79178486294715],"type":"Point"}
}