{
  "type": "Feature",
  "properties": {
    "iso:country":"GB",
    "wof:name":"TN22 4JL",
    "wof:placetype":"postalcode"
},
  "geometry": {"coordinates":[0.14872901419806,50.99259016860904],"type":"Point"}
}