{
  "type": "Feature",
  "properties": {
    "date:inception_lower": "2020-09-01",
    "date:inception_upper": "2020-09-01",
    "iso:country": "GB",
    "wof:name": "G42 7BT",
    "wof:placetype": "postalcode"
  },
  "geometry": {"coordinates":[-4.258294,55.841197],"type":"Point"}
}
