{
  "type": "Feature",
  "properties": {
    "iso:country": "GB",
    "wof:name": "DT11 0AS",
    "wof:placetype": "postalcode"
  },
  "geometry": {"coordinates":[-2.272984,50.818521],"type":"Point"}
}
