{
  "type": "Feature",
  "properties": {
    "iso:country":"GB",
    "wof:name":"DT11 0AS",
    "wof:placetype":"postalcode"
},
  "geometry": {"coordinates":[-2.27298404781592,50.81852066390923],"type":"Point"}
}