{
  "type": "Feature",
  "properties": {
    "iso:country": "GB",
    "wof:name": "NE12 8TQ",
    "wof:placetype": "postalcode"
  },
  "geometry": {"coordinates":[-1.592017,55.015128],"type":"Point"}
}
