{
  "type": "Feature",
  "properties": {
    "date:inception_lower": "2000-06-01",
    "date:inception_upper": "2000-06-01",
    "iso:country": "GB",
    "wof:name": "NE12 8TQ",
    "wof:placetype": "postalcode"
  },
  "geometry": {"coordinates":[-1.592017,55.015128],"type":"Point"}
}
