{
  "type": "Feature",
  "properties": {
    "iso:country":"GB",
    "wof:name":"NP44 5UD",
    "wof:placetype":"postalcode"
},
  "geometry": {"coordinates":[-3.05166225153096,51.6571082033152],"type":"Point"}
}