{
  "type": "Feature",
  "properties": {
    "date:inception_lower": "1980-01-01",
    "date:inception_upper": "1980-01-01",
    "iso:country": "GB",
    "wof:name": "NP44 5UD",
    "wof:placetype": "postalcode"
  },
  "geometry": {"coordinates":[-3.051662,51.657108],"type":"Point"}
}
