{
  "type": "Feature",
  "properties": {
    "iso:country":"GB",
    "wof:name":"FY5 3RP",
    "wof:placetype":"postalcode"
},
  "geometry": {"coordinates":[-3.02155246523636,53.86255508498996],"type":"Point"}
}