{
  "type": "Feature",
  "properties": {
    "iso:country":"GB",
    "wof:name":"CM14 4UT",
    "wof:placetype":"postalcode"
},
  "geometry": {"coordinates":[0.29714595942512,51.62335470404245],"type":"Point"}
}