{
  "type": "Feature",
  "properties": {
    "iso:country":"GB",
    "wof:name":"BN17 6GJ",
    "wof:placetype":"postalcode"
},
  "geometry": {"coordinates":[-0.52315434959431,50.81964078774084],"type":"Point"}
}