{
  "type": "Feature",
  "properties": {
    "date:inception_lower": "1982-03-01",
    "date:inception_upper": "1982-03-01",
    "iso:country": "GB",
    "wof:name": "EX8 5ED",
    "wof:placetype": "postalcode"
  },
  "geometry": {"coordinates":[-3.383453,50.650754],"type":"Point"}
}
