{
  "type": "Feature",
  "properties": {
    "iso:country":"GB",
    "wof:name":"EX8 5ED",
    "wof:placetype":"postalcode"
},
  "geometry": {"coordinates":[-3.38345291114194,50.65075437858728],"type":"Point"}
}