{
  "type": "Feature",
  "properties": {
    "iso:country":"GB",
    "wof:name":"LL40 2UR",
    "wof:placetype":"postalcode"
},
  "geometry": {"coordinates":[-3.98311026420365,52.76057269212548],"type":"Point"}
}