{
  "type": "Feature",
  "properties": {
    "date:inception_lower": "1980-01-01",
    "date:inception_upper": "1980-01-01",
    "iso:country": "GB",
    "wof:name": "LL40 2UR",
    "wof:placetype": "postalcode"
  },
  "geometry": {"coordinates":[-3.984403,52.761142],"type":"Point"}
}
