{
  "type": "Feature",
  "properties": {
    "iso:country": "GB",
    "wof:name": "LL40 2UR",
    "wof:placetype": "postalcode"
  },
  "geometry": {"coordinates":[-3.984403,52.761142],"type":"Point"}
}
