{
  "type": "Feature",
  "properties": {
    "iso:country": "GB",
    "wof:name": "RH2 0TJ",
    "wof:placetype": "postalcode"
  },
  "geometry": {"coordinates":[-0.174794,51.261624],"type":"Point"}
}
