{
  "type": "Feature",
  "properties": {
    "iso:country":"GB",
    "wof:name":"RH2 0TJ",
    "wof:placetype":"postalcode"
},
  "geometry": {"coordinates":[-0.17479378406488,51.26162449782291],"type":"Point"}
}