{
  "type": "Feature",
  "properties": {
    "iso:country":"GB",
    "wof:name":"WS10 7TW",
    "wof:placetype":"postalcode"
},
  "geometry": {"coordinates":[-2.02112046770051,52.55250883177033],"type":"Point"}
}