{
  "type": "Feature",
  "properties": {
    "date:inception_lower": "1994-05-01",
    "date:inception_upper": "1994-05-01",
    "iso:country": "GB",
    "wof:name": "M20 3EJ",
    "wof:placetype": "postalcode"
  },
  "geometry": {"coordinates":[-2.234172,53.434919],"type":"Point"}
}
