{
  "type": "Feature",
  "properties": {
    "iso:country": "GB",
    "wof:name": "DY12 2RL",
    "wof:placetype": "postalcode"
  },
  "geometry": {"coordinates":[-2.321464,52.377928],"type":"Point"}
}
