{
  "type": "Feature",
  "properties": {
    "iso:country":"GB",
    "wof:name":"NG4 4EJ",
    "wof:placetype":"postalcode"
},
  "geometry": {"coordinates":[-1.08613620584237,52.97816918414713],"type":"Point"}
}