{
  "type": "Feature",
  "properties": {
    "date:inception_lower": "1993-06-01",
    "date:inception_upper": "1993-06-01",
    "iso:country": "GB",
    "wof:name": "AB51 4WZ",
    "wof:placetype": "postalcode"
  },
  "geometry": {"coordinates":[-2.391263,57.294404],"type":"Point"}
}
