{
  "type": "Feature",
  "properties": {
    "iso:country":"GB",
    "wof:name":"S9 1AQ",
    "wof:placetype":"postalcode"
},
  "geometry": {"coordinates":[-1.42503195656676,53.41462950573133],"type":"Point"}
}