{
  "type": "Feature",
  "properties": {
    "date:inception_lower": "1980-01-01",
    "date:inception_upper": "1980-01-01",
    "iso:country": "GB",
    "wof:name": "NN2 8JE",
    "wof:placetype": "postalcode"
  },
  "geometry": {"coordinates":[-0.899115,52.268725],"type":"Point"}
}
