{
  "type": "Feature",
  "properties": {
    "date:inception_lower": "1983-07-01",
    "date:inception_upper": "1983-07-01",
    "iso:country": "GB",
    "wof:name": "BN11 2LP",
    "wof:placetype": "postalcode"
  },
  "geometry": {"coordinates":[-0.359333,50.813657],"type":"Point"}
}
