{
  "type": "Feature",
  "properties": {
    "date:inception_lower": "2004-03-01",
    "date:inception_upper": "2004-03-01",
    "iso:country": "GB",
    "wof:name": "PR3 3SF",
    "wof:placetype": "postalcode"
  },
  "geometry": {"coordinates":[-2.597803,53.826371],"type":"Point"}
}
