{
  "type": "Feature",
  "properties": {
    "iso:country":"GB",
    "wof:name":"PR3 3SF",
    "wof:placetype":"postalcode"
},
  "geometry": {"coordinates":[-2.59780348525234,53.82637081507401],"type":"Point"}
}