{
  "type": "Feature",
  "properties": {
    "date:inception_lower": "2001-06-01",
    "date:inception_upper": "2001-06-01",
    "iso:country": "GB",
    "wof:name": "BA16 0LZ",
    "wof:placetype": "postalcode"
  },
  "geometry": {"coordinates":[-2.735099,51.130926],"type":"Point"}
}
