{
  "type": "Feature",
  "properties": {
    "iso:country": "GB",
    "wof:name": "DE11 9LH",
    "wof:placetype": "postalcode"
  },
  "geometry": {"coordinates":[-1.576287,52.758284],"type":"Point"}
}
