{
  "type": "Feature",
  "properties": {
    "iso:country":"GB",
    "wof:name":"OL9 8LQ",
    "wof:placetype":"postalcode"
},
  "geometry": {"coordinates":[-2.14775403020747,53.52916607110239],"type":"Point"}
}