{
  "type": "Feature",
  "properties": {
    "iso:country": "GB",
    "wof:name": "PO9 4LJ",
    "wof:placetype": "postalcode"
  },
  "geometry": {"coordinates":[-0.99308,50.87341],"type":"Point"}
}
