{
  "type": "Feature",
  "properties": {
    "iso:country":"GB",
    "wof:name":"PO9 4LJ",
    "wof:placetype":"postalcode"
},
  "geometry": {"coordinates":[-0.99307960966317,50.87340957963256],"type":"Point"}
}