{
  "type": "Feature",
  "properties": {
    "iso:country": "GB",
    "wof:name": "NE47 8JY",
    "wof:placetype": "postalcode"
  },
  "geometry": {"coordinates":[-2.314272,54.932102],"type":"Point"}
}
