{
  "type": "Feature",
  "properties": {
    "iso:country":"GB",
    "wof:name":"NE47 8JY",
    "wof:placetype":"postalcode"
},
  "geometry": {"coordinates":[-2.31427228129705,54.93210161476397],"type":"Point"}
}