{
  "type": "Feature",
  "properties": {
    "date:inception_lower":"1980-01-01",
    "date:inception_upper":"1980-01-31",
    "iso:country":"GB",
    "wof:name":"PL20 6NG",
    "wof:placetype":"postalcode"
},
  "geometry": {"coordinates":[-4.065496,50.500701],"type":"Point"}
}