{
  "type": "Feature",
  "properties": {
    "iso:country":"GB",
    "wof:name":"PL20 6NG",
    "wof:placetype":"postalcode"
},
  "geometry": {"coordinates":[-4.06549576177671,50.50070107538792],"type":"Point"}
}