{
  "type": "Feature",
  "properties": {
    "iso:country":"GB",
    "wof:name":"BA2 9BW",
    "wof:placetype":"postalcode"
},
  "geometry": {"coordinates":[-2.43964214707064,51.37413949698521],"type":"Point"}
}