{
  "type": "Feature",
  "properties": {
    "date:inception_lower": "2012-12-01",
    "date:inception_upper": "2012-12-01",
    "iso:country": "GB",
    "wof:name": "DD8 3FD",
    "wof:placetype": "postalcode"
  },
  "geometry": {"coordinates":[-2.870161,56.650997],"type":"Point"}
}
