{
  "type": "Feature",
  "properties": {
    "iso:country":"GB",
    "wof:name":"DD8 3FD",
    "wof:placetype":"postalcode"
},
  "geometry": {"coordinates":[-2.87009156573877,56.65101637684356],"type":"Point"}
}