{
  "type": "Feature",
  "properties": {
    "date:inception_lower":"2012-12-01",
    "date:inception_upper":"2012-12-31",
    "iso:country":"GB",
    "wof:name":"DD8 3FD",
    "wof:placetype":"postalcode"
},
  "geometry": {"coordinates":[-2.870268,56.650681],"type":"Point"}
}