{
  "type": "Feature",
  "properties": {
    "date:inception_lower": "1980-01-01",
    "date:inception_upper": "1980-01-01",
    "iso:country": "GB",
    "wof:name": "BN25 3DF",
    "wof:placetype": "postalcode"
  },
  "geometry": {"coordinates":[0.117576,50.78564],"type":"Point"}
}
