{
  "type": "Feature",
  "properties": {
    "iso:country":"GB",
    "wof:name":"HA7 4SQ",
    "wof:placetype":"postalcode"
},
  "geometry": {"coordinates":[-0.29663423877381,51.61564075621106],"type":"Point"}
}