{
  "type": "Feature",
  "properties": {
    "iso:country":"GB",
    "wof:name":"PL6 8JW",
    "wof:placetype":"postalcode"
},
  "geometry": {"coordinates":[-4.10036091635306,50.41847240306692],"type":"Point"}
}