{
  "type": "Feature",
  "properties": {
    "iso:country": "GB",
    "wof:name": "PL6 8JW",
    "wof:placetype": "postalcode"
  },
  "geometry": {"coordinates":[-4.100361,50.418472],"type":"Point"}
}
