{
  "type": "Feature",
  "properties": {
    "iso:country":"GB",
    "wof:name":"BS20 0PD",
    "wof:placetype":"postalcode"
},
  "geometry": {"coordinates":[-2.69824177483006,51.4786979330006],"type":"Point"}
}