{
  "type": "Feature",
  "properties": {
    "iso:country": "GB",
    "wof:name": "HP20 2AU",
    "wof:placetype": "postalcode"
  },
  "geometry": {"coordinates":[-0.807188,51.827692],"type":"Point"}
}
