{
  "type": "Feature",
  "properties": {
    "iso:country":"GB",
    "wof:name":"HP20 2AU",
    "wof:placetype":"postalcode"
},
  "geometry": {"coordinates":[-0.8071880384785,51.8276917314049],"type":"Point"}
}