{
  "type": "Feature",
  "properties": {
    "iso:country": "GB",
    "wof:name": "G71 8QG",
    "wof:placetype": "postalcode"
  },
  "geometry": {"coordinates":[-4.07296,55.81168],"type":"Point"}
}
