{
  "type": "Feature",
  "properties": {
    "iso:country":"GB",
    "wof:name":"G71 8QG",
    "wof:placetype":"postalcode"
},
  "geometry": {"coordinates":[-4.07296039749506,55.81167999282768],"type":"Point"}
}