{
  "type": "Feature",
  "properties": {
    "iso:country":"GB",
    "wof:name":"TW12 3XB",
    "wof:placetype":"postalcode"
},
  "geometry": {"coordinates":[-0.37837404234023,51.42570418663747],"type":"Point"}
}