{
  "type": "Feature",
  "properties": {
    "date:inception_lower": "1996-06-01",
    "date:inception_upper": "1996-06-01",
    "iso:country": "GB",
    "wof:name": "HU17 0RQ",
    "wof:placetype": "postalcode"
  },
  "geometry": {"coordinates":[-0.408755,53.840619],"type":"Point"}
}
