{
  "type": "Feature",
  "properties": {
    "iso:country":"GB",
    "wof:name":"HU17 0RQ",
    "wof:placetype":"postalcode"
},
  "geometry": {"coordinates":[-0.4087552178833,53.84061891740444],"type":"Point"}
}