{
  "type": "Feature",
  "properties": {
    "date:inception_lower": "2014-03-01",
    "date:inception_upper": "2014-03-01",
    "iso:country": "GB",
    "wof:name": "LS25 7FF",
    "wof:placetype": "postalcode"
  },
  "geometry": {"coordinates":[-1.375402,53.772262],"type":"Point"}
}
