{
  "type": "Feature",
  "properties": {
    "iso:country": "GB",
    "wof:name": "LS25 7FF",
    "wof:placetype": "postalcode"
  },
  "geometry": {"coordinates":[-1.375445,53.772237],"type":"Point"}
}
