{
  "type": "Feature",
  "properties": {
    "iso:country": "GB",
    "wof:name": "WN3 4JA",
    "wof:placetype": "postalcode"
  },
  "geometry": {"coordinates":[-2.612886,53.531164],"type":"Point"}
}
