{
  "type": "Feature",
  "properties": {
    "iso:country":"GB",
    "wof:name":"WN3 4JA",
    "wof:placetype":"postalcode"
},
  "geometry": {"coordinates":[-2.61288647283125,53.53116422881369],"type":"Point"}
}