{
  "type": "Feature",
  "properties": {
    "iso:country":"GB",
    "wof:name":"NG18 2PS",
    "wof:placetype":"postalcode"
},
  "geometry": {"coordinates":[-1.17942301968377,53.14260803806423],"type":"Point"}
}