{
  "type": "Feature",
  "properties": {
    "iso:country": "GB",
    "wof:name": "NG18 2PS",
    "wof:placetype": "postalcode"
  },
  "geometry": {"coordinates":[-1.179423,53.142608],"type":"Point"}
}
