{
  "type": "Feature",
  "properties": {
    "iso:country":"GB",
    "wof:name":"GU22 8NA",
    "wof:placetype":"postalcode"
},
  "geometry": {"coordinates":[-0.52320723988399,51.32608613406834],"type":"Point"}
}