{
  "type": "Feature",
  "properties": {
    "date:inception_lower": "1980-01-01",
    "date:inception_upper": "1980-01-01",
    "iso:country": "GB",
    "wof:name": "GU22 8NA",
    "wof:placetype": "postalcode"
  },
  "geometry": {"coordinates":[-0.523207,51.326086],"type":"Point"}
}
