{
  "type": "Feature",
  "properties": {
    "date:inception_lower":"1980-01-01",
    "date:inception_upper":"1980-01-31",
    "iso:country":"GB",
    "wof:name":"BD3 8NB",
    "wof:placetype":"postalcode"
},
  "geometry": {"coordinates":[-1.713149,53.795711],"type":"Point"}
}