{
  "type": "Feature",
  "properties": {
    "iso:country":"GB",
    "wof:name":"BD3 8NB",
    "wof:placetype":"postalcode"
},
  "geometry": {"coordinates":[-1.71314889998705,53.79571079889295],"type":"Point"}
}