{
  "type": "Feature",
  "properties": {
    "date:inception_lower": "2007-01-01",
    "date:inception_upper": "2007-01-01",
    "iso:country": "GB",
    "wof:name": "MK17 8GJ",
    "wof:placetype": "postalcode"
  },
  "geometry": {"coordinates":[-0.651983,52.015806],"type":"Point"}
}
