{
  "type": "Feature",
  "properties": {
    "iso:country":"GB",
    "wof:name":"MK17 8GJ",
    "wof:placetype":"postalcode"
},
  "geometry": {"coordinates":[-0.65198308802476,52.01580610861981],"type":"Point"}
}