{
  "type": "Feature",
  "properties": {
    "iso:country":"GB",
    "wof:name":"S74 8EU",
    "wof:placetype":"postalcode"
},
  "geometry": {"coordinates":[-1.43105623937543,53.49194236409557],"type":"Point"}
}