{
  "type": "Feature",
  "properties": {
    "date:inception_lower": "1980-01-01",
    "date:inception_upper": "1980-01-01",
    "iso:country": "GB",
    "wof:name": "S74 8EU",
    "wof:placetype": "postalcode"
  },
  "geometry": {"coordinates":[-1.431056,53.491942],"type":"Point"}
}
