{
  "type": "Feature",
  "properties": {
    "iso:country":"GB",
    "wof:name":"SG13 8PT",
    "wof:placetype":"postalcode"
},
  "geometry": {"coordinates":[-0.10493229509315,51.77177637187269],"type":"Point"}
}