{
  "type": "Feature",
  "properties": {
    "date:inception_lower": "1980-01-01",
    "date:inception_upper": "1980-01-01",
    "iso:country": "GB",
    "wof:name": "SG13 8PT",
    "wof:placetype": "postalcode"
  },
  "geometry": {"coordinates":[-0.104932,51.771776],"type":"Point"}
}
