{
  "type": "Feature",
  "properties": {
    "iso:country": "GB",
    "wof:name": "SG13 8PT",
    "wof:placetype": "postalcode"
  },
  "geometry": {"coordinates":[-0.104932,51.771776],"type":"Point"}
}
