{
  "type": "Feature",
  "properties": {
    "iso:country":"GB",
    "wof:name":"LL29 8UP",
    "wof:placetype":"postalcode"
},
  "geometry": {"coordinates":[-3.6943700767376,53.27852611056225],"type":"Point"}
}