{
  "type": "Feature",
  "properties": {
    "iso:country":"GB",
    "wof:name":"BB12 0LS",
    "wof:placetype":"postalcode"
},
  "geometry": {"coordinates":[-2.27220163440614,53.80246673036812],"type":"Point"}
}