{
  "type": "Feature",
  "properties": {
    "date:inception_lower": "2002-06-01",
    "date:inception_upper": "2002-06-01",
    "iso:country": "GB",
    "wof:name": "DE23 4AJ",
    "wof:placetype": "postalcode"
  },
  "geometry": {"coordinates":[-1.533371,52.893056],"type":"Point"}
}
