{
  "type": "Feature",
  "properties": {
    "iso:country":"GB",
    "wof:name":"DE23 4AJ",
    "wof:placetype":"postalcode"
},
  "geometry": {"coordinates":[-1.53337096582085,52.89305574937147],"type":"Point"}
}