{
  "type": "Feature",
  "properties": {
    "iso:country": "GB",
    "wof:name": "WR11 4NL",
    "wof:placetype": "postalcode"
  },
  "geometry": {"coordinates":[-1.942298,52.105136],"type":"Point"}
}
