{
  "type": "Feature",
  "properties": {
    "iso:country": "GB",
    "wof:name": "LA2 6FJ",
    "wof:placetype": "postalcode"
  },
  "geometry": {"coordinates":[-2.748719,54.077943],"type":"Point"}
}
