{
  "type": "Feature",
  "properties": {
    "date:inception_lower": "2019-07-01",
    "date:inception_upper": "2019-07-01",
    "iso:country": "GB",
    "wof:name": "LA2 6FJ",
    "wof:placetype": "postalcode"
  },
  "geometry": {"coordinates":[-2.769096,54.079765],"type":"Point"}
}
