{
  "type": "Feature",
  "properties": {
    "iso:country": "GB",
    "wof:name": "DH4 6GP",
    "wof:placetype": "postalcode"
  },
  "geometry": {"coordinates":[-1.506022,54.858257],"type":"Point"}
}
