{
  "type": "Feature",
  "properties": {
    "iso:country":"GB",
    "wof:name":"DH4 6GP",
    "wof:placetype":"postalcode"
},
  "geometry": {"coordinates":[-1.50689863763157,54.85938449707022],"type":"Point"}
}