{
  "type": "Feature",
  "properties": {
    "iso:country":"GB",
    "wof:name":"G76 7HF",
    "wof:placetype":"postalcode"
},
  "geometry": {"coordinates":[-4.28433687733117,55.79260989157746],"type":"Point"}
}