{
  "type": "Feature",
  "properties": {
    "date:inception_lower": "2004-10-01",
    "date:inception_upper": "2004-10-01",
    "iso:country": "GB",
    "wof:name": "N17 9BF",
    "wof:placetype": "postalcode"
  },
  "geometry": {"coordinates":[-0.06919,51.59257],"type":"Point"}
}
