{
  "type": "Feature",
  "properties": {
    "iso:country":"GB",
    "wof:name":"N17 9BF",
    "wof:placetype":"postalcode"
},
  "geometry": {"coordinates":[-0.06918956510647,51.59257043920746],"type":"Point"}
}