{
  "type": "Feature",
  "properties": {
    "iso:country": "GB",
    "wof:name": "CM7 4EL",
    "wof:placetype": "postalcode"
  },
  "geometry": {"coordinates":[0.502261,51.960896],"type":"Point"}
}
