{
  "type": "Feature",
  "properties": {
    "date:inception_lower": "2017-08-01",
    "date:inception_upper": "2017-08-01",
    "iso:country": "GB",
    "wof:name": "DL17 9BT",
    "wof:placetype": "postalcode"
  },
  "geometry": {"coordinates":[-1.521665,54.702278],"type":"Point"}
}
