{
  "type": "Feature",
  "properties": {
    "iso:country": "GB",
    "wof:name": "DL17 9BT",
    "wof:placetype": "postalcode"
  },
  "geometry": {"coordinates":[-1.521665,54.702278],"type":"Point"}
}
