{
  "type": "Feature",
  "properties": {
    "iso:country":"GB",
    "wof:name":"BD17 7QS",
    "wof:placetype":"postalcode"
},
  "geometry": {"coordinates":[-1.7265901073613,53.86251356324625],"type":"Point"}
}