{
  "type": "Feature",
  "properties": {
    "date:inception_lower": "1988-03-01",
    "date:inception_upper": "1988-03-01",
    "iso:country": "GB",
    "wof:name": "E1 7RL",
    "wof:placetype": "postalcode"
  },
  "geometry": {"coordinates":[-0.071748,51.516843],"type":"Point"}
}
