{
  "type": "Feature",
  "properties": {
    "iso:country": "GB",
    "wof:name": "BB1 8DG",
    "wof:placetype": "postalcode"
  },
  "geometry": {"coordinates":[-2.496068,53.758795],"type":"Point"}
}
