{
  "type": "Feature",
  "properties": {
    "date:inception_lower": "1980-01-01",
    "date:inception_upper": "1980-01-01",
    "iso:country": "GB",
    "wof:name": "DL13 5RN",
    "wof:placetype": "postalcode"
  },
  "geometry": {"coordinates":[-1.894345,54.632395],"type":"Point"}
}
