{
  "type": "Feature",
  "properties": {
    "iso:country": "GB",
    "wof:name": "DL13 5RN",
    "wof:placetype": "postalcode"
  },
  "geometry": {"coordinates":[-1.894289,54.632359],"type":"Point"}
}
