{
  "type": "Feature",
  "properties": {
    "iso:country":"GB",
    "wof:name":"CV34 4EA",
    "wof:placetype":"postalcode"
},
  "geometry": {"coordinates":[-1.59076405598841,52.28057268109252],"type":"Point"}
}