{
  "type": "Feature",
  "properties": {
    "iso:country":"GB",
    "wof:name":"SW11 2DU",
    "wof:placetype":"postalcode"
},
  "geometry": {"coordinates":[-0.16478919054183,51.47076377358555],"type":"Point"}
}