{
  "type": "Feature",
  "properties": {
    "iso:country": "GB",
    "wof:name": "LS28 8DQ",
    "wof:placetype": "postalcode"
  },
  "geometry": {"coordinates":[-1.682102,53.794542],"type":"Point"}
}
