{
  "type": "Feature",
  "properties": {
    "date:inception_lower":"1980-01-01",
    "date:inception_upper":"1980-01-31",
    "iso:country":"GB",
    "wof:name":"IP17 2BN",
    "wof:placetype":"postalcode"
},
  "geometry": {"coordinates":[1.432298,52.224409],"type":"Point"}
}