{
  "type": "Feature",
  "properties": {
    "iso:country": "GB",
    "wof:name": "WD18 0DH",
    "wof:placetype": "postalcode"
  },
  "geometry": {"coordinates":[-0.40038,51.651144],"type":"Point"}
}
