{
  "type": "Feature",
  "properties": {
    "date:inception_lower": "2023-10-01",
    "date:inception_upper": "2023-10-01",
    "iso:country": "GB",
    "wof:name": "AB23 8NW",
    "wof:placetype": "postalcode"
  },
  "geometry": {"coordinates":[-2.088797,57.193442],"type":"Point"}
}
