{
  "type": "Feature",
  "properties": {
    "date:inception_lower": "2002-05-01",
    "date:inception_upper": "2002-05-01",
    "iso:country": "GB",
    "wof:name": "BN2 3GU",
    "wof:placetype": "postalcode"
  },
  "geometry": {"coordinates":[-0.126669,50.8343],"type":"Point"}
}
