{
  "type": "Feature",
  "properties": {
    "iso:country":"GB",
    "wof:name":"BN2 3GU",
    "wof:placetype":"postalcode"
},
  "geometry": {"coordinates":[-0.12666933653898,50.83430033947548],"type":"Point"}
}