{
  "type": "Feature",
  "properties": {
    "iso:country":"GB",
    "wof:name":"DD5 1AJ",
    "wof:placetype":"postalcode"
},
  "geometry": {"coordinates":[-2.87816616414968,56.46850704107632],"type":"Point"}
}