{
  "type": "Feature",
  "properties": {
    "iso:country": "GB",
    "wof:name": "LS19 7AD",
    "wof:placetype": "postalcode"
  },
  "geometry": {"coordinates":[-1.677055,53.86399],"type":"Point"}
}
