{
  "type": "Feature",
  "properties": {
    "date:inception_lower":"1980-01-01",
    "date:inception_upper":"1980-01-31",
    "iso:country":"GB",
    "wof:name":"LS19 7AD",
    "wof:placetype":"postalcode"
},
  "geometry": {"coordinates":[-1.677055,53.86399],"type":"Point"}
}