{
  "type": "Feature",
  "properties": {
    "date:inception_lower": "1980-01-01",
    "date:inception_upper": "1980-01-01",
    "iso:country": "GB",
    "wof:name": "LA3 2LP",
    "wof:placetype": "postalcode"
  },
  "geometry": {"coordinates":[-2.89261,54.043129],"type":"Point"}
}
