{
  "type": "Feature",
  "properties": {
    "iso:country": "GB",
    "wof:name": "LA3 2LP",
    "wof:placetype": "postalcode"
  },
  "geometry": {"coordinates":[-2.89261,54.043129],"type":"Point"}
}
