{
  "type": "Feature",
  "properties": {
    "iso:country":"GB",
    "wof:name":"DE55 6EG",
    "wof:placetype":"postalcode"
},
  "geometry": {"coordinates":[-1.41573236778288,53.12978061593618],"type":"Point"}
}