{
  "type": "Feature",
  "properties": {
    "date:inception_lower": "1980-01-01",
    "date:inception_upper": "1980-01-01",
    "iso:country": "GB",
    "wof:name": "EH12 5QN",
    "wof:placetype": "postalcode"
  },
  "geometry": {"coordinates":[-3.250211,55.943601],"type":"Point"}
}
