{
  "type": "Feature",
  "properties": {
    "iso:country":"GB",
    "wof:name":"EH12 5QN",
    "wof:placetype":"postalcode"
},
  "geometry": {"coordinates":[-3.25021103601052,55.94360111405427],"type":"Point"}
}