{
  "type": "Feature",
  "properties": {
    "iso:country":"GB",
    "wof:name":"GL12 7JB",
    "wof:placetype":"postalcode"
},
  "geometry": {"coordinates":[-2.34484431667041,51.63840223845011],"type":"Point"}
}