{
  "type": "Feature",
  "properties": {
    "date:inception_lower": "1980-01-01",
    "date:inception_upper": "1980-01-01",
    "iso:country": "GB",
    "wof:name": "GL12 7JB",
    "wof:placetype": "postalcode"
  },
  "geometry": {"coordinates":[-2.344844,51.638402],"type":"Point"}
}
