{
  "type": "Feature",
  "properties": {
    "iso:country":"GB",
    "wof:name":"KT9 1RU",
    "wof:placetype":"postalcode"
},
  "geometry": {"coordinates":[-0.30259789818269,51.37135084526797],"type":"Point"}
}