{
  "type": "Feature",
  "properties": {
    "iso:country":"GB",
    "wof:name":"CO6 2QL",
    "wof:placetype":"postalcode"
},
  "geometry": {"coordinates":[0.71347973991848,51.93455956849636],"type":"Point"}
}