{
  "type": "Feature",
  "properties": {
    "date:inception_lower":"1980-01-01",
    "date:inception_upper":"1980-01-31",
    "iso:country":"GB",
    "wof:name":"CO6 2QL",
    "wof:placetype":"postalcode"
},
  "geometry": {"coordinates":[0.721887,51.939081],"type":"Point"}
}