{
  "type": "Feature",
  "properties": {
    "iso:country":"GB",
    "wof:name":"B23 7RE",
    "wof:placetype":"postalcode"
},
  "geometry": {"coordinates":[-1.86062497260914,52.5164065841244],"type":"Point"}
}