{
  "type": "Feature",
  "properties": {
    "iso:country": "GB",
    "wof:name": "OX15 5AR",
    "wof:placetype": "postalcode"
  },
  "geometry": {"coordinates":[-1.551675,52.051613],"type":"Point"}
}
