{
  "type": "Feature",
  "properties": {
    "iso:country":"GB",
    "wof:name":"SG1 5QE",
    "wof:placetype":"postalcode"
},
  "geometry": {"coordinates":[-0.18065771810289,51.91130585742829],"type":"Point"}
}