{
  "type": "Feature",
  "properties": {
    "iso:country":"GB",
    "wof:name":"AB51 0UD",
    "wof:placetype":"postalcode"
},
  "geometry": {"coordinates":[-2.33832975475081,57.23436356116652],"type":"Point"}
}