{
  "type": "Feature",
  "properties": {
    "iso:country":"GB",
    "wof:name":"W10 5JP",
    "wof:placetype":"postalcode"
},
  "geometry": {"coordinates":[-0.22295216866651,51.52317738093468],"type":"Point"}
}