{
  "type": "Feature",
  "properties": {
    "iso:country": "GB",
    "wof:name": "SY11 4NZ",
    "wof:placetype": "postalcode"
  },
  "geometry": {"coordinates":[-3.007454,52.873452],"type":"Point"}
}
