{
  "type": "Feature",
  "properties": {
    "date:inception_lower": "1995-07-01",
    "date:inception_upper": "1995-07-01",
    "iso:country": "GB",
    "wof:name": "SY11 4NZ",
    "wof:placetype": "postalcode"
  },
  "geometry": {"coordinates":[-3.007468,52.873485],"type":"Point"}
}
