{
  "type": "Feature",
  "properties": {
    "iso:country": "GB",
    "wof:name": "PO16 9AU",
    "wof:placetype": "postalcode"
  },
  "geometry": {"coordinates":[-1.135454,50.843022],"type":"Point"}
}
