{
  "type": "Feature",
  "properties": {
    "iso:country":"GB",
    "wof:name":"SA32 7JU",
    "wof:placetype":"postalcode"
},
  "geometry": {"coordinates":[-4.1831494410023,51.93029642144256],"type":"Point"}
}