{
  "type": "Feature",
  "properties": {
    "iso:country": "GB",
    "wof:name": "SA8 4BW",
    "wof:placetype": "postalcode"
  },
  "geometry": {"coordinates":[-3.826468,51.737173],"type":"Point"}
}
