{
  "type": "Feature",
  "properties": {
    "date:inception_lower":"2009-12-01",
    "date:inception_upper":"2009-12-31",
    "iso:country":"GB",
    "wof:name":"SA8 4BW",
    "wof:placetype":"postalcode"
},
  "geometry": {"coordinates":[-3.826468,51.737173],"type":"Point"}
}