{
  "type": "Feature",
  "properties": {
    "iso:country": "GB",
    "wof:name": "ST20 0PY",
    "wof:placetype": "postalcode"
  },
  "geometry": {"coordinates":[-2.365608,52.833313],"type":"Point"}
}
