{
  "type": "Feature",
  "properties": {
    "iso:country":"GB",
    "wof:name":"ST20 0PY",
    "wof:placetype":"postalcode"
},
  "geometry": {"coordinates":[-2.36560812890081,52.83331348945445],"type":"Point"}
}