{
  "type": "Feature",
  "properties": {
    "date:inception_lower": "1994-12-01",
    "date:inception_upper": "1994-12-01",
    "iso:country": "GB",
    "wof:name": "SK16 5LJ",
    "wof:placetype": "postalcode"
  },
  "geometry": {"coordinates":[-2.084027,53.465581],"type":"Point"}
}
