{
  "type": "Feature",
  "properties": {
    "date:inception_lower": "1995-07-01",
    "date:inception_upper": "1995-07-01",
    "iso:country": "GB",
    "wof:name": "KT13 0XP",
    "wof:placetype": "postalcode"
  },
  "geometry": {"coordinates":[-0.461915,51.351996],"type":"Point"}
}
