{
  "type": "Feature",
  "properties": {
    "iso:country":"GB",
    "wof:name":"KT13 0XP",
    "wof:placetype":"postalcode"
},
  "geometry": {"coordinates":[-0.46191554027143,51.35199581429912],"type":"Point"}
}