{
  "type": "Feature",
  "properties": {
    "iso:country": "GB",
    "wof:name": "HR6 8AT",
    "wof:placetype": "postalcode"
  },
  "geometry": {"coordinates":[-2.731863,52.225655],"type":"Point"}
}
