{
  "type": "Feature",
  "properties": {
    "iso:country":"GB",
    "wof:name":"HR6 8AT",
    "wof:placetype":"postalcode"
},
  "geometry": {"coordinates":[-2.73184705076203,52.22556302675622],"type":"Point"}
}