{
  "type": "Feature",
  "properties": {
    "date:inception_lower": "1980-01-01",
    "date:inception_upper": "1980-01-01",
    "iso:country": "GB",
    "wof:name": "HR6 8AT",
    "wof:placetype": "postalcode"
  },
  "geometry": {"coordinates":[-2.731863,52.225655],"type":"Point"}
}
