{
  "type": "Feature",
  "properties": {
    "date:inception_lower":"1985-10-01",
    "date:inception_upper":"1985-10-31",
    "iso:country":"GB",
    "wof:name":"EX5 5EJ",
    "wof:placetype":"postalcode"
},
  "geometry": {"coordinates":[-3.553288,50.751498],"type":"Point"}
}