{
  "type": "Feature",
  "properties": {
    "iso:country":"GB",
    "wof:name":"EX5 5EJ",
    "wof:placetype":"postalcode"
},
  "geometry": {"coordinates":[-3.55328830140329,50.75149763180382],"type":"Point"}
}