{
  "type": "Feature",
  "properties": {
    "iso:country": "GB",
    "wof:name": "RG7 1LJ",
    "wof:placetype": "postalcode"
  },
  "geometry": {"coordinates":[-1.009389,51.402818],"type":"Point"}
}
