{
  "type": "Feature",
  "properties": {
    "iso:country":"GB",
    "wof:name":"RG7 1LJ",
    "wof:placetype":"postalcode"
},
  "geometry": {"coordinates":[-1.00938928019475,51.40281832540816],"type":"Point"}
}