{
  "type": "Feature",
  "properties": {
    "iso:country":"GB",
    "wof:name":"SG18 9AT",
    "wof:placetype":"postalcode"
},
  "geometry": {"coordinates":[-0.27714802110032,52.08636019275948],"type":"Point"}
}