{
  "type": "Feature",
  "properties": {
    "iso:country": "GB",
    "wof:name": "SG18 9AT",
    "wof:placetype": "postalcode"
  },
  "geometry": {"coordinates":[-0.277148,52.08636],"type":"Point"}
}
