{
  "type": "Feature",
  "properties": {
    "iso:country":"GB",
    "wof:name":"NN7 2QE",
    "wof:placetype":"postalcode"
},
  "geometry": {"coordinates":[-0.88106205218707,52.17019659781366],"type":"Point"}
}