{
  "type": "Feature",
  "properties": {
    "iso:country": "GB",
    "wof:name": "DA9 9BP",
    "wof:placetype": "postalcode"
  },
  "geometry": {"coordinates":[0.266837,51.450739],"type":"Point"}
}
