{
  "type": "Feature",
  "properties": {
    "iso:country":"GB",
    "wof:name":"AL1 5NG",
    "wof:placetype":"postalcode"
},
  "geometry": {"coordinates":[-0.30825652337548,51.7477406973687],"type":"Point"}
}