{
  "type": "Feature",
  "properties": {
    "iso:country":"GB",
    "wof:name":"RG31 7PJ",
    "wof:placetype":"postalcode"
},
  "geometry": {"coordinates":[-1.0300159759636,51.44169181429362],"type":"Point"}
}