{
  "type": "Feature",
  "properties": {
    "iso:country": "GB",
    "wof:name": "NN10 6FA",
    "wof:placetype": "postalcode"
  },
  "geometry": {"coordinates":[-0.624952,52.301371],"type":"Point"}
}
