{
  "type": "Feature",
  "properties": {
    "date:inception_lower": "2008-07-01",
    "date:inception_upper": "2008-07-01",
    "iso:country": "GB",
    "wof:name": "GU35 5BD",
    "wof:placetype": "postalcode"
  },
  "geometry": {"coordinates":[-0.86054,51.118697],"type":"Point"}
}
