{
  "type": "Feature",
  "properties": {
    "iso:country":"GB",
    "wof:name":"M26 2PL",
    "wof:placetype":"postalcode"
},
  "geometry": {"coordinates":[-2.30628987145689,53.5712448943973],"type":"Point"}
}