{
  "type": "Feature",
  "properties": {
    "iso:country": "GB",
    "wof:name": "M26 2PL",
    "wof:placetype": "postalcode"
  },
  "geometry": {"coordinates":[-2.30629,53.571245],"type":"Point"}
}
