{
  "type": "Feature",
  "properties": {
    "date:inception_lower": "1994-05-01",
    "date:inception_upper": "1994-05-01",
    "iso:country": "GB",
    "wof:name": "M26 2PL",
    "wof:placetype": "postalcode"
  },
  "geometry": {"coordinates":[-2.30629,53.571245],"type":"Point"}
}
