{
  "type": "Feature",
  "properties": {
    "iso:country": "GB",
    "wof:name": "TS18 3BF",
    "wof:placetype": "postalcode"
  },
  "geometry": {"coordinates":[-1.320248,54.554532],"type":"Point"}
}
