{
  "type": "Feature",
  "properties": {
    "date:inception_lower":"2010-06-01",
    "date:inception_upper":"2010-06-30",
    "iso:country":"GB",
    "wof:name":"TS18 3BF",
    "wof:placetype":"postalcode"
},
  "geometry": {"coordinates":[-1.320248,54.554532],"type":"Point"}
}