{
  "type": "Feature",
  "properties": {
    "date:inception_lower": "2010-06-01",
    "date:inception_upper": "2010-06-01",
    "iso:country": "GB",
    "wof:name": "TS18 3BF",
    "wof:placetype": "postalcode"
  },
  "geometry": {"coordinates":[-1.320323,54.554509],"type":"Point"}
}
