{
  "type": "Feature",
  "properties": {
    "date:inception_lower":"1980-01-01",
    "date:inception_upper":"1980-01-31",
    "iso:country":"GB",
    "wof:name":"EN6 5HH",
    "wof:placetype":"postalcode"
},
  "geometry": {"coordinates":[-0.167134,51.698586],"type":"Point"}
}