{
  "type": "Feature",
  "properties": {
    "iso:country":"GB",
    "wof:name":"EN6 5HH",
    "wof:placetype":"postalcode"
},
  "geometry": {"coordinates":[-0.16713420405594,51.69858636413741],"type":"Point"}
}