{
  "type": "Feature",
  "properties": {
    "iso:country":"GB",
    "wof:name":"B10 9PA",
    "wof:placetype":"postalcode"
},
  "geometry": {"coordinates":[-1.84696404617944,52.47402013902986],"type":"Point"}
}