{
  "type": "Feature",
  "properties": {
    "date:inception_lower": "1980-01-01",
    "date:inception_upper": "1980-01-01",
    "iso:country": "GB",
    "wof:name": "B10 9PA",
    "wof:placetype": "postalcode"
  },
  "geometry": {"coordinates":[-1.8469,52.474044],"type":"Point"}
}
