{
  "type": "Feature",
  "properties": {
    "date:inception_lower": "1997-12-01",
    "date:inception_upper": "1997-12-01",
    "iso:country": "GB",
    "wof:name": "BS37 7QN",
    "wof:placetype": "postalcode"
  },
  "geometry": {"coordinates":[-2.404291,51.568404],"type":"Point"}
}
