{
  "type": "Feature",
  "properties": {
    "iso:country": "GB",
    "wof:name": "BS37 7QN",
    "wof:placetype": "postalcode"
  },
  "geometry": {"coordinates":[-2.404291,51.568404],"type":"Point"}
}
