{
  "type": "Feature",
  "properties": {
    "iso:country":"GB",
    "wof:name":"BS37 7QN",
    "wof:placetype":"postalcode"
},
  "geometry": {"coordinates":[-2.40429058190667,51.56840360900662],"type":"Point"}
}