{
  "type": "Feature",
  "properties": {
    "iso:country":"GB",
    "wof:name":"OL16 5NL",
    "wof:placetype":"postalcode"
},
  "geometry": {"coordinates":[-2.14401993531647,53.61110804734548],"type":"Point"}
}