{
  "type": "Feature",
  "properties": {
    "iso:country": "GB",
    "wof:name": "OL16 5NL",
    "wof:placetype": "postalcode"
  },
  "geometry": {"coordinates":[-2.14402,53.611108],"type":"Point"}
}
