{
  "type": "Feature",
  "properties": {
    "iso:country": "GB",
    "wof:name": "KT6 4DY",
    "wof:placetype": "postalcode"
  },
  "geometry": {"coordinates":[-0.30785,51.393512],"type":"Point"}
}
