{
  "type": "Feature",
  "properties": {
    "iso:country":"GB",
    "wof:name":"KT6 4DY",
    "wof:placetype":"postalcode"
},
  "geometry": {"coordinates":[-0.30791651514868,51.39348640053796],"type":"Point"}
}