{
  "type": "Feature",
  "properties": {
    "date:inception_lower": "1980-01-01",
    "date:inception_upper": "1980-01-01",
    "iso:country": "GB",
    "wof:name": "KT6 4DY",
    "wof:placetype": "postalcode"
  },
  "geometry": {"coordinates":[-0.307806,51.393529],"type":"Point"}
}
