{
  "type": "Feature",
  "properties": {
    "date:inception_lower": "2003-05-01",
    "date:inception_upper": "2003-05-01",
    "iso:country": "GB",
    "wof:name": "GL20 8GD",
    "wof:placetype": "postalcode"
  },
  "geometry": {"coordinates":[-2.126993,52.00561],"type":"Point"}
}
