{
  "type": "Feature",
  "properties": {
    "date:inception_lower": "2018-12-01",
    "date:inception_upper": "2018-12-01",
    "iso:country": "GB",
    "wof:name": "DN14 9FS",
    "wof:placetype": "postalcode"
  },
  "geometry": {"coordinates":[-1.021766,53.712232],"type":"Point"}
}
