{
  "type": "Feature",
  "properties": {
    "iso:country": "GB",
    "wof:name": "EX32 9AA",
    "wof:placetype": "postalcode"
  },
  "geometry": {"coordinates":[-4.050907,51.073544],"type":"Point"}
}
