{
  "type": "Feature",
  "properties": {
    "iso:country": "GB",
    "wof:name": "DE22 3XR",
    "wof:placetype": "postalcode"
  },
  "geometry": {"coordinates":[-1.509173,52.919036],"type":"Point"}
}
