{
  "type": "Feature",
  "properties": {
    "iso:country":"GB",
    "wof:name":"TF7 4EY",
    "wof:placetype":"postalcode"
},
  "geometry": {"coordinates":[-2.4436311635393,52.63125685241527],"type":"Point"}
}