{
  "type": "Feature",
  "properties": {
    "iso:country":"GB",
    "wof:name":"TS19 0GD",
    "wof:placetype":"postalcode"
},
  "geometry": {"coordinates":[-1.31949715172251,54.57084828763389],"type":"Point"}
}