{
  "type": "Feature",
  "properties": {
    "date:inception_lower":"2006-10-01",
    "date:inception_upper":"2006-10-31",
    "iso:country":"GB",
    "wof:name":"TS19 0GD",
    "wof:placetype":"postalcode"
},
  "geometry": {"coordinates":[-1.319497,54.570848],"type":"Point"}
}