{
  "type": "Feature",
  "properties": {
    "iso:country":"GB",
    "wof:name":"SY12 9DG",
    "wof:placetype":"postalcode"
},
  "geometry": {"coordinates":[-2.89648661543797,52.91035446334268],"type":"Point"}
}