{
  "type": "Feature",
  "properties": {
    "date:inception_lower":"1980-01-01",
    "date:inception_upper":"1980-01-31",
    "iso:country":"GB",
    "wof:name":"SY12 9DG",
    "wof:placetype":"postalcode"
},
  "geometry": {"coordinates":[-2.896487,52.910354],"type":"Point"}
}