{
  "type": "Feature",
  "properties": {
    "iso:country":"GB",
    "wof:name":"SE1 9PS",
    "wof:placetype":"postalcode"
},
  "geometry": {"coordinates":[-0.10796112933426,51.50721567037244],"type":"Point"}
}