{
  "type": "Feature",
  "properties": {
    "date:inception_lower":"2001-12-01",
    "date:inception_upper":"2001-12-31",
    "iso:country":"GB",
    "wof:name":"SE1 9PS",
    "wof:placetype":"postalcode"
},
  "geometry": {"coordinates":[-0.107961,51.507216],"type":"Point"}
}