{
  "type": "Feature",
  "properties": {
    "date:inception_lower": "1990-07-01",
    "date:inception_upper": "1990-07-01",
    "iso:country": "GB",
    "wof:name": "OX2 0QS",
    "wof:placetype": "postalcode"
  },
  "geometry": {"coordinates":[-1.292401,51.752629],"type":"Point"}
}
