{
  "type": "Feature",
  "properties": {
    "date:inception_lower":"1990-07-01",
    "date:inception_upper":"1990-07-31",
    "iso:country":"GB",
    "wof:name":"TQ5 9DD",
    "wof:placetype":"postalcode"
},
  "geometry": {"coordinates":[-3.502106,50.399264],"type":"Point"}
}