{
  "type": "Feature",
  "properties": {
    "iso:country": "GB",
    "wof:name": "TQ5 9DD",
    "wof:placetype": "postalcode"
  },
  "geometry": {"coordinates":[-3.502106,50.399264],"type":"Point"}
}
