{
  "type": "Feature",
  "properties": {
    "iso:country":"GB",
    "wof:name":"TQ5 9DD",
    "wof:placetype":"postalcode"
},
  "geometry": {"coordinates":[-3.50210564529786,50.3992637802203],"type":"Point"}
}