{
  "type": "Feature",
  "properties": {
    "iso:country": "GB",
    "wof:name": "TN17 2DP",
    "wof:placetype": "postalcode"
  },
  "geometry": {"coordinates":[0.592509,51.141778],"type":"Point"}
}
