{
  "type": "Feature",
  "properties": {
    "iso:country":"GB",
    "wof:name":"TN17 2DP",
    "wof:placetype":"postalcode"
},
  "geometry": {"coordinates":[0.5925085263191,51.14177784823378],"type":"Point"}
}