{
  "type": "Feature",
  "properties": {
    "iso:country":"GB",
    "wof:name":"NE61 5TS",
    "wof:placetype":"postalcode"
},
  "geometry": {"coordinates":[-1.53639203996745,55.21290092464073],"type":"Point"}
}