{
  "type": "Feature",
  "properties": {
    "iso:country":"GB",
    "wof:name":"M23 2EF",
    "wof:placetype":"postalcode"
},
  "geometry": {"coordinates":[-2.28748137594015,53.38069999289996],"type":"Point"}
}