{
  "type": "Feature",
  "properties": {
    "iso:country":"GB",
    "wof:name":"B20 1ES",
    "wof:placetype":"postalcode"
},
  "geometry": {"coordinates":[-1.93462942321585,52.52712345496681],"type":"Point"}
}