{
  "type": "Feature",
  "properties": {
    "iso:country":"GB",
    "wof:name":"ME7 4QL",
    "wof:placetype":"postalcode"
},
  "geometry": {"coordinates":[0.5558478874925,51.38637906023597],"type":"Point"}
}