{
  "type": "Feature",
  "properties": {
    "iso:country": "GB",
    "wof:name": "ME7 4QL",
    "wof:placetype": "postalcode"
  },
  "geometry": {"coordinates":[0.555848,51.386379],"type":"Point"}
}
