{
  "type": "Feature",
  "properties": {
    "iso:country": "GB",
    "wof:name": "AB33 8DP",
    "wof:placetype": "postalcode"
  },
  "geometry": {"coordinates":[-2.619482,57.221658],"type":"Point"}
}
