{
  "type": "Feature",
  "properties": {
    "iso:country":"GB",
    "wof:name":"AB33 8DP",
    "wof:placetype":"postalcode"
},
  "geometry": {"coordinates":[-2.61948183224045,57.2216582315756],"type":"Point"}
}