{
  "type": "Feature",
  "properties": {
    "iso:country":"GB",
    "wof:name":"TR15 2QA",
    "wof:placetype":"postalcode"
},
  "geometry": {"coordinates":[-5.2264778634303,50.23203041664883],"type":"Point"}
}