{
  "type": "Feature",
  "properties": {
    "iso:country":"GB",
    "wof:name":"CT2 7LX",
    "wof:placetype":"postalcode"
},
  "geometry": {"coordinates":[1.06542471502244,51.29616583363618],"type":"Point"}
}