{
  "type": "Feature",
  "properties": {
    "iso:country": "GB",
    "wof:name": "CM9 8QE",
    "wof:placetype": "postalcode"
  },
  "geometry": {"coordinates":[0.837022,51.758331],"type":"Point"}
}
