{
  "type": "Feature",
  "properties": {
    "iso:country":"GB",
    "wof:name":"SY6 7EH",
    "wof:placetype":"postalcode"
},
  "geometry": {"coordinates":[-2.79694968895488,52.53948809170397],"type":"Point"}
}