{
  "type": "Feature",
  "properties": {
    "iso:country": "GB",
    "wof:name": "SY6 7EH",
    "wof:placetype": "postalcode"
  },
  "geometry": {"coordinates":[-2.79695,52.539488],"type":"Point"}
}
