{
  "type": "Feature",
  "properties": {
    "iso:country": "GB",
    "wof:name": "MK17 0DT",
    "wof:placetype": "postalcode"
  },
  "geometry": {"coordinates":[-0.766817,51.976352],"type":"Point"}
}
