{
  "type": "Feature",
  "properties": {
    "iso:country":"GB",
    "wof:name":"MK17 0DT",
    "wof:placetype":"postalcode"
},
  "geometry": {"coordinates":[-0.76681747108749,51.97635184154118],"type":"Point"}
}