{
  "type": "Feature",
  "properties": {
    "date:inception_lower": "1982-03-01",
    "date:inception_upper": "1982-03-01",
    "iso:country": "GB",
    "wof:name": "MK17 0DT",
    "wof:placetype": "postalcode"
  },
  "geometry": {"coordinates":[-0.766817,51.976352],"type":"Point"}
}
