{
  "type": "Feature",
  "properties": {
    "iso:country":"GB",
    "wof:name":"W5 4LQ",
    "wof:placetype":"postalcode"
},
  "geometry": {"coordinates":[-0.30287973973639,51.50038741817711],"type":"Point"}
}