{
  "type": "Feature",
  "properties": {
    "date:inception_lower": "1995-01-01",
    "date:inception_upper": "1995-01-01",
    "iso:country": "GB",
    "wof:name": "W5 4LQ",
    "wof:placetype": "postalcode"
  },
  "geometry": {"coordinates":[-0.30288,51.500387],"type":"Point"}
}
