{
  "type": "Feature",
  "properties": {
    "date:inception_lower": "2008-09-01",
    "date:inception_upper": "2008-09-01",
    "iso:country": "GB",
    "wof:name": "TA6 3EF",
    "wof:placetype": "postalcode"
  },
  "geometry": {"coordinates":[-2.998224,51.123292],"type":"Point"}
}
