{
  "type": "Feature",
  "properties": {
    "iso:country": "GB",
    "wof:name": "TA6 3EF",
    "wof:placetype": "postalcode"
  },
  "geometry": {"coordinates":[-2.998224,51.123292],"type":"Point"}
}
