{
  "type": "Feature",
  "properties": {
    "iso:country":"GB",
    "wof:name":"TA6 3EF",
    "wof:placetype":"postalcode"
},
  "geometry": {"coordinates":[-2.9982240210713,51.12329197151642],"type":"Point"}
}