{
  "type": "Feature",
  "properties": {
    "iso:country":"GB",
    "wof:name":"EC3M 8AF",
    "wof:placetype":"postalcode"
},
  "geometry": {"coordinates":[-0.08380347390155,51.51113989291223],"type":"Point"}
}