{
  "type": "Feature",
  "properties": {
    "iso:country": "GB",
    "wof:name": "NE26 1HT",
    "wof:placetype": "postalcode"
  },
  "geometry": {"coordinates":[-1.458762,55.057041],"type":"Point"}
}
