{
  "type": "Feature",
  "properties": {
    "iso:country":"GB",
    "wof:name":"NE26 1HT",
    "wof:placetype":"postalcode"
},
  "geometry": {"coordinates":[-1.45876206017623,55.05704114362564],"type":"Point"}
}