{
  "type": "Feature",
  "properties": {
    "iso:country":"GB",
    "wof:name":"NG16 5BZ",
    "wof:placetype":"postalcode"
},
  "geometry": {"coordinates":[-1.30184972218379,53.04381498050237],"type":"Point"}
}