{
  "type": "Feature",
  "properties": {
    "date:inception_lower":"1980-01-01",
    "date:inception_upper":"1980-01-31",
    "iso:country":"GB",
    "wof:name":"NG16 5BZ",
    "wof:placetype":"postalcode"
},
  "geometry": {"coordinates":[-1.301802,53.043861],"type":"Point"}
}