{
  "type": "Feature",
  "properties": {
    "date:inception_lower": "2017-10-01",
    "date:inception_upper": "2017-10-01",
    "iso:country": "GB",
    "wof:name": "OX16 2DT",
    "wof:placetype": "postalcode"
  },
  "geometry": {"coordinates":[-1.332993,52.085537],"type":"Point"}
}
