{
  "type": "Feature",
  "properties": {
    "iso:country": "GB",
    "wof:name": "OX16 2DT",
    "wof:placetype": "postalcode"
  },
  "geometry": {"coordinates":[-1.332993,52.085537],"type":"Point"}
}
