{
  "type": "Feature",
  "properties": {
    "iso:country": "GB",
    "wof:name": "EH14 7AY",
    "wof:placetype": "postalcode"
  },
  "geometry": {"coordinates":[-3.330441,55.87673],"type":"Point"}
}
