{
  "type": "Feature",
  "properties": {
    "date:inception_lower":"1982-12-01",
    "date:inception_upper":"1982-12-31",
    "iso:country":"GB",
    "wof:name":"EH14 7AY",
    "wof:placetype":"postalcode"
},
  "geometry": {"coordinates":[-3.330441,55.87673],"type":"Point"}
}