{
  "type": "Feature",
  "properties": {
    "iso:country":"GB",
    "wof:name":"EH14 7AY",
    "wof:placetype":"postalcode"
},
  "geometry": {"coordinates":[-3.33044253880419,55.87672474316457],"type":"Point"}
}