{
  "type": "Feature",
  "properties": {
    "iso:country":"GB",
    "wof:name":"HA3 6QP",
    "wof:placetype":"postalcode"
},
  "geometry": {"coordinates":[-0.3498850851367,51.60780482969295],"type":"Point"}
}