{
  "type": "Feature",
  "properties": {
    "date:inception_lower":"1980-01-01",
    "date:inception_upper":"1980-01-31",
    "iso:country":"GB",
    "wof:name":"FK3 0HJ",
    "wof:placetype":"postalcode"
},
  "geometry": {"coordinates":[-3.722533,56.001174],"type":"Point"}
}