{
  "type": "Feature",
  "properties": {
    "iso:country":"GB",
    "wof:name":"CR0 1QG",
    "wof:placetype":"postalcode"
},
  "geometry": {"coordinates":[-0.09966486689727,51.37018632727],"type":"Point"}
}