{
  "type": "Feature",
  "properties": {
    "iso:country":"GB",
    "wof:name":"M15 5JY",
    "wof:placetype":"postalcode"
},
  "geometry": {"coordinates":[-2.25562451902662,53.46558845767272],"type":"Point"}
}