{
  "type": "Feature",
  "properties": {
    "iso:country": "GB",
    "wof:name": "M15 5JY",
    "wof:placetype": "postalcode"
  },
  "geometry": {"coordinates":[-2.255624,53.465588],"type":"Point"}
}
