{
  "type": "Feature",
  "properties": {
    "iso:country":"GB",
    "wof:name":"B60 4FG",
    "wof:placetype":"postalcode"
},
  "geometry": {"coordinates":[-2.07320387701233,52.30014648287561],"type":"Point"}
}