{
  "type": "Feature",
  "properties": {
    "date:inception_lower":"2008-01-01",
    "date:inception_upper":"2008-01-31",
    "iso:country":"GB",
    "wof:name":"B60 4FG",
    "wof:placetype":"postalcode"
},
  "geometry": {"coordinates":[-2.073182,52.299585],"type":"Point"}
}