{
  "type": "Feature",
  "properties": {
    "iso:country":"GB",
    "wof:name":"CA2 4TL",
    "wof:placetype":"postalcode"
},
  "geometry": {"coordinates":[-2.92519355194162,54.85935677425986],"type":"Point"}
}