{
  "type": "Feature",
  "properties": {
    "date:inception_lower": "2021-06-01",
    "date:inception_upper": "2021-06-01",
    "iso:country": "GB",
    "wof:name": "RG40 4AG",
    "wof:placetype": "postalcode"
  },
  "geometry": {"coordinates":[-0.899879,51.377151],"type":"Point"}
}
