{
  "type": "Feature",
  "properties": {
    "date:inception_lower": "1980-01-01",
    "date:inception_upper": "1980-01-01",
    "iso:country": "GB",
    "wof:name": "PO1 5AL",
    "wof:placetype": "postalcode"
  },
  "geometry": {"coordinates":[-1.076405,50.796527],"type":"Point"}
}
