{
  "type": "Feature",
  "properties": {
    "iso:country": "GB",
    "wof:name": "BS14 0JR",
    "wof:placetype": "postalcode"
  },
  "geometry": {"coordinates":[-2.566811,51.406287],"type":"Point"}
}
