{
  "type": "Feature",
  "properties": {
    "iso:country":"GB",
    "wof:name":"EX39 1DG",
    "wof:placetype":"postalcode"
},
  "geometry": {"coordinates":[-4.20862663478602,51.04187188841132],"type":"Point"}
}