{
  "type": "Feature",
  "properties": {
    "iso:country":"GB",
    "wof:name":"SO30 4AA",
    "wof:placetype":"postalcode"
},
  "geometry": {"coordinates":[-1.30316935381315,50.91327878113183],"type":"Point"}
}