{
  "type": "Feature",
  "properties": {
    "date:inception_lower": "1994-12-01",
    "date:inception_upper": "1994-12-01",
    "iso:country": "GB",
    "wof:name": "SO30 4AA",
    "wof:placetype": "postalcode"
  },
  "geometry": {"coordinates":[-1.303159,50.913234],"type":"Point"}
}
