{
  "type": "Feature",
  "properties": {
    "iso:country": "GB",
    "wof:name": "SY5 9QL",
    "wof:placetype": "postalcode"
  },
  "geometry": {"coordinates":[-2.954472,52.679718],"type":"Point"}
}
