{
  "type": "Feature",
  "properties": {
    "iso:country": "GB",
    "wof:name": "LS28 6HT",
    "wof:placetype": "postalcode"
  },
  "geometry": {"coordinates":[-1.661301,53.809543],"type":"Point"}
}
