{
  "type": "Feature",
  "properties": {
    "iso:country":"GB",
    "wof:name":"TQ7 3RB",
    "wof:placetype":"postalcode"
},
  "geometry": {"coordinates":[-3.80959967737846,50.29800101120008],"type":"Point"}
}