{
  "type": "Feature",
  "properties": {
    "date:inception_lower": "1980-01-01",
    "date:inception_upper": "1980-01-01",
    "iso:country": "GB",
    "wof:name": "TQ7 3RB",
    "wof:placetype": "postalcode"
  },
  "geometry": {"coordinates":[-3.8096,50.298001],"type":"Point"}
}
