{
  "type": "Feature",
  "properties": {
    "iso:country":"GB",
    "wof:name":"NR19 2NY",
    "wof:placetype":"postalcode"
},
  "geometry": {"coordinates":[0.90092682280925,52.68275761695035],"type":"Point"}
}