{
  "type": "Feature",
  "properties": {
    "iso:country":"GB",
    "wof:name":"DN3 1JU",
    "wof:placetype":"postalcode"
},
  "geometry": {"coordinates":[-1.06797071052391,53.56070117187512],"type":"Point"}
}