{
  "type": "Feature",
  "properties": {
    "iso:country": "GB",
    "wof:name": "EC1A 4LX",
    "wof:placetype": "postalcode"
  },
  "geometry": {"coordinates":[-0.097025,51.520737],"type":"Point"}
}
