{
  "type": "Feature",
  "properties": {
    "date:inception_lower": "2018-05-01",
    "date:inception_upper": "2018-05-01",
    "iso:country": "GB",
    "wof:name": "PE14 7NX",
    "wof:placetype": "postalcode"
  },
  "geometry": {"coordinates":[0.217294,52.728761],"type":"Point"}
}
