{
  "type": "Feature",
  "properties": {
    "date:inception_lower":"2018-05-01",
    "date:inception_upper":"2018-05-31",
    "iso:country":"GB",
    "wof:name":"PE14 7NX",
    "wof:placetype":"postalcode"
},
  "geometry": {"coordinates":[0.217386,52.728517],"type":"Point"}
}