{
  "type": "Feature",
  "properties": {
    "iso:country":"GB",
    "wof:name":"CT1 3TR",
    "wof:placetype":"postalcode"
},
  "geometry": {"coordinates":[1.0668848826124,51.27072682825816],"type":"Point"}
}