{
  "type": "Feature",
  "properties": {
    "date:inception_lower":"1998-12-01",
    "date:inception_upper":"1998-12-31",
    "iso:country":"GB",
    "wof:name":"PL18 9PQ",
    "wof:placetype":"postalcode"
},
  "geometry": {"coordinates":[-4.220807,50.516189],"type":"Point"}
}