{
  "type": "Feature",
  "properties": {
    "date:inception_lower": "2018-01-01",
    "date:inception_upper": "2018-01-01",
    "iso:country": "GB",
    "wof:name": "NN15 5GP",
    "wof:placetype": "postalcode"
  },
  "geometry": {"coordinates":[-0.671061,52.360618],"type":"Point"}
}
