{
  "type": "Feature",
  "properties": {
    "iso:country":"GB",
    "wof:name":"SA8 4BX",
    "wof:placetype":"postalcode"
},
  "geometry": {"coordinates":[-3.87027107717189,51.70435485917171],"type":"Point"}
}