{
  "type": "Feature",
  "properties": {
    "iso:country": "GB",
    "wof:name": "NW1 7QE",
    "wof:placetype": "postalcode"
  },
  "geometry": {"coordinates":[-0.141676,51.534966],"type":"Point"}
}
