{
  "type": "Feature",
  "properties": {
    "iso:country":"GB",
    "wof:name":"NW1 7QE",
    "wof:placetype":"postalcode"
},
  "geometry": {"coordinates":[-0.14167558428227,51.53496600571541],"type":"Point"}
}