{
  "type": "Feature",
  "properties": {
    "iso:country":"GB",
    "wof:name":"W1K 1JA",
    "wof:placetype":"postalcode"
},
  "geometry": {"coordinates":[-0.15153724982986,51.5082882444555],"type":"Point"}
}