{
  "type": "Feature",
  "properties": {
    "iso:country":"GB",
    "wof:name":"SY8 1DW",
    "wof:placetype":"postalcode"
},
  "geometry": {"coordinates":[-2.72515307087307,52.37701189394848],"type":"Point"}
}