{
  "type": "Feature",
  "properties": {
    "iso:country":"GB",
    "wof:name":"PL26 7QB",
    "wof:placetype":"postalcode"
},
  "geometry": {"coordinates":[-4.89756821786489,50.34938859345001],"type":"Point"}
}