{
  "type": "Feature",
  "properties": {
    "date:inception_lower": "1980-01-01",
    "date:inception_upper": "1980-01-01",
    "iso:country": "GB",
    "wof:name": "PL26 7QB",
    "wof:placetype": "postalcode"
  },
  "geometry": {"coordinates":[-4.897568,50.349389],"type":"Point"}
}
