{
  "type": "Feature",
  "properties": {
    "iso:country":"GB",
    "wof:name":"M22 0ER",
    "wof:placetype":"postalcode"
},
  "geometry": {"coordinates":[-2.25742046878405,53.37158229044662],"type":"Point"}
}