{
  "type": "Feature",
  "properties": {
    "date:inception_lower": "1984-10-01",
    "date:inception_upper": "1984-10-01",
    "iso:country": "GB",
    "wof:name": "PA1 2SA",
    "wof:placetype": "postalcode"
  },
  "geometry": {"coordinates":[-4.437696,55.846737],"type":"Point"}
}
