{
  "type": "Feature",
  "properties": {
    "iso:country":"GB",
    "wof:name":"PA1 2SA",
    "wof:placetype":"postalcode"
},
  "geometry": {"coordinates":[-4.43769602244194,55.8467368255485],"type":"Point"}
}