{
  "type": "Feature",
  "properties": {
    "date:inception_lower": "1994-12-01",
    "date:inception_upper": "1994-12-01",
    "iso:country": "GB",
    "wof:name": "NE46 1BJ",
    "wof:placetype": "postalcode"
  },
  "geometry": {"coordinates":[-2.09564,54.967688],"type":"Point"}
}
