{
  "type": "Feature",
  "properties": {
    "iso:country":"GB",
    "wof:name":"NE46 1BJ",
    "wof:placetype":"postalcode"
},
  "geometry": {"coordinates":[-2.09564003909094,54.96768772453582],"type":"Point"}
}