{
  "type": "Feature",
  "properties": {
    "iso:country": "GB",
    "wof:name": "AB11 6BP",
    "wof:placetype": "postalcode"
  },
  "geometry": {"coordinates":[-2.102176,57.145218],"type":"Point"}
}
