{
  "type": "Feature",
  "properties": {
    "iso:country": "GB",
    "wof:name": "YO16 6ZJ",
    "wof:placetype": "postalcode"
  },
  "geometry": {"coordinates":[-0.18027,54.103603],"type":"Point"}
}
