{
  "type": "Feature",
  "properties": {
    "iso:country": "GB",
    "wof:name": "LL13 9PB",
    "wof:placetype": "postalcode"
  },
  "geometry": {"coordinates":[-2.966544,53.039983],"type":"Point"}
}
