{
  "type": "Feature",
  "properties": {
    "iso:country":"GB",
    "wof:name":"LL13 9PB",
    "wof:placetype":"postalcode"
},
  "geometry": {"coordinates":[-2.96654398913688,53.03998271413091],"type":"Point"}
}