{
  "type": "Feature",
  "properties": {
    "iso:country":"GB",
    "wof:name":"PH13 9AX",
    "wof:placetype":"postalcode"
},
  "geometry": {"coordinates":[-3.26803728283898,56.54806617692306],"type":"Point"}
}