{
  "type": "Feature",
  "properties": {
    "iso:country":"GB",
    "wof:name":"BH11 8SL",
    "wof:placetype":"postalcode"
},
  "geometry": {"coordinates":[-1.91355894829455,50.75445796207833],"type":"Point"}
}