{
  "type": "Feature",
  "properties": {
    "iso:country":"GB",
    "wof:name":"PL20 6NA",
    "wof:placetype":"postalcode"
},
  "geometry": {"coordinates":[-4.05855081509443,50.49632709317725],"type":"Point"}
}