{
  "type": "Feature",
  "properties": {
    "iso:country": "GB",
    "wof:name": "PL20 6NA",
    "wof:placetype": "postalcode"
  },
  "geometry": {"coordinates":[-4.058551,50.496327],"type":"Point"}
}
