{
  "type": "Feature",
  "properties": {
    "date:inception_lower": "2021-12-01",
    "date:inception_upper": "2021-12-01",
    "iso:country": "GB",
    "wof:name": "CW6 0US",
    "wof:placetype": "postalcode"
  },
  "geometry": {"coordinates":[-2.674217,53.171755],"type":"Point"}
}
