{
  "type": "Feature",
  "properties": {
    "date:inception_lower": "1980-01-01",
    "date:inception_upper": "1980-01-01",
    "iso:country": "GB",
    "wof:name": "HP3 8JW",
    "wof:placetype": "postalcode"
  },
  "geometry": {"coordinates":[-0.448607,51.736081],"type":"Point"}
}
