{
  "type": "Feature",
  "properties": {
    "iso:country": "GB",
    "wof:name": "SN15 2NE",
    "wof:placetype": "postalcode"
  },
  "geometry": {"coordinates":[-2.138313,51.422465],"type":"Point"}
}
