{
  "type": "Feature",
  "properties": {
    "iso:country":"GB",
    "wof:name":"TS26 8RX",
    "wof:placetype":"postalcode"
},
  "geometry": {"coordinates":[-1.22266135376585,54.68981000477704],"type":"Point"}
}