{
  "type": "Feature",
  "properties": {
    "iso:country": "GB",
    "wof:name": "MK41 8RH",
    "wof:placetype": "postalcode"
  },
  "geometry": {"coordinates":[-0.442106,52.157215],"type":"Point"}
}
