{
  "type": "Feature",
  "properties": {
    "date:inception_lower": "2002-07-01",
    "date:inception_upper": "2002-07-01",
    "iso:country": "GB",
    "wof:name": "ML6 8GS",
    "wof:placetype": "postalcode"
  },
  "geometry": {"coordinates":[-3.941361,55.840268],"type":"Point"}
}
