{
  "type": "Feature",
  "properties": {
    "iso:country":"GB",
    "wof:name":"ML6 8GS",
    "wof:placetype":"postalcode"
},
  "geometry": {"coordinates":[-3.94136153933306,55.84026778535929],"type":"Point"}
}