{
  "type": "Feature",
  "properties": {
    "date:inception_lower":"2011-02-01",
    "date:inception_upper":"2011-02-28",
    "iso:country":"GB",
    "wof:name":"NR14 6SH",
    "wof:placetype":"postalcode"
},
  "geometry": {"coordinates":[1.563437,52.529551],"type":"Point"}
}