{
  "type": "Feature",
  "properties": {
    "iso:country": "GB",
    "wof:name": "NR14 6SH",
    "wof:placetype": "postalcode"
  },
  "geometry": {"coordinates":[1.563437,52.529551],"type":"Point"}
}
