{
  "type": "Feature",
  "properties": {
    "iso:country":"GB",
    "wof:name":"EX31 4HE",
    "wof:placetype":"postalcode"
},
  "geometry": {"coordinates":[-4.06410267492085,51.13041039935244],"type":"Point"}
}