{
  "type": "Feature",
  "properties": {
    "iso:country":"GB",
    "wof:name":"BA11 3RH",
    "wof:placetype":"postalcode"
},
  "geometry": {"coordinates":[-2.41495346329612,51.24463962325412],"type":"Point"}
}