{
  "type": "Feature",
  "properties": {
    "iso:country":"GB",
    "wof:name":"LS29 0PU",
    "wof:placetype":"postalcode"
},
  "geometry": {"coordinates":[-1.89738593564302,53.94495619221978],"type":"Point"}
}