{
  "type": "Feature",
  "properties": {
    "iso:country":"GB",
    "wof:name":"NG1 4FG",
    "wof:placetype":"postalcode"
},
  "geometry": {"coordinates":[-1.1494659059799,52.95752269326798],"type":"Point"}
}