{
  "type": "Feature",
  "properties": {
    "iso:country":"GB",
    "wof:name":"CW5 7DQ",
    "wof:placetype":"postalcode"
},
  "geometry": {"coordinates":[-2.51630164654334,53.05971644443896],"type":"Point"}
}