{
  "type": "Feature",
  "properties": {
    "date:inception_lower": "1981-06-01",
    "date:inception_upper": "1981-06-01",
    "iso:country": "GB",
    "wof:name": "CW5 7DQ",
    "wof:placetype": "postalcode"
  },
  "geometry": {"coordinates":[-2.516302,53.059716],"type":"Point"}
}
