{
  "type": "Feature",
  "properties": {
    "date:inception_lower":"1980-01-01",
    "date:inception_upper":"1980-01-31",
    "iso:country":"GB",
    "wof:name":"G76 9DJ",
    "wof:placetype":"postalcode"
},
  "geometry": {"coordinates":[-4.234075,55.79215],"type":"Point"}
}