{
  "type": "Feature",
  "properties": {
    "iso:country": "GB",
    "wof:name": "SA1 4QX",
    "wof:placetype": "postalcode"
  },
  "geometry": {"coordinates":[-3.960772,51.616686],"type":"Point"}
}
