{
  "type": "Feature",
  "properties": {
    "iso:country":"GB",
    "wof:name":"SA1 4QX",
    "wof:placetype":"postalcode"
},
  "geometry": {"coordinates":[-3.96077228580028,51.6166862956988],"type":"Point"}
}