{
  "type": "Feature",
  "properties": {
    "iso:country":"GB",
    "wof:name":"BB5 3RE",
    "wof:placetype":"postalcode"
},
  "geometry": {"coordinates":[-2.42420906475604,53.74737765966596],"type":"Point"}
}