{
  "type": "Feature",
  "properties": {
    "iso:country":"GB",
    "wof:name":"SL6 4LR",
    "wof:placetype":"postalcode"
},
  "geometry": {"coordinates":[-0.74186742892659,51.51990888881009],"type":"Point"}
}