{
  "type": "Feature",
  "properties": {
    "iso:country":"GB",
    "wof:name":"NN14 3JD",
    "wof:placetype":"postalcode"
},
  "geometry": {"coordinates":[-0.5901387707109,52.45995729488959],"type":"Point"}
}