{
  "type": "Feature",
  "properties": {
    "date:inception_lower": "1980-01-01",
    "date:inception_upper": "1980-01-01",
    "iso:country": "GB",
    "wof:name": "NN14 3JD",
    "wof:placetype": "postalcode"
  },
  "geometry": {"coordinates":[-0.572419,52.462162],"type":"Point"}
}
