{
  "type": "Feature",
  "properties": {
    "iso:country": "GB",
    "wof:name": "NN14 3JD",
    "wof:placetype": "postalcode"
  },
  "geometry": {"coordinates":[-0.590122,52.459974],"type":"Point"}
}
