{
  "type": "Feature",
  "properties": {
    "iso:country":"GB",
    "wof:name":"SK8 2AA",
    "wof:placetype":"postalcode"
},
  "geometry": {"coordinates":[-2.2116952817622,53.39487180988005],"type":"Point"}
}