{
  "type": "Feature",
  "properties": {
    "date:inception_lower": "2002-08-01",
    "date:inception_upper": "2002-08-01",
    "iso:country": "GB",
    "wof:name": "EN5 4LH",
    "wof:placetype": "postalcode"
  },
  "geometry": {"coordinates":[-0.203883,51.657826],"type":"Point"}
}
