{
  "type": "Feature",
  "properties": {
    "iso:country": "GB",
    "wof:name": "EN5 4LH",
    "wof:placetype": "postalcode"
  },
  "geometry": {"coordinates":[-0.203883,51.657826],"type":"Point"}
}
