{
  "type": "Feature",
  "properties": {
    "iso:country": "GB",
    "wof:name": "IG10 3RP",
    "wof:placetype": "postalcode"
  },
  "geometry": {"coordinates":[0.081062,51.64501],"type":"Point"}
}
