{
  "type": "Feature",
  "properties": {
    "iso:country":"GB",
    "wof:name":"IG10 3RP",
    "wof:placetype":"postalcode"
},
  "geometry": {"coordinates":[0.08106197515815,51.64501017759832],"type":"Point"}
}