{
  "type": "Feature",
  "properties": {
    "iso:country":"GB",
    "wof:name":"TF12 5PH",
    "wof:placetype":"postalcode"
},
  "geometry": {"coordinates":[-2.48357297163593,52.61832594576709],"type":"Point"}
}