{
  "type": "Feature",
  "properties": {
    "iso:country":"GB",
    "wof:name":"CA28 6NU",
    "wof:placetype":"postalcode"
},
  "geometry": {"coordinates":[-3.58229587062152,54.5662490843216],"type":"Point"}
}