{
  "type": "Feature",
  "properties": {
    "date:inception_lower": "2005-06-01",
    "date:inception_upper": "2005-06-01",
    "iso:country": "GB",
    "wof:name": "CA28 6NU",
    "wof:placetype": "postalcode"
  },
  "geometry": {"coordinates":[-3.582297,54.566256],"type":"Point"}
}
