{
  "type": "Feature",
  "properties": {
    "iso:country":"GB",
    "wof:name":"SG2 8DH",
    "wof:placetype":"postalcode"
},
  "geometry": {"coordinates":[-0.18562652312377,51.88397518806878],"type":"Point"}
}