{
  "type": "Feature",
  "properties": {
    "iso:country":"GB",
    "wof:name":"GL17 9XG",
    "wof:placetype":"postalcode"
},
  "geometry": {"coordinates":[-2.55039189068472,51.85364940214541],"type":"Point"}
}