{
  "type": "Feature",
  "properties": {
    "date:inception_lower":"1980-01-01",
    "date:inception_upper":"1980-01-31",
    "iso:country":"GB",
    "wof:name":"BH9 3NL",
    "wof:placetype":"postalcode"
},
  "geometry": {"coordinates":[-1.86815,50.760665],"type":"Point"}
}