{
  "type": "Feature",
  "properties": {
    "iso:country": "GB",
    "wof:name": "BH9 3NL",
    "wof:placetype": "postalcode"
  },
  "geometry": {"coordinates":[-1.86815,50.760665],"type":"Point"}
}
