{
  "type": "Feature",
  "properties": {
    "iso:country": "GB",
    "wof:name": "PE29 2DD",
    "wof:placetype": "postalcode"
  },
  "geometry": {"coordinates":[-0.164273,52.315873],"type":"Point"}
}
