{
  "type": "Feature",
  "properties": {
    "iso:country":"GB",
    "wof:name":"PE29 2DD",
    "wof:placetype":"postalcode"
},
  "geometry": {"coordinates":[-0.16427281785653,52.3158734775306],"type":"Point"}
}