{
  "type": "Feature",
  "properties": {
    "date:inception_lower":"2000-06-01",
    "date:inception_upper":"2000-06-30",
    "iso:country":"GB",
    "wof:name":"PE29 2DD",
    "wof:placetype":"postalcode"
},
  "geometry": {"coordinates":[-0.164273,52.315873],"type":"Point"}
}