{
  "type": "Feature",
  "properties": {
    "iso:country":"GB",
    "wof:name":"NN3 3NA",
    "wof:placetype":"postalcode"
},
  "geometry": {"coordinates":[-0.8573435109143,52.24441326473071],"type":"Point"}
}