{
  "type": "Feature",
  "properties": {
    "iso:country":"GB",
    "wof:name":"CA1 3TP",
    "wof:placetype":"postalcode"
},
  "geometry": {"coordinates":[-2.88909762750681,54.87914560749554],"type":"Point"}
}