{
  "type": "Feature",
  "properties": {
    "iso:country": "GB",
    "wof:name": "CA1 3TP",
    "wof:placetype": "postalcode"
  },
  "geometry": {"coordinates":[-2.889098,54.879146],"type":"Point"}
}
