{
  "type": "Feature",
  "properties": {
    "iso:country": "GB",
    "wof:name": "WA4 4GF",
    "wof:placetype": "postalcode"
  },
  "geometry": {"coordinates":[-2.544842,53.348564],"type":"Point"}
}
