{
  "type": "Feature",
  "properties": {
    "date:inception_lower": "2019-04-01",
    "date:inception_upper": "2019-04-01",
    "iso:country": "GB",
    "wof:name": "WA4 4GF",
    "wof:placetype": "postalcode"
  },
  "geometry": {"coordinates":[-2.544887,53.348528],"type":"Point"}
}
