{
  "type": "Feature",
  "properties": {
    "iso:country":"GB",
    "wof:name":"LS11 6LH",
    "wof:placetype":"postalcode"
},
  "geometry": {"coordinates":[-1.54978807592035,53.77278395690212],"type":"Point"}
}