{
  "type": "Feature",
  "properties": {
    "iso:country": "GB",
    "wof:name": "CV37 9SH",
    "wof:placetype": "postalcode"
  },
  "geometry": {"coordinates":[-1.752473,52.17205],"type":"Point"}
}
