{
  "type": "Feature",
  "properties": {
    "iso:country":"GB",
    "wof:name":"TN30 6LD",
    "wof:placetype":"postalcode"
},
  "geometry": {"coordinates":[0.68548316602179,51.06682617507703],"type":"Point"}
}