{
  "type": "Feature",
  "properties": {
    "iso:country":"GB",
    "wof:name":"BB1 9GD",
    "wof:placetype":"postalcode"
},
  "geometry": {"coordinates":[-2.47979753451506,53.76852366636075],"type":"Point"}
}