{
  "type": "Feature",
  "properties": {
    "date:inception_lower": "1997-06-01",
    "date:inception_upper": "1997-06-01",
    "iso:country": "GB",
    "wof:name": "BB1 9GD",
    "wof:placetype": "postalcode"
  },
  "geometry": {"coordinates":[-2.479797,53.768524],"type":"Point"}
}
