{
  "type": "Feature",
  "properties": {
    "iso:country":"GB",
    "wof:name":"E16 1PW",
    "wof:placetype":"postalcode"
},
  "geometry": {"coordinates":[0.02344679311278,51.51600211602197],"type":"Point"}
}