{
  "type": "Feature",
  "properties": {
    "iso:country":"GB",
    "wof:name":"CW7 2HS",
    "wof:placetype":"postalcode"
},
  "geometry": {"coordinates":[-2.54496696885623,53.1956473203666],"type":"Point"}
}