{
  "type": "Feature",
  "properties": {
    "date:inception_lower": "1980-01-01",
    "date:inception_upper": "1980-01-01",
    "iso:country": "GB",
    "wof:name": "HG4 2RF",
    "wof:placetype": "postalcode"
  },
  "geometry": {"coordinates":[-1.544133,54.144835],"type":"Point"}
}
