{
  "type": "Feature",
  "properties": {
    "iso:country":"GB",
    "wof:name":"HG4 2RF",
    "wof:placetype":"postalcode"
},
  "geometry": {"coordinates":[-1.54395868639922,54.14474001689729],"type":"Point"}
}