{
  "type": "Feature",
  "properties": {
    "date:inception_lower":"1980-01-01",
    "date:inception_upper":"1980-01-31",
    "iso:country":"GB",
    "wof:name":"LD8 2SB",
    "wof:placetype":"postalcode"
},
  "geometry": {"coordinates":[-3.080815,52.254008],"type":"Point"}
}