{
  "type": "Feature",
  "properties": {
    "iso:country": "GB",
    "wof:name": "LD8 2SB",
    "wof:placetype": "postalcode"
  },
  "geometry": {"coordinates":[-3.080815,52.254008],"type":"Point"}
}
