{
  "type": "Feature",
  "properties": {
    "iso:country":"GB",
    "wof:name":"WV16 6GB",
    "wof:placetype":"postalcode"
},
  "geometry": {"coordinates":[-2.43998302571123,52.44566421948402],"type":"Point"}
}