{
  "type": "Feature",
  "properties": {
    "iso:country": "GB",
    "wof:name": "WV16 6GB",
    "wof:placetype": "postalcode"
  },
  "geometry": {"coordinates":[-2.440126,52.445552],"type":"Point"}
}
