{
  "type": "Feature",
  "properties": {
    "date:inception_lower": "2010-03-01",
    "date:inception_upper": "2010-03-01",
    "iso:country": "GB",
    "wof:name": "WV16 6GB",
    "wof:placetype": "postalcode"
  },
  "geometry": {"coordinates":[-2.439888,52.445265],"type":"Point"}
}
