{
  "type": "Feature",
  "properties": {
    "iso:country":"GB",
    "wof:name":"DY6 7RU",
    "wof:placetype":"postalcode"
},
  "geometry": {"coordinates":[-2.16657959840802,52.50867536968527],"type":"Point"}
}