{
  "type": "Feature",
  "properties": {
    "date:inception_lower": "1980-01-01",
    "date:inception_upper": "1980-01-01",
    "iso:country": "GB",
    "wof:name": "DY6 7RU",
    "wof:placetype": "postalcode"
  },
  "geometry": {"coordinates":[-2.16658,52.508675],"type":"Point"}
}
