{
  "type": "Feature",
  "properties": {
    "iso:country":"GB",
    "wof:name":"LS16 5DX",
    "wof:placetype":"postalcode"
},
  "geometry": {"coordinates":[-1.60753378129101,53.83482426156921],"type":"Point"}
}