{
  "type": "Feature",
  "properties": {
    "iso:country": "GB",
    "wof:name": "L25 3RT",
    "wof:placetype": "postalcode"
  },
  "geometry": {"coordinates":[-2.852314,53.387036],"type":"Point"}
}
