{
  "type": "Feature",
  "properties": {
    "iso:country": "GB",
    "wof:name": "NN7 3ED",
    "wof:placetype": "postalcode"
  },
  "geometry": {"coordinates":[-0.948469,52.184546],"type":"Point"}
}
