{
  "type": "Feature",
  "properties": {
    "iso:country":"GB",
    "wof:name":"NN7 3ED",
    "wof:placetype":"postalcode"
},
  "geometry": {"coordinates":[-0.9484687240942,52.18454550811324],"type":"Point"}
}