{
  "type": "Feature",
  "properties": {
    "date:inception_lower": "1980-01-01",
    "date:inception_upper": "1980-01-01",
    "iso:country": "GB",
    "wof:name": "NN7 3ED",
    "wof:placetype": "postalcode"
  },
  "geometry": {"coordinates":[-0.948469,52.184546],"type":"Point"}
}
