{
  "type": "Feature",
  "properties": {
    "date:inception_lower": "1980-01-01",
    "date:inception_upper": "1980-01-01",
    "iso:country": "GB",
    "wof:name": "CW10 9DT",
    "wof:placetype": "postalcode"
  },
  "geometry": {"coordinates":[-2.449377,53.195426],"type":"Point"}
}
