{
  "type": "Feature",
  "properties": {
    "iso:country":"GB",
    "wof:name":"DG3 4BL",
    "wof:placetype":"postalcode"
},
  "geometry": {"coordinates":[-3.81403503618728,55.23344287097335],"type":"Point"}
}