{
  "type": "Feature",
  "properties": {
    "iso:country":"GB",
    "wof:name":"DN6 9NT",
    "wof:placetype":"postalcode"
},
  "geometry": {"coordinates":[-1.17562335015369,53.6223257677885],"type":"Point"}
}