{
  "type": "Feature",
  "properties": {
    "iso:country": "GB",
    "wof:name": "DN31 3JP",
    "wof:placetype": "postalcode"
  },
  "geometry": {"coordinates":[-0.078391,53.573097],"type":"Point"}
}
