{
  "type": "Feature",
  "properties": {
    "date:inception_lower": "1980-01-01",
    "date:inception_upper": "1980-01-01",
    "iso:country": "GB",
    "wof:name": "DN31 3JP",
    "wof:placetype": "postalcode"
  },
  "geometry": {"coordinates":[-0.078337,53.573102],"type":"Point"}
}
