{
  "type": "Feature",
  "properties": {
    "date:inception_lower": "2019-09-01",
    "date:inception_upper": "2019-09-01",
    "iso:country": "GB",
    "wof:name": "PR4 6FN",
    "wof:placetype": "postalcode"
  },
  "geometry": {"coordinates":[-2.836513,53.697064],"type":"Point"}
}
