{
  "type": "Feature",
  "properties": {
    "iso:country":"GB",
    "wof:name":"SL3 6RG",
    "wof:placetype":"postalcode"
},
  "geometry": {"coordinates":[-0.5560136501742,51.52153626394707],"type":"Point"}
}