{
  "type": "Feature",
  "properties": {
    "iso:country": "GB",
    "wof:name": "LL15 1JF",
    "wof:placetype": "postalcode"
  },
  "geometry": {"coordinates":[-3.299074,53.11338],"type":"Point"}
}
