{
  "type": "Feature",
  "properties": {
    "iso:country": "GB",
    "wof:name": "HP23 6NR",
    "wof:placetype": "postalcode"
  },
  "geometry": {"coordinates":[-0.689145,51.748964],"type":"Point"}
}
