{
  "type": "Feature",
  "properties": {
    "iso:country":"GB",
    "wof:name":"WN2 3LW",
    "wof:placetype":"postalcode"
},
  "geometry": {"coordinates":[-2.57414981519453,53.53489804354903],"type":"Point"}
}