{
  "type": "Feature",
  "properties": {
    "iso:country":"GB",
    "wof:name":"BL8 4EH",
    "wof:placetype":"postalcode"
},
  "geometry": {"coordinates":[-2.33515645894151,53.63157779053279],"type":"Point"}
}