{
  "type": "Feature",
  "properties": {
    "iso:country": "GB",
    "wof:name": "BL8 4EH",
    "wof:placetype": "postalcode"
  },
  "geometry": {"coordinates":[-2.335156,53.631578],"type":"Point"}
}
