{
  "type": "Feature",
  "properties": {
    "iso:country":"GB",
    "wof:name":"GL6 8HW",
    "wof:placetype":"postalcode"
},
  "geometry": {"coordinates":[-2.14101853895655,51.71929553158385],"type":"Point"}
}