{
  "type": "Feature",
  "properties": {
    "date:inception_lower": "1980-01-01",
    "date:inception_upper": "1980-01-01",
    "iso:country": "GB",
    "wof:name": "WF12 0DS",
    "wof:placetype": "postalcode"
  },
  "geometry": {"coordinates":[-1.627183,53.661543],"type":"Point"}
}
