{
  "type": "Feature",
  "properties": {
    "iso:country":"GB",
    "wof:name":"S11 8PY",
    "wof:placetype":"postalcode"
},
  "geometry": {"coordinates":[-1.49773986707319,53.36905211975665],"type":"Point"}
}