{
  "type": "Feature",
  "properties": {
    "iso:country":"GB",
    "wof:name":"SL6 5ER",
    "wof:placetype":"postalcode"
},
  "geometry": {"coordinates":[-0.75446131987395,51.52742561609404],"type":"Point"}
}