{
  "type": "Feature",
  "properties": {
    "date:inception_lower": "1997-12-01",
    "date:inception_upper": "1997-12-01",
    "iso:country": "GB",
    "wof:name": "BS31 2DQ",
    "wof:placetype": "postalcode"
  },
  "geometry": {"coordinates":[-2.500766,51.418313],"type":"Point"}
}
