{
  "type": "Feature",
  "properties": {
    "date:inception_lower": "2018-03-01",
    "date:inception_upper": "2018-03-01",
    "iso:country": "GB",
    "wof:name": "E3 2XN",
    "wof:placetype": "postalcode"
  },
  "geometry": {"coordinates":[-0.022668,51.540495],"type":"Point"}
}
