{
  "type": "Feature",
  "properties": {
    "iso:country":"GB",
    "wof:name":"HP10 9BH",
    "wof:placetype":"postalcode"
},
  "geometry": {"coordinates":[-0.71001469314471,51.59638069871039],"type":"Point"}
}