{
  "type": "Feature",
  "properties": {
    "date:inception_lower":"2011-07-01",
    "date:inception_upper":"2011-07-31",
    "iso:country":"GB",
    "wof:name":"SA14 9UJ",
    "wof:placetype":"postalcode"
},
  "geometry": {"coordinates":[-4.101401,51.684611],"type":"Point"}
}