{
  "type": "Feature",
  "properties": {
    "iso:country":"GB",
    "wof:name":"SA14 9UJ",
    "wof:placetype":"postalcode"
},
  "geometry": {"coordinates":[-4.10140122406554,51.68461050917416],"type":"Point"}
}