{
  "type": "Feature",
  "properties": {
    "iso:country": "GB",
    "wof:name": "SA14 9UJ",
    "wof:placetype": "postalcode"
  },
  "geometry": {"coordinates":[-4.101401,51.684611],"type":"Point"}
}
