{
  "type": "Feature",
  "properties": {
    "date:inception_lower": "2021-11-01",
    "date:inception_upper": "2021-11-01",
    "iso:country": "GB",
    "wof:name": "SO21 1LG",
    "wof:placetype": "postalcode"
  },
  "geometry": {"coordinates":[-1.27815,51.017154],"type":"Point"}
}
