{
  "type": "Feature",
  "properties": {
    "date:inception_lower": "1980-01-01",
    "date:inception_upper": "1980-01-01",
    "iso:country": "GB",
    "wof:name": "BA2 7AY",
    "wof:placetype": "postalcode"
  },
  "geometry": {"coordinates":[-2.327157,51.379324],"type":"Point"}
}
