{
  "type": "Feature",
  "properties": {
    "iso:country":"GB",
    "wof:name":"BA2 7AY",
    "wof:placetype":"postalcode"
},
  "geometry": {"coordinates":[-2.33067314112076,51.38044141925436],"type":"Point"}
}