{
  "type": "Feature",
  "properties": {
    "date:inception_lower":"2012-11-01",
    "date:inception_upper":"2012-11-30",
    "iso:country":"GB",
    "wof:name":"LU7 4BY",
    "wof:placetype":"postalcode"
},
  "geometry": {"coordinates":[-0.64018,51.905643],"type":"Point"}
}