{
  "type": "Feature",
  "properties": {
    "iso:country": "GB",
    "wof:name": "CR0 8JB",
    "wof:placetype": "postalcode"
  },
  "geometry": {"coordinates":[-0.031332,51.366216],"type":"Point"}
}
