{
  "type": "Feature",
  "properties": {
    "date:inception_lower": "2022-05-01",
    "date:inception_upper": "2022-05-01",
    "iso:country": "GB",
    "wof:name": "PR3 1XP",
    "wof:placetype": "postalcode"
  },
  "geometry": {"coordinates":[-2.781788,53.896971],"type":"Point"}
}
