{
  "type": "Feature",
  "properties": {
    "date:inception_lower": "1980-01-01",
    "date:inception_upper": "1980-01-01",
    "iso:country": "GB",
    "wof:name": "PO33 4BP",
    "wof:placetype": "postalcode"
  },
  "geometry": {"coordinates":[-1.177147,50.710024],"type":"Point"}
}
