{
  "type": "Feature",
  "properties": {
    "iso:country":"GB",
    "wof:name":"LE4 3GD",
    "wof:placetype":"postalcode"
},
  "geometry": {"coordinates":[-1.13024194696352,52.68124646055735],"type":"Point"}
}