{
  "type": "Feature",
  "properties": {
    "date:inception_lower": "2006-05-01",
    "date:inception_upper": "2006-05-01",
    "iso:country": "GB",
    "wof:name": "LE3 9SJ",
    "wof:placetype": "postalcode"
  },
  "geometry": {"coordinates":[-1.18282,52.658696],"type":"Point"}
}
