{
  "type": "Feature",
  "properties": {
    "iso:country":"GB",
    "wof:name":"DH7 7PR",
    "wof:placetype":"postalcode"
},
  "geometry": {"coordinates":[-1.66452665512719,54.78106552247064],"type":"Point"}
}