{
  "type": "Feature",
  "properties": {
    "iso:country": "GB",
    "wof:name": "WV6 7DS",
    "wof:placetype": "postalcode"
  },
  "geometry": {"coordinates":[-2.262691,52.585769],"type":"Point"}
}
