{
  "type": "Feature",
  "properties": {
    "iso:country":"GB",
    "wof:name":"WV6 7DS",
    "wof:placetype":"postalcode"
},
  "geometry": {"coordinates":[-2.26269115953164,52.58576886426514],"type":"Point"}
}