{
  "type": "Feature",
  "properties": {
    "iso:country":"GB",
    "wof:name":"CO14 8QN",
    "wof:placetype":"postalcode"
},
  "geometry": {"coordinates":[1.26302908765653,51.85046970902895],"type":"Point"}
}