{
  "type": "Feature",
  "properties": {
    "date:inception_lower": "1980-01-01",
    "date:inception_upper": "1980-01-01",
    "iso:country": "GB",
    "wof:name": "CO14 8QN",
    "wof:placetype": "postalcode"
  },
  "geometry": {"coordinates":[1.263029,51.85047],"type":"Point"}
}
