{
  "type": "Feature",
  "properties": {
    "iso:country":"GB",
    "wof:name":"NW1 8LL",
    "wof:placetype":"postalcode"
},
  "geometry": {"coordinates":[-0.15374571657348,51.54027329808667],"type":"Point"}
}