{
  "type": "Feature",
  "properties": {
    "iso:country":"GB",
    "wof:name":"PO6 4NE",
    "wof:placetype":"postalcode"
},
  "geometry": {"coordinates":[-1.10606996335907,50.85478830845673],"type":"Point"}
}