{
  "type": "Feature",
  "properties": {
    "iso:country": "GB",
    "wof:name": "SY13 4RH",
    "wof:placetype": "postalcode"
  },
  "geometry": {"coordinates":[-2.730553,52.993444],"type":"Point"}
}
