{
  "type": "Feature",
  "properties": {
    "date:inception_lower": "2019-10-01",
    "date:inception_upper": "2019-10-01",
    "iso:country": "GB",
    "wof:name": "SY13 4RH",
    "wof:placetype": "postalcode"
  },
  "geometry": {"coordinates":[-2.730496,52.993598],"type":"Point"}
}
