{
  "type": "Feature",
  "properties": {
    "date:inception_lower": "2019-11-01",
    "date:inception_upper": "2019-11-01",
    "iso:country": "GB",
    "wof:name": "CO10 8RF",
    "wof:placetype": "postalcode"
  },
  "geometry": {"coordinates":[0.580811,52.076597],"type":"Point"}
}
