{
  "type": "Feature",
  "properties": {
    "iso:country": "GB",
    "wof:name": "CO10 8RF",
    "wof:placetype": "postalcode"
  },
  "geometry": {"coordinates":[0.580811,52.076597],"type":"Point"}
}
