{
  "type": "Feature",
  "properties": {
    "iso:country":"GB",
    "wof:name":"DL16 6LD",
    "wof:placetype":"postalcode"
},
  "geometry": {"coordinates":[-1.59596068496566,54.71394246779259],"type":"Point"}
}