{
  "type": "Feature",
  "properties": {
    "date:inception_lower": "1980-01-01",
    "date:inception_upper": "1980-01-01",
    "iso:country": "GB",
    "wof:name": "DL16 6LD",
    "wof:placetype": "postalcode"
  },
  "geometry": {"coordinates":[-1.59611,54.713953],"type":"Point"}
}
