{
  "type": "Feature",
  "properties": {
    "date:inception_lower": "2018-08-01",
    "date:inception_upper": "2018-08-01",
    "iso:country": "GB",
    "wof:name": "YO17 8FA",
    "wof:placetype": "postalcode"
  },
  "geometry": {"coordinates":[-0.534247,54.178128],"type":"Point"}
}
