{
  "type": "Feature",
  "properties": {
    "iso:country":"GB",
    "wof:name":"ME15 9LN",
    "wof:placetype":"postalcode"
},
  "geometry": {"coordinates":[0.55018927130491,51.24287313785742],"type":"Point"}
}