{
  "type": "Feature",
  "properties": {
    "date:inception_lower":"2012-06-01",
    "date:inception_upper":"2012-06-30",
    "iso:country":"GB",
    "wof:name":"BS16 1QB",
    "wof:placetype":"postalcode"
},
  "geometry": {"coordinates":[-2.558352,51.495308],"type":"Point"}
}