{
  "type": "Feature",
  "properties": {
    "iso:country":"GB",
    "wof:name":"BS16 1QB",
    "wof:placetype":"postalcode"
},
  "geometry": {"coordinates":[-2.5584371860331,51.49531743154792],"type":"Point"}
}