{
  "type": "Feature",
  "properties": {
    "iso:country":"GB",
    "wof:name":"OL3 5JS",
    "wof:placetype":"postalcode"
},
  "geometry": {"coordinates":[-1.99005873208107,53.55900868822521],"type":"Point"}
}