{
  "type": "Feature",
  "properties": {
    "iso:country":"GB",
    "wof:name":"L36 8DT",
    "wof:placetype":"postalcode"
},
  "geometry": {"coordinates":[-2.84887370412447,53.42795094805285],"type":"Point"}
}