{
  "type": "Feature",
  "properties": {
    "date:inception_lower": "2015-02-01",
    "date:inception_upper": "2015-02-01",
    "iso:country": "GB",
    "wof:name": "L36 8DT",
    "wof:placetype": "postalcode"
  },
  "geometry": {"coordinates":[-2.848862,53.428138],"type":"Point"}
}
