{
  "type": "Feature",
  "properties": {
    "iso:country": "GB",
    "wof:name": "L36 8DT",
    "wof:placetype": "postalcode"
  },
  "geometry": {"coordinates":[-2.848816,53.428129],"type":"Point"}
}
