{
  "type": "Feature",
  "properties": {
    "iso:country":"GB",
    "wof:name":"TS21 2EB",
    "wof:placetype":"postalcode"
},
  "geometry": {"coordinates":[-1.44314797679916,54.65136445865013],"type":"Point"}
}