{
  "type": "Feature",
  "properties": {
    "iso:country":"GB",
    "wof:name":"EH23 4AS",
    "wof:placetype":"postalcode"
},
  "geometry": {"coordinates":[-3.0558353276413,55.85125351014401],"type":"Point"}
}