{
  "type": "Feature",
  "properties": {
    "iso:country": "GB",
    "wof:name": "LD2 3BQ",
    "wof:placetype": "postalcode"
  },
  "geometry": {"coordinates":[-3.363414,52.042588],"type":"Point"}
}
