{
  "type": "Feature",
  "properties": {
    "iso:country":"GB",
    "wof:name":"LD2 3BQ",
    "wof:placetype":"postalcode"
},
  "geometry": {"coordinates":[-3.36341357088891,52.04258761954063],"type":"Point"}
}