{
  "type": "Feature",
  "properties": {
    "date:inception_lower": "1980-01-01",
    "date:inception_upper": "1980-01-01",
    "iso:country": "GB",
    "wof:name": "CA15 7ED",
    "wof:placetype": "postalcode"
  },
  "geometry": {"coordinates":[-3.455157,54.706055],"type":"Point"}
}
