{
  "type": "Feature",
  "properties": {
    "date:inception_lower":"1980-01-01",
    "date:inception_upper":"1980-01-31",
    "iso:country":"GB",
    "wof:name":"BH6 3LZ",
    "wof:placetype":"postalcode"
},
  "geometry": {"coordinates":[-1.803085,50.730619],"type":"Point"}
}