{
  "type": "Feature",
  "properties": {
    "iso:country":"GB",
    "wof:name":"BH6 3LZ",
    "wof:placetype":"postalcode"
},
  "geometry": {"coordinates":[-1.80308533287522,50.73061939650803],"type":"Point"}
}