{
  "type": "Feature",
  "properties": {
    "iso:country":"GB",
    "wof:name":"WA5 4BY",
    "wof:placetype":"postalcode"
},
  "geometry": {"coordinates":[-2.64352633023032,53.42660057572768],"type":"Point"}
}