{
  "type": "Feature",
  "properties": {
    "date:inception_lower": "2014-11-01",
    "date:inception_upper": "2014-11-01",
    "iso:country": "GB",
    "wof:name": "DA7 6FF",
    "wof:placetype": "postalcode"
  },
  "geometry": {"coordinates":[0.15553,51.454907],"type":"Point"}
}
