{
  "type": "Feature",
  "properties": {
    "date:inception_lower": "1980-01-01",
    "date:inception_upper": "1980-01-01",
    "iso:country": "GB",
    "wof:name": "LD2 3EZ",
    "wof:placetype": "postalcode"
  },
  "geometry": {"coordinates":[-3.31941,52.078757],"type":"Point"}
}
