{
  "type": "Feature",
  "properties": {
    "iso:country": "GB",
    "wof:name": "LD2 3EZ",
    "wof:placetype": "postalcode"
  },
  "geometry": {"coordinates":[-3.31941,52.078757],"type":"Point"}
}
