{
  "type": "Feature",
  "properties": {
    "iso:country":"GB",
    "wof:name":"LD2 3EZ",
    "wof:placetype":"postalcode"
},
  "geometry": {"coordinates":[-3.31940963668225,52.0787567153755],"type":"Point"}
}