{
  "type": "Feature",
  "properties": {
    "iso:country":"GB",
    "wof:name":"N13 4UE",
    "wof:placetype":"postalcode"
},
  "geometry": {"coordinates":[-0.11120487264474,51.61442228611934],"type":"Point"}
}