{
  "type": "Feature",
  "properties": {
    "iso:country": "GB",
    "wof:name": "WR1 2ET",
    "wof:placetype": "postalcode"
  },
  "geometry": {"coordinates":[-2.221053,52.191871],"type":"Point"}
}
