{
  "type": "Feature",
  "properties": {
    "date:inception_lower": "2000-06-01",
    "date:inception_upper": "2000-06-01",
    "iso:country": "GB",
    "wof:name": "M29 8RH",
    "wof:placetype": "postalcode"
  },
  "geometry": {"coordinates":[-2.434402,53.513682],"type":"Point"}
}
