{
  "type": "Feature",
  "properties": {
    "iso:country":"GB",
    "wof:name":"CM23 4DE",
    "wof:placetype":"postalcode"
},
  "geometry": {"coordinates":[0.13494391121981,51.87254263693438],"type":"Point"}
}