{
  "type": "Feature",
  "properties": {
    "date:inception_lower": "1991-09-01",
    "date:inception_upper": "1991-09-01",
    "iso:country": "GB",
    "wof:name": "CM23 4DE",
    "wof:placetype": "postalcode"
  },
  "geometry": {"coordinates":[0.134944,51.872543],"type":"Point"}
}
