{
  "type": "Feature",
  "properties": {
    "iso:country":"GB",
    "wof:name":"EH20 9RJ",
    "wof:placetype":"postalcode"
},
  "geometry": {"coordinates":[-3.14646205120988,55.877102467177],"type":"Point"}
}