{
  "type": "Feature",
  "properties": {
    "date:inception_lower": "2019-11-01",
    "date:inception_upper": "2019-11-01",
    "iso:country": "GB",
    "wof:name": "TR26 3BG",
    "wof:placetype": "postalcode"
  },
  "geometry": {"coordinates":[-5.442505,50.185593],"type":"Point"}
}
