{
  "type": "Feature",
  "properties": {
    "iso:country": "GB",
    "wof:name": "TR26 3BG",
    "wof:placetype": "postalcode"
  },
  "geometry": {"coordinates":[-5.442505,50.185593],"type":"Point"}
}
