{
  "type": "Feature",
  "properties": {
    "iso:country": "GB",
    "wof:name": "DL3 0FE",
    "wof:placetype": "postalcode"
  },
  "geometry": {"coordinates":[-1.555521,54.540967],"type":"Point"}
}
