{
  "type": "Feature",
  "properties": {
    "date:inception_lower":"1991-09-01",
    "date:inception_upper":"1991-09-30",
    "iso:country":"GB",
    "wof:name":"DL3 0FE",
    "wof:placetype":"postalcode"
},
  "geometry": {"coordinates":[-1.555521,54.540967],"type":"Point"}
}