{
  "type": "Feature",
  "properties": {
    "iso:country":"GB",
    "wof:name":"TS23 3DY",
    "wof:placetype":"postalcode"
},
  "geometry": {"coordinates":[-1.27173455609906,54.61496616498484],"type":"Point"}
}