{
  "type": "Feature",
  "properties": {
    "iso:country":"GB",
    "wof:name":"B63 2AR",
    "wof:placetype":"postalcode"
},
  "geometry": {"coordinates":[-2.07621951171127,52.45866724602368],"type":"Point"}
}