{
  "type": "Feature",
  "properties": {
    "date:inception_lower":"1980-01-01",
    "date:inception_upper":"1980-01-31",
    "iso:country":"GB",
    "wof:name":"CH6 5QT",
    "wof:placetype":"postalcode"
},
  "geometry": {"coordinates":[-3.142928,53.221902],"type":"Point"}
}