{
  "type": "Feature",
  "properties": {
    "iso:country":"GB",
    "wof:name":"CH6 5QT",
    "wof:placetype":"postalcode"
},
  "geometry": {"coordinates":[-3.14292820611892,53.22190235403988],"type":"Point"}
}