{
  "type": "Feature",
  "properties": {
    "iso:country": "GB",
    "wof:name": "CB22 7PU",
    "wof:placetype": "postalcode"
  },
  "geometry": {"coordinates":[0.079604,52.136419],"type":"Point"}
}
