{
  "type": "Feature",
  "properties": {
    "iso:country":"GB",
    "wof:name":"NG6 0AJ",
    "wof:placetype":"postalcode"
},
  "geometry": {"coordinates":[-1.17460263017816,52.98442552642111],"type":"Point"}
}