{
  "type": "Feature",
  "properties": {
    "iso:country": "GB",
    "wof:name": "BH21 3UX",
    "wof:placetype": "postalcode"
  },
  "geometry": {"coordinates":[-2.031098,50.761653],"type":"Point"}
}
