{
  "type": "Feature",
  "properties": {
    "iso:country":"GB",
    "wof:name":"DH8 8DG",
    "wof:placetype":"postalcode"
},
  "geometry": {"coordinates":[-1.86987659104715,54.83580909076031],"type":"Point"}
}