{
  "type": "Feature",
  "properties": {
    "iso:country": "GB",
    "wof:name": "DH8 8DG",
    "wof:placetype": "postalcode"
  },
  "geometry": {"coordinates":[-1.869877,54.835809],"type":"Point"}
}
