{
  "type": "Feature",
  "properties": {
    "date:inception_lower": "1984-02-01",
    "date:inception_upper": "1984-02-01",
    "iso:country": "GB",
    "wof:name": "SE1 5BY",
    "wof:placetype": "postalcode"
  },
  "geometry": {"coordinates":[-0.064656,51.489927],"type":"Point"}
}
