{
  "type": "Feature",
  "properties": {
    "iso:country":"GB",
    "wof:name":"SE1 5BY",
    "wof:placetype":"postalcode"
},
  "geometry": {"coordinates":[-0.06465599412479,51.48992666098194],"type":"Point"}
}