{
  "type": "Feature",
  "properties": {
    "date:inception_lower": "1991-01-01",
    "date:inception_upper": "1991-01-01",
    "iso:country": "GB",
    "wof:name": "SY8 1UE",
    "wof:placetype": "postalcode"
  },
  "geometry": {"coordinates":[-2.69924,52.367755],"type":"Point"}
}
