{
  "type": "Feature",
  "properties": {
    "iso:country":"GB",
    "wof:name":"SY8 1UE",
    "wof:placetype":"postalcode"
},
  "geometry": {"coordinates":[-2.69924036095859,52.36775525359464],"type":"Point"}
}