{
  "type": "Feature",
  "properties": {
    "iso:country": "GB",
    "wof:name": "BN12 5ET",
    "wof:placetype": "postalcode"
  },
  "geometry": {"coordinates":[-0.441924,50.806417],"type":"Point"}
}
