{
  "type": "Feature",
  "properties": {
    "iso:country":"GB",
    "wof:name":"BN12 5ET",
    "wof:placetype":"postalcode"
},
  "geometry": {"coordinates":[-0.44194825612364,50.80642586057255],"type":"Point"}
}