{
  "type": "Feature",
  "properties": {
    "date:inception_lower": "1980-01-01",
    "date:inception_upper": "1980-01-01",
    "iso:country": "GB",
    "wof:name": "BN12 5ET",
    "wof:placetype": "postalcode"
  },
  "geometry": {"coordinates":[-0.441991,50.806535],"type":"Point"}
}
