{
  "type": "Feature",
  "properties": {
    "iso:country":"GB",
    "wof:name":"GU11 3EN",
    "wof:placetype":"postalcode"
},
  "geometry": {"coordinates":[-0.76917520018489,51.24417698484096],"type":"Point"}
}