{
  "type": "Feature",
  "properties": {
    "iso:country":"GB",
    "wof:name":"CF24 2TN",
    "wof:placetype":"postalcode"
},
  "geometry": {"coordinates":[-3.14070832465506,51.4943533696018],"type":"Point"}
}