{
  "type": "Feature",
  "properties": {
    "iso:country":"GB",
    "wof:name":"B24 0EB",
    "wof:placetype":"postalcode"
},
  "geometry": {"coordinates":[-1.82821612797766,52.53250991615224],"type":"Point"}
}