{
  "type": "Feature",
  "properties": {
    "iso:country": "GB",
    "wof:name": "B24 0EB",
    "wof:placetype": "postalcode"
  },
  "geometry": {"coordinates":[-1.828216,52.53251],"type":"Point"}
}
