{
  "type": "Feature",
  "properties": {
    "iso:country":"GB",
    "wof:name":"HP21 8RL",
    "wof:placetype":"postalcode"
},
  "geometry": {"coordinates":[-0.82075347772439,51.79832763025343],"type":"Point"}
}