{
  "type": "Feature",
  "properties": {
    "date:inception_lower": "1980-01-01",
    "date:inception_upper": "1980-01-01",
    "iso:country": "GB",
    "wof:name": "HP21 8RL",
    "wof:placetype": "postalcode"
  },
  "geometry": {"coordinates":[-0.820753,51.798328],"type":"Point"}
}
