{
  "type": "Feature",
  "properties": {
    "date:inception_lower": "1980-01-01",
    "date:inception_upper": "1980-01-01",
    "iso:country": "GB",
    "wof:name": "TN2 5QG",
    "wof:placetype": "postalcode"
  },
  "geometry": {"coordinates":[0.251201,51.121049],"type":"Point"}
}
