{
  "type": "Feature",
  "properties": {
    "iso:country":"GB",
    "wof:name":"TN2 5QG",
    "wof:placetype":"postalcode"
},
  "geometry": {"coordinates":[0.25120074776601,51.12104914963815],"type":"Point"}
}