{
  "type": "Feature",
  "properties": {
    "iso:country":"GB",
    "wof:name":"GU2 9SR",
    "wof:placetype":"postalcode"
},
  "geometry": {"coordinates":[-0.60185113193841,51.25504937631218],"type":"Point"}
}