{
  "type": "Feature",
  "properties": {
    "iso:country":"GB",
    "wof:name":"TN27 9BH",
    "wof:placetype":"postalcode"
},
  "geometry": {"coordinates":[0.71311734427784,51.19162939283045],"type":"Point"}
}