{
  "type": "Feature",
  "properties": {
    "date:inception_lower": "2012-10-01",
    "date:inception_upper": "2012-10-01",
    "iso:country": "GB",
    "wof:name": "M41 5EG",
    "wof:placetype": "postalcode"
  },
  "geometry": {"coordinates":[-2.371755,53.451189],"type":"Point"}
}
