{
  "type": "Feature",
  "properties": {
    "iso:country":"GB",
    "wof:name":"M41 5EG",
    "wof:placetype":"postalcode"
},
  "geometry": {"coordinates":[-2.37175479763044,53.45118934578112],"type":"Point"}
}