{
  "type": "Feature",
  "properties": {
    "iso:country":"GB",
    "wof:name":"RG7 1JB",
    "wof:placetype":"postalcode"
},
  "geometry": {"coordinates":[-0.97641945049189,51.38631361634761],"type":"Point"}
}