{
  "type": "Feature",
  "properties": {
    "iso:country":"GB",
    "wof:name":"L40 2QF",
    "wof:placetype":"postalcode"
},
  "geometry": {"coordinates":[-2.78223858724564,53.62718017032559],"type":"Point"}
}