{
  "type": "Feature",
  "properties": {
    "date:inception_lower": "1980-01-01",
    "date:inception_upper": "1980-01-01",
    "iso:country": "GB",
    "wof:name": "L40 2QF",
    "wof:placetype": "postalcode"
  },
  "geometry": {"coordinates":[-2.782239,53.62718],"type":"Point"}
}
