{
  "type": "Feature",
  "properties": {
    "date:inception_lower": "2018-05-01",
    "date:inception_upper": "2018-05-01",
    "iso:country": "GB",
    "wof:name": "EX1 3GR",
    "wof:placetype": "postalcode"
  },
  "geometry": {"coordinates":[-3.464833,50.750258],"type":"Point"}
}
