{
  "type": "Feature",
  "properties": {
    "iso:country": "GB",
    "wof:name": "EX1 3GR",
    "wof:placetype": "postalcode"
  },
  "geometry": {"coordinates":[-3.464833,50.750258],"type":"Point"}
}
