{
  "type": "Feature",
  "properties": {
    "iso:country":"GB",
    "wof:name":"SY4 3EB",
    "wof:placetype":"postalcode"
},
  "geometry": {"coordinates":[-2.75799100129832,52.79553306727184],"type":"Point"}
}