{
  "type": "Feature",
  "properties": {
    "date:inception_lower": "1980-01-01",
    "date:inception_upper": "1980-01-01",
    "iso:country": "GB",
    "wof:name": "SY4 3EB",
    "wof:placetype": "postalcode"
  },
  "geometry": {"coordinates":[-2.757849,52.795217],"type":"Point"}
}
