{
  "type": "Feature",
  "properties": {
    "iso:country": "GB",
    "wof:name": "SY4 3EB",
    "wof:placetype": "postalcode"
  },
  "geometry": {"coordinates":[-2.757865,52.795261],"type":"Point"}
}
