{
  "type": "Feature",
  "properties": {
    "iso:country": "GB",
    "wof:name": "DE55 4EJ",
    "wof:placetype": "postalcode"
  },
  "geometry": {"coordinates":[-1.366577,53.066695],"type":"Point"}
}
