{
  "type": "Feature",
  "properties": {
    "iso:country":"GB",
    "wof:name":"DE55 4EJ",
    "wof:placetype":"postalcode"
},
  "geometry": {"coordinates":[-1.36657698808095,53.06669510047382],"type":"Point"}
}