{
  "type": "Feature",
  "properties": {
    "iso:country": "GB",
    "wof:name": "BA8 0AY",
    "wof:placetype": "postalcode"
  },
  "geometry": {"coordinates":[-2.3964,50.975921],"type":"Point"}
}
