{
  "type": "Feature",
  "properties": {
    "iso:country":"GB",
    "wof:name":"BA8 0AY",
    "wof:placetype":"postalcode"
},
  "geometry": {"coordinates":[-2.39640038646251,50.97592075577145],"type":"Point"}
}