{
  "type": "Feature",
  "properties": {
    "iso:country":"GB",
    "wof:name":"LL54 6NU",
    "wof:placetype":"postalcode"
},
  "geometry": {"coordinates":[-4.28529461293443,53.0535979364026],"type":"Point"}
}