{
  "type": "Feature",
  "properties": {
    "iso:country":"GB",
    "wof:name":"M13 9BD",
    "wof:placetype":"postalcode"
},
  "geometry": {"coordinates":[-2.21470148366092,53.46320623830795],"type":"Point"}
}