{
  "type": "Feature",
  "properties": {
    "iso:country": "GB",
    "wof:name": "M13 9BD",
    "wof:placetype": "postalcode"
  },
  "geometry": {"coordinates":[-2.214701,53.463206],"type":"Point"}
}
