{
  "type": "Feature",
  "properties": {
    "iso:country":"GB",
    "wof:name":"TQ6 9DT",
    "wof:placetype":"postalcode"
},
  "geometry": {"coordinates":[-3.58485683348616,50.35075889128256],"type":"Point"}
}