{
  "type": "Feature",
  "properties": {
    "iso:country":"GB",
    "wof:name":"S18 4AZ",
    "wof:placetype":"postalcode"
},
  "geometry": {"coordinates":[-1.43058870676949,53.30034620251362],"type":"Point"}
}