{
  "type": "Feature",
  "properties": {
    "iso:country":"GB",
    "wof:name":"TR1 1QH",
    "wof:placetype":"postalcode"
},
  "geometry": {"coordinates":[-5.04651298666937,50.26208985177215],"type":"Point"}
}