{
  "type": "Feature",
  "properties": {
    "iso:country": "GB",
    "wof:name": "OL16 1JW",
    "wof:placetype": "postalcode"
  },
  "geometry": {"coordinates":[-2.157587,53.61801],"type":"Point"}
}
