{
  "type": "Feature",
  "properties": {
    "date:inception_lower": "1992-01-01",
    "date:inception_upper": "1992-01-01",
    "iso:country": "GB",
    "wof:name": "BH20 7QQ",
    "wof:placetype": "postalcode"
  },
  "geometry": {"coordinates":[-2.091676,50.708537],"type":"Point"}
}
