{
  "type": "Feature",
  "properties": {
    "date:inception_lower": "1999-06-01",
    "date:inception_upper": "1999-06-01",
    "iso:country": "GB",
    "wof:name": "NP19 8JF",
    "wof:placetype": "postalcode"
  },
  "geometry": {"coordinates":[-2.96167,51.58806],"type":"Point"}
}
