{
  "type": "Feature",
  "properties": {
    "iso:country":"GB",
    "wof:name":"NP19 8JF",
    "wof:placetype":"postalcode"
},
  "geometry": {"coordinates":[-2.96166987846121,51.58806030211566],"type":"Point"}
}