{
  "type": "Feature",
  "properties": {
    "iso:country":"GB",
    "wof:name":"S74 0BB",
    "wof:placetype":"postalcode"
},
  "geometry": {"coordinates":[-1.45054457043762,53.49780413320631],"type":"Point"}
}