{
  "type": "Feature",
  "properties": {
    "iso:country":"GB",
    "wof:name":"M6 8FL",
    "wof:placetype":"postalcode"
},
  "geometry": {"coordinates":[-2.31949561676714,53.48817547451957],"type":"Point"}
}