{
  "type": "Feature",
  "properties": {
    "iso:country": "GB",
    "wof:name": "M6 8FL",
    "wof:placetype": "postalcode"
  },
  "geometry": {"coordinates":[-2.319496,53.488175],"type":"Point"}
}
