{
  "type": "Feature",
  "properties": {
    "iso:country":"GB",
    "wof:name":"TQ9 7DU",
    "wof:placetype":"postalcode"
},
  "geometry": {"coordinates":[-3.6851193743831,50.41733379124695],"type":"Point"}
}