{
  "type": "Feature",
  "properties": {
    "date:inception_lower": "1980-01-01",
    "date:inception_upper": "1980-01-01",
    "iso:country": "GB",
    "wof:name": "CA17 4DW",
    "wof:placetype": "postalcode"
  },
  "geometry": {"coordinates":[-2.361901,54.515762],"type":"Point"}
}
