{
  "type": "Feature",
  "properties": {
    "iso:country":"GB",
    "wof:name":"NE6 5YJ",
    "wof:placetype":"postalcode"
},
  "geometry": {"coordinates":[-1.57743034517909,54.98205335421055],"type":"Point"}
}