{
  "type": "Feature",
  "properties": {
    "iso:country":"GB",
    "wof:name":"EX2 7TA",
    "wof:placetype":"postalcode"
},
  "geometry": {"coordinates":[-3.47657215283569,50.71246562051778],"type":"Point"}
}