{
  "type": "Feature",
  "properties": {
    "iso:country":"GB",
    "wof:name":"UB8 2DP",
    "wof:placetype":"postalcode"
},
  "geometry": {"coordinates":[-0.47639470020604,51.53479976785948],"type":"Point"}
}