{
  "type": "Feature",
  "properties": {
    "iso:country":"GB",
    "wof:name":"HG4 1LU",
    "wof:placetype":"postalcode"
},
  "geometry": {"coordinates":[-1.51600149255708,54.13456489913217],"type":"Point"}
}