{
  "type": "Feature",
  "properties": {
    "iso:country": "GB",
    "wof:name": "NP16 5UH",
    "wof:placetype": "postalcode"
  },
  "geometry": {"coordinates":[-2.67072,51.621124],"type":"Point"}
}
