{
  "type": "Feature",
  "properties": {
    "date:inception_lower":"2006-08-01",
    "date:inception_upper":"2006-08-31",
    "iso:country":"GB",
    "wof:name":"NP16 5UH",
    "wof:placetype":"postalcode"
},
  "geometry": {"coordinates":[-2.670547,51.621179],"type":"Point"}
}