{
  "type": "Feature",
  "properties": {
    "iso:country":"GB",
    "wof:name":"NP16 5UH",
    "wof:placetype":"postalcode"
},
  "geometry": {"coordinates":[-2.66968558755078,51.62193768394391],"type":"Point"}
}