{
  "type": "Feature",
  "properties": {
    "date:inception_lower": "2006-08-01",
    "date:inception_upper": "2006-08-01",
    "iso:country": "GB",
    "wof:name": "NP16 5UH",
    "wof:placetype": "postalcode"
  },
  "geometry": {"coordinates":[-2.67072,51.621124],"type":"Point"}
}
