{
  "type": "Feature",
  "properties": {
    "iso:country": "GB",
    "wof:name": "TA1 3LQ",
    "wof:placetype": "postalcode"
  },
  "geometry": {"coordinates":[-3.101135,51.014485],"type":"Point"}
}
