{
  "type": "Feature",
  "properties": {
    "iso:country":"GB",
    "wof:name":"TA1 3LQ",
    "wof:placetype":"postalcode"
},
  "geometry": {"coordinates":[-3.10113529868382,51.0144851912003],"type":"Point"}
}