{
  "type": "Feature",
  "properties": {
    "iso:country":"GB",
    "wof:name":"SS7 3AU",
    "wof:placetype":"postalcode"
},
  "geometry": {"coordinates":[0.57726229718484,51.56742630211645],"type":"Point"}
}