{
  "type": "Feature",
  "properties": {
    "iso:country": "GB",
    "wof:name": "WV13 3XD",
    "wof:placetype": "postalcode"
  },
  "geometry": {"coordinates":[-2.088552,52.593046],"type":"Point"}
}
