{
  "type": "Feature",
  "properties": {
    "iso:country": "GB",
    "wof:name": "PH23 3BG",
    "wof:placetype": "postalcode"
  },
  "geometry": {"coordinates":[-3.810135,57.285197],"type":"Point"}
}
