{
  "type": "Feature",
  "properties": {
    "iso:country":"GB",
    "wof:name":"TN27 0DX",
    "wof:placetype":"postalcode"
},
  "geometry": {"coordinates":[0.80494044746806,51.19851101677095],"type":"Point"}
}