{
  "type": "Feature",
  "properties": {
    "iso:country": "GB",
    "wof:name": "S2 2NH",
    "wof:placetype": "postalcode"
  },
  "geometry": {"coordinates":[-1.441832,53.367923],"type":"Point"}
}
