{
  "type": "Feature",
  "properties": {
    "date:inception_lower": "1980-01-01",
    "date:inception_upper": "1980-01-01",
    "iso:country": "GB",
    "wof:name": "S2 2NH",
    "wof:placetype": "postalcode"
  },
  "geometry": {"coordinates":[-1.441832,53.367923],"type":"Point"}
}
