{
  "type": "Feature",
  "properties": {
    "iso:country": "GB",
    "wof:name": "S74 8EA",
    "wof:placetype": "postalcode"
  },
  "geometry": {"coordinates":[-1.42382,53.495504],"type":"Point"}
}
