{
  "type": "Feature",
  "properties": {
    "iso:country": "GB",
    "wof:name": "S74 8EA",
    "wof:placetype": "postalcode"
  },
  "geometry": {"coordinates":[-1.424185,53.495272],"type":"Point"}
}
