{
  "type": "Feature",
  "properties": {
    "date:inception_lower": "1980-01-01",
    "date:inception_upper": "1980-01-01",
    "iso:country": "GB",
    "wof:name": "S74 8EA",
    "wof:placetype": "postalcode"
  },
  "geometry": {"coordinates":[-1.42376,53.495458],"type":"Point"}
}
