{
  "type": "Feature",
  "properties": {
    "iso:country":"GB",
    "wof:name":"RH8 0SG",
    "wof:placetype":"postalcode"
},
  "geometry": {"coordinates":[0.01840619373697,51.26101534201204],"type":"Point"}
}