{
  "type": "Feature",
  "properties": {
    "date:inception_lower": "1994-05-01",
    "date:inception_upper": "1994-05-01",
    "iso:country": "GB",
    "wof:name": "M33 7EQ",
    "wof:placetype": "postalcode"
  },
  "geometry": {"coordinates":[-2.318329,53.426884],"type":"Point"}
}
