{
  "type": "Feature",
  "properties": {
    "iso:country": "GB",
    "wof:name": "M33 7EQ",
    "wof:placetype": "postalcode"
  },
  "geometry": {"coordinates":[-2.318328,53.426868],"type":"Point"}
}
