{
  "type": "Feature",
  "properties": {
    "iso:country":"GB",
    "wof:name":"WS10 9LF",
    "wof:placetype":"postalcode"
},
  "geometry": {"coordinates":[-2.02900601326379,52.56742128259914],"type":"Point"}
}