{
  "type": "Feature",
  "properties": {
    "iso:country": "GB",
    "wof:name": "WS10 9LF",
    "wof:placetype": "postalcode"
  },
  "geometry": {"coordinates":[-2.029006,52.567421],"type":"Point"}
}
