{
  "type": "Feature",
  "properties": {
    "iso:country":"GB",
    "wof:name":"TN4 8AG",
    "wof:placetype":"postalcode"
},
  "geometry": {"coordinates":[0.26152620292144,51.13671442215018],"type":"Point"}
}