{
  "type": "Feature",
  "properties": {
    "date:inception_lower": "1980-01-01",
    "date:inception_upper": "1980-01-01",
    "iso:country": "GB",
    "wof:name": "TN16 1JX",
    "wof:placetype": "postalcode"
  },
  "geometry": {"coordinates":[0.113728,51.276429],"type":"Point"}
}
