{
  "type": "Feature",
  "properties": {
    "iso:country": "GB",
    "wof:name": "ML2 0RP",
    "wof:placetype": "postalcode"
  },
  "geometry": {"coordinates":[-3.915107,55.755817],"type":"Point"}
}
