{
  "type": "Feature",
  "properties": {
    "date:inception_lower": "1990-02-01",
    "date:inception_upper": "1990-02-01",
    "iso:country": "GB",
    "wof:name": "ML2 0RP",
    "wof:placetype": "postalcode"
  },
  "geometry": {"coordinates":[-3.915107,55.755817],"type":"Point"}
}
