{
  "type": "Feature",
  "properties": {
    "iso:country":"GB",
    "wof:name":"ML2 0RP",
    "wof:placetype":"postalcode"
},
  "geometry": {"coordinates":[-3.9151066474271,55.75581686686526],"type":"Point"}
}