{
  "type": "Feature",
  "properties": {
    "date:inception_lower": "1980-01-01",
    "date:inception_upper": "1980-01-01",
    "iso:country": "GB",
    "wof:name": "WR14 4BX",
    "wof:placetype": "postalcode"
  },
  "geometry": {"coordinates":[-2.346638,52.118072],"type":"Point"}
}
