{
  "type": "Feature",
  "properties": {
    "iso:country":"GB",
    "wof:name":"WR14 4BX",
    "wof:placetype":"postalcode"
},
  "geometry": {"coordinates":[-2.34663780573517,52.1180715355395],"type":"Point"}
}