{
  "type": "Feature",
  "properties": {
    "iso:country":"GB",
    "wof:name":"CM14 4EX",
    "wof:placetype":"postalcode"
},
  "geometry": {"coordinates":[0.30433493499606,51.61781801922415],"type":"Point"}
}