{
  "type": "Feature",
  "properties": {
    "iso:country":"GB",
    "wof:name":"EN4 9NB",
    "wof:placetype":"postalcode"
},
  "geometry": {"coordinates":[-0.14877593817922,51.64844531147768],"type":"Point"}
}