{
  "type": "Feature",
  "properties": {
    "iso:country":"GB",
    "wof:name":"SP6 1EY",
    "wof:placetype":"postalcode"
},
  "geometry": {"coordinates":[-1.78669558709833,50.93569173142312],"type":"Point"}
}