{
  "type": "Feature",
  "properties": {
    "date:inception_lower": "2023-03-01",
    "date:inception_upper": "2023-03-01",
    "iso:country": "GB",
    "wof:name": "CB23 6LY",
    "wof:placetype": "postalcode"
  },
  "geometry": {"coordinates":[-0.094032,52.219149],"type":"Point"}
}
