{
  "type": "Feature",
  "properties": {
    "iso:country":"GB",
    "wof:name":"L13 8BB",
    "wof:placetype":"postalcode"
},
  "geometry": {"coordinates":[-2.93647982992609,53.42791623329311],"type":"Point"}
}