{
  "type": "Feature",
  "properties": {
    "iso:country": "GB",
    "wof:name": "SY7 0LW",
    "wof:placetype": "postalcode"
  },
  "geometry": {"coordinates":[-2.874595,52.360649],"type":"Point"}
}
