{
  "type": "Feature",
  "properties": {
    "iso:country":"GB",
    "wof:name":"SY7 0LW",
    "wof:placetype":"postalcode"
},
  "geometry": {"coordinates":[-2.87459716496255,52.36069855096769],"type":"Point"}
}