{
  "type": "Feature",
  "properties": {
    "iso:country":"GB",
    "wof:name":"PE11 3FG",
    "wof:placetype":"postalcode"
},
  "geometry": {"coordinates":[-0.16886206569903,52.79492416847803],"type":"Point"}
}