{
  "type": "Feature",
  "properties": {
    "iso:country": "GB",
    "wof:name": "PA30 8HE",
    "wof:placetype": "postalcode"
  },
  "geometry": {"coordinates":[-5.450901,56.015294],"type":"Point"}
}
