{
  "type": "Feature",
  "properties": {
    "iso:country": "GB",
    "wof:name": "PA30 8HE",
    "wof:placetype": "postalcode"
  },
  "geometry": {"coordinates":[-5.451588,56.015312],"type":"Point"}
}
