{
  "type": "Feature",
  "properties": {
    "iso:country":"GB",
    "wof:name":"ST10 4PT",
    "wof:placetype":"postalcode"
},
  "geometry": {"coordinates":[-1.96463520471695,52.92008894459944],"type":"Point"}
}