{
  "type": "Feature",
  "properties": {
    "iso:country":"GB",
    "wof:name":"DY6 8TB",
    "wof:placetype":"postalcode"
},
  "geometry": {"coordinates":[-2.14259360187009,52.49063698442433],"type":"Point"}
}