{
  "type": "Feature",
  "properties": {
    "date:inception_lower": "2006-07-01",
    "date:inception_upper": "2006-07-01",
    "iso:country": "GB",
    "wof:name": "TQ12 2GZ",
    "wof:placetype": "postalcode"
  },
  "geometry": {"coordinates":[-3.602751,50.529184],"type":"Point"}
}
