{
  "type": "Feature",
  "properties": {
    "iso:country": "GB",
    "wof:name": "TQ12 2GZ",
    "wof:placetype": "postalcode"
  },
  "geometry": {"coordinates":[-3.602751,50.529184],"type":"Point"}
}
