{
  "type": "Feature",
  "properties": {
    "iso:country":"GB",
    "wof:name":"TQ7 3ED",
    "wof:placetype":"postalcode"
},
  "geometry": {"coordinates":[-3.82134753744223,50.24676642062151],"type":"Point"}
}