{
  "type": "Feature",
  "properties": {
    "iso:country": "GB",
    "wof:name": "TQ7 3ED",
    "wof:placetype": "postalcode"
  },
  "geometry": {"coordinates":[-3.821632,50.246959],"type":"Point"}
}
