{
  "type": "Feature",
  "properties": {
    "date:inception_lower": "1980-01-01",
    "date:inception_upper": "1980-01-01",
    "iso:country": "GB",
    "wof:name": "TQ7 3ED",
    "wof:placetype": "postalcode"
  },
  "geometry": {"coordinates":[-3.821372,50.246748],"type":"Point"}
}
