{
  "type": "Feature",
  "properties": {
    "date:inception_lower":"1998-06-01",
    "date:inception_upper":"1998-06-30",
    "iso:country":"GB",
    "wof:name":"YO30 6JG",
    "wof:placetype":"postalcode"
},
  "geometry": {"coordinates":[-1.089823,53.97782],"type":"Point"}
}