{
  "type": "Feature",
  "properties": {
    "iso:country":"GB",
    "wof:name":"TS10 4HE",
    "wof:placetype":"postalcode"
},
  "geometry": {"coordinates":[-1.08250669659089,54.60134124194391],"type":"Point"}
}