{
  "type": "Feature",
  "properties": {
    "iso:country": "GB",
    "wof:name": "SK11 9HQ",
    "wof:placetype": "postalcode"
  },
  "geometry": {"coordinates":[-2.229042,53.21147],"type":"Point"}
}
