{
  "type": "Feature",
  "properties": {
    "iso:country":"GB",
    "wof:name":"SK11 9HQ",
    "wof:placetype":"postalcode"
},
  "geometry": {"coordinates":[-2.22904197885828,53.21146978322087],"type":"Point"}
}