{
  "type": "Feature",
  "properties": {
    "iso:country":"GB",
    "wof:name":"SK9 7BZ",
    "wof:placetype":"postalcode"
},
  "geometry": {"coordinates":[-2.22333302213718,53.29981352146351],"type":"Point"}
}