{
  "type": "Feature",
  "properties": {
    "iso:country":"GB",
    "wof:name":"EN5 3AT",
    "wof:placetype":"postalcode"
},
  "geometry": {"coordinates":[-0.22280271009363,51.64687339166625],"type":"Point"}
}