{
  "type": "Feature",
  "properties": {
    "iso:country": "GB",
    "wof:name": "EN5 3AT",
    "wof:placetype": "postalcode"
  },
  "geometry": {"coordinates":[-0.222803,51.646873],"type":"Point"}
}
