{
  "type": "Feature",
  "properties": {
    "date:inception_lower": "1995-12-01",
    "date:inception_upper": "1995-12-01",
    "iso:country": "GB",
    "wof:name": "NG18 5GS",
    "wof:placetype": "postalcode"
  },
  "geometry": {"coordinates":[-1.216178,53.134774],"type":"Point"}
}
