{
  "type": "Feature",
  "properties": {
    "iso:country":"GB",
    "wof:name":"WV8 1TD",
    "wof:placetype":"postalcode"
},
  "geometry": {"coordinates":[-2.15780503176079,52.62134804845148],"type":"Point"}
}