{
  "type": "Feature",
  "properties": {
    "iso:country": "GB",
    "wof:name": "WV8 1TD",
    "wof:placetype": "postalcode"
  },
  "geometry": {"coordinates":[-2.157805,52.621348],"type":"Point"}
}
