{
  "type": "Feature",
  "properties": {
    "iso:country": "GB",
    "wof:name": "TA1 5NS",
    "wof:placetype": "postalcode"
  },
  "geometry": {"coordinates":[-3.126023,51.010264],"type":"Point"}
}
