{
  "type": "Feature",
  "properties": {
    "iso:country":"GB",
    "wof:name":"TA1 5NS",
    "wof:placetype":"postalcode"
},
  "geometry": {"coordinates":[-3.12602340473301,51.01026421595868],"type":"Point"}
}