{
  "type": "Feature",
  "properties": {
    "date:inception_lower": "1980-01-01",
    "date:inception_upper": "1980-01-01",
    "iso:country": "GB",
    "wof:name": "PA2 0AZ",
    "wof:placetype": "postalcode"
  },
  "geometry": {"coordinates":[-4.459893,55.820544],"type":"Point"}
}
