{
  "type": "Feature",
  "properties": {
    "date:inception_lower": "1980-01-01",
    "date:inception_upper": "1980-01-01",
    "iso:country": "GB",
    "wof:name": "CW5 5QP",
    "wof:placetype": "postalcode"
  },
  "geometry": {"coordinates":[-2.519244,53.074859],"type":"Point"}
}
