{
  "type": "Feature",
  "properties": {
    "iso:country":"GB",
    "wof:name":"UB7 9JB",
    "wof:placetype":"postalcode"
},
  "geometry": {"coordinates":[-0.46643733811819,51.49643536202768],"type":"Point"}
}