{
  "type": "Feature",
  "properties": {
    "iso:country":"GB",
    "wof:name":"CH63 3ET",
    "wof:placetype":"postalcode"
},
  "geometry": {"coordinates":[-3.00840511048628,53.34332845721612],"type":"Point"}
}