{
  "type": "Feature",
  "properties": {
    "iso:country":"GB",
    "wof:name":"AB41 8YQ",
    "wof:placetype":"postalcode"
},
  "geometry": {"coordinates":[-2.04025030737415,57.42756496993157],"type":"Point"}
}