{
  "type": "Feature",
  "properties": {
    "iso:country":"GB",
    "wof:name":"BD12 0QJ",
    "wof:placetype":"postalcode"
},
  "geometry": {"coordinates":[-1.76281983821059,53.75282953719862],"type":"Point"}
}