{
  "type": "Feature",
  "properties": {
    "date:inception_lower": "1997-12-01",
    "date:inception_upper": "1997-12-01",
    "iso:country": "GB",
    "wof:name": "BB18 6XA",
    "wof:placetype": "postalcode"
  },
  "geometry": {"coordinates":[-2.144992,53.914925],"type":"Point"}
}
