{
  "type": "Feature",
  "properties": {
    "date:inception_lower":"1980-01-01",
    "date:inception_upper":"1980-01-31",
    "iso:country":"GB",
    "wof:name":"LL14 6RA",
    "wof:placetype":"postalcode"
},
  "geometry": {"coordinates":[-3.042742,52.999722],"type":"Point"}
}