{
  "type": "Feature",
  "properties": {
    "iso:country":"GB",
    "wof:name":"PH7 4JT",
    "wof:placetype":"postalcode"
},
  "geometry": {"coordinates":[-3.91501266520182,56.37934443353691],"type":"Point"}
}