{
  "type": "Feature",
  "properties": {
    "date:inception_lower": "2021-11-01",
    "date:inception_upper": "2021-11-01",
    "iso:country": "GB",
    "wof:name": "S3 7EB",
    "wof:placetype": "postalcode"
  },
  "geometry": {"coordinates":[-1.47687,53.375947],"type":"Point"}
}
