{
  "type": "Feature",
  "properties": {
    "iso:country":"GB",
    "wof:name":"LL34 6PN",
    "wof:placetype":"postalcode"
},
  "geometry": {"coordinates":[-3.93501057683518,53.2667535095024],"type":"Point"}
}