{
  "type": "Feature",
  "properties": {
    "date:inception_lower": "1980-01-01",
    "date:inception_upper": "1980-01-01",
    "iso:country": "GB",
    "wof:name": "BS7 8JD",
    "wof:placetype": "postalcode"
  },
  "geometry": {"coordinates":[-2.598612,51.47443],"type":"Point"}
}
