{
  "type": "Feature",
  "properties": {
    "iso:country":"GB",
    "wof:name":"BS7 8JD",
    "wof:placetype":"postalcode"
},
  "geometry": {"coordinates":[-2.59861230180466,51.47442951791518],"type":"Point"}
}