{
  "type": "Feature",
  "properties": {
    "date:inception_lower": "1980-01-01",
    "date:inception_upper": "1980-01-01",
    "iso:country": "GB",
    "wof:name": "ME1 3XB",
    "wof:placetype": "postalcode"
  },
  "geometry": {"coordinates":[0.458198,51.34754],"type":"Point"}
}
