{
  "type": "Feature",
  "properties": {
    "iso:country":"GB",
    "wof:name":"ME1 3XB",
    "wof:placetype":"postalcode"
},
  "geometry": {"coordinates":[0.45816657574542,51.34750444847001],"type":"Point"}
}