{
  "type": "Feature",
  "properties": {
    "iso:country":"GB",
    "wof:name":"LA13 9RD",
    "wof:placetype":"postalcode"
},
  "geometry": {"coordinates":[-3.20812770028448,54.11163954778107],"type":"Point"}
}