{
  "type": "Feature",
  "properties": {
    "iso:country":"GB",
    "wof:name":"PO13 0JS",
    "wof:placetype":"postalcode"
},
  "geometry": {"coordinates":[-1.1660285079159,50.82018755863386],"type":"Point"}
}