{
  "type": "Feature",
  "properties": {
    "date:inception_lower": "1999-06-01",
    "date:inception_upper": "1999-06-01",
    "iso:country": "GB",
    "wof:name": "SK10 3ND",
    "wof:placetype": "postalcode"
  },
  "geometry": {"coordinates":[-2.152655,53.264321],"type":"Point"}
}
