{
  "type": "Feature",
  "properties": {
    "iso:country":"GB",
    "wof:name":"SK10 3ND",
    "wof:placetype":"postalcode"
},
  "geometry": {"coordinates":[-2.15265485445478,53.26432064605221],"type":"Point"}
}