{
  "type": "Feature",
  "properties": {
    "iso:country":"GB",
    "wof:name":"TA1 9SA",
    "wof:placetype":"postalcode"
},
  "geometry": {"coordinates":[-3.10648096935836,51.02106219211767],"type":"Point"}
}