{
  "type": "Feature",
  "properties": {
    "iso:country": "GB",
    "wof:name": "TA1 9SA",
    "wof:placetype": "postalcode"
  },
  "geometry": {"coordinates":[-3.10649,51.021057],"type":"Point"}
}
