{
  "type": "Feature",
  "properties": {
    "iso:country":"GB",
    "wof:name":"AL2 3UH",
    "wof:placetype":"postalcode"
},
  "geometry": {"coordinates":[-0.37398451816926,51.70606455474145],"type":"Point"}
}