{
  "type": "Feature",
  "properties": {
    "iso:country":"GB",
    "wof:name":"WN6 0UF",
    "wof:placetype":"postalcode"
},
  "geometry": {"coordinates":[-2.66469810140284,53.58249029708374],"type":"Point"}
}