{
  "type": "Feature",
  "properties": {
    "date:inception_lower": "2024-06-01",
    "date:inception_upper": "2024-06-01",
    "iso:country": "GB",
    "wof:name": "PO20 2NZ",
    "wof:placetype": "postalcode"
  },
  "geometry": {"coordinates":[-0.749706,50.842199],"type":"Point"}
}
