{
  "type": "Feature",
  "properties": {
    "date:inception_lower": "2009-05-01",
    "date:inception_upper": "2009-05-01",
    "iso:country": "GB",
    "wof:name": "B3 1BJ",
    "wof:placetype": "postalcode"
  },
  "geometry": {"coordinates":[-1.905213,52.48397],"type":"Point"}
}
