{
  "type": "Feature",
  "properties": {
    "iso:country":"GB",
    "wof:name":"BB9 6NP",
    "wof:placetype":"postalcode"
},
  "geometry": {"coordinates":[-2.23934807818188,53.8589720719584],"type":"Point"}
}