{
  "type": "Feature",
  "properties": {
    "iso:country": "GB",
    "wof:name": "SK17 0HT",
    "wof:placetype": "postalcode"
  },
  "geometry": {"coordinates":[-1.852847,53.157181],"type":"Point"}
}
