{
  "type": "Feature",
  "properties": {
    "iso:country":"GB",
    "wof:name":"KT2 7EW",
    "wof:placetype":"postalcode"
},
  "geometry": {"coordinates":[-0.27769086768043,51.41330617666173],"type":"Point"}
}