{
  "type": "Feature",
  "properties": {
    "date:inception_lower": "1987-10-01",
    "date:inception_upper": "1987-10-01",
    "iso:country": "GB",
    "wof:name": "DY10 4RZ",
    "wof:placetype": "postalcode"
  },
  "geometry": {"coordinates":[-2.223932,52.375093],"type":"Point"}
}
