{
  "type": "Feature",
  "properties": {
    "iso:country": "GB",
    "wof:name": "LE2 7NJ",
    "wof:placetype": "postalcode"
  },
  "geometry": {"coordinates":[-1.131391,52.612095],"type":"Point"}
}
