{
  "type": "Feature",
  "properties": {
    "iso:country":"GB",
    "wof:name":"CF3 1RN",
    "wof:placetype":"postalcode"
},
  "geometry": {"coordinates":[-3.11001864678166,51.5183683765224],"type":"Point"}
}