{
  "type": "Feature",
  "properties": {
    "date:inception_lower": "1980-01-01",
    "date:inception_upper": "1980-01-01",
    "iso:country": "GB",
    "wof:name": "PR6 0JH",
    "wof:placetype": "postalcode"
  },
  "geometry": {"coordinates":[-2.621238,53.664572],"type":"Point"}
}
