{
  "type": "Feature",
  "properties": {
    "iso:country":"GB",
    "wof:name":"CM13 2BD",
    "wof:placetype":"postalcode"
},
  "geometry": {"coordinates":[0.32714300798469,51.61353697650854],"type":"Point"}
}