{
  "type": "Feature",
  "properties": {
    "iso:country":"GB",
    "wof:name":"PH2 8EW",
    "wof:placetype":"postalcode"
},
  "geometry": {"coordinates":[-3.42197323694796,56.37421902719841],"type":"Point"}
}