{
  "type": "Feature",
  "properties": {
    "iso:country": "GB",
    "wof:name": "PH2 8EW",
    "wof:placetype": "postalcode"
  },
  "geometry": {"coordinates":[-3.421453,56.374216],"type":"Point"}
}
