{
  "type": "Feature",
  "properties": {
    "iso:country": "GB",
    "wof:name": "WA7 3GN",
    "wof:placetype": "postalcode"
  },
  "geometry": {"coordinates":[-2.65753,53.318872],"type":"Point"}
}
