{
  "type": "Feature",
  "properties": {
    "date:inception_lower": "1980-01-01",
    "date:inception_upper": "1980-01-01",
    "iso:country": "GB",
    "wof:name": "IV24 3EG",
    "wof:placetype": "postalcode"
  },
  "geometry": {"coordinates":[-4.345773,57.892223],"type":"Point"}
}
