{
  "type": "Feature",
  "properties": {
    "iso:country": "GB",
    "wof:name": "IV24 3EG",
    "wof:placetype": "postalcode"
  },
  "geometry": {"coordinates":[-4.345773,57.892223],"type":"Point"}
}
