{
  "type": "Feature",
  "properties": {
    "iso:country": "GB",
    "wof:name": "LE4 0EP",
    "wof:placetype": "postalcode"
  },
  "geometry": {"coordinates":[-1.1522,52.653798],"type":"Point"}
}
