{
  "type": "Feature",
  "properties": {
    "date:inception_lower": "1980-01-01",
    "date:inception_upper": "1980-01-01",
    "iso:country": "GB",
    "wof:name": "SR2 9QJ",
    "wof:placetype": "postalcode"
  },
  "geometry": {"coordinates":[-1.36739,54.887738],"type":"Point"}
}
