{
  "type": "Feature",
  "properties": {
    "iso:country":"GB",
    "wof:name":"SR2 9QJ",
    "wof:placetype":"postalcode"
},
  "geometry": {"coordinates":[-1.36738975500649,54.8877377954564],"type":"Point"}
}