{
  "type": "Feature",
  "properties": {
    "iso:country": "GB",
    "wof:name": "GU10 1FG",
    "wof:placetype": "postalcode"
  },
  "geometry": {"coordinates":[-0.756773,51.224856],"type":"Point"}
}
