{
  "type": "Feature",
  "properties": {
    "iso:country": "GB",
    "wof:name": "L37 7AN",
    "wof:placetype": "postalcode"
  },
  "geometry": {"coordinates":[-3.066087,53.569474],"type":"Point"}
}
