{
  "type": "Feature",
  "properties": {
    "date:inception_lower": "2017-06-01",
    "date:inception_upper": "2017-06-01",
    "iso:country": "GB",
    "wof:name": "SE17 1FN",
    "wof:placetype": "postalcode"
  },
  "geometry": {"coordinates":[-0.094334,51.49233],"type":"Point"}
}
