{
  "type": "Feature",
  "properties": {
    "iso:country": "GB",
    "wof:name": "L14 2DR",
    "wof:placetype": "postalcode"
  },
  "geometry": {"coordinates":[-2.876369,53.42279],"type":"Point"}
}
