{
  "type": "Feature",
  "properties": {
    "date:inception_lower":"2003-02-01",
    "date:inception_upper":"2003-02-28",
    "iso:country":"GB",
    "wof:name":"IV2 3PR",
    "wof:placetype":"postalcode"
},
  "geometry": {"coordinates":[-4.221406,57.479824],"type":"Point"}
}