{
  "type": "Feature",
  "properties": {
    "date:inception_lower": "2003-02-01",
    "date:inception_upper": "2003-02-01",
    "iso:country": "GB",
    "wof:name": "IV2 3PR",
    "wof:placetype": "postalcode"
  },
  "geometry": {"coordinates":[-4.221398,57.479707],"type":"Point"}
}
