{
  "type": "Feature",
  "properties": {
    "iso:country": "GB",
    "wof:name": "IV2 3PR",
    "wof:placetype": "postalcode"
  },
  "geometry": {"coordinates":[-4.221406,57.479824],"type":"Point"}
}
