{
  "type": "Feature",
  "properties": {
    "iso:country":"GB",
    "wof:name":"NE3 4TY",
    "wof:placetype":"postalcode"
},
  "geometry": {"coordinates":[-1.6510424837139,54.9999625364626],"type":"Point"}
}