{
  "type": "Feature",
  "properties": {
    "iso:country":"GB",
    "wof:name":"SN5 7DX",
    "wof:placetype":"postalcode"
},
  "geometry": {"coordinates":[-1.82736442734401,51.56140354311746],"type":"Point"}
}