{
  "type": "Feature",
  "properties": {
    "date:inception_lower": "1982-03-01",
    "date:inception_upper": "1982-03-01",
    "iso:country": "GB",
    "wof:name": "SN5 7DX",
    "wof:placetype": "postalcode"
  },
  "geometry": {"coordinates":[-1.827364,51.561404],"type":"Point"}
}
