{
  "type": "Feature",
  "properties": {
    "iso:country": "GB",
    "wof:name": "WV5 8DF",
    "wof:placetype": "postalcode"
  },
  "geometry": {"coordinates":[-2.199653,52.540332],"type":"Point"}
}
