{
  "type": "Feature",
  "properties": {
    "iso:country": "GB",
    "wof:name": "SN16 0QP",
    "wof:placetype": "postalcode"
  },
  "geometry": {"coordinates":[-2.112526,51.589349],"type":"Point"}
}
