{
  "type": "Feature",
  "properties": {
    "iso:country":"GB",
    "wof:name":"CW11 3RF",
    "wof:placetype":"postalcode"
},
  "geometry": {"coordinates":[-2.38077575982099,53.13099859791092],"type":"Point"}
}