{
  "type": "Feature",
  "properties": {
    "iso:country": "GB",
    "wof:name": "CW11 3RF",
    "wof:placetype": "postalcode"
  },
  "geometry": {"coordinates":[-2.380776,53.130999],"type":"Point"}
}
