{
  "type": "Feature",
  "properties": {
    "iso:country": "GB",
    "wof:name": "HX3 7QE",
    "wof:placetype": "postalcode"
  },
  "geometry": {"coordinates":[-1.803725,53.75853],"type":"Point"}
}
