{
  "type": "Feature",
  "properties": {
    "iso:country":"GB",
    "wof:name":"DT6 3LH",
    "wof:placetype":"postalcode"
},
  "geometry": {"coordinates":[-2.7559029182151,50.73315352460385],"type":"Point"}
}