{
  "type": "Feature",
  "properties": {
    "iso:country": "GB",
    "wof:name": "GL3 1BQ",
    "wof:placetype": "postalcode"
  },
  "geometry": {"coordinates":[-2.207722,51.887039],"type":"Point"}
}
