{
  "type": "Feature",
  "properties": {
    "iso:country":"GB",
    "wof:name":"GL3 1BQ",
    "wof:placetype":"postalcode"
},
  "geometry": {"coordinates":[-2.20772601814677,51.88703159051936],"type":"Point"}
}