{
  "type": "Feature",
  "properties": {
    "iso:country":"GB",
    "wof:name":"M24 6DF",
    "wof:placetype":"postalcode"
},
  "geometry": {"coordinates":[-2.19534979476882,53.55557738342206],"type":"Point"}
}