{
  "type": "Feature",
  "properties": {
    "date:inception_lower":"2012-07-01",
    "date:inception_upper":"2012-07-31",
    "iso:country":"GB",
    "wof:name":"WD3 4FW",
    "wof:placetype":"postalcode"
},
  "geometry": {"coordinates":[-0.491048,51.640766],"type":"Point"}
}