{
  "type": "Feature",
  "properties": {
    "iso:country":"GB",
    "wof:name":"WD3 4FW",
    "wof:placetype":"postalcode"
},
  "geometry": {"coordinates":[-0.49098346183459,51.64075263723942],"type":"Point"}
}