{
  "type": "Feature",
  "properties": {
    "iso:country": "GB",
    "wof:name": "WD3 4FW",
    "wof:placetype": "postalcode"
  },
  "geometry": {"coordinates":[-0.491048,51.640766],"type":"Point"}
}
