{
  "type": "Feature",
  "properties": {
    "iso:country":"GB",
    "wof:name":"BD23 5PU",
    "wof:placetype":"postalcode"
},
  "geometry": {"coordinates":[-2.06877479144459,54.1256666554461],"type":"Point"}
}