{
  "type": "Feature",
  "properties": {
    "iso:country":"GB",
    "wof:name":"EH6 4QQ",
    "wof:placetype":"postalcode"
},
  "geometry": {"coordinates":[-3.19112905495358,55.97698348307621],"type":"Point"}
}