{
  "type": "Feature",
  "properties": {
    "iso:country":"GB",
    "wof:name":"FY1 5EG",
    "wof:placetype":"postalcode"
},
  "geometry": {"coordinates":[-3.04841295703165,53.8105234962234],"type":"Point"}
}