{
  "type": "Feature",
  "properties": {
    "iso:country":"GB",
    "wof:name":"GU34 5JG",
    "wof:placetype":"postalcode"
},
  "geometry": {"coordinates":[-1.04870697538301,51.11116130078043],"type":"Point"}
}