{
  "type": "Feature",
  "properties": {
    "iso:country": "GB",
    "wof:name": "GU34 5JG",
    "wof:placetype": "postalcode"
  },
  "geometry": {"coordinates":[-1.048707,51.111161],"type":"Point"}
}
