{
  "type": "Feature",
  "properties": {
    "iso:country":"GB",
    "wof:name":"YO31 0LE",
    "wof:placetype":"postalcode"
},
  "geometry": {"coordinates":[-1.05104332638555,53.96664500704146],"type":"Point"}
}