{
  "type": "Feature",
  "properties": {
    "iso:country":"GB",
    "wof:name":"ST10 4PE",
    "wof:placetype":"postalcode"
},
  "geometry": {"coordinates":[-2.01576865109263,52.92083915824313],"type":"Point"}
}