{
  "type": "Feature",
  "properties": {
    "iso:country": "GB",
    "wof:name": "ST10 4PE",
    "wof:placetype": "postalcode"
  },
  "geometry": {"coordinates":[-2.015769,52.920839],"type":"Point"}
}
