{
  "type": "Feature",
  "properties": {
    "iso:country": "GB",
    "wof:name": "ST14 8SG",
    "wof:placetype": "postalcode"
  },
  "geometry": {"coordinates":[-1.966318,52.897589],"type":"Point"}
}
