{
  "type": "Feature",
  "properties": {
    "iso:country":"GB",
    "wof:name":"ST14 8SG",
    "wof:placetype":"postalcode"
},
  "geometry": {"coordinates":[-1.96631829347394,52.89758920302289],"type":"Point"}
}