{
  "type": "Feature",
  "properties": {
    "date:inception_lower":"1990-02-01",
    "date:inception_upper":"1990-02-28",
    "iso:country":"GB",
    "wof:name":"IP17 3JS",
    "wof:placetype":"postalcode"
},
  "geometry": {"coordinates":[1.498685,52.270884],"type":"Point"}
}