{
  "type": "Feature",
  "properties": {
    "iso:country":"GB",
    "wof:name":"EH37 5UJ",
    "wof:placetype":"postalcode"
},
  "geometry": {"coordinates":[-2.93046890658109,55.87355174790045],"type":"Point"}
}