{
  "type": "Feature",
  "properties": {
    "iso:country": "GB",
    "wof:name": "BA2 2LP",
    "wof:placetype": "postalcode"
  },
  "geometry": {"coordinates":[-2.386823,51.364759],"type":"Point"}
}
