{
  "type": "Feature",
  "properties": {
    "date:inception_lower":"1980-01-01",
    "date:inception_upper":"1980-01-31",
    "iso:country":"GB",
    "wof:name":"BA2 2LP",
    "wof:placetype":"postalcode"
},
  "geometry": {"coordinates":[-2.386823,51.364759],"type":"Point"}
}