{
  "type": "Feature",
  "properties": {
    "iso:country":"GB",
    "wof:name":"BA2 2LP",
    "wof:placetype":"postalcode"
},
  "geometry": {"coordinates":[-2.38682288549584,51.36475870434369],"type":"Point"}
}