{
  "type": "Feature",
  "properties": {
    "iso:country":"GB",
    "wof:name":"WV3 9ES",
    "wof:placetype":"postalcode"
},
  "geometry": {"coordinates":[-2.17038658500541,52.58238685885098],"type":"Point"}
}