{
  "type": "Feature",
  "properties": {
    "date:inception_lower": "1980-01-01",
    "date:inception_upper": "1980-01-01",
    "iso:country": "GB",
    "wof:name": "CH2 2AN",
    "wof:placetype": "postalcode"
  },
  "geometry": {"coordinates":[-2.890875,53.202228],"type":"Point"}
}
