{
  "type": "Feature",
  "properties": {
    "iso:country":"GB",
    "wof:name":"CH2 2AN",
    "wof:placetype":"postalcode"
},
  "geometry": {"coordinates":[-2.89087517530563,53.20222790692296],"type":"Point"}
}