{
  "type": "Feature",
  "properties": {
    "date:inception_lower": "1980-01-01",
    "date:inception_upper": "1980-01-01",
    "iso:country": "GB",
    "wof:name": "ST16 1ND",
    "wof:placetype": "postalcode"
  },
  "geometry": {"coordinates":[-2.125779,52.82109],"type":"Point"}
}
