{
  "type": "Feature",
  "properties": {
    "iso:country":"GB",
    "wof:name":"SY16 2QQ",
    "wof:placetype":"postalcode"
},
  "geometry": {"coordinates":[-3.30677690764786,52.52265739697575],"type":"Point"}
}