{
  "type": "Feature",
  "properties": {
    "date:inception_lower": "1985-10-01",
    "date:inception_upper": "1985-10-01",
    "iso:country": "GB",
    "wof:name": "SY16 2QQ",
    "wof:placetype": "postalcode"
  },
  "geometry": {"coordinates":[-3.306777,52.522657],"type":"Point"}
}
