{
  "type": "Feature",
  "properties": {
    "iso:country":"GB",
    "wof:name":"NW10 7LF",
    "wof:placetype":"postalcode"
},
  "geometry": {"coordinates":[-0.26744000595412,51.52689130198065],"type":"Point"}
}