{
  "type": "Feature",
  "properties": {
    "iso:country": "GB",
    "wof:name": "NW10 7LF",
    "wof:placetype": "postalcode"
  },
  "geometry": {"coordinates":[-0.26744,51.526891],"type":"Point"}
}
