{
  "type": "Feature",
  "properties": {
    "date:inception_lower": "1980-01-01",
    "date:inception_upper": "1980-01-01",
    "iso:country": "GB",
    "wof:name": "RH12 3PA",
    "wof:placetype": "postalcode"
  },
  "geometry": {"coordinates":[-0.357161,51.077453],"type":"Point"}
}
