{
  "type": "Feature",
  "properties": {
    "iso:country":"GB",
    "wof:name":"RH12 3PA",
    "wof:placetype":"postalcode"
},
  "geometry": {"coordinates":[-0.3571913841486,51.07733992444781],"type":"Point"}
}