{
  "type": "Feature",
  "properties": {
    "iso:country": "GB",
    "wof:name": "RH12 3PA",
    "wof:placetype": "postalcode"
  },
  "geometry": {"coordinates":[-0.357191,51.07734],"type":"Point"}
}
