{
  "type": "Feature",
  "properties": {
    "iso:country":"GB",
    "wof:name":"PE7 8BP",
    "wof:placetype":"postalcode"
},
  "geometry": {"coordinates":[-0.26986592919398,52.53853118624767],"type":"Point"}
}