{
  "type": "Feature",
  "properties": {
    "date:inception_lower": "2000-06-01",
    "date:inception_upper": "2000-06-01",
    "iso:country": "GB",
    "wof:name": "PE7 8BP",
    "wof:placetype": "postalcode"
  },
  "geometry": {"coordinates":[-0.269866,52.538531],"type":"Point"}
}
