{
  "type": "Feature",
  "properties": {
    "iso:country":"GB",
    "wof:name":"S13 9BD",
    "wof:placetype":"postalcode"
},
  "geometry": {"coordinates":[-1.38070088744028,53.37476771429057],"type":"Point"}
}