{
  "type": "Feature",
  "properties": {
    "iso:country":"GB",
    "wof:name":"LU7 0SX",
    "wof:placetype":"postalcode"
},
  "geometry": {"coordinates":[-0.66386969937181,51.8499246650533],"type":"Point"}
}