{
  "type": "Feature",
  "properties": {
    "date:inception_lower":"1984-02-01",
    "date:inception_upper":"1984-02-29",
    "iso:country":"GB",
    "wof:name":"LU7 0SX",
    "wof:placetype":"postalcode"
},
  "geometry": {"coordinates":[-0.66387,51.849925],"type":"Point"}
}