{
  "type": "Feature",
  "properties": {
    "iso:country": "GB",
    "wof:name": "LU7 0SX",
    "wof:placetype": "postalcode"
  },
  "geometry": {"coordinates":[-0.66387,51.849925],"type":"Point"}
}
