{
  "type": "Feature",
  "properties": {
    "date:inception_lower":"2002-05-01",
    "date:inception_upper":"2002-05-31",
    "iso:country":"GB",
    "wof:name":"LS19 7ZB",
    "wof:placetype":"postalcode"
},
  "geometry": {"coordinates":[-1.683009,53.866927],"type":"Point"}
}