{
  "type": "Feature",
  "properties": {
    "iso:country": "GB",
    "wof:name": "LS19 7ZB",
    "wof:placetype": "postalcode"
  },
  "geometry": {"coordinates":[-1.683009,53.866927],"type":"Point"}
}
