{
  "type": "Feature",
  "properties": {
    "iso:country":"GB",
    "wof:name":"LS19 7ZB",
    "wof:placetype":"postalcode"
},
  "geometry": {"coordinates":[-1.68300911333366,53.86692737925194],"type":"Point"}
}