{
  "type": "Feature",
  "properties": {
    "iso:country": "GB",
    "wof:name": "DD10 8TZ",
    "wof:placetype": "postalcode"
  },
  "geometry": {"coordinates":[-2.459677,56.722267],"type":"Point"}
}
