{
  "type": "Feature",
  "properties": {
    "date:inception_lower": "2007-07-01",
    "date:inception_upper": "2007-07-01",
    "iso:country": "GB",
    "wof:name": "DD10 8TZ",
    "wof:placetype": "postalcode"
  },
  "geometry": {"coordinates":[-2.459677,56.722267],"type":"Point"}
}
