{
  "type": "Feature",
  "properties": {
    "iso:country":"GB",
    "wof:name":"SS9 5YD",
    "wof:placetype":"postalcode"
},
  "geometry": {"coordinates":[0.65700629699132,51.56740974925217],"type":"Point"}
}