{
  "type": "Feature",
  "properties": {
    "iso:country":"GB",
    "wof:name":"TD15 2EL",
    "wof:placetype":"postalcode"
},
  "geometry": {"coordinates":[-2.01533320555933,55.75460418353887],"type":"Point"}
}