{
  "type": "Feature",
  "properties": {
    "iso:country": "GB",
    "wof:name": "TD15 2EL",
    "wof:placetype": "postalcode"
  },
  "geometry": {"coordinates":[-2.015333,55.754604],"type":"Point"}
}
