{
  "type": "Feature",
  "properties": {
    "date:inception_lower": "1994-05-01",
    "date:inception_upper": "1994-05-01",
    "iso:country": "GB",
    "wof:name": "M41 9HR",
    "wof:placetype": "postalcode"
  },
  "geometry": {"coordinates":[-2.35628,53.444558],"type":"Point"}
}
