{
  "type": "Feature",
  "properties": {
    "iso:country":"GB",
    "wof:name":"EX23 9NB",
    "wof:placetype":"postalcode"
},
  "geometry": {"coordinates":[-4.50396677598578,50.83215218021958],"type":"Point"}
}