{
  "type": "Feature",
  "properties": {
    "date:inception_lower": "1980-01-01",
    "date:inception_upper": "1980-01-01",
    "iso:country": "GB",
    "wof:name": "L12 5HT",
    "wof:placetype": "postalcode"
  },
  "geometry": {"coordinates":[-2.914728,53.43542],"type":"Point"}
}
