{
  "type": "Feature",
  "properties": {
    "iso:country": "GB",
    "wof:name": "E1 4PH",
    "wof:placetype": "postalcode"
  },
  "geometry": {"coordinates":[-0.039039,51.521937],"type":"Point"}
}
