{
  "type": "Feature",
  "properties": {
    "iso:country":"GB",
    "wof:name":"SK22 4PD",
    "wof:placetype":"postalcode"
},
  "geometry": {"coordinates":[-1.99352944918975,53.36194580591267],"type":"Point"}
}