{
  "type": "Feature",
  "properties": {
    "iso:country": "GB",
    "wof:name": "SK22 4PD",
    "wof:placetype": "postalcode"
  },
  "geometry": {"coordinates":[-1.993529,53.361946],"type":"Point"}
}
