{
  "type": "Feature",
  "properties": {
    "iso:country": "GB",
    "wof:name": "CA26 3XD",
    "wof:placetype": "postalcode"
  },
  "geometry": {"coordinates":[-3.471336,54.556082],"type":"Point"}
}
