{
  "type": "Feature",
  "properties": {
    "date:inception_lower": "1980-01-01",
    "date:inception_upper": "1980-01-01",
    "iso:country": "GB",
    "wof:name": "CA26 3XD",
    "wof:placetype": "postalcode"
  },
  "geometry": {"coordinates":[-3.471336,54.556082],"type":"Point"}
}
