{
  "type": "Feature",
  "properties": {
    "iso:country": "GB",
    "wof:name": "FY1 6AH",
    "wof:placetype": "postalcode"
  },
  "geometry": {"coordinates":[-3.054815,53.806036],"type":"Point"}
}
