{
  "type": "Feature",
  "properties": {
    "iso:country":"GB",
    "wof:name":"FY1 6AH",
    "wof:placetype":"postalcode"
},
  "geometry": {"coordinates":[-3.05481552056717,53.80603606360539],"type":"Point"}
}