{
  "type": "Feature",
  "properties": {
    "date:inception_lower": "2019-12-01",
    "date:inception_upper": "2019-12-01",
    "iso:country": "GB",
    "wof:name": "IV2 7AE",
    "wof:placetype": "postalcode"
  },
  "geometry": {"coordinates":[-4.073803,57.538486],"type":"Point"}
}
