{
  "type": "Feature",
  "properties": {
    "iso:country": "GB",
    "wof:name": "IV2 7AE",
    "wof:placetype": "postalcode"
  },
  "geometry": {"coordinates":[-4.073695,57.538362],"type":"Point"}
}
