{
  "type": "Feature",
  "properties": {
    "iso:country": "GB",
    "wof:name": "ST4 8SU",
    "wof:placetype": "postalcode"
  },
  "geometry": {"coordinates":[-2.179821,52.960463],"type":"Point"}
}
