{
  "type": "Feature",
  "properties": {
    "date:inception_lower": "1980-01-01",
    "date:inception_upper": "1980-01-01",
    "iso:country": "GB",
    "wof:name": "PO12 1NZ",
    "wof:placetype": "postalcode"
  },
  "geometry": {"coordinates":[-1.136812,50.792457],"type":"Point"}
}
