{
  "type": "Feature",
  "properties": {
    "iso:country": "GB",
    "wof:name": "PR3 1NH",
    "wof:placetype": "postalcode"
  },
  "geometry": {"coordinates":[-2.785686,53.897686],"type":"Point"}
}
