{
  "type": "Feature",
  "properties": {
    "date:inception_lower": "2017-11-01",
    "date:inception_upper": "2017-11-01",
    "iso:country": "GB",
    "wof:name": "SK6 5PB",
    "wof:placetype": "postalcode"
  },
  "geometry": {"coordinates":[-1.999794,53.40073],"type":"Point"}
}
