{
  "type": "Feature",
  "properties": {
    "iso:country": "GB",
    "wof:name": "TS29 6LY",
    "wof:placetype": "postalcode"
  },
  "geometry": {"coordinates":[-1.425273,54.701158],"type":"Point"}
}
