{
  "type": "Feature",
  "properties": {
    "iso:country":"GB",
    "wof:name":"TS29 6LY",
    "wof:placetype":"postalcode"
},
  "geometry": {"coordinates":[-1.42527327733967,54.70115767501764],"type":"Point"}
}