{
  "type": "Feature",
  "properties": {
    "date:inception_lower":"1980-01-01",
    "date:inception_upper":"1980-01-31",
    "iso:country":"GB",
    "wof:name":"TS29 6LY",
    "wof:placetype":"postalcode"
},
  "geometry": {"coordinates":[-1.425273,54.701158],"type":"Point"}
}