{
  "type": "Feature",
  "properties": {
    "date:inception_lower": "1980-01-01",
    "date:inception_upper": "1980-01-01",
    "iso:country": "GB",
    "wof:name": "SR8 3DJ",
    "wof:placetype": "postalcode"
  },
  "geometry": {"coordinates":[-1.340002,54.787383],"type":"Point"}
}
