{
  "type": "Feature",
  "properties": {
    "iso:country":"GB",
    "wof:name":"SR8 3DJ",
    "wof:placetype":"postalcode"
},
  "geometry": {"coordinates":[-1.34000173831802,54.78738262909416],"type":"Point"}
}