{
  "type": "Feature",
  "properties": {
    "iso:country": "GB",
    "wof:name": "CF31 3LU",
    "wof:placetype": "postalcode"
  },
  "geometry": {"coordinates":[-3.579394,51.493131],"type":"Point"}
}
