{
  "type": "Feature",
  "properties": {
    "date:inception_lower":"1986-07-01",
    "date:inception_upper":"1986-07-31",
    "iso:country":"GB",
    "wof:name":"CF31 3LU",
    "wof:placetype":"postalcode"
},
  "geometry": {"coordinates":[-3.579394,51.493131],"type":"Point"}
}