{
  "type": "Feature",
  "properties": {
    "iso:country":"GB",
    "wof:name":"B91 2AS",
    "wof:placetype":"postalcode"
},
  "geometry": {"coordinates":[-1.77820405958064,52.4227581352378],"type":"Point"}
}