{
  "type": "Feature",
  "properties": {
    "iso:country":"GB",
    "wof:name":"NR34 9RF",
    "wof:placetype":"postalcode"
},
  "geometry": {"coordinates":[1.5709248853435,52.45492466748134],"type":"Point"}
}