{
  "type": "Feature",
  "properties": {
    "date:inception_lower":"1980-01-01",
    "date:inception_upper":"1980-01-31",
    "iso:country":"GB",
    "wof:name":"NR34 9RF",
    "wof:placetype":"postalcode"
},
  "geometry": {"coordinates":[1.570925,52.454925],"type":"Point"}
}