{
  "type": "Feature",
  "properties": {
    "date:inception_lower":"2012-07-01",
    "date:inception_upper":"2012-07-31",
    "iso:country":"GB",
    "wof:name":"IP28 8YP",
    "wof:placetype":"postalcode"
},
  "geometry": {"coordinates":[0.481081,52.371916],"type":"Point"}
}