{
  "type": "Feature",
  "properties": {
    "iso:country": "GB",
    "wof:name": "IP28 8YP",
    "wof:placetype": "postalcode"
  },
  "geometry": {"coordinates":[0.481081,52.371916],"type":"Point"}
}
