{
  "type": "Feature",
  "properties": {
    "date:inception_lower":"1998-06-01",
    "date:inception_upper":"1998-06-30",
    "iso:country":"GB",
    "wof:name":"YO42 2XF",
    "wof:placetype":"postalcode"
},
  "geometry": {"coordinates":[-0.788862,53.933081],"type":"Point"}
}