{
  "type": "Feature",
  "properties": {
    "iso:country":"GB",
    "wof:name":"YO42 2XF",
    "wof:placetype":"postalcode"
},
  "geometry": {"coordinates":[-0.78886173793958,53.93308120745026],"type":"Point"}
}