{
  "type": "Feature",
  "properties": {
    "date:inception_lower": "1980-01-01",
    "date:inception_upper": "1980-01-01",
    "iso:country": "GB",
    "wof:name": "G14 9NL",
    "wof:placetype": "postalcode"
  },
  "geometry": {"coordinates":[-4.330997,55.877683],"type":"Point"}
}
