{
  "type": "Feature",
  "properties": {
    "iso:country": "GB",
    "wof:name": "BS16 4LL",
    "wof:placetype": "postalcode"
  },
  "geometry": {"coordinates":[-2.514888,51.480986],"type":"Point"}
}
