{
  "type": "Feature",
  "properties": {
    "iso:country": "GB",
    "wof:name": "CV1 5QP",
    "wof:placetype": "postalcode"
  },
  "geometry": {"coordinates":[-1.506128,52.407192],"type":"Point"}
}
