{
  "type": "Feature",
  "properties": {
    "iso:country":"GB",
    "wof:name":"CV1 5QP",
    "wof:placetype":"postalcode"
},
  "geometry": {"coordinates":[-1.50612770246368,52.40719158896569],"type":"Point"}
}