{
  "type": "Feature",
  "properties": {
    "date:inception_lower":"1980-01-01",
    "date:inception_upper":"1980-01-31",
    "iso:country":"GB",
    "wof:name":"CV1 5QP",
    "wof:placetype":"postalcode"
},
  "geometry": {"coordinates":[-1.506128,52.407192],"type":"Point"}
}