{
  "type": "Feature",
  "properties": {
    "iso:country":"GB",
    "wof:name":"E11 3QT",
    "wof:placetype":"postalcode"
},
  "geometry": {"coordinates":[0.02235907649348,51.56334028352826],"type":"Point"}
}