{
  "type": "Feature",
  "properties": {
    "date:inception_lower": "1980-01-01",
    "date:inception_upper": "1980-01-01",
    "iso:country": "GB",
    "wof:name": "HU6 9SL",
    "wof:placetype": "postalcode"
  },
  "geometry": {"coordinates":[-0.379624,53.783769],"type":"Point"}
}
