{
  "type": "Feature",
  "properties": {
    "date:inception_lower":"1980-01-01",
    "date:inception_upper":"1980-01-31",
    "iso:country":"GB",
    "wof:name":"NW8 9ST",
    "wof:placetype":"postalcode"
},
  "geometry": {"coordinates":[-0.172246,51.533099],"type":"Point"}
}