{
  "type": "Feature",
  "properties": {
    "iso:country":"GB",
    "wof:name":"KA21 6DJ",
    "wof:placetype":"postalcode"
},
  "geometry": {"coordinates":[-4.79154935906304,55.64500593926952],"type":"Point"}
}