{
  "type": "Feature",
  "properties": {
    "iso:country": "GB",
    "wof:name": "KA21 6DJ",
    "wof:placetype": "postalcode"
  },
  "geometry": {"coordinates":[-4.791549,55.645006],"type":"Point"}
}
