{
  "type": "Feature",
  "properties": {
    "date:inception_lower": "1980-01-01",
    "date:inception_upper": "1980-01-01",
    "iso:country": "GB",
    "wof:name": "BB1 2BY",
    "wof:placetype": "postalcode"
  },
  "geometry": {"coordinates":[-2.434696,53.745318],"type":"Point"}
}
