{
  "type": "Feature",
  "properties": {
    "iso:country":"GB",
    "wof:name":"BB1 2BY",
    "wof:placetype":"postalcode"
},
  "geometry": {"coordinates":[-2.43469620179093,53.74531773837536],"type":"Point"}
}