{
  "type": "Feature",
  "properties": {
    "iso:country":"GB",
    "wof:name":"SA67 8AW",
    "wof:placetype":"postalcode"
},
  "geometry": {"coordinates":[-4.84885041199806,51.74951474596163],"type":"Point"}
}