{
  "type": "Feature",
  "properties": {
    "iso:country": "GB",
    "wof:name": "SA67 8AW",
    "wof:placetype": "postalcode"
  },
  "geometry": {"coordinates":[-4.84885,51.749515],"type":"Point"}
}
