{
  "type": "Feature",
  "properties": {
    "iso:country":"GB",
    "wof:name":"W6 9NL",
    "wof:placetype":"postalcode"
},
  "geometry": {"coordinates":[-0.24417468547274,51.49084556211734],"type":"Point"}
}