{
  "type": "Feature",
  "properties": {
    "iso:country": "GB",
    "wof:name": "CA11 7YF",
    "wof:placetype": "postalcode"
  },
  "geometry": {"coordinates":[-2.750828,54.664793],"type":"Point"}
}
