{
  "type": "Feature",
  "properties": {
    "date:inception_lower":"1980-01-01",
    "date:inception_upper":"1980-01-31",
    "iso:country":"GB",
    "wof:name":"CA11 7YF",
    "wof:placetype":"postalcode"
},
  "geometry": {"coordinates":[-2.750828,54.664793],"type":"Point"}
}