{
  "type": "Feature",
  "properties": {
    "iso:country": "GB",
    "wof:name": "IG11 7PB",
    "wof:placetype": "postalcode"
  },
  "geometry": {"coordinates":[0.082724,51.535486],"type":"Point"}
}
