{
  "type": "Feature",
  "properties": {
    "iso:country":"GB",
    "wof:name":"HX2 9RQ",
    "wof:placetype":"postalcode"
},
  "geometry": {"coordinates":[-1.88604830366951,53.75522978844222],"type":"Point"}
}