{
  "type": "Feature",
  "properties": {
    "iso:country":"GB",
    "wof:name":"NE8 4QU",
    "wof:placetype":"postalcode"
},
  "geometry": {"coordinates":[-1.61111713243849,54.94823345791832],"type":"Point"}
}