{
  "type": "Feature",
  "properties": {
    "date:inception_lower":"1980-01-01",
    "date:inception_upper":"1980-01-31",
    "iso:country":"GB",
    "wof:name":"NG17 1HZ",
    "wof:placetype":"postalcode"
},
  "geometry": {"coordinates":[-1.284493,53.120075],"type":"Point"}
}