{
  "type": "Feature",
  "properties": {
    "iso:country":"GB",
    "wof:name":"LU1 3UB",
    "wof:placetype":"postalcode"
},
  "geometry": {"coordinates":[-0.4174557294708,51.87440949465923],"type":"Point"}
}