{
  "type": "Feature",
  "properties": {
    "iso:country": "GB",
    "wof:name": "WA5 4LZ",
    "wof:placetype": "postalcode"
  },
  "geometry": {"coordinates":[-2.650703,53.432395],"type":"Point"}
}
