{
  "type": "Feature",
  "properties": {
    "iso:country":"GB",
    "wof:name":"WA5 4LZ",
    "wof:placetype":"postalcode"
},
  "geometry": {"coordinates":[-2.6507031359489,53.4323953311572],"type":"Point"}
}