{
  "type": "Feature",
  "properties": {
    "iso:country":"GB",
    "wof:name":"TN21 9QZ",
    "wof:placetype":"postalcode"
},
  "geometry": {"coordinates":[0.31512375773809,50.9393776625025],"type":"Point"}
}