{
  "type": "Feature",
  "properties": {
    "iso:country": "GB",
    "wof:name": "TN21 9QZ",
    "wof:placetype": "postalcode"
  },
  "geometry": {"coordinates":[0.315124,50.939378],"type":"Point"}
}
