{
  "type": "Feature",
  "properties": {
    "date:inception_lower": "1980-01-01",
    "date:inception_upper": "1980-01-01",
    "iso:country": "GB",
    "wof:name": "SA40 9RN",
    "wof:placetype": "postalcode"
  },
  "geometry": {"coordinates":[-4.14965,52.073119],"type":"Point"}
}
