{
  "type": "Feature",
  "properties": {
    "iso:country": "GB",
    "wof:name": "CA14 4PW",
    "wof:placetype": "postalcode"
  },
  "geometry": {"coordinates":[-3.531341,54.608203],"type":"Point"}
}
