{
  "type": "Feature",
  "properties": {
    "date:inception_lower":"1980-01-01",
    "date:inception_upper":"1980-01-31",
    "iso:country":"GB",
    "wof:name":"CA14 4PW",
    "wof:placetype":"postalcode"
},
  "geometry": {"coordinates":[-3.530984,54.60819],"type":"Point"}
}