{
  "type": "Feature",
  "properties": {
    "iso:country":"GB",
    "wof:name":"TF9 4BS",
    "wof:placetype":"postalcode"
},
  "geometry": {"coordinates":[-2.39574082782251,52.91983876191143],"type":"Point"}
}