{
  "type": "Feature",
  "properties": {
    "iso:country":"GB",
    "wof:name":"OX3 0LE",
    "wof:placetype":"postalcode"
},
  "geometry": {"coordinates":[-1.2376657627748,51.76429342326976],"type":"Point"}
}