{
  "type": "Feature",
  "properties": {
    "iso:country":"GB",
    "wof:name":"M26 1DR",
    "wof:placetype":"postalcode"
},
  "geometry": {"coordinates":[-2.33502731522458,53.54848118454326],"type":"Point"}
}