{
  "type": "Feature",
  "properties": {
    "iso:country":"GB",
    "wof:name":"WV14 8HY",
    "wof:placetype":"postalcode"
},
  "geometry": {"coordinates":[-2.08255191370194,52.53924872605422],"type":"Point"}
}