{
  "type": "Feature",
  "properties": {
    "iso:country":"GB",
    "wof:name":"B30 1HP",
    "wof:placetype":"postalcode"
},
  "geometry": {"coordinates":[-1.93827470575261,52.41819393269913],"type":"Point"}
}