{
  "type": "Feature",
  "properties": {
    "date:inception_lower": "1980-01-01",
    "date:inception_upper": "1980-01-01",
    "iso:country": "GB",
    "wof:name": "B30 1HP",
    "wof:placetype": "postalcode"
  },
  "geometry": {"coordinates":[-1.938275,52.418194],"type":"Point"}
}
