{
  "type": "Feature",
  "properties": {
    "iso:country":"GB",
    "wof:name":"WA16 0AJ",
    "wof:placetype":"postalcode"
},
  "geometry": {"coordinates":[-2.38486778011583,53.30596315764424],"type":"Point"}
}