{
  "type": "Feature",
  "properties": {
    "iso:country":"GB",
    "wof:name":"OX9 3YW",
    "wof:placetype":"postalcode"
},
  "geometry": {"coordinates":[-0.9644313230933,51.74976036384835],"type":"Point"}
}