{
  "type": "Feature",
  "properties": {
    "iso:country":"GB",
    "wof:name":"SG11 1RX",
    "wof:placetype":"postalcode"
},
  "geometry": {"coordinates":[0.01180230678793,51.88990091054626],"type":"Point"}
}