{
  "type": "Feature",
  "properties": {
    "date:inception_lower":"1980-01-01",
    "date:inception_upper":"1980-01-31",
    "iso:country":"GB",
    "wof:name":"SG11 1RX",
    "wof:placetype":"postalcode"
},
  "geometry": {"coordinates":[0.011802,51.889901],"type":"Point"}
}