{
  "type": "Feature",
  "properties": {
    "iso:country": "GB",
    "wof:name": "AB51 8SD",
    "wof:placetype": "postalcode"
  },
  "geometry": {"coordinates":[-2.461384,57.411042],"type":"Point"}
}
