{
  "type": "Feature",
  "properties": {
    "iso:country": "GB",
    "wof:name": "DN9 2EB",
    "wof:placetype": "postalcode"
  },
  "geometry": {"coordinates":[-0.870214,53.487419],"type":"Point"}
}
