{
  "type": "Feature",
  "properties": {
    "iso:country":"GB",
    "wof:name":"DN9 2EB",
    "wof:placetype":"postalcode"
},
  "geometry": {"coordinates":[-0.87021355537083,53.48741865871897],"type":"Point"}
}