{
  "type": "Feature",
  "properties": {
    "iso:country":"GB",
    "wof:name":"L23 8TA",
    "wof:placetype":"postalcode"
},
  "geometry": {"coordinates":[-3.05589045279925,53.49535256438641],"type":"Point"}
}