{
  "type": "Feature",
  "properties": {
    "iso:country": "GB",
    "wof:name": "UB10 8TU",
    "wof:placetype": "postalcode"
  },
  "geometry": {"coordinates":[-0.438144,51.565095],"type":"Point"}
}
