{
  "type": "Feature",
  "properties": {
    "iso:country":"GB",
    "wof:name":"UB10 8TU",
    "wof:placetype":"postalcode"
},
  "geometry": {"coordinates":[-0.43814393814166,51.56509488473557],"type":"Point"}
}