{
  "type": "Feature",
  "properties": {
    "date:inception_lower": "1984-10-01",
    "date:inception_upper": "1984-10-01",
    "iso:country": "GB",
    "wof:name": "UB10 8TU",
    "wof:placetype": "postalcode"
  },
  "geometry": {"coordinates":[-0.438144,51.565095],"type":"Point"}
}
