{
  "type": "Feature",
  "properties": {
    "date:inception_lower": "1980-01-01",
    "date:inception_upper": "1980-01-01",
    "iso:country": "GB",
    "wof:name": "G82 1LQ",
    "wof:placetype": "postalcode"
  },
  "geometry": {"coordinates":[-4.570358,55.94438],"type":"Point"}
}
