{
  "type": "Feature",
  "properties": {
    "iso:country":"GB",
    "wof:name":"G82 1LQ",
    "wof:placetype":"postalcode"
},
  "geometry": {"coordinates":[-4.57043881871749,55.94439589300688],"type":"Point"}
}