{
  "type": "Feature",
  "properties": {
    "iso:country":"GB",
    "wof:name":"DL5 4UU",
    "wof:placetype":"postalcode"
},
  "geometry": {"coordinates":[-1.57906553228555,54.62911325572453],"type":"Point"}
}