{
  "type": "Feature",
  "properties": {
    "date:inception_lower": "1990-07-01",
    "date:inception_upper": "1990-07-01",
    "iso:country": "GB",
    "wof:name": "DL5 4UU",
    "wof:placetype": "postalcode"
  },
  "geometry": {"coordinates":[-1.579065,54.629113],"type":"Point"}
}
