{
  "type": "Feature",
  "properties": {
    "iso:country":"GB",
    "wof:name":"SA47 0NL",
    "wof:placetype":"postalcode"
},
  "geometry": {"coordinates":[-4.31142827307625,52.19317537769727],"type":"Point"}
}