{
  "type": "Feature",
  "properties": {
    "date:inception_lower": "1980-01-01",
    "date:inception_upper": "1980-01-01",
    "iso:country": "GB",
    "wof:name": "SA13 3PB",
    "wof:placetype": "postalcode"
  },
  "geometry": {"coordinates":[-3.638892,51.646899],"type":"Point"}
}
