{
  "type": "Feature",
  "properties": {
    "iso:country":"GB",
    "wof:name":"M44 6EJ",
    "wof:placetype":"postalcode"
},
  "geometry": {"coordinates":[-2.41280347287144,53.44971518786582],"type":"Point"}
}