{
  "type": "Feature",
  "properties": {
    "iso:country":"GB",
    "wof:name":"FY4 4HQ",
    "wof:placetype":"postalcode"
},
  "geometry": {"coordinates":[-3.02484690152525,53.80385112237516],"type":"Point"}
}