{
  "type": "Feature",
  "properties": {
    "iso:country": "GB",
    "wof:name": "MK14 5FN",
    "wof:placetype": "postalcode"
  },
  "geometry": {"coordinates":[-0.748897,52.080236],"type":"Point"}
}
