{
  "type": "Feature",
  "properties": {
    "date:inception_lower":"2009-08-01",
    "date:inception_upper":"2009-08-31",
    "iso:country":"GB",
    "wof:name":"MK14 5FN",
    "wof:placetype":"postalcode"
},
  "geometry": {"coordinates":[-0.748897,52.080236],"type":"Point"}
}