{
  "type": "Feature",
  "properties": {
    "date:inception_lower":"1980-01-01",
    "date:inception_upper":"1980-01-31",
    "iso:country":"GB",
    "wof:name":"DT6 6EP",
    "wof:placetype":"postalcode"
},
  "geometry": {"coordinates":[-2.848081,50.734902],"type":"Point"}
}