{
  "type": "Feature",
  "properties": {
    "iso:country":"GB",
    "wof:name":"DT6 6EP",
    "wof:placetype":"postalcode"
},
  "geometry": {"coordinates":[-2.84808151638652,50.73490241893921],"type":"Point"}
}