{
  "type": "Feature",
  "properties": {
    "date:inception_lower": "1980-01-01",
    "date:inception_upper": "1980-01-01",
    "iso:country": "GB",
    "wof:name": "BN25 2TB",
    "wof:placetype": "postalcode"
  },
  "geometry": {"coordinates":[0.07931,50.785582],"type":"Point"}
}
