{
  "type": "Feature",
  "properties": {
    "iso:country":"GB",
    "wof:name":"NE24 4AS",
    "wof:placetype":"postalcode"
},
  "geometry": {"coordinates":[-1.53017315062791,55.10831581761754],"type":"Point"}
}