{
  "type": "Feature",
  "properties": {
    "date:inception_lower":"1980-01-01",
    "date:inception_upper":"1980-01-31",
    "iso:country":"GB",
    "wof:name":"L20 6ET",
    "wof:placetype":"postalcode"
},
  "geometry": {"coordinates":[-2.979024,53.465112],"type":"Point"}
}