{
  "type": "Feature",
  "properties": {
    "iso:country":"GB",
    "wof:name":"L20 6ET",
    "wof:placetype":"postalcode"
},
  "geometry": {"coordinates":[-2.97902406767887,53.46511249720762],"type":"Point"}
}