{
  "type": "Feature",
  "properties": {
    "iso:country": "GB",
    "wof:name": "L20 6ET",
    "wof:placetype": "postalcode"
  },
  "geometry": {"coordinates":[-2.979024,53.465112],"type":"Point"}
}
