{
  "type": "Feature",
  "properties": {
    "iso:country": "GB",
    "wof:name": "CR2 7AN",
    "wof:placetype": "postalcode"
  },
  "geometry": {"coordinates":[-0.086072,51.35644],"type":"Point"}
}
