{
  "type": "Feature",
  "properties": {
    "iso:country":"GB",
    "wof:name":"CR2 7AN",
    "wof:placetype":"postalcode"
},
  "geometry": {"coordinates":[-0.08607205006937,51.35643990955253],"type":"Point"}
}