{
  "type": "Feature",
  "properties": {
    "iso:country":"GB",
    "wof:name":"DE1 1DS",
    "wof:placetype":"postalcode"
},
  "geometry": {"coordinates":[-1.49010249115313,52.9234509493371],"type":"Point"}
}