{
  "type": "Feature",
  "properties": {
    "iso:country": "GB",
    "wof:name": "SW13 0DP",
    "wof:placetype": "postalcode"
  },
  "geometry": {"coordinates":[-0.253501,51.46783],"type":"Point"}
}
