{
  "type": "Feature",
  "properties": {
    "iso:country": "GB",
    "wof:name": "TS4 3EP",
    "wof:placetype": "postalcode"
  },
  "geometry": {"coordinates":[-1.22471,54.551262],"type":"Point"}
}
