{
  "type": "Feature",
  "properties": {
    "iso:country":"GB",
    "wof:name":"TS4 3EP",
    "wof:placetype":"postalcode"
},
  "geometry": {"coordinates":[-1.22470967803297,54.55126170692925],"type":"Point"}
}