{
  "type": "Feature",
  "properties": {
    "iso:country":"GB",
    "wof:name":"PR4 0UU",
    "wof:placetype":"postalcode"
},
  "geometry": {"coordinates":[-2.82061621936944,53.83497606592675],"type":"Point"}
}