{
  "type": "Feature",
  "properties": {
    "iso:country":"GB",
    "wof:name":"NG14 6RG",
    "wof:placetype":"postalcode"
},
  "geometry": {"coordinates":[-1.09904210789716,53.04077134622783],"type":"Point"}
}