{
  "type": "Feature",
  "properties": {
    "iso:country":"GB",
    "wof:name":"LL21 9RP",
    "wof:placetype":"postalcode"
},
  "geometry": {"coordinates":[-3.38469148962726,52.98797800173869],"type":"Point"}
}