{
  "type": "Feature",
  "properties": {
    "iso:country":"GB",
    "wof:name":"SR4 8HF",
    "wof:placetype":"postalcode"
},
  "geometry": {"coordinates":[-1.4393099314926,54.89164946369778],"type":"Point"}
}