{
  "type": "Feature",
  "properties": {
    "date:inception_lower": "1980-01-01",
    "date:inception_upper": "1980-01-01",
    "iso:country": "GB",
    "wof:name": "SR4 8HF",
    "wof:placetype": "postalcode"
  },
  "geometry": {"coordinates":[-1.43931,54.891649],"type":"Point"}
}
