{
  "type": "Feature",
  "properties": {
    "date:inception_lower": "1980-01-01",
    "date:inception_upper": "1980-01-01",
    "iso:country": "GB",
    "wof:name": "NE1 4QT",
    "wof:placetype": "postalcode"
  },
  "geometry": {"coordinates":[-1.617588,54.975193],"type":"Point"}
}
