{
  "type": "Feature",
  "properties": {
    "date:inception_lower":"1980-01-01",
    "date:inception_upper":"1980-01-31",
    "iso:country":"GB",
    "wof:name":"HU10 6RA",
    "wof:placetype":"postalcode"
},
  "geometry": {"coordinates":[-0.422745,53.751159],"type":"Point"}
}