{
  "type": "Feature",
  "properties": {
    "iso:country":"GB",
    "wof:name":"HU10 6RA",
    "wof:placetype":"postalcode"
},
  "geometry": {"coordinates":[-0.42287644833316,53.75114923649903],"type":"Point"}
}