{
  "type": "Feature",
  "properties": {
    "iso:country": "GB",
    "wof:name": "HD6 1HT",
    "wof:placetype": "postalcode"
  },
  "geometry": {"coordinates":[-1.782216,53.69714],"type":"Point"}
}
