{
  "type": "Feature",
  "properties": {
    "iso:country":"GB",
    "wof:name":"HU18 1TS",
    "wof:placetype":"postalcode"
},
  "geometry": {"coordinates":[-0.16411682785834,53.90014837917253],"type":"Point"}
}