{
  "type": "Feature",
  "properties": {
    "iso:country": "GB",
    "wof:name": "HU18 1TS",
    "wof:placetype": "postalcode"
  },
  "geometry": {"coordinates":[-0.164117,53.900148],"type":"Point"}
}
