{
  "type": "Feature",
  "properties": {
    "date:inception_lower":"1991-09-01",
    "date:inception_upper":"1991-09-30",
    "iso:country":"GB",
    "wof:name":"HU18 1TS",
    "wof:placetype":"postalcode"
},
  "geometry": {"coordinates":[-0.164117,53.900148],"type":"Point"}
}