{
  "type": "Feature",
  "properties": {
    "iso:country":"GB",
    "wof:name":"SY3 0NX",
    "wof:placetype":"postalcode"
},
  "geometry": {"coordinates":[-2.77546848444819,52.67494797012723],"type":"Point"}
}