{
  "type": "Feature",
  "properties": {
    "iso:country": "GB",
    "wof:name": "SY3 0NX",
    "wof:placetype": "postalcode"
  },
  "geometry": {"coordinates":[-2.775468,52.674948],"type":"Point"}
}
