{
  "type": "Feature",
  "properties": {
    "iso:country":"GB",
    "wof:name":"LE2 4TE",
    "wof:placetype":"postalcode"
},
  "geometry": {"coordinates":[-1.06117411198642,52.59232967529101],"type":"Point"}
}