{
  "type": "Feature",
  "properties": {
    "iso:country": "GB",
    "wof:name": "LE2 4TE",
    "wof:placetype": "postalcode"
  },
  "geometry": {"coordinates":[-1.06118,52.592339],"type":"Point"}
}
