{
  "type": "Feature",
  "properties": {
    "iso:country": "GB",
    "wof:name": "B92 0JL",
    "wof:placetype": "postalcode"
  },
  "geometry": {"coordinates":[-1.714161,52.407248],"type":"Point"}
}
