{
  "type": "Feature",
  "properties": {
    "iso:country":"GB",
    "wof:name":"B92 0JL",
    "wof:placetype":"postalcode"
},
  "geometry": {"coordinates":[-1.71416079999759,52.40724776845286],"type":"Point"}
}