{
  "type": "Feature",
  "properties": {
    "iso:country":"GB",
    "wof:name":"ME17 3LU",
    "wof:placetype":"postalcode"
},
  "geometry": {"coordinates":[0.58756457708099,51.22842678333449],"type":"Point"}
}