{
  "type": "Feature",
  "properties": {
    "iso:country": "GB",
    "wof:name": "ME17 3LU",
    "wof:placetype": "postalcode"
  },
  "geometry": {"coordinates":[0.587565,51.228427],"type":"Point"}
}
