{
  "type": "Feature",
  "properties": {
    "date:inception_lower":"1980-01-01",
    "date:inception_upper":"1980-01-31",
    "iso:country":"GB",
    "wof:name":"SN10 1SH",
    "wof:placetype":"postalcode"
},
  "geometry": {"coordinates":[-2.078941,51.325448],"type":"Point"}
}