{
  "type": "Feature",
  "properties": {
    "iso:country": "GB",
    "wof:name": "SN10 1SH",
    "wof:placetype": "postalcode"
  },
  "geometry": {"coordinates":[-2.078941,51.325448],"type":"Point"}
}
