{
  "type": "Feature",
  "properties": {
    "iso:country":"GB",
    "wof:name":"SM3 9SG",
    "wof:placetype":"postalcode"
},
  "geometry": {"coordinates":[-0.21764363810365,51.37618622355929],"type":"Point"}
}