{
  "type": "Feature",
  "properties": {
    "iso:country": "GB",
    "wof:name": "CB24 3BA",
    "wof:placetype": "postalcode"
  },
  "geometry": {"coordinates":[0.065193,52.26039],"type":"Point"}
}
