{
  "type": "Feature",
  "properties": {
    "date:inception_lower": "2006-09-01",
    "date:inception_upper": "2006-09-01",
    "iso:country": "GB",
    "wof:name": "CB24 3BA",
    "wof:placetype": "postalcode"
  },
  "geometry": {"coordinates":[0.065193,52.26039],"type":"Point"}
}
