{
  "type": "Feature",
  "properties": {
    "iso:country":"GB",
    "wof:name":"CB24 3BA",
    "wof:placetype":"postalcode"
},
  "geometry": {"coordinates":[0.06519279479484,52.2603904976756],"type":"Point"}
}