{
  "type": "Feature",
  "properties": {
    "iso:country":"GB",
    "wof:name":"HP17 0TX",
    "wof:placetype":"postalcode"
},
  "geometry": {"coordinates":[-0.78058240589446,51.75642213011824],"type":"Point"}
}