{
  "type": "Feature",
  "properties": {
    "iso:country": "GB",
    "wof:name": "CB2 1GA",
    "wof:placetype": "postalcode"
  },
  "geometry": {"coordinates":[0.122687,52.198846],"type":"Point"}
}
