{
  "type": "Feature",
  "properties": {
    "date:inception_lower":"1997-06-01",
    "date:inception_upper":"1997-06-30",
    "iso:country":"GB",
    "wof:name":"CB2 1GA",
    "wof:placetype":"postalcode"
},
  "geometry": {"coordinates":[0.122687,52.198846],"type":"Point"}
}