{
  "type": "Feature",
  "properties": {
    "iso:country":"GB",
    "wof:name":"CB2 1GA",
    "wof:placetype":"postalcode"
},
  "geometry": {"coordinates":[0.12268650477917,52.19884624467644],"type":"Point"}
}