{
  "type": "Feature",
  "properties": {
    "iso:country":"GB",
    "wof:name":"DN22 8EE",
    "wof:placetype":"postalcode"
},
  "geometry": {"coordinates":[-0.93724998287076,53.26281307212015],"type":"Point"}
}