{
  "type": "Feature",
  "properties": {
    "iso:country": "GB",
    "wof:name": "CT21 5TH",
    "wof:placetype": "postalcode"
  },
  "geometry": {"coordinates":[1.114153,51.078554],"type":"Point"}
}
