{
  "type": "Feature",
  "properties": {
    "date:inception_lower": "2017-05-01",
    "date:inception_upper": "2017-05-01",
    "iso:country": "GB",
    "wof:name": "LS7 2BP",
    "wof:placetype": "postalcode"
  },
  "geometry": {"coordinates":[-1.53834,53.809895],"type":"Point"}
}
