{
  "type": "Feature",
  "properties": {
    "iso:country":"GB",
    "wof:name":"LS7 2BP",
    "wof:placetype":"postalcode"
},
  "geometry": {"coordinates":[-1.53845112239961,53.8104008157555],"type":"Point"}
}