{
  "type": "Feature",
  "properties": {
    "iso:country": "GB",
    "wof:name": "HU11 5JD",
    "wof:placetype": "postalcode"
  },
  "geometry": {"coordinates":[-0.286632,53.862418],"type":"Point"}
}
