{
  "type": "Feature",
  "properties": {
    "date:inception_lower": "1993-01-01",
    "date:inception_upper": "1993-01-01",
    "iso:country": "GB",
    "wof:name": "HU11 5JD",
    "wof:placetype": "postalcode"
  },
  "geometry": {"coordinates":[-0.286359,53.862396],"type":"Point"}
}
