{
  "type": "Feature",
  "properties": {
    "date:inception_lower": "1995-12-01",
    "date:inception_upper": "1995-12-01",
    "iso:country": "GB",
    "wof:name": "TQ12 3GP",
    "wof:placetype": "postalcode"
  },
  "geometry": {"coordinates":[-3.606394,50.57409],"type":"Point"}
}
