{
  "type": "Feature",
  "properties": {
    "iso:country": "GB",
    "wof:name": "LS27 7NN",
    "wof:placetype": "postalcode"
  },
  "geometry": {"coordinates":[-1.629398,53.764758],"type":"Point"}
}
