{
  "type": "Feature",
  "properties": {
    "iso:country":"GB",
    "wof:name":"SG5 2WA",
    "wof:placetype":"postalcode"
},
  "geometry": {"coordinates":[-0.2867840920704,51.95774047677013],"type":"Point"}
}