{
  "type": "Feature",
  "properties": {
    "date:inception_lower":"2001-06-01",
    "date:inception_upper":"2001-06-30",
    "iso:country":"GB",
    "wof:name":"SG5 2WA",
    "wof:placetype":"postalcode"
},
  "geometry": {"coordinates":[-0.286734,51.957622],"type":"Point"}
}