{
  "type": "Feature",
  "properties": {
    "iso:country": "GB",
    "wof:name": "WA3 5BZ",
    "wof:placetype": "postalcode"
  },
  "geometry": {"coordinates":[-2.460424,53.425506],"type":"Point"}
}
