{
  "type": "Feature",
  "properties": {
    "iso:country":"GB",
    "wof:name":"WA3 5BZ",
    "wof:placetype":"postalcode"
},
  "geometry": {"coordinates":[-2.46042419467977,53.42550558337432],"type":"Point"}
}