{
  "type": "Feature",
  "properties": {
    "iso:country":"GB",
    "wof:name":"M17 1PB",
    "wof:placetype":"postalcode"
},
  "geometry": {"coordinates":[-2.31930765877423,53.47118775597239],"type":"Point"}
}