{
  "type": "Feature",
  "properties": {
    "date:inception_lower":"1980-01-01",
    "date:inception_upper":"1980-01-31",
    "iso:country":"GB",
    "wof:name":"M17 1PB",
    "wof:placetype":"postalcode"
},
  "geometry": {"coordinates":[-2.318695,53.47188],"type":"Point"}
}