{
  "type": "Feature",
  "properties": {
    "date:inception_lower":"2012-02-01",
    "date:inception_upper":"2012-02-29",
    "iso:country":"GB",
    "wof:name":"SS15 5UP",
    "wof:placetype":"postalcode"
},
  "geometry": {"coordinates":[0.423057,51.571184],"type":"Point"}
}