{
  "type": "Feature",
  "properties": {
    "iso:country":"GB",
    "wof:name":"SS15 5UP",
    "wof:placetype":"postalcode"
},
  "geometry": {"coordinates":[0.42337721659617,51.57154269294089],"type":"Point"}
}