{
  "type": "Feature",
  "properties": {
    "iso:country":"GB",
    "wof:name":"TR10 8FJ",
    "wof:placetype":"postalcode"
},
  "geometry": {"coordinates":[-5.10543947670937,50.17236053031461],"type":"Point"}
}