{
  "type": "Feature",
  "properties": {
    "date:inception_lower": "2010-07-01",
    "date:inception_upper": "2010-07-01",
    "iso:country": "GB",
    "wof:name": "TR10 8FJ",
    "wof:placetype": "postalcode"
  },
  "geometry": {"coordinates":[-5.105459,50.172565],"type":"Point"}
}
