{
  "type": "Feature",
  "properties": {
    "date:inception_lower":"2010-07-01",
    "date:inception_upper":"2010-07-31",
    "iso:country":"GB",
    "wof:name":"TR10 8FJ",
    "wof:placetype":"postalcode"
},
  "geometry": {"coordinates":[-5.105439,50.172361],"type":"Point"}
}