{
  "type": "Feature",
  "properties": {
    "iso:country":"GB",
    "wof:name":"TA3 6QU",
    "wof:placetype":"postalcode"
},
  "geometry": {"coordinates":[-2.91393793722284,51.01489484384649],"type":"Point"}
}