{
  "type": "Feature",
  "properties": {
    "iso:country": "GB",
    "wof:name": "TA3 6QU",
    "wof:placetype": "postalcode"
  },
  "geometry": {"coordinates":[-2.913915,51.01487],"type":"Point"}
}
