{
  "type": "Feature",
  "properties": {
    "date:inception_lower":"1980-01-01",
    "date:inception_upper":"1980-01-31",
    "iso:country":"GB",
    "wof:name":"TA3 6QU",
    "wof:placetype":"postalcode"
},
  "geometry": {"coordinates":[-2.913938,51.014895],"type":"Point"}
}