{
  "type": "Feature",
  "properties": {
    "iso:country":"GB",
    "wof:name":"HS1 2SX",
    "wof:placetype":"postalcode"
},
  "geometry": {"coordinates":[-6.36192674132527,58.2077489533585],"type":"Point"}
}