{
  "type": "Feature",
  "properties": {
    "date:inception_lower": "1995-07-01",
    "date:inception_upper": "1995-07-01",
    "iso:country": "GB",
    "wof:name": "HS1 2SX",
    "wof:placetype": "postalcode"
  },
  "geometry": {"coordinates":[-6.361927,58.207749],"type":"Point"}
}
