{
  "type": "Feature",
  "properties": {
    "iso:country":"GB",
    "wof:name":"RH14 0PU",
    "wof:placetype":"postalcode"
},
  "geometry": {"coordinates":[-0.56711089339916,51.0705061903418],"type":"Point"}
}