{
  "type": "Feature",
  "properties": {
    "date:inception_lower":"1980-01-01",
    "date:inception_upper":"1980-01-31",
    "iso:country":"GB",
    "wof:name":"CA13 9XW",
    "wof:placetype":"postalcode"
},
  "geometry": {"coordinates":[-3.292807,54.661881],"type":"Point"}
}