{
  "type": "Feature",
  "properties": {
    "iso:country": "GB",
    "wof:name": "CA13 9XW",
    "wof:placetype": "postalcode"
  },
  "geometry": {"coordinates":[-3.292807,54.661881],"type":"Point"}
}
