{
  "type": "Feature",
  "properties": {
    "date:inception_lower":"2012-02-01",
    "date:inception_upper":"2012-02-29",
    "iso:country":"GB",
    "wof:name":"LD1 5DF",
    "wof:placetype":"postalcode"
},
  "geometry": {"coordinates":[-3.369761,52.252035],"type":"Point"}
}