{
  "type": "Feature",
  "properties": {
    "iso:country":"GB",
    "wof:name":"LD1 5DF",
    "wof:placetype":"postalcode"
},
  "geometry": {"coordinates":[-3.3698193350646,52.25175419400193],"type":"Point"}
}