{
  "type": "Feature",
  "properties": {
    "date:inception_lower": "2012-02-01",
    "date:inception_upper": "2012-02-01",
    "iso:country": "GB",
    "wof:name": "LD1 5DF",
    "wof:placetype": "postalcode"
  },
  "geometry": {"coordinates":[-3.369826,52.251765],"type":"Point"}
}
