{
  "type": "Feature",
  "properties": {
    "date:inception_lower": "1980-01-01",
    "date:inception_upper": "1980-01-01",
    "iso:country": "GB",
    "wof:name": "HG4 1HH",
    "wof:placetype": "postalcode"
  },
  "geometry": {"coordinates":[-1.516456,54.14155],"type":"Point"}
}
