{
  "type": "Feature",
  "properties": {
    "iso:country":"GB",
    "wof:name":"HG4 1HH",
    "wof:placetype":"postalcode"
},
  "geometry": {"coordinates":[-1.51645584528529,54.14155004465852],"type":"Point"}
}