{
  "type": "Feature",
  "properties": {
    "iso:country":"GB",
    "wof:name":"BD23 1TD",
    "wof:placetype":"postalcode"
},
  "geometry": {"coordinates":[-2.03593022411738,53.95832313562486],"type":"Point"}
}