{
  "type": "Feature",
  "properties": {
    "date:inception_lower": "1980-01-01",
    "date:inception_upper": "1980-01-01",
    "iso:country": "GB",
    "wof:name": "BD23 1TD",
    "wof:placetype": "postalcode"
  },
  "geometry": {"coordinates":[-2.03593,53.958323],"type":"Point"}
}
