{
  "type": "Feature",
  "properties": {
    "iso:country":"GB",
    "wof:name":"LS18 5RU",
    "wof:placetype":"postalcode"
},
  "geometry": {"coordinates":[-1.65327339062654,53.84745829443622],"type":"Point"}
}