{
  "type": "Feature",
  "properties": {
    "date:inception_lower": "1980-01-01",
    "date:inception_upper": "1980-01-01",
    "iso:country": "GB",
    "wof:name": "LS18 5RU",
    "wof:placetype": "postalcode"
  },
  "geometry": {"coordinates":[-1.653273,53.847458],"type":"Point"}
}
