{
  "type": "Feature",
  "properties": {
    "iso:country":"GB",
    "wof:name":"S5 6UR",
    "wof:placetype":"postalcode"
},
  "geometry": {"coordinates":[-1.44847671781627,53.41079400190915],"type":"Point"}
}