{
  "type": "Feature",
  "properties": {
    "iso:country":"GB",
    "wof:name":"AB15 9PP",
    "wof:placetype":"postalcode"
},
  "geometry": {"coordinates":[-2.17958867469168,57.12291580755764],"type":"Point"}
}