{
  "type": "Feature",
  "properties": {
    "date:inception_lower": "2014-06-01",
    "date:inception_upper": "2014-06-01",
    "iso:country": "GB",
    "wof:name": "AB15 9PP",
    "wof:placetype": "postalcode"
  },
  "geometry": {"coordinates":[-2.17958,57.123053],"type":"Point"}
}
