{
  "type": "Feature",
  "properties": {
    "iso:country":"GB",
    "wof:name":"DG2 0BB",
    "wof:placetype":"postalcode"
},
  "geometry": {"coordinates":[-3.61962300725916,55.07453567312614],"type":"Point"}
}