{
  "type": "Feature",
  "properties": {
    "date:inception_lower": "2023-05-01",
    "date:inception_upper": "2023-05-01",
    "iso:country": "GB",
    "wof:name": "NN2 8GT",
    "wof:placetype": "postalcode"
  },
  "geometry": {"coordinates":[-0.915966,52.277851],"type":"Point"}
}
