{
  "type": "Feature",
  "properties": {
    "iso:country":"GB",
    "wof:name":"TR19 6PT",
    "wof:placetype":"postalcode"
},
  "geometry": {"coordinates":[-5.53684834519044,50.08564489579323],"type":"Point"}
}