{
  "type": "Feature",
  "properties": {
    "iso:country": "GB",
    "wof:name": "TR19 6PT",
    "wof:placetype": "postalcode"
  },
  "geometry": {"coordinates":[-5.536944,50.085616],"type":"Point"}
}
