{
  "type": "Feature",
  "properties": {
    "date:inception_lower":"2001-06-01",
    "date:inception_upper":"2001-06-30",
    "iso:country":"GB",
    "wof:name":"SL4 5BL",
    "wof:placetype":"postalcode"
},
  "geometry": {"coordinates":[-0.622825,51.479852],"type":"Point"}
}