{
  "type": "Feature",
  "properties": {
    "iso:country":"GB",
    "wof:name":"SL4 5BL",
    "wof:placetype":"postalcode"
},
  "geometry": {"coordinates":[-0.62282511924681,51.47985215773991],"type":"Point"}
}