{
  "type": "Feature",
  "properties": {
    "date:inception_lower": "1980-01-01",
    "date:inception_upper": "1980-01-01",
    "iso:country": "GB",
    "wof:name": "SY21 8TT",
    "wof:placetype": "postalcode"
  },
  "geometry": {"coordinates":[-3.113153,52.615466],"type":"Point"}
}
