{
  "type": "Feature",
  "properties": {
    "iso:country":"GB",
    "wof:name":"WA12 9LB",
    "wof:placetype":"postalcode"
},
  "geometry": {"coordinates":[-2.65483828657857,53.45268710196667],"type":"Point"}
}