{
  "type": "Feature",
  "properties": {
    "iso:country":"GB",
    "wof:name":"NN1 2BT",
    "wof:placetype":"postalcode"
},
  "geometry": {"coordinates":[-0.89074527207539,52.23883386619425],"type":"Point"}
}