{
  "type": "Feature",
  "properties": {
    "iso:country":"GB",
    "wof:name":"NE5 3UA",
    "wof:placetype":"postalcode"
},
  "geometry": {"coordinates":[-1.67227788271155,55.00105495328933],"type":"Point"}
}