{
  "type": "Feature",
  "properties": {
    "date:inception_lower":"1980-01-01",
    "date:inception_upper":"1980-01-31",
    "iso:country":"GB",
    "wof:name":"NE5 3UA",
    "wof:placetype":"postalcode"
},
  "geometry": {"coordinates":[-1.672278,55.001055],"type":"Point"}
}