{
  "type": "Feature",
  "properties": {
    "iso:country":"GB",
    "wof:name":"NG34 7FL",
    "wof:placetype":"postalcode"
},
  "geometry": {"coordinates":[-0.39534359473024,52.99463162201137],"type":"Point"}
}