{
  "type": "Feature",
  "properties": {
    "date:inception_lower": "1994-12-01",
    "date:inception_upper": "1994-12-01",
    "iso:country": "GB",
    "wof:name": "NG34 7FL",
    "wof:placetype": "postalcode"
  },
  "geometry": {"coordinates":[-0.395344,52.994632],"type":"Point"}
}
