{
  "type": "Feature",
  "properties": {
    "iso:country": "GB",
    "wof:name": "NG34 7FL",
    "wof:placetype": "postalcode"
  },
  "geometry": {"coordinates":[-0.395344,52.994632],"type":"Point"}
}
