{
  "type": "Feature",
  "properties": {
    "iso:country": "GB",
    "wof:name": "NR19 1LU",
    "wof:placetype": "postalcode"
  },
  "geometry": {"coordinates":[0.945034,52.662254],"type":"Point"}
}
