{
  "type": "Feature",
  "properties": {
    "iso:country": "GB",
    "wof:name": "TA19 9PX",
    "wof:placetype": "postalcode"
  },
  "geometry": {"coordinates":[-2.945696,50.93058],"type":"Point"}
}
