{
  "type": "Feature",
  "properties": {
    "iso:country":"GB",
    "wof:name":"RM12 5DP",
    "wof:placetype":"postalcode"
},
  "geometry": {"coordinates":[0.19352960871604,51.54699134181785],"type":"Point"}
}