{
  "type": "Feature",
  "properties": {
    "iso:country":"GB",
    "wof:name":"BR1 3RH",
    "wof:placetype":"postalcode"
},
  "geometry": {"coordinates":[0.01020086447265,51.41182403513027],"type":"Point"}
}