{
  "type": "Feature",
  "properties": {
    "iso:country": "GB",
    "wof:name": "TS17 5AA",
    "wof:placetype": "postalcode"
  },
  "geometry": {"coordinates":[-1.322326,54.52231],"type":"Point"}
}
