{
  "type": "Feature",
  "properties": {
    "date:inception_lower": "1980-01-01",
    "date:inception_upper": "1980-01-01",
    "iso:country": "GB",
    "wof:name": "TA6 3NU",
    "wof:placetype": "postalcode"
  },
  "geometry": {"coordinates":[-2.999266,51.125527],"type":"Point"}
}
