{
  "type": "Feature",
  "properties": {
    "date:inception_lower":"1990-07-01",
    "date:inception_upper":"1990-07-31",
    "iso:country":"GB",
    "wof:name":"LN11 8SN",
    "wof:placetype":"postalcode"
},
  "geometry": {"coordinates":[0.008592,53.361903],"type":"Point"}
}