{
  "type": "Feature",
  "properties": {
    "date:inception_lower":"2004-03-01",
    "date:inception_upper":"2004-03-31",
    "iso:country":"GB",
    "wof:name":"SG17 5FB",
    "wof:placetype":"postalcode"
},
  "geometry": {"coordinates":[-0.320797,52.036745],"type":"Point"}
}