{
  "type": "Feature",
  "properties": {
    "date:inception_lower": "2004-03-01",
    "date:inception_upper": "2004-03-01",
    "iso:country": "GB",
    "wof:name": "SG17 5FB",
    "wof:placetype": "postalcode"
  },
  "geometry": {"coordinates":[-0.320772,52.036774],"type":"Point"}
}
