{
  "type": "Feature",
  "properties": {
    "iso:country": "GB",
    "wof:name": "AB15 7TX",
    "wof:placetype": "postalcode"
  },
  "geometry": {"coordinates":[-2.148843,57.12849],"type":"Point"}
}
