{
  "type": "Feature",
  "properties": {
    "date:inception_lower": "1996-06-01",
    "date:inception_upper": "1996-06-01",
    "iso:country": "GB",
    "wof:name": "AB42 1EJ",
    "wof:placetype": "postalcode"
  },
  "geometry": {"coordinates":[-1.778947,57.50382],"type":"Point"}
}
