{
  "type": "Feature",
  "properties": {
    "iso:country": "GB",
    "wof:name": "AB42 1EJ",
    "wof:placetype": "postalcode"
  },
  "geometry": {"coordinates":[-1.778947,57.50382],"type":"Point"}
}
