{
  "type": "Feature",
  "properties": {
    "iso:country":"GB",
    "wof:name":"AB42 1EJ",
    "wof:placetype":"postalcode"
},
  "geometry": {"coordinates":[-1.77894709858445,57.50381984113281],"type":"Point"}
}