{
  "type": "Feature",
  "properties": {
    "iso:country": "GB",
    "wof:name": "HD1 5HT",
    "wof:placetype": "postalcode"
  },
  "geometry": {"coordinates":[-1.78942,53.658585],"type":"Point"}
}
