{
  "type": "Feature",
  "properties": {
    "iso:country": "GB",
    "wof:name": "DL11 6EL",
    "wof:placetype": "postalcode"
  },
  "geometry": {"coordinates":[-1.995473,54.417782],"type":"Point"}
}
