{
  "type": "Feature",
  "properties": {
    "iso:country": "GB",
    "wof:name": "TS22 5FN",
    "wof:placetype": "postalcode"
  },
  "geometry": {"coordinates":[-1.326492,54.640035],"type":"Point"}
}
