{
  "type": "Feature",
  "properties": {
    "iso:country":"GB",
    "wof:name":"NG11 0DF",
    "wof:placetype":"postalcode"
},
  "geometry": {"coordinates":[-1.24061496301504,52.85284549898572],"type":"Point"}
}