{
  "type": "Feature",
  "properties": {
    "iso:country": "GB",
    "wof:name": "NG11 0DF",
    "wof:placetype": "postalcode"
  },
  "geometry": {"coordinates":[-1.240615,52.852845],"type":"Point"}
}
