{
  "type": "Feature",
  "properties": {
    "iso:country":"GB",
    "wof:name":"G33 2JP",
    "wof:placetype":"postalcode"
},
  "geometry": {"coordinates":[-4.1918708133655,55.86488947953119],"type":"Point"}
}