{
  "type": "Feature",
  "properties": {
    "iso:country":"GB",
    "wof:name":"LS16 6NJ",
    "wof:placetype":"postalcode"
},
  "geometry": {"coordinates":[-1.61048007363268,53.84646426813931],"type":"Point"}
}