{
  "type": "Feature",
  "properties": {
    "date:inception_lower": "1980-01-01",
    "date:inception_upper": "1980-01-01",
    "iso:country": "GB",
    "wof:name": "GU7 1SP",
    "wof:placetype": "postalcode"
  },
  "geometry": {"coordinates":[-0.612854,51.174122],"type":"Point"}
}
