{
  "type": "Feature",
  "properties": {
    "date:inception_lower":"2012-06-01",
    "date:inception_upper":"2012-06-30",
    "iso:country":"GB",
    "wof:name":"RH13 9AD",
    "wof:placetype":"postalcode"
},
  "geometry": {"coordinates":[-0.347379,51.039404],"type":"Point"}
}