{
  "type": "Feature",
  "properties": {
    "iso:country":"GB",
    "wof:name":"RH13 9AD",
    "wof:placetype":"postalcode"
},
  "geometry": {"coordinates":[-0.34737889630131,51.03940433467052],"type":"Point"}
}