{
  "type": "Feature",
  "properties": {
    "iso:country": "GB",
    "wof:name": "RH13 9AD",
    "wof:placetype": "postalcode"
  },
  "geometry": {"coordinates":[-0.347379,51.039404],"type":"Point"}
}
