{
  "type": "Feature",
  "properties": {
    "iso:country": "GB",
    "wof:name": "EN6 3EZ",
    "wof:placetype": "postalcode"
  },
  "geometry": {"coordinates":[-0.205518,51.698028],"type":"Point"}
}
