{
  "type": "Feature",
  "properties": {
    "iso:country":"GB",
    "wof:name":"NG20 0JH",
    "wof:placetype":"postalcode"
},
  "geometry": {"coordinates":[-1.16350958275537,53.2060327946272],"type":"Point"}
}