{
  "type": "Feature",
  "properties": {
    "iso:country":"GB",
    "wof:name":"PL27 7PU",
    "wof:placetype":"postalcode"
},
  "geometry": {"coordinates":[-4.83692892264539,50.51153011548288],"type":"Point"}
}