{
  "type": "Feature",
  "properties": {
    "iso:country":"GB",
    "wof:name":"CV2 2TL",
    "wof:placetype":"postalcode"
},
  "geometry": {"coordinates":[-1.44504517970679,52.43680406978687],"type":"Point"}
}