{
  "type": "Feature",
  "properties": {
    "iso:country": "GB",
    "wof:name": "CV2 2TL",
    "wof:placetype": "postalcode"
  },
  "geometry": {"coordinates":[-1.445045,52.436804],"type":"Point"}
}
