{
  "type": "Feature",
  "properties": {
    "iso:country":"GB",
    "wof:name":"DD8 1LY",
    "wof:placetype":"postalcode"
},
  "geometry": {"coordinates":[-2.89195558799188,56.63829276810336],"type":"Point"}
}