{
  "type": "Feature",
  "properties": {
    "date:inception_lower": "2018-07-01",
    "date:inception_upper": "2018-07-01",
    "iso:country": "GB",
    "wof:name": "BN16 4PY",
    "wof:placetype": "postalcode"
  },
  "geometry": {"coordinates":[-0.472815,50.82054],"type":"Point"}
}
