{
  "type": "Feature",
  "properties": {
    "iso:country": "GB",
    "wof:name": "BN16 4PY",
    "wof:placetype": "postalcode"
  },
  "geometry": {"coordinates":[-0.472929,50.820542],"type":"Point"}
}
