{
  "type": "Feature",
  "properties": {
    "iso:country":"GB",
    "wof:name":"CO5 8UQ",
    "wof:placetype":"postalcode"
},
  "geometry": {"coordinates":[0.91350324314722,51.77774702358879],"type":"Point"}
}