{
  "type": "Feature",
  "properties": {
    "iso:country": "GB",
    "wof:name": "TN39 5HH",
    "wof:placetype": "postalcode"
  },
  "geometry": {"coordinates":[0.459738,50.857407],"type":"Point"}
}
