{
  "type": "Feature",
  "properties": {
    "date:inception_lower": "1995-12-01",
    "date:inception_upper": "1995-12-01",
    "iso:country": "GB",
    "wof:name": "BR3 5EL",
    "wof:placetype": "postalcode"
  },
  "geometry": {"coordinates":[-0.021317,51.410922],"type":"Point"}
}
