{
  "type": "Feature",
  "properties": {
    "iso:country":"GB",
    "wof:name":"S41 7DL",
    "wof:placetype":"postalcode"
},
  "geometry": {"coordinates":[-1.43158671690653,53.2511368927585],"type":"Point"}
}