{
  "type": "Feature",
  "properties": {
    "iso:country":"GB",
    "wof:name":"E15 3BW",
    "wof:placetype":"postalcode"
},
  "geometry": {"coordinates":[0.00656758237425,51.52843221739317],"type":"Point"}
}