{
  "type": "Feature",
  "properties": {
    "date:inception_lower": "1980-01-01",
    "date:inception_upper": "1980-01-01",
    "iso:country": "GB",
    "wof:name": "SP8 5ER",
    "wof:placetype": "postalcode"
  },
  "geometry": {"coordinates":[-2.333079,51.004507],"type":"Point"}
}
