{
  "type": "Feature",
  "properties": {
    "iso:country":"GB",
    "wof:name":"SP8 5ER",
    "wof:placetype":"postalcode"
},
  "geometry": {"coordinates":[-2.33307926676447,51.00450724544588],"type":"Point"}
}