{
  "type": "Feature",
  "properties": {
    "date:inception_lower":"1998-06-01",
    "date:inception_upper":"1998-06-30",
    "iso:country":"GB",
    "wof:name":"OX4 2UW",
    "wof:placetype":"postalcode"
},
  "geometry": {"coordinates":[-1.210471,51.734991],"type":"Point"}
}