{
  "type": "Feature",
  "properties": {
    "iso:country":"GB",
    "wof:name":"OX4 2UW",
    "wof:placetype":"postalcode"
},
  "geometry": {"coordinates":[-1.21047095263284,51.73499123114983],"type":"Point"}
}