{
  "type": "Feature",
  "properties": {
    "iso:country":"GB",
    "wof:name":"SY14 8HH",
    "wof:placetype":"postalcode"
},
  "geometry": {"coordinates":[-2.66087431691728,53.07148701643421],"type":"Point"}
}