{
  "type": "Feature",
  "properties": {
    "iso:country":"GB",
    "wof:name":"PL30 4LG",
    "wof:placetype":"postalcode"
},
  "geometry": {"coordinates":[-4.6648370735321,50.54216135031252],"type":"Point"}
}