{
  "type": "Feature",
  "properties": {
    "iso:country":"GB",
    "wof:name":"BD21 2SY",
    "wof:placetype":"postalcode"
},
  "geometry": {"coordinates":[-1.90915145605664,53.87274873725895],"type":"Point"}
}