{
  "type": "Feature",
  "properties": {
    "iso:country":"GB",
    "wof:name":"PO30 3DU",
    "wof:placetype":"postalcode"
},
  "geometry": {"coordinates":[-1.31786279207143,50.68221772513348],"type":"Point"}
}