{
  "type": "Feature",
  "properties": {
    "iso:country": "GB",
    "wof:name": "PO30 3DU",
    "wof:placetype": "postalcode"
  },
  "geometry": {"coordinates":[-1.317863,50.682218],"type":"Point"}
}
