{
  "type": "Feature",
  "properties": {
    "iso:country":"GB",
    "wof:name":"PA16 9DP",
    "wof:placetype":"postalcode"
},
  "geometry": {"coordinates":[-4.78496369804232,55.94185188897399],"type":"Point"}
}