{
  "type": "Feature",
  "properties": {
    "iso:country": "GB",
    "wof:name": "DE73 6AF",
    "wof:placetype": "postalcode"
  },
  "geometry": {"coordinates":[-1.432755,52.861002],"type":"Point"}
}
