{
  "type": "Feature",
  "properties": {
    "iso:country":"GB",
    "wof:name":"TA9 4LG",
    "wof:placetype":"postalcode"
},
  "geometry": {"coordinates":[-2.92992798303119,51.2202697866233],"type":"Point"}
}