{
  "type": "Feature",
  "properties": {
    "iso:country":"GB",
    "wof:name":"BS31 2PN",
    "wof:placetype":"postalcode"
},
  "geometry": {"coordinates":[-2.50408376196176,51.40874969698684],"type":"Point"}
}