{
  "type": "Feature",
  "properties": {
    "date:inception_lower": "1980-01-01",
    "date:inception_upper": "1980-01-01",
    "iso:country": "GB",
    "wof:name": "NE16 4PZ",
    "wof:placetype": "postalcode"
  },
  "geometry": {"coordinates":[-1.674812,54.936954],"type":"Point"}
}
