{
  "type": "Feature",
  "properties": {
    "date:inception_lower":"2010-08-01",
    "date:inception_upper":"2010-08-31",
    "iso:country":"GB",
    "wof:name":"TW18 4NJ",
    "wof:placetype":"postalcode"
},
  "geometry": {"coordinates":[-0.500557,51.432852],"type":"Point"}
}