{
  "type": "Feature",
  "properties": {
    "date:inception_lower": "2012-05-01",
    "date:inception_upper": "2012-05-01",
    "iso:country": "GB",
    "wof:name": "TN22 4AS",
    "wof:placetype": "postalcode"
  },
  "geometry": {"coordinates":[0.133345,50.990867],"type":"Point"}
}
