{
  "type": "Feature",
  "properties": {
    "iso:country":"GB",
    "wof:name":"TN22 4AS",
    "wof:placetype":"postalcode"
},
  "geometry": {"coordinates":[0.13334487364525,50.99086662674476],"type":"Point"}
}