{
  "type": "Feature",
  "properties": {
    "iso:country":"GB",
    "wof:name":"S11 7JB",
    "wof:placetype":"postalcode"
},
  "geometry": {"coordinates":[-1.51296472489402,53.36241859099992],"type":"Point"}
}