{
  "type": "Feature",
  "properties": {
    "iso:country": "GB",
    "wof:name": "S11 7JB",
    "wof:placetype": "postalcode"
  },
  "geometry": {"coordinates":[-1.512963,53.362454],"type":"Point"}
}
