{
  "type": "Feature",
  "properties": {
    "iso:country":"GB",
    "wof:name":"NG10 3AL",
    "wof:placetype":"postalcode"
},
  "geometry": {"coordinates":[-1.29853269663218,52.87946012984423],"type":"Point"}
}