{
  "type": "Feature",
  "properties": {
    "date:inception_lower": "1980-01-01",
    "date:inception_upper": "1980-01-01",
    "iso:country": "GB",
    "wof:name": "NG10 3AL",
    "wof:placetype": "postalcode"
  },
  "geometry": {"coordinates":[-1.298412,52.879236],"type":"Point"}
}
