{
  "type": "Feature",
  "properties": {
    "iso:country":"GB",
    "wof:name":"LL21 9NB",
    "wof:placetype":"postalcode"
},
  "geometry": {"coordinates":[-3.31300711489315,53.0140618474556],"type":"Point"}
}