{
  "type": "Feature",
  "properties": {
    "iso:country":"GB",
    "wof:name":"PO12 2RJ",
    "wof:placetype":"postalcode"
},
  "geometry": {"coordinates":[-1.15820469294765,50.79263161937819],"type":"Point"}
}