{
  "type": "Feature",
  "properties": {
    "iso:country":"GB",
    "wof:name":"RG12 9NG",
    "wof:placetype":"postalcode"
},
  "geometry": {"coordinates":[-0.73578026103187,51.4033699473294],"type":"Point"}
}