{
  "type": "Feature",
  "properties": {
    "date:inception_lower":"2014-01-01",
    "date:inception_upper":"2014-01-31",
    "iso:country":"GB",
    "wof:name":"HU13 0DH",
    "wof:placetype":"postalcode"
},
  "geometry": {"coordinates":[-0.461148,53.723574],"type":"Point"}
}