{
  "type": "Feature",
  "properties": {
    "iso:country": "GB",
    "wof:name": "HU13 0DH",
    "wof:placetype": "postalcode"
  },
  "geometry": {"coordinates":[-0.461148,53.723574],"type":"Point"}
}
