{
  "type": "Feature",
  "properties": {
    "iso:country":"GB",
    "wof:name":"HU13 0DH",
    "wof:placetype":"postalcode"
},
  "geometry": {"coordinates":[-0.461148332181,53.72357399671539],"type":"Point"}
}