{
  "type": "Feature",
  "properties": {
    "iso:country": "GB",
    "wof:name": "NR34 8JL",
    "wof:placetype": "postalcode"
  },
  "geometry": {"coordinates":[1.498699,52.434762],"type":"Point"}
}
