{
  "type": "Feature",
  "properties": {
    "iso:country":"GB",
    "wof:name":"NR34 8JL",
    "wof:placetype":"postalcode"
},
  "geometry": {"coordinates":[1.49869930800865,52.43476164674178],"type":"Point"}
}