{
  "type": "Feature",
  "properties": {
    "iso:country":"GB",
    "wof:name":"TS4 3NQ",
    "wof:placetype":"postalcode"
},
  "geometry": {"coordinates":[-1.21662729705444,54.54381327680774],"type":"Point"}
}