{
  "type": "Feature",
  "properties": {
    "date:inception_lower":"1980-01-01",
    "date:inception_upper":"1980-01-31",
    "iso:country":"GB",
    "wof:name":"TS4 3NQ",
    "wof:placetype":"postalcode"
},
  "geometry": {"coordinates":[-1.216627,54.543813],"type":"Point"}
}