{
  "type": "Feature",
  "properties": {
    "date:inception_lower": "1980-01-01",
    "date:inception_upper": "1980-01-01",
    "iso:country": "GB",
    "wof:name": "BD20 5DA",
    "wof:placetype": "postalcode"
  },
  "geometry": {"coordinates":[-1.893846,53.880699],"type":"Point"}
}
