{
  "type": "Feature",
  "properties": {
    "iso:country":"GB",
    "wof:name":"BD20 5DA",
    "wof:placetype":"postalcode"
},
  "geometry": {"coordinates":[-1.89384648217948,53.88069943855058],"type":"Point"}
}