{
  "type": "Feature",
  "properties": {
    "iso:country": "GB",
    "wof:name": "BD20 5DA",
    "wof:placetype": "postalcode"
  },
  "geometry": {"coordinates":[-1.893846,53.880699],"type":"Point"}
}
