{
  "type": "Feature",
  "properties": {
    "iso:country":"GB",
    "wof:name":"PE21 0NY",
    "wof:placetype":"postalcode"
},
  "geometry": {"coordinates":[-0.00229699139582,52.97266442854205],"type":"Point"}
}