{
  "type": "Feature",
  "properties": {
    "date:inception_lower": "2021-11-01",
    "date:inception_upper": "2021-11-01",
    "iso:country": "GB",
    "wof:name": "NP18 2EN",
    "wof:placetype": "postalcode"
  },
  "geometry": {"coordinates":[-2.913771,51.589677],"type":"Point"}
}
