{
  "type": "Feature",
  "properties": {
    "date:inception_lower": "1980-01-01",
    "date:inception_upper": "1980-01-01",
    "iso:country": "GB",
    "wof:name": "CM17 0HG",
    "wof:placetype": "postalcode"
  },
  "geometry": {"coordinates":[0.136386,51.79198],"type":"Point"}
}
