{
  "type": "Feature",
  "properties": {
    "iso:country":"GB",
    "wof:name":"CM17 0HG",
    "wof:placetype":"postalcode"
},
  "geometry": {"coordinates":[0.13638617885776,51.7919803040681],"type":"Point"}
}