{
  "type": "Feature",
  "properties": {
    "iso:country":"GB",
    "wof:name":"BD10 8AB",
    "wof:placetype":"postalcode"
},
  "geometry": {"coordinates":[-1.72473140944916,53.8236455598234],"type":"Point"}
}