{
  "type": "Feature",
  "properties": {
    "iso:country":"GB",
    "wof:name":"CH4 7PE",
    "wof:placetype":"postalcode"
},
  "geometry": {"coordinates":[-2.91460345352566,53.17196122775317],"type":"Point"}
}