{
  "type": "Feature",
  "properties": {
    "date:inception_lower": "1985-04-01",
    "date:inception_upper": "1985-04-01",
    "iso:country": "GB",
    "wof:name": "SK9 2EA",
    "wof:placetype": "postalcode"
  },
  "geometry": {"coordinates":[-2.216314,53.330082],"type":"Point"}
}
