{
  "type": "Feature",
  "properties": {
    "iso:country":"GB",
    "wof:name":"SK9 2EA",
    "wof:placetype":"postalcode"
},
  "geometry": {"coordinates":[-2.21631400297755,53.33008244976502],"type":"Point"}
}