{
  "type": "Feature",
  "properties": {
    "date:inception_lower": "2023-06-01",
    "date:inception_upper": "2023-06-01",
    "iso:country": "GB",
    "wof:name": "G33 6QN",
    "wof:placetype": "postalcode"
  },
  "geometry": {"coordinates":[-4.13291,55.895354],"type":"Point"}
}
