{
  "type": "Feature",
  "properties": {
    "iso:country":"GB",
    "wof:name":"BD2 3QL",
    "wof:placetype":"postalcode"
},
  "geometry": {"coordinates":[-1.71228144240886,53.8093434919632],"type":"Point"}
}