{
  "type": "Feature",
  "properties": {
    "iso:country":"GB",
    "wof:name":"BB12 8UA",
    "wof:placetype":"postalcode"
},
  "geometry": {"coordinates":[-2.29701161230921,53.80249768392307],"type":"Point"}
}