{
  "type": "Feature",
  "properties": {
    "iso:country":"GB",
    "wof:name":"S62 5QH",
    "wof:placetype":"postalcode"
},
  "geometry": {"coordinates":[-1.33814440714684,53.46803988429054],"type":"Point"}
}