{
  "type": "Feature",
  "properties": {
    "iso:country": "GB",
    "wof:name": "LL30 2ES",
    "wof:placetype": "postalcode"
  },
  "geometry": {"coordinates":[-3.836375,53.314397],"type":"Point"}
}
