{
  "type": "Feature",
  "properties": {
    "date:inception_lower":"1980-01-01",
    "date:inception_upper":"1980-01-31",
    "iso:country":"GB",
    "wof:name":"PL1 3HZ",
    "wof:placetype":"postalcode"
},
  "geometry": {"coordinates":[-4.155345,50.370048],"type":"Point"}
}