{
  "type": "Feature",
  "properties": {
    "iso:country":"GB",
    "wof:name":"PL1 3HZ",
    "wof:placetype":"postalcode"
},
  "geometry": {"coordinates":[-4.15534530764483,50.37004798546896],"type":"Point"}
}