{
  "type": "Feature",
  "properties": {
    "iso:country":"GB",
    "wof:name":"MK45 4AU",
    "wof:placetype":"postalcode"
},
  "geometry": {"coordinates":[-0.39761835554963,52.01916679282562],"type":"Point"}
}