{
  "type": "Feature",
  "properties": {
    "iso:country": "GB",
    "wof:name": "MK45 4AU",
    "wof:placetype": "postalcode"
  },
  "geometry": {"coordinates":[-0.398074,52.01797],"type":"Point"}
}
