{
  "type": "Feature",
  "properties": {
    "iso:country":"GB",
    "wof:name":"CH42 7LD",
    "wof:placetype":"postalcode"
},
  "geometry": {"coordinates":[-3.02773792925378,53.37772630389957],"type":"Point"}
}