{
  "type": "Feature",
  "properties": {
    "iso:country": "GB",
    "wof:name": "CH42 7LD",
    "wof:placetype": "postalcode"
  },
  "geometry": {"coordinates":[-3.027738,53.377726],"type":"Point"}
}
