{
  "type": "Feature",
  "properties": {
    "iso:country":"GB",
    "wof:name":"TN14 5FQ",
    "wof:placetype":"postalcode"
},
  "geometry": {"coordinates":[0.17146545450571,51.29248578214898],"type":"Point"}
}