{
  "type": "Feature",
  "properties": {
    "iso:country":"GB",
    "wof:name":"TW4 7EZ",
    "wof:placetype":"postalcode"
},
  "geometry": {"coordinates":[-0.38646226114027,51.46844847517993],"type":"Point"}
}