{
  "type": "Feature",
  "properties": {
    "date:inception_lower":"1980-01-01",
    "date:inception_upper":"1980-01-31",
    "iso:country":"GB",
    "wof:name":"TF5 0DA",
    "wof:placetype":"postalcode"
},
  "geometry": {"coordinates":[-2.554792,52.726448],"type":"Point"}
}