{
  "type": "Feature",
  "properties": {
    "iso:country": "GB",
    "wof:name": "NG17 7JR",
    "wof:placetype": "postalcode"
  },
  "geometry": {"coordinates":[-1.24545,53.11134],"type":"Point"}
}
