{
  "type": "Feature",
  "properties": {
    "date:inception_lower": "1981-06-01",
    "date:inception_upper": "1981-06-01",
    "iso:country": "GB",
    "wof:name": "NG17 7JR",
    "wof:placetype": "postalcode"
  },
  "geometry": {"coordinates":[-1.24545,53.11134],"type":"Point"}
}
