{
  "type": "Feature",
  "properties": {
    "iso:country":"GB",
    "wof:name":"NG17 7JR",
    "wof:placetype":"postalcode"
},
  "geometry": {"coordinates":[-1.245452400215,53.1113217251454],"type":"Point"}
}