{
  "type": "Feature",
  "properties": {
    "iso:country":"GB",
    "wof:name":"CF64 3LY",
    "wof:placetype":"postalcode"
},
  "geometry": {"coordinates":[-3.19291465361408,51.43594365686135],"type":"Point"}
}