{
  "type": "Feature",
  "properties": {
    "iso:country":"GB",
    "wof:name":"FK15 9HS",
    "wof:placetype":"postalcode"
},
  "geometry": {"coordinates":[-3.97904000357963,56.19124353415743],"type":"Point"}
}