{
  "type": "Feature",
  "properties": {
    "date:inception_lower":"1980-01-01",
    "date:inception_upper":"1980-01-31",
    "iso:country":"GB",
    "wof:name":"FK15 9HS",
    "wof:placetype":"postalcode"
},
  "geometry": {"coordinates":[-3.97904,56.191244],"type":"Point"}
}