{
  "type": "Feature",
  "properties": {
    "iso:country": "GB",
    "wof:name": "DY10 1YH",
    "wof:placetype": "postalcode"
  },
  "geometry": {"coordinates":[-2.248147,52.367649],"type":"Point"}
}
