{
  "type": "Feature",
  "properties": {
    "date:inception_lower": "1986-04-01",
    "date:inception_upper": "1986-04-01",
    "iso:country": "GB",
    "wof:name": "DY10 1YH",
    "wof:placetype": "postalcode"
  },
  "geometry": {"coordinates":[-2.248147,52.367649],"type":"Point"}
}
