{
  "type": "Feature",
  "properties": {
    "iso:country":"GB",
    "wof:name":"DN38 6HH",
    "wof:placetype":"postalcode"
},
  "geometry": {"coordinates":[-0.40564870239731,53.5786884371697],"type":"Point"}
}