{
  "type": "Feature",
  "properties": {
    "date:inception_lower": "1985-10-01",
    "date:inception_upper": "1985-10-01",
    "iso:country": "GB",
    "wof:name": "DN38 6HH",
    "wof:placetype": "postalcode"
  },
  "geometry": {"coordinates":[-0.405653,53.57871],"type":"Point"}
}
