{
  "type": "Feature",
  "properties": {
    "iso:country": "GB",
    "wof:name": "S60 1QA",
    "wof:placetype": "postalcode"
  },
  "geometry": {"coordinates":[-1.358063,53.429893],"type":"Point"}
}
