{
  "type": "Feature",
  "properties": {
    "iso:country": "GB",
    "wof:name": "PE10 0PG",
    "wof:placetype": "postalcode"
  },
  "geometry": {"coordinates":[-0.365006,52.800333],"type":"Point"}
}
