{
  "type": "Feature",
  "properties": {
    "iso:country":"GB",
    "wof:name":"PE10 0PG",
    "wof:placetype":"postalcode"
},
  "geometry": {"coordinates":[-0.36500567066138,52.80033320655647],"type":"Point"}
}