{
  "type": "Feature",
  "properties": {
    "date:inception_lower": "2007-03-01",
    "date:inception_upper": "2007-03-01",
    "iso:country": "GB",
    "wof:name": "NR12 9FA",
    "wof:placetype": "postalcode"
  },
  "geometry": {"coordinates":[1.511984,52.771947],"type":"Point"}
}
