{
  "type": "Feature",
  "properties": {
    "iso:country":"GB",
    "wof:name":"NR12 9FA",
    "wof:placetype":"postalcode"
},
  "geometry": {"coordinates":[1.5119839864061,52.77194676627537],"type":"Point"}
}