{
  "type": "Feature",
  "properties": {
    "iso:country":"GB",
    "wof:name":"ME19 5QB",
    "wof:placetype":"postalcode"
},
  "geometry": {"coordinates":[0.42561181931204,51.29967241482554],"type":"Point"}
}