{
  "type": "Feature",
  "properties": {
    "date:inception_lower":"2015-08-01",
    "date:inception_upper":"2015-08-31",
    "iso:country":"GB",
    "wof:name":"TQ9 5FS",
    "wof:placetype":"postalcode"
},
  "geometry": {"coordinates":[-3.675287,50.426536],"type":"Point"}
}