{
  "type": "Feature",
  "properties": {
    "iso:country":"GB",
    "wof:name":"S17 3GH",
    "wof:placetype":"postalcode"
},
  "geometry": {"coordinates":[-1.54486945159079,53.32401876490071],"type":"Point"}
}