{
  "type": "Feature",
  "properties": {
    "iso:country": "GB",
    "wof:name": "MK41 9SB",
    "wof:placetype": "postalcode"
  },
  "geometry": {"coordinates":[-0.441029,52.133634],"type":"Point"}
}
