{
  "type": "Feature",
  "properties": {
    "iso:country":"GB",
    "wof:name":"BB3 2NG",
    "wof:placetype":"postalcode"
},
  "geometry": {"coordinates":[-2.4644391805681,53.68009579653727],"type":"Point"}
}