{
  "type": "Feature",
  "properties": {
    "iso:country":"GB",
    "wof:name":"BL5 3ZQ",
    "wof:placetype":"postalcode"
},
  "geometry": {"coordinates":[-2.51284779999359,53.55605694015587],"type":"Point"}
}