{
  "type": "Feature",
  "properties": {
    "iso:country":"GB",
    "wof:name":"BR3 1NF",
    "wof:placetype":"postalcode"
},
  "geometry": {"coordinates":[-0.03190080032945,51.41359084063742],"type":"Point"}
}