{
  "type": "Feature",
  "properties": {
    "iso:country":"GB",
    "wof:name":"B32 3TP",
    "wof:placetype":"postalcode"
},
  "geometry": {"coordinates":[-1.99551307970637,52.44297737206078],"type":"Point"}
}