{
  "type": "Feature",
  "properties": {
    "iso:country": "GB",
    "wof:name": "HA7 2NW",
    "wof:placetype": "postalcode"
  },
  "geometry": {"coordinates":[-0.303684,51.59679],"type":"Point"}
}
