{
  "type": "Feature",
  "properties": {
    "iso:country":"GB",
    "wof:name":"TA6 7QE",
    "wof:placetype":"postalcode"
},
  "geometry": {"coordinates":[-3.02356480800058,51.13003292513751],"type":"Point"}
}