{
  "type": "Feature",
  "properties": {
    "date:inception_lower": "1996-06-01",
    "date:inception_upper": "1996-06-01",
    "iso:country": "GB",
    "wof:name": "PR6 9BN",
    "wof:placetype": "postalcode"
  },
  "geometry": {"coordinates":[-2.600461,53.666808],"type":"Point"}
}
