{
  "type": "Feature",
  "properties": {
    "iso:country": "GB",
    "wof:name": "SK11 7RR",
    "wof:placetype": "postalcode"
  },
  "geometry": {"coordinates":[-2.12347,53.24511],"type":"Point"}
}
