{
  "type": "Feature",
  "properties": {
    "iso:country": "GB",
    "wof:name": "BN26 5ET",
    "wof:placetype": "postalcode"
  },
  "geometry": {"coordinates":[0.240499,50.820685],"type":"Point"}
}
