{
  "type": "Feature",
  "properties": {
    "date:inception_lower":"1980-01-01",
    "date:inception_upper":"1980-01-31",
    "iso:country":"GB",
    "wof:name":"S80 2UG",
    "wof:placetype":"postalcode"
},
  "geometry": {"coordinates":[-1.106233,53.294187],"type":"Point"}
}