{
  "type": "Feature",
  "properties": {
    "iso:country":"GB",
    "wof:name":"S80 2UG",
    "wof:placetype":"postalcode"
},
  "geometry": {"coordinates":[-1.10623259218589,53.29418662712247],"type":"Point"}
}