{
  "type": "Feature",
  "properties": {
    "iso:country":"GB",
    "wof:name":"NE47 9NF",
    "wof:placetype":"postalcode"
},
  "geometry": {"coordinates":[-2.25976276689278,54.89612341825668],"type":"Point"}
}