{
  "type": "Feature",
  "properties": {
    "date:inception_lower":"1980-01-01",
    "date:inception_upper":"1980-01-31",
    "iso:country":"GB",
    "wof:name":"SY7 8DX",
    "wof:placetype":"postalcode"
},
  "geometry": {"coordinates":[-2.845891,52.443798],"type":"Point"}
}