{
  "type": "Feature",
  "properties": {
    "iso:country":"GB",
    "wof:name":"SY7 8DX",
    "wof:placetype":"postalcode"
},
  "geometry": {"coordinates":[-2.84589071103715,52.4437983884136],"type":"Point"}
}