{
  "type": "Feature",
  "properties": {
    "date:inception_lower":"1980-01-01",
    "date:inception_upper":"1980-01-31",
    "iso:country":"GB",
    "wof:name":"KW15 1TY",
    "wof:placetype":"postalcode"
},
  "geometry": {"coordinates":[-3.011992,58.9987],"type":"Point"}
}