{
  "type": "Feature",
  "properties": {
    "iso:country":"GB",
    "wof:name":"KW15 1TY",
    "wof:placetype":"postalcode"
},
  "geometry": {"coordinates":[-3.01199168188972,58.99869983863086],"type":"Point"}
}