{
  "type": "Feature",
  "properties": {
    "date:inception_lower": "2022-10-01",
    "date:inception_upper": "2022-10-01",
    "iso:country": "GB",
    "wof:name": "NG4 4NP",
    "wof:placetype": "postalcode"
  },
  "geometry": {"coordinates":[-1.095699,52.981535],"type":"Point"}
}
