{
  "type": "Feature",
  "properties": {
    "iso:country":"GB",
    "wof:name":"G4 0LG",
    "wof:placetype":"postalcode"
},
  "geometry": {"coordinates":[-4.24063122778522,55.86375939020398],"type":"Point"}
}