{
  "type": "Feature",
  "properties": {
    "iso:country": "GB",
    "wof:name": "RH15 8AA",
    "wof:placetype": "postalcode"
  },
  "geometry": {"coordinates":[-0.128413,50.963482],"type":"Point"}
}
