{
  "type": "Feature",
  "properties": {
    "date:inception_lower": "2021-10-01",
    "date:inception_upper": "2021-10-01",
    "iso:country": "GB",
    "wof:name": "KA11 5AR",
    "wof:placetype": "postalcode"
  },
  "geometry": {"coordinates":[-4.633523,55.600995],"type":"Point"}
}
