{
  "type": "Feature",
  "properties": {
    "date:inception_lower": "2017-11-01",
    "date:inception_upper": "2017-11-01",
    "iso:country": "GB",
    "wof:name": "KA11 5AR",
    "wof:placetype": "postalcode"
  },
  "geometry": {"coordinates":[-4.628237,55.596254],"type":"Point"}
}
