{
  "type": "Feature",
  "properties": {
    "iso:country":"GB",
    "wof:name":"HR1 1PQ",
    "wof:placetype":"postalcode"
},
  "geometry": {"coordinates":[-2.69415003810928,52.0612262312071],"type":"Point"}
}