{
  "type": "Feature",
  "properties": {
    "iso:country":"GB",
    "wof:name":"HG3 1AL",
    "wof:placetype":"postalcode"
},
  "geometry": {"coordinates":[-1.44938454306723,53.95851516224803],"type":"Point"}
}