{
  "type": "Feature",
  "properties": {
    "iso:country": "GB",
    "wof:name": "HG3 1AL",
    "wof:placetype": "postalcode"
  },
  "geometry": {"coordinates":[-1.449391,53.958531],"type":"Point"}
}
