{
  "type": "Feature",
  "properties": {
    "date:inception_lower": "1981-09-01",
    "date:inception_upper": "1981-09-01",
    "iso:country": "GB",
    "wof:name": "B98 7XG",
    "wof:placetype": "postalcode"
  },
  "geometry": {"coordinates":[-1.931779,52.282286],"type":"Point"}
}
