{
  "type": "Feature",
  "properties": {
    "iso:country":"GB",
    "wof:name":"B98 7XG",
    "wof:placetype":"postalcode"
},
  "geometry": {"coordinates":[-1.93177864480025,52.28228615846881],"type":"Point"}
}