{
  "type": "Feature",
  "properties": {
    "iso:country": "GB",
    "wof:name": "B98 7XG",
    "wof:placetype": "postalcode"
  },
  "geometry": {"coordinates":[-1.931779,52.282286],"type":"Point"}
}
