{
  "type": "Feature",
  "properties": {
    "iso:country":"GB",
    "wof:name":"TN19 7EA",
    "wof:placetype":"postalcode"
},
  "geometry": {"coordinates":[0.38818460218239,50.99729253052181],"type":"Point"}
}