{
  "type": "Feature",
  "properties": {
    "iso:country":"GB",
    "wof:name":"B16 8DR",
    "wof:placetype":"postalcode"
},
  "geometry": {"coordinates":[-1.92215528869072,52.47930751839004],"type":"Point"}
}