{
  "type": "Feature",
  "properties": {
    "iso:country":"GB",
    "wof:name":"B23 5FJ",
    "wof:placetype":"postalcode"
},
  "geometry": {"coordinates":[-1.87049514214802,52.53756199912016],"type":"Point"}
}