{
  "type": "Feature",
  "properties": {
    "iso:country": "GB",
    "wof:name": "B23 5FJ",
    "wof:placetype": "postalcode"
  },
  "geometry": {"coordinates":[-1.870495,52.537562],"type":"Point"}
}
