{
  "type": "Feature",
  "properties": {
    "iso:country":"GB",
    "wof:name":"SE19 2UA",
    "wof:placetype":"postalcode"
},
  "geometry": {"coordinates":[-0.08109031845477,51.41651090866051],"type":"Point"}
}