{
  "type": "Feature",
  "properties": {
    "iso:country":"GB",
    "wof:name":"HA6 1EJ",
    "wof:placetype":"postalcode"
},
  "geometry": {"coordinates":[-0.41941276545155,51.6105419741335],"type":"Point"}
}