{
  "type": "Feature",
  "properties": {
    "date:inception_lower": "2023-02-01",
    "date:inception_upper": "2023-02-01",
    "iso:country": "GB",
    "wof:name": "LE10 9RT",
    "wof:placetype": "postalcode"
  },
  "geometry": {"coordinates":[-1.369595,52.540369],"type":"Point"}
}
