{
  "type": "Feature",
  "properties": {
    "iso:country":"GB",
    "wof:name":"IP28 8ET",
    "wof:placetype":"postalcode"
},
  "geometry": {"coordinates":[0.47647194656563,52.37303736684698],"type":"Point"}
}