{
  "type": "Feature",
  "properties": {
    "iso:country":"GB",
    "wof:name":"BH21 1AT",
    "wof:placetype":"postalcode"
},
  "geometry": {"coordinates":[-1.98298990462138,50.80393879088363],"type":"Point"}
}