{
  "type": "Feature",
  "properties": {
    "iso:country": "GB",
    "wof:name": "BH21 1AT",
    "wof:placetype": "postalcode"
  },
  "geometry": {"coordinates":[-1.98299,50.803939],"type":"Point"}
}
