{
  "type": "Feature",
  "properties": {
    "iso:country": "GB",
    "wof:name": "CV9 2SH",
    "wof:placetype": "postalcode"
  },
  "geometry": {"coordinates":[-1.546658,52.576618],"type":"Point"}
}
