{
  "type": "Feature",
  "properties": {
    "iso:country":"GB",
    "wof:name":"IV30 5QU",
    "wof:placetype":"postalcode"
},
  "geometry": {"coordinates":[-3.38893407611585,57.71010963069006],"type":"Point"}
}