{
  "type": "Feature",
  "properties": {
    "date:inception_lower": "1998-12-01",
    "date:inception_upper": "1998-12-01",
    "iso:country": "GB",
    "wof:name": "IV30 5QU",
    "wof:placetype": "postalcode"
  },
  "geometry": {"coordinates":[-3.388934,57.71011],"type":"Point"}
}
