{
  "type": "Feature",
  "properties": {
    "iso:country":"GB",
    "wof:name":"HD2 1RD",
    "wof:placetype":"postalcode"
},
  "geometry": {"coordinates":[-1.75145742168864,53.68393971682524],"type":"Point"}
}