{
  "type": "Feature",
  "properties": {
    "iso:country":"GB",
    "wof:name":"SO40 9HR",
    "wof:placetype":"postalcode"
},
  "geometry": {"coordinates":[-1.48575628808758,50.91437815593356],"type":"Point"}
}