{
  "type": "Feature",
  "properties": {
    "iso:country":"GB",
    "wof:name":"LN12 2LT",
    "wof:placetype":"postalcode"
},
  "geometry": {"coordinates":[0.28062750387493,53.31750820902812],"type":"Point"}
}