{
  "type": "Feature",
  "properties": {
    "iso:country":"GB",
    "wof:name":"EX7 0HQ",
    "wof:placetype":"postalcode"
},
  "geometry": {"coordinates":[-3.46464295171587,50.58822009109435],"type":"Point"}
}