{
  "type": "Feature",
  "properties": {
    "iso:country":"GB",
    "wof:name":"CW6 0LR",
    "wof:placetype":"postalcode"
},
  "geometry": {"coordinates":[-2.67767785798566,53.18434108756227],"type":"Point"}
}