{
  "type": "Feature",
  "properties": {
    "iso:country": "GB",
    "wof:name": "CW6 0LR",
    "wof:placetype": "postalcode"
  },
  "geometry": {"coordinates":[-2.677678,53.184341],"type":"Point"}
}
