{
  "type": "Feature",
  "properties": {
    "date:inception_lower":"2011-06-01",
    "date:inception_upper":"2011-06-30",
    "iso:country":"GB",
    "wof:name":"SE16 7AW",
    "wof:placetype":"postalcode"
},
  "geometry": {"coordinates":[-0.048378,51.500052],"type":"Point"}
}