{
  "type": "Feature",
  "properties": {
    "iso:country":"GB",
    "wof:name":"NE8 3UN",
    "wof:placetype":"postalcode"
},
  "geometry": {"coordinates":[-1.58632453384643,54.94978719993465],"type":"Point"}
}