{
  "type": "Feature",
  "properties": {
    "date:inception_lower": "1985-10-01",
    "date:inception_upper": "1985-10-01",
    "iso:country": "GB",
    "wof:name": "TN13 3SY",
    "wof:placetype": "postalcode"
  },
  "geometry": {"coordinates":[0.192536,51.275347],"type":"Point"}
}
