{
  "type": "Feature",
  "properties": {
    "date:inception_lower": "1980-01-01",
    "date:inception_upper": "1980-01-01",
    "iso:country": "GB",
    "wof:name": "DA1 5JH",
    "wof:placetype": "postalcode"
  },
  "geometry": {"coordinates":[0.22469,51.453039],"type":"Point"}
}
