{
  "type": "Feature",
  "properties": {
    "iso:country":"GB",
    "wof:name":"NE64 6NX",
    "wof:placetype":"postalcode"
},
  "geometry": {"coordinates":[-1.5142960096238,55.18317028860884],"type":"Point"}
}