{
  "type": "Feature",
  "properties": {
    "date:inception_lower": "1993-08-01",
    "date:inception_upper": "1993-08-01",
    "iso:country": "GB",
    "wof:name": "PO2 9EP",
    "wof:placetype": "postalcode"
  },
  "geometry": {"coordinates":[-1.07942,50.82218],"type":"Point"}
}
