{
  "type": "Feature",
  "properties": {
    "iso:country":"GB",
    "wof:name":"CA3 9BS",
    "wof:placetype":"postalcode"
},
  "geometry": {"coordinates":[-2.93614855366259,54.91260005221551],"type":"Point"}
}