{
  "type": "Feature",
  "properties": {
    "iso:country":"GB",
    "wof:name":"BL6 5NQ",
    "wof:placetype":"postalcode"
},
  "geometry": {"coordinates":[-2.54570048884419,53.59399539874109],"type":"Point"}
}