{
  "type": "Feature",
  "properties": {
    "iso:country": "GB",
    "wof:name": "BL6 5NQ",
    "wof:placetype": "postalcode"
  },
  "geometry": {"coordinates":[-2.5457,53.594011],"type":"Point"}
}
