{
  "type": "Feature",
  "properties": {
    "date:inception_lower": "1980-01-01",
    "date:inception_upper": "1980-01-01",
    "iso:country": "GB",
    "wof:name": "CW12 4BU",
    "wof:placetype": "postalcode"
  },
  "geometry": {"coordinates":[-2.221956,53.158709],"type":"Point"}
}
