{
  "type": "Feature",
  "properties": {
    "iso:country":"GB",
    "wof:name":"DL5 7AH",
    "wof:placetype":"postalcode"
},
  "geometry": {"coordinates":[-1.5792606884215,54.6177007036283],"type":"Point"}
}