{
  "type": "Feature",
  "properties": {
    "date:inception_lower": "1980-01-01",
    "date:inception_upper": "1980-01-01",
    "iso:country": "GB",
    "wof:name": "DL5 7AH",
    "wof:placetype": "postalcode"
  },
  "geometry": {"coordinates":[-1.579261,54.617701],"type":"Point"}
}
