{
  "type": "Feature",
  "properties": {
    "iso:country": "GB",
    "wof:name": "DL5 7AH",
    "wof:placetype": "postalcode"
  },
  "geometry": {"coordinates":[-1.579261,54.617701],"type":"Point"}
}
