{
  "type": "Feature",
  "properties": {
    "iso:country":"GB",
    "wof:name":"NG20 8QT",
    "wof:placetype":"postalcode"
},
  "geometry": {"coordinates":[-1.22734074372226,53.20659846745819],"type":"Point"}
}