{
  "type": "Feature",
  "properties": {
    "date:inception_lower": "2006-07-01",
    "date:inception_upper": "2006-07-01",
    "iso:country": "GB",
    "wof:name": "NG20 8QT",
    "wof:placetype": "postalcode"
  },
  "geometry": {"coordinates":[-1.227341,53.206598],"type":"Point"}
}
