{
  "type": "Feature",
  "properties": {
    "iso:country": "GB",
    "wof:name": "NG20 8QT",
    "wof:placetype": "postalcode"
  },
  "geometry": {"coordinates":[-1.227341,53.206598],"type":"Point"}
}
