{
  "type": "Feature",
  "properties": {
    "iso:country":"GB",
    "wof:name":"TS24 8LA",
    "wof:placetype":"postalcode"
},
  "geometry": {"coordinates":[-1.22033943222881,54.69764064614695],"type":"Point"}
}