{
  "type": "Feature",
  "properties": {
    "iso:country": "GB",
    "wof:name": "LE2 7BJ",
    "wof:placetype": "postalcode"
  },
  "geometry": {"coordinates":[-1.140893,52.629929],"type":"Point"}
}
