{
  "type": "Feature",
  "properties": {
    "date:inception_lower": "1999-06-01",
    "date:inception_upper": "1999-06-01",
    "iso:country": "GB",
    "wof:name": "CH61 3UU",
    "wof:placetype": "postalcode"
  },
  "geometry": {"coordinates":[-3.09692,53.353244],"type":"Point"}
}
