{
  "type": "Feature",
  "properties": {
    "iso:country": "GB",
    "wof:name": "CH61 3UU",
    "wof:placetype": "postalcode"
  },
  "geometry": {"coordinates":[-3.09692,53.353244],"type":"Point"}
}
