{
  "type": "Feature",
  "properties": {
    "iso:country": "GB",
    "wof:name": "PH3 1HG",
    "wof:placetype": "postalcode"
  },
  "geometry": {"coordinates":[-3.653665,56.319965],"type":"Point"}
}
