{
  "type": "Feature",
  "properties": {
    "iso:country":"GB",
    "wof:name":"PH3 1HG",
    "wof:placetype":"postalcode"
},
  "geometry": {"coordinates":[-3.65355905433124,56.32002899455993],"type":"Point"}
}