{
  "type": "Feature",
  "properties": {
    "iso:country":"GB",
    "wof:name":"EX6 6HH",
    "wof:placetype":"postalcode"
},
  "geometry": {"coordinates":[-3.77249367915749,50.74088815198976],"type":"Point"}
}