{
  "type": "Feature",
  "properties": {
    "iso:country":"GB",
    "wof:name":"SY3 8JL",
    "wof:placetype":"postalcode"
},
  "geometry": {"coordinates":[-2.76123582337914,52.71038832411566],"type":"Point"}
}