{
  "type": "Feature",
  "properties": {
    "iso:country": "GB",
    "wof:name": "SY3 8JL",
    "wof:placetype": "postalcode"
  },
  "geometry": {"coordinates":[-2.761236,52.710388],"type":"Point"}
}
