{
  "type": "Feature",
  "properties": {
    "iso:country": "GB",
    "wof:name": "WA1 2BE",
    "wof:placetype": "postalcode"
  },
  "geometry": {"coordinates":[-2.586549,53.389384],"type":"Point"}
}
