{
  "type": "Feature",
  "properties": {
    "date:inception_lower": "2008-05-01",
    "date:inception_upper": "2008-05-01",
    "iso:country": "GB",
    "wof:name": "IV12 5BF",
    "wof:placetype": "postalcode"
  },
  "geometry": {"coordinates":[-3.89185,57.576303],"type":"Point"}
}
