{
  "type": "Feature",
  "properties": {
    "iso:country": "GB",
    "wof:name": "IV12 5BF",
    "wof:placetype": "postalcode"
  },
  "geometry": {"coordinates":[-3.89185,57.576303],"type":"Point"}
}
