{
  "type": "Feature",
  "properties": {
    "iso:country": "GB",
    "wof:name": "LN5 7NN",
    "wof:placetype": "postalcode"
  },
  "geometry": {"coordinates":[-0.535882,53.222863],"type":"Point"}
}
