{
  "type": "Feature",
  "properties": {
    "date:inception_lower": "2001-06-01",
    "date:inception_upper": "2001-06-01",
    "iso:country": "GB",
    "wof:name": "LN5 7NN",
    "wof:placetype": "postalcode"
  },
  "geometry": {"coordinates":[-0.535882,53.222863],"type":"Point"}
}
