{
  "type": "Feature",
  "properties": {
    "iso:country":"GB",
    "wof:name":"PR5 6TB",
    "wof:placetype":"postalcode"
},
  "geometry": {"coordinates":[-2.66562599904697,53.72980418318704],"type":"Point"}
}