{
  "type": "Feature",
  "properties": {
    "iso:country":"GB",
    "wof:name":"WD17 4JU",
    "wof:placetype":"postalcode"
},
  "geometry": {"coordinates":[-0.42524495542747,51.67903162294667],"type":"Point"}
}