{
  "type": "Feature",
  "properties": {
    "iso:country":"GB",
    "wof:name":"NE2 1JT",
    "wof:placetype":"postalcode"
},
  "geometry": {"coordinates":[-1.59560903838605,54.98764165076182],"type":"Point"}
}