{
  "type": "Feature",
  "properties": {
    "iso:country":"GB",
    "wof:name":"BS39 4LJ",
    "wof:placetype":"postalcode"
},
  "geometry": {"coordinates":[-2.50847155036746,51.38177360700013],"type":"Point"}
}