{
  "type": "Feature",
  "properties": {
    "iso:country": "GB",
    "wof:name": "UB2 5UN",
    "wof:placetype": "postalcode"
  },
  "geometry": {"coordinates":[-0.391348,51.494306],"type":"Point"}
}
