{
  "type": "Feature",
  "properties": {
    "iso:country":"GB",
    "wof:name":"UB2 5UN",
    "wof:placetype":"postalcode"
},
  "geometry": {"coordinates":[-0.39136934039748,51.4943057669817],"type":"Point"}
}