{
  "type": "Feature",
  "properties": {
    "date:inception_lower": "1980-01-01",
    "date:inception_upper": "1980-01-01",
    "iso:country": "GB",
    "wof:name": "UB2 5UN",
    "wof:placetype": "postalcode"
  },
  "geometry": {"coordinates":[-0.390837,51.49411],"type":"Point"}
}
