{
  "type": "Feature",
  "properties": {
    "iso:country": "GB",
    "wof:name": "ML1 4NY",
    "wof:placetype": "postalcode"
  },
  "geometry": {"coordinates":[-3.970752,55.817621],"type":"Point"}
}
