{
  "type": "Feature",
  "properties": {
    "iso:country":"GB",
    "wof:name":"MK18 7BP",
    "wof:placetype":"postalcode"
},
  "geometry": {"coordinates":[-0.97682736098051,52.000229564596],"type":"Point"}
}