{
  "type": "Feature",
  "properties": {
    "iso:country":"GB",
    "wof:name":"BS1 6GD",
    "wof:placetype":"postalcode"
},
  "geometry": {"coordinates":[-2.58434374943434,51.4507816072637],"type":"Point"}
}