{
  "type": "Feature",
  "properties": {
    "date:inception_lower": "2018-07-01",
    "date:inception_upper": "2018-07-01",
    "iso:country": "GB",
    "wof:name": "DE74 2BU",
    "wof:placetype": "postalcode"
  },
  "geometry": {"coordinates":[-1.314111,52.825938],"type":"Point"}
}
