{
  "type": "Feature",
  "properties": {
    "date:inception_lower": "2019-05-01",
    "date:inception_upper": "2019-05-01",
    "iso:country": "GB",
    "wof:name": "WR10 1FE",
    "wof:placetype": "postalcode"
  },
  "geometry": {"coordinates":[-2.070787,52.122897],"type":"Point"}
}
