{
  "type": "Feature",
  "properties": {
    "iso:country":"GB",
    "wof:name":"PO21 5SQ",
    "wof:placetype":"postalcode"
},
  "geometry": {"coordinates":[-0.70443233750791,50.78829543196937],"type":"Point"}
}