{
  "type": "Feature",
  "properties": {
    "iso:country":"GB",
    "wof:name":"LA3 3RR",
    "wof:placetype":"postalcode"
},
  "geometry": {"coordinates":[-2.85659667039268,54.05858059040725],"type":"Point"}
}