{
  "type": "Feature",
  "properties": {
    "date:inception_lower":"1980-01-01",
    "date:inception_upper":"1980-01-31",
    "iso:country":"GB",
    "wof:name":"BS2 9LW",
    "wof:placetype":"postalcode"
},
  "geometry": {"coordinates":[-2.57761,51.46566],"type":"Point"}
}