{
  "type": "Feature",
  "properties": {
    "iso:country":"GB",
    "wof:name":"BN1 6JF",
    "wof:placetype":"postalcode"
},
  "geometry": {"coordinates":[-0.13415380390505,50.84248739568229],"type":"Point"}
}