{
  "type": "Feature",
  "properties": {
    "iso:country": "GB",
    "wof:name": "CT1 1QR",
    "wof:placetype": "postalcode"
  },
  "geometry": {"coordinates":[1.091507,51.27973],"type":"Point"}
}
