{
  "type": "Feature",
  "properties": {
    "iso:country":"GB",
    "wof:name":"CT1 1QR",
    "wof:placetype":"postalcode"
},
  "geometry": {"coordinates":[1.09150712962339,51.27972998031431],"type":"Point"}
}