{
  "type": "Feature",
  "properties": {
    "iso:country":"GB",
    "wof:name":"OX11 9JX",
    "wof:placetype":"postalcode"
},
  "geometry": {"coordinates":[-1.23532917524245,51.59701181006579],"type":"Point"}
}