{
  "type": "Feature",
  "properties": {
    "iso:country": "GB",
    "wof:name": "OX11 9JX",
    "wof:placetype": "postalcode"
  },
  "geometry": {"coordinates":[-1.235329,51.597012],"type":"Point"}
}
