{
  "type": "Feature",
  "properties": {
    "iso:country":"GB",
    "wof:name":"BB5 5RT",
    "wof:placetype":"postalcode"
},
  "geometry": {"coordinates":[-2.38624239100486,53.77909915793158],"type":"Point"}
}