{
  "type": "Feature",
  "properties": {
    "iso:country":"GB",
    "wof:name":"LL18 4SU",
    "wof:placetype":"postalcode"
},
  "geometry": {"coordinates":[-3.46763362402114,53.30693757288869],"type":"Point"}
}