{
  "type": "Feature",
  "properties": {
    "date:inception_lower":"1980-01-01",
    "date:inception_upper":"1980-01-31",
    "iso:country":"GB",
    "wof:name":"LL18 4SU",
    "wof:placetype":"postalcode"
},
  "geometry": {"coordinates":[-3.467634,53.306938],"type":"Point"}
}