{
  "type": "Feature",
  "properties": {
    "iso:country":"GB",
    "wof:name":"SW18 2DR",
    "wof:placetype":"postalcode"
},
  "geometry": {"coordinates":[-0.18392187152565,51.45161983126086],"type":"Point"}
}