{
  "type": "Feature",
  "properties": {
    "date:inception_lower":"1993-01-01",
    "date:inception_upper":"1993-01-31",
    "iso:country":"GB",
    "wof:name":"TA21 9JH",
    "wof:placetype":"postalcode"
},
  "geometry": {"coordinates":[-3.202368,50.9848],"type":"Point"}
}