{
  "type": "Feature",
  "properties": {
    "iso:country": "GB",
    "wof:name": "G61 1QS",
    "wof:placetype": "postalcode"
  },
  "geometry": {"coordinates":[-4.3253,55.909115],"type":"Point"}
}
