{
  "type": "Feature",
  "properties": {
    "iso:country":"GB",
    "wof:name":"NW3 4XP",
    "wof:placetype":"postalcode"
},
  "geometry": {"coordinates":[-0.16215180595133,51.5481747551299],"type":"Point"}
}