{
  "type": "Feature",
  "properties": {
    "iso:country":"GB",
    "wof:name":"WA8 9JH",
    "wof:placetype":"postalcode"
},
  "geometry": {"coordinates":[-2.73011127931505,53.38827781651361],"type":"Point"}
}