{
  "type": "Feature",
  "properties": {
    "iso:country":"GB",
    "wof:name":"ST2 8BU",
    "wof:placetype":"postalcode"
},
  "geometry": {"coordinates":[-2.14474377243687,53.03492366567401],"type":"Point"}
}