{
  "type": "Feature",
  "properties": {
    "iso:country":"GB",
    "wof:name":"RH10 1NY",
    "wof:placetype":"postalcode"
},
  "geometry": {"coordinates":[-0.17938676584679,51.11620867262358],"type":"Point"}
}