{
  "type": "Feature",
  "properties": {
    "iso:country": "GB",
    "wof:name": "RH10 1NY",
    "wof:placetype": "postalcode"
  },
  "geometry": {"coordinates":[-0.179387,51.116209],"type":"Point"}
}
