{
  "type": "Feature",
  "properties": {
    "date:inception_lower": "2018-03-01",
    "date:inception_upper": "2018-03-01",
    "iso:country": "GB",
    "wof:name": "YO13 0AF",
    "wof:placetype": "postalcode"
  },
  "geometry": {"coordinates":[-0.431416,54.304107],"type":"Point"}
}
