{
  "type": "Feature",
  "properties": {
    "date:inception_lower": "1980-01-01",
    "date:inception_upper": "1980-01-01",
    "iso:country": "GB",
    "wof:name": "EX2 9AN",
    "wof:placetype": "postalcode"
  },
  "geometry": {"coordinates":[-3.539814,50.712843],"type":"Point"}
}
