{
  "type": "Feature",
  "properties": {
    "iso:country":"GB",
    "wof:name":"NW3 6BD",
    "wof:placetype":"postalcode"
},
  "geometry": {"coordinates":[-0.17924900304817,51.55452919391242],"type":"Point"}
}