{
  "type": "Feature",
  "properties": {
    "iso:country": "GB",
    "wof:name": "ST17 0RJ",
    "wof:placetype": "postalcode"
  },
  "geometry": {"coordinates":[-2.096286,52.75934],"type":"Point"}
}
