{
  "type": "Feature",
  "properties": {
    "date:inception_lower":"1980-01-01",
    "date:inception_upper":"1980-01-31",
    "iso:country":"GB",
    "wof:name":"ST17 0RJ",
    "wof:placetype":"postalcode"
},
  "geometry": {"coordinates":[-2.096286,52.75934],"type":"Point"}
}