{
  "type": "Feature",
  "properties": {
    "iso:country":"GB",
    "wof:name":"TW1 4LY",
    "wof:placetype":"postalcode"
},
  "geometry": {"coordinates":[-0.33715058039872,51.44389378003327],"type":"Point"}
}