{
  "type": "Feature",
  "properties": {
    "iso:country":"GB",
    "wof:name":"SA64 0AY",
    "wof:placetype":"postalcode"
},
  "geometry": {"coordinates":[-5.00335270967962,51.99809449732174],"type":"Point"}
}