{
  "type": "Feature",
  "properties": {
    "date:inception_lower":"1980-01-01",
    "date:inception_upper":"1980-01-31",
    "iso:country":"GB",
    "wof:name":"SA64 0AY",
    "wof:placetype":"postalcode"
},
  "geometry": {"coordinates":[-5.003337,51.998094],"type":"Point"}
}