{
  "type": "Feature",
  "properties": {
    "iso:country":"GB",
    "wof:name":"CM21 0HY",
    "wof:placetype":"postalcode"
},
  "geometry": {"coordinates":[0.12309407196652,51.80753527206449],"type":"Point"}
}