{
  "type": "Feature",
  "properties": {
    "date:inception_lower":"1980-01-01",
    "date:inception_upper":"1980-01-31",
    "iso:country":"GB",
    "wof:name":"CM21 0HY",
    "wof:placetype":"postalcode"
},
  "geometry": {"coordinates":[0.123094,51.807535],"type":"Point"}
}