{
  "type": "Feature",
  "properties": {
    "iso:country": "GB",
    "wof:name": "CM21 0HY",
    "wof:placetype": "postalcode"
  },
  "geometry": {"coordinates":[0.123094,51.807535],"type":"Point"}
}
