{
  "type": "Feature",
  "properties": {
    "iso:country": "GB",
    "wof:name": "EN1 4BP",
    "wof:placetype": "postalcode"
  },
  "geometry": {"coordinates":[-0.062685,51.662955],"type":"Point"}
}
