{
  "type": "Feature",
  "properties": {
    "date:inception_lower":"2016-03-01",
    "date:inception_upper":"2016-03-31",
    "iso:country":"GB",
    "wof:name":"EN1 4BP",
    "wof:placetype":"postalcode"
},
  "geometry": {"coordinates":[-0.062685,51.662955],"type":"Point"}
}