{
  "type": "Feature",
  "properties": {
    "iso:country":"GB",
    "wof:name":"EN1 4BP",
    "wof:placetype":"postalcode"
},
  "geometry": {"coordinates":[-0.06268504645263,51.66295499299905],"type":"Point"}
}