{
  "type": "Feature",
  "properties": {
    "date:inception_lower": "1980-01-01",
    "date:inception_upper": "1980-01-01",
    "iso:country": "GB",
    "wof:name": "EH9 2LE",
    "wof:placetype": "postalcode"
  },
  "geometry": {"coordinates":[-3.187142,55.93001],"type":"Point"}
}
