{
  "type": "Feature",
  "properties": {
    "date:inception_lower": "2018-10-01",
    "date:inception_upper": "2018-10-01",
    "iso:country": "GB",
    "wof:name": "CT9 5FN",
    "wof:placetype": "postalcode"
  },
  "geometry": {"coordinates":[1.365287,51.385025],"type":"Point"}
}
