{
  "type": "Feature",
  "properties": {
    "iso:country":"GB",
    "wof:name":"LL26 0AF",
    "wof:placetype":"postalcode"
},
  "geometry": {"coordinates":[-3.79502228030324,53.13976526869507],"type":"Point"}
}