{
  "type": "Feature",
  "properties": {
    "date:inception_lower":"1996-12-01",
    "date:inception_upper":"1996-12-31",
    "iso:country":"GB",
    "wof:name":"LL26 0AF",
    "wof:placetype":"postalcode"
},
  "geometry": {"coordinates":[-3.795022,53.139765],"type":"Point"}
}