{
  "type": "Feature",
  "properties": {
    "iso:country": "GB",
    "wof:name": "LL26 0AF",
    "wof:placetype": "postalcode"
  },
  "geometry": {"coordinates":[-3.795022,53.139765],"type":"Point"}
}
