{
  "type": "Feature",
  "properties": {
    "iso:country":"GB",
    "wof:name":"NN9 6SH",
    "wof:placetype":"postalcode"
},
  "geometry": {"coordinates":[-0.53823271969314,52.34990900076044],"type":"Point"}
}