{
  "type": "Feature",
  "properties": {
    "iso:country":"GB",
    "wof:name":"PO30 3AS",
    "wof:placetype":"postalcode"
},
  "geometry": {"coordinates":[-1.23275820234654,50.65315430441456],"type":"Point"}
}