{
  "type": "Feature",
  "properties": {
    "iso:country":"GB",
    "wof:name":"CW7 3DN",
    "wof:placetype":"postalcode"
},
  "geometry": {"coordinates":[-2.5026107080343,53.19215711825358],"type":"Point"}
}