{
  "type": "Feature",
  "properties": {
    "iso:country":"GB",
    "wof:name":"SO45 6JA",
    "wof:placetype":"postalcode"
},
  "geometry": {"coordinates":[-1.40009006346144,50.86492449366867],"type":"Point"}
}