{
  "type": "Feature",
  "properties": {
    "iso:country":"GB",
    "wof:name":"PA15 1NP",
    "wof:placetype":"postalcode"
},
  "geometry": {"coordinates":[-4.7590144952,55.94766750328663],"type":"Point"}
}