{
  "type": "Feature",
  "properties": {
    "date:inception_lower": "2000-06-01",
    "date:inception_upper": "2000-06-01",
    "iso:country": "GB",
    "wof:name": "KA7 4LB",
    "wof:placetype": "postalcode"
  },
  "geometry": {"coordinates":[-4.686044,55.429193],"type":"Point"}
}
