{
  "type": "Feature",
  "properties": {
    "iso:country":"GB",
    "wof:name":"KA7 4LB",
    "wof:placetype":"postalcode"
},
  "geometry": {"coordinates":[-4.68604396498696,55.42919272426678],"type":"Point"}
}