{
  "type": "Feature",
  "properties": {
    "date:inception_lower": "2016-05-01",
    "date:inception_upper": "2016-05-01",
    "iso:country": "GB",
    "wof:name": "B18 6LZ",
    "wof:placetype": "postalcode"
  },
  "geometry": {"coordinates":[-1.921069,52.491224],"type":"Point"}
}
