{
  "type": "Feature",
  "properties": {
    "date:inception_lower":"2016-05-01",
    "date:inception_upper":"2016-05-31",
    "iso:country":"GB",
    "wof:name":"B18 6LZ",
    "wof:placetype":"postalcode"
},
  "geometry": {"coordinates":[-1.921206,52.491308],"type":"Point"}
}