{
  "type": "Feature",
  "properties": {
    "iso:country":"GB",
    "wof:name":"LE12 9LT",
    "wof:placetype":"postalcode"
},
  "geometry": {"coordinates":[-1.29997412648111,52.76675685121978],"type":"Point"}
}