{
  "type": "Feature",
  "properties": {
    "iso:country": "GB",
    "wof:name": "BS40 7AL",
    "wof:placetype": "postalcode"
  },
  "geometry": {"coordinates":[-2.737625,51.332179],"type":"Point"}
}
