{
  "type": "Feature",
  "properties": {
    "iso:country":"GB",
    "wof:name":"BS40 7AL",
    "wof:placetype":"postalcode"
},
  "geometry": {"coordinates":[-2.73762456855431,51.33217855894583],"type":"Point"}
}