{
  "type": "Feature",
  "properties": {
    "iso:country":"GB",
    "wof:name":"ME13 8QJ",
    "wof:placetype":"postalcode"
},
  "geometry": {"coordinates":[0.88722123534564,51.31138368004789],"type":"Point"}
}