{
  "type": "Feature",
  "properties": {
    "date:inception_lower": "1980-01-01",
    "date:inception_upper": "1980-01-01",
    "iso:country": "GB",
    "wof:name": "ME13 8QJ",
    "wof:placetype": "postalcode"
  },
  "geometry": {"coordinates":[0.887221,51.311384],"type":"Point"}
}
