{
  "type": "Feature",
  "properties": {
    "date:inception_lower":"1980-01-01",
    "date:inception_upper":"1980-01-31",
    "iso:country":"GB",
    "wof:name":"PR3 2EP",
    "wof:placetype":"postalcode"
},
  "geometry": {"coordinates":[-2.671601,53.864993],"type":"Point"}
}