{
  "type": "Feature",
  "properties": {
    "iso:country": "GB",
    "wof:name": "PR3 2EP",
    "wof:placetype": "postalcode"
  },
  "geometry": {"coordinates":[-2.671601,53.864993],"type":"Point"}
}
