{
  "type": "Feature",
  "properties": {
    "iso:country":"GB",
    "wof:name":"HR8 2AE",
    "wof:placetype":"postalcode"
},
  "geometry": {"coordinates":[-2.42547477283859,52.03843494857561],"type":"Point"}
}