{
  "type": "Feature",
  "properties": {
    "iso:country": "GB",
    "wof:name": "CR8 5WS",
    "wof:placetype": "postalcode"
  },
  "geometry": {"coordinates":[-0.103427,51.346587],"type":"Point"}
}
