{
  "type": "Feature",
  "properties": {
    "date:inception_lower": "2006-09-01",
    "date:inception_upper": "2006-09-01",
    "iso:country": "GB",
    "wof:name": "CB23 8EL",
    "wof:placetype": "postalcode"
  },
  "geometry": {"coordinates":[0.017011,52.253973],"type":"Point"}
}
