{
  "type": "Feature",
  "properties": {
    "iso:country": "GB",
    "wof:name": "CB23 8EL",
    "wof:placetype": "postalcode"
  },
  "geometry": {"coordinates":[0.017177,52.254096],"type":"Point"}
}
