{
  "type": "Feature",
  "properties": {
    "iso:country":"GB",
    "wof:name":"GL54 5QF",
    "wof:placetype":"postalcode"
},
  "geometry": {"coordinates":[-1.97093829727295,51.9544002330445],"type":"Point"}
}