{
  "type": "Feature",
  "properties": {
    "iso:country": "GB",
    "wof:name": "GL54 5QF",
    "wof:placetype": "postalcode"
  },
  "geometry": {"coordinates":[-1.970938,51.9544],"type":"Point"}
}
