{
  "type": "Feature",
  "properties": {
    "iso:country":"GB",
    "wof:name":"AL1 5NR",
    "wof:placetype":"postalcode"
},
  "geometry": {"coordinates":[-0.30531665353057,51.74616970298442],"type":"Point"}
}