{
  "type": "Feature",
  "properties": {
    "iso:country":"GB",
    "wof:name":"DG11 1QR",
    "wof:placetype":"postalcode"
},
  "geometry": {"coordinates":[-3.43731061859836,55.12974884831451],"type":"Point"}
}