{
  "type": "Feature",
  "properties": {
    "date:inception_lower":"1981-07-01",
    "date:inception_upper":"1981-07-31",
    "iso:country":"GB",
    "wof:name":"DG11 1QR",
    "wof:placetype":"postalcode"
},
  "geometry": {"coordinates":[-3.437311,55.129749],"type":"Point"}
}