{
  "type": "Feature",
  "properties": {
    "iso:country": "GB",
    "wof:name": "IV30 6DE",
    "wof:placetype": "postalcode"
  },
  "geometry": {"coordinates":[-3.310448,57.635658],"type":"Point"}
}
