{
  "type": "Feature",
  "properties": {
    "iso:country":"GB",
    "wof:name":"SK3 9QY",
    "wof:placetype":"postalcode"
},
  "geometry": {"coordinates":[-2.16893302721295,53.39631531117207],"type":"Point"}
}