{
  "type": "Feature",
  "properties": {
    "date:inception_lower": "1980-01-01",
    "date:inception_upper": "1980-01-01",
    "iso:country": "GB",
    "wof:name": "SK3 9QY",
    "wof:placetype": "postalcode"
  },
  "geometry": {"coordinates":[-2.168933,53.396315],"type":"Point"}
}
