{
  "type": "Feature",
  "properties": {
    "date:inception_lower": "2021-02-01",
    "date:inception_upper": "2021-02-01",
    "iso:country": "GB",
    "wof:name": "BB7 9EE",
    "wof:placetype": "postalcode"
  },
  "geometry": {"coordinates":[-2.405463,53.836609],"type":"Point"}
}
