{
  "type": "Feature",
  "properties": {
    "iso:country":"GB",
    "wof:name":"LU1 1RX",
    "wof:placetype":"postalcode"
},
  "geometry": {"coordinates":[-0.42178794390055,51.88220053605215],"type":"Point"}
}