{
  "type": "Feature",
  "properties": {
    "date:inception_lower": "2018-12-01",
    "date:inception_upper": "2018-12-01",
    "iso:country": "GB",
    "wof:name": "L9 1DF",
    "wof:placetype": "postalcode"
  },
  "geometry": {"coordinates":[-2.967349,53.452531],"type":"Point"}
}
