{
  "type": "Feature",
  "properties": {
    "iso:country": "GB",
    "wof:name": "L9 1DF",
    "wof:placetype": "postalcode"
  },
  "geometry": {"coordinates":[-2.967349,53.452531],"type":"Point"}
}
