{
  "type": "Feature",
  "properties": {
    "iso:country":"GB",
    "wof:name":"KA19 8BN",
    "wof:placetype":"postalcode"
},
  "geometry": {"coordinates":[-4.69406250578705,55.35034368695241],"type":"Point"}
}