{
  "type": "Feature",
  "properties": {
    "date:inception_lower": "1980-01-01",
    "date:inception_upper": "1980-01-01",
    "iso:country": "GB",
    "wof:name": "KA19 8BN",
    "wof:placetype": "postalcode"
  },
  "geometry": {"coordinates":[-4.69404,55.350348],"type":"Point"}
}
