{
  "type": "Feature",
  "properties": {
    "iso:country":"GB",
    "wof:name":"NW4 2DL",
    "wof:placetype":"postalcode"
},
  "geometry": {"coordinates":[-0.22271091279007,51.58636301545062],"type":"Point"}
}