{
  "type": "Feature",
  "properties": {
    "iso:country":"GB",
    "wof:name":"CF72 9ED",
    "wof:placetype":"postalcode"
},
  "geometry": {"coordinates":[-3.3916506115524,51.52286383450642],"type":"Point"}
}