{
  "type": "Feature",
  "properties": {
    "iso:country": "GB",
    "wof:name": "CF72 9ED",
    "wof:placetype": "postalcode"
  },
  "geometry": {"coordinates":[-3.391651,51.522864],"type":"Point"}
}
