{
  "type": "Feature",
  "properties": {
    "iso:country":"GB",
    "wof:name":"PO14 3HX",
    "wof:placetype":"postalcode"
},
  "geometry": {"coordinates":[-1.23529115401949,50.82023925263097],"type":"Point"}
}