{
  "type": "Feature",
  "properties": {
    "iso:country": "GB",
    "wof:name": "KY11 4ST",
    "wof:placetype": "postalcode"
  },
  "geometry": {"coordinates":[-3.44764,56.067204],"type":"Point"}
}
