{
  "type": "Feature",
  "properties": {
    "iso:country":"GB",
    "wof:name":"BA1 2EJ",
    "wof:placetype":"postalcode"
},
  "geometry": {"coordinates":[-2.36253271946648,51.38461816535643],"type":"Point"}
}