{
  "type": "Feature",
  "properties": {
    "iso:country": "GB",
    "wof:name": "W1F 9NY",
    "wof:placetype": "postalcode"
  },
  "geometry": {"coordinates":[-0.135748,51.511698],"type":"Point"}
}
