{
  "type": "Feature",
  "properties": {
    "iso:country":"GB",
    "wof:name":"W1F 9NY",
    "wof:placetype":"postalcode"
},
  "geometry": {"coordinates":[-0.13574828722119,51.51169829240133],"type":"Point"}
}