{
  "type": "Feature",
  "properties": {
    "date:inception_lower": "1999-06-01",
    "date:inception_upper": "1999-06-01",
    "iso:country": "GB",
    "wof:name": "CH66 4QN",
    "wof:placetype": "postalcode"
  },
  "geometry": {"coordinates":[-2.956147,53.282139],"type":"Point"}
}
