{
  "type": "Feature",
  "properties": {
    "iso:country":"GB",
    "wof:name":"DA16 3NX",
    "wof:placetype":"postalcode"
},
  "geometry": {"coordinates":[0.09336055849069,51.47092605776336],"type":"Point"}
}