{
  "type": "Feature",
  "properties": {
    "iso:country":"GB",
    "wof:name":"TA6 6BZ",
    "wof:placetype":"postalcode"
},
  "geometry": {"coordinates":[-2.99836460925552,51.11722094218796],"type":"Point"}
}