{
  "type": "Feature",
  "properties": {
    "iso:country": "GB",
    "wof:name": "TQ12 1EL",
    "wof:placetype": "postalcode"
  },
  "geometry": {"coordinates":[-3.612321,50.52183],"type":"Point"}
}
