{
  "type": "Feature",
  "properties": {
    "iso:country":"GB",
    "wof:name":"DA2 7LF",
    "wof:placetype":"postalcode"
},
  "geometry": {"coordinates":[0.25712448095216,51.42191460240863],"type":"Point"}
}