{
  "type": "Feature",
  "properties": {
    "iso:country":"GB",
    "wof:name":"CT17 0JG",
    "wof:placetype":"postalcode"
},
  "geometry": {"coordinates":[1.29060997772587,51.1375101332455],"type":"Point"}
}