{
  "type": "Feature",
  "properties": {
    "iso:country": "GB",
    "wof:name": "G12 9ED",
    "wof:placetype": "postalcode"
  },
  "geometry": {"coordinates":[-4.297666,55.874769],"type":"Point"}
}
