{
  "type": "Feature",
  "properties": {
    "iso:country": "GB",
    "wof:name": "CF3 5SY",
    "wof:placetype": "postalcode"
  },
  "geometry": {"coordinates":[-3.120948,51.519146],"type":"Point"}
}
