{
  "type": "Feature",
  "properties": {
    "date:inception_lower":"1999-06-01",
    "date:inception_upper":"1999-06-30",
    "iso:country":"GB",
    "wof:name":"CF3 5SY",
    "wof:placetype":"postalcode"
},
  "geometry": {"coordinates":[-3.120948,51.519146],"type":"Point"}
}