{
  "type": "Feature",
  "properties": {
    "iso:country":"GB",
    "wof:name":"EN4 0AY",
    "wof:placetype":"postalcode"
},
  "geometry": {"coordinates":[-0.14044553158533,51.64784607941144],"type":"Point"}
}