{
  "type": "Feature",
  "properties": {
    "iso:country": "GB",
    "wof:name": "BH20 5BB",
    "wof:placetype": "postalcode"
  },
  "geometry": {"coordinates":[-2.103279,50.671612],"type":"Point"}
}
