{
  "type": "Feature",
  "properties": {
    "iso:country":"GB",
    "wof:name":"BH20 5BB",
    "wof:placetype":"postalcode"
},
  "geometry": {"coordinates":[-2.10327904457883,50.67161221263254],"type":"Point"}
}