{
  "type": "Feature",
  "properties": {
    "date:inception_lower": "2002-12-01",
    "date:inception_upper": "2002-12-01",
    "iso:country": "GB",
    "wof:name": "CW9 8XW",
    "wof:placetype": "postalcode"
  },
  "geometry": {"coordinates":[-2.515048,53.247071],"type":"Point"}
}
