{
  "type": "Feature",
  "properties": {
    "iso:country":"GB",
    "wof:name":"MK10 9DD",
    "wof:placetype":"postalcode"
},
  "geometry": {"coordinates":[-0.69650383519896,52.03827261631396],"type":"Point"}
}