{
  "type": "Feature",
  "properties": {
    "date:inception_lower": "2021-08-01",
    "date:inception_upper": "2021-08-01",
    "iso:country": "GB",
    "wof:name": "M40 0BT",
    "wof:placetype": "postalcode"
  },
  "geometry": {"coordinates":[-2.178025,53.521078],"type":"Point"}
}
