{
  "type": "Feature",
  "properties": {
    "iso:country":"GB",
    "wof:name":"M44 6DL",
    "wof:placetype":"postalcode"
},
  "geometry": {"coordinates":[-2.41260666503349,53.44805298629548],"type":"Point"}
}