{
  "type": "Feature",
  "properties": {
    "date:inception_lower": "1980-01-01",
    "date:inception_upper": "1980-01-01",
    "iso:country": "GB",
    "wof:name": "WD5 0HD",
    "wof:placetype": "postalcode"
  },
  "geometry": {"coordinates":[-0.427,51.699341],"type":"Point"}
}
