{
  "type": "Feature",
  "properties": {
    "iso:country":"GB",
    "wof:name":"RH15 8JN",
    "wof:placetype":"postalcode"
},
  "geometry": {"coordinates":[-0.13170914652233,50.96013543085084],"type":"Point"}
}