{
  "type": "Feature",
  "properties": {
    "iso:country": "GB",
    "wof:name": "RH15 8JN",
    "wof:placetype": "postalcode"
  },
  "geometry": {"coordinates":[-0.131709,50.960135],"type":"Point"}
}
