{
  "type": "Feature",
  "properties": {
    "iso:country":"GB",
    "wof:name":"SS0 0AY",
    "wof:placetype":"postalcode"
},
  "geometry": {"coordinates":[0.67599490632259,51.55262429018696],"type":"Point"}
}