{
  "type": "Feature",
  "properties": {
    "iso:country":"GB",
    "wof:name":"SN12 6FT",
    "wof:placetype":"postalcode"
},
  "geometry": {"coordinates":[-2.12678013592903,51.36922261666147],"type":"Point"}
}