{
  "type": "Feature",
  "properties": {
    "iso:country":"GB",
    "wof:name":"SO16 8DH",
    "wof:placetype":"postalcode"
},
  "geometry": {"coordinates":[-1.42529031544037,50.94414007270544],"type":"Point"}
}