{
  "type": "Feature",
  "properties": {
    "iso:country":"GB",
    "wof:name":"RM16 6PT",
    "wof:placetype":"postalcode"
},
  "geometry": {"coordinates":[0.31126648105275,51.48887447176314],"type":"Point"}
}