{
  "type": "Feature",
  "properties": {
    "date:inception_lower": "1992-01-01",
    "date:inception_upper": "1992-01-01",
    "iso:country": "GB",
    "wof:name": "RM16 6PT",
    "wof:placetype": "postalcode"
  },
  "geometry": {"coordinates":[0.311267,51.488874],"type":"Point"}
}
