{
  "type": "Feature",
  "properties": {
    "iso:country":"GB",
    "wof:name":"CV23 0GY",
    "wof:placetype":"postalcode"
},
  "geometry": {"coordinates":[-1.23774563957795,52.39711783605895],"type":"Point"}
}