{
  "type": "Feature",
  "properties": {
    "date:inception_lower": "2010-01-01",
    "date:inception_upper": "2010-01-01",
    "iso:country": "GB",
    "wof:name": "CV23 0GY",
    "wof:placetype": "postalcode"
  },
  "geometry": {"coordinates":[-1.237746,52.397118],"type":"Point"}
}
