{
  "type": "Feature",
  "properties": {
    "iso:country": "GB",
    "wof:name": "CV23 0GY",
    "wof:placetype": "postalcode"
  },
  "geometry": {"coordinates":[-1.237746,52.397118],"type":"Point"}
}
