{
  "type": "Feature",
  "properties": {
    "iso:country":"GB",
    "wof:name":"BS5 0SA",
    "wof:placetype":"postalcode"
},
  "geometry": {"coordinates":[-2.57002362502935,51.46107561761662],"type":"Point"}
}