{
  "type": "Feature",
  "properties": {
    "iso:country":"GB",
    "wof:name":"HX4 9EW",
    "wof:placetype":"postalcode"
},
  "geometry": {"coordinates":[-1.87518279620674,53.67532389297185],"type":"Point"}
}