{
  "type": "Feature",
  "properties": {
    "date:inception_lower": "1980-01-01",
    "date:inception_upper": "1980-01-01",
    "iso:country": "GB",
    "wof:name": "BS27 3YL",
    "wof:placetype": "postalcode"
  },
  "geometry": {"coordinates":[-2.7493,51.267934],"type":"Point"}
}
