{
  "type": "Feature",
  "properties": {
    "iso:country":"GB",
    "wof:name":"BS27 3YL",
    "wof:placetype":"postalcode"
},
  "geometry": {"coordinates":[-2.74913760544872,51.26795696935957],"type":"Point"}
}