{
  "type": "Feature",
  "properties": {
    "iso:country":"GB",
    "wof:name":"BR3 6TF",
    "wof:placetype":"postalcode"
},
  "geometry": {"coordinates":[-0.02113667016821,51.40576569784741],"type":"Point"}
}