{
  "type": "Feature",
  "properties": {
    "date:inception_lower": "2005-02-01",
    "date:inception_upper": "2005-02-01",
    "iso:country": "GB",
    "wof:name": "DG10 9RR",
    "wof:placetype": "postalcode"
  },
  "geometry": {"coordinates":[-3.449245,55.336367],"type":"Point"}
}
