{
  "type": "Feature",
  "properties": {
    "date:inception_lower": "2015-10-01",
    "date:inception_upper": "2015-10-01",
    "iso:country": "GB",
    "wof:name": "CA25 5SU",
    "wof:placetype": "postalcode"
  },
  "geometry": {"coordinates":[-3.531281,54.530666],"type":"Point"}
}
