{
  "type": "Feature",
  "properties": {
    "iso:country":"GB",
    "wof:name":"CA25 5SU",
    "wof:placetype":"postalcode"
},
  "geometry": {"coordinates":[-3.53160361557004,54.53064444069526],"type":"Point"}
}