{
  "type": "Feature",
  "properties": {
    "iso:country": "GB",
    "wof:name": "LS26 0UG",
    "wof:placetype": "postalcode"
  },
  "geometry": {"coordinates":[-1.496962,53.754526],"type":"Point"}
}
