{
  "type": "Feature",
  "properties": {
    "iso:country":"GB",
    "wof:name":"SS7 4HB",
    "wof:placetype":"postalcode"
},
  "geometry": {"coordinates":[0.55606990171047,51.57268349558174],"type":"Point"}
}