{
  "type": "Feature",
  "properties": {
    "iso:country":"GB",
    "wof:name":"RM11 1JT",
    "wof:placetype":"postalcode"
},
  "geometry": {"coordinates":[0.20653773967199,51.5636450031373],"type":"Point"}
}