{
  "type": "Feature",
  "properties": {
    "iso:country": "GB",
    "wof:name": "EH9 1QG",
    "wof:placetype": "postalcode"
  },
  "geometry": {"coordinates":[-3.18067,55.937719],"type":"Point"}
}
