{
  "type": "Feature",
  "properties": {
    "iso:country": "GB",
    "wof:name": "BB10 2ND",
    "wof:placetype": "postalcode"
  },
  "geometry": {"coordinates":[-2.227599,53.820455],"type":"Point"}
}
