{
  "type": "Feature",
  "properties": {
    "date:inception_lower": "1980-01-01",
    "date:inception_upper": "1980-01-01",
    "iso:country": "GB",
    "wof:name": "BB10 2ND",
    "wof:placetype": "postalcode"
  },
  "geometry": {"coordinates":[-2.227599,53.820455],"type":"Point"}
}
