{
  "type": "Feature",
  "properties": {
    "iso:country":"GB",
    "wof:name":"BB10 2ND",
    "wof:placetype":"postalcode"
},
  "geometry": {"coordinates":[-2.22759912709189,53.82045477996763],"type":"Point"}
}