{
  "type": "Feature",
  "properties": {
    "iso:country":"GB",
    "wof:name":"CB8 0AX",
    "wof:placetype":"postalcode"
},
  "geometry": {"coordinates":[0.3893085942533,52.25517339069423],"type":"Point"}
}