{
  "type": "Feature",
  "properties": {
    "date:inception_lower": "1996-06-01",
    "date:inception_upper": "1996-06-01",
    "iso:country": "GB",
    "wof:name": "CB8 0AX",
    "wof:placetype": "postalcode"
  },
  "geometry": {"coordinates":[0.389309,52.255173],"type":"Point"}
}
