{
  "type": "Feature",
  "properties": {
    "date:inception_lower":"2003-08-01",
    "date:inception_upper":"2003-08-31",
    "iso:country":"GB",
    "wof:name":"CT1 3HW",
    "wof:placetype":"postalcode"
},
  "geometry": {"coordinates":[1.07304,51.270552],"type":"Point"}
}