{
  "type": "Feature",
  "properties": {
    "iso:country":"GB",
    "wof:name":"CT1 3HW",
    "wof:placetype":"postalcode"
},
  "geometry": {"coordinates":[1.07296582144671,51.27053126992325],"type":"Point"}
}