{
  "type": "Feature",
  "properties": {
    "iso:country": "GB",
    "wof:name": "CT1 3HW",
    "wof:placetype": "postalcode"
  },
  "geometry": {"coordinates":[1.07304,51.270552],"type":"Point"}
}
