{
  "type": "Feature",
  "properties": {
    "iso:country": "GB",
    "wof:name": "OX11 9NT",
    "wof:placetype": "postalcode"
  },
  "geometry": {"coordinates":[-1.22882,51.567054],"type":"Point"}
}
