{
  "type": "Feature",
  "properties": {
    "iso:country":"GB",
    "wof:name":"LN12 2DA",
    "wof:placetype":"postalcode"
},
  "geometry": {"coordinates":[0.26909005266565,53.3332282229523],"type":"Point"}
}