{
  "type": "Feature",
  "properties": {
    "iso:country":"GB",
    "wof:name":"AB51 0JP",
    "wof:placetype":"postalcode"
},
  "geometry": {"coordinates":[-2.35819813452652,57.31865784091813],"type":"Point"}
}