{
  "type": "Feature",
  "properties": {
    "iso:country": "GB",
    "wof:name": "TQ7 2JD",
    "wof:placetype": "postalcode"
  },
  "geometry": {"coordinates":[-3.703152,50.272799],"type":"Point"}
}
