{
  "type": "Feature",
  "properties": {
    "iso:country":"GB",
    "wof:name":"DD2 4PH",
    "wof:placetype":"postalcode"
},
  "geometry": {"coordinates":[-3.02933617010668,56.47482964123446],"type":"Point"}
}