{
  "type": "Feature",
  "properties": {
    "date:inception_lower":"2002-12-01",
    "date:inception_upper":"2002-12-31",
    "iso:country":"GB",
    "wof:name":"DD8 1XQ",
    "wof:placetype":"postalcode"
},
  "geometry": {"coordinates":[-2.927546,56.563841],"type":"Point"}
}