{
  "type": "Feature",
  "properties": {
    "iso:country": "GB",
    "wof:name": "DD8 1XQ",
    "wof:placetype": "postalcode"
  },
  "geometry": {"coordinates":[-2.927546,56.563841],"type":"Point"}
}
