{
  "type": "Feature",
  "properties": {
    "iso:country":"GB",
    "wof:name":"DL1 3AT",
    "wof:placetype":"postalcode"
},
  "geometry": {"coordinates":[-1.54630738775222,54.55222930842411],"type":"Point"}
}