{
  "type": "Feature",
  "properties": {
    "iso:country": "GB",
    "wof:name": "S60 9ZQ",
    "wof:placetype": "postalcode"
  },
  "geometry": {"coordinates":[-1.357404,53.434708],"type":"Point"}
}
