{
  "type": "Feature",
  "properties": {
    "iso:country":"GB",
    "wof:name":"OX29 0SG",
    "wof:placetype":"postalcode"
},
  "geometry": {"coordinates":[-1.54766314391522,51.79124019932316],"type":"Point"}
}