{
  "type": "Feature",
  "properties": {
    "iso:country": "GB",
    "wof:name": "OX29 0SG",
    "wof:placetype": "postalcode"
  },
  "geometry": {"coordinates":[-1.547663,51.79124],"type":"Point"}
}
