{
  "type": "Feature",
  "properties": {
    "iso:country":"GB",
    "wof:name":"PE16 6XN",
    "wof:placetype":"postalcode"
},
  "geometry": {"coordinates":[0.09991921695972,52.47587440949697],"type":"Point"}
}