{
  "type": "Feature",
  "properties": {
    "date:inception_lower": "1995-07-01",
    "date:inception_upper": "1995-07-01",
    "iso:country": "GB",
    "wof:name": "PE16 6XN",
    "wof:placetype": "postalcode"
  },
  "geometry": {"coordinates":[0.099919,52.475874],"type":"Point"}
}
