{
  "type": "Feature",
  "properties": {
    "date:inception_lower": "1992-08-01",
    "date:inception_upper": "1992-08-01",
    "iso:country": "GB",
    "wof:name": "DE72 3BD",
    "wof:placetype": "postalcode"
  },
  "geometry": {"coordinates":[-1.310279,52.902425],"type":"Point"}
}
