{
  "type": "Feature",
  "properties": {
    "iso:country":"GB",
    "wof:name":"DE72 3BD",
    "wof:placetype":"postalcode"
},
  "geometry": {"coordinates":[-1.31027875267531,52.90242516985738],"type":"Point"}
}