{
  "type": "Feature",
  "properties": {
    "iso:country": "GB",
    "wof:name": "CO2 8QD",
    "wof:placetype": "postalcode"
  },
  "geometry": {"coordinates":[0.90591,51.869994],"type":"Point"}
}
