{
  "type": "Feature",
  "properties": {
    "date:inception_lower": "1980-01-01",
    "date:inception_upper": "1980-01-01",
    "iso:country": "GB",
    "wof:name": "KA13 6DW",
    "wof:placetype": "postalcode"
  },
  "geometry": {"coordinates":[-4.698561,55.650252],"type":"Point"}
}
