{
  "type": "Feature",
  "properties": {
    "date:inception_lower": "1980-01-01",
    "date:inception_upper": "1980-01-01",
    "iso:country": "GB",
    "wof:name": "DA8 2DD",
    "wof:placetype": "postalcode"
  },
  "geometry": {"coordinates":[0.182639,51.468273],"type":"Point"}
}
