{
  "type": "Feature",
  "properties": {
    "iso:country":"GB",
    "wof:name":"N9 8HH",
    "wof:placetype":"postalcode"
},
  "geometry": {"coordinates":[-0.03948058987003,51.63775074763539],"type":"Point"}
}