{
  "type": "Feature",
  "properties": {
    "date:inception_lower":"1998-06-01",
    "date:inception_upper":"1998-06-30",
    "iso:country":"GB",
    "wof:name":"YO8 5TP",
    "wof:placetype":"postalcode"
},
  "geometry": {"coordinates":[-0.965112,53.823813],"type":"Point"}
}