{
  "type": "Feature",
  "properties": {
    "iso:country":"GB",
    "wof:name":"LE65 1BT",
    "wof:placetype":"postalcode"
},
  "geometry": {"coordinates":[-1.46807201315063,52.7473216520683],"type":"Point"}
}