{
  "type": "Feature",
  "properties": {
    "date:inception_lower":"1997-12-01",
    "date:inception_upper":"1997-12-31",
    "iso:country":"GB",
    "wof:name":"BS39 7XJ",
    "wof:placetype":"postalcode"
},
  "geometry": {"coordinates":[-2.511056,51.305512],"type":"Point"}
}