{
  "type": "Feature",
  "properties": {
    "iso:country":"GB",
    "wof:name":"BS39 7XJ",
    "wof:placetype":"postalcode"
},
  "geometry": {"coordinates":[-2.5110564573092,51.30551203217095],"type":"Point"}
}