{
  "type": "Feature",
  "properties": {
    "date:inception_lower": "2000-06-01",
    "date:inception_upper": "2000-06-01",
    "iso:country": "GB",
    "wof:name": "GU2 9RB",
    "wof:placetype": "postalcode"
  },
  "geometry": {"coordinates":[-0.587408,51.264345],"type":"Point"}
}
