{
  "type": "Feature",
  "properties": {
    "iso:country":"GB",
    "wof:name":"GU2 9RB",
    "wof:placetype":"postalcode"
},
  "geometry": {"coordinates":[-0.58740782520393,51.2643450125187],"type":"Point"}
}