{
  "type": "Feature",
  "properties": {
    "iso:country": "GB",
    "wof:name": "GU2 9RB",
    "wof:placetype": "postalcode"
  },
  "geometry": {"coordinates":[-0.587408,51.264345],"type":"Point"}
}
