{
  "type": "Feature",
  "properties": {
    "date:inception_lower": "1980-01-01",
    "date:inception_upper": "1980-01-01",
    "iso:country": "GB",
    "wof:name": "TA21 9QX",
    "wof:placetype": "postalcode"
  },
  "geometry": {"coordinates":[-3.268823,50.941834],"type":"Point"}
}
