{
  "type": "Feature",
  "properties": {
    "iso:country":"GB",
    "wof:name":"TA21 9QX",
    "wof:placetype":"postalcode"
},
  "geometry": {"coordinates":[-3.27596808854558,50.94535070343658],"type":"Point"}
}