{
  "type": "Feature",
  "properties": {
    "iso:country": "GB",
    "wof:name": "TA21 9QX",
    "wof:placetype": "postalcode"
  },
  "geometry": {"coordinates":[-3.275968,50.945351],"type":"Point"}
}
