{
  "type": "Feature",
  "properties": {
    "date:inception_lower":"1980-01-01",
    "date:inception_upper":"1980-01-31",
    "iso:country":"GB",
    "wof:name":"TA21 9QX",
    "wof:placetype":"postalcode"
},
  "geometry": {"coordinates":[-3.275968,50.945351],"type":"Point"}
}