{
  "type": "Feature",
  "properties": {
    "iso:country":"GB",
    "wof:name":"GU30 7LH",
    "wof:placetype":"postalcode"
},
  "geometry": {"coordinates":[-0.77787147661625,51.07421235237661],"type":"Point"}
}