{
  "type": "Feature",
  "properties": {
    "iso:country":"GB",
    "wof:name":"G69 9ES",
    "wof:placetype":"postalcode"
},
  "geometry": {"coordinates":[-4.10088060971474,55.89733862132881],"type":"Point"}
}