{
  "type": "Feature",
  "properties": {
    "iso:country": "GB",
    "wof:name": "HU18 1SZ",
    "wof:placetype": "postalcode"
  },
  "geometry": {"coordinates":[-0.16762,53.90218],"type":"Point"}
}
