{
  "type": "Feature",
  "properties": {
    "iso:country": "GB",
    "wof:name": "LL30 1TQ",
    "wof:placetype": "postalcode"
  },
  "geometry": {"coordinates":[-3.815277,53.320203],"type":"Point"}
}
