{
  "type": "Feature",
  "properties": {
    "date:inception_lower": "1990-02-01",
    "date:inception_upper": "1990-02-01",
    "iso:country": "GB",
    "wof:name": "LL30 1TQ",
    "wof:placetype": "postalcode"
  },
  "geometry": {"coordinates":[-3.815277,53.320203],"type":"Point"}
}
