{
  "type": "Feature",
  "properties": {
    "date:inception_lower":"1980-01-01",
    "date:inception_upper":"1980-01-31",
    "iso:country":"GB",
    "wof:name":"TQ7 3JT",
    "wof:placetype":"postalcode"
},
  "geometry": {"coordinates":[-3.847724,50.26871],"type":"Point"}
}