{
  "type": "Feature",
  "properties": {
    "iso:country":"GB",
    "wof:name":"TQ7 3JT",
    "wof:placetype":"postalcode"
},
  "geometry": {"coordinates":[-3.84772421910914,50.26870954655386],"type":"Point"}
}