{
  "type": "Feature",
  "properties": {
    "iso:country":"GB",
    "wof:name":"NP26 4NJ",
    "wof:placetype":"postalcode"
},
  "geometry": {"coordinates":[-2.75722593114458,51.59786586829112],"type":"Point"}
}