{
  "type": "Feature",
  "properties": {
    "date:inception_lower": "1999-06-01",
    "date:inception_upper": "1999-06-01",
    "iso:country": "GB",
    "wof:name": "NP26 4NJ",
    "wof:placetype": "postalcode"
  },
  "geometry": {"coordinates":[-2.757226,51.597866],"type":"Point"}
}
