{
  "type": "Feature",
  "properties": {
    "iso:country": "GB",
    "wof:name": "TN40 1JB",
    "wof:placetype": "postalcode"
  },
  "geometry": {"coordinates":[0.476394,50.83948],"type":"Point"}
}
