{
  "type": "Feature",
  "properties": {
    "iso:country":"GB",
    "wof:name":"GU34 2RX",
    "wof:placetype":"postalcode"
},
  "geometry": {"coordinates":[-0.97090260876952,51.146813679912],"type":"Point"}
}