{
  "type": "Feature",
  "properties": {
    "iso:country":"GB",
    "wof:name":"TS5 5HE",
    "wof:placetype":"postalcode"
},
  "geometry": {"coordinates":[-1.26082630777357,54.55721243144637],"type":"Point"}
}