{
  "type": "Feature",
  "properties": {
    "date:inception_lower": "1980-01-01",
    "date:inception_upper": "1980-01-01",
    "iso:country": "GB",
    "wof:name": "TS5 5HE",
    "wof:placetype": "postalcode"
  },
  "geometry": {"coordinates":[-1.260826,54.557212],"type":"Point"}
}
