{
  "type": "Feature",
  "properties": {
    "iso:country": "GB",
    "wof:name": "SA5 4AB",
    "wof:placetype": "postalcode"
  },
  "geometry": {"coordinates":[-3.97822,51.641878],"type":"Point"}
}
