{
  "type": "Feature",
  "properties": {
    "iso:country":"GB",
    "wof:name":"SA5 4AB",
    "wof:placetype":"postalcode"
},
  "geometry": {"coordinates":[-3.97822001819645,51.64187818865791],"type":"Point"}
}