{
  "type": "Feature",
  "properties": {
    "iso:country":"GB",
    "wof:name":"RM16 3BU",
    "wof:placetype":"postalcode"
},
  "geometry": {"coordinates":[0.38728328354055,51.50623694440755],"type":"Point"}
}