{
  "type": "Feature",
  "properties": {
    "iso:country":"GB",
    "wof:name":"SY23 4BQ",
    "wof:placetype":"postalcode"
},
  "geometry": {"coordinates":[-3.92946444188604,52.32501663780369],"type":"Point"}
}