{
  "type": "Feature",
  "properties": {
    "iso:country":"GB",
    "wof:name":"NN6 9SH",
    "wof:placetype":"postalcode"
},
  "geometry": {"coordinates":[-0.8420759557303,52.31718827179785],"type":"Point"}
}