{
  "type": "Feature",
  "properties": {
    "iso:country": "GB",
    "wof:name": "NN6 9SH",
    "wof:placetype": "postalcode"
  },
  "geometry": {"coordinates":[-0.842076,52.317188],"type":"Point"}
}
