{
  "type": "Feature",
  "properties": {
    "iso:country":"GB",
    "wof:name":"B67 6LB",
    "wof:placetype":"postalcode"
},
  "geometry": {"coordinates":[-1.98423060247279,52.48077932070601],"type":"Point"}
}