{
  "type": "Feature",
  "properties": {
    "iso:country":"GB",
    "wof:name":"DN37 0HR",
    "wof:placetype":"postalcode"
},
  "geometry": {"coordinates":[-0.09454527171349,53.51209884814471],"type":"Point"}
}