{
  "type": "Feature",
  "properties": {
    "iso:country": "GB",
    "wof:name": "DN37 0HR",
    "wof:placetype": "postalcode"
  },
  "geometry": {"coordinates":[-0.094545,53.512099],"type":"Point"}
}
