{
  "type": "Feature",
  "properties": {
    "date:inception_lower":"2016-01-01",
    "date:inception_upper":"2016-01-31",
    "iso:country":"GB",
    "wof:name":"NE13 9DR",
    "wof:placetype":"postalcode"
},
  "geometry": {"coordinates":[-1.635567,55.034188],"type":"Point"}
}