{
  "type": "Feature",
  "properties": {
    "iso:country":"GB",
    "wof:name":"BH8 9DQ",
    "wof:placetype":"postalcode"
},
  "geometry": {"coordinates":[-1.8563518285982,50.73806204285334],"type":"Point"}
}