{
  "type": "Feature",
  "properties": {
    "iso:country": "GB",
    "wof:name": "PE24 4PY",
    "wof:placetype": "postalcode"
  },
  "geometry": {"coordinates":[0.201967,53.130281],"type":"Point"}
}
