{
  "type": "Feature",
  "properties": {
    "date:inception_lower": "1980-01-01",
    "date:inception_upper": "1980-01-01",
    "iso:country": "GB",
    "wof:name": "PE33 0RP",
    "wof:placetype": "postalcode"
  },
  "geometry": {"coordinates":[0.439051,52.688737],"type":"Point"}
}
