{
  "type": "Feature",
  "properties": {
    "date:inception_lower": "1988-03-01",
    "date:inception_upper": "1988-03-01",
    "iso:country": "GB",
    "wof:name": "WR5 3RS",
    "wof:placetype": "postalcode"
  },
  "geometry": {"coordinates":[-2.213374,52.168396],"type":"Point"}
}
