{
  "type": "Feature",
  "properties": {
    "iso:country":"GB",
    "wof:name":"WR5 3RS",
    "wof:placetype":"postalcode"
},
  "geometry": {"coordinates":[-2.21349443423045,52.16831223580951],"type":"Point"}
}