{
  "type": "Feature",
  "properties": {
    "iso:country": "GB",
    "wof:name": "KA30 8HE",
    "wof:placetype": "postalcode"
  },
  "geometry": {"coordinates":[-4.849729,55.799764],"type":"Point"}
}
