{
  "type": "Feature",
  "properties": {
    "date:inception_lower": "1980-01-01",
    "date:inception_upper": "1980-01-01",
    "iso:country": "GB",
    "wof:name": "SW19 3PL",
    "wof:placetype": "postalcode"
  },
  "geometry": {"coordinates":[-0.211802,51.416321],"type":"Point"}
}
