{
  "type": "Feature",
  "properties": {
    "iso:country": "GB",
    "wof:name": "S17 4JE",
    "wof:placetype": "postalcode"
  },
  "geometry": {"coordinates":[-1.517192,53.319416],"type":"Point"}
}
