{
  "type": "Feature",
  "properties": {
    "date:inception_lower":"1991-09-01",
    "date:inception_upper":"1991-09-30",
    "iso:country":"GB",
    "wof:name":"BL5 2UW",
    "wof:placetype":"postalcode"
},
  "geometry": {"coordinates":[-2.529741,53.54171],"type":"Point"}
}