{
  "type": "Feature",
  "properties": {
    "iso:country": "GB",
    "wof:name": "BL5 2UW",
    "wof:placetype": "postalcode"
  },
  "geometry": {"coordinates":[-2.529741,53.54171],"type":"Point"}
}
