{
  "type": "Feature",
  "properties": {
    "iso:country":"GB",
    "wof:name":"LL12 9PS",
    "wof:placetype":"postalcode"
},
  "geometry": {"coordinates":[-3.0341882417493,53.11868268108857],"type":"Point"}
}