{
  "type": "Feature",
  "properties": {
    "iso:country":"GB",
    "wof:name":"DG1 1PB",
    "wof:placetype":"postalcode"
},
  "geometry": {"coordinates":[-3.59879851065512,55.07748014898409],"type":"Point"}
}