{
  "type": "Feature",
  "properties": {
    "date:inception_lower": "1973-08-01",
    "date:inception_upper": "1973-08-01",
    "iso:country": "GB",
    "wof:name": "DG11 1EJ",
    "wof:placetype": "postalcode"
  },
  "geometry": {"coordinates":[-3.403146,55.174897],"type":"Point"}
}
