{
  "type": "Feature",
  "properties": {
    "iso:country": "GB",
    "wof:name": "M46 6AW",
    "wof:placetype": "postalcode"
  },
  "geometry": {"coordinates":[-2.491417,53.522655],"type":"Point"}
}
