{
  "type": "Feature",
  "properties": {
    "iso:country":"GB",
    "wof:name":"RM9 4SU",
    "wof:placetype":"postalcode"
},
  "geometry": {"coordinates":[0.11863331472821,51.53807120683401],"type":"Point"}
}