{
  "type": "Feature",
  "properties": {
    "date:inception_lower":"1980-01-01",
    "date:inception_upper":"1980-01-31",
    "iso:country":"GB",
    "wof:name":"SK1 1PP",
    "wof:placetype":"postalcode"
},
  "geometry": {"coordinates":[-2.159365,53.411456],"type":"Point"}
}