{
  "type": "Feature",
  "properties": {
    "iso:country": "GB",
    "wof:name": "SK1 1PP",
    "wof:placetype": "postalcode"
  },
  "geometry": {"coordinates":[-2.159365,53.411456],"type":"Point"}
}
