{
  "type": "Feature",
  "properties": {
    "date:inception_lower": "1980-01-01",
    "date:inception_upper": "1980-01-01",
    "iso:country": "GB",
    "wof:name": "WF7 5EB",
    "wof:placetype": "postalcode"
  },
  "geometry": {"coordinates":[-1.347407,53.67221],"type":"Point"}
}
