{
  "type": "Feature",
  "properties": {
    "iso:country":"GB",
    "wof:name":"WF7 5EB",
    "wof:placetype":"postalcode"
},
  "geometry": {"coordinates":[-1.34740754701744,53.67220998500321],"type":"Point"}
}