{
  "type": "Feature",
  "properties": {
    "date:inception_lower": "1980-01-01",
    "date:inception_upper": "1980-01-01",
    "iso:country": "GB",
    "wof:name": "BL3 3EY",
    "wof:placetype": "postalcode"
  },
  "geometry": {"coordinates":[-2.434518,53.557401],"type":"Point"}
}
