{
  "type": "Feature",
  "properties": {
    "iso:country":"GB",
    "wof:name":"BL3 3EY",
    "wof:placetype":"postalcode"
},
  "geometry": {"coordinates":[-2.43451755381061,53.55740097587496],"type":"Point"}
}