{
  "type": "Feature",
  "properties": {
    "iso:country": "GB",
    "wof:name": "NG19 0BG",
    "wof:placetype": "postalcode"
  },
  "geometry": {"coordinates":[-1.160072,53.152838],"type":"Point"}
}
