{
  "type": "Feature",
  "properties": {
    "iso:country":"GB",
    "wof:name":"YO8 8AP",
    "wof:placetype":"postalcode"
},
  "geometry": {"coordinates":[-1.05232519522244,53.78018561774635],"type":"Point"}
}