{
  "type": "Feature",
  "properties": {
    "date:inception_lower":"2004-04-01",
    "date:inception_upper":"2004-04-30",
    "iso:country":"GB",
    "wof:name":"EH14 1PN",
    "wof:placetype":"postalcode"
},
  "geometry": {"coordinates":[-3.237451,55.93009],"type":"Point"}
}