{
  "type": "Feature",
  "properties": {
    "iso:country": "GB",
    "wof:name": "EH14 1PN",
    "wof:placetype": "postalcode"
  },
  "geometry": {"coordinates":[-3.237451,55.93009],"type":"Point"}
}
