{
  "type": "Feature",
  "properties": {
    "iso:country":"GB",
    "wof:name":"DT4 7JN",
    "wof:placetype":"postalcode"
},
  "geometry": {"coordinates":[-2.45586738187661,50.61884102207105],"type":"Point"}
}