{
  "type": "Feature",
  "properties": {
    "iso:country": "GB",
    "wof:name": "DT4 7JN",
    "wof:placetype": "postalcode"
  },
  "geometry": {"coordinates":[-2.455779,50.61884],"type":"Point"}
}
