{
  "type": "Feature",
  "properties": {
    "iso:country":"GB",
    "wof:name":"SL6 4AU",
    "wof:placetype":"postalcode"
},
  "geometry": {"coordinates":[-0.74134698964432,51.51682806925466],"type":"Point"}
}