{
  "type": "Feature",
  "properties": {
    "iso:country":"GB",
    "wof:name":"IV36 1GA",
    "wof:placetype":"postalcode"
},
  "geometry": {"coordinates":[-3.62455210551064,57.60285896845318],"type":"Point"}
}