{
  "type": "Feature",
  "properties": {
    "iso:country":"GB",
    "wof:name":"HA9 0BP",
    "wof:placetype":"postalcode"
},
  "geometry": {"coordinates":[-0.27841829807196,51.56031549054161],"type":"Point"}
}