{
  "type": "Feature",
  "properties": {
    "date:inception_lower": "2008-04-01",
    "date:inception_upper": "2008-04-01",
    "iso:country": "GB",
    "wof:name": "HA9 0BP",
    "wof:placetype": "postalcode"
  },
  "geometry": {"coordinates":[-0.278418,51.560315],"type":"Point"}
}
