{
  "type": "Feature",
  "properties": {
    "iso:country":"GB",
    "wof:name":"RM15 5RF",
    "wof:placetype":"postalcode"
},
  "geometry": {"coordinates":[0.28406984958174,51.50444388223413],"type":"Point"}
}