{
  "type": "Feature",
  "properties": {
    "date:inception_lower": "2000-06-01",
    "date:inception_upper": "2000-06-01",
    "iso:country": "GB",
    "wof:name": "TS9 6SE",
    "wof:placetype": "postalcode"
  },
  "geometry": {"coordinates":[-1.130781,54.487366],"type":"Point"}
}
