{
  "type": "Feature",
  "properties": {
    "iso:country":"GB",
    "wof:name":"TS9 6SE",
    "wof:placetype":"postalcode"
},
  "geometry": {"coordinates":[-1.13079880063242,54.48735373094083],"type":"Point"}
}