{
  "type": "Feature",
  "properties": {
    "iso:country": "GB",
    "wof:name": "TS9 6SE",
    "wof:placetype": "postalcode"
  },
  "geometry": {"coordinates":[-1.130781,54.487366],"type":"Point"}
}
