{
  "type": "Feature",
  "properties": {
    "iso:country": "GB",
    "wof:name": "E1 4RB",
    "wof:placetype": "postalcode"
  },
  "geometry": {"coordinates":[-0.042703,51.521882],"type":"Point"}
}
