{
  "type": "Feature",
  "properties": {
    "iso:country": "GB",
    "wof:name": "DD3 9DJ",
    "wof:placetype": "postalcode"
  },
  "geometry": {"coordinates":[-3.000741,56.493679],"type":"Point"}
}
