{
  "type": "Feature",
  "properties": {
    "iso:country":"GB",
    "wof:name":"HR6 8BH",
    "wof:placetype":"postalcode"
},
  "geometry": {"coordinates":[-2.73359228399121,52.22130865661242],"type":"Point"}
}