{
  "type": "Feature",
  "properties": {
    "iso:country": "GB",
    "wof:name": "HR6 8BH",
    "wof:placetype": "postalcode"
  },
  "geometry": {"coordinates":[-2.733592,52.221309],"type":"Point"}
}
