{
  "type": "Feature",
  "properties": {
    "iso:country":"GB",
    "wof:name":"FY1 2DX",
    "wof:placetype":"postalcode"
},
  "geometry": {"coordinates":[-3.05067255211824,53.8243548159029],"type":"Point"}
}