{
  "type": "Feature",
  "properties": {
    "date:inception_lower":"1980-01-01",
    "date:inception_upper":"1980-01-31",
    "iso:country":"GB",
    "wof:name":"FY1 2DX",
    "wof:placetype":"postalcode"
},
  "geometry": {"coordinates":[-3.050673,53.824355],"type":"Point"}
}