{
  "type": "Feature",
  "properties": {
    "iso:country":"GB",
    "wof:name":"IP28 6SQ",
    "wof:placetype":"postalcode"
},
  "geometry": {"coordinates":[0.54328782363824,52.31619758638643],"type":"Point"}
}