{
  "type": "Feature",
  "properties": {
    "iso:country":"GB",
    "wof:name":"NN7 1AT",
    "wof:placetype":"postalcode"
},
  "geometry": {"coordinates":[-0.73395779564227,52.20069063698366],"type":"Point"}
}