{
  "type": "Feature",
  "properties": {
    "date:inception_lower":"2015-03-01",
    "date:inception_upper":"2015-03-31",
    "iso:country":"GB",
    "wof:name":"NN7 1AT",
    "wof:placetype":"postalcode"
},
  "geometry": {"coordinates":[-0.733975,52.200601],"type":"Point"}
}