{
  "type": "Feature",
  "properties": {
    "iso:country": "GB",
    "wof:name": "B76 9QR",
    "wof:placetype": "postalcode"
  },
  "geometry": {"coordinates":[-1.738096,52.553076],"type":"Point"}
}
