{
  "type": "Feature",
  "properties": {
    "iso:country":"GB",
    "wof:name":"B76 9QR",
    "wof:placetype":"postalcode"
},
  "geometry": {"coordinates":[-1.73809590836397,52.5530757087997],"type":"Point"}
}