{
  "type": "Feature",
  "properties": {
    "iso:country":"GB",
    "wof:name":"G66 2HJ",
    "wof:placetype":"postalcode"
},
  "geometry": {"coordinates":[-4.11694985019981,55.94507223325751],"type":"Point"}
}