{
  "type": "Feature",
  "properties": {
    "date:inception_lower": "1989-07-01",
    "date:inception_upper": "1989-07-01",
    "iso:country": "GB",
    "wof:name": "G66 2HJ",
    "wof:placetype": "postalcode"
  },
  "geometry": {"coordinates":[-4.11695,55.945072],"type":"Point"}
}
