{
  "type": "Feature",
  "properties": {
    "iso:country":"GB",
    "wof:name":"CR7 8FB",
    "wof:placetype":"postalcode"
},
  "geometry": {"coordinates":[-0.1128376656096,51.4114509735166],"type":"Point"}
}