{
  "type": "Feature",
  "properties": {
    "date:inception_lower": "1996-06-01",
    "date:inception_upper": "1996-06-01",
    "iso:country": "GB",
    "wof:name": "CR7 8FB",
    "wof:placetype": "postalcode"
  },
  "geometry": {"coordinates":[-0.112838,51.411451],"type":"Point"}
}
