{
  "type": "Feature",
  "properties": {
    "iso:country":"GB",
    "wof:name":"S36 6FB",
    "wof:placetype":"postalcode"
},
  "geometry": {"coordinates":[-1.62377307459393,53.52250059559316],"type":"Point"}
}