{
  "type": "Feature",
  "properties": {
    "iso:country":"GB",
    "wof:name":"BL6 5HD",
    "wof:placetype":"postalcode"
},
  "geometry": {"coordinates":[-2.58844339940459,53.59509606465477],"type":"Point"}
}