{
  "type": "Feature",
  "properties": {
    "iso:country":"GB",
    "wof:name":"YO31 8RH",
    "wof:placetype":"postalcode"
},
  "geometry": {"coordinates":[-1.07395461626306,53.96595188211266],"type":"Point"}
}