{
  "type": "Feature",
  "properties": {
    "iso:country": "GB",
    "wof:name": "HP15 6HU",
    "wof:placetype": "postalcode"
  },
  "geometry": {"coordinates":[-0.722325,51.676254],"type":"Point"}
}
