{
  "type": "Feature",
  "properties": {
    "date:inception_lower":"1984-10-01",
    "date:inception_upper":"1984-10-31",
    "iso:country":"GB",
    "wof:name":"HP15 6HU",
    "wof:placetype":"postalcode"
},
  "geometry": {"coordinates":[-0.722325,51.676254],"type":"Point"}
}