{
  "type": "Feature",
  "properties": {
    "iso:country": "GB",
    "wof:name": "DA7 6SP",
    "wof:placetype": "postalcode"
  },
  "geometry": {"coordinates":[0.174436,51.46686],"type":"Point"}
}
