{
  "type": "Feature",
  "properties": {
    "date:inception_lower":"1980-01-01",
    "date:inception_upper":"1980-01-31",
    "iso:country":"GB",
    "wof:name":"DA7 6SP",
    "wof:placetype":"postalcode"
},
  "geometry": {"coordinates":[0.174436,51.46686],"type":"Point"}
}