{
  "type": "Feature",
  "properties": {
    "iso:country": "GB",
    "wof:name": "TW6 2SD",
    "wof:placetype": "postalcode"
  },
  "geometry": {"coordinates":[-0.425436,51.479328],"type":"Point"}
}
