{
  "type": "Feature",
  "properties": {
    "iso:country":"GB",
    "wof:name":"TW6 2SD",
    "wof:placetype":"postalcode"
},
  "geometry": {"coordinates":[-0.42543597283825,51.47932838439566],"type":"Point"}
}