{
  "type": "Feature",
  "properties": {
    "iso:country":"GB",
    "wof:name":"M14 5JQ",
    "wof:placetype":"postalcode"
},
  "geometry": {"coordinates":[-2.22020396326356,53.44959662649673],"type":"Point"}
}