{
  "type": "Feature",
  "properties": {
    "date:inception_lower": "2016-08-01",
    "date:inception_upper": "2016-08-01",
    "iso:country": "GB",
    "wof:name": "BS8 2BD",
    "wof:placetype": "postalcode"
  },
  "geometry": {"coordinates":[-2.610423,51.46159],"type":"Point"}
}
