{
  "type": "Feature",
  "properties": {
    "date:inception_lower": "2007-09-01",
    "date:inception_upper": "2007-09-01",
    "iso:country": "GB",
    "wof:name": "IV51 9TR",
    "wof:placetype": "postalcode"
  },
  "geometry": {"coordinates":[-6.2039,57.418019],"type":"Point"}
}
