{
  "type": "Feature",
  "properties": {
    "iso:country":"GB",
    "wof:name":"IV51 9TR",
    "wof:placetype":"postalcode"
},
  "geometry": {"coordinates":[-6.20389979615737,57.41801910751258],"type":"Point"}
}