{
  "type": "Feature",
  "properties": {
    "iso:country":"GB",
    "wof:name":"NR3 3DX",
    "wof:placetype":"postalcode"
},
  "geometry": {"coordinates":[1.29265153449325,52.63194473384738],"type":"Point"}
}