{
  "type": "Feature",
  "properties": {
    "iso:country":"GB",
    "wof:name":"SE15 5TR",
    "wof:placetype":"postalcode"
},
  "geometry": {"coordinates":[-0.06521860787601,51.47459450658452],"type":"Point"}
}