{
  "type": "Feature",
  "properties": {
    "iso:country": "GB",
    "wof:name": "SE15 5TR",
    "wof:placetype": "postalcode"
  },
  "geometry": {"coordinates":[-0.065219,51.474595],"type":"Point"}
}
