{
  "type": "Feature",
  "properties": {
    "iso:country":"GB",
    "wof:name":"CH44 6LG",
    "wof:placetype":"postalcode"
},
  "geometry": {"coordinates":[-3.02342317123981,53.41280241675171],"type":"Point"}
}