{
  "type": "Feature",
  "properties": {
    "date:inception_lower": "1980-01-01",
    "date:inception_upper": "1980-01-01",
    "iso:country": "GB",
    "wof:name": "SN8 2JB",
    "wof:placetype": "postalcode"
  },
  "geometry": {"coordinates":[-1.598666,51.496952],"type":"Point"}
}
