{
  "type": "Feature",
  "properties": {
    "iso:country": "GB",
    "wof:name": "SN8 2JB",
    "wof:placetype": "postalcode"
  },
  "geometry": {"coordinates":[-1.598666,51.496952],"type":"Point"}
}
