{
  "type": "Feature",
  "properties": {
    "iso:country":"GB",
    "wof:name":"YO16 6XZ",
    "wof:placetype":"postalcode"
},
  "geometry": {"coordinates":[-0.1883247509527,54.10061206728125],"type":"Point"}
}