{
  "type": "Feature",
  "properties": {
    "date:inception_lower": "1998-06-01",
    "date:inception_upper": "1998-06-01",
    "iso:country": "GB",
    "wof:name": "YO16 6XZ",
    "wof:placetype": "postalcode"
  },
  "geometry": {"coordinates":[-0.188325,54.100612],"type":"Point"}
}
