{
  "type": "Feature",
  "properties": {
    "iso:country": "GB",
    "wof:name": "LL61 5EX",
    "wof:placetype": "postalcode"
  },
  "geometry": {"coordinates":[-4.204629,53.225281],"type":"Point"}
}
