{
  "type": "Feature",
  "properties": {
    "iso:country":"GB",
    "wof:name":"LL61 5EX",
    "wof:placetype":"postalcode"
},
  "geometry": {"coordinates":[-4.20462953183844,53.22528099375283],"type":"Point"}
}