{
  "type": "Feature",
  "properties": {
    "iso:country": "GB",
    "wof:name": "DG1 4RQ",
    "wof:placetype": "postalcode"
  },
  "geometry": {"coordinates":[-3.544526,54.979582],"type":"Point"}
}
