{
  "type": "Feature",
  "properties": {
    "date:inception_lower":"1997-12-01",
    "date:inception_upper":"1997-12-31",
    "iso:country":"GB",
    "wof:name":"L3 5XZ",
    "wof:placetype":"postalcode"
},
  "geometry": {"coordinates":[-2.970889,53.406311],"type":"Point"}
}