{
  "type": "Feature",
  "properties": {
    "date:inception_lower": "1980-01-01",
    "date:inception_upper": "1980-01-01",
    "iso:country": "GB",
    "wof:name": "CF31 4BJ",
    "wof:placetype": "postalcode"
  },
  "geometry": {"coordinates":[-3.588667,51.504624],"type":"Point"}
}
