{
  "type": "Feature",
  "properties": {
    "date:inception_lower": "1995-07-01",
    "date:inception_upper": "1995-07-01",
    "iso:country": "GB",
    "wof:name": "RG6 1DH",
    "wof:placetype": "postalcode"
  },
  "geometry": {"coordinates":[-0.933089,51.451892],"type":"Point"}
}
