{
  "type": "Feature",
  "properties": {
    "iso:country":"GB",
    "wof:name":"B93 9DW",
    "wof:placetype":"postalcode"
},
  "geometry": {"coordinates":[-1.7386069030754,52.39726234406234],"type":"Point"}
}