{
  "type": "Feature",
  "properties": {
    "iso:country":"GB",
    "wof:name":"TS10 2AQ",
    "wof:placetype":"postalcode"
},
  "geometry": {"coordinates":[-1.06615005265491,54.61530802661729],"type":"Point"}
}