{
  "type": "Feature",
  "properties": {
    "iso:country":"GB",
    "wof:name":"HP13 6EZ",
    "wof:placetype":"postalcode"
},
  "geometry": {"coordinates":[-0.74080882596006,51.63034429740098],"type":"Point"}
}