{
  "type": "Feature",
  "properties": {
    "iso:country":"GB",
    "wof:name":"TN17 4AF",
    "wof:placetype":"postalcode"
},
  "geometry": {"coordinates":[0.57520449404143,51.07566779129114],"type":"Point"}
}