{
  "type": "Feature",
  "properties": {
    "iso:country": "GB",
    "wof:name": "NR11 7DF",
    "wof:placetype": "postalcode"
  },
  "geometry": {"coordinates":[1.166118,52.823715],"type":"Point"}
}
