{
  "type": "Feature",
  "properties": {
    "iso:country":"GB",
    "wof:name":"NR11 7DF",
    "wof:placetype":"postalcode"
},
  "geometry": {"coordinates":[1.16611768760592,52.82371503507954],"type":"Point"}
}