{
  "type": "Feature",
  "properties": {
    "iso:country":"GB",
    "wof:name":"SA11 1HS",
    "wof:placetype":"postalcode"
},
  "geometry": {"coordinates":[-3.80234273778484,51.65863051077266],"type":"Point"}
}