{
  "type": "Feature",
  "properties": {
    "date:inception_lower":"1986-09-01",
    "date:inception_upper":"1986-09-30",
    "iso:country":"GB",
    "wof:name":"G41 2SJ",
    "wof:placetype":"postalcode"
},
  "geometry": {"coordinates":[-4.269782,55.841844],"type":"Point"}
}