{
  "type": "Feature",
  "properties": {
    "iso:country":"GB",
    "wof:name":"ME7 1BB",
    "wof:placetype":"postalcode"
},
  "geometry": {"coordinates":[0.5429607642999,51.38907883862439],"type":"Point"}
}