{
  "type": "Feature",
  "properties": {
    "iso:country":"GB",
    "wof:name":"OX25 5PP",
    "wof:placetype":"postalcode"
},
  "geometry": {"coordinates":[-1.311553269385,51.93556168053955],"type":"Point"}
}