{
  "type": "Feature",
  "properties": {
    "iso:country":"GB",
    "wof:name":"NG6 7GB",
    "wof:placetype":"postalcode"
},
  "geometry": {"coordinates":[-1.2168513189076,53.00225854822398],"type":"Point"}
}