{
  "type": "Feature",
  "properties": {
    "iso:country": "GB",
    "wof:name": "IP31 1JA",
    "wof:placetype": "postalcode"
  },
  "geometry": {"coordinates":[0.730953,52.29152],"type":"Point"}
}
