{
  "type": "Feature",
  "properties": {
    "date:inception_lower": "1991-01-01",
    "date:inception_upper": "1991-01-01",
    "iso:country": "GB",
    "wof:name": "DE55 3LE",
    "wof:placetype": "postalcode"
  },
  "geometry": {"coordinates":[-1.339517,53.094208],"type":"Point"}
}
