{
  "type": "Feature",
  "properties": {
    "iso:country":"GB",
    "wof:name":"OX18 4AW",
    "wof:placetype":"postalcode"
},
  "geometry": {"coordinates":[-1.62704752664916,51.7714954859052],"type":"Point"}
}