{
  "type": "Feature",
  "properties": {
    "iso:country":"GB",
    "wof:name":"BH24 1UG",
    "wof:placetype":"postalcode"
},
  "geometry": {"coordinates":[-1.76658095661453,50.85431691341565],"type":"Point"}
}