{
  "type": "Feature",
  "properties": {
    "date:inception_lower": "2009-01-01",
    "date:inception_upper": "2009-01-01",
    "iso:country": "GB",
    "wof:name": "BD23 6BB",
    "wof:placetype": "postalcode"
  },
  "geometry": {"coordinates":[-1.980627,54.052302],"type":"Point"}
}
