{
  "type": "Feature",
  "properties": {
    "iso:country":"GB",
    "wof:name":"BD23 6BB",
    "wof:placetype":"postalcode"
},
  "geometry": {"coordinates":[-1.9806271047578,54.05230185926835],"type":"Point"}
}