{
  "type": "Feature",
  "properties": {
    "iso:country": "GB",
    "wof:name": "SA45 9NH",
    "wof:placetype": "postalcode"
  },
  "geometry": {"coordinates":[-4.35893,52.214823],"type":"Point"}
}
