{
  "type": "Feature",
  "properties": {
    "iso:country":"GB",
    "wof:name":"PH10 7JP",
    "wof:placetype":"postalcode"
},
  "geometry": {"coordinates":[-3.38844296035317,56.65295313180633],"type":"Point"}
}