{
  "type": "Feature",
  "properties": {
    "date:inception_lower": "2010-07-01",
    "date:inception_upper": "2010-07-01",
    "iso:country": "GB",
    "wof:name": "WA5 0EX",
    "wof:placetype": "postalcode"
  },
  "geometry": {"coordinates":[-2.608013,53.396261],"type":"Point"}
}
