{
  "type": "Feature",
  "properties": {
    "iso:country":"GB",
    "wof:name":"IG1 2NB",
    "wof:placetype":"postalcode"
},
  "geometry": {"coordinates":[0.07613850249163,51.54730219026718],"type":"Point"}
}