{
  "type": "Feature",
  "properties": {
    "iso:country":"GB",
    "wof:name":"RM14 2AY",
    "wof:placetype":"postalcode"
},
  "geometry": {"coordinates":[0.24604340075485,51.55105160948151],"type":"Point"}
}