{
  "type": "Feature",
  "properties": {
    "date:inception_lower":"1993-01-01",
    "date:inception_upper":"1993-01-31",
    "iso:country":"GB",
    "wof:name":"NG19 9EH",
    "wof:placetype":"postalcode"
},
  "geometry": {"coordinates":[-1.178296,53.17657],"type":"Point"}
}