{
  "type": "Feature",
  "properties": {
    "iso:country":"GB",
    "wof:name":"L36 7TJ",
    "wof:placetype":"postalcode"
},
  "geometry": {"coordinates":[-2.83759408298904,53.41763955175355],"type":"Point"}
}