{
  "type": "Feature",
  "properties": {
    "date:inception_lower":"1980-01-01",
    "date:inception_upper":"1980-01-31",
    "iso:country":"GB",
    "wof:name":"L36 7TJ",
    "wof:placetype":"postalcode"
},
  "geometry": {"coordinates":[-2.837594,53.41764],"type":"Point"}
}