{
  "type": "Feature",
  "properties": {
    "iso:country": "GB",
    "wof:name": "LA14 4QG",
    "wof:placetype": "postalcode"
  },
  "geometry": {"coordinates":[-3.201757,54.15845],"type":"Point"}
}
