{
  "type": "Feature",
  "properties": {
    "date:inception_lower":"1980-01-01",
    "date:inception_upper":"1980-01-31",
    "iso:country":"GB",
    "wof:name":"LA14 4QG",
    "wof:placetype":"postalcode"
},
  "geometry": {"coordinates":[-3.201757,54.15845],"type":"Point"}
}