{
  "type": "Feature",
  "properties": {
    "date:inception_lower": "1996-12-01",
    "date:inception_upper": "1996-12-01",
    "iso:country": "GB",
    "wof:name": "RG40 1XZ",
    "wof:placetype": "postalcode"
  },
  "geometry": {"coordinates":[-0.833913,51.411195],"type":"Point"}
}
