{
  "type": "Feature",
  "properties": {
    "iso:country":"GB",
    "wof:name":"RG40 1XZ",
    "wof:placetype":"postalcode"
},
  "geometry": {"coordinates":[-0.83384619240388,51.41113060926385],"type":"Point"}
}