{
  "type": "Feature",
  "properties": {
    "date:inception_lower":"1980-01-01",
    "date:inception_upper":"1980-01-31",
    "iso:country":"GB",
    "wof:name":"FY6 0JA",
    "wof:placetype":"postalcode"
},
  "geometry": {"coordinates":[-2.967376,53.906103],"type":"Point"}
}