{
  "type": "Feature",
  "properties": {
    "iso:country":"GB",
    "wof:name":"LE11 2SS",
    "wof:placetype":"postalcode"
},
  "geometry": {"coordinates":[-1.21249687330586,52.75546587069059],"type":"Point"}
}