{
  "type": "Feature",
  "properties": {
    "date:inception_lower": "1980-01-01",
    "date:inception_upper": "1980-01-01",
    "iso:country": "GB",
    "wof:name": "LE11 2SS",
    "wof:placetype": "postalcode"
  },
  "geometry": {"coordinates":[-1.21249,52.755485],"type":"Point"}
}
