{
  "type": "Feature",
  "properties": {
    "iso:country": "GB",
    "wof:name": "WF13 3RJ",
    "wof:placetype": "postalcode"
  },
  "geometry": {"coordinates":[-1.64918,53.682336],"type":"Point"}
}
