{
  "type": "Feature",
  "properties": {
    "date:inception_lower": "1980-01-01",
    "date:inception_upper": "1980-01-01",
    "iso:country": "GB",
    "wof:name": "WF13 3RJ",
    "wof:placetype": "postalcode"
  },
  "geometry": {"coordinates":[-1.64918,53.682336],"type":"Point"}
}
