{
  "type": "Feature",
  "properties": {
    "iso:country":"GB",
    "wof:name":"HA3 5PX",
    "wof:placetype":"postalcode"
},
  "geometry": {"coordinates":[-0.34735086246702,51.60242784096836],"type":"Point"}
}