{
  "type": "Feature",
  "properties": {
    "iso:country": "GB",
    "wof:name": "HA3 5PX",
    "wof:placetype": "postalcode"
  },
  "geometry": {"coordinates":[-0.347351,51.602428],"type":"Point"}
}
