{
  "type": "Feature",
  "properties": {
    "iso:country": "GB",
    "wof:name": "SL2 4DR",
    "wof:placetype": "postalcode"
  },
  "geometry": {"coordinates":[-0.584924,51.554206],"type":"Point"}
}
