{
  "type": "Feature",
  "properties": {
    "iso:country": "GB",
    "wof:name": "HD2 2TN",
    "wof:placetype": "postalcode"
  },
  "geometry": {"coordinates":[-1.792334,53.66034],"type":"Point"}
}
