{
  "type": "Feature",
  "properties": {
    "date:inception_lower": "2018-06-01",
    "date:inception_upper": "2018-06-01",
    "iso:country": "GB",
    "wof:name": "GU25 9BQ",
    "wof:placetype": "postalcode"
  },
  "geometry": {"coordinates":[-0.562759,51.40134],"type":"Point"}
}
