{
  "type": "Feature",
  "properties": {
    "iso:country": "GB",
    "wof:name": "CA7 5DZ",
    "wof:placetype": "postalcode"
  },
  "geometry": {"coordinates":[-3.166162,54.933203],"type":"Point"}
}
