{
  "type": "Feature",
  "properties": {
    "iso:country":"GB",
    "wof:name":"CA7 5DZ",
    "wof:placetype":"postalcode"
},
  "geometry": {"coordinates":[-3.16616228153409,54.93320308134079],"type":"Point"}
}