{
  "type": "Feature",
  "properties": {
    "iso:country":"GB",
    "wof:name":"WA9 3SF",
    "wof:placetype":"postalcode"
},
  "geometry": {"coordinates":[-2.69282665831434,53.44500318073746],"type":"Point"}
}