{
  "type": "Feature",
  "properties": {
    "date:inception_lower": "2009-03-01",
    "date:inception_upper": "2009-03-01",
    "iso:country": "GB",
    "wof:name": "G23 5NF",
    "wof:placetype": "postalcode"
  },
  "geometry": {"coordinates":[-4.285555,55.906702],"type":"Point"}
}
