{
  "type": "Feature",
  "properties": {
    "iso:country":"GB",
    "wof:name":"G23 5NF",
    "wof:placetype":"postalcode"
},
  "geometry": {"coordinates":[-4.28555473274029,55.90670204799527],"type":"Point"}
}