{
  "type": "Feature",
  "properties": {
    "iso:country":"GB",
    "wof:name":"PL2 3NA",
    "wof:placetype":"postalcode"
},
  "geometry": {"coordinates":[-4.15078528920948,50.39608121275501],"type":"Point"}
}