{
  "type": "Feature",
  "properties": {
    "iso:country": "GB",
    "wof:name": "CV6 5NL",
    "wof:placetype": "postalcode"
  },
  "geometry": {"coordinates":[-1.50325,52.423172],"type":"Point"}
}
