{
  "type": "Feature",
  "properties": {
    "date:inception_lower":"2017-07-01",
    "date:inception_upper":"2017-07-31",
    "iso:country":"GB",
    "wof:name":"CV6 5NL",
    "wof:placetype":"postalcode"
},
  "geometry": {"coordinates":[-1.50325,52.423172],"type":"Point"}
}