{
  "type": "Feature",
  "properties": {
    "date:inception_lower": "1992-08-01",
    "date:inception_upper": "1992-08-01",
    "iso:country": "GB",
    "wof:name": "WA7 5XT",
    "wof:placetype": "postalcode"
  },
  "geometry": {"coordinates":[-2.713323,53.339211],"type":"Point"}
}
