{
  "type": "Feature",
  "properties": {
    "iso:country":"GB",
    "wof:name":"LS7 4ER",
    "wof:placetype":"postalcode"
},
  "geometry": {"coordinates":[-1.52846203878991,53.81685133761585],"type":"Point"}
}