{
  "type": "Feature",
  "properties": {
    "iso:country":"GB",
    "wof:name":"IP28 7EA",
    "wof:placetype":"postalcode"
},
  "geometry": {"coordinates":[0.51012208957819,52.34230176817211],"type":"Point"}
}