{
  "type": "Feature",
  "properties": {
    "iso:country": "GB",
    "wof:name": "CW5 8FQ",
    "wof:placetype": "postalcode"
  },
  "geometry": {"coordinates":[-2.611083,53.025043],"type":"Point"}
}
