{
  "type": "Feature",
  "properties": {
    "iso:country": "GB",
    "wof:name": "LL11 2ND",
    "wof:placetype": "postalcode"
  },
  "geometry": {"coordinates":[-2.996527,53.055062],"type":"Point"}
}
