{
  "type": "Feature",
  "properties": {
    "iso:country":"GB",
    "wof:name":"LL11 2ND",
    "wof:placetype":"postalcode"
},
  "geometry": {"coordinates":[-2.99652750948957,53.05506229021823],"type":"Point"}
}