{
  "type": "Feature",
  "properties": {
    "date:inception_lower": "2024-01-01",
    "date:inception_upper": "2024-01-01",
    "iso:country": "GB",
    "wof:name": "LL16 9BN",
    "wof:placetype": "postalcode"
  },
  "geometry": {"coordinates":[-3.418658,53.183157],"type":"Point"}
}
