{
  "type": "Feature",
  "properties": {
    "date:inception_lower": "2007-01-01",
    "date:inception_upper": "2007-01-01",
    "iso:country": "GB",
    "wof:name": "CT9 1DE",
    "wof:placetype": "postalcode"
  },
  "geometry": {"coordinates":[1.382161,51.390251],"type":"Point"}
}
