{
  "type": "Feature",
  "properties": {
    "iso:country": "GB",
    "wof:name": "CT9 1DE",
    "wof:placetype": "postalcode"
  },
  "geometry": {"coordinates":[1.382161,51.390251],"type":"Point"}
}
