{
  "type": "Feature",
  "properties": {
    "iso:country": "GB",
    "wof:name": "BL3 1HY",
    "wof:placetype": "postalcode"
  },
  "geometry": {"coordinates":[-2.369873,53.563731],"type":"Point"}
}
