{
  "type": "Feature",
  "properties": {
    "iso:country":"GB",
    "wof:name":"BL3 1HY",
    "wof:placetype":"postalcode"
},
  "geometry": {"coordinates":[-2.36987295642162,53.56373057003321],"type":"Point"}
}