{
  "type": "Feature",
  "properties": {
    "iso:country":"GB",
    "wof:name":"BA11 2NZ",
    "wof:placetype":"postalcode"
},
  "geometry": {"coordinates":[-2.32633384142093,51.24706948104735],"type":"Point"}
}