{
  "type": "Feature",
  "properties": {
    "iso:country": "GB",
    "wof:name": "BA11 2NZ",
    "wof:placetype": "postalcode"
  },
  "geometry": {"coordinates":[-2.326331,51.247065],"type":"Point"}
}
