{
  "type": "Feature",
  "properties": {
    "date:inception_lower": "1980-01-01",
    "date:inception_upper": "1980-01-01",
    "iso:country": "GB",
    "wof:name": "BA11 2NZ",
    "wof:placetype": "postalcode"
  },
  "geometry": {"coordinates":[-2.326331,51.247065],"type":"Point"}
}
