{
  "type": "Feature",
  "properties": {
    "date:inception_lower": "2007-08-01",
    "date:inception_upper": "2007-08-01",
    "iso:country": "GB",
    "wof:name": "B12 0ND",
    "wof:placetype": "postalcode"
  },
  "geometry": {"coordinates":[-1.882371,52.471872],"type":"Point"}
}
