{
  "type": "Feature",
  "properties": {
    "iso:country":"GB",
    "wof:name":"B12 0ND",
    "wof:placetype":"postalcode"
},
  "geometry": {"coordinates":[-1.88244994359398,52.47191203602088],"type":"Point"}
}