{
  "type": "Feature",
  "properties": {
    "date:inception_lower":"2008-11-01",
    "date:inception_upper":"2008-11-30",
    "iso:country":"GB",
    "wof:name":"TR26 1FJ",
    "wof:placetype":"postalcode"
},
  "geometry": {"coordinates":[-5.481343,50.212127],"type":"Point"}
}