{
  "type": "Feature",
  "properties": {
    "iso:country": "GB",
    "wof:name": "TR26 1FJ",
    "wof:placetype": "postalcode"
  },
  "geometry": {"coordinates":[-5.481288,50.212146],"type":"Point"}
}
