{
  "type": "Feature",
  "properties": {
    "date:inception_lower": "1980-01-01",
    "date:inception_upper": "1980-01-01",
    "iso:country": "GB",
    "wof:name": "BL9 5DT",
    "wof:placetype": "postalcode"
  },
  "geometry": {"coordinates":[-2.293613,53.605028],"type":"Point"}
}
