{
  "type": "Feature",
  "properties": {
    "iso:country":"GB",
    "wof:name":"E14 3RS",
    "wof:placetype":"postalcode"
},
  "geometry": {"coordinates":[-0.02422557583144,51.4921660279558],"type":"Point"}
}