{
  "type": "Feature",
  "properties": {
    "date:inception_lower":"2000-12-01",
    "date:inception_upper":"2000-12-31",
    "iso:country":"GB",
    "wof:name":"NG5 4EU",
    "wof:placetype":"postalcode"
},
  "geometry": {"coordinates":[-1.135255,52.998268],"type":"Point"}
}