{
  "type": "Feature",
  "properties": {
    "iso:country":"GB",
    "wof:name":"SW17 8NH",
    "wof:placetype":"postalcode"
},
  "geometry": {"coordinates":[-0.15735588057769,51.42759972758986],"type":"Point"}
}