{
  "type": "Feature",
  "properties": {
    "iso:country":"GB",
    "wof:name":"AL1 2BL",
    "wof:placetype":"postalcode"
},
  "geometry": {"coordinates":[-0.3341870305799,51.74301264561431],"type":"Point"}
}