{
  "type": "Feature",
  "properties": {
    "iso:country":"GB",
    "wof:name":"CB24 4YP",
    "wof:placetype":"postalcode"
},
  "geometry": {"coordinates":[-0.03856183674991,52.29673275773042],"type":"Point"}
}