{
  "type": "Feature",
  "properties": {
    "date:inception_lower": "1980-01-01",
    "date:inception_upper": "1980-01-01",
    "iso:country": "GB",
    "wof:name": "NE63 9JQ",
    "wof:placetype": "postalcode"
  },
  "geometry": {"coordinates":[-1.555176,55.185725],"type":"Point"}
}
