{
  "type": "Feature",
  "properties": {
    "iso:country": "GB",
    "wof:name": "AL4 9XU",
    "wof:placetype": "postalcode"
  },
  "geometry": {"coordinates":[-0.303042,51.761639],"type":"Point"}
}
