{
  "type": "Feature",
  "properties": {
    "iso:country": "GB",
    "wof:name": "LE16 7NH",
    "wof:placetype": "postalcode"
  },
  "geometry": {"coordinates":[-0.920792,52.480176],"type":"Point"}
}
