{
  "type": "Feature",
  "properties": {
    "iso:country":"GB",
    "wof:name":"SS3 9JB",
    "wof:placetype":"postalcode"
},
  "geometry": {"coordinates":[0.77758673155649,51.5287219750766],"type":"Point"}
}