{
  "type": "Feature",
  "properties": {
    "date:inception_lower":"1980-01-01",
    "date:inception_upper":"1980-01-31",
    "iso:country":"GB",
    "wof:name":"OL12 0AP",
    "wof:placetype":"postalcode"
},
  "geometry": {"coordinates":[-2.152508,53.630224],"type":"Point"}
}