{
  "type": "Feature",
  "properties": {
    "iso:country":"GB",
    "wof:name":"ME2 4RG",
    "wof:placetype":"postalcode"
},
  "geometry": {"coordinates":[0.49983316450158,51.40534114733597],"type":"Point"}
}