{
  "type": "Feature",
  "properties": {
    "iso:country": "GB",
    "wof:name": "BH23 4PE",
    "wof:placetype": "postalcode"
  },
  "geometry": {"coordinates":[-1.724168,50.749317],"type":"Point"}
}
