{
  "type": "Feature",
  "properties": {
    "iso:country":"GB",
    "wof:name":"WF8 1ST",
    "wof:placetype":"postalcode"
},
  "geometry": {"coordinates":[-1.30415727026677,53.70463014267175],"type":"Point"}
}