{
  "type": "Feature",
  "properties": {
    "date:inception_lower": "1980-01-01",
    "date:inception_upper": "1980-01-01",
    "iso:country": "GB",
    "wof:name": "TW2 7RA",
    "wof:placetype": "postalcode"
  },
  "geometry": {"coordinates":[-0.341065,51.453814],"type":"Point"}
}
