{
  "type": "Feature",
  "properties": {
    "iso:country":"GB",
    "wof:name":"TW2 7RA",
    "wof:placetype":"postalcode"
},
  "geometry": {"coordinates":[-0.34106487058019,51.45381387700048],"type":"Point"}
}