{
  "type": "Feature",
  "properties": {
    "iso:country":"GB",
    "wof:name":"LA2 8DH",
    "wof:placetype":"postalcode"
},
  "geometry": {"coordinates":[-2.34153647179177,54.11822690765217],"type":"Point"}
}