{
  "type": "Feature",
  "properties": {
    "iso:country": "GB",
    "wof:name": "NP44 4BJ",
    "wof:placetype": "postalcode"
  },
  "geometry": {"coordinates":[-3.043848,51.653324],"type":"Point"}
}
