{
  "type": "Feature",
  "properties": {
    "iso:country":"GB",
    "wof:name":"G15 7RH",
    "wof:placetype":"postalcode"
},
  "geometry": {"coordinates":[-4.35173677047468,55.91051537067339],"type":"Point"}
}