{
  "type": "Feature",
  "properties": {
    "iso:country": "GB",
    "wof:name": "G15 7RH",
    "wof:placetype": "postalcode"
  },
  "geometry": {"coordinates":[-4.351737,55.910515],"type":"Point"}
}
