{
  "type": "Feature",
  "properties": {
    "iso:country": "GB",
    "wof:name": "B74 2DX",
    "wof:placetype": "postalcode"
  },
  "geometry": {"coordinates":[-1.894173,52.571475],"type":"Point"}
}
