{
  "type": "Feature",
  "properties": {
    "iso:country":"GB",
    "wof:name":"B74 2DX",
    "wof:placetype":"postalcode"
},
  "geometry": {"coordinates":[-1.89418011968058,52.5714592340406],"type":"Point"}
}