{
  "type": "Feature",
  "properties": {
    "iso:country":"GB",
    "wof:name":"N16 7TZ",
    "wof:placetype":"postalcode"
},
  "geometry": {"coordinates":[-0.06929706793376,51.5549565515398],"type":"Point"}
}