{
  "type": "Feature",
  "properties": {
    "iso:country":"GB",
    "wof:name":"HR9 6PN",
    "wof:placetype":"postalcode"
},
  "geometry": {"coordinates":[-2.70270879996021,51.89823363599554],"type":"Point"}
}