{
  "type": "Feature",
  "properties": {
    "iso:country":"GB",
    "wof:name":"TN5 7FB",
    "wof:placetype":"postalcode"
},
  "geometry": {"coordinates":[0.40987373377235,51.04616929344253],"type":"Point"}
}