{
  "type": "Feature",
  "properties": {
    "date:inception_lower":"2013-11-01",
    "date:inception_upper":"2013-11-30",
    "iso:country":"GB",
    "wof:name":"TN5 7FB",
    "wof:placetype":"postalcode"
},
  "geometry": {"coordinates":[0.410001,51.046155],"type":"Point"}
}