{
  "type": "Feature",
  "properties": {
    "iso:country":"GB",
    "wof:name":"UB6 9DZ",
    "wof:placetype":"postalcode"
},
  "geometry": {"coordinates":[-0.35523325428108,51.52450420724573],"type":"Point"}
}