{
  "type": "Feature",
  "properties": {
    "iso:country":"GB",
    "wof:name":"NG8 3LZ",
    "wof:placetype":"postalcode"
},
  "geometry": {"coordinates":[-1.19530760449477,52.96756838118063],"type":"Point"}
}