{
  "type": "Feature",
  "properties": {
    "iso:country":"GB",
    "wof:name":"LE9 7FH",
    "wof:placetype":"postalcode"
},
  "geometry": {"coordinates":[-1.31470707018225,52.57190719457014],"type":"Point"}
}