{
  "type": "Feature",
  "properties": {
    "iso:country":"GB",
    "wof:name":"GL54 5JF",
    "wof:placetype":"postalcode"
},
  "geometry": {"coordinates":[-1.95813002007217,51.95776793979755],"type":"Point"}
}