{
  "type": "Feature",
  "properties": {
    "iso:country":"GB",
    "wof:name":"E10 5HF",
    "wof:placetype":"postalcode"
},
  "geometry": {"coordinates":[-0.01706180205884,51.56625229635659],"type":"Point"}
}