{
  "type": "Feature",
  "properties": {
    "iso:country":"GB",
    "wof:name":"WF6 1TB",
    "wof:placetype":"postalcode"
},
  "geometry": {"coordinates":[-1.40248452145065,53.70044184371807],"type":"Point"}
}