{
  "type": "Feature",
  "properties": {
    "iso:country":"GB",
    "wof:name":"SA33 4PB",
    "wof:placetype":"postalcode"
},
  "geometry": {"coordinates":[-4.56138903693838,51.74368912606313],"type":"Point"}
}