{
  "type": "Feature",
  "properties": {
    "date:inception_lower": "1992-08-01",
    "date:inception_upper": "1992-08-01",
    "iso:country": "GB",
    "wof:name": "DT9 3QU",
    "wof:placetype": "postalcode"
  },
  "geometry": {"coordinates":[-2.531224,50.946756],"type":"Point"}
}
