{
  "type": "Feature",
  "properties": {
    "iso:country":"GB",
    "wof:name":"BN2 8EN",
    "wof:placetype":"postalcode"
},
  "geometry": {"coordinates":[-0.02896272932074,50.8018785302319],"type":"Point"}
}