{
  "type": "Feature",
  "properties": {
    "date:inception_lower":"1987-10-01",
    "date:inception_upper":"1987-10-31",
    "iso:country":"GB",
    "wof:name":"ME20 6QZ",
    "wof:placetype":"postalcode"
},
  "geometry": {"coordinates":[0.431367,51.305965],"type":"Point"}
}