{
  "type": "Feature",
  "properties": {
    "iso:country":"GB",
    "wof:name":"NN9 5WA",
    "wof:placetype":"postalcode"
},
  "geometry": {"coordinates":[-0.6554006744327,52.33664527115884],"type":"Point"}
}