{
  "type": "Feature",
  "properties": {
    "date:inception_lower": "2008-06-01",
    "date:inception_upper": "2008-06-01",
    "iso:country": "GB",
    "wof:name": "NN9 5WA",
    "wof:placetype": "postalcode"
  },
  "geometry": {"coordinates":[-0.655414,52.33666],"type":"Point"}
}
