{
  "type": "Feature",
  "properties": {
    "iso:country": "GB",
    "wof:name": "TN6 3DE",
    "wof:placetype": "postalcode"
  },
  "geometry": {"coordinates":[0.169928,51.041031],"type":"Point"}
}
