{
  "type": "Feature",
  "properties": {
    "iso:country":"GB",
    "wof:name":"TN6 3DE",
    "wof:placetype":"postalcode"
},
  "geometry": {"coordinates":[0.16992691694705,51.04099725662671],"type":"Point"}
}