{
  "type": "Feature",
  "properties": {
    "date:inception_lower": "1980-01-01",
    "date:inception_upper": "1980-01-01",
    "iso:country": "GB",
    "wof:name": "CM3 2LP",
    "wof:placetype": "postalcode"
  },
  "geometry": {"coordinates":[0.598364,51.772899],"type":"Point"}
}
