{
  "type": "Feature",
  "properties": {
    "iso:country":"GB",
    "wof:name":"CM3 2LP",
    "wof:placetype":"postalcode"
},
  "geometry": {"coordinates":[0.59836385773514,51.77289902419081],"type":"Point"}
}