{
  "type": "Feature",
  "properties": {
    "date:inception_lower": "1984-10-01",
    "date:inception_upper": "1984-10-01",
    "iso:country": "GB",
    "wof:name": "SN5 7YJ",
    "wof:placetype": "postalcode"
  },
  "geometry": {"coordinates":[-1.813264,51.56052],"type":"Point"}
}
