{
  "type": "Feature",
  "properties": {
    "date:inception_lower":"1980-01-01",
    "date:inception_upper":"1980-01-31",
    "iso:country":"GB",
    "wof:name":"LS16 7HR",
    "wof:placetype":"postalcode"
},
  "geometry": {"coordinates":[-1.625064,53.860936],"type":"Point"}
}