{
  "type": "Feature",
  "properties": {
    "iso:country": "GB",
    "wof:name": "DA5 1DP",
    "wof:placetype": "postalcode"
  },
  "geometry": {"coordinates":[0.123295,51.449497],"type":"Point"}
}
