{
  "type": "Feature",
  "properties": {
    "iso:country": "GB",
    "wof:name": "CO10 0SX",
    "wof:placetype": "postalcode"
  },
  "geometry": {"coordinates":[0.804626,52.073833],"type":"Point"}
}
