{
  "type": "Feature",
  "properties": {
    "date:inception_lower": "1980-01-01",
    "date:inception_upper": "1980-01-01",
    "iso:country": "GB",
    "wof:name": "CO10 0SX",
    "wof:placetype": "postalcode"
  },
  "geometry": {"coordinates":[0.804686,52.073837],"type":"Point"}
}
