{
  "type": "Feature",
  "properties": {
    "iso:country":"GB",
    "wof:name":"BN26 6QA",
    "wof:placetype":"postalcode"
},
  "geometry": {"coordinates":[0.24348084782292,50.82632113256383],"type":"Point"}
}