{
  "type": "Feature",
  "properties": {
    "iso:country": "GB",
    "wof:name": "BN26 6QA",
    "wof:placetype": "postalcode"
  },
  "geometry": {"coordinates":[0.243481,50.826321],"type":"Point"}
}
