{
  "type": "Feature",
  "properties": {
    "date:inception_lower":"1980-01-01",
    "date:inception_upper":"1980-01-31",
    "iso:country":"GB",
    "wof:name":"BN8 6HB",
    "wof:placetype":"postalcode"
},
  "geometry": {"coordinates":[0.179515,50.912664],"type":"Point"}
}