{
  "type": "Feature",
  "properties": {
    "iso:country": "GB",
    "wof:name": "BN8 6HB",
    "wof:placetype": "postalcode"
  },
  "geometry": {"coordinates":[0.17678,50.912581],"type":"Point"}
}
