{
  "type": "Feature",
  "properties": {
    "iso:country":"GB",
    "wof:name":"NE24 5HJ",
    "wof:placetype":"postalcode"
},
  "geometry": {"coordinates":[-1.53020128367038,55.12730352006015],"type":"Point"}
}