{
  "type": "Feature",
  "properties": {
    "iso:country":"GB",
    "wof:name":"SY20 9JU",
    "wof:placetype":"postalcode"
},
  "geometry": {"coordinates":[-3.91865311260871,52.5853917337645],"type":"Point"}
}