{
  "type": "Feature",
  "properties": {
    "date:inception_lower": "1994-05-01",
    "date:inception_upper": "1994-05-01",
    "iso:country": "GB",
    "wof:name": "CM15 0SJ",
    "wof:placetype": "postalcode"
  },
  "geometry": {"coordinates":[0.306978,51.649155],"type":"Point"}
}
