{
  "type": "Feature",
  "properties": {
    "iso:country":"GB",
    "wof:name":"CM15 0SJ",
    "wof:placetype":"postalcode"
},
  "geometry": {"coordinates":[0.30695074344531,51.64916093448741],"type":"Point"}
}