{
  "type": "Feature",
  "properties": {
    "iso:country": "GB",
    "wof:name": "EH39 5JN",
    "wof:placetype": "postalcode"
  },
  "geometry": {"coordinates":[-2.726965,56.018485],"type":"Point"}
}
