{
  "type": "Feature",
  "properties": {
    "iso:country":"GB",
    "wof:name":"BS21 6JE",
    "wof:placetype":"postalcode"
},
  "geometry": {"coordinates":[-2.85243163671727,51.43144256281255],"type":"Point"}
}