{
  "type": "Feature",
  "properties": {
    "iso:country":"GB",
    "wof:name":"EX39 5AU",
    "wof:placetype":"postalcode"
},
  "geometry": {"coordinates":[-4.25021355211945,51.01424111018494],"type":"Point"}
}