{
  "type": "Feature",
  "properties": {
    "iso:country": "GB",
    "wof:name": "YO62 5EL",
    "wof:placetype": "postalcode"
  },
  "geometry": {"coordinates":[-1.094111,54.214059],"type":"Point"}
}
