{
  "type": "Feature",
  "properties": {
    "iso:country": "GB",
    "wof:name": "NG1 5AE",
    "wof:placetype": "postalcode"
  },
  "geometry": {"coordinates":[-1.156353,52.954581],"type":"Point"}
}
