{
  "type": "Feature",
  "properties": {
    "iso:country":"GB",
    "wof:name":"G78 2AY",
    "wof:placetype":"postalcode"
},
  "geometry": {"coordinates":[-4.39426592604464,55.79229687350172],"type":"Point"}
}