{
  "type": "Feature",
  "properties": {
    "iso:country":"GB",
    "wof:name":"SP4 6HY",
    "wof:placetype":"postalcode"
},
  "geometry": {"coordinates":[-1.74122222075211,51.11346599619256],"type":"Point"}
}