{
  "type": "Feature",
  "properties": {
    "iso:country":"GB",
    "wof:name":"NG13 9AT",
    "wof:placetype":"postalcode"
},
  "geometry": {"coordinates":[-0.89776519838382,52.95232715441451],"type":"Point"}
}