{
  "type": "Feature",
  "properties": {
    "iso:country":"GB",
    "wof:name":"CV9 1AY",
    "wof:placetype":"postalcode"
},
  "geometry": {"coordinates":[-1.54967753064822,52.57804071963874],"type":"Point"}
}