{
  "type": "Feature",
  "properties": {
    "iso:country":"GB",
    "wof:name":"DN6 7UE",
    "wof:placetype":"postalcode"
},
  "geometry": {"coordinates":[-1.20104362769038,53.56998717449046],"type":"Point"}
}