{
  "type": "Feature",
  "properties": {
    "date:inception_lower": "2012-02-01",
    "date:inception_upper": "2012-02-01",
    "iso:country": "GB",
    "wof:name": "KY11 9GJ",
    "wof:placetype": "postalcode"
  },
  "geometry": {"coordinates":[-3.340683,56.04614],"type":"Point"}
}
