{
  "type": "Feature",
  "properties": {
    "iso:country":"GB",
    "wof:name":"PO8 0ZF",
    "wof:placetype":"postalcode"
},
  "geometry": {"coordinates":[-0.99182019018072,50.94033111381245],"type":"Point"}
}