{
  "type": "Feature",
  "properties": {
    "iso:country":"GB",
    "wof:name":"SA1 5DT",
    "wof:placetype":"postalcode"
},
  "geometry": {"coordinates":[-3.94494023833429,51.62343332219465],"type":"Point"}
}