{
  "type": "Feature",
  "properties": {
    "date:inception_lower": "2014-01-01",
    "date:inception_upper": "2014-01-01",
    "iso:country": "GB",
    "wof:name": "EH14 4BD",
    "wof:placetype": "postalcode"
  },
  "geometry": {"coordinates":[-3.343789,55.898518],"type":"Point"}
}
