{
  "type": "Feature",
  "properties": {
    "iso:country":"GB",
    "wof:name":"EH14 4BD",
    "wof:placetype":"postalcode"
},
  "geometry": {"coordinates":[-3.34398224071891,55.89849389287792],"type":"Point"}
}