{
  "type": "Feature",
  "properties": {
    "iso:country": "GB",
    "wof:name": "EH14 4BD",
    "wof:placetype": "postalcode"
  },
  "geometry": {"coordinates":[-3.34398,55.898489],"type":"Point"}
}
