{
  "type": "Feature",
  "properties": {
    "iso:country":"GB",
    "wof:name":"NE10 9HT",
    "wof:placetype":"postalcode"
},
  "geometry": {"coordinates":[-1.573510617516,54.94790975052637],"type":"Point"}
}