{
  "type": "Feature",
  "properties": {
    "date:inception_lower": "1980-01-01",
    "date:inception_upper": "1980-01-01",
    "iso:country": "GB",
    "wof:name": "NE10 9HT",
    "wof:placetype": "postalcode"
  },
  "geometry": {"coordinates":[-1.573511,54.94791],"type":"Point"}
}
