{
  "type": "Feature",
  "properties": {
    "iso:country":"GB",
    "wof:name":"DT6 4EF",
    "wof:placetype":"postalcode"
},
  "geometry": {"coordinates":[-2.74501819036871,50.73479734283886],"type":"Point"}
}