{
  "type": "Feature",
  "properties": {
    "iso:country": "GB",
    "wof:name": "DT6 4EF",
    "wof:placetype": "postalcode"
  },
  "geometry": {"coordinates":[-2.745018,50.734797],"type":"Point"}
}
