{
  "type": "Feature",
  "properties": {
    "iso:country":"GB",
    "wof:name":"CV6 1DW",
    "wof:placetype":"postalcode"
},
  "geometry": {"coordinates":[-1.53382130284098,52.41706725203432],"type":"Point"}
}