{
  "type": "Feature",
  "properties": {
    "iso:country": "GB",
    "wof:name": "CV6 1DW",
    "wof:placetype": "postalcode"
  },
  "geometry": {"coordinates":[-1.533821,52.417067],"type":"Point"}
}
