{
  "type": "Feature",
  "properties": {
    "iso:country":"GB",
    "wof:name":"EX5 2JZ",
    "wof:placetype":"postalcode"
},
  "geometry": {"coordinates":[-3.40420418683267,50.70906123845611],"type":"Point"}
}