{
  "type": "Feature",
  "properties": {
    "iso:country":"GB",
    "wof:name":"BD20 8QX",
    "wof:placetype":"postalcode"
},
  "geometry": {"coordinates":[-2.00649214556158,53.89826320628238],"type":"Point"}
}