{
  "type": "Feature",
  "properties": {
    "iso:country": "GB",
    "wof:name": "BD20 8QX",
    "wof:placetype": "postalcode"
  },
  "geometry": {"coordinates":[-2.006492,53.898263],"type":"Point"}
}
