{
  "type": "Feature",
  "properties": {
    "iso:country":"GB",
    "wof:name":"BN1 2HD",
    "wof:placetype":"postalcode"
},
  "geometry": {"coordinates":[-0.14953788005596,50.82379220722452],"type":"Point"}
}