{
  "type": "Feature",
  "properties": {
    "date:inception_lower": "1980-01-01",
    "date:inception_upper": "1980-01-01",
    "iso:country": "GB",
    "wof:name": "BN1 2HD",
    "wof:placetype": "postalcode"
  },
  "geometry": {"coordinates":[-0.149707,50.823825],"type":"Point"}
}
