{
  "type": "Feature",
  "properties": {
    "iso:country": "GB",
    "wof:name": "BN1 2HD",
    "wof:placetype": "postalcode"
  },
  "geometry": {"coordinates":[-0.149707,50.823825],"type":"Point"}
}
