{
  "type": "Feature",
  "properties": {
    "iso:country":"GB",
    "wof:name":"DH2 3TD",
    "wof:placetype":"postalcode"
},
  "geometry": {"coordinates":[-1.5971578678266,54.84524902641024],"type":"Point"}
}