{
  "type": "Feature",
  "properties": {
    "iso:country":"GB",
    "wof:name":"HS2 0SN",
    "wof:placetype":"postalcode"
},
  "geometry": {"coordinates":[-6.28387808780262,58.47331292157411],"type":"Point"}
}