{
  "type": "Feature",
  "properties": {
    "iso:country": "GB",
    "wof:name": "HS2 0SN",
    "wof:placetype": "postalcode"
  },
  "geometry": {"coordinates":[-6.283878,58.473313],"type":"Point"}
}
