{
  "type": "Feature",
  "properties": {
    "date:inception_lower": "1990-07-01",
    "date:inception_upper": "1990-07-01",
    "iso:country": "GB",
    "wof:name": "BN41 2PR",
    "wof:placetype": "postalcode"
  },
  "geometry": {"coordinates":[-0.22492,50.846188],"type":"Point"}
}
