{
  "type": "Feature",
  "properties": {
    "iso:country":"GB",
    "wof:name":"SY10 0BW",
    "wof:placetype":"postalcode"
},
  "geometry": {"coordinates":[-3.32924073476333,52.82666586414383],"type":"Point"}
}