{
  "type": "Feature",
  "properties": {
    "iso:country":"GB",
    "wof:name":"NP16 5NQ",
    "wof:placetype":"postalcode"
},
  "geometry": {"coordinates":[-2.67497990786944,51.62536005911812],"type":"Point"}
}