{
  "type": "Feature",
  "properties": {
    "iso:country":"GB",
    "wof:name":"FY7 6EZ",
    "wof:placetype":"postalcode"
},
  "geometry": {"coordinates":[-3.01422003737699,53.92587652086433],"type":"Point"}
}