{
  "type": "Feature",
  "properties": {
    "iso:country":"GB",
    "wof:name":"PR5 4BD",
    "wof:placetype":"postalcode"
},
  "geometry": {"coordinates":[-2.6712739236256,53.74845919478977],"type":"Point"}
}