{
  "type": "Feature",
  "properties": {
    "iso:country": "GB",
    "wof:name": "SO53 1HD",
    "wof:placetype": "postalcode"
  },
  "geometry": {"coordinates":[-1.388788,50.992704],"type":"Point"}
}
