{
  "type": "Feature",
  "properties": {
    "date:inception_lower": "1994-12-01",
    "date:inception_upper": "1994-12-01",
    "iso:country": "GB",
    "wof:name": "SO53 1HD",
    "wof:placetype": "postalcode"
  },
  "geometry": {"coordinates":[-1.388788,50.992704],"type":"Point"}
}
