{
  "type": "Feature",
  "properties": {
    "date:inception_lower": "1986-07-01",
    "date:inception_upper": "1986-07-01",
    "iso:country": "GB",
    "wof:name": "CF5 2SF",
    "wof:placetype": "postalcode"
  },
  "geometry": {"coordinates":[-3.23875,51.504114],"type":"Point"}
}
