{
  "type": "Feature",
  "properties": {
    "iso:country":"GB",
    "wof:name":"SA71 4EQ",
    "wof:placetype":"postalcode"
},
  "geometry": {"coordinates":[-4.91960957397817,51.67277717464129],"type":"Point"}
}