{
  "type": "Feature",
  "properties": {
    "iso:country": "GB",
    "wof:name": "SA71 4EQ",
    "wof:placetype": "postalcode"
  },
  "geometry": {"coordinates":[-4.918994,51.672795],"type":"Point"}
}
