{
  "type": "Feature",
  "properties": {
    "date:inception_lower":"1980-01-01",
    "date:inception_upper":"1980-01-31",
    "iso:country":"GB",
    "wof:name":"SA71 4EQ",
    "wof:placetype":"postalcode"
},
  "geometry": {"coordinates":[-4.918994,51.672795],"type":"Point"}
}