{
  "type": "Feature",
  "properties": {
    "iso:country":"GB",
    "wof:name":"SY23 5EF",
    "wof:placetype":"postalcode"
},
  "geometry": {"coordinates":[-4.10832626117273,52.28899471330692],"type":"Point"}
}