{
  "type": "Feature",
  "properties": {
    "date:inception_lower": "1980-01-01",
    "date:inception_upper": "1980-01-01",
    "iso:country": "GB",
    "wof:name": "SY23 5EF",
    "wof:placetype": "postalcode"
  },
  "geometry": {"coordinates":[-4.108326,52.288995],"type":"Point"}
}
