{
  "type": "Feature",
  "properties": {
    "iso:country":"GB",
    "wof:name":"TS12 2XP",
    "wof:placetype":"postalcode"
},
  "geometry": {"coordinates":[-0.9331163412253,54.5655700202968],"type":"Point"}
}