{
  "type": "Feature",
  "properties": {
    "iso:country": "GB",
    "wof:name": "SY3 8EB",
    "wof:placetype": "postalcode"
  },
  "geometry": {"coordinates":[-2.806402,52.737308],"type":"Point"}
}
