{
  "type": "Feature",
  "properties": {
    "iso:country":"GB",
    "wof:name":"SY3 8EB",
    "wof:placetype":"postalcode"
},
  "geometry": {"coordinates":[-2.80697618498006,52.73698329146428],"type":"Point"}
}