{
  "type": "Feature",
  "properties": {
    "iso:country":"GB",
    "wof:name":"CH64 0TB",
    "wof:placetype":"postalcode"
},
  "geometry": {"coordinates":[-3.06637793270993,53.27744634619764],"type":"Point"}
}