{
  "type": "Feature",
  "properties": {
    "iso:country": "GB",
    "wof:name": "HU7 4DW",
    "wof:placetype": "postalcode"
  },
  "geometry": {"coordinates":[-0.32136,53.787408],"type":"Point"}
}
