{
  "type": "Feature",
  "properties": {
    "iso:country": "GB",
    "wof:name": "CF64 1JG",
    "wof:placetype": "postalcode"
  },
  "geometry": {"coordinates":[-3.187165,51.445021],"type":"Point"}
}
