{
  "type": "Feature",
  "properties": {
    "iso:country":"GB",
    "wof:name":"WF1 5AN",
    "wof:placetype":"postalcode"
},
  "geometry": {"coordinates":[-1.48836446368631,53.66942533411221],"type":"Point"}
}