{
  "type": "Feature",
  "properties": {
    "iso:country": "GB",
    "wof:name": "WF1 5AN",
    "wof:placetype": "postalcode"
  },
  "geometry": {"coordinates":[-1.488364,53.669425],"type":"Point"}
}
