{
  "type": "Feature",
  "properties": {
    "iso:country": "GB",
    "wof:name": "PE30 3SX",
    "wof:placetype": "postalcode"
  },
  "geometry": {"coordinates":[0.433041,52.790329],"type":"Point"}
}
