{
  "type": "Feature",
  "properties": {
    "iso:country":"GB",
    "wof:name":"PE30 3SX",
    "wof:placetype":"postalcode"
},
  "geometry": {"coordinates":[0.43304124373254,52.79032853185814],"type":"Point"}
}