{
  "type": "Feature",
  "properties": {
    "iso:country":"GB",
    "wof:name":"EX22 6PZ",
    "wof:placetype":"postalcode"
},
  "geometry": {"coordinates":[-4.37600224741283,50.75517790243705],"type":"Point"}
}