{
  "type": "Feature",
  "properties": {
    "date:inception_lower": "1980-01-01",
    "date:inception_upper": "1980-01-01",
    "iso:country": "GB",
    "wof:name": "BA13 4RW",
    "wof:placetype": "postalcode"
  },
  "geometry": {"coordinates":[-2.12279,51.270943],"type":"Point"}
}
