{
  "type": "Feature",
  "properties": {
    "iso:country":"GB",
    "wof:name":"BA13 4RW",
    "wof:placetype":"postalcode"
},
  "geometry": {"coordinates":[-2.12279633155894,51.27094708275674],"type":"Point"}
}