{
  "type": "Feature",
  "properties": {
    "iso:country":"GB",
    "wof:name":"TS7 0BP",
    "wof:placetype":"postalcode"
},
  "geometry": {"coordinates":[-1.17294592203973,54.52763334503313],"type":"Point"}
}