{
  "type": "Feature",
  "properties": {
    "iso:country":"GB",
    "wof:name":"SE22 0BQ",
    "wof:placetype":"postalcode"
},
  "geometry": {"coordinates":[-0.07182568818957,51.44835486162273],"type":"Point"}
}