{
  "type": "Feature",
  "properties": {
    "date:inception_lower": "1980-01-01",
    "date:inception_upper": "1980-01-01",
    "iso:country": "GB",
    "wof:name": "SE22 0BQ",
    "wof:placetype": "postalcode"
  },
  "geometry": {"coordinates":[-0.071826,51.448355],"type":"Point"}
}
