{
  "type": "Feature",
  "properties": {
    "iso:country":"GB",
    "wof:name":"PE2 5QZ",
    "wof:placetype":"postalcode"
},
  "geometry": {"coordinates":[-0.28795123523151,52.5421297827962],"type":"Point"}
}