{
  "type": "Feature",
  "properties": {
    "iso:country":"GB",
    "wof:name":"CM9 5HP",
    "wof:placetype":"postalcode"
},
  "geometry": {"coordinates":[0.68644723306778,51.72876609480076],"type":"Point"}
}