{
  "type": "Feature",
  "properties": {
    "date:inception_lower":"1995-07-01",
    "date:inception_upper":"1995-07-31",
    "iso:country":"GB",
    "wof:name":"CM9 5HP",
    "wof:placetype":"postalcode"
},
  "geometry": {"coordinates":[0.686447,51.728766],"type":"Point"}
}