{
  "type": "Feature",
  "properties": {
    "date:inception_lower":"1984-02-01",
    "date:inception_upper":"1984-02-29",
    "iso:country":"GB",
    "wof:name":"RG27 8JQ",
    "wof:placetype":"postalcode"
},
  "geometry": {"coordinates":[-0.914082,51.297442],"type":"Point"}
}