{
  "type": "Feature",
  "properties": {
    "date:inception_lower": "1980-01-01",
    "date:inception_upper": "1980-01-01",
    "iso:country": "GB",
    "wof:name": "LL14 6PS",
    "wof:placetype": "postalcode"
  },
  "geometry": {"coordinates":[-3.038954,52.99402],"type":"Point"}
}
