{
  "type": "Feature",
  "properties": {
    "date:inception_lower": "1980-01-01",
    "date:inception_upper": "1980-01-01",
    "iso:country": "GB",
    "wof:name": "HU12 9RA",
    "wof:placetype": "postalcode"
  },
  "geometry": {"coordinates":[-0.113881,53.708794],"type":"Point"}
}
