{
  "type": "Feature",
  "properties": {
    "iso:country": "GB",
    "wof:name": "E18 2BG",
    "wof:placetype": "postalcode"
  },
  "geometry": {"coordinates":[0.023956,51.59058],"type":"Point"}
}
