{
  "type": "Feature",
  "properties": {
    "date:inception_lower": "1980-01-01",
    "date:inception_upper": "1980-01-01",
    "iso:country": "GB",
    "wof:name": "TF9 1JT",
    "wof:placetype": "postalcode"
  },
  "geometry": {"coordinates":[-2.48217,52.902697],"type":"Point"}
}
