{
  "type": "Feature",
  "properties": {
    "iso:country":"GB",
    "wof:name":"HP6 6NQ",
    "wof:placetype":"postalcode"
},
  "geometry": {"coordinates":[-0.59023467047968,51.67628096002694],"type":"Point"}
}