{
  "type": "Feature",
  "properties": {
    "date:inception_lower": "1980-01-01",
    "date:inception_upper": "1980-01-01",
    "iso:country": "GB",
    "wof:name": "SL0 0ND",
    "wof:placetype": "postalcode"
  },
  "geometry": {"coordinates":[-0.530362,51.536866],"type":"Point"}
}
