{
  "type": "Feature",
  "properties": {
    "iso:country": "GB",
    "wof:name": "SL0 0ND",
    "wof:placetype": "postalcode"
  },
  "geometry": {"coordinates":[-0.530362,51.536866],"type":"Point"}
}
