{
  "type": "Feature",
  "properties": {
    "iso:country":"GB",
    "wof:name":"LN6 0FR",
    "wof:placetype":"postalcode"
},
  "geometry": {"coordinates":[-0.6117021688777,53.21046530240185],"type":"Point"}
}