{
  "type": "Feature",
  "properties": {
    "date:inception_lower":"2006-02-01",
    "date:inception_upper":"2006-02-28",
    "iso:country":"GB",
    "wof:name":"LN6 0FR",
    "wof:placetype":"postalcode"
},
  "geometry": {"coordinates":[-0.611702,53.210465],"type":"Point"}
}