{
  "type": "Feature",
  "properties": {
    "date:inception_lower":"2000-12-01",
    "date:inception_upper":"2000-12-31",
    "iso:country":"GB",
    "wof:name":"SA17 5LY",
    "wof:placetype":"postalcode"
},
  "geometry": {"coordinates":[-4.231784,51.773768],"type":"Point"}
}