{
  "type": "Feature",
  "properties": {
    "iso:country":"GB",
    "wof:name":"SA17 5LY",
    "wof:placetype":"postalcode"
},
  "geometry": {"coordinates":[-4.23178382709609,51.77376812324162],"type":"Point"}
}