{
  "type": "Feature",
  "properties": {
    "iso:country":"GB",
    "wof:name":"ST16 1AN",
    "wof:placetype":"postalcode"
},
  "geometry": {"coordinates":[-2.13617145812954,52.80380107602098],"type":"Point"}
}