{
  "type": "Feature",
  "properties": {
    "iso:country": "GB",
    "wof:name": "ST16 1AN",
    "wof:placetype": "postalcode"
  },
  "geometry": {"coordinates":[-2.136171,52.803801],"type":"Point"}
}
