{
  "type": "Feature",
  "properties": {
    "iso:country":"GB",
    "wof:name":"B13 0LN",
    "wof:placetype":"postalcode"
},
  "geometry": {"coordinates":[-1.86835940432054,52.42318034471253],"type":"Point"}
}