{
  "type": "Feature",
  "properties": {
    "iso:country":"GB",
    "wof:name":"OL7 0HP",
    "wof:placetype":"postalcode"
},
  "geometry": {"coordinates":[-2.11488073553996,53.47834584786137],"type":"Point"}
}