{
  "type": "Feature",
  "properties": {
    "iso:country":"GB",
    "wof:name":"LE10 1DA",
    "wof:placetype":"postalcode"
},
  "geometry": {"coordinates":[-1.36991062490032,52.54171067259583],"type":"Point"}
}