{
  "type": "Feature",
  "properties": {
    "iso:country":"GB",
    "wof:name":"SE21 8NX",
    "wof:placetype":"postalcode"
},
  "geometry": {"coordinates":[-0.08269166273805,51.43254411605507],"type":"Point"}
}