{
  "type": "Feature",
  "properties": {
    "iso:country": "GB",
    "wof:name": "GL7 5TJ",
    "wof:placetype": "postalcode"
  },
  "geometry": {"coordinates":[-1.902397,51.673566],"type":"Point"}
}
