{
  "type": "Feature",
  "properties": {
    "iso:country":"GB",
    "wof:name":"GL7 5TJ",
    "wof:placetype":"postalcode"
},
  "geometry": {"coordinates":[-1.90239733926795,51.67356613411351],"type":"Point"}
}