{
  "type": "Feature",
  "properties": {
    "iso:country": "GB",
    "wof:name": "TS1 5QN",
    "wof:placetype": "postalcode"
  },
  "geometry": {"coordinates":[-1.251578,54.569971],"type":"Point"}
}
