{
  "type": "Feature",
  "properties": {
    "iso:country":"GB",
    "wof:name":"SN8 3DP",
    "wof:placetype":"postalcode"
},
  "geometry": {"coordinates":[-1.65398470744803,51.35548264410524],"type":"Point"}
}