{
  "type": "Feature",
  "properties": {
    "date:inception_lower": "1980-01-01",
    "date:inception_upper": "1980-01-01",
    "iso:country": "GB",
    "wof:name": "SG4 8QW",
    "wof:placetype": "postalcode"
  },
  "geometry": {"coordinates":[-0.300747,51.850896],"type":"Point"}
}
