{
  "type": "Feature",
  "properties": {
    "iso:country":"GB",
    "wof:name":"SG4 8QW",
    "wof:placetype":"postalcode"
},
  "geometry": {"coordinates":[-0.30074675881839,51.85089566624944],"type":"Point"}
}