{
  "type": "Feature",
  "properties": {
    "iso:country":"GB",
    "wof:name":"RM1 4LY",
    "wof:placetype":"postalcode"
},
  "geometry": {"coordinates":[0.18197277269309,51.60325916882816],"type":"Point"}
}