{
  "type": "Feature",
  "properties": {
    "iso:country":"GB",
    "wof:name":"DL2 1EU",
    "wof:placetype":"postalcode"
},
  "geometry": {"coordinates":[-1.45432748523974,54.51660270406622],"type":"Point"}
}