{
  "type": "Feature",
  "properties": {
    "date:inception_lower":"1980-01-01",
    "date:inception_upper":"1980-01-31",
    "iso:country":"GB",
    "wof:name":"DL2 1EU",
    "wof:placetype":"postalcode"
},
  "geometry": {"coordinates":[-1.454327,54.516603],"type":"Point"}
}