{
  "type": "Feature",
  "properties": {
    "iso:country": "GB",
    "wof:name": "LL65 2GA",
    "wof:placetype": "postalcode"
  },
  "geometry": {"coordinates":[-4.622014,53.306693],"type":"Point"}
}
