{
  "type": "Feature",
  "properties": {
    "date:inception_lower": "2000-12-01",
    "date:inception_upper": "2000-12-01",
    "iso:country": "GB",
    "wof:name": "LL65 2GA",
    "wof:placetype": "postalcode"
  },
  "geometry": {"coordinates":[-4.622014,53.306693],"type":"Point"}
}
