{
  "type": "Feature",
  "properties": {
    "iso:country": "GB",
    "wof:name": "TA19 9RA",
    "wof:placetype": "postalcode"
  },
  "geometry": {"coordinates":[-2.973699,50.933902],"type":"Point"}
}
