{
  "type": "Feature",
  "properties": {
    "iso:country": "GB",
    "wof:name": "NG9 2SJ",
    "wof:placetype": "postalcode"
  },
  "geometry": {"coordinates":[-1.210844,52.939419],"type":"Point"}
}
