{
  "type": "Feature",
  "properties": {
    "iso:country":"GB",
    "wof:name":"NG9 2SJ",
    "wof:placetype":"postalcode"
},
  "geometry": {"coordinates":[-1.21084365888222,52.93941860287288],"type":"Point"}
}