{
  "type": "Feature",
  "properties": {
    "iso:country":"GB",
    "wof:name":"M2 7AR",
    "wof:placetype":"postalcode"
},
  "geometry": {"coordinates":[-2.24496076584341,53.48141254604175],"type":"Point"}
}