{
  "type": "Feature",
  "properties": {
    "iso:country": "GB",
    "wof:name": "EH40 3DT",
    "wof:placetype": "postalcode"
  },
  "geometry": {"coordinates":[-2.646754,56.003882],"type":"Point"}
}
