{
  "type": "Feature",
  "properties": {
    "date:inception_lower": "1980-01-01",
    "date:inception_upper": "1980-01-01",
    "iso:country": "GB",
    "wof:name": "EH40 3DT",
    "wof:placetype": "postalcode"
  },
  "geometry": {"coordinates":[-2.646754,56.003882],"type":"Point"}
}
