{
  "type": "Feature",
  "properties": {
    "iso:country":"GB",
    "wof:name":"NN7 4TA",
    "wof:placetype":"postalcode"
},
  "geometry": {"coordinates":[-1.08616158795841,52.24182966383114],"type":"Point"}
}