{
  "type": "Feature",
  "properties": {
    "date:inception_lower": "1980-01-01",
    "date:inception_upper": "1980-01-01",
    "iso:country": "GB",
    "wof:name": "NN7 4TA",
    "wof:placetype": "postalcode"
  },
  "geometry": {"coordinates":[-1.086162,52.24183],"type":"Point"}
}
