{
  "type": "Feature",
  "properties": {
    "iso:country":"GB",
    "wof:name":"PO7 5HJ",
    "wof:placetype":"postalcode"
},
  "geometry": {"coordinates":[-1.03960260220831,50.86139162643806],"type":"Point"}
}