{
  "type": "Feature",
  "properties": {
    "iso:country":"GB",
    "wof:name":"OX16 9HG",
    "wof:placetype":"postalcode"
},
  "geometry": {"coordinates":[-1.33493834255038,52.0459778648281],"type":"Point"}
}