{
  "type": "Feature",
  "properties": {
    "iso:country":"GB",
    "wof:name":"CH8 7PD",
    "wof:placetype":"postalcode"
},
  "geometry": {"coordinates":[-3.21935543574589,53.27490110499574],"type":"Point"}
}