{
  "type": "Feature",
  "properties": {
    "date:inception_lower": "1980-01-01",
    "date:inception_upper": "1980-01-01",
    "iso:country": "GB",
    "wof:name": "CM11 1AP",
    "wof:placetype": "postalcode"
  },
  "geometry": {"coordinates":[0.425847,51.62956],"type":"Point"}
}
