{
  "type": "Feature",
  "properties": {
    "iso:country":"GB",
    "wof:name":"CM11 1AP",
    "wof:placetype":"postalcode"
},
  "geometry": {"coordinates":[0.42584741828637,51.62956037017972],"type":"Point"}
}