{
  "type": "Feature",
  "properties": {
    "date:inception_lower": "1991-09-01",
    "date:inception_upper": "1991-09-01",
    "iso:country": "GB",
    "wof:name": "IP15 5PJ",
    "wof:placetype": "postalcode"
  },
  "geometry": {"coordinates":[1.570481,52.164117],"type":"Point"}
}
