{
  "type": "Feature",
  "properties": {
    "iso:country":"GB",
    "wof:name":"CV22 5EZ",
    "wof:placetype":"postalcode"
},
  "geometry": {"coordinates":[-1.22883028972833,52.35967828476075],"type":"Point"}
}