{
  "type": "Feature",
  "properties": {
    "date:inception_lower": "1980-01-01",
    "date:inception_upper": "1980-01-01",
    "iso:country": "GB",
    "wof:name": "RH4 3ET",
    "wof:placetype": "postalcode"
  },
  "geometry": {"coordinates":[-0.333139,51.220947],"type":"Point"}
}
