{
  "type": "Feature",
  "properties": {
    "iso:country":"GB",
    "wof:name":"RH4 3ET",
    "wof:placetype":"postalcode"
},
  "geometry": {"coordinates":[-0.33313892568394,51.22094738373713],"type":"Point"}
}