{
  "type": "Feature",
  "properties": {
    "date:inception_lower": "1992-01-01",
    "date:inception_upper": "1992-01-01",
    "iso:country": "GB",
    "wof:name": "GU30 7NW",
    "wof:placetype": "postalcode"
  },
  "geometry": {"coordinates":[-0.807609,51.035708],"type":"Point"}
}
