{
  "type": "Feature",
  "properties": {
    "iso:country": "GB",
    "wof:name": "ML8 5JR",
    "wof:placetype": "postalcode"
  },
  "geometry": {"coordinates":[-3.883013,55.755208],"type":"Point"}
}
