{
  "type": "Feature",
  "properties": {
    "iso:country":"GB",
    "wof:name":"N15 6AS",
    "wof:placetype":"postalcode"
},
  "geometry": {"coordinates":[-0.06812414669293,51.57786816581756],"type":"Point"}
}