{
  "type": "Feature",
  "properties": {
    "iso:country": "GB",
    "wof:name": "YO42 1TU",
    "wof:placetype": "postalcode"
  },
  "geometry": {"coordinates":[-0.750588,53.951304],"type":"Point"}
}
