{
  "type": "Feature",
  "properties": {
    "iso:country":"GB",
    "wof:name":"YO42 1TU",
    "wof:placetype":"postalcode"
},
  "geometry": {"coordinates":[-0.75058810483954,53.9513041814556],"type":"Point"}
}