{
  "type": "Feature",
  "properties": {
    "date:inception_lower": "1998-06-01",
    "date:inception_upper": "1998-06-01",
    "iso:country": "GB",
    "wof:name": "CB11 4FG",
    "wof:placetype": "postalcode"
  },
  "geometry": {"coordinates":[0.234721,52.017194],"type":"Point"}
}
