{
  "type": "Feature",
  "properties": {
    "iso:country": "GB",
    "wof:name": "CB11 4FG",
    "wof:placetype": "postalcode"
  },
  "geometry": {"coordinates":[0.234721,52.017194],"type":"Point"}
}
