{
  "type": "Feature",
  "properties": {
    "iso:country":"GB",
    "wof:name":"BB5 3SN",
    "wof:placetype":"postalcode"
},
  "geometry": {"coordinates":[-2.36055331747008,53.72096341166547],"type":"Point"}
}