{
  "type": "Feature",
  "properties": {
    "date:inception_lower":"2002-07-01",
    "date:inception_upper":"2002-07-31",
    "iso:country":"GB",
    "wof:name":"KW17 2HN",
    "wof:placetype":"postalcode"
},
  "geometry": {"coordinates":[-3.232888,59.069597],"type":"Point"}
}