{
  "type": "Feature",
  "properties": {
    "iso:country": "GB",
    "wof:name": "KW17 2HN",
    "wof:placetype": "postalcode"
  },
  "geometry": {"coordinates":[-3.232888,59.069597],"type":"Point"}
}
