{
  "type": "Feature",
  "properties": {
    "iso:country":"GB",
    "wof:name":"SW6 3SN",
    "wof:placetype":"postalcode"
},
  "geometry": {"coordinates":[-0.19344313822491,51.47329502788545],"type":"Point"}
}