{
  "type": "Feature",
  "properties": {
    "iso:country": "GB",
    "wof:name": "OX33 1EJ",
    "wof:placetype": "postalcode"
  },
  "geometry": {"coordinates":[-1.15234,51.766137],"type":"Point"}
}
