{
  "type": "Feature",
  "properties": {
    "iso:country":"GB",
    "wof:name":"OX33 1EJ",
    "wof:placetype":"postalcode"
},
  "geometry": {"coordinates":[-1.15234044167061,51.76613694967387],"type":"Point"}
}