{
  "type": "Feature",
  "properties": {
    "iso:country": "GB",
    "wof:name": "ML12 6LS",
    "wof:placetype": "postalcode"
  },
  "geometry": {"coordinates":[-3.601547,55.602386],"type":"Point"}
}
