{
  "type": "Feature",
  "properties": {
    "iso:country":"GB",
    "wof:name":"NP11 4HH",
    "wof:placetype":"postalcode"
},
  "geometry": {"coordinates":[-3.16848624517443,51.65826056935096],"type":"Point"}
}