{
  "type": "Feature",
  "properties": {
    "date:inception_lower": "1983-01-01",
    "date:inception_upper": "1983-01-01",
    "iso:country": "GB",
    "wof:name": "DL9 4PF",
    "wof:placetype": "postalcode"
  },
  "geometry": {"coordinates":[-1.692681,54.384318],"type":"Point"}
}
