{
  "type": "Feature",
  "properties": {
    "iso:country":"GB",
    "wof:name":"DL9 4PF",
    "wof:placetype":"postalcode"
},
  "geometry": {"coordinates":[-1.6926807659846,54.38431806735162],"type":"Point"}
}