{
  "type": "Feature",
  "properties": {
    "iso:country": "GB",
    "wof:name": "DL9 4PF",
    "wof:placetype": "postalcode"
  },
  "geometry": {"coordinates":[-1.692681,54.384318],"type":"Point"}
}
