{
  "type": "Feature",
  "properties": {
    "iso:country":"GB",
    "wof:name":"OL10 4TF",
    "wof:placetype":"postalcode"
},
  "geometry": {"coordinates":[-2.22028292705825,53.59840824171454],"type":"Point"}
}