{
  "type": "Feature",
  "properties": {
    "date:inception_lower": "1992-08-01",
    "date:inception_upper": "1992-08-01",
    "iso:country": "GB",
    "wof:name": "DE21 6GY",
    "wof:placetype": "postalcode"
  },
  "geometry": {"coordinates":[-1.447696,52.932835],"type":"Point"}
}
