{
  "type": "Feature",
  "properties": {
    "iso:country":"GB",
    "wof:name":"SW1P 4NF",
    "wof:placetype":"postalcode"
},
  "geometry": {"coordinates":[-0.13377819279741,51.49113701405787],"type":"Point"}
}