{
  "type": "Feature",
  "properties": {
    "iso:country": "GB",
    "wof:name": "NG6 0BX",
    "wof:placetype": "postalcode"
  },
  "geometry": {"coordinates":[-1.182609,52.986378],"type":"Point"}
}
