{
  "type": "Feature",
  "properties": {
    "iso:country":"GB",
    "wof:name":"NG6 0BX",
    "wof:placetype":"postalcode"
},
  "geometry": {"coordinates":[-1.18260933473484,52.98637759570173],"type":"Point"}
}