{
  "type": "Feature",
  "properties": {
    "iso:country":"GB",
    "wof:name":"AL3 6DU",
    "wof:placetype":"postalcode"
},
  "geometry": {"coordinates":[-0.34334033678907,51.77233886419825],"type":"Point"}
}