{
  "type": "Feature",
  "properties": {
    "date:inception_lower": "1980-01-01",
    "date:inception_upper": "1980-01-01",
    "iso:country": "GB",
    "wof:name": "L30 5RL",
    "wof:placetype": "postalcode"
  },
  "geometry": {"coordinates":[-2.968052,53.487377],"type":"Point"}
}
