{
  "type": "Feature",
  "properties": {
    "date:inception_lower": "2013-07-01",
    "date:inception_upper": "2013-07-01",
    "iso:country": "GB",
    "wof:name": "NG17 4PN",
    "wof:placetype": "postalcode"
  },
  "geometry": {"coordinates":[-1.24494,53.130223],"type":"Point"}
}
