{
  "type": "Feature",
  "properties": {
    "iso:country": "GB",
    "wof:name": "NG17 4PN",
    "wof:placetype": "postalcode"
  },
  "geometry": {"coordinates":[-1.24494,53.130223],"type":"Point"}
}
