{
  "type": "Feature",
  "properties": {
    "iso:country":"GB",
    "wof:name":"MK46 5DU",
    "wof:placetype":"postalcode"
},
  "geometry": {"coordinates":[-0.70896942139627,52.15963683245431],"type":"Point"}
}