{
  "type": "Feature",
  "properties": {
    "date:inception_lower": "1980-01-01",
    "date:inception_upper": "1980-01-01",
    "iso:country": "GB",
    "wof:name": "NW8 9XU",
    "wof:placetype": "postalcode"
  },
  "geometry": {"coordinates":[-0.183097,51.531083],"type":"Point"}
}
