{
  "type": "Feature",
  "properties": {
    "iso:country":"GB",
    "wof:name":"NW8 9XU",
    "wof:placetype":"postalcode"
},
  "geometry": {"coordinates":[-0.18309698981713,51.53108266572475],"type":"Point"}
}