{
  "type": "Feature",
  "properties": {
    "iso:country":"GB",
    "wof:name":"CF23 7EZ",
    "wof:placetype":"postalcode"
},
  "geometry": {"coordinates":[-3.14474558102083,51.52094789662783],"type":"Point"}
}