{
  "type": "Feature",
  "properties": {
    "iso:country": "GB",
    "wof:name": "S64 0HH",
    "wof:placetype": "postalcode"
  },
  "geometry": {"coordinates":[-1.271167,53.492792],"type":"Point"}
}
