{
  "type": "Feature",
  "properties": {
    "iso:country":"GB",
    "wof:name":"S64 0HH",
    "wof:placetype":"postalcode"
},
  "geometry": {"coordinates":[-1.27116722548714,53.49279153672484],"type":"Point"}
}