{
  "type": "Feature",
  "properties": {
    "iso:country": "GB",
    "wof:name": "WD7 9FH",
    "wof:placetype": "postalcode"
  },
  "geometry": {"coordinates":[-0.305137,51.703497],"type":"Point"}
}
