{
  "type": "Feature",
  "properties": {
    "date:inception_lower": "2019-10-01",
    "date:inception_upper": "2019-10-01",
    "iso:country": "GB",
    "wof:name": "WD7 9FH",
    "wof:placetype": "postalcode"
  },
  "geometry": {"coordinates":[-0.3052,51.70374],"type":"Point"}
}
