{
  "type": "Feature",
  "properties": {
    "iso:country":"GB",
    "wof:name":"PE19 1TE",
    "wof:placetype":"postalcode"
},
  "geometry": {"coordinates":[-0.25380832523132,52.23168768991363],"type":"Point"}
}