{
  "type": "Feature",
  "properties": {
    "date:inception_lower": "2016-08-01",
    "date:inception_upper": "2016-08-01",
    "iso:country": "GB",
    "wof:name": "NN2 8EY",
    "wof:placetype": "postalcode"
  },
  "geometry": {"coordinates":[-0.908807,52.27988],"type":"Point"}
}
