{
  "type": "Feature",
  "properties": {
    "iso:country":"GB",
    "wof:name":"TS24 0DL",
    "wof:placetype":"postalcode"
},
  "geometry": {"coordinates":[-1.19716374796729,54.70364542308106],"type":"Point"}
}