{
  "type": "Feature",
  "properties": {
    "iso:country":"GB",
    "wof:name":"EX23 0PJ",
    "wof:placetype":"postalcode"
},
  "geometry": {"coordinates":[-4.55506763665041,50.79368123355294],"type":"Point"}
}