{
  "type": "Feature",
  "properties": {
    "date:inception_lower": "1988-03-01",
    "date:inception_upper": "1988-03-01",
    "iso:country": "GB",
    "wof:name": "EX23 0PJ",
    "wof:placetype": "postalcode"
  },
  "geometry": {"coordinates":[-4.555068,50.793681],"type":"Point"}
}
