{
  "type": "Feature",
  "properties": {
    "iso:country": "GB",
    "wof:name": "SA34 0YN",
    "wof:placetype": "postalcode"
  },
  "geometry": {"coordinates":[-4.661938,51.924412],"type":"Point"}
}
