{
  "type": "Feature",
  "properties": {
    "iso:country":"GB",
    "wof:name":"S66 9HL",
    "wof:placetype":"postalcode"
},
  "geometry": {"coordinates":[-1.25889053128575,53.39455937945175],"type":"Point"}
}