{
  "type": "Feature",
  "properties": {
    "iso:country": "GB",
    "wof:name": "S66 9HL",
    "wof:placetype": "postalcode"
  },
  "geometry": {"coordinates":[-1.25889,53.394559],"type":"Point"}
}
