{
  "type": "Feature",
  "properties": {
    "iso:country":"GB",
    "wof:name":"BN2 9TL",
    "wof:placetype":"postalcode"
},
  "geometry": {"coordinates":[-0.12522056886362,50.83076062344922],"type":"Point"}
}