{
  "type": "Feature",
  "properties": {
    "iso:country":"GB",
    "wof:name":"N7 8JP",
    "wof:placetype":"postalcode"
},
  "geometry": {"coordinates":[-0.10483706253449,51.54672336460742],"type":"Point"}
}