{
  "type": "Feature",
  "properties": {
    "iso:country": "GB",
    "wof:name": "N7 8JP",
    "wof:placetype": "postalcode"
  },
  "geometry": {"coordinates":[-0.104837,51.546723],"type":"Point"}
}
