{
  "type": "Feature",
  "properties": {
    "iso:country":"GB",
    "wof:name":"SS13 1RB",
    "wof:placetype":"postalcode"
},
  "geometry": {"coordinates":[0.49951810226547,51.58309324220618],"type":"Point"}
}