{
  "type": "Feature",
  "properties": {
    "iso:country": "GB",
    "wof:name": "SS13 1RB",
    "wof:placetype": "postalcode"
  },
  "geometry": {"coordinates":[0.499518,51.583093],"type":"Point"}
}
