{
  "type": "Feature",
  "properties": {
    "iso:country":"GB",
    "wof:name":"SR3 4EH",
    "wof:placetype":"postalcode"
},
  "geometry": {"coordinates":[-1.42957364066281,54.88999558822652],"type":"Point"}
}