{
  "type": "Feature",
  "properties": {
    "date:inception_lower":"1980-01-01",
    "date:inception_upper":"1980-01-31",
    "iso:country":"GB",
    "wof:name":"SR3 4EH",
    "wof:placetype":"postalcode"
},
  "geometry": {"coordinates":[-1.429574,54.889996],"type":"Point"}
}