{
  "type": "Feature",
  "properties": {
    "iso:country":"GB",
    "wof:name":"CM7 9BD",
    "wof:placetype":"postalcode"
},
  "geometry": {"coordinates":[0.55735497647835,51.88152668741535],"type":"Point"}
}