{
  "type": "Feature",
  "properties": {
    "iso:country":"GB",
    "wof:name":"DL10 5PR",
    "wof:placetype":"postalcode"
},
  "geometry": {"coordinates":[-1.69767472740375,54.46534894481157],"type":"Point"}
}