{
  "type": "Feature",
  "properties": {
    "iso:country": "GB",
    "wof:name": "DL10 5PR",
    "wof:placetype": "postalcode"
  },
  "geometry": {"coordinates":[-1.697684,54.46536],"type":"Point"}
}
