{
  "type": "Feature",
  "properties": {
    "iso:country": "GB",
    "wof:name": "DL10 5PR",
    "wof:placetype": "postalcode"
  },
  "geometry": {"coordinates":[-1.699031,54.464707],"type":"Point"}
}
