{
  "type": "Feature",
  "properties": {
    "iso:country":"GB",
    "wof:name":"PH2 8ER",
    "wof:placetype":"postalcode"
},
  "geometry": {"coordinates":[-3.43756199781196,56.39387855575759],"type":"Point"}
}