{
  "type": "Feature",
  "properties": {
    "iso:country": "GB",
    "wof:name": "PH2 8ER",
    "wof:placetype": "postalcode"
  },
  "geometry": {"coordinates":[-3.437593,56.393869],"type":"Point"}
}
