{
  "type": "Feature",
  "properties": {
    "date:inception_lower":"1998-12-01",
    "date:inception_upper":"1998-12-31",
    "iso:country":"GB",
    "wof:name":"CB1 8DS",
    "wof:placetype":"postalcode"
},
  "geometry": {"coordinates":[0.166496,52.182835],"type":"Point"}
}