{
  "type": "Feature",
  "properties": {
    "iso:country":"GB",
    "wof:name":"CB1 8DS",
    "wof:placetype":"postalcode"
},
  "geometry": {"coordinates":[0.16649627234268,52.18283535544378],"type":"Point"}
}