{
  "type": "Feature",
  "properties": {
    "iso:country":"GB",
    "wof:name":"TS7 0HU",
    "wof:placetype":"postalcode"
},
  "geometry": {"coordinates":[-1.1687344328911,54.53110049004589],"type":"Point"}
}