{
  "type": "Feature",
  "properties": {
    "iso:country":"GB",
    "wof:name":"M22 5FX",
    "wof:placetype":"postalcode"
},
  "geometry": {"coordinates":[-2.25094492440459,53.37452638355926],"type":"Point"}
}