{
  "type": "Feature",
  "properties": {
    "date:inception_lower": "1993-01-01",
    "date:inception_upper": "1993-01-01",
    "iso:country": "GB",
    "wof:name": "MK17 8JL",
    "wof:placetype": "postalcode"
  },
  "geometry": {"coordinates":[-0.62089,52.01283],"type":"Point"}
}
