{
  "type": "Feature",
  "properties": {
    "iso:country": "GB",
    "wof:name": "MK17 8JL",
    "wof:placetype": "postalcode"
  },
  "geometry": {"coordinates":[-0.62089,52.01283],"type":"Point"}
}
