{
  "type": "Feature",
  "properties": {
    "iso:country":"GB",
    "wof:name":"GL4 4BL",
    "wof:placetype":"postalcode"
},
  "geometry": {"coordinates":[-2.20615085209138,51.8413065629512],"type":"Point"}
}