{
  "type": "Feature",
  "properties": {
    "iso:country": "GB",
    "wof:name": "GL4 4BL",
    "wof:placetype": "postalcode"
  },
  "geometry": {"coordinates":[-2.204319,51.841487],"type":"Point"}
}
