{
  "type": "Feature",
  "properties": {
    "iso:country":"GB",
    "wof:name":"EH53 0HG",
    "wof:placetype":"postalcode"
},
  "geometry": {"coordinates":[-3.45805598795353,55.89746523878576],"type":"Point"}
}