{
  "type": "Feature",
  "properties": {
    "iso:country": "GB",
    "wof:name": "EH53 0HG",
    "wof:placetype": "postalcode"
  },
  "geometry": {"coordinates":[-3.458056,55.897465],"type":"Point"}
}
