{
  "type": "Feature",
  "properties": {
    "iso:country":"GB",
    "wof:name":"SA64 0LF",
    "wof:placetype":"postalcode"
},
  "geometry": {"coordinates":[-5.0453230378787,51.97503504721731],"type":"Point"}
}