{
  "type": "Feature",
  "properties": {
    "iso:country":"GB",
    "wof:name":"TS25 2BS",
    "wof:placetype":"postalcode"
},
  "geometry": {"coordinates":[-1.20185758866176,54.64949424456055],"type":"Point"}
}