{
  "type": "Feature",
  "properties": {
    "date:inception_lower":"1985-10-01",
    "date:inception_upper":"1985-10-31",
    "iso:country":"GB",
    "wof:name":"TS25 2BS",
    "wof:placetype":"postalcode"
},
  "geometry": {"coordinates":[-1.201872,54.649505],"type":"Point"}
}