{
  "type": "Feature",
  "properties": {
    "iso:country": "GB",
    "wof:name": "TS25 2BS",
    "wof:placetype": "postalcode"
  },
  "geometry": {"coordinates":[-1.201872,54.649505],"type":"Point"}
}
