{
  "type": "Feature",
  "properties": {
    "date:inception_lower": "2005-07-01",
    "date:inception_upper": "2005-07-01",
    "iso:country": "GB",
    "wof:name": "LE11 2GY",
    "wof:placetype": "postalcode"
  },
  "geometry": {"coordinates":[-1.201972,52.748428],"type":"Point"}
}
