{
  "type": "Feature",
  "properties": {
    "iso:country":"GB",
    "wof:name":"LE11 2GY",
    "wof:placetype":"postalcode"
},
  "geometry": {"coordinates":[-1.2019718838148,52.74842847962678],"type":"Point"}
}