{
  "type": "Feature",
  "properties": {
    "iso:country":"GB",
    "wof:name":"LS7 1DS",
    "wof:placetype":"postalcode"
},
  "geometry": {"coordinates":[-1.53862843470091,53.80531427370323],"type":"Point"}
}