{
  "type": "Feature",
  "properties": {
    "iso:country": "GB",
    "wof:name": "LS7 1DS",
    "wof:placetype": "postalcode"
  },
  "geometry": {"coordinates":[-1.538628,53.805314],"type":"Point"}
}
