{
  "type": "Feature",
  "properties": {
    "date:inception_lower": "2008-06-01",
    "date:inception_upper": "2008-06-01",
    "iso:country": "GB",
    "wof:name": "EH6 7EB",
    "wof:placetype": "postalcode"
  },
  "geometry": {"coordinates":[-3.163344,55.972801],"type":"Point"}
}
