{
  "type": "Feature",
  "properties": {
    "iso:country":"GB",
    "wof:name":"DE22 3GH",
    "wof:placetype":"postalcode"
},
  "geometry": {"coordinates":[-1.50017315888267,52.92596579234011],"type":"Point"}
}