{
  "type": "Feature",
  "properties": {
    "iso:country":"GB",
    "wof:name":"BR2 0TR",
    "wof:placetype":"postalcode"
},
  "geometry": {"coordinates":[0.00760599056957,51.39559149454442],"type":"Point"}
}