{
  "type": "Feature",
  "properties": {
    "iso:country":"GB",
    "wof:name":"OX1 3LJ",
    "wof:placetype":"postalcode"
},
  "geometry": {"coordinates":[-1.26091661359243,51.7584626833526],"type":"Point"}
}