{
  "type": "Feature",
  "properties": {
    "iso:country":"GB",
    "wof:name":"SW6 1UL",
    "wof:placetype":"postalcode"
},
  "geometry": {"coordinates":[-0.20155716323121,51.48555961684296],"type":"Point"}
}