{
  "type": "Feature",
  "properties": {
    "date:inception_lower":"1980-01-01",
    "date:inception_upper":"1980-01-31",
    "iso:country":"GB",
    "wof:name":"SW6 1UL",
    "wof:placetype":"postalcode"
},
  "geometry": {"coordinates":[-0.201557,51.48556],"type":"Point"}
}