{
  "type": "Feature",
  "properties": {
    "iso:country":"GB",
    "wof:name":"CA14 4QF",
    "wof:placetype":"postalcode"
},
  "geometry": {"coordinates":[-3.49996718554848,54.57693287028636],"type":"Point"}
}