{
  "type": "Feature",
  "properties": {
    "iso:country":"GB",
    "wof:name":"SE15 6FJ",
    "wof:placetype":"postalcode"
},
  "geometry": {"coordinates":[-0.07999262545309,51.47734631429812],"type":"Point"}
}