{
  "type": "Feature",
  "properties": {
    "date:inception_lower": "1993-08-01",
    "date:inception_upper": "1993-08-01",
    "iso:country": "GB",
    "wof:name": "NW4 1BZ",
    "wof:placetype": "postalcode"
  },
  "geometry": {"coordinates":[-0.219597,51.591064],"type":"Point"}
}
