{
  "type": "Feature",
  "properties": {
    "date:inception_lower": "1980-01-01",
    "date:inception_upper": "1980-01-01",
    "iso:country": "GB",
    "wof:name": "NR34 9XX",
    "wof:placetype": "postalcode"
  },
  "geometry": {"coordinates":[1.567671,52.447459],"type":"Point"}
}
