{
  "type": "Feature",
  "properties": {
    "iso:country": "GB",
    "wof:name": "CW1 3NQ",
    "wof:placetype": "postalcode"
  },
  "geometry": {"coordinates":[-2.461221,53.105185],"type":"Point"}
}
