{
  "type": "Feature",
  "properties": {
    "iso:country":"GB",
    "wof:name":"CW1 3NQ",
    "wof:placetype":"postalcode"
},
  "geometry": {"coordinates":[-2.46122137519122,53.10518505418315],"type":"Point"}
}