{
  "type": "Feature",
  "properties": {
    "iso:country": "GB",
    "wof:name": "E11 2DT",
    "wof:placetype": "postalcode"
  },
  "geometry": {"coordinates":[0.030471,51.58186],"type":"Point"}
}
