{
  "type": "Feature",
  "properties": {
    "iso:country":"GB",
    "wof:name":"SN8 1SP",
    "wof:placetype":"postalcode"
},
  "geometry": {"coordinates":[-1.71392366645856,51.46898361233269],"type":"Point"}
}