{
  "type": "Feature",
  "properties": {
    "date:inception_lower": "1980-01-01",
    "date:inception_upper": "1980-01-01",
    "iso:country": "GB",
    "wof:name": "SN8 1SP",
    "wof:placetype": "postalcode"
  },
  "geometry": {"coordinates":[-1.713924,51.468984],"type":"Point"}
}
