{
  "type": "Feature",
  "properties": {
    "date:inception_lower":"2005-12-01",
    "date:inception_upper":"2005-12-31",
    "iso:country":"GB",
    "wof:name":"ME15 6FP",
    "wof:placetype":"postalcode"
},
  "geometry": {"coordinates":[0.510449,51.260101],"type":"Point"}
}