{
  "type": "Feature",
  "properties": {
    "iso:country":"GB",
    "wof:name":"DL14 6JN",
    "wof:placetype":"postalcode"
},
  "geometry": {"coordinates":[-1.6784949723533,54.6506624550906],"type":"Point"}
}