{
  "type": "Feature",
  "properties": {
    "iso:country":"GB",
    "wof:name":"NG5 1AZ",
    "wof:placetype":"postalcode"
},
  "geometry": {"coordinates":[-1.15590093880077,52.971834864561],"type":"Point"}
}