{
  "type": "Feature",
  "properties": {
    "iso:country": "GB",
    "wof:name": "NG5 1AZ",
    "wof:placetype": "postalcode"
  },
  "geometry": {"coordinates":[-1.155901,52.971835],"type":"Point"}
}
