{
  "type": "Feature",
  "properties": {
    "iso:country": "GB",
    "wof:name": "TR13 8SH",
    "wof:placetype": "postalcode"
  },
  "geometry": {"coordinates":[-5.271627,50.097237],"type":"Point"}
}
