{
  "type": "Feature",
  "properties": {
    "iso:country":"GB",
    "wof:name":"W5 4DJ",
    "wof:placetype":"postalcode"
},
  "geometry": {"coordinates":[-0.31422630987882,51.49510169755369],"type":"Point"}
}