{
  "type": "Feature",
  "properties": {
    "iso:country": "GB",
    "wof:name": "YO41 1FG",
    "wof:placetype": "postalcode"
  },
  "geometry": {"coordinates":[-0.90879,53.994371],"type":"Point"}
}
