{
  "type": "Feature",
  "properties": {
    "iso:country":"GB",
    "wof:name":"L7 5QQ",
    "wof:placetype":"postalcode"
},
  "geometry": {"coordinates":[-2.94607181968999,53.40645606246331],"type":"Point"}
}