{
  "type": "Feature",
  "properties": {
    "iso:country": "GB",
    "wof:name": "L7 5QQ",
    "wof:placetype": "postalcode"
  },
  "geometry": {"coordinates":[-2.946072,53.406456],"type":"Point"}
}
