{
  "type": "Feature",
  "properties": {
    "iso:country": "GB",
    "wof:name": "SW18 1RB",
    "wof:placetype": "postalcode"
  },
  "geometry": {"coordinates":[-0.199768,51.456747],"type":"Point"}
}
