{
  "type": "Feature",
  "properties": {
    "iso:country":"GB",
    "wof:name":"SW18 1RB",
    "wof:placetype":"postalcode"
},
  "geometry": {"coordinates":[-0.19976783157118,51.45674717360716],"type":"Point"}
}