{
  "type": "Feature",
  "properties": {
    "iso:country": "GB",
    "wof:name": "DH3 4BW",
    "wof:placetype": "postalcode"
  },
  "geometry": {"coordinates":[-1.569413,54.876912],"type":"Point"}
}
