{
  "type": "Feature",
  "properties": {
    "date:inception_lower": "2018-07-01",
    "date:inception_upper": "2018-07-01",
    "iso:country": "GB",
    "wof:name": "BD13 5FJ",
    "wof:placetype": "postalcode"
  },
  "geometry": {"coordinates":[-1.89804,53.821208],"type":"Point"}
}
