{
  "type": "Feature",
  "properties": {
    "iso:country":"GB",
    "wof:name":"SY5 6PA",
    "wof:placetype":"postalcode"
},
  "geometry": {"coordinates":[-2.62611074227119,52.59976815522474],"type":"Point"}
}