{
  "type": "Feature",
  "properties": {
    "iso:country":"GB",
    "wof:name":"RG9 9GY",
    "wof:placetype":"postalcode"
},
  "geometry": {"coordinates":[-0.90401959175617,51.53593145598853],"type":"Point"}
}