{
  "type": "Feature",
  "properties": {
    "date:inception_lower": "2017-09-01",
    "date:inception_upper": "2017-09-01",
    "iso:country": "GB",
    "wof:name": "CB3 0UD",
    "wof:placetype": "postalcode"
  },
  "geometry": {"coordinates":[0.094111,52.216392],"type":"Point"}
}
