{
  "type": "Feature",
  "properties": {
    "iso:country": "GB",
    "wof:name": "CB3 0UD",
    "wof:placetype": "postalcode"
  },
  "geometry": {"coordinates":[0.094111,52.216392],"type":"Point"}
}
