{
  "type": "Feature",
  "properties": {
    "date:inception_lower": "1980-01-01",
    "date:inception_upper": "1980-01-01",
    "iso:country": "GB",
    "wof:name": "PA3 3LJ",
    "wof:placetype": "postalcode"
  },
  "geometry": {"coordinates":[-4.509352,55.846554],"type":"Point"}
}
