{
  "type": "Feature",
  "properties": {
    "iso:country":"GB",
    "wof:name":"PA3 3LJ",
    "wof:placetype":"postalcode"
},
  "geometry": {"coordinates":[-4.50935163035016,55.84655386236858],"type":"Point"}
}