{
  "type": "Feature",
  "properties": {
    "date:inception_lower": "1980-01-01",
    "date:inception_upper": "1980-01-01",
    "iso:country": "GB",
    "wof:name": "IP19 0HA",
    "wof:placetype": "postalcode"
  },
  "geometry": {"coordinates":[1.403159,52.294114],"type":"Point"}
}
