{
  "type": "Feature",
  "properties": {
    "iso:country":"GB",
    "wof:name":"IP19 0HA",
    "wof:placetype":"postalcode"
},
  "geometry": {"coordinates":[1.40315875882619,52.29411364452277],"type":"Point"}
}