{
  "type": "Feature",
  "properties": {
    "iso:country": "GB",
    "wof:name": "IP19 0HA",
    "wof:placetype": "postalcode"
  },
  "geometry": {"coordinates":[1.403159,52.294114],"type":"Point"}
}
