{
  "type": "Feature",
  "properties": {
    "iso:country":"GB",
    "wof:name":"DT11 9JH",
    "wof:placetype":"postalcode"
},
  "geometry": {"coordinates":[-2.09579781430756,50.84013128910713],"type":"Point"}
}