{
  "type": "Feature",
  "properties": {
    "iso:country": "GB",
    "wof:name": "DT11 9JH",
    "wof:placetype": "postalcode"
  },
  "geometry": {"coordinates":[-2.095798,50.840131],"type":"Point"}
}
