{
  "type": "Feature",
  "properties": {
    "iso:country": "GB",
    "wof:name": "SE10 0TG",
    "wof:placetype": "postalcode"
  },
  "geometry": {"coordinates":[0.003254,51.490433],"type":"Point"}
}
