{
  "type": "Feature",
  "properties": {
    "date:inception_lower":"1990-02-01",
    "date:inception_upper":"1990-02-28",
    "iso:country":"GB",
    "wof:name":"LL19 9TJ",
    "wof:placetype":"postalcode"
},
  "geometry": {"coordinates":[-3.36406,53.337958],"type":"Point"}
}