{
  "type": "Feature",
  "properties": {
    "iso:country":"GB",
    "wof:name":"LL19 9TJ",
    "wof:placetype":"postalcode"
},
  "geometry": {"coordinates":[-3.36405979175757,53.33795815978895],"type":"Point"}
}