{
  "type": "Feature",
  "properties": {
    "iso:country": "GB",
    "wof:name": "LL19 9TJ",
    "wof:placetype": "postalcode"
  },
  "geometry": {"coordinates":[-3.36406,53.337958],"type":"Point"}
}
