{
  "type": "Feature",
  "properties": {
    "iso:country": "GB",
    "wof:name": "ST5 2NU",
    "wof:placetype": "postalcode"
  },
  "geometry": {"coordinates":[-2.241734,53.008194],"type":"Point"}
}
