{
  "type": "Feature",
  "properties": {
    "iso:country":"GB",
    "wof:name":"ST5 2NU",
    "wof:placetype":"postalcode"
},
  "geometry": {"coordinates":[-2.24173382517592,53.00819396336377],"type":"Point"}
}