{
  "type": "Feature",
  "properties": {
    "date:inception_lower":"1999-12-01",
    "date:inception_upper":"1999-12-31",
    "iso:country":"GB",
    "wof:name":"KT14 7YX",
    "wof:placetype":"postalcode"
},
  "geometry": {"coordinates":[-0.47877,51.346074],"type":"Point"}
}