{
  "type": "Feature",
  "properties": {
    "iso:country":"GB",
    "wof:name":"FY6 7LT",
    "wof:placetype":"postalcode"
},
  "geometry": {"coordinates":[-3.00096398196488,53.84855409415785],"type":"Point"}
}