{
  "type": "Feature",
  "properties": {
    "date:inception_lower": "1980-01-01",
    "date:inception_upper": "1980-01-01",
    "iso:country": "GB",
    "wof:name": "DA7 4HA",
    "wof:placetype": "postalcode"
  },
  "geometry": {"coordinates":[0.130768,51.459794],"type":"Point"}
}
