{
  "type": "Feature",
  "properties": {
    "iso:country":"GB",
    "wof:name":"DA7 4HA",
    "wof:placetype":"postalcode"
},
  "geometry": {"coordinates":[0.13080181277913,51.45987370466927],"type":"Point"}
}