{
  "type": "Feature",
  "properties": {
    "date:inception_lower": "2005-07-01",
    "date:inception_upper": "2005-07-01",
    "iso:country": "GB",
    "wof:name": "KY8 4FH",
    "wof:placetype": "postalcode"
  },
  "geometry": {"coordinates":[-3.027739,56.196055],"type":"Point"}
}
