{
  "type": "Feature",
  "properties": {
    "iso:country": "GB",
    "wof:name": "HU12 9RE",
    "wof:placetype": "postalcode"
  },
  "geometry": {"coordinates":[-0.112089,53.709898],"type":"Point"}
}
