{
  "type": "Feature",
  "properties": {
    "iso:country":"GB",
    "wof:name":"ML3 7FN",
    "wof:placetype":"postalcode"
},
  "geometry": {"coordinates":[-4.00305557717406,55.76660070572894],"type":"Point"}
}