{
  "type": "Feature",
  "properties": {
    "iso:country": "GB",
    "wof:name": "ML3 7FN",
    "wof:placetype": "postalcode"
  },
  "geometry": {"coordinates":[-4.002984,55.766625],"type":"Point"}
}
