{
  "type": "Feature",
  "properties": {
    "iso:country":"GB",
    "wof:name":"SK17 8QN",
    "wof:placetype":"postalcode"
},
  "geometry": {"coordinates":[-1.76181717180716,53.27121056915703],"type":"Point"}
}