{
  "type": "Feature",
  "properties": {
    "date:inception_lower": "2006-07-01",
    "date:inception_upper": "2006-07-01",
    "iso:country": "GB",
    "wof:name": "CF82 7GW",
    "wof:placetype": "postalcode"
  },
  "geometry": {"coordinates":[-3.240238,51.650376],"type":"Point"}
}
