{
  "type": "Feature",
  "properties": {
    "iso:country":"GB",
    "wof:name":"EN6 4HJ",
    "wof:placetype":"postalcode"
},
  "geometry": {"coordinates":[-0.11180475480744,51.70467005293984],"type":"Point"}
}