{
  "type": "Feature",
  "properties": {
    "date:inception_lower": "2020-12-01",
    "date:inception_upper": "2020-12-01",
    "iso:country": "GB",
    "wof:name": "CV23 1BG",
    "wof:placetype": "postalcode"
  },
  "geometry": {"coordinates":[-1.191438,52.360866],"type":"Point"}
}
