{
  "type": "Feature",
  "properties": {
    "iso:country":"GB",
    "wof:name":"G83 9JQ",
    "wof:placetype":"postalcode"
},
  "geometry": {"coordinates":[-4.57069045722646,55.98080146996141],"type":"Point"}
}