{
  "type": "Feature",
  "properties": {
    "date:inception_lower":"1980-01-01",
    "date:inception_upper":"1980-01-31",
    "iso:country":"GB",
    "wof:name":"PE12 8BB",
    "wof:placetype":"postalcode"
},
  "geometry": {"coordinates":[-0.009515,52.825268],"type":"Point"}
}