{
  "type": "Feature",
  "properties": {
    "iso:country": "GB",
    "wof:name": "PE12 8BB",
    "wof:placetype": "postalcode"
  },
  "geometry": {"coordinates":[-0.009515,52.825268],"type":"Point"}
}
