{
  "type": "Feature",
  "properties": {
    "iso:country":"GB",
    "wof:name":"PE12 8BB",
    "wof:placetype":"postalcode"
},
  "geometry": {"coordinates":[-0.00954161195141,52.82524709125736],"type":"Point"}
}