{
  "type": "Feature",
  "properties": {
    "iso:country": "GB",
    "wof:name": "MK8 8HG",
    "wof:placetype": "postalcode"
  },
  "geometry": {"coordinates":[-0.802193,52.038153],"type":"Point"}
}
