{
  "type": "Feature",
  "properties": {
    "iso:country":"GB",
    "wof:name":"TF2 9LG",
    "wof:placetype":"postalcode"
},
  "geometry": {"coordinates":[-2.43352235439426,52.69220882483749],"type":"Point"}
}