{
  "type": "Feature",
  "properties": {
    "iso:country":"GB",
    "wof:name":"M34 3BW",
    "wof:placetype":"postalcode"
},
  "geometry": {"coordinates":[-2.10626078196501,53.45974773617142],"type":"Point"}
}