{
  "type": "Feature",
  "properties": {
    "iso:country":"GB",
    "wof:name":"S6 4HL",
    "wof:placetype":"postalcode"
},
  "geometry": {"coordinates":[-1.50156330461483,53.40330600221342],"type":"Point"}
}