{
  "type": "Feature",
  "properties": {
    "date:inception_lower": "1981-06-01",
    "date:inception_upper": "1981-06-01",
    "iso:country": "GB",
    "wof:name": "S6 4HL",
    "wof:placetype": "postalcode"
  },
  "geometry": {"coordinates":[-1.501504,53.403296],"type":"Point"}
}
