{
  "type": "Feature",
  "properties": {
    "iso:country": "GB",
    "wof:name": "S6 4HL",
    "wof:placetype": "postalcode"
  },
  "geometry": {"coordinates":[-1.501563,53.403306],"type":"Point"}
}
