{
  "type": "Feature",
  "properties": {
    "date:inception_lower":"1980-01-01",
    "date:inception_upper":"1980-01-31",
    "iso:country":"GB",
    "wof:name":"SK17 9TL",
    "wof:placetype":"postalcode"
},
  "geometry": {"coordinates":[-1.799316,53.239702],"type":"Point"}
}