{
  "type": "Feature",
  "properties": {
    "date:inception_lower":"1980-01-01",
    "date:inception_upper":"1980-01-31",
    "iso:country":"GB",
    "wof:name":"NR19 1JH",
    "wof:placetype":"postalcode"
},
  "geometry": {"coordinates":[0.940903,52.66527],"type":"Point"}
}