{
  "type": "Feature",
  "properties": {
    "iso:country": "GB",
    "wof:name": "NR19 1JH",
    "wof:placetype": "postalcode"
  },
  "geometry": {"coordinates":[0.940903,52.66527],"type":"Point"}
}
