{
  "type": "Feature",
  "properties": {
    "date:inception_lower": "1980-01-01",
    "date:inception_upper": "1980-01-01",
    "iso:country": "GB",
    "wof:name": "BH21 7BQ",
    "wof:placetype": "postalcode"
  },
  "geometry": {"coordinates":[-1.926993,50.81648],"type":"Point"}
}
