{
  "type": "Feature",
  "properties": {
    "iso:country":"GB",
    "wof:name":"BH21 7BQ",
    "wof:placetype":"postalcode"
},
  "geometry": {"coordinates":[-1.93152972526407,50.81605098360966],"type":"Point"}
}