{
  "type": "Feature",
  "properties": {
    "iso:country": "GB",
    "wof:name": "BH21 7BQ",
    "wof:placetype": "postalcode"
  },
  "geometry": {"coordinates":[-1.926993,50.81648],"type":"Point"}
}
