{
  "type": "Feature",
  "properties": {
    "date:inception_lower": "1980-01-01",
    "date:inception_upper": "1980-01-01",
    "iso:country": "GB",
    "wof:name": "BN2 3JD",
    "wof:placetype": "postalcode"
  },
  "geometry": {"coordinates":[-0.13073,50.833268],"type":"Point"}
}
