{
  "type": "Feature",
  "properties": {
    "iso:country":"GB",
    "wof:name":"BN2 3JD",
    "wof:placetype":"postalcode"
},
  "geometry": {"coordinates":[-0.13072967212865,50.83326826123594],"type":"Point"}
}