{
  "type": "Feature",
  "properties": {
    "iso:country":"GB",
    "wof:name":"CF71 7EU",
    "wof:placetype":"postalcode"
},
  "geometry": {"coordinates":[-3.4411212890926,51.45940248541851],"type":"Point"}
}