{
  "type": "Feature",
  "properties": {
    "iso:country":"GB",
    "wof:name":"ML6 8QL",
    "wof:placetype":"postalcode"
},
  "geometry": {"coordinates":[-3.91240920085402,55.85366229920435],"type":"Point"}
}