{
  "type": "Feature",
  "properties": {
    "iso:country":"GB",
    "wof:name":"E8 2LA",
    "wof:placetype":"postalcode"
},
  "geometry": {"coordinates":[-0.07667025508672,51.5467056082765],"type":"Point"}
}