{
  "type": "Feature",
  "properties": {
    "iso:country":"GB",
    "wof:name":"CO8 5BQ",
    "wof:placetype":"postalcode"
},
  "geometry": {"coordinates":[0.77237215950591,51.96684846274095],"type":"Point"}
}