{
  "type": "Feature",
  "properties": {
    "iso:country": "GB",
    "wof:name": "LA12 7TN",
    "wof:placetype": "postalcode"
  },
  "geometry": {"coordinates":[-3.101916,54.193362],"type":"Point"}
}
