{
  "type": "Feature",
  "properties": {
    "iso:country":"GB",
    "wof:name":"NE46 3SH",
    "wof:placetype":"postalcode"
},
  "geometry": {"coordinates":[-2.11626352055214,54.97498448390396],"type":"Point"}
}