{
  "type": "Feature",
  "properties": {
    "iso:country": "GB",
    "wof:name": "NE46 3SH",
    "wof:placetype": "postalcode"
  },
  "geometry": {"coordinates":[-2.116263,54.974984],"type":"Point"}
}
