{
  "type": "Feature",
  "properties": {
    "iso:country":"GB",
    "wof:name":"S71 4BD",
    "wof:placetype":"postalcode"
},
  "geometry": {"coordinates":[-1.43275401830752,53.60301187200957],"type":"Point"}
}