{
  "type": "Feature",
  "properties": {
    "iso:country":"GB",
    "wof:name":"CF5 3NQ",
    "wof:placetype":"postalcode"
},
  "geometry": {"coordinates":[-3.24295292806012,51.49849343841997],"type":"Point"}
}