{
  "type": "Feature",
  "properties": {
    "iso:country":"GB",
    "wof:name":"G52 1AZ",
    "wof:placetype":"postalcode"
},
  "geometry": {"coordinates":[-4.32520166150331,55.848681508068],"type":"Point"}
}