{
  "type": "Feature",
  "properties": {
    "date:inception_lower": "1980-01-01",
    "date:inception_upper": "1980-01-01",
    "iso:country": "GB",
    "wof:name": "G52 1AZ",
    "wof:placetype": "postalcode"
  },
  "geometry": {"coordinates":[-4.325202,55.848682],"type":"Point"}
}
