{
  "type": "Feature",
  "properties": {
    "iso:country": "GB",
    "wof:name": "G52 1AZ",
    "wof:placetype": "postalcode"
  },
  "geometry": {"coordinates":[-4.325202,55.848682],"type":"Point"}
}
