{
  "type": "Feature",
  "properties": {
    "iso:country":"GB",
    "wof:name":"RH6 8LT",
    "wof:placetype":"postalcode"
},
  "geometry": {"coordinates":[-0.17693403834876,51.1853893383641],"type":"Point"}
}