{
  "type": "Feature",
  "properties": {
    "iso:country": "GB",
    "wof:name": "RH6 8LT",
    "wof:placetype": "postalcode"
  },
  "geometry": {"coordinates":[-0.176934,51.185389],"type":"Point"}
}
