{
  "type": "Feature",
  "properties": {
    "date:inception_lower": "1980-01-01",
    "date:inception_upper": "1980-01-01",
    "iso:country": "GB",
    "wof:name": "SM6 8SS",
    "wof:placetype": "postalcode"
  },
  "geometry": {"coordinates":[-0.14237,51.36222],"type":"Point"}
}
