{
  "type": "Feature",
  "properties": {
    "iso:country": "GB",
    "wof:name": "S41 0JL",
    "wof:placetype": "postalcode"
  },
  "geometry": {"coordinates":[-1.393596,53.213762],"type":"Point"}
}
