{
  "type": "Feature",
  "properties": {
    "iso:country":"GB",
    "wof:name":"S41 0JL",
    "wof:placetype":"postalcode"
},
  "geometry": {"coordinates":[-1.39359640474868,53.21376250013816],"type":"Point"}
}