{
  "type": "Feature",
  "properties": {
    "date:inception_lower": "2017-10-01",
    "date:inception_upper": "2017-10-01",
    "iso:country": "GB",
    "wof:name": "RG2 0GG",
    "wof:placetype": "postalcode"
  },
  "geometry": {"coordinates":[-0.974074,51.417631],"type":"Point"}
}
