{
  "type": "Feature",
  "properties": {
    "iso:country":"GB",
    "wof:name":"SE10 9HQ",
    "wof:placetype":"postalcode"
},
  "geometry": {"coordinates":[0.00876620305248,51.48436635627851],"type":"Point"}
}