{
  "type": "Feature",
  "properties": {
    "date:inception_lower": "2016-07-01",
    "date:inception_upper": "2016-07-01",
    "iso:country": "GB",
    "wof:name": "S75 1AR",
    "wof:placetype": "postalcode"
  },
  "geometry": {"coordinates":[-1.50328,53.567255],"type":"Point"}
}
