{
  "type": "Feature",
  "properties": {
    "iso:country":"GB",
    "wof:name":"HP3 8HN",
    "wof:placetype":"postalcode"
},
  "geometry": {"coordinates":[-0.4389134934718,51.74630269138573],"type":"Point"}
}