{
  "type": "Feature",
  "properties": {
    "iso:country":"GB",
    "wof:name":"PL14 4HN",
    "wof:placetype":"postalcode"
},
  "geometry": {"coordinates":[-4.47519720589796,50.45202321669319],"type":"Point"}
}