{
  "type": "Feature",
  "properties": {
    "iso:country": "GB",
    "wof:name": "IP22 1QR",
    "wof:placetype": "postalcode"
  },
  "geometry": {"coordinates":[1.059356,52.352255],"type":"Point"}
}
