{
  "type": "Feature",
  "properties": {
    "date:inception_lower": "2012-04-01",
    "date:inception_upper": "2012-04-01",
    "iso:country": "GB",
    "wof:name": "IP22 1QR",
    "wof:placetype": "postalcode"
  },
  "geometry": {"coordinates":[1.059419,52.35212],"type":"Point"}
}
