{
  "type": "Feature",
  "properties": {
    "iso:country":"GB",
    "wof:name":"B32 3TD",
    "wof:placetype":"postalcode"
},
  "geometry": {"coordinates":[-1.99708709815167,52.44529684106036],"type":"Point"}
}