{
  "type": "Feature",
  "properties": {
    "date:inception_lower": "1991-09-01",
    "date:inception_upper": "1991-09-01",
    "iso:country": "GB",
    "wof:name": "TA19 9SQ",
    "wof:placetype": "postalcode"
  },
  "geometry": {"coordinates":[-2.9665,50.929222],"type":"Point"}
}
