{
  "type": "Feature",
  "properties": {
    "iso:country":"GB",
    "wof:name":"EN4 8LE",
    "wof:placetype":"postalcode"
},
  "geometry": {"coordinates":[-0.1462305270852,51.63359479664766],"type":"Point"}
}