{
  "type": "Feature",
  "properties": {
    "date:inception_lower": "1992-01-01",
    "date:inception_upper": "1992-01-01",
    "iso:country": "GB",
    "wof:name": "RH11 9SH",
    "wof:placetype": "postalcode"
  },
  "geometry": {"coordinates":[-0.205896,51.098003],"type":"Point"}
}
