{
  "type": "Feature",
  "properties": {
    "date:inception_lower": "2017-07-01",
    "date:inception_upper": "2017-07-01",
    "iso:country": "GB",
    "wof:name": "DE65 5AD",
    "wof:placetype": "postalcode"
  },
  "geometry": {"coordinates":[-1.627241,52.864279],"type":"Point"}
}
