{
  "type": "Feature",
  "properties": {
    "iso:country": "GB",
    "wof:name": "WA7 3JN",
    "wof:placetype": "postalcode"
  },
  "geometry": {"coordinates":[-2.699277,53.316058],"type":"Point"}
}
