{
  "type": "Feature",
  "properties": {
    "iso:country":"GB",
    "wof:name":"WA7 3JN",
    "wof:placetype":"postalcode"
},
  "geometry": {"coordinates":[-2.69927693723546,53.31605750403565],"type":"Point"}
}