{
  "type": "Feature",
  "properties": {
    "iso:country": "GB",
    "wof:name": "PO18 9LT",
    "wof:placetype": "postalcode"
  },
  "geometry": {"coordinates":[-0.865553,50.869597],"type":"Point"}
}
