{
  "type": "Feature",
  "properties": {
    "iso:country":"GB",
    "wof:name":"LN5 7QR",
    "wof:placetype":"postalcode"
},
  "geometry": {"coordinates":[-0.54660285538022,53.22078238974385],"type":"Point"}
}