{
  "type": "Feature",
  "properties": {
    "iso:country": "GB",
    "wof:name": "LN5 7QR",
    "wof:placetype": "postalcode"
  },
  "geometry": {"coordinates":[-0.546603,53.220786],"type":"Point"}
}
