{
  "type": "Feature",
  "properties": {
    "iso:country":"GB",
    "wof:name":"CA12 4TG",
    "wof:placetype":"postalcode"
},
  "geometry": {"coordinates":[-3.0614363523529,54.56499319633424],"type":"Point"}
}