{
  "type": "Feature",
  "properties": {
    "iso:country": "GB",
    "wof:name": "CA12 4TG",
    "wof:placetype": "postalcode"
  },
  "geometry": {"coordinates":[-3.061436,54.564993],"type":"Point"}
}
