{
  "type": "Feature",
  "properties": {
    "iso:country":"GB",
    "wof:name":"N1 3RD",
    "wof:placetype":"postalcode"
},
  "geometry": {"coordinates":[-0.09378572214965,51.54094198133841],"type":"Point"}
}