{
  "type": "Feature",
  "properties": {
    "iso:country": "GB",
    "wof:name": "BD14 6JU",
    "wof:placetype": "postalcode"
  },
  "geometry": {"coordinates":[-1.811217,53.782297],"type":"Point"}
}
