{
  "type": "Feature",
  "properties": {
    "iso:country":"GB",
    "wof:name":"CT6 8QD",
    "wof:placetype":"postalcode"
},
  "geometry": {"coordinates":[1.11220660745354,51.36816508746862],"type":"Point"}
}