{
  "type": "Feature",
  "properties": {
    "iso:country": "GB",
    "wof:name": "PL33 9ED",
    "wof:placetype": "postalcode"
  },
  "geometry": {"coordinates":[-4.762624,50.621464],"type":"Point"}
}
