{
  "type": "Feature",
  "properties": {
    "iso:country":"GB",
    "wof:name":"LE2 6EA",
    "wof:placetype":"postalcode"
},
  "geometry": {"coordinates":[-1.12429121081576,52.61188992254056],"type":"Point"}
}