{
  "type": "Feature",
  "properties": {
    "iso:country":"GB",
    "wof:name":"CV21 4DZ",
    "wof:placetype":"postalcode"
},
  "geometry": {"coordinates":[-1.20347968308533,52.35670520082077],"type":"Point"}
}