{
  "type": "Feature",
  "properties": {
    "iso:country": "GB",
    "wof:name": "CV21 4DZ",
    "wof:placetype": "postalcode"
  },
  "geometry": {"coordinates":[-1.20348,52.356705],"type":"Point"}
}
