{
  "type": "Feature",
  "properties": {
    "date:inception_lower": "2016-09-01",
    "date:inception_upper": "2016-09-01",
    "iso:country": "GB",
    "wof:name": "M26 4AA",
    "wof:placetype": "postalcode"
  },
  "geometry": {"coordinates":[-2.326969,53.564554],"type":"Point"}
}
