{
  "type": "Feature",
  "properties": {
    "iso:country":"GB",
    "wof:name":"EH11 3PW",
    "wof:placetype":"postalcode"
},
  "geometry": {"coordinates":[-3.2683617346488,55.9282209335784],"type":"Point"}
}