{
  "type": "Feature",
  "properties": {
    "iso:country": "GB",
    "wof:name": "OX1 3QF",
    "wof:placetype": "postalcode"
  },
  "geometry": {"coordinates":[-1.258316,51.758033],"type":"Point"}
}
