{
  "type": "Feature",
  "properties": {
    "iso:country":"GB",
    "wof:name":"OX1 3QF",
    "wof:placetype":"postalcode"
},
  "geometry": {"coordinates":[-1.25831571952708,51.7580327100685],"type":"Point"}
}