{
  "type": "Feature",
  "properties": {
    "iso:country": "GB",
    "wof:name": "TN12 9RP",
    "wof:placetype": "postalcode"
  },
  "geometry": {"coordinates":[0.451625,51.194669],"type":"Point"}
}
