{
  "type": "Feature",
  "properties": {
    "iso:country":"GB",
    "wof:name":"N17 9HX",
    "wof:placetype":"postalcode"
},
  "geometry": {"coordinates":[-0.06970776599495,51.5902229330785],"type":"Point"}
}