{
  "type": "Feature",
  "properties": {
    "iso:country":"GB",
    "wof:name":"M24 1WQ",
    "wof:placetype":"postalcode"
},
  "geometry": {"coordinates":[-2.20096948287755,53.5342297095064],"type":"Point"}
}