{
  "type": "Feature",
  "properties": {
    "date:inception_lower": "1994-05-01",
    "date:inception_upper": "1994-05-01",
    "iso:country": "GB",
    "wof:name": "M24 1WQ",
    "wof:placetype": "postalcode"
  },
  "geometry": {"coordinates":[-2.200969,53.53423],"type":"Point"}
}
