{
  "type": "Feature",
  "properties": {
    "iso:country":"GB",
    "wof:name":"EH39 5LJ",
    "wof:placetype":"postalcode"
},
  "geometry": {"coordinates":[-2.74551352586719,55.99955065613018],"type":"Point"}
}