{
  "type": "Feature",
  "properties": {
    "iso:country":"GB",
    "wof:name":"L23 8UL",
    "wof:placetype":"postalcode"
},
  "geometry": {"coordinates":[-3.03893321339177,53.49108767813141],"type":"Point"}
}