{
  "type": "Feature",
  "properties": {
    "iso:country": "GB",
    "wof:name": "OL2 6UH",
    "wof:placetype": "postalcode"
  },
  "geometry": {"coordinates":[-2.129294,53.575172],"type":"Point"}
}
