{
  "type": "Feature",
  "properties": {
    "iso:country": "GB",
    "wof:name": "TF11 8FX",
    "wof:placetype": "postalcode"
  },
  "geometry": {"coordinates":[-2.373923,52.67478],"type":"Point"}
}
