{
  "type": "Feature",
  "properties": {
    "iso:country":"GB",
    "wof:name":"SW1P 4DD",
    "wof:placetype":"postalcode"
},
  "geometry": {"coordinates":[-0.12697662248204,51.49330368976315],"type":"Point"}
}