{
  "type": "Feature",
  "properties": {
    "date:inception_lower": "2003-02-01",
    "date:inception_upper": "2003-02-01",
    "iso:country": "GB",
    "wof:name": "SW1P 4DD",
    "wof:placetype": "postalcode"
  },
  "geometry": {"coordinates":[-0.126977,51.493304],"type":"Point"}
}
