{
  "type": "Feature",
  "properties": {
    "iso:country": "GB",
    "wof:name": "RH10 3DS",
    "wof:placetype": "postalcode"
  },
  "geometry": {"coordinates":[-0.150383,51.124054],"type":"Point"}
}
