{
  "type": "Feature",
  "properties": {
    "iso:country":"GB",
    "wof:name":"RH10 3DS",
    "wof:placetype":"postalcode"
},
  "geometry": {"coordinates":[-0.15038309768347,51.12405402516641],"type":"Point"}
}