{
  "type": "Feature",
  "properties": {
    "date:inception_lower": "2017-11-01",
    "date:inception_upper": "2017-11-01",
    "iso:country": "GB",
    "wof:name": "KY8 4FS",
    "wof:placetype": "postalcode"
  },
  "geometry": {"coordinates":[-3.037961,56.196681],"type":"Point"}
}
