{
  "type": "Feature",
  "properties": {
    "iso:country": "GB",
    "wof:name": "TF2 6QQ",
    "wof:placetype": "postalcode"
  },
  "geometry": {"coordinates":[-2.462668,52.70772],"type":"Point"}
}
