{
  "type": "Feature",
  "properties": {
    "iso:country":"GB",
    "wof:name":"DY14 8TU",
    "wof:placetype":"postalcode"
},
  "geometry": {"coordinates":[-2.48591434741465,52.44281427655682],"type":"Point"}
}