{
  "type": "Feature",
  "properties": {
    "iso:country":"GB",
    "wof:name":"LS23 6DT",
    "wof:placetype":"postalcode"
},
  "geometry": {"coordinates":[-1.34396428662882,53.90236867367175],"type":"Point"}
}