{
  "type": "Feature",
  "properties": {
    "date:inception_lower":"2001-12-01",
    "date:inception_upper":"2001-12-31",
    "iso:country":"GB",
    "wof:name":"NE1 3DY",
    "wof:placetype":"postalcode"
},
  "geometry": {"coordinates":[-1.597491,54.97132],"type":"Point"}
}