{
  "type": "Feature",
  "properties": {
    "iso:country":"GB",
    "wof:name":"NE1 3DY",
    "wof:placetype":"postalcode"
},
  "geometry": {"coordinates":[-1.59749126604063,54.97131985413859],"type":"Point"}
}