{
  "type": "Feature",
  "properties": {
    "date:inception_lower": "2014-02-01",
    "date:inception_upper": "2014-02-01",
    "iso:country": "GB",
    "wof:name": "CA11 7FN",
    "wof:placetype": "postalcode"
  },
  "geometry": {"coordinates":[-2.752205,54.662133],"type":"Point"}
}
