{
  "type": "Feature",
  "properties": {
    "iso:country":"GB",
    "wof:name":"CA11 7FN",
    "wof:placetype":"postalcode"
},
  "geometry": {"coordinates":[-2.75220515569998,54.66213289241962],"type":"Point"}
}