{
  "type": "Feature",
  "properties": {
    "iso:country":"GB",
    "wof:name":"NG18 3PQ",
    "wof:placetype":"postalcode"
},
  "geometry": {"coordinates":[-1.16403629210393,53.14122458418829],"type":"Point"}
}