{
  "type": "Feature",
  "properties": {
    "iso:country":"GB",
    "wof:name":"M21 0QY",
    "wof:placetype":"postalcode"
},
  "geometry": {"coordinates":[-2.2707758208538,53.44634662553562],"type":"Point"}
}