{
  "type": "Feature",
  "properties": {
    "date:inception_lower": "1980-01-01",
    "date:inception_upper": "1980-01-01",
    "iso:country": "GB",
    "wof:name": "TA24 8RL",
    "wof:placetype": "postalcode"
  },
  "geometry": {"coordinates":[-3.525035,51.181922],"type":"Point"}
}
