{
  "type": "Feature",
  "properties": {
    "date:inception_lower": "1980-01-01",
    "date:inception_upper": "1980-01-01",
    "iso:country": "GB",
    "wof:name": "BA11 5AN",
    "wof:placetype": "postalcode"
  },
  "geometry": {"coordinates":[-2.314956,51.221591],"type":"Point"}
}
