{
  "type": "Feature",
  "properties": {
    "iso:country":"GB",
    "wof:name":"B90 4SB",
    "wof:placetype":"postalcode"
},
  "geometry": {"coordinates":[-1.80509426048961,52.40059097671745],"type":"Point"}
}