{
  "type": "Feature",
  "properties": {
    "iso:country":"GB",
    "wof:name":"PH2 0HG",
    "wof:placetype":"postalcode"
},
  "geometry": {"coordinates":[-3.4444113213914,56.38779683281621],"type":"Point"}
}