{
  "type": "Feature",
  "properties": {
    "date:inception_lower":"1980-01-01",
    "date:inception_upper":"1980-01-31",
    "iso:country":"GB",
    "wof:name":"PH2 0HG",
    "wof:placetype":"postalcode"
},
  "geometry": {"coordinates":[-3.444411,56.387797],"type":"Point"}
}