{
  "type": "Feature",
  "properties": {
    "date:inception_lower": "1980-01-01",
    "date:inception_upper": "1980-01-01",
    "iso:country": "GB",
    "wof:name": "CH4 0LT",
    "wof:placetype": "postalcode"
  },
  "geometry": {"coordinates":[-3.041175,53.151181],"type":"Point"}
}
