{
  "type": "Feature",
  "properties": {
    "iso:country":"GB",
    "wof:name":"CH4 0LT",
    "wof:placetype":"postalcode"
},
  "geometry": {"coordinates":[-3.04117483621022,53.15118128129387],"type":"Point"}
}