{
  "type": "Feature",
  "properties": {
    "date:inception_lower": "2015-04-01",
    "date:inception_upper": "2015-04-01",
    "iso:country": "GB",
    "wof:name": "NN4 9EU",
    "wof:placetype": "postalcode"
  },
  "geometry": {"coordinates":[-0.95086,52.221543],"type":"Point"}
}
