{
  "type": "Feature",
  "properties": {
    "iso:country": "GB",
    "wof:name": "NN4 9EU",
    "wof:placetype": "postalcode"
  },
  "geometry": {"coordinates":[-0.95086,52.221543],"type":"Point"}
}
