{
  "type": "Feature",
  "properties": {
    "iso:country":"GB",
    "wof:name":"YO7 1EW",
    "wof:placetype":"postalcode"
},
  "geometry": {"coordinates":[-1.32993165610055,54.23656312117082],"type":"Point"}
}