{
  "type": "Feature",
  "properties": {
    "iso:country": "GB",
    "wof:name": "TA1 2BL",
    "wof:placetype": "postalcode"
  },
  "geometry": {"coordinates":[-3.07559,51.020083],"type":"Point"}
}
