{
  "type": "Feature",
  "properties": {
    "iso:country":"GB",
    "wof:name":"TA1 2BL",
    "wof:placetype":"postalcode"
},
  "geometry": {"coordinates":[-3.07559024469293,51.02008275532592],"type":"Point"}
}