{
  "type": "Feature",
  "properties": {
    "date:inception_lower":"1980-01-01",
    "date:inception_upper":"1980-01-31",
    "iso:country":"GB",
    "wof:name":"LA6 2LG",
    "wof:placetype":"postalcode"
},
  "geometry": {"coordinates":[-2.567509,54.232945],"type":"Point"}
}