{
  "type": "Feature",
  "properties": {
    "iso:country":"GB",
    "wof:name":"BS49 5JJ",
    "wof:placetype":"postalcode"
},
  "geometry": {"coordinates":[-2.80419354778294,51.3606582254668],"type":"Point"}
}