{
  "type": "Feature",
  "properties": {
    "iso:country": "GB",
    "wof:name": "BS49 5JJ",
    "wof:placetype": "postalcode"
  },
  "geometry": {"coordinates":[-2.804194,51.360658],"type":"Point"}
}
