{
  "type": "Feature",
  "properties": {
    "date:inception_lower": "1997-12-01",
    "date:inception_upper": "1997-12-01",
    "iso:country": "GB",
    "wof:name": "BS49 5JJ",
    "wof:placetype": "postalcode"
  },
  "geometry": {"coordinates":[-2.804194,51.360658],"type":"Point"}
}
