{
  "type": "Feature",
  "properties": {
    "iso:country":"GB",
    "wof:name":"SL9 8TW",
    "wof:placetype":"postalcode"
},
  "geometry": {"coordinates":[-0.57669073564164,51.61371402321245],"type":"Point"}
}