{
  "type": "Feature",
  "properties": {
    "date:inception_lower": "1980-01-01",
    "date:inception_upper": "1980-01-01",
    "iso:country": "GB",
    "wof:name": "SL9 8TW",
    "wof:placetype": "postalcode"
  },
  "geometry": {"coordinates":[-0.576691,51.613714],"type":"Point"}
}
