{
  "type": "Feature",
  "properties": {
    "iso:country": "GB",
    "wof:name": "GL6 9EY",
    "wof:placetype": "postalcode"
  },
  "geometry": {"coordinates":[-2.197821,51.706077],"type":"Point"}
}
