{
  "type": "Feature",
  "properties": {
    "iso:country": "GB",
    "wof:name": "NN29 7UD",
    "wof:placetype": "postalcode"
  },
  "geometry": {"coordinates":[-0.717562,52.272081],"type":"Point"}
}
