{
  "type": "Feature",
  "properties": {
    "date:inception_lower": "1980-01-01",
    "date:inception_upper": "1980-01-01",
    "iso:country": "GB",
    "wof:name": "CH7 5JR",
    "wof:placetype": "postalcode"
  },
  "geometry": {"coordinates":[-3.170898,53.165589],"type":"Point"}
}
