{
  "type": "Feature",
  "properties": {
    "iso:country":"GB",
    "wof:name":"BD16 3LR",
    "wof:placetype":"postalcode"
},
  "geometry": {"coordinates":[-1.80990346933184,53.8514933301416],"type":"Point"}
}