{
  "type": "Feature",
  "properties": {
    "iso:country": "GB",
    "wof:name": "RG14 1PN",
    "wof:placetype": "postalcode"
  },
  "geometry": {"coordinates":[-1.332143,51.410766],"type":"Point"}
}
