{
  "type": "Feature",
  "properties": {
    "date:inception_lower":"1995-07-01",
    "date:inception_upper":"1995-07-31",
    "iso:country":"GB",
    "wof:name":"RG14 1PN",
    "wof:placetype":"postalcode"
},
  "geometry": {"coordinates":[-1.332143,51.410766],"type":"Point"}
}