{
  "type": "Feature",
  "properties": {
    "iso:country":"GB",
    "wof:name":"DE24 0ED",
    "wof:placetype":"postalcode"
},
  "geometry": {"coordinates":[-1.42968597801923,52.89492270717783],"type":"Point"}
}