{
  "type": "Feature",
  "properties": {
    "date:inception_lower": "1990-02-01",
    "date:inception_upper": "1990-02-01",
    "iso:country": "GB",
    "wof:name": "NN6 7YH",
    "wof:placetype": "postalcode"
  },
  "geometry": {"coordinates":[-1.075668,52.304916],"type":"Point"}
}
