{
  "type": "Feature",
  "properties": {
    "iso:country": "GB",
    "wof:name": "RM18 8FJ",
    "wof:placetype": "postalcode"
  },
  "geometry": {"coordinates":[0.411808,51.480511],"type":"Point"}
}
