{
  "type": "Feature",
  "properties": {
    "iso:country": "GB",
    "wof:name": "E16 1YZ",
    "wof:placetype": "postalcode"
  },
  "geometry": {"coordinates":[0.01714,51.504763],"type":"Point"}
}
