{
  "type": "Feature",
  "properties": {
    "date:inception_lower": "2017-07-01",
    "date:inception_upper": "2017-07-01",
    "iso:country": "GB",
    "wof:name": "E16 1YZ",
    "wof:placetype": "postalcode"
  },
  "geometry": {"coordinates":[0.01714,51.504763],"type":"Point"}
}
