{
  "type": "Feature",
  "properties": {
    "iso:country":"GB",
    "wof:name":"N7 9LU",
    "wof:placetype":"postalcode"
},
  "geometry": {"coordinates":[-0.12479375302215,51.55103670393462],"type":"Point"}
}