{
  "type": "Feature",
  "properties": {
    "iso:country":"GB",
    "wof:name":"ME2 4JX",
    "wof:placetype":"postalcode"
},
  "geometry": {"coordinates":[0.5116588028563,51.40885648536897],"type":"Point"}
}