{
  "type": "Feature",
  "properties": {
    "iso:country":"GB",
    "wof:name":"DH9 6DZ",
    "wof:placetype":"postalcode"
},
  "geometry": {"coordinates":[-1.66274369310199,54.85336578934437],"type":"Point"}
}