{
  "type": "Feature",
  "properties": {
    "iso:country": "GB",
    "wof:name": "DH9 6DZ",
    "wof:placetype": "postalcode"
  },
  "geometry": {"coordinates":[-1.662744,54.853366],"type":"Point"}
}
