{
  "type": "Feature",
  "properties": {
    "date:inception_lower": "1980-01-01",
    "date:inception_upper": "1980-01-01",
    "iso:country": "GB",
    "wof:name": "RH1 1PA",
    "wof:placetype": "postalcode"
  },
  "geometry": {"coordinates":[-0.167396,51.240043],"type":"Point"}
}
