{
  "type": "Feature",
  "properties": {
    "iso:country":"GB",
    "wof:name":"GL51 0FE",
    "wof:placetype":"postalcode"
},
  "geometry": {"coordinates":[-2.11714865741611,51.914893591468],"type":"Point"}
}