{
  "type": "Feature",
  "properties": {
    "date:inception_lower": "2007-10-01",
    "date:inception_upper": "2007-10-01",
    "iso:country": "GB",
    "wof:name": "GL51 0FE",
    "wof:placetype": "postalcode"
  },
  "geometry": {"coordinates":[-2.117149,51.914894],"type":"Point"}
}
