{
  "type": "Feature",
  "properties": {
    "iso:country":"GB",
    "wof:name":"DD5 3TP",
    "wof:placetype":"postalcode"
},
  "geometry": {"coordinates":[-2.87736392795509,56.51392870557407],"type":"Point"}
}