{
  "type": "Feature",
  "properties": {
    "iso:country": "GB",
    "wof:name": "S63 0DZ",
    "wof:placetype": "postalcode"
  },
  "geometry": {"coordinates":[-1.301907,53.549297],"type":"Point"}
}
