{
  "type": "Feature",
  "properties": {
    "iso:country":"GB",
    "wof:name":"S63 0DZ",
    "wof:placetype":"postalcode"
},
  "geometry": {"coordinates":[-1.30190740254044,53.54929732605282],"type":"Point"}
}