{
  "type": "Feature",
  "properties": {
    "iso:country": "GB",
    "wof:name": "CF81 9PP",
    "wof:placetype": "postalcode"
  },
  "geometry": {"coordinates":[-3.280225,51.748496],"type":"Point"}
}
