{
  "type": "Feature",
  "properties": {
    "iso:country":"GB",
    "wof:name":"CF81 9PP",
    "wof:placetype":"postalcode"
},
  "geometry": {"coordinates":[-3.28022533662828,51.7484956732481],"type":"Point"}
}