{
  "type": "Feature",
  "properties": {
    "iso:country":"GB",
    "wof:name":"NR1 3DT",
    "wof:placetype":"postalcode"
},
  "geometry": {"coordinates":[1.29907880568577,52.62837516323777],"type":"Point"}
}