{
  "type": "Feature",
  "properties": {
    "iso:country":"GB",
    "wof:name":"CM1 3ED",
    "wof:placetype":"postalcode"
},
  "geometry": {"coordinates":[0.42987352383216,51.73211475033027],"type":"Point"}
}