{
  "type": "Feature",
  "properties": {
    "date:inception_lower": "2016-06-01",
    "date:inception_upper": "2016-06-01",
    "iso:country": "GB",
    "wof:name": "CV23 0FQ",
    "wof:placetype": "postalcode"
  },
  "geometry": {"coordinates":[-1.240715,52.410927],"type":"Point"}
}
