{
  "type": "Feature",
  "properties": {
    "date:inception_lower": "1980-01-01",
    "date:inception_upper": "1980-01-01",
    "iso:country": "GB",
    "wof:name": "DN17 2AQ",
    "wof:placetype": "postalcode"
  },
  "geometry": {"coordinates":[-0.679682,53.562475],"type":"Point"}
}
