{
  "type": "Feature",
  "properties": {
    "iso:country": "GB",
    "wof:name": "DN17 2AQ",
    "wof:placetype": "postalcode"
  },
  "geometry": {"coordinates":[-0.679682,53.562475],"type":"Point"}
}
