{
  "type": "Feature",
  "properties": {
    "iso:country":"GB",
    "wof:name":"DN17 2AQ",
    "wof:placetype":"postalcode"
},
  "geometry": {"coordinates":[-0.67968188535346,53.56247529519423],"type":"Point"}
}