{
  "type": "Feature",
  "properties": {
    "iso:country":"GB",
    "wof:name":"RG8 8LR",
    "wof:placetype":"postalcode"
},
  "geometry": {"coordinates":[-1.13456753814154,51.47939416804091],"type":"Point"}
}