{
  "type": "Feature",
  "properties": {
    "iso:country": "GB",
    "wof:name": "NE31 2FD",
    "wof:placetype": "postalcode"
  },
  "geometry": {"coordinates":[-1.502446,54.974049],"type":"Point"}
}
