{
  "type": "Feature",
  "properties": {
    "iso:country":"GB",
    "wof:name":"SA44 6LP",
    "wof:placetype":"postalcode"
},
  "geometry": {"coordinates":[-4.36722082201922,52.17968617352574],"type":"Point"}
}