{
  "type": "Feature",
  "properties": {
    "iso:country":"GB",
    "wof:name":"B14 5LJ",
    "wof:placetype":"postalcode"
},
  "geometry": {"coordinates":[-1.88830303947186,52.41015624413829],"type":"Point"}
}