{
  "type": "Feature",
  "properties": {
    "iso:country": "GB",
    "wof:name": "CF37 3BQ",
    "wof:placetype": "postalcode"
  },
  "geometry": {"coordinates":[-3.331294,51.624957],"type":"Point"}
}
