{
  "type": "Feature",
  "properties": {
    "iso:country":"GB",
    "wof:name":"DA16 2HQ",
    "wof:placetype":"postalcode"
},
  "geometry": {"coordinates":[0.09647764726997,51.46196742771381],"type":"Point"}
}