{
  "type": "Feature",
  "properties": {
    "date:inception_lower": "2020-02-01",
    "date:inception_upper": "2020-02-01",
    "iso:country": "GB",
    "wof:name": "SN2 9WA",
    "wof:placetype": "postalcode"
  },
  "geometry": {"coordinates":[-1.722535,51.551996],"type":"Point"}
}
