{
  "type": "Feature",
  "properties": {
    "iso:country":"GB",
    "wof:name":"UB8 2HH",
    "wof:placetype":"postalcode"
},
  "geometry": {"coordinates":[-0.48220159997586,51.52493873183619],"type":"Point"}
}