{
  "type": "Feature",
  "properties": {
    "iso:country":"GB",
    "wof:name":"PO13 0ZW",
    "wof:placetype":"postalcode"
},
  "geometry": {"coordinates":[-1.16392719962344,50.81781643506062],"type":"Point"}
}