{
  "type": "Feature",
  "properties": {
    "iso:country": "GB",
    "wof:name": "PO13 0ZW",
    "wof:placetype": "postalcode"
  },
  "geometry": {"coordinates":[-1.163927,50.817816],"type":"Point"}
}
