{
  "type": "Feature",
  "properties": {
    "iso:country": "GB",
    "wof:name": "HU9 4AL",
    "wof:placetype": "postalcode"
  },
  "geometry": {"coordinates":[-0.267338,53.77187],"type":"Point"}
}
