{
  "type": "Feature",
  "properties": {
    "iso:country":"GB",
    "wof:name":"PE7 1PP",
    "wof:placetype":"postalcode"
},
  "geometry": {"coordinates":[-0.11120397890537,52.56496705742688],"type":"Point"}
}