{
  "type": "Feature",
  "properties": {
    "date:inception_lower":"2016-11-01",
    "date:inception_upper":"2016-11-30",
    "iso:country":"GB",
    "wof:name":"AL2 1RA",
    "wof:placetype":"postalcode"
},
  "geometry": {"coordinates":[-0.301949,51.747655],"type":"Point"}
}