{
  "type": "Feature",
  "properties": {
    "iso:country":"GB",
    "wof:name":"TF12 5QB",
    "wof:placetype":"postalcode"
},
  "geometry": {"coordinates":[-2.48286901438644,52.62146626853895],"type":"Point"}
}