{
  "type": "Feature",
  "properties": {
    "iso:country": "GB",
    "wof:name": "TF12 5QB",
    "wof:placetype": "postalcode"
  },
  "geometry": {"coordinates":[-2.482869,52.621466],"type":"Point"}
}
