{
  "type": "Feature",
  "properties": {
    "iso:country":"GB",
    "wof:name":"NR3 2PZ",
    "wof:placetype":"postalcode"
},
  "geometry": {"coordinates":[1.27063752226241,52.64871649930005],"type":"Point"}
}