{
  "type": "Feature",
  "properties": {
    "iso:country":"GB",
    "wof:name":"WV8 1HF",
    "wof:placetype":"postalcode"
},
  "geometry": {"coordinates":[-2.1851610032958,52.62464359005062],"type":"Point"}
}