{
  "type": "Feature",
  "properties": {
    "iso:country": "GB",
    "wof:name": "WV8 1HF",
    "wof:placetype": "postalcode"
  },
  "geometry": {"coordinates":[-2.185161,52.624644],"type":"Point"}
}
