{
  "type": "Feature",
  "properties": {
    "date:inception_lower": "1980-01-01",
    "date:inception_upper": "1980-01-01",
    "iso:country": "GB",
    "wof:name": "HR7 4QA",
    "wof:placetype": "postalcode"
  },
  "geometry": {"coordinates":[-2.488022,52.252662],"type":"Point"}
}
