{
  "type": "Feature",
  "properties": {
    "iso:country": "GB",
    "wof:name": "LL11 4TL",
    "wof:placetype": "postalcode"
  },
  "geometry": {"coordinates":[-3.029344,53.075412],"type":"Point"}
}
