{
  "type": "Feature",
  "properties": {
    "date:inception_lower": "1980-01-01",
    "date:inception_upper": "1980-01-01",
    "iso:country": "GB",
    "wof:name": "LL11 4TL",
    "wof:placetype": "postalcode"
  },
  "geometry": {"coordinates":[-3.029627,53.075355],"type":"Point"}
}
