{
  "type": "Feature",
  "properties": {
    "iso:country":"GB",
    "wof:name":"PL25 5JG",
    "wof:placetype":"postalcode"
},
  "geometry": {"coordinates":[-4.80091864601813,50.33699737290202],"type":"Point"}
}