{
  "type": "Feature",
  "properties": {
    "date:inception_lower":"2002-05-01",
    "date:inception_upper":"2002-05-31",
    "iso:country":"GB",
    "wof:name":"IV6 7SW",
    "wof:placetype":"postalcode"
},
  "geometry": {"coordinates":[-4.341812,57.541243],"type":"Point"}
}