{
  "type": "Feature",
  "properties": {
    "iso:country":"GB",
    "wof:name":"IV6 7SW",
    "wof:placetype":"postalcode"
},
  "geometry": {"coordinates":[-4.34181239692013,57.54124343180543],"type":"Point"}
}