{
  "type": "Feature",
  "properties": {
    "iso:country": "GB",
    "wof:name": "TF1 2LX",
    "wof:placetype": "postalcode"
  },
  "geometry": {"coordinates":[-2.497371,52.691473],"type":"Point"}
}
