{
  "type": "Feature",
  "properties": {
    "iso:country":"GB",
    "wof:name":"TF1 2LX",
    "wof:placetype":"postalcode"
},
  "geometry": {"coordinates":[-2.49737142596644,52.69147256537501],"type":"Point"}
}