{
  "type": "Feature",
  "properties": {
    "date:inception_lower": "1980-01-01",
    "date:inception_upper": "1980-01-01",
    "iso:country": "GB",
    "wof:name": "TF1 2LX",
    "wof:placetype": "postalcode"
  },
  "geometry": {"coordinates":[-2.497988,52.691323],"type":"Point"}
}
