{
  "type": "Feature",
  "properties": {
    "date:inception_lower":"1981-06-01",
    "date:inception_upper":"1981-06-30",
    "iso:country":"GB",
    "wof:name":"PR3 2SY",
    "wof:placetype":"postalcode"
},
  "geometry": {"coordinates":[-2.587301,53.868437],"type":"Point"}
}