{
  "type": "Feature",
  "properties": {
    "iso:country": "GB",
    "wof:name": "PR3 2SY",
    "wof:placetype": "postalcode"
  },
  "geometry": {"coordinates":[-2.587301,53.868437],"type":"Point"}
}
