{
  "type": "Feature",
  "properties": {
    "iso:country": "GB",
    "wof:name": "BB18 6QP",
    "wof:placetype": "postalcode"
  },
  "geometry": {"coordinates":[-2.14148,53.91718],"type":"Point"}
}
