{
  "type": "Feature",
  "properties": {
    "iso:country": "GB",
    "wof:name": "BA11 3AR",
    "wof:placetype": "postalcode"
  },
  "geometry": {"coordinates":[-2.327892,51.236491],"type":"Point"}
}
