{
  "type": "Feature",
  "properties": {
    "iso:country":"GB",
    "wof:name":"BA11 3AR",
    "wof:placetype":"postalcode"
},
  "geometry": {"coordinates":[-2.32789184354954,51.23649065602299],"type":"Point"}
}