{
  "type": "Feature",
  "properties": {
    "iso:country":"GB",
    "wof:name":"G46 8EB",
    "wof:placetype":"postalcode"
},
  "geometry": {"coordinates":[-4.32321563542416,55.80736684012194],"type":"Point"}
}