{
  "type": "Feature",
  "properties": {
    "iso:country": "GB",
    "wof:name": "G46 8EB",
    "wof:placetype": "postalcode"
  },
  "geometry": {"coordinates":[-4.323216,55.807367],"type":"Point"}
}
