{
  "type": "Feature",
  "properties": {
    "iso:country":"GB",
    "wof:name":"SA15 2SD",
    "wof:placetype":"postalcode"
},
  "geometry": {"coordinates":[-4.16266458705957,51.67571938618627],"type":"Point"}
}