{
  "type": "Feature",
  "properties": {
    "date:inception_lower": "1990-07-01",
    "date:inception_upper": "1990-07-01",
    "iso:country": "GB",
    "wof:name": "BN41 2WT",
    "wof:placetype": "postalcode"
  },
  "geometry": {"coordinates":[-0.226116,50.851746],"type":"Point"}
}
