{
  "type": "Feature",
  "properties": {
    "iso:country":"GB",
    "wof:name":"BN41 2WT",
    "wof:placetype":"postalcode"
},
  "geometry": {"coordinates":[-0.22611563798835,50.8517459095279],"type":"Point"}
}