{
  "type": "Feature",
  "properties": {
    "date:inception_lower": "1980-01-01",
    "date:inception_upper": "1980-01-01",
    "iso:country": "GB",
    "wof:name": "PR6 7ER",
    "wof:placetype": "postalcode"
  },
  "geometry": {"coordinates":[-2.644628,53.703709],"type":"Point"}
}
