{
  "type": "Feature",
  "properties": {
    "date:inception_lower":"1987-04-01",
    "date:inception_upper":"1987-04-30",
    "iso:country":"GB",
    "wof:name":"SP2 0JP",
    "wof:placetype":"postalcode"
},
  "geometry": {"coordinates":[-1.860162,51.081135],"type":"Point"}
}