{
  "type": "Feature",
  "properties": {
    "iso:country":"GB",
    "wof:name":"SP2 0JP",
    "wof:placetype":"postalcode"
},
  "geometry": {"coordinates":[-1.86016198635852,51.08113505240892],"type":"Point"}
}