{
  "type": "Feature",
  "properties": {
    "iso:country":"GB",
    "wof:name":"KT11 2DJ",
    "wof:placetype":"postalcode"
},
  "geometry": {"coordinates":[-0.38996637235858,51.32457318025387],"type":"Point"}
}