{
  "type": "Feature",
  "properties": {
    "date:inception_lower": "1980-01-01",
    "date:inception_upper": "1980-01-01",
    "iso:country": "GB",
    "wof:name": "GL13 9QY",
    "wof:placetype": "postalcode"
  },
  "geometry": {"coordinates":[-2.517919,51.682016],"type":"Point"}
}
