{
  "type": "Feature",
  "properties": {
    "iso:country":"GB",
    "wof:name":"TN29 9TY",
    "wof:placetype":"postalcode"
},
  "geometry": {"coordinates":[0.85954546110703,51.00584067122201],"type":"Point"}
}