{
  "type": "Feature",
  "properties": {
    "iso:country": "GB",
    "wof:name": "PH2 6JA",
    "wof:placetype": "postalcode"
  },
  "geometry": {"coordinates":[-3.284675,56.479314],"type":"Point"}
}
