{
  "type": "Feature",
  "properties": {
    "iso:country":"GB",
    "wof:name":"PH2 6JA",
    "wof:placetype":"postalcode"
},
  "geometry": {"coordinates":[-3.28413766003056,56.48455798001001],"type":"Point"}
}