{
  "type": "Feature",
  "properties": {
    "date:inception_lower": "2023-03-01",
    "date:inception_upper": "2023-03-01",
    "iso:country": "GB",
    "wof:name": "TD8 6EQ",
    "wof:placetype": "postalcode"
  },
  "geometry": {"coordinates":[-2.551966,55.48215],"type":"Point"}
}
