{
  "type": "Feature",
  "properties": {
    "iso:country":"GB",
    "wof:name":"W1T 4PS",
    "wof:placetype":"postalcode"
},
  "geometry": {"coordinates":[-0.13699385048616,51.52037786777333],"type":"Point"}
}