{
  "type": "Feature",
  "properties": {
    "iso:country":"GB",
    "wof:name":"EX1 3DG",
    "wof:placetype":"postalcode"
},
  "geometry": {"coordinates":[-3.49160925633346,50.72166312211547],"type":"Point"}
}