{
  "type": "Feature",
  "properties": {
    "iso:country": "GB",
    "wof:name": "GL52 7ZB",
    "wof:placetype": "postalcode"
  },
  "geometry": {"coordinates":[-2.073005,51.951935],"type":"Point"}
}
