{
  "type": "Feature",
  "properties": {
    "iso:country":"GB",
    "wof:name":"LE7 9AN",
    "wof:placetype":"postalcode"
},
  "geometry": {"coordinates":[-0.93753287260553,52.61397647663247],"type":"Point"}
}