{
  "type": "Feature",
  "properties": {
    "iso:country": "GB",
    "wof:name": "HX4 0HF",
    "wof:placetype": "postalcode"
  },
  "geometry": {"coordinates":[-1.902297,53.673983],"type":"Point"}
}
