{
  "type": "Feature",
  "properties": {
    "iso:country":"GB",
    "wof:name":"HX4 0HF",
    "wof:placetype":"postalcode"
},
  "geometry": {"coordinates":[-1.90229741738335,53.67398282314934],"type":"Point"}
}