{
  "type": "Feature",
  "properties": {
    "iso:country":"GB",
    "wof:name":"NE66 3UJ",
    "wof:placetype":"postalcode"
},
  "geometry": {"coordinates":[-1.63425816896055,55.49664206418403],"type":"Point"}
}