{
  "type": "Feature",
  "properties": {
    "iso:country":"GB",
    "wof:name":"TQ1 1HB",
    "wof:placetype":"postalcode"
},
  "geometry": {"coordinates":[-3.52311816688063,50.46346642180028],"type":"Point"}
}