{
  "type": "Feature",
  "properties": {
    "iso:country":"GB",
    "wof:name":"M22 0NP",
    "wof:placetype":"postalcode"
},
  "geometry": {"coordinates":[-2.25966872334728,53.37056170141582],"type":"Point"}
}