{
  "type": "Feature",
  "properties": {
    "date:inception_lower": "2021-05-01",
    "date:inception_upper": "2021-05-01",
    "iso:country": "GB",
    "wof:name": "WS11 9AQ",
    "wof:placetype": "postalcode"
  },
  "geometry": {"coordinates":[-1.980655,52.664655],"type":"Point"}
}
