{
  "type": "Feature",
  "properties": {
    "iso:country":"GB",
    "wof:name":"SR8 4LZ",
    "wof:placetype":"postalcode"
},
  "geometry": {"coordinates":[-1.31640083639502,54.76312272130833],"type":"Point"}
}