{
  "type": "Feature",
  "properties": {
    "iso:country":"GB",
    "wof:name":"BN10 8UT",
    "wof:placetype":"postalcode"
},
  "geometry": {"coordinates":[0.02376925503107,50.79056981557876],"type":"Point"}
}