{
  "type": "Feature",
  "properties": {
    "iso:country":"GB",
    "wof:name":"KT17 4LX",
    "wof:placetype":"postalcode"
},
  "geometry": {"coordinates":[-0.25024389217641,51.32007809858136],"type":"Point"}
}