{
  "type": "Feature",
  "properties": {
    "iso:country":"GB",
    "wof:name":"OX4 3TY",
    "wof:placetype":"postalcode"
},
  "geometry": {"coordinates":[-1.21231659042878,51.72628204592375],"type":"Point"}
}