{
  "type": "Feature",
  "properties": {
    "iso:country": "GB",
    "wof:name": "OX4 3TY",
    "wof:placetype": "postalcode"
  },
  "geometry": {"coordinates":[-1.212317,51.726282],"type":"Point"}
}
