{
  "type": "Feature",
  "properties": {
    "date:inception_lower": "1980-01-01",
    "date:inception_upper": "1980-01-01",
    "iso:country": "GB",
    "wof:name": "CF33 6NG",
    "wof:placetype": "postalcode"
  },
  "geometry": {"coordinates":[-3.68495,51.528908],"type":"Point"}
}
