{
  "type": "Feature",
  "properties": {
    "iso:country":"GB",
    "wof:name":"CF33 6NG",
    "wof:placetype":"postalcode"
},
  "geometry": {"coordinates":[-3.68495019787259,51.52890803647873],"type":"Point"}
}