{
  "type": "Feature",
  "properties": {
    "iso:country": "GB",
    "wof:name": "TW16 7SG",
    "wof:placetype": "postalcode"
  },
  "geometry": {"coordinates":[-0.41635,51.424407],"type":"Point"}
}
