{
  "type": "Feature",
  "properties": {
    "date:inception_lower": "2015-12-01",
    "date:inception_upper": "2015-12-01",
    "iso:country": "GB",
    "wof:name": "ML6 7LG",
    "wof:placetype": "postalcode"
  },
  "geometry": {"coordinates":[-3.963431,55.87525],"type":"Point"}
}
