{
  "type": "Feature",
  "properties": {
    "iso:country":"GB",
    "wof:name":"ML6 7LG",
    "wof:placetype":"postalcode"
},
  "geometry": {"coordinates":[-3.9645654217032,55.87567593398818],"type":"Point"}
}