{
  "type": "Feature",
  "properties": {
    "iso:country":"GB",
    "wof:name":"G83 8HT",
    "wof:placetype":"postalcode"
},
  "geometry": {"coordinates":[-4.57183372076824,56.00573749711267],"type":"Point"}
}