{
  "type": "Feature",
  "properties": {
    "iso:country": "GB",
    "wof:name": "G83 8HT",
    "wof:placetype": "postalcode"
  },
  "geometry": {"coordinates":[-4.571834,56.005737],"type":"Point"}
}
