{
  "type": "Feature",
  "properties": {
    "iso:country": "GB",
    "wof:name": "CT12 5LX",
    "wof:placetype": "postalcode"
  },
  "geometry": {"coordinates":[1.344986,51.350078],"type":"Point"}
}
