{
  "type": "Feature",
  "properties": {
    "date:inception_lower":"1990-02-01",
    "date:inception_upper":"1990-02-28",
    "iso:country":"GB",
    "wof:name":"CT12 5LX",
    "wof:placetype":"postalcode"
},
  "geometry": {"coordinates":[1.344986,51.350078],"type":"Point"}
}