{
  "type": "Feature",
  "properties": {
    "iso:country": "GB",
    "wof:name": "CR5 3JZ",
    "wof:placetype": "postalcode"
  },
  "geometry": {"coordinates":[-0.140298,51.317339],"type":"Point"}
}
