{
  "type": "Feature",
  "properties": {
    "date:inception_lower": "2022-07-01",
    "date:inception_upper": "2022-07-01",
    "iso:country": "GB",
    "wof:name": "IV36 3SJ",
    "wof:placetype": "postalcode"
  },
  "geometry": {"coordinates":[-3.594745,57.654045],"type":"Point"}
}
