{
  "type": "Feature",
  "properties": {
    "iso:country": "GB",
    "wof:name": "SA1 8LY",
    "wof:placetype": "postalcode"
  },
  "geometry": {"coordinates":[-3.920419,51.622632],"type":"Point"}
}
