{
  "type": "Feature",
  "properties": {
    "iso:country":"GB",
    "wof:name":"KA23 9NZ",
    "wof:placetype":"postalcode"
},
  "geometry": {"coordinates":[-4.85652155266575,55.68919272161237],"type":"Point"}
}