{
  "type": "Feature",
  "properties": {
    "iso:country": "GB",
    "wof:name": "KT6 6SH",
    "wof:placetype": "postalcode"
  },
  "geometry": {"coordinates":[-0.312062,51.38825],"type":"Point"}
}
