{
  "type": "Feature",
  "properties": {
    "date:inception_lower":"1980-01-01",
    "date:inception_upper":"1980-01-31",
    "iso:country":"GB",
    "wof:name":"NE3 3QB",
    "wof:placetype":"postalcode"
},
  "geometry": {"coordinates":[-1.651214,55.003629],"type":"Point"}
}