{
  "type": "Feature",
  "properties": {
    "iso:country": "GB",
    "wof:name": "NE38 7AG",
    "wof:placetype": "postalcode"
  },
  "geometry": {"coordinates":[-1.513476,54.900524],"type":"Point"}
}
