{
  "type": "Feature",
  "properties": {
    "iso:country": "GB",
    "wof:name": "IP14 6AG",
    "wof:placetype": "postalcode"
  },
  "geometry": {"coordinates":[1.121144,52.191872],"type":"Point"}
}
