{
  "type": "Feature",
  "properties": {
    "iso:country":"GB",
    "wof:name":"IP14 6AG",
    "wof:placetype":"postalcode"
},
  "geometry": {"coordinates":[1.12177213914084,52.19185626042352],"type":"Point"}
}