{
  "type": "Feature",
  "properties": {
    "iso:country":"GB",
    "wof:name":"CH7 4RU",
    "wof:placetype":"postalcode"
},
  "geometry": {"coordinates":[-3.0915033246277,53.13095383018995],"type":"Point"}
}