{
  "type": "Feature",
  "properties": {
    "iso:country":"GB",
    "wof:name":"OX12 9LD",
    "wof:placetype":"postalcode"
},
  "geometry": {"coordinates":[-1.44998673850288,51.57246189369013],"type":"Point"}
}