{
  "type": "Feature",
  "properties": {
    "iso:country":"GB",
    "wof:name":"M33 2NY",
    "wof:placetype":"postalcode"
},
  "geometry": {"coordinates":[-2.31716533549047,53.42634073597838],"type":"Point"}
}