{
  "type": "Feature",
  "properties": {
    "iso:country":"GB",
    "wof:name":"SA15 1SH",
    "wof:placetype":"postalcode"
},
  "geometry": {"coordinates":[-4.15945678057903,51.6818664646494],"type":"Point"}
}