{
  "type": "Feature",
  "properties": {
    "iso:country": "GB",
    "wof:name": "SA15 1SH",
    "wof:placetype": "postalcode"
  },
  "geometry": {"coordinates":[-4.159457,51.681866],"type":"Point"}
}
