{
  "type": "Feature",
  "properties": {
    "iso:country": "GB",
    "wof:name": "TR3 7PJ",
    "wof:placetype": "postalcode"
  },
  "geometry": {"coordinates":[-5.141963,50.213981],"type":"Point"}
}
