{
  "type": "Feature",
  "properties": {
    "iso:country":"GB",
    "wof:name":"ME12 2JP",
    "wof:placetype":"postalcode"
},
  "geometry": {"coordinates":[0.80362526810431,51.4209217913867],"type":"Point"}
}