{
  "type": "Feature",
  "properties": {
    "iso:country":"GB",
    "wof:name":"PL1 3QA",
    "wof:placetype":"postalcode"
},
  "geometry": {"coordinates":[-4.16259678095113,50.36622560245811],"type":"Point"}
}