{
  "type": "Feature",
  "properties": {
    "date:inception_lower":"1998-12-01",
    "date:inception_upper":"1998-12-31",
    "iso:country":"GB",
    "wof:name":"PL1 3QA",
    "wof:placetype":"postalcode"
},
  "geometry": {"coordinates":[-4.162597,50.366226],"type":"Point"}
}