{
  "type": "Feature",
  "properties": {
    "iso:country":"GB",
    "wof:name":"SW12 8HG",
    "wof:placetype":"postalcode"
},
  "geometry": {"coordinates":[-0.1617083574337,51.44137278229933],"type":"Point"}
}