{
  "type": "Feature",
  "properties": {
    "iso:country": "GB",
    "wof:name": "CA12 4QW",
    "wof:placetype": "postalcode"
  },
  "geometry": {"coordinates":[-3.194382,54.678952],"type":"Point"}
}
