{
  "type": "Feature",
  "properties": {
    "iso:country": "GB",
    "wof:name": "DH2 3ND",
    "wof:placetype": "postalcode"
  },
  "geometry": {"coordinates":[-1.636015,54.861699],"type":"Point"}
}
