{
  "type": "Feature",
  "properties": {
    "date:inception_lower": "1980-01-01",
    "date:inception_upper": "1980-01-01",
    "iso:country": "GB",
    "wof:name": "DH2 3ND",
    "wof:placetype": "postalcode"
  },
  "geometry": {"coordinates":[-1.636078,54.86169],"type":"Point"}
}
