{
  "type": "Feature",
  "properties": {
    "iso:country":"GB",
    "wof:name":"DH2 3ND",
    "wof:placetype":"postalcode"
},
  "geometry": {"coordinates":[-1.63606580534691,54.86168215634108],"type":"Point"}
}