{
  "type": "Feature",
  "properties": {
    "iso:country": "GB",
    "wof:name": "MK19 7EH",
    "wof:placetype": "postalcode"
  },
  "geometry": {"coordinates":[-0.835018,52.091134],"type":"Point"}
}
