{
  "type": "Feature",
  "properties": {
    "iso:country":"GB",
    "wof:name":"EN1 1PR",
    "wof:placetype":"postalcode"
},
  "geometry": {"coordinates":[-0.07016904307645,51.65050685820923],"type":"Point"}
}