{
  "type": "Feature",
  "properties": {
    "date:inception_lower": "2003-07-01",
    "date:inception_upper": "2003-07-01",
    "iso:country": "GB",
    "wof:name": "TR6 0NA",
    "wof:placetype": "postalcode"
  },
  "geometry": {"coordinates":[-5.152219,50.345143],"type":"Point"}
}
