{
  "type": "Feature",
  "properties": {
    "iso:country":"GB",
    "wof:name":"TW14 0BQ",
    "wof:placetype":"postalcode"
},
  "geometry": {"coordinates":[-0.40631329558631,51.45489879332723],"type":"Point"}
}