{
  "type": "Feature",
  "properties": {
    "iso:country":"GB",
    "wof:name":"LS25 4DT",
    "wof:placetype":"postalcode"
},
  "geometry": {"coordinates":[-1.32433616084088,53.78492953253255],"type":"Point"}
}