{
  "type": "Feature",
  "properties": {
    "iso:country":"GB",
    "wof:name":"IG6 1EU",
    "wof:placetype":"postalcode"
},
  "geometry": {"coordinates":[0.08131665750728,51.58363988471705],"type":"Point"}
}