{
  "type": "Feature",
  "properties": {
    "iso:country": "GB",
    "wof:name": "EN8 0XB",
    "wof:placetype": "postalcode"
  },
  "geometry": {"coordinates":[-0.026325,51.716691],"type":"Point"}
}
