{
  "type": "Feature",
  "properties": {
    "iso:country":"GB",
    "wof:name":"EN8 0XB",
    "wof:placetype":"postalcode"
},
  "geometry": {"coordinates":[-0.02632524004675,51.71669058904787],"type":"Point"}
}