{
  "type": "Feature",
  "properties": {
    "date:inception_lower": "1990-02-01",
    "date:inception_upper": "1990-02-01",
    "iso:country": "GB",
    "wof:name": "EN8 0XB",
    "wof:placetype": "postalcode"
  },
  "geometry": {"coordinates":[-0.026325,51.716691],"type":"Point"}
}
