{
  "type": "Feature",
  "properties": {
    "date:inception_lower": "1980-01-01",
    "date:inception_upper": "1980-01-01",
    "iso:country": "GB",
    "wof:name": "L4 5QS",
    "wof:placetype": "postalcode"
  },
  "geometry": {"coordinates":[-2.971816,53.444335],"type":"Point"}
}
