{
  "type": "Feature",
  "properties": {
    "date:inception_lower":"1995-01-01",
    "date:inception_upper":"1995-01-31",
    "iso:country":"GB",
    "wof:name":"NG34 8BP",
    "wof:placetype":"postalcode"
},
  "geometry": {"coordinates":[-0.423366,53.009481],"type":"Point"}
}