{
  "type": "Feature",
  "properties": {
    "iso:country": "GB",
    "wof:name": "PO33 2EU",
    "wof:placetype": "postalcode"
  },
  "geometry": {"coordinates":[-1.157804,50.730558],"type":"Point"}
}
