{
  "type": "Feature",
  "properties": {
    "iso:country":"GB",
    "wof:name":"DA7 4PH",
    "wof:placetype":"postalcode"
},
  "geometry": {"coordinates":[0.13928754818642,51.46678758161776],"type":"Point"}
}