{
  "type": "Feature",
  "properties": {
    "iso:country":"GB",
    "wof:name":"B46 1NJ",
    "wof:placetype":"postalcode"
},
  "geometry": {"coordinates":[-1.74081081949924,52.52029553052634],"type":"Point"}
}