{
  "type": "Feature",
  "properties": {
    "iso:country":"GB",
    "wof:name":"DD3 7NR",
    "wof:placetype":"postalcode"
},
  "geometry": {"coordinates":[-2.96289344642261,56.47558739113823],"type":"Point"}
}