{
  "type": "Feature",
  "properties": {
    "iso:country":"GB",
    "wof:name":"S71 2NB",
    "wof:placetype":"postalcode"
},
  "geometry": {"coordinates":[-1.46383569793256,53.56389378565125],"type":"Point"}
}