{
  "type": "Feature",
  "properties": {
    "date:inception_lower": "1980-01-01",
    "date:inception_upper": "1980-01-01",
    "iso:country": "GB",
    "wof:name": "EH4 7DR",
    "wof:placetype": "postalcode"
  },
  "geometry": {"coordinates":[-3.284389,55.956944],"type":"Point"}
}
