{
  "type": "Feature",
  "properties": {
    "iso:country":"GB",
    "wof:name":"WV4 4JH",
    "wof:placetype":"postalcode"
},
  "geometry": {"coordinates":[-2.16542635865136,52.55852590549625],"type":"Point"}
}