{
  "type": "Feature",
  "properties": {
    "date:inception_lower": "1995-07-01",
    "date:inception_upper": "1995-07-01",
    "iso:country": "GB",
    "wof:name": "RG14 1JW",
    "wof:placetype": "postalcode"
  },
  "geometry": {"coordinates":[-1.321519,51.405769],"type":"Point"}
}
