{
  "type": "Feature",
  "properties": {
    "iso:country":"GB",
    "wof:name":"RG14 1JW",
    "wof:placetype":"postalcode"
},
  "geometry": {"coordinates":[-1.3215192148836,51.40576852609869],"type":"Point"}
}