{
  "type": "Feature",
  "properties": {
    "iso:country":"GB",
    "wof:name":"SA73 1QT",
    "wof:placetype":"postalcode"
},
  "geometry": {"coordinates":[-4.96856761488977,51.71686949091563],"type":"Point"}
}