{
  "type": "Feature",
  "properties": {
    "iso:country":"GB",
    "wof:name":"G12 8TT",
    "wof:placetype":"postalcode"
},
  "geometry": {"coordinates":[-4.29641783727378,55.87312921159523],"type":"Point"}
}