{
  "type": "Feature",
  "properties": {
    "iso:country": "GB",
    "wof:name": "OX7 3PZ",
    "wof:placetype": "postalcode"
  },
  "geometry": {"coordinates":[-1.47448,51.876693],"type":"Point"}
}
