{
  "type": "Feature",
  "properties": {
    "iso:country":"GB",
    "wof:name":"CM6 1JD",
    "wof:placetype":"postalcode"
},
  "geometry": {"coordinates":[0.34962800797822,51.85881876077084],"type":"Point"}
}