{
  "type": "Feature",
  "properties": {
    "iso:country": "GB",
    "wof:name": "HA6 2NF",
    "wof:placetype": "postalcode"
  },
  "geometry": {"coordinates":[-0.443464,51.6178],"type":"Point"}
}
