{
  "type": "Feature",
  "properties": {
    "iso:country":"GB",
    "wof:name":"HA6 2NF",
    "wof:placetype":"postalcode"
},
  "geometry": {"coordinates":[-0.44348555179043,51.61779647578783],"type":"Point"}
}