{
  "type": "Feature",
  "properties": {
    "iso:country": "GB",
    "wof:name": "HA6 2NF",
    "wof:placetype": "postalcode"
  },
  "geometry": {"coordinates":[-0.443423,51.618168],"type":"Point"}
}
