{
  "type": "Feature",
  "properties": {
    "iso:country": "GB",
    "wof:name": "SO21 3GY",
    "wof:placetype": "postalcode"
  },
  "geometry": {"coordinates":[-1.336918,51.118716],"type":"Point"}
}
