{
  "type": "Feature",
  "properties": {
    "iso:country":"GB",
    "wof:name":"SO21 3GY",
    "wof:placetype":"postalcode"
},
  "geometry": {"coordinates":[-1.33691770938016,51.11871633432659],"type":"Point"}
}