{
  "type": "Feature",
  "properties": {
    "iso:country":"GB",
    "wof:name":"ML5 5HW",
    "wof:placetype":"postalcode"
},
  "geometry": {"coordinates":[-4.03748420050365,55.8492726427924],"type":"Point"}
}