{
  "type": "Feature",
  "properties": {
    "iso:country":"GB",
    "wof:name":"IP22 5XA",
    "wof:placetype":"postalcode"
},
  "geometry": {"coordinates":[1.16602713851126,52.42182276763461],"type":"Point"}
}