{
  "type": "Feature",
  "properties": {
    "iso:country": "GB",
    "wof:name": "IP22 5XA",
    "wof:placetype": "postalcode"
  },
  "geometry": {"coordinates":[1.163233,52.421281],"type":"Point"}
}
