{
  "type": "Feature",
  "properties": {
    "date:inception_lower": "1999-12-01",
    "date:inception_upper": "1999-12-01",
    "iso:country": "GB",
    "wof:name": "IP22 5XA",
    "wof:placetype": "postalcode"
  },
  "geometry": {"coordinates":[1.163233,52.421281],"type":"Point"}
}
