{
  "type": "Feature",
  "properties": {
    "iso:country":"GB",
    "wof:name":"BH20 5DX",
    "wof:placetype":"postalcode"
},
  "geometry": {"coordinates":[-2.07142296897246,50.65177114468602],"type":"Point"}
}