{
  "type": "Feature",
  "properties": {
    "iso:country": "GB",
    "wof:name": "RG26 3XH",
    "wof:placetype": "postalcode"
  },
  "geometry": {"coordinates":[-1.125441,51.352596],"type":"Point"}
}
