{
  "type": "Feature",
  "properties": {
    "date:inception_lower":"1980-01-01",
    "date:inception_upper":"1980-01-31",
    "iso:country":"GB",
    "wof:name":"PH1 3TB",
    "wof:placetype":"postalcode"
},
  "geometry": {"coordinates":[-3.632611,56.450049],"type":"Point"}
}