{
  "type": "Feature",
  "properties": {
    "date:inception_lower": "1980-01-01",
    "date:inception_upper": "1980-01-01",
    "iso:country": "GB",
    "wof:name": "PH1 3TB",
    "wof:placetype": "postalcode"
  },
  "geometry": {"coordinates":[-3.63256,56.450067],"type":"Point"}
}
