{
  "type": "Feature",
  "properties": {
    "date:inception_lower":"1992-08-01",
    "date:inception_upper":"1992-08-31",
    "iso:country":"GB",
    "wof:name":"SY8 2AQ",
    "wof:placetype":"postalcode"
},
  "geometry": {"coordinates":[-2.730987,52.423366],"type":"Point"}
}