{
  "type": "Feature",
  "properties": {
    "iso:country":"GB",
    "wof:name":"SY8 2AQ",
    "wof:placetype":"postalcode"
},
  "geometry": {"coordinates":[-2.73098709253914,52.42336571887068],"type":"Point"}
}