{
  "type": "Feature",
  "properties": {
    "iso:country":"GB",
    "wof:name":"IG3 9JZ",
    "wof:placetype":"postalcode"
},
  "geometry": {"coordinates":[0.09875203236158,51.56073063435976],"type":"Point"}
}