{
  "type": "Feature",
  "properties": {
    "iso:country": "GB",
    "wof:name": "IG3 9JZ",
    "wof:placetype": "postalcode"
  },
  "geometry": {"coordinates":[0.098805,51.560677],"type":"Point"}
}
