{
  "type": "Feature",
  "properties": {
    "iso:country": "GB",
    "wof:name": "G15 6RY",
    "wof:placetype": "postalcode"
  },
  "geometry": {"coordinates":[-4.372556,55.905275],"type":"Point"}
}
