{
  "type": "Feature",
  "properties": {
    "iso:country":"GB",
    "wof:name":"G15 6RY",
    "wof:placetype":"postalcode"
},
  "geometry": {"coordinates":[-4.37253242472264,55.9051730784477],"type":"Point"}
}