{
  "type": "Feature",
  "properties": {
    "iso:country":"GB",
    "wof:name":"GU47 0SH",
    "wof:placetype":"postalcode"
},
  "geometry": {"coordinates":[-0.78252837235746,51.35369791536741],"type":"Point"}
}