{
  "type": "Feature",
  "properties": {
    "date:inception_lower": "1980-01-01",
    "date:inception_upper": "1980-01-01",
    "iso:country": "GB",
    "wof:name": "HU7 4DJ",
    "wof:placetype": "postalcode"
  },
  "geometry": {"coordinates":[-0.332608,53.791646],"type":"Point"}
}
