{
  "type": "Feature",
  "properties": {
    "iso:country": "GB",
    "wof:name": "M24 1FH",
    "wof:placetype": "postalcode"
  },
  "geometry": {"coordinates":[-2.189064,53.544127],"type":"Point"}
}
