{
  "type": "Feature",
  "properties": {
    "iso:country":"GB",
    "wof:name":"M24 1FH",
    "wof:placetype":"postalcode"
},
  "geometry": {"coordinates":[-2.18906449511121,53.54412735799661],"type":"Point"}
}