{
  "type": "Feature",
  "properties": {
    "date:inception_lower":"1993-01-01",
    "date:inception_upper":"1993-01-31",
    "iso:country":"GB",
    "wof:name":"M24 1FH",
    "wof:placetype":"postalcode"
},
  "geometry": {"coordinates":[-2.189064,53.544127],"type":"Point"}
}