{
  "type": "Feature",
  "properties": {
    "iso:country": "GB",
    "wof:name": "EH23 4FU",
    "wof:placetype": "postalcode"
  },
  "geometry": {"coordinates":[-3.046985,55.838584],"type":"Point"}
}
