{
  "type": "Feature",
  "properties": {
    "iso:country": "GB",
    "wof:name": "SS11 8EA",
    "wof:placetype": "postalcode"
  },
  "geometry": {"coordinates":[0.534155,51.613278],"type":"Point"}
}
