{
  "type": "Feature",
  "properties": {
    "date:inception_lower":"1980-01-01",
    "date:inception_upper":"1980-01-31",
    "iso:country":"GB",
    "wof:name":"SS11 8EA",
    "wof:placetype":"postalcode"
},
  "geometry": {"coordinates":[0.534155,51.613278],"type":"Point"}
}