{
  "type": "Feature",
  "properties": {
    "iso:country":"GB",
    "wof:name":"SS11 8EA",
    "wof:placetype":"postalcode"
},
  "geometry": {"coordinates":[0.53415482332574,51.61327818100652],"type":"Point"}
}