{
  "type": "Feature",
  "properties": {
    "date:inception_lower": "2019-01-01",
    "date:inception_upper": "2019-01-01",
    "iso:country": "GB",
    "wof:name": "UB2 4FZ",
    "wof:placetype": "postalcode"
  },
  "geometry": {"coordinates":[-0.348242,51.50796],"type":"Point"}
}
