{
  "type": "Feature",
  "properties": {
    "iso:country": "GB",
    "wof:name": "LE8 0QD",
    "wof:placetype": "postalcode"
  },
  "geometry": {"coordinates":[-0.998436,52.529406],"type":"Point"}
}
