{
  "type": "Feature",
  "properties": {
    "iso:country":"GB",
    "wof:name":"LE8 0QD",
    "wof:placetype":"postalcode"
},
  "geometry": {"coordinates":[-0.99843635106114,52.52940595689419],"type":"Point"}
}