{
  "type": "Feature",
  "properties": {
    "iso:country": "GB",
    "wof:name": "TQ1 1BA",
    "wof:placetype": "postalcode"
  },
  "geometry": {"coordinates":[-3.526249,50.46352],"type":"Point"}
}
