{
  "type": "Feature",
  "properties": {
    "date:inception_lower": "2001-12-01",
    "date:inception_upper": "2001-12-01",
    "iso:country": "GB",
    "wof:name": "PR3 1QY",
    "wof:placetype": "postalcode"
  },
  "geometry": {"coordinates":[-2.773819,53.897053],"type":"Point"}
}
