{
  "type": "Feature",
  "properties": {
    "iso:country": "GB",
    "wof:name": "WN6 8LR",
    "wof:placetype": "postalcode"
  },
  "geometry": {"coordinates":[-2.67793,53.560772],"type":"Point"}
}
