{
  "type": "Feature",
  "properties": {
    "date:inception_lower": "1980-01-01",
    "date:inception_upper": "1980-01-01",
    "iso:country": "GB",
    "wof:name": "WN6 8LR",
    "wof:placetype": "postalcode"
  },
  "geometry": {"coordinates":[-2.67793,53.560772],"type":"Point"}
}
