{
  "type": "Feature",
  "properties": {
    "iso:country":"GB",
    "wof:name":"WN6 8LR",
    "wof:placetype":"postalcode"
},
  "geometry": {"coordinates":[-2.67792967242254,53.56077176170344],"type":"Point"}
}