{
  "type": "Feature",
  "properties": {
    "iso:country": "GB",
    "wof:name": "DN4 9LZ",
    "wof:placetype": "postalcode"
  },
  "geometry": {"coordinates":[-1.176551,53.500744],"type":"Point"}
}
