{
  "type": "Feature",
  "properties": {
    "iso:country":"GB",
    "wof:name":"DN4 9LZ",
    "wof:placetype":"postalcode"
},
  "geometry": {"coordinates":[-1.17655095140901,53.50074356736228],"type":"Point"}
}