{
  "type": "Feature",
  "properties": {
    "date:inception_lower": "1980-01-01",
    "date:inception_upper": "1980-01-01",
    "iso:country": "GB",
    "wof:name": "DN4 9LZ",
    "wof:placetype": "postalcode"
  },
  "geometry": {"coordinates":[-1.177809,53.500547],"type":"Point"}
}
