{
  "type": "Feature",
  "properties": {
    "iso:country": "GB",
    "wof:name": "TQ9 5AH",
    "wof:placetype": "postalcode"
  },
  "geometry": {"coordinates":[-3.679333,50.42964],"type":"Point"}
}
