{
  "type": "Feature",
  "properties": {
    "iso:country":"GB",
    "wof:name":"HA7 3BP",
    "wof:placetype":"postalcode"
},
  "geometry": {"coordinates":[-0.31497302128216,51.62046444006386],"type":"Point"}
}