{
  "type": "Feature",
  "properties": {
    "iso:country": "GB",
    "wof:name": "CV34 7AB",
    "wof:placetype": "postalcode"
  },
  "geometry": {"coordinates":[-1.547975,52.263799],"type":"Point"}
}
