{
  "type": "Feature",
  "properties": {
    "iso:country":"GB",
    "wof:name":"TN2 4DF",
    "wof:placetype":"postalcode"
},
  "geometry": {"coordinates":[0.33155656531303,51.15369472174273],"type":"Point"}
}