{
  "type": "Feature",
  "properties": {
    "iso:country":"GB",
    "wof:name":"TS19 9BJ",
    "wof:placetype":"postalcode"
},
  "geometry": {"coordinates":[-1.34033506406657,54.58601680985553],"type":"Point"}
}