{
  "type": "Feature",
  "properties": {
    "iso:country": "GB",
    "wof:name": "OX11 7QA",
    "wof:placetype": "postalcode"
  },
  "geometry": {"coordinates":[-1.227554,51.61025],"type":"Point"}
}
