{
  "type": "Feature",
  "properties": {
    "iso:country":"GB",
    "wof:name":"OX11 7QA",
    "wof:placetype":"postalcode"
},
  "geometry": {"coordinates":[-1.227554030341,51.6102503436965],"type":"Point"}
}