{
  "type": "Feature",
  "properties": {
    "iso:country":"GB",
    "wof:name":"ME15 0NS",
    "wof:placetype":"postalcode"
},
  "geometry": {"coordinates":[0.46379049877189,51.24748551886781],"type":"Point"}
}