{
  "type": "Feature",
  "properties": {
    "date:inception_lower": "1980-01-01",
    "date:inception_upper": "1980-01-01",
    "iso:country": "GB",
    "wof:name": "ME15 0NS",
    "wof:placetype": "postalcode"
  },
  "geometry": {"coordinates":[0.46382,51.247484],"type":"Point"}
}
