{
  "type": "Feature",
  "properties": {
    "date:inception_lower": "2009-04-01",
    "date:inception_upper": "2009-04-01",
    "iso:country": "GB",
    "wof:name": "CH43 9WG",
    "wof:placetype": "postalcode"
  },
  "geometry": {"coordinates":[-3.081538,53.389503],"type":"Point"}
}
