{
  "type": "Feature",
  "properties": {
    "iso:country":"GB",
    "wof:name":"CH43 9WG",
    "wof:placetype":"postalcode"
},
  "geometry": {"coordinates":[-3.08153757777793,53.38950294029539],"type":"Point"}
}