{
  "type": "Feature",
  "properties": {
    "date:inception_lower": "1980-01-01",
    "date:inception_upper": "1980-01-01",
    "iso:country": "GB",
    "wof:name": "DE14 1RZ",
    "wof:placetype": "postalcode"
  },
  "geometry": {"coordinates":[-1.624165,52.821264],"type":"Point"}
}
