{
  "type": "Feature",
  "properties": {
    "iso:country":"GB",
    "wof:name":"TS6 9QR",
    "wof:placetype":"postalcode"
},
  "geometry": {"coordinates":[-1.15229204637438,54.56393330069994],"type":"Point"}
}