{
  "type": "Feature",
  "properties": {
    "iso:country":"GB",
    "wof:name":"CH48 6HB",
    "wof:placetype":"postalcode"
},
  "geometry": {"coordinates":[-3.15774521446037,53.37512461989647],"type":"Point"}
}