{
  "type": "Feature",
  "properties": {
    "iso:country": "GB",
    "wof:name": "CH48 6HB",
    "wof:placetype": "postalcode"
  },
  "geometry": {"coordinates":[-3.157745,53.375125],"type":"Point"}
}
