{
  "type": "Feature",
  "properties": {
    "date:inception_lower": "1980-01-01",
    "date:inception_upper": "1980-01-01",
    "iso:country": "GB",
    "wof:name": "TN37 7JF",
    "wof:placetype": "postalcode"
  },
  "geometry": {"coordinates":[0.557387,50.880482],"type":"Point"}
}
