{
  "type": "Feature",
  "properties": {
    "iso:country": "GB",
    "wof:name": "RG5 4NH",
    "wof:placetype": "postalcode"
  },
  "geometry": {"coordinates":[-0.901528,51.460889],"type":"Point"}
}
