{
  "type": "Feature",
  "properties": {
    "date:inception_lower": "1980-01-01",
    "date:inception_upper": "1980-01-01",
    "iso:country": "GB",
    "wof:name": "RG5 4NH",
    "wof:placetype": "postalcode"
  },
  "geometry": {"coordinates":[-0.901528,51.460889],"type":"Point"}
}
