{
  "type": "Feature",
  "properties": {
    "iso:country": "GB",
    "wof:name": "DN11 0BE",
    "wof:placetype": "postalcode"
  },
  "geometry": {"coordinates":[-1.079735,53.476354],"type":"Point"}
}
