{
  "type": "Feature",
  "properties": {
    "iso:country":"GB",
    "wof:name":"DN11 0BE",
    "wof:placetype":"postalcode"
},
  "geometry": {"coordinates":[-1.07977854077024,53.4763795423851],"type":"Point"}
}