{
  "type": "Feature",
  "properties": {
    "iso:country": "GB",
    "wof:name": "S41 9BB",
    "wof:placetype": "postalcode"
  },
  "geometry": {"coordinates":[-1.423589,53.257337],"type":"Point"}
}
