{
  "type": "Feature",
  "properties": {
    "date:inception_lower":"1980-01-01",
    "date:inception_upper":"1980-01-31",
    "iso:country":"GB",
    "wof:name":"S41 9BB",
    "wof:placetype":"postalcode"
},
  "geometry": {"coordinates":[-1.423589,53.257337],"type":"Point"}
}