{
  "type": "Feature",
  "properties": {
    "iso:country":"GB",
    "wof:name":"PE34 3AS",
    "wof:placetype":"postalcode"
},
  "geometry": {"coordinates":[0.3579420042567,52.7148054063941],"type":"Point"}
}