{
  "type": "Feature",
  "properties": {
    "date:inception_lower": "1980-01-01",
    "date:inception_upper": "1980-01-01",
    "iso:country": "GB",
    "wof:name": "PE34 3AS",
    "wof:placetype": "postalcode"
  },
  "geometry": {"coordinates":[0.357942,52.714805],"type":"Point"}
}
