{
  "type": "Feature",
  "properties": {
    "iso:country": "GB",
    "wof:name": "OX16 9NG",
    "wof:placetype": "postalcode"
  },
  "geometry": {"coordinates":[-1.35131,52.056247],"type":"Point"}
}
