{
  "type": "Feature",
  "properties": {
    "date:inception_lower":"1981-06-01",
    "date:inception_upper":"1981-06-30",
    "iso:country":"GB",
    "wof:name":"CA14 5SU",
    "wof:placetype":"postalcode"
},
  "geometry": {"coordinates":[-3.538698,54.598835],"type":"Point"}
}