{
  "type": "Feature",
  "properties": {
    "iso:country":"GB",
    "wof:name":"DG8 9TB",
    "wof:placetype":"postalcode"
},
  "geometry": {"coordinates":[-4.44601731984953,54.87467926804329],"type":"Point"}
}