{
  "type": "Feature",
  "properties": {
    "date:inception_lower": "1980-01-01",
    "date:inception_upper": "1980-01-01",
    "iso:country": "GB",
    "wof:name": "B37 7NA",
    "wof:placetype": "postalcode"
  },
  "geometry": {"coordinates":[-1.735318,52.475397],"type":"Point"}
}
