{
  "type": "Feature",
  "properties": {
    "iso:country":"GB",
    "wof:name":"WN4 9JB",
    "wof:placetype":"postalcode"
},
  "geometry": {"coordinates":[-2.6238383364013,53.48491541778441],"type":"Point"}
}