{
  "type": "Feature",
  "properties": {
    "date:inception_lower": "1980-01-01",
    "date:inception_upper": "1980-01-01",
    "iso:country": "GB",
    "wof:name": "DA3 7RB",
    "wof:placetype": "postalcode"
  },
  "geometry": {"coordinates":[0.302586,51.390309],"type":"Point"}
}
