{
  "type": "Feature",
  "properties": {
    "iso:country":"GB",
    "wof:name":"IV30 6HS",
    "wof:placetype":"postalcode"
},
  "geometry": {"coordinates":[-3.28347707978644,57.64358820699137],"type":"Point"}
}