{
  "type": "Feature",
  "properties": {
    "iso:country":"GB",
    "wof:name":"CV1 5BP",
    "wof:placetype":"postalcode"
},
  "geometry": {"coordinates":[-1.49221283453704,52.41435177055334],"type":"Point"}
}