{
  "type": "Feature",
  "properties": {
    "iso:country": "GB",
    "wof:name": "CV1 5BP",
    "wof:placetype": "postalcode"
  },
  "geometry": {"coordinates":[-1.492213,52.414352],"type":"Point"}
}
