{
  "type": "Feature",
  "properties": {
    "iso:country":"GB",
    "wof:name":"CT6 6LL",
    "wof:placetype":"postalcode"
},
  "geometry": {"coordinates":[1.15066886756198,51.36600293536839],"type":"Point"}
}