{
  "type": "Feature",
  "properties": {
    "iso:country": "GB",
    "wof:name": "IG10 3FN",
    "wof:placetype": "postalcode"
  },
  "geometry": {"coordinates":[0.072141,51.648813],"type":"Point"}
}
