{
  "type": "Feature",
  "properties": {
    "iso:country":"GB",
    "wof:name":"IG10 3FN",
    "wof:placetype":"postalcode"
},
  "geometry": {"coordinates":[0.07205932358522,51.64886536184458],"type":"Point"}
}