{
  "type": "Feature",
  "properties": {
    "date:inception_lower":"2012-07-01",
    "date:inception_upper":"2012-07-31",
    "iso:country":"GB",
    "wof:name":"IG10 3FN",
    "wof:placetype":"postalcode"
},
  "geometry": {"coordinates":[0.072141,51.648813],"type":"Point"}
}