{
  "type": "Feature",
  "properties": {
    "iso:country":"GB",
    "wof:name":"CV1 3DH",
    "wof:placetype":"postalcode"
},
  "geometry": {"coordinates":[-1.51824333341199,52.40422984846295],"type":"Point"}
}