{
  "type": "Feature",
  "properties": {
    "iso:country":"GB",
    "wof:name":"LL57 4HJ",
    "wof:placetype":"postalcode"
},
  "geometry": {"coordinates":[-4.18585518454987,53.20523610243975],"type":"Point"}
}