{
  "type": "Feature",
  "properties": {
    "iso:country": "GB",
    "wof:name": "LL57 4HJ",
    "wof:placetype": "postalcode"
  },
  "geometry": {"coordinates":[-4.185855,53.205236],"type":"Point"}
}
