{
  "type": "Feature",
  "properties": {
    "date:inception_lower": "2005-11-01",
    "date:inception_upper": "2005-11-01",
    "iso:country": "GB",
    "wof:name": "LL57 4HJ",
    "wof:placetype": "postalcode"
  },
  "geometry": {"coordinates":[-4.185855,53.205236],"type":"Point"}
}
