{
  "type": "Feature",
  "properties": {
    "iso:country": "GB",
    "wof:name": "DL1 9SQ",
    "wof:placetype": "postalcode"
  },
  "geometry": {"coordinates":[-1.552836,54.523576],"type":"Point"}
}
