{
  "type": "Feature",
  "properties": {
    "iso:country": "GB",
    "wof:name": "SO15 2QU",
    "wof:placetype": "postalcode"
  },
  "geometry": {"coordinates":[-1.406124,50.919405],"type":"Point"}
}
