{
  "type": "Feature",
  "properties": {
    "iso:country":"GB",
    "wof:name":"ME9 9NP",
    "wof:placetype":"postalcode"
},
  "geometry": {"coordinates":[0.77687387481713,51.33198793421585],"type":"Point"}
}