{
  "type": "Feature",
  "properties": {
    "iso:country": "GB",
    "wof:name": "ME9 9NP",
    "wof:placetype": "postalcode"
  },
  "geometry": {"coordinates":[0.776934,51.331998],"type":"Point"}
}
