{
  "type": "Feature",
  "properties": {
    "iso:country":"GB",
    "wof:name":"B29 6RT",
    "wof:placetype":"postalcode"
},
  "geometry": {"coordinates":[-1.95034699303892,52.44387512714558],"type":"Point"}
}