{
  "type": "Feature",
  "properties": {
    "iso:country": "GB",
    "wof:name": "DL11 6SD",
    "wof:placetype": "postalcode"
  },
  "geometry": {"coordinates":[-1.945622,54.389936],"type":"Point"}
}
