{
  "type": "Feature",
  "properties": {
    "date:inception_lower": "1996-12-01",
    "date:inception_upper": "1996-12-01",
    "iso:country": "GB",
    "wof:name": "DL11 6SD",
    "wof:placetype": "postalcode"
  },
  "geometry": {"coordinates":[-1.945622,54.389936],"type":"Point"}
}
