{
  "type": "Feature",
  "properties": {
    "iso:country":"GB",
    "wof:name":"W4 2RP",
    "wof:placetype":"postalcode"
},
  "geometry": {"coordinates":[-0.25737766673163,51.48609666933864],"type":"Point"}
}