{
  "type": "Feature",
  "properties": {
    "iso:country":"GB",
    "wof:name":"SY11 3BW",
    "wof:placetype":"postalcode"
},
  "geometry": {"coordinates":[-2.99801723161238,52.92445854137113],"type":"Point"}
}