{
  "type": "Feature",
  "properties": {
    "date:inception_lower":"1980-01-01",
    "date:inception_upper":"1980-01-31",
    "iso:country":"GB",
    "wof:name":"SY11 3BW",
    "wof:placetype":"postalcode"
},
  "geometry": {"coordinates":[-2.998001,52.924464],"type":"Point"}
}