{
  "type": "Feature",
  "properties": {
    "iso:country": "GB",
    "wof:name": "WF4 4HS",
    "wof:placetype": "postalcode"
  },
  "geometry": {"coordinates":[-1.57633,53.648628],"type":"Point"}
}
