{
  "type": "Feature",
  "properties": {
    "iso:country":"GB",
    "wof:name":"WF4 4HS",
    "wof:placetype":"postalcode"
},
  "geometry": {"coordinates":[-1.57632957381951,53.64862829946919],"type":"Point"}
}