{
  "type": "Feature",
  "properties": {
    "date:inception_lower": "1982-03-01",
    "date:inception_upper": "1982-03-01",
    "iso:country": "GB",
    "wof:name": "B46 1UE",
    "wof:placetype": "postalcode"
  },
  "geometry": {"coordinates":[-1.714405,52.510643],"type":"Point"}
}
