{
  "type": "Feature",
  "properties": {
    "iso:country":"GB",
    "wof:name":"B46 1UE",
    "wof:placetype":"postalcode"
},
  "geometry": {"coordinates":[-1.71440460697852,52.51064256108184],"type":"Point"}
}