{
  "type": "Feature",
  "properties": {
    "iso:country":"GB",
    "wof:name":"NW4 2EF",
    "wof:placetype":"postalcode"
},
  "geometry": {"coordinates":[-0.21996345535653,51.58500849903015],"type":"Point"}
}