{
  "type": "Feature",
  "properties": {
    "date:inception_lower": "1986-07-01",
    "date:inception_upper": "1986-07-01",
    "iso:country": "GB",
    "wof:name": "MK41 0RB",
    "wof:placetype": "postalcode"
  },
  "geometry": {"coordinates":[-0.414188,52.149527],"type":"Point"}
}
