{
  "type": "Feature",
  "properties": {
    "iso:country":"GB",
    "wof:name":"CF45 3BS",
    "wof:placetype":"postalcode"
},
  "geometry": {"coordinates":[-3.37386186921837,51.67349008104615],"type":"Point"}
}