{
  "type": "Feature",
  "properties": {
    "iso:country": "GB",
    "wof:name": "CO2 0AU",
    "wof:placetype": "postalcode"
  },
  "geometry": {"coordinates":[0.905118,51.857945],"type":"Point"}
}
