{
  "type": "Feature",
  "properties": {
    "iso:country":"GB",
    "wof:name":"CO2 0AU",
    "wof:placetype":"postalcode"
},
  "geometry": {"coordinates":[0.90511812321408,51.85794458859028],"type":"Point"}
}