{
  "type": "Feature",
  "properties": {
    "date:inception_lower": "1980-01-01",
    "date:inception_upper": "1980-01-01",
    "iso:country": "GB",
    "wof:name": "CO2 0AU",
    "wof:placetype": "postalcode"
  },
  "geometry": {"coordinates":[0.905118,51.857945],"type":"Point"}
}
