{
  "type": "Feature",
  "properties": {
    "iso:country":"GB",
    "wof:name":"LD3 9DS",
    "wof:placetype":"postalcode"
},
  "geometry": {"coordinates":[-3.39348246400987,51.95029031174948],"type":"Point"}
}