{
  "type": "Feature",
  "properties": {
    "date:inception_lower": "1980-01-01",
    "date:inception_upper": "1980-01-01",
    "iso:country": "GB",
    "wof:name": "LD3 9DS",
    "wof:placetype": "postalcode"
  },
  "geometry": {"coordinates":[-3.393482,51.95029],"type":"Point"}
}
