{
  "type": "Feature",
  "properties": {
    "iso:country":"GB",
    "wof:name":"M40 7AZ",
    "wof:placetype":"postalcode"
},
  "geometry": {"coordinates":[-2.21120262282221,53.48655551514559],"type":"Point"}
}