{
  "type": "Feature",
  "properties": {
    "date:inception_lower": "1980-01-01",
    "date:inception_upper": "1980-01-01",
    "iso:country": "GB",
    "wof:name": "SG19 2NZ",
    "wof:placetype": "postalcode"
  },
  "geometry": {"coordinates":[-0.215971,52.130768],"type":"Point"}
}
