{
  "type": "Feature",
  "properties": {
    "date:inception_lower": "1980-01-01",
    "date:inception_upper": "1980-01-01",
    "iso:country": "GB",
    "wof:name": "BN2 1FB",
    "wof:placetype": "postalcode"
  },
  "geometry": {"coordinates":[-0.115185,50.816911],"type":"Point"}
}
