{
  "type": "Feature",
  "properties": {
    "iso:country":"GB",
    "wof:name":"NP4 7LP",
    "wof:placetype":"postalcode"
},
  "geometry": {"coordinates":[-3.06635771310789,51.73620892904598],"type":"Point"}
}