{
  "type": "Feature",
  "properties": {
    "iso:country": "GB",
    "wof:name": "NP4 7LP",
    "wof:placetype": "postalcode"
  },
  "geometry": {"coordinates":[-3.066358,51.736209],"type":"Point"}
}
