{
  "type": "Feature",
  "properties": {
    "iso:country":"GB",
    "wof:name":"KA6 6EJ",
    "wof:placetype":"postalcode"
},
  "geometry": {"coordinates":[-4.58064636331272,55.39487841540046],"type":"Point"}
}