{
  "type": "Feature",
  "properties": {
    "date:inception_lower": "1980-01-01",
    "date:inception_upper": "1980-01-01",
    "iso:country": "GB",
    "wof:name": "CB6 2NN",
    "wof:placetype": "postalcode"
  },
  "geometry": {"coordinates":[0.120738,52.387384],"type":"Point"}
}
