{
  "type": "Feature",
  "properties": {
    "date:inception_lower": "2003-10-01",
    "date:inception_upper": "2003-10-01",
    "iso:country": "GB",
    "wof:name": "LE3 1UT",
    "wof:placetype": "postalcode"
  },
  "geometry": {"coordinates":[-1.208837,52.633099],"type":"Point"}
}
