{
  "type": "Feature",
  "properties": {
    "iso:country":"GB",
    "wof:name":"YO25 4YX",
    "wof:placetype":"postalcode"
},
  "geometry": {"coordinates":[-0.3909404786613,54.02160530777587],"type":"Point"}
}