{
  "type": "Feature",
  "properties": {
    "iso:country": "GB",
    "wof:name": "W2 3JS",
    "wof:placetype": "postalcode"
  },
  "geometry": {"coordinates":[-0.186797,51.511977],"type":"Point"}
}
