{
  "type": "Feature",
  "properties": {
    "date:inception_lower": "2017-02-01",
    "date:inception_upper": "2017-02-01",
    "iso:country": "GB",
    "wof:name": "BS49 4FP",
    "wof:placetype": "postalcode"
  },
  "geometry": {"coordinates":[-2.837846,51.396639],"type":"Point"}
}
