{
  "type": "Feature",
  "properties": {
    "date:inception_lower": "1980-01-01",
    "date:inception_upper": "1980-01-01",
    "iso:country": "GB",
    "wof:name": "MK46 4AN",
    "wof:placetype": "postalcode"
  },
  "geometry": {"coordinates":[-0.69868,52.152547],"type":"Point"}
}
