{
  "type": "Feature",
  "properties": {
    "iso:country":"GB",
    "wof:name":"BA3 5XL",
    "wof:placetype":"postalcode"
},
  "geometry": {"coordinates":[-2.37880267336856,51.28752759338984],"type":"Point"}
}