{
  "type": "Feature",
  "properties": {
    "date:inception_lower": "2016-06-01",
    "date:inception_upper": "2016-06-01",
    "iso:country": "GB",
    "wof:name": "TA11 7EP",
    "wof:placetype": "postalcode"
  },
  "geometry": {"coordinates":[-2.69165,51.030912],"type":"Point"}
}
