{
  "type": "Feature",
  "properties": {
    "iso:country":"GB",
    "wof:name":"N11 3BF",
    "wof:placetype":"postalcode"
},
  "geometry": {"coordinates":[-0.14737721279889,51.61183343122395],"type":"Point"}
}