{
  "type": "Feature",
  "properties": {
    "iso:country":"GB",
    "wof:name":"CM1 4QD",
    "wof:placetype":"postalcode"
},
  "geometry": {"coordinates":[0.34766140459405,51.77274345194229],"type":"Point"}
}