{
  "type": "Feature",
  "properties": {
    "date:inception_lower": "2001-06-01",
    "date:inception_upper": "2001-06-01",
    "iso:country": "GB",
    "wof:name": "BA3 5TS",
    "wof:placetype": "postalcode"
  },
  "geometry": {"coordinates":[-2.445172,51.242101],"type":"Point"}
}
