{
  "type": "Feature",
  "properties": {
    "iso:country":"GB",
    "wof:name":"OX7 6EY",
    "wof:placetype":"postalcode"
},
  "geometry": {"coordinates":[-1.62844290505633,51.85043214231522],"type":"Point"}
}