{
  "type": "Feature",
  "properties": {
    "iso:country":"GB",
    "wof:name":"SN4 0DH",
    "wof:placetype":"postalcode"
},
  "geometry": {"coordinates":[-1.67541816360579,51.54946510509101],"type":"Point"}
}