{
  "type": "Feature",
  "properties": {
    "date:inception_lower":"1980-01-01",
    "date:inception_upper":"1980-01-31",
    "iso:country":"GB",
    "wof:name":"DH4 6EL",
    "wof:placetype":"postalcode"
},
  "geometry": {"coordinates":[-1.516004,54.854856],"type":"Point"}
}