{
  "type": "Feature",
  "properties": {
    "iso:country":"GB",
    "wof:name":"DH4 6EL",
    "wof:placetype":"postalcode"
},
  "geometry": {"coordinates":[-1.51600364183061,54.854855972661],"type":"Point"}
}