{
  "type": "Feature",
  "properties": {
    "iso:country":"GB",
    "wof:name":"LE14 2AA",
    "wof:placetype":"postalcode"
},
  "geometry": {"coordinates":[-0.74121864939169,52.75938501437005],"type":"Point"}
}