{
  "type": "Feature",
  "properties": {
    "date:inception_lower": "1980-01-01",
    "date:inception_upper": "1980-01-01",
    "iso:country": "GB",
    "wof:name": "LE14 2AA",
    "wof:placetype": "postalcode"
  },
  "geometry": {"coordinates":[-0.741219,52.759385],"type":"Point"}
}
