{
  "type": "Feature",
  "properties": {
    "iso:country":"GB",
    "wof:name":"ME3 8EY",
    "wof:placetype":"postalcode"
},
  "geometry": {"coordinates":[0.49184225409418,51.4157279903741],"type":"Point"}
}