{
  "type": "Feature",
  "properties": {
    "iso:country":"GB",
    "wof:name":"CB7 4SS",
    "wof:placetype":"postalcode"
},
  "geometry": {"coordinates":[0.41218322002135,52.44529718390163],"type":"Point"}
}