{
  "type": "Feature",
  "properties": {
    "iso:country":"GB",
    "wof:name":"SW4 6BP",
    "wof:placetype":"postalcode"
},
  "geometry": {"coordinates":[-0.13637944868461,51.46443450814164],"type":"Point"}
}