{
  "type": "Feature",
  "properties": {
    "iso:country":"GB",
    "wof:name":"YO15 2DL",
    "wof:placetype":"postalcode"
},
  "geometry": {"coordinates":[-0.1918558964635,54.08272332496843],"type":"Point"}
}