{
  "type": "Feature",
  "properties": {
    "iso:country": "GB",
    "wof:name": "WF12 7DD",
    "wof:placetype": "postalcode"
  },
  "geometry": {"coordinates":[-1.621905,53.691957],"type":"Point"}
}
