{
  "type": "Feature",
  "properties": {
    "iso:country":"GB",
    "wof:name":"WF12 7DD",
    "wof:placetype":"postalcode"
},
  "geometry": {"coordinates":[-1.6218415250218,53.69189701340529],"type":"Point"}
}