{
  "type": "Feature",
  "properties": {
    "date:inception_lower": "1984-10-01",
    "date:inception_upper": "1984-10-01",
    "iso:country": "GB",
    "wof:name": "SS13 1AS",
    "wof:placetype": "postalcode"
  },
  "geometry": {"coordinates":[0.51254,51.579712],"type":"Point"}
}
