{
  "type": "Feature",
  "properties": {
    "iso:country": "GB",
    "wof:name": "CB7 4AA",
    "wof:placetype": "postalcode"
  },
  "geometry": {"coordinates":[0.267804,52.398357],"type":"Point"}
}
