{
  "type": "Feature",
  "properties": {
    "date:inception_lower": "2017-12-01",
    "date:inception_upper": "2017-12-01",
    "iso:country": "GB",
    "wof:name": "EH23 4NF",
    "wof:placetype": "postalcode"
  },
  "geometry": {"coordinates":[-3.045484,55.833232],"type":"Point"}
}
