{
  "type": "Feature",
  "properties": {
    "iso:country": "GB",
    "wof:name": "EH23 4NF",
    "wof:placetype": "postalcode"
  },
  "geometry": {"coordinates":[-3.045855,55.8334],"type":"Point"}
}
