{
  "type": "Feature",
  "properties": {
    "iso:country": "GB",
    "wof:name": "OX2 9GS",
    "wof:placetype": "postalcode"
  },
  "geometry": {"coordinates":[-1.294203,51.743175],"type":"Point"}
}
