{
  "type": "Feature",
  "properties": {
    "date:inception_lower": "2014-01-01",
    "date:inception_upper": "2014-01-01",
    "iso:country": "GB",
    "wof:name": "OX2 9GS",
    "wof:placetype": "postalcode"
  },
  "geometry": {"coordinates":[-1.294203,51.743175],"type":"Point"}
}
