{
  "type": "Feature",
  "properties": {
    "date:inception_lower":"2014-09-01",
    "date:inception_upper":"2014-09-30",
    "iso:country":"GB",
    "wof:name":"OL8 2AS",
    "wof:placetype":"postalcode"
},
  "geometry": {"coordinates":[-2.100608,53.527669],"type":"Point"}
}