{
  "type": "Feature",
  "properties": {
    "iso:country":"GB",
    "wof:name":"OX15 6JR",
    "wof:placetype":"postalcode"
},
  "geometry": {"coordinates":[-1.43314623991339,52.07339116987166],"type":"Point"}
}