{
  "type": "Feature",
  "properties": {
    "iso:country":"GB",
    "wof:name":"NE46 1UD",
    "wof:placetype":"postalcode"
},
  "geometry": {"coordinates":[-2.06272303402594,54.94366209501291],"type":"Point"}
}