{
  "type": "Feature",
  "properties": {
    "iso:country":"GB",
    "wof:name":"W8 6UU",
    "wof:placetype":"postalcode"
},
  "geometry": {"coordinates":[-0.19614448802963,51.4986234760169],"type":"Point"}
}