{
  "type": "Feature",
  "properties": {
    "iso:country": "GB",
    "wof:name": "CM13 3RG",
    "wof:placetype": "postalcode"
  },
  "geometry": {"coordinates":[0.339985,51.603713],"type":"Point"}
}
