{
  "type": "Feature",
  "properties": {
    "iso:country": "GB",
    "wof:name": "BS48 2AY",
    "wof:placetype": "postalcode"
  },
  "geometry": {"coordinates":[-2.780852,51.433137],"type":"Point"}
}
