{
  "type": "Feature",
  "properties": {
    "iso:country":"GB",
    "wof:name":"BS48 2AY",
    "wof:placetype":"postalcode"
},
  "geometry": {"coordinates":[-2.78085246928939,51.43313727104596],"type":"Point"}
}