{
  "type": "Feature",
  "properties": {
    "date:inception_lower": "2001-06-01",
    "date:inception_upper": "2001-06-01",
    "iso:country": "GB",
    "wof:name": "OX29 7NT",
    "wof:placetype": "postalcode"
  },
  "geometry": {"coordinates":[-1.519669,51.775898],"type":"Point"}
}
