{
  "type": "Feature",
  "properties": {
    "date:inception_lower": "1980-01-01",
    "date:inception_upper": "1980-01-01",
    "iso:country": "GB",
    "wof:name": "NR5 8AG",
    "wof:placetype": "postalcode"
  },
  "geometry": {"coordinates":[1.246914,52.631697],"type":"Point"}
}
