{
  "type": "Feature",
  "properties": {
    "iso:country":"GB",
    "wof:name":"NR5 8AG",
    "wof:placetype":"postalcode"
},
  "geometry": {"coordinates":[1.24691437927072,52.63169724290925],"type":"Point"}
}