{
  "type": "Feature",
  "properties": {
    "date:inception_lower": "2017-12-01",
    "date:inception_upper": "2017-12-01",
    "iso:country": "GB",
    "wof:name": "TS14 7FG",
    "wof:placetype": "postalcode"
  },
  "geometry": {"coordinates":[-1.051719,54.530612],"type":"Point"}
}
