{
  "type": "Feature",
  "properties": {
    "iso:country": "GB",
    "wof:name": "TS14 7FG",
    "wof:placetype": "postalcode"
  },
  "geometry": {"coordinates":[-1.051719,54.530612],"type":"Point"}
}
