{
  "type": "Feature",
  "properties": {
    "iso:country":"GB",
    "wof:name":"BL2 2PR",
    "wof:placetype":"postalcode"
},
  "geometry": {"coordinates":[-2.40819736612327,53.58159156227032],"type":"Point"}
}