{
  "type": "Feature",
  "properties": {
    "date:inception_lower": "2020-02-01",
    "date:inception_upper": "2020-02-01",
    "iso:country": "GB",
    "wof:name": "NR24 2RX",
    "wof:placetype": "postalcode"
  },
  "geometry": {"coordinates":[1.112406,52.869976],"type":"Point"}
}
