{
  "type": "Feature",
  "properties": {
    "iso:country": "GB",
    "wof:name": "NR24 2RX",
    "wof:placetype": "postalcode"
  },
  "geometry": {"coordinates":[1.11295,52.870115],"type":"Point"}
}
