{
  "type": "Feature",
  "properties": {
    "iso:country": "GB",
    "wof:name": "HP1 1EG",
    "wof:placetype": "postalcode"
  },
  "geometry": {"coordinates":[-0.473295,51.750828],"type":"Point"}
}
