{
  "type": "Feature",
  "properties": {
    "iso:country":"GB",
    "wof:name":"HP1 1EG",
    "wof:placetype":"postalcode"
},
  "geometry": {"coordinates":[-0.47329458454817,51.75082761134015],"type":"Point"}
}