{
  "type": "Feature",
  "properties": {
    "iso:country": "GB",
    "wof:name": "RM19 1TB",
    "wof:placetype": "postalcode"
  },
  "geometry": {"coordinates":[0.240604,51.486425],"type":"Point"}
}
