{
  "type": "Feature",
  "properties": {
    "iso:country": "GB",
    "wof:name": "WA7 1JA",
    "wof:placetype": "postalcode"
  },
  "geometry": {"coordinates":[-2.735244,53.341431],"type":"Point"}
}
