{
  "type": "Feature",
  "properties": {
    "iso:country":"GB",
    "wof:name":"NE15 9PA",
    "wof:placetype":"postalcode"
},
  "geometry": {"coordinates":[-1.75885383068156,54.9928820235685],"type":"Point"}
}