{
  "type": "Feature",
  "properties": {
    "iso:country":"GB",
    "wof:name":"PE37 7BF",
    "wof:placetype":"postalcode"
},
  "geometry": {"coordinates":[0.69332751297994,52.64694218458185],"type":"Point"}
}