{
  "type": "Feature",
  "properties": {
    "iso:country": "GB",
    "wof:name": "PE37 7BF",
    "wof:placetype": "postalcode"
  },
  "geometry": {"coordinates":[0.693328,52.646942],"type":"Point"}
}
