{
  "type": "Feature",
  "properties": {
    "date:inception_lower": "1996-12-01",
    "date:inception_upper": "1996-12-01",
    "iso:country": "GB",
    "wof:name": "IP14 6QQ",
    "wof:placetype": "postalcode"
  },
  "geometry": {"coordinates":[1.182042,52.220833],"type":"Point"}
}
