{
  "type": "Feature",
  "properties": {
    "date:inception_lower":"2006-01-01",
    "date:inception_upper":"2006-01-31",
    "iso:country":"GB",
    "wof:name":"PE3 9TN",
    "wof:placetype":"postalcode"
},
  "geometry": {"coordinates":[-0.258096,52.582936],"type":"Point"}
}