{
  "type": "Feature",
  "properties": {
    "iso:country":"GB",
    "wof:name":"SW19 3DL",
    "wof:placetype":"postalcode"
},
  "geometry": {"coordinates":[-0.19259324765392,51.40404827615146],"type":"Point"}
}