{
  "type": "Feature",
  "properties": {
    "date:inception_lower": "1980-01-01",
    "date:inception_upper": "1980-01-01",
    "iso:country": "GB",
    "wof:name": "S73 9PF",
    "wof:placetype": "postalcode"
  },
  "geometry": {"coordinates":[-1.385527,53.536435],"type":"Point"}
}
