{
  "type": "Feature",
  "properties": {
    "iso:country":"GB",
    "wof:name":"S73 9PF",
    "wof:placetype":"postalcode"
},
  "geometry": {"coordinates":[-1.3855272918522,53.53643503999495],"type":"Point"}
}