{
  "type": "Feature",
  "properties": {
    "iso:country": "GB",
    "wof:name": "SW1P 4RG",
    "wof:placetype": "postalcode"
  },
  "geometry": {"coordinates":[-0.127206,51.49087],"type":"Point"}
}
