{
  "type": "Feature",
  "properties": {
    "iso:country":"GB",
    "wof:name":"SW1P 4RG",
    "wof:placetype":"postalcode"
},
  "geometry": {"coordinates":[-0.12720599997596,51.49087037183733],"type":"Point"}
}