{
  "type": "Feature",
  "properties": {
    "iso:country": "GB",
    "wof:name": "OX10 6FE",
    "wof:placetype": "postalcode"
  },
  "geometry": {"coordinates":[-1.113341,51.623834],"type":"Point"}
}
