{
  "type": "Feature",
  "properties": {
    "date:inception_lower": "2019-09-01",
    "date:inception_upper": "2019-09-01",
    "iso:country": "GB",
    "wof:name": "OX10 6FE",
    "wof:placetype": "postalcode"
  },
  "geometry": {"coordinates":[-1.113438,51.624059],"type":"Point"}
}
