{
  "type": "Feature",
  "properties": {
    "iso:country": "GB",
    "wof:name": "KT12 4QZ",
    "wof:placetype": "postalcode"
  },
  "geometry": {"coordinates":[-0.391585,51.373883],"type":"Point"}
}
