{
  "type": "Feature",
  "properties": {
    "iso:country": "GB",
    "wof:name": "G33 4LD",
    "wof:placetype": "postalcode"
  },
  "geometry": {"coordinates":[-4.139631,55.861783],"type":"Point"}
}
