{
  "type": "Feature",
  "properties": {
    "iso:country": "GB",
    "wof:name": "LL19 8YP",
    "wof:placetype": "postalcode"
  },
  "geometry": {"coordinates":[-3.425426,53.327541],"type":"Point"}
}
