{
  "type": "Feature",
  "properties": {
    "date:inception_lower":"2006-11-01",
    "date:inception_upper":"2006-11-30",
    "iso:country":"GB",
    "wof:name":"LL19 8YP",
    "wof:placetype":"postalcode"
},
  "geometry": {"coordinates":[-3.425426,53.327541],"type":"Point"}
}