{
  "type": "Feature",
  "properties": {
    "iso:country":"GB",
    "wof:name":"LU5 4JF",
    "wof:placetype":"postalcode"
},
  "geometry": {"coordinates":[-0.5172572830765,51.8888911465781],"type":"Point"}
}