{
  "type": "Feature",
  "properties": {
    "iso:country": "GB",
    "wof:name": "LU5 4JF",
    "wof:placetype": "postalcode"
  },
  "geometry": {"coordinates":[-0.517257,51.888891],"type":"Point"}
}
