{
  "type": "Feature",
  "properties": {
    "iso:country": "GB",
    "wof:name": "PE13 2NB",
    "wof:placetype": "postalcode"
  },
  "geometry": {"coordinates":[0.162508,52.661931],"type":"Point"}
}
