{
  "type": "Feature",
  "properties": {
    "date:inception_lower": "1980-01-01",
    "date:inception_upper": "1980-01-01",
    "iso:country": "GB",
    "wof:name": "S70 6LQ",
    "wof:placetype": "postalcode"
  },
  "geometry": {"coordinates":[-1.49281,53.546079],"type":"Point"}
}
