{
  "type": "Feature",
  "properties": {
    "iso:country": "GB",
    "wof:name": "S70 6LQ",
    "wof:placetype": "postalcode"
  },
  "geometry": {"coordinates":[-1.49281,53.546079],"type":"Point"}
}
