{
  "type": "Feature",
  "properties": {
    "date:inception_lower": "1993-08-01",
    "date:inception_upper": "1993-08-01",
    "iso:country": "GB",
    "wof:name": "ST4 6PD",
    "wof:placetype": "postalcode"
  },
  "geometry": {"coordinates":[-2.208468,52.995546],"type":"Point"}
}
