{
  "type": "Feature",
  "properties": {
    "iso:country":"GB",
    "wof:name":"ST4 6PD",
    "wof:placetype":"postalcode"
},
  "geometry": {"coordinates":[-2.20846839849687,52.99554630213577],"type":"Point"}
}