{
  "type": "Feature",
  "properties": {
    "iso:country":"GB",
    "wof:name":"SW16 3QT",
    "wof:placetype":"postalcode"
},
  "geometry": {"coordinates":[-0.11384267272866,51.42441659610882],"type":"Point"}
}