{
  "type": "Feature",
  "properties": {
    "iso:country":"GB",
    "wof:name":"CT3 1TF",
    "wof:placetype":"postalcode"
},
  "geometry": {"coordinates":[1.15836351542995,51.27652293012704],"type":"Point"}
}