{
  "type": "Feature",
  "properties": {
    "date:inception_lower": "1980-01-01",
    "date:inception_upper": "1980-01-01",
    "iso:country": "GB",
    "wof:name": "CT3 1TF",
    "wof:placetype": "postalcode"
  },
  "geometry": {"coordinates":[1.158405,51.2765],"type":"Point"}
}
