{
  "type": "Feature",
  "properties": {
    "iso:country":"GB",
    "wof:name":"PL30 5EU",
    "wof:placetype":"postalcode"
},
  "geometry": {"coordinates":[-4.76503570853268,50.44429630516057],"type":"Point"}
}