{
  "type": "Feature",
  "properties": {
    "iso:country": "GB",
    "wof:name": "E3 5NR",
    "wof:placetype": "postalcode"
  },
  "geometry": {"coordinates":[-0.035821,51.53441],"type":"Point"}
}
