{
  "type": "Feature",
  "properties": {
    "iso:country":"GB",
    "wof:name":"KA18 2QS",
    "wof:placetype":"postalcode"
},
  "geometry": {"coordinates":[-4.40319877450057,55.43392844702099],"type":"Point"}
}