{
  "type": "Feature",
  "properties": {
    "date:inception_lower":"1999-06-01",
    "date:inception_upper":"1999-06-30",
    "iso:country":"GB",
    "wof:name":"DE6 1GJ",
    "wof:placetype":"postalcode"
},
  "geometry": {"coordinates":[-1.722828,53.022977],"type":"Point"}
}