{
  "type": "Feature",
  "properties": {
    "iso:country": "GB",
    "wof:name": "DE6 1GJ",
    "wof:placetype": "postalcode"
  },
  "geometry": {"coordinates":[-1.722828,53.022977],"type":"Point"}
}
