{
  "type": "Feature",
  "properties": {
    "iso:country":"GB",
    "wof:name":"NP7 6DF",
    "wof:placetype":"postalcode"
},
  "geometry": {"coordinates":[-3.01768756472214,51.83229963821595],"type":"Point"}
}