{
  "type": "Feature",
  "properties": {
    "iso:country": "GB",
    "wof:name": "BS5 0JD",
    "wof:placetype": "postalcode"
  },
  "geometry": {"coordinates":[-2.568712,51.465596],"type":"Point"}
}
