{
  "type": "Feature",
  "properties": {
    "date:inception_lower": "1998-06-01",
    "date:inception_upper": "1998-06-01",
    "iso:country": "GB",
    "wof:name": "BS5 0JD",
    "wof:placetype": "postalcode"
  },
  "geometry": {"coordinates":[-2.568713,51.465595],"type":"Point"}
}
