{
  "type": "Feature",
  "properties": {
    "iso:country":"GB",
    "wof:name":"S65 2DB",
    "wof:placetype":"postalcode"
},
  "geometry": {"coordinates":[-1.33210363677084,53.43731902226893],"type":"Point"}
}