{
  "type": "Feature",
  "properties": {
    "iso:country": "GB",
    "wof:name": "NN7 2QF",
    "wof:placetype": "postalcode"
  },
  "geometry": {"coordinates":[-0.872994,52.169441],"type":"Point"}
}
