{
  "type": "Feature",
  "properties": {
    "iso:country":"GB",
    "wof:name":"NN7 2QF",
    "wof:placetype":"postalcode"
},
  "geometry": {"coordinates":[-0.87300996541007,52.16942766686966],"type":"Point"}
}