{
  "type": "Feature",
  "properties": {
    "iso:country": "GB",
    "wof:name": "DY14 9EA",
    "wof:placetype": "postalcode"
  },
  "geometry": {"coordinates":[-2.422061,52.374636],"type":"Point"}
}
