{
  "type": "Feature",
  "properties": {
    "iso:country":"GB",
    "wof:name":"DY14 9EA",
    "wof:placetype":"postalcode"
},
  "geometry": {"coordinates":[-2.42206073349843,52.37463564807175],"type":"Point"}
}