{
  "type": "Feature",
  "properties": {
    "iso:country": "GB",
    "wof:name": "LD2 3JL",
    "wof:placetype": "postalcode"
  },
  "geometry": {"coordinates":[-3.217243,52.108637],"type":"Point"}
}
