{
  "type": "Feature",
  "properties": {
    "iso:country":"GB",
    "wof:name":"LD2 3JL",
    "wof:placetype":"postalcode"
},
  "geometry": {"coordinates":[-3.2172429283143,52.108636697332],"type":"Point"}
}