{
  "type": "Feature",
  "properties": {
    "iso:country":"GB",
    "wof:name":"PE7 1LB",
    "wof:placetype":"postalcode"
},
  "geometry": {"coordinates":[-0.14028356492138,52.55872909208935],"type":"Point"}
}