{
  "type": "Feature",
  "properties": {
    "date:inception_lower":"1980-01-01",
    "date:inception_upper":"1980-01-31",
    "iso:country":"GB",
    "wof:name":"CF43 4DB",
    "wof:placetype":"postalcode"
},
  "geometry": {"coordinates":[-3.485801,51.674981],"type":"Point"}
}