{
  "type": "Feature",
  "properties": {
    "iso:country":"GB",
    "wof:name":"CF43 4DB",
    "wof:placetype":"postalcode"
},
  "geometry": {"coordinates":[-3.48572551197701,51.67522118047337],"type":"Point"}
}