{
  "type": "Feature",
  "properties": {
    "date:inception_lower": "1987-04-01",
    "date:inception_upper": "1987-04-01",
    "iso:country": "GB",
    "wof:name": "CV22 5AU",
    "wof:placetype": "postalcode"
  },
  "geometry": {"coordinates":[-1.22771,52.359914],"type":"Point"}
}
