{
  "type": "Feature",
  "properties": {
    "iso:country": "GB",
    "wof:name": "CV22 5AU",
    "wof:placetype": "postalcode"
  },
  "geometry": {"coordinates":[-1.22771,52.359914],"type":"Point"}
}
