{
  "type": "Feature",
  "properties": {
    "iso:country": "GB",
    "wof:name": "SS9 3GA",
    "wof:placetype": "postalcode"
  },
  "geometry": {"coordinates":[0.672092,51.546822],"type":"Point"}
}
