{
  "type": "Feature",
  "properties": {
    "iso:country":"GB",
    "wof:name":"SS9 3GA",
    "wof:placetype":"postalcode"
},
  "geometry": {"coordinates":[0.67209148794338,51.5468224854006],"type":"Point"}
}