{
  "type": "Feature",
  "properties": {
    "date:inception_lower":"1980-01-01",
    "date:inception_upper":"1980-01-31",
    "iso:country":"GB",
    "wof:name":"LL16 4AN",
    "wof:placetype":"postalcode"
},
  "geometry": {"coordinates":[-3.396271,53.182282],"type":"Point"}
}