{
  "type": "Feature",
  "properties": {
    "iso:country":"GB",
    "wof:name":"LL16 4AN",
    "wof:placetype":"postalcode"
},
  "geometry": {"coordinates":[-3.39627112729657,53.18228241727583],"type":"Point"}
}