{
  "type": "Feature",
  "properties": {
    "iso:country":"GB",
    "wof:name":"B27 7JX",
    "wof:placetype":"postalcode"
},
  "geometry": {"coordinates":[-1.82109217952785,52.43164095222981],"type":"Point"}
}