{
  "type": "Feature",
  "properties": {
    "iso:country": "GB",
    "wof:name": "TQ8 8AP",
    "wof:placetype": "postalcode"
  },
  "geometry": {"coordinates":[-3.779252,50.233612],"type":"Point"}
}
