{
  "type": "Feature",
  "properties": {
    "date:inception_lower":"1980-01-01",
    "date:inception_upper":"1980-01-31",
    "iso:country":"GB",
    "wof:name":"TQ8 8AP",
    "wof:placetype":"postalcode"
},
  "geometry": {"coordinates":[-3.779252,50.233612],"type":"Point"}
}