{
  "type": "Feature",
  "properties": {
    "iso:country":"GB",
    "wof:name":"IV2 7RR",
    "wof:placetype":"postalcode"
},
  "geometry": {"coordinates":[-4.03704477661819,57.56750114101009],"type":"Point"}
}