{
  "type": "Feature",
  "properties": {
    "date:inception_lower": "1998-12-01",
    "date:inception_upper": "1998-12-01",
    "iso:country": "GB",
    "wof:name": "IV2 7RR",
    "wof:placetype": "postalcode"
  },
  "geometry": {"coordinates":[-4.037157,57.567724],"type":"Point"}
}
