{
  "type": "Feature",
  "properties": {
    "iso:country": "GB",
    "wof:name": "LL12 8BD",
    "wof:placetype": "postalcode"
  },
  "geometry": {"coordinates":[-2.988185,53.067996],"type":"Point"}
}
