{
  "type": "Feature",
  "properties": {
    "iso:country":"GB",
    "wof:name":"LL12 8BD",
    "wof:placetype":"postalcode"
},
  "geometry": {"coordinates":[-2.98818485551629,53.06799578431229],"type":"Point"}
}