{
  "type": "Feature",
  "properties": {
    "iso:country":"GB",
    "wof:name":"TW2 7DH",
    "wof:placetype":"postalcode"
},
  "geometry": {"coordinates":[-0.35046873006943,51.45366779757138],"type":"Point"}
}