{
  "type": "Feature",
  "properties": {
    "iso:country": "GB",
    "wof:name": "TW2 7DH",
    "wof:placetype": "postalcode"
  },
  "geometry": {"coordinates":[-0.350469,51.453668],"type":"Point"}
}
