{
  "type": "Feature",
  "properties": {
    "iso:country":"GB",
    "wof:name":"RG17 9XN",
    "wof:placetype":"postalcode"
},
  "geometry": {"coordinates":[-1.44501644709731,51.39853235317483],"type":"Point"}
}