{
  "type": "Feature",
  "properties": {
    "iso:country": "GB",
    "wof:name": "RG17 9XN",
    "wof:placetype": "postalcode"
  },
  "geometry": {"coordinates":[-1.445016,51.398532],"type":"Point"}
}
