{
  "type": "Feature",
  "properties": {
    "iso:country":"GB",
    "wof:name":"HU11 4PQ",
    "wof:placetype":"postalcode"
},
  "geometry": {"coordinates":[-0.19389384736101,53.79552490299872],"type":"Point"}
}