{
  "type": "Feature",
  "properties": {
    "iso:country":"GB",
    "wof:name":"G76 8BZ",
    "wof:placetype":"postalcode"
},
  "geometry": {"coordinates":[-4.26955083715066,55.78634088804036],"type":"Point"}
}