{
  "type": "Feature",
  "properties": {
    "iso:country": "GB",
    "wof:name": "G76 8BZ",
    "wof:placetype": "postalcode"
  },
  "geometry": {"coordinates":[-4.269551,55.786341],"type":"Point"}
}
