{
  "type": "Feature",
  "properties": {
    "iso:country":"GB",
    "wof:name":"CF11 7BX",
    "wof:placetype":"postalcode"
},
  "geometry": {"coordinates":[-3.18244999527171,51.46468911989133],"type":"Point"}
}