{
  "type": "Feature",
  "properties": {
    "iso:country":"GB",
    "wof:name":"CT4 7DY",
    "wof:placetype":"postalcode"
},
  "geometry": {"coordinates":[0.96846599656587,51.21914585176063],"type":"Point"}
}