{
  "type": "Feature",
  "properties": {
    "iso:country":"GB",
    "wof:name":"GU1 2AA",
    "wof:placetype":"postalcode"
},
  "geometry": {"coordinates":[-0.56490539066432,51.23945899623359],"type":"Point"}
}