{
  "type": "Feature",
  "properties": {
    "iso:country": "GB",
    "wof:name": "GU1 2AA",
    "wof:placetype": "postalcode"
  },
  "geometry": {"coordinates":[-0.564905,51.239459],"type":"Point"}
}
