{
  "type": "Feature",
  "properties": {
    "date:inception_lower": "1980-01-01",
    "date:inception_upper": "1980-01-01",
    "iso:country": "GB",
    "wof:name": "HP3 9UZ",
    "wof:placetype": "postalcode"
  },
  "geometry": {"coordinates":[-0.457503,51.734065],"type":"Point"}
}
