{
  "type": "Feature",
  "properties": {
    "date:inception_lower": "2023-08-01",
    "date:inception_upper": "2023-08-01",
    "iso:country": "GB",
    "wof:name": "SA62 6FL",
    "wof:placetype": "postalcode"
  },
  "geometry": {"coordinates":[-5.259016,51.881757],"type":"Point"}
}
