{
  "type": "Feature",
  "properties": {
    "date:inception_lower": "1980-01-01",
    "date:inception_upper": "1980-01-01",
    "iso:country": "GB",
    "wof:name": "BL1 7AJ",
    "wof:placetype": "postalcode"
  },
  "geometry": {"coordinates":[-2.431897,53.603871],"type":"Point"}
}
