{
  "type": "Feature",
  "properties": {
    "date:inception_lower": "2015-02-01",
    "date:inception_upper": "2015-02-01",
    "iso:country": "GB",
    "wof:name": "B60 9UJ",
    "wof:placetype": "postalcode"
  },
  "geometry": {"coordinates":[-2.050652,52.340372],"type":"Point"}
}
