{
  "type": "Feature",
  "properties": {
    "date:inception_lower":"1987-04-01",
    "date:inception_upper":"1987-04-30",
    "iso:country":"GB",
    "wof:name":"B27 6SA",
    "wof:placetype":"postalcode"
},
  "geometry": {"coordinates":[-1.810514,52.449497],"type":"Point"}
}