{
  "type": "Feature",
  "properties": {
    "date:inception_lower":"2008-10-01",
    "date:inception_upper":"2008-10-31",
    "iso:country":"GB",
    "wof:name":"NR29 5GA",
    "wof:placetype":"postalcode"
},
  "geometry": {"coordinates":[1.535702,52.742748],"type":"Point"}
}