{
  "type": "Feature",
  "properties": {
    "iso:country":"GB",
    "wof:name":"NR29 5GA",
    "wof:placetype":"postalcode"
},
  "geometry": {"coordinates":[1.53570187533725,52.74274815863715],"type":"Point"}
}