{
  "type": "Feature",
  "properties": {
    "iso:country": "GB",
    "wof:name": "NR29 5GA",
    "wof:placetype": "postalcode"
  },
  "geometry": {"coordinates":[1.535702,52.742748],"type":"Point"}
}
