{
  "type": "Feature",
  "properties": {
    "date:inception_lower": "1980-01-01",
    "date:inception_upper": "1980-01-01",
    "iso:country": "GB",
    "wof:name": "NG18 4BP",
    "wof:placetype": "postalcode"
  },
  "geometry": {"coordinates":[-1.190232,53.129881],"type":"Point"}
}
