{
  "type": "Feature",
  "properties": {
    "iso:country":"GB",
    "wof:name":"NR15 1LT",
    "wof:placetype":"postalcode"
},
  "geometry": {"coordinates":[1.23951924583675,52.52318565865999],"type":"Point"}
}