{
  "type": "Feature",
  "properties": {
    "iso:country":"GB",
    "wof:name":"NE28 9NJ",
    "wof:placetype":"postalcode"
},
  "geometry": {"coordinates":[-1.51024214264289,55.00764607040674],"type":"Point"}
}