{
  "type": "Feature",
  "properties": {
    "iso:country": "GB",
    "wof:name": "NE28 9NJ",
    "wof:placetype": "postalcode"
  },
  "geometry": {"coordinates":[-1.510242,55.007646],"type":"Point"}
}
