{
  "type": "Feature",
  "properties": {
    "date:inception_lower": "1980-01-01",
    "date:inception_upper": "1980-01-01",
    "iso:country": "GB",
    "wof:name": "NE28 9NJ",
    "wof:placetype": "postalcode"
  },
  "geometry": {"coordinates":[-1.510242,55.007646],"type":"Point"}
}
