{
  "type": "Feature",
  "properties": {
    "iso:country":"GB",
    "wof:name":"LU4 0EB",
    "wof:placetype":"postalcode"
},
  "geometry": {"coordinates":[-0.4723687924149,51.89492583179809],"type":"Point"}
}