{
  "type": "Feature",
  "properties": {
    "iso:country":"GB",
    "wof:name":"S42 5AY",
    "wof:placetype":"postalcode"
},
  "geometry": {"coordinates":[-1.39983307387913,53.20038248657498],"type":"Point"}
}