{
  "type": "Feature",
  "properties": {
    "date:inception_lower": "2004-05-01",
    "date:inception_upper": "2004-05-01",
    "iso:country": "GB",
    "wof:name": "YO12 4SZ",
    "wof:placetype": "postalcode"
  },
  "geometry": {"coordinates":[-0.44597,54.197506],"type":"Point"}
}
