{
  "type": "Feature",
  "properties": {
    "iso:country": "GB",
    "wof:name": "PE13 3LX",
    "wof:placetype": "postalcode"
  },
  "geometry": {"coordinates":[0.176948,52.668923],"type":"Point"}
}
