{
  "type": "Feature",
  "properties": {
    "iso:country":"GB",
    "wof:name":"PE13 3LX",
    "wof:placetype":"postalcode"
},
  "geometry": {"coordinates":[0.17694815159987,52.66892303663177],"type":"Point"}
}