{
  "type": "Feature",
  "properties": {
    "iso:country": "GB",
    "wof:name": "WA15 7EN",
    "wof:placetype": "postalcode"
  },
  "geometry": {"coordinates":[-2.302889,53.393228],"type":"Point"}
}
