{
  "type": "Feature",
  "properties": {
    "iso:country": "GB",
    "wof:name": "EX32 9FL",
    "wof:placetype": "postalcode"
  },
  "geometry": {"coordinates":[-4.034031,51.065805],"type":"Point"}
}
