{
  "type": "Feature",
  "properties": {
    "iso:country":"GB",
    "wof:name":"YO25 4DD",
    "wof:placetype":"postalcode"
},
  "geometry": {"coordinates":[-0.37021259136216,54.03365864938884],"type":"Point"}
}