{
  "type": "Feature",
  "properties": {
    "iso:country":"GB",
    "wof:name":"BS14 8PR",
    "wof:placetype":"postalcode"
},
  "geometry": {"coordinates":[-2.54587807166107,51.41346287868677],"type":"Point"}
}