{
  "type": "Feature",
  "properties": {
    "date:inception_lower": "1980-01-01",
    "date:inception_upper": "1980-01-01",
    "iso:country": "GB",
    "wof:name": "BS14 8PR",
    "wof:placetype": "postalcode"
  },
  "geometry": {"coordinates":[-2.545878,51.413463],"type":"Point"}
}
