{
  "type": "Feature",
  "properties": {
    "iso:country": "GB",
    "wof:name": "BS14 8PR",
    "wof:placetype": "postalcode"
  },
  "geometry": {"coordinates":[-2.545878,51.413463],"type":"Point"}
}
