{
  "type": "Feature",
  "properties": {
    "iso:country":"GB",
    "wof:name":"CV2 1UQ",
    "wof:placetype":"postalcode"
},
  "geometry": {"coordinates":[-1.46670089215377,52.44023000204906],"type":"Point"}
}