{
  "type": "Feature",
  "properties": {
    "iso:country": "GB",
    "wof:name": "CV2 1UQ",
    "wof:placetype": "postalcode"
  },
  "geometry": {"coordinates":[-1.468319,52.440228],"type":"Point"}
}
