{
  "type": "Feature",
  "properties": {
    "iso:country": "GB",
    "wof:name": "RH5 6BL",
    "wof:placetype": "postalcode"
  },
  "geometry": {"coordinates":[-0.389648,51.175423],"type":"Point"}
}
