{
  "type": "Feature",
  "properties": {
    "iso:country": "GB",
    "wof:name": "CB3 9EB",
    "wof:placetype": "postalcode"
  },
  "geometry": {"coordinates":[0.102428,52.195927],"type":"Point"}
}
