{
  "type": "Feature",
  "properties": {
    "iso:country":"GB",
    "wof:name":"ME10 2QA",
    "wof:placetype":"postalcode"
},
  "geometry": {"coordinates":[0.73912319892778,51.36198177246976],"type":"Point"}
}