{
  "type": "Feature",
  "properties": {
    "iso:country":"GB",
    "wof:name":"NR2 3JU",
    "wof:placetype":"postalcode"
},
  "geometry": {"coordinates":[1.27434964451207,52.62518560125684],"type":"Point"}
}