{
  "type": "Feature",
  "properties": {
    "iso:country":"GB",
    "wof:name":"DN22 0AS",
    "wof:placetype":"postalcode"
},
  "geometry": {"coordinates":[-0.82575251654916,53.33007665003913],"type":"Point"}
}