{
  "type": "Feature",
  "properties": {
    "date:inception_lower": "1980-01-01",
    "date:inception_upper": "1980-01-01",
    "iso:country": "GB",
    "wof:name": "DN22 0AS",
    "wof:placetype": "postalcode"
  },
  "geometry": {"coordinates":[-0.825752,53.330077],"type":"Point"}
}
