{
  "type": "Feature",
  "properties": {
    "iso:country": "GB",
    "wof:name": "WV6 7PW",
    "wof:placetype": "postalcode"
  },
  "geometry": {"coordinates":[-2.197192,52.593142],"type":"Point"}
}
