{
  "type": "Feature",
  "properties": {
    "date:inception_lower": "1983-07-01",
    "date:inception_upper": "1983-07-01",
    "iso:country": "GB",
    "wof:name": "WV6 7PW",
    "wof:placetype": "postalcode"
  },
  "geometry": {"coordinates":[-2.197192,52.593142],"type":"Point"}
}
