{
  "type": "Feature",
  "properties": {
    "iso:country":"GB",
    "wof:name":"SG1 4FX",
    "wof:placetype":"postalcode"
},
  "geometry": {"coordinates":[-0.16490729859894,51.92140202031914],"type":"Point"}
}