{
  "type": "Feature",
  "properties": {
    "iso:country": "GB",
    "wof:name": "SG1 4FX",
    "wof:placetype": "postalcode"
  },
  "geometry": {"coordinates":[-0.164907,51.921402],"type":"Point"}
}
