{
  "type": "Feature",
  "properties": {
    "date:inception_lower": "2010-11-01",
    "date:inception_upper": "2010-11-01",
    "iso:country": "GB",
    "wof:name": "EH5 1FX",
    "wof:placetype": "postalcode"
  },
  "geometry": {"coordinates":[-3.228558,55.984371],"type":"Point"}
}
