{
  "type": "Feature",
  "properties": {
    "date:inception_lower":"1980-01-01",
    "date:inception_upper":"1980-01-31",
    "iso:country":"GB",
    "wof:name":"BD9 5NE",
    "wof:placetype":"postalcode"
},
  "geometry": {"coordinates":[-1.799875,53.812362],"type":"Point"}
}