{
  "type": "Feature",
  "properties": {
    "iso:country":"GB",
    "wof:name":"BD9 5NE",
    "wof:placetype":"postalcode"
},
  "geometry": {"coordinates":[-1.79987466453657,53.81236161743178],"type":"Point"}
}