{
  "type": "Feature",
  "properties": {
    "iso:country":"GB",
    "wof:name":"NG7 4EP",
    "wof:placetype":"postalcode"
},
  "geometry": {"coordinates":[-1.16604505924943,52.96083140407779],"type":"Point"}
}