{
  "type": "Feature",
  "properties": {
    "date:inception_lower": "1980-01-01",
    "date:inception_upper": "1980-01-01",
    "iso:country": "GB",
    "wof:name": "NG7 4EP",
    "wof:placetype": "postalcode"
  },
  "geometry": {"coordinates":[-1.166045,52.960831],"type":"Point"}
}
