{
  "type": "Feature",
  "properties": {
    "iso:country": "GB",
    "wof:name": "PR3 2DD",
    "wof:placetype": "postalcode"
  },
  "geometry": {"coordinates":[-2.610807,53.829519],"type":"Point"}
}
