{
  "type": "Feature",
  "properties": {
    "date:inception_lower": "2018-01-01",
    "date:inception_upper": "2018-01-01",
    "iso:country": "GB",
    "wof:name": "PR3 2DD",
    "wof:placetype": "postalcode"
  },
  "geometry": {"coordinates":[-2.610895,53.830346],"type":"Point"}
}
