{
  "type": "Feature",
  "properties": {
    "iso:country":"GB",
    "wof:name":"TQ12 2JU",
    "wof:placetype":"postalcode"
},
  "geometry": {"coordinates":[-3.60857160556355,50.52981395860981],"type":"Point"}
}