{
  "type": "Feature",
  "properties": {
    "date:inception_lower":"1980-01-01",
    "date:inception_upper":"1980-01-31",
    "iso:country":"GB",
    "wof:name":"SM3 8LW",
    "wof:placetype":"postalcode"
},
  "geometry": {"coordinates":[-0.218716,51.367426],"type":"Point"}
}