{
  "type": "Feature",
  "properties": {
    "iso:country":"GB",
    "wof:name":"SM3 8LW",
    "wof:placetype":"postalcode"
},
  "geometry": {"coordinates":[-0.21871647374547,51.36742574584276],"type":"Point"}
}