{
  "type": "Feature",
  "properties": {
    "iso:country":"GB",
    "wof:name":"L16 7QE",
    "wof:placetype":"postalcode"
},
  "geometry": {"coordinates":[-2.88566189317488,53.39564748715915],"type":"Point"}
}