{
  "type": "Feature",
  "properties": {
    "iso:country": "GB",
    "wof:name": "L16 7QE",
    "wof:placetype": "postalcode"
  },
  "geometry": {"coordinates":[-2.885662,53.395647],"type":"Point"}
}
