{
  "type": "Feature",
  "properties": {
    "date:inception_lower": "1980-01-01",
    "date:inception_upper": "1980-01-01",
    "iso:country": "GB",
    "wof:name": "L16 7QE",
    "wof:placetype": "postalcode"
  },
  "geometry": {"coordinates":[-2.885662,53.395647],"type":"Point"}
}
