{
  "type": "Feature",
  "properties": {
    "iso:country":"GB",
    "wof:name":"PA2 0EU",
    "wof:placetype":"postalcode"
},
  "geometry": {"coordinates":[-4.47155511382985,55.82696148059397],"type":"Point"}
}