{
  "type": "Feature",
  "properties": {
    "iso:country":"GB",
    "wof:name":"EN7 5JP",
    "wof:placetype":"postalcode"
},
  "geometry": {"coordinates":[-0.08933651869767,51.70825438226015],"type":"Point"}
}