{
  "type": "Feature",
  "properties": {
    "iso:country":"GB",
    "wof:name":"S10 1BP",
    "wof:placetype":"postalcode"
},
  "geometry": {"coordinates":[-1.50023008826806,53.37843777451438],"type":"Point"}
}