{
  "type": "Feature",
  "properties": {
    "iso:country":"GB",
    "wof:name":"GL51 0FY",
    "wof:placetype":"postalcode"
},
  "geometry": {"coordinates":[-2.11953249849948,51.89832106766267],"type":"Point"}
}