{
  "type": "Feature",
  "properties": {
    "iso:country": "GB",
    "wof:name": "SK6 7JB",
    "wof:placetype": "postalcode"
  },
  "geometry": {"coordinates":[-2.064695,53.382117],"type":"Point"}
}
