{
  "type": "Feature",
  "properties": {
    "iso:country":"GB",
    "wof:name":"BB2 3SS",
    "wof:placetype":"postalcode"
},
  "geometry": {"coordinates":[-2.48192818077543,53.73864760147505],"type":"Point"}
}