{
  "type": "Feature",
  "properties": {
    "date:inception_lower": "2001-12-01",
    "date:inception_upper": "2001-12-01",
    "iso:country": "GB",
    "wof:name": "BB2 3SS",
    "wof:placetype": "postalcode"
  },
  "geometry": {"coordinates":[-2.481928,53.738648],"type":"Point"}
}
