{
  "type": "Feature",
  "properties": {
    "date:inception_lower":"1983-01-01",
    "date:inception_upper":"1983-01-31",
    "iso:country":"GB",
    "wof:name":"DG9 8TZ",
    "wof:placetype":"postalcode"
},
  "geometry": {"coordinates":[-5.118381,54.843373],"type":"Point"}
}