{
  "type": "Feature",
  "properties": {
    "date:inception_lower": "2014-05-01",
    "date:inception_upper": "2014-05-01",
    "iso:country": "GB",
    "wof:name": "CR0 1FL",
    "wof:placetype": "postalcode"
  },
  "geometry": {"coordinates":[-0.10116,51.370867],"type":"Point"}
}
