{
  "type": "Feature",
  "properties": {
    "iso:country": "GB",
    "wof:name": "CR0 1FL",
    "wof:placetype": "postalcode"
  },
  "geometry": {"coordinates":[-0.10116,51.370867],"type":"Point"}
}
