{
  "type": "Feature",
  "properties": {
    "iso:country":"GB",
    "wof:name":"ME3 8ET",
    "wof:placetype":"postalcode"
},
  "geometry": {"coordinates":[0.49273825438081,51.42135683227233],"type":"Point"}
}