{
  "type": "Feature",
  "properties": {
    "date:inception_lower": "2017-09-01",
    "date:inception_upper": "2017-09-01",
    "iso:country": "GB",
    "wof:name": "OX28 6FU",
    "wof:placetype": "postalcode"
  },
  "geometry": {"coordinates":[-1.490397,51.788152],"type":"Point"}
}
