{
  "type": "Feature",
  "properties": {
    "iso:country": "GB",
    "wof:name": "WN5 7TR",
    "wof:placetype": "postalcode"
  },
  "geometry": {"coordinates":[-2.712778,53.491007],"type":"Point"}
}
