{
  "type": "Feature",
  "properties": {
    "iso:country":"GB",
    "wof:name":"WN5 7TR",
    "wof:placetype":"postalcode"
},
  "geometry": {"coordinates":[-2.71277853977721,53.49100655743663],"type":"Point"}
}