{
  "type": "Feature",
  "properties": {
    "iso:country":"GB",
    "wof:name":"IG6 2EJ",
    "wof:placetype":"postalcode"
},
  "geometry": {"coordinates":[0.07544411079347,51.59477789970379],"type":"Point"}
}