{
  "type": "Feature",
  "properties": {
    "iso:country":"GB",
    "wof:name":"OL2 6RJ",
    "wof:placetype":"postalcode"
},
  "geometry": {"coordinates":[-2.09960351497411,53.56862982832804],"type":"Point"}
}