{
  "type": "Feature",
  "properties": {
    "iso:country": "GB",
    "wof:name": "OL2 6RJ",
    "wof:placetype": "postalcode"
  },
  "geometry": {"coordinates":[-2.099603,53.56863],"type":"Point"}
}
