{
  "type": "Feature",
  "properties": {
    "iso:country": "GB",
    "wof:name": "TW6 3YD",
    "wof:placetype": "postalcode"
  },
  "geometry": {"coordinates":[-0.445069,51.459295],"type":"Point"}
}
