{
  "type": "Feature",
  "properties": {
    "date:inception_lower":"1997-06-01",
    "date:inception_upper":"1997-06-30",
    "iso:country":"GB",
    "wof:name":"TW6 3YD",
    "wof:placetype":"postalcode"
},
  "geometry": {"coordinates":[-0.445069,51.459295],"type":"Point"}
}