{
  "type": "Feature",
  "properties": {
    "iso:country": "GB",
    "wof:name": "NG9 8LR",
    "wof:placetype": "postalcode"
  },
  "geometry": {"coordinates":[-1.267203,52.942413],"type":"Point"}
}
