{
  "type": "Feature",
  "properties": {
    "iso:country":"GB",
    "wof:name":"M33 3RQ",
    "wof:placetype":"postalcode"
},
  "geometry": {"coordinates":[-2.31924401684583,53.40852883503662],"type":"Point"}
}