{
  "type": "Feature",
  "properties": {
    "date:inception_lower":"2010-11-01",
    "date:inception_upper":"2010-11-30",
    "iso:country":"GB",
    "wof:name":"M5 3LJ",
    "wof:placetype":"postalcode"
},
  "geometry": {"coordinates":[-2.277363,53.47308],"type":"Point"}
}