{
  "type": "Feature",
  "properties": {
    "iso:country": "GB",
    "wof:name": "M5 3LJ",
    "wof:placetype": "postalcode"
  },
  "geometry": {"coordinates":[-2.277363,53.47308],"type":"Point"}
}
