{
  "type": "Feature",
  "properties": {
    "iso:country": "GB",
    "wof:name": "CW8 2SJ",
    "wof:placetype": "postalcode"
  },
  "geometry": {"coordinates":[-2.592219,53.240094],"type":"Point"}
}
