{
  "type": "Feature",
  "properties": {
    "iso:country": "GB",
    "wof:name": "CW8 2SJ",
    "wof:placetype": "postalcode"
  },
  "geometry": {"coordinates":[-2.593563,53.241894],"type":"Point"}
}
