{
  "type": "Feature",
  "properties": {
    "iso:country": "GB",
    "wof:name": "TA3 7LW",
    "wof:placetype": "postalcode"
  },
  "geometry": {"coordinates":[-3.112314,50.99272],"type":"Point"}
}
