{
  "type": "Feature",
  "properties": {
    "iso:country": "GB",
    "wof:name": "TA3 7LW",
    "wof:placetype": "postalcode"
  },
  "geometry": {"coordinates":[-3.112327,50.992675],"type":"Point"}
}
