{
  "type": "Feature",
  "properties": {
    "iso:country": "GB",
    "wof:name": "W10 5AE",
    "wof:placetype": "postalcode"
  },
  "geometry": {"coordinates":[-0.213202,51.524801],"type":"Point"}
}
