{
  "type": "Feature",
  "properties": {
    "date:inception_lower": "1980-01-01",
    "date:inception_upper": "1980-01-01",
    "iso:country": "GB",
    "wof:name": "W10 5AE",
    "wof:placetype": "postalcode"
  },
  "geometry": {"coordinates":[-0.213202,51.524801],"type":"Point"}
}
