{
  "type": "Feature",
  "properties": {
    "iso:country":"GB",
    "wof:name":"W10 5AE",
    "wof:placetype":"postalcode"
},
  "geometry": {"coordinates":[-0.21320172167184,51.52480076770108],"type":"Point"}
}