{
  "type": "Feature",
  "properties": {
    "iso:country":"GB",
    "wof:name":"S14 1GG",
    "wof:placetype":"postalcode"
},
  "geometry": {"coordinates":[-1.4489651722013,53.34383935066046],"type":"Point"}
}