{
  "type": "Feature",
  "properties": {
    "date:inception_lower": "1980-01-01",
    "date:inception_upper": "1980-01-01",
    "iso:country": "GB",
    "wof:name": "S14 1GG",
    "wof:placetype": "postalcode"
  },
  "geometry": {"coordinates":[-1.448934,53.343866],"type":"Point"}
}
