{
  "type": "Feature",
  "properties": {
    "iso:country":"GB",
    "wof:name":"L20 6EB",
    "wof:placetype":"postalcode"
},
  "geometry": {"coordinates":[-2.98486107578071,53.46673644039728],"type":"Point"}
}