{
  "type": "Feature",
  "properties": {
    "iso:country": "GB",
    "wof:name": "CV6 4GJ",
    "wof:placetype": "postalcode"
  },
  "geometry": {"coordinates":[-1.52013,52.447147],"type":"Point"}
}
