{
  "type": "Feature",
  "properties": {
    "iso:country":"GB",
    "wof:name":"CV6 4GJ",
    "wof:placetype":"postalcode"
},
  "geometry": {"coordinates":[-1.52012962875624,52.44714736439479],"type":"Point"}
}