{
  "type": "Feature",
  "properties": {
    "iso:country":"GB",
    "wof:name":"DN6 9HF",
    "wof:placetype":"postalcode"
},
  "geometry": {"coordinates":[-1.16481356214861,53.63226403559172],"type":"Point"}
}