{
  "type": "Feature",
  "properties": {
    "iso:country":"GB",
    "wof:name":"GU21 2PE",
    "wof:placetype":"postalcode"
},
  "geometry": {"coordinates":[-0.61632941157126,51.31836575327173],"type":"Point"}
}