{
  "type": "Feature",
  "properties": {
    "iso:country": "GB",
    "wof:name": "N18 1BB",
    "wof:placetype": "postalcode"
  },
  "geometry": {"coordinates":[-0.069234,51.614324],"type":"Point"}
}
