{
  "type": "Feature",
  "properties": {
    "iso:country":"GB",
    "wof:name":"N18 1BB",
    "wof:placetype":"postalcode"
},
  "geometry": {"coordinates":[-0.06923426631078,51.61432395066532],"type":"Point"}
}