{
  "type": "Feature",
  "properties": {
    "iso:country": "GB",
    "wof:name": "B42 1NA",
    "wof:placetype": "postalcode"
  },
  "geometry": {"coordinates":[-1.914761,52.534024],"type":"Point"}
}
