{
  "type": "Feature",
  "properties": {
    "iso:country":"GB",
    "wof:name":"TN9 9NN",
    "wof:placetype":"postalcode"
},
  "geometry": {"coordinates":[0.28699633940668,51.19012605659055],"type":"Point"}
}