{
  "type": "Feature",
  "properties": {
    "iso:country":"GB",
    "wof:name":"ME4 4SE",
    "wof:placetype":"postalcode"
},
  "geometry": {"coordinates":[0.52583858694456,51.38512341267442],"type":"Point"}
}