{
  "type": "Feature",
  "properties": {
    "iso:country":"GB",
    "wof:name":"SL3 8BT",
    "wof:placetype":"postalcode"
},
  "geometry": {"coordinates":[-0.54366621660695,51.50690636618808],"type":"Point"}
}