{
  "type": "Feature",
  "properties": {
    "date:inception_lower": "1991-01-01",
    "date:inception_upper": "1991-01-01",
    "iso:country": "GB",
    "wof:name": "L35 5HS",
    "wof:placetype": "postalcode"
  },
  "geometry": {"coordinates":[-2.790982,53.423414],"type":"Point"}
}
