{
  "type": "Feature",
  "properties": {
    "iso:country": "GB",
    "wof:name": "L35 5HS",
    "wof:placetype": "postalcode"
  },
  "geometry": {"coordinates":[-2.790982,53.423414],"type":"Point"}
}
