{
  "type": "Feature",
  "properties": {
    "iso:country":"GB",
    "wof:name":"SS15 5EN",
    "wof:placetype":"postalcode"
},
  "geometry": {"coordinates":[0.43780539659487,51.56985880049368],"type":"Point"}
}