{
  "type": "Feature",
  "properties": {
    "date:inception_lower": "1998-06-01",
    "date:inception_upper": "1998-06-01",
    "iso:country": "GB",
    "wof:name": "L39 3RH",
    "wof:placetype": "postalcode"
  },
  "geometry": {"coordinates":[-2.914791,53.551069],"type":"Point"}
}
