{
  "type": "Feature",
  "properties": {
    "iso:country":"GB",
    "wof:name":"CA2 6LF",
    "wof:placetype":"postalcode"
},
  "geometry": {"coordinates":[-2.9664876155226,54.87935419439386],"type":"Point"}
}