{
  "type": "Feature",
  "properties": {
    "date:inception_lower": "1980-01-01",
    "date:inception_upper": "1980-01-01",
    "iso:country": "GB",
    "wof:name": "SA61 1TN",
    "wof:placetype": "postalcode"
  },
  "geometry": {"coordinates":[-4.96445,51.801246],"type":"Point"}
}
