{
  "type": "Feature",
  "properties": {
    "iso:country": "GB",
    "wof:name": "GL20 7FT",
    "wof:placetype": "postalcode"
  },
  "geometry": {"coordinates":[-2.142778,51.975706],"type":"Point"}
}
