{
  "type": "Feature",
  "properties": {
    "iso:country":"GB",
    "wof:name":"CA4 0PA",
    "wof:placetype":"postalcode"
},
  "geometry": {"coordinates":[-2.9058987851129,54.78041843664224],"type":"Point"}
}