{
  "type": "Feature",
  "properties": {
    "iso:country":"GB",
    "wof:name":"RM7 0UB",
    "wof:placetype":"postalcode"
},
  "geometry": {"coordinates":[0.17295014032726,51.56248233897618],"type":"Point"}
}