{
  "type": "Feature",
  "properties": {
    "iso:country":"GB",
    "wof:name":"ME7 3QH",
    "wof:placetype":"postalcode"
},
  "geometry": {"coordinates":[0.56987416677354,51.34657200013146],"type":"Point"}
}