{
  "type": "Feature",
  "properties": {
    "iso:country":"GB",
    "wof:name":"PO20 0DD",
    "wof:placetype":"postalcode"
},
  "geometry": {"coordinates":[-0.78878715666108,50.73120579526657],"type":"Point"}
}