{
  "type": "Feature",
  "properties": {
    "date:inception_lower": "1983-03-01",
    "date:inception_upper": "1983-03-01",
    "iso:country": "GB",
    "wof:name": "BS2 0XH",
    "wof:placetype": "postalcode"
  },
  "geometry": {"coordinates":[-2.572425,51.443457],"type":"Point"}
}
