{
  "type": "Feature",
  "properties": {
    "iso:country":"GB",
    "wof:name":"BS2 0XH",
    "wof:placetype":"postalcode"
},
  "geometry": {"coordinates":[-2.57242287435599,51.44345829843061],"type":"Point"}
}