{
  "type": "Feature",
  "properties": {
    "iso:country": "GB",
    "wof:name": "TA1 1AH",
    "wof:placetype": "postalcode"
  },
  "geometry": {"coordinates":[-3.111601,51.02051],"type":"Point"}
}
