{
  "type": "Feature",
  "properties": {
    "iso:country":"GB",
    "wof:name":"LA14 3NY",
    "wof:placetype":"postalcode"
},
  "geometry": {"coordinates":[-3.26416480024948,54.11174692991773],"type":"Point"}
}