{
  "type": "Feature",
  "properties": {
    "iso:country":"GB",
    "wof:name":"CT21 4LE",
    "wof:placetype":"postalcode"
},
  "geometry": {"coordinates":[1.02617495113979,51.07455240121629],"type":"Point"}
}