{
  "type": "Feature",
  "properties": {
    "iso:country":"GB",
    "wof:name":"IP6 9EB",
    "wof:placetype":"postalcode"
},
  "geometry": {"coordinates":[1.23528549914117,52.08516664787479],"type":"Point"}
}