{
  "type": "Feature",
  "properties": {
    "iso:country":"GB",
    "wof:name":"KT12 2DQ",
    "wof:placetype":"postalcode"
},
  "geometry": {"coordinates":[-0.40634374935645,51.39034310422947],"type":"Point"}
}