{
  "type": "Feature",
  "properties": {
    "iso:country":"GB",
    "wof:name":"NW1 7ER",
    "wof:placetype":"postalcode"
},
  "geometry": {"coordinates":[-0.14087487178571,51.53480044662025],"type":"Point"}
}