{
  "type": "Feature",
  "properties": {
    "iso:country":"GB",
    "wof:name":"YO17 6PW",
    "wof:placetype":"postalcode"
},
  "geometry": {"coordinates":[-0.89700094038073,54.15827693512994],"type":"Point"}
}