{
  "type": "Feature",
  "properties": {
    "iso:country":"GB",
    "wof:name":"LS25 5AF",
    "wof:placetype":"postalcode"
},
  "geometry": {"coordinates":[-1.25156073139971,53.77808894406107],"type":"Point"}
}