{
  "type": "Feature",
  "properties": {
    "iso:country": "GB",
    "wof:name": "OX1 3UP",
    "wof:placetype": "postalcode"
  },
  "geometry": {"coordinates":[-1.246407,51.756249],"type":"Point"}
}
