{
  "type": "Feature",
  "properties": {
    "date:inception_lower":"2015-11-01",
    "date:inception_upper":"2015-11-30",
    "iso:country":"GB",
    "wof:name":"HX4 8QR",
    "wof:placetype":"postalcode"
},
  "geometry": {"coordinates":[-1.887861,53.684088],"type":"Point"}
}