{
  "type": "Feature",
  "properties": {
    "iso:country": "GB",
    "wof:name": "HX4 8QR",
    "wof:placetype": "postalcode"
  },
  "geometry": {"coordinates":[-1.887861,53.684088],"type":"Point"}
}
