{
  "type": "Feature",
  "properties": {
    "iso:country":"GB",
    "wof:name":"HX4 8QR",
    "wof:placetype":"postalcode"
},
  "geometry": {"coordinates":[-1.88807238109577,53.6839562287981],"type":"Point"}
}