{
  "type": "Feature",
  "properties": {
    "iso:country": "GB",
    "wof:name": "DL12 8LB",
    "wof:placetype": "postalcode"
  },
  "geometry": {"coordinates":[-1.915181,54.545087],"type":"Point"}
}
