{
  "type": "Feature",
  "properties": {
    "iso:country":"GB",
    "wof:name":"DL12 8LB",
    "wof:placetype":"postalcode"
},
  "geometry": {"coordinates":[-1.91518094781918,54.5450870432128],"type":"Point"}
}