{
  "type": "Feature",
  "properties": {
    "iso:country":"GB",
    "wof:name":"SR6 9NG",
    "wof:placetype":"postalcode"
},
  "geometry": {"coordinates":[-1.36821171957052,54.92686919045585],"type":"Point"}
}