{
  "type": "Feature",
  "properties": {
    "iso:country":"GB",
    "wof:name":"MK40 1HT",
    "wof:placetype":"postalcode"
},
  "geometry": {"coordinates":[-0.47448261662172,52.13722756978964],"type":"Point"}
}