{
  "type": "Feature",
  "properties": {
    "date:inception_lower":"2017-08-01",
    "date:inception_upper":"2017-08-31",
    "iso:country":"GB",
    "wof:name":"TN16 3PR",
    "wof:placetype":"postalcode"
},
  "geometry": {"coordinates":[0.024415,51.328909],"type":"Point"}
}