{
  "type": "Feature",
  "properties": {
    "iso:country":"GB",
    "wof:name":"GU12 6QW",
    "wof:placetype":"postalcode"
},
  "geometry": {"coordinates":[-0.73212358340101,51.24270248414881],"type":"Point"}
}