{
  "type": "Feature",
  "properties": {
    "iso:country":"GB",
    "wof:name":"HA2 9JT",
    "wof:placetype":"postalcode"
},
  "geometry": {"coordinates":[-0.3741245549109,51.57203957956899],"type":"Point"}
}