{
  "type": "Feature",
  "properties": {
    "iso:country": "GB",
    "wof:name": "DE21 7BT",
    "wof:placetype": "postalcode"
  },
  "geometry": {"coordinates":[-1.412817,52.92198],"type":"Point"}
}
