{
  "type": "Feature",
  "properties": {
    "iso:country":"GB",
    "wof:name":"DE21 7BT",
    "wof:placetype":"postalcode"
},
  "geometry": {"coordinates":[-1.41286817907763,52.92177314979025],"type":"Point"}
}