{
  "type": "Feature",
  "properties": {
    "iso:country":"GB",
    "wof:name":"PO11 9AN",
    "wof:placetype":"postalcode"
},
  "geometry": {"coordinates":[-0.98208757088773,50.7848612065722],"type":"Point"}
}