{
  "type": "Feature",
  "properties": {
    "date:inception_lower":"1980-01-01",
    "date:inception_upper":"1980-01-31",
    "iso:country":"GB",
    "wof:name":"PO11 9AN",
    "wof:placetype":"postalcode"
},
  "geometry": {"coordinates":[-0.982072,50.78485],"type":"Point"}
}