{
  "type": "Feature",
  "properties": {
    "iso:country":"GB",
    "wof:name":"NW2 2QA",
    "wof:placetype":"postalcode"
},
  "geometry": {"coordinates":[-0.19965256486108,51.56057218862522],"type":"Point"}
}