{
  "type": "Feature",
  "properties": {
    "date:inception_lower": "1980-01-01",
    "date:inception_upper": "1980-01-01",
    "iso:country": "GB",
    "wof:name": "KT1 3NJ",
    "wof:placetype": "postalcode"
  },
  "geometry": {"coordinates":[-0.287316,51.409895],"type":"Point"}
}
