{
  "type": "Feature",
  "properties": {
    "date:inception_lower":"1980-01-01",
    "date:inception_upper":"1980-01-31",
    "iso:country":"GB",
    "wof:name":"EH22 4LN",
    "wof:placetype":"postalcode"
},
  "geometry": {"coordinates":[-3.068137,55.866468],"type":"Point"}
}