{
  "type": "Feature",
  "properties": {
    "iso:country":"GB",
    "wof:name":"EH22 4LN",
    "wof:placetype":"postalcode"
},
  "geometry": {"coordinates":[-3.06813680720822,55.86646753528629],"type":"Point"}
}