{
  "type": "Feature",
  "properties": {
    "iso:country":"GB",
    "wof:name":"NP25 5DR",
    "wof:placetype":"postalcode"
},
  "geometry": {"coordinates":[-2.73394777919534,51.8156755349064],"type":"Point"}
}