{
  "type": "Feature",
  "properties": {
    "iso:country": "GB",
    "wof:name": "NP25 5DR",
    "wof:placetype": "postalcode"
  },
  "geometry": {"coordinates":[-2.733948,51.815676],"type":"Point"}
}
