{
  "type": "Feature",
  "properties": {
    "date:inception_lower":"2001-12-01",
    "date:inception_upper":"2001-12-31",
    "iso:country":"GB",
    "wof:name":"NP25 5DR",
    "wof:placetype":"postalcode"
},
  "geometry": {"coordinates":[-2.733948,51.815676],"type":"Point"}
}