{
  "type": "Feature",
  "properties": {
    "iso:country":"GB",
    "wof:name":"CO2 9PE",
    "wof:placetype":"postalcode"
},
  "geometry": {"coordinates":[0.87888515523942,51.8647415195617],"type":"Point"}
}