{
  "type": "Feature",
  "properties": {
    "date:inception_lower":"1980-01-01",
    "date:inception_upper":"1980-01-31",
    "iso:country":"GB",
    "wof:name":"CO2 9PE",
    "wof:placetype":"postalcode"
},
  "geometry": {"coordinates":[0.878885,51.864742],"type":"Point"}
}