{
  "type": "Feature",
  "properties": {
    "iso:country":"GB",
    "wof:name":"NE4 9XW",
    "wof:placetype":"postalcode"
},
  "geometry": {"coordinates":[-1.65636319078283,54.98464717576078],"type":"Point"}
}