{
  "type": "Feature",
  "properties": {
    "date:inception_lower": "1981-06-01",
    "date:inception_upper": "1981-06-01",
    "iso:country": "GB",
    "wof:name": "NE4 9XW",
    "wof:placetype": "postalcode"
  },
  "geometry": {"coordinates":[-1.656363,54.984647],"type":"Point"}
}
