{
  "type": "Feature",
  "properties": {
    "iso:country":"GB",
    "wof:name":"LN6 0PH",
    "wof:placetype":"postalcode"
},
  "geometry": {"coordinates":[-0.6058864436137,53.22124784327676],"type":"Point"}
}