{
  "type": "Feature",
  "properties": {
    "iso:country":"GB",
    "wof:name":"CH7 6XG",
    "wof:placetype":"postalcode"
},
  "geometry": {"coordinates":[-3.11483795018929,53.1709022658158],"type":"Point"}
}