{
  "type": "Feature",
  "properties": {
    "iso:country": "GB",
    "wof:name": "GL16 8DS",
    "wof:placetype": "postalcode"
  },
  "geometry": {"coordinates":[-2.622951,51.794086],"type":"Point"}
}
