{
  "type": "Feature",
  "properties": {
    "iso:country":"GB",
    "wof:name":"GL16 8DS",
    "wof:placetype":"postalcode"
},
  "geometry": {"coordinates":[-2.62335201899177,51.79391710743189],"type":"Point"}
}