{
  "type": "Feature",
  "properties": {
    "iso:country":"GB",
    "wof:name":"TS17 9HD",
    "wof:placetype":"postalcode"
},
  "geometry": {"coordinates":[-1.29894065672884,54.52933666646881],"type":"Point"}
}