{
  "type": "Feature",
  "properties": {
    "iso:country": "GB",
    "wof:name": "NE5 2SR",
    "wof:placetype": "postalcode"
  },
  "geometry": {"coordinates":[-1.677858,54.989415],"type":"Point"}
}
