{
  "type": "Feature",
  "properties": {
    "iso:country":"GB",
    "wof:name":"NE5 2SR",
    "wof:placetype":"postalcode"
},
  "geometry": {"coordinates":[-1.67785814909789,54.98941472922178],"type":"Point"}
}