{
  "type": "Feature",
  "properties": {
    "date:inception_lower":"1980-01-01",
    "date:inception_upper":"1980-01-31",
    "iso:country":"GB",
    "wof:name":"NE5 2SR",
    "wof:placetype":"postalcode"
},
  "geometry": {"coordinates":[-1.677858,54.989415],"type":"Point"}
}