{
  "type": "Feature",
  "properties": {
    "iso:country": "GB",
    "wof:name": "MK16 9FH",
    "wof:placetype": "postalcode"
  },
  "geometry": {"coordinates":[-0.707594,52.081725],"type":"Point"}
}
