{
  "type": "Feature",
  "properties": {
    "iso:country":"GB",
    "wof:name":"TF13 6NZ",
    "wof:placetype":"postalcode"
},
  "geometry": {"coordinates":[-2.5290644014415,52.62060362918852],"type":"Point"}
}