{
  "type": "Feature",
  "properties": {
    "date:inception_lower": "1980-01-01",
    "date:inception_upper": "1980-01-01",
    "iso:country": "GB",
    "wof:name": "TF13 6NZ",
    "wof:placetype": "postalcode"
  },
  "geometry": {"coordinates":[-2.529064,52.620604],"type":"Point"}
}
