{
  "type": "Feature",
  "properties": {
    "date:inception_lower": "1980-01-01",
    "date:inception_upper": "1980-01-01",
    "iso:country": "GB",
    "wof:name": "BS7 8DJ",
    "wof:placetype": "postalcode"
  },
  "geometry": {"coordinates":[-2.597088,51.473502],"type":"Point"}
}
