{
  "type": "Feature",
  "properties": {
    "iso:country":"GB",
    "wof:name":"RH10 1TG",
    "wof:placetype":"postalcode"
},
  "geometry": {"coordinates":[-0.17824033484159,51.11302527328523],"type":"Point"}
}