{
  "type": "Feature",
  "properties": {
    "iso:country": "GB",
    "wof:name": "BN26 6BE",
    "wof:placetype": "postalcode"
  },
  "geometry": {"coordinates":[0.245911,50.823095],"type":"Point"}
}
