{
  "type": "Feature",
  "properties": {
    "iso:country":"GB",
    "wof:name":"W6 8JE",
    "wof:placetype":"postalcode"
},
  "geometry": {"coordinates":[-0.22163540546345,51.48925598131191],"type":"Point"}
}