{
  "type": "Feature",
  "properties": {
    "date:inception_lower": "2010-11-01",
    "date:inception_upper": "2010-11-01",
    "iso:country": "GB",
    "wof:name": "RH15 5BW",
    "wof:placetype": "postalcode"
  },
  "geometry": {"coordinates":[-0.154065,50.954052],"type":"Point"}
}
