{
  "type": "Feature",
  "properties": {
    "iso:country": "GB",
    "wof:name": "BH25 6RJ",
    "wof:placetype": "postalcode"
  },
  "geometry": {"coordinates":[-1.67082,50.75265],"type":"Point"}
}
