{
  "type": "Feature",
  "properties": {
    "iso:country":"GB",
    "wof:name":"SP4 9BY",
    "wof:placetype":"postalcode"
},
  "geometry": {"coordinates":[-1.76014542230161,51.1973208500289],"type":"Point"}
}