{
  "type": "Feature",
  "properties": {
    "iso:country":"GB",
    "wof:name":"AL8 6YR",
    "wof:placetype":"postalcode"
},
  "geometry": {"coordinates":[-0.21961873717792,51.79035756424986],"type":"Point"}
}