{
  "type": "Feature",
  "properties": {
    "date:inception_lower": "1980-01-01",
    "date:inception_upper": "1980-01-01",
    "iso:country": "GB",
    "wof:name": "LL28 5PY",
    "wof:placetype": "postalcode"
  },
  "geometry": {"coordinates":[-3.796235,53.262947],"type":"Point"}
}
