{
  "type": "Feature",
  "properties": {
    "iso:country": "GB",
    "wof:name": "W7 3QA",
    "wof:placetype": "postalcode"
  },
  "geometry": {"coordinates":[-0.33233,51.509424],"type":"Point"}
}
