{
  "type": "Feature",
  "properties": {
    "iso:country":"GB",
    "wof:name":"W7 3QA",
    "wof:placetype":"postalcode"
},
  "geometry": {"coordinates":[-0.33233050408534,51.50942450533611],"type":"Point"}
}