{
  "type": "Feature",
  "properties": {
    "iso:country": "GB",
    "wof:name": "EH31 2AP",
    "wof:placetype": "postalcode"
  },
  "geometry": {"coordinates":[-2.833277,56.034273],"type":"Point"}
}
