{
  "type": "Feature",
  "properties": {
    "iso:country":"GB",
    "wof:name":"EH31 2AP",
    "wof:placetype":"postalcode"
},
  "geometry": {"coordinates":[-2.83327657160907,56.03427282185719],"type":"Point"}
}