{
  "type": "Feature",
  "properties": {
    "iso:country":"GB",
    "wof:name":"W1T 2PU",
    "wof:placetype":"postalcode"
},
  "geometry": {"coordinates":[-0.13524618072949,51.51940588352483],"type":"Point"}
}