{
  "type": "Feature",
  "properties": {
    "iso:country": "GB",
    "wof:name": "KY14 7DL",
    "wof:placetype": "postalcode"
  },
  "geometry": {"coordinates":[-3.22977,56.290594],"type":"Point"}
}
