{
  "type": "Feature",
  "properties": {
    "iso:country":"GB",
    "wof:name":"N19 3DD",
    "wof:placetype":"postalcode"
},
  "geometry": {"coordinates":[-0.13209206648486,51.57251918589302],"type":"Point"}
}