{
  "type": "Feature",
  "properties": {
    "iso:country":"GB",
    "wof:name":"SO24 9TS",
    "wof:placetype":"postalcode"
},
  "geometry": {"coordinates":[-1.1679548192277,51.15285014300812],"type":"Point"}
}