{
  "type": "Feature",
  "properties": {
    "iso:country": "GB",
    "wof:name": "SO24 9TS",
    "wof:placetype": "postalcode"
  },
  "geometry": {"coordinates":[-1.167955,51.15285],"type":"Point"}
}
