{
  "type": "Feature",
  "properties": {
    "date:inception_lower": "1980-01-01",
    "date:inception_upper": "1980-01-01",
    "iso:country": "GB",
    "wof:name": "SO24 9TS",
    "wof:placetype": "postalcode"
  },
  "geometry": {"coordinates":[-1.168329,51.152616],"type":"Point"}
}
