{
  "type": "Feature",
  "properties": {
    "date:inception_lower":"1982-03-01",
    "date:inception_upper":"1982-03-31",
    "iso:country":"GB",
    "wof:name":"B64 7HS",
    "wof:placetype":"postalcode"
},
  "geometry": {"coordinates":[-2.063724,52.468402],"type":"Point"}
}