{
  "type": "Feature",
  "properties": {
    "iso:country":"GB",
    "wof:name":"B64 7HS",
    "wof:placetype":"postalcode"
},
  "geometry": {"coordinates":[-2.06372418754824,52.46840182825918],"type":"Point"}
}