{
  "type": "Feature",
  "properties": {
    "iso:country": "GB",
    "wof:name": "LE17 6AU",
    "wof:placetype": "postalcode"
  },
  "geometry": {"coordinates":[-1.165905,52.411296],"type":"Point"}
}
