{
  "type": "Feature",
  "properties": {
    "iso:country": "GB",
    "wof:name": "PL1 9TD",
    "wof:placetype": "postalcode"
  },
  "geometry": {"coordinates":[-4.143005,50.369584],"type":"Point"}
}
