{
  "type": "Feature",
  "properties": {
    "iso:country":"GB",
    "wof:name":"NR3 3HR",
    "wof:placetype":"postalcode"
},
  "geometry": {"coordinates":[1.29204481581798,52.64314967983869],"type":"Point"}
}