{
  "type": "Feature",
  "properties": {
    "date:inception_lower":"2014-11-01",
    "date:inception_upper":"2014-11-30",
    "iso:country":"GB",
    "wof:name":"SY7 9DR",
    "wof:placetype":"postalcode"
},
  "geometry": {"coordinates":[-2.799146,52.406212],"type":"Point"}
}