{
  "type": "Feature",
  "properties": {
    "iso:country":"GB",
    "wof:name":"SY7 9DR",
    "wof:placetype":"postalcode"
},
  "geometry": {"coordinates":[-2.79914592110816,52.40621163915354],"type":"Point"}
}