{
  "type": "Feature",
  "properties": {
    "iso:country": "GB",
    "wof:name": "DN7 5RA",
    "wof:placetype": "postalcode"
  },
  "geometry": {"coordinates":[-1.028332,53.595999],"type":"Point"}
}
