{
  "type": "Feature",
  "properties": {
    "iso:country":"GB",
    "wof:name":"DN7 5RA",
    "wof:placetype":"postalcode"
},
  "geometry": {"coordinates":[-1.02833156951224,53.59599891253889],"type":"Point"}
}