{
  "type": "Feature",
  "properties": {
    "iso:country": "GB",
    "wof:name": "IP20 9BS",
    "wof:placetype": "postalcode"
  },
  "geometry": {"coordinates":[1.292962,52.401849],"type":"Point"}
}
