{
  "type": "Feature",
  "properties": {
    "date:inception_lower": "1985-04-01",
    "date:inception_upper": "1985-04-01",
    "iso:country": "GB",
    "wof:name": "IP20 9BS",
    "wof:placetype": "postalcode"
  },
  "geometry": {"coordinates":[1.292962,52.401849],"type":"Point"}
}
