{
  "type": "Feature",
  "properties": {
    "iso:country": "GB",
    "wof:name": "RM10 8LP",
    "wof:placetype": "postalcode"
  },
  "geometry": {"coordinates":[0.157393,51.550856],"type":"Point"}
}
