{
  "type": "Feature",
  "properties": {
    "iso:country": "GB",
    "wof:name": "NP11 3RJ",
    "wof:placetype": "postalcode"
  },
  "geometry": {"coordinates":[-3.156033,51.667708],"type":"Point"}
}
