{
  "type": "Feature",
  "properties": {
    "iso:country":"GB",
    "wof:name":"TD5 7SU",
    "wof:placetype":"postalcode"
},
  "geometry": {"coordinates":[-2.41794139740102,55.61947471324935],"type":"Point"}
}