{
  "type": "Feature",
  "properties": {
    "iso:country": "GB",
    "wof:name": "LS6 4RF",
    "wof:placetype": "postalcode"
  },
  "geometry": {"coordinates":[-1.571165,53.829469],"type":"Point"}
}
