{
  "type": "Feature",
  "properties": {
    "date:inception_lower":"1998-06-01",
    "date:inception_upper":"1998-06-30",
    "iso:country":"GB",
    "wof:name":"LS6 4RF",
    "wof:placetype":"postalcode"
},
  "geometry": {"coordinates":[-1.571165,53.829469],"type":"Point"}
}