{
  "type": "Feature",
  "properties": {
    "iso:country":"GB",
    "wof:name":"LS6 4RF",
    "wof:placetype":"postalcode"
},
  "geometry": {"coordinates":[-1.57116552832147,53.82946886315359],"type":"Point"}
}