{
  "type": "Feature",
  "properties": {
    "date:inception_lower": "1993-08-01",
    "date:inception_upper": "1993-08-01",
    "iso:country": "GB",
    "wof:name": "OX11 9PL",
    "wof:placetype": "postalcode"
  },
  "geometry": {"coordinates":[-1.229365,51.571491],"type":"Point"}
}
