{
  "type": "Feature",
  "properties": {
    "iso:country": "GB",
    "wof:name": "TS27 4SJ",
    "wof:placetype": "postalcode"
  },
  "geometry": {"coordinates":[-1.341411,54.736004],"type":"Point"}
}
