{
  "type": "Feature",
  "properties": {
    "iso:country": "GB",
    "wof:name": "TS17 0RL",
    "wof:placetype": "postalcode"
  },
  "geometry": {"coordinates":[-1.303834,54.524188],"type":"Point"}
}
