{
  "type": "Feature",
  "properties": {
    "iso:country":"GB",
    "wof:name":"TS17 0RL",
    "wof:placetype":"postalcode"
},
  "geometry": {"coordinates":[-1.30383386830226,54.52418836193871],"type":"Point"}
}