{
  "type": "Feature",
  "properties": {
    "date:inception_lower":"1983-07-01",
    "date:inception_upper":"1983-07-31",
    "iso:country":"GB",
    "wof:name":"TS17 0RL",
    "wof:placetype":"postalcode"
},
  "geometry": {"coordinates":[-1.303834,54.524188],"type":"Point"}
}