{
  "type": "Feature",
  "properties": {
    "iso:country": "GB",
    "wof:name": "GL51 3LE",
    "wof:placetype": "postalcode"
  },
  "geometry": {"coordinates":[-2.118829,51.885222],"type":"Point"}
}
