{
  "type": "Feature",
  "properties": {
    "iso:country":"GB",
    "wof:name":"SY10 0HJ",
    "wof:placetype":"postalcode"
},
  "geometry": {"coordinates":[-3.41953232983577,52.81822120628487],"type":"Point"}
}