{
  "type": "Feature",
  "properties": {
    "iso:country": "GB",
    "wof:name": "SY10 0HJ",
    "wof:placetype": "postalcode"
  },
  "geometry": {"coordinates":[-3.419532,52.818221],"type":"Point"}
}
