{
  "type": "Feature",
  "properties": {
    "iso:country":"GB",
    "wof:name":"WA4 5EW",
    "wof:placetype":"postalcode"
},
  "geometry": {"coordinates":[-2.57633546160706,53.35350612574508],"type":"Point"}
}