{
  "type": "Feature",
  "properties": {
    "iso:country": "GB",
    "wof:name": "CM5 9FH",
    "wof:placetype": "postalcode"
  },
  "geometry": {"coordinates":[0.242746,51.708512],"type":"Point"}
}
