{
  "type": "Feature",
  "properties": {
    "iso:country":"GB",
    "wof:name":"CM5 9FH",
    "wof:placetype":"postalcode"
},
  "geometry": {"coordinates":[0.24265895503178,51.70846406026246],"type":"Point"}
}