{
  "type": "Feature",
  "properties": {
    "date:inception_lower": "2020-08-01",
    "date:inception_upper": "2020-08-01",
    "iso:country": "GB",
    "wof:name": "HU15 2GW",
    "wof:placetype": "postalcode"
  },
  "geometry": {"coordinates":[-0.736029,53.748849],"type":"Point"}
}
