{
  "type": "Feature",
  "properties": {
    "iso:country":"GB",
    "wof:name":"EH6 7JB",
    "wof:placetype":"postalcode"
},
  "geometry": {"coordinates":[-3.16139039953596,55.97444589161328],"type":"Point"}
}