{
  "type": "Feature",
  "properties": {
    "iso:country": "GB",
    "wof:name": "EH6 7JB",
    "wof:placetype": "postalcode"
  },
  "geometry": {"coordinates":[-3.16139,55.974446],"type":"Point"}
}
