{
  "type": "Feature",
  "properties": {
    "date:inception_lower": "1980-01-01",
    "date:inception_upper": "1980-01-01",
    "iso:country": "GB",
    "wof:name": "EH46 7DG",
    "wof:placetype": "postalcode"
  },
  "geometry": {"coordinates":[-3.382073,55.694899],"type":"Point"}
}
