{
  "type": "Feature",
  "properties": {
    "iso:country":"GB",
    "wof:name":"CT15 7JG",
    "wof:placetype":"postalcode"
},
  "geometry": {"coordinates":[1.23705700335608,51.20744022828887],"type":"Point"}
}