{
  "type": "Feature",
  "properties": {
    "iso:country":"GB",
    "wof:name":"W1U 6AT",
    "wof:placetype":"postalcode"
},
  "geometry": {"coordinates":[-0.15681884313854,51.5195310424867],"type":"Point"}
}