{
  "type": "Feature",
  "properties": {
    "iso:country":"GB",
    "wof:name":"TA1 2LG",
    "wof:placetype":"postalcode"
},
  "geometry": {"coordinates":[-3.0785422493938,51.01151262113523],"type":"Point"}
}