{
  "type": "Feature",
  "properties": {
    "iso:country":"GB",
    "wof:name":"CF23 8PP",
    "wof:placetype":"postalcode"
},
  "geometry": {"coordinates":[-3.13075108749522,51.5326201621418],"type":"Point"}
}