{
  "type": "Feature",
  "properties": {
    "iso:country": "GB",
    "wof:name": "OX29 8PR",
    "wof:placetype": "postalcode"
  },
  "geometry": {"coordinates":[-1.429727,51.848927],"type":"Point"}
}
