{
  "type": "Feature",
  "properties": {
    "iso:country":"GB",
    "wof:name":"OX29 8PR",
    "wof:placetype":"postalcode"
},
  "geometry": {"coordinates":[-1.42972663334872,51.84892685207085],"type":"Point"}
}