{
  "type": "Feature",
  "properties": {
    "iso:country":"GB",
    "wof:name":"HU17 8GD",
    "wof:placetype":"postalcode"
},
  "geometry": {"coordinates":[-0.43942702292229,53.84224426796124],"type":"Point"}
}