{
  "type": "Feature",
  "properties": {
    "iso:country":"GB",
    "wof:name":"RH10 7XY",
    "wof:placetype":"postalcode"
},
  "geometry": {"coordinates":[-0.14256981057709,51.12467659160024],"type":"Point"}
}