{
  "type": "Feature",
  "properties": {
    "date:inception_lower": "1997-12-01",
    "date:inception_upper": "1997-12-01",
    "iso:country": "GB",
    "wof:name": "RH10 7XY",
    "wof:placetype": "postalcode"
  },
  "geometry": {"coordinates":[-0.14257,51.124677],"type":"Point"}
}
