{
  "type": "Feature",
  "properties": {
    "iso:country": "GB",
    "wof:name": "RH10 7XY",
    "wof:placetype": "postalcode"
  },
  "geometry": {"coordinates":[-0.14257,51.124677],"type":"Point"}
}
