{
  "type": "Feature",
  "properties": {
    "iso:country": "GB",
    "wof:name": "M20 2LG",
    "wof:placetype": "postalcode"
  },
  "geometry": {"coordinates":[-2.245848,53.426383],"type":"Point"}
}
