{
  "type": "Feature",
  "properties": {
    "iso:country":"GB",
    "wof:name":"S13 9ZH",
    "wof:placetype":"postalcode"
},
  "geometry": {"coordinates":[-1.33766360548656,53.37109408656102],"type":"Point"}
}