{
  "type": "Feature",
  "properties": {
    "date:inception_lower": "1997-12-01",
    "date:inception_upper": "1997-12-01",
    "iso:country": "GB",
    "wof:name": "S13 9ZH",
    "wof:placetype": "postalcode"
  },
  "geometry": {"coordinates":[-1.337664,53.371095],"type":"Point"}
}
