{
  "type": "Feature",
  "properties": {
    "iso:country":"GB",
    "wof:name":"GU25 4PA",
    "wof:placetype":"postalcode"
},
  "geometry": {"coordinates":[-0.59117987771382,51.40431085213059],"type":"Point"}
}