{
  "type": "Feature",
  "properties": {
    "iso:country": "GB",
    "wof:name": "B74 2EJ",
    "wof:placetype": "postalcode"
  },
  "geometry": {"coordinates":[-1.894397,52.573185],"type":"Point"}
}
