{
  "type": "Feature",
  "properties": {
    "iso:country": "GB",
    "wof:name": "PE13 1PX",
    "wof:placetype": "postalcode"
  },
  "geometry": {"coordinates":[0.150115,52.676372],"type":"Point"}
}
