{
  "type": "Feature",
  "properties": {
    "iso:country":"GB",
    "wof:name":"PE13 1PX",
    "wof:placetype":"postalcode"
},
  "geometry": {"coordinates":[0.15011456835729,52.67637229345856],"type":"Point"}
}