{
  "type": "Feature",
  "properties": {
    "iso:country": "GB",
    "wof:name": "SA72 6NZ",
    "wof:placetype": "postalcode"
  },
  "geometry": {"coordinates":[-4.948719,51.686871],"type":"Point"}
}
