{
  "type": "Feature",
  "properties": {
    "iso:country":"GB",
    "wof:name":"SA72 6NZ",
    "wof:placetype":"postalcode"
},
  "geometry": {"coordinates":[-4.94871855454359,51.68687137995592],"type":"Point"}
}