{
  "type": "Feature",
  "properties": {
    "date:inception_lower": "1990-08-01",
    "date:inception_upper": "1990-08-01",
    "iso:country": "GB",
    "wof:name": "AB52 6LL",
    "wof:placetype": "postalcode"
  },
  "geometry": {"coordinates":[-2.599235,57.347546],"type":"Point"}
}
