{
  "type": "Feature",
  "properties": {
    "iso:country":"GB",
    "wof:name":"B92 8DD",
    "wof:placetype":"postalcode"
},
  "geometry": {"coordinates":[-1.79720960803283,52.43735609120168],"type":"Point"}
}