{
  "type": "Feature",
  "properties": {
    "iso:country": "GB",
    "wof:name": "B92 8DD",
    "wof:placetype": "postalcode"
  },
  "geometry": {"coordinates":[-1.79721,52.437356],"type":"Point"}
}
