{
  "type": "Feature",
  "properties": {
    "iso:country":"GB",
    "wof:name":"NN17 1NH",
    "wof:placetype":"postalcode"
},
  "geometry": {"coordinates":[-0.70260053562318,52.48806300073191],"type":"Point"}
}