{
  "type": "Feature",
  "properties": {
    "iso:country":"GB",
    "wof:name":"CW12 3JB",
    "wof:placetype":"postalcode"
},
  "geometry": {"coordinates":[-2.18681569600845,53.15289097100646],"type":"Point"}
}