{
  "type": "Feature",
  "properties": {
    "iso:country":"GB",
    "wof:name":"GL52 8JR",
    "wof:placetype":"postalcode"
},
  "geometry": {"coordinates":[-2.05178863658201,51.94461028874913],"type":"Point"}
}