{
  "type": "Feature",
  "properties": {
    "date:inception_lower": "2000-10-01",
    "date:inception_upper": "2000-10-01",
    "iso:country": "GB",
    "wof:name": "GL52 8JR",
    "wof:placetype": "postalcode"
  },
  "geometry": {"coordinates":[-2.051789,51.94461],"type":"Point"}
}
