{
  "type": "Feature",
  "properties": {
    "iso:country":"GB",
    "wof:name":"LS27 9AL",
    "wof:placetype":"postalcode"
},
  "geometry": {"coordinates":[-1.59778670484143,53.7418646979754],"type":"Point"}
}