{
  "type": "Feature",
  "properties": {
    "date:inception_lower": "1980-01-01",
    "date:inception_upper": "1980-01-01",
    "iso:country": "GB",
    "wof:name": "NG5 8QQ",
    "wof:placetype": "postalcode"
  },
  "geometry": {"coordinates":[-1.106742,53.008827],"type":"Point"}
}
