{
  "type": "Feature",
  "properties": {
    "date:inception_lower": "2022-11-01",
    "date:inception_upper": "2022-11-01",
    "iso:country": "GB",
    "wof:name": "NP20 2SF",
    "wof:placetype": "postalcode"
  },
  "geometry": {"coordinates":[-2.998407,51.57532],"type":"Point"}
}
