{
  "type": "Feature",
  "properties": {
    "iso:country":"GB",
    "wof:name":"L10 8JW",
    "wof:placetype":"postalcode"
},
  "geometry": {"coordinates":[-2.92924197016236,53.48038657621699],"type":"Point"}
}