{
  "type": "Feature",
  "properties": {
    "iso:country":"GB",
    "wof:name":"B11 4LQ",
    "wof:placetype":"postalcode"
},
  "geometry": {"coordinates":[-1.87181550493781,52.45352547586992],"type":"Point"}
}