{
  "type": "Feature",
  "properties": {
    "iso:country":"GB",
    "wof:name":"CM7 1EF",
    "wof:placetype":"postalcode"
},
  "geometry": {"coordinates":[0.55876667862662,51.87261088909815],"type":"Point"}
}