{
  "type": "Feature",
  "properties": {
    "date:inception_lower":"1984-10-01",
    "date:inception_upper":"1984-10-31",
    "iso:country":"GB",
    "wof:name":"SW9 6XD",
    "wof:placetype":"postalcode"
},
  "geometry": {"coordinates":[-0.103676,51.477831],"type":"Point"}
}