{
  "type": "Feature",
  "properties": {
    "iso:country": "GB",
    "wof:name": "BA13 4SS",
    "wof:placetype": "postalcode"
  },
  "geometry": {"coordinates":[-2.125017,51.270693],"type":"Point"}
}
