{
  "type": "Feature",
  "properties": {
    "iso:country": "GB",
    "wof:name": "TW17 8RX",
    "wof:placetype": "postalcode"
  },
  "geometry": {"coordinates":[-0.43235,51.400684],"type":"Point"}
}
