{
  "type": "Feature",
  "properties": {
    "iso:country":"GB",
    "wof:name":"S66 8EL",
    "wof:placetype":"postalcode"
},
  "geometry": {"coordinates":[-1.22836274756857,53.42450543217706],"type":"Point"}
}