{
  "type": "Feature",
  "properties": {
    "iso:country":"GB",
    "wof:name":"WN7 2DR",
    "wof:placetype":"postalcode"
},
  "geometry": {"coordinates":[-2.5044868835037,53.49276874039715],"type":"Point"}
}