{
  "type": "Feature",
  "properties": {
    "iso:country":"GB",
    "wof:name":"LS12 4DG",
    "wof:placetype":"postalcode"
},
  "geometry": {"coordinates":[-1.58277126954252,53.78834467235333],"type":"Point"}
}