{
  "type": "Feature",
  "properties": {
    "iso:country":"GB",
    "wof:name":"TN11 8RA",
    "wof:placetype":"postalcode"
},
  "geometry": {"coordinates":[0.21558506852165,51.19438742385375],"type":"Point"}
}