{
  "type": "Feature",
  "properties": {
    "date:inception_lower":"1980-01-01",
    "date:inception_upper":"1980-01-31",
    "iso:country":"GB",
    "wof:name":"TN11 8RA",
    "wof:placetype":"postalcode"
},
  "geometry": {"coordinates":[0.215585,51.194387],"type":"Point"}
}