{
  "type": "Feature",
  "properties": {
    "date:inception_lower": "2023-09-01",
    "date:inception_upper": "2023-09-01",
    "iso:country": "GB",
    "wof:name": "NN4 6GD",
    "wof:placetype": "postalcode"
  },
  "geometry": {"coordinates":[-0.86959,52.207998],"type":"Point"}
}
