{
  "type": "Feature",
  "properties": {
    "iso:country":"GB",
    "wof:name":"HP22 6DS",
    "wof:placetype":"postalcode"
},
  "geometry": {"coordinates":[-0.74814735743072,51.76569318911489],"type":"Point"}
}