{
  "type": "Feature",
  "properties": {
    "date:inception_lower": "2017-09-01",
    "date:inception_upper": "2017-09-01",
    "iso:country": "GB",
    "wof:name": "ME1 3FS",
    "wof:placetype": "postalcode"
  },
  "geometry": {"coordinates":[0.459437,51.339312],"type":"Point"}
}
