{
  "type": "Feature",
  "properties": {
    "date:inception_lower":"1980-01-01",
    "date:inception_upper":"1980-01-31",
    "iso:country":"GB",
    "wof:name":"NR25 7TB",
    "wof:placetype":"postalcode"
},
  "geometry": {"coordinates":[1.140147,52.939813],"type":"Point"}
}