{
  "type": "Feature",
  "properties": {
    "iso:country": "GB",
    "wof:name": "SR8 4LN",
    "wof:placetype": "postalcode"
  },
  "geometry": {"coordinates":[-1.314807,54.764534],"type":"Point"}
}
