{
  "type": "Feature",
  "properties": {
    "iso:country":"GB",
    "wof:name":"SR8 4LN",
    "wof:placetype":"postalcode"
},
  "geometry": {"coordinates":[-1.31480735319624,54.76453363627569],"type":"Point"}
}