{
  "type": "Feature",
  "properties": {
    "iso:country":"GB",
    "wof:name":"B33 0HW",
    "wof:placetype":"postalcode"
},
  "geometry": {"coordinates":[-1.76510577286304,52.47740120106872],"type":"Point"}
}