{
  "type": "Feature",
  "properties": {
    "iso:country":"GB",
    "wof:name":"UB5 5JE",
    "wof:placetype":"postalcode"
},
  "geometry": {"coordinates":[-0.39058591158556,51.5378084466433],"type":"Point"}
}