{
  "type": "Feature",
  "properties": {
    "iso:country":"GB",
    "wof:name":"BN9 9TP",
    "wof:placetype":"postalcode"
},
  "geometry": {"coordinates":[0.03687195482556,50.78973913535916],"type":"Point"}
}