{
  "type": "Feature",
  "properties": {
    "iso:country":"GB",
    "wof:name":"WS11 5TZ",
    "wof:placetype":"postalcode"
},
  "geometry": {"coordinates":[-2.0135441498518,52.70712430484838],"type":"Point"}
}