{
  "type": "Feature",
  "properties": {
    "iso:country":"GB",
    "wof:name":"PE28 4RA",
    "wof:placetype":"postalcode"
},
  "geometry": {"coordinates":[-0.22946627827248,52.3244843360655],"type":"Point"}
}