{
  "type": "Feature",
  "properties": {
    "iso:country":"GB",
    "wof:name":"BS31 1HH",
    "wof:placetype":"postalcode"
},
  "geometry": {"coordinates":[-2.49454045412689,51.41306141848344],"type":"Point"}
}