{
  "type": "Feature",
  "properties": {
    "iso:country": "GB",
    "wof:name": "BS31 1HH",
    "wof:placetype": "postalcode"
  },
  "geometry": {"coordinates":[-2.49454,51.413061],"type":"Point"}
}
