{
  "type": "Feature",
  "properties": {
    "iso:country":"GB",
    "wof:name":"BD6 2RJ",
    "wof:placetype":"postalcode"
},
  "geometry": {"coordinates":[-1.79621263581486,53.75631532564238],"type":"Point"}
}