{
  "type": "Feature",
  "properties": {
    "date:inception_lower": "1993-01-01",
    "date:inception_upper": "1993-01-01",
    "iso:country": "GB",
    "wof:name": "EC2M 3YD",
    "wof:placetype": "postalcode"
  },
  "geometry": {"coordinates":[-0.080182,51.518437],"type":"Point"}
}
