{
  "type": "Feature",
  "properties": {
    "iso:country": "GB",
    "wof:name": "BN27 4RZ",
    "wof:placetype": "postalcode"
  },
  "geometry": {"coordinates":[0.346898,50.883161],"type":"Point"}
}
