{
  "type": "Feature",
  "properties": {
    "date:inception_lower":"1980-01-01",
    "date:inception_upper":"1980-01-31",
    "iso:country":"GB",
    "wof:name":"BN27 4RZ",
    "wof:placetype":"postalcode"
},
  "geometry": {"coordinates":[0.346898,50.883161],"type":"Point"}
}