{
  "type": "Feature",
  "properties": {
    "date:inception_lower": "2005-03-01",
    "date:inception_upper": "2005-03-01",
    "iso:country": "GB",
    "wof:name": "KA9 2SA",
    "wof:placetype": "postalcode"
  },
  "geometry": {"coordinates":[-4.611987,55.519831],"type":"Point"}
}
