{
  "type": "Feature",
  "properties": {
    "date:inception_lower": "1980-01-01",
    "date:inception_upper": "1980-01-01",
    "iso:country": "GB",
    "wof:name": "NE40 4EX",
    "wof:placetype": "postalcode"
  },
  "geometry": {"coordinates":[-1.797691,54.962184],"type":"Point"}
}
