{
  "type": "Feature",
  "properties": {
    "iso:country": "GB",
    "wof:name": "AB12 3ZR",
    "wof:placetype": "postalcode"
  },
  "geometry": {"coordinates":[-2.090557,57.127712],"type":"Point"}
}
