{
  "type": "Feature",
  "properties": {
    "iso:country":"GB",
    "wof:name":"WS7 0EB",
    "wof:placetype":"postalcode"
},
  "geometry": {"coordinates":[-1.91579148797845,52.67408544187093],"type":"Point"}
}