{
  "type": "Feature",
  "properties": {
    "iso:country": "GB",
    "wof:name": "GL51 3JZ",
    "wof:placetype": "postalcode"
  },
  "geometry": {"coordinates":[-2.117536,51.885304],"type":"Point"}
}
