{
  "type": "Feature",
  "properties": {
    "iso:country":"GB",
    "wof:name":"GL51 3JZ",
    "wof:placetype":"postalcode"
},
  "geometry": {"coordinates":[-2.11753647717223,51.88530431045133],"type":"Point"}
}