{
  "type": "Feature",
  "properties": {
    "iso:country":"GB",
    "wof:name":"IV36 1LA",
    "wof:placetype":"postalcode"
},
  "geometry": {"coordinates":[-3.61424769746009,57.60862392096657],"type":"Point"}
}