{
  "type": "Feature",
  "properties": {
    "iso:country": "GB",
    "wof:name": "RH10 3HT",
    "wof:placetype": "postalcode"
  },
  "geometry": {"coordinates":[-0.098154,51.145555],"type":"Point"}
}
