{
  "type": "Feature",
  "properties": {
    "iso:country":"GB",
    "wof:name":"RH10 3HT",
    "wof:placetype":"postalcode"
},
  "geometry": {"coordinates":[-0.0981540178844,51.14555496352487],"type":"Point"}
}