{
  "type": "Feature",
  "properties": {
    "iso:country":"GB",
    "wof:name":"BL3 4HJ",
    "wof:placetype":"postalcode"
},
  "geometry": {"coordinates":[-2.45890240395543,53.56626229828641],"type":"Point"}
}