{
  "type": "Feature",
  "properties": {
    "iso:country":"GB",
    "wof:name":"BR6 6DN",
    "wof:placetype":"postalcode"
},
  "geometry": {"coordinates":[0.09597681034518,51.35418705786117],"type":"Point"}
}