{
  "type": "Feature",
  "properties": {
    "iso:country":"GB",
    "wof:name":"EX33 2PH",
    "wof:placetype":"postalcode"
},
  "geometry": {"coordinates":[-4.15831406773956,51.10695373385018],"type":"Point"}
}