{
  "type": "Feature",
  "properties": {
    "date:inception_lower": "2005-04-01",
    "date:inception_upper": "2005-04-01",
    "iso:country": "GB",
    "wof:name": "EX33 2PH",
    "wof:placetype": "postalcode"
  },
  "geometry": {"coordinates":[-4.158314,51.106954],"type":"Point"}
}
