{
  "type": "Feature",
  "properties": {
    "iso:country": "GB",
    "wof:name": "EX33 2PH",
    "wof:placetype": "postalcode"
  },
  "geometry": {"coordinates":[-4.158314,51.106954],"type":"Point"}
}
