{
  "type": "Feature",
  "properties": {
    "iso:country":"GB",
    "wof:name":"BN42 4LL",
    "wof:placetype":"postalcode"
},
  "geometry": {"coordinates":[-0.22431774979187,50.83960452651586],"type":"Point"}
}