{
  "type": "Feature",
  "properties": {
    "iso:country":"GB",
    "wof:name":"G83 8DB",
    "wof:placetype":"postalcode"
},
  "geometry": {"coordinates":[-4.56629723308797,56.00498106481137],"type":"Point"}
}