{
  "type": "Feature",
  "properties": {
    "iso:country": "GB",
    "wof:name": "G83 8DB",
    "wof:placetype": "postalcode"
  },
  "geometry": {"coordinates":[-4.566297,56.004981],"type":"Point"}
}
