{
  "type": "Feature",
  "properties": {
    "iso:country": "GB",
    "wof:name": "GL3 4NS",
    "wof:placetype": "postalcode"
  },
  "geometry": {"coordinates":[-2.158806,51.841956],"type":"Point"}
}
