{
  "type": "Feature",
  "properties": {
    "iso:country":"GB",
    "wof:name":"GL3 4NS",
    "wof:placetype":"postalcode"
},
  "geometry": {"coordinates":[-2.15880570797695,51.84195553212433],"type":"Point"}
}