{
  "type": "Feature",
  "properties": {
    "date:inception_lower": "1998-12-01",
    "date:inception_upper": "1998-12-01",
    "iso:country": "GB",
    "wof:name": "GL3 4NS",
    "wof:placetype": "postalcode"
  },
  "geometry": {"coordinates":[-2.158806,51.841956],"type":"Point"}
}
