{
  "type": "Feature",
  "properties": {
    "iso:country":"GB",
    "wof:name":"SG1 2RS",
    "wof:placetype":"postalcode"
},
  "geometry": {"coordinates":[-0.21607000738669,51.91069701623992],"type":"Point"}
}