{
  "type": "Feature",
  "properties": {
    "iso:country":"GB",
    "wof:name":"BS9 1DH",
    "wof:placetype":"postalcode"
},
  "geometry": {"coordinates":[-2.64146941214424,51.48319444772633],"type":"Point"}
}