{
  "type": "Feature",
  "properties": {
    "iso:country": "GB",
    "wof:name": "SL4 1SQ",
    "wof:placetype": "postalcode"
  },
  "geometry": {"coordinates":[-0.618723,51.484552],"type":"Point"}
}
