{
  "type": "Feature",
  "properties": {
    "iso:country":"GB",
    "wof:name":"EH3 9JT",
    "wof:placetype":"postalcode"
},
  "geometry": {"coordinates":[-3.20202685594732,55.94290360258155],"type":"Point"}
}