{
  "type": "Feature",
  "properties": {
    "iso:country": "GB",
    "wof:name": "SY23 5NQ",
    "wof:placetype": "postalcode"
  },
  "geometry": {"coordinates":[-4.136141,52.238675],"type":"Point"}
}
