{
  "type": "Feature",
  "properties": {
    "date:inception_lower": "2015-02-01",
    "date:inception_upper": "2015-02-01",
    "iso:country": "GB",
    "wof:name": "SN8 9EF",
    "wof:placetype": "postalcode"
  },
  "geometry": {"coordinates":[-1.733617,51.419648],"type":"Point"}
}
