{
  "type": "Feature",
  "properties": {
    "iso:country":"GB",
    "wof:name":"SW9 6BT",
    "wof:placetype":"postalcode"
},
  "geometry": {"coordinates":[-0.11198929373445,51.47948456151197],"type":"Point"}
}