{
  "type": "Feature",
  "properties": {
    "iso:country":"GB",
    "wof:name":"G84 8SA",
    "wof:placetype":"postalcode"
},
  "geometry": {"coordinates":[-4.7813856851714,56.02010719643718],"type":"Point"}
}