{
  "type": "Feature",
  "properties": {
    "iso:country":"GB",
    "wof:name":"GL7 2JZ",
    "wof:placetype":"postalcode"
},
  "geometry": {"coordinates":[-1.97761212075687,51.72813572923159],"type":"Point"}
}