{
  "type": "Feature",
  "properties": {
    "date:inception_lower": "2006-11-01",
    "date:inception_upper": "2006-11-01",
    "iso:country": "GB",
    "wof:name": "GL7 2JZ",
    "wof:placetype": "postalcode"
  },
  "geometry": {"coordinates":[-1.977618,51.728419],"type":"Point"}
}
