{
  "type": "Feature",
  "properties": {
    "iso:country": "GB",
    "wof:name": "TW7 5LX",
    "wof:placetype": "postalcode"
  },
  "geometry": {"coordinates":[-0.342089,51.483944],"type":"Point"}
}
