{
  "type": "Feature",
  "properties": {
    "date:inception_lower":"1980-01-01",
    "date:inception_upper":"1980-01-31",
    "iso:country":"GB",
    "wof:name":"TW7 5LX",
    "wof:placetype":"postalcode"
},
  "geometry": {"coordinates":[-0.342089,51.483944],"type":"Point"}
}