{
  "type": "Feature",
  "properties": {
    "iso:country":"GB",
    "wof:name":"TW7 5LX",
    "wof:placetype":"postalcode"
},
  "geometry": {"coordinates":[-0.34208889814029,51.48394374579447],"type":"Point"}
}