{
  "type": "Feature",
  "properties": {
    "date:inception_lower":"1986-07-01",
    "date:inception_upper":"1986-07-31",
    "iso:country":"GB",
    "wof:name":"SN5 7XW",
    "wof:placetype":"postalcode"
},
  "geometry": {"coordinates":[-1.812659,51.559232],"type":"Point"}
}