{
  "type": "Feature",
  "properties": {
    "date:inception_lower": "2020-02-01",
    "date:inception_upper": "2020-02-01",
    "iso:country": "GB",
    "wof:name": "WF10 1FN",
    "wof:placetype": "postalcode"
  },
  "geometry": {"coordinates":[-1.359165,53.728585],"type":"Point"}
}
