{
  "type": "Feature",
  "properties": {
    "iso:country":"GB",
    "wof:name":"DH1 4AX",
    "wof:placetype":"postalcode"
},
  "geometry": {"coordinates":[-1.58954209551781,54.77621610519599],"type":"Point"}
}