{
  "type": "Feature",
  "properties": {
    "iso:country":"GB",
    "wof:name":"TN18 4PA",
    "wof:placetype":"postalcode"
},
  "geometry": {"coordinates":[0.50601146079923,51.04118752281555],"type":"Point"}
}