{
  "type": "Feature",
  "properties": {
    "iso:country":"GB",
    "wof:name":"BS9 2RX",
    "wof:placetype":"postalcode"
},
  "geometry": {"coordinates":[-2.64224203637223,51.4982061971647],"type":"Point"}
}