{
  "type": "Feature",
  "properties": {
    "iso:country":"GB",
    "wof:name":"WV4 6RH",
    "wof:placetype":"postalcode"
},
  "geometry": {"coordinates":[-2.11379130974813,52.55517076153757],"type":"Point"}
}