{
  "type": "Feature",
  "properties": {
    "date:inception_lower": "1992-08-01",
    "date:inception_upper": "1992-08-01",
    "iso:country": "GB",
    "wof:name": "NP44 3PJ",
    "wof:placetype": "postalcode"
  },
  "geometry": {"coordinates":[-3.020328,51.651019],"type":"Point"}
}
