{
  "type": "Feature",
  "properties": {
    "date:inception_lower":"2013-03-01",
    "date:inception_upper":"2013-03-31",
    "iso:country":"GB",
    "wof:name":"DN21 5ST",
    "wof:placetype":"postalcode"
},
  "geometry": {"coordinates":[-0.593296,53.428316],"type":"Point"}
}