{
  "type": "Feature",
  "properties": {
    "iso:country":"GB",
    "wof:name":"DN21 5ST",
    "wof:placetype":"postalcode"
},
  "geometry": {"coordinates":[-0.59329592341883,53.42831560458013],"type":"Point"}
}