{
  "type": "Feature",
  "properties": {
    "iso:country": "GB",
    "wof:name": "DN21 5ST",
    "wof:placetype": "postalcode"
  },
  "geometry": {"coordinates":[-0.593296,53.428316],"type":"Point"}
}
