{
  "type": "Feature",
  "properties": {
    "date:inception_lower": "1980-01-01",
    "date:inception_upper": "1980-01-01",
    "iso:country": "GB",
    "wof:name": "M32 0TX",
    "wof:placetype": "postalcode"
  },
  "geometry": {"coordinates":[-2.293382,53.451713],"type":"Point"}
}
