{
  "type": "Feature",
  "properties": {
    "iso:country":"GB",
    "wof:name":"L15 2HA",
    "wof:placetype":"postalcode"
},
  "geometry": {"coordinates":[-2.9352296485058,53.39564694616283],"type":"Point"}
}