{
  "type": "Feature",
  "properties": {
    "date:inception_lower": "1980-01-01",
    "date:inception_upper": "1980-01-01",
    "iso:country": "GB",
    "wof:name": "L15 2HA",
    "wof:placetype": "postalcode"
  },
  "geometry": {"coordinates":[-2.93523,53.395647],"type":"Point"}
}
