{
  "type": "Feature",
  "properties": {
    "iso:country": "GB",
    "wof:name": "B33 8TE",
    "wof:placetype": "postalcode"
  },
  "geometry": {"coordinates":[-1.818158,52.476344],"type":"Point"}
}
