{
  "type": "Feature",
  "properties": {
    "iso:country":"GB",
    "wof:name":"B33 8TE",
    "wof:placetype":"postalcode"
},
  "geometry": {"coordinates":[-1.81815801761343,52.47634379920147],"type":"Point"}
}