{
  "type": "Feature",
  "properties": {
    "iso:country":"GB",
    "wof:name":"SO18 1HP",
    "wof:placetype":"postalcode"
},
  "geometry": {"coordinates":[-1.37313865580478,50.9175779732645],"type":"Point"}
}