{
  "type": "Feature",
  "properties": {
    "iso:country": "GB",
    "wof:name": "HD8 9SY",
    "wof:placetype": "postalcode"
  },
  "geometry": {"coordinates":[-1.651903,53.614564],"type":"Point"}
}
