{
  "type": "Feature",
  "properties": {
    "iso:country":"GB",
    "wof:name":"HD8 9SY",
    "wof:placetype":"postalcode"
},
  "geometry": {"coordinates":[-1.65190279295351,53.61456352290642],"type":"Point"}
}