{
  "type": "Feature",
  "properties": {
    "date:inception_lower": "2023-07-01",
    "date:inception_upper": "2023-07-01",
    "iso:country": "GB",
    "wof:name": "LE67 1UG",
    "wof:placetype": "postalcode"
  },
  "geometry": {"coordinates":[-1.399935,52.685651],"type":"Point"}
}
