{
  "type": "Feature",
  "properties": {
    "iso:country":"GB",
    "wof:name":"DN21 4JR",
    "wof:placetype":"postalcode"
},
  "geometry": {"coordinates":[-0.59637015562773,53.48757295793022],"type":"Point"}
}