{
  "type": "Feature",
  "properties": {
    "iso:country": "GB",
    "wof:name": "DN21 4JR",
    "wof:placetype": "postalcode"
  },
  "geometry": {"coordinates":[-0.59637,53.487573],"type":"Point"}
}
