{
  "type": "Feature",
  "properties": {
    "iso:country": "GB",
    "wof:name": "CH1 6RR",
    "wof:placetype": "postalcode"
  },
  "geometry": {"coordinates":[-2.933192,53.225366],"type":"Point"}
}
