{
  "type": "Feature",
  "properties": {
    "date:inception_lower": "2001-12-01",
    "date:inception_upper": "2001-12-01",
    "iso:country": "GB",
    "wof:name": "CH1 6RR",
    "wof:placetype": "postalcode"
  },
  "geometry": {"coordinates":[-2.933192,53.225366],"type":"Point"}
}
