{
  "type": "Feature",
  "properties": {
    "iso:country": "GB",
    "wof:name": "NE48 1PP",
    "wof:placetype": "postalcode"
  },
  "geometry": {"coordinates":[-2.32289,55.177382],"type":"Point"}
}
