{
  "type": "Feature",
  "properties": {
    "iso:country":"GB",
    "wof:name":"LL18 2PA",
    "wof:placetype":"postalcode"
},
  "geometry": {"coordinates":[-3.47154714561724,53.30726690486317],"type":"Point"}
}