{
  "type": "Feature",
  "properties": {
    "iso:country": "GB",
    "wof:name": "LL18 2PA",
    "wof:placetype": "postalcode"
  },
  "geometry": {"coordinates":[-3.471547,53.307267],"type":"Point"}
}
