{
  "type": "Feature",
  "properties": {
    "iso:country":"GB",
    "wof:name":"NN14 2RS",
    "wof:placetype":"postalcode"
},
  "geometry": {"coordinates":[-0.81839283728094,52.44340651582231],"type":"Point"}
}