{
  "type": "Feature",
  "properties": {
    "iso:country":"GB",
    "wof:name":"NG6 8AQ",
    "wof:placetype":"postalcode"
},
  "geometry": {"coordinates":[-1.19303749677188,53.00711547001757],"type":"Point"}
}