{
  "type": "Feature",
  "properties": {
    "iso:country":"GB",
    "wof:name":"DA14 6DY",
    "wof:placetype":"postalcode"
},
  "geometry": {"coordinates":[0.10327440808354,51.42567624476881],"type":"Point"}
}