{
  "type": "Feature",
  "properties": {
    "date:inception_lower": "1980-01-01",
    "date:inception_upper": "1980-01-01",
    "iso:country": "GB",
    "wof:name": "LA5 9AR",
    "wof:placetype": "postalcode"
  },
  "geometry": {"coordinates":[-2.764339,54.120966],"type":"Point"}
}
