{
  "type": "Feature",
  "properties": {
    "iso:country":"GB",
    "wof:name":"LA5 9AR",
    "wof:placetype":"postalcode"
},
  "geometry": {"coordinates":[-2.76433859609996,54.12096634497022],"type":"Point"}
}