{
  "type": "Feature",
  "properties": {
    "iso:country":"GB",
    "wof:name":"YO1 9UJ",
    "wof:placetype":"postalcode"
},
  "geometry": {"coordinates":[-1.07192652919283,53.95774810689171],"type":"Point"}
}