{
  "type": "Feature",
  "properties": {
    "iso:country":"GB",
    "wof:name":"NR6 6TB",
    "wof:placetype":"postalcode"
},
  "geometry": {"coordinates":[1.27830978082135,52.66053769660377],"type":"Point"}
}