{
  "type": "Feature",
  "properties": {
    "iso:country":"GB",
    "wof:name":"WA4 2JH",
    "wof:placetype":"postalcode"
},
  "geometry": {"coordinates":[-2.52685684020374,53.38102464452862],"type":"Point"}
}