{
  "type": "Feature",
  "properties": {
    "iso:country":"GB",
    "wof:name":"PR9 9SA",
    "wof:placetype":"postalcode"
},
  "geometry": {"coordinates":[-2.9705830522347,53.66200668583043],"type":"Point"}
}