{
  "type": "Feature",
  "properties": {
    "iso:country":"GB",
    "wof:name":"LA5 8DQ",
    "wof:placetype":"postalcode"
},
  "geometry": {"coordinates":[-2.78766441923225,54.10932059365951],"type":"Point"}
}