{
  "type": "Feature",
  "properties": {
    "iso:country":"GB",
    "wof:name":"OL14 8HQ",
    "wof:placetype":"postalcode"
},
  "geometry": {"coordinates":[-2.1208785134665,53.72690115321974],"type":"Point"}
}