{
  "type": "Feature",
  "properties": {
    "date:inception_lower": "2024-01-01",
    "date:inception_upper": "2024-01-01",
    "iso:country": "GB",
    "wof:name": "LS7 2FB",
    "wof:placetype": "postalcode"
  },
  "geometry": {"coordinates":[-1.556644,53.828219],"type":"Point"}
}
