{
  "type": "Feature",
  "properties": {
    "date:inception_lower": "1980-01-01",
    "date:inception_upper": "1980-01-01",
    "iso:country": "GB",
    "wof:name": "G66 2EJ",
    "wof:placetype": "postalcode"
  },
  "geometry": {"coordinates":[-4.137019,55.940466],"type":"Point"}
}
