{
  "type": "Feature",
  "properties": {
    "iso:country":"GB",
    "wof:name":"LS1 4SP",
    "wof:placetype":"postalcode"
},
  "geometry": {"coordinates":[-1.54628021010559,53.79417131613327],"type":"Point"}
}