{
  "type": "Feature",
  "properties": {
    "date:inception_lower": "2003-01-01",
    "date:inception_upper": "2003-01-01",
    "iso:country": "GB",
    "wof:name": "LS1 4SP",
    "wof:placetype": "postalcode"
  },
  "geometry": {"coordinates":[-1.54628,53.794171],"type":"Point"}
}
