{
  "type": "Feature",
  "properties": {
    "date:inception_lower": "1980-01-01",
    "date:inception_upper": "1980-01-01",
    "iso:country": "GB",
    "wof:name": "PE31 6HT",
    "wof:placetype": "postalcode"
  },
  "geometry": {"coordinates":[0.509021,52.84766],"type":"Point"}
}
