{
  "type": "Feature",
  "properties": {
    "iso:country":"GB",
    "wof:name":"PE31 6HT",
    "wof:placetype":"postalcode"
},
  "geometry": {"coordinates":[0.50902100316495,52.84765963021288],"type":"Point"}
}