{
  "type": "Feature",
  "properties": {
    "date:inception_lower": "1980-01-01",
    "date:inception_upper": "1980-01-01",
    "iso:country": "GB",
    "wof:name": "PA8 7HG",
    "wof:placetype": "postalcode"
  },
  "geometry": {"coordinates":[-4.452426,55.896174],"type":"Point"}
}
