{
  "type": "Feature",
  "properties": {
    "iso:country":"GB",
    "wof:name":"PA8 7HG",
    "wof:placetype":"postalcode"
},
  "geometry": {"coordinates":[-4.45242602699522,55.89617409133677],"type":"Point"}
}