{
  "type": "Feature",
  "properties": {
    "iso:country":"GB",
    "wof:name":"SG8 7AY",
    "wof:placetype":"postalcode"
},
  "geometry": {"coordinates":[-0.02477257055445,52.05351897633441],"type":"Point"}
}