{
  "type": "Feature",
  "properties": {
    "iso:country":"GB",
    "wof:name":"DN8 5QX",
    "wof:placetype":"postalcode"
},
  "geometry": {"coordinates":[-0.96133528191207,53.60395753151177],"type":"Point"}
}