{
  "type": "Feature",
  "properties": {
    "iso:country":"GB",
    "wof:name":"W1B 5PZ",
    "wof:placetype":"postalcode"
},
  "geometry": {"coordinates":[-0.13955829330345,51.51298177102891],"type":"Point"}
}