{
  "type": "Feature",
  "properties": {
    "iso:country": "GB",
    "wof:name": "WD6 3JH",
    "wof:placetype": "postalcode"
  },
  "geometry": {"coordinates":[-0.278606,51.648136],"type":"Point"}
}
