{
  "type": "Feature",
  "properties": {
    "iso:country":"GB",
    "wof:name":"N2 9HT",
    "wof:placetype":"postalcode"
},
  "geometry": {"coordinates":[-0.15621570967491,51.5904628504569],"type":"Point"}
}