{
  "type": "Feature",
  "properties": {
    "iso:country": "GB",
    "wof:name": "MK42 8UR",
    "wof:placetype": "postalcode"
  },
  "geometry": {"coordinates":[-0.496181,52.123345],"type":"Point"}
}
