{
  "type": "Feature",
  "properties": {
    "iso:country":"GB",
    "wof:name":"WS11 5JL",
    "wof:placetype":"postalcode"
},
  "geometry": {"coordinates":[-2.02055811118954,52.70409378096961],"type":"Point"}
}