{
  "type": "Feature",
  "properties": {
    "iso:country": "GB",
    "wof:name": "CH66 1AE",
    "wof:placetype": "postalcode"
  },
  "geometry": {"coordinates":[-2.941889,53.297451],"type":"Point"}
}
