{
  "type": "Feature",
  "properties": {
    "iso:country":"GB",
    "wof:name":"CF81 9NT",
    "wof:placetype":"postalcode"
},
  "geometry": {"coordinates":[-3.27085998820996,51.70487105835675],"type":"Point"}
}