{
  "type": "Feature",
  "properties": {
    "iso:country":"GB",
    "wof:name":"LE2 3GD",
    "wof:placetype":"postalcode"
},
  "geometry": {"coordinates":[-1.12146196583924,52.6115723082588],"type":"Point"}
}