{
  "type": "Feature",
  "properties": {
    "iso:country": "GB",
    "wof:name": "CT2 8JU",
    "wof:placetype": "postalcode"
  },
  "geometry": {"coordinates":[1.061489,51.282948],"type":"Point"}
}
