{
  "type": "Feature",
  "properties": {
    "iso:country":"GB",
    "wof:name":"BD6 3EX",
    "wof:placetype":"postalcode"
},
  "geometry": {"coordinates":[-1.78645721830113,53.76891755640794],"type":"Point"}
}