{
  "type": "Feature",
  "properties": {
    "date:inception_lower":"1980-01-01",
    "date:inception_upper":"1980-01-31",
    "iso:country":"GB",
    "wof:name":"LA11 6NB",
    "wof:placetype":"postalcode"
},
  "geometry": {"coordinates":[-2.890007,54.221259],"type":"Point"}
}