{
  "type": "Feature",
  "properties": {
    "iso:country":"GB",
    "wof:name":"LA11 6NB",
    "wof:placetype":"postalcode"
},
  "geometry": {"coordinates":[-2.8900071042608,54.22125942502475],"type":"Point"}
}