{
  "type": "Feature",
  "properties": {
    "iso:country":"GB",
    "wof:name":"G51 4EJ",
    "wof:placetype":"postalcode"
},
  "geometry": {"coordinates":[-4.33430988240943,55.85590580608611],"type":"Point"}
}