{
  "type": "Feature",
  "properties": {
    "date:inception_lower": "1980-01-01",
    "date:inception_upper": "1980-01-01",
    "iso:country": "GB",
    "wof:name": "NG5 8NN",
    "wof:placetype": "postalcode"
  },
  "geometry": {"coordinates":[-1.15476,53.011245],"type":"Point"}
}
