{
  "type": "Feature",
  "properties": {
    "iso:country":"GB",
    "wof:name":"SY1 1XF",
    "wof:placetype":"postalcode"
},
  "geometry": {"coordinates":[-2.74882174389629,52.70634107708212],"type":"Point"}
}