{
  "type": "Feature",
  "properties": {
    "iso:country":"GB",
    "wof:name":"SW8 1LN",
    "wof:placetype":"postalcode"
},
  "geometry": {"coordinates":[-0.11851492494605,51.48154084335955],"type":"Point"}
}