{
  "type": "Feature",
  "properties": {
    "iso:country": "GB",
    "wof:name": "KT22 7EZ",
    "wof:placetype": "postalcode"
  },
  "geometry": {"coordinates":[-0.324259,51.299803],"type":"Point"}
}
