{
  "type": "Feature",
  "properties": {
    "iso:country":"GB",
    "wof:name":"M19 2AL",
    "wof:placetype":"postalcode"
},
  "geometry": {"coordinates":[-2.19779044587195,53.44782020615062],"type":"Point"}
}