{
  "type": "Feature",
  "properties": {
    "date:inception_lower":"1998-06-01",
    "date:inception_upper":"1998-06-30",
    "iso:country":"GB",
    "wof:name":"YO41 1PY",
    "wof:placetype":"postalcode"
},
  "geometry": {"coordinates":[-0.906758,53.987162],"type":"Point"}
}