{
  "type": "Feature",
  "properties": {
    "iso:country":"GB",
    "wof:name":"YO41 1PY",
    "wof:placetype":"postalcode"
},
  "geometry": {"coordinates":[-0.90675790503277,53.98716153352247],"type":"Point"}
}