{
  "type": "Feature",
  "properties": {
    "iso:country":"GB",
    "wof:name":"SO16 3BR",
    "wof:placetype":"postalcode"
},
  "geometry": {"coordinates":[-1.38418782570722,50.939461429175],"type":"Point"}
}