{
  "type": "Feature",
  "properties": {
    "date:inception_lower": "2022-02-01",
    "date:inception_upper": "2022-02-01",
    "iso:country": "GB",
    "wof:name": "PE31 8GT",
    "wof:placetype": "postalcode"
  },
  "geometry": {"coordinates":[0.712862,52.860411],"type":"Point"}
}
