{
  "type": "Feature",
  "properties": {
    "iso:country":"GB",
    "wof:name":"ML4 1NE",
    "wof:placetype":"postalcode"
},
  "geometry": {"coordinates":[-4.01879677689064,55.82530695460772],"type":"Point"}
}