{
  "type": "Feature",
  "properties": {
    "iso:country":"GB",
    "wof:name":"RG21 7LS",
    "wof:placetype":"postalcode"
},
  "geometry": {"coordinates":[-1.08757708515384,51.26411339574976],"type":"Point"}
}