{
  "type": "Feature",
  "properties": {
    "iso:country":"GB",
    "wof:name":"SR8 4NW",
    "wof:placetype":"postalcode"
},
  "geometry": {"coordinates":[-1.31963102691026,54.76511795211007],"type":"Point"}
}