{
  "type": "Feature",
  "properties": {
    "date:inception_lower": "1980-01-01",
    "date:inception_upper": "1980-01-01",
    "iso:country": "GB",
    "wof:name": "PE12 8ET",
    "wof:placetype": "postalcode"
  },
  "geometry": {"coordinates":[0.03365,52.861211],"type":"Point"}
}
