{
  "type": "Feature",
  "properties": {
    "iso:country":"GB",
    "wof:name":"MK44 2AY",
    "wof:placetype":"postalcode"
},
  "geometry": {"coordinates":[-0.41437627561132,52.27020635280505],"type":"Point"}
}