{
  "type": "Feature",
  "properties": {
    "iso:country": "GB",
    "wof:name": "MK44 2AY",
    "wof:placetype": "postalcode"
  },
  "geometry": {"coordinates":[-0.414376,52.270206],"type":"Point"}
}
