{
  "type": "Feature",
  "properties": {
    "iso:country": "GB",
    "wof:name": "CW2 8NH",
    "wof:placetype": "postalcode"
  },
  "geometry": {"coordinates":[-2.463788,53.093876],"type":"Point"}
}
