{
  "type": "Feature",
  "properties": {
    "date:inception_lower": "1980-01-01",
    "date:inception_upper": "1980-01-01",
    "iso:country": "GB",
    "wof:name": "CW2 8NH",
    "wof:placetype": "postalcode"
  },
  "geometry": {"coordinates":[-2.463788,53.093876],"type":"Point"}
}
