{
  "type": "Feature",
  "properties": {
    "iso:country":"GB",
    "wof:name":"PE19 2DL",
    "wof:placetype":"postalcode"
},
  "geometry": {"coordinates":[-0.26128786318999,52.22240212575794],"type":"Point"}
}