{
  "type": "Feature",
  "properties": {
    "iso:country": "GB",
    "wof:name": "NN17 4SJ",
    "wof:placetype": "postalcode"
  },
  "geometry": {"coordinates":[-0.682054,52.503901],"type":"Point"}
}
