{
  "type": "Feature",
  "properties": {
    "iso:country":"GB",
    "wof:name":"NN17 4SJ",
    "wof:placetype":"postalcode"
},
  "geometry": {"coordinates":[-0.68218647111265,52.50387654750847],"type":"Point"}
}