{
  "type": "Feature",
  "properties": {
    "iso:country":"GB",
    "wof:name":"EH39 4PL",
    "wof:placetype":"postalcode"
},
  "geometry": {"coordinates":[-2.71950738363116,56.05822383815438],"type":"Point"}
}