{
  "type": "Feature",
  "properties": {
    "iso:country":"GB",
    "wof:name":"SE16 3DX",
    "wof:placetype":"postalcode"
},
  "geometry": {"coordinates":[-0.05961180608404,51.48727140724677],"type":"Point"}
}