{
  "type": "Feature",
  "properties": {
    "iso:country": "GB",
    "wof:name": "LE15 7RN",
    "wof:placetype": "postalcode"
  },
  "geometry": {"coordinates":[-0.591237,52.743207],"type":"Point"}
}
