{
  "type": "Feature",
  "properties": {
    "date:inception_lower":"1996-06-01",
    "date:inception_upper":"1996-06-30",
    "iso:country":"GB",
    "wof:name":"LE15 7RN",
    "wof:placetype":"postalcode"
},
  "geometry": {"coordinates":[-0.591237,52.743207],"type":"Point"}
}