{
  "type": "Feature",
  "properties": {
    "iso:country":"GB",
    "wof:name":"LE15 7RN",
    "wof:placetype":"postalcode"
},
  "geometry": {"coordinates":[-0.59123670139478,52.74320652187993],"type":"Point"}
}