{
  "type": "Feature",
  "properties": {
    "iso:country": "GB",
    "wof:name": "HR6 8JT",
    "wof:placetype": "postalcode"
  },
  "geometry": {"coordinates":[-2.738247,52.218618],"type":"Point"}
}
