{
  "type": "Feature",
  "properties": {
    "iso:country":"GB",
    "wof:name":"HR6 8JT",
    "wof:placetype":"postalcode"
},
  "geometry": {"coordinates":[-2.73824667833438,52.21861842479453],"type":"Point"}
}