{
  "type": "Feature",
  "properties": {
    "iso:country": "GB",
    "wof:name": "OL4 3QR",
    "wof:placetype": "postalcode"
  },
  "geometry": {"coordinates":[-2.06208,53.547425],"type":"Point"}
}
