{
  "type": "Feature",
  "properties": {
    "iso:country": "GB",
    "wof:name": "NG6 9DT",
    "wof:placetype": "postalcode"
  },
  "geometry": {"coordinates":[-1.182258,52.994753],"type":"Point"}
}
