{
  "type": "Feature",
  "properties": {
    "iso:country":"GB",
    "wof:name":"NG6 9DT",
    "wof:placetype":"postalcode"
},
  "geometry": {"coordinates":[-1.18225754605345,52.99475332599145],"type":"Point"}
}