{
  "type": "Feature",
  "properties": {
    "date:inception_lower": "1984-02-01",
    "date:inception_upper": "1984-02-01",
    "iso:country": "GB",
    "wof:name": "NG6 9DT",
    "wof:placetype": "postalcode"
  },
  "geometry": {"coordinates":[-1.182258,52.994753],"type":"Point"}
}
