{
  "type": "Feature",
  "properties": {
    "iso:country":"GB",
    "wof:name":"LE4 8GS",
    "wof:placetype":"postalcode"
},
  "geometry": {"coordinates":[-1.08476058277556,52.68386180772239],"type":"Point"}
}