{
  "type": "Feature",
  "properties": {
    "iso:country": "GB",
    "wof:name": "ML2 8NQ",
    "wof:placetype": "postalcode"
  },
  "geometry": {"coordinates":[-3.896562,55.777592],"type":"Point"}
}
