{
  "type": "Feature",
  "properties": {
    "iso:country":"GB",
    "wof:name":"ML2 8NQ",
    "wof:placetype":"postalcode"
},
  "geometry": {"coordinates":[-3.89656219993567,55.77759206255571],"type":"Point"}
}