{
  "type": "Feature",
  "properties": {
    "iso:country": "GB",
    "wof:name": "CV10 8RD",
    "wof:placetype": "postalcode"
  },
  "geometry": {"coordinates":[-1.509911,52.5221],"type":"Point"}
}
