{
  "type": "Feature",
  "properties": {
    "iso:country":"GB",
    "wof:name":"TN4 8DR",
    "wof:placetype":"postalcode"
},
  "geometry": {"coordinates":[0.25195261412629,51.13503756023737],"type":"Point"}
}