{
  "type": "Feature",
  "properties": {
    "date:inception_lower": "1980-01-01",
    "date:inception_upper": "1980-01-01",
    "iso:country": "GB",
    "wof:name": "TN4 8DR",
    "wof:placetype": "postalcode"
  },
  "geometry": {"coordinates":[0.251953,51.135038],"type":"Point"}
}
