{
  "type": "Feature",
  "properties": {
    "iso:country":"GB",
    "wof:name":"BS7 0AG",
    "wof:placetype":"postalcode"
},
  "geometry": {"coordinates":[-2.5836662675097,51.48791136241173],"type":"Point"}
}