{
  "type": "Feature",
  "properties": {
    "date:inception_lower":"1980-01-01",
    "date:inception_upper":"1980-01-31",
    "iso:country":"GB",
    "wof:name":"LU3 3NJ",
    "wof:placetype":"postalcode"
},
  "geometry": {"coordinates":[-0.437145,51.927858],"type":"Point"}
}