{
  "type": "Feature",
  "properties": {
    "iso:country": "GB",
    "wof:name": "LU3 3NJ",
    "wof:placetype": "postalcode"
  },
  "geometry": {"coordinates":[-0.437145,51.927858],"type":"Point"}
}
