{
  "type": "Feature",
  "properties": {
    "iso:country":"GB",
    "wof:name":"MK44 3WJ",
    "wof:placetype":"postalcode"
},
  "geometry": {"coordinates":[-0.41878808369247,52.12836582899317],"type":"Point"}
}