{
  "type": "Feature",
  "properties": {
    "iso:country":"GB",
    "wof:name":"PR8 1NT",
    "wof:placetype":"postalcode"
},
  "geometry": {"coordinates":[-3.00658561119516,53.64866693772521],"type":"Point"}
}