{
  "type": "Feature",
  "properties": {
    "date:inception_lower":"1994-05-01",
    "date:inception_upper":"1994-05-31",
    "iso:country":"GB",
    "wof:name":"M33 3WS",
    "wof:placetype":"postalcode"
},
  "geometry": {"coordinates":[-2.31444,53.415903],"type":"Point"}
}