{
  "type": "Feature",
  "properties": {
    "iso:country":"GB",
    "wof:name":"BS36 2NU",
    "wof:placetype":"postalcode"
},
  "geometry": {"coordinates":[-2.4522973020036,51.53695606157504],"type":"Point"}
}