{
  "type": "Feature",
  "properties": {
    "date:inception_lower": "2021-06-01",
    "date:inception_upper": "2021-06-01",
    "iso:country": "GB",
    "wof:name": "HU16 5FY",
    "wof:placetype": "postalcode"
  },
  "geometry": {"coordinates":[-0.422631,53.788246],"type":"Point"}
}
