{
  "type": "Feature",
  "properties": {
    "iso:country":"GB",
    "wof:name":"NP12 2NH",
    "wof:placetype":"postalcode"
},
  "geometry": {"coordinates":[-3.19111899384775,51.64035550322058],"type":"Point"}
}