{
  "type": "Feature",
  "properties": {
    "date:inception_lower":"2006-03-01",
    "date:inception_upper":"2006-03-31",
    "iso:country":"GB",
    "wof:name":"OL1 2NA",
    "wof:placetype":"postalcode"
},
  "geometry": {"coordinates":[-2.132834,53.554025],"type":"Point"}
}