{
  "type": "Feature",
  "properties": {
    "iso:country": "GB",
    "wof:name": "OL1 2NA",
    "wof:placetype": "postalcode"
  },
  "geometry": {"coordinates":[-2.132834,53.554025],"type":"Point"}
}
