{
  "type": "Feature",
  "properties": {
    "date:inception_lower": "2006-03-01",
    "date:inception_upper": "2006-03-01",
    "iso:country": "GB",
    "wof:name": "OL1 2NA",
    "wof:placetype": "postalcode"
  },
  "geometry": {"coordinates":[-2.132096,53.554431],"type":"Point"}
}
