{
  "type": "Feature",
  "properties": {
    "iso:country":"GB",
    "wof:name":"NR24 2AY",
    "wof:placetype":"postalcode"
},
  "geometry": {"coordinates":[1.11410341154097,52.85367190753956],"type":"Point"}
}