{
  "type": "Feature",
  "properties": {
    "iso:country": "GB",
    "wof:name": "SP4 7BF",
    "wof:placetype": "postalcode"
  },
  "geometry": {"coordinates":[-1.768554,51.159117],"type":"Point"}
}
