{
  "type": "Feature",
  "properties": {
    "date:inception_lower": "2024-02-01",
    "date:inception_upper": "2024-02-01",
    "iso:country": "GB",
    "wof:name": "PO8 0WX",
    "wof:placetype": "postalcode"
  },
  "geometry": {"coordinates":[-1.032316,50.929119],"type":"Point"}
}
