{
  "type": "Feature",
  "properties": {
    "iso:country": "GB",
    "wof:name": "LE3 8JN",
    "wof:placetype": "postalcode"
  },
  "geometry": {"coordinates":[-1.190002,52.642824],"type":"Point"}
}
