{
  "type": "Feature",
  "properties": {
    "iso:country":"GB",
    "wof:name":"DN32 7QD",
    "wof:placetype":"postalcode"
},
  "geometry": {"coordinates":[-0.06872164671459,53.57052289881631],"type":"Point"}
}