{
  "type": "Feature",
  "properties": {
    "date:inception_lower":"1984-02-01",
    "date:inception_upper":"1984-02-29",
    "iso:country":"GB",
    "wof:name":"DN32 7QD",
    "wof:placetype":"postalcode"
},
  "geometry": {"coordinates":[-0.068722,53.570523],"type":"Point"}
}