{
  "type": "Feature",
  "properties": {
    "date:inception_lower": "1980-01-01",
    "date:inception_upper": "1980-01-01",
    "iso:country": "GB",
    "wof:name": "S66 9HU",
    "wof:placetype": "postalcode"
  },
  "geometry": {"coordinates":[-1.261921,53.399315],"type":"Point"}
}
