{
  "type": "Feature",
  "properties": {
    "date:inception_lower":"1998-06-01",
    "date:inception_upper":"1998-06-30",
    "iso:country":"GB",
    "wof:name":"YO19 6BW",
    "wof:placetype":"postalcode"
},
  "geometry": {"coordinates":[-0.964849,53.899178],"type":"Point"}
}