{
  "type": "Feature",
  "properties": {
    "date:inception_lower": "1998-06-01",
    "date:inception_upper": "1998-06-01",
    "iso:country": "GB",
    "wof:name": "YO19 6BW",
    "wof:placetype": "postalcode"
  },
  "geometry": {"coordinates":[-0.964887,53.899171],"type":"Point"}
}
