{
  "type": "Feature",
  "properties": {
    "iso:country": "GB",
    "wof:name": "YO19 6BW",
    "wof:placetype": "postalcode"
  },
  "geometry": {"coordinates":[-0.964849,53.899178],"type":"Point"}
}
