{
  "type": "Feature",
  "properties": {
    "iso:country": "GB",
    "wof:name": "YO19 6BW",
    "wof:placetype": "postalcode"
  },
  "geometry": {"coordinates":[-0.964887,53.899171],"type":"Point"}
}
