{
  "type": "Feature",
  "properties": {
    "date:inception_lower": "1983-07-01",
    "date:inception_upper": "1983-07-01",
    "iso:country": "GB",
    "wof:name": "CV22 6SL",
    "wof:placetype": "postalcode"
  },
  "geometry": {"coordinates":[-1.277829,52.363458],"type":"Point"}
}
