{
  "type": "Feature",
  "properties": {
    "iso:country":"GB",
    "wof:name":"CV22 6SL",
    "wof:placetype":"postalcode"
},
  "geometry": {"coordinates":[-1.27782923337518,52.36345802555695],"type":"Point"}
}