{
  "type": "Feature",
  "properties": {
    "iso:country": "GB",
    "wof:name": "LE67 5DF",
    "wof:placetype": "postalcode"
  },
  "geometry": {"coordinates":[-1.368319,52.740711],"type":"Point"}
}
