{
  "type": "Feature",
  "properties": {
    "iso:country":"GB",
    "wof:name":"TQ9 6QT",
    "wof:placetype":"postalcode"
},
  "geometry": {"coordinates":[-3.62553049497029,50.4044753166112],"type":"Point"}
}