{
  "type": "Feature",
  "properties": {
    "iso:country": "GB",
    "wof:name": "TQ9 6QT",
    "wof:placetype": "postalcode"
  },
  "geometry": {"coordinates":[-3.62553,50.404475],"type":"Point"}
}
