{
  "type": "Feature",
  "properties": {
    "iso:country":"GB",
    "wof:name":"DN2 6LE",
    "wof:placetype":"postalcode"
},
  "geometry": {"coordinates":[-1.10070119423873,53.52938348409329],"type":"Point"}
}