{
  "type": "Feature",
  "properties": {
    "date:inception_lower": "1992-08-01",
    "date:inception_upper": "1992-08-01",
    "iso:country": "GB",
    "wof:name": "SS3 8TE",
    "wof:placetype": "postalcode"
  },
  "geometry": {"coordinates":[0.784551,51.544773],"type":"Point"}
}
