{
  "type": "Feature",
  "properties": {
    "iso:country":"GB",
    "wof:name":"SS3 8TE",
    "wof:placetype":"postalcode"
},
  "geometry": {"coordinates":[0.78455053706164,51.54477262403253],"type":"Point"}
}