{
  "type": "Feature",
  "properties": {
    "iso:country":"GB",
    "wof:name":"SW17 7NP",
    "wof:placetype":"postalcode"
},
  "geometry": {"coordinates":[-0.16598339817238,51.43235723732575],"type":"Point"}
}