{
  "type": "Feature",
  "properties": {
    "iso:country":"GB",
    "wof:name":"KA28 0AZ",
    "wof:placetype":"postalcode"
},
  "geometry": {"coordinates":[-4.92928155795886,55.75429503880052],"type":"Point"}
}