{
  "type": "Feature",
  "properties": {
    "iso:country": "GB",
    "wof:name": "NE25 0ER",
    "wof:placetype": "postalcode"
  },
  "geometry": {"coordinates":[-1.532671,55.07006],"type":"Point"}
}
