{
  "type": "Feature",
  "properties": {
    "date:inception_lower":"2000-10-01",
    "date:inception_upper":"2000-10-31",
    "iso:country":"GB",
    "wof:name":"W1H 5JF",
    "wof:placetype":"postalcode"
},
  "geometry": {"coordinates":[-0.164712,51.517616],"type":"Point"}
}