{
  "type": "Feature",
  "properties": {
    "iso:country":"GB",
    "wof:name":"GU7 2FE",
    "wof:placetype":"postalcode"
},
  "geometry": {"coordinates":[-0.6097541893124,51.19444441144341],"type":"Point"}
}