{
  "type": "Feature",
  "properties": {
    "date:inception_lower":"2008-11-01",
    "date:inception_upper":"2008-11-30",
    "iso:country":"GB",
    "wof:name":"GU7 2FE",
    "wof:placetype":"postalcode"
},
  "geometry": {"coordinates":[-0.609734,51.194441],"type":"Point"}
}