{
  "type": "Feature",
  "properties": {
    "iso:country":"GB",
    "wof:name":"L38 7JA",
    "wof:placetype":"postalcode"
},
  "geometry": {"coordinates":[-3.0645796976329,53.53410724120369],"type":"Point"}
}