{
  "type": "Feature",
  "properties": {
    "iso:country":"GB",
    "wof:name":"BD23 5HP",
    "wof:placetype":"postalcode"
},
  "geometry": {"coordinates":[-2.01189896414687,54.07042168012645],"type":"Point"}
}