{
  "type": "Feature",
  "properties": {
    "iso:country": "GB",
    "wof:name": "BD23 5HP",
    "wof:placetype": "postalcode"
  },
  "geometry": {"coordinates":[-2.011842,54.070436],"type":"Point"}
}
