{
  "type": "Feature",
  "properties": {
    "iso:country":"GB",
    "wof:name":"RH15 8DT",
    "wof:placetype":"postalcode"
},
  "geometry": {"coordinates":[-0.12707954636674,50.95592436018346],"type":"Point"}
}