{
  "type": "Feature",
  "properties": {
    "iso:country": "GB",
    "wof:name": "RH15 8DT",
    "wof:placetype": "postalcode"
  },
  "geometry": {"coordinates":[-0.12708,50.955924],"type":"Point"}
}
