{
  "type": "Feature",
  "properties": {
    "iso:country":"GB",
    "wof:name":"E4 8JR",
    "wof:placetype":"postalcode"
},
  "geometry": {"coordinates":[-0.01722431390974,51.61390655485692],"type":"Point"}
}