{
  "type": "Feature",
  "properties": {
    "iso:country":"GB",
    "wof:name":"PO21 2HT",
    "wof:placetype":"postalcode"
},
  "geometry": {"coordinates":[-0.67936338792094,50.78528944561351],"type":"Point"}
}