{
  "type": "Feature",
  "properties": {
    "iso:country":"GB",
    "wof:name":"SW3 3BX",
    "wof:placetype":"postalcode"
},
  "geometry": {"coordinates":[-0.16335920695775,51.49202668843277],"type":"Point"}
}