{
  "type": "Feature",
  "properties": {
    "iso:country": "GB",
    "wof:name": "HU17 9HR",
    "wof:placetype": "postalcode"
  },
  "geometry": {"coordinates":[-0.428,53.850275],"type":"Point"}
}
