{
  "type": "Feature",
  "properties": {
    "iso:country": "GB",
    "wof:name": "TS27 3BL",
    "wof:placetype": "postalcode"
  },
  "geometry": {"coordinates":[-1.287752,54.696177],"type":"Point"}
}
