{
  "type": "Feature",
  "properties": {
    "iso:country":"GB",
    "wof:name":"TS27 3BL",
    "wof:placetype":"postalcode"
},
  "geometry": {"coordinates":[-1.28775191441668,54.69617713501097],"type":"Point"}
}