{
  "type": "Feature",
  "properties": {
    "iso:country":"GB",
    "wof:name":"NW9 8BL",
    "wof:placetype":"postalcode"
},
  "geometry": {"coordinates":[-0.25810296034009,51.57774848374041],"type":"Point"}
}