{
  "type": "Feature",
  "properties": {
    "iso:country":"GB",
    "wof:name":"EX32 7EA",
    "wof:placetype":"postalcode"
},
  "geometry": {"coordinates":[-4.05189023621307,51.08318582052847],"type":"Point"}
}