{
  "type": "Feature",
  "properties": {
    "iso:country": "GB",
    "wof:name": "EX32 7EA",
    "wof:placetype": "postalcode"
  },
  "geometry": {"coordinates":[-4.05189,51.083186],"type":"Point"}
}
