{
  "type": "Feature",
  "properties": {
    "date:inception_lower":"1980-01-01",
    "date:inception_upper":"1980-01-31",
    "iso:country":"GB",
    "wof:name":"EX32 7EA",
    "wof:placetype":"postalcode"
},
  "geometry": {"coordinates":[-4.05189,51.083186],"type":"Point"}
}