{
  "type": "Feature",
  "properties": {
    "date:inception_lower":"1995-01-01",
    "date:inception_upper":"1995-01-31",
    "iso:country":"GB",
    "wof:name":"RM6 4FE",
    "wof:placetype":"postalcode"
},
  "geometry": {"coordinates":[0.115861,51.577779],"type":"Point"}
}