{
  "type": "Feature",
  "properties": {
    "iso:country":"GB",
    "wof:name":"RM6 4FE",
    "wof:placetype":"postalcode"
},
  "geometry": {"coordinates":[0.11586109408122,51.57777932163224],"type":"Point"}
}