{
  "type": "Feature",
  "properties": {
    "iso:country":"GB",
    "wof:name":"W1F 0SA",
    "wof:placetype":"postalcode"
},
  "geometry": {"coordinates":[-0.13367974748221,51.51259162421115],"type":"Point"}
}