{
  "type": "Feature",
  "properties": {
    "iso:country": "GB",
    "wof:name": "PR8 3HA",
    "wof:placetype": "postalcode"
  },
  "geometry": {"coordinates":[-3.027422,53.602783],"type":"Point"}
}
