{
  "type": "Feature",
  "properties": {
    "date:inception_lower":"2005-02-01",
    "date:inception_upper":"2005-02-28",
    "iso:country":"GB",
    "wof:name":"BD11 2AG",
    "wof:placetype":"postalcode"
},
  "geometry": {"coordinates":[-1.695262,53.75425],"type":"Point"}
}