{
  "type": "Feature",
  "properties": {
    "iso:country":"GB",
    "wof:name":"BD11 2AG",
    "wof:placetype":"postalcode"
},
  "geometry": {"coordinates":[-1.69526225047047,53.75424989017582],"type":"Point"}
}