{
  "type": "Feature",
  "properties": {
    "iso:country":"GB",
    "wof:name":"LN2 2BP",
    "wof:placetype":"postalcode"
},
  "geometry": {"coordinates":[-0.49061134260525,53.26770475939275],"type":"Point"}
}