{
  "type": "Feature",
  "properties": {
    "iso:country": "GB",
    "wof:name": "LN2 2BP",
    "wof:placetype": "postalcode"
  },
  "geometry": {"coordinates":[-0.490611,53.267705],"type":"Point"}
}
