{
  "type": "Feature",
  "properties": {
    "date:inception_lower": "2011-05-01",
    "date:inception_upper": "2011-05-01",
    "iso:country": "GB",
    "wof:name": "LN2 2BP",
    "wof:placetype": "postalcode"
  },
  "geometry": {"coordinates":[-0.490611,53.267705],"type":"Point"}
}
