{
  "type": "Feature",
  "properties": {
    "date:inception_lower": "1980-01-01",
    "date:inception_upper": "1980-01-01",
    "iso:country": "GB",
    "wof:name": "BS1 3JP",
    "wof:placetype": "postalcode"
  },
  "geometry": {"coordinates":[-2.588637,51.458952],"type":"Point"}
}
