{
  "type": "Feature",
  "properties": {
    "iso:country": "GB",
    "wof:name": "BS1 3JP",
    "wof:placetype": "postalcode"
  },
  "geometry": {"coordinates":[-2.588637,51.458952],"type":"Point"}
}
