{
  "type": "Feature",
  "properties": {
    "iso:country":"GB",
    "wof:name":"BS1 3JP",
    "wof:placetype":"postalcode"
},
  "geometry": {"coordinates":[-2.58863659588047,51.45895150762094],"type":"Point"}
}