{
  "type": "Feature",
  "properties": {
    "iso:country":"GB",
    "wof:name":"SO23 0NU",
    "wof:placetype":"postalcode"
},
  "geometry": {"coordinates":[-1.29506697746196,51.06628069519343],"type":"Point"}
}