{
  "type": "Feature",
  "properties": {
    "iso:country": "GB",
    "wof:name": "SK11 0EN",
    "wof:placetype": "postalcode"
  },
  "geometry": {"coordinates":[-2.108409,53.238904],"type":"Point"}
}
