{
  "type": "Feature",
  "properties": {
    "iso:country":"GB",
    "wof:name":"SM1 4BH",
    "wof:placetype":"postalcode"
},
  "geometry": {"coordinates":[-0.19236456512318,51.36900049186269],"type":"Point"}
}