{
  "type": "Feature",
  "properties": {
    "date:inception_lower": "2008-02-01",
    "date:inception_upper": "2008-02-01",
    "iso:country": "GB",
    "wof:name": "SM1 4BH",
    "wof:placetype": "postalcode"
  },
  "geometry": {"coordinates":[-0.192354,51.368991],"type":"Point"}
}
