{
  "type": "Feature",
  "properties": {
    "iso:country": "GB",
    "wof:name": "SM1 4BH",
    "wof:placetype": "postalcode"
  },
  "geometry": {"coordinates":[-0.192354,51.368991],"type":"Point"}
}
