{
  "type": "Feature",
  "properties": {
    "date:inception_lower":"1994-12-01",
    "date:inception_upper":"1994-12-31",
    "iso:country":"GB",
    "wof:name":"BN16 3SN",
    "wof:placetype":"postalcode"
},
  "geometry": {"coordinates":[-0.51215,50.821048],"type":"Point"}
}