{
  "type": "Feature",
  "properties": {
    "iso:country":"GB",
    "wof:name":"S45 9EL",
    "wof:placetype":"postalcode"
},
  "geometry": {"coordinates":[-1.4155812435251,53.16295854075229],"type":"Point"}
}