{
  "type": "Feature",
  "properties": {
    "iso:country":"GB",
    "wof:name":"W1H 4JE",
    "wof:placetype":"postalcode"
},
  "geometry": {"coordinates":[-0.1634901732555,51.51923102470503],"type":"Point"}
}