{
  "type": "Feature",
  "properties": {
    "date:inception_lower": "2001-06-01",
    "date:inception_upper": "2001-06-01",
    "iso:country": "GB",
    "wof:name": "TS9 5PX",
    "wof:placetype": "postalcode"
  },
  "geometry": {"coordinates":[-1.198006,54.471767],"type":"Point"}
}
