{
  "type": "Feature",
  "properties": {
    "iso:country":"GB",
    "wof:name":"TS9 5PX",
    "wof:placetype":"postalcode"
},
  "geometry": {"coordinates":[-1.19800583769062,54.47176694490339],"type":"Point"}
}