{
  "type": "Feature",
  "properties": {
    "iso:country": "GB",
    "wof:name": "RH10 8JX",
    "wof:placetype": "postalcode"
  },
  "geometry": {"coordinates":[-0.17789,51.125565],"type":"Point"}
}
