{
  "type": "Feature",
  "properties": {
    "iso:country":"GB",
    "wof:name":"RH10 8JX",
    "wof:placetype":"postalcode"
},
  "geometry": {"coordinates":[-0.17788992663222,51.12556506459858],"type":"Point"}
}