{
  "type": "Feature",
  "properties": {
    "iso:country":"GB",
    "wof:name":"CH8 8NJ",
    "wof:placetype":"postalcode"
},
  "geometry": {"coordinates":[-3.270323926773,53.23323336594444],"type":"Point"}
}