{
  "type": "Feature",
  "properties": {
    "iso:country": "GB",
    "wof:name": "CH8 8NJ",
    "wof:placetype": "postalcode"
  },
  "geometry": {"coordinates":[-3.270324,53.233233],"type":"Point"}
}
