{
  "type": "Feature",
  "properties": {
    "date:inception_lower": "1980-01-01",
    "date:inception_upper": "1980-01-01",
    "iso:country": "GB",
    "wof:name": "DL14 7BN",
    "wof:placetype": "postalcode"
  },
  "geometry": {"coordinates":[-1.679712,54.661387],"type":"Point"}
}
