{
  "type": "Feature",
  "properties": {
    "iso:country":"GB",
    "wof:name":"DL14 7BN",
    "wof:placetype":"postalcode"
},
  "geometry": {"coordinates":[-1.67971253648277,54.66138682641078],"type":"Point"}
}