{
  "type": "Feature",
  "properties": {
    "iso:country":"GB",
    "wof:name":"BH1 2BZ",
    "wof:placetype":"postalcode"
},
  "geometry": {"coordinates":[-1.87437290878854,50.71855074472178],"type":"Point"}
}