{
  "type": "Feature",
  "properties": {
    "iso:country": "GB",
    "wof:name": "PE36 6AB",
    "wof:placetype": "postalcode"
  },
  "geometry": {"coordinates":[0.491593,52.940829],"type":"Point"}
}
