{
  "type": "Feature",
  "properties": {
    "iso:country": "GB",
    "wof:name": "B12 9QG",
    "wof:placetype": "postalcode"
  },
  "geometry": {"coordinates":[-1.890056,52.454026],"type":"Point"}
}
