{
  "type": "Feature",
  "properties": {
    "date:inception_lower": "1996-12-01",
    "date:inception_upper": "1996-12-01",
    "iso:country": "GB",
    "wof:name": "LN10 5HP",
    "wof:placetype": "postalcode"
  },
  "geometry": {"coordinates":[-0.241421,53.177464],"type":"Point"}
}
