{
  "type": "Feature",
  "properties": {
    "date:inception_lower": "1996-06-01",
    "date:inception_upper": "1996-06-01",
    "iso:country": "GB",
    "wof:name": "AB55 5DT",
    "wof:placetype": "postalcode"
  },
  "geometry": {"coordinates":[-2.964959,57.54379],"type":"Point"}
}
