{
  "type": "Feature",
  "properties": {
    "iso:country":"GB",
    "wof:name":"AB55 5DT",
    "wof:placetype":"postalcode"
},
  "geometry": {"coordinates":[-2.96495931432452,57.54379034200058],"type":"Point"}
}