{
  "type": "Feature",
  "properties": {
    "iso:country":"GB",
    "wof:name":"EH21 8LL",
    "wof:placetype":"postalcode"
},
  "geometry": {"coordinates":[-3.01824842134907,55.93723674753524],"type":"Point"}
}