{
  "type": "Feature",
  "properties": {
    "iso:country":"GB",
    "wof:name":"N18 2SA",
    "wof:placetype":"postalcode"
},
  "geometry": {"coordinates":[-0.05638798376382,51.60904019133272],"type":"Point"}
}