{
  "type": "Feature",
  "properties": {
    "iso:country": "GB",
    "wof:name": "IP24 2JB",
    "wof:placetype": "postalcode"
  },
  "geometry": {"coordinates":[0.755556,52.416227],"type":"Point"}
}
