{
  "type": "Feature",
  "properties": {
    "iso:country": "GB",
    "wof:name": "L8 4TX",
    "wof:placetype": "postalcode"
  },
  "geometry": {"coordinates":[-2.967456,53.384981],"type":"Point"}
}
