{
  "type": "Feature",
  "properties": {
    "iso:country":"GB",
    "wof:name":"SS8 9RZ",
    "wof:placetype":"postalcode"
},
  "geometry": {"coordinates":[0.5861678444342,51.53185902046375],"type":"Point"}
}