{
  "type": "Feature",
  "properties": {
    "date:inception_lower": "1981-09-01",
    "date:inception_upper": "1981-09-01",
    "iso:country": "GB",
    "wof:name": "SS8 9RZ",
    "wof:placetype": "postalcode"
  },
  "geometry": {"coordinates":[0.586177,51.5318],"type":"Point"}
}
