{
  "type": "Feature",
  "properties": {
    "iso:country":"GB",
    "wof:name":"EN5 2BS",
    "wof:placetype":"postalcode"
},
  "geometry": {"coordinates":[-0.18528234159401,51.64028368582778],"type":"Point"}
}