{
  "type": "Feature",
  "properties": {
    "iso:country": "GB",
    "wof:name": "EN5 2BS",
    "wof:placetype": "postalcode"
  },
  "geometry": {"coordinates":[-0.185282,51.640284],"type":"Point"}
}
