{
  "type": "Feature",
  "properties": {
    "iso:country": "GB",
    "wof:name": "DY1 3AY",
    "wof:placetype": "postalcode"
  },
  "geometry": {"coordinates":[-2.098034,52.515995],"type":"Point"}
}
