{
  "type": "Feature",
  "properties": {
    "iso:country":"GB",
    "wof:name":"DY1 3AY",
    "wof:placetype":"postalcode"
},
  "geometry": {"coordinates":[-2.09799566922152,52.51590815422465],"type":"Point"}
}