{
  "type": "Feature",
  "properties": {
    "iso:country":"GB",
    "wof:name":"WF12 8PW",
    "wof:placetype":"postalcode"
},
  "geometry": {"coordinates":[-1.59709732171263,53.68866154697675],"type":"Point"}
}