{
  "type": "Feature",
  "properties": {
    "iso:country":"GB",
    "wof:name":"HA3 0UR",
    "wof:placetype":"postalcode"
},
  "geometry": {"coordinates":[-0.29713065694487,51.58577583077648],"type":"Point"}
}