{
  "type": "Feature",
  "properties": {
    "iso:country":"GB",
    "wof:name":"CV6 7AY",
    "wof:placetype":"postalcode"
},
  "geometry": {"coordinates":[-1.48136938554871,52.44510491114955],"type":"Point"}
}