{
  "type": "Feature",
  "properties": {
    "iso:country":"GB",
    "wof:name":"HX7 8RX",
    "wof:placetype":"postalcode"
},
  "geometry": {"coordinates":[-2.00015992678241,53.75062790174179],"type":"Point"}
}