{
  "type": "Feature",
  "properties": {
    "iso:country":"GB",
    "wof:name":"LN1 1AE",
    "wof:placetype":"postalcode"
},
  "geometry": {"coordinates":[-0.55598451625857,53.24511445172452],"type":"Point"}
}