{
  "type": "Feature",
  "properties": {
    "date:inception_lower":"1990-07-01",
    "date:inception_upper":"1990-07-31",
    "iso:country":"GB",
    "wof:name":"BN10 8AR",
    "wof:placetype":"postalcode"
},
  "geometry": {"coordinates":[0.01747,50.802784],"type":"Point"}
}