{
  "type": "Feature",
  "properties": {
    "iso:country": "GB",
    "wof:name": "BN10 8AR",
    "wof:placetype": "postalcode"
  },
  "geometry": {"coordinates":[0.01747,50.802784],"type":"Point"}
}
