{
  "type": "Feature",
  "properties": {
    "iso:country": "GB",
    "wof:name": "BN16 1EP",
    "wof:placetype": "postalcode"
  },
  "geometry": {"coordinates":[-0.476405,50.815272],"type":"Point"}
}
