{
  "type": "Feature",
  "properties": {
    "date:inception_lower": "1980-01-01",
    "date:inception_upper": "1980-01-01",
    "iso:country": "GB",
    "wof:name": "DT4 7PS",
    "wof:placetype": "postalcode"
  },
  "geometry": {"coordinates":[-2.454508,50.620382],"type":"Point"}
}
