{
  "type": "Feature",
  "properties": {
    "iso:country":"GB",
    "wof:name":"DT4 7PS",
    "wof:placetype":"postalcode"
},
  "geometry": {"coordinates":[-2.45452535499635,50.62039304388377],"type":"Point"}
}