{
  "type": "Feature",
  "properties": {
    "date:inception_lower":"1999-06-01",
    "date:inception_upper":"1999-06-30",
    "iso:country":"GB",
    "wof:name":"HR3 5SZ",
    "wof:placetype":"postalcode"
},
  "geometry": {"coordinates":[-3.146905,52.085903],"type":"Point"}
}