{
  "type": "Feature",
  "properties": {
    "iso:country":"GB",
    "wof:name":"TS10 5HT",
    "wof:placetype":"postalcode"
},
  "geometry": {"coordinates":[-1.09048033929115,54.60474460102999],"type":"Point"}
}