{
  "type": "Feature",
  "properties": {
    "date:inception_lower":"1980-01-01",
    "date:inception_upper":"1980-01-31",
    "iso:country":"GB",
    "wof:name":"TS10 5HT",
    "wof:placetype":"postalcode"
},
  "geometry": {"coordinates":[-1.09048,54.604745],"type":"Point"}
}