{
  "type": "Feature",
  "properties": {
    "iso:country":"GB",
    "wof:name":"HA9 9JG",
    "wof:placetype":"postalcode"
},
  "geometry": {"coordinates":[-0.27453133937768,51.56886401645315],"type":"Point"}
}