{
  "type": "Feature",
  "properties": {
    "date:inception_lower": "2022-02-01",
    "date:inception_upper": "2022-02-01",
    "iso:country": "GB",
    "wof:name": "S2 5DX",
    "wof:placetype": "postalcode"
  },
  "geometry": {"coordinates":[-1.459018,53.380254],"type":"Point"}
}
