{
  "type": "Feature",
  "properties": {
    "iso:country":"GB",
    "wof:name":"CF37 5PG",
    "wof:placetype":"postalcode"
},
  "geometry": {"coordinates":[-3.31982501775242,51.58964984427659],"type":"Point"}
}