{
  "type": "Feature",
  "properties": {
    "date:inception_lower": "2020-01-01",
    "date:inception_upper": "2020-01-01",
    "iso:country": "GB",
    "wof:name": "SA31 3FF",
    "wof:placetype": "postalcode"
  },
  "geometry": {"coordinates":[-4.312887,51.854888],"type":"Point"}
}
