{
  "type": "Feature",
  "properties": {
    "iso:country": "GB",
    "wof:name": "SA31 3FF",
    "wof:placetype": "postalcode"
  },
  "geometry": {"coordinates":[-4.343729,51.850617],"type":"Point"}
}
