{
  "type": "Feature",
  "properties": {
    "iso:country": "GB",
    "wof:name": "TN22 3EL",
    "wof:placetype": "postalcode"
  },
  "geometry": {"coordinates":[0.078398,51.013217],"type":"Point"}
}
