{
  "type": "Feature",
  "properties": {
    "date:inception_lower": "2008-01-01",
    "date:inception_upper": "2008-01-01",
    "iso:country": "GB",
    "wof:name": "EX8 5SZ",
    "wof:placetype": "postalcode"
  },
  "geometry": {"coordinates":[-3.400157,50.642119],"type":"Point"}
}
