{
  "type": "Feature",
  "properties": {
    "iso:country":"GB",
    "wof:name":"PE20 1ER",
    "wof:placetype":"postalcode"
},
  "geometry": {"coordinates":[-0.05869201989758,52.9365754489937],"type":"Point"}
}