{
  "type": "Feature",
  "properties": {
    "date:inception_lower": "2008-02-01",
    "date:inception_upper": "2008-02-01",
    "iso:country": "GB",
    "wof:name": "OX10 0FD",
    "wof:placetype": "postalcode"
  },
  "geometry": {"coordinates":[-1.157121,51.612706],"type":"Point"}
}
