{
  "type": "Feature",
  "properties": {
    "iso:country":"GB",
    "wof:name":"OX10 0FD",
    "wof:placetype":"postalcode"
},
  "geometry": {"coordinates":[-1.15712141694855,51.61270617667422],"type":"Point"}
}