{
  "type": "Feature",
  "properties": {
    "date:inception_lower":"2005-03-01",
    "date:inception_upper":"2005-03-31",
    "iso:country":"GB",
    "wof:name":"HX4 8EH",
    "wof:placetype":"postalcode"
},
  "geometry": {"coordinates":[-1.855238,53.68651],"type":"Point"}
}