{
  "type": "Feature",
  "properties": {
    "iso:country":"GB",
    "wof:name":"HX4 8EH",
    "wof:placetype":"postalcode"
},
  "geometry": {"coordinates":[-1.85523850334685,53.68650970258693],"type":"Point"}
}