{
  "type": "Feature",
  "properties": {
    "iso:country":"GB",
    "wof:name":"CF23 5DT",
    "wof:placetype":"postalcode"
},
  "geometry": {"coordinates":[-3.15991788126596,51.49749190889793],"type":"Point"}
}