{
  "type": "Feature",
  "properties": {
    "iso:country":"GB",
    "wof:name":"LN8 6AH",
    "wof:placetype":"postalcode"
},
  "geometry": {"coordinates":[-0.20367549139725,53.38400341380876],"type":"Point"}
}