{
  "type": "Feature",
  "properties": {
    "date:inception_lower": "1998-12-01",
    "date:inception_upper": "1998-12-01",
    "iso:country": "GB",
    "wof:name": "G66 8AY",
    "wof:placetype": "postalcode"
  },
  "geometry": {"coordinates":[-4.160712,55.95817],"type":"Point"}
}
