{
  "type": "Feature",
  "properties": {
    "iso:country": "GB",
    "wof:name": "TR14 7EF",
    "wof:placetype": "postalcode"
  },
  "geometry": {"coordinates":[-5.30647,50.212714],"type":"Point"}
}
