{
  "type": "Feature",
  "properties": {
    "iso:country":"GB",
    "wof:name":"TR14 7EF",
    "wof:placetype":"postalcode"
},
  "geometry": {"coordinates":[-5.30647008878212,50.21271360961315],"type":"Point"}
}