{
  "type": "Feature",
  "properties": {
    "iso:country": "GB",
    "wof:name": "RG30 1LD",
    "wof:placetype": "postalcode"
  },
  "geometry": {"coordinates":[-1.003702,51.45916],"type":"Point"}
}
