{
  "type": "Feature",
  "properties": {
    "iso:country":"GB",
    "wof:name":"SK11 6PY",
    "wof:placetype":"postalcode"
},
  "geometry": {"coordinates":[-2.12963913255497,53.25844231596083],"type":"Point"}
}