{
  "type": "Feature",
  "properties": {
    "date:inception_lower":"1980-01-01",
    "date:inception_upper":"1980-01-31",
    "iso:country":"GB",
    "wof:name":"TR3 6AT",
    "wof:placetype":"postalcode"
},
  "geometry": {"coordinates":[-5.042733,50.227448],"type":"Point"}
}