{
  "type": "Feature",
  "properties": {
    "iso:country":"GB",
    "wof:name":"TR3 6AT",
    "wof:placetype":"postalcode"
},
  "geometry": {"coordinates":[-5.04273271463045,50.22744752417985],"type":"Point"}
}