{
  "type": "Feature",
  "properties": {
    "iso:country": "GB",
    "wof:name": "KA18 1DS",
    "wof:placetype": "postalcode"
  },
  "geometry": {"coordinates":[-4.267006,55.458873],"type":"Point"}
}
