{
  "type": "Feature",
  "properties": {
    "iso:country": "GB",
    "wof:name": "PH1 5AJ",
    "wof:placetype": "postalcode"
  },
  "geometry": {"coordinates":[-3.443951,56.404317],"type":"Point"}
}
