{
  "type": "Feature",
  "properties": {
    "iso:country": "GB",
    "wof:name": "KY12 8QA",
    "wof:placetype": "postalcode"
  },
  "geometry": {"coordinates":[-3.50768,56.064193],"type":"Point"}
}
