{
  "type": "Feature",
  "properties": {
    "date:inception_lower":"1980-01-01",
    "date:inception_upper":"1980-01-31",
    "iso:country":"GB",
    "wof:name":"KY12 8QA",
    "wof:placetype":"postalcode"
},
  "geometry": {"coordinates":[-3.50768,56.064193],"type":"Point"}
}