{
  "type": "Feature",
  "properties": {
    "iso:country":"GB",
    "wof:name":"AB15 7PH",
    "wof:placetype":"postalcode"
},
  "geometry": {"coordinates":[-2.14177325811602,57.1285607705208],"type":"Point"}
}