{
  "type": "Feature",
  "properties": {
    "iso:country":"GB",
    "wof:name":"CH7 5QH",
    "wof:placetype":"postalcode"
},
  "geometry": {"coordinates":[-3.20646690768553,53.1995664957498],"type":"Point"}
}