{
  "type": "Feature",
  "properties": {
    "iso:country":"GB",
    "wof:name":"SO41 8QL",
    "wof:placetype":"postalcode"
},
  "geometry": {"coordinates":[-1.55120128904674,50.76949935191762],"type":"Point"}
}