{
  "type": "Feature",
  "properties": {
    "iso:country":"GB",
    "wof:name":"TA2 7HY",
    "wof:placetype":"postalcode"
},
  "geometry": {"coordinates":[-3.09615555260857,51.03242718724977],"type":"Point"}
}