{
  "type": "Feature",
  "properties": {
    "date:inception_lower": "2022-10-01",
    "date:inception_upper": "2022-10-01",
    "iso:country": "GB",
    "wof:name": "PR1 9QW",
    "wof:placetype": "postalcode"
  },
  "geometry": {"coordinates":[-2.708154,53.74331],"type":"Point"}
}
