{
  "type": "Feature",
  "properties": {
    "iso:country":"GB",
    "wof:name":"SY1 4UF",
    "wof:placetype":"postalcode"
},
  "geometry": {"coordinates":[-2.71344861156046,52.73717844931342],"type":"Point"}
}