{
  "type": "Feature",
  "properties": {
    "iso:country": "GB",
    "wof:name": "SY1 4UF",
    "wof:placetype": "postalcode"
  },
  "geometry": {"coordinates":[-2.713449,52.737178],"type":"Point"}
}
