{
  "type": "Feature",
  "properties": {
    "iso:country": "GB",
    "wof:name": "M6 6DG",
    "wof:placetype": "postalcode"
  },
  "geometry": {"coordinates":[-2.280074,53.497946],"type":"Point"}
}
