{
  "type": "Feature",
  "properties": {
    "iso:country": "GB",
    "wof:name": "E12 5EE",
    "wof:placetype": "postalcode"
  },
  "geometry": {"coordinates":[0.040501,51.563143],"type":"Point"}
}
