{
  "type": "Feature",
  "properties": {
    "iso:country":"GB",
    "wof:name":"E12 5EE",
    "wof:placetype":"postalcode"
},
  "geometry": {"coordinates":[0.04050093865985,51.56314307572305],"type":"Point"}
}