{
  "type": "Feature",
  "properties": {
    "date:inception_lower": "2006-10-01",
    "date:inception_upper": "2006-10-01",
    "iso:country": "GB",
    "wof:name": "EH22 3NL",
    "wof:placetype": "postalcode"
  },
  "geometry": {"coordinates":[-3.08654,55.894314],"type":"Point"}
}
