{
  "type": "Feature",
  "properties": {
    "iso:country":"GB",
    "wof:name":"EH22 3NL",
    "wof:placetype":"postalcode"
},
  "geometry": {"coordinates":[-3.08653985633696,55.89431406865983],"type":"Point"}
}