{
  "type": "Feature",
  "properties": {
    "iso:country": "GB",
    "wof:name": "G82 4PZ",
    "wof:placetype": "postalcode"
  },
  "geometry": {"coordinates":[-4.585042,55.976052],"type":"Point"}
}
