{
  "type": "Feature",
  "properties": {
    "iso:country": "GB",
    "wof:name": "KA3 7SN",
    "wof:placetype": "postalcode"
  },
  "geometry": {"coordinates":[-4.463772,55.628184],"type":"Point"}
}
