{
  "type": "Feature",
  "properties": {
    "date:inception_lower": "1980-01-01",
    "date:inception_upper": "1980-01-01",
    "iso:country": "GB",
    "wof:name": "KA3 7SN",
    "wof:placetype": "postalcode"
  },
  "geometry": {"coordinates":[-4.463772,55.628184],"type":"Point"}
}
