{
  "type": "Feature",
  "properties": {
    "iso:country":"GB",
    "wof:name":"KA3 7SN",
    "wof:placetype":"postalcode"
},
  "geometry": {"coordinates":[-4.46377185870385,55.62818374006611],"type":"Point"}
}