{
  "type": "Feature",
  "properties": {
    "date:inception_lower": "2016-05-01",
    "date:inception_upper": "2016-05-01",
    "iso:country": "GB",
    "wof:name": "SN5 4GE",
    "wof:placetype": "postalcode"
  },
  "geometry": {"coordinates":[-1.837376,51.582747],"type":"Point"}
}
