{
  "type": "Feature",
  "properties": {
    "iso:country": "GB",
    "wof:name": "SN5 4GE",
    "wof:placetype": "postalcode"
  },
  "geometry": {"coordinates":[-1.837376,51.582747],"type":"Point"}
}
