{
  "type": "Feature",
  "properties": {
    "iso:country":"GB",
    "wof:name":"SR5 1HN",
    "wof:placetype":"postalcode"
},
  "geometry": {"coordinates":[-1.39240377394466,54.91924615644804],"type":"Point"}
}