{
  "type": "Feature",
  "properties": {
    "date:inception_lower": "1980-01-01",
    "date:inception_upper": "1980-01-01",
    "iso:country": "GB",
    "wof:name": "ST16 2PJ",
    "wof:placetype": "postalcode"
  },
  "geometry": {"coordinates":[-2.120961,52.812367],"type":"Point"}
}
