{
  "type": "Feature",
  "properties": {
    "iso:country": "GB",
    "wof:name": "RG2 7HF",
    "wof:placetype": "postalcode"
  },
  "geometry": {"coordinates":[-0.952129,51.438063],"type":"Point"}
}
