{
  "type": "Feature",
  "properties": {
    "iso:country":"GB",
    "wof:name":"RG2 7HF",
    "wof:placetype":"postalcode"
},
  "geometry": {"coordinates":[-0.95212881256466,51.43806334366019],"type":"Point"}
}