{
  "type": "Feature",
  "properties": {
    "iso:country":"GB",
    "wof:name":"NP19 4QX",
    "wof:placetype":"postalcode"
},
  "geometry": {"coordinates":[-2.9017206373004,51.57040924670561],"type":"Point"}
}