{
  "type": "Feature",
  "properties": {
    "iso:country": "GB",
    "wof:name": "NP19 4QX",
    "wof:placetype": "postalcode"
  },
  "geometry": {"coordinates":[-2.901726,51.570411],"type":"Point"}
}
