{
  "type": "Feature",
  "properties": {
    "iso:country": "GB",
    "wof:name": "E11 2SE",
    "wof:placetype": "postalcode"
  },
  "geometry": {"coordinates":[0.018837,51.576341],"type":"Point"}
}
