{
  "type": "Feature",
  "properties": {
    "iso:country":"GB",
    "wof:name":"E11 2SE",
    "wof:placetype":"postalcode"
},
  "geometry": {"coordinates":[0.0188373968104,51.57634131386396],"type":"Point"}
}