{
  "type": "Feature",
  "properties": {
    "date:inception_lower": "1996-06-01",
    "date:inception_upper": "1996-06-01",
    "iso:country": "GB",
    "wof:name": "LL20 7YQ",
    "wof:placetype": "postalcode"
  },
  "geometry": {"coordinates":[-3.088567,52.972073],"type":"Point"}
}
