{
  "type": "Feature",
  "properties": {
    "iso:country":"GB",
    "wof:name":"CA8 7AR",
    "wof:placetype":"postalcode"
},
  "geometry": {"coordinates":[-2.57113106080024,55.00245444124521],"type":"Point"}
}