{
  "type": "Feature",
  "properties": {
    "iso:country":"GB",
    "wof:name":"BB5 6EH",
    "wof:placetype":"postalcode"
},
  "geometry": {"coordinates":[-2.35721345813383,53.75777967437411],"type":"Point"}
}