{
  "type": "Feature",
  "properties": {
    "date:inception_lower": "1980-01-01",
    "date:inception_upper": "1980-01-01",
    "iso:country": "GB",
    "wof:name": "BB5 6EH",
    "wof:placetype": "postalcode"
  },
  "geometry": {"coordinates":[-2.357213,53.75778],"type":"Point"}
}
