{
  "type": "Feature",
  "properties": {
    "iso:country": "GB",
    "wof:name": "CM6 2EQ",
    "wof:placetype": "postalcode"
  },
  "geometry": {"coordinates":[0.318627,51.914306],"type":"Point"}
}
