{
  "type": "Feature",
  "properties": {
    "iso:country":"GB",
    "wof:name":"CM6 2EQ",
    "wof:placetype":"postalcode"
},
  "geometry": {"coordinates":[0.31822675076455,51.91412603846459],"type":"Point"}
}