{
  "type": "Feature",
  "properties": {
    "iso:country": "GB",
    "wof:name": "SG3 6AP",
    "wof:placetype": "postalcode"
  },
  "geometry": {"coordinates":[-0.184972,51.866323],"type":"Point"}
}
