{
  "type": "Feature",
  "properties": {
    "iso:country":"GB",
    "wof:name":"OX44 9PF",
    "wof:placetype":"postalcode"
},
  "geometry": {"coordinates":[-1.2210392706973,51.68542958172453],"type":"Point"}
}