{
  "type": "Feature",
  "properties": {
    "date:inception_lower": "1992-08-01",
    "date:inception_upper": "1992-08-01",
    "iso:country": "GB",
    "wof:name": "OX44 9PF",
    "wof:placetype": "postalcode"
  },
  "geometry": {"coordinates":[-1.221039,51.68543],"type":"Point"}
}
