{
  "type": "Feature",
  "properties": {
    "iso:country":"GB",
    "wof:name":"CA28 6AB",
    "wof:placetype":"postalcode"
},
  "geometry": {"coordinates":[-3.57918317898699,54.55455152776207],"type":"Point"}
}