{
  "type": "Feature",
  "properties": {
    "date:inception_lower": "2020-07-01",
    "date:inception_upper": "2020-07-01",
    "iso:country": "GB",
    "wof:name": "PR3 0DZ",
    "wof:placetype": "postalcode"
  },
  "geometry": {"coordinates":[-2.769991,53.879413],"type":"Point"}
}
