{
  "type": "Feature",
  "properties": {
    "iso:country":"GB",
    "wof:name":"RG5 4HB",
    "wof:placetype":"postalcode"
},
  "geometry": {"coordinates":[-0.88981290163953,51.44894560495718],"type":"Point"}
}