{
  "type": "Feature",
  "properties": {
    "iso:country": "GB",
    "wof:name": "PE28 2UL",
    "wof:placetype": "postalcode"
  },
  "geometry": {"coordinates":[-0.0308,52.407154],"type":"Point"}
}
