{
  "type": "Feature",
  "properties": {
    "iso:country":"GB",
    "wof:name":"PE28 2UL",
    "wof:placetype":"postalcode"
},
  "geometry": {"coordinates":[-0.03079982460531,52.40715403604759],"type":"Point"}
}