{
  "type": "Feature",
  "properties": {
    "iso:country":"GB",
    "wof:name":"RH2 8HR",
    "wof:placetype":"postalcode"
},
  "geometry": {"coordinates":[-0.20999821467141,51.22797750213102],"type":"Point"}
}