{
  "type": "Feature",
  "properties": {
    "iso:country":"GB",
    "wof:name":"TF1 5FF",
    "wof:placetype":"postalcode"
},
  "geometry": {"coordinates":[-2.47295202989768,52.69764959670763],"type":"Point"}
}