{
  "type": "Feature",
  "properties": {
    "date:inception_lower": "2014-09-01",
    "date:inception_upper": "2014-09-01",
    "iso:country": "GB",
    "wof:name": "TF1 5FF",
    "wof:placetype": "postalcode"
  },
  "geometry": {"coordinates":[-2.471731,52.697193],"type":"Point"}
}
