{
  "type": "Feature",
  "properties": {
    "iso:country": "GB",
    "wof:name": "PO40 9AD",
    "wof:placetype": "postalcode"
  },
  "geometry": {"coordinates":[-1.526878,50.683054],"type":"Point"}
}
