{
  "type": "Feature",
  "properties": {
    "iso:country": "GB",
    "wof:name": "CA10 2ND",
    "wof:placetype": "postalcode"
  },
  "geometry": {"coordinates":[-2.856715,54.576924],"type":"Point"}
}
