{
  "type": "Feature",
  "properties": {
    "iso:country":"GB",
    "wof:name":"CA10 2ND",
    "wof:placetype":"postalcode"
},
  "geometry": {"coordinates":[-2.85671482010702,54.57692446935885],"type":"Point"}
}