{
  "type": "Feature",
  "properties": {
    "iso:country": "GB",
    "wof:name": "TN23 4EZ",
    "wof:placetype": "postalcode"
  },
  "geometry": {"coordinates":[0.854186,51.13945],"type":"Point"}
}
