{
  "type": "Feature",
  "properties": {
    "iso:country":"GB",
    "wof:name":"TN23 4EZ",
    "wof:placetype":"postalcode"
},
  "geometry": {"coordinates":[0.85418628410131,51.1394496835121],"type":"Point"}
}