{
  "type": "Feature",
  "properties": {
    "iso:country": "GB",
    "wof:name": "NP10 8GU",
    "wof:placetype": "postalcode"
  },
  "geometry": {"coordinates":[-3.116697,51.585132],"type":"Point"}
}
