{
  "type": "Feature",
  "properties": {
    "iso:country":"GB",
    "wof:name":"EX18 7DB",
    "wof:placetype":"postalcode"
},
  "geometry": {"coordinates":[-3.8695654590918,50.91247791378956],"type":"Point"}
}