{
  "type": "Feature",
  "properties": {
    "iso:country":"GB",
    "wof:name":"BL6 9HY",
    "wof:placetype":"postalcode"
},
  "geometry": {"coordinates":[-2.53891844261191,53.58820167679079],"type":"Point"}
}