{
  "type": "Feature",
  "properties": {
    "date:inception_lower":"2017-01-01",
    "date:inception_upper":"2017-01-31",
    "iso:country":"GB",
    "wof:name":"BL6 9HY",
    "wof:placetype":"postalcode"
},
  "geometry": {"coordinates":[-2.538918,53.588218],"type":"Point"}
}