{
  "type": "Feature",
  "properties": {
    "iso:country":"GB",
    "wof:name":"SY3 0NH",
    "wof:placetype":"postalcode"
},
  "geometry": {"coordinates":[-2.77055792325446,52.67409000837478],"type":"Point"}
}