{
  "type": "Feature",
  "properties": {
    "date:inception_lower": "1998-06-01",
    "date:inception_upper": "1998-06-01",
    "iso:country": "GB",
    "wof:name": "YO8 4PQ",
    "wof:placetype": "postalcode"
  },
  "geometry": {"coordinates":[-1.066534,53.7848],"type":"Point"}
}
