{
  "type": "Feature",
  "properties": {
    "iso:country": "GB",
    "wof:name": "B43 6NS",
    "wof:placetype": "postalcode"
  },
  "geometry": {"coordinates":[-1.935954,52.548655],"type":"Point"}
}
