{
  "type": "Feature",
  "properties": {
    "iso:country":"GB",
    "wof:name":"B43 6NS",
    "wof:placetype":"postalcode"
},
  "geometry": {"coordinates":[-1.93595429579302,52.54865491666306],"type":"Point"}
}