{
  "type": "Feature",
  "properties": {
    "date:inception_lower":"1980-01-01",
    "date:inception_upper":"1980-01-31",
    "iso:country":"GB",
    "wof:name":"LS5 3AT",
    "wof:placetype":"postalcode"
},
  "geometry": {"coordinates":[-1.599797,53.814297],"type":"Point"}
}