{
  "type": "Feature",
  "properties": {
    "iso:country":"GB",
    "wof:name":"LS5 3AT",
    "wof:placetype":"postalcode"
},
  "geometry": {"coordinates":[-1.59979742553658,53.81429713826272],"type":"Point"}
}