{
  "type": "Feature",
  "properties": {
    "iso:country": "GB",
    "wof:name": "E16 2HB",
    "wof:placetype": "postalcode"
  },
  "geometry": {"coordinates":[0.043645,51.500985],"type":"Point"}
}
