{
  "type": "Feature",
  "properties": {
    "iso:country":"GB",
    "wof:name":"E16 2HB",
    "wof:placetype":"postalcode"
},
  "geometry": {"coordinates":[0.04364501492982,51.50098474823161],"type":"Point"}
}