{
  "type": "Feature",
  "properties": {
    "iso:country": "GB",
    "wof:name": "DN22 8RS",
    "wof:placetype": "postalcode"
  },
  "geometry": {"coordinates":[-0.961184,53.371361],"type":"Point"}
}
