{
  "type": "Feature",
  "properties": {
    "iso:country":"GB",
    "wof:name":"DN22 8RS",
    "wof:placetype":"postalcode"
},
  "geometry": {"coordinates":[-0.96118440515272,53.37136063696617],"type":"Point"}
}