{
  "type": "Feature",
  "properties": {
    "iso:country":"GB",
    "wof:name":"KA6 7AT",
    "wof:placetype":"postalcode"
},
  "geometry": {"coordinates":[-4.46466913308548,55.43430487922392],"type":"Point"}
}