{
  "type": "Feature",
  "properties": {
    "iso:country": "GB",
    "wof:name": "DE12 6LJ",
    "wof:placetype": "postalcode"
  },
  "geometry": {"coordinates":[-1.564801,52.739149],"type":"Point"}
}
