{
  "type": "Feature",
  "properties": {
    "iso:country":"GB",
    "wof:name":"RG18 9RQ",
    "wof:placetype":"postalcode"
},
  "geometry": {"coordinates":[-1.26634210412575,51.45512457552123],"type":"Point"}
}