{
  "type": "Feature",
  "properties": {
    "iso:country":"GB",
    "wof:name":"LE2 8QU",
    "wof:placetype":"postalcode"
},
  "geometry": {"coordinates":[-1.13978500106769,52.60428098227381],"type":"Point"}
}