{
  "type": "Feature",
  "properties": {
    "iso:country": "GB",
    "wof:name": "NR12 8DN",
    "wof:placetype": "postalcode"
  },
  "geometry": {"coordinates":[1.412829,52.715044],"type":"Point"}
}
