{
  "type": "Feature",
  "properties": {
    "iso:country":"GB",
    "wof:name":"S32 5QW",
    "wof:placetype":"postalcode"
},
  "geometry": {"coordinates":[-1.67819917399012,53.2863043426099],"type":"Point"}
}