{
  "type": "Feature",
  "properties": {
    "iso:country":"GB",
    "wof:name":"LL53 5UN",
    "wof:placetype":"postalcode"
},
  "geometry": {"coordinates":[-4.44822111452039,52.90670743661559],"type":"Point"}
}