{
  "type": "Feature",
  "properties": {
    "iso:country":"GB",
    "wof:name":"CH1 6EJ",
    "wof:placetype":"postalcode"
},
  "geometry": {"coordinates":[-2.9537250040605,53.22589524884867],"type":"Point"}
}