{
  "type": "Feature",
  "properties": {
    "iso:country":"GB",
    "wof:name":"S2 5LX",
    "wof:placetype":"postalcode"
},
  "geometry": {"coordinates":[-1.45414200292933,53.38070793818002],"type":"Point"}
}