{
  "type": "Feature",
  "properties": {
    "date:inception_lower":"1980-01-01",
    "date:inception_upper":"1980-01-31",
    "iso:country":"GB",
    "wof:name":"S2 5LX",
    "wof:placetype":"postalcode"
},
  "geometry": {"coordinates":[-1.454142,53.380708],"type":"Point"}
}