{
  "type": "Feature",
  "properties": {
    "iso:country":"GB",
    "wof:name":"NN9 6PX",
    "wof:placetype":"postalcode"
},
  "geometry": {"coordinates":[-0.55887860272812,52.32995106866363],"type":"Point"}
}