{
  "type": "Feature",
  "properties": {
    "iso:country":"GB",
    "wof:name":"IV51 9LY",
    "wof:placetype":"postalcode"
},
  "geometry": {"coordinates":[-6.21309096479472,57.41996880329155],"type":"Point"}
}