{
  "type": "Feature",
  "properties": {
    "iso:country":"GB",
    "wof:name":"CO13 0PQ",
    "wof:placetype":"postalcode"
},
  "geometry": {"coordinates":[1.23452904210102,51.84310866176558],"type":"Point"}
}