{
  "type": "Feature",
  "properties": {
    "iso:country":"GB",
    "wof:name":"BS10 5QL",
    "wof:placetype":"postalcode"
},
  "geometry": {"coordinates":[-2.60153415406107,51.50170404538892],"type":"Point"}
}