{
  "type": "Feature",
  "properties": {
    "iso:country":"GB",
    "wof:name":"EX10 8SH",
    "wof:placetype":"postalcode"
},
  "geometry": {"coordinates":[-3.25245780582952,50.681859840562],"type":"Point"}
}