{
  "type": "Feature",
  "properties": {
    "iso:country":"GB",
    "wof:name":"GU8 4TD",
    "wof:placetype":"postalcode"
},
  "geometry": {"coordinates":[-0.60504422730046,51.08681907624807],"type":"Point"}
}