{
  "type": "Feature",
  "properties": {
    "iso:country": "GB",
    "wof:name": "SN10 5EH",
    "wof:placetype": "postalcode"
  },
  "geometry": {"coordinates":[-1.98881,51.339753],"type":"Point"}
}
