{
  "type": "Feature",
  "properties": {
    "date:inception_lower": "1999-06-01",
    "date:inception_upper": "1999-06-01",
    "iso:country": "GB",
    "wof:name": "SN10 5EH",
    "wof:placetype": "postalcode"
  },
  "geometry": {"coordinates":[-1.988746,51.33974],"type":"Point"}
}
