{
  "type": "Feature",
  "properties": {
    "iso:country":"GB",
    "wof:name":"SM7 1AE",
    "wof:placetype":"postalcode"
},
  "geometry": {"coordinates":[-0.21299714161582,51.31541499848003],"type":"Point"}
}