{
  "type": "Feature",
  "properties": {
    "iso:country": "GB",
    "wof:name": "SM7 1AE",
    "wof:placetype": "postalcode"
  },
  "geometry": {"coordinates":[-0.212997,51.315415],"type":"Point"}
}
