{
  "type": "Feature",
  "properties": {
    "iso:country":"GB",
    "wof:name":"AB42 0HL",
    "wof:placetype":"postalcode"
},
  "geometry": {"coordinates":[-1.91369381988195,57.42670672544516],"type":"Point"}
}