{
  "type": "Feature",
  "properties": {
    "date:inception_lower": "2019-04-01",
    "date:inception_upper": "2019-04-01",
    "iso:country": "GB",
    "wof:name": "BS25 5AF",
    "wof:placetype": "postalcode"
  },
  "geometry": {"coordinates":[-2.82832,51.333898],"type":"Point"}
}
