{
  "type": "Feature",
  "properties": {
    "date:inception_lower": "2020-04-01",
    "date:inception_upper": "2020-04-01",
    "iso:country": "GB",
    "wof:name": "BS16 9AQ",
    "wof:placetype": "postalcode"
  },
  "geometry": {"coordinates":[-2.429919,51.480257],"type":"Point"}
}
