{
  "type": "Feature",
  "properties": {
    "date:inception_lower":"1980-01-01",
    "date:inception_upper":"1980-01-31",
    "iso:country":"GB",
    "wof:name":"NE21 6QL",
    "wof:placetype":"postalcode"
},
  "geometry": {"coordinates":[-1.723632,54.950824],"type":"Point"}
}