{
  "type": "Feature",
  "properties": {
    "iso:country":"GB",
    "wof:name":"DD4 0SD",
    "wof:placetype":"postalcode"
},
  "geometry": {"coordinates":[-2.9102310665962,56.48852693262412],"type":"Point"}
}