{
  "type": "Feature",
  "properties": {
    "iso:country": "GB",
    "wof:name": "DD4 0SD",
    "wof:placetype": "postalcode"
  },
  "geometry": {"coordinates":[-2.910231,56.488527],"type":"Point"}
}
