{
  "type": "Feature",
  "properties": {
    "iso:country": "GB",
    "wof:name": "ME15 6AJ",
    "wof:placetype": "postalcode"
  },
  "geometry": {"coordinates":[0.527112,51.254229],"type":"Point"}
}
