{
  "type": "Feature",
  "properties": {
    "date:inception_lower": "2004-05-01",
    "date:inception_upper": "2004-05-01",
    "iso:country": "GB",
    "wof:name": "S35 1RG",
    "wof:placetype": "postalcode"
  },
  "geometry": {"coordinates":[-1.467646,53.455078],"type":"Point"}
}
