{
  "type": "Feature",
  "properties": {
    "date:inception_lower": "1980-01-01",
    "date:inception_upper": "1980-01-01",
    "iso:country": "GB",
    "wof:name": "GU1 2HS",
    "wof:placetype": "postalcode"
  },
  "geometry": {"coordinates":[-0.54999,51.23727],"type":"Point"}
}
