{
  "type": "Feature",
  "properties": {
    "iso:country":"GB",
    "wof:name":"PL7 1NZ",
    "wof:placetype":"postalcode"
},
  "geometry": {"coordinates":[-4.03998289241321,50.3797927337617],"type":"Point"}
}