{
  "type": "Feature",
  "properties": {
    "iso:country": "GB",
    "wof:name": "WV2 3AT",
    "wof:placetype": "postalcode"
  },
  "geometry": {"coordinates":[-2.126642,52.571996],"type":"Point"}
}
