{
  "type": "Feature",
  "properties": {
    "iso:country":"GB",
    "wof:name":"YO21 3TN",
    "wof:placetype":"postalcode"
},
  "geometry": {"coordinates":[-0.69929837379783,54.48951259800828],"type":"Point"}
}