{
  "type": "Feature",
  "properties": {
    "date:inception_lower":"1980-01-01",
    "date:inception_upper":"1980-01-31",
    "iso:country":"GB",
    "wof:name":"YO21 3TN",
    "wof:placetype":"postalcode"
},
  "geometry": {"coordinates":[-0.698434,54.489553],"type":"Point"}
}