{
  "type": "Feature",
  "properties": {
    "iso:country":"GB",
    "wof:name":"OX28 1DD",
    "wof:placetype":"postalcode"
},
  "geometry": {"coordinates":[-1.47813325935518,51.79191436842581],"type":"Point"}
}