{
  "type": "Feature",
  "properties": {
    "date:inception_lower": "1980-01-01",
    "date:inception_upper": "1980-01-01",
    "iso:country": "GB",
    "wof:name": "NE46 4LY",
    "wof:placetype": "postalcode"
  },
  "geometry": {"coordinates":[-2.066409,54.992123],"type":"Point"}
}
