{
  "type": "Feature",
  "properties": {
    "iso:country": "GB",
    "wof:name": "WS13 7AS",
    "wof:placetype": "postalcode"
  },
  "geometry": {"coordinates":[-1.836338,52.68737],"type":"Point"}
}
