{
  "type": "Feature",
  "properties": {
    "iso:country":"GB",
    "wof:name":"W11 1PP",
    "wof:placetype":"postalcode"
},
  "geometry": {"coordinates":[-0.2097310537838,51.51589031749665],"type":"Point"}
}