{
  "type": "Feature",
  "properties": {
    "iso:country":"GB",
    "wof:name":"E5 8DT",
    "wof:placetype":"postalcode"
},
  "geometry": {"coordinates":[-0.05558872529354,51.55437945516298],"type":"Point"}
}