{
  "type": "Feature",
  "properties": {
    "iso:country": "GB",
    "wof:name": "E5 8DT",
    "wof:placetype": "postalcode"
  },
  "geometry": {"coordinates":[-0.055589,51.554379],"type":"Point"}
}
