{
  "type": "Feature",
  "properties": {
    "iso:country":"GB",
    "wof:name":"KA18 4BD",
    "wof:placetype":"postalcode"
},
  "geometry": {"coordinates":[-4.18211554857338,55.39417642320996],"type":"Point"}
}