{
  "type": "Feature",
  "properties": {
    "date:inception_lower": "1980-01-01",
    "date:inception_upper": "1980-01-01",
    "iso:country": "GB",
    "wof:name": "CT11 9ER",
    "wof:placetype": "postalcode"
  },
  "geometry": {"coordinates":[1.415723,51.33205],"type":"Point"}
}
