{
  "type": "Feature",
  "properties": {
    "iso:country":"GB",
    "wof:name":"CT11 9ER",
    "wof:placetype":"postalcode"
},
  "geometry": {"coordinates":[1.41576841519162,51.33204911426999],"type":"Point"}
}