{
  "type": "Feature",
  "properties": {
    "iso:country":"GB",
    "wof:name":"RG5 4QB",
    "wof:placetype":"postalcode"
},
  "geometry": {"coordinates":[-0.89246836128778,51.45874491938558],"type":"Point"}
}