{
  "type": "Feature",
  "properties": {
    "iso:country": "GB",
    "wof:name": "RH4 1EG",
    "wof:placetype": "postalcode"
  },
  "geometry": {"coordinates":[-0.337693,51.233269],"type":"Point"}
}
