{
  "type": "Feature",
  "properties": {
    "iso:country":"GB",
    "wof:name":"RH4 1EG",
    "wof:placetype":"postalcode"
},
  "geometry": {"coordinates":[-0.337692791197,51.23326920606033],"type":"Point"}
}