{
  "type": "Feature",
  "properties": {
    "iso:country":"GB",
    "wof:name":"BR1 5LA",
    "wof:placetype":"postalcode"
},
  "geometry": {"coordinates":[0.00804387492037,51.42921713866269],"type":"Point"}
}