{
  "type": "Feature",
  "properties": {
    "date:inception_lower": "1995-01-01",
    "date:inception_upper": "1995-01-01",
    "iso:country": "GB",
    "wof:name": "BR1 5LA",
    "wof:placetype": "postalcode"
  },
  "geometry": {"coordinates":[0.008044,51.429217],"type":"Point"}
}
