{
  "type": "Feature",
  "properties": {
    "iso:country": "GB",
    "wof:name": "DE65 6LH",
    "wof:placetype": "postalcode"
  },
  "geometry": {"coordinates":[-1.569569,52.882054],"type":"Point"}
}
