{
  "type": "Feature",
  "properties": {
    "date:inception_lower": "1992-08-01",
    "date:inception_upper": "1992-08-01",
    "iso:country": "GB",
    "wof:name": "DE65 6LH",
    "wof:placetype": "postalcode"
  },
  "geometry": {"coordinates":[-1.569569,52.882054],"type":"Point"}
}
