{
  "type": "Feature",
  "properties": {
    "date:inception_lower": "2003-07-01",
    "date:inception_upper": "2003-07-01",
    "iso:country": "GB",
    "wof:name": "SW1P 4AZ",
    "wof:placetype": "postalcode"
  },
  "geometry": {"coordinates":[-0.131115,51.491546],"type":"Point"}
}
