{
  "type": "Feature",
  "properties": {
    "iso:country":"GB",
    "wof:name":"SW1P 4AZ",
    "wof:placetype":"postalcode"
},
  "geometry": {"coordinates":[-0.13140112997216,51.49149483271118],"type":"Point"}
}