{
  "type": "Feature",
  "properties": {
    "date:inception_lower":"1980-01-01",
    "date:inception_upper":"1980-01-31",
    "iso:country":"GB",
    "wof:name":"KA3 5JH",
    "wof:placetype":"postalcode"
},
  "geometry": {"coordinates":[-4.509342,55.693369],"type":"Point"}
}