{
  "type": "Feature",
  "properties": {
    "iso:country":"GB",
    "wof:name":"KA3 5JH",
    "wof:placetype":"postalcode"
},
  "geometry": {"coordinates":[-4.50980254052328,55.6933501199584],"type":"Point"}
}