{
  "type": "Feature",
  "properties": {
    "iso:country":"GB",
    "wof:name":"L22 1RA",
    "wof:placetype":"postalcode"
},
  "geometry": {"coordinates":[-3.02560104902287,53.47202064451662],"type":"Point"}
}