{
  "type": "Feature",
  "properties": {
    "iso:country": "GB",
    "wof:name": "RG10 0HT",
    "wof:placetype": "postalcode"
  },
  "geometry": {"coordinates":[-0.803227,51.475241],"type":"Point"}
}
