{
  "type": "Feature",
  "properties": {
    "date:inception_lower": "1980-01-01",
    "date:inception_upper": "1980-01-01",
    "iso:country": "GB",
    "wof:name": "PA5 8HY",
    "wof:placetype": "postalcode"
  },
  "geometry": {"coordinates":[-4.500615,55.836387],"type":"Point"}
}
