{
  "type": "Feature",
  "properties": {
    "iso:country":"GB",
    "wof:name":"DT4 8LS",
    "wof:placetype":"postalcode"
},
  "geometry": {"coordinates":[-2.4534343375438,50.60543312467389],"type":"Point"}
}