{
  "type": "Feature",
  "properties": {
    "date:inception_lower": "1980-01-01",
    "date:inception_upper": "1980-01-01",
    "iso:country": "GB",
    "wof:name": "DT4 8LS",
    "wof:placetype": "postalcode"
  },
  "geometry": {"coordinates":[-2.453434,50.605433],"type":"Point"}
}
