{
  "type": "Feature",
  "properties": {
    "iso:country": "GB",
    "wof:name": "NG16 6HW",
    "wof:placetype": "postalcode"
  },
  "geometry": {"coordinates":[-1.306757,53.093096],"type":"Point"}
}
