{
  "type": "Feature",
  "properties": {
    "iso:country":"GB",
    "wof:name":"NP16 7HA",
    "wof:placetype":"postalcode"
},
  "geometry": {"coordinates":[-2.65819683248577,51.63556170816506],"type":"Point"}
}