{
  "type": "Feature",
  "properties": {
    "iso:country": "GB",
    "wof:name": "NG34 9RX",
    "wof:placetype": "postalcode"
  },
  "geometry": {"coordinates":[-0.298198,52.985285],"type":"Point"}
}
