{
  "type": "Feature",
  "properties": {
    "date:inception_lower":"1996-06-01",
    "date:inception_upper":"1996-06-30",
    "iso:country":"GB",
    "wof:name":"AB55 5EG",
    "wof:placetype":"postalcode"
},
  "geometry": {"coordinates":[-2.963979,57.541471],"type":"Point"}
}