{
  "type": "Feature",
  "properties": {
    "iso:country":"GB",
    "wof:name":"AB55 5EG",
    "wof:placetype":"postalcode"
},
  "geometry": {"coordinates":[-2.96397920957956,57.54147123848119],"type":"Point"}
}