{
  "type": "Feature",
  "properties": {
    "iso:country":"GB",
    "wof:name":"OX3 7TD",
    "wof:placetype":"postalcode"
},
  "geometry": {"coordinates":[-1.22158120677997,51.75756149485209],"type":"Point"}
}