{
  "type": "Feature",
  "properties": {
    "date:inception_lower": "2012-07-01",
    "date:inception_upper": "2012-07-01",
    "iso:country": "GB",
    "wof:name": "SA4 9FG",
    "wof:placetype": "postalcode"
  },
  "geometry": {"coordinates":[-4.000522,51.675051],"type":"Point"}
}
