{
  "type": "Feature",
  "properties": {
    "iso:country":"GB",
    "wof:name":"SA4 9FG",
    "wof:placetype":"postalcode"
},
  "geometry": {"coordinates":[-4.00052221502546,51.67505112925424],"type":"Point"}
}