{
  "type": "Feature",
  "properties": {
    "iso:country": "GB",
    "wof:name": "SA4 9FG",
    "wof:placetype": "postalcode"
  },
  "geometry": {"coordinates":[-4.000522,51.675051],"type":"Point"}
}
