{
  "type": "Feature",
  "properties": {
    "iso:country":"GB",
    "wof:name":"TN23 5DT",
    "wof:placetype":"postalcode"
},
  "geometry": {"coordinates":[0.84733749505603,51.13526345038893],"type":"Point"}
}