{
  "type": "Feature",
  "properties": {
    "date:inception_lower": "2016-10-01",
    "date:inception_upper": "2016-10-01",
    "iso:country": "GB",
    "wof:name": "PL1 1AE",
    "wof:placetype": "postalcode"
  },
  "geometry": {"coordinates":[-4.138757,50.371087],"type":"Point"}
}
