{
  "type": "Feature",
  "properties": {
    "date:inception_lower": "1983-03-01",
    "date:inception_upper": "1983-03-01",
    "iso:country": "GB",
    "wof:name": "G51 3XJ",
    "wof:placetype": "postalcode"
  },
  "geometry": {"coordinates":[-4.323265,55.860932],"type":"Point"}
}
