{
  "type": "Feature",
  "properties": {
    "date:inception_lower": "1980-01-01",
    "date:inception_upper": "1980-01-01",
    "iso:country": "GB",
    "wof:name": "KT2 6AR",
    "wof:placetype": "postalcode"
  },
  "geometry": {"coordinates":[-0.288636,51.41942],"type":"Point"}
}
