{
  "type": "Feature",
  "properties": {
    "iso:country":"GB",
    "wof:name":"HG4 2QE",
    "wof:placetype":"postalcode"
},
  "geometry": {"coordinates":[-1.53512794723111,54.13359767449272],"type":"Point"}
}