{
  "type": "Feature",
  "properties": {
    "iso:country": "GB",
    "wof:name": "NW6 4ES",
    "wof:placetype": "postalcode"
  },
  "geometry": {"coordinates":[-0.179137,51.543602],"type":"Point"}
}
