{
  "type": "Feature",
  "properties": {
    "iso:country":"GB",
    "wof:name":"NW6 4ES",
    "wof:placetype":"postalcode"
},
  "geometry": {"coordinates":[-0.17913720363848,51.54360167705999],"type":"Point"}
}