{
  "type": "Feature",
  "properties": {
    "iso:country":"GB",
    "wof:name":"BL6 6SL",
    "wof:placetype":"postalcode"
},
  "geometry": {"coordinates":[-2.51445333102151,53.62612340915772],"type":"Point"}
}