{
  "type": "Feature",
  "properties": {
    "date:inception_lower":"1980-01-01",
    "date:inception_upper":"1980-01-31",
    "iso:country":"GB",
    "wof:name":"BL6 6SL",
    "wof:placetype":"postalcode"
},
  "geometry": {"coordinates":[-2.514453,53.626123],"type":"Point"}
}