{
  "type": "Feature",
  "properties": {
    "date:inception_lower": "2023-01-01",
    "date:inception_upper": "2023-01-01",
    "iso:country": "GB",
    "wof:name": "BL6 6SL",
    "wof:placetype": "postalcode"
  },
  "geometry": {"coordinates":[-2.514452,53.626139],"type":"Point"}
}
