{
  "type": "Feature",
  "properties": {
    "iso:country":"GB",
    "wof:name":"BA5 3JD",
    "wof:placetype":"postalcode"
},
  "geometry": {"coordinates":[-2.63011414385719,51.21372632161998],"type":"Point"}
}