{
  "type": "Feature",
  "properties": {
    "iso:country": "GB",
    "wof:name": "BA5 3JD",
    "wof:placetype": "postalcode"
  },
  "geometry": {"coordinates":[-2.630114,51.213726],"type":"Point"}
}
