{
  "type": "Feature",
  "properties": {
    "iso:country":"GB",
    "wof:name":"DT6 3TJ",
    "wof:placetype":"postalcode"
},
  "geometry": {"coordinates":[-2.6826158240421,50.77793097797782],"type":"Point"}
}