{
  "type": "Feature",
  "properties": {
    "iso:country": "GB",
    "wof:name": "DT6 3TJ",
    "wof:placetype": "postalcode"
  },
  "geometry": {"coordinates":[-2.682602,50.77793],"type":"Point"}
}
