{
  "type": "Feature",
  "properties": {
    "date:inception_lower":"1984-10-01",
    "date:inception_upper":"1984-10-31",
    "iso:country":"GB",
    "wof:name":"PE9 2JE",
    "wof:placetype":"postalcode"
},
  "geometry": {"coordinates":[-0.478337,52.651908],"type":"Point"}
}