{
  "type": "Feature",
  "properties": {
    "iso:country":"GB",
    "wof:name":"CO2 7GE",
    "wof:placetype":"postalcode"
},
  "geometry": {"coordinates":[0.89268058177196,51.88299269694149],"type":"Point"}
}