{
  "type": "Feature",
  "properties": {
    "date:inception_lower":"2008-12-01",
    "date:inception_upper":"2008-12-31",
    "iso:country":"GB",
    "wof:name":"CO2 7GE",
    "wof:placetype":"postalcode"
},
  "geometry": {"coordinates":[0.892681,51.882993],"type":"Point"}
}