{
  "type": "Feature",
  "properties": {
    "iso:country":"GB",
    "wof:name":"CM7 1BJ",
    "wof:placetype":"postalcode"
},
  "geometry": {"coordinates":[0.55669590133501,51.86556043670075],"type":"Point"}
}