{
  "type": "Feature",
  "properties": {
    "iso:country":"GB",
    "wof:name":"IG6 3UW",
    "wof:placetype":"postalcode"
},
  "geometry": {"coordinates":[0.12263304920062,51.60880780325501],"type":"Point"}
}