{
  "type": "Feature",
  "properties": {
    "iso:country": "GB",
    "wof:name": "TW16 6NS",
    "wof:placetype": "postalcode"
  },
  "geometry": {"coordinates":[-0.419605,51.415935],"type":"Point"}
}
