{
  "type": "Feature",
  "properties": {
    "iso:country":"GB",
    "wof:name":"TW16 6NS",
    "wof:placetype":"postalcode"
},
  "geometry": {"coordinates":[-0.41960480458584,51.41593512831286],"type":"Point"}
}