{
  "type": "Feature",
  "properties": {
    "iso:country": "GB",
    "wof:name": "DE73 7HF",
    "wof:placetype": "postalcode"
  },
  "geometry": {"coordinates":[-1.471302,52.853701],"type":"Point"}
}
