{
  "type": "Feature",
  "properties": {
    "iso:country":"GB",
    "wof:name":"B62 9HN",
    "wof:placetype":"postalcode"
},
  "geometry": {"coordinates":[-2.02645518303769,52.47272231281568],"type":"Point"}
}