{
  "type": "Feature",
  "properties": {
    "date:inception_lower": "1997-12-01",
    "date:inception_upper": "1997-12-01",
    "iso:country": "GB",
    "wof:name": "B62 9HN",
    "wof:placetype": "postalcode"
  },
  "geometry": {"coordinates":[-2.026552,52.472701],"type":"Point"}
}
