{
  "type": "Feature",
  "properties": {
    "iso:country": "GB",
    "wof:name": "CV36 4GN",
    "wof:placetype": "postalcode"
  },
  "geometry": {"coordinates":[-1.623235,52.056965],"type":"Point"}
}
