{
  "type": "Feature",
  "properties": {
    "iso:country":"GB",
    "wof:name":"WF6 1EA",
    "wof:placetype":"postalcode"
},
  "geometry": {"coordinates":[-1.42417203050425,53.68732628969978],"type":"Point"}
}