{
  "type": "Feature",
  "properties": {
    "iso:country":"GB",
    "wof:name":"M41 0XS",
    "wof:placetype":"postalcode"
},
  "geometry": {"coordinates":[-2.34786522799393,53.45024563815675],"type":"Point"}
}