{
  "type": "Feature",
  "properties": {
    "iso:country": "GB",
    "wof:name": "NN8 5ZU",
    "wof:placetype": "postalcode"
  },
  "geometry": {"coordinates":[-0.715769,52.310776],"type":"Point"}
}
