{
  "type": "Feature",
  "properties": {
    "iso:country":"GB",
    "wof:name":"NN8 5ZU",
    "wof:placetype":"postalcode"
},
  "geometry": {"coordinates":[-0.71576950970676,52.3107760670495],"type":"Point"}
}