{
  "type": "Feature",
  "properties": {
    "iso:country":"GB",
    "wof:name":"BA14 6BY",
    "wof:placetype":"postalcode"
},
  "geometry": {"coordinates":[-2.13271874177003,51.33154979557153],"type":"Point"}
}