{
  "type": "Feature",
  "properties": {
    "date:inception_lower": "1980-01-01",
    "date:inception_upper": "1980-01-01",
    "iso:country": "GB",
    "wof:name": "BA14 6BY",
    "wof:placetype": "postalcode"
  },
  "geometry": {"coordinates":[-2.132719,51.33155],"type":"Point"}
}
