{
  "type": "Feature",
  "properties": {
    "iso:country": "GB",
    "wof:name": "SR2 7HE",
    "wof:placetype": "postalcode"
  },
  "geometry": {"coordinates":[-1.386757,54.897641],"type":"Point"}
}
