{
  "type": "Feature",
  "properties": {
    "iso:country":"GB",
    "wof:name":"G46 6HT",
    "wof:placetype":"postalcode"
},
  "geometry": {"coordinates":[-4.28702317686509,55.80740745288001],"type":"Point"}
}