{
  "type": "Feature",
  "properties": {
    "iso:country":"GB",
    "wof:name":"SA15 5RU",
    "wof:placetype":"postalcode"
},
  "geometry": {"coordinates":[-4.22002610702959,51.75631135695696],"type":"Point"}
}