{
  "type": "Feature",
  "properties": {
    "iso:country": "GB",
    "wof:name": "S35 8NU",
    "wof:placetype": "postalcode"
  },
  "geometry": {"coordinates":[-1.494214,53.439661],"type":"Point"}
}
