{
  "type": "Feature",
  "properties": {
    "iso:country":"GB",
    "wof:name":"S35 8NU",
    "wof:placetype":"postalcode"
},
  "geometry": {"coordinates":[-1.49422863364135,53.43964315677283],"type":"Point"}
}