{
  "type": "Feature",
  "properties": {
    "iso:country":"GB",
    "wof:name":"NN16 0RA",
    "wof:placetype":"postalcode"
},
  "geometry": {"coordinates":[-0.71292973034486,52.4025673901011],"type":"Point"}
}