{
  "type": "Feature",
  "properties": {
    "date:inception_lower": "2021-05-01",
    "date:inception_upper": "2021-05-01",
    "iso:country": "GB",
    "wof:name": "BS34 4AG",
    "wof:placetype": "postalcode"
  },
  "geometry": {"coordinates":[-2.583083,51.521065],"type":"Point"}
}
