{
  "type": "Feature",
  "properties": {
    "date:inception_lower": "1980-01-01",
    "date:inception_upper": "1980-01-01",
    "iso:country": "GB",
    "wof:name": "TW7 4PG",
    "wof:placetype": "postalcode"
  },
  "geometry": {"coordinates":[-0.343962,51.479951],"type":"Point"}
}
