{
  "type": "Feature",
  "properties": {
    "iso:country":"GB",
    "wof:name":"TW7 4PG",
    "wof:placetype":"postalcode"
},
  "geometry": {"coordinates":[-0.34396183700144,51.47995063760415],"type":"Point"}
}