{
  "type": "Feature",
  "properties": {
    "date:inception_lower": "1980-01-01",
    "date:inception_upper": "1980-01-01",
    "iso:country": "GB",
    "wof:name": "BB9 5DF",
    "wof:placetype": "postalcode"
  },
  "geometry": {"coordinates":[-2.228536,53.82488],"type":"Point"}
}
