{
  "type": "Feature",
  "properties": {
    "iso:country": "GB",
    "wof:name": "BB9 5DF",
    "wof:placetype": "postalcode"
  },
  "geometry": {"coordinates":[-2.228534,53.824857],"type":"Point"}
}
