{
  "type": "Feature",
  "properties": {
    "iso:country":"GB",
    "wof:name":"NG5 9HT",
    "wof:placetype":"postalcode"
},
  "geometry": {"coordinates":[-1.16951371228441,53.00667489723786],"type":"Point"}
}