{
  "type": "Feature",
  "properties": {
    "iso:country":"GB",
    "wof:name":"SR8 3PA",
    "wof:placetype":"postalcode"
},
  "geometry": {"coordinates":[-1.33995293816132,54.78846975073006],"type":"Point"}
}