{
  "type": "Feature",
  "properties": {
    "iso:country": "GB",
    "wof:name": "SR8 3PA",
    "wof:placetype": "postalcode"
  },
  "geometry": {"coordinates":[-1.340092,54.788453],"type":"Point"}
}
