{
  "type": "Feature",
  "properties": {
    "date:inception_lower": "2010-04-01",
    "date:inception_upper": "2010-04-01",
    "iso:country": "GB",
    "wof:name": "BD10 0JW",
    "wof:placetype": "postalcode"
  },
  "geometry": {"coordinates":[-1.709852,53.818101],"type":"Point"}
}
