{
  "type": "Feature",
  "properties": {
    "iso:country":"GB",
    "wof:name":"BD10 0JW",
    "wof:placetype":"postalcode"
},
  "geometry": {"coordinates":[-1.7098520148474,53.81810091212442],"type":"Point"}
}