{
  "type": "Feature",
  "properties": {
    "iso:country":"GB",
    "wof:name":"TR2 5ND",
    "wof:placetype":"postalcode"
},
  "geometry": {"coordinates":[-4.99116537567683,50.2163826479018],"type":"Point"}
}