{
  "type": "Feature",
  "properties": {
    "date:inception_lower": "1980-01-01",
    "date:inception_upper": "1980-01-01",
    "iso:country": "GB",
    "wof:name": "TR2 5ND",
    "wof:placetype": "postalcode"
  },
  "geometry": {"coordinates":[-4.991165,50.216383],"type":"Point"}
}
