{
  "type": "Feature",
  "properties": {
    "iso:country": "GB",
    "wof:name": "TR2 5ND",
    "wof:placetype": "postalcode"
  },
  "geometry": {"coordinates":[-4.991165,50.216383],"type":"Point"}
}
