{
  "type": "Feature",
  "properties": {
    "date:inception_lower": "2020-10-01",
    "date:inception_upper": "2020-10-01",
    "iso:country": "GB",
    "wof:name": "OL6 7DB",
    "wof:placetype": "postalcode"
  },
  "geometry": {"coordinates":[-2.100167,53.48802],"type":"Point"}
}
