{
  "type": "Feature",
  "properties": {
    "iso:country":"GB",
    "wof:name":"NP22 4HY",
    "wof:placetype":"postalcode"
},
  "geometry": {"coordinates":[-3.23602195537194,51.76256421199772],"type":"Point"}
}