{
  "type": "Feature",
  "properties": {
    "iso:country":"GB",
    "wof:name":"AB41 8AJ",
    "wof:placetype":"postalcode"
},
  "geometry": {"coordinates":[-2.06291883413269,57.37219558835647],"type":"Point"}
}