{
  "type": "Feature",
  "properties": {
    "iso:country":"GB",
    "wof:name":"DE3 0TY",
    "wof:placetype":"postalcode"
},
  "geometry": {"coordinates":[-1.54923571860228,52.90546840071568],"type":"Point"}
}