{
  "type": "Feature",
  "properties": {
    "date:inception_lower": "1995-07-01",
    "date:inception_upper": "1995-07-01",
    "iso:country": "GB",
    "wof:name": "RG6 5XD",
    "wof:placetype": "postalcode"
  },
  "geometry": {"coordinates":[-0.93044,51.4316],"type":"Point"}
}
