{
  "type": "Feature",
  "properties": {
    "iso:country":"GB",
    "wof:name":"E11 3NE",
    "wof:placetype":"postalcode"
},
  "geometry": {"coordinates":[0.01264359302205,51.55733840377768],"type":"Point"}
}