{
  "type": "Feature",
  "properties": {
    "iso:country": "GB",
    "wof:name": "E11 3NE",
    "wof:placetype": "postalcode"
  },
  "geometry": {"coordinates":[0.012644,51.557338],"type":"Point"}
}
