{
  "type": "Feature",
  "properties": {
    "iso:country":"GB",
    "wof:name":"PO6 1RG",
    "wof:placetype":"postalcode"
},
  "geometry": {"coordinates":[-1.03378224161338,50.84256679062849],"type":"Point"}
}