{
  "type": "Feature",
  "properties": {
    "iso:country":"GB",
    "wof:name":"DN3 3BJ",
    "wof:placetype":"postalcode"
},
  "geometry": {"coordinates":[-1.05585841436264,53.53308282920115],"type":"Point"}
}