{
  "type": "Feature",
  "properties": {
    "iso:country":"GB",
    "wof:name":"HA1 1UU",
    "wof:placetype":"postalcode"
},
  "geometry": {"coordinates":[-0.33962917007879,51.58965789380428],"type":"Point"}
}