{
  "type": "Feature",
  "properties": {
    "iso:country": "GB",
    "wof:name": "HA1 1UU",
    "wof:placetype": "postalcode"
  },
  "geometry": {"coordinates":[-0.339629,51.589658],"type":"Point"}
}
