{
  "type": "Feature",
  "properties": {
    "iso:country": "GB",
    "wof:name": "RG7 5TT",
    "wof:placetype": "postalcode"
  },
  "geometry": {"coordinates":[-1.187798,51.408371],"type":"Point"}
}
