{
  "type": "Feature",
  "properties": {
    "date:inception_lower": "1980-01-01",
    "date:inception_upper": "1980-01-01",
    "iso:country": "GB",
    "wof:name": "G33 2EG",
    "wof:placetype": "postalcode"
  },
  "geometry": {"coordinates":[-4.194437,55.86647],"type":"Point"}
}
