{
  "type": "Feature",
  "properties": {
    "iso:country":"GB",
    "wof:name":"WF15 6LP",
    "wof:placetype":"postalcode"
},
  "geometry": {"coordinates":[-1.69706517215186,53.71652246657917],"type":"Point"}
}