{
  "type": "Feature",
  "properties": {
    "date:inception_lower": "1980-01-01",
    "date:inception_upper": "1980-01-01",
    "iso:country": "GB",
    "wof:name": "WF15 6LP",
    "wof:placetype": "postalcode"
  },
  "geometry": {"coordinates":[-1.697065,53.716522],"type":"Point"}
}
