{
  "type": "Feature",
  "properties": {
    "iso:country": "GB",
    "wof:name": "CM3 6DS",
    "wof:placetype": "postalcode"
  },
  "geometry": {"coordinates":[0.774635,51.646265],"type":"Point"}
}
