{
  "type": "Feature",
  "properties": {
    "iso:country":"GB",
    "wof:name":"CM3 6DS",
    "wof:placetype":"postalcode"
},
  "geometry": {"coordinates":[0.77521969674842,51.64732434758558],"type":"Point"}
}