{
  "type": "Feature",
  "properties": {
    "date:inception_lower": "1980-01-01",
    "date:inception_upper": "1980-01-01",
    "iso:country": "GB",
    "wof:name": "BN14 9AG",
    "wof:placetype": "postalcode"
  },
  "geometry": {"coordinates":[-0.371374,50.827855],"type":"Point"}
}
