{
  "type": "Feature",
  "properties": {
    "iso:country":"GB",
    "wof:name":"RG7 5LW",
    "wof:placetype":"postalcode"
},
  "geometry": {"coordinates":[-1.1424530497116,51.42130234022753],"type":"Point"}
}