{
  "type": "Feature",
  "properties": {
    "iso:country":"GB",
    "wof:name":"L14 0JB",
    "wof:placetype":"postalcode"
},
  "geometry": {"coordinates":[-2.8787032085933,53.4148271977789],"type":"Point"}
}