{
  "type": "Feature",
  "properties": {
    "iso:country": "GB",
    "wof:name": "L14 0JB",
    "wof:placetype": "postalcode"
  },
  "geometry": {"coordinates":[-2.878703,53.414827],"type":"Point"}
}
