{
  "type": "Feature",
  "properties": {
    "iso:country":"GB",
    "wof:name":"DY5 2BT",
    "wof:placetype":"postalcode"
},
  "geometry": {"coordinates":[-2.12053143713092,52.4744616571014],"type":"Point"}
}