{
  "type": "Feature",
  "properties": {
    "iso:country":"GB",
    "wof:name":"UB10 0BN",
    "wof:placetype":"postalcode"
},
  "geometry": {"coordinates":[-0.45745253819625,51.54152116183091],"type":"Point"}
}