{
  "type": "Feature",
  "properties": {
    "date:inception_lower":"1980-01-01",
    "date:inception_upper":"1980-01-31",
    "iso:country":"GB",
    "wof:name":"SS11 8HL",
    "wof:placetype":"postalcode"
},
  "geometry": {"coordinates":[0.530788,51.616373],"type":"Point"}
}