{
  "type": "Feature",
  "properties": {
    "iso:country":"GB",
    "wof:name":"BS4 4RR",
    "wof:placetype":"postalcode"
},
  "geometry": {"coordinates":[-2.53592216349966,51.44247997941481],"type":"Point"}
}