{
  "type": "Feature",
  "properties": {
    "date:inception_lower": "1980-01-01",
    "date:inception_upper": "1980-01-01",
    "iso:country": "GB",
    "wof:name": "CM14 5SG",
    "wof:placetype": "postalcode"
  },
  "geometry": {"coordinates":[0.254228,51.650005],"type":"Point"}
}
