{
  "type": "Feature",
  "properties": {
    "iso:country":"GB",
    "wof:name":"WR4 0PJ",
    "wof:placetype":"postalcode"
},
  "geometry": {"coordinates":[-2.17582507967795,52.19651450205056],"type":"Point"}
}