{
  "type": "Feature",
  "properties": {
    "iso:country":"GB",
    "wof:name":"DH8 8PX",
    "wof:placetype":"postalcode"
},
  "geometry": {"coordinates":[-1.84990639966597,54.85981570014606],"type":"Point"}
}