{
  "type": "Feature",
  "properties": {
    "iso:country":"GB",
    "wof:name":"IP7 5AL",
    "wof:placetype":"postalcode"
},
  "geometry": {"coordinates":[0.95434937815346,52.04351555627156],"type":"Point"}
}