{
  "type": "Feature",
  "properties": {
    "date:inception_lower": "1980-01-01",
    "date:inception_upper": "1980-01-01",
    "iso:country": "GB",
    "wof:name": "OX16 0QH",
    "wof:placetype": "postalcode"
  },
  "geometry": {"coordinates":[-1.357864,52.059933],"type":"Point"}
}
