{
  "type": "Feature",
  "properties": {
    "iso:country":"GB",
    "wof:name":"WV10 0TD",
    "wof:placetype":"postalcode"
},
  "geometry": {"coordinates":[-2.1146322368434,52.59477009379513],"type":"Point"}
}