{
  "type": "Feature",
  "properties": {
    "date:inception_lower": "1992-01-01",
    "date:inception_upper": "1992-01-01",
    "iso:country": "GB",
    "wof:name": "WV10 0TD",
    "wof:placetype": "postalcode"
  },
  "geometry": {"coordinates":[-2.114632,52.59477],"type":"Point"}
}
