{
  "type": "Feature",
  "properties": {
    "date:inception_lower": "1980-01-01",
    "date:inception_upper": "1980-01-01",
    "iso:country": "GB",
    "wof:name": "KT6 6HA",
    "wof:placetype": "postalcode"
  },
  "geometry": {"coordinates":[-0.298227,51.389811],"type":"Point"}
}
