{
  "type": "Feature",
  "properties": {
    "iso:country":"GB",
    "wof:name":"KT6 6HA",
    "wof:placetype":"postalcode"
},
  "geometry": {"coordinates":[-0.29824972305328,51.38981236213052],"type":"Point"}
}