{
  "type": "Feature",
  "properties": {
    "iso:country":"GB",
    "wof:name":"S5 8QH",
    "wof:placetype":"postalcode"
},
  "geometry": {"coordinates":[-1.47998568385358,53.41389255305424],"type":"Point"}
}