{
  "type": "Feature",
  "properties": {
    "iso:country": "GB",
    "wof:name": "W5 9SJ",
    "wof:placetype": "postalcode"
  },
  "geometry": {"coordinates":[-0.30727,51.513328],"type":"Point"}
}
