{
  "type": "Feature",
  "properties": {
    "iso:country":"GB",
    "wof:name":"TS5 6PS",
    "wof:placetype":"postalcode"
},
  "geometry": {"coordinates":[-1.23764139550281,54.55919855945946],"type":"Point"}
}