{
  "type": "Feature",
  "properties": {
    "iso:country": "GB",
    "wof:name": "S1 2FN",
    "wof:placetype": "postalcode"
  },
  "geometry": {"coordinates":[-1.469659,53.378027],"type":"Point"}
}
