{
  "type": "Feature",
  "properties": {
    "date:inception_lower":"2013-11-01",
    "date:inception_upper":"2013-11-30",
    "iso:country":"GB",
    "wof:name":"S1 2FN",
    "wof:placetype":"postalcode"
},
  "geometry": {"coordinates":[-1.469704,53.377983],"type":"Point"}
}