{
  "type": "Feature",
  "properties": {
    "iso:country":"GB",
    "wof:name":"NP7 8PA",
    "wof:placetype":"postalcode"
},
  "geometry": {"coordinates":[-2.89178238238845,51.86703886278899],"type":"Point"}
}