{
  "type": "Feature",
  "properties": {
    "iso:country":"GB",
    "wof:name":"CO6 1JH",
    "wof:placetype":"postalcode"
},
  "geometry": {"coordinates":[0.74988825351841,51.90042106306496],"type":"Point"}
}