{
  "type": "Feature",
  "properties": {
    "date:inception_lower":"1996-06-01",
    "date:inception_upper":"1996-06-30",
    "iso:country":"GB",
    "wof:name":"AB24 5NS",
    "wof:placetype":"postalcode"
},
  "geometry": {"coordinates":[-2.078217,57.151041],"type":"Point"}
}