{
  "type": "Feature",
  "properties": {
    "date:inception_lower":"1980-01-01",
    "date:inception_upper":"1980-01-31",
    "iso:country":"GB",
    "wof:name":"KY11 4AY",
    "wof:placetype":"postalcode"
},
  "geometry": {"coordinates":[-3.438618,56.066051],"type":"Point"}
}