{
  "type": "Feature",
  "properties": {
    "iso:country":"GB",
    "wof:name":"KY11 4AY",
    "wof:placetype":"postalcode"
},
  "geometry": {"coordinates":[-3.43861818623058,56.06605116747916],"type":"Point"}
}