{
  "type": "Feature",
  "properties": {
    "iso:country": "GB",
    "wof:name": "NG21 9LR",
    "wof:placetype": "postalcode"
  },
  "geometry": {"coordinates":[-1.075417,53.196114],"type":"Point"}
}
