{
  "type": "Feature",
  "properties": {
    "iso:country":"GB",
    "wof:name":"NG21 9LR",
    "wof:placetype":"postalcode"
},
  "geometry": {"coordinates":[-1.0754166636233,53.19611417911314],"type":"Point"}
}