{
  "type": "Feature",
  "properties": {
    "iso:country": "GB",
    "wof:name": "GU12 6NJ",
    "wof:placetype": "postalcode"
  },
  "geometry": {"coordinates":[-0.71848,51.242374],"type":"Point"}
}
