{
  "type": "Feature",
  "properties": {
    "date:inception_lower": "1980-01-01",
    "date:inception_upper": "1980-01-01",
    "iso:country": "GB",
    "wof:name": "GU12 6NJ",
    "wof:placetype": "postalcode"
  },
  "geometry": {"coordinates":[-0.718225,51.242621],"type":"Point"}
}
