{
  "type": "Feature",
  "properties": {
    "iso:country": "GB",
    "wof:name": "HU9 1TX",
    "wof:placetype": "postalcode"
  },
  "geometry": {"coordinates":[-0.326175,53.740058],"type":"Point"}
}
