{
  "type": "Feature",
  "properties": {
    "iso:country": "GB",
    "wof:name": "IV4 7HQ",
    "wof:placetype": "postalcode"
  },
  "geometry": {"coordinates":[-4.488394,57.440921],"type":"Point"}
}
