{
  "type": "Feature",
  "properties": {
    "date:inception_lower": "1980-01-01",
    "date:inception_upper": "1980-01-01",
    "iso:country": "GB",
    "wof:name": "IV4 7HQ",
    "wof:placetype": "postalcode"
  },
  "geometry": {"coordinates":[-4.488394,57.440921],"type":"Point"}
}
