{
  "type": "Feature",
  "properties": {
    "iso:country":"GB",
    "wof:name":"IV4 7HQ",
    "wof:placetype":"postalcode"
},
  "geometry": {"coordinates":[-4.48839397462503,57.44092087066932],"type":"Point"}
}