{
  "type": "Feature",
  "properties": {
    "iso:country":"GB",
    "wof:name":"WA1 3RG",
    "wof:placetype":"postalcode"
},
  "geometry": {"coordinates":[-2.56644509172332,53.39730159971698],"type":"Point"}
}