{
  "type": "Feature",
  "properties": {
    "iso:country": "GB",
    "wof:name": "PH50 4RQ",
    "wof:placetype": "postalcode"
  },
  "geometry": {"coordinates":[-4.956962,56.715095],"type":"Point"}
}
