{
  "type": "Feature",
  "properties": {
    "date:inception_lower": "2000-12-01",
    "date:inception_upper": "2000-12-01",
    "iso:country": "GB",
    "wof:name": "PH50 4RQ",
    "wof:placetype": "postalcode"
  },
  "geometry": {"coordinates":[-4.956962,56.715095],"type":"Point"}
}
