{
  "type": "Feature",
  "properties": {
    "iso:country":"GB",
    "wof:name":"PH50 4RQ",
    "wof:placetype":"postalcode"
},
  "geometry": {"coordinates":[-4.957022398084,56.71508396128242],"type":"Point"}
}