{
  "type": "Feature",
  "properties": {
    "date:inception_lower": "1998-12-01",
    "date:inception_upper": "1998-12-01",
    "iso:country": "GB",
    "wof:name": "EC3V 3PF",
    "wof:placetype": "postalcode"
  },
  "geometry": {"coordinates":[-0.085355,51.513314],"type":"Point"}
}
