{
  "type": "Feature",
  "properties": {
    "iso:country":"GB",
    "wof:name":"EC3V 3PF",
    "wof:placetype":"postalcode"
},
  "geometry": {"coordinates":[-0.08535520625765,51.51331445983456],"type":"Point"}
}