{
  "type": "Feature",
  "properties": {
    "iso:country":"GB",
    "wof:name":"G77 6HA",
    "wof:placetype":"postalcode"
},
  "geometry": {"coordinates":[-4.32710021771088,55.77993477860902],"type":"Point"}
}