{
  "type": "Feature",
  "properties": {
    "iso:country":"GB",
    "wof:name":"E17 8BZ",
    "wof:placetype":"postalcode"
},
  "geometry": {"coordinates":[-0.03155529952172,51.57645110098759],"type":"Point"}
}