{
  "type": "Feature",
  "properties": {
    "date:inception_lower":"1980-01-01",
    "date:inception_upper":"1980-01-31",
    "iso:country":"GB",
    "wof:name":"E17 8BZ",
    "wof:placetype":"postalcode"
},
  "geometry": {"coordinates":[-0.031555,51.576451],"type":"Point"}
}