{
  "type": "Feature",
  "properties": {
    "iso:country": "GB",
    "wof:name": "NR7 9RP",
    "wof:placetype": "postalcode"
  },
  "geometry": {"coordinates":[1.340782,52.646695],"type":"Point"}
}
