{
  "type": "Feature",
  "properties": {
    "iso:country": "GB",
    "wof:name": "BB2 2BZ",
    "wof:placetype": "postalcode"
  },
  "geometry": {"coordinates":[-2.483271,53.747334],"type":"Point"}
}
