{
  "type": "Feature",
  "properties": {
    "iso:country":"GB",
    "wof:name":"BD22 6JU",
    "wof:placetype":"postalcode"
},
  "geometry": {"coordinates":[-1.92371616140621,53.86732119655417],"type":"Point"}
}