{
  "type": "Feature",
  "properties": {
    "date:inception_lower": "2018-05-01",
    "date:inception_upper": "2018-05-01",
    "iso:country": "GB",
    "wof:name": "LE8 6PL",
    "wof:placetype": "postalcode"
  },
  "geometry": {"coordinates":[-1.183804,52.567203],"type":"Point"}
}
