{
  "type": "Feature",
  "properties": {
    "iso:country":"GB",
    "wof:name":"WD25 0AQ",
    "wof:placetype":"postalcode"
},
  "geometry": {"coordinates":[-0.40016783784757,51.68220862361245],"type":"Point"}
}