{
  "type": "Feature",
  "properties": {
    "iso:country":"GB",
    "wof:name":"PL13 1BG",
    "wof:placetype":"postalcode"
},
  "geometry": {"coordinates":[-4.45267367272698,50.35453010316709],"type":"Point"}
}