{
  "type": "Feature",
  "properties": {
    "iso:country": "GB",
    "wof:name": "PL13 1BG",
    "wof:placetype": "postalcode"
  },
  "geometry": {"coordinates":[-4.452674,50.35453],"type":"Point"}
}
