{
  "type": "Feature",
  "properties": {
    "iso:country":"GB",
    "wof:name":"CV7 9AA",
    "wof:placetype":"postalcode"
},
  "geometry": {"coordinates":[-1.50052727700977,52.46314052276835],"type":"Point"}
}