{
  "type": "Feature",
  "properties": {
    "iso:country": "GB",
    "wof:name": "AL7 2AT",
    "wof:placetype": "postalcode"
  },
  "geometry": {"coordinates":[-0.178021,51.802867],"type":"Point"}
}
