{
  "type": "Feature",
  "properties": {
    "iso:country":"GB",
    "wof:name":"PO13 0RA",
    "wof:placetype":"postalcode"
},
  "geometry": {"coordinates":[-1.18237764605487,50.8229111167832],"type":"Point"}
}