{
  "type": "Feature",
  "properties": {
    "iso:country":"GB",
    "wof:name":"IP26 4RG",
    "wof:placetype":"postalcode"
},
  "geometry": {"coordinates":[0.55227359401443,52.54182779113643],"type":"Point"}
}