{
  "type": "Feature",
  "properties": {
    "iso:country":"GB",
    "wof:name":"LE3 0TH",
    "wof:placetype":"postalcode"
},
  "geometry": {"coordinates":[-1.16021421291325,52.63322250414123],"type":"Point"}
}