{
  "type": "Feature",
  "properties": {
    "iso:country": "GB",
    "wof:name": "LE3 0TH",
    "wof:placetype": "postalcode"
  },
  "geometry": {"coordinates":[-1.160296,52.63325],"type":"Point"}
}
