{
  "type": "Feature",
  "properties": {
    "date:inception_lower":"1980-01-01",
    "date:inception_upper":"1980-01-31",
    "iso:country":"GB",
    "wof:name":"LE3 0TH",
    "wof:placetype":"postalcode"
},
  "geometry": {"coordinates":[-1.160214,52.633222],"type":"Point"}
}