{
  "type": "Feature",
  "properties": {
    "iso:country":"GB",
    "wof:name":"DL10 7TX",
    "wof:placetype":"postalcode"
},
  "geometry": {"coordinates":[-1.65097598108264,54.39803598601912],"type":"Point"}
}