{
  "type": "Feature",
  "properties": {
    "iso:country": "GB",
    "wof:name": "DL10 7TX",
    "wof:placetype": "postalcode"
  },
  "geometry": {"coordinates":[-1.650976,54.398036],"type":"Point"}
}
