{
  "type": "Feature",
  "properties": {
    "iso:country":"GB",
    "wof:name":"LL11 5LR",
    "wof:placetype":"postalcode"
},
  "geometry": {"coordinates":[-3.06319830254489,53.08386267049852],"type":"Point"}
}