{
  "type": "Feature",
  "properties": {
    "iso:country": "GB",
    "wof:name": "LL11 5LR",
    "wof:placetype": "postalcode"
  },
  "geometry": {"coordinates":[-3.063198,53.083863],"type":"Point"}
}
