{
  "type": "Feature",
  "properties": {
    "date:inception_lower": "2004-11-01",
    "date:inception_upper": "2004-11-01",
    "iso:country": "GB",
    "wof:name": "NP8 1LJ",
    "wof:placetype": "postalcode"
  },
  "geometry": {"coordinates":[-3.151601,51.849029],"type":"Point"}
}
