{
  "type": "Feature",
  "properties": {
    "iso:country":"GB",
    "wof:name":"NP8 1LJ",
    "wof:placetype":"postalcode"
},
  "geometry": {"coordinates":[-3.15160086731955,51.84902912004961],"type":"Point"}
}