{
  "type": "Feature",
  "properties": {
    "iso:country": "GB",
    "wof:name": "SA39 9HR",
    "wof:placetype": "postalcode"
  },
  "geometry": {"coordinates":[-4.265594,51.997179],"type":"Point"}
}
