{
  "type": "Feature",
  "properties": {
    "iso:country":"GB",
    "wof:name":"WA12 8HR",
    "wof:placetype":"postalcode"
},
  "geometry": {"coordinates":[-2.62433352848668,53.45090892255467],"type":"Point"}
}