{
  "type": "Feature",
  "properties": {
    "iso:country": "GB",
    "wof:name": "TF1 2JP",
    "wof:placetype": "postalcode"
  },
  "geometry": {"coordinates":[-2.502641,52.690408],"type":"Point"}
}
