{
  "type": "Feature",
  "properties": {
    "iso:country":"GB",
    "wof:name":"TF1 2JP",
    "wof:placetype":"postalcode"
},
  "geometry": {"coordinates":[-2.50264110556827,52.69040752012975],"type":"Point"}
}