{
  "type": "Feature",
  "properties": {
    "iso:country":"GB",
    "wof:name":"DG5 4HY",
    "wof:placetype":"postalcode"
},
  "geometry": {"coordinates":[-3.8108394486502,54.93214588285873],"type":"Point"}
}