{
  "type": "Feature",
  "properties": {
    "iso:country":"GB",
    "wof:name":"GU47 0DU",
    "wof:placetype":"postalcode"
},
  "geometry": {"coordinates":[-0.78471144415045,51.34988992901598],"type":"Point"}
}