{
  "type": "Feature",
  "properties": {
    "iso:country":"GB",
    "wof:name":"IP5 1JJ",
    "wof:placetype":"postalcode"
},
  "geometry": {"coordinates":[1.23387623310097,52.06124512585819],"type":"Point"}
}