{
  "type": "Feature",
  "properties": {
    "iso:country": "GB",
    "wof:name": "SR3 3ND",
    "wof:placetype": "postalcode"
  },
  "geometry": {"coordinates":[-1.435783,54.876266],"type":"Point"}
}
