{
  "type": "Feature",
  "properties": {
    "iso:country":"GB",
    "wof:name":"SR3 3ND",
    "wof:placetype":"postalcode"
},
  "geometry": {"coordinates":[-1.43578309521534,54.87626627510503],"type":"Point"}
}