{
  "type": "Feature",
  "properties": {
    "iso:country": "GB",
    "wof:name": "LA9 6NH",
    "wof:placetype": "postalcode"
  },
  "geometry": {"coordinates":[-2.7404,54.341526],"type":"Point"}
}
