{
  "type": "Feature",
  "properties": {
    "iso:country":"GB",
    "wof:name":"LA9 6NH",
    "wof:placetype":"postalcode"
},
  "geometry": {"coordinates":[-2.74040045397805,54.34152645572929],"type":"Point"}
}