{
  "type": "Feature",
  "properties": {
    "date:inception_lower": "1980-01-01",
    "date:inception_upper": "1980-01-01",
    "iso:country": "GB",
    "wof:name": "TS27 4LB",
    "wof:placetype": "postalcode"
  },
  "geometry": {"coordinates":[-1.29093,54.747924],"type":"Point"}
}
