{
  "type": "Feature",
  "properties": {
    "iso:country":"GB",
    "wof:name":"RM6 6EE",
    "wof:placetype":"postalcode"
},
  "geometry": {"coordinates":[0.14484848802517,51.57238793121324],"type":"Point"}
}