{
  "type": "Feature",
  "properties": {
    "iso:country":"GB",
    "wof:name":"HP7 0ND",
    "wof:placetype":"postalcode"
},
  "geometry": {"coordinates":[-0.6298142068598,51.6611305380821],"type":"Point"}
}