{
  "type": "Feature",
  "properties": {
    "iso:country":"GB",
    "wof:name":"EC1N 8AS",
    "wof:placetype":"postalcode"
},
  "geometry": {"coordinates":[-0.1076447689054,51.52180546323857],"type":"Point"}
}