{
  "type": "Feature",
  "properties": {
    "date:inception_lower":"2014-09-01",
    "date:inception_upper":"2014-09-30",
    "iso:country":"GB",
    "wof:name":"EC1N 8AS",
    "wof:placetype":"postalcode"
},
  "geometry": {"coordinates":[-0.107645,51.521805],"type":"Point"}
}