{
  "type": "Feature",
  "properties": {
    "iso:country":"GB",
    "wof:name":"CF39 8DP",
    "wof:placetype":"postalcode"
},
  "geometry": {"coordinates":[-3.43918565753812,51.58032466126102],"type":"Point"}
}