{
  "type": "Feature",
  "properties": {
    "iso:country":"GB",
    "wof:name":"G66 7HF",
    "wof:placetype":"postalcode"
},
  "geometry": {"coordinates":[-4.2035106963217,55.97663589834188],"type":"Point"}
}