{
  "type": "Feature",
  "properties": {
    "iso:country": "GB",
    "wof:name": "G66 7HF",
    "wof:placetype": "postalcode"
  },
  "geometry": {"coordinates":[-4.203511,55.976636],"type":"Point"}
}
