{
  "type": "Feature",
  "properties": {
    "date:inception_lower": "2016-02-01",
    "date:inception_upper": "2016-02-01",
    "iso:country": "GB",
    "wof:name": "PE10 0FU",
    "wof:placetype": "postalcode"
  },
  "geometry": {"coordinates":[-0.373271,52.761035],"type":"Point"}
}
