{
  "type": "Feature",
  "properties": {
    "iso:country": "GB",
    "wof:name": "PE10 0FU",
    "wof:placetype": "postalcode"
  },
  "geometry": {"coordinates":[-0.373271,52.761035],"type":"Point"}
}
