{
  "type": "Feature",
  "properties": {
    "iso:country": "GB",
    "wof:name": "EX22 6HJ",
    "wof:placetype": "postalcode"
  },
  "geometry": {"coordinates":[-4.349739,50.81562],"type":"Point"}
}
