{
  "type": "Feature",
  "properties": {
    "iso:country":"GB",
    "wof:name":"EX23 8PZ",
    "wof:placetype":"postalcode"
},
  "geometry": {"coordinates":[-4.53657068857764,50.82368543687152],"type":"Point"}
}