{
  "type": "Feature",
  "properties": {
    "iso:country":"GB",
    "wof:name":"BN3 2TB",
    "wof:placetype":"postalcode"
},
  "geometry": {"coordinates":[-0.17775593179677,50.82583719934185],"type":"Point"}
}