{
  "type": "Feature",
  "properties": {
    "iso:country": "GB",
    "wof:name": "IP3 8NN",
    "wof:placetype": "postalcode"
  },
  "geometry": {"coordinates":[1.198814,52.050646],"type":"Point"}
}
