{
  "type": "Feature",
  "properties": {
    "iso:country":"GB",
    "wof:name":"CM7 2NY",
    "wof:placetype":"postalcode"
},
  "geometry": {"coordinates":[0.54500203980275,51.87790067921383],"type":"Point"}
}