{
  "type": "Feature",
  "properties": {
    "date:inception_lower": "1995-07-01",
    "date:inception_upper": "1995-07-01",
    "iso:country": "GB",
    "wof:name": "CM7 2NY",
    "wof:placetype": "postalcode"
  },
  "geometry": {"coordinates":[0.545002,51.877901],"type":"Point"}
}
