{
  "type": "Feature",
  "properties": {
    "date:inception_lower": "1990-07-01",
    "date:inception_upper": "1990-07-01",
    "iso:country": "GB",
    "wof:name": "BN10 8BE",
    "wof:placetype": "postalcode"
  },
  "geometry": {"coordinates":[0.005558,50.801011],"type":"Point"}
}
