{
  "type": "Feature",
  "properties": {
    "iso:country":"GB",
    "wof:name":"BN10 8BE",
    "wof:placetype":"postalcode"
},
  "geometry": {"coordinates":[0.00555798028751,50.80101126056232],"type":"Point"}
}