{
  "type": "Feature",
  "properties": {
    "iso:country":"GB",
    "wof:name":"B17 9JA",
    "wof:placetype":"postalcode"
},
  "geometry": {"coordinates":[-1.9543106156574,52.46656746687842],"type":"Point"}
}