{
  "type": "Feature",
  "properties": {
    "iso:country":"GB",
    "wof:name":"PE6 7AA",
    "wof:placetype":"postalcode"
},
  "geometry": {"coordinates":[-0.31177960762724,52.58445028335599],"type":"Point"}
}