{
  "type": "Feature",
  "properties": {
    "date:inception_lower": "1980-01-01",
    "date:inception_upper": "1980-01-01",
    "iso:country": "GB",
    "wof:name": "PE6 7AA",
    "wof:placetype": "postalcode"
  },
  "geometry": {"coordinates":[-0.31178,52.58445],"type":"Point"}
}
