{
  "type": "Feature",
  "properties": {
    "iso:country":"GB",
    "wof:name":"MK44 2NE",
    "wof:placetype":"postalcode"
},
  "geometry": {"coordinates":[-0.33854742789701,52.21606128118802],"type":"Point"}
}