{
  "type": "Feature",
  "properties": {
    "date:inception_lower": "1980-01-01",
    "date:inception_upper": "1980-01-01",
    "iso:country": "GB",
    "wof:name": "MK44 2NE",
    "wof:placetype": "postalcode"
  },
  "geometry": {"coordinates":[-0.338547,52.216061],"type":"Point"}
}
