{
  "type": "Feature",
  "properties": {
    "date:inception_lower": "1980-01-01",
    "date:inception_upper": "1980-01-01",
    "iso:country": "GB",
    "wof:name": "RH6 9RR",
    "wof:placetype": "postalcode"
  },
  "geometry": {"coordinates":[-0.111369,51.152802],"type":"Point"}
}
