{
  "type": "Feature",
  "properties": {
    "iso:country":"GB",
    "wof:name":"RH6 9RR",
    "wof:placetype":"postalcode"
},
  "geometry": {"coordinates":[-0.11136905817703,51.15280168994465],"type":"Point"}
}