{
  "type": "Feature",
  "properties": {
    "iso:country": "GB",
    "wof:name": "RH6 9RR",
    "wof:placetype": "postalcode"
  },
  "geometry": {"coordinates":[-0.111369,51.152802],"type":"Point"}
}
