{
  "type": "Feature",
  "properties": {
    "date:inception_lower": "1981-06-01",
    "date:inception_upper": "1981-06-01",
    "iso:country": "GB",
    "wof:name": "HX1 5NB",
    "wof:placetype": "postalcode"
  },
  "geometry": {"coordinates":[-1.877053,53.724662],"type":"Point"}
}
