{
  "type": "Feature",
  "properties": {
    "date:inception_lower": "1980-01-01",
    "date:inception_upper": "1980-01-01",
    "iso:country": "GB",
    "wof:name": "DH5 9BL",
    "wof:placetype": "postalcode"
  },
  "geometry": {"coordinates":[-1.453755,54.828756],"type":"Point"}
}
