{
  "type": "Feature",
  "properties": {
    "iso:country":"GB",
    "wof:name":"NW9 5GQ",
    "wof:placetype":"postalcode"
},
  "geometry": {"coordinates":[-0.24759465892906,51.60067522697666],"type":"Point"}
}