{
  "type": "Feature",
  "properties": {
    "iso:country":"GB",
    "wof:name":"YO7 1TQ",
    "wof:placetype":"postalcode"
},
  "geometry": {"coordinates":[-1.3476657101817,54.23182509859947],"type":"Point"}
}