{
  "type": "Feature",
  "properties": {
    "date:inception_lower": "2012-08-01",
    "date:inception_upper": "2012-08-01",
    "iso:country": "GB",
    "wof:name": "TF3 5GG",
    "wof:placetype": "postalcode"
  },
  "geometry": {"coordinates":[-2.483448,52.682019],"type":"Point"}
}
