{
  "type": "Feature",
  "properties": {
    "iso:country": "GB",
    "wof:name": "SO41 8JJ",
    "wof:placetype": "postalcode"
  },
  "geometry": {"coordinates":[-1.565091,50.749543],"type":"Point"}
}
