{
  "type": "Feature",
  "properties": {
    "iso:country": "GB",
    "wof:name": "SO41 8JJ",
    "wof:placetype": "postalcode"
  },
  "geometry": {"coordinates":[-1.564732,50.749389],"type":"Point"}
}
