{
  "type": "Feature",
  "properties": {
    "iso:country":"GB",
    "wof:name":"SO41 8JJ",
    "wof:placetype":"postalcode"
},
  "geometry": {"coordinates":[-1.56473181033863,50.7493890512289],"type":"Point"}
}