{
  "type": "Feature",
  "properties": {
    "iso:country":"GB",
    "wof:name":"NE12 2AL",
    "wof:placetype":"postalcode"
},
  "geometry": {"coordinates":[-1.56802578992377,55.01827083806429],"type":"Point"}
}