{
  "type": "Feature",
  "properties": {
    "iso:country":"GB",
    "wof:name":"IG8 8QS",
    "wof:placetype":"postalcode"
},
  "geometry": {"coordinates":[0.04716083474297,51.59352111870726],"type":"Point"}
}