{
  "type": "Feature",
  "properties": {
    "iso:country": "GB",
    "wof:name": "PL12 9AY",
    "wof:placetype": "postalcode"
  },
  "geometry": {"coordinates":[-4.213646,50.408542],"type":"Point"}
}
