{
  "type": "Feature",
  "properties": {
    "iso:country":"GB",
    "wof:name":"HP2 6LX",
    "wof:placetype":"postalcode"
},
  "geometry": {"coordinates":[-0.46429612588515,51.77523105318143],"type":"Point"}
}