{
  "type": "Feature",
  "properties": {
    "date:inception_lower": "1980-01-01",
    "date:inception_upper": "1980-01-01",
    "iso:country": "GB",
    "wof:name": "PH26 3NW",
    "wof:placetype": "postalcode"
  },
  "geometry": {"coordinates":[-3.549372,57.269779],"type":"Point"}
}
