{
  "type": "Feature",
  "properties": {
    "iso:country":"GB",
    "wof:name":"PH26 3NW",
    "wof:placetype":"postalcode"
},
  "geometry": {"coordinates":[-3.54937239814359,57.26977907320609],"type":"Point"}
}