{
  "type": "Feature",
  "properties": {
    "iso:country": "GB",
    "wof:name": "DH2 2RH",
    "wof:placetype": "postalcode"
  },
  "geometry": {"coordinates":[-1.602073,54.863283],"type":"Point"}
}
