{
  "type": "Feature",
  "properties": {
    "iso:country":"GB",
    "wof:name":"BD7 4PS",
    "wof:placetype":"postalcode"
},
  "geometry": {"coordinates":[-1.79219337476161,53.77786170494623],"type":"Point"}
}