{
  "type": "Feature",
  "properties": {
    "date:inception_lower": "2004-03-01",
    "date:inception_upper": "2004-03-01",
    "iso:country": "GB",
    "wof:name": "BD7 4PS",
    "wof:placetype": "postalcode"
  },
  "geometry": {"coordinates":[-1.792193,53.777862],"type":"Point"}
}
