{
  "type": "Feature",
  "properties": {
    "iso:country":"GB",
    "wof:name":"AB41 9JN",
    "wof:placetype":"postalcode"
},
  "geometry": {"coordinates":[-2.06826541390895,57.3682134605494],"type":"Point"}
}