{
  "type": "Feature",
  "properties": {
    "date:inception_lower": "2014-05-01",
    "date:inception_upper": "2014-05-01",
    "iso:country": "GB",
    "wof:name": "AB41 9JN",
    "wof:placetype": "postalcode"
  },
  "geometry": {"coordinates":[-2.068265,57.368213],"type":"Point"}
}
