{
  "type": "Feature",
  "properties": {
    "date:inception_lower": "1980-01-01",
    "date:inception_upper": "1980-01-01",
    "iso:country": "GB",
    "wof:name": "DY14 8PP",
    "wof:placetype": "postalcode"
  },
  "geometry": {"coordinates":[-2.449044,52.380317],"type":"Point"}
}
