{
  "type": "Feature",
  "properties": {
    "iso:country":"GB",
    "wof:name":"DY14 8PP",
    "wof:placetype":"postalcode"
},
  "geometry": {"coordinates":[-2.44904358651513,52.3803168462405],"type":"Point"}
}