{
  "type": "Feature",
  "properties": {
    "date:inception_lower": "1980-01-01",
    "date:inception_upper": "1980-01-01",
    "iso:country": "GB",
    "wof:name": "LL16 5TG",
    "wof:placetype": "postalcode"
  },
  "geometry": {"coordinates":[-3.408166,53.191348],"type":"Point"}
}
