{
  "type": "Feature",
  "properties": {
    "iso:country":"GB",
    "wof:name":"LL16 5TG",
    "wof:placetype":"postalcode"
},
  "geometry": {"coordinates":[-3.4081658471213,53.19134776588345],"type":"Point"}
}