{
  "type": "Feature",
  "properties": {
    "iso:country": "GB",
    "wof:name": "SN25 4FD",
    "wof:placetype": "postalcode"
  },
  "geometry": {"coordinates":[-1.794741,51.604644],"type":"Point"}
}
