{
  "type": "Feature",
  "properties": {
    "iso:country":"GB",
    "wof:name":"CF64 1AJ",
    "wof:placetype":"postalcode"
},
  "geometry": {"coordinates":[-3.16807879579952,51.43915218339463],"type":"Point"}
}