{
  "type": "Feature",
  "properties": {
    "iso:country": "GB",
    "wof:name": "OX28 1NF",
    "wof:placetype": "postalcode"
  },
  "geometry": {"coordinates":[-1.483189,51.792314],"type":"Point"}
}
