{
  "type": "Feature",
  "properties": {
    "iso:country":"GB",
    "wof:name":"OX28 1NF",
    "wof:placetype":"postalcode"
},
  "geometry": {"coordinates":[-1.48318887910996,51.79231431265053],"type":"Point"}
}