{
  "type": "Feature",
  "properties": {
    "iso:country": "GB",
    "wof:name": "SE15 5BB",
    "wof:placetype": "postalcode"
  },
  "geometry": {"coordinates":[-0.07304,51.471541],"type":"Point"}
}
