{
  "type": "Feature",
  "properties": {
    "iso:country":"GB",
    "wof:name":"HP3 8RS",
    "wof:placetype":"postalcode"
},
  "geometry": {"coordinates":[-0.44997513802757,51.72868117622751],"type":"Point"}
}