{
  "type": "Feature",
  "properties": {
    "iso:country": "GB",
    "wof:name": "HP3 8RS",
    "wof:placetype": "postalcode"
  },
  "geometry": {"coordinates":[-0.449975,51.728681],"type":"Point"}
}
