{
  "type": "Feature",
  "properties": {
    "date:inception_lower": "1980-01-01",
    "date:inception_upper": "1980-01-01",
    "iso:country": "GB",
    "wof:name": "GU5 9SR",
    "wof:placetype": "postalcode"
  },
  "geometry": {"coordinates":[-0.436651,51.195398],"type":"Point"}
}
