{
  "type": "Feature",
  "properties": {
    "iso:country":"GB",
    "wof:name":"GU5 9SR",
    "wof:placetype":"postalcode"
},
  "geometry": {"coordinates":[-0.43720194701601,51.19475795723773],"type":"Point"}
}