{
  "type": "Feature",
  "properties": {
    "iso:country": "GB",
    "wof:name": "GU5 9SR",
    "wof:placetype": "postalcode"
  },
  "geometry": {"coordinates":[-0.436651,51.195398],"type":"Point"}
}
