{
  "type": "Feature",
  "properties": {
    "iso:country":"GB",
    "wof:name":"EX10 0LZ",
    "wof:placetype":"postalcode"
},
  "geometry": {"coordinates":[-3.25819384524893,50.69997318713261],"type":"Point"}
}