{
  "type": "Feature",
  "properties": {
    "date:inception_lower":"1980-01-01",
    "date:inception_upper":"1980-01-31",
    "iso:country":"GB",
    "wof:name":"EX10 0LZ",
    "wof:placetype":"postalcode"
},
  "geometry": {"coordinates":[-3.258179,50.700035],"type":"Point"}
}