{
  "type": "Feature",
  "properties": {
    "date:inception_lower":"2017-08-01",
    "date:inception_upper":"2017-08-31",
    "iso:country":"GB",
    "wof:name":"E14 9ER",
    "wof:placetype":"postalcode"
},
  "geometry": {"coordinates":[-0.014439,51.497299],"type":"Point"}
}