{
  "type": "Feature",
  "properties": {
    "date:inception_lower": "1996-06-01",
    "date:inception_upper": "1996-06-01",
    "iso:country": "GB",
    "wof:name": "AB21 9AN",
    "wof:placetype": "postalcode"
  },
  "geometry": {"coordinates":[-2.174995,57.178294],"type":"Point"}
}
