{
  "type": "Feature",
  "properties": {
    "iso:country":"GB",
    "wof:name":"LS6 2RE",
    "wof:placetype":"postalcode"
},
  "geometry": {"coordinates":[-1.55714435047034,53.81340134034065],"type":"Point"}
}