{
  "type": "Feature",
  "properties": {
    "date:inception_lower": "1980-01-01",
    "date:inception_upper": "1980-01-01",
    "iso:country": "GB",
    "wof:name": "S5 7LF",
    "wof:placetype": "postalcode"
  },
  "geometry": {"coordinates":[-1.467363,53.415095],"type":"Point"}
}
