{
  "type": "Feature",
  "properties": {
    "iso:country":"GB",
    "wof:name":"NW1 7QY",
    "wof:placetype":"postalcode"
},
  "geometry": {"coordinates":[-0.13961819929542,51.53344064470755],"type":"Point"}
}