{
  "type": "Feature",
  "properties": {
    "date:inception_lower": "2007-07-01",
    "date:inception_upper": "2007-07-01",
    "iso:country": "GB",
    "wof:name": "NW1 7QY",
    "wof:placetype": "postalcode"
  },
  "geometry": {"coordinates":[-0.139618,51.533441],"type":"Point"}
}
