{
  "type": "Feature",
  "properties": {
    "date:inception_lower": "1980-01-01",
    "date:inception_upper": "1980-01-01",
    "iso:country": "GB",
    "wof:name": "NG16 2SJ",
    "wof:placetype": "postalcode"
  },
  "geometry": {"coordinates":[-1.28861,52.987284],"type":"Point"}
}
