{
  "type": "Feature",
  "properties": {
    "iso:country":"GB",
    "wof:name":"NG16 2SJ",
    "wof:placetype":"postalcode"
},
  "geometry": {"coordinates":[-1.28860972823052,52.98728357433028],"type":"Point"}
}