{
  "type": "Feature",
  "properties": {
    "iso:country": "GB",
    "wof:name": "BH15 4NU",
    "wof:placetype": "postalcode"
  },
  "geometry": {"coordinates":[-2.027061,50.721007],"type":"Point"}
}
