{
  "type": "Feature",
  "properties": {
    "iso:country":"GB",
    "wof:name":"BH15 4NU",
    "wof:placetype":"postalcode"
},
  "geometry": {"coordinates":[-2.02706152031448,50.72100698366158],"type":"Point"}
}