{
  "type": "Feature",
  "properties": {
    "iso:country":"GB",
    "wof:name":"BD4 8RP",
    "wof:placetype":"postalcode"
},
  "geometry": {"coordinates":[-1.72062270198386,53.78127571924534],"type":"Point"}
}