{
  "type": "Feature",
  "properties": {
    "date:inception_lower": "1980-01-01",
    "date:inception_upper": "1980-01-01",
    "iso:country": "GB",
    "wof:name": "NG24 3EH",
    "wof:placetype": "postalcode"
  },
  "geometry": {"coordinates":[-0.793772,53.056733],"type":"Point"}
}
