{
  "type": "Feature",
  "properties": {
    "iso:country": "GB",
    "wof:name": "UB7 0HD",
    "wof:placetype": "postalcode"
  },
  "geometry": {"coordinates":[-0.483987,51.484605],"type":"Point"}
}
