{
  "type": "Feature",
  "properties": {
    "iso:country":"GB",
    "wof:name":"UB7 0HD",
    "wof:placetype":"postalcode"
},
  "geometry": {"coordinates":[-0.48398752761693,51.48460500153931],"type":"Point"}
}