{
  "type": "Feature",
  "properties": {
    "iso:country": "GB",
    "wof:name": "WA6 6JY",
    "wof:placetype": "postalcode"
  },
  "geometry": {"coordinates":[-2.682941,53.25942],"type":"Point"}
}
