{
  "type": "Feature",
  "properties": {
    "iso:country":"GB",
    "wof:name":"WA6 6JY",
    "wof:placetype":"postalcode"
},
  "geometry": {"coordinates":[-2.68277514955653,53.25929827363291],"type":"Point"}
}