{
  "type": "Feature",
  "properties": {
    "iso:country":"GB",
    "wof:name":"CO7 7DX",
    "wof:placetype":"postalcode"
},
  "geometry": {"coordinates":[1.048911218688,51.87207512696352],"type":"Point"}
}