{
  "type": "Feature",
  "properties": {
    "date:inception_lower":"1992-01-01",
    "date:inception_upper":"1992-01-31",
    "iso:country":"GB",
    "wof:name":"CO7 7DX",
    "wof:placetype":"postalcode"
},
  "geometry": {"coordinates":[1.048911,51.872075],"type":"Point"}
}