{
  "type": "Feature",
  "properties": {
    "date:inception_lower":"2004-01-01",
    "date:inception_upper":"2004-01-31",
    "iso:country":"GB",
    "wof:name":"NP11 4GJ",
    "wof:placetype":"postalcode"
},
  "geometry": {"coordinates":[-3.162792,51.65911],"type":"Point"}
}