{
  "type": "Feature",
  "properties": {
    "iso:country":"GB",
    "wof:name":"NP11 4GJ",
    "wof:placetype":"postalcode"
},
  "geometry": {"coordinates":[-3.16278299419234,51.65910845480283],"type":"Point"}
}