{
  "type": "Feature",
  "properties": {
    "iso:country": "GB",
    "wof:name": "NP11 4GJ",
    "wof:placetype": "postalcode"
  },
  "geometry": {"coordinates":[-3.162721,51.659156],"type":"Point"}
}
