{
  "type": "Feature",
  "properties": {
    "iso:country": "GB",
    "wof:name": "WA11 8FZ",
    "wof:placetype": "postalcode"
  },
  "geometry": {"coordinates":[-2.785231,53.501615],"type":"Point"}
}
