{
  "type": "Feature",
  "properties": {
    "date:inception_lower": "2017-05-01",
    "date:inception_upper": "2017-05-01",
    "iso:country": "GB",
    "wof:name": "WA11 8FZ",
    "wof:placetype": "postalcode"
  },
  "geometry": {"coordinates":[-2.785368,53.501704],"type":"Point"}
}
