{
  "type": "Feature",
  "properties": {
    "iso:country":"GB",
    "wof:name":"SN3 4PZ",
    "wof:placetype":"postalcode"
},
  "geometry": {"coordinates":[-1.74956473378462,51.5829057197888],"type":"Point"}
}