{
  "type": "Feature",
  "properties": {
    "iso:country":"GB",
    "wof:name":"BN16 4ER",
    "wof:placetype":"postalcode"
},
  "geometry": {"coordinates":[-0.46507969144062,50.83292957241024],"type":"Point"}
}