{
  "type": "Feature",
  "properties": {
    "iso:country":"GB",
    "wof:name":"N6 6JU",
    "wof:placetype":"postalcode"
},
  "geometry": {"coordinates":[-0.15194702461061,51.57007288590817],"type":"Point"}
}