{
  "type": "Feature",
  "properties": {
    "date:inception_lower": "1980-01-01",
    "date:inception_upper": "1980-01-01",
    "iso:country": "GB",
    "wof:name": "CV35 7PA",
    "wof:placetype": "postalcode"
  },
  "geometry": {"coordinates":[-1.645242,52.320285],"type":"Point"}
}
