{
  "type": "Feature",
  "properties": {
    "date:inception_lower": "2021-09-01",
    "date:inception_upper": "2021-09-01",
    "iso:country": "GB",
    "wof:name": "PA1 1FA",
    "wof:placetype": "postalcode"
  },
  "geometry": {"coordinates":[-4.42143,55.843584],"type":"Point"}
}
