{
  "type": "Feature",
  "properties": {
    "iso:country":"GB",
    "wof:name":"S72 8AL",
    "wof:placetype":"postalcode"
},
  "geometry": {"coordinates":[-1.40774114591739,53.58805988846996],"type":"Point"}
}