{
  "type": "Feature",
  "properties": {
    "iso:country":"GB",
    "wof:name":"W2 1RY",
    "wof:placetype":"postalcode"
},
  "geometry": {"coordinates":[-0.17255646375324,51.51635115819264],"type":"Point"}
}