{
  "type": "Feature",
  "properties": {
    "iso:country": "GB",
    "wof:name": "SA62 6LB",
    "wof:placetype": "postalcode"
  },
  "geometry": {"coordinates":[-5.108023,51.880236],"type":"Point"}
}
