{
  "type": "Feature",
  "properties": {
    "iso:country":"GB",
    "wof:name":"MK44 3RH",
    "wof:placetype":"postalcode"
},
  "geometry": {"coordinates":[-0.33160668171317,52.12895387398592],"type":"Point"}
}