{
  "type": "Feature",
  "properties": {
    "iso:country":"GB",
    "wof:name":"BS48 3EQ",
    "wof:placetype":"postalcode"
},
  "geometry": {"coordinates":[-2.71784092675544,51.4026265655657],"type":"Point"}
}