{
  "type": "Feature",
  "properties": {
    "iso:country": "GB",
    "wof:name": "HP5 1RD",
    "wof:placetype": "postalcode"
  },
  "geometry": {"coordinates":[-0.602268,51.697879],"type":"Point"}
}
