{
  "type": "Feature",
  "properties": {
    "iso:country":"GB",
    "wof:name":"HP5 1RD",
    "wof:placetype":"postalcode"
},
  "geometry": {"coordinates":[-0.602268227627,51.69787917272458],"type":"Point"}
}