{
  "type": "Feature",
  "properties": {
    "date:inception_lower": "1980-01-01",
    "date:inception_upper": "1980-01-01",
    "iso:country": "GB",
    "wof:name": "DD2 2EJ",
    "wof:placetype": "postalcode"
  },
  "geometry": {"coordinates":[-3.017951,56.467377],"type":"Point"}
}
