{
  "type": "Feature",
  "properties": {
    "iso:country": "GB",
    "wof:name": "S70 4BY",
    "wof:placetype": "postalcode"
  },
  "geometry": {"coordinates":[-1.466841,53.540996],"type":"Point"}
}
