{
  "type": "Feature",
  "properties": {
    "iso:country":"GB",
    "wof:name":"S70 4BY",
    "wof:placetype":"postalcode"
},
  "geometry": {"coordinates":[-1.46684110658773,53.54099567847699],"type":"Point"}
}