{
  "type": "Feature",
  "properties": {
    "date:inception_lower":"2013-10-01",
    "date:inception_upper":"2013-10-31",
    "iso:country":"GB",
    "wof:name":"S70 4BY",
    "wof:placetype":"postalcode"
},
  "geometry": {"coordinates":[-1.466841,53.540996],"type":"Point"}
}