{
  "type": "Feature",
  "properties": {
    "iso:country":"GB",
    "wof:name":"RH10 1NU",
    "wof:placetype":"postalcode"
},
  "geometry": {"coordinates":[-0.17778947391895,51.11577011114498],"type":"Point"}
}