{
  "type": "Feature",
  "properties": {
    "iso:country": "GB",
    "wof:name": "HU18 1BB",
    "wof:placetype": "postalcode"
  },
  "geometry": {"coordinates":[-0.173445,53.909621],"type":"Point"}
}
