{
  "type": "Feature",
  "properties": {
    "iso:country":"GB",
    "wof:name":"CB10 2XS",
    "wof:placetype":"postalcode"
},
  "geometry": {"coordinates":[0.3334333655483,51.97320335150659],"type":"Point"}
}