{
  "type": "Feature",
  "properties": {
    "iso:country": "GB",
    "wof:name": "CB10 2XS",
    "wof:placetype": "postalcode"
  },
  "geometry": {"coordinates":[0.333487,51.973131],"type":"Point"}
}
