{
  "type": "Feature",
  "properties": {
    "iso:country":"GB",
    "wof:name":"SS6 8SR",
    "wof:placetype":"postalcode"
},
  "geometry": {"coordinates":[0.62144972609061,51.57896601395686],"type":"Point"}
}