{
  "type": "Feature",
  "properties": {
    "date:inception_lower": "1980-01-01",
    "date:inception_upper": "1980-01-01",
    "iso:country": "GB",
    "wof:name": "KY8 1EG",
    "wof:placetype": "postalcode"
  },
  "geometry": {"coordinates":[-3.04069,56.174383],"type":"Point"}
}
