{
  "type": "Feature",
  "properties": {
    "iso:country":"GB",
    "wof:name":"AB51 0UA",
    "wof:placetype":"postalcode"
},
  "geometry": {"coordinates":[-2.34496452229776,57.23705835771906],"type":"Point"}
}