{
  "type": "Feature",
  "properties": {
    "date:inception_lower":"1980-01-01",
    "date:inception_upper":"1980-01-31",
    "iso:country":"GB",
    "wof:name":"GU16 6HH",
    "wof:placetype":"postalcode"
},
  "geometry": {"coordinates":[-0.732169,51.301989],"type":"Point"}
}