{
  "type": "Feature",
  "properties": {
    "iso:country": "GB",
    "wof:name": "GU16 6HH",
    "wof:placetype": "postalcode"
  },
  "geometry": {"coordinates":[-0.732169,51.301989],"type":"Point"}
}
