{
  "type": "Feature",
  "properties": {
    "date:inception_lower": "2004-10-01",
    "date:inception_upper": "2004-10-01",
    "iso:country": "GB",
    "wof:name": "TW20 8TG",
    "wof:placetype": "postalcode"
  },
  "geometry": {"coordinates":[-0.52841,51.407892],"type":"Point"}
}
