{
  "type": "Feature",
  "properties": {
    "date:inception_lower": "1980-01-01",
    "date:inception_upper": "1980-01-01",
    "iso:country": "GB",
    "wof:name": "TS3 0JB",
    "wof:placetype": "postalcode"
  },
  "geometry": {"coordinates":[-1.189911,54.551852],"type":"Point"}
}
