{
  "type": "Feature",
  "properties": {
    "iso:country":"GB",
    "wof:name":"TS3 0JB",
    "wof:placetype":"postalcode"
},
  "geometry": {"coordinates":[-1.1899115435671,54.55185161824775],"type":"Point"}
}