{
  "type": "Feature",
  "properties": {
    "iso:country": "GB",
    "wof:name": "LL55 2TG",
    "wof:placetype": "postalcode"
  },
  "geometry": {"coordinates":[-4.242878,53.119473],"type":"Point"}
}
