{
  "type": "Feature",
  "properties": {
    "date:inception_lower":"1980-01-01",
    "date:inception_upper":"1980-01-31",
    "iso:country":"GB",
    "wof:name":"LL55 2TG",
    "wof:placetype":"postalcode"
},
  "geometry": {"coordinates":[-4.242878,53.119473],"type":"Point"}
}