{
  "type": "Feature",
  "properties": {
    "iso:country": "GB",
    "wof:name": "TA18 7AP",
    "wof:placetype": "postalcode"
  },
  "geometry": {"coordinates":[-2.796107,50.89033],"type":"Point"}
}
