{
  "type": "Feature",
  "properties": {
    "iso:country":"GB",
    "wof:name":"TA18 7AP",
    "wof:placetype":"postalcode"
},
  "geometry": {"coordinates":[-2.79610724122512,50.89033011969114],"type":"Point"}
}