{
  "type": "Feature",
  "properties": {
    "iso:country": "GB",
    "wof:name": "S1 9TL",
    "wof:placetype": "postalcode"
  },
  "geometry": {"coordinates":[-1.470006,53.380384],"type":"Point"}
}
