{
  "type": "Feature",
  "properties": {
    "iso:country":"GB",
    "wof:name":"W1H 6LD",
    "wof:placetype":"postalcode"
},
  "geometry": {"coordinates":[-0.1544706655962,51.51593309581625],"type":"Point"}
}