{
  "type": "Feature",
  "properties": {
    "iso:country": "GB",
    "wof:name": "NG3 5JL",
    "wof:placetype": "postalcode"
  },
  "geometry": {"coordinates":[-1.12429,52.98421],"type":"Point"}
}
