{
  "type": "Feature",
  "properties": {
    "iso:country":"GB",
    "wof:name":"NG3 5JL",
    "wof:placetype":"postalcode"
},
  "geometry": {"coordinates":[-1.1242900774556,52.98420953392174],"type":"Point"}
}