{
  "type": "Feature",
  "properties": {
    "iso:country": "GB",
    "wof:name": "TS9 5HB",
    "wof:placetype": "postalcode"
  },
  "geometry": {"coordinates":[-1.184132,54.473382],"type":"Point"}
}
