{
  "type": "Feature",
  "properties": {
    "date:inception_lower": "2007-07-01",
    "date:inception_upper": "2007-07-01",
    "iso:country": "GB",
    "wof:name": "BS22 6AE",
    "wof:placetype": "postalcode"
  },
  "geometry": {"coordinates":[-2.929479,51.356368],"type":"Point"}
}
