{
  "type": "Feature",
  "properties": {
    "iso:country":"GB",
    "wof:name":"BS22 6AE",
    "wof:placetype":"postalcode"
},
  "geometry": {"coordinates":[-2.92947923100398,51.35636799001416],"type":"Point"}
}