{
  "type": "Feature",
  "properties": {
    "iso:country":"GB",
    "wof:name":"DN1 2BJ",
    "wof:placetype":"postalcode"
},
  "geometry": {"coordinates":[-1.12722496522413,53.51605201320216],"type":"Point"}
}