{
  "type": "Feature",
  "properties": {
    "date:inception_lower":"1980-01-01",
    "date:inception_upper":"1980-01-31",
    "iso:country":"GB",
    "wof:name":"FY3 8RP",
    "wof:placetype":"postalcode"
},
  "geometry": {"coordinates":[-3.03639,53.825504],"type":"Point"}
}