{
  "type": "Feature",
  "properties": {
    "date:inception_lower": "1980-01-01",
    "date:inception_upper": "1980-01-01",
    "iso:country": "GB",
    "wof:name": "PL6 5UY",
    "wof:placetype": "postalcode"
  },
  "geometry": {"coordinates":[-4.099534,50.397549],"type":"Point"}
}
