{
  "type": "Feature",
  "properties": {
    "date:inception_lower":"1997-12-01",
    "date:inception_upper":"1997-12-31",
    "iso:country":"GB",
    "wof:name":"N4 2FR",
    "wof:placetype":"postalcode"
},
  "geometry": {"coordinates":[-0.09406,51.564741],"type":"Point"}
}