{
  "type": "Feature",
  "properties": {
    "iso:country":"GB",
    "wof:name":"N4 2FR",
    "wof:placetype":"postalcode"
},
  "geometry": {"coordinates":[-0.09406024945922,51.56474061285346],"type":"Point"}
}