{
  "type": "Feature",
  "properties": {
    "iso:country":"GB",
    "wof:name":"DD5 3HG",
    "wof:placetype":"postalcode"
},
  "geometry": {"coordinates":[-2.86882005522332,56.47574235281401],"type":"Point"}
}