{
  "type": "Feature",
  "properties": {
    "date:inception_lower": "1980-01-01",
    "date:inception_upper": "1980-01-01",
    "iso:country": "GB",
    "wof:name": "PE9 2UQ",
    "wof:placetype": "postalcode"
  },
  "geometry": {"coordinates":[-0.498866,52.657968],"type":"Point"}
}
