{
  "type": "Feature",
  "properties": {
    "iso:country":"GB",
    "wof:name":"PE9 2UQ",
    "wof:placetype":"postalcode"
},
  "geometry": {"coordinates":[-0.49886607530745,52.65796790893585],"type":"Point"}
}