{
  "type": "Feature",
  "properties": {
    "date:inception_lower": "2017-05-01",
    "date:inception_upper": "2017-05-01",
    "iso:country": "GB",
    "wof:name": "G74 4XW",
    "wof:placetype": "postalcode"
  },
  "geometry": {"coordinates":[-4.163621,55.789056],"type":"Point"}
}
