{
  "type": "Feature",
  "properties": {
    "date:inception_lower":"1980-01-01",
    "date:inception_upper":"1980-01-31",
    "iso:country":"GB",
    "wof:name":"SA33 5HB",
    "wof:placetype":"postalcode"
},
  "geometry": {"coordinates":[-4.396837,51.782846],"type":"Point"}
}