{
  "type": "Feature",
  "properties": {
    "date:inception_lower": "1980-01-01",
    "date:inception_upper": "1980-01-01",
    "iso:country": "GB",
    "wof:name": "TN4 9SG",
    "wof:placetype": "postalcode"
  },
  "geometry": {"coordinates":[0.253674,51.142784],"type":"Point"}
}
