{
  "type": "Feature",
  "properties": {
    "iso:country":"GB",
    "wof:name":"TN4 9SG",
    "wof:placetype":"postalcode"
},
  "geometry": {"coordinates":[0.25367355645181,51.14278377353745],"type":"Point"}
}