{
  "type": "Feature",
  "properties": {
    "iso:country": "GB",
    "wof:name": "NR8 6EU",
    "wof:placetype": "postalcode"
  },
  "geometry": {"coordinates":[1.219369,52.68489],"type":"Point"}
}
