{
  "type": "Feature",
  "properties": {
    "iso:country":"GB",
    "wof:name":"NR8 6EU",
    "wof:placetype":"postalcode"
},
  "geometry": {"coordinates":[1.21936930674157,52.68489029583171],"type":"Point"}
}