{
  "type": "Feature",
  "properties": {
    "date:inception_lower": "2001-06-01",
    "date:inception_upper": "2001-06-01",
    "iso:country": "GB",
    "wof:name": "SL1 3GE",
    "wof:placetype": "postalcode"
  },
  "geometry": {"coordinates":[-0.601475,51.514859],"type":"Point"}
}
