{
  "type": "Feature",
  "properties": {
    "iso:country":"GB",
    "wof:name":"CF45 4EU",
    "wof:placetype":"postalcode"
},
  "geometry": {"coordinates":[-3.37878191373292,51.6840607062113],"type":"Point"}
}