{
  "type": "Feature",
  "properties": {
    "date:inception_lower": "1980-01-01",
    "date:inception_upper": "1980-01-01",
    "iso:country": "GB",
    "wof:name": "L32 7RN",
    "wof:placetype": "postalcode"
  },
  "geometry": {"coordinates":[-2.889282,53.468987],"type":"Point"}
}
