{
  "type": "Feature",
  "properties": {
    "iso:country":"GB",
    "wof:name":"L32 7RN",
    "wof:placetype":"postalcode"
},
  "geometry": {"coordinates":[-2.88928239887031,53.46898732877847],"type":"Point"}
}