{
  "type": "Feature",
  "properties": {
    "iso:country":"GB",
    "wof:name":"NE38 7QW",
    "wof:placetype":"postalcode"
},
  "geometry": {"coordinates":[-1.52823615943555,54.90113930436724],"type":"Point"}
}