{
  "type": "Feature",
  "properties": {
    "iso:country":"GB",
    "wof:name":"CW5 8JF",
    "wof:placetype":"postalcode"
},
  "geometry": {"coordinates":[-2.61173283839528,53.07201956154181],"type":"Point"}
}