{
  "type": "Feature",
  "properties": {
    "iso:country": "GB",
    "wof:name": "CW5 8JF",
    "wof:placetype": "postalcode"
  },
  "geometry": {"coordinates":[-2.611733,53.07202],"type":"Point"}
}
