{
  "type": "Feature",
  "properties": {
    "date:inception_lower": "2001-06-01",
    "date:inception_upper": "2001-06-01",
    "iso:country": "GB",
    "wof:name": "AB42 1RQ",
    "wof:placetype": "postalcode"
  },
  "geometry": {"coordinates":[-1.786391,57.504277],"type":"Point"}
}
