{
  "type": "Feature",
  "properties": {
    "iso:country":"GB",
    "wof:name":"AB42 1RQ",
    "wof:placetype":"postalcode"
},
  "geometry": {"coordinates":[-1.78625339407369,57.50428153858442],"type":"Point"}
}