{
  "type": "Feature",
  "properties": {
    "iso:country": "GB",
    "wof:name": "HR2 8BW",
    "wof:placetype": "postalcode"
  },
  "geometry": {"coordinates":[-2.734808,52.016277],"type":"Point"}
}
