{
  "type": "Feature",
  "properties": {
    "date:inception_lower": "1980-01-01",
    "date:inception_upper": "1980-01-01",
    "iso:country": "GB",
    "wof:name": "HR2 8BW",
    "wof:placetype": "postalcode"
  },
  "geometry": {"coordinates":[-2.73449,52.017178],"type":"Point"}
}
