{
  "type": "Feature",
  "properties": {
    "iso:country":"GB",
    "wof:name":"SL4 1JA",
    "wof:placetype":"postalcode"
},
  "geometry": {"coordinates":[-0.61031366793954,51.47691702676343],"type":"Point"}
}