{
  "type": "Feature",
  "properties": {
    "iso:country":"GB",
    "wof:name":"DL5 6QU",
    "wof:placetype":"postalcode"
},
  "geometry": {"coordinates":[-1.6017491484429,54.60940100509615],"type":"Point"}
}