{
  "type": "Feature",
  "properties": {
    "iso:country":"GB",
    "wof:name":"NR30 4BL",
    "wof:placetype":"postalcode"
},
  "geometry": {"coordinates":[1.73236865929418,52.62483883099129],"type":"Point"}
}