{
  "type": "Feature",
  "properties": {
    "iso:country":"GB",
    "wof:name":"CA2 5NP",
    "wof:placetype":"postalcode"
},
  "geometry": {"coordinates":[-2.94705160001656,54.88932083643542],"type":"Point"}
}