{
  "type": "Feature",
  "properties": {
    "iso:country": "GB",
    "wof:name": "E6 5ZH",
    "wof:placetype": "postalcode"
  },
  "geometry": {"coordinates":[0.052486,51.518798],"type":"Point"}
}
