{
  "type": "Feature",
  "properties": {
    "date:inception_lower": "1998-06-01",
    "date:inception_upper": "1998-06-01",
    "iso:country": "GB",
    "wof:name": "E6 5ZH",
    "wof:placetype": "postalcode"
  },
  "geometry": {"coordinates":[0.052486,51.518798],"type":"Point"}
}
