{
  "type": "Feature",
  "properties": {
    "iso:country":"GB",
    "wof:name":"B63 2AX",
    "wof:placetype":"postalcode"
},
  "geometry": {"coordinates":[-2.07572493856796,52.46203881098073],"type":"Point"}
}