{
  "type": "Feature",
  "properties": {
    "iso:country": "GB",
    "wof:name": "GU34 3HB",
    "wof:placetype": "postalcode"
  },
  "geometry": {"coordinates":[-0.985084,51.135086],"type":"Point"}
}
