{
  "type": "Feature",
  "properties": {
    "iso:country": "GB",
    "wof:name": "SN6 6AP",
    "wof:placetype": "postalcode"
  },
  "geometry": {"coordinates":[-1.857327,51.639776],"type":"Point"}
}
