{
  "type": "Feature",
  "properties": {
    "date:inception_lower":"1980-01-01",
    "date:inception_upper":"1980-01-31",
    "iso:country":"GB",
    "wof:name":"SN6 6AP",
    "wof:placetype":"postalcode"
},
  "geometry": {"coordinates":[-1.857327,51.639776],"type":"Point"}
}