{
  "type": "Feature",
  "properties": {
    "iso:country":"GB",
    "wof:name":"SN6 6AP",
    "wof:placetype":"postalcode"
},
  "geometry": {"coordinates":[-1.85732662451351,51.63977606029395],"type":"Point"}
}