{
  "type": "Feature",
  "properties": {
    "date:inception_lower": "1983-07-01",
    "date:inception_upper": "1983-07-01",
    "iso:country": "GB",
    "wof:name": "NG18 2BY",
    "wof:placetype": "postalcode"
  },
  "geometry": {"coordinates":[-1.190811,53.148314],"type":"Point"}
}
