{
  "type": "Feature",
  "properties": {
    "date:inception_lower": "2011-09-01",
    "date:inception_upper": "2011-09-01",
    "iso:country": "GB",
    "wof:name": "L20 7ED",
    "wof:placetype": "postalcode"
  },
  "geometry": {"coordinates":[-2.992196,53.442774],"type":"Point"}
}
