{
  "type": "Feature",
  "properties": {
    "iso:country":"GB",
    "wof:name":"YO62 6AR",
    "wof:placetype":"postalcode"
},
  "geometry": {"coordinates":[-0.93397574787372,54.26940271200087],"type":"Point"}
}