{
  "type": "Feature",
  "properties": {
    "iso:country":"GB",
    "wof:name":"FK1 2NW",
    "wof:placetype":"postalcode"
},
  "geometry": {"coordinates":[-3.74468631377387,55.93191946583881],"type":"Point"}
}