{
  "type": "Feature",
  "properties": {
    "iso:country": "GB",
    "wof:name": "PL25 3PA",
    "wof:placetype": "postalcode"
  },
  "geometry": {"coordinates":[-4.758468,50.33374],"type":"Point"}
}
