{
  "type": "Feature",
  "properties": {
    "iso:country":"GB",
    "wof:name":"PL25 3PA",
    "wof:placetype":"postalcode"
},
  "geometry": {"coordinates":[-4.75846792323947,50.33374024422933],"type":"Point"}
}