{
  "type": "Feature",
  "properties": {
    "date:inception_lower": "2001-12-01",
    "date:inception_upper": "2001-12-01",
    "iso:country": "GB",
    "wof:name": "MK5 6AP",
    "wof:placetype": "postalcode"
  },
  "geometry": {"coordinates":[-0.793224,52.027974],"type":"Point"}
}
