{
  "type": "Feature",
  "properties": {
    "iso:country":"GB",
    "wof:name":"PE21 0EB",
    "wof:placetype":"postalcode"
},
  "geometry": {"coordinates":[-0.00779138169218,52.97560670070932],"type":"Point"}
}