{
  "type": "Feature",
  "properties": {
    "iso:country":"GB",
    "wof:name":"NN13 5SE",
    "wof:placetype":"postalcode"
},
  "geometry": {"coordinates":[-1.14586692613903,52.00974899262122],"type":"Point"}
}