{
  "type": "Feature",
  "properties": {
    "iso:country":"GB",
    "wof:name":"N1 5NN",
    "wof:placetype":"postalcode"
},
  "geometry": {"coordinates":[-0.08347225486334,51.53619674180298],"type":"Point"}
}