{
  "type": "Feature",
  "properties": {
    "iso:country":"GB",
    "wof:name":"M7 4PL",
    "wof:placetype":"postalcode"
},
  "geometry": {"coordinates":[-2.24749805426092,53.5134331028361],"type":"Point"}
}