{
  "type": "Feature",
  "properties": {
    "date:inception_lower":"1994-05-01",
    "date:inception_upper":"1994-05-31",
    "iso:country":"GB",
    "wof:name":"M7 4PL",
    "wof:placetype":"postalcode"
},
  "geometry": {"coordinates":[-2.247498,53.513433],"type":"Point"}
}