{
  "type": "Feature",
  "properties": {
    "iso:country": "GB",
    "wof:name": "IP1 5NU",
    "wof:placetype": "postalcode"
  },
  "geometry": {"coordinates":[1.110634,52.086177],"type":"Point"}
}
