{
  "type": "Feature",
  "properties": {
    "iso:country":"GB",
    "wof:name":"IP1 5NU",
    "wof:placetype":"postalcode"
},
  "geometry": {"coordinates":[1.110634151007,52.08617736086124],"type":"Point"}
}