{
  "type": "Feature",
  "properties": {
    "iso:country":"GB",
    "wof:name":"NR11 6QQ",
    "wof:placetype":"postalcode"
},
  "geometry": {"coordinates":[1.13456176114771,52.82710726952025],"type":"Point"}
}