{
  "type": "Feature",
  "properties": {
    "iso:country":"GB",
    "wof:name":"NN16 9RX",
    "wof:placetype":"postalcode"
},
  "geometry": {"coordinates":[-0.72773977840045,52.41046861596057],"type":"Point"}
}