{
  "type": "Feature",
  "properties": {
    "iso:country": "GB",
    "wof:name": "NN16 9RX",
    "wof:placetype": "postalcode"
  },
  "geometry": {"coordinates":[-0.72774,52.410469],"type":"Point"}
}
