{
  "type": "Feature",
  "properties": {
    "iso:country":"GB",
    "wof:name":"PL18 9SB",
    "wof:placetype":"postalcode"
},
  "geometry": {"coordinates":[-4.22462984281629,50.50448598229482],"type":"Point"}
}