{
  "type": "Feature",
  "properties": {
    "iso:country":"GB",
    "wof:name":"ME2 2AL",
    "wof:placetype":"postalcode"
},
  "geometry": {"coordinates":[0.48588813747189,51.38922476838378],"type":"Point"}
}