{
  "type": "Feature",
  "properties": {
    "iso:country": "GB",
    "wof:name": "ME2 2AL",
    "wof:placetype": "postalcode"
  },
  "geometry": {"coordinates":[0.485888,51.389225],"type":"Point"}
}
