{
  "type": "Feature",
  "properties": {
    "iso:country":"GB",
    "wof:name":"DE5 3GY",
    "wof:placetype":"postalcode"
},
  "geometry": {"coordinates":[-1.41392603846192,53.04716136056501],"type":"Point"}
}