{
  "type": "Feature",
  "properties": {
    "iso:country":"GB",
    "wof:name":"IV12 5EQ",
    "wof:placetype":"postalcode"
},
  "geometry": {"coordinates":[-3.87049565923176,57.57700516621004],"type":"Point"}
}