{
  "type": "Feature",
  "properties": {
    "iso:country":"GB",
    "wof:name":"G77 6NB",
    "wof:placetype":"postalcode"
},
  "geometry": {"coordinates":[-4.34977654821719,55.78202876396057],"type":"Point"}
}