{
  "type": "Feature",
  "properties": {
    "iso:country": "GB",
    "wof:name": "G77 6NB",
    "wof:placetype": "postalcode"
  },
  "geometry": {"coordinates":[-4.349776,55.782029],"type":"Point"}
}
