{
  "type": "Feature",
  "properties": {
    "iso:country":"GB",
    "wof:name":"B1 3PE",
    "wof:placetype":"postalcode"
},
  "geometry": {"coordinates":[-1.91105713111332,52.48481955459703],"type":"Point"}
}