{
  "type": "Feature",
  "properties": {
    "iso:country":"GB",
    "wof:name":"UB5 4RJ",
    "wof:placetype":"postalcode"
},
  "geometry": {"coordinates":[-0.36101761434025,51.54687692085774],"type":"Point"}
}