{
  "type": "Feature",
  "properties": {
    "date:inception_lower": "2021-06-01",
    "date:inception_upper": "2021-06-01",
    "iso:country": "GB",
    "wof:name": "S13 9DT",
    "wof:placetype": "postalcode"
  },
  "geometry": {"coordinates":[-1.389634,53.376531],"type":"Point"}
}
