{
  "type": "Feature",
  "properties": {
    "date:inception_lower": "1986-04-01",
    "date:inception_upper": "1986-04-01",
    "iso:country": "GB",
    "wof:name": "RG6 4HT",
    "wof:placetype": "postalcode"
  },
  "geometry": {"coordinates":[-0.9422,51.421294],"type":"Point"}
}
