{
  "type": "Feature",
  "properties": {
    "iso:country": "GB",
    "wof:name": "RG6 4HT",
    "wof:placetype": "postalcode"
  },
  "geometry": {"coordinates":[-0.9422,51.421294],"type":"Point"}
}
