{
  "type": "Feature",
  "properties": {
    "iso:country":"GB",
    "wof:name":"RG6 4HT",
    "wof:placetype":"postalcode"
},
  "geometry": {"coordinates":[-0.94220042299708,51.42129420219707],"type":"Point"}
}