{
  "type": "Feature",
  "properties": {
    "iso:country":"GB",
    "wof:name":"WV6 7EL",
    "wof:placetype":"postalcode"
},
  "geometry": {"coordinates":[-2.25623003095345,52.55856179676686],"type":"Point"}
}