{
  "type": "Feature",
  "properties": {
    "iso:country":"GB",
    "wof:name":"MK43 0AX",
    "wof:placetype":"postalcode"
},
  "geometry": {"coordinates":[-0.59668769957675,52.09101977410526],"type":"Point"}
}