{
  "type": "Feature",
  "properties": {
    "iso:country": "GB",
    "wof:name": "KT3 6QQ",
    "wof:placetype": "postalcode"
  },
  "geometry": {"coordinates":[-0.240281,51.398506],"type":"Point"}
}
