{
  "type": "Feature",
  "properties": {
    "date:inception_lower": "2022-07-01",
    "date:inception_upper": "2022-07-01",
    "iso:country": "GB",
    "wof:name": "L14 2EA",
    "wof:placetype": "postalcode"
  },
  "geometry": {"coordinates":[-2.877882,53.42249],"type":"Point"}
}
