{
  "type": "Feature",
  "properties": {
    "date:inception_lower": "2003-04-01",
    "date:inception_upper": "2003-04-01",
    "iso:country": "GB",
    "wof:name": "WC1X 0JJ",
    "wof:placetype": "postalcode"
  },
  "geometry": {"coordinates":[-0.110173,51.528017],"type":"Point"}
}
