{
  "type": "Feature",
  "properties": {
    "iso:country":"GB",
    "wof:name":"WC1X 0JJ",
    "wof:placetype":"postalcode"
},
  "geometry": {"coordinates":[-0.11019855378529,51.52801550889359],"type":"Point"}
}