{
  "type": "Feature",
  "properties": {
    "iso:country": "GB",
    "wof:name": "WS6 6BH",
    "wof:placetype": "postalcode"
  },
  "geometry": {"coordinates":[-2.013353,52.663489],"type":"Point"}
}
