{
  "type": "Feature",
  "properties": {
    "iso:country":"GB",
    "wof:name":"LL22 9AD",
    "wof:placetype":"postalcode"
},
  "geometry": {"coordinates":[-3.5674843125147,53.29748626748931],"type":"Point"}
}