{
  "type": "Feature",
  "properties": {
    "iso:country":"GB",
    "wof:name":"SO53 2NH",
    "wof:placetype":"postalcode"
},
  "geometry": {"coordinates":[-1.37667562930676,50.97866446742926],"type":"Point"}
}