{
  "type": "Feature",
  "properties": {
    "iso:country":"GB",
    "wof:name":"NP19 9NS",
    "wof:placetype":"postalcode"
},
  "geometry": {"coordinates":[-2.94572963800715,51.58575313115684],"type":"Point"}
}