{
  "type": "Feature",
  "properties": {
    "iso:country": "GB",
    "wof:name": "SL6 9LW",
    "wof:placetype": "postalcode"
  },
  "geometry": {"coordinates":[-0.730387,51.554386],"type":"Point"}
}
