{
  "type": "Feature",
  "properties": {
    "iso:country":"GB",
    "wof:name":"SP3 6QJ",
    "wof:placetype":"postalcode"
},
  "geometry": {"coordinates":[-2.10683739725512,51.08986467437512],"type":"Point"}
}