{
  "type": "Feature",
  "properties": {
    "date:inception_lower":"1980-01-01",
    "date:inception_upper":"1980-01-31",
    "iso:country":"GB",
    "wof:name":"TS29 6PF",
    "wof:placetype":"postalcode"
},
  "geometry": {"coordinates":[-1.429694,54.702159],"type":"Point"}
}