{
  "type": "Feature",
  "properties": {
    "iso:country": "GB",
    "wof:name": "TS29 6PF",
    "wof:placetype": "postalcode"
  },
  "geometry": {"coordinates":[-1.429694,54.702159],"type":"Point"}
}
