{
  "type": "Feature",
  "properties": {
    "iso:country": "GB",
    "wof:name": "DE23 1GL",
    "wof:placetype": "postalcode"
  },
  "geometry": {"coordinates":[-1.490968,52.895327],"type":"Point"}
}
