{
  "type": "Feature",
  "properties": {
    "iso:country": "GB",
    "wof:name": "WS10 7WJ",
    "wof:placetype": "postalcode"
  },
  "geometry": {"coordinates":[-2.03066,52.54838],"type":"Point"}
}
