{
  "type": "Feature",
  "properties": {
    "iso:country":"GB",
    "wof:name":"PO7 8EL",
    "wof:placetype":"postalcode"
},
  "geometry": {"coordinates":[-1.01710434247966,50.87247223782269],"type":"Point"}
}