{
  "type": "Feature",
  "properties": {
    "iso:country":"GB",
    "wof:name":"UB4 9EA",
    "wof:placetype":"postalcode"
},
  "geometry": {"coordinates":[-0.39488049059311,51.5259885714884],"type":"Point"}
}