{
  "type": "Feature",
  "properties": {
    "iso:country": "GB",
    "wof:name": "BH17 0GH",
    "wof:placetype": "postalcode"
  },
  "geometry": {"coordinates":[-1.973301,50.747203],"type":"Point"}
}
