{
  "type": "Feature",
  "properties": {
    "iso:country":"GB",
    "wof:name":"PL6 5HQ",
    "wof:placetype":"postalcode"
},
  "geometry": {"coordinates":[-4.13597745818501,50.42161924535957],"type":"Point"}
}