{
  "type": "Feature",
  "properties": {
    "iso:country":"GB",
    "wof:name":"WD19 5EX",
    "wof:placetype":"postalcode"
},
  "geometry": {"coordinates":[-0.38418914267853,51.62636511993198],"type":"Point"}
}