{
  "type": "Feature",
  "properties": {
    "date:inception_lower": "1980-01-01",
    "date:inception_upper": "1980-01-01",
    "iso:country": "GB",
    "wof:name": "NG14 6JJ",
    "wof:placetype": "postalcode"
  },
  "geometry": {"coordinates":[-1.078621,53.040885],"type":"Point"}
}
