{
  "type": "Feature",
  "properties": {
    "iso:country":"GB",
    "wof:name":"NG14 6JJ",
    "wof:placetype":"postalcode"
},
  "geometry": {"coordinates":[-1.07862111262679,53.04088465910018],"type":"Point"}
}