{
  "type": "Feature",
  "properties": {
    "iso:country":"GB",
    "wof:name":"WS4 1DB",
    "wof:placetype":"postalcode"
},
  "geometry": {"coordinates":[-1.96149510031392,52.61777051781776],"type":"Point"}
}