{
  "type": "Feature",
  "properties": {
    "date:inception_lower":"1980-01-01",
    "date:inception_upper":"1980-01-31",
    "iso:country":"GB",
    "wof:name":"WR3 7TL",
    "wof:placetype":"postalcode"
},
  "geometry": {"coordinates":[-2.197644,52.23058],"type":"Point"}
}