{
  "type": "Feature",
  "properties": {
    "date:inception_lower": "1987-04-01",
    "date:inception_upper": "1987-04-01",
    "iso:country": "GB",
    "wof:name": "SS7 5TE",
    "wof:placetype": "postalcode"
  },
  "geometry": {"coordinates":[0.546846,51.561813],"type":"Point"}
}
