{
  "type": "Feature",
  "properties": {
    "iso:country": "GB",
    "wof:name": "DD8 4GX",
    "wof:placetype": "postalcode"
  },
  "geometry": {"coordinates":[-3.006531,56.676482],"type":"Point"}
}
