{
  "type": "Feature",
  "properties": {
    "iso:country":"GB",
    "wof:name":"DD8 4GX",
    "wof:placetype":"postalcode"
},
  "geometry": {"coordinates":[-3.00653065410115,56.67648239912506],"type":"Point"}
}