{
  "type": "Feature",
  "properties": {
    "date:inception_lower": "1998-06-01",
    "date:inception_upper": "1998-06-01",
    "iso:country": "GB",
    "wof:name": "DD8 4GX",
    "wof:placetype": "postalcode"
  },
  "geometry": {"coordinates":[-3.006531,56.676482],"type":"Point"}
}
