{
  "type": "Feature",
  "properties": {
    "iso:country":"GB",
    "wof:name":"NG32 2NB",
    "wof:placetype":"postalcode"
},
  "geometry": {"coordinates":[-0.61431162081749,52.96301650501304],"type":"Point"}
}