{
  "type": "Feature",
  "properties": {
    "iso:country": "GB",
    "wof:name": "PE15 9LX",
    "wof:placetype": "postalcode"
  },
  "geometry": {"coordinates":[0.089875,52.543542],"type":"Point"}
}
