{
  "type": "Feature",
  "properties": {
    "date:inception_lower": "1982-03-01",
    "date:inception_upper": "1982-03-01",
    "iso:country": "GB",
    "wof:name": "PE15 9LX",
    "wof:placetype": "postalcode"
  },
  "geometry": {"coordinates":[0.089875,52.543542],"type":"Point"}
}
