{
  "type": "Feature",
  "properties": {
    "iso:country":"GB",
    "wof:name":"SK4 3HB",
    "wof:placetype":"postalcode"
},
  "geometry": {"coordinates":[-2.2001141150216,53.41366892062444],"type":"Point"}
}