{
  "type": "Feature",
  "properties": {
    "iso:country": "GB",
    "wof:name": "BS35 1BU",
    "wof:placetype": "postalcode"
  },
  "geometry": {"coordinates":[-2.528156,51.610865],"type":"Point"}
}
