{
  "type": "Feature",
  "properties": {
    "iso:country":"GB",
    "wof:name":"WS13 6RU",
    "wof:placetype":"postalcode"
},
  "geometry": {"coordinates":[-1.83129818003342,52.68234689099761],"type":"Point"}
}