{
  "type": "Feature",
  "properties": {
    "iso:country":"GB",
    "wof:name":"BH14 0BJ",
    "wof:placetype":"postalcode"
},
  "geometry": {"coordinates":[-1.9450621995929,50.72668073382275],"type":"Point"}
}