{
  "type": "Feature",
  "properties": {
    "iso:country": "GB",
    "wof:name": "BH14 0BJ",
    "wof:placetype": "postalcode"
  },
  "geometry": {"coordinates":[-1.945062,50.726681],"type":"Point"}
}
