{
  "type": "Feature",
  "properties": {
    "iso:country":"GB",
    "wof:name":"S66 9EY",
    "wof:placetype":"postalcode"
},
  "geometry": {"coordinates":[-1.25457847233714,53.39864041953869],"type":"Point"}
}