{
  "type": "Feature",
  "properties": {
    "date:inception_lower": "1980-01-01",
    "date:inception_upper": "1980-01-01",
    "iso:country": "GB",
    "wof:name": "DL12 0DE",
    "wof:placetype": "postalcode"
  },
  "geometry": {"coordinates":[-1.997452,54.608868],"type":"Point"}
}
