{
  "type": "Feature",
  "properties": {
    "date:inception_lower":"1980-01-01",
    "date:inception_upper":"1980-01-31",
    "iso:country":"GB",
    "wof:name":"DL12 0DE",
    "wof:placetype":"postalcode"
},
  "geometry": {"coordinates":[-1.997127,54.608743],"type":"Point"}
}