{
  "type": "Feature",
  "properties": {
    "iso:country":"GB",
    "wof:name":"N2 0RF",
    "wof:placetype":"postalcode"
},
  "geometry": {"coordinates":[-0.17698631911879,51.58225356329446],"type":"Point"}
}