{
  "type": "Feature",
  "properties": {
    "iso:country": "GB",
    "wof:name": "N2 0RF",
    "wof:placetype": "postalcode"
  },
  "geometry": {"coordinates":[-0.176986,51.582254],"type":"Point"}
}
