{
  "type": "Feature",
  "properties": {
    "date:inception_lower": "1991-07-01",
    "date:inception_upper": "1991-07-01",
    "iso:country": "GB",
    "wof:name": "KA9 2ND",
    "wof:placetype": "postalcode"
  },
  "geometry": {"coordinates":[-4.603982,55.484289],"type":"Point"}
}
