{
  "type": "Feature",
  "properties": {
    "iso:country":"GB",
    "wof:name":"CR0 6RU",
    "wof:placetype":"postalcode"
},
  "geometry": {"coordinates":[-0.07115753017443,51.38256211163164],"type":"Point"}
}