{
  "type": "Feature",
  "properties": {
    "iso:country": "GB",
    "wof:name": "CR0 6RU",
    "wof:placetype": "postalcode"
  },
  "geometry": {"coordinates":[-0.071157,51.382562],"type":"Point"}
}
