{
  "type": "Feature",
  "properties": {
    "iso:country":"GB",
    "wof:name":"DN40 2EN",
    "wof:placetype":"postalcode"
},
  "geometry": {"coordinates":[-0.22397892890786,53.61619560707311],"type":"Point"}
}