{
  "type": "Feature",
  "properties": {
    "iso:country": "GB",
    "wof:name": "CM23 3QH",
    "wof:placetype": "postalcode"
  },
  "geometry": {"coordinates":[0.154538,51.865486],"type":"Point"}
}
