{
  "type": "Feature",
  "properties": {
    "iso:country":"GB",
    "wof:name":"CM23 3QH",
    "wof:placetype":"postalcode"
},
  "geometry": {"coordinates":[0.15453804040725,51.86548603287166],"type":"Point"}
}