{
  "type": "Feature",
  "properties": {
    "iso:country":"GB",
    "wof:name":"SM6 9HL",
    "wof:placetype":"postalcode"
},
  "geometry": {"coordinates":[-0.13014579883919,51.35446291233193],"type":"Point"}
}