{
  "type": "Feature",
  "properties": {
    "iso:country":"GB",
    "wof:name":"SW19 6EQ",
    "wof:placetype":"postalcode"
},
  "geometry": {"coordinates":[-0.21862013499478,51.44353738846877],"type":"Point"}
}