{
  "type": "Feature",
  "properties": {
    "date:inception_lower": "2018-08-01",
    "date:inception_upper": "2018-08-01",
    "iso:country": "GB",
    "wof:name": "PO9 6BF",
    "wof:placetype": "postalcode"
  },
  "geometry": {"coordinates":[-0.961845,50.887812],"type":"Point"}
}
