{
  "type": "Feature",
  "properties": {
    "iso:country":"GB",
    "wof:name":"DD8 5LX",
    "wof:placetype":"postalcode"
},
  "geometry": {"coordinates":[-3.05029664796346,56.65691249133088],"type":"Point"}
}