{
  "type": "Feature",
  "properties": {
    "iso:country":"GB",
    "wof:name":"BD1 3RU",
    "wof:placetype":"postalcode"
},
  "geometry": {"coordinates":[-1.75996714800909,53.79836612435726],"type":"Point"}
}