{
  "type": "Feature",
  "properties": {
    "date:inception_lower":"2004-03-01",
    "date:inception_upper":"2004-03-31",
    "iso:country":"GB",
    "wof:name":"BD4 7QA",
    "wof:placetype":"postalcode"
},
  "geometry": {"coordinates":[-1.727822,53.777985],"type":"Point"}
}