{
  "type": "Feature",
  "properties": {
    "iso:country":"GB",
    "wof:name":"BD4 7QA",
    "wof:placetype":"postalcode"
},
  "geometry": {"coordinates":[-1.7278221289497,53.77798467219888],"type":"Point"}
}