{
  "type": "Feature",
  "properties": {
    "iso:country": "GB",
    "wof:name": "CF24 5FB",
    "wof:placetype": "postalcode"
  },
  "geometry": {"coordinates":[-3.153317,51.477397],"type":"Point"}
}
