{
  "type": "Feature",
  "properties": {
    "iso:country":"GB",
    "wof:name":"NE61 2DN",
    "wof:placetype":"postalcode"
},
  "geometry": {"coordinates":[-1.68970330542993,55.15361242761052],"type":"Point"}
}