{
  "type": "Feature",
  "properties": {
    "iso:country":"GB",
    "wof:name":"HA5 3YY",
    "wof:placetype":"postalcode"
},
  "geometry": {"coordinates":[-0.40043569857851,51.59944046753363],"type":"Point"}
}