{
  "type": "Feature",
  "properties": {
    "iso:country": "GB",
    "wof:name": "HA5 3YY",
    "wof:placetype": "postalcode"
  },
  "geometry": {"coordinates":[-0.400436,51.59944],"type":"Point"}
}
