{
  "type": "Feature",
  "properties": {
    "date:inception_lower":"1983-01-01",
    "date:inception_upper":"1983-01-31",
    "iso:country":"GB",
    "wof:name":"HA5 3YY",
    "wof:placetype":"postalcode"
},
  "geometry": {"coordinates":[-0.400436,51.59944],"type":"Point"}
}