{
  "type": "Feature",
  "properties": {
    "date:inception_lower": "2014-06-01",
    "date:inception_upper": "2014-06-01",
    "iso:country": "GB",
    "wof:name": "PR25 5AB",
    "wof:placetype": "postalcode"
  },
  "geometry": {"coordinates":[-2.671545,53.700784],"type":"Point"}
}
