{
  "type": "Feature",
  "properties": {
    "iso:country": "GB",
    "wof:name": "WS3 2JH",
    "wof:placetype": "postalcode"
  },
  "geometry": {"coordinates":[-2.005047,52.616705],"type":"Point"}
}
