{
  "type": "Feature",
  "properties": {
    "iso:country":"GB",
    "wof:name":"CB22 5BN",
    "wof:placetype":"postalcode"
},
  "geometry": {"coordinates":[0.15158150976508,52.14446971165494],"type":"Point"}
}