{
  "type": "Feature",
  "properties": {
    "iso:country":"GB",
    "wof:name":"TA8 2TU",
    "wof:placetype":"postalcode"
},
  "geometry": {"coordinates":[-2.98192931817709,51.24085958734452],"type":"Point"}
}