{
  "type": "Feature",
  "properties": {
    "iso:country":"GB",
    "wof:name":"BS36 1SF",
    "wof:placetype":"postalcode"
},
  "geometry": {"coordinates":[-2.51263932550087,51.52952359773995],"type":"Point"}
}