{
  "type": "Feature",
  "properties": {
    "iso:country":"GB",
    "wof:name":"SE5 8BU",
    "wof:placetype":"postalcode"
},
  "geometry": {"coordinates":[-0.0868012912789,51.46433736678223],"type":"Point"}
}