{
  "type": "Feature",
  "properties": {
    "date:inception_lower": "2013-09-01",
    "date:inception_upper": "2013-09-01",
    "iso:country": "GB",
    "wof:name": "NN6 7BZ",
    "wof:placetype": "postalcode"
  },
  "geometry": {"coordinates":[-1.165752,52.352407],"type":"Point"}
}
