{
  "type": "Feature",
  "properties": {
    "iso:country":"GB",
    "wof:name":"NN6 7BZ",
    "wof:placetype":"postalcode"
},
  "geometry": {"coordinates":[-1.16352148234156,52.35227564127526],"type":"Point"}
}