{
  "type": "Feature",
  "properties": {
    "iso:country": "GB",
    "wof:name": "MK18 5DR",
    "wof:placetype": "postalcode"
  },
  "geometry": {"coordinates":[-1.048253,52.007411],"type":"Point"}
}
