{
  "type": "Feature",
  "properties": {
    "iso:country":"GB",
    "wof:name":"SG6 4DD",
    "wof:placetype":"postalcode"
},
  "geometry": {"coordinates":[-0.23660919738968,51.98091777130884],"type":"Point"}
}