{
  "type": "Feature",
  "properties": {
    "date:inception_lower":"2012-02-01",
    "date:inception_upper":"2012-02-29",
    "iso:country":"GB",
    "wof:name":"EC1R 0JG",
    "wof:placetype":"postalcode"
},
  "geometry": {"coordinates":[-0.109311,51.525088],"type":"Point"}
}