{
  "type": "Feature",
  "properties": {
    "iso:country":"GB",
    "wof:name":"EC1R 0JG",
    "wof:placetype":"postalcode"
},
  "geometry": {"coordinates":[-0.10931067368631,51.52508762328689],"type":"Point"}
}