{
  "type": "Feature",
  "properties": {
    "iso:country":"GB",
    "wof:name":"SE1 1GA",
    "wof:placetype":"postalcode"
},
  "geometry": {"coordinates":[-0.0940485358663,51.50047078301569],"type":"Point"}
}