{
  "type": "Feature",
  "properties": {
    "iso:country": "GB",
    "wof:name": "SE1 1GA",
    "wof:placetype": "postalcode"
  },
  "geometry": {"coordinates":[-0.094048,51.500471],"type":"Point"}
}
