{
  "type": "Feature",
  "properties": {
    "iso:country":"GB",
    "wof:name":"GU21 3AN",
    "wof:placetype":"postalcode"
},
  "geometry": {"coordinates":[-0.58125489577473,51.31985252994494],"type":"Point"}
}