{
  "type": "Feature",
  "properties": {
    "iso:country":"GB",
    "wof:name":"LL52 0BH",
    "wof:placetype":"postalcode"
},
  "geometry": {"coordinates":[-4.23953795878571,52.92567148235051],"type":"Point"}
}