{
  "type": "Feature",
  "properties": {
    "date:inception_lower":"1981-06-01",
    "date:inception_upper":"1981-06-30",
    "iso:country":"GB",
    "wof:name":"EX23 9JP",
    "wof:placetype":"postalcode"
},
  "geometry": {"coordinates":[-4.53374,50.89723],"type":"Point"}
}