{
  "type": "Feature",
  "properties": {
    "date:inception_lower": "1981-06-01",
    "date:inception_upper": "1981-06-01",
    "iso:country": "GB",
    "wof:name": "EX23 9JP",
    "wof:placetype": "postalcode"
  },
  "geometry": {"coordinates":[-4.533801,50.897244],"type":"Point"}
}
