{
  "type": "Feature",
  "properties": {
    "iso:country":"GB",
    "wof:name":"CF33 4EY",
    "wof:placetype":"postalcode"
},
  "geometry": {"coordinates":[-3.70062393296147,51.51776512167],"type":"Point"}
}