{
  "type": "Feature",
  "properties": {
    "iso:country": "GB",
    "wof:name": "NG31 8RA",
    "wof:placetype": "postalcode"
  },
  "geometry": {"coordinates":[-0.668494,52.913005],"type":"Point"}
}
