{
  "type": "Feature",
  "properties": {
    "iso:country":"GB",
    "wof:name":"S9 1RX",
    "wof:placetype":"postalcode"
},
  "geometry": {"coordinates":[-1.39520897181296,53.41699910065253],"type":"Point"}
}