{
  "type": "Feature",
  "properties": {
    "iso:country":"GB",
    "wof:name":"BN25 3PY",
    "wof:placetype":"postalcode"
},
  "geometry": {"coordinates":[0.11578115247625,50.77825219978457],"type":"Point"}
}