{
  "type": "Feature",
  "properties": {
    "date:inception_lower":"1998-12-01",
    "date:inception_upper":"1998-12-31",
    "iso:country":"GB",
    "wof:name":"G69 0GD",
    "wof:placetype":"postalcode"
},
  "geometry": {"coordinates":[-4.080605,55.911496],"type":"Point"}
}