{
  "type": "Feature",
  "properties": {
    "iso:country": "GB",
    "wof:name": "G69 0GD",
    "wof:placetype": "postalcode"
  },
  "geometry": {"coordinates":[-4.080605,55.911496],"type":"Point"}
}
