{
  "type": "Feature",
  "properties": {
    "iso:country": "GB",
    "wof:name": "NE65 0YN",
    "wof:placetype": "postalcode"
  },
  "geometry": {"coordinates":[-1.626197,55.339783],"type":"Point"}
}
