{
  "type": "Feature",
  "properties": {
    "iso:country":"GB",
    "wof:name":"NE65 0YN",
    "wof:placetype":"postalcode"
},
  "geometry": {"coordinates":[-1.6261967827225,55.33978304693544],"type":"Point"}
}