{
  "type": "Feature",
  "properties": {
    "date:inception_lower": "1991-09-01",
    "date:inception_upper": "1991-09-01",
    "iso:country": "GB",
    "wof:name": "NE65 0YN",
    "wof:placetype": "postalcode"
  },
  "geometry": {"coordinates":[-1.626197,55.339783],"type":"Point"}
}
