{
  "type": "Feature",
  "properties": {
    "iso:country": "GB",
    "wof:name": "CA14 4SY",
    "wof:placetype": "postalcode"
  },
  "geometry": {"coordinates":[-3.463273,54.610727],"type":"Point"}
}
