{
  "type": "Feature",
  "properties": {
    "iso:country":"GB",
    "wof:name":"BB4 9PF",
    "wof:placetype":"postalcode"
},
  "geometry": {"coordinates":[-2.25170307041802,53.71361981549],"type":"Point"}
}