{
  "type": "Feature",
  "properties": {
    "date:inception_lower": "1980-01-01",
    "date:inception_upper": "1980-01-01",
    "iso:country": "GB",
    "wof:name": "G42 8ES",
    "wof:placetype": "postalcode"
  },
  "geometry": {"coordinates":[-4.25623,55.833456],"type":"Point"}
}
