{
  "type": "Feature",
  "properties": {
    "date:inception_lower":"2005-09-01",
    "date:inception_upper":"2005-09-30",
    "iso:country":"GB",
    "wof:name":"SS15 5GP",
    "wof:placetype":"postalcode"
},
  "geometry": {"coordinates":[0.43399,51.569219],"type":"Point"}
}