{
  "type": "Feature",
  "properties": {
    "iso:country":"GB",
    "wof:name":"OL12 6JT",
    "wof:placetype":"postalcode"
},
  "geometry": {"coordinates":[-2.16056210971001,53.62878479612604],"type":"Point"}
}