{
  "type": "Feature",
  "properties": {
    "iso:country":"GB",
    "wof:name":"E17 4QS",
    "wof:placetype":"postalcode"
},
  "geometry": {"coordinates":[-0.02056539570237,51.58856804384875],"type":"Point"}
}