{
  "type": "Feature",
  "properties": {
    "iso:country": "GB",
    "wof:name": "NR3 4RW",
    "wof:placetype": "postalcode"
  },
  "geometry": {"coordinates":[1.306951,52.641025],"type":"Point"}
}
