{
  "type": "Feature",
  "properties": {
    "iso:country": "GB",
    "wof:name": "RG12 8YS",
    "wof:placetype": "postalcode"
  },
  "geometry": {"coordinates":[-0.773942,51.407966],"type":"Point"}
}
