{
  "type": "Feature",
  "properties": {
    "iso:country":"GB",
    "wof:name":"RG12 8YS",
    "wof:placetype":"postalcode"
},
  "geometry": {"coordinates":[-0.7739420641463,51.40796562952537],"type":"Point"}
}