{
  "type": "Feature",
  "properties": {
    "iso:country": "GB",
    "wof:name": "BS48 2QN",
    "wof:placetype": "postalcode"
  },
  "geometry": {"coordinates":[-2.766186,51.427542],"type":"Point"}
}
