{
  "type": "Feature",
  "properties": {
    "date:inception_lower": "1980-01-01",
    "date:inception_upper": "1980-01-01",
    "iso:country": "GB",
    "wof:name": "KT17 4PP",
    "wof:placetype": "postalcode"
  },
  "geometry": {"coordinates":[-0.262112,51.33234],"type":"Point"}
}
