{
  "type": "Feature",
  "properties": {
    "iso:country":"GB",
    "wof:name":"KT17 4PP",
    "wof:placetype":"postalcode"
},
  "geometry": {"coordinates":[-0.26162290609751,51.33188402789909],"type":"Point"}
}