{
  "type": "Feature",
  "properties": {
    "iso:country":"GB",
    "wof:name":"OL10 1NX",
    "wof:placetype":"postalcode"
},
  "geometry": {"coordinates":[-2.21210134739786,53.59098973246563],"type":"Point"}
}