{
  "type": "Feature",
  "properties": {
    "iso:country":"GB",
    "wof:name":"NE23 2FH",
    "wof:placetype":"postalcode"
},
  "geometry": {"coordinates":[-1.57115082016757,55.09181561946134],"type":"Point"}
}