{
  "type": "Feature",
  "properties": {
    "iso:country":"GB",
    "wof:name":"KT12 5NF",
    "wof:placetype":"postalcode"
},
  "geometry": {"coordinates":[-0.40541893444873,51.36774157422126],"type":"Point"}
}