{
  "type": "Feature",
  "properties": {
    "iso:country":"GB",
    "wof:name":"BA5 1UF",
    "wof:placetype":"postalcode"
},
  "geometry": {"coordinates":[-2.65762700164489,51.20540112282839],"type":"Point"}
}