{
  "type": "Feature",
  "properties": {
    "date:inception_lower": "1990-07-01",
    "date:inception_upper": "1990-07-01",
    "iso:country": "GB",
    "wof:name": "DY1 2UE",
    "wof:placetype": "postalcode"
  },
  "geometry": {"coordinates":[-2.117331,52.513119],"type":"Point"}
}
