{
  "type": "Feature",
  "properties": {
    "iso:country":"GB",
    "wof:name":"PO9 1AA",
    "wof:placetype":"postalcode"
},
  "geometry": {"coordinates":[-0.97986413721829,50.85116372331768],"type":"Point"}
}