{
  "type": "Feature",
  "properties": {
    "iso:country":"GB",
    "wof:name":"PO15 7BW",
    "wof:placetype":"postalcode"
},
  "geometry": {"coordinates":[-1.26441607500626,50.88023633995027],"type":"Point"}
}