{
  "type": "Feature",
  "properties": {
    "date:inception_lower": "1980-01-01",
    "date:inception_upper": "1980-01-01",
    "iso:country": "GB",
    "wof:name": "GL52 5HD",
    "wof:placetype": "postalcode"
  },
  "geometry": {"coordinates":[-2.051478,51.909006],"type":"Point"}
}
