{
  "type": "Feature",
  "properties": {
    "iso:country":"GB",
    "wof:name":"BD6 2EJ",
    "wof:placetype":"postalcode"
},
  "geometry": {"coordinates":[-1.79568063291003,53.75968493342311],"type":"Point"}
}