{
  "type": "Feature",
  "properties": {
    "iso:country": "GB",
    "wof:name": "HR4 8AA",
    "wof:placetype": "postalcode"
  },
  "geometry": {"coordinates":[-2.723816,52.087229],"type":"Point"}
}
