{
  "type": "Feature",
  "properties": {
    "iso:country":"GB",
    "wof:name":"HR4 8AA",
    "wof:placetype":"postalcode"
},
  "geometry": {"coordinates":[-2.72381607623441,52.08722878316176],"type":"Point"}
}