{
  "type": "Feature",
  "properties": {
    "iso:country":"GB",
    "wof:name":"NG8 4AY",
    "wof:placetype":"postalcode"
},
  "geometry": {"coordinates":[-1.22866826163383,52.96796025413249],"type":"Point"}
}