{
  "type": "Feature",
  "properties": {
    "iso:country":"GB",
    "wof:name":"SP6 1BZ",
    "wof:placetype":"postalcode"
},
  "geometry": {"coordinates":[-1.80716590699381,50.92735539848903],"type":"Point"}
}