{
  "type": "Feature",
  "properties": {
    "iso:country":"GB",
    "wof:name":"SK1 4EE",
    "wof:placetype":"postalcode"
},
  "geometry": {"coordinates":[-2.14827342964439,53.40588865214436],"type":"Point"}
}