{
  "type": "Feature",
  "properties": {
    "iso:country": "GB",
    "wof:name": "SK1 4EE",
    "wof:placetype": "postalcode"
  },
  "geometry": {"coordinates":[-2.148273,53.405889],"type":"Point"}
}
