{
  "type": "Feature",
  "properties": {
    "date:inception_lower": "1980-01-01",
    "date:inception_upper": "1980-01-01",
    "iso:country": "GB",
    "wof:name": "NR19 1JS",
    "wof:placetype": "postalcode"
  },
  "geometry": {"coordinates":[0.938218,52.66361],"type":"Point"}
}
