{
  "type": "Feature",
  "properties": {
    "iso:country":"GB",
    "wof:name":"NR19 1JS",
    "wof:placetype":"postalcode"
},
  "geometry": {"coordinates":[0.93821752328468,52.66361011778793],"type":"Point"}
}