{
  "type": "Feature",
  "properties": {
    "iso:country":"GB",
    "wof:name":"TS3 7BB",
    "wof:placetype":"postalcode"
},
  "geometry": {"coordinates":[-1.21296297980488,54.56393857099177],"type":"Point"}
}