{
  "type": "Feature",
  "properties": {
    "iso:country": "GB",
    "wof:name": "SA41 3RE",
    "wof:placetype": "postalcode"
  },
  "geometry": {"coordinates":[-4.649072,51.972235],"type":"Point"}
}
