{
  "type": "Feature",
  "properties": {
    "date:inception_lower": "2000-06-01",
    "date:inception_upper": "2000-06-01",
    "iso:country": "GB",
    "wof:name": "SA41 3RE",
    "wof:placetype": "postalcode"
  },
  "geometry": {"coordinates":[-4.649573,51.972592],"type":"Point"}
}
