{
  "type": "Feature",
  "properties": {
    "iso:country": "GB",
    "wof:name": "NR23 1QL",
    "wof:placetype": "postalcode"
  },
  "geometry": {"coordinates":[0.93806,52.950083],"type":"Point"}
}
