{
  "type": "Feature",
  "properties": {
    "iso:country":"GB",
    "wof:name":"LS28 9NR",
    "wof:placetype":"postalcode"
},
  "geometry": {"coordinates":[-1.65970995847931,53.790295232147],"type":"Point"}
}