{
  "type": "Feature",
  "properties": {
    "iso:country":"GB",
    "wof:name":"G12 0HY",
    "wof:placetype":"postalcode"
},
  "geometry": {"coordinates":[-4.30448191357764,55.88916499677457],"type":"Point"}
}