{
  "type": "Feature",
  "properties": {
    "date:inception_lower": "1998-06-01",
    "date:inception_upper": "1998-06-01",
    "iso:country": "GB",
    "wof:name": "WA4 6SH",
    "wof:placetype": "postalcode"
  },
  "geometry": {"coordinates":[-2.614006,53.363377],"type":"Point"}
}
