{
  "type": "Feature",
  "properties": {
    "iso:country":"GB",
    "wof:name":"WA4 6SH",
    "wof:placetype":"postalcode"
},
  "geometry": {"coordinates":[-2.61400636812796,53.36337662050623],"type":"Point"}
}