{
  "type": "Feature",
  "properties": {
    "iso:country":"GB",
    "wof:name":"LA12 8NZ",
    "wof:placetype":"postalcode"
},
  "geometry": {"coordinates":[-2.96168309840613,54.25115890466287],"type":"Point"}
}