{
  "type": "Feature",
  "properties": {
    "iso:country": "GB",
    "wof:name": "S63 7SR",
    "wof:placetype": "postalcode"
  },
  "geometry": {"coordinates":[-1.346774,53.494667],"type":"Point"}
}
