{
  "type": "Feature",
  "properties": {
    "iso:country":"GB",
    "wof:name":"S63 7SR",
    "wof:placetype":"postalcode"
},
  "geometry": {"coordinates":[-1.3467741347297,53.49466665120703],"type":"Point"}
}