{
  "type": "Feature",
  "properties": {
    "date:inception_lower": "1999-06-01",
    "date:inception_upper": "1999-06-01",
    "iso:country": "GB",
    "wof:name": "CF11 8HG",
    "wof:placetype": "postalcode"
  },
  "geometry": {"coordinates":[-3.20035,51.48027],"type":"Point"}
}
