{
  "type": "Feature",
  "properties": {
    "date:inception_lower":"2015-01-01",
    "date:inception_upper":"2015-01-31",
    "iso:country":"GB",
    "wof:name":"WV1 9ZN",
    "wof:placetype":"postalcode"
},
  "geometry": {"coordinates":[-2.114955,52.588468],"type":"Point"}
}