{
  "type": "Feature",
  "properties": {
    "date:inception_lower": "1980-01-01",
    "date:inception_upper": "1980-01-01",
    "iso:country": "GB",
    "wof:name": "PA19 1EX",
    "wof:placetype": "postalcode"
  },
  "geometry": {"coordinates":[-4.836545,55.951812],"type":"Point"}
}
