{
  "type": "Feature",
  "properties": {
    "iso:country": "GB",
    "wof:name": "PA19 1EX",
    "wof:placetype": "postalcode"
  },
  "geometry": {"coordinates":[-4.836545,55.951812],"type":"Point"}
}
