{
  "type": "Feature",
  "properties": {
    "iso:country":"GB",
    "wof:name":"PA19 1EX",
    "wof:placetype":"postalcode"
},
  "geometry": {"coordinates":[-4.83654493844211,55.95181150327223],"type":"Point"}
}