{
  "type": "Feature",
  "properties": {
    "date:inception_lower": "1980-01-01",
    "date:inception_upper": "1980-01-01",
    "iso:country": "GB",
    "wof:name": "PL25 3SN",
    "wof:placetype": "postalcode"
  },
  "geometry": {"coordinates":[-4.747297,50.3345],"type":"Point"}
}
