{
  "type": "Feature",
  "properties": {
    "iso:country":"GB",
    "wof:name":"PL25 3SN",
    "wof:placetype":"postalcode"
},
  "geometry": {"coordinates":[-4.74729705892944,50.33449965513784],"type":"Point"}
}