{
  "type": "Feature",
  "properties": {
    "iso:country":"GB",
    "wof:name":"RG9 5SH",
    "wof:placetype":"postalcode"
},
  "geometry": {"coordinates":[-1.02473593055089,51.58342072950612],"type":"Point"}
}