{
  "type": "Feature",
  "properties": {
    "iso:country":"GB",
    "wof:name":"S63 0SD",
    "wof:placetype":"postalcode"
},
  "geometry": {"coordinates":[-1.32321742995766,53.54653445034426],"type":"Point"}
}