{
  "type": "Feature",
  "properties": {
    "iso:country":"GB",
    "wof:name":"CF45 3DH",
    "wof:placetype":"postalcode"
},
  "geometry": {"coordinates":[-3.39388840171858,51.68515021326714],"type":"Point"}
}