{
  "type": "Feature",
  "properties": {
    "date:inception_lower": "1980-01-01",
    "date:inception_upper": "1980-01-01",
    "iso:country": "GB",
    "wof:name": "PO15 5PW",
    "wof:placetype": "postalcode"
  },
  "geometry": {"coordinates":[-1.215955,50.855902],"type":"Point"}
}
