{
  "type": "Feature",
  "properties": {
    "iso:country":"GB",
    "wof:name":"PO15 5PW",
    "wof:placetype":"postalcode"
},
  "geometry": {"coordinates":[-1.21595494073034,50.85590174112566],"type":"Point"}
}