{
  "type": "Feature",
  "properties": {
    "iso:country": "GB",
    "wof:name": "YO7 4HY",
    "wof:placetype": "postalcode"
  },
  "geometry": {"coordinates":[-1.472996,54.232747],"type":"Point"}
}
