{
  "type": "Feature",
  "properties": {
    "date:inception_lower": "1995-12-01",
    "date:inception_upper": "1995-12-01",
    "iso:country": "GB",
    "wof:name": "YO7 4HY",
    "wof:placetype": "postalcode"
  },
  "geometry": {"coordinates":[-1.472996,54.232747],"type":"Point"}
}
