{
  "type": "Feature",
  "properties": {
    "iso:country": "GB",
    "wof:name": "SK12 2NQ",
    "wof:placetype": "postalcode"
  },
  "geometry": {"coordinates":[-2.055752,53.36098],"type":"Point"}
}
