{
  "type": "Feature",
  "properties": {
    "iso:country":"GB",
    "wof:name":"SK12 2NQ",
    "wof:placetype":"postalcode"
},
  "geometry": {"coordinates":[-2.05575229515706,53.36098003070642],"type":"Point"}
}