{
  "type": "Feature",
  "properties": {
    "iso:country":"GB",
    "wof:name":"WV6 8QA",
    "wof:placetype":"postalcode"
},
  "geometry": {"coordinates":[-2.1643384053841,52.59888270954435],"type":"Point"}
}