{
  "type": "Feature",
  "properties": {
    "iso:country": "GB",
    "wof:name": "YO62 6RZ",
    "wof:placetype": "postalcode"
  },
  "geometry": {"coordinates":[-0.858122,54.262669],"type":"Point"}
}
