{
  "type": "Feature",
  "properties": {
    "date:inception_lower": "1980-01-01",
    "date:inception_upper": "1980-01-01",
    "iso:country": "GB",
    "wof:name": "BS25 1QP",
    "wof:placetype": "postalcode"
  },
  "geometry": {"coordinates":[-2.78803,51.320979],"type":"Point"}
}
