{
  "type": "Feature",
  "properties": {
    "date:inception_lower": "1980-01-01",
    "date:inception_upper": "1980-01-01",
    "iso:country": "GB",
    "wof:name": "BB8 7QJ",
    "wof:placetype": "postalcode"
  },
  "geometry": {"coordinates":[-2.14461,53.879415],"type":"Point"}
}
