{
  "type": "Feature",
  "properties": {
    "iso:country":"GB",
    "wof:name":"CT20 1NQ",
    "wof:placetype":"postalcode"
},
  "geometry": {"coordinates":[1.18398506549676,51.08445230747427],"type":"Point"}
}