{
  "type": "Feature",
  "properties": {
    "date:inception_lower": "1980-01-01",
    "date:inception_upper": "1980-01-01",
    "iso:country": "GB",
    "wof:name": "HD5 0AE",
    "wof:placetype": "postalcode"
  },
  "geometry": {"coordinates":[-1.735217,53.64913],"type":"Point"}
}
