{
  "type": "Feature",
  "properties": {
    "iso:country":"GB",
    "wof:name":"HD5 0AE",
    "wof:placetype":"postalcode"
},
  "geometry": {"coordinates":[-1.73521748663545,53.64912967835722],"type":"Point"}
}