{
  "type": "Feature",
  "properties": {
    "iso:country":"GB",
    "wof:name":"BL8 4HB",
    "wof:placetype":"postalcode"
},
  "geometry": {"coordinates":[-2.33918693150673,53.62880703548881],"type":"Point"}
}