{
  "type": "Feature",
  "properties": {
    "date:inception_lower": "1992-08-01",
    "date:inception_upper": "1992-08-01",
    "iso:country": "GB",
    "wof:name": "DE75 7DT",
    "wof:placetype": "postalcode"
  },
  "geometry": {"coordinates":[-1.349726,53.010304],"type":"Point"}
}
