{
  "type": "Feature",
  "properties": {
    "iso:country": "GB",
    "wof:name": "DE75 7DT",
    "wof:placetype": "postalcode"
  },
  "geometry": {"coordinates":[-1.349726,53.010304],"type":"Point"}
}
