{
  "type": "Feature",
  "properties": {
    "iso:country":"GB",
    "wof:name":"DA6 7AL",
    "wof:placetype":"postalcode"
},
  "geometry": {"coordinates":[0.14075786023523,51.45328934065938],"type":"Point"}
}