{
  "type": "Feature",
  "properties": {
    "iso:country":"GB",
    "wof:name":"BD12 9JX",
    "wof:placetype":"postalcode"
},
  "geometry": {"coordinates":[-1.76841831779261,53.73306673922605],"type":"Point"}
}