{
  "type": "Feature",
  "properties": {
    "iso:country":"GB",
    "wof:name":"EX4 7HD",
    "wof:placetype":"postalcode"
},
  "geometry": {"coordinates":[-3.51007276559081,50.73719957574804],"type":"Point"}
}