{
  "type": "Feature",
  "properties": {
    "iso:country":"GB",
    "wof:name":"LL52 0BJ",
    "wof:placetype":"postalcode"
},
  "geometry": {"coordinates":[-4.23790896796949,52.92610679277045],"type":"Point"}
}