{
  "type": "Feature",
  "properties": {
    "date:inception_lower":"1993-08-01",
    "date:inception_upper":"1993-08-31",
    "iso:country":"GB",
    "wof:name":"LL52 0BJ",
    "wof:placetype":"postalcode"
},
  "geometry": {"coordinates":[-4.237909,52.926107],"type":"Point"}
}