{
  "type": "Feature",
  "properties": {
    "iso:country":"GB",
    "wof:name":"EX5 1EU",
    "wof:placetype":"postalcode"
},
  "geometry": {"coordinates":[-3.37205403302408,50.69791487650129],"type":"Point"}
}