{
  "type": "Feature",
  "properties": {
    "iso:country": "GB",
    "wof:name": "EX5 1EU",
    "wof:placetype": "postalcode"
  },
  "geometry": {"coordinates":[-3.372054,50.697915],"type":"Point"}
}
