{
  "type": "Feature",
  "properties": {
    "date:inception_lower": "2004-09-01",
    "date:inception_upper": "2004-09-01",
    "iso:country": "GB",
    "wof:name": "LE2 7FZ",
    "wof:placetype": "postalcode"
  },
  "geometry": {"coordinates":[-1.141477,52.62346],"type":"Point"}
}
