{
  "type": "Feature",
  "properties": {
    "iso:country":"GB",
    "wof:name":"LE2 7FZ",
    "wof:placetype":"postalcode"
},
  "geometry": {"coordinates":[-1.14147730399478,52.62345997299946],"type":"Point"}
}