{
  "type": "Feature",
  "properties": {
    "date:inception_lower": "1993-01-01",
    "date:inception_upper": "1993-01-01",
    "iso:country": "GB",
    "wof:name": "GL1 4JD",
    "wof:placetype": "postalcode"
  },
  "geometry": {"coordinates":[-2.230485,51.856852],"type":"Point"}
}
