{
  "type": "Feature",
  "properties": {
    "iso:country":"GB",
    "wof:name":"BN3 3RJ",
    "wof:placetype":"postalcode"
},
  "geometry": {"coordinates":[-0.17451002662129,50.83224373151191],"type":"Point"}
}