{
  "type": "Feature",
  "properties": {
    "iso:country": "GB",
    "wof:name": "SW14 8HS",
    "wof:placetype": "postalcode"
  },
  "geometry": {"coordinates":[-0.262522,51.470113],"type":"Point"}
}
