{
  "type": "Feature",
  "properties": {
    "iso:country":"GB",
    "wof:name":"SW14 8HS",
    "wof:placetype":"postalcode"
},
  "geometry": {"coordinates":[-0.26252219231183,51.47011254120708],"type":"Point"}
}