{
  "type": "Feature",
  "properties": {
    "date:inception_lower": "1990-02-01",
    "date:inception_upper": "1990-02-01",
    "iso:country": "GB",
    "wof:name": "L30 1SP",
    "wof:placetype": "postalcode"
  },
  "geometry": {"coordinates":[-2.964391,53.478173],"type":"Point"}
}
