{
  "type": "Feature",
  "properties": {
    "iso:country":"GB",
    "wof:name":"LE5 5NB",
    "wof:placetype":"postalcode"
},
  "geometry": {"coordinates":[-1.09896739405829,52.62677635072048],"type":"Point"}
}