{
  "type": "Feature",
  "properties": {
    "iso:country": "GB",
    "wof:name": "LE5 5NB",
    "wof:placetype": "postalcode"
  },
  "geometry": {"coordinates":[-1.098967,52.626776],"type":"Point"}
}
