{
  "type": "Feature",
  "properties": {
    "iso:country":"GB",
    "wof:name":"TW19 7RH",
    "wof:placetype":"postalcode"
},
  "geometry": {"coordinates":[-0.47643161046252,51.44856516736473],"type":"Point"}
}