{
  "type": "Feature",
  "properties": {
    "date:inception_lower": "1980-01-01",
    "date:inception_upper": "1980-01-01",
    "iso:country": "GB",
    "wof:name": "TW19 7RH",
    "wof:placetype": "postalcode"
  },
  "geometry": {"coordinates":[-0.476432,51.448565],"type":"Point"}
}
