{
  "type": "Feature",
  "properties": {
    "date:inception_lower": "1996-06-01",
    "date:inception_upper": "1996-06-01",
    "iso:country": "GB",
    "wof:name": "PA16 7ES",
    "wof:placetype": "postalcode"
  },
  "geometry": {"coordinates":[-4.785561,55.946865],"type":"Point"}
}
