{
  "type": "Feature",
  "properties": {
    "iso:country":"GB",
    "wof:name":"PA16 7ES",
    "wof:placetype":"postalcode"
},
  "geometry": {"coordinates":[-4.78527681878813,55.94710320581276],"type":"Point"}
}