{
  "type": "Feature",
  "properties": {
    "iso:country":"GB",
    "wof:name":"TQ12 3GX",
    "wof:placetype":"postalcode"
},
  "geometry": {"coordinates":[-3.58363765193769,50.58197691257954],"type":"Point"}
}