{
  "type": "Feature",
  "properties": {
    "iso:country": "GB",
    "wof:name": "TQ12 3GX",
    "wof:placetype": "postalcode"
  },
  "geometry": {"coordinates":[-3.583638,50.581977],"type":"Point"}
}
