{
  "type": "Feature",
  "properties": {
    "date:inception_lower":"1995-12-01",
    "date:inception_upper":"1995-12-31",
    "iso:country":"GB",
    "wof:name":"TQ12 3GX",
    "wof:placetype":"postalcode"
},
  "geometry": {"coordinates":[-3.583638,50.581977],"type":"Point"}
}