{
  "type": "Feature",
  "properties": {
    "date:inception_lower": "1980-01-01",
    "date:inception_upper": "1980-01-01",
    "iso:country": "GB",
    "wof:name": "SM3 8BZ",
    "wof:placetype": "postalcode"
  },
  "geometry": {"coordinates":[-0.216953,51.357452],"type":"Point"}
}
