{
  "type": "Feature",
  "properties": {
    "iso:country":"GB",
    "wof:name":"SM3 8BZ",
    "wof:placetype":"postalcode"
},
  "geometry": {"coordinates":[-0.21674654839253,51.35748589739852],"type":"Point"}
}