{
  "type": "Feature",
  "properties": {
    "iso:country":"GB",
    "wof:name":"CF81 8NY",
    "wof:placetype":"postalcode"
},
  "geometry": {"coordinates":[-3.23058564631252,51.68517662143871],"type":"Point"}
}