{
  "type": "Feature",
  "properties": {
    "iso:country": "GB",
    "wof:name": "CF81 8NY",
    "wof:placetype": "postalcode"
  },
  "geometry": {"coordinates":[-3.230586,51.685177],"type":"Point"}
}
