{
  "type": "Feature",
  "properties": {
    "iso:country":"GB",
    "wof:name":"BA2 2AQ",
    "wof:placetype":"postalcode"
},
  "geometry": {"coordinates":[-2.37771454950798,51.35233490171297],"type":"Point"}
}