{
  "type": "Feature",
  "properties": {
    "date:inception_lower": "1996-12-01",
    "date:inception_upper": "1996-12-01",
    "iso:country": "GB",
    "wof:name": "BA2 2AQ",
    "wof:placetype": "postalcode"
  },
  "geometry": {"coordinates":[-2.377715,51.352335],"type":"Point"}
}
