{
  "type": "Feature",
  "properties": {
    "iso:country":"GB",
    "wof:name":"DE13 0DA",
    "wof:placetype":"postalcode"
},
  "geometry": {"coordinates":[-1.61156032359822,52.8308244883414],"type":"Point"}
}