{
  "type": "Feature",
  "properties": {
    "iso:country":"GB",
    "wof:name":"BH6 5AW",
    "wof:placetype":"postalcode"
},
  "geometry": {"coordinates":[-1.81064655121635,50.73185490479771],"type":"Point"}
}