{
  "type": "Feature",
  "properties": {
    "date:inception_lower": "1980-01-01",
    "date:inception_upper": "1980-01-01",
    "iso:country": "GB",
    "wof:name": "GL18 2AT",
    "wof:placetype": "postalcode"
  },
  "geometry": {"coordinates":[-2.47818,51.981411],"type":"Point"}
}
