{
  "type": "Feature",
  "properties": {
    "iso:country": "GB",
    "wof:name": "GL18 2AT",
    "wof:placetype": "postalcode"
  },
  "geometry": {"coordinates":[-2.47818,51.981411],"type":"Point"}
}
