{
  "type": "Feature",
  "properties": {
    "date:inception_lower": "1998-06-01",
    "date:inception_upper": "1998-06-01",
    "iso:country": "GB",
    "wof:name": "YO19 4SB",
    "wof:placetype": "postalcode"
  },
  "geometry": {"coordinates":[-1.092851,53.901885],"type":"Point"}
}
