{
  "type": "Feature",
  "properties": {
    "iso:country":"GB",
    "wof:name":"YO19 4SB",
    "wof:placetype":"postalcode"
},
  "geometry": {"coordinates":[-1.0928138417332,53.90188476683898],"type":"Point"}
}