{
  "type": "Feature",
  "properties": {
    "iso:country":"GB",
    "wof:name":"WV14 9AY",
    "wof:placetype":"postalcode"
},
  "geometry": {"coordinates":[-2.09822591788118,52.53979409548835],"type":"Point"}
}