{
  "type": "Feature",
  "properties": {
    "iso:country":"GB",
    "wof:name":"IP27 0PS",
    "wof:placetype":"postalcode"
},
  "geometry": {"coordinates":[0.60884379793181,52.47108327032448],"type":"Point"}
}