{
  "type": "Feature",
  "properties": {
    "date:inception_lower": "2001-06-01",
    "date:inception_upper": "2001-06-01",
    "iso:country": "GB",
    "wof:name": "IP27 0PS",
    "wof:placetype": "postalcode"
  },
  "geometry": {"coordinates":[0.608844,52.471083],"type":"Point"}
}
