{
  "type": "Feature",
  "properties": {
    "date:inception_lower":"1990-07-01",
    "date:inception_upper":"1990-07-31",
    "iso:country":"GB",
    "wof:name":"WC1V 7RL",
    "wof:placetype":"postalcode"
},
  "geometry": {"coordinates":[-0.123769,51.516327],"type":"Point"}
}