{
  "type": "Feature",
  "properties": {
    "iso:country": "GB",
    "wof:name": "TA1 3BW",
    "wof:placetype": "postalcode"
  },
  "geometry": {"coordinates":[-3.090146,51.003006],"type":"Point"}
}
