{
  "type": "Feature",
  "properties": {
    "iso:country":"GB",
    "wof:name":"FY1 6RD",
    "wof:placetype":"postalcode"
},
  "geometry": {"coordinates":[-3.02932324770338,53.80496328993072],"type":"Point"}
}