{
  "type": "Feature",
  "properties": {
    "date:inception_lower": "1991-09-01",
    "date:inception_upper": "1991-09-01",
    "iso:country": "GB",
    "wof:name": "SA9 1LW",
    "wof:placetype": "postalcode"
  },
  "geometry": {"coordinates":[-3.757244,51.782083],"type":"Point"}
}
