{
  "type": "Feature",
  "properties": {
    "iso:country":"GB",
    "wof:name":"SA9 1LW",
    "wof:placetype":"postalcode"
},
  "geometry": {"coordinates":[-3.75724370306529,51.78208341022148],"type":"Point"}
}