{
  "type": "Feature",
  "properties": {
    "date:inception_lower":"1991-01-01",
    "date:inception_upper":"1991-01-31",
    "iso:country":"GB",
    "wof:name":"LN4 4AN",
    "wof:placetype":"postalcode"
},
  "geometry": {"coordinates":[-0.252421,53.030403],"type":"Point"}
}