{
  "type": "Feature",
  "properties": {
    "iso:country":"GB",
    "wof:name":"LN4 4AN",
    "wof:placetype":"postalcode"
},
  "geometry": {"coordinates":[-0.25242070475588,53.03040302406915],"type":"Point"}
}