{
  "type": "Feature",
  "properties": {
    "iso:country": "GB",
    "wof:name": "LN4 4AN",
    "wof:placetype": "postalcode"
  },
  "geometry": {"coordinates":[-0.252421,53.030403],"type":"Point"}
}
