{
  "type": "Feature",
  "properties": {
    "iso:country": "GB",
    "wof:name": "DL15 0SH",
    "wof:placetype": "postalcode"
  },
  "geometry": {"coordinates":[-1.688447,54.725323],"type":"Point"}
}
