{
  "type": "Feature",
  "properties": {
    "date:inception_lower":"2007-03-01",
    "date:inception_upper":"2007-03-31",
    "iso:country":"GB",
    "wof:name":"DL15 0SH",
    "wof:placetype":"postalcode"
},
  "geometry": {"coordinates":[-1.688447,54.725323],"type":"Point"}
}