{
  "type": "Feature",
  "properties": {
    "iso:country":"GB",
    "wof:name":"DL15 0SH",
    "wof:placetype":"postalcode"
},
  "geometry": {"coordinates":[-1.68844723965453,54.72532267374613],"type":"Point"}
}