{
  "type": "Feature",
  "properties": {
    "date:inception_lower": "1995-07-01",
    "date:inception_upper": "1995-07-01",
    "iso:country": "GB",
    "wof:name": "RG20 8HJ",
    "wof:placetype": "postalcode"
  },
  "geometry": {"coordinates":[-1.432388,51.444419],"type":"Point"}
}
