{
  "type": "Feature",
  "properties": {
    "iso:country": "GB",
    "wof:name": "RG20 8HJ",
    "wof:placetype": "postalcode"
  },
  "geometry": {"coordinates":[-1.432388,51.444419],"type":"Point"}
}
