{
  "type": "Feature",
  "properties": {
    "iso:country":"GB",
    "wof:name":"UB3 2NT",
    "wof:placetype":"postalcode"
},
  "geometry": {"coordinates":[-0.42776845565906,51.51576919980227],"type":"Point"}
}