{
  "type": "Feature",
  "properties": {
    "iso:country": "GB",
    "wof:name": "NG19 8FE",
    "wof:placetype": "postalcode"
  },
  "geometry": {"coordinates":[-1.197686,53.163687],"type":"Point"}
}
