{
  "type": "Feature",
  "properties": {
    "iso:country":"GB",
    "wof:name":"TN11 0BA",
    "wof:placetype":"postalcode"
},
  "geometry": {"coordinates":[0.33781249471722,51.21122747141727],"type":"Point"}
}