{
  "type": "Feature",
  "properties": {
    "date:inception_lower":"1980-01-01",
    "date:inception_upper":"1980-01-31",
    "iso:country":"GB",
    "wof:name":"BL5 3AG",
    "wof:placetype":"postalcode"
},
  "geometry": {"coordinates":[-2.522222,53.548736],"type":"Point"}
}