{
  "type": "Feature",
  "properties": {
    "iso:country": "GB",
    "wof:name": "EX8 1EH",
    "wof:placetype": "postalcode"
  },
  "geometry": {"coordinates":[-3.421626,50.619169],"type":"Point"}
}
