{
  "type": "Feature",
  "properties": {
    "iso:country":"GB",
    "wof:name":"EX8 1EH",
    "wof:placetype":"postalcode"
},
  "geometry": {"coordinates":[-3.42162646102867,50.61916883956638],"type":"Point"}
}