{
  "type": "Feature",
  "properties": {
    "date:inception_lower":"1980-01-01",
    "date:inception_upper":"1980-01-31",
    "iso:country":"GB",
    "wof:name":"EX8 1EH",
    "wof:placetype":"postalcode"
},
  "geometry": {"coordinates":[-3.421626,50.619169],"type":"Point"}
}