{
  "type": "Feature",
  "properties": {
    "iso:country":"GB",
    "wof:name":"NE10 0EU",
    "wof:placetype":"postalcode"
},
  "geometry": {"coordinates":[-1.56832171925103,54.9557275152543],"type":"Point"}
}