{
  "type": "Feature",
  "properties": {
    "date:inception_lower":"1995-12-01",
    "date:inception_upper":"1995-12-31",
    "iso:country":"GB",
    "wof:name":"GL4 6RX",
    "wof:placetype":"postalcode"
},
  "geometry": {"coordinates":[-2.231941,51.843542],"type":"Point"}
}