{
  "type": "Feature",
  "properties": {
    "iso:country":"GB",
    "wof:name":"BS48 2QX",
    "wof:placetype":"postalcode"
},
  "geometry": {"coordinates":[-2.75952954359261,51.42857472661245],"type":"Point"}
}