{
  "type": "Feature",
  "properties": {
    "iso:country":"GB",
    "wof:name":"CO10 0FA",
    "wof:placetype":"postalcode"
},
  "geometry": {"coordinates":[0.75595241334318,52.03044737835008],"type":"Point"}
}