{
  "type": "Feature",
  "properties": {
    "date:inception_lower":"2007-03-01",
    "date:inception_upper":"2007-03-31",
    "iso:country":"GB",
    "wof:name":"CO10 0FA",
    "wof:placetype":"postalcode"
},
  "geometry": {"coordinates":[0.756111,52.030394],"type":"Point"}
}