{
  "type": "Feature",
  "properties": {
    "iso:country":"GB",
    "wof:name":"NE23 2UA",
    "wof:placetype":"postalcode"
},
  "geometry": {"coordinates":[-1.56887964467229,55.09612093667901],"type":"Point"}
}