{
  "type": "Feature",
  "properties": {
    "date:inception_lower": "1999-06-01",
    "date:inception_upper": "1999-06-01",
    "iso:country": "GB",
    "wof:name": "NE23 2UA",
    "wof:placetype": "postalcode"
  },
  "geometry": {"coordinates":[-1.56888,55.096121],"type":"Point"}
}
