{
  "type": "Feature",
  "properties": {
    "date:inception_lower":"2006-08-01",
    "date:inception_upper":"2006-08-31",
    "iso:country":"GB",
    "wof:name":"DH5 0SD",
    "wof:placetype":"postalcode"
},
  "geometry": {"coordinates":[-1.44665,54.817886],"type":"Point"}
}