{
  "type": "Feature",
  "properties": {
    "iso:country":"GB",
    "wof:name":"DH5 0SD",
    "wof:placetype":"postalcode"
},
  "geometry": {"coordinates":[-1.44664982169764,54.81788586632135],"type":"Point"}
}