{
  "type": "Feature",
  "properties": {
    "iso:country":"GB",
    "wof:name":"IG6 3HJ",
    "wof:placetype":"postalcode"
},
  "geometry": {"coordinates":[0.10000819370654,51.59894516325657],"type":"Point"}
}