{
  "type": "Feature",
  "properties": {
    "date:inception_lower":"1980-01-01",
    "date:inception_upper":"1980-01-31",
    "iso:country":"GB",
    "wof:name":"IG6 3HJ",
    "wof:placetype":"postalcode"
},
  "geometry": {"coordinates":[0.099865,51.599336],"type":"Point"}
}