{
  "type": "Feature",
  "properties": {
    "iso:country": "GB",
    "wof:name": "IG6 3HJ",
    "wof:placetype": "postalcode"
  },
  "geometry": {"coordinates":[0.099865,51.599336],"type":"Point"}
}
