{
  "type": "Feature",
  "properties": {
    "iso:country": "GB",
    "wof:name": "PE1 2EL",
    "wof:placetype": "postalcode"
  },
  "geometry": {"coordinates":[-0.247391,52.580062],"type":"Point"}
}
