{
  "type": "Feature",
  "properties": {
    "iso:country":"GB",
    "wof:name":"PE1 2EL",
    "wof:placetype":"postalcode"
},
  "geometry": {"coordinates":[-0.24739086613166,52.58006230333843],"type":"Point"}
}