{
  "type": "Feature",
  "properties": {
    "iso:country": "GB",
    "wof:name": "OX25 2PF",
    "wof:placetype": "postalcode"
  },
  "geometry": {"coordinates":[-1.184421,51.874006],"type":"Point"}
}
