{
  "type": "Feature",
  "properties": {
    "iso:country": "GB",
    "wof:name": "ME12 1PZ",
    "wof:placetype": "postalcode"
  },
  "geometry": {"coordinates":[0.748199,51.432636],"type":"Point"}
}
