{
  "type": "Feature",
  "properties": {
    "iso:country": "GB",
    "wof:name": "B61 0AW",
    "wof:placetype": "postalcode"
  },
  "geometry": {"coordinates":[-2.058849,52.345204],"type":"Point"}
}
