{
  "type": "Feature",
  "properties": {
    "iso:country": "GB",
    "wof:name": "EN10 6GN",
    "wof:placetype": "postalcode"
  },
  "geometry": {"coordinates":[-0.026162,51.730401],"type":"Point"}
}
