{
  "type": "Feature",
  "properties": {
    "date:inception_lower":"2012-09-01",
    "date:inception_upper":"2012-09-30",
    "iso:country":"GB",
    "wof:name":"EN10 6GN",
    "wof:placetype":"postalcode"
},
  "geometry": {"coordinates":[-0.026162,51.730401],"type":"Point"}
}