{
  "type": "Feature",
  "properties": {
    "iso:country":"GB",
    "wof:name":"EN10 6GN",
    "wof:placetype":"postalcode"
},
  "geometry": {"coordinates":[-0.02616244965095,51.73040119629036],"type":"Point"}
}