{
  "type": "Feature",
  "properties": {
    "iso:country":"GB",
    "wof:name":"BL2 5EX",
    "wof:placetype":"postalcode"
},
  "geometry": {"coordinates":[-2.38545046973827,53.58823752948813],"type":"Point"}
}