{
  "type": "Feature",
  "properties": {
    "iso:country": "GB",
    "wof:name": "BL2 5EX",
    "wof:placetype": "postalcode"
  },
  "geometry": {"coordinates":[-2.38545,53.588238],"type":"Point"}
}
