{
  "type": "Feature",
  "properties": {
    "iso:country":"GB",
    "wof:name":"HG1 4BD",
    "wof:placetype":"postalcode"
},
  "geometry": {"coordinates":[-1.52890954894446,53.99894758141667],"type":"Point"}
}