{
  "type": "Feature",
  "properties": {
    "iso:country": "GB",
    "wof:name": "S44 5LZ",
    "wof:placetype": "postalcode"
  },
  "geometry": {"coordinates":[-1.293042,53.189954],"type":"Point"}
}
