{
  "type": "Feature",
  "properties": {
    "iso:country": "GB",
    "wof:name": "SP4 6AZ",
    "wof:placetype": "postalcode"
  },
  "geometry": {"coordinates":[-1.805124,51.14365],"type":"Point"}
}
