{
  "type": "Feature",
  "properties": {
    "iso:country":"GB",
    "wof:name":"SP4 6AZ",
    "wof:placetype":"postalcode"
},
  "geometry": {"coordinates":[-1.80512375513465,51.14365021776791],"type":"Point"}
}