{
  "type": "Feature",
  "properties": {
    "iso:country":"GB",
    "wof:name":"TQ7 1DP",
    "wof:placetype":"postalcode"
},
  "geometry": {"coordinates":[-3.7715696417229,50.28422339028418],"type":"Point"}
}