{
  "type": "Feature",
  "properties": {
    "iso:country":"GB",
    "wof:name":"SW15 5AD",
    "wof:placetype":"postalcode"
},
  "geometry": {"coordinates":[-0.23767056918728,51.46002978758859],"type":"Point"}
}