{
  "type": "Feature",
  "properties": {
    "date:inception_lower":"1980-01-01",
    "date:inception_upper":"1980-01-31",
    "iso:country":"GB",
    "wof:name":"ME17 2JN",
    "wof:placetype":"postalcode"
},
  "geometry": {"coordinates":[0.748603,51.219051],"type":"Point"}
}