{
  "type": "Feature",
  "properties": {
    "iso:country":"GB",
    "wof:name":"SO32 2LW",
    "wof:placetype":"postalcode"
},
  "geometry": {"coordinates":[-1.20123837199773,50.93228386187907],"type":"Point"}
}