{
  "type": "Feature",
  "properties": {
    "iso:country":"GB",
    "wof:name":"CT2 8HS",
    "wof:placetype":"postalcode"
},
  "geometry": {"coordinates":[1.05913357053293,51.29087977424993],"type":"Point"}
}