{
  "type": "Feature",
  "properties": {
    "iso:country": "GB",
    "wof:name": "CT2 8HS",
    "wof:placetype": "postalcode"
  },
  "geometry": {"coordinates":[1.059134,51.29088],"type":"Point"}
}
