{
  "type": "Feature",
  "properties": {
    "date:inception_lower": "1980-01-01",
    "date:inception_upper": "1980-01-01",
    "iso:country": "GB",
    "wof:name": "CT2 8HS",
    "wof:placetype": "postalcode"
  },
  "geometry": {"coordinates":[1.059134,51.29088],"type":"Point"}
}
