{
  "type": "Feature",
  "properties": {
    "iso:country":"GB",
    "wof:name":"LL57 3UL",
    "wof:placetype":"postalcode"
},
  "geometry": {"coordinates":[-4.05003692878142,53.1845187704708],"type":"Point"}
}