{
  "type": "Feature",
  "properties": {
    "date:inception_lower": "2018-10-01",
    "date:inception_upper": "2018-10-01",
    "iso:country": "GB",
    "wof:name": "S41 0FA",
    "wof:placetype": "postalcode"
  },
  "geometry": {"coordinates":[-1.408666,53.219826],"type":"Point"}
}
