{
  "type": "Feature",
  "properties": {
    "iso:country":"GB",
    "wof:name":"RM1 1QA",
    "wof:placetype":"postalcode"
},
  "geometry": {"coordinates":[0.18438156439046,51.57310642217355],"type":"Point"}
}