{
  "type": "Feature",
  "properties": {
    "iso:country":"GB",
    "wof:name":"AL1 2HZ",
    "wof:placetype":"postalcode"
},
  "geometry": {"coordinates":[-0.33436557561838,51.73973310573069],"type":"Point"}
}