{
  "type": "Feature",
  "properties": {
    "iso:country":"GB",
    "wof:name":"HS3 3AJ",
    "wof:placetype":"postalcode"
},
  "geometry": {"coordinates":[-6.84883378723142,57.92103585937948],"type":"Point"}
}