{
  "type": "Feature",
  "properties": {
    "iso:country": "GB",
    "wof:name": "HS3 3AJ",
    "wof:placetype": "postalcode"
  },
  "geometry": {"coordinates":[-6.848834,57.921036],"type":"Point"}
}
