{
  "type": "Feature",
  "properties": {
    "iso:country":"GB",
    "wof:name":"WS7 3XP",
    "wof:placetype":"postalcode"
},
  "geometry": {"coordinates":[-1.9403552921317,52.67494532043514],"type":"Point"}
}