{
  "type": "Feature",
  "properties": {
    "iso:country":"GB",
    "wof:name":"CM1 2TF",
    "wof:placetype":"postalcode"
},
  "geometry": {"coordinates":[0.4528330229013,51.72764467905459],"type":"Point"}
}