{
  "type": "Feature",
  "properties": {
    "iso:country":"GB",
    "wof:name":"WS11 9TY",
    "wof:placetype":"postalcode"
},
  "geometry": {"coordinates":[-1.97361689526874,52.6751191299608],"type":"Point"}
}