{
  "type": "Feature",
  "properties": {
    "iso:country": "GB",
    "wof:name": "WS11 9TY",
    "wof:placetype": "postalcode"
  },
  "geometry": {"coordinates":[-1.973617,52.675119],"type":"Point"}
}
