{
  "type": "Feature",
  "properties": {
    "date:inception_lower": "1980-01-01",
    "date:inception_upper": "1980-01-01",
    "iso:country": "GB",
    "wof:name": "L25 2RB",
    "wof:placetype": "postalcode"
  },
  "geometry": {"coordinates":[-2.865496,53.389755],"type":"Point"}
}
