{
  "type": "Feature",
  "properties": {
    "date:inception_lower": "1980-01-01",
    "date:inception_upper": "1980-01-01",
    "iso:country": "GB",
    "wof:name": "SL2 3XW",
    "wof:placetype": "postalcode"
  },
  "geometry": {"coordinates":[-0.606342,51.572071],"type":"Point"}
}
