{
  "type": "Feature",
  "properties": {
    "iso:country":"GB",
    "wof:name":"SL2 3XW",
    "wof:placetype":"postalcode"
},
  "geometry": {"coordinates":[-0.60636089203256,51.57206867772604],"type":"Point"}
}