{
  "type": "Feature",
  "properties": {
    "iso:country": "GB",
    "wof:name": "CV35 0JF",
    "wof:placetype": "postalcode"
  },
  "geometry": {"coordinates":[-1.523955,52.159788],"type":"Point"}
}
