{
  "type": "Feature",
  "properties": {
    "iso:country":"GB",
    "wof:name":"CV35 0JF",
    "wof:placetype":"postalcode"
},
  "geometry": {"coordinates":[-1.52395538062317,52.1597876853554],"type":"Point"}
}