{
  "type": "Feature",
  "properties": {
    "iso:country": "GB",
    "wof:name": "LN2 5LP",
    "wof:placetype": "postalcode"
  },
  "geometry": {"coordinates":[-0.525289,53.229955],"type":"Point"}
}
