{
  "type": "Feature",
  "properties": {
    "iso:country":"GB",
    "wof:name":"SL6 3EP",
    "wof:placetype":"postalcode"
},
  "geometry": {"coordinates":[-0.74334795438499,51.50643686297366],"type":"Point"}
}