{
  "type": "Feature",
  "properties": {
    "date:inception_lower": "1999-06-01",
    "date:inception_upper": "1999-06-01",
    "iso:country": "GB",
    "wof:name": "CH62 6HB",
    "wof:placetype": "postalcode"
  },
  "geometry": {"coordinates":[-2.984822,53.31983],"type":"Point"}
}
