{
  "type": "Feature",
  "properties": {
    "iso:country": "GB",
    "wof:name": "NN4 0SW",
    "wof:placetype": "postalcode"
  },
  "geometry": {"coordinates":[-0.90175,52.20532],"type":"Point"}
}
