{
  "type": "Feature",
  "properties": {
    "date:inception_lower": "1988-03-01",
    "date:inception_upper": "1988-03-01",
    "iso:country": "GB",
    "wof:name": "NN4 0SW",
    "wof:placetype": "postalcode"
  },
  "geometry": {"coordinates":[-0.90175,52.20532],"type":"Point"}
}
