{
  "type": "Feature",
  "properties": {
    "date:inception_lower": "1980-01-01",
    "date:inception_upper": "1980-01-01",
    "iso:country": "GB",
    "wof:name": "PO19 3DR",
    "wof:placetype": "postalcode"
  },
  "geometry": {"coordinates":[-0.790242,50.837491],"type":"Point"}
}
