{
  "type": "Feature",
  "properties": {
    "date:inception_lower": "1999-06-01",
    "date:inception_upper": "1999-06-01",
    "iso:country": "GB",
    "wof:name": "CH65 8JR",
    "wof:placetype": "postalcode"
  },
  "geometry": {"coordinates":[-2.90433,53.278067],"type":"Point"}
}
