{
  "type": "Feature",
  "properties": {
    "iso:country":"GB",
    "wof:name":"OX9 2AX",
    "wof:placetype":"postalcode"
},
  "geometry": {"coordinates":[-0.9889291782222,51.74512723595841],"type":"Point"}
}