{
  "type": "Feature",
  "properties": {
    "iso:country": "GB",
    "wof:name": "WV13 2JJ",
    "wof:placetype": "postalcode"
  },
  "geometry": {"coordinates":[-2.052123,52.578489],"type":"Point"}
}
