{
  "type": "Feature",
  "properties": {
    "iso:country":"GB",
    "wof:name":"WS10 9TN",
    "wof:placetype":"postalcode"
},
  "geometry": {"coordinates":[-2.02844581426777,52.56807767689256],"type":"Point"}
}