{
  "type": "Feature",
  "properties": {
    "iso:country": "GB",
    "wof:name": "LN11 8TU",
    "wof:placetype": "postalcode"
  },
  "geometry": {"coordinates":[0.100283,53.362787],"type":"Point"}
}
