{
  "type": "Feature",
  "properties": {
    "iso:country":"GB",
    "wof:name":"SA10 9BU",
    "wof:placetype":"postalcode"
},
  "geometry": {"coordinates":[-3.69658354721596,51.77427054789571],"type":"Point"}
}