{
  "type": "Feature",
  "properties": {
    "iso:country":"GB",
    "wof:name":"SY13 1QF",
    "wof:placetype":"postalcode"
},
  "geometry": {"coordinates":[-2.67744366380619,52.96698299095419],"type":"Point"}
}