{
  "type": "Feature",
  "properties": {
    "date:inception_lower": "1980-01-01",
    "date:inception_upper": "1980-01-01",
    "iso:country": "GB",
    "wof:name": "CF37 3EL",
    "wof:placetype": "postalcode"
  },
  "geometry": {"coordinates":[-3.358089,51.635084],"type":"Point"}
}
