{
  "type": "Feature",
  "properties": {
    "iso:country":"GB",
    "wof:name":"CF37 3EL",
    "wof:placetype":"postalcode"
},
  "geometry": {"coordinates":[-3.35807742158573,51.63508087046815],"type":"Point"}
}