{
  "type": "Feature",
  "properties": {
    "iso:country": "GB",
    "wof:name": "BN27 2RT",
    "wof:placetype": "postalcode"
  },
  "geometry": {"coordinates":[0.268647,50.849228],"type":"Point"}
}
