{
  "type": "Feature",
  "properties": {
    "date:inception_lower":"1980-01-01",
    "date:inception_upper":"1980-01-31",
    "iso:country":"GB",
    "wof:name":"BN27 2RT",
    "wof:placetype":"postalcode"
},
  "geometry": {"coordinates":[0.268647,50.849228],"type":"Point"}
}