{
  "type": "Feature",
  "properties": {
    "iso:country":"GB",
    "wof:name":"BN27 2RT",
    "wof:placetype":"postalcode"
},
  "geometry": {"coordinates":[0.26864648151429,50.8492275496401],"type":"Point"}
}