{
  "type": "Feature",
  "properties": {
    "date:inception_lower":"1980-01-01",
    "date:inception_upper":"1980-01-31",
    "iso:country":"GB",
    "wof:name":"HU13 9AY",
    "wof:placetype":"postalcode"
},
  "geometry": {"coordinates":[-0.423731,53.733991],"type":"Point"}
}