{
  "type": "Feature",
  "properties": {
    "iso:country":"GB",
    "wof:name":"HU13 9AY",
    "wof:placetype":"postalcode"
},
  "geometry": {"coordinates":[-0.42373104556868,53.73399137741031],"type":"Point"}
}