{
  "type": "Feature",
  "properties": {
    "iso:country":"GB",
    "wof:name":"SY14 7AU",
    "wof:placetype":"postalcode"
},
  "geometry": {"coordinates":[-2.83152845798588,53.0046952493167],"type":"Point"}
}