{
  "type": "Feature",
  "properties": {
    "date:inception_lower": "1980-01-01",
    "date:inception_upper": "1980-01-01",
    "iso:country": "GB",
    "wof:name": "NE6 3BJ",
    "wof:placetype": "postalcode"
  },
  "geometry": {"coordinates":[-1.553709,54.970925],"type":"Point"}
}
