{
  "type": "Feature",
  "properties": {
    "iso:country": "GB",
    "wof:name": "NE6 3BJ",
    "wof:placetype": "postalcode"
  },
  "geometry": {"coordinates":[-1.553709,54.970925],"type":"Point"}
}
