{
  "type": "Feature",
  "properties": {
    "iso:country":"GB",
    "wof:name":"NE6 3BJ",
    "wof:placetype":"postalcode"
},
  "geometry": {"coordinates":[-1.55370934674838,54.97092455060279],"type":"Point"}
}