{
  "type": "Feature",
  "properties": {
    "date:inception_lower": "1980-01-01",
    "date:inception_upper": "1980-01-01",
    "iso:country": "GB",
    "wof:name": "EX21 5LQ",
    "wof:placetype": "postalcode"
  },
  "geometry": {"coordinates":[-4.115853,50.819199],"type":"Point"}
}
