{
  "type": "Feature",
  "properties": {
    "iso:country":"GB",
    "wof:name":"IG1 2WS",
    "wof:placetype":"postalcode"
},
  "geometry": {"coordinates":[0.08129028871525,51.55936906115267],"type":"Point"}
}