{
  "type": "Feature",
  "properties": {
    "iso:country":"GB",
    "wof:name":"WN2 1QG",
    "wof:placetype":"postalcode"
},
  "geometry": {"coordinates":[-2.5614901511434,53.55989217197003],"type":"Point"}
}