{
  "type": "Feature",
  "properties": {
    "iso:country": "GB",
    "wof:name": "WN2 1QG",
    "wof:placetype": "postalcode"
  },
  "geometry": {"coordinates":[-2.56149,53.559892],"type":"Point"}
}
