{
  "type": "Feature",
  "properties": {
    "iso:country":"GB",
    "wof:name":"CW9 8TR",
    "wof:placetype":"postalcode"
},
  "geometry": {"coordinates":[-2.51929473695021,53.24873379522832],"type":"Point"}
}