{
  "type": "Feature",
  "properties": {
    "iso:country": "GB",
    "wof:name": "SA20 0JW",
    "wof:placetype": "postalcode"
  },
  "geometry": {"coordinates":[-3.797342,51.996528],"type":"Point"}
}
