{
  "type": "Feature",
  "properties": {
    "iso:country": "GB",
    "wof:name": "TN22 4AB",
    "wof:placetype": "postalcode"
  },
  "geometry": {"coordinates":[0.128664,51.019668],"type":"Point"}
}
