{
  "type": "Feature",
  "properties": {
    "date:inception_lower": "1980-01-01",
    "date:inception_upper": "1980-01-01",
    "iso:country": "GB",
    "wof:name": "BL3 6TP",
    "wof:placetype": "postalcode"
  },
  "geometry": {"coordinates":[-2.442384,53.566199],"type":"Point"}
}
