{
  "type": "Feature",
  "properties": {
    "date:inception_lower": "1994-05-01",
    "date:inception_upper": "1994-05-01",
    "iso:country": "GB",
    "wof:name": "M33 7XY",
    "wof:placetype": "postalcode"
  },
  "geometry": {"coordinates":[-2.319696,53.42458],"type":"Point"}
}
