{
  "type": "Feature",
  "properties": {
    "iso:country":"GB",
    "wof:name":"M33 7XY",
    "wof:placetype":"postalcode"
},
  "geometry": {"coordinates":[-2.31969528935208,53.42456323979578],"type":"Point"}
}