{
  "type": "Feature",
  "properties": {
    "iso:country":"GB",
    "wof:name":"EX38 7DA",
    "wof:placetype":"postalcode"
},
  "geometry": {"coordinates":[-4.12793313767071,50.95546708663285],"type":"Point"}
}