{
  "type": "Feature",
  "properties": {
    "iso:country": "GB",
    "wof:name": "EX38 7DA",
    "wof:placetype": "postalcode"
  },
  "geometry": {"coordinates":[-4.127933,50.955467],"type":"Point"}
}
