{
  "type": "Feature",
  "properties": {
    "date:inception_lower":"1997-06-01",
    "date:inception_upper":"1997-06-30",
    "iso:country":"GB",
    "wof:name":"EX38 7DA",
    "wof:placetype":"postalcode"
},
  "geometry": {"coordinates":[-4.127933,50.955467],"type":"Point"}
}