{
  "type": "Feature",
  "properties": {
    "date:inception_lower": "1980-01-01",
    "date:inception_upper": "1980-01-01",
    "iso:country": "GB",
    "wof:name": "WR9 7LF",
    "wof:placetype": "postalcode"
  },
  "geometry": {"coordinates":[-2.084255,52.223564],"type":"Point"}
}
