{
  "type": "Feature",
  "properties": {
    "date:inception_lower":"1980-01-01",
    "date:inception_upper":"1980-01-31",
    "iso:country":"GB",
    "wof:name":"WR9 7LF",
    "wof:placetype":"postalcode"
},
  "geometry": {"coordinates":[-2.083889,52.223573],"type":"Point"}
}