{
  "type": "Feature",
  "properties": {
    "iso:country": "GB",
    "wof:name": "YO19 6HA",
    "wof:placetype": "postalcode"
  },
  "geometry": {"coordinates":[-1.045607,53.88961],"type":"Point"}
}
