{
  "type": "Feature",
  "properties": {
    "iso:country":"GB",
    "wof:name":"S61 4NG",
    "wof:placetype":"postalcode"
},
  "geometry": {"coordinates":[-1.38888005114524,53.45545629624581],"type":"Point"}
}