{
  "type": "Feature",
  "properties": {
    "iso:country": "GB",
    "wof:name": "SO22 6LJ",
    "wof:placetype": "postalcode"
  },
  "geometry": {"coordinates":[-1.336852,51.083368],"type":"Point"}
}
