{
  "type": "Feature",
  "properties": {
    "iso:country":"GB",
    "wof:name":"NG18 3EW",
    "wof:placetype":"postalcode"
},
  "geometry": {"coordinates":[-1.13949066470664,53.14487920982554],"type":"Point"}
}