{
  "type": "Feature",
  "properties": {
    "date:inception_lower": "1980-01-01",
    "date:inception_upper": "1980-01-01",
    "iso:country": "GB",
    "wof:name": "NG18 3EW",
    "wof:placetype": "postalcode"
  },
  "geometry": {"coordinates":[-1.139491,53.144879],"type":"Point"}
}
