{
  "type": "Feature",
  "properties": {
    "date:inception_lower": "2019-03-01",
    "date:inception_upper": "2019-03-01",
    "iso:country": "GB",
    "wof:name": "TA6 6ZG",
    "wof:placetype": "postalcode"
  },
  "geometry": {"coordinates":[-3.001734,51.101584],"type":"Point"}
}
