{
  "type": "Feature",
  "properties": {
    "iso:country": "GB",
    "wof:name": "SW15 2HE",
    "wof:placetype": "postalcode"
  },
  "geometry": {"coordinates":[-0.212876,51.453926],"type":"Point"}
}
