{
  "type": "Feature",
  "properties": {
    "iso:country": "GB",
    "wof:name": "BS39 5RP",
    "wof:placetype": "postalcode"
  },
  "geometry": {"coordinates":[-2.547578,51.331873],"type":"Point"}
}
