{
  "type": "Feature",
  "properties": {
    "iso:country":"GB",
    "wof:name":"CH7 5JS",
    "wof:placetype":"postalcode"
},
  "geometry": {"coordinates":[-3.17454153689071,53.16147376899342],"type":"Point"}
}