{
  "type": "Feature",
  "properties": {
    "iso:country": "GB",
    "wof:name": "CH7 5JS",
    "wof:placetype": "postalcode"
  },
  "geometry": {"coordinates":[-3.174541,53.161474],"type":"Point"}
}
