{
  "type": "Feature",
  "properties": {
    "date:inception_lower": "2011-12-01",
    "date:inception_upper": "2011-12-01",
    "iso:country": "GB",
    "wof:name": "FK16 6DY",
    "wof:placetype": "postalcode"
  },
  "geometry": {"coordinates":[-4.052973,56.192841],"type":"Point"}
}
