{
  "type": "Feature",
  "properties": {
    "iso:country":"GB",
    "wof:name":"FK16 6DY",
    "wof:placetype":"postalcode"
},
  "geometry": {"coordinates":[-4.05297296439967,56.19284146711595],"type":"Point"}
}