{
  "type": "Feature",
  "properties": {
    "iso:country": "GB",
    "wof:name": "DN22 9BW",
    "wof:placetype": "postalcode"
  },
  "geometry": {"coordinates":[-0.857069,53.363488],"type":"Point"}
}
