{
  "type": "Feature",
  "properties": {
    "iso:country":"GB",
    "wof:name":"DN22 9BW",
    "wof:placetype":"postalcode"
},
  "geometry": {"coordinates":[-0.85706879673108,53.36348772170928],"type":"Point"}
}