{
  "type": "Feature",
  "properties": {
    "iso:country":"GB",
    "wof:name":"CA28 7EW",
    "wof:placetype":"postalcode"
},
  "geometry": {"coordinates":[-3.58861801647457,54.54983512994517],"type":"Point"}
}