{
  "type": "Feature",
  "properties": {
    "iso:country": "GB",
    "wof:name": "PE28 3NN",
    "wof:placetype": "postalcode"
  },
  "geometry": {"coordinates":[0.020517,52.364172],"type":"Point"}
}
