{
  "type": "Feature",
  "properties": {
    "date:inception_lower":"2000-06-01",
    "date:inception_upper":"2000-06-30",
    "iso:country":"GB",
    "wof:name":"PE28 3NN",
    "wof:placetype":"postalcode"
},
  "geometry": {"coordinates":[0.020517,52.364172],"type":"Point"}
}