{
  "type": "Feature",
  "properties": {
    "iso:country":"GB",
    "wof:name":"CA1 3RL",
    "wof:placetype":"postalcode"
},
  "geometry": {"coordinates":[-2.89231074040517,54.88277962821447],"type":"Point"}
}