{
  "type": "Feature",
  "properties": {
    "iso:country": "GB",
    "wof:name": "IV10 8UX",
    "wof:placetype": "postalcode"
  },
  "geometry": {"coordinates":[-4.118479,57.587698],"type":"Point"}
}
