{
  "type": "Feature",
  "properties": {
    "iso:country":"GB",
    "wof:name":"BA3 4PU",
    "wof:placetype":"postalcode"
},
  "geometry": {"coordinates":[-2.47915181217219,51.28203438317637],"type":"Point"}
}