{
  "type": "Feature",
  "properties": {
    "iso:country": "GB",
    "wof:name": "BA3 4PU",
    "wof:placetype": "postalcode"
  },
  "geometry": {"coordinates":[-2.479152,51.282034],"type":"Point"}
}
