{
  "type": "Feature",
  "properties": {
    "iso:country":"GB",
    "wof:name":"L12 9HD",
    "wof:placetype":"postalcode"
},
  "geometry": {"coordinates":[-2.89881095638828,53.42870909621212],"type":"Point"}
}