{
  "type": "Feature",
  "properties": {
    "iso:country": "GB",
    "wof:name": "RH17 5TJ",
    "wof:placetype": "postalcode"
  },
  "geometry": {"coordinates":[-0.216463,51.030825],"type":"Point"}
}
