{
  "type": "Feature",
  "properties": {
    "date:inception_lower":"1980-01-01",
    "date:inception_upper":"1980-01-31",
    "iso:country":"GB",
    "wof:name":"RH17 5TJ",
    "wof:placetype":"postalcode"
},
  "geometry": {"coordinates":[-0.216463,51.030825],"type":"Point"}
}