{
  "type": "Feature",
  "properties": {
    "iso:country": "GB",
    "wof:name": "SE28 8AX",
    "wof:placetype": "postalcode"
  },
  "geometry": {"coordinates":[0.115868,51.501439],"type":"Point"}
}
