{
  "type": "Feature",
  "properties": {
    "date:inception_lower": "1981-06-01",
    "date:inception_upper": "1981-06-01",
    "iso:country": "GB",
    "wof:name": "SG12 0XP",
    "wof:placetype": "postalcode"
  },
  "geometry": {"coordinates":[-0.043374,51.820351],"type":"Point"}
}
