{
  "type": "Feature",
  "properties": {
    "iso:country":"GB",
    "wof:name":"ST1 1LY",
    "wof:placetype":"postalcode"
},
  "geometry": {"coordinates":[-2.17494540819757,53.02486013738618],"type":"Point"}
}