{
  "type": "Feature",
  "properties": {
    "iso:country": "GB",
    "wof:name": "IP6 0DJ",
    "wof:placetype": "postalcode"
  },
  "geometry": {"coordinates":[1.109866,52.110175],"type":"Point"}
}
