{
  "type": "Feature",
  "properties": {
    "iso:country": "GB",
    "wof:name": "GU17 9FE",
    "wof:placetype": "postalcode"
  },
  "geometry": {"coordinates":[-0.795588,51.305132],"type":"Point"}
}
