{
  "type": "Feature",
  "properties": {
    "iso:country":"GB",
    "wof:name":"BS14 9TQ",
    "wof:placetype":"postalcode"
},
  "geometry": {"coordinates":[-2.5696917998547,51.42518256275858],"type":"Point"}
}