{
  "type": "Feature",
  "properties": {
    "iso:country": "GB",
    "wof:name": "BS14 9TQ",
    "wof:placetype": "postalcode"
  },
  "geometry": {"coordinates":[-2.569692,51.425183],"type":"Point"}
}
