{
  "type": "Feature",
  "properties": {
    "iso:country": "GB",
    "wof:name": "ME13 8FN",
    "wof:placetype": "postalcode"
  },
  "geometry": {"coordinates":[0.902581,51.308462],"type":"Point"}
}
