{
  "type": "Feature",
  "properties": {
    "iso:country":"GB",
    "wof:name":"ME13 8FN",
    "wof:placetype":"postalcode"
},
  "geometry": {"coordinates":[0.90254945312928,51.30845015294258],"type":"Point"}
}