{
  "type": "Feature",
  "properties": {
    "iso:country":"GB",
    "wof:name":"B66 4DT",
    "wof:placetype":"postalcode"
},
  "geometry": {"coordinates":[-1.96757723677002,52.48093778554456],"type":"Point"}
}