{
  "type": "Feature",
  "properties": {
    "iso:country":"GB",
    "wof:name":"SA6 5NE",
    "wof:placetype":"postalcode"
},
  "geometry": {"coordinates":[-3.88867851394389,51.70396135830561],"type":"Point"}
}