{
  "type": "Feature",
  "properties": {
    "date:inception_lower": "1980-01-01",
    "date:inception_upper": "1980-01-01",
    "iso:country": "GB",
    "wof:name": "B90 1LY",
    "wof:placetype": "postalcode"
  },
  "geometry": {"coordinates":[-1.865233,52.406761],"type":"Point"}
}
