{
  "type": "Feature",
  "properties": {
    "iso:country":"GB",
    "wof:name":"B90 1LY",
    "wof:placetype":"postalcode"
},
  "geometry": {"coordinates":[-1.8652330493561,52.40676097387011],"type":"Point"}
}