{
  "type": "Feature",
  "properties": {
    "iso:country":"GB",
    "wof:name":"NG2 3HJ",
    "wof:placetype":"postalcode"
},
  "geometry": {"coordinates":[-1.13610475234206,52.94224306414731],"type":"Point"}
}