{
  "type": "Feature",
  "properties": {
    "iso:country":"GB",
    "wof:name":"G63 9AJ",
    "wof:placetype":"postalcode"
},
  "geometry": {"coordinates":[-4.33947642245737,55.99886281942141],"type":"Point"}
}