{
  "type": "Feature",
  "properties": {
    "date:inception_lower":"1980-01-01",
    "date:inception_upper":"1980-01-31",
    "iso:country":"GB",
    "wof:name":"ME7 3RA",
    "wof:placetype":"postalcode"
},
  "geometry": {"coordinates":[0.572669,51.349299],"type":"Point"}
}