{
  "type": "Feature",
  "properties": {
    "iso:country": "GB",
    "wof:name": "ME7 3RA",
    "wof:placetype": "postalcode"
  },
  "geometry": {"coordinates":[0.572669,51.349299],"type":"Point"}
}
