{
  "type": "Feature",
  "properties": {
    "iso:country":"GB",
    "wof:name":"ME7 3RA",
    "wof:placetype":"postalcode"
},
  "geometry": {"coordinates":[0.57266938265292,51.34929865941067],"type":"Point"}
}