{
  "type": "Feature",
  "properties": {
    "iso:country":"GB",
    "wof:name":"HP27 9SY",
    "wof:placetype":"postalcode"
},
  "geometry": {"coordinates":[-0.86479761489468,51.74218676896984],"type":"Point"}
}