{
  "type": "Feature",
  "properties": {
    "iso:country":"GB",
    "wof:name":"BD4 6HA",
    "wof:placetype":"postalcode"
},
  "geometry": {"coordinates":[-1.724044069116,53.77097437615306],"type":"Point"}
}