{
  "type": "Feature",
  "properties": {
    "iso:country":"GB",
    "wof:name":"PH33 6RA",
    "wof:placetype":"postalcode"
},
  "geometry": {"coordinates":[-5.11383223468643,56.81532502866752],"type":"Point"}
}