{
  "type": "Feature",
  "properties": {
    "iso:country":"GB",
    "wof:name":"CT19 4AE",
    "wof:placetype":"postalcode"
},
  "geometry": {"coordinates":[1.15211835076541,51.09025484211931],"type":"Point"}
}