{
  "type": "Feature",
  "properties": {
    "date:inception_lower": "1980-01-01",
    "date:inception_upper": "1980-01-01",
    "iso:country": "GB",
    "wof:name": "CT19 4AE",
    "wof:placetype": "postalcode"
  },
  "geometry": {"coordinates":[1.152118,51.090255],"type":"Point"}
}
