{
  "type": "Feature",
  "properties": {
    "iso:country":"GB",
    "wof:name":"TW18 4PN",
    "wof:placetype":"postalcode"
},
  "geometry": {"coordinates":[-0.51059174338427,51.43321373902398],"type":"Point"}
}