{
  "type": "Feature",
  "properties": {
    "iso:country":"GB",
    "wof:name":"BA11 2DP",
    "wof:placetype":"postalcode"
},
  "geometry": {"coordinates":[-2.30274465196178,51.23511975145402],"type":"Point"}
}