{
  "type": "Feature",
  "properties": {
    "iso:country":"GB",
    "wof:name":"SA6 6EP",
    "wof:placetype":"postalcode"
},
  "geometry": {"coordinates":[-3.93207851365327,51.6722857042056],"type":"Point"}
}