{
  "type": "Feature",
  "properties": {
    "date:inception_lower": "1980-01-01",
    "date:inception_upper": "1980-01-01",
    "iso:country": "GB",
    "wof:name": "SA6 6EP",
    "wof:placetype": "postalcode"
  },
  "geometry": {"coordinates":[-3.932078,51.672286],"type":"Point"}
}
