{
  "type": "Feature",
  "properties": {
    "iso:country": "GB",
    "wof:name": "PL12 6PJ",
    "wof:placetype": "postalcode"
  },
  "geometry": {"coordinates":[-4.258767,50.43163],"type":"Point"}
}
