{
  "type": "Feature",
  "properties": {
    "iso:country":"GB",
    "wof:name":"PL12 6PJ",
    "wof:placetype":"postalcode"
},
  "geometry": {"coordinates":[-4.25876732345495,50.431630335715],"type":"Point"}
}