{
  "type": "Feature",
  "properties": {
    "date:inception_lower": "1994-05-01",
    "date:inception_upper": "1994-05-01",
    "iso:country": "GB",
    "wof:name": "M7 2HX",
    "wof:placetype": "postalcode"
  },
  "geometry": {"coordinates":[-2.268308,53.501496],"type":"Point"}
}
