{
  "type": "Feature",
  "properties": {
    "iso:country":"GB",
    "wof:name":"N1 4HP",
    "wof:placetype":"postalcode"
},
  "geometry": {"coordinates":[-0.08227224726051,51.5441625035784],"type":"Point"}
}