{
  "type": "Feature",
  "properties": {
    "iso:country":"GB",
    "wof:name":"NG4 4DB",
    "wof:placetype":"postalcode"
},
  "geometry": {"coordinates":[-1.07610527975479,52.97992553618143],"type":"Point"}
}