{
  "type": "Feature",
  "properties": {
    "iso:country":"GB",
    "wof:name":"RG41 2RA",
    "wof:placetype":"postalcode"
},
  "geometry": {"coordinates":[-0.84503822415522,51.4080672334926],"type":"Point"}
}