{
  "type": "Feature",
  "properties": {
    "iso:country":"GB",
    "wof:name":"NW9 0LT",
    "wof:placetype":"postalcode"
},
  "geometry": {"coordinates":[-0.25935859316807,51.58945707310684],"type":"Point"}
}