{
  "type": "Feature",
  "properties": {
    "iso:country":"GB",
    "wof:name":"N15 6BJ",
    "wof:placetype":"postalcode"
},
  "geometry": {"coordinates":[-0.064568272989,51.57765669911971],"type":"Point"}
}