{
  "type": "Feature",
  "properties": {
    "iso:country":"GB",
    "wof:name":"OX12 0BJ",
    "wof:placetype":"postalcode"
},
  "geometry": {"coordinates":[-1.42470010317056,51.60843231446257],"type":"Point"}
}