{
  "type": "Feature",
  "properties": {
    "date:inception_lower": "1980-01-01",
    "date:inception_upper": "1980-01-01",
    "iso:country": "GB",
    "wof:name": "OX12 0BJ",
    "wof:placetype": "postalcode"
  },
  "geometry": {"coordinates":[-1.4247,51.608432],"type":"Point"}
}
