{
  "type": "Feature",
  "properties": {
    "date:inception_lower": "1980-01-01",
    "date:inception_upper": "1980-01-01",
    "iso:country": "GB",
    "wof:name": "OL4 3BS",
    "wof:placetype": "postalcode"
  },
  "geometry": {"coordinates":[-2.07251,53.539213],"type":"Point"}
}
