{
  "type": "Feature",
  "properties": {
    "iso:country": "GB",
    "wof:name": "OL4 3BS",
    "wof:placetype": "postalcode"
  },
  "geometry": {"coordinates":[-2.07251,53.539213],"type":"Point"}
}
