{
  "type": "Feature",
  "properties": {
    "iso:country":"GB",
    "wof:name":"OL4 3BS",
    "wof:placetype":"postalcode"
},
  "geometry": {"coordinates":[-2.07249477600378,53.53925756119174],"type":"Point"}
}