{
  "type": "Feature",
  "properties": {
    "iso:country":"GB",
    "wof:name":"CV7 8BH",
    "wof:placetype":"postalcode"
},
  "geometry": {"coordinates":[-1.55223106471967,52.46920892672343],"type":"Point"}
}