{
  "type": "Feature",
  "properties": {
    "date:inception_lower": "1980-01-01",
    "date:inception_upper": "1980-01-01",
    "iso:country": "GB",
    "wof:name": "B9 5HA",
    "wof:placetype": "postalcode"
  },
  "geometry": {"coordinates":[-1.850282,52.476649],"type":"Point"}
}
