{
  "type": "Feature",
  "properties": {
    "iso:country":"GB",
    "wof:name":"B9 5HA",
    "wof:placetype":"postalcode"
},
  "geometry": {"coordinates":[-1.85028233679747,52.47664944942048],"type":"Point"}
}