{
  "type": "Feature",
  "properties": {
    "iso:country": "GB",
    "wof:name": "KY16 9PA",
    "wof:placetype": "postalcode"
  },
  "geometry": {"coordinates":[-2.79574,56.340154],"type":"Point"}
}
