{
  "type": "Feature",
  "properties": {
    "iso:country": "GB",
    "wof:name": "M27 0HT",
    "wof:placetype": "postalcode"
  },
  "geometry": {"coordinates":[-2.361306,53.504764],"type":"Point"}
}
