{
  "type": "Feature",
  "properties": {
    "iso:country":"GB",
    "wof:name":"M27 0HT",
    "wof:placetype":"postalcode"
},
  "geometry": {"coordinates":[-2.36130789154723,53.50474788004509],"type":"Point"}
}