{
  "type": "Feature",
  "properties": {
    "iso:country": "GB",
    "wof:name": "IV26 2WN",
    "wof:placetype": "postalcode"
  },
  "geometry": {"coordinates":[-5.155138,57.899898],"type":"Point"}
}
