{
  "type": "Feature",
  "properties": {
    "iso:country":"GB",
    "wof:name":"NR31 7HF",
    "wof:placetype":"postalcode"
},
  "geometry": {"coordinates":[1.71386590461018,52.56485949345998],"type":"Point"}
}