{
  "type": "Feature",
  "properties": {
    "iso:country":"GB",
    "wof:name":"ME3 7ED",
    "wof:placetype":"postalcode"
},
  "geometry": {"coordinates":[0.45242329473078,51.41660471573277],"type":"Point"}
}