{
  "type": "Feature",
  "properties": {
    "iso:country":"GB",
    "wof:name":"RM9 5DD",
    "wof:placetype":"postalcode"
},
  "geometry": {"coordinates":[0.14171376703632,51.54622220845045],"type":"Point"}
}