{
  "type": "Feature",
  "properties": {
    "iso:country":"GB",
    "wof:name":"DN31 2JD",
    "wof:placetype":"postalcode"
},
  "geometry": {"coordinates":[-0.09710141402572,53.56980911105109],"type":"Point"}
}