{
  "type": "Feature",
  "properties": {
    "date:inception_lower": "2002-06-01",
    "date:inception_upper": "2002-06-01",
    "iso:country": "GB",
    "wof:name": "CO4 0JY",
    "wof:placetype": "postalcode"
  },
  "geometry": {"coordinates":[0.936731,51.904403],"type":"Point"}
}
