{
  "type": "Feature",
  "properties": {
    "iso:country":"GB",
    "wof:name":"CO4 0JY",
    "wof:placetype":"postalcode"
},
  "geometry": {"coordinates":[0.9367305237775,51.90440296463473],"type":"Point"}
}