{
  "type": "Feature",
  "properties": {
    "iso:country":"GB",
    "wof:name":"RH9 8HE",
    "wof:placetype":"postalcode"
},
  "geometry": {"coordinates":[-0.04725672283155,51.21866614578789],"type":"Point"}
}