{
  "type": "Feature",
  "properties": {
    "iso:country": "GB",
    "wof:name": "RH9 8HE",
    "wof:placetype": "postalcode"
  },
  "geometry": {"coordinates":[-0.047257,51.218666],"type":"Point"}
}
