{
  "type": "Feature",
  "properties": {
    "iso:country":"GB",
    "wof:name":"G81 5EH",
    "wof:placetype":"postalcode"
},
  "geometry": {"coordinates":[-4.38900603980605,55.92978631570276],"type":"Point"}
}