{
  "type": "Feature",
  "properties": {
    "iso:country":"GB",
    "wof:name":"IP26 5LP",
    "wof:placetype":"postalcode"
},
  "geometry": {"coordinates":[0.57864531260691,52.54033877505076],"type":"Point"}
}