{
  "type": "Feature",
  "properties": {
    "date:inception_lower":"1980-01-01",
    "date:inception_upper":"1980-01-31",
    "iso:country":"GB",
    "wof:name":"IP26 5LP",
    "wof:placetype":"postalcode"
},
  "geometry": {"coordinates":[0.578645,52.540339],"type":"Point"}
}