{
  "type": "Feature",
  "properties": {
    "iso:country": "GB",
    "wof:name": "LL54 5AT",
    "wof:placetype": "postalcode"
  },
  "geometry": {"coordinates":[-4.404616,52.976446],"type":"Point"}
}
