{
  "type": "Feature",
  "properties": {
    "iso:country":"GB",
    "wof:name":"LL54 5AT",
    "wof:placetype":"postalcode"
},
  "geometry": {"coordinates":[-4.40461564689946,52.97644589467431],"type":"Point"}
}