{
  "type": "Feature",
  "properties": {
    "iso:country":"GB",
    "wof:name":"PO1 1AT",
    "wof:placetype":"postalcode"
},
  "geometry": {"coordinates":[-1.0914600804221,50.79945115165056],"type":"Point"}
}