{
  "type": "Feature",
  "properties": {
    "date:inception_lower": "2003-10-01",
    "date:inception_upper": "2003-10-01",
    "iso:country": "GB",
    "wof:name": "PO1 1AT",
    "wof:placetype": "postalcode"
  },
  "geometry": {"coordinates":[-1.09146,50.799451],"type":"Point"}
}
