{
  "type": "Feature",
  "properties": {
    "iso:country":"GB",
    "wof:name":"EH26 8NZ",
    "wof:placetype":"postalcode"
},
  "geometry": {"coordinates":[-3.21998657457856,55.82402723055959],"type":"Point"}
}