{
  "type": "Feature",
  "properties": {
    "iso:country":"GB",
    "wof:name":"NE16 6BT",
    "wof:placetype":"postalcode"
},
  "geometry": {"coordinates":[-1.73674875636122,54.90754765122626],"type":"Point"}
}