{
  "type": "Feature",
  "properties": {
    "iso:country":"GB",
    "wof:name":"SN1 4NL",
    "wof:placetype":"postalcode"
},
  "geometry": {"coordinates":[-1.80036880611355,51.55603788840066],"type":"Point"}
}