{
  "type": "Feature",
  "properties": {
    "date:inception_lower": "1984-10-01",
    "date:inception_upper": "1984-10-01",
    "iso:country": "GB",
    "wof:name": "SA5 4BH",
    "wof:placetype": "postalcode"
  },
  "geometry": {"coordinates":[-3.996869,51.650195],"type":"Point"}
}
