{
  "type": "Feature",
  "properties": {
    "date:inception_lower": "2023-04-01",
    "date:inception_upper": "2023-04-01",
    "iso:country": "GB",
    "wof:name": "DL8 2PJ",
    "wof:placetype": "postalcode"
  },
  "geometry": {"coordinates":[-1.573367,54.219842],"type":"Point"}
}
