{
  "type": "Feature",
  "properties": {
    "date:inception_lower": "2012-12-01",
    "date:inception_upper": "2012-12-01",
    "iso:country": "GB",
    "wof:name": "UB5 6WT",
    "wof:placetype": "postalcode"
  },
  "geometry": {"coordinates":[-0.375303,51.532499],"type":"Point"}
}
