{
  "type": "Feature",
  "properties": {
    "iso:country":"GB",
    "wof:name":"UB5 6WT",
    "wof:placetype":"postalcode"
},
  "geometry": {"coordinates":[-0.37525940664363,51.5325076037225],"type":"Point"}
}