{
  "type": "Feature",
  "properties": {
    "iso:country":"GB",
    "wof:name":"BN1 3LD",
    "wof:placetype":"postalcode"
},
  "geometry": {"coordinates":[-0.14331462795561,50.82568987891433],"type":"Point"}
}