{
  "type": "Feature",
  "properties": {
    "iso:country":"GB",
    "wof:name":"SP3 4EY",
    "wof:placetype":"postalcode"
},
  "geometry": {"coordinates":[-1.89953957363684,51.19097709849799],"type":"Point"}
}