{
  "type": "Feature",
  "properties": {
    "date:inception_lower": "2000-06-01",
    "date:inception_upper": "2000-06-01",
    "iso:country": "GB",
    "wof:name": "SO51 6FG",
    "wof:placetype": "postalcode"
  },
  "geometry": {"coordinates":[-1.574839,50.997862],"type":"Point"}
}
