{
  "type": "Feature",
  "properties": {
    "iso:country": "GB",
    "wof:name": "SO51 6FG",
    "wof:placetype": "postalcode"
  },
  "geometry": {"coordinates":[-1.574839,50.997862],"type":"Point"}
}
