{
  "type": "Feature",
  "properties": {
    "iso:country":"GB",
    "wof:name":"HX7 5PE",
    "wof:placetype":"postalcode"
},
  "geometry": {"coordinates":[-1.97571043065322,53.73106751622752],"type":"Point"}
}