{
  "type": "Feature",
  "properties": {
    "iso:country": "GB",
    "wof:name": "HX7 5PE",
    "wof:placetype": "postalcode"
  },
  "geometry": {"coordinates":[-1.97571,53.731068],"type":"Point"}
}
