{
  "type": "Feature",
  "properties": {
    "date:inception_lower":"1980-01-01",
    "date:inception_upper":"1980-01-31",
    "iso:country":"GB",
    "wof:name":"TQ1 2NR",
    "wof:placetype":"postalcode"
},
  "geometry": {"coordinates":[-3.503928,50.467475],"type":"Point"}
}