{
  "type": "Feature",
  "properties": {
    "date:inception_lower": "1980-01-01",
    "date:inception_upper": "1980-01-01",
    "iso:country": "GB",
    "wof:name": "EN10 6RT",
    "wof:placetype": "postalcode"
  },
  "geometry": {"coordinates":[-0.004986,51.735831],"type":"Point"}
}
