{
  "type": "Feature",
  "properties": {
    "iso:country": "GB",
    "wof:name": "EN10 6RT",
    "wof:placetype": "postalcode"
  },
  "geometry": {"coordinates":[-0.004986,51.735831],"type":"Point"}
}
