{
  "type": "Feature",
  "properties": {
    "iso:country":"GB",
    "wof:name":"BD21 4ED",
    "wof:placetype":"postalcode"
},
  "geometry": {"coordinates":[-1.88867651406158,53.87419655832473],"type":"Point"}
}