{
  "type": "Feature",
  "properties": {
    "iso:country":"GB",
    "wof:name":"UB9 6AZ",
    "wof:placetype":"postalcode"
},
  "geometry": {"coordinates":[-0.48434990746038,51.59219132779515],"type":"Point"}
}