{
  "type": "Feature",
  "properties": {
    "iso:country": "GB",
    "wof:name": "UB9 6AZ",
    "wof:placetype": "postalcode"
  },
  "geometry": {"coordinates":[-0.48435,51.592191],"type":"Point"}
}
