{
  "type": "Feature",
  "properties": {
    "date:inception_lower": "2023-03-01",
    "date:inception_upper": "2023-03-01",
    "iso:country": "GB",
    "wof:name": "B71 1FF",
    "wof:placetype": "postalcode"
  },
  "geometry": {"coordinates":[-1.9886,52.533944],"type":"Point"}
}
