{
  "type": "Feature",
  "properties": {
    "iso:country":"GB",
    "wof:name":"HU4 7PZ",
    "wof:placetype":"postalcode"
},
  "geometry": {"coordinates":[-0.41358960937419,53.74201963773273],"type":"Point"}
}