{
  "type": "Feature",
  "properties": {
    "date:inception_lower": "1980-01-01",
    "date:inception_upper": "1980-01-01",
    "iso:country": "GB",
    "wof:name": "HU4 7PZ",
    "wof:placetype": "postalcode"
  },
  "geometry": {"coordinates":[-0.41359,53.74202],"type":"Point"}
}
