{
  "type": "Feature",
  "properties": {
    "iso:country": "GB",
    "wof:name": "BB12 8FA",
    "wof:placetype": "postalcode"
  },
  "geometry": {"coordinates":[-2.320264,53.801346],"type":"Point"}
}
