{
  "type": "Feature",
  "properties": {
    "iso:country":"GB",
    "wof:name":"CT19 5HU",
    "wof:placetype":"postalcode"
},
  "geometry": {"coordinates":[1.16551573672645,51.08669932857511],"type":"Point"}
}