{
  "type": "Feature",
  "properties": {
    "iso:country": "GB",
    "wof:name": "CT19 5HU",
    "wof:placetype": "postalcode"
  },
  "geometry": {"coordinates":[1.165516,51.086699],"type":"Point"}
}
