{
  "type": "Feature",
  "properties": {
    "date:inception_lower": "1980-01-01",
    "date:inception_upper": "1980-01-01",
    "iso:country": "GB",
    "wof:name": "SY21 7SG",
    "wof:placetype": "postalcode"
  },
  "geometry": {"coordinates":[-3.148682,52.65917],"type":"Point"}
}
