{
  "type": "Feature",
  "properties": {
    "iso:country": "GB",
    "wof:name": "TN17 1LL",
    "wof:placetype": "postalcode"
  },
  "geometry": {"coordinates":[0.488029,51.136286],"type":"Point"}
}
