{
  "type": "Feature",
  "properties": {
    "iso:country":"GB",
    "wof:name":"TW20 9BY",
    "wof:placetype":"postalcode"
},
  "geometry": {"coordinates":[-0.5438994276559,51.4349090679377],"type":"Point"}
}