{
  "type": "Feature",
  "properties": {
    "date:inception_lower":"1980-01-01",
    "date:inception_upper":"1980-01-31",
    "iso:country":"GB",
    "wof:name":"BA1 4BE",
    "wof:placetype":"postalcode"
},
  "geometry": {"coordinates":[-2.388016,51.397089],"type":"Point"}
}