{
  "type": "Feature",
  "properties": {
    "date:inception_lower":"1980-01-01",
    "date:inception_upper":"1980-01-31",
    "iso:country":"GB",
    "wof:name":"NG7 3DS",
    "wof:placetype":"postalcode"
},
  "geometry": {"coordinates":[-1.179202,52.958658],"type":"Point"}
}