{
  "type": "Feature",
  "properties": {
    "iso:country":"GB",
    "wof:name":"NG7 3DS",
    "wof:placetype":"postalcode"
},
  "geometry": {"coordinates":[-1.17920196172905,52.95865760732159],"type":"Point"}
}