{
  "type": "Feature",
  "properties": {
    "date:inception_lower": "1980-01-01",
    "date:inception_upper": "1980-01-01",
    "iso:country": "GB",
    "wof:name": "HU3 1TB",
    "wof:placetype": "postalcode"
  },
  "geometry": {"coordinates":[-0.353374,53.754484],"type":"Point"}
}
