{
  "type": "Feature",
  "properties": {
    "iso:country":"GB",
    "wof:name":"LE2 6NX",
    "wof:placetype":"postalcode"
},
  "geometry": {"coordinates":[-1.13678406136106,52.60220043871006],"type":"Point"}
}