{
  "type": "Feature",
  "properties": {
    "date:inception_lower":"1980-01-01",
    "date:inception_upper":"1980-01-31",
    "iso:country":"GB",
    "wof:name":"LE2 6NX",
    "wof:placetype":"postalcode"
},
  "geometry": {"coordinates":[-1.136784,52.6022],"type":"Point"}
}