{
  "type": "Feature",
  "properties": {
    "iso:country":"GB",
    "wof:name":"FY6 6ZZ",
    "wof:placetype":"postalcode"
},
  "geometry": {"coordinates":[-2.97346670872641,53.84400761144951],"type":"Point"}
}