{
  "type": "Feature",
  "properties": {
    "iso:country": "GB",
    "wof:name": "FY6 6ZZ",
    "wof:placetype": "postalcode"
  },
  "geometry": {"coordinates":[-2.973467,53.844008],"type":"Point"}
}
