{
  "type": "Feature",
  "properties": {
    "iso:country":"GB",
    "wof:name":"B46 2HE",
    "wof:placetype":"postalcode"
},
  "geometry": {"coordinates":[-1.68358260627312,52.54316169386509],"type":"Point"}
}