{
  "type": "Feature",
  "properties": {
    "date:inception_lower":"1980-01-01",
    "date:inception_upper":"1980-01-31",
    "iso:country":"GB",
    "wof:name":"B46 2HE",
    "wof:placetype":"postalcode"
},
  "geometry": {"coordinates":[-1.683583,52.543162],"type":"Point"}
}