{
  "type": "Feature",
  "properties": {
    "iso:country":"GB",
    "wof:name":"RG29 1QH",
    "wof:placetype":"postalcode"
},
  "geometry": {"coordinates":[-0.94998868538895,51.24371723886807],"type":"Point"}
}