{
  "type": "Feature",
  "properties": {
    "iso:country": "GB",
    "wof:name": "FY5 3FH",
    "wof:placetype": "postalcode"
  },
  "geometry": {"coordinates":[-3.02467,53.87154],"type":"Point"}
}
