{
  "type": "Feature",
  "properties": {
    "iso:country":"GB",
    "wof:name":"FY5 3FH",
    "wof:placetype":"postalcode"
},
  "geometry": {"coordinates":[-3.02467606931613,53.87152572461014],"type":"Point"}
}