{
  "type": "Feature",
  "properties": {
    "iso:country": "GB",
    "wof:name": "EX17 5BL",
    "wof:placetype": "postalcode"
  },
  "geometry": {"coordinates":[-3.728279,50.776465],"type":"Point"}
}
