{
  "type": "Feature",
  "properties": {
    "iso:country":"GB",
    "wof:name":"EX17 5BL",
    "wof:placetype":"postalcode"
},
  "geometry": {"coordinates":[-3.72827947870666,50.77646456899222],"type":"Point"}
}