{
  "type": "Feature",
  "properties": {
    "iso:country":"GB",
    "wof:name":"B30 1TB",
    "wof:placetype":"postalcode"
},
  "geometry": {"coordinates":[-1.94682543692,52.42379886848785],"type":"Point"}
}