{
  "type": "Feature",
  "properties": {
    "date:inception_lower": "2006-07-01",
    "date:inception_upper": "2006-07-01",
    "iso:country": "GB",
    "wof:name": "ST15 0BG",
    "wof:placetype": "postalcode"
  },
  "geometry": {"coordinates":[-2.146685,52.890743],"type":"Point"}
}
