{
  "type": "Feature",
  "properties": {
    "iso:country":"GB",
    "wof:name":"CB25 0DU",
    "wof:placetype":"postalcode"
},
  "geometry": {"coordinates":[0.32627179116622,52.27782506535274],"type":"Point"}
}