{
  "type": "Feature",
  "properties": {
    "iso:country":"GB",
    "wof:name":"BS16 6UQ",
    "wof:placetype":"postalcode"
},
  "geometry": {"coordinates":[-2.48711609544891,51.49639975385414],"type":"Point"}
}