{
  "type": "Feature",
  "properties": {
    "date:inception_lower": "1980-01-01",
    "date:inception_upper": "1980-01-01",
    "iso:country": "GB",
    "wof:name": "BS16 6UQ",
    "wof:placetype": "postalcode"
  },
  "geometry": {"coordinates":[-2.487116,51.4964],"type":"Point"}
}
