{
  "type": "Feature",
  "properties": {
    "date:inception_lower": "1998-06-01",
    "date:inception_upper": "1998-06-01",
    "iso:country": "GB",
    "wof:name": "YO1 8SQ",
    "wof:placetype": "postalcode"
  },
  "geometry": {"coordinates":[-1.08214,53.95904],"type":"Point"}
}
