{
  "type": "Feature",
  "properties": {
    "iso:country":"GB",
    "wof:name":"YO1 8SQ",
    "wof:placetype":"postalcode"
},
  "geometry": {"coordinates":[-1.08213968463485,53.95903993487737],"type":"Point"}
}