{
  "type": "Feature",
  "properties": {
    "iso:country": "GB",
    "wof:name": "SY11 1ES",
    "wof:placetype": "postalcode"
  },
  "geometry": {"coordinates":[-3.052026,52.862961],"type":"Point"}
}
