{
  "type": "Feature",
  "properties": {
    "iso:country":"GB",
    "wof:name":"SY11 1ES",
    "wof:placetype":"postalcode"
},
  "geometry": {"coordinates":[-3.05202555304172,52.86296116512246],"type":"Point"}
}