{
  "type": "Feature",
  "properties": {
    "date:inception_lower": "2015-05-01",
    "date:inception_upper": "2015-05-01",
    "iso:country": "GB",
    "wof:name": "SY11 1ES",
    "wof:placetype": "postalcode"
  },
  "geometry": {"coordinates":[-3.052026,52.862961],"type":"Point"}
}
