{
  "type": "Feature",
  "properties": {
    "iso:country":"GB",
    "wof:name":"M24 6JD",
    "wof:placetype":"postalcode"
},
  "geometry": {"coordinates":[-2.19705931858312,53.56612687372056],"type":"Point"}
}