{
  "type": "Feature",
  "properties": {
    "date:inception_lower":"1980-01-01",
    "date:inception_upper":"1980-01-31",
    "iso:country":"GB",
    "wof:name":"HD6 1SR",
    "wof:placetype":"postalcode"
},
  "geometry": {"coordinates":[-1.779614,53.705225],"type":"Point"}
}