{
  "type": "Feature",
  "properties": {
    "date:inception_lower":"1980-01-01",
    "date:inception_upper":"1980-01-31",
    "iso:country":"GB",
    "wof:name":"IP25 7DR",
    "wof:placetype":"postalcode"
},
  "geometry": {"coordinates":[0.78696,52.631629],"type":"Point"}
}