{
  "type": "Feature",
  "properties": {
    "iso:country": "GB",
    "wof:name": "EH54 7EY",
    "wof:placetype": "postalcode"
  },
  "geometry": {"coordinates":[-3.525105,55.882235],"type":"Point"}
}
