{
  "type": "Feature",
  "properties": {
    "iso:country":"GB",
    "wof:name":"PH15 2AX",
    "wof:placetype":"postalcode"
},
  "geometry": {"coordinates":[-3.86079487037724,56.61890490817605],"type":"Point"}
}