{
  "type": "Feature",
  "properties": {
    "iso:country":"GB",
    "wof:name":"N3 3ED",
    "wof:placetype":"postalcode"
},
  "geometry": {"coordinates":[-0.20551081130921,51.59022876375405],"type":"Point"}
}