{
  "type": "Feature",
  "properties": {
    "iso:country":"GB",
    "wof:name":"TS25 5SL",
    "wof:placetype":"postalcode"
},
  "geometry": {"coordinates":[-1.21728540084475,54.67572888462228],"type":"Point"}
}