{
  "type": "Feature",
  "properties": {
    "iso:country":"GB",
    "wof:name":"DN4 9QJ",
    "wof:placetype":"postalcode"
},
  "geometry": {"coordinates":[-1.18252985869505,53.49636216415549],"type":"Point"}
}