{
  "type": "Feature",
  "properties": {
    "iso:country": "GB",
    "wof:name": "CO7 6BG",
    "wof:placetype": "postalcode"
  },
  "geometry": {"coordinates":[0.998255,51.950095],"type":"Point"}
}
