{
  "type": "Feature",
  "properties": {
    "iso:country":"GB",
    "wof:name":"CO7 6BG",
    "wof:placetype":"postalcode"
},
  "geometry": {"coordinates":[0.99825511681265,51.95009470552716],"type":"Point"}
}