{
  "type": "Feature",
  "properties": {
    "iso:country": "GB",
    "wof:name": "CF5 2DN",
    "wof:placetype": "postalcode"
  },
  "geometry": {"coordinates":[-3.221637,51.49548],"type":"Point"}
}
