{
  "type": "Feature",
  "properties": {
    "iso:country": "GB",
    "wof:name": "SL7 3DQ",
    "wof:placetype": "postalcode"
  },
  "geometry": {"coordinates":[-0.804841,51.602774],"type":"Point"}
}
