{
  "type": "Feature",
  "properties": {
    "iso:country":"GB",
    "wof:name":"N10 3PJ",
    "wof:placetype":"postalcode"
},
  "geometry": {"coordinates":[-0.14135987861656,51.59048031167249],"type":"Point"}
}