{
  "type": "Feature",
  "properties": {
    "iso:country": "GB",
    "wof:name": "CA14 3AG",
    "wof:placetype": "postalcode"
  },
  "geometry": {"coordinates":[-3.54448,54.644005],"type":"Point"}
}
