{
  "type": "Feature",
  "properties": {
    "iso:country": "GB",
    "wof:name": "MK5 7HF",
    "wof:placetype": "postalcode"
  },
  "geometry": {"coordinates":[-0.785769,52.010446],"type":"Point"}
}
