{
  "type": "Feature",
  "properties": {
    "date:inception_lower":"1993-08-01",
    "date:inception_upper":"1993-08-31",
    "iso:country":"GB",
    "wof:name":"MK5 7HF",
    "wof:placetype":"postalcode"
},
  "geometry": {"coordinates":[-0.785769,52.010446],"type":"Point"}
}