{
  "type": "Feature",
  "properties": {
    "date:inception_lower": "2022-08-01",
    "date:inception_upper": "2022-08-01",
    "iso:country": "GB",
    "wof:name": "OX49 5DD",
    "wof:placetype": "postalcode"
  },
  "geometry": {"coordinates":[-1.017363,51.645873],"type":"Point"}
}
