{
  "type": "Feature",
  "properties": {
    "iso:country":"GB",
    "wof:name":"E8 2ES",
    "wof:placetype":"postalcode"
},
  "geometry": {"coordinates":[-0.06867556565877,51.55055796467033],"type":"Point"}
}