{
  "type": "Feature",
  "properties": {
    "date:inception_lower": "1980-01-01",
    "date:inception_upper": "1980-01-01",
    "iso:country": "GB",
    "wof:name": "MK18 5EA",
    "wof:placetype": "postalcode"
  },
  "geometry": {"coordinates":[-1.044548,52.032952],"type":"Point"}
}
