{
  "type": "Feature",
  "properties": {
    "date:inception_lower": "1980-01-01",
    "date:inception_upper": "1980-01-01",
    "iso:country": "GB",
    "wof:name": "SW19 1NE",
    "wof:placetype": "postalcode"
  },
  "geometry": {"coordinates":[-0.19814,51.418854],"type":"Point"}
}
