{
  "type": "Feature",
  "properties": {
    "date:inception_lower": "1980-01-01",
    "date:inception_upper": "1980-01-01",
    "iso:country": "GB",
    "wof:name": "CA10 2RF",
    "wof:placetype": "postalcode"
  },
  "geometry": {"coordinates":[-2.755657,54.558877],"type":"Point"}
}
