{
  "type": "Feature",
  "properties": {
    "iso:country":"GB",
    "wof:name":"CA10 2RF",
    "wof:placetype":"postalcode"
},
  "geometry": {"coordinates":[-2.75568282958827,54.55880577105582],"type":"Point"}
}