{
  "type": "Feature",
  "properties": {
    "iso:country":"GB",
    "wof:name":"EX22 7NA",
    "wof:placetype":"postalcode"
},
  "geometry": {"coordinates":[-4.33376722949702,50.85063054474174],"type":"Point"}
}