{
  "type": "Feature",
  "properties": {
    "date:inception_lower": "1980-01-01",
    "date:inception_upper": "1980-01-01",
    "iso:country": "GB",
    "wof:name": "EX22 7NA",
    "wof:placetype": "postalcode"
  },
  "geometry": {"coordinates":[-4.333767,50.850631],"type":"Point"}
}
