{
  "type": "Feature",
  "properties": {
    "iso:country": "GB",
    "wof:name": "EX22 7NA",
    "wof:placetype": "postalcode"
  },
  "geometry": {"coordinates":[-4.333767,50.850631],"type":"Point"}
}
