{
  "type": "Feature",
  "properties": {
    "iso:country":"GB",
    "wof:name":"M22 5ED",
    "wof:placetype":"postalcode"
},
  "geometry": {"coordinates":[-2.25557941722875,53.38037711967333],"type":"Point"}
}