{
  "type": "Feature",
  "properties": {
    "date:inception_lower": "1980-01-01",
    "date:inception_upper": "1980-01-01",
    "iso:country": "GB",
    "wof:name": "M22 5ED",
    "wof:placetype": "postalcode"
  },
  "geometry": {"coordinates":[-2.255579,53.380377],"type":"Point"}
}
