{
  "type": "Feature",
  "properties": {
    "iso:country": "GB",
    "wof:name": "PL1 2BJ",
    "wof:placetype": "postalcode"
  },
  "geometry": {"coordinates":[-4.141085,50.369704],"type":"Point"}
}
