{
  "type": "Feature",
  "properties": {
    "iso:country":"GB",
    "wof:name":"GU21 4HQ",
    "wof:placetype":"postalcode"
},
  "geometry": {"coordinates":[-0.55189377036643,51.3326040615414],"type":"Point"}
}