{
  "type": "Feature",
  "properties": {
    "date:inception_lower": "1980-01-01",
    "date:inception_upper": "1980-01-01",
    "iso:country": "GB",
    "wof:name": "GU21 4HQ",
    "wof:placetype": "postalcode"
  },
  "geometry": {"coordinates":[-0.550906,51.332357],"type":"Point"}
}
