{
  "type": "Feature",
  "properties": {
    "iso:country": "GB",
    "wof:name": "GU21 4HQ",
    "wof:placetype": "postalcode"
  },
  "geometry": {"coordinates":[-0.551894,51.332604],"type":"Point"}
}
