{
  "type": "Feature",
  "properties": {
    "iso:country": "GB",
    "wof:name": "GU10 4BG",
    "wof:placetype": "postalcode"
  },
  "geometry": {"coordinates":[-0.827176,51.191976],"type":"Point"}
}
