{
  "type": "Feature",
  "properties": {
    "date:inception_lower": "1980-01-01",
    "date:inception_upper": "1980-01-01",
    "iso:country": "GB",
    "wof:name": "AL5 2UR",
    "wof:placetype": "postalcode"
  },
  "geometry": {"coordinates":[-0.362621,51.822676],"type":"Point"}
}
