{
  "type": "Feature",
  "properties": {
    "iso:country":"GB",
    "wof:name":"NE18 0QQ",
    "wof:placetype":"postalcode"
},
  "geometry": {"coordinates":[-1.88144727053663,55.04212727734004],"type":"Point"}
}