{
  "type": "Feature",
  "properties": {
    "iso:country":"GB",
    "wof:name":"TD9 0AZ",
    "wof:placetype":"postalcode"
},
  "geometry": {"coordinates":[-2.79521656779558,55.41904246735803],"type":"Point"}
}