{
  "type": "Feature",
  "properties": {
    "iso:country": "GB",
    "wof:name": "HG5 0SN",
    "wof:placetype": "postalcode"
  },
  "geometry": {"coordinates":[-1.429153,54.020473],"type":"Point"}
}
