{
  "type": "Feature",
  "properties": {
    "iso:country":"GB",
    "wof:name":"GL55 6JF",
    "wof:placetype":"postalcode"
},
  "geometry": {"coordinates":[-1.77718241587519,52.05232698630102],"type":"Point"}
}