{
  "type": "Feature",
  "properties": {
    "iso:country":"GB",
    "wof:name":"CH6 5EB",
    "wof:placetype":"postalcode"
},
  "geometry": {"coordinates":[-3.12426862417472,53.24546105059721],"type":"Point"}
}