{
  "type": "Feature",
  "properties": {
    "iso:country":"GB",
    "wof:name":"PL7 2FY",
    "wof:placetype":"postalcode"
},
  "geometry": {"coordinates":[-4.05401815383719,50.39113022911778],"type":"Point"}
}