{
  "type": "Feature",
  "properties": {
    "date:inception_lower": "2020-11-01",
    "date:inception_upper": "2020-11-01",
    "iso:country": "GB",
    "wof:name": "IV30 8AU",
    "wof:placetype": "postalcode"
  },
  "geometry": {"coordinates":[-3.30676,57.628647],"type":"Point"}
}
