{
  "type": "Feature",
  "properties": {
    "iso:country":"GB",
    "wof:name":"ML2 9JE",
    "wof:placetype":"postalcode"
},
  "geometry": {"coordinates":[-3.88829091709605,55.79152314429969],"type":"Point"}
}