{
  "type": "Feature",
  "properties": {
    "iso:country":"GB",
    "wof:name":"KW17 2UR",
    "wof:placetype":"postalcode"
},
  "geometry": {"coordinates":[-3.11484730355481,59.0052736695526],"type":"Point"}
}