{
  "type": "Feature",
  "properties": {
    "date:inception_lower":"1994-02-01",
    "date:inception_upper":"1994-02-28",
    "iso:country":"GB",
    "wof:name":"KW17 2UR",
    "wof:placetype":"postalcode"
},
  "geometry": {"coordinates":[-3.114847,59.005274],"type":"Point"}
}