{
  "type": "Feature",
  "properties": {
    "iso:country": "GB",
    "wof:name": "KW17 2UR",
    "wof:placetype": "postalcode"
  },
  "geometry": {"coordinates":[-3.114847,59.005274],"type":"Point"}
}
