{
  "type": "Feature",
  "properties": {
    "iso:country": "GB",
    "wof:name": "CM16 7NX",
    "wof:placetype": "postalcode"
  },
  "geometry": {"coordinates":[0.127926,51.674403],"type":"Point"}
}
