{
  "type": "Feature",
  "properties": {
    "iso:country":"GB",
    "wof:name":"LE5 3DT",
    "wof:placetype":"postalcode"
},
  "geometry": {"coordinates":[-1.11169840939912,52.63864937266654],"type":"Point"}
}