{
  "type": "Feature",
  "properties": {
    "iso:country": "GB",
    "wof:name": "SO41 5SJ",
    "wof:placetype": "postalcode"
  },
  "geometry": {"coordinates":[-1.498319,50.761739],"type":"Point"}
}
