{
  "type": "Feature",
  "properties": {
    "iso:country":"GB",
    "wof:name":"SO41 5SJ",
    "wof:placetype":"postalcode"
},
  "geometry": {"coordinates":[-1.49831924715264,50.76173915841589],"type":"Point"}
}