{
  "type": "Feature",
  "properties": {
    "iso:country":"GB",
    "wof:name":"GL4 4FT",
    "wof:placetype":"postalcode"
},
  "geometry": {"coordinates":[-2.21472015207999,51.84246902901525],"type":"Point"}
}