{
  "type": "Feature",
  "properties": {
    "iso:country": "GB",
    "wof:name": "GL4 4FT",
    "wof:placetype": "postalcode"
  },
  "geometry": {"coordinates":[-2.21472,51.842469],"type":"Point"}
}
