{
  "type": "Feature",
  "properties": {
    "date:inception_lower": "1980-01-01",
    "date:inception_upper": "1980-01-01",
    "iso:country": "GB",
    "wof:name": "BB11 2BU",
    "wof:placetype": "postalcode"
  },
  "geometry": {"coordinates":[-2.242764,53.787241],"type":"Point"}
}
