{
  "type": "Feature",
  "properties": {
    "iso:country":"GB",
    "wof:name":"BB11 2BU",
    "wof:placetype":"postalcode"
},
  "geometry": {"coordinates":[-2.24276401359136,53.78724142954927],"type":"Point"}
}