{
  "type": "Feature",
  "properties": {
    "iso:country": "GB",
    "wof:name": "BN16 3SB",
    "wof:placetype": "postalcode"
  },
  "geometry": {"coordinates":[-0.492009,50.815151],"type":"Point"}
}
