{
  "type": "Feature",
  "properties": {
    "iso:country":"GB",
    "wof:name":"BN16 3SB",
    "wof:placetype":"postalcode"
},
  "geometry": {"coordinates":[-0.49200928489502,50.81515053519763],"type":"Point"}
}