{
  "type": "Feature",
  "properties": {
    "iso:country": "GB",
    "wof:name": "BS15 8AY",
    "wof:placetype": "postalcode"
  },
  "geometry": {"coordinates":[-2.526607,51.460694],"type":"Point"}
}
