{
  "type": "Feature",
  "properties": {
    "iso:country":"GB",
    "wof:name":"G31 2PX",
    "wof:placetype":"postalcode"
},
  "geometry": {"coordinates":[-4.21737659440794,55.86121491730647],"type":"Point"}
}