{
  "type": "Feature",
  "properties": {
    "iso:country": "GB",
    "wof:name": "N21 2BZ",
    "wof:placetype": "postalcode"
  },
  "geometry": {"coordinates":[-0.082292,51.644114],"type":"Point"}
}
