{
  "type": "Feature",
  "properties": {
    "iso:country": "GB",
    "wof:name": "M5 4ZP",
    "wof:placetype": "postalcode"
  },
  "geometry": {"coordinates":[-2.263207,53.479008],"type":"Point"}
}
