{
  "type": "Feature",
  "properties": {
    "date:inception_lower": "1993-08-01",
    "date:inception_upper": "1993-08-01",
    "iso:country": "GB",
    "wof:name": "LU6 1NT",
    "wof:placetype": "postalcode"
  },
  "geometry": {"coordinates":[-0.525791,51.892784],"type":"Point"}
}
