{
  "type": "Feature",
  "properties": {
    "iso:country": "GB",
    "wof:name": "LU6 1NT",
    "wof:placetype": "postalcode"
  },
  "geometry": {"coordinates":[-0.525791,51.892784],"type":"Point"}
}
