{
  "type": "Feature",
  "properties": {
    "iso:country":"GB",
    "wof:name":"CF72 8HN",
    "wof:placetype":"postalcode"
},
  "geometry": {"coordinates":[-3.38861301102938,51.53483224280026],"type":"Point"}
}