{
  "type": "Feature",
  "properties": {
    "date:inception_lower":"1993-08-01",
    "date:inception_upper":"1993-08-31",
    "iso:country":"GB",
    "wof:name":"SK9 2EE",
    "wof:placetype":"postalcode"
},
  "geometry": {"coordinates":[-2.215485,53.323486],"type":"Point"}
}