{
  "type": "Feature",
  "properties": {
    "iso:country": "GB",
    "wof:name": "SK9 2EE",
    "wof:placetype": "postalcode"
  },
  "geometry": {"coordinates":[-2.215485,53.323486],"type":"Point"}
}
