{
  "type": "Feature",
  "properties": {
    "iso:country": "GB",
    "wof:name": "G66 7HX",
    "wof:placetype": "postalcode"
  },
  "geometry": {"coordinates":[-4.204786,55.979902],"type":"Point"}
}
