{
  "type": "Feature",
  "properties": {
    "iso:country":"GB",
    "wof:name":"CF45 4ND",
    "wof:placetype":"postalcode"
},
  "geometry": {"coordinates":[-3.33732909894895,51.65379723283709],"type":"Point"}
}