{
  "type": "Feature",
  "properties": {
    "iso:country":"GB",
    "wof:name":"KY4 9AZ",
    "wof:placetype":"postalcode"
},
  "geometry": {"coordinates":[-3.3523039444748,56.11575553892631],"type":"Point"}
}