{
  "type": "Feature",
  "properties": {
    "iso:country": "GB",
    "wof:name": "ME13 0SA",
    "wof:placetype": "postalcode"
  },
  "geometry": {"coordinates":[0.835227,51.29043],"type":"Point"}
}
