{
  "type": "Feature",
  "properties": {
    "iso:country":"GB",
    "wof:name":"ME13 0SA",
    "wof:placetype":"postalcode"
},
  "geometry": {"coordinates":[0.8352273727247,51.29043020479561],"type":"Point"}
}