{
  "type": "Feature",
  "properties": {
    "date:inception_lower":"1980-01-01",
    "date:inception_upper":"1980-01-31",
    "iso:country":"GB",
    "wof:name":"ME13 0SA",
    "wof:placetype":"postalcode"
},
  "geometry": {"coordinates":[0.835227,51.29043],"type":"Point"}
}