{
  "type": "Feature",
  "properties": {
    "iso:country":"GB",
    "wof:name":"S71 4EH",
    "wof:placetype":"postalcode"
},
  "geometry": {"coordinates":[-1.45465779108417,53.60367990984309],"type":"Point"}
}