{
  "type": "Feature",
  "properties": {
    "iso:country":"GB",
    "wof:name":"CF5 1HR",
    "wof:placetype":"postalcode"
},
  "geometry": {"coordinates":[-3.21426750902723,51.4843170000572],"type":"Point"}
}