{
  "type": "Feature",
  "properties": {
    "iso:country": "GB",
    "wof:name": "M12 6JL",
    "wof:placetype": "postalcode"
  },
  "geometry": {"coordinates":[-2.221963,53.475139],"type":"Point"}
}
