{
  "type": "Feature",
  "properties": {
    "date:inception_lower":"1996-06-01",
    "date:inception_upper":"1996-06-30",
    "iso:country":"GB",
    "wof:name":"PL7 1NJ",
    "wof:placetype":"postalcode"
},
  "geometry": {"coordinates":[-4.046161,50.382481],"type":"Point"}
}