{
  "type": "Feature",
  "properties": {
    "iso:country":"GB",
    "wof:name":"WV5 9AH",
    "wof:placetype":"postalcode"
},
  "geometry": {"coordinates":[-2.19051565652089,52.54126355915268],"type":"Point"}
}