{
  "type": "Feature",
  "properties": {
    "iso:country": "GB",
    "wof:name": "WV5 9AH",
    "wof:placetype": "postalcode"
  },
  "geometry": {"coordinates":[-2.190516,52.541264],"type":"Point"}
}
