{
  "type": "Feature",
  "properties": {
    "iso:country":"GB",
    "wof:name":"CM13 2PY",
    "wof:placetype":"postalcode"
},
  "geometry": {"coordinates":[0.33733889537971,51.62895517188449],"type":"Point"}
}