{
  "type": "Feature",
  "properties": {
    "iso:country": "GB",
    "wof:name": "CM13 2PY",
    "wof:placetype": "postalcode"
  },
  "geometry": {"coordinates":[0.337365,51.62894],"type":"Point"}
}
