{
  "type": "Feature",
  "properties": {
    "iso:country":"GB",
    "wof:name":"YO61 3NB",
    "wof:placetype":"postalcode"
},
  "geometry": {"coordinates":[-1.21615097113225,54.13279791888241],"type":"Point"}
}