{
  "type": "Feature",
  "properties": {
    "iso:country":"GB",
    "wof:name":"SY21 0LR",
    "wof:placetype":"postalcode"
},
  "geometry": {"coordinates":[-3.35820788364922,52.68078630146704],"type":"Point"}
}