{
  "type": "Feature",
  "properties": {
    "iso:country": "GB",
    "wof:name": "NG22 8UT",
    "wof:placetype": "postalcode"
  },
  "geometry": {"coordinates":[-1.032893,53.102782],"type":"Point"}
}
