{
  "type": "Feature",
  "properties": {
    "date:inception_lower":"2008-01-01",
    "date:inception_upper":"2008-01-31",
    "iso:country":"GB",
    "wof:name":"NG22 8UT",
    "wof:placetype":"postalcode"
},
  "geometry": {"coordinates":[-1.032893,53.102782],"type":"Point"}
}