{
  "type": "Feature",
  "properties": {
    "iso:country":"GB",
    "wof:name":"NG22 8UT",
    "wof:placetype":"postalcode"
},
  "geometry": {"coordinates":[-1.03289322916271,53.10278244451364],"type":"Point"}
}