{
  "type": "Feature",
  "properties": {
    "iso:country":"GB",
    "wof:name":"L20 0BW",
    "wof:placetype":"postalcode"
},
  "geometry": {"coordinates":[-2.9775366166473,53.45806843660299],"type":"Point"}
}