{
  "type": "Feature",
  "properties": {
    "iso:country":"GB",
    "wof:name":"CT13 9PX",
    "wof:placetype":"postalcode"
},
  "geometry": {"coordinates":[1.38792954542953,51.26705857102444],"type":"Point"}
}