{
  "type": "Feature",
  "properties": {
    "iso:country":"GB",
    "wof:name":"CF44 0AN",
    "wof:placetype":"postalcode"
},
  "geometry": {"coordinates":[-3.41001546777257,51.7009001378277],"type":"Point"}
}