{
  "type": "Feature",
  "properties": {
    "iso:country": "GB",
    "wof:name": "CF44 0AN",
    "wof:placetype": "postalcode"
  },
  "geometry": {"coordinates":[-3.409965,51.70078],"type":"Point"}
}
