{
  "type": "Feature",
  "properties": {
    "date:inception_lower":"2013-07-01",
    "date:inception_upper":"2013-07-31",
    "iso:country":"GB",
    "wof:name":"CF44 0AN",
    "wof:placetype":"postalcode"
},
  "geometry": {"coordinates":[-3.409965,51.70078],"type":"Point"}
}