{
  "type": "Feature",
  "properties": {
    "date:inception_lower":"1980-01-01",
    "date:inception_upper":"1980-01-31",
    "iso:country":"GB",
    "wof:name":"PO31 8EA",
    "wof:placetype":"postalcode"
},
  "geometry": {"coordinates":[-1.319012,50.760282],"type":"Point"}
}