{
  "type": "Feature",
  "properties": {
    "iso:country":"GB",
    "wof:name":"PO31 8EA",
    "wof:placetype":"postalcode"
},
  "geometry": {"coordinates":[-1.31901161420401,50.76028189589515],"type":"Point"}
}