{
  "type": "Feature",
  "properties": {
    "iso:country":"GB",
    "wof:name":"DH6 5EF",
    "wof:placetype":"postalcode"
},
  "geometry": {"coordinates":[-1.5218511174098,54.74092055868478],"type":"Point"}
}