{
  "type": "Feature",
  "properties": {
    "iso:country":"GB",
    "wof:name":"CO9 2EW",
    "wof:placetype":"postalcode"
},
  "geometry": {"coordinates":[0.64420978560225,51.94389773404055],"type":"Point"}
}