{
  "type": "Feature",
  "properties": {
    "iso:country": "GB",
    "wof:name": "CO9 2EW",
    "wof:placetype": "postalcode"
  },
  "geometry": {"coordinates":[0.644386,51.943914],"type":"Point"}
}
