{
  "type": "Feature",
  "properties": {
    "iso:country":"GB",
    "wof:name":"DN33 2PZ",
    "wof:placetype":"postalcode"
},
  "geometry": {"coordinates":[-0.09244864210131,53.52822013407334],"type":"Point"}
}