{
  "type": "Feature",
  "properties": {
    "iso:country":"GB",
    "wof:name":"SG2 8UJ",
    "wof:placetype":"postalcode"
},
  "geometry": {"coordinates":[-0.16524060306668,51.87469405755245],"type":"Point"}
}