{
  "type": "Feature",
  "properties": {
    "date:inception_lower": "1981-06-01",
    "date:inception_upper": "1981-06-01",
    "iso:country": "GB",
    "wof:name": "SG2 8UJ",
    "wof:placetype": "postalcode"
  },
  "geometry": {"coordinates":[-0.165241,51.874694],"type":"Point"}
}
