{
  "type": "Feature",
  "properties": {
    "date:inception_lower": "1980-01-01",
    "date:inception_upper": "1980-01-01",
    "iso:country": "GB",
    "wof:name": "WV10 6PW",
    "wof:placetype": "postalcode"
  },
  "geometry": {"coordinates":[-2.122664,52.632034],"type":"Point"}
}
