{
  "type": "Feature",
  "properties": {
    "iso:country":"GB",
    "wof:name":"WV10 6PW",
    "wof:placetype":"postalcode"
},
  "geometry": {"coordinates":[-2.12266404176407,52.63203357246329],"type":"Point"}
}