{
  "type": "Feature",
  "properties": {
    "iso:country":"GB",
    "wof:name":"SE25 6DJ",
    "wof:placetype":"postalcode"
},
  "geometry": {"coordinates":[-0.08622838769028,51.40643316465997],"type":"Point"}
}