{
  "type": "Feature",
  "properties": {
    "iso:country":"GB",
    "wof:name":"RG18 0SP",
    "wof:placetype":"postalcode"
},
  "geometry": {"coordinates":[-1.26790487353821,51.48429433863052],"type":"Point"}
}