{
  "type": "Feature",
  "properties": {
    "iso:country": "GB",
    "wof:name": "BD13 2FP",
    "wof:placetype": "postalcode"
  },
  "geometry": {"coordinates":[-1.845698,53.766398],"type":"Point"}
}
