{
  "type": "Feature",
  "properties": {
    "iso:country":"GB",
    "wof:name":"BD13 2FP",
    "wof:placetype":"postalcode"
},
  "geometry": {"coordinates":[-1.84533298170878,53.76589798203627],"type":"Point"}
}