{
  "type": "Feature",
  "properties": {
    "date:inception_lower": "1992-08-01",
    "date:inception_upper": "1992-08-01",
    "iso:country": "GB",
    "wof:name": "DL12 8JN",
    "wof:placetype": "postalcode"
  },
  "geometry": {"coordinates":[-1.922527,54.543205],"type":"Point"}
}
