{
  "type": "Feature",
  "properties": {
    "iso:country": "GB",
    "wof:name": "DL12 8JN",
    "wof:placetype": "postalcode"
  },
  "geometry": {"coordinates":[-1.922527,54.543205],"type":"Point"}
}
