{
  "type": "Feature",
  "properties": {
    "iso:country":"GB",
    "wof:name":"DL12 8JN",
    "wof:placetype":"postalcode"
},
  "geometry": {"coordinates":[-1.92252697185433,54.54320471861673],"type":"Point"}
}