{
  "type": "Feature",
  "properties": {
    "iso:country": "GB",
    "wof:name": "EX39 3BE",
    "wof:placetype": "postalcode"
  },
  "geometry": {"coordinates":[-4.233843,51.006547],"type":"Point"}
}
