{
  "type": "Feature",
  "properties": {
    "date:inception_lower":"2006-07-01",
    "date:inception_upper":"2006-07-31",
    "iso:country":"GB",
    "wof:name":"EX39 3BE",
    "wof:placetype":"postalcode"
},
  "geometry": {"coordinates":[-4.233843,51.006547],"type":"Point"}
}