{
  "type": "Feature",
  "properties": {
    "iso:country":"GB",
    "wof:name":"EX39 3BE",
    "wof:placetype":"postalcode"
},
  "geometry": {"coordinates":[-4.23371589419825,51.00678733145535],"type":"Point"}
}