{
  "type": "Feature",
  "properties": {
    "iso:country": "GB",
    "wof:name": "M16 9WT",
    "wof:placetype": "postalcode"
  },
  "geometry": {"coordinates":[-2.272279,53.45535],"type":"Point"}
}
