{
  "type": "Feature",
  "properties": {
    "iso:country":"GB",
    "wof:name":"M16 9WT",
    "wof:placetype":"postalcode"
},
  "geometry": {"coordinates":[-2.27227884050411,53.45534969264222],"type":"Point"}
}