{
  "type": "Feature",
  "properties": {
    "iso:country":"GB",
    "wof:name":"LE4 2GA",
    "wof:placetype":"postalcode"
},
  "geometry": {"coordinates":[-1.14763246837328,52.66554149254136],"type":"Point"}
}