{
  "type": "Feature",
  "properties": {
    "date:inception_lower": "1998-12-01",
    "date:inception_upper": "1998-12-01",
    "iso:country": "GB",
    "wof:name": "SW15 6FF",
    "wof:placetype": "postalcode"
  },
  "geometry": {"coordinates":[-0.226414,51.462243],"type":"Point"}
}
