{
  "type": "Feature",
  "properties": {
    "iso:country":"GB",
    "wof:name":"WS11 6XJ",
    "wof:placetype":"postalcode"
},
  "geometry": {"coordinates":[-2.01787613544529,52.69617436503273],"type":"Point"}
}