{
  "type": "Feature",
  "properties": {
    "iso:country":"GB",
    "wof:name":"CF11 8BE",
    "wof:placetype":"postalcode"
},
  "geometry": {"coordinates":[-3.19789877217771,51.466420578464],"type":"Point"}
}