{
  "type": "Feature",
  "properties": {
    "date:inception_lower":"1999-06-01",
    "date:inception_upper":"1999-06-30",
    "iso:country":"GB",
    "wof:name":"CF11 8BE",
    "wof:placetype":"postalcode"
},
  "geometry": {"coordinates":[-3.198729,51.467563],"type":"Point"}
}