{
  "type": "Feature",
  "properties": {
    "iso:country":"GB",
    "wof:name":"IP20 9ND",
    "wof:placetype":"postalcode"
},
  "geometry": {"coordinates":[1.28036769959615,52.39580478741217],"type":"Point"}
}