{
  "type": "Feature",
  "properties": {
    "date:inception_lower": "1980-01-01",
    "date:inception_upper": "1980-01-01",
    "iso:country": "GB",
    "wof:name": "IP17 3PZ",
    "wof:placetype": "postalcode"
  },
  "geometry": {"coordinates":[1.550384,52.271637],"type":"Point"}
}
