{
  "type": "Feature",
  "properties": {
    "date:inception_lower": "2014-04-01",
    "date:inception_upper": "2014-04-01",
    "iso:country": "GB",
    "wof:name": "SP11 6SB",
    "wof:placetype": "postalcode"
  },
  "geometry": {"coordinates":[-1.473346,51.229464],"type":"Point"}
}
