{
  "type": "Feature",
  "properties": {
    "iso:country": "GB",
    "wof:name": "SP11 6SB",
    "wof:placetype": "postalcode"
  },
  "geometry": {"coordinates":[-1.473346,51.229464],"type":"Point"}
}
