{
  "type": "Feature",
  "properties": {
    "iso:country": "GB",
    "wof:name": "WS11 1DF",
    "wof:placetype": "postalcode"
  },
  "geometry": {"coordinates":[-2.02277,52.689692],"type":"Point"}
}
