{
  "type": "Feature",
  "properties": {
    "iso:country":"GB",
    "wof:name":"PA5 8UG",
    "wof:placetype":"postalcode"
},
  "geometry": {"coordinates":[-4.53477560189873,55.84689529707872],"type":"Point"}
}