{
  "type": "Feature",
  "properties": {
    "date:inception_lower": "2023-03-01",
    "date:inception_upper": "2023-03-01",
    "iso:country": "GB",
    "wof:name": "G43 1FP",
    "wof:placetype": "postalcode"
  },
  "geometry": {"coordinates":[-4.300423,55.822953],"type":"Point"}
}
