{
  "type": "Feature",
  "properties": {
    "iso:country":"GB",
    "wof:name":"PO22 0HL",
    "wof:placetype":"postalcode"
},
  "geometry": {"coordinates":[-0.64510541387,50.83822527764669],"type":"Point"}
}