{
  "type": "Feature",
  "properties": {
    "iso:country": "GB",
    "wof:name": "PO22 0HL",
    "wof:placetype": "postalcode"
  },
  "geometry": {"coordinates":[-0.645105,50.838225],"type":"Point"}
}
