{
  "type": "Feature",
  "properties": {
    "iso:country": "GB",
    "wof:name": "G81 4JW",
    "wof:placetype": "postalcode"
  },
  "geometry": {"coordinates":[-4.438226,55.912538],"type":"Point"}
}
