{
  "type": "Feature",
  "properties": {
    "date:inception_lower": "1980-01-01",
    "date:inception_upper": "1980-01-01",
    "iso:country": "GB",
    "wof:name": "SW19 2ND",
    "wof:placetype": "postalcode"
  },
  "geometry": {"coordinates":[-0.185006,51.41519],"type":"Point"}
}
