{
  "type": "Feature",
  "properties": {
    "iso:country":"GB",
    "wof:name":"SY1 2QZ",
    "wof:placetype":"postalcode"
},
  "geometry": {"coordinates":[-2.7518200971146,52.72405897908593],"type":"Point"}
}