{
  "type": "Feature",
  "properties": {
    "iso:country":"GB",
    "wof:name":"DN40 1DZ",
    "wof:placetype":"postalcode"
},
  "geometry": {"coordinates":[-0.20752062862817,53.61462876201969],"type":"Point"}
}