{
  "type": "Feature",
  "properties": {
    "iso:country":"GB",
    "wof:name":"AB39 3PQ",
    "wof:placetype":"postalcode"
},
  "geometry": {"coordinates":[-2.16381580189649,57.02936020459208],"type":"Point"}
}