{
  "type": "Feature",
  "properties": {
    "iso:country": "GB",
    "wof:name": "AB39 3PQ",
    "wof:placetype": "postalcode"
  },
  "geometry": {"coordinates":[-2.163816,57.02936],"type":"Point"}
}
