{
  "type": "Feature",
  "properties": {
    "date:inception_lower":"1996-06-01",
    "date:inception_upper":"1996-06-30",
    "iso:country":"GB",
    "wof:name":"AB39 3PQ",
    "wof:placetype":"postalcode"
},
  "geometry": {"coordinates":[-2.163816,57.02936],"type":"Point"}
}