{
  "type": "Feature",
  "properties": {
    "iso:country":"GB",
    "wof:name":"DL14 6RU",
    "wof:placetype":"postalcode"
},
  "geometry": {"coordinates":[-1.66461266906422,54.65019348373061],"type":"Point"}
}