{
  "type": "Feature",
  "properties": {
    "iso:country":"GB",
    "wof:name":"HD4 6BN",
    "wof:placetype":"postalcode"
},
  "geometry": {"coordinates":[-1.78358272298754,53.63728142998827],"type":"Point"}
}