{
  "type": "Feature",
  "properties": {
    "iso:country": "GB",
    "wof:name": "BS16 2FS",
    "wof:placetype": "postalcode"
  },
  "geometry": {"coordinates":[-2.530566,51.485555],"type":"Point"}
}
