{
  "type": "Feature",
  "properties": {
    "date:inception_lower": "2008-03-01",
    "date:inception_upper": "2008-03-01",
    "iso:country": "GB",
    "wof:name": "HP11 9EG",
    "wof:placetype": "postalcode"
  },
  "geometry": {"coordinates":[-0.748018,51.627751],"type":"Point"}
}
