{
  "type": "Feature",
  "properties": {
    "date:inception_lower": "1980-01-01",
    "date:inception_upper": "1980-01-01",
    "iso:country": "GB",
    "wof:name": "CM3 1AR",
    "wof:placetype": "postalcode"
  },
  "geometry": {"coordinates":[0.456784,51.794317],"type":"Point"}
}
