{
  "type": "Feature",
  "properties": {
    "iso:country":"GB",
    "wof:name":"LL14 2AP",
    "wof:placetype":"postalcode"
},
  "geometry": {"coordinates":[-3.04055810443234,53.00434388299384],"type":"Point"}
}