{
  "type": "Feature",
  "properties": {
    "date:inception_lower": "2018-05-01",
    "date:inception_upper": "2018-05-01",
    "iso:country": "GB",
    "wof:name": "LE65 1GN",
    "wof:placetype": "postalcode"
  },
  "geometry": {"coordinates":[-1.455981,52.744462],"type":"Point"}
}
