{
  "type": "Feature",
  "properties": {
    "iso:country":"GB",
    "wof:name":"TN9 1DX",
    "wof:placetype":"postalcode"
},
  "geometry": {"coordinates":[0.27291379205668,51.19449258821801],"type":"Point"}
}