{
  "type": "Feature",
  "properties": {
    "iso:country":"GB",
    "wof:name":"DL8 1JT",
    "wof:placetype":"postalcode"
},
  "geometry": {"coordinates":[-1.65992840729768,54.31369897515209],"type":"Point"}
}