{
  "type": "Feature",
  "properties": {
    "iso:country": "GB",
    "wof:name": "DL8 1JT",
    "wof:placetype": "postalcode"
  },
  "geometry": {"coordinates":[-1.659936,54.31371],"type":"Point"}
}
