{
  "type": "Feature",
  "properties": {
    "iso:country": "GB",
    "wof:name": "EH26 9ED",
    "wof:placetype": "postalcode"
  },
  "geometry": {"coordinates":[-3.224855,55.82556],"type":"Point"}
}
