{
  "type": "Feature",
  "properties": {
    "iso:country": "GB",
    "wof:name": "DE55 7PE",
    "wof:placetype": "postalcode"
  },
  "geometry": {"coordinates":[-1.419002,53.092366],"type":"Point"}
}
