{
  "type": "Feature",
  "properties": {
    "iso:country": "GB",
    "wof:name": "IP3 8DP",
    "wof:placetype": "postalcode"
  },
  "geometry": {"coordinates":[1.177746,52.05225],"type":"Point"}
}
