{
  "type": "Feature",
  "properties": {
    "date:inception_lower": "2017-11-01",
    "date:inception_upper": "2017-11-01",
    "iso:country": "GB",
    "wof:name": "SG18 8NP",
    "wof:placetype": "postalcode"
  },
  "geometry": {"coordinates":[-0.244604,52.086746],"type":"Point"}
}
