{
  "type": "Feature",
  "properties": {
    "iso:country":"GB",
    "wof:name":"SL6 0HE",
    "wof:placetype":"postalcode"
},
  "geometry": {"coordinates":[-0.68759438708513,51.53469956337968],"type":"Point"}
}