{
  "type": "Feature",
  "properties": {
    "iso:country": "GB",
    "wof:name": "SL6 0HE",
    "wof:placetype": "postalcode"
  },
  "geometry": {"coordinates":[-0.687594,51.5347],"type":"Point"}
}
