{
  "type": "Feature",
  "properties": {
    "iso:country":"GB",
    "wof:name":"B97 6SL",
    "wof:placetype":"postalcode"
},
  "geometry": {"coordinates":[-1.96084986721049,52.31182325171142],"type":"Point"}
}