{
  "type": "Feature",
  "properties": {
    "iso:country":"GB",
    "wof:name":"NG32 3PU",
    "wof:placetype":"postalcode"
},
  "geometry": {"coordinates":[-0.53261276155279,52.98158036104648],"type":"Point"}
}