{
  "type": "Feature",
  "properties": {
    "date:inception_lower":"1984-10-01",
    "date:inception_upper":"1984-10-31",
    "iso:country":"GB",
    "wof:name":"RH10 3XG",
    "wof:placetype":"postalcode"
},
  "geometry": {"coordinates":[-0.127662,51.134646],"type":"Point"}
}