{
  "type": "Feature",
  "properties": {
    "iso:country":"GB",
    "wof:name":"N13 5PU",
    "wof:placetype":"postalcode"
},
  "geometry": {"coordinates":[-0.10139987292442,51.62162888975761],"type":"Point"}
}