{
  "type": "Feature",
  "properties": {
    "iso:country": "GB",
    "wof:name": "N13 5PU",
    "wof:placetype": "postalcode"
  },
  "geometry": {"coordinates":[-0.1014,51.621629],"type":"Point"}
}
