{
  "type": "Feature",
  "properties": {
    "iso:country": "GB",
    "wof:name": "DG6 4ES",
    "wof:placetype": "postalcode"
  },
  "geometry": {"coordinates":[-4.040501,54.842884],"type":"Point"}
}
