{
  "type": "Feature",
  "properties": {
    "iso:country":"GB",
    "wof:name":"DG6 4ES",
    "wof:placetype":"postalcode"
},
  "geometry": {"coordinates":[-4.04050128911245,54.84288403080787],"type":"Point"}
}