{
  "type": "Feature",
  "properties": {
    "date:inception_lower": "2022-07-01",
    "date:inception_upper": "2022-07-01",
    "iso:country": "GB",
    "wof:name": "TR19 7FA",
    "wof:placetype": "postalcode"
  },
  "geometry": {"coordinates":[-5.661665,50.151337],"type":"Point"}
}
