{
  "type": "Feature",
  "properties": {
    "iso:country":"GB",
    "wof:name":"CM6 1LY",
    "wof:placetype":"postalcode"
},
  "geometry": {"coordinates":[0.38710321441147,51.85397233597881],"type":"Point"}
}