{
  "type": "Feature",
  "properties": {
    "iso:country":"GB",
    "wof:name":"EC2V 6AF",
    "wof:placetype":"postalcode"
},
  "geometry": {"coordinates":[-0.09569964322829,51.51374365654384],"type":"Point"}
}