{
  "type": "Feature",
  "properties": {
    "iso:country": "GB",
    "wof:name": "GL7 3QZ",
    "wof:placetype": "postalcode"
  },
  "geometry": {"coordinates":[-1.65501,51.753536],"type":"Point"}
}
