{
  "type": "Feature",
  "properties": {
    "iso:country":"GB",
    "wof:name":"GL7 3QZ",
    "wof:placetype":"postalcode"
},
  "geometry": {"coordinates":[-1.65500991665548,51.7535356714816],"type":"Point"}
}