{
  "type": "Feature",
  "properties": {
    "date:inception_lower": "1980-01-01",
    "date:inception_upper": "1980-01-01",
    "iso:country": "GB",
    "wof:name": "GL7 3QZ",
    "wof:placetype": "postalcode"
  },
  "geometry": {"coordinates":[-1.65501,51.753536],"type":"Point"}
}
