{
  "type": "Feature",
  "properties": {
    "iso:country": "GB",
    "wof:name": "PL2 3FB",
    "wof:placetype": "postalcode"
  },
  "geometry": {"coordinates":[-4.152385,50.397208],"type":"Point"}
}
