{
  "type": "Feature",
  "properties": {
    "date:inception_lower": "2016-03-01",
    "date:inception_upper": "2016-03-01",
    "iso:country": "GB",
    "wof:name": "PL2 3FB",
    "wof:placetype": "postalcode"
  },
  "geometry": {"coordinates":[-4.152385,50.397208],"type":"Point"}
}
