{
  "type": "Feature",
  "properties": {
    "iso:country": "GB",
    "wof:name": "SO30 2SL",
    "wof:placetype": "postalcode"
  },
  "geometry": {"coordinates":[-1.274884,50.91834],"type":"Point"}
}
