{
  "type": "Feature",
  "properties": {
    "iso:country":"GB",
    "wof:name":"SO30 2SL",
    "wof:placetype":"postalcode"
},
  "geometry": {"coordinates":[-1.27488355919204,50.91834024976457],"type":"Point"}
}