{
  "type": "Feature",
  "properties": {
    "date:inception_lower": "2023-02-01",
    "date:inception_upper": "2023-02-01",
    "iso:country": "GB",
    "wof:name": "CH65 3EU",
    "wof:placetype": "postalcode"
  },
  "geometry": {"coordinates":[-2.908052,53.284607],"type":"Point"}
}
