{
  "type": "Feature",
  "properties": {
    "iso:country":"GB",
    "wof:name":"SE16 2AX",
    "wof:placetype":"postalcode"
},
  "geometry": {"coordinates":[-0.05406212596261,51.49007507104808],"type":"Point"}
}