{
  "type": "Feature",
  "properties": {
    "iso:country": "GB",
    "wof:name": "SE16 2AX",
    "wof:placetype": "postalcode"
  },
  "geometry": {"coordinates":[-0.054062,51.490075],"type":"Point"}
}
