{
  "type": "Feature",
  "properties": {
    "date:inception_lower": "1980-01-01",
    "date:inception_upper": "1980-01-01",
    "iso:country": "GB",
    "wof:name": "LA9 6QW",
    "wof:placetype": "postalcode"
  },
  "geometry": {"coordinates":[-2.762677,54.351678],"type":"Point"}
}
