{
  "type": "Feature",
  "properties": {
    "iso:country":"GB",
    "wof:name":"LA9 6QW",
    "wof:placetype":"postalcode"
},
  "geometry": {"coordinates":[-2.76267669486861,54.35167824003707],"type":"Point"}
}