{
  "type": "Feature",
  "properties": {
    "iso:country":"GB",
    "wof:name":"ME17 1NP",
    "wof:placetype":"postalcode"
},
  "geometry": {"coordinates":[0.68640872235421,51.2521191980303],"type":"Point"}
}