{
  "type": "Feature",
  "properties": {
    "iso:country": "GB",
    "wof:name": "ME17 1NP",
    "wof:placetype": "postalcode"
  },
  "geometry": {"coordinates":[0.686409,51.252119],"type":"Point"}
}
