{
  "type": "Feature",
  "properties": {
    "iso:country": "GB",
    "wof:name": "LA22 9EP",
    "wof:placetype": "postalcode"
  },
  "geometry": {"coordinates":[-2.957155,54.433039],"type":"Point"}
}
