{
  "type": "Feature",
  "properties": {
    "iso:country":"GB",
    "wof:name":"LL60 6EF",
    "wof:placetype":"postalcode"
},
  "geometry": {"coordinates":[-4.25611542266662,53.20892473055687],"type":"Point"}
}