{
  "type": "Feature",
  "properties": {
    "iso:country": "GB",
    "wof:name": "SA19 9PY",
    "wof:placetype": "postalcode"
  },
  "geometry": {"coordinates":[-3.85346,51.898959],"type":"Point"}
}
