{
  "type": "Feature",
  "properties": {
    "date:inception_lower": "1980-01-01",
    "date:inception_upper": "1980-01-01",
    "iso:country": "GB",
    "wof:name": "SA19 9PY",
    "wof:placetype": "postalcode"
  },
  "geometry": {"coordinates":[-3.85346,51.898959],"type":"Point"}
}
