{
  "type": "Feature",
  "properties": {
    "iso:country":"GB",
    "wof:name":"CV36 5HW",
    "wof:placetype":"postalcode"
},
  "geometry": {"coordinates":[-1.57516559757875,52.02884608946874],"type":"Point"}
}