{
  "type": "Feature",
  "properties": {
    "date:inception_lower": "1980-01-01",
    "date:inception_upper": "1980-01-01",
    "iso:country": "GB",
    "wof:name": "CV36 5HW",
    "wof:placetype": "postalcode"
  },
  "geometry": {"coordinates":[-1.575166,52.028846],"type":"Point"}
}
