{
  "type": "Feature",
  "properties": {
    "iso:country":"GB",
    "wof:name":"DH8 9HS",
    "wof:placetype":"postalcode"
},
  "geometry": {"coordinates":[-1.8908587723375,54.802750674316],"type":"Point"}
}