{
  "type": "Feature",
  "properties": {
    "iso:country": "GB",
    "wof:name": "DH8 9HS",
    "wof:placetype": "postalcode"
  },
  "geometry": {"coordinates":[-1.890859,54.802751],"type":"Point"}
}
