{
  "type": "Feature",
  "properties": {
    "date:inception_lower": "1980-01-01",
    "date:inception_upper": "1980-01-01",
    "iso:country": "GB",
    "wof:name": "SA62 5HS",
    "wof:placetype": "postalcode"
  },
  "geometry": {"coordinates":[-5.056217,51.904211],"type":"Point"}
}
