{
  "type": "Feature",
  "properties": {
    "iso:country":"GB",
    "wof:name":"SA62 5HS",
    "wof:placetype":"postalcode"
},
  "geometry": {"coordinates":[-5.05562426491953,51.90386042647639],"type":"Point"}
}