{
  "type": "Feature",
  "properties": {
    "iso:country":"GB",
    "wof:name":"SO51 0NT",
    "wof:placetype":"postalcode"
},
  "geometry": {"coordinates":[-1.503151375285,51.03340419596598],"type":"Point"}
}