{
  "type": "Feature",
  "properties": {
    "date:inception_lower": "1986-01-01",
    "date:inception_upper": "1986-01-01",
    "iso:country": "GB",
    "wof:name": "SO51 0NT",
    "wof:placetype": "postalcode"
  },
  "geometry": {"coordinates":[-1.503151,51.033404],"type":"Point"}
}
