{
  "type": "Feature",
  "properties": {
    "iso:country":"GB",
    "wof:name":"HU6 7AS",
    "wof:placetype":"postalcode"
},
  "geometry": {"coordinates":[-0.35986149040045,53.78883980737388],"type":"Point"}
}