{
  "type": "Feature",
  "properties": {
    "date:inception_lower":"2013-07-01",
    "date:inception_upper":"2013-07-31",
    "iso:country":"GB",
    "wof:name":"PL25 4EF",
    "wof:placetype":"postalcode"
},
  "geometry": {"coordinates":[-4.788093,50.340706],"type":"Point"}
}