{
  "type": "Feature",
  "properties": {
    "iso:country": "GB",
    "wof:name": "SA69 9HS",
    "wof:placetype": "postalcode"
  },
  "geometry": {"coordinates":[-4.703063,51.70759],"type":"Point"}
}
