{
  "type": "Feature",
  "properties": {
    "date:inception_lower": "1980-01-01",
    "date:inception_upper": "1980-01-01",
    "iso:country": "GB",
    "wof:name": "SA69 9HS",
    "wof:placetype": "postalcode"
  },
  "geometry": {"coordinates":[-4.703063,51.70759],"type":"Point"}
}
