{
  "type": "Feature",
  "properties": {
    "date:inception_lower": "1980-01-01",
    "date:inception_upper": "1980-01-01",
    "iso:country": "GB",
    "wof:name": "TS25 2AA",
    "wof:placetype": "postalcode"
  },
  "geometry": {"coordinates":[-1.19634,54.65893],"type":"Point"}
}
