{
  "type": "Feature",
  "properties": {
    "iso:country": "GB",
    "wof:name": "TS25 2AA",
    "wof:placetype": "postalcode"
  },
  "geometry": {"coordinates":[-1.19634,54.65893],"type":"Point"}
}
