{
  "type": "Feature",
  "properties": {
    "iso:country":"GB",
    "wof:name":"NP23 5EW",
    "wof:placetype":"postalcode"
},
  "geometry": {"coordinates":[-3.21005401984024,51.80531029649669],"type":"Point"}
}