{
  "type": "Feature",
  "properties": {
    "iso:country": "GB",
    "wof:name": "NP23 5EW",
    "wof:placetype": "postalcode"
  },
  "geometry": {"coordinates":[-3.210054,51.80531],"type":"Point"}
}
