{
  "type": "Feature",
  "properties": {
    "iso:country": "GB",
    "wof:name": "LN1 1XG",
    "wof:placetype": "postalcode"
  },
  "geometry": {"coordinates":[-0.543454,53.229716],"type":"Point"}
}
