{
  "type": "Feature",
  "properties": {
    "iso:country":"GB",
    "wof:name":"LN1 1XG",
    "wof:placetype":"postalcode"
},
  "geometry": {"coordinates":[-0.54345389580606,53.22971561115578],"type":"Point"}
}