{
  "type": "Feature",
  "properties": {
    "iso:country":"GB",
    "wof:name":"PE6 7AD",
    "wof:placetype":"postalcode"
},
  "geometry": {"coordinates":[-0.31816296833122,52.5889016554063],"type":"Point"}
}