{
  "type": "Feature",
  "properties": {
    "iso:country": "GB",
    "wof:name": "PE6 7AD",
    "wof:placetype": "postalcode"
  },
  "geometry": {"coordinates":[-0.318149,52.58892],"type":"Point"}
}
