{
  "type": "Feature",
  "properties": {
    "iso:country": "GB",
    "wof:name": "GL12 7HW",
    "wof:placetype": "postalcode"
  },
  "geometry": {"coordinates":[-2.343253,51.638128],"type":"Point"}
}
