{
  "type": "Feature",
  "properties": {
    "iso:country":"GB",
    "wof:name":"GL12 7HW",
    "wof:placetype":"postalcode"
},
  "geometry": {"coordinates":[-2.34325274345862,51.63812817502712],"type":"Point"}
}