{
  "type": "Feature",
  "properties": {
    "iso:country":"GB",
    "wof:name":"TS14 6RQ",
    "wof:placetype":"postalcode"
},
  "geometry": {"coordinates":[-1.0706694667456,54.56984984133385],"type":"Point"}
}