{
  "type": "Feature",
  "properties": {
    "iso:country": "GB",
    "wof:name": "TS14 6RQ",
    "wof:placetype": "postalcode"
  },
  "geometry": {"coordinates":[-1.067312,54.570529],"type":"Point"}
}
