{
  "type": "Feature",
  "properties": {
    "iso:country":"GB",
    "wof:name":"LS21 3JW",
    "wof:placetype":"postalcode"
},
  "geometry": {"coordinates":[-1.70169788968293,53.90334012437679],"type":"Point"}
}