{
  "type": "Feature",
  "properties": {
    "iso:country":"GB",
    "wof:name":"L12 8QR",
    "wof:placetype":"postalcode"
},
  "geometry": {"coordinates":[-2.90278934530309,53.42752851221518],"type":"Point"}
}