{
  "type": "Feature",
  "properties": {
    "iso:country": "GB",
    "wof:name": "DN17 2AL",
    "wof:placetype": "postalcode"
  },
  "geometry": {"coordinates":[-0.685868,53.565051],"type":"Point"}
}
