{
  "type": "Feature",
  "properties": {
    "iso:country":"GB",
    "wof:name":"DN17 2AL",
    "wof:placetype":"postalcode"
},
  "geometry": {"coordinates":[-0.68586792043749,53.56505134234254],"type":"Point"}
}