{
  "type": "Feature",
  "properties": {
    "iso:country":"GB",
    "wof:name":"BS16 1AY",
    "wof:placetype":"postalcode"
},
  "geometry": {"coordinates":[-2.55289530860848,51.48374456848298],"type":"Point"}
}