{
  "type": "Feature",
  "properties": {
    "iso:country":"GB",
    "wof:name":"DE23 8DQ",
    "wof:placetype":"postalcode"
},
  "geometry": {"coordinates":[-1.48454654125267,52.89904774232497],"type":"Point"}
}