{
  "type": "Feature",
  "properties": {
    "iso:country":"GB",
    "wof:name":"NE23 8HB",
    "wof:placetype":"postalcode"
},
  "geometry": {"coordinates":[-1.60566723052739,55.08549812273503],"type":"Point"}
}