{
  "type": "Feature",
  "properties": {
    "date:inception_lower": "2020-09-01",
    "date:inception_upper": "2020-09-01",
    "iso:country": "GB",
    "wof:name": "B29 6UX",
    "wof:placetype": "postalcode"
  },
  "geometry": {"coordinates":[-1.935712,52.437005],"type":"Point"}
}
