{
  "type": "Feature",
  "properties": {
    "date:inception_lower": "2000-06-01",
    "date:inception_upper": "2000-06-01",
    "iso:country": "GB",
    "wof:name": "CH41 1AW",
    "wof:placetype": "postalcode"
  },
  "geometry": {"coordinates":[-3.014562,53.397013],"type":"Point"}
}
