{
  "type": "Feature",
  "properties": {
    "iso:country": "GB",
    "wof:name": "CH41 1AW",
    "wof:placetype": "postalcode"
  },
  "geometry": {"coordinates":[-3.014562,53.397013],"type":"Point"}
}
