{
  "type": "Feature",
  "properties": {
    "iso:country":"GB",
    "wof:name":"BA22 7LX",
    "wof:placetype":"postalcode"
},
  "geometry": {"coordinates":[-2.57160777328968,51.06384051299221],"type":"Point"}
}