{
  "type": "Feature",
  "properties": {
    "iso:country":"GB",
    "wof:name":"SW12 8NF",
    "wof:placetype":"postalcode"
},
  "geometry": {"coordinates":[-0.16135245181758,51.44808465595831],"type":"Point"}
}