{
  "type": "Feature",
  "properties": {
    "iso:country": "GB",
    "wof:name": "EX14 2EZ",
    "wof:placetype": "postalcode"
  },
  "geometry": {"coordinates":[-3.187444,50.79614],"type":"Point"}
}
