{
  "type": "Feature",
  "properties": {
    "iso:country":"GB",
    "wof:name":"SK11 9LT",
    "wof:placetype":"postalcode"
},
  "geometry": {"coordinates":[-2.25501762677079,53.22596094432011],"type":"Point"}
}