{
  "type": "Feature",
  "properties": {
    "iso:country": "GB",
    "wof:name": "BD23 1FG",
    "wof:placetype": "postalcode"
  },
  "geometry": {"coordinates":[-2.028337,53.969691],"type":"Point"}
}
