{
  "type": "Feature",
  "properties": {
    "date:inception_lower":"2018-08-01",
    "date:inception_upper":"2018-08-31",
    "iso:country":"GB",
    "wof:name":"BD23 1FG",
    "wof:placetype":"postalcode"
},
  "geometry": {"coordinates":[-2.028642,53.969727],"type":"Point"}
}