{
  "type": "Feature",
  "properties": {
    "date:inception_lower": "2018-08-01",
    "date:inception_upper": "2018-08-01",
    "iso:country": "GB",
    "wof:name": "BD23 1FG",
    "wof:placetype": "postalcode"
  },
  "geometry": {"coordinates":[-2.028429,53.969619],"type":"Point"}
}
