{
  "type": "Feature",
  "properties": {
    "iso:country":"GB",
    "wof:name":"BS4 5BP",
    "wof:placetype":"postalcode"
},
  "geometry": {"coordinates":[-2.55116888945366,51.43133154227624],"type":"Point"}
}