{
  "type": "Feature",
  "properties": {
    "iso:country":"GB",
    "wof:name":"EX23 9FB",
    "wof:placetype":"postalcode"
},
  "geometry": {"coordinates":[-4.50757137791916,50.82574277809471],"type":"Point"}
}