{
  "type": "Feature",
  "properties": {
    "date:inception_lower":"2016-03-01",
    "date:inception_upper":"2016-03-31",
    "iso:country":"GB",
    "wof:name":"EX23 9FB",
    "wof:placetype":"postalcode"
},
  "geometry": {"coordinates":[-4.507571,50.825743],"type":"Point"}
}