{
  "type": "Feature",
  "properties": {
    "iso:country":"GB",
    "wof:name":"WF4 5BB",
    "wof:placetype":"postalcode"
},
  "geometry": {"coordinates":[-1.55299701738032,53.65767558355409],"type":"Point"}
}