{
  "type": "Feature",
  "properties": {
    "iso:country":"GB",
    "wof:name":"LS28 6BG",
    "wof:placetype":"postalcode"
},
  "geometry": {"coordinates":[-1.67532181316313,53.80699324066794],"type":"Point"}
}