{
  "type": "Feature",
  "properties": {
    "date:inception_lower": "2018-08-01",
    "date:inception_upper": "2018-08-01",
    "iso:country": "GB",
    "wof:name": "IV30 8AG",
    "wof:placetype": "postalcode"
  },
  "geometry": {"coordinates":[-3.309852,57.631256],"type":"Point"}
}
