{
  "type": "Feature",
  "properties": {
    "date:inception_lower": "2021-06-01",
    "date:inception_upper": "2021-06-01",
    "iso:country": "GB",
    "wof:name": "BB8 7BF",
    "wof:placetype": "postalcode"
  },
  "geometry": {"coordinates":[-2.149625,53.861154],"type":"Point"}
}
