{
  "type": "Feature",
  "properties": {
    "date:inception_lower": "1980-01-01",
    "date:inception_upper": "1980-01-01",
    "iso:country": "GB",
    "wof:name": "WA6 6ES",
    "wof:placetype": "postalcode"
  },
  "geometry": {"coordinates":[-2.715784,53.285304],"type":"Point"}
}
