{
  "type": "Feature",
  "properties": {
    "iso:country":"GB",
    "wof:name":"WS11 7LS",
    "wof:placetype":"postalcode"
},
  "geometry": {"coordinates":[-2.00776829365263,52.68703302241472],"type":"Point"}
}