{
  "type": "Feature",
  "properties": {
    "date:inception_lower": "2007-01-01",
    "date:inception_upper": "2007-01-01",
    "iso:country": "GB",
    "wof:name": "WS11 7LS",
    "wof:placetype": "postalcode"
  },
  "geometry": {"coordinates":[-2.007768,52.687033],"type":"Point"}
}
