{
  "type": "Feature",
  "properties": {
    "iso:country":"GB",
    "wof:name":"L32 7RQ",
    "wof:placetype":"postalcode"
},
  "geometry": {"coordinates":[-2.87956610200827,53.46609297317773],"type":"Point"}
}