{
  "type": "Feature",
  "properties": {
    "iso:country": "GB",
    "wof:name": "L32 7RQ",
    "wof:placetype": "postalcode"
  },
  "geometry": {"coordinates":[-2.879566,53.466093],"type":"Point"}
}
