{
  "type": "Feature",
  "properties": {
    "iso:country": "GB",
    "wof:name": "PE27 4RZ",
    "wof:placetype": "postalcode"
  },
  "geometry": {"coordinates":[-0.037553,52.330479],"type":"Point"}
}
