{
  "type": "Feature",
  "properties": {
    "iso:country": "GB",
    "wof:name": "RG20 8JL",
    "wof:placetype": "postalcode"
  },
  "geometry": {"coordinates":[-1.36084,51.412922],"type":"Point"}
}
