{
  "type": "Feature",
  "properties": {
    "date:inception_lower":"2005-10-01",
    "date:inception_upper":"2005-10-31",
    "iso:country":"GB",
    "wof:name":"RG20 8JL",
    "wof:placetype":"postalcode"
},
  "geometry": {"coordinates":[-1.36084,51.412922],"type":"Point"}
}