{
  "type": "Feature",
  "properties": {
    "iso:country":"GB",
    "wof:name":"SE6 1HT",
    "wof:placetype":"postalcode"
},
  "geometry": {"coordinates":[0.00327071401451,51.44178080493023],"type":"Point"}
}