{
  "type": "Feature",
  "properties": {
    "iso:country": "GB",
    "wof:name": "AB16 6PJ",
    "wof:placetype": "postalcode"
  },
  "geometry": {"coordinates":[-2.174633,57.154328],"type":"Point"}
}
