{
  "type": "Feature",
  "properties": {
    "iso:country": "GB",
    "wof:name": "TS6 9TD",
    "wof:placetype": "postalcode"
  },
  "geometry": {"coordinates":[-1.139651,54.558308],"type":"Point"}
}
