{
  "type": "Feature",
  "properties": {
    "iso:country":"GB",
    "wof:name":"TS6 9TD",
    "wof:placetype":"postalcode"
},
  "geometry": {"coordinates":[-1.13965139616659,54.55830803494437],"type":"Point"}
}