{
  "type": "Feature",
  "properties": {
    "iso:country":"GB",
    "wof:name":"G52 2NF",
    "wof:placetype":"postalcode"
},
  "geometry": {"coordinates":[-4.34390402501867,55.85150813209145],"type":"Point"}
}