{
  "type": "Feature",
  "properties": {
    "iso:country":"GB",
    "wof:name":"S12 3JG",
    "wof:placetype":"postalcode"
},
  "geometry": {"coordinates":[-1.42184863902255,53.33643920108815],"type":"Point"}
}