{
  "type": "Feature",
  "properties": {
    "iso:country":"GB",
    "wof:name":"SL6 1RS",
    "wof:placetype":"postalcode"
},
  "geometry": {"coordinates":[-0.71608724214349,51.52280375598857],"type":"Point"}
}