{
  "type": "Feature",
  "properties": {
    "date:inception_lower":"1994-05-01",
    "date:inception_upper":"1994-05-31",
    "iso:country":"GB",
    "wof:name":"DT8 3ST",
    "wof:placetype":"postalcode"
},
  "geometry": {"coordinates":[-2.796451,50.817919],"type":"Point"}
}