{
  "type": "Feature",
  "properties": {
    "iso:country":"GB",
    "wof:name":"DT8 3ST",
    "wof:placetype":"postalcode"
},
  "geometry": {"coordinates":[-2.79645071383506,50.81791904940725],"type":"Point"}
}