{
  "type": "Feature",
  "properties": {
    "iso:country": "GB",
    "wof:name": "DT8 3ST",
    "wof:placetype": "postalcode"
  },
  "geometry": {"coordinates":[-2.796451,50.817919],"type":"Point"}
}
