{
  "type": "Feature",
  "properties": {
    "iso:country": "GB",
    "wof:name": "WR6 6DA",
    "wof:placetype": "postalcode"
  },
  "geometry": {"coordinates":[-2.372869,52.299859],"type":"Point"}
}
