{
  "type": "Feature",
  "properties": {
    "iso:country":"GB",
    "wof:name":"WR6 6DA",
    "wof:placetype":"postalcode"
},
  "geometry": {"coordinates":[-2.37286861489734,52.29985866598237],"type":"Point"}
}