{
  "type": "Feature",
  "properties": {
    "date:inception_lower": "1980-01-01",
    "date:inception_upper": "1980-01-01",
    "iso:country": "GB",
    "wof:name": "ST17 0UY",
    "wof:placetype": "postalcode"
  },
  "geometry": {"coordinates":[-2.039297,52.789193],"type":"Point"}
}
