{
  "type": "Feature",
  "properties": {
    "iso:country":"GB",
    "wof:name":"SO16 6BR",
    "wof:placetype":"postalcode"
},
  "geometry": {"coordinates":[-1.43974067113089,50.92966950824406],"type":"Point"}
}