{
  "type": "Feature",
  "properties": {
    "date:inception_lower": "1980-01-01",
    "date:inception_upper": "1980-01-01",
    "iso:country": "GB",
    "wof:name": "EH4 3HX",
    "wof:placetype": "postalcode"
  },
  "geometry": {"coordinates":[-3.237686,55.952506],"type":"Point"}
}
