{
  "type": "Feature",
  "properties": {
    "iso:country":"GB",
    "wof:name":"EH4 3HX",
    "wof:placetype":"postalcode"
},
  "geometry": {"coordinates":[-3.23768592572607,55.95250645982708],"type":"Point"}
}