{
  "type": "Feature",
  "properties": {
    "date:inception_lower": "2020-08-01",
    "date:inception_upper": "2020-08-01",
    "iso:country": "GB",
    "wof:name": "WF2 9FE",
    "wof:placetype": "postalcode"
  },
  "geometry": {"coordinates":[-1.534734,53.682619],"type":"Point"}
}
