{
  "type": "Feature",
  "properties": {
    "iso:country":"GB",
    "wof:name":"M24 6DW",
    "wof:placetype":"postalcode"
},
  "geometry": {"coordinates":[-2.19715949428775,53.55521487672901],"type":"Point"}
}