{
  "type": "Feature",
  "properties": {
    "iso:country":"GB",
    "wof:name":"PL1 5PW",
    "wof:placetype":"postalcode"
},
  "geometry": {"coordinates":[-4.16133963841304,50.37569310554598],"type":"Point"}
}