{
  "type": "Feature",
  "properties": {
    "iso:country": "GB",
    "wof:name": "PL1 5PW",
    "wof:placetype": "postalcode"
  },
  "geometry": {"coordinates":[-4.16134,50.375693],"type":"Point"}
}
