{
  "type": "Feature",
  "properties": {
    "iso:country":"GB",
    "wof:name":"SW2 2DF",
    "wof:placetype":"postalcode"
},
  "geometry": {"coordinates":[-0.11613910892616,51.44796928627994],"type":"Point"}
}