{
  "type": "Feature",
  "properties": {
    "iso:country": "GB",
    "wof:name": "NE31 1BD",
    "wof:placetype": "postalcode"
  },
  "geometry": {"coordinates":[-1.520648,54.976775],"type":"Point"}
}
