{
  "type": "Feature",
  "properties": {
    "date:inception_lower":"1994-05-01",
    "date:inception_upper":"1994-05-31",
    "iso:country":"GB",
    "wof:name":"NE31 1BD",
    "wof:placetype":"postalcode"
},
  "geometry": {"coordinates":[-1.520648,54.976775],"type":"Point"}
}