{
  "type": "Feature",
  "properties": {
    "iso:country":"GB",
    "wof:name":"WA2 8EG",
    "wof:placetype":"postalcode"
},
  "geometry": {"coordinates":[-2.57699327899526,53.40551167476965],"type":"Point"}
}