{
  "type": "Feature",
  "properties": {
    "date:inception_lower":"1980-01-01",
    "date:inception_upper":"1980-01-31",
    "iso:country":"GB",
    "wof:name":"WA2 8EG",
    "wof:placetype":"postalcode"
},
  "geometry": {"coordinates":[-2.576993,53.405512],"type":"Point"}
}