{
  "type": "Feature",
  "properties": {
    "date:inception_lower": "1990-07-01",
    "date:inception_upper": "1990-07-01",
    "iso:country": "GB",
    "wof:name": "BN41 2RX",
    "wof:placetype": "postalcode"
  },
  "geometry": {"coordinates":[-0.232031,50.850469],"type":"Point"}
}
