{
  "type": "Feature",
  "properties": {
    "iso:country":"GB",
    "wof:name":"OL2 7TF",
    "wof:placetype":"postalcode"
},
  "geometry": {"coordinates":[-2.09286481176621,53.58040993180723],"type":"Point"}
}