{
  "type": "Feature",
  "properties": {
    "iso:country": "GB",
    "wof:name": "OL2 7TF",
    "wof:placetype": "postalcode"
  },
  "geometry": {"coordinates":[-2.092865,53.58041],"type":"Point"}
}
