{
  "type": "Feature",
  "properties": {
    "iso:country":"GB",
    "wof:name":"TN4 8NL",
    "wof:placetype":"postalcode"
},
  "geometry": {"coordinates":[0.23846876856224,51.12845245900255],"type":"Point"}
}