{
  "type": "Feature",
  "properties": {
    "iso:country":"GB",
    "wof:name":"LL19 9HP",
    "wof:placetype":"postalcode"
},
  "geometry": {"coordinates":[-3.38841544422303,53.33594221574076],"type":"Point"}
}