{
  "type": "Feature",
  "properties": {
    "date:inception_lower":"1980-01-01",
    "date:inception_upper":"1980-01-31",
    "iso:country":"GB",
    "wof:name":"LL19 9HP",
    "wof:placetype":"postalcode"
},
  "geometry": {"coordinates":[-3.388415,53.335942],"type":"Point"}
}