{
  "type": "Feature",
  "properties": {
    "iso:country": "GB",
    "wof:name": "LL19 9HP",
    "wof:placetype": "postalcode"
  },
  "geometry": {"coordinates":[-3.388415,53.335942],"type":"Point"}
}
