{
  "type": "Feature",
  "properties": {
    "iso:country": "GB",
    "wof:name": "TR19 7SH",
    "wof:placetype": "postalcode"
  },
  "geometry": {"coordinates":[-5.668848,50.148759],"type":"Point"}
}
