{
  "type": "Feature",
  "properties": {
    "iso:country":"GB",
    "wof:name":"TR19 7SH",
    "wof:placetype":"postalcode"
},
  "geometry": {"coordinates":[-5.66930870032519,50.14892397495257],"type":"Point"}
}