{
  "type": "Feature",
  "properties": {
    "iso:country":"GB",
    "wof:name":"GL10 2DR",
    "wof:placetype":"postalcode"
},
  "geometry": {"coordinates":[-2.28907970168877,51.74699565572693],"type":"Point"}
}