{
  "type": "Feature",
  "properties": {
    "iso:country": "GB",
    "wof:name": "GL10 2DR",
    "wof:placetype": "postalcode"
  },
  "geometry": {"coordinates":[-2.28908,51.746996],"type":"Point"}
}
