{
  "type": "Feature",
  "properties": {
    "iso:country":"GB",
    "wof:name":"BD2 3HF",
    "wof:placetype":"postalcode"
},
  "geometry": {"coordinates":[-1.72099034097988,53.81052349455783],"type":"Point"}
}