{
  "type": "Feature",
  "properties": {
    "iso:country":"GB",
    "wof:name":"LD6 5EB",
    "wof:placetype":"postalcode"
},
  "geometry": {"coordinates":[-3.50827037906744,52.30090141274988],"type":"Point"}
}