{
  "type": "Feature",
  "properties": {
    "date:inception_lower": "1980-01-01",
    "date:inception_upper": "1980-01-01",
    "iso:country": "GB",
    "wof:name": "LD6 5EB",
    "wof:placetype": "postalcode"
  },
  "geometry": {"coordinates":[-3.50827,52.300901],"type":"Point"}
}
