{
  "type": "Feature",
  "properties": {
    "iso:country": "GB",
    "wof:name": "S60 5QD",
    "wof:placetype": "postalcode"
  },
  "geometry": {"coordinates":[-1.354392,53.386961],"type":"Point"}
}
