{
  "type": "Feature",
  "properties": {
    "iso:country": "GB",
    "wof:name": "NR7 8GT",
    "wof:placetype": "postalcode"
  },
  "geometry": {"coordinates":[1.347901,52.657537],"type":"Point"}
}
