{
  "type": "Feature",
  "properties": {
    "iso:country": "GB",
    "wof:name": "SA11 3QG",
    "wof:placetype": "postalcode"
  },
  "geometry": {"coordinates":[-3.780211,51.648758],"type":"Point"}
}
