{
  "type": "Feature",
  "properties": {
    "date:inception_lower": "1980-01-01",
    "date:inception_upper": "1980-01-01",
    "iso:country": "GB",
    "wof:name": "SA11 3QG",
    "wof:placetype": "postalcode"
  },
  "geometry": {"coordinates":[-3.780211,51.648758],"type":"Point"}
}
