{
  "type": "Feature",
  "properties": {
    "iso:country":"GB",
    "wof:name":"SY4 2HZ",
    "wof:placetype":"postalcode"
},
  "geometry": {"coordinates":[-2.84528423931405,52.77330484649625],"type":"Point"}
}