{
  "type": "Feature",
  "properties": {
    "iso:country":"GB",
    "wof:name":"AL9 5DQ",
    "wof:placetype":"postalcode"
},
  "geometry": {"coordinates":[-0.2146374938162,51.76998696302447],"type":"Point"}
}