{
  "type": "Feature",
  "properties": {
    "date:inception_lower":"1980-01-01",
    "date:inception_upper":"1980-01-31",
    "iso:country":"GB",
    "wof:name":"AL9 5DQ",
    "wof:placetype":"postalcode"
},
  "geometry": {"coordinates":[-0.214637,51.769987],"type":"Point"}
}