{
  "type": "Feature",
  "properties": {
    "iso:country": "GB",
    "wof:name": "SW19 8SE",
    "wof:placetype": "postalcode"
  },
  "geometry": {"coordinates":[-0.186296,51.422224],"type":"Point"}
}
