{
  "type": "Feature",
  "properties": {
    "iso:country":"GB",
    "wof:name":"SW19 8SE",
    "wof:placetype":"postalcode"
},
  "geometry": {"coordinates":[-0.18629557760025,51.42222392740078],"type":"Point"}
}