{
  "type": "Feature",
  "properties": {
    "iso:country":"GB",
    "wof:name":"RG9 1TR",
    "wof:placetype":"postalcode"
},
  "geometry": {"coordinates":[-0.91373073624483,51.53621057839339],"type":"Point"}
}