{
  "type": "Feature",
  "properties": {
    "iso:country":"GB",
    "wof:name":"ME14 5LP",
    "wof:placetype":"postalcode"
},
  "geometry": {"coordinates":[0.53421160440628,51.27854771090635],"type":"Point"}
}