{
  "type": "Feature",
  "properties": {
    "iso:country":"GB",
    "wof:name":"RG20 0PR",
    "wof:placetype":"postalcode"
},
  "geometry": {"coordinates":[-1.35542497599082,51.36854509366185],"type":"Point"}
}