{
  "type": "Feature",
  "properties": {
    "iso:country":"GB",
    "wof:name":"SO53 5AB",
    "wof:placetype":"postalcode"
},
  "geometry": {"coordinates":[-1.37286454062875,51.0014577044882],"type":"Point"}
}