{
  "type": "Feature",
  "properties": {
    "iso:country": "GB",
    "wof:name": "IP7 6BF",
    "wof:placetype": "postalcode"
  },
  "geometry": {"coordinates":[0.96314,52.054677],"type":"Point"}
}
