{
  "type": "Feature",
  "properties": {
    "iso:country":"GB",
    "wof:name":"IP7 6BF",
    "wof:placetype":"postalcode"
},
  "geometry": {"coordinates":[0.96315144212836,52.05464423568461],"type":"Point"}
}