{
  "type": "Feature",
  "properties": {
    "date:inception_lower":"2003-06-01",
    "date:inception_upper":"2003-06-30",
    "iso:country":"GB",
    "wof:name":"NG34 7BP",
    "wof:placetype":"postalcode"
},
  "geometry": {"coordinates":[-0.422664,53.000517],"type":"Point"}
}