{
  "type": "Feature",
  "properties": {
    "iso:country":"GB",
    "wof:name":"CV5 7BB",
    "wof:placetype":"postalcode"
},
  "geometry": {"coordinates":[-1.58232815784498,52.41230386739143],"type":"Point"}
}