{
  "type": "Feature",
  "properties": {
    "iso:country": "GB",
    "wof:name": "BS39 5US",
    "wof:placetype": "postalcode"
  },
  "geometry": {"coordinates":[-2.592981,51.335437],"type":"Point"}
}
