{
  "type": "Feature",
  "properties": {
    "date:inception_lower": "1997-12-01",
    "date:inception_upper": "1997-12-01",
    "iso:country": "GB",
    "wof:name": "BS39 5US",
    "wof:placetype": "postalcode"
  },
  "geometry": {"coordinates":[-2.592981,51.335437],"type":"Point"}
}
