{
  "type": "Feature",
  "properties": {
    "date:inception_lower": "1999-12-01",
    "date:inception_upper": "1999-12-01",
    "iso:country": "GB",
    "wof:name": "IP11 2DW",
    "wof:placetype": "postalcode"
  },
  "geometry": {"coordinates":[1.336866,51.952607],"type":"Point"}
}
