{
  "type": "Feature",
  "properties": {
    "iso:country":"GB",
    "wof:name":"NR20 4QB",
    "wof:placetype":"postalcode"
},
  "geometry": {"coordinates":[0.98809662843869,52.72237155663888],"type":"Point"}
}