{
  "type": "Feature",
  "properties": {
    "iso:country": "GB",
    "wof:name": "SE18 4EA",
    "wof:placetype": "postalcode"
  },
  "geometry": {"coordinates":[0.045567,51.473488],"type":"Point"}
}
