{
  "type": "Feature",
  "properties": {
    "iso:country": "GB",
    "wof:name": "L4 4DJ",
    "wof:placetype": "postalcode"
  },
  "geometry": {"coordinates":[-2.969203,53.438684],"type":"Point"}
}
