{
  "type": "Feature",
  "properties": {
    "iso:country":"GB",
    "wof:name":"L4 4DJ",
    "wof:placetype":"postalcode"
},
  "geometry": {"coordinates":[-2.96920321156197,53.43868446074848],"type":"Point"}
}