{
  "type": "Feature",
  "properties": {
    "date:inception_lower": "1980-01-01",
    "date:inception_upper": "1980-01-01",
    "iso:country": "GB",
    "wof:name": "L4 4DJ",
    "wof:placetype": "postalcode"
  },
  "geometry": {"coordinates":[-2.969203,53.438684],"type":"Point"}
}
