{
  "type": "Feature",
  "properties": {
    "date:inception_lower": "1980-01-01",
    "date:inception_upper": "1980-01-01",
    "iso:country": "GB",
    "wof:name": "GL6 0NQ",
    "wof:placetype": "postalcode"
  },
  "geometry": {"coordinates":[-2.228745,51.69997],"type":"Point"}
}
