{
  "type": "Feature",
  "properties": {
    "iso:country":"GB",
    "wof:name":"GL6 0NQ",
    "wof:placetype":"postalcode"
},
  "geometry": {"coordinates":[-2.22874530894054,51.69997018563735],"type":"Point"}
}