{
  "type": "Feature",
  "properties": {
    "iso:country":"GB",
    "wof:name":"DH2 3JQ",
    "wof:placetype":"postalcode"
},
  "geometry": {"coordinates":[-1.59478481137956,54.84585221534311],"type":"Point"}
}