{
  "type": "Feature",
  "properties": {
    "iso:country": "GB",
    "wof:name": "DH2 3JQ",
    "wof:placetype": "postalcode"
  },
  "geometry": {"coordinates":[-1.594785,54.845852],"type":"Point"}
}
