{
  "type": "Feature",
  "properties": {
    "date:inception_lower": "1986-07-01",
    "date:inception_upper": "1986-07-01",
    "iso:country": "GB",
    "wof:name": "BD7 3JG",
    "wof:placetype": "postalcode"
  },
  "geometry": {"coordinates":[-1.781073,53.786075],"type":"Point"}
}
