{
  "type": "Feature",
  "properties": {
    "iso:country":"GB",
    "wof:name":"BD7 3JG",
    "wof:placetype":"postalcode"
},
  "geometry": {"coordinates":[-1.78107326307641,53.78607494881057],"type":"Point"}
}