{
  "type": "Feature",
  "properties": {
    "iso:country": "GB",
    "wof:name": "CT7 9JH",
    "wof:placetype": "postalcode"
  },
  "geometry": {"coordinates":[1.298699,51.379384],"type":"Point"}
}
