{
  "type": "Feature",
  "properties": {
    "iso:country":"GB",
    "wof:name":"CT7 9JH",
    "wof:placetype":"postalcode"
},
  "geometry": {"coordinates":[1.29869884143057,51.37938419700536],"type":"Point"}
}