{
  "type": "Feature",
  "properties": {
    "iso:country": "GB",
    "wof:name": "SE3 7QQ",
    "wof:placetype": "postalcode"
  },
  "geometry": {"coordinates":[0.008323,51.477234],"type":"Point"}
}
