{
  "type": "Feature",
  "properties": {
    "iso:country": "GB",
    "wof:name": "LE12 9NY",
    "wof:placetype": "postalcode"
  },
  "geometry": {"coordinates":[-1.294773,52.769441],"type":"Point"}
}
