{
  "type": "Feature",
  "properties": {
    "date:inception_lower": "2005-07-01",
    "date:inception_upper": "2005-07-01",
    "iso:country": "GB",
    "wof:name": "LE12 9NY",
    "wof:placetype": "postalcode"
  },
  "geometry": {"coordinates":[-1.294773,52.769441],"type":"Point"}
}
