{
  "type": "Feature",
  "properties": {
    "iso:country":"GB",
    "wof:name":"LE12 9NY",
    "wof:placetype":"postalcode"
},
  "geometry": {"coordinates":[-1.29477308774233,52.7694409490712],"type":"Point"}
}