{
  "type": "Feature",
  "properties": {
    "iso:country":"GB",
    "wof:name":"BD9 5QE",
    "wof:placetype":"postalcode"
},
  "geometry": {"coordinates":[-1.78505297229447,53.81220118701094],"type":"Point"}
}