{
  "type": "Feature",
  "properties": {
    "iso:country":"GB",
    "wof:name":"BR2 7BX",
    "wof:placetype":"postalcode"
},
  "geometry": {"coordinates":[0.01665759123755,51.37586757255778],"type":"Point"}
}