{
  "type": "Feature",
  "properties": {
    "iso:country": "GB",
    "wof:name": "AL7 2DU",
    "wof:placetype": "postalcode"
  },
  "geometry": {"coordinates":[-0.173918,51.806058],"type":"Point"}
}
