{
  "type": "Feature",
  "properties": {
    "iso:country": "GB",
    "wof:name": "G72 9SW",
    "wof:placetype": "postalcode"
  },
  "geometry": {"coordinates":[-4.106948,55.788814],"type":"Point"}
}
