{
  "type": "Feature",
  "properties": {
    "iso:country":"GB",
    "wof:name":"BL6 7QT",
    "wof:placetype":"postalcode"
},
  "geometry": {"coordinates":[-2.56079836674451,53.596595112282],"type":"Point"}
}