{
  "type": "Feature",
  "properties": {
    "date:inception_lower": "2021-09-01",
    "date:inception_upper": "2021-09-01",
    "iso:country": "GB",
    "wof:name": "PE11 9HB",
    "wof:placetype": "postalcode"
  },
  "geometry": {"coordinates":[-0.147531,52.803821],"type":"Point"}
}
