{
  "type": "Feature",
  "properties": {
    "iso:country":"GB",
    "wof:name":"SW7 5LZ",
    "wof:placetype":"postalcode"
},
  "geometry": {"coordinates":[-0.18198396286834,51.49712788342976],"type":"Point"}
}