{
  "type": "Feature",
  "properties": {
    "iso:country":"GB",
    "wof:name":"IV11 8XS",
    "wof:placetype":"postalcode"
},
  "geometry": {"coordinates":[-4.02360586567791,57.67114932845001],"type":"Point"}
}