{
  "type": "Feature",
  "properties": {
    "iso:country":"GB",
    "wof:name":"AB22 8XY",
    "wof:placetype":"postalcode"
},
  "geometry": {"coordinates":[-2.13089800768883,57.17813187728734],"type":"Point"}
}