{
  "type": "Feature",
  "properties": {
    "date:inception_lower": "1991-03-01",
    "date:inception_upper": "1991-03-01",
    "iso:country": "GB",
    "wof:name": "AB22 8XY",
    "wof:placetype": "postalcode"
  },
  "geometry": {"coordinates":[-2.130898,57.178132],"type":"Point"}
}
