{
  "type": "Feature",
  "properties": {
    "iso:country":"GB",
    "wof:name":"PR1 9BE",
    "wof:placetype":"postalcode"
},
  "geometry": {"coordinates":[-2.71549256725415,53.73684215415086],"type":"Point"}
}