{
  "type": "Feature",
  "properties": {
    "date:inception_lower": "2023-04-01",
    "date:inception_upper": "2023-04-01",
    "iso:country": "GB",
    "wof:name": "YO7 4FB",
    "wof:placetype": "postalcode"
  },
  "geometry": {"coordinates":[-1.472731,54.243953],"type":"Point"}
}
