{
  "type": "Feature",
  "properties": {
    "iso:country": "GB",
    "wof:name": "EX34 9EB",
    "wof:placetype": "postalcode"
  },
  "geometry": {"coordinates":[-4.117981,51.209865],"type":"Point"}
}
