{
  "type": "Feature",
  "properties": {
    "iso:country":"GB",
    "wof:name":"EX16 8QD",
    "wof:placetype":"postalcode"
},
  "geometry": {"coordinates":[-3.68767080247653,50.92482762808289],"type":"Point"}
}