{
  "type": "Feature",
  "properties": {
    "iso:country":"GB",
    "wof:name":"IP11 2LD",
    "wof:placetype":"postalcode"
},
  "geometry": {"coordinates":[1.33010382760323,51.96309675647326],"type":"Point"}
}