{
  "type": "Feature",
  "properties": {
    "iso:country":"GB",
    "wof:name":"M25 0GY",
    "wof:placetype":"postalcode"
},
  "geometry": {"coordinates":[-2.25497841971956,53.52610000199299],"type":"Point"}
}