{
  "type": "Feature",
  "properties": {
    "iso:country": "GB",
    "wof:name": "NR16 1EL",
    "wof:placetype": "postalcode"
  },
  "geometry": {"coordinates":[1.180286,52.530873],"type":"Point"}
}
