{
  "type": "Feature",
  "properties": {
    "iso:country":"GB",
    "wof:name":"NR16 1EL",
    "wof:placetype":"postalcode"
},
  "geometry": {"coordinates":[1.1802858825823,52.53087312389596],"type":"Point"}
}