{
  "type": "Feature",
  "properties": {
    "date:inception_lower": "1981-06-01",
    "date:inception_upper": "1981-06-01",
    "iso:country": "GB",
    "wof:name": "RH11 9JE",
    "wof:placetype": "postalcode"
  },
  "geometry": {"coordinates":[-0.206559,51.094155],"type":"Point"}
}
