{
  "type": "Feature",
  "properties": {
    "iso:country":"GB",
    "wof:name":"RH11 9JE",
    "wof:placetype":"postalcode"
},
  "geometry": {"coordinates":[-0.20655898385765,51.09415510622561],"type":"Point"}
}