{
  "type": "Feature",
  "properties": {
    "iso:country": "GB",
    "wof:name": "RH11 9JE",
    "wof:placetype": "postalcode"
  },
  "geometry": {"coordinates":[-0.206559,51.094155],"type":"Point"}
}
