{
  "type": "Feature",
  "properties": {
    "iso:country": "GB",
    "wof:name": "L11 1AU",
    "wof:placetype": "postalcode"
  },
  "geometry": {"coordinates":[-2.926432,53.439231],"type":"Point"}
}
