{
  "type": "Feature",
  "properties": {
    "iso:country":"GB",
    "wof:name":"BH21 7HJ",
    "wof:placetype":"postalcode"
},
  "geometry": {"coordinates":[-1.97608851803812,50.86913315285683],"type":"Point"}
}