{
  "type": "Feature",
  "properties": {
    "date:inception_lower": "2005-05-01",
    "date:inception_upper": "2005-05-01",
    "iso:country": "GB",
    "wof:name": "PR7 1AP",
    "wof:placetype": "postalcode"
  },
  "geometry": {"coordinates":[-2.644736,53.661266],"type":"Point"}
}
