{
  "type": "Feature",
  "properties": {
    "iso:country":"GB",
    "wof:name":"TW3 3SU",
    "wof:placetype":"postalcode"
},
  "geometry": {"coordinates":[-0.37345092536041,51.46145252716373],"type":"Point"}
}