{
  "type": "Feature",
  "properties": {
    "iso:country": "GB",
    "wof:name": "TW3 3SU",
    "wof:placetype": "postalcode"
  },
  "geometry": {"coordinates":[-0.373451,51.461453],"type":"Point"}
}
