{
  "type": "Feature",
  "properties": {
    "iso:country":"GB",
    "wof:name":"PR6 0JW",
    "wof:placetype":"postalcode"
},
  "geometry": {"coordinates":[-2.6177488854409,53.66296325860849],"type":"Point"}
}