{
  "type": "Feature",
  "properties": {
    "date:inception_lower": "1981-09-01",
    "date:inception_upper": "1981-09-01",
    "iso:country": "GB",
    "wof:name": "SN7 8JA",
    "wof:placetype": "postalcode"
  },
  "geometry": {"coordinates":[-1.511701,51.641114],"type":"Point"}
}
