{
  "type": "Feature",
  "properties": {
    "iso:country":"GB",
    "wof:name":"SN7 8JA",
    "wof:placetype":"postalcode"
},
  "geometry": {"coordinates":[-1.51170071964,51.64111412881309],"type":"Point"}
}