{
  "type": "Feature",
  "properties": {
    "iso:country": "GB",
    "wof:name": "SN7 8JA",
    "wof:placetype": "postalcode"
  },
  "geometry": {"coordinates":[-1.511701,51.641114],"type":"Point"}
}
