{
  "type": "Feature",
  "properties": {
    "date:inception_lower": "1981-09-01",
    "date:inception_upper": "1981-09-01",
    "iso:country": "GB",
    "wof:name": "SY4 5DF",
    "wof:placetype": "postalcode"
  },
  "geometry": {"coordinates":[-2.717221,52.859672],"type":"Point"}
}
