{
  "type": "Feature",
  "properties": {
    "iso:country":"GB",
    "wof:name":"LN6 5UT",
    "wof:placetype":"postalcode"
},
  "geometry": {"coordinates":[-0.61381058579915,53.23468077350504],"type":"Point"}
}