{
  "type": "Feature",
  "properties": {
    "date:inception_lower": "1983-01-01",
    "date:inception_upper": "1983-01-01",
    "iso:country": "GB",
    "wof:name": "LN6 5UT",
    "wof:placetype": "postalcode"
  },
  "geometry": {"coordinates":[-0.613811,53.234681],"type":"Point"}
}
