{
  "type": "Feature",
  "properties": {
    "iso:country": "GB",
    "wof:name": "B92 0JY",
    "wof:placetype": "postalcode"
  },
  "geometry": {"coordinates":[-1.694857,52.399969],"type":"Point"}
}
