{
  "type": "Feature",
  "properties": {
    "iso:country": "GB",
    "wof:name": "CH5 2JU",
    "wof:placetype": "postalcode"
  },
  "geometry": {"coordinates":[-3.003853,53.214694],"type":"Point"}
}
