{
  "type": "Feature",
  "properties": {
    "iso:country": "GB",
    "wof:name": "CF48 4LL",
    "wof:placetype": "postalcode"
  },
  "geometry": {"coordinates":[-3.340724,51.706585],"type":"Point"}
}
