{
  "type": "Feature",
  "properties": {
    "iso:country":"GB",
    "wof:name":"CF48 4LL",
    "wof:placetype":"postalcode"
},
  "geometry": {"coordinates":[-3.34072358798219,51.70658506618122],"type":"Point"}
}