{
  "type": "Feature",
  "properties": {
    "iso:country":"GB",
    "wof:name":"PL25 3TG",
    "wof:placetype":"postalcode"
},
  "geometry": {"coordinates":[-4.74828593144564,50.34992097903792],"type":"Point"}
}