{
  "type": "Feature",
  "properties": {
    "iso:country": "GB",
    "wof:name": "G74 4TU",
    "wof:placetype": "postalcode"
  },
  "geometry": {"coordinates":[-4.192527,55.768147],"type":"Point"}
}
