{
  "type": "Feature",
  "properties": {
    "date:inception_lower": "1981-09-01",
    "date:inception_upper": "1981-09-01",
    "iso:country": "GB",
    "wof:name": "PE31 6JU",
    "wof:placetype": "postalcode"
  },
  "geometry": {"coordinates":[0.508201,52.845294],"type":"Point"}
}
