{
  "type": "Feature",
  "properties": {
    "iso:country":"GB",
    "wof:name":"PE31 6JU",
    "wof:placetype":"postalcode"
},
  "geometry": {"coordinates":[0.50820141426376,52.84529414824521],"type":"Point"}
}