{
  "type": "Feature",
  "properties": {
    "iso:country": "GB",
    "wof:name": "OL14 8RA",
    "wof:placetype": "postalcode"
  },
  "geometry": {"coordinates":[-2.087003,53.71894],"type":"Point"}
}
