{
  "type": "Feature",
  "properties": {
    "iso:country":"GB",
    "wof:name":"OL14 8RA",
    "wof:placetype":"postalcode"
},
  "geometry": {"coordinates":[-2.08700315697451,53.71894021317355],"type":"Point"}
}