{
  "type": "Feature",
  "properties": {
    "iso:country":"GB",
    "wof:name":"LE2 6FF",
    "wof:placetype":"postalcode"
},
  "geometry": {"coordinates":[-1.12455522363706,52.60827788005318],"type":"Point"}
}