{
  "type": "Feature",
  "properties": {
    "iso:country":"GB",
    "wof:name":"BD22 0DY",
    "wof:placetype":"postalcode"
},
  "geometry": {"coordinates":[-1.94239502047808,53.84155435894446],"type":"Point"}
}