{
  "type": "Feature",
  "properties": {
    "date:inception_lower":"2007-03-01",
    "date:inception_upper":"2007-03-31",
    "iso:country":"GB",
    "wof:name":"WA10 3QY",
    "wof:placetype":"postalcode"
},
  "geometry": {"coordinates":[-2.745072,53.449381],"type":"Point"}
}