{
  "type": "Feature",
  "properties": {
    "iso:country": "GB",
    "wof:name": "WA10 3QY",
    "wof:placetype": "postalcode"
  },
  "geometry": {"coordinates":[-2.745072,53.449381],"type":"Point"}
}
