{
  "type": "Feature",
  "properties": {
    "date:inception_lower":"1980-01-01",
    "date:inception_upper":"1980-01-31",
    "iso:country":"GB",
    "wof:name":"PE15 8JE",
    "wof:placetype":"postalcode"
},
  "geometry": {"coordinates":[0.083568,52.558282],"type":"Point"}
}