{
  "type": "Feature",
  "properties": {
    "iso:country":"GB",
    "wof:name":"GL7 2JA",
    "wof:placetype":"postalcode"
},
  "geometry": {"coordinates":[-1.97387599697755,51.72928582879831],"type":"Point"}
}