{
  "type": "Feature",
  "properties": {
    "iso:country": "GB",
    "wof:name": "DL14 7QS",
    "wof:placetype": "postalcode"
  },
  "geometry": {"coordinates":[-1.683038,54.662384],"type":"Point"}
}
