{
  "type": "Feature",
  "properties": {
    "iso:country":"GB",
    "wof:name":"DL14 7QS",
    "wof:placetype":"postalcode"
},
  "geometry": {"coordinates":[-1.68303771492321,54.66238410127107],"type":"Point"}
}