{
  "type": "Feature",
  "properties": {
    "iso:country": "GB",
    "wof:name": "WA10 6DD",
    "wof:placetype": "postalcode"
  },
  "geometry": {"coordinates":[-2.763851,53.465451],"type":"Point"}
}
