{
  "type": "Feature",
  "properties": {
    "iso:country":"GB",
    "wof:name":"WA10 6DD",
    "wof:placetype":"postalcode"
},
  "geometry": {"coordinates":[-2.76385141747323,53.46545077413582],"type":"Point"}
}