{
  "type": "Feature",
  "properties": {
    "iso:country":"GB",
    "wof:name":"ST7 8DZ",
    "wof:placetype":"postalcode"
},
  "geometry": {"coordinates":[-2.30148868901308,53.05416271952863],"type":"Point"}
}