{
  "type": "Feature",
  "properties": {
    "iso:country":"GB",
    "wof:name":"SE7 7EF",
    "wof:placetype":"postalcode"
},
  "geometry": {"coordinates":[0.03678292831546,51.47763305341018],"type":"Point"}
}