{
  "type": "Feature",
  "properties": {
    "date:inception_lower": "1998-12-01",
    "date:inception_upper": "1998-12-01",
    "iso:country": "GB",
    "wof:name": "SE7 7EF",
    "wof:placetype": "postalcode"
  },
  "geometry": {"coordinates":[0.036783,51.477633],"type":"Point"}
}
