{
  "type": "Feature",
  "properties": {
    "iso:country":"GB",
    "wof:name":"LS2 9BW",
    "wof:placetype":"postalcode"
},
  "geometry": {"coordinates":[-1.55328133944114,53.80962104559522],"type":"Point"}
}