{
  "type": "Feature",
  "properties": {
    "iso:country": "GB",
    "wof:name": "G62 8AX",
    "wof:placetype": "postalcode"
  },
  "geometry": {"coordinates":[-4.311939,55.94863],"type":"Point"}
}
