{
  "type": "Feature",
  "properties": {
    "iso:country":"GB",
    "wof:name":"AB21 9AD",
    "wof:placetype":"postalcode"
},
  "geometry": {"coordinates":[-2.17082310970921,57.17753585436099],"type":"Point"}
}