{
  "type": "Feature",
  "properties": {
    "date:inception_lower": "1980-01-01",
    "date:inception_upper": "1980-01-01",
    "iso:country": "GB",
    "wof:name": "SN4 7EN",
    "wof:placetype": "postalcode"
  },
  "geometry": {"coordinates":[-1.898329,51.533172],"type":"Point"}
}
