{
  "type": "Feature",
  "properties": {
    "iso:country":"GB",
    "wof:name":"SN4 7EN",
    "wof:placetype":"postalcode"
},
  "geometry": {"coordinates":[-1.89832881718659,51.53317241679071],"type":"Point"}
}