{
  "type": "Feature",
  "properties": {
    "iso:country":"GB",
    "wof:name":"BH20 4EZ",
    "wof:placetype":"postalcode"
},
  "geometry": {"coordinates":[-2.11820376258128,50.6978477772394],"type":"Point"}
}