{
  "type": "Feature",
  "properties": {
    "iso:country": "GB",
    "wof:name": "CA7 9JQ",
    "wof:placetype": "postalcode"
  },
  "geometry": {"coordinates":[-3.148971,54.828876],"type":"Point"}
}
