{
  "type": "Feature",
  "properties": {
    "date:inception_lower": "1980-01-01",
    "date:inception_upper": "1980-01-01",
    "iso:country": "GB",
    "wof:name": "CA7 9JQ",
    "wof:placetype": "postalcode"
  },
  "geometry": {"coordinates":[-3.148971,54.828876],"type":"Point"}
}
