{
  "type": "Feature",
  "properties": {
    "iso:country":"GB",
    "wof:name":"DL3 0ZL",
    "wof:placetype":"postalcode"
},
  "geometry": {"coordinates":[-1.55304271276035,54.55415059978979],"type":"Point"}
}