{
  "type": "Feature",
  "properties": {
    "iso:country": "GB",
    "wof:name": "SL2 5SY",
    "wof:placetype": "postalcode"
  },
  "geometry": {"coordinates":[-0.578724,51.521724],"type":"Point"}
}
