{
  "type": "Feature",
  "properties": {
    "iso:country":"GB",
    "wof:name":"SL2 5SY",
    "wof:placetype":"postalcode"
},
  "geometry": {"coordinates":[-0.57872421827192,51.52172367316495],"type":"Point"}
}