{
  "type": "Feature",
  "properties": {
    "date:inception_lower": "1980-01-01",
    "date:inception_upper": "1980-01-01",
    "iso:country": "GB",
    "wof:name": "LS24 9EJ",
    "wof:placetype": "postalcode"
  },
  "geometry": {"coordinates":[-1.169991,53.831365],"type":"Point"}
}
