{
  "type": "Feature",
  "properties": {
    "iso:country":"GB",
    "wof:name":"TS13 4QY",
    "wof:placetype":"postalcode"
},
  "geometry": {"coordinates":[-0.90185955391444,54.55229474710645],"type":"Point"}
}