{
  "type": "Feature",
  "properties": {
    "iso:country": "GB",
    "wof:name": "SA10 6PF",
    "wof:placetype": "postalcode"
  },
  "geometry": {"coordinates":[-3.838434,51.666227],"type":"Point"}
}
