{
  "type": "Feature",
  "properties": {
    "iso:country":"GB",
    "wof:name":"SA10 6PF",
    "wof:placetype":"postalcode"
},
  "geometry": {"coordinates":[-3.83843400622002,51.66622686743928],"type":"Point"}
}