{
  "type": "Feature",
  "properties": {
    "iso:country":"GB",
    "wof:name":"AB51 0QG",
    "wof:placetype":"postalcode"
},
  "geometry": {"coordinates":[-2.34389215116846,57.22152976566665],"type":"Point"}
}