{
  "type": "Feature",
  "properties": {
    "iso:country": "GB",
    "wof:name": "AB51 0QG",
    "wof:placetype": "postalcode"
  },
  "geometry": {"coordinates":[-2.346263,57.221356],"type":"Point"}
}
