{
  "type": "Feature",
  "properties": {
    "iso:country":"GB",
    "wof:name":"YO13 0BS",
    "wof:placetype":"postalcode"
},
  "geometry": {"coordinates":[-0.5702212449379,54.29585651109152],"type":"Point"}
}