{
  "type": "Feature",
  "properties": {
    "iso:country": "GB",
    "wof:name": "YO13 0BS",
    "wof:placetype": "postalcode"
  },
  "geometry": {"coordinates":[-0.570221,54.295857],"type":"Point"}
}
