{
  "type": "Feature",
  "properties": {
    "iso:country":"GB",
    "wof:name":"EH39 4AG",
    "wof:placetype":"postalcode"
},
  "geometry": {"coordinates":[-2.72595509239503,56.0578176903259],"type":"Point"}
}