{
  "type": "Feature",
  "properties": {
    "date:inception_lower": "1980-01-01",
    "date:inception_upper": "1980-01-01",
    "iso:country": "GB",
    "wof:name": "W11 4TD",
    "wof:placetype": "postalcode"
  },
  "geometry": {"coordinates":[-0.216362,51.508114],"type":"Point"}
}
