{
  "type": "Feature",
  "properties": {
    "iso:country":"GB",
    "wof:name":"DD1 4AU",
    "wof:placetype":"postalcode"
},
  "geometry": {"coordinates":[-2.96916578927049,56.45925867813308],"type":"Point"}
}