{
  "type": "Feature",
  "properties": {
    "iso:country":"GB",
    "wof:name":"WC2N 5RD",
    "wof:placetype":"postalcode"
},
  "geometry": {"coordinates":[-0.12564185269654,51.50758050385567],"type":"Point"}
}