{
  "type": "Feature",
  "properties": {
    "iso:country": "GB",
    "wof:name": "RG4 8PN",
    "wof:placetype": "postalcode"
  },
  "geometry": {"coordinates":[-0.974921,51.477137],"type":"Point"}
}
