{
  "type": "Feature",
  "properties": {
    "iso:country":"GB",
    "wof:name":"RG4 8PN",
    "wof:placetype":"postalcode"
},
  "geometry": {"coordinates":[-0.9749210288914,51.47713657263011],"type":"Point"}
}