{
  "type": "Feature",
  "properties": {
    "iso:country": "GB",
    "wof:name": "CA4 8FL",
    "wof:placetype": "postalcode"
  },
  "geometry": {"coordinates":[-2.854447,54.868482],"type":"Point"}
}
