{
  "type": "Feature",
  "properties": {
    "iso:country": "GB",
    "wof:name": "PR2 3BZ",
    "wof:placetype": "postalcode"
  },
  "geometry": {"coordinates":[-2.712732,53.774535],"type":"Point"}
}
