{
  "type": "Feature",
  "properties": {
    "iso:country":"GB",
    "wof:name":"SY11 2YS",
    "wof:placetype":"postalcode"
},
  "geometry": {"coordinates":[-3.03091127297085,52.85892120829395],"type":"Point"}
}