{
  "type": "Feature",
  "properties": {
    "iso:country":"GB",
    "wof:name":"NP19 4XE",
    "wof:placetype":"postalcode"
},
  "geometry": {"coordinates":[-2.96279598426446,51.55802798582827],"type":"Point"}
}