{
  "type": "Feature",
  "properties": {
    "date:inception_lower": "1980-01-01",
    "date:inception_upper": "1980-01-01",
    "iso:country": "GB",
    "wof:name": "ML11 8QE",
    "wof:placetype": "postalcode"
  },
  "geometry": {"coordinates":[-3.690946,55.694934],"type":"Point"}
}
