{
  "type": "Feature",
  "properties": {
    "iso:country": "GB",
    "wof:name": "ML11 8QE",
    "wof:placetype": "postalcode"
  },
  "geometry": {"coordinates":[-3.690946,55.694934],"type":"Point"}
}
