{
  "type": "Feature",
  "properties": {
    "date:inception_lower": "1982-03-01",
    "date:inception_upper": "1982-03-01",
    "iso:country": "GB",
    "wof:name": "SR8 1NQ",
    "wof:placetype": "postalcode"
  },
  "geometry": {"coordinates":[-1.351509,54.746528],"type":"Point"}
}
