{
  "type": "Feature",
  "properties": {
    "iso:country":"GB",
    "wof:name":"CW5 6EG",
    "wof:placetype":"postalcode"
},
  "geometry": {"coordinates":[-2.5026785208686,53.14038014222202],"type":"Point"}
}