{
  "type": "Feature",
  "properties": {
    "iso:country": "GB",
    "wof:name": "CW5 6EG",
    "wof:placetype": "postalcode"
  },
  "geometry": {"coordinates":[-2.502678,53.14038],"type":"Point"}
}
