{
  "type": "Feature",
  "properties": {
    "iso:country": "GB",
    "wof:name": "TA6 4HG",
    "wof:placetype": "postalcode"
  },
  "geometry": {"coordinates":[-2.980443,51.13855],"type":"Point"}
}
