{
  "type": "Feature",
  "properties": {
    "iso:country":"GB",
    "wof:name":"TA6 4HG",
    "wof:placetype":"postalcode"
},
  "geometry": {"coordinates":[-2.98044283715344,51.13854953056389],"type":"Point"}
}