{
  "type": "Feature",
  "properties": {
    "iso:country": "GB",
    "wof:name": "DT5 2BH",
    "wof:placetype": "postalcode"
  },
  "geometry": {"coordinates":[-2.440372,50.545896],"type":"Point"}
}
