{
  "type": "Feature",
  "properties": {
    "iso:country":"GB",
    "wof:name":"DT5 2BH",
    "wof:placetype":"postalcode"
},
  "geometry": {"coordinates":[-2.44037231157849,50.54589599575779],"type":"Point"}
}