{
  "type": "Feature",
  "properties": {
    "iso:country":"GB",
    "wof:name":"WS14 9LT",
    "wof:placetype":"postalcode"
},
  "geometry": {"coordinates":[-1.76042011413279,52.67320834805296],"type":"Point"}
}