{
  "type": "Feature",
  "properties": {
    "iso:country": "GB",
    "wof:name": "WS14 9LT",
    "wof:placetype": "postalcode"
  },
  "geometry": {"coordinates":[-1.760132,52.673162],"type":"Point"}
}
