{
  "type": "Feature",
  "properties": {
    "iso:country": "GB",
    "wof:name": "CM5 9HY",
    "wof:placetype": "postalcode"
  },
  "geometry": {"coordinates":[0.24673,51.70416],"type":"Point"}
}
