{
  "type": "Feature",
  "properties": {
    "iso:country":"GB",
    "wof:name":"CM5 9HY",
    "wof:placetype":"postalcode"
},
  "geometry": {"coordinates":[0.24673019738694,51.70415966586607],"type":"Point"}
}