{
  "type": "Feature",
  "properties": {
    "date:inception_lower": "1982-03-01",
    "date:inception_upper": "1982-03-01",
    "iso:country": "GB",
    "wof:name": "NG15 6TD",
    "wof:placetype": "postalcode"
  },
  "geometry": {"coordinates":[-1.232271,53.033418],"type":"Point"}
}
