{
  "type": "Feature",
  "properties": {
    "iso:country":"GB",
    "wof:name":"CR0 9DZ",
    "wof:placetype":"postalcode"
},
  "geometry": {"coordinates":[-0.0202210608539,51.35470692961675],"type":"Point"}
}