{
  "type": "Feature",
  "properties": {
    "date:inception_lower": "1998-12-01",
    "date:inception_upper": "1998-12-01",
    "iso:country": "GB",
    "wof:name": "EX24 6NX",
    "wof:placetype": "postalcode"
  },
  "geometry": {"coordinates":[-3.073793,50.739355],"type":"Point"}
}
