{
  "type": "Feature",
  "properties": {
    "iso:country":"GB",
    "wof:name":"TS23 3AL",
    "wof:placetype":"postalcode"
},
  "geometry": {"coordinates":[-1.28142999067247,54.6086972466256],"type":"Point"}
}