{
  "type": "Feature",
  "properties": {
    "iso:country":"GB",
    "wof:name":"PL9 9JD",
    "wof:placetype":"postalcode"
},
  "geometry": {"coordinates":[-4.08672882420541,50.35074787705408],"type":"Point"}
}