{
  "type": "Feature",
  "properties": {
    "iso:country": "GB",
    "wof:name": "PE11 3WY",
    "wof:placetype": "postalcode"
  },
  "geometry": {"coordinates":[-0.174382,52.78921],"type":"Point"}
}
