{
  "type": "Feature",
  "properties": {
    "iso:country":"GB",
    "wof:name":"PE11 3WY",
    "wof:placetype":"postalcode"
},
  "geometry": {"coordinates":[-0.17438160497792,52.78921021752178],"type":"Point"}
}