{
  "type": "Feature",
  "properties": {
    "date:inception_lower": "1980-01-01",
    "date:inception_upper": "1980-01-01",
    "iso:country": "GB",
    "wof:name": "CO15 1RR",
    "wof:placetype": "postalcode"
  },
  "geometry": {"coordinates":[1.153083,51.79035],"type":"Point"}
}
