{
  "type": "Feature",
  "properties": {
    "iso:country":"GB",
    "wof:name":"PE24 5BW",
    "wof:placetype":"postalcode"
},
  "geometry": {"coordinates":[0.23654081986105,53.15876646505745],"type":"Point"}
}