{
  "type": "Feature",
  "properties": {
    "date:inception_lower": "1992-08-01",
    "date:inception_upper": "1992-08-01",
    "iso:country": "GB",
    "wof:name": "TS21 2JS",
    "wof:placetype": "postalcode"
  },
  "geometry": {"coordinates":[-1.454726,54.651336],"type":"Point"}
}
