{
  "type": "Feature",
  "properties": {
    "iso:country":"GB",
    "wof:name":"TS21 2JS",
    "wof:placetype":"postalcode"
},
  "geometry": {"coordinates":[-1.45472563533528,54.65133621874941],"type":"Point"}
}