{
  "type": "Feature",
  "properties": {
    "iso:country":"GB",
    "wof:name":"KT6 6AD",
    "wof:placetype":"postalcode"
},
  "geometry": {"coordinates":[-0.29824632269797,51.39377800731992],"type":"Point"}
}