{
  "type": "Feature",
  "properties": {
    "iso:country":"GB",
    "wof:name":"LL28 5YT",
    "wof:placetype":"postalcode"
},
  "geometry": {"coordinates":[-3.74604110561181,53.27630612789788],"type":"Point"}
}