{
  "type": "Feature",
  "properties": {
    "iso:country":"GB",
    "wof:name":"SK9 2AJ",
    "wof:placetype":"postalcode"
},
  "geometry": {"coordinates":[-2.2154899078863,53.32447500300619],"type":"Point"}
}