{
  "type": "Feature",
  "properties": {
    "iso:country": "GB",
    "wof:name": "PE15 8FE",
    "wof:placetype": "postalcode"
  },
  "geometry": {"coordinates":[0.076373,52.553059],"type":"Point"}
}
