{
  "type": "Feature",
  "properties": {
    "iso:country": "GB",
    "wof:name": "PE21 9ET",
    "wof:placetype": "postalcode"
  },
  "geometry": {"coordinates":[-0.02932,52.986593],"type":"Point"}
}
