{
  "type": "Feature",
  "properties": {
    "date:inception_lower": "2020-10-01",
    "date:inception_upper": "2020-10-01",
    "iso:country": "GB",
    "wof:name": "WN7 5FS",
    "wof:placetype": "postalcode"
  },
  "geometry": {"coordinates":[-2.529823,53.501214],"type":"Point"}
}
