{
  "type": "Feature",
  "properties": {
    "iso:country":"GB",
    "wof:name":"DN32 9RS",
    "wof:placetype":"postalcode"
},
  "geometry": {"coordinates":[-0.07447855627763,53.55317550007199],"type":"Point"}
}