{
  "type": "Feature",
  "properties": {
    "date:inception_lower": "1980-01-01",
    "date:inception_upper": "1980-01-01",
    "iso:country": "GB",
    "wof:name": "KY15 5EW",
    "wof:placetype": "postalcode"
  },
  "geometry": {"coordinates":[-3.018085,56.315166],"type":"Point"}
}
