{
  "type": "Feature",
  "properties": {
    "iso:country":"GB",
    "wof:name":"ST14 5EN",
    "wof:placetype":"postalcode"
},
  "geometry": {"coordinates":[-1.91990711556384,52.92288994929087],"type":"Point"}
}