{
  "type": "Feature",
  "properties": {
    "date:inception_lower": "1980-01-01",
    "date:inception_upper": "1980-01-01",
    "iso:country": "GB",
    "wof:name": "ST14 5EN",
    "wof:placetype": "postalcode"
  },
  "geometry": {"coordinates":[-1.920901,52.922737],"type":"Point"}
}
