{
  "type": "Feature",
  "properties": {
    "iso:country":"GB",
    "wof:name":"RM9 5PB",
    "wof:placetype":"postalcode"
},
  "geometry": {"coordinates":[0.14443854085417,51.5440501240592],"type":"Point"}
}