{
  "type": "Feature",
  "properties": {
    "iso:country": "GB",
    "wof:name": "DY10 1PY",
    "wof:placetype": "postalcode"
  },
  "geometry": {"coordinates":[-2.242699,52.386603],"type":"Point"}
}
