{
  "type": "Feature",
  "properties": {
    "iso:country":"GB",
    "wof:name":"DE5 8JS",
    "wof:placetype":"postalcode"
},
  "geometry": {"coordinates":[-1.42856623678927,53.01166211351626],"type":"Point"}
}