{
  "type": "Feature",
  "properties": {
    "iso:country": "GB",
    "wof:name": "DE5 8JS",
    "wof:placetype": "postalcode"
  },
  "geometry": {"coordinates":[-1.428566,53.011662],"type":"Point"}
}
