{
  "type": "Feature",
  "properties": {
    "iso:country":"GB",
    "wof:name":"IV4 7AS",
    "wof:placetype":"postalcode"
},
  "geometry": {"coordinates":[-4.45479187392253,57.49826393845747],"type":"Point"}
}