{
  "type": "Feature",
  "properties": {
    "date:inception_lower": "2002-12-01",
    "date:inception_upper": "2002-12-01",
    "iso:country": "GB",
    "wof:name": "IV4 7AS",
    "wof:placetype": "postalcode"
  },
  "geometry": {"coordinates":[-4.454792,57.498264],"type":"Point"}
}
