{
  "type": "Feature",
  "properties": {
    "iso:country": "GB",
    "wof:name": "IV4 7AS",
    "wof:placetype": "postalcode"
  },
  "geometry": {"coordinates":[-4.454792,57.498264],"type":"Point"}
}
