{
  "type": "Feature",
  "properties": {
    "iso:country":"GB",
    "wof:name":"SK14 5LX",
    "wof:placetype":"postalcode"
},
  "geometry": {"coordinates":[-2.06469226128261,53.43965234930293],"type":"Point"}
}