{
  "type": "Feature",
  "properties": {
    "iso:country": "GB",
    "wof:name": "DH2 3SZ",
    "wof:placetype": "postalcode"
  },
  "geometry": {"coordinates":[-1.598014,54.846896],"type":"Point"}
}
