{
  "type": "Feature",
  "properties": {
    "date:inception_lower": "1993-01-01",
    "date:inception_upper": "1993-01-01",
    "iso:country": "GB",
    "wof:name": "DH2 3SZ",
    "wof:placetype": "postalcode"
  },
  "geometry": {"coordinates":[-1.598014,54.846896],"type":"Point"}
}
