{
  "type": "Feature",
  "properties": {
    "iso:country":"GB",
    "wof:name":"DH2 3SZ",
    "wof:placetype":"postalcode"
},
  "geometry": {"coordinates":[-1.59801356144987,54.84689638191954],"type":"Point"}
}