{
  "type": "Feature",
  "properties": {
    "iso:country":"GB",
    "wof:name":"EH8 9LH",
    "wof:placetype":"postalcode"
},
  "geometry": {"coordinates":[-3.18817666011138,55.94288521775054],"type":"Point"}
}