{
  "type": "Feature",
  "properties": {
    "iso:country":"GB",
    "wof:name":"M19 1HS",
    "wof:placetype":"postalcode"
},
  "geometry": {"coordinates":[-2.19609860190073,53.43356722107703],"type":"Point"}
}