{
  "type": "Feature",
  "properties": {
    "date:inception_lower": "2006-09-01",
    "date:inception_upper": "2006-09-01",
    "iso:country": "GB",
    "wof:name": "CV23 9DZ",
    "wof:placetype": "postalcode"
  },
  "geometry": {"coordinates":[-1.298309,52.377768],"type":"Point"}
}
