{
  "type": "Feature",
  "properties": {
    "date:inception_lower": "1999-06-01",
    "date:inception_upper": "1999-06-01",
    "iso:country": "GB",
    "wof:name": "NP25 4LD",
    "wof:placetype": "postalcode"
  },
  "geometry": {"coordinates":[-2.674845,51.780366],"type":"Point"}
}
