{
  "type": "Feature",
  "properties": {
    "iso:country":"GB",
    "wof:name":"NP25 4LD",
    "wof:placetype":"postalcode"
},
  "geometry": {"coordinates":[-2.67485614865381,51.7803706984605],"type":"Point"}
}