{
  "type": "Feature",
  "properties": {
    "iso:country": "GB",
    "wof:name": "SY13 2QF",
    "wof:placetype": "postalcode"
  },
  "geometry": {"coordinates":[-2.766794,52.90903],"type":"Point"}
}
