{
  "type": "Feature",
  "properties": {
    "iso:country":"GB",
    "wof:name":"EX8 4DD",
    "wof:placetype":"postalcode"
},
  "geometry": {"coordinates":[-3.39197539103115,50.63136220734575],"type":"Point"}
}