{
  "type": "Feature",
  "properties": {
    "iso:country":"GB",
    "wof:name":"SE11 4AB",
    "wof:placetype":"postalcode"
},
  "geometry": {"coordinates":[-0.108879007251,51.48608895194435],"type":"Point"}
}