{
  "type": "Feature",
  "properties": {
    "date:inception_lower":"2003-07-01",
    "date:inception_upper":"2003-07-31",
    "iso:country":"GB",
    "wof:name":"SE11 4AB",
    "wof:placetype":"postalcode"
},
  "geometry": {"coordinates":[-0.108879,51.486098],"type":"Point"}
}