{
  "type": "Feature",
  "properties": {
    "iso:country":"GB",
    "wof:name":"W1G 7BD",
    "wof:placetype":"postalcode"
},
  "geometry": {"coordinates":[-0.14697871343328,51.52119248422015],"type":"Point"}
}