{
  "type": "Feature",
  "properties": {
    "iso:country": "GB",
    "wof:name": "PE11 3EE",
    "wof:placetype": "postalcode"
  },
  "geometry": {"coordinates":[-0.170327,52.780526],"type":"Point"}
}
