{
  "type": "Feature",
  "properties": {
    "date:inception_lower": "1990-07-01",
    "date:inception_upper": "1990-07-01",
    "iso:country": "GB",
    "wof:name": "PE11 3EE",
    "wof:placetype": "postalcode"
  },
  "geometry": {"coordinates":[-0.170327,52.780526],"type":"Point"}
}
