{
  "type": "Feature",
  "properties": {
    "iso:country":"GB",
    "wof:name":"PE11 3EE",
    "wof:placetype":"postalcode"
},
  "geometry": {"coordinates":[-0.17032655659458,52.78052565361806],"type":"Point"}
}