{
  "type": "Feature",
  "properties": {
    "iso:country": "GB",
    "wof:name": "TN39 4LJ",
    "wof:placetype": "postalcode"
  },
  "geometry": {"coordinates":[0.45145,50.854092],"type":"Point"}
}
