{
  "type": "Feature",
  "properties": {
    "iso:country": "GB",
    "wof:name": "LS16 7PF",
    "wof:placetype": "postalcode"
  },
  "geometry": {"coordinates":[-1.593823,53.857258],"type":"Point"}
}
