{
  "type": "Feature",
  "properties": {
    "iso:country":"GB",
    "wof:name":"BA6 9BY",
    "wof:placetype":"postalcode"
},
  "geometry": {"coordinates":[-2.71450821833125,51.15242769881905],"type":"Point"}
}