{
  "type": "Feature",
  "properties": {
    "iso:country": "GB",
    "wof:name": "BA6 9BY",
    "wof:placetype": "postalcode"
  },
  "geometry": {"coordinates":[-2.714508,51.152428],"type":"Point"}
}
