{
  "type": "Feature",
  "properties": {
    "iso:country": "GB",
    "wof:name": "CO10 7JQ",
    "wof:placetype": "postalcode"
  },
  "geometry": {"coordinates":[0.674277,52.070758],"type":"Point"}
}
