{
  "type": "Feature",
  "properties": {
    "iso:country":"GB",
    "wof:name":"CO10 7JQ",
    "wof:placetype":"postalcode"
},
  "geometry": {"coordinates":[0.67427666888737,52.07075767312392],"type":"Point"}
}