{
  "type": "Feature",
  "properties": {
    "iso:country":"GB",
    "wof:name":"MK12 5HG",
    "wof:placetype":"postalcode"
},
  "geometry": {"coordinates":[-0.80823880831136,52.05970347848594],"type":"Point"}
}