{
  "type": "Feature",
  "properties": {
    "iso:country":"GB",
    "wof:name":"IP18 6QR",
    "wof:placetype":"postalcode"
},
  "geometry": {"coordinates":[1.6718743791069,52.34017766516602],"type":"Point"}
}