{
  "type": "Feature",
  "properties": {
    "iso:country": "GB",
    "wof:name": "IP18 6QR",
    "wof:placetype": "postalcode"
  },
  "geometry": {"coordinates":[1.671874,52.340178],"type":"Point"}
}
