{
  "type": "Feature",
  "properties": {
    "iso:country":"GB",
    "wof:name":"MK43 7AU",
    "wof:placetype":"postalcode"
},
  "geometry": {"coordinates":[-0.59002727983106,52.20822065462885],"type":"Point"}
}