{
  "type": "Feature",
  "properties": {
    "iso:country":"GB",
    "wof:name":"RG9 5EA",
    "wof:placetype":"postalcode"
},
  "geometry": {"coordinates":[-0.99033023067574,51.55268406362011],"type":"Point"}
}