{
  "type": "Feature",
  "properties": {
    "date:inception_lower": "1980-01-01",
    "date:inception_upper": "1980-01-01",
    "iso:country": "GB",
    "wof:name": "DL15 0QB",
    "wof:placetype": "postalcode"
  },
  "geometry": {"coordinates":[-1.694171,54.70536],"type":"Point"}
}
