{
  "type": "Feature",
  "properties": {
    "iso:country":"GB",
    "wof:name":"DL15 0QB",
    "wof:placetype":"postalcode"
},
  "geometry": {"coordinates":[-1.69417137143841,54.70535997623613],"type":"Point"}
}