{
  "type": "Feature",
  "properties": {
    "date:inception_lower": "1999-06-01",
    "date:inception_upper": "1999-06-01",
    "iso:country": "GB",
    "wof:name": "CF14 1PF",
    "wof:placetype": "postalcode"
  },
  "geometry": {"coordinates":[-3.223241,51.508755],"type":"Point"}
}
