{
  "type": "Feature",
  "properties": {
    "iso:country":"GB",
    "wof:name":"CF14 1PF",
    "wof:placetype":"postalcode"
},
  "geometry": {"coordinates":[-3.22344549811247,51.5086706386162],"type":"Point"}
}