{
  "type": "Feature",
  "properties": {
    "iso:country": "GB",
    "wof:name": "CF14 1PF",
    "wof:placetype": "postalcode"
  },
  "geometry": {"coordinates":[-3.223455,51.508672],"type":"Point"}
}
