{
  "type": "Feature",
  "properties": {
    "date:inception_lower": "1999-06-01",
    "date:inception_upper": "1999-06-01",
    "iso:country": "GB",
    "wof:name": "CH66 3JG",
    "wof:placetype": "postalcode"
  },
  "geometry": {"coordinates":[-2.92472,53.277748],"type":"Point"}
}
