{
  "type": "Feature",
  "properties": {
    "date:inception_lower": "1995-01-01",
    "date:inception_upper": "1995-01-01",
    "iso:country": "GB",
    "wof:name": "PL4 8BP",
    "wof:placetype": "postalcode"
  },
  "geometry": {"coordinates":[-4.132849,50.373602],"type":"Point"}
}
