{
  "type": "Feature",
  "properties": {
    "iso:country":"GB",
    "wof:name":"PE30 2NF",
    "wof:placetype":"postalcode"
},
  "geometry": {"coordinates":[0.40995265985368,52.7665404670921],"type":"Point"}
}