{
  "type": "Feature",
  "properties": {
    "date:inception_lower":"2004-11-01",
    "date:inception_upper":"2004-11-30",
    "iso:country":"GB",
    "wof:name":"PE30 2NF",
    "wof:placetype":"postalcode"
},
  "geometry": {"coordinates":[0.409953,52.76654],"type":"Point"}
}