{
  "type": "Feature",
  "properties": {
    "iso:country":"GB",
    "wof:name":"BR1 2TA",
    "wof:placetype":"postalcode"
},
  "geometry": {"coordinates":[0.04275246977545,51.4104067869457],"type":"Point"}
}