{
  "type": "Feature",
  "properties": {
    "iso:country": "GB",
    "wof:name": "FY7 8PB",
    "wof:placetype": "postalcode"
  },
  "geometry": {"coordinates":[-3.045331,53.908739],"type":"Point"}
}
