{
  "type": "Feature",
  "properties": {
    "date:inception_lower": "1980-01-01",
    "date:inception_upper": "1980-01-01",
    "iso:country": "GB",
    "wof:name": "FY7 8PB",
    "wof:placetype": "postalcode"
  },
  "geometry": {"coordinates":[-3.045331,53.908739],"type":"Point"}
}
