{
  "type": "Feature",
  "properties": {
    "iso:country":"GB",
    "wof:name":"FY7 8PB",
    "wof:placetype":"postalcode"
},
  "geometry": {"coordinates":[-3.04533079461115,53.90873877451199],"type":"Point"}
}