{
  "type": "Feature",
  "properties": {
    "date:inception_lower": "2020-02-01",
    "date:inception_upper": "2020-02-01",
    "iso:country": "GB",
    "wof:name": "NP15 9AR",
    "wof:placetype": "postalcode"
  },
  "geometry": {"coordinates":[-2.905638,51.702422],"type":"Point"}
}
