{
  "type": "Feature",
  "properties": {
    "iso:country": "GB",
    "wof:name": "NP15 9AR",
    "wof:placetype": "postalcode"
  },
  "geometry": {"coordinates":[-2.905638,51.702422],"type":"Point"}
}
