{
  "type": "Feature",
  "properties": {
    "iso:country": "GB",
    "wof:name": "NP23 5LL",
    "wof:placetype": "postalcode"
  },
  "geometry": {"coordinates":[-3.208592,51.789168],"type":"Point"}
}
