{
  "type": "Feature",
  "properties": {
    "date:inception_lower": "2005-09-01",
    "date:inception_upper": "2005-09-01",
    "iso:country": "GB",
    "wof:name": "DN35 8JG",
    "wof:placetype": "postalcode"
  },
  "geometry": {"coordinates":[-0.032173,53.555552],"type":"Point"}
}
