{
  "type": "Feature",
  "properties": {
    "iso:country": "GB",
    "wof:name": "DN35 8JG",
    "wof:placetype": "postalcode"
  },
  "geometry": {"coordinates":[-0.032173,53.555552],"type":"Point"}
}
