{
  "type": "Feature",
  "properties": {
    "date:inception_lower": "2021-06-01",
    "date:inception_upper": "2021-06-01",
    "iso:country": "GB",
    "wof:name": "MK2 2FX",
    "wof:placetype": "postalcode"
  },
  "geometry": {"coordinates":[-0.73023,51.998262],"type":"Point"}
}
