{
  "type": "Feature",
  "properties": {
    "iso:country":"GB",
    "wof:name":"G53 5EN",
    "wof:placetype":"postalcode"
},
  "geometry": {"coordinates":[-4.33865816963811,55.83014542434538],"type":"Point"}
}