{
  "type": "Feature",
  "properties": {
    "iso:country":"GB",
    "wof:name":"TA1 2XA",
    "wof:placetype":"postalcode"
},
  "geometry": {"coordinates":[-3.06808250373643,51.02158145427946],"type":"Point"}
}