{
  "type": "Feature",
  "properties": {
    "iso:country": "GB",
    "wof:name": "NG31 8TT",
    "wof:placetype": "postalcode"
  },
  "geometry": {"coordinates":[-0.657975,52.91846],"type":"Point"}
}
