{
  "type": "Feature",
  "properties": {
    "iso:country": "GB",
    "wof:name": "LL32 8LQ",
    "wof:placetype": "postalcode"
  },
  "geometry": {"coordinates":[-3.85092,53.275155],"type":"Point"}
}
