{
  "type": "Feature",
  "properties": {
    "date:inception_lower": "1980-01-01",
    "date:inception_upper": "1980-01-01",
    "iso:country": "GB",
    "wof:name": "LL32 8LQ",
    "wof:placetype": "postalcode"
  },
  "geometry": {"coordinates":[-3.85092,53.275155],"type":"Point"}
}
