{
  "type": "Feature",
  "properties": {
    "date:inception_lower": "2022-05-01",
    "date:inception_upper": "2022-05-01",
    "iso:country": "GB",
    "wof:name": "WR2 5FN",
    "wof:placetype": "postalcode"
  },
  "geometry": {"coordinates":[-2.260455,52.186076],"type":"Point"}
}
