{
  "type": "Feature",
  "properties": {
    "iso:country": "GB",
    "wof:name": "E7 9JF",
    "wof:placetype": "postalcode"
  },
  "geometry": {"coordinates":[0.016976,51.545376],"type":"Point"}
}
