{
  "type": "Feature",
  "properties": {
    "iso:country":"GB",
    "wof:name":"E7 9JF",
    "wof:placetype":"postalcode"
},
  "geometry": {"coordinates":[0.01697601596159,51.54537572770542],"type":"Point"}
}