{
  "type": "Feature",
  "properties": {
    "date:inception_lower": "1999-06-01",
    "date:inception_upper": "1999-06-01",
    "iso:country": "GB",
    "wof:name": "NP26 4LE",
    "wof:placetype": "postalcode"
  },
  "geometry": {"coordinates":[-2.764646,51.588944],"type":"Point"}
}
