{
  "type": "Feature",
  "properties": {
    "iso:country": "GB",
    "wof:name": "NP26 4LE",
    "wof:placetype": "postalcode"
  },
  "geometry": {"coordinates":[-2.764714,51.588961],"type":"Point"}
}
