{
  "type": "Feature",
  "properties": {
    "iso:country":"GB",
    "wof:name":"NP26 4LE",
    "wof:placetype":"postalcode"
},
  "geometry": {"coordinates":[-2.76471370007281,51.58896068251515],"type":"Point"}
}