{
  "type": "Feature",
  "properties": {
    "date:inception_lower": "1980-01-01",
    "date:inception_upper": "1980-01-01",
    "iso:country": "GB",
    "wof:name": "ST5 5EW",
    "wof:placetype": "postalcode"
  },
  "geometry": {"coordinates":[-2.350252,52.959533],"type":"Point"}
}
