{
  "type": "Feature",
  "properties": {
    "iso:country":"GB",
    "wof:name":"ST5 5EW",
    "wof:placetype":"postalcode"
},
  "geometry": {"coordinates":[-2.34749914613769,52.95957862861489],"type":"Point"}
}