{
  "type": "Feature",
  "properties": {
    "iso:country":"GB",
    "wof:name":"MK45 1BL",
    "wof:placetype":"postalcode"
},
  "geometry": {"coordinates":[-0.50374080183459,52.00919724914856],"type":"Point"}
}