{
  "type": "Feature",
  "properties": {
    "iso:country":"GB",
    "wof:name":"LA6 2BJ",
    "wof:placetype":"postalcode"
},
  "geometry": {"coordinates":[-2.5974047139042,54.20304165411029],"type":"Point"}
}