{
  "type": "Feature",
  "properties": {
    "date:inception_lower": "2021-05-01",
    "date:inception_upper": "2021-05-01",
    "iso:country": "GB",
    "wof:name": "CH62 9BF",
    "wof:placetype": "postalcode"
  },
  "geometry": {"coordinates":[-2.97156,53.309645],"type":"Point"}
}
