{
  "type": "Feature",
  "properties": {
    "iso:country":"GB",
    "wof:name":"IP14 6JN",
    "wof:placetype":"postalcode"
},
  "geometry": {"coordinates":[1.207710232721,52.25447597652223],"type":"Point"}
}