{
  "type": "Feature",
  "properties": {
    "date:inception_lower": "1980-01-01",
    "date:inception_upper": "1980-01-01",
    "iso:country": "GB",
    "wof:name": "IP14 6JN",
    "wof:placetype": "postalcode"
  },
  "geometry": {"coordinates":[1.20771,52.254476],"type":"Point"}
}
