{
  "type": "Feature",
  "properties": {
    "date:inception_lower": "2006-07-01",
    "date:inception_upper": "2006-07-01",
    "iso:country": "GB",
    "wof:name": "BB1 2PW",
    "wof:placetype": "postalcode"
  },
  "geometry": {"coordinates":[-2.458886,53.736192],"type":"Point"}
}
