{
  "type": "Feature",
  "properties": {
    "iso:country":"GB",
    "wof:name":"BB1 2PW",
    "wof:placetype":"postalcode"
},
  "geometry": {"coordinates":[-2.45554402306065,53.7368004214733],"type":"Point"}
}