{
  "type": "Feature",
  "properties": {
    "iso:country": "GB",
    "wof:name": "BB1 2PW",
    "wof:placetype": "postalcode"
  },
  "geometry": {"coordinates":[-2.455544,53.7368],"type":"Point"}
}
