{
  "type": "Feature",
  "properties": {
    "iso:country": "GB",
    "wof:name": "SO40 3PH",
    "wof:placetype": "postalcode"
  },
  "geometry": {"coordinates":[-1.502895,50.927896],"type":"Point"}
}
