{
  "type": "Feature",
  "properties": {
    "iso:country":"GB",
    "wof:name":"TN29 0JX",
    "wof:placetype":"postalcode"
},
  "geometry": {"coordinates":[1.02705697454577,51.04388434796448],"type":"Point"}
}