{
  "type": "Feature",
  "properties": {
    "iso:country":"GB",
    "wof:name":"SA72 6XF",
    "wof:placetype":"postalcode"
},
  "geometry": {"coordinates":[-4.94740146335307,51.6919860286513],"type":"Point"}
}