{
  "type": "Feature",
  "properties": {
    "date:inception_lower": "1997-06-01",
    "date:inception_upper": "1997-06-01",
    "iso:country": "GB",
    "wof:name": "TQ13 9RY",
    "wof:placetype": "postalcode"
  },
  "geometry": {"coordinates":[-3.714507,50.571418],"type":"Point"}
}
