{
  "type": "Feature",
  "properties": {
    "iso:country":"GB",
    "wof:name":"SM3 9AD",
    "wof:placetype":"postalcode"
},
  "geometry": {"coordinates":[-0.21164873727908,51.37073526888847],"type":"Point"}
}