{
  "type": "Feature",
  "properties": {
    "date:inception_lower":"1980-01-01",
    "date:inception_upper":"1980-01-31",
    "iso:country":"GB",
    "wof:name":"IG6 1QJ",
    "wof:placetype":"postalcode"
},
  "geometry": {"coordinates":[0.084952,51.587741],"type":"Point"}
}