{
  "type": "Feature",
  "properties": {
    "iso:country":"GB",
    "wof:name":"LS13 4RR",
    "wof:placetype":"postalcode"
},
  "geometry": {"coordinates":[-1.63309179845231,53.80353703931554],"type":"Point"}
}