{
  "type": "Feature",
  "properties": {
    "iso:country":"GB",
    "wof:name":"NR7 0TG",
    "wof:placetype":"postalcode"
},
  "geometry": {"coordinates":[1.36252668816062,52.638911144692],"type":"Point"}
}