{
  "type": "Feature",
  "properties": {
    "date:inception_lower":"1992-08-01",
    "date:inception_upper":"1992-08-31",
    "iso:country":"GB",
    "wof:name":"NR7 0TG",
    "wof:placetype":"postalcode"
},
  "geometry": {"coordinates":[1.362527,52.638911],"type":"Point"}
}