{
  "type": "Feature",
  "properties": {
    "date:inception_lower": "2007-07-01",
    "date:inception_upper": "2007-07-01",
    "iso:country": "GB",
    "wof:name": "CH42 7HE",
    "wof:placetype": "postalcode"
  },
  "geometry": {"coordinates":[-3.028405,53.382314],"type":"Point"}
}
