{
  "type": "Feature",
  "properties": {
    "iso:country": "GB",
    "wof:name": "BB10 2UB",
    "wof:placetype": "postalcode"
  },
  "geometry": {"coordinates":[-2.218319,53.814792],"type":"Point"}
}
