{
  "type": "Feature",
  "properties": {
    "date:inception_lower":"2014-02-01",
    "date:inception_upper":"2014-02-28",
    "iso:country":"GB",
    "wof:name":"BB10 2UB",
    "wof:placetype":"postalcode"
},
  "geometry": {"coordinates":[-2.218319,53.814792],"type":"Point"}
}