{
  "type": "Feature",
  "properties": {
    "iso:country":"GB",
    "wof:name":"KY11 2QZ",
    "wof:placetype":"postalcode"
},
  "geometry": {"coordinates":[-3.42335496846969,56.04067300194023],"type":"Point"}
}