{
  "type": "Feature",
  "properties": {
    "iso:country": "GB",
    "wof:name": "KY11 2QZ",
    "wof:placetype": "postalcode"
  },
  "geometry": {"coordinates":[-3.423378,56.04043],"type":"Point"}
}
