{
  "type": "Feature",
  "properties": {
    "iso:country": "GB",
    "wof:name": "YO23 1PX",
    "wof:placetype": "postalcode"
  },
  "geometry": {"coordinates":[-1.089541,53.943196],"type":"Point"}
}
