{
  "type": "Feature",
  "properties": {
    "iso:country":"GB",
    "wof:name":"YO23 1PX",
    "wof:placetype":"postalcode"
},
  "geometry": {"coordinates":[-1.08954127436269,53.94319633798693],"type":"Point"}
}