{
  "type": "Feature",
  "properties": {
    "date:inception_lower":"2016-03-01",
    "date:inception_upper":"2016-03-31",
    "iso:country":"GB",
    "wof:name":"YO23 1PX",
    "wof:placetype":"postalcode"
},
  "geometry": {"coordinates":[-1.089541,53.943196],"type":"Point"}
}