{
  "type": "Feature",
  "properties": {
    "iso:country":"GB",
    "wof:name":"SN8 2JL",
    "wof:placetype":"postalcode"
},
  "geometry": {"coordinates":[-1.59312338119606,51.50133818923916],"type":"Point"}
}