{
  "type": "Feature",
  "properties": {
    "iso:country":"GB",
    "wof:name":"MK18 3AN",
    "wof:placetype":"postalcode"
},
  "geometry": {"coordinates":[-0.88342093587322,51.94182000805245],"type":"Point"}
}