{
  "type": "Feature",
  "properties": {
    "iso:country":"GB",
    "wof:name":"CF46 5BW",
    "wof:placetype":"postalcode"
},
  "geometry": {"coordinates":[-3.31202485067953,51.66157287653941],"type":"Point"}
}