{
  "type": "Feature",
  "properties": {
    "iso:country":"GB",
    "wof:name":"PE3 6HA",
    "wof:placetype":"postalcode"
},
  "geometry": {"coordinates":[-0.26203927856637,52.57839012456781],"type":"Point"}
}