{
  "type": "Feature",
  "properties": {
    "iso:country":"GB",
    "wof:name":"WV4 5EG",
    "wof:placetype":"postalcode"
},
  "geometry": {"coordinates":[-2.1217733461783,52.56145569377061],"type":"Point"}
}