{
  "type": "Feature",
  "properties": {
    "iso:country":"GB",
    "wof:name":"DN10 4QJ",
    "wof:placetype":"postalcode"
},
  "geometry": {"coordinates":[-0.83098077995901,53.40026130089959],"type":"Point"}
}