{
  "type": "Feature",
  "properties": {
    "iso:country": "GB",
    "wof:name": "HU11 4TG",
    "wof:placetype": "postalcode"
  },
  "geometry": {"coordinates":[-0.18224,53.846615],"type":"Point"}
}
