{
  "type": "Feature",
  "properties": {
    "iso:country":"GB",
    "wof:name":"HU11 4TG",
    "wof:placetype":"postalcode"
},
  "geometry": {"coordinates":[-0.18223968771148,53.84661470772167],"type":"Point"}
}