{
  "type": "Feature",
  "properties": {
    "iso:country": "GB",
    "wof:name": "KA6 6LQ",
    "wof:placetype": "postalcode"
  },
  "geometry": {"coordinates":[-4.502628,55.443864],"type":"Point"}
}
