{
  "type": "Feature",
  "properties": {
    "date:inception_lower": "1980-01-01",
    "date:inception_upper": "1980-01-01",
    "iso:country": "GB",
    "wof:name": "KA6 6LQ",
    "wof:placetype": "postalcode"
  },
  "geometry": {"coordinates":[-4.502404,55.44358],"type":"Point"}
}
