{
  "type": "Feature",
  "properties": {
    "iso:country":"GB",
    "wof:name":"KA6 6LQ",
    "wof:placetype":"postalcode"
},
  "geometry": {"coordinates":[-4.50264585591941,55.4438613840086],"type":"Point"}
}