{
  "type": "Feature",
  "properties": {
    "iso:country":"GB",
    "wof:name":"EX6 6AQ",
    "wof:placetype":"postalcode"
},
  "geometry": {"coordinates":[-3.63446303361135,50.72630354446554],"type":"Point"}
}