{
  "type": "Feature",
  "properties": {
    "iso:country":"GB",
    "wof:name":"SA31 1EZ",
    "wof:placetype":"postalcode"
},
  "geometry": {"coordinates":[-4.3057352972591,51.85973108626236],"type":"Point"}
}