{
  "type": "Feature",
  "properties": {
    "date:inception_lower":"1980-01-01",
    "date:inception_upper":"1980-01-31",
    "iso:country":"GB",
    "wof:name":"SA31 1EZ",
    "wof:placetype":"postalcode"
},
  "geometry": {"coordinates":[-4.305735,51.859731],"type":"Point"}
}