{
  "type": "Feature",
  "properties": {
    "iso:country":"GB",
    "wof:name":"S70 2SH",
    "wof:placetype":"postalcode"
},
  "geometry": {"coordinates":[-1.48398666008124,53.55312434788939],"type":"Point"}
}