{
  "type": "Feature",
  "properties": {
    "iso:country": "GB",
    "wof:name": "S70 2SH",
    "wof:placetype": "postalcode"
  },
  "geometry": {"coordinates":[-1.483988,53.553143],"type":"Point"}
}
