{
  "type": "Feature",
  "properties": {
    "iso:country":"GB",
    "wof:name":"SW4 8LF",
    "wof:placetype":"postalcode"
},
  "geometry": {"coordinates":[-0.13361554764898,51.45243039678712],"type":"Point"}
}