{
  "type": "Feature",
  "properties": {
    "iso:country":"GB",
    "wof:name":"SW15 2EE",
    "wof:placetype":"postalcode"
},
  "geometry": {"coordinates":[-0.20685750637283,51.46095640742105],"type":"Point"}
}