{
  "type": "Feature",
  "properties": {
    "iso:country":"GB",
    "wof:name":"CT4 6UN",
    "wof:placetype":"postalcode"
},
  "geometry": {"coordinates":[1.11053833449379,51.15422547060322],"type":"Point"}
}