{
  "type": "Feature",
  "properties": {
    "iso:country": "GB",
    "wof:name": "LL77 7YD",
    "wof:placetype": "postalcode"
  },
  "geometry": {"coordinates":[-4.32348,53.239016],"type":"Point"}
}
