{
  "type": "Feature",
  "properties": {
    "date:inception_lower": "1980-01-01",
    "date:inception_upper": "1980-01-01",
    "iso:country": "GB",
    "wof:name": "LL77 7YD",
    "wof:placetype": "postalcode"
  },
  "geometry": {"coordinates":[-4.32348,53.239016],"type":"Point"}
}
