{
  "type": "Feature",
  "properties": {
    "iso:country":"GB",
    "wof:name":"LL77 7YD",
    "wof:placetype":"postalcode"
},
  "geometry": {"coordinates":[-4.32343971220389,53.23919744340119],"type":"Point"}
}