{
  "type": "Feature",
  "properties": {
    "iso:country":"GB",
    "wof:name":"EX12 2LH",
    "wof:placetype":"postalcode"
},
  "geometry": {"coordinates":[-3.07128297842712,50.70574417369259],"type":"Point"}
}