{
  "type": "Feature",
  "properties": {
    "iso:country":"GB",
    "wof:name":"IP21 5PJ",
    "wof:placetype":"postalcode"
},
  "geometry": {"coordinates":[1.31087470144781,52.34711470600434],"type":"Point"}
}