{
  "type": "Feature",
  "properties": {
    "iso:country": "GB",
    "wof:name": "LU2 0RZ",
    "wof:placetype": "postalcode"
  },
  "geometry": {"coordinates":[-0.392706,51.885691],"type":"Point"}
}
