{
  "type": "Feature",
  "properties": {
    "date:inception_lower": "1980-01-01",
    "date:inception_upper": "1980-01-01",
    "iso:country": "GB",
    "wof:name": "EN6 5AB",
    "wof:placetype": "postalcode"
  },
  "geometry": {"coordinates":[-0.177822,51.694427],"type":"Point"}
}
