{
  "type": "Feature",
  "properties": {
    "date:inception_lower": "1980-01-01",
    "date:inception_upper": "1980-01-01",
    "iso:country": "GB",
    "wof:name": "SR2 9JG",
    "wof:placetype": "postalcode"
  },
  "geometry": {"coordinates":[-1.382575,54.882523],"type":"Point"}
}
