{
  "type": "Feature",
  "properties": {
    "iso:country":"GB",
    "wof:name":"SR2 9JG",
    "wof:placetype":"postalcode"
},
  "geometry": {"coordinates":[-1.38263690466446,54.88256807778875],"type":"Point"}
}