{
  "type": "Feature",
  "properties": {
    "iso:country":"GB",
    "wof:name":"PE28 0TX",
    "wof:placetype":"postalcode"
},
  "geometry": {"coordinates":[-0.33228947205097,52.3322385615925],"type":"Point"}
}