{
  "type": "Feature",
  "properties": {
    "iso:country":"GB",
    "wof:name":"YO25 9EN",
    "wof:placetype":"postalcode"
},
  "geometry": {"coordinates":[-0.59635959435657,53.9798297472821],"type":"Point"}
}