{
  "type": "Feature",
  "properties": {
    "iso:country":"GB",
    "wof:name":"DT4 7NQ",
    "wof:placetype":"postalcode"
},
  "geometry": {"coordinates":[-2.45967194752624,50.62630814087787],"type":"Point"}
}