{
  "type": "Feature",
  "properties": {
    "iso:country": "GB",
    "wof:name": "DT4 7NQ",
    "wof:placetype": "postalcode"
  },
  "geometry": {"coordinates":[-2.459672,50.626308],"type":"Point"}
}
