{
  "type": "Feature",
  "properties": {
    "date:inception_lower":"2007-07-01",
    "date:inception_upper":"2007-07-31",
    "iso:country":"GB",
    "wof:name":"DT4 7NQ",
    "wof:placetype":"postalcode"
},
  "geometry": {"coordinates":[-2.459672,50.626308],"type":"Point"}
}