{
  "type": "Feature",
  "properties": {
    "iso:country":"GB",
    "wof:name":"IP17 3NL",
    "wof:placetype":"postalcode"
},
  "geometry": {"coordinates":[1.55842513478125,52.25470528182449],"type":"Point"}
}