{
  "type": "Feature",
  "properties": {
    "date:inception_lower": "1980-01-01",
    "date:inception_upper": "1980-01-01",
    "iso:country": "GB",
    "wof:name": "IP17 3NL",
    "wof:placetype": "postalcode"
  },
  "geometry": {"coordinates":[1.558445,52.254772],"type":"Point"}
}
