{
  "type": "Feature",
  "properties": {
    "iso:country": "GB",
    "wof:name": "DA1 2QA",
    "wof:placetype": "postalcode"
  },
  "geometry": {"coordinates":[0.203096,51.438923],"type":"Point"}
}
