{
  "type": "Feature",
  "properties": {
    "date:inception_lower": "1988-03-01",
    "date:inception_upper": "1988-03-01",
    "iso:country": "GB",
    "wof:name": "DA1 2QA",
    "wof:placetype": "postalcode"
  },
  "geometry": {"coordinates":[0.203096,51.438923],"type":"Point"}
}
