{
  "type": "Feature",
  "properties": {
    "date:inception_lower": "2022-02-01",
    "date:inception_upper": "2022-02-01",
    "iso:country": "GB",
    "wof:name": "PA1 2FJ",
    "wof:placetype": "postalcode"
  },
  "geometry": {"coordinates":[-4.45601,55.840993],"type":"Point"}
}
