{
  "type": "Feature",
  "properties": {
    "iso:country":"GB",
    "wof:name":"TN20 6HP",
    "wof:placetype":"postalcode"
},
  "geometry": {"coordinates":[0.21975260349372,51.00748639562188],"type":"Point"}
}