{
  "type": "Feature",
  "properties": {
    "iso:country": "GB",
    "wof:name": "HP21 7SF",
    "wof:placetype": "postalcode"
  },
  "geometry": {"coordinates":[-0.807269,51.815833],"type":"Point"}
}
