{
  "type": "Feature",
  "properties": {
    "iso:country":"GB",
    "wof:name":"SK7 3HB",
    "wof:placetype":"postalcode"
},
  "geometry": {"coordinates":[-2.16155294230141,53.38145842224028],"type":"Point"}
}