{
  "type": "Feature",
  "properties": {
    "iso:country":"GB",
    "wof:name":"BH16 5NT",
    "wof:placetype":"postalcode"
},
  "geometry": {"coordinates":[-2.0380700396486,50.74026615130312],"type":"Point"}
}