{
  "type": "Feature",
  "properties": {
    "iso:country": "GB",
    "wof:name": "BH16 5NT",
    "wof:placetype": "postalcode"
  },
  "geometry": {"coordinates":[-2.03807,50.740266],"type":"Point"}
}
