{
  "type": "Feature",
  "properties": {
    "date:inception_lower": "2020-08-01",
    "date:inception_upper": "2020-08-01",
    "iso:country": "GB",
    "wof:name": "CF62 5DT",
    "wof:placetype": "postalcode"
  },
  "geometry": {"coordinates":[-3.267815,51.396203],"type":"Point"}
}
