{
  "type": "Feature",
  "properties": {
    "date:inception_lower": "1980-01-01",
    "date:inception_upper": "1980-01-01",
    "iso:country": "GB",
    "wof:name": "WN7 5EL",
    "wof:placetype": "postalcode"
  },
  "geometry": {"coordinates":[-2.536674,53.506435],"type":"Point"}
}
