{
  "type": "Feature",
  "properties": {
    "iso:country":"GB",
    "wof:name":"WN7 5EL",
    "wof:placetype":"postalcode"
},
  "geometry": {"coordinates":[-2.53667400985928,53.50643485605124],"type":"Point"}
}