{
  "type": "Feature",
  "properties": {
    "iso:country": "GB",
    "wof:name": "WN7 5EL",
    "wof:placetype": "postalcode"
  },
  "geometry": {"coordinates":[-2.536674,53.506435],"type":"Point"}
}
