{
  "type": "Feature",
  "properties": {
    "iso:country":"GB",
    "wof:name":"LE12 7LY",
    "wof:placetype":"postalcode"
},
  "geometry": {"coordinates":[-1.08401763013222,52.75329404122141],"type":"Point"}
}