{
  "type": "Feature",
  "properties": {
    "iso:country":"GB",
    "wof:name":"G63 0AA",
    "wof:placetype":"postalcode"
},
  "geometry": {"coordinates":[-4.43520914177489,56.06919739398059],"type":"Point"}
}