{
  "type": "Feature",
  "properties": {
    "date:inception_lower": "1980-01-01",
    "date:inception_upper": "1980-01-01",
    "iso:country": "GB",
    "wof:name": "G63 0AA",
    "wof:placetype": "postalcode"
  },
  "geometry": {"coordinates":[-4.435209,56.069197],"type":"Point"}
}
