{
  "type": "Feature",
  "properties": {
    "date:inception_lower":"1980-01-01",
    "date:inception_upper":"1980-01-31",
    "iso:country":"GB",
    "wof:name":"TR18 2LU",
    "wof:placetype":"postalcode"
},
  "geometry": {"coordinates":[-5.534371,50.118837],"type":"Point"}
}