{
  "type": "Feature",
  "properties": {
    "iso:country":"GB",
    "wof:name":"B91 2SZ",
    "wof:placetype":"postalcode"
},
  "geometry": {"coordinates":[-1.73875309776768,52.41482931197952],"type":"Point"}
}