{
  "type": "Feature",
  "properties": {
    "iso:country":"GB",
    "wof:name":"RG12 1DS",
    "wof:placetype":"postalcode"
},
  "geometry": {"coordinates":[-0.75198626615018,51.41696878277976],"type":"Point"}
}