{
  "type": "Feature",
  "properties": {
    "iso:country":"GB",
    "wof:name":"NN6 0QS",
    "wof:placetype":"postalcode"
},
  "geometry": {"coordinates":[-0.82300726484076,52.28055150278023],"type":"Point"}
}