{
  "type": "Feature",
  "properties": {
    "date:inception_lower": "2006-07-01",
    "date:inception_upper": "2006-07-01",
    "iso:country": "GB",
    "wof:name": "NN6 0QS",
    "wof:placetype": "postalcode"
  },
  "geometry": {"coordinates":[-0.823007,52.280551],"type":"Point"}
}
