{
  "type": "Feature",
  "properties": {
    "iso:country":"GB",
    "wof:name":"NG14 6NH",
    "wof:placetype":"postalcode"
},
  "geometry": {"coordinates":[-1.09280960571918,53.04138921036659],"type":"Point"}
}