{
  "type": "Feature",
  "properties": {
    "iso:country": "GB",
    "wof:name": "NG14 6NH",
    "wof:placetype": "postalcode"
  },
  "geometry": {"coordinates":[-1.09281,53.041389],"type":"Point"}
}
