{
  "type": "Feature",
  "properties": {
    "date:inception_lower": "1997-12-01",
    "date:inception_upper": "1997-12-01",
    "iso:country": "GB",
    "wof:name": "NE33 1JL",
    "wof:placetype": "postalcode"
  },
  "geometry": {"coordinates":[-1.439269,54.998965],"type":"Point"}
}
