{
  "type": "Feature",
  "properties": {
    "iso:country": "GB",
    "wof:name": "NE33 1JL",
    "wof:placetype": "postalcode"
  },
  "geometry": {"coordinates":[-1.439269,54.998965],"type":"Point"}
}
