{
  "type": "Feature",
  "properties": {
    "date:inception_lower": "1980-01-01",
    "date:inception_upper": "1980-01-01",
    "iso:country": "GB",
    "wof:name": "SK6 6BA",
    "wof:placetype": "postalcode"
  },
  "geometry": {"coordinates":[-2.061934,53.396678],"type":"Point"}
}
