{
  "type": "Feature",
  "properties": {
    "iso:country": "GB",
    "wof:name": "SK6 6BA",
    "wof:placetype": "postalcode"
  },
  "geometry": {"coordinates":[-2.06225,53.396248],"type":"Point"}
}
