{
  "type": "Feature",
  "properties": {
    "date:inception_lower": "2023-07-01",
    "date:inception_upper": "2023-07-01",
    "iso:country": "GB",
    "wof:name": "TA5 1ES",
    "wof:placetype": "postalcode"
  },
  "geometry": {"coordinates":[-3.157476,51.149679],"type":"Point"}
}
