{
  "type": "Feature",
  "properties": {
    "date:inception_lower": "1980-01-01",
    "date:inception_upper": "1980-01-01",
    "iso:country": "GB",
    "wof:name": "HX3 6HN",
    "wof:placetype": "postalcode"
  },
  "geometry": {"coordinates":[-1.860524,53.732023],"type":"Point"}
}
