{
  "type": "Feature",
  "properties": {
    "iso:country":"GB",
    "wof:name":"HX3 6HN",
    "wof:placetype":"postalcode"
},
  "geometry": {"coordinates":[-1.8605242037461,53.73202269655093],"type":"Point"}
}