{
  "type": "Feature",
  "properties": {
    "iso:country": "GB",
    "wof:name": "EX4 6AX",
    "wof:placetype": "postalcode"
  },
  "geometry": {"coordinates":[-3.52,50.731268],"type":"Point"}
}
