{
  "type": "Feature",
  "properties": {
    "iso:country":"GB",
    "wof:name":"OL13 0AJ",
    "wof:placetype":"postalcode"
},
  "geometry": {"coordinates":[-2.20133006198087,53.70208454222857],"type":"Point"}
}