{
  "type": "Feature",
  "properties": {
    "iso:country":"GB",
    "wof:name":"TQ9 6AP",
    "wof:placetype":"postalcode"
},
  "geometry": {"coordinates":[-3.70664402488732,50.4706232748307],"type":"Point"}
}