{
  "type": "Feature",
  "properties": {
    "date:inception_lower":"1995-12-01",
    "date:inception_upper":"1995-12-31",
    "iso:country":"GB",
    "wof:name":"KW17 2HW",
    "wof:placetype":"postalcode"
},
  "geometry": {"coordinates":[-3.228804,59.070498],"type":"Point"}
}