{
  "type": "Feature",
  "properties": {
    "iso:country":"GB",
    "wof:name":"KW17 2HW",
    "wof:placetype":"postalcode"
},
  "geometry": {"coordinates":[-3.22880367134829,59.07049766709502],"type":"Point"}
}