{
  "type": "Feature",
  "properties": {
    "iso:country": "GB",
    "wof:name": "KT18 7TR",
    "wof:placetype": "postalcode"
  },
  "geometry": {"coordinates":[-0.305641,51.337565],"type":"Point"}
}
