{
  "type": "Feature",
  "properties": {
    "date:inception_lower":"1981-06-01",
    "date:inception_upper":"1981-06-30",
    "iso:country":"GB",
    "wof:name":"TN21 0HH",
    "wof:placetype":"postalcode"
},
  "geometry": {"coordinates":[0.249193,50.93474],"type":"Point"}
}