{
  "type": "Feature",
  "properties": {
    "iso:country":"GB",
    "wof:name":"TN21 0HH",
    "wof:placetype":"postalcode"
},
  "geometry": {"coordinates":[0.24919325860281,50.93473965995531],"type":"Point"}
}