{
  "type": "Feature",
  "properties": {
    "iso:country": "GB",
    "wof:name": "TN21 0HH",
    "wof:placetype": "postalcode"
  },
  "geometry": {"coordinates":[0.249193,50.93474],"type":"Point"}
}
