{
  "type": "Feature",
  "properties": {
    "iso:country":"GB",
    "wof:name":"PE33 0PQ",
    "wof:placetype":"postalcode"
},
  "geometry": {"coordinates":[0.40809572145708,52.71219653105879],"type":"Point"}
}