{
  "type": "Feature",
  "properties": {
    "iso:country":"GB",
    "wof:name":"LE3 2BB",
    "wof:placetype":"postalcode"
},
  "geometry": {"coordinates":[-1.15640406598434,52.61697750116664],"type":"Point"}
}