{
  "type": "Feature",
  "properties": {
    "iso:country":"GB",
    "wof:name":"HA9 6NP",
    "wof:placetype":"postalcode"
},
  "geometry": {"coordinates":[-0.27320030775653,51.54915130994547],"type":"Point"}
}