{
  "type": "Feature",
  "properties": {
    "date:inception_lower": "1988-03-01",
    "date:inception_upper": "1988-03-01",
    "iso:country": "GB",
    "wof:name": "CA13 9BN",
    "wof:placetype": "postalcode"
  },
  "geometry": {"coordinates":[-3.349425,54.662369],"type":"Point"}
}
