{
  "type": "Feature",
  "properties": {
    "iso:country": "GB",
    "wof:name": "NG33 5FF",
    "wof:placetype": "postalcode"
  },
  "geometry": {"coordinates":[-0.700059,52.830541],"type":"Point"}
}
