{
  "type": "Feature",
  "properties": {
    "iso:country": "GB",
    "wof:name": "PA12 4LB",
    "wof:placetype": "postalcode"
  },
  "geometry": {"coordinates":[-4.650854,55.817006],"type":"Point"}
}
