{
  "type": "Feature",
  "properties": {
    "date:inception_lower": "1980-01-01",
    "date:inception_upper": "1980-01-01",
    "iso:country": "GB",
    "wof:name": "PA12 4LB",
    "wof:placetype": "postalcode"
  },
  "geometry": {"coordinates":[-4.650854,55.817006],"type":"Point"}
}
