{
  "type": "Feature",
  "properties": {
    "iso:country": "GB",
    "wof:name": "GU10 4JX",
    "wof:placetype": "postalcode"
  },
  "geometry": {"coordinates":[-0.829424,51.191351],"type":"Point"}
}
