{
  "type": "Feature",
  "properties": {
    "date:inception_lower":"1980-01-01",
    "date:inception_upper":"1980-01-31",
    "iso:country":"GB",
    "wof:name":"GU10 4JX",
    "wof:placetype":"postalcode"
},
  "geometry": {"coordinates":[-0.829424,51.191351],"type":"Point"}
}