{
  "type": "Feature",
  "properties": {
    "iso:country":"GB",
    "wof:name":"EN8 0HA",
    "wof:placetype":"postalcode"
},
  "geometry": {"coordinates":[-0.04628337841584,51.71110722574167],"type":"Point"}
}