{
  "type": "Feature",
  "properties": {
    "iso:country":"GB",
    "wof:name":"BH23 2RR",
    "wof:placetype":"postalcode"
},
  "geometry": {"coordinates":[-1.80229703057669,50.75635501547789],"type":"Point"}
}