{
  "type": "Feature",
  "properties": {
    "iso:country":"GB",
    "wof:name":"CM13 1YZ",
    "wof:placetype":"postalcode"
},
  "geometry": {"coordinates":[0.34359443358454,51.63341685471157],"type":"Point"}
}