{
  "type": "Feature",
  "properties": {
    "date:inception_lower": "1991-01-01",
    "date:inception_upper": "1991-01-01",
    "iso:country": "GB",
    "wof:name": "CM13 1YZ",
    "wof:placetype": "postalcode"
  },
  "geometry": {"coordinates":[0.343594,51.633417],"type":"Point"}
}
