{
  "type": "Feature",
  "properties": {
    "date:inception_lower": "1980-01-01",
    "date:inception_upper": "1980-01-01",
    "iso:country": "GB",
    "wof:name": "DN3 1DS",
    "wof:placetype": "postalcode"
  },
  "geometry": {"coordinates":[-1.068634,53.57516],"type":"Point"}
}
