{
  "type": "Feature",
  "properties": {
    "date:inception_lower": "2017-10-01",
    "date:inception_upper": "2017-10-01",
    "iso:country": "GB",
    "wof:name": "DN21 9EP",
    "wof:placetype": "postalcode"
  },
  "geometry": {"coordinates":[-0.774067,53.400862],"type":"Point"}
}
