{
  "type": "Feature",
  "properties": {
    "iso:country":"GB",
    "wof:name":"IG7 5DH",
    "wof:placetype":"postalcode"
},
  "geometry": {"coordinates":[0.07905861841828,51.61543298627336],"type":"Point"}
}