{
  "type": "Feature",
  "properties": {
    "date:inception_lower":"1980-01-01",
    "date:inception_upper":"1980-01-31",
    "iso:country":"GB",
    "wof:name":"EH26 0BH",
    "wof:placetype":"postalcode"
},
  "geometry": {"coordinates":[-3.21903,55.83836],"type":"Point"}
}