{
  "type": "Feature",
  "properties": {
    "iso:country": "GB",
    "wof:name": "EH26 0BH",
    "wof:placetype": "postalcode"
  },
  "geometry": {"coordinates":[-3.21903,55.83836],"type":"Point"}
}
