{
  "type": "Feature",
  "properties": {
    "iso:country":"GB",
    "wof:name":"EH26 0BH",
    "wof:placetype":"postalcode"
},
  "geometry": {"coordinates":[-3.21903025405923,55.83835987969384],"type":"Point"}
}