{
  "type": "Feature",
  "properties": {
    "iso:country":"GB",
    "wof:name":"RM14 1NA",
    "wof:placetype":"postalcode"
},
  "geometry": {"coordinates":[0.26962960790646,51.56817887428532],"type":"Point"}
}