{
  "type": "Feature",
  "properties": {
    "iso:country": "GB",
    "wof:name": "NE4 6RW",
    "wof:placetype": "postalcode"
  },
  "geometry": {"coordinates":[-1.635234,54.96762],"type":"Point"}
}
