{
  "type": "Feature",
  "properties": {
    "iso:country":"GB",
    "wof:name":"E14 6QW",
    "wof:placetype":"postalcode"
},
  "geometry": {"coordinates":[-0.01381808500032,51.5175024069685],"type":"Point"}
}