{
  "type": "Feature",
  "properties": {
    "date:inception_lower": "2020-04-01",
    "date:inception_upper": "2020-04-01",
    "iso:country": "GB",
    "wof:name": "M24 6TR",
    "wof:placetype": "postalcode"
  },
  "geometry": {"coordinates":[-2.203592,53.565566],"type":"Point"}
}
