{
  "type": "Feature",
  "properties": {
    "date:inception_lower": "2020-04-01",
    "date:inception_upper": "2020-04-01",
    "iso:country": "GB",
    "wof:name": "M24 6TR",
    "wof:placetype": "postalcode"
  },
  "geometry": {"coordinates":[-2.199467,53.564764],"type":"Point"}
}
