{
  "type": "Feature",
  "properties": {
    "date:inception_lower": "1980-01-01",
    "date:inception_upper": "1980-01-01",
    "iso:country": "GB",
    "wof:name": "TN30 6DR",
    "wof:placetype": "postalcode"
  },
  "geometry": {"coordinates":[0.69037,51.084574],"type":"Point"}
}
