{
  "type": "Feature",
  "properties": {
    "iso:country": "GB",
    "wof:name": "KY4 8BP",
    "wof:placetype": "postalcode"
  },
  "geometry": {"coordinates":[-3.365765,56.083044],"type":"Point"}
}
