{
  "type": "Feature",
  "properties": {
    "iso:country":"GB",
    "wof:name":"SR3 1XD",
    "wof:placetype":"postalcode"
},
  "geometry": {"coordinates":[-1.40201596775884,54.89280172368736],"type":"Point"}
}