{
  "type": "Feature",
  "properties": {
    "iso:country":"GB",
    "wof:name":"DD8 4QG",
    "wof:placetype":"postalcode"
},
  "geometry": {"coordinates":[-2.99320443987372,56.69723512142845],"type":"Point"}
}