{
  "type": "Feature",
  "properties": {
    "iso:country":"GB",
    "wof:name":"WS8 6AJ",
    "wof:placetype":"postalcode"
},
  "geometry": {"coordinates":[-1.92460446922923,52.64904610040975],"type":"Point"}
}