{
  "type": "Feature",
  "properties": {
    "iso:country":"GB",
    "wof:name":"SK22 1AG",
    "wof:placetype":"postalcode"
},
  "geometry": {"coordinates":[-1.97867468464256,53.37965165366931],"type":"Point"}
}