{
  "type": "Feature",
  "properties": {
    "iso:country": "GB",
    "wof:name": "SK22 1AG",
    "wof:placetype": "postalcode"
  },
  "geometry": {"coordinates":[-1.978869,53.379839],"type":"Point"}
}
