{
  "type": "Feature",
  "properties": {
    "date:inception_lower": "1980-01-01",
    "date:inception_upper": "1980-01-01",
    "iso:country": "GB",
    "wof:name": "EX2 4PR",
    "wof:placetype": "postalcode"
  },
  "geometry": {"coordinates":[-3.519626,50.717542],"type":"Point"}
}
