{
  "type": "Feature",
  "properties": {
    "date:inception_lower":"1995-12-01",
    "date:inception_upper":"1995-12-31",
    "iso:country":"GB",
    "wof:name":"DY4 8JL",
    "wof:placetype":"postalcode"
},
  "geometry": {"coordinates":[-2.072249,52.523433],"type":"Point"}
}