{
  "type": "Feature",
  "properties": {
    "iso:country":"GB",
    "wof:name":"UB1 2BT",
    "wof:placetype":"postalcode"
},
  "geometry": {"coordinates":[-0.37638275821467,51.52038363843575],"type":"Point"}
}