{
  "type": "Feature",
  "properties": {
    "iso:country":"GB",
    "wof:name":"PO9 3RR",
    "wof:placetype":"postalcode"
},
  "geometry": {"coordinates":[-0.98636581343235,50.86514112521665],"type":"Point"}
}