{
  "type": "Feature",
  "properties": {
    "date:inception_lower":"1980-01-01",
    "date:inception_upper":"1980-01-31",
    "iso:country":"GB",
    "wof:name":"BA6 8LN",
    "wof:placetype":"postalcode"
},
  "geometry": {"coordinates":[-2.631998,51.132565],"type":"Point"}
}