{
  "type": "Feature",
  "properties": {
    "iso:country": "GB",
    "wof:name": "BA6 8LN",
    "wof:placetype": "postalcode"
  },
  "geometry": {"coordinates":[-2.631998,51.132565],"type":"Point"}
}
