{
  "type": "Feature",
  "properties": {
    "iso:country":"GB",
    "wof:name":"BA6 8LN",
    "wof:placetype":"postalcode"
},
  "geometry": {"coordinates":[-2.63199552435823,51.13257159356798],"type":"Point"}
}