{
  "type": "Feature",
  "properties": {
    "date:inception_lower": "1980-01-01",
    "date:inception_upper": "1980-01-01",
    "iso:country": "GB",
    "wof:name": "GU4 8JT",
    "wof:placetype": "postalcode"
  },
  "geometry": {"coordinates":[-0.56687,51.210815],"type":"Point"}
}
