{
  "type": "Feature",
  "properties": {
    "iso:country":"GB",
    "wof:name":"WS6 7EL",
    "wof:placetype":"postalcode"
},
  "geometry": {"coordinates":[-2.02653065524668,52.66944650111567],"type":"Point"}
}