{
  "type": "Feature",
  "properties": {
    "iso:country":"GB",
    "wof:name":"NR26 8BH",
    "wof:placetype":"postalcode"
},
  "geometry": {"coordinates":[1.21411861945241,52.94466821042861],"type":"Point"}
}