{
  "type": "Feature",
  "properties": {
    "date:inception_lower": "1980-01-01",
    "date:inception_upper": "1980-01-01",
    "iso:country": "GB",
    "wof:name": "NR26 8BH",
    "wof:placetype": "postalcode"
  },
  "geometry": {"coordinates":[1.214107,52.944698],"type":"Point"}
}
