{
  "type": "Feature",
  "properties": {
    "date:inception_lower":"2009-09-01",
    "date:inception_upper":"2009-09-30",
    "iso:country":"GB",
    "wof:name":"SW6 1BF",
    "wof:placetype":"postalcode"
},
  "geometry": {"coordinates":[-0.19559,51.47947],"type":"Point"}
}