{
  "type": "Feature",
  "properties": {
    "iso:country": "GB",
    "wof:name": "SW6 1BF",
    "wof:placetype": "postalcode"
  },
  "geometry": {"coordinates":[-0.19559,51.47947],"type":"Point"}
}
