{
  "type": "Feature",
  "properties": {
    "iso:country":"GB",
    "wof:name":"SW6 1BF",
    "wof:placetype":"postalcode"
},
  "geometry": {"coordinates":[-0.19558976736331,51.4794699566108],"type":"Point"}
}