{
  "type": "Feature",
  "properties": {
    "iso:country":"GB",
    "wof:name":"M21 8TL",
    "wof:placetype":"postalcode"
},
  "geometry": {"coordinates":[-2.27370814774017,53.4387626130307],"type":"Point"}
}