{
  "type": "Feature",
  "properties": {
    "iso:country":"GB",
    "wof:name":"NE44 6HR",
    "wof:placetype":"postalcode"
},
  "geometry": {"coordinates":[-1.97595784121286,54.94844777352314],"type":"Point"}
}