{
  "type": "Feature",
  "properties": {
    "date:inception_lower": "2021-12-01",
    "date:inception_upper": "2021-12-01",
    "iso:country": "GB",
    "wof:name": "BN18 0ZE",
    "wof:placetype": "postalcode"
  },
  "geometry": {"coordinates":[-0.613428,50.825209],"type":"Point"}
}
