{
  "type": "Feature",
  "properties": {
    "iso:country":"GB",
    "wof:name":"CM1 6QT",
    "wof:placetype":"postalcode"
},
  "geometry": {"coordinates":[0.50541554678785,51.75042053563434],"type":"Point"}
}