{
  "type": "Feature",
  "properties": {
    "iso:country": "GB",
    "wof:name": "SA14 7EQ",
    "wof:placetype": "postalcode"
  },
  "geometry": {"coordinates":[-4.113759,51.812793],"type":"Point"}
}
