{
  "type": "Feature",
  "properties": {
    "date:inception_lower": "1990-02-01",
    "date:inception_upper": "1990-02-01",
    "iso:country": "GB",
    "wof:name": "SA14 7EQ",
    "wof:placetype": "postalcode"
  },
  "geometry": {"coordinates":[-4.113759,51.812793],"type":"Point"}
}
