{
  "type": "Feature",
  "properties": {
    "iso:country":"GB",
    "wof:name":"OX11 9HQ",
    "wof:placetype":"postalcode"
},
  "geometry": {"coordinates":[-1.2051520400404,51.57073598330938],"type":"Point"}
}