{
  "type": "Feature",
  "properties": {
    "iso:country":"GB",
    "wof:name":"SO31 7DZ",
    "wof:placetype":"postalcode"
},
  "geometry": {"coordinates":[-1.28759204258491,50.86395958817436],"type":"Point"}
}