{
  "type": "Feature",
  "properties": {
    "iso:country": "GB",
    "wof:name": "SO31 7DZ",
    "wof:placetype": "postalcode"
  },
  "geometry": {"coordinates":[-1.287582,50.86395],"type":"Point"}
}
