{
  "type": "Feature",
  "properties": {
    "iso:country":"GB",
    "wof:name":"ST5 0GP",
    "wof:placetype":"postalcode"
},
  "geometry": {"coordinates":[-2.21900722621853,53.01718225340187],"type":"Point"}
}