{
  "type": "Feature",
  "properties": {
    "date:inception_lower": "2008-12-01",
    "date:inception_upper": "2008-12-01",
    "iso:country": "GB",
    "wof:name": "ST5 0GP",
    "wof:placetype": "postalcode"
  },
  "geometry": {"coordinates":[-2.219007,53.017182],"type":"Point"}
}
