{
  "type": "Feature",
  "properties": {
    "date:inception_lower": "1980-01-01",
    "date:inception_upper": "1980-01-01",
    "iso:country": "GB",
    "wof:name": "NR28 9EE",
    "wof:placetype": "postalcode"
  },
  "geometry": {"coordinates":[1.394982,52.823014],"type":"Point"}
}
