{
  "type": "Feature",
  "properties": {
    "iso:country": "GB",
    "wof:name": "NR28 9EE",
    "wof:placetype": "postalcode"
  },
  "geometry": {"coordinates":[1.394982,52.823014],"type":"Point"}
}
