{
  "type": "Feature",
  "properties": {
    "iso:country":"GB",
    "wof:name":"NR28 9EE",
    "wof:placetype":"postalcode"
},
  "geometry": {"coordinates":[1.39498232934556,52.82301379474587],"type":"Point"}
}