{
  "type": "Feature",
  "properties": {
    "iso:country":"GB",
    "wof:name":"HD8 8SX",
    "wof:placetype":"postalcode"
},
  "geometry": {"coordinates":[-1.64044367205294,53.57908876257685],"type":"Point"}
}