{
  "type": "Feature",
  "properties": {
    "iso:country": "GB",
    "wof:name": "SK8 7DZ",
    "wof:placetype": "postalcode"
  },
  "geometry": {"coordinates":[-2.182158,53.36951],"type":"Point"}
}
