{
  "type": "Feature",
  "properties": {
    "date:inception_lower": "1980-01-01",
    "date:inception_upper": "1980-01-01",
    "iso:country": "GB",
    "wof:name": "SK8 7DZ",
    "wof:placetype": "postalcode"
  },
  "geometry": {"coordinates":[-2.182158,53.36951],"type":"Point"}
}
