{
  "type": "Feature",
  "properties": {
    "iso:country":"GB",
    "wof:name":"HP14 4NX",
    "wof:placetype":"postalcode"
},
  "geometry": {"coordinates":[-0.75336302798282,51.66201222128215],"type":"Point"}
}