{
  "type": "Feature",
  "properties": {
    "date:inception_lower":"1980-01-01",
    "date:inception_upper":"1980-01-31",
    "iso:country":"GB",
    "wof:name":"BA3 2LE",
    "wof:placetype":"postalcode"
},
  "geometry": {"coordinates":[-2.483438,51.285978],"type":"Point"}
}