{
  "type": "Feature",
  "properties": {
    "iso:country":"GB",
    "wof:name":"BA3 2LE",
    "wof:placetype":"postalcode"
},
  "geometry": {"coordinates":[-2.48336609842898,51.28602742515854],"type":"Point"}
}