{
  "type": "Feature",
  "properties": {
    "iso:country": "GB",
    "wof:name": "BA3 2LE",
    "wof:placetype": "postalcode"
  },
  "geometry": {"coordinates":[-2.483438,51.285978],"type":"Point"}
}
