{
  "type": "Feature",
  "properties": {
    "iso:country":"GB",
    "wof:name":"ST6 1HB",
    "wof:placetype":"postalcode"
},
  "geometry": {"coordinates":[-2.18617072866467,53.04879908189411],"type":"Point"}
}