{
  "type": "Feature",
  "properties": {
    "iso:country": "GB",
    "wof:name": "LE7 9TZ",
    "wof:placetype": "postalcode"
  },
  "geometry": {"coordinates":[-1.03831,52.636333],"type":"Point"}
}
