{
  "type": "Feature",
  "properties": {
    "iso:country":"GB",
    "wof:name":"GL14 2SH",
    "wof:placetype":"postalcode"
},
  "geometry": {"coordinates":[-2.49907397549526,51.82406418091144],"type":"Point"}
}