{
  "type": "Feature",
  "properties": {
    "iso:country": "GB",
    "wof:name": "CV22 6DF",
    "wof:placetype": "postalcode"
  },
  "geometry": {"coordinates":[-1.279968,52.363111],"type":"Point"}
}
