{
  "type": "Feature",
  "properties": {
    "iso:country":"GB",
    "wof:name":"BL8 1LP",
    "wof:placetype":"postalcode"
},
  "geometry": {"coordinates":[-2.31358939722649,53.59855943817604],"type":"Point"}
}