{
  "type": "Feature",
  "properties": {
    "iso:country":"GB",
    "wof:name":"TW1 4RY",
    "wof:placetype":"postalcode"
},
  "geometry": {"coordinates":[-0.33190227657006,51.43943992067388],"type":"Point"}
}