{
  "type": "Feature",
  "properties": {
    "iso:country":"GB",
    "wof:name":"PO11 0BH",
    "wof:placetype":"postalcode"
},
  "geometry": {"coordinates":[-0.99072986417778,50.7866898910263],"type":"Point"}
}