{
  "type": "Feature",
  "properties": {
    "date:inception_lower": "2011-10-01",
    "date:inception_upper": "2011-10-01",
    "iso:country": "GB",
    "wof:name": "LL31 9LJ",
    "wof:placetype": "postalcode"
  },
  "geometry": {"coordinates":[-3.804181,53.287838],"type":"Point"}
}
