{
  "type": "Feature",
  "properties": {
    "iso:country":"GB",
    "wof:name":"LL31 9LJ",
    "wof:placetype":"postalcode"
},
  "geometry": {"coordinates":[-3.804180570235,53.28783755603933],"type":"Point"}
}