{
  "type": "Feature",
  "properties": {
    "iso:country": "GB",
    "wof:name": "LL31 9LJ",
    "wof:placetype": "postalcode"
  },
  "geometry": {"coordinates":[-3.804181,53.287838],"type":"Point"}
}
