{
  "type": "Feature",
  "properties": {
    "iso:country":"GB",
    "wof:name":"CT9 1DS",
    "wof:placetype":"postalcode"
},
  "geometry": {"coordinates":[1.37991800497072,51.38885090047552],"type":"Point"}
}