{
  "type": "Feature",
  "properties": {
    "iso:country":"GB",
    "wof:name":"ST9 0LS",
    "wof:placetype":"postalcode"
},
  "geometry": {"coordinates":[-2.0993330425658,53.02741949005671],"type":"Point"}
}