{
  "type": "Feature",
  "properties": {
    "date:inception_lower": "1980-01-01",
    "date:inception_upper": "1980-01-01",
    "iso:country": "GB",
    "wof:name": "CA28 9RH",
    "wof:placetype": "postalcode"
  },
  "geometry": {"coordinates":[-3.579094,54.523823],"type":"Point"}
}
