{
  "type": "Feature",
  "properties": {
    "iso:country":"GB",
    "wof:name":"CV1 5AF",
    "wof:placetype":"postalcode"
},
  "geometry": {"coordinates":[-1.4961995603103,52.41672423349569],"type":"Point"}
}