{
  "type": "Feature",
  "properties": {
    "iso:country": "GB",
    "wof:name": "CV1 5AF",
    "wof:placetype": "postalcode"
  },
  "geometry": {"coordinates":[-1.4962,52.416724],"type":"Point"}
}
