{
  "type": "Feature",
  "properties": {
    "iso:country":"GB",
    "wof:name":"W1U 4RD",
    "wof:placetype":"postalcode"
},
  "geometry": {"coordinates":[-0.15205928599395,51.51995973319871],"type":"Point"}
}