{
  "type": "Feature",
  "properties": {
    "iso:country":"GB",
    "wof:name":"PL5 2EX",
    "wof:placetype":"postalcode"
},
  "geometry": {"coordinates":[-4.18207969593765,50.41202976992901],"type":"Point"}
}