{
  "type": "Feature",
  "properties": {
    "iso:country": "GB",
    "wof:name": "RH16 2EE",
    "wof:placetype": "postalcode"
  },
  "geometry": {"coordinates":[-0.084167,51.008451],"type":"Point"}
}
