{
  "type": "Feature",
  "properties": {
    "iso:country":"GB",
    "wof:name":"RH16 2EE",
    "wof:placetype":"postalcode"
},
  "geometry": {"coordinates":[-0.08416683739525,51.00845057910456],"type":"Point"}
}