{
  "type": "Feature",
  "properties": {
    "iso:country": "GB",
    "wof:name": "RH10 6SD",
    "wof:placetype": "postalcode"
  },
  "geometry": {"coordinates":[-0.165098,51.111534],"type":"Point"}
}
