{
  "type": "Feature",
  "properties": {
    "iso:country":"GB",
    "wof:name":"DN3 2EF",
    "wof:placetype":"postalcode"
},
  "geometry": {"coordinates":[-1.05517031303971,53.54095150287549],"type":"Point"}
}