{
  "type": "Feature",
  "properties": {
    "iso:country": "GB",
    "wof:name": "DN3 2EF",
    "wof:placetype": "postalcode"
  },
  "geometry": {"coordinates":[-1.05517,53.540951],"type":"Point"}
}
