{
  "type": "Feature",
  "properties": {
    "date:inception_lower":"1993-08-01",
    "date:inception_upper":"1993-08-31",
    "iso:country":"GB",
    "wof:name":"RG4 8PY",
    "wof:placetype":"postalcode"
},
  "geometry": {"coordinates":[-0.971775,51.472955],"type":"Point"}
}