{
  "type": "Feature",
  "properties": {
    "iso:country":"GB",
    "wof:name":"RG4 8PY",
    "wof:placetype":"postalcode"
},
  "geometry": {"coordinates":[-0.9717751533298,51.47295481469509],"type":"Point"}
}