{
  "type": "Feature",
  "properties": {
    "iso:country":"GB",
    "wof:name":"LU2 0PN",
    "wof:placetype":"postalcode"
},
  "geometry": {"coordinates":[-0.39513133696998,51.8881881301343],"type":"Point"}
}