{
  "type": "Feature",
  "properties": {
    "iso:country": "GB",
    "wof:name": "NE23 6PX",
    "wof:placetype": "postalcode"
  },
  "geometry": {"coordinates":[-1.588125,55.073003],"type":"Point"}
}
