{
  "type": "Feature",
  "properties": {
    "date:inception_lower": "1980-01-01",
    "date:inception_upper": "1980-01-01",
    "iso:country": "GB",
    "wof:name": "PE15 9QA",
    "wof:placetype": "postalcode"
  },
  "geometry": {"coordinates":[0.080895,52.534529],"type":"Point"}
}
