{
  "type": "Feature",
  "properties": {
    "date:inception_lower": "1980-01-01",
    "date:inception_upper": "1980-01-01",
    "iso:country": "GB",
    "wof:name": "NR14 6SP",
    "wof:placetype": "postalcode"
  },
  "geometry": {"coordinates":[1.505408,52.52275],"type":"Point"}
}
