{
  "type": "Feature",
  "properties": {
    "date:inception_lower": "1995-01-01",
    "date:inception_upper": "1995-01-01",
    "iso:country": "GB",
    "wof:name": "CT19 5JZ",
    "wof:placetype": "postalcode"
  },
  "geometry": {"coordinates":[1.163399,51.093525],"type":"Point"}
}
