{
  "type": "Feature",
  "properties": {
    "iso:country":"GB",
    "wof:name":"CT19 5JZ",
    "wof:placetype":"postalcode"
},
  "geometry": {"coordinates":[1.16336794663112,51.09352174293263],"type":"Point"}
}