{
  "type": "Feature",
  "properties": {
    "iso:country":"GB",
    "wof:name":"HA2 8LE",
    "wof:placetype":"postalcode"
},
  "geometry": {"coordinates":[-0.35276523921628,51.56212905763315],"type":"Point"}
}