{
  "type": "Feature",
  "properties": {
    "iso:country":"GB",
    "wof:name":"HU4 7SQ",
    "wof:placetype":"postalcode"
},
  "geometry": {"coordinates":[-0.41225249293148,53.74852799539937],"type":"Point"}
}