{
  "type": "Feature",
  "properties": {
    "iso:country": "GB",
    "wof:name": "G1 5NF",
    "wof:placetype": "postalcode"
  },
  "geometry": {"coordinates":[-4.246373,55.85526],"type":"Point"}
}
