{
  "type": "Feature",
  "properties": {
    "iso:country":"GB",
    "wof:name":"SK13 7QH",
    "wof:placetype":"postalcode"
},
  "geometry": {"coordinates":[-1.95576037149137,53.45709058493692],"type":"Point"}
}