{
  "type": "Feature",
  "properties": {
    "iso:country":"GB",
    "wof:name":"SW17 0QH",
    "wof:placetype":"postalcode"
},
  "geometry": {"coordinates":[-0.17198568494936,51.42831441127741],"type":"Point"}
}