{
  "type": "Feature",
  "properties": {
    "iso:country":"GB",
    "wof:name":"SO51 8HY",
    "wof:placetype":"postalcode"
},
  "geometry": {"coordinates":[-1.50460079314521,50.98837695934529],"type":"Point"}
}