{
  "type": "Feature",
  "properties": {
    "iso:country":"GB",
    "wof:name":"HA1 4BT",
    "wof:placetype":"postalcode"
},
  "geometry": {"coordinates":[-0.35156921162271,51.57685047662638],"type":"Point"}
}