{
  "type": "Feature",
  "properties": {
    "iso:country":"GB",
    "wof:name":"ML4 3HF",
    "wof:placetype":"postalcode"
},
  "geometry": {"coordinates":[-4.03704689038186,55.81801405361204],"type":"Point"}
}