{
  "type": "Feature",
  "properties": {
    "iso:country": "GB",
    "wof:name": "ML4 3HF",
    "wof:placetype": "postalcode"
  },
  "geometry": {"coordinates":[-4.037047,55.818014],"type":"Point"}
}
