{
  "type": "Feature",
  "properties": {
    "iso:country":"GB",
    "wof:name":"BS4 2QG",
    "wof:placetype":"postalcode"
},
  "geometry": {"coordinates":[-2.56658784207216,51.43470180791301],"type":"Point"}
}