{
  "type": "Feature",
  "properties": {
    "date:inception_lower":"1980-01-01",
    "date:inception_upper":"1980-01-31",
    "iso:country":"GB",
    "wof:name":"IP7 5QT",
    "wof:placetype":"postalcode"
},
  "geometry": {"coordinates":[0.961747,52.007841],"type":"Point"}
}