{
  "type": "Feature",
  "properties": {
    "iso:country":"GB",
    "wof:name":"IP7 5QT",
    "wof:placetype":"postalcode"
},
  "geometry": {"coordinates":[0.96174739890637,52.00784109177768],"type":"Point"}
}