{
  "type": "Feature",
  "properties": {
    "iso:country": "GB",
    "wof:name": "IP7 5QT",
    "wof:placetype": "postalcode"
  },
  "geometry": {"coordinates":[0.961792,52.007845],"type":"Point"}
}
