{
  "type": "Feature",
  "properties": {
    "date:inception_lower": "1981-06-01",
    "date:inception_upper": "1981-06-01",
    "iso:country": "GB",
    "wof:name": "SW2 5JZ",
    "wof:placetype": "postalcode"
  },
  "geometry": {"coordinates":[-0.125877,51.457668],"type":"Point"}
}
