{
  "type": "Feature",
  "properties": {
    "iso:country": "GB",
    "wof:name": "SW2 5JZ",
    "wof:placetype": "postalcode"
  },
  "geometry": {"coordinates":[-0.125877,51.457668],"type":"Point"}
}
