{
  "type": "Feature",
  "properties": {
    "iso:country":"GB",
    "wof:name":"SW2 5JZ",
    "wof:placetype":"postalcode"
},
  "geometry": {"coordinates":[-0.12590239863477,51.45766693580063],"type":"Point"}
}