{
  "type": "Feature",
  "properties": {
    "iso:country":"GB",
    "wof:name":"SG1 3HW",
    "wof:placetype":"postalcode"
},
  "geometry": {"coordinates":[-0.2092211769988,51.912184562123],"type":"Point"}
}