{
  "type": "Feature",
  "properties": {
    "iso:country": "GB",
    "wof:name": "SG1 3HW",
    "wof:placetype": "postalcode"
  },
  "geometry": {"coordinates":[-0.209221,51.912185],"type":"Point"}
}
