{
  "type": "Feature",
  "properties": {
    "iso:country": "GB",
    "wof:name": "CM2 8XJ",
    "wof:placetype": "postalcode"
  },
  "geometry": {"coordinates":[0.476861,51.713129],"type":"Point"}
}
