{
  "type": "Feature",
  "properties": {
    "iso:country":"GB",
    "wof:name":"CM2 8XJ",
    "wof:placetype":"postalcode"
},
  "geometry": {"coordinates":[0.47686072538204,51.71312927163564],"type":"Point"}
}