{
  "type": "Feature",
  "properties": {
    "date:inception_lower": "1980-01-01",
    "date:inception_upper": "1980-01-01",
    "iso:country": "GB",
    "wof:name": "CM2 8XJ",
    "wof:placetype": "postalcode"
  },
  "geometry": {"coordinates":[0.476861,51.713129],"type":"Point"}
}
