{
  "type": "Feature",
  "properties": {
    "iso:country":"GB",
    "wof:name":"SW18 3ET",
    "wof:placetype":"postalcode"
},
  "geometry": {"coordinates":[-0.17844839926923,51.44413403970254],"type":"Point"}
}