{
  "type": "Feature",
  "properties": {
    "date:inception_lower": "1994-12-01",
    "date:inception_upper": "1994-12-01",
    "iso:country": "GB",
    "wof:name": "E8 2LU",
    "wof:placetype": "postalcode"
  },
  "geometry": {"coordinates":[-0.074032,51.549414],"type":"Point"}
}
