{
  "type": "Feature",
  "properties": {
    "iso:country":"GB",
    "wof:name":"E8 2LU",
    "wof:placetype":"postalcode"
},
  "geometry": {"coordinates":[-0.07403189776265,51.54941404079805],"type":"Point"}
}