{
  "type": "Feature",
  "properties": {
    "date:inception_lower": "1980-01-01",
    "date:inception_upper": "1980-01-01",
    "iso:country": "GB",
    "wof:name": "HP4 2PB",
    "wof:placetype": "postalcode"
  },
  "geometry": {"coordinates":[-0.552882,51.761824],"type":"Point"}
}
