{
  "type": "Feature",
  "properties": {
    "iso:country":"GB",
    "wof:name":"L28 0QG",
    "wof:placetype":"postalcode"
},
  "geometry": {"coordinates":[-2.87644449461207,53.43448438037155],"type":"Point"}
}