{
  "type": "Feature",
  "properties": {
    "iso:country": "GB",
    "wof:name": "WA8 0EE",
    "wof:placetype": "postalcode"
  },
  "geometry": {"coordinates":[-2.735566,53.350599],"type":"Point"}
}
