{
  "type": "Feature",
  "properties": {
    "iso:country":"GB",
    "wof:name":"SW9 0EB",
    "wof:placetype":"postalcode"
},
  "geometry": {"coordinates":[-0.11668363745332,51.47670041363053],"type":"Point"}
}