{
  "type": "Feature",
  "properties": {
    "iso:country":"GB",
    "wof:name":"SW16 1JF",
    "wof:placetype":"postalcode"
},
  "geometry": {"coordinates":[-0.13224450724185,51.43559237699556],"type":"Point"}
}