{
  "type": "Feature",
  "properties": {
    "iso:country":"GB",
    "wof:name":"N18 1PT",
    "wof:placetype":"postalcode"
},
  "geometry": {"coordinates":[-0.07822989966919,51.6181584697645],"type":"Point"}
}