{
  "type": "Feature",
  "properties": {
    "iso:country": "GB",
    "wof:name": "SG8 5EF",
    "wof:placetype": "postalcode"
  },
  "geometry": {"coordinates":[-0.026778,52.060658],"type":"Point"}
}
