{
  "type": "Feature",
  "properties": {
    "iso:country":"GB",
    "wof:name":"SG8 5EF",
    "wof:placetype":"postalcode"
},
  "geometry": {"coordinates":[-0.02686542578806,52.06063966151659],"type":"Point"}
}