{
  "type": "Feature",
  "properties": {
    "iso:country":"GB",
    "wof:name":"EH22 3EH",
    "wof:placetype":"postalcode"
},
  "geometry": {"coordinates":[-3.08741138378911,55.88831308697323],"type":"Point"}
}