{
  "type": "Feature",
  "properties": {
    "iso:country":"GB",
    "wof:name":"KY7 4AD",
    "wof:placetype":"postalcode"
},
  "geometry": {"coordinates":[-3.14838117941534,56.17705031691106],"type":"Point"}
}