{
  "type": "Feature",
  "properties": {
    "date:inception_lower": "2006-07-01",
    "date:inception_upper": "2006-07-01",
    "iso:country": "GB",
    "wof:name": "KY7 4AD",
    "wof:placetype": "postalcode"
  },
  "geometry": {"coordinates":[-3.148383,56.177043],"type":"Point"}
}
