{
  "type": "Feature",
  "properties": {
    "iso:country": "GB",
    "wof:name": "KY7 4AD",
    "wof:placetype": "postalcode"
  },
  "geometry": {"coordinates":[-3.150107,56.177054],"type":"Point"}
}
