{
  "type": "Feature",
  "properties": {
    "iso:country": "GB",
    "wof:name": "KY7 4AD",
    "wof:placetype": "postalcode"
  },
  "geometry": {"coordinates":[-3.148383,56.177043],"type":"Point"}
}
