{
  "type": "Feature",
  "properties": {
    "date:inception_lower": "2003-02-01",
    "date:inception_upper": "2003-02-01",
    "iso:country": "GB",
    "wof:name": "SM2 7WQ",
    "wof:placetype": "postalcode"
  },
  "geometry": {"coordinates":[-0.192999,51.359918],"type":"Point"}
}
