{
  "type": "Feature",
  "properties": {
    "iso:country":"GB",
    "wof:name":"DE3 9DW",
    "wof:placetype":"postalcode"
},
  "geometry": {"coordinates":[-1.52779276935855,52.91260363156868],"type":"Point"}
}