{
  "type": "Feature",
  "properties": {
    "iso:country":"GB",
    "wof:name":"TF8 7AS",
    "wof:placetype":"postalcode"
},
  "geometry": {"coordinates":[-2.48872972511727,52.62909256186902],"type":"Point"}
}