{
  "type": "Feature",
  "properties": {
    "date:inception_lower":"1980-01-01",
    "date:inception_upper":"1980-01-31",
    "iso:country":"GB",
    "wof:name":"TF8 7AS",
    "wof:placetype":"postalcode"
},
  "geometry": {"coordinates":[-2.48873,52.629093],"type":"Point"}
}