{
  "type": "Feature",
  "properties": {
    "date:inception_lower": "2004-11-01",
    "date:inception_upper": "2004-11-01",
    "iso:country": "GB",
    "wof:name": "S6 1SR",
    "wof:placetype": "postalcode"
  },
  "geometry": {"coordinates":[-1.520136,53.416973],"type":"Point"}
}
