{
  "type": "Feature",
  "properties": {
    "date:inception_lower": "1980-01-01",
    "date:inception_upper": "1980-01-01",
    "iso:country": "GB",
    "wof:name": "PE7 2AQ",
    "wof:placetype": "postalcode"
  },
  "geometry": {"coordinates":[-0.114965,52.556737],"type":"Point"}
}
