{
  "type": "Feature",
  "properties": {
    "iso:country":"GB",
    "wof:name":"PE7 2AQ",
    "wof:placetype":"postalcode"
},
  "geometry": {"coordinates":[-0.11496516755485,52.55673721195382],"type":"Point"}
}