{
  "type": "Feature",
  "properties": {
    "iso:country":"GB",
    "wof:name":"TF2 7DQ",
    "wof:placetype":"postalcode"
},
  "geometry": {"coordinates":[-2.45445780987843,52.71497317996761],"type":"Point"}
}