{
  "type": "Feature",
  "properties": {
    "iso:country": "GB",
    "wof:name": "TF2 7DQ",
    "wof:placetype": "postalcode"
  },
  "geometry": {"coordinates":[-2.454458,52.714973],"type":"Point"}
}
