{
  "type": "Feature",
  "properties": {
    "iso:country":"GB",
    "wof:name":"CM3 4HL",
    "wof:placetype":"postalcode"
},
  "geometry": {"coordinates":[0.59142094205962,51.67596120880225],"type":"Point"}
}