{
  "type": "Feature",
  "properties": {
    "date:inception_lower": "1980-01-01",
    "date:inception_upper": "1980-01-01",
    "iso:country": "GB",
    "wof:name": "CM3 4HL",
    "wof:placetype": "postalcode"
  },
  "geometry": {"coordinates":[0.591421,51.675961],"type":"Point"}
}
