{
  "type": "Feature",
  "properties": {
    "iso:country":"GB",
    "wof:name":"SO24 9HF",
    "wof:placetype":"postalcode"
},
  "geometry": {"coordinates":[-1.1711643649693,51.08617740326689],"type":"Point"}
}