{
  "type": "Feature",
  "properties": {
    "iso:country": "GB",
    "wof:name": "SO24 9HF",
    "wof:placetype": "postalcode"
  },
  "geometry": {"coordinates":[-1.171164,51.086177],"type":"Point"}
}
