{
  "type": "Feature",
  "properties": {
    "date:inception_lower": "2019-09-01",
    "date:inception_upper": "2019-09-01",
    "iso:country": "GB",
    "wof:name": "SE17 3FH",
    "wof:placetype": "postalcode"
  },
  "geometry": {"coordinates":[-0.096781,51.487882],"type":"Point"}
}
