{
  "type": "Feature",
  "properties": {
    "iso:country":"GB",
    "wof:name":"EX34 9NN",
    "wof:placetype":"postalcode"
},
  "geometry": {"coordinates":[-4.11733065462864,51.20880608715176],"type":"Point"}
}