{
  "type": "Feature",
  "properties": {
    "iso:country": "GB",
    "wof:name": "M46 9AQ",
    "wof:placetype": "postalcode"
  },
  "geometry": {"coordinates":[-2.47904,53.517781],"type":"Point"}
}
