{
  "type": "Feature",
  "properties": {
    "iso:country":"GB",
    "wof:name":"OX16 5TU",
    "wof:placetype":"postalcode"
},
  "geometry": {"coordinates":[-1.32690431070334,52.05761127082656],"type":"Point"}
}