{
  "type": "Feature",
  "properties": {
    "iso:country":"GB",
    "wof:name":"L25 9NQ",
    "wof:placetype":"postalcode"
},
  "geometry": {"coordinates":[-2.85301894837367,53.37339508366134],"type":"Point"}
}