{
  "type": "Feature",
  "properties": {
    "date:inception_lower": "2018-01-01",
    "date:inception_upper": "2018-01-01",
    "iso:country": "GB",
    "wof:name": "RG2 9TG",
    "wof:placetype": "postalcode"
  },
  "geometry": {"coordinates":[-0.88664,51.387474],"type":"Point"}
}
