{
  "type": "Feature",
  "properties": {
    "iso:country":"GB",
    "wof:name":"NN11 8AZ",
    "wof:placetype":"postalcode"
},
  "geometry": {"coordinates":[-1.17574717138409,52.27984461386881],"type":"Point"}
}