{
  "type": "Feature",
  "properties": {
    "iso:country":"GB",
    "wof:name":"LS29 7DB",
    "wof:placetype":"postalcode"
},
  "geometry": {"coordinates":[-1.74500950989354,53.91658898707711],"type":"Point"}
}