{
  "type": "Feature",
  "properties": {
    "iso:country":"GB",
    "wof:name":"UB8 2PX",
    "wof:placetype":"postalcode"
},
  "geometry": {"coordinates":[-0.47786451444413,51.5365543254749],"type":"Point"}
}