{
  "type": "Feature",
  "properties": {
    "iso:country":"GB",
    "wof:name":"CT5 1HA",
    "wof:placetype":"postalcode"
},
  "geometry": {"coordinates":[1.02817669934874,51.36187797349767],"type":"Point"}
}