{
  "type": "Feature",
  "properties": {
    "date:inception_lower":"1996-06-01",
    "date:inception_upper":"1996-06-30",
    "iso:country":"GB",
    "wof:name":"AB41 9AB",
    "wof:placetype":"postalcode"
},
  "geometry": {"coordinates":[-2.079462,57.364299],"type":"Point"}
}