{
  "type": "Feature",
  "properties": {
    "iso:country":"GB",
    "wof:name":"AB41 9AB",
    "wof:placetype":"postalcode"
},
  "geometry": {"coordinates":[-2.07946254056426,57.36429939608991],"type":"Point"}
}