{
  "type": "Feature",
  "properties": {
    "iso:country":"GB",
    "wof:name":"OX4 7YA",
    "wof:placetype":"postalcode"
},
  "geometry": {"coordinates":[-1.19995901502542,51.71030192116498],"type":"Point"}
}