{
  "type": "Feature",
  "properties": {
    "iso:country":"GB",
    "wof:name":"TW9 1XD",
    "wof:placetype":"postalcode"
},
  "geometry": {"coordinates":[-0.28916237839805,51.4619345032927],"type":"Point"}
}