{
  "type": "Feature",
  "properties": {
    "iso:country":"GB",
    "wof:name":"N13 4UY",
    "wof:placetype":"postalcode"
},
  "geometry": {"coordinates":[-0.11181786041851,51.61183334362611],"type":"Point"}
}