{
  "type": "Feature",
  "properties": {
    "iso:country":"GB",
    "wof:name":"KA19 7JJ",
    "wof:placetype":"postalcode"
},
  "geometry": {"coordinates":[-4.64644080765271,55.37454053698389],"type":"Point"}
}