{
  "type": "Feature",
  "properties": {
    "iso:country": "GB",
    "wof:name": "KA19 7JJ",
    "wof:placetype": "postalcode"
  },
  "geometry": {"coordinates":[-4.646441,55.374541],"type":"Point"}
}
