{
  "type": "Feature",
  "properties": {
    "iso:country": "GB",
    "wof:name": "AB15 9QL",
    "wof:placetype": "postalcode"
  },
  "geometry": {"coordinates":[-2.18673,57.124316],"type":"Point"}
}
