{
  "type": "Feature",
  "properties": {
    "iso:country":"GB",
    "wof:name":"AB15 9QL",
    "wof:placetype":"postalcode"
},
  "geometry": {"coordinates":[-2.18673043104304,57.12431570463308],"type":"Point"}
}