{
  "type": "Feature",
  "properties": {
    "iso:country":"GB",
    "wof:name":"BR6 9HL",
    "wof:placetype":"postalcode"
},
  "geometry": {"coordinates":[0.09875400829777,51.36624190854742],"type":"Point"}
}