{
  "type": "Feature",
  "properties": {
    "iso:country":"GB",
    "wof:name":"SY23 3ET",
    "wof:placetype":"postalcode"
},
  "geometry": {"coordinates":[-3.95880024595588,52.44152131013942],"type":"Point"}
}