{
  "type": "Feature",
  "properties": {
    "iso:country":"GB",
    "wof:name":"SW11 2JL",
    "wof:placetype":"postalcode"
},
  "geometry": {"coordinates":[-0.16376187534147,51.46694384418075],"type":"Point"}
}