{
  "type": "Feature",
  "properties": {
    "iso:country":"GB",
    "wof:name":"M8 9DW",
    "wof:placetype":"postalcode"
},
  "geometry": {"coordinates":[-2.2457292934988,53.50225516350034],"type":"Point"}
}