{
  "type": "Feature",
  "properties": {
    "iso:country": "GB",
    "wof:name": "BB4 7AL",
    "wof:placetype": "postalcode"
  },
  "geometry": {"coordinates":[-2.252648,53.691768],"type":"Point"}
}
