{
  "type": "Feature",
  "properties": {
    "iso:country":"GB",
    "wof:name":"BB4 7AL",
    "wof:placetype":"postalcode"
},
  "geometry": {"coordinates":[-2.2526477723996,53.69176769327348],"type":"Point"}
}