{
  "type": "Feature",
  "properties": {
    "date:inception_lower": "1995-01-01",
    "date:inception_upper": "1995-01-01",
    "iso:country": "GB",
    "wof:name": "BB4 7AL",
    "wof:placetype": "postalcode"
  },
  "geometry": {"coordinates":[-2.252648,53.691768],"type":"Point"}
}
