{
  "type": "Feature",
  "properties": {
    "iso:country":"GB",
    "wof:name":"EX10 0LA",
    "wof:placetype":"postalcode"
},
  "geometry": {"coordinates":[-3.30664832963972,50.68002371596891],"type":"Point"}
}