{
  "type": "Feature",
  "properties": {
    "iso:country":"GB",
    "wof:name":"PE33 0JE",
    "wof:placetype":"postalcode"
},
  "geometry": {"coordinates":[0.39050363649881,52.67314200984678],"type":"Point"}
}