{
  "type": "Feature",
  "properties": {
    "iso:country":"GB",
    "wof:name":"BS40 7BY",
    "wof:placetype":"postalcode"
},
  "geometry": {"coordinates":[-2.71248975026455,51.32468210771157],"type":"Point"}
}