{
  "type": "Feature",
  "properties": {
    "date:inception_lower": "2012-10-01",
    "date:inception_upper": "2012-10-01",
    "iso:country": "GB",
    "wof:name": "BS40 7BY",
    "wof:placetype": "postalcode"
  },
  "geometry": {"coordinates":[-2.71249,51.324682],"type":"Point"}
}
