{
  "type": "Feature",
  "properties": {
    "iso:country":"GB",
    "wof:name":"NN6 7WE",
    "wof:placetype":"postalcode"
},
  "geometry": {"coordinates":[-1.0899377830971,52.29778013052763],"type":"Point"}
}