{
  "type": "Feature",
  "properties": {
    "date:inception_lower": "1980-01-01",
    "date:inception_upper": "1980-01-01",
    "iso:country": "GB",
    "wof:name": "HA2 6QE",
    "wof:placetype": "postalcode"
  },
  "geometry": {"coordinates":[-0.348884,51.59337],"type":"Point"}
}
