{
  "type": "Feature",
  "properties": {
    "iso:country":"GB",
    "wof:name":"HA2 6QE",
    "wof:placetype":"postalcode"
},
  "geometry": {"coordinates":[-0.34886389154793,51.59335805755229],"type":"Point"}
}