{
  "type": "Feature",
  "properties": {
    "iso:country":"GB",
    "wof:name":"LL11 3PL",
    "wof:placetype":"postalcode"
},
  "geometry": {"coordinates":[-3.07424234637596,53.05851197769783],"type":"Point"}
}