{
  "type": "Feature",
  "properties": {
    "date:inception_lower": "1993-01-01",
    "date:inception_upper": "1993-01-01",
    "iso:country": "GB",
    "wof:name": "ME2 1NJ",
    "wof:placetype": "postalcode"
  },
  "geometry": {"coordinates":[0.44772,51.349279],"type":"Point"}
}
