{
  "type": "Feature",
  "properties": {
    "iso:country":"GB",
    "wof:name":"ME2 1NJ",
    "wof:placetype":"postalcode"
},
  "geometry": {"coordinates":[0.44772007120536,51.34927915627671],"type":"Point"}
}