{
  "type": "Feature",
  "properties": {
    "iso:country":"GB",
    "wof:name":"SE23 3LU",
    "wof:placetype":"postalcode"
},
  "geometry": {"coordinates":[-0.05358610381462,51.4413718439467],"type":"Point"}
}