{
  "type": "Feature",
  "properties": {
    "iso:country":"GB",
    "wof:name":"G62 6QQ",
    "wof:placetype":"postalcode"
},
  "geometry": {"coordinates":[-4.32062504695164,55.93961427984119],"type":"Point"}
}