{
  "type": "Feature",
  "properties": {
    "iso:country":"GB",
    "wof:name":"CM8 2QR",
    "wof:placetype":"postalcode"
},
  "geometry": {"coordinates":[0.63154297784989,51.81567886861418],"type":"Point"}
}