{
  "type": "Feature",
  "properties": {
    "iso:country": "GB",
    "wof:name": "CM8 2QR",
    "wof:placetype": "postalcode"
  },
  "geometry": {"coordinates":[0.631543,51.815679],"type":"Point"}
}
