{
  "type": "Feature",
  "properties": {
    "iso:country": "GB",
    "wof:name": "RG41 5LU",
    "wof:placetype": "postalcode"
  },
  "geometry": {"coordinates":[-0.877047,51.429653],"type":"Point"}
}
