{
  "type": "Feature",
  "properties": {
    "date:inception_lower": "1995-07-01",
    "date:inception_upper": "1995-07-01",
    "iso:country": "GB",
    "wof:name": "RG41 5LU",
    "wof:placetype": "postalcode"
  },
  "geometry": {"coordinates":[-0.877047,51.429653],"type":"Point"}
}
