{
  "type": "Feature",
  "properties": {
    "date:inception_lower": "2013-03-01",
    "date:inception_upper": "2013-03-01",
    "iso:country": "GB",
    "wof:name": "WN3 6GN",
    "wof:placetype": "postalcode"
  },
  "geometry": {"coordinates":[-2.669139,53.52893],"type":"Point"}
}
