{
  "type": "Feature",
  "properties": {
    "date:inception_lower": "2021-01-01",
    "date:inception_upper": "2021-01-01",
    "iso:country": "GB",
    "wof:name": "TS11 6HF",
    "wof:placetype": "postalcode"
  },
  "geometry": {"coordinates":[-1.028397,54.591271],"type":"Point"}
}
