{
  "type": "Feature",
  "properties": {
    "iso:country":"GB",
    "wof:name":"BN17 6SU",
    "wof:placetype":"postalcode"
},
  "geometry": {"coordinates":[-0.52295873492406,50.81729110783387],"type":"Point"}
}