{
  "type": "Feature",
  "properties": {
    "date:inception_lower":"1990-07-01",
    "date:inception_upper":"1990-07-31",
    "iso:country":"GB",
    "wof:name":"BN17 6SU",
    "wof:placetype":"postalcode"
},
  "geometry": {"coordinates":[-0.522959,50.817291],"type":"Point"}
}