{
  "type": "Feature",
  "properties": {
    "iso:country":"GB",
    "wof:name":"FY8 4UA",
    "wof:placetype":"postalcode"
},
  "geometry": {"coordinates":[-2.98952877608004,53.75553861322842],"type":"Point"}
}