{
  "type": "Feature",
  "properties": {
    "date:inception_lower": "1997-12-01",
    "date:inception_upper": "1997-12-01",
    "iso:country": "GB",
    "wof:name": "BS37 4BT",
    "wof:placetype": "postalcode"
  },
  "geometry": {"coordinates":[-2.426044,51.538637],"type":"Point"}
}
