{
  "type": "Feature",
  "properties": {
    "iso:country":"GB",
    "wof:name":"BS37 4BT",
    "wof:placetype":"postalcode"
},
  "geometry": {"coordinates":[-2.42604356615152,51.53863688378238],"type":"Point"}
}