{
  "type": "Feature",
  "properties": {
    "iso:country":"GB",
    "wof:name":"CM17 0HA",
    "wof:placetype":"postalcode"
},
  "geometry": {"coordinates":[0.13978925486227,51.78391509102661],"type":"Point"}
}