{
  "type": "Feature",
  "properties": {
    "iso:country": "GB",
    "wof:name": "SP10 3EA",
    "wof:placetype": "postalcode"
  },
  "geometry": {"coordinates":[-1.498384,51.208056],"type":"Point"}
}
