{
  "type": "Feature",
  "properties": {
    "iso:country":"GB",
    "wof:name":"SP10 3EA",
    "wof:placetype":"postalcode"
},
  "geometry": {"coordinates":[-1.49838379981731,51.20805582209488],"type":"Point"}
}