{
  "type": "Feature",
  "properties": {
    "date:inception_lower":"1980-01-01",
    "date:inception_upper":"1980-01-31",
    "iso:country":"GB",
    "wof:name":"SP10 3EA",
    "wof:placetype":"postalcode"
},
  "geometry": {"coordinates":[-1.498384,51.208056],"type":"Point"}
}