{
  "type": "Feature",
  "properties": {
    "iso:country": "GB",
    "wof:name": "LL65 3DY",
    "wof:placetype": "postalcode"
  },
  "geometry": {"coordinates":[-4.564193,53.286525],"type":"Point"}
}
