{
  "type": "Feature",
  "properties": {
    "date:inception_lower": "1988-03-01",
    "date:inception_upper": "1988-03-01",
    "iso:country": "GB",
    "wof:name": "LL65 3DY",
    "wof:placetype": "postalcode"
  },
  "geometry": {"coordinates":[-4.564193,53.286525],"type":"Point"}
}
