{
  "type": "Feature",
  "properties": {
    "iso:country":"GB",
    "wof:name":"LL65 3DY",
    "wof:placetype":"postalcode"
},
  "geometry": {"coordinates":[-4.5641928418273,53.28652499782222],"type":"Point"}
}