{
  "type": "Feature",
  "properties": {
    "date:inception_lower": "2022-10-01",
    "date:inception_upper": "2022-10-01",
    "iso:country": "GB",
    "wof:name": "PR25 1EJ",
    "wof:placetype": "postalcode"
  },
  "geometry": {"coordinates":[-2.712883,53.682306],"type":"Point"}
}
