{
  "type": "Feature",
  "properties": {
    "iso:country":"GB",
    "wof:name":"NG5 7DT",
    "wof:placetype":"postalcode"
},
  "geometry": {"coordinates":[-1.13043110335948,53.00477752383518],"type":"Point"}
}