{
  "type": "Feature",
  "properties": {
    "date:inception_lower":"2010-10-01",
    "date:inception_upper":"2010-10-31",
    "iso:country":"GB",
    "wof:name":"NG5 7DT",
    "wof:placetype":"postalcode"
},
  "geometry": {"coordinates":[-1.130416,53.004786],"type":"Point"}
}