{
  "type": "Feature",
  "properties": {
    "iso:country": "GB",
    "wof:name": "NG5 7DT",
    "wof:placetype": "postalcode"
  },
  "geometry": {"coordinates":[-1.130416,53.004786],"type":"Point"}
}
