{
  "type": "Feature",
  "properties": {
    "date:inception_lower":"2008-06-01",
    "date:inception_upper":"2008-06-30",
    "iso:country":"GB",
    "wof:name":"CM6 1FE",
    "wof:placetype":"postalcode"
},
  "geometry": {"coordinates":[0.276633,51.867718],"type":"Point"}
}