{
  "type": "Feature",
  "properties": {
    "iso:country": "GB",
    "wof:name": "CM6 1FE",
    "wof:placetype": "postalcode"
  },
  "geometry": {"coordinates":[0.276633,51.867718],"type":"Point"}
}
