{
  "type": "Feature",
  "properties": {
    "iso:country":"GB",
    "wof:name":"CM6 1FE",
    "wof:placetype":"postalcode"
},
  "geometry": {"coordinates":[0.27663324963309,51.86771831735349],"type":"Point"}
}