{
  "type": "Feature",
  "properties": {
    "iso:country":"GB",
    "wof:name":"SP3 6JQ",
    "wof:placetype":"postalcode"
},
  "geometry": {"coordinates":[-2.0762982209764,51.06528622479697],"type":"Point"}
}