{
  "type": "Feature",
  "properties": {
    "iso:country": "GB",
    "wof:name": "TW10 6HS",
    "wof:placetype": "postalcode"
  },
  "geometry": {"coordinates":[-0.289891,51.460938],"type":"Point"}
}
