{
  "type": "Feature",
  "properties": {
    "iso:country": "GB",
    "wof:name": "SG11 2RD",
    "wof:placetype": "postalcode"
  },
  "geometry": {"coordinates":[0.02664,51.909915],"type":"Point"}
}
