{
  "type": "Feature",
  "properties": {
    "iso:country":"GB",
    "wof:name":"SG11 2RD",
    "wof:placetype":"postalcode"
},
  "geometry": {"coordinates":[0.02681565737635,51.91027130427351],"type":"Point"}
}