{
  "type": "Feature",
  "properties": {
    "iso:country": "GB",
    "wof:name": "RH14 9QJ",
    "wof:placetype": "postalcode"
  },
  "geometry": {"coordinates":[-0.44713,51.022661],"type":"Point"}
}
