{
  "type": "Feature",
  "properties": {
    "date:inception_lower":"1990-08-01",
    "date:inception_upper":"1990-08-31",
    "iso:country":"GB",
    "wof:name":"AB56 1DH",
    "wof:placetype":"postalcode"
},
  "geometry": {"coordinates":[-2.97807,57.671974],"type":"Point"}
}