{
  "type": "Feature",
  "properties": {
    "iso:country": "GB",
    "wof:name": "TD7 4LQ",
    "wof:placetype": "postalcode"
  },
  "geometry": {"coordinates":[-2.841115,55.551482],"type":"Point"}
}
