{
  "type": "Feature",
  "properties": {
    "iso:country":"GB",
    "wof:name":"LE4 1EL",
    "wof:placetype":"postalcode"
},
  "geometry": {"coordinates":[-1.16558921588696,52.66680196526416],"type":"Point"}
}