{
  "type": "Feature",
  "properties": {
    "iso:country":"GB",
    "wof:name":"G71 5BE",
    "wof:placetype":"postalcode"
},
  "geometry": {"coordinates":[-4.05437665771723,55.83456745955201],"type":"Point"}
}