{
  "type": "Feature",
  "properties": {
    "iso:country": "GB",
    "wof:name": "G71 5BE",
    "wof:placetype": "postalcode"
  },
  "geometry": {"coordinates":[-4.054377,55.834567],"type":"Point"}
}
