{
  "type": "Feature",
  "properties": {
    "iso:country": "GB",
    "wof:name": "OX12 9WP",
    "wof:placetype": "postalcode"
  },
  "geometry": {"coordinates":[-1.437479,51.597805],"type":"Point"}
}
