{
  "type": "Feature",
  "properties": {
    "iso:country":"GB",
    "wof:name":"S42 5DF",
    "wof:placetype":"postalcode"
},
  "geometry": {"coordinates":[-1.36908988933237,53.19594497391058],"type":"Point"}
}