{
  "type": "Feature",
  "properties": {
    "iso:country": "GB",
    "wof:name": "S42 5DF",
    "wof:placetype": "postalcode"
  },
  "geometry": {"coordinates":[-1.36909,53.195945],"type":"Point"}
}
