{
  "type": "Feature",
  "properties": {
    "iso:country":"GB",
    "wof:name":"GL2 9DE",
    "wof:placetype":"postalcode"
},
  "geometry": {"coordinates":[-2.22680282198217,51.87827516397451],"type":"Point"}
}