{
  "type": "Feature",
  "properties": {
    "date:inception_lower": "1980-01-01",
    "date:inception_upper": "1980-01-01",
    "iso:country": "GB",
    "wof:name": "SG6 2JZ",
    "wof:placetype": "postalcode"
  },
  "geometry": {"coordinates":[-0.208135,51.973492],"type":"Point"}
}
