{
  "type": "Feature",
  "properties": {
    "iso:country": "GB",
    "wof:name": "EX16 7EY",
    "wof:placetype": "postalcode"
  },
  "geometry": {"coordinates":[-3.369163,50.946318],"type":"Point"}
}
