{
  "type": "Feature",
  "properties": {
    "iso:country":"GB",
    "wof:name":"EX16 7EY",
    "wof:placetype":"postalcode"
},
  "geometry": {"coordinates":[-3.36916350510998,50.94631834227589],"type":"Point"}
}