{
  "type": "Feature",
  "properties": {
    "date:inception_lower": "1980-01-01",
    "date:inception_upper": "1980-01-01",
    "iso:country": "GB",
    "wof:name": "LL18 3YE",
    "wof:placetype": "postalcode"
  },
  "geometry": {"coordinates":[-3.446839,53.330195],"type":"Point"}
}
