{
  "type": "Feature",
  "properties": {
    "iso:country":"GB",
    "wof:name":"LU4 0DQ",
    "wof:placetype":"postalcode"
},
  "geometry": {"coordinates":[-0.47227596501097,51.88952066439153],"type":"Point"}
}