{
  "type": "Feature",
  "properties": {
    "iso:country":"GB",
    "wof:name":"SY4 2AJ",
    "wof:placetype":"postalcode"
},
  "geometry": {"coordinates":[-2.85309857139431,52.83177205697658],"type":"Point"}
}