{
  "type": "Feature",
  "properties": {
    "iso:country": "GB",
    "wof:name": "SY4 2AJ",
    "wof:placetype": "postalcode"
  },
  "geometry": {"coordinates":[-2.853099,52.831772],"type":"Point"}
}
