{
  "type": "Feature",
  "properties": {
    "iso:country":"GB",
    "wof:name":"KT13 9XZ",
    "wof:placetype":"postalcode"
},
  "geometry": {"coordinates":[-0.45264446978251,51.36801508362196],"type":"Point"}
}