{
  "type": "Feature",
  "properties": {
    "iso:country":"GB",
    "wof:name":"TD6 0BW",
    "wof:placetype":"postalcode"
},
  "geometry": {"coordinates":[-2.63838427069278,55.57210618821551],"type":"Point"}
}