{
  "type": "Feature",
  "properties": {
    "date:inception_lower":"1980-01-01",
    "date:inception_upper":"1980-01-31",
    "iso:country":"GB",
    "wof:name":"TD6 0BW",
    "wof:placetype":"postalcode"
},
  "geometry": {"coordinates":[-2.638384,55.572106],"type":"Point"}
}