{
  "type": "Feature",
  "properties": {
    "iso:country": "GB",
    "wof:name": "HS1 2BE",
    "wof:placetype": "postalcode"
  },
  "geometry": {"coordinates":[-6.389683,58.208037],"type":"Point"}
}
