{
  "type": "Feature",
  "properties": {
    "iso:country":"GB",
    "wof:name":"HS1 2BE",
    "wof:placetype":"postalcode"
},
  "geometry": {"coordinates":[-6.38968342526259,58.20803706915618],"type":"Point"}
}