{
  "type": "Feature",
  "properties": {
    "date:inception_lower":"1980-01-01",
    "date:inception_upper":"1980-01-31",
    "iso:country":"GB",
    "wof:name":"LS11 7ES",
    "wof:placetype":"postalcode"
},
  "geometry": {"coordinates":[-1.560071,53.768831],"type":"Point"}
}