{
  "type": "Feature",
  "properties": {
    "iso:country":"GB",
    "wof:name":"LS11 7ES",
    "wof:placetype":"postalcode"
},
  "geometry": {"coordinates":[-1.56007103059781,53.76883139976531],"type":"Point"}
}