{
  "type": "Feature",
  "properties": {
    "iso:country": "GB",
    "wof:name": "NP18 2BL",
    "wof:placetype": "postalcode"
  },
  "geometry": {"coordinates":[-2.919333,51.602328],"type":"Point"}
}
