{
  "type": "Feature",
  "properties": {
    "date:inception_lower":"2013-12-01",
    "date:inception_upper":"2013-12-31",
    "iso:country":"GB",
    "wof:name":"NP18 2BL",
    "wof:placetype":"postalcode"
},
  "geometry": {"coordinates":[-2.919333,51.602328],"type":"Point"}
}