{
  "type": "Feature",
  "properties": {
    "iso:country":"GB",
    "wof:name":"NP18 2BL",
    "wof:placetype":"postalcode"
},
  "geometry": {"coordinates":[-2.91933309965191,51.60232759093713],"type":"Point"}
}