{
  "type": "Feature",
  "properties": {
    "date:inception_lower": "1995-07-01",
    "date:inception_upper": "1995-07-01",
    "iso:country": "GB",
    "wof:name": "BD16 2JF",
    "wof:placetype": "postalcode"
  },
  "geometry": {"coordinates":[-1.838491,53.849162],"type":"Point"}
}
