{
  "type": "Feature",
  "properties": {
    "iso:country":"GB",
    "wof:name":"BD16 2JF",
    "wof:placetype":"postalcode"
},
  "geometry": {"coordinates":[-1.83876323566451,53.84941437099311],"type":"Point"}
}