{
  "type": "Feature",
  "properties": {
    "iso:country": "GB",
    "wof:name": "SP5 2RT",
    "wof:placetype": "postalcode"
  },
  "geometry": {"coordinates":[-1.649183,51.012838],"type":"Point"}
}
