{
  "type": "Feature",
  "properties": {
    "iso:country":"GB",
    "wof:name":"NW3 1PH",
    "wof:placetype":"postalcode"
},
  "geometry": {"coordinates":[-0.16934703352195,51.55361075977434],"type":"Point"}
}