{
  "type": "Feature",
  "properties": {
    "iso:country":"GB",
    "wof:name":"NW1 6TB",
    "wof:placetype":"postalcode"
},
  "geometry": {"coordinates":[-0.16718087071702,51.52172571063925],"type":"Point"}
}