{
  "type": "Feature",
  "properties": {
    "iso:country":"GB",
    "wof:name":"S70 4HG",
    "wof:placetype":"postalcode"
},
  "geometry": {"coordinates":[-1.47397271147181,53.53538249195412],"type":"Point"}
}