{
  "type": "Feature",
  "properties": {
    "date:inception_lower": "2015-11-01",
    "date:inception_upper": "2015-11-01",
    "iso:country": "GB",
    "wof:name": "NG6 8UH",
    "wof:placetype": "postalcode"
  },
  "geometry": {"coordinates":[-1.180349,53.02632],"type":"Point"}
}
