{
  "type": "Feature",
  "properties": {
    "iso:country":"GB",
    "wof:name":"NG6 8UH",
    "wof:placetype":"postalcode"
},
  "geometry": {"coordinates":[-1.18034876959827,53.02631995404666],"type":"Point"}
}