{
  "type": "Feature",
  "properties": {
    "iso:country":"GB",
    "wof:name":"FK7 8LG",
    "wof:placetype":"postalcode"
},
  "geometry": {"coordinates":[-3.91175723526365,56.09083742274063],"type":"Point"}
}