{
  "type": "Feature",
  "properties": {
    "date:inception_lower": "1980-01-01",
    "date:inception_upper": "1980-01-01",
    "iso:country": "GB",
    "wof:name": "DN14 7RG",
    "wof:placetype": "postalcode"
  },
  "geometry": {"coordinates":[-0.8427,53.725448],"type":"Point"}
}
