{
  "type": "Feature",
  "properties": {
    "iso:country":"GB",
    "wof:name":"DN14 7RG",
    "wof:placetype":"postalcode"
},
  "geometry": {"coordinates":[-0.84270028535378,53.72544815927112],"type":"Point"}
}