{
  "type": "Feature",
  "properties": {
    "iso:country": "GB",
    "wof:name": "DN14 7RG",
    "wof:placetype": "postalcode"
  },
  "geometry": {"coordinates":[-0.8427,53.725448],"type":"Point"}
}
