{
  "type": "Feature",
  "properties": {
    "iso:country": "GB",
    "wof:name": "PR4 0EZ",
    "wof:placetype": "postalcode"
  },
  "geometry": {"coordinates":[-2.768803,53.785586],"type":"Point"}
}
