{
  "type": "Feature",
  "properties": {
    "iso:country": "GB",
    "wof:name": "WF17 9DD",
    "wof:placetype": "postalcode"
  },
  "geometry": {"coordinates":[-1.656536,53.74025],"type":"Point"}
}
