{
  "type": "Feature",
  "properties": {
    "iso:country":"GB",
    "wof:name":"BH15 4LL",
    "wof:placetype":"postalcode"
},
  "geometry": {"coordinates":[-2.01358895120401,50.71857234884656],"type":"Point"}
}