{
  "type": "Feature",
  "properties": {
    "date:inception_lower":"1980-01-01",
    "date:inception_upper":"1980-01-31",
    "iso:country":"GB",
    "wof:name":"RM8 2XJ",
    "wof:placetype":"postalcode"
},
  "geometry": {"coordinates":[0.124239,51.550677],"type":"Point"}
}