{
  "type": "Feature",
  "properties": {
    "iso:country":"GB",
    "wof:name":"RM8 2XJ",
    "wof:placetype":"postalcode"
},
  "geometry": {"coordinates":[0.12423866358132,51.55067664150738],"type":"Point"}
}