{
  "type": "Feature",
  "properties": {
    "iso:country": "GB",
    "wof:name": "RM8 2XJ",
    "wof:placetype": "postalcode"
  },
  "geometry": {"coordinates":[0.124239,51.550677],"type":"Point"}
}
