{
  "type": "Feature",
  "properties": {
    "iso:country":"GB",
    "wof:name":"WF12 9JH",
    "wof:placetype":"postalcode"
},
  "geometry": {"coordinates":[-1.62739436556264,53.67700300630652],"type":"Point"}
}