{
  "type": "Feature",
  "properties": {
    "iso:country":"GB",
    "wof:name":"PR3 2EN",
    "wof:placetype":"postalcode"
},
  "geometry": {"coordinates":[-2.66493054206608,53.85752058554245],"type":"Point"}
}