{
  "type": "Feature",
  "properties": {
    "date:inception_lower": "1980-01-01",
    "date:inception_upper": "1980-01-01",
    "iso:country": "GB",
    "wof:name": "PR3 2EN",
    "wof:placetype": "postalcode"
  },
  "geometry": {"coordinates":[-2.66493,53.857521],"type":"Point"}
}
