{
  "type": "Feature",
  "properties": {
    "iso:country": "GB",
    "wof:name": "SK6 1LZ",
    "wof:placetype": "postalcode"
  },
  "geometry": {"coordinates":[-2.099795,53.425552],"type":"Point"}
}
