{
  "type": "Feature",
  "properties": {
    "iso:country":"GB",
    "wof:name":"CF71 7TG",
    "wof:placetype":"postalcode"
},
  "geometry": {"coordinates":[-3.425863016127,51.4787872903933],"type":"Point"}
}