{
  "type": "Feature",
  "properties": {
    "date:inception_lower": "2018-11-01",
    "date:inception_upper": "2018-11-01",
    "iso:country": "GB",
    "wof:name": "EC1N 2AB",
    "wof:placetype": "postalcode"
  },
  "geometry": {"coordinates":[-0.109514,51.51816],"type":"Point"}
}
