{
  "type": "Feature",
  "properties": {
    "iso:country": "GB",
    "wof:name": "LE3 2SW",
    "wof:placetype": "postalcode"
  },
  "geometry": {"coordinates":[-1.174799,52.615857],"type":"Point"}
}
