{
  "type": "Feature",
  "properties": {
    "iso:country": "GB",
    "wof:name": "EH14 5ER",
    "wof:placetype": "postalcode"
  },
  "geometry": {"coordinates":[-3.291686,55.901408],"type":"Point"}
}
