{
  "type": "Feature",
  "properties": {
    "iso:country":"GB",
    "wof:name":"OX10 8JY",
    "wof:placetype":"postalcode"
},
  "geometry": {"coordinates":[-1.12460149292384,51.6064978903747],"type":"Point"}
}