{
  "type": "Feature",
  "properties": {
    "iso:country":"GB",
    "wof:name":"DH4 6HZ",
    "wof:placetype":"postalcode"
},
  "geometry": {"coordinates":[-1.50468823041019,54.8478009149744],"type":"Point"}
}