{
  "type": "Feature",
  "properties": {
    "date:inception_lower": "2002-11-01",
    "date:inception_upper": "2002-11-01",
    "iso:country": "GB",
    "wof:name": "NE40 3WZ",
    "wof:placetype": "postalcode"
  },
  "geometry": {"coordinates":[-1.707966,54.964626],"type":"Point"}
}
