{
  "type": "Feature",
  "properties": {
    "iso:country":"GB",
    "wof:name":"YO30 4SY",
    "wof:placetype":"postalcode"
},
  "geometry": {"coordinates":[-1.10865874493909,53.98690468979267],"type":"Point"}
}