{
  "type": "Feature",
  "properties": {
    "iso:country": "GB",
    "wof:name": "WR12 7PE",
    "wof:placetype": "postalcode"
  },
  "geometry": {"coordinates":[-1.852131,52.054854],"type":"Point"}
}
