{
  "type": "Feature",
  "properties": {
    "iso:country": "GB",
    "wof:name": "BA11 3JB",
    "wof:placetype": "postalcode"
  },
  "geometry": {"coordinates":[-2.322494,51.232711],"type":"Point"}
}
