{
  "type": "Feature",
  "properties": {
    "iso:country":"GB",
    "wof:name":"AL3 7GA",
    "wof:placetype":"postalcode"
},
  "geometry": {"coordinates":[-0.39962772396991,51.79508570429385],"type":"Point"}
}