{
  "type": "Feature",
  "properties": {
    "date:inception_lower": "1980-01-01",
    "date:inception_upper": "1980-01-01",
    "iso:country": "GB",
    "wof:name": "B18 6BA",
    "wof:placetype": "postalcode"
  },
  "geometry": {"coordinates":[-1.911473,52.4906],"type":"Point"}
}
