{
  "type": "Feature",
  "properties": {
    "iso:country":"GB",
    "wof:name":"B18 6BA",
    "wof:placetype":"postalcode"
},
  "geometry": {"coordinates":[-1.91117836058044,52.49044735340645],"type":"Point"}
}