{
  "type": "Feature",
  "properties": {
    "date:inception_lower":"2008-11-01",
    "date:inception_upper":"2008-11-30",
    "iso:country":"GB",
    "wof:name":"EN1 2FD",
    "wof:placetype":"postalcode"
},
  "geometry": {"coordinates":[-0.07725,51.64681],"type":"Point"}
}