{
  "type": "Feature",
  "properties": {
    "iso:country":"GB",
    "wof:name":"EN1 2FD",
    "wof:placetype":"postalcode"
},
  "geometry": {"coordinates":[-0.07724974110842,51.64681024439974],"type":"Point"}
}