{
  "type": "Feature",
  "properties": {
    "iso:country": "GB",
    "wof:name": "LE5 0PZ",
    "wof:placetype": "postalcode"
  },
  "geometry": {"coordinates":[-1.08754,52.643078],"type":"Point"}
}
