{
  "type": "Feature",
  "properties": {
    "date:inception_lower": "2017-02-01",
    "date:inception_upper": "2017-02-01",
    "iso:country": "GB",
    "wof:name": "LE5 0PZ",
    "wof:placetype": "postalcode"
  },
  "geometry": {"coordinates":[-1.087496,52.643069],"type":"Point"}
}
