{
  "type": "Feature",
  "properties": {
    "iso:country": "GB",
    "wof:name": "DY5 3TW",
    "wof:placetype": "postalcode"
  },
  "geometry": {"coordinates":[-2.129912,52.487358],"type":"Point"}
}
