{
  "type": "Feature",
  "properties": {
    "date:inception_lower":"2002-11-01",
    "date:inception_upper":"2002-11-30",
    "iso:country":"GB",
    "wof:name":"DY5 3TW",
    "wof:placetype":"postalcode"
},
  "geometry": {"coordinates":[-2.129912,52.487358],"type":"Point"}
}