{
  "type": "Feature",
  "properties": {
    "iso:country":"GB",
    "wof:name":"DY5 3TW",
    "wof:placetype":"postalcode"
},
  "geometry": {"coordinates":[-2.12990346770722,52.48737928292719],"type":"Point"}
}