{
  "type": "Feature",
  "properties": {
    "iso:country":"GB",
    "wof:name":"B78 3UL",
    "wof:placetype":"postalcode"
},
  "geometry": {"coordinates":[-1.71567104174696,52.59982513232478],"type":"Point"}
}