{
  "type": "Feature",
  "properties": {
    "iso:country": "GB",
    "wof:name": "B78 3UL",
    "wof:placetype": "postalcode"
  },
  "geometry": {"coordinates":[-1.715671,52.599825],"type":"Point"}
}
