{
  "type": "Feature",
  "properties": {
    "date:inception_lower":"1982-03-01",
    "date:inception_upper":"1982-03-31",
    "iso:country":"GB",
    "wof:name":"B78 3UL",
    "wof:placetype":"postalcode"
},
  "geometry": {"coordinates":[-1.715671,52.599825],"type":"Point"}
}