{
  "type": "Feature",
  "properties": {
    "iso:country":"GB",
    "wof:name":"BA15 2RP",
    "wof:placetype":"postalcode"
},
  "geometry": {"coordinates":[-2.23610919660695,51.36571715974382],"type":"Point"}
}