{
  "type": "Feature",
  "properties": {
    "iso:country":"GB",
    "wof:name":"DE75 7EZ",
    "wof:placetype":"postalcode"
},
  "geometry": {"coordinates":[-1.35744721104769,53.01528155208587],"type":"Point"}
}