{
  "type": "Feature",
  "properties": {
    "iso:country":"GB",
    "wof:name":"DA1 4TA",
    "wof:placetype":"postalcode"
},
  "geometry": {"coordinates":[0.1858793647862,51.46226791943067],"type":"Point"}
}