{
  "type": "Feature",
  "properties": {
    "date:inception_lower": "1983-07-01",
    "date:inception_upper": "1983-07-01",
    "iso:country": "GB",
    "wof:name": "DA1 4TA",
    "wof:placetype": "postalcode"
  },
  "geometry": {"coordinates":[0.185879,51.462268],"type":"Point"}
}
