{
  "type": "Feature",
  "properties": {
    "date:inception_lower": "1996-12-01",
    "date:inception_upper": "1996-12-01",
    "iso:country": "GB",
    "wof:name": "LN8 2DL",
    "wof:placetype": "postalcode"
  },
  "geometry": {"coordinates":[-0.531193,53.352372],"type":"Point"}
}
