{
  "type": "Feature",
  "properties": {
    "iso:country":"GB",
    "wof:name":"NE6 2UG",
    "wof:placetype":"postalcode"
},
  "geometry": {"coordinates":[-1.57802382558919,54.97909893158052],"type":"Point"}
}