{
  "type": "Feature",
  "properties": {
    "iso:country":"GB",
    "wof:name":"HU17 7AZ",
    "wof:placetype":"postalcode"
},
  "geometry": {"coordinates":[-0.43676264037981,53.85052431313851],"type":"Point"}
}