{
  "type": "Feature",
  "properties": {
    "date:inception_lower": "1980-01-01",
    "date:inception_upper": "1980-01-01",
    "iso:country": "GB",
    "wof:name": "BD18 1NB",
    "wof:placetype": "postalcode"
  },
  "geometry": {"coordinates":[-1.751644,53.829762],"type":"Point"}
}
