{
  "type": "Feature",
  "properties": {
    "iso:country":"GB",
    "wof:name":"BD18 1NB",
    "wof:placetype":"postalcode"
},
  "geometry": {"coordinates":[-1.75164428251857,53.82976210363691],"type":"Point"}
}