{
  "type": "Feature",
  "properties": {
    "iso:country": "GB",
    "wof:name": "BD18 1NB",
    "wof:placetype": "postalcode"
  },
  "geometry": {"coordinates":[-1.751644,53.829762],"type":"Point"}
}
