{
  "type": "Feature",
  "properties": {
    "iso:country": "GB",
    "wof:name": "NR25 6QS",
    "wof:placetype": "postalcode"
  },
  "geometry": {"coordinates":[1.119103,52.915052],"type":"Point"}
}
