{
  "type": "Feature",
  "properties": {
    "iso:country":"GB",
    "wof:name":"NE8 3HY",
    "wof:placetype":"postalcode"
},
  "geometry": {"coordinates":[-1.59629337786946,54.95835766759351],"type":"Point"}
}