{
  "type": "Feature",
  "properties": {
    "iso:country":"GB",
    "wof:name":"LE17 5JS",
    "wof:placetype":"postalcode"
},
  "geometry": {"coordinates":[-1.20935026638899,52.50156861504302],"type":"Point"}
}