{
  "type": "Feature",
  "properties": {
    "iso:country": "GB",
    "wof:name": "LE17 5JS",
    "wof:placetype": "postalcode"
  },
  "geometry": {"coordinates":[-1.20935,52.501569],"type":"Point"}
}
