{
  "type": "Feature",
  "properties": {
    "date:inception_lower":"1980-01-01",
    "date:inception_upper":"1980-01-31",
    "iso:country":"GB",
    "wof:name":"LE17 5JS",
    "wof:placetype":"postalcode"
},
  "geometry": {"coordinates":[-1.20935,52.501569],"type":"Point"}
}