{
  "type": "Feature",
  "properties": {
    "date:inception_lower":"1998-06-01",
    "date:inception_upper":"1998-06-30",
    "iso:country":"GB",
    "wof:name":"YO62 5DA",
    "wof:placetype":"postalcode"
},
  "geometry": {"coordinates":[-1.055904,54.245532],"type":"Point"}
}