{
  "type": "Feature",
  "properties": {
    "iso:country":"GB",
    "wof:name":"YO62 5DA",
    "wof:placetype":"postalcode"
},
  "geometry": {"coordinates":[-1.0559042727701,54.24553199050398],"type":"Point"}
}