{
  "type": "Feature",
  "properties": {
    "iso:country":"GB",
    "wof:name":"BA2 2UL",
    "wof:placetype":"postalcode"
},
  "geometry": {"coordinates":[-2.37588264213358,51.35659388626403],"type":"Point"}
}