{
  "type": "Feature",
  "properties": {
    "iso:country": "GB",
    "wof:name": "RH12 2BP",
    "wof:placetype": "postalcode"
  },
  "geometry": {"coordinates":[-0.328602,51.070469],"type":"Point"}
}
