{
  "type": "Feature",
  "properties": {
    "date:inception_lower":"1980-01-01",
    "date:inception_upper":"1980-01-31",
    "iso:country":"GB",
    "wof:name":"RH12 2BP",
    "wof:placetype":"postalcode"
},
  "geometry": {"coordinates":[-0.328602,51.070469],"type":"Point"}
}