{
  "type": "Feature",
  "properties": {
    "iso:country":"GB",
    "wof:name":"HA5 4RT",
    "wof:placetype":"postalcode"
},
  "geometry": {"coordinates":[-0.38385691201546,51.60928455393451],"type":"Point"}
}