{
  "type": "Feature",
  "properties": {
    "iso:country":"GB",
    "wof:name":"SS15 5JW",
    "wof:placetype":"postalcode"
},
  "geometry": {"coordinates":[0.42813617496563,51.56985249401101],"type":"Point"}
}