{
  "type": "Feature",
  "properties": {
    "iso:country":"GB",
    "wof:name":"G75 8NX",
    "wof:placetype":"postalcode"
},
  "geometry": {"coordinates":[-4.20916311855973,55.76209670644206],"type":"Point"}
}