{
  "type": "Feature",
  "properties": {
    "iso:country":"GB",
    "wof:name":"BR3 3SR",
    "wof:placetype":"postalcode"
},
  "geometry": {"coordinates":[-0.02251040281124,51.38858565446873],"type":"Point"}
}