{
  "type": "Feature",
  "properties": {
    "iso:country":"GB",
    "wof:name":"HA8 9BW",
    "wof:placetype":"postalcode"
},
  "geometry": {"coordinates":[-0.26665906048046,51.60928511182597],"type":"Point"}
}