{
  "type": "Feature",
  "properties": {
    "date:inception_lower": "1999-12-01",
    "date:inception_upper": "1999-12-01",
    "iso:country": "GB",
    "wof:name": "UB8 2RS",
    "wof:placetype": "postalcode"
  },
  "geometry": {"coordinates":[-0.487001,51.540188],"type":"Point"}
}
