{
  "type": "Feature",
  "properties": {
    "date:inception_lower": "1981-06-01",
    "date:inception_upper": "1981-06-01",
    "iso:country": "GB",
    "wof:name": "BN3 6FU",
    "wof:placetype": "postalcode"
  },
  "geometry": {"coordinates":[-0.166598,50.837363],"type":"Point"}
}
