{
  "type": "Feature",
  "properties": {
    "iso:country":"GB",
    "wof:name":"OX10 9HG",
    "wof:placetype":"postalcode"
},
  "geometry": {"coordinates":[-1.12905962019599,51.58027569775565],"type":"Point"}
}