{
  "type": "Feature",
  "properties": {
    "date:inception_lower": "1980-01-01",
    "date:inception_upper": "1980-01-01",
    "iso:country": "GB",
    "wof:name": "WN8 8PA",
    "wof:placetype": "postalcode"
  },
  "geometry": {"coordinates":[-2.798049,53.553936],"type":"Point"}
}
