{
  "type": "Feature",
  "properties": {
    "iso:country":"GB",
    "wof:name":"WN8 8PA",
    "wof:placetype":"postalcode"
},
  "geometry": {"coordinates":[-2.79804924601265,53.55393613728647],"type":"Point"}
}