{
  "type": "Feature",
  "properties": {
    "iso:country":"GB",
    "wof:name":"KW5 6DJ",
    "wof:placetype":"postalcode"
},
  "geometry": {"coordinates":[-3.3694919820963,58.28849771617575],"type":"Point"}
}