{
  "type": "Feature",
  "properties": {
    "date:inception_lower":"1980-01-01",
    "date:inception_upper":"1980-01-31",
    "iso:country":"GB",
    "wof:name":"SK6 3LH",
    "wof:placetype":"postalcode"
},
  "geometry": {"coordinates":[-2.117248,53.408053],"type":"Point"}
}