{
  "type": "Feature",
  "properties": {
    "iso:country":"GB",
    "wof:name":"CT16 1HT",
    "wof:placetype":"postalcode"
},
  "geometry": {"coordinates":[1.31010277808617,51.13257886695533],"type":"Point"}
}