{
  "type": "Feature",
  "properties": {
    "date:inception_lower": "1980-01-01",
    "date:inception_upper": "1980-01-01",
    "iso:country": "GB",
    "wof:name": "TW8 0SF",
    "wof:placetype": "postalcode"
  },
  "geometry": {"coordinates":[-0.298936,51.487894],"type":"Point"}
}
