{
  "type": "Feature",
  "properties": {
    "iso:country": "GB",
    "wof:name": "GL15 6BB",
    "wof:placetype": "postalcode"
  },
  "geometry": {"coordinates":[-2.578252,51.706133],"type":"Point"}
}
