{
  "type": "Feature",
  "properties": {
    "iso:country":"GB",
    "wof:name":"GL15 6BB",
    "wof:placetype":"postalcode"
},
  "geometry": {"coordinates":[-2.57825156753829,51.70613294357904],"type":"Point"}
}