{
  "type": "Feature",
  "properties": {
    "iso:country":"GB",
    "wof:name":"NR14 6RX",
    "wof:placetype":"postalcode"
},
  "geometry": {"coordinates":[1.54982869813469,52.53336197342996],"type":"Point"}
}