{
  "type": "Feature",
  "properties": {
    "iso:country":"GB",
    "wof:name":"SA12 9NL",
    "wof:placetype":"postalcode"
},
  "geometry": {"coordinates":[-3.7608406840562,51.61703284628444],"type":"Point"}
}