{
  "type": "Feature",
  "properties": {
    "iso:country":"GB",
    "wof:name":"NG16 1HX",
    "wof:placetype":"postalcode"
},
  "geometry": {"coordinates":[-1.24999495654999,53.0029665471959],"type":"Point"}
}