{
  "type": "Feature",
  "properties": {
    "iso:country":"GB",
    "wof:name":"TN17 3QE",
    "wof:placetype":"postalcode"
},
  "geometry": {"coordinates":[0.50787550242295,51.08598232314626],"type":"Point"}
}