{
  "type": "Feature",
  "properties": {
    "iso:country": "GB",
    "wof:name": "TN17 3QE",
    "wof:placetype": "postalcode"
  },
  "geometry": {"coordinates":[0.507876,51.085982],"type":"Point"}
}
