{
  "type": "Feature",
  "properties": {
    "iso:country":"GB",
    "wof:name":"M20 5NG",
    "wof:placetype":"postalcode"
},
  "geometry": {"coordinates":[-2.22078021477995,53.40976737982275],"type":"Point"}
}