{
  "type": "Feature",
  "properties": {
    "date:inception_lower":"2006-07-01",
    "date:inception_upper":"2006-07-31",
    "iso:country":"GB",
    "wof:name":"TQ7 3GZ",
    "wof:placetype":"postalcode"
},
  "geometry": {"coordinates":[-3.80191,50.275833],"type":"Point"}
}