{
  "type": "Feature",
  "properties": {
    "iso:country":"GB",
    "wof:name":"TQ7 3GZ",
    "wof:placetype":"postalcode"
},
  "geometry": {"coordinates":[-3.80190990775361,50.27583298393575],"type":"Point"}
}