{
  "type": "Feature",
  "properties": {
    "iso:country": "GB",
    "wof:name": "TQ7 3GZ",
    "wof:placetype": "postalcode"
  },
  "geometry": {"coordinates":[-3.80191,50.275833],"type":"Point"}
}
