{
  "type": "Feature",
  "properties": {
    "iso:country":"GB",
    "wof:name":"CW1 3RZ",
    "wof:placetype":"postalcode"
},
  "geometry": {"coordinates":[-2.45674836465305,53.11439813582172],"type":"Point"}
}