{
  "type": "Feature",
  "properties": {
    "date:inception_lower": "1984-10-01",
    "date:inception_upper": "1984-10-01",
    "iso:country": "GB",
    "wof:name": "CW1 3RZ",
    "wof:placetype": "postalcode"
  },
  "geometry": {"coordinates":[-2.456748,53.114398],"type":"Point"}
}
