{
  "type": "Feature",
  "properties": {
    "iso:country":"GB",
    "wof:name":"CO12 4JE",
    "wof:placetype":"postalcode"
},
  "geometry": {"coordinates":[1.25984373602386,51.93189379028398],"type":"Point"}
}