{
  "type": "Feature",
  "properties": {
    "iso:country":"GB",
    "wof:name":"WA5 3NS",
    "wof:placetype":"postalcode"
},
  "geometry": {"coordinates":[-2.66313217130288,53.39446650187906],"type":"Point"}
}