{
  "type": "Feature",
  "properties": {
    "iso:country":"GB",
    "wof:name":"N1 0QU",
    "wof:placetype":"postalcode"
},
  "geometry": {"coordinates":[-0.10440289236731,51.53808354232694],"type":"Point"}
}