{
  "type": "Feature",
  "properties": {
    "iso:country":"GB",
    "wof:name":"SN16 9JD",
    "wof:placetype":"postalcode"
},
  "geometry": {"coordinates":[-2.08202442182203,51.58855624968596],"type":"Point"}
}