{
  "type": "Feature",
  "properties": {
    "date:inception_lower": "1980-01-01",
    "date:inception_upper": "1980-01-01",
    "iso:country": "GB",
    "wof:name": "SN16 9JD",
    "wof:placetype": "postalcode"
  },
  "geometry": {"coordinates":[-2.082019,51.588558],"type":"Point"}
}
