{
  "type": "Feature",
  "properties": {
    "iso:country":"GB",
    "wof:name":"TN4 0HZ",
    "wof:placetype":"postalcode"
},
  "geometry": {"coordinates":[0.25117096863032,51.15187942691747],"type":"Point"}
}