{
  "type": "Feature",
  "properties": {
    "date:inception_lower": "2006-07-01",
    "date:inception_upper": "2006-07-01",
    "iso:country": "GB",
    "wof:name": "CH65 0BZ",
    "wof:placetype": "postalcode"
  },
  "geometry": {"coordinates":[-2.89797,53.276578],"type":"Point"}
}
