{
  "type": "Feature",
  "properties": {
    "iso:country": "GB",
    "wof:name": "CH65 0BZ",
    "wof:placetype": "postalcode"
  },
  "geometry": {"coordinates":[-2.89797,53.276578],"type":"Point"}
}
