{
  "type": "Feature",
  "properties": {
    "iso:country": "GB",
    "wof:name": "PL6 8SY",
    "wof:placetype": "postalcode"
  },
  "geometry": {"coordinates":[-4.103628,50.418818],"type":"Point"}
}
