{
  "type": "Feature",
  "properties": {
    "iso:country":"GB",
    "wof:name":"PL6 8SY",
    "wof:placetype":"postalcode"
},
  "geometry": {"coordinates":[-4.10362809858257,50.41881808856966],"type":"Point"}
}