{
  "type": "Feature",
  "properties": {
    "iso:country":"GB",
    "wof:name":"TN13 3DS",
    "wof:placetype":"postalcode"
},
  "geometry": {"coordinates":[0.1727060340501,51.28017805732745],"type":"Point"}
}