{
  "type": "Feature",
  "properties": {
    "iso:country":"GB",
    "wof:name":"M5 5JL",
    "wof:placetype":"postalcode"
},
  "geometry": {"coordinates":[-2.30837552419354,53.48641600178993],"type":"Point"}
}