{
  "type": "Feature",
  "properties": {
    "iso:country":"GB",
    "wof:name":"G64 2HL",
    "wof:placetype":"postalcode"
},
  "geometry": {"coordinates":[-4.21190668322077,55.91677416508263],"type":"Point"}
}