{
  "type": "Feature",
  "properties": {
    "date:inception_lower":"1984-10-01",
    "date:inception_upper":"1984-10-31",
    "iso:country":"GB",
    "wof:name":"TN37 7JQ",
    "wof:placetype":"postalcode"
},
  "geometry": {"coordinates":[0.555747,50.878566],"type":"Point"}
}