{
  "type": "Feature",
  "properties": {
    "iso:country": "GB",
    "wof:name": "GL17 9NZ",
    "wof:placetype": "postalcode"
  },
  "geometry": {"coordinates":[-2.583215,51.860082],"type":"Point"}
}
