{
  "type": "Feature",
  "properties": {
    "iso:country":"GB",
    "wof:name":"BS5 8RS",
    "wof:placetype":"postalcode"
},
  "geometry": {"coordinates":[-2.52493186268401,51.45145841474034],"type":"Point"}
}