{
  "type": "Feature",
  "properties": {
    "iso:country": "GB",
    "wof:name": "BS5 8RS",
    "wof:placetype": "postalcode"
  },
  "geometry": {"coordinates":[-2.524932,51.451458],"type":"Point"}
}
