{
  "type": "Feature",
  "properties": {
    "date:inception_lower": "2003-06-01",
    "date:inception_upper": "2003-06-01",
    "iso:country": "GB",
    "wof:name": "NG22 9SS",
    "wof:placetype": "postalcode"
  },
  "geometry": {"coordinates":[-1.012351,53.202045],"type":"Point"}
}
