{
  "type": "Feature",
  "properties": {
    "iso:country":"GB",
    "wof:name":"NG22 9SS",
    "wof:placetype":"postalcode"
},
  "geometry": {"coordinates":[-1.0123511920187,53.20204453580324],"type":"Point"}
}