{
  "type": "Feature",
  "properties": {
    "date:inception_lower":"1980-01-01",
    "date:inception_upper":"1980-01-31",
    "iso:country":"GB",
    "wof:name":"IP7 7LL",
    "wof:placetype":"postalcode"
},
  "geometry": {"coordinates":[0.906126,52.138839],"type":"Point"}
}