{
  "type": "Feature",
  "properties": {
    "iso:country":"GB",
    "wof:name":"IP7 7LL",
    "wof:placetype":"postalcode"
},
  "geometry": {"coordinates":[0.90619217761668,52.13875774786295],"type":"Point"}
}