{
  "type": "Feature",
  "properties": {
    "iso:country": "GB",
    "wof:name": "IP7 7LL",
    "wof:placetype": "postalcode"
  },
  "geometry": {"coordinates":[0.906126,52.138839],"type":"Point"}
}
