{
  "type": "Feature",
  "properties": {
    "iso:country":"GB",
    "wof:name":"BR8 7RX",
    "wof:placetype":"postalcode"
},
  "geometry": {"coordinates":[0.18789912456355,51.41267871923505],"type":"Point"}
}