{
  "type": "Feature",
  "properties": {
    "iso:country":"GB",
    "wof:name":"LL19 7AS",
    "wof:placetype":"postalcode"
},
  "geometry": {"coordinates":[-3.43601471401191,53.33163907929731],"type":"Point"}
}