{
  "type": "Feature",
  "properties": {
    "iso:country":"GB",
    "wof:name":"EX31 1SB",
    "wof:placetype":"postalcode"
},
  "geometry": {"coordinates":[-4.05793115575139,51.0803186328166],"type":"Point"}
}