{
  "type": "Feature",
  "properties": {
    "date:inception_lower": "1980-01-01",
    "date:inception_upper": "1980-01-01",
    "iso:country": "GB",
    "wof:name": "EX31 1SB",
    "wof:placetype": "postalcode"
  },
  "geometry": {"coordinates":[-4.057931,51.080319],"type":"Point"}
}
