{
  "type": "Feature",
  "properties": {
    "iso:country": "GB",
    "wof:name": "EX31 1SB",
    "wof:placetype": "postalcode"
  },
  "geometry": {"coordinates":[-4.057931,51.080319],"type":"Point"}
}
