{
  "type": "Feature",
  "properties": {
    "iso:country": "GB",
    "wof:name": "SO21 2AL",
    "wof:placetype": "postalcode"
  },
  "geometry": {"coordinates":[-1.339812,51.023802],"type":"Point"}
}
