{
  "type": "Feature",
  "properties": {
    "iso:country":"GB",
    "wof:name":"SO21 2AL",
    "wof:placetype":"postalcode"
},
  "geometry": {"coordinates":[-1.33981203636101,51.0238015060369],"type":"Point"}
}