{
  "type": "Feature",
  "properties": {
    "iso:country":"GB",
    "wof:name":"NW3 5JN",
    "wof:placetype":"postalcode"
},
  "geometry": {"coordinates":[-0.17829843301758,51.5461874652321],"type":"Point"}
}