{
  "type": "Feature",
  "properties": {
    "iso:country":"GB",
    "wof:name":"BA12 9LY",
    "wof:placetype":"postalcode"
},
  "geometry": {"coordinates":[-2.16831480023085,51.19829892770431],"type":"Point"}
}