{
  "type": "Feature",
  "properties": {
    "iso:country": "GB",
    "wof:name": "MK16 9JT",
    "wof:placetype": "postalcode"
  },
  "geometry": {"coordinates":[-0.609241,52.129498],"type":"Point"}
}
