{
  "type": "Feature",
  "properties": {
    "iso:country":"GB",
    "wof:name":"MK16 9JT",
    "wof:placetype":"postalcode"
},
  "geometry": {"coordinates":[-0.60924121240713,52.12949790059155],"type":"Point"}
}