{
  "type": "Feature",
  "properties": {
    "date:inception_lower": "1980-01-01",
    "date:inception_upper": "1980-01-01",
    "iso:country": "GB",
    "wof:name": "MK16 9JT",
    "wof:placetype": "postalcode"
  },
  "geometry": {"coordinates":[-0.609241,52.129498],"type":"Point"}
}
