{
  "type": "Feature",
  "properties": {
    "iso:country": "GB",
    "wof:name": "CO16 8BY",
    "wof:placetype": "postalcode"
  },
  "geometry": {"coordinates":[1.123897,51.801401],"type":"Point"}
}
