{
  "type": "Feature",
  "properties": {
    "iso:country":"GB",
    "wof:name":"LA4 4LA",
    "wof:placetype":"postalcode"
},
  "geometry": {"coordinates":[-2.87312914496983,54.06525651835803],"type":"Point"}
}