{
  "type": "Feature",
  "properties": {
    "iso:country": "GB",
    "wof:name": "YO25 6DG",
    "wof:placetype": "postalcode"
  },
  "geometry": {"coordinates":[-0.437997,54.00708],"type":"Point"}
}
