{
  "type": "Feature",
  "properties": {
    "iso:country":"GB",
    "wof:name":"YO25 6DG",
    "wof:placetype":"postalcode"
},
  "geometry": {"coordinates":[-0.43799680567512,54.00707997838496],"type":"Point"}
}