{
  "type": "Feature",
  "properties": {
    "iso:country":"GB",
    "wof:name":"PO36 9LQ",
    "wof:placetype":"postalcode"
},
  "geometry": {"coordinates":[-1.16799086959761,50.64477825113453],"type":"Point"}
}