{
  "type": "Feature",
  "properties": {
    "iso:country": "GB",
    "wof:name": "PO36 9LQ",
    "wof:placetype": "postalcode"
  },
  "geometry": {"coordinates":[-1.16798,50.644793],"type":"Point"}
}
