{
  "type": "Feature",
  "properties": {
    "iso:country":"GB",
    "wof:name":"NE10 8SJ",
    "wof:placetype":"postalcode"
},
  "geometry": {"coordinates":[-1.547670453787,54.93696093298228],"type":"Point"}
}