{
  "type": "Feature",
  "properties": {
    "iso:country": "GB",
    "wof:name": "NE10 8SJ",
    "wof:placetype": "postalcode"
  },
  "geometry": {"coordinates":[-1.54767,54.936961],"type":"Point"}
}
