{
  "type": "Feature",
  "properties": {
    "iso:country":"GB",
    "wof:name":"PE7 3GY",
    "wof:placetype":"postalcode"
},
  "geometry": {"coordinates":[-0.25911222545554,52.514034977434],"type":"Point"}
}