{
  "type": "Feature",
  "properties": {
    "iso:country": "GB",
    "wof:name": "PE7 3GY",
    "wof:placetype": "postalcode"
  },
  "geometry": {"coordinates":[-0.259112,52.514035],"type":"Point"}
}
