{
  "type": "Feature",
  "properties": {
    "iso:country":"GB",
    "wof:name":"N16 8EX",
    "wof:placetype":"postalcode"
},
  "geometry": {"coordinates":[-0.07810732042099,51.55812268897179],"type":"Point"}
}