{
  "type": "Feature",
  "properties": {
    "iso:country":"GB",
    "wof:name":"WF12 0LN",
    "wof:placetype":"postalcode"
},
  "geometry": {"coordinates":[-1.62290369143901,53.66452232151365],"type":"Point"}
}