{
  "type": "Feature",
  "properties": {
    "iso:country": "GB",
    "wof:name": "WF12 0LN",
    "wof:placetype": "postalcode"
  },
  "geometry": {"coordinates":[-1.622904,53.664522],"type":"Point"}
}
