{
  "type": "Feature",
  "properties": {
    "date:inception_lower": "1980-01-01",
    "date:inception_upper": "1980-01-01",
    "iso:country": "GB",
    "wof:name": "WF12 0LN",
    "wof:placetype": "postalcode"
  },
  "geometry": {"coordinates":[-1.622904,53.664522],"type":"Point"}
}
