{
  "type": "Feature",
  "properties": {
    "iso:country": "GB",
    "wof:name": "CH2 3LA",
    "wof:placetype": "postalcode"
  },
  "geometry": {"coordinates":[-2.860135,53.204998],"type":"Point"}
}
