{
  "type": "Feature",
  "properties": {
    "date:inception_lower":"1980-01-01",
    "date:inception_upper":"1980-01-31",
    "iso:country":"GB",
    "wof:name":"CH2 3LA",
    "wof:placetype":"postalcode"
},
  "geometry": {"coordinates":[-2.860135,53.204998],"type":"Point"}
}