{
  "type": "Feature",
  "properties": {
    "date:inception_lower": "2022-09-01",
    "date:inception_upper": "2022-09-01",
    "iso:country": "GB",
    "wof:name": "NN17 5BS",
    "wof:placetype": "postalcode"
  },
  "geometry": {"coordinates":[-0.641333,52.501445],"type":"Point"}
}
