{
  "type": "Feature",
  "properties": {
    "iso:country":"GB",
    "wof:name":"CV5 7HY",
    "wof:placetype":"postalcode"
},
  "geometry": {"coordinates":[-1.56374107418382,52.41123888613044],"type":"Point"}
}