{
  "type": "Feature",
  "properties": {
    "iso:country":"GB",
    "wof:name":"IP7 6AT",
    "wof:placetype":"postalcode"
},
  "geometry": {"coordinates":[0.95950062111427,52.05017632103203],"type":"Point"}
}