{
  "type": "Feature",
  "properties": {
    "iso:country": "GB",
    "wof:name": "IP7 6AT",
    "wof:placetype": "postalcode"
  },
  "geometry": {"coordinates":[0.959595,52.050269],"type":"Point"}
}
