{
  "type": "Feature",
  "properties": {
    "date:inception_lower":"1999-12-01",
    "date:inception_upper":"1999-12-31",
    "iso:country":"GB",
    "wof:name":"SR2 8NX",
    "wof:placetype":"postalcode"
},
  "geometry": {"coordinates":[-1.363682,54.899428],"type":"Point"}
}