{
  "type": "Feature",
  "properties": {
    "iso:country":"GB",
    "wof:name":"SR2 8NX",
    "wof:placetype":"postalcode"
},
  "geometry": {"coordinates":[-1.36373319513543,54.89917649658739],"type":"Point"}
}