{
  "type": "Feature",
  "properties": {
    "iso:country":"GB",
    "wof:name":"KA20 4DU",
    "wof:placetype":"postalcode"
},
  "geometry": {"coordinates":[-4.74229230081811,55.64979394269696],"type":"Point"}
}