{
  "type": "Feature",
  "properties": {
    "date:inception_lower":"1980-01-01",
    "date:inception_upper":"1980-01-31",
    "iso:country":"GB",
    "wof:name":"KA20 4DU",
    "wof:placetype":"postalcode"
},
  "geometry": {"coordinates":[-4.742292,55.649794],"type":"Point"}
}