{
  "type": "Feature",
  "properties": {
    "iso:country":"GB",
    "wof:name":"WA3 7NN",
    "wof:placetype":"postalcode"
},
  "geometry": {"coordinates":[-2.54285050880224,53.42222893448998],"type":"Point"}
}