{
  "type": "Feature",
  "properties": {
    "iso:country":"GB",
    "wof:name":"WA6 8LP",
    "wof:placetype":"postalcode"
},
  "geometry": {"coordinates":[-2.65158451457845,53.24778724691421],"type":"Point"}
}