{
  "type": "Feature",
  "properties": {
    "iso:country":"GB",
    "wof:name":"HP1 3JL",
    "wof:placetype":"postalcode"
},
  "geometry": {"coordinates":[-0.48887672876212,51.76185509674961],"type":"Point"}
}