{
  "type": "Feature",
  "properties": {
    "date:inception_lower":"1980-01-01",
    "date:inception_upper":"1980-01-31",
    "iso:country":"GB",
    "wof:name":"TR15 3EJ",
    "wof:placetype":"postalcode"
},
  "geometry": {"coordinates":[-5.25444,50.228794],"type":"Point"}
}