{
  "type": "Feature",
  "properties": {
    "iso:country":"GB",
    "wof:name":"TR15 3EJ",
    "wof:placetype":"postalcode"
},
  "geometry": {"coordinates":[-5.25439334445869,50.22883117324492],"type":"Point"}
}