{
  "type": "Feature",
  "properties": {
    "iso:country":"GB",
    "wof:name":"CV2 1QA",
    "wof:placetype":"postalcode"
},
  "geometry": {"coordinates":[-1.47632505639704,52.44865176709776],"type":"Point"}
}