{
  "type": "Feature",
  "properties": {
    "date:inception_lower": "1980-01-01",
    "date:inception_upper": "1980-01-01",
    "iso:country": "GB",
    "wof:name": "B37 5AS",
    "wof:placetype": "postalcode"
  },
  "geometry": {"coordinates":[-1.759725,52.481364],"type":"Point"}
}
