{
  "type": "Feature",
  "properties": {
    "iso:country":"GB",
    "wof:name":"B37 5AS",
    "wof:placetype":"postalcode"
},
  "geometry": {"coordinates":[-1.75972494237226,52.48136397856432],"type":"Point"}
}