{
  "type": "Feature",
  "properties": {
    "date:inception_lower":"1998-12-01",
    "date:inception_upper":"1998-12-31",
    "iso:country":"GB",
    "wof:name":"GU47 9BG",
    "wof:placetype":"postalcode"
},
  "geometry": {"coordinates":[-0.796068,51.345026],"type":"Point"}
}