{
  "type": "Feature",
  "properties": {
    "iso:country":"GB",
    "wof:name":"SN14 8BB",
    "wof:placetype":"postalcode"
},
  "geometry": {"coordinates":[-2.32578200326035,51.45643433502587],"type":"Point"}
}