{
  "type": "Feature",
  "properties": {
    "iso:country": "GB",
    "wof:name": "SN14 8BB",
    "wof:placetype": "postalcode"
  },
  "geometry": {"coordinates":[-2.325794,51.456495],"type":"Point"}
}
