{
  "type": "Feature",
  "properties": {
    "date:inception_lower":"1996-06-01",
    "date:inception_upper":"1996-06-30",
    "iso:country":"GB",
    "wof:name":"SN14 8BB",
    "wof:placetype":"postalcode"
},
  "geometry": {"coordinates":[-2.325794,51.456495],"type":"Point"}
}