{
  "type": "Feature",
  "properties": {
    "iso:country":"GB",
    "wof:name":"WN2 1LZ",
    "wof:placetype":"postalcode"
},
  "geometry": {"coordinates":[-2.6220680188094,53.58423867692738],"type":"Point"}
}