{
  "type": "Feature",
  "properties": {
    "iso:country": "GB",
    "wof:name": "WN2 1LZ",
    "wof:placetype": "postalcode"
  },
  "geometry": {"coordinates":[-2.622068,53.584239],"type":"Point"}
}
