{
  "type": "Feature",
  "properties": {
    "iso:country":"GB",
    "wof:name":"ST4 3QF",
    "wof:placetype":"postalcode"
},
  "geometry": {"coordinates":[-2.16587860354908,52.99713260529515],"type":"Point"}
}