{
  "type": "Feature",
  "properties": {
    "date:inception_lower": "1980-01-01",
    "date:inception_upper": "1980-01-01",
    "iso:country": "GB",
    "wof:name": "DD3 9EX",
    "wof:placetype": "postalcode"
  },
  "geometry": {"coordinates":[-3.00394,56.494902],"type":"Point"}
}
