{
  "type": "Feature",
  "properties": {
    "iso:country":"GB",
    "wof:name":"DD3 9EX",
    "wof:placetype":"postalcode"
},
  "geometry": {"coordinates":[-3.00394048456585,56.49490235871126],"type":"Point"}
}