{
  "type": "Feature",
  "properties": {
    "iso:country":"GB",
    "wof:name":"BN8 5TP",
    "wof:placetype":"postalcode"
},
  "geometry": {"coordinates":[0.0198451802136,50.91272590183709],"type":"Point"}
}