{
  "type": "Feature",
  "properties": {
    "date:inception_lower":"1980-01-01",
    "date:inception_upper":"1980-01-31",
    "iso:country":"GB",
    "wof:name":"BN8 5TP",
    "wof:placetype":"postalcode"
},
  "geometry": {"coordinates":[0.019845,50.912726],"type":"Point"}
}