{
  "type": "Feature",
  "properties": {
    "iso:country": "GB",
    "wof:name": "AL10 0SZ",
    "wof:placetype": "postalcode"
  },
  "geometry": {"coordinates":[-0.23639,51.7626],"type":"Point"}
}
