{
  "type": "Feature",
  "properties": {
    "date:inception_lower":"1990-02-01",
    "date:inception_upper":"1990-02-28",
    "iso:country":"GB",
    "wof:name":"BS7 8HA",
    "wof:placetype":"postalcode"
},
  "geometry": {"coordinates":[-2.593096,51.47649],"type":"Point"}
}