{
  "type": "Feature",
  "properties": {
    "iso:country":"GB",
    "wof:name":"BS7 8HA",
    "wof:placetype":"postalcode"
},
  "geometry": {"coordinates":[-2.59309569544412,51.47648966380216],"type":"Point"}
}