{
  "type": "Feature",
  "properties": {
    "date:inception_lower": "2005-01-01",
    "date:inception_upper": "2005-01-01",
    "iso:country": "GB",
    "wof:name": "SO32 1NT",
    "wof:placetype": "postalcode"
  },
  "geometry": {"coordinates":[-1.224829,50.956471],"type":"Point"}
}
