{
  "type": "Feature",
  "properties": {
    "iso:country":"GB",
    "wof:name":"SO32 1NT",
    "wof:placetype":"postalcode"
},
  "geometry": {"coordinates":[-1.2248287269223,50.95647072599353],"type":"Point"}
}