{
  "type": "Feature",
  "properties": {
    "iso:country": "GB",
    "wof:name": "ME6 5EL",
    "wof:placetype": "postalcode"
  },
  "geometry": {"coordinates":[0.439509,51.325555],"type":"Point"}
}
