{
  "type": "Feature",
  "properties": {
    "iso:country":"GB",
    "wof:name":"ME6 5EL",
    "wof:placetype":"postalcode"
},
  "geometry": {"coordinates":[0.43950884586825,51.3255547834615],"type":"Point"}
}