{
  "type": "Feature",
  "properties": {
    "date:inception_lower": "1980-01-01",
    "date:inception_upper": "1980-01-01",
    "iso:country": "GB",
    "wof:name": "PR4 6LP",
    "wof:placetype": "postalcode"
  },
  "geometry": {"coordinates":[-2.862503,53.685144],"type":"Point"}
}
