{
  "type": "Feature",
  "properties": {
    "iso:country":"GB",
    "wof:name":"PR4 6LP",
    "wof:placetype":"postalcode"
},
  "geometry": {"coordinates":[-2.86250348173417,53.68514350413761],"type":"Point"}
}