{
  "type": "Feature",
  "properties": {
    "iso:country":"GB",
    "wof:name":"CF3 1TF",
    "wof:placetype":"postalcode"
},
  "geometry": {"coordinates":[-3.10492746069415,51.51464888440029],"type":"Point"}
}