{
  "type": "Feature",
  "properties": {
    "iso:country":"GB",
    "wof:name":"CV8 2EQ",
    "wof:placetype":"postalcode"
},
  "geometry": {"coordinates":[-1.56068018397191,52.35378034768773],"type":"Point"}
}