{
  "type": "Feature",
  "properties": {
    "iso:country": "GB",
    "wof:name": "CV8 2EQ",
    "wof:placetype": "postalcode"
  },
  "geometry": {"coordinates":[-1.56068,52.35378],"type":"Point"}
}
