{
  "type": "Feature",
  "properties": {
    "iso:country":"GB",
    "wof:name":"SY21 8JJ",
    "wof:placetype":"postalcode"
},
  "geometry": {"coordinates":[-3.10148201682011,52.60302483425862],"type":"Point"}
}