{
  "type": "Feature",
  "properties": {
    "date:inception_lower":"1980-01-01",
    "date:inception_upper":"1980-01-31",
    "iso:country":"GB",
    "wof:name":"SY21 8JJ",
    "wof:placetype":"postalcode"
},
  "geometry": {"coordinates":[-3.101482,52.603025],"type":"Point"}
}