{
  "type": "Feature",
  "properties": {
    "iso:country": "GB",
    "wof:name": "M43 6NW",
    "wof:placetype": "postalcode"
  },
  "geometry": {"coordinates":[-2.165884,53.485953],"type":"Point"}
}
