{
  "type": "Feature",
  "properties": {
    "iso:country":"GB",
    "wof:name":"EX16 4LJ",
    "wof:placetype":"postalcode"
},
  "geometry": {"coordinates":[-3.48144598330794,50.90181725850912],"type":"Point"}
}