{
  "type": "Feature",
  "properties": {
    "date:inception_lower": "1980-01-01",
    "date:inception_upper": "1980-01-01",
    "iso:country": "GB",
    "wof:name": "EX16 4LJ",
    "wof:placetype": "postalcode"
  },
  "geometry": {"coordinates":[-3.481461,50.90181],"type":"Point"}
}
