{
  "type": "Feature",
  "properties": {
    "iso:country":"GB",
    "wof:name":"SP4 7BX",
    "wof:placetype":"postalcode"
},
  "geometry": {"coordinates":[-1.81128820967538,51.14985581345152],"type":"Point"}
}