{
  "type": "Feature",
  "properties": {
    "iso:country": "GB",
    "wof:name": "SP4 7BX",
    "wof:placetype": "postalcode"
  },
  "geometry": {"coordinates":[-1.811277,51.14985],"type":"Point"}
}
