{
  "type": "Feature",
  "properties": {
    "date:inception_lower": "1990-02-01",
    "date:inception_upper": "1990-02-01",
    "iso:country": "GB",
    "wof:name": "SP4 7BX",
    "wof:placetype": "postalcode"
  },
  "geometry": {"coordinates":[-1.811277,51.14985],"type":"Point"}
}
