{
  "type": "Feature",
  "properties": {
    "iso:country":"GB",
    "wof:name":"YO30 2DA",
    "wof:placetype":"postalcode"
},
  "geometry": {"coordinates":[-1.21860886588987,54.03055983586318],"type":"Point"}
}