{
  "type": "Feature",
  "properties": {
    "iso:country": "GB",
    "wof:name": "YO30 2DA",
    "wof:placetype": "postalcode"
  },
  "geometry": {"coordinates":[-1.218616,54.030567],"type":"Point"}
}
