{
  "type": "Feature",
  "properties": {
    "iso:country":"GB",
    "wof:name":"CV7 8NB",
    "wof:placetype":"postalcode"
},
  "geometry": {"coordinates":[-1.52672794520254,52.46299646705058],"type":"Point"}
}