{
  "type": "Feature",
  "properties": {
    "iso:country":"GB",
    "wof:name":"BS32 0EL",
    "wof:placetype":"postalcode"
},
  "geometry": {"coordinates":[-2.55513003715212,51.54320403811234],"type":"Point"}
}