{
  "type": "Feature",
  "properties": {
    "iso:country":"GB",
    "wof:name":"W9 3UN",
    "wof:placetype":"postalcode"
},
  "geometry": {"coordinates":[-0.19627316305229,51.52236551649165],"type":"Point"}
}