{
  "type": "Feature",
  "properties": {
    "date:inception_lower":"2002-06-01",
    "date:inception_upper":"2002-06-30",
    "iso:country":"GB",
    "wof:name":"W9 3UN",
    "wof:placetype":"postalcode"
},
  "geometry": {"coordinates":[-0.196273,51.522366],"type":"Point"}
}