{
  "type": "Feature",
  "properties": {
    "iso:country": "GB",
    "wof:name": "PO20 0JP",
    "wof:placetype": "postalcode"
  },
  "geometry": {"coordinates":[-0.787031,50.729542],"type":"Point"}
}
