{
  "type": "Feature",
  "properties": {
    "iso:country":"GB",
    "wof:name":"PO20 0JP",
    "wof:placetype":"postalcode"
},
  "geometry": {"coordinates":[-0.78703057354009,50.72954180913209],"type":"Point"}
}