{
  "type": "Feature",
  "properties": {
    "iso:country":"GB",
    "wof:name":"CH5 2PF",
    "wof:placetype":"postalcode"
},
  "geometry": {"coordinates":[-3.0023972604418,53.19658635340823],"type":"Point"}
}