{
  "type": "Feature",
  "properties": {
    "iso:country":"GB",
    "wof:name":"CO7 8SE",
    "wof:placetype":"postalcode"
},
  "geometry": {"coordinates":[1.08075153827681,51.88320705402619],"type":"Point"}
}