{
  "type": "Feature",
  "properties": {
    "date:inception_lower": "1980-01-01",
    "date:inception_upper": "1980-01-01",
    "iso:country": "GB",
    "wof:name": "CO7 8SE",
    "wof:placetype": "postalcode"
  },
  "geometry": {"coordinates":[1.08084,51.883217],"type":"Point"}
}
