{
  "type": "Feature",
  "properties": {
    "date:inception_lower":"1995-12-01",
    "date:inception_upper":"1995-12-31",
    "iso:country":"GB",
    "wof:name":"BN2 4QL",
    "wof:placetype":"postalcode"
},
  "geometry": {"coordinates":[-0.104059,50.852915],"type":"Point"}
}