{
  "type": "Feature",
  "properties": {
    "iso:country":"GB",
    "wof:name":"BN2 4QL",
    "wof:placetype":"postalcode"
},
  "geometry": {"coordinates":[-0.10408654102146,50.8529207735453],"type":"Point"}
}