{
  "type": "Feature",
  "properties": {
    "iso:country":"GB",
    "wof:name":"CA28 8UQ",
    "wof:placetype":"postalcode"
},
  "geometry": {"coordinates":[-3.56094861447424,54.54474873152871],"type":"Point"}
}