{
  "type": "Feature",
  "properties": {
    "iso:country":"GB",
    "wof:name":"N18 2JD",
    "wof:placetype":"postalcode"
},
  "geometry": {"coordinates":[-0.06422028890544,51.6143672654632],"type":"Point"}
}