{
  "type": "Feature",
  "properties": {
    "iso:country": "GB",
    "wof:name": "OL9 9DD",
    "wof:placetype": "postalcode"
  },
  "geometry": {"coordinates":[-2.143695,53.537773],"type":"Point"}
}
