{
  "type": "Feature",
  "properties": {
    "iso:country": "GB",
    "wof:name": "CR0 9ES",
    "wof:placetype": "postalcode"
  },
  "geometry": {"coordinates":[-0.018749,51.358198],"type":"Point"}
}
