{
  "type": "Feature",
  "properties": {
    "iso:country":"GB",
    "wof:name":"NE5 3AA",
    "wof:placetype":"postalcode"
},
  "geometry": {"coordinates":[-1.65735078259843,54.99162327116371],"type":"Point"}
}