{
  "type": "Feature",
  "properties": {
    "iso:country":"GB",
    "wof:name":"B47 6DR",
    "wof:placetype":"postalcode"
},
  "geometry": {"coordinates":[-1.89008953686459,52.3596065394198],"type":"Point"}
}