{
  "type": "Feature",
  "properties": {
    "iso:country": "GB",
    "wof:name": "N16 8SN",
    "wof:placetype": "postalcode"
  },
  "geometry": {"coordinates":[-0.079834,51.556523],"type":"Point"}
}
