{
  "type": "Feature",
  "properties": {
    "iso:country":"GB",
    "wof:name":"N16 8SN",
    "wof:placetype":"postalcode"
},
  "geometry": {"coordinates":[-0.07983371447922,51.55652330985252],"type":"Point"}
}