{
  "type": "Feature",
  "properties": {
    "iso:country": "GB",
    "wof:name": "MK40 4QZ",
    "wof:placetype": "postalcode"
  },
  "geometry": {"coordinates":[-0.5082,52.141831],"type":"Point"}
}
