{
  "type": "Feature",
  "properties": {
    "iso:country": "GB",
    "wof:name": "BA16 0LB",
    "wof:placetype": "postalcode"
  },
  "geometry": {"coordinates":[-2.741931,51.121189],"type":"Point"}
}
