{
  "type": "Feature",
  "properties": {
    "iso:country":"GB",
    "wof:name":"BA16 0LB",
    "wof:placetype":"postalcode"
},
  "geometry": {"coordinates":[-2.74193101523232,51.12118891227031],"type":"Point"}
}