{
  "type": "Feature",
  "properties": {
    "iso:country": "GB",
    "wof:name": "WV4 6SE",
    "wof:placetype": "postalcode"
  },
  "geometry": {"coordinates":[-2.11528,52.560392],"type":"Point"}
}
