{
  "type": "Feature",
  "properties": {
    "iso:country":"GB",
    "wof:name":"LS9 6RY",
    "wof:placetype":"postalcode"
},
  "geometry": {"coordinates":[-1.49762316805269,53.81097387430108],"type":"Point"}
}