{
  "type": "Feature",
  "properties": {
    "iso:country":"GB",
    "wof:name":"NN12 6YN",
    "wof:placetype":"postalcode"
},
  "geometry": {"coordinates":[-1.00116093653271,52.13136421591988],"type":"Point"}
}