{
  "type": "Feature",
  "properties": {
    "date:inception_lower": "1994-05-01",
    "date:inception_upper": "1994-05-01",
    "iso:country": "GB",
    "wof:name": "NN12 6YN",
    "wof:placetype": "postalcode"
  },
  "geometry": {"coordinates":[-1.001161,52.131364],"type":"Point"}
}
