{
  "type": "Feature",
  "properties": {
    "iso:country": "GB",
    "wof:name": "RG6 9HS",
    "wof:placetype": "postalcode"
  },
  "geometry": {"coordinates":[-0.945616,51.457626],"type":"Point"}
}
