{
  "type": "Feature",
  "properties": {
    "date:inception_lower": "1980-01-01",
    "date:inception_upper": "1980-01-01",
    "iso:country": "GB",
    "wof:name": "CM18 7LJ",
    "wof:placetype": "postalcode"
  },
  "geometry": {"coordinates":[0.102868,51.75074],"type":"Point"}
}
