{
  "type": "Feature",
  "properties": {
    "iso:country":"GB",
    "wof:name":"CM18 7LJ",
    "wof:placetype":"postalcode"
},
  "geometry": {"coordinates":[0.10302958930178,51.75074889417446],"type":"Point"}
}