{
  "type": "Feature",
  "properties": {
    "iso:country":"GB",
    "wof:name":"B30 1AA",
    "wof:placetype":"postalcode"
},
  "geometry": {"coordinates":[-1.93188333630584,52.41516078897812],"type":"Point"}
}