{
  "type": "Feature",
  "properties": {
    "iso:country": "GB",
    "wof:name": "PO40 9PL",
    "wof:placetype": "postalcode"
  },
  "geometry": {"coordinates":[-1.536501,50.687589],"type":"Point"}
}
