{
  "type": "Feature",
  "properties": {
    "iso:country":"GB",
    "wof:name":"ME18 6DB",
    "wof:placetype":"postalcode"
},
  "geometry": {"coordinates":[0.42012514879857,51.21523741750585],"type":"Point"}
}