{
  "type": "Feature",
  "properties": {
    "date:inception_lower": "1980-01-01",
    "date:inception_upper": "1980-01-01",
    "iso:country": "GB",
    "wof:name": "ME18 6DB",
    "wof:placetype": "postalcode"
  },
  "geometry": {"coordinates":[0.420125,51.215237],"type":"Point"}
}
