{
  "type": "Feature",
  "properties": {
    "iso:country":"GB",
    "wof:name":"SW3 1ER",
    "wof:placetype":"postalcode"
},
  "geometry": {"coordinates":[-0.16421481116438,51.49977363867086],"type":"Point"}
}