{
  "type": "Feature",
  "properties": {
    "iso:country":"GB",
    "wof:name":"GU12 6SS",
    "wof:placetype":"postalcode"
},
  "geometry": {"coordinates":[-0.7202255343321,51.25173620773166],"type":"Point"}
}