{
  "type": "Feature",
  "properties": {
    "iso:country": "GB",
    "wof:name": "DG11 3PF",
    "wof:placetype": "postalcode"
  },
  "geometry": {"coordinates":[-3.199681,55.058719],"type":"Point"}
}
