{
  "type": "Feature",
  "properties": {
    "iso:country":"GB",
    "wof:name":"DG11 3PF",
    "wof:placetype":"postalcode"
},
  "geometry": {"coordinates":[-3.19968124473089,55.05871944038746],"type":"Point"}
}