{
  "type": "Feature",
  "properties": {
    "iso:country":"GB",
    "wof:name":"CB23 5FL",
    "wof:placetype":"postalcode"
},
  "geometry": {"coordinates":[-0.07002740328408,52.21385435454337],"type":"Point"}
}