{
  "type": "Feature",
  "properties": {
    "date:inception_lower":"1980-01-01",
    "date:inception_upper":"1980-01-31",
    "iso:country":"GB",
    "wof:name":"NR5 0HN",
    "wof:placetype":"postalcode"
},
  "geometry": {"coordinates":[1.22797,52.645813],"type":"Point"}
}