{
  "type": "Feature",
  "properties": {
    "iso:country":"GB",
    "wof:name":"NR5 0HN",
    "wof:placetype":"postalcode"
},
  "geometry": {"coordinates":[1.22797015824304,52.64581349552995],"type":"Point"}
}