{
  "type": "Feature",
  "properties": {
    "iso:country": "GB",
    "wof:name": "EC3R 7QR",
    "wof:placetype": "postalcode"
  },
  "geometry": {"coordinates":[-0.080289,51.510066],"type":"Point"}
}
