{
  "type": "Feature",
  "properties": {
    "iso:country":"GB",
    "wof:name":"BD3 0LY",
    "wof:placetype":"postalcode"
},
  "geometry": {"coordinates":[-1.74853161792216,53.80657570200357],"type":"Point"}
}