{
  "type": "Feature",
  "properties": {
    "date:inception_lower":"1980-01-01",
    "date:inception_upper":"1980-01-31",
    "iso:country":"GB",
    "wof:name":"BD3 0LY",
    "wof:placetype":"postalcode"
},
  "geometry": {"coordinates":[-1.748532,53.806576],"type":"Point"}
}