{
  "type": "Feature",
  "properties": {
    "date:inception_lower":"1980-01-01",
    "date:inception_upper":"1980-01-31",
    "iso:country":"GB",
    "wof:name":"TQ4 5BW",
    "wof:placetype":"postalcode"
},
  "geometry": {"coordinates":[-3.566762,50.437695],"type":"Point"}
}