{
  "type": "Feature",
  "properties": {
    "iso:country": "GB",
    "wof:name": "TQ4 5BW",
    "wof:placetype": "postalcode"
  },
  "geometry": {"coordinates":[-3.566762,50.437695],"type":"Point"}
}
