{
  "type": "Feature",
  "properties": {
    "date:inception_lower": "1980-01-01",
    "date:inception_upper": "1980-01-01",
    "iso:country": "GB",
    "wof:name": "HU8 8LP",
    "wof:placetype": "postalcode"
  },
  "geometry": {"coordinates":[-0.305188,53.76193],"type":"Point"}
}
