{
  "type": "Feature",
  "properties": {
    "iso:country":"GB",
    "wof:name":"HU8 8LP",
    "wof:placetype":"postalcode"
},
  "geometry": {"coordinates":[-0.30518838715683,53.76192999763202],"type":"Point"}
}