{
  "type": "Feature",
  "properties": {
    "iso:country":"GB",
    "wof:name":"DH6 5BN",
    "wof:placetype":"postalcode"
},
  "geometry": {"coordinates":[-1.51867185210054,54.7352643731036],"type":"Point"}
}