{
  "type": "Feature",
  "properties": {
    "iso:country":"GB",
    "wof:name":"OL12 0RL",
    "wof:placetype":"postalcode"
},
  "geometry": {"coordinates":[-2.15961309598992,53.62573905964617],"type":"Point"}
}