{
  "type": "Feature",
  "properties": {
    "iso:country":"GB",
    "wof:name":"OL11 2UZ",
    "wof:placetype":"postalcode"
},
  "geometry": {"coordinates":[-2.17116631694961,53.58881729701361],"type":"Point"}
}