{
  "type": "Feature",
  "properties": {
    "iso:country":"GB",
    "wof:name":"G43 2SB",
    "wof:placetype":"postalcode"
},
  "geometry": {"coordinates":[-4.28627902732495,55.81866476813881],"type":"Point"}
}