{
  "type": "Feature",
  "properties": {
    "date:inception_lower":"2012-06-01",
    "date:inception_upper":"2012-06-30",
    "iso:country":"GB",
    "wof:name":"M44 5GN",
    "wof:placetype":"postalcode"
},
  "geometry": {"coordinates":[-2.432515,53.42463],"type":"Point"}
}