{
  "type": "Feature",
  "properties": {
    "iso:country": "GB",
    "wof:name": "M44 5GN",
    "wof:placetype": "postalcode"
  },
  "geometry": {"coordinates":[-2.432515,53.42463],"type":"Point"}
}
