{
  "type": "Feature",
  "properties": {
    "iso:country":"GB",
    "wof:name":"M44 5GN",
    "wof:placetype":"postalcode"
},
  "geometry": {"coordinates":[-2.43251467385557,53.42463021028418],"type":"Point"}
}