{
  "type": "Feature",
  "properties": {
    "date:inception_lower": "1980-01-01",
    "date:inception_upper": "1980-01-01",
    "iso:country": "GB",
    "wof:name": "TF2 9QB",
    "wof:placetype": "postalcode"
  },
  "geometry": {"coordinates":[-2.443729,52.697871],"type":"Point"}
}
