{
  "type": "Feature",
  "properties": {
    "iso:country":"GB",
    "wof:name":"TF2 9QB",
    "wof:placetype":"postalcode"
},
  "geometry": {"coordinates":[-2.44372950404857,52.69787050825796],"type":"Point"}
}