{
  "type": "Feature",
  "properties": {
    "iso:country":"GB",
    "wof:name":"W1D 4SA",
    "wof:placetype":"postalcode"
},
  "geometry": {"coordinates":[-0.13146078740428,51.5132846882212],"type":"Point"}
}