{
  "type": "Feature",
  "properties": {
    "iso:country":"GB",
    "wof:name":"W1F 9LX",
    "wof:placetype":"postalcode"
},
  "geometry": {"coordinates":[-0.135294479551,51.51187092862155],"type":"Point"}
}