{
  "type": "Feature",
  "properties": {
    "date:inception_lower": "2014-03-01",
    "date:inception_upper": "2014-03-01",
    "iso:country": "GB",
    "wof:name": "HR9 7QH",
    "wof:placetype": "postalcode"
  },
  "geometry": {"coordinates":[-2.57203,51.928423],"type":"Point"}
}
