{
  "type": "Feature",
  "properties": {
    "iso:country": "GB",
    "wof:name": "HR9 7QH",
    "wof:placetype": "postalcode"
  },
  "geometry": {"coordinates":[-2.57203,51.928423],"type":"Point"}
}
