{
  "type": "Feature",
  "properties": {
    "iso:country":"GB",
    "wof:name":"HR9 7QH",
    "wof:placetype":"postalcode"
},
  "geometry": {"coordinates":[-2.57203042688996,51.92842290982617],"type":"Point"}
}