{
  "type": "Feature",
  "properties": {
    "iso:country":"GB",
    "wof:name":"HU17 0JD",
    "wof:placetype":"postalcode"
},
  "geometry": {"coordinates":[-0.40913630381298,53.84379706609203],"type":"Point"}
}