{
  "type": "Feature",
  "properties": {
    "date:inception_lower": "1980-01-01",
    "date:inception_upper": "1980-01-01",
    "iso:country": "GB",
    "wof:name": "HU17 0JD",
    "wof:placetype": "postalcode"
  },
  "geometry": {"coordinates":[-0.409136,53.843797],"type":"Point"}
}
