{
  "type": "Feature",
  "properties": {
    "iso:country": "GB",
    "wof:name": "SS3 0BT",
    "wof:placetype": "postalcode"
  },
  "geometry": {"coordinates":[0.813974,51.560169],"type":"Point"}
}
