{
  "type": "Feature",
  "properties": {
    "iso:country":"GB",
    "wof:name":"SS3 0BT",
    "wof:placetype":"postalcode"
},
  "geometry": {"coordinates":[0.81397432499224,51.56016918327488],"type":"Point"}
}