{
  "type": "Feature",
  "properties": {
    "iso:country":"GB",
    "wof:name":"BN12 6EZ",
    "wof:placetype":"postalcode"
},
  "geometry": {"coordinates":[-0.41254058625846,50.8219204272712],"type":"Point"}
}