{
  "type": "Feature",
  "properties": {
    "iso:country":"GB",
    "wof:name":"BB3 2ET",
    "wof:placetype":"postalcode"
},
  "geometry": {"coordinates":[-2.45544910819804,53.68456152830243],"type":"Point"}
}