{
  "type": "Feature",
  "properties": {
    "iso:country":"GB",
    "wof:name":"OX15 6NL",
    "wof:placetype":"postalcode"
},
  "geometry": {"coordinates":[-1.45055854703361,52.08239233046446],"type":"Point"}
}