{
  "type": "Feature",
  "properties": {
    "iso:country":"GB",
    "wof:name":"GL11 6AZ",
    "wof:placetype":"postalcode"
},
  "geometry": {"coordinates":[-2.38825623180813,51.66761415874301],"type":"Point"}
}