{
  "type": "Feature",
  "properties": {
    "date:inception_lower": "1980-01-01",
    "date:inception_upper": "1980-01-01",
    "iso:country": "GB",
    "wof:name": "GL11 6AZ",
    "wof:placetype": "postalcode"
  },
  "geometry": {"coordinates":[-2.388256,51.667614],"type":"Point"}
}
