{
  "type": "Feature",
  "properties": {
    "iso:country":"GB",
    "wof:name":"ML5 1QD",
    "wof:placetype":"postalcode"
},
  "geometry": {"coordinates":[-4.03272782354606,55.86403606164387],"type":"Point"}
}