{
  "type": "Feature",
  "properties": {
    "iso:country":"GB",
    "wof:name":"GL15 4AH",
    "wof:placetype":"postalcode"
},
  "geometry": {"coordinates":[-2.48502979248523,51.76336120430809],"type":"Point"}
}