{
  "type": "Feature",
  "properties": {
    "iso:country":"GB",
    "wof:name":"HU12 8PU",
    "wof:placetype":"postalcode"
},
  "geometry": {"coordinates":[-0.19064200125614,53.73489663975699],"type":"Point"}
}