{
  "type": "Feature",
  "properties": {
    "iso:country": "GB",
    "wof:name": "HU12 8PU",
    "wof:placetype": "postalcode"
  },
  "geometry": {"coordinates":[-0.190642,53.734897],"type":"Point"}
}
