{
  "type": "Feature",
  "properties": {
    "iso:country":"GB",
    "wof:name":"EH6 8HG",
    "wof:placetype":"postalcode"
},
  "geometry": {"coordinates":[-3.17103065191902,55.97052687973394],"type":"Point"}
}