{
  "type": "Feature",
  "properties": {
    "date:inception_lower": "1994-05-01",
    "date:inception_upper": "1994-05-01",
    "iso:country": "GB",
    "wof:name": "M9 7AE",
    "wof:placetype": "postalcode"
  },
  "geometry": {"coordinates":[-2.199329,53.525397],"type":"Point"}
}
