{
  "type": "Feature",
  "properties": {
    "iso:country":"GB",
    "wof:name":"CO15 3QS",
    "wof:placetype":"postalcode"
},
  "geometry": {"coordinates":[1.14995051173329,51.79556025889037],"type":"Point"}
}