{
  "type": "Feature",
  "properties": {
    "iso:country":"GB",
    "wof:name":"PO5 2JP",
    "wof:placetype":"postalcode"
},
  "geometry": {"coordinates":[-1.08217931429038,50.77990912657549],"type":"Point"}
}