{
  "type": "Feature",
  "properties": {
    "date:inception_lower":"2002-08-01",
    "date:inception_upper":"2002-08-31",
    "iso:country":"GB",
    "wof:name":"PO5 2JP",
    "wof:placetype":"postalcode"
},
  "geometry": {"coordinates":[-1.082179,50.779909],"type":"Point"}
}