{
  "type": "Feature",
  "properties": {
    "iso:country":"GB",
    "wof:name":"WF3 3HY",
    "wof:placetype":"postalcode"
},
  "geometry": {"coordinates":[-1.4980568379637,53.71736452844262],"type":"Point"}
}