{
  "type": "Feature",
  "properties": {
    "iso:country": "GB",
    "wof:name": "WF3 3HY",
    "wof:placetype": "postalcode"
  },
  "geometry": {"coordinates":[-1.498057,53.717365],"type":"Point"}
}
