{
  "type": "Feature",
  "properties": {
    "iso:country":"GB",
    "wof:name":"OX5 2QF",
    "wof:placetype":"postalcode"
},
  "geometry": {"coordinates":[-1.27503863938447,51.8365220523574],"type":"Point"}
}