{
  "type": "Feature",
  "properties": {
    "iso:country":"GB",
    "wof:name":"S36 8WW",
    "wof:placetype":"postalcode"
},
  "geometry": {"coordinates":[-1.60546578997611,53.50910278018681],"type":"Point"}
}