{
  "type": "Feature",
  "properties": {
    "iso:country": "GB",
    "wof:name": "SO32 1PW",
    "wof:placetype": "postalcode"
  },
  "geometry": {"coordinates":[-1.209595,50.956405],"type":"Point"}
}
