{
  "type": "Feature",
  "properties": {
    "iso:country":"GB",
    "wof:name":"BA13 3ER",
    "wof:placetype":"postalcode"
},
  "geometry": {"coordinates":[-2.18851829731258,51.26361214202025],"type":"Point"}
}