{
  "type": "Feature",
  "properties": {
    "date:inception_lower": "1997-12-01",
    "date:inception_upper": "1997-12-01",
    "iso:country": "GB",
    "wof:name": "BA13 3ER",
    "wof:placetype": "postalcode"
  },
  "geometry": {"coordinates":[-2.188518,51.263612],"type":"Point"}
}
