{
  "type": "Feature",
  "properties": {
    "iso:country":"GB",
    "wof:name":"AL7 4DY",
    "wof:placetype":"postalcode"
},
  "geometry": {"coordinates":[-0.19636768433147,51.78290841453025],"type":"Point"}
}