{
  "type": "Feature",
  "properties": {
    "iso:country": "GB",
    "wof:name": "G71 7WR",
    "wof:placetype": "postalcode"
  },
  "geometry": {"coordinates":[-4.108484,55.839004],"type":"Point"}
}
