{
  "type": "Feature",
  "properties": {
    "iso:country": "GB",
    "wof:name": "W2 2HH",
    "wof:placetype": "postalcode"
  },
  "geometry": {"coordinates":[-0.162825,51.513555],"type":"Point"}
}
