{
  "type": "Feature",
  "properties": {
    "iso:country": "GB",
    "wof:name": "G31 4HN",
    "wof:placetype": "postalcode"
  },
  "geometry": {"coordinates":[-4.200194,55.849561],"type":"Point"}
}
