{
  "type": "Feature",
  "properties": {
    "iso:country": "GB",
    "wof:name": "RG1 7BL",
    "wof:placetype": "postalcode"
  },
  "geometry": {"coordinates":[-0.977462,51.459427],"type":"Point"}
}
