{
  "type": "Feature",
  "properties": {
    "date:inception_lower": "1980-01-01",
    "date:inception_upper": "1980-01-01",
    "iso:country": "GB",
    "wof:name": "RG1 7BL",
    "wof:placetype": "postalcode"
  },
  "geometry": {"coordinates":[-0.977462,51.459427],"type":"Point"}
}
