{
  "type": "Feature",
  "properties": {
    "iso:country":"GB",
    "wof:name":"PH33 7BT",
    "wof:placetype":"postalcode"
},
  "geometry": {"coordinates":[-5.09976449881217,56.83627774960364],"type":"Point"}
}