{
  "type": "Feature",
  "properties": {
    "date:inception_lower": "2011-08-01",
    "date:inception_upper": "2011-08-01",
    "iso:country": "GB",
    "wof:name": "SE25 4FE",
    "wof:placetype": "postalcode"
  },
  "geometry": {"coordinates":[-0.071037,51.397452],"type":"Point"}
}
