{
  "type": "Feature",
  "properties": {
    "iso:country":"GB",
    "wof:name":"SE25 4FE",
    "wof:placetype":"postalcode"
},
  "geometry": {"coordinates":[-0.07106310642849,51.39745256180103],"type":"Point"}
}