{
  "type": "Feature",
  "properties": {
    "iso:country":"GB",
    "wof:name":"CA25 5NT",
    "wof:placetype":"postalcode"
},
  "geometry": {"coordinates":[-3.51951771339996,54.5177285276806],"type":"Point"}
}