{
  "type": "Feature",
  "properties": {
    "iso:country":"GB",
    "wof:name":"DN15 6SH",
    "wof:placetype":"postalcode"
},
  "geometry": {"coordinates":[-0.64588092215792,53.59399950631593],"type":"Point"}
}