{
  "type": "Feature",
  "properties": {
    "iso:country": "GB",
    "wof:name": "LN6 7BL",
    "wof:placetype": "postalcode"
  },
  "geometry": {"coordinates":[-0.5541,53.22856],"type":"Point"}
}
