{
  "type": "Feature",
  "properties": {
    "date:inception_lower":"2006-07-01",
    "date:inception_upper":"2006-07-31",
    "iso:country":"GB",
    "wof:name":"LN6 7BL",
    "wof:placetype":"postalcode"
},
  "geometry": {"coordinates":[-0.5541,53.22856],"type":"Point"}
}