{
  "type": "Feature",
  "properties": {
    "date:inception_lower": "1991-09-01",
    "date:inception_upper": "1991-09-01",
    "iso:country": "GB",
    "wof:name": "N20 9LZ",
    "wof:placetype": "postalcode"
  },
  "geometry": {"coordinates":[-0.17722,51.633831],"type":"Point"}
}
