{
  "type": "Feature",
  "properties": {
    "iso:country":"GB",
    "wof:name":"N20 9LZ",
    "wof:placetype":"postalcode"
},
  "geometry": {"coordinates":[-0.17724559580681,51.63382862251297],"type":"Point"}
}