{
  "type": "Feature",
  "properties": {
    "iso:country": "GB",
    "wof:name": "NP20 5AW",
    "wof:placetype": "postalcode"
  },
  "geometry": {"coordinates":[-3.017756,51.589071],"type":"Point"}
}
