{
  "type": "Feature",
  "properties": {
    "iso:country":"GB",
    "wof:name":"GU7 3JA",
    "wof:placetype":"postalcode"
},
  "geometry": {"coordinates":[-0.59805077161067,51.19338754120188],"type":"Point"}
}