{
  "type": "Feature",
  "properties": {
    "iso:country":"GB",
    "wof:name":"N5 2LN",
    "wof:placetype":"postalcode"
},
  "geometry": {"coordinates":[-0.09617035688947,51.56154656566638],"type":"Point"}
}