{
  "type": "Feature",
  "properties": {
    "iso:country":"GB",
    "wof:name":"NW10 4RT",
    "wof:placetype":"postalcode"
},
  "geometry": {"coordinates":[-0.24569970713738,51.53478721836268],"type":"Point"}
}