{
  "type": "Feature",
  "properties": {
    "date:inception_lower":"1980-01-01",
    "date:inception_upper":"1980-01-31",
    "iso:country":"GB",
    "wof:name":"M33 2ND",
    "wof:placetype":"postalcode"
},
  "geometry": {"coordinates":[-2.297854,53.428044],"type":"Point"}
}