{
  "type": "Feature",
  "properties": {
    "iso:country":"GB",
    "wof:name":"M33 2ND",
    "wof:placetype":"postalcode"
},
  "geometry": {"coordinates":[-2.29785419814466,53.42804438720521],"type":"Point"}
}