{
  "type": "Feature",
  "properties": {
    "iso:country":"GB",
    "wof:name":"SK23 7RB",
    "wof:placetype":"postalcode"
},
  "geometry": {"coordinates":[-2.01665309261698,53.3191767858152],"type":"Point"}
}