{
  "type": "Feature",
  "properties": {
    "iso:country":"GB",
    "wof:name":"HA8 0ES",
    "wof:placetype":"postalcode"
},
  "geometry": {"coordinates":[-0.25862494349818,51.60260186618216],"type":"Point"}
}