{
  "type": "Feature",
  "properties": {
    "iso:country": "GB",
    "wof:name": "KW1 5XH",
    "wof:placetype": "postalcode"
  },
  "geometry": {"coordinates":[-3.309759,58.474648],"type":"Point"}
}
