{
  "type": "Feature",
  "properties": {
    "iso:country":"GB",
    "wof:name":"NG5 2EH",
    "wof:placetype":"postalcode"
},
  "geometry": {"coordinates":[-1.15133354608788,52.97314178770216],"type":"Point"}
}