{
  "type": "Feature",
  "properties": {
    "iso:country":"GB",
    "wof:name":"WV11 1DR",
    "wof:placetype":"postalcode"
},
  "geometry": {"coordinates":[-2.09676512235337,52.61281057058937],"type":"Point"}
}