{
  "type": "Feature",
  "properties": {
    "iso:country":"GB",
    "wof:name":"S65 1DZ",
    "wof:placetype":"postalcode"
},
  "geometry": {"coordinates":[-1.35098278748367,53.43122984925225],"type":"Point"}
}