{
  "type": "Feature",
  "properties": {
    "iso:country":"GB",
    "wof:name":"BD20 7JR",
    "wof:placetype":"postalcode"
},
  "geometry": {"coordinates":[-1.9912448900676,53.89193567868624],"type":"Point"}
}