{
  "type": "Feature",
  "properties": {
    "iso:country":"GB",
    "wof:name":"BB7 4DW",
    "wof:placetype":"postalcode"
},
  "geometry": {"coordinates":[-2.3298353019883,53.89871741107338],"type":"Point"}
}