{
  "type": "Feature",
  "properties": {
    "iso:country": "GB",
    "wof:name": "BB7 4DW",
    "wof:placetype": "postalcode"
  },
  "geometry": {"coordinates":[-2.329836,53.898731],"type":"Point"}
}
