{
  "type": "Feature",
  "properties": {
    "iso:country":"GB",
    "wof:name":"TS22 5JZ",
    "wof:placetype":"postalcode"
},
  "geometry": {"coordinates":[-1.29768675607712,54.62576894499043],"type":"Point"}
}