{
  "type": "Feature",
  "properties": {
    "iso:country": "GB",
    "wof:name": "TS22 5JZ",
    "wof:placetype": "postalcode"
  },
  "geometry": {"coordinates":[-1.297702,54.625781],"type":"Point"}
}
