{
  "type": "Feature",
  "properties": {
    "iso:country":"GB",
    "wof:name":"SE26 4HW",
    "wof:placetype":"postalcode"
},
  "geometry": {"coordinates":[-0.04640563679106,51.42889638608636],"type":"Point"}
}