{
  "type": "Feature",
  "properties": {
    "date:inception_lower": "1980-01-01",
    "date:inception_upper": "1980-01-01",
    "iso:country": "GB",
    "wof:name": "SE26 4HW",
    "wof:placetype": "postalcode"
  },
  "geometry": {"coordinates":[-0.046406,51.428896],"type":"Point"}
}
