{
  "type": "Feature",
  "properties": {
    "iso:country":"GB",
    "wof:name":"PA1 2FE",
    "wof:placetype":"postalcode"
},
  "geometry": {"coordinates":[-4.47986066184251,55.84681055989171],"type":"Point"}
}