{
  "type": "Feature",
  "properties": {
    "iso:country": "GB",
    "wof:name": "NP20 7AD",
    "wof:placetype": "postalcode"
  },
  "geometry": {"coordinates":[-3.034517,51.605694],"type":"Point"}
}
