{
  "type": "Feature",
  "properties": {
    "date:inception_lower": "2013-12-01",
    "date:inception_upper": "2013-12-01",
    "iso:country": "GB",
    "wof:name": "ST1 3DP",
    "wof:placetype": "postalcode"
  },
  "geometry": {"coordinates":[-2.17246,53.014832],"type":"Point"}
}
