{
  "type": "Feature",
  "properties": {
    "iso:country": "GB",
    "wof:name": "WR5 2ZW",
    "wof:placetype": "postalcode"
  },
  "geometry": {"coordinates":[-2.216947,52.196683],"type":"Point"}
}
