{
  "type": "Feature",
  "properties": {
    "date:inception_lower":"2019-04-01",
    "date:inception_upper":"2019-04-30",
    "iso:country":"GB",
    "wof:name":"WR5 2ZW",
    "wof:placetype":"postalcode"
},
  "geometry": {"coordinates":[-2.216947,52.196683],"type":"Point"}
}