{
  "type": "Feature",
  "properties": {
    "date:inception_lower": "1995-01-01",
    "date:inception_upper": "1995-01-01",
    "iso:country": "GB",
    "wof:name": "KT13 0SH",
    "wof:placetype": "postalcode"
  },
  "geometry": {"coordinates":[-0.459813,51.359873],"type":"Point"}
}
