{
  "type": "Feature",
  "properties": {
    "iso:country":"GB",
    "wof:name":"G23 5PL",
    "wof:placetype":"postalcode"
},
  "geometry": {"coordinates":[-4.29792238469056,55.90237347853515],"type":"Point"}
}