{
  "type": "Feature",
  "properties": {
    "iso:country":"GB",
    "wof:name":"HU13 9AZ",
    "wof:placetype":"postalcode"
},
  "geometry": {"coordinates":[-0.42429873006989,53.73340556435416],"type":"Point"}
}