{
  "type": "Feature",
  "properties": {
    "iso:country": "GB",
    "wof:name": "NG33 5LL",
    "wof:placetype": "postalcode"
  },
  "geometry": {"coordinates":[-0.610512,52.780851],"type":"Point"}
}
