{
  "type": "Feature",
  "properties": {
    "iso:country":"GB",
    "wof:name":"NG33 5LL",
    "wof:placetype":"postalcode"
},
  "geometry": {"coordinates":[-0.61051179586583,52.78085122625653],"type":"Point"}
}