{
  "type": "Feature",
  "properties": {
    "iso:country":"GB",
    "wof:name":"NE23 2XQ",
    "wof:placetype":"postalcode"
},
  "geometry": {"coordinates":[-1.57439928145285,55.0928064902477],"type":"Point"}
}