{
  "type": "Feature",
  "properties": {
    "date:inception_lower":"1999-06-01",
    "date:inception_upper":"1999-06-30",
    "iso:country":"GB",
    "wof:name":"NE23 2XQ",
    "wof:placetype":"postalcode"
},
  "geometry": {"coordinates":[-1.574399,55.092806],"type":"Point"}
}