{
  "type": "Feature",
  "properties": {
    "iso:country": "GB",
    "wof:name": "NE23 2XQ",
    "wof:placetype": "postalcode"
  },
  "geometry": {"coordinates":[-1.574399,55.092806],"type":"Point"}
}
