{
  "type": "Feature",
  "properties": {
    "iso:country":"GB",
    "wof:name":"M28 7FW",
    "wof:placetype":"postalcode"
},
  "geometry": {"coordinates":[-2.38495415182977,53.51867802379542],"type":"Point"}
}