{
  "type": "Feature",
  "properties": {
    "iso:country":"GB",
    "wof:name":"CO15 2AZ",
    "wof:placetype":"postalcode"
},
  "geometry": {"coordinates":[1.13761650526765,51.7925714620984],"type":"Point"}
}