{
  "type": "Feature",
  "properties": {
    "iso:country":"GB",
    "wof:name":"CH61 2XB",
    "wof:placetype":"postalcode"
},
  "geometry": {"coordinates":[-3.11491889780464,53.34747740984478],"type":"Point"}
}