{
  "type": "Feature",
  "properties": {
    "date:inception_lower":"2002-11-01",
    "date:inception_upper":"2002-11-30",
    "iso:country":"GB",
    "wof:name":"DT5 1HX",
    "wof:placetype":"postalcode"
},
  "geometry": {"coordinates":[-2.43349,50.546416],"type":"Point"}
}