{
  "type": "Feature",
  "properties": {
    "iso:country":"GB",
    "wof:name":"DT5 1HX",
    "wof:placetype":"postalcode"
},
  "geometry": {"coordinates":[-2.43348968219696,50.54641644917556],"type":"Point"}
}