{
  "type": "Feature",
  "properties": {
    "iso:country": "GB",
    "wof:name": "DT5 1HX",
    "wof:placetype": "postalcode"
  },
  "geometry": {"coordinates":[-2.43349,50.546416],"type":"Point"}
}
