{
  "type": "Feature",
  "properties": {
    "iso:country": "GB",
    "wof:name": "DN9 1HS",
    "wof:placetype": "postalcode"
  },
  "geometry": {"coordinates":[-0.811439,53.522849],"type":"Point"}
}
