{
  "type": "Feature",
  "properties": {
    "date:inception_lower": "1980-01-01",
    "date:inception_upper": "1980-01-01",
    "iso:country": "GB",
    "wof:name": "DN9 1HS",
    "wof:placetype": "postalcode"
  },
  "geometry": {"coordinates":[-0.811439,53.522849],"type":"Point"}
}
