{
  "type": "Feature",
  "properties": {
    "iso:country": "GB",
    "wof:name": "PE19 8TD",
    "wof:placetype": "postalcode"
  },
  "geometry": {"coordinates":[-0.296898,52.215009],"type":"Point"}
}
