{
  "type": "Feature",
  "properties": {
    "iso:country":"GB",
    "wof:name":"PE19 8TD",
    "wof:placetype":"postalcode"
},
  "geometry": {"coordinates":[-0.29689798406614,52.21500900309679],"type":"Point"}
}