{
  "type": "Feature",
  "properties": {
    "iso:country":"GB",
    "wof:name":"NR18 0EE",
    "wof:placetype":"postalcode"
},
  "geometry": {"coordinates":[1.11309126460348,52.58012760318571],"type":"Point"}
}