{
  "type": "Feature",
  "properties": {
    "date:inception_lower":"1980-01-01",
    "date:inception_upper":"1980-01-31",
    "iso:country":"GB",
    "wof:name":"NR18 0EE",
    "wof:placetype":"postalcode"
},
  "geometry": {"coordinates":[1.113091,52.580128],"type":"Point"}
}