{
  "type": "Feature",
  "properties": {
    "iso:country": "GB",
    "wof:name": "NR18 0EE",
    "wof:placetype": "postalcode"
  },
  "geometry": {"coordinates":[1.113091,52.580128],"type":"Point"}
}
