{
  "type": "Feature",
  "properties": {
    "date:inception_lower":"1980-01-01",
    "date:inception_upper":"1980-01-31",
    "iso:country":"GB",
    "wof:name":"ML9 2EW",
    "wof:placetype":"postalcode"
},
  "geometry": {"coordinates":[-3.958062,55.737507],"type":"Point"}
}