{
  "type": "Feature",
  "properties": {
    "iso:country":"GB",
    "wof:name":"ML9 2EW",
    "wof:placetype":"postalcode"
},
  "geometry": {"coordinates":[-3.95806209641768,55.73750726043073],"type":"Point"}
}