{
  "type": "Feature",
  "properties": {
    "iso:country":"GB",
    "wof:name":"N5 2EN",
    "wof:placetype":"postalcode"
},
  "geometry": {"coordinates":[-0.09373725564426,51.55038333591455],"type":"Point"}
}