{
  "type": "Feature",
  "properties": {
    "date:inception_lower": "1985-10-01",
    "date:inception_upper": "1985-10-01",
    "iso:country": "GB",
    "wof:name": "PO14 4DR",
    "wof:placetype": "postalcode"
  },
  "geometry": {"coordinates":[-1.254519,50.858187],"type":"Point"}
}
