{
  "type": "Feature",
  "properties": {
    "iso:country":"GB",
    "wof:name":"RG2 7SB",
    "wof:placetype":"postalcode"
},
  "geometry": {"coordinates":[-0.96406448308183,51.4338622841429],"type":"Point"}
}