{
  "type": "Feature",
  "properties": {
    "iso:country":"GB",
    "wof:name":"B31 2DP",
    "wof:placetype":"postalcode"
},
  "geometry": {"coordinates":[-1.95137877728637,52.41522430928253],"type":"Point"}
}