{
  "type": "Feature",
  "properties": {
    "iso:country":"GB",
    "wof:name":"DN37 9HU",
    "wof:placetype":"postalcode"
},
  "geometry": {"coordinates":[-0.13278526236468,53.57536078610639],"type":"Point"}
}