{
  "type": "Feature",
  "properties": {
    "iso:country": "GB",
    "wof:name": "DN37 9HU",
    "wof:placetype": "postalcode"
  },
  "geometry": {"coordinates":[-0.132785,53.575361],"type":"Point"}
}
