{
  "type": "Feature",
  "properties": {
    "date:inception_lower": "2006-07-01",
    "date:inception_upper": "2006-07-01",
    "iso:country": "GB",
    "wof:name": "DN37 9HU",
    "wof:placetype": "postalcode"
  },
  "geometry": {"coordinates":[-0.132785,53.575361],"type":"Point"}
}
