{
  "type": "Feature",
  "properties": {
    "iso:country": "GB",
    "wof:name": "B69 2BZ",
    "wof:placetype": "postalcode"
  },
  "geometry": {"coordinates":[-2.020035,52.500889],"type":"Point"}
}
