{
  "type": "Feature",
  "properties": {
    "date:inception_lower": "1995-01-01",
    "date:inception_upper": "1995-01-01",
    "iso:country": "GB",
    "wof:name": "B69 2BZ",
    "wof:placetype": "postalcode"
  },
  "geometry": {"coordinates":[-2.020035,52.500889],"type":"Point"}
}
