{
  "type": "Feature",
  "properties": {
    "iso:country":"GB",
    "wof:name":"B69 2BZ",
    "wof:placetype":"postalcode"
},
  "geometry": {"coordinates":[-2.02003477531758,52.50088909431853],"type":"Point"}
}