{
  "type": "Feature",
  "properties": {
    "iso:country":"GB",
    "wof:name":"SE6 4JG",
    "wof:placetype":"postalcode"
},
  "geometry": {"coordinates":[-0.01754203956681,51.45063280667387],"type":"Point"}
}