{
  "type": "Feature",
  "properties": {
    "iso:country":"GB",
    "wof:name":"SY2 6AT",
    "wof:placetype":"postalcode"
},
  "geometry": {"coordinates":[-2.74788452750097,52.70865737655643],"type":"Point"}
}