{
  "type": "Feature",
  "properties": {
    "date:inception_lower": "1999-06-01",
    "date:inception_upper": "1999-06-01",
    "iso:country": "GB",
    "wof:name": "NP19 7RG",
    "wof:placetype": "postalcode"
  },
  "geometry": {"coordinates":[-2.967795,51.598476],"type":"Point"}
}
