{
  "type": "Feature",
  "properties": {
    "iso:country": "GB",
    "wof:name": "IP28 7LF",
    "wof:placetype": "postalcode"
  },
  "geometry": {"coordinates":[0.51746,52.341804],"type":"Point"}
}
