{
  "type": "Feature",
  "properties": {
    "date:inception_lower":"1980-01-01",
    "date:inception_upper":"1980-01-31",
    "iso:country":"GB",
    "wof:name":"IP28 7LF",
    "wof:placetype":"postalcode"
},
  "geometry": {"coordinates":[0.51746,52.341804],"type":"Point"}
}