{
  "type": "Feature",
  "properties": {
    "iso:country":"GB",
    "wof:name":"IP28 7LF",
    "wof:placetype":"postalcode"
},
  "geometry": {"coordinates":[0.51746154981838,52.34175887501912],"type":"Point"}
}