{
  "type": "Feature",
  "properties": {
    "iso:country":"GB",
    "wof:name":"OL12 9EF",
    "wof:placetype":"postalcode"
},
  "geometry": {"coordinates":[-2.14290993088205,53.6314856981563],"type":"Point"}
}