{
  "type": "Feature",
  "properties": {
    "date:inception_lower": "1981-06-01",
    "date:inception_upper": "1981-06-01",
    "iso:country": "GB",
    "wof:name": "OL12 9EF",
    "wof:placetype": "postalcode"
  },
  "geometry": {"coordinates":[-2.14291,53.631486],"type":"Point"}
}
