{
  "type": "Feature",
  "properties": {
    "iso:country": "GB",
    "wof:name": "OL12 9EF",
    "wof:placetype": "postalcode"
  },
  "geometry": {"coordinates":[-2.14291,53.631486],"type":"Point"}
}
