{
  "type": "Feature",
  "properties": {
    "iso:country":"GB",
    "wof:name":"AL4 9JA",
    "wof:placetype":"postalcode"
},
  "geometry": {"coordinates":[-0.29316182868566,51.76541652011326],"type":"Point"}
}