{
  "type": "Feature",
  "properties": {
    "date:inception_lower": "1980-01-01",
    "date:inception_upper": "1980-01-01",
    "iso:country": "GB",
    "wof:name": "AL4 9JA",
    "wof:placetype": "postalcode"
  },
  "geometry": {"coordinates":[-0.293162,51.765417],"type":"Point"}
}
