{
  "type": "Feature",
  "properties": {
    "iso:country": "GB",
    "wof:name": "RM3 0EN",
    "wof:placetype": "postalcode"
  },
  "geometry": {"coordinates":[0.233645,51.593935],"type":"Point"}
}
