{
  "type": "Feature",
  "properties": {
    "iso:country":"GB",
    "wof:name":"RM3 0EN",
    "wof:placetype":"postalcode"
},
  "geometry": {"coordinates":[0.23337285816755,51.5936231146692],"type":"Point"}
}