{
  "type": "Feature",
  "properties": {
    "iso:country": "GB",
    "wof:name": "HG5 9LB",
    "wof:placetype": "postalcode"
  },
  "geometry": {"coordinates":[-1.439209,54.059185],"type":"Point"}
}
