{
  "type": "Feature",
  "properties": {
    "iso:country":"GB",
    "wof:name":"NG2 7JP",
    "wof:placetype":"postalcode"
},
  "geometry": {"coordinates":[-1.14551945196983,52.91151291842188],"type":"Point"}
}