{
  "type": "Feature",
  "properties": {
    "date:inception_lower":"2015-04-01",
    "date:inception_upper":"2015-04-30",
    "iso:country":"GB",
    "wof:name":"NG2 7JP",
    "wof:placetype":"postalcode"
},
  "geometry": {"coordinates":[-1.145519,52.911513],"type":"Point"}
}