{
  "type": "Feature",
  "properties": {
    "iso:country":"GB",
    "wof:name":"SO50 5EP",
    "wof:placetype":"postalcode"
},
  "geometry": {"coordinates":[-1.36154554277523,50.96325974537309],"type":"Point"}
}