{
  "type": "Feature",
  "properties": {
    "iso:country":"GB",
    "wof:name":"TN22 1PG",
    "wof:placetype":"postalcode"
},
  "geometry": {"coordinates":[0.10183603734298,50.98104141593895],"type":"Point"}
}