{
  "type": "Feature",
  "properties": {
    "iso:country": "GB",
    "wof:name": "CF72 8TZ",
    "wof:placetype": "postalcode"
  },
  "geometry": {"coordinates":[-3.39981,51.534251],"type":"Point"}
}
