{
  "type": "Feature",
  "properties": {
    "iso:country":"GB",
    "wof:name":"SS7 1BD",
    "wof:placetype":"postalcode"
},
  "geometry": {"coordinates":[0.61567874276231,51.55086428073335],"type":"Point"}
}