{
  "type": "Feature",
  "properties": {
    "date:inception_lower":"2004-11-01",
    "date:inception_upper":"2004-11-30",
    "iso:country":"GB",
    "wof:name":"SS7 1BD",
    "wof:placetype":"postalcode"
},
  "geometry": {"coordinates":[0.615679,51.550864],"type":"Point"}
}