{
  "type": "Feature",
  "properties": {
    "iso:country": "GB",
    "wof:name": "SS7 1BD",
    "wof:placetype": "postalcode"
  },
  "geometry": {"coordinates":[0.615679,51.550864],"type":"Point"}
}
