{
  "type": "Feature",
  "properties": {
    "iso:country":"GB",
    "wof:name":"OX2 0QL",
    "wof:placetype":"postalcode"
},
  "geometry": {"coordinates":[-1.29178836407301,51.75311407034152],"type":"Point"}
}