{
  "type": "Feature",
  "properties": {
    "date:inception_lower":"1998-06-01",
    "date:inception_upper":"1998-06-30",
    "iso:country":"GB",
    "wof:name":"OX2 0QL",
    "wof:placetype":"postalcode"
},
  "geometry": {"coordinates":[-1.291788,51.753114],"type":"Point"}
}