{
  "type": "Feature",
  "properties": {
    "iso:country": "GB",
    "wof:name": "BS16 4JZ",
    "wof:placetype": "postalcode"
  },
  "geometry": {"coordinates":[-2.51148,51.47236],"type":"Point"}
}
