{
  "type": "Feature",
  "properties": {
    "date:inception_lower": "1985-04-01",
    "date:inception_upper": "1985-04-01",
    "iso:country": "GB",
    "wof:name": "NE6 2RT",
    "wof:placetype": "postalcode"
  },
  "geometry": {"coordinates":[-1.569603,54.976095],"type":"Point"}
}
