{
  "type": "Feature",
  "properties": {
    "iso:country":"GB",
    "wof:name":"B9 5PN",
    "wof:placetype":"postalcode"
},
  "geometry": {"coordinates":[-1.85170542201937,52.47376545722918],"type":"Point"}
}