{
  "type": "Feature",
  "properties": {
    "date:inception_lower": "1980-01-01",
    "date:inception_upper": "1980-01-01",
    "iso:country": "GB",
    "wof:name": "GL2 8JX",
    "wof:placetype": "postalcode"
  },
  "geometry": {"coordinates":[-2.357398,51.836222],"type":"Point"}
}
