{
  "type": "Feature",
  "properties": {
    "iso:country":"GB",
    "wof:name":"GL2 8JX",
    "wof:placetype":"postalcode"
},
  "geometry": {"coordinates":[-2.35700311402385,51.83753755529456],"type":"Point"}
}