{
  "type": "Feature",
  "properties": {
    "iso:country":"GB",
    "wof:name":"PE20 2BU",
    "wof:placetype":"postalcode"
},
  "geometry": {"coordinates":[-0.04575016578096,52.87964978742666],"type":"Point"}
}