{
  "type": "Feature",
  "properties": {
    "iso:country":"GB",
    "wof:name":"SG5 3NX",
    "wof:placetype":"postalcode"
},
  "geometry": {"coordinates":[-0.36507827282922,51.99629473271279],"type":"Point"}
}