{
  "type": "Feature",
  "properties": {
    "iso:country":"GB",
    "wof:name":"G62 6BZ",
    "wof:placetype":"postalcode"
},
  "geometry": {"coordinates":[-4.31783673351614,55.93877703030498],"type":"Point"}
}