{
  "type": "Feature",
  "properties": {
    "iso:country":"GB",
    "wof:name":"E17 3RR",
    "wof:placetype":"postalcode"
},
  "geometry": {"coordinates":[-0.00005015590565,51.59188918409087],"type":"Point"}
}