{
  "type": "Feature",
  "properties": {
    "iso:country":"GB",
    "wof:name":"SE20 7JD",
    "wof:placetype":"postalcode"
},
  "geometry": {"coordinates":[-0.05235469820569,51.41585701223441],"type":"Point"}
}