{
  "type": "Feature",
  "properties": {
    "iso:country":"GB",
    "wof:name":"GU19 5AR",
    "wof:placetype":"postalcode"
},
  "geometry": {"coordinates":[-0.69128798236056,51.36294743880359],"type":"Point"}
}