{
  "type": "Feature",
  "properties": {
    "iso:country":"GB",
    "wof:name":"NW1 9NX",
    "wof:placetype":"postalcode"
},
  "geometry": {"coordinates":[-0.14214192121322,51.53980234924434],"type":"Point"}
}