{
  "type": "Feature",
  "properties": {
    "iso:country":"GB",
    "wof:name":"NP4 0YN",
    "wof:placetype":"postalcode"
},
  "geometry": {"coordinates":[-3.01410703383336,51.69282919937229],"type":"Point"}
}