{
  "type": "Feature",
  "properties": {
    "date:inception_lower": "1980-01-01",
    "date:inception_upper": "1980-01-01",
    "iso:country": "GB",
    "wof:name": "NP4 0YN",
    "wof:placetype": "postalcode"
  },
  "geometry": {"coordinates":[-3.014107,51.692829],"type":"Point"}
}
