{
  "type": "Feature",
  "properties": {
    "iso:country":"GB",
    "wof:name":"SG1 2DY",
    "wof:placetype":"postalcode"
},
  "geometry": {"coordinates":[-0.21741075316156,51.90364072894401],"type":"Point"}
}