{
  "type": "Feature",
  "properties": {
    "iso:country":"GB",
    "wof:name":"CT6 7QA",
    "wof:placetype":"postalcode"
},
  "geometry": {"coordinates":[1.10967549028,51.35838327339921],"type":"Point"}
}