{
  "type": "Feature",
  "properties": {
    "iso:country": "GB",
    "wof:name": "CT6 7QA",
    "wof:placetype": "postalcode"
  },
  "geometry": {"coordinates":[1.109676,51.358383],"type":"Point"}
}
