{
  "type": "Feature",
  "properties": {
    "date:inception_lower": "1980-01-01",
    "date:inception_upper": "1980-01-01",
    "iso:country": "GB",
    "wof:name": "EH19 3EX",
    "wof:placetype": "postalcode"
  },
  "geometry": {"coordinates":[-3.104254,55.872789],"type":"Point"}
}
