{
  "type": "Feature",
  "properties": {
    "iso:country":"GB",
    "wof:name":"EH19 3EX",
    "wof:placetype":"postalcode"
},
  "geometry": {"coordinates":[-3.10425399509303,55.87278900458558],"type":"Point"}
}