{
  "type": "Feature",
  "properties": {
    "iso:country": "GB",
    "wof:name": "DT11 9FP",
    "wof:placetype": "postalcode"
  },
  "geometry": {"coordinates":[-2.167947,50.850024],"type":"Point"}
}
