{
  "type": "Feature",
  "properties": {
    "iso:country": "GB",
    "wof:name": "LN5 7LY",
    "wof:placetype": "postalcode"
  },
  "geometry": {"coordinates":[-0.536993,53.222346],"type":"Point"}
}
