{
  "type": "Feature",
  "properties": {
    "date:inception_lower": "1980-01-01",
    "date:inception_upper": "1980-01-01",
    "iso:country": "GB",
    "wof:name": "LN5 7LY",
    "wof:placetype": "postalcode"
  },
  "geometry": {"coordinates":[-0.536993,53.222346],"type":"Point"}
}
