{
  "type": "Feature",
  "properties": {
    "iso:country":"GB",
    "wof:name":"LN5 7LY",
    "wof:placetype":"postalcode"
},
  "geometry": {"coordinates":[-0.53699344191877,53.22234588646999],"type":"Point"}
}