{
  "type": "Feature",
  "properties": {
    "date:inception_lower": "1980-01-01",
    "date:inception_upper": "1980-01-01",
    "iso:country": "GB",
    "wof:name": "B31 3PU",
    "wof:placetype": "postalcode"
  },
  "geometry": {"coordinates":[-1.960193,52.390091],"type":"Point"}
}
