{
  "type": "Feature",
  "properties": {
    "iso:country":"GB",
    "wof:name":"PE10 0RF",
    "wof:placetype":"postalcode"
},
  "geometry": {"coordinates":[-0.3889038411164,52.80270987504253],"type":"Point"}
}