{
  "type": "Feature",
  "properties": {
    "iso:country":"GB",
    "wof:name":"M3 6BJ",
    "wof:placetype":"postalcode"
},
  "geometry": {"coordinates":[-2.25850915147846,53.48665121534214],"type":"Point"}
}