{
  "type": "Feature",
  "properties": {
    "iso:country":"GB",
    "wof:name":"DN32 9RP",
    "wof:placetype":"postalcode"
},
  "geometry": {"coordinates":[-0.0738201727394,53.55105228997276],"type":"Point"}
}