{
  "type": "Feature",
  "properties": {
    "date:inception_lower": "1991-09-01",
    "date:inception_upper": "1991-09-01",
    "iso:country": "GB",
    "wof:name": "RG12 8UN",
    "wof:placetype": "postalcode"
  },
  "geometry": {"coordinates":[-0.774599,51.40059],"type":"Point"}
}
