{
  "type": "Feature",
  "properties": {
    "iso:country":"GB",
    "wof:name":"RG12 8UN",
    "wof:placetype":"postalcode"
},
  "geometry": {"coordinates":[-0.77459927620568,51.40059001622448],"type":"Point"}
}