{
  "type": "Feature",
  "properties": {
    "iso:country":"GB",
    "wof:name":"E2 0SP",
    "wof:placetype":"postalcode"
},
  "geometry": {"coordinates":[-0.04266578733477,51.52946194528465],"type":"Point"}
}