{
  "type": "Feature",
  "properties": {
    "iso:country": "GB",
    "wof:name": "HD1 2AD",
    "wof:placetype": "postalcode"
  },
  "geometry": {"coordinates":[-1.782039,53.646312],"type":"Point"}
}
