{
  "type": "Feature",
  "properties": {
    "iso:country":"GB",
    "wof:name":"LS12 6BZ",
    "wof:placetype":"postalcode"
},
  "geometry": {"coordinates":[-1.57501096159126,53.78424585301847],"type":"Point"}
}