{
  "type": "Feature",
  "properties": {
    "iso:country": "GB",
    "wof:name": "LS12 6BZ",
    "wof:placetype": "postalcode"
  },
  "geometry": {"coordinates":[-1.576927,53.782723],"type":"Point"}
}
