{
  "type": "Feature",
  "properties": {
    "iso:country":"GB",
    "wof:name":"SY3 6BW",
    "wof:placetype":"postalcode"
},
  "geometry": {"coordinates":[-2.77364112585951,52.69373074759655],"type":"Point"}
}