{
  "type": "Feature",
  "properties": {
    "iso:country":"GB",
    "wof:name":"WF11 9DB",
    "wof:placetype":"postalcode"
},
  "geometry": {"coordinates":[-1.23710872255388,53.70972295436943],"type":"Point"}
}