{
  "type": "Feature",
  "properties": {
    "iso:country": "GB",
    "wof:name": "WF11 9DB",
    "wof:placetype": "postalcode"
  },
  "geometry": {"coordinates":[-1.237109,53.709723],"type":"Point"}
}
