{
  "type": "Feature",
  "properties": {
    "date:inception_lower":"1980-01-01",
    "date:inception_upper":"1980-01-31",
    "iso:country":"GB",
    "wof:name":"NE46 1LD",
    "wof:placetype":"postalcode"
},
  "geometry": {"coordinates":[-2.081858,54.968522],"type":"Point"}
}