{
  "type": "Feature",
  "properties": {
    "iso:country": "GB",
    "wof:name": "NE46 1LD",
    "wof:placetype": "postalcode"
  },
  "geometry": {"coordinates":[-2.081858,54.968522],"type":"Point"}
}
