{
  "type": "Feature",
  "properties": {
    "iso:country": "GB",
    "wof:name": "HP17 8EZ",
    "wof:placetype": "postalcode"
  },
  "geometry": {"coordinates":[-0.93821,51.770198],"type":"Point"}
}
