{
  "type": "Feature",
  "properties": {
    "iso:country":"GB",
    "wof:name":"HP17 8EZ",
    "wof:placetype":"postalcode"
},
  "geometry": {"coordinates":[-0.93821045629821,51.77019774613827],"type":"Point"}
}