{
  "type": "Feature",
  "properties": {
    "iso:country":"GB",
    "wof:name":"WD3 1HX",
    "wof:placetype":"postalcode"
},
  "geometry": {"coordinates":[-0.46899186201636,51.64363315377531],"type":"Point"}
}