{
  "type": "Feature",
  "properties": {
    "iso:country":"GB",
    "wof:name":"NR1 4JT",
    "wof:placetype":"postalcode"
},
  "geometry": {"coordinates":[1.32342327064264,52.63579743525506],"type":"Point"}
}