{
  "type": "Feature",
  "properties": {
    "iso:country":"GB",
    "wof:name":"NN3 9SN",
    "wof:placetype":"postalcode"
},
  "geometry": {"coordinates":[-0.8184464371233,52.25250872953893],"type":"Point"}
}