{
  "type": "Feature",
  "properties": {
    "iso:country":"GB",
    "wof:name":"HU19 2HP",
    "wof:placetype":"postalcode"
},
  "geometry": {"coordinates":[0.03752849714735,53.72744915418038],"type":"Point"}
}