{
  "type": "Feature",
  "properties": {
    "iso:country":"GB",
    "wof:name":"WN8 7HE",
    "wof:placetype":"postalcode"
},
  "geometry": {"coordinates":[-2.76704061165341,53.59124374816204],"type":"Point"}
}