{
  "type": "Feature",
  "properties": {
    "date:inception_lower": "1983-01-01",
    "date:inception_upper": "1983-01-01",
    "iso:country": "GB",
    "wof:name": "PO16 0PN",
    "wof:placetype": "postalcode"
  },
  "geometry": {"coordinates":[-1.175959,50.852875],"type":"Point"}
}
