{
  "type": "Feature",
  "properties": {
    "iso:country": "GB",
    "wof:name": "CV9 3QN",
    "wof:placetype": "postalcode"
  },
  "geometry": {"coordinates":[-1.493804,52.629588],"type":"Point"}
}
