{
  "type": "Feature",
  "properties": {
    "iso:country":"GB",
    "wof:name":"CV9 3QN",
    "wof:placetype":"postalcode"
},
  "geometry": {"coordinates":[-1.49380399188559,52.62958780243112],"type":"Point"}
}