{
  "type": "Feature",
  "properties": {
    "date:inception_lower": "1987-04-01",
    "date:inception_upper": "1987-04-01",
    "iso:country": "GB",
    "wof:name": "DT11 7XA",
    "wof:placetype": "postalcode"
  },
  "geometry": {"coordinates":[-2.161657,50.865885],"type":"Point"}
}
