{
  "type": "Feature",
  "properties": {
    "iso:country":"GB",
    "wof:name":"DT11 7XA",
    "wof:placetype":"postalcode"
},
  "geometry": {"coordinates":[-2.161656548045,50.8658848740276],"type":"Point"}
}