{
  "type": "Feature",
  "properties": {
    "iso:country":"GB",
    "wof:name":"SY20 8TB",
    "wof:placetype":"postalcode"
},
  "geometry": {"coordinates":[-3.94216914229079,52.54133810048251],"type":"Point"}
}