{
  "type": "Feature",
  "properties": {
    "iso:country": "GB",
    "wof:name": "SY20 8TB",
    "wof:placetype": "postalcode"
  },
  "geometry": {"coordinates":[-3.942169,52.541338],"type":"Point"}
}
