{
  "type": "Feature",
  "properties": {
    "iso:country":"GB",
    "wof:name":"LE4 2LL",
    "wof:placetype":"postalcode"
},
  "geometry": {"coordinates":[-1.144951273631,52.66730219275581],"type":"Point"}
}