{
  "type": "Feature",
  "properties": {
    "date:inception_lower": "2005-03-01",
    "date:inception_upper": "2005-03-01",
    "iso:country": "GB",
    "wof:name": "TA5 1JX",
    "wof:placetype": "postalcode"
  },
  "geometry": {"coordinates":[-3.159836,51.15658],"type":"Point"}
}
