{
  "type": "Feature",
  "properties": {
    "iso:country":"GB",
    "wof:name":"LL16 3ER",
    "wof:placetype":"postalcode"
},
  "geometry": {"coordinates":[-3.40733630279678,53.18704254339271],"type":"Point"}
}