{
  "type": "Feature",
  "properties": {
    "iso:country": "GB",
    "wof:name": "LL16 3ER",
    "wof:placetype": "postalcode"
  },
  "geometry": {"coordinates":[-3.407336,53.187043],"type":"Point"}
}
