{
  "type": "Feature",
  "properties": {
    "iso:country":"GB",
    "wof:name":"SL5 8PS",
    "wof:placetype":"postalcode"
},
  "geometry": {"coordinates":[-0.68629140610915,51.4225994008509],"type":"Point"}
}