{
  "type": "Feature",
  "properties": {
    "iso:country": "GB",
    "wof:name": "TF10 8PQ",
    "wof:placetype": "postalcode"
  },
  "geometry": {"coordinates":[-2.492701,52.769564],"type":"Point"}
}
