{
  "type": "Feature",
  "properties": {
    "date:inception_lower": "1980-01-01",
    "date:inception_upper": "1980-01-01",
    "iso:country": "GB",
    "wof:name": "SA47 0NF",
    "wof:placetype": "postalcode"
  },
  "geometry": {"coordinates":[-4.308288,52.193003],"type":"Point"}
}
