{
  "type": "Feature",
  "properties": {
    "iso:country":"GB",
    "wof:name":"S35 4JL",
    "wof:placetype":"postalcode"
},
  "geometry": {"coordinates":[-1.48955910308971,53.47129005999557],"type":"Point"}
}