{
  "type": "Feature",
  "properties": {
    "iso:country":"GB",
    "wof:name":"TA2 6FB",
    "wof:placetype":"postalcode"
},
  "geometry": {"coordinates":[-3.13962559971261,51.02900771574284],"type":"Point"}
}