{
  "type": "Feature",
  "properties": {
    "date:inception_lower": "1995-07-01",
    "date:inception_upper": "1995-07-01",
    "iso:country": "GB",
    "wof:name": "BH17 8QX",
    "wof:placetype": "postalcode"
  },
  "geometry": {"coordinates":[-1.963115,50.741265],"type":"Point"}
}
