{
  "type": "Feature",
  "properties": {
    "iso:country":"GB",
    "wof:name":"BH17 8QX",
    "wof:placetype":"postalcode"
},
  "geometry": {"coordinates":[-1.9631146425559,50.74126488600592],"type":"Point"}
}