{
  "type": "Feature",
  "properties": {
    "iso:country":"GB",
    "wof:name":"BS32 0HB",
    "wof:placetype":"postalcode"
},
  "geometry": {"coordinates":[-2.53222988003452,51.52579475834739],"type":"Point"}
}