{
  "type": "Feature",
  "properties": {
    "iso:country": "GB",
    "wof:name": "SY4 2LN",
    "wof:placetype": "postalcode"
  },
  "geometry": {"coordinates":[-2.850272,52.81775],"type":"Point"}
}
