{
  "type": "Feature",
  "properties": {
    "iso:country":"GB",
    "wof:name":"SY4 2LN",
    "wof:placetype":"postalcode"
},
  "geometry": {"coordinates":[-2.85027168342565,52.81775043686087],"type":"Point"}
}