{
  "type": "Feature",
  "properties": {
    "date:inception_lower":"1982-03-01",
    "date:inception_upper":"1982-03-31",
    "iso:country":"GB",
    "wof:name":"CM18 6RF",
    "wof:placetype":"postalcode"
},
  "geometry": {"coordinates":[0.110416,51.756596],"type":"Point"}
}