{
  "type": "Feature",
  "properties": {
    "date:inception_lower":"2003-02-01",
    "date:inception_upper":"2003-02-28",
    "iso:country":"GB",
    "wof:name":"LA13 0AX",
    "wof:placetype":"postalcode"
},
  "geometry": {"coordinates":[-3.19514,54.117459],"type":"Point"}
}