{
  "type": "Feature",
  "properties": {
    "iso:country":"GB",
    "wof:name":"TS25 1AX",
    "wof:placetype":"postalcode"
},
  "geometry": {"coordinates":[-1.18857115114545,54.66140359883008],"type":"Point"}
}