{
  "type": "Feature",
  "properties": {
    "iso:country": "GB",
    "wof:name": "RG30 2HT",
    "wof:placetype": "postalcode"
  },
  "geometry": {"coordinates":[-1.002662,51.452999],"type":"Point"}
}
