{
  "type": "Feature",
  "properties": {
    "iso:country": "GB",
    "wof:name": "RG30 2HT",
    "wof:placetype": "postalcode"
  },
  "geometry": {"coordinates":[-1.002426,51.452963],"type":"Point"}
}
