{
  "type": "Feature",
  "properties": {
    "date:inception_lower": "1999-12-01",
    "date:inception_upper": "1999-12-01",
    "iso:country": "GB",
    "wof:name": "RG30 2HT",
    "wof:placetype": "postalcode"
  },
  "geometry": {"coordinates":[-1.002426,51.452963],"type":"Point"}
}
