{
  "type": "Feature",
  "properties": {
    "iso:country":"GB",
    "wof:name":"RG30 2HT",
    "wof:placetype":"postalcode"
},
  "geometry": {"coordinates":[-1.00266221705399,51.45299890101147],"type":"Point"}
}