{
  "type": "Feature",
  "properties": {
    "iso:country":"GB",
    "wof:name":"KA10 6AT",
    "wof:placetype":"postalcode"
},
  "geometry": {"coordinates":[-4.66818477875638,55.54346441574132],"type":"Point"}
}