{
  "type": "Feature",
  "properties": {
    "iso:country":"GB",
    "wof:name":"LL22 9RT",
    "wof:placetype":"postalcode"
},
  "geometry": {"coordinates":[-3.5473712701607,53.26079243566234],"type":"Point"}
}