{
  "type": "Feature",
  "properties": {
    "date:inception_lower": "1980-01-01",
    "date:inception_upper": "1980-01-01",
    "iso:country": "GB",
    "wof:name": "LL22 9RT",
    "wof:placetype": "postalcode"
  },
  "geometry": {"coordinates":[-3.547371,53.260792],"type":"Point"}
}
