{
  "type": "Feature",
  "properties": {
    "iso:country":"GB",
    "wof:name":"PL22 0RN",
    "wof:placetype":"postalcode"
},
  "geometry": {"coordinates":[-4.58838476888179,50.43015716343663],"type":"Point"}
}