{
  "type": "Feature",
  "properties": {
    "iso:country": "GB",
    "wof:name": "SA4 3HF",
    "wof:placetype": "postalcode"
  },
  "geometry": {"coordinates":[-4.052257,51.648781],"type":"Point"}
}
