{
  "type": "Feature",
  "properties": {
    "date:inception_lower":"1987-04-01",
    "date:inception_upper":"1987-04-30",
    "iso:country":"GB",
    "wof:name":"SA4 3HF",
    "wof:placetype":"postalcode"
},
  "geometry": {"coordinates":[-4.052257,51.648781],"type":"Point"}
}