{
  "type": "Feature",
  "properties": {
    "iso:country":"GB",
    "wof:name":"SA4 3HF",
    "wof:placetype":"postalcode"
},
  "geometry": {"coordinates":[-4.05225717692805,51.64878124838314],"type":"Point"}
}