{
  "type": "Feature",
  "properties": {
    "date:inception_lower": "1980-01-01",
    "date:inception_upper": "1980-01-01",
    "iso:country": "GB",
    "wof:name": "NN14 4NZ",
    "wof:placetype": "postalcode"
  },
  "geometry": {"coordinates":[-0.533245,52.397661],"type":"Point"}
}
