{
  "type": "Feature",
  "properties": {
    "iso:country":"GB",
    "wof:name":"NN14 4NZ",
    "wof:placetype":"postalcode"
},
  "geometry": {"coordinates":[-0.53332998223531,52.39776957448031],"type":"Point"}
}