{
  "type": "Feature",
  "properties": {
    "date:inception_lower": "1985-10-01",
    "date:inception_upper": "1985-10-01",
    "iso:country": "GB",
    "wof:name": "HP20 1XP",
    "wof:placetype": "postalcode"
  },
  "geometry": {"coordinates":[-0.791048,51.824047],"type":"Point"}
}
