{
  "type": "Feature",
  "properties": {
    "iso:country": "GB",
    "wof:name": "WN3 4PB",
    "wof:placetype": "postalcode"
  },
  "geometry": {"coordinates":[-2.607757,53.528008],"type":"Point"}
}
