{
  "type": "Feature",
  "properties": {
    "iso:country":"GB",
    "wof:name":"WN3 4PB",
    "wof:placetype":"postalcode"
},
  "geometry": {"coordinates":[-2.6077571430835,53.52800848780004],"type":"Point"}
}