{
  "type": "Feature",
  "properties": {
    "date:inception_lower": "1993-08-01",
    "date:inception_upper": "1993-08-01",
    "iso:country": "GB",
    "wof:name": "WN3 4PB",
    "wof:placetype": "postalcode"
  },
  "geometry": {"coordinates":[-2.607757,53.528008],"type":"Point"}
}
