{
  "type": "Feature",
  "properties": {
    "iso:country": "GB",
    "wof:name": "CA2 7FG",
    "wof:placetype": "postalcode"
  },
  "geometry": {"coordinates":[-2.962542,54.888918],"type":"Point"}
}
