{
  "type": "Feature",
  "properties": {
    "iso:country":"GB",
    "wof:name":"TW11 8PN",
    "wof:placetype":"postalcode"
},
  "geometry": {"coordinates":[-0.33956180382264,51.42700425799784],"type":"Point"}
}