{
  "type": "Feature",
  "properties": {
    "date:inception_lower": "1980-01-01",
    "date:inception_upper": "1980-01-01",
    "iso:country": "GB",
    "wof:name": "DY12 1JR",
    "wof:placetype": "postalcode"
  },
  "geometry": {"coordinates":[-2.300875,52.383215],"type":"Point"}
}
