{
  "type": "Feature",
  "properties": {
    "iso:country": "GB",
    "wof:name": "CT16 3GQ",
    "wof:placetype": "postalcode"
  },
  "geometry": {"coordinates":[1.283942,51.156937],"type":"Point"}
}
