{
  "type": "Feature",
  "properties": {
    "iso:country":"GB",
    "wof:name":"SA1 6TD",
    "wof:placetype":"postalcode"
},
  "geometry": {"coordinates":[-3.95223801526567,51.63189095898481],"type":"Point"}
}