{
  "type": "Feature",
  "properties": {
    "iso:country":"GB",
    "wof:name":"HU10 6RJ",
    "wof:placetype":"postalcode"
},
  "geometry": {"coordinates":[-0.42477715782152,53.74818087813308],"type":"Point"}
}