{
  "type": "Feature",
  "properties": {
    "iso:country": "GB",
    "wof:name": "HU10 6RJ",
    "wof:placetype": "postalcode"
  },
  "geometry": {"coordinates":[-0.424131,53.748183],"type":"Point"}
}
