{
  "type": "Feature",
  "properties": {
    "date:inception_lower": "1994-12-01",
    "date:inception_upper": "1994-12-01",
    "iso:country": "GB",
    "wof:name": "N10 1LY",
    "wof:placetype": "postalcode"
  },
  "geometry": {"coordinates":[-0.147139,51.598254],"type":"Point"}
}
