{
  "type": "Feature",
  "properties": {
    "iso:country": "GB",
    "wof:name": "N10 1LY",
    "wof:placetype": "postalcode"
  },
  "geometry": {"coordinates":[-0.147139,51.598254],"type":"Point"}
}
