{
  "type": "Feature",
  "properties": {
    "iso:country": "GB",
    "wof:name": "SG14 3AS",
    "wof:placetype": "postalcode"
  },
  "geometry": {"coordinates":[-0.08658,51.80199],"type":"Point"}
}
