{
  "type": "Feature",
  "properties": {
    "iso:country":"GB",
    "wof:name":"B65 9LU",
    "wof:placetype":"postalcode"
},
  "geometry": {"coordinates":[-2.03969860986389,52.48226592051553],"type":"Point"}
}