{
  "type": "Feature",
  "properties": {
    "iso:country":"GB",
    "wof:name":"CV5 7JJ",
    "wof:placetype":"postalcode"
},
  "geometry": {"coordinates":[-1.56688625047614,52.41283270430816],"type":"Point"}
}