{
  "type": "Feature",
  "properties": {
    "iso:country": "GB",
    "wof:name": "CF14 2LS",
    "wof:placetype": "postalcode"
  },
  "geometry": {"coordinates":[-3.227173,51.505817],"type":"Point"}
}
