{
  "type": "Feature",
  "properties": {
    "iso:country":"GB",
    "wof:name":"CF14 2LS",
    "wof:placetype":"postalcode"
},
  "geometry": {"coordinates":[-3.2271729578083,51.50581722073299],"type":"Point"}
}