{
  "type": "Feature",
  "properties": {
    "iso:country":"GB",
    "wof:name":"LL57 3PP",
    "wof:placetype":"postalcode"
},
  "geometry": {"coordinates":[-4.05658127536828,53.1764672960638],"type":"Point"}
}