{
  "type": "Feature",
  "properties": {
    "iso:country":"GB",
    "wof:name":"BH18 8LL",
    "wof:placetype":"postalcode"
},
  "geometry": {"coordinates":[-1.98415332961298,50.76197960362325],"type":"Point"}
}