{
  "type": "Feature",
  "properties": {
    "iso:country":"GB",
    "wof:name":"W12 7EW",
    "wof:placetype":"postalcode"
},
  "geometry": {"coordinates":[-0.23027957233537,51.50669717179763],"type":"Point"}
}