{
  "type": "Feature",
  "properties": {
    "date:inception_lower": "1980-01-01",
    "date:inception_upper": "1980-01-01",
    "iso:country": "GB",
    "wof:name": "WA7 3JJ",
    "wof:placetype": "postalcode"
  },
  "geometry": {"coordinates":[-2.698915,53.316896],"type":"Point"}
}
