{
  "type": "Feature",
  "properties": {
    "iso:country":"GB",
    "wof:name":"WA7 3JJ",
    "wof:placetype":"postalcode"
},
  "geometry": {"coordinates":[-2.69891537008903,53.31689558889479],"type":"Point"}
}