{
  "type": "Feature",
  "properties": {
    "iso:country":"GB",
    "wof:name":"B19 3RH",
    "wof:placetype":"postalcode"
},
  "geometry": {"coordinates":[-1.89935048782863,52.49115710579947],"type":"Point"}
}