{
  "type": "Feature",
  "properties": {
    "iso:country":"GB",
    "wof:name":"TN24 0NH",
    "wof:placetype":"postalcode"
},
  "geometry": {"coordinates":[0.90925824955573,51.14237319116307],"type":"Point"}
}