{
  "type": "Feature",
  "properties": {
    "iso:country": "GB",
    "wof:name": "BL6 5PY",
    "wof:placetype": "postalcode"
  },
  "geometry": {"coordinates":[-2.542552,53.59827],"type":"Point"}
}
