{
  "type": "Feature",
  "properties": {
    "date:inception_lower":"1980-01-01",
    "date:inception_upper":"1980-01-31",
    "iso:country":"GB",
    "wof:name":"TS21 4DN",
    "wof:placetype":"postalcode"
},
  "geometry": {"coordinates":[-1.431088,54.681513],"type":"Point"}
}