{
  "type": "Feature",
  "properties": {
    "iso:country":"GB",
    "wof:name":"DH5 9RD",
    "wof:placetype":"postalcode"
},
  "geometry": {"coordinates":[-1.48056521377832,54.82229527721979],"type":"Point"}
}