{
  "type": "Feature",
  "properties": {
    "iso:country":"GB",
    "wof:name":"SS16 5JD",
    "wof:placetype":"postalcode"
},
  "geometry": {"coordinates":[0.46710903372793,51.56281600129095],"type":"Point"}
}