{
  "type": "Feature",
  "properties": {
    "date:inception_lower": "1982-03-01",
    "date:inception_upper": "1982-03-01",
    "iso:country": "GB",
    "wof:name": "OL3 5NR",
    "wof:placetype": "postalcode"
  },
  "geometry": {"coordinates":[-2.00479,53.560275],"type":"Point"}
}
