{
  "type": "Feature",
  "properties": {
    "iso:country": "GB",
    "wof:name": "LE8 6FA",
    "wof:placetype": "postalcode"
  },
  "geometry": {"coordinates":[-1.176321,52.560723],"type":"Point"}
}
