{
  "type": "Feature",
  "properties": {
    "iso:country": "GB",
    "wof:name": "SA18 1BJ",
    "wof:placetype": "postalcode"
  },
  "geometry": {"coordinates":[-3.875796,51.807731],"type":"Point"}
}
