{
  "type": "Feature",
  "properties": {
    "date:inception_lower":"2007-10-01",
    "date:inception_upper":"2007-10-31",
    "iso:country":"GB",
    "wof:name":"SA18 1BJ",
    "wof:placetype":"postalcode"
},
  "geometry": {"coordinates":[-3.875796,51.807731],"type":"Point"}
}