{
  "type": "Feature",
  "properties": {
    "iso:country":"GB",
    "wof:name":"SA18 1BJ",
    "wof:placetype":"postalcode"
},
  "geometry": {"coordinates":[-3.87579592690697,51.80773090463542],"type":"Point"}
}