{
  "type": "Feature",
  "properties": {
    "iso:country": "GB",
    "wof:name": "ME13 7AE",
    "wof:placetype": "postalcode"
  },
  "geometry": {"coordinates":[0.890749,51.315654],"type":"Point"}
}
