{
  "type": "Feature",
  "properties": {
    "iso:country": "GB",
    "wof:name": "SY16 4JH",
    "wof:placetype": "postalcode"
  },
  "geometry": {"coordinates":[-3.351054,52.496717],"type":"Point"}
}
