{
  "type": "Feature",
  "properties": {
    "iso:country": "GB",
    "wof:name": "EX8 1XL",
    "wof:placetype": "postalcode"
  },
  "geometry": {"coordinates":[-3.425533,50.618393],"type":"Point"}
}
