{
  "type": "Feature",
  "properties": {
    "date:inception_lower": "2001-06-01",
    "date:inception_upper": "2001-06-01",
    "iso:country": "GB",
    "wof:name": "EX8 1XL",
    "wof:placetype": "postalcode"
  },
  "geometry": {"coordinates":[-3.425533,50.618393],"type":"Point"}
}
