{
  "type": "Feature",
  "properties": {
    "date:inception_lower": "1980-01-01",
    "date:inception_upper": "1980-01-01",
    "iso:country": "GB",
    "wof:name": "L6 0AW",
    "wof:placetype": "postalcode"
  },
  "geometry": {"coordinates":[-2.9498,53.426589],"type":"Point"}
}
