{
  "type": "Feature",
  "properties": {
    "date:inception_lower": "1999-06-01",
    "date:inception_upper": "1999-06-01",
    "iso:country": "GB",
    "wof:name": "CH42 7HJ",
    "wof:placetype": "postalcode"
  },
  "geometry": {"coordinates":[-3.028673,53.38161],"type":"Point"}
}
