{
  "type": "Feature",
  "properties": {
    "iso:country": "GB",
    "wof:name": "SY5 6JS",
    "wof:placetype": "postalcode"
  },
  "geometry": {"coordinates":[-2.667507,52.655873],"type":"Point"}
}
