{
  "type": "Feature",
  "properties": {
    "iso:country":"GB",
    "wof:name":"SY5 6JS",
    "wof:placetype":"postalcode"
},
  "geometry": {"coordinates":[-2.66750744985808,52.65587266923815],"type":"Point"}
}