{
  "type": "Feature",
  "properties": {
    "date:inception_lower":"2000-06-01",
    "date:inception_upper":"2000-06-30",
    "iso:country":"GB",
    "wof:name":"OX4 6DQ",
    "wof:placetype":"postalcode"
},
  "geometry": {"coordinates":[-1.207371,51.718471],"type":"Point"}
}