{
  "type": "Feature",
  "properties": {
    "iso:country": "GB",
    "wof:name": "OX4 6DQ",
    "wof:placetype": "postalcode"
  },
  "geometry": {"coordinates":[-1.207371,51.718471],"type":"Point"}
}
