{
  "type": "Feature",
  "properties": {
    "iso:country": "GB",
    "wof:name": "CF14 1HX",
    "wof:placetype": "postalcode"
  },
  "geometry": {"coordinates":[-3.200831,51.506791],"type":"Point"}
}
