{
  "type": "Feature",
  "properties": {
    "iso:country":"GB",
    "wof:name":"WV4 4HP",
    "wof:placetype":"postalcode"
},
  "geometry": {"coordinates":[-2.16168338701831,52.55951097734285],"type":"Point"}
}