{
  "type": "Feature",
  "properties": {
    "date:inception_lower": "2021-12-01",
    "date:inception_upper": "2021-12-01",
    "iso:country": "GB",
    "wof:name": "SY23 3FT",
    "wof:placetype": "postalcode"
  },
  "geometry": {"coordinates":[-4.077307,52.412593],"type":"Point"}
}
