{
  "type": "Feature",
  "properties": {
    "date:inception_lower": "2021-12-01",
    "date:inception_upper": "2021-12-01",
    "iso:country": "GB",
    "wof:name": "SY23 3FT",
    "wof:placetype": "postalcode"
  },
  "geometry": {"coordinates":[-3.985637,52.437681],"type":"Point"}
}
