{
  "type": "Feature",
  "properties": {
    "iso:country":"GB",
    "wof:name":"M40 9NF",
    "wof:placetype":"postalcode"
},
  "geometry": {"coordinates":[-2.19863735821027,53.51305697499639],"type":"Point"}
}