{
  "type": "Feature",
  "properties": {
    "iso:country": "GB",
    "wof:name": "DD3 8PJ",
    "wof:placetype": "postalcode"
  },
  "geometry": {"coordinates":[-2.993677,56.48503],"type":"Point"}
}
