{
  "type": "Feature",
  "properties": {
    "date:inception_lower":"1987-09-01",
    "date:inception_upper":"1987-09-30",
    "iso:country":"GB",
    "wof:name":"DD3 8PJ",
    "wof:placetype":"postalcode"
},
  "geometry": {"coordinates":[-2.993677,56.48503],"type":"Point"}
}