{
  "type": "Feature",
  "properties": {
    "date:inception_lower": "2018-01-01",
    "date:inception_upper": "2018-01-01",
    "iso:country": "GB",
    "wof:name": "CT6 5EN",
    "wof:placetype": "postalcode"
  },
  "geometry": {"coordinates":[1.125706,51.358123],"type":"Point"}
}
