{
  "type": "Feature",
  "properties": {
    "iso:country": "GB",
    "wof:name": "CT6 5EN",
    "wof:placetype": "postalcode"
  },
  "geometry": {"coordinates":[1.125706,51.358123],"type":"Point"}
}
