{
  "type": "Feature",
  "properties": {
    "iso:country": "GB",
    "wof:name": "LL37 2JA",
    "wof:placetype": "postalcode"
  },
  "geometry": {"coordinates":[-4.084636,52.666546],"type":"Point"}
}
