{
  "type": "Feature",
  "properties": {
    "iso:country":"GB",
    "wof:name":"LL37 2JA",
    "wof:placetype":"postalcode"
},
  "geometry": {"coordinates":[-4.0846359184889,52.66654569550646],"type":"Point"}
}