{
  "type": "Feature",
  "properties": {
    "iso:country":"GB",
    "wof:name":"EH48 2EX",
    "wof:placetype":"postalcode"
},
  "geometry": {"coordinates":[-3.6549042602137,55.9005297496368],"type":"Point"}
}