{
  "type": "Feature",
  "properties": {
    "iso:country": "GB",
    "wof:name": "EH48 2EX",
    "wof:placetype": "postalcode"
  },
  "geometry": {"coordinates":[-3.654904,55.90053],"type":"Point"}
}
