{
  "type": "Feature",
  "properties": {
    "date:inception_lower": "1980-01-01",
    "date:inception_upper": "1980-01-01",
    "iso:country": "GB",
    "wof:name": "EH47 7AR",
    "wof:placetype": "postalcode"
  },
  "geometry": {"coordinates":[-3.590884,55.878167],"type":"Point"}
}
