{
  "type": "Feature",
  "properties": {
    "date:inception_lower": "1980-01-01",
    "date:inception_upper": "1980-01-01",
    "iso:country": "GB",
    "wof:name": "EN1 3QY",
    "wof:placetype": "postalcode"
  },
  "geometry": {"coordinates":[-0.073711,51.665501],"type":"Point"}
}
