{
  "type": "Feature",
  "properties": {
    "iso:country":"GB",
    "wof:name":"GU32 2EX",
    "wof:placetype":"postalcode"
},
  "geometry": {"coordinates":[-0.9438260289245,51.00943771545414],"type":"Point"}
}