{
  "type": "Feature",
  "properties": {
    "date:inception_lower": "1980-01-01",
    "date:inception_upper": "1980-01-01",
    "iso:country": "GB",
    "wof:name": "GU32 2EX",
    "wof:placetype": "postalcode"
  },
  "geometry": {"coordinates":[-0.943826,51.009438],"type":"Point"}
}
