{
  "type": "Feature",
  "properties": {
    "iso:country": "GB",
    "wof:name": "CR0 2JH",
    "wof:placetype": "postalcode"
  },
  "geometry": {"coordinates":[-0.098346,51.383987],"type":"Point"}
}
