{
  "type": "Feature",
  "properties": {
    "iso:country":"GB",
    "wof:name":"SP1 3GS",
    "wof:placetype":"postalcode"
},
  "geometry": {"coordinates":[-1.78456982141778,51.09087573132241],"type":"Point"}
}