{
  "type": "Feature",
  "properties": {
    "iso:country": "GB",
    "wof:name": "SP1 3GS",
    "wof:placetype": "postalcode"
  },
  "geometry": {"coordinates":[-1.78457,51.090876],"type":"Point"}
}
