{
  "type": "Feature",
  "properties": {
    "iso:country": "GB",
    "wof:name": "CH44 0ER",
    "wof:placetype": "postalcode"
  },
  "geometry": {"coordinates":[-3.032312,53.424483],"type":"Point"}
}
