{
  "type": "Feature",
  "properties": {
    "iso:country":"GB",
    "wof:name":"PO21 4DL",
    "wof:placetype":"postalcode"
},
  "geometry": {"coordinates":[-0.71007449315019,50.77710767506764],"type":"Point"}
}