{
  "type": "Feature",
  "properties": {
    "date:inception_lower":"2010-02-01",
    "date:inception_upper":"2010-02-28",
    "iso:country":"GB",
    "wof:name":"SP11 6FN",
    "wof:placetype":"postalcode"
},
  "geometry": {"coordinates":[-1.466296,51.226051],"type":"Point"}
}