{
  "type": "Feature",
  "properties": {
    "date:inception_lower":"1985-04-01",
    "date:inception_upper":"1985-04-30",
    "iso:country":"GB",
    "wof:name":"TF3 4HW",
    "wof:placetype":"postalcode"
},
  "geometry": {"coordinates":[-2.452292,52.677369],"type":"Point"}
}