{
  "type": "Feature",
  "properties": {
    "iso:country": "GB",
    "wof:name": "TQ12 4FH",
    "wof:placetype": "postalcode"
  },
  "geometry": {"coordinates":[-3.584556,50.532271],"type":"Point"}
}
