{
  "type": "Feature",
  "properties": {
    "iso:country": "GB",
    "wof:name": "PR3 0ZB",
    "wof:placetype": "postalcode"
  },
  "geometry": {"coordinates":[-2.872448,53.85492],"type":"Point"}
}
