{
  "type": "Feature",
  "properties": {
    "iso:country": "GB",
    "wof:name": "SE6 4FE",
    "wof:placetype": "postalcode"
  },
  "geometry": {"coordinates":[-0.027702,51.443035],"type":"Point"}
}
