{
  "type": "Feature",
  "properties": {
    "iso:country":"GB",
    "wof:name":"ME12 2SY",
    "wof:placetype":"postalcode"
},
  "geometry": {"coordinates":[0.79028614274904,51.42179790717739],"type":"Point"}
}