{
  "type": "Feature",
  "properties": {
    "iso:country":"GB",
    "wof:name":"BL1 7AA",
    "wof:placetype":"postalcode"
},
  "geometry": {"coordinates":[-2.43292647766561,53.60260921069413],"type":"Point"}
}