{
  "type": "Feature",
  "properties": {
    "iso:country":"GB",
    "wof:name":"AB56 4SQ",
    "wof:placetype":"postalcode"
},
  "geometry": {"coordinates":[-2.81342516280456,57.68946154695357],"type":"Point"}
}