{
  "type": "Feature",
  "properties": {
    "date:inception_lower": "2019-12-01",
    "date:inception_upper": "2019-12-01",
    "iso:country": "GB",
    "wof:name": "PE12 0FF",
    "wof:placetype": "postalcode"
  },
  "geometry": {"coordinates":[0.052505,52.763917],"type":"Point"}
}
