{
  "type": "Feature",
  "properties": {
    "date:inception_lower": "2020-04-01",
    "date:inception_upper": "2020-04-01",
    "iso:country": "GB",
    "wof:name": "PA16 0GR",
    "wof:placetype": "postalcode"
  },
  "geometry": {"coordinates":[-4.862246,55.90872],"type":"Point"}
}
