{
  "type": "Feature",
  "properties": {
    "iso:country":"GB",
    "wof:name":"NE7 7FD",
    "wof:placetype":"postalcode"
},
  "geometry": {"coordinates":[-1.56329185663012,54.99766649721935],"type":"Point"}
}