{
  "type": "Feature",
  "properties": {
    "iso:country":"GB",
    "wof:name":"LA4 6NL",
    "wof:placetype":"postalcode"
},
  "geometry": {"coordinates":[-2.82951423404131,54.06721006031012],"type":"Point"}
}