{
  "type": "Feature",
  "properties": {
    "iso:country":"GB",
    "wof:name":"CT6 5UB",
    "wof:placetype":"postalcode"
},
  "geometry": {"coordinates":[1.1318991176106,51.36257594091509],"type":"Point"}
}