{
  "type": "Feature",
  "properties": {
    "date:inception_lower": "1980-01-01",
    "date:inception_upper": "1980-01-01",
    "iso:country": "GB",
    "wof:name": "CT6 5UB",
    "wof:placetype": "postalcode"
  },
  "geometry": {"coordinates":[1.131942,51.362571],"type":"Point"}
}
