{
  "type": "Feature",
  "properties": {
    "iso:country":"GB",
    "wof:name":"LL42 1ED",
    "wof:placetype":"postalcode"
},
  "geometry": {"coordinates":[-4.05238740945209,52.72062417808512],"type":"Point"}
}