{
  "type": "Feature",
  "properties": {
    "iso:country":"GB",
    "wof:name":"MK5 6AX",
    "wof:placetype":"postalcode"
},
  "geometry": {"coordinates":[-0.7818225396406,52.02378362921522],"type":"Point"}
}