{
  "type": "Feature",
  "properties": {
    "date:inception_lower": "1987-10-01",
    "date:inception_upper": "1987-10-01",
    "iso:country": "GB",
    "wof:name": "MK5 6AX",
    "wof:placetype": "postalcode"
  },
  "geometry": {"coordinates":[-0.781822,52.023784],"type":"Point"}
}
