{
  "type": "Feature",
  "properties": {
    "iso:country":"GB",
    "wof:name":"KY11 8GR",
    "wof:placetype":"postalcode"
},
  "geometry": {"coordinates":[-3.42932463553429,56.04843947258844],"type":"Point"}
}