{
  "type": "Feature",
  "properties": {
    "iso:country":"GB",
    "wof:name":"M28 2RG",
    "wof:placetype":"postalcode"
},
  "geometry": {"coordinates":[-2.37493823492432,53.50996412160168],"type":"Point"}
}