{
  "type": "Feature",
  "properties": {
    "iso:country":"GB",
    "wof:name":"OX29 4NA",
    "wof:placetype":"postalcode"
},
  "geometry": {"coordinates":[-1.37386653135312,51.78587605359887],"type":"Point"}
}