{
  "type": "Feature",
  "properties": {
    "iso:country":"GB",
    "wof:name":"BH22 9PS",
    "wof:placetype":"postalcode"
},
  "geometry": {"coordinates":[-1.90212906908177,50.81086838226383],"type":"Point"}
}