{
  "type": "Feature",
  "properties": {
    "iso:country":"GB",
    "wof:name":"TR14 7SE",
    "wof:placetype":"postalcode"
},
  "geometry": {"coordinates":[-5.28628232168371,50.20659387496029],"type":"Point"}
}