{
  "type": "Feature",
  "properties": {
    "date:inception_lower": "1980-01-01",
    "date:inception_upper": "1980-01-01",
    "iso:country": "GB",
    "wof:name": "CA3 8LF",
    "wof:placetype": "postalcode"
  },
  "geometry": {"coordinates":[-2.933689,54.893115],"type":"Point"}
}
