{
  "type": "Feature",
  "properties": {
    "iso:country":"GB",
    "wof:name":"CA3 8LF",
    "wof:placetype":"postalcode"
},
  "geometry": {"coordinates":[-2.93399783872752,54.89315140664331],"type":"Point"}
}