{
  "type": "Feature",
  "properties": {
    "iso:country": "GB",
    "wof:name": "SA14 6EN",
    "wof:placetype": "postalcode"
  },
  "geometry": {"coordinates":[-4.117423,51.787772],"type":"Point"}
}
