{
  "type": "Feature",
  "properties": {
    "iso:country": "GB",
    "wof:name": "SN16 0JT",
    "wof:placetype": "postalcode"
  },
  "geometry": {"coordinates":[-2.114106,51.551854],"type":"Point"}
}
