{
  "type": "Feature",
  "properties": {
    "date:inception_lower":"2000-06-01",
    "date:inception_upper":"2000-06-30",
    "iso:country":"GB",
    "wof:name":"SN16 0JT",
    "wof:placetype":"postalcode"
},
  "geometry": {"coordinates":[-2.114106,51.551854],"type":"Point"}
}