{
  "type": "Feature",
  "properties": {
    "iso:country":"GB",
    "wof:name":"IP26 4ER",
    "wof:placetype":"postalcode"
},
  "geometry": {"coordinates":[0.43903895081189,52.51289696845618],"type":"Point"}
}