{
  "type": "Feature",
  "properties": {
    "iso:country":"GB",
    "wof:name":"DN2 6EA",
    "wof:placetype":"postalcode"
},
  "geometry": {"coordinates":[-1.09768066340068,53.52456976310418],"type":"Point"}
}