{
  "type": "Feature",
  "properties": {
    "iso:country":"GB",
    "wof:name":"HP16 9HJ",
    "wof:placetype":"postalcode"
},
  "geometry": {"coordinates":[-0.7431759716873,51.70098151317164],"type":"Point"}
}