{
  "type": "Feature",
  "properties": {
    "date:inception_lower": "1994-05-01",
    "date:inception_upper": "1994-05-01",
    "iso:country": "GB",
    "wof:name": "RH14 0NP",
    "wof:placetype": "postalcode"
  },
  "geometry": {"coordinates":[-0.551888,51.029554],"type":"Point"}
}
