{
  "type": "Feature",
  "properties": {
    "date:inception_lower":"1991-09-01",
    "date:inception_upper":"1991-09-30",
    "iso:country":"GB",
    "wof:name":"CV37 0UE",
    "wof:placetype":"postalcode"
},
  "geometry": {"coordinates":[-1.722931,52.201248],"type":"Point"}
}