{
  "type": "Feature",
  "properties": {
    "iso:country":"GB",
    "wof:name":"CV37 0UE",
    "wof:placetype":"postalcode"
},
  "geometry": {"coordinates":[-1.72293066669661,52.20124798162678],"type":"Point"}
}