{
  "type": "Feature",
  "properties": {
    "iso:country": "GB",
    "wof:name": "CV37 0UE",
    "wof:placetype": "postalcode"
  },
  "geometry": {"coordinates":[-1.722931,52.201248],"type":"Point"}
}
