{
  "type": "Feature",
  "properties": {
    "iso:country":"GB",
    "wof:name":"N14 7DN",
    "wof:placetype":"postalcode"
},
  "geometry": {"coordinates":[-0.12287233446605,51.62115589689238],"type":"Point"}
}