{
  "type": "Feature",
  "properties": {
    "iso:country": "GB",
    "wof:name": "DT2 0NU",
    "wof:placetype": "postalcode"
  },
  "geometry": {"coordinates":[-2.681992,50.845101],"type":"Point"}
}
