{
  "type": "Feature",
  "properties": {
    "date:inception_lower":"1980-01-01",
    "date:inception_upper":"1980-01-31",
    "iso:country":"GB",
    "wof:name":"DT2 0NU",
    "wof:placetype":"postalcode"
},
  "geometry": {"coordinates":[-2.681992,50.845101],"type":"Point"}
}