{
  "type": "Feature",
  "properties": {
    "iso:country":"GB",
    "wof:name":"DT2 0NU",
    "wof:placetype":"postalcode"
},
  "geometry": {"coordinates":[-2.68200575953291,50.84514566637066],"type":"Point"}
}