{
  "type": "Feature",
  "properties": {
    "iso:country": "GB",
    "wof:name": "HX4 9LG",
    "wof:placetype": "postalcode"
  },
  "geometry": {"coordinates":[-1.90337,53.655024],"type":"Point"}
}
