{
  "type": "Feature",
  "properties": {
    "date:inception_lower": "2021-03-01",
    "date:inception_upper": "2021-03-01",
    "iso:country": "GB",
    "wof:name": "MK17 9GL",
    "wof:placetype": "postalcode"
  },
  "geometry": {"coordinates":[-0.704421,51.989071],"type":"Point"}
}
