{
  "type": "Feature",
  "properties": {
    "iso:country":"GB",
    "wof:name":"DE15 9DZ",
    "wof:placetype":"postalcode"
},
  "geometry": {"coordinates":[-1.61847944488854,52.79662387837519],"type":"Point"}
}