{
  "type": "Feature",
  "properties": {
    "date:inception_lower": "1980-01-01",
    "date:inception_upper": "1980-01-01",
    "iso:country": "GB",
    "wof:name": "DE15 9DZ",
    "wof:placetype": "postalcode"
  },
  "geometry": {"coordinates":[-1.618479,52.796624],"type":"Point"}
}
