{
  "type": "Feature",
  "properties": {
    "date:inception_lower": "2004-01-01",
    "date:inception_upper": "2004-01-01",
    "iso:country": "GB",
    "wof:name": "PA2 8EJ",
    "wof:placetype": "postalcode"
  },
  "geometry": {"coordinates":[-4.450737,55.820682],"type":"Point"}
}
