{
  "type": "Feature",
  "properties": {
    "iso:country": "GB",
    "wof:name": "TS18 1EJ",
    "wof:placetype": "postalcode"
  },
  "geometry": {"coordinates":[-1.312118,54.564312],"type":"Point"}
}
