{
  "type": "Feature",
  "properties": {
    "iso:country": "GB",
    "wof:name": "GU19 5FG",
    "wof:placetype": "postalcode"
  },
  "geometry": {"coordinates":[-0.697529,51.355113],"type":"Point"}
}
