{
  "type": "Feature",
  "properties": {
    "iso:country": "GB",
    "wof:name": "PE11 4DQ",
    "wof:placetype": "postalcode"
  },
  "geometry": {"coordinates":[-0.116753,52.840995],"type":"Point"}
}
