{
  "type": "Feature",
  "properties": {
    "iso:country":"GB",
    "wof:name":"PE11 4DQ",
    "wof:placetype":"postalcode"
},
  "geometry": {"coordinates":[-0.1167529313271,52.84099527659712],"type":"Point"}
}