{
  "type": "Feature",
  "properties": {
    "iso:country":"GB",
    "wof:name":"RG27 9JX",
    "wof:placetype":"postalcode"
},
  "geometry": {"coordinates":[-0.96330071445436,51.28628778520863],"type":"Point"}
}