{
  "type": "Feature",
  "properties": {
    "date:inception_lower": "2003-02-01",
    "date:inception_upper": "2003-02-01",
    "iso:country": "GB",
    "wof:name": "MK5 7GH",
    "wof:placetype": "postalcode"
  },
  "geometry": {"coordinates":[-0.792324,52.009425],"type":"Point"}
}
