{
  "type": "Feature",
  "properties": {
    "iso:country": "GB",
    "wof:name": "W1U 8EH",
    "wof:placetype": "postalcode"
  },
  "geometry": {"coordinates":[-0.155822,51.517807],"type":"Point"}
}
