{
  "type": "Feature",
  "properties": {
    "iso:country":"GB",
    "wof:name":"W1U 8EH",
    "wof:placetype":"postalcode"
},
  "geometry": {"coordinates":[-0.15582185830288,51.51780680010527],"type":"Point"}
}