{
  "type": "Feature",
  "properties": {
    "iso:country":"GB",
    "wof:name":"LN4 3QB",
    "wof:placetype":"postalcode"
},
  "geometry": {"coordinates":[-0.36444336701295,53.06629343535715],"type":"Point"}
}