{
  "type": "Feature",
  "properties": {
    "date:inception_lower": "1980-01-01",
    "date:inception_upper": "1980-01-01",
    "iso:country": "GB",
    "wof:name": "LN4 3QB",
    "wof:placetype": "postalcode"
  },
  "geometry": {"coordinates":[-0.364443,53.066293],"type":"Point"}
}
