{
  "type": "Feature",
  "properties": {
    "iso:country":"GB",
    "wof:name":"GU11 3NA",
    "wof:placetype":"postalcode"
},
  "geometry": {"coordinates":[-0.77947855076052,51.24679370912156],"type":"Point"}
}