{
  "type": "Feature",
  "properties": {
    "iso:country": "GB",
    "wof:name": "GU11 3NA",
    "wof:placetype": "postalcode"
  },
  "geometry": {"coordinates":[-0.779479,51.246794],"type":"Point"}
}
