{
  "type": "Feature",
  "properties": {
    "iso:country":"GB",
    "wof:name":"NE15 8SR",
    "wof:placetype":"postalcode"
},
  "geometry": {"coordinates":[-1.71612816907307,54.97659676974482],"type":"Point"}
}