{
  "type": "Feature",
  "properties": {
    "date:inception_lower": "1980-01-01",
    "date:inception_upper": "1980-01-01",
    "iso:country": "GB",
    "wof:name": "EH8 9JZ",
    "wof:placetype": "postalcode"
  },
  "geometry": {"coordinates":[-3.188133,55.944561],"type":"Point"}
}
