{
  "type": "Feature",
  "properties": {
    "iso:country":"GB",
    "wof:name":"SA73 1AX",
    "wof:placetype":"postalcode"
},
  "geometry": {"coordinates":[-5.018198992967,51.72614494844323],"type":"Point"}
}