{
  "type": "Feature",
  "properties": {
    "date:inception_lower":"1986-04-01",
    "date:inception_upper":"1986-04-30",
    "iso:country":"GB",
    "wof:name":"SA73 1AX",
    "wof:placetype":"postalcode"
},
  "geometry": {"coordinates":[-5.018199,51.726145],"type":"Point"}
}