{
  "type": "Feature",
  "properties": {
    "iso:country": "GB",
    "wof:name": "SA73 1AX",
    "wof:placetype": "postalcode"
  },
  "geometry": {"coordinates":[-5.018199,51.726145],"type":"Point"}
}
