{
  "type": "Feature",
  "properties": {
    "date:inception_lower": "1980-01-01",
    "date:inception_upper": "1980-01-01",
    "iso:country": "GB",
    "wof:name": "BL8 3AT",
    "wof:placetype": "postalcode"
  },
  "geometry": {"coordinates":[-2.337371,53.603969],"type":"Point"}
}
