{
  "type": "Feature",
  "properties": {
    "iso:country": "GB",
    "wof:name": "BL8 3AT",
    "wof:placetype": "postalcode"
  },
  "geometry": {"coordinates":[-2.337371,53.603969],"type":"Point"}
}
