{
  "type": "Feature",
  "properties": {
    "iso:country":"GB",
    "wof:name":"BL8 3AT",
    "wof:placetype":"postalcode"
},
  "geometry": {"coordinates":[-2.33737073951107,53.60396857846175],"type":"Point"}
}