{
  "type": "Feature",
  "properties": {
    "iso:country": "GB",
    "wof:name": "EX4 1PN",
    "wof:placetype": "postalcode"
  },
  "geometry": {"coordinates":[-3.549772,50.718854],"type":"Point"}
}
