{
  "type": "Feature",
  "properties": {
    "iso:country": "GB",
    "wof:name": "IP14 2PY",
    "wof:placetype": "postalcode"
  },
  "geometry": {"coordinates":[1.00613,52.17683],"type":"Point"}
}
