{
  "type": "Feature",
  "properties": {
    "date:inception_lower": "2020-04-01",
    "date:inception_upper": "2020-04-01",
    "iso:country": "GB",
    "wof:name": "N21 3EQ",
    "wof:placetype": "postalcode"
  },
  "geometry": {"coordinates":[-0.107197,51.630619],"type":"Point"}
}
