{
  "type": "Feature",
  "properties": {
    "iso:country":"GB",
    "wof:name":"CA20 1AF",
    "wof:placetype":"postalcode"
},
  "geometry": {"coordinates":[-3.46886979180769,54.42930241119321],"type":"Point"}
}