{
  "type": "Feature",
  "properties": {
    "iso:country": "GB",
    "wof:name": "CA20 1AF",
    "wof:placetype": "postalcode"
  },
  "geometry": {"coordinates":[-3.46887,54.429302],"type":"Point"}
}
