{
  "type": "Feature",
  "properties": {
    "date:inception_lower":"1980-01-01",
    "date:inception_upper":"1980-01-31",
    "iso:country":"GB",
    "wof:name":"CA20 1AF",
    "wof:placetype":"postalcode"
},
  "geometry": {"coordinates":[-3.46887,54.429302],"type":"Point"}
}