{
  "type": "Feature",
  "properties": {
    "iso:country": "GB",
    "wof:name": "EN4 0HU",
    "wof:placetype": "postalcode"
  },
  "geometry": {"coordinates":[-0.168342,51.670459],"type":"Point"}
}
