{
  "type": "Feature",
  "properties": {
    "date:inception_lower": "1980-01-01",
    "date:inception_upper": "1980-01-01",
    "iso:country": "GB",
    "wof:name": "PE30 3SA",
    "wof:placetype": "postalcode"
  },
  "geometry": {"coordinates":[0.437658,52.770767],"type":"Point"}
}
