{
  "type": "Feature",
  "properties": {
    "iso:country": "GB",
    "wof:name": "MK16 9NA",
    "wof:placetype": "postalcode"
  },
  "geometry": {"coordinates":[-0.705,52.108506],"type":"Point"}
}
