{
  "type": "Feature",
  "properties": {
    "date:inception_lower": "1980-01-01",
    "date:inception_upper": "1980-01-01",
    "iso:country": "GB",
    "wof:name": "MK16 9NA",
    "wof:placetype": "postalcode"
  },
  "geometry": {"coordinates":[-0.705,52.108506],"type":"Point"}
}
