{
  "type": "Feature",
  "properties": {
    "date:inception_lower":"2005-01-01",
    "date:inception_upper":"2005-01-31",
    "iso:country":"GB",
    "wof:name":"YO10 3UN",
    "wof:placetype":"postalcode"
},
  "geometry": {"coordinates":[-1.060854,53.956089],"type":"Point"}
}