{
  "type": "Feature",
  "properties": {
    "iso:country":"GB",
    "wof:name":"LA8 0HZ",
    "wof:placetype":"postalcode"
},
  "geometry": {"coordinates":[-2.68072139349302,54.26251024668212],"type":"Point"}
}