{
  "type": "Feature",
  "properties": {
    "iso:country": "GB",
    "wof:name": "PE19 6BA",
    "wof:placetype": "postalcode"
  },
  "geometry": {"coordinates":[-0.239315,52.230492],"type":"Point"}
}
