{
  "type": "Feature",
  "properties": {
    "iso:country": "GB",
    "wof:name": "G4 0AN",
    "wof:placetype": "postalcode"
  },
  "geometry": {"coordinates":[-4.24263,55.857405],"type":"Point"}
}
