{
  "type": "Feature",
  "properties": {
    "iso:country": "GB",
    "wof:name": "EC3N 1LQ",
    "wof:placetype": "postalcode"
  },
  "geometry": {"coordinates":[-0.074501,51.512669],"type":"Point"}
}
