{
  "type": "Feature",
  "properties": {
    "iso:country": "GB",
    "wof:name": "AL5 4TR",
    "wof:placetype": "postalcode"
  },
  "geometry": {"coordinates":[-0.34656,51.819475],"type":"Point"}
}
