{
  "type": "Feature",
  "properties": {
    "date:inception_lower": "1980-01-01",
    "date:inception_upper": "1980-01-01",
    "iso:country": "GB",
    "wof:name": "AL5 4TR",
    "wof:placetype": "postalcode"
  },
  "geometry": {"coordinates":[-0.34656,51.819475],"type":"Point"}
}
