{
  "type": "Feature",
  "properties": {
    "iso:country": "GB",
    "wof:name": "PL17 8PS",
    "wof:placetype": "postalcode"
  },
  "geometry": {"coordinates":[-4.323451,50.530238],"type":"Point"}
}
