{
  "type": "Feature",
  "properties": {
    "iso:country": "GB",
    "wof:name": "NG17 4EL",
    "wof:placetype": "postalcode"
  },
  "geometry": {"coordinates":[-1.255824,53.130983],"type":"Point"}
}
