{
  "type": "Feature",
  "properties": {
    "date:inception_lower": "1980-01-01",
    "date:inception_upper": "1980-01-01",
    "iso:country": "GB",
    "wof:name": "SA14 8PU",
    "wof:placetype": "postalcode"
  },
  "geometry": {"coordinates":[-4.120098,51.685345],"type":"Point"}
}
