{
  "type": "Feature",
  "properties": {
    "iso:country":"GB",
    "wof:name":"YO26 8EA",
    "wof:placetype":"postalcode"
},
  "geometry": {"coordinates":[-1.31957887607405,53.98122795065483],"type":"Point"}
}