{
  "type": "Feature",
  "properties": {
    "date:inception_lower": "1998-06-01",
    "date:inception_upper": "1998-06-01",
    "iso:country": "GB",
    "wof:name": "YO26 8EA",
    "wof:placetype": "postalcode"
  },
  "geometry": {"coordinates":[-1.319579,53.981228],"type":"Point"}
}
