{
  "type": "Feature",
  "properties": {
    "iso:country": "GB",
    "wof:name": "LN12 2NG",
    "wof:placetype": "postalcode"
  },
  "geometry": {"coordinates":[0.276677,53.320317],"type":"Point"}
}
