{
  "type": "Feature",
  "properties": {
    "iso:country":"GB",
    "wof:name":"B96 6BB",
    "wof:placetype":"postalcode"
},
  "geometry": {"coordinates":[-1.9404054828967,52.25460073588514],"type":"Point"}
}