{
  "type": "Feature",
  "properties": {
    "iso:country": "GB",
    "wof:name": "BN21 1LG",
    "wof:placetype": "postalcode"
  },
  "geometry": {"coordinates":[0.27091,50.774098],"type":"Point"}
}
