{
  "type": "Feature",
  "properties": {
    "iso:country":"GB",
    "wof:name":"BN21 1LG",
    "wof:placetype":"postalcode"
},
  "geometry": {"coordinates":[0.27088128252326,50.77410260274391],"type":"Point"}
}