{
  "type": "Feature",
  "properties": {
    "iso:country":"GB",
    "wof:name":"NG21 0EZ",
    "wof:placetype":"postalcode"
},
  "geometry": {"coordinates":[-1.10990464729781,53.1136757989493],"type":"Point"}
}