{
  "type": "Feature",
  "properties": {
    "date:inception_lower": "2021-02-01",
    "date:inception_upper": "2021-02-01",
    "iso:country": "GB",
    "wof:name": "OX29 0AX",
    "wof:placetype": "postalcode"
  },
  "geometry": {"coordinates":[-1.521333,51.785675],"type":"Point"}
}
