{
  "type": "Feature",
  "properties": {
    "iso:country":"GB",
    "wof:name":"M21 9SS",
    "wof:placetype":"postalcode"
},
  "geometry": {"coordinates":[-2.28125384007209,53.44846166235431],"type":"Point"}
}