{
  "type": "Feature",
  "properties": {
    "iso:country":"GB",
    "wof:name":"NN11 0XA",
    "wof:placetype":"postalcode"
},
  "geometry": {"coordinates":[-1.16314487413031,52.27108915331452],"type":"Point"}
}