{
  "type": "Feature",
  "properties": {
    "date:inception_lower": "2001-12-01",
    "date:inception_upper": "2001-12-01",
    "iso:country": "GB",
    "wof:name": "WR3 8EW",
    "wof:placetype": "postalcode"
  },
  "geometry": {"coordinates":[-2.209613,52.200963],"type":"Point"}
}
