{
  "type": "Feature",
  "properties": {
    "iso:country":"GB",
    "wof:name":"WR3 8EW",
    "wof:placetype":"postalcode"
},
  "geometry": {"coordinates":[-2.20961269239214,52.20096343918599],"type":"Point"}
}