{
  "type": "Feature",
  "properties": {
    "iso:country":"GB",
    "wof:name":"LE5 1SL",
    "wof:placetype":"postalcode"
},
  "geometry": {"coordinates":[-1.05136664681672,52.64930249991634],"type":"Point"}
}