{
  "type": "Feature",
  "properties": {
    "iso:country":"GB",
    "wof:name":"LE12 5RF",
    "wof:placetype":"postalcode"
},
  "geometry": {"coordinates":[-1.21667850422682,52.83373991504883],"type":"Point"}
}