{
  "type": "Feature",
  "properties": {
    "iso:country":"GB",
    "wof:name":"ML4 1TG",
    "wof:placetype":"postalcode"
},
  "geometry": {"coordinates":[-4.00911769706142,55.82708314058443],"type":"Point"}
}