{
  "type": "Feature",
  "properties": {
    "iso:country":"GB",
    "wof:name":"CH49 0TT",
    "wof:placetype":"postalcode"
},
  "geometry": {"coordinates":[-3.08740160733221,53.38713048811685],"type":"Point"}
}