{
  "type": "Feature",
  "properties": {
    "iso:country": "GB",
    "wof:name": "SE9 6BD",
    "wof:placetype": "postalcode"
  },
  "geometry": {"coordinates":[0.032562,51.458803],"type":"Point"}
}
