{
  "type": "Feature",
  "properties": {
    "iso:country":"GB",
    "wof:name":"SE9 6BD",
    "wof:placetype":"postalcode"
},
  "geometry": {"coordinates":[0.03256163431813,51.45880349720554],"type":"Point"}
}