{
  "type": "Feature",
  "properties": {
    "iso:country":"GB",
    "wof:name":"CT4 6JP",
    "wof:placetype":"postalcode"
},
  "geometry": {"coordinates":[1.10487510470526,51.19893621763651],"type":"Point"}
}