{
  "type": "Feature",
  "properties": {
    "iso:country":"GB",
    "wof:name":"GL52 6PF",
    "wof:placetype":"postalcode"
},
  "geometry": {"coordinates":[-2.0469680570837,51.89814778742944],"type":"Point"}
}