{
  "type": "Feature",
  "properties": {
    "iso:country": "GB",
    "wof:name": "GL52 6PF",
    "wof:placetype": "postalcode"
  },
  "geometry": {"coordinates":[-2.046968,51.898148],"type":"Point"}
}
