{
  "type": "Feature",
  "properties": {
    "iso:country":"GB",
    "wof:name":"CH6 6BW",
    "wof:placetype":"postalcode"
},
  "geometry": {"coordinates":[-3.17014813595116,53.26820282970341],"type":"Point"}
}