{
  "type": "Feature",
  "properties": {
    "date:inception_lower": "2005-06-01",
    "date:inception_upper": "2005-06-01",
    "iso:country": "GB",
    "wof:name": "BR3 4UE",
    "wof:placetype": "postalcode"
  },
  "geometry": {"coordinates":[-0.0329,51.407735],"type":"Point"}
}
