{
  "type": "Feature",
  "properties": {
    "iso:country":"GB",
    "wof:name":"BR3 4UE",
    "wof:placetype":"postalcode"
},
  "geometry": {"coordinates":[-0.03289995157172,51.40773533561325],"type":"Point"}
}