{
  "type": "Feature",
  "properties": {
    "iso:country":"GB",
    "wof:name":"GU5 0QH",
    "wof:placetype":"postalcode"
},
  "geometry": {"coordinates":[-0.55440098022009,51.20117452020104],"type":"Point"}
}