{
  "type": "Feature",
  "properties": {
    "iso:country": "GB",
    "wof:name": "GU5 0QH",
    "wof:placetype": "postalcode"
  },
  "geometry": {"coordinates":[-0.551811,51.200923],"type":"Point"}
}
