{
  "type": "Feature",
  "properties": {
    "iso:country":"GB",
    "wof:name":"SP7 8LL",
    "wof:placetype":"postalcode"
},
  "geometry": {"coordinates":[-2.20559028855451,51.00700450663541],"type":"Point"}
}