{
  "type": "Feature",
  "properties": {
    "iso:country": "GB",
    "wof:name": "SP7 8LL",
    "wof:placetype": "postalcode"
  },
  "geometry": {"coordinates":[-2.20559,51.007005],"type":"Point"}
}
