{
  "type": "Feature",
  "properties": {
    "iso:country":"GB",
    "wof:name":"WD23 1JT",
    "wof:placetype":"postalcode"
},
  "geometry": {"coordinates":[-0.34929814863143,51.63234509205526],"type":"Point"}
}