{
  "type": "Feature",
  "properties": {
    "date:inception_lower": "1980-01-01",
    "date:inception_upper": "1980-01-01",
    "iso:country": "GB",
    "wof:name": "SP6 1HA",
    "wof:placetype": "postalcode"
  },
  "geometry": {"coordinates":[-1.792518,50.935154],"type":"Point"}
}
