{
  "type": "Feature",
  "properties": {
    "iso:country":"GB",
    "wof:name":"SP6 1HA",
    "wof:placetype":"postalcode"
},
  "geometry": {"coordinates":[-1.79251850849746,50.93515367520104],"type":"Point"}
}