{
  "type": "Feature",
  "properties": {
    "iso:country":"GB",
    "wof:name":"IP4 5EJ",
    "wof:placetype":"postalcode"
},
  "geometry": {"coordinates":[1.1868141738506,52.05278773308305],"type":"Point"}
}