{
  "type": "Feature",
  "properties": {
    "date:inception_lower": "1980-01-01",
    "date:inception_upper": "1980-01-01",
    "iso:country": "GB",
    "wof:name": "IP4 5EJ",
    "wof:placetype": "postalcode"
  },
  "geometry": {"coordinates":[1.186814,52.052788],"type":"Point"}
}
