{
  "type": "Feature",
  "properties": {
    "iso:country":"GB",
    "wof:name":"CM7 9BJ",
    "wof:placetype":"postalcode"
},
  "geometry": {"coordinates":[0.55940223673393,51.88456675389531],"type":"Point"}
}