{
  "type": "Feature",
  "properties": {
    "iso:country": "GB",
    "wof:name": "CM7 9BJ",
    "wof:placetype": "postalcode"
  },
  "geometry": {"coordinates":[0.559402,51.884567],"type":"Point"}
}
