{
  "type": "Feature",
  "properties": {
    "iso:country":"GB",
    "wof:name":"CB21 6BZ",
    "wof:placetype":"postalcode"
},
  "geometry": {"coordinates":[0.25635094210082,52.11561560635782],"type":"Point"}
}