{
  "type": "Feature",
  "properties": {
    "date:inception_lower": "2008-05-01",
    "date:inception_upper": "2008-05-01",
    "iso:country": "GB",
    "wof:name": "CM9 4QZ",
    "wof:placetype": "postalcode"
  },
  "geometry": {"coordinates":[0.692386,51.735366],"type":"Point"}
}
