{
  "type": "Feature",
  "properties": {
    "iso:country":"GB",
    "wof:name":"CM9 4QZ",
    "wof:placetype":"postalcode"
},
  "geometry": {"coordinates":[0.69238638403551,51.73536616234289],"type":"Point"}
}