{
  "type": "Feature",
  "properties": {
    "iso:country":"GB",
    "wof:name":"SY12 0HH",
    "wof:placetype":"postalcode"
},
  "geometry": {"coordinates":[-2.89168912524692,52.90917698325234],"type":"Point"}
}