{
  "type": "Feature",
  "properties": {
    "date:inception_lower": "1980-01-01",
    "date:inception_upper": "1980-01-01",
    "iso:country": "GB",
    "wof:name": "SY12 0HH",
    "wof:placetype": "postalcode"
  },
  "geometry": {"coordinates":[-2.890626,52.909622],"type":"Point"}
}
