{
  "type": "Feature",
  "properties": {
    "date:inception_lower": "2024-08-01",
    "date:inception_upper": "2024-08-01",
    "iso:country": "GB",
    "wof:name": "CA5 6FG",
    "wof:placetype": "postalcode"
  },
  "geometry": {"coordinates":[-3.066348,54.89808],"type":"Point"}
}
