{
  "type": "Feature",
  "properties": {
    "iso:country":"GB",
    "wof:name":"HD3 4PH",
    "wof:placetype":"postalcode"
},
  "geometry": {"coordinates":[-1.82912164309615,53.64092330688482],"type":"Point"}
}