{
  "type": "Feature",
  "properties": {
    "iso:country":"GB",
    "wof:name":"AB31 4QU",
    "wof:placetype":"postalcode"
},
  "geometry": {"coordinates":[-2.75677672083826,57.1024878554878],"type":"Point"}
}