{
  "type": "Feature",
  "properties": {
    "date:inception_lower": "1980-01-01",
    "date:inception_upper": "1980-01-01",
    "iso:country": "GB",
    "wof:name": "BN26 6TA",
    "wof:placetype": "postalcode"
  },
  "geometry": {"coordinates":[0.166504,50.840471],"type":"Point"}
}
