{
  "type": "Feature",
  "properties": {
    "iso:country":"GB",
    "wof:name":"SP2 0QD",
    "wof:placetype":"postalcode"
},
  "geometry": {"coordinates":[-1.87588169171695,51.10704999745675],"type":"Point"}
}