{
  "type": "Feature",
  "properties": {
    "iso:country": "GB",
    "wof:name": "SP2 0QD",
    "wof:placetype": "postalcode"
  },
  "geometry": {"coordinates":[-1.875882,51.10705],"type":"Point"}
}
