{
  "type": "Feature",
  "properties": {
    "date:inception_lower":"1987-04-01",
    "date:inception_upper":"1987-04-30",
    "iso:country":"GB",
    "wof:name":"EX39 1SW",
    "wof:placetype":"postalcode"
},
  "geometry": {"coordinates":[-4.215882,51.045629],"type":"Point"}
}