{
  "type": "Feature",
  "properties": {
    "iso:country":"GB",
    "wof:name":"EX39 1SW",
    "wof:placetype":"postalcode"
},
  "geometry": {"coordinates":[-4.21588181295688,51.04562869507486],"type":"Point"}
}