{
  "type": "Feature",
  "properties": {
    "iso:country": "GB",
    "wof:name": "BN5 9NB",
    "wof:placetype": "postalcode"
  },
  "geometry": {"coordinates":[-0.223226,50.889636],"type":"Point"}
}
