{
  "type": "Feature",
  "properties": {
    "iso:country":"GB",
    "wof:name":"BN5 9NB",
    "wof:placetype":"postalcode"
},
  "geometry": {"coordinates":[-0.2232264392369,50.88963574892697],"type":"Point"}
}