{
  "type": "Feature",
  "properties": {
    "date:inception_lower": "2021-06-01",
    "date:inception_upper": "2021-06-01",
    "iso:country": "GB",
    "wof:name": "NE61 6GF",
    "wof:placetype": "postalcode"
  },
  "geometry": {"coordinates":[-1.643246,55.184087],"type":"Point"}
}
