{
  "type": "Feature",
  "properties": {
    "iso:country":"GB",
    "wof:name":"SE9 6ER",
    "wof:placetype":"postalcode"
},
  "geometry": {"coordinates":[0.04942282203562,51.45472395848025],"type":"Point"}
}