{
  "type": "Feature",
  "properties": {
    "iso:country":"GB",
    "wof:name":"GU25 4DW",
    "wof:placetype":"postalcode"
},
  "geometry": {"coordinates":[-0.56750076361757,51.40339438261525],"type":"Point"}
}