{
  "type": "Feature",
  "properties": {
    "iso:country":"GB",
    "wof:name":"GL54 4NU",
    "wof:placetype":"postalcode"
},
  "geometry": {"coordinates":[-1.94228288426437,51.80926800033881],"type":"Point"}
}