{
  "type": "Feature",
  "properties": {
    "date:inception_lower":"1980-01-01",
    "date:inception_upper":"1980-01-31",
    "iso:country":"GB",
    "wof:name":"GL54 4NU",
    "wof:placetype":"postalcode"
},
  "geometry": {"coordinates":[-1.941765,51.809589],"type":"Point"}
}