{
  "type": "Feature",
  "properties": {
    "iso:country": "GB",
    "wof:name": "GL54 4NU",
    "wof:placetype": "postalcode"
  },
  "geometry": {"coordinates":[-1.941765,51.809589],"type":"Point"}
}
