{
  "type": "Feature",
  "properties": {
    "iso:country": "GB",
    "wof:name": "EH14 5AZ",
    "wof:placetype": "postalcode"
  },
  "geometry": {"coordinates":[-3.333998,55.890434],"type":"Point"}
}
