{
  "type": "Feature",
  "properties": {
    "iso:country":"GB",
    "wof:name":"LU6 1NL",
    "wof:placetype":"postalcode"
},
  "geometry": {"coordinates":[-0.52683858810052,51.89184382251938],"type":"Point"}
}