{
  "type": "Feature",
  "properties": {
    "iso:country": "GB",
    "wof:name": "LU6 1NL",
    "wof:placetype": "postalcode"
  },
  "geometry": {"coordinates":[-0.526839,51.891844],"type":"Point"}
}
