{
  "type": "Feature",
  "properties": {
    "iso:country":"GB",
    "wof:name":"BL1 3AF",
    "wof:placetype":"postalcode"
},
  "geometry": {"coordinates":[-2.443907428287,53.58481698066339],"type":"Point"}
}