{
  "type": "Feature",
  "properties": {
    "date:inception_lower": "2024-05-01",
    "date:inception_upper": "2024-05-01",
    "iso:country": "GB",
    "wof:name": "NR18 0FB",
    "wof:placetype": "postalcode"
  },
  "geometry": {"coordinates":[1.131349,52.582251],"type":"Point"}
}
