{
  "type": "Feature",
  "properties": {
    "iso:country":"GB",
    "wof:name":"EH23 4GF",
    "wof:placetype":"postalcode"
},
  "geometry": {"coordinates":[-3.05230152796933,55.84402353452391],"type":"Point"}
}