{
  "type": "Feature",
  "properties": {
    "iso:country":"GB",
    "wof:name":"SY5 6RA",
    "wof:placetype":"postalcode"
},
  "geometry": {"coordinates":[-2.61685838919995,52.65788227382193],"type":"Point"}
}