{
  "type": "Feature",
  "properties": {
    "iso:country":"GB",
    "wof:name":"M22 4LF",
    "wof:placetype":"postalcode"
},
  "geometry": {"coordinates":[-2.25199789100811,53.40264050169534],"type":"Point"}
}