{
  "type": "Feature",
  "properties": {
    "iso:country":"GB",
    "wof:name":"SG8 7EN",
    "wof:placetype":"postalcode"
},
  "geometry": {"coordinates":[-0.01323363946668,52.04895489283928],"type":"Point"}
}