{
  "type": "Feature",
  "properties": {
    "iso:country":"GB",
    "wof:name":"HA7 3HG",
    "wof:placetype":"postalcode"
},
  "geometry": {"coordinates":[-0.32471444229403,51.62581929864346],"type":"Point"}
}