{
  "type": "Feature",
  "properties": {
    "iso:country": "GB",
    "wof:name": "LL68 9AW",
    "wof:placetype": "postalcode"
  },
  "geometry": {"coordinates":[-4.34937,53.408921],"type":"Point"}
}
