{
  "type": "Feature",
  "properties": {
    "iso:country":"GB",
    "wof:name":"L31 0AR",
    "wof:placetype":"postalcode"
},
  "geometry": {"coordinates":[-2.94063015228323,53.51766373492728],"type":"Point"}
}