{
  "type": "Feature",
  "properties": {
    "iso:country":"GB",
    "wof:name":"TS1 2EF",
    "wof:placetype":"postalcode"
},
  "geometry": {"coordinates":[-1.22774848593211,54.57291302149471],"type":"Point"}
}