{
  "type": "Feature",
  "properties": {
    "iso:country":"GB",
    "wof:name":"DA14 6HH",
    "wof:placetype":"postalcode"
},
  "geometry": {"coordinates":[0.10706603321271,51.42429516644337],"type":"Point"}
}