{
  "type": "Feature",
  "properties": {
    "iso:country": "GB",
    "wof:name": "CT11 7RH",
    "wof:placetype": "postalcode"
  },
  "geometry": {"coordinates":[1.409974,51.339486],"type":"Point"}
}
