{
  "type": "Feature",
  "properties": {
    "iso:country": "GB",
    "wof:name": "LE9 6RT",
    "wof:placetype": "postalcode"
  },
  "geometry": {"coordinates":[-1.227754,52.536653],"type":"Point"}
}
