{
  "type": "Feature",
  "properties": {
    "iso:country":"GB",
    "wof:name":"LE17 6LE",
    "wof:placetype":"postalcode"
},
  "geometry": {"coordinates":[-1.05787893844794,52.45466346952158],"type":"Point"}
}