{
  "type": "Feature",
  "properties": {
    "iso:country":"GB",
    "wof:name":"BL1 6PF",
    "wof:placetype":"postalcode"
},
  "geometry": {"coordinates":[-2.44037863767537,53.59990348115926],"type":"Point"}
}