{
  "type": "Feature",
  "properties": {
    "date:inception_lower": "2002-06-01",
    "date:inception_upper": "2002-06-01",
    "iso:country": "GB",
    "wof:name": "DE75 7TJ",
    "wof:placetype": "postalcode"
  },
  "geometry": {"coordinates":[-1.367888,53.015814],"type":"Point"}
}
