{
  "type": "Feature",
  "properties": {
    "iso:country":"GB",
    "wof:name":"DE75 7TJ",
    "wof:placetype":"postalcode"
},
  "geometry": {"coordinates":[-1.36788847250202,53.01581391330087],"type":"Point"}
}