{
  "type": "Feature",
  "properties": {
    "iso:country":"GB",
    "wof:name":"HU15 1GP",
    "wof:placetype":"postalcode"
},
  "geometry": {"coordinates":[-0.55966721925787,53.72574250623069],"type":"Point"}
}