{
  "type": "Feature",
  "properties": {
    "iso:country":"GB",
    "wof:name":"ST3 5JE",
    "wof:placetype":"postalcode"
},
  "geometry": {"coordinates":[-2.11454495036131,52.98394318883936],"type":"Point"}
}