{
  "type": "Feature",
  "properties": {
    "iso:country":"GB",
    "wof:name":"DL12 9TB",
    "wof:placetype":"postalcode"
},
  "geometry": {"coordinates":[-1.9324785385638,54.54491815926004],"type":"Point"}
}