{
  "type": "Feature",
  "properties": {
    "iso:country": "GB",
    "wof:name": "DL12 9TB",
    "wof:placetype": "postalcode"
  },
  "geometry": {"coordinates":[-1.932478,54.544918],"type":"Point"}
}
