{
  "type": "Feature",
  "properties": {
    "date:inception_lower": "2023-03-01",
    "date:inception_upper": "2023-03-01",
    "iso:country": "GB",
    "wof:name": "MK17 8AL",
    "wof:placetype": "postalcode"
  },
  "geometry": {"coordinates":[-0.678486,52.027068],"type":"Point"}
}
