{
  "type": "Feature",
  "properties": {
    "iso:country": "GB",
    "wof:name": "SN15 2HJ",
    "wof:placetype": "postalcode"
  },
  "geometry": {"coordinates":[-2.041871,51.388283],"type":"Point"}
}
