{
  "type": "Feature",
  "properties": {
    "date:inception_lower": "2022-02-01",
    "date:inception_upper": "2022-02-01",
    "iso:country": "GB",
    "wof:name": "PE29 3LP",
    "wof:placetype": "postalcode"
  },
  "geometry": {"coordinates":[-0.185181,52.331479],"type":"Point"}
}
