{
  "type": "Feature",
  "properties": {
    "iso:country":"GB",
    "wof:name":"CH6 5JX",
    "wof:placetype":"postalcode"
},
  "geometry": {"coordinates":[-3.1305643065758,53.24153609874397],"type":"Point"}
}