{
  "type": "Feature",
  "properties": {
    "iso:country":"GB",
    "wof:name":"SK11 0DS",
    "wof:placetype":"postalcode"
},
  "geometry": {"coordinates":[-2.10585696298146,53.23706353969942],"type":"Point"}
}