{
  "type": "Feature",
  "properties": {
    "iso:country":"GB",
    "wof:name":"WA8 0EL",
    "wof:placetype":"postalcode"
},
  "geometry": {"coordinates":[-2.73630045311544,53.34961484668607],"type":"Point"}
}