{
  "type": "Feature",
  "properties": {
    "date:inception_lower": "1980-01-01",
    "date:inception_upper": "1980-01-01",
    "iso:country": "GB",
    "wof:name": "WA8 0EL",
    "wof:placetype": "postalcode"
  },
  "geometry": {"coordinates":[-2.7363,53.349615],"type":"Point"}
}
