{
  "type": "Feature",
  "properties": {
    "iso:country":"GB",
    "wof:name":"KW14 7UR",
    "wof:placetype":"postalcode"
},
  "geometry": {"coordinates":[-3.55518065844502,58.60961432321888],"type":"Point"}
}