{
  "type": "Feature",
  "properties": {
    "iso:country":"GB",
    "wof:name":"NR17 2JP",
    "wof:placetype":"postalcode"
},
  "geometry": {"coordinates":[1.00487833857256,52.50653791542545],"type":"Point"}
}