{
  "type": "Feature",
  "properties": {
    "iso:country": "GB",
    "wof:name": "NR17 2JP",
    "wof:placetype": "postalcode"
  },
  "geometry": {"coordinates":[1.004878,52.506538],"type":"Point"}
}
