{
  "type": "Feature",
  "properties": {
    "iso:country": "GB",
    "wof:name": "LL53 6EU",
    "wof:placetype": "postalcode"
  },
  "geometry": {"coordinates":[-4.543879,52.932076],"type":"Point"}
}
