{
  "type": "Feature",
  "properties": {
    "iso:country": "GB",
    "wof:name": "SO14 0PH",
    "wof:placetype": "postalcode"
  },
  "geometry": {"coordinates":[-1.391206,50.909904],"type":"Point"}
}
