{
  "type": "Feature",
  "properties": {
    "iso:country":"GB",
    "wof:name":"M3 5LF",
    "wof:placetype":"postalcode"
},
  "geometry": {"coordinates":[-2.26295846686383,53.4823540059875],"type":"Point"}
}