{
  "type": "Feature",
  "properties": {
    "iso:country": "GB",
    "wof:name": "SY12 9HF",
    "wof:placetype": "postalcode"
  },
  "geometry": {"coordinates":[-2.940515,52.903416],"type":"Point"}
}
