{
  "type": "Feature",
  "properties": {
    "date:inception_lower":"1980-01-01",
    "date:inception_upper":"1980-01-31",
    "iso:country":"GB",
    "wof:name":"SY12 9HF",
    "wof:placetype":"postalcode"
},
  "geometry": {"coordinates":[-2.940515,52.903416],"type":"Point"}
}