{
  "type": "Feature",
  "properties": {
    "iso:country": "GB",
    "wof:name": "BS7 8AS",
    "wof:placetype": "postalcode"
  },
  "geometry": {"coordinates":[-2.591457,51.472236],"type":"Point"}
}
