{
  "type": "Feature",
  "properties": {
    "iso:country":"GB",
    "wof:name":"BS7 8AS",
    "wof:placetype":"postalcode"
},
  "geometry": {"coordinates":[-2.59145677660826,51.47223592137112],"type":"Point"}
}