{
  "type": "Feature",
  "properties": {
    "iso:country":"GB",
    "wof:name":"HA8 8JH",
    "wof:placetype":"postalcode"
},
  "geometry": {"coordinates":[-0.27620919852482,51.62252739318805],"type":"Point"}
}