{
  "type": "Feature",
  "properties": {
    "iso:country": "GB",
    "wof:name": "BR6 9NT",
    "wof:placetype": "postalcode"
  },
  "geometry": {"coordinates":[0.080523,51.361153],"type":"Point"}
}
