{
  "type": "Feature",
  "properties": {
    "iso:country":"GB",
    "wof:name":"BR6 9NT",
    "wof:placetype":"postalcode"
},
  "geometry": {"coordinates":[0.08052246315328,51.36115337627716],"type":"Point"}
}