{
  "type": "Feature",
  "properties": {
    "iso:country":"GB",
    "wof:name":"G44 3XE",
    "wof:placetype":"postalcode"
},
  "geometry": {"coordinates":[-4.27035698716593,55.79854910018389],"type":"Point"}
}