{
  "type": "Feature",
  "properties": {
    "date:inception_lower": "1980-01-01",
    "date:inception_upper": "1980-01-01",
    "iso:country": "GB",
    "wof:name": "G44 3XE",
    "wof:placetype": "postalcode"
  },
  "geometry": {"coordinates":[-4.270567,55.798271],"type":"Point"}
}
