{
  "type": "Feature",
  "properties": {
    "date:inception_lower":"1980-01-01",
    "date:inception_upper":"1980-01-31",
    "iso:country":"GB",
    "wof:name":"G51 2JG",
    "wof:placetype":"postalcode"
},
  "geometry": {"coordinates":[-4.311894,55.853264],"type":"Point"}
}