{
  "type": "Feature",
  "properties": {
    "iso:country":"GB",
    "wof:name":"G51 2JG",
    "wof:placetype":"postalcode"
},
  "geometry": {"coordinates":[-4.31189433708108,55.85326440009972],"type":"Point"}
}