{
  "type": "Feature",
  "properties": {
    "iso:country": "GB",
    "wof:name": "CH5 3BS",
    "wof:placetype": "postalcode"
  },
  "geometry": {"coordinates":[-3.055956,53.19356],"type":"Point"}
}
