{
  "type": "Feature",
  "properties": {
    "iso:country":"GB",
    "wof:name":"IP1 5AE",
    "wof:placetype":"postalcode"
},
  "geometry": {"coordinates":[1.11796981282167,52.06617898723427],"type":"Point"}
}