{
  "type": "Feature",
  "properties": {
    "iso:country":"GB",
    "wof:name":"HG4 2DF",
    "wof:placetype":"postalcode"
},
  "geometry": {"coordinates":[-1.53882633990754,54.1368294289222],"type":"Point"}
}