{
  "type": "Feature",
  "properties": {
    "iso:country":"GB",
    "wof:name":"WA2 9UH",
    "wof:placetype":"postalcode"
},
  "geometry": {"coordinates":[-2.59236679476147,53.41962949119424],"type":"Point"}
}