{
  "type": "Feature",
  "properties": {
    "date:inception_lower": "1994-05-01",
    "date:inception_upper": "1994-05-01",
    "iso:country": "GB",
    "wof:name": "IV9 8RS",
    "wof:placetype": "postalcode"
  },
  "geometry": {"coordinates":[-4.178912,57.569832],"type":"Point"}
}
