{
  "type": "Feature",
  "properties": {
    "iso:country": "GB",
    "wof:name": "IV9 8RS",
    "wof:placetype": "postalcode"
  },
  "geometry": {"coordinates":[-4.178912,57.569832],"type":"Point"}
}
