{
  "type": "Feature",
  "properties": {
    "iso:country":"GB",
    "wof:name":"IV9 8RS",
    "wof:placetype":"postalcode"
},
  "geometry": {"coordinates":[-4.17891188585222,57.56983177725426],"type":"Point"}
}