{
  "type": "Feature",
  "properties": {
    "iso:country":"GB",
    "wof:name":"M11 4JQ",
    "wof:placetype":"postalcode"
},
  "geometry": {"coordinates":[-2.18118437004513,53.48700933413436],"type":"Point"}
}