{
  "type": "Feature",
  "properties": {
    "iso:country":"GB",
    "wof:name":"CO4 9WT",
    "wof:placetype":"postalcode"
},
  "geometry": {"coordinates":[0.91672487028468,51.92011799418203],"type":"Point"}
}