{
  "type": "Feature",
  "properties": {
    "date:inception_lower": "2002-05-01",
    "date:inception_upper": "2002-05-01",
    "iso:country": "GB",
    "wof:name": "CO4 9WT",
    "wof:placetype": "postalcode"
  },
  "geometry": {"coordinates":[0.916725,51.920118],"type":"Point"}
}
