{
  "type": "Feature",
  "properties": {
    "iso:country":"GB",
    "wof:name":"OX1 2HP",
    "wof:placetype":"postalcode"
},
  "geometry": {"coordinates":[-1.26172451731055,51.75867455699198],"type":"Point"}
}