{
  "type": "Feature",
  "properties": {
    "iso:country":"GB",
    "wof:name":"TS9 6DF",
    "wof:placetype":"postalcode"
},
  "geometry": {"coordinates":[-1.13315354244121,54.49352689805811],"type":"Point"}
}