{
  "type": "Feature",
  "properties": {
    "iso:country":"GB",
    "wof:name":"G82 4JQ",
    "wof:placetype":"postalcode"
},
  "geometry": {"coordinates":[-4.5901038788902,55.94770493070179],"type":"Point"}
}