{
  "type": "Feature",
  "properties": {
    "date:inception_lower": "1980-01-01",
    "date:inception_upper": "1980-01-01",
    "iso:country": "GB",
    "wof:name": "G82 4JQ",
    "wof:placetype": "postalcode"
  },
  "geometry": {"coordinates":[-4.590104,55.947705],"type":"Point"}
}
