{
  "type": "Feature",
  "properties": {
    "iso:country":"GB",
    "wof:name":"AL9 7QY",
    "wof:placetype":"postalcode"
},
  "geometry": {"coordinates":[-0.20152259453416,51.72434988509915],"type":"Point"}
}