{
  "type": "Feature",
  "properties": {
    "date:inception_lower":"1980-01-01",
    "date:inception_upper":"1980-01-31",
    "iso:country":"GB",
    "wof:name":"E7 8NP",
    "wof:placetype":"postalcode"
},
  "geometry": {"coordinates":[0.036764,51.543451],"type":"Point"}
}