{
  "type": "Feature",
  "properties": {
    "iso:country":"GB",
    "wof:name":"E7 8NP",
    "wof:placetype":"postalcode"
},
  "geometry": {"coordinates":[0.03676669910225,51.54350503116349],"type":"Point"}
}