{
  "type": "Feature",
  "properties": {
    "iso:country":"GB",
    "wof:name":"LE67 1SZ",
    "wof:placetype":"postalcode"
},
  "geometry": {"coordinates":[-1.32904058576272,52.70289986160449],"type":"Point"}
}