{
  "type": "Feature",
  "properties": {
    "iso:country": "GB",
    "wof:name": "BS20 6PG",
    "wof:placetype": "postalcode"
  },
  "geometry": {"coordinates":[-2.78243,51.481456],"type":"Point"}
}
