{
  "type": "Feature",
  "properties": {
    "iso:country": "GB",
    "wof:name": "CA2 4LA",
    "wof:placetype": "postalcode"
  },
  "geometry": {"coordinates":[-2.927023,54.878482],"type":"Point"}
}
