{
  "type": "Feature",
  "properties": {
    "iso:country":"GB",
    "wof:name":"CA2 4LA",
    "wof:placetype":"postalcode"
},
  "geometry": {"coordinates":[-2.92659861932256,54.87850580101503],"type":"Point"}
}