{
  "type": "Feature",
  "properties": {
    "iso:country":"GB",
    "wof:name":"S72 8LQ",
    "wof:placetype":"postalcode"
},
  "geometry": {"coordinates":[-1.41117828949086,53.57117860696807],"type":"Point"}
}