{
  "type": "Feature",
  "properties": {
    "date:inception_lower": "2003-01-01",
    "date:inception_upper": "2003-01-01",
    "iso:country": "GB",
    "wof:name": "S72 8LQ",
    "wof:placetype": "postalcode"
  },
  "geometry": {"coordinates":[-1.411178,53.571179],"type":"Point"}
}
