{
  "type": "Feature",
  "properties": {
    "iso:country": "GB",
    "wof:name": "BS4 1BY",
    "wof:placetype": "postalcode"
  },
  "geometry": {"coordinates":[-2.573606,51.42643],"type":"Point"}
}
