{
  "type": "Feature",
  "properties": {
    "iso:country":"GB",
    "wof:name":"BS4 1BY",
    "wof:placetype":"postalcode"
},
  "geometry": {"coordinates":[-2.573518429273,51.42639575487051],"type":"Point"}
}