{
  "type": "Feature",
  "properties": {
    "iso:country":"GB",
    "wof:name":"W5 4LR",
    "wof:placetype":"postalcode"
},
  "geometry": {"coordinates":[-0.28689418720486,51.5017376710769],"type":"Point"}
}