{
  "type": "Feature",
  "properties": {
    "iso:country": "GB",
    "wof:name": "W5 4LR",
    "wof:placetype": "postalcode"
  },
  "geometry": {"coordinates":[-0.286872,51.501739],"type":"Point"}
}
