{
  "type": "Feature",
  "properties": {
    "date:inception_lower":"1980-01-01",
    "date:inception_upper":"1980-01-31",
    "iso:country":"GB",
    "wof:name":"W5 4LR",
    "wof:placetype":"postalcode"
},
  "geometry": {"coordinates":[-0.287027,51.501831],"type":"Point"}
}