{
  "type": "Feature",
  "properties": {
    "iso:country": "GB",
    "wof:name": "W5 4LR",
    "wof:placetype": "postalcode"
  },
  "geometry": {"coordinates":[-0.287027,51.501831],"type":"Point"}
}
