{
  "type": "Feature",
  "properties": {
    "iso:country":"GB",
    "wof:name":"NN14 4RQ",
    "wof:placetype":"postalcode"
},
  "geometry": {"coordinates":[-0.53745797357746,52.39338823483034],"type":"Point"}
}