{
  "type": "Feature",
  "properties": {
    "iso:country": "GB",
    "wof:name": "PL14 6FT",
    "wof:placetype": "postalcode"
  },
  "geometry": {"coordinates":[-4.46009,50.46345],"type":"Point"}
}
