{
  "type": "Feature",
  "properties": {
    "iso:country":"GB",
    "wof:name":"LL11 3EA",
    "wof:placetype":"postalcode"
},
  "geometry": {"coordinates":[-3.08062617301583,53.04470017418625],"type":"Point"}
}