{
  "type": "Feature",
  "properties": {
    "iso:country":"GB",
    "wof:name":"M35 9LG",
    "wof:placetype":"postalcode"
},
  "geometry": {"coordinates":[-2.14225659712938,53.51380261796466],"type":"Point"}
}