{
  "type": "Feature",
  "properties": {
    "date:inception_lower": "1989-04-01",
    "date:inception_upper": "1989-04-01",
    "iso:country": "GB",
    "wof:name": "G4 0RH",
    "wof:placetype": "postalcode"
  },
  "geometry": {"coordinates":[-4.236376,55.862538],"type":"Point"}
}
