{
  "type": "Feature",
  "properties": {
    "iso:country": "GB",
    "wof:name": "RM9 4DJ",
    "wof:placetype": "postalcode"
  },
  "geometry": {"coordinates":[0.117891,51.535432],"type":"Point"}
}
