{
  "type": "Feature",
  "properties": {
    "iso:country":"GB",
    "wof:name":"LL31 9UB",
    "wof:placetype":"postalcode"
},
  "geometry": {"coordinates":[-3.82391965044367,53.29090845423516],"type":"Point"}
}