{
  "type": "Feature",
  "properties": {
    "iso:country": "GB",
    "wof:name": "NR34 0DQ",
    "wof:placetype": "postalcode"
  },
  "geometry": {"coordinates":[1.60203,52.493601],"type":"Point"}
}
