{
  "type": "Feature",
  "properties": {
    "iso:country":"GB",
    "wof:name":"NR34 0DQ",
    "wof:placetype":"postalcode"
},
  "geometry": {"coordinates":[1.60202991059315,52.49360140263123],"type":"Point"}
}