{
  "type": "Feature",
  "properties": {
    "iso:country": "GB",
    "wof:name": "SL2 1HH",
    "wof:placetype": "postalcode"
  },
  "geometry": {"coordinates":[-0.620028,51.530058],"type":"Point"}
}
