{
  "type": "Feature",
  "properties": {
    "iso:country":"GB",
    "wof:name":"SL2 1HH",
    "wof:placetype":"postalcode"
},
  "geometry": {"coordinates":[-0.62002780554439,51.53005780735894],"type":"Point"}
}