{
  "type": "Feature",
  "properties": {
    "iso:country":"GB",
    "wof:name":"B38 0EL",
    "wof:placetype":"postalcode"
},
  "geometry": {"coordinates":[-1.92081074486428,52.38311325827971],"type":"Point"}
}