{
  "type": "Feature",
  "properties": {
    "iso:country": "GB",
    "wof:name": "B38 0EL",
    "wof:placetype": "postalcode"
  },
  "geometry": {"coordinates":[-1.92117,52.383326],"type":"Point"}
}
