{
  "type": "Feature",
  "properties": {
    "date:inception_lower":"1980-01-01",
    "date:inception_upper":"1980-01-31",
    "iso:country":"GB",
    "wof:name":"TR13 0RU",
    "wof:placetype":"postalcode"
},
  "geometry": {"coordinates":[-5.300971,50.126758],"type":"Point"}
}