{
  "type": "Feature",
  "properties": {
    "iso:country": "GB",
    "wof:name": "TR13 0RU",
    "wof:placetype": "postalcode"
  },
  "geometry": {"coordinates":[-5.300971,50.126758],"type":"Point"}
}
