{
  "type": "Feature",
  "properties": {
    "iso:country": "GB",
    "wof:name": "PO3 5JA",
    "wof:placetype": "postalcode"
  },
  "geometry": {"coordinates":[-1.06617,50.830924],"type":"Point"}
}
