{
  "type": "Feature",
  "properties": {
    "iso:country": "GB",
    "wof:name": "PE14 0NA",
    "wof:placetype": "postalcode"
  },
  "geometry": {"coordinates":[0.177394,52.624623],"type":"Point"}
}
