{
  "type": "Feature",
  "properties": {
    "date:inception_lower": "2015-09-01",
    "date:inception_upper": "2015-09-01",
    "iso:country": "GB",
    "wof:name": "PE14 0NA",
    "wof:placetype": "postalcode"
  },
  "geometry": {"coordinates":[0.177394,52.624623],"type":"Point"}
}
