{
  "type": "Feature",
  "properties": {
    "iso:country":"GB",
    "wof:name":"PE14 0NA",
    "wof:placetype":"postalcode"
},
  "geometry": {"coordinates":[0.17719937411432,52.62458177427948],"type":"Point"}
}