{
  "type": "Feature",
  "properties": {
    "iso:country": "GB",
    "wof:name": "SR7 8EL",
    "wof:placetype": "postalcode"
  },
  "geometry": {"coordinates":[-1.368052,54.835304],"type":"Point"}
}
