{
  "type": "Feature",
  "properties": {
    "iso:country":"GB",
    "wof:name":"SR7 8EL",
    "wof:placetype":"postalcode"
},
  "geometry": {"coordinates":[-1.36802238393103,54.83533156064698],"type":"Point"}
}