{
  "type": "Feature",
  "properties": {
    "iso:country":"GB",
    "wof:name":"HA8 6DL",
    "wof:placetype":"postalcode"
},
  "geometry": {"coordinates":[-0.28464549966268,51.60146531435803],"type":"Point"}
}