{
  "type": "Feature",
  "properties": {
    "iso:country":"GB",
    "wof:name":"BL6 6JE",
    "wof:placetype":"postalcode"
},
  "geometry": {"coordinates":[-2.52347391551954,53.58531309723086],"type":"Point"}
}