{
  "type": "Feature",
  "properties": {
    "iso:country":"GB",
    "wof:name":"BS21 7QE",
    "wof:placetype":"postalcode"
},
  "geometry": {"coordinates":[-2.85783828068094,51.44131205838582],"type":"Point"}
}