{
  "type": "Feature",
  "properties": {
    "date:inception_lower":"1980-01-01",
    "date:inception_upper":"1980-01-31",
    "iso:country":"GB",
    "wof:name":"NR23 1HW",
    "wof:placetype":"postalcode"
},
  "geometry": {"coordinates":[0.848443,52.951844],"type":"Point"}
}