{
  "type": "Feature",
  "properties": {
    "iso:country":"GB",
    "wof:name":"DD11 1QZ",
    "wof:placetype":"postalcode"
},
  "geometry": {"coordinates":[-2.58987211182976,56.55729488721853],"type":"Point"}
}