{
  "type": "Feature",
  "properties": {
    "date:inception_lower": "1980-01-01",
    "date:inception_upper": "1980-01-01",
    "iso:country": "GB",
    "wof:name": "DD11 1QZ",
    "wof:placetype": "postalcode"
  },
  "geometry": {"coordinates":[-2.589872,56.557295],"type":"Point"}
}
