{
  "type": "Feature",
  "properties": {
    "iso:country":"GB",
    "wof:name":"GL54 3DW",
    "wof:placetype":"postalcode"
},
  "geometry": {"coordinates":[-1.75562239256725,51.83101164862174],"type":"Point"}
}