{
  "type": "Feature",
  "properties": {
    "iso:country": "GB",
    "wof:name": "GL54 3DW",
    "wof:placetype": "postalcode"
  },
  "geometry": {"coordinates":[-1.754655,51.830693],"type":"Point"}
}
