{
  "type": "Feature",
  "properties": {
    "iso:country":"GB",
    "wof:name":"NN3 9TB",
    "wof:placetype":"postalcode"
},
  "geometry": {"coordinates":[-0.83065635468383,52.25447338675274],"type":"Point"}
}