{
  "type": "Feature",
  "properties": {
    "date:inception_lower": "2000-06-01",
    "date:inception_upper": "2000-06-01",
    "iso:country": "GB",
    "wof:name": "CT14 7NY",
    "wof:placetype": "postalcode"
  },
  "geometry": {"coordinates":[1.40144,51.210995],"type":"Point"}
}
