{
  "type": "Feature",
  "properties": {
    "iso:country":"GB",
    "wof:name":"CT14 7NY",
    "wof:placetype":"postalcode"
},
  "geometry": {"coordinates":[1.40143393593284,51.2111206844175],"type":"Point"}
}