{
  "type": "Feature",
  "properties": {
    "iso:country":"GB",
    "wof:name":"B13 9DN",
    "wof:placetype":"postalcode"
},
  "geometry": {"coordinates":[-1.88054272381374,52.44768209683575],"type":"Point"}
}