{
  "type": "Feature",
  "properties": {
    "iso:country":"GB",
    "wof:name":"PO35 5AD",
    "wof:placetype":"postalcode"
},
  "geometry": {"coordinates":[-1.081280714947,50.68597142746088],"type":"Point"}
}