{
  "type": "Feature",
  "properties": {
    "date:inception_lower":"2004-03-01",
    "date:inception_upper":"2004-03-31",
    "iso:country":"GB",
    "wof:name":"PO35 5AD",
    "wof:placetype":"postalcode"
},
  "geometry": {"coordinates":[-1.081281,50.685971],"type":"Point"}
}