{
  "type": "Feature",
  "properties": {
    "iso:country": "GB",
    "wof:name": "PO35 5AD",
    "wof:placetype": "postalcode"
  },
  "geometry": {"coordinates":[-1.081281,50.685971],"type":"Point"}
}
