{
  "type": "Feature",
  "properties": {
    "date:inception_lower": "1980-01-01",
    "date:inception_upper": "1980-01-01",
    "iso:country": "GB",
    "wof:name": "KA18 2BP",
    "wof:placetype": "postalcode"
  },
  "geometry": {"coordinates":[-4.29654,55.47415],"type":"Point"}
}
