{
  "type": "Feature",
  "properties": {
    "iso:country": "GB",
    "wof:name": "BB4 4EW",
    "wof:placetype": "postalcode"
  },
  "geometry": {"coordinates":[-2.32374,53.690815],"type":"Point"}
}
