{
  "type": "Feature",
  "properties": {
    "iso:country": "GB",
    "wof:name": "BS14 0FR",
    "wof:placetype": "postalcode"
  },
  "geometry": {"coordinates":[-2.551485,51.403822],"type":"Point"}
}
