{
  "type": "Feature",
  "properties": {
    "iso:country": "GB",
    "wof:name": "BS35 4QB",
    "wof:placetype": "postalcode"
  },
  "geometry": {"coordinates":[-2.659224,51.556935],"type":"Point"}
}
