{
  "type": "Feature",
  "properties": {
    "iso:country":"GB",
    "wof:name":"BS35 4QB",
    "wof:placetype":"postalcode"
},
  "geometry": {"coordinates":[-2.65922446523496,51.55693469654462],"type":"Point"}
}