{
  "type": "Feature",
  "properties": {
    "iso:country":"GB",
    "wof:name":"SA71 5QP",
    "wof:placetype":"postalcode"
},
  "geometry": {"coordinates":[-4.93910294778491,51.66643554202919],"type":"Point"}
}