{
  "type": "Feature",
  "properties": {
    "date:inception_lower":"1980-01-01",
    "date:inception_upper":"1980-01-31",
    "iso:country":"GB",
    "wof:name":"SA71 5QP",
    "wof:placetype":"postalcode"
},
  "geometry": {"coordinates":[-4.939103,51.666436],"type":"Point"}
}