{
  "type": "Feature",
  "properties": {
    "iso:country": "GB",
    "wof:name": "S75 6GA",
    "wof:placetype": "postalcode"
  },
  "geometry": {"coordinates":[-1.498383,53.58149],"type":"Point"}
}
