{
  "type": "Feature",
  "properties": {
    "date:inception_lower": "1998-12-01",
    "date:inception_upper": "1998-12-01",
    "iso:country": "GB",
    "wof:name": "S75 6GA",
    "wof:placetype": "postalcode"
  },
  "geometry": {"coordinates":[-1.498383,53.58149],"type":"Point"}
}
