{
  "type": "Feature",
  "properties": {
    "iso:country":"GB",
    "wof:name":"S75 6GA",
    "wof:placetype":"postalcode"
},
  "geometry": {"coordinates":[-1.49838321008055,53.58149004509822],"type":"Point"}
}