{
  "type": "Feature",
  "properties": {
    "date:inception_lower": "2023-09-01",
    "date:inception_upper": "2023-09-01",
    "iso:country": "GB",
    "wof:name": "ML6 6FF",
    "wof:placetype": "postalcode"
  },
  "geometry": {"coordinates":[-3.972663,55.880458],"type":"Point"}
}
