{
  "type": "Feature",
  "properties": {
    "iso:country": "GB",
    "wof:name": "SW19 4LU",
    "wof:placetype": "postalcode"
  },
  "geometry": {"coordinates":[-0.2202,51.417699],"type":"Point"}
}
