{
  "type": "Feature",
  "properties": {
    "iso:country":"GB",
    "wof:name":"SW19 4LU",
    "wof:placetype":"postalcode"
},
  "geometry": {"coordinates":[-0.22020009412061,51.41769886334258],"type":"Point"}
}