{
  "type": "Feature",
  "properties": {
    "date:inception_lower":"1983-03-01",
    "date:inception_upper":"1983-03-31",
    "iso:country":"GB",
    "wof:name":"SW19 4LU",
    "wof:placetype":"postalcode"
},
  "geometry": {"coordinates":[-0.2202,51.417699],"type":"Point"}
}