{
  "type": "Feature",
  "properties": {
    "date:inception_lower":"1995-07-01",
    "date:inception_upper":"1995-07-31",
    "iso:country":"GB",
    "wof:name":"CF83 1HS",
    "wof:placetype":"postalcode"
},
  "geometry": {"coordinates":[-3.214613,51.569332],"type":"Point"}
}