{
  "type": "Feature",
  "properties": {
    "iso:country":"GB",
    "wof:name":"SA1 2PU",
    "wof:placetype":"postalcode"
},
  "geometry": {"coordinates":[-3.94300685584429,51.64005640563386],"type":"Point"}
}