{
  "type": "Feature",
  "properties": {
    "iso:country": "GB",
    "wof:name": "SA1 2PU",
    "wof:placetype": "postalcode"
  },
  "geometry": {"coordinates":[-3.943007,51.640056],"type":"Point"}
}
