{
  "type": "Feature",
  "properties": {
    "iso:country": "GB",
    "wof:name": "RH11 7NP",
    "wof:placetype": "postalcode"
  },
  "geometry": {"coordinates":[-0.197145,51.129461],"type":"Point"}
}
