{
  "type": "Feature",
  "properties": {
    "iso:country":"GB",
    "wof:name":"YO14 9AB",
    "wof:placetype":"postalcode"
},
  "geometry": {"coordinates":[-0.28928338087301,54.20939651054715],"type":"Point"}
}