{
  "type": "Feature",
  "properties": {
    "iso:country": "GB",
    "wof:name": "DN2 6LL",
    "wof:placetype": "postalcode"
  },
  "geometry": {"coordinates":[-1.101071,53.529036],"type":"Point"}
}
