{
  "type": "Feature",
  "properties": {
    "date:inception_lower": "1992-08-01",
    "date:inception_upper": "1992-08-01",
    "iso:country": "GB",
    "wof:name": "DE24 8LG",
    "wof:placetype": "postalcode"
  },
  "geometry": {"coordinates":[-1.451437,52.895394],"type":"Point"}
}
