{
  "type": "Feature",
  "properties": {
    "date:inception_lower":"1980-01-01",
    "date:inception_upper":"1980-01-31",
    "iso:country":"GB",
    "wof:name":"BD16 1TP",
    "wof:placetype":"postalcode"
},
  "geometry": {"coordinates":[-1.817781,53.840289],"type":"Point"}
}