{
  "type": "Feature",
  "properties": {
    "iso:country":"GB",
    "wof:name":"BD16 1TP",
    "wof:placetype":"postalcode"
},
  "geometry": {"coordinates":[-1.81778065740812,53.8402886374709],"type":"Point"}
}