{
  "type": "Feature",
  "properties": {
    "iso:country": "GB",
    "wof:name": "BD16 1TP",
    "wof:placetype": "postalcode"
  },
  "geometry": {"coordinates":[-1.817781,53.840289],"type":"Point"}
}
