{
  "type": "Feature",
  "properties": {
    "iso:country": "GB",
    "wof:name": "RG10 9HA",
    "wof:placetype": "postalcode"
  },
  "geometry": {"coordinates":[-0.860882,51.482712],"type":"Point"}
}
