{
  "type": "Feature",
  "properties": {
    "iso:country":"GB",
    "wof:name":"HA6 2NJ",
    "wof:placetype":"postalcode"
},
  "geometry": {"coordinates":[-0.4365044186499,51.61203872375111],"type":"Point"}
}