{
  "type": "Feature",
  "properties": {
    "iso:country":"GB",
    "wof:name":"L14 5NG",
    "wof:placetype":"postalcode"
},
  "geometry": {"coordinates":[-2.89469033093109,53.41739612772017],"type":"Point"}
}