{
  "type": "Feature",
  "properties": {
    "iso:country": "GB",
    "wof:name": "L14 5NG",
    "wof:placetype": "postalcode"
  },
  "geometry": {"coordinates":[-2.89469,53.417396],"type":"Point"}
}
