{
  "type": "Feature",
  "properties": {
    "iso:country":"GB",
    "wof:name":"KA9 1TW",
    "wof:placetype":"postalcode"
},
  "geometry": {"coordinates":[-4.61707772268837,55.4862662826499],"type":"Point"}
}