{
  "type": "Feature",
  "properties": {
    "iso:country": "GB",
    "wof:name": "OL10 3PR",
    "wof:placetype": "postalcode"
  },
  "geometry": {"coordinates":[-2.248165,53.586148],"type":"Point"}
}
