{
  "type": "Feature",
  "properties": {
    "iso:country":"GB",
    "wof:name":"S3 7RW",
    "wof:placetype":"postalcode"
},
  "geometry": {"coordinates":[-1.48174312008786,53.37944662522575],"type":"Point"}
}