{
  "type": "Feature",
  "properties": {
    "iso:country": "GB",
    "wof:name": "GL7 5FF",
    "wof:placetype": "postalcode"
  },
  "geometry": {"coordinates":[-1.840339,51.783196],"type":"Point"}
}
