{
  "type": "Feature",
  "properties": {
    "iso:country": "GB",
    "wof:name": "KT14 7BQ",
    "wof:placetype": "postalcode"
  },
  "geometry": {"coordinates":[-0.482368,51.343216],"type":"Point"}
}
