{
  "type": "Feature",
  "properties": {
    "iso:country":"GB",
    "wof:name":"KT14 7BQ",
    "wof:placetype":"postalcode"
},
  "geometry": {"coordinates":[-0.48236816374927,51.34321620557083],"type":"Point"}
}