{
  "type": "Feature",
  "properties": {
    "date:inception_lower": "2007-11-01",
    "date:inception_upper": "2007-11-01",
    "iso:country": "GB",
    "wof:name": "KT14 7BQ",
    "wof:placetype": "postalcode"
  },
  "geometry": {"coordinates":[-0.482368,51.343216],"type":"Point"}
}
