{
  "type": "Feature",
  "properties": {
    "iso:country":"GB",
    "wof:name":"UB6 7LR",
    "wof:placetype":"postalcode"
},
  "geometry": {"coordinates":[-0.3192168603167,51.53996399951718],"type":"Point"}
}