{
  "type": "Feature",
  "properties": {
    "iso:country": "GB",
    "wof:name": "N17 8HB",
    "wof:placetype": "postalcode"
  },
  "geometry": {"coordinates":[-0.076116,51.605975],"type":"Point"}
}
