{
  "type": "Feature",
  "properties": {
    "date:inception_lower": "1992-08-01",
    "date:inception_upper": "1992-08-01",
    "iso:country": "GB",
    "wof:name": "N17 8HB",
    "wof:placetype": "postalcode"
  },
  "geometry": {"coordinates":[-0.076116,51.605975],"type":"Point"}
}
