{
  "type": "Feature",
  "properties": {
    "iso:country":"GB",
    "wof:name":"N17 8HB",
    "wof:placetype":"postalcode"
},
  "geometry": {"coordinates":[-0.07611606292483,51.60597504960799],"type":"Point"}
}