{
  "type": "Feature",
  "properties": {
    "iso:country": "GB",
    "wof:name": "HD6 1LJ",
    "wof:placetype": "postalcode"
  },
  "geometry": {"coordinates":[-1.766582,53.695079],"type":"Point"}
}
