{
  "type": "Feature",
  "properties": {
    "iso:country":"GB",
    "wof:name":"HD6 1LJ",
    "wof:placetype":"postalcode"
},
  "geometry": {"coordinates":[-1.7665820783836,53.69507945390121],"type":"Point"}
}