{
  "type": "Feature",
  "properties": {
    "iso:country":"GB",
    "wof:name":"M33 5NL",
    "wof:placetype":"postalcode"
},
  "geometry": {"coordinates":[-2.353830042773,53.4305701605151],"type":"Point"}
}