{
  "type": "Feature",
  "properties": {
    "date:inception_lower":"2005-06-01",
    "date:inception_upper":"2005-06-30",
    "iso:country":"GB",
    "wof:name":"M33 5NL",
    "wof:placetype":"postalcode"
},
  "geometry": {"coordinates":[-2.3538,53.430588],"type":"Point"}
}