{
  "type": "Feature",
  "properties": {
    "date:inception_lower": "2019-04-01",
    "date:inception_upper": "2019-04-01",
    "iso:country": "GB",
    "wof:name": "ST17 0WE",
    "wof:placetype": "postalcode"
  },
  "geometry": {"coordinates":[-2.081196,52.788558],"type":"Point"}
}
