{
  "type": "Feature",
  "properties": {
    "iso:country": "GB",
    "wof:name": "ST17 0WE",
    "wof:placetype": "postalcode"
  },
  "geometry": {"coordinates":[-2.081581,52.788073],"type":"Point"}
}
