{
  "type": "Feature",
  "properties": {
    "iso:country":"GB",
    "wof:name":"RH1 4EW",
    "wof:placetype":"postalcode"
},
  "geometry": {"coordinates":[-0.13329582119338,51.23977384645461],"type":"Point"}
}