{
  "type": "Feature",
  "properties": {
    "iso:country":"GB",
    "wof:name":"BH12 4EX",
    "wof:placetype":"postalcode"
},
  "geometry": {"coordinates":[-1.92718861231728,50.74111318148263],"type":"Point"}
}