{
  "type": "Feature",
  "properties": {
    "iso:country":"GB",
    "wof:name":"ME16 9BH",
    "wof:placetype":"postalcode"
},
  "geometry": {"coordinates":[0.48372955016324,51.26354934334072],"type":"Point"}
}