{
  "type": "Feature",
  "properties": {
    "iso:country": "GB",
    "wof:name": "S60 2JG",
    "wof:placetype": "postalcode"
  },
  "geometry": {"coordinates":[-1.359711,53.424419],"type":"Point"}
}
