{
  "type": "Feature",
  "properties": {
    "date:inception_lower":"2017-01-01",
    "date:inception_upper":"2017-01-31",
    "iso:country":"GB",
    "wof:name":"S60 2JG",
    "wof:placetype":"postalcode"
},
  "geometry": {"coordinates":[-1.359711,53.424419],"type":"Point"}
}