{
  "type": "Feature",
  "properties": {
    "iso:country":"GB",
    "wof:name":"OL4 5BE",
    "wof:placetype":"postalcode"
},
  "geometry": {"coordinates":[-2.07529509744119,53.53575036790036],"type":"Point"}
}