{
  "type": "Feature",
  "properties": {
    "iso:country":"GB",
    "wof:name":"BR4 0DJ",
    "wof:placetype":"postalcode"
},
  "geometry": {"coordinates":[-0.0042107520596,51.38072137334368],"type":"Point"}
}