{
  "type": "Feature",
  "properties": {
    "iso:country":"GB",
    "wof:name":"LS15 7PE",
    "wof:placetype":"postalcode"
},
  "geometry": {"coordinates":[-1.45426149350813,53.80892399296098],"type":"Point"}
}