{
  "type": "Feature",
  "properties": {
    "iso:country":"GB",
    "wof:name":"G74 4GZ",
    "wof:placetype":"postalcode"
},
  "geometry": {"coordinates":[-4.1757394574687,55.76814857673681],"type":"Point"}
}