{
  "type": "Feature",
  "properties": {
    "iso:country": "GB",
    "wof:name": "G74 4GZ",
    "wof:placetype": "postalcode"
  },
  "geometry": {"coordinates":[-4.175739,55.768149],"type":"Point"}
}
