{
  "type": "Feature",
  "properties": {
    "date:inception_lower":"2006-05-01",
    "date:inception_upper":"2006-05-31",
    "iso:country":"GB",
    "wof:name":"G74 4GZ",
    "wof:placetype":"postalcode"
},
  "geometry": {"coordinates":[-4.175739,55.768149],"type":"Point"}
}