{
  "type": "Feature",
  "properties": {
    "iso:country":"GB",
    "wof:name":"ST5 5HR",
    "wof:placetype":"postalcode"
},
  "geometry": {"coordinates":[-2.29147159733389,52.96480826546401],"type":"Point"}
}