{
  "type": "Feature",
  "properties": {
    "iso:country": "GB",
    "wof:name": "EX12 2UJ",
    "wof:placetype": "postalcode"
  },
  "geometry": {"coordinates":[-3.071473,50.706642],"type":"Point"}
}
