{
  "type": "Feature",
  "properties": {
    "iso:country":"GB",
    "wof:name":"SS4 2AF",
    "wof:placetype":"postalcode"
},
  "geometry": {"coordinates":[0.72699774463857,51.58453711420142],"type":"Point"}
}