{
  "type": "Feature",
  "properties": {
    "date:inception_lower": "1980-01-01",
    "date:inception_upper": "1980-01-01",
    "iso:country": "GB",
    "wof:name": "MK44 1HG",
    "wof:placetype": "postalcode"
  },
  "geometry": {"coordinates":[-0.55939,52.245487],"type":"Point"}
}
