{
  "type": "Feature",
  "properties": {
    "iso:country":"GB",
    "wof:name":"KT5 8DF",
    "wof:placetype":"postalcode"
},
  "geometry": {"coordinates":[-0.29318520530282,51.39690573126351],"type":"Point"}
}