{
  "type": "Feature",
  "properties": {
    "iso:country": "GB",
    "wof:name": "CF47 0HA",
    "wof:placetype": "postalcode"
  },
  "geometry": {"coordinates":[-3.370043,51.747708],"type":"Point"}
}
