{
  "type": "Feature",
  "properties": {
    "date:inception_lower": "1980-01-01",
    "date:inception_upper": "1980-01-01",
    "iso:country": "GB",
    "wof:name": "ME2 3SJ",
    "wof:placetype": "postalcode"
  },
  "geometry": {"coordinates":[0.475637,51.403553],"type":"Point"}
}
