{
  "type": "Feature",
  "properties": {
    "iso:country":"GB",
    "wof:name":"ME2 3SJ",
    "wof:placetype":"postalcode"
},
  "geometry": {"coordinates":[0.47563669095277,51.40355264693434],"type":"Point"}
}