{
  "type": "Feature",
  "properties": {
    "iso:country":"GB",
    "wof:name":"BR1 4HY",
    "wof:placetype":"postalcode"
},
  "geometry": {"coordinates":[0.00534410113369,51.41651156965447],"type":"Point"}
}