{
  "type": "Feature",
  "properties": {
    "iso:country":"GB",
    "wof:name":"LL12 8JB",
    "wof:placetype":"postalcode"
},
  "geometry": {"coordinates":[-2.98640871413181,53.06929601379835],"type":"Point"}
}