{
  "type": "Feature",
  "properties": {
    "iso:country":"GB",
    "wof:name":"MK10 7ER",
    "wof:placetype":"postalcode"
},
  "geometry": {"coordinates":[-0.69129375779719,52.052429946552],"type":"Point"}
}