{
  "type": "Feature",
  "properties": {
    "date:inception_lower": "2011-08-01",
    "date:inception_upper": "2011-08-01",
    "iso:country": "GB",
    "wof:name": "MK10 7ER",
    "wof:placetype": "postalcode"
  },
  "geometry": {"coordinates":[-0.691294,52.05243],"type":"Point"}
}
