{
  "type": "Feature",
  "properties": {
    "iso:country": "GB",
    "wof:name": "B17 9PY",
    "wof:placetype": "postalcode"
  },
  "geometry": {"coordinates":[-1.957351,52.457848],"type":"Point"}
}
