{
  "type": "Feature",
  "properties": {
    "iso:country":"GB",
    "wof:name":"B24 9PP",
    "wof:placetype":"postalcode"
},
  "geometry": {"coordinates":[-1.81660843809031,52.51622979563567],"type":"Point"}
}