{
  "type": "Feature",
  "properties": {
    "iso:country":"GB",
    "wof:name":"NP20 5PH",
    "wof:placetype":"postalcode"
},
  "geometry": {"coordinates":[-3.00142265057425,51.59857168525262],"type":"Point"}
}