{
  "type": "Feature",
  "properties": {
    "iso:country":"GB",
    "wof:name":"WD23 3NW",
    "wof:placetype":"postalcode"
},
  "geometry": {"coordinates":[-0.36299902313129,51.64631278780646],"type":"Point"}
}