{
  "type": "Feature",
  "properties": {
    "iso:country": "GB",
    "wof:name": "HR2 9SJ",
    "wof:placetype": "postalcode"
  },
  "geometry": {"coordinates":[-2.790698,52.035677],"type":"Point"}
}
