{
  "type": "Feature",
  "properties": {
    "iso:country":"GB",
    "wof:name":"HR2 9SJ",
    "wof:placetype":"postalcode"
},
  "geometry": {"coordinates":[-2.79069773087701,52.03567726656038],"type":"Point"}
}