{
  "type": "Feature",
  "properties": {
    "iso:country":"GB",
    "wof:name":"M33 4QP",
    "wof:placetype":"postalcode"
},
  "geometry": {"coordinates":[-2.35978280783409,53.41724029129582],"type":"Point"}
}