{
  "type": "Feature",
  "properties": {
    "date:inception_lower": "1980-01-01",
    "date:inception_upper": "1980-01-01",
    "iso:country": "GB",
    "wof:name": "NG6 0FP",
    "wof:placetype": "postalcode"
  },
  "geometry": {"coordinates":[-1.172178,52.985793],"type":"Point"}
}
