{
  "type": "Feature",
  "properties": {
    "iso:country":"GB",
    "wof:name":"S42 7LP",
    "wof:placetype":"postalcode"
},
  "geometry": {"coordinates":[-1.47157594214647,53.22175621715072],"type":"Point"}
}