{
  "type": "Feature",
  "properties": {
    "iso:country": "GB",
    "wof:name": "RH10 7WG",
    "wof:placetype": "postalcode"
  },
  "geometry": {"coordinates":[-0.147885,51.111109],"type":"Point"}
}
