{
  "type": "Feature",
  "properties": {
    "iso:country":"GB",
    "wof:name":"RH10 7WG",
    "wof:placetype":"postalcode"
},
  "geometry": {"coordinates":[-0.14788550967321,51.11110946884636],"type":"Point"}
}