{
  "type": "Feature",
  "properties": {
    "iso:country": "GB",
    "wof:name": "HS2 0EL",
    "wof:placetype": "postalcode"
  },
  "geometry": {"coordinates":[-6.417154,58.212795],"type":"Point"}
}
