{
  "type": "Feature",
  "properties": {
    "date:inception_lower":"2008-11-01",
    "date:inception_upper":"2008-11-30",
    "iso:country":"GB",
    "wof:name":"HS2 0EL",
    "wof:placetype":"postalcode"
},
  "geometry": {"coordinates":[-6.417154,58.212795],"type":"Point"}
}