{
  "type": "Feature",
  "properties": {
    "iso:country":"GB",
    "wof:name":"LS4 2AS",
    "wof:placetype":"postalcode"
},
  "geometry": {"coordinates":[-1.5777357130498,53.80461336950021],"type":"Point"}
}