{
  "type": "Feature",
  "properties": {
    "date:inception_lower":"1980-01-01",
    "date:inception_upper":"1980-01-31",
    "iso:country":"GB",
    "wof:name":"LS4 2AS",
    "wof:placetype":"postalcode"
},
  "geometry": {"coordinates":[-1.577736,53.804613],"type":"Point"}
}