{
  "type": "Feature",
  "properties": {
    "date:inception_lower": "2021-09-01",
    "date:inception_upper": "2021-09-01",
    "iso:country": "GB",
    "wof:name": "DT1 3FS",
    "wof:placetype": "postalcode"
  },
  "geometry": {"coordinates":[-2.464805,50.716872],"type":"Point"}
}
