{
  "type": "Feature",
  "properties": {
    "date:inception_lower": "2018-11-01",
    "date:inception_upper": "2018-11-01",
    "iso:country": "GB",
    "wof:name": "EC2R 7AG",
    "wof:placetype": "postalcode"
  },
  "geometry": {"coordinates":[-0.087494,51.515312],"type":"Point"}
}
