{
  "type": "Feature",
  "properties": {
    "iso:country": "GB",
    "wof:name": "M15 6BJ",
    "wof:placetype": "postalcode"
  },
  "geometry": {"coordinates":[-2.241667,53.469213],"type":"Point"}
}
