{
  "type": "Feature",
  "properties": {
    "iso:country":"GB",
    "wof:name":"M15 6BJ",
    "wof:placetype":"postalcode"
},
  "geometry": {"coordinates":[-2.2416666954668,53.46921292238665],"type":"Point"}
}