{
  "type": "Feature",
  "properties": {
    "iso:country":"GB",
    "wof:name":"BH20 7AW",
    "wof:placetype":"postalcode"
},
  "geometry": {"coordinates":[-2.10011730571932,50.70858405210395],"type":"Point"}
}