{
  "type": "Feature",
  "properties": {
    "iso:country":"GB",
    "wof:name":"TN12 6YB",
    "wof:placetype":"postalcode"
},
  "geometry": {"coordinates":[0.39407249702418,51.18063547889432],"type":"Point"}
}