{
  "type": "Feature",
  "properties": {
    "date:inception_lower": "1991-01-01",
    "date:inception_upper": "1991-01-01",
    "iso:country": "GB",
    "wof:name": "TN12 6YB",
    "wof:placetype": "postalcode"
  },
  "geometry": {"coordinates":[0.394073,51.180635],"type":"Point"}
}
