{
  "type": "Feature",
  "properties": {
    "iso:country":"GB",
    "wof:name":"CA7 2ET",
    "wof:placetype":"postalcode"
},
  "geometry": {"coordinates":[-3.31898936242505,54.74028502525157],"type":"Point"}
}