{
  "type": "Feature",
  "properties": {
    "iso:country": "GB",
    "wof:name": "CA7 2ET",
    "wof:placetype": "postalcode"
  },
  "geometry": {"coordinates":[-3.318989,54.740285],"type":"Point"}
}
