{
  "type": "Feature",
  "properties": {
    "date:inception_lower": "2007-04-01",
    "date:inception_upper": "2007-04-01",
    "iso:country": "GB",
    "wof:name": "CA11 9FB",
    "wof:placetype": "postalcode"
  },
  "geometry": {"coordinates":[-2.767671,54.670025],"type":"Point"}
}
