{
  "type": "Feature",
  "properties": {
    "iso:country":"GB",
    "wof:name":"CA11 9FB",
    "wof:placetype":"postalcode"
},
  "geometry": {"coordinates":[-2.76766982689642,54.66998029214499],"type":"Point"}
}