{
  "type": "Feature",
  "properties": {
    "iso:country":"GB",
    "wof:name":"IP1 2JH",
    "wof:placetype":"postalcode"
},
  "geometry": {"coordinates":[1.14341679412824,52.06073570764855],"type":"Point"}
}