{
  "type": "Feature",
  "properties": {
    "date:inception_lower": "2022-02-01",
    "date:inception_upper": "2022-02-01",
    "iso:country": "GB",
    "wof:name": "DL2 2WJ",
    "wof:placetype": "postalcode"
  },
  "geometry": {"coordinates":[-1.601852,54.544221],"type":"Point"}
}
