{
  "type": "Feature",
  "properties": {
    "date:inception_lower": "1980-01-01",
    "date:inception_upper": "1980-01-01",
    "iso:country": "GB",
    "wof:name": "TF10 9DR",
    "wof:placetype": "postalcode"
  },
  "geometry": {"coordinates":[-2.30293,52.750841],"type":"Point"}
}
