{
  "type": "Feature",
  "properties": {
    "iso:country":"GB",
    "wof:name":"TF10 9DR",
    "wof:placetype":"postalcode"
},
  "geometry": {"coordinates":[-2.30292960680275,52.750840507919],"type":"Point"}
}