{
  "type": "Feature",
  "properties": {
    "iso:country":"GB",
    "wof:name":"PO6 4DY",
    "wof:placetype":"postalcode"
},
  "geometry": {"coordinates":[-1.0986826531479,50.85182686811829],"type":"Point"}
}