{
  "type": "Feature",
  "properties": {
    "iso:country":"GB",
    "wof:name":"DE13 9HJ",
    "wof:placetype":"postalcode"
},
  "geometry": {"coordinates":[-1.6945767328742,52.84744567152038],"type":"Point"}
}