{
  "type": "Feature",
  "properties": {
    "iso:country": "GB",
    "wof:name": "PH10 6TB",
    "wof:placetype": "postalcode"
  },
  "geometry": {"coordinates":[-3.349352,56.603374],"type":"Point"}
}
