{
  "type": "Feature",
  "properties": {
    "date:inception_lower": "1980-01-01",
    "date:inception_upper": "1980-01-01",
    "iso:country": "GB",
    "wof:name": "G13 3UB",
    "wof:placetype": "postalcode"
  },
  "geometry": {"coordinates":[-4.36397,55.893303],"type":"Point"}
}
