{
  "type": "Feature",
  "properties": {
    "iso:country":"GB",
    "wof:name":"LE2 9UG",
    "wof:placetype":"postalcode"
},
  "geometry": {"coordinates":[-1.14909434630461,52.57954466909111],"type":"Point"}
}