{
  "type": "Feature",
  "properties": {
    "date:inception_lower":"1986-04-01",
    "date:inception_upper":"1986-04-30",
    "iso:country":"GB",
    "wof:name":"LE2 9UG",
    "wof:placetype":"postalcode"
},
  "geometry": {"coordinates":[-1.149094,52.579545],"type":"Point"}
}