{
  "type": "Feature",
  "properties": {
    "date:inception_lower": "1980-01-01",
    "date:inception_upper": "1980-01-01",
    "iso:country": "GB",
    "wof:name": "BA5 1NT",
    "wof:placetype": "postalcode"
  },
  "geometry": {"coordinates":[-2.71028,51.19151],"type":"Point"}
}
