{
  "type": "Feature",
  "properties": {
    "iso:country":"GB",
    "wof:name":"BA5 1NT",
    "wof:placetype":"postalcode"
},
  "geometry": {"coordinates":[-2.71030475044542,51.19152406137979],"type":"Point"}
}