{
  "type": "Feature",
  "properties": {
    "date:inception_lower": "1980-01-01",
    "date:inception_upper": "1980-01-01",
    "iso:country": "GB",
    "wof:name": "NG18 3NG",
    "wof:placetype": "postalcode"
  },
  "geometry": {"coordinates":[-1.161786,53.140103],"type":"Point"}
}
