{
  "type": "Feature",
  "properties": {
    "iso:country":"GB",
    "wof:name":"KT19 9AB",
    "wof:placetype":"postalcode"
},
  "geometry": {"coordinates":[-0.26516345725644,51.33962521236264],"type":"Point"}
}