{
  "type": "Feature",
  "properties": {
    "iso:country":"GB",
    "wof:name":"SA33 5JT",
    "wof:placetype":"postalcode"
},
  "geometry": {"coordinates":[-4.39193928320124,51.77029297420198],"type":"Point"}
}