{
  "type": "Feature",
  "properties": {
    "date:inception_lower": "1980-01-01",
    "date:inception_upper": "1980-01-01",
    "iso:country": "GB",
    "wof:name": "NR29 3BW",
    "wof:placetype": "postalcode"
  },
  "geometry": {"coordinates":[1.560884,52.676282],"type":"Point"}
}
