{
  "type": "Feature",
  "properties": {
    "date:inception_lower": "2003-02-01",
    "date:inception_upper": "2003-02-01",
    "iso:country": "GB",
    "wof:name": "NE2 1RF",
    "wof:placetype": "postalcode"
  },
  "geometry": {"coordinates":[-1.594861,54.98276],"type":"Point"}
}
