{
  "type": "Feature",
  "properties": {
    "iso:country":"GB",
    "wof:name":"NE2 1RF",
    "wof:placetype":"postalcode"
},
  "geometry": {"coordinates":[-1.59486116987619,54.98275962888804],"type":"Point"}
}