{
  "type": "Feature",
  "properties": {
    "date:inception_lower":"1980-01-01",
    "date:inception_upper":"1980-01-31",
    "iso:country":"GB",
    "wof:name":"TW2 6EG",
    "wof:placetype":"postalcode"
},
  "geometry": {"coordinates":[-0.372747,51.446848],"type":"Point"}
}