{
  "type": "Feature",
  "properties": {
    "iso:country":"GB",
    "wof:name":"TW2 6EG",
    "wof:placetype":"postalcode"
},
  "geometry": {"coordinates":[-0.37274669001878,51.44684818589555],"type":"Point"}
}