{
  "type": "Feature",
  "properties": {
    "iso:country":"GB",
    "wof:name":"SS2 5BE",
    "wof:placetype":"postalcode"
},
  "geometry": {"coordinates":[0.71638667930056,51.54193753323236],"type":"Point"}
}