{
  "type": "Feature",
  "properties": {
    "iso:country":"GB",
    "wof:name":"SA14 7NS",
    "wof:placetype":"postalcode"
},
  "geometry": {"coordinates":[-4.05147352491905,51.80091130257092],"type":"Point"}
}