{
  "type": "Feature",
  "properties": {
    "iso:country":"GB",
    "wof:name":"CT12 6BW",
    "wof:placetype":"postalcode"
},
  "geometry": {"coordinates":[1.40660287262857,51.34302060029599],"type":"Point"}
}