{
  "type": "Feature",
  "properties": {
    "date:inception_lower":"1995-01-01",
    "date:inception_upper":"1995-01-31",
    "iso:country":"GB",
    "wof:name":"CT12 6BW",
    "wof:placetype":"postalcode"
},
  "geometry": {"coordinates":[1.406603,51.343021],"type":"Point"}
}