{
  "type": "Feature",
  "properties": {
    "date:inception_lower":"1983-01-01",
    "date:inception_upper":"1983-01-31",
    "iso:country":"GB",
    "wof:name":"LL13 0HD",
    "wof:placetype":"postalcode"
},
  "geometry": {"coordinates":[-2.911921,53.003683],"type":"Point"}
}