{
  "type": "Feature",
  "properties": {
    "iso:country":"GB",
    "wof:name":"EH39 4DD",
    "wof:placetype":"postalcode"
},
  "geometry": {"coordinates":[-2.7262990824509,56.05305368613782],"type":"Point"}
}