{
  "type": "Feature",
  "properties": {
    "date:inception_lower":"1980-01-01",
    "date:inception_upper":"1980-01-31",
    "iso:country":"GB",
    "wof:name":"WD3 6AN",
    "wof:placetype":"postalcode"
},
  "geometry": {"coordinates":[-0.485405,51.684543],"type":"Point"}
}