{
  "type": "Feature",
  "properties": {
    "iso:country":"GB",
    "wof:name":"WD3 6AN",
    "wof:placetype":"postalcode"
},
  "geometry": {"coordinates":[-0.48540528853767,51.68454347720801],"type":"Point"}
}