{
  "type": "Feature",
  "properties": {
    "iso:country": "GB",
    "wof:name": "WA3 5LZ",
    "wof:placetype": "postalcode"
  },
  "geometry": {"coordinates":[-2.495242,53.470345],"type":"Point"}
}
