{
  "type": "Feature",
  "properties": {
    "iso:country":"GB",
    "wof:name":"CW10 0QG",
    "wof:placetype":"postalcode"
},
  "geometry": {"coordinates":[-2.43759108113218,53.18895304516566],"type":"Point"}
}