{
  "type": "Feature",
  "properties": {
    "date:inception_lower": "2006-01-01",
    "date:inception_upper": "2006-01-01",
    "iso:country": "GB",
    "wof:name": "CW10 0QG",
    "wof:placetype": "postalcode"
  },
  "geometry": {"coordinates":[-2.437757,53.189132],"type":"Point"}
}
