{
  "type": "Feature",
  "properties": {
    "iso:country": "GB",
    "wof:name": "BS39 6YG",
    "wof:placetype": "postalcode"
  },
  "geometry": {"coordinates":[-2.518691,51.327374],"type":"Point"}
}
