{
  "type": "Feature",
  "properties": {
    "iso:country":"GB",
    "wof:name":"NE19 1RH",
    "wof:placetype":"postalcode"
},
  "geometry": {"coordinates":[-2.26713801400956,55.27654123852592],"type":"Point"}
}