{
  "type": "Feature",
  "properties": {
    "iso:country":"GB",
    "wof:name":"PE29 6JT",
    "wof:placetype":"postalcode"
},
  "geometry": {"coordinates":[-0.21344372008782,52.33500566638813],"type":"Point"}
}