{
  "type": "Feature",
  "properties": {
    "iso:country": "GB",
    "wof:name": "PE29 6JT",
    "wof:placetype": "postalcode"
  },
  "geometry": {"coordinates":[-0.213444,52.335006],"type":"Point"}
}
