{
  "type": "Feature",
  "properties": {
    "iso:country":"GB",
    "wof:name":"GL15 5RA",
    "wof:placetype":"postalcode"
},
  "geometry": {"coordinates":[-2.52927931856167,51.72719651268062],"type":"Point"}
}