{
  "type": "Feature",
  "properties": {
    "iso:country": "GB",
    "wof:name": "GL15 5RA",
    "wof:placetype": "postalcode"
  },
  "geometry": {"coordinates":[-2.529424,51.727196],"type":"Point"}
}
