{
  "type": "Feature",
  "properties": {
    "date:inception_lower": "1980-01-01",
    "date:inception_upper": "1980-01-01",
    "iso:country": "GB",
    "wof:name": "DH7 9DQ",
    "wof:placetype": "postalcode"
  },
  "geometry": {"coordinates":[-1.72223,54.788643],"type":"Point"}
}
