{
  "type": "Feature",
  "properties": {
    "iso:country":"GB",
    "wof:name":"DH7 9DQ",
    "wof:placetype":"postalcode"
},
  "geometry": {"coordinates":[-1.72223505161087,54.78858915034047],"type":"Point"}
}