{
  "type": "Feature",
  "properties": {
    "iso:country":"GB",
    "wof:name":"DH8 8NQ",
    "wof:placetype":"postalcode"
},
  "geometry": {"coordinates":[-1.84743574378051,54.8581591342554],"type":"Point"}
}