{
  "type": "Feature",
  "properties": {
    "date:inception_lower": "2019-11-01",
    "date:inception_upper": "2019-11-01",
    "iso:country": "GB",
    "wof:name": "BA22 8FX",
    "wof:placetype": "postalcode"
  },
  "geometry": {"coordinates":[-2.683128,50.947017],"type":"Point"}
}
