{
  "type": "Feature",
  "properties": {
    "iso:country": "GB",
    "wof:name": "BA22 8FX",
    "wof:placetype": "postalcode"
  },
  "geometry": {"coordinates":[-2.682655,50.946849],"type":"Point"}
}
