{
  "type": "Feature",
  "properties": {
    "iso:country":"GB",
    "wof:name":"HP1 1AQ",
    "wof:placetype":"postalcode"
},
  "geometry": {"coordinates":[-0.47538902447914,51.74627796076503],"type":"Point"}
}