{
  "type": "Feature",
  "properties": {
    "iso:country":"GB",
    "wof:name":"WN2 1HF",
    "wof:placetype":"postalcode"
},
  "geometry": {"coordinates":[-2.59492728578937,53.55330371738317],"type":"Point"}
}