{
  "type": "Feature",
  "properties": {
    "iso:country":"GB",
    "wof:name":"LL65 1YD",
    "wof:placetype":"postalcode"
},
  "geometry": {"coordinates":[-4.63729834985125,53.3167862640904],"type":"Point"}
}