{
  "type": "Feature",
  "properties": {
    "iso:country":"GB",
    "wof:name":"TR18 2SP",
    "wof:placetype":"postalcode"
},
  "geometry": {"coordinates":[-5.53889742810046,50.12006660586331],"type":"Point"}
}