{
  "type": "Feature",
  "properties": {
    "iso:country": "GB",
    "wof:name": "GU6 7GG",
    "wof:placetype": "postalcode"
  },
  "geometry": {"coordinates":[-0.441882,51.149053],"type":"Point"}
}
