{
  "type": "Feature",
  "properties": {
    "iso:country":"GB",
    "wof:name":"L35 5EZ",
    "wof:placetype":"postalcode"
},
  "geometry": {"coordinates":[-2.80703020947458,53.41819163600696],"type":"Point"}
}