{
  "type": "Feature",
  "properties": {
    "iso:country": "GB",
    "wof:name": "BN14 8HR",
    "wof:placetype": "postalcode"
  },
  "geometry": {"coordinates":[-0.369848,50.826873],"type":"Point"}
}
