{
  "type": "Feature",
  "properties": {
    "iso:country": "GB",
    "wof:name": "OL13 0QN",
    "wof:placetype": "postalcode"
  },
  "geometry": {"coordinates":[-2.22385,53.692832],"type":"Point"}
}
