{
  "type": "Feature",
  "properties": {
    "date:inception_lower":"1992-08-01",
    "date:inception_upper":"1992-08-31",
    "iso:country":"GB",
    "wof:name":"OL13 0QN",
    "wof:placetype":"postalcode"
},
  "geometry": {"coordinates":[-2.22385,53.692832],"type":"Point"}
}