{
  "type": "Feature",
  "properties": {
    "iso:country":"GB",
    "wof:name":"OL13 0QN",
    "wof:placetype":"postalcode"
},
  "geometry": {"coordinates":[-2.22385034145352,53.69283170123067],"type":"Point"}
}