{
  "type": "Feature",
  "properties": {
    "iso:country":"GB",
    "wof:name":"BD21 5NJ",
    "wof:placetype":"postalcode"
},
  "geometry": {"coordinates":[-1.9069318271225,53.85861813126343],"type":"Point"}
}