{
  "type": "Feature",
  "properties": {
    "iso:country": "GB",
    "wof:name": "TF2 7AL",
    "wof:placetype": "postalcode"
  },
  "geometry": {"coordinates":[-2.443985,52.708459],"type":"Point"}
}
