{
  "type": "Feature",
  "properties": {
    "iso:country": "GB",
    "wof:name": "SO15 8PU",
    "wof:placetype": "postalcode"
  },
  "geometry": {"coordinates":[-1.435846,50.918707],"type":"Point"}
}
