{
  "type": "Feature",
  "properties": {
    "iso:country":"GB",
    "wof:name":"SO15 8PU",
    "wof:placetype":"postalcode"
},
  "geometry": {"coordinates":[-1.43584628576732,50.91870696430902],"type":"Point"}
}