{
  "type": "Feature",
  "properties": {
    "date:inception_lower": "1984-10-01",
    "date:inception_upper": "1984-10-01",
    "iso:country": "GB",
    "wof:name": "EX4 3AY",
    "wof:placetype": "postalcode"
  },
  "geometry": {"coordinates":[-3.537909,50.719513],"type":"Point"}
}
