{
  "type": "Feature",
  "properties": {
    "date:inception_lower": "1980-01-01",
    "date:inception_upper": "1980-01-01",
    "iso:country": "GB",
    "wof:name": "PL25 3JH",
    "wof:placetype": "postalcode"
  },
  "geometry": {"coordinates":[-4.754477,50.34176],"type":"Point"}
}
