{
  "type": "Feature",
  "properties": {
    "date:inception_lower": "1980-01-01",
    "date:inception_upper": "1980-01-01",
    "iso:country": "GB",
    "wof:name": "PR8 3DU",
    "wof:placetype": "postalcode"
  },
  "geometry": {"coordinates":[-3.023089,53.612941],"type":"Point"}
}
