{
  "type": "Feature",
  "properties": {
    "iso:country": "GB",
    "wof:name": "PR8 3DU",
    "wof:placetype": "postalcode"
  },
  "geometry": {"coordinates":[-3.023089,53.612941],"type":"Point"}
}
