{
  "type": "Feature",
  "properties": {
    "iso:country":"GB",
    "wof:name":"PL30 4QB",
    "wof:placetype":"postalcode"
},
  "geometry": {"coordinates":[-4.7173079498685,50.50786453414164],"type":"Point"}
}