{
  "type": "Feature",
  "properties": {
    "date:inception_lower": "2012-08-01",
    "date:inception_upper": "2012-08-01",
    "iso:country": "GB",
    "wof:name": "HP15 7HQ",
    "wof:placetype": "postalcode"
  },
  "geometry": {"coordinates":[-0.710411,51.65324],"type":"Point"}
}
