{
  "type": "Feature",
  "properties": {
    "iso:country":"GB",
    "wof:name":"NP26 3BB",
    "wof:placetype":"postalcode"
},
  "geometry": {"coordinates":[-2.82588503139743,51.59837382157097],"type":"Point"}
}