{
  "type": "Feature",
  "properties": {
    "date:inception_lower":"1999-06-01",
    "date:inception_upper":"1999-06-30",
    "iso:country":"GB",
    "wof:name":"NP26 3BB",
    "wof:placetype":"postalcode"
},
  "geometry": {"coordinates":[-2.82585,51.598519],"type":"Point"}
}