{
  "type": "Feature",
  "properties": {
    "iso:country":"GB",
    "wof:name":"B18 5PW",
    "wof:placetype":"postalcode"
},
  "geometry": {"coordinates":[-1.91691887124689,52.49217757943332],"type":"Point"}
}