{
  "type": "Feature",
  "properties": {
    "iso:country":"GB",
    "wof:name":"DN15 9HL",
    "wof:placetype":"postalcode"
},
  "geometry": {"coordinates":[-0.68525566864451,53.64707770956487],"type":"Point"}
}