{
  "type": "Feature",
  "properties": {
    "iso:country":"GB",
    "wof:name":"YO10 4JW",
    "wof:placetype":"postalcode"
},
  "geometry": {"coordinates":[-1.07149538566879,53.94079324167526],"type":"Point"}
}