{
  "type": "Feature",
  "properties": {
    "date:inception_lower":"1980-01-01",
    "date:inception_upper":"1980-01-31",
    "iso:country":"GB",
    "wof:name":"EH15 1DB",
    "wof:placetype":"postalcode"
},
  "geometry": {"coordinates":[-3.115425,55.956325],"type":"Point"}
}