{
  "type": "Feature",
  "properties": {
    "iso:country": "GB",
    "wof:name": "DE55 7HS",
    "wof:placetype": "postalcode"
  },
  "geometry": {"coordinates":[-1.382716,53.097541],"type":"Point"}
}
