{
  "type": "Feature",
  "properties": {
    "iso:country":"GB",
    "wof:name":"G82 5AH",
    "wof:placetype":"postalcode"
},
  "geometry": {"coordinates":[-4.58832480918174,55.95008825028655],"type":"Point"}
}