{
  "type": "Feature",
  "properties": {
    "date:inception_lower": "1980-01-01",
    "date:inception_upper": "1980-01-01",
    "iso:country": "GB",
    "wof:name": "G82 5AH",
    "wof:placetype": "postalcode"
  },
  "geometry": {"coordinates":[-4.588325,55.950088],"type":"Point"}
}
