{
  "type": "Feature",
  "properties": {
    "iso:country": "GB",
    "wof:name": "DE13 8NZ",
    "wof:placetype": "postalcode"
  },
  "geometry": {"coordinates":[-1.794988,52.772077],"type":"Point"}
}
