{
  "type": "Feature",
  "properties": {
    "iso:country":"GB",
    "wof:name":"PH2 7NX",
    "wof:placetype":"postalcode"
},
  "geometry": {"coordinates":[-3.30547454467533,56.37619256504153],"type":"Point"}
}