{
  "type": "Feature",
  "properties": {
    "date:inception_lower": "1980-01-01",
    "date:inception_upper": "1980-01-01",
    "iso:country": "GB",
    "wof:name": "CM22 7TF",
    "wof:placetype": "postalcode"
  },
  "geometry": {"coordinates":[0.220905,51.869691],"type":"Point"}
}
