{
  "type": "Feature",
  "properties": {
    "iso:country":"GB",
    "wof:name":"CM22 7TF",
    "wof:placetype":"postalcode"
},
  "geometry": {"coordinates":[0.22039876148349,51.86969261340427],"type":"Point"}
}