{
  "type": "Feature",
  "properties": {
    "date:inception_lower":"1992-08-01",
    "date:inception_upper":"1992-08-31",
    "iso:country":"GB",
    "wof:name":"SS14 3BX",
    "wof:placetype":"postalcode"
},
  "geometry": {"coordinates":[0.458424,51.583161],"type":"Point"}
}