{
  "type": "Feature",
  "properties": {
    "iso:country":"GB",
    "wof:name":"SS14 3BX",
    "wof:placetype":"postalcode"
},
  "geometry": {"coordinates":[0.45759528806877,51.58412281395915],"type":"Point"}
}