{
  "type": "Feature",
  "properties": {
    "iso:country":"GB",
    "wof:name":"TR26 2BX",
    "wof:placetype":"postalcode"
},
  "geometry": {"coordinates":[-5.48178431625331,50.20889057350564],"type":"Point"}
}