{
  "type": "Feature",
  "properties": {
    "iso:country":"GB",
    "wof:name":"OX33 1UP",
    "wof:placetype":"postalcode"
},
  "geometry": {"coordinates":[-1.13273982949482,51.74389338095327],"type":"Point"}
}