{
  "type": "Feature",
  "properties": {
    "iso:country":"GB",
    "wof:name":"CV22 6NP",
    "wof:placetype":"postalcode"
},
  "geometry": {"coordinates":[-1.29124463830057,52.33452741021826],"type":"Point"}
}