{
  "type": "Feature",
  "properties": {
    "iso:country":"GB",
    "wof:name":"S72 8TH",
    "wof:placetype":"postalcode"
},
  "geometry": {"coordinates":[-1.41489425493232,53.58094028689626],"type":"Point"}
}