{
  "type": "Feature",
  "properties": {
    "iso:country": "GB",
    "wof:name": "NE65 9TZ",
    "wof:placetype": "postalcode"
  },
  "geometry": {"coordinates":[-1.613397,55.307107],"type":"Point"}
}
