{
  "type": "Feature",
  "properties": {
    "iso:country":"GB",
    "wof:name":"NE65 9TZ",
    "wof:placetype":"postalcode"
},
  "geometry": {"coordinates":[-1.61339751218465,55.30710702644609],"type":"Point"}
}