{
  "type": "Feature",
  "properties": {
    "iso:country":"GB",
    "wof:name":"SA11 1RH",
    "wof:placetype":"postalcode"
},
  "geometry": {"coordinates":[-3.8005321406294,51.66547440716613],"type":"Point"}
}