{
  "type": "Feature",
  "properties": {
    "date:inception_lower": "1980-01-01",
    "date:inception_upper": "1980-01-01",
    "iso:country": "GB",
    "wof:name": "B61 7HY",
    "wof:placetype": "postalcode"
  },
  "geometry": {"coordinates":[-2.08014,52.319539],"type":"Point"}
}
