{
  "type": "Feature",
  "properties": {
    "date:inception_lower": "1994-05-01",
    "date:inception_upper": "1994-05-01",
    "iso:country": "GB",
    "wof:name": "M40 1NZ",
    "wof:placetype": "postalcode"
  },
  "geometry": {"coordinates":[-2.174181,53.499199],"type":"Point"}
}
