{
  "type": "Feature",
  "properties": {
    "date:inception_lower": "2001-12-01",
    "date:inception_upper": "2001-12-01",
    "iso:country": "GB",
    "wof:name": "HX3 9HD",
    "wof:placetype": "postalcode"
  },
  "geometry": {"coordinates":[-1.855987,53.715578],"type":"Point"}
}
