{
  "type": "Feature",
  "properties": {
    "date:inception_lower": "2015-05-01",
    "date:inception_upper": "2015-05-01",
    "iso:country": "GB",
    "wof:name": "TR7 1GR",
    "wof:placetype": "postalcode"
  },
  "geometry": {"coordinates":[-5.090363,50.410286],"type":"Point"}
}
