{
  "type": "Feature",
  "properties": {
    "iso:country":"GB",
    "wof:name":"SE5 8JD",
    "wof:placetype":"postalcode"
},
  "geometry": {"coordinates":[-0.08792824827745,51.47319550598522],"type":"Point"}
}