{
  "type": "Feature",
  "properties": {
    "iso:country":"GB",
    "wof:name":"CM17 0DG",
    "wof:placetype":"postalcode"
},
  "geometry": {"coordinates":[0.13318562474791,51.78223662739666],"type":"Point"}
}