{
  "type": "Feature",
  "properties": {
    "iso:country": "GB",
    "wof:name": "PO30 4NU",
    "wof:placetype": "postalcode"
  },
  "geometry": {"coordinates":[-1.392061,50.706646],"type":"Point"}
}
