{
  "type": "Feature",
  "properties": {
    "iso:country":"GB",
    "wof:name":"SE6 9LP",
    "wof:placetype":"postalcode"
},
  "geometry": {"coordinates":[-0.01994393060636,51.43836233808419],"type":"Point"}
}