{
  "type": "Feature",
  "properties": {
    "iso:country":"GB",
    "wof:name":"RH5 6NJ",
    "wof:placetype":"postalcode"
},
  "geometry": {"coordinates":[-0.41244997637134,51.19411898449081],"type":"Point"}
}