{
  "type": "Feature",
  "properties": {
    "iso:country": "GB",
    "wof:name": "EX39 5JA",
    "wof:placetype": "postalcode"
  },
  "geometry": {"coordinates":[-4.194488,50.994522],"type":"Point"}
}
