{
  "type": "Feature",
  "properties": {
    "iso:country":"GB",
    "wof:name":"EX39 5JA",
    "wof:placetype":"postalcode"
},
  "geometry": {"coordinates":[-4.19451076390737,50.99432807355034],"type":"Point"}
}