{
  "type": "Feature",
  "properties": {
    "iso:country":"GB",
    "wof:name":"G71 5SX",
    "wof:placetype":"postalcode"
},
  "geometry": {"coordinates":[-4.07999608141299,55.83555676271668],"type":"Point"}
}