{
  "type": "Feature",
  "properties": {
    "date:inception_lower":"1980-12-01",
    "date:inception_upper":"1980-12-31",
    "iso:country":"GB",
    "wof:name":"G71 5SX",
    "wof:placetype":"postalcode"
},
  "geometry": {"coordinates":[-4.079996,55.835557],"type":"Point"}
}