{
  "type": "Feature",
  "properties": {
    "iso:country": "GB",
    "wof:name": "PO4 8HR",
    "wof:placetype": "postalcode"
  },
  "geometry": {"coordinates":[-1.053552,50.790634],"type":"Point"}
}
