{
  "type": "Feature",
  "properties": {
    "iso:country":"GB",
    "wof:name":"SN7 8AF",
    "wof:placetype":"postalcode"
},
  "geometry": {"coordinates":[-1.57955134901651,51.6594939440294],"type":"Point"}
}