{
  "type": "Feature",
  "properties": {
    "date:inception_lower": "1987-04-01",
    "date:inception_upper": "1987-04-01",
    "iso:country": "GB",
    "wof:name": "SN7 8AF",
    "wof:placetype": "postalcode"
  },
  "geometry": {"coordinates":[-1.579551,51.659494],"type":"Point"}
}
