{
  "type": "Feature",
  "properties": {
    "date:inception_lower": "2002-11-01",
    "date:inception_upper": "2002-11-01",
    "iso:country": "GB",
    "wof:name": "AB41 9QR",
    "wof:placetype": "postalcode"
  },
  "geometry": {"coordinates":[-2.051005,57.36594],"type":"Point"}
}
