{
  "type": "Feature",
  "properties": {
    "iso:country": "GB",
    "wof:name": "LA6 1FD",
    "wof:placetype": "postalcode"
  },
  "geometry": {"coordinates":[-2.758595,54.106389],"type":"Point"}
}
