{
  "type": "Feature",
  "properties": {
    "date:inception_lower":"2000-06-01",
    "date:inception_upper":"2000-06-30",
    "iso:country":"GB",
    "wof:name":"LA6 1FD",
    "wof:placetype":"postalcode"
},
  "geometry": {"coordinates":[-2.758595,54.106389],"type":"Point"}
}