{
  "type": "Feature",
  "properties": {
    "date:inception_lower": "1980-01-01",
    "date:inception_upper": "1980-01-01",
    "iso:country": "GB",
    "wof:name": "TS24 0LN",
    "wof:placetype": "postalcode"
  },
  "geometry": {"coordinates":[-1.187021,54.699435],"type":"Point"}
}
