{
  "type": "Feature",
  "properties": {
    "iso:country":"GB",
    "wof:name":"CT2 0AU",
    "wof:placetype":"postalcode"
},
  "geometry": {"coordinates":[1.12205289520874,51.29893198321312],"type":"Point"}
}