{
  "type": "Feature",
  "properties": {
    "iso:country": "GB",
    "wof:name": "CT2 0AU",
    "wof:placetype": "postalcode"
  },
  "geometry": {"coordinates":[1.122021,51.298875],"type":"Point"}
}
