{
  "type": "Feature",
  "properties": {
    "iso:country":"GB",
    "wof:name":"DL5 6UD",
    "wof:placetype":"postalcode"
},
  "geometry": {"coordinates":[-1.57966162144288,54.60734030189441],"type":"Point"}
}