{
  "type": "Feature",
  "properties": {
    "date:inception_lower":"1980-01-01",
    "date:inception_upper":"1980-01-31",
    "iso:country":"GB",
    "wof:name":"BN20 0JZ",
    "wof:placetype":"postalcode"
},
  "geometry": {"coordinates":[0.212749,50.767081],"type":"Point"}
}