{
  "type": "Feature",
  "properties": {
    "iso:country": "GB",
    "wof:name": "BN20 0JZ",
    "wof:placetype": "postalcode"
  },
  "geometry": {"coordinates":[0.212749,50.767081],"type":"Point"}
}
