{
  "type": "Feature",
  "properties": {
    "date:inception_lower": "1980-01-01",
    "date:inception_upper": "1980-01-01",
    "iso:country": "GB",
    "wof:name": "CT3 4BH",
    "wof:placetype": "postalcode"
  },
  "geometry": {"coordinates":[1.197649,51.304667],"type":"Point"}
}
