{
  "type": "Feature",
  "properties": {
    "iso:country":"GB",
    "wof:name":"CT3 4BH",
    "wof:placetype":"postalcode"
},
  "geometry": {"coordinates":[1.19762185407298,51.30468960188412],"type":"Point"}
}