{
  "type": "Feature",
  "properties": {
    "iso:country": "GB",
    "wof:name": "CT3 4BH",
    "wof:placetype": "postalcode"
  },
  "geometry": {"coordinates":[1.197649,51.304667],"type":"Point"}
}
