{
  "type": "Feature",
  "properties": {
    "iso:country": "GB",
    "wof:name": "SG12 8XL",
    "wof:placetype": "postalcode"
  },
  "geometry": {"coordinates":[0.008723,51.788197],"type":"Point"}
}
