{
  "type": "Feature",
  "properties": {
    "iso:country": "GB",
    "wof:name": "AL10 9UB",
    "wof:placetype": "postalcode"
  },
  "geometry": {"coordinates":[-0.244735,51.764164],"type":"Point"}
}
