{
  "type": "Feature",
  "properties": {
    "date:inception_lower":"2016-09-01",
    "date:inception_upper":"2016-09-30",
    "iso:country":"GB",
    "wof:name":"NN15 6WR",
    "wof:placetype":"postalcode"
},
  "geometry": {"coordinates":[-0.701784,52.378626],"type":"Point"}
}