{
  "type": "Feature",
  "properties": {
    "iso:country":"GB",
    "wof:name":"GL1 5EF",
    "wof:placetype":"postalcode"
},
  "geometry": {"coordinates":[-2.24921611337848,51.84650080358691],"type":"Point"}
}