{
  "type": "Feature",
  "properties": {
    "iso:country":"GB",
    "wof:name":"DL17 8JB",
    "wof:placetype":"postalcode"
},
  "geometry": {"coordinates":[-1.54977646215486,54.69063912728001],"type":"Point"}
}