{
  "type": "Feature",
  "properties": {
    "iso:country":"GB",
    "wof:name":"ME1 2DT",
    "wof:placetype":"postalcode"
},
  "geometry": {"coordinates":[0.5079374605868,51.38053464874071],"type":"Point"}
}