{
  "type": "Feature",
  "properties": {
    "iso:country": "GB",
    "wof:name": "CT21 5QN",
    "wof:placetype": "postalcode"
  },
  "geometry": {"coordinates":[1.109675,51.07182],"type":"Point"}
}
