{
  "type": "Feature",
  "properties": {
    "iso:country":"GB",
    "wof:name":"CT21 5QN",
    "wof:placetype":"postalcode"
},
  "geometry": {"coordinates":[1.10967472072401,51.07181953357065],"type":"Point"}
}