{
  "type": "Feature",
  "properties": {
    "iso:country": "GB",
    "wof:name": "CV6 1JJ",
    "wof:placetype": "postalcode"
  },
  "geometry": {"coordinates":[-1.526898,52.418244],"type":"Point"}
}
