{
  "type": "Feature",
  "properties": {
    "iso:country":"GB",
    "wof:name":"CO14 8RA",
    "wof:placetype":"postalcode"
},
  "geometry": {"coordinates":[1.26087002366971,51.84873075881089],"type":"Point"}
}