{
  "type": "Feature",
  "properties": {
    "iso:country": "GB",
    "wof:name": "CO14 8RA",
    "wof:placetype": "postalcode"
  },
  "geometry": {"coordinates":[1.26087,51.848731],"type":"Point"}
}
