{
  "type": "Feature",
  "properties": {
    "date:inception_lower":"1980-01-01",
    "date:inception_upper":"1980-01-31",
    "iso:country":"GB",
    "wof:name":"CO14 8RA",
    "wof:placetype":"postalcode"
},
  "geometry": {"coordinates":[1.26087,51.848731],"type":"Point"}
}