{
  "type": "Feature",
  "properties": {
    "iso:country": "GB",
    "wof:name": "TW17 8DA",
    "wof:placetype": "postalcode"
  },
  "geometry": {"coordinates":[-0.447994,51.395757],"type":"Point"}
}
