{
  "type": "Feature",
  "properties": {
    "date:inception_lower": "2008-10-01",
    "date:inception_upper": "2008-10-01",
    "iso:country": "GB",
    "wof:name": "BB9 8LF",
    "wof:placetype": "postalcode"
  },
  "geometry": {"coordinates":[-2.194381,53.843783],"type":"Point"}
}
