{
  "type": "Feature",
  "properties": {
    "iso:country": "GB",
    "wof:name": "SK8 2NZ",
    "wof:placetype": "postalcode"
  },
  "geometry": {"coordinates":[-2.217297,53.402205],"type":"Point"}
}
