{
  "type": "Feature",
  "properties": {
    "iso:country":"GB",
    "wof:name":"SK8 2NZ",
    "wof:placetype":"postalcode"
},
  "geometry": {"coordinates":[-2.21729466956742,53.40180092150494],"type":"Point"}
}