{
  "type": "Feature",
  "properties": {
    "iso:country":"GB",
    "wof:name":"WN2 5JP",
    "wof:placetype":"postalcode"
},
  "geometry": {"coordinates":[-2.60685315189463,53.51015288391258],"type":"Point"}
}