{
  "type": "Feature",
  "properties": {
    "iso:country":"GB",
    "wof:name":"BB1 5LA",
    "wof:placetype":"postalcode"
},
  "geometry": {"coordinates":[-2.46685255769163,53.75587461683371],"type":"Point"}
}