{
  "type": "Feature",
  "properties": {
    "iso:country":"GB",
    "wof:name":"M11 2GN",
    "wof:placetype":"postalcode"
},
  "geometry": {"coordinates":[-2.18303291453161,53.47882702900261],"type":"Point"}
}