{
  "type": "Feature",
  "properties": {
    "iso:country": "GB",
    "wof:name": "M11 2GN",
    "wof:placetype": "postalcode"
  },
  "geometry": {"coordinates":[-2.183033,53.478827],"type":"Point"}
}
