{
  "type": "Feature",
  "properties": {
    "date:inception_lower": "1995-01-01",
    "date:inception_upper": "1995-01-01",
    "iso:country": "GB",
    "wof:name": "B13 8AT",
    "wof:placetype": "postalcode"
  },
  "geometry": {"coordinates":[-1.886581,52.451041],"type":"Point"}
}
