{
  "type": "Feature",
  "properties": {
    "iso:country":"GB",
    "wof:name":"B13 8AT",
    "wof:placetype":"postalcode"
},
  "geometry": {"coordinates":[-1.88658129350856,52.45104130127732],"type":"Point"}
}