{
  "type": "Feature",
  "properties": {
    "iso:country": "GB",
    "wof:name": "TS24 7HX",
    "wof:placetype": "postalcode"
  },
  "geometry": {"coordinates":[-1.20595,54.682045],"type":"Point"}
}
