{
  "type": "Feature",
  "properties": {
    "iso:country":"GB",
    "wof:name":"PL1 2ER",
    "wof:placetype":"postalcode"
},
  "geometry": {"coordinates":[-4.14169380101798,50.36919398667464],"type":"Point"}
}