{
  "type": "Feature",
  "properties": {
    "iso:country":"GB",
    "wof:name":"DL2 2XW",
    "wof:placetype":"postalcode"
},
  "geometry": {"coordinates":[-1.60059787871324,54.58306581030007],"type":"Point"}
}