{
  "type": "Feature",
  "properties": {
    "date:inception_lower": "1990-07-01",
    "date:inception_upper": "1990-07-01",
    "iso:country": "GB",
    "wof:name": "CR8 4EA",
    "wof:placetype": "postalcode"
  },
  "geometry": {"coordinates":[-0.125116,51.327152],"type":"Point"}
}
