{
  "type": "Feature",
  "properties": {
    "date:inception_lower":"2001-12-01",
    "date:inception_upper":"2001-12-31",
    "iso:country":"GB",
    "wof:name":"CB9 7WN",
    "wof:placetype":"postalcode"
},
  "geometry": {"coordinates":[0.407559,52.085781],"type":"Point"}
}