{
  "type": "Feature",
  "properties": {
    "iso:country":"GB",
    "wof:name":"PO5 2LQ",
    "wof:placetype":"postalcode"
},
  "geometry": {"coordinates":[-1.08363684476304,50.78081087098297],"type":"Point"}
}