{
  "type": "Feature",
  "properties": {
    "iso:country": "GB",
    "wof:name": "PO5 2LQ",
    "wof:placetype": "postalcode"
  },
  "geometry": {"coordinates":[-1.083637,50.780811],"type":"Point"}
}
