{
  "type": "Feature",
  "properties": {
    "iso:country": "GB",
    "wof:name": "SS13 1HU",
    "wof:placetype": "postalcode"
  },
  "geometry": {"coordinates":[0.516143,51.577261],"type":"Point"}
}
