{
  "type": "Feature",
  "properties": {
    "iso:country":"GB",
    "wof:name":"SS13 1HU",
    "wof:placetype":"postalcode"
},
  "geometry": {"coordinates":[0.51614316998101,51.57726093229859],"type":"Point"}
}