{
  "type": "Feature",
  "properties": {
    "iso:country":"GB",
    "wof:name":"LA20 6EZ",
    "wof:placetype":"postalcode"
},
  "geometry": {"coordinates":[-3.21182121426595,54.27477941956215],"type":"Point"}
}