{
  "type": "Feature",
  "properties": {
    "date:inception_lower": "1980-01-01",
    "date:inception_upper": "1980-01-01",
    "iso:country": "GB",
    "wof:name": "LA20 6EZ",
    "wof:placetype": "postalcode"
  },
  "geometry": {"coordinates":[-3.212453,54.274278],"type":"Point"}
}
