{
  "type": "Feature",
  "properties": {
    "iso:country":"GB",
    "wof:name":"MK3 7HQ",
    "wof:placetype":"postalcode"
},
  "geometry": {"coordinates":[-0.75224336914735,52.00361258408152],"type":"Point"}
}