{
  "type": "Feature",
  "properties": {
    "iso:country":"GB",
    "wof:name":"YO32 2PR",
    "wof:placetype":"postalcode"
},
  "geometry": {"coordinates":[-1.08685249048292,54.01885514670023],"type":"Point"}
}