{
  "type": "Feature",
  "properties": {
    "date:inception_lower": "1980-01-01",
    "date:inception_upper": "1980-01-01",
    "iso:country": "GB",
    "wof:name": "CO15 5DG",
    "wof:placetype": "postalcode"
  },
  "geometry": {"coordinates":[1.185677,51.805435],"type":"Point"}
}
