{
  "type": "Feature",
  "properties": {
    "iso:country":"GB",
    "wof:name":"BD2 1DS",
    "wof:placetype":"postalcode"
},
  "geometry": {"coordinates":[-1.75318557756802,53.81049512307794],"type":"Point"}
}