{
  "type": "Feature",
  "properties": {
    "iso:country": "GB",
    "wof:name": "BR2 6JA",
    "wof:placetype": "postalcode"
  },
  "geometry": {"coordinates":[0.038393,51.361849],"type":"Point"}
}
