{
  "type": "Feature",
  "properties": {
    "iso:country":"GB",
    "wof:name":"HR6 8JF",
    "wof:placetype":"postalcode"
},
  "geometry": {"coordinates":[-2.73947105771007,52.22447258916244],"type":"Point"}
}