{
  "type": "Feature",
  "properties": {
    "date:inception_lower": "1992-08-01",
    "date:inception_upper": "1992-08-01",
    "iso:country": "GB",
    "wof:name": "LE67 5DJ",
    "wof:placetype": "postalcode"
  },
  "geometry": {"coordinates":[-1.360994,52.740672],"type":"Point"}
}
