{
  "type": "Feature",
  "properties": {
    "iso:country":"GB",
    "wof:name":"IP25 6TW",
    "wof:placetype":"postalcode"
},
  "geometry": {"coordinates":[0.81319168271995,52.57031716692177],"type":"Point"}
}