{
  "type": "Feature",
  "properties": {
    "iso:country":"GB",
    "wof:name":"SK11 8UJ",
    "wof:placetype":"postalcode"
},
  "geometry": {"coordinates":[-2.16114505423846,53.25361280669495],"type":"Point"}
}