{
  "type": "Feature",
  "properties": {
    "iso:country":"GB",
    "wof:name":"SE25 4BX",
    "wof:placetype":"postalcode"
},
  "geometry": {"coordinates":[-0.07767639774216,51.40361335362305],"type":"Point"}
}