{
  "type": "Feature",
  "properties": {
    "date:inception_lower": "2007-08-01",
    "date:inception_upper": "2007-08-01",
    "iso:country": "GB",
    "wof:name": "RG19 4PH",
    "wof:placetype": "postalcode"
  },
  "geometry": {"coordinates":[-1.256426,51.394835],"type":"Point"}
}
