{
  "type": "Feature",
  "properties": {
    "date:inception_lower": "1980-01-01",
    "date:inception_upper": "1980-01-01",
    "iso:country": "GB",
    "wof:name": "PR6 0JQ",
    "wof:placetype": "postalcode"
  },
  "geometry": {"coordinates":[-2.621279,53.663233],"type":"Point"}
}
