{
  "type": "Feature",
  "properties": {
    "date:inception_lower": "1980-01-01",
    "date:inception_upper": "1980-01-01",
    "iso:country": "GB",
    "wof:name": "FK1 2DU",
    "wof:placetype": "postalcode"
  },
  "geometry": {"coordinates":[-3.76795,55.973823],"type":"Point"}
}
