{
  "type": "Feature",
  "properties": {
    "iso:country": "GB",
    "wof:name": "FK1 2DU",
    "wof:placetype": "postalcode"
  },
  "geometry": {"coordinates":[-3.76795,55.973823],"type":"Point"}
}
