{
  "type": "Feature",
  "properties": {
    "iso:country":"GB",
    "wof:name":"DG2 0PY",
    "wof:placetype":"postalcode"
},
  "geometry": {"coordinates":[-3.62461224510823,55.08092206324542],"type":"Point"}
}