{
  "type": "Feature",
  "properties": {
    "date:inception_lower":"1980-01-01",
    "date:inception_upper":"1980-01-31",
    "iso:country":"GB",
    "wof:name":"DG2 0PY",
    "wof:placetype":"postalcode"
},
  "geometry": {"coordinates":[-3.624612,55.080922],"type":"Point"}
}