{
  "type": "Feature",
  "properties": {
    "iso:country": "GB",
    "wof:name": "DG2 0PY",
    "wof:placetype": "postalcode"
  },
  "geometry": {"coordinates":[-3.624612,55.080922],"type":"Point"}
}
