{
  "type": "Feature",
  "properties": {
    "iso:country":"GB",
    "wof:name":"SK8 3SX",
    "wof:placetype":"postalcode"
},
  "geometry": {"coordinates":[-2.2283808230501,53.37680090779556],"type":"Point"}
}