{
  "type": "Feature",
  "properties": {
    "iso:country":"GB",
    "wof:name":"SM7 2AA",
    "wof:placetype":"postalcode"
},
  "geometry": {"coordinates":[-0.20739246949477,51.32740653276232],"type":"Point"}
}