{
  "type": "Feature",
  "properties": {
    "iso:country": "GB",
    "wof:name": "SM7 2AA",
    "wof:placetype": "postalcode"
  },
  "geometry": {"coordinates":[-0.207392,51.327407],"type":"Point"}
}
