{
  "type": "Feature",
  "properties": {
    "date:inception_lower": "1980-01-01",
    "date:inception_upper": "1980-01-01",
    "iso:country": "GB",
    "wof:name": "TS4 2SQ",
    "wof:placetype": "postalcode"
  },
  "geometry": {"coordinates":[-1.228978,54.560204],"type":"Point"}
}
