{
  "type": "Feature",
  "properties": {
    "iso:country": "GB",
    "wof:name": "TS4 2SQ",
    "wof:placetype": "postalcode"
  },
  "geometry": {"coordinates":[-1.228978,54.560204],"type":"Point"}
}
