{
  "type": "Feature",
  "properties": {
    "date:inception_lower": "1980-01-01",
    "date:inception_upper": "1980-01-01",
    "iso:country": "GB",
    "wof:name": "SY4 2BA",
    "wof:placetype": "postalcode"
  },
  "geometry": {"coordinates":[-2.858955,52.793943],"type":"Point"}
}
