{
  "type": "Feature",
  "properties": {
    "iso:country":"GB",
    "wof:name":"LE12 8WT",
    "wof:placetype":"postalcode"
},
  "geometry": {"coordinates":[-1.17350785953248,52.75102945005341],"type":"Point"}
}