{
  "type": "Feature",
  "properties": {
    "iso:country":"GB",
    "wof:name":"WF7 6HP",
    "wof:placetype":"postalcode"
},
  "geometry": {"coordinates":[-1.37775208747208,53.69205577249614],"type":"Point"}
}