{
  "type": "Feature",
  "properties": {
    "iso:country": "GB",
    "wof:name": "WF7 6HP",
    "wof:placetype": "postalcode"
  },
  "geometry": {"coordinates":[-1.377752,53.692056],"type":"Point"}
}
