{
  "type": "Feature",
  "properties": {
    "iso:country":"GB",
    "wof:name":"S65 4EY",
    "wof:placetype":"postalcode"
},
  "geometry": {"coordinates":[-1.29970788480156,53.45112895372232],"type":"Point"}
}