{
  "type": "Feature",
  "properties": {
    "date:inception_lower":"1980-01-01",
    "date:inception_upper":"1980-01-31",
    "iso:country":"GB",
    "wof:name":"PR8 6SY",
    "wof:placetype":"postalcode"
},
  "geometry": {"coordinates":[-2.993281,53.643906],"type":"Point"}
}