{
  "type": "Feature",
  "properties": {
    "iso:country":"GB",
    "wof:name":"PR8 6SY",
    "wof:placetype":"postalcode"
},
  "geometry": {"coordinates":[-2.99328140642209,53.64390627028291],"type":"Point"}
}