{
  "type": "Feature",
  "properties": {
    "date:inception_lower": "1980-01-01",
    "date:inception_upper": "1980-01-01",
    "iso:country": "GB",
    "wof:name": "WR10 2AE",
    "wof:placetype": "postalcode"
  },
  "geometry": {"coordinates":[-2.118371,52.130228],"type":"Point"}
}
