{
  "type": "Feature",
  "properties": {
    "iso:country":"GB",
    "wof:name":"WR10 2AE",
    "wof:placetype":"postalcode"
},
  "geometry": {"coordinates":[-2.11837121973009,52.13022775455723],"type":"Point"}
}