{
  "type": "Feature",
  "properties": {
    "date:inception_lower": "2024-04-01",
    "date:inception_upper": "2024-04-01",
    "iso:country": "GB",
    "wof:name": "MK42 6HF",
    "wof:placetype": "postalcode"
  },
  "geometry": {"coordinates":[-0.47658,52.088785],"type":"Point"}
}
