{
  "type": "Feature",
  "properties": {
    "iso:country": "GB",
    "wof:name": "CB2 9DF",
    "wof:placetype": "postalcode"
  },
  "geometry": {"coordinates":[0.122431,52.17785],"type":"Point"}
}
