{
  "type": "Feature",
  "properties": {
    "iso:country": "GB",
    "wof:name": "SE12 8PD",
    "wof:placetype": "postalcode"
  },
  "geometry": {"coordinates":[0.007515,51.455215],"type":"Point"}
}
