{
  "type": "Feature",
  "properties": {
    "iso:country":"GB",
    "wof:name":"SE12 8PD",
    "wof:placetype":"postalcode"
},
  "geometry": {"coordinates":[0.0075149307463,51.45521533194862],"type":"Point"}
}