{
  "type": "Feature",
  "properties": {
    "date:inception_lower":"2011-03-01",
    "date:inception_upper":"2011-03-31",
    "iso:country":"GB",
    "wof:name":"SE12 8PD",
    "wof:placetype":"postalcode"
},
  "geometry": {"coordinates":[0.007515,51.455215],"type":"Point"}
}