{
  "type": "Feature",
  "properties": {
    "iso:country":"GB",
    "wof:name":"LU3 2PW",
    "wof:placetype":"postalcode"
},
  "geometry": {"coordinates":[-0.44521911475371,51.90464989470146],"type":"Point"}
}