{
  "type": "Feature",
  "properties": {
    "date:inception_lower": "1980-01-01",
    "date:inception_upper": "1980-01-01",
    "iso:country": "GB",
    "wof:name": "SK4 5BE",
    "wof:placetype": "postalcode"
  },
  "geometry": {"coordinates":[-2.186295,53.435866],"type":"Point"}
}
