{
  "type": "Feature",
  "properties": {
    "iso:country":"GB",
    "wof:name":"SK4 5BE",
    "wof:placetype":"postalcode"
},
  "geometry": {"coordinates":[-2.18629501038794,53.43586601735434],"type":"Point"}
}