{
  "type": "Feature",
  "properties": {
    "iso:country": "GB",
    "wof:name": "SK11 9FW",
    "wof:placetype": "postalcode"
  },
  "geometry": {"coordinates":[-2.282685,53.269502],"type":"Point"}
}
