{
  "type": "Feature",
  "properties": {
    "iso:country":"GB",
    "wof:name":"N22 8LY",
    "wof:placetype":"postalcode"
},
  "geometry": {"coordinates":[-0.11353961578823,51.60618681860112],"type":"Point"}
}