{
  "type": "Feature",
  "properties": {
    "iso:country":"GB",
    "wof:name":"NE5 1QT",
    "wof:placetype":"postalcode"
},
  "geometry": {"coordinates":[-1.72670890225262,55.003660466207],"type":"Point"}
}