{
  "type": "Feature",
  "properties": {
    "date:inception_lower":"1990-07-01",
    "date:inception_upper":"1990-07-31",
    "iso:country":"GB",
    "wof:name":"NE5 1QT",
    "wof:placetype":"postalcode"
},
  "geometry": {"coordinates":[-1.726709,55.00366],"type":"Point"}
}