{
  "type": "Feature",
  "properties": {
    "iso:country":"GB",
    "wof:name":"SP10 5LQ",
    "wof:placetype":"postalcode"
},
  "geometry": {"coordinates":[-1.45328534378402,51.21946258632411],"type":"Point"}
}