{
  "type": "Feature",
  "properties": {
    "iso:country": "GB",
    "wof:name": "SP10 5LQ",
    "wof:placetype": "postalcode"
  },
  "geometry": {"coordinates":[-1.452518,51.219068],"type":"Point"}
}
