{
  "type": "Feature",
  "properties": {
    "iso:country":"GB",
    "wof:name":"TW2 6RH",
    "wof:placetype":"postalcode"
},
  "geometry": {"coordinates":[-0.34444485160058,51.44592138617848],"type":"Point"}
}