{
  "type": "Feature",
  "properties": {
    "iso:country":"GB",
    "wof:name":"SO40 3AB",
    "wof:placetype":"postalcode"
},
  "geometry": {"coordinates":[-1.48220026847245,50.91821121350733],"type":"Point"}
}