{
  "type": "Feature",
  "properties": {
    "date:inception_lower": "1994-12-01",
    "date:inception_upper": "1994-12-01",
    "iso:country": "GB",
    "wof:name": "SO40 3AB",
    "wof:placetype": "postalcode"
  },
  "geometry": {"coordinates":[-1.4822,50.918211],"type":"Point"}
}
