{
  "type": "Feature",
  "properties": {
    "iso:country":"GB",
    "wof:name":"WS15 3EX",
    "wof:placetype":"postalcode"
},
  "geometry": {"coordinates":[-1.88828418608239,52.81894743111745],"type":"Point"}
}