{
  "type": "Feature",
  "properties": {
    "date:inception_lower":"1980-01-01",
    "date:inception_upper":"1980-01-31",
    "iso:country":"GB",
    "wof:name":"WF8 4LN",
    "wof:placetype":"postalcode"
},
  "geometry": {"coordinates":[-1.317047,53.681326],"type":"Point"}
}