{
  "type": "Feature",
  "properties": {
    "iso:country":"GB",
    "wof:name":"WF8 4LN",
    "wof:placetype":"postalcode"
},
  "geometry": {"coordinates":[-1.31704705968468,53.68132570923938],"type":"Point"}
}