{
  "type": "Feature",
  "properties": {
    "date:inception_lower": "1980-01-01",
    "date:inception_upper": "1980-01-01",
    "iso:country": "GB",
    "wof:name": "PL25 5QJ",
    "wof:placetype": "postalcode"
  },
  "geometry": {"coordinates":[-4.793104,50.340817],"type":"Point"}
}
