{
  "type": "Feature",
  "properties": {
    "iso:country": "GB",
    "wof:name": "YO25 9BW",
    "wof:placetype": "postalcode"
  },
  "geometry": {"coordinates":[-0.45097,53.935736],"type":"Point"}
}
