{
  "type": "Feature",
  "properties": {
    "iso:country":"GB",
    "wof:name":"KA15 1JZ",
    "wof:placetype":"postalcode"
},
  "geometry": {"coordinates":[-4.61665950131659,55.72116662759119],"type":"Point"}
}