{
  "type": "Feature",
  "properties": {
    "iso:country":"GB",
    "wof:name":"SL9 0JZ",
    "wof:placetype":"postalcode"
},
  "geometry": {"coordinates":[-0.54962924214278,51.61763603069455],"type":"Point"}
}