{
  "type": "Feature",
  "properties": {
    "iso:country": "GB",
    "wof:name": "SL9 0JZ",
    "wof:placetype": "postalcode"
  },
  "geometry": {"coordinates":[-0.549629,51.617636],"type":"Point"}
}
