{
  "type": "Feature",
  "properties": {
    "iso:country":"GB",
    "wof:name":"TN2 3GH",
    "wof:placetype":"postalcode"
},
  "geometry": {"coordinates":[0.27605568125379,51.14612748725934],"type":"Point"}
}