{
  "type": "Feature",
  "properties": {
    "date:inception_lower": "2007-01-01",
    "date:inception_upper": "2007-01-01",
    "iso:country": "GB",
    "wof:name": "TN2 3GH",
    "wof:placetype": "postalcode"
  },
  "geometry": {"coordinates":[0.276056,51.146127],"type":"Point"}
}
