{
  "type": "Feature",
  "properties": {
    "date:inception_lower": "1980-01-01",
    "date:inception_upper": "1980-01-01",
    "iso:country": "GB",
    "wof:name": "LA22 0NT",
    "wof:placetype": "postalcode"
  },
  "geometry": {"coordinates":[-2.998085,54.374064],"type":"Point"}
}
