{
  "type": "Feature",
  "properties": {
    "date:inception_lower": "1980-01-01",
    "date:inception_upper": "1980-01-01",
    "iso:country": "GB",
    "wof:name": "SL9 0PP",
    "wof:placetype": "postalcode"
  },
  "geometry": {"coordinates":[-0.557128,51.622575],"type":"Point"}
}
