{
  "type": "Feature",
  "properties": {
    "iso:country": "GB",
    "wof:name": "SL9 0PP",
    "wof:placetype": "postalcode"
  },
  "geometry": {"coordinates":[-0.557128,51.622575],"type":"Point"}
}
