{
  "type": "Feature",
  "properties": {
    "iso:country": "GB",
    "wof:name": "IP29 5NJ",
    "wof:placetype": "postalcode"
  },
  "geometry": {"coordinates":[0.720771,52.199264],"type":"Point"}
}
