{
  "type": "Feature",
  "properties": {
    "iso:country":"GB",
    "wof:name":"EH8 8BZ",
    "wof:placetype":"postalcode"
},
  "geometry": {"coordinates":[-3.17675032930371,55.95204325694355],"type":"Point"}
}