{
  "type": "Feature",
  "properties": {
    "iso:country":"GB",
    "wof:name":"MK46 5EZ",
    "wof:placetype":"postalcode"
},
  "geometry": {"coordinates":[-0.70256770461879,52.16159857033073],"type":"Point"}
}