{
  "type": "Feature",
  "properties": {
    "date:inception_lower": "1999-06-01",
    "date:inception_upper": "1999-06-01",
    "iso:country": "GB",
    "wof:name": "MK46 5EZ",
    "wof:placetype": "postalcode"
  },
  "geometry": {"coordinates":[-0.702568,52.161599],"type":"Point"}
}
