{
  "type": "Feature",
  "properties": {
    "iso:country":"GB",
    "wof:name":"CO5 7ER",
    "wof:placetype":"postalcode"
},
  "geometry": {"coordinates":[0.94776114298805,51.85548005683942],"type":"Point"}
}