{
  "type": "Feature",
  "properties": {
    "iso:country": "GB",
    "wof:name": "CO5 7ER",
    "wof:placetype": "postalcode"
  },
  "geometry": {"coordinates":[0.947761,51.85548],"type":"Point"}
}
