{
  "type": "Feature",
  "properties": {
    "iso:country":"GB",
    "wof:name":"UB7 9LW",
    "wof:placetype":"postalcode"
},
  "geometry": {"coordinates":[-0.45946896437305,51.50186524941356],"type":"Point"}
}