{
  "type": "Feature",
  "properties": {
    "iso:country":"GB",
    "wof:name":"NR2 4AD",
    "wof:placetype":"postalcode"
},
  "geometry": {"coordinates":[1.29596633942199,52.63042248927889],"type":"Point"}
}