{
  "type": "Feature",
  "properties": {
    "iso:country":"GB",
    "wof:name":"G3 6NS",
    "wof:placetype":"postalcode"
},
  "geometry": {"coordinates":[-4.26668952936229,55.8685576490114],"type":"Point"}
}