{
  "type": "Feature",
  "properties": {
    "iso:country": "GB",
    "wof:name": "G3 6NS",
    "wof:placetype": "postalcode"
  },
  "geometry": {"coordinates":[-4.266689,55.868558],"type":"Point"}
}
