{
  "type": "Feature",
  "properties": {
    "date:inception_lower":"1985-07-01",
    "date:inception_upper":"1985-07-31",
    "iso:country":"GB",
    "wof:name":"G3 6NS",
    "wof:placetype":"postalcode"
},
  "geometry": {"coordinates":[-4.266689,55.868558],"type":"Point"}
}