{
  "type": "Feature",
  "properties": {
    "date:inception_lower":"1980-01-01",
    "date:inception_upper":"1980-01-31",
    "iso:country":"GB",
    "wof:name":"LE12 7SJ",
    "wof:placetype":"postalcode"
},
  "geometry": {"coordinates":[-1.104962,52.724677],"type":"Point"}
}