{
  "type": "Feature",
  "properties": {
    "date:inception_lower": "2017-10-01",
    "date:inception_upper": "2017-10-01",
    "iso:country": "GB",
    "wof:name": "WR8 0RY",
    "wof:placetype": "postalcode"
  },
  "geometry": {"coordinates":[-2.201114,52.066805],"type":"Point"}
}
