{
  "type": "Feature",
  "properties": {
    "iso:country":"GB",
    "wof:name":"YO62 6EF",
    "wof:placetype":"postalcode"
},
  "geometry": {"coordinates":[-0.94011492530981,54.27370801718037],"type":"Point"}
}