{
  "type": "Feature",
  "properties": {
    "date:inception_lower": "1998-06-01",
    "date:inception_upper": "1998-06-01",
    "iso:country": "GB",
    "wof:name": "YO62 6EF",
    "wof:placetype": "postalcode"
  },
  "geometry": {"coordinates":[-0.940115,54.273708],"type":"Point"}
}
