{
  "type": "Feature",
  "properties": {
    "date:inception_lower": "1980-01-01",
    "date:inception_upper": "1980-01-01",
    "iso:country": "GB",
    "wof:name": "SG4 9EL",
    "wof:placetype": "postalcode"
  },
  "geometry": {"coordinates":[-0.267449,51.93755],"type":"Point"}
}
