{
  "type": "Feature",
  "properties": {
    "iso:country":"GB",
    "wof:name":"SG4 9EL",
    "wof:placetype":"postalcode"
},
  "geometry": {"coordinates":[-0.26744877960477,51.93754978737309],"type":"Point"}
}