{
  "type": "Feature",
  "properties": {
    "iso:country": "GB",
    "wof:name": "NG18 1JT",
    "wof:placetype": "postalcode"
  },
  "geometry": {"coordinates":[-1.197401,53.143809],"type":"Point"}
}
