{
  "type": "Feature",
  "properties": {
    "iso:country":"GB",
    "wof:name":"DN1 3RX",
    "wof:placetype":"postalcode"
},
  "geometry": {"coordinates":[-1.13874703895989,53.51605464828863],"type":"Point"}
}