{
  "type": "Feature",
  "properties": {
    "iso:country": "GB",
    "wof:name": "SA3 4UU",
    "wof:placetype": "postalcode"
  },
  "geometry": {"coordinates":[-4.01536,51.58016],"type":"Point"}
}
