{
  "type": "Feature",
  "properties": {
    "date:inception_lower": "1985-04-01",
    "date:inception_upper": "1985-04-01",
    "iso:country": "GB",
    "wof:name": "SA3 4UU",
    "wof:placetype": "postalcode"
  },
  "geometry": {"coordinates":[-4.015462,51.580073],"type":"Point"}
}
