{
  "type": "Feature",
  "properties": {
    "iso:country": "GB",
    "wof:name": "PE19 1PY",
    "wof:placetype": "postalcode"
  },
  "geometry": {"coordinates":[-0.252068,52.227526],"type":"Point"}
}
