{
  "type": "Feature",
  "properties": {
    "iso:country": "GB",
    "wof:name": "WV11 2QP",
    "wof:placetype": "postalcode"
  },
  "geometry": {"coordinates":[-2.062205,52.611449],"type":"Point"}
}
