{
  "type": "Feature",
  "properties": {
    "date:inception_lower": "1980-01-01",
    "date:inception_upper": "1980-01-01",
    "iso:country": "GB",
    "wof:name": "WV11 2QP",
    "wof:placetype": "postalcode"
  },
  "geometry": {"coordinates":[-2.062205,52.611449],"type":"Point"}
}
