{
  "type": "Feature",
  "properties": {
    "iso:country": "GB",
    "wof:name": "RH11 8ER",
    "wof:placetype": "postalcode"
  },
  "geometry": {"coordinates":[-0.21447,51.111606],"type":"Point"}
}
