{
  "type": "Feature",
  "properties": {
    "iso:country":"GB",
    "wof:name":"ME2 1DB",
    "wof:placetype":"postalcode"
},
  "geometry": {"coordinates":[0.44548602681992,51.35182602344901],"type":"Point"}
}