{
  "type": "Feature",
  "properties": {
    "iso:country": "GB",
    "wof:name": "ME2 1DB",
    "wof:placetype": "postalcode"
  },
  "geometry": {"coordinates":[0.445486,51.351826],"type":"Point"}
}
