{
  "type": "Feature",
  "properties": {
    "iso:country": "GB",
    "wof:name": "CM18 6HA",
    "wof:placetype": "postalcode"
  },
  "geometry": {"coordinates":[0.115955,51.760409],"type":"Point"}
}
