{
  "type": "Feature",
  "properties": {
    "iso:country":"GB",
    "wof:name":"LE14 4RE",
    "wof:placetype":"postalcode"
},
  "geometry": {"coordinates":[-0.73099047705636,52.81096902045887],"type":"Point"}
}