{
  "type": "Feature",
  "properties": {
    "iso:country": "GB",
    "wof:name": "LE14 4RE",
    "wof:placetype": "postalcode"
  },
  "geometry": {"coordinates":[-0.73099,52.810969],"type":"Point"}
}
