{
  "type": "Feature",
  "properties": {
    "iso:country": "GB",
    "wof:name": "M45 8LG",
    "wof:placetype": "postalcode"
  },
  "geometry": {"coordinates":[-2.271424,53.554907],"type":"Point"}
}
