{
  "type": "Feature",
  "properties": {
    "date:inception_lower":"2004-10-01",
    "date:inception_upper":"2004-10-31",
    "iso:country":"GB",
    "wof:name":"NG18 4XA",
    "wof:placetype":"postalcode"
},
  "geometry": {"coordinates":[-1.179824,53.134134],"type":"Point"}
}