{
  "type": "Feature",
  "properties": {
    "iso:country":"GB",
    "wof:name":"ML5 3SQ",
    "wof:placetype":"postalcode"
},
  "geometry": {"coordinates":[-4.02236387400041,55.8574217152891],"type":"Point"}
}