{
  "type": "Feature",
  "properties": {
    "iso:country": "GB",
    "wof:name": "ML5 3SQ",
    "wof:placetype": "postalcode"
  },
  "geometry": {"coordinates":[-4.023144,55.85789],"type":"Point"}
}
