{
  "type": "Feature",
  "properties": {
    "date:inception_lower": "1995-12-01",
    "date:inception_upper": "1995-12-01",
    "iso:country": "GB",
    "wof:name": "ML5 3SQ",
    "wof:placetype": "postalcode"
  },
  "geometry": {"coordinates":[-4.02286,55.857643],"type":"Point"}
}
