{
  "type": "Feature",
  "properties": {
    "date:inception_lower": "1980-01-01",
    "date:inception_upper": "1980-01-01",
    "iso:country": "GB",
    "wof:name": "BH21 5RN",
    "wof:placetype": "postalcode"
  },
  "geometry": {"coordinates":[-1.923697,50.923319],"type":"Point"}
}
