{
  "type": "Feature",
  "properties": {
    "iso:country":"GB",
    "wof:name":"BH21 5RN",
    "wof:placetype":"postalcode"
},
  "geometry": {"coordinates":[-1.92370446898458,50.92332596322186],"type":"Point"}
}