{
  "type": "Feature",
  "properties": {
    "iso:country":"GB",
    "wof:name":"LL15 2LB",
    "wof:placetype":"postalcode"
},
  "geometry": {"coordinates":[-3.27281034272588,53.06234225429702],"type":"Point"}
}