{
  "type": "Feature",
  "properties": {
    "iso:country":"GB",
    "wof:name":"DH4 6SD",
    "wof:placetype":"postalcode"
},
  "geometry": {"coordinates":[-1.51141915616096,54.81400292323656],"type":"Point"}
}