{
  "type": "Feature",
  "properties": {
    "iso:country": "GB",
    "wof:name": "DH4 6SD",
    "wof:placetype": "postalcode"
  },
  "geometry": {"coordinates":[-1.511419,54.814003],"type":"Point"}
}
