{
  "type": "Feature",
  "properties": {
    "iso:country":"GB",
    "wof:name":"M9 6TA",
    "wof:placetype":"postalcode"
},
  "geometry": {"coordinates":[-2.1993183440823,53.52961245278986],"type":"Point"}
}