{
  "type": "Feature",
  "properties": {
    "date:inception_lower":"1995-12-01",
    "date:inception_upper":"1995-12-31",
    "iso:country":"GB",
    "wof:name":"SO52 9LB",
    "wof:placetype":"postalcode"
},
  "geometry": {"coordinates":[-1.444089,50.974365],"type":"Point"}
}