{
  "type": "Feature",
  "properties": {
    "iso:country":"GB",
    "wof:name":"SO52 9LB",
    "wof:placetype":"postalcode"
},
  "geometry": {"coordinates":[-1.44408868143609,50.97436451142774],"type":"Point"}
}