{
  "type": "Feature",
  "properties": {
    "date:inception_lower": "2020-05-01",
    "date:inception_upper": "2020-05-01",
    "iso:country": "GB",
    "wof:name": "DH4 6FN",
    "wof:placetype": "postalcode"
  },
  "geometry": {"coordinates":[-1.489099,54.853757],"type":"Point"}
}
