{
  "type": "Feature",
  "properties": {
    "date:inception_lower":"1980-01-01",
    "date:inception_upper":"1980-01-31",
    "iso:country":"GB",
    "wof:name":"LU5 5NZ",
    "wof:placetype":"postalcode"
},
  "geometry": {"coordinates":[-0.509403,51.914157],"type":"Point"}
}