{
  "type": "Feature",
  "properties": {
    "date:inception_lower":"2015-07-01",
    "date:inception_upper":"2015-07-31",
    "iso:country":"GB",
    "wof:name":"HA6 9GF",
    "wof:placetype":"postalcode"
},
  "geometry": {"coordinates":[-0.415666,51.603657],"type":"Point"}
}