{
  "type": "Feature",
  "properties": {
    "iso:country": "GB",
    "wof:name": "CV37 8BP",
    "wof:placetype": "postalcode"
  },
  "geometry": {"coordinates":[-1.681389,52.140071],"type":"Point"}
}
