{
  "type": "Feature",
  "properties": {
    "iso:country":"GB",
    "wof:name":"CV37 8BP",
    "wof:placetype":"postalcode"
},
  "geometry": {"coordinates":[-1.68138883016619,52.14007099388825],"type":"Point"}
}