{
  "type": "Feature",
  "properties": {
    "iso:country":"GB",
    "wof:name":"SP2 7RG",
    "wof:placetype":"postalcode"
},
  "geometry": {"coordinates":[-1.79897089586688,51.06920334966243],"type":"Point"}
}