{
  "type": "Feature",
  "properties": {
    "iso:country":"GB",
    "wof:name":"LN8 6LU",
    "wof:placetype":"postalcode"
},
  "geometry": {"coordinates":[-0.24376688486851,53.33600994588419],"type":"Point"}
}