{
  "type": "Feature",
  "properties": {
    "date:inception_lower": "1980-01-01",
    "date:inception_upper": "1980-01-01",
    "iso:country": "GB",
    "wof:name": "NE3 1DU",
    "wof:placetype": "postalcode"
  },
  "geometry": {"coordinates":[-1.624455,55.006298],"type":"Point"}
}
