{
  "type": "Feature",
  "properties": {
    "iso:country":"GB",
    "wof:name":"NE3 1DU",
    "wof:placetype":"postalcode"
},
  "geometry": {"coordinates":[-1.62442411202643,55.00629051323023],"type":"Point"}
}