{
  "type": "Feature",
  "properties": {
    "date:inception_lower": "1980-01-01",
    "date:inception_upper": "1980-01-01",
    "iso:country": "GB",
    "wof:name": "WS5 4NX",
    "wof:placetype": "postalcode"
  },
  "geometry": {"coordinates":[-1.978846,52.564349],"type":"Point"}
}
