{
  "type": "Feature",
  "properties": {
    "iso:country":"GB",
    "wof:name":"GL18 1UE",
    "wof:placetype":"postalcode"
},
  "geometry": {"coordinates":[-2.39880160341305,51.92767207694658],"type":"Point"}
}