{
  "type": "Feature",
  "properties": {
    "iso:country": "GB",
    "wof:name": "GL18 1UE",
    "wof:placetype": "postalcode"
  },
  "geometry": {"coordinates":[-2.398802,51.927672],"type":"Point"}
}
