{
  "type": "Feature",
  "properties": {
    "iso:country":"GB",
    "wof:name":"RG6 3AR",
    "wof:placetype":"postalcode"
},
  "geometry": {"coordinates":[-0.90765383263208,51.43039197752751],"type":"Point"}
}