{
  "type": "Feature",
  "properties": {
    "iso:country":"GB",
    "wof:name":"ST4 7HH",
    "wof:placetype":"postalcode"
},
  "geometry": {"coordinates":[-2.19238854198698,53.00469745601932],"type":"Point"}
}