{
  "type": "Feature",
  "properties": {
    "iso:country":"GB",
    "wof:name":"SE1 7HF",
    "wof:placetype":"postalcode"
},
  "geometry": {"coordinates":[-0.12133552611902,51.49210736939764],"type":"Point"}
}