{
  "type": "Feature",
  "properties": {
    "iso:country": "GB",
    "wof:name": "ME17 4NF",
    "wof:placetype": "postalcode"
  },
  "geometry": {"coordinates":[0.545567,51.234654],"type":"Point"}
}
