{
  "type": "Feature",
  "properties": {
    "date:inception_lower": "2007-07-01",
    "date:inception_upper": "2007-07-01",
    "iso:country": "GB",
    "wof:name": "LS24 9DH",
    "wof:placetype": "postalcode"
  },
  "geometry": {"coordinates":[-1.211127,53.854517],"type":"Point"}
}
