{
  "type": "Feature",
  "properties": {
    "iso:country":"GB",
    "wof:name":"EH5 1JR",
    "wof:placetype":"postalcode"
},
  "geometry": {"coordinates":[-3.23420660352637,55.97703585474505],"type":"Point"}
}