{
  "type": "Feature",
  "properties": {
    "iso:country":"GB",
    "wof:name":"E9 5LT",
    "wof:placetype":"postalcode"
},
  "geometry": {"coordinates":[-0.02666250992022,51.54413053346998],"type":"Point"}
}