{
  "type": "Feature",
  "properties": {
    "iso:country":"GB",
    "wof:name":"DA17 5AZ",
    "wof:placetype":"postalcode"
},
  "geometry": {"coordinates":[0.14743211181863,51.48845546762591],"type":"Point"}
}