{
  "type": "Feature",
  "properties": {
    "iso:country":"GB",
    "wof:name":"TS6 0GH",
    "wof:placetype":"postalcode"
},
  "geometry": {"coordinates":[-1.17245131468615,54.56355155179954],"type":"Point"}
}