{
  "type": "Feature",
  "properties": {
    "date:inception_lower":"2016-01-01",
    "date:inception_upper":"2016-01-31",
    "iso:country":"GB",
    "wof:name":"TS6 0GH",
    "wof:placetype":"postalcode"
},
  "geometry": {"coordinates":[-1.1723,54.564094],"type":"Point"}
}