{
  "type": "Feature",
  "properties": {
    "iso:country":"GB",
    "wof:name":"BH21 7SH",
    "wof:placetype":"postalcode"
},
  "geometry": {"coordinates":[-1.92099421901762,50.80940786317176],"type":"Point"}
}