{
  "type": "Feature",
  "properties": {
    "iso:country":"GB",
    "wof:name":"BN3 5PQ",
    "wof:placetype":"postalcode"
},
  "geometry": {"coordinates":[-0.18318755762535,50.83222629138998],"type":"Point"}
}