{
  "type": "Feature",
  "properties": {
    "iso:country":"GB",
    "wof:name":"DN39 6TD",
    "wof:placetype":"postalcode"
},
  "geometry": {"coordinates":[-0.33817970536048,53.61784485966853],"type":"Point"}
}