{
  "type": "Feature",
  "properties": {
    "iso:country": "GB",
    "wof:name": "DN39 6TD",
    "wof:placetype": "postalcode"
  },
  "geometry": {"coordinates":[-0.33823,53.617867],"type":"Point"}
}
