{
  "type": "Feature",
  "properties": {
    "iso:country":"GB",
    "wof:name":"PL3 6AD",
    "wof:placetype":"postalcode"
},
  "geometry": {"coordinates":[-4.11148945644501,50.38318407520248],"type":"Point"}
}