{
  "type": "Feature",
  "properties": {
    "date:inception_lower":"1980-01-01",
    "date:inception_upper":"1980-01-31",
    "iso:country":"GB",
    "wof:name":"EX22 6LN",
    "wof:placetype":"postalcode"
},
  "geometry": {"coordinates":[-4.41181,50.810422],"type":"Point"}
}