{
  "type": "Feature",
  "properties": {
    "iso:country":"GB",
    "wof:name":"EX22 6LN",
    "wof:placetype":"postalcode"
},
  "geometry": {"coordinates":[-4.41181003112053,50.81042210680517],"type":"Point"}
}