{
  "type": "Feature",
  "properties": {
    "iso:country":"GB",
    "wof:name":"PE11 3PG",
    "wof:placetype":"postalcode"
},
  "geometry": {"coordinates":[-0.16210581737946,52.8042509634904],"type":"Point"}
}