{
  "type": "Feature",
  "properties": {
    "iso:country": "GB",
    "wof:name": "IP30 9XH",
    "wof:placetype": "postalcode"
  },
  "geometry": {"coordinates":[0.830927,52.215978],"type":"Point"}
}
