{
  "type": "Feature",
  "properties": {
    "date:inception_lower": "1980-01-01",
    "date:inception_upper": "1980-01-01",
    "iso:country": "GB",
    "wof:name": "HG3 4AL",
    "wof:placetype": "postalcode"
  },
  "geometry": {"coordinates":[-1.758183,54.032707],"type":"Point"}
}
