{
  "type": "Feature",
  "properties": {
    "iso:country":"GB",
    "wof:name":"HG3 4AL",
    "wof:placetype":"postalcode"
},
  "geometry": {"coordinates":[-1.75876172634403,54.03211847623085],"type":"Point"}
}