{
  "type": "Feature",
  "properties": {
    "iso:country":"GB",
    "wof:name":"CB8 0JD",
    "wof:placetype":"postalcode"
},
  "geometry": {"coordinates":[0.40159026491741,52.24627352097024],"type":"Point"}
}