{
  "type": "Feature",
  "properties": {
    "date:inception_lower": "1980-01-01",
    "date:inception_upper": "1980-01-01",
    "iso:country": "GB",
    "wof:name": "IP12 2QE",
    "wof:placetype": "postalcode"
  },
  "geometry": {"coordinates":[1.379093,52.116629],"type":"Point"}
}
