{
  "type": "Feature",
  "properties": {
    "date:inception_lower": "1980-01-01",
    "date:inception_upper": "1980-01-01",
    "iso:country": "GB",
    "wof:name": "LL18 5NW",
    "wof:placetype": "postalcode"
  },
  "geometry": {"coordinates":[-3.527063,53.310596],"type":"Point"}
}
