{
  "type": "Feature",
  "properties": {
    "iso:country":"GB",
    "wof:name":"LL18 5NW",
    "wof:placetype":"postalcode"
},
  "geometry": {"coordinates":[-3.52706277070618,53.31059625646009],"type":"Point"}
}