{
  "type": "Feature",
  "properties": {
    "iso:country": "GB",
    "wof:name": "OX29 7XD",
    "wof:placetype": "postalcode"
  },
  "geometry": {"coordinates":[-1.482676,51.766139],"type":"Point"}
}
