{
  "type": "Feature",
  "properties": {
    "iso:country":"GB",
    "wof:name":"OX29 7XD",
    "wof:placetype":"postalcode"
},
  "geometry": {"coordinates":[-1.48267619686474,51.76613891258506],"type":"Point"}
}