{
  "type": "Feature",
  "properties": {
    "iso:country":"GB",
    "wof:name":"LE3 3HR",
    "wof:placetype":"postalcode"
},
  "geometry": {"coordinates":[-1.2108764775913,52.62441887532786],"type":"Point"}
}