{
  "type": "Feature",
  "properties": {
    "iso:country": "GB",
    "wof:name": "SO24 9TF",
    "wof:placetype": "postalcode"
  },
  "geometry": {"coordinates":[-1.202384,51.097302],"type":"Point"}
}
