{
  "type": "Feature",
  "properties": {
    "date:inception_lower": "1980-01-01",
    "date:inception_upper": "1980-01-01",
    "iso:country": "GB",
    "wof:name": "SO24 9TF",
    "wof:placetype": "postalcode"
  },
  "geometry": {"coordinates":[-1.202384,51.097302],"type":"Point"}
}
