{
  "type": "Feature",
  "properties": {
    "iso:country": "GB",
    "wof:name": "SK13 2EA",
    "wof:placetype": "postalcode"
  },
  "geometry": {"coordinates":[-1.979586,53.456036],"type":"Point"}
}
