{
  "type": "Feature",
  "properties": {
    "iso:country":"GB",
    "wof:name":"SK13 2EA",
    "wof:placetype":"postalcode"
},
  "geometry": {"coordinates":[-1.97958565895991,53.45603633871738],"type":"Point"}
}