{
  "type": "Feature",
  "properties": {
    "iso:country":"GB",
    "wof:name":"SL4 5LB",
    "wof:placetype":"postalcode"
},
  "geometry": {"coordinates":[-0.63474127113588,51.48010837448636],"type":"Point"}
}