{
  "type": "Feature",
  "properties": {
    "date:inception_lower": "2002-06-01",
    "date:inception_upper": "2002-06-01",
    "iso:country": "GB",
    "wof:name": "LS28 6LU",
    "wof:placetype": "postalcode"
  },
  "geometry": {"coordinates":[-1.650732,53.80758],"type":"Point"}
}
