{
  "type": "Feature",
  "properties": {
    "iso:country":"GB",
    "wof:name":"E16 1GD",
    "wof:placetype":"postalcode"
},
  "geometry": {"coordinates":[0.02037129004595,51.51392386764847],"type":"Point"}
}