{
  "type": "Feature",
  "properties": {
    "date:inception_lower": "2009-03-01",
    "date:inception_upper": "2009-03-01",
    "iso:country": "GB",
    "wof:name": "E16 1GD",
    "wof:placetype": "postalcode"
  },
  "geometry": {"coordinates":[0.020371,51.513924],"type":"Point"}
}
