{
  "type": "Feature",
  "properties": {
    "iso:country": "GB",
    "wof:name": "E16 1GD",
    "wof:placetype": "postalcode"
  },
  "geometry": {"coordinates":[0.020371,51.513924],"type":"Point"}
}
