{
  "type": "Feature",
  "properties": {
    "iso:country": "GB",
    "wof:name": "PO7 5FE",
    "wof:placetype": "postalcode"
  },
  "geometry": {"coordinates":[-1.028418,50.865616],"type":"Point"}
}
