{
  "type": "Feature",
  "properties": {
    "iso:country":"GB",
    "wof:name":"HP4 3PD",
    "wof:placetype":"postalcode"
},
  "geometry": {"coordinates":[-0.57332375252889,51.75736243330235],"type":"Point"}
}