{
  "type": "Feature",
  "properties": {
    "iso:country": "GB",
    "wof:name": "TW9 1QD",
    "wof:placetype": "postalcode"
  },
  "geometry": {"coordinates":[-0.305601,51.460797],"type":"Point"}
}
