{
  "type": "Feature",
  "properties": {
    "iso:country":"GB",
    "wof:name":"TW9 1QD",
    "wof:placetype":"postalcode"
},
  "geometry": {"coordinates":[-0.30560105988026,51.46079738133557],"type":"Point"}
}