{
  "type": "Feature",
  "properties": {
    "iso:country":"GB",
    "wof:name":"E10 7HS",
    "wof:placetype":"postalcode"
},
  "geometry": {"coordinates":[-0.02293356393748,51.57026315087977],"type":"Point"}
}