{
  "type": "Feature",
  "properties": {
    "date:inception_lower": "1980-01-01",
    "date:inception_upper": "1980-01-01",
    "iso:country": "GB",
    "wof:name": "S41 0QZ",
    "wof:placetype": "postalcode"
  },
  "geometry": {"coordinates":[-1.419338,53.22253],"type":"Point"}
}
