{
  "type": "Feature",
  "properties": {
    "iso:country":"GB",
    "wof:name":"S41 0QZ",
    "wof:placetype":"postalcode"
},
  "geometry": {"coordinates":[-1.41933942193689,53.22251106553642],"type":"Point"}
}