{
  "type": "Feature",
  "properties": {
    "iso:country":"GB",
    "wof:name":"RM8 2ES",
    "wof:placetype":"postalcode"
},
  "geometry": {"coordinates":[0.12033396983822,51.549218510204],"type":"Point"}
}