{
  "type": "Feature",
  "properties": {
    "iso:country":"GB",
    "wof:name":"HP13 6FY",
    "wof:placetype":"postalcode"
},
  "geometry": {"coordinates":[-0.74540720604845,51.63439484389659],"type":"Point"}
}