{
  "type": "Feature",
  "properties": {
    "date:inception_lower": "2003-01-01",
    "date:inception_upper": "2003-01-01",
    "iso:country": "GB",
    "wof:name": "HP13 6FY",
    "wof:placetype": "postalcode"
  },
  "geometry": {"coordinates":[-0.745407,51.634395],"type":"Point"}
}
