{
  "type": "Feature",
  "properties": {
    "iso:country": "GB",
    "wof:name": "CF14 2ED",
    "wof:placetype": "postalcode"
  },
  "geometry": {"coordinates":[-3.228416,51.509167],"type":"Point"}
}
