{
  "type": "Feature",
  "properties": {
    "iso:country":"GB",
    "wof:name":"CF14 2ED",
    "wof:placetype":"postalcode"
},
  "geometry": {"coordinates":[-3.22841576837043,51.50916718449811],"type":"Point"}
}