{
  "type": "Feature",
  "properties": {
    "date:inception_lower": "2022-09-01",
    "date:inception_upper": "2022-09-01",
    "iso:country": "GB",
    "wof:name": "SY2 5WY",
    "wof:placetype": "postalcode"
  },
  "geometry": {"coordinates":[-2.716474,52.699633],"type":"Point"}
}
