{
  "type": "Feature",
  "properties": {
    "date:inception_lower": "2002-09-01",
    "date:inception_upper": "2002-09-01",
    "iso:country": "GB",
    "wof:name": "AB51 5HG",
    "wof:placetype": "postalcode"
  },
  "geometry": {"coordinates":[-2.473598,57.306275],"type":"Point"}
}
