{
  "type": "Feature",
  "properties": {
    "date:inception_lower": "2020-05-01",
    "date:inception_upper": "2020-05-01",
    "iso:country": "GB",
    "wof:name": "M4 1AG",
    "wof:placetype": "postalcode"
  },
  "geometry": {"coordinates":[-2.237039,53.482658],"type":"Point"}
}
