{
  "type": "Feature",
  "properties": {
    "date:inception_lower": "1984-02-01",
    "date:inception_upper": "1984-02-01",
    "iso:country": "GB",
    "wof:name": "GU15 3HX",
    "wof:placetype": "postalcode"
  },
  "geometry": {"coordinates":[-0.762793,51.334536],"type":"Point"}
}
