{
  "type": "Feature",
  "properties": {
    "iso:country": "GB",
    "wof:name": "TA4 4ZN",
    "wof:placetype": "postalcode"
  },
  "geometry": {"coordinates":[-3.109646,51.023442],"type":"Point"}
}
