{
  "type": "Feature",
  "properties": {
    "iso:country":"GB",
    "wof:name":"E7 8BX",
    "wof:placetype":"postalcode"
},
  "geometry": {"coordinates":[0.03072130487256,51.54603785945948],"type":"Point"}
}