{
  "type": "Feature",
  "properties": {
    "date:inception_lower": "1980-01-01",
    "date:inception_upper": "1980-01-01",
    "iso:country": "GB",
    "wof:name": "RH1 5QD",
    "wof:placetype": "postalcode"
  },
  "geometry": {"coordinates":[-0.117542,51.193307],"type":"Point"}
}
