{
  "type": "Feature",
  "properties": {
    "iso:country":"GB",
    "wof:name":"RH1 5QD",
    "wof:placetype":"postalcode"
},
  "geometry": {"coordinates":[-0.11754200008893,51.19330677265572],"type":"Point"}
}