{
  "type": "Feature",
  "properties": {
    "iso:country":"GB",
    "wof:name":"M19 3AA",
    "wof:placetype":"postalcode"
},
  "geometry": {"coordinates":[-2.19197788753871,53.44433317302634],"type":"Point"}
}