{
  "type": "Feature",
  "properties": {
    "iso:country":"GB",
    "wof:name":"PO33 1TU",
    "wof:placetype":"postalcode"
},
  "geometry": {"coordinates":[-1.10960239703772,50.69740532863007],"type":"Point"}
}