{
  "type": "Feature",
  "properties": {
    "iso:country": "GB",
    "wof:name": "AB21 0UD",
    "wof:placetype": "postalcode"
  },
  "geometry": {"coordinates":[-2.18561,57.273084],"type":"Point"}
}
