{
  "type": "Feature",
  "properties": {
    "iso:country":"GB",
    "wof:name":"UB5 6JR",
    "wof:placetype":"postalcode"
},
  "geometry": {"coordinates":[-0.39648926010657,51.53271876125026],"type":"Point"}
}