{
  "type": "Feature",
  "properties": {
    "iso:country":"GB",
    "wof:name":"GU23 6LN",
    "wof:placetype":"postalcode"
},
  "geometry": {"coordinates":[-0.51056150448422,51.2880049681342],"type":"Point"}
}