{
  "type": "Feature",
  "properties": {
    "date:inception_lower": "1980-01-01",
    "date:inception_upper": "1980-01-01",
    "iso:country": "GB",
    "wof:name": "HP4 2QQ",
    "wof:placetype": "postalcode"
  },
  "geometry": {"coordinates":[-0.527947,51.76842],"type":"Point"}
}
