{
  "type": "Feature",
  "properties": {
    "iso:country":"GB",
    "wof:name":"HP4 2QQ",
    "wof:placetype":"postalcode"
},
  "geometry": {"coordinates":[-0.52794690739846,51.76842028026698],"type":"Point"}
}