{
  "type": "Feature",
  "properties": {
    "iso:country":"GB",
    "wof:name":"PR2 9PR",
    "wof:placetype":"postalcode"
},
  "geometry": {"coordinates":[-2.68519392508062,53.79125406968264],"type":"Point"}
}