{
  "type": "Feature",
  "properties": {
    "iso:country":"GB",
    "wof:name":"DL2 3DB",
    "wof:placetype":"postalcode"
},
  "geometry": {"coordinates":[-1.73083334555564,54.54701953700674],"type":"Point"}
}