{
  "type": "Feature",
  "properties": {
    "iso:country": "GB",
    "wof:name": "DL2 3DB",
    "wof:placetype": "postalcode"
  },
  "geometry": {"coordinates":[-1.730833,54.54702],"type":"Point"}
}
