{
  "type": "Feature",
  "properties": {
    "iso:country": "GB",
    "wof:name": "DL8 4EX",
    "wof:placetype": "postalcode"
  },
  "geometry": {"coordinates":[-1.946341,54.322407],"type":"Point"}
}
