{
  "type": "Feature",
  "properties": {
    "iso:country":"GB",
    "wof:name":"DL8 4EX",
    "wof:placetype":"postalcode"
},
  "geometry": {"coordinates":[-1.94634059626601,54.32240693407986],"type":"Point"}
}