{
  "type": "Feature",
  "properties": {
    "date:inception_lower":"2007-10-01",
    "date:inception_upper":"2007-10-31",
    "iso:country":"GB",
    "wof:name":"PA16 0LY",
    "wof:placetype":"postalcode"
},
  "geometry": {"coordinates":[-4.856965,55.913451],"type":"Point"}
}