{
  "type": "Feature",
  "properties": {
    "iso:country":"GB",
    "wof:name":"PA16 0LY",
    "wof:placetype":"postalcode"
},
  "geometry": {"coordinates":[-4.85696458889554,55.91345104235445],"type":"Point"}
}