{
  "type": "Feature",
  "properties": {
    "iso:country":"GB",
    "wof:name":"B93 9ER",
    "wof:placetype":"postalcode"
},
  "geometry": {"coordinates":[-1.75278630123973,52.38723287587904],"type":"Point"}
}