{
  "type": "Feature",
  "properties": {
    "iso:country":"GB",
    "wof:name":"YO24 4JN",
    "wof:placetype":"postalcode"
},
  "geometry": {"coordinates":[-1.10918019213615,53.9524484490365],"type":"Point"}
}