{
  "type": "Feature",
  "properties": {
    "date:inception_lower": "1998-06-01",
    "date:inception_upper": "1998-06-01",
    "iso:country": "GB",
    "wof:name": "YO24 4JN",
    "wof:placetype": "postalcode"
  },
  "geometry": {"coordinates":[-1.109496,53.952361],"type":"Point"}
}
