{
  "type": "Feature",
  "properties": {
    "date:inception_lower": "1980-01-01",
    "date:inception_upper": "1980-01-01",
    "iso:country": "GB",
    "wof:name": "GL52 3JS",
    "wof:placetype": "postalcode"
  },
  "geometry": {"coordinates":[-2.064566,51.911894],"type":"Point"}
}
