{
  "type": "Feature",
  "properties": {
    "iso:country": "GB",
    "wof:name": "DH3 1LE",
    "wof:placetype": "postalcode"
  },
  "geometry": {"coordinates":[-1.577153,54.896799],"type":"Point"}
}
