{
  "type": "Feature",
  "properties": {
    "iso:country":"GB",
    "wof:name":"DH3 1LE",
    "wof:placetype":"postalcode"
},
  "geometry": {"coordinates":[-1.5771534056272,54.89679910584135],"type":"Point"}
}