{
  "type": "Feature",
  "properties": {
    "iso:country":"GB",
    "wof:name":"SL1 5HQ",
    "wof:placetype":"postalcode"
},
  "geometry": {"coordinates":[-0.64464117925996,51.51728834260779],"type":"Point"}
}