{
  "type": "Feature",
  "properties": {
    "date:inception_lower": "1980-01-01",
    "date:inception_upper": "1980-01-01",
    "iso:country": "GB",
    "wof:name": "KA26 0ED",
    "wof:placetype": "postalcode"
  },
  "geometry": {"coordinates":[-4.850749,55.236088],"type":"Point"}
}
