{
  "type": "Feature",
  "properties": {
    "iso:country":"GB",
    "wof:name":"KA26 0ED",
    "wof:placetype":"postalcode"
},
  "geometry": {"coordinates":[-4.85074900348792,55.23608831555043],"type":"Point"}
}