{
  "type": "Feature",
  "properties": {
    "iso:country": "GB",
    "wof:name": "PE24 5DF",
    "wof:placetype": "postalcode"
  },
  "geometry": {"coordinates":[0.202487,53.153314],"type":"Point"}
}
