{
  "type": "Feature",
  "properties": {
    "iso:country": "GB",
    "wof:name": "PE24 5DF",
    "wof:placetype": "postalcode"
  },
  "geometry": {"coordinates":[0.206686,53.153839],"type":"Point"}
}
