{
  "type": "Feature",
  "properties": {
    "iso:country": "GB",
    "wof:name": "CV35 0HH",
    "wof:placetype": "postalcode"
  },
  "geometry": {"coordinates":[-1.464386,52.170726],"type":"Point"}
}
