{
  "type": "Feature",
  "properties": {
    "iso:country":"GB",
    "wof:name":"CV35 0HH",
    "wof:placetype":"postalcode"
},
  "geometry": {"coordinates":[-1.46438595579224,52.17072560443672],"type":"Point"}
}