{
  "type": "Feature",
  "properties": {
    "iso:country":"GB",
    "wof:name":"S75 2BW",
    "wof:placetype":"postalcode"
},
  "geometry": {"coordinates":[-1.49360967653725,53.55498111725464],"type":"Point"}
}