{
  "type": "Feature",
  "properties": {
    "iso:country": "GB",
    "wof:name": "TN12 8BB",
    "wof:placetype": "postalcode"
  },
  "geometry": {"coordinates":[0.444936,51.134552],"type":"Point"}
}
