{
  "type": "Feature",
  "properties": {
    "date:inception_lower": "1980-01-01",
    "date:inception_upper": "1980-01-01",
    "iso:country": "GB",
    "wof:name": "SW19 2PT",
    "wof:placetype": "postalcode"
  },
  "geometry": {"coordinates":[-0.173701,51.413152],"type":"Point"}
}
