{
  "type": "Feature",
  "properties": {
    "iso:country":"GB",
    "wof:name":"SW19 2PT",
    "wof:placetype":"postalcode"
},
  "geometry": {"coordinates":[-0.17372656625737,51.41315305264721],"type":"Point"}
}