{
  "type": "Feature",
  "properties": {
    "iso:country":"GB",
    "wof:name":"TS7 8JN",
    "wof:placetype":"postalcode"
},
  "geometry": {"coordinates":[-1.20810577283957,54.53125672586398],"type":"Point"}
}