{
  "type": "Feature",
  "properties": {
    "date:inception_lower": "1980-01-01",
    "date:inception_upper": "1980-01-01",
    "iso:country": "GB",
    "wof:name": "TS7 8JN",
    "wof:placetype": "postalcode"
  },
  "geometry": {"coordinates":[-1.208106,54.531257],"type":"Point"}
}
