{
  "type": "Feature",
  "properties": {
    "iso:country":"GB",
    "wof:name":"LU5 5ES",
    "wof:placetype":"postalcode"
},
  "geometry": {"coordinates":[-0.51937392455932,51.90495874892895],"type":"Point"}
}