{
  "type": "Feature",
  "properties": {
    "iso:country":"GB",
    "wof:name":"ST10 2HE",
    "wof:placetype":"postalcode"
},
  "geometry": {"coordinates":[-1.96555156970479,53.02175716622279],"type":"Point"}
}