{
  "type": "Feature",
  "properties": {
    "iso:country": "GB",
    "wof:name": "SG7 6HE",
    "wof:placetype": "postalcode"
  },
  "geometry": {"coordinates":[-0.190953,51.981116],"type":"Point"}
}
