{
  "type": "Feature",
  "properties": {
    "iso:country":"GB",
    "wof:name":"SG7 6HE",
    "wof:placetype":"postalcode"
},
  "geometry": {"coordinates":[-0.19102335378168,51.98111650490559],"type":"Point"}
}