{
  "type": "Feature",
  "properties": {
    "iso:country":"GB",
    "wof:name":"E1 3NL",
    "wof:placetype":"postalcode"
},
  "geometry": {"coordinates":[-0.03980761616238,51.51779576353078],"type":"Point"}
}