{
  "type": "Feature",
  "properties": {
    "iso:country":"GB",
    "wof:name":"SA13 1PZ",
    "wof:placetype":"postalcode"
},
  "geometry": {"coordinates":[-3.77234609078384,51.58607905806321],"type":"Point"}
}