{
  "type": "Feature",
  "properties": {
    "iso:country": "GB",
    "wof:name": "SA13 1PZ",
    "wof:placetype": "postalcode"
  },
  "geometry": {"coordinates":[-3.772362,51.586082],"type":"Point"}
}
