{
  "type": "Feature",
  "properties": {
    "date:inception_lower": "1980-01-01",
    "date:inception_upper": "1980-01-01",
    "iso:country": "GB",
    "wof:name": "NE34 7HF",
    "wof:placetype": "postalcode"
  },
  "geometry": {"coordinates":[-1.396813,54.982209],"type":"Point"}
}
