{
  "type": "Feature",
  "properties": {
    "iso:country":"GB",
    "wof:name":"TW3 2AT",
    "wof:placetype":"postalcode"
},
  "geometry": {"coordinates":[-0.3642216174505,51.4619086333206],"type":"Point"}
}