{
  "type": "Feature",
  "properties": {
    "date:inception_lower": "1998-06-01",
    "date:inception_upper": "1998-06-01",
    "iso:country": "GB",
    "wof:name": "RG22 5JW",
    "wof:placetype": "postalcode"
  },
  "geometry": {"coordinates":[-1.135394,51.250961],"type":"Point"}
}
