{
  "type": "Feature",
  "properties": {
    "date:inception_lower": "2021-12-01",
    "date:inception_upper": "2021-12-01",
    "iso:country": "GB",
    "wof:name": "MK11 4DZ",
    "wof:placetype": "postalcode"
  },
  "geometry": {"coordinates":[-0.83587,52.046468],"type":"Point"}
}
