{
  "type": "Feature",
  "properties": {
    "iso:country":"GB",
    "wof:name":"BB4 9NZ",
    "wof:placetype":"postalcode"
},
  "geometry": {"coordinates":[-2.25237319053052,53.71166798459503],"type":"Point"}
}