{
  "type": "Feature",
  "properties": {
    "iso:country":"GB",
    "wof:name":"S11 8RL",
    "wof:placetype":"postalcode"
},
  "geometry": {"coordinates":[-1.49884057225547,53.37002752324914],"type":"Point"}
}