{
  "type": "Feature",
  "properties": {
    "date:inception_lower":"1995-12-01",
    "date:inception_upper":"1995-12-31",
    "iso:country":"GB",
    "wof:name":"NR11 8LQ",
    "wof:placetype":"postalcode"
},
  "geometry": {"coordinates":[1.440308,52.873862],"type":"Point"}
}