{
  "type": "Feature",
  "properties": {
    "iso:country":"GB",
    "wof:name":"N17 6XB",
    "wof:placetype":"postalcode"
},
  "geometry": {"coordinates":[-0.07266467533416,51.59676409781323],"type":"Point"}
}