{
  "type": "Feature",
  "properties": {
    "iso:country": "GB",
    "wof:name": "N17 6XB",
    "wof:placetype": "postalcode"
  },
  "geometry": {"coordinates":[-0.072665,51.596764],"type":"Point"}
}
