{
  "type": "Feature",
  "properties": {
    "iso:country":"GB",
    "wof:name":"CR4 3RG",
    "wof:placetype":"postalcode"
},
  "geometry": {"coordinates":[-0.17126804110475,51.4142208061126],"type":"Point"}
}