{
  "type": "Feature",
  "properties": {
    "iso:country": "GB",
    "wof:name": "PO15 5NR",
    "wof:placetype": "postalcode"
  },
  "geometry": {"coordinates":[-1.22482,50.852454],"type":"Point"}
}
