{
  "type": "Feature",
  "properties": {
    "date:inception_lower": "1980-01-01",
    "date:inception_upper": "1980-01-01",
    "iso:country": "GB",
    "wof:name": "PO15 5NR",
    "wof:placetype": "postalcode"
  },
  "geometry": {"coordinates":[-1.22482,50.852454],"type":"Point"}
}
