{
  "type": "Feature",
  "properties": {
    "date:inception_lower": "2005-02-01",
    "date:inception_upper": "2005-02-01",
    "iso:country": "GB",
    "wof:name": "SN15 9SS",
    "wof:placetype": "postalcode"
  },
  "geometry": {"coordinates":[-2.115246,51.460931],"type":"Point"}
}
