{
  "type": "Feature",
  "properties": {
    "iso:country": "GB",
    "wof:name": "RG42 4SS",
    "wof:placetype": "postalcode"
  },
  "geometry": {"coordinates":[-0.752383,51.430389],"type":"Point"}
}
