{
  "type": "Feature",
  "properties": {
    "iso:country": "GB",
    "wof:name": "WS2 9TW",
    "wof:placetype": "postalcode"
  },
  "geometry": {"coordinates":[-2.001403,52.580154],"type":"Point"}
}
