{
  "type": "Feature",
  "properties": {
    "iso:country":"GB",
    "wof:name":"CO7 6HH",
    "wof:placetype":"postalcode"
},
  "geometry": {"coordinates":[0.99095588615318,51.95850973524808],"type":"Point"}
}