{
  "type": "Feature",
  "properties": {
    "date:inception_lower": "2017-07-01",
    "date:inception_upper": "2017-07-01",
    "iso:country": "GB",
    "wof:name": "M4 5BR",
    "wof:placetype": "postalcode"
  },
  "geometry": {"coordinates":[-2.230058,53.484658],"type":"Point"}
}
