{
  "type": "Feature",
  "properties": {
    "iso:country":"GB",
    "wof:name":"PE19 6NS",
    "wof:placetype":"postalcode"
},
  "geometry": {"coordinates":[-0.26441464936897,52.24658995474369],"type":"Point"}
}