{
  "type": "Feature",
  "properties": {
    "iso:country": "GB",
    "wof:name": "EX23 0DS",
    "wof:placetype": "postalcode"
  },
  "geometry": {"coordinates":[-4.541965,50.765792],"type":"Point"}
}
