{
  "type": "Feature",
  "properties": {
    "iso:country":"GB",
    "wof:name":"KY16 8NH",
    "wof:placetype":"postalcode"
},
  "geometry": {"coordinates":[-2.80467664134371,56.33129178236884],"type":"Point"}
}