{
  "type": "Feature",
  "properties": {
    "iso:country": "GB",
    "wof:name": "SG8 8ER",
    "wof:placetype": "postalcode"
  },
  "geometry": {"coordinates":[0.014632,51.997272],"type":"Point"}
}
