{
  "type": "Feature",
  "properties": {
    "iso:country":"GB",
    "wof:name":"SG8 8ER",
    "wof:placetype":"postalcode"
},
  "geometry": {"coordinates":[0.01463161410877,51.99727224598111],"type":"Point"}
}