{
  "type": "Feature",
  "properties": {
    "iso:country":"GB",
    "wof:name":"SG8 6AD",
    "wof:placetype":"postalcode"
},
  "geometry": {"coordinates":[0.01426650686374,52.08384427316948],"type":"Point"}
}