{
  "type": "Feature",
  "properties": {
    "date:inception_lower": "1980-01-01",
    "date:inception_upper": "1980-01-01",
    "iso:country": "GB",
    "wof:name": "SG8 6AD",
    "wof:placetype": "postalcode"
  },
  "geometry": {"coordinates":[0.014267,52.083844],"type":"Point"}
}
