{
  "type": "Feature",
  "properties": {
    "iso:country":"GB",
    "wof:name":"SE1 8JW",
    "wof:placetype":"postalcode"
},
  "geometry": {"coordinates":[-0.1062881877969,51.4999496592817],"type":"Point"}
}