{
  "type": "Feature",
  "properties": {
    "iso:country": "GB",
    "wof:name": "W5 1AY",
    "wof:placetype": "postalcode"
  },
  "geometry": {"coordinates":[-0.29571,51.531291],"type":"Point"}
}
