{
  "type": "Feature",
  "properties": {
    "iso:country": "GB",
    "wof:name": "KY15 5TX",
    "wof:placetype": "postalcode"
  },
  "geometry": {"coordinates":[-2.91451,56.312524],"type":"Point"}
}
