{
  "type": "Feature",
  "properties": {
    "date:inception_lower":"1980-01-01",
    "date:inception_upper":"1980-01-31",
    "iso:country":"GB",
    "wof:name":"WR9 7EE",
    "wof:placetype":"postalcode"
},
  "geometry": {"coordinates":[-2.069428,52.253818],"type":"Point"}
}