{
  "type": "Feature",
  "properties": {
    "iso:country":"GB",
    "wof:name":"SN25 3PP",
    "wof:placetype":"postalcode"
},
  "geometry": {"coordinates":[-1.80671554132593,51.58664611476169],"type":"Point"}
}