{
  "type": "Feature",
  "properties": {
    "iso:country": "GB",
    "wof:name": "DT11 9EE",
    "wof:placetype": "postalcode"
  },
  "geometry": {"coordinates":[-2.104201,50.812706],"type":"Point"}
}
