{
  "type": "Feature",
  "properties": {
    "iso:country":"GB",
    "wof:name":"DT11 9EE",
    "wof:placetype":"postalcode"
},
  "geometry": {"coordinates":[-2.10880276586123,50.81399662252532],"type":"Point"}
}