{
  "type": "Feature",
  "properties": {
    "iso:country": "GB",
    "wof:name": "LN11 8NP",
    "wof:placetype": "postalcode"
  },
  "geometry": {"coordinates":[0.02203,53.335925],"type":"Point"}
}
