{
  "type": "Feature",
  "properties": {
    "iso:country":"GB",
    "wof:name":"B50 4EF",
    "wof:placetype":"postalcode"
},
  "geometry": {"coordinates":[-1.85401194874203,52.16705833318011],"type":"Point"}
}