{
  "type": "Feature",
  "properties": {
    "date:inception_lower": "1987-04-01",
    "date:inception_upper": "1987-04-01",
    "iso:country": "GB",
    "wof:name": "B50 4EF",
    "wof:placetype": "postalcode"
  },
  "geometry": {"coordinates":[-1.854012,52.167058],"type":"Point"}
}
