{
  "type": "Feature",
  "properties": {
    "iso:country":"GB",
    "wof:name":"HR9 5QL",
    "wof:placetype":"postalcode"
},
  "geometry": {"coordinates":[-2.58826537542656,51.90877859725911],"type":"Point"}
}