{
  "type": "Feature",
  "properties": {
    "iso:country": "GB",
    "wof:name": "HR9 5QL",
    "wof:placetype": "postalcode"
  },
  "geometry": {"coordinates":[-2.588265,51.908779],"type":"Point"}
}
