{
  "type": "Feature",
  "properties": {
    "iso:country": "GB",
    "wof:name": "MK14 6HA",
    "wof:placetype": "postalcode"
  },
  "geometry": {"coordinates":[-0.749158,52.059936],"type":"Point"}
}
