{
  "type": "Feature",
  "properties": {
    "iso:country":"GB",
    "wof:name":"MK14 6HA",
    "wof:placetype":"postalcode"
},
  "geometry": {"coordinates":[-0.74915772689572,52.05993647482605],"type":"Point"}
}