{
  "type": "Feature",
  "properties": {
    "iso:country": "GB",
    "wof:name": "LE16 8QB",
    "wof:placetype": "postalcode"
  },
  "geometry": {"coordinates":[-0.804012,52.484384],"type":"Point"}
}
