{
  "type": "Feature",
  "properties": {
    "iso:country":"GB",
    "wof:name":"LE16 8QB",
    "wof:placetype":"postalcode"
},
  "geometry": {"coordinates":[-0.80401207323203,52.48438446408487],"type":"Point"}
}