{
  "type": "Feature",
  "properties": {
    "iso:country": "GB",
    "wof:name": "BH12 1DS",
    "wof:placetype": "postalcode"
  },
  "geometry": {"coordinates":[-1.916244,50.72714],"type":"Point"}
}
