{
  "type": "Feature",
  "properties": {
    "iso:country": "GB",
    "wof:name": "TF3 5AQ",
    "wof:placetype": "postalcode"
  },
  "geometry": {"coordinates":[-2.475022,52.685244],"type":"Point"}
}
