{
  "type": "Feature",
  "properties": {
    "date:inception_lower": "1980-01-01",
    "date:inception_upper": "1980-01-01",
    "iso:country": "GB",
    "wof:name": "TF3 5AQ",
    "wof:placetype": "postalcode"
  },
  "geometry": {"coordinates":[-2.475022,52.685244],"type":"Point"}
}
