{
  "type": "Feature",
  "properties": {
    "date:inception_lower": "1980-01-01",
    "date:inception_upper": "1980-01-01",
    "iso:country": "GB",
    "wof:name": "TF11 9DB",
    "wof:placetype": "postalcode"
  },
  "geometry": {"coordinates":[-2.337462,52.616279],"type":"Point"}
}
