{
  "type": "Feature",
  "properties": {
    "iso:country":"GB",
    "wof:name":"TF11 9DB",
    "wof:placetype":"postalcode"
},
  "geometry": {"coordinates":[-2.33746156172157,52.61627946656454],"type":"Point"}
}