{
  "type": "Feature",
  "properties": {
    "date:inception_lower":"1990-07-01",
    "date:inception_upper":"1990-07-31",
    "iso:country":"GB",
    "wof:name":"PL12 4UQ",
    "wof:placetype":"postalcode"
},
  "geometry": {"coordinates":[-4.239098,50.408113],"type":"Point"}
}