{
  "type": "Feature",
  "properties": {
    "iso:country":"GB",
    "wof:name":"CV12 9QT",
    "wof:placetype":"postalcode"
},
  "geometry": {"coordinates":[-1.42026871224803,52.48090760857429],"type":"Point"}
}