{
  "type": "Feature",
  "properties": {
    "iso:country":"GB",
    "wof:name":"E11 2DX",
    "wof:placetype":"postalcode"
},
  "geometry": {"coordinates":[0.029132717337,51.58261144029696],"type":"Point"}
}