{
  "type": "Feature",
  "properties": {
    "iso:country": "GB",
    "wof:name": "E11 2DX",
    "wof:placetype": "postalcode"
  },
  "geometry": {"coordinates":[0.029133,51.582611],"type":"Point"}
}
