{
  "type": "Feature",
  "properties": {
    "date:inception_lower": "1980-01-01",
    "date:inception_upper": "1980-01-01",
    "iso:country": "GB",
    "wof:name": "LA4 6ES",
    "wof:placetype": "postalcode"
  },
  "geometry": {"coordinates":[-2.837696,54.07589],"type":"Point"}
}
