{
  "type": "Feature",
  "properties": {
    "iso:country":"GB",
    "wof:name":"LA4 6ES",
    "wof:placetype":"postalcode"
},
  "geometry": {"coordinates":[-2.83769587967434,54.07588952765836],"type":"Point"}
}