{
  "type": "Feature",
  "properties": {
    "iso:country": "GB",
    "wof:name": "SP7 8JU",
    "wof:placetype": "postalcode"
  },
  "geometry": {"coordinates":[-2.197648,51.006281],"type":"Point"}
}
