{
  "type": "Feature",
  "properties": {
    "date:inception_lower":"1980-01-01",
    "date:inception_upper":"1980-01-31",
    "iso:country":"GB",
    "wof:name":"SP7 8JU",
    "wof:placetype":"postalcode"
},
  "geometry": {"coordinates":[-2.197648,51.006281],"type":"Point"}
}