{
  "type": "Feature",
  "properties": {
    "iso:country":"GB",
    "wof:name":"EH10 5QX",
    "wof:placetype":"postalcode"
},
  "geometry": {"coordinates":[-3.22179977973729,55.919993635571],"type":"Point"}
}