{
  "type": "Feature",
  "properties": {
    "iso:country": "GB",
    "wof:name": "EH10 5QX",
    "wof:placetype": "postalcode"
  },
  "geometry": {"coordinates":[-3.2218,55.919994],"type":"Point"}
}
