{
  "type": "Feature",
  "properties": {
    "iso:country":"GB",
    "wof:name":"RH5 5AE",
    "wof:placetype":"postalcode"
},
  "geometry": {"coordinates":[-0.2916493363926,51.16881138082221],"type":"Point"}
}