{
  "type": "Feature",
  "properties": {
    "iso:country":"GB",
    "wof:name":"CA21 2YX",
    "wof:placetype":"postalcode"
},
  "geometry": {"coordinates":[-3.51748036061299,54.4456797436901],"type":"Point"}
}