{
  "type": "Feature",
  "properties": {
    "date:inception_lower": "1990-02-01",
    "date:inception_upper": "1990-02-01",
    "iso:country": "GB",
    "wof:name": "CA21 2YX",
    "wof:placetype": "postalcode"
  },
  "geometry": {"coordinates":[-3.51748,54.44568],"type":"Point"}
}
