{
  "type": "Feature",
  "properties": {
    "iso:country": "GB",
    "wof:name": "CA21 2YX",
    "wof:placetype": "postalcode"
  },
  "geometry": {"coordinates":[-3.51748,54.44568],"type":"Point"}
}
