{
  "type": "Feature",
  "properties": {
    "date:inception_lower": "1980-01-01",
    "date:inception_upper": "1980-01-01",
    "iso:country": "GB",
    "wof:name": "DA7 6HQ",
    "wof:placetype": "postalcode"
  },
  "geometry": {"coordinates":[0.159551,51.464807],"type":"Point"}
}
