{
  "type": "Feature",
  "properties": {
    "iso:country":"GB",
    "wof:name":"BR6 0DB",
    "wof:placetype":"postalcode"
},
  "geometry": {"coordinates":[0.10142581480087,51.38192274263251],"type":"Point"}
}