{
  "type": "Feature",
  "properties": {
    "iso:country":"GB",
    "wof:name":"CV35 0TD",
    "wof:placetype":"postalcode"
},
  "geometry": {"coordinates":[-1.50756917988323,52.09075369762382],"type":"Point"}
}