{
  "type": "Feature",
  "properties": {
    "date:inception_lower": "2005-05-01",
    "date:inception_upper": "2005-05-01",
    "iso:country": "GB",
    "wof:name": "SP3 4SR",
    "wof:placetype": "postalcode"
  },
  "geometry": {"coordinates":[-1.891965,51.168392],"type":"Point"}
}
