{
  "type": "Feature",
  "properties": {
    "iso:country":"GB",
    "wof:name":"SP3 4SR",
    "wof:placetype":"postalcode"
},
  "geometry": {"coordinates":[-1.89196522978071,51.16839155065849],"type":"Point"}
}