{
  "type": "Feature",
  "properties": {
    "iso:country": "GB",
    "wof:name": "GL15 6HN",
    "wof:placetype": "postalcode"
  },
  "geometry": {"coordinates":[-2.583922,51.749775],"type":"Point"}
}
