{
  "type": "Feature",
  "properties": {
    "iso:country":"GB",
    "wof:name":"GL15 6HN",
    "wof:placetype":"postalcode"
},
  "geometry": {"coordinates":[-2.5839223726103,51.74977524435097],"type":"Point"}
}