{
  "type": "Feature",
  "properties": {
    "iso:country": "GB",
    "wof:name": "CV33 9QW",
    "wof:placetype": "postalcode"
  },
  "geometry": {"coordinates":[-1.549343,52.223926],"type":"Point"}
}
