{
  "type": "Feature",
  "properties": {
    "iso:country": "GB",
    "wof:name": "PE15 0SX",
    "wof:placetype": "postalcode"
  },
  "geometry": {"coordinates":[0.035441,52.492116],"type":"Point"}
}
