{
  "type": "Feature",
  "properties": {
    "iso:country":"GB",
    "wof:name":"PE15 0SX",
    "wof:placetype":"postalcode"
},
  "geometry": {"coordinates":[0.00666663791904,52.48788730025842],"type":"Point"}
}