{
  "type": "Feature",
  "properties": {
    "iso:country":"GB",
    "wof:name":"SE1 9AS",
    "wof:placetype":"postalcode"
},
  "geometry": {"coordinates":[-0.09573153228984,51.50744938081353],"type":"Point"}
}