{
  "type": "Feature",
  "properties": {
    "date:inception_lower": "1999-06-01",
    "date:inception_upper": "1999-06-01",
    "iso:country": "GB",
    "wof:name": "SE1 9AS",
    "wof:placetype": "postalcode"
  },
  "geometry": {"coordinates":[-0.095731,51.507449],"type":"Point"}
}
