{
  "type": "Feature",
  "properties": {
    "iso:country": "GB",
    "wof:name": "AB41 6RD",
    "wof:placetype": "postalcode"
  },
  "geometry": {"coordinates":[-2.109982,57.297292],"type":"Point"}
}
