{
  "type": "Feature",
  "properties": {
    "iso:country":"GB",
    "wof:name":"SG12 0RN",
    "wof:placetype":"postalcode"
},
  "geometry": {"coordinates":[-0.03154841833034,51.82135851883106],"type":"Point"}
}