{
  "type": "Feature",
  "properties": {
    "iso:country": "GB",
    "wof:name": "KT24 6BP",
    "wof:placetype": "postalcode"
  },
  "geometry": {"coordinates":[-0.454106,51.262416],"type":"Point"}
}
