{
  "type": "Feature",
  "properties": {
    "date:inception_lower": "1983-03-01",
    "date:inception_upper": "1983-03-01",
    "iso:country": "GB",
    "wof:name": "KT24 6BP",
    "wof:placetype": "postalcode"
  },
  "geometry": {"coordinates":[-0.453991,51.262432],"type":"Point"}
}
