{
  "type": "Feature",
  "properties": {
    "iso:country":"GB",
    "wof:name":"SR3 1RE",
    "wof:placetype":"postalcode"
},
  "geometry": {"coordinates":[-1.41936197753861,54.88567866289108],"type":"Point"}
}