{
  "type": "Feature",
  "properties": {
    "date:inception_lower": "1980-01-01",
    "date:inception_upper": "1980-01-01",
    "iso:country": "GB",
    "wof:name": "LN1 3LW",
    "wof:placetype": "postalcode"
  },
  "geometry": {"coordinates":[-0.54592,53.240066],"type":"Point"}
}
