{
  "type": "Feature",
  "properties": {
    "iso:country": "GB",
    "wof:name": "WA2 8JA",
    "wof:placetype": "postalcode"
  },
  "geometry": {"coordinates":[-2.60053,53.407382],"type":"Point"}
}
