{
  "type": "Feature",
  "properties": {
    "date:inception_lower": "2001-12-01",
    "date:inception_upper": "2001-12-01",
    "iso:country": "GB",
    "wof:name": "WA2 8JA",
    "wof:placetype": "postalcode"
  },
  "geometry": {"coordinates":[-2.60053,53.407382],"type":"Point"}
}
