{
  "type": "Feature",
  "properties": {
    "iso:country":"GB",
    "wof:name":"WA2 8JA",
    "wof:placetype":"postalcode"
},
  "geometry": {"coordinates":[-2.60053015873532,53.40738208000811],"type":"Point"}
}