{
  "type": "Feature",
  "properties": {
    "iso:country": "GB",
    "wof:name": "DL10 7QD",
    "wof:placetype": "postalcode"
  },
  "geometry": {"coordinates":[-1.628242,54.348557],"type":"Point"}
}
