{
  "type": "Feature",
  "properties": {
    "iso:country":"GB",
    "wof:name":"DL10 7QD",
    "wof:placetype":"postalcode"
},
  "geometry": {"coordinates":[-1.62824200460158,54.34855684136475],"type":"Point"}
}