{
  "type": "Feature",
  "properties": {
    "date:inception_lower": "2002-06-01",
    "date:inception_upper": "2002-06-01",
    "iso:country": "GB",
    "wof:name": "PR4 2HF",
    "wof:placetype": "postalcode"
  },
  "geometry": {"coordinates":[-2.885372,53.784873],"type":"Point"}
}
