{
  "type": "Feature",
  "properties": {
    "iso:country": "GB",
    "wof:name": "TD9 9PS",
    "wof:placetype": "postalcode"
  },
  "geometry": {"coordinates":[-2.769119,55.430424],"type":"Point"}
}
