{
  "type": "Feature",
  "properties": {
    "iso:country":"GB",
    "wof:name":"TD9 9PS",
    "wof:placetype":"postalcode"
},
  "geometry": {"coordinates":[-2.76911866370438,55.43042367253211],"type":"Point"}
}