{
  "type": "Feature",
  "properties": {
    "date:inception_lower":"1994-10-01",
    "date:inception_upper":"1994-10-31",
    "iso:country":"GB",
    "wof:name":"TD9 9PS",
    "wof:placetype":"postalcode"
},
  "geometry": {"coordinates":[-2.769119,55.430424],"type":"Point"}
}