{
  "type": "Feature",
  "properties": {
    "iso:country": "GB",
    "wof:name": "TN38 0BF",
    "wof:placetype": "postalcode"
  },
  "geometry": {"coordinates":[0.537631,50.853103],"type":"Point"}
}
