{
  "type": "Feature",
  "properties": {
    "date:inception_lower":"2015-02-01",
    "date:inception_upper":"2015-02-28",
    "iso:country":"GB",
    "wof:name":"TN38 0BF",
    "wof:placetype":"postalcode"
},
  "geometry": {"coordinates":[0.537631,50.853103],"type":"Point"}
}