{
  "type": "Feature",
  "properties": {
    "iso:country":"GB",
    "wof:name":"SP7 8ER",
    "wof:placetype":"postalcode"
},
  "geometry": {"coordinates":[-2.19044205434953,51.00417068046242],"type":"Point"}
}