{
  "type": "Feature",
  "properties": {
    "iso:country": "GB",
    "wof:name": "SP1 3YS",
    "wof:placetype": "postalcode"
  },
  "geometry": {"coordinates":[-1.808915,51.095264],"type":"Point"}
}
