{
  "type": "Feature",
  "properties": {
    "iso:country":"GB",
    "wof:name":"SP1 3YS",
    "wof:placetype":"postalcode"
},
  "geometry": {"coordinates":[-1.80904001121259,51.09519844325771],"type":"Point"}
}