{
  "type": "Feature",
  "properties": {
    "iso:country": "GB",
    "wof:name": "HR4 8BD",
    "wof:placetype": "postalcode"
  },
  "geometry": {"coordinates":[-2.734359,52.137332],"type":"Point"}
}
