{
  "type": "Feature",
  "properties": {
    "iso:country":"GB",
    "wof:name":"N18 2JQ",
    "wof:placetype":"postalcode"
},
  "geometry": {"coordinates":[-0.06099584269659,51.61309107112218],"type":"Point"}
}