{
  "type": "Feature",
  "properties": {
    "iso:country": "GB",
    "wof:name": "N18 2JQ",
    "wof:placetype": "postalcode"
  },
  "geometry": {"coordinates":[-0.060996,51.613091],"type":"Point"}
}
