{
  "type": "Feature",
  "properties": {
    "iso:country": "GB",
    "wof:name": "BD9 6SR",
    "wof:placetype": "postalcode"
  },
  "geometry": {"coordinates":[-1.810682,53.820342],"type":"Point"}
}
