{
  "type": "Feature",
  "properties": {
    "iso:country":"GB",
    "wof:name":"SO53 5PR",
    "wof:placetype":"postalcode"
},
  "geometry": {"coordinates":[-1.39589158124734,51.00280194033139],"type":"Point"}
}