{
  "type": "Feature",
  "properties": {
    "date:inception_lower": "1980-01-01",
    "date:inception_upper": "1980-01-01",
    "iso:country": "GB",
    "wof:name": "E17 3HY",
    "wof:placetype": "postalcode"
  },
  "geometry": {"coordinates":[-0.00521,51.590763],"type":"Point"}
}
