{
  "type": "Feature",
  "properties": {
    "iso:country": "GB",
    "wof:name": "CW2 7NP",
    "wof:placetype": "postalcode"
  },
  "geometry": {"coordinates":[-2.450907,53.087345],"type":"Point"}
}
