{
  "type": "Feature",
  "properties": {
    "iso:country":"GB",
    "wof:name":"CW2 7NP",
    "wof:placetype":"postalcode"
},
  "geometry": {"coordinates":[-2.45090753352958,53.08734527889855],"type":"Point"}
}