{
  "type": "Feature",
  "properties": {
    "date:inception_lower": "1995-07-01",
    "date:inception_upper": "1995-07-01",
    "iso:country": "GB",
    "wof:name": "CF81 9PW",
    "wof:placetype": "postalcode"
  },
  "geometry": {"coordinates":[-3.28145,51.747884],"type":"Point"}
}
