{
  "type": "Feature",
  "properties": {
    "iso:country":"GB",
    "wof:name":"LN6 7HE",
    "wof:placetype":"postalcode"
},
  "geometry": {"coordinates":[-0.58419350726916,53.20002834464712],"type":"Point"}
}