{
  "type": "Feature",
  "properties": {
    "iso:country": "GB",
    "wof:name": "HX3 7UP",
    "wof:placetype": "postalcode"
  },
  "geometry": {"coordinates":[-1.84032,53.740344],"type":"Point"}
}
