{
  "type": "Feature",
  "properties": {
    "iso:country":"GB",
    "wof:name":"LN5 9NQ",
    "wof:placetype":"postalcode"
},
  "geometry": {"coordinates":[-0.53391031636772,53.17005989993559],"type":"Point"}
}