{
  "type": "Feature",
  "properties": {
    "iso:country": "GB",
    "wof:name": "E8 2ET",
    "wof:placetype": "postalcode"
  },
  "geometry": {"coordinates":[-0.068497,51.552057],"type":"Point"}
}
