{
  "type": "Feature",
  "properties": {
    "iso:country":"GB",
    "wof:name":"PR1 8DN",
    "wof:placetype":"postalcode"
},
  "geometry": {"coordinates":[-2.71436528601801,53.75439393288978],"type":"Point"}
}