{
  "type": "Feature",
  "properties": {
    "iso:country": "GB",
    "wof:name": "PR1 8DN",
    "wof:placetype": "postalcode"
  },
  "geometry": {"coordinates":[-2.714363,53.754455],"type":"Point"}
}
