{
  "type": "Feature",
  "properties": {
    "iso:country":"GB",
    "wof:name":"MK14 7BF",
    "wof:placetype":"postalcode"
},
  "geometry": {"coordinates":[-0.75599640114441,52.04794275975343],"type":"Point"}
}