{
  "type": "Feature",
  "properties": {
    "iso:country": "GB",
    "wof:name": "MK14 7BF",
    "wof:placetype": "postalcode"
  },
  "geometry": {"coordinates":[-0.755996,52.047943],"type":"Point"}
}
