{
  "type": "Feature",
  "properties": {
    "iso:country": "GB",
    "wof:name": "OL12 8LP",
    "wof:placetype": "postalcode"
  },
  "geometry": {"coordinates":[-2.171295,53.669118],"type":"Point"}
}
