{
  "type": "Feature",
  "properties": {
    "iso:country":"GB",
    "wof:name":"OL12 8LP",
    "wof:placetype":"postalcode"
},
  "geometry": {"coordinates":[-2.17158259842903,53.669045572352],"type":"Point"}
}