{
  "type": "Feature",
  "properties": {
    "iso:country": "GB",
    "wof:name": "LL31 9JZ",
    "wof:placetype": "postalcode"
  },
  "geometry": {"coordinates":[-3.777668,53.29897],"type":"Point"}
}
