{
  "type": "Feature",
  "properties": {
    "iso:country":"GB",
    "wof:name":"TW2 7RE",
    "wof:placetype":"postalcode"
},
  "geometry": {"coordinates":[-0.34326788733543,51.45418673829662],"type":"Point"}
}