{
  "type": "Feature",
  "properties": {
    "date:inception_lower":"1980-01-01",
    "date:inception_upper":"1980-01-31",
    "iso:country":"GB",
    "wof:name":"BB9 6LB",
    "wof:placetype":"postalcode"
},
  "geometry": {"coordinates":[-2.226259,53.878897],"type":"Point"}
}