{
  "type": "Feature",
  "properties": {
    "iso:country":"GB",
    "wof:name":"BB9 6LB",
    "wof:placetype":"postalcode"
},
  "geometry": {"coordinates":[-2.22625873350367,53.87889663363448],"type":"Point"}
}