{
  "type": "Feature",
  "properties": {
    "iso:country":"GB",
    "wof:name":"CM17 9GQ",
    "wof:placetype":"postalcode"
},
  "geometry": {"coordinates":[0.14410237723709,51.77183149520826],"type":"Point"}
}