{
  "type": "Feature",
  "properties": {
    "date:inception_lower": "2014-12-01",
    "date:inception_upper": "2014-12-01",
    "iso:country": "GB",
    "wof:name": "CM17 9GQ",
    "wof:placetype": "postalcode"
  },
  "geometry": {"coordinates":[0.144102,51.771831],"type":"Point"}
}
