{
  "type": "Feature",
  "properties": {
    "iso:country":"GB",
    "wof:name":"NE28 8RX",
    "wof:placetype":"postalcode"
},
  "geometry": {"coordinates":[-1.53837779509406,54.99336002024183],"type":"Point"}
}