{
  "type": "Feature",
  "properties": {
    "iso:country": "GB",
    "wof:name": "HP14 3UB",
    "wof:placetype": "postalcode"
  },
  "geometry": {"coordinates":[-0.901908,51.658936],"type":"Point"}
}
