{
  "type": "Feature",
  "properties": {
    "iso:country":"GB",
    "wof:name":"TN2 5HU",
    "wof:placetype":"postalcode"
},
  "geometry": {"coordinates":[0.26809514773025,51.11469691488375],"type":"Point"}
}