{
  "type": "Feature",
  "properties": {
    "date:inception_lower":"1980-01-01",
    "date:inception_upper":"1980-01-31",
    "iso:country":"GB",
    "wof:name":"CF32 8TB",
    "wof:placetype":"postalcode"
},
  "geometry": {"coordinates":[-3.588112,51.567361],"type":"Point"}
}