{
  "type": "Feature",
  "properties": {
    "iso:country":"GB",
    "wof:name":"CF32 8TB",
    "wof:placetype":"postalcode"
},
  "geometry": {"coordinates":[-3.58811190664207,51.56736103701151],"type":"Point"}
}