{
  "type": "Feature",
  "properties": {
    "iso:country": "GB",
    "wof:name": "CF32 8TB",
    "wof:placetype": "postalcode"
  },
  "geometry": {"coordinates":[-3.588112,51.567361],"type":"Point"}
}
