{
  "type": "Feature",
  "properties": {
    "iso:country":"GB",
    "wof:name":"BD24 9DR",
    "wof:placetype":"postalcode"
},
  "geometry": {"coordinates":[-2.27630820701804,54.06842371415998],"type":"Point"}
}