{
  "type": "Feature",
  "properties": {
    "iso:country": "GB",
    "wof:name": "BD24 9DR",
    "wof:placetype": "postalcode"
  },
  "geometry": {"coordinates":[-2.276308,54.068424],"type":"Point"}
}
