{
  "type": "Feature",
  "properties": {
    "iso:country":"GB",
    "wof:name":"CA13 9UU",
    "wof:placetype":"postalcode"
},
  "geometry": {"coordinates":[-3.30287336840396,54.59329929823463],"type":"Point"}
}