{
  "type": "Feature",
  "properties": {
    "date:inception_lower": "1980-01-01",
    "date:inception_upper": "1980-01-01",
    "iso:country": "GB",
    "wof:name": "CA13 9UU",
    "wof:placetype": "postalcode"
  },
  "geometry": {"coordinates":[-3.302862,54.593307],"type":"Point"}
}
