{
  "type": "Feature",
  "properties": {
    "iso:country":"GB",
    "wof:name":"DD7 7JW",
    "wof:placetype":"postalcode"
},
  "geometry": {"coordinates":[-2.73288881065754,56.49744477103705],"type":"Point"}
}