{
  "type": "Feature",
  "properties": {
    "date:inception_lower":"1980-01-01",
    "date:inception_upper":"1980-01-31",
    "iso:country":"GB",
    "wof:name":"B94 6AU",
    "wof:placetype":"postalcode"
},
  "geometry": {"coordinates":[-1.745674,52.342219],"type":"Point"}
}