{
  "type": "Feature",
  "properties": {
    "iso:country":"GB",
    "wof:name":"B94 6AU",
    "wof:placetype":"postalcode"
},
  "geometry": {"coordinates":[-1.74568339885292,52.34220411001836],"type":"Point"}
}