{
  "type": "Feature",
  "properties": {
    "iso:country": "GB",
    "wof:name": "B94 6AU",
    "wof:placetype": "postalcode"
  },
  "geometry": {"coordinates":[-1.745674,52.342219],"type":"Point"}
}
