{
  "type": "Feature",
  "properties": {
    "iso:country": "GB",
    "wof:name": "CV4 7AQ",
    "wof:placetype": "postalcode"
  },
  "geometry": {"coordinates":[-1.555656,52.368712],"type":"Point"}
}
