{
  "type": "Feature",
  "properties": {
    "date:inception_lower":"1980-01-01",
    "date:inception_upper":"1980-01-31",
    "iso:country":"GB",
    "wof:name":"CV4 7AQ",
    "wof:placetype":"postalcode"
},
  "geometry": {"coordinates":[-1.555656,52.368712],"type":"Point"}
}