{
  "type": "Feature",
  "properties": {
    "iso:country":"GB",
    "wof:name":"SY23 5HN",
    "wof:placetype":"postalcode"
},
  "geometry": {"coordinates":[-4.17301493630996,52.28438663872841],"type":"Point"}
}