{
  "type": "Feature",
  "properties": {
    "iso:country":"GB",
    "wof:name":"IV1 1UF",
    "wof:placetype":"postalcode"
},
  "geometry": {"coordinates":[-4.20855566338385,57.48497181613784],"type":"Point"}
}