{
  "type": "Feature",
  "properties": {
    "iso:country": "GB",
    "wof:name": "ST19 5SF",
    "wof:placetype": "postalcode"
  },
  "geometry": {"coordinates":[-2.106592,52.72422],"type":"Point"}
}
