{
  "type": "Feature",
  "properties": {
    "date:inception_lower": "1985-10-01",
    "date:inception_upper": "1985-10-01",
    "iso:country": "GB",
    "wof:name": "ST19 5SF",
    "wof:placetype": "postalcode"
  },
  "geometry": {"coordinates":[-2.106592,52.72422],"type":"Point"}
}
