{
  "type": "Feature",
  "properties": {
    "iso:country":"GB",
    "wof:name":"ST19 5SF",
    "wof:placetype":"postalcode"
},
  "geometry": {"coordinates":[-2.10659183210652,52.72422013210036],"type":"Point"}
}