{
  "type": "Feature",
  "properties": {
    "iso:country":"GB",
    "wof:name":"TS3 8AR",
    "wof:placetype":"postalcode"
},
  "geometry": {"coordinates":[-1.20143343531144,54.57700216839623],"type":"Point"}
}