{
  "type": "Feature",
  "properties": {
    "iso:country": "GB",
    "wof:name": "PR3 2PF",
    "wof:placetype": "postalcode"
  },
  "geometry": {"coordinates":[-2.608213,53.835024],"type":"Point"}
}
