{
  "type": "Feature",
  "properties": {
    "iso:country":"GB",
    "wof:name":"CM11 2PJ",
    "wof:placetype":"postalcode"
},
  "geometry": {"coordinates":[0.43145760197496,51.61584667634695],"type":"Point"}
}