{
  "type": "Feature",
  "properties": {
    "date:inception_lower": "2008-03-01",
    "date:inception_upper": "2008-03-01",
    "iso:country": "GB",
    "wof:name": "AB42 4EG",
    "wof:placetype": "postalcode"
  },
  "geometry": {"coordinates":[-2.129572,57.521175],"type":"Point"}
}
