{
  "type": "Feature",
  "properties": {
    "date:inception_lower":"1980-01-01",
    "date:inception_upper":"1980-01-31",
    "iso:country":"GB",
    "wof:name":"EX36 3PW",
    "wof:placetype":"postalcode"
},
  "geometry": {"coordinates":[-3.658459,51.029575],"type":"Point"}
}