{
  "type": "Feature",
  "properties": {
    "iso:country":"GB",
    "wof:name":"EX36 3PW",
    "wof:placetype":"postalcode"
},
  "geometry": {"coordinates":[-3.65845916505749,51.02957470148083],"type":"Point"}
}