{
  "type": "Feature",
  "properties": {
    "iso:country": "GB",
    "wof:name": "HP11 1AF",
    "wof:placetype": "postalcode"
  },
  "geometry": {"coordinates":[-0.738146,51.625289],"type":"Point"}
}
