{
  "type": "Feature",
  "properties": {
    "date:inception_lower": "1990-02-01",
    "date:inception_upper": "1990-02-01",
    "iso:country": "GB",
    "wof:name": "HP11 1AF",
    "wof:placetype": "postalcode"
  },
  "geometry": {"coordinates":[-0.738146,51.625289],"type":"Point"}
}
