{
  "type": "Feature",
  "properties": {
    "iso:country": "GB",
    "wof:name": "BS24 9QP",
    "wof:placetype": "postalcode"
  },
  "geometry": {"coordinates":[-2.934629,51.325718],"type":"Point"}
}
