{
  "type": "Feature",
  "properties": {
    "iso:country":"GB",
    "wof:name":"BS24 9QP",
    "wof:placetype":"postalcode"
},
  "geometry": {"coordinates":[-2.93462876915939,51.32571834054644],"type":"Point"}
}