{
  "type": "Feature",
  "properties": {
    "date:inception_lower":"1980-01-01",
    "date:inception_upper":"1980-01-31",
    "iso:country":"GB",
    "wof:name":"CH4 0QP",
    "wof:placetype":"postalcode"
},
  "geometry": {"coordinates":[-2.98915,53.164093],"type":"Point"}
}