{
  "type": "Feature",
  "properties": {
    "iso:country":"GB",
    "wof:name":"CH4 0QP",
    "wof:placetype":"postalcode"
},
  "geometry": {"coordinates":[-2.98915000083831,53.16409302641565],"type":"Point"}
}