{
  "type": "Feature",
  "properties": {
    "iso:country":"GB",
    "wof:name":"ME9 9JE",
    "wof:placetype":"postalcode"
},
  "geometry": {"coordinates":[0.81181631611977,51.3249029176835],"type":"Point"}
}