{
  "type": "Feature",
  "properties": {
    "iso:country": "GB",
    "wof:name": "ME9 9JE",
    "wof:placetype": "postalcode"
  },
  "geometry": {"coordinates":[0.811816,51.324903],"type":"Point"}
}
