{
  "type": "Feature",
  "properties": {
    "date:inception_lower":"2016-10-01",
    "date:inception_upper":"2016-10-31",
    "iso:country":"GB",
    "wof:name":"CR4 4JA",
    "wof:placetype":"postalcode"
},
  "geometry": {"coordinates":[-0.157858,51.397653],"type":"Point"}
}