{
  "type": "Feature",
  "properties": {
    "iso:country":"GB",
    "wof:name":"DG9 7DR",
    "wof:placetype":"postalcode"
},
  "geometry": {"coordinates":[-5.02396035025883,54.90090822352067],"type":"Point"}
}