{
  "type": "Feature",
  "properties": {
    "iso:country": "GB",
    "wof:name": "OL10 1FZ",
    "wof:placetype": "postalcode"
  },
  "geometry": {"coordinates":[-2.221732,53.592849],"type":"Point"}
}
