{
  "type": "Feature",
  "properties": {
    "iso:country": "GB",
    "wof:name": "OL10 1FZ",
    "wof:placetype": "postalcode"
  },
  "geometry": {"coordinates":[-2.221673,53.593047],"type":"Point"}
}
