{
  "type": "Feature",
  "properties": {
    "iso:country": "GB",
    "wof:name": "BN2 5JS",
    "wof:placetype": "postalcode"
  },
  "geometry": {"coordinates":[-0.108373,50.81859],"type":"Point"}
}
