{
  "type": "Feature",
  "properties": {
    "iso:country":"GB",
    "wof:name":"EH51 9BQ",
    "wof:placetype":"postalcode"
},
  "geometry": {"coordinates":[-3.60309831060756,56.0125255014687],"type":"Point"}
}