{
  "type": "Feature",
  "properties": {
    "iso:country":"GB",
    "wof:name":"SO40 9HD",
    "wof:placetype":"postalcode"
},
  "geometry": {"coordinates":[-1.48280966401564,50.91200013469567],"type":"Point"}
}