{
  "type": "Feature",
  "properties": {
    "date:inception_lower": "1994-05-01",
    "date:inception_upper": "1994-05-01",
    "iso:country": "GB",
    "wof:name": "M45 7NY",
    "wof:placetype": "postalcode"
  },
  "geometry": {"coordinates":[-2.29484,53.547246],"type":"Point"}
}
