{
  "type": "Feature",
  "properties": {
    "iso:country":"GB",
    "wof:name":"N14 4JH",
    "wof:placetype":"postalcode"
},
  "geometry": {"coordinates":[-0.12794381789868,51.63657785023225],"type":"Point"}
}