{
  "type": "Feature",
  "properties": {
    "date:inception_lower": "1996-06-01",
    "date:inception_upper": "1996-06-01",
    "iso:country": "GB",
    "wof:name": "LS15 9JD",
    "wof:placetype": "postalcode"
  },
  "geometry": {"coordinates":[-1.434187,53.791906],"type":"Point"}
}
