{
  "type": "Feature",
  "properties": {
    "date:inception_lower":"1980-01-01",
    "date:inception_upper":"1980-01-31",
    "iso:country":"GB",
    "wof:name":"NP7 6ND",
    "wof:placetype":"postalcode"
},
  "geometry": {"coordinates":[-3.00627,51.837046],"type":"Point"}
}