{
  "type": "Feature",
  "properties": {
    "iso:country":"GB",
    "wof:name":"NP7 6ND",
    "wof:placetype":"postalcode"
},
  "geometry": {"coordinates":[-3.00627049734593,51.83704638688778],"type":"Point"}
}