{
  "type": "Feature",
  "properties": {
    "iso:country": "GB",
    "wof:name": "DA1 1QG",
    "wof:placetype": "postalcode"
  },
  "geometry": {"coordinates":[0.236925,51.433894],"type":"Point"}
}
