{
  "type": "Feature",
  "properties": {
    "iso:country":"GB",
    "wof:name":"DA1 1QG",
    "wof:placetype":"postalcode"
},
  "geometry": {"coordinates":[0.23692461661571,51.43389405162165],"type":"Point"}
}