{
  "type": "Feature",
  "properties": {
    "date:inception_lower":"1990-07-01",
    "date:inception_upper":"1990-07-31",
    "iso:country":"GB",
    "wof:name":"DA1 1QG",
    "wof:placetype":"postalcode"
},
  "geometry": {"coordinates":[0.236925,51.433894],"type":"Point"}
}