{
  "type": "Feature",
  "properties": {
    "iso:country":"GB",
    "wof:name":"NP16 5HQ",
    "wof:placetype":"postalcode"
},
  "geometry": {"coordinates":[-2.67172653061626,51.64471022700374],"type":"Point"}
}