{
  "type": "Feature",
  "properties": {
    "iso:country": "GB",
    "wof:name": "NP16 5HQ",
    "wof:placetype": "postalcode"
  },
  "geometry": {"coordinates":[-2.671726,51.64471],"type":"Point"}
}
