{
  "type": "Feature",
  "properties": {
    "iso:country": "GB",
    "wof:name": "W3 8SU",
    "wof:placetype": "postalcode"
  },
  "geometry": {"coordinates":[-0.277456,51.500782],"type":"Point"}
}
