{
  "type": "Feature",
  "properties": {
    "iso:country":"GB",
    "wof:name":"CT3 2LX",
    "wof:placetype":"postalcode"
},
  "geometry": {"coordinates":[1.27364023842031,51.29954701341332],"type":"Point"}
}