{
  "type": "Feature",
  "properties": {
    "date:inception_lower": "1980-01-01",
    "date:inception_upper": "1980-01-01",
    "iso:country": "GB",
    "wof:name": "BA2 6ST",
    "wof:placetype": "postalcode"
  },
  "geometry": {"coordinates":[-2.327312,51.394667],"type":"Point"}
}
