{
  "type": "Feature",
  "properties": {
    "iso:country":"GB",
    "wof:name":"BA2 6ST",
    "wof:placetype":"postalcode"
},
  "geometry": {"coordinates":[-2.32731185128555,51.39466669337711],"type":"Point"}
}