{
  "type": "Feature",
  "properties": {
    "iso:country": "GB",
    "wof:name": "ST18 9FH",
    "wof:placetype": "postalcode"
  },
  "geometry": {"coordinates":[-2.101953,52.856691],"type":"Point"}
}
