{
  "type": "Feature",
  "properties": {
    "date:inception_lower": "2017-11-01",
    "date:inception_upper": "2017-11-01",
    "iso:country": "GB",
    "wof:name": "ST18 9FH",
    "wof:placetype": "postalcode"
  },
  "geometry": {"coordinates":[-2.102058,52.856997],"type":"Point"}
}
