{
  "type": "Feature",
  "properties": {
    "iso:country":"GB",
    "wof:name":"B19 1RJ",
    "wof:placetype":"postalcode"
},
  "geometry": {"coordinates":[-1.91368653335634,52.50324188097853],"type":"Point"}
}