{
  "type": "Feature",
  "properties": {
    "iso:country":"GB",
    "wof:name":"KA15 1JX",
    "wof:placetype":"postalcode"
},
  "geometry": {"coordinates":[-4.62118138636916,55.73754610100308],"type":"Point"}
}