{
  "type": "Feature",
  "properties": {
    "date:inception_lower":"2014-12-01",
    "date:inception_upper":"2014-12-31",
    "iso:country":"GB",
    "wof:name":"PO13 9FU",
    "wof:placetype":"postalcode"
},
  "geometry": {"coordinates":[-1.194498,50.812572],"type":"Point"}
}