{
  "type": "Feature",
  "properties": {
    "iso:country": "GB",
    "wof:name": "PO13 9FU",
    "wof:placetype": "postalcode"
  },
  "geometry": {"coordinates":[-1.194498,50.812572],"type":"Point"}
}
