{
  "type": "Feature",
  "properties": {
    "date:inception_lower": "1980-01-01",
    "date:inception_upper": "1980-01-01",
    "iso:country": "GB",
    "wof:name": "SA43 2QW",
    "wof:placetype": "postalcode"
  },
  "geometry": {"coordinates":[-4.577143,52.061765],"type":"Point"}
}
