{
  "type": "Feature",
  "properties": {
    "iso:country": "GB",
    "wof:name": "SA43 2QW",
    "wof:placetype": "postalcode"
  },
  "geometry": {"coordinates":[-4.577143,52.061765],"type":"Point"}
}
