{
  "type": "Feature",
  "properties": {
    "iso:country":"GB",
    "wof:name":"SA43 2QW",
    "wof:placetype":"postalcode"
},
  "geometry": {"coordinates":[-4.5762207931962,52.06184314328332],"type":"Point"}
}