{
  "type": "Feature",
  "properties": {
    "iso:country":"GB",
    "wof:name":"WA16 6JS",
    "wof:placetype":"postalcode"
},
  "geometry": {"coordinates":[-2.34188724625751,53.32271433970645],"type":"Point"}
}