{
  "type": "Feature",
  "properties": {
    "date:inception_lower": "1980-01-01",
    "date:inception_upper": "1980-01-01",
    "iso:country": "GB",
    "wof:name": "SY22 6AP",
    "wof:placetype": "postalcode"
  },
  "geometry": {"coordinates":[-3.15777,52.775224],"type":"Point"}
}
