{
  "type": "Feature",
  "properties": {
    "iso:country":"GB",
    "wof:name":"SY22 6AP",
    "wof:placetype":"postalcode"
},
  "geometry": {"coordinates":[-3.15776956757088,52.77522410729289],"type":"Point"}
}