{
  "type": "Feature",
  "properties": {
    "iso:country":"GB",
    "wof:name":"L32 7QT",
    "wof:placetype":"postalcode"
},
  "geometry": {"coordinates":[-2.87906701900052,53.46672586045153],"type":"Point"}
}