{
  "type": "Feature",
  "properties": {
    "iso:country":"GB",
    "wof:name":"WF16 0DZ",
    "wof:placetype":"postalcode"
},
  "geometry": {"coordinates":[-1.66412432942807,53.70882178558001],"type":"Point"}
}