{
  "type": "Feature",
  "properties": {
    "date:inception_lower": "2017-12-01",
    "date:inception_upper": "2017-12-01",
    "iso:country": "GB",
    "wof:name": "NG5 2BF",
    "wof:placetype": "postalcode"
  },
  "geometry": {"coordinates":[-1.154091,52.972876],"type":"Point"}
}
