{
  "type": "Feature",
  "properties": {
    "iso:country":"GB",
    "wof:name":"SL2 1NJ",
    "wof:placetype":"postalcode"
},
  "geometry": {"coordinates":[-0.60718050076698,51.52871006099402],"type":"Point"}
}