{
  "type": "Feature",
  "properties": {
    "iso:country":"GB",
    "wof:name":"SW15 1PD",
    "wof:placetype":"postalcode"
},
  "geometry": {"coordinates":[-0.21983552236676,51.46371703824248],"type":"Point"}
}