{
  "type": "Feature",
  "properties": {
    "iso:country":"GB",
    "wof:name":"LE2 7TR",
    "wof:placetype":"postalcode"
},
  "geometry": {"coordinates":[-1.13415348762442,52.62403598935762],"type":"Point"}
}