{
  "type": "Feature",
  "properties": {
    "iso:country": "GB",
    "wof:name": "OX14 5TW",
    "wof:placetype": "postalcode"
  },
  "geometry": {"coordinates":[-1.282759,51.657266],"type":"Point"}
}
