{
  "type": "Feature",
  "properties": {
    "iso:country":"GB",
    "wof:name":"OX14 5TW",
    "wof:placetype":"postalcode"
},
  "geometry": {"coordinates":[-1.2827587151335,51.65726592266999],"type":"Point"}
}