{
  "type": "Feature",
  "properties": {
    "iso:country":"GB",
    "wof:name":"B26 1RN",
    "wof:placetype":"postalcode"
},
  "geometry": {"coordinates":[-1.79790197258927,52.46610734388134],"type":"Point"}
}