{
  "type": "Feature",
  "properties": {
    "iso:country": "GB",
    "wof:name": "B26 1RN",
    "wof:placetype": "postalcode"
  },
  "geometry": {"coordinates":[-1.797902,52.466107],"type":"Point"}
}
