{
  "type": "Feature",
  "properties": {
    "iso:country":"GB",
    "wof:name":"SK2 6JA",
    "wof:placetype":"postalcode"
},
  "geometry": {"coordinates":[-2.15254723008729,53.39382959252705],"type":"Point"}
}