{
  "type": "Feature",
  "properties": {
    "iso:country": "GB",
    "wof:name": "CW11 3FT",
    "wof:placetype": "postalcode"
  },
  "geometry": {"coordinates":[-2.392578,53.14848],"type":"Point"}
}
