{
  "type": "Feature",
  "properties": {
    "iso:country":"GB",
    "wof:name":"YO43 3JX",
    "wof:placetype":"postalcode"
},
  "geometry": {"coordinates":[-0.65979360332939,53.86532106982395],"type":"Point"}
}