{
  "type": "Feature",
  "properties": {
    "iso:country":"GB",
    "wof:name":"CM24 8JW",
    "wof:placetype":"postalcode"
},
  "geometry": {"coordinates":[0.1903358690183,51.90510193435304],"type":"Point"}
}