{
  "type": "Feature",
  "properties": {
    "iso:country": "GB",
    "wof:name": "CM24 8JW",
    "wof:placetype": "postalcode"
  },
  "geometry": {"coordinates":[0.190336,51.905102],"type":"Point"}
}
