{
  "type": "Feature",
  "properties": {
    "date:inception_lower": "1980-01-01",
    "date:inception_upper": "1980-01-01",
    "iso:country": "GB",
    "wof:name": "WF12 0JZ",
    "wof:placetype": "postalcode"
  },
  "geometry": {"coordinates":[-1.617065,53.664609],"type":"Point"}
}
