{
  "type": "Feature",
  "properties": {
    "iso:country":"GB",
    "wof:name":"WF12 0JZ",
    "wof:placetype":"postalcode"
},
  "geometry": {"coordinates":[-1.61706137250553,53.66459367720075],"type":"Point"}
}