{
  "type": "Feature",
  "properties": {
    "iso:country":"GB",
    "wof:name":"SW9 6UR",
    "wof:placetype":"postalcode"
},
  "geometry": {"coordinates":[-0.10219352050242,51.47712323547212],"type":"Point"}
}