{
  "type": "Feature",
  "properties": {
    "date:inception_lower": "2000-06-01",
    "date:inception_upper": "2000-06-01",
    "iso:country": "GB",
    "wof:name": "SW9 6UR",
    "wof:placetype": "postalcode"
  },
  "geometry": {"coordinates":[-0.102193,51.477123],"type":"Point"}
}
