{
  "type": "Feature",
  "properties": {
    "iso:country":"GB",
    "wof:name":"S73 0UX",
    "wof:placetype":"postalcode"
},
  "geometry": {"coordinates":[-1.37354193094888,53.51531277076206],"type":"Point"}
}