{
  "type": "Feature",
  "properties": {
    "date:inception_lower": "2005-10-01",
    "date:inception_upper": "2005-10-01",
    "iso:country": "GB",
    "wof:name": "S73 0UX",
    "wof:placetype": "postalcode"
  },
  "geometry": {"coordinates":[-1.373542,53.515313],"type":"Point"}
}
