{
  "type": "Feature",
  "properties": {
    "iso:country":"GB",
    "wof:name":"EH7 5DR",
    "wof:placetype":"postalcode"
},
  "geometry": {"coordinates":[-3.17101776708399,55.95737233234249],"type":"Point"}
}