{
  "type": "Feature",
  "properties": {
    "iso:country": "GB",
    "wof:name": "M26 3XZ",
    "wof:placetype": "postalcode"
  },
  "geometry": {"coordinates":[-2.365121,53.571179],"type":"Point"}
}
