{
  "type": "Feature",
  "properties": {
    "iso:country":"GB",
    "wof:name":"SY20 9QG",
    "wof:placetype":"postalcode"
},
  "geometry": {"coordinates":[-3.71752528315065,52.67995290424159],"type":"Point"}
}