{
  "type": "Feature",
  "properties": {
    "date:inception_lower":"2015-12-01",
    "date:inception_upper":"2015-12-31",
    "iso:country":"GB",
    "wof:name":"EH23 4GR",
    "wof:placetype":"postalcode"
},
  "geometry": {"coordinates":[-3.041079,55.845858],"type":"Point"}
}