{
  "type": "Feature",
  "properties": {
    "date:inception_lower": "1980-01-01",
    "date:inception_upper": "1980-01-01",
    "iso:country": "GB",
    "wof:name": "HP12 4DH",
    "wof:placetype": "postalcode"
  },
  "geometry": {"coordinates":[-0.785901,51.635774],"type":"Point"}
}
