{
  "type": "Feature",
  "properties": {
    "date:inception_lower": "2015-12-01",
    "date:inception_upper": "2015-12-01",
    "iso:country": "GB",
    "wof:name": "MK43 0WA",
    "wof:placetype": "postalcode"
  },
  "geometry": {"coordinates":[-0.556307,52.039841],"type":"Point"}
}
