{
  "type": "Feature",
  "properties": {
    "iso:country":"GB",
    "wof:name":"MK43 0WA",
    "wof:placetype":"postalcode"
},
  "geometry": {"coordinates":[-0.5563581660653,52.03984893043285],"type":"Point"}
}