{
  "type": "Feature",
  "properties": {
    "iso:country":"GB",
    "wof:name":"CF48 2RL",
    "wof:placetype":"postalcode"
},
  "geometry": {"coordinates":[-3.40324579604134,51.76035363267505],"type":"Point"}
}