{
  "type": "Feature",
  "properties": {
    "iso:country": "GB",
    "wof:name": "CF48 2RL",
    "wof:placetype": "postalcode"
  },
  "geometry": {"coordinates":[-3.403246,51.760354],"type":"Point"}
}
