{
  "type": "Feature",
  "properties": {
    "date:inception_lower": "1980-01-01",
    "date:inception_upper": "1980-01-01",
    "iso:country": "GB",
    "wof:name": "SY6 6QP",
    "wof:placetype": "postalcode"
  },
  "geometry": {"coordinates":[-2.785274,52.508191],"type":"Point"}
}
