{
  "type": "Feature",
  "properties": {
    "iso:country":"GB",
    "wof:name":"BD16 1DH",
    "wof:placetype":"postalcode"
},
  "geometry": {"coordinates":[-1.8858198956008,53.83959956374368],"type":"Point"}
}