{
  "type": "Feature",
  "properties": {
    "iso:country":"GB",
    "wof:name":"M17 1FR",
    "wof:placetype":"postalcode"
},
  "geometry": {"coordinates":[-2.32146155032365,53.4751189341922],"type":"Point"}
}