{
  "type": "Feature",
  "properties": {
    "date:inception_lower": "2008-09-01",
    "date:inception_upper": "2008-09-01",
    "iso:country": "GB",
    "wof:name": "BH10 4GE",
    "wof:placetype": "postalcode"
  },
  "geometry": {"coordinates":[-1.900621,50.752065],"type":"Point"}
}
