{
  "type": "Feature",
  "properties": {
    "iso:country": "GB",
    "wof:name": "BH10 4GE",
    "wof:placetype": "postalcode"
  },
  "geometry": {"coordinates":[-1.900621,50.752065],"type":"Point"}
}
