{
  "type": "Feature",
  "properties": {
    "date:inception_lower": "1980-01-01",
    "date:inception_upper": "1980-01-01",
    "iso:country": "GB",
    "wof:name": "CH4 0JQ",
    "wof:placetype": "postalcode"
  },
  "geometry": {"coordinates":[-3.043225,53.151847],"type":"Point"}
}
