{
  "type": "Feature",
  "properties": {
    "iso:country":"GB",
    "wof:name":"CH4 0JQ",
    "wof:placetype":"postalcode"
},
  "geometry": {"coordinates":[-3.04322462266971,53.15184652911843],"type":"Point"}
}