{
  "type": "Feature",
  "properties": {
    "iso:country":"GB",
    "wof:name":"SG4 9RG",
    "wof:placetype":"postalcode"
},
  "geometry": {"coordinates":[-0.26909971681515,51.95059414395666],"type":"Point"}
}