{
  "type": "Feature",
  "properties": {
    "date:inception_lower":"1993-01-01",
    "date:inception_upper":"1993-01-31",
    "iso:country":"GB",
    "wof:name":"SA6 8JG",
    "wof:placetype":"postalcode"
},
  "geometry": {"coordinates":[-3.925175,51.654024],"type":"Point"}
}