{
  "type": "Feature",
  "properties": {
    "iso:country": "GB",
    "wof:name": "RH10 7XZ",
    "wof:placetype": "postalcode"
  },
  "geometry": {"coordinates":[-0.144687,51.113217],"type":"Point"}
}
