{
  "type": "Feature",
  "properties": {
    "date:inception_lower": "2010-08-01",
    "date:inception_upper": "2010-08-01",
    "iso:country": "GB",
    "wof:name": "RH10 7XZ",
    "wof:placetype": "postalcode"
  },
  "geometry": {"coordinates":[-0.144687,51.113217],"type":"Point"}
}
