{
  "type": "Feature",
  "properties": {
    "iso:country":"GB",
    "wof:name":"IP18 6XW",
    "wof:placetype":"postalcode"
},
  "geometry": {"coordinates":[1.66448900925587,52.33646749343381],"type":"Point"}
}