{
  "type": "Feature",
  "properties": {
    "date:inception_lower": "1981-06-01",
    "date:inception_upper": "1981-06-01",
    "iso:country": "GB",
    "wof:name": "IP18 6XW",
    "wof:placetype": "postalcode"
  },
  "geometry": {"coordinates":[1.664489,52.336467],"type":"Point"}
}
