{
  "type": "Feature",
  "properties": {
    "iso:country": "GB",
    "wof:name": "IP8 4LE",
    "wof:placetype": "postalcode"
  },
  "geometry": {"coordinates":[1.041613,52.08217],"type":"Point"}
}
