{
  "type": "Feature",
  "properties": {
    "date:inception_lower": "2002-12-01",
    "date:inception_upper": "2002-12-01",
    "iso:country": "GB",
    "wof:name": "CO15 6PE",
    "wof:placetype": "postalcode"
  },
  "geometry": {"coordinates":[1.180157,51.803273],"type":"Point"}
}
