{
  "type": "Feature",
  "properties": {
    "iso:country":"GB",
    "wof:name":"CO15 6PE",
    "wof:placetype":"postalcode"
},
  "geometry": {"coordinates":[1.180156974715,51.80327301506691],"type":"Point"}
}