{
  "type": "Feature",
  "properties": {
    "iso:country":"GB",
    "wof:name":"M46 0GQ",
    "wof:placetype":"postalcode"
},
  "geometry": {"coordinates":[-2.49236681592193,53.52383858433706],"type":"Point"}
}