{
  "type": "Feature",
  "properties": {
    "iso:country":"GB",
    "wof:name":"TN16 9DQ",
    "wof:placetype":"postalcode"
},
  "geometry": {"coordinates":[0.03371725784737,51.31432172265186],"type":"Point"}
}