{
  "type": "Feature",
  "properties": {
    "iso:country": "GB",
    "wof:name": "NN15 7HQ",
    "wof:placetype": "postalcode"
  },
  "geometry": {"coordinates":[-0.72818,52.395681],"type":"Point"}
}
