{
  "type": "Feature",
  "properties": {
    "iso:country":"GB",
    "wof:name":"HU13 9JZ",
    "wof:placetype":"postalcode"
},
  "geometry": {"coordinates":[-0.43195035070261,53.72374380116617],"type":"Point"}
}