{
  "type": "Feature",
  "properties": {
    "iso:country": "GB",
    "wof:name": "NE23 8BW",
    "wof:placetype": "postalcode"
  },
  "geometry": {"coordinates":[-1.625338,55.082601],"type":"Point"}
}
