{
  "type": "Feature",
  "properties": {
    "date:inception_lower": "1980-01-01",
    "date:inception_upper": "1980-01-01",
    "iso:country": "GB",
    "wof:name": "DE14 2DS",
    "wof:placetype": "postalcode"
  },
  "geometry": {"coordinates":[-1.647455,52.805721],"type":"Point"}
}
