{
  "type": "Feature",
  "properties": {
    "iso:country":"GB",
    "wof:name":"DE14 2DS",
    "wof:placetype":"postalcode"
},
  "geometry": {"coordinates":[-1.6474298814894,52.80572983346307],"type":"Point"}
}