{
  "type": "Feature",
  "properties": {
    "iso:country":"GB",
    "wof:name":"DE6 5HX",
    "wof:placetype":"postalcode"
},
  "geometry": {"coordinates":[-1.78727683856732,52.89545323303075],"type":"Point"}
}