{
  "type": "Feature",
  "properties": {
    "iso:country": "GB",
    "wof:name": "DE6 5HX",
    "wof:placetype": "postalcode"
  },
  "geometry": {"coordinates":[-1.787277,52.895453],"type":"Point"}
}
