{
  "type": "Feature",
  "properties": {
    "iso:country": "GB",
    "wof:name": "BA2 8EJ",
    "wof:placetype": "postalcode"
  },
  "geometry": {"coordinates":[-2.417698,51.318219],"type":"Point"}
}
