{
  "type": "Feature",
  "properties": {
    "iso:country": "GB",
    "wof:name": "OX13 5QP",
    "wof:placetype": "postalcode"
  },
  "geometry": {"coordinates":[-1.396821,51.697352],"type":"Point"}
}
