{
  "type": "Feature",
  "properties": {
    "iso:country":"GB",
    "wof:name":"GL53 7EA",
    "wof:placetype":"postalcode"
},
  "geometry": {"coordinates":[-2.07721490779907,51.88321591915676],"type":"Point"}
}