{
  "type": "Feature",
  "properties": {
    "iso:country":"GB",
    "wof:name":"EX32 9EP",
    "wof:placetype":"postalcode"
},
  "geometry": {"coordinates":[-4.04334221640763,51.06838871525858],"type":"Point"}
}