{
  "type": "Feature",
  "properties": {
    "iso:country":"GB",
    "wof:name":"RG12 7FD",
    "wof:placetype":"postalcode"
},
  "geometry": {"coordinates":[-0.74336729515809,51.39249016475496],"type":"Point"}
}