{
  "type": "Feature",
  "properties": {
    "date:inception_lower":"2000-06-01",
    "date:inception_upper":"2000-06-30",
    "iso:country":"GB",
    "wof:name":"PE19 5EX",
    "wof:placetype":"postalcode"
},
  "geometry": {"coordinates":[-0.348718,52.285046],"type":"Point"}
}