{
  "type": "Feature",
  "properties": {
    "date:inception_lower": "1993-01-01",
    "date:inception_upper": "1993-01-01",
    "iso:country": "GB",
    "wof:name": "TF3 2JY",
    "wof:placetype": "postalcode"
  },
  "geometry": {"coordinates":[-2.457073,52.673449],"type":"Point"}
}
