{
  "type": "Feature",
  "properties": {
    "iso:country":"GB",
    "wof:name":"TF3 2JY",
    "wof:placetype":"postalcode"
},
  "geometry": {"coordinates":[-2.45707313313985,52.67344865878509],"type":"Point"}
}