{
  "type": "Feature",
  "properties": {
    "iso:country":"GB",
    "wof:name":"BL4 9XX",
    "wof:placetype":"postalcode"
},
  "geometry": {"coordinates":[-2.39276986158264,53.53858891187306],"type":"Point"}
}