{
  "type": "Feature",
  "properties": {
    "iso:country": "GB",
    "wof:name": "BL4 9XX",
    "wof:placetype": "postalcode"
  },
  "geometry": {"coordinates":[-2.39277,53.538589],"type":"Point"}
}
