{
  "type": "Feature",
  "properties": {
    "iso:country":"GB",
    "wof:name":"EN5 4DB",
    "wof:placetype":"postalcode"
},
  "geometry": {"coordinates":[-0.2182445575172,51.65290104643027],"type":"Point"}
}