{
  "type": "Feature",
  "properties": {
    "iso:country":"GB",
    "wof:name":"M13 0JH",
    "wof:placetype":"postalcode"
},
  "geometry": {"coordinates":[-2.22658179747783,53.45968775536339],"type":"Point"}
}