{
  "type": "Feature",
  "properties": {
    "date:inception_lower": "2021-10-01",
    "date:inception_upper": "2021-10-01",
    "iso:country": "GB",
    "wof:name": "RG27 9YW",
    "wof:placetype": "postalcode"
  },
  "geometry": {"coordinates":[-0.952191,51.291045],"type":"Point"}
}
