{
  "type": "Feature",
  "properties": {
    "iso:country":"GB",
    "wof:name":"G51 1QQ",
    "wof:placetype":"postalcode"
},
  "geometry": {"coordinates":[-4.29978334739366,55.85002224615905],"type":"Point"}
}