{
  "type": "Feature",
  "properties": {
    "iso:country":"GB",
    "wof:name":"CM1 7GE",
    "wof:placetype":"postalcode"
},
  "geometry": {"coordinates":[0.47119960970952,51.77044423179285],"type":"Point"}
}