{
  "type": "Feature",
  "properties": {
    "date:inception_lower":"2009-03-01",
    "date:inception_upper":"2009-03-31",
    "iso:country":"GB",
    "wof:name":"CM1 7GE",
    "wof:placetype":"postalcode"
},
  "geometry": {"coordinates":[0.4712,51.770444],"type":"Point"}
}