{
  "type": "Feature",
  "properties": {
    "date:inception_lower": "2023-08-01",
    "date:inception_upper": "2023-08-01",
    "iso:country": "GB",
    "wof:name": "WA5 3EP",
    "wof:placetype": "postalcode"
  },
  "geometry": {"coordinates":[-2.651767,53.40952],"type":"Point"}
}
