{
  "type": "Feature",
  "properties": {
    "iso:country":"GB",
    "wof:name":"SK14 4DN",
    "wof:placetype":"postalcode"
},
  "geometry": {"coordinates":[-2.06420768963046,53.45765654684334],"type":"Point"}
}