{
  "type": "Feature",
  "properties": {
    "iso:country":"GB",
    "wof:name":"DL2 1SU",
    "wof:placetype":"postalcode"
},
  "geometry": {"coordinates":[-1.45445825139002,54.56011822847879],"type":"Point"}
}