{
  "type": "Feature",
  "properties": {
    "iso:country":"GB",
    "wof:name":"B94 5PN",
    "wof:placetype":"postalcode"
},
  "geometry": {"coordinates":[-1.79384192197789,52.32978348884328],"type":"Point"}
}