{
  "type": "Feature",
  "properties": {
    "iso:country": "GB",
    "wof:name": "B94 5PN",
    "wof:placetype": "postalcode"
  },
  "geometry": {"coordinates":[-1.793842,52.329783],"type":"Point"}
}
