{
  "type": "Feature",
  "properties": {
    "date:inception_lower": "1995-07-01",
    "date:inception_upper": "1995-07-01",
    "iso:country": "GB",
    "wof:name": "RG6 5TD",
    "wof:placetype": "postalcode"
  },
  "geometry": {"coordinates":[-0.939604,51.432807],"type":"Point"}
}
