{
  "type": "Feature",
  "properties": {
    "iso:country":"GB",
    "wof:name":"FK11 7BL",
    "wof:placetype":"postalcode"
},
  "geometry": {"coordinates":[-3.85343867813636,56.15135985325059],"type":"Point"}
}