{
  "type": "Feature",
  "properties": {
    "iso:country": "GB",
    "wof:name": "FK11 7BL",
    "wof:placetype": "postalcode"
  },
  "geometry": {"coordinates":[-3.853439,56.15136],"type":"Point"}
}
