{
  "type": "Feature",
  "properties": {
    "iso:country":"GB",
    "wof:name":"SA6 5PP",
    "wof:placetype":"postalcode"
},
  "geometry": {"coordinates":[-3.87694950742972,51.69961729596977],"type":"Point"}
}