{
  "type": "Feature",
  "properties": {
    "date:inception_lower": "1996-12-01",
    "date:inception_upper": "1996-12-01",
    "iso:country": "GB",
    "wof:name": "PR2 9LU",
    "wof:placetype": "postalcode"
  },
  "geometry": {"coordinates":[-2.666321,53.787118],"type":"Point"}
}
