{
  "type": "Feature",
  "properties": {
    "date:inception_lower": "2004-07-01",
    "date:inception_upper": "2004-07-01",
    "iso:country": "GB",
    "wof:name": "G53 6UG",
    "wof:placetype": "postalcode"
  },
  "geometry": {"coordinates":[-4.342089,55.813372],"type":"Point"}
}
