{
  "type": "Feature",
  "properties": {
    "iso:country": "GB",
    "wof:name": "SK17 6ZD",
    "wof:placetype": "postalcode"
  },
  "geometry": {"coordinates":[-1.912541,53.256142],"type":"Point"}
}
