{
  "type": "Feature",
  "properties": {
    "date:inception_lower":"1998-12-01",
    "date:inception_upper":"1998-12-31",
    "iso:country":"GB",
    "wof:name":"ME15 7RZ",
    "wof:placetype":"postalcode"
},
  "geometry": {"coordinates":[0.530256,51.272581],"type":"Point"}
}