{
  "type": "Feature",
  "properties": {
    "iso:country":"GB",
    "wof:name":"ME15 7RZ",
    "wof:placetype":"postalcode"
},
  "geometry": {"coordinates":[0.5302556602023,51.27258054199049],"type":"Point"}
}