{
  "type": "Feature",
  "properties": {
    "date:inception_lower":"1980-01-01",
    "date:inception_upper":"1980-01-31",
    "iso:country":"GB",
    "wof:name":"TD1 2BN",
    "wof:placetype":"postalcode"
},
  "geometry": {"coordinates":[-2.806686,55.620301],"type":"Point"}
}