{
  "type": "Feature",
  "properties": {
    "iso:country":"GB",
    "wof:name":"TD1 2BN",
    "wof:placetype":"postalcode"
},
  "geometry": {"coordinates":[-2.80668651216774,55.62030102441873],"type":"Point"}
}