{
  "type": "Feature",
  "properties": {
    "iso:country": "GB",
    "wof:name": "WR11 7AF",
    "wof:placetype": "postalcode"
  },
  "geometry": {"coordinates":[-1.832393,52.100746],"type":"Point"}
}
