{
  "type": "Feature",
  "properties": {
    "iso:country": "GB",
    "wof:name": "HX6 2JR",
    "wof:placetype": "postalcode"
  },
  "geometry": {"coordinates":[-1.908943,53.708808],"type":"Point"}
}
