{
  "type": "Feature",
  "properties": {
    "date:inception_lower": "2000-06-01",
    "date:inception_upper": "2000-06-01",
    "iso:country": "GB",
    "wof:name": "HX6 2JR",
    "wof:placetype": "postalcode"
  },
  "geometry": {"coordinates":[-1.908943,53.708808],"type":"Point"}
}
