{
  "type": "Feature",
  "properties": {
    "date:inception_lower":"1980-01-01",
    "date:inception_upper":"1980-01-31",
    "iso:country":"GB",
    "wof:name":"HR9 5HD",
    "wof:placetype":"postalcode"
},
  "geometry": {"coordinates":[-2.584221,51.914084],"type":"Point"}
}