{
  "type": "Feature",
  "properties": {
    "iso:country":"GB",
    "wof:name":"HR9 5HD",
    "wof:placetype":"postalcode"
},
  "geometry": {"coordinates":[-2.58430817555183,51.91412994569424],"type":"Point"}
}