{
  "type": "Feature",
  "properties": {
    "iso:country": "GB",
    "wof:name": "IG8 0JL",
    "wof:placetype": "postalcode"
  },
  "geometry": {"coordinates":[0.038471,51.614832],"type":"Point"}
}
