{
  "type": "Feature",
  "properties": {
    "iso:country":"GB",
    "wof:name":"IG8 0JL",
    "wof:placetype":"postalcode"
},
  "geometry": {"coordinates":[0.03847070120589,51.61483197262732],"type":"Point"}
}