{
  "type": "Feature",
  "properties": {
    "date:inception_lower": "2006-08-01",
    "date:inception_upper": "2006-08-01",
    "iso:country": "GB",
    "wof:name": "LS26 0ZL",
    "wof:placetype": "postalcode"
  },
  "geometry": {"coordinates":[-1.50165,53.756936],"type":"Point"}
}
