{
  "type": "Feature",
  "properties": {
    "iso:country":"GB",
    "wof:name":"KY12 7NZ",
    "wof:placetype":"postalcode"
},
  "geometry": {"coordinates":[-3.46042083969838,56.07001832721404],"type":"Point"}
}