{
  "type": "Feature",
  "properties": {
    "iso:country":"GB",
    "wof:name":"DN7 4EA",
    "wof:placetype":"postalcode"
},
  "geometry": {"coordinates":[-1.02342045076267,53.58356358797364],"type":"Point"}
}