{
  "type": "Feature",
  "properties": {
    "iso:country":"GB",
    "wof:name":"ML1 4DQ",
    "wof:placetype":"postalcode"
},
  "geometry": {"coordinates":[-3.9584406719412,55.80481340151861],"type":"Point"}
}