{
  "type": "Feature",
  "properties": {
    "date:inception_lower": "1990-07-01",
    "date:inception_upper": "1990-07-01",
    "iso:country": "GB",
    "wof:name": "ST6 2BY",
    "wof:placetype": "postalcode"
  },
  "geometry": {"coordinates":[-2.182802,53.0459],"type":"Point"}
}
