{
  "type": "Feature",
  "properties": {
    "date:inception_lower":"1990-07-01",
    "date:inception_upper":"1990-07-31",
    "iso:country":"GB",
    "wof:name":"ST6 2BY",
    "wof:placetype":"postalcode"
},
  "geometry": {"coordinates":[-2.183905,53.045602],"type":"Point"}
}