{
  "type": "Feature",
  "properties": {
    "date:inception_lower": "1997-12-01",
    "date:inception_upper": "1997-12-01",
    "iso:country": "GB",
    "wof:name": "BS48 1BX",
    "wof:placetype": "postalcode"
  },
  "geometry": {"coordinates":[-2.7513,51.435479],"type":"Point"}
}
