{
  "type": "Feature",
  "properties": {
    "iso:country":"GB",
    "wof:name":"CM5 0DS",
    "wof:placetype":"postalcode"
},
  "geometry": {"coordinates":[0.20910963478882,51.74891933688401],"type":"Point"}
}