{
  "type": "Feature",
  "properties": {
    "iso:country":"GB",
    "wof:name":"ST5 3NR",
    "wof:placetype":"postalcode"
},
  "geometry": {"coordinates":[-2.22817283546629,52.99426058433969],"type":"Point"}
}