{
  "type": "Feature",
  "properties": {
    "iso:country": "GB",
    "wof:name": "PO20 2HH",
    "wof:placetype": "postalcode"
  },
  "geometry": {"coordinates":[-0.719265,50.850331],"type":"Point"}
}
