{
  "type": "Feature",
  "properties": {
    "iso:country":"GB",
    "wof:name":"EX8 1XX",
    "wof:placetype":"postalcode"
},
  "geometry": {"coordinates":[-3.42090206626754,50.61811646206611],"type":"Point"}
}