{
  "type": "Feature",
  "properties": {
    "date:inception_lower": "1998-06-01",
    "date:inception_upper": "1998-06-01",
    "iso:country": "GB",
    "wof:name": "EX8 1XX",
    "wof:placetype": "postalcode"
  },
  "geometry": {"coordinates":[-3.420902,50.618116],"type":"Point"}
}
