{
  "type": "Feature",
  "properties": {
    "iso:country":"GB",
    "wof:name":"EC1M 6BQ",
    "wof:placetype":"postalcode"
},
  "geometry": {"coordinates":[-0.09887224942176,51.52131289586309],"type":"Point"}
}