{
  "type": "Feature",
  "properties": {
    "date:inception_lower": "1980-01-01",
    "date:inception_upper": "1980-01-01",
    "iso:country": "GB",
    "wof:name": "EC1M 6BQ",
    "wof:placetype": "postalcode"
  },
  "geometry": {"coordinates":[-0.098872,51.521313],"type":"Point"}
}
