{
  "type": "Feature",
  "properties": {
    "iso:country":"GB",
    "wof:name":"CT4 6QW",
    "wof:placetype":"postalcode"
},
  "geometry": {"coordinates":[1.15606138499553,51.20255777562107],"type":"Point"}
}