{
  "type": "Feature",
  "properties": {
    "iso:country": "GB",
    "wof:name": "CT4 6QW",
    "wof:placetype": "postalcode"
  },
  "geometry": {"coordinates":[1.156094,51.202813],"type":"Point"}
}
