{
  "type": "Feature",
  "properties": {
    "iso:country":"GB",
    "wof:name":"E1W 2QB",
    "wof:placetype":"postalcode"
},
  "geometry": {"coordinates":[-0.05903208462206,51.50431183123869],"type":"Point"}
}