{
  "type": "Feature",
  "properties": {
    "iso:country":"GB",
    "wof:name":"LS29 8JU",
    "wof:placetype":"postalcode"
},
  "geometry": {"coordinates":[-1.81241508794135,53.928990351568],"type":"Point"}
}