{
  "type": "Feature",
  "properties": {
    "iso:country": "GB",
    "wof:name": "NW7 1SP",
    "wof:placetype": "postalcode"
  },
  "geometry": {"coordinates":[-0.209532,51.61326],"type":"Point"}
}
