{
  "type": "Feature",
  "properties": {
    "date:inception_lower": "2021-04-01",
    "date:inception_upper": "2021-04-01",
    "iso:country": "GB",
    "wof:name": "NW7 1SP",
    "wof:placetype": "postalcode"
  },
  "geometry": {"coordinates":[-0.209532,51.61326],"type":"Point"}
}
