{
  "type": "Feature",
  "properties": {
    "date:inception_lower": "2007-10-01",
    "date:inception_upper": "2007-10-01",
    "iso:country": "GB",
    "wof:name": "B11 4HL",
    "wof:placetype": "postalcode"
  },
  "geometry": {"coordinates":[-1.867473,52.448963],"type":"Point"}
}
