{
  "type": "Feature",
  "properties": {
    "iso:country":"GB",
    "wof:name":"B11 4HL",
    "wof:placetype":"postalcode"
},
  "geometry": {"coordinates":[-1.86747345154295,52.44896276647166],"type":"Point"}
}