{
  "type": "Feature",
  "properties": {
    "iso:country":"GB",
    "wof:name":"TW17 8SF",
    "wof:placetype":"postalcode"
},
  "geometry": {"coordinates":[-0.43362362543547,51.40254486864501],"type":"Point"}
}