{
  "type": "Feature",
  "properties": {
    "iso:country": "GB",
    "wof:name": "W10 4AQ",
    "wof:placetype": "postalcode"
  },
  "geometry": {"coordinates":[-0.213957,51.532033],"type":"Point"}
}
