{
  "type": "Feature",
  "properties": {
    "date:inception_lower": "2005-11-01",
    "date:inception_upper": "2005-11-01",
    "iso:country": "GB",
    "wof:name": "W10 4AQ",
    "wof:placetype": "postalcode"
  },
  "geometry": {"coordinates":[-0.213957,51.532033],"type":"Point"}
}
