{
  "type": "Feature",
  "properties": {
    "iso:country":"GB",
    "wof:name":"SO40 9HS",
    "wof:placetype":"postalcode"
},
  "geometry": {"coordinates":[-1.48505752536727,50.91453694194407],"type":"Point"}
}