{
  "type": "Feature",
  "properties": {
    "iso:country":"GB",
    "wof:name":"NE34 8UE",
    "wof:placetype":"postalcode"
},
  "geometry": {"coordinates":[-1.42062818097437,54.96147619980018],"type":"Point"}
}