{
  "type": "Feature",
  "properties": {
    "iso:country": "GB",
    "wof:name": "CH61 9NF",
    "wof:placetype": "postalcode"
  },
  "geometry": {"coordinates":[-3.094796,53.346585],"type":"Point"}
}
