{
  "type": "Feature",
  "properties": {
    "date:inception_lower": "1999-06-01",
    "date:inception_upper": "1999-06-01",
    "iso:country": "GB",
    "wof:name": "CH61 9NF",
    "wof:placetype": "postalcode"
  },
  "geometry": {"coordinates":[-3.094796,53.346585],"type":"Point"}
}
