{
  "type": "Feature",
  "properties": {
    "date:inception_lower":"2004-09-01",
    "date:inception_upper":"2004-09-30",
    "iso:country":"GB",
    "wof:name":"CF41 7AE",
    "wof:placetype":"postalcode"
},
  "geometry": {"coordinates":[-3.488971,51.651136],"type":"Point"}
}