{
  "type": "Feature",
  "properties": {
    "iso:country": "GB",
    "wof:name": "CF41 7AE",
    "wof:placetype": "postalcode"
  },
  "geometry": {"coordinates":[-3.488951,51.651086],"type":"Point"}
}
