{
  "type": "Feature",
  "properties": {
    "iso:country": "GB",
    "wof:name": "CF41 7AE",
    "wof:placetype": "postalcode"
  },
  "geometry": {"coordinates":[-3.488971,51.651136],"type":"Point"}
}
