{
  "type": "Feature",
  "properties": {
    "date:inception_lower": "2004-09-01",
    "date:inception_upper": "2004-09-01",
    "iso:country": "GB",
    "wof:name": "CF41 7AE",
    "wof:placetype": "postalcode"
  },
  "geometry": {"coordinates":[-3.489293,51.650946],"type":"Point"}
}
