{
  "type": "Feature",
  "properties": {
    "iso:country": "GB",
    "wof:name": "DA16 3PG",
    "wof:placetype": "postalcode"
  },
  "geometry": {"coordinates":[0.102291,51.463167],"type":"Point"}
}
