{
  "type": "Feature",
  "properties": {
    "iso:country":"GB",
    "wof:name":"DA16 3PG",
    "wof:placetype":"postalcode"
},
  "geometry": {"coordinates":[0.10229132455742,51.46316727773247],"type":"Point"}
}