{
  "type": "Feature",
  "properties": {
    "iso:country":"GB",
    "wof:name":"G75 9AS",
    "wof:placetype":"postalcode"
},
  "geometry": {"coordinates":[-4.19197883232681,55.75270708356133],"type":"Point"}
}