{
  "type": "Feature",
  "properties": {
    "date:inception_lower": "1980-01-01",
    "date:inception_upper": "1980-01-01",
    "iso:country": "GB",
    "wof:name": "G75 9AS",
    "wof:placetype": "postalcode"
  },
  "geometry": {"coordinates":[-4.191979,55.752707],"type":"Point"}
}
