{
  "type": "Feature",
  "properties": {
    "date:inception_lower": "1980-01-01",
    "date:inception_upper": "1980-01-01",
    "iso:country": "GB",
    "wof:name": "B90 4HJ",
    "wof:placetype": "postalcode"
  },
  "geometry": {"coordinates":[-1.812925,52.380367],"type":"Point"}
}
