{
  "type": "Feature",
  "properties": {
    "iso:country":"GB",
    "wof:name":"B90 4HJ",
    "wof:placetype":"postalcode"
},
  "geometry": {"coordinates":[-1.81292533386361,52.38036687909112],"type":"Point"}
}