{
  "type": "Feature",
  "properties": {
    "iso:country": "GB",
    "wof:name": "NR10 5NY",
    "wof:placetype": "postalcode"
  },
  "geometry": {"coordinates":[1.260164,52.729452],"type":"Point"}
}
