{
  "type": "Feature",
  "properties": {
    "iso:country":"GB",
    "wof:name":"NR10 5NY",
    "wof:placetype":"postalcode"
},
  "geometry": {"coordinates":[1.26016352144236,52.72945221965843],"type":"Point"}
}