{
  "type": "Feature",
  "properties": {
    "iso:country": "GB",
    "wof:name": "CT2 7TX",
    "wof:placetype": "postalcode"
  },
  "geometry": {"coordinates":[1.08768,51.297074],"type":"Point"}
}
