{
  "type": "Feature",
  "properties": {
    "date:inception_lower": "1980-01-01",
    "date:inception_upper": "1980-01-01",
    "iso:country": "GB",
    "wof:name": "CT2 7TX",
    "wof:placetype": "postalcode"
  },
  "geometry": {"coordinates":[1.08768,51.297074],"type":"Point"}
}
