{
  "type": "Feature",
  "properties": {
    "iso:country":"GB",
    "wof:name":"CT2 7TX",
    "wof:placetype":"postalcode"
},
  "geometry": {"coordinates":[1.08768012398131,51.29707375339902],"type":"Point"}
}