{
  "type": "Feature",
  "properties": {
    "date:inception_lower": "1990-03-01",
    "date:inception_upper": "1990-03-01",
    "iso:country": "GB",
    "wof:name": "FK10 2NP",
    "wof:placetype": "postalcode"
  },
  "geometry": {"coordinates":[-3.79616,56.124861],"type":"Point"}
}
