{
  "type": "Feature",
  "properties": {
    "iso:country":"GB",
    "wof:name":"AB42 1PS",
    "wof:placetype":"postalcode"
},
  "geometry": {"coordinates":[-1.81329963049247,57.51161819179074],"type":"Point"}
}