{
  "type": "Feature",
  "properties": {
    "iso:country": "GB",
    "wof:name": "AB42 1PS",
    "wof:placetype": "postalcode"
  },
  "geometry": {"coordinates":[-1.8133,57.511618],"type":"Point"}
}
