{
  "type": "Feature",
  "properties": {
    "iso:country": "GB",
    "wof:name": "YO42 4LL",
    "wof:placetype": "postalcode"
  },
  "geometry": {"coordinates":[-0.722857,53.884607],"type":"Point"}
}
