{
  "type": "Feature",
  "properties": {
    "iso:country":"GB",
    "wof:name":"GL2 2EN",
    "wof:placetype":"postalcode"
},
  "geometry": {"coordinates":[-2.26120829050195,51.82170463563971],"type":"Point"}
}