{
  "type": "Feature",
  "properties": {
    "iso:country":"GB",
    "wof:name":"KA22 8JW",
    "wof:placetype":"postalcode"
},
  "geometry": {"coordinates":[-4.80761462490082,55.64472002479916],"type":"Point"}
}