{
  "type": "Feature",
  "properties": {
    "date:inception_lower": "1980-01-01",
    "date:inception_upper": "1980-01-01",
    "iso:country": "GB",
    "wof:name": "KA22 8JW",
    "wof:placetype": "postalcode"
  },
  "geometry": {"coordinates":[-4.807615,55.64472],"type":"Point"}
}
