{
  "type": "Feature",
  "properties": {
    "date:inception_lower":"1997-06-01",
    "date:inception_upper":"1997-06-30",
    "iso:country":"GB",
    "wof:name":"BS16 2HE",
    "wof:placetype":"postalcode"
},
  "geometry": {"coordinates":[-2.520873,51.488036],"type":"Point"}
}