{
  "type": "Feature",
  "properties": {
    "iso:country":"GB",
    "wof:name":"BS16 2HE",
    "wof:placetype":"postalcode"
},
  "geometry": {"coordinates":[-2.5208728168147,51.48803634473624],"type":"Point"}
}