{
  "type": "Feature",
  "properties": {
    "iso:country":"GB",
    "wof:name":"W1K 3PQ",
    "wof:placetype":"postalcode"
},
  "geometry": {"coordinates":[-0.14557686835247,51.51099082337593],"type":"Point"}
}