{
  "type": "Feature",
  "properties": {
    "iso:country":"GB",
    "wof:name":"NR15 1YR",
    "wof:placetype":"postalcode"
},
  "geometry": {"coordinates":[1.32017501897344,52.54840648992258],"type":"Point"}
}