{
  "type": "Feature",
  "properties": {
    "iso:country":"GB",
    "wof:name":"IP11 0UP",
    "wof:placetype":"postalcode"
},
  "geometry": {"coordinates":[1.31380936258394,51.99245574578687],"type":"Point"}
}