{
  "type": "Feature",
  "properties": {
    "iso:country":"GB",
    "wof:name":"M23 0WA",
    "wof:placetype":"postalcode"
},
  "geometry": {"coordinates":[-2.28681748156565,53.41162235861386],"type":"Point"}
}