{
  "type": "Feature",
  "properties": {
    "iso:country":"GB",
    "wof:name":"TN12 6LB",
    "wof:placetype":"postalcode"
},
  "geometry": {"coordinates":[0.38751398303214,51.17583205612846],"type":"Point"}
}