{
  "type": "Feature",
  "properties": {
    "iso:country":"GB",
    "wof:name":"SL1 3QZ",
    "wof:placetype":"postalcode"
},
  "geometry": {"coordinates":[-0.59177187479399,51.51648578817166],"type":"Point"}
}