{
  "type": "Feature",
  "properties": {
    "iso:country": "GB",
    "wof:name": "E1W 1NR",
    "wof:placetype": "postalcode"
  },
  "geometry": {"coordinates":[-0.063438,51.504052],"type":"Point"}
}
