{
  "type": "Feature",
  "properties": {
    "iso:country":"GB",
    "wof:name":"E1W 1NR",
    "wof:placetype":"postalcode"
},
  "geometry": {"coordinates":[-0.06343795924017,51.50405194127105],"type":"Point"}
}