{
  "type": "Feature",
  "properties": {
    "iso:country":"GB",
    "wof:name":"W9 3PU",
    "wof:placetype":"postalcode"
},
  "geometry": {"coordinates":[-0.20519555500931,51.52530801126949],"type":"Point"}
}