{
  "type": "Feature",
  "properties": {
    "iso:country": "GB",
    "wof:name": "W9 3PU",
    "wof:placetype": "postalcode"
  },
  "geometry": {"coordinates":[-0.205196,51.525308],"type":"Point"}
}
