{
  "type": "Feature",
  "properties": {
    "date:inception_lower": "1980-01-01",
    "date:inception_upper": "1980-01-01",
    "iso:country": "GB",
    "wof:name": "LL46 2PU",
    "wof:placetype": "postalcode"
  },
  "geometry": {"coordinates":[-4.112967,52.855901],"type":"Point"}
}
