{
  "type": "Feature",
  "properties": {
    "iso:country":"GB",
    "wof:name":"LL46 2PU",
    "wof:placetype":"postalcode"
},
  "geometry": {"coordinates":[-4.11296742804455,52.85590110268019],"type":"Point"}
}