{
  "type": "Feature",
  "properties": {
    "iso:country":"GB",
    "wof:name":"CV2 2SS",
    "wof:placetype":"postalcode"
},
  "geometry": {"coordinates":[-1.45640764139558,52.44225988053933],"type":"Point"}
}