{
  "type": "Feature",
  "properties": {
    "iso:country": "GB",
    "wof:name": "CV2 2SS",
    "wof:placetype": "postalcode"
  },
  "geometry": {"coordinates":[-1.456408,52.44226],"type":"Point"}
}
