{
  "type": "Feature",
  "properties": {
    "iso:country":"GB",
    "wof:name":"DN21 1BY",
    "wof:placetype":"postalcode"
},
  "geometry": {"coordinates":[-0.77192338753028,53.39215365868282],"type":"Point"}
}