{
  "type": "Feature",
  "properties": {
    "date:inception_lower": "1980-01-01",
    "date:inception_upper": "1980-01-01",
    "iso:country": "GB",
    "wof:name": "DN21 1BY",
    "wof:placetype": "postalcode"
  },
  "geometry": {"coordinates":[-0.771923,53.392154],"type":"Point"}
}
