{
  "type": "Feature",
  "properties": {
    "iso:country":"GB",
    "wof:name":"G46 6TX",
    "wof:placetype":"postalcode"
},
  "geometry": {"coordinates":[-4.30590632618882,55.78183529573152],"type":"Point"}
}