{
  "type": "Feature",
  "properties": {
    "iso:country": "GB",
    "wof:name": "OL8 1HF",
    "wof:placetype": "postalcode"
  },
  "geometry": {"coordinates":[-2.115923,53.53541],"type":"Point"}
}
