{
  "type": "Feature",
  "properties": {
    "iso:country":"GB",
    "wof:name":"OL8 1HF",
    "wof:placetype":"postalcode"
},
  "geometry": {"coordinates":[-2.11588030704358,53.53537628124457],"type":"Point"}
}