{
  "type": "Feature",
  "properties": {
    "iso:country":"GB",
    "wof:name":"OL4 2QE",
    "wof:placetype":"postalcode"
},
  "geometry": {"coordinates":[-2.07651692895925,53.56061132387075],"type":"Point"}
}