{
  "type": "Feature",
  "properties": {
    "date:inception_lower": "1994-05-01",
    "date:inception_upper": "1994-05-01",
    "iso:country": "GB",
    "wof:name": "M19 3BW",
    "wof:placetype": "postalcode"
  },
  "geometry": {"coordinates":[-2.193147,53.446569],"type":"Point"}
}
