{
  "type": "Feature",
  "properties": {
    "iso:country":"GB",
    "wof:name":"CV37 7LP",
    "wof:placetype":"postalcode"
},
  "geometry": {"coordinates":[-1.69830984198081,52.18759413861777],"type":"Point"}
}