{
  "type": "Feature",
  "properties": {
    "iso:country":"GB",
    "wof:name":"SS11 7JY",
    "wof:placetype":"postalcode"
},
  "geometry": {"coordinates":[0.51914276663987,51.62156045607021],"type":"Point"}
}