{
  "type": "Feature",
  "properties": {
    "date:inception_lower":"1991-09-01",
    "date:inception_upper":"1991-09-30",
    "iso:country":"GB",
    "wof:name":"OX5 3UB",
    "wof:placetype":"postalcode"
},
  "geometry": {"coordinates":[-1.274628,51.875622],"type":"Point"}
}