{
  "type": "Feature",
  "properties": {
    "iso:country":"GB",
    "wof:name":"DY2 8JW",
    "wof:placetype":"postalcode"
},
  "geometry": {"coordinates":[-2.08150342841763,52.49866005360526],"type":"Point"}
}