{
  "type": "Feature",
  "properties": {
    "date:inception_lower": "2007-08-01",
    "date:inception_upper": "2007-08-01",
    "iso:country": "GB",
    "wof:name": "DY2 8JW",
    "wof:placetype": "postalcode"
  },
  "geometry": {"coordinates":[-2.081498,52.498675],"type":"Point"}
}
