{
  "type": "Feature",
  "properties": {
    "iso:country": "GB",
    "wof:name": "NR1 3JQ",
    "wof:placetype": "postalcode"
  },
  "geometry": {"coordinates":[1.297338,52.629114],"type":"Point"}
}
