{
  "type": "Feature",
  "properties": {
    "iso:country":"GB",
    "wof:name":"NR1 3JQ",
    "wof:placetype":"postalcode"
},
  "geometry": {"coordinates":[1.29736336544433,52.62875572968608],"type":"Point"}
}