{
  "type": "Feature",
  "properties": {
    "iso:country":"GB",
    "wof:name":"TD11 3SZ",
    "wof:placetype":"postalcode"
},
  "geometry": {"coordinates":[-2.34159432263638,55.78829997734322],"type":"Point"}
}