{
  "type": "Feature",
  "properties": {
    "date:inception_lower": "1980-01-01",
    "date:inception_upper": "1980-01-01",
    "iso:country": "GB",
    "wof:name": "TD11 3SZ",
    "wof:placetype": "postalcode"
  },
  "geometry": {"coordinates":[-2.341594,55.7883],"type":"Point"}
}
