{
  "type": "Feature",
  "properties": {
    "iso:country": "GB",
    "wof:name": "TD11 3SZ",
    "wof:placetype": "postalcode"
  },
  "geometry": {"coordinates":[-2.341594,55.7883],"type":"Point"}
}
