{
  "type": "Feature",
  "properties": {
    "iso:country":"GB",
    "wof:name":"LN5 0LL",
    "wof:placetype":"postalcode"
},
  "geometry": {"coordinates":[-0.5720034012234,53.11721355666309],"type":"Point"}
}