{
  "type": "Feature",
  "properties": {
    "date:inception_lower": "1980-01-01",
    "date:inception_upper": "1980-01-01",
    "iso:country": "GB",
    "wof:name": "LN5 0LL",
    "wof:placetype": "postalcode"
  },
  "geometry": {"coordinates":[-0.575592,53.117512],"type":"Point"}
}
