{
  "type": "Feature",
  "properties": {
    "date:inception_lower":"1980-01-01",
    "date:inception_upper":"1980-01-31",
    "iso:country":"GB",
    "wof:name":"LN5 0LL",
    "wof:placetype":"postalcode"
},
  "geometry": {"coordinates":[-0.572003,53.117214],"type":"Point"}
}