{
  "type": "Feature",
  "properties": {
    "iso:country": "GB",
    "wof:name": "LN5 0LL",
    "wof:placetype": "postalcode"
  },
  "geometry": {"coordinates":[-0.572003,53.117214],"type":"Point"}
}
