{
  "type": "Feature",
  "properties": {
    "date:inception_lower":"1980-01-01",
    "date:inception_upper":"1980-01-31",
    "iso:country":"GB",
    "wof:name":"CW8 1LN",
    "wof:placetype":"postalcode"
},
  "geometry": {"coordinates":[-2.539887,53.250078],"type":"Point"}
}