{
  "type": "Feature",
  "properties": {
    "iso:country":"GB",
    "wof:name":"CW8 1LN",
    "wof:placetype":"postalcode"
},
  "geometry": {"coordinates":[-2.5398883989649,53.25006251660399],"type":"Point"}
}