{
  "type": "Feature",
  "properties": {
    "iso:country":"GB",
    "wof:name":"CH1 5DG",
    "wof:placetype":"postalcode"
},
  "geometry": {"coordinates":[-2.92006520334044,53.20836137725617],"type":"Point"}
}