{
  "type": "Feature",
  "properties": {
    "iso:country":"GB",
    "wof:name":"HR9 7DF",
    "wof:placetype":"postalcode"
},
  "geometry": {"coordinates":[-2.58661564163473,51.9193871507786],"type":"Point"}
}