{
  "type": "Feature",
  "properties": {
    "iso:country":"GB",
    "wof:name":"EH5 2BL",
    "wof:placetype":"postalcode"
},
  "geometry": {"coordinates":[-3.22165228643815,55.97581311528687],"type":"Point"}
}