{
  "type": "Feature",
  "properties": {
    "iso:country":"GB",
    "wof:name":"SY3 9NY",
    "wof:placetype":"postalcode"
},
  "geometry": {"coordinates":[-2.76233314491426,52.68502993459415],"type":"Point"}
}