{
  "type": "Feature",
  "properties": {
    "iso:country":"GB",
    "wof:name":"AL8 6YH",
    "wof:placetype":"postalcode"
},
  "geometry": {"coordinates":[-0.21546465161841,51.79274041554209],"type":"Point"}
}