{
  "type": "Feature",
  "properties": {
    "iso:country":"GB",
    "wof:name":"KA7 2UX",
    "wof:placetype":"postalcode"
},
  "geometry": {"coordinates":[-4.6375802544482,55.4540953661929],"type":"Point"}
}