{
  "type": "Feature",
  "properties": {
    "iso:country":"GB",
    "wof:name":"IG2 6YD",
    "wof:placetype":"postalcode"
},
  "geometry": {"coordinates":[0.06826966810215,51.58527342641013],"type":"Point"}
}