{
  "type": "Feature",
  "properties": {
    "date:inception_lower": "1980-01-01",
    "date:inception_upper": "1980-01-01",
    "iso:country": "GB",
    "wof:name": "LS1 6NA",
    "wof:placetype": "postalcode"
  },
  "geometry": {"coordinates":[-1.542125,53.795153],"type":"Point"}
}
