{
  "type": "Feature",
  "properties": {
    "iso:country": "GB",
    "wof:name": "LS1 6NA",
    "wof:placetype": "postalcode"
  },
  "geometry": {"coordinates":[-1.542125,53.795153],"type":"Point"}
}
