{
  "type": "Feature",
  "properties": {
    "iso:country":"GB",
    "wof:name":"SA11 3XA",
    "wof:placetype":"postalcode"
},
  "geometry": {"coordinates":[-3.77539210924754,51.65343002995653],"type":"Point"}
}