{
  "type": "Feature",
  "properties": {
    "iso:country": "GB",
    "wof:name": "G61 2AY",
    "wof:placetype": "postalcode"
  },
  "geometry": {"coordinates":[-4.308171,55.92057],"type":"Point"}
}
