{
  "type": "Feature",
  "properties": {
    "iso:country":"GB",
    "wof:name":"G61 2AY",
    "wof:placetype":"postalcode"
},
  "geometry": {"coordinates":[-4.3081705571137,55.92057017705379],"type":"Point"}
}