{
  "type": "Feature",
  "properties": {
    "iso:country":"GB",
    "wof:name":"BS15 9QA",
    "wof:placetype":"postalcode"
},
  "geometry": {"coordinates":[-2.50604508032366,51.45743998996054],"type":"Point"}
}