{
  "type": "Feature",
  "properties": {
    "date:inception_lower":"1986-04-01",
    "date:inception_upper":"1986-04-30",
    "iso:country":"GB",
    "wof:name":"YO11 2RJ",
    "wof:placetype":"postalcode"
},
  "geometry": {"coordinates":[-0.404747,54.273522],"type":"Point"}
}