{
  "type": "Feature",
  "properties": {
    "iso:country": "GB",
    "wof:name": "SM7 3RE",
    "wof:placetype": "postalcode"
  },
  "geometry": {"coordinates":[-0.195822,51.331464],"type":"Point"}
}
