{
  "type": "Feature",
  "properties": {
    "iso:country": "GB",
    "wof:name": "SM7 3RE",
    "wof:placetype": "postalcode"
  },
  "geometry": {"coordinates":[-0.195797,51.331463],"type":"Point"}
}
