{
  "type": "Feature",
  "properties": {
    "iso:country":"GB",
    "wof:name":"SM7 3RE",
    "wof:placetype":"postalcode"
},
  "geometry": {"coordinates":[-0.1958221311659,51.33146442427466],"type":"Point"}
}