{
  "type": "Feature",
  "properties": {
    "iso:country":"GB",
    "wof:name":"SE4 1QL",
    "wof:placetype":"postalcode"
},
  "geometry": {"coordinates":[-0.02696515183409,51.46307584299478],"type":"Point"}
}