{
  "type": "Feature",
  "properties": {
    "iso:country": "GB",
    "wof:name": "SK11 9HS",
    "wof:placetype": "postalcode"
  },
  "geometry": {"coordinates":[-2.255695,53.206373],"type":"Point"}
}
