{
  "type": "Feature",
  "properties": {
    "iso:country":"GB",
    "wof:name":"SK11 9HS",
    "wof:placetype":"postalcode"
},
  "geometry": {"coordinates":[-2.25569471442534,53.20637276404344],"type":"Point"}
}