{
  "type": "Feature",
  "properties": {
    "iso:country":"GB",
    "wof:name":"LS14 1AE",
    "wof:placetype":"postalcode"
},
  "geometry": {"coordinates":[-1.44903290021529,53.83939652420075],"type":"Point"}
}