{
  "type": "Feature",
  "properties": {
    "date:inception_lower": "1980-01-01",
    "date:inception_upper": "1980-01-01",
    "iso:country": "GB",
    "wof:name": "BS14 9SF",
    "wof:placetype": "postalcode"
  },
  "geometry": {"coordinates":[-2.570765,51.41668],"type":"Point"}
}
