{
  "type": "Feature",
  "properties": {
    "iso:country": "GB",
    "wof:name": "LS27 0FW",
    "wof:placetype": "postalcode"
  },
  "geometry": {"coordinates":[-1.603393,53.736128],"type":"Point"}
}
