{
  "type": "Feature",
  "properties": {
    "date:inception_lower": "2018-08-01",
    "date:inception_upper": "2018-08-01",
    "iso:country": "GB",
    "wof:name": "LS27 0FW",
    "wof:placetype": "postalcode"
  },
  "geometry": {"coordinates":[-1.603196,53.736137],"type":"Point"}
}
