{
  "type": "Feature",
  "properties": {
    "date:inception_lower": "1980-01-01",
    "date:inception_upper": "1980-01-01",
    "iso:country": "GB",
    "wof:name": "PA13 4JX",
    "wof:placetype": "postalcode"
  },
  "geometry": {"coordinates":[-4.638271,55.893582],"type":"Point"}
}
