{
  "type": "Feature",
  "properties": {
    "iso:country":"GB",
    "wof:name":"PA13 4JX",
    "wof:placetype":"postalcode"
},
  "geometry": {"coordinates":[-4.6383388875017,55.89361377276851],"type":"Point"}
}