{
  "type": "Feature",
  "properties": {
    "iso:country": "GB",
    "wof:name": "PA13 4JX",
    "wof:placetype": "postalcode"
  },
  "geometry": {"coordinates":[-4.638339,55.893614],"type":"Point"}
}
