{
  "type": "Feature",
  "properties": {
    "iso:country":"GB",
    "wof:name":"BN21 3XY",
    "wof:placetype":"postalcode"
},
  "geometry": {"coordinates":[0.27939148328717,50.77030296642003],"type":"Point"}
}