{
  "type": "Feature",
  "properties": {
    "date:inception_lower": "1992-08-01",
    "date:inception_upper": "1992-08-01",
    "iso:country": "GB",
    "wof:name": "DE56 2FR",
    "wof:placetype": "postalcode"
  },
  "geometry": {"coordinates":[-1.467041,53.072895],"type":"Point"}
}
