{
  "type": "Feature",
  "properties": {
    "iso:country":"GB",
    "wof:name":"DE56 2FR",
    "wof:placetype":"postalcode"
},
  "geometry": {"coordinates":[-1.46704082647661,53.07289536163847],"type":"Point"}
}