{
  "type": "Feature",
  "properties": {
    "iso:country":"GB",
    "wof:name":"NG16 2PY",
    "wof:placetype":"postalcode"
},
  "geometry": {"coordinates":[-1.25165092474562,52.99251333994528],"type":"Point"}
}