{
  "type": "Feature",
  "properties": {
    "iso:country":"GB",
    "wof:name":"PA5 8DX",
    "wof:placetype":"postalcode"
},
  "geometry": {"coordinates":[-4.51357621244126,55.83651775238442],"type":"Point"}
}