{
  "type": "Feature",
  "properties": {
    "iso:country":"GB",
    "wof:name":"B12 8HG",
    "wof:placetype":"postalcode"
},
  "geometry": {"coordinates":[-1.87507868198319,52.45480554018825],"type":"Point"}
}