{
  "type": "Feature",
  "properties": {
    "date:inception_lower": "1980-01-01",
    "date:inception_upper": "1980-01-01",
    "iso:country": "GB",
    "wof:name": "SS9 4PG",
    "wof:placetype": "postalcode"
  },
  "geometry": {"coordinates":[0.649769,51.560585],"type":"Point"}
}
