{
  "type": "Feature",
  "properties": {
    "iso:country":"GB",
    "wof:name":"SS9 4PG",
    "wof:placetype":"postalcode"
},
  "geometry": {"coordinates":[0.64976910732213,51.5605854845132],"type":"Point"}
}