{
  "type": "Feature",
  "properties": {
    "iso:country": "GB",
    "wof:name": "SS9 4PG",
    "wof:placetype": "postalcode"
  },
  "geometry": {"coordinates":[0.649769,51.560585],"type":"Point"}
}
