{
  "type": "Feature",
  "properties": {
    "date:inception_lower": "1980-01-01",
    "date:inception_upper": "1980-01-01",
    "iso:country": "GB",
    "wof:name": "PR7 6HZ",
    "wof:placetype": "postalcode"
  },
  "geometry": {"coordinates":[-2.673868,53.65849],"type":"Point"}
}
