{
  "type": "Feature",
  "properties": {
    "iso:country":"GB",
    "wof:name":"PR7 6HZ",
    "wof:placetype":"postalcode"
},
  "geometry": {"coordinates":[-2.67386816807342,53.65848989240374],"type":"Point"}
}