{
  "type": "Feature",
  "properties": {
    "iso:country":"GB",
    "wof:name":"YO30 6DR",
    "wof:placetype":"postalcode"
},
  "geometry": {"coordinates":[-1.08954071014959,53.97400740626535],"type":"Point"}
}