{
  "type": "Feature",
  "properties": {
    "iso:country": "GB",
    "wof:name": "YO30 6DR",
    "wof:placetype": "postalcode"
  },
  "geometry": {"coordinates":[-1.089541,53.974007],"type":"Point"}
}
