{
  "type": "Feature",
  "properties": {
    "iso:country": "GB",
    "wof:name": "CF5 6SA",
    "wof:placetype": "postalcode"
  },
  "geometry": {"coordinates":[-3.281025,51.464445],"type":"Point"}
}
