{
  "type": "Feature",
  "properties": {
    "iso:country":"GB",
    "wof:name":"CF5 6SA",
    "wof:placetype":"postalcode"
},
  "geometry": {"coordinates":[-3.28102541581645,51.46444461945402],"type":"Point"}
}