{
  "type": "Feature",
  "properties": {
    "iso:country":"GB",
    "wof:name":"CA1 3SF",
    "wof:placetype":"postalcode"
},
  "geometry": {"coordinates":[-2.89319828550801,54.88273715722135],"type":"Point"}
}