{
  "type": "Feature",
  "properties": {
    "iso:country": "GB",
    "wof:name": "TF11 9JY",
    "wof:placetype": "postalcode"
  },
  "geometry": {"coordinates":[-2.367271,52.641416],"type":"Point"}
}
