{
  "type": "Feature",
  "properties": {
    "date:inception_lower":"2015-09-01",
    "date:inception_upper":"2015-09-30",
    "iso:country":"GB",
    "wof:name":"MK19 7JU",
    "wof:placetype":"postalcode"
},
  "geometry": {"coordinates":[-0.845172,52.075395],"type":"Point"}
}