{
  "type": "Feature",
  "properties": {
    "iso:country":"GB",
    "wof:name":"WF12 9DY",
    "wof:placetype":"postalcode"
},
  "geometry": {"coordinates":[-1.63557789664285,53.67422385092483],"type":"Point"}
}