{
  "type": "Feature",
  "properties": {
    "iso:country": "GB",
    "wof:name": "B45 9UX",
    "wof:placetype": "postalcode"
  },
  "geometry": {"coordinates":[-2.02982,52.398149],"type":"Point"}
}
