{
  "type": "Feature",
  "properties": {
    "iso:country": "GB",
    "wof:name": "LL12 0UW",
    "wof:placetype": "postalcode"
  },
  "geometry": {"coordinates":[-2.986656,53.095139],"type":"Point"}
}
