{
  "type": "Feature",
  "properties": {
    "date:inception_lower":"2008-03-01",
    "date:inception_upper":"2008-03-31",
    "iso:country":"GB",
    "wof:name":"CW12 2DP",
    "wof:placetype":"postalcode"
},
  "geometry": {"coordinates":[-2.201724,53.169109],"type":"Point"}
}