{
  "type": "Feature",
  "properties": {
    "date:inception_lower": "2022-02-01",
    "date:inception_upper": "2022-02-01",
    "iso:country": "GB",
    "wof:name": "NR29 4WR",
    "wof:placetype": "postalcode"
  },
  "geometry": {"coordinates":[1.693965,52.6922],"type":"Point"}
}
