{
  "type": "Feature",
  "properties": {
    "iso:country":"GB",
    "wof:name":"FK7 9QW",
    "wof:placetype":"postalcode"
},
  "geometry": {"coordinates":[-3.94591207553961,56.06654332792456],"type":"Point"}
}