{
  "type": "Feature",
  "properties": {
    "date:inception_lower":"1980-01-01",
    "date:inception_upper":"1980-01-31",
    "iso:country":"GB",
    "wof:name":"FK7 9QW",
    "wof:placetype":"postalcode"
},
  "geometry": {"coordinates":[-3.945904,56.066537],"type":"Point"}
}