{
  "type": "Feature",
  "properties": {
    "iso:country":"GB",
    "wof:name":"CM11 2TG",
    "wof:placetype":"postalcode"
},
  "geometry": {"coordinates":[0.42916314831985,51.61318725989505],"type":"Point"}
}