{
  "type": "Feature",
  "properties": {
    "iso:country": "GB",
    "wof:name": "CM11 2TG",
    "wof:placetype": "postalcode"
  },
  "geometry": {"coordinates":[0.429163,51.613187],"type":"Point"}
}
