{
  "type": "Feature",
  "properties": {
    "iso:country":"GB",
    "wof:name":"S75 2RW",
    "wof:placetype":"postalcode"
},
  "geometry": {"coordinates":[-1.51896833663438,53.55903164558622],"type":"Point"}
}