{
  "type": "Feature",
  "properties": {
    "iso:country": "GB",
    "wof:name": "S75 2RW",
    "wof:placetype": "postalcode"
  },
  "geometry": {"coordinates":[-1.519893,53.558873],"type":"Point"}
}
