{
  "type": "Feature",
  "properties": {
    "date:inception_lower": "1990-07-01",
    "date:inception_upper": "1990-07-01",
    "iso:country": "GB",
    "wof:name": "IG7 6PL",
    "wof:placetype": "postalcode"
  },
  "geometry": {"coordinates":[0.076071,51.619604],"type":"Point"}
}
