{
  "type": "Feature",
  "properties": {
    "iso:country":"GB",
    "wof:name":"IG7 6PL",
    "wof:placetype":"postalcode"
},
  "geometry": {"coordinates":[0.07607113486123,51.61960448944229],"type":"Point"}
}