{
  "type": "Feature",
  "properties": {
    "date:inception_lower": "1990-07-01",
    "date:inception_upper": "1990-07-01",
    "iso:country": "GB",
    "wof:name": "BN42 4AN",
    "wof:placetype": "postalcode"
  },
  "geometry": {"coordinates":[-0.230217,50.832338],"type":"Point"}
}
