{
  "type": "Feature",
  "properties": {
    "iso:country":"GB",
    "wof:name":"S18 3BT",
    "wof:placetype":"postalcode"
},
  "geometry": {"coordinates":[-1.44974784927729,53.30868781462512],"type":"Point"}
}