{
  "type": "Feature",
  "properties": {
    "iso:country": "GB",
    "wof:name": "LN11 0ZL",
    "wof:placetype": "postalcode"
  },
  "geometry": {"coordinates":[0.006562,53.379825],"type":"Point"}
}
