{
  "type": "Feature",
  "properties": {
    "date:inception_lower": "2019-01-01",
    "date:inception_upper": "2019-01-01",
    "iso:country": "GB",
    "wof:name": "LN11 0ZL",
    "wof:placetype": "postalcode"
  },
  "geometry": {"coordinates":[0.006605,53.379798],"type":"Point"}
}
