{
  "type": "Feature",
  "properties": {
    "iso:country":"GB",
    "wof:name":"LL14 6PG",
    "wof:placetype":"postalcode"
},
  "geometry": {"coordinates":[-3.03865770905879,52.98974345297901],"type":"Point"}
}