{
  "type": "Feature",
  "properties": {
    "iso:country":"GB",
    "wof:name":"PL6 6BQ",
    "wof:placetype":"postalcode"
},
  "geometry": {"coordinates":[-4.12935349740725,50.42365650980626],"type":"Point"}
}