{
  "type": "Feature",
  "properties": {
    "iso:country":"GB",
    "wof:name":"WR14 4JG",
    "wof:placetype":"postalcode"
},
  "geometry": {"coordinates":[-2.3239433872266,52.07191552694972],"type":"Point"}
}