{
  "type": "Feature",
  "properties": {
    "date:inception_lower": "1996-06-01",
    "date:inception_upper": "1996-06-01",
    "iso:country": "GB",
    "wof:name": "WR14 4JG",
    "wof:placetype": "postalcode"
  },
  "geometry": {"coordinates":[-2.323943,52.071916],"type":"Point"}
}
