{
  "type": "Feature",
  "properties": {
    "iso:country": "GB",
    "wof:name": "WF17 7SX",
    "wof:placetype": "postalcode"
  },
  "geometry": {"coordinates":[-1.642421,53.711635],"type":"Point"}
}
