{
  "type": "Feature",
  "properties": {
    "date:inception_lower": "1980-01-01",
    "date:inception_upper": "1980-01-01",
    "iso:country": "GB",
    "wof:name": "WF17 7SX",
    "wof:placetype": "postalcode"
  },
  "geometry": {"coordinates":[-1.642421,53.711635],"type":"Point"}
}
