{
  "type": "Feature",
  "properties": {
    "iso:country":"GB",
    "wof:name":"BS34 6LB",
    "wof:placetype":"postalcode"
},
  "geometry": {"coordinates":[-2.55586099512272,51.52509168200121],"type":"Point"}
}