{
  "type": "Feature",
  "properties": {
    "iso:country":"GB",
    "wof:name":"SW6 6LZ",
    "wof:placetype":"postalcode"
},
  "geometry": {"coordinates":[-0.2224193762155,51.48094984734508],"type":"Point"}
}