{
  "type": "Feature",
  "properties": {
    "date:inception_lower":"1980-01-01",
    "date:inception_upper":"1980-01-31",
    "iso:country":"GB",
    "wof:name":"SW6 6LZ",
    "wof:placetype":"postalcode"
},
  "geometry": {"coordinates":[-0.222419,51.48095],"type":"Point"}
}