{
  "type": "Feature",
  "properties": {
    "date:inception_lower": "2021-12-01",
    "date:inception_upper": "2021-12-01",
    "iso:country": "GB",
    "wof:name": "BD20 0FL",
    "wof:placetype": "postalcode"
  },
  "geometry": {"coordinates":[-1.936374,53.906116],"type":"Point"}
}
