{
  "type": "Feature",
  "properties": {
    "iso:country": "GB",
    "wof:name": "IG10 1LS",
    "wof:placetype": "postalcode"
  },
  "geometry": {"coordinates":[0.064009,51.656219],"type":"Point"}
}
