{
  "type": "Feature",
  "properties": {
    "date:inception_lower":"1980-01-01",
    "date:inception_upper":"1980-01-31",
    "iso:country":"GB",
    "wof:name":"IG10 1LS",
    "wof:placetype":"postalcode"
},
  "geometry": {"coordinates":[0.064009,51.656219],"type":"Point"}
}