{
  "type": "Feature",
  "properties": {
    "iso:country":"GB",
    "wof:name":"IG10 1LS",
    "wof:placetype":"postalcode"
},
  "geometry": {"coordinates":[0.06400923681056,51.65621919420701],"type":"Point"}
}