{
  "type": "Feature",
  "properties": {
    "iso:country":"GB",
    "wof:name":"CF62 7HH",
    "wof:placetype":"postalcode"
},
  "geometry": {"coordinates":[-3.28258443180794,51.40553854379351],"type":"Point"}
}