{
  "type": "Feature",
  "properties": {
    "iso:country":"GB",
    "wof:name":"PH10 7JA",
    "wof:placetype":"postalcode"
},
  "geometry": {"coordinates":[-3.33531396068297,56.60348952675599],"type":"Point"}
}