{
  "type": "Feature",
  "properties": {
    "iso:country":"GB",
    "wof:name":"DG7 2AE",
    "wof:placetype":"postalcode"
},
  "geometry": {"coordinates":[-4.01337693644439,54.92459037494402],"type":"Point"}
}