{
  "type": "Feature",
  "properties": {
    "iso:country":"GB",
    "wof:name":"BH10 4BD",
    "wof:placetype":"postalcode"
},
  "geometry": {"coordinates":[-1.90185574987359,50.75146317690005],"type":"Point"}
}