{
  "type": "Feature",
  "properties": {
    "iso:country":"GB",
    "wof:name":"EH53 0QY",
    "wof:placetype":"postalcode"
},
  "geometry": {"coordinates":[-3.46120335767417,55.88546766137983],"type":"Point"}
}