{
  "type": "Feature",
  "properties": {
    "iso:country": "GB",
    "wof:name": "EH53 0QY",
    "wof:placetype": "postalcode"
  },
  "geometry": {"coordinates":[-3.461203,55.885468],"type":"Point"}
}
