{
  "type": "Feature",
  "properties": {
    "date:inception_lower": "1980-01-01",
    "date:inception_upper": "1980-01-01",
    "iso:country": "GB",
    "wof:name": "SK6 2AN",
    "wof:placetype": "postalcode"
  },
  "geometry": {"coordinates":[-2.115949,53.42249],"type":"Point"}
}
