{
  "type": "Feature",
  "properties": {
    "iso:country":"GB",
    "wof:name":"SK6 2AN",
    "wof:placetype":"postalcode"
},
  "geometry": {"coordinates":[-2.11594863736195,53.42249036320668],"type":"Point"}
}