{
  "type": "Feature",
  "properties": {
    "iso:country": "GB",
    "wof:name": "IP30 9AL",
    "wof:placetype": "postalcode"
  },
  "geometry": {"coordinates":[0.830634,52.228873],"type":"Point"}
}
