{
  "type": "Feature",
  "properties": {
    "iso:country": "GB",
    "wof:name": "DN17 2PR",
    "wof:placetype": "postalcode"
  },
  "geometry": {"coordinates":[-0.658611,53.554636],"type":"Point"}
}
