{
  "type": "Feature",
  "properties": {
    "date:inception_lower": "1980-01-01",
    "date:inception_upper": "1980-01-01",
    "iso:country": "GB",
    "wof:name": "CW2 6SW",
    "wof:placetype": "postalcode"
  },
  "geometry": {"coordinates":[-2.459241,53.077749],"type":"Point"}
}
