{
  "type": "Feature",
  "properties": {
    "iso:country":"GB",
    "wof:name":"BA1 7EG",
    "wof:placetype":"postalcode"
},
  "geometry": {"coordinates":[-2.32031603279898,51.41167125437638],"type":"Point"}
}