{
  "type": "Feature",
  "properties": {
    "date:inception_lower": "1980-01-01",
    "date:inception_upper": "1980-01-01",
    "iso:country": "GB",
    "wof:name": "GL3 4DG",
    "wof:placetype": "postalcode"
  },
  "geometry": {"coordinates":[-2.162951,51.852218],"type":"Point"}
}
