{
  "type": "Feature",
  "properties": {
    "iso:country":"GB",
    "wof:name":"HD3 4DB",
    "wof:placetype":"postalcode"
},
  "geometry": {"coordinates":[-1.81807267593201,53.65322088066136],"type":"Point"}
}