{
  "type": "Feature",
  "properties": {
    "iso:country":"GB",
    "wof:name":"NE25 8EL",
    "wof:placetype":"postalcode"
},
  "geometry": {"coordinates":[-1.46906940540606,55.04234012723232],"type":"Point"}
}