{
  "type": "Feature",
  "properties": {
    "date:inception_lower": "1998-06-01",
    "date:inception_upper": "1998-06-01",
    "iso:country": "GB",
    "wof:name": "YO26 8LD",
    "wof:placetype": "postalcode"
  },
  "geometry": {"coordinates":[-1.203097,53.974292],"type":"Point"}
}
