{
  "type": "Feature",
  "properties": {
    "iso:country":"GB",
    "wof:name":"YO26 8LD",
    "wof:placetype":"postalcode"
},
  "geometry": {"coordinates":[-1.20307413189331,53.97427445998983],"type":"Point"}
}