{
  "type": "Feature",
  "properties": {
    "iso:country": "GB",
    "wof:name": "YO26 8LD",
    "wof:placetype": "postalcode"
  },
  "geometry": {"coordinates":[-1.203097,53.974292],"type":"Point"}
}
