{
  "type": "Feature",
  "properties": {
    "date:inception_lower": "1980-01-01",
    "date:inception_upper": "1980-01-01",
    "iso:country": "GB",
    "wof:name": "UB3 4NH",
    "wof:placetype": "postalcode"
  },
  "geometry": {"coordinates":[-0.413572,51.49817],"type":"Point"}
}
