{
  "type": "Feature",
  "properties": {
    "iso:country":"GB",
    "wof:name":"UB3 4NH",
    "wof:placetype":"postalcode"
},
  "geometry": {"coordinates":[-0.41359272629975,51.49816939787082],"type":"Point"}
}