{
  "type": "Feature",
  "properties": {
    "date:inception_lower":"1997-12-01",
    "date:inception_upper":"1997-12-31",
    "iso:country":"GB",
    "wof:name":"AL5 5EJ",
    "wof:placetype":"postalcode"
},
  "geometry": {"coordinates":[-0.344821,51.828523],"type":"Point"}
}