{
  "type": "Feature",
  "properties": {
    "iso:country":"GB",
    "wof:name":"AL5 5EJ",
    "wof:placetype":"postalcode"
},
  "geometry": {"coordinates":[-0.34482066902255,51.8285229963337],"type":"Point"}
}