{
  "type": "Feature",
  "properties": {
    "date:inception_lower": "2021-08-01",
    "date:inception_upper": "2021-08-01",
    "iso:country": "GB",
    "wof:name": "S80 4UH",
    "wof:placetype": "postalcode"
  },
  "geometry": {"coordinates":[-1.20637,53.284813],"type":"Point"}
}
