{
  "type": "Feature",
  "properties": {
    "iso:country": "GB",
    "wof:name": "PE1 3LL",
    "wof:placetype": "postalcode"
  },
  "geometry": {"coordinates":[-0.253015,52.600078],"type":"Point"}
}
