{
  "type": "Feature",
  "properties": {
    "iso:country":"GB",
    "wof:name":"PE1 3LL",
    "wof:placetype":"postalcode"
},
  "geometry": {"coordinates":[-0.25301529230768,52.60007819947865],"type":"Point"}
}