{
  "type": "Feature",
  "properties": {
    "iso:country": "GB",
    "wof:name": "IV19 1FG",
    "wof:placetype": "postalcode"
  },
  "geometry": {"coordinates":[-4.065486,57.805596],"type":"Point"}
}
