{
  "type": "Feature",
  "properties": {
    "iso:country": "GB",
    "wof:name": "B97 4QU",
    "wof:placetype": "postalcode"
  },
  "geometry": {"coordinates":[-1.942946,52.307168],"type":"Point"}
}
