{
  "type": "Feature",
  "properties": {
    "date:inception_lower":"1980-01-01",
    "date:inception_upper":"1980-01-31",
    "iso:country":"GB",
    "wof:name":"B97 4QU",
    "wof:placetype":"postalcode"
},
  "geometry": {"coordinates":[-1.942946,52.307168],"type":"Point"}
}