{
  "type": "Feature",
  "properties": {
    "iso:country":"GB",
    "wof:name":"B97 4QU",
    "wof:placetype":"postalcode"
},
  "geometry": {"coordinates":[-1.94294591018342,52.3071680576808],"type":"Point"}
}