{
  "type": "Feature",
  "properties": {
    "iso:country":"GB",
    "wof:name":"HR7 4EA",
    "wof:placetype":"postalcode"
},
  "geometry": {"coordinates":[-2.50807952080486,52.19137936858865],"type":"Point"}
}