{
  "type": "Feature",
  "properties": {
    "iso:country":"GB",
    "wof:name":"WD3 7DG",
    "wof:placetype":"postalcode"
},
  "geometry": {"coordinates":[-0.47484349546495,51.64067001100746],"type":"Point"}
}