{
  "type": "Feature",
  "properties": {
    "iso:country": "GB",
    "wof:name": "SK6 4PE",
    "wof:placetype": "postalcode"
  },
  "geometry": {"coordinates":[-2.086772,53.415396],"type":"Point"}
}
