{
  "type": "Feature",
  "properties": {
    "iso:country": "GB",
    "wof:name": "DL12 0UQ",
    "wof:placetype": "postalcode"
  },
  "geometry": {"coordinates":[-2.115131,54.639342],"type":"Point"}
}
