{
  "type": "Feature",
  "properties": {
    "iso:country":"GB",
    "wof:name":"DL12 0UQ",
    "wof:placetype":"postalcode"
},
  "geometry": {"coordinates":[-2.11513131467633,54.63934174748757],"type":"Point"}
}