{
  "type": "Feature",
  "properties": {
    "iso:country": "GB",
    "wof:name": "NN17 1TT",
    "wof:placetype": "postalcode"
  },
  "geometry": {"coordinates":[-0.689399,52.48923],"type":"Point"}
}
