{
  "type": "Feature",
  "properties": {
    "date:inception_lower": "1983-03-01",
    "date:inception_upper": "1983-03-01",
    "iso:country": "GB",
    "wof:name": "NN17 1TT",
    "wof:placetype": "postalcode"
  },
  "geometry": {"coordinates":[-0.689399,52.48923],"type":"Point"}
}
