{
  "type": "Feature",
  "properties": {
    "iso:country":"GB",
    "wof:name":"NE47 5DH",
    "wof:placetype":"postalcode"
},
  "geometry": {"coordinates":[-2.17913952891053,55.00547899704479],"type":"Point"}
}