{
  "type": "Feature",
  "properties": {
    "iso:country": "GB",
    "wof:name": "NE47 5DH",
    "wof:placetype": "postalcode"
  },
  "geometry": {"coordinates":[-2.179139,55.005479],"type":"Point"}
}
