{
  "type": "Feature",
  "properties": {
    "iso:country":"GB",
    "wof:name":"CV3 2PQ",
    "wof:placetype":"postalcode"
},
  "geometry": {"coordinates":[-1.46167169775192,52.39537333018995],"type":"Point"}
}