{
  "type": "Feature",
  "properties": {
    "date:inception_lower": "1980-01-01",
    "date:inception_upper": "1980-01-01",
    "iso:country": "GB",
    "wof:name": "BD20 9EL",
    "wof:placetype": "postalcode"
  },
  "geometry": {"coordinates":[-2.000436,53.932642],"type":"Point"}
}
