{
  "type": "Feature",
  "properties": {
    "iso:country": "GB",
    "wof:name": "KT8 1RX",
    "wof:placetype": "postalcode"
  },
  "geometry": {"coordinates":[-0.368055,51.405274],"type":"Point"}
}
