{
  "type": "Feature",
  "properties": {
    "iso:country": "GB",
    "wof:name": "N10 1AG",
    "wof:placetype": "postalcode"
  },
  "geometry": {"coordinates":[-0.150276,51.601286],"type":"Point"}
}
