{
  "type": "Feature",
  "properties": {
    "iso:country":"GB",
    "wof:name":"N10 1AG",
    "wof:placetype":"postalcode"
},
  "geometry": {"coordinates":[-0.15027574143621,51.60128613401569],"type":"Point"}
}