{
  "type": "Feature",
  "properties": {
    "date:inception_lower": "2010-09-01",
    "date:inception_upper": "2010-09-01",
    "iso:country": "GB",
    "wof:name": "AB41 8BY",
    "wof:placetype": "postalcode"
  },
  "geometry": {"coordinates":[-2.049367,57.3688],"type":"Point"}
}
