{
  "type": "Feature",
  "properties": {
    "iso:country":"GB",
    "wof:name":"AB41 8BY",
    "wof:placetype":"postalcode"
},
  "geometry": {"coordinates":[-2.05094216340531,57.3686169344446],"type":"Point"}
}