{
  "type": "Feature",
  "properties": {
    "iso:country": "GB",
    "wof:name": "AB41 8BY",
    "wof:placetype": "postalcode"
  },
  "geometry": {"coordinates":[-2.050942,57.368617],"type":"Point"}
}
