{
  "type": "Feature",
  "properties": {
    "iso:country": "GB",
    "wof:name": "KY7 5DP",
    "wof:placetype": "postalcode"
  },
  "geometry": {"coordinates":[-3.149689,56.188997],"type":"Point"}
}
