{
  "type": "Feature",
  "properties": {
    "iso:country": "GB",
    "wof:name": "CT21 5RS",
    "wof:placetype": "postalcode"
  },
  "geometry": {"coordinates":[1.121864,51.072403],"type":"Point"}
}
