{
  "type": "Feature",
  "properties": {
    "date:inception_lower": "1980-01-01",
    "date:inception_upper": "1980-01-01",
    "iso:country": "GB",
    "wof:name": "CT21 5RS",
    "wof:placetype": "postalcode"
  },
  "geometry": {"coordinates":[1.121864,51.072403],"type":"Point"}
}
