{
  "type": "Feature",
  "properties": {
    "iso:country":"GB",
    "wof:name":"CT21 5RS",
    "wof:placetype":"postalcode"
},
  "geometry": {"coordinates":[1.12186393924689,51.07240285652598],"type":"Point"}
}