{
  "type": "Feature",
  "properties": {
    "date:inception_lower": "1980-01-01",
    "date:inception_upper": "1980-01-01",
    "iso:country": "GB",
    "wof:name": "IP25 6EZ",
    "wof:placetype": "postalcode"
  },
  "geometry": {"coordinates":[0.828255,52.574589],"type":"Point"}
}
