{
  "type": "Feature",
  "properties": {
    "date:inception_lower": "1995-07-01",
    "date:inception_upper": "1995-07-01",
    "iso:country": "GB",
    "wof:name": "OX7 5LE",
    "wof:placetype": "postalcode"
  },
  "geometry": {"coordinates":[-1.545513,51.945975],"type":"Point"}
}
