{
  "type": "Feature",
  "properties": {
    "iso:country":"GB",
    "wof:name":"OX7 5LE",
    "wof:placetype":"postalcode"
},
  "geometry": {"coordinates":[-1.54551265015943,51.94597536868758],"type":"Point"}
}