{
  "type": "Feature",
  "properties": {
    "date:inception_lower": "1980-01-01",
    "date:inception_upper": "1980-01-01",
    "iso:country": "GB",
    "wof:name": "B21 0DH",
    "wof:placetype": "postalcode"
  },
  "geometry": {"coordinates":[-1.954241,52.505737],"type":"Point"}
}
