{
  "type": "Feature",
  "properties": {
    "iso:country": "GB",
    "wof:name": "B21 0DH",
    "wof:placetype": "postalcode"
  },
  "geometry": {"coordinates":[-1.954241,52.505737],"type":"Point"}
}
