{
  "type": "Feature",
  "properties": {
    "iso:country":"GB",
    "wof:name":"PE7 1TN",
    "wof:placetype":"postalcode"
},
  "geometry": {"coordinates":[-0.11850351934723,52.55264860526042],"type":"Point"}
}