{
  "type": "Feature",
  "properties": {
    "iso:country":"GB",
    "wof:name":"LE2 3BD",
    "wof:placetype":"postalcode"
},
  "geometry": {"coordinates":[-1.11144803430599,52.6174490411074],"type":"Point"}
}