{
  "type": "Feature",
  "properties": {
    "iso:country": "GB",
    "wof:name": "LE2 3BD",
    "wof:placetype": "postalcode"
  },
  "geometry": {"coordinates":[-1.111448,52.617449],"type":"Point"}
}
