{
  "type": "Feature",
  "properties": {
    "iso:country":"GB",
    "wof:name":"W2 2QN",
    "wof:placetype":"postalcode"
},
  "geometry": {"coordinates":[-0.16499950139409,51.51574758233234],"type":"Point"}
}