{
  "type": "Feature",
  "properties": {
    "date:inception_lower": "1980-01-01",
    "date:inception_upper": "1980-01-01",
    "iso:country": "GB",
    "wof:name": "GU1 1YG",
    "wof:placetype": "postalcode"
  },
  "geometry": {"coordinates":[-0.544733,51.257231],"type":"Point"}
}
