{
  "type": "Feature",
  "properties": {
    "iso:country": "GB",
    "wof:name": "AB42 0PD",
    "wof:placetype": "postalcode"
  },
  "geometry": {"coordinates":[-1.84773,57.440011],"type":"Point"}
}
