{
  "type": "Feature",
  "properties": {
    "iso:country":"GB",
    "wof:name":"AB42 0PD",
    "wof:placetype":"postalcode"
},
  "geometry": {"coordinates":[-1.84772982901849,57.44001055569139],"type":"Point"}
}