{
  "type": "Feature",
  "properties": {
    "date:inception_lower": "1996-06-01",
    "date:inception_upper": "1996-06-01",
    "iso:country": "GB",
    "wof:name": "AB42 0PD",
    "wof:placetype": "postalcode"
  },
  "geometry": {"coordinates":[-1.84773,57.440011],"type":"Point"}
}
