{
  "type": "Feature",
  "properties": {
    "date:inception_lower": "2003-01-01",
    "date:inception_upper": "2003-01-01",
    "iso:country": "GB",
    "wof:name": "EX1 1BH",
    "wof:placetype": "postalcode"
  },
  "geometry": {"coordinates":[-3.533605,50.72048],"type":"Point"}
}
