{
  "type": "Feature",
  "properties": {
    "iso:country": "GB",
    "wof:name": "EX1 1BH",
    "wof:placetype": "postalcode"
  },
  "geometry": {"coordinates":[-3.533605,50.72048],"type":"Point"}
}
