{
  "type": "Feature",
  "properties": {
    "iso:country": "GB",
    "wof:name": "G20 8JN",
    "wof:placetype": "postalcode"
  },
  "geometry": {"coordinates":[-4.290276,55.888247],"type":"Point"}
}
