{
  "type": "Feature",
  "properties": {
    "date:inception_lower":"1980-01-01",
    "date:inception_upper":"1980-01-31",
    "iso:country":"GB",
    "wof:name":"TS13 4LR",
    "wof:placetype":"postalcode"
},
  "geometry": {"coordinates":[-0.874534,54.553023],"type":"Point"}
}