{
  "type": "Feature",
  "properties": {
    "iso:country":"GB",
    "wof:name":"TS13 4LR",
    "wof:placetype":"postalcode"
},
  "geometry": {"coordinates":[-0.87453448653189,54.55302331783859],"type":"Point"}
}