{
  "type": "Feature",
  "properties": {
    "iso:country":"GB",
    "wof:name":"ST6 4DB",
    "wof:placetype":"postalcode"
},
  "geometry": {"coordinates":[-2.20732945171181,53.04385599144729],"type":"Point"}
}