{
  "type": "Feature",
  "properties": {
    "iso:country":"GB",
    "wof:name":"B2 4DU",
    "wof:placetype":"postalcode"
},
  "geometry": {"coordinates":[-1.90101124019243,52.47956146362273],"type":"Point"}
}