{
  "type": "Feature",
  "properties": {
    "date:inception_lower": "1987-04-01",
    "date:inception_upper": "1987-04-01",
    "iso:country": "GB",
    "wof:name": "SP8 4QY",
    "wof:placetype": "postalcode"
  },
  "geometry": {"coordinates":[-2.283532,51.036165],"type":"Point"}
}
