{
  "type": "Feature",
  "properties": {
    "date:inception_lower":"1993-08-01",
    "date:inception_upper":"1993-08-31",
    "iso:country":"GB",
    "wof:name":"SL4 1NA",
    "wof:placetype":"postalcode"
},
  "geometry": {"coordinates":[-0.606323,51.485943],"type":"Point"}
}