{
  "type": "Feature",
  "properties": {
    "iso:country": "GB",
    "wof:name": "SL4 1NA",
    "wof:placetype": "postalcode"
  },
  "geometry": {"coordinates":[-0.606323,51.485943],"type":"Point"}
}
