{
  "type": "Feature",
  "properties": {
    "iso:country":"GB",
    "wof:name":"SL4 1NA",
    "wof:placetype":"postalcode"
},
  "geometry": {"coordinates":[-0.6063234390735,51.48594269160743],"type":"Point"}
}