{
  "type": "Feature",
  "properties": {
    "date:inception_lower": "1992-08-01",
    "date:inception_upper": "1992-08-01",
    "iso:country": "GB",
    "wof:name": "BL3 5RS",
    "wof:placetype": "postalcode"
  },
  "geometry": {"coordinates":[-2.457667,53.567948],"type":"Point"}
}
