{
  "type": "Feature",
  "properties": {
    "date:inception_lower":"1999-06-01",
    "date:inception_upper":"1999-06-30",
    "iso:country":"GB",
    "wof:name":"NE23 1DX",
    "wof:placetype":"postalcode"
},
  "geometry": {"coordinates":[-1.581655,55.085211],"type":"Point"}
}