{
  "type": "Feature",
  "properties": {
    "iso:country":"GB",
    "wof:name":"NE23 1DX",
    "wof:placetype":"postalcode"
},
  "geometry": {"coordinates":[-1.58165472474781,55.08521139053703],"type":"Point"}
}