{
  "type": "Feature",
  "properties": {
    "iso:country": "GB",
    "wof:name": "GU31 5QN",
    "wof:placetype": "postalcode"
  },
  "geometry": {"coordinates":[-0.883316,50.966718],"type":"Point"}
}
