{
  "type": "Feature",
  "properties": {
    "date:inception_lower":"2006-05-01",
    "date:inception_upper":"2006-05-31",
    "iso:country":"GB",
    "wof:name":"CW6 9GY",
    "wof:placetype":"postalcode"
},
  "geometry": {"coordinates":[-2.613286,53.126709],"type":"Point"}
}