{
  "type": "Feature",
  "properties": {
    "date:inception_lower": "2006-05-01",
    "date:inception_upper": "2006-05-01",
    "iso:country": "GB",
    "wof:name": "CW6 9GY",
    "wof:placetype": "postalcode"
  },
  "geometry": {"coordinates":[-2.613333,53.126897],"type":"Point"}
}
