{
  "type": "Feature",
  "properties": {
    "iso:country":"GB",
    "wof:name":"TD14 5PH",
    "wof:placetype":"postalcode"
},
  "geometry": {"coordinates":[-2.13147420688703,55.8986889616935],"type":"Point"}
}