{
  "type": "Feature",
  "properties": {
    "iso:country":"GB",
    "wof:name":"HX6 2JF",
    "wof:placetype":"postalcode"
},
  "geometry": {"coordinates":[-1.91291724983737,53.71392518779657],"type":"Point"}
}