{
  "type": "Feature",
  "properties": {
    "iso:country":"GB",
    "wof:name":"DN33 3BE",
    "wof:placetype":"postalcode"
},
  "geometry": {"coordinates":[-0.09359454605752,53.52655731618614],"type":"Point"}
}