{
  "type": "Feature",
  "properties": {
    "iso:country":"GB",
    "wof:name":"LE6 0GZ",
    "wof:placetype":"postalcode"
},
  "geometry": {"coordinates":[-1.22372949119656,52.6586205355569],"type":"Point"}
}