{
  "type": "Feature",
  "properties": {
    "iso:country": "GB",
    "wof:name": "TD12 4AG",
    "wof:placetype": "postalcode"
  },
  "geometry": {"coordinates":[-2.249535,55.65253],"type":"Point"}
}
