{
  "type": "Feature",
  "properties": {
    "date:inception_lower": "1980-01-01",
    "date:inception_upper": "1980-01-01",
    "iso:country": "GB",
    "wof:name": "TD12 4AG",
    "wof:placetype": "postalcode"
  },
  "geometry": {"coordinates":[-2.249535,55.65253],"type":"Point"}
}
