{
  "type": "Feature",
  "properties": {
    "iso:country":"GB",
    "wof:name":"DL14 8NQ",
    "wof:placetype":"postalcode"
},
  "geometry": {"coordinates":[-1.62190014075168,54.66028570798498],"type":"Point"}
}