{
  "type": "Feature",
  "properties": {
    "iso:country":"GB",
    "wof:name":"SL9 9HL",
    "wof:placetype":"postalcode"
},
  "geometry": {"coordinates":[-0.56718245733038,51.60331159603029],"type":"Point"}
}