{
  "type": "Feature",
  "properties": {
    "iso:country": "GB",
    "wof:name": "NN18 8GN",
    "wof:placetype": "postalcode"
  },
  "geometry": {"coordinates":[-0.675529,52.4739],"type":"Point"}
}
