{
  "type": "Feature",
  "properties": {
    "date:inception_lower": "2009-01-01",
    "date:inception_upper": "2009-01-01",
    "iso:country": "GB",
    "wof:name": "NN18 8GN",
    "wof:placetype": "postalcode"
  },
  "geometry": {"coordinates":[-0.675529,52.4739],"type":"Point"}
}
