{
  "type": "Feature",
  "properties": {
    "iso:country": "GB",
    "wof:name": "TQ12 6QG",
    "wof:placetype": "postalcode"
  },
  "geometry": {"coordinates":[-3.643979,50.556354],"type":"Point"}
}
