{
  "type": "Feature",
  "properties": {
    "iso:country":"GB",
    "wof:name":"CV35 9UD",
    "wof:placetype":"postalcode"
},
  "geometry": {"coordinates":[-1.59378993916288,52.20123402574063],"type":"Point"}
}