{
  "type": "Feature",
  "properties": {
    "iso:country": "GB",
    "wof:name": "CV35 9UD",
    "wof:placetype": "postalcode"
  },
  "geometry": {"coordinates":[-1.59379,52.201234],"type":"Point"}
}
