{
  "type": "Feature",
  "properties": {
    "date:inception_lower": "1998-12-01",
    "date:inception_upper": "1998-12-01",
    "iso:country": "GB",
    "wof:name": "CV35 9UD",
    "wof:placetype": "postalcode"
  },
  "geometry": {"coordinates":[-1.59379,52.201234],"type":"Point"}
}
