{
  "type": "Feature",
  "properties": {
    "iso:country":"GB",
    "wof:name":"DN41 7RR",
    "wof:placetype":"postalcode"
},
  "geometry": {"coordinates":[-0.1580500911018,53.57755043551067],"type":"Point"}
}