{
  "type": "Feature",
  "properties": {
    "iso:country": "GB",
    "wof:name": "CW11 2AG",
    "wof:placetype": "postalcode"
  },
  "geometry": {"coordinates":[-2.31891,53.158614],"type":"Point"}
}
