{
  "type": "Feature",
  "properties": {
    "date:inception_lower": "2017-09-01",
    "date:inception_upper": "2017-09-01",
    "iso:country": "GB",
    "wof:name": "CW11 2AG",
    "wof:placetype": "postalcode"
  },
  "geometry": {"coordinates":[-2.31891,53.158614],"type":"Point"}
}
