{
  "type": "Feature",
  "properties": {
    "iso:country":"GB",
    "wof:name":"NG8 3JD",
    "wof:placetype":"postalcode"
},
  "geometry": {"coordinates":[-1.21229734898735,52.96097600822594],"type":"Point"}
}