{
  "type": "Feature",
  "properties": {
    "iso:country": "GB",
    "wof:name": "BA5 3HF",
    "wof:placetype": "postalcode"
  },
  "geometry": {"coordinates":[-2.589194,51.203455],"type":"Point"}
}
