{
  "type": "Feature",
  "properties": {
    "iso:country":"GB",
    "wof:name":"E10 6AD",
    "wof:placetype":"postalcode"
},
  "geometry": {"coordinates":[-0.00877803600686,51.57388160116268],"type":"Point"}
}