{
  "type": "Feature",
  "properties": {
    "iso:country":"GB",
    "wof:name":"G75 9AP",
    "wof:placetype":"postalcode"
},
  "geometry": {"coordinates":[-4.19225813630067,55.75086865867284],"type":"Point"}
}