{
  "type": "Feature",
  "properties": {
    "iso:country": "GB",
    "wof:name": "RG12 0QJ",
    "wof:placetype": "postalcode"
  },
  "geometry": {"coordinates":[-0.742723,51.39448],"type":"Point"}
}
