{
  "type": "Feature",
  "properties": {
    "iso:country":"GB",
    "wof:name":"RG12 0QJ",
    "wof:placetype":"postalcode"
},
  "geometry": {"coordinates":[-0.74272347352215,51.39447950740625],"type":"Point"}
}