{
  "type": "Feature",
  "properties": {
    "iso:country":"GB",
    "wof:name":"CV31 2ET",
    "wof:placetype":"postalcode"
},
  "geometry": {"coordinates":[-1.52701434214464,52.26284846660866],"type":"Point"}
}