{
  "type": "Feature",
  "properties": {
    "iso:country":"GB",
    "wof:name":"BS7 8PP",
    "wof:placetype":"postalcode"
},
  "geometry": {"coordinates":[-2.59073782781766,51.48010720325448],"type":"Point"}
}