{
  "type": "Feature",
  "properties": {
    "iso:country":"GB",
    "wof:name":"NW9 7NB",
    "wof:placetype":"postalcode"
},
  "geometry": {"coordinates":[-0.25026303659866,51.57294686863498],"type":"Point"}
}