{
  "type": "Feature",
  "properties": {
    "iso:country": "GB",
    "wof:name": "PE28 2XR",
    "wof:placetype": "postalcode"
  },
  "geometry": {"coordinates":[-0.035485,52.41768],"type":"Point"}
}
