{
  "type": "Feature",
  "properties": {
    "iso:country":"GB",
    "wof:name":"PE28 2XR",
    "wof:placetype":"postalcode"
},
  "geometry": {"coordinates":[-0.03550798354302,52.41766241120135],"type":"Point"}
}