{
  "type": "Feature",
  "properties": {
    "iso:country":"GB",
    "wof:name":"GU51 2RT",
    "wof:placetype":"postalcode"
},
  "geometry": {"coordinates":[-0.81171573984492,51.29348033600261],"type":"Point"}
}