{
  "type": "Feature",
  "properties": {
    "iso:country": "GB",
    "wof:name": "GU51 2RT",
    "wof:placetype": "postalcode"
  },
  "geometry": {"coordinates":[-0.811716,51.29348],"type":"Point"}
}
