{
  "type": "Feature",
  "properties": {
    "iso:country":"GB",
    "wof:name":"HX2 7PJ",
    "wof:placetype":"postalcode"
},
  "geometry": {"coordinates":[-1.88845763450642,53.71585538311624],"type":"Point"}
}