{
  "type": "Feature",
  "properties": {
    "iso:country": "GB",
    "wof:name": "HX2 7PJ",
    "wof:placetype": "postalcode"
  },
  "geometry": {"coordinates":[-1.888458,53.715855],"type":"Point"}
}
