{
  "type": "Feature",
  "properties": {
    "date:inception_lower": "1980-01-01",
    "date:inception_upper": "1980-01-01",
    "iso:country": "GB",
    "wof:name": "HX2 7PJ",
    "wof:placetype": "postalcode"
  },
  "geometry": {"coordinates":[-1.888399,53.715852],"type":"Point"}
}
