{
  "type": "Feature",
  "properties": {
    "iso:country":"GB",
    "wof:name":"CO4 3NX",
    "wof:placetype":"postalcode"
},
  "geometry": {"coordinates":[0.93491710350786,51.89376376656658],"type":"Point"}
}