{
  "type": "Feature",
  "properties": {
    "date:inception_lower":"1980-01-01",
    "date:inception_upper":"1980-01-31",
    "iso:country":"GB",
    "wof:name":"MK17 9BE",
    "wof:placetype":"postalcode"
},
  "geometry": {"coordinates":[-0.690808,51.968186],"type":"Point"}
}