{
  "type": "Feature",
  "properties": {
    "iso:country":"GB",
    "wof:name":"MK17 9BE",
    "wof:placetype":"postalcode"
},
  "geometry": {"coordinates":[-0.69080847506382,51.96818559011249],"type":"Point"}
}