{
  "type": "Feature",
  "properties": {
    "date:inception_lower": "2008-07-01",
    "date:inception_upper": "2008-07-01",
    "iso:country": "GB",
    "wof:name": "MK9 2FE",
    "wof:placetype": "postalcode"
  },
  "geometry": {"coordinates":[-0.760271,52.036067],"type":"Point"}
}
