{
  "type": "Feature",
  "properties": {
    "iso:country":"GB",
    "wof:name":"BL0 9PH",
    "wof:placetype":"postalcode"
},
  "geometry": {"coordinates":[-2.32589691877042,53.64075340735066],"type":"Point"}
}