{
  "type": "Feature",
  "properties": {
    "date:inception_lower": "1980-01-01",
    "date:inception_upper": "1980-01-01",
    "iso:country": "GB",
    "wof:name": "DN8 4DP",
    "wof:placetype": "postalcode"
  },
  "geometry": {"coordinates":[-0.966073,53.618506],"type":"Point"}
}
