{
  "type": "Feature",
  "properties": {
    "iso:country":"GB",
    "wof:name":"DN8 4DP",
    "wof:placetype":"postalcode"
},
  "geometry": {"coordinates":[-0.96607302138445,53.61850626153059],"type":"Point"}
}