{
  "type": "Feature",
  "properties": {
    "iso:country":"GB",
    "wof:name":"CO9 1BB",
    "wof:placetype":"postalcode"
},
  "geometry": {"coordinates":[0.62986484475668,51.93449771881906],"type":"Point"}
}