{
  "type": "Feature",
  "properties": {
    "iso:country": "GB",
    "wof:name": "CO9 1BB",
    "wof:placetype": "postalcode"
  },
  "geometry": {"coordinates":[0.629775,51.934942],"type":"Point"}
}
