{
  "type": "Feature",
  "properties": {
    "iso:country":"GB",
    "wof:name":"E4 8AR",
    "wof:placetype":"postalcode"
},
  "geometry": {"coordinates":[-0.02388930890835,51.62174351006271],"type":"Point"}
}