{
  "type": "Feature",
  "properties": {
    "iso:country":"GB",
    "wof:name":"SG6 3JH",
    "wof:placetype":"postalcode"
},
  "geometry": {"coordinates":[-0.22988523424203,51.97454963546735],"type":"Point"}
}