{
  "type": "Feature",
  "properties": {
    "iso:country": "GB",
    "wof:name": "TW18 1BY",
    "wof:placetype": "postalcode"
  },
  "geometry": {"coordinates":[-0.491713,51.429843],"type":"Point"}
}
