{
  "type": "Feature",
  "properties": {
    "iso:country":"GB",
    "wof:name":"TW18 1BY",
    "wof:placetype":"postalcode"
},
  "geometry": {"coordinates":[-0.4917129158584,51.42984305769742],"type":"Point"}
}