{
  "type": "Feature",
  "properties": {
    "iso:country":"GB",
    "wof:name":"SS6 8HB",
    "wof:placetype":"postalcode"
},
  "geometry": {"coordinates":[0.62211235275754,51.59448292852336],"type":"Point"}
}