{
  "type": "Feature",
  "properties": {
    "iso:country": "GB",
    "wof:name": "SG7 6DR",
    "wof:placetype": "postalcode"
  },
  "geometry": {"coordinates":[-0.185253,51.989147],"type":"Point"}
}
