{
  "type": "Feature",
  "properties": {
    "date:inception_lower": "2017-05-01",
    "date:inception_upper": "2017-05-01",
    "iso:country": "GB",
    "wof:name": "OX10 6ET",
    "wof:placetype": "postalcode"
  },
  "geometry": {"coordinates":[-1.120063,51.572056],"type":"Point"}
}
