{
  "type": "Feature",
  "properties": {
    "iso:country":"GB",
    "wof:name":"LN13 0HY",
    "wof:placetype":"postalcode"
},
  "geometry": {"coordinates":[0.1833912196849,53.28327577800648],"type":"Point"}
}