{
  "type": "Feature",
  "properties": {
    "date:inception_lower": "1980-01-01",
    "date:inception_upper": "1980-01-01",
    "iso:country": "GB",
    "wof:name": "LN13 0HY",
    "wof:placetype": "postalcode"
  },
  "geometry": {"coordinates":[0.183391,53.283276],"type":"Point"}
}
