{
  "type": "Feature",
  "properties": {
    "iso:country": "GB",
    "wof:name": "SR7 8BH",
    "wof:placetype": "postalcode"
  },
  "geometry": {"coordinates":[-1.361405,54.83428],"type":"Point"}
}
