{
  "type": "Feature",
  "properties": {
    "iso:country":"GB",
    "wof:name":"SR7 8BH",
    "wof:placetype":"postalcode"
},
  "geometry": {"coordinates":[-1.36139119873024,54.83427240745225],"type":"Point"}
}