{
  "type": "Feature",
  "properties": {
    "iso:country":"GB",
    "wof:name":"DD1 5QT",
    "wof:placetype":"postalcode"
},
  "geometry": {"coordinates":[-2.99008596547551,56.46249868877],"type":"Point"}
}