{
  "type": "Feature",
  "properties": {
    "iso:country":"GB",
    "wof:name":"CW1 4NE",
    "wof:placetype":"postalcode"
},
  "geometry": {"coordinates":[-2.43467167146332,53.11634156863054],"type":"Point"}
}