{
  "type": "Feature",
  "properties": {
    "iso:country": "GB",
    "wof:name": "RG9 4BD",
    "wof:placetype": "postalcode"
  },
  "geometry": {"coordinates":[-0.932543,51.525632],"type":"Point"}
}
