{
  "type": "Feature",
  "properties": {
    "date:inception_lower": "2019-02-01",
    "date:inception_upper": "2019-02-01",
    "iso:country": "GB",
    "wof:name": "RG9 4BD",
    "wof:placetype": "postalcode"
  },
  "geometry": {"coordinates":[-0.932543,51.525632],"type":"Point"}
}
