{
  "type": "Feature",
  "properties": {
    "iso:country": "GB",
    "wof:name": "RG9 4BD",
    "wof:placetype": "postalcode"
  },
  "geometry": {"coordinates":[-0.932703,51.525579],"type":"Point"}
}
