{
  "type": "Feature",
  "properties": {
    "iso:country":"GB",
    "wof:name":"IP8 3BB",
    "wof:placetype":"postalcode"
},
  "geometry": {"coordinates":[1.10017983505092,52.06068577036772],"type":"Point"}
}