{
  "type": "Feature",
  "properties": {
    "iso:country":"GB",
    "wof:name":"EX39 6AJ",
    "wof:placetype":"postalcode"
},
  "geometry": {"coordinates":[-4.45257641775083,50.99162969618829],"type":"Point"}
}