{
  "type": "Feature",
  "properties": {
    "date:inception_lower": "1980-01-01",
    "date:inception_upper": "1980-01-01",
    "iso:country": "GB",
    "wof:name": "YO11 1QN",
    "wof:placetype": "postalcode"
  },
  "geometry": {"coordinates":[-0.392464,54.284486],"type":"Point"}
}
