{
  "type": "Feature",
  "properties": {
    "iso:country":"GB",
    "wof:name":"SY1 4SE",
    "wof:placetype":"postalcode"
},
  "geometry": {"coordinates":[-2.7378998026468,52.72743670444504],"type":"Point"}
}