{
  "type": "Feature",
  "properties": {
    "date:inception_lower":"1980-01-01",
    "date:inception_upper":"1980-01-31",
    "iso:country":"GB",
    "wof:name":"SY1 4SE",
    "wof:placetype":"postalcode"
},
  "geometry": {"coordinates":[-2.7379,52.727437],"type":"Point"}
}