{
  "type": "Feature",
  "properties": {
    "iso:country":"GB",
    "wof:name":"CV11 4GJ",
    "wof:placetype":"postalcode"
},
  "geometry": {"coordinates":[-1.44477377045305,52.50170220227144],"type":"Point"}
}