{
  "type": "Feature",
  "properties": {
    "iso:country": "GB",
    "wof:name": "M41 9JN",
    "wof:placetype": "postalcode"
  },
  "geometry": {"coordinates":[-2.353081,53.447345],"type":"Point"}
}
