{
  "type": "Feature",
  "properties": {
    "iso:country":"GB",
    "wof:name":"M41 9JN",
    "wof:placetype":"postalcode"
},
  "geometry": {"coordinates":[-2.35308119170286,53.44734500731843],"type":"Point"}
}