{
  "type": "Feature",
  "properties": {
    "date:inception_lower": "1987-10-01",
    "date:inception_upper": "1987-10-01",
    "iso:country": "GB",
    "wof:name": "UB8 3TW",
    "wof:placetype": "postalcode"
  },
  "geometry": {"coordinates":[-0.462666,51.530432],"type":"Point"}
}
