{
  "type": "Feature",
  "properties": {
    "iso:country": "GB",
    "wof:name": "DD1 4EF",
    "wof:placetype": "postalcode"
  },
  "geometry": {"coordinates":[-2.975624,56.458462],"type":"Point"}
}
