{
  "type": "Feature",
  "properties": {
    "date:inception_lower": "2016-10-01",
    "date:inception_upper": "2016-10-01",
    "iso:country": "GB",
    "wof:name": "DD1 4EF",
    "wof:placetype": "postalcode"
  },
  "geometry": {"coordinates":[-2.975624,56.458462],"type":"Point"}
}
