{
  "type": "Feature",
  "properties": {
    "iso:country":"GB",
    "wof:name":"TS19 8XQ",
    "wof:placetype":"postalcode"
},
  "geometry": {"coordinates":[-1.36082617252879,54.57784971503772],"type":"Point"}
}