{
  "type": "Feature",
  "properties": {
    "iso:country":"GB",
    "wof:name":"BB10 2HZ",
    "wof:placetype":"postalcode"
},
  "geometry": {"coordinates":[-2.20063925642726,53.81139817059972],"type":"Point"}
}