{
  "type": "Feature",
  "properties": {
    "date:inception_lower":"1980-01-01",
    "date:inception_upper":"1980-01-31",
    "iso:country":"GB",
    "wof:name":"BB10 2HZ",
    "wof:placetype":"postalcode"
},
  "geometry": {"coordinates":[-2.200639,53.811398],"type":"Point"}
}