{
  "type": "Feature",
  "properties": {
    "iso:country":"GB",
    "wof:name":"SN11 8XS",
    "wof:placetype":"postalcode"
},
  "geometry": {"coordinates":[-1.94861300766308,51.4310257836307],"type":"Point"}
}