{
  "type": "Feature",
  "properties": {
    "iso:country":"GB",
    "wof:name":"HU3 6PR",
    "wof:placetype":"postalcode"
},
  "geometry": {"coordinates":[-0.3796235050015,53.74951159467913],"type":"Point"}
}