{
  "type": "Feature",
  "properties": {
    "iso:country": "GB",
    "wof:name": "RM2 5RD",
    "wof:placetype": "postalcode"
  },
  "geometry": {"coordinates":[0.185819,51.592579],"type":"Point"}
}
