{
  "type": "Feature",
  "properties": {
    "iso:country":"GB",
    "wof:name":"LL65 2LX",
    "wof:placetype":"postalcode"
},
  "geometry": {"coordinates":[-4.61954549667488,53.28704753676885],"type":"Point"}
}