{
  "type": "Feature",
  "properties": {
    "iso:country":"GB",
    "wof:name":"DL5 7DX",
    "wof:placetype":"postalcode"
},
  "geometry": {"coordinates":[-1.59335860541833,54.61863852937557],"type":"Point"}
}