{
  "type": "Feature",
  "properties": {
    "iso:country":"GB",
    "wof:name":"BA3 5HL",
    "wof:placetype":"postalcode"
},
  "geometry": {"coordinates":[-2.47882640834077,51.23006248428723],"type":"Point"}
}