{
  "type": "Feature",
  "properties": {
    "iso:country": "GB",
    "wof:name": "BA3 5HL",
    "wof:placetype": "postalcode"
  },
  "geometry": {"coordinates":[-2.478826,51.230062],"type":"Point"}
}
