{
  "type": "Feature",
  "properties": {
    "iso:country":"GB",
    "wof:name":"BN22 0QE",
    "wof:placetype":"postalcode"
},
  "geometry": {"coordinates":[0.26083826115974,50.80672999507643],"type":"Point"}
}