{
  "type": "Feature",
  "properties": {
    "date:inception_lower":"2004-03-01",
    "date:inception_upper":"2004-03-31",
    "iso:country":"GB",
    "wof:name":"S6 1RN",
    "wof:placetype":"postalcode"
},
  "geometry": {"coordinates":[-1.523077,53.418962],"type":"Point"}
}