{
  "type": "Feature",
  "properties": {
    "iso:country":"GB",
    "wof:name":"S6 1RN",
    "wof:placetype":"postalcode"
},
  "geometry": {"coordinates":[-1.52307753144544,53.4189621224985],"type":"Point"}
}