{
  "type": "Feature",
  "properties": {
    "date:inception_lower": "1980-01-01",
    "date:inception_upper": "1980-01-01",
    "iso:country": "GB",
    "wof:name": "SK7 2AN",
    "wof:placetype": "postalcode"
  },
  "geometry": {"coordinates":[-2.175694,53.365609],"type":"Point"}
}
