{
  "type": "Feature",
  "properties": {
    "iso:country":"GB",
    "wof:name":"BA14 8QQ",
    "wof:placetype":"postalcode"
},
  "geometry": {"coordinates":[-2.20500925516551,51.32673374960572],"type":"Point"}
}