{
  "type": "Feature",
  "properties": {
    "iso:country":"GB",
    "wof:name":"LS13 4DX",
    "wof:placetype":"postalcode"
},
  "geometry": {"coordinates":[-1.6380077424674,53.80219477784193],"type":"Point"}
}