{
  "type": "Feature",
  "properties": {
    "date:inception_lower": "1980-01-01",
    "date:inception_upper": "1980-01-01",
    "iso:country": "GB",
    "wof:name": "CR4 2LP",
    "wof:placetype": "postalcode"
  },
  "geometry": {"coordinates":[-0.156209,51.409992],"type":"Point"}
}
