{
  "type": "Feature",
  "properties": {
    "iso:country":"GB",
    "wof:name":"CR4 2LP",
    "wof:placetype":"postalcode"
},
  "geometry": {"coordinates":[-0.15620889563776,51.40999212626371],"type":"Point"}
}