{
  "type": "Feature",
  "properties": {
    "date:inception_lower": "1980-01-01",
    "date:inception_upper": "1980-01-01",
    "iso:country": "GB",
    "wof:name": "CA8 2LF",
    "wof:placetype": "postalcode"
  },
  "geometry": {"coordinates":[-2.649468,54.959762],"type":"Point"}
}
