{
  "type": "Feature",
  "properties": {
    "iso:country":"GB",
    "wof:name":"NR32 3BY",
    "wof:placetype":"postalcode"
},
  "geometry": {"coordinates":[1.71982024633088,52.48141633948705],"type":"Point"}
}