{
  "type": "Feature",
  "properties": {
    "iso:country":"GB",
    "wof:name":"DN36 4TD",
    "wof:placetype":"postalcode"
},
  "geometry": {"coordinates":[-0.0525087912374,53.52565234306256],"type":"Point"}
}