{
  "type": "Feature",
  "properties": {
    "date:inception_lower": "1980-01-01",
    "date:inception_upper": "1980-01-01",
    "iso:country": "GB",
    "wof:name": "DN36 4TD",
    "wof:placetype": "postalcode"
  },
  "geometry": {"coordinates":[-0.052509,53.525652],"type":"Point"}
}
