{
  "type": "Feature",
  "properties": {
    "iso:country":"GB",
    "wof:name":"CF72 8HG",
    "wof:placetype":"postalcode"
},
  "geometry": {"coordinates":[-3.36475682313254,51.53647004608838],"type":"Point"}
}