{
  "type": "Feature",
  "properties": {
    "iso:country": "GB",
    "wof:name": "CF72 8HG",
    "wof:placetype": "postalcode"
  },
  "geometry": {"coordinates":[-3.364757,51.53647],"type":"Point"}
}
