{
  "type": "Feature",
  "properties": {
    "date:inception_lower": "1980-01-01",
    "date:inception_upper": "1980-01-01",
    "iso:country": "GB",
    "wof:name": "GL6 9JL",
    "wof:placetype": "postalcode"
  },
  "geometry": {"coordinates":[-2.184532,51.70484],"type":"Point"}
}
