{
  "type": "Feature",
  "properties": {
    "iso:country": "GB",
    "wof:name": "TA19 9PE",
    "wof:placetype": "postalcode"
  },
  "geometry": {"coordinates":[-2.921779,50.928604],"type":"Point"}
}
