{
  "type": "Feature",
  "properties": {
    "date:inception_lower": "2001-06-01",
    "date:inception_upper": "2001-06-01",
    "iso:country": "GB",
    "wof:name": "TA19 9PE",
    "wof:placetype": "postalcode"
  },
  "geometry": {"coordinates":[-2.921779,50.928604],"type":"Point"}
}
