{
  "type": "Feature",
  "properties": {
    "date:inception_lower": "1980-01-01",
    "date:inception_upper": "1980-01-01",
    "iso:country": "GB",
    "wof:name": "WN6 0SN",
    "wof:placetype": "postalcode"
  },
  "geometry": {"coordinates":[-2.687981,53.591284],"type":"Point"}
}
