{
  "type": "Feature",
  "properties": {
    "iso:country":"GB",
    "wof:name":"WN6 0SN",
    "wof:placetype":"postalcode"
},
  "geometry": {"coordinates":[-2.68798145732793,53.59128417252175],"type":"Point"}
}