{
  "type": "Feature",
  "properties": {
    "iso:country":"GB",
    "wof:name":"NE10 9AN",
    "wof:placetype":"postalcode"
},
  "geometry": {"coordinates":[-1.55718019359345,54.9422349553965],"type":"Point"}
}