{
  "type": "Feature",
  "properties": {
    "date:inception_lower": "2023-07-01",
    "date:inception_upper": "2023-07-01",
    "iso:country": "GB",
    "wof:name": "LE12 5FG",
    "wof:placetype": "postalcode"
  },
  "geometry": {"coordinates":[-1.121643,52.785072],"type":"Point"}
}
