{
  "type": "Feature",
  "properties": {
    "iso:country":"GB",
    "wof:name":"DA3 8EQ",
    "wof:placetype":"postalcode"
},
  "geometry": {"coordinates":[0.29282054140947,51.38846833092514],"type":"Point"}
}