{
  "type": "Feature",
  "properties": {
    "iso:country":"GB",
    "wof:name":"NG13 9HW",
    "wof:placetype":"postalcode"
},
  "geometry": {"coordinates":[-0.92609468358327,52.90828520834673],"type":"Point"}
}