{
  "type": "Feature",
  "properties": {
    "iso:country": "GB",
    "wof:name": "NG13 9HW",
    "wof:placetype": "postalcode"
  },
  "geometry": {"coordinates":[-0.926095,52.908285],"type":"Point"}
}
