{
  "type": "Feature",
  "properties": {
    "date:inception_lower":"2013-07-01",
    "date:inception_upper":"2013-07-31",
    "iso:country":"GB",
    "wof:name":"NG13 9HW",
    "wof:placetype":"postalcode"
},
  "geometry": {"coordinates":[-0.926095,52.908285],"type":"Point"}
}