{
  "type": "Feature",
  "properties": {
    "date:inception_lower": "1980-01-01",
    "date:inception_upper": "1980-01-01",
    "iso:country": "GB",
    "wof:name": "GU9 7BE",
    "wof:placetype": "postalcode"
  },
  "geometry": {"coordinates":[-0.809741,51.213924],"type":"Point"}
}
