{
  "type": "Feature",
  "properties": {
    "iso:country": "GB",
    "wof:name": "KT17 4PF",
    "wof:placetype": "postalcode"
  },
  "geometry": {"coordinates":[-0.262624,51.3335],"type":"Point"}
}
