{
  "type": "Feature",
  "properties": {
    "iso:country": "GB",
    "wof:name": "CV4 9YA",
    "wof:placetype": "postalcode"
  },
  "geometry": {"coordinates":[-1.575166,52.400321],"type":"Point"}
}
