{
  "type": "Feature",
  "properties": {
    "iso:country":"GB",
    "wof:name":"CV4 9YA",
    "wof:placetype":"postalcode"
},
  "geometry": {"coordinates":[-1.57516589559948,52.40032148882268],"type":"Point"}
}