{
  "type": "Feature",
  "properties": {
    "date:inception_lower": "1980-01-01",
    "date:inception_upper": "1980-01-01",
    "iso:country": "GB",
    "wof:name": "SA19 7NJ",
    "wof:placetype": "postalcode"
  },
  "geometry": {"coordinates":[-4.040517,51.997628],"type":"Point"}
}
