{
  "type": "Feature",
  "properties": {
    "date:inception_lower": "2005-04-01",
    "date:inception_upper": "2005-04-01",
    "iso:country": "GB",
    "wof:name": "PL31 1RJ",
    "wof:placetype": "postalcode"
  },
  "geometry": {"coordinates":[-4.734502,50.468324],"type":"Point"}
}
