{
  "type": "Feature",
  "properties": {
    "iso:country": "GB",
    "wof:name": "HP5 2QY",
    "wof:placetype": "postalcode"
  },
  "geometry": {"coordinates":[-0.623554,51.712643],"type":"Point"}
}
