{
  "type": "Feature",
  "properties": {
    "date:inception_lower":"1980-01-01",
    "date:inception_upper":"1980-01-31",
    "iso:country":"GB",
    "wof:name":"HP5 2QY",
    "wof:placetype":"postalcode"
},
  "geometry": {"coordinates":[-0.623554,51.712643],"type":"Point"}
}