{
  "type": "Feature",
  "properties": {
    "iso:country": "GB",
    "wof:name": "GU30 7PT",
    "wof:placetype": "postalcode"
  },
  "geometry": {"coordinates":[-0.8048,51.083739],"type":"Point"}
}
