{
  "type": "Feature",
  "properties": {
    "date:inception_lower": "1980-01-01",
    "date:inception_upper": "1980-01-01",
    "iso:country": "GB",
    "wof:name": "FY5 3SY",
    "wof:placetype": "postalcode"
  },
  "geometry": {"coordinates":[-3.019426,53.871648],"type":"Point"}
}
