{
  "type": "Feature",
  "properties": {
    "iso:country":"GB",
    "wof:name":"FY5 3SY",
    "wof:placetype":"postalcode"
},
  "geometry": {"coordinates":[-3.01945320414922,53.87127359930544],"type":"Point"}
}