{
  "type": "Feature",
  "properties": {
    "iso:country": "GB",
    "wof:name": "CA10 2ET",
    "wof:placetype": "postalcode"
  },
  "geometry": {"coordinates":[-2.721999,54.632876],"type":"Point"}
}
