{
  "type": "Feature",
  "properties": {
    "iso:country":"GB",
    "wof:name":"BS14 9BB",
    "wof:placetype":"postalcode"
},
  "geometry": {"coordinates":[-2.56179202004873,51.42254118606743],"type":"Point"}
}