{
  "type": "Feature",
  "properties": {
    "date:inception_lower": "1980-01-01",
    "date:inception_upper": "1980-01-01",
    "iso:country": "GB",
    "wof:name": "CW9 6JX",
    "wof:placetype": "postalcode"
  },
  "geometry": {"coordinates":[-2.518735,53.320081],"type":"Point"}
}
