{
  "type": "Feature",
  "properties": {
    "iso:country": "GB",
    "wof:name": "TS13 4XA",
    "wof:placetype": "postalcode"
  },
  "geometry": {"coordinates":[-0.890103,54.555935],"type":"Point"}
}
