{
  "type": "Feature",
  "properties": {
    "date:inception_lower":"2016-06-01",
    "date:inception_upper":"2016-06-30",
    "iso:country":"GB",
    "wof:name":"E14 9BP",
    "wof:placetype":"postalcode"
},
  "geometry": {"coordinates":[-0.019634,51.498725],"type":"Point"}
}