{
  "type": "Feature",
  "properties": {
    "iso:country": "GB",
    "wof:name": "TS21 1FR",
    "wof:placetype": "postalcode"
  },
  "geometry": {"coordinates":[-1.496412,54.580954],"type":"Point"}
}
