{
  "type": "Feature",
  "properties": {
    "date:inception_lower": "2018-09-01",
    "date:inception_upper": "2018-09-01",
    "iso:country": "GB",
    "wof:name": "TS21 1FR",
    "wof:placetype": "postalcode"
  },
  "geometry": {"coordinates":[-1.479265,54.576523],"type":"Point"}
}
