{
  "type": "Feature",
  "properties": {
    "iso:country":"GB",
    "wof:name":"CB1 9GS",
    "wof:placetype":"postalcode"
},
  "geometry": {"coordinates":[0.1835029965636,52.19435524940782],"type":"Point"}
}