{
  "type": "Feature",
  "properties": {
    "date:inception_lower": "2021-02-01",
    "date:inception_upper": "2021-02-01",
    "iso:country": "GB",
    "wof:name": "WV15 6BF",
    "wof:placetype": "postalcode"
  },
  "geometry": {"coordinates":[-2.337319,52.480888],"type":"Point"}
}
