{
  "type": "Feature",
  "properties": {
    "iso:country":"GB",
    "wof:name":"CF15 7LE",
    "wof:placetype":"postalcode"
},
  "geometry": {"coordinates":[-3.24820389689592,51.53037696144919],"type":"Point"}
}