{
  "type": "Feature",
  "properties": {
    "iso:country":"GB",
    "wof:name":"S5 6WQ",
    "wof:placetype":"postalcode"
},
  "geometry": {"coordinates":[-1.44749844134718,53.40966589949866],"type":"Point"}
}