{
  "type": "Feature",
  "properties": {
    "iso:country": "GB",
    "wof:name": "DE6 1PP",
    "wof:placetype": "postalcode"
  },
  "geometry": {"coordinates":[-1.658065,53.059026],"type":"Point"}
}
