{
  "type": "Feature",
  "properties": {
    "date:inception_lower": "2010-09-01",
    "date:inception_upper": "2010-09-01",
    "iso:country": "GB",
    "wof:name": "DE6 1PP",
    "wof:placetype": "postalcode"
  },
  "geometry": {"coordinates":[-1.658065,53.059026],"type":"Point"}
}
