{
  "type": "Feature",
  "properties": {
    "iso:country": "GB",
    "wof:name": "DA7 6QT",
    "wof:placetype": "postalcode"
  },
  "geometry": {"coordinates":[0.169054,51.466915],"type":"Point"}
}
