{
  "type": "Feature",
  "properties": {
    "iso:country":"GB",
    "wof:name":"DA7 6QT",
    "wof:placetype":"postalcode"
},
  "geometry": {"coordinates":[0.16905418424111,51.4669150610444],"type":"Point"}
}