{
  "type": "Feature",
  "properties": {
    "iso:country":"GB",
    "wof:name":"B31 5EY",
    "wof:placetype":"postalcode"
},
  "geometry": {"coordinates":[-2.000676075129,52.40398762154009],"type":"Point"}
}