{
  "type": "Feature",
  "properties": {
    "iso:country":"GB",
    "wof:name":"IG5 0QD",
    "wof:placetype":"postalcode"
},
  "geometry": {"coordinates":[0.07078188724976,51.59575952418117],"type":"Point"}
}