{
  "type": "Feature",
  "properties": {
    "iso:country":"GB",
    "wof:name":"NN10 0GA",
    "wof:placetype":"postalcode"
},
  "geometry": {"coordinates":[-0.59099149959643,52.27579054147508],"type":"Point"}
}