{
  "type": "Feature",
  "properties": {
    "iso:country": "GB",
    "wof:name": "NN10 0GA",
    "wof:placetype": "postalcode"
  },
  "geometry": {"coordinates":[-0.590991,52.275791],"type":"Point"}
}
