{
  "type": "Feature",
  "properties": {
    "iso:country": "GB",
    "wof:name": "WN2 2SX",
    "wof:placetype": "postalcode"
  },
  "geometry": {"coordinates":[-2.577767,53.55452],"type":"Point"}
}
