{
  "type": "Feature",
  "properties": {
    "iso:country":"GB",
    "wof:name":"WN2 2SX",
    "wof:placetype":"postalcode"
},
  "geometry": {"coordinates":[-2.57776656772135,53.55452042694641],"type":"Point"}
}