{
  "type": "Feature",
  "properties": {
    "date:inception_lower": "1980-01-01",
    "date:inception_upper": "1980-01-01",
    "iso:country": "GB",
    "wof:name": "RM13 8NH",
    "wof:placetype": "postalcode"
  },
  "geometry": {"coordinates":[0.180502,51.529736],"type":"Point"}
}
