{
  "type": "Feature",
  "properties": {
    "iso:country":"GB",
    "wof:name":"RM13 8NH",
    "wof:placetype":"postalcode"
},
  "geometry": {"coordinates":[0.18045913564942,51.52973489748803],"type":"Point"}
}