{
  "type": "Feature",
  "properties": {
    "iso:country":"GB",
    "wof:name":"KA1 3PG",
    "wof:placetype":"postalcode"
},
  "geometry": {"coordinates":[-4.48580737738884,55.59382605066196],"type":"Point"}
}