{
  "type": "Feature",
  "properties": {
    "iso:country":"GB",
    "wof:name":"TA10 9NX",
    "wof:placetype":"postalcode"
},
  "geometry": {"coordinates":[-2.76238210899569,51.03116144357834],"type":"Point"}
}