{
  "type": "Feature",
  "properties": {
    "date:inception_lower": "2006-01-01",
    "date:inception_upper": "2006-01-01",
    "iso:country": "GB",
    "wof:name": "TA10 9NX",
    "wof:placetype": "postalcode"
  },
  "geometry": {"coordinates":[-2.762382,51.031161],"type":"Point"}
}
