{
  "type": "Feature",
  "properties": {
    "iso:country": "GB",
    "wof:name": "CF5 6LQ",
    "wof:placetype": "postalcode"
  },
  "geometry": {"coordinates":[-3.32125,51.475013],"type":"Point"}
}
