{
  "type": "Feature",
  "properties": {
    "date:inception_lower": "1980-01-01",
    "date:inception_upper": "1980-01-01",
    "iso:country": "GB",
    "wof:name": "CF5 6LQ",
    "wof:placetype": "postalcode"
  },
  "geometry": {"coordinates":[-3.32125,51.475013],"type":"Point"}
}
