{
  "type": "Feature",
  "properties": {
    "iso:country":"GB",
    "wof:name":"CF5 6LQ",
    "wof:placetype":"postalcode"
},
  "geometry": {"coordinates":[-3.32125026656234,51.47501338695876],"type":"Point"}
}