{
  "type": "Feature",
  "properties": {
    "iso:country":"GB",
    "wof:name":"SW9 0NT",
    "wof:placetype":"postalcode"
},
  "geometry": {"coordinates":[-0.11445926990771,51.4747672283624],"type":"Point"}
}