{
  "type": "Feature",
  "properties": {
    "date:inception_lower": "1980-01-01",
    "date:inception_upper": "1980-01-01",
    "iso:country": "GB",
    "wof:name": "SW9 0NT",
    "wof:placetype": "postalcode"
  },
  "geometry": {"coordinates":[-0.114459,51.474767],"type":"Point"}
}
