{
  "type": "Feature",
  "properties": {
    "iso:country":"GB",
    "wof:name":"LE5 1FB",
    "wof:placetype":"postalcode"
},
  "geometry": {"coordinates":[-1.05972771512548,52.65092439376829],"type":"Point"}
}