{
  "type": "Feature",
  "properties": {
    "date:inception_lower": "1980-01-01",
    "date:inception_upper": "1980-01-01",
    "iso:country": "GB",
    "wof:name": "LE5 1FB",
    "wof:placetype": "postalcode"
  },
  "geometry": {"coordinates":[-1.059728,52.650924],"type":"Point"}
}
