{
  "type": "Feature",
  "properties": {
    "date:inception_lower": "1980-01-01",
    "date:inception_upper": "1980-01-01",
    "iso:country": "GB",
    "wof:name": "B71 2RU",
    "wof:placetype": "postalcode"
  },
  "geometry": {"coordinates":[-2.006472,52.533137],"type":"Point"}
}
