{
  "type": "Feature",
  "properties": {
    "iso:country":"GB",
    "wof:name":"G65 0PQ",
    "wof:placetype":"postalcode"
},
  "geometry": {"coordinates":[-4.04866902815995,55.97640483312679],"type":"Point"}
}