{
  "type": "Feature",
  "properties": {
    "iso:country":"GB",
    "wof:name":"WS1 1LF",
    "wof:placetype":"postalcode"
},
  "geometry": {"coordinates":[-1.98304259126227,52.58509769134137],"type":"Point"}
}