{
  "type": "Feature",
  "properties": {
    "iso:country":"GB",
    "wof:name":"PO19 5DT",
    "wof:placetype":"postalcode"
},
  "geometry": {"coordinates":[-0.78255915251342,50.85112509757174],"type":"Point"}
}