{
  "type": "Feature",
  "properties": {
    "iso:country":"GB",
    "wof:name":"SR3 2EF",
    "wof:placetype":"postalcode"
},
  "geometry": {"coordinates":[-1.39788244239408,54.87201352595761],"type":"Point"}
}