{
  "type": "Feature",
  "properties": {
    "iso:country":"GB",
    "wof:name":"EH26 0HR",
    "wof:placetype":"postalcode"
},
  "geometry": {"coordinates":[-3.22688414861913,55.83828179387806],"type":"Point"}
}