{
  "type": "Feature",
  "properties": {
    "iso:country":"GB",
    "wof:name":"B23 7PU",
    "wof:placetype":"postalcode"
},
  "geometry": {"coordinates":[-1.86022519933013,52.51235166321344],"type":"Point"}
}