{
  "type": "Feature",
  "properties": {
    "iso:country":"GB",
    "wof:name":"PL2 3NZ",
    "wof:placetype":"postalcode"
},
  "geometry": {"coordinates":[-4.1427082203506,50.39638324942234],"type":"Point"}
}