{
  "type": "Feature",
  "properties": {
    "iso:country":"GB",
    "wof:name":"PO18 0PF",
    "wof:placetype":"postalcode"
},
  "geometry": {"coordinates":[-0.74029322161083,50.85914789773726],"type":"Point"}
}