{
  "type": "Feature",
  "properties": {
    "date:inception_lower":"1980-01-01",
    "date:inception_upper":"1980-01-31",
    "iso:country":"GB",
    "wof:name":"PO18 0PF",
    "wof:placetype":"postalcode"
},
  "geometry": {"coordinates":[-0.740293,50.859148],"type":"Point"}
}