{
  "type": "Feature",
  "properties": {
    "date:inception_lower":"1980-01-01",
    "date:inception_upper":"1980-01-31",
    "iso:country":"GB",
    "wof:name":"GL15 5AT",
    "wof:placetype":"postalcode"
},
  "geometry": {"coordinates":[-2.521298,51.726796],"type":"Point"}
}