{
  "type": "Feature",
  "properties": {
    "iso:country":"GB",
    "wof:name":"PL6 5SD",
    "wof:placetype":"postalcode"
},
  "geometry": {"coordinates":[-4.11112659111359,50.39623243200308],"type":"Point"}
}