{
  "type": "Feature",
  "properties": {
    "iso:country": "GB",
    "wof:name": "W3 7EU",
    "wof:placetype": "postalcode"
  },
  "geometry": {"coordinates":[-0.252345,51.50282],"type":"Point"}
}
