{
  "type": "Feature",
  "properties": {
    "iso:country":"GB",
    "wof:name":"GL15 6JW",
    "wof:placetype":"postalcode"
},
  "geometry": {"coordinates":[-2.57369761422718,51.75108438310501],"type":"Point"}
}