{
  "type": "Feature",
  "properties": {
    "iso:country": "GB",
    "wof:name": "GL15 6JW",
    "wof:placetype": "postalcode"
  },
  "geometry": {"coordinates":[-2.573756,51.751079],"type":"Point"}
}
