{
  "type": "Feature",
  "properties": {
    "iso:country":"GB",
    "wof:name":"WA11 0HT",
    "wof:placetype":"postalcode"
},
  "geometry": {"coordinates":[-2.68119356885814,53.46790128975189],"type":"Point"}
}