{
  "type": "Feature",
  "properties": {
    "iso:country":"GB",
    "wof:name":"NE66 3SE",
    "wof:placetype":"postalcode"
},
  "geometry": {"coordinates":[-1.67800875663139,55.47518167584823],"type":"Point"}
}