{
  "type": "Feature",
  "properties": {
    "iso:country": "GB",
    "wof:name": "NE66 3SE",
    "wof:placetype": "postalcode"
  },
  "geometry": {"coordinates":[-1.678009,55.475182],"type":"Point"}
}
