{
  "type": "Feature",
  "properties": {
    "iso:country": "GB",
    "wof:name": "CF10 4RA",
    "wof:placetype": "postalcode"
  },
  "geometry": {"coordinates":[-3.15842,51.466269],"type":"Point"}
}
