{
  "type": "Feature",
  "properties": {
    "iso:country":"GB",
    "wof:name":"CF10 4RA",
    "wof:placetype":"postalcode"
},
  "geometry": {"coordinates":[-3.15842039264039,51.46626884349438],"type":"Point"}
}