{
  "type": "Feature",
  "properties": {
    "date:inception_lower": "1990-02-01",
    "date:inception_upper": "1990-02-01",
    "iso:country": "GB",
    "wof:name": "HP13 6LY",
    "wof:placetype": "postalcode"
  },
  "geometry": {"coordinates":[-0.746185,51.633423],"type":"Point"}
}
