{
  "type": "Feature",
  "properties": {
    "iso:country": "GB",
    "wof:name": "DL1 1GL",
    "wof:placetype": "postalcode"
  },
  "geometry": {"coordinates":[-1.544601,54.523573],"type":"Point"}
}
