{
  "type": "Feature",
  "properties": {
    "iso:country":"GB",
    "wof:name":"WV14 9UH",
    "wof:placetype":"postalcode"
},
  "geometry": {"coordinates":[-2.09654745571543,52.54757171215451],"type":"Point"}
}