{
  "type": "Feature",
  "properties": {
    "iso:country":"GB",
    "wof:name":"CH7 6WF",
    "wof:placetype":"postalcode"
},
  "geometry": {"coordinates":[-3.17683096295639,53.21014682574246],"type":"Point"}
}