{
  "type": "Feature",
  "properties": {
    "date:inception_lower":"2001-12-01",
    "date:inception_upper":"2001-12-31",
    "iso:country":"GB",
    "wof:name":"CH7 6WF",
    "wof:placetype":"postalcode"
},
  "geometry": {"coordinates":[-3.176831,53.210147],"type":"Point"}
}