{
  "type": "Feature",
  "properties": {
    "iso:country": "GB",
    "wof:name": "BA20 1NU",
    "wof:placetype": "postalcode"
  },
  "geometry": {"coordinates":[-2.629198,50.939189],"type":"Point"}
}
