{
  "type": "Feature",
  "properties": {
    "iso:country":"GB",
    "wof:name":"BA20 1NU",
    "wof:placetype":"postalcode"
},
  "geometry": {"coordinates":[-2.62919850533206,50.93918940649745],"type":"Point"}
}