{
  "type": "Feature",
  "properties": {
    "date:inception_lower":"1984-10-01",
    "date:inception_upper":"1984-10-31",
    "iso:country":"GB",
    "wof:name":"BA20 1NU",
    "wof:placetype":"postalcode"
},
  "geometry": {"coordinates":[-2.629198,50.939189],"type":"Point"}
}