{
  "type": "Feature",
  "properties": {
    "iso:country":"GB",
    "wof:name":"MK1 1DT",
    "wof:placetype":"postalcode"
},
  "geometry": {"coordinates":[-0.73289836521486,52.00459294671175],"type":"Point"}
}