{
  "type": "Feature",
  "properties": {
    "date:inception_lower": "1980-01-01",
    "date:inception_upper": "1980-01-01",
    "iso:country": "GB",
    "wof:name": "WF17 8JW",
    "wof:placetype": "postalcode"
  },
  "geometry": {"coordinates":[-1.654132,53.72463],"type":"Point"}
}
