{
  "type": "Feature",
  "properties": {
    "iso:country":"GB",
    "wof:name":"BD1 2RW",
    "wof:placetype":"postalcode"
},
  "geometry": {"coordinates":[-1.7616293443452,53.79706617893427],"type":"Point"}
}