{
  "type": "Feature",
  "properties": {
    "iso:country":"GB",
    "wof:name":"BL8 4LJ",
    "wof:placetype":"postalcode"
},
  "geometry": {"coordinates":[-2.36719069951507,53.63049503968573],"type":"Point"}
}