{
  "type": "Feature",
  "properties": {
    "iso:country": "GB",
    "wof:name": "SN3 5LB",
    "wof:placetype": "postalcode"
  },
  "geometry": {"coordinates":[-1.725735,51.55925],"type":"Point"}
}
