{
  "type": "Feature",
  "properties": {
    "iso:country":"GB",
    "wof:name":"SY9 5LL",
    "wof:placetype":"postalcode"
},
  "geometry": {"coordinates":[-3.05017363453832,52.48457693004535],"type":"Point"}
}