{
  "type": "Feature",
  "properties": {
    "date:inception_lower": "1980-01-01",
    "date:inception_upper": "1980-01-01",
    "iso:country": "GB",
    "wof:name": "SY9 5LL",
    "wof:placetype": "postalcode"
  },
  "geometry": {"coordinates":[-3.050174,52.484577],"type":"Point"}
}
