{
  "type": "Feature",
  "properties": {
    "iso:country": "GB",
    "wof:name": "PO6 1QQ",
    "wof:placetype": "postalcode"
  },
  "geometry": {"coordinates":[-1.048311,50.844008],"type":"Point"}
}
