{
  "type": "Feature",
  "properties": {
    "iso:country":"GB",
    "wof:name":"NR28 0DX",
    "wof:placetype":"postalcode"
},
  "geometry": {"coordinates":[1.37997998242989,52.81374720416663],"type":"Point"}
}