{
  "type": "Feature",
  "properties": {
    "iso:country": "GB",
    "wof:name": "WS3 3JY",
    "wof:placetype": "postalcode"
  },
  "geometry": {"coordinates":[-1.998642,52.617759],"type":"Point"}
}
