{
  "type": "Feature",
  "properties": {
    "date:inception_lower": "2013-08-01",
    "date:inception_upper": "2013-08-01",
    "iso:country": "GB",
    "wof:name": "WS3 3JY",
    "wof:placetype": "postalcode"
  },
  "geometry": {"coordinates":[-1.998642,52.617759],"type":"Point"}
}
