{
  "type": "Feature",
  "properties": {
    "iso:country":"GB",
    "wof:name":"CF62 3AQ",
    "wof:placetype":"postalcode"
},
  "geometry": {"coordinates":[-3.38679348349155,51.40656352560156],"type":"Point"}
}