{
  "type": "Feature",
  "properties": {
    "iso:country": "GB",
    "wof:name": "S35 7BR",
    "wof:placetype": "postalcode"
  },
  "geometry": {"coordinates":[-1.576143,53.508589],"type":"Point"}
}
