{
  "type": "Feature",
  "properties": {
    "iso:country":"GB",
    "wof:name":"LE2 7DE",
    "wof:placetype":"postalcode"
},
  "geometry": {"coordinates":[-1.13893743693664,52.62717239624635],"type":"Point"}
}