{
  "type": "Feature",
  "properties": {
    "iso:country": "GB",
    "wof:name": "BB10 4AU",
    "wof:placetype": "postalcode"
  },
  "geometry": {"coordinates":[-2.23421,53.788472],"type":"Point"}
}
