{
  "type": "Feature",
  "properties": {
    "date:inception_lower": "2002-06-01",
    "date:inception_upper": "2002-06-01",
    "iso:country": "GB",
    "wof:name": "SO14 3FX",
    "wof:placetype": "postalcode"
  },
  "geometry": {"coordinates":[-1.393747,50.897148],"type":"Point"}
}
