{
  "type": "Feature",
  "properties": {
    "date:inception_lower": "2017-07-01",
    "date:inception_upper": "2017-07-01",
    "iso:country": "GB",
    "wof:name": "TW3 1AQ",
    "wof:placetype": "postalcode"
  },
  "geometry": {"coordinates":[-0.352985,51.46872],"type":"Point"}
}
