{
  "type": "Feature",
  "properties": {
    "iso:country": "GB",
    "wof:name": "HX1 5JB",
    "wof:placetype": "postalcode"
  },
  "geometry": {"coordinates":[-1.87888,53.721751],"type":"Point"}
}
