{
  "type": "Feature",
  "properties": {
    "iso:country":"GB",
    "wof:name":"HX1 5JB",
    "wof:placetype":"postalcode"
},
  "geometry": {"coordinates":[-1.87887969776126,53.72175127434728],"type":"Point"}
}