{
  "type": "Feature",
  "properties": {
    "iso:country":"GB",
    "wof:name":"WD23 4NP",
    "wof:placetype":"postalcode"
},
  "geometry": {"coordinates":[-0.35299519373413,51.64636173860663],"type":"Point"}
}