{
  "type": "Feature",
  "properties": {
    "date:inception_lower": "2014-02-01",
    "date:inception_upper": "2014-02-01",
    "iso:country": "GB",
    "wof:name": "YO16 4BF",
    "wof:placetype": "postalcode"
  },
  "geometry": {"coordinates":[-0.206849,54.088844],"type":"Point"}
}
