{
  "type": "Feature",
  "properties": {
    "iso:country":"GB",
    "wof:name":"YO16 4BF",
    "wof:placetype":"postalcode"
},
  "geometry": {"coordinates":[-0.2068492537841,54.08884445459373],"type":"Point"}
}