{
  "type": "Feature",
  "properties": {
    "iso:country":"GB",
    "wof:name":"TN2 4BB",
    "wof:placetype":"postalcode"
},
  "geometry": {"coordinates":[0.34865974247046,51.14974598875224],"type":"Point"}
}