{
  "type": "Feature",
  "properties": {
    "date:inception_lower":"1980-01-01",
    "date:inception_upper":"1980-01-31",
    "iso:country":"GB",
    "wof:name":"CF39 0NN",
    "wof:placetype":"postalcode"
},
  "geometry": {"coordinates":[-3.412307,51.622949],"type":"Point"}
}