{
  "type": "Feature",
  "properties": {
    "iso:country":"GB",
    "wof:name":"PR2 8DP",
    "wof:placetype":"postalcode"
},
  "geometry": {"coordinates":[-2.696072217975,53.78175381548902],"type":"Point"}
}