{
  "type": "Feature",
  "properties": {
    "date:inception_lower": "2018-12-01",
    "date:inception_upper": "2018-12-01",
    "iso:country": "GB",
    "wof:name": "HA1 3RW",
    "wof:placetype": "postalcode"
  },
  "geometry": {"coordinates":[-0.336385,51.557332],"type":"Point"}
}
