{
  "type": "Feature",
  "properties": {
    "iso:country":"GB",
    "wof:name":"HA1 3RW",
    "wof:placetype":"postalcode"
},
  "geometry": {"coordinates":[-0.33640685441244,51.5573302361134],"type":"Point"}
}