{
  "type": "Feature",
  "properties": {
    "date:inception_lower": "1980-01-01",
    "date:inception_upper": "1980-01-01",
    "iso:country": "GB",
    "wof:name": "CF34 0EP",
    "wof:placetype": "postalcode"
  },
  "geometry": {"coordinates":[-3.662104,51.619201],"type":"Point"}
}
