{
  "type": "Feature",
  "properties": {
    "iso:country": "GB",
    "wof:name": "CF34 0EP",
    "wof:placetype": "postalcode"
  },
  "geometry": {"coordinates":[-3.662104,51.619201],"type":"Point"}
}
