{
  "type": "Feature",
  "properties": {
    "iso:country":"GB",
    "wof:name":"M41 7NF",
    "wof:placetype":"postalcode"
},
  "geometry": {"coordinates":[-2.36210935029258,53.46081873306909],"type":"Point"}
}