{
  "type": "Feature",
  "properties": {
    "iso:country":"GB",
    "wof:name":"ME10 5BP",
    "wof:placetype":"postalcode"
},
  "geometry": {"coordinates":[0.71806806764716,51.35116707852075],"type":"Point"}
}