{
  "type": "Feature",
  "properties": {
    "iso:country":"GB",
    "wof:name":"IG6 2DJ",
    "wof:placetype":"postalcode"
},
  "geometry": {"coordinates":[0.08242962580041,51.59030169902653],"type":"Point"}
}