{
  "type": "Feature",
  "properties": {
    "date:inception_lower": "1980-01-01",
    "date:inception_upper": "1980-01-01",
    "iso:country": "GB",
    "wof:name": "HR4 7LB",
    "wof:placetype": "postalcode"
  },
  "geometry": {"coordinates":[-2.890834,52.0855],"type":"Point"}
}
