{
  "type": "Feature",
  "properties": {
    "iso:country":"GB",
    "wof:name":"HR4 7LB",
    "wof:placetype":"postalcode"
},
  "geometry": {"coordinates":[-2.89083414334332,52.08550016859959],"type":"Point"}
}