{
  "type": "Feature",
  "properties": {
    "iso:country":"GB",
    "wof:name":"CF14 9HY",
    "wof:placetype":"postalcode"
},
  "geometry": {"coordinates":[-3.19744375526818,51.54082419623445],"type":"Point"}
}