{
  "type": "Feature",
  "properties": {
    "iso:country":"GB",
    "wof:name":"CV1 5FG",
    "wof:placetype":"postalcode"
},
  "geometry": {"coordinates":[-1.49745070438161,52.4153091121252],"type":"Point"}
}