{
  "type": "Feature",
  "properties": {
    "iso:country":"GB",
    "wof:name":"TN15 9AT",
    "wof:placetype":"postalcode"
},
  "geometry": {"coordinates":[0.28503220025212,51.28429845999912],"type":"Point"}
}