{
  "type": "Feature",
  "properties": {
    "iso:country":"GB",
    "wof:name":"N16 7DS",
    "wof:placetype":"postalcode"
},
  "geometry": {"coordinates":[-0.06808040527891,51.56256218825149],"type":"Point"}
}