{
  "type": "Feature",
  "properties": {
    "iso:country": "GB",
    "wof:name": "N16 7DS",
    "wof:placetype": "postalcode"
  },
  "geometry": {"coordinates":[-0.06808,51.562562],"type":"Point"}
}
