{
  "type": "Feature",
  "properties": {
    "iso:country":"GB",
    "wof:name":"IP1 4LU",
    "wof:placetype":"postalcode"
},
  "geometry": {"coordinates":[1.14881946214414,52.07696026168248],"type":"Point"}
}