{
  "type": "Feature",
  "properties": {
    "iso:country": "GB",
    "wof:name": "IP1 4LU",
    "wof:placetype": "postalcode"
  },
  "geometry": {"coordinates":[1.14882,52.07696],"type":"Point"}
}
