{
  "type": "Feature",
  "properties": {
    "iso:country":"GB",
    "wof:name":"G78 2PR",
    "wof:placetype":"postalcode"
},
  "geometry": {"coordinates":[-4.37753716512589,55.79265762064853],"type":"Point"}
}