{
  "type": "Feature",
  "properties": {
    "iso:country":"GB",
    "wof:name":"TS7 8QA",
    "wof:placetype":"postalcode"
},
  "geometry": {"coordinates":[-1.19206455867897,54.5320853402911],"type":"Point"}
}