{
  "type": "Feature",
  "properties": {
    "iso:country": "GB",
    "wof:name": "TS7 8QA",
    "wof:placetype": "postalcode"
  },
  "geometry": {"coordinates":[-1.192065,54.532085],"type":"Point"}
}
