{
  "type": "Feature",
  "properties": {
    "iso:country":"GB",
    "wof:name":"BS15 3SD",
    "wof:placetype":"postalcode"
},
  "geometry": {"coordinates":[-2.50531327507406,51.44591589561974],"type":"Point"}
}