{
  "type": "Feature",
  "properties": {
    "date:inception_lower": "2007-01-01",
    "date:inception_upper": "2007-01-01",
    "iso:country": "GB",
    "wof:name": "SG2 0BP",
    "wof:placetype": "postalcode"
  },
  "geometry": {"coordinates":[-0.172805,51.904179],"type":"Point"}
}
