{
  "type": "Feature",
  "properties": {
    "iso:country":"GB",
    "wof:name":"SG2 0BP",
    "wof:placetype":"postalcode"
},
  "geometry": {"coordinates":[-0.17280505737783,51.904179489571],"type":"Point"}
}