{
  "type": "Feature",
  "properties": {
    "date:inception_lower": "2022-12-01",
    "date:inception_upper": "2022-12-01",
    "iso:country": "GB",
    "wof:name": "OL16 9DN",
    "wof:placetype": "postalcode"
  },
  "geometry": {"coordinates":[-2.148781,53.61155],"type":"Point"}
}
