{
  "type": "Feature",
  "properties": {
    "iso:country":"GB",
    "wof:name":"WN3 5TS",
    "wof:placetype":"postalcode"
},
  "geometry": {"coordinates":[-2.64574533212375,53.53318442688902],"type":"Point"}
}