{
  "type": "Feature",
  "properties": {
    "date:inception_lower": "1992-08-01",
    "date:inception_upper": "1992-08-01",
    "iso:country": "GB",
    "wof:name": "DE65 6BU",
    "wof:placetype": "postalcode"
  },
  "geometry": {"coordinates":[-1.572976,52.85286],"type":"Point"}
}
