{
  "type": "Feature",
  "properties": {
    "date:inception_lower": "2016-08-01",
    "date:inception_upper": "2016-08-01",
    "iso:country": "GB",
    "wof:name": "YO25 6AX",
    "wof:placetype": "postalcode"
  },
  "geometry": {"coordinates":[-0.441202,54.00369],"type":"Point"}
}
