{
  "type": "Feature",
  "properties": {
    "date:inception_lower": "2020-02-01",
    "date:inception_upper": "2020-02-01",
    "iso:country": "GB",
    "wof:name": "CW12 3UJ",
    "wof:placetype": "postalcode"
  },
  "geometry": {"coordinates":[-2.210343,53.157211],"type":"Point"}
}
