{
  "type": "Feature",
  "properties": {
    "iso:country": "GB",
    "wof:name": "HP20 1NU",
    "wof:placetype": "postalcode"
  },
  "geometry": {"coordinates":[-0.785516,51.817157],"type":"Point"}
}
