{
  "type": "Feature",
  "properties": {
    "date:inception_lower": "1980-01-01",
    "date:inception_upper": "1980-01-01",
    "iso:country": "GB",
    "wof:name": "TN5 6EJ",
    "wof:placetype": "postalcode"
  },
  "geometry": {"coordinates":[0.341389,51.071899],"type":"Point"}
}
