{
  "type": "Feature",
  "properties": {
    "date:inception_lower": "2022-10-01",
    "date:inception_upper": "2022-10-01",
    "iso:country": "GB",
    "wof:name": "PR26 7BB",
    "wof:placetype": "postalcode"
  },
  "geometry": {"coordinates":[-2.736725,53.701109],"type":"Point"}
}
