{
  "type": "Feature",
  "properties": {
    "iso:country":"GB",
    "wof:name":"PR1 5HS",
    "wof:placetype":"postalcode"
},
  "geometry": {"coordinates":[-2.68343263607315,53.76788588001507],"type":"Point"}
}