{
  "type": "Feature",
  "properties": {
    "iso:country": "GB",
    "wof:name": "PR1 5HS",
    "wof:placetype": "postalcode"
  },
  "geometry": {"coordinates":[-2.683433,53.767886],"type":"Point"}
}
