{
  "type": "Feature",
  "properties": {
    "date:inception_lower":"1980-01-01",
    "date:inception_upper":"1980-01-31",
    "iso:country":"GB",
    "wof:name":"PR1 5HS",
    "wof:placetype":"postalcode"
},
  "geometry": {"coordinates":[-2.683433,53.767886],"type":"Point"}
}