{
  "type": "Feature",
  "properties": {
    "iso:country":"GB",
    "wof:name":"BB9 0RX",
    "wof:placetype":"postalcode"
},
  "geometry": {"coordinates":[-2.21043801141349,53.82720912348002],"type":"Point"}
}