{
  "type": "Feature",
  "properties": {
    "date:inception_lower": "1980-01-01",
    "date:inception_upper": "1980-01-01",
    "iso:country": "GB",
    "wof:name": "BB9 0RX",
    "wof:placetype": "postalcode"
  },
  "geometry": {"coordinates":[-2.210438,53.827209],"type":"Point"}
}
