{
  "type": "Feature",
  "properties": {
    "iso:country":"GB",
    "wof:name":"B74 3TD",
    "wof:placetype":"postalcode"
},
  "geometry": {"coordinates":[-1.89521690841997,52.57600001195296],"type":"Point"}
}