{
  "type": "Feature",
  "properties": {
    "date:inception_lower": "1980-01-01",
    "date:inception_upper": "1980-01-01",
    "iso:country": "GB",
    "wof:name": "B74 3TD",
    "wof:placetype": "postalcode"
  },
  "geometry": {"coordinates":[-1.895217,52.576],"type":"Point"}
}
