{
  "type": "Feature",
  "properties": {
    "iso:country":"GB",
    "wof:name":"CM3 1ET",
    "wof:placetype":"postalcode"
},
  "geometry": {"coordinates":[0.45565055088509,51.79454759414024],"type":"Point"}
}