{
  "type": "Feature",
  "properties": {
    "iso:country": "GB",
    "wof:name": "CM3 1ET",
    "wof:placetype": "postalcode"
  },
  "geometry": {"coordinates":[0.455651,51.794548],"type":"Point"}
}
