{
  "type": "Feature",
  "properties": {
    "iso:country": "GB",
    "wof:name": "L33 5XE",
    "wof:placetype": "postalcode"
  },
  "geometry": {"coordinates":[-2.870257,53.482305],"type":"Point"}
}
