{
  "type": "Feature",
  "properties": {
    "date:inception_lower":"1980-01-01",
    "date:inception_upper":"1980-01-31",
    "iso:country":"GB",
    "wof:name":"L33 5XE",
    "wof:placetype":"postalcode"
},
  "geometry": {"coordinates":[-2.870257,53.482305],"type":"Point"}
}