{
  "type": "Feature",
  "properties": {
    "iso:country": "GB",
    "wof:name": "BS26 2FR",
    "wof:placetype": "postalcode"
  },
  "geometry": {"coordinates":[-2.850137,51.274744],"type":"Point"}
}
