{
  "type": "Feature",
  "properties": {
    "iso:country":"GB",
    "wof:name":"B13 9BX",
    "wof:placetype":"postalcode"
},
  "geometry": {"coordinates":[-1.87379012071289,52.44739640897318],"type":"Point"}
}