{
  "type": "Feature",
  "properties": {
    "iso:country":"GB",
    "wof:name":"NR18 0HD",
    "wof:placetype":"postalcode"
},
  "geometry": {"coordinates":[1.13167730748162,52.5807343206349],"type":"Point"}
}