{
  "type": "Feature",
  "properties": {
    "date:inception_lower": "1980-01-01",
    "date:inception_upper": "1980-01-01",
    "iso:country": "GB",
    "wof:name": "NR18 0HD",
    "wof:placetype": "postalcode"
  },
  "geometry": {"coordinates":[1.131677,52.580734],"type":"Point"}
}
