{
  "type": "Feature",
  "properties": {
    "iso:country":"GB",
    "wof:name":"PE37 8DG",
    "wof:placetype":"postalcode"
},
  "geometry": {"coordinates":[0.72755448925246,52.65289413135527],"type":"Point"}
}