{
  "type": "Feature",
  "properties": {
    "iso:country": "GB",
    "wof:name": "PE37 8DG",
    "wof:placetype": "postalcode"
  },
  "geometry": {"coordinates":[0.727555,52.652894],"type":"Point"}
}
