{
  "type": "Feature",
  "properties": {
    "iso:country": "GB",
    "wof:name": "YO10 4QA",
    "wof:placetype": "postalcode"
  },
  "geometry": {"coordinates":[-1.075922,53.938329],"type":"Point"}
}
