{
  "type": "Feature",
  "properties": {
    "iso:country":"GB",
    "wof:name":"UB1 1LR",
    "wof:placetype":"postalcode"
},
  "geometry": {"coordinates":[-0.38353951560432,51.51202976668078],"type":"Point"}
}