{
  "type": "Feature",
  "properties": {
    "iso:country":"GB",
    "wof:name":"AB39 9AJ",
    "wof:placetype":"postalcode"
},
  "geometry": {"coordinates":[-2.20788795694987,56.96524414561967],"type":"Point"}
}