{
  "type": "Feature",
  "properties": {
    "date:inception_lower": "2000-12-01",
    "date:inception_upper": "2000-12-01",
    "iso:country": "GB",
    "wof:name": "BB6 8BS",
    "wof:placetype": "postalcode"
  },
  "geometry": {"coordinates":[-2.454082,53.826066],"type":"Point"}
}
