{
  "type": "Feature",
  "properties": {
    "iso:country":"GB",
    "wof:name":"BB6 8BS",
    "wof:placetype":"postalcode"
},
  "geometry": {"coordinates":[-2.45408168491665,53.82606644823713],"type":"Point"}
}