{
  "type": "Feature",
  "properties": {
    "iso:country": "GB",
    "wof:name": "BB6 8BS",
    "wof:placetype": "postalcode"
  },
  "geometry": {"coordinates":[-2.454082,53.826066],"type":"Point"}
}
