{
  "type": "Feature",
  "properties": {
    "iso:country": "GB",
    "wof:name": "AB54 4RD",
    "wof:placetype": "postalcode"
  },
  "geometry": {"coordinates":[-2.761385,57.431989],"type":"Point"}
}
