{
  "type": "Feature",
  "properties": {
    "iso:country": "GB",
    "wof:name": "S13 7JX",
    "wof:placetype": "postalcode"
  },
  "geometry": {"coordinates":[-1.369633,53.3588],"type":"Point"}
}
