{
  "type": "Feature",
  "properties": {
    "iso:country":"GB",
    "wof:name":"HG5 0AN",
    "wof:placetype":"postalcode"
},
  "geometry": {"coordinates":[-1.45894372858683,54.00650848164541],"type":"Point"}
}