{
  "type": "Feature",
  "properties": {
    "iso:country":"GB",
    "wof:name":"E15 1LU",
    "wof:placetype":"postalcode"
},
  "geometry": {"coordinates":[0.00318243761767,51.54951487667583],"type":"Point"}
}