{
  "type": "Feature",
  "properties": {
    "iso:country":"GB",
    "wof:name":"TW3 2NS",
    "wof:placetype":"postalcode"
},
  "geometry": {"coordinates":[-0.35078921525021,51.46554221528297],"type":"Point"}
}