{
  "type": "Feature",
  "properties": {
    "iso:country": "GB",
    "wof:name": "PE22 7HL",
    "wof:placetype": "postalcode"
  },
  "geometry": {"coordinates":[-0.059926,53.04531],"type":"Point"}
}
