{
  "type": "Feature",
  "properties": {
    "iso:country":"GB",
    "wof:name":"DY13 8AY",
    "wof:placetype":"postalcode"
},
  "geometry": {"coordinates":[-2.27865124945477,52.34668808537516],"type":"Point"}
}