{
  "type": "Feature",
  "properties": {
    "date:inception_lower":"1991-09-01",
    "date:inception_upper":"1991-09-30",
    "iso:country":"GB",
    "wof:name":"DY13 8AY",
    "wof:placetype":"postalcode"
},
  "geometry": {"coordinates":[-2.278651,52.346688],"type":"Point"}
}