{
  "type": "Feature",
  "properties": {
    "iso:country":"GB",
    "wof:name":"PL4 7NE",
    "wof:placetype":"postalcode"
},
  "geometry": {"coordinates":[-4.12519865792691,50.37990318638426],"type":"Point"}
}