{
  "type": "Feature",
  "properties": {
    "iso:country":"GB",
    "wof:name":"SR6 7LZ",
    "wof:placetype":"postalcode"
},
  "geometry": {"coordinates":[-1.36588959160355,54.96240739444703],"type":"Point"}
}