{
  "type": "Feature",
  "properties": {
    "iso:country":"GB",
    "wof:name":"M24 5SS",
    "wof:placetype":"postalcode"
},
  "geometry": {"coordinates":[-2.20904505116041,53.55642607150173],"type":"Point"}
}