{
  "type": "Feature",
  "properties": {
    "iso:country":"GB",
    "wof:name":"EH3 9JY",
    "wof:placetype":"postalcode"
},
  "geometry": {"coordinates":[-3.20192233569474,55.94211389862058],"type":"Point"}
}