{
  "type": "Feature",
  "properties": {
    "iso:country":"GB",
    "wof:name":"GL5 5AP",
    "wof:placetype":"postalcode"
},
  "geometry": {"coordinates":[-2.22391312411145,51.71474298938288],"type":"Point"}
}