{
  "type": "Feature",
  "properties": {
    "iso:country":"GB",
    "wof:name":"PH22 1UN",
    "wof:placetype":"postalcode"
},
  "geometry": {"coordinates":[-3.8336431193674,57.20473921603714],"type":"Point"}
}