{
  "type": "Feature",
  "properties": {
    "date:inception_lower": "2003-06-01",
    "date:inception_upper": "2003-06-01",
    "iso:country": "GB",
    "wof:name": "LA2 7FE",
    "wof:placetype": "postalcode"
  },
  "geometry": {"coordinates":[-2.507002,54.119036],"type":"Point"}
}
