{
  "type": "Feature",
  "properties": {
    "iso:country":"GB",
    "wof:name":"LA2 7FE",
    "wof:placetype":"postalcode"
},
  "geometry": {"coordinates":[-2.50700177443549,54.11903640778741],"type":"Point"}
}