{
  "type": "Feature",
  "properties": {
    "iso:country":"GB",
    "wof:name":"LL11 3RN",
    "wof:placetype":"postalcode"
},
  "geometry": {"coordinates":[-3.06719658459176,53.05115006357937],"type":"Point"}
}