{
  "type": "Feature",
  "properties": {
    "date:inception_lower":"1980-01-01",
    "date:inception_upper":"1980-01-31",
    "iso:country":"GB",
    "wof:name":"LL11 3RN",
    "wof:placetype":"postalcode"
},
  "geometry": {"coordinates":[-3.06717,53.051274],"type":"Point"}
}