{
  "type": "Feature",
  "properties": {
    "iso:country":"GB",
    "wof:name":"GU16 8NS",
    "wof:placetype":"postalcode"
},
  "geometry": {"coordinates":[-0.7243336066028,51.31608483762958],"type":"Point"}
}