{
  "type": "Feature",
  "properties": {
    "iso:country":"GB",
    "wof:name":"IV2 3DU",
    "wof:placetype":"postalcode"
},
  "geometry": {"coordinates":[-4.22402415210496,57.47678378617886],"type":"Point"}
}