{
  "type": "Feature",
  "properties": {
    "iso:country":"GB",
    "wof:name":"E10 7AW",
    "wof:placetype":"postalcode"
},
  "geometry": {"coordinates":[-0.01858020440627,51.56816638894603],"type":"Point"}
}