{
  "type": "Feature",
  "properties": {
    "iso:country": "GB",
    "wof:name": "LS9 7UY",
    "wof:placetype": "postalcode"
  },
  "geometry": {"coordinates":[-1.521509,53.79918],"type":"Point"}
}
