{
  "type": "Feature",
  "properties": {
    "iso:country":"GB",
    "wof:name":"AL5 5HL",
    "wof:placetype":"postalcode"
},
  "geometry": {"coordinates":[-0.33697743324804,51.82752215988572],"type":"Point"}
}