{
  "type": "Feature",
  "properties": {
    "date:inception_lower": "1980-01-01",
    "date:inception_upper": "1980-01-01",
    "iso:country": "GB",
    "wof:name": "NR8 5AN",
    "wof:placetype": "postalcode"
  },
  "geometry": {"coordinates":[1.198451,52.661029],"type":"Point"}
}
