{
  "type": "Feature",
  "properties": {
    "date:inception_lower": "2019-02-01",
    "date:inception_upper": "2019-02-01",
    "iso:country": "GB",
    "wof:name": "TF9 3GN",
    "wof:placetype": "postalcode"
  },
  "geometry": {"coordinates":[-2.484816,52.906651],"type":"Point"}
}
