{
  "type": "Feature",
  "properties": {
    "iso:country": "GB",
    "wof:name": "TF9 3GN",
    "wof:placetype": "postalcode"
  },
  "geometry": {"coordinates":[-2.484816,52.906651],"type":"Point"}
}
