{
  "type": "Feature",
  "properties": {
    "iso:country":"GB",
    "wof:name":"PL4 6AG",
    "wof:placetype":"postalcode"
},
  "geometry": {"coordinates":[-4.1436833730881,50.37682952067624],"type":"Point"}
}