{
  "type": "Feature",
  "properties": {
    "iso:country":"GB",
    "wof:name":"BN14 8NA",
    "wof:placetype":"postalcode"
},
  "geometry": {"coordinates":[-0.35270578427927,50.82249392584527],"type":"Point"}
}