{
  "type": "Feature",
  "properties": {
    "iso:country": "GB",
    "wof:name": "SN11 0DD",
    "wof:placetype": "postalcode"
  },
  "geometry": {"coordinates":[-2.006425,51.439354],"type":"Point"}
}
