{
  "type": "Feature",
  "properties": {
    "iso:country":"GB",
    "wof:name":"G73 4QE",
    "wof:placetype":"postalcode"
},
  "geometry": {"coordinates":[-4.22272561688279,55.81300876242801],"type":"Point"}
}