{
  "type": "Feature",
  "properties": {
    "date:inception_lower": "1980-01-01",
    "date:inception_upper": "1980-01-01",
    "iso:country": "GB",
    "wof:name": "G73 4QE",
    "wof:placetype": "postalcode"
  },
  "geometry": {"coordinates":[-4.222726,55.813009],"type":"Point"}
}
