{
  "type": "Feature",
  "properties": {
    "iso:country":"GB",
    "wof:name":"SW19 6JZ",
    "wof:placetype":"postalcode"
},
  "geometry": {"coordinates":[-0.21223446634207,51.44271178260652],"type":"Point"}
}