{
  "type": "Feature",
  "properties": {
    "iso:country": "GB",
    "wof:name": "DY2 8ES",
    "wof:placetype": "postalcode"
  },
  "geometry": {"coordinates":[-2.072299,52.49424],"type":"Point"}
}
