{
  "type": "Feature",
  "properties": {
    "iso:country":"GB",
    "wof:name":"DY2 8ES",
    "wof:placetype":"postalcode"
},
  "geometry": {"coordinates":[-2.07237802723123,52.49421598952972],"type":"Point"}
}