{
  "type": "Feature",
  "properties": {
    "iso:country":"GB",
    "wof:name":"IP8 4AT",
    "wof:placetype":"postalcode"
},
  "geometry": {"coordinates":[1.10215379876059,52.07484399751602],"type":"Point"}
}