{
  "type": "Feature",
  "properties": {
    "iso:country": "GB",
    "wof:name": "IP8 4AT",
    "wof:placetype": "postalcode"
  },
  "geometry": {"coordinates":[1.102226,52.07484],"type":"Point"}
}
