{
  "type": "Feature",
  "properties": {
    "iso:country": "GB",
    "wof:name": "NG24 4XL",
    "wof:placetype": "postalcode"
  },
  "geometry": {"coordinates":[-0.814902,53.074751],"type":"Point"}
}
