{
  "type": "Feature",
  "properties": {
    "date:inception_lower": "2000-12-01",
    "date:inception_upper": "2000-12-01",
    "iso:country": "GB",
    "wof:name": "TF9 3QA",
    "wof:placetype": "postalcode"
  },
  "geometry": {"coordinates":[-2.503261,52.904761],"type":"Point"}
}
