{
  "type": "Feature",
  "properties": {
    "iso:country":"GB",
    "wof:name":"CH7 2EU",
    "wof:placetype":"postalcode"
},
  "geometry": {"coordinates":[-3.06642311037243,53.16714764529105],"type":"Point"}
}