{
  "type": "Feature",
  "properties": {
    "date:inception_lower": "1980-01-01",
    "date:inception_upper": "1980-01-01",
    "iso:country": "GB",
    "wof:name": "CH7 2EU",
    "wof:placetype": "postalcode"
  },
  "geometry": {"coordinates":[-3.070469,53.166839],"type":"Point"}
}
