{
  "type": "Feature",
  "properties": {
    "iso:country": "GB",
    "wof:name": "SE5 7TT",
    "wof:placetype": "postalcode"
  },
  "geometry": {"coordinates":[-0.088562,51.479743],"type":"Point"}
}
