{
  "type": "Feature",
  "properties": {
    "iso:country": "GB",
    "wof:name": "LD3 0AU",
    "wof:placetype": "postalcode"
  },
  "geometry": {"coordinates":[-3.228961,51.998356],"type":"Point"}
}
