{
  "type": "Feature",
  "properties": {
    "iso:country":"GB",
    "wof:name":"LD3 0AU",
    "wof:placetype":"postalcode"
},
  "geometry": {"coordinates":[-3.22896063820678,51.99835597389837],"type":"Point"}
}