{
  "type": "Feature",
  "properties": {
    "iso:country":"GB",
    "wof:name":"SR5 5NQ",
    "wof:placetype":"postalcode"
},
  "geometry": {"coordinates":[-1.42784594098104,54.92720930965694],"type":"Point"}
}