{
  "type": "Feature",
  "properties": {
    "iso:country":"GB",
    "wof:name":"IG11 9SU",
    "wof:placetype":"postalcode"
},
  "geometry": {"coordinates":[0.08654383899852,51.53861043989298],"type":"Point"}
}