{
  "type": "Feature",
  "properties": {
    "date:inception_lower":"1995-12-01",
    "date:inception_upper":"1995-12-31",
    "iso:country":"GB",
    "wof:name":"IG11 9SU",
    "wof:placetype":"postalcode"
},
  "geometry": {"coordinates":[0.086544,51.53861],"type":"Point"}
}