{
  "type": "Feature",
  "properties": {
    "iso:country": "GB",
    "wof:name": "G76 8EL",
    "wof:placetype": "postalcode"
  },
  "geometry": {"coordinates":[-4.274494,55.781387],"type":"Point"}
}
