{
  "type": "Feature",
  "properties": {
    "iso:country":"GB",
    "wof:name":"G76 8EL",
    "wof:placetype":"postalcode"
},
  "geometry": {"coordinates":[-4.27449372556149,55.78138720728113],"type":"Point"}
}