{
  "type": "Feature",
  "properties": {
    "iso:country":"GB",
    "wof:name":"DE7 8NU",
    "wof:placetype":"postalcode"
},
  "geometry": {"coordinates":[-1.30894341848452,52.98820350357351],"type":"Point"}
}