{
  "type": "Feature",
  "properties": {
    "iso:country":"GB",
    "wof:name":"SL9 7NA",
    "wof:placetype":"postalcode"
},
  "geometry": {"coordinates":[-0.5601332336117,51.58193237471856],"type":"Point"}
}