{
  "type": "Feature",
  "properties": {
    "date:inception_lower": "1980-01-01",
    "date:inception_upper": "1980-01-01",
    "iso:country": "GB",
    "wof:name": "SL9 7NA",
    "wof:placetype": "postalcode"
  },
  "geometry": {"coordinates":[-0.560133,51.581932],"type":"Point"}
}
