{
  "type": "Feature",
  "properties": {
    "iso:country": "GB",
    "wof:name": "SL9 7NA",
    "wof:placetype": "postalcode"
  },
  "geometry": {"coordinates":[-0.560133,51.581932],"type":"Point"}
}
