{
  "type": "Feature",
  "properties": {
    "iso:country":"GB",
    "wof:name":"CT7 0HG",
    "wof:placetype":"postalcode"
},
  "geometry": {"coordinates":[1.34653929635895,51.3568070145502],"type":"Point"}
}