{
  "type": "Feature",
  "properties": {
    "date:inception_lower": "1999-06-01",
    "date:inception_upper": "1999-06-01",
    "iso:country": "GB",
    "wof:name": "CH49 4NE",
    "wof:placetype": "postalcode"
  },
  "geometry": {"coordinates":[-3.106876,53.391311],"type":"Point"}
}
