{
  "type": "Feature",
  "properties": {
    "iso:country": "GB",
    "wof:name": "DT6 5FG",
    "wof:placetype": "postalcode"
  },
  "geometry": {"coordinates":[-2.758858,50.741505],"type":"Point"}
}
