{
  "type": "Feature",
  "properties": {
    "date:inception_lower": "1999-12-01",
    "date:inception_upper": "1999-12-01",
    "iso:country": "GB",
    "wof:name": "IP22 4BY",
    "wof:placetype": "postalcode"
  },
  "geometry": {"coordinates":[1.100196,52.375885],"type":"Point"}
}
