{
  "type": "Feature",
  "properties": {
    "iso:country": "GB",
    "wof:name": "SP6 3JH",
    "wof:placetype": "postalcode"
  },
  "geometry": {"coordinates":[-1.877468,50.927684],"type":"Point"}
}
