{
  "type": "Feature",
  "properties": {
    "iso:country":"GB",
    "wof:name":"DE4 5GN",
    "wof:placetype":"postalcode"
},
  "geometry": {"coordinates":[-1.51229640303742,53.11246164924584],"type":"Point"}
}