{
  "type": "Feature",
  "properties": {
    "iso:country": "GB",
    "wof:name": "NG14 6EN",
    "wof:placetype": "postalcode"
  },
  "geometry": {"coordinates":[-1.107972,53.024325],"type":"Point"}
}
