{
  "type": "Feature",
  "properties": {
    "iso:country":"GB",
    "wof:name":"TN5 6TG",
    "wof:placetype":"postalcode"
},
  "geometry": {"coordinates":[0.3342054110832,51.06899374141638],"type":"Point"}
}