{
  "type": "Feature",
  "properties": {
    "iso:country": "GB",
    "wof:name": "SA19 8NY",
    "wof:placetype": "postalcode"
  },
  "geometry": {"coordinates":[-3.874078,52.018108],"type":"Point"}
}
