{
  "type": "Feature",
  "properties": {
    "date:inception_lower": "2001-12-01",
    "date:inception_upper": "2001-12-01",
    "iso:country": "GB",
    "wof:name": "SA19 8NY",
    "wof:placetype": "postalcode"
  },
  "geometry": {"coordinates":[-3.878025,52.016993],"type":"Point"}
}
