{
  "type": "Feature",
  "properties": {
    "iso:country": "GB",
    "wof:name": "SA19 8NY",
    "wof:placetype": "postalcode"
  },
  "geometry": {"coordinates":[-3.878025,52.016993],"type":"Point"}
}
