{
  "type": "Feature",
  "properties": {
    "iso:country":"GB",
    "wof:name":"KT1 2ND",
    "wof:placetype":"postalcode"
},
  "geometry": {"coordinates":[-0.30781907291286,51.40119155487778],"type":"Point"}
}