{
  "type": "Feature",
  "properties": {
    "iso:country": "GB",
    "wof:name": "CV2 3DQ",
    "wof:placetype": "postalcode"
  },
  "geometry": {"coordinates":[-1.46582,52.420565],"type":"Point"}
}
