{
  "type": "Feature",
  "properties": {
    "iso:country":"GB",
    "wof:name":"CV2 3DQ",
    "wof:placetype":"postalcode"
},
  "geometry": {"coordinates":[-1.46582054000098,52.42056460926922],"type":"Point"}
}