{
  "type": "Feature",
  "properties": {
    "iso:country":"GB",
    "wof:name":"LN2 4GA",
    "wof:placetype":"postalcode"
},
  "geometry": {"coordinates":[-0.4773280913107,53.25076115103791],"type":"Point"}
}