{
  "type": "Feature",
  "properties": {
    "date:inception_lower": "2007-01-01",
    "date:inception_upper": "2007-01-01",
    "iso:country": "GB",
    "wof:name": "TF1 1NF",
    "wof:placetype": "postalcode"
  },
  "geometry": {"coordinates":[-2.524088,52.698603],"type":"Point"}
}
