{
  "type": "Feature",
  "properties": {
    "iso:country":"GB",
    "wof:name":"TF1 1NF",
    "wof:placetype":"postalcode"
},
  "geometry": {"coordinates":[-2.52408838169602,52.69860313024757],"type":"Point"}
}