{
  "type": "Feature",
  "properties": {
    "iso:country":"GB",
    "wof:name":"NN2 7BD",
    "wof:placetype":"postalcode"
},
  "geometry": {"coordinates":[-0.90120086899392,52.26258622314609],"type":"Point"}
}