{
  "type": "Feature",
  "properties": {
    "iso:country":"GB",
    "wof:name":"HP1 2LF",
    "wof:placetype":"postalcode"
},
  "geometry": {"coordinates":[-0.49727773906596,51.75497617551807],"type":"Point"}
}