{
  "type": "Feature",
  "properties": {
    "iso:country": "GB",
    "wof:name": "PA36 4AB",
    "wof:placetype": "postalcode"
  },
  "geometry": {"coordinates":[-4.768985,56.517772],"type":"Point"}
}
