{
  "type": "Feature",
  "properties": {
    "iso:country":"GB",
    "wof:name":"RH20 4HF",
    "wof:placetype":"postalcode"
},
  "geometry": {"coordinates":[-0.46817034953486,50.92933096344808],"type":"Point"}
}