{
  "type": "Feature",
  "properties": {
    "iso:country":"GB",
    "wof:name":"MK14 7PL",
    "wof:placetype":"postalcode"
},
  "geometry": {"coordinates":[-0.74637664826161,52.05611267287908],"type":"Point"}
}