{
  "type": "Feature",
  "properties": {
    "date:inception_lower": "1981-06-01",
    "date:inception_upper": "1981-06-01",
    "iso:country": "GB",
    "wof:name": "MK14 7PL",
    "wof:placetype": "postalcode"
  },
  "geometry": {"coordinates":[-0.746377,52.056113],"type":"Point"}
}
