{
  "type": "Feature",
  "properties": {
    "date:inception_lower": "1980-01-01",
    "date:inception_upper": "1980-01-01",
    "iso:country": "GB",
    "wof:name": "CM4 9PD",
    "wof:placetype": "postalcode"
  },
  "geometry": {"coordinates":[0.431916,51.655479],"type":"Point"}
}
