{
  "type": "Feature",
  "properties": {
    "date:inception_lower":"1980-01-01",
    "date:inception_upper":"1980-01-31",
    "iso:country":"GB",
    "wof:name":"PA75 6PT",
    "wof:placetype":"postalcode"
},
  "geometry": {"coordinates":[-6.069164,56.625881],"type":"Point"}
}