{
  "type": "Feature",
  "properties": {
    "iso:country":"GB",
    "wof:name":"PA75 6PT",
    "wof:placetype":"postalcode"
},
  "geometry": {"coordinates":[-6.06916390709457,56.62588089479917],"type":"Point"}
}