{
  "type": "Feature",
  "properties": {
    "iso:country":"GB",
    "wof:name":"PO15 5PJ",
    "wof:placetype":"postalcode"
},
  "geometry": {"coordinates":[-1.21856799901269,50.85596422356494],"type":"Point"}
}