{
  "type": "Feature",
  "properties": {
    "iso:country":"GB",
    "wof:name":"OX29 4NT",
    "wof:placetype":"postalcode"
},
  "geometry": {"coordinates":[-1.37079248442116,51.78383664095629],"type":"Point"}
}