{
  "type": "Feature",
  "properties": {
    "date:inception_lower":"1994-12-01",
    "date:inception_upper":"1994-12-31",
    "iso:country":"GB",
    "wof:name":"E16 3LD",
    "wof:placetype":"postalcode"
},
  "geometry": {"coordinates":[0.037678,51.516115],"type":"Point"}
}