{
  "type": "Feature",
  "properties": {
    "date:inception_lower": "2023-08-01",
    "date:inception_upper": "2023-08-01",
    "iso:country": "GB",
    "wof:name": "EX36 3FR",
    "wof:placetype": "postalcode"
  },
  "geometry": {"coordinates":[-3.844323,51.021829],"type":"Point"}
}
