{
  "type": "Feature",
  "properties": {
    "date:inception_lower":"2000-12-01",
    "date:inception_upper":"2000-12-31",
    "iso:country":"GB",
    "wof:name":"FY8 2ET",
    "wof:placetype":"postalcode"
},
  "geometry": {"coordinates":[-3.03221,53.755583],"type":"Point"}
}