{
  "type": "Feature",
  "properties": {
    "iso:country":"GB",
    "wof:name":"FY8 2ET",
    "wof:placetype":"postalcode"
},
  "geometry": {"coordinates":[-3.03221029416036,53.7555830506107],"type":"Point"}
}