{
  "type": "Feature",
  "properties": {
    "iso:country": "GB",
    "wof:name": "IP30 0HN",
    "wof:placetype": "postalcode"
  },
  "geometry": {"coordinates":[0.806187,52.168206],"type":"Point"}
}
