{
  "type": "Feature",
  "properties": {
    "iso:country":"GB",
    "wof:name":"IP30 0HN",
    "wof:placetype":"postalcode"
},
  "geometry": {"coordinates":[0.80618701146013,52.16820557916559],"type":"Point"}
}