{
  "type": "Feature",
  "properties": {
    "date:inception_lower": "2020-08-01",
    "date:inception_upper": "2020-08-01",
    "iso:country": "GB",
    "wof:name": "EH15 1BN",
    "wof:placetype": "postalcode"
  },
  "geometry": {"coordinates":[-3.120275,55.954461],"type":"Point"}
}
