{
  "type": "Feature",
  "properties": {
    "iso:country":"GB",
    "wof:name":"DH8 5DY",
    "wof:placetype":"postalcode"
},
  "geometry": {"coordinates":[-1.8368259985406,54.85468561021489],"type":"Point"}
}