{
  "type": "Feature",
  "properties": {
    "iso:country":"GB",
    "wof:name":"ML6 8QY",
    "wof:placetype":"postalcode"
},
  "geometry": {"coordinates":[-3.94961524493604,55.84977110339268],"type":"Point"}
}