{
  "type": "Feature",
  "properties": {
    "date:inception_lower": "1996-12-01",
    "date:inception_upper": "1996-12-01",
    "iso:country": "GB",
    "wof:name": "ML6 8QY",
    "wof:placetype": "postalcode"
  },
  "geometry": {"coordinates":[-3.949615,55.849771],"type":"Point"}
}
