{
  "type": "Feature",
  "properties": {
    "iso:country": "GB",
    "wof:name": "MK43 8DH",
    "wof:placetype": "postalcode"
  },
  "geometry": {"coordinates":[-0.619658,52.161143],"type":"Point"}
}
