{
  "type": "Feature",
  "properties": {
    "iso:country": "GB",
    "wof:name": "TN11 9DA",
    "wof:placetype": "postalcode"
  },
  "geometry": {"coordinates":[0.260202,51.208787],"type":"Point"}
}
