{
  "type": "Feature",
  "properties": {
    "date:inception_lower":"1980-01-01",
    "date:inception_upper":"1980-01-31",
    "iso:country":"GB",
    "wof:name":"NR20 3JJ",
    "wof:placetype":"postalcode"
},
  "geometry": {"coordinates":[1.091912,52.668007],"type":"Point"}
}