{
  "type": "Feature",
  "properties": {
    "iso:country": "GB",
    "wof:name": "HR4 8SF",
    "wof:placetype": "postalcode"
  },
  "geometry": {"coordinates":[-2.878441,52.161143],"type":"Point"}
}
