{
  "type": "Feature",
  "properties": {
    "iso:country":"GB",
    "wof:name":"GU24 0DH",
    "wof:placetype":"postalcode"
},
  "geometry": {"coordinates":[-0.65831308737462,51.27669823386969],"type":"Point"}
}