{
  "type": "Feature",
  "properties": {
    "iso:country": "GB",
    "wof:name": "GU24 0DH",
    "wof:placetype": "postalcode"
  },
  "geometry": {"coordinates":[-0.658313,51.276698],"type":"Point"}
}
