{
  "type": "Feature",
  "properties": {
    "iso:country":"GB",
    "wof:name":"OX11 0UE",
    "wof:placetype":"postalcode"
},
  "geometry": {"coordinates":[-1.30779266241015,51.56921006917307],"type":"Point"}
}