{
  "type": "Feature",
  "properties": {
    "iso:country":"GB",
    "wof:name":"SA43 1JS",
    "wof:placetype":"postalcode"
},
  "geometry": {"coordinates":[-4.65972842005165,52.08482530657059],"type":"Point"}
}