{
  "type": "Feature",
  "properties": {
    "iso:country": "GB",
    "wof:name": "BS1 6WX",
    "wof:placetype": "postalcode"
  },
  "geometry": {"coordinates":[-2.592629,51.448104],"type":"Point"}
}
