{
  "type": "Feature",
  "properties": {
    "date:inception_lower":"1980-01-01",
    "date:inception_upper":"1980-01-31",
    "iso:country":"GB",
    "wof:name":"OL10 1AS",
    "wof:placetype":"postalcode"
},
  "geometry": {"coordinates":[-2.219506,53.588388],"type":"Point"}
}