{
  "type": "Feature",
  "properties": {
    "iso:country": "GB",
    "wof:name": "OL10 1AS",
    "wof:placetype": "postalcode"
  },
  "geometry": {"coordinates":[-2.219506,53.588388],"type":"Point"}
}
