{
  "type": "Feature",
  "properties": {
    "iso:country":"GB",
    "wof:name":"NE15 6AE",
    "wof:placetype":"postalcode"
},
  "geometry": {"coordinates":[-1.69185625082194,54.97165822953787],"type":"Point"}
}