{
  "type": "Feature",
  "properties": {
    "date:inception_lower": "1993-01-01",
    "date:inception_upper": "1993-01-01",
    "iso:country": "GB",
    "wof:name": "LE8 0UW",
    "wof:placetype": "postalcode"
  },
  "geometry": {"coordinates":[-0.983767,52.537165],"type":"Point"}
}
