{
  "type": "Feature",
  "properties": {
    "iso:country":"GB",
    "wof:name":"LE8 0UW",
    "wof:placetype":"postalcode"
},
  "geometry": {"coordinates":[-0.98376666216162,52.53716538780463],"type":"Point"}
}