{
  "type": "Feature",
  "properties": {
    "date:inception_lower": "2020-12-01",
    "date:inception_upper": "2020-12-01",
    "iso:country": "GB",
    "wof:name": "YO17 6AF",
    "wof:placetype": "postalcode"
  },
  "geometry": {"coordinates":[-0.819929,54.124559],"type":"Point"}
}
