{
  "type": "Feature",
  "properties": {
    "iso:country": "GB",
    "wof:name": "N1 7BG",
    "wof:placetype": "postalcode"
  },
  "geometry": {"coordinates":[-0.090024,51.53607],"type":"Point"}
}
