{
  "type": "Feature",
  "properties": {
    "iso:country":"GB",
    "wof:name":"YO42 2RF",
    "wof:placetype":"postalcode"
},
  "geometry": {"coordinates":[-0.77510754453121,53.92891495060307],"type":"Point"}
}