{
  "type": "Feature",
  "properties": {
    "iso:country":"GB",
    "wof:name":"AL5 1RU",
    "wof:placetype":"postalcode"
},
  "geometry": {"coordinates":[-0.34069908875965,51.80127352375982],"type":"Point"}
}