{
  "type": "Feature",
  "properties": {
    "iso:country": "GB",
    "wof:name": "S10 1LY",
    "wof:placetype": "postalcode"
  },
  "geometry": {"coordinates":[-1.50031,53.385746],"type":"Point"}
}
