{
  "type": "Feature",
  "properties": {
    "date:inception_lower": "2011-05-01",
    "date:inception_upper": "2011-05-01",
    "iso:country": "GB",
    "wof:name": "L40 4BF",
    "wof:placetype": "postalcode"
  },
  "geometry": {"coordinates":[-2.830933,53.597442],"type":"Point"}
}
