{
  "type": "Feature",
  "properties": {
    "date:inception_lower": "1993-01-01",
    "date:inception_upper": "1993-01-01",
    "iso:country": "GB",
    "wof:name": "DE65 5JF",
    "wof:placetype": "postalcode"
  },
  "geometry": {"coordinates":[-1.636742,52.870691],"type":"Point"}
}
