{
  "type": "Feature",
  "properties": {
    "iso:country":"GB",
    "wof:name":"DE65 5JF",
    "wof:placetype":"postalcode"
},
  "geometry": {"coordinates":[-1.63674221737253,52.87069141876236],"type":"Point"}
}