{
  "type": "Feature",
  "properties": {
    "date:inception_lower": "2000-12-01",
    "date:inception_upper": "2000-12-01",
    "iso:country": "GB",
    "wof:name": "ST13 5TY",
    "wof:placetype": "postalcode"
  },
  "geometry": {"coordinates":[-2.031308,53.100754],"type":"Point"}
}
