{
  "type": "Feature",
  "properties": {
    "date:inception_lower": "2005-10-01",
    "date:inception_upper": "2005-10-01",
    "iso:country": "GB",
    "wof:name": "TW12 3ER",
    "wof:placetype": "postalcode"
  },
  "geometry": {"coordinates":[-0.377917,51.430473],"type":"Point"}
}
