{
  "type": "Feature",
  "properties": {
    "iso:country":"GB",
    "wof:name":"TW12 3ER",
    "wof:placetype":"postalcode"
},
  "geometry": {"coordinates":[-0.37791751023797,51.43047282003637],"type":"Point"}
}