{
  "type": "Feature",
  "properties": {
    "date:inception_lower": "2002-09-01",
    "date:inception_upper": "2002-09-01",
    "iso:country": "GB",
    "wof:name": "CV32 6HD",
    "wof:placetype": "postalcode"
  },
  "geometry": {"coordinates":[-1.537786,52.303848],"type":"Point"}
}
