{
  "type": "Feature",
  "properties": {
    "iso:country":"GB",
    "wof:name":"SW15 5DF",
    "wof:placetype":"postalcode"
},
  "geometry": {"coordinates":[-0.23391062011762,51.45264433696416],"type":"Point"}
}