{
  "type": "Feature",
  "properties": {
    "iso:country":"GB",
    "wof:name":"M22 1RX",
    "wof:placetype":"postalcode"
},
  "geometry": {"coordinates":[-2.2820181094451,53.37520301004169],"type":"Point"}
}