{
  "type": "Feature",
  "properties": {
    "date:inception_lower": "1994-12-01",
    "date:inception_upper": "1994-12-01",
    "iso:country": "GB",
    "wof:name": "AL1 5BU",
    "wof:placetype": "postalcode"
  },
  "geometry": {"coordinates":[-0.325748,51.751075],"type":"Point"}
}
