{
  "type": "Feature",
  "properties": {
    "iso:country":"GB",
    "wof:name":"B32 3BE",
    "wof:placetype":"postalcode"
},
  "geometry": {"coordinates":[-1.98249416853103,52.44044100607676],"type":"Point"}
}