{
  "type": "Feature",
  "properties": {
    "iso:country": "GB",
    "wof:name": "G61 4HJ",
    "wof:placetype": "postalcode"
  },
  "geometry": {"coordinates":[-4.354582,55.921821],"type":"Point"}
}
