{
  "type": "Feature",
  "properties": {
    "date:inception_lower":"1980-01-01",
    "date:inception_upper":"1980-01-31",
    "iso:country":"GB",
    "wof:name":"BH21 2TA",
    "wof:placetype":"postalcode"
},
  "geometry": {"coordinates":[-1.950286,50.811204],"type":"Point"}
}