{
  "type": "Feature",
  "properties": {
    "iso:country":"GB",
    "wof:name":"BH21 2TA",
    "wof:placetype":"postalcode"
},
  "geometry": {"coordinates":[-1.95028606458454,50.81120447544249],"type":"Point"}
}