{
  "type": "Feature",
  "properties": {
    "iso:country":"GB",
    "wof:name":"ST12 9BQ",
    "wof:placetype":"postalcode"
},
  "geometry": {"coordinates":[-2.15918406033407,52.95539587868471],"type":"Point"}
}