{
  "type": "Feature",
  "properties": {
    "date:inception_lower":"2012-03-01",
    "date:inception_upper":"2012-03-31",
    "iso:country":"GB",
    "wof:name":"CF83 2AY",
    "wof:placetype":"postalcode"
},
  "geometry": {"coordinates":[-3.244679,51.573953],"type":"Point"}
}