{
  "type": "Feature",
  "properties": {
    "iso:country": "GB",
    "wof:name": "CF83 2AY",
    "wof:placetype": "postalcode"
  },
  "geometry": {"coordinates":[-3.244679,51.573953],"type":"Point"}
}
