{
  "type": "Feature",
  "properties": {
    "iso:country":"GB",
    "wof:name":"DT2 7SW",
    "wof:placetype":"postalcode"
},
  "geometry": {"coordinates":[-2.39183765918621,50.75851584679587],"type":"Point"}
}