{
  "type": "Feature",
  "properties": {
    "iso:country": "GB",
    "wof:name": "DT2 7SW",
    "wof:placetype": "postalcode"
  },
  "geometry": {"coordinates":[-2.391838,50.758516],"type":"Point"}
}
