{
  "type": "Feature",
  "properties": {
    "iso:country": "GB",
    "wof:name": "NR18 9HU",
    "wof:placetype": "postalcode"
  },
  "geometry": {"coordinates":[1.074305,52.587464],"type":"Point"}
}
