{
  "type": "Feature",
  "properties": {
    "iso:country":"GB",
    "wof:name":"NR18 9HU",
    "wof:placetype":"postalcode"
},
  "geometry": {"coordinates":[1.0743051961447,52.58746390554578],"type":"Point"}
}