{
  "type": "Feature",
  "properties": {
    "iso:country":"GB",
    "wof:name":"CT19 5SF",
    "wof:placetype":"postalcode"
},
  "geometry": {"coordinates":[1.1802696128954,51.08753987478591],"type":"Point"}
}