{
  "type": "Feature",
  "properties": {
    "date:inception_lower": "2020-11-01",
    "date:inception_upper": "2020-11-01",
    "iso:country": "GB",
    "wof:name": "WN7 1DH",
    "wof:placetype": "postalcode"
  },
  "geometry": {"coordinates":[-2.52232,53.502883],"type":"Point"}
}
