{
  "type": "Feature",
  "properties": {
    "iso:country": "GB",
    "wof:name": "CF42 6HL",
    "wof:placetype": "postalcode"
  },
  "geometry": {"coordinates":[-3.508616,51.656388],"type":"Point"}
}
