{
  "type": "Feature",
  "properties": {
    "date:inception_lower":"1985-10-01",
    "date:inception_upper":"1985-10-31",
    "iso:country":"GB",
    "wof:name":"CF42 6HL",
    "wof:placetype":"postalcode"
},
  "geometry": {"coordinates":[-3.508616,51.656388],"type":"Point"}
}