{
  "type": "Feature",
  "properties": {
    "iso:country":"GB",
    "wof:name":"CO16 0HS",
    "wof:placetype":"postalcode"
},
  "geometry": {"coordinates":[1.18065163085899,51.85414895236355],"type":"Point"}
}