{
  "type": "Feature",
  "properties": {
    "iso:country":"GB",
    "wof:name":"IP6 9LB",
    "wof:placetype":"postalcode"
},
  "geometry": {"coordinates":[1.18926088683856,52.13599656533653],"type":"Point"}
}