{
  "type": "Feature",
  "properties": {
    "iso:country": "GB",
    "wof:name": "BL1 2HJ",
    "wof:placetype": "postalcode"
  },
  "geometry": {"coordinates":[-2.429882,53.585774],"type":"Point"}
}
