{
  "type": "Feature",
  "properties": {
    "iso:country":"GB",
    "wof:name":"CW2 8JW",
    "wof:placetype":"postalcode"
},
  "geometry": {"coordinates":[-2.47357563442716,53.07813323337637],"type":"Point"}
}