{
  "type": "Feature",
  "properties": {
    "iso:country":"GB",
    "wof:name":"NE66 2AU",
    "wof:placetype":"postalcode"
},
  "geometry": {"coordinates":[-1.76477581323537,55.40410571305073],"type":"Point"}
}