{
  "type": "Feature",
  "properties": {
    "iso:country": "GB",
    "wof:name": "NE66 2AU",
    "wof:placetype": "postalcode"
  },
  "geometry": {"coordinates":[-1.764947,55.404144],"type":"Point"}
}
