{
  "type": "Feature",
  "properties": {
    "date:inception_lower": "2013-07-01",
    "date:inception_upper": "2013-07-01",
    "iso:country": "GB",
    "wof:name": "WS14 4HX",
    "wof:placetype": "postalcode"
  },
  "geometry": {"coordinates":[-1.803049,52.684794],"type":"Point"}
}
