{
  "type": "Feature",
  "properties": {
    "iso:country":"GB",
    "wof:name":"CM4 0HZ",
    "wof:placetype":"postalcode"
},
  "geometry": {"coordinates":[0.37240253945709,51.68586078238557],"type":"Point"}
}