{
  "type": "Feature",
  "properties": {
    "iso:country":"GB",
    "wof:name":"SN10 3BX",
    "wof:placetype":"postalcode"
},
  "geometry": {"coordinates":[-1.98073729476144,51.35243954370564],"type":"Point"}
}