{
  "type": "Feature",
  "properties": {
    "iso:country":"GB",
    "wof:name":"CV35 9QU",
    "wof:placetype":"postalcode"
},
  "geometry": {"coordinates":[-1.59378763396473,52.19345728146314],"type":"Point"}
}