{
  "type": "Feature",
  "properties": {
    "date:inception_lower": "1980-01-01",
    "date:inception_upper": "1980-01-01",
    "iso:country": "GB",
    "wof:name": "LE9 7GP",
    "wof:placetype": "postalcode"
  },
  "geometry": {"coordinates":[-1.313209,52.574263],"type":"Point"}
}
