{
  "type": "Feature",
  "properties": {
    "iso:country":"GB",
    "wof:name":"LE9 7GP",
    "wof:placetype":"postalcode"
},
  "geometry": {"coordinates":[-1.31320952001639,52.57426288739567],"type":"Point"}
}