{
  "type": "Feature",
  "properties": {
    "iso:country":"GB",
    "wof:name":"TR11 3QJ",
    "wof:placetype":"postalcode"
},
  "geometry": {"coordinates":[-5.07685534611037,50.15236851321053],"type":"Point"}
}