{
  "type": "Feature",
  "properties": {
    "iso:country":"GB",
    "wof:name":"KT15 1NG",
    "wof:placetype":"postalcode"
},
  "geometry": {"coordinates":[-0.49918797247041,51.36675009795607],"type":"Point"}
}