{
  "type": "Feature",
  "properties": {
    "date:inception_lower": "1988-03-01",
    "date:inception_upper": "1988-03-01",
    "iso:country": "GB",
    "wof:name": "KT15 1NG",
    "wof:placetype": "postalcode"
  },
  "geometry": {"coordinates":[-0.499188,51.36675],"type":"Point"}
}
