{
  "type": "Feature",
  "properties": {
    "iso:country":"GB",
    "wof:name":"TN5 7PL",
    "wof:placetype":"postalcode"
},
  "geometry": {"coordinates":[0.44646833403827,51.05777525007219],"type":"Point"}
}