{
  "type": "Feature",
  "properties": {
    "iso:country":"GB",
    "wof:name":"NE26 3UG",
    "wof:placetype":"postalcode"
},
  "geometry": {"coordinates":[-1.46020067671134,55.05366871232788],"type":"Point"}
}