{
  "type": "Feature",
  "properties": {
    "iso:country":"GB",
    "wof:name":"BS20 0FD",
    "wof:placetype":"postalcode"
},
  "geometry": {"coordinates":[-2.69954412625888,51.47441014347426],"type":"Point"}
}