{
  "type": "Feature",
  "properties": {
    "date:inception_lower":"2010-05-01",
    "date:inception_upper":"2010-05-31",
    "iso:country":"GB",
    "wof:name":"BS20 0FD",
    "wof:placetype":"postalcode"
},
  "geometry": {"coordinates":[-2.699544,51.47441],"type":"Point"}
}