{
  "type": "Feature",
  "properties": {
    "date:inception_lower": "1980-01-01",
    "date:inception_upper": "1980-01-01",
    "iso:country": "GB",
    "wof:name": "OX12 9TL",
    "wof:placetype": "postalcode"
  },
  "geometry": {"coordinates":[-1.471412,51.593771],"type":"Point"}
}
