{
  "type": "Feature",
  "properties": {
    "iso:country":"GB",
    "wof:name":"OX12 9TL",
    "wof:placetype":"postalcode"
},
  "geometry": {"coordinates":[-1.47141232019285,51.59377106057993],"type":"Point"}
}