{
  "type": "Feature",
  "properties": {
    "iso:country": "GB",
    "wof:name": "TA20 3NA",
    "wof:placetype": "postalcode"
  },
  "geometry": {"coordinates":[-2.997968,50.896251],"type":"Point"}
}
