{
  "type": "Feature",
  "properties": {
    "date:inception_lower": "1980-01-01",
    "date:inception_upper": "1980-01-01",
    "iso:country": "GB",
    "wof:name": "TA20 3NA",
    "wof:placetype": "postalcode"
  },
  "geometry": {"coordinates":[-2.997968,50.896251],"type":"Point"}
}
