{
  "type": "Feature",
  "properties": {
    "date:inception_lower": "2005-07-01",
    "date:inception_upper": "2005-07-01",
    "iso:country": "GB",
    "wof:name": "PA34 4HF",
    "wof:placetype": "postalcode"
  },
  "geometry": {"coordinates":[-5.478036,56.39812],"type":"Point"}
}
