{
  "type": "Feature",
  "properties": {
    "iso:country": "GB",
    "wof:name": "PA34 4HF",
    "wof:placetype": "postalcode"
  },
  "geometry": {"coordinates":[-5.478036,56.39812],"type":"Point"}
}
