{
  "type": "Feature",
  "properties": {
    "iso:country": "GB",
    "wof:name": "M4 1LT",
    "wof:placetype": "postalcode"
  },
  "geometry": {"coordinates":[-2.234531,53.484146],"type":"Point"}
}
