{
  "type": "Feature",
  "properties": {
    "date:inception_lower":"1980-01-01",
    "date:inception_upper":"1980-01-31",
    "iso:country":"GB",
    "wof:name":"M4 1LT",
    "wof:placetype":"postalcode"
},
  "geometry": {"coordinates":[-2.234531,53.484146],"type":"Point"}
}