{
  "type": "Feature",
  "properties": {
    "iso:country":"GB",
    "wof:name":"M4 1LT",
    "wof:placetype":"postalcode"
},
  "geometry": {"coordinates":[-2.23453325330928,53.48413002203056],"type":"Point"}
}