{
  "type": "Feature",
  "properties": {
    "iso:country":"GB",
    "wof:name":"LU5 5NL",
    "wof:placetype":"postalcode"
},
  "geometry": {"coordinates":[-0.5083482683439,51.91394595999521],"type":"Point"}
}