{
  "type": "Feature",
  "properties": {
    "date:inception_lower": "1980-01-01",
    "date:inception_upper": "1980-01-01",
    "iso:country": "GB",
    "wof:name": "LU5 5NL",
    "wof:placetype": "postalcode"
  },
  "geometry": {"coordinates":[-0.508323,51.913954],"type":"Point"}
}
