{
  "type": "Feature",
  "properties": {
    "iso:country":"GB",
    "wof:name":"SW1X 9JS",
    "wof:placetype":"postalcode"
},
  "geometry": {"coordinates":[-0.15934572570926,51.50047067484635],"type":"Point"}
}