{
  "type": "Feature",
  "properties": {
    "iso:country":"GB",
    "wof:name":"TS10 4AB",
    "wof:placetype":"postalcode"
},
  "geometry": {"coordinates":[-1.08139116640023,54.60551179753689],"type":"Point"}
}