{
  "type": "Feature",
  "properties": {
    "iso:country": "GB",
    "wof:name": "TS10 4AB",
    "wof:placetype": "postalcode"
  },
  "geometry": {"coordinates":[-1.080707,54.605609],"type":"Point"}
}
