{
  "type": "Feature",
  "properties": {
    "date:inception_lower": "1980-01-01",
    "date:inception_upper": "1980-01-01",
    "iso:country": "GB",
    "wof:name": "TS10 4AB",
    "wof:placetype": "postalcode"
  },
  "geometry": {"coordinates":[-1.080707,54.605609],"type":"Point"}
}
