{
  "type": "Feature",
  "properties": {
    "date:inception_lower":"1996-06-01",
    "date:inception_upper":"1996-06-30",
    "iso:country":"GB",
    "wof:name":"AB42 1PH",
    "wof:placetype":"postalcode"
},
  "geometry": {"coordinates":[-1.783336,57.512181],"type":"Point"}
}