{
  "type": "Feature",
  "properties": {
    "iso:country":"GB",
    "wof:name":"AB42 1PH",
    "wof:placetype":"postalcode"
},
  "geometry": {"coordinates":[-1.78333640712535,57.51218118530591],"type":"Point"}
}