{
  "type": "Feature",
  "properties": {
    "iso:country": "GB",
    "wof:name": "AB42 1PH",
    "wof:placetype": "postalcode"
  },
  "geometry": {"coordinates":[-1.783336,57.512181],"type":"Point"}
}
