{
  "type": "Feature",
  "properties": {
    "iso:country": "GB",
    "wof:name": "LL21 9PW",
    "wof:placetype": "postalcode"
  },
  "geometry": {"coordinates":[-3.466077,53.017002],"type":"Point"}
}
