{
  "type": "Feature",
  "properties": {
    "iso:country":"GB",
    "wof:name":"LL21 9PW",
    "wof:placetype":"postalcode"
},
  "geometry": {"coordinates":[-3.46607664979217,53.01700153879054],"type":"Point"}
}