{
  "type": "Feature",
  "properties": {
    "iso:country": "GB",
    "wof:name": "M20 3JZ",
    "wof:placetype": "postalcode"
  },
  "geometry": {"coordinates":[-2.234644,53.427844],"type":"Point"}
}
