{
  "type": "Feature",
  "properties": {
    "iso:country":"GB",
    "wof:name":"M20 3JZ",
    "wof:placetype":"postalcode"
},
  "geometry": {"coordinates":[-2.23464437164359,53.42784385445628],"type":"Point"}
}