{
  "type": "Feature",
  "properties": {
    "iso:country":"GB",
    "wof:name":"DH4 4QL",
    "wof:placetype":"postalcode"
},
  "geometry": {"coordinates":[-1.49986618944047,54.85867278498971],"type":"Point"}
}