{
  "type": "Feature",
  "properties": {
    "iso:country": "GB",
    "wof:name": "DH4 4QL",
    "wof:placetype": "postalcode"
  },
  "geometry": {"coordinates":[-1.499866,54.858673],"type":"Point"}
}
