{
  "type": "Feature",
  "properties": {
    "date:inception_lower": "1995-01-01",
    "date:inception_upper": "1995-01-01",
    "iso:country": "GB",
    "wof:name": "DH4 4QL",
    "wof:placetype": "postalcode"
  },
  "geometry": {"coordinates":[-1.499866,54.858673],"type":"Point"}
}
