{
  "type": "Feature",
  "properties": {
    "iso:country": "GB",
    "wof:name": "IP25 7EQ",
    "wof:placetype": "postalcode"
  },
  "geometry": {"coordinates":[0.805826,52.578621],"type":"Point"}
}
