{
  "type": "Feature",
  "properties": {
    "iso:country":"GB",
    "wof:name":"EX39 1EF",
    "wof:placetype":"postalcode"
},
  "geometry": {"coordinates":[-4.21081148882948,51.0422172789639],"type":"Point"}
}