{
  "type": "Feature",
  "properties": {
    "iso:country":"GB",
    "wof:name":"IG8 7BX",
    "wof:placetype":"postalcode"
},
  "geometry": {"coordinates":[0.03289030791749,51.60405671895928],"type":"Point"}
}