{
  "type": "Feature",
  "properties": {
    "iso:country": "GB",
    "wof:name": "IG8 7BX",
    "wof:placetype": "postalcode"
  },
  "geometry": {"coordinates":[0.03289,51.604057],"type":"Point"}
}
