{
  "type": "Feature",
  "properties": {
    "date:inception_lower": "1980-01-01",
    "date:inception_upper": "1980-01-01",
    "iso:country": "GB",
    "wof:name": "NE23 7NJ",
    "wof:placetype": "postalcode"
  },
  "geometry": {"coordinates":[-1.574415,55.045593],"type":"Point"}
}
