{
  "type": "Feature",
  "properties": {
    "date:inception_lower": "1980-01-01",
    "date:inception_upper": "1980-01-01",
    "iso:country": "GB",
    "wof:name": "NR24 2ES",
    "wof:placetype": "postalcode"
  },
  "geometry": {"coordinates":[1.064994,52.866992],"type":"Point"}
}
