{
  "type": "Feature",
  "properties": {
    "iso:country":"GB",
    "wof:name":"NR24 2ES",
    "wof:placetype":"postalcode"
},
  "geometry": {"coordinates":[1.06496156807439,52.86697506379024],"type":"Point"}
}