{
  "type": "Feature",
  "properties": {
    "date:inception_lower": "1980-01-01",
    "date:inception_upper": "1980-01-01",
    "iso:country": "GB",
    "wof:name": "PA7 5JR",
    "wof:placetype": "postalcode"
  },
  "geometry": {"coordinates":[-4.513694,55.909319],"type":"Point"}
}
