{
  "type": "Feature",
  "properties": {
    "iso:country":"GB",
    "wof:name":"PA7 5JR",
    "wof:placetype":"postalcode"
},
  "geometry": {"coordinates":[-4.51369407591744,55.90931868838182],"type":"Point"}
}