{
  "type": "Feature",
  "properties": {
    "date:inception_lower":"1980-01-01",
    "date:inception_upper":"1980-01-31",
    "iso:country":"GB",
    "wof:name":"WS2 9BY",
    "wof:placetype":"postalcode"
},
  "geometry": {"coordinates":[-1.997788,52.569969],"type":"Point"}
}