{
  "type": "Feature",
  "properties": {
    "iso:country": "GB",
    "wof:name": "WS2 9BY",
    "wof:placetype": "postalcode"
  },
  "geometry": {"coordinates":[-1.997788,52.569969],"type":"Point"}
}
