{
  "type": "Feature",
  "properties": {
    "iso:country":"GB",
    "wof:name":"WS2 9BY",
    "wof:placetype":"postalcode"
},
  "geometry": {"coordinates":[-1.99778779501786,52.56996900376384],"type":"Point"}
}