{
  "type": "Feature",
  "properties": {
    "iso:country": "GB",
    "wof:name": "HA1 1NL",
    "wof:placetype": "postalcode"
  },
  "geometry": {"coordinates":[-0.340983,51.580417],"type":"Point"}
}
