{
  "type": "Feature",
  "properties": {
    "iso:country":"GB",
    "wof:name":"WN4 8DN",
    "wof:placetype":"postalcode"
},
  "geometry": {"coordinates":[-2.64078051081322,53.49813783862056],"type":"Point"}
}