{
  "type": "Feature",
  "properties": {
    "date:inception_lower": "1980-01-01",
    "date:inception_upper": "1980-01-01",
    "iso:country": "GB",
    "wof:name": "CH6 5SU",
    "wof:placetype": "postalcode"
  },
  "geometry": {"coordinates":[-3.100509,53.22303],"type":"Point"}
}
