{
  "type": "Feature",
  "properties": {
    "iso:country": "GB",
    "wof:name": "HP18 0QZ",
    "wof:placetype": "postalcode"
  },
  "geometry": {"coordinates":[-0.84992,51.841189],"type":"Point"}
}
