{
  "type": "Feature",
  "properties": {
    "date:inception_lower": "2000-06-01",
    "date:inception_upper": "2000-06-01",
    "iso:country": "GB",
    "wof:name": "PE28 2RZ",
    "wof:placetype": "postalcode"
  },
  "geometry": {"coordinates":[-0.085068,52.405384],"type":"Point"}
}
