{
  "type": "Feature",
  "properties": {
    "iso:country":"GB",
    "wof:name":"W1H 1FX",
    "wof:placetype":"postalcode"
},
  "geometry": {"coordinates":[-0.16158483765002,51.5207298975832],"type":"Point"}
}