{
  "type": "Feature",
  "properties": {
    "iso:country":"GB",
    "wof:name":"CR0 0TY",
    "wof:placetype":"postalcode"
},
  "geometry": {"coordinates":[-0.02030184066907,51.34950142432528],"type":"Point"}
}