{
  "type": "Feature",
  "properties": {
    "iso:country": "GB",
    "wof:name": "NG10 5HZ",
    "wof:placetype": "postalcode"
  },
  "geometry": {"coordinates":[-1.294222,52.922548],"type":"Point"}
}
