{
  "type": "Feature",
  "properties": {
    "iso:country":"GB",
    "wof:name":"S42 7HB",
    "wof:placetype":"postalcode"
},
  "geometry": {"coordinates":[-1.49621409538444,53.2191751613036],"type":"Point"}
}