{
  "type": "Feature",
  "properties": {
    "date:inception_lower":"1980-01-01",
    "date:inception_upper":"1980-01-31",
    "iso:country":"GB",
    "wof:name":"S42 7HB",
    "wof:placetype":"postalcode"
},
  "geometry": {"coordinates":[-1.496198,53.219194],"type":"Point"}
}