{
  "type": "Feature",
  "properties": {
    "iso:country":"GB",
    "wof:name":"LL61 6AZ",
    "wof:placetype":"postalcode"
},
  "geometry": {"coordinates":[-4.31329567080528,53.17615274198035],"type":"Point"}
}