{
  "type": "Feature",
  "properties": {
    "date:inception_lower":"1980-01-01",
    "date:inception_upper":"1980-01-31",
    "iso:country":"GB",
    "wof:name":"LL61 6AZ",
    "wof:placetype":"postalcode"
},
  "geometry": {"coordinates":[-4.313485,53.176499],"type":"Point"}
}