{
  "type": "Feature",
  "properties": {
    "iso:country":"GB",
    "wof:name":"IP21 4BZ",
    "wof:placetype":"postalcode"
},
  "geometry": {"coordinates":[1.09870825262802,52.34772084377105],"type":"Point"}
}