{
  "type": "Feature",
  "properties": {
    "iso:country":"GB",
    "wof:name":"CV6 1JT",
    "wof:placetype":"postalcode"
},
  "geometry": {"coordinates":[-1.52738886253403,52.41910946147545],"type":"Point"}
}