{
  "type": "Feature",
  "properties": {
    "iso:country":"GB",
    "wof:name":"AL10 0XX",
    "wof:placetype":"postalcode"
},
  "geometry": {"coordinates":[-0.23843398005278,51.76296352573094],"type":"Point"}
}