{
  "type": "Feature",
  "properties": {
    "iso:country":"GB",
    "wof:name":"BN7 2PS",
    "wof:placetype":"postalcode"
},
  "geometry": {"coordinates":[0.01241092414331,50.87558511685468],"type":"Point"}
}