{
  "type": "Feature",
  "properties": {
    "iso:country":"GB",
    "wof:name":"OX14 3BD",
    "wof:placetype":"postalcode"
},
  "geometry": {"coordinates":[-1.22832435273113,51.67553318798299],"type":"Point"}
}