{
  "type": "Feature",
  "properties": {
    "iso:country":"GB",
    "wof:name":"NR7 0RU",
    "wof:placetype":"postalcode"
},
  "geometry": {"coordinates":[1.36597646353639,52.64032405472371],"type":"Point"}
}