{
  "type": "Feature",
  "properties": {
    "date:inception_lower": "1996-12-01",
    "date:inception_upper": "1996-12-01",
    "iso:country": "GB",
    "wof:name": "NR7 0RU",
    "wof:placetype": "postalcode"
  },
  "geometry": {"coordinates":[1.365977,52.640324],"type":"Point"}
}
