{
  "type": "Feature",
  "properties": {
    "date:inception_lower": "1980-01-01",
    "date:inception_upper": "1980-01-01",
    "iso:country": "GB",
    "wof:name": "CH5 2HX",
    "wof:placetype": "postalcode"
  },
  "geometry": {"coordinates":[-3.005577,53.214763],"type":"Point"}
}
