{
  "type": "Feature",
  "properties": {
    "iso:country":"GB",
    "wof:name":"CH5 2HX",
    "wof:placetype":"postalcode"
},
  "geometry": {"coordinates":[-3.00557712542477,53.21476276647545],"type":"Point"}
}