{
  "type": "Feature",
  "properties": {
    "iso:country": "GB",
    "wof:name": "NP12 1GF",
    "wof:placetype": "postalcode"
  },
  "geometry": {"coordinates":[-3.199431,51.679304],"type":"Point"}
}
