{
  "type": "Feature",
  "properties": {
    "date:inception_lower":"1999-06-01",
    "date:inception_upper":"1999-06-30",
    "iso:country":"GB",
    "wof:name":"NP12 1GF",
    "wof:placetype":"postalcode"
},
  "geometry": {"coordinates":[-3.199431,51.679304],"type":"Point"}
}