{
  "type": "Feature",
  "properties": {
    "iso:country":"GB",
    "wof:name":"NP12 1GF",
    "wof:placetype":"postalcode"
},
  "geometry": {"coordinates":[-3.19943062952363,51.6793037139439],"type":"Point"}
}