{
  "type": "Feature",
  "properties": {
    "date:inception_lower": "1980-01-01",
    "date:inception_upper": "1980-01-01",
    "iso:country": "GB",
    "wof:name": "CV36 5DR",
    "wof:placetype": "postalcode"
  },
  "geometry": {"coordinates":[-1.584857,52.096661],"type":"Point"}
}
