{
  "type": "Feature",
  "properties": {
    "iso:country":"GB",
    "wof:name":"CM1 6AS",
    "wof:placetype":"postalcode"
},
  "geometry": {"coordinates":[0.49796353420506,51.76162269776307],"type":"Point"}
}