{
  "type": "Feature",
  "properties": {
    "iso:country": "GB",
    "wof:name": "CM1 6AS",
    "wof:placetype": "postalcode"
  },
  "geometry": {"coordinates":[0.497964,51.761623],"type":"Point"}
}
