{
  "type": "Feature",
  "properties": {
    "iso:country": "GB",
    "wof:name": "DL11 7LY",
    "wof:placetype": "postalcode"
  },
  "geometry": {"coordinates":[-1.846831,54.403071],"type":"Point"}
}
