{
  "type": "Feature",
  "properties": {
    "iso:country":"GB",
    "wof:name":"DL11 7LY",
    "wof:placetype":"postalcode"
},
  "geometry": {"coordinates":[-1.84683136867304,54.4030711025007],"type":"Point"}
}