{
  "type": "Feature",
  "properties": {
    "iso:country": "GB",
    "wof:name": "NE16 4BZ",
    "wof:placetype": "postalcode"
  },
  "geometry": {"coordinates":[-1.679524,54.947049],"type":"Point"}
}
