{
  "type": "Feature",
  "properties": {
    "date:inception_lower": "2007-05-01",
    "date:inception_upper": "2007-05-01",
    "iso:country": "GB",
    "wof:name": "LE65 1NU",
    "wof:placetype": "postalcode"
  },
  "geometry": {"coordinates":[-1.450765,52.748834],"type":"Point"}
}
