{
  "type": "Feature",
  "properties": {
    "iso:country":"GB",
    "wof:name":"LL31 9AY",
    "wof:placetype":"postalcode"
},
  "geometry": {"coordinates":[-3.800521094287,53.28322707421405],"type":"Point"}
}