{
  "type": "Feature",
  "properties": {
    "iso:country":"GB",
    "wof:name":"WF1 4AR",
    "wof:placetype":"postalcode"
},
  "geometry": {"coordinates":[-1.48506590721108,53.69045267643536],"type":"Point"}
}