{
  "type": "Feature",
  "properties": {
    "iso:country":"GB",
    "wof:name":"DN12 4UQ",
    "wof:placetype":"postalcode"
},
  "geometry": {"coordinates":[-1.25140516840214,53.49030543176032],"type":"Point"}
}