{
  "type": "Feature",
  "properties": {
    "iso:country":"GB",
    "wof:name":"NN18 8BX",
    "wof:placetype":"postalcode"
},
  "geometry": {"coordinates":[-0.69741379087557,52.48266563274575],"type":"Point"}
}