{
  "type": "Feature",
  "properties": {
    "date:inception_lower": "1980-01-01",
    "date:inception_upper": "1980-01-01",
    "iso:country": "GB",
    "wof:name": "NN18 8BX",
    "wof:placetype": "postalcode"
  },
  "geometry": {"coordinates":[-0.697414,52.482666],"type":"Point"}
}
