{
  "type": "Feature",
  "properties": {
    "iso:country":"GB",
    "wof:name":"EH16 5UL",
    "wof:placetype":"postalcode"
},
  "geometry": {"coordinates":[-3.15173682669339,55.91703870019906],"type":"Point"}
}