{
  "type": "Feature",
  "properties": {
    "iso:country":"GB",
    "wof:name":"NG22 0AS",
    "wof:placetype":"postalcode"
},
  "geometry": {"coordinates":[-0.96737945062572,53.17270888181237],"type":"Point"}
}