{
  "type": "Feature",
  "properties": {
    "date:inception_lower": "2022-06-01",
    "date:inception_upper": "2022-06-01",
    "iso:country": "GB",
    "wof:name": "PR6 7YN",
    "wof:placetype": "postalcode"
  },
  "geometry": {"coordinates":[-2.629634,53.681847],"type":"Point"}
}
