{
  "type": "Feature",
  "properties": {
    "iso:country":"GB",
    "wof:name":"GL50 4GL",
    "wof:placetype":"postalcode"
},
  "geometry": {"coordinates":[-2.08252767968259,51.91234266556706],"type":"Point"}
}