{
  "type": "Feature",
  "properties": {
    "iso:country": "GB",
    "wof:name": "AB43 8YQ",
    "wof:placetype": "postalcode"
  },
  "geometry": {"coordinates":[-1.925186,57.662773],"type":"Point"}
}
