{
  "type": "Feature",
  "properties": {
    "iso:country":"GB",
    "wof:name":"BS20 6SX",
    "wof:placetype":"postalcode"
},
  "geometry": {"coordinates":[-2.77766082414921,51.47897128705672],"type":"Point"}
}