{
  "type": "Feature",
  "properties": {
    "iso:country":"GB",
    "wof:name":"DH2 3QA",
    "wof:placetype":"postalcode"
},
  "geometry": {"coordinates":[-1.59611968414011,54.82132357775032],"type":"Point"}
}