{
  "type": "Feature",
  "properties": {
    "iso:country": "GB",
    "wof:name": "DH2 3QA",
    "wof:placetype": "postalcode"
  },
  "geometry": {"coordinates":[-1.59612,54.821324],"type":"Point"}
}
