{
  "type": "Feature",
  "properties": {
    "iso:country":"GB",
    "wof:name":"BD16 1PW",
    "wof:placetype":"postalcode"
},
  "geometry": {"coordinates":[-1.82441324836665,53.83141845624446],"type":"Point"}
}