{
  "type": "Feature",
  "properties": {
    "iso:country":"GB",
    "wof:name":"DL7 8HS",
    "wof:placetype":"postalcode"
},
  "geometry": {"coordinates":[-1.44926058665832,54.32685200420432],"type":"Point"}
}