{
  "type": "Feature",
  "properties": {
    "iso:country": "GB",
    "wof:name": "DL7 8HS",
    "wof:placetype": "postalcode"
  },
  "geometry": {"coordinates":[-1.449261,54.326852],"type":"Point"}
}
