{
  "type": "Feature",
  "properties": {
    "date:inception_lower": "1993-01-01",
    "date:inception_upper": "1993-01-01",
    "iso:country": "GB",
    "wof:name": "DL5 4XE",
    "wof:placetype": "postalcode"
  },
  "geometry": {"coordinates":[-1.57954,54.634201],"type":"Point"}
}
