{
  "type": "Feature",
  "properties": {
    "iso:country": "GB",
    "wof:name": "PE12 0BP",
    "wof:placetype": "postalcode"
  },
  "geometry": {"coordinates":[0.081152,52.803617],"type":"Point"}
}
