{
  "type": "Feature",
  "properties": {
    "iso:country":"GB",
    "wof:name":"G11 6BT",
    "wof:placetype":"postalcode"
},
  "geometry": {"coordinates":[-4.31717766392582,55.8682012334026],"type":"Point"}
}