{
  "type": "Feature",
  "properties": {
    "date:inception_lower": "1994-05-01",
    "date:inception_upper": "1994-05-01",
    "iso:country": "GB",
    "wof:name": "PL12 6AN",
    "wof:placetype": "postalcode"
  },
  "geometry": {"coordinates":[-4.209753,50.408422],"type":"Point"}
}
