{
  "type": "Feature",
  "properties": {
    "iso:country": "GB",
    "wof:name": "TR3 7FD",
    "wof:placetype": "postalcode"
  },
  "geometry": {"coordinates":[-5.180135,50.191487],"type":"Point"}
}
