{
  "type": "Feature",
  "properties": {
    "date:inception_lower": "2008-01-01",
    "date:inception_upper": "2008-01-01",
    "iso:country": "GB",
    "wof:name": "TR3 7FD",
    "wof:placetype": "postalcode"
  },
  "geometry": {"coordinates":[-5.180135,50.191487],"type":"Point"}
}
