{
  "type": "Feature",
  "properties": {
    "iso:country":"GB",
    "wof:name":"TR3 7FD",
    "wof:placetype":"postalcode"
},
  "geometry": {"coordinates":[-5.18013466291568,50.19148705848234],"type":"Point"}
}