{
  "type": "Feature",
  "properties": {
    "date:inception_lower": "1998-12-01",
    "date:inception_upper": "1998-12-01",
    "iso:country": "GB",
    "wof:name": "PR1 3AG",
    "wof:placetype": "postalcode"
  },
  "geometry": {"coordinates":[-2.693845,53.758278],"type":"Point"}
}
