{
  "type": "Feature",
  "properties": {
    "iso:country":"GB",
    "wof:name":"PR1 3AG",
    "wof:placetype":"postalcode"
},
  "geometry": {"coordinates":[-2.69385197319865,53.75848726257705],"type":"Point"}
}