{
  "type": "Feature",
  "properties": {
    "iso:country":"GB",
    "wof:name":"PL6 5QB",
    "wof:placetype":"postalcode"
},
  "geometry": {"coordinates":[-4.10638209733786,50.40315415204372],"type":"Point"}
}