{
  "type": "Feature",
  "properties": {
    "date:inception_lower":"1997-12-01",
    "date:inception_upper":"1997-12-31",
    "iso:country":"GB",
    "wof:name":"BS40 9YA",
    "wof:placetype":"postalcode"
},
  "geometry": {"coordinates":[-2.684578,51.389092],"type":"Point"}
}