{
  "type": "Feature",
  "properties": {
    "iso:country":"GB",
    "wof:name":"BS40 9YA",
    "wof:placetype":"postalcode"
},
  "geometry": {"coordinates":[-2.68448873416343,51.38912272039764],"type":"Point"}
}