{
  "type": "Feature",
  "properties": {
    "iso:country": "GB",
    "wof:name": "BS40 9YA",
    "wof:placetype": "postalcode"
  },
  "geometry": {"coordinates":[-2.684578,51.389092],"type":"Point"}
}
