{
  "type": "Feature",
  "properties": {
    "iso:country": "GB",
    "wof:name": "YO30 5GD",
    "wof:placetype": "postalcode"
  },
  "geometry": {"coordinates":[-1.09489,53.980438],"type":"Point"}
}
