{
  "type": "Feature",
  "properties": {
    "iso:country":"GB",
    "wof:name":"CV23 9QE",
    "wof:placetype":"postalcode"
},
  "geometry": {"coordinates":[-1.41825257395267,52.34220620179136],"type":"Point"}
}