{
  "type": "Feature",
  "properties": {
    "iso:country": "GB",
    "wof:name": "CV23 9QE",
    "wof:placetype": "postalcode"
  },
  "geometry": {"coordinates":[-1.418242,52.342223],"type":"Point"}
}
