{
  "type": "Feature",
  "properties": {
    "iso:country":"GB",
    "wof:name":"M6 8RA",
    "wof:placetype":"postalcode"
},
  "geometry": {"coordinates":[-2.29723458246058,53.49231371324453],"type":"Point"}
}