{
  "type": "Feature",
  "properties": {
    "iso:country":"GB",
    "wof:name":"HA7 1DF",
    "wof:placetype":"postalcode"
},
  "geometry": {"coordinates":[-0.2925255858284,51.59964687876834],"type":"Point"}
}