{
  "type": "Feature",
  "properties": {
    "iso:country": "GB",
    "wof:name": "NG23 5GS",
    "wof:placetype": "postalcode"
  },
  "geometry": {"coordinates":[-0.734874,52.990773],"type":"Point"}
}
