{
  "type": "Feature",
  "properties": {
    "date:inception_lower": "1996-12-01",
    "date:inception_upper": "1996-12-01",
    "iso:country": "GB",
    "wof:name": "NG23 5GS",
    "wof:placetype": "postalcode"
  },
  "geometry": {"coordinates":[-0.734874,52.990773],"type":"Point"}
}
