{
  "type": "Feature",
  "properties": {
    "iso:country":"GB",
    "wof:name":"NG23 5GS",
    "wof:placetype":"postalcode"
},
  "geometry": {"coordinates":[-0.73487442038022,52.99077271829444],"type":"Point"}
}