{
  "type": "Feature",
  "properties": {
    "date:inception_lower": "1985-04-01",
    "date:inception_upper": "1985-04-01",
    "iso:country": "GB",
    "wof:name": "IV2 3PE",
    "wof:placetype": "postalcode"
  },
  "geometry": {"coordinates":[-4.208218,57.473854],"type":"Point"}
}
