{
  "type": "Feature",
  "properties": {
    "iso:country": "GB",
    "wof:name": "IV2 3PE",
    "wof:placetype": "postalcode"
  },
  "geometry": {"coordinates":[-4.208218,57.473854],"type":"Point"}
}
