{
  "type": "Feature",
  "properties": {
    "iso:country": "GB",
    "wof:name": "LS15 8EG",
    "wof:placetype": "postalcode"
  },
  "geometry": {"coordinates":[-1.441763,53.806673],"type":"Point"}
}
