{
  "type": "Feature",
  "properties": {
    "iso:country":"GB",
    "wof:name":"YO32 2WS",
    "wof:placetype":"postalcode"
},
  "geometry": {"coordinates":[-1.07879667100767,54.00905072884256],"type":"Point"}
}