{
  "type": "Feature",
  "properties": {
    "date:inception_lower": "2009-04-01",
    "date:inception_upper": "2009-04-01",
    "iso:country": "GB",
    "wof:name": "DG8 8BZ",
    "wof:placetype": "postalcode"
  },
  "geometry": {"coordinates":[-4.364852,54.787135],"type":"Point"}
}
