{
  "type": "Feature",
  "properties": {
    "iso:country": "GB",
    "wof:name": "DG8 8BZ",
    "wof:placetype": "postalcode"
  },
  "geometry": {"coordinates":[-4.364852,54.787135],"type":"Point"}
}
