{
  "type": "Feature",
  "properties": {
    "date:inception_lower": "1980-01-01",
    "date:inception_upper": "1980-01-01",
    "iso:country": "GB",
    "wof:name": "HR1 1RA",
    "wof:placetype": "postalcode"
  },
  "geometry": {"coordinates":[-2.683244,52.059609],"type":"Point"}
}
