{
  "type": "Feature",
  "properties": {
    "iso:country":"GB",
    "wof:name":"HR1 1RA",
    "wof:placetype":"postalcode"
},
  "geometry": {"coordinates":[-2.68324399651087,52.05960871327022],"type":"Point"}
}