{
  "type": "Feature",
  "properties": {
    "iso:country":"GB",
    "wof:name":"G3 6SF",
    "wof:placetype":"postalcode"
},
  "geometry": {"coordinates":[-4.26113224000298,55.86754546997313],"type":"Point"}
}