{
  "type": "Feature",
  "properties": {
    "date:inception_lower": "2020-07-01",
    "date:inception_upper": "2020-07-01",
    "iso:country": "GB",
    "wof:name": "PO31 7GJ",
    "wof:placetype": "postalcode"
  },
  "geometry": {"coordinates":[-1.310031,50.751342],"type":"Point"}
}
