{
  "type": "Feature",
  "properties": {
    "iso:country": "GB",
    "wof:name": "W2 5DL",
    "wof:placetype": "postalcode"
  },
  "geometry": {"coordinates":[-0.195752,51.515487],"type":"Point"}
}
