{
  "type": "Feature",
  "properties": {
    "iso:country":"GB",
    "wof:name":"RG5 4AJ",
    "wof:placetype":"postalcode"
},
  "geometry": {"coordinates":[-0.89649129899608,51.44471949740526],"type":"Point"}
}