{
  "type": "Feature",
  "properties": {
    "iso:country":"GB",
    "wof:name":"PL15 7SD",
    "wof:placetype":"postalcode"
},
  "geometry": {"coordinates":[-4.52843739299739,50.58372896424702],"type":"Point"}
}