{
  "type": "Feature",
  "properties": {
    "date:inception_lower": "1980-01-01",
    "date:inception_upper": "1980-01-01",
    "iso:country": "GB",
    "wof:name": "PL15 7SD",
    "wof:placetype": "postalcode"
  },
  "geometry": {"coordinates":[-4.527895,50.583489],"type":"Point"}
}
