{
  "type": "Feature",
  "properties": {
    "iso:country":"GB",
    "wof:name":"SM2 5QJ",
    "wof:placetype":"postalcode"
},
  "geometry": {"coordinates":[-0.1924310314746,51.34943348426406],"type":"Point"}
}