{
  "type": "Feature",
  "properties": {
    "date:inception_lower": "2020-10-01",
    "date:inception_upper": "2020-10-01",
    "iso:country": "GB",
    "wof:name": "TR27 4FU",
    "wof:placetype": "postalcode"
  },
  "geometry": {"coordinates":[-5.425146,50.189526],"type":"Point"}
}
