{
  "type": "Feature",
  "properties": {
    "iso:country": "GB",
    "wof:name": "TF7 5LW",
    "wof:placetype": "postalcode"
  },
  "geometry": {"coordinates":[-2.468648,52.638397],"type":"Point"}
}
