{
  "type": "Feature",
  "properties": {
    "iso:country":"GB",
    "wof:name":"TF7 5LW",
    "wof:placetype":"postalcode"
},
  "geometry": {"coordinates":[-2.46864760002358,52.63839727843187],"type":"Point"}
}