{
  "type": "Feature",
  "properties": {
    "iso:country":"GB",
    "wof:name":"OX4 7FW",
    "wof:placetype":"postalcode"
},
  "geometry": {"coordinates":[-1.2042338977766,51.71412528550479],"type":"Point"}
}