{
  "type": "Feature",
  "properties": {
    "date:inception_lower": "1992-08-01",
    "date:inception_upper": "1992-08-01",
    "iso:country": "GB",
    "wof:name": "N11 1HH",
    "wof:placetype": "postalcode"
  },
  "geometry": {"coordinates":[-0.15016,51.623325],"type":"Point"}
}
