{
  "type": "Feature",
  "properties": {
    "date:inception_lower": "2000-12-01",
    "date:inception_upper": "2000-12-01",
    "iso:country": "GB",
    "wof:name": "W1G 9TS",
    "wof:placetype": "postalcode"
  },
  "geometry": {"coordinates":[-0.149925,51.519002],"type":"Point"}
}
