{
  "type": "Feature",
  "properties": {
    "iso:country":"GB",
    "wof:name":"SP5 4HY",
    "wof:placetype":"postalcode"
},
  "geometry": {"coordinates":[-1.78038231136121,51.03431629524872],"type":"Point"}
}