{
  "type": "Feature",
  "properties": {
    "iso:country": "GB",
    "wof:name": "SP5 4HY",
    "wof:placetype": "postalcode"
  },
  "geometry": {"coordinates":[-1.780382,51.034316],"type":"Point"}
}
