{
  "type": "Feature",
  "properties": {
    "iso:country":"GB",
    "wof:name":"LA23 3LB",
    "wof:placetype":"postalcode"
},
  "geometry": {"coordinates":[-2.92915433630571,54.34710481830133],"type":"Point"}
}