{
  "type": "Feature",
  "properties": {
    "iso:country": "GB",
    "wof:name": "LA23 3LB",
    "wof:placetype": "postalcode"
  },
  "geometry": {"coordinates":[-2.929073,54.346799],"type":"Point"}
}
