{
  "type": "Feature",
  "properties": {
    "date:inception_lower": "1980-01-01",
    "date:inception_upper": "1980-01-01",
    "iso:country": "GB",
    "wof:name": "CM1 2LA",
    "wof:placetype": "postalcode"
  },
  "geometry": {"coordinates":[0.436968,51.746599],"type":"Point"}
}
