{
  "type": "Feature",
  "properties": {
    "date:inception_lower": "1980-01-01",
    "date:inception_upper": "1980-01-01",
    "iso:country": "GB",
    "wof:name": "SS2 5DT",
    "wof:placetype": "postalcode"
  },
  "geometry": {"coordinates":[0.713017,51.55002],"type":"Point"}
}
