{
  "type": "Feature",
  "properties": {
    "iso:country":"GB",
    "wof:name":"PE11 3TW",
    "wof:placetype":"postalcode"
},
  "geometry": {"coordinates":[-0.16520527977095,52.81590591063733],"type":"Point"}
}