{
  "type": "Feature",
  "properties": {
    "iso:country":"GB",
    "wof:name":"DE13 7ES",
    "wof:placetype":"postalcode"
},
  "geometry": {"coordinates":[-1.74909388140112,52.72966686173582],"type":"Point"}
}