{
  "type": "Feature",
  "properties": {
    "iso:country":"GB",
    "wof:name":"HS2 9AW",
    "wof:placetype":"postalcode"
},
  "geometry": {"coordinates":[-6.78036850784624,58.28303322841773],"type":"Point"}
}