{
  "type": "Feature",
  "properties": {
    "iso:country": "GB",
    "wof:name": "HS2 9AW",
    "wof:placetype": "postalcode"
  },
  "geometry": {"coordinates":[-6.780368,58.283033],"type":"Point"}
}
