{
  "type": "Feature",
  "properties": {
    "iso:country": "GB",
    "wof:name": "DE24 3GL",
    "wof:placetype": "postalcode"
  },
  "geometry": {"coordinates":[-1.488451,52.870146],"type":"Point"}
}
