{
  "type": "Feature",
  "properties": {
    "iso:country":"GB",
    "wof:name":"SO53 2GJ",
    "wof:placetype":"postalcode"
},
  "geometry": {"coordinates":[-1.374907053278,50.9873236692454],"type":"Point"}
}