{
  "type": "Feature",
  "properties": {
    "date:inception_lower":"1984-10-01",
    "date:inception_upper":"1984-10-31",
    "iso:country":"GB",
    "wof:name":"WN5 0LX",
    "wof:placetype":"postalcode"
},
  "geometry": {"coordinates":[-2.666798,53.554659],"type":"Point"}
}