{
  "type": "Feature",
  "properties": {
    "iso:country":"GB",
    "wof:name":"KY8 1JX",
    "wof:placetype":"postalcode"
},
  "geometry": {"coordinates":[-3.03324191557549,56.1717500137107],"type":"Point"}
}