{
  "type": "Feature",
  "properties": {
    "date:inception_lower":"1980-01-01",
    "date:inception_upper":"1980-01-31",
    "iso:country":"GB",
    "wof:name":"SL8 5JD",
    "wof:placetype":"postalcode"
},
  "geometry": {"coordinates":[-0.697161,51.577365],"type":"Point"}
}