{
  "type": "Feature",
  "properties": {
    "iso:country":"GB",
    "wof:name":"SN8 3EB",
    "wof:placetype":"postalcode"
},
  "geometry": {"coordinates":[-1.64493448160615,51.28517584395812],"type":"Point"}
}