{
  "type": "Feature",
  "properties": {
    "iso:country":"GB",
    "wof:name":"PL25 3SJ",
    "wof:placetype":"postalcode"
},
  "geometry": {"coordinates":[-4.73731238778034,50.33854026875651],"type":"Point"}
}