{
  "type": "Feature",
  "properties": {
    "iso:country":"GB",
    "wof:name":"BB8 7DX",
    "wof:placetype":"postalcode"
},
  "geometry": {"coordinates":[-2.14725336302097,53.86623000537057],"type":"Point"}
}