{
  "type": "Feature",
  "properties": {
    "date:inception_lower":"1980-01-01",
    "date:inception_upper":"1980-01-31",
    "iso:country":"GB",
    "wof:name":"BB8 7DX",
    "wof:placetype":"postalcode"
},
  "geometry": {"coordinates":[-2.147253,53.86623],"type":"Point"}
}