{
  "type": "Feature",
  "properties": {
    "iso:country": "GB",
    "wof:name": "NR9 3RF",
    "wof:placetype": "postalcode"
  },
  "geometry": {"coordinates":[1.186701,52.617946],"type":"Point"}
}
