{
  "type": "Feature",
  "properties": {
    "iso:country":"GB",
    "wof:name":"NR9 3RF",
    "wof:placetype":"postalcode"
},
  "geometry": {"coordinates":[1.18670142566629,52.61794583798932],"type":"Point"}
}