{
  "type": "Feature",
  "properties": {
    "date:inception_lower": "1980-01-01",
    "date:inception_upper": "1980-01-01",
    "iso:country": "GB",
    "wof:name": "WR13 6AR",
    "wof:placetype": "postalcode"
  },
  "geometry": {"coordinates":[-2.295461,52.021337],"type":"Point"}
}
