{
  "type": "Feature",
  "properties": {
    "date:inception_lower": "2018-01-01",
    "date:inception_upper": "2018-01-01",
    "iso:country": "GB",
    "wof:name": "WR3 7WD",
    "wof:placetype": "postalcode"
  },
  "geometry": {"coordinates":[-2.195328,52.23138],"type":"Point"}
}
