{
  "type": "Feature",
  "properties": {
    "iso:country": "GB",
    "wof:name": "WR3 7WD",
    "wof:placetype": "postalcode"
  },
  "geometry": {"coordinates":[-2.195564,52.231622],"type":"Point"}
}
