{
  "type": "Feature",
  "properties": {
    "iso:country":"GB",
    "wof:name":"WV3 9PS",
    "wof:placetype":"postalcode"
},
  "geometry": {"coordinates":[-2.14510252251052,52.5859625758203],"type":"Point"}
}