{
  "type": "Feature",
  "properties": {
    "iso:country":"GB",
    "wof:name":"HG3 5EU",
    "wof:placetype":"postalcode"
},
  "geometry": {"coordinates":[-1.68901428133634,54.09252590328175],"type":"Point"}
}