{
  "type": "Feature",
  "properties": {
    "iso:country":"GB",
    "wof:name":"IV20 1SE",
    "wof:placetype":"postalcode"
},
  "geometry": {"coordinates":[-3.91747518692797,57.81827680264097],"type":"Point"}
}