{
  "type": "Feature",
  "properties": {
    "iso:country":"GB",
    "wof:name":"GU1 1QP",
    "wof:placetype":"postalcode"
},
  "geometry": {"coordinates":[-0.57064302459406,51.25817055794074],"type":"Point"}
}