{
  "type": "Feature",
  "properties": {
    "iso:country": "GB",
    "wof:name": "EX2 4LU",
    "wof:placetype": "postalcode"
  },
  "geometry": {"coordinates":[-3.521274,50.718114],"type":"Point"}
}
