{
  "type": "Feature",
  "properties": {
    "iso:country":"GB",
    "wof:name":"NN5 4RD",
    "wof:placetype":"postalcode"
},
  "geometry": {"coordinates":[-0.95660275657313,52.24134026308813],"type":"Point"}
}