{
  "type": "Feature",
  "properties": {
    "iso:country":"GB",
    "wof:name":"NR30 2BG",
    "wof:placetype":"postalcode"
},
  "geometry": {"coordinates":[1.72857813305295,52.60808418028301],"type":"Point"}
}