{
  "type": "Feature",
  "properties": {
    "iso:country":"GB",
    "wof:name":"HP22 5HY",
    "wof:placetype":"postalcode"
},
  "geometry": {"coordinates":[-0.71557542102643,51.80585777776501],"type":"Point"}
}