{
  "type": "Feature",
  "properties": {
    "iso:country": "GB",
    "wof:name": "HP22 5HY",
    "wof:placetype": "postalcode"
  },
  "geometry": {"coordinates":[-0.715575,51.805858],"type":"Point"}
}
