{
  "type": "Feature",
  "properties": {
    "iso:country":"GB",
    "wof:name":"KY2 5UY",
    "wof:placetype":"postalcode"
},
  "geometry": {"coordinates":[-3.2336428810132,56.09715838942657],"type":"Point"}
}