{
  "type": "Feature",
  "properties": {
    "iso:country": "GB",
    "wof:name": "KY2 5UY",
    "wof:placetype": "postalcode"
  },
  "geometry": {"coordinates":[-3.233643,56.097158],"type":"Point"}
}
