{
  "type": "Feature",
  "properties": {
    "iso:country": "GB",
    "wof:name": "PO20 0BZ",
    "wof:placetype": "postalcode"
  },
  "geometry": {"coordinates":[-0.781696,50.730141],"type":"Point"}
}
