{
  "type": "Feature",
  "properties": {
    "iso:country":"GB",
    "wof:name":"KA3 7QA",
    "wof:placetype":"postalcode"
},
  "geometry": {"coordinates":[-4.47729976387721,55.61975878070445],"type":"Point"}
}