{
  "type": "Feature",
  "properties": {
    "date:inception_lower": "1997-12-01",
    "date:inception_upper": "1997-12-01",
    "iso:country": "GB",
    "wof:name": "WF12 9AW",
    "wof:placetype": "postalcode"
  },
  "geometry": {"coordinates":[-1.623904,53.684731],"type":"Point"}
}
