{
  "type": "Feature",
  "properties": {
    "iso:country":"GB",
    "wof:name":"NR5 8RB",
    "wof:placetype":"postalcode"
},
  "geometry": {"coordinates":[1.2370016563567,52.63657340520445],"type":"Point"}
}