{
  "type": "Feature",
  "properties": {
    "iso:country": "GB",
    "wof:name": "EC4M 5AB",
    "wof:placetype": "postalcode"
  },
  "geometry": {"coordinates":[-0.096928,51.512687],"type":"Point"}
}
