{
  "type": "Feature",
  "properties": {
    "iso:country": "GB",
    "wof:name": "W1B 1NU",
    "wof:placetype": "postalcode"
  },
  "geometry": {"coordinates":[-0.145538,51.522231],"type":"Point"}
}
