{
  "type": "Feature",
  "properties": {
    "iso:country":"GB",
    "wof:name":"W1B 1NU",
    "wof:placetype":"postalcode"
},
  "geometry": {"coordinates":[-0.14553832201558,51.52223083412449],"type":"Point"}
}