{
  "type": "Feature",
  "properties": {
    "date:inception_lower":"2002-07-01",
    "date:inception_upper":"2002-07-31",
    "iso:country":"GB",
    "wof:name":"NE8 3JD",
    "wof:placetype":"postalcode"
},
  "geometry": {"coordinates":[-1.586964,54.960519],"type":"Point"}
}