{
  "type": "Feature",
  "properties": {
    "iso:country":"GB",
    "wof:name":"NE8 3JD",
    "wof:placetype":"postalcode"
},
  "geometry": {"coordinates":[-1.58696397543263,54.96051901467553],"type":"Point"}
}