{
  "type": "Feature",
  "properties": {
    "iso:country":"GB",
    "wof:name":"L4 5XE",
    "wof:placetype":"postalcode"
},
  "geometry": {"coordinates":[-2.96716273649095,53.44097518709904],"type":"Point"}
}