{
  "type": "Feature",
  "properties": {
    "iso:country":"GB",
    "wof:name":"SE1 2LN",
    "wof:placetype":"postalcode"
},
  "geometry": {"coordinates":[-0.07624948547357,51.50332756671875],"type":"Point"}
}