{
  "type": "Feature",
  "properties": {
    "date:inception_lower": "1980-01-01",
    "date:inception_upper": "1980-01-01",
    "iso:country": "GB",
    "wof:name": "SE1 2LN",
    "wof:placetype": "postalcode"
  },
  "geometry": {"coordinates":[-0.076249,51.503328],"type":"Point"}
}
