{
  "type": "Feature",
  "properties": {
    "iso:country":"GB",
    "wof:name":"IP14 2QA",
    "wof:placetype":"postalcode"
},
  "geometry": {"coordinates":[0.99457114778637,52.12213756146549],"type":"Point"}
}