{
  "type": "Feature",
  "properties": {
    "date:inception_lower":"1998-12-01",
    "date:inception_upper":"1998-12-31",
    "iso:country":"GB",
    "wof:name":"IP14 2QA",
    "wof:placetype":"postalcode"
},
  "geometry": {"coordinates":[0.994602,52.122153],"type":"Point"}
}