{
  "type": "Feature",
  "properties": {
    "iso:country":"GB",
    "wof:name":"OL12 6TX",
    "wof:placetype":"postalcode"
},
  "geometry": {"coordinates":[-2.16127988296387,53.61876195465693],"type":"Point"}
}