{
  "type": "Feature",
  "properties": {
    "iso:country": "GB",
    "wof:name": "OL12 6TX",
    "wof:placetype": "postalcode"
  },
  "geometry": {"coordinates":[-2.16128,53.618762],"type":"Point"}
}
