{
  "type": "Feature",
  "properties": {
    "iso:country":"GB",
    "wof:name":"B74 2FH",
    "wof:placetype":"postalcode"
},
  "geometry": {"coordinates":[-1.88451339347364,52.56673955383894],"type":"Point"}
}