{
  "type": "Feature",
  "properties": {
    "date:inception_lower": "1980-01-01",
    "date:inception_upper": "1980-01-01",
    "iso:country": "GB",
    "wof:name": "HR9 6QJ",
    "wof:placetype": "postalcode"
  },
  "geometry": {"coordinates":[-2.618603,51.923512],"type":"Point"}
}
