{
  "type": "Feature",
  "properties": {
    "iso:country":"GB",
    "wof:name":"HR9 6QJ",
    "wof:placetype":"postalcode"
},
  "geometry": {"coordinates":[-2.61860261217173,51.92351200432707],"type":"Point"}
}