{
  "type": "Feature",
  "properties": {
    "iso:country": "GB",
    "wof:name": "HR9 6QJ",
    "wof:placetype": "postalcode"
  },
  "geometry": {"coordinates":[-2.618603,51.923512],"type":"Point"}
}
