{
  "type": "Feature",
  "properties": {
    "iso:country":"GB",
    "wof:name":"TN38 0QZ",
    "wof:placetype":"postalcode"
},
  "geometry": {"coordinates":[0.55409594765534,50.8566923149354],"type":"Point"}
}