{
  "type": "Feature",
  "properties": {
    "date:inception_lower":"2007-08-01",
    "date:inception_upper":"2007-08-31",
    "iso:country":"GB",
    "wof:name":"TN38 0QZ",
    "wof:placetype":"postalcode"
},
  "geometry": {"coordinates":[0.554096,50.856692],"type":"Point"}
}