{
  "type": "Feature",
  "properties": {
    "iso:country":"GB",
    "wof:name":"SE16 7DT",
    "wof:placetype":"postalcode"
},
  "geometry": {"coordinates":[-0.05039663563956,51.50069743789296],"type":"Point"}
}