{
  "type": "Feature",
  "properties": {
    "iso:country":"GB",
    "wof:name":"BA5 2QT",
    "wof:placetype":"postalcode"
},
  "geometry": {"coordinates":[-2.65464686291054,51.2163071953847],"type":"Point"}
}