{
  "type": "Feature",
  "properties": {
    "iso:country":"GB",
    "wof:name":"BH23 2DL",
    "wof:placetype":"postalcode"
},
  "geometry": {"coordinates":[-1.79119674326879,50.74039174722159],"type":"Point"}
}