{
  "type": "Feature",
  "properties": {
    "iso:country":"GB",
    "wof:name":"NN5 6AJ",
    "wof:placetype":"postalcode"
},
  "geometry": {"coordinates":[-0.93058606402894,52.24464083548973],"type":"Point"}
}