{
  "type": "Feature",
  "properties": {
    "iso:country":"GB",
    "wof:name":"PO5 4DJ",
    "wof:placetype":"postalcode"
},
  "geometry": {"coordinates":[-1.09461074672243,50.79134616793296],"type":"Point"}
}