{
  "type": "Feature",
  "properties": {
    "iso:country": "GB",
    "wof:name": "PO5 4DJ",
    "wof:placetype": "postalcode"
  },
  "geometry": {"coordinates":[-1.094611,50.791346],"type":"Point"}
}
