{
  "type": "Feature",
  "properties": {
    "iso:country":"GB",
    "wof:name":"L21 4NW",
    "wof:placetype":"postalcode"
},
  "geometry": {"coordinates":[-3.00716925418324,53.46157959562759],"type":"Point"}
}