{
  "type": "Feature",
  "properties": {
    "date:inception_lower": "1980-01-01",
    "date:inception_upper": "1980-01-01",
    "iso:country": "GB",
    "wof:name": "L21 4NW",
    "wof:placetype": "postalcode"
  },
  "geometry": {"coordinates":[-3.007169,53.46158],"type":"Point"}
}
