{
  "type": "Feature",
  "properties": {
    "date:inception_lower":"2005-08-01",
    "date:inception_upper":"2005-08-31",
    "iso:country":"GB",
    "wof:name":"B29 4DH",
    "wof:placetype":"postalcode"
},
  "geometry": {"coordinates":[-1.971308,52.426999],"type":"Point"}
}