{
  "type": "Feature",
  "properties": {
    "iso:country": "GB",
    "wof:name": "B29 4DH",
    "wof:placetype": "postalcode"
  },
  "geometry": {"coordinates":[-1.971308,52.426999],"type":"Point"}
}
