{
  "type": "Feature",
  "properties": {
    "date:inception_lower":"1998-12-01",
    "date:inception_upper":"1998-12-31",
    "iso:country":"GB",
    "wof:name":"PH23 3BE",
    "wof:placetype":"postalcode"
},
  "geometry": {"coordinates":[-3.808244,57.281487],"type":"Point"}
}