{
  "type": "Feature",
  "properties": {
    "iso:country":"GB",
    "wof:name":"PH23 3BE",
    "wof:placetype":"postalcode"
},
  "geometry": {"coordinates":[-3.80824410793704,57.28148679006895],"type":"Point"}
}