{
  "type": "Feature",
  "properties": {
    "iso:country": "GB",
    "wof:name": "SK16 5QE",
    "wof:placetype": "postalcode"
  },
  "geometry": {"coordinates":[-2.075546,53.473515],"type":"Point"}
}
