{
  "type": "Feature",
  "properties": {
    "date:inception_lower":"1990-02-01",
    "date:inception_upper":"1990-02-28",
    "iso:country":"GB",
    "wof:name":"SK16 5QE",
    "wof:placetype":"postalcode"
},
  "geometry": {"coordinates":[-2.075546,53.473515],"type":"Point"}
}