{
  "type": "Feature",
  "properties": {
    "iso:country":"GB",
    "wof:name":"SK16 5QE",
    "wof:placetype":"postalcode"
},
  "geometry": {"coordinates":[-2.07554608655543,53.47351452272363],"type":"Point"}
}