{
  "type": "Feature",
  "properties": {
    "iso:country":"GB",
    "wof:name":"LA11 6ST",
    "wof:placetype":"postalcode"
},
  "geometry": {"coordinates":[-2.94843230096283,54.20076202784974],"type":"Point"}
}