{
  "type": "Feature",
  "properties": {
    "iso:country":"GB",
    "wof:name":"TS26 9NP",
    "wof:placetype":"postalcode"
},
  "geometry": {"coordinates":[-1.23073203389663,54.67894240977338],"type":"Point"}
}