{
  "type": "Feature",
  "properties": {
    "iso:country": "GB",
    "wof:name": "TS26 9NP",
    "wof:placetype": "postalcode"
  },
  "geometry": {"coordinates":[-1.230732,54.678942],"type":"Point"}
}
