{
  "type": "Feature",
  "properties": {
    "date:inception_lower": "1980-01-01",
    "date:inception_upper": "1980-01-01",
    "iso:country": "GB",
    "wof:name": "GL19 4QN",
    "wof:placetype": "postalcode"
  },
  "geometry": {"coordinates":[-2.21238,51.998779],"type":"Point"}
}
