{
  "type": "Feature",
  "properties": {
    "iso:country": "GB",
    "wof:name": "CB24 5PN",
    "wof:placetype": "postalcode"
  },
  "geometry": {"coordinates":[0.017088,52.311126],"type":"Point"}
}
