{
  "type": "Feature",
  "properties": {
    "iso:country":"GB",
    "wof:name":"CB24 5PN",
    "wof:placetype":"postalcode"
},
  "geometry": {"coordinates":[0.01708779163071,52.31112598914557],"type":"Point"}
}