{
  "type": "Feature",
  "properties": {
    "iso:country":"GB",
    "wof:name":"PO2 7PL",
    "wof:placetype":"postalcode"
},
  "geometry": {"coordinates":[-1.07477975693478,50.80986861340402],"type":"Point"}
}