{
  "type": "Feature",
  "properties": {
    "date:inception_lower": "1980-01-01",
    "date:inception_upper": "1980-01-01",
    "iso:country": "GB",
    "wof:name": "PO2 7PL",
    "wof:placetype": "postalcode"
  },
  "geometry": {"coordinates":[-1.07478,50.809869],"type":"Point"}
}
