{
  "type": "Feature",
  "properties": {
    "iso:country":"GB",
    "wof:name":"L24 9HL",
    "wof:placetype":"postalcode"
},
  "geometry": {"coordinates":[-2.86790946318818,53.35392560785132],"type":"Point"}
}