{
  "type": "Feature",
  "properties": {
    "date:inception_lower": "2003-05-01",
    "date:inception_upper": "2003-05-01",
    "iso:country": "GB",
    "wof:name": "L24 9HL",
    "wof:placetype": "postalcode"
  },
  "geometry": {"coordinates":[-2.867909,53.353926],"type":"Point"}
}
