{
  "type": "Feature",
  "properties": {
    "iso:country":"GB",
    "wof:name":"DD5 2TW",
    "wof:placetype":"postalcode"
},
  "geometry": {"coordinates":[-2.84413692595556,56.47614624115266],"type":"Point"}
}