{
  "type": "Feature",
  "properties": {
    "iso:country":"GB",
    "wof:name":"EX7 0EG",
    "wof:placetype":"postalcode"
},
  "geometry": {"coordinates":[-3.47053665474949,50.58604134377609],"type":"Point"}
}