{
  "type": "Feature",
  "properties": {
    "date:inception_lower": "2016-07-01",
    "date:inception_upper": "2016-07-01",
    "iso:country": "GB",
    "wof:name": "CW6 9YG",
    "wof:placetype": "postalcode"
  },
  "geometry": {"coordinates":[-2.668692,53.155016],"type":"Point"}
}
