{
  "type": "Feature",
  "properties": {
    "iso:country":"GB",
    "wof:name":"WA15 9SH",
    "wof:placetype":"postalcode"
},
  "geometry": {"coordinates":[-2.34504035919295,53.37668227903109],"type":"Point"}
}