{
  "type": "Feature",
  "properties": {
    "date:inception_lower":"2001-12-01",
    "date:inception_upper":"2001-12-31",
    "iso:country":"GB",
    "wof:name":"RH14 9SL",
    "wof:placetype":"postalcode"
},
  "geometry": {"coordinates":[-0.448838,51.016455],"type":"Point"}
}