{
  "type": "Feature",
  "properties": {
    "iso:country": "GB",
    "wof:name": "RH14 9SL",
    "wof:placetype": "postalcode"
  },
  "geometry": {"coordinates":[-0.448838,51.016455],"type":"Point"}
}
