{
  "type": "Feature",
  "properties": {
    "date:inception_lower":"1980-01-01",
    "date:inception_upper":"1980-01-31",
    "iso:country":"GB",
    "wof:name":"SA73 1ST",
    "wof:placetype":"postalcode"
},
  "geometry": {"coordinates":[-4.945217,51.709597],"type":"Point"}
}