{
  "type": "Feature",
  "properties": {
    "iso:country":"GB",
    "wof:name":"SA73 1ST",
    "wof:placetype":"postalcode"
},
  "geometry": {"coordinates":[-4.94521725555936,51.70959695897072],"type":"Point"}
}