{
  "type": "Feature",
  "properties": {
    "iso:country": "GB",
    "wof:name": "PE7 1HG",
    "wof:placetype": "postalcode"
  },
  "geometry": {"coordinates":[-0.131815,52.558407],"type":"Point"}
}
