{
  "type": "Feature",
  "properties": {
    "iso:country":"GB",
    "wof:name":"SR1 1JX",
    "wof:placetype":"postalcode"
},
  "geometry": {"coordinates":[-1.37924376557224,54.90456769702725],"type":"Point"}
}