{
  "type": "Feature",
  "properties": {
    "iso:country": "GB",
    "wof:name": "SR1 1JX",
    "wof:placetype": "postalcode"
  },
  "geometry": {"coordinates":[-1.379257,54.904576],"type":"Point"}
}
