{
  "type": "Feature",
  "properties": {
    "iso:country":"GB",
    "wof:name":"E8 1AR",
    "wof:placetype":"postalcode"
},
  "geometry": {"coordinates":[-0.0619245418118,51.54921465606541],"type":"Point"}
}