{
  "type": "Feature",
  "properties": {
    "date:inception_lower": "1980-01-01",
    "date:inception_upper": "1980-01-01",
    "iso:country": "GB",
    "wof:name": "ME14 2UQ",
    "wof:placetype": "postalcode"
  },
  "geometry": {"coordinates":[0.527123,51.27951],"type":"Point"}
}
