{
  "type": "Feature",
  "properties": {
    "iso:country": "GB",
    "wof:name": "ME14 2UQ",
    "wof:placetype": "postalcode"
  },
  "geometry": {"coordinates":[0.527123,51.27951],"type":"Point"}
}
