{
  "type": "Feature",
  "properties": {
    "date:inception_lower": "2016-09-01",
    "date:inception_upper": "2016-09-01",
    "iso:country": "GB",
    "wof:name": "LL17 0EQ",
    "wof:placetype": "postalcode"
  },
  "geometry": {"coordinates":[-3.435441,53.252779],"type":"Point"}
}
