{
  "type": "Feature",
  "properties": {
    "iso:country":"GB",
    "wof:name":"G61 1EF",
    "wof:placetype":"postalcode"
},
  "geometry": {"coordinates":[-4.33951930256752,55.91197049664989],"type":"Point"}
}