{
  "type": "Feature",
  "properties": {
    "iso:country": "GB",
    "wof:name": "G61 1EF",
    "wof:placetype": "postalcode"
  },
  "geometry": {"coordinates":[-4.339519,55.91197],"type":"Point"}
}
