{
  "type": "Feature",
  "properties": {
    "date:inception_lower": "2021-03-01",
    "date:inception_upper": "2021-03-01",
    "iso:country": "GB",
    "wof:name": "YO17 6AL",
    "wof:placetype": "postalcode"
  },
  "geometry": {"coordinates":[-0.820635,54.123964],"type":"Point"}
}
