{
  "type": "Feature",
  "properties": {
    "iso:country":"GB",
    "wof:name":"G84 8RL",
    "wof:placetype":"postalcode"
},
  "geometry": {"coordinates":[-4.78004524052667,56.01686557949605],"type":"Point"}
}