{
  "type": "Feature",
  "properties": {
    "date:inception_lower":"1986-07-01",
    "date:inception_upper":"1986-07-31",
    "iso:country":"GB",
    "wof:name":"SK15 2DR",
    "wof:placetype":"postalcode"
},
  "geometry": {"coordinates":[-2.056136,53.48104],"type":"Point"}
}