{
  "type": "Feature",
  "properties": {
    "iso:country": "GB",
    "wof:name": "SK15 2DR",
    "wof:placetype": "postalcode"
  },
  "geometry": {"coordinates":[-2.056136,53.48104],"type":"Point"}
}
