{
  "type": "Feature",
  "properties": {
    "date:inception_lower": "1980-01-01",
    "date:inception_upper": "1980-01-01",
    "iso:country": "GB",
    "wof:name": "DN6 9JE",
    "wof:placetype": "postalcode"
  },
  "geometry": {"coordinates":[-1.162025,53.59302],"type":"Point"}
}
