{
  "type": "Feature",
  "properties": {
    "iso:country": "GB",
    "wof:name": "DN6 9JE",
    "wof:placetype": "postalcode"
  },
  "geometry": {"coordinates":[-1.161492,53.596261],"type":"Point"}
}
