{
  "type": "Feature",
  "properties": {
    "iso:country":"GB",
    "wof:name":"HA3 5JX",
    "wof:placetype":"postalcode"
},
  "geometry": {"coordinates":[-0.34534622305131,51.60355059710944],"type":"Point"}
}