{
  "type": "Feature",
  "properties": {
    "iso:country":"GB",
    "wof:name":"WR2 5QE",
    "wof:placetype":"postalcode"
},
  "geometry": {"coordinates":[-2.25282292750516,52.19371332194582],"type":"Point"}
}