{
  "type": "Feature",
  "properties": {
    "date:inception_lower":"1980-01-01",
    "date:inception_upper":"1980-01-31",
    "iso:country":"GB",
    "wof:name":"SY10 9DP",
    "wof:placetype":"postalcode"
},
  "geometry": {"coordinates":[-3.10583,52.834433],"type":"Point"}
}