{
  "type": "Feature",
  "properties": {
    "iso:country": "GB",
    "wof:name": "SY10 9DP",
    "wof:placetype": "postalcode"
  },
  "geometry": {"coordinates":[-3.10583,52.834433],"type":"Point"}
}
