{
  "type": "Feature",
  "properties": {
    "iso:country":"GB",
    "wof:name":"SY10 9DP",
    "wof:placetype":"postalcode"
},
  "geometry": {"coordinates":[-3.10582960278332,52.83443283249032],"type":"Point"}
}