{
  "type": "Feature",
  "properties": {
    "iso:country":"GB",
    "wof:name":"TN39 4LF",
    "wof:placetype":"postalcode"
},
  "geometry": {"coordinates":[0.44174339734371,50.84507626876364],"type":"Point"}
}