{
  "type": "Feature",
  "properties": {
    "iso:country":"GB",
    "wof:name":"IP31 2DJ",
    "wof:placetype":"postalcode"
},
  "geometry": {"coordinates":[0.88487195123868,52.32080894483171],"type":"Point"}
}