{
  "type": "Feature",
  "properties": {
    "iso:country":"GB",
    "wof:name":"PE25 1NT",
    "wof:placetype":"postalcode"
},
  "geometry": {"coordinates":[0.33461340198709,53.19382781276841],"type":"Point"}
}