{
  "type": "Feature",
  "properties": {
    "date:inception_lower": "1980-01-01",
    "date:inception_upper": "1980-01-01",
    "iso:country": "GB",
    "wof:name": "PE25 1NT",
    "wof:placetype": "postalcode"
  },
  "geometry": {"coordinates":[0.334595,53.194044],"type":"Point"}
}
