{
  "type": "Feature",
  "properties": {
    "iso:country":"GB",
    "wof:name":"BD6 1BQ",
    "wof:placetype":"postalcode"
},
  "geometry": {"coordinates":[-1.75894815407726,53.76156718600046],"type":"Point"}
}