{
  "type": "Feature",
  "properties": {
    "iso:country":"GB",
    "wof:name":"RM3 9UA",
    "wof:placetype":"postalcode"
},
  "geometry": {"coordinates":[0.23947920811939,51.60768849586915],"type":"Point"}
}