{
  "type": "Feature",
  "properties": {
    "iso:country": "GB",
    "wof:name": "CT16 3EF",
    "wof:placetype": "postalcode"
  },
  "geometry": {"coordinates":[1.265361,51.145217],"type":"Point"}
}
