{
  "type": "Feature",
  "properties": {
    "iso:country": "GB",
    "wof:name": "S26 7YH",
    "wof:placetype": "postalcode"
  },
  "geometry": {"coordinates":[-1.260686,53.322156],"type":"Point"}
}
