{
  "type": "Feature",
  "properties": {
    "iso:country":"GB",
    "wof:name":"S26 7YH",
    "wof:placetype":"postalcode"
},
  "geometry": {"coordinates":[-1.26068563848049,53.32215645433276],"type":"Point"}
}