{
  "type": "Feature",
  "properties": {
    "date:inception_lower": "2021-12-01",
    "date:inception_upper": "2021-12-01",
    "iso:country": "GB",
    "wof:name": "RM17 6FT",
    "wof:placetype": "postalcode"
  },
  "geometry": {"coordinates":[0.322394,51.474842],"type":"Point"}
}
