{
  "type": "Feature",
  "properties": {
    "date:inception_lower":"1980-01-01",
    "date:inception_upper":"1980-01-31",
    "iso:country":"GB",
    "wof:name":"L39 6RX",
    "wof:placetype":"postalcode"
},
  "geometry": {"coordinates":[-2.91882,53.544746],"type":"Point"}
}