{
  "type": "Feature",
  "properties": {
    "iso:country":"GB",
    "wof:name":"L39 6RX",
    "wof:placetype":"postalcode"
},
  "geometry": {"coordinates":[-2.91883493412146,53.54475442135541],"type":"Point"}
}