{
  "type": "Feature",
  "properties": {
    "date:inception_lower": "2018-11-01",
    "date:inception_upper": "2018-11-01",
    "iso:country": "GB",
    "wof:name": "ME10 4FD",
    "wof:placetype": "postalcode"
  },
  "geometry": {"coordinates":[0.748387,51.337672],"type":"Point"}
}
