{
  "type": "Feature",
  "properties": {
    "iso:country":"GB",
    "wof:name":"SL1 3HP",
    "wof:placetype":"postalcode"
},
  "geometry": {"coordinates":[-0.61020737602112,51.5230450150269],"type":"Point"}
}