{
  "type": "Feature",
  "properties": {
    "date:inception_lower":"1980-01-01",
    "date:inception_upper":"1980-01-31",
    "iso:country":"GB",
    "wof:name":"SL1 3HP",
    "wof:placetype":"postalcode"
},
  "geometry": {"coordinates":[-0.610207,51.523045],"type":"Point"}
}