{
  "type": "Feature",
  "properties": {
    "iso:country":"GB",
    "wof:name":"DY8 1BD",
    "wof:placetype":"postalcode"
},
  "geometry": {"coordinates":[-2.14830502404527,52.45042676022585],"type":"Point"}
}