{
  "type": "Feature",
  "properties": {
    "iso:country":"GB",
    "wof:name":"SS5 6BL",
    "wof:placetype":"postalcode"
},
  "geometry": {"coordinates":[0.61847901869491,51.61866649744069],"type":"Point"}
}