{
  "type": "Feature",
  "properties": {
    "iso:country": "GB",
    "wof:name": "SS5 6BL",
    "wof:placetype": "postalcode"
  },
  "geometry": {"coordinates":[0.618507,51.61869],"type":"Point"}
}
