{
  "type": "Feature",
  "properties": {
    "iso:country": "GB",
    "wof:name": "SA5 5LB",
    "wof:placetype": "postalcode"
  },
  "geometry": {"coordinates":[-3.974208,51.649005],"type":"Point"}
}
