{
  "type": "Feature",
  "properties": {
    "iso:country": "GB",
    "wof:name": "CF48 1BF",
    "wof:placetype": "postalcode"
  },
  "geometry": {"coordinates":[-3.410682,51.74604],"type":"Point"}
}
