{
  "type": "Feature",
  "properties": {
    "iso:country": "GB",
    "wof:name": "OL13 0DW",
    "wof:placetype": "postalcode"
  },
  "geometry": {"coordinates":[-2.210313,53.69309],"type":"Point"}
}
