{
  "type": "Feature",
  "properties": {
    "date:inception_lower":"2000-12-01",
    "date:inception_upper":"2000-12-31",
    "iso:country":"GB",
    "wof:name":"OL13 0DW",
    "wof:placetype":"postalcode"
},
  "geometry": {"coordinates":[-2.210313,53.69309],"type":"Point"}
}