{
  "type": "Feature",
  "properties": {
    "iso:country":"GB",
    "wof:name":"DN2 4SB",
    "wof:placetype":"postalcode"
},
  "geometry": {"coordinates":[-1.08362132194376,53.54906489933693],"type":"Point"}
}