{
  "type": "Feature",
  "properties": {
    "iso:country": "GB",
    "wof:name": "DN2 4SB",
    "wof:placetype": "postalcode"
  },
  "geometry": {"coordinates":[-1.083621,53.549065],"type":"Point"}
}
