{
  "type": "Feature",
  "properties": {
    "iso:country":"GB",
    "wof:name":"NE16 6JA",
    "wof:placetype":"postalcode"
},
  "geometry": {"coordinates":[-1.73869786194082,54.90520642253004],"type":"Point"}
}