{
  "type": "Feature",
  "properties": {
    "iso:country":"GB",
    "wof:name":"NR10 3QA",
    "wof:placetype":"postalcode"
},
  "geometry": {"coordinates":[1.31922684733239,52.68946346487586],"type":"Point"}
}