{
  "type": "Feature",
  "properties": {
    "iso:country": "GB",
    "wof:name": "NR10 3QA",
    "wof:placetype": "postalcode"
  },
  "geometry": {"coordinates":[1.319227,52.689463],"type":"Point"}
}
