{
  "type": "Feature",
  "properties": {
    "iso:country":"GB",
    "wof:name":"BH2 5JS",
    "wof:placetype":"postalcode"
},
  "geometry": {"coordinates":[-1.89049240259357,50.7187917782117],"type":"Point"}
}