{
  "type": "Feature",
  "properties": {
    "iso:country": "GB",
    "wof:name": "BH2 5JS",
    "wof:placetype": "postalcode"
  },
  "geometry": {"coordinates":[-1.890492,50.718792],"type":"Point"}
}
