{
  "type": "Feature",
  "properties": {
    "date:inception_lower": "1997-06-01",
    "date:inception_upper": "1997-06-01",
    "iso:country": "GB",
    "wof:name": "CF82 8LB",
    "wof:placetype": "postalcode"
  },
  "geometry": {"coordinates":[-3.239613,51.664572],"type":"Point"}
}
