{
  "type": "Feature",
  "properties": {
    "iso:country":"GB",
    "wof:name":"TS23 2DF",
    "wof:placetype":"postalcode"
},
  "geometry": {"coordinates":[-1.29091191590495,54.61098189613914],"type":"Point"}
}