{
  "type": "Feature",
  "properties": {
    "iso:country":"GB",
    "wof:name":"CF45 4HA",
    "wof:placetype":"postalcode"
},
  "geometry": {"coordinates":[-3.37352838989544,51.68158658860849],"type":"Point"}
}