{
  "type": "Feature",
  "properties": {
    "iso:country":"GB",
    "wof:name":"B90 4EL",
    "wof:placetype":"postalcode"
},
  "geometry": {"coordinates":[-1.79263905797446,52.38309304604359],"type":"Point"}
}