{
  "type": "Feature",
  "properties": {
    "iso:country":"GB",
    "wof:name":"CW6 9JS",
    "wof:placetype":"postalcode"
},
  "geometry": {"coordinates":[-2.60291057892349,53.11997681065527],"type":"Point"}
}