{
  "type": "Feature",
  "properties": {
    "iso:country": "GB",
    "wof:name": "CW6 9JS",
    "wof:placetype": "postalcode"
  },
  "geometry": {"coordinates":[-2.602911,53.119977],"type":"Point"}
}
