{
  "type": "Feature",
  "properties": {
    "iso:country":"GB",
    "wof:name":"S10 2DS",
    "wof:placetype":"postalcode"
},
  "geometry": {"coordinates":[-1.48927472358185,53.37314203586433],"type":"Point"}
}