{
  "type": "Feature",
  "properties": {
    "iso:country":"GB",
    "wof:name":"SW4 9NR",
    "wof:placetype":"postalcode"
},
  "geometry": {"coordinates":[-0.13205499724604,51.45857446219199],"type":"Point"}
}