{
  "type": "Feature",
  "properties": {
    "date:inception_lower": "2006-09-01",
    "date:inception_upper": "2006-09-01",
    "iso:country": "GB",
    "wof:name": "SW4 9NR",
    "wof:placetype": "postalcode"
  },
  "geometry": {"coordinates":[-0.132055,51.458574],"type":"Point"}
}
