{
  "type": "Feature",
  "properties": {
    "iso:country":"GB",
    "wof:name":"HD1 5HQ",
    "wof:placetype":"postalcode"
},
  "geometry": {"coordinates":[-1.7911231306683,53.65698795384074],"type":"Point"}
}