{
  "type": "Feature",
  "properties": {
    "date:inception_lower": "1980-01-01",
    "date:inception_upper": "1980-01-01",
    "iso:country": "GB",
    "wof:name": "TS10 1SW",
    "wof:placetype": "postalcode"
  },
  "geometry": {"coordinates":[-1.0739,54.617722],"type":"Point"}
}
