{
  "type": "Feature",
  "properties": {
    "iso:country":"GB",
    "wof:name":"CM9 6SS",
    "wof:placetype":"postalcode"
},
  "geometry": {"coordinates":[0.61847708272188,51.7106507257412],"type":"Point"}
}