{
  "type": "Feature",
  "properties": {
    "date:inception_lower": "1980-01-01",
    "date:inception_upper": "1980-01-01",
    "iso:country": "GB",
    "wof:name": "DE12 6HJ",
    "wof:placetype": "postalcode"
  },
  "geometry": {"coordinates":[-1.516099,52.747365],"type":"Point"}
}
