{
  "type": "Feature",
  "properties": {
    "iso:country":"GB",
    "wof:name":"DE12 6HJ",
    "wof:placetype":"postalcode"
},
  "geometry": {"coordinates":[-1.51609916883936,52.74736538071527],"type":"Point"}
}