{
  "type": "Feature",
  "properties": {
    "iso:country":"GB",
    "wof:name":"E7 9NF",
    "wof:placetype":"postalcode"
},
  "geometry": {"coordinates":[0.0245507308654,51.54349167836472],"type":"Point"}
}