{
  "type": "Feature",
  "properties": {
    "iso:country":"GB",
    "wof:name":"FY1 4HQ",
    "wof:placetype":"postalcode"
},
  "geometry": {"coordinates":[-3.03856371783486,53.81695500276715],"type":"Point"}
}