{
  "type": "Feature",
  "properties": {
    "iso:country": "GB",
    "wof:name": "FY1 4HQ",
    "wof:placetype": "postalcode"
  },
  "geometry": {"coordinates":[-3.038564,53.816955],"type":"Point"}
}
