{
  "type": "Feature",
  "properties": {
    "iso:country":"GB",
    "wof:name":"DN22 0RH",
    "wof:placetype":"postalcode"
},
  "geometry": {"coordinates":[-0.89024211315417,53.29319095816991],"type":"Point"}
}