{
  "type": "Feature",
  "properties": {
    "iso:country":"GB",
    "wof:name":"LL30 2HR",
    "wof:placetype":"postalcode"
},
  "geometry": {"coordinates":[-3.83929624831981,53.32541863913337],"type":"Point"}
}