{
  "type": "Feature",
  "properties": {
    "iso:country": "GB",
    "wof:name": "LL30 2HR",
    "wof:placetype": "postalcode"
  },
  "geometry": {"coordinates":[-3.839296,53.325419],"type":"Point"}
}
