{
  "type": "Feature",
  "properties": {
    "iso:country":"GB",
    "wof:name":"CW1 4LA",
    "wof:placetype":"postalcode"
},
  "geometry": {"coordinates":[-2.43945429519004,53.10624725492925],"type":"Point"}
}