{
  "type": "Feature",
  "properties": {
    "date:inception_lower":"1994-12-01",
    "date:inception_upper":"1994-12-31",
    "iso:country":"GB",
    "wof:name":"SO14 2LX",
    "wof:placetype":"postalcode"
},
  "geometry": {"coordinates":[-1.405768,50.897848],"type":"Point"}
}