{
  "type": "Feature",
  "properties": {
    "iso:country":"GB",
    "wof:name":"CB1 8RA",
    "wof:placetype":"postalcode"
},
  "geometry": {"coordinates":[0.15892283510014,52.18352273165936],"type":"Point"}
}