{
  "type": "Feature",
  "properties": {
    "iso:country":"GB",
    "wof:name":"PE30 3JG",
    "wof:placetype":"postalcode"
},
  "geometry": {"coordinates":[0.4421623138042,52.78475507014119],"type":"Point"}
}