{
  "type": "Feature",
  "properties": {
    "date:inception_lower": "1994-05-01",
    "date:inception_upper": "1994-05-01",
    "iso:country": "GB",
    "wof:name": "M38 9LN",
    "wof:placetype": "postalcode"
  },
  "geometry": {"coordinates":[-2.405718,53.52616],"type":"Point"}
}
