{
  "type": "Feature",
  "properties": {
    "iso:country":"GB",
    "wof:name":"PL9 8BZ",
    "wof:placetype":"postalcode"
},
  "geometry": {"coordinates":[-4.05868616973351,50.36053005994445],"type":"Point"}
}