{
  "type": "Feature",
  "properties": {
    "iso:country": "GB",
    "wof:name": "PL9 8BZ",
    "wof:placetype": "postalcode"
  },
  "geometry": {"coordinates":[-4.058686,50.36053],"type":"Point"}
}
