{
  "type": "Feature",
  "properties": {
    "iso:country":"GB",
    "wof:name":"PO22 7QB",
    "wof:placetype":"postalcode"
},
  "geometry": {"coordinates":[-0.63716955224101,50.79323965306914],"type":"Point"}
}