{
  "type": "Feature",
  "properties": {
    "iso:country": "GB",
    "wof:name": "PO22 7QB",
    "wof:placetype": "postalcode"
  },
  "geometry": {"coordinates":[-0.63717,50.79324],"type":"Point"}
}
