{
  "type": "Feature",
  "properties": {
    "date:inception_lower":"2004-01-01",
    "date:inception_upper":"2004-01-31",
    "iso:country":"GB",
    "wof:name":"TD12 4DD",
    "wof:placetype":"postalcode"
},
  "geometry": {"coordinates":[-2.252193,55.651655],"type":"Point"}
}