{
  "type": "Feature",
  "properties": {
    "iso:country":"GB",
    "wof:name":"OL2 8EE",
    "wof:placetype":"postalcode"
},
  "geometry": {"coordinates":[-2.08899814078411,53.58752260967447],"type":"Point"}
}