{
  "type": "Feature",
  "properties": {
    "date:inception_lower":"1980-01-01",
    "date:inception_upper":"1980-01-31",
    "iso:country":"GB",
    "wof:name":"L23 6XH",
    "wof:placetype":"postalcode"
},
  "geometry": {"coordinates":[-3.048741,53.488476],"type":"Point"}
}