{
  "type": "Feature",
  "properties": {
    "iso:country": "GB",
    "wof:name": "L23 6XH",
    "wof:placetype": "postalcode"
  },
  "geometry": {"coordinates":[-3.048741,53.488476],"type":"Point"}
}
