{
  "type": "Feature",
  "properties": {
    "date:inception_lower": "1980-01-01",
    "date:inception_upper": "1980-01-01",
    "iso:country": "GB",
    "wof:name": "WS11 1JP",
    "wof:placetype": "postalcode"
  },
  "geometry": {"coordinates":[-2.02895,52.69173],"type":"Point"}
}
