{
  "type": "Feature",
  "properties": {
    "iso:country": "GB",
    "wof:name": "WS11 1JP",
    "wof:placetype": "postalcode"
  },
  "geometry": {"coordinates":[-2.028876,52.69173],"type":"Point"}
}
