{
  "type": "Feature",
  "properties": {
    "iso:country":"GB",
    "wof:name":"WS11 1JP",
    "wof:placetype":"postalcode"
},
  "geometry": {"coordinates":[-2.0275954718812,52.69285530601602],"type":"Point"}
}