{
  "type": "Feature",
  "properties": {
    "iso:country":"GB",
    "wof:name":"OL8 3PQ",
    "wof:placetype":"postalcode"
},
  "geometry": {"coordinates":[-2.12832305273629,53.51393526433374],"type":"Point"}
}