{
  "type": "Feature",
  "properties": {
    "iso:country": "GB",
    "wof:name": "DT4 8EE",
    "wof:placetype": "postalcode"
  },
  "geometry": {"coordinates":[-2.455516,50.609182],"type":"Point"}
}
