{
  "type": "Feature",
  "properties": {
    "iso:country":"GB",
    "wof:name":"DT4 8EE",
    "wof:placetype":"postalcode"
},
  "geometry": {"coordinates":[-2.45550565960931,50.60920205843718],"type":"Point"}
}