{
  "type": "Feature",
  "properties": {
    "iso:country":"GB",
    "wof:name":"CH63 9JB",
    "wof:placetype":"postalcode"
},
  "geometry": {"coordinates":[-3.00018576036603,53.33934359370556],"type":"Point"}
}