{
  "type": "Feature",
  "properties": {
    "iso:country": "GB",
    "wof:name": "N11 2HY",
    "wof:placetype": "postalcode"
  },
  "geometry": {"coordinates":[-0.122695,51.612511],"type":"Point"}
}
