{
  "type": "Feature",
  "properties": {
    "date:inception_lower":"1980-01-01",
    "date:inception_upper":"1980-01-31",
    "iso:country":"GB",
    "wof:name":"N11 2HY",
    "wof:placetype":"postalcode"
},
  "geometry": {"coordinates":[-0.122695,51.612511],"type":"Point"}
}