{
  "type": "Feature",
  "properties": {
    "date:inception_lower": "1980-01-01",
    "date:inception_upper": "1980-01-01",
    "iso:country": "GB",
    "wof:name": "CM4 0LH",
    "wof:placetype": "postalcode"
  },
  "geometry": {"coordinates":[0.31572,51.713437],"type":"Point"}
}
