{
  "type": "Feature",
  "properties": {
    "iso:country":"GB",
    "wof:name":"EH33 1HZ",
    "wof:placetype":"postalcode"
},
  "geometry": {"coordinates":[-2.94672806876644,55.94597477370026],"type":"Point"}
}