{
  "type": "Feature",
  "properties": {
    "iso:country": "GB",
    "wof:name": "S71 2PP",
    "wof:placetype": "postalcode"
  },
  "geometry": {"coordinates":[-1.448301,53.568452],"type":"Point"}
}
