{
  "type": "Feature",
  "properties": {
    "date:inception_lower": "2021-02-01",
    "date:inception_upper": "2021-02-01",
    "iso:country": "GB",
    "wof:name": "SE22 2FA",
    "wof:placetype": "postalcode"
  },
  "geometry": {"coordinates":[-0.072905,51.454245],"type":"Point"}
}
