{
  "type": "Feature",
  "properties": {
    "iso:country": "GB",
    "wof:name": "BA3 5EW",
    "wof:placetype": "postalcode"
  },
  "geometry": {"coordinates":[-2.472007,51.24802],"type":"Point"}
}
