{
  "type": "Feature",
  "properties": {
    "date:inception_lower": "1980-01-01",
    "date:inception_upper": "1980-01-01",
    "iso:country": "GB",
    "wof:name": "BA3 5EW",
    "wof:placetype": "postalcode"
  },
  "geometry": {"coordinates":[-2.47185,51.248133],"type":"Point"}
}
