{
  "type": "Feature",
  "properties": {
    "iso:country": "GB",
    "wof:name": "TN21 0SS",
    "wof:placetype": "postalcode"
  },
  "geometry": {"coordinates":[0.217716,50.972572],"type":"Point"}
}
