{
  "type": "Feature",
  "properties": {
    "iso:country": "GB",
    "wof:name": "TR8 5PT",
    "wof:placetype": "postalcode"
  },
  "geometry": {"coordinates":[-5.13867,50.387636],"type":"Point"}
}
