{
  "type": "Feature",
  "properties": {
    "iso:country":"GB",
    "wof:name":"TR8 5PT",
    "wof:placetype":"postalcode"
},
  "geometry": {"coordinates":[-5.13866960679429,50.38763614733755],"type":"Point"}
}