{
  "type": "Feature",
  "properties": {
    "iso:country":"GB",
    "wof:name":"PL4 0HQ",
    "wof:placetype":"postalcode"
},
  "geometry": {"coordinates":[-4.12878436888848,50.36982685927074],"type":"Point"}
}