{
  "type": "Feature",
  "properties": {
    "iso:country": "GB",
    "wof:name": "PL4 0HQ",
    "wof:placetype": "postalcode"
  },
  "geometry": {"coordinates":[-4.128784,50.369827],"type":"Point"}
}
