{
  "type": "Feature",
  "properties": {
    "iso:country":"GB",
    "wof:name":"HU11 4UJ",
    "wof:placetype":"postalcode"
},
  "geometry": {"coordinates":[-0.13459773200069,53.86438342929787],"type":"Point"}
}