{
  "type": "Feature",
  "properties": {
    "iso:country": "GB",
    "wof:name": "HU11 4UJ",
    "wof:placetype": "postalcode"
  },
  "geometry": {"coordinates":[-0.134598,53.864383],"type":"Point"}
}
