{
  "type": "Feature",
  "properties": {
    "iso:country":"GB",
    "wof:name":"B7 5BP",
    "wof:placetype":"postalcode"
},
  "geometry": {"coordinates":[-1.87243845290897,52.49264152520151],"type":"Point"}
}