{
  "type": "Feature",
  "properties": {
    "iso:country":"GB",
    "wof:name":"CA13 9NP",
    "wof:placetype":"postalcode"
},
  "geometry": {"coordinates":[-3.36117293265734,54.66320979084045],"type":"Point"}
}