{
  "type": "Feature",
  "properties": {
    "iso:country": "GB",
    "wof:name": "CA13 9NP",
    "wof:placetype": "postalcode"
  },
  "geometry": {"coordinates":[-3.361174,54.663217],"type":"Point"}
}
