{
  "type": "Feature",
  "properties": {
    "iso:country":"GB",
    "wof:name":"NR32 3HQ",
    "wof:placetype":"postalcode"
},
  "geometry": {"coordinates":[1.71545297999248,52.48500776330014],"type":"Point"}
}