{
  "type": "Feature",
  "properties": {
    "date:inception_lower": "1990-08-01",
    "date:inception_upper": "1990-08-01",
    "iso:country": "GB",
    "wof:name": "AB22 8PW",
    "wof:placetype": "postalcode"
  },
  "geometry": {"coordinates":[-2.102329,57.182632],"type":"Point"}
}
