{
  "type": "Feature",
  "properties": {
    "iso:country":"GB",
    "wof:name":"AB22 8PW",
    "wof:placetype":"postalcode"
},
  "geometry": {"coordinates":[-2.1023291604793,57.18263199176712],"type":"Point"}
}