{
  "type": "Feature",
  "properties": {
    "date:inception_lower": "1980-01-01",
    "date:inception_upper": "1980-01-01",
    "iso:country": "GB",
    "wof:name": "TF2 7JD",
    "wof:placetype": "postalcode"
  },
  "geometry": {"coordinates":[-2.445651,52.715327],"type":"Point"}
}
