{
  "type": "Feature",
  "properties": {
    "iso:country": "GB",
    "wof:name": "TF2 7JD",
    "wof:placetype": "postalcode"
  },
  "geometry": {"coordinates":[-2.445681,52.715372],"type":"Point"}
}
