{
  "type": "Feature",
  "properties": {
    "iso:country": "GB",
    "wof:name": "NG11 6EQ",
    "wof:placetype": "postalcode"
  },
  "geometry": {"coordinates":[-1.14976,52.894697],"type":"Point"}
}
