{
  "type": "Feature",
  "properties": {
    "date:inception_lower": "2013-10-01",
    "date:inception_upper": "2013-10-01",
    "iso:country": "GB",
    "wof:name": "LS10 4DB",
    "wof:placetype": "postalcode"
  },
  "geometry": {"coordinates":[-1.541332,53.744339],"type":"Point"}
}
