{
  "type": "Feature",
  "properties": {
    "iso:country": "GB",
    "wof:name": "LS10 4DB",
    "wof:placetype": "postalcode"
  },
  "geometry": {"coordinates":[-1.541392,53.744366],"type":"Point"}
}
