{
  "type": "Feature",
  "properties": {
    "date:inception_lower": "1994-12-01",
    "date:inception_upper": "1994-12-01",
    "iso:country": "GB",
    "wof:name": "SO17 3TL",
    "wof:placetype": "postalcode"
  },
  "geometry": {"coordinates":[-1.385116,50.935977],"type":"Point"}
}
