{
  "type": "Feature",
  "properties": {
    "date:inception_lower": "1995-07-01",
    "date:inception_upper": "1995-07-01",
    "iso:country": "GB",
    "wof:name": "RG30 2DE",
    "wof:placetype": "postalcode"
  },
  "geometry": {"coordinates":[-0.998695,51.450124],"type":"Point"}
}
