{
  "type": "Feature",
  "properties": {
    "iso:country": "GB",
    "wof:name": "ST17 9XS",
    "wof:placetype": "postalcode"
  },
  "geometry": {"coordinates":[-2.125512,52.790239],"type":"Point"}
}
