{
  "type": "Feature",
  "properties": {
    "iso:country": "GB",
    "wof:name": "SW6 2XH",
    "wof:placetype": "postalcode"
  },
  "geometry": {"coordinates":[-0.184743,51.476021],"type":"Point"}
}
