{
  "type": "Feature",
  "properties": {
    "date:inception_lower": "2019-04-01",
    "date:inception_upper": "2019-04-01",
    "iso:country": "GB",
    "wof:name": "SW6 2XH",
    "wof:placetype": "postalcode"
  },
  "geometry": {"coordinates":[-0.184743,51.476021],"type":"Point"}
}
