{
  "type": "Feature",
  "properties": {
    "iso:country":"GB",
    "wof:name":"B24 9DZ",
    "wof:placetype":"postalcode"
},
  "geometry": {"coordinates":[-1.82613031339694,52.52313041467976],"type":"Point"}
}