{
  "type": "Feature",
  "properties": {
    "date:inception_lower": "1980-01-01",
    "date:inception_upper": "1980-01-01",
    "iso:country": "GB",
    "wof:name": "LS13 1JL",
    "wof:placetype": "postalcode"
  },
  "geometry": {"coordinates":[-1.659334,53.82177],"type":"Point"}
}
