{
  "type": "Feature",
  "properties": {
    "iso:country": "GB",
    "wof:name": "LS13 1JL",
    "wof:placetype": "postalcode"
  },
  "geometry": {"coordinates":[-1.659334,53.82177],"type":"Point"}
}
