{
  "type": "Feature",
  "properties": {
    "iso:country":"GB",
    "wof:name":"BN1 8TD",
    "wof:placetype":"postalcode"
},
  "geometry": {"coordinates":[-0.14040337026533,50.86392855465098],"type":"Point"}
}