{
  "type": "Feature",
  "properties": {
    "iso:country": "GB",
    "wof:name": "NE61 6DD",
    "wof:placetype": "postalcode"
  },
  "geometry": {"coordinates":[-1.720393,55.124748],"type":"Point"}
}
