{
  "type": "Feature",
  "properties": {
    "iso:country":"GB",
    "wof:name":"CM7 9EJ",
    "wof:placetype":"postalcode"
},
  "geometry": {"coordinates":[0.56711965615698,51.88075638987407],"type":"Point"}
}