{
  "type": "Feature",
  "properties": {
    "iso:country":"GB",
    "wof:name":"YO12 6US",
    "wof:placetype":"postalcode"
},
  "geometry": {"coordinates":[-0.44150850791886,54.29685969699251],"type":"Point"}
}