{
  "type": "Feature",
  "properties": {
    "date:inception_lower": "2005-01-01",
    "date:inception_upper": "2005-01-01",
    "iso:country": "GB",
    "wof:name": "YO12 6US",
    "wof:placetype": "postalcode"
  },
  "geometry": {"coordinates":[-0.441508,54.29686],"type":"Point"}
}
