{
  "type": "Feature",
  "properties": {
    "iso:country":"GB",
    "wof:name":"CM1 2DP",
    "wof:placetype":"postalcode"
},
  "geometry": {"coordinates":[0.45147459070472,51.74883358895081],"type":"Point"}
}