{
  "type": "Feature",
  "properties": {
    "date:inception_lower": "1980-01-01",
    "date:inception_upper": "1980-01-01",
    "iso:country": "GB",
    "wof:name": "CT2 7HE",
    "wof:placetype": "postalcode"
  },
  "geometry": {"coordinates":[1.075358,51.287644],"type":"Point"}
}
