{
  "type": "Feature",
  "properties": {
    "date:inception_lower":"1980-01-01",
    "date:inception_upper":"1980-01-31",
    "iso:country":"GB",
    "wof:name":"CM23 2HR",
    "wof:placetype":"postalcode"
},
  "geometry": {"coordinates":[0.159724,51.875193],"type":"Point"}
}