{
  "type": "Feature",
  "properties": {
    "date:inception_lower": "1980-01-01",
    "date:inception_upper": "1980-01-01",
    "iso:country": "GB",
    "wof:name": "PE30 2HJ",
    "wof:placetype": "postalcode"
  },
  "geometry": {"coordinates":[0.393951,52.766707],"type":"Point"}
}
