{
  "type": "Feature",
  "properties": {
    "iso:country":"GB",
    "wof:name":"PE30 2HJ",
    "wof:placetype":"postalcode"
},
  "geometry": {"coordinates":[0.39404635010229,52.76680870238987],"type":"Point"}
}