{
  "type": "Feature",
  "properties": {
    "iso:country":"GB",
    "wof:name":"SN15 4BU",
    "wof:placetype":"postalcode"
},
  "geometry": {"coordinates":[-2.04011142075264,51.51134213285644],"type":"Point"}
}