{
  "type": "Feature",
  "properties": {
    "iso:country": "GB",
    "wof:name": "WF6 2FX",
    "wof:placetype": "postalcode"
  },
  "geometry": {"coordinates":[-1.419226,53.69922],"type":"Point"}
}
