{
  "type": "Feature",
  "properties": {
    "iso:country": "GB",
    "wof:name": "HP1 1TB",
    "wof:placetype": "postalcode"
  },
  "geometry": {"coordinates":[-0.484052,51.75297],"type":"Point"}
}
