{
  "type": "Feature",
  "properties": {
    "iso:country":"GB",
    "wof:name":"WN6 8PA",
    "wof:placetype":"postalcode"
},
  "geometry": {"coordinates":[-2.65717200361041,53.55984498659581],"type":"Point"}
}