{
  "type": "Feature",
  "properties": {
    "iso:country":"GB",
    "wof:name":"EH3 5DR",
    "wof:placetype":"postalcode"
},
  "geometry": {"coordinates":[-3.20227172467322,55.96062058976008],"type":"Point"}
}