{
  "type": "Feature",
  "properties": {
    "iso:country":"GB",
    "wof:name":"G2 2LD",
    "wof:placetype":"postalcode"
},
  "geometry": {"coordinates":[-4.25915073847295,55.86232420922727],"type":"Point"}
}