{
  "type": "Feature",
  "properties": {
    "iso:country":"GB",
    "wof:name":"AL10 9JN",
    "wof:placetype":"postalcode"
},
  "geometry": {"coordinates":[-0.23276928036815,51.75142260304787],"type":"Point"}
}