{
  "type": "Feature",
  "properties": {
    "iso:country":"GB",
    "wof:name":"CO16 8RX",
    "wof:placetype":"postalcode"
},
  "geometry": {"coordinates":[1.08179228623719,51.79239419433565],"type":"Point"}
}