{
  "type": "Feature",
  "properties": {
    "iso:country":"GB",
    "wof:name":"DA3 7BE",
    "wof:placetype":"postalcode"
},
  "geometry": {"coordinates":[0.29435145392764,51.39665816025488],"type":"Point"}
}