{
  "type": "Feature",
  "properties": {
    "iso:country":"GB",
    "wof:name":"RM12 4SY",
    "wof:placetype":"postalcode"
},
  "geometry": {"coordinates":[0.201836684339,51.56459664274931],"type":"Point"}
}