{
  "type": "Feature",
  "properties": {
    "date:inception_lower": "1980-01-01",
    "date:inception_upper": "1980-01-01",
    "iso:country": "GB",
    "wof:name": "RM12 4SY",
    "wof:placetype": "postalcode"
  },
  "geometry": {"coordinates":[0.201935,51.564588],"type":"Point"}
}
