{
  "type": "Feature",
  "properties": {
    "date:inception_lower":"2008-06-01",
    "date:inception_upper":"2008-06-30",
    "iso:country":"GB",
    "wof:name":"SP11 9FJ",
    "wof:placetype":"postalcode"
},
  "geometry": {"coordinates":[-1.626789,51.254445],"type":"Point"}
}