{
  "type": "Feature",
  "properties": {
    "iso:country":"GB",
    "wof:name":"SK17 6NN",
    "wof:placetype":"postalcode"
},
  "geometry": {"coordinates":[-1.91217055691176,53.25496631141547],"type":"Point"}
}