{
  "type": "Feature",
  "properties": {
    "date:inception_lower": "1980-01-01",
    "date:inception_upper": "1980-01-01",
    "iso:country": "GB",
    "wof:name": "SK17 6NN",
    "wof:placetype": "postalcode"
  },
  "geometry": {"coordinates":[-1.912171,53.254966],"type":"Point"}
}
