{
  "type": "Feature",
  "properties": {
    "iso:country":"GB",
    "wof:name":"HA8 6NN",
    "wof:placetype":"postalcode"
},
  "geometry": {"coordinates":[-0.28763714459259,51.60676944158129],"type":"Point"}
}