{
  "type": "Feature",
  "properties": {
    "iso:country":"GB",
    "wof:name":"RG1 5NA",
    "wof:placetype":"postalcode"
},
  "geometry": {"coordinates":[-0.95042914990675,51.44944985296694],"type":"Point"}
}