{
  "type": "Feature",
  "properties": {
    "iso:country":"GB",
    "wof:name":"SE19 2LF",
    "wof:placetype":"postalcode"
},
  "geometry": {"coordinates":[-0.07836251462595,51.41777015512117],"type":"Point"}
}