{
  "type": "Feature",
  "properties": {
    "date:inception_lower": "1981-07-01",
    "date:inception_upper": "1981-07-01",
    "iso:country": "GB",
    "wof:name": "EH14 5DG",
    "wof:placetype": "postalcode"
  },
  "geometry": {"coordinates":[-3.283545,55.903856],"type":"Point"}
}
