{
  "type": "Feature",
  "properties": {
    "iso:country": "GB",
    "wof:name": "EH14 5DG",
    "wof:placetype": "postalcode"
  },
  "geometry": {"coordinates":[-3.283545,55.903856],"type":"Point"}
}
