{
  "type": "Feature",
  "properties": {
    "iso:country":"GB",
    "wof:name":"B63 3BX",
    "wof:placetype":"postalcode"
},
  "geometry": {"coordinates":[-2.05053917141403,52.44657153163444],"type":"Point"}
}