{
  "type": "Feature",
  "properties": {
    "date:inception_lower": "2022-07-01",
    "date:inception_upper": "2022-07-01",
    "iso:country": "GB",
    "wof:name": "TR1 1QN",
    "wof:placetype": "postalcode"
  },
  "geometry": {"coordinates":[-5.042386,50.256692],"type":"Point"}
}
