{
  "type": "Feature",
  "properties": {
    "iso:country":"GB",
    "wof:name":"TR1 1QN",
    "wof:placetype":"postalcode"
},
  "geometry": {"coordinates":[-5.04306811200091,50.25714259402591],"type":"Point"}
}