{
  "type": "Feature",
  "properties": {
    "date:inception_lower": "1980-01-01",
    "date:inception_upper": "1980-01-01",
    "iso:country": "GB",
    "wof:name": "TR1 1QN",
    "wof:placetype": "postalcode"
  },
  "geometry": {"coordinates":[-5.043068,50.257143],"type":"Point"}
}
