{
  "type": "Feature",
  "properties": {
    "iso:country": "GB",
    "wof:name": "CA7 9BF",
    "wof:placetype": "postalcode"
  },
  "geometry": {"coordinates":[-3.161361,54.82395],"type":"Point"}
}
