{
  "type": "Feature",
  "properties": {
    "iso:country": "GB",
    "wof:name": "TN37 7PE",
    "wof:placetype": "postalcode"
  },
  "geometry": {"coordinates":[0.552096,50.882783],"type":"Point"}
}
