{
  "type": "Feature",
  "properties": {
    "date:inception_lower": "1980-01-01",
    "date:inception_upper": "1980-01-01",
    "iso:country": "GB",
    "wof:name": "TN37 7PE",
    "wof:placetype": "postalcode"
  },
  "geometry": {"coordinates":[0.552096,50.882783],"type":"Point"}
}
