{
  "type": "Feature",
  "properties": {
    "iso:country": "GB",
    "wof:name": "TS13 4LE",
    "wof:placetype": "postalcode"
  },
  "geometry": {"coordinates":[-0.879994,54.554148],"type":"Point"}
}
