{
  "type": "Feature",
  "properties": {
    "iso:country":"GB",
    "wof:name":"TS13 4LE",
    "wof:placetype":"postalcode"
},
  "geometry": {"coordinates":[-0.88013235613764,54.55412677510866],"type":"Point"}
}