{
  "type": "Feature",
  "properties": {
    "date:inception_lower":"1995-01-01",
    "date:inception_upper":"1995-01-31",
    "iso:country":"GB",
    "wof:name":"WA5 3HZ",
    "wof:placetype":"postalcode"
},
  "geometry": {"coordinates":[-2.651528,53.401712],"type":"Point"}
}