{
  "type": "Feature",
  "properties": {
    "iso:country":"GB",
    "wof:name":"WA5 3HZ",
    "wof:placetype":"postalcode"
},
  "geometry": {"coordinates":[-2.65152821464821,53.40171240219681],"type":"Point"}
}