{
  "type": "Feature",
  "properties": {
    "iso:country":"GB",
    "wof:name":"WA15 6LX",
    "wof:placetype":"postalcode"
},
  "geometry": {"coordinates":[-2.32851661756983,53.39372641235546],"type":"Point"}
}