{
  "type": "Feature",
  "properties": {
    "iso:country": "GB",
    "wof:name": "BS5 6SX",
    "wof:placetype": "postalcode"
  },
  "geometry": {"coordinates":[-2.559239,51.473716],"type":"Point"}
}
