{
  "type": "Feature",
  "properties": {
    "iso:country": "GB",
    "wof:name": "HR2 0BL",
    "wof:placetype": "postalcode"
  },
  "geometry": {"coordinates":[-2.848164,51.94321],"type":"Point"}
}
