{
  "type": "Feature",
  "properties": {
    "iso:country":"GB",
    "wof:name":"HR2 0BL",
    "wof:placetype":"postalcode"
},
  "geometry": {"coordinates":[-2.84816444186209,51.94321018551728],"type":"Point"}
}