{
  "type": "Feature",
  "properties": {
    "iso:country": "GB",
    "wof:name": "HU11 5JS",
    "wof:placetype": "postalcode"
  },
  "geometry": {"coordinates":[-0.289854,53.868548],"type":"Point"}
}
