{
  "type": "Feature",
  "properties": {
    "date:inception_lower": "1980-01-01",
    "date:inception_upper": "1980-01-01",
    "iso:country": "GB",
    "wof:name": "DL1 5AJ",
    "wof:placetype": "postalcode"
  },
  "geometry": {"coordinates":[-1.552154,54.512448],"type":"Point"}
}
