{
  "type": "Feature",
  "properties": {
    "iso:country": "GB",
    "wof:name": "DL1 5AJ",
    "wof:placetype": "postalcode"
  },
  "geometry": {"coordinates":[-1.552154,54.512448],"type":"Point"}
}
