{
  "type": "Feature",
  "properties": {
    "iso:country":"GB",
    "wof:name":"DL1 5AJ",
    "wof:placetype":"postalcode"
},
  "geometry": {"coordinates":[-1.55215405572128,54.51244791597443],"type":"Point"}
}