{
  "type": "Feature",
  "properties": {
    "date:inception_lower":"2003-03-01",
    "date:inception_upper":"2003-03-31",
    "iso:country":"GB",
    "wof:name":"DN15 6TP",
    "wof:placetype":"postalcode"
},
  "geometry": {"coordinates":[-0.640162,53.591867],"type":"Point"}
}