{
  "type": "Feature",
  "properties": {
    "iso:country": "GB",
    "wof:name": "DN15 6TP",
    "wof:placetype": "postalcode"
  },
  "geometry": {"coordinates":[-0.640162,53.591867],"type":"Point"}
}
