{
  "type": "Feature",
  "properties": {
    "iso:country":"GB",
    "wof:name":"DN15 6TP",
    "wof:placetype":"postalcode"
},
  "geometry": {"coordinates":[-0.64016233046992,53.59186718642677],"type":"Point"}
}