{
  "type": "Feature",
  "properties": {
    "date:inception_lower": "2003-03-01",
    "date:inception_upper": "2003-03-01",
    "iso:country": "GB",
    "wof:name": "DN15 6TP",
    "wof:placetype": "postalcode"
  },
  "geometry": {"coordinates":[-0.6403,53.591971],"type":"Point"}
}
