{
  "type": "Feature",
  "properties": {
    "iso:country": "GB",
    "wof:name": "CA28 6QQ",
    "wof:placetype": "postalcode"
  },
  "geometry": {"coordinates":[-3.574413,54.582054],"type":"Point"}
}
