{
  "type": "Feature",
  "properties": {
    "iso:country": "GB",
    "wof:name": "PL15 7JB",
    "wof:placetype": "postalcode"
  },
  "geometry": {"coordinates":[-4.390751,50.612677],"type":"Point"}
}
