{
  "type": "Feature",
  "properties": {
    "date:inception_lower": "2012-03-01",
    "date:inception_upper": "2012-03-01",
    "iso:country": "GB",
    "wof:name": "CW11 4BQ",
    "wof:placetype": "postalcode"
  },
  "geometry": {"coordinates":[-2.362819,53.140817],"type":"Point"}
}
