{
  "type": "Feature",
  "properties": {
    "iso:country":"GB",
    "wof:name":"CW11 4BQ",
    "wof:placetype":"postalcode"
},
  "geometry": {"coordinates":[-2.3628190051255,53.14081676709796],"type":"Point"}
}