{
  "type": "Feature",
  "properties": {
    "date:inception_lower": "2017-06-01",
    "date:inception_upper": "2017-06-01",
    "iso:country": "GB",
    "wof:name": "G53 7HP",
    "wof:placetype": "postalcode"
  },
  "geometry": {"coordinates":[-4.3704,55.827708],"type":"Point"}
}
