{
  "type": "Feature",
  "properties": {
    "date:inception_lower":"1980-01-01",
    "date:inception_upper":"1980-01-31",
    "iso:country":"GB",
    "wof:name":"HP8 4TN",
    "wof:placetype":"postalcode"
},
  "geometry": {"coordinates":[-0.573905,51.660204],"type":"Point"}
}