{
  "type": "Feature",
  "properties": {
    "iso:country":"GB",
    "wof:name":"HP8 4TN",
    "wof:placetype":"postalcode"
},
  "geometry": {"coordinates":[-0.5739045880929,51.66020424917689],"type":"Point"}
}