{
  "type": "Feature",
  "properties": {
    "date:inception_lower": "2007-11-01",
    "date:inception_upper": "2007-11-01",
    "iso:country": "GB",
    "wof:name": "OX3 8FW",
    "wof:placetype": "postalcode"
  },
  "geometry": {"coordinates":[-1.193273,51.762307],"type":"Point"}
}
