{
  "type": "Feature",
  "properties": {
    "iso:country": "GB",
    "wof:name": "NE20 0HG",
    "wof:placetype": "postalcode"
  },
  "geometry": {"coordinates":[-1.888316,55.126899],"type":"Point"}
}
