{
  "type": "Feature",
  "properties": {
    "iso:country":"GB",
    "wof:name":"DT2 9NZ",
    "wof:placetype":"postalcode"
},
  "geometry": {"coordinates":[-2.51971046084237,50.79367173621115],"type":"Point"}
}