{
  "type": "Feature",
  "properties": {
    "iso:country": "GB",
    "wof:name": "DT2 9NZ",
    "wof:placetype": "postalcode"
  },
  "geometry": {"coordinates":[-2.51971,50.793672],"type":"Point"}
}
