{
  "type": "Feature",
  "properties": {
    "iso:country":"GB",
    "wof:name":"NP13 1PG",
    "wof:placetype":"postalcode"
},
  "geometry": {"coordinates":[-3.13812483630027,51.73545470548844],"type":"Point"}
}