{
  "type": "Feature",
  "properties": {
    "date:inception_lower": "1980-01-01",
    "date:inception_upper": "1980-01-01",
    "iso:country": "GB",
    "wof:name": "NR5 8XQ",
    "wof:placetype": "postalcode"
  },
  "geometry": {"coordinates":[1.247407,52.639337],"type":"Point"}
}
