{
  "type": "Feature",
  "properties": {
    "iso:country":"GB",
    "wof:name":"NR5 8XQ",
    "wof:placetype":"postalcode"
},
  "geometry": {"coordinates":[1.2474066713851,52.63933722553102],"type":"Point"}
}