{
  "type": "Feature",
  "properties": {
    "iso:country":"GB",
    "wof:name":"NE34 0NB",
    "wof:placetype":"postalcode"
},
  "geometry": {"coordinates":[-1.43922068695634,54.96877935577137],"type":"Point"}
}