{
  "type": "Feature",
  "properties": {
    "iso:country": "GB",
    "wof:name": "EX1 2JW",
    "wof:placetype": "postalcode"
  },
  "geometry": {"coordinates":[-3.52281,50.724434],"type":"Point"}
}
