{
  "type": "Feature",
  "properties": {
    "iso:country":"GB",
    "wof:name":"EX1 2JW",
    "wof:placetype":"postalcode"
},
  "geometry": {"coordinates":[-3.5228101686722,50.7244342828596],"type":"Point"}
}