{
  "type": "Feature",
  "properties": {
    "iso:country": "GB",
    "wof:name": "DD8 5DS",
    "wof:placetype": "postalcode"
  },
  "geometry": {"coordinates":[-3.008691,56.668765],"type":"Point"}
}
