{
  "type": "Feature",
  "properties": {
    "iso:country":"GB",
    "wof:name":"NN6 9SN",
    "wof:placetype":"postalcode"
},
  "geometry": {"coordinates":[-0.83464983565104,52.31896733637774],"type":"Point"}
}