{
  "type": "Feature",
  "properties": {
    "iso:country": "GB",
    "wof:name": "NN6 9SN",
    "wof:placetype": "postalcode"
  },
  "geometry": {"coordinates":[-0.831612,52.317864],"type":"Point"}
}
