{
  "type": "Feature",
  "properties": {
    "iso:country":"GB",
    "wof:name":"PE29 1WS",
    "wof:placetype":"postalcode"
},
  "geometry": {"coordinates":[-0.17579937053415,52.3327669728002],"type":"Point"}
}