{
  "type": "Feature",
  "properties": {
    "iso:country":"GB",
    "wof:name":"KA13 6EA",
    "wof:placetype":"postalcode"
},
  "geometry": {"coordinates":[-4.71203131737317,55.66045354444314],"type":"Point"}
}