{
  "type": "Feature",
  "properties": {
    "iso:country":"GB",
    "wof:name":"KT10 8EX",
    "wof:placetype":"postalcode"
},
  "geometry": {"coordinates":[-0.35563096892951,51.38406713442416],"type":"Point"}
}