{
  "type": "Feature",
  "properties": {
    "iso:country": "GB",
    "wof:name": "CW7 2TW",
    "wof:placetype": "postalcode"
  },
  "geometry": {"coordinates":[-2.550335,53.192872],"type":"Point"}
}
