{
  "type": "Feature",
  "properties": {
    "iso:country":"GB",
    "wof:name":"BN23 5BH",
    "wof:placetype":"postalcode"
},
  "geometry": {"coordinates":[0.33511161533551,50.79695600389466],"type":"Point"}
}