{
  "type": "Feature",
  "properties": {
    "iso:country":"GB",
    "wof:name":"ME17 2HL",
    "wof:placetype":"postalcode"
},
  "geometry": {"coordinates":[0.70962578100933,51.23699546339898],"type":"Point"}
}