{
  "type": "Feature",
  "properties": {
    "iso:country": "GB",
    "wof:name": "LS17 0BG",
    "wof:placetype": "postalcode"
  },
  "geometry": {"coordinates":[-1.551265,53.917916],"type":"Point"}
}
