{
  "type": "Feature",
  "properties": {
    "date:inception_lower": "1980-01-01",
    "date:inception_upper": "1980-01-01",
    "iso:country": "GB",
    "wof:name": "LS17 0BG",
    "wof:placetype": "postalcode"
  },
  "geometry": {"coordinates":[-1.551265,53.917916],"type":"Point"}
}
