{
  "type": "Feature",
  "properties": {
    "iso:country":"GB",
    "wof:name":"LS17 0BG",
    "wof:placetype":"postalcode"
},
  "geometry": {"coordinates":[-1.55125918442454,53.9179001958191],"type":"Point"}
}