{
  "type": "Feature",
  "properties": {
    "iso:country": "GB",
    "wof:name": "SS8 7TD",
    "wof:placetype": "postalcode"
  },
  "geometry": {"coordinates":[0.614686,51.517961],"type":"Point"}
}
