{
  "type": "Feature",
  "properties": {
    "iso:country":"GB",
    "wof:name":"SS8 7TD",
    "wof:placetype":"postalcode"
},
  "geometry": {"coordinates":[0.61468624423109,51.51796112550667],"type":"Point"}
}