{
  "type": "Feature",
  "properties": {
    "iso:country":"GB",
    "wof:name":"SE20 7WA",
    "wof:placetype":"postalcode"
},
  "geometry": {"coordinates":[-0.05367808160673,51.41178729998117],"type":"Point"}
}