{
  "type": "Feature",
  "properties": {
    "iso:country":"GB",
    "wof:name":"N6 4EA",
    "wof:placetype":"postalcode"
},
  "geometry": {"coordinates":[-0.15619949571262,51.58016631041107],"type":"Point"}
}