{
  "type": "Feature",
  "properties": {
    "date:inception_lower": "1980-01-01",
    "date:inception_upper": "1980-01-01",
    "iso:country": "GB",
    "wof:name": "B37 5ER",
    "wof:placetype": "postalcode"
  },
  "geometry": {"coordinates":[-1.75538,52.478928],"type":"Point"}
}
