{
  "type": "Feature",
  "properties": {
    "iso:country":"GB",
    "wof:name":"B37 5ER",
    "wof:placetype":"postalcode"
},
  "geometry": {"coordinates":[-1.75537996168904,52.47892779062072],"type":"Point"}
}