{
  "type": "Feature",
  "properties": {
    "iso:country":"GB",
    "wof:name":"TN6 3BE",
    "wof:placetype":"postalcode"
},
  "geometry": {"coordinates":[0.16871392671736,51.04495893779031],"type":"Point"}
}