{
  "type": "Feature",
  "properties": {
    "iso:country": "GB",
    "wof:name": "PR2 5TR",
    "wof:placetype": "postalcode"
  },
  "geometry": {"coordinates":[-2.632108,53.799254],"type":"Point"}
}
