{
  "type": "Feature",
  "properties": {
    "iso:country": "GB",
    "wof:name": "NN9 5EG",
    "wof:placetype": "postalcode"
  },
  "geometry": {"coordinates":[-0.617125,52.329955],"type":"Point"}
}
