{
  "type": "Feature",
  "properties": {
    "iso:country":"GB",
    "wof:name":"W1B 5BD",
    "wof:placetype":"postalcode"
},
  "geometry": {"coordinates":[-0.14052632926324,51.51327588986339],"type":"Point"}
}