{
  "type": "Feature",
  "properties": {
    "iso:country":"GB",
    "wof:name":"CH45 1HE",
    "wof:placetype":"postalcode"
},
  "geometry": {"coordinates":[-3.0401209496579,53.43182255572264],"type":"Point"}
}