{
  "type": "Feature",
  "properties": {
    "iso:country":"GB",
    "wof:name":"AL5 1JP",
    "wof:placetype":"postalcode"
},
  "geometry": {"coordinates":[-0.32983157729372,51.80531887379061],"type":"Point"}
}