{
  "type": "Feature",
  "properties": {
    "iso:country":"GB",
    "wof:name":"WR1 1HU",
    "wof:placetype":"postalcode"
},
  "geometry": {"coordinates":[-2.22580495552979,52.20284848654667],"type":"Point"}
}