{
  "type": "Feature",
  "properties": {
    "iso:country":"GB",
    "wof:name":"LU7 2LZ",
    "wof:placetype":"postalcode"
},
  "geometry": {"coordinates":[-0.67292102056455,51.91435191966247],"type":"Point"}
}