{
  "type": "Feature",
  "properties": {
    "iso:country":"GB",
    "wof:name":"NG17 3EH",
    "wof:placetype":"postalcode"
},
  "geometry": {"coordinates":[-1.26700950322774,53.14208248278618],"type":"Point"}
}