{
  "type": "Feature",
  "properties": {
    "date:inception_lower": "1983-03-01",
    "date:inception_upper": "1983-03-01",
    "iso:country": "GB",
    "wof:name": "EX6 8SB",
    "wof:placetype": "postalcode"
  },
  "geometry": {"coordinates":[-3.450222,50.62647],"type":"Point"}
}
