{
  "type": "Feature",
  "properties": {
    "iso:country":"GB",
    "wof:name":"EX6 8SB",
    "wof:placetype":"postalcode"
},
  "geometry": {"coordinates":[-3.45022249215216,50.62646965712142],"type":"Point"}
}