{
  "type": "Feature",
  "properties": {
    "iso:country":"GB",
    "wof:name":"IP7 5EF",
    "wof:placetype":"postalcode"
},
  "geometry": {"coordinates":[0.95363688517809,52.04443278351202],"type":"Point"}
}