{
  "type": "Feature",
  "properties": {
    "date:inception_lower": "2000-10-01",
    "date:inception_upper": "2000-10-01",
    "iso:country": "GB",
    "wof:name": "WD25 0AZ",
    "wof:placetype": "postalcode"
  },
  "geometry": {"coordinates":[-0.408682,51.686506],"type":"Point"}
}
