{
  "type": "Feature",
  "properties": {
    "iso:country":"GB",
    "wof:name":"WD25 0AZ",
    "wof:placetype":"postalcode"
},
  "geometry": {"coordinates":[-0.4086818463081,51.68650554090947],"type":"Point"}
}