{
  "type": "Feature",
  "properties": {
    "iso:country": "GB",
    "wof:name": "EX8 5PP",
    "wof:placetype": "postalcode"
  },
  "geometry": {"coordinates":[-3.392687,50.643468],"type":"Point"}
}
