{
  "type": "Feature",
  "properties": {
    "iso:country":"GB",
    "wof:name":"EX8 5PP",
    "wof:placetype":"postalcode"
},
  "geometry": {"coordinates":[-3.39268670755878,50.64346770234842],"type":"Point"}
}