{
  "type": "Feature",
  "properties": {
    "iso:country": "GB",
    "wof:name": "FY1 4RZ",
    "wof:placetype": "postalcode"
  },
  "geometry": {"coordinates":[-3.054095,53.816073],"type":"Point"}
}
