{
  "type": "Feature",
  "properties": {
    "iso:country":"GB",
    "wof:name":"CH41 9HT",
    "wof:placetype":"postalcode"
},
  "geometry": {"coordinates":[-3.01383673887919,53.38232172401154],"type":"Point"}
}