{
  "type": "Feature",
  "properties": {
    "date:inception_lower": "1999-06-01",
    "date:inception_upper": "1999-06-01",
    "iso:country": "GB",
    "wof:name": "CH41 9HT",
    "wof:placetype": "postalcode"
  },
  "geometry": {"coordinates":[-3.013836,53.382312],"type":"Point"}
}
