{
  "type": "Feature",
  "properties": {
    "iso:country": "GB",
    "wof:name": "BB5 6RX",
    "wof:placetype": "postalcode"
  },
  "geometry": {"coordinates":[-2.353454,53.75265],"type":"Point"}
}
