{
  "type": "Feature",
  "properties": {
    "date:inception_lower": "1993-08-01",
    "date:inception_upper": "1993-08-01",
    "iso:country": "GB",
    "wof:name": "SP7 8JS",
    "wof:placetype": "postalcode"
  },
  "geometry": {"coordinates":[-2.197632,51.005741],"type":"Point"}
}
