{
  "type": "Feature",
  "properties": {
    "date:inception_lower": "1980-01-01",
    "date:inception_upper": "1980-01-01",
    "iso:country": "GB",
    "wof:name": "SK10 3JJ",
    "wof:placetype": "postalcode"
  },
  "geometry": {"coordinates":[-2.177852,53.266892],"type":"Point"}
}
