{
  "type": "Feature",
  "properties": {
    "iso:country": "GB",
    "wof:name": "SK10 3JJ",
    "wof:placetype": "postalcode"
  },
  "geometry": {"coordinates":[-2.177852,53.266892],"type":"Point"}
}
