{
  "type": "Feature",
  "properties": {
    "iso:country":"GB",
    "wof:name":"SK10 3JJ",
    "wof:placetype":"postalcode"
},
  "geometry": {"coordinates":[-2.1778523067179,53.26689241473267],"type":"Point"}
}