{
  "type": "Feature",
  "properties": {
    "iso:country":"GB",
    "wof:name":"PO21 4DR",
    "wof:placetype":"postalcode"
},
  "geometry": {"coordinates":[-0.70901327136507,50.77701499809575],"type":"Point"}
}