{
  "type": "Feature",
  "properties": {
    "iso:country":"GB",
    "wof:name":"CH44 5SP",
    "wof:placetype":"postalcode"
},
  "geometry": {"coordinates":[-3.05106542748161,53.41115997955364],"type":"Point"}
}