{
  "type": "Feature",
  "properties": {
    "iso:country":"GB",
    "wof:name":"M33 5AY",
    "wof:placetype":"postalcode"
},
  "geometry": {"coordinates":[-2.34196612448663,53.42069934169568],"type":"Point"}
}