{
  "type": "Feature",
  "properties": {
    "iso:country": "GB",
    "wof:name": "M33 5AY",
    "wof:placetype": "postalcode"
  },
  "geometry": {"coordinates":[-2.341966,53.420699],"type":"Point"}
}
