{
  "type": "Feature",
  "properties": {
    "date:inception_lower": "1980-01-01",
    "date:inception_upper": "1980-01-01",
    "iso:country": "GB",
    "wof:name": "B31 2SB",
    "wof:placetype": "postalcode"
  },
  "geometry": {"coordinates":[-1.980231,52.402053],"type":"Point"}
}
