{
  "type": "Feature",
  "properties": {
    "iso:country":"GB",
    "wof:name":"SK9 4DX",
    "wof:placetype":"postalcode"
},
  "geometry": {"coordinates":[-2.23536780967991,53.33544854272151],"type":"Point"}
}