{
  "type": "Feature",
  "properties": {
    "iso:country":"GB",
    "wof:name":"S43 4RS",
    "wof:placetype":"postalcode"
},
  "geometry": {"coordinates":[-1.25695726376584,53.27575943620564],"type":"Point"}
}