{
  "type": "Feature",
  "properties": {
    "iso:country": "GB",
    "wof:name": "TQ12 9JJ",
    "wof:placetype": "postalcode"
  },
  "geometry": {"coordinates":[-3.59831,50.529232],"type":"Point"}
}
