{
  "type": "Feature",
  "properties": {
    "iso:country":"GB",
    "wof:name":"DN3 3TA",
    "wof:placetype":"postalcode"
},
  "geometry": {"coordinates":[-1.04237985871144,53.53533071953907],"type":"Point"}
}