{
  "type": "Feature",
  "properties": {
    "date:inception_lower":"1981-09-01",
    "date:inception_upper":"1981-09-30",
    "iso:country":"GB",
    "wof:name":"DN3 3TA",
    "wof:placetype":"postalcode"
},
  "geometry": {"coordinates":[-1.04238,53.535331],"type":"Point"}
}