{
  "type": "Feature",
  "properties": {
    "iso:country": "GB",
    "wof:name": "DN3 3TA",
    "wof:placetype": "postalcode"
  },
  "geometry": {"coordinates":[-1.04238,53.535331],"type":"Point"}
}
