{
  "type": "Feature",
  "properties": {
    "date:inception_lower": "2001-12-01",
    "date:inception_upper": "2001-12-01",
    "iso:country": "GB",
    "wof:name": "YO42 4UA",
    "wof:placetype": "postalcode"
  },
  "geometry": {"coordinates":[-0.929407,53.872837],"type":"Point"}
}
