{
  "type": "Feature",
  "properties": {
    "date:inception_lower":"1991-01-01",
    "date:inception_upper":"1991-01-31",
    "iso:country":"GB",
    "wof:name":"CT9 5QG",
    "wof:placetype":"postalcode"
},
  "geometry": {"coordinates":[1.373485,51.384656],"type":"Point"}
}