{
  "type": "Feature",
  "properties": {
    "iso:country":"GB",
    "wof:name":"CT9 5QG",
    "wof:placetype":"postalcode"
},
  "geometry": {"coordinates":[1.37348471540176,51.38465585680392],"type":"Point"}
}