{
  "type": "Feature",
  "properties": {
    "date:inception_lower": "1991-09-01",
    "date:inception_upper": "1991-09-01",
    "iso:country": "GB",
    "wof:name": "GU5 0EP",
    "wof:placetype": "postalcode"
  },
  "geometry": {"coordinates":[-0.554182,51.192152],"type":"Point"}
}
