{
  "type": "Feature",
  "properties": {
    "date:inception_lower": "1980-01-01",
    "date:inception_upper": "1980-01-01",
    "iso:country": "GB",
    "wof:name": "OL8 3EE",
    "wof:placetype": "postalcode"
  },
  "geometry": {"coordinates":[-2.115615,53.527168],"type":"Point"}
}
