{
  "type": "Feature",
  "properties": {
    "iso:country":"GB",
    "wof:name":"NG7 7DH",
    "wof:placetype":"postalcode"
},
  "geometry": {"coordinates":[-1.17421300128579,52.97439059398777],"type":"Point"}
}