{
  "type": "Feature",
  "properties": {
    "iso:country":"GB",
    "wof:name":"LU7 1YY",
    "wof:placetype":"postalcode"
},
  "geometry": {"coordinates":[-0.665298441152,51.92037089901098],"type":"Point"}
}