{
  "type": "Feature",
  "properties": {
    "iso:country":"GB",
    "wof:name":"HA3 5FE",
    "wof:placetype":"postalcode"
},
  "geometry": {"coordinates":[-0.33838962658969,51.59751750083154],"type":"Point"}
}