{
  "type": "Feature",
  "properties": {
    "iso:country": "GB",
    "wof:name": "TN3 9AR",
    "wof:placetype": "postalcode"
  },
  "geometry": {"coordinates":[0.296598,51.101979],"type":"Point"}
}
