{
  "type": "Feature",
  "properties": {
    "iso:country":"GB",
    "wof:name":"TN3 9AR",
    "wof:placetype":"postalcode"
},
  "geometry": {"coordinates":[0.2965701500767,51.10198160857637],"type":"Point"}
}