{
  "type": "Feature",
  "properties": {
    "iso:country":"GB",
    "wof:name":"SK9 7EN",
    "wof:placetype":"postalcode"
},
  "geometry": {"coordinates":[-2.23833812770031,53.29991029394825],"type":"Point"}
}