{
  "type": "Feature",
  "properties": {
    "iso:country": "GB",
    "wof:name": "SK9 7EN",
    "wof:placetype": "postalcode"
  },
  "geometry": {"coordinates":[-2.238338,53.29991],"type":"Point"}
}
