{
  "type": "Feature",
  "properties": {
    "date:inception_lower":"1980-01-01",
    "date:inception_upper":"1980-01-31",
    "iso:country":"GB",
    "wof:name":"CO7 9NN",
    "wof:placetype":"postalcode"
},
  "geometry": {"coordinates":[0.967304,51.858253],"type":"Point"}
}