{
  "type": "Feature",
  "properties": {
    "date:inception_lower": "2022-02-01",
    "date:inception_upper": "2022-02-01",
    "iso:country": "GB",
    "wof:name": "RG2 9WJ",
    "wof:placetype": "postalcode"
  },
  "geometry": {"coordinates":[-0.955461,51.401389],"type":"Point"}
}
