{
  "type": "Feature",
  "properties": {
    "iso:country":"GB",
    "wof:name":"SA15 4LB",
    "wof:placetype":"postalcode"
},
  "geometry": {"coordinates":[-4.15511452382342,51.69399639094536],"type":"Point"}
}