{
  "type": "Feature",
  "properties": {
    "iso:country": "GB",
    "wof:name": "CF48 4NG",
    "wof:placetype": "postalcode"
  },
  "geometry": {"coordinates":[-3.344435,51.71277],"type":"Point"}
}
