{
  "type": "Feature",
  "properties": {
    "date:inception_lower": "1980-01-01",
    "date:inception_upper": "1980-01-01",
    "iso:country": "GB",
    "wof:name": "CF48 4NG",
    "wof:placetype": "postalcode"
  },
  "geometry": {"coordinates":[-3.344435,51.71277],"type":"Point"}
}
