{
  "type": "Feature",
  "properties": {
    "iso:country":"GB",
    "wof:name":"CF48 4NG",
    "wof:placetype":"postalcode"
},
  "geometry": {"coordinates":[-3.34455658263415,51.71285343416776],"type":"Point"}
}