{
  "type": "Feature",
  "properties": {
    "date:inception_lower":"1980-01-01",
    "date:inception_upper":"1980-01-31",
    "iso:country":"GB",
    "wof:name":"SS1 3EG",
    "wof:placetype":"postalcode"
},
  "geometry": {"coordinates":[0.746269,51.538067],"type":"Point"}
}