{
  "type": "Feature",
  "properties": {
    "iso:country":"GB",
    "wof:name":"SS1 3EG",
    "wof:placetype":"postalcode"
},
  "geometry": {"coordinates":[0.74626895874828,51.5380667143929],"type":"Point"}
}