{
  "type": "Feature",
  "properties": {
    "date:inception_lower": "1980-01-01",
    "date:inception_upper": "1980-01-01",
    "iso:country": "GB",
    "wof:name": "CT8 8NU",
    "wof:placetype": "postalcode"
  },
  "geometry": {"coordinates":[1.334885,51.382065],"type":"Point"}
}
