{
  "type": "Feature",
  "properties": {
    "iso:country":"GB",
    "wof:name":"CT8 8NU",
    "wof:placetype":"postalcode"
},
  "geometry": {"coordinates":[1.33488527076581,51.382064860786],"type":"Point"}
}