{
  "type": "Feature",
  "properties": {
    "iso:country":"GB",
    "wof:name":"CV3 2DE",
    "wof:placetype":"postalcode"
},
  "geometry": {"coordinates":[-1.42379034895797,52.39384631636769],"type":"Point"}
}