{
  "type": "Feature",
  "properties": {
    "iso:country": "GB",
    "wof:name": "CV3 2DE",
    "wof:placetype": "postalcode"
  },
  "geometry": {"coordinates":[-1.423766,52.393864],"type":"Point"}
}
