{
  "type": "Feature",
  "properties": {
    "iso:country":"GB",
    "wof:name":"AB15 4BS",
    "wof:placetype":"postalcode"
},
  "geometry": {"coordinates":[-2.13477516114456,57.14369593017339],"type":"Point"}
}