{
  "type": "Feature",
  "properties": {
    "date:inception_lower":"1996-06-01",
    "date:inception_upper":"1996-06-30",
    "iso:country":"GB",
    "wof:name":"AB15 4BS",
    "wof:placetype":"postalcode"
},
  "geometry": {"coordinates":[-2.134775,57.143696],"type":"Point"}
}