{
  "type": "Feature",
  "properties": {
    "iso:country": "GB",
    "wof:name": "YO21 2AL",
    "wof:placetype": "postalcode"
  },
  "geometry": {"coordinates":[-0.826293,54.45443],"type":"Point"}
}
