{
  "type": "Feature",
  "properties": {
    "iso:country":"GB",
    "wof:name":"W8 4QH",
    "wof:placetype":"postalcode"
},
  "geometry": {"coordinates":[-0.19145852741073,51.50635676584233],"type":"Point"}
}