{
  "type": "Feature",
  "properties": {
    "iso:country": "GB",
    "wof:name": "SY14 8DX",
    "wof:placetype": "postalcode"
  },
  "geometry": {"coordinates":[-2.726711,53.027226],"type":"Point"}
}
