{
  "type": "Feature",
  "properties": {
    "date:inception_lower": "1998-12-01",
    "date:inception_upper": "1998-12-01",
    "iso:country": "GB",
    "wof:name": "BS27 3UE",
    "wof:placetype": "postalcode"
  },
  "geometry": {"coordinates":[-2.761493,51.259245],"type":"Point"}
}
