{
  "type": "Feature",
  "properties": {
    "iso:country":"GB",
    "wof:name":"WF3 3NT",
    "wof:placetype":"postalcode"
},
  "geometry": {"coordinates":[-1.50019424045019,53.72624478412068],"type":"Point"}
}