{
  "type": "Feature",
  "properties": {
    "iso:country": "GB",
    "wof:name": "BS31 1FN",
    "wof:placetype": "postalcode"
  },
  "geometry": {"coordinates":[-2.505157,51.403062],"type":"Point"}
}
