{
  "type": "Feature",
  "properties": {
    "iso:country":"GB",
    "wof:name":"BS31 1FN",
    "wof:placetype":"postalcode"
},
  "geometry": {"coordinates":[-2.50554392769929,51.40296175048185],"type":"Point"}
}