{
  "type": "Feature",
  "properties": {
    "iso:country": "GB",
    "wof:name": "SA5 9NL",
    "wof:placetype": "postalcode"
  },
  "geometry": {"coordinates":[-3.947257,51.637635],"type":"Point"}
}
