{
  "type": "Feature",
  "properties": {
    "iso:country":"GB",
    "wof:name":"SA5 9NL",
    "wof:placetype":"postalcode"
},
  "geometry": {"coordinates":[-3.94725497845862,51.6376749491058],"type":"Point"}
}