{
  "type": "Feature",
  "properties": {
    "date:inception_lower": "2023-06-01",
    "date:inception_upper": "2023-06-01",
    "iso:country": "GB",
    "wof:name": "S42 6SZ",
    "wof:placetype": "postalcode"
  },
  "geometry": {"coordinates":[-1.406283,53.184164],"type":"Point"}
}
