{
  "type": "Feature",
  "properties": {
    "iso:country": "GB",
    "wof:name": "LA3 3HT",
    "wof:placetype": "postalcode"
  },
  "geometry": {"coordinates":[-2.876792,53.994666],"type":"Point"}
}
