{
  "type": "Feature",
  "properties": {
    "iso:country":"GB",
    "wof:name":"LA3 3HT",
    "wof:placetype":"postalcode"
},
  "geometry": {"coordinates":[-2.87679155594377,53.99466562317445],"type":"Point"}
}