{
  "type": "Feature",
  "properties": {
    "date:inception_lower":"1980-01-01",
    "date:inception_upper":"1980-01-31",
    "iso:country":"GB",
    "wof:name":"LL41 3BX",
    "wof:placetype":"postalcode"
},
  "geometry": {"coordinates":[-3.928918,52.990261],"type":"Point"}
}