{
  "type": "Feature",
  "properties": {
    "iso:country":"GB",
    "wof:name":"NG2 6DH",
    "wof:placetype":"postalcode"
},
  "geometry": {"coordinates":[-1.12588854171787,52.926382734313],"type":"Point"}
}