{
  "type": "Feature",
  "properties": {
    "iso:country":"GB",
    "wof:name":"PA1 2TH",
    "wof:placetype":"postalcode"
},
  "geometry": {"coordinates":[-4.46689296051109,55.84058205159243],"type":"Point"}
}