{
  "type": "Feature",
  "properties": {
    "iso:country":"GB",
    "wof:name":"E1 2AF",
    "wof:placetype":"postalcode"
},
  "geometry": {"coordinates":[-0.06106460020811,51.51515456312992],"type":"Point"}
}