{
  "type": "Feature",
  "properties": {
    "iso:country":"GB",
    "wof:name":"SO16 5EP",
    "wof:placetype":"postalcode"
},
  "geometry": {"coordinates":[-1.44508936176875,50.93458691619623],"type":"Point"}
}