{
  "type": "Feature",
  "properties": {
    "date:inception_lower": "1980-01-01",
    "date:inception_upper": "1980-01-01",
    "iso:country": "GB",
    "wof:name": "N8 9NH",
    "wof:placetype": "postalcode"
  },
  "geometry": {"coordinates":[-0.111522,51.58067],"type":"Point"}
}
