{
  "type": "Feature",
  "properties": {
    "iso:country":"GB",
    "wof:name":"N8 9NH",
    "wof:placetype":"postalcode"
},
  "geometry": {"coordinates":[-0.11152222784253,51.58066983237936],"type":"Point"}
}