{
  "type": "Feature",
  "properties": {
    "iso:country": "GB",
    "wof:name": "BS8 3SN",
    "wof:placetype": "postalcode"
  },
  "geometry": {"coordinates":[-2.69393,51.459284],"type":"Point"}
}
