{
  "type": "Feature",
  "properties": {
    "date:inception_lower":"1980-01-01",
    "date:inception_upper":"1980-01-31",
    "iso:country":"GB",
    "wof:name":"BS8 3SN",
    "wof:placetype":"postalcode"
},
  "geometry": {"coordinates":[-2.69393,51.459284],"type":"Point"}
}