{
  "type": "Feature",
  "properties": {
    "iso:country":"GB",
    "wof:name":"BS8 3SN",
    "wof:placetype":"postalcode"
},
  "geometry": {"coordinates":[-2.69392957091703,51.45928357178992],"type":"Point"}
}