{
  "type": "Feature",
  "properties": {
    "iso:country":"GB",
    "wof:name":"M26 1QQ",
    "wof:placetype":"postalcode"
},
  "geometry": {"coordinates":[-2.322817681984,53.55642455273475],"type":"Point"}
}