{
  "type": "Feature",
  "properties": {
    "date:inception_lower": "2016-11-01",
    "date:inception_upper": "2016-11-01",
    "iso:country": "GB",
    "wof:name": "MK43 9FS",
    "wof:placetype": "postalcode"
  },
  "geometry": {"coordinates":[-0.522287,52.09834],"type":"Point"}
}
