{
  "type": "Feature",
  "properties": {
    "date:inception_lower":"2010-11-01",
    "date:inception_upper":"2010-11-30",
    "iso:country":"GB",
    "wof:name":"B23 6DF",
    "wof:placetype":"postalcode"
},
  "geometry": {"coordinates":[-1.846815,52.521361],"type":"Point"}
}