{
  "type": "Feature",
  "properties": {
    "iso:country":"GB",
    "wof:name":"B23 6DF",
    "wof:placetype":"postalcode"
},
  "geometry": {"coordinates":[-1.84681461621449,52.52136096478225],"type":"Point"}
}