{
  "type": "Feature",
  "properties": {
    "iso:country":"GB",
    "wof:name":"SK6 7LA",
    "wof:placetype":"postalcode"
},
  "geometry": {"coordinates":[-2.06051054697725,53.38914796316267],"type":"Point"}
}