{
  "type": "Feature",
  "properties": {
    "date:inception_lower":"1980-01-01",
    "date:inception_upper":"1980-01-31",
    "iso:country":"GB",
    "wof:name":"SK6 7LA",
    "wof:placetype":"postalcode"
},
  "geometry": {"coordinates":[-2.060511,53.389148],"type":"Point"}
}