{
  "type": "Feature",
  "properties": {
    "date:inception_lower":"1980-01-01",
    "date:inception_upper":"1980-01-31",
    "iso:country":"GB",
    "wof:name":"WS3 3RH",
    "wof:placetype":"postalcode"
},
  "geometry": {"coordinates":[-1.996869,52.625274],"type":"Point"}
}