{
  "type": "Feature",
  "properties": {
    "iso:country":"GB",
    "wof:name":"FK1 5QW",
    "wof:placetype":"postalcode"
},
  "geometry": {"coordinates":[-3.79146013150214,55.9956622525445],"type":"Point"}
}