{
  "type": "Feature",
  "properties": {
    "iso:country":"GB",
    "wof:name":"DE72 3SE",
    "wof:placetype":"postalcode"
},
  "geometry": {"coordinates":[-1.37250628262849,52.92345472452601],"type":"Point"}
}