{
  "type": "Feature",
  "properties": {
    "iso:country":"GB",
    "wof:name":"ST6 8LG",
    "wof:placetype":"postalcode"
},
  "geometry": {"coordinates":[-2.16342729542415,53.06201954143511],"type":"Point"}
}