{
  "type": "Feature",
  "properties": {
    "iso:country":"GB",
    "wof:name":"TQ8 8PL",
    "wof:placetype":"postalcode"
},
  "geometry": {"coordinates":[-3.74249736284138,50.22844058417241],"type":"Point"}
}