{
  "type": "Feature",
  "properties": {
    "iso:country": "GB",
    "wof:name": "TQ8 8PL",
    "wof:placetype": "postalcode"
  },
  "geometry": {"coordinates":[-3.742497,50.228441],"type":"Point"}
}
