{
  "type": "Feature",
  "properties": {
    "iso:country":"GB",
    "wof:name":"SO50 9AU",
    "wof:placetype":"postalcode"
},
  "geometry": {"coordinates":[-1.35521917599726,50.97177678470251],"type":"Point"}
}