{
  "type": "Feature",
  "properties": {
    "date:inception_lower": "1994-12-01",
    "date:inception_upper": "1994-12-01",
    "iso:country": "GB",
    "wof:name": "SO50 9AU",
    "wof:placetype": "postalcode"
  },
  "geometry": {"coordinates":[-1.355194,50.971769],"type":"Point"}
}
