{
  "type": "Feature",
  "properties": {
    "iso:country":"GB",
    "wof:name":"NR10 5NS",
    "wof:placetype":"postalcode"
},
  "geometry": {"coordinates":[1.21595635216845,52.73788201607497],"type":"Point"}
}