{
  "type": "Feature",
  "properties": {
    "iso:country": "GB",
    "wof:name": "RG14 7LA",
    "wof:placetype": "postalcode"
  },
  "geometry": {"coordinates":[-1.316662,51.392136],"type":"Point"}
}
