{
  "type": "Feature",
  "properties": {
    "iso:country":"GB",
    "wof:name":"RG14 7LA",
    "wof:placetype":"postalcode"
},
  "geometry": {"coordinates":[-1.31666169174853,51.39213578324071],"type":"Point"}
}