{
  "type": "Feature",
  "properties": {
    "iso:country":"GB",
    "wof:name":"W1H 1SF",
    "wof:placetype":"postalcode"
},
  "geometry": {"coordinates":[-0.16111445716501,51.52095632856183],"type":"Point"}
}