{
  "type": "Feature",
  "properties": {
    "iso:country":"GB",
    "wof:name":"M14 7GA",
    "wof:placetype":"postalcode"
},
  "geometry": {"coordinates":[-2.23255155795728,53.44970803148415],"type":"Point"}
}