{
  "type": "Feature",
  "properties": {
    "iso:country":"GB",
    "wof:name":"EN8 0EU",
    "wof:placetype":"postalcode"
},
  "geometry": {"coordinates":[-0.04277478354592,51.71358466560476],"type":"Point"}
}