{
  "type": "Feature",
  "properties": {
    "iso:country": "GB",
    "wof:name": "LE15 8PA",
    "wof:placetype": "postalcode"
  },
  "geometry": {"coordinates":[-0.594233,52.585002],"type":"Point"}
}
