{
  "type": "Feature",
  "properties": {
    "iso:country":"GB",
    "wof:name":"LD3 7HL",
    "wof:placetype":"postalcode"
},
  "geometry": {"coordinates":[-3.38899047424657,51.94336607424226],"type":"Point"}
}