{
  "type": "Feature",
  "properties": {
    "iso:country": "GB",
    "wof:name": "BA6 8BP",
    "wof:placetype": "postalcode"
  },
  "geometry": {"coordinates":[-2.709125,51.143549],"type":"Point"}
}
