{
  "type": "Feature",
  "properties": {
    "iso:country":"GB",
    "wof:name":"BA6 8BP",
    "wof:placetype":"postalcode"
},
  "geometry": {"coordinates":[-2.70912476451435,51.14354924715974],"type":"Point"}
}