{
  "type": "Feature",
  "properties": {
    "iso:country":"GB",
    "wof:name":"AB15 6WL",
    "wof:placetype":"postalcode"
},
  "geometry": {"coordinates":[-2.17906104521258,57.15043162093981],"type":"Point"}
}