{
  "type": "Feature",
  "properties": {
    "iso:country":"GB",
    "wof:name":"SS3 0QE",
    "wof:placetype":"postalcode"
},
  "geometry": {"coordinates":[0.75189882219907,51.55559842150459],"type":"Point"}
}