{
  "type": "Feature",
  "properties": {
    "date:inception_lower":"1980-01-01",
    "date:inception_upper":"1980-01-31",
    "iso:country":"GB",
    "wof:name":"SS3 0QE",
    "wof:placetype":"postalcode"
},
  "geometry": {"coordinates":[0.751899,51.555598],"type":"Point"}
}