{
  "type": "Feature",
  "properties": {
    "iso:country": "GB",
    "wof:name": "HG3 4BJ",
    "wof:placetype": "postalcode"
  },
  "geometry": {"coordinates":[-1.700278,54.061224],"type":"Point"}
}
