{
  "type": "Feature",
  "properties": {
    "iso:country":"GB",
    "wof:name":"HG3 4BJ",
    "wof:placetype":"postalcode"
},
  "geometry": {"coordinates":[-1.70027844498561,54.06122378212878],"type":"Point"}
}