{
  "type": "Feature",
  "properties": {
    "iso:country":"GB",
    "wof:name":"BN2 5NZ",
    "wof:placetype":"postalcode"
},
  "geometry": {"coordinates":[-0.10412645988933,50.82354871773718],"type":"Point"}
}