{
  "type": "Feature",
  "properties": {
    "iso:country":"GB",
    "wof:name":"ML4 2DH",
    "wof:placetype":"postalcode"
},
  "geometry": {"coordinates":[-4.01912533227256,55.80761513902934],"type":"Point"}
}