{
  "type": "Feature",
  "properties": {
    "iso:country":"GB",
    "wof:name":"AL10 0QR",
    "wof:placetype":"postalcode"
},
  "geometry": {"coordinates":[-0.22654620397524,51.77270299706721],"type":"Point"}
}