{
  "type": "Feature",
  "properties": {
    "iso:country":"GB",
    "wof:name":"SA48 8BB",
    "wof:placetype":"postalcode"
},
  "geometry": {"coordinates":[-4.13218834027413,52.16383948430788],"type":"Point"}
}