{
  "type": "Feature",
  "properties": {
    "iso:country":"GB",
    "wof:name":"DD3 9JW",
    "wof:placetype":"postalcode"
},
  "geometry": {"coordinates":[-3.01534692480141,56.49262638250338],"type":"Point"}
}