{
  "type": "Feature",
  "properties": {
    "date:inception_lower": "1980-01-01",
    "date:inception_upper": "1980-01-01",
    "iso:country": "GB",
    "wof:name": "BB10 1LN",
    "wof:placetype": "postalcode"
  },
  "geometry": {"coordinates":[-2.236495,53.800682],"type":"Point"}
}
