{
  "type": "Feature",
  "properties": {
    "iso:country":"GB",
    "wof:name":"BB10 1LN",
    "wof:placetype":"postalcode"
},
  "geometry": {"coordinates":[-2.23649531417396,53.80068201816048],"type":"Point"}
}