{
  "type": "Feature",
  "properties": {
    "iso:country":"GB",
    "wof:name":"SN25 3DX",
    "wof:placetype":"postalcode"
},
  "geometry": {"coordinates":[-1.80551355820049,51.58419848664626],"type":"Point"}
}