{
  "type": "Feature",
  "properties": {
    "date:inception_lower": "2002-08-01",
    "date:inception_upper": "2002-08-01",
    "iso:country": "GB",
    "wof:name": "SO14 5FE",
    "wof:placetype": "postalcode"
  },
  "geometry": {"coordinates":[-1.392755,50.899076],"type":"Point"}
}
