{
  "type": "Feature",
  "properties": {
    "iso:country": "GB",
    "wof:name": "DN15 5SP",
    "wof:placetype": "postalcode"
  },
  "geometry": {"coordinates":[-0.655556,53.581479],"type":"Point"}
}
