{
  "type": "Feature",
  "properties": {
    "iso:country":"GB",
    "wof:name":"AB31 6NA",
    "wof:placetype":"postalcode"
},
  "geometry": {"coordinates":[-2.63549860361011,57.020379816418],"type":"Point"}
}