{
  "type": "Feature",
  "properties": {
    "date:inception_lower": "1996-06-01",
    "date:inception_upper": "1996-06-01",
    "iso:country": "GB",
    "wof:name": "AB31 6NA",
    "wof:placetype": "postalcode"
  },
  "geometry": {"coordinates":[-2.635499,57.02038],"type":"Point"}
}
