{
  "type": "Feature",
  "properties": {
    "iso:country":"GB",
    "wof:name":"NE6 1XG",
    "wof:placetype":"postalcode"
},
  "geometry": {"coordinates":[-1.58036533372174,54.97780401784518],"type":"Point"}
}