{
  "type": "Feature",
  "properties": {
    "date:inception_lower": "1980-01-01",
    "date:inception_upper": "1980-01-01",
    "iso:country": "GB",
    "wof:name": "NE6 1XG",
    "wof:placetype": "postalcode"
  },
  "geometry": {"coordinates":[-1.580365,54.977804],"type":"Point"}
}
