{
  "type": "Feature",
  "properties": {
    "date:inception_lower":"2004-01-01",
    "date:inception_upper":"2004-01-31",
    "iso:country":"GB",
    "wof:name":"LL65 1PZ",
    "wof:placetype":"postalcode"
},
  "geometry": {"coordinates":[-4.645961,53.308529],"type":"Point"}
}