{
  "type": "Feature",
  "properties": {
    "date:inception_lower": "1999-06-01",
    "date:inception_upper": "1999-06-01",
    "iso:country": "GB",
    "wof:name": "CH44 4ET",
    "wof:placetype": "postalcode"
  },
  "geometry": {"coordinates":[-3.04521,53.412892],"type":"Point"}
}
