{
  "type": "Feature",
  "properties": {
    "iso:country": "GB",
    "wof:name": "CH44 4ET",
    "wof:placetype": "postalcode"
  },
  "geometry": {"coordinates":[-3.04521,53.412892],"type":"Point"}
}
