{
  "type": "Feature",
  "properties": {
    "iso:country":"GB",
    "wof:name":"G67 4AB",
    "wof:placetype":"postalcode"
},
  "geometry": {"coordinates":[-3.97992604743482,55.93120188090307],"type":"Point"}
}