{
  "type": "Feature",
  "properties": {
    "iso:country": "GB",
    "wof:name": "DE4 3SS",
    "wof:placetype": "postalcode"
  },
  "geometry": {"coordinates":[-1.546781,53.136185],"type":"Point"}
}
