{
  "type": "Feature",
  "properties": {
    "iso:country":"GB",
    "wof:name":"DE4 3SS",
    "wof:placetype":"postalcode"
},
  "geometry": {"coordinates":[-1.5467811048823,53.13618512153882],"type":"Point"}
}