{
  "type": "Feature",
  "properties": {
    "iso:country": "GB",
    "wof:name": "MK43 0RP",
    "wof:placetype": "postalcode"
  },
  "geometry": {"coordinates":[-0.556972,52.04116],"type":"Point"}
}
