{
  "type": "Feature",
  "properties": {
    "iso:country":"GB",
    "wof:name":"ST4 7JP",
    "wof:placetype":"postalcode"
},
  "geometry": {"coordinates":[-2.19408986373453,53.00525201640512],"type":"Point"}
}