{
  "type": "Feature",
  "properties": {
    "iso:country":"GB",
    "wof:name":"HP19 7GT",
    "wof:placetype":"postalcode"
},
  "geometry": {"coordinates":[-0.84063959382201,51.81625643553504],"type":"Point"}
}