{
  "type": "Feature",
  "properties": {
    "date:inception_lower":"1980-01-01",
    "date:inception_upper":"1980-01-31",
    "iso:country":"GB",
    "wof:name":"BH11 9NE",
    "wof:placetype":"postalcode"
},
  "geometry": {"coordinates":[-1.932034,50.771691],"type":"Point"}
}