{
  "type": "Feature",
  "properties": {
    "iso:country":"GB",
    "wof:name":"BH11 9NE",
    "wof:placetype":"postalcode"
},
  "geometry": {"coordinates":[-1.93203387229031,50.77169098933207],"type":"Point"}
}