{
  "type": "Feature",
  "properties": {
    "iso:country":"GB",
    "wof:name":"DL11 6BD",
    "wof:placetype":"postalcode"
},
  "geometry": {"coordinates":[-1.75188395505694,54.39707197720162],"type":"Point"}
}