{
  "type": "Feature",
  "properties": {
    "date:inception_lower": "1980-01-01",
    "date:inception_upper": "1980-01-01",
    "iso:country": "GB",
    "wof:name": "SW4 9SP",
    "wof:placetype": "postalcode"
  },
  "geometry": {"coordinates":[-0.161858,51.461294],"type":"Point"}
}
