{
  "type": "Feature",
  "properties": {
    "iso:country":"GB",
    "wof:name":"SW4 9SP",
    "wof:placetype":"postalcode"
},
  "geometry": {"coordinates":[-0.16185811598949,51.46129366901814],"type":"Point"}
}