{
  "type": "Feature",
  "properties": {
    "iso:country": "GB",
    "wof:name": "SW4 9SP",
    "wof:placetype": "postalcode"
  },
  "geometry": {"coordinates":[-0.161858,51.461294],"type":"Point"}
}
