{
  "type": "Feature",
  "properties": {
    "date:inception_lower": "1994-12-01",
    "date:inception_upper": "1994-12-01",
    "iso:country": "GB",
    "wof:name": "SO16 5GT",
    "wof:placetype": "postalcode"
  },
  "geometry": {"coordinates":[-1.43917,50.938066],"type":"Point"}
}
