{
  "type": "Feature",
  "properties": {
    "iso:country": "GB",
    "wof:name": "SO16 5GT",
    "wof:placetype": "postalcode"
  },
  "geometry": {"coordinates":[-1.43917,50.938066],"type":"Point"}
}
