{
  "type": "Feature",
  "properties": {
    "date:inception_lower": "1996-12-01",
    "date:inception_upper": "1996-12-01",
    "iso:country": "GB",
    "wof:name": "NW8 6QG",
    "wof:placetype": "postalcode"
  },
  "geometry": {"coordinates":[-0.17363,51.537068],"type":"Point"}
}
