{
  "type": "Feature",
  "properties": {
    "date:inception_lower": "1980-01-01",
    "date:inception_upper": "1980-01-01",
    "iso:country": "GB",
    "wof:name": "LA5 9QX",
    "wof:placetype": "postalcode"
  },
  "geometry": {"coordinates":[-2.768437,54.144821],"type":"Point"}
}
