{
  "type": "Feature",
  "properties": {
    "iso:country":"GB",
    "wof:name":"PO13 0DF",
    "wof:placetype":"postalcode"
},
  "geometry": {"coordinates":[-1.16441316037665,50.81603935819741],"type":"Point"}
}