{
  "type": "Feature",
  "properties": {
    "iso:country":"GB",
    "wof:name":"PE2 6GG",
    "wof:placetype":"postalcode"
},
  "geometry": {"coordinates":[-0.32288725856755,52.55331105773144],"type":"Point"}
}