{
  "type": "Feature",
  "properties": {
    "date:inception_lower": "2021-04-01",
    "date:inception_upper": "2021-04-01",
    "iso:country": "GB",
    "wof:name": "PE2 6GG",
    "wof:placetype": "postalcode"
  },
  "geometry": {"coordinates":[-0.322858,52.553302],"type":"Point"}
}
