{
  "type": "Feature",
  "properties": {
    "date:inception_lower": "2002-07-01",
    "date:inception_upper": "2002-07-01",
    "iso:country": "GB",
    "wof:name": "NN5 5FF",
    "wof:placetype": "postalcode"
  },
  "geometry": {"coordinates":[-0.921787,52.23967],"type":"Point"}
}
