{
  "type": "Feature",
  "properties": {
    "iso:country":"GB",
    "wof:name":"NN5 5FF",
    "wof:placetype":"postalcode"
},
  "geometry": {"coordinates":[-0.92178668502648,52.23966985910228],"type":"Point"}
}