{
  "type": "Feature",
  "properties": {
    "iso:country": "GB",
    "wof:name": "CB8 8AX",
    "wof:placetype": "postalcode"
  },
  "geometry": {"coordinates":[0.407689,52.242292],"type":"Point"}
}
