{
  "type": "Feature",
  "properties": {
    "iso:country": "GB",
    "wof:name": "LE14 2TL",
    "wof:placetype": "postalcode"
  },
  "geometry": {"coordinates":[-0.951747,52.708033],"type":"Point"}
}
