{
  "type": "Feature",
  "properties": {
    "iso:country":"GB",
    "wof:name":"LE14 2TL",
    "wof:placetype":"postalcode"
},
  "geometry": {"coordinates":[-0.95175414128074,52.7080134927237],"type":"Point"}
}