{
  "type": "Feature",
  "properties": {
    "iso:country": "GB",
    "wof:name": "SW4 6TE",
    "wof:placetype": "postalcode"
  },
  "geometry": {"coordinates":[-0.124848,51.473207],"type":"Point"}
}
