{
  "type": "Feature",
  "properties": {
    "date:inception_lower": "1980-01-01",
    "date:inception_upper": "1980-01-01",
    "iso:country": "GB",
    "wof:name": "SW4 6TE",
    "wof:placetype": "postalcode"
  },
  "geometry": {"coordinates":[-0.124848,51.473207],"type":"Point"}
}
