{
  "type": "Feature",
  "properties": {
    "iso:country":"GB",
    "wof:name":"PO20 2GQ",
    "wof:placetype":"postalcode"
},
  "geometry": {"coordinates":[-0.70831347657492,50.85027309145337],"type":"Point"}
}