{
  "type": "Feature",
  "properties": {
    "date:inception_lower": "2002-06-01",
    "date:inception_upper": "2002-06-01",
    "iso:country": "GB",
    "wof:name": "PO20 2GQ",
    "wof:placetype": "postalcode"
  },
  "geometry": {"coordinates":[-0.708313,50.850273],"type":"Point"}
}
