{
  "type": "Feature",
  "properties": {
    "date:inception_lower": "2023-04-01",
    "date:inception_upper": "2023-04-01",
    "iso:country": "GB",
    "wof:name": "OX11 9GS",
    "wof:placetype": "postalcode"
  },
  "geometry": {"coordinates":[-1.228093,51.619941],"type":"Point"}
}
