{
  "type": "Feature",
  "properties": {
    "iso:country": "GB",
    "wof:name": "CT13 9HA",
    "wof:placetype": "postalcode"
  },
  "geometry": {"coordinates":[1.3383,51.276104],"type":"Point"}
}
