{
  "type": "Feature",
  "properties": {
    "iso:country":"GB",
    "wof:name":"GL51 6JL",
    "wof:placetype":"postalcode"
},
  "geometry": {"coordinates":[-2.12335301969062,51.88710550984893],"type":"Point"}
}