{
  "type": "Feature",
  "properties": {
    "date:inception_lower": "1980-01-01",
    "date:inception_upper": "1980-01-01",
    "iso:country": "GB",
    "wof:name": "GL51 6JL",
    "wof:placetype": "postalcode"
  },
  "geometry": {"coordinates":[-2.123353,51.887106],"type":"Point"}
}
