{
  "type": "Feature",
  "properties": {
    "iso:country": "GB",
    "wof:name": "NG21 9FD",
    "wof:placetype": "postalcode"
  },
  "geometry": {"coordinates":[-1.119551,53.167314],"type":"Point"}
}
