{
  "type": "Feature",
  "properties": {
    "date:inception_lower":"1980-01-01",
    "date:inception_upper":"1980-01-31",
    "iso:country":"GB",
    "wof:name":"GU25 4DU",
    "wof:placetype":"postalcode"
},
  "geometry": {"coordinates":[-0.554559,51.398901],"type":"Point"}
}