{
  "type": "Feature",
  "properties": {
    "iso:country":"GB",
    "wof:name":"DT6 5NN",
    "wof:placetype":"postalcode"
},
  "geometry": {"coordinates":[-2.80297992549696,50.76655273917523],"type":"Point"}
}