{
  "type": "Feature",
  "properties": {
    "iso:country":"GB",
    "wof:name":"BN26 5SB",
    "wof:placetype":"postalcode"
},
  "geometry": {"coordinates":[0.2225181844919,50.81369030667294],"type":"Point"}
}