{
  "type": "Feature",
  "properties": {
    "iso:country": "GB",
    "wof:name": "BN26 5SB",
    "wof:placetype": "postalcode"
  },
  "geometry": {"coordinates":[0.222518,50.81369],"type":"Point"}
}
