{
  "type": "Feature",
  "properties": {
    "iso:country":"GB",
    "wof:name":"SG9 9FN",
    "wof:placetype":"postalcode"
},
  "geometry": {"coordinates":[-0.02266228849856,51.95160443037249],"type":"Point"}
}