{
  "type": "Feature",
  "properties": {
    "date:inception_lower": "2011-08-01",
    "date:inception_upper": "2011-08-01",
    "iso:country": "GB",
    "wof:name": "SG9 9FN",
    "wof:placetype": "postalcode"
  },
  "geometry": {"coordinates":[-0.022662,51.951604],"type":"Point"}
}
