{
  "type": "Feature",
  "properties": {
    "date:inception_lower": "1999-12-01",
    "date:inception_upper": "1999-12-01",
    "iso:country": "GB",
    "wof:name": "SP8 4UU",
    "wof:placetype": "postalcode"
  },
  "geometry": {"coordinates":[-2.277357,51.038572],"type":"Point"}
}
