{
  "type": "Feature",
  "properties": {
    "iso:country": "GB",
    "wof:name": "SP8 4UU",
    "wof:placetype": "postalcode"
  },
  "geometry": {"coordinates":[-2.277357,51.038572],"type":"Point"}
}
