{
  "type": "Feature",
  "properties": {
    "date:inception_lower":"1980-01-01",
    "date:inception_upper":"1980-01-31",
    "iso:country":"GB",
    "wof:name":"BN12 5LX",
    "wof:placetype":"postalcode"
},
  "geometry": {"coordinates":[-0.449647,50.809371],"type":"Point"}
}