{
  "type": "Feature",
  "properties": {
    "iso:country":"GB",
    "wof:name":"SP2 8NR",
    "wof:placetype":"postalcode"
},
  "geometry": {"coordinates":[-1.80024023745618,51.05280383410958],"type":"Point"}
}