{
  "type": "Feature",
  "properties": {
    "date:inception_lower": "1984-10-01",
    "date:inception_upper": "1984-10-01",
    "iso:country": "GB",
    "wof:name": "SP2 8NR",
    "wof:placetype": "postalcode"
  },
  "geometry": {"coordinates":[-1.80024,51.052804],"type":"Point"}
}
