{
  "type": "Feature",
  "properties": {
    "date:inception_lower":"2005-12-01",
    "date:inception_upper":"2005-12-31",
    "iso:country":"GB",
    "wof:name":"SO53 4TL",
    "wof:placetype":"postalcode"
},
  "geometry": {"coordinates":[-1.398454,50.985379],"type":"Point"}
}