{
  "type": "Feature",
  "properties": {
    "iso:country":"GB",
    "wof:name":"BA2 5BT",
    "wof:placetype":"postalcode"
},
  "geometry": {"coordinates":[-2.35268864927748,51.36024475852588],"type":"Point"}
}