{
  "type": "Feature",
  "properties": {
    "iso:country":"GB",
    "wof:name":"L22 4RJ",
    "wof:placetype":"postalcode"
},
  "geometry": {"coordinates":[-3.01752166248299,53.48003588032563],"type":"Point"}
}