{
  "type": "Feature",
  "properties": {
    "date:inception_lower": "1980-01-01",
    "date:inception_upper": "1980-01-01",
    "iso:country": "GB",
    "wof:name": "NG22 9LA",
    "wof:placetype": "postalcode"
  },
  "geometry": {"coordinates":[-0.988376,53.205484],"type":"Point"}
}
