{
  "type": "Feature",
  "properties": {
    "iso:country": "GB",
    "wof:name": "HD4 5QU",
    "wof:placetype": "postalcode"
  },
  "geometry": {"coordinates":[-1.815294,53.634728],"type":"Point"}
}
