{
  "type": "Feature",
  "properties": {
    "iso:country": "GB",
    "wof:name": "TQ7 4SQ",
    "wof:placetype": "postalcode"
  },
  "geometry": {"coordinates":[-3.839383,50.315522],"type":"Point"}
}
