{
  "type": "Feature",
  "properties": {
    "date:inception_lower":"1993-08-01",
    "date:inception_upper":"1993-08-31",
    "iso:country":"GB",
    "wof:name":"TQ7 4SQ",
    "wof:placetype":"postalcode"
},
  "geometry": {"coordinates":[-3.839383,50.315522],"type":"Point"}
}