{
  "type": "Feature",
  "properties": {
    "iso:country":"GB",
    "wof:name":"TQ7 4SQ",
    "wof:placetype":"postalcode"
},
  "geometry": {"coordinates":[-3.83938325799593,50.31552171545442],"type":"Point"}
}