{
  "type": "Feature",
  "properties": {
    "iso:country":"GB",
    "wof:name":"M33 2SY",
    "wof:placetype":"postalcode"
},
  "geometry": {"coordinates":[-2.30039014779106,53.4184562289613],"type":"Point"}
}