{
  "type": "Feature",
  "properties": {
    "iso:country":"GB",
    "wof:name":"CH43 9XU",
    "wof:placetype":"postalcode"
},
  "geometry": {"coordinates":[-3.0848842153989,53.39338279843447],"type":"Point"}
}