{
  "type": "Feature",
  "properties": {
    "iso:country":"GB",
    "wof:name":"SE11 5PG",
    "wof:placetype":"postalcode"
},
  "geometry": {"coordinates":[-0.11322078796838,51.4880293488868],"type":"Point"}
}