{
  "type": "Feature",
  "properties": {
    "iso:country": "GB",
    "wof:name": "IP14 1NW",
    "wof:placetype": "postalcode"
  },
  "geometry": {"coordinates":[0.990257,52.195553],"type":"Point"}
}
