{
  "type": "Feature",
  "properties": {
    "date:inception_lower": "1980-01-01",
    "date:inception_upper": "1980-01-01",
    "iso:country": "GB",
    "wof:name": "IP14 1NW",
    "wof:placetype": "postalcode"
  },
  "geometry": {"coordinates":[0.989971,52.195415],"type":"Point"}
}
