{
  "type": "Feature",
  "properties": {
    "date:inception_lower": "1993-01-01",
    "date:inception_upper": "1993-01-01",
    "iso:country": "GB",
    "wof:name": "DE22 5JH",
    "wof:placetype": "postalcode"
  },
  "geometry": {"coordinates":[-1.536543,52.959419],"type":"Point"}
}
