{
  "type": "Feature",
  "properties": {
    "iso:country":"GB",
    "wof:name":"NR32 4AW",
    "wof:placetype":"postalcode"
},
  "geometry": {"coordinates":[1.75356762679667,52.48775192614836],"type":"Point"}
}