{
  "type": "Feature",
  "properties": {
    "iso:country": "GB",
    "wof:name": "BN25 1JR",
    "wof:placetype": "postalcode"
  },
  "geometry": {"coordinates":[0.0995,50.770092],"type":"Point"}
}
