{
  "type": "Feature",
  "properties": {
    "iso:country":"GB",
    "wof:name":"M24 2RT",
    "wof:placetype":"postalcode"
},
  "geometry": {"coordinates":[-2.15986074996569,53.56731497557276],"type":"Point"}
}