{
  "type": "Feature",
  "properties": {
    "iso:country": "GB",
    "wof:name": "M24 2RT",
    "wof:placetype": "postalcode"
  },
  "geometry": {"coordinates":[-2.159861,53.567315],"type":"Point"}
}
