{
  "type": "Feature",
  "properties": {
    "date:inception_lower": "2007-09-01",
    "date:inception_upper": "2007-09-01",
    "iso:country": "GB",
    "wof:name": "LL22 7SR",
    "wof:placetype": "postalcode"
  },
  "geometry": {"coordinates":[-3.581236,53.28507],"type":"Point"}
}
