{
  "type": "Feature",
  "properties": {
    "iso:country": "GB",
    "wof:name": "SW7 2EA",
    "wof:placetype": "postalcode"
  },
  "geometry": {"coordinates":[-0.177841,51.494815],"type":"Point"}
}
