{
  "type": "Feature",
  "properties": {
    "iso:country":"GB",
    "wof:name":"SW7 2EA",
    "wof:placetype":"postalcode"
},
  "geometry": {"coordinates":[-0.17784056045137,51.49481545651096],"type":"Point"}
}