{
  "type": "Feature",
  "properties": {
    "iso:country":"GB",
    "wof:name":"WD24 4HQ",
    "wof:placetype":"postalcode"
},
  "geometry": {"coordinates":[-0.38662476840973,51.66847242865332],"type":"Point"}
}