{
  "type": "Feature",
  "properties": {
    "iso:country":"GB",
    "wof:name":"LE67 9RE",
    "wof:placetype":"postalcode"
},
  "geometry": {"coordinates":[-1.27176037626837,52.68819626674702],"type":"Point"}
}