{
  "type": "Feature",
  "properties": {
    "iso:country":"GB",
    "wof:name":"SO53 2LX",
    "wof:placetype":"postalcode"
},
  "geometry": {"coordinates":[-1.37059327184772,50.98077205460126],"type":"Point"}
}