{
  "type": "Feature",
  "properties": {
    "date:inception_lower": "1980-01-01",
    "date:inception_upper": "1980-01-01",
    "iso:country": "GB",
    "wof:name": "NE3 4PB",
    "wof:placetype": "postalcode"
  },
  "geometry": {"coordinates":[-1.639675,55.007235],"type":"Point"}
}
