{
  "type": "Feature",
  "properties": {
    "iso:country": "GB",
    "wof:name": "NE3 4PB",
    "wof:placetype": "postalcode"
  },
  "geometry": {"coordinates":[-1.639675,55.007235],"type":"Point"}
}
