{
  "type": "Feature",
  "properties": {
    "iso:country":"GB",
    "wof:name":"NE3 4PB",
    "wof:placetype":"postalcode"
},
  "geometry": {"coordinates":[-1.63967519330621,55.00723521729115],"type":"Point"}
}