{
  "type": "Feature",
  "properties": {
    "date:inception_lower":"1998-12-01",
    "date:inception_upper":"1998-12-31",
    "iso:country":"GB",
    "wof:name":"SA2 7QP",
    "wof:placetype":"postalcode"
},
  "geometry": {"coordinates":[-4.022445,51.617816],"type":"Point"}
}