{
  "type": "Feature",
  "properties": {
    "date:inception_lower": "2024-01-01",
    "date:inception_upper": "2024-01-01",
    "iso:country": "GB",
    "wof:name": "NE6 2DN",
    "wof:placetype": "postalcode"
  },
  "geometry": {"coordinates":[-1.580295,54.976822],"type":"Point"}
}
