{
  "type": "Feature",
  "properties": {
    "date:inception_lower":"2010-09-01",
    "date:inception_upper":"2010-09-30",
    "iso:country":"GB",
    "wof:name":"IV17 0WG",
    "wof:placetype":"postalcode"
},
  "geometry": {"coordinates":[-4.241275,57.696555],"type":"Point"}
}