{
  "type": "Feature",
  "properties": {
    "iso:country":"GB",
    "wof:name":"B43 6AQ",
    "wof:placetype":"postalcode"
},
  "geometry": {"coordinates":[-1.94390746517365,52.54510794073326],"type":"Point"}
}