{
  "type": "Feature",
  "properties": {
    "iso:country":"GB",
    "wof:name":"TS14 8AP",
    "wof:placetype":"postalcode"
},
  "geometry": {"coordinates":[-1.06846365792415,54.52886017859252],"type":"Point"}
}