{
  "type": "Feature",
  "properties": {
    "iso:country": "GB",
    "wof:name": "CB3 0NA",
    "wof:placetype": "postalcode"
  },
  "geometry": {"coordinates":[0.086699,52.231603],"type":"Point"}
}
