{
  "type": "Feature",
  "properties": {
    "iso:country":"GB",
    "wof:name":"CB3 0NA",
    "wof:placetype":"postalcode"
},
  "geometry": {"coordinates":[0.08643137714517,52.23178273412652],"type":"Point"}
}