{
  "type": "Feature",
  "properties": {
    "date:inception_lower": "1980-01-01",
    "date:inception_upper": "1980-01-01",
    "iso:country": "GB",
    "wof:name": "SA41 3PU",
    "wof:placetype": "postalcode"
  },
  "geometry": {"coordinates":[-4.737403,52.028314],"type":"Point"}
}
