{
  "type": "Feature",
  "properties": {
    "iso:country":"GB",
    "wof:name":"SA41 3PU",
    "wof:placetype":"postalcode"
},
  "geometry": {"coordinates":[-4.73740307718028,52.02831370556257],"type":"Point"}
}