{
  "type": "Feature",
  "properties": {
    "iso:country":"GB",
    "wof:name":"ST13 7PF",
    "wof:placetype":"postalcode"
},
  "geometry": {"coordinates":[-1.91431982786689,53.07120739579876],"type":"Point"}
}