{
  "type": "Feature",
  "properties": {
    "iso:country":"GB",
    "wof:name":"LS27 8LG",
    "wof:placetype":"postalcode"
},
  "geometry": {"coordinates":[-1.5931642012453,53.74796101696442],"type":"Point"}
}