{
  "type": "Feature",
  "properties": {
    "iso:country":"GB",
    "wof:name":"CV6 1PA",
    "wof:placetype":"postalcode"
},
  "geometry": {"coordinates":[-1.52340344949254,52.42189839413855],"type":"Point"}
}