{
  "type": "Feature",
  "properties": {
    "iso:country": "GB",
    "wof:name": "LL58 8HU",
    "wof:placetype": "postalcode"
  },
  "geometry": {"coordinates":[-4.101204,53.276481],"type":"Point"}
}
