{
  "type": "Feature",
  "properties": {
    "iso:country":"GB",
    "wof:name":"LL58 8HU",
    "wof:placetype":"postalcode"
},
  "geometry": {"coordinates":[-4.10120411543295,53.27648101959728],"type":"Point"}
}