{
  "type": "Feature",
  "properties": {
    "date:inception_lower": "1980-01-01",
    "date:inception_upper": "1980-01-01",
    "iso:country": "GB",
    "wof:name": "SA13 1YY",
    "wof:placetype": "postalcode"
  },
  "geometry": {"coordinates":[-3.776988,51.598121],"type":"Point"}
}
