{
  "type": "Feature",
  "properties": {
    "iso:country":"GB",
    "wof:name":"G41 5AL",
    "wof:placetype":"postalcode"
},
  "geometry": {"coordinates":[-4.30392599217173,55.84524420611774],"type":"Point"}
}