{
  "type": "Feature",
  "properties": {
    "iso:country": "GB",
    "wof:name": "TR26 2HA",
    "wof:placetype": "postalcode"
  },
  "geometry": {"coordinates":[-5.492899,50.207324],"type":"Point"}
}
