{
  "type": "Feature",
  "properties": {
    "iso:country": "GB",
    "wof:name": "DE6 2FE",
    "wof:placetype": "postalcode"
  },
  "geometry": {"coordinates":[-1.800976,52.931785],"type":"Point"}
}
