{
  "type": "Feature",
  "properties": {
    "iso:country":"GB",
    "wof:name":"DE6 2FE",
    "wof:placetype":"postalcode"
},
  "geometry": {"coordinates":[-1.7944351333969,52.92825883799096],"type":"Point"}
}