{
  "type": "Feature",
  "properties": {
    "date:inception_lower":"2001-12-01",
    "date:inception_upper":"2001-12-31",
    "iso:country":"GB",
    "wof:name":"NP22 3EL",
    "wof:placetype":"postalcode"
},
  "geometry": {"coordinates":[-3.243311,51.775759],"type":"Point"}
}