{
  "type": "Feature",
  "properties": {
    "date:inception_lower": "2015-03-01",
    "date:inception_upper": "2015-03-01",
    "iso:country": "GB",
    "wof:name": "LU7 9SE",
    "wof:placetype": "postalcode"
  },
  "geometry": {"coordinates":[-0.657675,51.902949],"type":"Point"}
}
