{
  "type": "Feature",
  "properties": {
    "iso:country":"GB",
    "wof:name":"DT7 3SD",
    "wof:placetype":"postalcode"
},
  "geometry": {"coordinates":[-2.95782552224115,50.73457391648722],"type":"Point"}
}