{
  "type": "Feature",
  "properties": {
    "iso:country": "GB",
    "wof:name": "LS11 7AE",
    "wof:placetype": "postalcode"
  },
  "geometry": {"coordinates":[-1.563,53.76877],"type":"Point"}
}
