{
  "type": "Feature",
  "properties": {
    "date:inception_lower":"1980-01-01",
    "date:inception_upper":"1980-01-31",
    "iso:country":"GB",
    "wof:name":"FK2 9EX",
    "wof:placetype":"postalcode"
},
  "geometry": {"coordinates":[-3.776703,56.007073],"type":"Point"}
}