{
  "type": "Feature",
  "properties": {
    "iso:country":"GB",
    "wof:name":"PE2 9QZ",
    "wof:placetype":"postalcode"
},
  "geometry": {"coordinates":[-0.25436558737411,52.56462006018278],"type":"Point"}
}