{
  "type": "Feature",
  "properties": {
    "iso:country":"GB",
    "wof:name":"DN35 9DJ",
    "wof:placetype":"postalcode"
},
  "geometry": {"coordinates":[-0.04584327635683,53.54885433148719],"type":"Point"}
}