{
  "type": "Feature",
  "properties": {
    "iso:country":"GB",
    "wof:name":"CV11 4TP",
    "wof:placetype":"postalcode"
},
  "geometry": {"coordinates":[-1.43291868617779,52.50026154597342],"type":"Point"}
}