{
  "type": "Feature",
  "properties": {
    "iso:country": "GB",
    "wof:name": "CV11 4TP",
    "wof:placetype": "postalcode"
  },
  "geometry": {"coordinates":[-1.432919,52.500262],"type":"Point"}
}
