{
  "type": "Feature",
  "properties": {
    "iso:country":"GB",
    "wof:name":"DY9 9TA",
    "wof:placetype":"postalcode"
},
  "geometry": {"coordinates":[-2.11834693258221,52.39019127261489],"type":"Point"}
}