{
  "type": "Feature",
  "properties": {
    "iso:country": "GB",
    "wof:name": "DY9 9TA",
    "wof:placetype": "postalcode"
  },
  "geometry": {"coordinates":[-2.118347,52.390191],"type":"Point"}
}
