{
  "type": "Feature",
  "properties": {
    "date:inception_lower":"2007-10-01",
    "date:inception_upper":"2007-10-31",
    "iso:country":"GB",
    "wof:name":"DY9 9TA",
    "wof:placetype":"postalcode"
},
  "geometry": {"coordinates":[-2.118347,52.390191],"type":"Point"}
}