{
  "type": "Feature",
  "properties": {
    "iso:country":"GB",
    "wof:name":"PA36 4AQ",
    "wof:placetype":"postalcode"
},
  "geometry": {"coordinates":[-4.80833056160519,56.53269870832192],"type":"Point"}
}