{
  "type": "Feature",
  "properties": {
    "date:inception_lower": "1980-01-01",
    "date:inception_upper": "1980-01-01",
    "iso:country": "GB",
    "wof:name": "PA36 4AQ",
    "wof:placetype": "postalcode"
  },
  "geometry": {"coordinates":[-4.808331,56.532699],"type":"Point"}
}
