{
  "type": "Feature",
  "properties": {
    "iso:country":"GB",
    "wof:name":"SA44 5QS",
    "wof:placetype":"postalcode"
},
  "geometry": {"coordinates":[-4.43834603739552,52.09899493952328],"type":"Point"}
}