{
  "type": "Feature",
  "properties": {
    "iso:country":"GB",
    "wof:name":"SA11 2EX",
    "wof:placetype":"postalcode"
},
  "geometry": {"coordinates":[-3.82084892205132,51.63049584071026],"type":"Point"}
}