{
  "type": "Feature",
  "properties": {
    "iso:country":"GB",
    "wof:name":"SK6 6HL",
    "wof:placetype":"postalcode"
},
  "geometry": {"coordinates":[-2.08125239289628,53.40083871856491],"type":"Point"}
}