{
  "type": "Feature",
  "properties": {
    "iso:country":"GB",
    "wof:name":"DD5 1EG",
    "wof:placetype":"postalcode"
},
  "geometry": {"coordinates":[-2.87887994768149,56.46568088575032],"type":"Point"}
}