{
  "type": "Feature",
  "properties": {
    "iso:country": "GB",
    "wof:name": "DD5 1EG",
    "wof:placetype": "postalcode"
  },
  "geometry": {"coordinates":[-2.87888,56.465681],"type":"Point"}
}
