{
  "type": "Feature",
  "properties": {
    "date:inception_lower": "1980-01-01",
    "date:inception_upper": "1980-01-01",
    "iso:country": "GB",
    "wof:name": "LN11 7SP",
    "wof:placetype": "postalcode"
  },
  "geometry": {"coordinates":[0.148393,53.3834],"type":"Point"}
}
