{
  "type": "Feature",
  "properties": {
    "iso:country":"GB",
    "wof:name":"NG1 6BN",
    "wof:placetype":"postalcode"
},
  "geometry": {"coordinates":[-1.15395950359221,52.95228690611864],"type":"Point"}
}