{
  "type": "Feature",
  "properties": {
    "date:inception_lower": "1980-01-01",
    "date:inception_upper": "1980-01-01",
    "iso:country": "GB",
    "wof:name": "HP21 7AJ",
    "wof:placetype": "postalcode"
  },
  "geometry": {"coordinates":[-0.778314,51.810067],"type":"Point"}
}
