{
  "type": "Feature",
  "properties": {
    "iso:country":"GB",
    "wof:name":"M30 7RR",
    "wof:placetype":"postalcode"
},
  "geometry": {"coordinates":[-2.40364802596542,53.47504919432007],"type":"Point"}
}