{
  "type": "Feature",
  "properties": {
    "iso:country": "GB",
    "wof:name": "BN20 0EW",
    "wof:placetype": "postalcode"
  },
  "geometry": {"coordinates":[0.206754,50.764136],"type":"Point"}
}
