{
  "type": "Feature",
  "properties": {
    "date:inception_lower":"1980-01-01",
    "date:inception_upper":"1980-01-31",
    "iso:country":"GB",
    "wof:name":"BN20 0EW",
    "wof:placetype":"postalcode"
},
  "geometry": {"coordinates":[0.206754,50.764136],"type":"Point"}
}