{
  "type": "Feature",
  "properties": {
    "iso:country":"GB",
    "wof:name":"CB7 5JF",
    "wof:placetype":"postalcode"
},
  "geometry": {"coordinates":[0.34042944493482,52.335589287327],"type":"Point"}
}