{
  "type": "Feature",
  "properties": {
    "iso:country": "GB",
    "wof:name": "TS17 6JL",
    "wof:placetype": "postalcode"
  },
  "geometry": {"coordinates":[-1.30248,54.553775],"type":"Point"}
}
