{
  "type": "Feature",
  "properties": {
    "iso:country":"GB",
    "wof:name":"TS17 6JL",
    "wof:placetype":"postalcode"
},
  "geometry": {"coordinates":[-1.30247990216533,54.55377494851153],"type":"Point"}
}