{
  "type": "Feature",
  "properties": {
    "date:inception_lower": "1981-06-01",
    "date:inception_upper": "1981-06-01",
    "iso:country": "GB",
    "wof:name": "PR5 8AD",
    "wof:placetype": "postalcode"
  },
  "geometry": {"coordinates":[-2.651383,53.721512],"type":"Point"}
}
