{
  "type": "Feature",
  "properties": {
    "iso:country":"GB",
    "wof:name":"WF4 3QF",
    "wof:placetype":"postalcode"
},
  "geometry": {"coordinates":[-1.52368079813635,53.65020123492657],"type":"Point"}
}