{
  "type": "Feature",
  "properties": {
    "date:inception_lower":"1991-01-01",
    "date:inception_upper":"1991-01-31",
    "iso:country":"GB",
    "wof:name":"WF4 3QF",
    "wof:placetype":"postalcode"
},
  "geometry": {"coordinates":[-1.523681,53.650201],"type":"Point"}
}