{
  "type": "Feature",
  "properties": {
    "iso:country":"GB",
    "wof:name":"EX16 9RY",
    "wof:placetype":"postalcode"
},
  "geometry": {"coordinates":[-3.45411871495144,51.00647861410233],"type":"Point"}
}