{
  "type": "Feature",
  "properties": {
    "date:inception_lower": "2015-02-01",
    "date:inception_upper": "2015-02-01",
    "iso:country": "GB",
    "wof:name": "CV4 8LZ",
    "wof:placetype": "postalcode"
  },
  "geometry": {"coordinates":[-1.5582,52.396859],"type":"Point"}
}
