{
  "type": "Feature",
  "properties": {
    "iso:country":"GB",
    "wof:name":"CV4 8LZ",
    "wof:placetype":"postalcode"
},
  "geometry": {"coordinates":[-1.5575785427527,52.39680480359688],"type":"Point"}
}