{
  "type": "Feature",
  "properties": {
    "iso:country":"GB",
    "wof:name":"CH1 1RP",
    "wof:placetype":"postalcode"
},
  "geometry": {"coordinates":[-2.8883660142314,53.18731563032914],"type":"Point"}
}