{
  "type": "Feature",
  "properties": {
    "iso:country":"GB",
    "wof:name":"LA11 6SL",
    "wof:placetype":"postalcode"
},
  "geometry": {"coordinates":[-2.83151154812419,54.25332268209263],"type":"Point"}
}