{
  "type": "Feature",
  "properties": {
    "iso:country": "GB",
    "wof:name": "LA11 6SL",
    "wof:placetype": "postalcode"
  },
  "geometry": {"coordinates":[-2.834737,54.25189],"type":"Point"}
}
