{
  "type": "Feature",
  "properties": {
    "date:inception_lower": "1980-01-01",
    "date:inception_upper": "1980-01-01",
    "iso:country": "GB",
    "wof:name": "LA11 6SL",
    "wof:placetype": "postalcode"
  },
  "geometry": {"coordinates":[-2.834737,54.25189],"type":"Point"}
}
