{
  "type": "Feature",
  "properties": {
    "iso:country": "GB",
    "wof:name": "TN8 5BN",
    "wof:placetype": "postalcode"
  },
  "geometry": {"coordinates":[0.06516,51.193156],"type":"Point"}
}
