{
  "type": "Feature",
  "properties": {
    "iso:country": "GB",
    "wof:name": "NN15 6XE",
    "wof:placetype": "postalcode"
  },
  "geometry": {"coordinates":[-0.718484,52.377262],"type":"Point"}
}
