{
  "type": "Feature",
  "properties": {
    "date:inception_lower":"1991-09-01",
    "date:inception_upper":"1991-09-30",
    "iso:country":"GB",
    "wof:name":"NN15 6XE",
    "wof:placetype":"postalcode"
},
  "geometry": {"coordinates":[-0.718484,52.377262],"type":"Point"}
}