{
  "type": "Feature",
  "properties": {
    "iso:country": "GB",
    "wof:name": "BH15 1UH",
    "wof:placetype": "postalcode"
  },
  "geometry": {"coordinates":[-1.979907,50.712322],"type":"Point"}
}
