{
  "type": "Feature",
  "properties": {
    "iso:country": "GB",
    "wof:name": "M30 7QF",
    "wof:placetype": "postalcode"
  },
  "geometry": {"coordinates":[-2.383869,53.47711],"type":"Point"}
}
