{
  "type": "Feature",
  "properties": {
    "iso:country":"GB",
    "wof:name":"SG5 4DJ",
    "wof:placetype":"postalcode"
},
  "geometry": {"coordinates":[-0.22548179480731,52.01781454716868],"type":"Point"}
}