{
  "type": "Feature",
  "properties": {
    "iso:country": "GB",
    "wof:name": "SG5 4DJ",
    "wof:placetype": "postalcode"
  },
  "geometry": {"coordinates":[-0.225482,52.017815],"type":"Point"}
}
