{
  "type": "Feature",
  "properties": {
    "iso:country": "GB",
    "wof:name": "BN2 1EW",
    "wof:placetype": "postalcode"
  },
  "geometry": {"coordinates":[-0.115755,50.818269],"type":"Point"}
}
