{
  "type": "Feature",
  "properties": {
    "iso:country":"GB",
    "wof:name":"BN2 1EW",
    "wof:placetype":"postalcode"
},
  "geometry": {"coordinates":[-0.11575462081371,50.81826906482749],"type":"Point"}
}