{
  "type": "Feature",
  "properties": {
    "iso:country":"GB",
    "wof:name":"AL3 8DS",
    "wof:placetype":"postalcode"
},
  "geometry": {"coordinates":[-0.4403314018403,51.81403883533952],"type":"Point"}
}