{
  "type": "Feature",
  "properties": {
    "date:inception_lower":"1980-01-01",
    "date:inception_upper":"1980-01-31",
    "iso:country":"GB",
    "wof:name":"NE8 4AU",
    "wof:placetype":"postalcode"
},
  "geometry": {"coordinates":[-1.598393,54.956028],"type":"Point"}
}