{
  "type": "Feature",
  "properties": {
    "iso:country": "GB",
    "wof:name": "NE8 4AU",
    "wof:placetype": "postalcode"
  },
  "geometry": {"coordinates":[-1.598393,54.956028],"type":"Point"}
}
