{
  "type": "Feature",
  "properties": {
    "iso:country": "GB",
    "wof:name": "NE11 9LF",
    "wof:placetype": "postalcode"
  },
  "geometry": {"coordinates":[-1.639326,54.957271],"type":"Point"}
}
