{
  "type": "Feature",
  "properties": {
    "iso:country":"GB",
    "wof:name":"GU31 5NQ",
    "wof:placetype":"postalcode"
},
  "geometry": {"coordinates":[-0.86946410465087,50.96593713410532],"type":"Point"}
}