{
  "type": "Feature",
  "properties": {
    "iso:country":"GB",
    "wof:name":"PH2 8HB",
    "wof:placetype":"postalcode"
},
  "geometry": {"coordinates":[-3.4371347748367,56.39285919607878],"type":"Point"}
}