{
  "type": "Feature",
  "properties": {
    "iso:country": "GB",
    "wof:name": "PH2 8HB",
    "wof:placetype": "postalcode"
  },
  "geometry": {"coordinates":[-3.437135,56.392859],"type":"Point"}
}
