{
  "type": "Feature",
  "properties": {
    "iso:country":"GB",
    "wof:name":"RG24 9JT",
    "wof:placetype":"postalcode"
},
  "geometry": {"coordinates":[-1.10995089346007,51.29080311754905],"type":"Point"}
}