{
  "type": "Feature",
  "properties": {
    "iso:country": "GB",
    "wof:name": "ME12 1UH",
    "wof:placetype": "postalcode"
  },
  "geometry": {"coordinates":[0.76415,51.437554],"type":"Point"}
}
