{
  "type": "Feature",
  "properties": {
    "iso:country":"GB",
    "wof:name":"ME12 1UH",
    "wof:placetype":"postalcode"
},
  "geometry": {"coordinates":[0.76414983242947,51.43755425974013],"type":"Point"}
}