{
  "type": "Feature",
  "properties": {
    "iso:country":"GB",
    "wof:name":"N16 0NT",
    "wof:placetype":"postalcode"
},
  "geometry": {"coordinates":[-0.0768718003794,51.56176239838506],"type":"Point"}
}