{
  "type": "Feature",
  "properties": {
    "iso:country": "GB",
    "wof:name": "OX11 8NE",
    "wof:placetype": "postalcode"
  },
  "geometry": {"coordinates":[-1.255391,51.59911],"type":"Point"}
}
