{
  "type": "Feature",
  "properties": {
    "iso:country": "GB",
    "wof:name": "HU3 1TG",
    "wof:placetype": "postalcode"
  },
  "geometry": {"coordinates":[-0.353427,53.755833],"type":"Point"}
}
