{
  "type": "Feature",
  "properties": {
    "iso:country":"GB",
    "wof:name":"PE11 2JL",
    "wof:placetype":"postalcode"
},
  "geometry": {"coordinates":[-0.13690176428223,52.79033583265937],"type":"Point"}
}