{
  "type": "Feature",
  "properties": {
    "iso:country": "GB",
    "wof:name": "ME16 0GT",
    "wof:placetype": "postalcode"
  },
  "geometry": {"coordinates":[0.517413,51.275807],"type":"Point"}
}
