{
  "type": "Feature",
  "properties": {
    "iso:country": "GB",
    "wof:name": "CA13 9AL",
    "wof:placetype": "postalcode"
  },
  "geometry": {"coordinates":[-3.357733,54.66235],"type":"Point"}
}
