{
  "type": "Feature",
  "properties": {
    "iso:country":"GB",
    "wof:name":"NP20 4GG",
    "wof:placetype":"postalcode"
},
  "geometry": {"coordinates":[-3.00179305465193,51.58456854835421],"type":"Point"}
}