{
  "type": "Feature",
  "properties": {
    "iso:country":"GB",
    "wof:name":"BA1 6SS",
    "wof:placetype":"postalcode"
},
  "geometry": {"coordinates":[-2.34400784712669,51.39967214993315],"type":"Point"}
}