{
  "type": "Feature",
  "properties": {
    "date:inception_lower":"1980-01-01",
    "date:inception_upper":"1980-01-31",
    "iso:country":"GB",
    "wof:name":"BA1 6SS",
    "wof:placetype":"postalcode"
},
  "geometry": {"coordinates":[-2.344008,51.399672],"type":"Point"}
}