{
  "type": "Feature",
  "properties": {
    "iso:country":"GB",
    "wof:name":"W1J 8BJ",
    "wof:placetype":"postalcode"
},
  "geometry": {"coordinates":[-0.14461176290334,51.50743251213348],"type":"Point"}
}