{
  "type": "Feature",
  "properties": {
    "iso:country": "GB",
    "wof:name": "S20 6QG",
    "wof:placetype": "postalcode"
  },
  "geometry": {"coordinates":[-1.375255,53.337067],"type":"Point"}
}
