{
  "type": "Feature",
  "properties": {
    "iso:country":"GB",
    "wof:name":"S20 6QG",
    "wof:placetype":"postalcode"
},
  "geometry": {"coordinates":[-1.37525480908021,53.337067386154],"type":"Point"}
}