{
  "type": "Feature",
  "properties": {
    "date:inception_lower":"1980-01-01",
    "date:inception_upper":"1980-01-31",
    "iso:country":"GB",
    "wof:name":"WA11 0RL",
    "wof:placetype":"postalcode"
},
  "geometry": {"coordinates":[-2.64766,53.468852],"type":"Point"}
}