{
  "type": "Feature",
  "properties": {
    "iso:country":"GB",
    "wof:name":"WA11 0RL",
    "wof:placetype":"postalcode"
},
  "geometry": {"coordinates":[-2.64766043471091,53.46885184816529],"type":"Point"}
}