{
  "type": "Feature",
  "properties": {
    "iso:country":"GB",
    "wof:name":"E16 2EW",
    "wof:placetype":"postalcode"
},
  "geometry": {"coordinates":[0.04712854836124,51.50155348010454],"type":"Point"}
}