{
  "type": "Feature",
  "properties": {
    "date:inception_lower": "1994-05-01",
    "date:inception_upper": "1994-05-01",
    "iso:country": "GB",
    "wof:name": "M7 2HY",
    "wof:placetype": "postalcode"
  },
  "geometry": {"coordinates":[-2.268672,53.501756],"type":"Point"}
}
