{
  "type": "Feature",
  "properties": {
    "date:inception_lower": "1998-12-01",
    "date:inception_upper": "1998-12-01",
    "iso:country": "GB",
    "wof:name": "TN22 5AF",
    "wof:placetype": "postalcode"
  },
  "geometry": {"coordinates":[0.092251,50.966884],"type":"Point"}
}
