{
  "type": "Feature",
  "properties": {
    "date:inception_lower": "1980-01-01",
    "date:inception_upper": "1980-01-01",
    "iso:country": "GB",
    "wof:name": "CV10 8NE",
    "wof:placetype": "postalcode"
  },
  "geometry": {"coordinates":[-1.518993,52.517706],"type":"Point"}
}
