{
  "type": "Feature",
  "properties": {
    "iso:country":"GB",
    "wof:name":"BS3 2NW",
    "wof:placetype":"postalcode"
},
  "geometry": {"coordinates":[-2.61281856484577,51.43431629747474],"type":"Point"}
}