{
  "type": "Feature",
  "properties": {
    "date:inception_lower":"1980-01-01",
    "date:inception_upper":"1980-01-31",
    "iso:country":"GB",
    "wof:name":"BS3 2NW",
    "wof:placetype":"postalcode"
},
  "geometry": {"coordinates":[-2.612923,51.434359],"type":"Point"}
}