{
  "type": "Feature",
  "properties": {
    "iso:country": "GB",
    "wof:name": "AB32 6JF",
    "wof:placetype": "postalcode"
  },
  "geometry": {"coordinates":[-2.306939,57.152771],"type":"Point"}
}
