{
  "type": "Feature",
  "properties": {
    "iso:country":"GB",
    "wof:name":"AB32 6JF",
    "wof:placetype":"postalcode"
},
  "geometry": {"coordinates":[-2.30693948705004,57.15277083513408],"type":"Point"}
}