{
  "type": "Feature",
  "properties": {
    "date:inception_lower": "2006-07-01",
    "date:inception_upper": "2006-07-01",
    "iso:country": "GB",
    "wof:name": "CF64 3NS",
    "wof:placetype": "postalcode"
  },
  "geometry": {"coordinates":[-3.168474,51.435489],"type":"Point"}
}
