{
  "type": "Feature",
  "properties": {
    "iso:country":"GB",
    "wof:name":"DY5 3TL",
    "wof:placetype":"postalcode"
},
  "geometry": {"coordinates":[-2.1445948221906,52.48114115765728],"type":"Point"}
}