{
  "type": "Feature",
  "properties": {
    "date:inception_lower": "1980-01-01",
    "date:inception_upper": "1980-01-01",
    "iso:country": "GB",
    "wof:name": "DY5 3TL",
    "wof:placetype": "postalcode"
  },
  "geometry": {"coordinates":[-2.144633,52.481173],"type":"Point"}
}
