{
  "type": "Feature",
  "properties": {
    "iso:country": "GB",
    "wof:name": "CH3 5ES",
    "wof:placetype": "postalcode"
  },
  "geometry": {"coordinates":[-2.863829,53.192144],"type":"Point"}
}
