{
  "type": "Feature",
  "properties": {
    "iso:country":"GB",
    "wof:name":"CH3 5ES",
    "wof:placetype":"postalcode"
},
  "geometry": {"coordinates":[-2.86382948634782,53.19214351309724],"type":"Point"}
}