{
  "type": "Feature",
  "properties": {
    "iso:country":"GB",
    "wof:name":"SR6 7LB",
    "wof:placetype":"postalcode"
},
  "geometry": {"coordinates":[-1.37298247740153,54.95122014087102],"type":"Point"}
}