{
  "type": "Feature",
  "properties": {
    "iso:country": "GB",
    "wof:name": "SR6 7LB",
    "wof:placetype": "postalcode"
  },
  "geometry": {"coordinates":[-1.372982,54.95122],"type":"Point"}
}
