{
  "type": "Feature",
  "properties": {
    "date:inception_lower": "1980-01-01",
    "date:inception_upper": "1980-01-01",
    "iso:country": "GB",
    "wof:name": "CH2 2BT",
    "wof:placetype": "postalcode"
  },
  "geometry": {"coordinates":[-2.889253,53.20633],"type":"Point"}
}
