{
  "type": "Feature",
  "properties": {
    "iso:country":"GB",
    "wof:name":"KY11 2RD",
    "wof:placetype":"postalcode"
},
  "geometry": {"coordinates":[-3.42367058212864,56.04052558920392],"type":"Point"}
}