{
  "type": "Feature",
  "properties": {
    "iso:country":"GB",
    "wof:name":"CO16 8EJ",
    "wof:placetype":"postalcode"
},
  "geometry": {"coordinates":[1.07006752430325,51.7985023219065],"type":"Point"}
}