{
  "type": "Feature",
  "properties": {
    "date:inception_lower": "1980-01-01",
    "date:inception_upper": "1980-01-01",
    "iso:country": "GB",
    "wof:name": "L9 9DA",
    "wof:placetype": "postalcode"
  },
  "geometry": {"coordinates":[-2.945007,53.467686],"type":"Point"}
}
