{
  "type": "Feature",
  "properties": {
    "iso:country": "GB",
    "wof:name": "LE10 0DJ",
    "wof:placetype": "postalcode"
  },
  "geometry": {"coordinates":[-1.376311,52.549952],"type":"Point"}
}
