{
  "type": "Feature",
  "properties": {
    "date:inception_lower":"1980-01-01",
    "date:inception_upper":"1980-01-31",
    "iso:country":"GB",
    "wof:name":"KW1 5LE",
    "wof:placetype":"postalcode"
},
  "geometry": {"coordinates":[-3.101597,58.440808],"type":"Point"}
}