{
  "type": "Feature",
  "properties": {
    "iso:country": "GB",
    "wof:name": "KW1 5LE",
    "wof:placetype": "postalcode"
  },
  "geometry": {"coordinates":[-3.101597,58.440808],"type":"Point"}
}
