{
  "type": "Feature",
  "properties": {
    "date:inception_lower": "1980-01-01",
    "date:inception_upper": "1980-01-01",
    "iso:country": "GB",
    "wof:name": "TR13 0BE",
    "wof:placetype": "postalcode"
  },
  "geometry": {"coordinates":[-5.290282,50.148455],"type":"Point"}
}
