{
  "type": "Feature",
  "properties": {
    "iso:country":"GB",
    "wof:name":"TR13 0BE",
    "wof:placetype":"postalcode"
},
  "geometry": {"coordinates":[-5.29013731247007,50.1485312751767],"type":"Point"}
}