{
  "type": "Feature",
  "properties": {
    "iso:country":"GB",
    "wof:name":"B92 0BG",
    "wof:placetype":"postalcode"
},
  "geometry": {"coordinates":[-1.70125018298751,52.4274525611895],"type":"Point"}
}