{
  "type": "Feature",
  "properties": {
    "iso:country": "GB",
    "wof:name": "WA7 1TQ",
    "wof:placetype": "postalcode"
  },
  "geometry": {"coordinates":[-2.667948,53.350547],"type":"Point"}
}
