{
  "type": "Feature",
  "properties": {
    "date:inception_lower":"1990-07-01",
    "date:inception_upper":"1990-07-31",
    "iso:country":"GB",
    "wof:name":"WA7 1TQ",
    "wof:placetype":"postalcode"
},
  "geometry": {"coordinates":[-2.667948,53.350547],"type":"Point"}
}