{
  "type": "Feature",
  "properties": {
    "date:inception_lower": "2011-08-01",
    "date:inception_upper": "2011-08-01",
    "iso:country": "GB",
    "wof:name": "AB12 4UZ",
    "wof:placetype": "postalcode"
  },
  "geometry": {"coordinates":[-2.127586,57.076223],"type":"Point"}
}
