{
  "type": "Feature",
  "properties": {
    "iso:country":"GB",
    "wof:name":"ML3 8UN",
    "wof:placetype":"postalcode"
},
  "geometry": {"coordinates":[-4.07282303563478,55.76316068324192],"type":"Point"}
}