{
  "type": "Feature",
  "properties": {
    "iso:country":"GB",
    "wof:name":"DD4 9EA",
    "wof:placetype":"postalcode"
},
  "geometry": {"coordinates":[-2.95001668553873,56.49105899802613],"type":"Point"}
}