{
  "type": "Feature",
  "properties": {
    "iso:country":"GB",
    "wof:name":"SP2 7SU",
    "wof:placetype":"postalcode"
},
  "geometry": {"coordinates":[-1.80058234974559,51.06950284667007],"type":"Point"}
}