{
  "type": "Feature",
  "properties": {
    "iso:country":"GB",
    "wof:name":"NP12 0PT",
    "wof:placetype":"postalcode"
},
  "geometry": {"coordinates":[-3.20799581022162,51.70656844850777],"type":"Point"}
}