{
  "type": "Feature",
  "properties": {
    "iso:country": "GB",
    "wof:name": "B60 3NE",
    "wof:placetype": "postalcode"
  },
  "geometry": {"coordinates":[-2.07053,52.324664],"type":"Point"}
}
