{
  "type": "Feature",
  "properties": {
    "iso:country":"GB",
    "wof:name":"B60 3NE",
    "wof:placetype":"postalcode"
},
  "geometry": {"coordinates":[-2.07053007130094,52.32466443511123],"type":"Point"}
}