{
  "type": "Feature",
  "properties": {
    "iso:country": "GB",
    "wof:name": "WC2N 5SA",
    "wof:placetype": "postalcode"
  },
  "geometry": {"coordinates":[-0.125937,51.507848],"type":"Point"}
}
