{
  "type": "Feature",
  "properties": {
    "iso:country":"GB",
    "wof:name":"NG18 3JZ",
    "wof:placetype":"postalcode"
},
  "geometry": {"coordinates":[-1.16508340124077,53.13579344979469],"type":"Point"}
}