{
  "type": "Feature",
  "properties": {
    "iso:country":"GB",
    "wof:name":"L23 3AH",
    "wof:placetype":"postalcode"
},
  "geometry": {"coordinates":[-3.03637573900497,53.48819750040903],"type":"Point"}
}