{
  "type": "Feature",
  "properties": {
    "date:inception_lower": "1980-01-01",
    "date:inception_upper": "1980-01-01",
    "iso:country": "GB",
    "wof:name": "L23 3AH",
    "wof:placetype": "postalcode"
  },
  "geometry": {"coordinates":[-3.036376,53.488197],"type":"Point"}
}
