{
  "type": "Feature",
  "properties": {
    "iso:country": "GB",
    "wof:name": "PE27 5JE",
    "wof:placetype": "postalcode"
  },
  "geometry": {"coordinates":[-0.070071,52.323876],"type":"Point"}
}
