{
  "type": "Feature",
  "properties": {
    "iso:country":"GB",
    "wof:name":"PE27 5JE",
    "wof:placetype":"postalcode"
},
  "geometry": {"coordinates":[-0.07007062950841,52.32387575855135],"type":"Point"}
}