{
  "type": "Feature",
  "properties": {
    "date:inception_lower":"1980-01-01",
    "date:inception_upper":"1980-01-31",
    "iso:country":"GB",
    "wof:name":"BS23 3YT",
    "wof:placetype":"postalcode"
},
  "geometry": {"coordinates":[-2.956086,51.335819],"type":"Point"}
}