{
  "type": "Feature",
  "properties": {
    "iso:country": "GB",
    "wof:name": "GU33 7BQ",
    "wof:placetype": "postalcode"
  },
  "geometry": {"coordinates":[-0.880346,51.050414],"type":"Point"}
}
