{
  "type": "Feature",
  "properties": {
    "iso:country":"GB",
    "wof:name":"GU33 7BQ",
    "wof:placetype":"postalcode"
},
  "geometry": {"coordinates":[-0.88055110284049,51.05031336389914],"type":"Point"}
}