{
  "type": "Feature",
  "properties": {
    "iso:country":"GB",
    "wof:name":"CF33 4RQ",
    "wof:placetype":"postalcode"
},
  "geometry": {"coordinates":[-3.70309541918866,51.51176733571064],"type":"Point"}
}