{
  "type": "Feature",
  "properties": {
    "date:inception_lower":"2004-05-01",
    "date:inception_upper":"2004-05-31",
    "iso:country":"GB",
    "wof:name":"CF33 4RQ",
    "wof:placetype":"postalcode"
},
  "geometry": {"coordinates":[-3.703095,51.511767],"type":"Point"}
}