{
  "type": "Feature",
  "properties": {
    "iso:country":"GB",
    "wof:name":"B29 5AY",
    "wof:placetype":"postalcode"
},
  "geometry": {"coordinates":[-1.95865084338309,52.4371537690205],"type":"Point"}
}