{
  "type": "Feature",
  "properties": {
    "iso:country":"GB",
    "wof:name":"EX34 0DR",
    "wof:placetype":"postalcode"
},
  "geometry": {"coordinates":[-4.03122553261582,51.20616031536272],"type":"Point"}
}