{
  "type": "Feature",
  "properties": {
    "iso:country": "GB",
    "wof:name": "EX34 0DR",
    "wof:placetype": "postalcode"
  },
  "geometry": {"coordinates":[-4.031225,51.20616],"type":"Point"}
}
