{
  "type": "Feature",
  "properties": {
    "iso:country":"GB",
    "wof:name":"PO9 2RZ",
    "wof:placetype":"postalcode"
},
  "geometry": {"coordinates":[-0.96573994871847,50.85004123585001],"type":"Point"}
}