{
  "type": "Feature",
  "properties": {
    "date:inception_lower": "1980-01-01",
    "date:inception_upper": "1980-01-01",
    "iso:country": "GB",
    "wof:name": "PO9 2RZ",
    "wof:placetype": "postalcode"
  },
  "geometry": {"coordinates":[-0.96574,50.850041],"type":"Point"}
}
