{
  "type": "Feature",
  "properties": {
    "date:inception_lower": "1980-01-01",
    "date:inception_upper": "1980-01-01",
    "iso:country": "GB",
    "wof:name": "NG21 0TU",
    "wof:placetype": "postalcode"
  },
  "geometry": {"coordinates":[-1.116481,53.096043],"type":"Point"}
}
