{
  "type": "Feature",
  "properties": {
    "iso:country":"GB",
    "wof:name":"GL20 7PQ",
    "wof:placetype":"postalcode"
},
  "geometry": {"coordinates":[-2.0569447044188,52.04076349819331],"type":"Point"}
}