{
  "type": "Feature",
  "properties": {
    "iso:country": "GB",
    "wof:name": "GL20 7PQ",
    "wof:placetype": "postalcode"
  },
  "geometry": {"coordinates":[-2.056945,52.040763],"type":"Point"}
}
