{
  "type": "Feature",
  "properties": {
    "iso:country":"GB",
    "wof:name":"DH8 7SU",
    "wof:placetype":"postalcode"
},
  "geometry": {"coordinates":[-1.77206205069972,54.85172379507904],"type":"Point"}
}