{
  "type": "Feature",
  "properties": {
    "iso:country": "GB",
    "wof:name": "DH8 7SU",
    "wof:placetype": "postalcode"
  },
  "geometry": {"coordinates":[-1.772062,54.851724],"type":"Point"}
}
