{
  "type": "Feature",
  "properties": {
    "iso:country": "GB",
    "wof:name": "PE11 1HT",
    "wof:placetype": "postalcode"
  },
  "geometry": {"coordinates":[-0.166227,52.79316],"type":"Point"}
}
