{
  "type": "Feature",
  "properties": {
    "date:inception_lower":"1993-08-01",
    "date:inception_upper":"1993-08-31",
    "iso:country":"GB",
    "wof:name":"PE11 1HT",
    "wof:placetype":"postalcode"
},
  "geometry": {"coordinates":[-0.166227,52.79316],"type":"Point"}
}