{
  "type": "Feature",
  "properties": {
    "date:inception_lower":"1980-01-01",
    "date:inception_upper":"1980-01-31",
    "iso:country":"GB",
    "wof:name":"ST7 1LE",
    "wof:placetype":"postalcode"
},
  "geometry": {"coordinates":[-2.256227,53.087349],"type":"Point"}
}