{
  "type": "Feature",
  "properties": {
    "iso:country": "GB",
    "wof:name": "E12 6DT",
    "wof:placetype": "postalcode"
  },
  "geometry": {"coordinates":[0.054488,51.549194],"type":"Point"}
}
