{
  "type": "Feature",
  "properties": {
    "iso:country": "GB",
    "wof:name": "DE13 0NR",
    "wof:placetype": "postalcode"
  },
  "geometry": {"coordinates":[-1.652616,52.825073],"type":"Point"}
}
