{
  "type": "Feature",
  "properties": {
    "iso:country":"GB",
    "wof:name":"DE13 0NR",
    "wof:placetype":"postalcode"
},
  "geometry": {"coordinates":[-1.65261604829696,52.82507251761204],"type":"Point"}
}