{
  "type": "Feature",
  "properties": {
    "iso:country": "GB",
    "wof:name": "NE27 0LU",
    "wof:placetype": "postalcode"
  },
  "geometry": {"coordinates":[-1.488923,55.030455],"type":"Point"}
}
