{
  "type": "Feature",
  "properties": {
    "iso:country":"GB",
    "wof:name":"NN15 5YP",
    "wof:placetype":"postalcode"
},
  "geometry": {"coordinates":[-0.67671189090431,52.3632108126276],"type":"Point"}
}