{
  "type": "Feature",
  "properties": {
    "date:inception_lower": "1998-06-01",
    "date:inception_upper": "1998-06-01",
    "iso:country": "GB",
    "wof:name": "NN15 5YP",
    "wof:placetype": "postalcode"
  },
  "geometry": {"coordinates":[-0.676712,52.363211],"type":"Point"}
}
