{
  "type": "Feature",
  "properties": {
    "iso:country":"GB",
    "wof:name":"FK5 3LT",
    "wof:placetype":"postalcode"
},
  "geometry": {"coordinates":[-3.81748992769844,56.01832222938727],"type":"Point"}
}