{
  "type": "Feature",
  "properties": {
    "date:inception_lower":"1980-01-01",
    "date:inception_upper":"1980-01-31",
    "iso:country":"GB",
    "wof:name":"FK5 3LT",
    "wof:placetype":"postalcode"
},
  "geometry": {"coordinates":[-3.81749,56.018322],"type":"Point"}
}