{
  "type": "Feature",
  "properties": {
    "iso:country":"GB",
    "wof:name":"EH3 5ND",
    "wof:placetype":"postalcode"
},
  "geometry": {"coordinates":[-3.20139739660793,55.96859024070621],"type":"Point"}
}