{
  "type": "Feature",
  "properties": {
    "iso:country": "GB",
    "wof:name": "IV31 6EF",
    "wof:placetype": "postalcode"
  },
  "geometry": {"coordinates":[-3.289965,57.714975],"type":"Point"}
}
