{
  "type": "Feature",
  "properties": {
    "iso:country":"GB",
    "wof:name":"NE66 1DX",
    "wof:placetype":"postalcode"
},
  "geometry": {"coordinates":[-1.71747253910304,55.4118860634602],"type":"Point"}
}