{
  "type": "Feature",
  "properties": {
    "iso:country":"GB",
    "wof:name":"LE2 4QQ",
    "wof:placetype":"postalcode"
},
  "geometry": {"coordinates":[-1.06967843934891,52.59505783308083],"type":"Point"}
}