{
  "type": "Feature",
  "properties": {
    "date:inception_lower":"1980-01-01",
    "date:inception_upper":"1980-01-31",
    "iso:country":"GB",
    "wof:name":"CA4 8DL",
    "wof:placetype":"postalcode"
},
  "geometry": {"coordinates":[-2.862685,54.866296],"type":"Point"}
}