{
  "type": "Feature",
  "properties": {
    "iso:country": "GB",
    "wof:name": "TA9 3AR",
    "wof:placetype": "postalcode"
  },
  "geometry": {"coordinates":[-2.977515,51.22115],"type":"Point"}
}
