{
  "type": "Feature",
  "properties": {
    "iso:country":"GB",
    "wof:name":"TA9 3AR",
    "wof:placetype":"postalcode"
},
  "geometry": {"coordinates":[-2.97751466861099,51.22114976504142],"type":"Point"}
}