{
  "type": "Feature",
  "properties": {
    "iso:country":"GB",
    "wof:name":"SP8 5PN",
    "wof:placetype":"postalcode"
},
  "geometry": {"coordinates":[-2.31498743466503,51.07091095376467],"type":"Point"}
}