{
  "type": "Feature",
  "properties": {
    "iso:country": "GB",
    "wof:name": "WR11 4JQ",
    "wof:placetype": "postalcode"
  },
  "geometry": {"coordinates":[-1.948543,52.09533],"type":"Point"}
}
