{
  "type": "Feature",
  "properties": {
    "iso:country":"GB",
    "wof:name":"WR11 4JQ",
    "wof:placetype":"postalcode"
},
  "geometry": {"coordinates":[-1.94854323582915,52.09533015715393],"type":"Point"}
}