{
  "type": "Feature",
  "properties": {
    "iso:country": "GB",
    "wof:name": "LE11 3QX",
    "wof:placetype": "postalcode"
  },
  "geometry": {"coordinates":[-1.261857,52.76133],"type":"Point"}
}
