{
  "type": "Feature",
  "properties": {
    "iso:country":"GB",
    "wof:name":"TQ13 0FH",
    "wof:placetype":"postalcode"
},
  "geometry": {"coordinates":[-3.59306558927918,50.60810943163328],"type":"Point"}
}