{
  "type": "Feature",
  "properties": {
    "date:inception_lower": "2014-08-01",
    "date:inception_upper": "2014-08-01",
    "iso:country": "GB",
    "wof:name": "TQ13 0FH",
    "wof:placetype": "postalcode"
  },
  "geometry": {"coordinates":[-3.593066,50.608109],"type":"Point"}
}
