{
  "type": "Feature",
  "properties": {
    "iso:country": "GB",
    "wof:name": "SG13 8FP",
    "wof:placetype": "postalcode"
  },
  "geometry": {"coordinates":[-0.066296,51.790966],"type":"Point"}
}
