{
  "type": "Feature",
  "properties": {
    "iso:country":"GB",
    "wof:name":"SG13 8FP",
    "wof:placetype":"postalcode"
},
  "geometry": {"coordinates":[-0.06629604264053,51.79096596138136],"type":"Point"}
}