{
  "type": "Feature",
  "properties": {
    "iso:country": "GB",
    "wof:name": "FY4 4XE",
    "wof:placetype": "postalcode"
  },
  "geometry": {"coordinates":[-2.95998,53.807929],"type":"Point"}
}
