{
  "type": "Feature",
  "properties": {
    "iso:country":"GB",
    "wof:name":"FY4 4XE",
    "wof:placetype":"postalcode"
},
  "geometry": {"coordinates":[-2.95998045139731,53.80792942603552],"type":"Point"}
}