{
  "type": "Feature",
  "properties": {
    "date:inception_lower":"1980-01-01",
    "date:inception_upper":"1980-01-31",
    "iso:country":"GB",
    "wof:name":"FY4 4XE",
    "wof:placetype":"postalcode"
},
  "geometry": {"coordinates":[-2.95998,53.807929],"type":"Point"}
}