{
  "type": "Feature",
  "properties": {
    "iso:country": "GB",
    "wof:name": "PL26 7FD",
    "wof:placetype": "postalcode"
  },
  "geometry": {"coordinates":[-4.855773,50.35312],"type":"Point"}
}
