{
  "type": "Feature",
  "properties": {
    "date:inception_lower":"1980-01-01",
    "date:inception_upper":"1980-01-31",
    "iso:country":"GB",
    "wof:name":"DL12 9QR",
    "wof:placetype":"postalcode"
},
  "geometry": {"coordinates":[-1.965563,54.567705],"type":"Point"}
}