{
  "type": "Feature",
  "properties": {
    "iso:country":"GB",
    "wof:name":"DL12 9QR",
    "wof:placetype":"postalcode"
},
  "geometry": {"coordinates":[-1.96555457032741,54.56769563180369],"type":"Point"}
}