{
  "type": "Feature",
  "properties": {
    "iso:country":"GB",
    "wof:name":"HD4 6JR",
    "wof:placetype":"postalcode"
},
  "geometry": {"coordinates":[-1.78659475952679,53.62781324296866],"type":"Point"}
}