{
  "type": "Feature",
  "properties": {
    "iso:country":"GB",
    "wof:name":"HA3 9PE",
    "wof:placetype":"postalcode"
},
  "geometry": {"coordinates":[-0.2910044690062,51.59170259140828],"type":"Point"}
}