{
  "type": "Feature",
  "properties": {
    "date:inception_lower":"2012-07-01",
    "date:inception_upper":"2012-07-31",
    "iso:country":"GB",
    "wof:name":"ST16 3WP",
    "wof:placetype":"postalcode"
},
  "geometry": {"coordinates":[-2.111654,52.810416],"type":"Point"}
}