{
  "type": "Feature",
  "properties": {
    "iso:country":"GB",
    "wof:name":"ST16 3WP",
    "wof:placetype":"postalcode"
},
  "geometry": {"coordinates":[-2.11165425956256,52.81041600348727],"type":"Point"}
}