{
  "type": "Feature",
  "properties": {
    "date:inception_lower": "2006-03-01",
    "date:inception_upper": "2006-03-01",
    "iso:country": "GB",
    "wof:name": "M17 1EJ",
    "wof:placetype": "postalcode"
  },
  "geometry": {"coordinates":[-2.300469,53.465844],"type":"Point"}
}
