{
  "type": "Feature",
  "properties": {
    "iso:country": "GB",
    "wof:name": "L31 5LY",
    "wof:placetype": "postalcode"
  },
  "geometry": {"coordinates":[-2.940072,53.504724],"type":"Point"}
}
