{
  "type": "Feature",
  "properties": {
    "iso:country": "GB",
    "wof:name": "PE30 3XZ",
    "wof:placetype": "postalcode"
  },
  "geometry": {"coordinates":[0.446211,52.767569],"type":"Point"}
}
