{
  "type": "Feature",
  "properties": {
    "date:inception_lower": "1996-06-01",
    "date:inception_upper": "1996-06-01",
    "iso:country": "GB",
    "wof:name": "PE30 3XZ",
    "wof:placetype": "postalcode"
  },
  "geometry": {"coordinates":[0.446211,52.767569],"type":"Point"}
}
