{
  "type": "Feature",
  "properties": {
    "iso:country":"GB",
    "wof:name":"PE30 3XZ",
    "wof:placetype":"postalcode"
},
  "geometry": {"coordinates":[0.44621086645149,52.76756942881602],"type":"Point"}
}