{
  "type": "Feature",
  "properties": {
    "iso:country":"GB",
    "wof:name":"CV9 2QN",
    "wof:placetype":"postalcode"
},
  "geometry": {"coordinates":[-1.64425854083787,52.57945915475506],"type":"Point"}
}