{
  "type": "Feature",
  "properties": {
    "date:inception_lower": "1980-01-01",
    "date:inception_upper": "1980-01-01",
    "iso:country": "GB",
    "wof:name": "CV9 2QN",
    "wof:placetype": "postalcode"
  },
  "geometry": {"coordinates":[-1.644258,52.579459],"type":"Point"}
}
