{
  "type": "Feature",
  "properties": {
    "iso:country": "GB",
    "wof:name": "WS10 8NE",
    "wof:placetype": "postalcode"
  },
  "geometry": {"coordinates":[-2.038569,52.570448],"type":"Point"}
}
