{
  "type": "Feature",
  "properties": {
    "iso:country":"GB",
    "wof:name":"WV1 2PG",
    "wof:placetype":"postalcode"
},
  "geometry": {"coordinates":[-2.09251468509797,52.58624019137797],"type":"Point"}
}