{
  "type": "Feature",
  "properties": {
    "iso:country":"GB",
    "wof:name":"CM15 8AA",
    "wof:placetype":"postalcode"
},
  "geometry": {"coordinates":[0.30714562550157,51.62139594966561],"type":"Point"}
}