{
  "type": "Feature",
  "properties": {
    "iso:country":"GB",
    "wof:name":"BR2 0HF",
    "wof:placetype":"postalcode"
},
  "geometry": {"coordinates":[0.0039734770726,51.40292888089937],"type":"Point"}
}