{
  "type": "Feature",
  "properties": {
    "iso:country":"GB",
    "wof:name":"SN3 2LU",
    "wof:placetype":"postalcode"
},
  "geometry": {"coordinates":[-1.75265428754792,51.55343852849737],"type":"Point"}
}