{
  "type": "Feature",
  "properties": {
    "iso:country":"GB",
    "wof:name":"DG8 6DX",
    "wof:placetype":"postalcode"
},
  "geometry": {"coordinates":[-4.49006866232994,54.96607529387607],"type":"Point"}
}