{
  "type": "Feature",
  "properties": {
    "iso:country": "GB",
    "wof:name": "DG8 6DX",
    "wof:placetype": "postalcode"
  },
  "geometry": {"coordinates":[-4.49001,54.966112],"type":"Point"}
}
