{
  "type": "Feature",
  "properties": {
    "iso:country":"GB",
    "wof:name":"HU5 1BJ",
    "wof:placetype":"postalcode"
},
  "geometry": {"coordinates":[-0.34605738480769,53.76233905569634],"type":"Point"}
}