{
  "type": "Feature",
  "properties": {
    "iso:country":"GB",
    "wof:name":"M27 6EW",
    "wof:placetype":"postalcode"
},
  "geometry": {"coordinates":[-2.33441003936471,53.51997171338112],"type":"Point"}
}