{
  "type": "Feature",
  "properties": {
    "iso:country":"GB",
    "wof:name":"RG1 7PP",
    "wof:placetype":"postalcode"
},
  "geometry": {"coordinates":[-0.98658091429179,51.45650273566008],"type":"Point"}
}