{
  "type": "Feature",
  "properties": {
    "iso:country":"GB",
    "wof:name":"BD6 1JE",
    "wof:placetype":"postalcode"
},
  "geometry": {"coordinates":[-1.76939507853157,53.76235169607076],"type":"Point"}
}