{
  "type": "Feature",
  "properties": {
    "date:inception_lower":"2006-07-01",
    "date:inception_upper":"2006-07-31",
    "iso:country":"GB",
    "wof:name":"IP33 2TS",
    "wof:placetype":"postalcode"
},
  "geometry": {"coordinates":[0.720014,52.236224],"type":"Point"}
}