{
  "type": "Feature",
  "properties": {
    "iso:country":"GB",
    "wof:name":"BS35 1AY",
    "wof:placetype":"postalcode"
},
  "geometry": {"coordinates":[-2.51415314068506,51.61391058095126],"type":"Point"}
}