{
  "type": "Feature",
  "properties": {
    "iso:country": "GB",
    "wof:name": "G69 0DP",
    "wof:placetype": "postalcode"
  },
  "geometry": {"coordinates":[-4.089363,55.91337],"type":"Point"}
}
