{
  "type": "Feature",
  "properties": {
    "iso:country":"GB",
    "wof:name":"G69 0DP",
    "wof:placetype":"postalcode"
},
  "geometry": {"coordinates":[-4.08936256062549,55.9133698382176],"type":"Point"}
}