{
  "type": "Feature",
  "properties": {
    "iso:country":"GB",
    "wof:name":"NE30 4PN",
    "wof:placetype":"postalcode"
},
  "geometry": {"coordinates":[-1.43295391693718,55.03552751667194],"type":"Point"}
}