{
  "type": "Feature",
  "properties": {
    "iso:country":"GB",
    "wof:name":"PO21 3BX",
    "wof:placetype":"postalcode"
},
  "geometry": {"coordinates":[-0.7133768696734,50.78391589634412],"type":"Point"}
}