{
  "type": "Feature",
  "properties": {
    "iso:country":"GB",
    "wof:name":"HS7 5QH",
    "wof:placetype":"postalcode"
},
  "geometry": {"coordinates":[-7.23675646355939,57.41411615005775],"type":"Point"}
}