{
  "type": "Feature",
  "properties": {
    "date:inception_lower": "1995-07-01",
    "date:inception_upper": "1995-07-01",
    "iso:country": "GB",
    "wof:name": "HS7 5QH",
    "wof:placetype": "postalcode"
  },
  "geometry": {"coordinates":[-7.23674,57.414083],"type":"Point"}
}
