{
  "type": "Feature",
  "properties": {
    "iso:country": "GB",
    "wof:name": "HS7 5QH",
    "wof:placetype": "postalcode"
  },
  "geometry": {"coordinates":[-7.235605,57.414778],"type":"Point"}
}
