{
  "type": "Feature",
  "properties": {
    "iso:country": "GB",
    "wof:name": "HS7 5QH",
    "wof:placetype": "postalcode"
  },
  "geometry": {"coordinates":[-7.23674,57.414083],"type":"Point"}
}
