{
  "type": "Feature",
  "properties": {
    "iso:country": "GB",
    "wof:name": "NR30 2EG",
    "wof:placetype": "postalcode"
  },
  "geometry": {"coordinates":[1.731845,52.608971],"type":"Point"}
}
