{
  "type": "Feature",
  "properties": {
    "iso:country":"GB",
    "wof:name":"DA1 4DZ",
    "wof:placetype":"postalcode"
},
  "geometry": {"coordinates":[0.17200945182376,51.4539554378929],"type":"Point"}
}