{
  "type": "Feature",
  "properties": {
    "date:inception_lower": "1980-01-01",
    "date:inception_upper": "1980-01-01",
    "iso:country": "GB",
    "wof:name": "DA1 4DZ",
    "wof:placetype": "postalcode"
  },
  "geometry": {"coordinates":[0.172009,51.453955],"type":"Point"}
}
