{
  "type": "Feature",
  "properties": {
    "iso:country":"GB",
    "wof:name":"SS8 7QP",
    "wof:placetype":"postalcode"
},
  "geometry": {"coordinates":[0.62061245741907,51.51723524332196],"type":"Point"}
}