{
  "type": "Feature",
  "properties": {
    "iso:country": "GB",
    "wof:name": "SS8 7QP",
    "wof:placetype": "postalcode"
  },
  "geometry": {"coordinates":[0.621001,51.517248],"type":"Point"}
}
