{
  "type": "Feature",
  "properties": {
    "date:inception_lower": "1980-01-01",
    "date:inception_upper": "1980-01-01",
    "iso:country": "GB",
    "wof:name": "SS8 7QP",
    "wof:placetype": "postalcode"
  },
  "geometry": {"coordinates":[0.621001,51.517248],"type":"Point"}
}
