{
  "type": "Feature",
  "properties": {
    "iso:country":"GB",
    "wof:name":"S25 2UE",
    "wof:placetype":"postalcode"
},
  "geometry": {"coordinates":[-1.20693172560774,53.37846827428055],"type":"Point"}
}