{
  "type": "Feature",
  "properties": {
    "iso:country": "GB",
    "wof:name": "CV47 2BB",
    "wof:placetype": "postalcode"
  },
  "geometry": {"coordinates":[-1.421542,52.160661],"type":"Point"}
}
