{
  "type": "Feature",
  "properties": {
    "iso:country":"GB",
    "wof:name":"CV47 2BB",
    "wof:placetype":"postalcode"
},
  "geometry": {"coordinates":[-1.4215424901811,52.16066077356043],"type":"Point"}
}