{
  "type": "Feature",
  "properties": {
    "iso:country":"GB",
    "wof:name":"SW13 8ES",
    "wof:placetype":"postalcode"
},
  "geometry": {"coordinates":[-0.23299786825344,51.48485058715762],"type":"Point"}
}