{
  "type": "Feature",
  "properties": {
    "date:inception_lower": "2016-10-01",
    "date:inception_upper": "2016-10-01",
    "iso:country": "GB",
    "wof:name": "EX12 2FU",
    "wof:placetype": "postalcode"
  },
  "geometry": {"coordinates":[-3.069853,50.704738],"type":"Point"}
}
