{
  "type": "Feature",
  "properties": {
    "iso:country":"GB",
    "wof:name":"S40 2UJ",
    "wof:placetype":"postalcode"
},
  "geometry": {"coordinates":[-1.43854464199582,53.22107491862495],"type":"Point"}
}