{
  "type": "Feature",
  "properties": {
    "iso:country":"GB",
    "wof:name":"WF6 2HE",
    "wof:placetype":"postalcode"
},
  "geometry": {"coordinates":[-1.40975464790487,53.70480121152351],"type":"Point"}
}