{
  "type": "Feature",
  "properties": {
    "iso:country": "GB",
    "wof:name": "NE63 8AX",
    "wof:placetype": "postalcode"
  },
  "geometry": {"coordinates":[-1.582659,55.185711],"type":"Point"}
}
