{
  "type": "Feature",
  "properties": {
    "date:inception_lower": "1980-01-01",
    "date:inception_upper": "1980-01-01",
    "iso:country": "GB",
    "wof:name": "NP4 8UZ",
    "wof:placetype": "postalcode"
  },
  "geometry": {"coordinates":[-3.058896,51.747183],"type":"Point"}
}
