{
  "type": "Feature",
  "properties": {
    "iso:country":"GB",
    "wof:name":"NP4 8UZ",
    "wof:placetype":"postalcode"
},
  "geometry": {"coordinates":[-3.05889555015721,51.74718304709546],"type":"Point"}
}