{
  "type": "Feature",
  "properties": {
    "iso:country":"GB",
    "wof:name":"BN1 1HW",
    "wof:placetype":"postalcode"
},
  "geometry": {"coordinates":[-0.14061460385481,50.82145592444368],"type":"Point"}
}