{
  "type": "Feature",
  "properties": {
    "date:inception_lower": "1980-01-01",
    "date:inception_upper": "1980-01-01",
    "iso:country": "GB",
    "wof:name": "WA11 9RD",
    "wof:placetype": "postalcode"
  },
  "geometry": {"coordinates":[-2.705397,53.461244],"type":"Point"}
}
