{
  "type": "Feature",
  "properties": {
    "date:inception_lower": "2015-06-01",
    "date:inception_upper": "2015-06-01",
    "iso:country": "GB",
    "wof:name": "LE9 4AA",
    "wof:placetype": "postalcode"
  },
  "geometry": {"coordinates":[-1.279703,52.533429],"type":"Point"}
}
