{
  "type": "Feature",
  "properties": {
    "iso:country":"GB",
    "wof:name":"BS16 5UP",
    "wof:placetype":"postalcode"
},
  "geometry": {"coordinates":[-2.50655482218483,51.48786530961266],"type":"Point"}
}