{
  "type": "Feature",
  "properties": {
    "iso:country": "GB",
    "wof:name": "PE12 8RD",
    "wof:placetype": "postalcode"
  },
  "geometry": {"coordinates":[-0.00288,52.753621],"type":"Point"}
}
