{
  "type": "Feature",
  "properties": {
    "iso:country":"GB",
    "wof:name":"NG5 2JP",
    "wof:placetype":"postalcode"
},
  "geometry": {"coordinates":[-1.14762965759231,52.98125975753445],"type":"Point"}
}