{
  "type": "Feature",
  "properties": {
    "iso:country":"GB",
    "wof:name":"RG7 4PR",
    "wof:placetype":"postalcode"
},
  "geometry": {"coordinates":[-1.14120843673128,51.36335872667858],"type":"Point"}
}