{
  "type": "Feature",
  "properties": {
    "date:inception_lower": "1980-01-01",
    "date:inception_upper": "1980-01-01",
    "iso:country": "GB",
    "wof:name": "N12 7PD",
    "wof:placetype": "postalcode"
  },
  "geometry": {"coordinates":[-0.189176,51.612908],"type":"Point"}
}
