{
  "type": "Feature",
  "properties": {
    "iso:country":"GB",
    "wof:name":"N12 7PD",
    "wof:placetype":"postalcode"
},
  "geometry": {"coordinates":[-0.18917641084067,51.6129083176865],"type":"Point"}
}