{
  "type": "Feature",
  "properties": {
    "iso:country":"GB",
    "wof:name":"CO4 0HU",
    "wof:placetype":"postalcode"
},
  "geometry": {"coordinates":[0.93045605466233,51.91209614285999],"type":"Point"}
}