{
  "type": "Feature",
  "properties": {
    "iso:country": "GB",
    "wof:name": "CO4 0HU",
    "wof:placetype": "postalcode"
  },
  "geometry": {"coordinates":[0.930456,51.912096],"type":"Point"}
}
