{
  "type": "Feature",
  "properties": {
    "iso:country":"GB",
    "wof:name":"BA6 8TQ",
    "wof:placetype":"postalcode"
},
  "geometry": {"coordinates":[-2.68741826209771,51.09595734264119],"type":"Point"}
}