{
  "type": "Feature",
  "properties": {
    "iso:country": "GB",
    "wof:name": "BA6 8TQ",
    "wof:placetype": "postalcode"
  },
  "geometry": {"coordinates":[-2.687422,51.095951],"type":"Point"}
}
