{
  "type": "Feature",
  "properties": {
    "iso:country":"GB",
    "wof:name":"NG4 2BF",
    "wof:placetype":"postalcode"
},
  "geometry": {"coordinates":[-1.07866471875891,52.96392605945758],"type":"Point"}
}