{
  "type": "Feature",
  "properties": {
    "date:inception_lower": "2023-01-01",
    "date:inception_upper": "2023-01-01",
    "iso:country": "GB",
    "wof:name": "CM23 4SH",
    "wof:placetype": "postalcode"
  },
  "geometry": {"coordinates":[0.15632,51.852395],"type":"Point"}
}
