{
  "type": "Feature",
  "properties": {
    "iso:country": "GB",
    "wof:name": "BD12 8NE",
    "wof:placetype": "postalcode"
  },
  "geometry": {"coordinates":[-1.766519,53.74481],"type":"Point"}
}
