{
  "type": "Feature",
  "properties": {
    "iso:country":"GB",
    "wof:name":"SE17 3DT",
    "wof:placetype":"postalcode"
},
  "geometry": {"coordinates":[-0.09914633737468,51.48633625072177],"type":"Point"}
}