{
  "type": "Feature",
  "properties": {
    "iso:country":"GB",
    "wof:name":"TQ1 4LR",
    "wof:placetype":"postalcode"
},
  "geometry": {"coordinates":[-3.52839810344708,50.47776905314593],"type":"Point"}
}