{
  "type": "Feature",
  "properties": {
    "iso:country":"GB",
    "wof:name":"G84 8QD",
    "wof:placetype":"postalcode"
},
  "geometry": {"coordinates":[-4.76066998284858,56.01048774087246],"type":"Point"}
}