{
  "type": "Feature",
  "properties": {
    "iso:country":"GB",
    "wof:name":"OX16 2EL",
    "wof:placetype":"postalcode"
},
  "geometry": {"coordinates":[-1.34125948786015,52.06431852891305],"type":"Point"}
}