{
  "type": "Feature",
  "properties": {
    "iso:country":"GB",
    "wof:name":"SG18 8EE",
    "wof:placetype":"postalcode"
},
  "geometry": {"coordinates":[-0.25149989912541,52.08345588448618],"type":"Point"}
}