{
  "type": "Feature",
  "properties": {
    "date:inception_lower": "1984-10-01",
    "date:inception_upper": "1984-10-01",
    "iso:country": "GB",
    "wof:name": "BS14 9JP",
    "wof:placetype": "postalcode"
  },
  "geometry": {"coordinates":[-2.566745,51.41251],"type":"Point"}
}
