{
  "type": "Feature",
  "properties": {
    "iso:country": "GB",
    "wof:name": "BS14 9JP",
    "wof:placetype": "postalcode"
  },
  "geometry": {"coordinates":[-2.566745,51.41251],"type":"Point"}
}
