{
  "type": "Feature",
  "properties": {
    "iso:country":"GB",
    "wof:name":"NN11 4SE",
    "wof:placetype":"postalcode"
},
  "geometry": {"coordinates":[-1.15344380302773,52.24719508874296],"type":"Point"}
}