{
  "type": "Feature",
  "properties": {
    "iso:country":"GB",
    "wof:name":"CR2 6BA",
    "wof:placetype":"postalcode"
},
  "geometry": {"coordinates":[-0.10011908947994,51.35296356253349],"type":"Point"}
}