{
  "type": "Feature",
  "properties": {
    "iso:country":"GB",
    "wof:name":"IP28 6DN",
    "wof:placetype":"postalcode"
},
  "geometry": {"coordinates":[0.69452394406795,52.30212350882204],"type":"Point"}
}