{
  "type": "Feature",
  "properties": {
    "iso:country":"GB",
    "wof:name":"LN9 5BL",
    "wof:placetype":"postalcode"
},
  "geometry": {"coordinates":[-0.11542453510572,53.20887311017616],"type":"Point"}
}