{
  "type": "Feature",
  "properties": {
    "date:inception_lower": "2008-04-01",
    "date:inception_upper": "2008-04-01",
    "iso:country": "GB",
    "wof:name": "TQ12 6FR",
    "wof:placetype": "postalcode"
  },
  "geometry": {"coordinates":[-3.638468,50.518286],"type":"Point"}
}
