{
  "type": "Feature",
  "properties": {
    "date:inception_lower": "2003-10-01",
    "date:inception_upper": "2003-10-01",
    "iso:country": "GB",
    "wof:name": "G69 6GD",
    "wof:placetype": "postalcode"
  },
  "geometry": {"coordinates":[-4.119449,55.860047],"type":"Point"}
}
