{
  "type": "Feature",
  "properties": {
    "iso:country":"GB",
    "wof:name":"G69 6GD",
    "wof:placetype":"postalcode"
},
  "geometry": {"coordinates":[-4.11944862940288,55.86004721554121],"type":"Point"}
}