{
  "type": "Feature",
  "properties": {
    "iso:country":"GB",
    "wof:name":"WR15 8PS",
    "wof:placetype":"postalcode"
},
  "geometry": {"coordinates":[-2.61485580188401,52.25608799241718],"type":"Point"}
}