{
  "type": "Feature",
  "properties": {
    "date:inception_lower": "1990-09-01",
    "date:inception_upper": "1990-09-01",
    "iso:country": "GB",
    "wof:name": "EH54 9EN",
    "wof:placetype": "postalcode"
  },
  "geometry": {"coordinates":[-3.515412,55.867631],"type":"Point"}
}
