{
  "type": "Feature",
  "properties": {
    "iso:country":"GB",
    "wof:name":"EH54 9EN",
    "wof:placetype":"postalcode"
},
  "geometry": {"coordinates":[-3.51541165577982,55.86763089840066],"type":"Point"}
}