{
  "type": "Feature",
  "properties": {
    "iso:country":"GB",
    "wof:name":"NR12 9NP",
    "wof:placetype":"postalcode"
},
  "geometry": {"coordinates":[1.46098956816318,52.76099038526311],"type":"Point"}
}