{
  "type": "Feature",
  "properties": {
    "date:inception_lower": "1980-01-01",
    "date:inception_upper": "1980-01-01",
    "iso:country": "GB",
    "wof:name": "NR12 9NP",
    "wof:placetype": "postalcode"
  },
  "geometry": {"coordinates":[1.460894,52.761039],"type":"Point"}
}
