{
  "type": "Feature",
  "properties": {
    "iso:country": "GB",
    "wof:name": "NR12 9NP",
    "wof:placetype": "postalcode"
  },
  "geometry": {"coordinates":[1.461025,52.761008],"type":"Point"}
}
