{
  "type": "Feature",
  "properties": {
    "date:inception_lower": "1980-01-01",
    "date:inception_upper": "1980-01-01",
    "iso:country": "GB",
    "wof:name": "ML4 1LS",
    "wof:placetype": "postalcode"
  },
  "geometry": {"coordinates":[-4.017281,55.827183],"type":"Point"}
}
