{
  "type": "Feature",
  "properties": {
    "iso:country":"GB",
    "wof:name":"ML4 1LS",
    "wof:placetype":"postalcode"
},
  "geometry": {"coordinates":[-4.01728143564516,55.8271831435352],"type":"Point"}
}