{
  "type": "Feature",
  "properties": {
    "date:inception_lower": "2022-09-01",
    "date:inception_upper": "2022-09-01",
    "iso:country": "GB",
    "wof:name": "CB22 7RQ",
    "wof:placetype": "postalcode"
  },
  "geometry": {"coordinates":[0.039787,52.131389],"type":"Point"}
}
