{
  "type": "Feature",
  "properties": {
    "iso:country":"GB",
    "wof:name":"CB22 7RQ",
    "wof:placetype":"postalcode"
},
  "geometry": {"coordinates":[0.03965889536902,52.13527294716001],"type":"Point"}
}