{
  "type": "Feature",
  "properties": {
    "iso:country":"GB",
    "wof:name":"BB9 9NW",
    "wof:placetype":"postalcode"
},
  "geometry": {"coordinates":[-2.19611938017741,53.83536748407902],"type":"Point"}
}