{
  "type": "Feature",
  "properties": {
    "iso:country":"GB",
    "wof:name":"B69 1NA",
    "wof:placetype":"postalcode"
},
  "geometry": {"coordinates":[-2.03763988512727,52.50260184067324],"type":"Point"}
}