{
  "type": "Feature",
  "properties": {
    "date:inception_lower": "2016-08-01",
    "date:inception_upper": "2016-08-01",
    "iso:country": "GB",
    "wof:name": "TS24 0GB",
    "wof:placetype": "postalcode"
  },
  "geometry": {"coordinates":[-1.216085,54.709855],"type":"Point"}
}
