{
  "type": "Feature",
  "properties": {
    "iso:country": "GB",
    "wof:name": "TS24 0GB",
    "wof:placetype": "postalcode"
  },
  "geometry": {"coordinates":[-1.219303,54.711179],"type":"Point"}
}
