{
  "type": "Feature",
  "properties": {
    "iso:country":"GB",
    "wof:name":"NP19 0FF",
    "wof:placetype":"postalcode"
},
  "geometry": {"coordinates":[-2.97587829290879,51.58492181104702],"type":"Point"}
}