{
  "type": "Feature",
  "properties": {
    "date:inception_lower": "1999-06-01",
    "date:inception_upper": "1999-06-01",
    "iso:country": "GB",
    "wof:name": "NP19 0FF",
    "wof:placetype": "postalcode"
  },
  "geometry": {"coordinates":[-2.975878,51.584922],"type":"Point"}
}
