{
  "type": "Feature",
  "properties": {
    "date:inception_lower": "2012-11-01",
    "date:inception_upper": "2012-11-01",
    "iso:country": "GB",
    "wof:name": "CH7 3FB",
    "wof:placetype": "postalcode"
  },
  "geometry": {"coordinates":[-3.067594,53.169106],"type":"Point"}
}
