{
  "type": "Feature",
  "properties": {
    "iso:country":"GB",
    "wof:name":"CH7 3FB",
    "wof:placetype":"postalcode"
},
  "geometry": {"coordinates":[-3.06759364624064,53.16910582371381],"type":"Point"}
}