{
  "type": "Feature",
  "properties": {
    "iso:country": "GB",
    "wof:name": "DE24 8LZ",
    "wof:placetype": "postalcode"
  },
  "geometry": {"coordinates":[-1.448963,52.915932],"type":"Point"}
}
