{
  "type": "Feature",
  "properties": {
    "iso:country":"GB",
    "wof:name":"DE24 8LZ",
    "wof:placetype":"postalcode"
},
  "geometry": {"coordinates":[-1.44904147797073,52.91587845939923],"type":"Point"}
}