{
  "type": "Feature",
  "properties": {
    "iso:country": "GB",
    "wof:name": "CM21 9JB",
    "wof:placetype": "postalcode"
  },
  "geometry": {"coordinates":[0.157547,51.807232],"type":"Point"}
}
