{
  "type": "Feature",
  "properties": {
    "date:inception_lower":"1998-12-01",
    "date:inception_upper":"1998-12-31",
    "iso:country":"GB",
    "wof:name":"CM21 9JB",
    "wof:placetype":"postalcode"
},
  "geometry": {"coordinates":[0.157547,51.807232],"type":"Point"}
}