{
  "type": "Feature",
  "properties": {
    "iso:country":"GB",
    "wof:name":"NW8 8QH",
    "wof:placetype":"postalcode"
},
  "geometry": {"coordinates":[-0.17568987282268,51.52774841270677],"type":"Point"}
}