{
  "type": "Feature",
  "properties": {
    "iso:country":"GB",
    "wof:name":"PE1 5WA",
    "wof:placetype":"postalcode"
},
  "geometry": {"coordinates":[-0.20639987272096,52.58486103765085],"type":"Point"}
}