{
  "type": "Feature",
  "properties": {
    "date:inception_lower":"1998-06-01",
    "date:inception_upper":"1998-06-30",
    "iso:country":"GB",
    "wof:name":"PE1 5WA",
    "wof:placetype":"postalcode"
},
  "geometry": {"coordinates":[-0.206393,52.5847],"type":"Point"}
}