{
  "type": "Feature",
  "properties": {
    "iso:country": "GB",
    "wof:name": "PE1 5WA",
    "wof:placetype": "postalcode"
  },
  "geometry": {"coordinates":[-0.206393,52.5847],"type":"Point"}
}
