{
  "type": "Feature",
  "properties": {
    "iso:country":"GB",
    "wof:name":"MK7 7SE",
    "wof:placetype":"postalcode"
},
  "geometry": {"coordinates":[-0.68653068156988,52.02436935047431],"type":"Point"}
}