{
  "type": "Feature",
  "properties": {
    "iso:country":"GB",
    "wof:name":"TN5 7HR",
    "wof:placetype":"postalcode"
},
  "geometry": {"coordinates":[0.41160559452952,51.06082945654305],"type":"Point"}
}