{
  "type": "Feature",
  "properties": {
    "date:inception_lower": "2019-09-01",
    "date:inception_upper": "2019-09-01",
    "iso:country": "GB",
    "wof:name": "TF10 7GU",
    "wof:placetype": "postalcode"
  },
  "geometry": {"coordinates":[-2.363521,52.766633],"type":"Point"}
}
