{
  "type": "Feature",
  "properties": {
    "iso:country":"GB",
    "wof:name":"TR11 4RX",
    "wof:placetype":"postalcode"
},
  "geometry": {"coordinates":[-5.09496440766564,50.15332621970491],"type":"Point"}
}