{
  "type": "Feature",
  "properties": {
    "date:inception_lower": "1999-06-01",
    "date:inception_upper": "1999-06-01",
    "iso:country": "GB",
    "wof:name": "TR11 4RX",
    "wof:placetype": "postalcode"
  },
  "geometry": {"coordinates":[-5.094918,50.153388],"type":"Point"}
}
