{
  "type": "Feature",
  "properties": {
    "iso:country":"GB",
    "wof:name":"PL19 8NH",
    "wof:placetype":"postalcode"
},
  "geometry": {"coordinates":[-4.16436971465348,50.55046759224741],"type":"Point"}
}