{
  "type": "Feature",
  "properties": {
    "date:inception_lower": "1980-01-01",
    "date:inception_upper": "1980-01-01",
    "iso:country": "GB",
    "wof:name": "PL19 8NH",
    "wof:placetype": "postalcode"
  },
  "geometry": {"coordinates":[-4.16437,50.550468],"type":"Point"}
}
