{
  "type": "Feature",
  "properties": {
    "date:inception_lower": "1980-01-01",
    "date:inception_upper": "1980-01-01",
    "iso:country": "GB",
    "wof:name": "S11 9HE",
    "wof:placetype": "postalcode"
  },
  "geometry": {"coordinates":[-1.505638,53.35278],"type":"Point"}
}
