{
  "type": "Feature",
  "properties": {
    "iso:country":"GB",
    "wof:name":"S11 9HE",
    "wof:placetype":"postalcode"
},
  "geometry": {"coordinates":[-1.50563802237235,53.35277954913236],"type":"Point"}
}