{
  "type": "Feature",
  "properties": {
    "iso:country":"GB",
    "wof:name":"BH9 1TQ",
    "wof:placetype":"postalcode"
},
  "geometry": {"coordinates":[-1.87243718297914,50.75333222114588],"type":"Point"}
}