{
  "type": "Feature",
  "properties": {
    "iso:country":"GB",
    "wof:name":"HG1 2JU",
    "wof:placetype":"postalcode"
},
  "geometry": {"coordinates":[-1.54971709585751,54.00179550343229],"type":"Point"}
}