{
  "type": "Feature",
  "properties": {
    "iso:country": "GB",
    "wof:name": "KA8 9PB",
    "wof:placetype": "postalcode"
  },
  "geometry": {"coordinates":[-4.607092,55.470974],"type":"Point"}
}
