{
  "type": "Feature",
  "properties": {
    "iso:country":"GB",
    "wof:name":"KA8 9PB",
    "wof:placetype":"postalcode"
},
  "geometry": {"coordinates":[-4.60709162176329,55.47097383059667],"type":"Point"}
}