{
  "type": "Feature",
  "properties": {
    "iso:country":"GB",
    "wof:name":"SK6 7DE",
    "wof:placetype":"postalcode"
},
  "geometry": {"coordinates":[-2.0561274356464,53.39473201584051],"type":"Point"}
}