{
  "type": "Feature",
  "properties": {
    "date:inception_lower":"1983-01-01",
    "date:inception_upper":"1983-01-31",
    "iso:country":"GB",
    "wof:name":"BS24 9NY",
    "wof:placetype":"postalcode"
},
  "geometry": {"coordinates":[-2.960511,51.321211],"type":"Point"}
}