{
  "type": "Feature",
  "properties": {
    "iso:country":"GB",
    "wof:name":"SA32 7NN",
    "wof:placetype":"postalcode"
},
  "geometry": {"coordinates":[-4.12697713577008,51.88363007060004],"type":"Point"}
}