{
  "type": "Feature",
  "properties": {
    "date:inception_lower": "1980-01-01",
    "date:inception_upper": "1980-01-01",
    "iso:country": "GB",
    "wof:name": "SA32 7NN",
    "wof:placetype": "postalcode"
  },
  "geometry": {"coordinates":[-4.126977,51.88363],"type":"Point"}
}
