{
  "type": "Feature",
  "properties": {
    "iso:country":"GB",
    "wof:name":"SS5 4UJ",
    "wof:placetype":"postalcode"
},
  "geometry": {"coordinates":[0.64671847694601,51.60319370173655],"type":"Point"}
}