{
  "type": "Feature",
  "properties": {
    "iso:country":"GB",
    "wof:name":"SP10 2EY",
    "wof:placetype":"postalcode"
},
  "geometry": {"coordinates":[-1.47150784093633,51.19988076013098],"type":"Point"}
}