{
  "type": "Feature",
  "properties": {
    "date:inception_lower": "1993-01-01",
    "date:inception_upper": "1993-01-01",
    "iso:country": "GB",
    "wof:name": "SP10 2EY",
    "wof:placetype": "postalcode"
  },
  "geometry": {"coordinates":[-1.471508,51.199881],"type":"Point"}
}
