{
  "type": "Feature",
  "properties": {
    "date:inception_lower": "1980-01-01",
    "date:inception_upper": "1980-01-01",
    "iso:country": "GB",
    "wof:name": "NG19 6TA",
    "wof:placetype": "postalcode"
  },
  "geometry": {"coordinates":[-1.214856,53.14816],"type":"Point"}
}
