{
  "type": "Feature",
  "properties": {
    "iso:country": "GB",
    "wof:name": "NG19 6TA",
    "wof:placetype": "postalcode"
  },
  "geometry": {"coordinates":[-1.214856,53.14816],"type":"Point"}
}
