{
  "type": "Feature",
  "properties": {
    "iso:country":"GB",
    "wof:name":"NG19 6TA",
    "wof:placetype":"postalcode"
},
  "geometry": {"coordinates":[-1.21477030413906,53.14806000360011],"type":"Point"}
}