{
  "type": "Feature",
  "properties": {
    "iso:country":"GB",
    "wof:name":"NG8 3NY",
    "wof:placetype":"postalcode"
},
  "geometry": {"coordinates":[-1.19239456433032,52.96248756564781],"type":"Point"}
}