{
  "type": "Feature",
  "properties": {
    "iso:country":"GB",
    "wof:name":"IP8 3HT",
    "wof:placetype":"postalcode"
},
  "geometry": {"coordinates":[1.08548712951757,52.03635672504995],"type":"Point"}
}