{
  "type": "Feature",
  "properties": {
    "date:inception_lower":"1999-06-01",
    "date:inception_upper":"1999-06-30",
    "iso:country":"GB",
    "wof:name":"NP25 3PN",
    "wof:placetype":"postalcode"
},
  "geometry": {"coordinates":[-2.704732,51.806468],"type":"Point"}
}