{
  "type": "Feature",
  "properties": {
    "iso:country":"GB",
    "wof:name":"NP25 3PN",
    "wof:placetype":"postalcode"
},
  "geometry": {"coordinates":[-2.70473234094747,51.80646754540762],"type":"Point"}
}