{
  "type": "Feature",
  "properties": {
    "iso:country": "GB",
    "wof:name": "NP25 3PN",
    "wof:placetype": "postalcode"
  },
  "geometry": {"coordinates":[-2.704732,51.806468],"type":"Point"}
}
