{
  "type": "Feature",
  "properties": {
    "date:inception_lower": "2018-08-01",
    "date:inception_upper": "2018-08-01",
    "iso:country": "GB",
    "wof:name": "TR8 5FP",
    "wof:placetype": "postalcode"
  },
  "geometry": {"coordinates":[-5.138022,50.387151],"type":"Point"}
}
