{
  "type": "Feature",
  "properties": {
    "iso:country":"GB",
    "wof:name":"G11 7RB",
    "wof:placetype":"postalcode"
},
  "geometry": {"coordinates":[-4.31902407145555,55.87343317033565],"type":"Point"}
}