{
  "type": "Feature",
  "properties": {
    "iso:country":"GB",
    "wof:name":"CB4 2AA",
    "wof:placetype":"postalcode"
},
  "geometry": {"coordinates":[0.12810225585481,52.2200055525218],"type":"Point"}
}