{
  "type": "Feature",
  "properties": {
    "date:inception_lower": "1992-10-01",
    "date:inception_upper": "1992-10-01",
    "iso:country": "GB",
    "wof:name": "DG2 8RH",
    "wof:placetype": "postalcode"
  },
  "geometry": {"coordinates":[-3.833212,55.037174],"type":"Point"}
}
