{
  "type": "Feature",
  "properties": {
    "iso:country":"GB",
    "wof:name":"DG2 8RH",
    "wof:placetype":"postalcode"
},
  "geometry": {"coordinates":[-3.83321220745582,55.03717376591683],"type":"Point"}
}