{
  "type": "Feature",
  "properties": {
    "iso:country":"GB",
    "wof:name":"BN1 1BN",
    "wof:placetype":"postalcode"
},
  "geometry": {"coordinates":[-0.13959439289979,50.82283364667786],"type":"Point"}
}