{
  "type": "Feature",
  "properties": {
    "iso:country":"GB",
    "wof:name":"WC1A 2HR",
    "wof:placetype":"postalcode"
},
  "geometry": {"coordinates":[-0.12581220816295,51.51747500319595],"type":"Point"}
}