{
  "type": "Feature",
  "properties": {
    "date:inception_lower": "1982-03-01",
    "date:inception_upper": "1982-03-01",
    "iso:country": "GB",
    "wof:name": "BD9 6NW",
    "wof:placetype": "postalcode"
  },
  "geometry": {"coordinates":[-1.815459,53.815191],"type":"Point"}
}
