{
  "type": "Feature",
  "properties": {
    "iso:country": "GB",
    "wof:name": "BD9 6NW",
    "wof:placetype": "postalcode"
  },
  "geometry": {"coordinates":[-1.815459,53.815191],"type":"Point"}
}
