{
  "type": "Feature",
  "properties": {
    "iso:country":"GB",
    "wof:name":"EN5 1QJ",
    "wof:placetype":"postalcode"
},
  "geometry": {"coordinates":[-0.17620814551718,51.64924327789171],"type":"Point"}
}