{
  "type": "Feature",
  "properties": {
    "date:inception_lower": "1980-01-01",
    "date:inception_upper": "1980-01-01",
    "iso:country": "GB",
    "wof:name": "SG2 7LG",
    "wof:placetype": "postalcode"
  },
  "geometry": {"coordinates":[-0.109788,51.895865],"type":"Point"}
}
