{
  "type": "Feature",
  "properties": {
    "iso:country":"GB",
    "wof:name":"SG2 7LG",
    "wof:placetype":"postalcode"
},
  "geometry": {"coordinates":[-0.10978774458975,51.8958646243663],"type":"Point"}
}