{
  "type": "Feature",
  "properties": {
    "iso:country":"GB",
    "wof:name":"N1 8BF",
    "wof:placetype":"postalcode"
},
  "geometry": {"coordinates":[-0.09241637034525,51.53816800968367],"type":"Point"}
}