{
  "type": "Feature",
  "properties": {
    "iso:country":"GB",
    "wof:name":"CW5 6EN",
    "wof:placetype":"postalcode"
},
  "geometry": {"coordinates":[-2.48205436829599,53.07144721085847],"type":"Point"}
}