{
  "type": "Feature",
  "properties": {
    "date:inception_lower":"1980-01-01",
    "date:inception_upper":"1980-01-31",
    "iso:country":"GB",
    "wof:name":"BB3 1HY",
    "wof:placetype":"postalcode"
},
  "geometry": {"coordinates":[-2.480847,53.703706],"type":"Point"}
}