{
  "type": "Feature",
  "properties": {
    "iso:country":"GB",
    "wof:name":"BB3 1HY",
    "wof:placetype":"postalcode"
},
  "geometry": {"coordinates":[-2.48084699438553,53.70370595812857],"type":"Point"}
}