{
  "type": "Feature",
  "properties": {
    "date:inception_lower": "1980-01-01",
    "date:inception_upper": "1980-01-01",
    "iso:country": "GB",
    "wof:name": "SW11 1TQ",
    "wof:placetype": "postalcode"
  },
  "geometry": {"coordinates":[-0.177008,51.460155],"type":"Point"}
}
