{
  "type": "Feature",
  "properties": {
    "iso:country":"GB",
    "wof:name":"SW11 1TQ",
    "wof:placetype":"postalcode"
},
  "geometry": {"coordinates":[-0.1770332751333,51.46015475074282],"type":"Point"}
}