{
  "type": "Feature",
  "properties": {
    "date:inception_lower": "1980-01-01",
    "date:inception_upper": "1980-01-01",
    "iso:country": "GB",
    "wof:name": "IP22 2EN",
    "wof:placetype": "postalcode"
  },
  "geometry": {"coordinates":[1.098698,52.436495],"type":"Point"}
}
