{
  "type": "Feature",
  "properties": {
    "iso:country":"GB",
    "wof:name":"IP22 2EN",
    "wof:placetype":"postalcode"
},
  "geometry": {"coordinates":[1.09869788528386,52.43649540994917],"type":"Point"}
}