{
  "type": "Feature",
  "properties": {
    "iso:country":"GB",
    "wof:name":"SG18 0LY",
    "wof:placetype":"postalcode"
},
  "geometry": {"coordinates":[-0.26621980470217,52.09002137024132],"type":"Point"}
}