{
  "type": "Feature",
  "properties": {
    "date:inception_lower": "1980-01-01",
    "date:inception_upper": "1980-01-01",
    "iso:country": "GB",
    "wof:name": "SG18 0LY",
    "wof:placetype": "postalcode"
  },
  "geometry": {"coordinates":[-0.26622,52.090021],"type":"Point"}
}
