{
  "type": "Feature",
  "properties": {
    "iso:country":"GB",
    "wof:name":"NN16 8DP",
    "wof:placetype":"postalcode"
},
  "geometry": {"coordinates":[-0.72932414819993,52.4013781400759],"type":"Point"}
}