{
  "type": "Feature",
  "properties": {
    "iso:country": "GB",
    "wof:name": "SN7 7NU",
    "wof:placetype": "postalcode"
  },
  "geometry": {"coordinates":[-1.576464,51.624678],"type":"Point"}
}
