{
  "type": "Feature",
  "properties": {
    "date:inception_lower": "2002-06-01",
    "date:inception_upper": "2002-06-01",
    "iso:country": "GB",
    "wof:name": "SA7 0EP",
    "wof:placetype": "postalcode"
  },
  "geometry": {"coordinates":[-3.903861,51.667357],"type":"Point"}
}
