{
  "type": "Feature",
  "properties": {
    "iso:country":"GB",
    "wof:name":"NE33 1NA",
    "wof:placetype":"postalcode"
},
  "geometry": {"coordinates":[-1.43163918667374,54.99794974998008],"type":"Point"}
}