{
  "type": "Feature",
  "properties": {
    "iso:country": "GB",
    "wof:name": "NE33 1NA",
    "wof:placetype": "postalcode"
  },
  "geometry": {"coordinates":[-1.431498,54.997813],"type":"Point"}
}
