{
  "type": "Feature",
  "properties": {
    "date:inception_lower":"2005-10-01",
    "date:inception_upper":"2005-10-31",
    "iso:country":"GB",
    "wof:name":"S41 7GE",
    "wof:placetype":"postalcode"
},
  "geometry": {"coordinates":[-1.419615,53.249749],"type":"Point"}
}