{
  "type": "Feature",
  "properties": {
    "iso:country":"GB",
    "wof:name":"S41 7GE",
    "wof:placetype":"postalcode"
},
  "geometry": {"coordinates":[-1.4196153259852,53.24974888368693],"type":"Point"}
}