{
  "type": "Feature",
  "properties": {
    "iso:country": "GB",
    "wof:name": "S41 7GE",
    "wof:placetype": "postalcode"
  },
  "geometry": {"coordinates":[-1.419615,53.249749],"type":"Point"}
}
