{
  "type": "Feature",
  "properties": {
    "iso:country":"GB",
    "wof:name":"HD7 5XD",
    "wof:placetype":"postalcode"
},
  "geometry": {"coordinates":[-1.898954254484,53.62232495508663],"type":"Point"}
}