{
  "type": "Feature",
  "properties": {
    "iso:country": "GB",
    "wof:name": "EX2 7PZ",
    "wof:placetype": "postalcode"
  },
  "geometry": {"coordinates":[-3.475577,50.714601],"type":"Point"}
}
