{
  "type": "Feature",
  "properties": {
    "date:inception_lower":"1980-01-01",
    "date:inception_upper":"1980-01-31",
    "iso:country":"GB",
    "wof:name":"SW14 7AE",
    "wof:placetype":"postalcode"
},
  "geometry": {"coordinates":[-0.271703,51.461094],"type":"Point"}
}