{
  "type": "Feature",
  "properties": {
    "iso:country":"GB",
    "wof:name":"KT5 9BH",
    "wof:placetype":"postalcode"
},
  "geometry": {"coordinates":[-0.2872698340803,51.38324072131713],"type":"Point"}
}