{
  "type": "Feature",
  "properties": {
    "iso:country":"GB",
    "wof:name":"B76 1AW",
    "wof:placetype":"postalcode"
},
  "geometry": {"coordinates":[-1.79033898589393,52.54302107893649],"type":"Point"}
}