{
  "type": "Feature",
  "properties": {
    "date:inception_lower":"1991-09-01",
    "date:inception_upper":"1991-09-30",
    "iso:country":"GB",
    "wof:name":"SG18 9ET",
    "wof:placetype":"postalcode"
},
  "geometry": {"coordinates":[-0.280533,52.105364],"type":"Point"}
}