{
  "type": "Feature",
  "properties": {
    "iso:country":"GB",
    "wof:name":"SG18 9ET",
    "wof:placetype":"postalcode"
},
  "geometry": {"coordinates":[-0.28053346965932,52.10536378370619],"type":"Point"}
}