{
  "type": "Feature",
  "properties": {
    "iso:country": "GB",
    "wof:name": "EX34 7AF",
    "wof:placetype": "postalcode"
  },
  "geometry": {"coordinates":[-4.191998,51.171475],"type":"Point"}
}
