{
  "type": "Feature",
  "properties": {
    "iso:country":"GB",
    "wof:name":"AL1 1PU",
    "wof:placetype":"postalcode"
},
  "geometry": {"coordinates":[-0.33222159022607,51.74682434214424],"type":"Point"}
}