{
  "type": "Feature",
  "properties": {
    "iso:country":"GB",
    "wof:name":"CO15 3DB",
    "wof:placetype":"postalcode"
},
  "geometry": {"coordinates":[1.1462312354508,51.79485044496445],"type":"Point"}
}