{
  "type": "Feature",
  "properties": {
    "iso:country": "GB",
    "wof:name": "CO15 3DB",
    "wof:placetype": "postalcode"
  },
  "geometry": {"coordinates":[1.146231,51.79485],"type":"Point"}
}
