{
  "type": "Feature",
  "properties": {
    "iso:country":"GB",
    "wof:name":"PO12 2SS",
    "wof:placetype":"postalcode"
},
  "geometry": {"coordinates":[-1.16474080439098,50.7928854205978],"type":"Point"}
}