{
  "type": "Feature",
  "properties": {
    "date:inception_lower": "1980-01-01",
    "date:inception_upper": "1980-01-01",
    "iso:country": "GB",
    "wof:name": "DA2 6HY",
    "wof:placetype": "postalcode"
  },
  "geometry": {"coordinates":[0.241141,51.43626],"type":"Point"}
}
