{
  "type": "Feature",
  "properties": {
    "iso:country": "GB",
    "wof:name": "DA2 6HY",
    "wof:placetype": "postalcode"
  },
  "geometry": {"coordinates":[0.241141,51.43626],"type":"Point"}
}
