{
  "type": "Feature",
  "properties": {
    "iso:country":"GB",
    "wof:name":"PL26 7LG",
    "wof:placetype":"postalcode"
},
  "geometry": {"coordinates":[-4.86443526705166,50.3309870906423],"type":"Point"}
}