{
  "type": "Feature",
  "properties": {
    "date:inception_lower": "1980-01-01",
    "date:inception_upper": "1980-01-01",
    "iso:country": "GB",
    "wof:name": "PL26 7LG",
    "wof:placetype": "postalcode"
  },
  "geometry": {"coordinates":[-4.865519,50.332379],"type":"Point"}
}
