{
  "type": "Feature",
  "properties": {
    "date:inception_lower":"1980-01-01",
    "date:inception_upper":"1980-01-31",
    "iso:country":"GB",
    "wof:name":"FK8 2DX",
    "wof:placetype":"postalcode"
},
  "geometry": {"coordinates":[-3.935476,56.116322],"type":"Point"}
}