{
  "type": "Feature",
  "properties": {
    "iso:country":"GB",
    "wof:name":"DL5 6NZ",
    "wof:placetype":"postalcode"
},
  "geometry": {"coordinates":[-1.6277665336841,54.60522398496805],"type":"Point"}
}