{
  "type": "Feature",
  "properties": {
    "iso:country":"GB",
    "wof:name":"WA3 5DJ",
    "wof:placetype":"postalcode"
},
  "geometry": {"coordinates":[-2.51691440638642,53.4512604035303],"type":"Point"}
}