{
  "type": "Feature",
  "properties": {
    "iso:country": "GB",
    "wof:name": "CV23 0RE",
    "wof:placetype": "postalcode"
  },
  "geometry": {"coordinates":[-1.318611,52.444594],"type":"Point"}
}
