{
  "type": "Feature",
  "properties": {
    "iso:country":"GB",
    "wof:name":"BN3 4BE",
    "wof:placetype":"postalcode"
},
  "geometry": {"coordinates":[-0.19472166611116,50.83141605416854],"type":"Point"}
}