{
  "type": "Feature",
  "properties": {
    "iso:country":"GB",
    "wof:name":"EX13 7TR",
    "wof:placetype":"postalcode"
},
  "geometry": {"coordinates":[-3.03646217594163,50.83419868235373],"type":"Point"}
}