{
  "type": "Feature",
  "properties": {
    "iso:country": "GB",
    "wof:name": "IP18 6RE",
    "wof:placetype": "postalcode"
  },
  "geometry": {"coordinates":[1.670366,52.337211],"type":"Point"}
}
