{
  "type": "Feature",
  "properties": {
    "date:inception_lower": "2006-10-01",
    "date:inception_upper": "2006-10-01",
    "iso:country": "GB",
    "wof:name": "KA19 8HE",
    "wof:placetype": "postalcode"
  },
  "geometry": {"coordinates":[-4.765113,55.320844],"type":"Point"}
}
