{
  "type": "Feature",
  "properties": {
    "iso:country":"GB",
    "wof:name":"KA19 8HE",
    "wof:placetype":"postalcode"
},
  "geometry": {"coordinates":[-4.76511283139491,55.32084376399556],"type":"Point"}
}