{
  "type": "Feature",
  "properties": {
    "iso:country":"GB",
    "wof:name":"MK11 1HG",
    "wof:placetype":"postalcode"
},
  "geometry": {"coordinates":[-0.84713468591636,52.05142295070616],"type":"Point"}
}