{
  "type": "Feature",
  "properties": {
    "date:inception_lower": "1980-01-01",
    "date:inception_upper": "1980-01-01",
    "iso:country": "GB",
    "wof:name": "MK11 1HG",
    "wof:placetype": "postalcode"
  },
  "geometry": {"coordinates":[-0.847135,52.051423],"type":"Point"}
}
