{
  "type": "Feature",
  "properties": {
    "iso:country":"GB",
    "wof:name":"G33 6DU",
    "wof:placetype":"postalcode"
},
  "geometry": {"coordinates":[-4.14739229167095,55.89324660834774],"type":"Point"}
}