{
  "type": "Feature",
  "properties": {
    "iso:country": "GB",
    "wof:name": "OX7 3BG",
    "wof:placetype": "postalcode"
  },
  "geometry": {"coordinates":[-1.525633,51.895521],"type":"Point"}
}
