{
  "type": "Feature",
  "properties": {
    "date:inception_lower": "2007-08-01",
    "date:inception_upper": "2007-08-01",
    "iso:country": "GB",
    "wof:name": "OX7 3BG",
    "wof:placetype": "postalcode"
  },
  "geometry": {"coordinates":[-1.525633,51.895521],"type":"Point"}
}
