{
  "type": "Feature",
  "properties": {
    "iso:country":"GB",
    "wof:name":"OX7 3BG",
    "wof:placetype":"postalcode"
},
  "geometry": {"coordinates":[-1.52563260502533,51.89552104610966],"type":"Point"}
}