{
  "type": "Feature",
  "properties": {
    "iso:country":"GB",
    "wof:name":"NG8 2BY",
    "wof:placetype":"postalcode"
},
  "geometry": {"coordinates":[-1.22597323249232,52.95711945007581],"type":"Point"}
}