{
  "type": "Feature",
  "properties": {
    "date:inception_lower": "1985-04-01",
    "date:inception_upper": "1985-04-01",
    "iso:country": "GB",
    "wof:name": "NG8 2BY",
    "wof:placetype": "postalcode"
  },
  "geometry": {"coordinates":[-1.225973,52.957119],"type":"Point"}
}
