{
  "type": "Feature",
  "properties": {
    "iso:country":"GB",
    "wof:name":"SW19 4RX",
    "wof:placetype":"postalcode"
},
  "geometry": {"coordinates":[-0.21388652219758,51.42360084964942],"type":"Point"}
}