{
  "type": "Feature",
  "properties": {
    "iso:country":"GB",
    "wof:name":"PE31 8AT",
    "wof:placetype":"postalcode"
},
  "geometry": {"coordinates":[0.63743473256827,52.96491696185256],"type":"Point"}
}