{
  "type": "Feature",
  "properties": {
    "iso:country": "GB",
    "wof:name": "PR4 0LU",
    "wof:placetype": "postalcode"
  },
  "geometry": {"coordinates":[-2.751823,53.789848],"type":"Point"}
}
