{
  "type": "Feature",
  "properties": {
    "iso:country": "GB",
    "wof:name": "NE29 8DU",
    "wof:placetype": "postalcode"
  },
  "geometry": {"coordinates":[-1.487213,55.022244],"type":"Point"}
}
