{
  "type": "Feature",
  "properties": {
    "iso:country":"GB",
    "wof:name":"NE29 8DU",
    "wof:placetype":"postalcode"
},
  "geometry": {"coordinates":[-1.48721267420829,55.02224377842725],"type":"Point"}
}