{
  "type": "Feature",
  "properties": {
    "iso:country":"GB",
    "wof:name":"ME19 5RD",
    "wof:placetype":"postalcode"
},
  "geometry": {"coordinates":[0.43127792396972,51.30454627325233],"type":"Point"}
}