{
  "type": "Feature",
  "properties": {
    "iso:country": "GB",
    "wof:name": "SK17 7PT",
    "wof:placetype": "postalcode"
  },
  "geometry": {"coordinates":[-1.902582,53.259795],"type":"Point"}
}
