{
  "type": "Feature",
  "properties": {
    "iso:country":"GB",
    "wof:name":"SK17 7PT",
    "wof:placetype":"postalcode"
},
  "geometry": {"coordinates":[-1.90258174799566,53.25979484558618],"type":"Point"}
}