{
  "type": "Feature",
  "properties": {
    "iso:country": "GB",
    "wof:name": "NN11 1SH",
    "wof:placetype": "postalcode"
  },
  "geometry": {"coordinates":[-1.158475,52.259962],"type":"Point"}
}
