{
  "type": "Feature",
  "properties": {
    "date:inception_lower":"1980-01-01",
    "date:inception_upper":"1980-01-31",
    "iso:country":"GB",
    "wof:name":"CM14 5HP",
    "wof:placetype":"postalcode"
},
  "geometry": {"coordinates":[0.298314,51.611596],"type":"Point"}
}