{
  "type": "Feature",
  "properties": {
    "iso:country": "GB",
    "wof:name": "DD4 6JD",
    "wof:placetype": "postalcode"
  },
  "geometry": {"coordinates":[-2.947768,56.467312],"type":"Point"}
}
