{
  "type": "Feature",
  "properties": {
    "date:inception_lower": "1980-01-01",
    "date:inception_upper": "1980-01-01",
    "iso:country": "GB",
    "wof:name": "DD4 6JD",
    "wof:placetype": "postalcode"
  },
  "geometry": {"coordinates":[-2.947768,56.467312],"type":"Point"}
}
