{
  "type": "Feature",
  "properties": {
    "iso:country":"GB",
    "wof:name":"CW9 6BW",
    "wof:placetype":"postalcode"
},
  "geometry": {"coordinates":[-2.55806477776017,53.29009613041944],"type":"Point"}
}