{
  "type": "Feature",
  "properties": {
    "date:inception_lower": "1980-01-01",
    "date:inception_upper": "1980-01-01",
    "iso:country": "GB",
    "wof:name": "SN2 2AA",
    "wof:placetype": "postalcode"
  },
  "geometry": {"coordinates":[-1.799765,51.562898],"type":"Point"}
}
