{
  "type": "Feature",
  "properties": {
    "iso:country":"GB",
    "wof:name":"SE9 6PY",
    "wof:placetype":"postalcode"
},
  "geometry": {"coordinates":[0.04669793858284,51.45269422697785],"type":"Point"}
}