{
  "type": "Feature",
  "properties": {
    "date:inception_lower":"1980-01-01",
    "date:inception_upper":"1980-01-31",
    "iso:country":"GB",
    "wof:name":"SE9 6PY",
    "wof:placetype":"postalcode"
},
  "geometry": {"coordinates":[0.046698,51.452694],"type":"Point"}
}