{
  "type": "Feature",
  "properties": {
    "iso:country": "GB",
    "wof:name": "NG25 0EW",
    "wof:placetype": "postalcode"
  },
  "geometry": {"coordinates":[-0.957012,53.080711],"type":"Point"}
}
