{
  "type": "Feature",
  "properties": {
    "iso:country":"GB",
    "wof:name":"NG25 0EW",
    "wof:placetype":"postalcode"
},
  "geometry": {"coordinates":[-0.95701171634486,53.08071108311155],"type":"Point"}
}