{
  "type": "Feature",
  "properties": {
    "iso:country": "GB",
    "wof:name": "WD18 0EJ",
    "wof:placetype": "postalcode"
  },
  "geometry": {"coordinates":[-0.400034,51.652344],"type":"Point"}
}
