{
  "type": "Feature",
  "properties": {
    "iso:country":"GB",
    "wof:name":"WD18 0EJ",
    "wof:placetype":"postalcode"
},
  "geometry": {"coordinates":[-0.40003412788255,51.65234433390335],"type":"Point"}
}