{
  "type": "Feature",
  "properties": {
    "iso:country":"GB",
    "wof:name":"G74 3EJ",
    "wof:placetype":"postalcode"
},
  "geometry": {"coordinates":[-4.16370676314723,55.7702304538906],"type":"Point"}
}