{
  "type": "Feature",
  "properties": {
    "iso:country":"GB",
    "wof:name":"G41 5NW",
    "wof:placetype":"postalcode"
},
  "geometry": {"coordinates":[-4.31120780855725,55.8427797833701],"type":"Point"}
}