{
  "type": "Feature",
  "properties": {
    "iso:country": "GB",
    "wof:name": "WD23 2HT",
    "wof:placetype": "postalcode"
  },
  "geometry": {"coordinates":[-0.383545,51.656273],"type":"Point"}
}
