{
  "type": "Feature",
  "properties": {
    "iso:country":"GB",
    "wof:name":"WD23 2HT",
    "wof:placetype":"postalcode"
},
  "geometry": {"coordinates":[-0.38354497571729,51.65627285193636],"type":"Point"}
}