{
  "type": "Feature",
  "properties": {
    "date:inception_lower": "2000-10-01",
    "date:inception_upper": "2000-10-01",
    "iso:country": "GB",
    "wof:name": "WD23 2HT",
    "wof:placetype": "postalcode"
  },
  "geometry": {"coordinates":[-0.383521,51.656278],"type":"Point"}
}
