{
  "type": "Feature",
  "properties": {
    "iso:country":"GB",
    "wof:name":"E14 6PG",
    "wof:placetype":"postalcode"
},
  "geometry": {"coordinates":[-0.01433599851034,51.51421087300758],"type":"Point"}
}