{
  "type": "Feature",
  "properties": {
    "iso:country":"GB",
    "wof:name":"BS15 4JH",
    "wof:placetype":"postalcode"
},
  "geometry": {"coordinates":[-2.48901063797231,51.46210701369694],"type":"Point"}
}