{
  "type": "Feature",
  "properties": {
    "iso:country": "GB",
    "wof:name": "LE13 1BW",
    "wof:placetype": "postalcode"
  },
  "geometry": {"coordinates":[-0.877341,52.764779],"type":"Point"}
}
