{
  "type": "Feature",
  "properties": {
    "iso:country":"GB",
    "wof:name":"LE13 1BW",
    "wof:placetype":"postalcode"
},
  "geometry": {"coordinates":[-0.87734061197584,52.76477864660353],"type":"Point"}
}