{
  "type": "Feature",
  "properties": {
    "iso:country":"GB",
    "wof:name":"LE17 4AB",
    "wof:placetype":"postalcode"
},
  "geometry": {"coordinates":[-1.19855222274568,52.45454025302168],"type":"Point"}
}