{
  "type": "Feature",
  "properties": {
    "iso:country": "GB",
    "wof:name": "OX9 3RY",
    "wof:placetype": "postalcode"
  },
  "geometry": {"coordinates":[-0.966127,51.762435],"type":"Point"}
}
