{
  "type": "Feature",
  "properties": {
    "iso:country":"GB",
    "wof:name":"OX9 3RY",
    "wof:placetype":"postalcode"
},
  "geometry": {"coordinates":[-0.96612655835791,51.76243518876213],"type":"Point"}
}