{
  "type": "Feature",
  "properties": {
    "iso:country":"GB",
    "wof:name":"NE1 3DX",
    "wof:placetype":"postalcode"
},
  "geometry": {"coordinates":[-1.59930666422459,54.97098436605568],"type":"Point"}
}