{
  "type": "Feature",
  "properties": {
    "iso:country":"GB",
    "wof:name":"PL5 1BA",
    "wof:placetype":"postalcode"
},
  "geometry": {"coordinates":[-4.17999674294078,50.39731806017025],"type":"Point"}
}