{
  "type": "Feature",
  "properties": {
    "date:inception_lower": "1980-01-01",
    "date:inception_upper": "1980-01-01",
    "iso:country": "GB",
    "wof:name": "TQ14 9EX",
    "wof:placetype": "postalcode"
  },
  "geometry": {"coordinates":[-3.509774,50.555825],"type":"Point"}
}
