{
  "type": "Feature",
  "properties": {
    "iso:country":"GB",
    "wof:name":"BS5 7SR",
    "wof:placetype":"postalcode"
},
  "geometry": {"coordinates":[-2.53332608636108,51.46540247522729],"type":"Point"}
}