{
  "type": "Feature",
  "properties": {
    "iso:country":"GB",
    "wof:name":"M27 6DP",
    "wof:placetype":"postalcode"
},
  "geometry": {"coordinates":[-2.3376980248335,53.51618732701844],"type":"Point"}
}