{
  "type": "Feature",
  "properties": {
    "date:inception_lower": "2023-10-01",
    "date:inception_upper": "2023-10-01",
    "iso:country": "GB",
    "wof:name": "BR1 1LY",
    "wof:placetype": "postalcode"
  },
  "geometry": {"coordinates":[0.018475,51.401574],"type":"Point"}
}
