{
  "type": "Feature",
  "properties": {
    "iso:country":"GB",
    "wof:name":"BB5 4JS",
    "wof:placetype":"postalcode"
},
  "geometry": {"coordinates":[-2.39416472819121,53.75654028175853],"type":"Point"}
}