{
  "type": "Feature",
  "properties": {
    "iso:country": "GB",
    "wof:name": "G5 0QE",
    "wof:placetype": "postalcode"
  },
  "geometry": {"coordinates":[-4.239068,55.847988],"type":"Point"}
}
