{
  "type": "Feature",
  "properties": {
    "iso:country":"GB",
    "wof:name":"DT6 4QL",
    "wof:placetype":"postalcode"
},
  "geometry": {"coordinates":[-2.72367793735965,50.70631665757067],"type":"Point"}
}