{
  "type": "Feature",
  "properties": {
    "date:inception_lower": "1980-01-01",
    "date:inception_upper": "1980-01-01",
    "iso:country": "GB",
    "wof:name": "CM12 9XG",
    "wof:placetype": "postalcode"
  },
  "geometry": {"coordinates":[0.407762,51.629681],"type":"Point"}
}
