{
  "type": "Feature",
  "properties": {
    "iso:country": "GB",
    "wof:name": "RG24 8PF",
    "wof:placetype": "postalcode"
  },
  "geometry": {"coordinates":[-1.071703,51.277306],"type":"Point"}
}
