{
  "type": "Feature",
  "properties": {
    "iso:country": "GB",
    "wof:name": "DT3 5PX",
    "wof:placetype": "postalcode"
  },
  "geometry": {"coordinates":[-2.446298,50.659417],"type":"Point"}
}
