{
  "type": "Feature",
  "properties": {
    "date:inception_lower": "1980-01-01",
    "date:inception_upper": "1980-01-01",
    "iso:country": "GB",
    "wof:name": "EH33 1DT",
    "wof:placetype": "postalcode"
  },
  "geometry": {"coordinates":[-2.952206,55.954522],"type":"Point"}
}
