{
  "type": "Feature",
  "properties": {
    "iso:country":"GB",
    "wof:name":"EH33 1DT",
    "wof:placetype":"postalcode"
},
  "geometry": {"coordinates":[-2.952205812757,55.95452241866945],"type":"Point"}
}