{
  "type": "Feature",
  "properties": {
    "iso:country": "GB",
    "wof:name": "CW12 1LE",
    "wof:placetype": "postalcode"
  },
  "geometry": {"coordinates":[-2.22097,53.164779],"type":"Point"}
}
