{
  "type": "Feature",
  "properties": {
    "iso:country":"GB",
    "wof:name":"CW12 1LE",
    "wof:placetype":"postalcode"
},
  "geometry": {"coordinates":[-2.22097030454574,53.16477873062347],"type":"Point"}
}