{
  "type": "Feature",
  "properties": {
    "iso:country":"GB",
    "wof:name":"DL17 0JN",
    "wof:placetype":"postalcode"
},
  "geometry": {"coordinates":[-1.56348988447087,54.66173404228138],"type":"Point"}
}