{
  "type": "Feature",
  "properties": {
    "date:inception_lower": "1980-01-01",
    "date:inception_upper": "1980-01-01",
    "iso:country": "GB",
    "wof:name": "DL17 0JN",
    "wof:placetype": "postalcode"
  },
  "geometry": {"coordinates":[-1.56349,54.661734],"type":"Point"}
}
