{
  "type": "Feature",
  "properties": {
    "iso:country": "GB",
    "wof:name": "DL17 0JN",
    "wof:placetype": "postalcode"
  },
  "geometry": {"coordinates":[-1.56349,54.661734],"type":"Point"}
}
