{
  "type": "Feature",
  "properties": {
    "date:inception_lower": "1992-08-01",
    "date:inception_upper": "1992-08-01",
    "iso:country": "GB",
    "wof:name": "DE22 2FX",
    "wof:placetype": "postalcode"
  },
  "geometry": {"coordinates":[-1.489161,52.955404],"type":"Point"}
}
