{
  "type": "Feature",
  "properties": {
    "date:inception_lower": "2003-06-01",
    "date:inception_upper": "2003-06-01",
    "iso:country": "GB",
    "wof:name": "NG8 1GT",
    "wof:placetype": "postalcode"
  },
  "geometry": {"coordinates":[-1.212422,52.957381],"type":"Point"}
}
