{
  "type": "Feature",
  "properties": {
    "iso:country":"GB",
    "wof:name":"CB8 9XB",
    "wof:placetype":"postalcode"
},
  "geometry": {"coordinates":[0.38185830541264,52.20307886352457],"type":"Point"}
}