{
  "type": "Feature",
  "properties": {
    "date:inception_lower": "1980-01-01",
    "date:inception_upper": "1980-01-01",
    "iso:country": "GB",
    "wof:name": "CB8 9XB",
    "wof:placetype": "postalcode"
  },
  "geometry": {"coordinates":[0.381887,52.203094],"type":"Point"}
}
