{
  "type": "Feature",
  "properties": {
    "iso:country":"GB",
    "wof:name":"RG1 7BS",
    "wof:placetype":"postalcode"
},
  "geometry": {"coordinates":[-0.97701830196621,51.45933307146758],"type":"Point"}
}