{
  "type": "Feature",
  "properties": {
    "iso:country":"GB",
    "wof:name":"L15 8LF",
    "wof:placetype":"postalcode"
},
  "geometry": {"coordinates":[-2.91192447083402,53.40009698993382],"type":"Point"}
}