{
  "type": "Feature",
  "properties": {
    "iso:country": "GB",
    "wof:name": "L15 8LF",
    "wof:placetype": "postalcode"
  },
  "geometry": {"coordinates":[-2.911924,53.400097],"type":"Point"}
}
