{
  "type": "Feature",
  "properties": {
    "iso:country":"GB",
    "wof:name":"PO3 6DJ",
    "wof:placetype":"postalcode"
},
  "geometry": {"coordinates":[-1.05532077894571,50.80283323700262],"type":"Point"}
}