{
  "type": "Feature",
  "properties": {
    "iso:country": "GB",
    "wof:name": "PO3 6DJ",
    "wof:placetype": "postalcode"
  },
  "geometry": {"coordinates":[-1.055321,50.802833],"type":"Point"}
}
