{
  "type": "Feature",
  "properties": {
    "date:inception_lower": "1980-01-01",
    "date:inception_upper": "1980-01-01",
    "iso:country": "GB",
    "wof:name": "EH29 9EB",
    "wof:placetype": "postalcode"
  },
  "geometry": {"coordinates":[-3.425476,55.945355],"type":"Point"}
}
