{
  "type": "Feature",
  "properties": {
    "iso:country":"GB",
    "wof:name":"CA1 3HF",
    "wof:placetype":"postalcode"
},
  "geometry": {"coordinates":[-2.89714839471234,54.87320909183845],"type":"Point"}
}