{
  "type": "Feature",
  "properties": {
    "iso:country": "GB",
    "wof:name": "TA11 6PW",
    "wof:placetype": "postalcode"
  },
  "geometry": {"coordinates":[-2.744246,51.051817],"type":"Point"}
}
