{
  "type": "Feature",
  "properties": {
    "date:inception_lower":"1997-12-01",
    "date:inception_upper":"1997-12-31",
    "iso:country":"GB",
    "wof:name":"TA11 6PW",
    "wof:placetype":"postalcode"
},
  "geometry": {"coordinates":[-2.744246,51.051817],"type":"Point"}
}