{
  "type": "Feature",
  "properties": {
    "iso:country":"GB",
    "wof:name":"TA11 6PW",
    "wof:placetype":"postalcode"
},
  "geometry": {"coordinates":[-2.74424565667724,51.05181687965391],"type":"Point"}
}