{
  "type": "Feature",
  "properties": {
    "iso:country":"GB",
    "wof:name":"WA15 7AF",
    "wof:placetype":"postalcode"
},
  "geometry": {"coordinates":[-2.31441264760462,53.38778698865562],"type":"Point"}
}