{
  "type": "Feature",
  "properties": {
    "iso:country": "GB",
    "wof:name": "E14 9EP",
    "wof:placetype": "postalcode"
  },
  "geometry": {"coordinates":[-0.015451,51.496838],"type":"Point"}
}
