{
  "type": "Feature",
  "properties": {
    "iso:country":"GB",
    "wof:name":"SE5 7FD",
    "wof:placetype":"postalcode"
},
  "geometry": {"coordinates":[-0.07728389760705,51.47498182815542],"type":"Point"}
}