{
  "type": "Feature",
  "properties": {
    "date:inception_lower": "1995-07-01",
    "date:inception_upper": "1995-07-01",
    "iso:country": "GB",
    "wof:name": "PR4 0NF",
    "wof:placetype": "postalcode"
  },
  "geometry": {"coordinates":[-2.755619,53.784036],"type":"Point"}
}
