{
  "type": "Feature",
  "properties": {
    "iso:country":"GB",
    "wof:name":"BS31 2QS",
    "wof:placetype":"postalcode"
},
  "geometry": {"coordinates":[-2.50745237517926,51.40783598532116],"type":"Point"}
}