{
  "type": "Feature",
  "properties": {
    "date:inception_lower": "2001-06-01",
    "date:inception_upper": "2001-06-01",
    "iso:country": "GB",
    "wof:name": "N1 9HH",
    "wof:placetype": "postalcode"
  },
  "geometry": {"coordinates":[-0.107583,51.532058],"type":"Point"}
}
