{
  "type": "Feature",
  "properties": {
    "iso:country": "GB",
    "wof:name": "N1 9HH",
    "wof:placetype": "postalcode"
  },
  "geometry": {"coordinates":[-0.107583,51.532058],"type":"Point"}
}
