{
  "type": "Feature",
  "properties": {
    "iso:country":"GB",
    "wof:name":"N1 9HH",
    "wof:placetype":"postalcode"
},
  "geometry": {"coordinates":[-0.10787081457035,51.53234834948304],"type":"Point"}
}