{
  "type": "Feature",
  "properties": {
    "iso:country":"GB",
    "wof:name":"ME7 1RZ",
    "wof:placetype":"postalcode"
},
  "geometry": {"coordinates":[0.55282873242643,51.39540253011353],"type":"Point"}
}