{
  "type": "Feature",
  "properties": {
    "iso:country":"GB",
    "wof:name":"BA21 5PR",
    "wof:placetype":"postalcode"
},
  "geometry": {"coordinates":[-2.62145085863926,50.95373569676249],"type":"Point"}
}