{
  "type": "Feature",
  "properties": {
    "iso:country":"GB",
    "wof:name":"TS19 0RS",
    "wof:placetype":"postalcode"
},
  "geometry": {"coordinates":[-1.33468690996287,54.57368273424066],"type":"Point"}
}