{
  "type": "Feature",
  "properties": {
    "iso:country": "GB",
    "wof:name": "TS19 0RS",
    "wof:placetype": "postalcode"
  },
  "geometry": {"coordinates":[-1.334687,54.573683],"type":"Point"}
}
