{
  "type": "Feature",
  "properties": {
    "iso:country":"GB",
    "wof:name":"TN26 2JA",
    "wof:placetype":"postalcode"
},
  "geometry": {"coordinates":[0.85831713881534,51.06187961540125],"type":"Point"}
}