{
  "type": "Feature",
  "properties": {
    "iso:country": "GB",
    "wof:name": "TN26 2JA",
    "wof:placetype": "postalcode"
  },
  "geometry": {"coordinates":[0.858317,51.06188],"type":"Point"}
}
