{
  "type": "Feature",
  "properties": {
    "iso:country":"GB",
    "wof:name":"AB51 0EZ",
    "wof:placetype":"postalcode"
},
  "geometry": {"coordinates":[-2.32662490799238,57.33245160362066],"type":"Point"}
}