{
  "type": "Feature",
  "properties": {
    "iso:country":"GB",
    "wof:name":"DG12 5NG",
    "wof:placetype":"postalcode"
},
  "geometry": {"coordinates":[-3.27630011314554,55.0226937220522],"type":"Point"}
}