{
  "type": "Feature",
  "properties": {
    "iso:country":"GB",
    "wof:name":"GL16 8QZ",
    "wof:placetype":"postalcode"
},
  "geometry": {"coordinates":[-2.62182246342825,51.81026207885342],"type":"Point"}
}