{
  "type": "Feature",
  "properties": {
    "iso:country":"GB",
    "wof:name":"BD22 9NF",
    "wof:placetype":"postalcode"
},
  "geometry": {"coordinates":[-1.94942888180264,53.80567774786368],"type":"Point"}
}