{
  "type": "Feature",
  "properties": {
    "date:inception_lower": "2023-04-01",
    "date:inception_upper": "2023-04-01",
    "iso:country": "GB",
    "wof:name": "EX39 1GR",
    "wof:placetype": "postalcode"
  },
  "geometry": {"coordinates":[-4.239922,51.032998],"type":"Point"}
}
