{
  "type": "Feature",
  "properties": {
    "iso:country":"GB",
    "wof:name":"WN2 1YG",
    "wof:placetype":"postalcode"
},
  "geometry": {"coordinates":[-2.58627475559776,53.57378619074963],"type":"Point"}
}