{
  "type": "Feature",
  "properties": {
    "iso:country":"GB",
    "wof:name":"DL13 3BG",
    "wof:placetype":"postalcode"
},
  "geometry": {"coordinates":[-1.91926937855062,54.72172349035111],"type":"Point"}
}