{
  "type": "Feature",
  "properties": {
    "date:inception_lower":"1980-01-01",
    "date:inception_upper":"1980-01-31",
    "iso:country":"GB",
    "wof:name":"DL13 3BG",
    "wof:placetype":"postalcode"
},
  "geometry": {"coordinates":[-1.918828,54.721884],"type":"Point"}
}