{
  "type": "Feature",
  "properties": {
    "iso:country": "GB",
    "wof:name": "DL13 3BG",
    "wof:placetype": "postalcode"
  },
  "geometry": {"coordinates":[-1.918828,54.721884],"type":"Point"}
}
