{
  "type": "Feature",
  "properties": {
    "iso:country":"GB",
    "wof:name":"SK6 7EU",
    "wof:placetype":"postalcode"
},
  "geometry": {"coordinates":[-2.05349995595735,53.37415836452497],"type":"Point"}
}