{
  "type": "Feature",
  "properties": {
    "iso:country":"GB",
    "wof:name":"NN9 6TS",
    "wof:placetype":"postalcode"
},
  "geometry": {"coordinates":[-0.53814434371492,52.34101590430521],"type":"Point"}
}