{
  "type": "Feature",
  "properties": {
    "date:inception_lower":"2004-05-01",
    "date:inception_upper":"2004-05-31",
    "iso:country":"GB",
    "wof:name":"NN9 6TS",
    "wof:placetype":"postalcode"
},
  "geometry": {"coordinates":[-0.538144,52.341016],"type":"Point"}
}