{
  "type": "Feature",
  "properties": {
    "iso:country":"GB",
    "wof:name":"PO21 2NE",
    "wof:placetype":"postalcode"
},
  "geometry": {"coordinates":[-0.68437435785949,50.7856788075278],"type":"Point"}
}