{
  "type": "Feature",
  "properties": {
    "date:inception_lower": "1990-02-01",
    "date:inception_upper": "1990-02-01",
    "iso:country": "GB",
    "wof:name": "PO21 2NE",
    "wof:placetype": "postalcode"
  },
  "geometry": {"coordinates":[-0.684374,50.785679],"type":"Point"}
}
