{
  "type": "Feature",
  "properties": {
    "iso:country":"GB",
    "wof:name":"EH41 3QB",
    "wof:placetype":"postalcode"
},
  "geometry": {"coordinates":[-2.77334173750102,55.95989009851331],"type":"Point"}
}