{
  "type": "Feature",
  "properties": {
    "iso:country": "GB",
    "wof:name": "SK6 1NW",
    "wof:placetype": "postalcode"
  },
  "geometry": {"coordinates":[-2.096308,53.427595],"type":"Point"}
}
