{
  "type": "Feature",
  "properties": {
    "iso:country": "GB",
    "wof:name": "G2 9JZ",
    "wof:placetype": "postalcode"
  },
  "geometry": {"coordinates":[-4.243477,55.868735],"type":"Point"}
}
