{
  "type": "Feature",
  "properties": {
    "iso:country": "GB",
    "wof:name": "LN6 7UE",
    "wof:placetype": "postalcode"
  },
  "geometry": {"coordinates":[-0.556377,53.216977],"type":"Point"}
}
