{
  "type": "Feature",
  "properties": {
    "iso:country":"GB",
    "wof:name":"BH14 0PF",
    "wof:placetype":"postalcode"
},
  "geometry": {"coordinates":[-1.95650766636652,50.72888874003723],"type":"Point"}
}