{
  "type": "Feature",
  "properties": {
    "iso:country":"GB",
    "wof:name":"DL13 3HW",
    "wof:placetype":"postalcode"
},
  "geometry": {"coordinates":[-1.87919421053135,54.73394794751531],"type":"Point"}
}