{
  "type": "Feature",
  "properties": {
    "iso:country":"GB",
    "wof:name":"SK16 4EL",
    "wof:placetype":"postalcode"
},
  "geometry": {"coordinates":[-2.08875749557606,53.48012090649226],"type":"Point"}
}