{
  "type": "Feature",
  "properties": {
    "iso:country":"GB",
    "wof:name":"BH31 6PP",
    "wof:placetype":"postalcode"
},
  "geometry": {"coordinates":[-1.8919426812207,50.87681028131342],"type":"Point"}
}