{
  "type": "Feature",
  "properties": {
    "date:inception_lower":"1991-09-01",
    "date:inception_upper":"1991-09-30",
    "iso:country":"GB",
    "wof:name":"BH31 6PP",
    "wof:placetype":"postalcode"
},
  "geometry": {"coordinates":[-1.891943,50.87681],"type":"Point"}
}