{
  "type": "Feature",
  "properties": {
    "iso:country":"GB",
    "wof:name":"PL4 0FB",
    "wof:placetype":"postalcode"
},
  "geometry": {"coordinates":[-4.12665111834533,50.36489201850879],"type":"Point"}
}