{
  "type": "Feature",
  "properties": {
    "date:inception_lower": "2012-03-01",
    "date:inception_upper": "2012-03-01",
    "iso:country": "GB",
    "wof:name": "PL4 0FB",
    "wof:placetype": "postalcode"
  },
  "geometry": {"coordinates":[-4.12668,50.364878],"type":"Point"}
}
