{
  "type": "Feature",
  "properties": {
    "date:inception_lower":"2012-03-01",
    "date:inception_upper":"2012-03-31",
    "iso:country":"GB",
    "wof:name":"PL4 0FB",
    "wof:placetype":"postalcode"
},
  "geometry": {"coordinates":[-4.126708,50.364868],"type":"Point"}
}