{
  "type": "Feature",
  "properties": {
    "iso:country":"GB",
    "wof:name":"WF7 5JF",
    "wof:placetype":"postalcode"
},
  "geometry": {"coordinates":[-1.36544631354661,53.67148894504647],"type":"Point"}
}