{
  "type": "Feature",
  "properties": {
    "date:inception_lower": "1980-01-01",
    "date:inception_upper": "1980-01-01",
    "iso:country": "GB",
    "wof:name": "WF7 5JF",
    "wof:placetype": "postalcode"
  },
  "geometry": {"coordinates":[-1.365446,53.671489],"type":"Point"}
}
