{
  "type": "Feature",
  "properties": {
    "iso:country": "GB",
    "wof:name": "DH1 2ST",
    "wof:placetype": "postalcode"
  },
  "geometry": {"coordinates":[-1.539422,54.766197],"type":"Point"}
}
