{
  "type": "Feature",
  "properties": {
    "iso:country":"GB",
    "wof:name":"DH1 2ST",
    "wof:placetype":"postalcode"
},
  "geometry": {"coordinates":[-1.53941138646382,54.76618695991814],"type":"Point"}
}