{
  "type": "Feature",
  "properties": {
    "iso:country":"GB",
    "wof:name":"EH54 7ER",
    "wof:placetype":"postalcode"
},
  "geometry": {"coordinates":[-3.55376658023845,55.88605029401467],"type":"Point"}
}