{
  "type": "Feature",
  "properties": {
    "date:inception_lower": "2002-06-01",
    "date:inception_upper": "2002-06-01",
    "iso:country": "GB",
    "wof:name": "EH54 7ER",
    "wof:placetype": "postalcode"
  },
  "geometry": {"coordinates":[-3.55359,55.88577],"type":"Point"}
}
