{
  "type": "Feature",
  "properties": {
    "iso:country":"GB",
    "wof:name":"CT21 5TG",
    "wof:placetype":"postalcode"
},
  "geometry": {"coordinates":[1.1147207516875,51.07764870579556],"type":"Point"}
}