{
  "type": "Feature",
  "properties": {
    "date:inception_lower": "1980-01-01",
    "date:inception_upper": "1980-01-01",
    "iso:country": "GB",
    "wof:name": "CT21 5TG",
    "wof:placetype": "postalcode"
  },
  "geometry": {"coordinates":[1.114721,51.077649],"type":"Point"}
}
