{
  "type": "Feature",
  "properties": {
    "iso:country":"GB",
    "wof:name":"B12 8DP",
    "wof:placetype":"postalcode"
},
  "geometry": {"coordinates":[-1.87628731084115,52.4593737268094],"type":"Point"}
}