{
  "type": "Feature",
  "properties": {
    "iso:country":"GB",
    "wof:name":"N16 9HH",
    "wof:placetype":"postalcode"
},
  "geometry": {"coordinates":[-0.08639182484422,51.55975085627195],"type":"Point"}
}