{
  "type": "Feature",
  "properties": {
    "iso:country": "GB",
    "wof:name": "GL11 4LJ",
    "wof:placetype": "postalcode"
  },
  "geometry": {"coordinates":[-2.353596,51.6805],"type":"Point"}
}
