{
  "type": "Feature",
  "properties": {
    "iso:country":"GB",
    "wof:name":"SE11 6LR",
    "wof:placetype":"postalcode"
},
  "geometry": {"coordinates":[-0.11247103184293,51.49502249391673],"type":"Point"}
}