{
  "type": "Feature",
  "properties": {
    "iso:country":"GB",
    "wof:name":"BB1 2PH",
    "wof:placetype":"postalcode"
},
  "geometry": {"coordinates":[-2.41115313125513,53.71632427325788],"type":"Point"}
}