{
  "type": "Feature",
  "properties": {
    "iso:country":"GB",
    "wof:name":"S42 5DU",
    "wof:placetype":"postalcode"
},
  "geometry": {"coordinates":[-1.374648694153,53.20276995819108],"type":"Point"}
}