{
  "type": "Feature",
  "properties": {
    "iso:country": "GB",
    "wof:name": "S42 5DU",
    "wof:placetype": "postalcode"
  },
  "geometry": {"coordinates":[-1.374617,53.20278],"type":"Point"}
}
