{
  "type": "Feature",
  "properties": {
    "date:inception_lower":"2005-02-01",
    "date:inception_upper":"2005-02-28",
    "iso:country":"GB",
    "wof:name":"S42 5DU",
    "wof:placetype":"postalcode"
},
  "geometry": {"coordinates":[-1.374617,53.20278],"type":"Point"}
}