{
  "type": "Feature",
  "properties": {
    "iso:country":"GB",
    "wof:name":"HX2 6BJ",
    "wof:placetype":"postalcode"
},
  "geometry": {"coordinates":[-1.92896256257885,53.71399865605092],"type":"Point"}
}