{
  "type": "Feature",
  "properties": {
    "date:inception_lower": "2009-06-01",
    "date:inception_upper": "2009-06-01",
    "iso:country": "GB",
    "wof:name": "GU3 1JT",
    "wof:placetype": "postalcode"
  },
  "geometry": {"coordinates":[-0.629334,51.213685],"type":"Point"}
}
