{
  "type": "Feature",
  "properties": {
    "iso:country":"GB",
    "wof:name":"EH16 4SX",
    "wof:placetype":"postalcode"
},
  "geometry": {"coordinates":[-3.14198420597844,55.920561974986],"type":"Point"}
}