{
  "type": "Feature",
  "properties": {
    "iso:country":"GB",
    "wof:name":"BD9 4JR",
    "wof:placetype":"postalcode"
},
  "geometry": {"coordinates":[-1.77361184561168,53.81601802023777],"type":"Point"}
}