{
  "type": "Feature",
  "properties": {
    "date:inception_lower": "1981-06-01",
    "date:inception_upper": "1981-06-01",
    "iso:country": "GB",
    "wof:name": "HP10 9QY",
    "wof:placetype": "postalcode"
  },
  "geometry": {"coordinates":[-0.696355,51.604847],"type":"Point"}
}
