{
  "type": "Feature",
  "properties": {
    "iso:country":"GB",
    "wof:name":"M40 7DY",
    "wof:placetype":"postalcode"
},
  "geometry": {"coordinates":[-2.21449134115207,53.48722378471938],"type":"Point"}
}