{
  "type": "Feature",
  "properties": {
    "iso:country":"GB",
    "wof:name":"LE16 9EU",
    "wof:placetype":"postalcode"
},
  "geometry": {"coordinates":[-0.91886580905052,52.47163537725516],"type":"Point"}
}