{
  "type": "Feature",
  "properties": {
    "iso:country":"GB",
    "wof:name":"HG3 2HJ",
    "wof:placetype":"postalcode"
},
  "geometry": {"coordinates":[-1.59678923596909,54.01523734988038],"type":"Point"}
}