{
  "type": "Feature",
  "properties": {
    "iso:country":"GB",
    "wof:name":"LS6 2LA",
    "wof:placetype":"postalcode"
},
  "geometry": {"coordinates":[-1.55321075395419,53.81483383207925],"type":"Point"}
}