{
  "type": "Feature",
  "properties": {
    "iso:country":"GB",
    "wof:name":"RG10 9NB",
    "wof:placetype":"postalcode"
},
  "geometry": {"coordinates":[-0.87076504805592,51.48372425013755],"type":"Point"}
}