{
  "type": "Feature",
  "properties": {
    "iso:country": "GB",
    "wof:name": "GL51 6DY",
    "wof:placetype": "postalcode"
  },
  "geometry": {"coordinates":[-2.091327,51.892961],"type":"Point"}
}
