{
  "type": "Feature",
  "properties": {
    "iso:country":"GB",
    "wof:name":"G46 6PF",
    "wof:placetype":"postalcode"
},
  "geometry": {"coordinates":[-4.28992956246355,55.79738608351919],"type":"Point"}
}