{
  "type": "Feature",
  "properties": {
    "iso:country":"GB",
    "wof:name":"PE29 1YN",
    "wof:placetype":"postalcode"
},
  "geometry": {"coordinates":[-0.16088138121028,52.33892851215899],"type":"Point"}
}