{
  "type": "Feature",
  "properties": {
    "date:inception_lower": "1988-03-01",
    "date:inception_upper": "1988-03-01",
    "iso:country": "GB",
    "wof:name": "NE35 9LF",
    "wof:placetype": "postalcode"
  },
  "geometry": {"coordinates":[-1.468872,54.954256],"type":"Point"}
}
