{
  "type": "Feature",
  "properties": {
    "iso:country":"GB",
    "wof:name":"IG6 1HU",
    "wof:placetype":"postalcode"
},
  "geometry": {"coordinates":[0.07645542452088,51.58307853420202],"type":"Point"}
}