{
  "type": "Feature",
  "properties": {
    "iso:country": "GB",
    "wof:name": "IG6 1HU",
    "wof:placetype": "postalcode"
  },
  "geometry": {"coordinates":[0.0765,51.583105],"type":"Point"}
}
