{
  "type": "Feature",
  "properties": {
    "iso:country":"GB",
    "wof:name":"CA10 2JZ",
    "wof:placetype":"postalcode"
},
  "geometry": {"coordinates":[-2.76456726327956,54.63606524776662],"type":"Point"}
}