{
  "type": "Feature",
  "properties": {
    "iso:country": "GB",
    "wof:name": "CA10 2JZ",
    "wof:placetype": "postalcode"
  },
  "geometry": {"coordinates":[-2.764567,54.636065],"type":"Point"}
}
