{
  "type": "Feature",
  "properties": {
    "iso:country":"GB",
    "wof:name":"FY6 0NL",
    "wof:placetype":"postalcode"
},
  "geometry": {"coordinates":[-2.9647333273779,53.91825792811519],"type":"Point"}
}