{
  "type": "Feature",
  "properties": {
    "iso:country":"GB",
    "wof:name":"IP30 9TW",
    "wof:placetype":"postalcode"
},
  "geometry": {"coordinates":[0.88199405661854,52.19675586592129],"type":"Point"}
}