{
  "type": "Feature",
  "properties": {
    "iso:country": "GB",
    "wof:name": "DN8 5BX",
    "wof:placetype": "postalcode"
  },
  "geometry": {"coordinates":[-0.955599,53.611665],"type":"Point"}
}
