{
  "type": "Feature",
  "properties": {
    "iso:country":"GB",
    "wof:name":"DN8 5BX",
    "wof:placetype":"postalcode"
},
  "geometry": {"coordinates":[-0.95559875200401,53.61166484793147],"type":"Point"}
}