{
  "type": "Feature",
  "properties": {
    "date:inception_lower":"1980-01-01",
    "date:inception_upper":"1980-01-31",
    "iso:country":"GB",
    "wof:name":"RM17 6ED",
    "wof:placetype":"postalcode"
},
  "geometry": {"coordinates":[0.33258,51.47606],"type":"Point"}
}