{
  "type": "Feature",
  "properties": {
    "iso:country": "GB",
    "wof:name": "RM17 6ED",
    "wof:placetype": "postalcode"
  },
  "geometry": {"coordinates":[0.33258,51.47606],"type":"Point"}
}
