{
  "type": "Feature",
  "properties": {
    "iso:country":"GB",
    "wof:name":"RM17 6ED",
    "wof:placetype":"postalcode"
},
  "geometry": {"coordinates":[0.33258043498685,51.47605977458613],"type":"Point"}
}