{
  "type": "Feature",
  "properties": {
    "iso:country": "GB",
    "wof:name": "WF3 1DL",
    "wof:placetype": "postalcode"
  },
  "geometry": {"coordinates":[-1.582861,53.719523],"type":"Point"}
}
