{
  "type": "Feature",
  "properties": {
    "iso:country":"GB",
    "wof:name":"RM3 9JR",
    "wof:placetype":"postalcode"
},
  "geometry": {"coordinates":[0.23428949670263,51.6037676054354],"type":"Point"}
}