{
  "type": "Feature",
  "properties": {
    "iso:country":"GB",
    "wof:name":"M23 2SL",
    "wof:placetype":"postalcode"
},
  "geometry": {"coordinates":[-2.29023313760077,53.38522359150065],"type":"Point"}
}