{
  "type": "Feature",
  "properties": {
    "iso:country":"GB",
    "wof:name":"DD9 7TN",
    "wof:placetype":"postalcode"
},
  "geometry": {"coordinates":[-2.65213994592712,56.80793136202281],"type":"Point"}
}