{
  "type": "Feature",
  "properties": {
    "date:inception_lower":"1980-01-01",
    "date:inception_upper":"1980-01-31",
    "iso:country":"GB",
    "wof:name":"DD9 7TN",
    "wof:placetype":"postalcode"
},
  "geometry": {"coordinates":[-2.65214,56.807931],"type":"Point"}
}