{
  "type": "Feature",
  "properties": {
    "iso:country":"GB",
    "wof:name":"NE27 0NS",
    "wof:placetype":"postalcode"
},
  "geometry": {"coordinates":[-1.50906528687746,55.03616363842909],"type":"Point"}
}