{
  "type": "Feature",
  "properties": {
    "iso:country":"GB",
    "wof:name":"HG4 2PH",
    "wof:placetype":"postalcode"
},
  "geometry": {"coordinates":[-1.52874877490732,54.12525940291852],"type":"Point"}
}