{
  "type": "Feature",
  "properties": {
    "iso:country":"GB",
    "wof:name":"CB24 9NS",
    "wof:placetype":"postalcode"
},
  "geometry": {"coordinates":[0.11035834717265,52.2465624771003],"type":"Point"}
}