{
  "type": "Feature",
  "properties": {
    "iso:country":"GB",
    "wof:name":"KY14 6EU",
    "wof:placetype":"postalcode"
},
  "geometry": {"coordinates":[-3.23352389549448,56.31934475222223],"type":"Point"}
}