{
  "type": "Feature",
  "properties": {
    "iso:country":"GB",
    "wof:name":"EX16 4DA",
    "wof:placetype":"postalcode"
},
  "geometry": {"coordinates":[-3.47850369648643,50.9045614617731],"type":"Point"}
}