{
  "type": "Feature",
  "properties": {
    "iso:country": "GB",
    "wof:name": "EX16 4DA",
    "wof:placetype": "postalcode"
  },
  "geometry": {"coordinates":[-3.478504,50.904561],"type":"Point"}
}
