{
  "type": "Feature",
  "properties": {
    "iso:country":"GB",
    "wof:name":"YO30 5TQ",
    "wof:placetype":"postalcode"
},
  "geometry": {"coordinates":[-1.11304304673395,53.98225436641878],"type":"Point"}
}