{
  "type": "Feature",
  "properties": {
    "iso:country": "GB",
    "wof:name": "NE29 7NS",
    "wof:placetype": "postalcode"
  },
  "geometry": {"coordinates":[-1.472859,55.012334],"type":"Point"}
}
