{
  "type": "Feature",
  "properties": {
    "iso:country":"GB",
    "wof:name":"NG16 6RL",
    "wof:placetype":"postalcode"
},
  "geometry": {"coordinates":[-1.28886590838416,53.07415778225575],"type":"Point"}
}