{
  "type": "Feature",
  "properties": {
    "date:inception_lower":"1981-06-01",
    "date:inception_upper":"1981-06-30",
    "iso:country":"GB",
    "wof:name":"NG16 6RL",
    "wof:placetype":"postalcode"
},
  "geometry": {"coordinates":[-1.288866,53.074158],"type":"Point"}
}