{
  "type": "Feature",
  "properties": {
    "iso:country": "GB",
    "wof:name": "M5 5AJ",
    "wof:placetype": "postalcode"
  },
  "geometry": {"coordinates":[-2.322814,53.484553],"type":"Point"}
}
