{
  "type": "Feature",
  "properties": {
    "iso:country":"GB",
    "wof:name":"M5 5AJ",
    "wof:placetype":"postalcode"
},
  "geometry": {"coordinates":[-2.32281385235505,53.48455318747311],"type":"Point"}
}