{
  "type": "Feature",
  "properties": {
    "iso:country":"GB",
    "wof:name":"KA30 8HB",
    "wof:placetype":"postalcode"
},
  "geometry": {"coordinates":[-4.85746872103346,55.78103985938068],"type":"Point"}
}