{
  "type": "Feature",
  "properties": {
    "iso:country":"GB",
    "wof:name":"EN1 4TX",
    "wof:placetype":"postalcode"
},
  "geometry": {"coordinates":[-0.06729736750942,51.66669988768634],"type":"Point"}
}