{
  "type": "Feature",
  "properties": {
    "iso:country": "GB",
    "wof:name": "BS48 3BB",
    "wof:placetype": "postalcode"
  },
  "geometry": {"coordinates":[-2.752584,51.403281],"type":"Point"}
}
