{
  "type": "Feature",
  "properties": {
    "date:inception_lower": "1997-12-01",
    "date:inception_upper": "1997-12-01",
    "iso:country": "GB",
    "wof:name": "BS48 3BB",
    "wof:placetype": "postalcode"
  },
  "geometry": {"coordinates":[-2.752584,51.403281],"type":"Point"}
}
