{
  "type": "Feature",
  "properties": {
    "iso:country":"GB",
    "wof:name":"CF83 2LA",
    "wof:placetype":"postalcode"
},
  "geometry": {"coordinates":[-3.24311973814912,51.59243874138622],"type":"Point"}
}