{
  "type": "Feature",
  "properties": {
    "iso:country": "GB",
    "wof:name": "DL16 6XF",
    "wof:placetype": "postalcode"
  },
  "geometry": {"coordinates":[-1.590903,54.703942],"type":"Point"}
}
