{
  "type": "Feature",
  "properties": {
    "iso:country":"GB",
    "wof:name":"TR1 2DE",
    "wof:placetype":"postalcode"
},
  "geometry": {"coordinates":[-5.06138325974737,50.25698497827067],"type":"Point"}
}