{
  "type": "Feature",
  "properties": {
    "iso:country":"GB",
    "wof:name":"CT21 4JE",
    "wof:placetype":"postalcode"
},
  "geometry": {"coordinates":[1.06533887135057,51.07605873472886],"type":"Point"}
}