{
  "type": "Feature",
  "properties": {
    "date:inception_lower":"1997-12-01",
    "date:inception_upper":"1997-12-31",
    "iso:country":"GB",
    "wof:name":"CT21 4JE",
    "wof:placetype":"postalcode"
},
  "geometry": {"coordinates":[1.065373,51.076061],"type":"Point"}
}