{
  "type": "Feature",
  "properties": {
    "date:inception_lower": "1980-01-01",
    "date:inception_upper": "1980-01-01",
    "iso:country": "GB",
    "wof:name": "OX2 9JZ",
    "wof:placetype": "postalcode"
  },
  "geometry": {"coordinates":[-1.298616,51.752822],"type":"Point"}
}
