{
  "type": "Feature",
  "properties": {
    "iso:country":"GB",
    "wof:name":"OX2 9JZ",
    "wof:placetype":"postalcode"
},
  "geometry": {"coordinates":[-1.29861616278368,51.75282231980163],"type":"Point"}
}