{
  "type": "Feature",
  "properties": {
    "iso:country":"GB",
    "wof:name":"M4 1FR",
    "wof:placetype":"postalcode"
},
  "geometry": {"coordinates":[-2.23707821955091,53.4838103996158],"type":"Point"}
}