{
  "type": "Feature",
  "properties": {
    "iso:country": "GB",
    "wof:name": "M4 1FR",
    "wof:placetype": "postalcode"
  },
  "geometry": {"coordinates":[-2.237154,53.483819],"type":"Point"}
}
