{
  "type": "Feature",
  "properties": {
    "date:inception_lower": "1994-05-01",
    "date:inception_upper": "1994-05-01",
    "iso:country": "GB",
    "wof:name": "M4 1FR",
    "wof:placetype": "postalcode"
  },
  "geometry": {"coordinates":[-2.23694,53.483791],"type":"Point"}
}
