{
  "type": "Feature",
  "properties": {
    "iso:country":"GB",
    "wof:name":"LS8 1EE",
    "wof:placetype":"postalcode"
},
  "geometry": {"coordinates":[-1.51046305406468,53.83773931391011],"type":"Point"}
}