{
  "type": "Feature",
  "properties": {
    "iso:country":"GB",
    "wof:name":"BN13 3BT",
    "wof:placetype":"postalcode"
},
  "geometry": {"coordinates":[-0.41031834189357,50.84931040263928],"type":"Point"}
}