{
  "type": "Feature",
  "properties": {
    "iso:country":"GB",
    "wof:name":"ME2 1BZ",
    "wof:placetype":"postalcode"
},
  "geometry": {"coordinates":[0.44682380273257,51.34674373489572],"type":"Point"}
}