{
  "type": "Feature",
  "properties": {
    "iso:country": "GB",
    "wof:name": "CV36 4QN",
    "wof:placetype": "postalcode"
  },
  "geometry": {"coordinates":[-1.62496,52.064951],"type":"Point"}
}
