{
  "type": "Feature",
  "properties": {
    "iso:country":"GB",
    "wof:name":"CV36 4QN",
    "wof:placetype":"postalcode"
},
  "geometry": {"coordinates":[-1.62495988152636,52.06495069300473],"type":"Point"}
}