{
  "type": "Feature",
  "properties": {
    "iso:country": "GB",
    "wof:name": "S62 6HL",
    "wof:placetype": "postalcode"
  },
  "geometry": {"coordinates":[-1.345672,53.452765],"type":"Point"}
}
