{
  "type": "Feature",
  "properties": {
    "iso:country":"GB",
    "wof:name":"S62 6HL",
    "wof:placetype":"postalcode"
},
  "geometry": {"coordinates":[-1.34567050370851,53.45274670379805],"type":"Point"}
}