{
  "type": "Feature",
  "properties": {
    "iso:country": "GB",
    "wof:name": "KT11 1PG",
    "wof:placetype": "postalcode"
  },
  "geometry": {"coordinates":[-0.421306,51.314281],"type":"Point"}
}
