{
  "type": "Feature",
  "properties": {
    "iso:country":"GB",
    "wof:name":"KT11 1PG",
    "wof:placetype":"postalcode"
},
  "geometry": {"coordinates":[-0.42130643334366,51.31428075728091],"type":"Point"}
}