{
  "type": "Feature",
  "properties": {
    "date:inception_lower": "1994-05-01",
    "date:inception_upper": "1994-05-01",
    "iso:country": "GB",
    "wof:name": "HU2 8NZ",
    "wof:placetype": "postalcode"
  },
  "geometry": {"coordinates":[-0.347148,53.748088],"type":"Point"}
}
