{
  "type": "Feature",
  "properties": {
    "iso:country":"GB",
    "wof:name":"HU2 8NZ",
    "wof:placetype":"postalcode"
},
  "geometry": {"coordinates":[-0.34714798237965,53.7480883298754],"type":"Point"}
}