{
  "type": "Feature",
  "properties": {
    "iso:country":"GB",
    "wof:name":"GU1 4AA",
    "wof:placetype":"postalcode"
},
  "geometry": {"coordinates":[-0.57092624135083,51.2370147666858],"type":"Point"}
}