{
  "type": "Feature",
  "properties": {
    "iso:country": "GB",
    "wof:name": "GU1 4AA",
    "wof:placetype": "postalcode"
  },
  "geometry": {"coordinates":[-0.570806,51.236974],"type":"Point"}
}
