{
  "type": "Feature",
  "properties": {
    "iso:country":"GB",
    "wof:name":"KA16 9LE",
    "wof:placetype":"postalcode"
},
  "geometry": {"coordinates":[-4.29437482522887,55.6213592875194],"type":"Point"}
}