{
  "type": "Feature",
  "properties": {
    "date:inception_lower": "2017-08-01",
    "date:inception_upper": "2017-08-01",
    "iso:country": "GB",
    "wof:name": "LS21 1GA",
    "wof:placetype": "postalcode"
  },
  "geometry": {"coordinates":[-1.690498,53.90978],"type":"Point"}
}
