{
  "type": "Feature",
  "properties": {
    "iso:country":"GB",
    "wof:name":"PR25 3SN",
    "wof:placetype":"postalcode"
},
  "geometry": {"coordinates":[-2.68894162401416,53.6975662358648],"type":"Point"}
}