{
  "type": "Feature",
  "properties": {
    "date:inception_lower":"1980-01-01",
    "date:inception_upper":"1980-01-31",
    "iso:country":"GB",
    "wof:name":"SA8 3DD",
    "wof:placetype":"postalcode"
},
  "geometry": {"coordinates":[-3.838234,51.721631],"type":"Point"}
}