{
  "type": "Feature",
  "properties": {
    "iso:country": "GB",
    "wof:name": "SA8 3DD",
    "wof:placetype": "postalcode"
  },
  "geometry": {"coordinates":[-3.838234,51.721631],"type":"Point"}
}
