{
  "type": "Feature",
  "properties": {
    "iso:country":"GB",
    "wof:name":"SA8 3DD",
    "wof:placetype":"postalcode"
},
  "geometry": {"coordinates":[-3.83823435152775,51.7216311421253],"type":"Point"}
}