{
  "type": "Feature",
  "properties": {
    "iso:country":"GB",
    "wof:name":"SA4 4ZD",
    "wof:placetype":"postalcode"
},
  "geometry": {"coordinates":[-4.05535309679181,51.66959878131291],"type":"Point"}
}