{
  "type": "Feature",
  "properties": {
    "date:inception_lower": "1993-01-01",
    "date:inception_upper": "1993-01-01",
    "iso:country": "GB",
    "wof:name": "SA4 4ZD",
    "wof:placetype": "postalcode"
  },
  "geometry": {"coordinates":[-4.055457,51.66954],"type":"Point"}
}
