{
  "type": "Feature",
  "properties": {
    "iso:country": "GB",
    "wof:name": "SA4 4ZD",
    "wof:placetype": "postalcode"
  },
  "geometry": {"coordinates":[-4.055457,51.66954],"type":"Point"}
}
