{
  "type": "Feature",
  "properties": {
    "iso:country":"GB",
    "wof:name":"NW10 0RW",
    "wof:placetype":"postalcode"
},
  "geometry": {"coordinates":[-0.27540043685672,51.54398611391014],"type":"Point"}
}