{
  "type": "Feature",
  "properties": {
    "iso:country": "GB",
    "wof:name": "DL3 6NR",
    "wof:placetype": "postalcode"
  },
  "geometry": {"coordinates":[-1.559709,54.533838],"type":"Point"}
}
