{
  "type": "Feature",
  "properties": {
    "iso:country":"GB",
    "wof:name":"TN21 0EU",
    "wof:placetype":"postalcode"
},
  "geometry": {"coordinates":[0.24437344093978,50.93632538703643],"type":"Point"}
}