{
  "type": "Feature",
  "properties": {
    "date:inception_lower":"1981-09-01",
    "date:inception_upper":"1981-09-30",
    "iso:country":"GB",
    "wof:name":"LS11 6DG",
    "wof:placetype":"postalcode"
},
  "geometry": {"coordinates":[-1.550695,53.777353],"type":"Point"}
}