{
  "type": "Feature",
  "properties": {
    "iso:country":"GB",
    "wof:name":"SK3 9RZ",
    "wof:placetype":"postalcode"
},
  "geometry": {"coordinates":[-2.17570671373315,53.39786054438006],"type":"Point"}
}