{
  "type": "Feature",
  "properties": {
    "date:inception_lower": "1991-09-01",
    "date:inception_upper": "1991-09-01",
    "iso:country": "GB",
    "wof:name": "SK3 9RZ",
    "wof:placetype": "postalcode"
  },
  "geometry": {"coordinates":[-2.175707,53.397861],"type":"Point"}
}
