{
  "type": "Feature",
  "properties": {
    "iso:country":"GB",
    "wof:name":"DE1 1PR",
    "wof:placetype":"postalcode"
},
  "geometry": {"coordinates":[-1.48100799857349,52.9177572720752],"type":"Point"}
}