{
  "type": "Feature",
  "properties": {
    "iso:country": "GB",
    "wof:name": "IV6 7SA",
    "wof:placetype": "postalcode"
  },
  "geometry": {"coordinates":[-4.333319,57.547439],"type":"Point"}
}
