{
  "type": "Feature",
  "properties": {
    "iso:country":"GB",
    "wof:name":"IV6 7SA",
    "wof:placetype":"postalcode"
},
  "geometry": {"coordinates":[-4.33331879485692,57.54743908554691],"type":"Point"}
}