{
  "type": "Feature",
  "properties": {
    "date:inception_lower":"1980-01-01",
    "date:inception_upper":"1980-01-31",
    "iso:country":"GB",
    "wof:name":"IV6 7SA",
    "wof:placetype":"postalcode"
},
  "geometry": {"coordinates":[-4.333319,57.547439],"type":"Point"}
}