{
  "type": "Feature",
  "properties": {
    "date:inception_lower": "2018-07-01",
    "date:inception_upper": "2018-07-01",
    "iso:country": "GB",
    "wof:name": "SL0 9BY",
    "wof:placetype": "postalcode"
  },
  "geometry": {"coordinates":[-0.508119,51.515103],"type":"Point"}
}
