{
  "type": "Feature",
  "properties": {
    "iso:country":"GB",
    "wof:name":"LU2 8HU",
    "wof:placetype":"postalcode"
},
  "geometry": {"coordinates":[-0.38046949954609,51.90273365251822],"type":"Point"}
}