{
  "type": "Feature",
  "properties": {
    "iso:country":"GB",
    "wof:name":"NE2 2SP",
    "wof:placetype":"postalcode"
},
  "geometry": {"coordinates":[-1.60624980728449,54.98940189204919],"type":"Point"}
}