{
  "type": "Feature",
  "properties": {
    "iso:country": "GB",
    "wof:name": "NE2 2SP",
    "wof:placetype": "postalcode"
  },
  "geometry": {"coordinates":[-1.60625,54.989402],"type":"Point"}
}
