{
  "type": "Feature",
  "properties": {
    "iso:country":"GB",
    "wof:name":"LL58 8YA",
    "wof:placetype":"postalcode"
},
  "geometry": {"coordinates":[-4.13467360265858,53.30879150674529],"type":"Point"}
}