{
  "type": "Feature",
  "properties": {
    "iso:country": "GB",
    "wof:name": "LL58 8YA",
    "wof:placetype": "postalcode"
  },
  "geometry": {"coordinates":[-4.134674,53.308792],"type":"Point"}
}
