{
  "type": "Feature",
  "properties": {
    "iso:country":"GB",
    "wof:name":"SO21 2HR",
    "wof:placetype":"postalcode"
},
  "geometry": {"coordinates":[-1.3528493589166,50.99780561378318],"type":"Point"}
}