{
  "type": "Feature",
  "properties": {
    "iso:country":"GB",
    "wof:name":"SW2 1BG",
    "wof:placetype":"postalcode"
},
  "geometry": {"coordinates":[-0.11063127162598,51.45797935995412],"type":"Point"}
}