{
  "type": "Feature",
  "properties": {
    "date:inception_lower": "1980-01-01",
    "date:inception_upper": "1980-01-01",
    "iso:country": "GB",
    "wof:name": "TN15 7AB",
    "wof:placetype": "postalcode"
  },
  "geometry": {"coordinates":[0.310692,51.309219],"type":"Point"}
}
