{
  "type": "Feature",
  "properties": {
    "iso:country": "GB",
    "wof:name": "TN15 7AB",
    "wof:placetype": "postalcode"
  },
  "geometry": {"coordinates":[0.310692,51.309219],"type":"Point"}
}
