{
  "type": "Feature",
  "properties": {
    "iso:country": "GB",
    "wof:name": "B60 3QQ",
    "wof:placetype": "postalcode"
  },
  "geometry": {"coordinates":[-2.074278,52.3197],"type":"Point"}
}
