{
  "type": "Feature",
  "properties": {
    "iso:country":"GB",
    "wof:name":"WC1R 4AJ",
    "wof:placetype":"postalcode"
},
  "geometry": {"coordinates":[-0.11703855192152,51.51877328602473],"type":"Point"}
}