{
  "type": "Feature",
  "properties": {
    "iso:country": "GB",
    "wof:name": "DH4 6DA",
    "wof:placetype": "postalcode"
  },
  "geometry": {"coordinates":[-1.513499,54.851988],"type":"Point"}
}
