{
  "type": "Feature",
  "properties": {
    "iso:country":"GB",
    "wof:name":"OL13 0PD",
    "wof:placetype":"postalcode"
},
  "geometry": {"coordinates":[-2.234846458707,53.69040180375281],"type":"Point"}
}