{
  "type": "Feature",
  "properties": {
    "iso:country":"GB",
    "wof:name":"SR6 7TE",
    "wof:placetype":"postalcode"
},
  "geometry": {"coordinates":[-1.41532452766711,54.95028075970689],"type":"Point"}
}