{
  "type": "Feature",
  "properties": {
    "iso:country": "GB",
    "wof:name": "SR6 7TE",
    "wof:placetype": "postalcode"
  },
  "geometry": {"coordinates":[-1.415324,54.950281],"type":"Point"}
}
