{
  "type": "Feature",
  "properties": {
    "iso:country":"GB",
    "wof:name":"OL4 5HQ",
    "wof:placetype":"postalcode"
},
  "geometry": {"coordinates":[-2.08602438464957,53.53665991974199],"type":"Point"}
}