{
  "type": "Feature",
  "properties": {
    "iso:country":"GB",
    "wof:name":"BH12 2DH",
    "wof:placetype":"postalcode"
},
  "geometry": {"coordinates":[-1.9328728571267,50.73028043802215],"type":"Point"}
}