{
  "type": "Feature",
  "properties": {
    "date:inception_lower":"1980-01-01",
    "date:inception_upper":"1980-01-31",
    "iso:country":"GB",
    "wof:name":"S41 9DT",
    "wof:placetype":"postalcode"
},
  "geometry": {"coordinates":[-1.435737,53.269458],"type":"Point"}
}