{
  "type": "Feature",
  "properties": {
    "iso:country": "GB",
    "wof:name": "S41 9DT",
    "wof:placetype": "postalcode"
  },
  "geometry": {"coordinates":[-1.435737,53.269458],"type":"Point"}
}
