{
  "type": "Feature",
  "properties": {
    "iso:country": "GB",
    "wof:name": "SW6 2FR",
    "wof:placetype": "postalcode"
  },
  "geometry": {"coordinates":[-0.186779,51.475145],"type":"Point"}
}
