{
  "type": "Feature",
  "properties": {
    "iso:country":"GB",
    "wof:name":"BS23 1ES",
    "wof:placetype":"postalcode"
},
  "geometry": {"coordinates":[-2.97668247159545,51.34069749615686],"type":"Point"}
}