{
  "type": "Feature",
  "properties": {
    "iso:country":"GB",
    "wof:name":"SK17 0TN",
    "wof:placetype":"postalcode"
},
  "geometry": {"coordinates":[-1.96449573563454,53.20126709294423],"type":"Point"}
}