{
  "type": "Feature",
  "properties": {
    "iso:country": "GB",
    "wof:name": "SK17 0TN",
    "wof:placetype": "postalcode"
  },
  "geometry": {"coordinates":[-1.964496,53.201267],"type":"Point"}
}
