{
  "type": "Feature",
  "properties": {
    "date:inception_lower":"1996-06-01",
    "date:inception_upper":"1996-06-30",
    "iso:country":"GB",
    "wof:name":"SK17 0TN",
    "wof:placetype":"postalcode"
},
  "geometry": {"coordinates":[-1.964496,53.201267],"type":"Point"}
}