{
  "type": "Feature",
  "properties": {
    "date:inception_lower": "1980-01-01",
    "date:inception_upper": "1980-01-01",
    "iso:country": "GB",
    "wof:name": "NE9 6EA",
    "wof:placetype": "postalcode"
  },
  "geometry": {"coordinates":[-1.609068,54.938998],"type":"Point"}
}
