{
  "type": "Feature",
  "properties": {
    "iso:country":"GB",
    "wof:name":"N9 0JP",
    "wof:placetype":"postalcode"
},
  "geometry": {"coordinates":[-0.05080574435949,51.62674371961495],"type":"Point"}
}