{
  "type": "Feature",
  "properties": {
    "iso:country":"GB",
    "wof:name":"M40 0FX",
    "wof:placetype":"postalcode"
},
  "geometry": {"coordinates":[-2.17341495160013,53.52191388635948],"type":"Point"}
}