{
  "type": "Feature",
  "properties": {
    "date:inception_lower": "1983-07-01",
    "date:inception_upper": "1983-07-01",
    "iso:country": "GB",
    "wof:name": "BB2 7DZ",
    "wof:placetype": "postalcode"
  },
  "geometry": {"coordinates":[-2.510879,53.763164],"type":"Point"}
}
