{
  "type": "Feature",
  "properties": {
    "iso:country":"GB",
    "wof:name":"BB2 7DZ",
    "wof:placetype":"postalcode"
},
  "geometry": {"coordinates":[-2.5108791457392,53.76316410294186],"type":"Point"}
}