{
  "type": "Feature",
  "properties": {
    "iso:country":"GB",
    "wof:name":"G65 0HZ",
    "wof:placetype":"postalcode"
},
  "geometry": {"coordinates":[-4.04823366566215,55.97938671970493],"type":"Point"}
}