{
  "type": "Feature",
  "properties": {
    "iso:country": "GB",
    "wof:name": "PL25 5BN",
    "wof:placetype": "postalcode"
  },
  "geometry": {"coordinates":[-4.793946,50.335537],"type":"Point"}
}
