{
  "type": "Feature",
  "properties": {
    "date:inception_lower":"1980-01-01",
    "date:inception_upper":"1980-01-31",
    "iso:country":"GB",
    "wof:name":"SA61 1PA",
    "wof:placetype":"postalcode"
},
  "geometry": {"coordinates":[-4.973544,51.79567],"type":"Point"}
}