{
  "type": "Feature",
  "properties": {
    "date:inception_lower": "1980-01-01",
    "date:inception_upper": "1980-01-01",
    "iso:country": "GB",
    "wof:name": "NE61 2XW",
    "wof:placetype": "postalcode"
  },
  "geometry": {"coordinates":[-1.705925,55.158415],"type":"Point"}
}
