{
  "type": "Feature",
  "properties": {
    "iso:country":"GB",
    "wof:name":"HU8 8PA",
    "wof:placetype":"postalcode"
},
  "geometry": {"coordinates":[-0.30787502070999,53.76000831011928],"type":"Point"}
}