{
  "type": "Feature",
  "properties": {
    "iso:country":"GB",
    "wof:name":"NE6 1HN",
    "wof:placetype":"postalcode"
},
  "geometry": {"coordinates":[-1.57891500947466,54.97754739339547],"type":"Point"}
}