{
  "type": "Feature",
  "properties": {
    "iso:country":"GB",
    "wof:name":"GU24 9HQ",
    "wof:placetype":"postalcode"
},
  "geometry": {"coordinates":[-0.63363232919399,51.32813667886956],"type":"Point"}
}