{
  "type": "Feature",
  "properties": {
    "date:inception_lower": "1984-10-01",
    "date:inception_upper": "1984-10-01",
    "iso:country": "GB",
    "wof:name": "GU24 9HQ",
    "wof:placetype": "postalcode"
  },
  "geometry": {"coordinates":[-0.633632,51.328137],"type":"Point"}
}
