{
  "type": "Feature",
  "properties": {
    "iso:country":"GB",
    "wof:name":"M41 9DL",
    "wof:placetype":"postalcode"
},
  "geometry": {"coordinates":[-2.36241545520727,53.44548337462796],"type":"Point"}
}