{
  "type": "Feature",
  "properties": {
    "iso:country":"GB",
    "wof:name":"NP23 4TG",
    "wof:placetype":"postalcode"
},
  "geometry": {"coordinates":[-3.18338818387893,51.80114896902233],"type":"Point"}
}