{
  "type": "Feature",
  "properties": {
    "iso:country":"GB",
    "wof:name":"SA43 2NW",
    "wof:placetype":"postalcode"
},
  "geometry": {"coordinates":[-4.6049827106969,52.06669611444625],"type":"Point"}
}