{
  "type": "Feature",
  "properties": {
    "iso:country":"GB",
    "wof:name":"BN7 3EJ",
    "wof:placetype":"postalcode"
},
  "geometry": {"coordinates":[-0.0032371219774,50.84836060732876],"type":"Point"}
}