{
  "type": "Feature",
  "properties": {
    "iso:country": "GB",
    "wof:name": "BN7 3EJ",
    "wof:placetype": "postalcode"
  },
  "geometry": {"coordinates":[-0.003237,50.848361],"type":"Point"}
}
