{
  "type": "Feature",
  "properties": {
    "iso:country":"GB",
    "wof:name":"EH21 6SJ",
    "wof:placetype":"postalcode"
},
  "geometry": {"coordinates":[-3.06716272190524,55.94277996640408],"type":"Point"}
}