{
  "type": "Feature",
  "properties": {
    "iso:country":"GB",
    "wof:name":"BN15 8LN",
    "wof:placetype":"postalcode"
},
  "geometry": {"coordinates":[-0.30366512160533,50.8240934988462],"type":"Point"}
}