{
  "type": "Feature",
  "properties": {
    "date:inception_lower": "1980-01-01",
    "date:inception_upper": "1980-01-01",
    "iso:country": "GB",
    "wof:name": "BN15 8LN",
    "wof:placetype": "postalcode"
  },
  "geometry": {"coordinates":[-0.303665,50.824093],"type":"Point"}
}
