{
  "type": "Feature",
  "properties": {
    "iso:country":"GB",
    "wof:name":"B74 3HQ",
    "wof:placetype":"postalcode"
},
  "geometry": {"coordinates":[-1.89408601734791,52.57377852372648],"type":"Point"}
}