{
  "type": "Feature",
  "properties": {
    "date:inception_lower": "1980-01-01",
    "date:inception_upper": "1980-01-01",
    "iso:country": "GB",
    "wof:name": "DN17 4QW",
    "wof:placetype": "postalcode"
  },
  "geometry": {"coordinates":[-0.74876,53.638781],"type":"Point"}
}
