{
  "type": "Feature",
  "properties": {
    "iso:country": "GB",
    "wof:name": "DN17 4QW",
    "wof:placetype": "postalcode"
  },
  "geometry": {"coordinates":[-0.748976,53.638622],"type":"Point"}
}
