{
  "type": "Feature",
  "properties": {
    "iso:country":"GB",
    "wof:name":"DN17 4QW",
    "wof:placetype":"postalcode"
},
  "geometry": {"coordinates":[-0.74875472113078,53.63876028345627],"type":"Point"}
}