{
  "type": "Feature",
  "properties": {
    "iso:country":"GB",
    "wof:name":"EC2A 2AL",
    "wof:placetype":"postalcode"
},
  "geometry": {"coordinates":[-0.08450632347742,51.52049465239718],"type":"Point"}
}