{
  "type": "Feature",
  "properties": {
    "iso:country":"GB",
    "wof:name":"NN12 7UN",
    "wof:placetype":"postalcode"
},
  "geometry": {"coordinates":[-0.888842203468,52.09614910917406],"type":"Point"}
}