{
  "type": "Feature",
  "properties": {
    "date:inception_lower": "1980-01-01",
    "date:inception_upper": "1980-01-01",
    "iso:country": "GB",
    "wof:name": "NN12 7UN",
    "wof:placetype": "postalcode"
  },
  "geometry": {"coordinates":[-0.888842,52.096149],"type":"Point"}
}
