{
  "type": "Feature",
  "properties": {
    "iso:country": "GB",
    "wof:name": "RH15 0GT",
    "wof:placetype": "postalcode"
  },
  "geometry": {"coordinates":[-0.099807,50.952903],"type":"Point"}
}
