{
  "type": "Feature",
  "properties": {
    "iso:country":"GB",
    "wof:name":"S62 6BN",
    "wof:placetype":"postalcode"
},
  "geometry": {"coordinates":[-1.3415141090182,53.45275983226119],"type":"Point"}
}