{
  "type": "Feature",
  "properties": {
    "iso:country": "GB",
    "wof:name": "S62 6BN",
    "wof:placetype": "postalcode"
  },
  "geometry": {"coordinates":[-1.341514,53.45276],"type":"Point"}
}
