{
  "type": "Feature",
  "properties": {
    "iso:country":"GB",
    "wof:name":"DN17 3DD",
    "wof:placetype":"postalcode"
},
  "geometry": {"coordinates":[-0.73862398253461,53.58640163339935],"type":"Point"}
}