{
  "type": "Feature",
  "properties": {
    "iso:country": "GB",
    "wof:name": "DN17 3DD",
    "wof:placetype": "postalcode"
  },
  "geometry": {"coordinates":[-0.738624,53.586402],"type":"Point"}
}
