{
  "type": "Feature",
  "properties": {
    "iso:country":"GB",
    "wof:name":"DE21 6BE",
    "wof:placetype":"postalcode"
},
  "geometry": {"coordinates":[-1.45576468878588,52.92883617716108],"type":"Point"}
}