{
  "type": "Feature",
  "properties": {
    "iso:country": "GB",
    "wof:name": "GL1 4DW",
    "wof:placetype": "postalcode"
  },
  "geometry": {"coordinates":[-2.228584,51.857053],"type":"Point"}
}
