{
  "type": "Feature",
  "properties": {
    "iso:country":"GB",
    "wof:name":"NG13 8RH",
    "wof:placetype":"postalcode"
},
  "geometry": {"coordinates":[-0.96684874026424,52.95217451087095],"type":"Point"}
}