{
  "type": "Feature",
  "properties": {
    "iso:country": "GB",
    "wof:name": "CW8 1BP",
    "wof:placetype": "postalcode"
  },
  "geometry": {"coordinates":[-2.520018,53.254025],"type":"Point"}
}
