{
  "type": "Feature",
  "properties": {
    "iso:country":"GB",
    "wof:name":"CW8 1BP",
    "wof:placetype":"postalcode"
},
  "geometry": {"coordinates":[-2.52001834787238,53.25402509418343],"type":"Point"}
}