{
  "type": "Feature",
  "properties": {
    "iso:country": "GB",
    "wof:name": "G51 3ED",
    "wof:placetype": "postalcode"
  },
  "geometry": {"coordinates":[-4.318343,55.864683],"type":"Point"}
}
