{
  "type": "Feature",
  "properties": {
    "iso:country":"GB",
    "wof:name":"G51 3ED",
    "wof:placetype":"postalcode"
},
  "geometry": {"coordinates":[-4.31834259047757,55.8646831108079],"type":"Point"}
}