{
  "type": "Feature",
  "properties": {
    "iso:country": "GB",
    "wof:name": "CV37 9BY",
    "wof:placetype": "postalcode"
  },
  "geometry": {"coordinates":[-1.718677,52.196006],"type":"Point"}
}
