{
  "type": "Feature",
  "properties": {
    "iso:country":"GB",
    "wof:name":"CV37 9BY",
    "wof:placetype":"postalcode"
},
  "geometry": {"coordinates":[-1.71867660637655,52.19600550478722],"type":"Point"}
}