{
  "type": "Feature",
  "properties": {
    "iso:country":"GB",
    "wof:name":"WF2 6RU",
    "wof:placetype":"postalcode"
},
  "geometry": {"coordinates":[-1.45139681518197,53.64308787357137],"type":"Point"}
}