{
  "type": "Feature",
  "properties": {
    "date:inception_lower": "1991-01-01",
    "date:inception_upper": "1991-01-01",
    "iso:country": "GB",
    "wof:name": "WF2 6RU",
    "wof:placetype": "postalcode"
  },
  "geometry": {"coordinates":[-1.451397,53.643088],"type":"Point"}
}
