{
  "type": "Feature",
  "properties": {
    "iso:country":"GB",
    "wof:name":"E2 6DZ",
    "wof:placetype":"postalcode"
},
  "geometry": {"coordinates":[-0.07019509378496,51.52453153634474],"type":"Point"}
}