{
  "type": "Feature",
  "properties": {
    "date:inception_lower": "1980-01-01",
    "date:inception_upper": "1980-01-01",
    "iso:country": "GB",
    "wof:name": "E2 6DZ",
    "wof:placetype": "postalcode"
  },
  "geometry": {"coordinates":[-0.070208,51.524577],"type":"Point"}
}
