{
  "type": "Feature",
  "properties": {
    "iso:country": "GB",
    "wof:name": "E2 6DZ",
    "wof:placetype": "postalcode"
  },
  "geometry": {"coordinates":[-0.070208,51.524577],"type":"Point"}
}
