{
  "type": "Feature",
  "properties": {
    "iso:country":"GB",
    "wof:name":"M44 5WA",
    "wof:placetype":"postalcode"
},
  "geometry": {"coordinates":[-2.42732491159594,53.45781671327521],"type":"Point"}
}