{
  "type": "Feature",
  "properties": {
    "date:inception_lower":"2005-07-01",
    "date:inception_upper":"2005-07-31",
    "iso:country":"GB",
    "wof:name":"CM3 6GJ",
    "wof:placetype":"postalcode"
},
  "geometry": {"coordinates":[0.75429,51.688145],"type":"Point"}
}