{
  "type": "Feature",
  "properties": {
    "iso:country": "GB",
    "wof:name": "CM3 6GJ",
    "wof:placetype": "postalcode"
  },
  "geometry": {"coordinates":[0.75429,51.688145],"type":"Point"}
}
