{
  "type": "Feature",
  "properties": {
    "iso:country":"GB",
    "wof:name":"CM3 6GJ",
    "wof:placetype":"postalcode"
},
  "geometry": {"coordinates":[0.75429030901826,51.68814467182523],"type":"Point"}
}