{
  "type": "Feature",
  "properties": {
    "date:inception_lower":"1995-12-01",
    "date:inception_upper":"1995-12-31",
    "iso:country":"GB",
    "wof:name":"PA5 8DW",
    "wof:placetype":"postalcode"
},
  "geometry": {"coordinates":[-4.514595,55.835967],"type":"Point"}
}