{
  "type": "Feature",
  "properties": {
    "date:inception_lower":"1999-12-01",
    "date:inception_upper":"1999-12-31",
    "iso:country":"GB",
    "wof:name":"MK42 9FN",
    "wof:placetype":"postalcode"
},
  "geometry": {"coordinates":[-0.468241,52.121969],"type":"Point"}
}