{
  "type": "Feature",
  "properties": {
    "date:inception_lower": "1980-01-01",
    "date:inception_upper": "1980-01-01",
    "iso:country": "GB",
    "wof:name": "DY7 6RX",
    "wof:placetype": "postalcode"
  },
  "geometry": {"coordinates":[-2.175874,52.463793],"type":"Point"}
}
