{
  "type": "Feature",
  "properties": {
    "iso:country":"GB",
    "wof:name":"DY7 6RX",
    "wof:placetype":"postalcode"
},
  "geometry": {"coordinates":[-2.17587399694769,52.46379301518444],"type":"Point"}
}