{
  "type": "Feature",
  "properties": {
    "iso:country":"GB",
    "wof:name":"EX20 4BY",
    "wof:placetype":"postalcode"
},
  "geometry": {"coordinates":[-4.21555220487541,50.65864860726632],"type":"Point"}
}