{
  "type": "Feature",
  "properties": {
    "iso:country":"GB",
    "wof:name":"FK10 2HA",
    "wof:placetype":"postalcode"
},
  "geometry": {"coordinates":[-3.81410030278952,56.13036796589808],"type":"Point"}
}