{
  "type": "Feature",
  "properties": {
    "date:inception_lower": "1980-01-01",
    "date:inception_upper": "1980-01-01",
    "iso:country": "GB",
    "wof:name": "FK10 2HA",
    "wof:placetype": "postalcode"
  },
  "geometry": {"coordinates":[-3.8141,56.130368],"type":"Point"}
}
