{
  "type": "Feature",
  "properties": {
    "iso:country": "GB",
    "wof:name": "LS12 3EJ",
    "wof:placetype": "postalcode"
  },
  "geometry": {"coordinates":[-1.600847,53.795307],"type":"Point"}
}
