{
  "type": "Feature",
  "properties": {
    "iso:country":"GB",
    "wof:name":"NG4 2FG",
    "wof:placetype":"postalcode"
},
  "geometry": {"coordinates":[-1.07773036997724,52.96305582002574],"type":"Point"}
}