{
  "type": "Feature",
  "properties": {
    "iso:country":"GB",
    "wof:name":"AB15 4UF",
    "wof:placetype":"postalcode"
},
  "geometry": {"coordinates":[-2.13582328696454,57.13661617058452],"type":"Point"}
}