{
  "type": "Feature",
  "properties": {
    "iso:country": "GB",
    "wof:name": "TA1 2BJ",
    "wof:placetype": "postalcode"
  },
  "geometry": {"coordinates":[-3.077212,51.019951],"type":"Point"}
}
