{
  "type": "Feature",
  "properties": {
    "iso:country":"GB",
    "wof:name":"BS4 4GH",
    "wof:placetype":"postalcode"
},
  "geometry": {"coordinates":[-2.55362028919722,51.45085883677998],"type":"Point"}
}