{
  "type": "Feature",
  "properties": {
    "date:inception_lower": "1998-06-01",
    "date:inception_upper": "1998-06-01",
    "iso:country": "GB",
    "wof:name": "BS4 4GH",
    "wof:placetype": "postalcode"
  },
  "geometry": {"coordinates":[-2.552861,51.451068],"type":"Point"}
}
