{
  "type": "Feature",
  "properties": {
    "iso:country":"GB",
    "wof:name":"CW10 0JZ",
    "wof:placetype":"postalcode"
},
  "geometry": {"coordinates":[-2.43114285178636,53.19512500486028],"type":"Point"}
}