{
  "type": "Feature",
  "properties": {
    "iso:country":"GB",
    "wof:name":"EH54 6DT",
    "wof:placetype":"postalcode"
},
  "geometry": {"coordinates":[-3.51478875416496,55.8975979349714],"type":"Point"}
}