{
  "type": "Feature",
  "properties": {
    "iso:country":"GB",
    "wof:name":"CF3 0DJ",
    "wof:placetype":"postalcode"
},
  "geometry": {"coordinates":[-3.10248091058099,51.52791683924888],"type":"Point"}
}