{
  "type": "Feature",
  "properties": {
    "date:inception_lower":"1992-01-01",
    "date:inception_upper":"1992-01-31",
    "iso:country":"GB",
    "wof:name":"CF3 0DJ",
    "wof:placetype":"postalcode"
},
  "geometry": {"coordinates":[-3.102481,51.527917],"type":"Point"}
}