{
  "type": "Feature",
  "properties": {
    "iso:country":"GB",
    "wof:name":"SM2 5RA",
    "wof:placetype":"postalcode"
},
  "geometry": {"coordinates":[-0.18595584550416,51.34503488019218],"type":"Point"}
}