{
  "type": "Feature",
  "properties": {
    "iso:country":"GB",
    "wof:name":"NP4 5DA",
    "wof:placetype":"postalcode"
},
  "geometry": {"coordinates":[-3.03320370705628,51.68072202302892],"type":"Point"}
}