{
  "type": "Feature",
  "properties": {
    "iso:country": "GB",
    "wof:name": "HX3 8TH",
    "wof:placetype": "postalcode"
  },
  "geometry": {"coordinates":[-1.792701,53.72456],"type":"Point"}
}
