{
  "type": "Feature",
  "properties": {
    "date:inception_lower": "2017-08-01",
    "date:inception_upper": "2017-08-01",
    "iso:country": "GB",
    "wof:name": "PL25 4FU",
    "wof:placetype": "postalcode"
  },
  "geometry": {"coordinates":[-4.772914,50.332745],"type":"Point"}
}
