{
  "type": "Feature",
  "properties": {
    "iso:country":"GB",
    "wof:name":"SP3 6PT",
    "wof:placetype":"postalcode"
},
  "geometry": {"coordinates":[-2.08126876891177,51.06773771669591],"type":"Point"}
}