{
  "type": "Feature",
  "properties": {
    "iso:country":"GB",
    "wof:name":"WV8 1UG",
    "wof:placetype":"postalcode"
},
  "geometry": {"coordinates":[-2.15989633995781,52.61963718686804],"type":"Point"}
}