{
  "type": "Feature",
  "properties": {
    "date:inception_lower": "2011-02-01",
    "date:inception_upper": "2011-02-01",
    "iso:country": "GB",
    "wof:name": "OL9 7PN",
    "wof:placetype": "postalcode"
  },
  "geometry": {"coordinates":[-2.141293,53.523905],"type":"Point"}
}
