{
  "type": "Feature",
  "properties": {
    "iso:country": "GB",
    "wof:name": "OL9 7PN",
    "wof:placetype": "postalcode"
  },
  "geometry": {"coordinates":[-2.141489,53.523851],"type":"Point"}
}
