{
  "type": "Feature",
  "properties": {
    "iso:country":"GB",
    "wof:name":"BR5 1JD",
    "wof:placetype":"postalcode"
},
  "geometry": {"coordinates":[0.08192885884225,51.38677631926646],"type":"Point"}
}