{
  "type": "Feature",
  "properties": {
    "iso:country": "GB",
    "wof:name": "LA3 2XE",
    "wof:placetype": "postalcode"
  },
  "geometry": {"coordinates":[-2.913786,54.033284],"type":"Point"}
}
