{
  "type": "Feature",
  "properties": {
    "iso:country":"GB",
    "wof:name":"DA17 5PZ",
    "wof:placetype":"postalcode"
},
  "geometry": {"coordinates":[0.14972582733778,51.49097641078894],"type":"Point"}
}