{
  "type": "Feature",
  "properties": {
    "date:inception_lower": "2022-04-01",
    "date:inception_upper": "2022-04-01",
    "iso:country": "GB",
    "wof:name": "EH19 3SH",
    "wof:placetype": "postalcode"
  },
  "geometry": {"coordinates":[-3.088636,55.877686],"type":"Point"}
}
