{
  "type": "Feature",
  "properties": {
    "date:inception_lower":"2004-06-01",
    "date:inception_upper":"2004-06-30",
    "iso:country":"GB",
    "wof:name":"WD19 4RA",
    "wof:placetype":"postalcode"
},
  "geometry": {"coordinates":[-0.390969,51.643804],"type":"Point"}
}