{
  "type": "Feature",
  "properties": {
    "iso:country":"GB",
    "wof:name":"WD19 4RA",
    "wof:placetype":"postalcode"
},
  "geometry": {"coordinates":[-0.3909692326884,51.64380392682755],"type":"Point"}
}