{
  "type": "Feature",
  "properties": {
    "iso:country":"GB",
    "wof:name":"EN5 4EF",
    "wof:placetype":"postalcode"
},
  "geometry": {"coordinates":[-0.21720781824713,51.65427011389443],"type":"Point"}
}