{
  "type": "Feature",
  "properties": {
    "date:inception_lower": "2009-02-01",
    "date:inception_upper": "2009-02-01",
    "iso:country": "GB",
    "wof:name": "DA12 1AG",
    "wof:placetype": "postalcode"
  },
  "geometry": {"coordinates":[0.377211,51.439235],"type":"Point"}
}
