{
  "type": "Feature",
  "properties": {
    "iso:country": "GB",
    "wof:name": "DA12 1AG",
    "wof:placetype": "postalcode"
  },
  "geometry": {"coordinates":[0.377211,51.439235],"type":"Point"}
}
