{
  "type": "Feature",
  "properties": {
    "iso:country":"GB",
    "wof:name":"CH43 2GJ",
    "wof:placetype":"postalcode"
},
  "geometry": {"coordinates":[-3.05627588139106,53.37918504919325],"type":"Point"}
}