{
  "type": "Feature",
  "properties": {
    "date:inception_lower": "2022-02-01",
    "date:inception_upper": "2022-02-01",
    "iso:country": "GB",
    "wof:name": "PR8 3FF",
    "wof:placetype": "postalcode"
  },
  "geometry": {"coordinates":[-3.024117,53.607456],"type":"Point"}
}
