{
  "type": "Feature",
  "properties": {
    "iso:country": "GB",
    "wof:name": "WD19 4AY",
    "wof:placetype": "postalcode"
  },
  "geometry": {"coordinates":[-0.381238,51.639066],"type":"Point"}
}
