{
  "type": "Feature",
  "properties": {
    "iso:country":"GB",
    "wof:name":"WD19 4AY",
    "wof:placetype":"postalcode"
},
  "geometry": {"coordinates":[-0.38123765051065,51.63906624041611],"type":"Point"}
}