{
  "type": "Feature",
  "properties": {
    "iso:country": "GB",
    "wof:name": "CV2 1GQ",
    "wof:placetype": "postalcode"
  },
  "geometry": {"coordinates":[-1.464477,52.442863],"type":"Point"}
}
