{
  "type": "Feature",
  "properties": {
    "iso:country":"GB",
    "wof:name":"CV2 1GQ",
    "wof:placetype":"postalcode"
},
  "geometry": {"coordinates":[-1.46447704393386,52.44286305271774],"type":"Point"}
}