{
  "type": "Feature",
  "properties": {
    "iso:country":"GB",
    "wof:name":"NE45 5PH",
    "wof:placetype":"postalcode"
},
  "geometry": {"coordinates":[-2.00600456041911,55.00516177474697],"type":"Point"}
}