{
  "type": "Feature",
  "properties": {
    "iso:country":"GB",
    "wof:name":"B15 3JF",
    "wof:placetype":"postalcode"
},
  "geometry": {"coordinates":[-1.9403878000078,52.46512290462329],"type":"Point"}
}