{
  "type": "Feature",
  "properties": {
    "iso:country": "GB",
    "wof:name": "G75 0NX",
    "wof:placetype": "postalcode"
  },
  "geometry": {"coordinates":[-4.169462,55.75388],"type":"Point"}
}
