{
  "type": "Feature",
  "properties": {
    "iso:country":"GB",
    "wof:name":"M11 4RY",
    "wof:placetype":"postalcode"
},
  "geometry": {"coordinates":[-2.17793910465332,53.48219641201675],"type":"Point"}
}