{
  "type": "Feature",
  "properties": {
    "date:inception_lower": "1980-01-01",
    "date:inception_upper": "1980-01-01",
    "iso:country": "GB",
    "wof:name": "M11 4RY",
    "wof:placetype": "postalcode"
  },
  "geometry": {"coordinates":[-2.177939,53.482196],"type":"Point"}
}
