{
  "type": "Feature",
  "properties": {
    "date:inception_lower": "2002-06-01",
    "date:inception_upper": "2002-06-01",
    "iso:country": "GB",
    "wof:name": "PE38 9UB",
    "wof:placetype": "postalcode"
  },
  "geometry": {"coordinates":[0.391231,52.60925],"type":"Point"}
}
