{
  "type": "Feature",
  "properties": {
    "iso:country":"GB",
    "wof:name":"PE38 9UB",
    "wof:placetype":"postalcode"
},
  "geometry": {"coordinates":[0.3912310490901,52.6092497910639],"type":"Point"}
}