{
  "type": "Feature",
  "properties": {
    "iso:country":"GB",
    "wof:name":"PL18 9QF",
    "wof:placetype":"postalcode"
},
  "geometry": {"coordinates":[-4.20609564049377,50.49716675795516],"type":"Point"}
}