{
  "type": "Feature",
  "properties": {
    "iso:country": "GB",
    "wof:name": "RH5 4TR",
    "wof:placetype": "postalcode"
  },
  "geometry": {"coordinates":[-0.316371,51.215411],"type":"Point"}
}
