{
  "type": "Feature",
  "properties": {
    "iso:country":"GB",
    "wof:name":"RH5 4TR",
    "wof:placetype":"postalcode"
},
  "geometry": {"coordinates":[-0.3163714830717,51.21541063219354],"type":"Point"}
}