{
  "type": "Feature",
  "properties": {
    "iso:country":"GB",
    "wof:name":"PE11 3NU",
    "wof:placetype":"postalcode"
},
  "geometry": {"coordinates":[-0.15717937809543,52.7997151653668],"type":"Point"}
}