{
  "type": "Feature",
  "properties": {
    "date:inception_lower": "1980-01-01",
    "date:inception_upper": "1980-01-01",
    "iso:country": "GB",
    "wof:name": "LS3 1JS",
    "wof:placetype": "postalcode"
  },
  "geometry": {"coordinates":[-1.569195,53.802381],"type":"Point"}
}
