{
  "type": "Feature",
  "properties": {
    "iso:country":"GB",
    "wof:name":"LS3 1JS",
    "wof:placetype":"postalcode"
},
  "geometry": {"coordinates":[-1.56919464040422,53.80238094879579],"type":"Point"}
}