{
  "type": "Feature",
  "properties": {
    "date:inception_lower": "2023-06-01",
    "date:inception_upper": "2023-06-01",
    "iso:country": "GB",
    "wof:name": "SL6 0FR",
    "wof:placetype": "postalcode"
  },
  "geometry": {"coordinates":[-0.657361,51.518363],"type":"Point"}
}
