{
  "type": "Feature",
  "properties": {
    "iso:country": "GB",
    "wof:name": "CV21 1TU",
    "wof:placetype": "postalcode"
  },
  "geometry": {"coordinates":[-1.235867,52.388484],"type":"Point"}
}
