{
  "type": "Feature",
  "properties": {
    "iso:country":"GB",
    "wof:name":"SM1 4NL",
    "wof:placetype":"postalcode"
},
  "geometry": {"coordinates":[-0.18338755106759,51.36350200971269],"type":"Point"}
}