{
  "type": "Feature",
  "properties": {
    "iso:country": "GB",
    "wof:name": "PO9 2TP",
    "wof:placetype": "postalcode"
  },
  "geometry": {"coordinates":[-0.969286,50.848355],"type":"Point"}
}
