{
  "type": "Feature",
  "properties": {
    "date:inception_lower": "1980-01-01",
    "date:inception_upper": "1980-01-01",
    "iso:country": "GB",
    "wof:name": "SY7 9HP",
    "wof:placetype": "postalcode"
  },
  "geometry": {"coordinates":[-2.682253,52.470088],"type":"Point"}
}
