{
  "type": "Feature",
  "properties": {
    "iso:country": "GB",
    "wof:name": "SY7 9HP",
    "wof:placetype": "postalcode"
  },
  "geometry": {"coordinates":[-2.686218,52.46747],"type":"Point"}
}
