{
  "type": "Feature",
  "properties": {
    "iso:country": "GB",
    "wof:name": "DN36 4YA",
    "wof:placetype": "postalcode"
  },
  "geometry": {"coordinates":[-0.06622,53.523726],"type":"Point"}
}
