{
  "type": "Feature",
  "properties": {
    "iso:country": "GB",
    "wof:name": "NN4 4GD",
    "wof:placetype": "postalcode"
  },
  "geometry": {"coordinates":[-0.898231,52.245285],"type":"Point"}
}
