{
  "type": "Feature",
  "properties": {
    "iso:country":"GB",
    "wof:name":"KT17 3AR",
    "wof:placetype":"postalcode"
},
  "geometry": {"coordinates":[-0.23432071534568,51.32102614076384],"type":"Point"}
}