{
  "type": "Feature",
  "properties": {
    "date:inception_lower": "1994-12-01",
    "date:inception_upper": "1994-12-01",
    "iso:country": "GB",
    "wof:name": "SO45 5AA",
    "wof:placetype": "postalcode"
  },
  "geometry": {"coordinates":[-1.408385,50.869679],"type":"Point"}
}
