{
  "type": "Feature",
  "properties": {
    "iso:country":"GB",
    "wof:name":"SO45 5AA",
    "wof:placetype":"postalcode"
},
  "geometry": {"coordinates":[-1.40838522320518,50.86967890595014],"type":"Point"}
}