{
  "type": "Feature",
  "properties": {
    "iso:country":"GB",
    "wof:name":"CF24 4SQ",
    "wof:placetype":"postalcode"
},
  "geometry": {"coordinates":[-3.17442073053662,51.49621456746679],"type":"Point"}
}