{
  "type": "Feature",
  "properties": {
    "iso:country":"GB",
    "wof:name":"WN2 2DF",
    "wof:placetype":"postalcode"
},
  "geometry": {"coordinates":[-2.60850138545207,53.53993244393369],"type":"Point"}
}