{
  "type": "Feature",
  "properties": {
    "iso:country":"GB",
    "wof:name":"TN40 1NQ",
    "wof:placetype":"postalcode"
},
  "geometry": {"coordinates":[0.48304582729714,50.83955438387427],"type":"Point"}
}