{
  "type": "Feature",
  "properties": {
    "date:inception_lower":"1981-06-01",
    "date:inception_upper":"1981-06-30",
    "iso:country":"GB",
    "wof:name":"NG12 3QQ",
    "wof:placetype":"postalcode"
},
  "geometry": {"coordinates":[-1.042674,52.904149],"type":"Point"}
}