{
  "type": "Feature",
  "properties": {
    "iso:country": "GB",
    "wof:name": "HX7 7PA",
    "wof:placetype": "postalcode"
  },
  "geometry": {"coordinates":[-2.023119,53.74943],"type":"Point"}
}
