{
  "type": "Feature",
  "properties": {
    "date:inception_lower": "2022-06-01",
    "date:inception_upper": "2022-06-01",
    "iso:country": "GB",
    "wof:name": "SK11 7JH",
    "wof:placetype": "postalcode"
  },
  "geometry": {"coordinates":[-2.12455,53.256982],"type":"Point"}
}
