{
  "type": "Feature",
  "properties": {
    "date:inception_lower": "2017-10-01",
    "date:inception_upper": "2017-10-01",
    "iso:country": "GB",
    "wof:name": "YO62 7JA",
    "wof:placetype": "postalcode"
  },
  "geometry": {"coordinates":[-0.956225,54.279615],"type":"Point"}
}
