{
  "type": "Feature",
  "properties": {
    "iso:country": "GB",
    "wof:name": "MK3 5LA",
    "wof:placetype": "postalcode"
  },
  "geometry": {"coordinates":[-0.776455,51.988438],"type":"Point"}
}
