{
  "type": "Feature",
  "properties": {
    "date:inception_lower": "1980-01-01",
    "date:inception_upper": "1980-01-01",
    "iso:country": "GB",
    "wof:name": "MK3 5LA",
    "wof:placetype": "postalcode"
  },
  "geometry": {"coordinates":[-0.779038,51.988258],"type":"Point"}
}
