{
  "type": "Feature",
  "properties": {
    "iso:country":"GB",
    "wof:name":"MK3 5LA",
    "wof:placetype":"postalcode"
},
  "geometry": {"coordinates":[-0.77647612556773,51.98842886790601],"type":"Point"}
}