{
  "type": "Feature",
  "properties": {
    "date:inception_lower": "2007-05-01",
    "date:inception_upper": "2007-05-01",
    "iso:country": "GB",
    "wof:name": "DT4 0FD",
    "wof:placetype": "postalcode"
  },
  "geometry": {"coordinates":[-2.464083,50.616576],"type":"Point"}
}
