{
  "type": "Feature",
  "properties": {
    "iso:country":"GB",
    "wof:name":"DN32 0PY",
    "wof:placetype":"postalcode"
},
  "geometry": {"coordinates":[-0.08014468675223,53.55406669427018],"type":"Point"}
}