{
  "type": "Feature",
  "properties": {
    "date:inception_lower": "2016-09-01",
    "date:inception_upper": "2016-09-01",
    "iso:country": "GB",
    "wof:name": "SO31 6BT",
    "wof:placetype": "postalcode"
  },
  "geometry": {"coordinates":[-1.287394,50.862339],"type":"Point"}
}
