{
  "type": "Feature",
  "properties": {
    "iso:country":"GB",
    "wof:name":"MK16 8QB",
    "wof:placetype":"postalcode"
},
  "geometry": {"coordinates":[-0.74524510258374,52.08608598097449],"type":"Point"}
}