{
  "type": "Feature",
  "properties": {
    "iso:country": "GB",
    "wof:name": "MK16 8QB",
    "wof:placetype": "postalcode"
  },
  "geometry": {"coordinates":[-0.745245,52.086086],"type":"Point"}
}
