{
  "type": "Feature",
  "properties": {
    "iso:country":"GB",
    "wof:name":"G45 9SF",
    "wof:placetype":"postalcode"
},
  "geometry": {"coordinates":[-4.24606687369192,55.80924115736316],"type":"Point"}
}