{
  "type": "Feature",
  "properties": {
    "iso:country":"GB",
    "wof:name":"PE31 7AH",
    "wof:placetype":"postalcode"
},
  "geometry": {"coordinates":[0.48340221764812,52.91164348011301],"type":"Point"}
}