{
  "type": "Feature",
  "properties": {
    "date:inception_lower": "1980-01-01",
    "date:inception_upper": "1980-01-01",
    "iso:country": "GB",
    "wof:name": "PE31 7AH",
    "wof:placetype": "postalcode"
  },
  "geometry": {"coordinates":[0.483402,52.911643],"type":"Point"}
}
