{
  "type": "Feature",
  "properties": {
    "iso:country":"GB",
    "wof:name":"NR33 8RB",
    "wof:placetype":"postalcode"
},
  "geometry": {"coordinates":[1.69930846306936,52.46084154030077],"type":"Point"}
}