{
  "type": "Feature",
  "properties": {
    "date:inception_lower": "1985-04-01",
    "date:inception_upper": "1985-04-01",
    "iso:country": "GB",
    "wof:name": "NR33 8RB",
    "wof:placetype": "postalcode"
  },
  "geometry": {"coordinates":[1.699309,52.460842],"type":"Point"}
}
