{
  "type": "Feature",
  "properties": {
    "date:inception_lower": "2020-02-01",
    "date:inception_upper": "2020-02-01",
    "iso:country": "GB",
    "wof:name": "SW9 1EB",
    "wof:placetype": "postalcode"
  },
  "geometry": {"coordinates":[-0.113562,51.468675],"type":"Point"}
}
