{
  "type": "Feature",
  "properties": {
    "iso:country":"GB",
    "wof:name":"TQ1 3NL",
    "wof:placetype":"postalcode"
},
  "geometry": {"coordinates":[-3.52211814874221,50.47927237164242],"type":"Point"}
}