{
  "type": "Feature",
  "properties": {
    "iso:country": "GB",
    "wof:name": "NR5 8NE",
    "wof:placetype": "postalcode"
  },
  "geometry": {"coordinates":[1.234746,52.632651],"type":"Point"}
}
