{
  "type": "Feature",
  "properties": {
    "iso:country":"GB",
    "wof:name":"NR5 8NE",
    "wof:placetype":"postalcode"
},
  "geometry": {"coordinates":[1.23474595610305,52.63265094803429],"type":"Point"}
}