{
  "type": "Feature",
  "properties": {
    "iso:country": "GB",
    "wof:name": "L6 8NA",
    "wof:placetype": "postalcode"
  },
  "geometry": {"coordinates":[-2.939834,53.414191],"type":"Point"}
}
