{
  "type": "Feature",
  "properties": {
    "date:inception_lower":"1980-01-01",
    "date:inception_upper":"1980-01-31",
    "iso:country":"GB",
    "wof:name":"LL11 3HR",
    "wof:placetype":"postalcode"
},
  "geometry": {"coordinates":[-3.061502,53.054977],"type":"Point"}
}