{
  "type": "Feature",
  "properties": {
    "iso:country":"GB",
    "wof:name":"LL11 3HR",
    "wof:placetype":"postalcode"
},
  "geometry": {"coordinates":[-3.06150217641266,53.05497661578661],"type":"Point"}
}