{
  "type": "Feature",
  "properties": {
    "date:inception_lower": "2015-11-01",
    "date:inception_upper": "2015-11-01",
    "iso:country": "GB",
    "wof:name": "NE24 4TT",
    "wof:placetype": "postalcode"
  },
  "geometry": {"coordinates":[-1.538875,55.103934],"type":"Point"}
}
