{
  "type": "Feature",
  "properties": {
    "iso:country":"GB",
    "wof:name":"NE24 4TT",
    "wof:placetype":"postalcode"
},
  "geometry": {"coordinates":[-1.53925074471793,55.10405510895672],"type":"Point"}
}