{
  "type": "Feature",
  "properties": {
    "date:inception_lower": "1987-04-01",
    "date:inception_upper": "1987-04-01",
    "iso:country": "GB",
    "wof:name": "IP28 8BW",
    "wof:placetype": "postalcode"
  },
  "geometry": {"coordinates":[0.496872,52.373696],"type":"Point"}
}
