{
  "type": "Feature",
  "properties": {
    "iso:country":"GB",
    "wof:name":"IV32 7HL",
    "wof:placetype":"postalcode"
},
  "geometry": {"coordinates":[-3.09955085651313,57.61319806017421],"type":"Point"}
}