{
  "type": "Feature",
  "properties": {
    "date:inception_lower": "1980-01-01",
    "date:inception_upper": "1980-01-01",
    "iso:country": "GB",
    "wof:name": "IV32 7HL",
    "wof:placetype": "postalcode"
  },
  "geometry": {"coordinates":[-3.09955,57.613182],"type":"Point"}
}
