{
  "type": "Feature",
  "properties": {
    "date:inception_lower": "1980-01-01",
    "date:inception_upper": "1980-01-01",
    "iso:country": "GB",
    "wof:name": "GL53 0DA",
    "wof:placetype": "postalcode"
  },
  "geometry": {"coordinates":[-2.077318,51.879995],"type":"Point"}
}
