{
  "type": "Feature",
  "properties": {
    "iso:country":"GB",
    "wof:name":"YO10 3WL",
    "wof:placetype":"postalcode"
},
  "geometry": {"coordinates":[-1.0698748729808,53.9547482026366],"type":"Point"}
}