{
  "type": "Feature",
  "properties": {
    "iso:country": "GB",
    "wof:name": "YO10 3WL",
    "wof:placetype": "postalcode"
  },
  "geometry": {"coordinates":[-1.069875,53.954748],"type":"Point"}
}
