{
  "type": "Feature",
  "properties": {
    "date:inception_lower": "1980-01-01",
    "date:inception_upper": "1980-01-01",
    "iso:country": "GB",
    "wof:name": "CW12 1HF",
    "wof:placetype": "postalcode"
  },
  "geometry": {"coordinates":[-2.216185,53.165039],"type":"Point"}
}
