{
  "type": "Feature",
  "properties": {
    "date:inception_lower":"1994-12-01",
    "date:inception_upper":"1994-12-31",
    "iso:country":"GB",
    "wof:name":"LS5 3RL",
    "wof:placetype":"postalcode"
},
  "geometry": {"coordinates":[-1.596128,53.816864],"type":"Point"}
}