{
  "type": "Feature",
  "properties": {
    "iso:country":"GB",
    "wof:name":"SG8 0EA",
    "wof:placetype":"postalcode"
},
  "geometry": {"coordinates":[-0.09954107120979,52.13142138629243],"type":"Point"}
}