{
  "type": "Feature",
  "properties": {
    "iso:country":"GB",
    "wof:name":"BS24 9NQ",
    "wof:placetype":"postalcode"
},
  "geometry": {"coordinates":[-2.96072689683843,51.3198421484981],"type":"Point"}
}