{
  "type": "Feature",
  "properties": {
    "iso:country":"GB",
    "wof:name":"WA16 7LD",
    "wof:placetype":"postalcode"
},
  "geometry": {"coordinates":[-2.29673759546907,53.31526677121899],"type":"Point"}
}