{
  "type": "Feature",
  "properties": {
    "date:inception_lower": "1980-01-01",
    "date:inception_upper": "1980-01-01",
    "iso:country": "GB",
    "wof:name": "LL13 7BN",
    "wof:placetype": "postalcode"
  },
  "geometry": {"coordinates":[-2.98525,53.034211],"type":"Point"}
}
