{
  "type": "Feature",
  "properties": {
    "iso:country":"GB",
    "wof:name":"AL5 3PX",
    "wof:placetype":"postalcode"
},
  "geometry": {"coordinates":[-0.41164114026288,51.83162939332208],"type":"Point"}
}