{
  "type": "Feature",
  "properties": {
    "iso:country": "GB",
    "wof:name": "CV36 4LN",
    "wof:placetype": "postalcode"
  },
  "geometry": {"coordinates":[-1.689525,52.092447],"type":"Point"}
}
