{
  "type": "Feature",
  "properties": {
    "iso:country":"GB",
    "wof:name":"NP23 7SA",
    "wof:placetype":"postalcode"
},
  "geometry": {"coordinates":[-3.17973296914722,51.74055608456332],"type":"Point"}
}