{
  "type": "Feature",
  "properties": {
    "date:inception_lower": "1999-06-01",
    "date:inception_upper": "1999-06-01",
    "iso:country": "GB",
    "wof:name": "NP23 7SA",
    "wof:placetype": "postalcode"
  },
  "geometry": {"coordinates":[-3.179733,51.740556],"type":"Point"}
}
