{
  "type": "Feature",
  "properties": {
    "date:inception_lower": "1980-01-01",
    "date:inception_upper": "1980-01-01",
    "iso:country": "GB",
    "wof:name": "DA16 2DH",
    "wof:placetype": "postalcode"
  },
  "geometry": {"coordinates":[0.106933,51.46142],"type":"Point"}
}
