{
  "type": "Feature",
  "properties": {
    "iso:country":"GB",
    "wof:name":"N11 3DX",
    "wof:placetype":"postalcode"
},
  "geometry": {"coordinates":[-0.15142009778423,51.61435208172499],"type":"Point"}
}