{
  "type": "Feature",
  "properties": {
    "date:inception_lower": "1980-01-01",
    "date:inception_upper": "1980-01-01",
    "iso:country": "GB",
    "wof:name": "N11 3DX",
    "wof:placetype": "postalcode"
  },
  "geometry": {"coordinates":[-0.151457,51.61423],"type":"Point"}
}
