{
  "type": "Feature",
  "properties": {
    "iso:country":"GB",
    "wof:name":"BH16 5FB",
    "wof:placetype":"postalcode"
},
  "geometry": {"coordinates":[-2.03111038010425,50.7383078356379],"type":"Point"}
}