{
  "type": "Feature",
  "properties": {
    "iso:country": "GB",
    "wof:name": "BH16 5FB",
    "wof:placetype": "postalcode"
  },
  "geometry": {"coordinates":[-2.03111,50.738308],"type":"Point"}
}
