{
  "type": "Feature",
  "properties": {
    "date:inception_lower":"2015-02-01",
    "date:inception_upper":"2015-02-28",
    "iso:country":"GB",
    "wof:name":"BH16 5FB",
    "wof:placetype":"postalcode"
},
  "geometry": {"coordinates":[-2.03111,50.738308],"type":"Point"}
}