{
  "type": "Feature",
  "properties": {
    "iso:country":"GB",
    "wof:name":"SL7 2PE",
    "wof:placetype":"postalcode"
},
  "geometry": {"coordinates":[-0.78403210775521,51.57216449177523],"type":"Point"}
}