{
  "type": "Feature",
  "properties": {
    "iso:country":"GB",
    "wof:name":"G67 4BW",
    "wof:placetype":"postalcode"
},
  "geometry": {"coordinates":[-3.99279897368156,55.93872288202096],"type":"Point"}
}