{
  "type": "Feature",
  "properties": {
    "iso:country":"GB",
    "wof:name":"NG8 4PL",
    "wof:placetype":"postalcode"
},
  "geometry": {"coordinates":[-1.23043970205573,52.9637916426056],"type":"Point"}
}