{
  "type": "Feature",
  "properties": {
    "date:inception_lower": "1980-01-01",
    "date:inception_upper": "1980-01-01",
    "iso:country": "GB",
    "wof:name": "NG8 4PL",
    "wof:placetype": "postalcode"
  },
  "geometry": {"coordinates":[-1.23044,52.963792],"type":"Point"}
}
