{
  "type": "Feature",
  "properties": {
    "iso:country":"GB",
    "wof:name":"WD23 3LH",
    "wof:placetype":"postalcode"
},
  "geometry": {"coordinates":[-0.35921708395203,51.64497413749746],"type":"Point"}
}