{
  "type": "Feature",
  "properties": {
    "iso:country": "GB",
    "wof:name": "WR1 3AJ",
    "wof:placetype": "postalcode"
  },
  "geometry": {"coordinates":[-2.229727,52.202994],"type":"Point"}
}
