{
  "type": "Feature",
  "properties": {
    "iso:country":"GB",
    "wof:name":"WR1 3AJ",
    "wof:placetype":"postalcode"
},
  "geometry": {"coordinates":[-2.22972717680537,52.2029937446333],"type":"Point"}
}