{
  "type": "Feature",
  "properties": {
    "iso:country":"GB",
    "wof:name":"NE32 5SA",
    "wof:placetype":"postalcode"
},
  "geometry": {"coordinates":[-1.49457010124871,54.97696574569968],"type":"Point"}
}