{
  "type": "Feature",
  "properties": {
    "date:inception_lower": "1980-01-01",
    "date:inception_upper": "1980-01-01",
    "iso:country": "GB",
    "wof:name": "NE32 5SA",
    "wof:placetype": "postalcode"
  },
  "geometry": {"coordinates":[-1.49457,54.976966],"type":"Point"}
}
