{
  "type": "Feature",
  "properties": {
    "iso:country":"GB",
    "wof:name":"DL5 7PP",
    "wof:placetype":"postalcode"
},
  "geometry": {"coordinates":[-1.58883174306882,54.62835594806083],"type":"Point"}
}