{
  "type": "Feature",
  "properties": {
    "iso:country": "GB",
    "wof:name": "CA23 3AS",
    "wof:placetype": "postalcode"
  },
  "geometry": {"coordinates":[-3.421648,54.52619],"type":"Point"}
}
