{
  "type": "Feature",
  "properties": {
    "date:inception_lower": "1980-01-01",
    "date:inception_upper": "1980-01-01",
    "iso:country": "GB",
    "wof:name": "BH15 3DZ",
    "wof:placetype": "postalcode"
  },
  "geometry": {"coordinates":[-1.977448,50.72903],"type":"Point"}
}
