{
  "type": "Feature",
  "properties": {
    "iso:country":"GB",
    "wof:name":"BH15 3DZ",
    "wof:placetype":"postalcode"
},
  "geometry": {"coordinates":[-1.97744843786495,50.7290295122955],"type":"Point"}
}