{
  "type": "Feature",
  "properties": {
    "date:inception_lower":"2014-07-01",
    "date:inception_upper":"2014-07-31",
    "iso:country":"GB",
    "wof:name":"BD3 7FF",
    "wof:placetype":"postalcode"
},
  "geometry": {"coordinates":[-1.702675,53.797753],"type":"Point"}
}