{
  "type": "Feature",
  "properties": {
    "iso:country": "GB",
    "wof:name": "BD3 7FF",
    "wof:placetype": "postalcode"
  },
  "geometry": {"coordinates":[-1.702675,53.797753],"type":"Point"}
}
