{
  "type": "Feature",
  "properties": {
    "iso:country": "GB",
    "wof:name": "G74 2EQ",
    "wof:placetype": "postalcode"
  },
  "geometry": {"coordinates":[-4.164145,55.760022],"type":"Point"}
}
