{
  "type": "Feature",
  "properties": {
    "date:inception_lower": "1980-01-01",
    "date:inception_upper": "1980-01-01",
    "iso:country": "GB",
    "wof:name": "G74 2EQ",
    "wof:placetype": "postalcode"
  },
  "geometry": {"coordinates":[-4.164145,55.760022],"type":"Point"}
}
