{
  "type": "Feature",
  "properties": {
    "iso:country":"GB",
    "wof:name":"PL1 4PQ",
    "wof:placetype":"postalcode"
},
  "geometry": {"coordinates":[-4.1801878197345,50.37418986679971],"type":"Point"}
}