{
  "type": "Feature",
  "properties": {
    "iso:country":"GB",
    "wof:name":"IG1 2PZ",
    "wof:placetype":"postalcode"
},
  "geometry": {"coordinates":[0.08675275249139,51.5479052194747],"type":"Point"}
}