{
  "type": "Feature",
  "properties": {
    "iso:country":"GB",
    "wof:name":"PL1 3JE",
    "wof:placetype":"postalcode"
},
  "geometry": {"coordinates":[-4.15698729139977,50.37059317130993],"type":"Point"}
}