{
  "type": "Feature",
  "properties": {
    "iso:country":"GB",
    "wof:name":"N11 1JY",
    "wof:placetype":"postalcode"
},
  "geometry": {"coordinates":[-0.14267856870506,51.61831461347723],"type":"Point"}
}