{
  "type": "Feature",
  "properties": {
    "date:inception_lower": "2022-08-01",
    "date:inception_upper": "2022-08-01",
    "iso:country": "GB",
    "wof:name": "ME20 7WQ",
    "wof:placetype": "postalcode"
  },
  "geometry": {"coordinates":[0.475418,51.290247],"type":"Point"}
}
