{
  "type": "Feature",
  "properties": {
    "iso:country": "GB",
    "wof:name": "PA16 7LY",
    "wof:placetype": "postalcode"
  },
  "geometry": {"coordinates":[-4.801453,55.944183],"type":"Point"}
}
