{
  "type": "Feature",
  "properties": {
    "iso:country":"GB",
    "wof:name":"CO6 2HJ",
    "wof:placetype":"postalcode"
},
  "geometry": {"coordinates":[0.69374173470913,51.9501755982183],"type":"Point"}
}