{
  "type": "Feature",
  "properties": {
    "iso:country": "GB",
    "wof:name": "SE17 2EF",
    "wof:placetype": "postalcode"
  },
  "geometry": {"coordinates":[-0.088238,51.487823],"type":"Point"}
}
