{
  "type": "Feature",
  "properties": {
    "iso:country":"GB",
    "wof:name":"SE17 2EF",
    "wof:placetype":"postalcode"
},
  "geometry": {"coordinates":[-0.08823823511999,51.48782254833316],"type":"Point"}
}