{
  "type": "Feature",
  "properties": {
    "iso:country":"GB",
    "wof:name":"LA5 0BQ",
    "wof:placetype":"postalcode"
},
  "geometry": {"coordinates":[-2.84837381568718,54.19393176930528],"type":"Point"}
}