{
  "type": "Feature",
  "properties": {
    "iso:country": "GB",
    "wof:name": "LA5 0BQ",
    "wof:placetype": "postalcode"
  },
  "geometry": {"coordinates":[-2.848374,54.193932],"type":"Point"}
}
