{
  "type": "Feature",
  "properties": {
    "iso:country":"GB",
    "wof:name":"SS7 1HE",
    "wof:placetype":"postalcode"
},
  "geometry": {"coordinates":[0.57200634995197,51.55714527423439],"type":"Point"}
}