{
  "type": "Feature",
  "properties": {
    "iso:country":"GB",
    "wof:name":"SN16 0BP",
    "wof:placetype":"postalcode"
},
  "geometry": {"coordinates":[-2.10472778447473,51.58788177153812],"type":"Point"}
}