{
  "type": "Feature",
  "properties": {
    "iso:country": "GB",
    "wof:name": "BB7 1JB",
    "wof:placetype": "postalcode"
  },
  "geometry": {"coordinates":[-2.381835,53.870197],"type":"Point"}
}
