{
  "type": "Feature",
  "properties": {
    "iso:country":"GB",
    "wof:name":"BB7 1JB",
    "wof:placetype":"postalcode"
},
  "geometry": {"coordinates":[-2.38183498301449,53.87019742479069],"type":"Point"}
}