{
  "type": "Feature",
  "properties": {
    "iso:country":"GB",
    "wof:name":"SK16 4LS",
    "wof:placetype":"postalcode"
},
  "geometry": {"coordinates":[-2.09345147826756,53.47682754848991],"type":"Point"}
}