{
  "type": "Feature",
  "properties": {
    "date:inception_lower": "2015-12-01",
    "date:inception_upper": "2015-12-01",
    "iso:country": "GB",
    "wof:name": "SK16 4LS",
    "wof:placetype": "postalcode"
  },
  "geometry": {"coordinates":[-2.095108,53.476637],"type":"Point"}
}
