{
  "type": "Feature",
  "properties": {
    "iso:country":"GB",
    "wof:name":"KT14 6PW",
    "wof:placetype":"postalcode"
},
  "geometry": {"coordinates":[-0.49315597071934,51.34000130549061],"type":"Point"}
}