{
  "type": "Feature",
  "properties": {
    "iso:country": "GB",
    "wof:name": "IP24 2JL",
    "wof:placetype": "postalcode"
  },
  "geometry": {"coordinates":[0.762368,52.420744],"type":"Point"}
}
