{
  "type": "Feature",
  "properties": {
    "iso:country":"GB",
    "wof:name":"NR24 2PF",
    "wof:placetype":"postalcode"
},
  "geometry": {"coordinates":[1.01580631236705,52.88907069842428],"type":"Point"}
}