{
  "type": "Feature",
  "properties": {
    "date:inception_lower":"1980-01-01",
    "date:inception_upper":"1980-01-31",
    "iso:country":"GB",
    "wof:name":"NR24 2PF",
    "wof:placetype":"postalcode"
},
  "geometry": {"coordinates":[1.015806,52.889071],"type":"Point"}
}