{
  "type": "Feature",
  "properties": {
    "iso:country":"GB",
    "wof:name":"NR15 2RD",
    "wof:placetype":"postalcode"
},
  "geometry": {"coordinates":[1.26088422424094,52.50965650710458],"type":"Point"}
}