{
  "type": "Feature",
  "properties": {
    "iso:country":"GB",
    "wof:name":"PR4 1EL",
    "wof:placetype":"postalcode"
},
  "geometry": {"coordinates":[-2.89923450640774,53.74893367696909],"type":"Point"}
}