{
  "type": "Feature",
  "properties": {
    "iso:country": "GB",
    "wof:name": "DE13 8PR",
    "wof:placetype": "postalcode"
  },
  "geometry": {"coordinates":[-1.800962,52.77197],"type":"Point"}
}
