{
  "type": "Feature",
  "properties": {
    "iso:country":"GB",
    "wof:name":"B27 6BN",
    "wof:placetype":"postalcode"
},
  "geometry": {"coordinates":[-1.81992417631233,52.44758749697999],"type":"Point"}
}