{
  "type": "Feature",
  "properties": {
    "iso:country":"GB",
    "wof:name":"SW19 8DT",
    "wof:placetype":"postalcode"
},
  "geometry": {"coordinates":[-0.1974127223269,51.43687345425884],"type":"Point"}
}