{
  "type": "Feature",
  "properties": {
    "date:inception_lower": "1980-01-01",
    "date:inception_upper": "1980-01-01",
    "iso:country": "GB",
    "wof:name": "SW19 8DT",
    "wof:placetype": "postalcode"
  },
  "geometry": {"coordinates":[-0.197413,51.436873],"type":"Point"}
}
