{
  "type": "Feature",
  "properties": {
    "date:inception_lower": "1980-01-01",
    "date:inception_upper": "1980-01-01",
    "iso:country": "GB",
    "wof:name": "LA6 3BQ",
    "wof:placetype": "postalcode"
  },
  "geometry": {"coordinates":[-2.466828,54.15186],"type":"Point"}
}
