{
  "type": "Feature",
  "properties": {
    "iso:country":"GB",
    "wof:name":"LA6 3BQ",
    "wof:placetype":"postalcode"
},
  "geometry": {"coordinates":[-2.46682847168417,54.15185972129475],"type":"Point"}
}