{
  "type": "Feature",
  "properties": {
    "iso:country":"GB",
    "wof:name":"FK4 2DA",
    "wof:placetype":"postalcode"
},
  "geometry": {"coordinates":[-3.89371427127743,55.99469086776289],"type":"Point"}
}