{
  "type": "Feature",
  "properties": {
    "date:inception_lower": "1980-01-01",
    "date:inception_upper": "1980-01-01",
    "iso:country": "GB",
    "wof:name": "FK4 2DA",
    "wof:placetype": "postalcode"
  },
  "geometry": {"coordinates":[-3.893714,55.994691],"type":"Point"}
}
