{
  "type": "Feature",
  "properties": {
    "iso:country": "GB",
    "wof:name": "HG1 3AA",
    "wof:placetype": "postalcode"
  },
  "geometry": {"coordinates":[-1.538446,54.007556],"type":"Point"}
}
