{
  "type": "Feature",
  "properties": {
    "iso:country":"GB",
    "wof:name":"HG1 3AA",
    "wof:placetype":"postalcode"
},
  "geometry": {"coordinates":[-1.53834877304293,54.0075494949177],"type":"Point"}
}