{
  "type": "Feature",
  "properties": {
    "date:inception_lower": "1980-01-01",
    "date:inception_upper": "1980-01-01",
    "iso:country": "GB",
    "wof:name": "HG1 3AA",
    "wof:placetype": "postalcode"
  },
  "geometry": {"coordinates":[-1.538354,54.007565],"type":"Point"}
}
