{
  "type": "Feature",
  "properties": {
    "iso:country": "GB",
    "wof:name": "YO30 2AH",
    "wof:placetype": "postalcode"
  },
  "geometry": {"coordinates":[-1.275433,54.041421],"type":"Point"}
}
