{
  "type": "Feature",
  "properties": {
    "date:inception_lower":"1980-01-01",
    "date:inception_upper":"1980-01-31",
    "iso:country":"GB",
    "wof:name":"BN17 7PQ",
    "wof:placetype":"postalcode"
},
  "geometry": {"coordinates":[-0.542274,50.825664],"type":"Point"}
}