{
  "type": "Feature",
  "properties": {
    "date:inception_lower":"1980-01-01",
    "date:inception_upper":"1980-01-31",
    "iso:country":"GB",
    "wof:name":"L31 6AJ",
    "wof:placetype":"postalcode"
},
  "geometry": {"coordinates":[-2.928651,53.513335],"type":"Point"}
}