{
  "type": "Feature",
  "properties": {
    "iso:country": "GB",
    "wof:name": "L31 6AJ",
    "wof:placetype": "postalcode"
  },
  "geometry": {"coordinates":[-2.928651,53.513335],"type":"Point"}
}
