{
  "type": "Feature",
  "properties": {
    "iso:country":"GB",
    "wof:name":"TS25 4PB",
    "wof:placetype":"postalcode"
},
  "geometry": {"coordinates":[-1.24410624061954,54.67197183206709],"type":"Point"}
}