{
  "type": "Feature",
  "properties": {
    "iso:country": "GB",
    "wof:name": "GU51 4HF",
    "wof:placetype": "postalcode"
  },
  "geometry": {"coordinates":[-0.861696,51.282521],"type":"Point"}
}
