{
  "type": "Feature",
  "properties": {
    "iso:country": "GB",
    "wof:name": "TN5 7JG",
    "wof:placetype": "postalcode"
  },
  "geometry": {"coordinates":[0.383364,51.049483],"type":"Point"}
}
