{
  "type": "Feature",
  "properties": {
    "iso:country":"GB",
    "wof:name":"LU2 0TP",
    "wof:placetype":"postalcode"
},
  "geometry": {"coordinates":[-0.41489216004645,51.88534485258845],"type":"Point"}
}