{
  "type": "Feature",
  "properties": {
    "iso:country": "GB",
    "wof:name": "LU2 0TP",
    "wof:placetype": "postalcode"
  },
  "geometry": {"coordinates":[-0.414892,51.885345],"type":"Point"}
}
