{
  "type": "Feature",
  "properties": {
    "date:inception_lower": "1980-01-01",
    "date:inception_upper": "1980-01-01",
    "iso:country": "GB",
    "wof:name": "FY6 8AQ",
    "wof:placetype": "postalcode"
  },
  "geometry": {"coordinates":[-2.996162,53.841592],"type":"Point"}
}
