{
  "type": "Feature",
  "properties": {
    "iso:country": "GB",
    "wof:name": "NE31 2TF",
    "wof:placetype": "postalcode"
  },
  "geometry": {"coordinates":[-1.519802,54.966446],"type":"Point"}
}
