{
  "type": "Feature",
  "properties": {
    "iso:country":"GB",
    "wof:name":"NE31 2TF",
    "wof:placetype":"postalcode"
},
  "geometry": {"coordinates":[-1.51980246991343,54.96644610958624],"type":"Point"}
}