{
  "type": "Feature",
  "properties": {
    "date:inception_lower": "2016-10-01",
    "date:inception_upper": "2016-10-01",
    "iso:country": "GB",
    "wof:name": "CW9 8GX",
    "wof:placetype": "postalcode"
  },
  "geometry": {"coordinates":[-2.514923,53.224318],"type":"Point"}
}
