{
  "type": "Feature",
  "properties": {
    "iso:country":"GB",
    "wof:name":"LE12 6TE",
    "wof:placetype":"postalcode"
},
  "geometry": {"coordinates":[-1.05565378807912,52.82339000477001],"type":"Point"}
}