{
  "type": "Feature",
  "properties": {
    "iso:country":"GB",
    "wof:name":"DD4 9HH",
    "wof:placetype":"postalcode"
},
  "geometry": {"coordinates":[-2.9416853834538,56.49106855384295],"type":"Point"}
}