{
  "type": "Feature",
  "properties": {
    "iso:country":"GB",
    "wof:name":"KT4 7FD",
    "wof:placetype":"postalcode"
},
  "geometry": {"coordinates":[-0.248006063913,51.37991747756804],"type":"Point"}
}