{
  "type": "Feature",
  "properties": {
    "date:inception_lower": "2013-02-01",
    "date:inception_upper": "2013-02-01",
    "iso:country": "GB",
    "wof:name": "KT4 7FD",
    "wof:placetype": "postalcode"
  },
  "geometry": {"coordinates":[-0.248024,51.379935],"type":"Point"}
}
