{
  "type": "Feature",
  "properties": {
    "iso:country":"GB",
    "wof:name":"BS5 9JY",
    "wof:placetype":"postalcode"
},
  "geometry": {"coordinates":[-2.559221999103,51.45822335989682],"type":"Point"}
}