{
  "type": "Feature",
  "properties": {
    "iso:country": "GB",
    "wof:name": "BS5 9JY",
    "wof:placetype": "postalcode"
  },
  "geometry": {"coordinates":[-2.559222,51.458223],"type":"Point"}
}
