{
  "type": "Feature",
  "properties": {
    "date:inception_lower": "1980-01-01",
    "date:inception_upper": "1980-01-01",
    "iso:country": "GB",
    "wof:name": "BS5 9JY",
    "wof:placetype": "postalcode"
  },
  "geometry": {"coordinates":[-2.559222,51.458223],"type":"Point"}
}
