{
  "type": "Feature",
  "properties": {
    "iso:country": "GB",
    "wof:name": "TA11 6EY",
    "wof:placetype": "postalcode"
  },
  "geometry": {"coordinates":[-2.64589,51.074397],"type":"Point"}
}
