{
  "type": "Feature",
  "properties": {
    "iso:country":"GB",
    "wof:name":"TA11 6EY",
    "wof:placetype":"postalcode"
},
  "geometry": {"coordinates":[-2.64589015202968,51.0743970673936],"type":"Point"}
}