{
  "type": "Feature",
  "properties": {
    "date:inception_lower":"1990-02-01",
    "date:inception_upper":"1990-02-28",
    "iso:country":"GB",
    "wof:name":"TA11 6EY",
    "wof:placetype":"postalcode"
},
  "geometry": {"coordinates":[-2.64589,51.074397],"type":"Point"}
}