{
  "type": "Feature",
  "properties": {
    "iso:country":"GB",
    "wof:name":"WA7 2RA",
    "wof:placetype":"postalcode"
},
  "geometry": {"coordinates":[-2.7066661825556,53.33174446637172],"type":"Point"}
}