{
  "type": "Feature",
  "properties": {
    "date:inception_lower": "1980-01-01",
    "date:inception_upper": "1980-01-01",
    "iso:country": "GB",
    "wof:name": "DD7 7BH",
    "wof:placetype": "postalcode"
  },
  "geometry": {"coordinates":[-2.726413,56.502801],"type":"Point"}
}
