{
  "type": "Feature",
  "properties": {
    "iso:country": "GB",
    "wof:name": "LL29 7YD",
    "wof:placetype": "postalcode"
  },
  "geometry": {"coordinates":[-3.737858,53.29677],"type":"Point"}
}
