{
  "type": "Feature",
  "properties": {
    "date:inception_lower": "1980-01-01",
    "date:inception_upper": "1980-01-01",
    "iso:country": "GB",
    "wof:name": "EH48 3NF",
    "wof:placetype": "postalcode"
  },
  "geometry": {"coordinates":[-3.70569,55.899855],"type":"Point"}
}
