{
  "type": "Feature",
  "properties": {
    "iso:country":"GB",
    "wof:name":"B9 5JN",
    "wof:placetype":"postalcode"
},
  "geometry": {"coordinates":[-1.82522485914073,52.47638140379813],"type":"Point"}
}