{
  "type": "Feature",
  "properties": {
    "date:inception_lower": "2000-10-01",
    "date:inception_upper": "2000-10-01",
    "iso:country": "GB",
    "wof:name": "WD18 8YB",
    "wof:placetype": "postalcode"
  },
  "geometry": {"coordinates":[-0.424151,51.64179],"type":"Point"}
}
