{
  "type": "Feature",
  "properties": {
    "iso:country":"GB",
    "wof:name":"WD18 8YB",
    "wof:placetype":"postalcode"
},
  "geometry": {"coordinates":[-0.4241507762011,51.6417900827589],"type":"Point"}
}