{
  "type": "Feature",
  "properties": {
    "iso:country":"GB",
    "wof:name":"SA3 3AN",
    "wof:placetype":"postalcode"
},
  "geometry": {"coordinates":[-4.03160303797245,51.5809318536281],"type":"Point"}
}