{
  "type": "Feature",
  "properties": {
    "iso:country":"GB",
    "wof:name":"NP20 3PN",
    "wof:placetype":"postalcode"
},
  "geometry": {"coordinates":[-3.03307915131721,51.57669031523653],"type":"Point"}
}