{
  "type": "Feature",
  "properties": {
    "iso:country": "GB",
    "wof:name": "NR32 3NJ",
    "wof:placetype": "postalcode"
  },
  "geometry": {"coordinates":[1.714604,52.478612],"type":"Point"}
}
