{
  "type": "Feature",
  "properties": {
    "iso:country":"GB",
    "wof:name":"NR32 3NJ",
    "wof:placetype":"postalcode"
},
  "geometry": {"coordinates":[1.71460414484757,52.47861213640174],"type":"Point"}
}