{
  "type": "Feature",
  "properties": {
    "iso:country":"GB",
    "wof:name":"HU5 4SJ",
    "wof:placetype":"postalcode"
},
  "geometry": {"coordinates":[-0.39699134064378,53.76696819446384],"type":"Point"}
}