{
  "type": "Feature",
  "properties": {
    "date:inception_lower":"1980-01-01",
    "date:inception_upper":"1980-01-31",
    "iso:country":"GB",
    "wof:name":"HU5 4SJ",
    "wof:placetype":"postalcode"
},
  "geometry": {"coordinates":[-0.396991,53.766968],"type":"Point"}
}