{
  "type": "Feature",
  "properties": {
    "iso:country": "GB",
    "wof:name": "NE40 4QP",
    "wof:placetype": "postalcode"
  },
  "geometry": {"coordinates":[-1.776372,54.962317],"type":"Point"}
}
