{
  "type": "Feature",
  "properties": {
    "iso:country":"GB",
    "wof:name":"NE40 4QP",
    "wof:placetype":"postalcode"
},
  "geometry": {"coordinates":[-1.7763722930644,54.96231739963143],"type":"Point"}
}