{
  "type": "Feature",
  "properties": {
    "date:inception_lower": "1980-01-01",
    "date:inception_upper": "1980-01-01",
    "iso:country": "GB",
    "wof:name": "B19 3SH",
    "wof:placetype": "postalcode"
  },
  "geometry": {"coordinates":[-1.896378,52.488149],"type":"Point"}
}
