{
  "type": "Feature",
  "properties": {
    "iso:country":"GB",
    "wof:name":"S60 1EF",
    "wof:placetype":"postalcode"
},
  "geometry": {"coordinates":[-1.36773770139485,53.42899160794996],"type":"Point"}
}