{
  "type": "Feature",
  "properties": {
    "iso:country":"GB",
    "wof:name":"G67 2UB",
    "wof:placetype":"postalcode"
},
  "geometry": {"coordinates":[-3.97446546919165,55.94343964820951],"type":"Point"}
}