{
  "type": "Feature",
  "properties": {
    "iso:country": "GB",
    "wof:name": "G67 2UB",
    "wof:placetype": "postalcode"
  },
  "geometry": {"coordinates":[-3.974465,55.94344],"type":"Point"}
}
