{
  "type": "Feature",
  "properties": {
    "iso:country":"GB",
    "wof:name":"N22 5QW",
    "wof:placetype":"postalcode"
},
  "geometry": {"coordinates":[-0.1000573487747,51.6046564646357],"type":"Point"}
}