{
  "type": "Feature",
  "properties": {
    "iso:country":"GB",
    "wof:name":"NG9 2SR",
    "wof:placetype":"postalcode"
},
  "geometry": {"coordinates":[-1.21045863777254,52.93768107471372],"type":"Point"}
}