{
  "type": "Feature",
  "properties": {
    "iso:country": "GB",
    "wof:name": "TR11 3DH",
    "wof:placetype": "postalcode"
  },
  "geometry": {"coordinates":[-5.068746,50.154517],"type":"Point"}
}
