{
  "type": "Feature",
  "properties": {
    "iso:country":"GB",
    "wof:name":"NR34 9YW",
    "wof:placetype":"postalcode"
},
  "geometry": {"coordinates":[1.57094103385846,52.44639739851916],"type":"Point"}
}