{
  "type": "Feature",
  "properties": {
    "iso:country": "GB",
    "wof:name": "CW11 4XX",
    "wof:placetype": "postalcode"
  },
  "geometry": {"coordinates":[-2.327133,53.118825],"type":"Point"}
}
