{
  "type": "Feature",
  "properties": {
    "iso:country": "GB",
    "wof:name": "W1H 2LF",
    "wof:placetype": "postalcode"
  },
  "geometry": {"coordinates":[-0.159081,51.518469],"type":"Point"}
}
