{
  "type": "Feature",
  "properties": {
    "iso:country":"GB",
    "wof:name":"W1H 2LF",
    "wof:placetype":"postalcode"
},
  "geometry": {"coordinates":[-0.15908140306773,51.51846949229528],"type":"Point"}
}