{
  "type": "Feature",
  "properties": {
    "iso:country": "GB",
    "wof:name": "DY12 2PS",
    "wof:placetype": "postalcode"
  },
  "geometry": {"coordinates":[-2.330535,52.376851],"type":"Point"}
}
