{
  "type": "Feature",
  "properties": {
    "date:inception_lower":"1980-01-01",
    "date:inception_upper":"1980-01-31",
    "iso:country":"GB",
    "wof:name":"DY12 2PS",
    "wof:placetype":"postalcode"
},
  "geometry": {"coordinates":[-2.330535,52.376851],"type":"Point"}
}