{
  "type": "Feature",
  "properties": {
    "iso:country":"GB",
    "wof:name":"TN37 7DR",
    "wof:placetype":"postalcode"
},
  "geometry": {"coordinates":[0.55638468952836,50.87073618834856],"type":"Point"}
}