{
  "type": "Feature",
  "properties": {
    "iso:country": "GB",
    "wof:name": "HP7 9PD",
    "wof:placetype": "postalcode"
  },
  "geometry": {"coordinates":[-0.575955,51.670435],"type":"Point"}
}
