{
  "type": "Feature",
  "properties": {
    "date:inception_lower": "1980-01-01",
    "date:inception_upper": "1980-01-01",
    "iso:country": "GB",
    "wof:name": "HP7 9PD",
    "wof:placetype": "postalcode"
  },
  "geometry": {"coordinates":[-0.575955,51.670435],"type":"Point"}
}
