{
  "type": "Feature",
  "properties": {
    "iso:country":"GB",
    "wof:name":"DN11 9TA",
    "wof:placetype":"postalcode"
},
  "geometry": {"coordinates":[-1.1370861716759,53.48273054151532],"type":"Point"}
}