{
  "type": "Feature",
  "properties": {
    "iso:country": "GB",
    "wof:name": "DN11 9TA",
    "wof:placetype": "postalcode"
  },
  "geometry": {"coordinates":[-1.137086,53.482731],"type":"Point"}
}
