{
  "type": "Feature",
  "properties": {
    "iso:country":"GB",
    "wof:name":"OX5 2LW",
    "wof:placetype":"postalcode"
},
  "geometry": {"coordinates":[-1.27758114611347,51.81276513851802],"type":"Point"}
}