{
  "type": "Feature",
  "properties": {
    "date:inception_lower":"2000-12-01",
    "date:inception_upper":"2000-12-31",
    "iso:country":"GB",
    "wof:name":"RG12 1RT",
    "wof:placetype":"postalcode"
},
  "geometry": {"coordinates":[-0.773069,51.419116],"type":"Point"}
}