{
  "type": "Feature",
  "properties": {
    "iso:country":"GB",
    "wof:name":"CH7 4TG",
    "wof:placetype":"postalcode"
},
  "geometry": {"coordinates":[-3.09200527753869,53.12422513559525],"type":"Point"}
}