{
  "type": "Feature",
  "properties": {
    "iso:country":"GB",
    "wof:name":"NE6 5PQ",
    "wof:placetype":"postalcode"
},
  "geometry": {"coordinates":[-1.58891021152156,54.97793202657175],"type":"Point"}
}