{
  "type": "Feature",
  "properties": {
    "iso:country": "GB",
    "wof:name": "IP6 0NJ",
    "wof:placetype": "postalcode"
  },
  "geometry": {"coordinates":[1.093467,52.115102],"type":"Point"}
}
