{
  "type": "Feature",
  "properties": {
    "iso:country":"GB",
    "wof:name":"IP6 0NJ",
    "wof:placetype":"postalcode"
},
  "geometry": {"coordinates":[1.09340786205232,52.11508726731846],"type":"Point"}
}