{
  "type": "Feature",
  "properties": {
    "date:inception_lower": "1980-01-01",
    "date:inception_upper": "1980-01-01",
    "iso:country": "GB",
    "wof:name": "SR8 2DU",
    "wof:placetype": "postalcode"
  },
  "geometry": {"coordinates":[-1.348784,54.767264],"type":"Point"}
}
