{
  "type": "Feature",
  "properties": {
    "iso:country": "GB",
    "wof:name": "SR8 2DU",
    "wof:placetype": "postalcode"
  },
  "geometry": {"coordinates":[-1.348784,54.767264],"type":"Point"}
}
