{
  "type": "Feature",
  "properties": {
    "date:inception_lower": "1980-01-01",
    "date:inception_upper": "1980-01-01",
    "iso:country": "GB",
    "wof:name": "CV22 5DT",
    "wof:placetype": "postalcode"
  },
  "geometry": {"coordinates":[-1.260178,52.367951],"type":"Point"}
}
