{
  "type": "Feature",
  "properties": {
    "iso:country": "GB",
    "wof:name": "GL6 7PL",
    "wof:placetype": "postalcode"
  },
  "geometry": {"coordinates":[-2.116074,51.740902],"type":"Point"}
}
