{
  "type": "Feature",
  "properties": {
    "date:inception_lower":"1980-01-01",
    "date:inception_upper":"1980-01-31",
    "iso:country":"GB",
    "wof:name":"CT9 5DU",
    "wof:placetype":"postalcode"
},
  "geometry": {"coordinates":[1.358821,51.384086],"type":"Point"}
}