{
  "type": "Feature",
  "properties": {
    "iso:country":"GB",
    "wof:name":"LL13 9EY",
    "wof:placetype":"postalcode"
},
  "geometry": {"coordinates":[-2.9756819327427,53.0503358645549],"type":"Point"}
}