{
  "type": "Feature",
  "properties": {
    "iso:country":"GB",
    "wof:name":"BN13 1LB",
    "wof:placetype":"postalcode"
},
  "geometry": {"coordinates":[-0.41044961804088,50.82287221903783],"type":"Point"}
}