{
  "type": "Feature",
  "properties": {
    "iso:country": "GB",
    "wof:name": "EN1 3NX",
    "wof:placetype": "postalcode"
  },
  "geometry": {"coordinates":[-0.07064,51.664606],"type":"Point"}
}
