{
  "type": "Feature",
  "properties": {
    "iso:country":"GB",
    "wof:name":"EN1 3NX",
    "wof:placetype":"postalcode"
},
  "geometry": {"coordinates":[-0.07064003505414,51.66460567435668],"type":"Point"}
}