{
  "type": "Feature",
  "properties": {
    "iso:country": "GB",
    "wof:name": "NE66 3AY",
    "wof:placetype": "postalcode"
  },
  "geometry": {"coordinates":[-1.624777,55.398293],"type":"Point"}
}
