{
  "type": "Feature",
  "properties": {
    "date:inception_lower": "1980-01-01",
    "date:inception_upper": "1980-01-01",
    "iso:country": "GB",
    "wof:name": "NE66 3AY",
    "wof:placetype": "postalcode"
  },
  "geometry": {"coordinates":[-1.624777,55.398293],"type":"Point"}
}
