{
  "type": "Feature",
  "properties": {
    "iso:country": "GB",
    "wof:name": "IG8 8AL",
    "wof:placetype": "postalcode"
  },
  "geometry": {"coordinates":[0.055392,51.606659],"type":"Point"}
}
