{
  "type": "Feature",
  "properties": {
    "iso:country":"GB",
    "wof:name":"IG8 8AL",
    "wof:placetype":"postalcode"
},
  "geometry": {"coordinates":[0.05539163930636,51.60665935980929],"type":"Point"}
}