{
  "type": "Feature",
  "properties": {
    "iso:country":"GB",
    "wof:name":"BA6 9NY",
    "wof:placetype":"postalcode"
},
  "geometry": {"coordinates":[-2.73543200458477,51.14111171227152],"type":"Point"}
}