{
  "type": "Feature",
  "properties": {
    "iso:country": "GB",
    "wof:name": "BA6 9NY",
    "wof:placetype": "postalcode"
  },
  "geometry": {"coordinates":[-2.735436,51.141106],"type":"Point"}
}
