{
  "type": "Feature",
  "properties": {
    "iso:country":"GB",
    "wof:name":"EN3 4XX",
    "wof:placetype":"postalcode"
},
  "geometry": {"coordinates":[-0.0295147058025,51.64361784784179],"type":"Point"}
}