{
  "type": "Feature",
  "properties": {
    "date:inception_lower": "1994-12-01",
    "date:inception_upper": "1994-12-01",
    "iso:country": "GB",
    "wof:name": "SK13 8TR",
    "wof:placetype": "postalcode"
  },
  "geometry": {"coordinates":[-1.937758,53.440373],"type":"Point"}
}
