{
  "type": "Feature",
  "properties": {
    "iso:country":"GB",
    "wof:name":"PE36 6EN",
    "wof:placetype":"postalcode"
},
  "geometry": {"coordinates":[0.4967094375986,52.94877849105133],"type":"Point"}
}