{
  "type": "Feature",
  "properties": {
    "iso:country":"GB",
    "wof:name":"SS12 9JY",
    "wof:placetype":"postalcode"
},
  "geometry": {"coordinates":[0.53447418477763,51.5855628832931],"type":"Point"}
}