{
  "type": "Feature",
  "properties": {
    "iso:country": "GB",
    "wof:name": "SS12 9JY",
    "wof:placetype": "postalcode"
  },
  "geometry": {"coordinates":[0.534474,51.585563],"type":"Point"}
}
