{
  "type": "Feature",
  "properties": {
    "iso:country":"GB",
    "wof:name":"IV3 8TT",
    "wof:placetype":"postalcode"
},
  "geometry": {"coordinates":[-4.25065556673,57.48101053791313],"type":"Point"}
}