{
  "type": "Feature",
  "properties": {
    "date:inception_lower": "1998-12-01",
    "date:inception_upper": "1998-12-01",
    "iso:country": "GB",
    "wof:name": "IV3 8TT",
    "wof:placetype": "postalcode"
  },
  "geometry": {"coordinates":[-4.250656,57.481011],"type":"Point"}
}
