{
  "type": "Feature",
  "properties": {
    "iso:country":"GB",
    "wof:name":"CO10 1NJ",
    "wof:placetype":"postalcode"
},
  "geometry": {"coordinates":[0.73036649992138,52.04507268431868],"type":"Point"}
}