{
  "type": "Feature",
  "properties": {
    "iso:country": "GB",
    "wof:name": "YO31 8AB",
    "wof:placetype": "postalcode"
  },
  "geometry": {"coordinates":[-1.075296,53.972155],"type":"Point"}
}
