{
  "type": "Feature",
  "properties": {
    "date:inception_lower": "2001-06-01",
    "date:inception_upper": "2001-06-01",
    "iso:country": "GB",
    "wof:name": "BA2 7SL",
    "wof:placetype": "postalcode"
  },
  "geometry": {"coordinates":[-2.329233,51.321936],"type":"Point"}
}
