{
  "type": "Feature",
  "properties": {
    "iso:country":"GB",
    "wof:name":"BA2 7SL",
    "wof:placetype":"postalcode"
},
  "geometry": {"coordinates":[-2.32923307000294,51.32193631533942],"type":"Point"}
}