{
  "type": "Feature",
  "properties": {
    "iso:country": "GB",
    "wof:name": "BA2 7SL",
    "wof:placetype": "postalcode"
  },
  "geometry": {"coordinates":[-2.329233,51.321936],"type":"Point"}
}
