{
  "type": "Feature",
  "properties": {
    "iso:country":"GB",
    "wof:name":"DL10 7AW",
    "wof:placetype":"postalcode"
},
  "geometry": {"coordinates":[-1.7291172221321,54.40678307517488],"type":"Point"}
}