{
  "type": "Feature",
  "properties": {
    "date:inception_lower": "1980-01-01",
    "date:inception_upper": "1980-01-01",
    "iso:country": "GB",
    "wof:name": "DL10 7AW",
    "wof:placetype": "postalcode"
  },
  "geometry": {"coordinates":[-1.729117,54.406783],"type":"Point"}
}
