{
  "type": "Feature",
  "properties": {
    "iso:country":"GB",
    "wof:name":"SW8 2JB",
    "wof:placetype":"postalcode"
},
  "geometry": {"coordinates":[-0.12640236131165,51.48517423821838],"type":"Point"}
}