{
  "type": "Feature",
  "properties": {
    "date:inception_lower": "2005-09-01",
    "date:inception_upper": "2005-09-01",
    "iso:country": "GB",
    "wof:name": "SW8 2JB",
    "wof:placetype": "postalcode"
  },
  "geometry": {"coordinates":[-0.126402,51.485174],"type":"Point"}
}
