{
  "type": "Feature",
  "properties": {
    "iso:country":"GB",
    "wof:name":"PR3 3NP",
    "wof:placetype":"postalcode"
},
  "geometry": {"coordinates":[-2.60705775527573,53.83282269127104],"type":"Point"}
}