{
  "type": "Feature",
  "properties": {
    "iso:country":"GB",
    "wof:name":"EX31 1QR",
    "wof:placetype":"postalcode"
},
  "geometry": {"coordinates":[-4.06308397698548,51.08798901135187],"type":"Point"}
}