{
  "type": "Feature",
  "properties": {
    "iso:country":"GB",
    "wof:name":"RG1 4JS",
    "wof:placetype":"postalcode"
},
  "geometry": {"coordinates":[-0.96114251875514,51.45169430605707],"type":"Point"}
}