{
  "type": "Feature",
  "properties": {
    "date:inception_lower": "1990-07-01",
    "date:inception_upper": "1990-07-01",
    "iso:country": "GB",
    "wof:name": "RG1 4JS",
    "wof:placetype": "postalcode"
  },
  "geometry": {"coordinates":[-0.961142,51.451694],"type":"Point"}
}
