{
  "type": "Feature",
  "properties": {
    "iso:country":"GB",
    "wof:name":"SA73 1PB",
    "wof:placetype":"postalcode"
},
  "geometry": {"coordinates":[-4.93627271567301,51.70963215643987],"type":"Point"}
}