{
  "type": "Feature",
  "properties": {
    "iso:country":"GB",
    "wof:name":"SP8 5HL",
    "wof:placetype":"postalcode"
},
  "geometry": {"coordinates":[-2.35526388024755,51.02049302096771],"type":"Point"}
}