{
  "type": "Feature",
  "properties": {
    "iso:country": "GB",
    "wof:name": "SP8 5HL",
    "wof:placetype": "postalcode"
  },
  "geometry": {"coordinates":[-2.355264,51.020493],"type":"Point"}
}
