{
  "type": "Feature",
  "properties": {
    "iso:country": "GB",
    "wof:name": "BS22 8EE",
    "wof:placetype": "postalcode"
  },
  "geometry": {"coordinates":[-2.947591,51.353405],"type":"Point"}
}
