{
  "type": "Feature",
  "properties": {
    "iso:country":"GB",
    "wof:name":"UB1 1DU",
    "wof:placetype":"postalcode"
},
  "geometry": {"coordinates":[-0.38615297348672,51.50821707022524],"type":"Point"}
}