{
  "type": "Feature",
  "properties": {
    "iso:country": "GB",
    "wof:name": "UB1 1DU",
    "wof:placetype": "postalcode"
  },
  "geometry": {"coordinates":[-0.38606,51.508217],"type":"Point"}
}
