{
  "type": "Feature",
  "properties": {
    "date:inception_lower": "1980-01-01",
    "date:inception_upper": "1980-01-01",
    "iso:country": "GB",
    "wof:name": "NE5 2XF",
    "wof:placetype": "postalcode"
  },
  "geometry": {"coordinates":[-1.684719,54.989406],"type":"Point"}
}
