{
  "type": "Feature",
  "properties": {
    "iso:country":"GB",
    "wof:name":"NE5 2XF",
    "wof:placetype":"postalcode"
},
  "geometry": {"coordinates":[-1.68471899505278,54.98940572933874],"type":"Point"}
}