{
  "type": "Feature",
  "properties": {
    "iso:country":"GB",
    "wof:name":"RM3 7QS",
    "wof:placetype":"postalcode"
},
  "geometry": {"coordinates":[0.21014747622152,51.60623015232415],"type":"Point"}
}