{
  "type": "Feature",
  "properties": {
    "iso:country":"GB",
    "wof:name":"TN5 6JY",
    "wof:placetype":"postalcode"
},
  "geometry": {"coordinates":[0.29877722445446,51.07102713651058],"type":"Point"}
}