{
  "type": "Feature",
  "properties": {
    "iso:country":"GB",
    "wof:name":"NR2 1JT",
    "wof:placetype":"postalcode"
},
  "geometry": {"coordinates":[1.29692545462149,52.62981119113196],"type":"Point"}
}