{
  "type": "Feature",
  "properties": {
    "date:inception_lower": "1980-01-01",
    "date:inception_upper": "1980-01-01",
    "iso:country": "GB",
    "wof:name": "SN10 4SF",
    "wof:placetype": "postalcode"
  },
  "geometry": {"coordinates":[-1.940221,51.313465],"type":"Point"}
}
