{
  "type": "Feature",
  "properties": {
    "date:inception_lower": "2001-12-01",
    "date:inception_upper": "2001-12-01",
    "iso:country": "GB",
    "wof:name": "M43 7FR",
    "wof:placetype": "postalcode"
  },
  "geometry": {"coordinates":[-2.144059,53.48493],"type":"Point"}
}
