{
  "type": "Feature",
  "properties": {
    "iso:country": "GB",
    "wof:name": "LL18 1DE",
    "wof:placetype": "postalcode"
  },
  "geometry": {"coordinates":[-3.49488,53.316119],"type":"Point"}
}
