{
  "type": "Feature",
  "properties": {
    "iso:country":"GB",
    "wof:name":"LL18 1DE",
    "wof:placetype":"postalcode"
},
  "geometry": {"coordinates":[-3.49487963980535,53.31611908490564],"type":"Point"}
}