{
  "type": "Feature",
  "properties": {
    "date:inception_lower": "1998-12-01",
    "date:inception_upper": "1998-12-01",
    "iso:country": "GB",
    "wof:name": "OX4 4XQ",
    "wof:placetype": "postalcode"
  },
  "geometry": {"coordinates":[-1.226056,51.718677],"type":"Point"}
}
