{
  "type": "Feature",
  "properties": {
    "iso:country": "GB",
    "wof:name": "S81 8BL",
    "wof:placetype": "postalcode"
  },
  "geometry": {"coordinates":[-1.170424,53.336323],"type":"Point"}
}
