{
  "type": "Feature",
  "properties": {
    "date:inception_lower": "1980-01-01",
    "date:inception_upper": "1980-01-01",
    "iso:country": "GB",
    "wof:name": "NE7 7PU",
    "wof:placetype": "postalcode"
  },
  "geometry": {"coordinates":[-1.581457,54.999042],"type":"Point"}
}
