{
  "type": "Feature",
  "properties": {
    "date:inception_lower":"1992-08-01",
    "date:inception_upper":"1992-08-31",
    "iso:country":"GB",
    "wof:name":"OL4 3NU",
    "wof:placetype":"postalcode"
},
  "geometry": {"coordinates":[-2.07122,53.543744],"type":"Point"}
}