{
  "type": "Feature",
  "properties": {
    "iso:country":"GB",
    "wof:name":"NW4 2JN",
    "wof:placetype":"postalcode"
},
  "geometry": {"coordinates":[-0.21241822885995,51.58931804018523],"type":"Point"}
}