{
  "type": "Feature",
  "properties": {
    "iso:country":"GB",
    "wof:name":"LS26 9AF",
    "wof:placetype":"postalcode"
},
  "geometry": {"coordinates":[-1.3931972969916,53.72903168750102],"type":"Point"}
}