{
  "type": "Feature",
  "properties": {
    "date:inception_lower":"1980-01-01",
    "date:inception_upper":"1980-01-31",
    "iso:country":"GB",
    "wof:name":"SO21 2DA",
    "wof:placetype":"postalcode"
},
  "geometry": {"coordinates":[-1.33499,51.017239],"type":"Point"}
}