{
  "type": "Feature",
  "properties": {
    "iso:country":"GB",
    "wof:name":"SO21 2DA",
    "wof:placetype":"postalcode"
},
  "geometry": {"coordinates":[-1.33589978782033,51.0171969610909],"type":"Point"}
}