{
  "type": "Feature",
  "properties": {
    "iso:country": "GB",
    "wof:name": "GU20 6NQ",
    "wof:placetype": "postalcode"
  },
  "geometry": {"coordinates":[-0.671271,51.375122],"type":"Point"}
}
