{
  "type": "Feature",
  "properties": {
    "date:inception_lower": "1980-01-01",
    "date:inception_upper": "1980-01-01",
    "iso:country": "GB",
    "wof:name": "NR35 1JZ",
    "wof:placetype": "postalcode"
  },
  "geometry": {"coordinates":[1.453467,52.4523],"type":"Point"}
}
