{
  "type": "Feature",
  "properties": {
    "iso:country":"GB",
    "wof:name":"NR35 1JZ",
    "wof:placetype":"postalcode"
},
  "geometry": {"coordinates":[1.45346656931467,52.45230022026782],"type":"Point"}
}