{
  "type": "Feature",
  "properties": {
    "iso:country": "GB",
    "wof:name": "B62 8DD",
    "wof:placetype": "postalcode"
  },
  "geometry": {"coordinates":[-2.040153,52.455005],"type":"Point"}
}
