{
  "type": "Feature",
  "properties": {
    "iso:country":"GB",
    "wof:name":"B62 8DD",
    "wof:placetype":"postalcode"
},
  "geometry": {"coordinates":[-2.03899733388042,52.45537713866167],"type":"Point"}
}