{
  "type": "Feature",
  "properties": {
    "iso:country":"GB",
    "wof:name":"GU15 2QT",
    "wof:placetype":"postalcode"
},
  "geometry": {"coordinates":[-0.75567410494088,51.32503649740074],"type":"Point"}
}