{
  "type": "Feature",
  "properties": {
    "date:inception_lower":"2019-03-01",
    "date:inception_upper":"2019-03-31",
    "iso:country":"GB",
    "wof:name":"E17 5UE",
    "wof:placetype":"postalcode"
},
  "geometry": {"coordinates":[-0.017986,51.585505],"type":"Point"}
}