{
  "type": "Feature",
  "properties": {
    "date:inception_lower": "1980-01-01",
    "date:inception_upper": "1980-01-01",
    "iso:country": "GB",
    "wof:name": "B14 7NL",
    "wof:placetype": "postalcode"
  },
  "geometry": {"coordinates":[-1.906128,52.427181],"type":"Point"}
}
