{
  "type": "Feature",
  "properties": {
    "iso:country": "GB",
    "wof:name": "B14 7NL",
    "wof:placetype": "postalcode"
  },
  "geometry": {"coordinates":[-1.906128,52.427181],"type":"Point"}
}
