{
  "type": "Feature",
  "properties": {
    "iso:country": "GB",
    "wof:name": "NG31 7PB",
    "wof:placetype": "postalcode"
  },
  "geometry": {"coordinates":[-0.655267,52.906351],"type":"Point"}
}
