{
  "type": "Feature",
  "properties": {
    "date:inception_lower":"1980-01-01",
    "date:inception_upper":"1980-01-31",
    "iso:country":"GB",
    "wof:name":"NG31 7PB",
    "wof:placetype":"postalcode"
},
  "geometry": {"coordinates":[-0.655267,52.906351],"type":"Point"}
}