{
  "type": "Feature",
  "properties": {
    "iso:country": "GB",
    "wof:name": "CR2 6JQ",
    "wof:placetype": "postalcode"
  },
  "geometry": {"coordinates":[-0.104011,51.355041],"type":"Point"}
}
