{
  "type": "Feature",
  "properties": {
    "iso:country":"GB",
    "wof:name":"CR2 6JQ",
    "wof:placetype":"postalcode"
},
  "geometry": {"coordinates":[-0.10401152042222,51.35504101173052],"type":"Point"}
}