{
  "type": "Feature",
  "properties": {
    "iso:country": "GB",
    "wof:name": "SO50 5DR",
    "wof:placetype": "postalcode"
  },
  "geometry": {"coordinates":[-1.369221,50.9635],"type":"Point"}
}
