{
  "type": "Feature",
  "properties": {
    "iso:country":"GB",
    "wof:name":"SO50 5DR",
    "wof:placetype":"postalcode"
},
  "geometry": {"coordinates":[-1.36923161927167,50.96350831275844],"type":"Point"}
}