{
  "type": "Feature",
  "properties": {
    "date:inception_lower": "1980-01-01",
    "date:inception_upper": "1980-01-01",
    "iso:country": "GB",
    "wof:name": "BS15 4DF",
    "wof:placetype": "postalcode"
  },
  "geometry": {"coordinates":[-2.497062,51.463907],"type":"Point"}
}
