{
  "type": "Feature",
  "properties": {
    "iso:country":"GB",
    "wof:name":"NW5 4HS",
    "wof:placetype":"postalcode"
},
  "geometry": {"coordinates":[-0.15433722045313,51.55024623612059],"type":"Point"}
}