{
  "type": "Feature",
  "properties": {
    "date:inception_lower": "2024-06-01",
    "date:inception_upper": "2024-06-01",
    "iso:country": "GB",
    "wof:name": "CH7 9GB",
    "wof:placetype": "postalcode"
  },
  "geometry": {"coordinates":[-3.14398,53.167513],"type":"Point"}
}
