{
  "type": "Feature",
  "properties": {
    "iso:country":"GB",
    "wof:name":"CT4 5EZ",
    "wof:placetype":"postalcode"
},
  "geometry": {"coordinates":[1.15250097216228,51.25688356786884],"type":"Point"}
}