{
  "type": "Feature",
  "properties": {
    "date:inception_lower": "1995-12-01",
    "date:inception_upper": "1995-12-01",
    "iso:country": "GB",
    "wof:name": "CT4 5EZ",
    "wof:placetype": "postalcode"
  },
  "geometry": {"coordinates":[1.152501,51.256884],"type":"Point"}
}
