{
  "type": "Feature",
  "properties": {
    "iso:country": "GB",
    "wof:name": "CT4 5EZ",
    "wof:placetype": "postalcode"
  },
  "geometry": {"coordinates":[1.152501,51.256884],"type":"Point"}
}
