{
  "type": "Feature",
  "properties": {
    "iso:country":"GB",
    "wof:name":"M25 0BT",
    "wof:placetype":"postalcode"
},
  "geometry": {"coordinates":[-2.25731200415955,53.52535794982418],"type":"Point"}
}