{
  "type": "Feature",
  "properties": {
    "date:inception_lower": "1991-01-01",
    "date:inception_upper": "1991-01-01",
    "iso:country": "GB",
    "wof:name": "TA3 5TE",
    "wof:placetype": "postalcode"
  },
  "geometry": {"coordinates":[-3.037075,51.024936],"type":"Point"}
}
