{
  "type": "Feature",
  "properties": {
    "iso:country": "GB",
    "wof:name": "TA3 5TE",
    "wof:placetype": "postalcode"
  },
  "geometry": {"coordinates":[-3.037075,51.024936],"type":"Point"}
}
