{
  "type": "Feature",
  "properties": {
    "iso:country":"GB",
    "wof:name":"TA3 5TE",
    "wof:placetype":"postalcode"
},
  "geometry": {"coordinates":[-3.03707519081606,51.02493628231786],"type":"Point"}
}