{
  "type": "Feature",
  "properties": {
    "iso:country":"GB",
    "wof:name":"NN6 6JP",
    "wof:placetype":"postalcode"
},
  "geometry": {"coordinates":[-1.13731387648759,52.40506753407966],"type":"Point"}
}