{
  "type": "Feature",
  "properties": {
    "iso:country": "GB",
    "wof:name": "NN6 6JP",
    "wof:placetype": "postalcode"
  },
  "geometry": {"coordinates":[-1.137314,52.405068],"type":"Point"}
}
