{
  "type": "Feature",
  "properties": {
    "iso:country":"GB",
    "wof:name":"TA21 0PT",
    "wof:placetype":"postalcode"
},
  "geometry": {"coordinates":[-3.34483460454214,50.9576263196217],"type":"Point"}
}