{
  "type": "Feature",
  "properties": {
    "iso:country": "GB",
    "wof:name": "TA21 0PT",
    "wof:placetype": "postalcode"
  },
  "geometry": {"coordinates":[-3.344835,50.957626],"type":"Point"}
}
