{
  "type": "Feature",
  "properties": {
    "iso:country":"GB",
    "wof:name":"BN22 7LW",
    "wof:placetype":"postalcode"
},
  "geometry": {"coordinates":[0.30396342075143,50.78025308052444],"type":"Point"}
}