{
  "type": "Feature",
  "properties": {
    "date:inception_lower": "2002-08-01",
    "date:inception_upper": "2002-08-01",
    "iso:country": "GB",
    "wof:name": "PR2 2DR",
    "wof:placetype": "postalcode"
  },
  "geometry": {"coordinates":[-2.722343,53.768521],"type":"Point"}
}
