{
  "type": "Feature",
  "properties": {
    "iso:country":"GB",
    "wof:name":"WN3 4NJ",
    "wof:placetype":"postalcode"
},
  "geometry": {"coordinates":[-2.61626368189796,53.53205470368192],"type":"Point"}
}