{
  "type": "Feature",
  "properties": {
    "date:inception_lower": "1984-02-01",
    "date:inception_upper": "1984-02-01",
    "iso:country": "GB",
    "wof:name": "OX14 2HW",
    "wof:placetype": "postalcode"
  },
  "geometry": {"coordinates":[-1.247833,51.690388],"type":"Point"}
}
