{
  "type": "Feature",
  "properties": {
    "iso:country":"GB",
    "wof:name":"N17 6EP",
    "wof:placetype":"postalcode"
},
  "geometry": {"coordinates":[-0.07546080435503,51.59585677982989],"type":"Point"}
}