{
  "type": "Feature",
  "properties": {
    "iso:country": "GB",
    "wof:name": "N17 6EP",
    "wof:placetype": "postalcode"
  },
  "geometry": {"coordinates":[-0.075461,51.595857],"type":"Point"}
}
