{
  "type": "Feature",
  "properties": {
    "iso:country":"GB",
    "wof:name":"W11 3RL",
    "wof:placetype":"postalcode"
},
  "geometry": {"coordinates":[-0.20109060774301,51.50802462118916],"type":"Point"}
}