{
  "type": "Feature",
  "properties": {
    "iso:country":"GB",
    "wof:name":"PA5 8TE",
    "wof:placetype":"postalcode"
},
  "geometry": {"coordinates":[-4.52091733752679,55.83445298644847],"type":"Point"}
}