{
  "type": "Feature",
  "properties": {
    "iso:country":"GB",
    "wof:name":"UB4 9JZ",
    "wof:placetype":"postalcode"
},
  "geometry": {"coordinates":[-0.40501080087773,51.5327000391191],"type":"Point"}
}