{
  "type": "Feature",
  "properties": {
    "date:inception_lower":"1980-01-01",
    "date:inception_upper":"1980-01-31",
    "iso:country":"GB",
    "wof:name":"NG20 9AG",
    "wof:placetype":"postalcode"
},
  "geometry": {"coordinates":[-1.214952,53.213493],"type":"Point"}
}