{
  "type": "Feature",
  "properties": {
    "iso:country": "GB",
    "wof:name": "NG20 9AG",
    "wof:placetype": "postalcode"
  },
  "geometry": {"coordinates":[-1.214952,53.213493],"type":"Point"}
}
