{
  "type": "Feature",
  "properties": {
    "iso:country":"GB",
    "wof:name":"NG20 9AG",
    "wof:placetype":"postalcode"
},
  "geometry": {"coordinates":[-1.21495242309539,53.21349305365199],"type":"Point"}
}