{
  "type": "Feature",
  "properties": {
    "iso:country":"GB",
    "wof:name":"N5 1DD",
    "wof:placetype":"postalcode"
},
  "geometry": {"coordinates":[-0.10003150861166,51.55786827713409],"type":"Point"}
}