{
  "type": "Feature",
  "properties": {
    "iso:country": "GB",
    "wof:name": "HR9 5SP",
    "wof:placetype": "postalcode"
  },
  "geometry": {"coordinates":[-2.572592,51.883403],"type":"Point"}
}
