{
  "type": "Feature",
  "properties": {
    "date:inception_lower":"1980-01-01",
    "date:inception_upper":"1980-01-31",
    "iso:country":"GB",
    "wof:name":"HR9 5SP",
    "wof:placetype":"postalcode"
},
  "geometry": {"coordinates":[-2.572592,51.883403],"type":"Point"}
}