{
  "type": "Feature",
  "properties": {
    "iso:country":"GB",
    "wof:name":"HR9 5SP",
    "wof:placetype":"postalcode"
},
  "geometry": {"coordinates":[-2.57259176843386,51.88340251645534],"type":"Point"}
}