{
  "type": "Feature",
  "properties": {
    "iso:country":"GB",
    "wof:name":"M26 4HX",
    "wof:placetype":"postalcode"
},
  "geometry": {"coordinates":[-2.33534539339827,53.57532851480804],"type":"Point"}
}