{
  "type": "Feature",
  "properties": {
    "iso:country": "GB",
    "wof:name": "M26 4HX",
    "wof:placetype": "postalcode"
  },
  "geometry": {"coordinates":[-2.335345,53.575329],"type":"Point"}
}
