{
  "type": "Feature",
  "properties": {
    "date:inception_lower":"2012-02-01",
    "date:inception_upper":"2012-02-29",
    "iso:country":"GB",
    "wof:name":"CV34 4AF",
    "wof:placetype":"postalcode"
},
  "geometry": {"coordinates":[-1.593115,52.284788],"type":"Point"}
}