{
  "type": "Feature",
  "properties": {
    "iso:country": "GB",
    "wof:name": "CV34 4AF",
    "wof:placetype": "postalcode"
  },
  "geometry": {"coordinates":[-1.593115,52.284788],"type":"Point"}
}
