{
  "type": "Feature",
  "properties": {
    "iso:country": "GB",
    "wof:name": "DD4 8YZ",
    "wof:placetype": "postalcode"
  },
  "geometry": {"coordinates":[-2.901871,56.482497],"type":"Point"}
}
