{
  "type": "Feature",
  "properties": {
    "iso:country": "GB",
    "wof:name": "PR5 4GJ",
    "wof:placetype": "postalcode"
  },
  "geometry": {"coordinates":[-2.673345,53.738596],"type":"Point"}
}
