{
  "type": "Feature",
  "properties": {
    "iso:country":"GB",
    "wof:name":"PR5 4GJ",
    "wof:placetype":"postalcode"
},
  "geometry": {"coordinates":[-2.67334530971582,53.73859647901086],"type":"Point"}
}