{
  "type": "Feature",
  "properties": {
    "date:inception_lower": "1980-01-01",
    "date:inception_upper": "1980-01-01",
    "iso:country": "GB",
    "wof:name": "PR5 4GJ",
    "wof:placetype": "postalcode"
  },
  "geometry": {"coordinates":[-2.673345,53.738596],"type":"Point"}
}
