{
  "type": "Feature",
  "properties": {
    "iso:country":"GB",
    "wof:name":"DE13 8HN",
    "wof:placetype":"postalcode"
},
  "geometry": {"coordinates":[-1.72392350693422,52.76431975641838],"type":"Point"}
}