{
  "type": "Feature",
  "properties": {
    "iso:country":"GB",
    "wof:name":"TN30 7AT",
    "wof:placetype":"postalcode"
},
  "geometry": {"coordinates":[0.6980915409897,51.07670812363968],"type":"Point"}
}