{
  "type": "Feature",
  "properties": {
    "iso:country":"GB",
    "wof:name":"NW1 2HE",
    "wof:placetype":"postalcode"
},
  "geometry": {"coordinates":[-0.1351287362776,51.52686779056675],"type":"Point"}
}