{
  "type": "Feature",
  "properties": {
    "iso:country":"GB",
    "wof:name":"KT18 5SJ",
    "wof:placetype":"postalcode"
},
  "geometry": {"coordinates":[-0.23813510369634,51.31099380777394],"type":"Point"}
}