{
  "type": "Feature",
  "properties": {
    "iso:country": "GB",
    "wof:name": "TN15 0QE",
    "wof:placetype": "postalcode"
  },
  "geometry": {"coordinates":[0.296376,51.258453],"type":"Point"}
}
