{
  "type": "Feature",
  "properties": {
    "iso:country": "GB",
    "wof:name": "PL30 4EE",
    "wof:placetype": "postalcode"
  },
  "geometry": {"coordinates":[-4.638423,50.478926],"type":"Point"}
}
