{
  "type": "Feature",
  "properties": {
    "date:inception_lower":"1980-01-01",
    "date:inception_upper":"1980-01-31",
    "iso:country":"GB",
    "wof:name":"PL30 4EE",
    "wof:placetype":"postalcode"
},
  "geometry": {"coordinates":[-4.638423,50.478926],"type":"Point"}
}