{
  "type": "Feature",
  "properties": {
    "iso:country":"GB",
    "wof:name":"PL30 4EE",
    "wof:placetype":"postalcode"
},
  "geometry": {"coordinates":[-4.63887815201034,50.4781701863368],"type":"Point"}
}