{
  "type": "Feature",
  "properties": {
    "date:inception_lower": "2000-12-01",
    "date:inception_upper": "2000-12-01",
    "iso:country": "GB",
    "wof:name": "EH54 7EJ",
    "wof:placetype": "postalcode"
  },
  "geometry": {"coordinates":[-3.546452,55.87673],"type":"Point"}
}
