{
  "type": "Feature",
  "properties": {
    "iso:country":"GB",
    "wof:name":"SE11 5PR",
    "wof:placetype":"postalcode"
},
  "geometry": {"coordinates":[-0.11605202378732,51.48853349076671],"type":"Point"}
}