{
  "type": "Feature",
  "properties": {
    "date:inception_lower": "2002-06-01",
    "date:inception_upper": "2002-06-01",
    "iso:country": "GB",
    "wof:name": "E8 2RL",
    "wof:placetype": "postalcode"
  },
  "geometry": {"coordinates":[-0.06661,51.552331],"type":"Point"}
}
