{
  "type": "Feature",
  "properties": {
    "iso:country":"GB",
    "wof:name":"E8 2RL",
    "wof:placetype":"postalcode"
},
  "geometry": {"coordinates":[-0.06660986414967,51.55233144166563],"type":"Point"}
}