{
  "type": "Feature",
  "properties": {
    "iso:country":"GB",
    "wof:name":"WF9 3DL",
    "wof:placetype":"postalcode"
},
  "geometry": {"coordinates":[-1.31047313996752,53.59894545411147],"type":"Point"}
}