{
  "type": "Feature",
  "properties": {
    "iso:country": "GB",
    "wof:name": "WF9 3DL",
    "wof:placetype": "postalcode"
  },
  "geometry": {"coordinates":[-1.310384,53.598989],"type":"Point"}
}
