{
  "type": "Feature",
  "properties": {
    "iso:country":"GB",
    "wof:name":"BL3 1NN",
    "wof:placetype":"postalcode"
},
  "geometry": {"coordinates":[-2.36009450640727,53.56253800928384],"type":"Point"}
}