{
  "type": "Feature",
  "properties": {
    "iso:country": "GB",
    "wof:name": "BD6 3FA",
    "wof:placetype": "postalcode"
  },
  "geometry": {"coordinates":[-1.806845,53.769473],"type":"Point"}
}
