{
  "type": "Feature",
  "properties": {
    "iso:country":"GB",
    "wof:name":"BD6 3FA",
    "wof:placetype":"postalcode"
},
  "geometry": {"coordinates":[-1.80684491820044,53.76947339516784],"type":"Point"}
}