{
  "type": "Feature",
  "properties": {
    "date:inception_lower":"1980-01-01",
    "date:inception_upper":"1980-01-31",
    "iso:country":"GB",
    "wof:name":"FY4 2PB",
    "wof:placetype":"postalcode"
},
  "geometry": {"coordinates":[-3.0428,53.784488],"type":"Point"}
}