{
  "type": "Feature",
  "properties": {
    "iso:country": "GB",
    "wof:name": "FY4 2PB",
    "wof:placetype": "postalcode"
  },
  "geometry": {"coordinates":[-3.0428,53.784488],"type":"Point"}
}
