{
  "type": "Feature",
  "properties": {
    "iso:country": "GB",
    "wof:name": "YO1 7NY",
    "wof:placetype": "postalcode"
  },
  "geometry": {"coordinates":[-1.078559,53.958977],"type":"Point"}
}
