{
  "type": "Feature",
  "properties": {
    "iso:country":"GB",
    "wof:name":"YO1 7NY",
    "wof:placetype":"postalcode"
},
  "geometry": {"coordinates":[-1.07855948642693,53.95897658523587],"type":"Point"}
}