{
  "type": "Feature",
  "properties": {
    "iso:country":"GB",
    "wof:name":"IP22 1RU",
    "wof:placetype":"postalcode"
},
  "geometry": {"coordinates":[1.00800151599597,52.35795369419679],"type":"Point"}
}