{
  "type": "Feature",
  "properties": {
    "date:inception_lower": "2018-10-01",
    "date:inception_upper": "2018-10-01",
    "iso:country": "GB",
    "wof:name": "CF23 5RF",
    "wof:placetype": "postalcode"
  },
  "geometry": {"coordinates":[-3.160796,51.499957],"type":"Point"}
}
