{
  "type": "Feature",
  "properties": {
    "date:inception_lower": "2019-06-01",
    "date:inception_upper": "2019-06-01",
    "iso:country": "GB",
    "wof:name": "NG18 6AJ",
    "wof:placetype": "postalcode"
  },
  "geometry": {"coordinates":[-1.177011,53.120047],"type":"Point"}
}
