{
  "type": "Feature",
  "properties": {
    "iso:country": "GB",
    "wof:name": "FK1 3AJ",
    "wof:placetype": "postalcode"
  },
  "geometry": {"coordinates":[-3.822922,55.96471],"type":"Point"}
}
