{
  "type": "Feature",
  "properties": {
    "iso:country":"GB",
    "wof:name":"FK1 3AJ",
    "wof:placetype":"postalcode"
},
  "geometry": {"coordinates":[-3.82292210849874,55.96471010953591],"type":"Point"}
}