{
  "type": "Feature",
  "properties": {
    "date:inception_lower": "1992-01-01",
    "date:inception_upper": "1992-01-01",
    "iso:country": "GB",
    "wof:name": "GU29 9NE",
    "wof:placetype": "postalcode"
  },
  "geometry": {"coordinates":[-0.74084,50.985395],"type":"Point"}
}
