{
  "type": "Feature",
  "properties": {
    "date:inception_lower": "1981-09-01",
    "date:inception_upper": "1981-09-01",
    "iso:country": "GB",
    "wof:name": "TS4 3SP",
    "wof:placetype": "postalcode"
  },
  "geometry": {"coordinates":[-1.21987,54.555338],"type":"Point"}
}
