{
  "type": "Feature",
  "properties": {
    "iso:country":"GB",
    "wof:name":"PA28 6AY",
    "wof:placetype":"postalcode"
},
  "geometry": {"coordinates":[-5.60551613252973,55.42331022634469],"type":"Point"}
}