{
  "type": "Feature",
  "properties": {
    "date:inception_lower": "1980-01-01",
    "date:inception_upper": "1980-01-01",
    "iso:country": "GB",
    "wof:name": "PA28 6AY",
    "wof:placetype": "postalcode"
  },
  "geometry": {"coordinates":[-5.605516,55.42331],"type":"Point"}
}
