{
  "type": "Feature",
  "properties": {
    "iso:country":"GB",
    "wof:name":"NE31 1JP",
    "wof:placetype":"postalcode"
},
  "geometry": {"coordinates":[-1.50593944847604,54.9773359389355],"type":"Point"}
}