{
  "type": "Feature",
  "properties": {
    "date:inception_lower":"1980-01-01",
    "date:inception_upper":"1980-01-31",
    "iso:country":"GB",
    "wof:name":"BA1 5PP",
    "wof:placetype":"postalcode"
},
  "geometry": {"coordinates":[-2.361918,51.392299],"type":"Point"}
}