{
  "type": "Feature",
  "properties": {
    "iso:country":"GB",
    "wof:name":"BA1 5PP",
    "wof:placetype":"postalcode"
},
  "geometry": {"coordinates":[-2.36191796293653,51.39229895784944],"type":"Point"}
}