{
  "type": "Feature",
  "properties": {
    "iso:country": "GB",
    "wof:name": "AB33 8AA",
    "wof:placetype": "postalcode"
  },
  "geometry": {"coordinates":[-2.699567,57.231326],"type":"Point"}
}
