{
  "type": "Feature",
  "properties": {
    "iso:country":"GB",
    "wof:name":"HX1 5JY",
    "wof:placetype":"postalcode"
},
  "geometry": {"coordinates":[-1.8756369219231,53.72166706727737],"type":"Point"}
}