{
  "type": "Feature",
  "properties": {
    "date:inception_lower": "2021-04-01",
    "date:inception_upper": "2021-04-01",
    "iso:country": "GB",
    "wof:name": "TN23 8AG",
    "wof:placetype": "postalcode"
  },
  "geometry": {"coordinates":[0.826976,51.125567],"type":"Point"}
}
