{
  "type": "Feature",
  "properties": {
    "iso:country": "GB",
    "wof:name": "L4 5UL",
    "wof:placetype": "postalcode"
  },
  "geometry": {"coordinates":[-2.961598,53.443888],"type":"Point"}
}
