{
  "type": "Feature",
  "properties": {
    "iso:country":"GB",
    "wof:name":"L4 5UL",
    "wof:placetype":"postalcode"
},
  "geometry": {"coordinates":[-2.96159800975541,53.44388757019204],"type":"Point"}
}