{
  "type": "Feature",
  "properties": {
    "iso:country":"GB",
    "wof:name":"S73 9JU",
    "wof:placetype":"postalcode"
},
  "geometry": {"coordinates":[-1.37477742552272,53.53383559576555],"type":"Point"}
}