{
  "type": "Feature",
  "properties": {
    "iso:country":"GB",
    "wof:name":"HG4 1BD",
    "wof:placetype":"postalcode"
},
  "geometry": {"coordinates":[-1.5248056278808,54.13556161914015],"type":"Point"}
}