{
  "type": "Feature",
  "properties": {
    "iso:country": "GB",
    "wof:name": "CB24 5AS",
    "wof:placetype": "postalcode"
  },
  "geometry": {"coordinates":[0.067136,52.316094],"type":"Point"}
}
