{
  "type": "Feature",
  "properties": {
    "date:inception_lower": "1987-10-01",
    "date:inception_upper": "1987-10-01",
    "iso:country": "GB",
    "wof:name": "NG15 0BX",
    "wof:placetype": "postalcode"
  },
  "geometry": {"coordinates":[-1.226713,53.071622],"type":"Point"}
}
