{
  "type": "Feature",
  "properties": {
    "iso:country": "GB",
    "wof:name": "WS11 9TQ",
    "wof:placetype": "postalcode"
  },
  "geometry": {"coordinates":[-1.971993,52.670552],"type":"Point"}
}
