{
  "type": "Feature",
  "properties": {
    "iso:country":"GB",
    "wof:name":"WS11 9TQ",
    "wof:placetype":"postalcode"
},
  "geometry": {"coordinates":[-1.97199293100535,52.67055201200875],"type":"Point"}
}