{
  "type": "Feature",
  "properties": {
    "iso:country":"GB",
    "wof:name":"BD6 1DG",
    "wof:placetype":"postalcode"
},
  "geometry": {"coordinates":[-1.74899169462006,53.76508806011154],"type":"Point"}
}