{
  "type": "Feature",
  "properties": {
    "date:inception_lower": "1980-01-01",
    "date:inception_upper": "1980-01-01",
    "iso:country": "GB",
    "wof:name": "BD6 1DG",
    "wof:placetype": "postalcode"
  },
  "geometry": {"coordinates":[-1.748992,53.765088],"type":"Point"}
}
