{
  "type": "Feature",
  "properties": {
    "iso:country":"GB",
    "wof:name":"PE2 5RP",
    "wof:placetype":"postalcode"
},
  "geometry": {"coordinates":[-0.29575470872461,52.54625232940662],"type":"Point"}
}