{
  "type": "Feature",
  "properties": {
    "iso:country":"GB",
    "wof:name":"AL7 1HX",
    "wof:placetype":"postalcode"
},
  "geometry": {"coordinates":[-0.19801634755853,51.80083687830069],"type":"Point"}
}