{
  "type": "Feature",
  "properties": {
    "iso:country": "GB",
    "wof:name": "DN16 3DF",
    "wof:placetype": "postalcode"
  },
  "geometry": {"coordinates":[-0.627677,53.560299],"type":"Point"}
}
