{
  "type": "Feature",
  "properties": {
    "date:inception_lower": "2001-06-01",
    "date:inception_upper": "2001-06-01",
    "iso:country": "GB",
    "wof:name": "WA5 8TF",
    "wof:placetype": "postalcode"
  },
  "geometry": {"coordinates":[-2.63379,53.405482],"type":"Point"}
}
