{
  "type": "Feature",
  "properties": {
    "iso:country": "GB",
    "wof:name": "WA5 8TF",
    "wof:placetype": "postalcode"
  },
  "geometry": {"coordinates":[-2.633806,53.405466],"type":"Point"}
}
