{
  "type": "Feature",
  "properties": {
    "iso:country":"GB",
    "wof:name":"WA5 8TF",
    "wof:placetype":"postalcode"
},
  "geometry": {"coordinates":[-2.63380600178342,53.40546622591302],"type":"Point"}
}