{
  "type": "Feature",
  "properties": {
    "iso:country":"GB",
    "wof:name":"EN3 4AB",
    "wof:placetype":"postalcode"
},
  "geometry": {"coordinates":[-0.05070753023352,51.64386370469515],"type":"Point"}
}