{
  "type": "Feature",
  "properties": {
    "iso:country":"GB",
    "wof:name":"TF12 5SP",
    "wof:placetype":"postalcode"
},
  "geometry": {"coordinates":[-2.47108645588263,52.6081997914953],"type":"Point"}
}