{
  "type": "Feature",
  "properties": {
    "date:inception_lower": "1980-01-01",
    "date:inception_upper": "1980-01-01",
    "iso:country": "GB",
    "wof:name": "TF12 5SP",
    "wof:placetype": "postalcode"
  },
  "geometry": {"coordinates":[-2.471085,52.608233],"type":"Point"}
}
