{
  "type": "Feature",
  "properties": {
    "iso:country":"GB",
    "wof:name":"SG8 0LE",
    "wof:placetype":"postalcode"
},
  "geometry": {"coordinates":[-0.14617199978557,52.0907480890427],"type":"Point"}
}