{
  "type": "Feature",
  "properties": {
    "date:inception_lower":"1980-01-01",
    "date:inception_upper":"1980-01-31",
    "iso:country":"GB",
    "wof:name":"SG8 0LE",
    "wof:placetype":"postalcode"
},
  "geometry": {"coordinates":[-0.146146,52.090759],"type":"Point"}
}