{
  "type": "Feature",
  "properties": {
    "iso:country":"GB",
    "wof:name":"ST20 0RQ",
    "wof:placetype":"postalcode"
},
  "geometry": {"coordinates":[-2.38164965971207,52.86329671892456],"type":"Point"}
}