{
  "type": "Feature",
  "properties": {
    "date:inception_lower": "1980-01-01",
    "date:inception_upper": "1980-01-01",
    "iso:country": "GB",
    "wof:name": "ST20 0RQ",
    "wof:placetype": "postalcode"
  },
  "geometry": {"coordinates":[-2.38165,52.863297],"type":"Point"}
}
