{
  "type": "Feature",
  "properties": {
    "iso:country": "GB",
    "wof:name": "ME18 5PD",
    "wof:placetype": "postalcode"
  },
  "geometry": {"coordinates":[0.41547,51.255958],"type":"Point"}
}
