{
  "type": "Feature",
  "properties": {
    "date:inception_lower": "1991-09-01",
    "date:inception_upper": "1991-09-01",
    "iso:country": "GB",
    "wof:name": "BB5 5YB",
    "wof:placetype": "postalcode"
  },
  "geometry": {"coordinates":[-2.34375,53.791794],"type":"Point"}
}
