{
  "type": "Feature",
  "properties": {
    "iso:country":"GB",
    "wof:name":"BB5 5YB",
    "wof:placetype":"postalcode"
},
  "geometry": {"coordinates":[-2.34374984962856,53.79179385276689],"type":"Point"}
}