{
  "type": "Feature",
  "properties": {
    "iso:country":"GB",
    "wof:name":"BH8 9DE",
    "wof:placetype":"postalcode"
},
  "geometry": {"coordinates":[-1.84963329887272,50.74293659520576],"type":"Point"}
}