{
  "type": "Feature",
  "properties": {
    "iso:country": "GB",
    "wof:name": "NN1 3DL",
    "wof:placetype": "postalcode"
  },
  "geometry": {"coordinates":[-0.887864,52.241609],"type":"Point"}
}
