{
  "type": "Feature",
  "properties": {
    "iso:country":"GB",
    "wof:name":"B92 9DL",
    "wof:placetype":"postalcode"
},
  "geometry": {"coordinates":[-1.76482718827343,52.44953164055531],"type":"Point"}
}