{
  "type": "Feature",
  "properties": {
    "date:inception_lower": "1980-01-01",
    "date:inception_upper": "1980-01-01",
    "iso:country": "GB",
    "wof:name": "B92 9DL",
    "wof:placetype": "postalcode"
  },
  "geometry": {"coordinates":[-1.765335,52.449601],"type":"Point"}
}
