{
  "type": "Feature",
  "properties": {
    "iso:country":"GB",
    "wof:name":"LA2 7FL",
    "wof:placetype":"postalcode"
},
  "geometry": {"coordinates":[-2.53779209862057,54.11733887210754],"type":"Point"}
}