{
  "type": "Feature",
  "properties": {
    "iso:country": "GB",
    "wof:name": "LA2 7FL",
    "wof:placetype": "postalcode"
  },
  "geometry": {"coordinates":[-2.537547,54.117145],"type":"Point"}
}
