{
  "type": "Feature",
  "properties": {
    "date:inception_lower": "1980-01-01",
    "date:inception_upper": "1980-01-01",
    "iso:country": "GB",
    "wof:name": "PA20 0DJ",
    "wof:placetype": "postalcode"
  },
  "geometry": {"coordinates":[-5.05829,55.835584],"type":"Point"}
}
