{
  "type": "Feature",
  "properties": {
    "iso:country": "GB",
    "wof:name": "M43 7GZ",
    "wof:placetype": "postalcode"
  },
  "geometry": {"coordinates":[-2.149828,53.488464],"type":"Point"}
}
