{
  "type": "Feature",
  "properties": {
    "date:inception_lower": "1994-12-01",
    "date:inception_upper": "1994-12-01",
    "iso:country": "GB",
    "wof:name": "M43 7GZ",
    "wof:placetype": "postalcode"
  },
  "geometry": {"coordinates":[-2.149828,53.488464],"type":"Point"}
}
