{
  "type": "Feature",
  "properties": {
    "iso:country":"GB",
    "wof:name":"YO15 1AE",
    "wof:placetype":"postalcode"
},
  "geometry": {"coordinates":[-0.12208835031786,54.11067097817809],"type":"Point"}
}