{
  "type": "Feature",
  "properties": {
    "iso:country":"GB",
    "wof:name":"NE66 3PZ",
    "wof:placetype":"postalcode"
},
  "geometry": {"coordinates":[-1.63240757045944,55.39269156187282],"type":"Point"}
}