{
  "type": "Feature",
  "properties": {
    "iso:country":"GB",
    "wof:name":"BN14 9PF",
    "wof:placetype":"postalcode"
},
  "geometry": {"coordinates":[-0.38216515995583,50.83115292331597],"type":"Point"}
}