{
  "type": "Feature",
  "properties": {
    "iso:country":"GB",
    "wof:name":"WF17 6EW",
    "wof:placetype":"postalcode"
},
  "geometry": {"coordinates":[-1.63231432522844,53.70309289008103],"type":"Point"}
}