{
  "type": "Feature",
  "properties": {
    "date:inception_lower": "2009-09-01",
    "date:inception_upper": "2009-09-01",
    "iso:country": "GB",
    "wof:name": "WF17 6EW",
    "wof:placetype": "postalcode"
  },
  "geometry": {"coordinates":[-1.632314,53.703093],"type":"Point"}
}
