{
  "type": "Feature",
  "properties": {
    "iso:country":"GB",
    "wof:name":"EX36 3ES",
    "wof:placetype":"postalcode"
},
  "geometry": {"coordinates":[-3.83259553065269,51.06950104087115],"type":"Point"}
}