{
  "type": "Feature",
  "properties": {
    "date:inception_lower": "1980-01-01",
    "date:inception_upper": "1980-01-01",
    "iso:country": "GB",
    "wof:name": "CO14 8UH",
    "wof:placetype": "postalcode"
  },
  "geometry": {"coordinates":[1.252763,51.846473],"type":"Point"}
}
