{
  "type": "Feature",
  "properties": {
    "iso:country": "GB",
    "wof:name": "SP10 4BP",
    "wof:placetype": "postalcode"
  },
  "geometry": {"coordinates":[-1.484366,51.221168],"type":"Point"}
}
