{
  "type": "Feature",
  "properties": {
    "date:inception_lower":"1980-01-01",
    "date:inception_upper":"1980-01-31",
    "iso:country":"GB",
    "wof:name":"SP10 4BP",
    "wof:placetype":"postalcode"
},
  "geometry": {"coordinates":[-1.484366,51.221168],"type":"Point"}
}