{
  "type": "Feature",
  "properties": {
    "iso:country": "GB",
    "wof:name": "G83 0UX",
    "wof:placetype": "postalcode"
  },
  "geometry": {"coordinates":[-4.580514,55.992047],"type":"Point"}
}
