{
  "type": "Feature",
  "properties": {
    "iso:country":"GB",
    "wof:name":"CW10 9PW",
    "wof:placetype":"postalcode"
},
  "geometry": {"coordinates":[-2.44792213968716,53.19369675370378],"type":"Point"}
}