{
  "type": "Feature",
  "properties": {
    "date:inception_lower": "2008-03-01",
    "date:inception_upper": "2008-03-01",
    "iso:country": "GB",
    "wof:name": "CW10 9PW",
    "wof:placetype": "postalcode"
  },
  "geometry": {"coordinates":[-2.447922,53.193697],"type":"Point"}
}
