{
  "type": "Feature",
  "properties": {
    "date:inception_lower":"2004-05-01",
    "date:inception_upper":"2004-05-31",
    "iso:country":"GB",
    "wof:name":"GU14 7PB",
    "wof:placetype":"postalcode"
},
  "geometry": {"coordinates":[-0.760828,51.293016],"type":"Point"}
}