{
  "type": "Feature",
  "properties": {
    "iso:country":"GB",
    "wof:name":"CM2 7UA",
    "wof:placetype":"postalcode"
},
  "geometry": {"coordinates":[0.5256219488557,51.71343977383076],"type":"Point"}
}