{
  "type": "Feature",
  "properties": {
    "iso:country":"GB",
    "wof:name":"TF10 7PH",
    "wof:placetype":"postalcode"
},
  "geometry": {"coordinates":[-2.38869503499931,52.76909086031883],"type":"Point"}
}