{
  "type": "Feature",
  "properties": {
    "iso:country":"GB",
    "wof:name":"LE15 6JX",
    "wof:placetype":"postalcode"
},
  "geometry": {"coordinates":[-0.72440499776537,52.67035538484903],"type":"Point"}
}