{
  "type": "Feature",
  "properties": {
    "date:inception_lower": "1991-01-01",
    "date:inception_upper": "1991-01-01",
    "iso:country": "GB",
    "wof:name": "LE15 6JX",
    "wof:placetype": "postalcode"
  },
  "geometry": {"coordinates":[-0.724405,52.670355],"type":"Point"}
}
