{
  "type": "Feature",
  "properties": {
    "iso:country":"GB",
    "wof:name":"LE2 1LB",
    "wof:placetype":"postalcode"
},
  "geometry": {"coordinates":[-1.10746127021706,52.62174328367715],"type":"Point"}
}