{
  "type": "Feature",
  "properties": {
    "iso:country": "GB",
    "wof:name": "LE2 1LB",
    "wof:placetype": "postalcode"
  },
  "geometry": {"coordinates":[-1.107461,52.621743],"type":"Point"}
}
