{
  "type": "Feature",
  "properties": {
    "iso:country":"GB",
    "wof:name":"CB24 6DB",
    "wof:placetype":"postalcode"
},
  "geometry": {"coordinates":[0.16448949060564,52.24660719986931],"type":"Point"}
}