{
  "type": "Feature",
  "properties": {
    "iso:country":"GB",
    "wof:name":"WS3 1JX",
    "wof:placetype":"postalcode"
},
  "geometry": {"coordinates":[-1.98186445795578,52.61496155005757],"type":"Point"}
}