{
  "type": "Feature",
  "properties": {
    "iso:country": "GB",
    "wof:name": "AB22 8GW",
    "wof:placetype": "postalcode"
  },
  "geometry": {"coordinates":[-2.110487,57.177927],"type":"Point"}
}
