{
  "type": "Feature",
  "properties": {
    "date:inception_lower":"1998-12-01",
    "date:inception_upper":"1998-12-31",
    "iso:country":"GB",
    "wof:name":"NN6 7ZD",
    "wof:placetype":"postalcode"
},
  "geometry": {"coordinates":[-1.074065,52.340989],"type":"Point"}
}