{
  "type": "Feature",
  "properties": {
    "iso:country":"GB",
    "wof:name":"NN6 7ZD",
    "wof:placetype":"postalcode"
},
  "geometry": {"coordinates":[-1.07415220209076,52.34100966200746],"type":"Point"}
}