{
  "type": "Feature",
  "properties": {
    "iso:country":"GB",
    "wof:name":"NR10 5BH",
    "wof:placetype":"postalcode"
},
  "geometry": {"coordinates":[1.36545089383633,52.78478725236243],"type":"Point"}
}