{
  "type": "Feature",
  "properties": {
    "iso:country": "GB",
    "wof:name": "NR10 5BH",
    "wof:placetype": "postalcode"
  },
  "geometry": {"coordinates":[1.365451,52.784787],"type":"Point"}
}
