{
  "type": "Feature",
  "properties": {
    "iso:country":"GB",
    "wof:name":"NE26 3AN",
    "wof:placetype":"postalcode"
},
  "geometry": {"coordinates":[-1.4564071259355,55.04597761214816],"type":"Point"}
}