{
  "type": "Feature",
  "properties": {
    "iso:country":"GB",
    "wof:name":"LE4 8AH",
    "wof:placetype":"postalcode"
},
  "geometry": {"coordinates":[-1.10221925552427,52.67145430719187],"type":"Point"}
}