{
  "type": "Feature",
  "properties": {
    "date:inception_lower": "1980-01-01",
    "date:inception_upper": "1980-01-01",
    "iso:country": "GB",
    "wof:name": "LE4 8AH",
    "wof:placetype": "postalcode"
  },
  "geometry": {"coordinates":[-1.102219,52.671454],"type":"Point"}
}
