{
  "type": "Feature",
  "properties": {
    "date:inception_lower": "1981-09-01",
    "date:inception_upper": "1981-09-01",
    "iso:country": "GB",
    "wof:name": "MK13 0PD",
    "wof:placetype": "postalcode"
  },
  "geometry": {"coordinates":[-0.791027,52.056453],"type":"Point"}
}
