{
  "type": "Feature",
  "properties": {
    "iso:country":"GB",
    "wof:name":"MK13 0PD",
    "wof:placetype":"postalcode"
},
  "geometry": {"coordinates":[-0.79102720899622,52.05645324618003],"type":"Point"}
}