{
  "type": "Feature",
  "properties": {
    "iso:country":"GB",
    "wof:name":"AB31 4PA",
    "wof:placetype":"postalcode"
},
  "geometry": {"coordinates":[-2.6294597478056,57.14340103123654],"type":"Point"}
}