{
  "type": "Feature",
  "properties": {
    "iso:country":"GB",
    "wof:name":"CW5 6ER",
    "wof:placetype":"postalcode"
},
  "geometry": {"coordinates":[-2.51206381255093,53.07101616803264],"type":"Point"}
}