{
  "type": "Feature",
  "properties": {
    "iso:country": "GB",
    "wof:name": "CW5 6ER",
    "wof:placetype": "postalcode"
  },
  "geometry": {"coordinates":[-2.512064,53.071016],"type":"Point"}
}
