{
  "type": "Feature",
  "properties": {
    "iso:country": "GB",
    "wof:name": "HU12 9HZ",
    "wof:placetype": "postalcode"
  },
  "geometry": {"coordinates":[-0.143921,53.73269],"type":"Point"}
}
