{
  "type": "Feature",
  "properties": {
    "iso:country":"GB",
    "wof:name":"HU12 9HZ",
    "wof:placetype":"postalcode"
},
  "geometry": {"coordinates":[-0.14392096649989,53.73268979934402],"type":"Point"}
}