{
  "type": "Feature",
  "properties": {
    "iso:country":"GB",
    "wof:name":"NR15 2RX",
    "wof:placetype":"postalcode"
},
  "geometry": {"coordinates":[1.25618976083348,52.47827200090641],"type":"Point"}
}