{
  "type": "Feature",
  "properties": {
    "iso:country": "GB",
    "wof:name": "KA13 6NL",
    "wof:placetype": "postalcode"
  },
  "geometry": {"coordinates":[-4.717705,55.659492],"type":"Point"}
}
