{
  "type": "Feature",
  "properties": {
    "iso:country":"GB",
    "wof:name":"CA11 0TZ",
    "wof:placetype":"postalcode"
},
  "geometry": {"coordinates":[-2.87043260386689,54.66954602552671],"type":"Point"}
}