{
  "type": "Feature",
  "properties": {
    "date:inception_lower":"1991-01-01",
    "date:inception_upper":"1991-01-31",
    "iso:country":"GB",
    "wof:name":"CA11 0TZ",
    "wof:placetype":"postalcode"
},
  "geometry": {"coordinates":[-2.870433,54.669546],"type":"Point"}
}