{
  "type": "Feature",
  "properties": {
    "date:inception_lower": "1980-01-01",
    "date:inception_upper": "1980-01-01",
    "iso:country": "GB",
    "wof:name": "MK41 8PA",
    "wof:placetype": "postalcode"
  },
  "geometry": {"coordinates":[-0.438855,52.156542],"type":"Point"}
}
