{
  "type": "Feature",
  "properties": {
    "iso:country":"GB",
    "wof:name":"EH4 4ST",
    "wof:placetype":"postalcode"
},
  "geometry": {"coordinates":[-3.2643784005532,55.97200362472113],"type":"Point"}
}