{
  "type": "Feature",
  "properties": {
    "iso:country":"GB",
    "wof:name":"G64 1LN",
    "wof:placetype":"postalcode"
},
  "geometry": {"coordinates":[-4.19811131509457,55.90263263769177],"type":"Point"}
}