{
  "type": "Feature",
  "properties": {
    "iso:country": "GB",
    "wof:name": "G64 1LN",
    "wof:placetype": "postalcode"
  },
  "geometry": {"coordinates":[-4.198111,55.902633],"type":"Point"}
}
