{
  "type": "Feature",
  "properties": {
    "iso:country": "GB",
    "wof:name": "SW1Y 4RX",
    "wof:placetype": "postalcode"
  },
  "geometry": {"coordinates":[-0.132331,51.50998],"type":"Point"}
}
