{
  "type": "Feature",
  "properties": {
    "date:inception_lower":"1998-12-01",
    "date:inception_upper":"1998-12-31",
    "iso:country":"GB",
    "wof:name":"SW1Y 4RX",
    "wof:placetype":"postalcode"
},
  "geometry": {"coordinates":[-0.132331,51.50998],"type":"Point"}
}