{
  "type": "Feature",
  "properties": {
    "iso:country":"GB",
    "wof:name":"HX1 1DF",
    "wof:placetype":"postalcode"
},
  "geometry": {"coordinates":[-1.8599994819244,53.72112854407873],"type":"Point"}
}