{
  "type": "Feature",
  "properties": {
    "iso:country":"GB",
    "wof:name":"UB5 6ET",
    "wof:placetype":"postalcode"
},
  "geometry": {"coordinates":[-0.38813697827188,51.53121051311339],"type":"Point"}
}