{
  "type": "Feature",
  "properties": {
    "iso:country":"GB",
    "wof:name":"CV7 7LX",
    "wof:placetype":"postalcode"
},
  "geometry": {"coordinates":[-1.64608212433877,52.43890663092618],"type":"Point"}
}