{
  "type": "Feature",
  "properties": {
    "iso:country":"GB",
    "wof:name":"TR1 3EW",
    "wof:placetype":"postalcode"
},
  "geometry": {"coordinates":[-5.06142054787287,50.26194064067306],"type":"Point"}
}