{
  "type": "Feature",
  "properties": {
    "iso:country":"GB",
    "wof:name":"TQ13 7BP",
    "wof:placetype":"postalcode"
},
  "geometry": {"coordinates":[-3.74455506733552,50.52235998636592],"type":"Point"}
}