{
  "type": "Feature",
  "properties": {
    "iso:country":"GB",
    "wof:name":"PR8 6HU",
    "wof:placetype":"postalcode"
},
  "geometry": {"coordinates":[-2.97665408967089,53.63200739236093],"type":"Point"}
}