{
  "type": "Feature",
  "properties": {
    "iso:country":"GB",
    "wof:name":"LL48 6BS",
    "wof:placetype":"postalcode"
},
  "geometry": {"coordinates":[-4.06751201289579,52.93233325102852],"type":"Point"}
}