{
  "type": "Feature",
  "properties": {
    "iso:country": "GB",
    "wof:name": "CM20 3NX",
    "wof:placetype": "postalcode"
  },
  "geometry": {"coordinates":[0.107696,51.770997],"type":"Point"}
}
