{
  "type": "Feature",
  "properties": {
    "date:inception_lower": "1985-04-01",
    "date:inception_upper": "1985-04-01",
    "iso:country": "GB",
    "wof:name": "PO8 9TT",
    "wof:placetype": "postalcode"
  },
  "geometry": {"coordinates":[-1.023314,50.910519],"type":"Point"}
}
