{
  "type": "Feature",
  "properties": {
    "iso:country":"GB",
    "wof:name":"LS11 8BA",
    "wof:placetype":"postalcode"
},
  "geometry": {"coordinates":[-1.57827122709574,53.77392109114367],"type":"Point"}
}