{
  "type": "Feature",
  "properties": {
    "date:inception_lower":"1980-01-01",
    "date:inception_upper":"1980-01-31",
    "iso:country":"GB",
    "wof:name":"LS11 8BA",
    "wof:placetype":"postalcode"
},
  "geometry": {"coordinates":[-1.578271,53.773921],"type":"Point"}
}