{
  "type": "Feature",
  "properties": {
    "date:inception_lower": "1980-01-01",
    "date:inception_upper": "1980-01-01",
    "iso:country": "GB",
    "wof:name": "G14 9AE",
    "wof:placetype": "postalcode"
  },
  "geometry": {"coordinates":[-4.354401,55.884787],"type":"Point"}
}
