{
  "type": "Feature",
  "properties": {
    "iso:country":"GB",
    "wof:name":"G14 9AE",
    "wof:placetype":"postalcode"
},
  "geometry": {"coordinates":[-4.35440149856403,55.88478673343803],"type":"Point"}
}