{
  "type": "Feature",
  "properties": {
    "iso:country":"GB",
    "wof:name":"SW19 8PA",
    "wof:placetype":"postalcode"
},
  "geometry": {"coordinates":[-0.19172402438607,51.42353079551332],"type":"Point"}
}