{
  "type": "Feature",
  "properties": {
    "iso:country":"GB",
    "wof:name":"DY2 7HB",
    "wof:placetype":"postalcode"
},
  "geometry": {"coordinates":[-2.06959941067673,52.50674962258698],"type":"Point"}
}