{
  "type": "Feature",
  "properties": {
    "iso:country": "GB",
    "wof:name": "DY2 7HB",
    "wof:placetype": "postalcode"
  },
  "geometry": {"coordinates":[-2.069599,52.50675],"type":"Point"}
}
