{
  "type": "Feature",
  "properties": {
    "date:inception_lower": "1980-01-01",
    "date:inception_upper": "1980-01-01",
    "iso:country": "GB",
    "wof:name": "DY2 7HB",
    "wof:placetype": "postalcode"
  },
  "geometry": {"coordinates":[-2.069579,52.506765],"type":"Point"}
}
