{
  "type": "Feature",
  "properties": {
    "iso:country":"GB",
    "wof:name":"EX6 7ED",
    "wof:placetype":"postalcode"
},
  "geometry": {"coordinates":[-3.68787162213897,50.68587218375984],"type":"Point"}
}