{
  "type": "Feature",
  "properties": {
    "iso:country":"GB",
    "wof:name":"BS5 6LA",
    "wof:placetype":"postalcode"
},
  "geometry": {"coordinates":[-2.5604684824338,51.46950188313972],"type":"Point"}
}