{
  "type": "Feature",
  "properties": {
    "date:inception_lower": "2008-07-01",
    "date:inception_upper": "2008-07-01",
    "iso:country": "GB",
    "wof:name": "TN9 2EW",
    "wof:placetype": "postalcode"
  },
  "geometry": {"coordinates":[0.284552,51.187575],"type":"Point"}
}
