{
  "type": "Feature",
  "properties": {
    "iso:country":"GB",
    "wof:name":"TN9 2EW",
    "wof:placetype":"postalcode"
},
  "geometry": {"coordinates":[0.2845516377301,51.1875747197096],"type":"Point"}
}