{
  "type": "Feature",
  "properties": {
    "iso:country":"GB",
    "wof:name":"WA15 7LN",
    "wof:placetype":"postalcode"
},
  "geometry": {"coordinates":[-2.30614722427361,53.39673417158243],"type":"Point"}
}