{
  "type": "Feature",
  "properties": {
    "date:inception_lower": "1990-07-01",
    "date:inception_upper": "1990-07-01",
    "iso:country": "GB",
    "wof:name": "WA15 7LN",
    "wof:placetype": "postalcode"
  },
  "geometry": {"coordinates":[-2.306147,53.396734],"type":"Point"}
}
