{
  "type": "Feature",
  "properties": {
    "iso:country":"GB",
    "wof:name":"SK15 2NY",
    "wof:placetype":"postalcode"
},
  "geometry": {"coordinates":[-2.04530527242974,53.48394747967698],"type":"Point"}
}