{
  "type": "Feature",
  "properties": {
    "date:inception_lower": "1980-01-01",
    "date:inception_upper": "1980-01-01",
    "iso:country": "GB",
    "wof:name": "SK15 2NY",
    "wof:placetype": "postalcode"
  },
  "geometry": {"coordinates":[-2.045305,53.483947],"type":"Point"}
}
