{
  "type": "Feature",
  "properties": {
    "date:inception_lower": "2006-01-01",
    "date:inception_upper": "2006-01-01",
    "iso:country": "GB",
    "wof:name": "NE22 7DE",
    "wof:placetype": "postalcode"
  },
  "geometry": {"coordinates":[-1.58842,55.146501],"type":"Point"}
}
