{
  "type": "Feature",
  "properties": {
    "iso:country":"GB",
    "wof:name":"NE22 7DE",
    "wof:placetype":"postalcode"
},
  "geometry": {"coordinates":[-1.58841965083156,55.14650139255123],"type":"Point"}
}