{
  "type": "Feature",
  "properties": {
    "iso:country": "GB",
    "wof:name": "DG2 8BQ",
    "wof:placetype": "postalcode"
  },
  "geometry": {"coordinates":[-3.577334,54.901671],"type":"Point"}
}
