{
  "type": "Feature",
  "properties": {
    "iso:country":"GB",
    "wof:name":"DG2 8BQ",
    "wof:placetype":"postalcode"
},
  "geometry": {"coordinates":[-3.57733398451763,54.90167134233683],"type":"Point"}
}