{
  "type": "Feature",
  "properties": {
    "iso:country":"GB",
    "wof:name":"KA4 8DA",
    "wof:placetype":"postalcode"
},
  "geometry": {"coordinates":[-4.39248162962513,55.59625878016146],"type":"Point"}
}