{
  "type": "Feature",
  "properties": {
    "date:inception_lower": "1980-01-01",
    "date:inception_upper": "1980-01-01",
    "iso:country": "GB",
    "wof:name": "KA4 8DA",
    "wof:placetype": "postalcode"
  },
  "geometry": {"coordinates":[-4.392482,55.596259],"type":"Point"}
}
