{
  "type": "Feature",
  "properties": {
    "iso:country": "GB",
    "wof:name": "TS14 7LR",
    "wof:placetype": "postalcode"
  },
  "geometry": {"coordinates":[-1.049443,54.526142],"type":"Point"}
}
