{
  "type": "Feature",
  "properties": {
    "iso:country":"GB",
    "wof:name":"HP14 3PR",
    "wof:placetype":"postalcode"
},
  "geometry": {"coordinates":[-0.85992602516264,51.62834208695068],"type":"Point"}
}