{
  "type": "Feature",
  "properties": {
    "date:inception_lower": "1980-01-01",
    "date:inception_upper": "1980-01-01",
    "iso:country": "GB",
    "wof:name": "HP14 3PR",
    "wof:placetype": "postalcode"
  },
  "geometry": {"coordinates":[-0.859926,51.628342],"type":"Point"}
}
