{
  "type": "Feature",
  "properties": {
    "iso:country": "GB",
    "wof:name": "HP14 3PR",
    "wof:placetype": "postalcode"
  },
  "geometry": {"coordinates":[-0.859926,51.628342],"type":"Point"}
}
