{
  "type": "Feature",
  "properties": {
    "date:inception_lower": "1980-01-01",
    "date:inception_upper": "1980-01-01",
    "iso:country": "GB",
    "wof:name": "PO39 0JD",
    "wof:placetype": "postalcode"
  },
  "geometry": {"coordinates":[-1.566699,50.669793],"type":"Point"}
}
