{
  "type": "Feature",
  "properties": {
    "iso:country":"GB",
    "wof:name":"L16 2LQ",
    "wof:placetype":"postalcode"
},
  "geometry": {"coordinates":[-2.87089456524789,53.40230902200783],"type":"Point"}
}