{
  "type": "Feature",
  "properties": {
    "date:inception_lower":"1980-01-01",
    "date:inception_upper":"1980-01-31",
    "iso:country":"GB",
    "wof:name":"L16 2LQ",
    "wof:placetype":"postalcode"
},
  "geometry": {"coordinates":[-2.870895,53.402309],"type":"Point"}
}