{
  "type": "Feature",
  "properties": {
    "iso:country":"GB",
    "wof:name":"B26 3JY",
    "wof:placetype":"postalcode"
},
  "geometry": {"coordinates":[-1.77801153880097,52.45233500594726],"type":"Point"}
}