{
  "type": "Feature",
  "properties": {
    "iso:country": "GB",
    "wof:name": "B26 3JY",
    "wof:placetype": "postalcode"
  },
  "geometry": {"coordinates":[-1.778011,52.452335],"type":"Point"}
}
