{
  "type": "Feature",
  "properties": {
    "date:inception_lower": "2001-12-01",
    "date:inception_upper": "2001-12-01",
    "iso:country": "GB",
    "wof:name": "SA4 3AL",
    "wof:placetype": "postalcode"
  },
  "geometry": {"coordinates":[-4.106148,51.640381],"type":"Point"}
}
