{
  "type": "Feature",
  "properties": {
    "iso:country":"GB",
    "wof:name":"SA4 3AL",
    "wof:placetype":"postalcode"
},
  "geometry": {"coordinates":[-4.10614790587134,51.64038073742712],"type":"Point"}
}