{
  "type": "Feature",
  "properties": {
    "date:inception_lower": "1980-01-01",
    "date:inception_upper": "1980-01-01",
    "iso:country": "GB",
    "wof:name": "SE2 9HT",
    "wof:placetype": "postalcode"
  },
  "geometry": {"coordinates":[0.105825,51.489579],"type":"Point"}
}
