{
  "type": "Feature",
  "properties": {
    "iso:country":"GB",
    "wof:name":"SE2 9HT",
    "wof:placetype":"postalcode"
},
  "geometry": {"coordinates":[0.10582538003372,51.48957881703846],"type":"Point"}
}