{
  "type": "Feature",
  "properties": {
    "date:inception_lower": "1980-01-01",
    "date:inception_upper": "1980-01-01",
    "iso:country": "GB",
    "wof:name": "NR16 2DN",
    "wof:placetype": "postalcode"
  },
  "geometry": {"coordinates":[1.037101,52.430082],"type":"Point"}
}
