{
  "type": "Feature",
  "properties": {
    "iso:country":"GB",
    "wof:name":"AL4 8LL",
    "wof:placetype":"postalcode"
},
  "geometry": {"coordinates":[-0.30510885348603,51.83565444979761],"type":"Point"}
}