{
  "type": "Feature",
  "properties": {
    "iso:country":"GB",
    "wof:name":"HX6 3BJ",
    "wof:placetype":"postalcode"
},
  "geometry": {"coordinates":[-1.9198289199788,53.70456440501813],"type":"Point"}
}