{
  "type": "Feature",
  "properties": {
    "iso:country":"GB",
    "wof:name":"SO21 2NZ",
    "wof:placetype":"postalcode"
},
  "geometry": {"coordinates":[-1.38015760276732,51.07552111047415],"type":"Point"}
}