{
  "type": "Feature",
  "properties": {
    "iso:country": "GB",
    "wof:name": "SO21 2NZ",
    "wof:placetype": "postalcode"
  },
  "geometry": {"coordinates":[-1.380158,51.075521],"type":"Point"}
}
