{
  "type": "Feature",
  "properties": {
    "iso:country": "GB",
    "wof:name": "RG14 5SA",
    "wof:placetype": "postalcode"
  },
  "geometry": {"coordinates":[-1.312492,51.398981],"type":"Point"}
}
