{
  "type": "Feature",
  "properties": {
    "date:inception_lower": "1980-01-01",
    "date:inception_upper": "1980-01-01",
    "iso:country": "GB",
    "wof:name": "BD23 2NE",
    "wof:placetype": "postalcode"
  },
  "geometry": {"coordinates":[-2.018419,53.957105],"type":"Point"}
}
