{
  "type": "Feature",
  "properties": {
    "date:inception_lower":"1980-01-01",
    "date:inception_upper":"1980-01-31",
    "iso:country":"GB",
    "wof:name":"LL47 6TU",
    "wof:placetype":"postalcode"
},
  "geometry": {"coordinates":[-4.065961,52.902277],"type":"Point"}
}