{
  "type": "Feature",
  "properties": {
    "iso:country":"GB",
    "wof:name":"LL47 6TU",
    "wof:placetype":"postalcode"
},
  "geometry": {"coordinates":[-4.06596128196597,52.90227674353874],"type":"Point"}
}