{
  "type": "Feature",
  "properties": {
    "iso:country":"GB",
    "wof:name":"DE12 7DX",
    "wof:placetype":"postalcode"
},
  "geometry": {"coordinates":[-1.51931058612791,52.70050629722743],"type":"Point"}
}