{
  "type": "Feature",
  "properties": {
    "iso:country": "GB",
    "wof:name": "RH19 1QP",
    "wof:placetype": "postalcode"
  },
  "geometry": {"coordinates":[-0.024545,51.134334],"type":"Point"}
}
