{
  "type": "Feature",
  "properties": {
    "iso:country": "GB",
    "wof:name": "WS5 3JP",
    "wof:placetype": "postalcode"
  },
  "geometry": {"coordinates":[-1.948838,52.565508],"type":"Point"}
}
