{
  "type": "Feature",
  "properties": {
    "iso:country":"GB",
    "wof:name":"WS5 3JP",
    "wof:placetype":"postalcode"
},
  "geometry": {"coordinates":[-1.94883847984496,52.56550811841259],"type":"Point"}
}