{
  "type": "Feature",
  "properties": {
    "date:inception_lower": "1980-01-01",
    "date:inception_upper": "1980-01-01",
    "iso:country": "GB",
    "wof:name": "WS5 3JP",
    "wof:placetype": "postalcode"
  },
  "geometry": {"coordinates":[-1.948838,52.565508],"type":"Point"}
}
