{
  "type": "Feature",
  "properties": {
    "iso:country": "GB",
    "wof:name": "ML2 0PW",
    "wof:placetype": "postalcode"
  },
  "geometry": {"coordinates":[-3.921622,55.765151],"type":"Point"}
}
