{
  "type": "Feature",
  "properties": {
    "iso:country":"GB",
    "wof:name":"SO21 3JW",
    "wof:placetype":"postalcode"
},
  "geometry": {"coordinates":[-1.33937014642904,51.15313418516367],"type":"Point"}
}