{
  "type": "Feature",
  "properties": {
    "iso:country": "GB",
    "wof:name": "SO21 3JW",
    "wof:placetype": "postalcode"
  },
  "geometry": {"coordinates":[-1.33937,51.153134],"type":"Point"}
}
