{
  "type": "Feature",
  "properties": {
    "iso:country":"GB",
    "wof:name":"HX7 7PQ",
    "wof:placetype":"postalcode"
},
  "geometry": {"coordinates":[-2.05909626742415,53.75511620582961],"type":"Point"}
}