{
  "type": "Feature",
  "properties": {
    "iso:country": "GB",
    "wof:name": "SY10 7EY",
    "wof:placetype": "postalcode"
  },
  "geometry": {"coordinates":[-3.070161,52.897972],"type":"Point"}
}
