{
  "type": "Feature",
  "properties": {
    "date:inception_lower": "1987-04-01",
    "date:inception_upper": "1987-04-01",
    "iso:country": "GB",
    "wof:name": "TR11 5BU",
    "wof:placetype": "postalcode"
  },
  "geometry": {"coordinates":[-5.084627,50.141079],"type":"Point"}
}
