{
  "type": "Feature",
  "properties": {
    "iso:country":"GB",
    "wof:name":"TR11 5BU",
    "wof:placetype":"postalcode"
},
  "geometry": {"coordinates":[-5.08462695610431,50.14107922891396],"type":"Point"}
}