{
  "type": "Feature",
  "properties": {
    "iso:country":"GB",
    "wof:name":"CV13 0RH",
    "wof:placetype":"postalcode"
},
  "geometry": {"coordinates":[-1.40125822771162,52.62407720409485],"type":"Point"}
}