{
  "type": "Feature",
  "properties": {
    "iso:country":"GB",
    "wof:name":"N10 3PY",
    "wof:placetype":"postalcode"
},
  "geometry": {"coordinates":[-0.13882528704005,51.58714892488975],"type":"Point"}
}