{
  "type": "Feature",
  "properties": {
    "iso:country": "GB",
    "wof:name": "RH10 5HR",
    "wof:placetype": "postalcode"
  },
  "geometry": {"coordinates":[-0.183509,51.097064],"type":"Point"}
}
