{
  "type": "Feature",
  "properties": {
    "iso:country":"GB",
    "wof:name":"TR7 2DR",
    "wof:placetype":"postalcode"
},
  "geometry": {"coordinates":[-5.08270545261674,50.40942831293167],"type":"Point"}
}