{
  "type": "Feature",
  "properties": {
    "iso:country": "GB",
    "wof:name": "ML1 3DU",
    "wof:placetype": "postalcode"
  },
  "geometry": {"coordinates":[-4.006664,55.78687],"type":"Point"}
}
