{
  "type": "Feature",
  "properties": {
    "iso:country":"GB",
    "wof:name":"M20 3GW",
    "wof:placetype":"postalcode"
},
  "geometry": {"coordinates":[-2.23112228038216,53.43329777924653],"type":"Point"}
}