{
  "type": "Feature",
  "properties": {
    "iso:country": "GB",
    "wof:name": "SW11 4DL",
    "wof:placetype": "postalcode"
  },
  "geometry": {"coordinates":[-0.153493,51.475937],"type":"Point"}
}
