{
  "type": "Feature",
  "properties": {
    "iso:country":"GB",
    "wof:name":"LL28 4AH",
    "wof:placetype":"postalcode"
},
  "geometry": {"coordinates":[-3.75014004793801,53.30210102584358],"type":"Point"}
}