{
  "type": "Feature",
  "properties": {
    "iso:country": "GB",
    "wof:name": "SO51 8JR",
    "wof:placetype": "postalcode"
  },
  "geometry": {"coordinates":[-1.500182,50.988565],"type":"Point"}
}
