{
  "type": "Feature",
  "properties": {
    "date:inception_lower": "2005-01-01",
    "date:inception_upper": "2005-01-01",
    "iso:country": "GB",
    "wof:name": "SO51 8JR",
    "wof:placetype": "postalcode"
  },
  "geometry": {"coordinates":[-1.500182,50.988565],"type":"Point"}
}
