{
  "type": "Feature",
  "properties": {
    "iso:country":"GB",
    "wof:name":"SO51 8JR",
    "wof:placetype":"postalcode"
},
  "geometry": {"coordinates":[-1.50018210569117,50.98856497218222],"type":"Point"}
}