{
  "type": "Feature",
  "properties": {
    "iso:country":"GB",
    "wof:name":"WF11 8AD",
    "wof:placetype":"postalcode"
},
  "geometry": {"coordinates":[-1.2377300745893,53.70552037006209],"type":"Point"}
}