{
  "type": "Feature",
  "properties": {
    "date:inception_lower": "1980-01-01",
    "date:inception_upper": "1980-01-01",
    "iso:country": "GB",
    "wof:name": "PE25 3PY",
    "wof:placetype": "postalcode"
  },
  "geometry": {"coordinates":[0.335347,53.139571],"type":"Point"}
}
