{
  "type": "Feature",
  "properties": {
    "iso:country":"GB",
    "wof:name":"LA4 5QP",
    "wof:placetype":"postalcode"
},
  "geometry": {"coordinates":[-2.85078848836904,54.06964993295519],"type":"Point"}
}