{
  "type": "Feature",
  "properties": {
    "date:inception_lower":"1980-01-01",
    "date:inception_upper":"1980-01-31",
    "iso:country":"GB",
    "wof:name":"LA4 5QP",
    "wof:placetype":"postalcode"
},
  "geometry": {"coordinates":[-2.850788,54.06965],"type":"Point"}
}