{
  "type": "Feature",
  "properties": {
    "iso:country":"GB",
    "wof:name":"TD12 4ES",
    "wof:placetype":"postalcode"
},
  "geometry": {"coordinates":[-2.25154637819772,55.66238434277234],"type":"Point"}
}