{
  "type": "Feature",
  "properties": {
    "iso:country": "GB",
    "wof:name": "PR2 2TY",
    "wof:placetype": "postalcode"
  },
  "geometry": {"coordinates":[-2.760212,53.761024],"type":"Point"}
}
