{
  "type": "Feature",
  "properties": {
    "iso:country":"GB",
    "wof:name":"PR2 2TY",
    "wof:placetype":"postalcode"
},
  "geometry": {"coordinates":[-2.76021183407394,53.7610238085863],"type":"Point"}
}