{
  "type": "Feature",
  "properties": {
    "date:inception_lower": "1980-01-01",
    "date:inception_upper": "1980-01-01",
    "iso:country": "GB",
    "wof:name": "SA3 1LY",
    "wof:placetype": "postalcode"
  },
  "geometry": {"coordinates":[-4.172129,51.555586],"type":"Point"}
}
