{
  "type": "Feature",
  "properties": {
    "iso:country":"GB",
    "wof:name":"SA3 1LY",
    "wof:placetype":"postalcode"
},
  "geometry": {"coordinates":[-4.17210594743745,51.55557266391537],"type":"Point"}
}