{
  "type": "Feature",
  "properties": {
    "iso:country": "GB",
    "wof:name": "SA3 1LY",
    "wof:placetype": "postalcode"
  },
  "geometry": {"coordinates":[-4.172128,51.555577],"type":"Point"}
}
