{
  "type": "Feature",
  "properties": {
    "date:inception_lower": "1980-01-01",
    "date:inception_upper": "1980-01-01",
    "iso:country": "GB",
    "wof:name": "EH14 7BG",
    "wof:placetype": "postalcode"
  },
  "geometry": {"coordinates":[-3.365488,55.881566],"type":"Point"}
}
