{
  "type": "Feature",
  "properties": {
    "iso:country":"GB",
    "wof:name":"EH14 7BG",
    "wof:placetype":"postalcode"
},
  "geometry": {"coordinates":[-3.36573953724326,55.88092984801586],"type":"Point"}
}