{
  "type": "Feature",
  "properties": {
    "date:inception_lower": "2020-02-01",
    "date:inception_upper": "2020-02-01",
    "iso:country": "GB",
    "wof:name": "FK1 9GJ",
    "wof:placetype": "postalcode"
  },
  "geometry": {"coordinates":[-3.78477,56.001991],"type":"Point"}
}
