{
  "type": "Feature",
  "properties": {
    "iso:country":"GB",
    "wof:name":"WF9 2SD",
    "wof:placetype":"postalcode"
},
  "geometry": {"coordinates":[-1.29566878159737,53.58779446698446],"type":"Point"}
}