{
  "type": "Feature",
  "properties": {
    "date:inception_lower": "2001-12-01",
    "date:inception_upper": "2001-12-01",
    "iso:country": "GB",
    "wof:name": "WF9 2SD",
    "wof:placetype": "postalcode"
  },
  "geometry": {"coordinates":[-1.295669,53.587794],"type":"Point"}
}
