{
  "type": "Feature",
  "properties": {
    "iso:country": "GB",
    "wof:name": "NN5 7EL",
    "wof:placetype": "postalcode"
  },
  "geometry": {"coordinates":[-0.911301,52.248645],"type":"Point"}
}
