{
  "type": "Feature",
  "properties": {
    "iso:country":"GB",
    "wof:name":"NN5 7EL",
    "wof:placetype":"postalcode"
},
  "geometry": {"coordinates":[-0.91130086955949,52.2486452751948],"type":"Point"}
}