{
  "type": "Feature",
  "properties": {
    "iso:country":"GB",
    "wof:name":"LE11 4PL",
    "wof:placetype":"postalcode"
},
  "geometry": {"coordinates":[-1.24572137389162,52.76379045431742],"type":"Point"}
}