{
  "type": "Feature",
  "properties": {
    "iso:country": "GB",
    "wof:name": "CV9 1JW",
    "wof:placetype": "postalcode"
  },
  "geometry": {"coordinates":[-1.540764,52.576676],"type":"Point"}
}
