{
  "type": "Feature",
  "properties": {
    "iso:country": "GB",
    "wof:name": "BH24 3FH",
    "wof:placetype": "postalcode"
  },
  "geometry": {"coordinates":[-1.781403,50.839571],"type":"Point"}
}
