{
  "type": "Feature",
  "properties": {
    "iso:country": "GB",
    "wof:name": "KA1 3JE",
    "wof:placetype": "postalcode"
  },
  "geometry": {"coordinates":[-4.484389,55.604785],"type":"Point"}
}
