{
  "type": "Feature",
  "properties": {
    "iso:country":"GB",
    "wof:name":"LE67 9HA",
    "wof:placetype":"postalcode"
},
  "geometry": {"coordinates":[-1.27333985956892,52.6759258345622],"type":"Point"}
}