{
  "type": "Feature",
  "properties": {
    "date:inception_lower": "1995-12-01",
    "date:inception_upper": "1995-12-01",
    "iso:country": "GB",
    "wof:name": "LE67 9HA",
    "wof:placetype": "postalcode"
  },
  "geometry": {"coordinates":[-1.27334,52.675926],"type":"Point"}
}
