{
  "type": "Feature",
  "properties": {
    "date:inception_lower": "2006-01-01",
    "date:inception_upper": "2006-01-01",
    "iso:country": "GB",
    "wof:name": "SP4 7WS",
    "wof:placetype": "postalcode"
  },
  "geometry": {"coordinates":[-1.778044,51.174436],"type":"Point"}
}
