{
  "type": "Feature",
  "properties": {
    "iso:country":"GB",
    "wof:name":"DN4 9BJ",
    "wof:placetype":"postalcode"
},
  "geometry": {"coordinates":[-1.15465264602802,53.49281553629665],"type":"Point"}
}