{
  "type": "Feature",
  "properties": {
    "iso:country":"GB",
    "wof:name":"BB12 8JP",
    "wof:placetype":"postalcode"
},
  "geometry": {"coordinates":[-2.32155110282032,53.80090639289442],"type":"Point"}
}