{
  "type": "Feature",
  "properties": {
    "date:inception_lower": "1980-01-01",
    "date:inception_upper": "1980-01-01",
    "iso:country": "GB",
    "wof:name": "BL0 9LL",
    "wof:placetype": "postalcode"
  },
  "geometry": {"coordinates":[-2.315532,53.638193],"type":"Point"}
}
