{
  "type": "Feature",
  "properties": {
    "date:inception_lower":"2009-05-01",
    "date:inception_upper":"2009-05-31",
    "iso:country":"GB",
    "wof:name":"DE22 1LA",
    "wof:placetype":"postalcode"
},
  "geometry": {"coordinates":[-1.485061,52.945615],"type":"Point"}
}