{
  "type": "Feature",
  "properties": {
    "iso:country": "GB",
    "wof:name": "DE22 1LA",
    "wof:placetype": "postalcode"
  },
  "geometry": {"coordinates":[-1.485061,52.945615],"type":"Point"}
}
