{
  "type": "Feature",
  "properties": {
    "iso:country":"GB",
    "wof:name":"WA8 7XH",
    "wof:placetype":"postalcode"
},
  "geometry": {"coordinates":[-2.76842711051629,53.37181245513352],"type":"Point"}
}