{
  "type": "Feature",
  "properties": {
    "date:inception_lower":"1992-08-01",
    "date:inception_upper":"1992-08-31",
    "iso:country":"GB",
    "wof:name":"LU4 0XZ",
    "wof:placetype":"postalcode"
},
  "geometry": {"coordinates":[-0.486349,51.900564],"type":"Point"}
}