{
  "type": "Feature",
  "properties": {
    "date:inception_lower": "2002-07-01",
    "date:inception_upper": "2002-07-01",
    "iso:country": "GB",
    "wof:name": "CF62 3LJ",
    "wof:placetype": "postalcode"
  },
  "geometry": {"coordinates":[-3.338738,51.384723],"type":"Point"}
}
