{
  "type": "Feature",
  "properties": {
    "iso:country":"GB",
    "wof:name":"CF62 3LJ",
    "wof:placetype":"postalcode"
},
  "geometry": {"coordinates":[-3.33873803552995,51.38472297287968],"type":"Point"}
}