{
  "type": "Feature",
  "properties": {
    "iso:country":"GB",
    "wof:name":"BS30 8SA",
    "wof:placetype":"postalcode"
},
  "geometry": {"coordinates":[-2.48885683680112,51.45175832009412],"type":"Point"}
}