{
  "type": "Feature",
  "properties": {
    "iso:country":"GB",
    "wof:name":"GL6 6HW",
    "wof:placetype":"postalcode"
},
  "geometry": {"coordinates":[-2.24745397436907,51.75814979839883],"type":"Point"}
}