{
  "type": "Feature",
  "properties": {
    "iso:country":"GB",
    "wof:name":"DH9 9DJ",
    "wof:placetype":"postalcode"
},
  "geometry": {"coordinates":[-1.76216483091421,54.87679481673737],"type":"Point"}
}