{
  "type": "Feature",
  "properties": {
    "iso:country":"GB",
    "wof:name":"HP3 9SB",
    "wof:placetype":"postalcode"
},
  "geometry": {"coordinates":[-0.4690606542426,51.73765345637148],"type":"Point"}
}