{
  "type": "Feature",
  "properties": {
    "iso:country": "GB",
    "wof:name": "HP3 9SB",
    "wof:placetype": "postalcode"
  },
  "geometry": {"coordinates":[-0.469169,51.73768],"type":"Point"}
}
