{
  "type": "Feature",
  "properties": {
    "iso:country":"GB",
    "wof:name":"DN8 4AN",
    "wof:placetype":"postalcode"
},
  "geometry": {"coordinates":[-0.96643617068004,53.61477910315818],"type":"Point"}
}