{
  "type": "Feature",
  "properties": {
    "iso:country":"GB",
    "wof:name":"MK42 9TD",
    "wof:placetype":"postalcode"
},
  "geometry": {"coordinates":[-0.4607635416523,52.11937243152685],"type":"Point"}
}