{
  "type": "Feature",
  "properties": {
    "iso:country":"GB",
    "wof:name":"BS40 5EY",
    "wof:placetype":"postalcode"
},
  "geometry": {"coordinates":[-2.78751426359519,51.35120421065648],"type":"Point"}
}