{
  "type": "Feature",
  "properties": {
    "date:inception_lower": "1997-12-01",
    "date:inception_upper": "1997-12-01",
    "iso:country": "GB",
    "wof:name": "BS40 5EY",
    "wof:placetype": "postalcode"
  },
  "geometry": {"coordinates":[-2.787514,51.351204],"type":"Point"}
}
