{
  "type": "Feature",
  "properties": {
    "iso:country": "GB",
    "wof:name": "BS40 5EY",
    "wof:placetype": "postalcode"
  },
  "geometry": {"coordinates":[-2.787514,51.351204],"type":"Point"}
}
