{
  "type": "Feature",
  "properties": {
    "iso:country": "GB",
    "wof:name": "CH65 9DW",
    "wof:placetype": "postalcode"
  },
  "geometry": {"coordinates":[-2.890364,53.268569],"type":"Point"}
}
