{
  "type": "Feature",
  "properties": {
    "iso:country":"GB",
    "wof:name":"B73 5NP",
    "wof:placetype":"postalcode"
},
  "geometry": {"coordinates":[-1.82567871899399,52.54788789106698],"type":"Point"}
}