{
  "type": "Feature",
  "properties": {
    "iso:country": "GB",
    "wof:name": "B73 5NP",
    "wof:placetype": "postalcode"
  },
  "geometry": {"coordinates":[-1.825679,52.547888],"type":"Point"}
}
