{
  "type": "Feature",
  "properties": {
    "iso:country":"GB",
    "wof:name":"OX14 5AW",
    "wof:placetype":"postalcode"
},
  "geometry": {"coordinates":[-1.28423469403821,51.67002468959401],"type":"Point"}
}