{
  "type": "Feature",
  "properties": {
    "date:inception_lower": "1980-01-01",
    "date:inception_upper": "1980-01-01",
    "iso:country": "GB",
    "wof:name": "RH14 0NT",
    "wof:placetype": "postalcode"
  },
  "geometry": {"coordinates":[-0.564236,51.065165],"type":"Point"}
}
