{
  "type": "Feature",
  "properties": {
    "iso:country": "GB",
    "wof:name": "RH14 0NT",
    "wof:placetype": "postalcode"
  },
  "geometry": {"coordinates":[-0.564236,51.065165],"type":"Point"}
}
