{
  "type": "Feature",
  "properties": {
    "iso:country":"GB",
    "wof:name":"RH14 0NT",
    "wof:placetype":"postalcode"
},
  "geometry": {"coordinates":[-0.56423592068752,51.06516520916787],"type":"Point"}
}