{
  "type": "Feature",
  "properties": {
    "iso:country": "GB",
    "wof:name": "TR4 8TN",
    "wof:placetype": "postalcode"
  },
  "geometry": {"coordinates":[-5.205194,50.280164],"type":"Point"}
}
