{
  "type": "Feature",
  "properties": {
    "iso:country":"GB",
    "wof:name":"LS9 7NP",
    "wof:placetype":"postalcode"
},
  "geometry": {"coordinates":[-1.52719179258421,53.80420018459717],"type":"Point"}
}