{
  "type": "Feature",
  "properties": {
    "date:inception_lower": "1980-01-01",
    "date:inception_upper": "1980-01-01",
    "iso:country": "GB",
    "wof:name": "LS9 7NP",
    "wof:placetype": "postalcode"
  },
  "geometry": {"coordinates":[-1.527238,53.804486],"type":"Point"}
}
