{
  "type": "Feature",
  "properties": {
    "iso:country":"GB",
    "wof:name":"CH64 0XA",
    "wof:placetype":"postalcode"
},
  "geometry": {"coordinates":[-3.06197953197994,53.27727885688036],"type":"Point"}
}