{
  "type": "Feature",
  "properties": {
    "iso:country": "GB",
    "wof:name": "ST5 4EH",
    "wof:placetype": "postalcode"
  },
  "geometry": {"coordinates":[-2.219299,52.977934],"type":"Point"}
}
