{
  "type": "Feature",
  "properties": {
    "iso:country":"GB",
    "wof:name":"ST5 4EH",
    "wof:placetype":"postalcode"
},
  "geometry": {"coordinates":[-2.21921033183566,52.97788115653029],"type":"Point"}
}