{
  "type": "Feature",
  "properties": {
    "iso:country": "GB",
    "wof:name": "ST18 0HZ",
    "wof:placetype": "postalcode"
  },
  "geometry": {"coordinates":[-2.040754,52.840361],"type":"Point"}
}
