{
  "type": "Feature",
  "properties": {
    "iso:country":"GB",
    "wof:name":"ST18 0HZ",
    "wof:placetype":"postalcode"
},
  "geometry": {"coordinates":[-2.04075398000386,52.84036052756151],"type":"Point"}
}