{
  "type": "Feature",
  "properties": {
    "iso:country":"GB",
    "wof:name":"YO17 9PA",
    "wof:placetype":"postalcode"
},
  "geometry": {"coordinates":[-0.72707545047057,54.08628645743038],"type":"Point"}
}