{
  "type": "Feature",
  "properties": {
    "date:inception_lower": "1980-01-01",
    "date:inception_upper": "1980-01-01",
    "iso:country": "GB",
    "wof:name": "YO17 9PA",
    "wof:placetype": "postalcode"
  },
  "geometry": {"coordinates":[-0.727075,54.086286],"type":"Point"}
}
