{
  "type": "Feature",
  "properties": {
    "iso:country":"GB",
    "wof:name":"CF83 2QR",
    "wof:placetype":"postalcode"
},
  "geometry": {"coordinates":[-3.23074280588093,51.58370329117054],"type":"Point"}
}