{
  "type": "Feature",
  "properties": {
    "iso:country":"GB",
    "wof:name":"NP23 7TE",
    "wof:placetype":"postalcode"
},
  "geometry": {"coordinates":[-3.17980172501237,51.73541223351835],"type":"Point"}
}