{
  "type": "Feature",
  "properties": {
    "iso:country":"GB",
    "wof:name":"SO23 0HB",
    "wof:placetype":"postalcode"
},
  "geometry": {"coordinates":[-1.30148362812753,51.06664292229792],"type":"Point"}
}