{
  "type": "Feature",
  "properties": {
    "iso:country": "GB",
    "wof:name": "SW11 2PF",
    "wof:placetype": "postalcode"
  },
  "geometry": {"coordinates":[-0.169974,51.467131],"type":"Point"}
}
