{
  "type": "Feature",
  "properties": {
    "iso:country":"GB",
    "wof:name":"SW11 2PF",
    "wof:placetype":"postalcode"
},
  "geometry": {"coordinates":[-0.16997406190449,51.46713089691734],"type":"Point"}
}