{
  "type": "Feature",
  "properties": {
    "date:inception_lower": "1980-01-01",
    "date:inception_upper": "1980-01-01",
    "iso:country": "GB",
    "wof:name": "L35 5BD",
    "wof:placetype": "postalcode"
  },
  "geometry": {"coordinates":[-2.793749,53.423314],"type":"Point"}
}
