{
  "type": "Feature",
  "properties": {
    "date:inception_lower": "2001-06-01",
    "date:inception_upper": "2001-06-01",
    "iso:country": "GB",
    "wof:name": "PR25 1QJ",
    "wof:placetype": "postalcode"
  },
  "geometry": {"coordinates":[-2.711277,53.698155],"type":"Point"}
}
