{
  "type": "Feature",
  "properties": {
    "iso:country":"GB",
    "wof:name":"PR25 1QJ",
    "wof:placetype":"postalcode"
},
  "geometry": {"coordinates":[-2.7112766875611,53.6981547205854],"type":"Point"}
}