{
  "type": "Feature",
  "properties": {
    "iso:country": "GB",
    "wof:name": "EH16 5AD",
    "wof:placetype": "postalcode"
  },
  "geometry": {"coordinates":[-3.17314,55.937993],"type":"Point"}
}
