{
  "type": "Feature",
  "properties": {
    "iso:country": "GB",
    "wof:name": "EH16 5AD",
    "wof:placetype": "postalcode"
  },
  "geometry": {"coordinates":[-3.173979,55.938209],"type":"Point"}
}
