{
  "type": "Feature",
  "properties": {
    "iso:country":"GB",
    "wof:name":"BN11 2AH",
    "wof:placetype":"postalcode"
},
  "geometry": {"coordinates":[-0.35550559124223,50.81998833024583],"type":"Point"}
}