{
  "type": "Feature",
  "properties": {
    "iso:country":"GB",
    "wof:name":"SG9 0SP",
    "wof:placetype":"postalcode"
},
  "geometry": {"coordinates":[-0.09290247349422,51.9654239548324],"type":"Point"}
}