{
  "type": "Feature",
  "properties": {
    "iso:country": "GB",
    "wof:name": "SG9 0SP",
    "wof:placetype": "postalcode"
  },
  "geometry": {"coordinates":[-0.093084,51.965643],"type":"Point"}
}
