{
  "type": "Feature",
  "properties": {
    "date:inception_lower": "1980-01-01",
    "date:inception_upper": "1980-01-01",
    "iso:country": "GB",
    "wof:name": "PO41 0SW",
    "wof:placetype": "postalcode"
  },
  "geometry": {"coordinates":[-1.475324,50.698095],"type":"Point"}
}
