{
  "type": "Feature",
  "properties": {
    "iso:country":"GB",
    "wof:name":"ME7 1NB",
    "wof:placetype":"postalcode"
},
  "geometry": {"coordinates":[0.54682651107781,51.39294303410467],"type":"Point"}
}