{
  "type": "Feature",
  "properties": {
    "iso:country":"GB",
    "wof:name":"PL17 7QL",
    "wof:placetype":"postalcode"
},
  "geometry": {"coordinates":[-4.30929862792423,50.504922970912],"type":"Point"}
}