{
  "type": "Feature",
  "properties": {
    "iso:country":"GB",
    "wof:name":"WS8 6JQ",
    "wof:placetype":"postalcode"
},
  "geometry": {"coordinates":[-1.92476219945419,52.65188694527437],"type":"Point"}
}