{
  "type": "Feature",
  "properties": {
    "date:inception_lower": "1980-01-01",
    "date:inception_upper": "1980-01-01",
    "iso:country": "GB",
    "wof:name": "WS8 6JQ",
    "wof:placetype": "postalcode"
  },
  "geometry": {"coordinates":[-1.924762,52.651887],"type":"Point"}
}
