{
  "type": "Feature",
  "properties": {
    "iso:country": "GB",
    "wof:name": "WS8 6JQ",
    "wof:placetype": "postalcode"
  },
  "geometry": {"coordinates":[-1.924762,52.651887],"type":"Point"}
}
