{
  "type": "Feature",
  "properties": {
    "iso:country": "GB",
    "wof:name": "BB11 3JR",
    "wof:placetype": "postalcode"
  },
  "geometry": {"coordinates":[-2.235462,53.784295],"type":"Point"}
}
