{
  "type": "Feature",
  "properties": {
    "date:inception_lower": "2017-11-01",
    "date:inception_upper": "2017-11-01",
    "iso:country": "GB",
    "wof:name": "BB11 3JR",
    "wof:placetype": "postalcode"
  },
  "geometry": {"coordinates":[-2.235462,53.784295],"type":"Point"}
}
