{
  "type": "Feature",
  "properties": {
    "iso:country": "GB",
    "wof:name": "PE12 0QP",
    "wof:placetype": "postalcode"
  },
  "geometry": {"coordinates":[0.01457,52.665124],"type":"Point"}
}
