{
  "type": "Feature",
  "properties": {
    "iso:country":"GB",
    "wof:name":"GU25 4NE",
    "wof:placetype":"postalcode"
},
  "geometry": {"coordinates":[-0.60669623235081,51.3947307941005],"type":"Point"}
}