{
  "type": "Feature",
  "properties": {
    "iso:country":"GB",
    "wof:name":"B98 0EY",
    "wof:placetype":"postalcode"
},
  "geometry": {"coordinates":[-1.90232606416767,52.29065344833865],"type":"Point"}
}