{
  "type": "Feature",
  "properties": {
    "iso:country": "GB",
    "wof:name": "LU5 5AL",
    "wof:placetype": "postalcode"
  },
  "geometry": {"coordinates":[-0.53215,51.896541],"type":"Point"}
}
