{
  "type": "Feature",
  "properties": {
    "iso:country":"GB",
    "wof:name":"HD1 2UU",
    "wof:placetype":"postalcode"
},
  "geometry": {"coordinates":[-1.7831545112915,53.64411169688185],"type":"Point"}
}