{
  "type": "Feature",
  "properties": {
    "iso:country": "GB",
    "wof:name": "RM16 3HR",
    "wof:placetype": "postalcode"
  },
  "geometry": {"coordinates":[0.366447,51.512937],"type":"Point"}
}
