{
  "type": "Feature",
  "properties": {
    "iso:country":"GB",
    "wof:name":"MK42 8AJ",
    "wof:placetype":"postalcode"
},
  "geometry": {"coordinates":[-0.48206345993738,52.12441392551721],"type":"Point"}
}