{
  "type": "Feature",
  "properties": {
    "date:inception_lower":"1999-06-01",
    "date:inception_upper":"1999-06-30",
    "iso:country":"GB",
    "wof:name":"NP15 2HX",
    "wof:placetype":"postalcode"
},
  "geometry": {"coordinates":[-2.854199,51.751919],"type":"Point"}
}