{
  "type": "Feature",
  "properties": {
    "iso:country":"GB",
    "wof:name":"NP15 2HX",
    "wof:placetype":"postalcode"
},
  "geometry": {"coordinates":[-2.84716516869853,51.75484363275282],"type":"Point"}
}