{
  "type": "Feature",
  "properties": {
    "date:inception_lower":"1980-01-01",
    "date:inception_upper":"1980-01-31",
    "iso:country":"GB",
    "wof:name":"HP9 2RX",
    "wof:placetype":"postalcode"
},
  "geometry": {"coordinates":[-0.622466,51.597337],"type":"Point"}
}