{
  "type": "Feature",
  "properties": {
    "iso:country":"GB",
    "wof:name":"HP9 2RX",
    "wof:placetype":"postalcode"
},
  "geometry": {"coordinates":[-0.6224655443614,51.59733727014937],"type":"Point"}
}