{
  "type": "Feature",
  "properties": {
    "iso:country": "GB",
    "wof:name": "HP9 2RX",
    "wof:placetype": "postalcode"
  },
  "geometry": {"coordinates":[-0.622466,51.597337],"type":"Point"}
}
