{
  "type": "Feature",
  "properties": {
    "iso:country":"GB",
    "wof:name":"PE12 7PS",
    "wof:placetype":"postalcode"
},
  "geometry": {"coordinates":[0.01888122841631,52.8111277265311],"type":"Point"}
}