{
  "type": "Feature",
  "properties": {
    "date:inception_lower": "1980-01-01",
    "date:inception_upper": "1980-01-01",
    "iso:country": "GB",
    "wof:name": "SA44 4RN",
    "wof:placetype": "postalcode"
  },
  "geometry": {"coordinates":[-4.305848,52.031696],"type":"Point"}
}
