{
  "type": "Feature",
  "properties": {
    "iso:country":"GB",
    "wof:name":"SA44 4RN",
    "wof:placetype":"postalcode"
},
  "geometry": {"coordinates":[-4.30581391995953,52.03170253004074],"type":"Point"}
}