{
  "type": "Feature",
  "properties": {
    "iso:country": "GB",
    "wof:name": "SA44 4RN",
    "wof:placetype": "postalcode"
  },
  "geometry": {"coordinates":[-4.305848,52.031696],"type":"Point"}
}
