{
  "type": "Feature",
  "properties": {
    "iso:country":"GB",
    "wof:name":"UB4 9LN",
    "wof:placetype":"postalcode"
},
  "geometry": {"coordinates":[-0.39679540808791,51.53016016608861],"type":"Point"}
}