{
  "type": "Feature",
  "properties": {
    "iso:country":"GB",
    "wof:name":"DN33 1BW",
    "wof:placetype":"postalcode"
},
  "geometry": {"coordinates":[-0.09692124940184,53.55061308444282],"type":"Point"}
}