{
  "type": "Feature",
  "properties": {
    "iso:country":"GB",
    "wof:name":"RH14 9LS",
    "wof:placetype":"postalcode"
},
  "geometry": {"coordinates":[-0.46593940014488,51.02045411538657],"type":"Point"}
}