{
  "type": "Feature",
  "properties": {
    "iso:country": "GB",
    "wof:name": "CM16 7ES",
    "wof:placetype": "postalcode"
  },
  "geometry": {"coordinates":[0.099952,51.671867],"type":"Point"}
}
