{
  "type": "Feature",
  "properties": {
    "date:inception_lower": "2018-10-01",
    "date:inception_upper": "2018-10-01",
    "iso:country": "GB",
    "wof:name": "TS21 2BF",
    "wof:placetype": "postalcode"
  },
  "geometry": {"coordinates":[-1.444015,54.65004],"type":"Point"}
}
