{
  "type": "Feature",
  "properties": {
    "date:inception_lower": "1980-01-01",
    "date:inception_upper": "1980-01-01",
    "iso:country": "GB",
    "wof:name": "LE9 9PE",
    "wof:placetype": "postalcode"
  },
  "geometry": {"coordinates":[-1.34258,52.632046],"type":"Point"}
}
