{
  "type": "Feature",
  "properties": {
    "iso:country":"GB",
    "wof:name":"LE9 9PE",
    "wof:placetype":"postalcode"
},
  "geometry": {"coordinates":[-1.34258014761036,52.63204594405382],"type":"Point"}
}