{
  "type": "Feature",
  "properties": {
    "iso:country": "GB",
    "wof:name": "NE25 0BB",
    "wof:placetype": "postalcode"
  },
  "geometry": {"coordinates":[-1.5154,55.070067],"type":"Point"}
}
