{
  "type": "Feature",
  "properties": {
    "date:inception_lower": "2020-02-01",
    "date:inception_upper": "2020-02-01",
    "iso:country": "GB",
    "wof:name": "RH7 9BB",
    "wof:placetype": "postalcode"
  },
  "geometry": {"coordinates":[-0.019733,51.173973],"type":"Point"}
}
