{
  "type": "Feature",
  "properties": {
    "iso:country": "GB",
    "wof:name": "RH7 9BB",
    "wof:placetype": "postalcode"
  },
  "geometry": {"coordinates":[-0.019733,51.173973],"type":"Point"}
}
