{
  "type": "Feature",
  "properties": {
    "date:inception_lower":"1997-12-01",
    "date:inception_upper":"1997-12-31",
    "iso:country":"GB",
    "wof:name":"BS32 0EZ",
    "wof:placetype":"postalcode"
},
  "geometry": {"coordinates":[-2.548612,51.543226],"type":"Point"}
}