{
  "type": "Feature",
  "properties": {
    "iso:country":"GB",
    "wof:name":"BS32 0EZ",
    "wof:placetype":"postalcode"
},
  "geometry": {"coordinates":[-2.54861248355766,51.54322571503651],"type":"Point"}
}