{
  "type": "Feature",
  "properties": {
    "iso:country": "GB",
    "wof:name": "LN3 5FB",
    "wof:placetype": "postalcode"
  },
  "geometry": {"coordinates":[-0.324655,53.208807],"type":"Point"}
}
