{
  "type": "Feature",
  "properties": {
    "iso:country":"GB",
    "wof:name":"NE6 3AR",
    "wof:placetype":"postalcode"
},
  "geometry": {"coordinates":[-1.55079549375722,54.97447240051152],"type":"Point"}
}