{
  "type": "Feature",
  "properties": {
    "iso:country":"GB",
    "wof:name":"BR7 5RZ",
    "wof:placetype":"postalcode"
},
  "geometry": {"coordinates":[0.06442427434194,51.40596219706504],"type":"Point"}
}