{
  "type": "Feature",
  "properties": {
    "iso:country": "GB",
    "wof:name": "NR4 7BD",
    "wof:placetype": "postalcode"
  },
  "geometry": {"coordinates":[1.235189,52.609211],"type":"Point"}
}
