{
  "type": "Feature",
  "properties": {
    "iso:country":"GB",
    "wof:name":"NR4 7BD",
    "wof:placetype":"postalcode"
},
  "geometry": {"coordinates":[1.23518853754406,52.60921076285167],"type":"Point"}
}