{
  "type": "Feature",
  "properties": {
    "iso:country":"GB",
    "wof:name":"TN18 5JT",
    "wof:placetype":"postalcode"
},
  "geometry": {"coordinates":[0.56397310614568,51.02615976355827],"type":"Point"}
}