{
  "type": "Feature",
  "properties": {
    "iso:country":"GB",
    "wof:name":"SL3 6SA",
    "wof:placetype":"postalcode"
},
  "geometry": {"coordinates":[-0.55793812708067,51.52175776082429],"type":"Point"}
}