{
  "type": "Feature",
  "properties": {
    "iso:country":"GB",
    "wof:name":"G33 2HQ",
    "wof:placetype":"postalcode"
},
  "geometry": {"coordinates":[-4.19163833836895,55.86558564402194],"type":"Point"}
}