{
  "type": "Feature",
  "properties": {
    "date:inception_lower": "1980-01-01",
    "date:inception_upper": "1980-01-01",
    "iso:country": "GB",
    "wof:name": "N8 9HR",
    "wof:placetype": "postalcode"
  },
  "geometry": {"coordinates":[-0.117976,51.578516],"type":"Point"}
}
