{
  "type": "Feature",
  "properties": {
    "iso:country":"GB",
    "wof:name":"HP5 3LP",
    "wof:placetype":"postalcode"
},
  "geometry": {"coordinates":[-0.59779858585858,51.71000077290382],"type":"Point"}
}