{
  "type": "Feature",
  "properties": {
    "iso:country":"GB",
    "wof:name":"NN8 4HZ",
    "wof:placetype":"postalcode"
},
  "geometry": {"coordinates":[-0.69611257982701,52.31778934275403],"type":"Point"}
}