{
  "type": "Feature",
  "properties": {
    "date:inception_lower":"1980-01-01",
    "date:inception_upper":"1980-01-31",
    "iso:country":"GB",
    "wof:name":"NW5 3BY",
    "wof:placetype":"postalcode"
},
  "geometry": {"coordinates":[-0.142229,51.548284],"type":"Point"}
}