{
  "type": "Feature",
  "properties": {
    "iso:country":"GB",
    "wof:name":"IP5 3UD",
    "wof:placetype":"postalcode"
},
  "geometry": {"coordinates":[1.26654622180276,52.05403840369554],"type":"Point"}
}