{
  "type": "Feature",
  "properties": {
    "iso:country":"GB",
    "wof:name":"EN6 4PL",
    "wof:placetype":"postalcode"
},
  "geometry": {"coordinates":[-0.13046997883526,51.71707214341175],"type":"Point"}
}