{
  "type": "Feature",
  "properties": {
    "iso:country": "GB",
    "wof:name": "EN6 4PL",
    "wof:placetype": "postalcode"
  },
  "geometry": {"coordinates":[-0.13047,51.717072],"type":"Point"}
}
