{
  "type": "Feature",
  "properties": {
    "iso:country":"GB",
    "wof:name":"SM5 2JT",
    "wof:placetype":"postalcode"
},
  "geometry": {"coordinates":[-0.15934590284321,51.37089641114156],"type":"Point"}
}