{
  "type": "Feature",
  "properties": {
    "date:inception_lower":"2002-11-01",
    "date:inception_upper":"2002-11-30",
    "iso:country":"GB",
    "wof:name":"SM5 2JT",
    "wof:placetype":"postalcode"
},
  "geometry": {"coordinates":[-0.159346,51.370896],"type":"Point"}
}