{
  "type": "Feature",
  "properties": {
    "date:inception_lower": "1980-01-01",
    "date:inception_upper": "1980-01-01",
    "iso:country": "GB",
    "wof:name": "PL2 2BY",
    "wof:placetype": "postalcode"
  },
  "geometry": {"coordinates":[-4.178319,50.391413],"type":"Point"}
}
