{
  "type": "Feature",
  "properties": {
    "iso:country": "GB",
    "wof:name": "CH3 5EQ",
    "wof:placetype": "postalcode"
  },
  "geometry": {"coordinates":[-2.86412,53.191683],"type":"Point"}
}
