{
  "type": "Feature",
  "properties": {
    "date:inception_lower":"1985-10-01",
    "date:inception_upper":"1985-10-31",
    "iso:country":"GB",
    "wof:name":"HP21 7FF",
    "wof:placetype":"postalcode"
},
  "geometry": {"coordinates":[-0.792416,51.80758],"type":"Point"}
}