{
  "type": "Feature",
  "properties": {
    "date:inception_lower":"2003-04-01",
    "date:inception_upper":"2003-04-30",
    "iso:country":"GB",
    "wof:name":"SG18 0AS",
    "wof:placetype":"postalcode"
},
  "geometry": {"coordinates":[-0.267095,52.08891],"type":"Point"}
}