{
  "type": "Feature",
  "properties": {
    "iso:country":"GB",
    "wof:name":"SG18 0AS",
    "wof:placetype":"postalcode"
},
  "geometry": {"coordinates":[-0.26709488276024,52.08891029312444],"type":"Point"}
}