{
  "type": "Feature",
  "properties": {
    "iso:country":"GB",
    "wof:name":"PA31 8QF",
    "wof:placetype":"postalcode"
},
  "geometry": {"coordinates":[-5.51419806667239,56.1131883746612],"type":"Point"}
}