{
  "type": "Feature",
  "properties": {
    "date:inception_lower":"1980-01-01",
    "date:inception_upper":"1980-01-31",
    "iso:country":"GB",
    "wof:name":"N14 6EH",
    "wof:placetype":"postalcode"
},
  "geometry": {"coordinates":[-0.124115,51.626475],"type":"Point"}
}