{
  "type": "Feature",
  "properties": {
    "date:inception_lower": "2016-10-01",
    "date:inception_upper": "2016-10-01",
    "iso:country": "GB",
    "wof:name": "LL17 0EJ",
    "wof:placetype": "postalcode"
  },
  "geometry": {"coordinates":[-3.435899,53.252135],"type":"Point"}
}
