{
  "type": "Feature",
  "properties": {
    "iso:country": "GB",
    "wof:name": "LL17 0EJ",
    "wof:placetype": "postalcode"
  },
  "geometry": {"coordinates":[-3.435899,53.252135],"type":"Point"}
}
