{
  "type": "Feature",
  "properties": {
    "iso:country":"GB",
    "wof:name":"GL54 3EP",
    "wof:placetype":"postalcode"
},
  "geometry": {"coordinates":[-1.83547348453308,51.82865077446701],"type":"Point"}
}