{
  "type": "Feature",
  "properties": {
    "iso:country":"GB",
    "wof:name":"LU3 2DP",
    "wof:placetype":"postalcode"
},
  "geometry": {"coordinates":[-0.43301603225819,51.9157096087671],"type":"Point"}
}