{
  "type": "Feature",
  "properties": {
    "iso:country":"GB",
    "wof:name":"PE12 7DQ",
    "wof:placetype":"postalcode"
},
  "geometry": {"coordinates":[0.02157217816491,52.80132671944268],"type":"Point"}
}