{
  "type": "Feature",
  "properties": {
    "iso:country": "GB",
    "wof:name": "PE12 7DQ",
    "wof:placetype": "postalcode"
  },
  "geometry": {"coordinates":[0.021615,52.801365],"type":"Point"}
}
