{
  "type": "Feature",
  "properties": {
    "iso:country":"GB",
    "wof:name":"KY7 4DR",
    "wof:placetype":"postalcode"
},
  "geometry": {"coordinates":[-3.16221409232462,56.19396577021129],"type":"Point"}
}