{
  "type": "Feature",
  "properties": {
    "date:inception_lower": "2021-09-01",
    "date:inception_upper": "2021-09-01",
    "iso:country": "GB",
    "wof:name": "PA7 9AG",
    "wof:placetype": "postalcode"
  },
  "geometry": {"coordinates":[-4.454545,55.905392],"type":"Point"}
}
