{
  "type": "Feature",
  "properties": {
    "iso:country": "GB",
    "wof:name": "HX3 8RY",
    "wof:placetype": "postalcode"
  },
  "geometry": {"coordinates":[-1.792831,53.725256],"type":"Point"}
}
