{
  "type": "Feature",
  "properties": {
    "iso:country":"GB",
    "wof:name":"SE1 0LE",
    "wof:placetype":"postalcode"
},
  "geometry": {"coordinates":[-0.09728637094215,51.50367975285442],"type":"Point"}
}