{
  "type": "Feature",
  "properties": {
    "iso:country": "GB",
    "wof:name": "SE1 0LE",
    "wof:placetype": "postalcode"
  },
  "geometry": {"coordinates":[-0.097286,51.50368],"type":"Point"}
}
