{
  "type": "Feature",
  "properties": {
    "iso:country": "GB",
    "wof:name": "PO20 1WL",
    "wof:placetype": "postalcode"
  },
  "geometry": {"coordinates":[-0.781342,50.83077],"type":"Point"}
}
