{
  "type": "Feature",
  "properties": {
    "date:inception_lower": "1980-01-01",
    "date:inception_upper": "1980-01-01",
    "iso:country": "GB",
    "wof:name": "PR4 6PH",
    "wof:placetype": "postalcode"
  },
  "geometry": {"coordinates":[-2.842305,53.699597],"type":"Point"}
}
