{
  "type": "Feature",
  "properties": {
    "iso:country":"GB",
    "wof:name":"CV9 2GB",
    "wof:placetype":"postalcode"
},
  "geometry": {"coordinates":[-1.64165356706483,52.56047369991681],"type":"Point"}
}