{
  "type": "Feature",
  "properties": {
    "iso:country":"GB",
    "wof:name":"G71 8LU",
    "wof:placetype":"postalcode"
},
  "geometry": {"coordinates":[-4.07589326457199,55.79902155414533],"type":"Point"}
}