{
  "type": "Feature",
  "properties": {
    "date:inception_lower":"1990-09-01",
    "date:inception_upper":"1990-09-30",
    "iso:country":"GB",
    "wof:name":"G71 8LU",
    "wof:placetype":"postalcode"
},
  "geometry": {"coordinates":[-4.075893,55.799022],"type":"Point"}
}