{
  "type": "Feature",
  "properties": {
    "iso:country":"GB",
    "wof:name":"NW8 9AB",
    "wof:placetype":"postalcode"
},
  "geometry": {"coordinates":[-0.17831067330564,51.53251916552308],"type":"Point"}
}