{
  "type": "Feature",
  "properties": {
    "date:inception_lower":"1980-01-01",
    "date:inception_upper":"1980-01-31",
    "iso:country":"GB",
    "wof:name":"SN10 4NY",
    "wof:placetype":"postalcode"
},
  "geometry": {"coordinates":[-1.971662,51.29289],"type":"Point"}
}