{
  "type": "Feature",
  "properties": {
    "iso:country":"GB",
    "wof:name":"SN10 4NY",
    "wof:placetype":"postalcode"
},
  "geometry": {"coordinates":[-1.9715835823856,51.29272356973637],"type":"Point"}
}