{
  "type": "Feature",
  "properties": {
    "iso:country": "GB",
    "wof:name": "DY5 2YA",
    "wof:placetype": "postalcode"
  },
  "geometry": {"coordinates":[-2.117155,52.4694],"type":"Point"}
}
