{
  "type": "Feature",
  "properties": {
    "iso:country":"GB",
    "wof:name":"BR3 3RX",
    "wof:placetype":"postalcode"
},
  "geometry": {"coordinates":[-0.04192929168173,51.38990999561783],"type":"Point"}
}