{
  "type": "Feature",
  "properties": {
    "iso:country":"GB",
    "wof:name":"PE37 7HA",
    "wof:placetype":"postalcode"
},
  "geometry": {"coordinates":[0.68923254793345,52.64381599359984],"type":"Point"}
}