{
  "type": "Feature",
  "properties": {
    "date:inception_lower": "1980-01-01",
    "date:inception_upper": "1980-01-01",
    "iso:country": "GB",
    "wof:name": "PE37 7HA",
    "wof:placetype": "postalcode"
  },
  "geometry": {"coordinates":[0.689233,52.643816],"type":"Point"}
}
