{
  "type": "Feature",
  "properties": {
    "iso:country":"GB",
    "wof:name":"BL6 4BR",
    "wof:placetype":"postalcode"
},
  "geometry": {"coordinates":[-2.52453144298819,53.57678746626169],"type":"Point"}
}