{
  "type": "Feature",
  "properties": {
    "iso:country": "GB",
    "wof:name": "BL6 4BR",
    "wof:placetype": "postalcode"
  },
  "geometry": {"coordinates":[-2.524567,53.578468],"type":"Point"}
}
