{
  "type": "Feature",
  "properties": {
    "iso:country":"GB",
    "wof:name":"WV10 7DZ",
    "wof:placetype":"postalcode"
},
  "geometry": {"coordinates":[-2.12196085839194,52.67130131307034],"type":"Point"}
}