{
  "type": "Feature",
  "properties": {
    "date:inception_lower": "1994-05-01",
    "date:inception_upper": "1994-05-01",
    "iso:country": "GB",
    "wof:name": "WV10 7DZ",
    "wof:placetype": "postalcode"
  },
  "geometry": {"coordinates":[-2.121961,52.671301],"type":"Point"}
}
