{
  "type": "Feature",
  "properties": {
    "date:inception_lower": "1995-01-01",
    "date:inception_upper": "1995-01-01",
    "iso:country": "GB",
    "wof:name": "SL2 1BF",
    "wof:placetype": "postalcode"
  },
  "geometry": {"coordinates":[-0.611905,51.532156],"type":"Point"}
}
