{
  "type": "Feature",
  "properties": {
    "iso:country":"GB",
    "wof:name":"SL2 1BF",
    "wof:placetype":"postalcode"
},
  "geometry": {"coordinates":[-0.61190512482394,51.53215604091331],"type":"Point"}
}