{
  "type": "Feature",
  "properties": {
    "iso:country":"GB",
    "wof:name":"GL20 6DQ",
    "wof:placetype":"postalcode"
},
  "geometry": {"coordinates":[-2.14362543489337,52.02916352756053],"type":"Point"}
}