{
  "type": "Feature",
  "properties": {
    "iso:country": "GB",
    "wof:name": "L32 3AB",
    "wof:placetype": "postalcode"
  },
  "geometry": {"coordinates":[-2.883951,53.470571],"type":"Point"}
}
