{
  "type": "Feature",
  "properties": {
    "iso:country":"GB",
    "wof:name":"PE29 1JE",
    "wof:placetype":"postalcode"
},
  "geometry": {"coordinates":[-0.18359692631748,52.33410095485834],"type":"Point"}
}