{
  "type": "Feature",
  "properties": {
    "iso:country": "GB",
    "wof:name": "PE29 1JE",
    "wof:placetype": "postalcode"
  },
  "geometry": {"coordinates":[-0.183597,52.334101],"type":"Point"}
}
