{
  "type": "Feature",
  "properties": {
    "iso:country":"GB",
    "wof:name":"RG7 1XX",
    "wof:placetype":"postalcode"
},
  "geometry": {"coordinates":[-0.94554847319122,51.35763424212494],"type":"Point"}
}