{
  "type": "Feature",
  "properties": {
    "date:inception_lower": "2013-09-01",
    "date:inception_upper": "2013-09-01",
    "iso:country": "GB",
    "wof:name": "WV98 1GH",
    "wof:placetype": "postalcode"
  },
  "geometry": {"coordinates":[-2.238936,52.364612],"type":"Point"}
}
