{
  "type": "Feature",
  "properties": {
    "iso:country":"GB",
    "wof:name":"EX36 3HF",
    "wof:placetype":"postalcode"
},
  "geometry": {"coordinates":[-3.80780323535164,51.05450908710433],"type":"Point"}
}