{
  "type": "Feature",
  "properties": {
    "iso:country": "GB",
    "wof:name": "EX36 3HF",
    "wof:placetype": "postalcode"
  },
  "geometry": {"coordinates":[-3.807803,51.054509],"type":"Point"}
}
