{
  "type": "Feature",
  "properties": {
    "iso:country": "GB",
    "wof:name": "TR7 3FS",
    "wof:placetype": "postalcode"
  },
  "geometry": {"coordinates":[-5.05606,50.42144],"type":"Point"}
}
