{
  "type": "Feature",
  "properties": {
    "date:inception_lower": "2019-08-01",
    "date:inception_upper": "2019-08-01",
    "iso:country": "GB",
    "wof:name": "TR7 3FS",
    "wof:placetype": "postalcode"
  },
  "geometry": {"coordinates":[-5.05619,50.421491],"type":"Point"}
}
