{
  "type": "Feature",
  "properties": {
    "iso:country": "GB",
    "wof:name": "NG17 5DH",
    "wof:placetype": "postalcode"
  },
  "geometry": {"coordinates":[-1.256205,53.121053],"type":"Point"}
}
