{
  "type": "Feature",
  "properties": {
    "iso:country":"GB",
    "wof:name":"WF3 4JX",
    "wof:placetype":"postalcode"
},
  "geometry": {"coordinates":[-1.47686034548834,53.7012838989814],"type":"Point"}
}