{
  "type": "Feature",
  "properties": {
    "date:inception_lower": "1980-01-01",
    "date:inception_upper": "1980-01-01",
    "iso:country": "GB",
    "wof:name": "WF3 4JX",
    "wof:placetype": "postalcode"
  },
  "geometry": {"coordinates":[-1.47686,53.701284],"type":"Point"}
}
