{
  "type": "Feature",
  "properties": {
    "date:inception_lower": "2022-02-01",
    "date:inception_upper": "2022-02-01",
    "iso:country": "GB",
    "wof:name": "SG19 2GB",
    "wof:placetype": "postalcode"
  },
  "geometry": {"coordinates":[-0.211654,52.12817],"type":"Point"}
}
