{
  "type": "Feature",
  "properties": {
    "date:inception_lower":"1994-10-01",
    "date:inception_upper":"1994-10-31",
    "iso:country":"GB",
    "wof:name":"PH36 4JJ",
    "wof:placetype":"postalcode"
},
  "geometry": {"coordinates":[-5.793302,56.740842],"type":"Point"}
}