{
  "type": "Feature",
  "properties": {
    "iso:country":"GB",
    "wof:name":"CH7 3AG",
    "wof:placetype":"postalcode"
},
  "geometry": {"coordinates":[-3.05601971866144,53.16503797010705],"type":"Point"}
}