{
  "type": "Feature",
  "properties": {
    "date:inception_lower": "1995-07-01",
    "date:inception_upper": "1995-07-01",
    "iso:country": "GB",
    "wof:name": "CH7 3AG",
    "wof:placetype": "postalcode"
  },
  "geometry": {"coordinates":[-3.05602,53.165038],"type":"Point"}
}
