{
  "type": "Feature",
  "properties": {
    "iso:country":"GB",
    "wof:name":"G46 6QH",
    "wof:placetype":"postalcode"
},
  "geometry": {"coordinates":[-4.29437823543551,55.79408554279733],"type":"Point"}
}