{
  "type": "Feature",
  "properties": {
    "iso:country":"GB",
    "wof:name":"SO16 9HF",
    "wof:placetype":"postalcode"
},
  "geometry": {"coordinates":[-1.46164794168099,50.92649027211529],"type":"Point"}
}