{
  "type": "Feature",
  "properties": {
    "date:inception_lower": "2001-06-01",
    "date:inception_upper": "2001-06-01",
    "iso:country": "GB",
    "wof:name": "OX29 8AR",
    "wof:placetype": "postalcode"
  },
  "geometry": {"coordinates":[-1.401389,51.805063],"type":"Point"}
}
