{
  "type": "Feature",
  "properties": {
    "iso:country":"GB",
    "wof:name":"OX29 8AR",
    "wof:placetype":"postalcode"
},
  "geometry": {"coordinates":[-1.40138933917274,51.80506253665875],"type":"Point"}
}