{
  "type": "Feature",
  "properties": {
    "iso:country":"GB",
    "wof:name":"NW8 8PT",
    "wof:placetype":"postalcode"
},
  "geometry": {"coordinates":[-0.17086620442892,51.52328497788328],"type":"Point"}
}