{
  "type": "Feature",
  "properties": {
    "date:inception_lower": "1980-01-01",
    "date:inception_upper": "1980-01-01",
    "iso:country": "GB",
    "wof:name": "NW8 8PT",
    "wof:placetype": "postalcode"
  },
  "geometry": {"coordinates":[-0.170866,51.523285],"type":"Point"}
}
