{
  "type": "Feature",
  "properties": {
    "date:inception_lower":"1980-01-01",
    "date:inception_upper":"1980-01-31",
    "iso:country":"GB",
    "wof:name":"B91 2SU",
    "wof:placetype":"postalcode"
},
  "geometry": {"coordinates":[-1.742877,52.408473],"type":"Point"}
}