{
  "type": "Feature",
  "properties": {
    "iso:country":"GB",
    "wof:name":"B91 2SU",
    "wof:placetype":"postalcode"
},
  "geometry": {"coordinates":[-1.74287729700023,52.40847336236949],"type":"Point"}
}