{
  "type": "Feature",
  "properties": {
    "iso:country":"GB",
    "wof:name":"B28 8PU",
    "wof:placetype":"postalcode"
},
  "geometry": {"coordinates":[-1.83186696592657,52.43326595467948],"type":"Point"}
}