{
  "type": "Feature",
  "properties": {
    "iso:country":"GB",
    "wof:name":"FY5 4EE",
    "wof:placetype":"postalcode"
},
  "geometry": {"coordinates":[-2.99810203045331,53.87520120551572],"type":"Point"}
}