{
  "type": "Feature",
  "properties": {
    "iso:country":"GB",
    "wof:name":"L35 3PR",
    "wof:placetype":"postalcode"
},
  "geometry": {"coordinates":[-2.79857938317275,53.40964619062479],"type":"Point"}
}