{
  "type": "Feature",
  "properties": {
    "iso:country": "GB",
    "wof:name": "SA13 3DH",
    "wof:placetype": "postalcode"
  },
  "geometry": {"coordinates":[-3.626116,51.681661],"type":"Point"}
}
