{
  "type": "Feature",
  "properties": {
    "iso:country":"GB",
    "wof:name":"SA13 3DH",
    "wof:placetype":"postalcode"
},
  "geometry": {"coordinates":[-3.62611624508812,51.68166052694869],"type":"Point"}
}