{
  "type": "Feature",
  "properties": {
    "iso:country":"GB",
    "wof:name":"WR7 4EE",
    "wof:placetype":"postalcode"
},
  "geometry": {"coordinates":[-1.9825968668223,52.2133307816779],"type":"Point"}
}