{
  "type": "Feature",
  "properties": {
    "iso:country": "GB",
    "wof:name": "BA11 3SF",
    "wof:placetype": "postalcode"
  },
  "geometry": {"coordinates":[-2.330305,51.235414],"type":"Point"}
}
