{
  "type": "Feature",
  "properties": {
    "date:inception_lower":"1993-08-01",
    "date:inception_upper":"1993-08-31",
    "iso:country":"GB",
    "wof:name":"BA11 3SF",
    "wof:placetype":"postalcode"
},
  "geometry": {"coordinates":[-2.330305,51.235414],"type":"Point"}
}