{
  "type": "Feature",
  "properties": {
    "iso:country":"GB",
    "wof:name":"BA11 3SF",
    "wof:placetype":"postalcode"
},
  "geometry": {"coordinates":[-2.3303048416803,51.23541382970183],"type":"Point"}
}