{
  "type": "Feature",
  "properties": {
    "iso:country":"GB",
    "wof:name":"SW16 3LN",
    "wof:placetype":"postalcode"
},
  "geometry": {"coordinates":[-0.12282088280151,51.41382350764832],"type":"Point"}
}