{
  "type": "Feature",
  "properties": {
    "iso:country":"GB",
    "wof:name":"M29 7JE",
    "wof:placetype":"postalcode"
},
  "geometry": {"coordinates":[-2.44957439137121,53.49252060717374],"type":"Point"}
}