{
  "type": "Feature",
  "properties": {
    "iso:country":"GB",
    "wof:name":"NG11 6HZ",
    "wof:placetype":"postalcode"
},
  "geometry": {"coordinates":[-1.15567702729083,52.89003749426519],"type":"Point"}
}