{
  "type": "Feature",
  "properties": {
    "iso:country": "GB",
    "wof:name": "TF2 9FZ",
    "wof:placetype": "postalcode"
  },
  "geometry": {"coordinates":[-2.429723,52.69871],"type":"Point"}
}
