{
  "type": "Feature",
  "properties": {
    "date:inception_lower":"2013-04-01",
    "date:inception_upper":"2013-04-30",
    "iso:country":"GB",
    "wof:name":"TF2 9FZ",
    "wof:placetype":"postalcode"
},
  "geometry": {"coordinates":[-2.429723,52.69871],"type":"Point"}
}