{
  "type": "Feature",
  "properties": {
    "iso:country":"GB",
    "wof:name":"TF2 9FZ",
    "wof:placetype":"postalcode"
},
  "geometry": {"coordinates":[-2.42942869081476,52.6987142927377],"type":"Point"}
}