{
  "type": "Feature",
  "properties": {
    "date:inception_lower":"1980-01-01",
    "date:inception_upper":"1980-01-31",
    "iso:country":"GB",
    "wof:name":"DN17 3LY",
    "wof:placetype":"postalcode"
},
  "geometry": {"coordinates":[-0.739049,53.574658],"type":"Point"}
}