{
  "type": "Feature",
  "properties": {
    "iso:country":"GB",
    "wof:name":"TN35 5BU",
    "wof:placetype":"postalcode"
},
  "geometry": {"coordinates":[0.60647699184944,50.87407095667329],"type":"Point"}
}