{
  "type": "Feature",
  "properties": {
    "iso:country": "GB",
    "wof:name": "TN35 5BU",
    "wof:placetype": "postalcode"
  },
  "geometry": {"coordinates":[0.606477,50.874071],"type":"Point"}
}
