{
  "type": "Feature",
  "properties": {
    "iso:country":"GB",
    "wof:name":"LU5 6EG",
    "wof:placetype":"postalcode"
},
  "geometry": {"coordinates":[-0.53071362305116,51.94233472281039],"type":"Point"}
}