{
  "type": "Feature",
  "properties": {
    "iso:country": "GB",
    "wof:name": "LU5 6EG",
    "wof:placetype": "postalcode"
  },
  "geometry": {"coordinates":[-0.530714,51.942335],"type":"Point"}
}
