{
  "type": "Feature",
  "properties": {
    "date:inception_lower": "1980-01-01",
    "date:inception_upper": "1980-01-01",
    "iso:country": "GB",
    "wof:name": "LU5 6EG",
    "wof:placetype": "postalcode"
  },
  "geometry": {"coordinates":[-0.530714,51.942335],"type":"Point"}
}
