{
  "type": "Feature",
  "properties": {
    "iso:country": "GB",
    "wof:name": "CF23 9DZ",
    "wof:placetype": "postalcode"
  },
  "geometry": {"coordinates":[-3.151742,51.504622],"type":"Point"}
}
