{
  "type": "Feature",
  "properties": {
    "date:inception_lower":"1999-06-01",
    "date:inception_upper":"1999-06-30",
    "iso:country":"GB",
    "wof:name":"CF23 9DZ",
    "wof:placetype":"postalcode"
},
  "geometry": {"coordinates":[-3.151742,51.504622],"type":"Point"}
}