{
  "type": "Feature",
  "properties": {
    "iso:country":"GB",
    "wof:name":"CF23 9DZ",
    "wof:placetype":"postalcode"
},
  "geometry": {"coordinates":[-3.15174216697116,51.50462212572454],"type":"Point"}
}