{
  "type": "Feature",
  "properties": {
    "iso:country":"GB",
    "wof:name":"LS29 0EP",
    "wof:placetype":"postalcode"
},
  "geometry": {"coordinates":[-1.85961996729837,53.95804016863365],"type":"Point"}
}