{
  "type": "Feature",
  "properties": {
    "iso:country": "GB",
    "wof:name": "LS29 0EP",
    "wof:placetype": "postalcode"
  },
  "geometry": {"coordinates":[-1.85962,53.95804],"type":"Point"}
}
