{
  "type": "Feature",
  "properties": {
    "iso:country":"GB",
    "wof:name":"EX39 3JG",
    "wof:placetype":"postalcode"
},
  "geometry": {"coordinates":[-4.21015195109494,51.0199706429751],"type":"Point"}
}