{
  "type": "Feature",
  "properties": {
    "iso:country":"GB",
    "wof:name":"SE14 6PP",
    "wof:placetype":"postalcode"
},
  "geometry": {"coordinates":[-0.03530817793749,51.4753021335497],"type":"Point"}
}