{
  "type": "Feature",
  "properties": {
    "date:inception_lower": "1994-06-01",
    "date:inception_upper": "1994-06-01",
    "iso:country": "GB",
    "wof:name": "G81 1XL",
    "wof:placetype": "postalcode"
  },
  "geometry": {"coordinates":[-4.40415,55.899763],"type":"Point"}
}
