{
  "type": "Feature",
  "properties": {
    "iso:country": "GB",
    "wof:name": "G81 1XL",
    "wof:placetype": "postalcode"
  },
  "geometry": {"coordinates":[-4.40415,55.899763],"type":"Point"}
}
