{
  "type": "Feature",
  "properties": {
    "iso:country": "GB",
    "wof:name": "LL12 9NE",
    "wof:placetype": "postalcode"
  },
  "geometry": {"coordinates":[-3.034033,53.120302],"type":"Point"}
}
