{
  "type": "Feature",
  "properties": {
    "date:inception_lower": "1980-01-01",
    "date:inception_upper": "1980-01-01",
    "iso:country": "GB",
    "wof:name": "LL12 9NE",
    "wof:placetype": "postalcode"
  },
  "geometry": {"coordinates":[-3.034033,53.120302],"type":"Point"}
}
