{
  "type": "Feature",
  "properties": {
    "iso:country": "GB",
    "wof:name": "L34 6JL",
    "wof:placetype": "postalcode"
  },
  "geometry": {"coordinates":[-2.80057,53.431512],"type":"Point"}
}
