{
  "type": "Feature",
  "properties": {
    "iso:country":"GB",
    "wof:name":"L34 6JL",
    "wof:placetype":"postalcode"
},
  "geometry": {"coordinates":[-2.80056971604235,53.43151154896093],"type":"Point"}
}