{
  "type": "Feature",
  "properties": {
    "date:inception_lower": "2016-05-01",
    "date:inception_upper": "2016-05-01",
    "iso:country": "GB",
    "wof:name": "TW3 1AL",
    "wof:placetype": "postalcode"
  },
  "geometry": {"coordinates":[-0.355934,51.470596],"type":"Point"}
}
