{
  "type": "Feature",
  "properties": {
    "iso:country":"GB",
    "wof:name":"TA21 0NS",
    "wof:placetype":"postalcode"
},
  "geometry": {"coordinates":[-3.36220865496858,50.96308139626281],"type":"Point"}
}