{
  "type": "Feature",
  "properties": {
    "date:inception_lower": "1980-01-01",
    "date:inception_upper": "1980-01-01",
    "iso:country": "GB",
    "wof:name": "TA21 0NS",
    "wof:placetype": "postalcode"
  },
  "geometry": {"coordinates":[-3.362209,50.963081],"type":"Point"}
}
