{
  "type": "Feature",
  "properties": {
    "date:inception_lower":"1992-08-01",
    "date:inception_upper":"1992-08-31",
    "iso:country":"GB",
    "wof:name":"BB2 4HJ",
    "wof:placetype":"postalcode"
},
  "geometry": {"coordinates":[-2.496516,53.732539],"type":"Point"}
}