{
  "type": "Feature",
  "properties": {
    "iso:country":"GB",
    "wof:name":"BB2 4HJ",
    "wof:placetype":"postalcode"
},
  "geometry": {"coordinates":[-2.49651639903653,53.73253899704432],"type":"Point"}
}