{
  "type": "Feature",
  "properties": {
    "iso:country": "GB",
    "wof:name": "CW11 3NG",
    "wof:placetype": "postalcode"
  },
  "geometry": {"coordinates":[-2.396682,53.141113],"type":"Point"}
}
