{
  "type": "Feature",
  "properties": {
    "iso:country":"GB",
    "wof:name":"WN8 6AJ",
    "wof:placetype":"postalcode"
},
  "geometry": {"coordinates":[-2.75648296752042,53.54741998895844],"type":"Point"}
}