{
  "type": "Feature",
  "properties": {
    "iso:country":"GB",
    "wof:name":"WV16 6TH",
    "wof:placetype":"postalcode"
},
  "geometry": {"coordinates":[-2.57788455528907,52.50059329880463],"type":"Point"}
}