{
  "type": "Feature",
  "properties": {
    "date:inception_lower": "1990-02-01",
    "date:inception_upper": "1990-02-01",
    "iso:country": "GB",
    "wof:name": "WV16 6TH",
    "wof:placetype": "postalcode"
  },
  "geometry": {"coordinates":[-2.577885,52.500593],"type":"Point"}
}
