{
  "type": "Feature",
  "properties": {
    "iso:country":"GB",
    "wof:name":"TR20 8PY",
    "wof:placetype":"postalcode"
},
  "geometry": {"coordinates":[-5.63038769199941,50.13159739716939],"type":"Point"}
}