{
  "type": "Feature",
  "properties": {
    "iso:country": "GB",
    "wof:name": "LD2 3UW",
    "wof:placetype": "postalcode"
  },
  "geometry": {"coordinates":[-3.343822,52.116585],"type":"Point"}
}
