{
  "type": "Feature",
  "properties": {
    "iso:country":"GB",
    "wof:name":"CT9 2RG",
    "wof:placetype":"postalcode"
},
  "geometry": {"coordinates":[1.391514217065,51.38080670487176],"type":"Point"}
}