{
  "type": "Feature",
  "properties": {
    "iso:country": "GB",
    "wof:name": "DN10 4BF",
    "wof:placetype": "postalcode"
  },
  "geometry": {"coordinates":[-0.849676,53.447243],"type":"Point"}
}
