{
  "type": "Feature",
  "properties": {
    "date:inception_lower":"1992-08-01",
    "date:inception_upper":"1992-08-31",
    "iso:country":"GB",
    "wof:name":"DN10 4BF",
    "wof:placetype":"postalcode"
},
  "geometry": {"coordinates":[-0.849444,53.447327],"type":"Point"}
}