{
  "type": "Feature",
  "properties": {
    "date:inception_lower": "1981-06-01",
    "date:inception_upper": "1981-06-01",
    "iso:country": "GB",
    "wof:name": "CH2 4AY",
    "wof:placetype": "postalcode"
  },
  "geometry": {"coordinates":[-2.898822,53.224282],"type":"Point"}
}
