{
  "type": "Feature",
  "properties": {
    "iso:country": "GB",
    "wof:name": "PO35 5PJ",
    "wof:placetype": "postalcode"
  },
  "geometry": {"coordinates":[-1.096907,50.67648],"type":"Point"}
}
