{
  "type": "Feature",
  "properties": {
    "iso:country":"GB",
    "wof:name":"PO35 5PJ",
    "wof:placetype":"postalcode"
},
  "geometry": {"coordinates":[-1.09690681591859,50.67648004247487],"type":"Point"}
}