{
  "type": "Feature",
  "properties": {
    "iso:country": "GB",
    "wof:name": "FY5 2AP",
    "wof:placetype": "postalcode"
  },
  "geometry": {"coordinates":[-3.038018,53.881505],"type":"Point"}
}
