{
  "type": "Feature",
  "properties": {
    "iso:country":"GB",
    "wof:name":"NG19 6EE",
    "wof:placetype":"postalcode"
},
  "geometry": {"coordinates":[-1.20562266142487,53.14870950318036],"type":"Point"}
}