{
  "type": "Feature",
  "properties": {
    "date:inception_lower": "1995-12-01",
    "date:inception_upper": "1995-12-01",
    "iso:country": "GB",
    "wof:name": "NG19 6EE",
    "wof:placetype": "postalcode"
  },
  "geometry": {"coordinates":[-1.205623,53.148709],"type":"Point"}
}
