{
  "type": "Feature",
  "properties": {
    "date:inception_lower": "2002-09-01",
    "date:inception_upper": "2002-09-01",
    "iso:country": "GB",
    "wof:name": "WS8 6EG",
    "wof:placetype": "postalcode"
  },
  "geometry": {"coordinates":[-1.938267,52.645431],"type":"Point"}
}
