{
  "type": "Feature",
  "properties": {
    "iso:country": "GB",
    "wof:name": "WS8 6EG",
    "wof:placetype": "postalcode"
  },
  "geometry": {"coordinates":[-1.938267,52.645431],"type":"Point"}
}
