{
  "type": "Feature",
  "properties": {
    "iso:country":"GB",
    "wof:name":"WS8 6EG",
    "wof:placetype":"postalcode"
},
  "geometry": {"coordinates":[-1.93826701231586,52.64543112410413],"type":"Point"}
}