{
  "type": "Feature",
  "properties": {
    "date:inception_lower": "1980-01-01",
    "date:inception_upper": "1980-01-01",
    "iso:country": "GB",
    "wof:name": "BN15 9EY",
    "wof:placetype": "postalcode"
  },
  "geometry": {"coordinates":[-0.314387,50.835464],"type":"Point"}
}
