{
  "type": "Feature",
  "properties": {
    "date:inception_lower":"1980-01-01",
    "date:inception_upper":"1980-01-31",
    "iso:country":"GB",
    "wof:name":"TR14 8JS",
    "wof:placetype":"postalcode"
},
  "geometry": {"coordinates":[-5.299876,50.213855],"type":"Point"}
}