{
  "type": "Feature",
  "properties": {
    "iso:country":"GB",
    "wof:name":"TR14 8JS",
    "wof:placetype":"postalcode"
},
  "geometry": {"coordinates":[-5.29987577944508,50.21385488691506],"type":"Point"}
}