{
  "type": "Feature",
  "properties": {
    "iso:country": "GB",
    "wof:name": "TN24 0XR",
    "wof:placetype": "postalcode"
  },
  "geometry": {"coordinates":[0.885734,51.136319],"type":"Point"}
}
