{
  "type": "Feature",
  "properties": {
    "iso:country":"GB",
    "wof:name":"TN35 4QL",
    "wof:placetype":"postalcode"
},
  "geometry": {"coordinates":[0.57782042892083,50.91014504983806],"type":"Point"}
}