{
  "type": "Feature",
  "properties": {
    "date:inception_lower": "1980-01-01",
    "date:inception_upper": "1980-01-01",
    "iso:country": "GB",
    "wof:name": "NG1 1DP",
    "wof:placetype": "postalcode"
  },
  "geometry": {"coordinates":[-1.13908,52.953529],"type":"Point"}
}
