{
  "type": "Feature",
  "properties": {
    "iso:country":"GB",
    "wof:name":"NG1 1DP",
    "wof:placetype":"postalcode"
},
  "geometry": {"coordinates":[-1.13908018970206,52.95352851880992],"type":"Point"}
}