{
  "type": "Feature",
  "properties": {
    "iso:country":"GB",
    "wof:name":"EH19 3HD",
    "wof:placetype":"postalcode"
},
  "geometry": {"coordinates":[-3.10618217527894,55.87483834904008],"type":"Point"}
}