{
  "type": "Feature",
  "properties": {
    "iso:country": "GB",
    "wof:name": "SM7 2AX",
    "wof:placetype": "postalcode"
  },
  "geometry": {"coordinates":[-0.203047,51.319238],"type":"Point"}
}
