{
  "type": "Feature",
  "properties": {
    "iso:country":"GB",
    "wof:name":"NE37 1LL",
    "wof:placetype":"postalcode"
},
  "geometry": {"coordinates":[-1.54785850149986,54.90347842659097],"type":"Point"}
}