{
  "type": "Feature",
  "properties": {
    "iso:country":"GB",
    "wof:name":"LL53 7SG",
    "wof:placetype":"postalcode"
},
  "geometry": {"coordinates":[-4.53022346575365,52.84031052998989],"type":"Point"}
}