{
  "type": "Feature",
  "properties": {
    "date:inception_lower": "1980-01-01",
    "date:inception_upper": "1980-01-01",
    "iso:country": "GB",
    "wof:name": "LL53 7SG",
    "wof:placetype": "postalcode"
  },
  "geometry": {"coordinates":[-4.530223,52.840311],"type":"Point"}
}
