{
  "type": "Feature",
  "properties": {
    "iso:country":"GB",
    "wof:name":"N17 6TF",
    "wof:placetype":"postalcode"
},
  "geometry": {"coordinates":[-0.07720925629293,51.59411392151165],"type":"Point"}
}