{
  "type": "Feature",
  "properties": {
    "iso:country":"GB",
    "wof:name":"M25 9QL",
    "wof:placetype":"postalcode"
},
  "geometry": {"coordinates":[-2.29159208929677,53.52664543038412],"type":"Point"}
}