{
  "type": "Feature",
  "properties": {
    "date:inception_lower": "1980-01-01",
    "date:inception_upper": "1980-01-01",
    "iso:country": "GB",
    "wof:name": "ST14 5DZ",
    "wof:placetype": "postalcode"
  },
  "geometry": {"coordinates":[-1.907739,52.923447],"type":"Point"}
}
