{
  "type": "Feature",
  "properties": {
    "iso:country":"GB",
    "wof:name":"ST14 5DZ",
    "wof:placetype":"postalcode"
},
  "geometry": {"coordinates":[-1.90773907983284,52.92344747661882],"type":"Point"}
}