{
  "type": "Feature",
  "properties": {
    "iso:country":"GB",
    "wof:name":"BD5 7HX",
    "wof:placetype":"postalcode"
},
  "geometry": {"coordinates":[-1.7544825756143,53.77821293878829],"type":"Point"}
}