{
  "type": "Feature",
  "properties": {
    "iso:country":"GB",
    "wof:name":"HP4 3TH",
    "wof:placetype":"postalcode"
},
  "geometry": {"coordinates":[-0.60149012102314,51.77612485049842],"type":"Point"}
}