{
  "type": "Feature",
  "properties": {
    "date:inception_lower": "1980-01-01",
    "date:inception_upper": "1980-01-01",
    "iso:country": "GB",
    "wof:name": "HP4 3TH",
    "wof:placetype": "postalcode"
  },
  "geometry": {"coordinates":[-0.60149,51.776125],"type":"Point"}
}
