{
  "type": "Feature",
  "properties": {
    "iso:country": "GB",
    "wof:name": "BB4 8PN",
    "wof:placetype": "postalcode"
  },
  "geometry": {"coordinates":[-2.282993,53.725288],"type":"Point"}
}
