{
  "type": "Feature",
  "properties": {
    "iso:country": "GB",
    "wof:name": "NG21 9GU",
    "wof:placetype": "postalcode"
  },
  "geometry": {"coordinates":[-1.126251,53.170223],"type":"Point"}
}
