{
  "type": "Feature",
  "properties": {
    "iso:country":"GB",
    "wof:name":"NE40 3AY",
    "wof:placetype":"postalcode"
},
  "geometry": {"coordinates":[-1.77623419150792,54.97031488845924],"type":"Point"}
}