{
  "type": "Feature",
  "properties": {
    "iso:country":"GB",
    "wof:name":"TN38 8DP",
    "wof:placetype":"postalcode"
},
  "geometry": {"coordinates":[0.52971353576811,50.85882459368316],"type":"Point"}
}