{
  "type": "Feature",
  "properties": {
    "iso:country": "GB",
    "wof:name": "TA6 4UF",
    "wof:placetype": "postalcode"
  },
  "geometry": {"coordinates":[-2.975018,51.138181],"type":"Point"}
}
