{
  "type": "Feature",
  "properties": {
    "iso:country":"GB",
    "wof:name":"TW7 7AS",
    "wof:placetype":"postalcode"
},
  "geometry": {"coordinates":[-0.3278325947376,51.46498327231206],"type":"Point"}
}