{
  "type": "Feature",
  "properties": {
    "date:inception_lower": "1980-01-01",
    "date:inception_upper": "1980-01-01",
    "iso:country": "GB",
    "wof:name": "TW7 7AS",
    "wof:placetype": "postalcode"
  },
  "geometry": {"coordinates":[-0.327833,51.464983],"type":"Point"}
}
