{
  "type": "Feature",
  "properties": {
    "iso:country":"GB",
    "wof:name":"HP1 1TL",
    "wof:placetype":"postalcode"
},
  "geometry": {"coordinates":[-0.48177858078871,51.75401270216214],"type":"Point"}
}