{
  "type": "Feature",
  "properties": {
    "iso:country": "GB",
    "wof:name": "HP1 1TL",
    "wof:placetype": "postalcode"
  },
  "geometry": {"coordinates":[-0.481779,51.754013],"type":"Point"}
}
