{
  "type": "Feature",
  "properties": {
    "date:inception_lower": "2007-07-01",
    "date:inception_upper": "2007-07-01",
    "iso:country": "GB",
    "wof:name": "SR5 3JT",
    "wof:placetype": "postalcode"
  },
  "geometry": {"coordinates":[-1.418704,54.921521],"type":"Point"}
}
