{
  "type": "Feature",
  "properties": {
    "iso:country":"GB",
    "wof:name":"SR5 3JT",
    "wof:placetype":"postalcode"
},
  "geometry": {"coordinates":[-1.41869031155151,54.92151343059634],"type":"Point"}
}