{
  "type": "Feature",
  "properties": {
    "iso:country":"GB",
    "wof:name":"RG22 5FY",
    "wof:placetype":"postalcode"
},
  "geometry": {"coordinates":[-1.13523419477214,51.26023976416288],"type":"Point"}
}