{
  "type": "Feature",
  "properties": {
    "iso:country":"GB",
    "wof:name":"B35 6NX",
    "wof:placetype":"postalcode"
},
  "geometry": {"coordinates":[-1.78126037442353,52.52430569626195],"type":"Point"}
}