{
  "type": "Feature",
  "properties": {
    "date:inception_lower":"1980-01-01",
    "date:inception_upper":"1980-01-31",
    "iso:country":"GB",
    "wof:name":"B35 6NX",
    "wof:placetype":"postalcode"
},
  "geometry": {"coordinates":[-1.781208,52.524275],"type":"Point"}
}