{
  "type": "Feature",
  "properties": {
    "date:inception_lower": "1980-01-01",
    "date:inception_upper": "1980-01-01",
    "iso:country": "GB",
    "wof:name": "LL40 1TD",
    "wof:placetype": "postalcode"
  },
  "geometry": {"coordinates":[-3.884411,52.730729],"type":"Point"}
}
