{
  "type": "Feature",
  "properties": {
    "iso:country": "GB",
    "wof:name": "LE67 4RJ",
    "wof:placetype": "postalcode"
  },
  "geometry": {"coordinates":[-1.330269,52.723179],"type":"Point"}
}
