{
  "type": "Feature",
  "properties": {
    "iso:country": "GB",
    "wof:name": "LL14 3AL",
    "wof:placetype": "postalcode"
  },
  "geometry": {"coordinates":[-3.072113,52.973912],"type":"Point"}
}
