{
  "type": "Feature",
  "properties": {
    "iso:country":"GB",
    "wof:name":"ML3 8EG",
    "wof:placetype":"postalcode"
},
  "geometry": {"coordinates":[-4.06121184786667,55.75970725648723],"type":"Point"}
}