{
  "type": "Feature",
  "properties": {
    "iso:country": "GB",
    "wof:name": "PE6 9NY",
    "wof:placetype": "postalcode"
  },
  "geometry": {"coordinates":[-0.364412,52.716875],"type":"Point"}
}
