{
  "type": "Feature",
  "properties": {
    "iso:country":"GB",
    "wof:name":"PE6 9NY",
    "wof:placetype":"postalcode"
},
  "geometry": {"coordinates":[-0.36441205385007,52.71687512162757],"type":"Point"}
}