{
  "type": "Feature",
  "properties": {
    "iso:country":"GB",
    "wof:name":"AL3 5TT",
    "wof:placetype":"postalcode"
},
  "geometry": {"coordinates":[-0.34759280307376,51.76067324710352],"type":"Point"}
}