{
  "type": "Feature",
  "properties": {
    "iso:country": "GB",
    "wof:name": "AL3 5TT",
    "wof:placetype": "postalcode"
  },
  "geometry": {"coordinates":[-0.347593,51.760673],"type":"Point"}
}
