{
  "type": "Feature",
  "properties": {
    "iso:country":"GB",
    "wof:name":"M11 2HJ",
    "wof:placetype":"postalcode"
},
  "geometry": {"coordinates":[-2.17989742004781,53.47849023553613],"type":"Point"}
}