{
  "type": "Feature",
  "properties": {
    "iso:country":"GB",
    "wof:name":"SE14 6BW",
    "wof:placetype":"postalcode"
},
  "geometry": {"coordinates":[-0.0407058864406,51.47703811767646],"type":"Point"}
}