{
  "type": "Feature",
  "properties": {
    "iso:country": "GB",
    "wof:name": "NR28 0FP",
    "wof:placetype": "postalcode"
  },
  "geometry": {"coordinates":[1.383218,52.814871],"type":"Point"}
}
