{
  "type": "Feature",
  "properties": {
    "date:inception_lower":"2015-09-01",
    "date:inception_upper":"2015-09-30",
    "iso:country":"GB",
    "wof:name":"NR28 0FP",
    "wof:placetype":"postalcode"
},
  "geometry": {"coordinates":[1.383218,52.814871],"type":"Point"}
}