{
  "type": "Feature",
  "properties": {
    "date:inception_lower": "1980-01-01",
    "date:inception_upper": "1980-01-01",
    "iso:country": "GB",
    "wof:name": "OL16 4TL",
    "wof:placetype": "postalcode"
  },
  "geometry": {"coordinates":[-2.14398,53.599414],"type":"Point"}
}
