{
  "type": "Feature",
  "properties": {
    "date:inception_lower": "2004-07-01",
    "date:inception_upper": "2004-07-01",
    "iso:country": "GB",
    "wof:name": "TR1 2GH",
    "wof:placetype": "postalcode"
  },
  "geometry": {"coordinates":[-5.058245,50.25991],"type":"Point"}
}
