{
  "type": "Feature",
  "properties": {
    "iso:country":"GB",
    "wof:name":"TF2 8DE",
    "wof:placetype":"postalcode"
},
  "geometry": {"coordinates":[-2.43535636301294,52.71592587685343],"type":"Point"}
}