{
  "type": "Feature",
  "properties": {
    "iso:country":"GB",
    "wof:name":"DA7 6EP",
    "wof:placetype":"postalcode"
},
  "geometry": {"coordinates":[0.16710035775394,51.4584978186449],"type":"Point"}
}