{
  "type": "Feature",
  "properties": {
    "date:inception_lower":"2010-08-01",
    "date:inception_upper":"2010-08-31",
    "iso:country":"GB",
    "wof:name":"ME9 7FD",
    "wof:placetype":"postalcode"
},
  "geometry": {"coordinates":[0.668962,51.351408],"type":"Point"}
}