{
  "type": "Feature",
  "properties": {
    "iso:country":"GB",
    "wof:name":"ME9 7FD",
    "wof:placetype":"postalcode"
},
  "geometry": {"coordinates":[0.66917649600055,51.3514104686055],"type":"Point"}
}