{
  "type": "Feature",
  "properties": {
    "iso:country": "GB",
    "wof:name": "ME9 7FD",
    "wof:placetype": "postalcode"
  },
  "geometry": {"coordinates":[0.668962,51.351408],"type":"Point"}
}
