{
  "type": "Feature",
  "properties": {
    "iso:country":"GB",
    "wof:name":"KW1 5TE",
    "wof:placetype":"postalcode"
},
  "geometry": {"coordinates":[-3.13412086520808,58.390575439088],"type":"Point"}
}