{
  "type": "Feature",
  "properties": {
    "date:inception_lower": "2000-06-01",
    "date:inception_upper": "2000-06-01",
    "iso:country": "GB",
    "wof:name": "KW1 5TE",
    "wof:placetype": "postalcode"
  },
  "geometry": {"coordinates":[-3.134412,58.390909],"type":"Point"}
}
