{
  "type": "Feature",
  "properties": {
    "date:inception_lower":"2000-06-01",
    "date:inception_upper":"2000-06-30",
    "iso:country":"GB",
    "wof:name":"KW1 5TE",
    "wof:placetype":"postalcode"
},
  "geometry": {"coordinates":[-3.134121,58.390575],"type":"Point"}
}