{
  "type": "Feature",
  "properties": {
    "date:inception_lower": "2021-11-01",
    "date:inception_upper": "2021-11-01",
    "iso:country": "GB",
    "wof:name": "BN8 4FQ",
    "wof:placetype": "postalcode"
  },
  "geometry": {"coordinates":[-0.011751,50.92643],"type":"Point"}
}
