{
  "type": "Feature",
  "properties": {
    "iso:country":"GB",
    "wof:name":"SA6 8NA",
    "wof:placetype":"postalcode"
},
  "geometry": {"coordinates":[-3.93450900200587,51.65194086199124],"type":"Point"}
}