{
  "type": "Feature",
  "properties": {
    "date:inception_lower":"1980-01-01",
    "date:inception_upper":"1980-01-31",
    "iso:country":"GB",
    "wof:name":"SA6 8NA",
    "wof:placetype":"postalcode"
},
  "geometry": {"coordinates":[-3.934509,51.651941],"type":"Point"}
}