{
  "type": "Feature",
  "properties": {
    "iso:country":"GB",
    "wof:name":"TN14 5AA",
    "wof:placetype":"postalcode"
},
  "geometry": {"coordinates":[0.20307820045077,51.28918814275514],"type":"Point"}
}