{
  "type": "Feature",
  "properties": {
    "iso:country":"GB",
    "wof:name":"WR5 3TL",
    "wof:placetype":"postalcode"
},
  "geometry": {"coordinates":[-2.19851077076513,52.1689587738773],"type":"Point"}
}