{
  "type": "Feature",
  "properties": {
    "date:inception_lower":"1992-08-01",
    "date:inception_upper":"1992-08-31",
    "iso:country":"GB",
    "wof:name":"WR5 3TL",
    "wof:placetype":"postalcode"
},
  "geometry": {"coordinates":[-2.198511,52.168959],"type":"Point"}
}