{
  "type": "Feature",
  "properties": {
    "iso:country": "GB",
    "wof:name": "WR5 3TL",
    "wof:placetype": "postalcode"
  },
  "geometry": {"coordinates":[-2.198511,52.168959],"type":"Point"}
}
