{
  "type": "Feature",
  "properties": {
    "iso:country": "GB",
    "wof:name": "S80 1RQ",
    "wof:placetype": "postalcode"
  },
  "geometry": {"coordinates":[-1.121313,53.30798],"type":"Point"}
}
