{
  "type": "Feature",
  "properties": {
    "iso:country": "GB",
    "wof:name": "ME5 9EL",
    "wof:placetype": "postalcode"
  },
  "geometry": {"coordinates":[0.519681,51.339209],"type":"Point"}
}
