{
  "type": "Feature",
  "properties": {
    "iso:country":"GB",
    "wof:name":"SG8 7SN",
    "wof:placetype":"postalcode"
},
  "geometry": {"coordinates":[0.06950773004414,52.09323695136675],"type":"Point"}
}