{
  "type": "Feature",
  "properties": {
    "iso:country":"GB",
    "wof:name":"CW8 1BN",
    "wof:placetype":"postalcode"
},
  "geometry": {"coordinates":[-2.52281450299537,53.25347352654634],"type":"Point"}
}