{
  "type": "Feature",
  "properties": {
    "date:inception_lower":"1980-01-01",
    "date:inception_upper":"1980-01-31",
    "iso:country":"GB",
    "wof:name":"CT2 9NH",
    "wof:placetype":"postalcode"
},
  "geometry": {"coordinates":[1.07078,51.307589],"type":"Point"}
}