{
  "type": "Feature",
  "properties": {
    "iso:country":"GB",
    "wof:name":"CT2 9NH",
    "wof:placetype":"postalcode"
},
  "geometry": {"coordinates":[1.07073272384315,51.30754871108345],"type":"Point"}
}