{
  "type": "Feature",
  "properties": {
    "iso:country": "GB",
    "wof:name": "HP3 8RT",
    "wof:placetype": "postalcode"
  },
  "geometry": {"coordinates":[-0.448014,51.725913],"type":"Point"}
}
