{
  "type": "Feature",
  "properties": {
    "iso:country":"GB",
    "wof:name":"HP3 8RT",
    "wof:placetype":"postalcode"
},
  "geometry": {"coordinates":[-0.44801379303049,51.72591276698789],"type":"Point"}
}