{
  "type": "Feature",
  "properties": {
    "iso:country":"GB",
    "wof:name":"AB16 6UX",
    "wof:placetype":"postalcode"
},
  "geometry": {"coordinates":[-2.1576277564622,57.15506870626663],"type":"Point"}
}