{
  "type": "Feature",
  "properties": {
    "iso:country":"GB",
    "wof:name":"CR3 5TU",
    "wof:placetype":"postalcode"
},
  "geometry": {"coordinates":[-0.09111796276374,51.28892317617699],"type":"Point"}
}