{
  "type": "Feature",
  "properties": {
    "iso:country": "GB",
    "wof:name": "CR3 5TU",
    "wof:placetype": "postalcode"
  },
  "geometry": {"coordinates":[-0.091118,51.288923],"type":"Point"}
}
