{
  "type": "Feature",
  "properties": {
    "iso:country":"GB",
    "wof:name":"SA7 9PB",
    "wof:placetype":"postalcode"
},
  "geometry": {"coordinates":[-3.87660430595173,51.6629432386215],"type":"Point"}
}