{
  "type": "Feature",
  "properties": {
    "iso:country":"GB",
    "wof:name":"TW15 1NR",
    "wof:placetype":"postalcode"
},
  "geometry": {"coordinates":[-0.44291364658094,51.42997836058446],"type":"Point"}
}