{
  "type": "Feature",
  "properties": {
    "iso:country":"GB",
    "wof:name":"LL28 4ES",
    "wof:placetype":"postalcode"
},
  "geometry": {"coordinates":[-3.75029748872672,53.30851750148297],"type":"Point"}
}