{
  "type": "Feature",
  "properties": {
    "date:inception_lower": "2007-07-01",
    "date:inception_upper": "2007-07-01",
    "iso:country": "GB",
    "wof:name": "LL28 4ES",
    "wof:placetype": "postalcode"
  },
  "geometry": {"coordinates":[-3.750297,53.308517],"type":"Point"}
}
