{
  "type": "Feature",
  "properties": {
    "iso:country": "GB",
    "wof:name": "EX14 9HL",
    "wof:placetype": "postalcode"
  },
  "geometry": {"coordinates":[-3.130939,50.815353],"type":"Point"}
}
