{
  "type": "Feature",
  "properties": {
    "iso:country":"GB",
    "wof:name":"LA3 1UW",
    "wof:placetype":"postalcode"
},
  "geometry": {"coordinates":[-2.88200505774681,54.06157861522203],"type":"Point"}
}