{
  "type": "Feature",
  "properties": {
    "iso:country":"GB",
    "wof:name":"BH14 9LP",
    "wof:placetype":"postalcode"
},
  "geometry": {"coordinates":[-1.93057297294804,50.72374143160043],"type":"Point"}
}