{
  "type": "Feature",
  "properties": {
    "date:inception_lower": "1980-01-01",
    "date:inception_upper": "1980-01-01",
    "iso:country": "GB",
    "wof:name": "BH14 9LP",
    "wof:placetype": "postalcode"
  },
  "geometry": {"coordinates":[-1.930451,50.723748],"type":"Point"}
}
