{
  "type": "Feature",
  "properties": {
    "iso:country": "GB",
    "wof:name": "BH14 9LP",
    "wof:placetype": "postalcode"
  },
  "geometry": {"coordinates":[-1.930451,50.723748],"type":"Point"}
}
