{
  "type": "Feature",
  "properties": {
    "iso:country":"GB",
    "wof:name":"CH44 9EE",
    "wof:placetype":"postalcode"
},
  "geometry": {"coordinates":[-3.03214924583246,53.4109384925403],"type":"Point"}
}