{
  "type": "Feature",
  "properties": {
    "iso:country": "GB",
    "wof:name": "CH44 9EE",
    "wof:placetype": "postalcode"
  },
  "geometry": {"coordinates":[-3.031647,53.410753],"type":"Point"}
}
