{
  "type": "Feature",
  "properties": {
    "iso:country":"GB",
    "wof:name":"LL16 4BW",
    "wof:placetype":"postalcode"
},
  "geometry": {"coordinates":[-3.379736702676,53.20656725190909],"type":"Point"}
}