{
  "type": "Feature",
  "properties": {
    "date:inception_lower": "1980-01-01",
    "date:inception_upper": "1980-01-01",
    "iso:country": "GB",
    "wof:name": "LL16 4BW",
    "wof:placetype": "postalcode"
  },
  "geometry": {"coordinates":[-3.379544,53.20663],"type":"Point"}
}
