{
  "type": "Feature",
  "properties": {
    "iso:country":"GB",
    "wof:name":"GL2 9PX",
    "wof:placetype":"postalcode"
},
  "geometry": {"coordinates":[-2.21509853173727,51.90348960316317],"type":"Point"}
}