{
  "type": "Feature",
  "properties": {
    "iso:country":"GB",
    "wof:name":"CO9 4SY",
    "wof:placetype":"postalcode"
},
  "geometry": {"coordinates":[0.52983332140664,52.03067500545767],"type":"Point"}
}