{
  "type": "Feature",
  "properties": {
    "iso:country":"GB",
    "wof:name":"SE15 2AQ",
    "wof:placetype":"postalcode"
},
  "geometry": {"coordinates":[-0.06297796350164,51.4710593688596],"type":"Point"}
}