{
  "type": "Feature",
  "properties": {
    "iso:country":"GB",
    "wof:name":"BN1 2DG",
    "wof:placetype":"postalcode"
},
  "geometry": {"coordinates":[-0.14504790351649,50.82387379198448],"type":"Point"}
}