{
  "type": "Feature",
  "properties": {
    "iso:country":"GB",
    "wof:name":"W1D 5PT",
    "wof:placetype":"postalcode"
},
  "geometry": {"coordinates":[-0.131127820589,51.51191252041308],"type":"Point"}
}