{
  "type": "Feature",
  "properties": {
    "iso:country": "GB",
    "wof:name": "BS15 8FU",
    "wof:placetype": "postalcode"
  },
  "geometry": {"coordinates":[-2.511187,51.457776],"type":"Point"}
}
