{
  "type": "Feature",
  "properties": {
    "date:inception_lower": "2019-09-01",
    "date:inception_upper": "2019-09-01",
    "iso:country": "GB",
    "wof:name": "BS15 8FU",
    "wof:placetype": "postalcode"
  },
  "geometry": {"coordinates":[-2.511187,51.457776],"type":"Point"}
}
