{
  "type": "Feature",
  "properties": {
    "iso:country":"GB",
    "wof:name":"IP1 3RS",
    "wof:placetype":"postalcode"
},
  "geometry": {"coordinates":[1.14883305422576,52.06616721976523],"type":"Point"}
}