{
  "type": "Feature",
  "properties": {
    "date:inception_lower": "1980-01-01",
    "date:inception_upper": "1980-01-01",
    "iso:country": "GB",
    "wof:name": "IP1 3RS",
    "wof:placetype": "postalcode"
  },
  "geometry": {"coordinates":[1.148833,52.066167],"type":"Point"}
}
