{
  "type": "Feature",
  "properties": {
    "iso:country":"GB",
    "wof:name":"LL21 9EB",
    "wof:placetype":"postalcode"
},
  "geometry": {"coordinates":[-3.36994393199679,53.0275334684412],"type":"Point"}
}