{
  "type": "Feature",
  "properties": {
    "iso:country":"GB",
    "wof:name":"EN2 0HA",
    "wof:placetype":"postalcode"
},
  "geometry": {"coordinates":[-0.08653449722975,51.66694297244632],"type":"Point"}
}