{
  "type": "Feature",
  "properties": {
    "date:inception_lower":"2019-02-01",
    "date:inception_upper":"2019-02-28",
    "iso:country":"GB",
    "wof:name":"SL3 8QY",
    "wof:placetype":"postalcode"
},
  "geometry": {"coordinates":[-0.541574,51.490615],"type":"Point"}
}