{
  "type": "Feature",
  "properties": {
    "iso:country":"GB",
    "wof:name":"PL24 2JY",
    "wof:placetype":"postalcode"
},
  "geometry": {"coordinates":[-4.71842400802561,50.35578660421022],"type":"Point"}
}