{
  "type": "Feature",
  "properties": {
    "date:inception_lower":"1980-01-01",
    "date:inception_upper":"1980-01-31",
    "iso:country":"GB",
    "wof:name":"PL24 2JY",
    "wof:placetype":"postalcode"
},
  "geometry": {"coordinates":[-4.718424,50.355787],"type":"Point"}
}