{
  "type": "Feature",
  "properties": {
    "iso:country": "GB",
    "wof:name": "TN23 4XA",
    "wof:placetype": "postalcode"
  },
  "geometry": {"coordinates":[0.857002,51.143338],"type":"Point"}
}
