{
  "type": "Feature",
  "properties": {
    "iso:country":"GB",
    "wof:name":"CV22 5RF",
    "wof:placetype":"postalcode"
},
  "geometry": {"coordinates":[-1.26651573418712,52.353148389533],"type":"Point"}
}