{
  "type": "Feature",
  "properties": {
    "iso:country":"GB",
    "wof:name":"NR10 3NA",
    "wof:placetype":"postalcode"
},
  "geometry": {"coordinates":[1.29618339896336,52.71912928885754],"type":"Point"}
}