{
  "type": "Feature",
  "properties": {
    "iso:country": "GB",
    "wof:name": "NR10 3NA",
    "wof:placetype": "postalcode"
  },
  "geometry": {"coordinates":[1.296183,52.719129],"type":"Point"}
}
