{
  "type": "Feature",
  "properties": {
    "date:inception_lower": "1986-07-01",
    "date:inception_upper": "1986-07-01",
    "iso:country": "GB",
    "wof:name": "PL6 7HP",
    "wof:placetype": "postalcode"
  },
  "geometry": {"coordinates":[-4.103046,50.434587],"type":"Point"}
}
