{
  "type": "Feature",
  "properties": {
    "date:inception_lower": "1980-01-01",
    "date:inception_upper": "1980-01-01",
    "iso:country": "GB",
    "wof:name": "ST13 6JD",
    "wof:placetype": "postalcode"
  },
  "geometry": {"coordinates":[-2.022407,53.106509],"type":"Point"}
}
