{
  "type": "Feature",
  "properties": {
    "iso:country":"GB",
    "wof:name":"ST13 6JD",
    "wof:placetype":"postalcode"
},
  "geometry": {"coordinates":[-2.02251450541885,53.10647286512648],"type":"Point"}
}