{
  "type": "Feature",
  "properties": {
    "iso:country": "GB",
    "wof:name": "CT2 8NB",
    "wof:placetype": "postalcode"
  },
  "geometry": {"coordinates":[1.061696,51.282178],"type":"Point"}
}
