{
  "type": "Feature",
  "properties": {
    "iso:country":"GB",
    "wof:name":"CT2 8NB",
    "wof:placetype":"postalcode"
},
  "geometry": {"coordinates":[1.0616959824622,51.28217794861084],"type":"Point"}
}