{
  "type": "Feature",
  "properties": {
    "date:inception_lower":"1992-08-01",
    "date:inception_upper":"1992-08-31",
    "iso:country":"GB",
    "wof:name":"TF3 5ED",
    "wof:placetype":"postalcode"
},
  "geometry": {"coordinates":[-2.468525,52.684965],"type":"Point"}
}