{
  "type": "Feature",
  "properties": {
    "iso:country":"GB",
    "wof:name":"TF3 5ED",
    "wof:placetype":"postalcode"
},
  "geometry": {"coordinates":[-2.46852491423939,52.68496471759877],"type":"Point"}
}