{
  "type": "Feature",
  "properties": {
    "iso:country": "GB",
    "wof:name": "BR7 6RU",
    "wof:placetype": "postalcode"
  },
  "geometry": {"coordinates":[0.075274,51.419152],"type":"Point"}
}
