{
  "type": "Feature",
  "properties": {
    "iso:country":"GB",
    "wof:name":"BR7 6RU",
    "wof:placetype":"postalcode"
},
  "geometry": {"coordinates":[0.07527351036914,51.41915198959179],"type":"Point"}
}