{
  "type": "Feature",
  "properties": {
    "iso:country":"GB",
    "wof:name":"TS10 3PT",
    "wof:placetype":"postalcode"
},
  "geometry": {"coordinates":[-1.04540133084514,54.60730947559434],"type":"Point"}
}