{
  "type": "Feature",
  "properties": {
    "iso:country":"GB",
    "wof:name":"DN11 0TF",
    "wof:placetype":"postalcode"
},
  "geometry": {"coordinates":[-1.07811851507205,53.48067237526997],"type":"Point"}
}