{
  "type": "Feature",
  "properties": {
    "iso:country": "GB",
    "wof:name": "DN11 0TF",
    "wof:placetype": "postalcode"
  },
  "geometry": {"coordinates":[-1.078118,53.480672],"type":"Point"}
}
