{
  "type": "Feature",
  "properties": {
    "date:inception_lower": "2021-09-01",
    "date:inception_upper": "2021-09-01",
    "iso:country": "GB",
    "wof:name": "WA16 9GJ",
    "wof:placetype": "postalcode"
  },
  "geometry": {"coordinates":[-2.393648,53.255694],"type":"Point"}
}
