{
  "type": "Feature",
  "properties": {
    "iso:country":"GB",
    "wof:name":"NG10 1EJ",
    "wof:placetype":"postalcode"
},
  "geometry": {"coordinates":[-1.27466287683971,52.88960083472014],"type":"Point"}
}