{
  "type": "Feature",
  "properties": {
    "iso:country":"GB",
    "wof:name":"IP4 3LU",
    "wof:placetype":"postalcode"
},
  "geometry": {"coordinates":[1.19978151282504,52.0668354691115],"type":"Point"}
}