{
  "type": "Feature",
  "properties": {
    "iso:country":"GB",
    "wof:name":"BN15 8LY",
    "wof:placetype":"postalcode"
},
  "geometry": {"coordinates":[-0.30163240830068,50.82533198257109],"type":"Point"}
}