{
  "type": "Feature",
  "properties": {
    "iso:country":"GB",
    "wof:name":"DT6 3QN",
    "wof:placetype":"postalcode"
},
  "geometry": {"coordinates":[-2.75934534274001,50.73397647382885],"type":"Point"}
}