{
  "type": "Feature",
  "properties": {
    "date:inception_lower":"1980-01-01",
    "date:inception_upper":"1980-01-31",
    "iso:country":"GB",
    "wof:name":"DT6 3QN",
    "wof:placetype":"postalcode"
},
  "geometry": {"coordinates":[-2.759345,50.733976],"type":"Point"}
}