{
  "type": "Feature",
  "properties": {
    "iso:country": "GB",
    "wof:name": "DT6 3QN",
    "wof:placetype": "postalcode"
  },
  "geometry": {"coordinates":[-2.759345,50.733976],"type":"Point"}
}
