{
  "type": "Feature",
  "properties": {
    "iso:country":"GB",
    "wof:name":"LS24 8DH",
    "wof:placetype":"postalcode"
},
  "geometry": {"coordinates":[-1.22474478070948,53.90656582428015],"type":"Point"}
}