{
  "type": "Feature",
  "properties": {
    "iso:country":"GB",
    "wof:name":"UB5 5NR",
    "wof:placetype":"postalcode"
},
  "geometry": {"coordinates":[-0.38714473271963,51.53725762787345],"type":"Point"}
}