{
  "type": "Feature",
  "properties": {
    "iso:country":"GB",
    "wof:name":"SE6 1RD",
    "wof:placetype":"postalcode"
},
  "geometry": {"coordinates":[-0.00207216423283,51.4387155355403],"type":"Point"}
}