{
  "type": "Feature",
  "properties": {
    "date:inception_lower": "1980-01-01",
    "date:inception_upper": "1980-01-01",
    "iso:country": "GB",
    "wof:name": "SE6 1RD",
    "wof:placetype": "postalcode"
  },
  "geometry": {"coordinates":[-0.002072,51.438716],"type":"Point"}
}
