{
  "type": "Feature",
  "properties": {
    "date:inception_lower": "1980-01-01",
    "date:inception_upper": "1980-01-01",
    "iso:country": "GB",
    "wof:name": "IP2 9NA",
    "wof:placetype": "postalcode"
  },
  "geometry": {"coordinates":[1.125841,52.042451],"type":"Point"}
}
