{
  "type": "Feature",
  "properties": {
    "iso:country":"GB",
    "wof:name":"IP2 9NA",
    "wof:placetype":"postalcode"
},
  "geometry": {"coordinates":[1.12584114705862,52.0424513471061],"type":"Point"}
}