{
  "type": "Feature",
  "properties": {
    "iso:country":"GB",
    "wof:name":"S75 1PL",
    "wof:placetype":"postalcode"
},
  "geometry": {"coordinates":[-1.5277554742393,53.55757456503508],"type":"Point"}
}