{
  "type": "Feature",
  "properties": {
    "iso:country": "GB",
    "wof:name": "NN7 4GH",
    "wof:placetype": "postalcode"
  },
  "geometry": {"coordinates":[-0.983795,52.228082],"type":"Point"}
}
