{
  "type": "Feature",
  "properties": {
    "iso:country":"GB",
    "wof:name":"KA7 4PW",
    "wof:placetype":"postalcode"
},
  "geometry": {"coordinates":[-4.642585960171,55.43221618540536],"type":"Point"}
}