{
  "type": "Feature",
  "properties": {
    "iso:country":"GB",
    "wof:name":"KW15 1AN",
    "wof:placetype":"postalcode"
},
  "geometry": {"coordinates":[-2.96415790428402,58.98117467021232],"type":"Point"}
}