{
  "type": "Feature",
  "properties": {
    "iso:country":"GB",
    "wof:name":"LS7 4PX",
    "wof:placetype":"postalcode"
},
  "geometry": {"coordinates":[-1.53336450952088,53.83221302216855],"type":"Point"}
}