{
  "type": "Feature",
  "properties": {
    "iso:country":"GB",
    "wof:name":"HA4 0PW",
    "wof:placetype":"postalcode"
},
  "geometry": {"coordinates":[-0.38522100448849,51.5606468400501],"type":"Point"}
}