{
  "type": "Feature",
  "properties": {
    "iso:country":"GB",
    "wof:name":"SE15 1NP",
    "wof:placetype":"postalcode"
},
  "geometry": {"coordinates":[-0.05358813593897,51.48158713917365],"type":"Point"}
}