{
  "type": "Feature",
  "properties": {
    "iso:country":"GB",
    "wof:name":"AL8 6TD",
    "wof:placetype":"postalcode"
},
  "geometry": {"coordinates":[-0.2207624233898,51.79371991289499],"type":"Point"}
}