{
  "type": "Feature",
  "properties": {
    "date:inception_lower": "1980-01-01",
    "date:inception_upper": "1980-01-01",
    "iso:country": "GB",
    "wof:name": "AL8 6TD",
    "wof:placetype": "postalcode"
  },
  "geometry": {"coordinates":[-0.220762,51.79372],"type":"Point"}
}
