{
  "type": "Feature",
  "properties": {
    "iso:country": "GB",
    "wof:name": "AL8 6TD",
    "wof:placetype": "postalcode"
  },
  "geometry": {"coordinates":[-0.220762,51.79372],"type":"Point"}
}
