{
  "type": "Feature",
  "properties": {
    "iso:country":"GB",
    "wof:name":"LS6 3QA",
    "wof:placetype":"postalcode"
},
  "geometry": {"coordinates":[-1.584424650726,53.82532709484174],"type":"Point"}
}