{
  "type": "Feature",
  "properties": {
    "date:inception_lower": "1980-01-01",
    "date:inception_upper": "1980-01-01",
    "iso:country": "GB",
    "wof:name": "SY11 3BX",
    "wof:placetype": "postalcode"
  },
  "geometry": {"coordinates":[-3.001593,52.926631],"type":"Point"}
}
