{
  "type": "Feature",
  "properties": {
    "iso:country":"GB",
    "wof:name":"KT20 5PA",
    "wof:placetype":"postalcode"
},
  "geometry": {"coordinates":[-0.22533337757874,51.30995518588556],"type":"Point"}
}