{
  "type": "Feature",
  "properties": {
    "iso:country":"GB",
    "wof:name":"SP3 5HW",
    "wof:placetype":"postalcode"
},
  "geometry": {"coordinates":[-1.98256092890469,51.08322234354951],"type":"Point"}
}