{
  "type": "Feature",
  "properties": {
    "iso:country": "GB",
    "wof:name": "BN11 5BG",
    "wof:placetype": "postalcode"
  },
  "geometry": {"coordinates":[-0.39614,50.813296],"type":"Point"}
}
