{
  "type": "Feature",
  "properties": {
    "iso:country": "GB",
    "wof:name": "CM22 6FY",
    "wof:placetype": "postalcode"
  },
  "geometry": {"coordinates":[0.256756,51.867354],"type":"Point"}
}
