{
  "type": "Feature",
  "properties": {
    "iso:country": "GB",
    "wof:name": "OX15 0RT",
    "wof:placetype": "postalcode"
  },
  "geometry": {"coordinates":[-1.327558,51.983872],"type":"Point"}
}
