{
  "type": "Feature",
  "properties": {
    "iso:country": "GB",
    "wof:name": "BL0 0EU",
    "wof:placetype": "postalcode"
  },
  "geometry": {"coordinates":[-2.304675,53.665716],"type":"Point"}
}
