{
  "type": "Feature",
  "properties": {
    "iso:country":"GB",
    "wof:name":"ST3 7SG",
    "wof:placetype":"postalcode"
},
  "geometry": {"coordinates":[-2.08764278248092,52.96826198303603],"type":"Point"}
}