{
  "type": "Feature",
  "properties": {
    "date:inception_lower": "1980-01-01",
    "date:inception_upper": "1980-01-01",
    "iso:country": "GB",
    "wof:name": "ST9 0EH",
    "wof:placetype": "postalcode"
  },
  "geometry": {"coordinates":[-2.091445,53.02721],"type":"Point"}
}
