{
  "type": "Feature",
  "properties": {
    "iso:country":"GB",
    "wof:name":"ST9 0EH",
    "wof:placetype":"postalcode"
},
  "geometry": {"coordinates":[-2.09144529352652,53.02721009375308],"type":"Point"}
}