{
  "type": "Feature",
  "properties": {
    "date:inception_lower": "2023-05-01",
    "date:inception_upper": "2023-05-01",
    "iso:country": "GB",
    "wof:name": "DN11 8SU",
    "wof:placetype": "postalcode"
  },
  "geometry": {"coordinates":[-1.06798,53.425566],"type":"Point"}
}
