{
  "type": "Feature",
  "properties": {
    "iso:country":"GB",
    "wof:name":"TS25 3JL",
    "wof:placetype":"postalcode"
},
  "geometry": {"coordinates":[-1.23389917286358,54.66063815480493],"type":"Point"}
}