{
  "type": "Feature",
  "properties": {
    "iso:country": "GB",
    "wof:name": "LL19 9BW",
    "wof:placetype": "postalcode"
  },
  "geometry": {"coordinates":[-3.402348,53.333055],"type":"Point"}
}
