{
  "type": "Feature",
  "properties": {
    "iso:country":"GB",
    "wof:name":"LS26 0UW",
    "wof:placetype":"postalcode"
},
  "geometry": {"coordinates":[-1.49400881432171,53.75417197759959],"type":"Point"}
}