{
  "type": "Feature",
  "properties": {
    "iso:country": "GB",
    "wof:name": "LS26 0UW",
    "wof:placetype": "postalcode"
  },
  "geometry": {"coordinates":[-1.494009,53.754172],"type":"Point"}
}
