{
  "type": "Feature",
  "properties": {
    "date:inception_lower": "1993-01-01",
    "date:inception_upper": "1993-01-01",
    "iso:country": "GB",
    "wof:name": "CF63 1BS",
    "wof:placetype": "postalcode"
  },
  "geometry": {"coordinates":[-3.259289,51.413767],"type":"Point"}
}
