{
  "type": "Feature",
  "properties": {
    "iso:country":"GB",
    "wof:name":"CF63 1BS",
    "wof:placetype":"postalcode"
},
  "geometry": {"coordinates":[-3.25928937570299,51.41376720860401],"type":"Point"}
}