{
  "type": "Feature",
  "properties": {
    "iso:country":"GB",
    "wof:name":"W9 2DZ",
    "wof:placetype":"postalcode"
},
  "geometry": {"coordinates":[-0.19493077595412,51.52350489058367],"type":"Point"}
}