{
  "type": "Feature",
  "properties": {
    "iso:country": "GB",
    "wof:name": "S5 7JT",
    "wof:placetype": "postalcode"
  },
  "geometry": {"coordinates":[-1.460158,53.410227],"type":"Point"}
}
