{
  "type": "Feature",
  "properties": {
    "date:inception_lower":"2014-06-01",
    "date:inception_upper":"2014-06-30",
    "iso:country":"GB",
    "wof:name":"PE1 5DF",
    "wof:placetype":"postalcode"
},
  "geometry": {"coordinates":[-0.227498,52.568644],"type":"Point"}
}