{
  "type": "Feature",
  "properties": {
    "iso:country": "GB",
    "wof:name": "CM17 0FX",
    "wof:placetype": "postalcode"
  },
  "geometry": {"coordinates":[0.153282,51.787183],"type":"Point"}
}
