{
  "type": "Feature",
  "properties": {
    "iso:country":"GB",
    "wof:name":"CO10 1PT",
    "wof:placetype":"postalcode"
},
  "geometry": {"coordinates":[0.7450125365562,52.05082955639312],"type":"Point"}
}