{
  "type": "Feature",
  "properties": {
    "iso:country": "GB",
    "wof:name": "RH8 9LB",
    "wof:placetype": "postalcode"
  },
  "geometry": {"coordinates":[-0.010253,51.254869],"type":"Point"}
}
