{
  "type": "Feature",
  "properties": {
    "date:inception_lower": "1980-01-01",
    "date:inception_upper": "1980-01-01",
    "iso:country": "GB",
    "wof:name": "BH23 7NA",
    "wof:placetype": "postalcode"
  },
  "geometry": {"coordinates":[-1.77235,50.754547],"type":"Point"}
}
