{
  "type": "Feature",
  "properties": {
    "iso:country": "GB",
    "wof:name": "BH23 7NA",
    "wof:placetype": "postalcode"
  },
  "geometry": {"coordinates":[-1.77235,50.754547],"type":"Point"}
}
