{
  "type": "Feature",
  "properties": {
    "iso:country":"GB",
    "wof:name":"BH23 7NA",
    "wof:placetype":"postalcode"
},
  "geometry": {"coordinates":[-1.77235048521092,50.75454691314961],"type":"Point"}
}