{
  "type": "Feature",
  "properties": {
    "date:inception_lower": "2006-04-01",
    "date:inception_upper": "2006-04-01",
    "iso:country": "GB",
    "wof:name": "ML11 9GW",
    "wof:placetype": "postalcode"
  },
  "geometry": {"coordinates":[-3.811263,55.682505],"type":"Point"}
}
