{
  "type": "Feature",
  "properties": {
    "iso:country": "GB",
    "wof:name": "ML11 9GW",
    "wof:placetype": "postalcode"
  },
  "geometry": {"coordinates":[-3.811263,55.682505],"type":"Point"}
}
