{
  "type": "Feature",
  "properties": {
    "date:inception_lower":"1993-08-01",
    "date:inception_upper":"1993-08-31",
    "iso:country":"GB",
    "wof:name":"DN9 1QZ",
    "wof:placetype":"postalcode"
},
  "geometry": {"coordinates":[-0.809819,53.523588],"type":"Point"}
}