{
  "type": "Feature",
  "properties": {
    "iso:country":"GB",
    "wof:name":"DN9 1QZ",
    "wof:placetype":"postalcode"
},
  "geometry": {"coordinates":[-0.80981897738422,53.523588461298],"type":"Point"}
}