{
  "type": "Feature",
  "properties": {
    "iso:country":"GB",
    "wof:name":"WD3 3BY",
    "wof:placetype":"postalcode"
},
  "geometry": {"coordinates":[-0.44619403988016,51.64591441778671],"type":"Point"}
}