{
  "type": "Feature",
  "properties": {
    "date:inception_lower":"1980-01-01",
    "date:inception_upper":"1980-01-31",
    "iso:country":"GB",
    "wof:name":"NE31 1NU",
    "wof:placetype":"postalcode"
},
  "geometry": {"coordinates":[-1.52187,54.97385],"type":"Point"}
}