{
  "type": "Feature",
  "properties": {
    "iso:country": "GB",
    "wof:name": "ST21 6AX",
    "wof:placetype": "postalcode"
  },
  "geometry": {"coordinates":[-2.254957,52.854557],"type":"Point"}
}
