{
  "type": "Feature",
  "properties": {
    "iso:country":"GB",
    "wof:name":"NG8 5JH",
    "wof:placetype":"postalcode"
},
  "geometry": {"coordinates":[-1.19764692341806,52.97713098193335],"type":"Point"}
}