{
  "type": "Feature",
  "properties": {
    "iso:country": "GB",
    "wof:name": "NG8 5JH",
    "wof:placetype": "postalcode"
  },
  "geometry": {"coordinates":[-1.197647,52.977131],"type":"Point"}
}
