{
  "type": "Feature",
  "properties": {
    "date:inception_lower": "1980-01-01",
    "date:inception_upper": "1980-01-01",
    "iso:country": "GB",
    "wof:name": "HX6 4LJ",
    "wof:placetype": "postalcode"
  },
  "geometry": {"coordinates":[-1.966543,53.668913],"type":"Point"}
}
