{
  "type": "Feature",
  "properties": {
    "iso:country":"GB",
    "wof:name":"PA19 1BQ",
    "wof:placetype":"postalcode"
},
  "geometry": {"coordinates":[-4.86572616829036,55.94410645795489],"type":"Point"}
}