{
  "type": "Feature",
  "properties": {
    "date:inception_lower": "2004-08-01",
    "date:inception_upper": "2004-08-01",
    "iso:country": "GB",
    "wof:name": "PA19 1BQ",
    "wof:placetype": "postalcode"
  },
  "geometry": {"coordinates":[-4.865726,55.944106],"type":"Point"}
}
