{
  "type": "Feature",
  "properties": {
    "iso:country":"GB",
    "wof:name":"KY11 2UY",
    "wof:placetype":"postalcode"
},
  "geometry": {"coordinates":[-3.41392406342204,56.02859691599735],"type":"Point"}
}