{
  "type": "Feature",
  "properties": {
    "iso:country":"GB",
    "wof:name":"NG19 0NA",
    "wof:placetype":"postalcode"
},
  "geometry": {"coordinates":[-1.17729985581152,53.15592437204806],"type":"Point"}
}