{
  "type": "Feature",
  "properties": {
    "iso:country": "GB",
    "wof:name": "NG19 0NA",
    "wof:placetype": "postalcode"
  },
  "geometry": {"coordinates":[-1.1773,53.155924],"type":"Point"}
}
