{
  "type": "Feature",
  "properties": {
    "date:inception_lower": "2022-03-01",
    "date:inception_upper": "2022-03-01",
    "iso:country": "GB",
    "wof:name": "CA12 5FJ",
    "wof:placetype": "postalcode"
  },
  "geometry": {"coordinates":[-3.136479,54.601023],"type":"Point"}
}
