{
  "type": "Feature",
  "properties": {
    "iso:country":"GB",
    "wof:name":"LS6 3BP",
    "wof:placetype":"postalcode"
},
  "geometry": {"coordinates":[-1.57815870772834,53.81693741755013],"type":"Point"}
}