{
  "type": "Feature",
  "properties": {
    "date:inception_lower":"1993-01-01",
    "date:inception_upper":"1993-01-31",
    "iso:country":"GB",
    "wof:name":"CO10 5LD",
    "wof:placetype":"postalcode"
},
  "geometry": {"coordinates":[0.811289,52.02216],"type":"Point"}
}