{
  "type": "Feature",
  "properties": {
    "iso:country":"GB",
    "wof:name":"CO10 5LD",
    "wof:placetype":"postalcode"
},
  "geometry": {"coordinates":[0.81128899696957,52.02216041860796],"type":"Point"}
}