{
  "type": "Feature",
  "properties": {
    "iso:country": "GB",
    "wof:name": "PL6 8BH",
    "wof:placetype": "postalcode"
  },
  "geometry": {"coordinates":[-4.110758,50.420866],"type":"Point"}
}
