{
  "type": "Feature",
  "properties": {
    "date:inception_lower": "1980-01-01",
    "date:inception_upper": "1980-01-01",
    "iso:country": "GB",
    "wof:name": "WS10 0EG",
    "wof:placetype": "postalcode"
  },
  "geometry": {"coordinates":[-1.992465,52.549184],"type":"Point"}
}
