{
  "type": "Feature",
  "properties": {
    "iso:country":"GB",
    "wof:name":"WS10 0EG",
    "wof:placetype":"postalcode"
},
  "geometry": {"coordinates":[-1.99246496131629,52.54918429537675],"type":"Point"}
}