{
  "type": "Feature",
  "properties": {
    "date:inception_lower": "2019-03-01",
    "date:inception_upper": "2019-03-01",
    "iso:country": "GB",
    "wof:name": "S71 4GH",
    "wof:placetype": "postalcode"
  },
  "geometry": {"coordinates":[-1.472967,53.598386],"type":"Point"}
}
