{
  "type": "Feature",
  "properties": {
    "iso:country": "GB",
    "wof:name": "S71 4GH",
    "wof:placetype": "postalcode"
  },
  "geometry": {"coordinates":[-1.472967,53.598386],"type":"Point"}
}
