{
  "type": "Feature",
  "properties": {
    "iso:country":"GB",
    "wof:name":"E14 9YB",
    "wof:placetype":"postalcode"
},
  "geometry": {"coordinates":[-0.02160527809132,51.49013446695349],"type":"Point"}
}