{
  "type": "Feature",
  "properties": {
    "date:inception_lower": "1987-10-01",
    "date:inception_upper": "1987-10-01",
    "iso:country": "GB",
    "wof:name": "E14 9YB",
    "wof:placetype": "postalcode"
  },
  "geometry": {"coordinates":[-0.021605,51.490134],"type":"Point"}
}
