{
  "type": "Feature",
  "properties": {
    "iso:country":"GB",
    "wof:name":"HU6 7SX",
    "wof:placetype":"postalcode"
},
  "geometry": {"coordinates":[-0.3638837658026,53.77012554649981],"type":"Point"}
}