{
  "type": "Feature",
  "properties": {
    "iso:country":"GB",
    "wof:name":"NG16 6AN",
    "wof:placetype":"postalcode"
},
  "geometry": {"coordinates":[-1.29338990857242,53.07225203341383],"type":"Point"}
}