{
  "type": "Feature",
  "properties": {
    "iso:country": "GB",
    "wof:name": "LU7 9AE",
    "wof:placetype": "postalcode"
  },
  "geometry": {"coordinates":[-0.649327,51.835219],"type":"Point"}
}
