{
  "type": "Feature",
  "properties": {
    "iso:country":"GB",
    "wof:name":"LU7 9AE",
    "wof:placetype":"postalcode"
},
  "geometry": {"coordinates":[-0.64932669509739,51.83521930449312],"type":"Point"}
}