{
  "type": "Feature",
  "properties": {
    "iso:country": "GB",
    "wof:name": "EH22 1RU",
    "wof:placetype": "postalcode"
  },
  "geometry": {"coordinates":[-3.089201,55.899673],"type":"Point"}
}
