{
  "type": "Feature",
  "properties": {
    "date:inception_lower":"1980-01-01",
    "date:inception_upper":"1980-01-31",
    "iso:country":"GB",
    "wof:name":"EH22 1RU",
    "wof:placetype":"postalcode"
},
  "geometry": {"coordinates":[-3.089201,55.899673],"type":"Point"}
}