{
  "type": "Feature",
  "properties": {
    "iso:country": "GB",
    "wof:name": "KA17 0BE",
    "wof:placetype": "postalcode"
  },
  "geometry": {"coordinates":[-4.275273,55.613751],"type":"Point"}
}
