{
  "type": "Feature",
  "properties": {
    "date:inception_lower": "2018-08-01",
    "date:inception_upper": "2018-08-01",
    "iso:country": "GB",
    "wof:name": "KW17 2AQ",
    "wof:placetype": "postalcode"
  },
  "geometry": {"coordinates":[-3.316669,59.115074],"type":"Point"}
}
