{
  "type": "Feature",
  "properties": {
    "iso:country": "GB",
    "wof:name": "KW17 2AQ",
    "wof:placetype": "postalcode"
  },
  "geometry": {"coordinates":[-3.316669,59.115074],"type":"Point"}
}
