{
  "type": "Feature",
  "properties": {
    "date:inception_lower": "2001-12-01",
    "date:inception_upper": "2001-12-01",
    "iso:country": "GB",
    "wof:name": "WR11 8TR",
    "wof:placetype": "postalcode"
  },
  "geometry": {"coordinates":[-1.879892,52.11393],"type":"Point"}
}
