{
  "type": "Feature",
  "properties": {
    "iso:country": "GB",
    "wof:name": "HX2 7SH",
    "wof:placetype": "postalcode"
  },
  "geometry": {"coordinates":[-1.921392,53.71927],"type":"Point"}
}
