{
  "type": "Feature",
  "properties": {
    "iso:country":"GB",
    "wof:name":"HX2 7SH",
    "wof:placetype":"postalcode"
},
  "geometry": {"coordinates":[-1.92140751156581,53.71916210162992],"type":"Point"}
}