{
  "type": "Feature",
  "properties": {
    "iso:country":"GB",
    "wof:name":"BH23 8NJ",
    "wof:placetype":"postalcode"
},
  "geometry": {"coordinates":[-1.7369009683793,50.78149522178986],"type":"Point"}
}