{
  "type": "Feature",
  "properties": {
    "iso:country": "GB",
    "wof:name": "HA9 0EF",
    "wof:placetype": "postalcode"
  },
  "geometry": {"coordinates":[-0.283022,51.56043],"type":"Point"}
}
