{
  "type": "Feature",
  "properties": {
    "date:inception_lower":"2016-09-01",
    "date:inception_upper":"2016-09-30",
    "iso:country":"GB",
    "wof:name":"HA9 0EF",
    "wof:placetype":"postalcode"
},
  "geometry": {"coordinates":[-0.283022,51.56043],"type":"Point"}
}