{
  "type": "Feature",
  "properties": {
    "iso:country":"GB",
    "wof:name":"DH9 7BB",
    "wof:placetype":"postalcode"
},
  "geometry": {"coordinates":[-1.70886538007224,54.85951488888443],"type":"Point"}
}