{
  "type": "Feature",
  "properties": {
    "iso:country": "GB",
    "wof:name": "BN20 9PX",
    "wof:placetype": "postalcode"
  },
  "geometry": {"coordinates":[0.244378,50.810079],"type":"Point"}
}
