{
  "type": "Feature",
  "properties": {
    "iso:country":"GB",
    "wof:name":"PL5 3HP",
    "wof:placetype":"postalcode"
},
  "geometry": {"coordinates":[-4.14429968946095,50.40358536239501],"type":"Point"}
}