{
  "type": "Feature",
  "properties": {
    "iso:country":"GB",
    "wof:name":"LL11 3DS",
    "wof:placetype":"postalcode"
},
  "geometry": {"coordinates":[-3.08578744059113,53.05479336173747],"type":"Point"}
}