{
  "type": "Feature",
  "properties": {
    "iso:country":"GB",
    "wof:name":"WC2E 7NR",
    "wof:placetype":"postalcode"
},
  "geometry": {"coordinates":[-0.12391636956737,51.51029563730683],"type":"Point"}
}