{
  "type": "Feature",
  "properties": {
    "iso:country":"GB",
    "wof:name":"DL8 1SJ",
    "wof:placetype":"postalcode"
},
  "geometry": {"coordinates":[-1.67126637429295,54.30285582255556],"type":"Point"}
}