{
  "type": "Feature",
  "properties": {
    "date:inception_lower": "1980-01-01",
    "date:inception_upper": "1980-01-01",
    "iso:country": "GB",
    "wof:name": "NW10 9SU",
    "wof:placetype": "postalcode"
  },
  "geometry": {"coordinates":[-0.246945,51.547395],"type":"Point"}
}
