{
  "type": "Feature",
  "properties": {
    "date:inception_lower": "2012-06-01",
    "date:inception_upper": "2012-06-01",
    "iso:country": "GB",
    "wof:name": "OX11 0TX",
    "wof:placetype": "postalcode"
  },
  "geometry": {"coordinates":[-1.304478,51.571762],"type":"Point"}
}
