{
  "type": "Feature",
  "properties": {
    "iso:country": "GB",
    "wof:name": "OX11 0TX",
    "wof:placetype": "postalcode"
  },
  "geometry": {"coordinates":[-1.304478,51.571762],"type":"Point"}
}
