{
  "type": "Feature",
  "properties": {
    "date:inception_lower":"1993-01-01",
    "date:inception_upper":"1993-01-31",
    "iso:country":"GB",
    "wof:name":"NG12 3TU",
    "wof:placetype":"postalcode"
},
  "geometry": {"coordinates":[-1.042305,52.912785],"type":"Point"}
}