{
  "type": "Feature",
  "properties": {
    "iso:country":"GB",
    "wof:name":"NG12 3TU",
    "wof:placetype":"postalcode"
},
  "geometry": {"coordinates":[-1.04230495354676,52.9127845816383],"type":"Point"}
}