{
  "type": "Feature",
  "properties": {
    "iso:country": "GB",
    "wof:name": "NG12 3TU",
    "wof:placetype": "postalcode"
  },
  "geometry": {"coordinates":[-1.042305,52.912785],"type":"Point"}
}
