{
  "type": "Feature",
  "properties": {
    "date:inception_lower":"1980-01-01",
    "date:inception_upper":"1980-01-31",
    "iso:country":"GB",
    "wof:name":"NE38 7RE",
    "wof:placetype":"postalcode"
},
  "geometry": {"coordinates":[-1.523016,54.896823],"type":"Point"}
}