{
  "type": "Feature",
  "properties": {
    "iso:country":"GB",
    "wof:name":"NE38 7RE",
    "wof:placetype":"postalcode"
},
  "geometry": {"coordinates":[-1.52301634136578,54.89682343538363],"type":"Point"}
}