{
  "type": "Feature",
  "properties": {
    "iso:country": "GB",
    "wof:name": "NE38 7RE",
    "wof:placetype": "postalcode"
  },
  "geometry": {"coordinates":[-1.523016,54.896823],"type":"Point"}
}
