{
  "type": "Feature",
  "properties": {
    "iso:country":"GB",
    "wof:name":"BD6 2AU",
    "wof:placetype":"postalcode"
},
  "geometry": {"coordinates":[-1.80540396560396,53.76282892252908],"type":"Point"}
}