{
  "type": "Feature",
  "properties": {
    "iso:country": "GB",
    "wof:name": "BD6 2AU",
    "wof:placetype": "postalcode"
  },
  "geometry": {"coordinates":[-1.805404,53.762829],"type":"Point"}
}
