{
  "type": "Feature",
  "properties": {
    "iso:country":"GB",
    "wof:name":"PO4 0SN",
    "wof:placetype":"postalcode"
},
  "geometry": {"coordinates":[-1.07816383842132,50.77925696577723],"type":"Point"}
}