{
  "type": "Feature",
  "properties": {
    "date:inception_lower":"2002-10-01",
    "date:inception_upper":"2002-10-31",
    "iso:country":"GB",
    "wof:name":"PO4 0SN",
    "wof:placetype":"postalcode"
},
  "geometry": {"coordinates":[-1.078164,50.779257],"type":"Point"}
}