{
  "type": "Feature",
  "properties": {
    "date:inception_lower": "1990-02-01",
    "date:inception_upper": "1990-02-01",
    "iso:country": "GB",
    "wof:name": "CV10 8LW",
    "wof:placetype": "postalcode"
  },
  "geometry": {"coordinates":[-1.497961,52.51662],"type":"Point"}
}
