{
  "type": "Feature",
  "properties": {
    "iso:country":"GB",
    "wof:name":"LL16 3HR",
    "wof:placetype":"postalcode"
},
  "geometry": {"coordinates":[-3.40215434158381,53.18739133043326],"type":"Point"}
}