{
  "type": "Feature",
  "properties": {
    "iso:country":"GB",
    "wof:name":"LL21 9AY",
    "wof:placetype":"postalcode"
},
  "geometry": {"coordinates":[-3.32178252384587,52.98221254885586],"type":"Point"}
}