{
  "type": "Feature",
  "properties": {
    "iso:country": "GB",
    "wof:name": "BS2 0QW",
    "wof:placetype": "postalcode"
  },
  "geometry": {"coordinates":[-2.573919,51.451308],"type":"Point"}
}
