{
  "type": "Feature",
  "properties": {
    "date:inception_lower":"1980-01-01",
    "date:inception_upper":"1980-01-31",
    "iso:country":"GB",
    "wof:name":"BN14 8LQ",
    "wof:placetype":"postalcode"
},
  "geometry": {"coordinates":[-0.362399,50.82424],"type":"Point"}
}