{
  "type": "Feature",
  "properties": {
    "iso:country":"GB",
    "wof:name":"OX2 0BQ",
    "wof:placetype":"postalcode"
},
  "geometry": {"coordinates":[-1.27446683582616,51.75101241174553],"type":"Point"}
}