{
  "type": "Feature",
  "properties": {
    "iso:country":"GB",
    "wof:name":"BN1 8LE",
    "wof:placetype":"postalcode"
},
  "geometry": {"coordinates":[-0.13621022918805,50.86217089960631],"type":"Point"}
}