{
  "type": "Feature",
  "properties": {
    "iso:country": "GB",
    "wof:name": "PE32 2QZ",
    "wof:placetype": "postalcode"
  },
  "geometry": {"coordinates":[0.714606,52.725697],"type":"Point"}
}
