{
  "type": "Feature",
  "properties": {
    "iso:country":"GB",
    "wof:name":"HR6 9EG",
    "wof:placetype":"postalcode"
},
  "geometry": {"coordinates":[-2.91184374324675,52.19606065737468],"type":"Point"}
}