{
  "type": "Feature",
  "properties": {
    "date:inception_lower": "1980-01-01",
    "date:inception_upper": "1980-01-01",
    "iso:country": "GB",
    "wof:name": "HR6 9EG",
    "wof:placetype": "postalcode"
  },
  "geometry": {"coordinates":[-2.911845,52.196071],"type":"Point"}
}
