{
  "type": "Feature",
  "properties": {
    "iso:country": "GB",
    "wof:name": "HR6 9EG",
    "wof:placetype": "postalcode"
  },
  "geometry": {"coordinates":[-2.912193,52.192328],"type":"Point"}
}
