{
  "type": "Feature",
  "properties": {
    "date:inception_lower":"2004-05-01",
    "date:inception_upper":"2004-05-31",
    "iso:country":"GB",
    "wof:name":"PL16 0BA",
    "wof:placetype":"postalcode"
},
  "geometry": {"coordinates":[-4.267181,50.643336],"type":"Point"}
}