{
  "type": "Feature",
  "properties": {
    "iso:country":"GB",
    "wof:name":"PL16 0BA",
    "wof:placetype":"postalcode"
},
  "geometry": {"coordinates":[-4.26718133261635,50.64333640078046],"type":"Point"}
}