{
  "type": "Feature",
  "properties": {
    "date:inception_lower":"1980-01-01",
    "date:inception_upper":"1980-01-31",
    "iso:country":"GB",
    "wof:name":"CB11 4PF",
    "wof:placetype":"postalcode"
},
  "geometry": {"coordinates":[0.144345,51.964129],"type":"Point"}
}