{
  "type": "Feature",
  "properties": {
    "date:inception_lower": "1980-01-01",
    "date:inception_upper": "1980-01-01",
    "iso:country": "GB",
    "wof:name": "TS9 5AW",
    "wof:placetype": "postalcode"
  },
  "geometry": {"coordinates":[-1.183984,54.468411],"type":"Point"}
}
