{
  "type": "Feature",
  "properties": {
    "iso:country":"GB",
    "wof:name":"CF5 2DP",
    "wof:placetype":"postalcode"
},
  "geometry": {"coordinates":[-3.22052666838805,51.4943499523859],"type":"Point"}
}