{
  "type": "Feature",
  "properties": {
    "iso:country": "GB",
    "wof:name": "CF5 2DP",
    "wof:placetype": "postalcode"
  },
  "geometry": {"coordinates":[-3.220527,51.49435],"type":"Point"}
}
