{
  "type": "Feature",
  "properties": {
    "iso:country": "GB",
    "wof:name": "SE9 2BG",
    "wof:placetype": "postalcode"
  },
  "geometry": {"coordinates":[0.075493,51.43833],"type":"Point"}
}
