{
  "type": "Feature",
  "properties": {
    "iso:country":"GB",
    "wof:name":"CO10 0TS",
    "wof:placetype":"postalcode"
},
  "geometry": {"coordinates":[0.79629462542457,52.05915591442572],"type":"Point"}
}