{
  "type": "Feature",
  "properties": {
    "iso:country":"GB",
    "wof:name":"LE67 9RA",
    "wof:placetype":"postalcode"
},
  "geometry": {"coordinates":[-1.26360892833762,52.68202384835746],"type":"Point"}
}