{
  "type": "Feature",
  "properties": {
    "iso:country": "GB",
    "wof:name": "LE67 9RA",
    "wof:placetype": "postalcode"
  },
  "geometry": {"coordinates":[-1.263609,52.682024],"type":"Point"}
}
