{
  "type": "Feature",
  "properties": {
    "iso:country": "GB",
    "wof:name": "GL5 5NH",
    "wof:placetype": "postalcode"
  },
  "geometry": {"coordinates":[-2.230922,51.7239],"type":"Point"}
}
