{
  "type": "Feature",
  "properties": {
    "iso:country":"GB",
    "wof:name":"GL5 5NH",
    "wof:placetype":"postalcode"
},
  "geometry": {"coordinates":[-2.23092195857651,51.72390037468844],"type":"Point"}
}