{
  "type": "Feature",
  "properties": {
    "iso:country": "GB",
    "wof:name": "E18 2FG",
    "wof:placetype": "postalcode"
  },
  "geometry": {"coordinates":[0.024035,51.596854],"type":"Point"}
}
