{
  "type": "Feature",
  "properties": {
    "date:inception_lower":"2011-02-01",
    "date:inception_upper":"2011-02-28",
    "iso:country":"GB",
    "wof:name":"E18 2FG",
    "wof:placetype":"postalcode"
},
  "geometry": {"coordinates":[0.024035,51.596854],"type":"Point"}
}