{
  "type": "Feature",
  "properties": {
    "iso:country":"GB",
    "wof:name":"E18 2FG",
    "wof:placetype":"postalcode"
},
  "geometry": {"coordinates":[0.02403528264729,51.59685382592667],"type":"Point"}
}