{
  "type": "Feature",
  "properties": {
    "date:inception_lower": "2016-06-01",
    "date:inception_upper": "2016-06-01",
    "iso:country": "GB",
    "wof:name": "PO6 2NQ",
    "wof:placetype": "postalcode"
  },
  "geometry": {"coordinates":[-1.050693,50.839342],"type":"Point"}
}
