{
  "type": "Feature",
  "properties": {
    "iso:country":"GB",
    "wof:name":"ST2 9JX",
    "wof:placetype":"postalcode"
},
  "geometry": {"coordinates":[-2.13956974554709,53.01666394276334],"type":"Point"}
}