{
  "type": "Feature",
  "properties": {
    "iso:country": "GB",
    "wof:name": "WA9 2DZ",
    "wof:placetype": "postalcode"
  },
  "geometry": {"coordinates":[-2.700371,53.454244],"type":"Point"}
}
