{
  "type": "Feature",
  "properties": {
    "iso:country":"GB",
    "wof:name":"WA9 2DZ",
    "wof:placetype":"postalcode"
},
  "geometry": {"coordinates":[-2.70037120177068,53.45424447534845],"type":"Point"}
}