{
  "type": "Feature",
  "properties": {
    "iso:country":"GB",
    "wof:name":"WR4 9YQ",
    "wof:placetype":"postalcode"
},
  "geometry": {"coordinates":[-2.186271642528,52.21411961646679],"type":"Point"}
}