{
  "type": "Feature",
  "properties": {
    "iso:country":"GB",
    "wof:name":"DY5 3NL",
    "wof:placetype":"postalcode"
},
  "geometry": {"coordinates":[-2.1405841490225,52.4793839670097],"type":"Point"}
}