{
  "type": "Feature",
  "properties": {
    "iso:country": "GB",
    "wof:name": "DY5 3NL",
    "wof:placetype": "postalcode"
  },
  "geometry": {"coordinates":[-2.140607,52.479416],"type":"Point"}
}
