{
  "type": "Feature",
  "properties": {
    "date:inception_lower":"1995-01-01",
    "date:inception_upper":"1995-01-31",
    "iso:country":"GB",
    "wof:name":"TN23 3LU",
    "wof:placetype":"postalcode"
},
  "geometry": {"coordinates":[0.865151,51.123261],"type":"Point"}
}