{
  "type": "Feature",
  "properties": {
    "iso:country":"GB",
    "wof:name":"TN23 3LU",
    "wof:placetype":"postalcode"
},
  "geometry": {"coordinates":[0.86515060976048,51.12326130131324],"type":"Point"}
}