{
  "type": "Feature",
  "properties": {
    "iso:country": "GB",
    "wof:name": "TN23 3LU",
    "wof:placetype": "postalcode"
  },
  "geometry": {"coordinates":[0.865151,51.123261],"type":"Point"}
}
