{
  "type": "Feature",
  "properties": {
    "iso:country":"GB",
    "wof:name":"ME15 6PN",
    "wof:placetype":"postalcode"
},
  "geometry": {"coordinates":[0.52156319855103,51.26622974322819],"type":"Point"}
}