{
  "type": "Feature",
  "properties": {
    "iso:country":"GB",
    "wof:name":"WR9 9DL",
    "wof:placetype":"postalcode"
},
  "geometry": {"coordinates":[-2.16284161322539,52.27465922705475],"type":"Point"}
}