{
  "type": "Feature",
  "properties": {
    "iso:country":"GB",
    "wof:name":"LS6 1PX",
    "wof:placetype":"postalcode"
},
  "geometry": {"coordinates":[-1.5680632014221,53.80758094632115],"type":"Point"}
}