{
  "type": "Feature",
  "properties": {
    "iso:country":"GB",
    "wof:name":"NG23 7HF",
    "wof:placetype":"postalcode"
},
  "geometry": {"coordinates":[-0.74864699640405,53.21342016507366],"type":"Point"}
}