{
  "type": "Feature",
  "properties": {
    "iso:country": "GB",
    "wof:name": "NG23 7HF",
    "wof:placetype": "postalcode"
  },
  "geometry": {"coordinates":[-0.748647,53.21342],"type":"Point"}
}
