{
  "type": "Feature",
  "properties": {
    "date:inception_lower": "1980-01-01",
    "date:inception_upper": "1980-01-01",
    "iso:country": "GB",
    "wof:name": "BS15 4LG",
    "wof:placetype": "postalcode"
  },
  "geometry": {"coordinates":[-2.489988,51.46596],"type":"Point"}
}
