{
  "type": "Feature",
  "properties": {
    "iso:country":"GB",
    "wof:name":"E6 3QJ",
    "wof:placetype":"postalcode"
},
  "geometry": {"coordinates":[0.0530539904672,51.52502885382108],"type":"Point"}
}