{
  "type": "Feature",
  "properties": {
    "iso:country":"GB",
    "wof:name":"B13 0SH",
    "wof:placetype":"postalcode"
},
  "geometry": {"coordinates":[-1.88464871300021,52.43037137481266],"type":"Point"}
}