{
  "type": "Feature",
  "properties": {
    "date:inception_lower": "2016-05-01",
    "date:inception_upper": "2016-05-01",
    "iso:country": "GB",
    "wof:name": "SE18 1DS",
    "wof:placetype": "postalcode"
  },
  "geometry": {"coordinates":[0.090372,51.484335],"type":"Point"}
}
