{
  "type": "Feature",
  "properties": {
    "date:inception_lower": "2001-12-01",
    "date:inception_upper": "2001-12-01",
    "iso:country": "GB",
    "wof:name": "WR11 2QN",
    "wof:placetype": "postalcode"
  },
  "geometry": {"coordinates":[-1.9615,52.084061],"type":"Point"}
}
