{
  "type": "Feature",
  "properties": {
    "iso:country":"GB",
    "wof:name":"WV1 4DW",
    "wof:placetype":"postalcode"
},
  "geometry": {"coordinates":[-2.13252752876956,52.58602229164136],"type":"Point"}
}