{
  "type": "Feature",
  "properties": {
    "iso:country": "GB",
    "wof:name": "WV1 4DW",
    "wof:placetype": "postalcode"
  },
  "geometry": {"coordinates":[-2.132527,52.586022],"type":"Point"}
}
