{
  "type": "Feature",
  "properties": {
    "date:inception_lower": "2016-10-01",
    "date:inception_upper": "2016-10-01",
    "iso:country": "GB",
    "wof:name": "NG3 5XA",
    "wof:placetype": "postalcode"
  },
  "geometry": {"coordinates":[-1.091957,52.994505],"type":"Point"}
}
