{
  "type": "Feature",
  "properties": {
    "iso:country":"GB",
    "wof:name":"EH11 1AX",
    "wof:placetype":"postalcode"
},
  "geometry": {"coordinates":[-3.21768627401544,55.94036864350039],"type":"Point"}
}