{
  "type": "Feature",
  "properties": {
    "iso:country":"GB",
    "wof:name":"WN8 0BN",
    "wof:placetype":"postalcode"
},
  "geometry": {"coordinates":[-2.73275939962238,53.53877693801526],"type":"Point"}
}