{
  "type": "Feature",
  "properties": {
    "iso:country": "GB",
    "wof:name": "WN8 0BN",
    "wof:placetype": "postalcode"
  },
  "geometry": {"coordinates":[-2.732759,53.538777],"type":"Point"}
}
