{
  "type": "Feature",
  "properties": {
    "iso:country":"GB",
    "wof:name":"OL10 4UR",
    "wof:placetype":"postalcode"
},
  "geometry": {"coordinates":[-2.22430757719788,53.59941643200703],"type":"Point"}
}