{
  "type": "Feature",
  "properties": {
    "date:inception_lower": "1980-01-01",
    "date:inception_upper": "1980-01-01",
    "iso:country": "GB",
    "wof:name": "OL10 4UR",
    "wof:placetype": "postalcode"
  },
  "geometry": {"coordinates":[-2.224308,53.599416],"type":"Point"}
}
