{
  "type": "Feature",
  "properties": {
    "iso:country":"GB",
    "wof:name":"NG25 0TT",
    "wof:placetype":"postalcode"
},
  "geometry": {"coordinates":[-0.89498995939379,53.05765070175836],"type":"Point"}
}