{
  "type": "Feature",
  "properties": {
    "date:inception_lower": "1980-01-01",
    "date:inception_upper": "1980-01-01",
    "iso:country": "GB",
    "wof:name": "B37 7QR",
    "wof:placetype": "postalcode"
  },
  "geometry": {"coordinates":[-1.733998,52.472067],"type":"Point"}
}
