{
  "type": "Feature",
  "properties": {
    "iso:country":"GB",
    "wof:name":"B37 7QR",
    "wof:placetype":"postalcode"
},
  "geometry": {"coordinates":[-1.73399819499226,52.47206728659125],"type":"Point"}
}