{
  "type": "Feature",
  "properties": {
    "date:inception_lower": "1980-01-01",
    "date:inception_upper": "1980-01-01",
    "iso:country": "GB",
    "wof:name": "BD17 7PJ",
    "wof:placetype": "postalcode"
  },
  "geometry": {"coordinates":[-1.776639,53.841402],"type":"Point"}
}
