{
  "type": "Feature",
  "properties": {
    "iso:country":"GB",
    "wof:name":"EX6 7TS",
    "wof:placetype":"postalcode"
},
  "geometry": {"coordinates":[-3.53595606180518,50.66629968033767],"type":"Point"}
}