{
  "type": "Feature",
  "properties": {
    "date:inception_lower":"1980-01-01",
    "date:inception_upper":"1980-01-31",
    "iso:country":"GB",
    "wof:name":"LE11 2LP",
    "wof:placetype":"postalcode"
},
  "geometry": {"coordinates":[-1.20378,52.758141],"type":"Point"}
}