{
  "type": "Feature",
  "properties": {
    "iso:country":"GB",
    "wof:name":"LE11 2LP",
    "wof:placetype":"postalcode"
},
  "geometry": {"coordinates":[-1.20378006217849,52.75814059036718],"type":"Point"}
}