{
  "type": "Feature",
  "properties": {
    "iso:country":"GB",
    "wof:name":"TF9 4QX",
    "wof:placetype":"postalcode"
},
  "geometry": {"coordinates":[-2.44372853060765,52.94528876112154],"type":"Point"}
}