{
  "type": "Feature",
  "properties": {
    "date:inception_lower": "2000-06-01",
    "date:inception_upper": "2000-06-01",
    "iso:country": "GB",
    "wof:name": "TF9 4QX",
    "wof:placetype": "postalcode"
  },
  "geometry": {"coordinates":[-2.443728,52.945289],"type":"Point"}
}
