{
  "type": "Feature",
  "properties": {
    "iso:country": "GB",
    "wof:name": "WV6 0EA",
    "wof:placetype": "postalcode"
  },
  "geometry": {"coordinates":[-2.150867,52.592617],"type":"Point"}
}
