{
  "type": "Feature",
  "properties": {
    "iso:country": "GB",
    "wof:name": "SN3 5PA",
    "wof:placetype": "postalcode"
  },
  "geometry": {"coordinates":[-1.725109,51.555382],"type":"Point"}
}
