{
  "type": "Feature",
  "properties": {
    "date:inception_lower": "1995-12-01",
    "date:inception_upper": "1995-12-01",
    "iso:country": "GB",
    "wof:name": "TS27 4QG",
    "wof:placetype": "postalcode"
  },
  "geometry": {"coordinates":[-1.293238,54.736651],"type":"Point"}
}
