{
  "type": "Feature",
  "properties": {
    "iso:country": "GB",
    "wof:name": "S42 7DA",
    "wof:placetype": "postalcode"
  },
  "geometry": {"coordinates":[-1.541827,53.237849],"type":"Point"}
}
