{
  "type": "Feature",
  "properties": {
    "iso:country":"GB",
    "wof:name":"PE32 2LP",
    "wof:placetype":"postalcode"
},
  "geometry": {"coordinates":[0.73046006010407,52.70328328183657],"type":"Point"}
}