{
  "type": "Feature",
  "properties": {
    "iso:country": "GB",
    "wof:name": "PE32 2LP",
    "wof:placetype": "postalcode"
  },
  "geometry": {"coordinates":[0.73046,52.703283],"type":"Point"}
}
