{
  "type": "Feature",
  "properties": {
    "iso:country":"GB",
    "wof:name":"SS1 3FW",
    "wof:placetype":"postalcode"
},
  "geometry": {"coordinates":[0.7537939588711,51.53084812198731],"type":"Point"}
}