{
  "type": "Feature",
  "properties": {
    "iso:country":"GB",
    "wof:name":"LS20 8HD",
    "wof:placetype":"postalcode"
},
  "geometry": {"coordinates":[-1.73368439730936,53.8683356712319],"type":"Point"}
}