{
  "type": "Feature",
  "properties": {
    "iso:country": "GB",
    "wof:name": "LS20 8HD",
    "wof:placetype": "postalcode"
  },
  "geometry": {"coordinates":[-1.733684,53.868336],"type":"Point"}
}
