{
  "type": "Feature",
  "properties": {
    "iso:country":"GB",
    "wof:name":"NE47 0DL",
    "wof:placetype":"postalcode"
},
  "geometry": {"coordinates":[-2.0280838952054,54.92182053305908],"type":"Point"}
}