{
  "type": "Feature",
  "properties": {
    "iso:country": "GB",
    "wof:name": "NE47 0DL",
    "wof:placetype": "postalcode"
  },
  "geometry": {"coordinates":[-2.028084,54.921821],"type":"Point"}
}
