{
  "type": "Feature",
  "properties": {
    "iso:country": "GB",
    "wof:name": "BD19 6PJ",
    "wof:placetype": "postalcode"
  },
  "geometry": {"coordinates":[-1.753393,53.718063],"type":"Point"}
}
