{
  "type": "Feature",
  "properties": {
    "date:inception_lower":"2002-11-01",
    "date:inception_upper":"2002-11-30",
    "iso:country":"GB",
    "wof:name":"BD19 6PJ",
    "wof:placetype":"postalcode"
},
  "geometry": {"coordinates":[-1.753393,53.718063],"type":"Point"}
}