{
  "type": "Feature",
  "properties": {
    "iso:country":"GB",
    "wof:name":"BD19 6PJ",
    "wof:placetype":"postalcode"
},
  "geometry": {"coordinates":[-1.75339308944973,53.71806264038792],"type":"Point"}
}