{
  "type": "Feature",
  "properties": {
    "iso:country":"GB",
    "wof:name":"BH1 4AX",
    "wof:placetype":"postalcode"
},
  "geometry": {"coordinates":[-1.84199328047751,50.72635304783365],"type":"Point"}
}