{
  "type": "Feature",
  "properties": {
    "iso:country":"GB",
    "wof:name":"WS7 0EQ",
    "wof:placetype":"postalcode"
},
  "geometry": {"coordinates":[-1.91578119629413,52.67173913188111],"type":"Point"}
}