{
  "type": "Feature",
  "properties": {
    "iso:country": "GB",
    "wof:name": "WS7 0EQ",
    "wof:placetype": "postalcode"
  },
  "geometry": {"coordinates":[-1.915781,52.671739],"type":"Point"}
}
