{
  "type": "Feature",
  "properties": {
    "iso:country":"GB",
    "wof:name":"LA13 9NJ",
    "wof:placetype":"postalcode"
},
  "geometry": {"coordinates":[-3.20416114817303,54.13100370029823],"type":"Point"}
}