{
  "type": "Feature",
  "properties": {
    "date:inception_lower":"1981-06-01",
    "date:inception_upper":"1981-06-30",
    "iso:country":"GB",
    "wof:name":"LA13 9NJ",
    "wof:placetype":"postalcode"
},
  "geometry": {"coordinates":[-3.204161,54.131004],"type":"Point"}
}