{
  "type": "Feature",
  "properties": {
    "iso:country": "GB",
    "wof:name": "TN4 0AD",
    "wof:placetype": "postalcode"
  },
  "geometry": {"coordinates":[0.265619,51.156943],"type":"Point"}
}
