{
  "type": "Feature",
  "properties": {
    "date:inception_lower": "1980-01-01",
    "date:inception_upper": "1980-01-01",
    "iso:country": "GB",
    "wof:name": "TN4 0AD",
    "wof:placetype": "postalcode"
  },
  "geometry": {"coordinates":[0.265619,51.156943],"type":"Point"}
}
