{
  "type": "Feature",
  "properties": {
    "iso:country":"GB",
    "wof:name":"RG4 7LU",
    "wof:placetype":"postalcode"
},
  "geometry": {"coordinates":[-0.97955064388975,51.47293280134831],"type":"Point"}
}