{
  "type": "Feature",
  "properties": {
    "iso:country":"GB",
    "wof:name":"CR3 5JP",
    "wof:placetype":"postalcode"
},
  "geometry": {"coordinates":[-0.09901264042918,51.29292755421367],"type":"Point"}
}