{
  "type": "Feature",
  "properties": {
    "iso:country": "GB",
    "wof:name": "WN3 6HQ",
    "wof:placetype": "postalcode"
  },
  "geometry": {"coordinates":[-2.667885,53.524038],"type":"Point"}
}
