{
  "type": "Feature",
  "properties": {
    "iso:country":"GB",
    "wof:name":"WN3 6HQ",
    "wof:placetype":"postalcode"
},
  "geometry": {"coordinates":[-2.66788514582685,53.52403827647417],"type":"Point"}
}