{
  "type": "Feature",
  "properties": {
    "iso:country":"GB",
    "wof:name":"SY3 7EP",
    "wof:placetype":"postalcode"
},
  "geometry": {"coordinates":[-2.74745767480796,52.70273578057334],"type":"Point"}
}