{
  "type": "Feature",
  "properties": {
    "date:inception_lower": "1980-01-01",
    "date:inception_upper": "1980-01-01",
    "iso:country": "GB",
    "wof:name": "SY3 7EP",
    "wof:placetype": "postalcode"
  },
  "geometry": {"coordinates":[-2.747458,52.702736],"type":"Point"}
}
