{
  "type": "Feature",
  "properties": {
    "date:inception_lower": "1980-01-01",
    "date:inception_upper": "1980-01-01",
    "iso:country": "GB",
    "wof:name": "LE1 7RJ",
    "wof:placetype": "postalcode"
  },
  "geometry": {"coordinates":[-1.123367,52.619327],"type":"Point"}
}
