{
  "type": "Feature",
  "properties": {
    "iso:country": "GB",
    "wof:name": "LE1 7RJ",
    "wof:placetype": "postalcode"
  },
  "geometry": {"coordinates":[-1.124243,52.618731],"type":"Point"}
}
