{
  "type": "Feature",
  "properties": {
    "date:inception_lower":"1980-01-01",
    "date:inception_upper":"1980-01-31",
    "iso:country":"GB",
    "wof:name":"MK17 8SP",
    "wof:placetype":"postalcode"
},
  "geometry": {"coordinates":[-0.643176,52.018161],"type":"Point"}
}