{
  "type": "Feature",
  "properties": {
    "iso:country":"GB",
    "wof:name":"YO11 3PF",
    "wof:placetype":"postalcode"
},
  "geometry": {"coordinates":[-0.34995028199351,54.22582867003693],"type":"Point"}
}