{
  "type": "Feature",
  "properties": {
    "iso:country": "GB",
    "wof:name": "YO11 3PF",
    "wof:placetype": "postalcode"
  },
  "geometry": {"coordinates":[-0.34995,54.225829],"type":"Point"}
}
