{
  "type": "Feature",
  "properties": {
    "iso:country":"GB",
    "wof:name":"LS27 0QX",
    "wof:placetype":"postalcode"
},
  "geometry": {"coordinates":[-1.59504254160353,53.73396390079129],"type":"Point"}
}