{
  "type": "Feature",
  "properties": {
    "date:inception_lower": "2021-11-01",
    "date:inception_upper": "2021-11-01",
    "iso:country": "GB",
    "wof:name": "PE11 1YJ",
    "wof:placetype": "postalcode"
  },
  "geometry": {"coordinates":[-0.169971,52.774958],"type":"Point"}
}
