{
  "type": "Feature",
  "properties": {
    "iso:country": "GB",
    "wof:name": "RM12 5SB",
    "wof:placetype": "postalcode"
  },
  "geometry": {"coordinates":[0.204769,51.544993],"type":"Point"}
}
