{
  "type": "Feature",
  "properties": {
    "iso:country":"GB",
    "wof:name":"RM12 5SB",
    "wof:placetype":"postalcode"
},
  "geometry": {"coordinates":[0.20487011174036,51.54498014832852],"type":"Point"}
}