{
  "type": "Feature",
  "properties": {
    "iso:country": "GB",
    "wof:name": "RG12 9JE",
    "wof:placetype": "postalcode"
  },
  "geometry": {"coordinates":[-0.731155,51.404264],"type":"Point"}
}
