{
  "type": "Feature",
  "properties": {
    "date:inception_lower": "1980-01-01",
    "date:inception_upper": "1980-01-01",
    "iso:country": "GB",
    "wof:name": "DE4 4EN",
    "wof:placetype": "postalcode"
  },
  "geometry": {"coordinates":[-1.574861,53.08381],"type":"Point"}
}
