{
  "type": "Feature",
  "properties": {
    "iso:country":"GB",
    "wof:name":"MK5 6JA",
    "wof:placetype":"postalcode"
},
  "geometry": {"coordinates":[-0.78030104565739,52.022922721675],"type":"Point"}
}