{
  "type": "Feature",
  "properties": {
    "date:inception_lower": "1991-01-01",
    "date:inception_upper": "1991-01-01",
    "iso:country": "GB",
    "wof:name": "MK5 6JA",
    "wof:placetype": "postalcode"
  },
  "geometry": {"coordinates":[-0.780301,52.022923],"type":"Point"}
}
