{
  "type": "Feature",
  "properties": {
    "iso:country": "GB",
    "wof:name": "IG8 9PW",
    "wof:placetype": "postalcode"
  },
  "geometry": {"coordinates":[0.007113,51.603394],"type":"Point"}
}
