{
  "type": "Feature",
  "properties": {
    "iso:country":"GB",
    "wof:name":"IG8 9PW",
    "wof:placetype":"postalcode"
},
  "geometry": {"coordinates":[0.00711260788511,51.60339429080409],"type":"Point"}
}