{
  "type": "Feature",
  "properties": {
    "date:inception_lower":"1980-01-01",
    "date:inception_upper":"1980-01-31",
    "iso:country":"GB",
    "wof:name":"KY7 4DY",
    "wof:placetype":"postalcode"
},
  "geometry": {"coordinates":[-3.165939,56.192457],"type":"Point"}
}