{
  "type": "Feature",
  "properties": {
    "date:inception_lower": "2022-04-01",
    "date:inception_upper": "2022-04-01",
    "iso:country": "GB",
    "wof:name": "BD20 9FN",
    "wof:placetype": "postalcode"
  },
  "geometry": {"coordinates":[-1.931893,53.919236],"type":"Point"}
}
