{
  "type": "Feature",
  "properties": {
    "iso:country":"GB",
    "wof:name":"CB23 2RT",
    "wof:placetype":"postalcode"
},
  "geometry": {"coordinates":[-0.01495083005046,52.18809651088164],"type":"Point"}
}