{
  "type": "Feature",
  "properties": {
    "date:inception_lower": "1980-01-01",
    "date:inception_upper": "1980-01-01",
    "iso:country": "GB",
    "wof:name": "GU30 7BU",
    "wof:placetype": "postalcode"
  },
  "geometry": {"coordinates":[-0.790769,51.078285],"type":"Point"}
}
