{
  "type": "Feature",
  "properties": {
    "iso:country":"GB",
    "wof:name":"GU30 7BU",
    "wof:placetype":"postalcode"
},
  "geometry": {"coordinates":[-0.79076915128141,51.07828519436642],"type":"Point"}
}