{
  "type": "Feature",
  "properties": {
    "iso:country":"GB",
    "wof:name":"BA9 9DA",
    "wof:placetype":"postalcode"
},
  "geometry": {"coordinates":[-2.4166983582851,51.05710413755636],"type":"Point"}
}