{
  "type": "Feature",
  "properties": {
    "date:inception_lower": "2022-02-01",
    "date:inception_upper": "2022-02-01",
    "iso:country": "GB",
    "wof:name": "IV30 4FL",
    "wof:placetype": "postalcode"
  },
  "geometry": {"coordinates":[-3.314594,57.665163],"type":"Point"}
}
