{
  "type": "Feature",
  "properties": {
    "date:inception_lower": "1980-01-01",
    "date:inception_upper": "1980-01-01",
    "iso:country": "GB",
    "wof:name": "S64 0DX",
    "wof:placetype": "postalcode"
  },
  "geometry": {"coordinates":[-1.276124,53.499114],"type":"Point"}
}
