{
  "type": "Feature",
  "properties": {
    "iso:country":"GB",
    "wof:name":"B28 9AU",
    "wof:placetype":"postalcode"
},
  "geometry": {"coordinates":[-1.84299939022083,52.43381164471606],"type":"Point"}
}