{
  "type": "Feature",
  "properties": {
    "iso:country":"GB",
    "wof:name":"CV9 3LP",
    "wof:placetype":"postalcode"
},
  "geometry": {"coordinates":[-1.51757846244727,52.57557700827083],"type":"Point"}
}