{
  "type": "Feature",
  "properties": {
    "date:inception_lower":"1988-03-01",
    "date:inception_upper":"1988-03-31",
    "iso:country":"GB",
    "wof:name":"WV14 9SF",
    "wof:placetype":"postalcode"
},
  "geometry": {"coordinates":[-2.103169,52.547665],"type":"Point"}
}