{
  "type": "Feature",
  "properties": {
    "iso:country":"GB",
    "wof:name":"WV14 9SF",
    "wof:placetype":"postalcode"
},
  "geometry": {"coordinates":[-2.10316894641586,52.54766500092402],"type":"Point"}
}