{
  "type": "Feature",
  "properties": {
    "iso:country": "GB",
    "wof:name": "WV14 9SF",
    "wof:placetype": "postalcode"
  },
  "geometry": {"coordinates":[-2.103169,52.547665],"type":"Point"}
}
