{
  "type": "Feature",
  "properties": {
    "iso:country":"GB",
    "wof:name":"DY12 2TL",
    "wof:placetype":"postalcode"
},
  "geometry": {"coordinates":[-2.31236671485408,52.36899823133976],"type":"Point"}
}