{
  "type": "Feature",
  "properties": {
    "iso:country": "GB",
    "wof:name": "YO61 4QQ",
    "wof:placetype": "postalcode"
  },
  "geometry": {"coordinates":[-1.197454,54.17264],"type":"Point"}
}
