{
  "type": "Feature",
  "properties": {
    "iso:country":"GB",
    "wof:name":"YO61 4QQ",
    "wof:placetype":"postalcode"
},
  "geometry": {"coordinates":[-1.19023528130735,54.17701668912169],"type":"Point"}
}