{
  "type": "Feature",
  "properties": {
    "iso:country":"GB",
    "wof:name":"LE9 8AD",
    "wof:placetype":"postalcode"
},
  "geometry": {"coordinates":[-1.33758462670832,52.57241491021983],"type":"Point"}
}