{
  "type": "Feature",
  "properties": {
    "date:inception_lower": "1980-01-01",
    "date:inception_upper": "1980-01-01",
    "iso:country": "GB",
    "wof:name": "PH10 6HJ",
    "wof:placetype": "postalcode"
  },
  "geometry": {"coordinates":[-3.344132,56.594913],"type":"Point"}
}
