{
  "type": "Feature",
  "properties": {
    "iso:country":"GB",
    "wof:name":"PH10 6HJ",
    "wof:placetype":"postalcode"
},
  "geometry": {"coordinates":[-3.34413165285516,56.59491292062844],"type":"Point"}
}