{
  "type": "Feature",
  "properties": {
    "iso:country": "GB",
    "wof:name": "CO12 4BZ",
    "wof:placetype": "postalcode"
  },
  "geometry": {"coordinates":[1.253701,51.944116],"type":"Point"}
}
