{
  "type": "Feature",
  "properties": {
    "iso:country":"GB",
    "wof:name":"CO12 4BZ",
    "wof:placetype":"postalcode"
},
  "geometry": {"coordinates":[1.25370114792012,51.9441161972987],"type":"Point"}
}