{
  "type": "Feature",
  "properties": {
    "date:inception_lower":"1998-06-01",
    "date:inception_upper":"1998-06-30",
    "iso:country":"GB",
    "wof:name":"CO12 4BZ",
    "wof:placetype":"postalcode"
},
  "geometry": {"coordinates":[1.253701,51.944116],"type":"Point"}
}