{
  "type": "Feature",
  "properties": {
    "iso:country":"GB",
    "wof:name":"N4 1JE",
    "wof:placetype":"postalcode"
},
  "geometry": {"coordinates":[-0.09330323983542,51.58042019129966],"type":"Point"}
}