{
  "type": "Feature",
  "properties": {
    "iso:country":"GB",
    "wof:name":"B95 5DX",
    "wof:placetype":"postalcode"
},
  "geometry": {"coordinates":[-1.7527147209046,52.29733981934072],"type":"Point"}
}