{
  "type": "Feature",
  "properties": {
    "date:inception_lower": "1980-01-01",
    "date:inception_upper": "1980-01-01",
    "iso:country": "GB",
    "wof:name": "B95 5DX",
    "wof:placetype": "postalcode"
  },
  "geometry": {"coordinates":[-1.752715,52.29734],"type":"Point"}
}
