{
  "type": "Feature",
  "properties": {
    "iso:country": "GB",
    "wof:name": "B95 5DX",
    "wof:placetype": "postalcode"
  },
  "geometry": {"coordinates":[-1.752715,52.29734],"type":"Point"}
}
