{
  "type": "Feature",
  "properties": {
    "iso:country":"GB",
    "wof:name":"PR2 3NQ",
    "wof:placetype":"postalcode"
},
  "geometry": {"coordinates":[-2.72441226764263,53.79354916431743],"type":"Point"}
}