{
  "type": "Feature",
  "properties": {
    "iso:country":"GB",
    "wof:name":"KA22 8NG",
    "wof:placetype":"postalcode"
},
  "geometry": {"coordinates":[-4.81549373261697,55.65040925720493],"type":"Point"}
}