{
  "type": "Feature",
  "properties": {
    "iso:country": "GB",
    "wof:name": "KY5 0AL",
    "wof:placetype": "postalcode"
  },
  "geometry": {"coordinates":[-3.257704,56.130071],"type":"Point"}
}
