{
  "type": "Feature",
  "properties": {
    "iso:country":"GB",
    "wof:name":"WN5 8HU",
    "wof:placetype":"postalcode"
},
  "geometry": {"coordinates":[-2.69037689952774,53.53618883758949],"type":"Point"}
}