{
  "type": "Feature",
  "properties": {
    "iso:country": "GB",
    "wof:name": "WN5 8HU",
    "wof:placetype": "postalcode"
  },
  "geometry": {"coordinates":[-2.690377,53.536189],"type":"Point"}
}
