{
  "type": "Feature",
  "properties": {
    "iso:country":"GB",
    "wof:name":"EH51 9QY",
    "wof:placetype":"postalcode"
},
  "geometry": {"coordinates":[-3.5968788593561,56.0126331647663],"type":"Point"}
}