{
  "type": "Feature",
  "properties": {
    "iso:country":"GB",
    "wof:name":"LU7 1JA",
    "wof:placetype":"postalcode"
},
  "geometry": {"coordinates":[-0.65917833464166,51.91835920675399],"type":"Point"}
}