{
  "type": "Feature",
  "properties": {
    "iso:country":"GB",
    "wof:name":"YO32 9WN",
    "wof:placetype":"postalcode"
},
  "geometry": {"coordinates":[-1.04859987779451,53.99093840052354],"type":"Point"}
}