{
  "type": "Feature",
  "properties": {
    "date:inception_lower":"2004-01-01",
    "date:inception_upper":"2004-01-31",
    "iso:country":"GB",
    "wof:name":"YO32 9WN",
    "wof:placetype":"postalcode"
},
  "geometry": {"coordinates":[-1.048084,53.990538],"type":"Point"}
}