{
  "type": "Feature",
  "properties": {
    "iso:country":"GB",
    "wof:name":"EN7 5NW",
    "wof:placetype":"postalcode"
},
  "geometry": {"coordinates":[-0.09419595280183,51.71488869484503],"type":"Point"}
}