{
  "type": "Feature",
  "properties": {
    "date:inception_lower": "1980-01-01",
    "date:inception_upper": "1980-01-01",
    "iso:country": "GB",
    "wof:name": "EN7 5NW",
    "wof:placetype": "postalcode"
  },
  "geometry": {"coordinates":[-0.094196,51.714889],"type":"Point"}
}
