{
  "type": "Feature",
  "properties": {
    "iso:country": "GB",
    "wof:name": "IV30 1NX",
    "wof:placetype": "postalcode"
  },
  "geometry": {"coordinates":[-3.320917,57.645341],"type":"Point"}
}
