{
  "type": "Feature",
  "properties": {
    "iso:country":"GB",
    "wof:name":"CW12 2HQ",
    "wof:placetype":"postalcode"
},
  "geometry": {"coordinates":[-2.21108384056725,53.17399235103804],"type":"Point"}
}