{
  "type": "Feature",
  "properties": {
    "date:inception_lower": "2005-02-01",
    "date:inception_upper": "2005-02-01",
    "iso:country": "GB",
    "wof:name": "LE1 9SH",
    "wof:placetype": "postalcode"
  },
  "geometry": {"coordinates":[-1.13299,52.633575],"type":"Point"}
}
