{
  "type": "Feature",
  "properties": {
    "iso:country": "GB",
    "wof:name": "DN39 6US",
    "wof:placetype": "postalcode"
  },
  "geometry": {"coordinates":[-0.32515,53.618535],"type":"Point"}
}
