{
  "type": "Feature",
  "properties": {
    "iso:country": "GB",
    "wof:name": "TF7 5SU",
    "wof:placetype": "postalcode"
  },
  "geometry": {"coordinates":[-2.460007,52.63177],"type":"Point"}
}
