{
  "type": "Feature",
  "properties": {
    "iso:country":"GB",
    "wof:name":"TF7 5SU",
    "wof:placetype":"postalcode"
},
  "geometry": {"coordinates":[-2.46000717774125,52.63176971657882],"type":"Point"}
}