{
  "type": "Feature",
  "properties": {
    "iso:country":"GB",
    "wof:name":"TR3 7EZ",
    "wof:placetype":"postalcode"
},
  "geometry": {"coordinates":[-5.14387742077028,50.19756663668994],"type":"Point"}
}