{
  "type": "Feature",
  "properties": {
    "iso:country": "GB",
    "wof:name": "BS10 6ES",
    "wof:placetype": "postalcode"
  },
  "geometry": {"coordinates":[-2.600553,51.505953],"type":"Point"}
}
