{
  "type": "Feature",
  "properties": {
    "iso:country":"GB",
    "wof:name":"BS10 6ES",
    "wof:placetype":"postalcode"
},
  "geometry": {"coordinates":[-2.6005527356156,51.50595309689174],"type":"Point"}
}