{
  "type": "Feature",
  "properties": {
    "iso:country":"GB",
    "wof:name":"L6 2BG",
    "wof:placetype":"postalcode"
},
  "geometry": {"coordinates":[-2.9570731776774,53.41740674089243],"type":"Point"}
}