{
  "type": "Feature",
  "properties": {
    "date:inception_lower": "1980-01-01",
    "date:inception_upper": "1980-01-01",
    "iso:country": "GB",
    "wof:name": "L6 2BG",
    "wof:placetype": "postalcode"
  },
  "geometry": {"coordinates":[-2.957073,53.417407],"type":"Point"}
}
