{
  "type": "Feature",
  "properties": {
    "date:inception_lower":"1998-12-01",
    "date:inception_upper":"1998-12-31",
    "iso:country":"GB",
    "wof:name":"B73 6RQ",
    "wof:placetype":"postalcode"
},
  "geometry": {"coordinates":[-1.861871,52.551594],"type":"Point"}
}