{
  "type": "Feature",
  "properties": {
    "iso:country":"GB",
    "wof:name":"B73 6RQ",
    "wof:placetype":"postalcode"
},
  "geometry": {"coordinates":[-1.86187055055731,52.55159443956626],"type":"Point"}
}