{
  "type": "Feature",
  "properties": {
    "iso:country": "GB",
    "wof:name": "IP12 2UN",
    "wof:placetype": "postalcode"
  },
  "geometry": {"coordinates":[1.420796,52.130617],"type":"Point"}
}
