{
  "type": "Feature",
  "properties": {
    "iso:country":"GB",
    "wof:name":"TR3 6HY",
    "wof:placetype":"postalcode"
},
  "geometry": {"coordinates":[-5.08827532787106,50.22305134937906],"type":"Point"}
}