{
  "type": "Feature",
  "properties": {
    "iso:country":"GB",
    "wof:name":"RG6 6JL",
    "wof:placetype":"postalcode"
},
  "geometry": {"coordinates":[-0.94389479383305,51.44449960206514],"type":"Point"}
}