{
  "type": "Feature",
  "properties": {
    "iso:country": "GB",
    "wof:name": "DN6 9DL",
    "wof:placetype": "postalcode"
  },
  "geometry": {"coordinates":[-1.184661,53.63116],"type":"Point"}
}
