{
  "type": "Feature",
  "properties": {
    "iso:country":"GB",
    "wof:name":"DN6 9DL",
    "wof:placetype":"postalcode"
},
  "geometry": {"coordinates":[-1.18466067457348,53.63116040925946],"type":"Point"}
}