{
  "type": "Feature",
  "properties": {
    "date:inception_lower": "2017-03-01",
    "date:inception_upper": "2017-03-01",
    "iso:country": "GB",
    "wof:name": "IP1 2JY",
    "wof:placetype": "postalcode"
  },
  "geometry": {"coordinates":[1.138601,52.05989],"type":"Point"}
}
