{
  "type": "Feature",
  "properties": {
    "iso:country":"GB",
    "wof:name":"CF14 4PE",
    "wof:placetype":"postalcode"
},
  "geometry": {"coordinates":[-3.19831563261443,51.51527840083168],"type":"Point"}
}