{
  "type": "Feature",
  "properties": {
    "date:inception_lower":"1980-01-01",
    "date:inception_upper":"1980-01-31",
    "iso:country":"GB",
    "wof:name":"SY5 8JB",
    "wof:placetype":"postalcode"
},
  "geometry": {"coordinates":[-2.876714,52.668695],"type":"Point"}
}