{
  "type": "Feature",
  "properties": {
    "iso:country":"GB",
    "wof:name":"EH4 6QG",
    "wof:placetype":"postalcode"
},
  "geometry": {"coordinates":[-3.29552165932586,55.97517555426941],"type":"Point"}
}