{
  "type": "Feature",
  "properties": {
    "iso:country": "GB",
    "wof:name": "EH4 6QG",
    "wof:placetype": "postalcode"
  },
  "geometry": {"coordinates":[-3.296432,55.97463],"type":"Point"}
}
