{
  "type": "Feature",
  "properties": {
    "iso:country":"GB",
    "wof:name":"SP6 1PX",
    "wof:placetype":"postalcode"
},
  "geometry": {"coordinates":[-1.83820181504325,50.93048683087994],"type":"Point"}
}