{
  "type": "Feature",
  "properties": {
    "iso:country":"GB",
    "wof:name":"WN4 8BQ",
    "wof:placetype":"postalcode"
},
  "geometry": {"coordinates":[-2.63810659925177,53.4957521994377],"type":"Point"}
}