{
  "type": "Feature",
  "properties": {
    "iso:country":"GB",
    "wof:name":"SA37 0HB",
    "wof:placetype":"postalcode"
},
  "geometry": {"coordinates":[-4.55305183140077,52.03268045405362],"type":"Point"}
}