{
  "type": "Feature",
  "properties": {
    "iso:country": "GB",
    "wof:name": "SA37 0HB",
    "wof:placetype": "postalcode"
  },
  "geometry": {"coordinates":[-4.552944,52.032444],"type":"Point"}
}
