{
  "type": "Feature",
  "properties": {
    "iso:country":"GB",
    "wof:name":"B43 7EA",
    "wof:placetype":"postalcode"
},
  "geometry": {"coordinates":[-1.89846055394763,52.55796923442907],"type":"Point"}
}