{
  "type": "Feature",
  "properties": {
    "iso:country":"GB",
    "wof:name":"E11 1QL",
    "wof:placetype":"postalcode"
},
  "geometry": {"coordinates":[0.02349213410187,51.58203439499484],"type":"Point"}
}