{
  "type": "Feature",
  "properties": {
    "date:inception_lower": "2005-09-01",
    "date:inception_upper": "2005-09-01",
    "iso:country": "GB",
    "wof:name": "SK6 3BJ",
    "wof:placetype": "postalcode"
  },
  "geometry": {"coordinates":[-2.094982,53.413359],"type":"Point"}
}
