{
  "type": "Feature",
  "properties": {
    "iso:country":"GB",
    "wof:name":"SK6 3BJ",
    "wof:placetype":"postalcode"
},
  "geometry": {"coordinates":[-2.0949818403194,53.41335859561859],"type":"Point"}
}