{
  "type": "Feature",
  "properties": {
    "iso:country":"GB",
    "wof:name":"TS4 3BD",
    "wof:placetype":"postalcode"
},
  "geometry": {"coordinates":[-1.22969687611087,54.55325273622145],"type":"Point"}
}