{
  "type": "Feature",
  "properties": {
    "date:inception_lower": "2010-03-01",
    "date:inception_upper": "2010-03-01",
    "iso:country": "GB",
    "wof:name": "TS4 3BD",
    "wof:placetype": "postalcode"
  },
  "geometry": {"coordinates":[-1.229697,54.553253],"type":"Point"}
}
