{
  "type": "Feature",
  "properties": {
    "iso:country":"GB",
    "wof:name":"M12 4UP",
    "wof:placetype":"postalcode"
},
  "geometry": {"coordinates":[-2.20764400223168,53.46456699747851],"type":"Point"}
}