{
  "type": "Feature",
  "properties": {
    "iso:country": "GB",
    "wof:name": "M12 4UP",
    "wof:placetype": "postalcode"
  },
  "geometry": {"coordinates":[-2.207688,53.464646],"type":"Point"}
}
