{
  "type": "Feature",
  "properties": {
    "date:inception_lower": "2024-01-01",
    "date:inception_upper": "2024-01-01",
    "iso:country": "GB",
    "wof:name": "B69 9HQ",
    "wof:placetype": "postalcode"
  },
  "geometry": {"coordinates":[-2.009055,52.504007],"type":"Point"}
}
