{
  "type": "Feature",
  "properties": {
    "iso:country":"GB",
    "wof:name":"WA4 4ST",
    "wof:placetype":"postalcode"
},
  "geometry": {"coordinates":[-2.53231568493658,53.35104101448063],"type":"Point"}
}