{
  "type": "Feature",
  "properties": {
    "date:inception_lower":"1983-03-01",
    "date:inception_upper":"1983-03-31",
    "iso:country":"GB",
    "wof:name":"WA4 4ST",
    "wof:placetype":"postalcode"
},
  "geometry": {"coordinates":[-2.532316,53.351041],"type":"Point"}
}