{
  "type": "Feature",
  "properties": {
    "iso:country":"GB",
    "wof:name":"CF38 2AX",
    "wof:placetype":"postalcode"
},
  "geometry": {"coordinates":[-3.32375516819326,51.56097539029479],"type":"Point"}
}