{
  "type": "Feature",
  "properties": {
    "date:inception_lower":"2000-06-01",
    "date:inception_upper":"2000-06-30",
    "iso:country":"GB",
    "wof:name":"CF38 2AX",
    "wof:placetype":"postalcode"
},
  "geometry": {"coordinates":[-3.323755,51.560975],"type":"Point"}
}