{
  "type": "Feature",
  "properties": {
    "iso:country":"GB",
    "wof:name":"CV47 9PT",
    "wof:placetype":"postalcode"
},
  "geometry": {"coordinates":[-1.40564581820596,52.28398501299529],"type":"Point"}
}