{
  "type": "Feature",
  "properties": {
    "iso:country":"GB",
    "wof:name":"W1T 4SP",
    "wof:placetype":"postalcode"
},
  "geometry": {"coordinates":[-0.13679371306069,51.51927760359364],"type":"Point"}
}