{
  "type": "Feature",
  "properties": {
    "iso:country":"GB",
    "wof:name":"S65 3SP",
    "wof:placetype":"postalcode"
},
  "geometry": {"coordinates":[-1.33260885647143,53.44350605114589],"type":"Point"}
}