{
  "type": "Feature",
  "properties": {
    "iso:country":"GB",
    "wof:name":"DN1 1NJ",
    "wof:placetype":"postalcode"
},
  "geometry": {"coordinates":[-1.13330396345695,53.52412311033346],"type":"Point"}
}