{
  "type": "Feature",
  "properties": {
    "iso:country": "GB",
    "wof:name": "DN1 1NJ",
    "wof:placetype": "postalcode"
  },
  "geometry": {"coordinates":[-1.133304,53.524123],"type":"Point"}
}
