{
  "type": "Feature",
  "properties": {
    "iso:country":"GB",
    "wof:name":"ST5 5AJ",
    "wof:placetype":"postalcode"
},
  "geometry": {"coordinates":[-2.30147589713131,53.00960353419926],"type":"Point"}
}