{
  "type": "Feature",
  "properties": {
    "date:inception_lower": "1987-04-01",
    "date:inception_upper": "1987-04-01",
    "iso:country": "GB",
    "wof:name": "CM4 0BS",
    "wof:placetype": "postalcode"
  },
  "geometry": {"coordinates":[0.385325,51.669394],"type":"Point"}
}
