{
  "type": "Feature",
  "properties": {
    "iso:country": "GB",
    "wof:name": "KA10 9AY",
    "wof:placetype": "postalcode"
  },
  "geometry": {"coordinates":[-4.661812,55.54424],"type":"Point"}
}
