{
  "type": "Feature",
  "properties": {
    "iso:country":"GB",
    "wof:name":"M27 0EY",
    "wof:placetype":"postalcode"
},
  "geometry": {"coordinates":[-2.3586473980158,53.50570867268329],"type":"Point"}
}