{
  "type": "Feature",
  "properties": {
    "iso:country": "GB",
    "wof:name": "G3 7YW",
    "wof:placetype": "postalcode"
  },
  "geometry": {"coordinates":[-4.273724,55.868041],"type":"Point"}
}
