{
  "type": "Feature",
  "properties": {
    "date:inception_lower": "1980-01-01",
    "date:inception_upper": "1980-01-01",
    "iso:country": "GB",
    "wof:name": "G3 7YW",
    "wof:placetype": "postalcode"
  },
  "geometry": {"coordinates":[-4.273551,55.868057],"type":"Point"}
}
