{
  "type": "Feature",
  "properties": {
    "iso:country":"GB",
    "wof:name":"G3 7YW",
    "wof:placetype":"postalcode"
},
  "geometry": {"coordinates":[-4.27386740082846,55.86802973898808],"type":"Point"}
}