{
  "type": "Feature",
  "properties": {
    "date:inception_lower": "2021-06-01",
    "date:inception_upper": "2021-06-01",
    "iso:country": "GB",
    "wof:name": "WV15 6JJ",
    "wof:placetype": "postalcode"
  },
  "geometry": {"coordinates":[-2.344148,52.457917],"type":"Point"}
}
