{
  "type": "Feature",
  "properties": {
    "iso:country":"GB",
    "wof:name":"B32 1JY",
    "wof:placetype":"postalcode"
},
  "geometry": {"coordinates":[-1.99194982872676,52.46003122390591],"type":"Point"}
}