{
  "type": "Feature",
  "properties": {
    "iso:country":"GB",
    "wof:name":"CM19 4RJ",
    "wof:placetype":"postalcode"
},
  "geometry": {"coordinates":[0.08646980673146,51.74540581840549],"type":"Point"}
}