{
  "type": "Feature",
  "properties": {
    "date:inception_lower": "1980-01-01",
    "date:inception_upper": "1980-01-01",
    "iso:country": "GB",
    "wof:name": "CM19 4RJ",
    "wof:placetype": "postalcode"
  },
  "geometry": {"coordinates":[0.08647,51.745406],"type":"Point"}
}
