{
  "type": "Feature",
  "properties": {
    "iso:country": "GB",
    "wof:name": "CM19 4RJ",
    "wof:placetype": "postalcode"
  },
  "geometry": {"coordinates":[0.08647,51.745406],"type":"Point"}
}
