{
  "type": "Feature",
  "properties": {
    "iso:country":"GB",
    "wof:name":"NW8 9PS",
    "wof:placetype":"postalcode"
},
  "geometry": {"coordinates":[-0.17815630615635,51.53132976644559],"type":"Point"}
}