{
  "type": "Feature",
  "properties": {
    "iso:country":"GB",
    "wof:name":"TF12 5ET",
    "wof:placetype":"postalcode"
},
  "geometry": {"coordinates":[-2.4814982421489,52.61232020184325],"type":"Point"}
}