{
  "type": "Feature",
  "properties": {
    "iso:country":"GB",
    "wof:name":"TS19 7JY",
    "wof:placetype":"postalcode"
},
  "geometry": {"coordinates":[-1.36088083457957,54.57237693852347],"type":"Point"}
}