{
  "type": "Feature",
  "properties": {
    "iso:country":"GB",
    "wof:name":"DL1 2DT",
    "wof:placetype":"postalcode"
},
  "geometry": {"coordinates":[-1.51858131584218,54.54083463785897],"type":"Point"}
}