{
  "type": "Feature",
  "properties": {
    "date:inception_lower": "2005-05-01",
    "date:inception_upper": "2005-05-01",
    "iso:country": "GB",
    "wof:name": "DT10 1QX",
    "wof:placetype": "postalcode"
  },
  "geometry": {"coordinates":[-2.30381,50.928845],"type":"Point"}
}
