{
  "type": "Feature",
  "properties": {
    "iso:country":"GB",
    "wof:name":"DT10 1QX",
    "wof:placetype":"postalcode"
},
  "geometry": {"coordinates":[-2.30380971908378,50.92884481698162],"type":"Point"}
}