{
  "type": "Feature",
  "properties": {
    "iso:country":"GB",
    "wof:name":"SG2 9JX",
    "wof:placetype":"postalcode"
},
  "geometry": {"coordinates":[-0.16638825837974,51.89433241395439],"type":"Point"}
}