{
  "type": "Feature",
  "properties": {
    "iso:country": "GB",
    "wof:name": "SE2 9DE",
    "wof:placetype": "postalcode"
  },
  "geometry": {"coordinates":[0.107851,51.495073],"type":"Point"}
}
