{
  "type": "Feature",
  "properties": {
    "iso:country": "GB",
    "wof:name": "YO25 3YL",
    "wof:placetype": "postalcode"
  },
  "geometry": {"coordinates":[-0.396011,54.142049],"type":"Point"}
}
