{
  "type": "Feature",
  "properties": {
    "iso:country":"GB",
    "wof:name":"YO25 3YL",
    "wof:placetype":"postalcode"
},
  "geometry": {"coordinates":[-0.39601117667945,54.14204869911535],"type":"Point"}
}