{
  "type": "Feature",
  "properties": {
    "iso:country":"GB",
    "wof:name":"S10 3DX",
    "wof:placetype":"postalcode"
},
  "geometry": {"coordinates":[-1.52130315819549,53.36924776026262],"type":"Point"}
}