{
  "type": "Feature",
  "properties": {
    "date:inception_lower": "2022-12-01",
    "date:inception_upper": "2022-12-01",
    "iso:country": "GB",
    "wof:name": "WR11 3FS",
    "wof:placetype": "postalcode"
  },
  "geometry": {"coordinates":[-1.933366,52.096611],"type":"Point"}
}
