{
  "type": "Feature",
  "properties": {
    "iso:country": "GB",
    "wof:name": "HG1 3DA",
    "wof:placetype": "postalcode"
  },
  "geometry": {"coordinates":[-1.545501,54.012071],"type":"Point"}
}
