{
  "type": "Feature",
  "properties": {
    "date:inception_lower": "1999-06-01",
    "date:inception_upper": "1999-06-01",
    "iso:country": "GB",
    "wof:name": "CH43 0UR",
    "wof:placetype": "postalcode"
  },
  "geometry": {"coordinates":[-3.056988,53.369111],"type":"Point"}
}
