{
  "type": "Feature",
  "properties": {
    "iso:country": "GB",
    "wof:name": "SN10 5SW",
    "wof:placetype": "postalcode"
  },
  "geometry": {"coordinates":[-2.049203,51.310475],"type":"Point"}
}
