{
  "type": "Feature",
  "properties": {
    "iso:country":"GB",
    "wof:name":"SN10 5SW",
    "wof:placetype":"postalcode"
},
  "geometry": {"coordinates":[-2.04920287122988,51.31047525260266],"type":"Point"}
}