{
  "type": "Feature",
  "properties": {
    "iso:country":"GB",
    "wof:name":"BS34 6DS",
    "wof:placetype":"postalcode"
},
  "geometry": {"coordinates":[-2.56212839383234,51.53305526380309],"type":"Point"}
}