{
  "type": "Feature",
  "properties": {
    "date:inception_lower": "1980-01-01",
    "date:inception_upper": "1980-01-01",
    "iso:country": "GB",
    "wof:name": "WA4 4QW",
    "wof:placetype": "postalcode"
  },
  "geometry": {"coordinates":[-2.568152,53.316601],"type":"Point"}
}
