{
  "type": "Feature",
  "properties": {
    "iso:country":"GB",
    "wof:name":"SK17 9PP",
    "wof:placetype":"postalcode"
},
  "geometry": {"coordinates":[-1.89596292105561,53.23213074767692],"type":"Point"}
}