{
  "type": "Feature",
  "properties": {
    "iso:country":"GB",
    "wof:name":"NR35 1RX",
    "wof:placetype":"postalcode"
},
  "geometry": {"coordinates":[1.44813687794278,52.44965868949902],"type":"Point"}
}