{
  "type": "Feature",
  "properties": {
    "date:inception_lower": "2018-02-01",
    "date:inception_upper": "2018-02-01",
    "iso:country": "GB",
    "wof:name": "B64 5RJ",
    "wof:placetype": "postalcode"
  },
  "geometry": {"coordinates":[-2.065073,52.488788],"type":"Point"}
}
