{
  "type": "Feature",
  "properties": {
    "iso:country":"GB",
    "wof:name":"CM3 6TE",
    "wof:placetype":"postalcode"
},
  "geometry": {"coordinates":[0.76305014689287,51.69156325415545],"type":"Point"}
}