{
  "type": "Feature",
  "properties": {
    "iso:country":"GB",
    "wof:name":"BS15 3GW",
    "wof:placetype":"postalcode"
},
  "geometry": {"coordinates":[-2.50529570138896,51.44432445355335],"type":"Point"}
}