{
  "type": "Feature",
  "properties": {
    "iso:country": "GB",
    "wof:name": "PO15 5HX",
    "wof:placetype": "postalcode"
  },
  "geometry": {"coordinates":[-1.211229,50.857309],"type":"Point"}
}
