{
  "type": "Feature",
  "properties": {
    "iso:country":"GB",
    "wof:name":"PO15 5HX",
    "wof:placetype":"postalcode"
},
  "geometry": {"coordinates":[-1.21122867100182,50.85730872612532],"type":"Point"}
}