{
  "type": "Feature",
  "properties": {
    "date:inception_lower": "1980-01-01",
    "date:inception_upper": "1980-01-01",
    "iso:country": "GB",
    "wof:name": "PO15 5HX",
    "wof:placetype": "postalcode"
  },
  "geometry": {"coordinates":[-1.211229,50.857309],"type":"Point"}
}
