{
  "type": "Feature",
  "properties": {
    "iso:country":"GB",
    "wof:name":"TS3 0JW",
    "wof:placetype":"postalcode"
},
  "geometry": {"coordinates":[-1.18616251804721,54.55455854964855],"type":"Point"}
}