{
  "type": "Feature",
  "properties": {
    "iso:country":"GB",
    "wof:name":"FY4 5RE",
    "wof:placetype":"postalcode"
},
  "geometry": {"coordinates":[-3.01691723992837,53.78928555009571],"type":"Point"}
}