{
  "type": "Feature",
  "properties": {
    "date:inception_lower":"1981-07-01",
    "date:inception_upper":"1981-07-31",
    "iso:country":"GB",
    "wof:name":"PA2 0SG",
    "wof:placetype":"postalcode"
},
  "geometry": {"coordinates":[-4.446826,55.829065],"type":"Point"}
}