{
  "type": "Feature",
  "properties": {
    "date:inception_lower": "1980-01-01",
    "date:inception_upper": "1980-01-01",
    "iso:country": "GB",
    "wof:name": "CV6 1HG",
    "wof:placetype": "postalcode"
  },
  "geometry": {"coordinates":[-1.523725,52.420722],"type":"Point"}
}
