{
  "type": "Feature",
  "properties": {
    "iso:country":"GB",
    "wof:name":"CV6 1HG",
    "wof:placetype":"postalcode"
},
  "geometry": {"coordinates":[-1.52372492131658,52.42072198204876],"type":"Point"}
}