{
  "type": "Feature",
  "properties": {
    "iso:country": "GB",
    "wof:name": "NE17 7RG",
    "wof:placetype": "postalcode"
  },
  "geometry": {"coordinates":[-1.821143,54.896576],"type":"Point"}
}
