{
  "type": "Feature",
  "properties": {
    "iso:country":"GB",
    "wof:name":"NE17 7RG",
    "wof:placetype":"postalcode"
},
  "geometry": {"coordinates":[-1.82114276195233,54.89657591571104],"type":"Point"}
}