{
  "type": "Feature",
  "properties": {
    "iso:country":"GB",
    "wof:name":"DD9 7UY",
    "wof:placetype":"postalcode"
},
  "geometry": {"coordinates":[-2.61636713809132,56.82955729943333],"type":"Point"}
}