{
  "type": "Feature",
  "properties": {
    "iso:country": "GB",
    "wof:name": "DD9 7UY",
    "wof:placetype": "postalcode"
  },
  "geometry": {"coordinates":[-2.616367,56.829557],"type":"Point"}
}
