{
  "type": "Feature",
  "properties": {
    "iso:country":"GB",
    "wof:name":"HR9 5ND",
    "wof:placetype":"postalcode"
},
  "geometry": {"coordinates":[-2.57481401896278,51.91181209803876],"type":"Point"}
}