{
  "type": "Feature",
  "properties": {
    "date:inception_lower":"1980-01-01",
    "date:inception_upper":"1980-01-31",
    "iso:country":"GB",
    "wof:name":"LS28 7SF",
    "wof:placetype":"postalcode"
},
  "geometry": {"coordinates":[-1.670379,53.7925],"type":"Point"}
}