{
  "type": "Feature",
  "properties": {
    "iso:country":"GB",
    "wof:name":"NG34 9AH",
    "wof:placetype":"postalcode"
},
  "geometry": {"coordinates":[-0.39880145035504,53.03849601289354],"type":"Point"}
}