{
  "type": "Feature",
  "properties": {
    "iso:country":"GB",
    "wof:name":"LE8 4AQ",
    "wof:placetype":"postalcode"
},
  "geometry": {"coordinates":[-1.16130396481417,52.56536450825756],"type":"Point"}
}