{
  "type": "Feature",
  "properties": {
    "date:inception_lower": "1980-01-01",
    "date:inception_upper": "1980-01-01",
    "iso:country": "GB",
    "wof:name": "BN22 0UF",
    "wof:placetype": "postalcode"
  },
  "geometry": {"coordinates":[0.269639,50.807917],"type":"Point"}
}
