{
  "type": "Feature",
  "properties": {
    "iso:country":"GB",
    "wof:name":"BN22 0UF",
    "wof:placetype":"postalcode"
},
  "geometry": {"coordinates":[0.26963937828852,50.8079171369335],"type":"Point"}
}