{
  "type": "Feature",
  "properties": {
    "iso:country":"GB",
    "wof:name":"WA4 2GU",
    "wof:placetype":"postalcode"
},
  "geometry": {"coordinates":[-2.56758988138928,53.3782311230899],"type":"Point"}
}