{
  "type": "Feature",
  "properties": {
    "date:inception_lower": "2005-01-01",
    "date:inception_upper": "2005-01-01",
    "iso:country": "GB",
    "wof:name": "NE48 4BF",
    "wof:placetype": "postalcode"
  },
  "geometry": {"coordinates":[-2.149362,55.069995],"type":"Point"}
}
