{
  "type": "Feature",
  "properties": {
    "iso:country":"GB",
    "wof:name":"NE48 4BF",
    "wof:placetype":"postalcode"
},
  "geometry": {"coordinates":[-2.14936175282695,55.06999458467455],"type":"Point"}
}