{
  "type": "Feature",
  "properties": {
    "iso:country":"GB",
    "wof:name":"PR2 8DD",
    "wof:placetype":"postalcode"
},
  "geometry": {"coordinates":[-2.68594020428948,53.78303461835937],"type":"Point"}
}