{
  "type": "Feature",
  "properties": {
    "iso:country":"GB",
    "wof:name":"SW2 1EB",
    "wof:placetype":"postalcode"
},
  "geometry": {"coordinates":[-0.11378499706203,51.45969377687994],"type":"Point"}
}