{
  "type": "Feature",
  "properties": {
    "iso:country":"GB",
    "wof:name":"CF11 6NW",
    "wof:placetype":"postalcode"
},
  "geometry": {"coordinates":[-3.19002161492877,51.46964798973659],"type":"Point"}
}