{
  "type": "Feature",
  "properties": {
    "iso:country":"GB",
    "wof:name":"G32 7PQ",
    "wof:placetype":"postalcode"
},
  "geometry": {"coordinates":[-4.16775774518728,55.8514763495771],"type":"Point"}
}