{
  "type": "Feature",
  "properties": {
    "iso:country":"GB",
    "wof:name":"TQ13 9YF",
    "wof:placetype":"postalcode"
},
  "geometry": {"coordinates":[-3.67572851341345,50.5810027422123],"type":"Point"}
}