{
  "type": "Feature",
  "properties": {
    "date:inception_lower": "2013-07-01",
    "date:inception_upper": "2013-07-01",
    "iso:country": "GB",
    "wof:name": "ME4 4RP",
    "wof:placetype": "postalcode"
  },
  "geometry": {"coordinates":[0.522687,51.381909],"type":"Point"}
}
