{
  "type": "Feature",
  "properties": {
    "iso:country":"GB",
    "wof:name":"ME4 4RP",
    "wof:placetype":"postalcode"
},
  "geometry": {"coordinates":[0.52268651044304,51.38190869331353],"type":"Point"}
}