{
  "type": "Feature",
  "properties": {
    "iso:country":"GB",
    "wof:name":"MK40 2HU",
    "wof:placetype":"postalcode"
},
  "geometry": {"coordinates":[-0.48094561799663,52.13924411269716],"type":"Point"}
}