{
  "type": "Feature",
  "properties": {
    "iso:country": "GB",
    "wof:name": "B16 8WP",
    "wof:placetype": "postalcode"
  },
  "geometry": {"coordinates":[-1.913926,52.475963],"type":"Point"}
}
