{
  "type": "Feature",
  "properties": {
    "iso:country":"GB",
    "wof:name":"HR6 9SH",
    "wof:placetype":"postalcode"
},
  "geometry": {"coordinates":[-2.81433954290648,52.25010616973881],"type":"Point"}
}