{
  "type": "Feature",
  "properties": {
    "iso:country": "GB",
    "wof:name": "CH45 8PN",
    "wof:placetype": "postalcode"
  },
  "geometry": {"coordinates":[-3.066122,53.421283],"type":"Point"}
}
