{
  "type": "Feature",
  "properties": {
    "date:inception_lower":"1999-06-01",
    "date:inception_upper":"1999-06-30",
    "iso:country":"GB",
    "wof:name":"CH45 8PN",
    "wof:placetype":"postalcode"
},
  "geometry": {"coordinates":[-3.066122,53.421283],"type":"Point"}
}