{
  "type": "Feature",
  "properties": {
    "iso:country":"GB",
    "wof:name":"CH45 8PN",
    "wof:placetype":"postalcode"
},
  "geometry": {"coordinates":[-3.06612237813852,53.4212828979374],"type":"Point"}
}