{
  "type": "Feature",
  "properties": {
    "date:inception_lower": "1980-01-01",
    "date:inception_upper": "1980-01-01",
    "iso:country": "GB",
    "wof:name": "IP19 8NN",
    "wof:placetype": "postalcode"
  },
  "geometry": {"coordinates":[1.541219,52.352999],"type":"Point"}
}
