{
  "type": "Feature",
  "properties": {
    "iso:country":"GB",
    "wof:name":"IP19 8NN",
    "wof:placetype":"postalcode"
},
  "geometry": {"coordinates":[1.54118850115244,52.35297700288854],"type":"Point"}
}