{
  "type": "Feature",
  "properties": {
    "iso:country":"GB",
    "wof:name":"HA5 5JZ",
    "wof:placetype":"postalcode"
},
  "geometry": {"coordinates":[-0.37606941288411,51.58508715701817],"type":"Point"}
}