{
  "type": "Feature",
  "properties": {
    "iso:country":"GB",
    "wof:name":"NG20 8EH",
    "wof:placetype":"postalcode"
},
  "geometry": {"coordinates":[-1.23909009900733,53.20343797718211],"type":"Point"}
}