{
  "type": "Feature",
  "properties": {
    "date:inception_lower": "1980-01-01",
    "date:inception_upper": "1980-01-01",
    "iso:country": "GB",
    "wof:name": "NG20 8EH",
    "wof:placetype": "postalcode"
  },
  "geometry": {"coordinates":[-1.23909,53.203438],"type":"Point"}
}
