{
  "type": "Feature",
  "properties": {
    "iso:country": "GB",
    "wof:name": "NG20 8EH",
    "wof:placetype": "postalcode"
  },
  "geometry": {"coordinates":[-1.23909,53.203438],"type":"Point"}
}
