{
  "type": "Feature",
  "properties": {
    "iso:country": "GB",
    "wof:name": "SY12 9EZ",
    "wof:placetype": "postalcode"
  },
  "geometry": {"coordinates":[-2.924665,52.914534],"type":"Point"}
}
