{
  "type": "Feature",
  "properties": {
    "iso:country":"GB",
    "wof:name":"LE2 0UQ",
    "wof:placetype":"postalcode"
},
  "geometry": {"coordinates":[-1.11492132771375,52.6341874740903],"type":"Point"}
}