{
  "type": "Feature",
  "properties": {
    "iso:country":"GB",
    "wof:name":"SL1 8EE",
    "wof:placetype":"postalcode"
},
  "geometry": {"coordinates":[-0.65337349946218,51.54128957568545],"type":"Point"}
}