{
  "type": "Feature",
  "properties": {
    "iso:country": "GB",
    "wof:name": "SL1 8EE",
    "wof:placetype": "postalcode"
  },
  "geometry": {"coordinates":[-0.653373,51.54129],"type":"Point"}
}
