{
  "type": "Feature",
  "properties": {
    "iso:country": "GB",
    "wof:name": "PE3 9XG",
    "wof:placetype": "postalcode"
  },
  "geometry": {"coordinates":[-0.282963,52.584908],"type":"Point"}
}
