{
  "type": "Feature",
  "properties": {
    "iso:country":"GB",
    "wof:name":"PE3 9XG",
    "wof:placetype":"postalcode"
},
  "geometry": {"coordinates":[-0.2829634447553,52.58490807147424],"type":"Point"}
}