{
  "type": "Feature",
  "properties": {
    "iso:country":"GB",
    "wof:name":"M12 4DT",
    "wof:placetype":"postalcode"
},
  "geometry": {"coordinates":[-2.20746892515328,53.46264376773854],"type":"Point"}
}