{
  "type": "Feature",
  "properties": {
    "iso:country": "GB",
    "wof:name": "SK22 3EG",
    "wof:placetype": "postalcode"
  },
  "geometry": {"coordinates":[-2.001163,53.362764],"type":"Point"}
}
