{
  "type": "Feature",
  "properties": {
    "date:inception_lower": "2006-03-01",
    "date:inception_upper": "2006-03-01",
    "iso:country": "GB",
    "wof:name": "SK22 3EG",
    "wof:placetype": "postalcode"
  },
  "geometry": {"coordinates":[-2.001147,53.36278],"type":"Point"}
}
