{
  "type": "Feature",
  "properties": {
    "iso:country":"GB",
    "wof:name":"SK22 3EG",
    "wof:placetype":"postalcode"
},
  "geometry": {"coordinates":[-2.001162861642,53.36276392266308],"type":"Point"}
}