{
  "type": "Feature",
  "properties": {
    "iso:country":"GB",
    "wof:name":"SN10 5LR",
    "wof:placetype":"postalcode"
},
  "geometry": {"coordinates":[-2.00428504287201,51.32846909624715],"type":"Point"}
}