{
  "type": "Feature",
  "properties": {
    "date:inception_lower":"1980-01-01",
    "date:inception_upper":"1980-01-31",
    "iso:country":"GB",
    "wof:name":"SN10 5LR",
    "wof:placetype":"postalcode"
},
  "geometry": {"coordinates":[-2.004285,51.328469],"type":"Point"}
}