{
  "type": "Feature",
  "properties": {
    "iso:country":"GB",
    "wof:name":"M26 3UN",
    "wof:placetype":"postalcode"
},
  "geometry": {"coordinates":[-2.35403149895626,53.57050182621386],"type":"Point"}
}