{
  "type": "Feature",
  "properties": {
    "date:inception_lower":"1980-01-01",
    "date:inception_upper":"1980-01-31",
    "iso:country":"GB",
    "wof:name":"UB7 7XA",
    "wof:placetype":"postalcode"
},
  "geometry": {"coordinates":[-0.472857,51.512561],"type":"Point"}
}