{
  "type": "Feature",
  "properties": {
    "iso:country": "GB",
    "wof:name": "WS5 4SN",
    "wof:placetype": "postalcode"
  },
  "geometry": {"coordinates":[-1.963688,52.555733],"type":"Point"}
}
