{
  "type": "Feature",
  "properties": {
    "iso:country":"GB",
    "wof:name":"NP19 7PP",
    "wof:placetype":"postalcode"
},
  "geometry": {"coordinates":[-2.96301781656577,51.59719371435612],"type":"Point"}
}