{
  "type": "Feature",
  "properties": {
    "date:inception_lower": "1980-01-01",
    "date:inception_upper": "1980-01-01",
    "iso:country": "GB",
    "wof:name": "E9 6NX",
    "wof:placetype": "postalcode"
  },
  "geometry": {"coordinates":[-0.054305,51.545258],"type":"Point"}
}
