{
  "type": "Feature",
  "properties": {
    "iso:country":"GB",
    "wof:name":"WA10 2BH",
    "wof:placetype":"postalcode"
},
  "geometry": {"coordinates":[-2.7422934488721,53.45840472942205],"type":"Point"}
}