{
  "type": "Feature",
  "properties": {
    "iso:country": "GB",
    "wof:name": "TF4 2DJ",
    "wof:placetype": "postalcode"
  },
  "geometry": {"coordinates":[-2.459353,52.665187],"type":"Point"}
}
