{
  "type": "Feature",
  "properties": {
    "iso:country": "GB",
    "wof:name": "BB9 5DQ",
    "wof:placetype": "postalcode"
  },
  "geometry": {"coordinates":[-2.229252,53.825557],"type":"Point"}
}
