{
  "type": "Feature",
  "properties": {
    "iso:country": "GB",
    "wof:name": "N7 0HY",
    "wof:placetype": "postalcode"
  },
  "geometry": {"coordinates":[-0.1288,51.551478],"type":"Point"}
}
