{
  "type": "Feature",
  "properties": {
    "iso:country":"GB",
    "wof:name":"N7 0HY",
    "wof:placetype":"postalcode"
},
  "geometry": {"coordinates":[-0.12879992888942,51.55147835036345],"type":"Point"}
}