{
  "type": "Feature",
  "properties": {
    "iso:country":"GB",
    "wof:name":"EC1M 6PR",
    "wof:placetype":"postalcode"
},
  "geometry": {"coordinates":[-0.1037287656281,51.51926027890367],"type":"Point"}
}