{
  "type": "Feature",
  "properties": {
    "date:inception_lower": "1980-01-01",
    "date:inception_upper": "1980-01-01",
    "iso:country": "GB",
    "wof:name": "GU18 5RJ",
    "wof:placetype": "postalcode"
  },
  "geometry": {"coordinates":[-0.676115,51.35365],"type":"Point"}
}
