{
  "type": "Feature",
  "properties": {
    "iso:country":"GB",
    "wof:name":"GU18 5RJ",
    "wof:placetype":"postalcode"
},
  "geometry": {"coordinates":[-0.67611476596155,51.35364989467458],"type":"Point"}
}