{
  "type": "Feature",
  "properties": {
    "iso:country":"GB",
    "wof:name":"EH32 0LY",
    "wof:placetype":"postalcode"
},
  "geometry": {"coordinates":[-2.89543484782782,55.97617997470772],"type":"Point"}
}