{
  "type": "Feature",
  "properties": {
    "date:inception_lower": "1985-07-01",
    "date:inception_upper": "1985-07-01",
    "iso:country": "GB",
    "wof:name": "EH32 0LY",
    "wof:placetype": "postalcode"
  },
  "geometry": {"coordinates":[-2.895435,55.97618],"type":"Point"}
}
