{
  "type": "Feature",
  "properties": {
    "iso:country":"GB",
    "wof:name":"NN12 6DS",
    "wof:placetype":"postalcode"
},
  "geometry": {"coordinates":[-0.99068384973982,52.12563777618561],"type":"Point"}
}