{
  "type": "Feature",
  "properties": {
    "iso:country": "GB",
    "wof:name": "NN12 6DS",
    "wof:placetype": "postalcode"
  },
  "geometry": {"coordinates":[-0.990684,52.125638],"type":"Point"}
}
