{
  "type": "Feature",
  "properties": {
    "iso:country": "GB",
    "wof:name": "EX1 3TA",
    "wof:placetype": "postalcode"
  },
  "geometry": {"coordinates":[-3.465501,50.740772],"type":"Point"}
}
