{
  "type": "Feature",
  "properties": {
    "iso:country": "GB",
    "wof:name": "NP12 0AP",
    "wof:placetype": "postalcode"
  },
  "geometry": {"coordinates":[-3.192543,51.6935],"type":"Point"}
}
