{
  "type": "Feature",
  "properties": {
    "iso:country":"GB",
    "wof:name":"GU34 1SD",
    "wof:placetype":"postalcode"
},
  "geometry": {"coordinates":[-0.9888152385706,51.13376016465384],"type":"Point"}
}