{
  "type": "Feature",
  "properties": {
    "iso:country":"GB",
    "wof:name":"TS3 8JP",
    "wof:placetype":"postalcode"
},
  "geometry": {"coordinates":[-1.19838618683525,54.56436416687912],"type":"Point"}
}