{
  "type": "Feature",
  "properties": {
    "iso:country": "GB",
    "wof:name": "TS3 8JP",
    "wof:placetype": "postalcode"
  },
  "geometry": {"coordinates":[-1.198386,54.564364],"type":"Point"}
}
