{
  "type": "Feature",
  "properties": {
    "iso:country":"GB",
    "wof:name":"DE4 4AF",
    "wof:placetype":"postalcode"
},
  "geometry": {"coordinates":[-1.55780407664788,53.07288049486917],"type":"Point"}
}