{
  "type": "Feature",
  "properties": {
    "iso:country":"GB",
    "wof:name":"SW8 3RX",
    "wof:placetype":"postalcode"
},
  "geometry": {"coordinates":[-0.15023218964762,51.46684807090824],"type":"Point"}
}