{
  "type": "Feature",
  "properties": {
    "iso:country":"GB",
    "wof:name":"NE32 4LH",
    "wof:placetype":"postalcode"
},
  "geometry": {"coordinates":[-1.47468806311862,54.95609616223265],"type":"Point"}
}