{
  "type": "Feature",
  "properties": {
    "iso:country":"GB",
    "wof:name":"RM1 4AX",
    "wof:placetype":"postalcode"
},
  "geometry": {"coordinates":[0.1813876635907,51.58201106081378],"type":"Point"}
}