{
  "type": "Feature",
  "properties": {
    "iso:country":"GB",
    "wof:name":"TS3 0LY",
    "wof:placetype":"postalcode"
},
  "geometry": {"coordinates":[-1.18863088247511,54.5501624484187],"type":"Point"}
}