{
  "type": "Feature",
  "properties": {
    "date:inception_lower": "2023-06-01",
    "date:inception_upper": "2023-06-01",
    "iso:country": "GB",
    "wof:name": "CT10 2RY",
    "wof:placetype": "postalcode"
  },
  "geometry": {"coordinates":[1.420091,51.360824],"type":"Point"}
}
