{
  "type": "Feature",
  "properties": {
    "iso:country":"GB",
    "wof:name":"B45 8QS",
    "wof:placetype":"postalcode"
},
  "geometry": {"coordinates":[-2.00135160556776,52.38719413171147],"type":"Point"}
}