{
  "type": "Feature",
  "properties": {
    "iso:country":"GB",
    "wof:name":"BN6 8EH",
    "wof:placetype":"postalcode"
},
  "geometry": {"coordinates":[-0.14399293593446,50.93131895370964],"type":"Point"}
}