{
  "type": "Feature",
  "properties": {
    "iso:country": "GB",
    "wof:name": "BN6 8EH",
    "wof:placetype": "postalcode"
  },
  "geometry": {"coordinates":[-0.143993,50.931319],"type":"Point"}
}
