{
  "type": "Feature",
  "properties": {
    "date:inception_lower": "1980-01-01",
    "date:inception_upper": "1980-01-01",
    "iso:country": "GB",
    "wof:name": "DE55 2BG",
    "wof:placetype": "postalcode"
  },
  "geometry": {"coordinates":[-1.347061,53.101917],"type":"Point"}
}
