{
  "type": "Feature",
  "properties": {
    "iso:country":"GB",
    "wof:name":"DE55 2BG",
    "wof:placetype":"postalcode"
},
  "geometry": {"coordinates":[-1.34706151514482,53.1019172090589],"type":"Point"}
}