{
  "type": "Feature",
  "properties": {
    "iso:country":"GB",
    "wof:name":"SA1 2ES",
    "wof:placetype":"postalcode"
},
  "geometry": {"coordinates":[-3.93927164866501,51.63211491286935],"type":"Point"}
}