{
  "type": "Feature",
  "properties": {
    "iso:country":"GB",
    "wof:name":"FY1 2HU",
    "wof:placetype":"postalcode"
},
  "geometry": {"coordinates":[-3.05234884994804,53.82516704856692],"type":"Point"}
}