{
  "type": "Feature",
  "properties": {
    "iso:country":"GB",
    "wof:name":"PE22 9PW",
    "wof:placetype":"postalcode"
},
  "geometry": {"coordinates":[0.08673589859857,53.04710676432824],"type":"Point"}
}