{
  "type": "Feature",
  "properties": {
    "iso:country": "GB",
    "wof:name": "PE22 9PW",
    "wof:placetype": "postalcode"
  },
  "geometry": {"coordinates":[0.086887,53.047005],"type":"Point"}
}
