{
  "type": "Feature",
  "properties": {
    "iso:country":"GB",
    "wof:name":"W1H 7DJ",
    "wof:placetype":"postalcode"
},
  "geometry": {"coordinates":[-0.15939129375854,51.51471549875662],"type":"Point"}
}