{
  "type": "Feature",
  "properties": {
    "date:inception_lower": "1980-01-01",
    "date:inception_upper": "1980-01-01",
    "iso:country": "GB",
    "wof:name": "SE15 4HH",
    "wof:placetype": "postalcode"
  },
  "geometry": {"coordinates":[-0.06755,51.463105],"type":"Point"}
}
