{
  "type": "Feature",
  "properties": {
    "iso:country": "GB",
    "wof:name": "NG9 7ES",
    "wof:placetype": "postalcode"
  },
  "geometry": {"coordinates":[-1.271326,52.921943],"type":"Point"}
}
