{
  "type": "Feature",
  "properties": {
    "iso:country":"GB",
    "wof:name":"NG9 7ES",
    "wof:placetype":"postalcode"
},
  "geometry": {"coordinates":[-1.27132639746373,52.9219426394142],"type":"Point"}
}