{
  "type": "Feature",
  "properties": {
    "iso:country": "GB",
    "wof:name": "NR11 6UU",
    "wof:placetype": "postalcode"
  },
  "geometry": {"coordinates":[1.249812,52.786611],"type":"Point"}
}
