{
  "type": "Feature",
  "properties": {
    "date:inception_lower":"1996-06-01",
    "date:inception_upper":"1996-06-30",
    "iso:country":"GB",
    "wof:name":"NR11 6UU",
    "wof:placetype":"postalcode"
},
  "geometry": {"coordinates":[1.249812,52.786611],"type":"Point"}
}