{
  "type": "Feature",
  "properties": {
    "iso:country":"GB",
    "wof:name":"NR11 6UU",
    "wof:placetype":"postalcode"
},
  "geometry": {"coordinates":[1.24981222152267,52.78661085773743],"type":"Point"}
}