{
  "type": "Feature",
  "properties": {
    "iso:country":"GB",
    "wof:name":"GL56 0NR",
    "wof:placetype":"postalcode"
},
  "geometry": {"coordinates":[-1.67536294453487,51.95962117728889],"type":"Point"}
}