{
  "type": "Feature",
  "properties": {
    "iso:country":"GB",
    "wof:name":"LD1 5TN",
    "wof:placetype":"postalcode"
},
  "geometry": {"coordinates":[-3.2047132594535,52.30441574499032],"type":"Point"}
}