{
  "type": "Feature",
  "properties": {
    "iso:country": "GB",
    "wof:name": "AL2 3XX",
    "wof:placetype": "postalcode"
  },
  "geometry": {"coordinates":[-0.36658,51.69224],"type":"Point"}
}
