{
  "type": "Feature",
  "properties": {
    "iso:country":"GB",
    "wof:name":"AL2 3XX",
    "wof:placetype":"postalcode"
},
  "geometry": {"coordinates":[-0.36658019629941,51.69224005520679],"type":"Point"}
}