{
  "type": "Feature",
  "properties": {
    "iso:country": "GB",
    "wof:name": "HP27 0BP",
    "wof:placetype": "postalcode"
  },
  "geometry": {"coordinates":[-0.827554,51.721132],"type":"Point"}
}
