{
  "type": "Feature",
  "properties": {
    "iso:country":"GB",
    "wof:name":"HP27 0BP",
    "wof:placetype":"postalcode"
},
  "geometry": {"coordinates":[-0.82755440693001,51.72113165755935],"type":"Point"}
}