{
  "type": "Feature",
  "properties": {
    "date:inception_lower":"1992-08-01",
    "date:inception_upper":"1992-08-31",
    "iso:country":"GB",
    "wof:name":"PE30 4JQ",
    "wof:placetype":"postalcode"
},
  "geometry": {"coordinates":[0.410074,52.733291],"type":"Point"}
}