{
  "type": "Feature",
  "properties": {
    "iso:country":"GB",
    "wof:name":"PE30 4JQ",
    "wof:placetype":"postalcode"
},
  "geometry": {"coordinates":[0.41025840542549,52.7334269357909],"type":"Point"}
}