{
  "type": "Feature",
  "properties": {
    "iso:country": "GB",
    "wof:name": "PE30 4JQ",
    "wof:placetype": "postalcode"
  },
  "geometry": {"coordinates":[0.411053,52.732786],"type":"Point"}
}
