{
  "type": "Feature",
  "properties": {
    "iso:country":"GB",
    "wof:name":"WF13 3AW",
    "wof:placetype":"postalcode"
},
  "geometry": {"coordinates":[-1.66680511835015,53.6801210929292],"type":"Point"}
}