{
  "type": "Feature",
  "properties": {
    "iso:country":"GB",
    "wof:name":"WV14 0RP",
    "wof:placetype":"postalcode"
},
  "geometry": {"coordinates":[-2.0828204546541,52.55653603185462],"type":"Point"}
}