{
  "type": "Feature",
  "properties": {
    "date:inception_lower":"1980-01-01",
    "date:inception_upper":"1980-01-31",
    "iso:country":"GB",
    "wof:name":"WV14 0RP",
    "wof:placetype":"postalcode"
},
  "geometry": {"coordinates":[-2.08282,52.556536],"type":"Point"}
}