{
  "type": "Feature",
  "properties": {
    "iso:country":"GB",
    "wof:name":"CR0 8TR",
    "wof:placetype":"postalcode"
},
  "geometry": {"coordinates":[-0.04817001958667,51.37633608630587],"type":"Point"}
}