{
  "type": "Feature",
  "properties": {
    "iso:country":"GB",
    "wof:name":"LL13 0RR",
    "wof:placetype":"postalcode"
},
  "geometry": {"coordinates":[-2.96178529756413,53.02453244661586],"type":"Point"}
}