{
  "type": "Feature",
  "properties": {
    "date:inception_lower":"1980-01-01",
    "date:inception_upper":"1980-01-31",
    "iso:country":"GB",
    "wof:name":"LL13 0RR",
    "wof:placetype":"postalcode"
},
  "geometry": {"coordinates":[-2.961785,53.024532],"type":"Point"}
}