{
  "type": "Feature",
  "properties": {
    "date:inception_lower": "1980-01-01",
    "date:inception_upper": "1980-01-01",
    "iso:country": "GB",
    "wof:name": "HR9 6JA",
    "wof:placetype": "postalcode"
  },
  "geometry": {"coordinates":[-2.623285,51.868948],"type":"Point"}
}
