{
  "type": "Feature",
  "properties": {
    "iso:country": "GB",
    "wof:name": "SM2 6HD",
    "wof:placetype": "postalcode"
  },
  "geometry": {"coordinates":[-0.204026,51.355249],"type":"Point"}
}
