{
  "type": "Feature",
  "properties": {
    "date:inception_lower": "1980-01-01",
    "date:inception_upper": "1980-01-01",
    "iso:country": "GB",
    "wof:name": "LA10 5HQ",
    "wof:placetype": "postalcode"
  },
  "geometry": {"coordinates":[-2.537142,54.317349],"type":"Point"}
}
