{
  "type": "Feature",
  "properties": {
    "iso:country":"GB",
    "wof:name":"LA10 5HQ",
    "wof:placetype":"postalcode"
},
  "geometry": {"coordinates":[-2.53717086699002,54.31740225186284],"type":"Point"}
}