{
  "type": "Feature",
  "properties": {
    "date:inception_lower":"2011-01-01",
    "date:inception_upper":"2011-01-31",
    "iso:country":"GB",
    "wof:name":"SA62 4EF",
    "wof:placetype":"postalcode"
},
  "geometry": {"coordinates":[-4.950203,51.822952],"type":"Point"}
}