{
  "type": "Feature",
  "properties": {
    "iso:country":"GB",
    "wof:name":"SA62 4EF",
    "wof:placetype":"postalcode"
},
  "geometry": {"coordinates":[-4.95015552257442,51.82292125352458],"type":"Point"}
}