{
  "type": "Feature",
  "properties": {
    "date:inception_lower": "1980-01-01",
    "date:inception_upper": "1980-01-01",
    "iso:country": "GB",
    "wof:name": "CA14 3NS",
    "wof:placetype": "postalcode"
  },
  "geometry": {"coordinates":[-3.551393,54.63101],"type":"Point"}
}
