{
  "type": "Feature",
  "properties": {
    "iso:country": "GB",
    "wof:name": "KA6 5EF",
    "wof:placetype": "postalcode"
  },
  "geometry": {"coordinates":[-4.523533,55.474793],"type":"Point"}
}
