{
  "type": "Feature",
  "properties": {
    "iso:country":"GB",
    "wof:name":"LE4 0LT",
    "wof:placetype":"postalcode"
},
  "geometry": {"coordinates":[-1.16239103492416,52.65850867623872],"type":"Point"}
}