{
  "type": "Feature",
  "properties": {
    "iso:country":"GB",
    "wof:name":"SE23 1HD",
    "wof:placetype":"postalcode"
},
  "geometry": {"coordinates":[-0.04776159892544,51.44500695551987],"type":"Point"}
}