{
  "type": "Feature",
  "properties": {
    "iso:country":"GB",
    "wof:name":"LN11 0JD",
    "wof:placetype":"postalcode"
},
  "geometry": {"coordinates":[-0.0056834423989,53.3744946024631],"type":"Point"}
}