{
  "type": "Feature",
  "properties": {
    "date:inception_lower": "2013-12-01",
    "date:inception_upper": "2013-12-01",
    "iso:country": "GB",
    "wof:name": "PR7 5FL",
    "wof:placetype": "postalcode"
  },
  "geometry": {"coordinates":[-2.716836,53.641295],"type":"Point"}
}
