{
  "type": "Feature",
  "properties": {
    "iso:country":"GB",
    "wof:name":"PR7 5FL",
    "wof:placetype":"postalcode"
},
  "geometry": {"coordinates":[-2.71686778228794,53.64123406297985],"type":"Point"}
}