{
  "type": "Feature",
  "properties": {
    "date:inception_lower":"2000-12-01",
    "date:inception_upper":"2000-12-31",
    "iso:country":"GB",
    "wof:name":"HP3 9QU",
    "wof:placetype":"postalcode"
},
  "geometry": {"coordinates":[-0.461718,51.733617],"type":"Point"}
}