{
  "type": "Feature",
  "properties": {
    "iso:country":"GB",
    "wof:name":"CO7 9JP",
    "wof:placetype":"postalcode"
},
  "geometry": {"coordinates":[0.96285986699984,51.85626967253275],"type":"Point"}
}