{
  "type": "Feature",
  "properties": {
    "iso:country": "GB",
    "wof:name": "CO7 9JP",
    "wof:placetype": "postalcode"
  },
  "geometry": {"coordinates":[0.96286,51.85627],"type":"Point"}
}
