{
  "type": "Feature",
  "properties": {
    "iso:country": "GB",
    "wof:name": "NG1 5GS",
    "wof:placetype": "postalcode"
  },
  "geometry": {"coordinates":[-1.154682,52.956436],"type":"Point"}
}
