{
  "type": "Feature",
  "properties": {
    "date:inception_lower":"1980-01-01",
    "date:inception_upper":"1980-01-31",
    "iso:country":"GB",
    "wof:name":"BD6 2LH",
    "wof:placetype":"postalcode"
},
  "geometry": {"coordinates":[-1.785062,53.759783],"type":"Point"}
}