{
  "type": "Feature",
  "properties": {
    "iso:country":"GB",
    "wof:name":"BD6 2LH",
    "wof:placetype":"postalcode"
},
  "geometry": {"coordinates":[-1.78506253902493,53.75978323420723],"type":"Point"}
}