{
  "type": "Feature",
  "properties": {
    "date:inception_lower": "1980-01-01",
    "date:inception_upper": "1980-01-01",
    "iso:country": "GB",
    "wof:name": "HU5 5XH",
    "wof:placetype": "postalcode"
  },
  "geometry": {"coordinates":[-0.404611,53.755285],"type":"Point"}
}
