{
  "type": "Feature",
  "properties": {
    "iso:country":"GB",
    "wof:name":"S71 1QE",
    "wof:placetype":"postalcode"
},
  "geometry": {"coordinates":[-1.47958825821964,53.56222855430066],"type":"Point"}
}