{
  "type": "Feature",
  "properties": {
    "iso:country":"GB",
    "wof:name":"NP44 4AD",
    "wof:placetype":"postalcode"
},
  "geometry": {"coordinates":[-3.04023809849812,51.64937832053704],"type":"Point"}
}