{
  "type": "Feature",
  "properties": {
    "date:inception_lower":"2011-05-01",
    "date:inception_upper":"2011-05-31",
    "iso:country":"GB",
    "wof:name":"NP44 4AD",
    "wof:placetype":"postalcode"
},
  "geometry": {"coordinates":[-3.040238,51.649378],"type":"Point"}
}