{
  "type": "Feature",
  "properties": {
    "iso:country":"GB",
    "wof:name":"HU9 3HH",
    "wof:placetype":"postalcode"
},
  "geometry": {"coordinates":[-0.29448069676424,53.76185902844172],"type":"Point"}
}