{
  "type": "Feature",
  "properties": {
    "date:inception_lower": "1980-01-01",
    "date:inception_upper": "1980-01-01",
    "iso:country": "GB",
    "wof:name": "HU9 3HH",
    "wof:placetype": "postalcode"
  },
  "geometry": {"coordinates":[-0.294481,53.761859],"type":"Point"}
}
