{
  "type": "Feature",
  "properties": {
    "iso:country": "GB",
    "wof:name": "HU9 3HH",
    "wof:placetype": "postalcode"
  },
  "geometry": {"coordinates":[-0.294481,53.761859],"type":"Point"}
}
