{
  "type": "Feature",
  "properties": {
    "iso:country": "GB",
    "wof:name": "CA5 6DL",
    "wof:placetype": "postalcode"
  },
  "geometry": {"coordinates":[-3.015426,54.91022],"type":"Point"}
}
