{
  "type": "Feature",
  "properties": {
    "iso:country":"GB",
    "wof:name":"TR1 1TE",
    "wof:placetype":"postalcode"
},
  "geometry": {"coordinates":[-5.0096887214039,50.27051655518201],"type":"Point"}
}