{
  "type": "Feature",
  "properties": {
    "iso:country": "GB",
    "wof:name": "HX1 4AN",
    "wof:placetype": "postalcode"
  },
  "geometry": {"coordinates":[-1.879542,53.728565],"type":"Point"}
}
