{
  "type": "Feature",
  "properties": {
    "iso:country":"GB",
    "wof:name":"GL7 5ES",
    "wof:placetype":"postalcode"
},
  "geometry": {"coordinates":[-1.86953740847181,51.77582631278758],"type":"Point"}
}