{
  "type": "Feature",
  "properties": {
    "date:inception_lower": "1980-01-01",
    "date:inception_upper": "1980-01-01",
    "iso:country": "GB",
    "wof:name": "GL7 5ES",
    "wof:placetype": "postalcode"
  },
  "geometry": {"coordinates":[-1.869537,51.775826],"type":"Point"}
}
