{
  "type": "Feature",
  "properties": {
    "date:inception_lower": "2005-02-01",
    "date:inception_upper": "2005-02-01",
    "iso:country": "GB",
    "wof:name": "CV37 1SR",
    "wof:placetype": "postalcode"
  },
  "geometry": {"coordinates":[-1.708975,52.190242],"type":"Point"}
}
