{
  "type": "Feature",
  "properties": {
    "iso:country": "GB",
    "wof:name": "ML11 8JP",
    "wof:placetype": "postalcode"
  },
  "geometry": {"coordinates":[-3.619287,55.698102],"type":"Point"}
}
