{
  "type": "Feature",
  "properties": {
    "date:inception_lower":"1980-01-01",
    "date:inception_upper":"1980-01-31",
    "iso:country":"GB",
    "wof:name":"ML11 8JP",
    "wof:placetype":"postalcode"
},
  "geometry": {"coordinates":[-3.619287,55.698102],"type":"Point"}
}