{
  "type": "Feature",
  "properties": {
    "iso:country":"GB",
    "wof:name":"ST5 9AT",
    "wof:placetype":"postalcode"
},
  "geometry": {"coordinates":[-2.24215829422594,53.02277352121735],"type":"Point"}
}