{
  "type": "Feature",
  "properties": {
    "iso:country": "GB",
    "wof:name": "ST5 9AT",
    "wof:placetype": "postalcode"
  },
  "geometry": {"coordinates":[-2.242158,53.022774],"type":"Point"}
}
