{
  "type": "Feature",
  "properties": {
    "date:inception_lower":"1980-01-01",
    "date:inception_upper":"1980-01-31",
    "iso:country":"GB",
    "wof:name":"ST5 9AT",
    "wof:placetype":"postalcode"
},
  "geometry": {"coordinates":[-2.242158,53.022774],"type":"Point"}
}