{
  "type": "Feature",
  "properties": {
    "iso:country":"GB",
    "wof:name":"M45 8PW",
    "wof:placetype":"postalcode"
},
  "geometry": {"coordinates":[-2.29372807173972,53.55626588960257],"type":"Point"}
}