{
  "type": "Feature",
  "properties": {
    "iso:country":"GB",
    "wof:name":"SS17 9EA",
    "wof:placetype":"postalcode"
},
  "geometry": {"coordinates":[0.46330002669604,51.53185128946042],"type":"Point"}
}