{
  "type": "Feature",
  "properties": {
    "iso:country": "GB",
    "wof:name": "B45 9QT",
    "wof:placetype": "postalcode"
  },
  "geometry": {"coordinates":[-2.018292,52.386267],"type":"Point"}
}
