{
  "type": "Feature",
  "properties": {
    "iso:country":"GB",
    "wof:name":"IV30 1UJ",
    "wof:placetype":"postalcode"
},
  "geometry": {"coordinates":[-3.29849098871067,57.64367746493244],"type":"Point"}
}