{
  "type": "Feature",
  "properties": {
    "iso:country":"GB",
    "wof:name":"DE12 7NA",
    "wof:placetype":"postalcode"
},
  "geometry": {"coordinates":[-1.51187173807946,52.70141085087997],"type":"Point"}
}