{
  "type": "Feature",
  "properties": {
    "iso:country": "GB",
    "wof:name": "OX9 3QH",
    "wof:placetype": "postalcode"
  },
  "geometry": {"coordinates":[-0.937838,51.749321],"type":"Point"}
}
