{
  "type": "Feature",
  "properties": {
    "iso:country":"GB",
    "wof:name":"OX9 3QH",
    "wof:placetype":"postalcode"
},
  "geometry": {"coordinates":[-0.93862092228137,51.749602104175],"type":"Point"}
}