{
  "type": "Feature",
  "properties": {
    "iso:country": "GB",
    "wof:name": "BL3 2QA",
    "wof:placetype": "postalcode"
  },
  "geometry": {"coordinates":[-2.397363,53.556946],"type":"Point"}
}
