{
  "type": "Feature",
  "properties": {
    "iso:country":"GB",
    "wof:name":"BL3 2QA",
    "wof:placetype":"postalcode"
},
  "geometry": {"coordinates":[-2.39736293918417,53.55694601122849],"type":"Point"}
}