{
  "type": "Feature",
  "properties": {
    "date:inception_lower":"1980-01-01",
    "date:inception_upper":"1980-01-31",
    "iso:country":"GB",
    "wof:name":"SK16 5HD",
    "wof:placetype":"postalcode"
},
  "geometry": {"coordinates":[-2.062511,53.471563],"type":"Point"}
}