{
  "type": "Feature",
  "properties": {
    "date:inception_lower": "2022-07-01",
    "date:inception_upper": "2022-07-01",
    "iso:country": "GB",
    "wof:name": "G69 9FX",
    "wof:placetype": "postalcode"
  },
  "geometry": {"coordinates":[-4.104903,55.907133],"type":"Point"}
}
