{
  "type": "Feature",
  "properties": {
    "iso:country":"GB",
    "wof:name":"S60 5SU",
    "wof:placetype":"postalcode"
},
  "geometry": {"coordinates":[-1.36358104882568,53.39187317409258],"type":"Point"}
}