{
  "type": "Feature",
  "properties": {
    "iso:country": "GB",
    "wof:name": "LS21 1TS",
    "wof:placetype": "postalcode"
  },
  "geometry": {"coordinates":[-1.621071,53.898961],"type":"Point"}
}
