{
  "type": "Feature",
  "properties": {
    "iso:country":"GB",
    "wof:name":"LS21 1TS",
    "wof:placetype":"postalcode"
},
  "geometry": {"coordinates":[-1.62107134244016,53.89896054088899],"type":"Point"}
}