{
  "type": "Feature",
  "properties": {
    "iso:country":"GB",
    "wof:name":"SA2 7PR",
    "wof:placetype":"postalcode"
},
  "geometry": {"coordinates":[-4.0263319347996,51.62529351850982],"type":"Point"}
}