{
  "type": "Feature",
  "properties": {
    "iso:country": "GB",
    "wof:name": "LN2 2FS",
    "wof:placetype": "postalcode"
  },
  "geometry": {"coordinates":[-0.493402,53.269408],"type":"Point"}
}
