{
  "type": "Feature",
  "properties": {
    "date:inception_lower": "2011-10-01",
    "date:inception_upper": "2011-10-01",
    "iso:country": "GB",
    "wof:name": "PE3 8AF",
    "wof:placetype": "postalcode"
  },
  "geometry": {"coordinates":[-0.27771,52.605574],"type":"Point"}
}
