{
  "type": "Feature",
  "properties": {
    "iso:country":"GB",
    "wof:name":"PE3 8AF",
    "wof:placetype":"postalcode"
},
  "geometry": {"coordinates":[-0.27771012942391,52.60557365629764],"type":"Point"}
}