{
  "type": "Feature",
  "properties": {
    "iso:country": "GB",
    "wof:name": "AB56 1PT",
    "wof:placetype": "postalcode"
  },
  "geometry": {"coordinates":[-2.967014,57.674853],"type":"Point"}
}
