{
  "type": "Feature",
  "properties": {
    "iso:country":"GB",
    "wof:name":"RG12 9UB",
    "wof:placetype":"postalcode"
},
  "geometry": {"coordinates":[-0.71843579622318,51.41336964474905],"type":"Point"}
}