{
  "type": "Feature",
  "properties": {
    "date:inception_lower": "1995-07-01",
    "date:inception_upper": "1995-07-01",
    "iso:country": "GB",
    "wof:name": "RG12 9UB",
    "wof:placetype": "postalcode"
  },
  "geometry": {"coordinates":[-0.718418,51.41337],"type":"Point"}
}
