{
  "type": "Feature",
  "properties": {
    "iso:country": "GB",
    "wof:name": "RG12 9UB",
    "wof:placetype": "postalcode"
  },
  "geometry": {"coordinates":[-0.718418,51.41337],"type":"Point"}
}
