{
  "type": "Feature",
  "properties": {
    "iso:country": "GB",
    "wof:name": "TA5 1BN",
    "wof:placetype": "postalcode"
  },
  "geometry": {"coordinates":[-3.091635,51.125218],"type":"Point"}
}
