{
  "type": "Feature",
  "properties": {
    "iso:country":"GB",
    "wof:name":"LN11 7HR",
    "wof:placetype":"postalcode"
},
  "geometry": {"coordinates":[0.0838127243699,53.45270010434567],"type":"Point"}
}