{
  "type": "Feature",
  "properties": {
    "iso:country": "GB",
    "wof:name": "LN11 7HR",
    "wof:placetype": "postalcode"
  },
  "geometry": {"coordinates":[0.083813,53.4527],"type":"Point"}
}
