{
  "type": "Feature",
  "properties": {
    "iso:country":"GB",
    "wof:name":"B45 0ER",
    "wof:placetype":"postalcode"
},
  "geometry": {"coordinates":[-2.01383204185749,52.40573984917937],"type":"Point"}
}