{
  "type": "Feature",
  "properties": {
    "date:inception_lower":"1980-01-01",
    "date:inception_upper":"1980-01-31",
    "iso:country":"GB",
    "wof:name":"S5 8DD",
    "wof:placetype":"postalcode"
},
  "geometry": {"coordinates":[-1.47561,53.422295],"type":"Point"}
}