{
  "type": "Feature",
  "properties": {
    "iso:country":"GB",
    "wof:name":"DE24 3AS",
    "wof:placetype":"postalcode"
},
  "geometry": {"coordinates":[-1.50429277979768,52.87259494091076],"type":"Point"}
}