{
  "type": "Feature",
  "properties": {
    "iso:country": "GB",
    "wof:name": "PL4 9PN",
    "wof:placetype": "postalcode"
  },
  "geometry": {"coordinates":[-4.122963,50.372038],"type":"Point"}
}
