{
  "type": "Feature",
  "properties": {
    "date:inception_lower":"1980-01-01",
    "date:inception_upper":"1980-01-31",
    "iso:country":"GB",
    "wof:name":"PL4 9PN",
    "wof:placetype":"postalcode"
},
  "geometry": {"coordinates":[-4.122963,50.372038],"type":"Point"}
}