{
  "type": "Feature",
  "properties": {
    "iso:country":"GB",
    "wof:name":"PL4 9PN",
    "wof:placetype":"postalcode"
},
  "geometry": {"coordinates":[-4.12296258046991,50.37203800429943],"type":"Point"}
}