{
  "type": "Feature",
  "properties": {
    "iso:country":"GB",
    "wof:name":"WA8 3YR",
    "wof:placetype":"postalcode"
},
  "geometry": {"coordinates":[-2.70122681266213,53.37727796970746],"type":"Point"}
}