{
  "type": "Feature",
  "properties": {
    "iso:country": "GB",
    "wof:name": "SL6 3RG",
    "wof:placetype": "postalcode"
  },
  "geometry": {"coordinates":[-0.792501,51.513913],"type":"Point"}
}
