{
  "type": "Feature",
  "properties": {
    "iso:country":"GB",
    "wof:name":"BD10 8QP",
    "wof:placetype":"postalcode"
},
  "geometry": {"coordinates":[-1.73704494430433,53.82953329161233],"type":"Point"}
}