{
  "type": "Feature",
  "properties": {
    "iso:country": "GB",
    "wof:name": "CV2 1AR",
    "wof:placetype": "postalcode"
  },
  "geometry": {"coordinates":[-1.453279,52.428814],"type":"Point"}
}
