{
  "type": "Feature",
  "properties": {
    "date:inception_lower": "2024-09-01",
    "date:inception_upper": "2024-09-01",
    "iso:country": "GB",
    "wof:name": "B1 1WJ",
    "wof:placetype": "postalcode"
  },
  "geometry": {"coordinates":[-1.902151,52.474615],"type":"Point"}
}
