{
  "type": "Feature",
  "properties": {
    "iso:country":"GB",
    "wof:name":"OL8 2JL",
    "wof:placetype":"postalcode"
},
  "geometry": {"coordinates":[-2.09270954873065,53.53028216340545],"type":"Point"}
}