{
  "type": "Feature",
  "properties": {
    "iso:country":"GB",
    "wof:name":"CA28 8AF",
    "wof:placetype":"postalcode"
},
  "geometry": {"coordinates":[-3.57695169972604,54.5400022016847],"type":"Point"}
}