{
  "type": "Feature",
  "properties": {
    "iso:country": "GB",
    "wof:name": "CW8 4UX",
    "wof:placetype": "postalcode"
  },
  "geometry": {"coordinates":[-2.555917,53.27378],"type":"Point"}
}
