{
  "type": "Feature",
  "properties": {
    "iso:country":"GB",
    "wof:name":"NE6 2QZ",
    "wof:placetype":"postalcode"
},
  "geometry": {"coordinates":[-1.57257094054634,54.97468561712482],"type":"Point"}
}