{
  "type": "Feature",
  "properties": {
    "iso:country":"GB",
    "wof:name":"S6 6SD",
    "wof:placetype":"postalcode"
},
  "geometry": {"coordinates":[-1.55864598040671,53.4045821620638],"type":"Point"}
}