{
  "type": "Feature",
  "properties": {
    "iso:country": "GB",
    "wof:name": "GU34 4AQ",
    "wof:placetype": "postalcode"
  },
  "geometry": {"coordinates":[-1.0155,51.143076],"type":"Point"}
}
