{
  "type": "Feature",
  "properties": {
    "date:inception_lower":"1980-01-01",
    "date:inception_upper":"1980-01-31",
    "iso:country":"GB",
    "wof:name":"GU34 4AQ",
    "wof:placetype":"postalcode"
},
  "geometry": {"coordinates":[-1.0155,51.143076],"type":"Point"}
}