{
  "type": "Feature",
  "properties": {
    "date:inception_lower": "1980-01-01",
    "date:inception_upper": "1980-01-01",
    "iso:country": "GB",
    "wof:name": "SG6 4LG",
    "wof:placetype": "postalcode"
  },
  "geometry": {"coordinates":[-0.252857,51.979541],"type":"Point"}
}
