{
  "type": "Feature",
  "properties": {
    "date:inception_lower": "1990-02-01",
    "date:inception_upper": "1990-02-01",
    "iso:country": "GB",
    "wof:name": "DN1 1PN",
    "wof:placetype": "postalcode"
  },
  "geometry": {"coordinates":[-1.138273,53.521707],"type":"Point"}
}
