{
  "type": "Feature",
  "properties": {
    "iso:country": "GB",
    "wof:name": "CH46 6FL",
    "wof:placetype": "postalcode"
  },
  "geometry": {"coordinates":[-3.12795,53.40235],"type":"Point"}
}
