{
  "type": "Feature",
  "properties": {
    "date:inception_lower": "1980-01-01",
    "date:inception_upper": "1980-01-01",
    "iso:country": "GB",
    "wof:name": "B71 1QE",
    "wof:placetype": "postalcode"
  },
  "geometry": {"coordinates":[-1.992291,52.528867],"type":"Point"}
}
