{
  "type": "Feature",
  "properties": {
    "iso:country":"GB",
    "wof:name":"B71 1QE",
    "wof:placetype":"postalcode"
},
  "geometry": {"coordinates":[-1.99229143178061,52.52886718388031],"type":"Point"}
}