{
  "type": "Feature",
  "properties": {
    "iso:country":"GB",
    "wof:name":"N1 2UN",
    "wof:placetype":"postalcode"
},
  "geometry": {"coordinates":[-0.10274684652057,51.54427059660195],"type":"Point"}
}