{
  "type": "Feature",
  "properties": {
    "date:inception_lower": "2015-08-01",
    "date:inception_upper": "2015-08-01",
    "iso:country": "GB",
    "wof:name": "DH8 1FP",
    "wof:placetype": "postalcode"
  },
  "geometry": {"coordinates":[-1.792582,54.850224],"type":"Point"}
}
