{
  "type": "Feature",
  "properties": {
    "iso:country": "GB",
    "wof:name": "OL4 4NR",
    "wof:placetype": "postalcode"
  },
  "geometry": {"coordinates":[-2.063369,53.54151],"type":"Point"}
}
