{
  "type": "Feature",
  "properties": {
    "iso:country":"GB",
    "wof:name":"BH23 2DB",
    "wof:placetype":"postalcode"
},
  "geometry": {"coordinates":[-1.79058703813226,50.74046259654988],"type":"Point"}
}