{
  "type": "Feature",
  "properties": {
    "date:inception_lower":"2000-06-01",
    "date:inception_upper":"2000-06-30",
    "iso:country":"GB",
    "wof:name":"PE28 5LN",
    "wof:placetype":"postalcode"
},
  "geometry": {"coordinates":[-0.386727,52.382967],"type":"Point"}
}