{
  "type": "Feature",
  "properties": {
    "iso:country": "GB",
    "wof:name": "PE28 5LN",
    "wof:placetype": "postalcode"
  },
  "geometry": {"coordinates":[-0.386727,52.382967],"type":"Point"}
}
