{
  "type": "Feature",
  "properties": {
    "iso:country":"GB",
    "wof:name":"CO7 6DR",
    "wof:placetype":"postalcode"
},
  "geometry": {"coordinates":[0.97218515196486,51.95621534502848],"type":"Point"}
}