{
  "type": "Feature",
  "properties": {
    "iso:country": "GB",
    "wof:name": "OX39 4JU",
    "wof:placetype": "postalcode"
  },
  "geometry": {"coordinates":[-0.917765,51.699707],"type":"Point"}
}
