{
  "type": "Feature",
  "properties": {
    "iso:country":"GB",
    "wof:name":"UB5 4BP",
    "wof:placetype":"postalcode"
},
  "geometry": {"coordinates":[-0.3653435897803,51.55574963583057],"type":"Point"}
}