{
  "type": "Feature",
  "properties": {
    "iso:country": "GB",
    "wof:name": "UB5 4BP",
    "wof:placetype": "postalcode"
  },
  "geometry": {"coordinates":[-0.365344,51.55575],"type":"Point"}
}
