{
  "type": "Feature",
  "properties": {
    "date:inception_lower":"1995-12-01",
    "date:inception_upper":"1995-12-31",
    "iso:country":"GB",
    "wof:name":"OX14 4YA",
    "wof:placetype":"postalcode"
},
  "geometry": {"coordinates":[-1.238046,51.639973],"type":"Point"}
}