{
  "type": "Feature",
  "properties": {
    "iso:country": "GB",
    "wof:name": "OX14 4YA",
    "wof:placetype": "postalcode"
  },
  "geometry": {"coordinates":[-1.238046,51.639973],"type":"Point"}
}
