{
  "type": "Feature",
  "properties": {
    "date:inception_lower": "2012-10-01",
    "date:inception_upper": "2012-10-01",
    "iso:country": "GB",
    "wof:name": "LN4 1BU",
    "wof:placetype": "postalcode"
  },
  "geometry": {"coordinates":[-0.488408,53.222598],"type":"Point"}
}
