{
  "type": "Feature",
  "properties": {
    "iso:country":"GB",
    "wof:name":"LN4 1BU",
    "wof:placetype":"postalcode"
},
  "geometry": {"coordinates":[-0.48838115621798,53.22251237017717],"type":"Point"}
}