{
  "type": "Feature",
  "properties": {
    "iso:country": "GB",
    "wof:name": "RH12 4JH",
    "wof:placetype": "postalcode"
  },
  "geometry": {"coordinates":[-0.299596,51.078315],"type":"Point"}
}
