{
  "type": "Feature",
  "properties": {
    "iso:country":"GB",
    "wof:name":"RH12 4JH",
    "wof:placetype":"postalcode"
},
  "geometry": {"coordinates":[-0.29960829547088,51.07836003407191],"type":"Point"}
}