{
  "type": "Feature",
  "properties": {
    "date:inception_lower": "1980-01-01",
    "date:inception_upper": "1980-01-01",
    "iso:country": "GB",
    "wof:name": "RH12 4JH",
    "wof:placetype": "postalcode"
  },
  "geometry": {"coordinates":[-0.299596,51.078315],"type":"Point"}
}
