{
  "type": "Feature",
  "properties": {
    "iso:country": "GB",
    "wof:name": "CM4 9PJ",
    "wof:placetype": "postalcode"
  },
  "geometry": {"coordinates":[0.433925,51.64845],"type":"Point"}
}
