{
  "type": "Feature",
  "properties": {
    "iso:country": "GB",
    "wof:name": "GL5 2NL",
    "wof:placetype": "postalcode"
  },
  "geometry": {"coordinates":[-2.208097,51.728304],"type":"Point"}
}
