{
  "type": "Feature",
  "properties": {
    "iso:country":"GB",
    "wof:name":"OL8 3SU",
    "wof:placetype":"postalcode"
},
  "geometry": {"coordinates":[-2.13395346968424,53.52046363335359],"type":"Point"}
}