{
  "type": "Feature",
  "properties": {
    "iso:country":"GB",
    "wof:name":"B60 3NR",
    "wof:placetype":"postalcode"
},
  "geometry": {"coordinates":[-2.0747374817802,52.32254015203687],"type":"Point"}
}