{
  "type": "Feature",
  "properties": {
    "iso:country":"GB",
    "wof:name":"B64 5NZ",
    "wof:placetype":"postalcode"
},
  "geometry": {"coordinates":[-2.06418035601793,52.47837145672002],"type":"Point"}
}