{
  "type": "Feature",
  "properties": {
    "date:inception_lower": "1991-09-01",
    "date:inception_upper": "1991-09-01",
    "iso:country": "GB",
    "wof:name": "B64 5NZ",
    "wof:placetype": "postalcode"
  },
  "geometry": {"coordinates":[-2.06418,52.478371],"type":"Point"}
}
