{
  "type": "Feature",
  "properties": {
    "date:inception_lower": "1980-01-01",
    "date:inception_upper": "1980-01-01",
    "iso:country": "GB",
    "wof:name": "M16 7GQ",
    "wof:placetype": "postalcode"
  },
  "geometry": {"coordinates":[-2.263454,53.457733],"type":"Point"}
}
