{
  "type": "Feature",
  "properties": {
    "iso:country":"GB",
    "wof:name":"W4 3LY",
    "wof:placetype":"postalcode"
},
  "geometry": {"coordinates":[-0.27431767612839,51.48795681351993],"type":"Point"}
}