{
  "type": "Feature",
  "properties": {
    "iso:country":"GB",
    "wof:name":"B49 6PH",
    "wof:placetype":"postalcode"
},
  "geometry": {"coordinates":[-1.86302936523941,52.21112213485162],"type":"Point"}
}