{
  "type": "Feature",
  "properties": {
    "date:inception_lower": "1987-04-01",
    "date:inception_upper": "1987-04-01",
    "iso:country": "GB",
    "wof:name": "CF35 5HX",
    "wof:placetype": "postalcode"
  },
  "geometry": {"coordinates":[-3.505711,51.517617],"type":"Point"}
}
