{
  "type": "Feature",
  "properties": {
    "iso:country":"GB",
    "wof:name":"CF35 5HX",
    "wof:placetype":"postalcode"
},
  "geometry": {"coordinates":[-3.50569779673747,51.51763337712534],"type":"Point"}
}