{
  "type": "Feature",
  "properties": {
    "date:inception_lower": "1980-01-01",
    "date:inception_upper": "1980-01-01",
    "iso:country": "GB",
    "wof:name": "GU14 9TA",
    "wof:placetype": "postalcode"
  },
  "geometry": {"coordinates":[-0.788796,51.297868],"type":"Point"}
}
