{
  "type": "Feature",
  "properties": {
    "iso:country":"GB",
    "wof:name":"WA10 2EA",
    "wof:placetype":"postalcode"
},
  "geometry": {"coordinates":[-2.74579946594644,53.4530705710519],"type":"Point"}
}