{
  "type": "Feature",
  "properties": {
    "iso:country": "GB",
    "wof:name": "WA10 2EA",
    "wof:placetype": "postalcode"
  },
  "geometry": {"coordinates":[-2.745799,53.453071],"type":"Point"}
}
