{
  "type": "Feature",
  "properties": {
    "date:inception_lower":"1980-01-01",
    "date:inception_upper":"1980-01-31",
    "iso:country":"GB",
    "wof:name":"EX13 7JF",
    "wof:placetype":"postalcode"
},
  "geometry": {"coordinates":[-3.026528,50.802776],"type":"Point"}
}