{
  "type": "Feature",
  "properties": {
    "iso:country":"GB",
    "wof:name":"SY7 8QB",
    "wof:placetype":"postalcode"
},
  "geometry": {"coordinates":[-3.06029364614972,52.42283951832976],"type":"Point"}
}