{
  "type": "Feature",
  "properties": {
    "date:inception_lower":"1980-01-01",
    "date:inception_upper":"1980-01-31",
    "iso:country":"GB",
    "wof:name":"SY7 8QB",
    "wof:placetype":"postalcode"
},
  "geometry": {"coordinates":[-3.060294,52.42284],"type":"Point"}
}