{
  "type": "Feature",
  "properties": {
    "date:inception_lower": "2020-10-01",
    "date:inception_upper": "2020-10-01",
    "iso:country": "GB",
    "wof:name": "BN9 0FD",
    "wof:placetype": "postalcode"
  },
  "geometry": {"coordinates":[0.056351,50.793898],"type":"Point"}
}
