{
  "type": "Feature",
  "properties": {
    "iso:country":"GB",
    "wof:name":"SW6 2PH",
    "wof:placetype":"postalcode"
},
  "geometry": {"coordinates":[-0.18684774526246,51.47076524665498],"type":"Point"}
}