{
  "type": "Feature",
  "properties": {
    "iso:country":"GB",
    "wof:name":"WA15 7DT",
    "wof:placetype":"postalcode"
},
  "geometry": {"coordinates":[-2.30965975946485,53.39376785654967],"type":"Point"}
}