{
  "type": "Feature",
  "properties": {
    "iso:country":"GB",
    "wof:name":"S35 1PQ",
    "wof:placetype":"postalcode"
},
  "geometry": {"coordinates":[-1.4772894785448,53.4571070199212],"type":"Point"}
}