{
  "type": "Feature",
  "properties": {
    "iso:country": "GB",
    "wof:name": "S35 1PQ",
    "wof:placetype": "postalcode"
  },
  "geometry": {"coordinates":[-1.477274,53.457107],"type":"Point"}
}
