{
  "type": "Feature",
  "properties": {
    "iso:country": "GB",
    "wof:name": "TA3 5DZ",
    "wof:placetype": "postalcode"
  },
  "geometry": {"coordinates":[-3.039956,51.029416],"type":"Point"}
}
