{
  "type": "Feature",
  "properties": {
    "iso:country":"GB",
    "wof:name":"TA3 5DZ",
    "wof:placetype":"postalcode"
},
  "geometry": {"coordinates":[-3.03995594488096,51.02941591674593],"type":"Point"}
}