{
  "type": "Feature",
  "properties": {
    "date:inception_lower": "1997-06-01",
    "date:inception_upper": "1997-06-01",
    "iso:country": "GB",
    "wof:name": "CA12 4NG",
    "wof:placetype": "postalcode"
  },
  "geometry": {"coordinates":[-3.114706,54.605836],"type":"Point"}
}
