{
  "type": "Feature",
  "properties": {
    "iso:country":"GB",
    "wof:name":"CA12 4NG",
    "wof:placetype":"postalcode"
},
  "geometry": {"coordinates":[-3.11471848070145,54.60581972131278],"type":"Point"}
}