{
  "type": "Feature",
  "properties": {
    "iso:country": "GB",
    "wof:name": "PO12 4QJ",
    "wof:placetype": "postalcode"
  },
  "geometry": {"coordinates":[-1.140259,50.805648],"type":"Point"}
}
