{
  "type": "Feature",
  "properties": {
    "date:inception_lower":"1999-12-01",
    "date:inception_upper":"1999-12-31",
    "iso:country":"GB",
    "wof:name":"PO12 4QJ",
    "wof:placetype":"postalcode"
},
  "geometry": {"coordinates":[-1.140259,50.805648],"type":"Point"}
}