{
  "type": "Feature",
  "properties": {
    "date:inception_lower": "1999-12-01",
    "date:inception_upper": "1999-12-01",
    "iso:country": "GB",
    "wof:name": "PO12 4QJ",
    "wof:placetype": "postalcode"
  },
  "geometry": {"coordinates":[-1.140459,50.805693],"type":"Point"}
}
