{
  "type": "Feature",
  "properties": {
    "iso:country": "GB",
    "wof:name": "B63 4QP",
    "wof:placetype": "postalcode"
  },
  "geometry": {"coordinates":[-2.059223,52.442555],"type":"Point"}
}
