{
  "type": "Feature",
  "properties": {
    "iso:country":"GB",
    "wof:name":"B63 4QP",
    "wof:placetype":"postalcode"
},
  "geometry": {"coordinates":[-2.0593170854045,52.44233313928695],"type":"Point"}
}