{
  "type": "Feature",
  "properties": {
    "iso:country":"GB",
    "wof:name":"HP18 0AG",
    "wof:placetype":"postalcode"
},
  "geometry": {"coordinates":[-0.92979125815124,51.79099044999344],"type":"Point"}
}