{
  "type": "Feature",
  "properties": {
    "iso:country": "GB",
    "wof:name": "CW5 8EU",
    "wof:placetype": "postalcode"
  },
  "geometry": {"coordinates":[-2.604403,53.022913],"type":"Point"}
}
