{
  "type": "Feature",
  "properties": {
    "iso:country":"GB",
    "wof:name":"CW5 8EU",
    "wof:placetype":"postalcode"
},
  "geometry": {"coordinates":[-2.60440334725379,53.02291290627035],"type":"Point"}
}