{
  "type": "Feature",
  "properties": {
    "date:inception_lower": "2010-09-01",
    "date:inception_upper": "2010-09-01",
    "iso:country": "GB",
    "wof:name": "SN7 7GD",
    "wof:placetype": "postalcode"
  },
  "geometry": {"coordinates":[-1.594023,51.648072],"type":"Point"}
}
