{
  "type": "Feature",
  "properties": {
    "iso:country":"GB",
    "wof:name":"EC4M 7DD",
    "wof:placetype":"postalcode"
},
  "geometry": {"coordinates":[-0.10152877589826,51.51427879010082],"type":"Point"}
}