{
  "type": "Feature",
  "properties": {
    "date:inception_lower": "2002-06-01",
    "date:inception_upper": "2002-06-01",
    "iso:country": "GB",
    "wof:name": "CM77 8NW",
    "wof:placetype": "postalcode"
  },
  "geometry": {"coordinates":[0.570363,51.853814],"type":"Point"}
}
