{
  "type": "Feature",
  "properties": {
    "iso:country": "GB",
    "wof:name": "CM77 8NW",
    "wof:placetype": "postalcode"
  },
  "geometry": {"coordinates":[0.570363,51.853814],"type":"Point"}
}
