{
  "type": "Feature",
  "properties": {
    "iso:country":"GB",
    "wof:name":"DN22 8RZ",
    "wof:placetype":"postalcode"
},
  "geometry": {"coordinates":[-0.96018631490401,53.36358542609073],"type":"Point"}
}