{
  "type": "Feature",
  "properties": {
    "iso:country":"GB",
    "wof:name":"SO18 3BX",
    "wof:placetype":"postalcode"
},
  "geometry": {"coordinates":[-1.34461685145525,50.92258311575798],"type":"Point"}
}