{
  "type": "Feature",
  "properties": {
    "iso:country": "GB",
    "wof:name": "SO18 3BX",
    "wof:placetype": "postalcode"
  },
  "geometry": {"coordinates":[-1.344617,50.922583],"type":"Point"}
}
