{
  "type": "Feature",
  "properties": {
    "iso:country":"GB",
    "wof:name":"L23 1XE",
    "wof:placetype":"postalcode"
},
  "geometry": {"coordinates":[-2.99635543588502,53.49826381774543],"type":"Point"}
}