{
  "type": "Feature",
  "properties": {
    "date:inception_lower": "1985-10-01",
    "date:inception_upper": "1985-10-01",
    "iso:country": "GB",
    "wof:name": "L23 1XE",
    "wof:placetype": "postalcode"
  },
  "geometry": {"coordinates":[-2.996355,53.498264],"type":"Point"}
}
