{
  "type": "Feature",
  "properties": {
    "iso:country": "GB",
    "wof:name": "L23 1XE",
    "wof:placetype": "postalcode"
  },
  "geometry": {"coordinates":[-2.996355,53.498264],"type":"Point"}
}
