{
  "type": "Feature",
  "properties": {
    "iso:country": "GB",
    "wof:name": "LL11 1EW",
    "wof:placetype": "postalcode"
  },
  "geometry": {"coordinates":[-2.992858,53.052504],"type":"Point"}
}
