{
  "type": "Feature",
  "properties": {
    "date:inception_lower":"1980-01-01",
    "date:inception_upper":"1980-01-31",
    "iso:country":"GB",
    "wof:name":"LL11 1EW",
    "wof:placetype":"postalcode"
},
  "geometry": {"coordinates":[-2.992858,53.052504],"type":"Point"}
}