{
  "type": "Feature",
  "properties": {
    "date:inception_lower": "1998-12-01",
    "date:inception_upper": "1998-12-01",
    "iso:country": "GB",
    "wof:name": "IV2 6UB",
    "wof:placetype": "postalcode"
  },
  "geometry": {"coordinates":[-4.243486,57.318563],"type":"Point"}
}
