{
  "type": "Feature",
  "properties": {
    "date:inception_lower":"2001-06-01",
    "date:inception_upper":"2001-06-30",
    "iso:country":"GB",
    "wof:name":"SE28 0LB",
    "wof:placetype":"postalcode"
},
  "geometry": {"coordinates":[0.092878,51.500323],"type":"Point"}
}