{
  "type": "Feature",
  "properties": {
    "iso:country":"GB",
    "wof:name":"SE28 0LB",
    "wof:placetype":"postalcode"
},
  "geometry": {"coordinates":[0.09287760492839,51.50032324153415],"type":"Point"}
}