{
  "type": "Feature",
  "properties": {
    "iso:country": "GB",
    "wof:name": "ST1 4AJ",
    "wof:placetype": "postalcode"
  },
  "geometry": {"coordinates":[-2.180902,53.023287],"type":"Point"}
}
