{
  "type": "Feature",
  "properties": {
    "date:inception_lower":"2011-07-01",
    "date:inception_upper":"2011-07-31",
    "iso:country":"GB",
    "wof:name":"ST1 4AJ",
    "wof:placetype":"postalcode"
},
  "geometry": {"coordinates":[-2.180902,53.023287],"type":"Point"}
}