{
  "type": "Feature",
  "properties": {
    "iso:country":"GB",
    "wof:name":"ST1 4AJ",
    "wof:placetype":"postalcode"
},
  "geometry": {"coordinates":[-2.18090240619425,53.02328710336273],"type":"Point"}
}