{
  "type": "Feature",
  "properties": {
    "iso:country":"GB",
    "wof:name":"PE8 6JZ",
    "wof:placetype":"postalcode"
},
  "geometry": {"coordinates":[-0.39160057682958,52.55312271498003],"type":"Point"}
}