{
  "type": "Feature",
  "properties": {
    "iso:country":"GB",
    "wof:name":"TS4 2NB",
    "wof:placetype":"postalcode"
},
  "geometry": {"coordinates":[-1.2231843545744,54.56237793722528],"type":"Point"}
}