{
  "type": "Feature",
  "properties": {
    "iso:country": "GB",
    "wof:name": "NE32 4NR",
    "wof:placetype": "postalcode"
  },
  "geometry": {"coordinates":[-1.481143,54.954398],"type":"Point"}
}
