{
  "type": "Feature",
  "properties": {
    "iso:country":"GB",
    "wof:name":"BN1 8NN",
    "wof:placetype":"postalcode"
},
  "geometry": {"coordinates":[-0.14257515345284,50.86256017087236],"type":"Point"}
}