{
  "type": "Feature",
  "properties": {
    "iso:country": "GB",
    "wof:name": "GL1 3EH",
    "wof:placetype": "postalcode"
  },
  "geometry": {"coordinates":[-2.240607,51.868806],"type":"Point"}
}
