{
  "type": "Feature",
  "properties": {
    "iso:country":"GB",
    "wof:name":"BH24 1EZ",
    "wof:placetype":"postalcode"
},
  "geometry": {"coordinates":[-1.79207413746285,50.84634376279912],"type":"Point"}
}