{
  "type": "Feature",
  "properties": {
    "date:inception_lower":"1999-06-01",
    "date:inception_upper":"1999-06-30",
    "iso:country":"GB",
    "wof:name":"NP19 7QT",
    "wof:placetype":"postalcode"
},
  "geometry": {"coordinates":[-2.967598,51.596688],"type":"Point"}
}