{
  "type": "Feature",
  "properties": {
    "iso:country":"GB",
    "wof:name":"NP19 7QT",
    "wof:placetype":"postalcode"
},
  "geometry": {"coordinates":[-2.96759815354167,51.59668847378427],"type":"Point"}
}