{
  "type": "Feature",
  "properties": {
    "date:inception_lower":"2015-10-01",
    "date:inception_upper":"2015-10-31",
    "iso:country":"GB",
    "wof:name":"WR2 6RU",
    "wof:placetype":"postalcode"
},
  "geometry": {"coordinates":[-2.276777,52.209343],"type":"Point"}
}