{
  "type": "Feature",
  "properties": {
    "iso:country": "GB",
    "wof:name": "WR2 6RU",
    "wof:placetype": "postalcode"
  },
  "geometry": {"coordinates":[-2.276777,52.209343],"type":"Point"}
}
