{
  "type": "Feature",
  "properties": {
    "iso:country":"GB",
    "wof:name":"WS15 4BA",
    "wof:placetype":"postalcode"
},
  "geometry": {"coordinates":[-1.88629422990147,52.74544738662597],"type":"Point"}
}