{
  "type": "Feature",
  "properties": {
    "iso:country":"GB",
    "wof:name":"DY4 9QS",
    "wof:placetype":"postalcode"
},
  "geometry": {"coordinates":[-2.06469397043247,52.53717422190871],"type":"Point"}
}