{
  "type": "Feature",
  "properties": {
    "iso:country":"GB",
    "wof:name":"CR0 1LA",
    "wof:placetype":"postalcode"
},
  "geometry": {"coordinates":[-0.09872613357034,51.37411891283949],"type":"Point"}
}