{
  "type": "Feature",
  "properties": {
    "date:inception_lower":"1980-01-01",
    "date:inception_upper":"1980-01-31",
    "iso:country":"GB",
    "wof:name":"CR0 1LA",
    "wof:placetype":"postalcode"
},
  "geometry": {"coordinates":[-0.098596,51.374135],"type":"Point"}
}