{
  "type": "Feature",
  "properties": {
    "iso:country":"GB",
    "wof:name":"TD15 1JA",
    "wof:placetype":"postalcode"
},
  "geometry": {"coordinates":[-1.99826888462468,55.76729202415676],"type":"Point"}
}