{
  "type": "Feature",
  "properties": {
    "iso:country": "GB",
    "wof:name": "CV37 8AW",
    "wof:placetype": "postalcode"
  },
  "geometry": {"coordinates":[-1.796689,52.133898],"type":"Point"}
}
