{
  "type": "Feature",
  "properties": {
    "iso:country":"GB",
    "wof:name":"CV37 8AW",
    "wof:placetype":"postalcode"
},
  "geometry": {"coordinates":[-1.79668926738265,52.13389763785145],"type":"Point"}
}