{
  "type": "Feature",
  "properties": {
    "iso:country": "GB",
    "wof:name": "PO3 6AX",
    "wof:placetype": "postalcode"
  },
  "geometry": {"coordinates":[-1.065074,50.805466],"type":"Point"}
}
