{
  "type": "Feature",
  "properties": {
    "iso:country":"GB",
    "wof:name":"SO30 4TN",
    "wof:placetype":"postalcode"
},
  "geometry": {"coordinates":[-1.30578390972321,50.91920242314601],"type":"Point"}
}