{
  "type": "Feature",
  "properties": {
    "iso:country":"GB",
    "wof:name":"E1 4AX",
    "wof:placetype":"postalcode"
},
  "geometry": {"coordinates":[-0.05109305078302,51.52320853180291],"type":"Point"}
}