{
  "type": "Feature",
  "properties": {
    "date:inception_lower":"1980-01-01",
    "date:inception_upper":"1980-01-31",
    "iso:country":"GB",
    "wof:name":"S43 1AY",
    "wof:placetype":"postalcode"
},
  "geometry": {"coordinates":[-1.408365,53.25373],"type":"Point"}
}