{
  "type": "Feature",
  "properties": {
    "iso:country": "GB",
    "wof:name": "S43 1AY",
    "wof:placetype": "postalcode"
  },
  "geometry": {"coordinates":[-1.408365,53.25373],"type":"Point"}
}
