{
  "type": "Feature",
  "properties": {
    "iso:country":"GB",
    "wof:name":"S43 1AY",
    "wof:placetype":"postalcode"
},
  "geometry": {"coordinates":[-1.40836497136092,53.25372963350777],"type":"Point"}
}