{
  "type": "Feature",
  "properties": {
    "date:inception_lower": "2012-10-01",
    "date:inception_upper": "2012-10-01",
    "iso:country": "GB",
    "wof:name": "KY11 8XA",
    "wof:placetype": "postalcode"
  },
  "geometry": {"coordinates":[-3.392049,56.052186],"type":"Point"}
}
