{
  "type": "Feature",
  "properties": {
    "iso:country":"GB",
    "wof:name":"KY11 8XA",
    "wof:placetype":"postalcode"
},
  "geometry": {"coordinates":[-3.39410556494392,56.0521761448045],"type":"Point"}
}