{
  "type": "Feature",
  "properties": {
    "date:inception_lower":"2009-12-01",
    "date:inception_upper":"2009-12-31",
    "iso:country":"GB",
    "wof:name":"LN13 9SZ",
    "wof:placetype":"postalcode"
},
  "geometry": {"coordinates":[0.206758,53.225206],"type":"Point"}
}