{
  "type": "Feature",
  "properties": {
    "iso:country":"GB",
    "wof:name":"LN13 9SZ",
    "wof:placetype":"postalcode"
},
  "geometry": {"coordinates":[0.20675800948154,53.22520638207067],"type":"Point"}
}