{
  "type": "Feature",
  "properties": {
    "date:inception_lower": "1980-01-01",
    "date:inception_upper": "1980-01-01",
    "iso:country": "GB",
    "wof:name": "DG7 2PZ",
    "wof:placetype": "postalcode"
  },
  "geometry": {"coordinates":[-4.156301,54.954791],"type":"Point"}
}
