{
  "type": "Feature",
  "properties": {
    "iso:country":"GB",
    "wof:name":"DG7 2PZ",
    "wof:placetype":"postalcode"
},
  "geometry": {"coordinates":[-4.1563095163049,54.95478342548648],"type":"Point"}
}