{
  "type": "Feature",
  "properties": {
    "iso:country": "GB",
    "wof:name": "EX22 7YB",
    "wof:placetype": "postalcode"
  },
  "geometry": {"coordinates":[-4.227958,50.818613],"type":"Point"}
}
