{
  "type": "Feature",
  "properties": {
    "iso:country":"GB",
    "wof:name":"WD6 1GJ",
    "wof:placetype":"postalcode"
},
  "geometry": {"coordinates":[-0.2544549014269,51.65822872257448],"type":"Point"}
}