{
  "type": "Feature",
  "properties": {
    "iso:country":"GB",
    "wof:name":"AL2 1HZ",
    "wof:placetype":"postalcode"
},
  "geometry": {"coordinates":[-0.29779894275762,51.72881436684236],"type":"Point"}
}