{
  "type": "Feature",
  "properties": {
    "date:inception_lower": "1980-01-01",
    "date:inception_upper": "1980-01-01",
    "iso:country": "GB",
    "wof:name": "AL2 1HZ",
    "wof:placetype": "postalcode"
  },
  "geometry": {"coordinates":[-0.297799,51.728814],"type":"Point"}
}
