{
  "type": "Feature",
  "properties": {
    "iso:country":"GB",
    "wof:name":"YO30 5XQ",
    "wof:placetype":"postalcode"
},
  "geometry": {"coordinates":[-1.12132843646428,53.98708784047724],"type":"Point"}
}