{
  "type": "Feature",
  "properties": {
    "iso:country": "GB",
    "wof:name": "PL19 9FR",
    "wof:placetype": "postalcode"
  },
  "geometry": {"coordinates":[-4.136825,50.533555],"type":"Point"}
}
