{
  "type": "Feature",
  "properties": {
    "date:inception_lower":"2007-07-01",
    "date:inception_upper":"2007-07-31",
    "iso:country":"GB",
    "wof:name":"PL19 9FR",
    "wof:placetype":"postalcode"
},
  "geometry": {"coordinates":[-4.136825,50.533555],"type":"Point"}
}