{
  "type": "Feature",
  "properties": {
    "date:inception_lower": "2007-09-01",
    "date:inception_upper": "2007-09-01",
    "iso:country": "GB",
    "wof:name": "DN21 4SG",
    "wof:placetype": "postalcode"
  },
  "geometry": {"coordinates":[-0.52175,53.452388],"type":"Point"}
}
