{
  "type": "Feature",
  "properties": {
    "iso:country":"GB",
    "wof:name":"DN21 4SG",
    "wof:placetype":"postalcode"
},
  "geometry": {"coordinates":[-0.52175043727848,53.45238809103834],"type":"Point"}
}