{
  "type": "Feature",
  "properties": {
    "iso:country":"GB",
    "wof:name":"LA2 7EN",
    "wof:placetype":"postalcode"
},
  "geometry": {"coordinates":[-2.53680426395924,54.12139668876329],"type":"Point"}
}