{
  "type": "Feature",
  "properties": {
    "date:inception_lower": "1980-01-01",
    "date:inception_upper": "1980-01-01",
    "iso:country": "GB",
    "wof:name": "LA2 7EN",
    "wof:placetype": "postalcode"
  },
  "geometry": {"coordinates":[-2.536804,54.121397],"type":"Point"}
}
