{
  "type": "Feature",
  "properties": {
    "iso:country":"GB",
    "wof:name":"NN15 7BP",
    "wof:placetype":"postalcode"
},
  "geometry": {"coordinates":[-0.71988225694308,52.3959718046864],"type":"Point"}
}