{
  "type": "Feature",
  "properties": {
    "date:inception_lower": "2005-05-01",
    "date:inception_upper": "2005-05-01",
    "iso:country": "GB",
    "wof:name": "BH8 9UT",
    "wof:placetype": "postalcode"
  },
  "geometry": {"coordinates":[-1.845481,50.751357],"type":"Point"}
}
