{
  "type": "Feature",
  "properties": {
    "iso:country":"GB",
    "wof:name":"BH8 9UT",
    "wof:placetype":"postalcode"
},
  "geometry": {"coordinates":[-1.845481402563,50.75135727692681],"type":"Point"}
}