{
  "type": "Feature",
  "properties": {
    "iso:country":"GB",
    "wof:name":"NE8 3UP",
    "wof:placetype":"postalcode"
},
  "geometry": {"coordinates":[-1.58541495245869,54.95017950162004],"type":"Point"}
}