{
  "type": "Feature",
  "properties": {
    "iso:country":"GB",
    "wof:name":"TW7 4AE",
    "wof:placetype":"postalcode"
},
  "geometry": {"coordinates":[-0.34777712766836,51.47479789378895],"type":"Point"}
}