{
  "type": "Feature",
  "properties": {
    "date:inception_lower": "1980-01-01",
    "date:inception_upper": "1980-01-01",
    "iso:country": "GB",
    "wof:name": "RM14 1TP",
    "wof:placetype": "postalcode"
  },
  "geometry": {"coordinates":[0.261273,51.58417],"type":"Point"}
}
