{
  "type": "Feature",
  "properties": {
    "date:inception_lower": "1985-04-01",
    "date:inception_upper": "1985-04-01",
    "iso:country": "GB",
    "wof:name": "DE13 0NQ",
    "wof:placetype": "postalcode"
  },
  "geometry": {"coordinates":[-1.640926,52.82457],"type":"Point"}
}
