{
  "type": "Feature",
  "properties": {
    "iso:country": "GB",
    "wof:name": "SE8 5AE",
    "wof:placetype": "postalcode"
  },
  "geometry": {"coordinates":[-0.042131,51.486792],"type":"Point"}
}
