{
  "type": "Feature",
  "properties": {
    "iso:country":"GB",
    "wof:name":"SE8 5AE",
    "wof:placetype":"postalcode"
},
  "geometry": {"coordinates":[-0.04213147469095,51.48679199498952],"type":"Point"}
}