{
  "type": "Feature",
  "properties": {
    "date:inception_lower": "1985-10-01",
    "date:inception_upper": "1985-10-01",
    "iso:country": "GB",
    "wof:name": "SE8 5AE",
    "wof:placetype": "postalcode"
  },
  "geometry": {"coordinates":[-0.04213,51.486883],"type":"Point"}
}
