{
  "type": "Feature",
  "properties": {
    "iso:country":"GB",
    "wof:name":"M41 9AR",
    "wof:placetype":"postalcode"
},
  "geometry": {"coordinates":[-2.34591773281553,53.44777046248112],"type":"Point"}
}