{
  "type": "Feature",
  "properties": {
    "date:inception_lower":"1980-01-01",
    "date:inception_upper":"1980-01-31",
    "iso:country":"GB",
    "wof:name":"KA27 8BQ",
    "wof:placetype":"postalcode"
},
  "geometry": {"coordinates":[-5.135673,55.573708],"type":"Point"}
}