{
  "type": "Feature",
  "properties": {
    "date:inception_lower": "1980-01-01",
    "date:inception_upper": "1980-01-01",
    "iso:country": "GB",
    "wof:name": "TA11 7NQ",
    "wof:placetype": "postalcode"
  },
  "geometry": {"coordinates":[-2.728917,51.055079],"type":"Point"}
}
