{
  "type": "Feature",
  "properties": {
    "iso:country":"GB",
    "wof:name":"WS11 9PL",
    "wof:placetype":"postalcode"
},
  "geometry": {"coordinates":[-1.98166557389924,52.66753335249727],"type":"Point"}
}