{
  "type": "Feature",
  "properties": {
    "iso:country": "GB",
    "wof:name": "WS11 9PL",
    "wof:placetype": "postalcode"
  },
  "geometry": {"coordinates":[-1.981666,52.667533],"type":"Point"}
}
