{
  "type": "Feature",
  "properties": {
    "date:inception_lower":"2003-03-01",
    "date:inception_upper":"2003-03-31",
    "iso:country":"GB",
    "wof:name":"WS11 9PL",
    "wof:placetype":"postalcode"
},
  "geometry": {"coordinates":[-1.981666,52.667533],"type":"Point"}
}