{
  "type": "Feature",
  "properties": {
    "iso:country": "GB",
    "wof:name": "NP10 8RH",
    "wof:placetype": "postalcode"
  },
  "geometry": {"coordinates":[-3.068046,51.581035],"type":"Point"}
}
