{
  "type": "Feature",
  "properties": {
    "date:inception_lower":"1999-06-01",
    "date:inception_upper":"1999-06-30",
    "iso:country":"GB",
    "wof:name":"NP10 8RH",
    "wof:placetype":"postalcode"
},
  "geometry": {"coordinates":[-3.068046,51.581035],"type":"Point"}
}