{
  "type": "Feature",
  "properties": {
    "iso:country":"GB",
    "wof:name":"NP10 8RH",
    "wof:placetype":"postalcode"
},
  "geometry": {"coordinates":[-3.0680461634995,51.58103492612143],"type":"Point"}
}