{
  "type": "Feature",
  "properties": {
    "iso:country":"GB",
    "wof:name":"WN5 8QB",
    "wof:placetype":"postalcode"
},
  "geometry": {"coordinates":[-2.7018039482639,53.54744785644346],"type":"Point"}
}