{
  "type": "Feature",
  "properties": {
    "iso:country":"GB",
    "wof:name":"NW10 5AB",
    "wof:placetype":"postalcode"
},
  "geometry": {"coordinates":[-0.22950454378455,51.53412127851041],"type":"Point"}
}