{
  "type": "Feature",
  "properties": {
    "iso:country":"GB",
    "wof:name":"SP3 4HH",
    "wof:placetype":"postalcode"
},
  "geometry": {"coordinates":[-1.89405434782688,51.20552122108992],"type":"Point"}
}