{
  "type": "Feature",
  "properties": {
    "iso:country":"GB",
    "wof:name":"CW9 5PL",
    "wof:placetype":"postalcode"
},
  "geometry": {"coordinates":[-2.50223629235097,53.256114872615],"type":"Point"}
}