{
  "type": "Feature",
  "properties": {
    "date:inception_lower":"1980-01-01",
    "date:inception_upper":"1980-01-31",
    "iso:country":"GB",
    "wof:name":"LL45 2EZ",
    "wof:placetype":"postalcode"
},
  "geometry": {"coordinates":[-4.118447,52.818356],"type":"Point"}
}