{
  "type": "Feature",
  "properties": {
    "iso:country":"GB",
    "wof:name":"LL45 2EZ",
    "wof:placetype":"postalcode"
},
  "geometry": {"coordinates":[-4.11844676081992,52.81835561622684],"type":"Point"}
}