{
  "type": "Feature",
  "properties": {
    "iso:country":"GB",
    "wof:name":"MK10 9AN",
    "wof:placetype":"postalcode"
},
  "geometry": {"coordinates":[-0.70566071296605,52.04530575127018],"type":"Point"}
}