{
  "type": "Feature",
  "properties": {
    "iso:country": "GB",
    "wof:name": "MK10 9AN",
    "wof:placetype": "postalcode"
  },
  "geometry": {"coordinates":[-0.705661,52.045306],"type":"Point"}
}
