{
  "type": "Feature",
  "properties": {
    "iso:country": "GB",
    "wof:name": "NN12 8SB",
    "wof:placetype": "postalcode"
  },
  "geometry": {"coordinates":[-1.101675,52.134213],"type":"Point"}
}
