{
  "type": "Feature",
  "properties": {
    "iso:country":"GB",
    "wof:name":"DY4 9ES",
    "wof:placetype":"postalcode"
},
  "geometry": {"coordinates":[-2.07189207410405,52.53925570330824],"type":"Point"}
}