{
  "type": "Feature",
  "properties": {
    "date:inception_lower": "1980-01-01",
    "date:inception_upper": "1980-01-01",
    "iso:country": "GB",
    "wof:name": "NG5 6BB",
    "wof:placetype": "postalcode"
  },
  "geometry": {"coordinates":[-1.138141,52.996862],"type":"Point"}
}
