{
  "type": "Feature",
  "properties": {
    "iso:country":"GB",
    "wof:name":"NG5 6BB",
    "wof:placetype":"postalcode"
},
  "geometry": {"coordinates":[-1.13814449289158,52.99685103542745],"type":"Point"}
}