{
  "type": "Feature",
  "properties": {
    "iso:country":"GB",
    "wof:name":"DD10 8EZ",
    "wof:placetype":"postalcode"
},
  "geometry": {"coordinates":[-2.46494766872408,56.71113475687127],"type":"Point"}
}