{
  "type": "Feature",
  "properties": {
    "iso:country": "GB",
    "wof:name": "DD10 8EZ",
    "wof:placetype": "postalcode"
  },
  "geometry": {"coordinates":[-2.464948,56.711135],"type":"Point"}
}
