{
  "type": "Feature",
  "properties": {
    "date:inception_lower": "1990-02-01",
    "date:inception_upper": "1990-02-01",
    "iso:country": "GB",
    "wof:name": "DL5 4UJ",
    "wof:placetype": "postalcode"
  },
  "geometry": {"coordinates":[-1.570579,54.633325],"type":"Point"}
}
