{
  "type": "Feature",
  "properties": {
    "iso:country":"GB",
    "wof:name":"DL5 4UJ",
    "wof:placetype":"postalcode"
},
  "geometry": {"coordinates":[-1.57057924213493,54.63332524452076],"type":"Point"}
}