{
  "type": "Feature",
  "properties": {
    "date:inception_lower":"1987-04-01",
    "date:inception_upper":"1987-04-30",
    "iso:country":"GB",
    "wof:name":"BA3 5PS",
    "wof:placetype":"postalcode"
},
  "geometry": {"coordinates":[-2.445438,51.242918],"type":"Point"}
}