{
  "type": "Feature",
  "properties": {
    "iso:country":"GB",
    "wof:name":"BA3 5PS",
    "wof:placetype":"postalcode"
},
  "geometry": {"coordinates":[-2.44543756781748,51.24291797018564],"type":"Point"}
}