{
  "type": "Feature",
  "properties": {
    "iso:country":"GB",
    "wof:name":"IG7 4GL",
    "wof:placetype":"postalcode"
},
  "geometry": {"coordinates":[0.09164003589095,51.61417530240455],"type":"Point"}
}