{
  "type": "Feature",
  "properties": {
    "date:inception_lower":"2014-07-01",
    "date:inception_upper":"2014-07-31",
    "iso:country":"GB",
    "wof:name":"IG7 4GL",
    "wof:placetype":"postalcode"
},
  "geometry": {"coordinates":[0.091667,51.614177],"type":"Point"}
}