{
  "type": "Feature",
  "properties": {
    "iso:country": "GB",
    "wof:name": "KT13 8AX",
    "wof:placetype": "postalcode"
  },
  "geometry": {"coordinates":[-0.457739,51.372721],"type":"Point"}
}
