{
  "type": "Feature",
  "properties": {
    "iso:country":"GB",
    "wof:name":"B78 2AP",
    "wof:placetype":"postalcode"
},
  "geometry": {"coordinates":[-1.73763884441629,52.582750185602],"type":"Point"}
}