{
  "type": "Feature",
  "properties": {
    "iso:country": "GB",
    "wof:name": "EN8 8TD",
    "wof:placetype": "postalcode"
  },
  "geometry": {"coordinates":[-0.033921,51.694427],"type":"Point"}
}
