{
  "type": "Feature",
  "properties": {
    "iso:country":"GB",
    "wof:name":"E4 0AW",
    "wof:placetype":"postalcode"
},
  "geometry": {"coordinates":[0.00815582737609,51.63324966852438],"type":"Point"}
}