{
  "type": "Feature",
  "properties": {
    "iso:country":"GB",
    "wof:name":"TQ7 3NA",
    "wof:placetype":"postalcode"
},
  "geometry": {"coordinates":[-3.85555147113521,50.27332475795946],"type":"Point"}
}