{
  "type": "Feature",
  "properties": {
    "iso:country":"GB",
    "wof:name":"W1S 2TB",
    "wof:placetype":"postalcode"
},
  "geometry": {"coordinates":[-0.14453748410984,51.51209844805673],"type":"Point"}
}