{
  "type": "Feature",
  "properties": {
    "iso:country":"GB",
    "wof:name":"CB1 9YW",
    "wof:placetype":"postalcode"
},
  "geometry": {"coordinates":[0.18233955771784,52.18524088942194],"type":"Point"}
}