{
  "type": "Feature",
  "properties": {
    "iso:country": "GB",
    "wof:name": "CB1 9YW",
    "wof:placetype": "postalcode"
  },
  "geometry": {"coordinates":[0.18234,52.185241],"type":"Point"}
}
