{
  "type": "Feature",
  "properties": {
    "iso:country":"GB",
    "wof:name":"IP27 9DW",
    "wof:placetype":"postalcode"
},
  "geometry": {"coordinates":[0.51742821911711,52.41632389095371],"type":"Point"}
}