{
  "type": "Feature",
  "properties": {
    "iso:country":"GB",
    "wof:name":"IG8 0HF",
    "wof:placetype":"postalcode"
},
  "geometry": {"coordinates":[0.03332232504943,51.60855452258228],"type":"Point"}
}