{
  "type": "Feature",
  "properties": {
    "date:inception_lower": "1980-01-01",
    "date:inception_upper": "1980-01-01",
    "iso:country": "GB",
    "wof:name": "IG8 0HF",
    "wof:placetype": "postalcode"
  },
  "geometry": {"coordinates":[0.033322,51.608555],"type":"Point"}
}
