{
  "type": "Feature",
  "properties": {
    "date:inception_lower": "2021-02-01",
    "date:inception_upper": "2021-02-01",
    "iso:country": "GB",
    "wof:name": "SY2 6GL",
    "wof:placetype": "postalcode"
  },
  "geometry": {"coordinates":[-2.727171,52.688816],"type":"Point"}
}
