{
  "type": "Feature",
  "properties": {
    "iso:country": "GB",
    "wof:name": "WA3 4HJ",
    "wof:placetype": "postalcode"
  },
  "geometry": {"coordinates":[-2.532585,53.45689],"type":"Point"}
}
