{
  "type": "Feature",
  "properties": {
    "iso:country":"GB",
    "wof:name":"WA3 4HJ",
    "wof:placetype":"postalcode"
},
  "geometry": {"coordinates":[-2.5325850004336,53.45689030745269],"type":"Point"}
}