{
  "type": "Feature",
  "properties": {
    "iso:country":"GB",
    "wof:name":"NN3 6QJ",
    "wof:placetype":"postalcode"
},
  "geometry": {"coordinates":[-0.86217752408375,52.26500380086926],"type":"Point"}
}