{
  "type": "Feature",
  "properties": {
    "iso:country": "GB",
    "wof:name": "NN3 6QJ",
    "wof:placetype": "postalcode"
  },
  "geometry": {"coordinates":[-0.862177,52.265004],"type":"Point"}
}
