{
  "type": "Feature",
  "properties": {
    "iso:country":"GB",
    "wof:name":"CV5 9HG",
    "wof:placetype":"postalcode"
},
  "geometry": {"coordinates":[-1.5641876772186,52.4136588763682],"type":"Point"}
}