{
  "type": "Feature",
  "properties": {
    "date:inception_lower": "1980-01-01",
    "date:inception_upper": "1980-01-01",
    "iso:country": "GB",
    "wof:name": "HX3 7PD",
    "wof:placetype": "postalcode"
  },
  "geometry": {"coordinates":[-1.81483,53.755084],"type":"Point"}
}
