{
  "type": "Feature",
  "properties": {
    "iso:country":"GB",
    "wof:name":"HX3 7PD",
    "wof:placetype":"postalcode"
},
  "geometry": {"coordinates":[-1.81476738818275,53.7549971862148],"type":"Point"}
}