{
  "type": "Feature",
  "properties": {
    "iso:country": "GB",
    "wof:name": "G71 8QB",
    "wof:placetype": "postalcode"
  },
  "geometry": {"coordinates":[-4.072787,55.811126],"type":"Point"}
}
