{
  "type": "Feature",
  "properties": {
    "iso:country":"GB",
    "wof:name":"G71 8QB",
    "wof:placetype":"postalcode"
},
  "geometry": {"coordinates":[-4.07278728673558,55.81112571030937],"type":"Point"}
}