{
  "type": "Feature",
  "properties": {
    "date:inception_lower":"2005-05-01",
    "date:inception_upper":"2005-05-31",
    "iso:country":"GB",
    "wof:name":"LS10 4BF",
    "wof:placetype":"postalcode"
},
  "geometry": {"coordinates":[-1.542422,53.738529],"type":"Point"}
}