{
  "type": "Feature",
  "properties": {
    "iso:country":"GB",
    "wof:name":"LS10 4BF",
    "wof:placetype":"postalcode"
},
  "geometry": {"coordinates":[-1.54242217609506,53.73852938517887],"type":"Point"}
}