{
  "type": "Feature",
  "properties": {
    "date:inception_lower": "2002-07-01",
    "date:inception_upper": "2002-07-01",
    "iso:country": "GB",
    "wof:name": "MK18 4BE",
    "wof:placetype": "postalcode"
  },
  "geometry": {"coordinates":[-1.074543,51.989538],"type":"Point"}
}
