{
  "type": "Feature",
  "properties": {
    "iso:country": "GB",
    "wof:name": "MK18 4BE",
    "wof:placetype": "postalcode"
  },
  "geometry": {"coordinates":[-1.074543,51.989538],"type":"Point"}
}
