{
  "type": "Feature",
  "properties": {
    "iso:country": "GB",
    "wof:name": "ST15 0HH",
    "wof:placetype": "postalcode"
  },
  "geometry": {"coordinates":[-2.157126,52.896932],"type":"Point"}
}
