{
  "type": "Feature",
  "properties": {
    "date:inception_lower": "1999-12-01",
    "date:inception_upper": "1999-12-01",
    "iso:country": "GB",
    "wof:name": "M14 7DP",
    "wof:placetype": "postalcode"
  },
  "geometry": {"coordinates":[-2.225224,53.442262],"type":"Point"}
}
