{
  "type": "Feature",
  "properties": {
    "iso:country":"GB",
    "wof:name":"M14 7DP",
    "wof:placetype":"postalcode"
},
  "geometry": {"coordinates":[-2.22522437050048,53.44226162348406],"type":"Point"}
}