{
  "type": "Feature",
  "properties": {
    "iso:country": "GB",
    "wof:name": "M14 7DP",
    "wof:placetype": "postalcode"
  },
  "geometry": {"coordinates":[-2.225224,53.442262],"type":"Point"}
}
