{
  "type": "Feature",
  "properties": {
    "iso:country":"GB",
    "wof:name":"CB9 8NH",
    "wof:placetype":"postalcode"
},
  "geometry": {"coordinates":[0.43032732581352,52.07874049344156],"type":"Point"}
}