{
  "type": "Feature",
  "properties": {
    "date:inception_lower": "2016-02-01",
    "date:inception_upper": "2016-02-01",
    "iso:country": "GB",
    "wof:name": "CB9 8NH",
    "wof:placetype": "postalcode"
  },
  "geometry": {"coordinates":[0.43028,52.07867],"type":"Point"}
}
