{
  "type": "Feature",
  "properties": {
    "iso:country": "GB",
    "wof:name": "CB9 8NH",
    "wof:placetype": "postalcode"
  },
  "geometry": {"coordinates":[0.43028,52.07867],"type":"Point"}
}
