{
  "type": "Feature",
  "properties": {
    "date:inception_lower": "1980-01-01",
    "date:inception_upper": "1980-01-01",
    "iso:country": "GB",
    "wof:name": "WV7 3AX",
    "wof:placetype": "postalcode"
  },
  "geometry": {"coordinates":[-2.265519,52.614734],"type":"Point"}
}
