{
  "type": "Feature",
  "properties": {
    "iso:country": "GB",
    "wof:name": "WV7 3AX",
    "wof:placetype": "postalcode"
  },
  "geometry": {"coordinates":[-2.265548,52.614707],"type":"Point"}
}
