{
  "type": "Feature",
  "properties": {
    "iso:country":"GB",
    "wof:name":"LE16 7XA",
    "wof:placetype":"postalcode"
},
  "geometry": {"coordinates":[-0.91916393438989,52.47929790104144],"type":"Point"}
}