{
  "type": "Feature",
  "properties": {
    "date:inception_lower":"1980-01-01",
    "date:inception_upper":"1980-01-31",
    "iso:country":"GB",
    "wof:name":"SP1 2RL",
    "wof:placetype":"postalcode"
},
  "geometry": {"coordinates":[-1.780619,51.065825],"type":"Point"}
}