{
  "type": "Feature",
  "properties": {
    "iso:country":"GB",
    "wof:name":"SP1 2RL",
    "wof:placetype":"postalcode"
},
  "geometry": {"coordinates":[-1.78061874300033,51.06582531327646],"type":"Point"}
}