{
  "type": "Feature",
  "properties": {
    "iso:country": "GB",
    "wof:name": "SP1 2RL",
    "wof:placetype": "postalcode"
  },
  "geometry": {"coordinates":[-1.780619,51.065825],"type":"Point"}
}
