{
  "type": "Feature",
  "properties": {
    "iso:country":"GB",
    "wof:name":"DH1 2SE",
    "wof:placetype":"postalcode"
},
  "geometry": {"coordinates":[-1.5219064091187,54.76788963548488],"type":"Point"}
}