{
  "type": "Feature",
  "properties": {
    "iso:country": "GB",
    "wof:name": "DH1 2SE",
    "wof:placetype": "postalcode"
  },
  "geometry": {"coordinates":[-1.523762,54.768329],"type":"Point"}
}
