{
  "type": "Feature",
  "properties": {
    "iso:country": "GB",
    "wof:name": "HP13 7JS",
    "wof:placetype": "postalcode"
  },
  "geometry": {"coordinates":[-0.73215,51.631006],"type":"Point"}
}
