{
  "type": "Feature",
  "properties": {
    "iso:country":"GB",
    "wof:name":"HP13 7JS",
    "wof:placetype":"postalcode"
},
  "geometry": {"coordinates":[-0.73215034139962,51.63100644398549],"type":"Point"}
}