{
  "type": "Feature",
  "properties": {
    "iso:country":"GB",
    "wof:name":"RG42 2PW",
    "wof:placetype":"postalcode"
},
  "geometry": {"coordinates":[-0.75305427494691,51.42898453980943],"type":"Point"}
}