{
  "type": "Feature",
  "properties": {
    "iso:country":"GB",
    "wof:name":"DL7 9JD",
    "wof:placetype":"postalcode"
},
  "geometry": {"coordinates":[-1.41004742820778,54.28627762738365],"type":"Point"}
}