{
  "type": "Feature",
  "properties": {
    "iso:country":"GB",
    "wof:name":"SN2 1SA",
    "wof:placetype":"postalcode"
},
  "geometry": {"coordinates":[-1.77954006255613,51.58007056280998],"type":"Point"}
}