{
  "type": "Feature",
  "properties": {
    "iso:country": "GB",
    "wof:name": "MK18 3JW",
    "wof:placetype": "postalcode"
  },
  "geometry": {"coordinates":[-0.866243,51.949541],"type":"Point"}
}
