{
  "type": "Feature",
  "properties": {
    "iso:country":"GB",
    "wof:name":"MK18 3JW",
    "wof:placetype":"postalcode"
},
  "geometry": {"coordinates":[-0.86543723326276,51.94999193669884],"type":"Point"}
}