{
  "type": "Feature",
  "properties": {
    "iso:country": "GB",
    "wof:name": "LL53 6RN",
    "wof:placetype": "postalcode"
  },
  "geometry": {"coordinates":[-4.400955,52.955022],"type":"Point"}
}
