{
  "type": "Feature",
  "properties": {
    "iso:country":"GB",
    "wof:name":"CR5 1SW",
    "wof:placetype":"postalcode"
},
  "geometry": {"coordinates":[-0.10464324533081,51.30143614536989],"type":"Point"}
}