{
  "type": "Feature",
  "properties": {
    "iso:country":"GB",
    "wof:name":"CV2 1SZ",
    "wof:placetype":"postalcode"
},
  "geometry": {"coordinates":[-1.46040526093308,52.4401744898764],"type":"Point"}
}