{
  "type": "Feature",
  "properties": {
    "iso:country":"GB",
    "wof:name":"G44 3XH",
    "wof:placetype":"postalcode"
},
  "geometry": {"coordinates":[-4.26345649382151,55.79758888286877],"type":"Point"}
}