{
  "type": "Feature",
  "properties": {
    "iso:country":"GB",
    "wof:name":"DH2 2BT",
    "wof:placetype":"postalcode"
},
  "geometry": {"coordinates":[-1.60579559603243,54.85695074988859],"type":"Point"}
}