{
  "type": "Feature",
  "properties": {
    "date:inception_lower": "2006-07-01",
    "date:inception_upper": "2006-07-01",
    "iso:country": "GB",
    "wof:name": "DH2 2BT",
    "wof:placetype": "postalcode"
  },
  "geometry": {"coordinates":[-1.605796,54.856951],"type":"Point"}
}
