{
  "type": "Feature",
  "properties": {
    "iso:country":"GB",
    "wof:name":"CA28 8DG",
    "wof:placetype":"postalcode"
},
  "geometry": {"coordinates":[-3.57450200290001,54.52937440688961],"type":"Point"}
}