{
  "type": "Feature",
  "properties": {
    "date:inception_lower": "1980-01-01",
    "date:inception_upper": "1980-01-01",
    "iso:country": "GB",
    "wof:name": "CA28 8DG",
    "wof:placetype": "postalcode"
  },
  "geometry": {"coordinates":[-3.574502,54.529374],"type":"Point"}
}
