{
  "type": "Feature",
  "properties": {
    "iso:country":"GB",
    "wof:name":"YO25 3EU",
    "wof:placetype":"postalcode"
},
  "geometry": {"coordinates":[-0.50444053654885,54.02271117369425],"type":"Point"}
}