{
  "type": "Feature",
  "properties": {
    "date:inception_lower": "2002-11-01",
    "date:inception_upper": "2002-11-01",
    "iso:country": "GB",
    "wof:name": "DN34 4ST",
    "wof:placetype": "postalcode"
  },
  "geometry": {"coordinates":[-0.09585,53.558004],"type":"Point"}
}
