{
  "type": "Feature",
  "properties": {
    "iso:country":"GB",
    "wof:name":"BS1 5LU",
    "wof:placetype":"postalcode"
},
  "geometry": {"coordinates":[-2.60192526346576,51.45484676788797],"type":"Point"}
}