{
  "type": "Feature",
  "properties": {
    "iso:country": "GB",
    "wof:name": "NN14 2XJ",
    "wof:placetype": "postalcode"
  },
  "geometry": {"coordinates":[-0.834552,52.443216],"type":"Point"}
}
