{
  "type": "Feature",
  "properties": {
    "iso:country": "GB",
    "wof:name": "N11 2RP",
    "wof:placetype": "postalcode"
  },
  "geometry": {"coordinates":[-0.128803,51.611938],"type":"Point"}
}
