{
  "type": "Feature",
  "properties": {
    "date:inception_lower":"1998-06-01",
    "date:inception_upper":"1998-06-30",
    "iso:country":"GB",
    "wof:name":"DN15 6BS",
    "wof:placetype":"postalcode"
},
  "geometry": {"coordinates":[-0.639957,53.588845],"type":"Point"}
}