{
  "type": "Feature",
  "properties": {
    "iso:country":"GB",
    "wof:name":"HR2 6BZ",
    "wof:placetype":"postalcode"
},
  "geometry": {"coordinates":[-2.71583418462763,52.0426294020299],"type":"Point"}
}