{
  "type": "Feature",
  "properties": {
    "iso:country":"GB",
    "wof:name":"TN29 0PP",
    "wof:placetype":"postalcode"
},
  "geometry": {"coordinates":[0.99492213603804,51.02549110493809],"type":"Point"}
}