{
  "type": "Feature",
  "properties": {
    "iso:country": "GB",
    "wof:name": "DN14 7BG",
    "wof:placetype": "postalcode"
  },
  "geometry": {"coordinates":[-0.87418,53.744768],"type":"Point"}
}
