{
  "type": "Feature",
  "properties": {
    "date:inception_lower":"1986-07-01",
    "date:inception_upper":"1986-07-31",
    "iso:country":"GB",
    "wof:name":"DN14 7BG",
    "wof:placetype":"postalcode"
},
  "geometry": {"coordinates":[-0.87418,53.744768],"type":"Point"}
}