{
  "type": "Feature",
  "properties": {
    "iso:country":"GB",
    "wof:name":"CM1 3QA",
    "wof:placetype":"postalcode"
},
  "geometry": {"coordinates":[0.38654328842337,51.7137401870293],"type":"Point"}
}