{
  "type": "Feature",
  "properties": {
    "iso:country":"GB",
    "wof:name":"W10 5BN",
    "wof:placetype":"postalcode"
},
  "geometry": {"coordinates":[-0.20816612085538,51.52601886339581],"type":"Point"}
}