{
  "type": "Feature",
  "properties": {
    "date:inception_lower":"2006-09-01",
    "date:inception_upper":"2006-09-30",
    "iso:country":"GB",
    "wof:name":"RG2 0GS",
    "wof:placetype":"postalcode"
},
  "geometry": {"coordinates":[-0.976251,51.431218],"type":"Point"}
}