{
  "type": "Feature",
  "properties": {
    "iso:country":"GB",
    "wof:name":"BR2 0QH",
    "wof:placetype":"postalcode"
},
  "geometry": {"coordinates":[0.00519449776045,51.39600149546848],"type":"Point"}
}