{
  "type": "Feature",
  "properties": {
    "iso:country": "GB",
    "wof:name": "CV22 7PD",
    "wof:placetype": "postalcode"
  },
  "geometry": {"coordinates":[-1.284846,52.362754],"type":"Point"}
}
