{
  "type": "Feature",
  "properties": {
    "date:inception_lower": "1980-01-01",
    "date:inception_upper": "1980-01-01",
    "iso:country": "GB",
    "wof:name": "CV22 7PD",
    "wof:placetype": "postalcode"
  },
  "geometry": {"coordinates":[-1.284846,52.362754],"type":"Point"}
}
