{
  "type": "Feature",
  "properties": {
    "iso:country":"GB",
    "wof:name":"BN1 6UH",
    "wof:placetype":"postalcode"
},
  "geometry": {"coordinates":[-0.15406818390074,50.84860490430081],"type":"Point"}
}