{
  "type": "Feature",
  "properties": {
    "iso:country":"GB",
    "wof:name":"RG24 9JB",
    "wof:placetype":"postalcode"
},
  "geometry": {"coordinates":[-1.1095417276432,51.29564670557659],"type":"Point"}
}