{
  "type": "Feature",
  "properties": {
    "iso:country":"GB",
    "wof:name":"CM3 3LG",
    "wof:placetype":"postalcode"
},
  "geometry": {"coordinates":[0.48663717351711,51.81103670175149],"type":"Point"}
}