{
  "type": "Feature",
  "properties": {
    "iso:country":"GB",
    "wof:name":"ML11 9XJ",
    "wof:placetype":"postalcode"
},
  "geometry": {"coordinates":[-3.89312323768882,55.67044964553534],"type":"Point"}
}