{
  "type": "Feature",
  "properties": {
    "date:inception_lower": "1980-01-01",
    "date:inception_upper": "1980-01-01",
    "iso:country": "GB",
    "wof:name": "ML11 9XJ",
    "wof:placetype": "postalcode"
  },
  "geometry": {"coordinates":[-3.864463,55.667321],"type":"Point"}
}
