{
  "type": "Feature",
  "properties": {
    "iso:country":"GB",
    "wof:name":"SW16 2TS",
    "wof:placetype":"postalcode"
},
  "geometry": {"coordinates":[-0.12440488020993,51.43239171231883],"type":"Point"}
}