{
  "type": "Feature",
  "properties": {
    "iso:country":"GB",
    "wof:name":"NG12 4AZ",
    "wof:placetype":"postalcode"
},
  "geometry": {"coordinates":[-1.11354246548603,52.91323842818552],"type":"Point"}
}