{
  "type": "Feature",
  "properties": {
    "iso:country":"GB",
    "wof:name":"NG9 6JQ",
    "wof:placetype":"postalcode"
},
  "geometry": {"coordinates":[-1.26588047716965,52.91150828729442],"type":"Point"}
}