{
  "type": "Feature",
  "properties": {
    "date:inception_lower": "1997-12-01",
    "date:inception_upper": "1997-12-01",
    "iso:country": "GB",
    "wof:name": "BS32 9BE",
    "wof:placetype": "postalcode"
  },
  "geometry": {"coordinates":[-2.557965,51.535656],"type":"Point"}
}
