{
  "type": "Feature",
  "properties": {
    "iso:country":"GB",
    "wof:name":"W1K 1JQ",
    "wof:placetype":"postalcode"
},
  "geometry": {"coordinates":[-0.15103860198054,51.50743508925117],"type":"Point"}
}