{
  "type": "Feature",
  "properties": {
    "date:inception_lower": "2000-12-01",
    "date:inception_upper": "2000-12-01",
    "iso:country": "GB",
    "wof:name": "W1K 1JQ",
    "wof:placetype": "postalcode"
  },
  "geometry": {"coordinates":[-0.151039,51.507435],"type":"Point"}
}
