{
  "type": "Feature",
  "properties": {
    "iso:country": "GB",
    "wof:name": "TN4 0QR",
    "wof:placetype": "postalcode"
  },
  "geometry": {"coordinates":[0.256897,51.158154],"type":"Point"}
}
