{
  "type": "Feature",
  "properties": {
    "iso:country":"GB",
    "wof:name":"B94 6EU",
    "wof:placetype":"postalcode"
},
  "geometry": {"coordinates":[-1.72680045963762,52.35758016625083],"type":"Point"}
}