{
  "type": "Feature",
  "properties": {
    "iso:country":"GB",
    "wof:name":"BN25 2XQ",
    "wof:placetype":"postalcode"
},
  "geometry": {"coordinates":[0.10044643666306,50.78647093070504],"type":"Point"}
}