{
  "type": "Feature",
  "properties": {
    "iso:country": "GB",
    "wof:name": "TA4 4TB",
    "wof:placetype": "postalcode"
  },
  "geometry": {"coordinates":[-3.313401,51.166107],"type":"Point"}
}
