{
  "type": "Feature",
  "properties": {
    "date:inception_lower": "1988-03-01",
    "date:inception_upper": "1988-03-01",
    "iso:country": "GB",
    "wof:name": "TA4 4TB",
    "wof:placetype": "postalcode"
  },
  "geometry": {"coordinates":[-3.313302,51.166153],"type":"Point"}
}
