{
  "type": "Feature",
  "properties": {
    "iso:country": "GB",
    "wof:name": "AB12 5RW",
    "wof:placetype": "postalcode"
  },
  "geometry": {"coordinates":[-2.11567,57.111304],"type":"Point"}
}
