{
  "type": "Feature",
  "properties": {
    "iso:country": "GB",
    "wof:name": "MK41 6DL",
    "wof:placetype": "postalcode"
  },
  "geometry": {"coordinates":[-0.489842,52.159184],"type":"Point"}
}
