{
  "type": "Feature",
  "properties": {
    "iso:country": "GB",
    "wof:name": "SA67 7BT",
    "wof:placetype": "postalcode"
  },
  "geometry": {"coordinates":[-4.741443,51.800009],"type":"Point"}
}
