{
  "type": "Feature",
  "properties": {
    "iso:country":"GB",
    "wof:name":"SA67 7BT",
    "wof:placetype":"postalcode"
},
  "geometry": {"coordinates":[-4.7413838714542,51.79998055977423],"type":"Point"}
}