{
  "type": "Feature",
  "properties": {
    "iso:country": "GB",
    "wof:name": "CH6 5FZ",
    "wof:placetype": "postalcode"
  },
  "geometry": {"coordinates":[-3.1439,53.226323],"type":"Point"}
}
