{
  "type": "Feature",
  "properties": {
    "iso:country":"GB",
    "wof:name":"CW7 2DF",
    "wof:placetype":"postalcode"
},
  "geometry": {"coordinates":[-2.53163060632985,53.19568063168867],"type":"Point"}
}