{
  "type": "Feature",
  "properties": {
    "iso:country":"GB",
    "wof:name":"CO3 4BJ",
    "wof:placetype":"postalcode"
},
  "geometry": {"coordinates":[0.85956203983604,51.8901071957557],"type":"Point"}
}