{
  "type": "Feature",
  "properties": {
    "date:inception_lower": "1980-01-01",
    "date:inception_upper": "1980-01-01",
    "iso:country": "GB",
    "wof:name": "CO3 4BJ",
    "wof:placetype": "postalcode"
  },
  "geometry": {"coordinates":[0.859562,51.890107],"type":"Point"}
}
