{
  "type": "Feature",
  "properties": {
    "iso:country": "GB",
    "wof:name": "EH49 7BD",
    "wof:placetype": "postalcode"
  },
  "geometry": {"coordinates":[-3.61625,55.974837],"type":"Point"}
}
