{
  "type": "Feature",
  "properties": {
    "iso:country":"GB",
    "wof:name":"EH49 7BD",
    "wof:placetype":"postalcode"
},
  "geometry": {"coordinates":[-3.61625001838261,55.97483715736306],"type":"Point"}
}