{
  "type": "Feature",
  "properties": {
    "iso:country":"GB",
    "wof:name":"WA11 8QT",
    "wof:placetype":"postalcode"
},
  "geometry": {"coordinates":[-2.75317705236101,53.49467777524669],"type":"Point"}
}