{
  "type": "Feature",
  "properties": {
    "iso:country": "GB",
    "wof:name": "TQ3 1QD",
    "wof:placetype": "postalcode"
  },
  "geometry": {"coordinates":[-3.573975,50.445845],"type":"Point"}
}
