{
  "type": "Feature",
  "properties": {
    "iso:country": "GB",
    "wof:name": "PE25 1NQ",
    "wof:placetype": "postalcode"
  },
  "geometry": {"coordinates":[0.337099,53.19136],"type":"Point"}
}
