{
  "type": "Feature",
  "properties": {
    "iso:country": "GB",
    "wof:name": "LE5 1HU",
    "wof:placetype": "postalcode"
  },
  "geometry": {"coordinates":[-1.080816,52.642711],"type":"Point"}
}
