{
  "type": "Feature",
  "properties": {
    "date:inception_lower": "1980-01-01",
    "date:inception_upper": "1980-01-01",
    "iso:country": "GB",
    "wof:name": "LE5 1HU",
    "wof:placetype": "postalcode"
  },
  "geometry": {"coordinates":[-1.080816,52.642711],"type":"Point"}
}
