{
  "type": "Feature",
  "properties": {
    "date:inception_lower": "2011-05-01",
    "date:inception_upper": "2011-05-01",
    "iso:country": "GB",
    "wof:name": "LL11 5FT",
    "wof:placetype": "postalcode"
  },
  "geometry": {"coordinates":[-3.053662,53.069367],"type":"Point"}
}
