{
  "type": "Feature",
  "properties": {
    "iso:country":"GB",
    "wof:name":"LL11 5FT",
    "wof:placetype":"postalcode"
},
  "geometry": {"coordinates":[-3.0536622526743,53.06936658341591],"type":"Point"}
}