{
  "type": "Feature",
  "properties": {
    "iso:country":"GB",
    "wof:name":"S66 2SB",
    "wof:placetype":"postalcode"
},
  "geometry": {"coordinates":[-1.26511453992914,53.42522252327282],"type":"Point"}
}