{
  "type": "Feature",
  "properties": {
    "date:inception_lower":"1980-11-01",
    "date:inception_upper":"1980-11-30",
    "iso:country":"GB",
    "wof:name":"KA1 2LW",
    "wof:placetype":"postalcode"
},
  "geometry": {"coordinates":[-4.512577,55.612821],"type":"Point"}
}