{
  "type": "Feature",
  "properties": {
    "iso:country":"GB",
    "wof:name":"KA1 2LW",
    "wof:placetype":"postalcode"
},
  "geometry": {"coordinates":[-4.51257738782995,55.61282084921192],"type":"Point"}
}