{
  "type": "Feature",
  "properties": {
    "iso:country":"GB",
    "wof:name":"N14 4AS",
    "wof:placetype":"postalcode"
},
  "geometry": {"coordinates":[-0.13732846513992,51.64525184502634],"type":"Point"}
}