{
  "type": "Feature",
  "properties": {
    "date:inception_lower": "1980-01-01",
    "date:inception_upper": "1980-01-01",
    "iso:country": "GB",
    "wof:name": "CA7 8HY",
    "wof:placetype": "postalcode"
  },
  "geometry": {"coordinates":[-2.961562,54.731317],"type":"Point"}
}
