{
  "type": "Feature",
  "properties": {
    "date:inception_lower": "1980-01-01",
    "date:inception_upper": "1980-01-01",
    "iso:country": "GB",
    "wof:name": "SP11 0JG",
    "wof:placetype": "postalcode"
  },
  "geometry": {"coordinates":[-1.495999,51.273084],"type":"Point"}
}
