{
  "type": "Feature",
  "properties": {
    "iso:country": "GB",
    "wof:name": "SP11 0JG",
    "wof:placetype": "postalcode"
  },
  "geometry": {"coordinates":[-1.495999,51.273084],"type":"Point"}
}
