{
  "type": "Feature",
  "properties": {
    "date:inception_lower": "1980-01-01",
    "date:inception_upper": "1980-01-01",
    "iso:country": "GB",
    "wof:name": "L35 8PW",
    "wof:placetype": "postalcode"
  },
  "geometry": {"coordinates":[-2.772332,53.423976],"type":"Point"}
}
