{
  "type": "Feature",
  "properties": {
    "iso:country": "GB",
    "wof:name": "LN4 4QQ",
    "wof:placetype": "postalcode"
  },
  "geometry": {"coordinates":[-0.172494,53.039765],"type":"Point"}
}
