{
  "type": "Feature",
  "properties": {
    "iso:country":"GB",
    "wof:name":"LN4 4QQ",
    "wof:placetype":"postalcode"
},
  "geometry": {"coordinates":[-0.17249453871801,53.03976545363185],"type":"Point"}
}