{
  "type": "Feature",
  "properties": {
    "date:inception_lower":"1980-01-01",
    "date:inception_upper":"1980-01-31",
    "iso:country":"GB",
    "wof:name":"NE65 8QY",
    "wof:placetype":"postalcode"
},
  "geometry": {"coordinates":[-1.801003,55.245504],"type":"Point"}
}