{
  "type": "Feature",
  "properties": {
    "iso:country": "GB",
    "wof:name": "NE65 8QY",
    "wof:placetype": "postalcode"
  },
  "geometry": {"coordinates":[-1.802665,55.246531],"type":"Point"}
}
