{
  "type": "Feature",
  "properties": {
    "date:inception_lower":"2005-01-01",
    "date:inception_upper":"2005-01-31",
    "iso:country":"GB",
    "wof:name":"MK8 0PP",
    "wof:placetype":"postalcode"
},
  "geometry": {"coordinates":[-0.811652,52.022326],"type":"Point"}
}