{
  "type": "Feature",
  "properties": {
    "iso:country":"GB",
    "wof:name":"SG8 9DE",
    "wof:placetype":"postalcode"
},
  "geometry": {"coordinates":[-0.01461864859987,52.04304356404911],"type":"Point"}
}