{
  "type": "Feature",
  "properties": {
    "iso:country": "GB",
    "wof:name": "SG8 9DE",
    "wof:placetype": "postalcode"
  },
  "geometry": {"coordinates":[-0.014633,52.043063],"type":"Point"}
}
