{
  "type": "Feature",
  "properties": {
    "iso:country": "GB",
    "wof:name": "SK23 6DT",
    "wof:placetype": "postalcode"
  },
  "geometry": {"coordinates":[-1.920759,53.336455],"type":"Point"}
}
