{
  "type": "Feature",
  "properties": {
    "date:inception_lower": "1980-01-01",
    "date:inception_upper": "1980-01-01",
    "iso:country": "GB",
    "wof:name": "TF4 3ND",
    "wof:placetype": "postalcode"
  },
  "geometry": {"coordinates":[-2.458669,52.655118],"type":"Point"}
}
