{
  "type": "Feature",
  "properties": {
    "iso:country": "GB",
    "wof:name": "TF4 3ND",
    "wof:placetype": "postalcode"
  },
  "geometry": {"coordinates":[-2.458833,52.655271],"type":"Point"}
}
