{
  "type": "Feature",
  "properties": {
    "iso:country":"GB",
    "wof:name":"TF4 3ND",
    "wof:placetype":"postalcode"
},
  "geometry": {"coordinates":[-2.45867041371813,52.65510339079508],"type":"Point"}
}