{
  "type": "Feature",
  "properties": {
    "date:inception_lower": "2023-06-01",
    "date:inception_upper": "2023-06-01",
    "iso:country": "GB",
    "wof:name": "SL5 0FY",
    "wof:placetype": "postalcode"
  },
  "geometry": {"coordinates":[-0.635952,51.402188],"type":"Point"}
}
