{
  "type": "Feature",
  "properties": {
    "iso:country":"GB",
    "wof:name":"SA43 3HP",
    "wof:placetype":"postalcode"
},
  "geometry": {"coordinates":[-4.67599927372408,52.08083262099311],"type":"Point"}
}