{
  "type": "Feature",
  "properties": {
    "iso:country": "GB",
    "wof:name": "SA43 3HP",
    "wof:placetype": "postalcode"
  },
  "geometry": {"coordinates":[-4.675578,52.08074],"type":"Point"}
}
