{
  "type": "Feature",
  "properties": {
    "date:inception_lower": "2005-09-01",
    "date:inception_upper": "2005-09-01",
    "iso:country": "GB",
    "wof:name": "SO15 5QW",
    "wof:placetype": "postalcode"
  },
  "geometry": {"coordinates":[-1.434759,50.925113],"type":"Point"}
}
