{
  "type": "Feature",
  "properties": {
    "iso:country":"GB",
    "wof:name":"LL53 8TT",
    "wof:placetype":"postalcode"
},
  "geometry": {"coordinates":[-4.48305980495166,52.89671354711139],"type":"Point"}
}