{
  "type": "Feature",
  "properties": {
    "date:inception_lower":"1980-01-01",
    "date:inception_upper":"1980-01-31",
    "iso:country":"GB",
    "wof:name":"WS15 3HR",
    "wof:placetype":"postalcode"
},
  "geometry": {"coordinates":[-1.896909,52.779491],"type":"Point"}
}