{
  "type": "Feature",
  "properties": {
    "iso:country": "GB",
    "wof:name": "WS15 3HR",
    "wof:placetype": "postalcode"
  },
  "geometry": {"coordinates":[-1.896909,52.779491],"type":"Point"}
}
