{
  "type": "Feature",
  "properties": {
    "iso:country":"GB",
    "wof:name":"WS15 3HR",
    "wof:placetype":"postalcode"
},
  "geometry": {"coordinates":[-1.8969093630328,52.77949142463304],"type":"Point"}
}