{
  "type": "Feature",
  "properties": {
    "iso:country":"GB",
    "wof:name":"M38 0BS",
    "wof:placetype":"postalcode"
},
  "geometry": {"coordinates":[-2.42706956495802,53.52985136629608],"type":"Point"}
}