{
  "type": "Feature",
  "properties": {
    "iso:country":"GB",
    "wof:name":"CT2 7PH",
    "wof:placetype":"postalcode"
},
  "geometry": {"coordinates":[1.0838756967958,51.28569695299818],"type":"Point"}
}