{
  "type": "Feature",
  "properties": {
    "iso:country":"GB",
    "wof:name":"NN15 6LD",
    "wof:placetype":"postalcode"
},
  "geometry": {"coordinates":[-0.71536000333769,52.38012614145563],"type":"Point"}
}