{
  "type": "Feature",
  "properties": {
    "iso:country":"GB",
    "wof:name":"GU20 6JR",
    "wof:placetype":"postalcode"
},
  "geometry": {"coordinates":[-0.66729075337082,51.37415999538649],"type":"Point"}
}