{
  "type": "Feature",
  "properties": {
    "iso:country":"GB",
    "wof:name":"OL16 3RZ",
    "wof:placetype":"postalcode"
},
  "geometry": {"coordinates":[-2.10017865313962,53.60105906497976],"type":"Point"}
}