{
  "type": "Feature",
  "properties": {
    "iso:country":"GB",
    "wof:name":"LS11 5QA",
    "wof:placetype":"postalcode"
},
  "geometry": {"coordinates":[-1.55066910653876,53.79116784719157],"type":"Point"}
}