{
  "type": "Feature",
  "properties": {
    "iso:country":"GB",
    "wof:name":"SL6 8LH",
    "wof:placetype":"postalcode"
},
  "geometry": {"coordinates":[-0.69923720736882,51.53999956810593],"type":"Point"}
}