{
  "type": "Feature",
  "properties": {
    "date:inception_lower":"1980-01-01",
    "date:inception_upper":"1980-01-31",
    "iso:country":"GB",
    "wof:name":"DL12 0TL",
    "wof:placetype":"postalcode"
},
  "geometry": {"coordinates":[-2.064272,54.618988],"type":"Point"}
}