{
  "type": "Feature",
  "properties": {
    "iso:country":"GB",
    "wof:name":"SS5 4HS",
    "wof:placetype":"postalcode"
},
  "geometry": {"coordinates":[0.65723829178907,51.60354049841962],"type":"Point"}
}