{
  "type": "Feature",
  "properties": {
    "iso:country": "GB",
    "wof:name": "B49 6QU",
    "wof:placetype": "postalcode"
  },
  "geometry": {"coordinates":[-1.858982,52.218193],"type":"Point"}
}
