{
  "type": "Feature",
  "properties": {
    "iso:country":"GB",
    "wof:name":"SG12 0XB",
    "wof:placetype":"postalcode"
},
  "geometry": {"coordinates":[-0.04062350829788,51.82021521250326],"type":"Point"}
}