{
  "type": "Feature",
  "properties": {
    "iso:country": "GB",
    "wof:name": "HP17 0UG",
    "wof:placetype": "postalcode"
  },
  "geometry": {"coordinates":[-0.808302,51.756859],"type":"Point"}
}
