{
  "type": "Feature",
  "properties": {
    "iso:country":"GB",
    "wof:name":"BH15 3JD",
    "wof:placetype":"postalcode"
},
  "geometry": {"coordinates":[-1.96195694421477,50.73577900456287],"type":"Point"}
}