{
  "type": "Feature",
  "properties": {
    "iso:country":"GB",
    "wof:name":"PE12 6LS",
    "wof:placetype":"postalcode"
},
  "geometry": {"coordinates":[-0.05880931180172,52.83747249054692],"type":"Point"}
}