{
  "type": "Feature",
  "properties": {
    "iso:country":"GB",
    "wof:name":"B45 9SF",
    "wof:placetype":"postalcode"
},
  "geometry": {"coordinates":[-2.01728391996752,52.39950926433983],"type":"Point"}
}