{
  "type": "Feature",
  "properties": {
    "date:inception_lower": "1994-05-01",
    "date:inception_upper": "1994-05-01",
    "iso:country": "GB",
    "wof:name": "B45 9SF",
    "wof:placetype": "postalcode"
  },
  "geometry": {"coordinates":[-2.017284,52.399509],"type":"Point"}
}
