{
  "type": "Feature",
  "properties": {
    "iso:country":"GB",
    "wof:name":"S70 1UA",
    "wof:placetype":"postalcode"
},
  "geometry": {"coordinates":[-1.47295128688982,53.54717084867531],"type":"Point"}
}