{
  "type": "Feature",
  "properties": {
    "iso:country":"GB",
    "wof:name":"TN13 3AG",
    "wof:placetype":"postalcode"
},
  "geometry": {"coordinates":[0.1903809358571,51.27644020575589],"type":"Point"}
}