{
  "type": "Feature",
  "properties": {
    "iso:country":"GB",
    "wof:name":"OX16 1RE",
    "wof:placetype":"postalcode"
},
  "geometry": {"coordinates":[-1.34567099424664,52.07488022759662],"type":"Point"}
}