{
  "type": "Feature",
  "properties": {
    "date:inception_lower": "2008-06-01",
    "date:inception_upper": "2008-06-01",
    "iso:country": "GB",
    "wof:name": "HA2 8FE",
    "wof:placetype": "postalcode"
  },
  "geometry": {"coordinates":[-0.355346,51.567776],"type":"Point"}
}
