{
  "type": "Feature",
  "properties": {
    "iso:country":"GB",
    "wof:name":"KT4 8AP",
    "wof:placetype":"postalcode"
},
  "geometry": {"coordinates":[-0.24031717755898,51.38406473637055],"type":"Point"}
}