{
  "type": "Feature",
  "properties": {
    "iso:country": "GB",
    "wof:name": "WA11 9EH",
    "wof:placetype": "postalcode"
  },
  "geometry": {"coordinates":[-2.713625,53.469591],"type":"Point"}
}
