{
  "type": "Feature",
  "properties": {
    "iso:country":"GB",
    "wof:name":"YO11 3RD",
    "wof:placetype":"postalcode"
},
  "geometry": {"coordinates":[-0.39018527558158,54.24481708481777],"type":"Point"}
}