{
  "type": "Feature",
  "properties": {
    "date:inception_lower": "1980-01-01",
    "date:inception_upper": "1980-01-01",
    "iso:country": "GB",
    "wof:name": "YO11 3RD",
    "wof:placetype": "postalcode"
  },
  "geometry": {"coordinates":[-0.390185,54.244817],"type":"Point"}
}
