{
  "type": "Feature",
  "properties": {
    "iso:country": "GB",
    "wof:name": "YO11 3RD",
    "wof:placetype": "postalcode"
  },
  "geometry": {"coordinates":[-0.390185,54.244817],"type":"Point"}
}
