{
  "type": "Feature",
  "properties": {
    "iso:country":"GB",
    "wof:name":"KA3 5LJ",
    "wof:placetype":"postalcode"
},
  "geometry": {"coordinates":[-4.52678300322899,55.70347302278235],"type":"Point"}
}