{
  "type": "Feature",
  "properties": {
    "iso:country":"GB",
    "wof:name":"G83 8SW",
    "wof:placetype":"postalcode"
},
  "geometry": {"coordinates":[-4.5824927541403,56.00200026345293],"type":"Point"}
}