{
  "type": "Feature",
  "properties": {
    "iso:country":"GB",
    "wof:name":"BN10 7QP",
    "wof:placetype":"postalcode"
},
  "geometry": {"coordinates":[-0.00184057278725,50.7989078202933],"type":"Point"}
}