{
  "type": "Feature",
  "properties": {
    "iso:country":"GB",
    "wof:name":"TR16 4LT",
    "wof:placetype":"postalcode"
},
  "geometry": {"coordinates":[-5.28278780567281,50.26080435547706],"type":"Point"}
}