{
  "type": "Feature",
  "properties": {
    "iso:country":"GB",
    "wof:name":"CF37 1BE",
    "wof:placetype":"postalcode"
},
  "geometry": {"coordinates":[-3.32668634665767,51.59574988378367],"type":"Point"}
}