{
  "type": "Feature",
  "properties": {
    "iso:country": "GB",
    "wof:name": "CF37 1BE",
    "wof:placetype": "postalcode"
  },
  "geometry": {"coordinates":[-3.326686,51.59575],"type":"Point"}
}
