{
  "type": "Feature",
  "properties": {
    "date:inception_lower":"1980-01-01",
    "date:inception_upper":"1980-01-31",
    "iso:country":"GB",
    "wof:name":"BN15 0JY",
    "wof:placetype":"postalcode"
},
  "geometry": {"coordinates":[-0.336732,50.841693],"type":"Point"}
}