{
  "type": "Feature",
  "properties": {
    "iso:country":"GB",
    "wof:name":"BN15 0JY",
    "wof:placetype":"postalcode"
},
  "geometry": {"coordinates":[-0.33673244892367,50.8416927476492],"type":"Point"}
}