{
  "type": "Feature",
  "properties": {
    "date:inception_lower": "2022-09-01",
    "date:inception_upper": "2022-09-01",
    "iso:country": "GB",
    "wof:name": "SA48 7AU",
    "wof:placetype": "postalcode"
  },
  "geometry": {"coordinates":[-4.145819,52.102764],"type":"Point"}
}
