{
  "type": "Feature",
  "properties": {
    "iso:country":"GB",
    "wof:name":"PL30 3DT",
    "wof:placetype":"postalcode"
},
  "geometry": {"coordinates":[-4.75903781626412,50.5498062292551],"type":"Point"}
}