{
  "type": "Feature",
  "properties": {
    "iso:country": "GB",
    "wof:name": "PL30 3DT",
    "wof:placetype": "postalcode"
  },
  "geometry": {"coordinates":[-4.759038,50.549806],"type":"Point"}
}
