{
  "type": "Feature",
  "properties": {
    "iso:country":"GB",
    "wof:name":"BS4 2HB",
    "wof:placetype":"postalcode"
},
  "geometry": {"coordinates":[-2.57182459780809,51.43703218558957],"type":"Point"}
}