{
  "type": "Feature",
  "properties": {
    "iso:country":"GB",
    "wof:name":"BR3 1QQ",
    "wof:placetype":"postalcode"
},
  "geometry": {"coordinates":[-0.03056651858809,51.41452165831193],"type":"Point"}
}