{
  "type": "Feature",
  "properties": {
    "iso:country":"GB",
    "wof:name":"SA33 6SS",
    "wof:placetype":"postalcode"
},
  "geometry": {"coordinates":[-4.39317030660661,51.96365713986759],"type":"Point"}
}