{
  "type": "Feature",
  "properties": {
    "date:inception_lower": "1980-01-01",
    "date:inception_upper": "1980-01-01",
    "iso:country": "GB",
    "wof:name": "NE65 9AE",
    "wof:placetype": "postalcode"
  },
  "geometry": {"coordinates":[-1.682145,55.322332],"type":"Point"}
}
