{
  "type": "Feature",
  "properties": {
    "date:inception_lower": "2017-04-01",
    "date:inception_upper": "2017-04-01",
    "iso:country": "GB",
    "wof:name": "IP13 8FB",
    "wof:placetype": "postalcode"
  },
  "geometry": {"coordinates":[1.359872,52.299152],"type":"Point"}
}
