{
  "type": "Feature",
  "properties": {
    "iso:country":"GB",
    "wof:name":"B76 2RX",
    "wof:placetype":"postalcode"
},
  "geometry": {"coordinates":[-1.79669063205365,52.54378729257231],"type":"Point"}
}