{
  "type": "Feature",
  "properties": {
    "iso:country":"GB",
    "wof:name":"LE9 9JF",
    "wof:placetype":"postalcode"
},
  "geometry": {"coordinates":[-1.29352260138384,52.62583035334639],"type":"Point"}
}