{
  "type": "Feature",
  "properties": {
    "iso:country":"GB",
    "wof:name":"RH10 9SY",
    "wof:placetype":"postalcode"
},
  "geometry": {"coordinates":[-0.1685359565463,51.12792797817975],"type":"Point"}
}