{
  "type": "Feature",
  "properties": {
    "date:inception_lower": "2007-01-01",
    "date:inception_upper": "2007-01-01",
    "iso:country": "GB",
    "wof:name": "GL7 3WS",
    "wof:placetype": "postalcode"
  },
  "geometry": {"coordinates":[-1.781598,51.707687],"type":"Point"}
}
