{
  "type": "Feature",
  "properties": {
    "iso:country": "GB",
    "wof:name": "LL15 2EN",
    "wof:placetype": "postalcode"
  },
  "geometry": {"coordinates":[-3.298753,53.087356],"type":"Point"}
}
