{
  "type": "Feature",
  "properties": {
    "iso:country": "GB",
    "wof:name": "DG1 4QH",
    "wof:placetype": "postalcode"
  },
  "geometry": {"coordinates":[-3.573198,55.060603],"type":"Point"}
}
