{
  "type": "Feature",
  "properties": {
    "iso:country":"GB",
    "wof:name":"DG1 4QH",
    "wof:placetype":"postalcode"
},
  "geometry": {"coordinates":[-3.57319819500893,55.06060312621226],"type":"Point"}
}