{
  "type": "Feature",
  "properties": {
    "date:inception_lower": "2000-12-01",
    "date:inception_upper": "2000-12-01",
    "iso:country": "GB",
    "wof:name": "W1T 6DJ",
    "wof:placetype": "postalcode"
  },
  "geometry": {"coordinates":[-0.140866,51.522624],"type":"Point"}
}
