{
  "type": "Feature",
  "properties": {
    "iso:country":"GB",
    "wof:name":"W1T 6DJ",
    "wof:placetype":"postalcode"
},
  "geometry": {"coordinates":[-0.14086628683713,51.52262448615327],"type":"Point"}
}