{
  "type": "Feature",
  "properties": {
    "iso:country": "GB",
    "wof:name": "W1T 6DJ",
    "wof:placetype": "postalcode"
  },
  "geometry": {"coordinates":[-0.140866,51.522624],"type":"Point"}
}
