{
  "type": "Feature",
  "properties": {
    "iso:country": "GB",
    "wof:name": "B36 0RW",
    "wof:placetype": "postalcode"
  },
  "geometry": {"coordinates":[-1.750135,52.5055],"type":"Point"}
}
