{
  "type": "Feature",
  "properties": {
    "iso:country":"GB",
    "wof:name":"ME11 5AY",
    "wof:placetype":"postalcode"
},
  "geometry": {"coordinates":[0.74747734010636,51.41607332637029],"type":"Point"}
}