{
  "type": "Feature",
  "properties": {
    "iso:country":"GB",
    "wof:name":"M18 8PF",
    "wof:placetype":"postalcode"
},
  "geometry": {"coordinates":[-2.16539174811339,53.46412968596408],"type":"Point"}
}