{
  "type": "Feature",
  "properties": {
    "iso:country":"GB",
    "wof:name":"IP29 5SS",
    "wof:placetype":"postalcode"
},
  "geometry": {"coordinates":[0.67228154440462,52.22213511105519],"type":"Point"}
}