{
  "type": "Feature",
  "properties": {
    "iso:country":"GB",
    "wof:name":"OL9 0EQ",
    "wof:placetype":"postalcode"
},
  "geometry": {"coordinates":[-2.13750780317335,53.5514244861904],"type":"Point"}
}