{
  "type": "Feature",
  "properties": {
    "date:inception_lower":"1980-01-01",
    "date:inception_upper":"1980-01-31",
    "iso:country":"GB",
    "wof:name":"OL9 0EQ",
    "wof:placetype":"postalcode"
},
  "geometry": {"coordinates":[-2.137508,53.551424],"type":"Point"}
}