{
  "type": "Feature",
  "properties": {
    "date:inception_lower": "1980-01-01",
    "date:inception_upper": "1980-01-01",
    "iso:country": "GB",
    "wof:name": "EH4 7EG",
    "wof:placetype": "postalcode"
  },
  "geometry": {"coordinates":[-3.285718,55.955483],"type":"Point"}
}
