{
  "type": "Feature",
  "properties": {
    "iso:country": "GB",
    "wof:name": "PO16 7SE",
    "wof:placetype": "postalcode"
  },
  "geometry": {"coordinates":[-1.184205,50.85331],"type":"Point"}
}
