{
  "type": "Feature",
  "properties": {
    "date:inception_lower": "1980-01-01",
    "date:inception_upper": "1980-01-01",
    "iso:country": "GB",
    "wof:name": "PO16 7SE",
    "wof:placetype": "postalcode"
  },
  "geometry": {"coordinates":[-1.184205,50.85331],"type":"Point"}
}
