{
  "type": "Feature",
  "properties": {
    "date:inception_lower": "1996-06-01",
    "date:inception_upper": "1996-06-01",
    "iso:country": "GB",
    "wof:name": "PR6 8ED",
    "wof:placetype": "postalcode"
  },
  "geometry": {"coordinates":[-2.572835,53.70331],"type":"Point"}
}
