{
  "type": "Feature",
  "properties": {
    "iso:country":"GB",
    "wof:name":"FY2 0PH",
    "wof:placetype":"postalcode"
},
  "geometry": {"coordinates":[-3.02510342785268,53.86039457154327],"type":"Point"}
}