{
  "type": "Feature",
  "properties": {
    "iso:country":"GB",
    "wof:name":"HG1 4PY",
    "wof:placetype":"postalcode"
},
  "geometry": {"coordinates":[-1.50021171463142,53.99921822326648],"type":"Point"}
}