{
  "type": "Feature",
  "properties": {
    "iso:country": "GB",
    "wof:name": "HG1 4PY",
    "wof:placetype": "postalcode"
  },
  "geometry": {"coordinates":[-1.500212,53.999218],"type":"Point"}
}
