{
  "type": "Feature",
  "properties": {
    "iso:country":"GB",
    "wof:name":"B33 8RQ",
    "wof:placetype":"postalcode"
},
  "geometry": {"coordinates":[-1.8029663857141,52.47910640096732],"type":"Point"}
}