{
  "type": "Feature",
  "properties": {
    "iso:country":"GB",
    "wof:name":"NG15 7GA",
    "wof:placetype":"postalcode"
},
  "geometry": {"coordinates":[-1.20731108247387,53.03660667102221],"type":"Point"}
}