{
  "type": "Feature",
  "properties": {
    "date:inception_lower": "2023-04-01",
    "date:inception_upper": "2023-04-01",
    "iso:country": "GB",
    "wof:name": "EH51 9UJ",
    "wof:placetype": "postalcode"
  },
  "geometry": {"coordinates":[-3.592512,56.005649],"type":"Point"}
}
