{
  "type": "Feature",
  "properties": {
    "iso:country":"GB",
    "wof:name":"PA8 7DG",
    "wof:placetype":"postalcode"
},
  "geometry": {"coordinates":[-4.42654263516592,55.89691187501734],"type":"Point"}
}