{
  "type": "Feature",
  "properties": {
    "iso:country": "GB",
    "wof:name": "CF14 5AH",
    "wof:placetype": "postalcode"
  },
  "geometry": {"coordinates":[-3.191343,51.534718],"type":"Point"}
}
