{
  "type": "Feature",
  "properties": {
    "iso:country":"GB",
    "wof:name":"CF14 5AH",
    "wof:placetype":"postalcode"
},
  "geometry": {"coordinates":[-3.19134333139415,51.5347179101877],"type":"Point"}
}