{
  "type": "Feature",
  "properties": {
    "date:inception_lower": "1980-01-01",
    "date:inception_upper": "1980-01-01",
    "iso:country": "GB",
    "wof:name": "S6 6EA",
    "wof:placetype": "postalcode"
  },
  "geometry": {"coordinates":[-1.550586,53.39008],"type":"Point"}
}
