{
  "type": "Feature",
  "properties": {
    "iso:country":"GB",
    "wof:name":"LS12 5EH",
    "wof:placetype":"postalcode"
},
  "geometry": {"coordinates":[-1.6308385762884,53.77307869920607],"type":"Point"}
}