{
  "type": "Feature",
  "properties": {
    "iso:country": "GB",
    "wof:name": "LS12 5EH",
    "wof:placetype": "postalcode"
  },
  "geometry": {"coordinates":[-1.630839,53.773079],"type":"Point"}
}
