{
  "type": "Feature",
  "properties": {
    "iso:country": "GB",
    "wof:name": "CO5 0AP",
    "wof:placetype": "postalcode"
  },
  "geometry": {"coordinates":[0.747273,51.809406],"type":"Point"}
}
