{
  "type": "Feature",
  "properties": {
    "iso:country":"GB",
    "wof:name":"SS16 4HA",
    "wof:placetype":"postalcode"
},
  "geometry": {"coordinates":[0.4807918149151,51.56607077078079],"type":"Point"}
}