{
  "type": "Feature",
  "properties": {
    "date:inception_lower": "2023-01-01",
    "date:inception_upper": "2023-01-01",
    "iso:country": "GB",
    "wof:name": "TN22 4DG",
    "wof:placetype": "postalcode"
  },
  "geometry": {"coordinates":[0.132785,50.990496],"type":"Point"}
}
