{
  "type": "Feature",
  "properties": {
    "iso:country": "GB",
    "wof:name": "EH21 7HR",
    "wof:placetype": "postalcode"
  },
  "geometry": {"coordinates":[-3.039389,55.939387],"type":"Point"}
}
