{
  "type": "Feature",
  "properties": {
    "date:inception_lower": "2021-05-01",
    "date:inception_upper": "2021-05-01",
    "iso:country": "GB",
    "wof:name": "CV37 9PR",
    "wof:placetype": "postalcode"
  },
  "geometry": {"coordinates":[-1.727362,52.197757],"type":"Point"}
}
