{
  "type": "Feature",
  "properties": {
    "iso:country":"GB",
    "wof:name":"WF2 0RX",
    "wof:placetype":"postalcode"
},
  "geometry": {"coordinates":[-1.54727611974779,53.7015795206403],"type":"Point"}
}