{
  "type": "Feature",
  "properties": {
    "iso:country":"GB",
    "wof:name":"WF15 8AT",
    "wof:placetype":"postalcode"
},
  "geometry": {"coordinates":[-1.71305153332018,53.69639242457016],"type":"Point"}
}