{
  "type": "Feature",
  "properties": {
    "iso:country":"GB",
    "wof:name":"CT21 5JS",
    "wof:placetype":"postalcode"
},
  "geometry": {"coordinates":[1.09006686231143,51.07216902262429],"type":"Point"}
}