{
  "type": "Feature",
  "properties": {
    "iso:country":"GB",
    "wof:name":"TR20 8TJ",
    "wof:placetype":"postalcode"
},
  "geometry": {"coordinates":[-5.56543157882368,50.11240735520099],"type":"Point"}
}