{
  "type": "Feature",
  "properties": {
    "iso:country":"GB",
    "wof:name":"KA24 5AY",
    "wof:placetype":"postalcode"
},
  "geometry": {"coordinates":[-4.71657636460713,55.70857798363434],"type":"Point"}
}