{
  "type": "Feature",
  "properties": {
    "iso:country": "GB",
    "wof:name": "CA4 0AS",
    "wof:placetype": "postalcode"
  },
  "geometry": {"coordinates":[-2.8392,54.854823],"type":"Point"}
}
