{
  "type": "Feature",
  "properties": {
    "iso:country":"GB",
    "wof:name":"B23 7AU",
    "wof:placetype":"postalcode"
},
  "geometry": {"coordinates":[-1.87340746973693,52.53481424026192],"type":"Point"}
}