{
  "type": "Feature",
  "properties": {
    "iso:country":"GB",
    "wof:name":"HA8 7NL",
    "wof:placetype":"postalcode"
},
  "geometry": {"coordinates":[-0.2798303166396,51.61196070933675],"type":"Point"}
}