{
  "type": "Feature",
  "properties": {
    "iso:country": "GB",
    "wof:name": "TW19 7RE",
    "wof:placetype": "postalcode"
  },
  "geometry": {"coordinates":[-0.476732,51.449495],"type":"Point"}
}
