{
  "type": "Feature",
  "properties": {
    "date:inception_lower": "2020-11-01",
    "date:inception_upper": "2020-11-01",
    "iso:country": "GB",
    "wof:name": "PL13 2FS",
    "wof:placetype": "postalcode"
  },
  "geometry": {"coordinates":[-4.529565,50.37183],"type":"Point"}
}
