{
  "type": "Feature",
  "properties": {
    "iso:country": "GB",
    "wof:name": "PO13 8NR",
    "wof:placetype": "postalcode"
  },
  "geometry": {"coordinates":[-1.167835,50.80252],"type":"Point"}
}
