{
  "type": "Feature",
  "properties": {
    "iso:country":"GB",
    "wof:name":"LL60 6DA",
    "wof:placetype":"postalcode"
},
  "geometry": {"coordinates":[-4.27729104042268,53.22274522541692],"type":"Point"}
}