{
  "type": "Feature",
  "properties": {
    "iso:country": "GB",
    "wof:name": "LE9 3GG",
    "wof:placetype": "postalcode"
  },
  "geometry": {"coordinates":[-1.24539,52.553974],"type":"Point"}
}
