{
  "type": "Feature",
  "properties": {
    "iso:country":"GB",
    "wof:name":"LE9 3GG",
    "wof:placetype":"postalcode"
},
  "geometry": {"coordinates":[-1.24540022147605,52.55395540201837],"type":"Point"}
}