{
  "type": "Feature",
  "properties": {
    "iso:country":"GB",
    "wof:name":"KA12 0LU",
    "wof:placetype":"postalcode"
},
  "geometry": {"coordinates":[-4.65523178458888,55.61487418209911],"type":"Point"}
}