{
  "type": "Feature",
  "properties": {
    "iso:country":"GB",
    "wof:name":"GU22 9PB",
    "wof:placetype":"postalcode"
},
  "geometry": {"coordinates":[-0.56064797355425,51.30011463380815],"type":"Point"}
}