{
  "type": "Feature",
  "properties": {
    "date:inception_lower": "1995-12-01",
    "date:inception_upper": "1995-12-01",
    "iso:country": "GB",
    "wof:name": "RH15 9XD",
    "wof:placetype": "postalcode"
  },
  "geometry": {"coordinates":[-0.156277,50.962208],"type":"Point"}
}
