{
  "type": "Feature",
  "properties": {
    "iso:country":"GB",
    "wof:name":"LE3 2SF",
    "wof:placetype":"postalcode"
},
  "geometry": {"coordinates":[-1.17571978824586,52.61640322480546],"type":"Point"}
}