{
  "type": "Feature",
  "properties": {
    "iso:country":"GB",
    "wof:name":"ME8 6PY",
    "wof:placetype":"postalcode"
},
  "geometry": {"coordinates":[0.58172606925583,51.3790752530436],"type":"Point"}
}