{
  "type": "Feature",
  "properties": {
    "iso:country":"GB",
    "wof:name":"BB3 2EH",
    "wof:placetype":"postalcode"
},
  "geometry": {"coordinates":[-2.45546639227786,53.68055271911992],"type":"Point"}
}