{
  "type": "Feature",
  "properties": {
    "iso:country":"GB",
    "wof:name":"DT4 8PB",
    "wof:placetype":"postalcode"
},
  "geometry": {"coordinates":[-2.45372492296399,50.61066586036093],"type":"Point"}
}