{
  "type": "Feature",
  "properties": {
    "iso:country":"GB",
    "wof:name":"KA10 6TD",
    "wof:placetype":"postalcode"
},
  "geometry": {"coordinates":[-4.65475445019362,55.56340585624519],"type":"Point"}
}