{
  "type": "Feature",
  "properties": {
    "iso:country": "GB",
    "wof:name": "KA10 6TD",
    "wof:placetype": "postalcode"
  },
  "geometry": {"coordinates":[-4.654754,55.563406],"type":"Point"}
}
