{
  "type": "Feature",
  "properties": {
    "iso:country": "GB",
    "wof:name": "CW1 3YE",
    "wof:placetype": "postalcode"
  },
  "geometry": {"coordinates":[-2.455888,53.116406],"type":"Point"}
}
