{
  "type": "Feature",
  "properties": {
    "date:inception_lower":"1983-03-01",
    "date:inception_upper":"1983-03-31",
    "iso:country":"GB",
    "wof:name":"CW1 3YE",
    "wof:placetype":"postalcode"
},
  "geometry": {"coordinates":[-2.455888,53.116406],"type":"Point"}
}