{
  "type": "Feature",
  "properties": {
    "iso:country":"GB",
    "wof:name":"CW1 3YE",
    "wof:placetype":"postalcode"
},
  "geometry": {"coordinates":[-2.45588815307162,53.11640599695936],"type":"Point"}
}