{
  "type": "Feature",
  "properties": {
    "date:inception_lower": "1991-09-01",
    "date:inception_upper": "1991-09-01",
    "iso:country": "GB",
    "wof:name": "B20 2LR",
    "wof:placetype": "postalcode"
  },
  "geometry": {"coordinates":[-1.918915,52.519904],"type":"Point"}
}
