{
  "type": "Feature",
  "properties": {
    "iso:country": "GB",
    "wof:name": "LE67 4JW",
    "wof:placetype": "postalcode"
  },
  "geometry": {"coordinates":[-1.36138,52.726002],"type":"Point"}
}
