{
  "type": "Feature",
  "properties": {
    "date:inception_lower": "2019-03-01",
    "date:inception_upper": "2019-03-01",
    "iso:country": "GB",
    "wof:name": "IP19 1BB",
    "wof:placetype": "postalcode"
  },
  "geometry": {"coordinates":[1.502288,52.345687],"type":"Point"}
}
