{
  "type": "Feature",
  "properties": {
    "iso:country":"GB",
    "wof:name":"GU10 5HU",
    "wof:placetype":"postalcode"
},
  "geometry": {"coordinates":[-0.87475024959692,51.19008075383264],"type":"Point"}
}