{
  "type": "Feature",
  "properties": {
    "iso:country":"GB",
    "wof:name":"S65 1RJ",
    "wof:placetype":"postalcode"
},
  "geometry": {"coordinates":[-1.35157634720959,53.43772289195924],"type":"Point"}
}