{
  "type": "Feature",
  "properties": {
    "iso:country":"GB",
    "wof:name":"SN8 1QR",
    "wof:placetype":"postalcode"
},
  "geometry": {"coordinates":[-1.87689222434346,51.42025460326251],"type":"Point"}
}