{
  "type": "Feature",
  "properties": {
    "iso:country": "GB",
    "wof:name": "SN8 1QR",
    "wof:placetype": "postalcode"
  },
  "geometry": {"coordinates":[-1.876892,51.420255],"type":"Point"}
}
