{
  "type": "Feature",
  "properties": {
    "iso:country":"GB",
    "wof:name":"L8 7QE",
    "wof:placetype":"postalcode"
},
  "geometry": {"coordinates":[-2.95455828778584,53.39783106032775],"type":"Point"}
}