{
  "type": "Feature",
  "properties": {
    "iso:country":"GB",
    "wof:name":"LL55 2TB",
    "wof:placetype":"postalcode"
},
  "geometry": {"coordinates":[-4.24800741173603,53.12468989145186],"type":"Point"}
}