{
  "type": "Feature",
  "properties": {
    "iso:country": "GB",
    "wof:name": "LL55 2TB",
    "wof:placetype": "postalcode"
  },
  "geometry": {"coordinates":[-4.248007,53.12469],"type":"Point"}
}
