{
  "type": "Feature",
  "properties": {
    "iso:country":"GB",
    "wof:name":"DA1 3DU",
    "wof:placetype":"postalcode"
},
  "geometry": {"coordinates":[0.20645457319165,51.44739468350287],"type":"Point"}
}