{
  "type": "Feature",
  "properties": {
    "iso:country":"GB",
    "wof:name":"ST8 6AS",
    "wof:placetype":"postalcode"
},
  "geometry": {"coordinates":[-2.17652369260251,53.11546762261402],"type":"Point"}
}