{
  "type": "Feature",
  "properties": {
    "iso:country":"GB",
    "wof:name":"IP13 8LR",
    "wof:placetype":"postalcode"
},
  "geometry": {"coordinates":[1.38845941825212,52.27700700932093],"type":"Point"}
}