{
  "type": "Feature",
  "properties": {
    "date:inception_lower": "2013-08-01",
    "date:inception_upper": "2013-08-01",
    "iso:country": "GB",
    "wof:name": "UB2 4FF",
    "wof:placetype": "postalcode"
  },
  "geometry": {"coordinates":[-0.380133,51.504456],"type":"Point"}
}
