{
  "type": "Feature",
  "properties": {
    "date:inception_lower": "2021-03-01",
    "date:inception_upper": "2021-03-01",
    "iso:country": "GB",
    "wof:name": "YO13 0FJ",
    "wof:placetype": "postalcode"
  },
  "geometry": {"coordinates":[-0.429925,54.301275],"type":"Point"}
}
