{
  "type": "Feature",
  "properties": {
    "iso:country":"GB",
    "wof:name":"SO19 4AA",
    "wof:placetype":"postalcode"
},
  "geometry": {"coordinates":[-1.36526892427167,50.91360576253933],"type":"Point"}
}