{
  "type": "Feature",
  "properties": {
    "iso:country":"GB",
    "wof:name":"S71 4NW",
    "wof:placetype":"postalcode"
},
  "geometry": {"coordinates":[-1.4514789809767,53.59474891951955],"type":"Point"}
}