{
  "type": "Feature",
  "properties": {
    "iso:country": "GB",
    "wof:name": "S71 4NW",
    "wof:placetype": "postalcode"
  },
  "geometry": {"coordinates":[-1.451479,53.594749],"type":"Point"}
}
