{
  "type": "Feature",
  "properties": {
    "date:inception_lower": "1980-01-01",
    "date:inception_upper": "1980-01-01",
    "iso:country": "GB",
    "wof:name": "MK14 6AY",
    "wof:placetype": "postalcode"
  },
  "geometry": {"coordinates":[-0.763851,52.067158],"type":"Point"}
}
