{
  "type": "Feature",
  "properties": {
    "iso:country":"GB",
    "wof:name":"HU8 7TH",
    "wof:placetype":"postalcode"
},
  "geometry": {"coordinates":[-0.32108910499162,53.75922328869729],"type":"Point"}
}