{
  "type": "Feature",
  "properties": {
    "iso:country":"GB",
    "wof:name":"TN39 3XA",
    "wof:placetype":"postalcode"
},
  "geometry": {"coordinates":[0.46548113616517,50.84479281744718],"type":"Point"}
}