{
  "type": "Feature",
  "properties": {
    "iso:country":"GB",
    "wof:name":"EC1V 0JA",
    "wof:placetype":"postalcode"
},
  "geometry": {"coordinates":[-0.10082064440951,51.52714464631891],"type":"Point"}
}