{
  "type": "Feature",
  "properties": {
    "iso:country": "GB",
    "wof:name": "EC1V 0JA",
    "wof:placetype": "postalcode"
  },
  "geometry": {"coordinates":[-0.101667,51.527305],"type":"Point"}
}
