{
  "type": "Feature",
  "properties": {
    "iso:country":"GB",
    "wof:name":"NP4 9AE",
    "wof:placetype":"postalcode"
},
  "geometry": {"coordinates":[-3.08694105148727,51.77320893435574],"type":"Point"}
}