{
  "type": "Feature",
  "properties": {
    "iso:country": "GB",
    "wof:name": "NP4 9AE",
    "wof:placetype": "postalcode"
  },
  "geometry": {"coordinates":[-3.086948,51.773213],"type":"Point"}
}
