{
  "type": "Feature",
  "properties": {
    "iso:country":"GB",
    "wof:name":"PE1 3QG",
    "wof:placetype":"postalcode"
},
  "geometry": {"coordinates":[-0.24622660411174,52.59148148340967],"type":"Point"}
}