{
  "type": "Feature",
  "properties": {
    "date:inception_lower": "1990-02-01",
    "date:inception_upper": "1990-02-01",
    "iso:country": "GB",
    "wof:name": "HU3 3QN",
    "wof:placetype": "postalcode"
  },
  "geometry": {"coordinates":[-0.375011,53.738168],"type":"Point"}
}
