{
  "type": "Feature",
  "properties": {
    "iso:country":"GB",
    "wof:name":"RG9 4ND",
    "wof:placetype":"postalcode"
},
  "geometry": {"coordinates":[-0.94366404699272,51.4993927533674],"type":"Point"}
}