{
  "type": "Feature",
  "properties": {
    "iso:country":"GB",
    "wof:name":"B93 9NT",
    "wof:placetype":"postalcode"
},
  "geometry": {"coordinates":[-1.73880017479835,52.39439492560102],"type":"Point"}
}