{
  "type": "Feature",
  "properties": {
    "iso:country":"GB",
    "wof:name":"PA17 5BE",
    "wof:placetype":"postalcode"
},
  "geometry": {"coordinates":[-4.87947483285414,55.87102845284687],"type":"Point"}
}