{
  "type": "Feature",
  "properties": {
    "iso:country": "GB",
    "wof:name": "DE7 4DE",
    "wof:placetype": "postalcode"
  },
  "geometry": {"coordinates":[-1.304996,52.958498],"type":"Point"}
}
