{
  "type": "Feature",
  "properties": {
    "iso:country":"GB",
    "wof:name":"NN5 7DP",
    "wof:placetype":"postalcode"
},
  "geometry": {"coordinates":[-0.91242366999168,52.24226322002147],"type":"Point"}
}