{
  "type": "Feature",
  "properties": {
    "date:inception_lower":"1980-01-01",
    "date:inception_upper":"1980-01-31",
    "iso:country":"GB",
    "wof:name":"NE2 3HP",
    "wof:placetype":"postalcode"
},
  "geometry": {"coordinates":[-1.609605,54.994715],"type":"Point"}
}