{
  "type": "Feature",
  "properties": {
    "iso:country": "GB",
    "wof:name": "NE2 3HP",
    "wof:placetype": "postalcode"
  },
  "geometry": {"coordinates":[-1.609605,54.994715],"type":"Point"}
}
