{
  "type": "Feature",
  "properties": {
    "date:inception_lower": "1980-01-01",
    "date:inception_upper": "1980-01-01",
    "iso:country": "GB",
    "wof:name": "DN35 7LE",
    "wof:placetype": "postalcode"
  },
  "geometry": {"coordinates":[-0.036459,53.564406],"type":"Point"}
}
