{
  "type": "Feature",
  "properties": {
    "iso:country":"GB",
    "wof:name":"TQ12 3PY",
    "wof:placetype":"postalcode"
},
  "geometry": {"coordinates":[-3.59893079977889,50.56349296584124],"type":"Point"}
}