{
  "type": "Feature",
  "properties": {
    "iso:country":"GB",
    "wof:name":"W11 3QA",
    "wof:placetype":"postalcode"
},
  "geometry": {"coordinates":[-0.197832960826,51.50914362934278],"type":"Point"}
}