{
  "type": "Feature",
  "properties": {
    "iso:country": "GB",
    "wof:name": "MK18 2EA",
    "wof:placetype": "postalcode"
  },
  "geometry": {"coordinates":[-0.927642,51.980849],"type":"Point"}
}
