{
  "type": "Feature",
  "properties": {
    "date:inception_lower": "1981-06-01",
    "date:inception_upper": "1981-06-01",
    "iso:country": "GB",
    "wof:name": "WR5 1JL",
    "wof:placetype": "postalcode"
  },
  "geometry": {"coordinates":[-2.194758,52.194456],"type":"Point"}
}
