{
  "type": "Feature",
  "properties": {
    "iso:country":"GB",
    "wof:name":"WR5 1JL",
    "wof:placetype":"postalcode"
},
  "geometry": {"coordinates":[-2.19476209448581,52.19441693117019],"type":"Point"}
}