{
  "type": "Feature",
  "properties": {
    "date:inception_lower":"1995-12-01",
    "date:inception_upper":"1995-12-31",
    "iso:country":"GB",
    "wof:name":"EH45 8EQ",
    "wof:placetype":"postalcode"
},
  "geometry": {"coordinates":[-3.193376,55.656488],"type":"Point"}
}