{
  "type": "Feature",
  "properties": {
    "iso:country": "GB",
    "wof:name": "RM12 5AR",
    "wof:placetype": "postalcode"
  },
  "geometry": {"coordinates":[0.200373,51.536962],"type":"Point"}
}
