{
  "type": "Feature",
  "properties": {
    "iso:country":"GB",
    "wof:name":"HX3 9UD",
    "wof:placetype":"postalcode"
},
  "geometry": {"coordinates":[-1.84486885976802,53.7229884534042],"type":"Point"}
}