{
  "type": "Feature",
  "properties": {
    "iso:country":"GB",
    "wof:name":"WA11 9ND",
    "wof:placetype":"postalcode"
},
  "geometry": {"coordinates":[-2.72935194552943,53.47132926649557],"type":"Point"}
}