{
  "type": "Feature",
  "properties": {
    "iso:country":"GB",
    "wof:name":"NE4 9QX",
    "wof:placetype":"postalcode"
},
  "geometry": {"coordinates":[-1.65595476486328,54.97758283963814],"type":"Point"}
}