{
  "type": "Feature",
  "properties": {
    "iso:country": "GB",
    "wof:name": "NE4 9QX",
    "wof:placetype": "postalcode"
  },
  "geometry": {"coordinates":[-1.655955,54.977583],"type":"Point"}
}
