{
  "type": "Feature",
  "properties": {
    "iso:country":"GB",
    "wof:name":"NE22 5HR",
    "wof:placetype":"postalcode"
},
  "geometry": {"coordinates":[-1.57217341463206,55.13546456306452],"type":"Point"}
}