{
  "type": "Feature",
  "properties": {
    "iso:country":"GB",
    "wof:name":"G22 6EW",
    "wof:placetype":"postalcode"
},
  "geometry": {"coordinates":[-4.24271614830372,55.88716955036738],"type":"Point"}
}