{
  "type": "Feature",
  "properties": {
    "iso:country":"GB",
    "wof:name":"HR1 2TE",
    "wof:placetype":"postalcode"
},
  "geometry": {"coordinates":[-2.70023204828312,52.06026419049768],"type":"Point"}
}