{
  "type": "Feature",
  "properties": {
    "date:inception_lower": "2008-01-01",
    "date:inception_upper": "2008-01-01",
    "iso:country": "GB",
    "wof:name": "HR1 2TE",
    "wof:placetype": "postalcode"
  },
  "geometry": {"coordinates":[-2.700232,52.060264],"type":"Point"}
}
