{
  "type": "Feature",
  "properties": {
    "iso:country":"GB",
    "wof:name":"OX17 3ND",
    "wof:placetype":"postalcode"
},
  "geometry": {"coordinates":[-1.31140877923748,52.0171980791053],"type":"Point"}
}