{
  "type": "Feature",
  "properties": {
    "date:inception_lower":"1980-01-01",
    "date:inception_upper":"1980-01-31",
    "iso:country":"GB",
    "wof:name":"OX17 3ND",
    "wof:placetype":"postalcode"
},
  "geometry": {"coordinates":[-1.311409,52.017198],"type":"Point"}
}