{
  "type": "Feature",
  "properties": {
    "date:inception_lower": "1980-01-01",
    "date:inception_upper": "1980-01-01",
    "iso:country": "GB",
    "wof:name": "OX17 3ND",
    "wof:placetype": "postalcode"
  },
  "geometry": {"coordinates":[-1.310967,52.017377],"type":"Point"}
}
