{
  "type": "Feature",
  "properties": {
    "date:inception_lower": "2022-06-01",
    "date:inception_upper": "2022-06-01",
    "iso:country": "GB",
    "wof:name": "IP8 3GG",
    "wof:placetype": "postalcode"
  },
  "geometry": {"coordinates":[1.077694,52.033715],"type":"Point"}
}
