{
  "type": "Feature",
  "properties": {
    "iso:country": "GB",
    "wof:name": "HR4 7SF",
    "wof:placetype": "postalcode"
  },
  "geometry": {"coordinates":[-2.759846,52.096424],"type":"Point"}
}
