{
  "type": "Feature",
  "properties": {
    "iso:country":"GB",
    "wof:name":"ME13 7SS",
    "wof:placetype":"postalcode"
},
  "geometry": {"coordinates":[0.88217329631314,51.31830774326459],"type":"Point"}
}