{
  "type": "Feature",
  "properties": {
    "date:inception_lower": "1992-08-01",
    "date:inception_upper": "1992-08-01",
    "iso:country": "GB",
    "wof:name": "LL19 7SB",
    "wof:placetype": "postalcode"
  },
  "geometry": {"coordinates":[-3.408348,53.33694],"type":"Point"}
}
