{
  "type": "Feature",
  "properties": {
    "iso:country":"GB",
    "wof:name":"BN22 7SN",
    "wof:placetype":"postalcode"
},
  "geometry": {"coordinates":[0.30650392613679,50.78460093472564],"type":"Point"}
}