{
  "type": "Feature",
  "properties": {
    "iso:country":"GB",
    "wof:name":"DE23 6JE",
    "wof:placetype":"postalcode"
},
  "geometry": {"coordinates":[-1.50863458916456,52.90120833804939],"type":"Point"}
}