{
  "type": "Feature",
  "properties": {
    "date:inception_lower": "1980-01-01",
    "date:inception_upper": "1980-01-01",
    "iso:country": "GB",
    "wof:name": "BA12 8BY",
    "wof:placetype": "postalcode"
  },
  "geometry": {"coordinates":[-2.189879,51.197286],"type":"Point"}
}
