{
  "type": "Feature",
  "properties": {
    "iso:country": "GB",
    "wof:name": "CH42 1LG",
    "wof:placetype": "postalcode"
  },
  "geometry": {"coordinates":[-3.010906,53.376],"type":"Point"}
}
