{
  "type": "Feature",
  "properties": {
    "date:inception_lower": "1980-01-01",
    "date:inception_upper": "1980-01-01",
    "iso:country": "GB",
    "wof:name": "BB7 3AQ",
    "wof:placetype": "postalcode"
  },
  "geometry": {"coordinates":[-2.432422,53.99425],"type":"Point"}
}
