{
  "type": "Feature",
  "properties": {
    "iso:country":"GB",
    "wof:name":"BB7 3AQ",
    "wof:placetype":"postalcode"
},
  "geometry": {"coordinates":[-2.43314017211084,53.98861762924479],"type":"Point"}
}