{
  "type": "Feature",
  "properties": {
    "iso:country":"GB",
    "wof:name":"G44 3ET",
    "wof:placetype":"postalcode"
},
  "geometry": {"coordinates":[-4.27517179831137,55.8113392537234],"type":"Point"}
}