{
  "type": "Feature",
  "properties": {
    "date:inception_lower": "1980-01-01",
    "date:inception_upper": "1980-01-01",
    "iso:country": "GB",
    "wof:name": "G44 3ET",
    "wof:placetype": "postalcode"
  },
  "geometry": {"coordinates":[-4.275172,55.811339],"type":"Point"}
}
