{
  "type": "Feature",
  "properties": {
    "iso:country": "GB",
    "wof:name": "GL2 0RY",
    "wof:placetype": "postalcode"
  },
  "geometry": {"coordinates":[-2.219479,51.865954],"type":"Point"}
}
