{
  "type": "Feature",
  "properties": {
    "iso:country":"GB",
    "wof:name":"GL2 0RY",
    "wof:placetype":"postalcode"
},
  "geometry": {"coordinates":[-2.21947938159549,51.86595354456873],"type":"Point"}
}