{
  "type": "Feature",
  "properties": {
    "iso:country": "GB",
    "wof:name": "CM7 4FE",
    "wof:placetype": "postalcode"
  },
  "geometry": {"coordinates":[0.44062,51.942811],"type":"Point"}
}
