{
  "type": "Feature",
  "properties": {
    "date:inception_lower": "2019-07-01",
    "date:inception_upper": "2019-07-01",
    "iso:country": "GB",
    "wof:name": "CM7 4FE",
    "wof:placetype": "postalcode"
  },
  "geometry": {"coordinates":[0.44062,51.942811],"type":"Point"}
}
