{
  "type": "Feature",
  "properties": {
    "iso:country":"GB",
    "wof:name":"SK11 9PB",
    "wof:placetype":"postalcode"
},
  "geometry": {"coordinates":[-2.18299161972152,53.26261495938947],"type":"Point"}
}