{
  "type": "Feature",
  "properties": {
    "date:inception_lower": "2014-08-01",
    "date:inception_upper": "2014-08-01",
    "iso:country": "GB",
    "wof:name": "TS17 5NH",
    "wof:placetype": "postalcode"
  },
  "geometry": {"coordinates":[-1.324632,54.524046],"type":"Point"}
}
