{
  "type": "Feature",
  "properties": {
    "iso:country":"GB",
    "wof:name":"TS17 5NH",
    "wof:placetype":"postalcode"
},
  "geometry": {"coordinates":[-1.32463231608551,54.52404561605071],"type":"Point"}
}