{
  "type": "Feature",
  "properties": {
    "iso:country": "GB",
    "wof:name": "SA18 2NG",
    "wof:placetype": "postalcode"
  },
  "geometry": {"coordinates":[-3.97886,51.795133],"type":"Point"}
}
