{
  "type": "Feature",
  "properties": {
    "iso:country":"GB",
    "wof:name":"M5 4LT",
    "wof:placetype":"postalcode"
},
  "geometry": {"coordinates":[-2.27088843571673,53.48057453976674],"type":"Point"}
}