{
  "type": "Feature",
  "properties": {
    "iso:country":"GB",
    "wof:name":"GL54 1HR",
    "wof:placetype":"postalcode"
},
  "geometry": {"coordinates":[-1.71080859413974,51.92426271641728],"type":"Point"}
}