{
  "type": "Feature",
  "properties": {
    "iso:country":"GB",
    "wof:name":"EH19 3HR",
    "wof:placetype":"postalcode"
},
  "geometry": {"coordinates":[-3.09739159793646,55.87087358427885],"type":"Point"}
}