{
  "type": "Feature",
  "properties": {
    "iso:country": "GB",
    "wof:name": "EH19 3HR",
    "wof:placetype": "postalcode"
  },
  "geometry": {"coordinates":[-3.097392,55.870874],"type":"Point"}
}
