{
  "type": "Feature",
  "properties": {
    "iso:country":"GB",
    "wof:name":"PE1 5SW",
    "wof:placetype":"postalcode"
},
  "geometry": {"coordinates":[-0.21066003599257,52.5737677219414],"type":"Point"}
}