{
  "type": "Feature",
  "properties": {
    "iso:country": "GB",
    "wof:name": "PE1 5SW",
    "wof:placetype": "postalcode"
  },
  "geometry": {"coordinates":[-0.21066,52.573768],"type":"Point"}
}
