{
  "type": "Feature",
  "properties": {
    "date:inception_lower": "1994-12-01",
    "date:inception_upper": "1994-12-01",
    "iso:country": "GB",
    "wof:name": "PE1 5SW",
    "wof:placetype": "postalcode"
  },
  "geometry": {"coordinates":[-0.21066,52.573768],"type":"Point"}
}
