{
  "type": "Feature",
  "properties": {
    "iso:country":"GB",
    "wof:name":"N5 2BY",
    "wof:placetype":"postalcode"
},
  "geometry": {"coordinates":[-0.09392754889908,51.55100691080874],"type":"Point"}
}