{
  "type": "Feature",
  "properties": {
    "iso:country":"GB",
    "wof:name":"PL3 5BN",
    "wof:placetype":"postalcode"
},
  "geometry": {"coordinates":[-4.12315104174966,50.38507637015984],"type":"Point"}
}