{
  "type": "Feature",
  "properties": {
    "iso:country":"GB",
    "wof:name":"CW11 4RX",
    "wof:placetype":"postalcode"
},
  "geometry": {"coordinates":[-2.35860432342742,53.11402428535722],"type":"Point"}
}