{
  "type": "Feature",
  "properties": {
    "iso:country": "GB",
    "wof:name": "CW11 4RX",
    "wof:placetype": "postalcode"
  },
  "geometry": {"coordinates":[-2.358604,53.114024],"type":"Point"}
}
