{
  "type": "Feature",
  "properties": {
    "date:inception_lower": "1995-12-01",
    "date:inception_upper": "1995-12-01",
    "iso:country": "GB",
    "wof:name": "CW11 4RX",
    "wof:placetype": "postalcode"
  },
  "geometry": {"coordinates":[-2.358604,53.114024],"type":"Point"}
}
