{
  "type": "Feature",
  "properties": {
    "date:inception_lower": "1980-01-01",
    "date:inception_upper": "1980-01-01",
    "iso:country": "GB",
    "wof:name": "NE11 9UR",
    "wof:placetype": "postalcode"
  },
  "geometry": {"coordinates":[-1.644931,54.946728],"type":"Point"}
}
