{
  "type": "Feature",
  "properties": {
    "iso:country":"GB",
    "wof:name":"SA6 6AE",
    "wof:placetype":"postalcode"
},
  "geometry": {"coordinates":[-3.92569959986036,51.66851479244662],"type":"Point"}
}