{
  "type": "Feature",
  "properties": {
    "iso:country": "GB",
    "wof:name": "TQ9 6DJ",
    "wof:placetype": "postalcode"
  },
  "geometry": {"coordinates":[-3.713839,50.436943],"type":"Point"}
}
