{
  "type": "Feature",
  "properties": {
    "iso:country":"GB",
    "wof:name":"NR20 3AD",
    "wof:placetype":"postalcode"
},
  "geometry": {"coordinates":[1.03729631078526,52.7099783689672],"type":"Point"}
}