{
  "type": "Feature",
  "properties": {
    "iso:country":"GB",
    "wof:name":"DN10 6RG",
    "wof:placetype":"postalcode"
},
  "geometry": {"coordinates":[-1.00583813725615,53.44692423143933],"type":"Point"}
}