{
  "type": "Feature",
  "properties": {
    "date:inception_lower":"1980-01-01",
    "date:inception_upper":"1980-01-31",
    "iso:country":"GB",
    "wof:name":"DN10 6RG",
    "wof:placetype":"postalcode"
},
  "geometry": {"coordinates":[-1.005838,53.446924],"type":"Point"}
}