{
  "type": "Feature",
  "properties": {
    "iso:country": "GB",
    "wof:name": "DN10 6RG",
    "wof:placetype": "postalcode"
  },
  "geometry": {"coordinates":[-1.005838,53.446924],"type":"Point"}
}
