{
  "type": "Feature",
  "properties": {
    "iso:country":"GB",
    "wof:name":"SS7 1LH",
    "wof:placetype":"postalcode"
},
  "geometry": {"coordinates":[0.56858749592256,51.54640110309089],"type":"Point"}
}