{
  "type": "Feature",
  "properties": {
    "date:inception_lower": "1980-01-01",
    "date:inception_upper": "1980-01-01",
    "iso:country": "GB",
    "wof:name": "SS7 1LH",
    "wof:placetype": "postalcode"
  },
  "geometry": {"coordinates":[0.568588,51.546401],"type":"Point"}
}
