{
  "type": "Feature",
  "properties": {
    "iso:country": "GB",
    "wof:name": "L36 3TD",
    "wof:placetype": "postalcode"
  },
  "geometry": {"coordinates":[-2.855862,53.425256],"type":"Point"}
}
