{
  "type": "Feature",
  "properties": {
    "iso:country": "GB",
    "wof:name": "L36 3TD",
    "wof:placetype": "postalcode"
  },
  "geometry": {"coordinates":[-2.856093,53.425472],"type":"Point"}
}
