{
  "type": "Feature",
  "properties": {
    "iso:country":"GB",
    "wof:name":"L36 3TD",
    "wof:placetype":"postalcode"
},
  "geometry": {"coordinates":[-2.85609308617777,53.42547242786708],"type":"Point"}
}