{
  "type": "Feature",
  "properties": {
    "iso:country":"GB",
    "wof:name":"EX2 4HQ",
    "wof:placetype":"postalcode"
},
  "geometry": {"coordinates":[-3.52479336035806,50.71962392134452],"type":"Point"}
}