{
  "type": "Feature",
  "properties": {
    "date:inception_lower": "1991-09-01",
    "date:inception_upper": "1991-09-01",
    "iso:country": "GB",
    "wof:name": "B67 7BJ",
    "wof:placetype": "postalcode"
  },
  "geometry": {"coordinates":[-1.97555,52.494461],"type":"Point"}
}
