{
  "type": "Feature",
  "properties": {
    "iso:country":"GB",
    "wof:name":"B67 7BJ",
    "wof:placetype":"postalcode"
},
  "geometry": {"coordinates":[-1.97555045212643,52.49446056316635],"type":"Point"}
}