{
  "type": "Feature",
  "properties": {
    "iso:country": "GB",
    "wof:name": "NR30 2DH",
    "wof:placetype": "postalcode"
  },
  "geometry": {"coordinates":[1.736539,52.609362],"type":"Point"}
}
