{
  "type": "Feature",
  "properties": {
    "iso:country": "GB",
    "wof:name": "NR30 2DH",
    "wof:placetype": "postalcode"
  },
  "geometry": {"coordinates":[1.736402,52.608962],"type":"Point"}
}
