{
  "type": "Feature",
  "properties": {
    "iso:country":"GB",
    "wof:name":"NR30 2DH",
    "wof:placetype":"postalcode"
},
  "geometry": {"coordinates":[1.73636395448241,52.60911579238347],"type":"Point"}
}