{
  "type": "Feature",
  "properties": {
    "date:inception_lower": "2005-06-01",
    "date:inception_upper": "2005-06-01",
    "iso:country": "GB",
    "wof:name": "DY13 9GF",
    "wof:placetype": "postalcode"
  },
  "geometry": {"coordinates":[-2.265833,52.341315],"type":"Point"}
}
