{
  "type": "Feature",
  "properties": {
    "date:inception_lower":"1980-01-01",
    "date:inception_upper":"1980-01-31",
    "iso:country":"GB",
    "wof:name":"UB6 8RP",
    "wof:placetype":"postalcode"
},
  "geometry": {"coordinates":[-0.348042,51.530032],"type":"Point"}
}