{
  "type": "Feature",
  "properties": {
    "iso:country":"GB",
    "wof:name":"UB6 8RP",
    "wof:placetype":"postalcode"
},
  "geometry": {"coordinates":[-0.34804180876195,51.53003231428936],"type":"Point"}
}