{
  "type": "Feature",
  "properties": {
    "iso:country": "GB",
    "wof:name": "EN7 6JE",
    "wof:placetype": "postalcode"
  },
  "geometry": {"coordinates":[-0.057343,51.708044],"type":"Point"}
}
