{
  "type": "Feature",
  "properties": {
    "date:inception_lower": "1980-01-01",
    "date:inception_upper": "1980-01-01",
    "iso:country": "GB",
    "wof:name": "SP3 5NE",
    "wof:placetype": "postalcode"
  },
  "geometry": {"coordinates":[-2.02966,51.051525],"type":"Point"}
}
