{
  "type": "Feature",
  "properties": {
    "iso:country":"GB",
    "wof:name":"SP3 5NE",
    "wof:placetype":"postalcode"
},
  "geometry": {"coordinates":[-2.02966662553152,51.05153149703384],"type":"Point"}
}