{
  "type": "Feature",
  "properties": {
    "iso:country": "GB",
    "wof:name": "SP3 5NE",
    "wof:placetype": "postalcode"
  },
  "geometry": {"coordinates":[-2.02966,51.051525],"type":"Point"}
}
