{
  "type": "Feature",
  "properties": {
    "iso:country":"GB",
    "wof:name":"IG8 9AN",
    "wof:placetype":"postalcode"
},
  "geometry": {"coordinates":[0.02820703525498,51.60266295930317],"type":"Point"}
}