{
  "type": "Feature",
  "properties": {
    "iso:country":"GB",
    "wof:name":"NE69 7AY",
    "wof:placetype":"postalcode"
},
  "geometry": {"coordinates":[-1.69954744792924,55.60309861550676],"type":"Point"}
}