{
  "type": "Feature",
  "properties": {
    "date:inception_lower": "2000-06-01",
    "date:inception_upper": "2000-06-01",
    "iso:country": "GB",
    "wof:name": "CF24 1DX",
    "wof:placetype": "postalcode"
  },
  "geometry": {"coordinates":[-3.155488,51.491188],"type":"Point"}
}
