{
  "type": "Feature",
  "properties": {
    "date:inception_lower":"2000-06-01",
    "date:inception_upper":"2000-06-30",
    "iso:country":"GB",
    "wof:name":"CF24 1DX",
    "wof:placetype":"postalcode"
},
  "geometry": {"coordinates":[-3.155537,51.491178],"type":"Point"}
}