{
  "type": "Feature",
  "properties": {
    "iso:country":"GB",
    "wof:name":"M6 7GZ",
    "wof:placetype":"postalcode"
},
  "geometry": {"coordinates":[-2.30706561910201,53.49909309728405],"type":"Point"}
}