{
  "type": "Feature",
  "properties": {
    "iso:country":"GB",
    "wof:name":"WN1 2LY",
    "wof:placetype":"postalcode"
},
  "geometry": {"coordinates":[-2.62683993683391,53.55556754595413],"type":"Point"}
}