{
  "type": "Feature",
  "properties": {
    "date:inception_lower":"1980-01-01",
    "date:inception_upper":"1980-01-31",
    "iso:country":"GB",
    "wof:name":"WN1 2LY",
    "wof:placetype":"postalcode"
},
  "geometry": {"coordinates":[-2.62684,53.555568],"type":"Point"}
}