{
  "type": "Feature",
  "properties": {
    "iso:country": "GB",
    "wof:name": "M30 9RD",
    "wof:placetype": "postalcode"
  },
  "geometry": {"coordinates":[-2.340249,53.486374],"type":"Point"}
}
