{
  "type": "Feature",
  "properties": {
    "iso:country": "GB",
    "wof:name": "CW1 5QQ",
    "wof:placetype": "postalcode"
  },
  "geometry": {"coordinates":[-2.3959,53.098454],"type":"Point"}
}
