{
  "type": "Feature",
  "properties": {
    "iso:country":"GB",
    "wof:name":"LL40 2AG",
    "wof:placetype":"postalcode"
},
  "geometry": {"coordinates":[-3.84688320858983,52.75544524776259],"type":"Point"}
}