{
  "type": "Feature",
  "properties": {
    "date:inception_lower":"1993-08-01",
    "date:inception_upper":"1993-08-31",
    "iso:country":"GB",
    "wof:name":"LL40 2AG",
    "wof:placetype":"postalcode"
},
  "geometry": {"coordinates":[-3.846883,52.755445],"type":"Point"}
}