{
  "type": "Feature",
  "properties": {
    "iso:country": "GB",
    "wof:name": "M46 9JB",
    "wof:placetype": "postalcode"
  },
  "geometry": {"coordinates":[-2.488315,53.525653],"type":"Point"}
}
