{
  "type": "Feature",
  "properties": {
    "iso:country":"GB",
    "wof:name":"SA4 6QF",
    "wof:placetype":"postalcode"
},
  "geometry": {"coordinates":[-4.05771958014278,51.66437762348463],"type":"Point"}
}