{
  "type": "Feature",
  "properties": {
    "iso:country": "GB",
    "wof:name": "SA4 6QF",
    "wof:placetype": "postalcode"
  },
  "geometry": {"coordinates":[-4.05772,51.664378],"type":"Point"}
}
