{
  "type": "Feature",
  "properties": {
    "iso:country":"GB",
    "wof:name":"NG3 5JE",
    "wof:placetype":"postalcode"
},
  "geometry": {"coordinates":[-1.13328218405757,52.97625679362336],"type":"Point"}
}