{
  "type": "Feature",
  "properties": {
    "date:inception_lower": "1980-01-01",
    "date:inception_upper": "1980-01-01",
    "iso:country": "GB",
    "wof:name": "NG3 5JE",
    "wof:placetype": "postalcode"
  },
  "geometry": {"coordinates":[-1.133279,52.976277],"type":"Point"}
}
