{
  "type": "Feature",
  "properties": {
    "iso:country":"GB",
    "wof:name":"S80 2PF",
    "wof:placetype":"postalcode"
},
  "geometry": {"coordinates":[-1.10964880361312,53.30161912306833],"type":"Point"}
}