{
  "type": "Feature",
  "properties": {
    "iso:country":"GB",
    "wof:name":"PE32 2QN",
    "wof:placetype":"postalcode"
},
  "geometry": {"coordinates":[0.73001651244254,52.72107130553097],"type":"Point"}
}