{
  "type": "Feature",
  "properties": {
    "iso:country": "GB",
    "wof:name": "PE28 3JE",
    "wof:placetype": "postalcode"
  },
  "geometry": {"coordinates":[0.003068,52.383009],"type":"Point"}
}
