{
  "type": "Feature",
  "properties": {
    "iso:country":"GB",
    "wof:name":"KT3 3BA",
    "wof:placetype":"postalcode"
},
  "geometry": {"coordinates":[-0.26439224346403,51.41246253195381],"type":"Point"}
}