{
  "type": "Feature",
  "properties": {
    "iso:country": "GB",
    "wof:name": "KT3 3BA",
    "wof:placetype": "postalcode"
  },
  "geometry": {"coordinates":[-0.264392,51.412463],"type":"Point"}
}
