{
  "type": "Feature",
  "properties": {
    "iso:country":"GB",
    "wof:name":"WR4 9AJ",
    "wof:placetype":"postalcode"
},
  "geometry": {"coordinates":[-2.19483749790685,52.19827369038235],"type":"Point"}
}