{
  "type": "Feature",
  "properties": {
    "iso:country":"GB",
    "wof:name":"NW8 0SN",
    "wof:placetype":"postalcode"
},
  "geometry": {"coordinates":[-0.18237960972003,51.54040569269178],"type":"Point"}
}