{
  "type": "Feature",
  "properties": {
    "iso:country":"GB",
    "wof:name":"SS1 3QR",
    "wof:placetype":"postalcode"
},
  "geometry": {"coordinates":[0.7576046596875,51.54236050832353],"type":"Point"}
}