{
  "type": "Feature",
  "properties": {
    "date:inception_lower": "1980-01-01",
    "date:inception_upper": "1980-01-01",
    "iso:country": "GB",
    "wof:name": "IV10 8UB",
    "wof:placetype": "postalcode"
  },
  "geometry": {"coordinates":[-4.118884,57.586598],"type":"Point"}
}
