{
  "type": "Feature",
  "properties": {
    "iso:country":"GB",
    "wof:name":"IV10 8UB",
    "wof:placetype":"postalcode"
},
  "geometry": {"coordinates":[-4.12000679810842,57.58663917465707],"type":"Point"}
}