{
  "type": "Feature",
  "properties": {
    "iso:country":"GB",
    "wof:name":"SE25 6AW",
    "wof:placetype":"postalcode"
},
  "geometry": {"coordinates":[-0.08710262445349,51.39237382434895],"type":"Point"}
}