{
  "type": "Feature",
  "properties": {
    "date:inception_lower": "2008-03-01",
    "date:inception_upper": "2008-03-01",
    "iso:country": "GB",
    "wof:name": "SE25 6AW",
    "wof:placetype": "postalcode"
  },
  "geometry": {"coordinates":[-0.087103,51.392374],"type":"Point"}
}
