{
  "type": "Feature",
  "properties": {
    "iso:country": "GB",
    "wof:name": "SE25 6AW",
    "wof:placetype": "postalcode"
  },
  "geometry": {"coordinates":[-0.087103,51.392374],"type":"Point"}
}
