{
  "type": "Feature",
  "properties": {
    "iso:country": "GB",
    "wof:name": "DE7 4LD",
    "wof:placetype": "postalcode"
  },
  "geometry": {"coordinates":[-1.310465,52.964696],"type":"Point"}
}
