{
  "type": "Feature",
  "properties": {
    "iso:country":"GB",
    "wof:name":"DE7 4LD",
    "wof:placetype":"postalcode"
},
  "geometry": {"coordinates":[-1.31046462348849,52.96469611811082],"type":"Point"}
}