{
  "type": "Feature",
  "properties": {
    "iso:country":"GB",
    "wof:name":"TQ4 6BX",
    "wof:placetype":"postalcode"
},
  "geometry": {"coordinates":[-3.56253598033342,50.42909131259646],"type":"Point"}
}