{
  "type": "Feature",
  "properties": {
    "iso:country": "GB",
    "wof:name": "TQ4 6BX",
    "wof:placetype": "postalcode"
  },
  "geometry": {"coordinates":[-3.562528,50.428762],"type":"Point"}
}
