{
  "type": "Feature",
  "properties": {
    "iso:country": "GB",
    "wof:name": "WA10 2DQ",
    "wof:placetype": "postalcode"
  },
  "geometry": {"coordinates":[-2.74297,53.458365],"type":"Point"}
}
