{
  "type": "Feature",
  "properties": {
    "iso:country":"GB",
    "wof:name":"WA10 2DQ",
    "wof:placetype":"postalcode"
},
  "geometry": {"coordinates":[-2.74297048116141,53.45836456515841],"type":"Point"}
}