{
  "type": "Feature",
  "properties": {
    "iso:country": "GB",
    "wof:name": "LL40 1HA",
    "wof:placetype": "postalcode"
  },
  "geometry": {"coordinates":[-3.880896,52.743328],"type":"Point"}
}
