{
  "type": "Feature",
  "properties": {
    "date:inception_lower":"1981-06-01",
    "date:inception_upper":"1981-06-30",
    "iso:country":"GB",
    "wof:name":"LL40 1HA",
    "wof:placetype":"postalcode"
},
  "geometry": {"coordinates":[-3.880896,52.743328],"type":"Point"}
}