{
  "type": "Feature",
  "properties": {
    "date:inception_lower": "1995-07-01",
    "date:inception_upper": "1995-07-01",
    "iso:country": "GB",
    "wof:name": "HS1 2JD",
    "wof:placetype": "postalcode"
  },
  "geometry": {"coordinates":[-6.386504,58.210296],"type":"Point"}
}
