{
  "type": "Feature",
  "properties": {
    "iso:country":"GB",
    "wof:name":"HS1 2JD",
    "wof:placetype":"postalcode"
},
  "geometry": {"coordinates":[-6.38650367833131,58.21029592810449],"type":"Point"}
}