{
  "type": "Feature",
  "properties": {
    "iso:country": "GB",
    "wof:name": "BL3 4RD",
    "wof:placetype": "postalcode"
  },
  "geometry": {"coordinates":[-2.477057,53.561561],"type":"Point"}
}
