{
  "type": "Feature",
  "properties": {
    "iso:country":"GB",
    "wof:name":"SK22 2HQ",
    "wof:placetype":"postalcode"
},
  "geometry": {"coordinates":[-1.95096809509845,53.38100082756959],"type":"Point"}
}