{
  "type": "Feature",
  "properties": {
    "iso:country": "GB",
    "wof:name": "SK22 2HQ",
    "wof:placetype": "postalcode"
  },
  "geometry": {"coordinates":[-1.950968,53.381001],"type":"Point"}
}
