{
  "type": "Feature",
  "properties": {
    "date:inception_lower": "2023-02-01",
    "date:inception_upper": "2023-02-01",
    "iso:country": "GB",
    "wof:name": "M50 2AR",
    "wof:placetype": "postalcode"
  },
  "geometry": {"coordinates":[-2.299367,53.474106],"type":"Point"}
}
