{
  "type": "Feature",
  "properties": {
    "iso:country":"GB",
    "wof:name":"L20 9NA",
    "wof:placetype":"postalcode"
},
  "geometry": {"coordinates":[-2.97838880921036,53.44469502551503],"type":"Point"}
}