{
  "type": "Feature",
  "properties": {
    "iso:country":"GB",
    "wof:name":"WV4 6QL",
    "wof:placetype":"postalcode"
},
  "geometry": {"coordinates":[-2.11447404126091,52.55115163866301],"type":"Point"}
}