{
  "type": "Feature",
  "properties": {
    "iso:country":"GB",
    "wof:name":"IV4 7DR",
    "wof:placetype":"postalcode"
},
  "geometry": {"coordinates":[-4.46008222197809,57.48486154061473],"type":"Point"}
}