{
  "type": "Feature",
  "properties": {
    "iso:country": "GB",
    "wof:name": "IV4 7DR",
    "wof:placetype": "postalcode"
  },
  "geometry": {"coordinates":[-4.460082,57.484862],"type":"Point"}
}
