{
  "type": "Feature",
  "properties": {
    "iso:country": "GB",
    "wof:name": "CF31 3PB",
    "wof:placetype": "postalcode"
  },
  "geometry": {"coordinates":[-3.586108,51.499407],"type":"Point"}
}
