{
  "type": "Feature",
  "properties": {
    "date:inception_lower": "2006-07-01",
    "date:inception_upper": "2006-07-01",
    "iso:country": "GB",
    "wof:name": "DE7 6JT",
    "wof:placetype": "postalcode"
  },
  "geometry": {"coordinates":[-1.392949,53.000699],"type":"Point"}
}
