{
  "type": "Feature",
  "properties": {
    "iso:country":"GB",
    "wof:name":"DE7 6JT",
    "wof:placetype":"postalcode"
},
  "geometry": {"coordinates":[-1.39294891664979,53.00069857233827],"type":"Point"}
}