{
  "type": "Feature",
  "properties": {
    "iso:country": "GB",
    "wof:name": "DE7 6JT",
    "wof:placetype": "postalcode"
  },
  "geometry": {"coordinates":[-1.392949,53.000699],"type":"Point"}
}
