{
  "type": "Feature",
  "properties": {
    "iso:country":"GB",
    "wof:name":"CM2 9PT",
    "wof:placetype":"postalcode"
},
  "geometry": {"coordinates":[0.47109746709918,51.72451898200829],"type":"Point"}
}