{
  "type": "Feature",
  "properties": {
    "iso:country": "GB",
    "wof:name": "LA2 8NA",
    "wof:placetype": "postalcode"
  },
  "geometry": {"coordinates":[-2.636194,54.113506],"type":"Point"}
}
