{
  "type": "Feature",
  "properties": {
    "iso:country":"GB",
    "wof:name":"DG12 6RP",
    "wof:placetype":"postalcode"
},
  "geometry": {"coordinates":[-3.20898100842916,55.02131431491764],"type":"Point"}
}