{
  "type": "Feature",
  "properties": {
    "iso:country":"GB",
    "wof:name":"M1 3FS",
    "wof:placetype":"postalcode"
},
  "geometry": {"coordinates":[-2.23516609910164,53.47867278457726],"type":"Point"}
}