{
  "type": "Feature",
  "properties": {
    "date:inception_lower":"1995-07-01",
    "date:inception_upper":"1995-07-31",
    "iso:country":"GB",
    "wof:name":"M1 3FS",
    "wof:placetype":"postalcode"
},
  "geometry": {"coordinates":[-2.235166,53.478673],"type":"Point"}
}