{
  "type": "Feature",
  "properties": {
    "iso:country":"GB",
    "wof:name":"PE16 6TL",
    "wof:placetype":"postalcode"
},
  "geometry": {"coordinates":[0.04405515219706,52.44861988509998],"type":"Point"}
}