{
  "type": "Feature",
  "properties": {
    "iso:country":"GB",
    "wof:name":"MK45 2TA",
    "wof:placetype":"postalcode"
},
  "geometry": {"coordinates":[-0.48844060171655,52.02739837013632],"type":"Point"}
}