{
  "type": "Feature",
  "properties": {
    "iso:country":"GB",
    "wof:name":"PO18 8FF",
    "wof:placetype":"postalcode"
},
  "geometry": {"coordinates":[-0.88539490322825,50.84699951570945],"type":"Point"}
}