{
  "type": "Feature",
  "properties": {
    "iso:country":"GB",
    "wof:name":"W1U 3AY",
    "wof:placetype":"postalcode"
},
  "geometry": {"coordinates":[-0.15143410007926,51.51653273686458],"type":"Point"}
}