{
  "type": "Feature",
  "properties": {
    "iso:country": "GB",
    "wof:name": "KA24 4ED",
    "wof:placetype": "postalcode"
  },
  "geometry": {"coordinates":[-4.712424,55.705407],"type":"Point"}
}
