{
  "type": "Feature",
  "properties": {
    "date:inception_lower":"1997-06-01",
    "date:inception_upper":"1997-06-30",
    "iso:country":"GB",
    "wof:name":"KA24 4ED",
    "wof:placetype":"postalcode"
},
  "geometry": {"coordinates":[-4.712424,55.705407],"type":"Point"}
}