{
  "type": "Feature",
  "properties": {
    "iso:country":"GB",
    "wof:name":"KA24 4ED",
    "wof:placetype":"postalcode"
},
  "geometry": {"coordinates":[-4.71242416923618,55.70540689544423],"type":"Point"}
}