{
  "type": "Feature",
  "properties": {
    "iso:country":"GB",
    "wof:name":"HU5 5UE",
    "wof:placetype":"postalcode"
},
  "geometry": {"coordinates":[-0.40727072905036,53.75794536176929],"type":"Point"}
}