{
  "type": "Feature",
  "properties": {
    "iso:country": "GB",
    "wof:name": "PA3 2DJ",
    "wof:placetype": "postalcode"
  },
  "geometry": {"coordinates":[-4.425357,55.84791],"type":"Point"}
}
