{
  "type": "Feature",
  "properties": {
    "date:inception_lower": "2023-05-01",
    "date:inception_upper": "2023-05-01",
    "iso:country": "GB",
    "wof:name": "WA13 9EP",
    "wof:placetype": "postalcode"
  },
  "geometry": {"coordinates":[-2.45777,53.385839],"type":"Point"}
}
