{
  "type": "Feature",
  "properties": {
    "date:inception_lower": "2008-06-01",
    "date:inception_upper": "2008-06-01",
    "iso:country": "GB",
    "wof:name": "WR11 4BF",
    "wof:placetype": "postalcode"
  },
  "geometry": {"coordinates":[-1.948741,52.093481],"type":"Point"}
}
