{
  "type": "Feature",
  "properties": {
    "iso:country": "GB",
    "wof:name": "NE12 9QU",
    "wof:placetype": "postalcode"
  },
  "geometry": {"coordinates":[-1.551378,55.021724],"type":"Point"}
}
