{
  "type": "Feature",
  "properties": {
    "iso:country":"GB",
    "wof:name":"NW2 1LW",
    "wof:placetype":"postalcode"
},
  "geometry": {"coordinates":[-0.21892285541287,51.57470549088829],"type":"Point"}
}