{
  "type": "Feature",
  "properties": {
    "iso:country": "GB",
    "wof:name": "ML2 7RU",
    "wof:placetype": "postalcode"
  },
  "geometry": {"coordinates":[-3.945446,55.77814],"type":"Point"}
}
