{
  "type": "Feature",
  "properties": {
    "iso:country":"GB",
    "wof:name":"L13 2AS",
    "wof:placetype":"postalcode"
},
  "geometry": {"coordinates":[-2.92281508630123,53.41266964319259],"type":"Point"}
}