{
  "type": "Feature",
  "properties": {
    "iso:country":"GB",
    "wof:name":"PL26 8QZ",
    "wof:placetype":"postalcode"
},
  "geometry": {"coordinates":[-4.79082259698756,50.39632980413989],"type":"Point"}
}