{
  "type": "Feature",
  "properties": {
    "date:inception_lower": "1995-07-01",
    "date:inception_upper": "1995-07-01",
    "iso:country": "GB",
    "wof:name": "PL26 8QZ",
    "wof:placetype": "postalcode"
  },
  "geometry": {"coordinates":[-4.790823,50.39633],"type":"Point"}
}
