{
  "type": "Feature",
  "properties": {
    "date:inception_lower": "2022-08-01",
    "date:inception_upper": "2022-08-01",
    "iso:country": "GB",
    "wof:name": "CA14 3FQ",
    "wof:placetype": "postalcode"
  },
  "geometry": {"coordinates":[-3.566952,54.63516],"type":"Point"}
}
