{
  "type": "Feature",
  "properties": {
    "date:inception_lower": "2020-08-01",
    "date:inception_upper": "2020-08-01",
    "iso:country": "GB",
    "wof:name": "S21 5AD",
    "wof:placetype": "postalcode"
  },
  "geometry": {"coordinates":[-1.392542,53.308267],"type":"Point"}
}
