{
  "type": "Feature",
  "properties": {
    "iso:country":"GB",
    "wof:name":"RG6 7NG",
    "wof:placetype":"postalcode"
},
  "geometry": {"coordinates":[-0.92498921812716,51.43645089841912],"type":"Point"}
}