{
  "type": "Feature",
  "properties": {
    "iso:country":"GB",
    "wof:name":"DL13 5DG",
    "wof:placetype":"postalcode"
},
  "geometry": {"coordinates":[-1.80418495920848,54.61152378161287],"type":"Point"}
}