{
  "type": "Feature",
  "properties": {
    "iso:country":"GB",
    "wof:name":"CM22 6AE",
    "wof:placetype":"postalcode"
},
  "geometry": {"coordinates":[0.2474380793753,51.92891619960899],"type":"Point"}
}