{
  "type": "Feature",
  "properties": {
    "iso:country": "GB",
    "wof:name": "CM22 6AE",
    "wof:placetype": "postalcode"
  },
  "geometry": {"coordinates":[0.247438,51.928916],"type":"Point"}
}
