{
  "type": "Feature",
  "properties": {
    "iso:country":"GB",
    "wof:name":"B32 1NB",
    "wof:placetype":"postalcode"
},
  "geometry": {"coordinates":[-1.99200956710766,52.45506875213287],"type":"Point"}
}