{
  "type": "Feature",
  "properties": {
    "date:inception_lower": "1980-01-01",
    "date:inception_upper": "1980-01-01",
    "iso:country": "GB",
    "wof:name": "B32 1NB",
    "wof:placetype": "postalcode"
  },
  "geometry": {"coordinates":[-1.99201,52.455069],"type":"Point"}
}
