{
  "type": "Feature",
  "properties": {
    "iso:country": "GB",
    "wof:name": "B32 1NB",
    "wof:placetype": "postalcode"
  },
  "geometry": {"coordinates":[-1.99201,52.455069],"type":"Point"}
}
