{
  "type": "Feature",
  "properties": {
    "date:inception_lower":"1999-06-01",
    "date:inception_upper":"1999-06-30",
    "iso:country":"GB",
    "wof:name":"CH63 7TA",
    "wof:placetype":"postalcode"
},
  "geometry": {"coordinates":[-3.006772,53.354965],"type":"Point"}
}