{
  "type": "Feature",
  "properties": {
    "iso:country": "GB",
    "wof:name": "AB51 3UB",
    "wof:placetype": "postalcode"
  },
  "geometry": {"coordinates":[-2.372551,57.276792],"type":"Point"}
}
