{
  "type": "Feature",
  "properties": {
    "iso:country":"GB",
    "wof:name":"SN5 3NQ",
    "wof:placetype":"postalcode"
},
  "geometry": {"coordinates":[-1.85850709978279,51.57139859541282],"type":"Point"}
}