{
  "type": "Feature",
  "properties": {
    "iso:country": "GB",
    "wof:name": "SN5 3NQ",
    "wof:placetype": "postalcode"
  },
  "geometry": {"coordinates":[-1.858507,51.571399],"type":"Point"}
}
