{
  "type": "Feature",
  "properties": {
    "date:inception_lower": "1980-01-01",
    "date:inception_upper": "1980-01-01",
    "iso:country": "GB",
    "wof:name": "KT12 5PL",
    "wof:placetype": "postalcode"
  },
  "geometry": {"coordinates":[-0.418323,51.371198],"type":"Point"}
}
