{
  "type": "Feature",
  "properties": {
    "iso:country":"GB",
    "wof:name":"SY3 8SB",
    "wof:placetype":"postalcode"
},
  "geometry": {"coordinates":[-2.76869527774153,52.70782303239803],"type":"Point"}
}