{
  "type": "Feature",
  "properties": {
    "iso:country":"GB",
    "wof:name":"TN22 3AA",
    "wof:placetype":"postalcode"
},
  "geometry": {"coordinates":[0.10342425387702,50.98844146278504],"type":"Point"}
}