{
  "type": "Feature",
  "properties": {
    "iso:country":"GB",
    "wof:name":"B74 4HN",
    "wof:placetype":"postalcode"
},
  "geometry": {"coordinates":[-1.85692678843245,52.59798504143419],"type":"Point"}
}