{
  "type": "Feature",
  "properties": {
    "date:inception_lower": "1991-09-01",
    "date:inception_upper": "1991-09-01",
    "iso:country": "GB",
    "wof:name": "RG27 8NP",
    "wof:placetype": "postalcode"
  },
  "geometry": {"coordinates":[-0.900474,51.307476],"type":"Point"}
}
