{
  "type": "Feature",
  "properties": {
    "iso:country": "GB",
    "wof:name": "RG27 8NP",
    "wof:placetype": "postalcode"
  },
  "geometry": {"coordinates":[-0.900474,51.307476],"type":"Point"}
}
