{
  "type": "Feature",
  "properties": {
    "iso:country":"GB",
    "wof:name":"GL20 7NZ",
    "wof:placetype":"postalcode"
},
  "geometry": {"coordinates":[-2.06247811777553,52.03595069159916],"type":"Point"}
}