{
  "type": "Feature",
  "properties": {
    "iso:country": "GB",
    "wof:name": "RM5 3EN",
    "wof:placetype": "postalcode"
  },
  "geometry": {"coordinates":[0.166733,51.592897],"type":"Point"}
}
