{
  "type": "Feature",
  "properties": {
    "iso:country":"GB",
    "wof:name":"B97 6TW",
    "wof:placetype":"postalcode"
},
  "geometry": {"coordinates":[-1.96483789368217,52.31402709959191],"type":"Point"}
}