{
  "type": "Feature",
  "properties": {
    "date:inception_lower": "2000-06-01",
    "date:inception_upper": "2000-06-01",
    "iso:country": "GB",
    "wof:name": "B97 6TW",
    "wof:placetype": "postalcode"
  },
  "geometry": {"coordinates":[-1.964838,52.314027],"type":"Point"}
}
