{
  "type": "Feature",
  "properties": {
    "date:inception_lower":"2009-10-01",
    "date:inception_upper":"2009-10-31",
    "iso:country":"GB",
    "wof:name":"SY4 5EN",
    "wof:placetype":"postalcode"
},
  "geometry": {"coordinates":[-2.728042,52.854684],"type":"Point"}
}