{
  "type": "Feature",
  "properties": {
    "iso:country":"GB",
    "wof:name":"RH6 9RB",
    "wof:placetype":"postalcode"
},
  "geometry": {"coordinates":[-0.12545466830496,51.17113123492731],"type":"Point"}
}