{
  "type": "Feature",
  "properties": {
    "iso:country": "GB",
    "wof:name": "RH6 9RB",
    "wof:placetype": "postalcode"
  },
  "geometry": {"coordinates":[-0.125455,51.171131],"type":"Point"}
}
