{
  "type": "Feature",
  "properties": {
    "date:inception_lower": "1980-01-01",
    "date:inception_upper": "1980-01-01",
    "iso:country": "GB",
    "wof:name": "NR13 5LP",
    "wof:placetype": "postalcode"
  },
  "geometry": {"coordinates":[1.427674,52.625404],"type":"Point"}
}
