{
  "type": "Feature",
  "properties": {
    "date:inception_lower":"1980-01-01",
    "date:inception_upper":"1980-01-31",
    "iso:country":"GB",
    "wof:name":"TA21 9JP",
    "wof:placetype":"postalcode"
},
  "geometry": {"coordinates":[-3.186139,50.983609],"type":"Point"}
}