{
  "type": "Feature",
  "properties": {
    "iso:country":"GB",
    "wof:name":"B61 9AP",
    "wof:placetype":"postalcode"
},
  "geometry": {"coordinates":[-2.08790608047618,52.3487104668182],"type":"Point"}
}