{
  "type": "Feature",
  "properties": {
    "iso:country": "GB",
    "wof:name": "MK45 1XS",
    "wof:placetype": "postalcode"
  },
  "geometry": {"coordinates":[-0.499697,52.014226],"type":"Point"}
}
