{
  "type": "Feature",
  "properties": {
    "date:inception_lower":"1993-08-01",
    "date:inception_upper":"1993-08-31",
    "iso:country":"GB",
    "wof:name":"MK45 1XS",
    "wof:placetype":"postalcode"
},
  "geometry": {"coordinates":[-0.499697,52.014226],"type":"Point"}
}