{
  "type": "Feature",
  "properties": {
    "iso:country":"GB",
    "wof:name":"GL50 4LF",
    "wof:placetype":"postalcode"
},
  "geometry": {"coordinates":[-2.07330326571271,51.90775447617419],"type":"Point"}
}