{
  "type": "Feature",
  "properties": {
    "date:inception_lower": "1980-01-01",
    "date:inception_upper": "1980-01-01",
    "iso:country": "GB",
    "wof:name": "GL50 4LF",
    "wof:placetype": "postalcode"
  },
  "geometry": {"coordinates":[-2.073303,51.907754],"type":"Point"}
}
