{
  "type": "Feature",
  "properties": {
    "iso:country": "GB",
    "wof:name": "LN6 7NN",
    "wof:placetype": "postalcode"
  },
  "geometry": {"coordinates":[-0.570582,53.206878],"type":"Point"}
}
