{
  "type": "Feature",
  "properties": {
    "date:inception_lower": "1980-01-01",
    "date:inception_upper": "1980-01-01",
    "iso:country": "GB",
    "wof:name": "LN6 7NN",
    "wof:placetype": "postalcode"
  },
  "geometry": {"coordinates":[-0.570582,53.206878],"type":"Point"}
}
