{
  "type": "Feature",
  "properties": {
    "iso:country": "GB",
    "wof:name": "HA0 2JD",
    "wof:placetype": "postalcode"
  },
  "geometry": {"coordinates":[-0.304816,51.555754],"type":"Point"}
}
