{
  "type": "Feature",
  "properties": {
    "iso:country":"GB",
    "wof:name":"SP5 5EH",
    "wof:placetype":"postalcode"
},
  "geometry": {"coordinates":[-1.94144058413193,51.0300115113468],"type":"Point"}
}