{
  "type": "Feature",
  "properties": {
    "date:inception_lower": "1980-01-01",
    "date:inception_upper": "1980-01-01",
    "iso:country": "GB",
    "wof:name": "TS19 9JH",
    "wof:placetype": "postalcode"
  },
  "geometry": {"coordinates":[-1.3387,54.589531],"type":"Point"}
}
