{
  "type": "Feature",
  "properties": {
    "iso:country": "GB",
    "wof:name": "TS19 9JH",
    "wof:placetype": "postalcode"
  },
  "geometry": {"coordinates":[-1.3387,54.589531],"type":"Point"}
}
