{
  "type": "Feature",
  "properties": {
    "iso:country": "GB",
    "wof:name": "SA20 0SE",
    "wof:placetype": "postalcode"
  },
  "geometry": {"coordinates":[-3.698852,51.9822],"type":"Point"}
}
