{
  "type": "Feature",
  "properties": {
    "iso:country":"GB",
    "wof:name":"SA20 0SE",
    "wof:placetype":"postalcode"
},
  "geometry": {"coordinates":[-3.6988391272059,51.98219174174917],"type":"Point"}
}