{
  "type": "Feature",
  "properties": {
    "iso:country": "GB",
    "wof:name": "NG12 3FN",
    "wof:placetype": "postalcode"
  },
  "geometry": {"coordinates":[-0.956756,52.891559],"type":"Point"}
}
