{
  "type": "Feature",
  "properties": {
    "iso:country":"GB",
    "wof:name":"NG12 3FN",
    "wof:placetype":"postalcode"
},
  "geometry": {"coordinates":[-0.95675601865563,52.89155879548355],"type":"Point"}
}