{
  "type": "Feature",
  "properties": {
    "iso:country": "GB",
    "wof:name": "DL5 4AZ",
    "wof:placetype": "postalcode"
  },
  "geometry": {"coordinates":[-1.55817,54.62619],"type":"Point"}
}
