{
  "type": "Feature",
  "properties": {
    "date:inception_lower": "1980-01-01",
    "date:inception_upper": "1980-01-01",
    "iso:country": "GB",
    "wof:name": "DL5 4AZ",
    "wof:placetype": "postalcode"
  },
  "geometry": {"coordinates":[-1.55817,54.62619],"type":"Point"}
}
