{
  "type": "Feature",
  "properties": {
    "date:inception_lower": "2020-07-01",
    "date:inception_upper": "2020-07-01",
    "iso:country": "GB",
    "wof:name": "DL2 2HY",
    "wof:placetype": "postalcode"
  },
  "geometry": {"coordinates":[-1.52895,54.490811],"type":"Point"}
}
