{
  "type": "Feature",
  "properties": {
    "iso:country": "GB",
    "wof:name": "TA9 3GS",
    "wof:placetype": "postalcode"
  },
  "geometry": {"coordinates":[-2.985859,51.204449],"type":"Point"}
}
