{
  "type": "Feature",
  "properties": {
    "iso:country":"GB",
    "wof:name":"SA4 9EQ",
    "wof:placetype":"postalcode"
},
  "geometry": {"coordinates":[-4.01080368827614,51.68479417678927],"type":"Point"}
}