{
  "type": "Feature",
  "properties": {
    "iso:country": "GB",
    "wof:name": "SA4 9EQ",
    "wof:placetype": "postalcode"
  },
  "geometry": {"coordinates":[-4.010804,51.684794],"type":"Point"}
}
