{
  "type": "Feature",
  "properties": {
    "iso:country":"GB",
    "wof:name":"AL6 0DY",
    "wof:placetype":"postalcode"
},
  "geometry": {"coordinates":[-0.19318615226331,51.82370142283837],"type":"Point"}
}