{
  "type": "Feature",
  "properties": {
    "iso:country": "GB",
    "wof:name": "PE1 4JU",
    "wof:placetype": "postalcode"
  },
  "geometry": {"coordinates":[-0.225464,52.591244],"type":"Point"}
}
