{
  "type": "Feature",
  "properties": {
    "iso:country":"GB",
    "wof:name":"PE1 4JU",
    "wof:placetype":"postalcode"
},
  "geometry": {"coordinates":[-0.22546428214924,52.59124411111221],"type":"Point"}
}