{
  "type": "Feature",
  "properties": {
    "iso:country": "GB",
    "wof:name": "NW10 8AR",
    "wof:placetype": "postalcode"
  },
  "geometry": {"coordinates":[-0.254174,51.536029],"type":"Point"}
}
