{
  "type": "Feature",
  "properties": {
    "iso:country":"GB",
    "wof:name":"NG3 6BZ",
    "wof:placetype":"postalcode"
},
  "geometry": {"coordinates":[-1.11576178152553,52.97949886684216],"type":"Point"}
}