{
  "type": "Feature",
  "properties": {
    "iso:country": "GB",
    "wof:name": "PO2 9SP",
    "wof:placetype": "postalcode"
  },
  "geometry": {"coordinates":[-1.074833,50.832342],"type":"Point"}
}
