{
  "type": "Feature",
  "properties": {
    "iso:country":"GB",
    "wof:name":"PO2 9SP",
    "wof:placetype":"postalcode"
},
  "geometry": {"coordinates":[-1.07483264217437,50.83234191356787],"type":"Point"}
}