{
  "type": "Feature",
  "properties": {
    "iso:country": "GB",
    "wof:name": "NE2 4PZ",
    "wof:placetype": "postalcode"
  },
  "geometry": {"coordinates":[-1.614847,54.985925],"type":"Point"}
}
