{
  "type": "Feature",
  "properties": {
    "date:inception_lower": "2001-12-01",
    "date:inception_upper": "2001-12-01",
    "iso:country": "GB",
    "wof:name": "DE65 5JY",
    "wof:placetype": "postalcode"
  },
  "geometry": {"coordinates":[-1.631452,52.865605],"type":"Point"}
}
