{
  "type": "Feature",
  "properties": {
    "date:inception_lower": "1980-01-01",
    "date:inception_upper": "1980-01-01",
    "iso:country": "GB",
    "wof:name": "KA12 9LY",
    "wof:placetype": "postalcode"
  },
  "geometry": {"coordinates":[-4.660114,55.629267],"type":"Point"}
}
