{
  "type": "Feature",
  "properties": {
    "iso:country":"GB",
    "wof:name":"KA12 9LY",
    "wof:placetype":"postalcode"
},
  "geometry": {"coordinates":[-4.6601140440258,55.62926716251741],"type":"Point"}
}