{
  "type": "Feature",
  "properties": {
    "iso:country":"GB",
    "wof:name":"BA1 9BS",
    "wof:placetype":"postalcode"
},
  "geometry": {"coordinates":[-2.3948793044057,51.41629010459679],"type":"Point"}
}