{
  "type": "Feature",
  "properties": {
    "iso:country":"GB",
    "wof:name":"CV1 2UJ",
    "wof:placetype":"postalcode"
},
  "geometry": {"coordinates":[-1.50187482844058,52.40106943837432],"type":"Point"}
}