{
  "type": "Feature",
  "properties": {
    "date:inception_lower": "2001-12-01",
    "date:inception_upper": "2001-12-01",
    "iso:country": "GB",
    "wof:name": "CV1 2UJ",
    "wof:placetype": "postalcode"
  },
  "geometry": {"coordinates":[-1.501875,52.401069],"type":"Point"}
}
