{
  "type": "Feature",
  "properties": {
    "date:inception_lower": "1980-01-01",
    "date:inception_upper": "1980-01-01",
    "iso:country": "GB",
    "wof:name": "CB7 5QP",
    "wof:placetype": "postalcode"
  },
  "geometry": {"coordinates":[0.416555,52.340405],"type":"Point"}
}
