{
  "type": "Feature",
  "properties": {
    "iso:country": "GB",
    "wof:name": "CB7 5QP",
    "wof:placetype": "postalcode"
  },
  "geometry": {"coordinates":[0.416555,52.340405],"type":"Point"}
}
