{
  "type": "Feature",
  "properties": {
    "iso:country":"GB",
    "wof:name":"SK9 7EF",
    "wof:placetype":"postalcode"
},
  "geometry": {"coordinates":[-2.23661465668108,53.30028226675336],"type":"Point"}
}