{
  "type": "Feature",
  "properties": {
    "iso:country": "GB",
    "wof:name": "BH11 9QH",
    "wof:placetype": "postalcode"
  },
  "geometry": {"coordinates":[-1.93634,50.769633],"type":"Point"}
}
