{
  "type": "Feature",
  "properties": {
    "iso:country": "GB",
    "wof:name": "BH11 9QH",
    "wof:placetype": "postalcode"
  },
  "geometry": {"coordinates":[-1.936368,50.76957],"type":"Point"}
}
