{
  "type": "Feature",
  "properties": {
    "iso:country":"GB",
    "wof:name":"NE30 1PT",
    "wof:placetype":"postalcode"
},
  "geometry": {"coordinates":[-1.44550921730978,55.01121458284825],"type":"Point"}
}