{
  "type": "Feature",
  "properties": {
    "iso:country":"GB",
    "wof:name":"TS15 9RH",
    "wof:placetype":"postalcode"
},
  "geometry": {"coordinates":[-1.33672404494597,54.50628215114818],"type":"Point"}
}