{
  "type": "Feature",
  "properties": {
    "iso:country":"GB",
    "wof:name":"HU5 4PH",
    "wof:placetype":"postalcode"
},
  "geometry": {"coordinates":[-0.39333349616368,53.7646180265904],"type":"Point"}
}