{
  "type": "Feature",
  "properties": {
    "iso:country":"GB",
    "wof:name":"M5 4HL",
    "wof:placetype":"postalcode"
},
  "geometry": {"coordinates":[-2.28201110298098,53.48091731501776],"type":"Point"}
}