{
  "type": "Feature",
  "properties": {
    "iso:country":"GB",
    "wof:name":"B42 2PU",
    "wof:placetype":"postalcode"
},
  "geometry": {"coordinates":[-1.91158185954957,52.53906507394984],"type":"Point"}
}