{
  "type": "Feature",
  "properties": {
    "date:inception_lower": "1980-01-01",
    "date:inception_upper": "1980-01-01",
    "iso:country": "GB",
    "wof:name": "IV19 1QN",
    "wof:placetype": "postalcode"
  },
  "geometry": {"coordinates":[-3.974208,57.750104],"type":"Point"}
}
