{
  "type": "Feature",
  "properties": {
    "iso:country":"GB",
    "wof:name":"IV19 1QN",
    "wof:placetype":"postalcode"
},
  "geometry": {"coordinates":[-3.97420832385142,57.75010403555546],"type":"Point"}
}