{
  "type": "Feature",
  "properties": {
    "date:inception_lower":"2002-12-01",
    "date:inception_upper":"2002-12-31",
    "iso:country":"GB",
    "wof:name":"GU52 8LH",
    "wof:placetype":"postalcode"
},
  "geometry": {"coordinates":[-0.840947,51.255772],"type":"Point"}
}