{
  "type": "Feature",
  "properties": {
    "date:inception_lower": "1980-01-01",
    "date:inception_upper": "1980-01-01",
    "iso:country": "GB",
    "wof:name": "KY11 4TN",
    "wof:placetype": "postalcode"
  },
  "geometry": {"coordinates":[-3.448382,56.063955],"type":"Point"}
}
