{
  "type": "Feature",
  "properties": {
    "iso:country": "GB",
    "wof:name": "SY17 5LS",
    "wof:placetype": "postalcode"
  },
  "geometry": {"coordinates":[-3.530586,52.550326],"type":"Point"}
}
