{
  "type": "Feature",
  "properties": {
    "iso:country":"GB",
    "wof:name":"SY17 5LS",
    "wof:placetype":"postalcode"
},
  "geometry": {"coordinates":[-3.53058606645465,52.55032642106673],"type":"Point"}
}