{
  "type": "Feature",
  "properties": {
    "iso:country": "GB",
    "wof:name": "NG11 6LD",
    "wof:placetype": "postalcode"
  },
  "geometry": {"coordinates":[-1.148946,52.892947],"type":"Point"}
}
