{
  "type": "Feature",
  "properties": {
    "iso:country":"GB",
    "wof:name":"SG7 6TR",
    "wof:placetype":"postalcode"
},
  "geometry": {"coordinates":[-0.17402350485738,51.9920129680441],"type":"Point"}
}