{
  "type": "Feature",
  "properties": {
    "iso:country": "GB",
    "wof:name": "SG7 6TR",
    "wof:placetype": "postalcode"
  },
  "geometry": {"coordinates":[-0.174023,51.992013],"type":"Point"}
}
