{
  "type": "Feature",
  "properties": {
    "date:inception_lower": "1993-01-01",
    "date:inception_upper": "1993-01-01",
    "iso:country": "GB",
    "wof:name": "SY22 5DG",
    "wof:placetype": "postalcode"
  },
  "geometry": {"coordinates":[-3.273059,52.767084],"type":"Point"}
}
