{
  "type": "Feature",
  "properties": {
    "iso:country": "GB",
    "wof:name": "SY22 5DG",
    "wof:placetype": "postalcode"
  },
  "geometry": {"coordinates":[-3.273059,52.767084],"type":"Point"}
}
