{
  "type": "Feature",
  "properties": {
    "iso:country":"GB",
    "wof:name":"CT3 1UB",
    "wof:placetype":"postalcode"
},
  "geometry": {"coordinates":[1.15803373895258,51.28091228699872],"type":"Point"}
}