{
  "type": "Feature",
  "properties": {
    "date:inception_lower": "1980-01-01",
    "date:inception_upper": "1980-01-01",
    "iso:country": "GB",
    "wof:name": "CT3 1UB",
    "wof:placetype": "postalcode"
  },
  "geometry": {"coordinates":[1.158034,51.280912],"type":"Point"}
}
