{
  "type": "Feature",
  "properties": {
    "iso:country":"GB",
    "wof:name":"BN13 3BU",
    "wof:placetype":"postalcode"
},
  "geometry": {"coordinates":[-0.40908859922151,50.85038181804166],"type":"Point"}
}