{
  "type": "Feature",
  "properties": {
    "date:inception_lower": "1998-06-01",
    "date:inception_upper": "1998-06-01",
    "iso:country": "GB",
    "wof:name": "TA1 5ZD",
    "wof:placetype": "postalcode"
  },
  "geometry": {"coordinates":[-3.12104,51.012291],"type":"Point"}
}
