{
  "type": "Feature",
  "properties": {
    "date:inception_lower": "2018-02-01",
    "date:inception_upper": "2018-02-01",
    "iso:country": "GB",
    "wof:name": "DE55 1SH",
    "wof:placetype": "postalcode"
  },
  "geometry": {"coordinates":[-1.372106,53.080425],"type":"Point"}
}
