{
  "type": "Feature",
  "properties": {
    "date:inception_lower": "2009-06-01",
    "date:inception_upper": "2009-06-01",
    "iso:country": "GB",
    "wof:name": "MK17 9FH",
    "wof:placetype": "postalcode"
  },
  "geometry": {"coordinates":[-0.695095,52.004531],"type":"Point"}
}
