{
  "type": "Feature",
  "properties": {
    "iso:country":"GB",
    "wof:name":"MK17 9FH",
    "wof:placetype":"postalcode"
},
  "geometry": {"coordinates":[-0.69509497933932,52.00453094168445],"type":"Point"}
}