{
  "type": "Feature",
  "properties": {
    "date:inception_lower": "2023-01-01",
    "date:inception_upper": "2023-01-01",
    "iso:country": "GB",
    "wof:name": "CH4 7DJ",
    "wof:placetype": "postalcode"
  },
  "geometry": {"coordinates":[-2.908577,53.167762],"type":"Point"}
}
