{
  "type": "Feature",
  "properties": {
    "iso:country":"GB",
    "wof:name":"WV4 5BZ",
    "wof:placetype":"postalcode"
},
  "geometry": {"coordinates":[-2.13254875874702,52.56374549626138],"type":"Point"}
}