{
  "type": "Feature",
  "properties": {
    "date:inception_lower":"1980-01-01",
    "date:inception_upper":"1980-01-31",
    "iso:country":"GB",
    "wof:name":"B70 6PY",
    "wof:placetype":"postalcode"
},
  "geometry": {"coordinates":[-1.980713,52.512289],"type":"Point"}
}