{
  "type": "Feature",
  "properties": {
    "date:inception_lower": "1980-01-01",
    "date:inception_upper": "1980-01-01",
    "iso:country": "GB",
    "wof:name": "WV14 9DE",
    "wof:placetype": "postalcode"
  },
  "geometry": {"coordinates":[-2.086889,52.543369],"type":"Point"}
}
