{
  "type": "Feature",
  "properties": {
    "iso:country":"GB",
    "wof:name":"WV14 9DE",
    "wof:placetype":"postalcode"
},
  "geometry": {"coordinates":[-2.08689475515451,52.54335397743957],"type":"Point"}
}