{
  "type": "Feature",
  "properties": {
    "iso:country":"GB",
    "wof:name":"EX31 2BG",
    "wof:placetype":"postalcode"
},
  "geometry": {"coordinates":[-4.07147884556062,51.07261475875411],"type":"Point"}
}