{
  "type": "Feature",
  "properties": {
    "date:inception_lower": "1980-01-01",
    "date:inception_upper": "1980-01-01",
    "iso:country": "GB",
    "wof:name": "EX31 2BG",
    "wof:placetype": "postalcode"
  },
  "geometry": {"coordinates":[-4.071479,51.072615],"type":"Point"}
}
