{
  "type": "Feature",
  "properties": {
    "iso:country":"GB",
    "wof:name":"TF11 8AQ",
    "wof:placetype":"postalcode"
},
  "geometry": {"coordinates":[-2.37522254933447,52.66740744036748],"type":"Point"}
}