{
  "type": "Feature",
  "properties": {
    "iso:country": "GB",
    "wof:name": "TF11 8AQ",
    "wof:placetype": "postalcode"
  },
  "geometry": {"coordinates":[-2.375014,52.667495],"type":"Point"}
}
