{
  "type": "Feature",
  "properties": {
    "iso:country":"GB",
    "wof:name":"WS4 1JR",
    "wof:placetype":"postalcode"
},
  "geometry": {"coordinates":[-1.95824258109021,52.60538153777357],"type":"Point"}
}