{
  "type": "Feature",
  "properties": {
    "iso:country": "GB",
    "wof:name": "EH5 3DG",
    "wof:placetype": "postalcode"
  },
  "geometry": {"coordinates":[-3.200515,55.977342],"type":"Point"}
}
