{
  "type": "Feature",
  "properties": {
    "iso:country":"GB",
    "wof:name":"EH5 3DG",
    "wof:placetype":"postalcode"
},
  "geometry": {"coordinates":[-3.20051490457173,55.97734168709805],"type":"Point"}
}