{
  "type": "Feature",
  "properties": {
    "iso:country":"GB",
    "wof:name":"EN8 8UR",
    "wof:placetype":"postalcode"
},
  "geometry": {"coordinates":[-0.03378836454506,51.69749113241595],"type":"Point"}
}