{
  "type": "Feature",
  "properties": {
    "iso:country": "GB",
    "wof:name": "EN8 8UR",
    "wof:placetype": "postalcode"
  },
  "geometry": {"coordinates":[-0.033762,51.697494],"type":"Point"}
}
