{
  "type": "Feature",
  "properties": {
    "iso:country":"GB",
    "wof:name":"SS5 6DQ",
    "wof:placetype":"postalcode"
},
  "geometry": {"coordinates":[0.61062670652222,51.61828386181168],"type":"Point"}
}