{
  "type": "Feature",
  "properties": {
    "date:inception_lower": "1980-01-01",
    "date:inception_upper": "1980-01-01",
    "iso:country": "GB",
    "wof:name": "MK45 4LD",
    "wof:placetype": "postalcode"
  },
  "geometry": {"coordinates":[-0.426968,51.962377],"type":"Point"}
}
