{
  "type": "Feature",
  "properties": {
    "iso:country":"GB",
    "wof:name":"MK45 4LD",
    "wof:placetype":"postalcode"
},
  "geometry": {"coordinates":[-0.4269846643247,51.96221462345925],"type":"Point"}
}