{
  "type": "Feature",
  "properties": {
    "date:inception_lower": "1980-01-01",
    "date:inception_upper": "1980-01-01",
    "iso:country": "GB",
    "wof:name": "GU27 2JP",
    "wof:placetype": "postalcode"
  },
  "geometry": {"coordinates":[-0.707674,51.084842],"type":"Point"}
}
