{
  "type": "Feature",
  "properties": {
    "iso:country": "GB",
    "wof:name": "GU27 2JP",
    "wof:placetype": "postalcode"
  },
  "geometry": {"coordinates":[-0.707674,51.084842],"type":"Point"}
}
