{
  "type": "Feature",
  "properties": {
    "iso:country":"GB",
    "wof:name":"CV10 0FD",
    "wof:placetype":"postalcode"
},
  "geometry": {"coordinates":[-1.46990518946281,52.54217346977908],"type":"Point"}
}