{
  "type": "Feature",
  "properties": {
    "date:inception_lower":"2016-03-01",
    "date:inception_upper":"2016-03-31",
    "iso:country":"GB",
    "wof:name":"CV10 0FD",
    "wof:placetype":"postalcode"
},
  "geometry": {"coordinates":[-1.465374,52.544202],"type":"Point"}
}