{
  "type": "Feature",
  "properties": {
    "date:inception_lower": "2000-12-01",
    "date:inception_upper": "2000-12-01",
    "iso:country": "GB",
    "wof:name": "TS10 5SY",
    "wof:placetype": "postalcode"
  },
  "geometry": {"coordinates":[-1.093252,54.604711],"type":"Point"}
}
