{
  "type": "Feature",
  "properties": {
    "iso:country": "GB",
    "wof:name": "TS10 5SY",
    "wof:placetype": "postalcode"
  },
  "geometry": {"coordinates":[-1.093252,54.604711],"type":"Point"}
}
