{
  "type": "Feature",
  "properties": {
    "iso:country":"GB",
    "wof:name":"TS10 5SY",
    "wof:placetype":"postalcode"
},
  "geometry": {"coordinates":[-1.0932521846722,54.60471146465429],"type":"Point"}
}