{
  "type": "Feature",
  "properties": {
    "date:inception_lower": "1980-01-01",
    "date:inception_upper": "1980-01-01",
    "iso:country": "GB",
    "wof:name": "ME12 4LX",
    "wof:placetype": "postalcode"
  },
  "geometry": {"coordinates":[0.910671,51.39882],"type":"Point"}
}
