{
  "type": "Feature",
  "properties": {
    "iso:country": "GB",
    "wof:name": "GU34 1SN",
    "wof:placetype": "postalcode"
  },
  "geometry": {"coordinates":[-0.996896,51.13418],"type":"Point"}
}
