{
  "type": "Feature",
  "properties": {
    "iso:country": "GB",
    "wof:name": "OX3 7SH",
    "wof:placetype": "postalcode"
  },
  "geometry": {"coordinates":[-1.199763,51.741923],"type":"Point"}
}
