{
  "type": "Feature",
  "properties": {
    "date:inception_lower": "1998-06-01",
    "date:inception_upper": "1998-06-01",
    "iso:country": "GB",
    "wof:name": "OX3 7SH",
    "wof:placetype": "postalcode"
  },
  "geometry": {"coordinates":[-1.199763,51.741923],"type":"Point"}
}
