{
  "type": "Feature",
  "properties": {
    "iso:country":"GB",
    "wof:name":"OX3 7SH",
    "wof:placetype":"postalcode"
},
  "geometry": {"coordinates":[-1.19976289149488,51.74192305174752],"type":"Point"}
}