{
  "type": "Feature",
  "properties": {
    "iso:country":"GB",
    "wof:name":"SS6 7SL",
    "wof:placetype":"postalcode"
},
  "geometry": {"coordinates":[0.59967074043546,51.57825455655549],"type":"Point"}
}