{
  "type": "Feature",
  "properties": {
    "iso:country": "GB",
    "wof:name": "CT13 0ES",
    "wof:placetype": "postalcode"
  },
  "geometry": {"coordinates":[1.283312,51.24328],"type":"Point"}
}
