{
  "type": "Feature",
  "properties": {
    "iso:country":"GB",
    "wof:name":"CT13 0ES",
    "wof:placetype":"postalcode"
},
  "geometry": {"coordinates":[1.2833234192217,51.24323668472495],"type":"Point"}
}