{
  "type": "Feature",
  "properties": {
    "date:inception_lower": "2021-10-01",
    "date:inception_upper": "2021-10-01",
    "iso:country": "GB",
    "wof:name": "MK46 5GF",
    "wof:placetype": "postalcode"
  },
  "geometry": {"coordinates":[-0.71179,52.162574],"type":"Point"}
}
