{
  "type": "Feature",
  "properties": {
    "date:inception_lower": "1980-01-01",
    "date:inception_upper": "1980-01-01",
    "iso:country": "GB",
    "wof:name": "TN6 1SB",
    "wof:placetype": "postalcode"
  },
  "geometry": {"coordinates":[0.146812,51.065887],"type":"Point"}
}
