{
  "type": "Feature",
  "properties": {
    "date:inception_lower":"2009-10-01",
    "date:inception_upper":"2009-10-31",
    "iso:country":"GB",
    "wof:name":"CV21 2LS",
    "wof:placetype":"postalcode"
},
  "geometry": {"coordinates":[-1.265216,52.377513],"type":"Point"}
}