{
  "type": "Feature",
  "properties": {
    "iso:country": "GB",
    "wof:name": "CV21 2LS",
    "wof:placetype": "postalcode"
  },
  "geometry": {"coordinates":[-1.265204,52.377512],"type":"Point"}
}
