{
  "type": "Feature",
  "properties": {
    "date:inception_lower": "2009-10-01",
    "date:inception_upper": "2009-10-01",
    "iso:country": "GB",
    "wof:name": "CV21 2LS",
    "wof:placetype": "postalcode"
  },
  "geometry": {"coordinates":[-1.265204,52.377512],"type":"Point"}
}
