{
  "type": "Feature",
  "properties": {
    "iso:country": "GB",
    "wof:name": "NE31 1BY",
    "wof:placetype": "postalcode"
  },
  "geometry": {"coordinates":[-1.519565,54.979844],"type":"Point"}
}
