{
  "type": "Feature",
  "properties": {
    "iso:country":"GB",
    "wof:name":"NE31 1BY",
    "wof:placetype":"postalcode"
},
  "geometry": {"coordinates":[-1.5195645577777,54.97984374614986],"type":"Point"}
}