{
  "type": "Feature",
  "properties": {
    "iso:country":"GB",
    "wof:name":"UB6 8SZ",
    "wof:placetype":"postalcode"
},
  "geometry": {"coordinates":[-0.33513490783722,51.53448087553936],"type":"Point"}
}