{
  "type": "Feature",
  "properties": {
    "date:inception_lower":"1980-01-01",
    "date:inception_upper":"1980-01-31",
    "iso:country":"GB",
    "wof:name":"DH6 5AY",
    "wof:placetype":"postalcode"
},
  "geometry": {"coordinates":[-1.5224,54.732565],"type":"Point"}
}