{
  "type": "Feature",
  "properties": {
    "iso:country":"GB",
    "wof:name":"DH6 5AY",
    "wof:placetype":"postalcode"
},
  "geometry": {"coordinates":[-1.52239979854618,54.7325651349714],"type":"Point"}
}