{
  "type": "Feature",
  "properties": {
    "iso:country": "GB",
    "wof:name": "N19 3LZ",
    "wof:placetype": "postalcode"
  },
  "geometry": {"coordinates":[-0.128196,51.572151],"type":"Point"}
}
