{
  "type": "Feature",
  "properties": {
    "date:inception_lower": "2018-02-01",
    "date:inception_upper": "2018-02-01",
    "iso:country": "GB",
    "wof:name": "SK10 2ZE",
    "wof:placetype": "postalcode"
  },
  "geometry": {"coordinates":[-2.117918,53.28124],"type":"Point"}
}
