{
  "type": "Feature",
  "properties": {
    "iso:country": "GB",
    "wof:name": "DT11 7XH",
    "wof:placetype": "postalcode"
  },
  "geometry": {"coordinates":[-2.148281,50.864617],"type":"Point"}
}
