{
  "type": "Feature",
  "properties": {
    "iso:country": "GB",
    "wof:name": "SW19 7RD",
    "wof:placetype": "postalcode"
  },
  "geometry": {"coordinates":[-0.216192,51.425336],"type":"Point"}
}
