{
  "type": "Feature",
  "properties": {
    "iso:country":"GB",
    "wof:name":"SW19 7RD",
    "wof:placetype":"postalcode"
},
  "geometry": {"coordinates":[-0.21619228122713,51.42533555546031],"type":"Point"}
}