{
  "type": "Feature",
  "properties": {
    "date:inception_lower": "1980-01-01",
    "date:inception_upper": "1980-01-01",
    "iso:country": "GB",
    "wof:name": "SK2 6HJ",
    "wof:placetype": "postalcode"
  },
  "geometry": {"coordinates":[-2.143196,53.394354],"type":"Point"}
}
