{
  "type": "Feature",
  "properties": {
    "iso:country":"GB",
    "wof:name":"SK2 6HJ",
    "wof:placetype":"postalcode"
},
  "geometry": {"coordinates":[-2.14319561060232,53.39435354274444],"type":"Point"}
}