{
  "type": "Feature",
  "properties": {
    "iso:country":"GB",
    "wof:name":"EN5 4EQ",
    "wof:placetype":"postalcode"
},
  "geometry": {"coordinates":[-0.21789180040402,51.65489196713034],"type":"Point"}
}