{
  "type": "Feature",
  "properties": {
    "date:inception_lower": "1980-01-01",
    "date:inception_upper": "1980-01-01",
    "iso:country": "GB",
    "wof:name": "EN5 4EQ",
    "wof:placetype": "postalcode"
  },
  "geometry": {"coordinates":[-0.217866,51.654922],"type":"Point"}
}
