{
  "type": "Feature",
  "properties": {
    "date:inception_lower":"2005-01-01",
    "date:inception_upper":"2005-01-31",
    "iso:country":"GB",
    "wof:name":"NP10 8ED",
    "wof:placetype":"postalcode"
},
  "geometry": {"coordinates":[-3.023862,51.551208],"type":"Point"}
}