{
  "type": "Feature",
  "properties": {
    "iso:country":"GB",
    "wof:name":"NP10 8ED",
    "wof:placetype":"postalcode"
},
  "geometry": {"coordinates":[-3.02386237002881,51.5512077305083],"type":"Point"}
}