{
  "type": "Feature",
  "properties": {
    "iso:country": "GB",
    "wof:name": "YO19 4SR",
    "wof:placetype": "postalcode"
  },
  "geometry": {"coordinates":[-1.05029,53.904522],"type":"Point"}
}
