{
  "type": "Feature",
  "properties": {
    "iso:country":"GB",
    "wof:name":"YO19 4SR",
    "wof:placetype":"postalcode"
},
  "geometry": {"coordinates":[-1.05029016222037,53.90452212435049],"type":"Point"}
}