{
  "type": "Feature",
  "properties": {
    "iso:country":"GB",
    "wof:name":"W1D 5LL",
    "wof:placetype":"postalcode"
},
  "geometry": {"coordinates":[-0.13125798720848,51.51295772656927],"type":"Point"}
}