{
  "type": "Feature",
  "properties": {
    "date:inception_lower": "1992-08-01",
    "date:inception_upper": "1992-08-01",
    "iso:country": "GB",
    "wof:name": "DE21 5AA",
    "wof:placetype": "postalcode"
  },
  "geometry": {"coordinates":[-1.459106,52.972252],"type":"Point"}
}
