{
  "type": "Feature",
  "properties": {
    "iso:country": "GB",
    "wof:name": "DE21 5AA",
    "wof:placetype": "postalcode"
  },
  "geometry": {"coordinates":[-1.459106,52.972252],"type":"Point"}
}
