{
  "type": "Feature",
  "properties": {
    "iso:country":"GB",
    "wof:name":"DE21 5AA",
    "wof:placetype":"postalcode"
},
  "geometry": {"coordinates":[-1.45910627321333,52.97225200322312],"type":"Point"}
}