{
  "type": "Feature",
  "properties": {
    "iso:country": "GB",
    "wof:name": "BH13 7HS",
    "wof:placetype": "postalcode"
  },
  "geometry": {"coordinates":[-1.92049,50.704796],"type":"Point"}
}
