{
  "type": "Feature",
  "properties": {
    "iso:country":"GB",
    "wof:name":"TS10 4LY",
    "wof:placetype":"postalcode"
},
  "geometry": {"coordinates":[-1.06687976987091,54.60100614080335],"type":"Point"}
}