{
  "type": "Feature",
  "properties": {
    "iso:country":"GB",
    "wof:name":"IP26 5EP",
    "wof:placetype":"postalcode"
},
  "geometry": {"coordinates":[0.70475946936301,52.49573469742528],"type":"Point"}
}