{
  "type": "Feature",
  "properties": {
    "date:inception_lower": "1980-01-01",
    "date:inception_upper": "1980-01-01",
    "iso:country": "GB",
    "wof:name": "IP26 5EP",
    "wof:placetype": "postalcode"
  },
  "geometry": {"coordinates":[0.70476,52.495735],"type":"Point"}
}
