{
  "type": "Feature",
  "properties": {
    "iso:country": "GB",
    "wof:name": "HP11 2FP",
    "wof:placetype": "postalcode"
  },
  "geometry": {"coordinates":[-0.757895,51.629846],"type":"Point"}
}
