{
  "type": "Feature",
  "properties": {
    "date:inception_lower": "2018-07-01",
    "date:inception_upper": "2018-07-01",
    "iso:country": "GB",
    "wof:name": "HP11 2FP",
    "wof:placetype": "postalcode"
  },
  "geometry": {"coordinates":[-0.757895,51.629846],"type":"Point"}
}
