{
  "type": "Feature",
  "properties": {
    "iso:country": "GB",
    "wof:name": "CH46 0PF",
    "wof:placetype": "postalcode"
  },
  "geometry": {"coordinates":[-3.113109,53.400791],"type":"Point"}
}
