{
  "type": "Feature",
  "properties": {
    "date:inception_lower": "1999-06-01",
    "date:inception_upper": "1999-06-01",
    "iso:country": "GB",
    "wof:name": "CH46 0PF",
    "wof:placetype": "postalcode"
  },
  "geometry": {"coordinates":[-3.113107,53.400808],"type":"Point"}
}
