{
  "type": "Feature",
  "properties": {
    "iso:country":"GB",
    "wof:name":"SK8 4RD",
    "wof:placetype":"postalcode"
},
  "geometry": {"coordinates":[-2.2303105971375,53.38064432142636],"type":"Point"}
}