{
  "type": "Feature",
  "properties": {
    "date:inception_lower": "1993-08-01",
    "date:inception_upper": "1993-08-01",
    "iso:country": "GB",
    "wof:name": "SK8 4RD",
    "wof:placetype": "postalcode"
  },
  "geometry": {"coordinates":[-2.230311,53.380644],"type":"Point"}
}
