{
  "type": "Feature",
  "properties": {
    "date:inception_lower": "1980-01-01",
    "date:inception_upper": "1980-01-01",
    "iso:country": "GB",
    "wof:name": "ME14 2QJ",
    "wof:placetype": "postalcode"
  },
  "geometry": {"coordinates":[0.515992,51.289158],"type":"Point"}
}
