{
  "type": "Feature",
  "properties": {
    "iso:country": "GB",
    "wof:name": "ME14 2QJ",
    "wof:placetype": "postalcode"
  },
  "geometry": {"coordinates":[0.515992,51.289158],"type":"Point"}
}
