{
  "type": "Feature",
  "properties": {
    "iso:country":"GB",
    "wof:name":"RM1 4LZ",
    "wof:placetype":"postalcode"
},
  "geometry": {"coordinates":[0.18161787839628,51.60308591089503],"type":"Point"}
}