{
  "type": "Feature",
  "properties": {
    "date:inception_lower":"1980-01-01",
    "date:inception_upper":"1980-01-31",
    "iso:country":"GB",
    "wof:name":"PO15 6BZ",
    "wof:placetype":"postalcode"
},
  "geometry": {"coordinates":[-1.204529,50.862758],"type":"Point"}
}