{
  "type": "Feature",
  "properties": {
    "date:inception_lower":"2000-12-01",
    "date:inception_upper":"2000-12-31",
    "iso:country":"GB",
    "wof:name":"EH14 2AD",
    "wof:placetype":"postalcode"
},
  "geometry": {"coordinates":[-3.288269,55.916072],"type":"Point"}
}