{
  "type": "Feature",
  "properties": {
    "iso:country":"GB",
    "wof:name":"SA1 6NN",
    "wof:placetype":"postalcode"
},
  "geometry": {"coordinates":[-3.96661081760839,51.62376460245632],"type":"Point"}
}