{
  "type": "Feature",
  "properties": {
    "iso:country": "GB",
    "wof:name": "SN15 3FX",
    "wof:placetype": "postalcode"
  },
  "geometry": {"coordinates":[-2.109136,51.446065],"type":"Point"}
}
