{
  "type": "Feature",
  "properties": {
    "date:inception_lower":"1991-01-01",
    "date:inception_upper":"1991-01-31",
    "iso:country":"GB",
    "wof:name":"SN15 3FX",
    "wof:placetype":"postalcode"
},
  "geometry": {"coordinates":[-2.109136,51.446065],"type":"Point"}
}