{
  "type": "Feature",
  "properties": {
    "iso:country":"GB",
    "wof:name":"FK6 5JG",
    "wof:placetype":"postalcode"
},
  "geometry": {"coordinates":[-4.01910306507189,56.02998663063916],"type":"Point"}
}