{
  "type": "Feature",
  "properties": {
    "iso:country": "GB",
    "wof:name": "TS1 5PS",
    "wof:placetype": "postalcode"
  },
  "geometry": {"coordinates":[-1.251818,54.571989],"type":"Point"}
}
