{
  "type": "Feature",
  "properties": {
    "iso:country":"GB",
    "wof:name":"FK4 1JU",
    "wof:placetype":"postalcode"
},
  "geometry": {"coordinates":[-3.94967196035759,55.98857923249228],"type":"Point"}
}