{
  "type": "Feature",
  "properties": {
    "date:inception_lower": "1980-01-01",
    "date:inception_upper": "1980-01-01",
    "iso:country": "GB",
    "wof:name": "RM12 6TL",
    "wof:placetype": "postalcode"
  },
  "geometry": {"coordinates":[0.212367,51.543762],"type":"Point"}
}
