{
  "type": "Feature",
  "properties": {
    "iso:country": "GB",
    "wof:name": "BS22 8UL",
    "wof:placetype": "postalcode"
  },
  "geometry": {"coordinates":[-2.924717,51.357113],"type":"Point"}
}
