{
  "type": "Feature",
  "properties": {
    "iso:country":"GB",
    "wof:name":"BA15 1QN",
    "wof:placetype":"postalcode"
},
  "geometry": {"coordinates":[-2.25081320473749,51.34908789080264],"type":"Point"}
}