{
  "type": "Feature",
  "properties": {
    "iso:country":"GB",
    "wof:name":"DL6 3RW",
    "wof:placetype":"postalcode"
},
  "geometry": {"coordinates":[-1.41508203133525,54.32883920600445],"type":"Point"}
}