{
  "type": "Feature",
  "properties": {
    "iso:country":"GB",
    "wof:name":"G62 7PN",
    "wof:placetype":"postalcode"
},
  "geometry": {"coordinates":[-4.33406331208058,55.94365634911337],"type":"Point"}
}