{
  "type": "Feature",
  "properties": {
    "iso:country":"GB",
    "wof:name":"IP7 5DS",
    "wof:placetype":"postalcode"
},
  "geometry": {"coordinates":[0.95198138952619,52.04210899982368],"type":"Point"}
}