{
  "type": "Feature",
  "properties": {
    "iso:country":"GB",
    "wof:name":"SE9 6UE",
    "wof:placetype":"postalcode"
},
  "geometry": {"coordinates":[0.05115922974576,51.46359646983757],"type":"Point"}
}