{
  "type": "Feature",
  "properties": {
    "date:inception_lower":"2002-11-01",
    "date:inception_upper":"2002-11-30",
    "iso:country":"GB",
    "wof:name":"BH23 4UP",
    "wof:placetype":"postalcode"
},
  "geometry": {"coordinates":[-1.727979,50.744803],"type":"Point"}
}