{
  "type": "Feature",
  "properties": {
    "iso:country":"GB",
    "wof:name":"WD3 1QW",
    "wof:placetype":"postalcode"
},
  "geometry": {"coordinates":[-0.44805052619273,51.62836858654948],"type":"Point"}
}