{
  "type": "Feature",
  "properties": {
    "iso:country":"GB",
    "wof:name":"NG18 5DN",
    "wof:placetype":"postalcode"
},
  "geometry": {"coordinates":[-1.21801057699076,53.13182886996331],"type":"Point"}
}