{
  "type": "Feature",
  "properties": {
    "iso:country":"GB",
    "wof:name":"RM7 0EU",
    "wof:placetype":"postalcode"
},
  "geometry": {"coordinates":[0.15367884266135,51.56746898616764],"type":"Point"}
}