{
  "type": "Feature",
  "properties": {
    "date:inception_lower": "1980-01-01",
    "date:inception_upper": "1980-01-01",
    "iso:country": "GB",
    "wof:name": "RM7 0EU",
    "wof:placetype": "postalcode"
  },
  "geometry": {"coordinates":[0.153691,51.567462],"type":"Point"}
}
