{
  "type": "Feature",
  "properties": {
    "iso:country":"GB",
    "wof:name":"KT2 6HR",
    "wof:placetype":"postalcode"
},
  "geometry": {"coordinates":[-0.29719538939463,51.4143375544754],"type":"Point"}
}