{
  "type": "Feature",
  "properties": {
    "iso:country":"GB",
    "wof:name":"PO13 8ND",
    "wof:placetype":"postalcode"
},
  "geometry": {"coordinates":[-1.16753610887211,50.79846291093813],"type":"Point"}
}