{
  "type": "Feature",
  "properties": {
    "date:inception_lower": "2011-11-01",
    "date:inception_upper": "2011-11-01",
    "iso:country": "GB",
    "wof:name": "PO13 8ND",
    "wof:placetype": "postalcode"
  },
  "geometry": {"coordinates":[-1.167536,50.798463],"type":"Point"}
}
