{
  "type": "Feature",
  "properties": {
    "date:inception_lower":"1986-06-01",
    "date:inception_upper":"1986-06-30",
    "iso:country":"GB",
    "wof:name":"KY12 9YN",
    "wof:placetype":"postalcode"
},
  "geometry": {"coordinates":[-3.469649,56.079919],"type":"Point"}
}