{
  "type": "Feature",
  "properties": {
    "date:inception_lower": "1999-06-01",
    "date:inception_upper": "1999-06-01",
    "iso:country": "GB",
    "wof:name": "NP19 7LA",
    "wof:placetype": "postalcode"
  },
  "geometry": {"coordinates":[-2.978552,51.599169],"type":"Point"}
}
