{
  "type": "Feature",
  "properties": {
    "iso:country":"GB",
    "wof:name":"LS9 8JY",
    "wof:placetype":"postalcode"
},
  "geometry": {"coordinates":[-1.52375855540502,53.79361666565539],"type":"Point"}
}