{
  "type": "Feature",
  "properties": {
    "iso:country": "GB",
    "wof:name": "CV37 6EP",
    "wof:placetype": "postalcode"
  },
  "geometry": {"coordinates":[-1.707677,52.191133],"type":"Point"}
}
