{
  "type": "Feature",
  "properties": {
    "iso:country":"GB",
    "wof:name":"CV37 6EP",
    "wof:placetype":"postalcode"
},
  "geometry": {"coordinates":[-1.70767742529333,52.19113295551045],"type":"Point"}
}