{
  "type": "Feature",
  "properties": {
    "iso:country":"GB",
    "wof:name":"PE1 5LA",
    "wof:placetype":"postalcode"
},
  "geometry": {"coordinates":[-0.22692992526414,52.58126816317421],"type":"Point"}
}