{
  "type": "Feature",
  "properties": {
    "date:inception_lower": "1997-12-01",
    "date:inception_upper": "1997-12-01",
    "iso:country": "GB",
    "wof:name": "BS35 2LY",
    "wof:placetype": "postalcode"
  },
  "geometry": {"coordinates":[-2.512291,51.610151],"type":"Point"}
}
