{
  "type": "Feature",
  "properties": {
    "iso:country": "GB",
    "wof:name": "BS35 2LY",
    "wof:placetype": "postalcode"
  },
  "geometry": {"coordinates":[-2.512291,51.610151],"type":"Point"}
}
