{
  "type": "Feature",
  "properties": {
    "iso:country": "GB",
    "wof:name": "L30 7PX",
    "wof:placetype": "postalcode"
  },
  "geometry": {"coordinates":[-2.958529,53.48811],"type":"Point"}
}
