{
  "type": "Feature",
  "properties": {
    "date:inception_lower": "2022-12-01",
    "date:inception_upper": "2022-12-01",
    "iso:country": "GB",
    "wof:name": "OX10 6FN",
    "wof:placetype": "postalcode"
  },
  "geometry": {"coordinates":[-1.114654,51.626883],"type":"Point"}
}
