{
  "type": "Feature",
  "properties": {
    "iso:country": "GB",
    "wof:name": "ML3 6NU",
    "wof:placetype": "postalcode"
  },
  "geometry": {"coordinates":[-4.057384,55.772965],"type":"Point"}
}
