{
  "type": "Feature",
  "properties": {
    "iso:country":"GB",
    "wof:name":"TS15 9DE",
    "wof:placetype":"postalcode"
},
  "geometry": {"coordinates":[-1.3520238744346,54.50853095594668],"type":"Point"}
}