{
  "type": "Feature",
  "properties": {
    "date:inception_lower":"2002-06-01",
    "date:inception_upper":"2002-06-30",
    "iso:country":"GB",
    "wof:name":"BN24 5GF",
    "wof:placetype":"postalcode"
},
  "geometry": {"coordinates":[0.294921,50.815472],"type":"Point"}
}