{
  "type": "Feature",
  "properties": {
    "iso:country": "GB",
    "wof:name": "NE68 7SP",
    "wof:placetype": "postalcode"
  },
  "geometry": {"coordinates":[-1.65613,55.5829],"type":"Point"}
}
