{
  "type": "Feature",
  "properties": {
    "date:inception_lower": "1980-01-01",
    "date:inception_upper": "1980-01-01",
    "iso:country": "GB",
    "wof:name": "NE68 7SP",
    "wof:placetype": "postalcode"
  },
  "geometry": {"coordinates":[-1.655819,55.582216],"type":"Point"}
}
