{
  "type": "Feature",
  "properties": {
    "iso:country":"GB",
    "wof:name":"NE68 7SP",
    "wof:placetype":"postalcode"
},
  "geometry": {"coordinates":[-1.65610975602561,55.5829023853621],"type":"Point"}
}