{
  "type": "Feature",
  "properties": {
    "iso:country":"GB",
    "wof:name":"HR9 5RB",
    "wof:placetype":"postalcode"
},
  "geometry": {"coordinates":[-2.57794101016302,51.873423329184],"type":"Point"}
}