{
  "type": "Feature",
  "properties": {
    "iso:country":"GB",
    "wof:name":"LS14 2JE",
    "wof:placetype":"postalcode"
},
  "geometry": {"coordinates":[-1.45291226336344,53.83208004074888],"type":"Point"}
}