{
  "type": "Feature",
  "properties": {
    "date:inception_lower": "1987-04-01",
    "date:inception_upper": "1987-04-01",
    "iso:country": "GB",
    "wof:name": "LS14 2JE",
    "wof:placetype": "postalcode"
  },
  "geometry": {"coordinates":[-1.452912,53.83208],"type":"Point"}
}
