{
  "type": "Feature",
  "properties": {
    "iso:country":"GB",
    "wof:name":"NP12 2BS",
    "wof:placetype":"postalcode"
},
  "geometry": {"coordinates":[-3.19026926249523,51.65370777737719],"type":"Point"}
}