{
  "type": "Feature",
  "properties": {
    "iso:country":"GB",
    "wof:name":"BB1 9RA",
    "wof:placetype":"postalcode"
},
  "geometry": {"coordinates":[-2.47475767813071,53.77766664721736],"type":"Point"}
}