{
  "type": "Feature",
  "properties": {
    "iso:country":"GB",
    "wof:name":"S80 4NP",
    "wof:placetype":"postalcode"
},
  "geometry": {"coordinates":[-1.20706396175926,53.28224288918344],"type":"Point"}
}