{
  "type": "Feature",
  "properties": {
    "iso:country":"GB",
    "wof:name":"FY6 0NS",
    "wof:placetype":"postalcode"
},
  "geometry": {"coordinates":[-2.95810214569881,53.91592018192301],"type":"Point"}
}