{
  "type": "Feature",
  "properties": {
    "date:inception_lower": "1980-01-01",
    "date:inception_upper": "1980-01-01",
    "iso:country": "GB",
    "wof:name": "G83 0BD",
    "wof:placetype": "postalcode"
  },
  "geometry": {"coordinates":[-4.585714,55.979633],"type":"Point"}
}
