{
  "type": "Feature",
  "properties": {
    "date:inception_lower": "2020-04-01",
    "date:inception_upper": "2020-04-01",
    "iso:country": "GB",
    "wof:name": "NR3 3FD",
    "wof:placetype": "postalcode"
  },
  "geometry": {"coordinates":[1.291881,52.633412],"type":"Point"}
}
