{
  "type": "Feature",
  "properties": {
    "iso:country": "GB",
    "wof:name": "NR3 3FD",
    "wof:placetype": "postalcode"
  },
  "geometry": {"coordinates":[1.29229,52.641217],"type":"Point"}
}
