{
  "type": "Feature",
  "properties": {
    "iso:country": "GB",
    "wof:name": "TQ12 4DN",
    "wof:placetype": "postalcode"
  },
  "geometry": {"coordinates":[-3.584126,50.529574],"type":"Point"}
}
