{
  "type": "Feature",
  "properties": {
    "date:inception_lower": "1980-01-01",
    "date:inception_upper": "1980-01-01",
    "iso:country": "GB",
    "wof:name": "TQ12 4DN",
    "wof:placetype": "postalcode"
  },
  "geometry": {"coordinates":[-3.584126,50.529574],"type":"Point"}
}
