{
  "type": "Feature",
  "properties": {
    "iso:country":"GB",
    "wof:name":"TQ12 4DN",
    "wof:placetype":"postalcode"
},
  "geometry": {"coordinates":[-3.58412555190204,50.52957364394657],"type":"Point"}
}