{
  "type": "Feature",
  "properties": {
    "iso:country": "GB",
    "wof:name": "FY8 3RU",
    "wof:placetype": "postalcode"
  },
  "geometry": {"coordinates":[-3.013747,53.763561],"type":"Point"}
}
