{
  "type": "Feature",
  "properties": {
    "iso:country": "GB",
    "wof:name": "LL11 3SA",
    "wof:placetype": "postalcode"
  },
  "geometry": {"coordinates":[-3.071043,53.053471],"type":"Point"}
}
