{
  "type": "Feature",
  "properties": {
    "iso:country":"GB",
    "wof:name":"S2 5BR",
    "wof:placetype":"postalcode"
},
  "geometry": {"coordinates":[-1.44575397167788,53.38298839629483],"type":"Point"}
}