{
  "type": "Feature",
  "properties": {
    "iso:country":"GB",
    "wof:name":"BA3 2SW",
    "wof:placetype":"postalcode"
},
  "geometry": {"coordinates":[-2.49274761556019,51.29440468265096],"type":"Point"}
}