{
  "type": "Feature",
  "properties": {
    "iso:country":"GB",
    "wof:name":"CV8 2LD",
    "wof:placetype":"postalcode"
},
  "geometry": {"coordinates":[-1.55806197012015,52.32626944857275],"type":"Point"}
}