{
  "type": "Feature",
  "properties": {
    "date:inception_lower": "2001-12-01",
    "date:inception_upper": "2001-12-01",
    "iso:country": "GB",
    "wof:name": "DA11 0BP",
    "wof:placetype": "postalcode"
  },
  "geometry": {"coordinates":[0.365744,51.445385],"type":"Point"}
}
