{
  "type": "Feature",
  "properties": {
    "iso:country":"GB",
    "wof:name":"DA11 0BP",
    "wof:placetype":"postalcode"
},
  "geometry": {"coordinates":[0.36574365788424,51.44538476711943],"type":"Point"}
}