{
  "type": "Feature",
  "properties": {
    "iso:country": "GB",
    "wof:name": "DA11 0BP",
    "wof:placetype": "postalcode"
  },
  "geometry": {"coordinates":[0.365744,51.445385],"type":"Point"}
}
