{
  "type": "Feature",
  "properties": {
    "iso:country":"GB",
    "wof:name":"DD4 0SR",
    "wof:placetype":"postalcode"
},
  "geometry": {"coordinates":[-2.90381644300216,56.49262575392341],"type":"Point"}
}