{
  "type": "Feature",
  "properties": {
    "date:inception_lower": "2011-11-01",
    "date:inception_upper": "2011-11-01",
    "iso:country": "GB",
    "wof:name": "DD4 0SR",
    "wof:placetype": "postalcode"
  },
  "geometry": {"coordinates":[-2.903793,56.493488],"type":"Point"}
}
