{
  "type": "Feature",
  "properties": {
    "iso:country": "GB",
    "wof:name": "DD4 0SR",
    "wof:placetype": "postalcode"
  },
  "geometry": {"coordinates":[-2.903816,56.492626],"type":"Point"}
}
