{
  "type": "Feature",
  "properties": {
    "iso:country":"GB",
    "wof:name":"SA66 7TD",
    "wof:placetype":"postalcode"
},
  "geometry": {"coordinates":[-4.72931826700637,51.85929387995154],"type":"Point"}
}