{
  "type": "Feature",
  "properties": {
    "date:inception_lower": "2016-04-01",
    "date:inception_upper": "2016-04-01",
    "iso:country": "GB",
    "wof:name": "NN9 6US",
    "wof:placetype": "postalcode"
  },
  "geometry": {"coordinates":[-0.541133,52.352298],"type":"Point"}
}
