{
  "type": "Feature",
  "properties": {
    "iso:country": "GB",
    "wof:name": "KY12 0PU",
    "wof:placetype": "postalcode"
  },
  "geometry": {"coordinates":[-3.462696,56.085977],"type":"Point"}
}
