{
  "type": "Feature",
  "properties": {
    "iso:country":"GB",
    "wof:name":"KY12 0PU",
    "wof:placetype":"postalcode"
},
  "geometry": {"coordinates":[-3.46269616629598,56.08597687926542],"type":"Point"}
}