{
  "type": "Feature",
  "properties": {
    "iso:country":"GB",
    "wof:name":"WA8 3XF",
    "wof:placetype":"postalcode"
},
  "geometry": {"coordinates":[-2.71250372544184,53.40805163685418],"type":"Point"}
}