{
  "type": "Feature",
  "properties": {
    "iso:country": "GB",
    "wof:name": "GL54 3EE",
    "wof:placetype": "postalcode"
  },
  "geometry": {"coordinates":[-1.837939,51.830064],"type":"Point"}
}
