{
  "type": "Feature",
  "properties": {
    "date:inception_lower": "1980-01-01",
    "date:inception_upper": "1980-01-01",
    "iso:country": "GB",
    "wof:name": "SN8 2HW",
    "wof:placetype": "postalcode"
  },
  "geometry": {"coordinates":[-1.6343,51.425602],"type":"Point"}
}
