{
  "type": "Feature",
  "properties": {
    "iso:country":"GB",
    "wof:name":"SN8 2HW",
    "wof:placetype":"postalcode"
},
  "geometry": {"coordinates":[-1.63423965901345,51.42569263624942],"type":"Point"}
}