{
  "type": "Feature",
  "properties": {
    "iso:country":"GB",
    "wof:name":"HA8 9BD",
    "wof:placetype":"postalcode"
},
  "geometry": {"coordinates":[-0.2720740112805,51.6058849509121],"type":"Point"}
}