{
  "type": "Feature",
  "properties": {
    "iso:country": "GB",
    "wof:name": "RH14 9EQ",
    "wof:placetype": "postalcode"
  },
  "geometry": {"coordinates":[-0.459709,51.011482],"type":"Point"}
}
