{
  "type": "Feature",
  "properties": {
    "iso:country":"GB",
    "wof:name":"RH14 9EQ",
    "wof:placetype":"postalcode"
},
  "geometry": {"coordinates":[-0.4597342007185,51.01150550062621],"type":"Point"}
}