{
  "type": "Feature",
  "properties": {
    "iso:country": "GB",
    "wof:name": "DL7 8YR",
    "wof:placetype": "postalcode"
  },
  "geometry": {"coordinates":[-1.43208,54.329085],"type":"Point"}
}
