{
  "type": "Feature",
  "properties": {
    "iso:country":"GB",
    "wof:name":"DL7 8YR",
    "wof:placetype":"postalcode"
},
  "geometry": {"coordinates":[-1.43207000680671,54.32909107863296],"type":"Point"}
}