{
  "type": "Feature",
  "properties": {
    "date:inception_lower": "1990-02-01",
    "date:inception_upper": "1990-02-01",
    "iso:country": "GB",
    "wof:name": "DL7 8YR",
    "wof:placetype": "postalcode"
  },
  "geometry": {"coordinates":[-1.43208,54.329085],"type":"Point"}
}
