{
  "type": "Feature",
  "properties": {
    "iso:country":"GB",
    "wof:name":"TQ7 4HJ",
    "wof:placetype":"postalcode"
},
  "geometry": {"coordinates":[-3.89302663891039,50.29960399442166],"type":"Point"}
}