{
  "type": "Feature",
  "properties": {
    "iso:country": "GB",
    "wof:name": "WA7 3FP",
    "wof:placetype": "postalcode"
  },
  "geometry": {"coordinates":[-2.703967,53.31007],"type":"Point"}
}
