{
  "type": "Feature",
  "properties": {
    "date:inception_lower":"2000-12-01",
    "date:inception_upper":"2000-12-31",
    "iso:country":"GB",
    "wof:name":"WA7 3FP",
    "wof:placetype":"postalcode"
},
  "geometry": {"coordinates":[-2.703967,53.31007],"type":"Point"}
}