{
  "type": "Feature",
  "properties": {
    "iso:country":"GB",
    "wof:name":"WV6 6SE",
    "wof:placetype":"postalcode"
},
  "geometry": {"coordinates":[-2.19196088690543,52.62566657399859],"type":"Point"}
}