{
  "type": "Feature",
  "properties": {
    "date:inception_lower":"2012-09-01",
    "date:inception_upper":"2012-09-30",
    "iso:country":"GB",
    "wof:name":"L7 1QT",
    "wof:placetype":"postalcode"
},
  "geometry": {"coordinates":[-2.948739,53.405311],"type":"Point"}
}