{
  "type": "Feature",
  "properties": {
    "iso:country":"GB",
    "wof:name":"L7 1QT",
    "wof:placetype":"postalcode"
},
  "geometry": {"coordinates":[-2.94873897064402,53.40531128269164],"type":"Point"}
}