{
  "type": "Feature",
  "properties": {
    "iso:country":"GB",
    "wof:name":"NE61 6JS",
    "wof:placetype":"postalcode"
},
  "geometry": {"coordinates":[-1.66830940294844,55.15992720075104],"type":"Point"}
}