{
  "type": "Feature",
  "properties": {
    "date:inception_lower":"2002-12-01",
    "date:inception_upper":"2002-12-31",
    "iso:country":"GB",
    "wof:name":"NE61 6JS",
    "wof:placetype":"postalcode"
},
  "geometry": {"coordinates":[-1.668309,55.159927],"type":"Point"}
}