{
  "type": "Feature",
  "properties": {
    "date:inception_lower": "2018-01-01",
    "date:inception_upper": "2018-01-01",
    "iso:country": "GB",
    "wof:name": "SP1 1AL",
    "wof:placetype": "postalcode"
  },
  "geometry": {"coordinates":[-1.793876,51.070277],"type":"Point"}
}
