{
  "type": "Feature",
  "properties": {
    "date:inception_lower":"1990-08-01",
    "date:inception_upper":"1990-08-31",
    "iso:country":"GB",
    "wof:name":"AB54 4UR",
    "wof:placetype":"postalcode"
},
  "geometry": {"coordinates":[-2.835296,57.452963],"type":"Point"}
}