{
  "type": "Feature",
  "properties": {
    "date:inception_lower":"1998-06-01",
    "date:inception_upper":"1998-06-30",
    "iso:country":"GB",
    "wof:name":"YO41 4BW",
    "wof:placetype":"postalcode"
},
  "geometry": {"coordinates":[-0.924261,53.915135],"type":"Point"}
}