{
  "type": "Feature",
  "properties": {
    "iso:country": "GB",
    "wof:name": "YO41 4BW",
    "wof:placetype": "postalcode"
  },
  "geometry": {"coordinates":[-0.924261,53.915135],"type":"Point"}
}
