{
  "type": "Feature",
  "properties": {
    "iso:country":"GB",
    "wof:name":"YO41 4BW",
    "wof:placetype":"postalcode"
},
  "geometry": {"coordinates":[-0.92426076681467,53.91513513257006],"type":"Point"}
}