{
  "type": "Feature",
  "properties": {
    "date:inception_lower": "2020-09-01",
    "date:inception_upper": "2020-09-01",
    "iso:country": "GB",
    "wof:name": "WR5 2FZ",
    "wof:placetype": "postalcode"
  },
  "geometry": {"coordinates":[-2.1881,52.18037],"type":"Point"}
}
