{
  "type": "Feature",
  "properties": {
    "iso:country": "GB",
    "wof:name": "CA2 6JR",
    "wof:placetype": "postalcode"
  },
  "geometry": {"coordinates":[-2.965588,54.885254],"type":"Point"}
}
