{
  "type": "Feature",
  "properties": {
    "iso:country":"GB",
    "wof:name":"WR11 1EH",
    "wof:placetype":"postalcode"
},
  "geometry": {"coordinates":[-1.93575343507242,52.08702562769827],"type":"Point"}
}