{
  "type": "Feature",
  "properties": {
    "iso:country":"GB",
    "wof:name":"OX4 3LG",
    "wof:placetype":"postalcode"
},
  "geometry": {"coordinates":[-1.21924245130249,51.72934033693068],"type":"Point"}
}