{
  "type": "Feature",
  "properties": {
    "iso:country": "GB",
    "wof:name": "OX4 3LG",
    "wof:placetype": "postalcode"
  },
  "geometry": {"coordinates":[-1.219242,51.72934],"type":"Point"}
}
