{
  "type": "Feature",
  "properties": {
    "iso:country": "GB",
    "wof:name": "CH46 3RH",
    "wof:placetype": "postalcode"
  },
  "geometry": {"coordinates":[-3.105965,53.415329],"type":"Point"}
}
