{
  "type": "Feature",
  "properties": {
    "date:inception_lower": "1980-01-01",
    "date:inception_upper": "1980-01-01",
    "iso:country": "GB",
    "wof:name": "KA23 9EJ",
    "wof:placetype": "postalcode"
  },
  "geometry": {"coordinates":[-4.861562,55.693929],"type":"Point"}
}
