{
  "type": "Feature",
  "properties": {
    "iso:country":"GB",
    "wof:name":"PL26 7PN",
    "wof:placetype":"postalcode"
},
  "geometry": {"coordinates":[-4.89304277271903,50.34247597299643],"type":"Point"}
}