{
  "type": "Feature",
  "properties": {
    "date:inception_lower":"1992-08-01",
    "date:inception_upper":"1992-08-31",
    "iso:country":"GB",
    "wof:name":"PL26 7PN",
    "wof:placetype":"postalcode"
},
  "geometry": {"coordinates":[-4.893043,50.342476],"type":"Point"}
}