{
  "type": "Feature",
  "properties": {
    "iso:country":"GB",
    "wof:name":"CR0 6BT",
    "wof:placetype":"postalcode"
},
  "geometry": {"coordinates":[-0.0918666437964,51.37598579601019],"type":"Point"}
}