{
  "type": "Feature",
  "properties": {
    "iso:country": "GB",
    "wof:name": "WV7 3DJ",
    "wof:placetype": "postalcode"
  },
  "geometry": {"coordinates":[-2.274383,52.635708],"type":"Point"}
}
