{
  "type": "Feature",
  "properties": {
    "date:inception_lower":"1980-01-01",
    "date:inception_upper":"1980-01-31",
    "iso:country":"GB",
    "wof:name":"ST7 3BB",
    "wof:placetype":"postalcode"
},
  "geometry": {"coordinates":[-2.25369,53.100253],"type":"Point"}
}