{
  "type": "Feature",
  "properties": {
    "iso:country":"GB",
    "wof:name":"ST7 3BB",
    "wof:placetype":"postalcode"
},
  "geometry": {"coordinates":[-2.25369037098521,53.1002534382248],"type":"Point"}
}