{
  "type": "Feature",
  "properties": {
    "date:inception_lower": "1980-01-01",
    "date:inception_upper": "1980-01-01",
    "iso:country": "GB",
    "wof:name": "BD24 9JL",
    "wof:placetype": "postalcode"
  },
  "geometry": {"coordinates":[-2.281393,54.071939],"type":"Point"}
}
