{
  "type": "Feature",
  "properties": {
    "iso:country": "GB",
    "wof:name": "BD24 9JL",
    "wof:placetype": "postalcode"
  },
  "geometry": {"coordinates":[-2.28142,54.071917],"type":"Point"}
}
