{
  "type": "Feature",
  "properties": {
    "date:inception_lower":"2000-12-01",
    "date:inception_upper":"2000-12-31",
    "iso:country":"GB",
    "wof:name":"WC1A 2QS",
    "wof:placetype":"postalcode"
},
  "geometry": {"coordinates":[-0.12131,51.518376],"type":"Point"}
}