{
  "type": "Feature",
  "properties": {
    "iso:country": "GB",
    "wof:name": "WC1A 2QS",
    "wof:placetype": "postalcode"
  },
  "geometry": {"coordinates":[-0.12131,51.518376],"type":"Point"}
}
