{
  "type": "Feature",
  "properties": {
    "date:inception_lower": "1995-12-01",
    "date:inception_upper": "1995-12-01",
    "iso:country": "GB",
    "wof:name": "HU15 1LL",
    "wof:placetype": "postalcode"
  },
  "geometry": {"coordinates":[-0.571814,53.743003],"type":"Point"}
}
