{
  "type": "Feature",
  "properties": {
    "iso:country":"GB",
    "wof:name":"HU15 1LL",
    "wof:placetype":"postalcode"
},
  "geometry": {"coordinates":[-0.57181428751614,53.74300273000745],"type":"Point"}
}