{
  "type": "Feature",
  "properties": {
    "iso:country": "GB",
    "wof:name": "PH21 1JG",
    "wof:placetype": "postalcode"
  },
  "geometry": {"coordinates":[-4.047939,57.080585],"type":"Point"}
}
