{
  "type": "Feature",
  "properties": {
    "date:inception_lower": "1993-08-01",
    "date:inception_upper": "1993-08-01",
    "iso:country": "GB",
    "wof:name": "BA6 9LA",
    "wof:placetype": "postalcode"
  },
  "geometry": {"coordinates":[-2.728697,51.154294],"type":"Point"}
}
