{
  "type": "Feature",
  "properties": {
    "iso:country":"GB",
    "wof:name":"CO4 5YP",
    "wof:placetype":"postalcode"
},
  "geometry": {"coordinates":[0.88434567756859,51.90306423138672],"type":"Point"}
}