{
  "type": "Feature",
  "properties": {
    "iso:country":"GB",
    "wof:name":"CV47 9RA",
    "wof:placetype":"postalcode"
},
  "geometry": {"coordinates":[-1.38968002014038,52.27344778929276],"type":"Point"}
}