{
  "type": "Feature",
  "properties": {
    "date:inception_lower": "1999-12-01",
    "date:inception_upper": "1999-12-01",
    "iso:country": "GB",
    "wof:name": "CV47 9RA",
    "wof:placetype": "postalcode"
  },
  "geometry": {"coordinates":[-1.38968,52.273448],"type":"Point"}
}
