{
  "type": "Feature",
  "properties": {
    "date:inception_lower": "1980-01-01",
    "date:inception_upper": "1980-01-01",
    "iso:country": "GB",
    "wof:name": "SR2 7QE",
    "wof:placetype": "postalcode"
  },
  "geometry": {"coordinates":[-1.398031,54.896547],"type":"Point"}
}
