{
  "type": "Feature",
  "properties": {
    "date:inception_lower": "1980-01-01",
    "date:inception_upper": "1980-01-01",
    "iso:country": "GB",
    "wof:name": "TA21 0HS",
    "wof:placetype": "postalcode"
  },
  "geometry": {"coordinates":[-3.346449,50.997221],"type":"Point"}
}
