{
  "type": "Feature",
  "properties": {
    "iso:country":"GB",
    "wof:name":"TA21 0HS",
    "wof:placetype":"postalcode"
},
  "geometry": {"coordinates":[-3.34644947231445,50.99722092284649],"type":"Point"}
}