{
  "type": "Feature",
  "properties": {
    "date:inception_lower": "1999-06-01",
    "date:inception_upper": "1999-06-01",
    "iso:country": "GB",
    "wof:name": "CH63 3HQ",
    "wof:placetype": "postalcode"
  },
  "geometry": {"coordinates":[-3.009673,53.346122],"type":"Point"}
}
