{
  "type": "Feature",
  "properties": {
    "iso:country": "GB",
    "wof:name": "DL13 4BL",
    "wof:placetype": "postalcode"
  },
  "geometry": {"coordinates":[-1.818961,54.78489],"type":"Point"}
}
