{
  "type": "Feature",
  "properties": {
    "date:inception_lower": "2008-04-01",
    "date:inception_upper": "2008-04-01",
    "iso:country": "GB",
    "wof:name": "DL13 4BL",
    "wof:placetype": "postalcode"
  },
  "geometry": {"coordinates":[-1.818961,54.78489],"type":"Point"}
}
