{
  "type": "Feature",
  "properties": {
    "iso:country":"GB",
    "wof:name":"ML3 7YB",
    "wof:placetype":"postalcode"
},
  "geometry": {"coordinates":[-4.03680277480283,55.75681611028681],"type":"Point"}
}