{
  "type": "Feature",
  "properties": {
    "iso:country":"GB",
    "wof:name":"N11 3ER",
    "wof:placetype":"postalcode"
},
  "geometry": {"coordinates":[-0.1493157039907,51.61601847858783],"type":"Point"}
}