{
  "type": "Feature",
  "properties": {
    "iso:country":"GB",
    "wof:name":"WN7 3BG",
    "wof:placetype":"postalcode"
},
  "geometry": {"coordinates":[-2.49911099020584,53.49063407649049],"type":"Point"}
}