{
  "type": "Feature",
  "properties": {
    "iso:country": "GB",
    "wof:name": "WN7 3BG",
    "wof:placetype": "postalcode"
  },
  "geometry": {"coordinates":[-2.499064,53.490614],"type":"Point"}
}
