{
  "type": "Feature",
  "properties": {
    "date:inception_lower":"1980-01-01",
    "date:inception_upper":"1980-01-31",
    "iso:country":"GB",
    "wof:name":"TS16 0LH",
    "wof:placetype":"postalcode"
},
  "geometry": {"coordinates":[-1.357353,54.516333],"type":"Point"}
}