{
  "type": "Feature",
  "properties": {
    "iso:country":"GB",
    "wof:name":"SS0 7RU",
    "wof:placetype":"postalcode"
},
  "geometry": {"coordinates":[0.69414867088335,51.53636185819435],"type":"Point"}
}