{
  "type": "Feature",
  "properties": {
    "date:inception_lower": "1987-04-01",
    "date:inception_upper": "1987-04-01",
    "iso:country": "GB",
    "wof:name": "SS0 7RU",
    "wof:placetype": "postalcode"
  },
  "geometry": {"coordinates":[0.694149,51.536362],"type":"Point"}
}
