{
  "type": "Feature",
  "properties": {
    "date:inception_lower": "2001-12-01",
    "date:inception_upper": "2001-12-01",
    "iso:country": "GB",
    "wof:name": "PE15 0FE",
    "wof:placetype": "postalcode"
  },
  "geometry": {"coordinates":[0.078146,52.502541],"type":"Point"}
}
