{
  "type": "Feature",
  "properties": {
    "iso:country":"GB",
    "wof:name":"PE15 0FE",
    "wof:placetype":"postalcode"
},
  "geometry": {"coordinates":[0.07814581245519,52.5025410436434],"type":"Point"}
}