{
  "type": "Feature",
  "properties": {
    "iso:country":"GB",
    "wof:name":"G21 3SJ",
    "wof:placetype":"postalcode"
},
  "geometry": {"coordinates":[-4.20074205640237,55.89456896958796],"type":"Point"}
}