{
  "type": "Feature",
  "properties": {
    "iso:country":"GB",
    "wof:name":"DL16 6LT",
    "wof:placetype":"postalcode"
},
  "geometry": {"coordinates":[-1.59834645196675,54.7065543697741],"type":"Point"}
}