{
  "type": "Feature",
  "properties": {
    "date:inception_lower": "1980-01-01",
    "date:inception_upper": "1980-01-01",
    "iso:country": "GB",
    "wof:name": "DL16 6LT",
    "wof:placetype": "postalcode"
  },
  "geometry": {"coordinates":[-1.598346,54.706554],"type":"Point"}
}
