{
  "type": "Feature",
  "properties": {
    "iso:country":"GB",
    "wof:name":"S12 2HA",
    "wof:placetype":"postalcode"
},
  "geometry": {"coordinates":[-1.42732154484714,53.34604761289873],"type":"Point"}
}