{
  "type": "Feature",
  "properties": {
    "date:inception_lower": "2023-06-01",
    "date:inception_upper": "2023-06-01",
    "iso:country": "GB",
    "wof:name": "YO11 2EE",
    "wof:placetype": "postalcode"
  },
  "geometry": {"coordinates":[-0.399339,54.275598],"type":"Point"}
}
