{
  "type": "Feature",
  "properties": {
    "iso:country":"GB",
    "wof:name":"B97 5PP",
    "wof:placetype":"postalcode"
},
  "geometry": {"coordinates":[-1.97865897899887,52.2769815930359],"type":"Point"}
}