{
  "type": "Feature",
  "properties": {
    "iso:country":"GB",
    "wof:name":"BN10 8AW",
    "wof:placetype":"postalcode"
},
  "geometry": {"coordinates":[0.00341267658692,50.80361131790904],"type":"Point"}
}