{
  "type": "Feature",
  "properties": {
    "date:inception_lower": "1990-07-01",
    "date:inception_upper": "1990-07-01",
    "iso:country": "GB",
    "wof:name": "BN10 8AW",
    "wof:placetype": "postalcode"
  },
  "geometry": {"coordinates":[0.003413,50.803611],"type":"Point"}
}
