{
  "type": "Feature",
  "properties": {
    "iso:country":"GB",
    "wof:name":"PE31 7EH",
    "wof:placetype":"postalcode"
},
  "geometry": {"coordinates":[0.49048098217825,52.90592043345738],"type":"Point"}
}