{
  "type": "Feature",
  "properties": {
    "iso:country": "GB",
    "wof:name": "PE31 7EH",
    "wof:placetype": "postalcode"
  },
  "geometry": {"coordinates":[0.490481,52.90592],"type":"Point"}
}
