{
  "type": "Feature",
  "properties": {
    "date:inception_lower": "1995-07-01",
    "date:inception_upper": "1995-07-01",
    "iso:country": "GB",
    "wof:name": "WR4 0LG",
    "wof:placetype": "postalcode"
  },
  "geometry": {"coordinates":[-2.171639,52.211256],"type":"Point"}
}
