{
  "type": "Feature",
  "properties": {
    "iso:country": "GB",
    "wof:name": "RG19 4RH",
    "wof:placetype": "postalcode"
  },
  "geometry": {"coordinates":[-1.249246,51.396147],"type":"Point"}
}
