{
  "type": "Feature",
  "properties": {
    "iso:country":"GB",
    "wof:name":"CA7 8AG",
    "wof:placetype":"postalcode"
},
  "geometry": {"coordinates":[-3.11511635164078,54.80359646435767],"type":"Point"}
}