{
  "type": "Feature",
  "properties": {
    "iso:country":"GB",
    "wof:name":"SS6 9LD",
    "wof:placetype":"postalcode"
},
  "geometry": {"coordinates":[0.60380308843627,51.59624871423905],"type":"Point"}
}