{
  "type": "Feature",
  "properties": {
    "iso:country":"GB",
    "wof:name":"S71 2RT",
    "wof:placetype":"postalcode"
},
  "geometry": {"coordinates":[-1.44509818109789,53.57319229095482],"type":"Point"}
}