{
  "type": "Feature",
  "properties": {
    "iso:country":"GB",
    "wof:name":"SN4 0ET",
    "wof:placetype":"postalcode"
},
  "geometry": {"coordinates":[-1.72224893952312,51.52761013883591],"type":"Point"}
}