{
  "type": "Feature",
  "properties": {
    "iso:country": "GB",
    "wof:name": "SN4 0ET",
    "wof:placetype": "postalcode"
  },
  "geometry": {"coordinates":[-1.722249,51.52761],"type":"Point"}
}
