{
  "type": "Feature",
  "properties": {
    "iso:country":"GB",
    "wof:name":"LS25 5HQ",
    "wof:placetype":"postalcode"
},
  "geometry": {"coordinates":[-1.23155789435209,53.75410765421346],"type":"Point"}
}