{
  "type": "Feature",
  "properties": {
    "iso:country":"GB",
    "wof:name":"WF6 1QW",
    "wof:placetype":"postalcode"
},
  "geometry": {"coordinates":[-1.40463958756947,53.70336475945295],"type":"Point"}
}