{
  "type": "Feature",
  "properties": {
    "iso:country": "GB",
    "wof:name": "WF6 1QW",
    "wof:placetype": "postalcode"
  },
  "geometry": {"coordinates":[-1.40464,53.703365],"type":"Point"}
}
