{
  "type": "Feature",
  "properties": {
    "iso:country": "GB",
    "wof:name": "GL56 9LF",
    "wof:placetype": "postalcode"
  },
  "geometry": {"coordinates":[-1.737817,52.020797],"type":"Point"}
}
