{
  "type": "Feature",
  "properties": {
    "date:inception_lower": "1996-06-01",
    "date:inception_upper": "1996-06-01",
    "iso:country": "GB",
    "wof:name": "EH23 4TQ",
    "wof:placetype": "postalcode"
  },
  "geometry": {"coordinates":[-3.051043,55.841761],"type":"Point"}
}
