{
  "type": "Feature",
  "properties": {
    "iso:country":"GB",
    "wof:name":"EH23 4TQ",
    "wof:placetype":"postalcode"
},
  "geometry": {"coordinates":[-3.05104270015493,55.84176097345323],"type":"Point"}
}