{
  "type": "Feature",
  "properties": {
    "date:inception_lower": "2007-07-01",
    "date:inception_upper": "2007-07-01",
    "iso:country": "GB",
    "wof:name": "B92 7BQ",
    "wof:placetype": "postalcode"
  },
  "geometry": {"coordinates":[-1.813339,52.430736],"type":"Point"}
}
