{
  "type": "Feature",
  "properties": {
    "date:inception_lower": "1980-01-01",
    "date:inception_upper": "1980-01-01",
    "iso:country": "GB",
    "wof:name": "WV14 8TE",
    "wof:placetype": "postalcode"
  },
  "geometry": {"coordinates":[-2.076496,52.553283],"type":"Point"}
}
