{
  "type": "Feature",
  "properties": {
    "iso:country": "GB",
    "wof:name": "WV14 8TE",
    "wof:placetype": "postalcode"
  },
  "geometry": {"coordinates":[-2.076364,52.553266],"type":"Point"}
}
