{
  "type": "Feature",
  "properties": {
    "iso:country": "GB",
    "wof:name": "DY7 5JU",
    "wof:placetype": "postalcode"
  },
  "geometry": {"coordinates":[-2.253839,52.486729],"type":"Point"}
}
