{
  "type": "Feature",
  "properties": {
    "date:inception_lower": "2020-04-01",
    "date:inception_upper": "2020-04-01",
    "iso:country": "GB",
    "wof:name": "OL4 2AY",
    "wof:placetype": "postalcode"
  },
  "geometry": {"coordinates":[-2.077881,53.556807],"type":"Point"}
}
