{
  "type": "Feature",
  "properties": {
    "iso:country": "GB",
    "wof:name": "OL4 2AY",
    "wof:placetype": "postalcode"
  },
  "geometry": {"coordinates":[-2.077881,53.556807],"type":"Point"}
}
