{
  "type": "Feature",
  "properties": {
    "iso:country":"GB",
    "wof:name":"ME2 2TT",
    "wof:placetype":"postalcode"
},
  "geometry": {"coordinates":[0.45883098117635,51.39690968522985],"type":"Point"}
}