{
  "type": "Feature",
  "properties": {
    "iso:country":"GB",
    "wof:name":"DN15 8ES",
    "wof:placetype":"postalcode"
},
  "geometry": {"coordinates":[-0.6622359225043,53.59236768337541],"type":"Point"}
}