{
  "type": "Feature",
  "properties": {
    "iso:country": "GB",
    "wof:name": "DN14 8QL",
    "wof:placetype": "postalcode"
  },
  "geometry": {"coordinates":[-0.966121,53.698363],"type":"Point"}
}
