{
  "type": "Feature",
  "properties": {
    "iso:country":"GB",
    "wof:name":"DN14 8QL",
    "wof:placetype":"postalcode"
},
  "geometry": {"coordinates":[-0.966146781471,53.69837060816142],"type":"Point"}
}