{
  "type": "Feature",
  "properties": {
    "iso:country":"GB",
    "wof:name":"NN15 5YZ",
    "wof:placetype":"postalcode"
},
  "geometry": {"coordinates":[-0.68496450086357,52.37165531106029],"type":"Point"}
}