{
  "type": "Feature",
  "properties": {
    "iso:country":"GB",
    "wof:name":"EH11 3DH",
    "wof:placetype":"postalcode"
},
  "geometry": {"coordinates":[-3.25947450712675,55.93302058490264],"type":"Point"}
}