{
  "type": "Feature",
  "properties": {
    "date:inception_lower": "2019-02-01",
    "date:inception_upper": "2019-02-01",
    "iso:country": "GB",
    "wof:name": "IP26 4FA",
    "wof:placetype": "postalcode"
  },
  "geometry": {"coordinates":[0.533218,52.471487],"type":"Point"}
}
