{
  "type": "Feature",
  "properties": {
    "iso:country":"GB",
    "wof:name":"S71 3NA",
    "wof:placetype":"postalcode"
},
  "geometry": {"coordinates":[-1.4810956448374,53.58463419839785],"type":"Point"}
}