{
  "type": "Feature",
  "properties": {
    "iso:country":"GB",
    "wof:name":"IV36 1JD",
    "wof:placetype":"postalcode"
},
  "geometry": {"coordinates":[-3.63563345342556,57.60515064508115],"type":"Point"}
}