{
  "type": "Feature",
  "properties": {
    "iso:country": "GB",
    "wof:name": "YO14 0EY",
    "wof:placetype": "postalcode"
  },
  "geometry": {"coordinates":[-0.3211,54.200748],"type":"Point"}
}
