{
  "type": "Feature",
  "properties": {
    "iso:country":"GB",
    "wof:name":"YO14 0EY",
    "wof:placetype":"postalcode"
},
  "geometry": {"coordinates":[-0.32110019227212,54.20074764250638],"type":"Point"}
}