{
  "type": "Feature",
  "properties": {
    "date:inception_lower": "1995-07-01",
    "date:inception_upper": "1995-07-01",
    "iso:country": "GB",
    "wof:name": "YO14 0EY",
    "wof:placetype": "postalcode"
  },
  "geometry": {"coordinates":[-0.3211,54.200748],"type":"Point"}
}
