{
  "type": "Feature",
  "properties": {
    "iso:country": "GB",
    "wof:name": "GL7 3ND",
    "wof:placetype": "postalcode"
  },
  "geometry": {"coordinates":[-1.773146,51.742575],"type":"Point"}
}
