{
  "type": "Feature",
  "properties": {
    "date:inception_lower":"1985-10-01",
    "date:inception_upper":"1985-10-31",
    "iso:country":"GB",
    "wof:name":"GU4 7YD",
    "wof:placetype":"postalcode"
},
  "geometry": {"coordinates":[-0.548835,51.256221],"type":"Point"}
}