{
  "type": "Feature",
  "properties": {
    "date:inception_lower": "1980-01-01",
    "date:inception_upper": "1980-01-01",
    "iso:country": "GB",
    "wof:name": "TN25 5NG",
    "wof:placetype": "postalcode"
  },
  "geometry": {"coordinates":[0.941403,51.134033],"type":"Point"}
}
