{
  "type": "Feature",
  "properties": {
    "iso:country":"GB",
    "wof:name":"TN25 5NG",
    "wof:placetype":"postalcode"
},
  "geometry": {"coordinates":[0.94137129894045,51.13403200324382],"type":"Point"}
}