{
  "type": "Feature",
  "properties": {
    "iso:country": "GB",
    "wof:name": "TN25 5NG",
    "wof:placetype": "postalcode"
  },
  "geometry": {"coordinates":[0.941403,51.134033],"type":"Point"}
}
