{
  "type": "Feature",
  "properties": {
    "iso:country":"GB",
    "wof:name":"ST5 3PY",
    "wof:placetype":"postalcode"
},
  "geometry": {"coordinates":[-2.2300571700759,52.99840096605764],"type":"Point"}
}