{
  "type": "Feature",
  "properties": {
    "date:inception_lower": "1980-01-01",
    "date:inception_upper": "1980-01-01",
    "iso:country": "GB",
    "wof:name": "TQ9 7AL",
    "wof:placetype": "postalcode"
  },
  "geometry": {"coordinates":[-3.66941,50.329195],"type":"Point"}
}
