{
  "type": "Feature",
  "properties": {
    "iso:country":"GB",
    "wof:name":"TQ9 7AL",
    "wof:placetype":"postalcode"
},
  "geometry": {"coordinates":[-3.66940991297259,50.3291950947553],"type":"Point"}
}