{
  "type": "Feature",
  "properties": {
    "iso:country": "GB",
    "wof:name": "NE16 4AS",
    "wof:placetype": "postalcode"
  },
  "geometry": {"coordinates":[-1.686028,54.94579],"type":"Point"}
}
