{
  "type": "Feature",
  "properties": {
    "iso:country":"GB",
    "wof:name":"RG40 3DG",
    "wof:placetype":"postalcode"
},
  "geometry": {"coordinates":[-0.78618588357536,51.4016817174362],"type":"Point"}
}