{
  "type": "Feature",
  "properties": {
    "iso:country":"GB",
    "wof:name":"WN5 8PG",
    "wof:placetype":"postalcode"
},
  "geometry": {"coordinates":[-2.70102966664909,53.54443225196736],"type":"Point"}
}