{
  "type": "Feature",
  "properties": {
    "iso:country":"GB",
    "wof:name":"OX28 1EH",
    "wof:placetype":"postalcode"
},
  "geometry": {"coordinates":[-1.46481597540637,51.79496546034013],"type":"Point"}
}