{
  "type": "Feature",
  "properties": {
    "iso:country":"GB",
    "wof:name":"B69 3BL",
    "wof:placetype":"postalcode"
},
  "geometry": {"coordinates":[-2.01418850757371,52.5068952201824],"type":"Point"}
}