{
  "type": "Feature",
  "properties": {
    "date:inception_lower": "2008-06-01",
    "date:inception_upper": "2008-06-01",
    "iso:country": "GB",
    "wof:name": "B69 3BL",
    "wof:placetype": "postalcode"
  },
  "geometry": {"coordinates":[-2.014188,52.506895],"type":"Point"}
}
