{
  "type": "Feature",
  "properties": {
    "date:inception_lower": "2016-08-01",
    "date:inception_upper": "2016-08-01",
    "iso:country": "GB",
    "wof:name": "PL22 0FB",
    "wof:placetype": "postalcode"
  },
  "geometry": {"coordinates":[-4.661566,50.411575],"type":"Point"}
}
