{
  "type": "Feature",
  "properties": {
    "iso:country": "GB",
    "wof:name": "PO4 0HR",
    "wof:placetype": "postalcode"
  },
  "geometry": {"coordinates":[-1.071155,50.787942],"type":"Point"}
}
