{
  "type": "Feature",
  "properties": {
    "iso:country":"GB",
    "wof:name":"PO4 0HR",
    "wof:placetype":"postalcode"
},
  "geometry": {"coordinates":[-1.07115515260997,50.78794238918746],"type":"Point"}
}