{
  "type": "Feature",
  "properties": {
    "iso:country":"GB",
    "wof:name":"HD5 8XY",
    "wof:placetype":"postalcode"
},
  "geometry": {"coordinates":[-1.74089161660423,53.6341407428101],"type":"Point"}
}