{
  "type": "Feature",
  "properties": {
    "iso:country":"GB",
    "wof:name":"GL4 3AN",
    "wof:placetype":"postalcode"
},
  "geometry": {"coordinates":[-2.21171302484881,51.86048333234472],"type":"Point"}
}