{
  "type": "Feature",
  "properties": {
    "iso:country": "GB",
    "wof:name": "GL4 3AN",
    "wof:placetype": "postalcode"
  },
  "geometry": {"coordinates":[-2.211713,51.860483],"type":"Point"}
}
