{
  "type": "Feature",
  "properties": {
    "date:inception_lower": "1980-01-01",
    "date:inception_upper": "1980-01-01",
    "iso:country": "GB",
    "wof:name": "N16 5AR",
    "wof:placetype": "postalcode"
  },
  "geometry": {"coordinates":[-0.083878,51.574925],"type":"Point"}
}
