{
  "type": "Feature",
  "properties": {
    "iso:country":"GB",
    "wof:name":"N16 5AR",
    "wof:placetype":"postalcode"
},
  "geometry": {"coordinates":[-0.08387844052241,51.57492514417861],"type":"Point"}
}