{
  "type": "Feature",
  "properties": {
    "date:inception_lower": "1980-01-01",
    "date:inception_upper": "1980-01-01",
    "iso:country": "GB",
    "wof:name": "PO13 9AE",
    "wof:placetype": "postalcode"
  },
  "geometry": {"coordinates":[-1.193408,50.794913],"type":"Point"}
}
