{
  "type": "Feature",
  "properties": {
    "iso:country":"GB",
    "wof:name":"PO13 9AE",
    "wof:placetype":"postalcode"
},
  "geometry": {"coordinates":[-1.19340822728913,50.79491262084294],"type":"Point"}
}