{
  "type": "Feature",
  "properties": {
    "iso:country":"GB",
    "wof:name":"NP22 3AX",
    "wof:placetype":"postalcode"
},
  "geometry": {"coordinates":[-3.2810485573291,51.78730333059098],"type":"Point"}
}