{
  "type": "Feature",
  "properties": {
    "date:inception_lower":"1980-01-01",
    "date:inception_upper":"1980-01-31",
    "iso:country":"GB",
    "wof:name":"L20 3BU",
    "wof:placetype":"postalcode"
},
  "geometry": {"coordinates":[-2.985425,53.451433],"type":"Point"}
}