{
  "type": "Feature",
  "properties": {
    "iso:country":"GB",
    "wof:name":"OX18 4NY",
    "wof:placetype":"postalcode"
},
  "geometry": {"coordinates":[-1.63469877001582,51.80392328249219],"type":"Point"}
}