{
  "type": "Feature",
  "properties": {
    "iso:country": "GB",
    "wof:name": "OX18 4NY",
    "wof:placetype": "postalcode"
  },
  "geometry": {"coordinates":[-1.634699,51.803923],"type":"Point"}
}
