{
  "type": "Feature",
  "properties": {
    "iso:country":"GB",
    "wof:name":"M33 7ES",
    "wof:placetype":"postalcode"
},
  "geometry": {"coordinates":[-2.32024475799671,53.42759091071689],"type":"Point"}
}