{
  "type": "Feature",
  "properties": {
    "date:inception_lower": "2018-01-01",
    "date:inception_upper": "2018-01-01",
    "iso:country": "GB",
    "wof:name": "LU1 5FY",
    "wof:placetype": "postalcode"
  },
  "geometry": {"coordinates":[-0.42183,51.875322],"type":"Point"}
}
