{
  "type": "Feature",
  "properties": {
    "iso:country":"GB",
    "wof:name":"OL6 9AH",
    "wof:placetype":"postalcode"
},
  "geometry": {"coordinates":[-2.04967541821552,53.50961663622239],"type":"Point"}
}