{
  "type": "Feature",
  "properties": {
    "iso:country": "GB",
    "wof:name": "OL6 9AH",
    "wof:placetype": "postalcode"
  },
  "geometry": {"coordinates":[-2.049129,53.508034],"type":"Point"}
}
