{
  "type": "Feature",
  "properties": {
    "iso:country": "GB",
    "wof:name": "BH13 7PF",
    "wof:placetype": "postalcode"
  },
  "geometry": {"coordinates":[-1.930568,50.698211],"type":"Point"}
}
