{
  "type": "Feature",
  "properties": {
    "iso:country":"GB",
    "wof:name":"NN6 7DZ",
    "wof:placetype":"postalcode"
},
  "geometry": {"coordinates":[-1.07498601571604,52.34255356051042],"type":"Point"}
}