{
  "type": "Feature",
  "properties": {
    "date:inception_lower":"1994-12-01",
    "date:inception_upper":"1994-12-31",
    "iso:country":"GB",
    "wof:name":"NN6 7DZ",
    "wof:placetype":"postalcode"
},
  "geometry": {"coordinates":[-1.075247,52.342716],"type":"Point"}
}