{
  "type": "Feature",
  "properties": {
    "iso:country": "GB",
    "wof:name": "RG22 5DZ",
    "wof:placetype": "postalcode"
  },
  "geometry": {"coordinates":[-1.129423,51.262103],"type":"Point"}
}
