{
  "type": "Feature",
  "properties": {
    "date:inception_lower":"1980-01-01",
    "date:inception_upper":"1980-01-31",
    "iso:country":"GB",
    "wof:name":"RG22 5DZ",
    "wof:placetype":"postalcode"
},
  "geometry": {"coordinates":[-1.129423,51.262103],"type":"Point"}
}