{
  "type": "Feature",
  "properties": {
    "date:inception_lower":"2005-05-01",
    "date:inception_upper":"2005-05-31",
    "iso:country":"GB",
    "wof:name":"SP6 1TD",
    "wof:placetype":"postalcode"
},
  "geometry": {"coordinates":[-1.819854,50.932133],"type":"Point"}
}