{
  "type": "Feature",
  "properties": {
    "iso:country": "GB",
    "wof:name": "SP6 1TD",
    "wof:placetype": "postalcode"
  },
  "geometry": {"coordinates":[-1.819854,50.932133],"type":"Point"}
}
