{
  "type": "Feature",
  "properties": {
    "iso:country":"GB",
    "wof:name":"SP6 1TD",
    "wof:placetype":"postalcode"
},
  "geometry": {"coordinates":[-1.81985360247625,50.93213258733272],"type":"Point"}
}