{
  "type": "Feature",
  "properties": {
    "date:inception_lower": "1980-01-01",
    "date:inception_upper": "1980-01-01",
    "iso:country": "GB",
    "wof:name": "LL61 6YR",
    "wof:placetype": "postalcode"
  },
  "geometry": {"coordinates":[-4.324487,53.166044],"type":"Point"}
}
