{
  "type": "Feature",
  "properties": {
    "iso:country":"GB",
    "wof:name":"CF64 3JR",
    "wof:placetype":"postalcode"
},
  "geometry": {"coordinates":[-3.18315102808028,51.43112401246296],"type":"Point"}
}