{
  "type": "Feature",
  "properties": {
    "iso:country":"GB",
    "wof:name":"SW6 1TP",
    "wof:placetype":"postalcode"
},
  "geometry": {"coordinates":[-0.19892551868774,51.48837883473288],"type":"Point"}
}