{
  "type": "Feature",
  "properties": {
    "iso:country":"GB",
    "wof:name":"TR4 9DP",
    "wof:placetype":"postalcode"
},
  "geometry": {"coordinates":[-5.09184753229836,50.29295238710432],"type":"Point"}
}