{
  "type": "Feature",
  "properties": {
    "date:inception_lower": "1995-07-01",
    "date:inception_upper": "1995-07-01",
    "iso:country": "GB",
    "wof:name": "CM7 2SY",
    "wof:placetype": "postalcode"
  },
  "geometry": {"coordinates":[0.546623,51.88318],"type":"Point"}
}
