{
  "type": "Feature",
  "properties": {
    "date:inception_lower": "1980-01-01",
    "date:inception_upper": "1980-01-01",
    "iso:country": "GB",
    "wof:name": "SK8 5JS",
    "wof:placetype": "postalcode"
  },
  "geometry": {"coordinates":[-2.19565,53.385156],"type":"Point"}
}
