{
  "type": "Feature",
  "properties": {
    "iso:country":"GB",
    "wof:name":"SK8 5JS",
    "wof:placetype":"postalcode"
},
  "geometry": {"coordinates":[-2.19565026406407,53.38515558462819],"type":"Point"}
}