{
  "type": "Feature",
  "properties": {
    "date:inception_lower": "1991-09-01",
    "date:inception_upper": "1991-09-01",
    "iso:country": "GB",
    "wof:name": "DN14 7YW",
    "wof:placetype": "postalcode"
  },
  "geometry": {"coordinates":[-0.723693,53.707817],"type":"Point"}
}
