{
  "type": "Feature",
  "properties": {
    "iso:country": "GB",
    "wof:name": "DN14 7YW",
    "wof:placetype": "postalcode"
  },
  "geometry": {"coordinates":[-0.723693,53.707817],"type":"Point"}
}
