{
  "type": "Feature",
  "properties": {
    "iso:country":"GB",
    "wof:name":"CM2 7EG",
    "wof:placetype":"postalcode"
},
  "geometry": {"coordinates":[0.49926335873787,51.72217838412845],"type":"Point"}
}