{
  "type": "Feature",
  "properties": {
    "date:inception_lower": "1980-01-01",
    "date:inception_upper": "1980-01-01",
    "iso:country": "GB",
    "wof:name": "CM2 7EG",
    "wof:placetype": "postalcode"
  },
  "geometry": {"coordinates":[0.499263,51.722178],"type":"Point"}
}
