{
  "type": "Feature",
  "properties": {
    "iso:country":"GB",
    "wof:name":"TS1 3JR",
    "wof:placetype":"postalcode"
},
  "geometry": {"coordinates":[-1.22864242256619,54.57062702059896],"type":"Point"}
}