{
  "type": "Feature",
  "properties": {
    "iso:country":"GB",
    "wof:name":"SO40 4XD",
    "wof:placetype":"postalcode"
},
  "geometry": {"coordinates":[-1.44792890434674,50.89304623114448],"type":"Point"}
}