{
  "type": "Feature",
  "properties": {
    "date:inception_lower": "1980-01-01",
    "date:inception_upper": "1980-01-01",
    "iso:country": "GB",
    "wof:name": "PO2 9AH",
    "wof:placetype": "postalcode"
  },
  "geometry": {"coordinates":[-1.07834,50.819348],"type":"Point"}
}
