{
  "type": "Feature",
  "properties": {
    "iso:country":"GB",
    "wof:name":"DH8 5TW",
    "wof:placetype":"postalcode"
},
  "geometry": {"coordinates":[-1.83650247765792,54.86151482287406],"type":"Point"}
}