{
  "type": "Feature",
  "properties": {
    "date:inception_lower": "1999-06-01",
    "date:inception_upper": "1999-06-01",
    "iso:country": "GB",
    "wof:name": "CF24 3RQ",
    "wof:placetype": "postalcode"
  },
  "geometry": {"coordinates":[-3.169421,51.493028],"type":"Point"}
}
