{
  "type": "Feature",
  "properties": {
    "iso:country": "GB",
    "wof:name": "PO32 6DH",
    "wof:placetype": "postalcode"
  },
  "geometry": {"coordinates":[-1.286214,50.751487],"type":"Point"}
}
