{
  "type": "Feature",
  "properties": {
    "iso:country":"GB",
    "wof:name":"RM3 7GN",
    "wof:placetype":"postalcode"
},
  "geometry": {"coordinates":[0.21009242411352,51.61044882223815],"type":"Point"}
}