{
  "type": "Feature",
  "properties": {
    "iso:country":"GB",
    "wof:name":"N1 0HB",
    "wof:placetype":"postalcode"
},
  "geometry": {"coordinates":[-0.11131098534308,51.53422926895039],"type":"Point"}
}