{
  "type": "Feature",
  "properties": {
    "iso:country": "GB",
    "wof:name": "N1 0HB",
    "wof:placetype": "postalcode"
  },
  "geometry": {"coordinates":[-0.111311,51.534229],"type":"Point"}
}
