{
  "type": "Feature",
  "properties": {
    "date:inception_lower": "2006-07-01",
    "date:inception_upper": "2006-07-01",
    "iso:country": "GB",
    "wof:name": "LA11 6DE",
    "wof:placetype": "postalcode"
  },
  "geometry": {"coordinates":[-2.90878,54.193339],"type":"Point"}
}
