{
  "type": "Feature",
  "properties": {
    "date:inception_lower": "1998-06-01",
    "date:inception_upper": "1998-06-01",
    "iso:country": "GB",
    "wof:name": "YO25 3XR",
    "wof:placetype": "postalcode"
  },
  "geometry": {"coordinates":[-0.569102,54.069878],"type":"Point"}
}
