{
  "type": "Feature",
  "properties": {
    "iso:country": "GB",
    "wof:name": "LA14 4BN",
    "wof:placetype": "postalcode"
  },
  "geometry": {"coordinates":[-3.235084,54.136425],"type":"Point"}
}
