{
  "type": "Feature",
  "properties": {
    "iso:country":"GB",
    "wof:name":"HR2 6HP",
    "wof:placetype":"postalcode"
},
  "geometry": {"coordinates":[-2.71145074228588,52.03836734717299],"type":"Point"}
}