{
  "type": "Feature",
  "properties": {
    "date:inception_lower":"1980-01-01",
    "date:inception_upper":"1980-01-31",
    "iso:country":"GB",
    "wof:name":"HR2 6HP",
    "wof:placetype":"postalcode"
},
  "geometry": {"coordinates":[-2.711451,52.038367],"type":"Point"}
}