{
  "type": "Feature",
  "properties": {
    "date:inception_lower": "1980-01-01",
    "date:inception_upper": "1980-01-01",
    "iso:country": "GB",
    "wof:name": "DG2 7EB",
    "wof:placetype": "postalcode"
  },
  "geometry": {"coordinates":[-3.609397,55.05977],"type":"Point"}
}
