{
  "type": "Feature",
  "properties": {
    "iso:country":"GB",
    "wof:name":"ST5 2SW",
    "wof:placetype":"postalcode"
},
  "geometry": {"coordinates":[-2.23332381935999,53.01286716821002],"type":"Point"}
}