{
  "type": "Feature",
  "properties": {
    "date:inception_lower":"2003-06-01",
    "date:inception_upper":"2003-06-30",
    "iso:country":"GB",
    "wof:name":"KT16 9HP",
    "wof:placetype":"postalcode"
},
  "geometry": {"coordinates":[-0.510877,51.38813],"type":"Point"}
}