{
  "type": "Feature",
  "properties": {
    "iso:country":"GB",
    "wof:name":"KT16 9HP",
    "wof:placetype":"postalcode"
},
  "geometry": {"coordinates":[-0.51087737178588,51.38813011306915],"type":"Point"}
}