{
  "type": "Feature",
  "properties": {
    "iso:country": "GB",
    "wof:name": "LE9 6HY",
    "wof:placetype": "postalcode"
  },
  "geometry": {"coordinates":[-1.222447,52.520211],"type":"Point"}
}
