{
  "type": "Feature",
  "properties": {
    "iso:country":"GB",
    "wof:name":"E4 6JA",
    "wof:placetype":"postalcode"
},
  "geometry": {"coordinates":[0.00919930822984,51.61925741969416],"type":"Point"}
}