{
  "type": "Feature",
  "properties": {
    "iso:country": "GB",
    "wof:name": "CW5 7LL",
    "wof:placetype": "postalcode"
  },
  "geometry": {"coordinates":[-2.44994,53.044695],"type":"Point"}
}
