{
  "type": "Feature",
  "properties": {
    "iso:country":"GB",
    "wof:name":"CW5 7LL",
    "wof:placetype":"postalcode"
},
  "geometry": {"coordinates":[-2.44994002556535,53.04469546932067],"type":"Point"}
}