{
  "type": "Feature",
  "properties": {
    "iso:country":"GB",
    "wof:name":"TR1 1RD",
    "wof:placetype":"postalcode"
},
  "geometry": {"coordinates":[-5.0411605975021,50.27256620565143],"type":"Point"}
}