{
  "type": "Feature",
  "properties": {
    "date:inception_lower": "1985-10-01",
    "date:inception_upper": "1985-10-01",
    "iso:country": "GB",
    "wof:name": "LN7 6JN",
    "wof:placetype": "postalcode"
  },
  "geometry": {"coordinates":[-0.427029,53.503182],"type":"Point"}
}
