{
  "type": "Feature",
  "properties": {
    "iso:country":"GB",
    "wof:name":"CF43 4NH",
    "wof:placetype":"postalcode"
},
  "geometry": {"coordinates":[-3.44777943091242,51.66583109688306],"type":"Point"}
}