{
  "type": "Feature",
  "properties": {
    "iso:country": "GB",
    "wof:name": "NE11 0HT",
    "wof:placetype": "postalcode"
  },
  "geometry": {"coordinates":[-1.624221,54.918762],"type":"Point"}
}
