{
  "type": "Feature",
  "properties": {
    "iso:country":"GB",
    "wof:name":"NE11 0HT",
    "wof:placetype":"postalcode"
},
  "geometry": {"coordinates":[-1.62392847508898,54.91878063099262],"type":"Point"}
}