{
  "type": "Feature",
  "properties": {
    "date:inception_lower":"2015-09-01",
    "date:inception_upper":"2015-09-30",
    "iso:country":"GB",
    "wof:name":"NE11 0HT",
    "wof:placetype":"postalcode"
},
  "geometry": {"coordinates":[-1.623924,54.918797],"type":"Point"}
}