{
  "type": "Feature",
  "properties": {
    "iso:country":"GB",
    "wof:name":"S60 1PD",
    "wof:placetype":"postalcode"
},
  "geometry": {"coordinates":[-1.3566765039556,53.43093704499682],"type":"Point"}
}