{
  "type": "Feature",
  "properties": {
    "iso:country": "GB",
    "wof:name": "NR18 8EU",
    "wof:placetype": "postalcode"
  },
  "geometry": {"coordinates":[1.110638,52.571663],"type":"Point"}
}
