{
  "type": "Feature",
  "properties": {
    "iso:country":"GB",
    "wof:name":"DG12 5HL",
    "wof:placetype":"postalcode"
},
  "geometry": {"coordinates":[-3.25311687829266,54.9955786599004],"type":"Point"}
}