{
  "type": "Feature",
  "properties": {
    "iso:country":"GB",
    "wof:name":"ME2 3LX",
    "wof:placetype":"postalcode"
},
  "geometry": {"coordinates":[0.49091285698345,51.40366051234069],"type":"Point"}
}