{
  "type": "Feature",
  "properties": {
    "iso:country":"GB",
    "wof:name":"WF8 3NH",
    "wof:placetype":"postalcode"
},
  "geometry": {"coordinates":[-1.30191315322653,53.68003405601846],"type":"Point"}
}