{
  "type": "Feature",
  "properties": {
    "iso:country":"GB",
    "wof:name":"DA17 5PY",
    "wof:placetype":"postalcode"
},
  "geometry": {"coordinates":[0.14940408298136,51.49118015300697],"type":"Point"}
}