{
  "type": "Feature",
  "properties": {
    "date:inception_lower": "1980-01-01",
    "date:inception_upper": "1980-01-01",
    "iso:country": "GB",
    "wof:name": "DA17 5PY",
    "wof:placetype": "postalcode"
  },
  "geometry": {"coordinates":[0.149404,51.49118],"type":"Point"}
}
