{
  "type": "Feature",
  "properties": {
    "date:inception_lower": "1980-01-01",
    "date:inception_upper": "1980-01-01",
    "iso:country": "GB",
    "wof:name": "TA21 0QB",
    "wof:placetype": "postalcode"
  },
  "geometry": {"coordinates":[-3.353299,50.955415],"type":"Point"}
}
