{
  "type": "Feature",
  "properties": {
    "iso:country":"GB",
    "wof:name":"TA21 0QB",
    "wof:placetype":"postalcode"
},
  "geometry": {"coordinates":[-3.35329928860721,50.95541520341642],"type":"Point"}
}