{
  "type": "Feature",
  "properties": {
    "iso:country": "GB",
    "wof:name": "NR30 2PA",
    "wof:placetype": "postalcode"
  },
  "geometry": {"coordinates":[1.728267,52.605737],"type":"Point"}
}
