{
  "type": "Feature",
  "properties": {
    "iso:country":"GB",
    "wof:name":"NR30 2PA",
    "wof:placetype":"postalcode"
},
  "geometry": {"coordinates":[1.72820220995546,52.60574839485167],"type":"Point"}
}