{
  "type": "Feature",
  "properties": {
    "iso:country": "GB",
    "wof:name": "IP29 5BH",
    "wof:placetype": "postalcode"
  },
  "geometry": {"coordinates":[0.703031,52.20575],"type":"Point"}
}
