{
  "type": "Feature",
  "properties": {
    "date:inception_lower": "2019-01-01",
    "date:inception_upper": "2019-01-01",
    "iso:country": "GB",
    "wof:name": "IP29 5BH",
    "wof:placetype": "postalcode"
  },
  "geometry": {"coordinates":[0.703031,52.20575],"type":"Point"}
}
