{
  "type": "Feature",
  "properties": {
    "iso:country":"GB",
    "wof:name":"NW4 4AP",
    "wof:placetype":"postalcode"
},
  "geometry": {"coordinates":[-0.22989393586617,51.58650754047491],"type":"Point"}
}