{
  "type": "Feature",
  "properties": {
    "iso:country":"GB",
    "wof:name":"NW10 3ER",
    "wof:placetype":"postalcode"
},
  "geometry": {"coordinates":[-0.22063051072404,51.5376199390048],"type":"Point"}
}