{
  "type": "Feature",
  "properties": {
    "iso:country":"GB",
    "wof:name":"TN17 4LS",
    "wof:placetype":"postalcode"
},
  "geometry": {"coordinates":[0.62948355848053,51.05044452335293],"type":"Point"}
}