{
  "type": "Feature",
  "properties": {
    "iso:country": "GB",
    "wof:name": "CA17 4JE",
    "wof:placetype": "postalcode"
  },
  "geometry": {"coordinates":[-2.347267,54.456402],"type":"Point"}
}
