{
  "type": "Feature",
  "properties": {
    "iso:country":"GB",
    "wof:name":"TN15 6BJ",
    "wof:placetype":"postalcode"
},
  "geometry": {"coordinates":[0.25190178391896,51.34694907885737],"type":"Point"}
}