{
  "type": "Feature",
  "properties": {
    "iso:country":"GB",
    "wof:name":"EC4A 3BA",
    "wof:placetype":"postalcode"
},
  "geometry": {"coordinates":[-0.10769540818376,51.51536762361194],"type":"Point"}
}