{
  "type": "Feature",
  "properties": {
    "date:inception_lower": "1980-01-01",
    "date:inception_upper": "1980-01-01",
    "iso:country": "GB",
    "wof:name": "EH26 8PS",
    "wof:placetype": "postalcode"
  },
  "geometry": {"coordinates":[-3.222972,55.798124],"type":"Point"}
}
