{
  "type": "Feature",
  "properties": {
    "date:inception_lower": "1980-01-01",
    "date:inception_upper": "1980-01-01",
    "iso:country": "GB",
    "wof:name": "W13 0DY",
    "wof:placetype": "postalcode"
  },
  "geometry": {"coordinates":[-0.324457,51.515859],"type":"Point"}
}
