{
  "type": "Feature",
  "properties": {
    "iso:country": "GB",
    "wof:name": "W13 0DY",
    "wof:placetype": "postalcode"
  },
  "geometry": {"coordinates":[-0.324457,51.515859],"type":"Point"}
}
