{
  "type": "Feature",
  "properties": {
    "iso:country":"GB",
    "wof:name":"W13 0DY",
    "wof:placetype":"postalcode"
},
  "geometry": {"coordinates":[-0.32445688603575,51.51585869531647],"type":"Point"}
}