{
  "type": "Feature",
  "properties": {
    "iso:country":"GB",
    "wof:name":"N11 3ET",
    "wof:placetype":"postalcode"
},
  "geometry": {"coordinates":[-0.14953278478592,51.61565321423699],"type":"Point"}
}