{
  "type": "Feature",
  "properties": {
    "date:inception_lower": "1980-01-01",
    "date:inception_upper": "1980-01-01",
    "iso:country": "GB",
    "wof:name": "N11 3ET",
    "wof:placetype": "postalcode"
  },
  "geometry": {"coordinates":[-0.149536,51.615665],"type":"Point"}
}
