{
  "type": "Feature",
  "properties": {
    "iso:country":"GB",
    "wof:name":"W1H 5JG",
    "wof:placetype":"postalcode"
},
  "geometry": {"coordinates":[-0.16448289865282,51.51748403917813],"type":"Point"}
}