{
  "type": "Feature",
  "properties": {
    "date:inception_lower": "2000-12-01",
    "date:inception_upper": "2000-12-01",
    "iso:country": "GB",
    "wof:name": "W1H 5JG",
    "wof:placetype": "postalcode"
  },
  "geometry": {"coordinates":[-0.164483,51.517484],"type":"Point"}
}
