{
  "type": "Feature",
  "properties": {
    "date:inception_lower": "1998-12-01",
    "date:inception_upper": "1998-12-01",
    "iso:country": "GB",
    "wof:name": "DA9 9SP",
    "wof:placetype": "postalcode"
  },
  "geometry": {"coordinates":[0.272579,51.439144],"type":"Point"}
}
