{
  "type": "Feature",
  "properties": {
    "iso:country": "GB",
    "wof:name": "DA9 9SP",
    "wof:placetype": "postalcode"
  },
  "geometry": {"coordinates":[0.272426,51.439254],"type":"Point"}
}
