{
  "type": "Feature",
  "properties": {
    "iso:country":"GB",
    "wof:name":"DA9 9SP",
    "wof:placetype":"postalcode"
},
  "geometry": {"coordinates":[0.27239771011712,51.43925495750688],"type":"Point"}
}