{
  "type": "Feature",
  "properties": {
    "iso:country":"GB",
    "wof:name":"SA70 7LX",
    "wof:placetype":"postalcode"
},
  "geometry": {"coordinates":[-4.7049538446116,51.67138244402744],"type":"Point"}
}