{
  "type": "Feature",
  "properties": {
    "iso:country": "GB",
    "wof:name": "SA70 7LX",
    "wof:placetype": "postalcode"
  },
  "geometry": {"coordinates":[-4.704888,51.671465],"type":"Point"}
}
