{
  "type": "Feature",
  "properties": {
    "date:inception_lower":"1980-01-01",
    "date:inception_upper":"1980-01-31",
    "iso:country":"GB",
    "wof:name":"SA70 7LX",
    "wof:placetype":"postalcode"
},
  "geometry": {"coordinates":[-4.704986,51.671409],"type":"Point"}
}