{
  "type": "Feature",
  "properties": {
    "iso:country":"GB",
    "wof:name":"LN1 1EY",
    "wof:placetype":"postalcode"
},
  "geometry": {"coordinates":[-0.5420738100074,53.23153262465392],"type":"Point"}
}