{
  "type": "Feature",
  "properties": {
    "date:inception_lower":"1980-01-01",
    "date:inception_upper":"1980-01-31",
    "iso:country":"GB",
    "wof:name":"OX14 2DQ",
    "wof:placetype":"postalcode"
},
  "geometry": {"coordinates":[-1.270432,51.687405],"type":"Point"}
}