{
  "type": "Feature",
  "properties": {
    "date:inception_lower": "1982-03-01",
    "date:inception_upper": "1982-03-01",
    "iso:country": "GB",
    "wof:name": "HU12 8NY",
    "wof:placetype": "postalcode"
  },
  "geometry": {"coordinates":[-0.184888,53.738235],"type":"Point"}
}
