{
  "type": "Feature",
  "properties": {
    "iso:country":"GB",
    "wof:name":"HU12 8NY",
    "wof:placetype":"postalcode"
},
  "geometry": {"coordinates":[-0.184888489228,53.73823458652937],"type":"Point"}
}