{
  "type": "Feature",
  "properties": {
    "iso:country":"GB",
    "wof:name":"BS34 6AX",
    "wof:placetype":"postalcode"
},
  "geometry": {"coordinates":[-2.56174270844412,51.539198310113],"type":"Point"}
}