{
  "type": "Feature",
  "properties": {
    "iso:country":"GB",
    "wof:name":"WF4 6EL",
    "wof:placetype":"postalcode"
},
  "geometry": {"coordinates":[-1.5661799982189,53.66323383058379],"type":"Point"}
}