{
  "type": "Feature",
  "properties": {
    "date:inception_lower": "1980-01-01",
    "date:inception_upper": "1980-01-01",
    "iso:country": "GB",
    "wof:name": "WF4 6EL",
    "wof:placetype": "postalcode"
  },
  "geometry": {"coordinates":[-1.56618,53.663234],"type":"Point"}
}
