{
  "type": "Feature",
  "properties": {
    "iso:country":"GB",
    "wof:name":"HU6 9DX",
    "wof:placetype":"postalcode"
},
  "geometry": {"coordinates":[-0.38568212478312,53.79282177718525],"type":"Point"}
}