{
  "type": "Feature",
  "properties": {
    "date:inception_lower": "2007-08-01",
    "date:inception_upper": "2007-08-01",
    "iso:country": "GB",
    "wof:name": "HU6 9DX",
    "wof:placetype": "postalcode"
  },
  "geometry": {"coordinates":[-0.386264,53.792086],"type":"Point"}
}
