{
  "type": "Feature",
  "properties": {
    "iso:country": "GB",
    "wof:name": "G75 0EQ",
    "wof:placetype": "postalcode"
  },
  "geometry": {"coordinates":[-4.183757,55.755864],"type":"Point"}
}
