{
  "type": "Feature",
  "properties": {
    "iso:country":"GB",
    "wof:name":"DE7 8NL",
    "wof:placetype":"postalcode"
},
  "geometry": {"coordinates":[-1.31190186955936,52.98576655921475],"type":"Point"}
}