{
  "type": "Feature",
  "properties": {
    "iso:country":"GB",
    "wof:name":"DY4 0NL",
    "wof:placetype":"postalcode"
},
  "geometry": {"coordinates":[-2.05177752548927,52.53600293151839],"type":"Point"}
}