{
  "type": "Feature",
  "properties": {
    "iso:country": "GB",
    "wof:name": "DA13 0HX",
    "wof:placetype": "postalcode"
  },
  "geometry": {"coordinates":[0.359564,51.381882],"type":"Point"}
}
