{
  "type": "Feature",
  "properties": {
    "iso:country":"GB",
    "wof:name":"DA13 0HX",
    "wof:placetype":"postalcode"
},
  "geometry": {"coordinates":[0.35956378761819,51.38188186411444],"type":"Point"}
}