{
  "type": "Feature",
  "properties": {
    "iso:country":"GB",
    "wof:name":"SS14 3BL",
    "wof:placetype":"postalcode"
},
  "geometry": {"coordinates":[0.45461201235599,51.58207186361506],"type":"Point"}
}