{
  "type": "Feature",
  "properties": {
    "iso:country":"GB",
    "wof:name":"DL17 0SH",
    "wof:placetype":"postalcode"
},
  "geometry": {"coordinates":[-1.56879162487568,54.66759439575632],"type":"Point"}
}