{
  "type": "Feature",
  "properties": {
    "iso:country": "GB",
    "wof:name": "EH51 0AX",
    "wof:placetype": "postalcode"
  },
  "geometry": {"coordinates":[-3.616919,56.014295],"type":"Point"}
}
