{
  "type": "Feature",
  "properties": {
    "date:inception_lower": "1993-08-01",
    "date:inception_upper": "1993-08-01",
    "iso:country": "GB",
    "wof:name": "SY22 6NB",
    "wof:placetype": "postalcode"
  },
  "geometry": {"coordinates":[-3.075938,52.75895],"type":"Point"}
}
