{
  "type": "Feature",
  "properties": {
    "date:inception_lower": "1990-07-01",
    "date:inception_upper": "1990-07-01",
    "iso:country": "GB",
    "wof:name": "PL12 4UW",
    "wof:placetype": "postalcode"
  },
  "geometry": {"coordinates":[-4.237201,50.406089],"type":"Point"}
}
