{
  "type": "Feature",
  "properties": {
    "date:inception_lower": "2003-05-01",
    "date:inception_upper": "2003-05-01",
    "iso:country": "GB",
    "wof:name": "TN32 5DD",
    "wof:placetype": "postalcode"
  },
  "geometry": {"coordinates":[0.469001,50.984486],"type":"Point"}
}
