{
  "type": "Feature",
  "properties": {
    "iso:country":"GB",
    "wof:name":"DN1 2TB",
    "wof:placetype":"postalcode"
},
  "geometry": {"coordinates":[-1.1246318471183,53.53284188236885],"type":"Point"}
}