{
  "type": "Feature",
  "properties": {
    "iso:country":"GB",
    "wof:name":"CH64 6SL",
    "wof:placetype":"postalcode"
},
  "geometry": {"coordinates":[-3.08337197787037,53.29590074119148],"type":"Point"}
}