{
  "type": "Feature",
  "properties": {
    "iso:country": "GB",
    "wof:name": "CH64 6SL",
    "wof:placetype": "postalcode"
  },
  "geometry": {"coordinates":[-3.083372,53.295901],"type":"Point"}
}
