{
  "type": "Feature",
  "properties": {
    "date:inception_lower": "1980-01-01",
    "date:inception_upper": "1980-01-01",
    "iso:country": "GB",
    "wof:name": "GU10 5PL",
    "wof:placetype": "postalcode"
  },
  "geometry": {"coordinates":[-0.860632,51.230454],"type":"Point"}
}
