{
  "type": "Feature",
  "properties": {
    "date:inception_lower": "1991-09-01",
    "date:inception_upper": "1991-09-01",
    "iso:country": "GB",
    "wof:name": "E17 9HQ",
    "wof:placetype": "postalcode"
  },
  "geometry": {"coordinates":[-0.008138,51.583888],"type":"Point"}
}
