{
  "type": "Feature",
  "properties": {
    "iso:country":"GB",
    "wof:name":"E17 9HQ",
    "wof:placetype":"postalcode"
},
  "geometry": {"coordinates":[-0.00813847805961,51.5838884743158],"type":"Point"}
}