{
  "type": "Feature",
  "properties": {
    "iso:country":"GB",
    "wof:name":"SP7 0NR",
    "wof:placetype":"postalcode"
},
  "geometry": {"coordinates":[-2.2006167722711,50.9576635536467],"type":"Point"}
}