{
  "type": "Feature",
  "properties": {
    "iso:country":"GB",
    "wof:name":"N11 2JY",
    "wof:placetype":"postalcode"
},
  "geometry": {"coordinates":[-0.12822616979785,51.61322018325528],"type":"Point"}
}