{
  "type": "Feature",
  "properties": {
    "iso:country": "GB",
    "wof:name": "DN21 4PB",
    "wof:placetype": "postalcode"
  },
  "geometry": {"coordinates":[-0.591124,53.475416],"type":"Point"}
}
