{
  "type": "Feature",
  "properties": {
    "iso:country":"GB",
    "wof:name":"DN21 4PB",
    "wof:placetype":"postalcode"
},
  "geometry": {"coordinates":[-0.59098584154399,53.4754011217297],"type":"Point"}
}