{
  "type": "Feature",
  "properties": {
    "iso:country": "GB",
    "wof:name": "YO26 6DD",
    "wof:placetype": "postalcode"
  },
  "geometry": {"coordinates":[-1.152606,53.979375],"type":"Point"}
}
