{
  "type": "Feature",
  "properties": {
    "iso:country":"GB",
    "wof:name":"YO26 6DD",
    "wof:placetype":"postalcode"
},
  "geometry": {"coordinates":[-1.15259806895032,53.97932200873868],"type":"Point"}
}