{
  "type": "Feature",
  "properties": {
    "iso:country":"GB",
    "wof:name":"B93 0BU",
    "wof:placetype":"postalcode"
},
  "geometry": {"coordinates":[-1.69381902590331,52.35155688344389],"type":"Point"}
}