{
  "type": "Feature",
  "properties": {
    "iso:country":"GB",
    "wof:name":"WD6 4HS",
    "wof:placetype":"postalcode"
},
  "geometry": {"coordinates":[-0.28449452661598,51.66866164606204],"type":"Point"}
}