{
  "type": "Feature",
  "properties": {
    "iso:country":"GB",
    "wof:name":"BN27 4EW",
    "wof:placetype":"postalcode"
},
  "geometry": {"coordinates":[0.26350108160941,50.88262278761196],"type":"Point"}
}