{
  "type": "Feature",
  "properties": {
    "iso:country":"GB",
    "wof:name":"G78 2BA",
    "wof:placetype":"postalcode"
},
  "geometry": {"coordinates":[-4.39430561301272,55.79606201592602],"type":"Point"}
}