{
  "type": "Feature",
  "properties": {
    "iso:country":"GB",
    "wof:name":"HD4 7BR",
    "wof:placetype":"postalcode"
},
  "geometry": {"coordinates":[-1.81172618548814,53.62080857813668],"type":"Point"}
}