{
  "type": "Feature",
  "properties": {
    "iso:country":"GB",
    "wof:name":"BH25 5SG",
    "wof:placetype":"postalcode"
},
  "geometry": {"coordinates":[-1.66008201213851,50.77714225632489],"type":"Point"}
}