{
  "type": "Feature",
  "properties": {
    "date:inception_lower": "1980-01-01",
    "date:inception_upper": "1980-01-01",
    "iso:country": "GB",
    "wof:name": "BH25 5SG",
    "wof:placetype": "postalcode"
  },
  "geometry": {"coordinates":[-1.660082,50.777142],"type":"Point"}
}
