{
  "type": "Feature",
  "properties": {
    "iso:country": "GB",
    "wof:name": "ST7 9FA",
    "wof:placetype": "postalcode"
  },
  "geometry": {"coordinates":[-2.257153,53.087383],"type":"Point"}
}
