{
  "type": "Feature",
  "properties": {
    "date:inception_lower":"2014-07-01",
    "date:inception_upper":"2014-07-31",
    "iso:country":"GB",
    "wof:name":"ST7 9FA",
    "wof:placetype":"postalcode"
},
  "geometry": {"coordinates":[-2.257153,53.087383],"type":"Point"}
}