{
  "type": "Feature",
  "properties": {
    "iso:country": "GB",
    "wof:name": "HP22 7BP",
    "wof:placetype": "postalcode"
  },
  "geometry": {"coordinates":[-0.775475,51.82223],"type":"Point"}
}
