{
  "type": "Feature",
  "properties": {
    "date:inception_lower": "2018-05-01",
    "date:inception_upper": "2018-05-01",
    "iso:country": "GB",
    "wof:name": "HP22 7BP",
    "wof:placetype": "postalcode"
  },
  "geometry": {"coordinates":[-0.775827,51.822099],"type":"Point"}
}
