{
  "type": "Feature",
  "properties": {
    "iso:country": "GB",
    "wof:name": "DE13 9SH",
    "wof:placetype": "postalcode"
  },
  "geometry": {"coordinates":[-1.705213,52.805015],"type":"Point"}
}
