{
  "type": "Feature",
  "properties": {
    "date:inception_lower":"1980-01-01",
    "date:inception_upper":"1980-01-31",
    "iso:country":"GB",
    "wof:name":"DE13 9SH",
    "wof:placetype":"postalcode"
},
  "geometry": {"coordinates":[-1.705213,52.805015],"type":"Point"}
}