{
  "type": "Feature",
  "properties": {
    "iso:country":"GB",
    "wof:name":"DE13 9SH",
    "wof:placetype":"postalcode"
},
  "geometry": {"coordinates":[-1.70521295564506,52.80501530664976],"type":"Point"}
}