{
  "type": "Feature",
  "properties": {
    "iso:country": "GB",
    "wof:name": "RG9 4EH",
    "wof:placetype": "postalcode"
  },
  "geometry": {"coordinates":[-0.923456,51.502275],"type":"Point"}
}
