{
  "type": "Feature",
  "properties": {
    "iso:country":"GB",
    "wof:name":"DG8 9EU",
    "wof:placetype":"postalcode"
},
  "geometry": {"coordinates":[-4.44368949012979,54.86532354341128],"type":"Point"}
}