{
  "type": "Feature",
  "properties": {
    "iso:country":"GB",
    "wof:name":"SS9 3AE",
    "wof:placetype":"postalcode"
},
  "geometry": {"coordinates":[0.64793349984531,51.55631003777238],"type":"Point"}
}