{
  "type": "Feature",
  "properties": {
    "iso:country": "GB",
    "wof:name": "SS9 3AE",
    "wof:placetype": "postalcode"
  },
  "geometry": {"coordinates":[0.647934,51.55631],"type":"Point"}
}
