{
  "type": "Feature",
  "properties": {
    "date:inception_lower": "1991-09-01",
    "date:inception_upper": "1991-09-01",
    "iso:country": "GB",
    "wof:name": "EX1 3UJ",
    "wof:placetype": "postalcode"
  },
  "geometry": {"coordinates":[-3.478576,50.723475],"type":"Point"}
}
