{
  "type": "Feature",
  "properties": {
    "iso:country":"GB",
    "wof:name":"EX1 3UJ",
    "wof:placetype":"postalcode"
},
  "geometry": {"coordinates":[-3.47857587357101,50.72347495444427],"type":"Point"}
}