{
  "type": "Feature",
  "properties": {
    "date:inception_lower": "1992-08-01",
    "date:inception_upper": "1992-08-01",
    "iso:country": "GB",
    "wof:name": "DE74 2XB",
    "wof:placetype": "postalcode"
  },
  "geometry": {"coordinates":[-1.347195,52.844912],"type":"Point"}
}
