{
  "type": "Feature",
  "properties": {
    "iso:country":"GB",
    "wof:name":"DE74 2XB",
    "wof:placetype":"postalcode"
},
  "geometry": {"coordinates":[-1.34719538129946,52.84491201301424],"type":"Point"}
}