{
  "type": "Feature",
  "properties": {
    "iso:country": "GB",
    "wof:name": "CR3 5DJ",
    "wof:placetype": "postalcode"
  },
  "geometry": {"coordinates":[-0.101236,51.279717],"type":"Point"}
}
