{
  "type": "Feature",
  "properties": {
    "iso:country": "GB",
    "wof:name": "DN20 8RQ",
    "wof:placetype": "postalcode"
  },
  "geometry": {"coordinates":[-0.467675,53.562644],"type":"Point"}
}
