{
  "type": "Feature",
  "properties": {
    "iso:country":"GB",
    "wof:name":"DN20 8RQ",
    "wof:placetype":"postalcode"
},
  "geometry": {"coordinates":[-0.46767498039451,53.56264413464032],"type":"Point"}
}