{
  "type": "Feature",
  "properties": {
    "iso:country":"GB",
    "wof:name":"NR17 2DD",
    "wof:placetype":"postalcode"
},
  "geometry": {"coordinates":[1.00842263040879,52.51419087237475],"type":"Point"}
}