{
  "type": "Feature",
  "properties": {
    "date:inception_lower": "1980-01-01",
    "date:inception_upper": "1980-01-01",
    "iso:country": "GB",
    "wof:name": "NR17 2DD",
    "wof:placetype": "postalcode"
  },
  "geometry": {"coordinates":[1.008423,52.514191],"type":"Point"}
}
