{
  "type": "Feature",
  "properties": {
    "iso:country": "GB",
    "wof:name": "SW19 1GD",
    "wof:placetype": "postalcode"
  },
  "geometry": {"coordinates":[-0.188717,51.415922],"type":"Point"}
}
