{
  "type": "Feature",
  "properties": {
    "iso:country":"GB",
    "wof:name":"BN22 0LS",
    "wof:placetype":"postalcode"
},
  "geometry": {"coordinates":[0.25873974952409,50.80530464437399],"type":"Point"}
}