{
  "type": "Feature",
  "properties": {
    "date:inception_lower":"1980-01-01",
    "date:inception_upper":"1980-01-31",
    "iso:country":"GB",
    "wof:name":"CM20 2ND",
    "wof:placetype":"postalcode"
},
  "geometry": {"coordinates":[0.122147,51.77964],"type":"Point"}
}