{
  "type": "Feature",
  "properties": {
    "iso:country":"GB",
    "wof:name":"CM20 2ND",
    "wof:placetype":"postalcode"
},
  "geometry": {"coordinates":[0.12214660566045,51.77963979670277],"type":"Point"}
}