{
  "type": "Feature",
  "properties": {
    "iso:country": "GB",
    "wof:name": "AL3 5JU",
    "wof:placetype": "postalcode"
  },
  "geometry": {"coordinates":[-0.342052,51.755827],"type":"Point"}
}
