{
  "type": "Feature",
  "properties": {
    "iso:country":"GB",
    "wof:name":"WF3 1HZ",
    "wof:placetype":"postalcode"
},
  "geometry": {"coordinates":[-1.5909079134462,53.73201742170025],"type":"Point"}
}