{
  "type": "Feature",
  "properties": {
    "date:inception_lower": "1999-06-01",
    "date:inception_upper": "1999-06-01",
    "iso:country": "GB",
    "wof:name": "CH47 1HR",
    "wof:placetype": "postalcode"
  },
  "geometry": {"coordinates":[-3.192284,53.388969],"type":"Point"}
}
