{
  "type": "Feature",
  "properties": {
    "date:inception_lower":"1980-01-01",
    "date:inception_upper":"1980-01-31",
    "iso:country":"GB",
    "wof:name":"HG4 2LW",
    "wof:placetype":"postalcode"
},
  "geometry": {"coordinates":[-1.533947,54.124309],"type":"Point"}
}