{
  "type": "Feature",
  "properties": {
    "iso:country":"GB",
    "wof:name":"HG4 2LW",
    "wof:placetype":"postalcode"
},
  "geometry": {"coordinates":[-1.53394658000216,54.12430897114633],"type":"Point"}
}