{
  "type": "Feature",
  "properties": {
    "iso:country":"GB",
    "wof:name":"UB5 6PJ",
    "wof:placetype":"postalcode"
},
  "geometry": {"coordinates":[-0.40495755172397,51.53587356013899],"type":"Point"}
}