{
  "type": "Feature",
  "properties": {
    "iso:country": "GB",
    "wof:name": "NN9 6DG",
    "wof:placetype": "postalcode"
  },
  "geometry": {"coordinates":[-0.550861,52.336398],"type":"Point"}
}
