{
  "type": "Feature",
  "properties": {
    "iso:country":"GB",
    "wof:name":"SR5 2BT",
    "wof:placetype":"postalcode"
},
  "geometry": {"coordinates":[-1.40492954370912,54.91620777691401],"type":"Point"}
}