{
  "type": "Feature",
  "properties": {
    "date:inception_lower": "1980-01-01",
    "date:inception_upper": "1980-01-01",
    "iso:country": "GB",
    "wof:name": "SR5 2BT",
    "wof:placetype": "postalcode"
  },
  "geometry": {"coordinates":[-1.405068,54.916216],"type":"Point"}
}
