{
  "type": "Feature",
  "properties": {
    "iso:country":"GB",
    "wof:name":"B67 5HE",
    "wof:placetype":"postalcode"
},
  "geometry": {"coordinates":[-1.97536884366508,52.47660648606996],"type":"Point"}
}