{
  "type": "Feature",
  "properties": {
    "iso:country":"GB",
    "wof:name":"CF39 8RY",
    "wof:placetype":"postalcode"
},
  "geometry": {"coordinates":[-3.47240132194483,51.6032827361925],"type":"Point"}
}