{
  "type": "Feature",
  "properties": {
    "date:inception_lower": "1980-01-01",
    "date:inception_upper": "1980-01-01",
    "iso:country": "GB",
    "wof:name": "CB6 3BJ",
    "wof:placetype": "postalcode"
  },
  "geometry": {"coordinates":[0.250503,52.396513],"type":"Point"}
}
