{
  "type": "Feature",
  "properties": {
    "iso:country": "GB",
    "wof:name": "RM15 6HS",
    "wof:placetype": "postalcode"
  },
  "geometry": {"coordinates":[0.291955,51.51599],"type":"Point"}
}
