{
  "type": "Feature",
  "properties": {
    "iso:country":"GB",
    "wof:name":"HP14 3NS",
    "wof:placetype":"postalcode"
},
  "geometry": {"coordinates":[-0.8164416612353,51.61769730015029],"type":"Point"}
}