{
  "type": "Feature",
  "properties": {
    "iso:country":"GB",
    "wof:name":"LL19 8LU",
    "wof:placetype":"postalcode"
},
  "geometry": {"coordinates":[-3.40536055733541,53.32282596200804],"type":"Point"}
}