{
  "type": "Feature",
  "properties": {
    "date:inception_lower": "1980-01-01",
    "date:inception_upper": "1980-01-01",
    "iso:country": "GB",
    "wof:name": "DL11 6HW",
    "wof:placetype": "postalcode"
  },
  "geometry": {"coordinates":[-1.92973,54.380428],"type":"Point"}
}
