{
  "type": "Feature",
  "properties": {
    "iso:country":"GB",
    "wof:name":"DL11 6HW",
    "wof:placetype":"postalcode"
},
  "geometry": {"coordinates":[-1.92973012332772,54.38042830487309],"type":"Point"}
}