{
  "type": "Feature",
  "properties": {
    "iso:country": "GB",
    "wof:name": "HA1 2HE",
    "wof:placetype": "postalcode"
  },
  "geometry": {"coordinates":[-0.328666,51.579998],"type":"Point"}
}
