{
  "type": "Feature",
  "properties": {
    "iso:country": "GB",
    "wof:name": "CV1 1QX",
    "wof:placetype": "postalcode"
  },
  "geometry": {"coordinates":[-1.512161,52.409239],"type":"Point"}
}
