{
  "type": "Feature",
  "properties": {
    "iso:country":"GB",
    "wof:name":"CV1 1QX",
    "wof:placetype":"postalcode"
},
  "geometry": {"coordinates":[-1.51216151640291,52.40923940931731],"type":"Point"}
}