{
  "type": "Feature",
  "properties": {
    "iso:country":"GB",
    "wof:name":"SW2 3PF",
    "wof:placetype":"postalcode"
},
  "geometry": {"coordinates":[-0.11140219599963,51.44174210398889],"type":"Point"}
}