{
  "type": "Feature",
  "properties": {
    "iso:country": "GB",
    "wof:name": "M9 6JN",
    "wof:placetype": "postalcode"
  },
  "geometry": {"coordinates":[-2.208136,53.531107],"type":"Point"}
}
