{
  "type": "Feature",
  "properties": {
    "date:inception_lower": "1994-05-01",
    "date:inception_upper": "1994-05-01",
    "iso:country": "GB",
    "wof:name": "M9 6JN",
    "wof:placetype": "postalcode"
  },
  "geometry": {"coordinates":[-2.208136,53.531107],"type":"Point"}
}
