{
  "type": "Feature",
  "properties": {
    "iso:country":"GB",
    "wof:name":"M9 6JN",
    "wof:placetype":"postalcode"
},
  "geometry": {"coordinates":[-2.20813570823979,53.5311074587509],"type":"Point"}
}