{
  "type": "Feature",
  "properties": {
    "date:inception_lower": "2012-05-01",
    "date:inception_upper": "2012-05-01",
    "iso:country": "GB",
    "wof:name": "NP12 0EZ",
    "wof:placetype": "postalcode"
  },
  "geometry": {"coordinates":[-3.173823,51.681837],"type":"Point"}
}
