{
  "type": "Feature",
  "properties": {
    "date:inception_lower": "1999-06-01",
    "date:inception_upper": "1999-06-01",
    "iso:country": "GB",
    "wof:name": "CF14 5DS",
    "wof:placetype": "postalcode"
  },
  "geometry": {"coordinates":[-3.18108,51.537591],"type":"Point"}
}
