{
  "type": "Feature",
  "properties": {
    "iso:country":"GB",
    "wof:name":"CF15 7RB",
    "wof:placetype":"postalcode"
},
  "geometry": {"coordinates":[-3.26648193891624,51.54172661868074],"type":"Point"}
}