{
  "type": "Feature",
  "properties": {
    "date:inception_lower": "1999-06-01",
    "date:inception_upper": "1999-06-01",
    "iso:country": "GB",
    "wof:name": "CF15 7RB",
    "wof:placetype": "postalcode"
  },
  "geometry": {"coordinates":[-3.266405,51.54172],"type":"Point"}
}
