{
  "type": "Feature",
  "properties": {
    "iso:country":"GB",
    "wof:name":"EX4 8EF",
    "wof:placetype":"postalcode"
},
  "geometry": {"coordinates":[-3.48763580090308,50.73308138437782],"type":"Point"}
}