{
  "type": "Feature",
  "properties": {
    "iso:country":"GB",
    "wof:name":"KT22 7ED",
    "wof:placetype":"postalcode"
},
  "geometry": {"coordinates":[-0.32735270575433,51.30349836142962],"type":"Point"}
}