{
  "type": "Feature",
  "properties": {
    "iso:country": "GB",
    "wof:name": "WR9 0DN",
    "wof:placetype": "postalcode"
  },
  "geometry": {"coordinates":[-2.172545,52.267372],"type":"Point"}
}
