{
  "type": "Feature",
  "properties": {
    "iso:country":"GB",
    "wof:name":"WR9 0DN",
    "wof:placetype":"postalcode"
},
  "geometry": {"coordinates":[-2.17254484531121,52.26737228328655],"type":"Point"}
}