{
  "type": "Feature",
  "properties": {
    "date:inception_lower": "1986-07-01",
    "date:inception_upper": "1986-07-01",
    "iso:country": "GB",
    "wof:name": "WR9 0DN",
    "wof:placetype": "postalcode"
  },
  "geometry": {"coordinates":[-2.172545,52.267372],"type":"Point"}
}
