{
  "type": "Feature",
  "properties": {
    "iso:country": "GB",
    "wof:name": "PH16 5AT",
    "wof:placetype": "postalcode"
  },
  "geometry": {"coordinates":[-3.737241,56.706142],"type":"Point"}
}
