{
  "type": "Feature",
  "properties": {
    "iso:country":"GB",
    "wof:name":"EX7 9RW",
    "wof:placetype":"postalcode"
},
  "geometry": {"coordinates":[-3.471972433725,50.57500621438793],"type":"Point"}
}