{
  "type": "Feature",
  "properties": {
    "iso:country":"GB",
    "wof:name":"RG41 3UD",
    "wof:placetype":"postalcode"
},
  "geometry": {"coordinates":[-0.85975438288605,51.41354355459183],"type":"Point"}
}