{
  "type": "Feature",
  "properties": {
    "date:inception_lower": "1980-01-01",
    "date:inception_upper": "1980-01-01",
    "iso:country": "GB",
    "wof:name": "NR9 4PA",
    "wof:placetype": "postalcode"
  },
  "geometry": {"coordinates":[0.918934,52.568111],"type":"Point"}
}
