{
  "type": "Feature",
  "properties": {
    "iso:country":"GB",
    "wof:name":"HA8 8RE",
    "wof:placetype":"postalcode"
},
  "geometry": {"coordinates":[-0.26963778053793,51.62779906934497],"type":"Point"}
}