{
  "type": "Feature",
  "properties": {
    "iso:country": "GB",
    "wof:name": "LE2 3EG",
    "wof:placetype": "postalcode"
  },
  "geometry": {"coordinates":[-1.117522,52.615058],"type":"Point"}
}
