{
  "type": "Feature",
  "properties": {
    "iso:country":"GB",
    "wof:name":"PA3 1LB",
    "wof:placetype":"postalcode"
},
  "geometry": {"coordinates":[-4.44788920384347,55.85081260475866],"type":"Point"}
}