{
  "type": "Feature",
  "properties": {
    "iso:country":"GB",
    "wof:name":"N16 0LW",
    "wof:placetype":"postalcode"
},
  "geometry": {"coordinates":[-0.07392374625168,51.56324276904905],"type":"Point"}
}