{
  "type": "Feature",
  "properties": {
    "iso:country":"GB",
    "wof:name":"S10 2SN",
    "wof:placetype":"postalcode"
},
  "geometry": {"coordinates":[-1.49838014848199,53.37851990688078],"type":"Point"}
}