{
  "type": "Feature",
  "properties": {
    "date:inception_lower": "1980-01-01",
    "date:inception_upper": "1980-01-01",
    "iso:country": "GB",
    "wof:name": "S10 2SN",
    "wof:placetype": "postalcode"
  },
  "geometry": {"coordinates":[-1.49838,53.37852],"type":"Point"}
}
