{
  "type": "Feature",
  "properties": {
    "iso:country":"GB",
    "wof:name":"BL2 4LN",
    "wof:placetype":"postalcode"
},
  "geometry": {"coordinates":[-2.39142371380448,53.59543575310396],"type":"Point"}
}