{
  "type": "Feature",
  "properties": {
    "date:inception_lower": "1990-02-01",
    "date:inception_upper": "1990-02-01",
    "iso:country": "GB",
    "wof:name": "BL2 4LN",
    "wof:placetype": "postalcode"
  },
  "geometry": {"coordinates":[-2.391424,53.595436],"type":"Point"}
}
