{
  "type": "Feature",
  "properties": {
    "iso:country":"GB",
    "wof:name":"NR3 4DT",
    "wof:placetype":"postalcode"
},
  "geometry": {"coordinates":[1.30821857852148,52.65076610078304],"type":"Point"}
}