{
  "type": "Feature",
  "properties": {
    "date:inception_lower": "1980-01-01",
    "date:inception_upper": "1980-01-01",
    "iso:country": "GB",
    "wof:name": "BD23 4AQ",
    "wof:placetype": "postalcode"
  },
  "geometry": {"coordinates":[-2.150168,54.029098],"type":"Point"}
}
