{
  "type": "Feature",
  "properties": {
    "iso:country":"GB",
    "wof:name":"LL57 1HE",
    "wof:placetype":"postalcode"
},
  "geometry": {"coordinates":[-4.1246156761819,53.22653713697613],"type":"Point"}
}