{
  "type": "Feature",
  "properties": {
    "iso:country": "GB",
    "wof:name": "L2 0RL",
    "wof:placetype": "postalcode"
  },
  "geometry": {"coordinates":[-2.993463,53.406089],"type":"Point"}
}
