{
  "type": "Feature",
  "properties": {
    "date:inception_lower":"1993-01-01",
    "date:inception_upper":"1993-01-31",
    "iso:country":"GB",
    "wof:name":"L2 0RL",
    "wof:placetype":"postalcode"
},
  "geometry": {"coordinates":[-2.993463,53.406089],"type":"Point"}
}