{
  "type": "Feature",
  "properties": {
    "iso:country": "GB",
    "wof:name": "SN6 6LH",
    "wof:placetype": "postalcode"
  },
  "geometry": {"coordinates":[-1.817169,51.672161],"type":"Point"}
}
