{
  "type": "Feature",
  "properties": {
    "date:inception_lower": "1980-01-01",
    "date:inception_upper": "1980-01-01",
    "iso:country": "GB",
    "wof:name": "SN6 6LH",
    "wof:placetype": "postalcode"
  },
  "geometry": {"coordinates":[-1.817169,51.672161],"type":"Point"}
}
