{
  "type": "Feature",
  "properties": {
    "iso:country":"GB",
    "wof:name":"SY11 1HD",
    "wof:placetype":"postalcode"
},
  "geometry": {"coordinates":[-3.04762290230708,52.86518461529196],"type":"Point"}
}