{
  "type": "Feature",
  "properties": {
    "date:inception_lower": "1997-12-01",
    "date:inception_upper": "1997-12-01",
    "iso:country": "GB",
    "wof:name": "ST5 9JJ",
    "wof:placetype": "postalcode"
  },
  "geometry": {"coordinates":[-2.23137,53.021042],"type":"Point"}
}
