{
  "type": "Feature",
  "properties": {
    "iso:country":"GB",
    "wof:name":"ST5 9JJ",
    "wof:placetype":"postalcode"
},
  "geometry": {"coordinates":[-2.231370343629,53.0210421341314],"type":"Point"}
}