{
  "type": "Feature",
  "properties": {
    "iso:country":"GB",
    "wof:name":"PO1 4PX",
    "wof:placetype":"postalcode"
},
  "geometry": {"coordinates":[-1.08193709252372,50.80532084243144],"type":"Point"}
}