{
  "type": "Feature",
  "properties": {
    "iso:country":"GB",
    "wof:name":"TN25 4LN",
    "wof:placetype":"postalcode"
},
  "geometry": {"coordinates":[0.81535106921238,51.1828356692111],"type":"Point"}
}