{
  "type": "Feature",
  "properties": {
    "date:inception_lower":"1980-01-01",
    "date:inception_upper":"1980-01-31",
    "iso:country":"GB",
    "wof:name":"TN25 4LN",
    "wof:placetype":"postalcode"
},
  "geometry": {"coordinates":[0.815451,51.182806],"type":"Point"}
}