{
  "type": "Feature",
  "properties": {
    "iso:country":"GB",
    "wof:name":"B65 9BG",
    "wof:placetype":"postalcode"
},
  "geometry": {"coordinates":[-2.03814947803642,52.47879630999082],"type":"Point"}
}