{
  "type": "Feature",
  "properties": {
    "iso:country":"GB",
    "wof:name":"BR6 9PX",
    "wof:placetype":"postalcode"
},
  "geometry": {"coordinates":[0.0831691334447,51.36598053033985],"type":"Point"}
}