{
  "type": "Feature",
  "properties": {
    "date:inception_lower":"1980-01-01",
    "date:inception_upper":"1980-01-31",
    "iso:country":"GB",
    "wof:name":"BR6 9PX",
    "wof:placetype":"postalcode"
},
  "geometry": {"coordinates":[0.083169,51.365981],"type":"Point"}
}