{
  "type": "Feature",
  "properties": {
    "date:inception_lower": "2022-02-01",
    "date:inception_upper": "2022-02-01",
    "iso:country": "GB",
    "wof:name": "OL12 8US",
    "wof:placetype": "postalcode"
  },
  "geometry": {"coordinates":[-2.185499,53.650166],"type":"Point"}
}
