{
  "type": "Feature",
  "properties": {
    "iso:country":"GB",
    "wof:name":"CO10 7LD",
    "wof:placetype":"postalcode"
},
  "geometry": {"coordinates":[0.67397991632807,52.0704316696244],"type":"Point"}
}