{
  "type": "Feature",
  "properties": {
    "iso:country": "GB",
    "wof:name": "CA1 1SH",
    "wof:placetype": "postalcode"
  },
  "geometry": {"coordinates":[-2.927704,54.889144],"type":"Point"}
}
