{
  "type": "Feature",
  "properties": {
    "iso:country":"GB",
    "wof:name":"CA1 1SH",
    "wof:placetype":"postalcode"
},
  "geometry": {"coordinates":[-2.92771552569413,54.88912856969691],"type":"Point"}
}