{
  "type": "Feature",
  "properties": {
    "iso:country":"GB",
    "wof:name":"DD4 9GA",
    "wof:placetype":"postalcode"
},
  "geometry": {"coordinates":[-2.952445545655,56.4972486389571],"type":"Point"}
}