{
  "type": "Feature",
  "properties": {
    "date:inception_lower": "1980-01-01",
    "date:inception_upper": "1980-01-01",
    "iso:country": "GB",
    "wof:name": "GL4 8EH",
    "wof:placetype": "postalcode"
  },
  "geometry": {"coordinates":[-2.198266,51.830657],"type":"Point"}
}
