{
  "type": "Feature",
  "properties": {
    "iso:country":"GB",
    "wof:name":"GL4 8EH",
    "wof:placetype":"postalcode"
},
  "geometry": {"coordinates":[-2.19826599373795,51.83065685719334],"type":"Point"}
}