{
  "type": "Feature",
  "properties": {
    "iso:country":"GB",
    "wof:name":"CH46 7UB",
    "wof:placetype":"postalcode"
},
  "geometry": {"coordinates":[-3.11659592948681,53.40414689273742],"type":"Point"}
}