{
  "type": "Feature",
  "properties": {
    "iso:country":"GB",
    "wof:name":"GU3 3JP",
    "wof:placetype":"postalcode"
},
  "geometry": {"coordinates":[-0.6072617040202,51.26094994364642],"type":"Point"}
}