{
  "type": "Feature",
  "properties": {
    "iso:country": "GB",
    "wof:name": "GU3 3JP",
    "wof:placetype": "postalcode"
  },
  "geometry": {"coordinates":[-0.607262,51.26095],"type":"Point"}
}
