{
  "type": "Feature",
  "properties": {
    "iso:country": "GB",
    "wof:name": "WA7 1SP",
    "wof:placetype": "postalcode"
  },
  "geometry": {"coordinates":[-2.671374,53.345773],"type":"Point"}
}
