{
  "type": "Feature",
  "properties": {
    "date:inception_lower": "1986-07-01",
    "date:inception_upper": "1986-07-01",
    "iso:country": "GB",
    "wof:name": "WA7 1SP",
    "wof:placetype": "postalcode"
  },
  "geometry": {"coordinates":[-2.671374,53.345773],"type":"Point"}
}
