{
  "type": "Feature",
  "properties": {
    "iso:country":"GB",
    "wof:name":"KA13 7GW",
    "wof:placetype":"postalcode"
},
  "geometry": {"coordinates":[-4.68827775996076,55.65538548505381],"type":"Point"}
}