{
  "type": "Feature",
  "properties": {
    "date:inception_lower": "2001-12-01",
    "date:inception_upper": "2001-12-01",
    "iso:country": "GB",
    "wof:name": "KA13 7GW",
    "wof:placetype": "postalcode"
  },
  "geometry": {"coordinates":[-4.688278,55.655385],"type":"Point"}
}
