{
  "type": "Feature",
  "properties": {
    "iso:country":"GB",
    "wof:name":"TA24 7TW",
    "wof:placetype":"postalcode"
},
  "geometry": {"coordinates":[-3.4919481439727,51.16752917219066],"type":"Point"}
}