{
  "type": "Feature",
  "properties": {
    "iso:country": "GB",
    "wof:name": "TA24 7TW",
    "wof:placetype": "postalcode"
  },
  "geometry": {"coordinates":[-3.491948,51.167529],"type":"Point"}
}
