{
  "type": "Feature",
  "properties": {
    "date:inception_lower": "2007-09-01",
    "date:inception_upper": "2007-09-01",
    "iso:country": "GB",
    "wof:name": "YO21 1HG",
    "wof:placetype": "postalcode"
  },
  "geometry": {"coordinates":[-0.634267,54.483663],"type":"Point"}
}
