{
  "type": "Feature",
  "properties": {
    "iso:country":"GB",
    "wof:name":"YO21 1HG",
    "wof:placetype":"postalcode"
},
  "geometry": {"coordinates":[-0.63426686680905,54.48366349739818],"type":"Point"}
}