{
  "type": "Feature",
  "properties": {
    "iso:country": "GB",
    "wof:name": "DT10 1PD",
    "wof:placetype": "postalcode"
  },
  "geometry": {"coordinates":[-2.323941,50.96521],"type":"Point"}
}
