{
  "type": "Feature",
  "properties": {
    "date:inception_lower": "1995-01-01",
    "date:inception_upper": "1995-01-01",
    "iso:country": "GB",
    "wof:name": "DT10 1PD",
    "wof:placetype": "postalcode"
  },
  "geometry": {"coordinates":[-2.323941,50.96521],"type":"Point"}
}
