{
  "type": "Feature",
  "properties": {
    "iso:country":"GB",
    "wof:name":"SL6 3XP",
    "wof:placetype":"postalcode"
},
  "geometry": {"coordinates":[-0.75737044675253,51.50528240387724],"type":"Point"}
}