{
  "type": "Feature",
  "properties": {
    "date:inception_lower": "1980-01-01",
    "date:inception_upper": "1980-01-01",
    "iso:country": "GB",
    "wof:name": "CO7 7SX",
    "wof:placetype": "postalcode"
  },
  "geometry": {"coordinates":[0.99756,51.912396],"type":"Point"}
}
