{
  "type": "Feature",
  "properties": {
    "iso:country":"GB",
    "wof:name":"CO7 7SX",
    "wof:placetype":"postalcode"
},
  "geometry": {"coordinates":[0.99745833840775,51.91240424109842],"type":"Point"}
}