{
  "type": "Feature",
  "properties": {
    "iso:country":"GB",
    "wof:name":"SW19 2BU",
    "wof:placetype":"postalcode"
},
  "geometry": {"coordinates":[-0.17727601829004,51.42044735272993],"type":"Point"}
}