{
  "type": "Feature",
  "properties": {
    "date:inception_lower": "2021-05-01",
    "date:inception_upper": "2021-05-01",
    "iso:country": "GB",
    "wof:name": "TF4 3GT",
    "wof:placetype": "postalcode"
  },
  "geometry": {"coordinates":[-2.481563,52.656106],"type":"Point"}
}
