{
  "type": "Feature",
  "properties": {
    "date:inception_lower": "1980-01-01",
    "date:inception_upper": "1980-01-01",
    "iso:country": "GB",
    "wof:name": "IP12 4SZ",
    "wof:placetype": "postalcode"
  },
  "geometry": {"coordinates":[1.275111,52.073381],"type":"Point"}
}
