{
  "type": "Feature",
  "properties": {
    "iso:country":"GB",
    "wof:name":"WN5 9PY",
    "wof:placetype":"postalcode"
},
  "geometry": {"coordinates":[-2.66547908175292,53.53893671179021],"type":"Point"}
}