{
  "type": "Feature",
  "properties": {
    "iso:country":"GB",
    "wof:name":"OL2 6QQ",
    "wof:placetype":"postalcode"
},
  "geometry": {"coordinates":[-2.12263997987232,53.56676577654879],"type":"Point"}
}