{
  "type": "Feature",
  "properties": {
    "iso:country":"GB",
    "wof:name":"LN1 3QP",
    "wof:placetype":"postalcode"
},
  "geometry": {"coordinates":[-0.55202520124709,53.25141308582972],"type":"Point"}
}