{
  "type": "Feature",
  "properties": {
    "iso:country":"GB",
    "wof:name":"ME3 9TF",
    "wof:placetype":"postalcode"
},
  "geometry": {"coordinates":[0.56294374882158,51.41252131071915],"type":"Point"}
}