{
  "type": "Feature",
  "properties": {
    "date:inception_lower":"1987-04-01",
    "date:inception_upper":"1987-04-30",
    "iso:country":"GB",
    "wof:name":"ME3 9TF",
    "wof:placetype":"postalcode"
},
  "geometry": {"coordinates":[0.562944,51.412521],"type":"Point"}
}