{
  "type": "Feature",
  "properties": {
    "iso:country": "GB",
    "wof:name": "TR9 6RY",
    "wof:placetype": "postalcode"
  },
  "geometry": {"coordinates":[-4.941504,50.429873],"type":"Point"}
}
