{
  "type": "Feature",
  "properties": {
    "iso:country":"GB",
    "wof:name":"TR9 6RY",
    "wof:placetype":"postalcode"
},
  "geometry": {"coordinates":[-4.94150411079976,50.42987284892273],"type":"Point"}
}