{
  "type": "Feature",
  "properties": {
    "date:inception_lower": "1980-01-01",
    "date:inception_upper": "1980-01-01",
    "iso:country": "GB",
    "wof:name": "ST13 5JT",
    "wof:placetype": "postalcode"
  },
  "geometry": {"coordinates":[-2.020079,53.104756],"type":"Point"}
}
