{
  "type": "Feature",
  "properties": {
    "iso:country":"GB",
    "wof:name":"G68 9ES",
    "wof:placetype":"postalcode"
},
  "geometry": {"coordinates":[-4.03553308124857,55.93747578723208],"type":"Point"}
}