{
  "type": "Feature",
  "properties": {
    "iso:country": "GB",
    "wof:name": "WN2 1BU",
    "wof:placetype": "postalcode"
  },
  "geometry": {"coordinates":[-2.599163,53.557226],"type":"Point"}
}
