{
  "type": "Feature",
  "properties": {
    "iso:country":"GB",
    "wof:name":"B48 7DB",
    "wof:placetype":"postalcode"
},
  "geometry": {"coordinates":[-1.98904850431963,52.34659422812295],"type":"Point"}
}