{
  "type": "Feature",
  "properties": {
    "iso:country":"GB",
    "wof:name":"ME13 8QG",
    "wof:placetype":"postalcode"
},
  "geometry": {"coordinates":[0.88793034008576,51.31124925907264],"type":"Point"}
}