{
  "type": "Feature",
  "properties": {
    "date:inception_lower": "1980-01-01",
    "date:inception_upper": "1980-01-01",
    "iso:country": "GB",
    "wof:name": "KY10 3UW",
    "wof:placetype": "postalcode"
  },
  "geometry": {"coordinates":[-2.629148,56.261016],"type":"Point"}
}
