{
  "type": "Feature",
  "properties": {
    "iso:country":"GB",
    "wof:name":"KY10 3UW",
    "wof:placetype":"postalcode"
},
  "geometry": {"coordinates":[-2.62914822477681,56.26101603782408],"type":"Point"}
}