{
  "type": "Feature",
  "properties": {
    "iso:country":"GB",
    "wof:name":"RH6 9EU",
    "wof:placetype":"postalcode"
},
  "geometry": {"coordinates":[-0.15519586727816,51.16501223936449],"type":"Point"}
}