{
  "type": "Feature",
  "properties": {
    "iso:country":"GB",
    "wof:name":"EH14 7LA",
    "wof:placetype":"postalcode"
},
  "geometry": {"coordinates":[-3.34030074098397,55.88124544594755],"type":"Point"}
}