{
  "type": "Feature",
  "properties": {
    "iso:country":"GB",
    "wof:name":"NW10 4JX",
    "wof:placetype":"postalcode"
},
  "geometry": {"coordinates":[-0.24844628259723,51.53798457420013],"type":"Point"}
}