{
  "type": "Feature",
  "properties": {
    "iso:country":"GB",
    "wof:name":"G75 0PR",
    "wof:placetype":"postalcode"
},
  "geometry": {"coordinates":[-4.16971401128197,55.75180820983114],"type":"Point"}
}