{
  "type": "Feature",
  "properties": {
    "iso:country":"GB",
    "wof:name":"GU17 0DJ",
    "wof:placetype":"postalcode"
},
  "geometry": {"coordinates":[-0.79956002163803,51.33942329086491],"type":"Point"}
}