{
  "type": "Feature",
  "properties": {
    "date:inception_lower": "1980-01-01",
    "date:inception_upper": "1980-01-01",
    "iso:country": "GB",
    "wof:name": "GU17 0DJ",
    "wof:placetype": "postalcode"
  },
  "geometry": {"coordinates":[-0.79956,51.339423],"type":"Point"}
}
