{
  "type": "Feature",
  "properties": {
    "iso:country":"GB",
    "wof:name":"DY8 2ED",
    "wof:placetype":"postalcode"
},
  "geometry": {"coordinates":[-2.14467178936448,52.44630485168404],"type":"Point"}
}