{
  "type": "Feature",
  "properties": {
    "iso:country":"GB",
    "wof:name":"M9 5RH",
    "wof:placetype":"postalcode"
},
  "geometry": {"coordinates":[-2.21484668715845,53.50681791960204],"type":"Point"}
}