{
  "type": "Feature",
  "properties": {
    "date:inception_lower":"2007-07-01",
    "date:inception_upper":"2007-07-31",
    "iso:country":"GB",
    "wof:name":"OX17 1FE",
    "wof:placetype":"postalcode"
},
  "geometry": {"coordinates":[-1.28547,52.107761],"type":"Point"}
}