{
  "type": "Feature",
  "properties": {
    "iso:country":"GB",
    "wof:name":"OX17 1FE",
    "wof:placetype":"postalcode"
},
  "geometry": {"coordinates":[-1.28547013512146,52.10776051988432],"type":"Point"}
}