{
  "type": "Feature",
  "properties": {
    "date:inception_lower":"1980-01-01",
    "date:inception_upper":"1980-01-31",
    "iso:country":"GB",
    "wof:name":"CB9 7JQ",
    "wof:placetype":"postalcode"
},
  "geometry": {"coordinates":[0.450921,52.133861],"type":"Point"}
}