{
  "type": "Feature",
  "properties": {
    "iso:country":"GB",
    "wof:name":"AB16 5XS",
    "wof:placetype":"postalcode"
},
  "geometry": {"coordinates":[-2.13893584619041,57.16035487205154],"type":"Point"}
}