{
  "type": "Feature",
  "properties": {
    "iso:country":"GB",
    "wof:name":"WR2 4HY",
    "wof:placetype":"postalcode"
},
  "geometry": {"coordinates":[-2.23803969755737,52.18408838803634],"type":"Point"}
}