{
  "type": "Feature",
  "properties": {
    "iso:country": "GB",
    "wof:name": "WS6 6AJ",
    "wof:placetype": "postalcode"
  },
  "geometry": {"coordinates":[-2.0217,52.649976],"type":"Point"}
}
