{
  "type": "Feature",
  "properties": {
    "iso:country":"GB",
    "wof:name":"G52 2RJ",
    "wof:placetype":"postalcode"
},
  "geometry": {"coordinates":[-4.36646211968264,55.84832591129127],"type":"Point"}
}