{
  "type": "Feature",
  "properties": {
    "date:inception_lower":"1980-01-01",
    "date:inception_upper":"1980-01-31",
    "iso:country":"GB",
    "wof:name":"HR1 3NB",
    "wof:placetype":"postalcode"
},
  "geometry": {"coordinates":[-2.68261,52.072532],"type":"Point"}
}