{
  "type": "Feature",
  "properties": {
    "iso:country":"GB",
    "wof:name":"HR1 3NB",
    "wof:placetype":"postalcode"
},
  "geometry": {"coordinates":[-2.68260970111063,52.07253209450506],"type":"Point"}
}