{
  "type": "Feature",
  "properties": {
    "iso:country":"GB",
    "wof:name":"TN4 9EE",
    "wof:placetype":"postalcode"
},
  "geometry": {"coordinates":[0.26815053793153,51.15111960759267],"type":"Point"}
}