{
  "type": "Feature",
  "properties": {
    "iso:country": "GB",
    "wof:name": "TN10 4QP",
    "wof:placetype": "postalcode"
  },
  "geometry": {"coordinates":[0.285025,51.210166],"type":"Point"}
}
