{
  "type": "Feature",
  "properties": {
    "iso:country":"GB",
    "wof:name":"BL3 1HR",
    "wof:placetype":"postalcode"
},
  "geometry": {"coordinates":[-2.37058788557263,53.56261379851312],"type":"Point"}
}