{
  "type": "Feature",
  "properties": {
    "iso:country":"GB",
    "wof:name":"SE20 7TY",
    "wof:placetype":"postalcode"
},
  "geometry": {"coordinates":[-0.06425772023445,51.40609927009128],"type":"Point"}
}