{
  "type": "Feature",
  "properties": {
    "iso:country":"GB",
    "wof:name":"CM6 1FA",
    "wof:placetype":"postalcode"
},
  "geometry": {"coordinates":[0.28489057941549,51.8681337186521],"type":"Point"}
}