{
  "type": "Feature",
  "properties": {
    "date:inception_lower":"2007-09-01",
    "date:inception_upper":"2007-09-30",
    "iso:country":"GB",
    "wof:name":"CM6 1FA",
    "wof:placetype":"postalcode"
},
  "geometry": {"coordinates":[0.284891,51.868134],"type":"Point"}
}