{
  "type": "Feature",
  "properties": {
    "iso:country": "GB",
    "wof:name": "CM6 1FA",
    "wof:placetype": "postalcode"
  },
  "geometry": {"coordinates":[0.284891,51.868134],"type":"Point"}
}
