{
  "type": "Feature",
  "properties": {
    "iso:country":"GB",
    "wof:name":"E16 3AT",
    "wof:placetype":"postalcode"
},
  "geometry": {"coordinates":[0.02652437650823,51.51065227451837],"type":"Point"}
}