{
  "type": "Feature",
  "properties": {
    "iso:country": "GB",
    "wof:name": "KA19 7BS",
    "wof:placetype": "postalcode"
  },
  "geometry": {"coordinates":[-4.677293,55.357224],"type":"Point"}
}
