{
  "type": "Feature",
  "properties": {
    "iso:country":"GB",
    "wof:name":"LU3 2RW",
    "wof:placetype":"postalcode"
},
  "geometry": {"coordinates":[-0.45270415638593,51.90384038441277],"type":"Point"}
}