{
  "type": "Feature",
  "properties": {
    "iso:country": "GB",
    "wof:name": "LU3 2RW",
    "wof:placetype": "postalcode"
  },
  "geometry": {"coordinates":[-0.452704,51.90384],"type":"Point"}
}
