{
  "type": "Feature",
  "properties": {
    "iso:country":"GB",
    "wof:name":"WA8 7RU",
    "wof:placetype":"postalcode"
},
  "geometry": {"coordinates":[-2.7352008160641,53.36078576400597],"type":"Point"}
}