{
  "type": "Feature",
  "properties": {
    "iso:country": "GB",
    "wof:name": "SW15 4DR",
    "wof:placetype": "postalcode"
  },
  "geometry": {"coordinates":[-0.244906,51.451173],"type":"Point"}
}
