{
  "type": "Feature",
  "properties": {
    "iso:country":"GB",
    "wof:name":"SW15 4DR",
    "wof:placetype":"postalcode"
},
  "geometry": {"coordinates":[-0.24490554717088,51.45117282286108],"type":"Point"}
}