{
  "type": "Feature",
  "properties": {
    "iso:country":"GB",
    "wof:name":"DD2 5PJ",
    "wof:placetype":"postalcode"
},
  "geometry": {"coordinates":[-3.08618552274181,56.48781316839281],"type":"Point"}
}