{
  "type": "Feature",
  "properties": {
    "date:inception_lower": "1980-01-01",
    "date:inception_upper": "1980-01-01",
    "iso:country": "GB",
    "wof:name": "DD2 5PJ",
    "wof:placetype": "postalcode"
  },
  "geometry": {"coordinates":[-3.086185,56.487813],"type":"Point"}
}
