{
  "type": "Feature",
  "properties": {
    "date:inception_lower": "1980-01-01",
    "date:inception_upper": "1980-01-01",
    "iso:country": "GB",
    "wof:name": "WA3 2HQ",
    "wof:placetype": "postalcode"
  },
  "geometry": {"coordinates":[-2.575202,53.481142],"type":"Point"}
}
