{
  "type": "Feature",
  "properties": {
    "iso:country":"GB",
    "wof:name":"WA3 2HQ",
    "wof:placetype":"postalcode"
},
  "geometry": {"coordinates":[-2.57520155197161,53.4811416039857],"type":"Point"}
}