{
  "type": "Feature",
  "properties": {
    "date:inception_lower":"1980-01-01",
    "date:inception_upper":"1980-01-31",
    "iso:country":"GB",
    "wof:name":"UB4 8RQ",
    "wof:placetype":"postalcode"
},
  "geometry": {"coordinates":[-0.418331,51.529427],"type":"Point"}
}