{
  "type": "Feature",
  "properties": {
    "date:inception_lower": "2008-04-01",
    "date:inception_upper": "2008-04-01",
    "iso:country": "GB",
    "wof:name": "SO53 3LG",
    "wof:placetype": "postalcode"
  },
  "geometry": {"coordinates":[-1.384775,50.965373],"type":"Point"}
}
