{
  "type": "Feature",
  "properties": {
    "iso:country": "GB",
    "wof:name": "SO53 3LG",
    "wof:placetype": "postalcode"
  },
  "geometry": {"coordinates":[-1.384775,50.965373],"type":"Point"}
}
