{
  "type": "Feature",
  "properties": {
    "iso:country":"GB",
    "wof:name":"PA10 2ED",
    "wof:placetype":"postalcode"
},
  "geometry": {"coordinates":[-4.54730842198132,55.83553590653344],"type":"Point"}
}