{
  "type": "Feature",
  "properties": {
    "date:inception_lower": "2015-04-01",
    "date:inception_upper": "2015-04-01",
    "iso:country": "GB",
    "wof:name": "CW4 8GE",
    "wof:placetype": "postalcode"
  },
  "geometry": {"coordinates":[-2.356407,53.211542],"type":"Point"}
}
