{
  "type": "Feature",
  "properties": {
    "iso:country":"GB",
    "wof:name":"CW4 8GE",
    "wof:placetype":"postalcode"
},
  "geometry": {"coordinates":[-2.35640818239211,53.21145329532908],"type":"Point"}
}