{
  "type": "Feature",
  "properties": {
    "iso:country": "GB",
    "wof:name": "CW4 8GE",
    "wof:placetype": "postalcode"
  },
  "geometry": {"coordinates":[-2.356408,53.211453],"type":"Point"}
}
