{
  "type": "Feature",
  "properties": {
    "iso:country":"GB",
    "wof:name":"BA1 6EH",
    "wof:placetype":"postalcode"
},
  "geometry": {"coordinates":[-2.35302773463536,51.39497863631939],"type":"Point"}
}