{
  "type": "Feature",
  "properties": {
    "iso:country":"GB",
    "wof:name":"RG14 5BQ",
    "wof:placetype":"postalcode"
},
  "geometry": {"coordinates":[-1.324316259928,51.40132476977515],"type":"Point"}
}