{
  "type": "Feature",
  "properties": {
    "date:inception_lower":"1980-01-01",
    "date:inception_upper":"1980-01-31",
    "iso:country":"GB",
    "wof:name":"RG14 5BQ",
    "wof:placetype":"postalcode"
},
  "geometry": {"coordinates":[-1.324316,51.401325],"type":"Point"}
}