{
  "type": "Feature",
  "properties": {
    "iso:country":"GB",
    "wof:name":"B38 0DS",
    "wof:placetype":"postalcode"
},
  "geometry": {"coordinates":[-1.90840043327294,52.38814776978906],"type":"Point"}
}