{
  "type": "Feature",
  "properties": {
    "date:inception_lower": "1980-01-01",
    "date:inception_upper": "1980-01-01",
    "iso:country": "GB",
    "wof:name": "GU24 0PX",
    "wof:placetype": "postalcode"
  },
  "geometry": {"coordinates":[-0.660658,51.30452],"type":"Point"}
}
