{
  "type": "Feature",
  "properties": {
    "iso:country":"GB",
    "wof:name":"DL10 6QJ",
    "wof:placetype":"postalcode"
},
  "geometry": {"coordinates":[-1.63662983755759,54.42839702393308],"type":"Point"}
}