{
  "type": "Feature",
  "properties": {
    "iso:country": "GB",
    "wof:name": "DL10 6QJ",
    "wof:placetype": "postalcode"
  },
  "geometry": {"coordinates":[-1.636632,54.429082],"type":"Point"}
}
