{
  "type": "Feature",
  "properties": {
    "iso:country":"GB",
    "wof:name":"N4 1TR",
    "wof:placetype":"postalcode"
},
  "geometry": {"coordinates":[-0.10434833830423,51.57755967914655],"type":"Point"}
}