{
  "type": "Feature",
  "properties": {
    "date:inception_lower": "1996-06-01",
    "date:inception_upper": "1996-06-01",
    "iso:country": "GB",
    "wof:name": "N4 1TR",
    "wof:placetype": "postalcode"
  },
  "geometry": {"coordinates":[-0.104348,51.57756],"type":"Point"}
}
