{
  "type": "Feature",
  "properties": {
    "iso:country": "GB",
    "wof:name": "DH3 4DS",
    "wof:placetype": "postalcode"
  },
  "geometry": {"coordinates":[-1.516437,54.860087],"type":"Point"}
}
