{
  "type": "Feature",
  "properties": {
    "date:inception_lower": "2020-04-01",
    "date:inception_upper": "2020-04-01",
    "iso:country": "GB",
    "wof:name": "DH3 4DS",
    "wof:placetype": "postalcode"
  },
  "geometry": {"coordinates":[-1.51691,54.859595],"type":"Point"}
}
