{
  "type": "Feature",
  "properties": {
    "date:inception_lower": "2022-10-01",
    "date:inception_upper": "2022-10-01",
    "iso:country": "GB",
    "wof:name": "BD20 9FS",
    "wof:placetype": "postalcode"
  },
  "geometry": {"coordinates":[-1.998536,53.935136],"type":"Point"}
}
