{
  "type": "Feature",
  "properties": {
    "iso:country":"GB",
    "wof:name":"AB23 8UR",
    "wof:placetype":"postalcode"
},
  "geometry": {"coordinates":[-2.10412172133184,57.23755211402646],"type":"Point"}
}