{
  "type": "Feature",
  "properties": {
    "iso:country": "GB",
    "wof:name": "IP13 9FU",
    "wof:placetype": "postalcode"
  },
  "geometry": {"coordinates":[1.346875,52.216108],"type":"Point"}
}
