{
  "type": "Feature",
  "properties": {
    "date:inception_lower": "2020-04-01",
    "date:inception_upper": "2020-04-01",
    "iso:country": "GB",
    "wof:name": "IP13 9FU",
    "wof:placetype": "postalcode"
  },
  "geometry": {"coordinates":[1.346875,52.216108],"type":"Point"}
}
