{
  "type": "Feature",
  "properties": {
    "iso:country":"GB",
    "wof:name":"PE28 3XZ",
    "wof:placetype":"postalcode"
},
  "geometry": {"coordinates":[0.0076039483183,52.35310741676926],"type":"Point"}
}