{
  "type": "Feature",
  "properties": {
    "iso:country": "GB",
    "wof:name": "PE28 3XZ",
    "wof:placetype": "postalcode"
  },
  "geometry": {"coordinates":[0.007604,52.353107],"type":"Point"}
}
