{
  "type": "Feature",
  "properties": {
    "date:inception_lower": "1997-12-01",
    "date:inception_upper": "1997-12-01",
    "iso:country": "GB",
    "wof:name": "BS34 5UR",
    "wof:placetype": "postalcode"
  },
  "geometry": {"coordinates":[-2.595758,51.524986],"type":"Point"}
}
