{
  "type": "Feature",
  "properties": {
    "date:inception_lower": "1980-01-01",
    "date:inception_upper": "1980-01-01",
    "iso:country": "GB",
    "wof:name": "DN11 8QR",
    "wof:placetype": "postalcode"
  },
  "geometry": {"coordinates":[-1.058016,53.424229],"type":"Point"}
}
