{
  "type": "Feature",
  "properties": {
    "iso:country":"GB",
    "wof:name":"DN11 8QR",
    "wof:placetype":"postalcode"
},
  "geometry": {"coordinates":[-1.05767023069251,53.42418892510125],"type":"Point"}
}