{
  "type": "Feature",
  "properties": {
    "iso:country": "GB",
    "wof:name": "FK15 0GD",
    "wof:placetype": "postalcode"
  },
  "geometry": {"coordinates":[-3.963848,56.190239],"type":"Point"}
}
