{
  "type": "Feature",
  "properties": {
    "iso:country":"GB",
    "wof:name":"TN15 8RS",
    "wof:placetype":"postalcode"
},
  "geometry": {"coordinates":[0.30173168262694,51.29159763277477],"type":"Point"}
}