{
  "type": "Feature",
  "properties": {
    "iso:country": "GB",
    "wof:name": "TN15 8RS",
    "wof:placetype": "postalcode"
  },
  "geometry": {"coordinates":[0.301732,51.291598],"type":"Point"}
}
