{
  "type": "Feature",
  "properties": {
    "iso:country":"GB",
    "wof:name":"NE40 3JQ",
    "wof:placetype":"postalcode"
},
  "geometry": {"coordinates":[-1.75801587458447,54.97107083411961],"type":"Point"}
}