{
  "type": "Feature",
  "properties": {
    "date:inception_lower": "1980-01-01",
    "date:inception_upper": "1980-01-01",
    "iso:country": "GB",
    "wof:name": "NE40 3JQ",
    "wof:placetype": "postalcode"
  },
  "geometry": {"coordinates":[-1.758016,54.971071],"type":"Point"}
}
