{
  "type": "Feature",
  "properties": {
    "iso:country":"GB",
    "wof:name":"SY1 3EZ",
    "wof:placetype":"postalcode"
},
  "geometry": {"coordinates":[-2.74368061133076,52.73212920432555],"type":"Point"}
}