{
  "type": "Feature",
  "properties": {
    "iso:country":"GB",
    "wof:name":"CM21 9DA",
    "wof:placetype":"postalcode"
},
  "geometry": {"coordinates":[0.14859842498093,51.81368137983119],"type":"Point"}
}