{
  "type": "Feature",
  "properties": {
    "iso:country": "GB",
    "wof:name": "CM21 9DA",
    "wof:placetype": "postalcode"
  },
  "geometry": {"coordinates":[0.148598,51.813681],"type":"Point"}
}
