{
  "type": "Feature",
  "properties": {
    "date:inception_lower":"1997-12-01",
    "date:inception_upper":"1997-12-31",
    "iso:country":"GB",
    "wof:name":"BB18 5EZ",
    "wof:placetype":"postalcode"
},
  "geometry": {"coordinates":[-2.190766,53.920505],"type":"Point"}
}