{
  "type": "Feature",
  "properties": {
    "iso:country":"GB",
    "wof:name":"BB18 5EZ",
    "wof:placetype":"postalcode"
},
  "geometry": {"coordinates":[-2.19073255079669,53.9204641528198],"type":"Point"}
}