{
  "type": "Feature",
  "properties": {
    "iso:country":"GB",
    "wof:name":"NE62 5LT",
    "wof:placetype":"postalcode"
},
  "geometry": {"coordinates":[-1.60355404853523,55.15977891171474],"type":"Point"}
}