{
  "type": "Feature",
  "properties": {
    "iso:country": "GB",
    "wof:name": "LL17 0NP",
    "wof:placetype": "postalcode"
  },
  "geometry": {"coordinates":[-3.449529,53.254525],"type":"Point"}
}
