{
  "type": "Feature",
  "properties": {
    "iso:country":"GB",
    "wof:name":"CR0 5BH",
    "wof:placetype":"postalcode"
},
  "geometry": {"coordinates":[-0.04792660659959,51.35706042709649],"type":"Point"}
}