{
  "type": "Feature",
  "properties": {
    "iso:country":"GB",
    "wof:name":"SW16 3DP",
    "wof:placetype":"postalcode"
},
  "geometry": {"coordinates":[-0.12060100098412,51.42096407285901],"type":"Point"}
}