{
  "type": "Feature",
  "properties": {
    "iso:country":"GB",
    "wof:name":"AB11 6AR",
    "wof:placetype":"postalcode"
},
  "geometry": {"coordinates":[-2.09971169539007,57.14445639186938],"type":"Point"}
}