{
  "type": "Feature",
  "properties": {
    "iso:country": "GB",
    "wof:name": "WN2 3XL",
    "wof:placetype": "postalcode"
  },
  "geometry": {"coordinates":[-2.574073,53.529236],"type":"Point"}
}
