{
  "type": "Feature",
  "properties": {
    "iso:country":"GB",
    "wof:name":"WN2 3XL",
    "wof:placetype":"postalcode"
},
  "geometry": {"coordinates":[-2.57407319361625,53.52923566348345],"type":"Point"}
}