{
  "type": "Feature",
  "properties": {
    "iso:country":"GB",
    "wof:name":"CF33 4RP",
    "wof:placetype":"postalcode"
},
  "geometry": {"coordinates":[-3.69922097134561,51.50369447019875],"type":"Point"}
}