{
  "type": "Feature",
  "properties": {
    "date:inception_lower": "1980-01-01",
    "date:inception_upper": "1980-01-01",
    "iso:country": "GB",
    "wof:name": "CF33 4RP",
    "wof:placetype": "postalcode"
  },
  "geometry": {"coordinates":[-3.699682,51.504004],"type":"Point"}
}
