{
  "type": "Feature",
  "properties": {
    "iso:country":"GB",
    "wof:name":"LE12 8PQ",
    "wof:placetype":"postalcode"
},
  "geometry": {"coordinates":[-1.14973206751729,52.75313587725579],"type":"Point"}
}