{
  "type": "Feature",
  "properties": {
    "iso:country": "GB",
    "wof:name": "NE15 0BX",
    "wof:placetype": "postalcode"
  },
  "geometry": {"coordinates":[-1.790088,54.988698],"type":"Point"}
}
