{
  "type": "Feature",
  "properties": {
    "iso:country":"GB",
    "wof:name":"GU3 3NH",
    "wof:placetype":"postalcode"
},
  "geometry": {"coordinates":[-0.62228175322858,51.25999461821608],"type":"Point"}
}