{
  "type": "Feature",
  "properties": {
    "date:inception_lower": "1993-01-01",
    "date:inception_upper": "1993-01-01",
    "iso:country": "GB",
    "wof:name": "CF63 2HS",
    "wof:placetype": "postalcode"
  },
  "geometry": {"coordinates":[-3.258795,51.4146],"type":"Point"}
}
