{
  "type": "Feature",
  "properties": {
    "iso:country":"GB",
    "wof:name":"PR7 6BJ",
    "wof:placetype":"postalcode"
},
  "geometry": {"coordinates":[-2.68110345466817,53.67363924060114],"type":"Point"}
}