{
  "type": "Feature",
  "properties": {
    "iso:country": "GB",
    "wof:name": "WV3 8AJ",
    "wof:placetype": "postalcode"
  },
  "geometry": {"coordinates":[-2.165906,52.576262],"type":"Point"}
}
