{
  "type": "Feature",
  "properties": {
    "iso:country":"GB",
    "wof:name":"WV3 8AJ",
    "wof:placetype":"postalcode"
},
  "geometry": {"coordinates":[-2.16590638919142,52.57626217533858],"type":"Point"}
}