{
  "type": "Feature",
  "properties": {
    "iso:country": "GB",
    "wof:name": "E13 0HA",
    "wof:placetype": "postalcode"
  },
  "geometry": {"coordinates":[0.015708,51.525173],"type":"Point"}
}
