{
  "type": "Feature",
  "properties": {
    "iso:country":"GB",
    "wof:name":"PE12 0AU",
    "wof:placetype":"postalcode"
},
  "geometry": {"coordinates":[0.11573099347892,52.82273819756978],"type":"Point"}
}