{
  "type": "Feature",
  "properties": {
    "iso:country": "GB",
    "wof:name": "PE12 0AU",
    "wof:placetype": "postalcode"
  },
  "geometry": {"coordinates":[0.115731,52.822738],"type":"Point"}
}
