{
  "type": "Feature",
  "properties": {
    "date:inception_lower": "1983-07-01",
    "date:inception_upper": "1983-07-01",
    "iso:country": "GB",
    "wof:name": "BB9 8QY",
    "wof:placetype": "postalcode"
  },
  "geometry": {"coordinates":[-2.22681,53.848432],"type":"Point"}
}
