{
  "type": "Feature",
  "properties": {
    "iso:country":"GB",
    "wof:name":"BB9 8QY",
    "wof:placetype":"postalcode"
},
  "geometry": {"coordinates":[-2.22682380350874,53.84842666156337],"type":"Point"}
}