{
  "type": "Feature",
  "properties": {
    "iso:country":"GB",
    "wof:name":"SL4 4DN",
    "wof:placetype":"postalcode"
},
  "geometry": {"coordinates":[-0.6402870850716,51.47376145938318],"type":"Point"}
}