{
  "type": "Feature",
  "properties": {
    "iso:country": "GB",
    "wof:name": "DN20 0BB",
    "wof:placetype": "postalcode"
  },
  "geometry": {"coordinates":[-0.554285,53.571857],"type":"Point"}
}
