{
  "type": "Feature",
  "properties": {
    "date:inception_lower": "2004-02-01",
    "date:inception_upper": "2004-02-01",
    "iso:country": "GB",
    "wof:name": "CF24 2HB",
    "wof:placetype": "postalcode"
  },
  "geometry": {"coordinates":[-3.131666,51.490117],"type":"Point"}
}
