{
  "type": "Feature",
  "properties": {
    "iso:country":"GB",
    "wof:name":"CF24 2HB",
    "wof:placetype":"postalcode"
},
  "geometry": {"coordinates":[-3.13190177136859,51.49007765873459],"type":"Point"}
}