{
  "type": "Feature",
  "properties": {
    "iso:country":"GB",
    "wof:name":"OL14 5SL",
    "wof:placetype":"postalcode"
},
  "geometry": {"coordinates":[-2.08113519330834,53.71705684637774],"type":"Point"}
}