{
  "type": "Feature",
  "properties": {
    "iso:country":"GB",
    "wof:name":"SL1 2JE",
    "wof:placetype":"postalcode"
},
  "geometry": {"coordinates":[-0.59800627335008,51.50353996805528],"type":"Point"}
}