{
  "type": "Feature",
  "properties": {
    "iso:country":"GB",
    "wof:name":"WR6 6QQ",
    "wof:placetype":"postalcode"
},
  "geometry": {"coordinates":[-2.34728239840624,52.25528185649633],"type":"Point"}
}