{
  "type": "Feature",
  "properties": {
    "iso:country": "GB",
    "wof:name": "WR6 6QQ",
    "wof:placetype": "postalcode"
  },
  "geometry": {"coordinates":[-2.347282,52.255282],"type":"Point"}
}
