{
  "type": "Feature",
  "properties": {
    "iso:country":"GB",
    "wof:name":"CV21 1LQ",
    "wof:placetype":"postalcode"
},
  "geometry": {"coordinates":[-1.2422935708667,52.38814778146877],"type":"Point"}
}