{
  "type": "Feature",
  "properties": {
    "iso:country":"GB",
    "wof:name":"YO41 1DX",
    "wof:placetype":"postalcode"
},
  "geometry": {"coordinates":[-0.91439065134913,53.98454324674963],"type":"Point"}
}