{
  "type": "Feature",
  "properties": {
    "iso:country":"GB",
    "wof:name":"PE9 2BJ",
    "wof:placetype":"postalcode"
},
  "geometry": {"coordinates":[-0.47599707125087,52.65233565614071],"type":"Point"}
}