{
  "type": "Feature",
  "properties": {
    "iso:country":"GB",
    "wof:name":"TS18 5DQ",
    "wof:placetype":"postalcode"
},
  "geometry": {"coordinates":[-1.34748268603372,54.55218358271372],"type":"Point"}
}