{
  "type": "Feature",
  "properties": {
    "iso:country":"GB",
    "wof:name":"TS17 6HE",
    "wof:placetype":"postalcode"
},
  "geometry": {"coordinates":[-1.3057100706353,54.55293975181328],"type":"Point"}
}