{
  "type": "Feature",
  "properties": {
    "date:inception_lower": "2009-11-01",
    "date:inception_upper": "2009-11-01",
    "iso:country": "GB",
    "wof:name": "TS17 6HE",
    "wof:placetype": "postalcode"
  },
  "geometry": {"coordinates":[-1.305723,54.552952],"type":"Point"}
}
