{
  "type": "Feature",
  "properties": {
    "iso:country":"GB",
    "wof:name":"TQ1 1QQ",
    "wof:placetype":"postalcode"
},
  "geometry": {"coordinates":[-3.52403207192986,50.4660356365432],"type":"Point"}
}