{
  "type": "Feature",
  "properties": {
    "iso:country": "GB",
    "wof:name": "DY8 5DX",
    "wof:placetype": "postalcode"
  },
  "geometry": {"coordinates":[-2.154862,52.479929],"type":"Point"}
}
