{
  "type": "Feature",
  "properties": {
    "iso:country":"GB",
    "wof:name":"DY8 5DX",
    "wof:placetype":"postalcode"
},
  "geometry": {"coordinates":[-2.15494182348568,52.47991439182275],"type":"Point"}
}