{
  "type": "Feature",
  "properties": {
    "date:inception_lower": "1980-01-01",
    "date:inception_upper": "1980-01-01",
    "iso:country": "GB",
    "wof:name": "DY8 5DX",
    "wof:placetype": "postalcode"
  },
  "geometry": {"coordinates":[-2.154862,52.479929],"type":"Point"}
}
