{
  "type": "Feature",
  "properties": {
    "date:inception_lower": "2021-08-01",
    "date:inception_upper": "2021-08-01",
    "iso:country": "GB",
    "wof:name": "NG4 4DJ",
    "wof:placetype": "postalcode"
  },
  "geometry": {"coordinates":[-1.091306,52.986463],"type":"Point"}
}
