{
  "type": "Feature",
  "properties": {
    "iso:country": "GB",
    "wof:name": "CH61 8RD",
    "wof:placetype": "postalcode"
  },
  "geometry": {"coordinates":[-3.099316,53.348269],"type":"Point"}
}
