{
  "type": "Feature",
  "properties": {
    "iso:country":"GB",
    "wof:name":"CF5 1SE",
    "wof:placetype":"postalcode"
},
  "geometry": {"coordinates":[-3.21083098129193,51.48778746047493],"type":"Point"}
}