{
  "type": "Feature",
  "properties": {
    "date:inception_lower":"1991-01-01",
    "date:inception_upper":"1991-01-31",
    "iso:country":"GB",
    "wof:name":"HD7 4LQ",
    "wof:placetype":"postalcode"
},
  "geometry": {"coordinates":[-1.871563,53.635916],"type":"Point"}
}