{
  "type": "Feature",
  "properties": {
    "date:inception_lower": "2003-02-01",
    "date:inception_upper": "2003-02-01",
    "iso:country": "GB",
    "wof:name": "FY3 9ZL",
    "wof:placetype": "postalcode"
  },
  "geometry": {"coordinates":[-2.994661,53.802622],"type":"Point"}
}
