{
  "type": "Feature",
  "properties": {
    "iso:country":"GB",
    "wof:name":"PA8 7HF",
    "wof:placetype":"postalcode"
},
  "geometry": {"coordinates":[-4.45108974063056,55.89502330156719],"type":"Point"}
}