{
  "type": "Feature",
  "properties": {
    "iso:country": "GB",
    "wof:name": "PA8 7HF",
    "wof:placetype": "postalcode"
  },
  "geometry": {"coordinates":[-4.45109,55.895023],"type":"Point"}
}
