{
  "type": "Feature",
  "properties": {
    "date:inception_lower": "1980-01-01",
    "date:inception_upper": "1980-01-01",
    "iso:country": "GB",
    "wof:name": "CB6 2PR",
    "wof:placetype": "postalcode"
  },
  "geometry": {"coordinates":[0.121969,52.389448],"type":"Point"}
}
