{
  "type": "Feature",
  "properties": {
    "iso:country": "GB",
    "wof:name": "CB6 2PR",
    "wof:placetype": "postalcode"
  },
  "geometry": {"coordinates":[0.121969,52.389448],"type":"Point"}
}
