{
  "type": "Feature",
  "properties": {
    "iso:country":"GB",
    "wof:name":"CB6 2PR",
    "wof:placetype":"postalcode"
},
  "geometry": {"coordinates":[0.12194375462544,52.38943162713851],"type":"Point"}
}