{
  "type": "Feature",
  "properties": {
    "date:inception_lower":"1995-07-01",
    "date:inception_upper":"1995-07-31",
    "iso:country":"GB",
    "wof:name":"RG18 3BD",
    "wof:placetype":"postalcode"
},
  "geometry": {"coordinates":[-1.271063,51.405358],"type":"Point"}
}