{
  "type": "Feature",
  "properties": {
    "iso:country":"GB",
    "wof:name":"YO62 4LT",
    "wof:placetype":"postalcode"
},
  "geometry": {"coordinates":[-0.96330178725376,54.16601120367526],"type":"Point"}
}