{
  "type": "Feature",
  "properties": {
    "iso:country":"GB",
    "wof:name":"DA11 9NZ",
    "wof:placetype":"postalcode"
},
  "geometry": {"coordinates":[0.35469824941037,51.43937489769864],"type":"Point"}
}