{
  "type": "Feature",
  "properties": {
    "date:inception_lower":"1980-01-01",
    "date:inception_upper":"1980-01-31",
    "iso:country":"GB",
    "wof:name":"NN14 1HU",
    "wof:placetype":"postalcode"
},
  "geometry": {"coordinates":[-0.700908,52.358405],"type":"Point"}
}