{
  "type": "Feature",
  "properties": {
    "iso:country": "GB",
    "wof:name": "NN14 1HU",
    "wof:placetype": "postalcode"
  },
  "geometry": {"coordinates":[-0.700908,52.358405],"type":"Point"}
}
