{
  "type": "Feature",
  "properties": {
    "iso:country":"GB",
    "wof:name":"EX33 2LZ",
    "wof:placetype":"postalcode"
},
  "geometry": {"coordinates":[-4.15604103270434,51.12625056323268],"type":"Point"}
}