{
  "type": "Feature",
  "properties": {
    "iso:country":"GB",
    "wof:name":"GL5 1QS",
    "wof:placetype":"postalcode"
},
  "geometry": {"coordinates":[-2.21170903623381,51.74831151068874],"type":"Point"}
}