{
  "type": "Feature",
  "properties": {
    "iso:country":"GB",
    "wof:name":"WF9 4BG",
    "wof:placetype":"postalcode"
},
  "geometry": {"coordinates":[-1.34737512630103,53.61059457291081],"type":"Point"}
}