{
  "type": "Feature",
  "properties": {
    "iso:country": "GB",
    "wof:name": "PE11 2RU",
    "wof:placetype": "postalcode"
  },
  "geometry": {"coordinates":[-0.145594,52.779153],"type":"Point"}
}
