{
  "type": "Feature",
  "properties": {
    "iso:country":"GB",
    "wof:name":"KT16 8BX",
    "wof:placetype":"postalcode"
},
  "geometry": {"coordinates":[-0.50218367029721,51.38368502249526],"type":"Point"}
}