{
  "type": "Feature",
  "properties": {
    "iso:country": "GB",
    "wof:name": "KT16 8BX",
    "wof:placetype": "postalcode"
  },
  "geometry": {"coordinates":[-0.502184,51.383685],"type":"Point"}
}
