{
  "type": "Feature",
  "properties": {
    "iso:country":"GB",
    "wof:name":"KA6 7AP",
    "wof:placetype":"postalcode"
},
  "geometry": {"coordinates":[-4.46261090851686,55.4355238354381],"type":"Point"}
}