{
  "type": "Feature",
  "properties": {
    "iso:country": "GB",
    "wof:name": "LE17 5NQ",
    "wof:placetype": "postalcode"
  },
  "geometry": {"coordinates":[-1.173783,52.510487],"type":"Point"}
}
