{
  "type": "Feature",
  "properties": {
    "iso:country":"GB",
    "wof:name":"DL13 3NU",
    "wof:placetype":"postalcode"
},
  "geometry": {"coordinates":[-1.9022104169038,54.70754811302193],"type":"Point"}
}