{
  "type": "Feature",
  "properties": {
    "iso:country":"GB",
    "wof:name":"OX4 3LX",
    "wof:placetype":"postalcode"
},
  "geometry": {"coordinates":[-1.21273138474608,51.73324409545153],"type":"Point"}
}