{
  "type": "Feature",
  "properties": {
    "date:inception_lower": "1980-01-01",
    "date:inception_upper": "1980-01-01",
    "iso:country": "GB",
    "wof:name": "OX4 3LX",
    "wof:placetype": "postalcode"
  },
  "geometry": {"coordinates":[-1.212564,51.733446],"type":"Point"}
}
