{
  "type": "Feature",
  "properties": {
    "iso:country":"GB",
    "wof:name":"CF64 1SS",
    "wof:placetype":"postalcode"
},
  "geometry": {"coordinates":[-3.17829000399163,51.44626153128888],"type":"Point"}
}