{
  "type": "Feature",
  "properties": {
    "date:inception_lower": "2001-12-01",
    "date:inception_upper": "2001-12-01",
    "iso:country": "GB",
    "wof:name": "CF64 1SS",
    "wof:placetype": "postalcode"
  },
  "geometry": {"coordinates":[-3.17829,51.446262],"type":"Point"}
}
