{
  "type": "Feature",
  "properties": {
    "iso:country": "GB",
    "wof:name": "CF64 1SS",
    "wof:placetype": "postalcode"
  },
  "geometry": {"coordinates":[-3.17829,51.446262],"type":"Point"}
}
