{
  "type": "Feature",
  "properties": {
    "iso:country":"GB",
    "wof:name":"SE6 3NQ",
    "wof:placetype":"postalcode"
},
  "geometry": {"coordinates":[-0.02866549478096,51.42528101374467],"type":"Point"}
}