{
  "type": "Feature",
  "properties": {
    "iso:country":"GB",
    "wof:name":"CT6 7EA",
    "wof:placetype":"postalcode"
},
  "geometry": {"coordinates":[1.14355518457413,51.35864766133442],"type":"Point"}
}