{
  "type": "Feature",
  "properties": {
    "iso:country":"GB",
    "wof:name":"CM6 1XH",
    "wof:placetype":"postalcode"
},
  "geometry": {"coordinates":[0.37034277085774,51.86829505890776],"type":"Point"}
}