{
  "type": "Feature",
  "properties": {
    "iso:country": "GB",
    "wof:name": "CM6 1XH",
    "wof:placetype": "postalcode"
  },
  "geometry": {"coordinates":[0.370343,51.868295],"type":"Point"}
}
