{
  "type": "Feature",
  "properties": {
    "iso:country": "GB",
    "wof:name": "CO3 4RZ",
    "wof:placetype": "postalcode"
  },
  "geometry": {"coordinates":[0.865648,51.874508],"type":"Point"}
}
