{
  "type": "Feature",
  "properties": {
    "date:inception_lower": "1981-06-01",
    "date:inception_upper": "1981-06-01",
    "iso:country": "GB",
    "wof:name": "BA14 6RP",
    "wof:placetype": "postalcode"
  },
  "geometry": {"coordinates":[-2.199587,51.357009],"type":"Point"}
}
