{
  "type": "Feature",
  "properties": {
    "iso:country":"GB",
    "wof:name":"BN3 6NN",
    "wof:placetype":"postalcode"
},
  "geometry": {"coordinates":[-0.16375682242302,50.83810957461501],"type":"Point"}
}