{
  "type": "Feature",
  "properties": {
    "date:inception_lower": "1980-01-01",
    "date:inception_upper": "1980-01-01",
    "iso:country": "GB",
    "wof:name": "OX5 1LW",
    "wof:placetype": "postalcode"
  },
  "geometry": {"coordinates":[-1.312177,51.807074],"type":"Point"}
}
