{
  "type": "Feature",
  "properties": {
    "iso:country":"GB",
    "wof:name":"OX5 1LW",
    "wof:placetype":"postalcode"
},
  "geometry": {"coordinates":[-1.31217732035332,51.80707430674478],"type":"Point"}
}