{
  "type": "Feature",
  "properties": {
    "iso:country":"GB",
    "wof:name":"NP12 0QR",
    "wof:placetype":"postalcode"
},
  "geometry": {"coordinates":[-3.20279440738602,51.70253064604471],"type":"Point"}
}