{
  "type": "Feature",
  "properties": {
    "date:inception_lower":"1999-06-01",
    "date:inception_upper":"1999-06-30",
    "iso:country":"GB",
    "wof:name":"NP12 0QR",
    "wof:placetype":"postalcode"
},
  "geometry": {"coordinates":[-3.202794,51.702531],"type":"Point"}
}