{
  "type": "Feature",
  "properties": {
    "iso:country": "GB",
    "wof:name": "IP30 0NR",
    "wof:placetype": "postalcode"
  },
  "geometry": {"coordinates":[0.836331,52.147771],"type":"Point"}
}
