{
  "type": "Feature",
  "properties": {
    "iso:country":"GB",
    "wof:name":"IP30 0NR",
    "wof:placetype":"postalcode"
},
  "geometry": {"coordinates":[0.83633142694494,52.14777116168116],"type":"Point"}
}