{
  "type": "Feature",
  "properties": {
    "iso:country":"GB",
    "wof:name":"EX3 0QX",
    "wof:placetype":"postalcode"
},
  "geometry": {"coordinates":[-3.43989754219248,50.68323772544218],"type":"Point"}
}