{
  "type": "Feature",
  "properties": {
    "iso:country": "GB",
    "wof:name": "NE26 4AE",
    "wof:placetype": "postalcode"
  },
  "geometry": {"coordinates":[-1.463992,55.05932],"type":"Point"}
}
