{
  "type": "Feature",
  "properties": {
    "iso:country":"GB",
    "wof:name":"BD8 8AH",
    "wof:placetype":"postalcode"
},
  "geometry": {"coordinates":[-1.76886632142445,53.8061941315832],"type":"Point"}
}