{
  "type": "Feature",
  "properties": {
    "iso:country": "GB",
    "wof:name": "NE11 9UD",
    "wof:placetype": "postalcode"
  },
  "geometry": {"coordinates":[-1.644953,54.947744],"type":"Point"}
}
