{
  "type": "Feature",
  "properties": {
    "iso:country":"GB",
    "wof:name":"M31 4FU",
    "wof:placetype":"postalcode"
},
  "geometry": {"coordinates":[-2.4288203703915,53.41492686232259],"type":"Point"}
}