{
  "type": "Feature",
  "properties": {
    "date:inception_lower": "1980-01-01",
    "date:inception_upper": "1980-01-01",
    "iso:country": "GB",
    "wof:name": "M31 4FU",
    "wof:placetype": "postalcode"
  },
  "geometry": {"coordinates":[-2.42882,53.414927],"type":"Point"}
}
