{
  "type": "Feature",
  "properties": {
    "iso:country":"GB",
    "wof:name":"BN3 2RT",
    "wof:placetype":"postalcode"
},
  "geometry": {"coordinates":[-0.17244353907464,50.82697720918608],"type":"Point"}
}