{
  "type": "Feature",
  "properties": {
    "iso:country":"GB",
    "wof:name":"KT1 2DD",
    "wof:placetype":"postalcode"
},
  "geometry": {"coordinates":[-0.30284465241347,51.4043029602914],"type":"Point"}
}