{
  "type": "Feature",
  "properties": {
    "iso:country":"GB",
    "wof:name":"HD8 9BE",
    "wof:placetype":"postalcode"
},
  "geometry": {"coordinates":[-1.65206706674418,53.5945650416536],"type":"Point"}
}