{
  "type": "Feature",
  "properties": {
    "date:inception_lower":"1986-07-01",
    "date:inception_upper":"1986-07-31",
    "iso:country":"GB",
    "wof:name":"IP22 1TG",
    "wof:placetype":"postalcode"
},
  "geometry": {"coordinates":[1.111539,52.363988],"type":"Point"}
}