{
  "type": "Feature",
  "properties": {
    "iso:country":"GB",
    "wof:name":"IP22 1TG",
    "wof:placetype":"postalcode"
},
  "geometry": {"coordinates":[1.11036492500893,52.36376452880603],"type":"Point"}
}