{
  "type": "Feature",
  "properties": {
    "iso:country":"GB",
    "wof:name":"CM1 2NS",
    "wof:placetype":"postalcode"
},
  "geometry": {"coordinates":[0.44028487531711,51.73987571395249],"type":"Point"}
}