{
  "type": "Feature",
  "properties": {
    "iso:country":"GB",
    "wof:name":"N4 3RW",
    "wof:placetype":"postalcode"
},
  "geometry": {"coordinates":[-0.11351559486626,51.57087314391034],"type":"Point"}
}