{
  "type": "Feature",
  "properties": {
    "iso:country":"GB",
    "wof:name":"CV47 7RU",
    "wof:placetype":"postalcode"
},
  "geometry": {"coordinates":[-1.27884542601176,52.21515812510349],"type":"Point"}
}