{
  "type": "Feature",
  "properties": {
    "date:inception_lower": "1999-12-01",
    "date:inception_upper": "1999-12-01",
    "iso:country": "GB",
    "wof:name": "CV47 7RU",
    "wof:placetype": "postalcode"
  },
  "geometry": {"coordinates":[-1.278845,52.215158],"type":"Point"}
}
