{
  "type": "Feature",
  "properties": {
    "iso:country":"GB",
    "wof:name":"NE61 6NR",
    "wof:placetype":"postalcode"
},
  "geometry": {"coordinates":[-1.63764298982927,55.16325465556138],"type":"Point"}
}