{
  "type": "Feature",
  "properties": {
    "date:inception_lower":"1980-01-01",
    "date:inception_upper":"1980-01-31",
    "iso:country":"GB",
    "wof:name":"G72 7BZ",
    "wof:placetype":"postalcode"
},
  "geometry": {"coordinates":[-4.187408,55.825299],"type":"Point"}
}