{
  "type": "Feature",
  "properties": {
    "iso:country":"GB",
    "wof:name":"CV2 2RQ",
    "wof:placetype":"postalcode"
},
  "geometry": {"coordinates":[-1.44351748658392,52.43546635495485],"type":"Point"}
}