{
  "type": "Feature",
  "properties": {
    "date:inception_lower": "2014-06-01",
    "date:inception_upper": "2014-06-01",
    "iso:country": "GB",
    "wof:name": "IP1 2DX",
    "wof:placetype": "postalcode"
  },
  "geometry": {"coordinates":[1.147969,52.057835],"type":"Point"}
}
