{
  "type": "Feature",
  "properties": {
    "iso:country": "GB",
    "wof:name": "L37 7EJ",
    "wof:placetype": "postalcode"
  },
  "geometry": {"coordinates":[-3.056421,53.567591],"type":"Point"}
}
