{
  "type": "Feature",
  "properties": {
    "iso:country": "GB",
    "wof:name": "MK6 5DG",
    "wof:placetype": "postalcode"
  },
  "geometry": {"coordinates":[-0.746702,52.024665],"type":"Point"}
}
