{
  "type": "Feature",
  "properties": {
    "iso:country":"GB",
    "wof:name":"G21 3HE",
    "wof:placetype":"postalcode"
},
  "geometry": {"coordinates":[-4.20436353250683,55.88002560386497],"type":"Point"}
}