{
  "type": "Feature",
  "properties": {
    "iso:country":"GB",
    "wof:name":"HU3 2PJ",
    "wof:placetype":"postalcode"
},
  "geometry": {"coordinates":[-0.35620830209483,53.73937660401315],"type":"Point"}
}