{
  "type": "Feature",
  "properties": {
    "date:inception_lower":"1994-12-01",
    "date:inception_upper":"1994-12-31",
    "iso:country":"GB",
    "wof:name":"HU3 2PJ",
    "wof:placetype":"postalcode"
},
  "geometry": {"coordinates":[-0.356208,53.739377],"type":"Point"}
}