{
  "type": "Feature",
  "properties": {
    "iso:country": "GB",
    "wof:name": "HU3 2PJ",
    "wof:placetype": "postalcode"
  },
  "geometry": {"coordinates":[-0.356208,53.739377],"type":"Point"}
}
