{
  "type": "Feature",
  "properties": {
    "iso:country":"GB",
    "wof:name":"G84 8XG",
    "wof:placetype":"postalcode"
},
  "geometry": {"coordinates":[-4.73673938610526,56.00629351101391],"type":"Point"}
}