{
  "type": "Feature",
  "properties": {
    "iso:country":"GB",
    "wof:name":"SW3 6DU",
    "wof:placetype":"postalcode"
},
  "geometry": {"coordinates":[-0.17448943622228,51.48602262979229],"type":"Point"}
}