{
  "type": "Feature",
  "properties": {
    "iso:country":"GB",
    "wof:name":"W6 8AB",
    "wof:placetype":"postalcode"
},
  "geometry": {"coordinates":[-0.22346286246387,51.49226917171475],"type":"Point"}
}