{
  "type": "Feature",
  "properties": {
    "date:inception_lower": "1992-01-01",
    "date:inception_upper": "1992-01-01",
    "iso:country": "GB",
    "wof:name": "PL17 7LB",
    "wof:placetype": "postalcode"
  },
  "geometry": {"coordinates":[-4.314638,50.502496],"type":"Point"}
}
