{
  "type": "Feature",
  "properties": {
    "iso:country":"GB",
    "wof:name":"SM6 9QW",
    "wof:placetype":"postalcode"
},
  "geometry": {"coordinates":[-0.14604476626185,51.35659510410814],"type":"Point"}
}