{
  "type": "Feature",
  "properties": {
    "iso:country":"GB",
    "wof:name":"LS13 2SF",
    "wof:placetype":"postalcode"
},
  "geometry": {"coordinates":[-1.61173440799031,53.81436330727668],"type":"Point"}
}