{
  "type": "Feature",
  "properties": {
    "iso:country":"GB",
    "wof:name":"BN1 7JS",
    "wof:placetype":"postalcode"
},
  "geometry": {"coordinates":[-0.13347701939052,50.84592105892494],"type":"Point"}
}