{
  "type": "Feature",
  "properties": {
    "date:inception_lower":"1997-06-01",
    "date:inception_upper":"1997-06-30",
    "iso:country":"GB",
    "wof:name":"S35 7DG",
    "wof:placetype":"postalcode"
},
  "geometry": {"coordinates":[-1.520664,53.470385],"type":"Point"}
}