{
  "type": "Feature",
  "properties": {
    "iso:country": "GB",
    "wof:name": "S35 7DG",
    "wof:placetype": "postalcode"
  },
  "geometry": {"coordinates":[-1.520664,53.470385],"type":"Point"}
}
