{
  "type": "Feature",
  "properties": {
    "date:inception_lower":"2008-09-01",
    "date:inception_upper":"2008-09-30",
    "iso:country":"GB",
    "wof:name":"LE11 3AP",
    "wof:placetype":"postalcode"
},
  "geometry": {"coordinates":[-1.222003,52.772116],"type":"Point"}
}