{
  "type": "Feature",
  "properties": {
    "iso:country":"GB",
    "wof:name":"LE11 3AP",
    "wof:placetype":"postalcode"
},
  "geometry": {"coordinates":[-1.22200975714667,52.77208773176431],"type":"Point"}
}