{
  "type": "Feature",
  "properties": {
    "iso:country":"GB",
    "wof:name":"GL7 1HZ",
    "wof:placetype":"postalcode"
},
  "geometry": {"coordinates":[-1.94840192916435,51.70869677326765],"type":"Point"}
}