{
  "type": "Feature",
  "properties": {
    "iso:country": "GB",
    "wof:name": "GL7 1HZ",
    "wof:placetype": "postalcode"
  },
  "geometry": {"coordinates":[-1.948402,51.708697],"type":"Point"}
}
