{
  "type": "Feature",
  "properties": {
    "iso:country":"GB",
    "wof:name":"SE1 5HB",
    "wof:placetype":"postalcode"
},
  "geometry": {"coordinates":[-0.06844736779002,51.48781295909735],"type":"Point"}
}