{
  "type": "Feature",
  "properties": {
    "iso:country":"GB",
    "wof:name":"HD7 6NW",
    "wof:placetype":"postalcode"
},
  "geometry": {"coordinates":[-1.92300295897665,53.59179173973902],"type":"Point"}
}