{
  "type": "Feature",
  "properties": {
    "iso:country": "GB",
    "wof:name": "LS14 6AH",
    "wof:placetype": "postalcode"
  },
  "geometry": {"coordinates":[-1.477793,53.803661],"type":"Point"}
}
