{
  "type": "Feature",
  "properties": {
    "iso:country":"GB",
    "wof:name":"HU16 4DN",
    "wof:placetype":"postalcode"
},
  "geometry": {"coordinates":[-0.40948530635656,53.78122941009228],"type":"Point"}
}