{
  "type": "Feature",
  "properties": {
    "iso:country": "GB",
    "wof:name": "HU16 4DN",
    "wof:placetype": "postalcode"
  },
  "geometry": {"coordinates":[-0.409485,53.781229],"type":"Point"}
}
