{
  "type": "Feature",
  "properties": {
    "iso:country": "GB",
    "wof:name": "HP23 6EY",
    "wof:placetype": "postalcode"
  },
  "geometry": {"coordinates":[-0.640942,51.781551],"type":"Point"}
}
