{
  "type": "Feature",
  "properties": {
    "iso:country":"GB",
    "wof:name":"HP23 6EY",
    "wof:placetype":"postalcode"
},
  "geometry": {"coordinates":[-0.64094164967721,51.78155088429551],"type":"Point"}
}