{
  "type": "Feature",
  "properties": {
    "date:inception_lower": "2007-02-01",
    "date:inception_upper": "2007-02-01",
    "iso:country": "GB",
    "wof:name": "NW1 0TU",
    "wof:placetype": "postalcode"
  },
  "geometry": {"coordinates":[-0.133524,51.536851],"type":"Point"}
}
