{
  "type": "Feature",
  "properties": {
    "date:inception_lower": "1980-01-01",
    "date:inception_upper": "1980-01-01",
    "iso:country": "GB",
    "wof:name": "TS21 3LQ",
    "wof:placetype": "postalcode"
  },
  "geometry": {"coordinates":[-1.364684,54.609156],"type":"Point"}
}
