{
  "type": "Feature",
  "properties": {
    "iso:country":"GB",
    "wof:name":"TS21 3LQ",
    "wof:placetype":"postalcode"
},
  "geometry": {"coordinates":[-1.3646862746428,54.6091715470211],"type":"Point"}
}