{
  "type": "Feature",
  "properties": {
    "date:inception_lower":"1980-01-01",
    "date:inception_upper":"1980-01-31",
    "iso:country":"GB",
    "wof:name":"TS21 3LQ",
    "wof:placetype":"postalcode"
},
  "geometry": {"coordinates":[-1.367996,54.609236],"type":"Point"}
}