{
  "type": "Feature",
  "properties": {
    "iso:country": "GB",
    "wof:name": "TS21 3LQ",
    "wof:placetype": "postalcode"
  },
  "geometry": {"coordinates":[-1.367996,54.609236],"type":"Point"}
}
