{
  "type": "Feature",
  "properties": {
    "iso:country": "GB",
    "wof:name": "TA12 6DT",
    "wof:placetype": "postalcode"
  },
  "geometry": {"coordinates":[-2.769771,50.972743],"type":"Point"}
}
