{
  "type": "Feature",
  "properties": {
    "iso:country": "GB",
    "wof:name": "SK8 7AG",
    "wof:placetype": "postalcode"
  },
  "geometry": {"coordinates":[-2.187226,53.373754],"type":"Point"}
}
