{
  "type": "Feature",
  "properties": {
    "iso:country":"GB",
    "wof:name":"SS7 2GA",
    "wof:placetype":"postalcode"
},
  "geometry": {"coordinates":[0.61762178547152,51.5517922277275],"type":"Point"}
}