{
  "type": "Feature",
  "properties": {
    "date:inception_lower": "1999-12-01",
    "date:inception_upper": "1999-12-01",
    "iso:country": "GB",
    "wof:name": "SS7 2GA",
    "wof:placetype": "postalcode"
  },
  "geometry": {"coordinates":[0.617622,51.551792],"type":"Point"}
}
