{
  "type": "Feature",
  "properties": {
    "iso:country": "GB",
    "wof:name": "SS7 2GA",
    "wof:placetype": "postalcode"
  },
  "geometry": {"coordinates":[0.617622,51.551792],"type":"Point"}
}
