{
  "type": "Feature",
  "properties": {
    "iso:country":"GB",
    "wof:name":"B24 9SN",
    "wof:placetype":"postalcode"
},
  "geometry": {"coordinates":[-1.82774025989583,52.51470023062856],"type":"Point"}
}