{
  "type": "Feature",
  "properties": {
    "iso:country":"GB",
    "wof:name":"TN3 0DG",
    "wof:placetype":"postalcode"
},
  "geometry": {"coordinates":[0.21359035941153,51.13273938117133],"type":"Point"}
}