{
  "type": "Feature",
  "properties": {
    "iso:country":"GB",
    "wof:name":"KA21 6LR",
    "wof:placetype":"postalcode"
},
  "geometry": {"coordinates":[-4.77750658867498,55.64265510483974],"type":"Point"}
}