{
  "type": "Feature",
  "properties": {
    "iso:country":"GB",
    "wof:name":"E16 3AF",
    "wof:placetype":"postalcode"
},
  "geometry": {"coordinates":[0.01945211945967,51.51073829763549],"type":"Point"}
}