{
  "type": "Feature",
  "properties": {
    "iso:country":"GB",
    "wof:name":"L40 7SJ",
    "wof:placetype":"postalcode"
},
  "geometry": {"coordinates":[-2.84701216230456,53.59828153549955],"type":"Point"}
}