{
  "type": "Feature",
  "properties": {
    "iso:country":"GB",
    "wof:name":"OX49 5QZ",
    "wof:placetype":"postalcode"
},
  "geometry": {"coordinates":[-1.00314887236918,51.64716966528862],"type":"Point"}
}