{
  "type": "Feature",
  "properties": {
    "iso:country":"GB",
    "wof:name":"SS14 2SH",
    "wof:placetype":"postalcode"
},
  "geometry": {"coordinates":[0.4812119121504,51.57855352994319],"type":"Point"}
}