{
  "type": "Feature",
  "properties": {
    "date:inception_lower": "2024-05-01",
    "date:inception_upper": "2024-05-01",
    "iso:country": "GB",
    "wof:name": "PR5 5BZ",
    "wof:placetype": "postalcode"
  },
  "geometry": {"coordinates":[-2.686972,53.738643],"type":"Point"}
}
