{
  "type": "Feature",
  "properties": {
    "iso:country":"GB",
    "wof:name":"WS6 6LF",
    "wof:placetype":"postalcode"
},
  "geometry": {"coordinates":[-2.02196006256891,52.66709215259264],"type":"Point"}
}