{
  "type": "Feature",
  "properties": {
    "iso:country": "GB",
    "wof:name": "DE24 9PS",
    "wof:placetype": "postalcode"
  },
  "geometry": {"coordinates":[-1.483482,52.881073],"type":"Point"}
}
