{
  "type": "Feature",
  "properties": {
    "iso:country":"GB",
    "wof:name":"CT1 3RD",
    "wof:placetype":"postalcode"
},
  "geometry": {"coordinates":[1.07160474752577,51.27420084119355],"type":"Point"}
}