{
  "type": "Feature",
  "properties": {
    "iso:country":"GB",
    "wof:name":"AB33 8SJ",
    "wof:placetype":"postalcode"
},
  "geometry": {"coordinates":[-2.89803975139523,57.19981638344526],"type":"Point"}
}