{
  "type": "Feature",
  "properties": {
    "iso:country": "GB",
    "wof:name": "AB33 8SJ",
    "wof:placetype": "postalcode"
  },
  "geometry": {"coordinates":[-2.89804,57.199816],"type":"Point"}
}
