{
  "type": "Feature",
  "properties": {
    "iso:country":"GB",
    "wof:name":"CR0 5EB",
    "wof:placetype":"postalcode"
},
  "geometry": {"coordinates":[-0.05615899362921,51.37261100442554],"type":"Point"}
}