{
  "type": "Feature",
  "properties": {
    "iso:country":"GB",
    "wof:name":"PH33 7LN",
    "wof:placetype":"postalcode"
},
  "geometry": {"coordinates":[-5.13330372489025,56.84397017380997],"type":"Point"}
}