{
  "type": "Feature",
  "properties": {
    "iso:country": "GB",
    "wof:name": "PH33 7LN",
    "wof:placetype": "postalcode"
  },
  "geometry": {"coordinates":[-5.133304,56.84397],"type":"Point"}
}
