{
  "type": "Feature",
  "properties": {
    "date:inception_lower": "1998-06-01",
    "date:inception_upper": "1998-06-01",
    "iso:country": "GB",
    "wof:name": "CV11 4GA",
    "wof:placetype": "postalcode"
  },
  "geometry": {"coordinates":[-1.44757,52.501913],"type":"Point"}
}
