{
  "type": "Feature",
  "properties": {
    "iso:country":"GB",
    "wof:name":"CO2 8RR",
    "wof:placetype":"postalcode"
},
  "geometry": {"coordinates":[0.91164671846926,51.87289241393186],"type":"Point"}
}