{
  "type": "Feature",
  "properties": {
    "date:inception_lower": "2020-06-01",
    "date:inception_upper": "2020-06-01",
    "iso:country": "GB",
    "wof:name": "NR7 8GZ",
    "wof:placetype": "postalcode"
  },
  "geometry": {"coordinates":[1.34211,52.654903],"type":"Point"}
}
