{
  "type": "Feature",
  "properties": {
    "iso:country":"GB",
    "wof:name":"PO10 7JU",
    "wof:placetype":"postalcode"
},
  "geometry": {"coordinates":[-0.95089524499628,50.84497172606982],"type":"Point"}
}