{
  "type": "Feature",
  "properties": {
    "date:inception_lower": "1980-01-01",
    "date:inception_upper": "1980-01-01",
    "iso:country": "GB",
    "wof:name": "PO10 7JU",
    "wof:placetype": "postalcode"
  },
  "geometry": {"coordinates":[-0.950895,50.844972],"type":"Point"}
}
