{
  "type": "Feature",
  "properties": {
    "iso:country":"GB",
    "wof:name":"L31 6ER",
    "wof:placetype":"postalcode"
},
  "geometry": {"coordinates":[-2.9402365195835,53.51214774790225],"type":"Point"}
}