{
  "type": "Feature",
  "properties": {
    "iso:country": "GB",
    "wof:name": "L31 6ER",
    "wof:placetype": "postalcode"
  },
  "geometry": {"coordinates":[-2.940236,53.512148],"type":"Point"}
}
