{
  "type": "Feature",
  "properties": {
    "iso:country":"GB",
    "wof:name":"CO13 0DF",
    "wof:placetype":"postalcode"
},
  "geometry": {"coordinates":[1.23153008446401,51.85151090067476],"type":"Point"}
}