{
  "type": "Feature",
  "properties": {
    "iso:country":"GB",
    "wof:name":"SO24 0LR",
    "wof:placetype":"postalcode"
},
  "geometry": {"coordinates":[-1.122242653771,51.04653284355339],"type":"Point"}
}