{
  "type": "Feature",
  "properties": {
    "date:inception_lower":"1980-01-01",
    "date:inception_upper":"1980-01-31",
    "iso:country":"GB",
    "wof:name":"TA22 9QL",
    "wof:placetype":"postalcode"
},
  "geometry": {"coordinates":[-3.629825,51.063773],"type":"Point"}
}