{
  "type": "Feature",
  "properties": {
    "date:inception_lower": "1980-01-01",
    "date:inception_upper": "1980-01-01",
    "iso:country": "GB",
    "wof:name": "CO15 5AB",
    "wof:placetype": "postalcode"
  },
  "geometry": {"coordinates":[1.173334,51.79557],"type":"Point"}
}
