{
  "type": "Feature",
  "properties": {
    "iso:country":"GB",
    "wof:name":"CO15 5AB",
    "wof:placetype":"postalcode"
},
  "geometry": {"coordinates":[1.17333374289845,51.79556955880252],"type":"Point"}
}