{
  "type": "Feature",
  "properties": {
    "iso:country":"GB",
    "wof:name":"LL30 2YL",
    "wof:placetype":"postalcode"
},
  "geometry": {"coordinates":[-3.83504204145949,53.32285909555426],"type":"Point"}
}