{
  "type": "Feature",
  "properties": {
    "iso:country":"GB",
    "wof:name":"LS6 2RY",
    "wof:placetype":"postalcode"
},
  "geometry": {"coordinates":[-1.54687007861272,53.81410000843688],"type":"Point"}
}