{
  "type": "Feature",
  "properties": {
    "date:inception_lower": "1998-06-01",
    "date:inception_upper": "1998-06-01",
    "iso:country": "GB",
    "wof:name": "LS6 2RY",
    "wof:placetype": "postalcode"
  },
  "geometry": {"coordinates":[-1.54687,53.8141],"type":"Point"}
}
