{
  "type": "Feature",
  "properties": {
    "iso:country":"GB",
    "wof:name":"DD9 6HH",
    "wof:placetype":"postalcode"
},
  "geometry": {"coordinates":[-2.66019123411019,56.7311764086976],"type":"Point"}
}