{
  "type": "Feature",
  "properties": {
    "date:inception_lower": "1980-01-01",
    "date:inception_upper": "1980-01-01",
    "iso:country": "GB",
    "wof:name": "DD9 6HH",
    "wof:placetype": "postalcode"
  },
  "geometry": {"coordinates":[-2.660191,56.731176],"type":"Point"}
}
