{
  "type": "Feature",
  "properties": {
    "iso:country": "GB",
    "wof:name": "DD9 6HH",
    "wof:placetype": "postalcode"
  },
  "geometry": {"coordinates":[-2.660191,56.731176],"type":"Point"}
}
