{
  "type": "Feature",
  "properties": {
    "iso:country":"GB",
    "wof:name":"B46 3LU",
    "wof:placetype":"postalcode"
},
  "geometry": {"coordinates":[-1.70640207639091,52.4932004649808],"type":"Point"}
}