{
  "type": "Feature",
  "properties": {
    "iso:country": "GB",
    "wof:name": "SR2 8QT",
    "wof:placetype": "postalcode"
  },
  "geometry": {"coordinates":[-1.366966,54.899867],"type":"Point"}
}
