{
  "type": "Feature",
  "properties": {
    "iso:country":"GB",
    "wof:name":"B68 0BL",
    "wof:placetype":"postalcode"
},
  "geometry": {"coordinates":[-1.99986781986964,52.46350161455573],"type":"Point"}
}