{
  "type": "Feature",
  "properties": {
    "iso:country": "GB",
    "wof:name": "B68 0BL",
    "wof:placetype": "postalcode"
  },
  "geometry": {"coordinates":[-1.999868,52.463502],"type":"Point"}
}
