{
  "type": "Feature",
  "properties": {
    "date:inception_lower": "2008-01-01",
    "date:inception_upper": "2008-01-01",
    "iso:country": "GB",
    "wof:name": "B68 0BL",
    "wof:placetype": "postalcode"
  },
  "geometry": {"coordinates":[-1.999868,52.463502],"type":"Point"}
}
