{
  "type": "Feature",
  "properties": {
    "iso:country":"GB",
    "wof:name":"SN12 6PN",
    "wof:placetype":"postalcode"
},
  "geometry": {"coordinates":[-2.1011266834726,51.33786661407949],"type":"Point"}
}