{
  "type": "Feature",
  "properties": {
    "date:inception_lower": "1980-01-01",
    "date:inception_upper": "1980-01-01",
    "iso:country": "GB",
    "wof:name": "SN12 6PN",
    "wof:placetype": "postalcode"
  },
  "geometry": {"coordinates":[-2.101127,51.337867],"type":"Point"}
}
