{
  "type": "Feature",
  "properties": {
    "iso:country":"GB",
    "wof:name":"SW12 0BD",
    "wof:placetype":"postalcode"
},
  "geometry": {"coordinates":[-0.13142331024803,51.44690099275565],"type":"Point"}
}