{
  "type": "Feature",
  "properties": {
    "date:inception_lower": "2006-08-01",
    "date:inception_upper": "2006-08-01",
    "iso:country": "GB",
    "wof:name": "BS3 3NW",
    "wof:placetype": "postalcode"
  },
  "geometry": {"coordinates":[-2.601504,51.439239],"type":"Point"}
}
