{
  "type": "Feature",
  "properties": {
    "iso:country":"GB",
    "wof:name":"BS3 3NW",
    "wof:placetype":"postalcode"
},
  "geometry": {"coordinates":[-2.60150419039628,51.43923941537361],"type":"Point"}
}