{
  "type": "Feature",
  "properties": {
    "date:inception_lower": "1980-01-01",
    "date:inception_upper": "1980-01-01",
    "iso:country": "GB",
    "wof:name": "PH2 7EQ",
    "wof:placetype": "postalcode"
  },
  "geometry": {"coordinates":[-3.419479,56.402488],"type":"Point"}
}
