{
  "type": "Feature",
  "properties": {
    "date:inception_lower": "1980-01-01",
    "date:inception_upper": "1980-01-01",
    "iso:country": "GB",
    "wof:name": "TS16 0LB",
    "wof:placetype": "postalcode"
  },
  "geometry": {"coordinates":[-1.359729,54.515573],"type":"Point"}
}
