{
  "type": "Feature",
  "properties": {
    "iso:country":"GB",
    "wof:name":"TS16 0LB",
    "wof:placetype":"postalcode"
},
  "geometry": {"coordinates":[-1.35972863902181,54.51557290206227],"type":"Point"}
}