{
  "type": "Feature",
  "properties": {
    "iso:country":"GB",
    "wof:name":"NG5 5JB",
    "wof:placetype":"postalcode"
},
  "geometry": {"coordinates":[-1.16761272562749,52.99083123021052],"type":"Point"}
}