{
  "type": "Feature",
  "properties": {
    "iso:country":"GB",
    "wof:name":"LN4 2FD",
    "wof:placetype":"postalcode"
},
  "geometry": {"coordinates":[-0.42306373759367,53.18645293978761],"type":"Point"}
}