{
  "type": "Feature",
  "properties": {
    "iso:country": "GB",
    "wof:name": "LN4 2FD",
    "wof:placetype": "postalcode"
  },
  "geometry": {"coordinates":[-0.423064,53.186453],"type":"Point"}
}
