{
  "type": "Feature",
  "properties": {
    "iso:country":"GB",
    "wof:name":"TS5 8PS",
    "wof:placetype":"postalcode"
},
  "geometry": {"coordinates":[-1.2611715118394,54.54238587472069],"type":"Point"}
}