{
  "type": "Feature",
  "properties": {
    "iso:country": "GB",
    "wof:name": "HR6 8AW",
    "wof:placetype": "postalcode"
  },
  "geometry": {"coordinates":[-2.732992,52.225763],"type":"Point"}
}
