{
  "type": "Feature",
  "properties": {
    "iso:country":"GB",
    "wof:name":"SG1 5RB",
    "wof:placetype":"postalcode"
},
  "geometry": {"coordinates":[-0.17956091916263,51.91829359105353],"type":"Point"}
}