{
  "type": "Feature",
  "properties": {
    "iso:country": "GB",
    "wof:name": "SK15 3JX",
    "wof:placetype": "postalcode"
  },
  "geometry": {"coordinates":[-2.027459,53.500213],"type":"Point"}
}
