{
  "type": "Feature",
  "properties": {
    "iso:country": "GB",
    "wof:name": "NE16 4BS",
    "wof:placetype": "postalcode"
  },
  "geometry": {"coordinates":[-1.677144,54.947932],"type":"Point"}
}
