{
  "type": "Feature",
  "properties": {
    "iso:country":"GB",
    "wof:name":"NE16 4BS",
    "wof:placetype":"postalcode"
},
  "geometry": {"coordinates":[-1.67714366704223,54.94793231011434],"type":"Point"}
}