{
  "type": "Feature",
  "properties": {
    "date:inception_lower": "1980-01-01",
    "date:inception_upper": "1980-01-01",
    "iso:country": "GB",
    "wof:name": "NG4 3LE",
    "wof:placetype": "postalcode"
  },
  "geometry": {"coordinates":[-1.083034,52.974873],"type":"Point"}
}
