{
  "type": "Feature",
  "properties": {
    "iso:country": "GB",
    "wof:name": "WA10 4NB",
    "wof:placetype": "postalcode"
  },
  "geometry": {"coordinates":[-2.755431,53.456093],"type":"Point"}
}
