{
  "type": "Feature",
  "properties": {
    "date:inception_lower": "1980-01-01",
    "date:inception_upper": "1980-01-01",
    "iso:country": "GB",
    "wof:name": "WD3 5HN",
    "wof:placetype": "postalcode"
  },
  "geometry": {"coordinates":[-0.524234,51.646202],"type":"Point"}
}
