{
  "type": "Feature",
  "properties": {
    "iso:country":"GB",
    "wof:name":"WD3 5HN",
    "wof:placetype":"postalcode"
},
  "geometry": {"coordinates":[-0.52423365763974,51.64620168791501],"type":"Point"}
}