{
  "type": "Feature",
  "properties": {
    "date:inception_lower": "1990-07-01",
    "date:inception_upper": "1990-07-01",
    "iso:country": "GB",
    "wof:name": "RH2 9EZ",
    "wof:placetype": "postalcode"
  },
  "geometry": {"coordinates":[-0.21435,51.243197],"type":"Point"}
}
