{
  "type": "Feature",
  "properties": {
    "iso:country":"GB",
    "wof:name":"B94 5NN",
    "wof:placetype":"postalcode"
},
  "geometry": {"coordinates":[-1.77388668273794,52.3380989236727],"type":"Point"}
}