{
  "type": "Feature",
  "properties": {
    "iso:country":"GB",
    "wof:name":"BS21 7TR",
    "wof:placetype":"postalcode"
},
  "geometry": {"coordinates":[-2.86949735570421,51.43398774921818],"type":"Point"}
}