{
  "type": "Feature",
  "properties": {
    "date:inception_lower": "1980-01-01",
    "date:inception_upper": "1980-01-01",
    "iso:country": "GB",
    "wof:name": "BS21 7TR",
    "wof:placetype": "postalcode"
  },
  "geometry": {"coordinates":[-2.869497,51.433988],"type":"Point"}
}
