{
  "type": "Feature",
  "properties": {
    "iso:country": "GB",
    "wof:name": "BS21 7TR",
    "wof:placetype": "postalcode"
  },
  "geometry": {"coordinates":[-2.869497,51.433988],"type":"Point"}
}
