{
  "type": "Feature",
  "properties": {
    "iso:country":"GB",
    "wof:name":"OX26 3ZJ",
    "wof:placetype":"postalcode"
},
  "geometry": {"coordinates":[-1.16310862283613,51.9125003588867],"type":"Point"}
}