{
  "type": "Feature",
  "properties": {
    "date:inception_lower":"2000-10-01",
    "date:inception_upper":"2000-10-31",
    "iso:country":"GB",
    "wof:name":"OX26 3ZJ",
    "wof:placetype":"postalcode"
},
  "geometry": {"coordinates":[-1.163109,51.9125],"type":"Point"}
}