{
  "type": "Feature",
  "properties": {
    "date:inception_lower": "1980-01-01",
    "date:inception_upper": "1980-01-01",
    "iso:country": "GB",
    "wof:name": "HP14 3ED",
    "wof:placetype": "postalcode"
  },
  "geometry": {"coordinates":[-0.829444,51.623196],"type":"Point"}
}
