{
  "type": "Feature",
  "properties": {
    "iso:country":"GB",
    "wof:name":"HP14 3ED",
    "wof:placetype":"postalcode"
},
  "geometry": {"coordinates":[-0.82944433314669,51.6231956868443],"type":"Point"}
}