{
  "type": "Feature",
  "properties": {
    "iso:country":"GB",
    "wof:name":"AB42 0RT",
    "wof:placetype":"postalcode"
},
  "geometry": {"coordinates":[-1.89881135607426,57.43113309579229],"type":"Point"}
}