{
  "type": "Feature",
  "properties": {
    "iso:country":"GB",
    "wof:name":"TA5 1RW",
    "wof:placetype":"postalcode"
},
  "geometry": {"coordinates":[-3.14445965212504,51.18165229028963],"type":"Point"}
}