{
  "type": "Feature",
  "properties": {
    "date:inception_lower": "1980-01-01",
    "date:inception_upper": "1980-01-01",
    "iso:country": "GB",
    "wof:name": "TA5 1RW",
    "wof:placetype": "postalcode"
  },
  "geometry": {"coordinates":[-3.14446,51.181652],"type":"Point"}
}
