{
  "type": "Feature",
  "properties": {
    "iso:country": "GB",
    "wof:name": "PE29 3QB",
    "wof:placetype": "postalcode"
  },
  "geometry": {"coordinates":[-0.180064,52.329344],"type":"Point"}
}
