{
  "type": "Feature",
  "properties": {
    "date:inception_lower": "2006-04-01",
    "date:inception_upper": "2006-04-01",
    "iso:country": "GB",
    "wof:name": "PE29 3QB",
    "wof:placetype": "postalcode"
  },
  "geometry": {"coordinates":[-0.180015,52.329331],"type":"Point"}
}
