{
  "type": "Feature",
  "properties": {
    "iso:country":"GB",
    "wof:name":"OX4 6RD",
    "wof:placetype":"postalcode"
},
  "geometry": {"coordinates":[-1.19472961881665,51.71952728737708],"type":"Point"}
}