{
  "type": "Feature",
  "properties": {
    "date:inception_lower": "2000-06-01",
    "date:inception_upper": "2000-06-01",
    "iso:country": "GB",
    "wof:name": "OX4 6RD",
    "wof:placetype": "postalcode"
  },
  "geometry": {"coordinates":[-1.19473,51.719527],"type":"Point"}
}
