{
  "type": "Feature",
  "properties": {
    "iso:country": "GB",
    "wof:name": "CT19 6JU",
    "wof:placetype": "postalcode"
  },
  "geometry": {"coordinates":[1.183961,51.094698],"type":"Point"}
}
