{
  "type": "Feature",
  "properties": {
    "iso:country":"GB",
    "wof:name":"CT19 6JU",
    "wof:placetype":"postalcode"
},
  "geometry": {"coordinates":[1.18396080387942,51.09469830061339],"type":"Point"}
}