{
  "type": "Feature",
  "properties": {
    "iso:country":"GB",
    "wof:name":"ME9 0AU",
    "wof:placetype":"postalcode"
},
  "geometry": {"coordinates":[0.77517193200865,51.2862125647892],"type":"Point"}
}