{
  "type": "Feature",
  "properties": {
    "iso:country": "GB",
    "wof:name": "ME9 0AU",
    "wof:placetype": "postalcode"
  },
  "geometry": {"coordinates":[0.775172,51.286213],"type":"Point"}
}
