{
  "type": "Feature",
  "properties": {
    "date:inception_lower": "2019-06-01",
    "date:inception_upper": "2019-06-01",
    "iso:country": "GB",
    "wof:name": "CB21 4AN",
    "wof:placetype": "postalcode"
  },
  "geometry": {"coordinates":[0.318591,52.130553],"type":"Point"}
}
