{
  "type": "Feature",
  "properties": {
    "date:inception_lower": "1980-01-01",
    "date:inception_upper": "1980-01-01",
    "iso:country": "GB",
    "wof:name": "S75 1LP",
    "wof:placetype": "postalcode"
  },
  "geometry": {"coordinates":[-1.526877,53.571395],"type":"Point"}
}
