{
  "type": "Feature",
  "properties": {
    "iso:country":"GB",
    "wof:name":"DL15 0GQ",
    "wof:placetype":"postalcode"
},
  "geometry": {"coordinates":[-1.67849754207603,54.71123266041338],"type":"Point"}
}