{
  "type": "Feature",
  "properties": {
    "date:inception_lower":"2014-09-01",
    "date:inception_upper":"2014-09-30",
    "iso:country":"GB",
    "wof:name":"M12 4TH",
    "wof:placetype":"postalcode"
},
  "geometry": {"coordinates":[-2.191783,53.461169],"type":"Point"}
}