{
  "type": "Feature",
  "properties": {
    "iso:country": "GB",
    "wof:name": "M12 4TH",
    "wof:placetype": "postalcode"
  },
  "geometry": {"coordinates":[-2.191783,53.461169],"type":"Point"}
}
