{
  "type": "Feature",
  "properties": {
    "iso:country":"GB",
    "wof:name":"M12 4TH",
    "wof:placetype":"postalcode"
},
  "geometry": {"coordinates":[-2.19178282353487,53.46116893149933],"type":"Point"}
}