{
  "type": "Feature",
  "properties": {
    "date:inception_lower": "1980-01-01",
    "date:inception_upper": "1980-01-01",
    "iso:country": "GB",
    "wof:name": "LA23 1PB",
    "wof:placetype": "postalcode"
  },
  "geometry": {"coordinates":[-2.905148,54.417308],"type":"Point"}
}
