{
  "type": "Feature",
  "properties": {
    "iso:country":"GB",
    "wof:name":"LA23 1PB",
    "wof:placetype":"postalcode"
},
  "geometry": {"coordinates":[-2.90525188700903,54.41725371896928],"type":"Point"}
}