{
  "type": "Feature",
  "properties": {
    "iso:country": "GB",
    "wof:name": "LA23 1PB",
    "wof:placetype": "postalcode"
  },
  "geometry": {"coordinates":[-2.905148,54.417308],"type":"Point"}
}
