{
  "type": "Feature",
  "properties": {
    "iso:country":"GB",
    "wof:name":"PA34 4JF",
    "wof:placetype":"postalcode"
},
  "geometry": {"coordinates":[-5.46998139907311,56.40597867943468],"type":"Point"}
}