{
  "type": "Feature",
  "properties": {
    "iso:country": "GB",
    "wof:name": "SR5 5NE",
    "wof:placetype": "postalcode"
  },
  "geometry": {"coordinates":[-1.428905,54.927322],"type":"Point"}
}
