{
  "type": "Feature",
  "properties": {
    "date:inception_lower": "1980-01-01",
    "date:inception_upper": "1980-01-01",
    "iso:country": "GB",
    "wof:name": "LS29 0DS",
    "wof:placetype": "postalcode"
  },
  "geometry": {"coordinates":[-1.815223,53.937964],"type":"Point"}
}
