{
  "type": "Feature",
  "properties": {
    "date:inception_lower":"1998-06-01",
    "date:inception_upper":"1998-06-30",
    "iso:country":"GB",
    "wof:name":"LE10 3QQ",
    "wof:placetype":"postalcode"
},
  "geometry": {"coordinates":[-1.394947,52.531035],"type":"Point"}
}