{
  "type": "Feature",
  "properties": {
    "iso:country": "GB",
    "wof:name": "PR4 1JH",
    "wof:placetype": "postalcode"
  },
  "geometry": {"coordinates":[-2.8684,53.76854],"type":"Point"}
}
