{
  "type": "Feature",
  "properties": {
    "iso:country":"GB",
    "wof:name":"PR4 1JH",
    "wof:placetype":"postalcode"
},
  "geometry": {"coordinates":[-2.86839988484006,53.76853993878029],"type":"Point"}
}