{
  "type": "Feature",
  "properties": {
    "iso:country":"GB",
    "wof:name":"N13 5RX",
    "wof:placetype":"postalcode"
},
  "geometry": {"coordinates":[-0.09877831883671,51.62524636964883],"type":"Point"}
}