{
  "type": "Feature",
  "properties": {
    "iso:country": "GB",
    "wof:name": "N13 5RX",
    "wof:placetype": "postalcode"
  },
  "geometry": {"coordinates":[-0.098778,51.625246],"type":"Point"}
}
