{
  "type": "Feature",
  "properties": {
    "iso:country":"GB",
    "wof:name":"OL9 6QB",
    "wof:placetype":"postalcode"
},
  "geometry": {"coordinates":[-2.12876315205446,53.54463006605825],"type":"Point"}
}