{
  "type": "Feature",
  "properties": {
    "date:inception_lower": "1980-01-01",
    "date:inception_upper": "1980-01-01",
    "iso:country": "GB",
    "wof:name": "TR15 3YG",
    "wof:placetype": "postalcode"
  },
  "geometry": {"coordinates":[-5.260992,50.214648],"type":"Point"}
}
