{
  "type": "Feature",
  "properties": {
    "iso:country":"GB",
    "wof:name":"NW7 1FE",
    "wof:placetype":"postalcode"
},
  "geometry": {"coordinates":[-0.21271442869094,51.61192920272702],"type":"Point"}
}