{
  "type": "Feature",
  "properties": {
    "iso:country": "GB",
    "wof:name": "NW7 1FE",
    "wof:placetype": "postalcode"
  },
  "geometry": {"coordinates":[-0.212714,51.611929],"type":"Point"}
}
