{
  "type": "Feature",
  "properties": {
    "date:inception_lower":"2015-08-01",
    "date:inception_upper":"2015-08-31",
    "iso:country":"GB",
    "wof:name":"NW7 1FE",
    "wof:placetype":"postalcode"
},
  "geometry": {"coordinates":[-0.212714,51.611929],"type":"Point"}
}