{
  "type": "Feature",
  "properties": {
    "date:inception_lower": "1980-01-01",
    "date:inception_upper": "1980-01-01",
    "iso:country": "GB",
    "wof:name": "CO5 9QF",
    "wof:placetype": "postalcode"
  },
  "geometry": {"coordinates":[0.716342,51.848959],"type":"Point"}
}
