{
  "type": "Feature",
  "properties": {
    "iso:country":"GB",
    "wof:name":"CO5 9QF",
    "wof:placetype":"postalcode"
},
  "geometry": {"coordinates":[0.71634150384159,51.84895860804774],"type":"Point"}
}