{
  "type": "Feature",
  "properties": {
    "date:inception_lower": "1980-01-01",
    "date:inception_upper": "1980-01-01",
    "iso:country": "GB",
    "wof:name": "IP13 6SH",
    "wof:placetype": "postalcode"
  },
  "geometry": {"coordinates":[1.245712,52.137853],"type":"Point"}
}
