{
  "type": "Feature",
  "properties": {
    "date:inception_lower":"1980-01-01",
    "date:inception_upper":"1980-01-31",
    "iso:country":"GB",
    "wof:name":"BA1 3HG",
    "wof:placetype":"postalcode"
},
  "geometry": {"coordinates":[-2.393021,51.384043],"type":"Point"}
}