{
  "type": "Feature",
  "properties": {
    "iso:country":"GB",
    "wof:name":"M33 4RX",
    "wof:placetype":"postalcode"
},
  "geometry": {"coordinates":[-2.33806612898038,53.41466114142415],"type":"Point"}
}