{
  "type": "Feature",
  "properties": {
    "date:inception_lower": "1980-01-01",
    "date:inception_upper": "1980-01-01",
    "iso:country": "GB",
    "wof:name": "TN13 1HD",
    "wof:placetype": "postalcode"
  },
  "geometry": {"coordinates":[0.185009,51.275327],"type":"Point"}
}
