{
  "type": "Feature",
  "properties": {
    "iso:country":"GB",
    "wof:name":"TN13 1HD",
    "wof:placetype":"postalcode"
},
  "geometry": {"coordinates":[0.18500854724462,51.27532653401149],"type":"Point"}
}