{
  "type": "Feature",
  "properties": {
    "iso:country": "GB",
    "wof:name": "TN13 1HD",
    "wof:placetype": "postalcode"
  },
  "geometry": {"coordinates":[0.185009,51.275327],"type":"Point"}
}
