{
  "type": "Feature",
  "properties": {
    "iso:country":"GB",
    "wof:name":"G14 0PY",
    "wof:placetype":"postalcode"
},
  "geometry": {"coordinates":[-4.3817597085665,55.88970677197379],"type":"Point"}
}