{
  "type": "Feature",
  "properties": {
    "iso:country": "GB",
    "wof:name": "SK17 9HJ",
    "wof:placetype": "postalcode"
  },
  "geometry": {"coordinates":[-1.908879,53.251917],"type":"Point"}
}
