{
  "type": "Feature",
  "properties": {
    "date:inception_lower": "1980-01-01",
    "date:inception_upper": "1980-01-01",
    "iso:country": "GB",
    "wof:name": "SK17 9HJ",
    "wof:placetype": "postalcode"
  },
  "geometry": {"coordinates":[-1.908879,53.251917],"type":"Point"}
}
