{
  "type": "Feature",
  "properties": {
    "iso:country": "GB",
    "wof:name": "HU14 3EP",
    "wof:placetype": "postalcode"
  },
  "geometry": {"coordinates":[-0.508364,53.722634],"type":"Point"}
}
