{
  "type": "Feature",
  "properties": {
    "iso:country": "GB",
    "wof:name": "EN11 8FE",
    "wof:placetype": "postalcode"
  },
  "geometry": {"coordinates":[-0.01305,51.76026],"type":"Point"}
}
