{
  "type": "Feature",
  "properties": {
    "iso:country":"GB",
    "wof:name":"EN11 8FE",
    "wof:placetype":"postalcode"
},
  "geometry": {"coordinates":[-0.01305043018882,51.76025957594983],"type":"Point"}
}