{
  "type": "Feature",
  "properties": {
    "iso:country": "GB",
    "wof:name": "BA15 1BP",
    "wof:placetype": "postalcode"
  },
  "geometry": {"coordinates":[-2.253473,51.347586],"type":"Point"}
}
