{
  "type": "Feature",
  "properties": {
    "iso:country":"GB",
    "wof:name":"BA15 1BP",
    "wof:placetype":"postalcode"
},
  "geometry": {"coordinates":[-2.25347566866693,51.34758952955481],"type":"Point"}
}