{
  "type": "Feature",
  "properties": {
    "iso:country":"GB",
    "wof:name":"PE30 2AY",
    "wof:placetype":"postalcode"
},
  "geometry": {"coordinates":[0.39954415349057,52.75976503734412],"type":"Point"}
}