{
  "type": "Feature",
  "properties": {
    "iso:country": "GB",
    "wof:name": "PE30 2AY",
    "wof:placetype": "postalcode"
  },
  "geometry": {"coordinates":[0.399544,52.759765],"type":"Point"}
}
