{
  "type": "Feature",
  "properties": {
    "date:inception_lower": "1987-04-01",
    "date:inception_upper": "1987-04-01",
    "iso:country": "GB",
    "wof:name": "DL1 3RZ",
    "wof:placetype": "postalcode"
  },
  "geometry": {"coordinates":[-1.515815,54.54733],"type":"Point"}
}
