{
  "type": "Feature",
  "properties": {
    "iso:country":"GB",
    "wof:name":"DL1 3RZ",
    "wof:placetype":"postalcode"
},
  "geometry": {"coordinates":[-1.51581504318309,54.54733014767886],"type":"Point"}
}