{
  "type": "Feature",
  "properties": {
    "iso:country": "GB",
    "wof:name": "S6 1LE",
    "wof:placetype": "postalcode"
  },
  "geometry": {"coordinates":[-1.501133,53.419547],"type":"Point"}
}
