{
  "type": "Feature",
  "properties": {
    "iso:country": "GB",
    "wof:name": "BH18 8EL",
    "wof:placetype": "postalcode"
  },
  "geometry": {"coordinates":[-1.990684,50.757384],"type":"Point"}
}
