{
  "type": "Feature",
  "properties": {
    "date:inception_lower": "2019-06-01",
    "date:inception_upper": "2019-06-01",
    "iso:country": "GB",
    "wof:name": "BH18 8EL",
    "wof:placetype": "postalcode"
  },
  "geometry": {"coordinates":[-1.990684,50.757384],"type":"Point"}
}
