{
  "type": "Feature",
  "properties": {
    "iso:country": "GB",
    "wof:name": "SY10 9QA",
    "wof:placetype": "postalcode"
  },
  "geometry": {"coordinates":[-3.071882,52.801338],"type":"Point"}
}
