{
  "type": "Feature",
  "properties": {
    "iso:country":"GB",
    "wof:name":"SY10 9QA",
    "wof:placetype":"postalcode"
},
  "geometry": {"coordinates":[-3.0718821219003,52.80133795470262],"type":"Point"}
}