{
  "type": "Feature",
  "properties": {
    "iso:country":"GB",
    "wof:name":"TW10 7HW",
    "wof:placetype":"postalcode"
},
  "geometry": {"coordinates":[-0.31360982750471,51.43839585869445],"type":"Point"}
}