{
  "type": "Feature",
  "properties": {
    "date:inception_lower":"1980-01-01",
    "date:inception_upper":"1980-01-31",
    "iso:country":"GB",
    "wof:name":"TW10 7HW",
    "wof:placetype":"postalcode"
},
  "geometry": {"coordinates":[-0.31361,51.438396],"type":"Point"}
}