{
  "type": "Feature",
  "properties": {
    "date:inception_lower": "2023-04-01",
    "date:inception_upper": "2023-04-01",
    "iso:country": "GB",
    "wof:name": "EH32 9SY",
    "wof:placetype": "postalcode"
  },
  "geometry": {"coordinates":[-2.989508,55.950666],"type":"Point"}
}
