{
  "type": "Feature",
  "properties": {
    "iso:country":"GB",
    "wof:name":"PE15 0QW",
    "wof:placetype":"postalcode"
},
  "geometry": {"coordinates":[0.09969500352277,52.52341637662737],"type":"Point"}
}