{
  "type": "Feature",
  "properties": {
    "date:inception_lower": "1980-01-01",
    "date:inception_upper": "1980-01-01",
    "iso:country": "GB",
    "wof:name": "SK1 1DH",
    "wof:placetype": "postalcode"
  },
  "geometry": {"coordinates":[-2.15943,53.409073],"type":"Point"}
}
