{
  "type": "Feature",
  "properties": {
    "iso:country":"GB",
    "wof:name":"OL7 9NH",
    "wof:placetype":"postalcode"
},
  "geometry": {"coordinates":[-2.10739012107486,53.50132724510846],"type":"Point"}
}