{
  "type": "Feature",
  "properties": {
    "date:inception_lower": "1980-01-01",
    "date:inception_upper": "1980-01-01",
    "iso:country": "GB",
    "wof:name": "DL12 0XU",
    "wof:placetype": "postalcode"
  },
  "geometry": {"coordinates":[-2.257979,54.686767],"type":"Point"}
}
