{
  "type": "Feature",
  "properties": {
    "iso:country":"GB",
    "wof:name":"DL12 0XU",
    "wof:placetype":"postalcode"
},
  "geometry": {"coordinates":[-2.25262687694851,54.68265525224686],"type":"Point"}
}