{
  "type": "Feature",
  "properties": {
    "iso:country": "GB",
    "wof:name": "DL12 0XU",
    "wof:placetype": "postalcode"
  },
  "geometry": {"coordinates":[-2.252633,54.682663],"type":"Point"}
}
