{
  "type": "Feature",
  "properties": {
    "date:inception_lower": "2019-07-01",
    "date:inception_upper": "2019-07-01",
    "iso:country": "GB",
    "wof:name": "BB5 4BF",
    "wof:placetype": "postalcode"
  },
  "geometry": {"coordinates":[-2.392792,53.757414],"type":"Point"}
}
