{
  "type": "Feature",
  "properties": {
    "date:inception_lower": "1980-01-01",
    "date:inception_upper": "1980-01-01",
    "iso:country": "GB",
    "wof:name": "SW8 1EF",
    "wof:placetype": "postalcode"
  },
  "geometry": {"coordinates":[-0.122523,51.480031],"type":"Point"}
}
