{
  "type": "Feature",
  "properties": {
    "iso:country":"GB",
    "wof:name":"SW8 1EF",
    "wof:placetype":"postalcode"
},
  "geometry": {"coordinates":[-0.12257843769604,51.48008623067383],"type":"Point"}
}