{
  "type": "Feature",
  "properties": {
    "iso:country":"GB",
    "wof:name":"ST5 7DN",
    "wof:placetype":"postalcode"
},
  "geometry": {"coordinates":[-2.2567186615789,53.04701362281893],"type":"Point"}
}