{
  "type": "Feature",
  "properties": {
    "iso:country": "GB",
    "wof:name": "OX17 3NY",
    "wof:placetype": "postalcode"
  },
  "geometry": {"coordinates":[-1.281759,52.005883],"type":"Point"}
}
