{
  "type": "Feature",
  "properties": {
    "iso:country":"GB",
    "wof:name":"PL4 8PL",
    "wof:placetype":"postalcode"
},
  "geometry": {"coordinates":[-4.12894915752108,50.37570615566971],"type":"Point"}
}