{
  "type": "Feature",
  "properties": {
    "date:inception_lower": "2000-06-01",
    "date:inception_upper": "2000-06-01",
    "iso:country": "GB",
    "wof:name": "BS16 7EL",
    "wof:placetype": "postalcode"
  },
  "geometry": {"coordinates":[-2.472909,51.489065],"type":"Point"}
}
