{
  "type": "Feature",
  "properties": {
    "iso:country":"GB",
    "wof:name":"BS16 7EL",
    "wof:placetype":"postalcode"
},
  "geometry": {"coordinates":[-2.47306688420644,51.48903926632975],"type":"Point"}
}