{
  "type": "Feature",
  "properties": {
    "iso:country":"GB",
    "wof:name":"IP12 4AZ",
    "wof:placetype":"postalcode"
},
  "geometry": {"coordinates":[1.31206905488555,52.09014668904003],"type":"Point"}
}