{
  "type": "Feature",
  "properties": {
    "iso:country":"GB",
    "wof:name":"L39 4QU",
    "wof:placetype":"postalcode"
},
  "geometry": {"coordinates":[-2.87287828386185,53.56367828012069],"type":"Point"}
}