{
  "type": "Feature",
  "properties": {
    "iso:country": "GB",
    "wof:name": "L39 4QU",
    "wof:placetype": "postalcode"
  },
  "geometry": {"coordinates":[-2.872878,53.563678],"type":"Point"}
}
