{
  "type": "Feature",
  "properties": {
    "iso:country":"GB",
    "wof:name":"ML6 9TD",
    "wof:placetype":"postalcode"
},
  "geometry": {"coordinates":[-3.96888648342687,55.84545600764826],"type":"Point"}
}