{
  "type": "Feature",
  "properties": {
    "date:inception_lower": "1980-01-01",
    "date:inception_upper": "1980-01-01",
    "iso:country": "GB",
    "wof:name": "EX39 4PD",
    "wof:placetype": "postalcode"
  },
  "geometry": {"coordinates":[-4.135552,51.028181],"type":"Point"}
}
