{
  "type": "Feature",
  "properties": {
    "iso:country": "GB",
    "wof:name": "EX39 4PD",
    "wof:placetype": "postalcode"
  },
  "geometry": {"coordinates":[-4.135553,51.028131],"type":"Point"}
}
