{
  "type": "Feature",
  "properties": {
    "iso:country": "GB",
    "wof:name": "NG8 1NE",
    "wof:placetype": "postalcode"
  },
  "geometry": {"coordinates":[-1.201579,52.959349],"type":"Point"}
}
