{
  "type": "Feature",
  "properties": {
    "iso:country":"GB",
    "wof:name":"NG8 1NE",
    "wof:placetype":"postalcode"
},
  "geometry": {"coordinates":[-1.20157863452748,52.95934934024806],"type":"Point"}
}