{
  "type": "Feature",
  "properties": {
    "iso:country":"GB",
    "wof:name":"WA16 8TB",
    "wof:placetype":"postalcode"
},
  "geometry": {"coordinates":[-2.3107765051053,53.27871869106481],"type":"Point"}
}