{
  "type": "Feature",
  "properties": {
    "iso:country": "GB",
    "wof:name": "IP22 2HX",
    "wof:placetype": "postalcode"
  },
  "geometry": {"coordinates":[1.013835,52.381493],"type":"Point"}
}
