{
  "type": "Feature",
  "properties": {
    "date:inception_lower":"1991-09-01",
    "date:inception_upper":"1991-09-30",
    "iso:country":"GB",
    "wof:name":"IP22 2HX",
    "wof:placetype":"postalcode"
},
  "geometry": {"coordinates":[1.013835,52.381493],"type":"Point"}
}