{
  "type": "Feature",
  "properties": {
    "iso:country":"GB",
    "wof:name":"IP22 2HX",
    "wof:placetype":"postalcode"
},
  "geometry": {"coordinates":[1.01383482296687,52.38149327518025],"type":"Point"}
}