{
  "type": "Feature",
  "properties": {
    "iso:country": "GB",
    "wof:name": "S11 8RD",
    "wof:placetype": "postalcode"
  },
  "geometry": {"coordinates":[-1.494769,53.369857],"type":"Point"}
}
