{
  "type": "Feature",
  "properties": {
    "iso:country":"GB",
    "wof:name":"B90 4XL",
    "wof:placetype":"postalcode"
},
  "geometry": {"coordinates":[-1.79430540863112,52.38809445870917],"type":"Point"}
}