{
  "type": "Feature",
  "properties": {
    "iso:country": "GB",
    "wof:name": "S18 2GL",
    "wof:placetype": "postalcode"
  },
  "geometry": {"coordinates":[-1.469922,53.304734],"type":"Point"}
}
