{
  "type": "Feature",
  "properties": {
    "iso:country":"GB",
    "wof:name":"S18 2GL",
    "wof:placetype":"postalcode"
},
  "geometry": {"coordinates":[-1.46989273251124,53.30469806875697],"type":"Point"}
}