{
  "type": "Feature",
  "properties": {
    "iso:country":"GB",
    "wof:name":"LS14 1EY",
    "wof:placetype":"postalcode"
},
  "geometry": {"coordinates":[-1.46200243132362,53.82465207512834],"type":"Point"}
}