{
  "type": "Feature",
  "properties": {
    "iso:country":"GB",
    "wof:name":"LL12 8XN",
    "wof:placetype":"postalcode"
},
  "geometry": {"coordinates":[-2.96149995292309,53.08675060033983],"type":"Point"}
}