{
  "type": "Feature",
  "properties": {
    "iso:country": "GB",
    "wof:name": "LL12 8XN",
    "wof:placetype": "postalcode"
  },
  "geometry": {"coordinates":[-2.9615,53.086751],"type":"Point"}
}
