{
  "type": "Feature",
  "properties": {
    "iso:country":"GB",
    "wof:name":"FK10 4RZ",
    "wof:placetype":"postalcode"
},
  "geometry": {"coordinates":[-3.71124744586679,56.07053310838363],"type":"Point"}
}