{
  "type": "Feature",
  "properties": {
    "iso:country": "GB",
    "wof:name": "RH17 5PA",
    "wof:placetype": "postalcode"
  },
  "geometry": {"coordinates":[-0.186747,50.976957],"type":"Point"}
}
