{
  "type": "Feature",
  "properties": {
    "iso:country":"GB",
    "wof:name":"RH17 5PA",
    "wof:placetype":"postalcode"
},
  "geometry": {"coordinates":[-0.18674719368129,50.97695691933945],"type":"Point"}
}