{
  "type": "Feature",
  "properties": {
    "date:inception_lower": "1980-01-01",
    "date:inception_upper": "1980-01-01",
    "iso:country": "GB",
    "wof:name": "RH17 5PA",
    "wof:placetype": "postalcode"
  },
  "geometry": {"coordinates":[-0.186624,50.978687],"type":"Point"}
}
