{
  "type": "Feature",
  "properties": {
    "date:inception_lower": "1980-01-01",
    "date:inception_upper": "1980-01-01",
    "iso:country": "GB",
    "wof:name": "N9 9DW",
    "wof:placetype": "postalcode"
  },
  "geometry": {"coordinates":[-0.06197,51.626506],"type":"Point"}
}
