{
  "type": "Feature",
  "properties": {
    "iso:country":"GB",
    "wof:name":"ME14 4PN",
    "wof:placetype":"postalcode"
},
  "geometry": {"coordinates":[0.55229119590605,51.27073496162446],"type":"Point"}
}