{
  "type": "Feature",
  "properties": {
    "date:inception_lower":"2001-12-01",
    "date:inception_upper":"2001-12-31",
    "iso:country":"GB",
    "wof:name":"ME14 4PN",
    "wof:placetype":"postalcode"
},
  "geometry": {"coordinates":[0.552291,51.270735],"type":"Point"}
}