{
  "type": "Feature",
  "properties": {
    "iso:country": "GB",
    "wof:name": "ME14 4PN",
    "wof:placetype": "postalcode"
  },
  "geometry": {"coordinates":[0.552291,51.270735],"type":"Point"}
}
