{
  "type": "Feature",
  "properties": {
    "date:inception_lower":"1980-01-01",
    "date:inception_upper":"1980-01-31",
    "iso:country":"GB",
    "wof:name":"S70 2JP",
    "wof:placetype":"postalcode"
},
  "geometry": {"coordinates":[-1.478697,53.553668],"type":"Point"}
}