{
  "type": "Feature",
  "properties": {
    "iso:country":"GB",
    "wof:name":"S70 2JP",
    "wof:placetype":"postalcode"
},
  "geometry": {"coordinates":[-1.47869702459349,53.55366769336064],"type":"Point"}
}