{
  "type": "Feature",
  "properties": {
    "iso:country":"GB",
    "wof:name":"NE34 9FB",
    "wof:placetype":"postalcode"
},
  "geometry": {"coordinates":[-1.45363652073707,54.96890784285071],"type":"Point"}
}