{
  "type": "Feature",
  "properties": {
    "date:inception_lower": "2006-10-01",
    "date:inception_upper": "2006-10-01",
    "iso:country": "GB",
    "wof:name": "NE34 9FB",
    "wof:placetype": "postalcode"
  },
  "geometry": {"coordinates":[-1.453636,54.968908],"type":"Point"}
}
