{
  "type": "Feature",
  "properties": {
    "iso:country":"GB",
    "wof:name":"L31 0AP",
    "wof:placetype":"postalcode"
},
  "geometry": {"coordinates":[-2.9418088604794,53.5170881624716],"type":"Point"}
}