{
  "type": "Feature",
  "properties": {
    "iso:country": "GB",
    "wof:name": "DH7 9BE",
    "wof:placetype": "postalcode"
  },
  "geometry": {"coordinates":[-1.707534,54.767175],"type":"Point"}
}
