{
  "type": "Feature",
  "properties": {
    "iso:country":"GB",
    "wof:name":"DH7 9BE",
    "wof:placetype":"postalcode"
},
  "geometry": {"coordinates":[-1.70780007752816,54.76755377597836],"type":"Point"}
}