{
  "type": "Feature",
  "properties": {
    "iso:country":"GB",
    "wof:name":"EC1N 2JS",
    "wof:placetype":"postalcode"
},
  "geometry": {"coordinates":[-0.10991498887996,51.51780442015153],"type":"Point"}
}