{
  "type": "Feature",
  "properties": {
    "date:inception_lower": "2012-09-01",
    "date:inception_upper": "2012-09-01",
    "iso:country": "GB",
    "wof:name": "CM1 2WU",
    "wof:placetype": "postalcode"
  },
  "geometry": {"coordinates":[0.460793,51.740077],"type":"Point"}
}
