{
  "type": "Feature",
  "properties": {
    "iso:country":"GB",
    "wof:name":"CM1 2WU",
    "wof:placetype":"postalcode"
},
  "geometry": {"coordinates":[0.46079266193451,51.74007743285203],"type":"Point"}
}