{
  "type": "Feature",
  "properties": {
    "date:inception_lower": "1997-06-01",
    "date:inception_upper": "1997-06-01",
    "iso:country": "GB",
    "wof:name": "LS7 2UN",
    "wof:placetype": "postalcode"
  },
  "geometry": {"coordinates":[-1.561336,53.830826],"type":"Point"}
}
