{
  "type": "Feature",
  "properties": {
    "iso:country":"GB",
    "wof:name":"SE16 6QQ",
    "wof:placetype":"postalcode"
},
  "geometry": {"coordinates":[-0.03780727056929,51.49793355539959],"type":"Point"}
}