{
  "type": "Feature",
  "properties": {
    "date:inception_lower":"1980-01-01",
    "date:inception_upper":"1980-01-31",
    "iso:country":"GB",
    "wof:name":"PL14 3PD",
    "wof:placetype":"postalcode"
},
  "geometry": {"coordinates":[-4.454183,50.454852],"type":"Point"}
}