{
  "type": "Feature",
  "properties": {
    "iso:country":"GB",
    "wof:name":"DE22 3PT",
    "wof:placetype":"postalcode"
},
  "geometry": {"coordinates":[-1.49267223991339,52.91356463112484],"type":"Point"}
}