{
  "type": "Feature",
  "properties": {
    "date:inception_lower":"1992-08-01",
    "date:inception_upper":"1992-08-31",
    "iso:country":"GB",
    "wof:name":"DE22 3PT",
    "wof:placetype":"postalcode"
},
  "geometry": {"coordinates":[-1.492624,52.913538],"type":"Point"}
}