{
  "type": "Feature",
  "properties": {
    "date:inception_lower": "1980-01-01",
    "date:inception_upper": "1980-01-01",
    "iso:country": "GB",
    "wof:name": "SN15 5DA",
    "wof:placetype": "postalcode"
  },
  "geometry": {"coordinates":[-2.024939,51.565241],"type":"Point"}
}
