{
  "type": "Feature",
  "properties": {
    "iso:country":"GB",
    "wof:name":"DN6 0AU",
    "wof:placetype":"postalcode"
},
  "geometry": {"coordinates":[-1.16027251597905,53.61038121626179],"type":"Point"}
}