{
  "type": "Feature",
  "properties": {
    "iso:country":"GB",
    "wof:name":"ST5 9JL",
    "wof:placetype":"postalcode"
},
  "geometry": {"coordinates":[-2.22083689585615,53.02810068151684],"type":"Point"}
}