{
  "type": "Feature",
  "properties": {
    "iso:country":"GB",
    "wof:name":"YO8 5BT",
    "wof:placetype":"postalcode"
},
  "geometry": {"coordinates":[-1.04414590708126,53.79218307314102],"type":"Point"}
}