{
  "type": "Feature",
  "properties": {
    "iso:country": "GB",
    "wof:name": "YO8 5BT",
    "wof:placetype": "postalcode"
  },
  "geometry": {"coordinates":[-1.044146,53.792183],"type":"Point"}
}
