{
  "type": "Feature",
  "properties": {
    "iso:country":"GB",
    "wof:name":"TD9 0NA",
    "wof:placetype":"postalcode"
},
  "geometry": {"coordinates":[-2.72453367515885,55.27205006721997],"type":"Point"}
}