{
  "type": "Feature",
  "properties": {
    "date:inception_lower":"1980-01-01",
    "date:inception_upper":"1980-01-31",
    "iso:country":"GB",
    "wof:name":"TD9 0NA",
    "wof:placetype":"postalcode"
},
  "geometry": {"coordinates":[-2.724534,55.27205],"type":"Point"}
}