{
  "type": "Feature",
  "properties": {
    "date:inception_lower": "2020-12-01",
    "date:inception_upper": "2020-12-01",
    "iso:country": "GB",
    "wof:name": "PR2 8FT",
    "wof:placetype": "postalcode"
  },
  "geometry": {"coordinates":[-2.678199,53.782204],"type":"Point"}
}
