{
  "type": "Feature",
  "properties": {
    "iso:country":"GB",
    "wof:name":"NE40 4JB",
    "wof:placetype":"postalcode"
},
  "geometry": {"coordinates":[-1.78650157672997,54.95175877799801],"type":"Point"}
}