{
  "type": "Feature",
  "properties": {
    "iso:country":"GB",
    "wof:name":"WF11 9ES",
    "wof:placetype":"postalcode"
},
  "geometry": {"coordinates":[-1.26926600037375,53.72674042655345],"type":"Point"}
}