{
  "type": "Feature",
  "properties": {
    "date:inception_lower":"1994-10-01",
    "date:inception_upper":"1994-10-31",
    "iso:country":"GB",
    "wof:name":"PH3 1QG",
    "wof:placetype":"postalcode"
},
  "geometry": {"coordinates":[-3.715934,56.294604],"type":"Point"}
}