{
  "type": "Feature",
  "properties": {
    "iso:country": "GB",
    "wof:name": "PH3 1QG",
    "wof:placetype": "postalcode"
  },
  "geometry": {"coordinates":[-3.715934,56.294604],"type":"Point"}
}
