{
  "type": "Feature",
  "properties": {
    "iso:country":"GB",
    "wof:name":"CA5 7QP",
    "wof:placetype":"postalcode"
},
  "geometry": {"coordinates":[-2.97974793021097,54.83166277280148],"type":"Point"}
}