{
  "type": "Feature",
  "properties": {
    "iso:country": "GB",
    "wof:name": "CA5 7QP",
    "wof:placetype": "postalcode"
  },
  "geometry": {"coordinates":[-2.979748,54.831663],"type":"Point"}
}
