{
  "type": "Feature",
  "properties": {
    "iso:country":"GB",
    "wof:name":"PH2 7US",
    "wof:placetype":"postalcode"
},
  "geometry": {"coordinates":[-3.21354474385064,56.39488976064955],"type":"Point"}
}