{
  "type": "Feature",
  "properties": {
    "iso:country": "GB",
    "wof:name": "PH2 7US",
    "wof:placetype": "postalcode"
  },
  "geometry": {"coordinates":[-3.213545,56.39489],"type":"Point"}
}
