{
  "type": "Feature",
  "properties": {
    "date:inception_lower": "2012-06-01",
    "date:inception_upper": "2012-06-01",
    "iso:country": "GB",
    "wof:name": "PH2 7US",
    "wof:placetype": "postalcode"
  },
  "geometry": {"coordinates":[-3.213545,56.39489],"type":"Point"}
}
