{
  "type": "Feature",
  "properties": {
    "iso:country":"GB",
    "wof:name":"WF6 1US",
    "wof:placetype":"postalcode"
},
  "geometry": {"coordinates":[-1.40295330950821,53.69407150895019],"type":"Point"}
}