{
  "type": "Feature",
  "properties": {
    "date:inception_lower":"2001-06-01",
    "date:inception_upper":"2001-06-30",
    "iso:country":"GB",
    "wof:name":"WF6 1US",
    "wof:placetype":"postalcode"
},
  "geometry": {"coordinates":[-1.402953,53.694072],"type":"Point"}
}