{
  "type": "Feature",
  "properties": {
    "iso:country": "GB",
    "wof:name": "PE7 1FY",
    "wof:placetype": "postalcode"
  },
  "geometry": {"coordinates":[-0.138086,52.564296],"type":"Point"}
}
