{
  "type": "Feature",
  "properties": {
    "iso:country":"GB",
    "wof:name":"PE7 1FY",
    "wof:placetype":"postalcode"
},
  "geometry": {"coordinates":[-0.13808575645974,52.56429598010541],"type":"Point"}
}