{
  "type": "Feature",
  "properties": {
    "iso:country":"GB",
    "wof:name":"WV10 9BA",
    "wof:placetype":"postalcode"
},
  "geometry": {"coordinates":[-2.11279715651476,52.61021629333496],"type":"Point"}
}