{
  "type": "Feature",
  "properties": {
    "date:inception_lower": "1980-01-01",
    "date:inception_upper": "1980-01-01",
    "iso:country": "GB",
    "wof:name": "WV10 9BA",
    "wof:placetype": "postalcode"
  },
  "geometry": {"coordinates":[-2.112797,52.610216],"type":"Point"}
}
