{
  "type": "Feature",
  "properties": {
    "iso:country": "GB",
    "wof:name": "LU6 2FD",
    "wof:placetype": "postalcode"
  },
  "geometry": {"coordinates":[-0.589558,51.876104],"type":"Point"}
}
