{
  "type": "Feature",
  "properties": {
    "date:inception_lower":"1999-12-01",
    "date:inception_upper":"1999-12-31",
    "iso:country":"GB",
    "wof:name":"LU6 2FD",
    "wof:placetype":"postalcode"
},
  "geometry": {"coordinates":[-0.589558,51.876104],"type":"Point"}
}