{
  "type": "Feature",
  "properties": {
    "iso:country":"GB",
    "wof:name":"LU6 2FD",
    "wof:placetype":"postalcode"
},
  "geometry": {"coordinates":[-0.58955815599614,51.87610379567602],"type":"Point"}
}