{
  "type": "Feature",
  "properties": {
    "iso:country": "GB",
    "wof:name": "WD25 9QL",
    "wof:placetype": "postalcode"
  },
  "geometry": {"coordinates":[-0.38405,51.687986],"type":"Point"}
}
