{
  "type": "Feature",
  "properties": {
    "iso:country":"GB",
    "wof:name":"E7 0AU",
    "wof:placetype":"postalcode"
},
  "geometry": {"coordinates":[0.01937202543362,51.55388651622492],"type":"Point"}
}