{
  "type": "Feature",
  "properties": {
    "iso:country": "GB",
    "wof:name": "IP2 8LA",
    "wof:placetype": "postalcode"
  },
  "geometry": {"coordinates":[1.154146,52.043414],"type":"Point"}
}
