{
  "type": "Feature",
  "properties": {
    "iso:country":"GB",
    "wof:name":"BS10 7DQ",
    "wof:placetype":"postalcode"
},
  "geometry": {"coordinates":[-2.61583669751804,51.50465096300285],"type":"Point"}
}