{
  "type": "Feature",
  "properties": {
    "iso:country":"GB",
    "wof:name":"BN1 6PA",
    "wof:placetype":"postalcode"
},
  "geometry": {"coordinates":[-0.14580784253537,50.84447186133304],"type":"Point"}
}