{
  "type": "Feature",
  "properties": {
    "date:inception_lower":"2002-11-01",
    "date:inception_upper":"2002-11-30",
    "iso:country":"GB",
    "wof:name":"TA6 3TG",
    "wof:placetype":"postalcode"
},
  "geometry": {"coordinates":[-3.011635,51.137403],"type":"Point"}
}