{
  "type": "Feature",
  "properties": {
    "iso:country":"GB",
    "wof:name":"TA6 3TG",
    "wof:placetype":"postalcode"
},
  "geometry": {"coordinates":[-3.01163550241783,51.13740255587403],"type":"Point"}
}