{
  "type": "Feature",
  "properties": {
    "iso:country":"GB",
    "wof:name":"BL9 8RE",
    "wof:placetype":"postalcode"
},
  "geometry": {"coordinates":[-2.28189812795636,53.57511596019968],"type":"Point"}
}