{
  "type": "Feature",
  "properties": {
    "iso:country":"GB",
    "wof:name":"UB4 0QA",
    "wof:placetype":"postalcode"
},
  "geometry": {"coordinates":[-0.4133494521505,51.52301161348485],"type":"Point"}
}