{
  "type": "Feature",
  "properties": {
    "iso:country": "GB",
    "wof:name": "UB4 0QA",
    "wof:placetype": "postalcode"
  },
  "geometry": {"coordinates":[-0.413349,51.523012],"type":"Point"}
}
