{
  "type": "Feature",
  "properties": {
    "iso:country":"GB",
    "wof:name":"NN2 6DG",
    "wof:placetype":"postalcode"
},
  "geometry": {"coordinates":[-0.89999802640211,52.24901702743735],"type":"Point"}
}