{
  "type": "Feature",
  "properties": {
    "iso:country":"GB",
    "wof:name":"CW8 4EY",
    "wof:placetype":"postalcode"
},
  "geometry": {"coordinates":[-2.54768144076496,53.26997329210015],"type":"Point"}
}