{
  "type": "Feature",
  "properties": {
    "date:inception_lower": "1980-01-01",
    "date:inception_upper": "1980-01-01",
    "iso:country": "GB",
    "wof:name": "CW8 4EY",
    "wof:placetype": "postalcode"
  },
  "geometry": {"coordinates":[-2.547681,53.269973],"type":"Point"}
}
