{
  "type": "Feature",
  "properties": {
    "iso:country":"GB",
    "wof:name":"OL9 6LE",
    "wof:placetype":"postalcode"
},
  "geometry": {"coordinates":[-2.13040543381233,53.54377439026408],"type":"Point"}
}