{
  "type": "Feature",
  "properties": {
    "iso:country": "GB",
    "wof:name": "RH10 5JD",
    "wof:placetype": "postalcode"
  },
  "geometry": {"coordinates":[-0.181591,51.098644],"type":"Point"}
}
