{
  "type": "Feature",
  "properties": {
    "date:inception_lower":"1992-08-01",
    "date:inception_upper":"1992-08-31",
    "iso:country":"GB",
    "wof:name":"LE65 2YA",
    "wof:placetype":"postalcode"
},
  "geometry": {"coordinates":[-1.478447,52.749417],"type":"Point"}
}