{
  "type": "Feature",
  "properties": {
    "iso:country":"GB",
    "wof:name":"LE65 2YA",
    "wof:placetype":"postalcode"
},
  "geometry": {"coordinates":[-1.47844657931568,52.74941733832988],"type":"Point"}
}