{
  "type": "Feature",
  "properties": {
    "iso:country": "GB",
    "wof:name": "NR21 7ER",
    "wof:placetype": "postalcode"
  },
  "geometry": {"coordinates":[0.784586,52.795543],"type":"Point"}
}
