{
  "type": "Feature",
  "properties": {
    "date:inception_lower":"1980-01-01",
    "date:inception_upper":"1980-01-31",
    "iso:country":"GB",
    "wof:name":"NR21 7ER",
    "wof:placetype":"postalcode"
},
  "geometry": {"coordinates":[0.784829,52.795636],"type":"Point"}
}