{
  "type": "Feature",
  "properties": {
    "iso:country":"GB",
    "wof:name":"NP4 9LY",
    "wof:placetype":"postalcode"
},
  "geometry": {"coordinates":[-3.07513313389445,51.77095280563302],"type":"Point"}
}