{
  "type": "Feature",
  "properties": {
    "date:inception_lower":"1995-01-01",
    "date:inception_upper":"1995-01-31",
    "iso:country":"GB",
    "wof:name":"NP4 9LY",
    "wof:placetype":"postalcode"
},
  "geometry": {"coordinates":[-3.075133,51.770953],"type":"Point"}
}