{
  "type": "Feature",
  "properties": {
    "iso:country":"GB",
    "wof:name":"B92 0PY",
    "wof:placetype":"postalcode"
},
  "geometry": {"coordinates":[-1.7568375150308,52.42812819451943],"type":"Point"}
}