{
  "type": "Feature",
  "properties": {
    "date:inception_lower": "2004-05-01",
    "date:inception_upper": "2004-05-01",
    "iso:country": "GB",
    "wof:name": "NE48 1AR",
    "wof:placetype": "postalcode"
  },
  "geometry": {"coordinates":[-2.579801,55.232468],"type":"Point"}
}
