{
  "type": "Feature",
  "properties": {
    "iso:country":"GB",
    "wof:name":"NE48 1AR",
    "wof:placetype":"postalcode"
},
  "geometry": {"coordinates":[-2.57980113122785,55.23246755624333],"type":"Point"}
}