{
  "type": "Feature",
  "properties": {
    "iso:country":"GB",
    "wof:name":"SN2 7AD",
    "wof:placetype":"postalcode"
},
  "geometry": {"coordinates":[-1.76768300826945,51.58463331078774],"type":"Point"}
}