{
  "type": "Feature",
  "properties": {
    "iso:country": "GB",
    "wof:name": "SN2 7AD",
    "wof:placetype": "postalcode"
  },
  "geometry": {"coordinates":[-1.767683,51.584633],"type":"Point"}
}
