{
  "type": "Feature",
  "properties": {
    "date:inception_lower":"2008-05-01",
    "date:inception_upper":"2008-05-31",
    "iso:country":"GB",
    "wof:name":"SN2 7AD",
    "wof:placetype":"postalcode"
},
  "geometry": {"coordinates":[-1.767683,51.584633],"type":"Point"}
}