{
  "type": "Feature",
  "properties": {
    "iso:country":"GB",
    "wof:name":"CO5 8AL",
    "wof:placetype":"postalcode"
},
  "geometry": {"coordinates":[0.91948026987924,51.77510736913612],"type":"Point"}
}