{
  "type": "Feature",
  "properties": {
    "date:inception_lower": "1986-07-01",
    "date:inception_upper": "1986-07-01",
    "iso:country": "GB",
    "wof:name": "CO5 8AL",
    "wof:placetype": "postalcode"
  },
  "geometry": {"coordinates":[0.91948,51.775107],"type":"Point"}
}
