{
  "type": "Feature",
  "properties": {
    "iso:country": "GB",
    "wof:name": "G41 5AN",
    "wof:placetype": "postalcode"
  },
  "geometry": {"coordinates":[-4.304441,55.844776],"type":"Point"}
}
