{
  "type": "Feature",
  "properties": {
    "iso:country": "GB",
    "wof:name": "B93 9EJ",
    "wof:placetype": "postalcode"
  },
  "geometry": {"coordinates":[-1.752747,52.383718],"type":"Point"}
}
