{
  "type": "Feature",
  "properties": {
    "iso:country":"GB",
    "wof:name":"B93 9EJ",
    "wof:placetype":"postalcode"
},
  "geometry": {"coordinates":[-1.75274714640493,52.38371765571607],"type":"Point"}
}