{
  "type": "Feature",
  "properties": {
    "iso:country": "GB",
    "wof:name": "DE23 6FW",
    "wof:placetype": "postalcode"
  },
  "geometry": {"coordinates":[-1.510045,52.905313],"type":"Point"}
}
