{
  "type": "Feature",
  "properties": {
    "iso:country":"GB",
    "wof:name":"N1 5RN",
    "wof:placetype":"postalcode"
},
  "geometry": {"coordinates":[-0.07982968161378,51.53606523375348],"type":"Point"}
}