{
  "type": "Feature",
  "properties": {
    "iso:country":"GB",
    "wof:name":"FY5 2QH",
    "wof:placetype":"postalcode"
},
  "geometry": {"coordinates":[-3.02789785425873,53.8869220446494],"type":"Point"}
}