{
  "type": "Feature",
  "properties": {
    "date:inception_lower": "1980-01-01",
    "date:inception_upper": "1980-01-01",
    "iso:country": "GB",
    "wof:name": "FY5 2QH",
    "wof:placetype": "postalcode"
  },
  "geometry": {"coordinates":[-3.027898,53.886922],"type":"Point"}
}
