{
  "type": "Feature",
  "properties": {
    "iso:country": "GB",
    "wof:name": "OX11 0FR",
    "wof:placetype": "postalcode"
  },
  "geometry": {"coordinates":[-1.295003,51.602971],"type":"Point"}
}
