{
  "type": "Feature",
  "properties": {
    "date:inception_lower": "2021-07-01",
    "date:inception_upper": "2021-07-01",
    "iso:country": "GB",
    "wof:name": "M40 7NA",
    "wof:placetype": "postalcode"
  },
  "geometry": {"coordinates":[-2.213569,53.490028],"type":"Point"}
}
