{
  "type": "Feature",
  "properties": {
    "iso:country":"GB",
    "wof:name":"TS7 9LH",
    "wof:placetype":"postalcode"
},
  "geometry": {"coordinates":[-1.17760602717065,54.54794010979491],"type":"Point"}
}