{
  "type": "Feature",
  "properties": {
    "iso:country":"GB",
    "wof:name":"EN10 6JA",
    "wof:placetype":"postalcode"
},
  "geometry": {"coordinates":[-0.02055474050914,51.73114314497872],"type":"Point"}
}