{
  "type": "Feature",
  "properties": {
    "date:inception_lower": "1980-01-01",
    "date:inception_upper": "1980-01-01",
    "iso:country": "GB",
    "wof:name": "EN10 6JA",
    "wof:placetype": "postalcode"
  },
  "geometry": {"coordinates":[-0.020555,51.731143],"type":"Point"}
}
