{
  "type": "Feature",
  "properties": {
    "iso:country":"GB",
    "wof:name":"NP22 4PF",
    "wof:placetype":"postalcode"
},
  "geometry": {"coordinates":[-3.23685042756645,51.78491743262354],"type":"Point"}
}