{
  "type": "Feature",
  "properties": {
    "iso:country":"GB",
    "wof:name":"KY8 6HT",
    "wof:placetype":"postalcode"
},
  "geometry": {"coordinates":[-2.93339779212317,56.2147102868017],"type":"Point"}
}