{
  "type": "Feature",
  "properties": {
    "iso:country":"GB",
    "wof:name":"NR16 1RL",
    "wof:placetype":"postalcode"
},
  "geometry": {"coordinates":[1.11247360839473,52.49034555234056],"type":"Point"}
}