{
  "type": "Feature",
  "properties": {
    "iso:country": "GB",
    "wof:name": "NR16 1RL",
    "wof:placetype": "postalcode"
  },
  "geometry": {"coordinates":[1.112474,52.490346],"type":"Point"}
}
