{
  "type": "Feature",
  "properties": {
    "iso:country": "GB",
    "wof:name": "LE12 9WE",
    "wof:placetype": "postalcode"
  },
  "geometry": {"coordinates":[-1.282731,52.779375],"type":"Point"}
}
