{
  "type": "Feature",
  "properties": {
    "date:inception_lower":"2018-09-01",
    "date:inception_upper":"2018-09-30",
    "iso:country":"GB",
    "wof:name":"LE12 9WE",
    "wof:placetype":"postalcode"
},
  "geometry": {"coordinates":[-1.282731,52.779375],"type":"Point"}
}