{
  "type": "Feature",
  "properties": {
    "iso:country":"GB",
    "wof:name":"BH9 2HP",
    "wof:placetype":"postalcode"
},
  "geometry": {"coordinates":[-1.87958651125395,50.74039940578173],"type":"Point"}
}