{
  "type": "Feature",
  "properties": {
    "date:inception_lower":"1980-01-01",
    "date:inception_upper":"1980-01-31",
    "iso:country":"GB",
    "wof:name":"BH9 2HP",
    "wof:placetype":"postalcode"
},
  "geometry": {"coordinates":[-1.879586,50.740399],"type":"Point"}
}