{
  "type": "Feature",
  "properties": {
    "iso:country":"GB",
    "wof:name":"N16 8PX",
    "wof:placetype":"postalcode"
},
  "geometry": {"coordinates":[-0.08060715508131,51.55254328665118],"type":"Point"}
}