{
  "type": "Feature",
  "properties": {
    "iso:country":"GB",
    "wof:name":"HG1 4HH",
    "wof:placetype":"postalcode"
},
  "geometry": {"coordinates":[-1.53294281165927,54.00796003654532],"type":"Point"}
}