{
  "type": "Feature",
  "properties": {
    "iso:country": "GB",
    "wof:name": "WF13 4AG",
    "wof:placetype": "postalcode"
  },
  "geometry": {"coordinates":[-1.653161,53.70267],"type":"Point"}
}
