{
  "type": "Feature",
  "properties": {
    "iso:country":"GB",
    "wof:name":"S41 7HE",
    "wof:placetype":"postalcode"
},
  "geometry": {"coordinates":[-1.43647526969617,53.24409480457897],"type":"Point"}
}