{
  "type": "Feature",
  "properties": {
    "iso:country":"GB",
    "wof:name":"KT22 8NW",
    "wof:placetype":"postalcode"
},
  "geometry": {"coordinates":[-0.31968027232066,51.29242651936271],"type":"Point"}
}