{
  "type": "Feature",
  "properties": {
    "iso:country":"GB",
    "wof:name":"WN5 9LG",
    "wof:placetype":"postalcode"
},
  "geometry": {"coordinates":[-2.67015460019054,53.53593538881508],"type":"Point"}
}