{
  "type": "Feature",
  "properties": {
    "iso:country":"GB",
    "wof:name":"PH3 1LS",
    "wof:placetype":"postalcode"
},
  "geometry": {"coordinates":[-3.72303762711645,56.29086646282393],"type":"Point"}
}