{
  "type": "Feature",
  "properties": {
    "iso:country": "GB",
    "wof:name": "TS10 2HL",
    "wof:placetype": "postalcode"
  },
  "geometry": {"coordinates":[-1.063558,54.612178],"type":"Point"}
}
