{
  "type": "Feature",
  "properties": {
    "iso:country":"GB",
    "wof:name":"TS10 2HL",
    "wof:placetype":"postalcode"
},
  "geometry": {"coordinates":[-1.06355845188,54.61217847127535],"type":"Point"}
}