{
  "type": "Feature",
  "properties": {
    "iso:country": "GB",
    "wof:name": "BS37 6JG",
    "wof:placetype": "postalcode"
  },
  "geometry": {"coordinates":[-2.401995,51.53392],"type":"Point"}
}
