{
  "type": "Feature",
  "properties": {
    "iso:country": "GB",
    "wof:name": "MK18 3GH",
    "wof:placetype": "postalcode"
  },
  "geometry": {"coordinates":[-0.889781,51.949145],"type":"Point"}
}
