{
  "type": "Feature",
  "properties": {
    "iso:country":"GB",
    "wof:name":"PE12 7AD",
    "wof:placetype":"postalcode"
},
  "geometry": {"coordinates":[0.01960917578686,52.80346403452545],"type":"Point"}
}