{
  "type": "Feature",
  "properties": {
    "iso:country": "GB",
    "wof:name": "S7 1GN",
    "wof:placetype": "postalcode"
  },
  "geometry": {"coordinates":[-1.48075,53.359667],"type":"Point"}
}
