{
  "type": "Feature",
  "properties": {
    "iso:country": "GB",
    "wof:name": "ST9 0DY",
    "wof:placetype": "postalcode"
  },
  "geometry": {"coordinates":[-2.0877,53.025874],"type":"Point"}
}
