{
  "type": "Feature",
  "properties": {
    "iso:country":"GB",
    "wof:name":"ST9 0DY",
    "wof:placetype":"postalcode"
},
  "geometry": {"coordinates":[-2.08770022313983,53.02587354222658],"type":"Point"}
}