{
  "type": "Feature",
  "properties": {
    "date:inception_lower":"1980-01-01",
    "date:inception_upper":"1980-01-31",
    "iso:country":"GB",
    "wof:name":"NR11 6QJ",
    "wof:placetype":"postalcode"
},
  "geometry": {"coordinates":[1.134617,52.825811],"type":"Point"}
}