{
  "type": "Feature",
  "properties": {
    "iso:country": "GB",
    "wof:name": "PE11 3XA",
    "wof:placetype": "postalcode"
  },
  "geometry": {"coordinates":[-0.16038,52.817148],"type":"Point"}
}
