{
  "type": "Feature",
  "properties": {
    "iso:country":"GB",
    "wof:name":"PE11 3XA",
    "wof:placetype":"postalcode"
},
  "geometry": {"coordinates":[-0.16050477464836,52.81722670281253],"type":"Point"}
}