{
  "type": "Feature",
  "properties": {
    "iso:country": "GB",
    "wof:name": "AL10 0HG",
    "wof:placetype": "postalcode"
  },
  "geometry": {"coordinates":[-0.218806,51.767928],"type":"Point"}
}
