{
  "type": "Feature",
  "properties": {
    "date:inception_lower": "1985-10-01",
    "date:inception_upper": "1985-10-01",
    "iso:country": "GB",
    "wof:name": "BA2 1NE",
    "wof:placetype": "postalcode"
  },
  "geometry": {"coordinates":[-2.393571,51.37442],"type":"Point"}
}
