{
  "type": "Feature",
  "properties": {
    "iso:country":"GB",
    "wof:name":"NR30 2AH",
    "wof:placetype":"postalcode"
},
  "geometry": {"coordinates":[1.73193015373297,52.60736684070643],"type":"Point"}
}