{
  "type": "Feature",
  "properties": {
    "iso:country":"GB",
    "wof:name":"NR6 6UG",
    "wof:placetype":"postalcode"
},
  "geometry": {"coordinates":[1.26482435965055,52.6703085546803],"type":"Point"}
}