{
  "type": "Feature",
  "properties": {
    "iso:country":"GB",
    "wof:name":"DN11 8RU",
    "wof:placetype":"postalcode"
},
  "geometry": {"coordinates":[-1.07093153424955,53.41230163708642],"type":"Point"}
}