{
  "type": "Feature",
  "properties": {
    "date:inception_lower": "2009-03-01",
    "date:inception_upper": "2009-03-01",
    "iso:country": "GB",
    "wof:name": "DN11 8RU",
    "wof:placetype": "postalcode"
  },
  "geometry": {"coordinates":[-1.070931,53.412302],"type":"Point"}
}
