{
  "type": "Feature",
  "properties": {
    "iso:country":"GB",
    "wof:name":"B11 1PN",
    "wof:placetype":"postalcode"
},
  "geometry": {"coordinates":[-1.86411137120643,52.46093364268512],"type":"Point"}
}