{
  "type": "Feature",
  "properties": {
    "iso:country": "GB",
    "wof:name": "BS3 3LZ",
    "wof:placetype": "postalcode"
  },
  "geometry": {"coordinates":[-2.60526,51.437116],"type":"Point"}
}
