{
  "type": "Feature",
  "properties": {
    "iso:country":"GB",
    "wof:name":"BS3 3LZ",
    "wof:placetype":"postalcode"
},
  "geometry": {"coordinates":[-2.60525994883127,51.4371160264043],"type":"Point"}
}