{
  "type": "Feature",
  "properties": {
    "iso:country":"GB",
    "wof:name":"HP10 0DH",
    "wof:placetype":"postalcode"
},
  "geometry": {"coordinates":[-0.68831393820697,51.59742607470945],"type":"Point"}
}