{
  "type": "Feature",
  "properties": {
    "iso:country":"GB",
    "wof:name":"BB3 1AW",
    "wof:placetype":"postalcode"
},
  "geometry": {"coordinates":[-2.47240581941494,53.69661192045302],"type":"Point"}
}