{
  "type": "Feature",
  "properties": {
    "iso:country":"GB",
    "wof:name":"PL5 2TG",
    "wof:placetype":"postalcode"
},
  "geometry": {"coordinates":[-4.1783961570936,50.41887159050213],"type":"Point"}
}