{
  "type": "Feature",
  "properties": {
    "iso:country":"GB",
    "wof:name":"B98 7GF",
    "wof:placetype":"postalcode"
},
  "geometry": {"coordinates":[-1.91949692443132,52.28924590216987],"type":"Point"}
}