{
  "type": "Feature",
  "properties": {
    "date:inception_lower": "2015-03-01",
    "date:inception_upper": "2015-03-01",
    "iso:country": "GB",
    "wof:name": "B98 7GF",
    "wof:placetype": "postalcode"
  },
  "geometry": {"coordinates":[-1.918198,52.289736],"type":"Point"}
}
