{
  "type": "Feature",
  "properties": {
    "iso:country": "GB",
    "wof:name": "B98 7GF",
    "wof:placetype": "postalcode"
  },
  "geometry": {"coordinates":[-1.918198,52.289736],"type":"Point"}
}
