{
  "type": "Feature",
  "properties": {
    "iso:country": "GB",
    "wof:name": "CB8 8DY",
    "wof:placetype": "postalcode"
  },
  "geometry": {"coordinates":[0.411078,52.2459],"type":"Point"}
}
