{
  "type": "Feature",
  "properties": {
    "iso:country": "GB",
    "wof:name": "PR8 2DB",
    "wof:placetype": "postalcode"
  },
  "geometry": {"coordinates":[-3.022389,53.63967],"type":"Point"}
}
