{
  "type": "Feature",
  "properties": {
    "iso:country":"GB",
    "wof:name":"WN8 9SA",
    "wof:placetype":"postalcode"
},
  "geometry": {"coordinates":[-2.78984202710529,53.54525373470341],"type":"Point"}
}