{
  "type": "Feature",
  "properties": {
    "iso:country":"GB",
    "wof:name":"BB6 8BU",
    "wof:placetype":"postalcode"
},
  "geometry": {"coordinates":[-2.44937522264594,53.80365009910815],"type":"Point"}
}