{
  "type": "Feature",
  "properties": {
    "date:inception_lower": "1980-01-01",
    "date:inception_upper": "1980-01-01",
    "iso:country": "GB",
    "wof:name": "LA14 4PF",
    "wof:placetype": "postalcode"
  },
  "geometry": {"coordinates":[-3.208676,54.139947],"type":"Point"}
}
