{
  "type": "Feature",
  "properties": {
    "iso:country":"GB",
    "wof:name":"LA14 4PF",
    "wof:placetype":"postalcode"
},
  "geometry": {"coordinates":[-3.20867616943506,54.13994651219757],"type":"Point"}
}