{
  "type": "Feature",
  "properties": {
    "iso:country": "GB",
    "wof:name": "FK12 5DE",
    "wof:placetype": "postalcode"
  },
  "geometry": {"coordinates":[-3.812927,56.150568],"type":"Point"}
}
