{
  "type": "Feature",
  "properties": {
    "iso:country":"GB",
    "wof:name":"BD9 6HL",
    "wof:placetype":"postalcode"
},
  "geometry": {"coordinates":[-1.80317906142112,53.81696890585281],"type":"Point"}
}