{
  "type": "Feature",
  "properties": {
    "date:inception_lower": "1980-01-01",
    "date:inception_upper": "1980-01-01",
    "iso:country": "GB",
    "wof:name": "BB8 7DL",
    "wof:placetype": "postalcode"
  },
  "geometry": {"coordinates":[-2.154353,53.861727],"type":"Point"}
}
