{
  "type": "Feature",
  "properties": {
    "iso:country":"GB",
    "wof:name":"BB8 7DL",
    "wof:placetype":"postalcode"
},
  "geometry": {"coordinates":[-2.15435339684375,53.86172713649613],"type":"Point"}
}