{
  "type": "Feature",
  "properties": {
    "iso:country":"GB",
    "wof:name":"GL6 0JU",
    "wof:placetype":"postalcode"
},
  "geometry": {"coordinates":[-2.22621291140552,51.68833151540969],"type":"Point"}
}