{
  "type": "Feature",
  "properties": {
    "date:inception_lower":"1980-01-01",
    "date:inception_upper":"1980-01-31",
    "iso:country":"GB",
    "wof:name":"GL6 0JU",
    "wof:placetype":"postalcode"
},
  "geometry": {"coordinates":[-2.226079,51.688344],"type":"Point"}
}