{
  "type": "Feature",
  "properties": {
    "iso:country":"GB",
    "wof:name":"CR4 3LG",
    "wof:placetype":"postalcode"
},
  "geometry": {"coordinates":[-0.16387924198915,51.41701888494896],"type":"Point"}
}