{
  "type": "Feature",
  "properties": {
    "date:inception_lower":"2001-12-01",
    "date:inception_upper":"2001-12-31",
    "iso:country":"GB",
    "wof:name":"LS13 1RF",
    "wof:placetype":"postalcode"
},
  "geometry": {"coordinates":[-1.65584,53.821706],"type":"Point"}
}