{
  "type": "Feature",
  "properties": {
    "iso:country":"GB",
    "wof:name":"LS13 1RF",
    "wof:placetype":"postalcode"
},
  "geometry": {"coordinates":[-1.65584038114693,53.82170621718469],"type":"Point"}
}