{
  "type": "Feature",
  "properties": {
    "iso:country":"GB",
    "wof:name":"SO18 2DA",
    "wof:placetype":"postalcode"
},
  "geometry": {"coordinates":[-1.35696996154055,50.92540346426838],"type":"Point"}
}