{
  "type": "Feature",
  "properties": {
    "iso:country": "GB",
    "wof:name": "SO18 2DA",
    "wof:placetype": "postalcode"
  },
  "geometry": {"coordinates":[-1.35697,50.925403],"type":"Point"}
}
