{
  "type": "Feature",
  "properties": {
    "iso:country": "GB",
    "wof:name": "SK23 7ED",
    "wof:placetype": "postalcode"
  },
  "geometry": {"coordinates":[-1.978928,53.322008],"type":"Point"}
}
