{
  "type": "Feature",
  "properties": {
    "iso:country":"GB",
    "wof:name":"SK23 7ED",
    "wof:placetype":"postalcode"
},
  "geometry": {"coordinates":[-1.9789282633844,53.32200760386997],"type":"Point"}
}