{
  "type": "Feature",
  "properties": {
    "iso:country":"GB",
    "wof:name":"BD13 4JW",
    "wof:placetype":"postalcode"
},
  "geometry": {"coordinates":[-1.89480997728144,53.80569633096244],"type":"Point"}
}