{
  "type": "Feature",
  "properties": {
    "iso:country": "GB",
    "wof:name": "CT5 4TE",
    "wof:placetype": "postalcode"
  },
  "geometry": {"coordinates":[1.015436,51.342239],"type":"Point"}
}
