{
  "type": "Feature",
  "properties": {
    "iso:country":"GB",
    "wof:name":"CT5 4TE",
    "wof:placetype":"postalcode"
},
  "geometry": {"coordinates":[1.01543558484835,51.34223921763833],"type":"Point"}
}