{
  "type": "Feature",
  "properties": {
    "date:inception_lower":"2009-01-01",
    "date:inception_upper":"2009-01-31",
    "iso:country":"GB",
    "wof:name":"KA1 4QJ",
    "wof:placetype":"postalcode"
},
  "geometry": {"coordinates":[-4.494915,55.58503],"type":"Point"}
}