{
  "type": "Feature",
  "properties": {
    "iso:country":"GB",
    "wof:name":"KA1 4QJ",
    "wof:placetype":"postalcode"
},
  "geometry": {"coordinates":[-4.49491550678661,55.58503010781942],"type":"Point"}
}