{
  "type": "Feature",
  "properties": {
    "date:inception_lower": "1980-01-01",
    "date:inception_upper": "1980-01-01",
    "iso:country": "GB",
    "wof:name": "NN14 4AN",
    "wof:placetype": "postalcode"
  },
  "geometry": {"coordinates":[-0.641241,52.401556],"type":"Point"}
}
