{
  "type": "Feature",
  "properties": {
    "iso:country":"GB",
    "wof:name":"NN14 4AN",
    "wof:placetype":"postalcode"
},
  "geometry": {"coordinates":[-0.64076868487759,52.4012024063039],"type":"Point"}
}