{
  "type": "Feature",
  "properties": {
    "iso:country":"GB",
    "wof:name":"SA6 8QY",
    "wof:placetype":"postalcode"
},
  "geometry": {"coordinates":[-3.91714974072722,51.65165913360364],"type":"Point"}
}