{
  "type": "Feature",
  "properties": {
    "iso:country": "GB",
    "wof:name": "SA6 8QY",
    "wof:placetype": "postalcode"
  },
  "geometry": {"coordinates":[-3.917168,51.651664],"type":"Point"}
}
