{
  "type": "Feature",
  "properties": {
    "date:inception_lower": "1995-01-01",
    "date:inception_upper": "1995-01-01",
    "iso:country": "GB",
    "wof:name": "SA6 8QY",
    "wof:placetype": "postalcode"
  },
  "geometry": {"coordinates":[-3.91842,51.651536],"type":"Point"}
}
