{
  "type": "Feature",
  "properties": {
    "date:inception_lower":"1995-01-01",
    "date:inception_upper":"1995-01-31",
    "iso:country":"GB",
    "wof:name":"SA6 8QY",
    "wof:placetype":"postalcode"
},
  "geometry": {"coordinates":[-3.917168,51.651664],"type":"Point"}
}