{
  "type": "Feature",
  "properties": {
    "iso:country": "GB",
    "wof:name": "S26 7XU",
    "wof:placetype": "postalcode"
  },
  "geometry": {"coordinates":[-1.261261,53.321881],"type":"Point"}
}
