{
  "type": "Feature",
  "properties": {
    "iso:country":"GB",
    "wof:name":"S26 7XU",
    "wof:placetype":"postalcode"
},
  "geometry": {"coordinates":[-1.26126087148082,53.32188136062825],"type":"Point"}
}