{
  "type": "Feature",
  "properties": {
    "date:inception_lower": "2000-12-01",
    "date:inception_upper": "2000-12-01",
    "iso:country": "GB",
    "wof:name": "CM2 5AS",
    "wof:placetype": "postalcode"
  },
  "geometry": {"coordinates":[0.516902,51.74574],"type":"Point"}
}
