{
  "type": "Feature",
  "properties": {
    "iso:country": "GB",
    "wof:name": "CM2 5AS",
    "wof:placetype": "postalcode"
  },
  "geometry": {"coordinates":[0.516902,51.74574],"type":"Point"}
}
