{
  "type": "Feature",
  "properties": {
    "iso:country":"GB",
    "wof:name":"CM2 5AS",
    "wof:placetype":"postalcode"
},
  "geometry": {"coordinates":[0.51581966057633,51.74809381271108],"type":"Point"}
}