{
  "type": "Feature",
  "properties": {
    "iso:country":"GB",
    "wof:name":"S74 0AJ",
    "wof:placetype":"postalcode"
},
  "geometry": {"coordinates":[-1.4587442417263,53.49550450708202],"type":"Point"}
}