{
  "type": "Feature",
  "properties": {
    "iso:country":"GB",
    "wof:name":"OX11 0AE",
    "wof:placetype":"postalcode"
},
  "geometry": {"coordinates":[-1.25824452534275,51.60476558547351],"type":"Point"}
}