{
  "type": "Feature",
  "properties": {
    "date:inception_lower": "1980-01-01",
    "date:inception_upper": "1980-01-01",
    "iso:country": "GB",
    "wof:name": "OX11 0AE",
    "wof:placetype": "postalcode"
  },
  "geometry": {"coordinates":[-1.258082,51.604785],"type":"Point"}
}
