{
  "type": "Feature",
  "properties": {
    "iso:country":"GB",
    "wof:name":"HX4 8HJ",
    "wof:placetype":"postalcode"
},
  "geometry": {"coordinates":[-1.8594661146261,53.69013694360324],"type":"Point"}
}