{
  "type": "Feature",
  "properties": {
    "date:inception_lower":"2004-09-01",
    "date:inception_upper":"2004-09-30",
    "iso:country":"GB",
    "wof:name":"BA2 1BU",
    "wof:placetype":"postalcode"
},
  "geometry": {"coordinates":[-2.389406,51.379712],"type":"Point"}
}