{
  "type": "Feature",
  "properties": {
    "iso:country": "GB",
    "wof:name": "BA2 1BU",
    "wof:placetype": "postalcode"
  },
  "geometry": {"coordinates":[-2.389406,51.379712],"type":"Point"}
}
