{
  "type": "Feature",
  "properties": {
    "iso:country":"GB",
    "wof:name":"BA2 1BU",
    "wof:placetype":"postalcode"
},
  "geometry": {"coordinates":[-2.38940600589548,51.3797123421956],"type":"Point"}
}