{
  "type": "Feature",
  "properties": {
    "iso:country": "GB",
    "wof:name": "DE7 6EW",
    "wof:placetype": "postalcode"
  },
  "geometry": {"coordinates":[-1.396189,52.996788],"type":"Point"}
}
