{
  "type": "Feature",
  "properties": {
    "date:inception_lower":"1980-01-01",
    "date:inception_upper":"1980-01-31",
    "iso:country":"GB",
    "wof:name":"CF45 3EE",
    "wof:placetype":"postalcode"
},
  "geometry": {"coordinates":[-3.397732,51.685482],"type":"Point"}
}