{
  "type": "Feature",
  "properties": {
    "iso:country":"GB",
    "wof:name":"ST10 2PX",
    "wof:placetype":"postalcode"
},
  "geometry": {"coordinates":[-2.01990970980097,52.99837959083982],"type":"Point"}
}