{
  "type": "Feature",
  "properties": {
    "iso:country":"GB",
    "wof:name":"EN1 3UP",
    "wof:placetype":"postalcode"
},
  "geometry": {"coordinates":[-0.07750280925565,51.65756928629669],"type":"Point"}
}