{
  "type": "Feature",
  "properties": {
    "date:inception_lower": "2001-12-01",
    "date:inception_upper": "2001-12-01",
    "iso:country": "GB",
    "wof:name": "GL4 4DA",
    "wof:placetype": "postalcode"
  },
  "geometry": {"coordinates":[-2.212075,51.838734],"type":"Point"}
}
