{
  "type": "Feature",
  "properties": {
    "iso:country":"GB",
    "wof:name":"G5 0LS",
    "wof:placetype":"postalcode"
},
  "geometry": {"coordinates":[-4.23894276669253,55.83941621904804],"type":"Point"}
}