{
  "type": "Feature",
  "properties": {
    "iso:country": "GB",
    "wof:name": "G5 0LS",
    "wof:placetype": "postalcode"
  },
  "geometry": {"coordinates":[-4.238943,55.839416],"type":"Point"}
}
