{
  "type": "Feature",
  "properties": {
    "iso:country": "GB",
    "wof:name": "B45 9HH",
    "wof:placetype": "postalcode"
  },
  "geometry": {"coordinates":[-2.030244,52.395155],"type":"Point"}
}
