{
  "type": "Feature",
  "properties": {
    "iso:country":"GB",
    "wof:name":"B45 9HH",
    "wof:placetype":"postalcode"
},
  "geometry": {"coordinates":[-2.03024392916661,52.39515542941268],"type":"Point"}
}