{
  "type": "Feature",
  "properties": {
    "date:inception_lower":"1985-04-01",
    "date:inception_upper":"1985-04-30",
    "iso:country":"GB",
    "wof:name":"L26 7AQ",
    "wof:placetype":"postalcode"
},
  "geometry": {"coordinates":[-2.838128,53.36444],"type":"Point"}
}