{
  "type": "Feature",
  "properties": {
    "iso:country":"GB",
    "wof:name":"L26 7AQ",
    "wof:placetype":"postalcode"
},
  "geometry": {"coordinates":[-2.83812789375768,53.364439805766],"type":"Point"}
}