{
  "type": "Feature",
  "properties": {
    "date:inception_lower": "1980-01-01",
    "date:inception_upper": "1980-01-01",
    "iso:country": "GB",
    "wof:name": "CA11 0NN",
    "wof:placetype": "postalcode"
  },
  "geometry": {"coordinates":[-2.93585,54.534539],"type":"Point"}
}
