{
  "type": "Feature",
  "properties": {
    "iso:country": "GB",
    "wof:name": "CA11 0NN",
    "wof:placetype": "postalcode"
  },
  "geometry": {"coordinates":[-2.93585,54.534539],"type":"Point"}
}
