{
  "type": "Feature",
  "properties": {
    "iso:country": "GB",
    "wof:name": "LA1 4BG",
    "wof:placetype": "postalcode"
  },
  "geometry": {"coordinates":[-2.787917,54.03712],"type":"Point"}
}
