{
  "type": "Feature",
  "properties": {
    "iso:country": "GB",
    "wof:name": "BN41 1QR",
    "wof:placetype": "postalcode"
  },
  "geometry": {"coordinates":[-0.222727,50.833618],"type":"Point"}
}
