{
  "type": "Feature",
  "properties": {
    "iso:country":"GB",
    "wof:name":"S74 9SZ",
    "wof:placetype":"postalcode"
},
  "geometry": {"coordinates":[-1.43324815724858,53.51181742508098],"type":"Point"}
}