{
  "type": "Feature",
  "properties": {
    "date:inception_lower": "1980-01-01",
    "date:inception_upper": "1980-01-01",
    "iso:country": "GB",
    "wof:name": "AL4 9PL",
    "wof:placetype": "postalcode"
  },
  "geometry": {"coordinates":[-0.304061,51.769261],"type":"Point"}
}
