{
  "type": "Feature",
  "properties": {
    "iso:country":"GB",
    "wof:name":"AL4 9PL",
    "wof:placetype":"postalcode"
},
  "geometry": {"coordinates":[-0.3040606293439,51.76926098216755],"type":"Point"}
}