{
  "type": "Feature",
  "properties": {
    "iso:country":"GB",
    "wof:name":"B90 4PJ",
    "wof:placetype":"postalcode"
},
  "geometry": {"coordinates":[-1.81749364997011,52.39834523656599],"type":"Point"}
}