{
  "type": "Feature",
  "properties": {
    "iso:country":"GB",
    "wof:name":"HP22 5DT",
    "wof:placetype":"postalcode"
},
  "geometry": {"coordinates":[-0.77824819436857,51.83483062961349],"type":"Point"}
}