{
  "type": "Feature",
  "properties": {
    "iso:country":"GB",
    "wof:name":"SE7 8AB",
    "wof:placetype":"postalcode"
},
  "geometry": {"coordinates":[0.03834633842348,51.48621195809591],"type":"Point"}
}