{
  "type": "Feature",
  "properties": {
    "iso:country":"GB",
    "wof:name":"LN4 4LA",
    "wof:placetype":"postalcode"
},
  "geometry": {"coordinates":[-0.18951709381184,53.10552009739347],"type":"Point"}
}