{
  "type": "Feature",
  "properties": {
    "date:inception_lower": "1994-05-01",
    "date:inception_upper": "1994-05-01",
    "iso:country": "GB",
    "wof:name": "LN4 4LA",
    "wof:placetype": "postalcode"
  },
  "geometry": {"coordinates":[-0.189517,53.10552],"type":"Point"}
}
