{
  "type": "Feature",
  "properties": {
    "date:inception_lower": "1990-02-01",
    "date:inception_upper": "1990-02-01",
    "iso:country": "GB",
    "wof:name": "G76 8BB",
    "wof:placetype": "postalcode"
  },
  "geometry": {"coordinates":[-4.274146,55.783083],"type":"Point"}
}
