{
  "type": "Feature",
  "properties": {
    "iso:country": "GB",
    "wof:name": "HX1 5HW",
    "wof:placetype": "postalcode"
  },
  "geometry": {"coordinates":[-1.86556,53.721548],"type":"Point"}
}
