{
  "type": "Feature",
  "properties": {
    "iso:country":"GB",
    "wof:name":"SE26 4ED",
    "wof:placetype":"postalcode"
},
  "geometry": {"coordinates":[-0.05651608730866,51.43370471721638],"type":"Point"}
}