{
  "type": "Feature",
  "properties": {
    "iso:country": "GB",
    "wof:name": "RG2 9AX",
    "wof:placetype": "postalcode"
  },
  "geometry": {"coordinates":[-0.951472,51.419633],"type":"Point"}
}
