{
  "type": "Feature",
  "properties": {
    "iso:country":"GB",
    "wof:name":"E13 8BE",
    "wof:placetype":"postalcode"
},
  "geometry": {"coordinates":[0.02285590613951,51.52933947440431],"type":"Point"}
}