{
  "type": "Feature",
  "properties": {
    "date:inception_lower":"1980-01-01",
    "date:inception_upper":"1980-01-31",
    "iso:country":"GB",
    "wof:name":"TN25 6SB",
    "wof:placetype":"postalcode"
},
  "geometry": {"coordinates":[0.965354,51.12212],"type":"Point"}
}