{
  "type": "Feature",
  "properties": {
    "date:inception_lower": "2001-12-01",
    "date:inception_upper": "2001-12-01",
    "iso:country": "GB",
    "wof:name": "LA15 8TA",
    "wof:placetype": "postalcode"
  },
  "geometry": {"coordinates":[-3.181191,54.153656],"type":"Point"}
}
