{
  "type": "Feature",
  "properties": {
    "iso:country":"GB",
    "wof:name":"LA15 8TA",
    "wof:placetype":"postalcode"
},
  "geometry": {"coordinates":[-3.18119130888603,54.15365648408762],"type":"Point"}
}