{
  "type": "Feature",
  "properties": {
    "iso:country":"GB",
    "wof:name":"BL1 2JS",
    "wof:placetype":"postalcode"
},
  "geometry": {"coordinates":[-2.4342226991173,53.58018758358649],"type":"Point"}
}