{
  "type": "Feature",
  "properties": {
    "date:inception_lower": "1980-01-01",
    "date:inception_upper": "1980-01-01",
    "iso:country": "GB",
    "wof:name": "SY7 9LS",
    "wof:placetype": "postalcode"
  },
  "geometry": {"coordinates":[-2.795254,52.428453],"type":"Point"}
}
