{
  "type": "Feature",
  "properties": {
    "iso:country":"GB",
    "wof:name":"SY7 9LS",
    "wof:placetype":"postalcode"
},
  "geometry": {"coordinates":[-2.79525371892756,52.42845286187734],"type":"Point"}
}