{
  "type": "Feature",
  "properties": {
    "date:inception_lower": "2024-02-01",
    "date:inception_upper": "2024-02-01",
    "iso:country": "GB",
    "wof:name": "NR16 2FP",
    "wof:placetype": "postalcode"
  },
  "geometry": {"coordinates":[0.940105,52.439939],"type":"Point"}
}
