{
  "type": "Feature",
  "properties": {
    "iso:country":"GB",
    "wof:name":"N9 7LJ",
    "wof:placetype":"postalcode"
},
  "geometry": {"coordinates":[-0.05418507337538,51.63927230105914],"type":"Point"}
}