{
  "type": "Feature",
  "properties": {
    "iso:country": "GB",
    "wof:name": "EX12 3LE",
    "wof:placetype": "postalcode"
  },
  "geometry": {"coordinates":[-3.09772,50.699554],"type":"Point"}
}
