{
  "type": "Feature",
  "properties": {
    "date:inception_lower": "1998-12-01",
    "date:inception_upper": "1998-12-01",
    "iso:country": "GB",
    "wof:name": "G72 0US",
    "wof:placetype": "postalcode"
  },
  "geometry": {"coordinates":[-4.086198,55.781079],"type":"Point"}
}
