{
  "type": "Feature",
  "properties": {
    "date:inception_lower": "2019-09-01",
    "date:inception_upper": "2019-09-01",
    "iso:country": "GB",
    "wof:name": "AB15 6BU",
    "wof:placetype": "postalcode"
  },
  "geometry": {"coordinates":[-2.186286,57.152958],"type":"Point"}
}
