{
  "type": "Feature",
  "properties": {
    "iso:country": "GB",
    "wof:name": "WS15 3AF",
    "wof:placetype": "postalcode"
  },
  "geometry": {"coordinates":[-1.859221,52.808246],"type":"Point"}
}
