{
  "type": "Feature",
  "properties": {
    "iso:country": "GB",
    "wof:name": "CM24 8NL",
    "wof:placetype": "postalcode"
  },
  "geometry": {"coordinates":[0.200965,51.897116],"type":"Point"}
}
