{
  "type": "Feature",
  "properties": {
    "iso:country":"GB",
    "wof:name":"CM24 8NL",
    "wof:placetype":"postalcode"
},
  "geometry": {"coordinates":[0.20096518856983,51.89711613831984],"type":"Point"}
}