{
  "type": "Feature",
  "properties": {
    "iso:country":"GB",
    "wof:name":"BN1 8SB",
    "wof:placetype":"postalcode"
},
  "geometry": {"coordinates":[-0.13375435509542,50.86744675672393],"type":"Point"}
}