{
  "type": "Feature",
  "properties": {
    "iso:country": "GB",
    "wof:name": "BN1 8SB",
    "wof:placetype": "postalcode"
  },
  "geometry": {"coordinates":[-0.133872,50.867359],"type":"Point"}
}
