{
  "type": "Feature",
  "properties": {
    "iso:country":"GB",
    "wof:name":"G71 8QH",
    "wof:placetype":"postalcode"
},
  "geometry": {"coordinates":[-4.07184857172733,55.80877792185691],"type":"Point"}
}