{
  "type": "Feature",
  "properties": {
    "iso:country":"GB",
    "wof:name":"IG1 2JL",
    "wof:placetype":"postalcode"
},
  "geometry": {"coordinates":[0.07481438004309,51.54451089455583],"type":"Point"}
}