{
  "type": "Feature",
  "properties": {
    "iso:country":"GB",
    "wof:name":"BA1 3NJ",
    "wof:placetype":"postalcode"
},
  "geometry": {"coordinates":[-2.39388510078784,51.39097293863868],"type":"Point"}
}