{
  "type": "Feature",
  "properties": {
    "date:inception_lower":"1980-01-01",
    "date:inception_upper":"1980-01-31",
    "iso:country":"GB",
    "wof:name":"BA1 3NJ",
    "wof:placetype":"postalcode"
},
  "geometry": {"coordinates":[-2.393885,51.390973],"type":"Point"}
}