{
  "type": "Feature",
  "properties": {
    "iso:country": "GB",
    "wof:name": "NE15 9BZ",
    "wof:placetype": "postalcode"
  },
  "geometry": {"coordinates":[-1.749587,54.989833],"type":"Point"}
}
