{
  "type": "Feature",
  "properties": {
    "iso:country":"GB",
    "wof:name":"S41 0BP",
    "wof:placetype":"postalcode"
},
  "geometry": {"coordinates":[-1.40176611841657,53.23143113033198],"type":"Point"}
}