{
  "type": "Feature",
  "properties": {
    "iso:country":"GB",
    "wof:name":"RG21 7NT",
    "wof:placetype":"postalcode"
},
  "geometry": {"coordinates":[-1.08574996856803,51.26229173788074],"type":"Point"}
}