{
  "type": "Feature",
  "properties": {
    "iso:country":"GB",
    "wof:name":"PR26 7DP",
    "wof:placetype":"postalcode"
},
  "geometry": {"coordinates":[-2.72044642121502,53.70118289713934],"type":"Point"}
}