{
  "type": "Feature",
  "properties": {
    "date:inception_lower":"1998-12-01",
    "date:inception_upper":"1998-12-31",
    "iso:country":"GB",
    "wof:name":"PO38 1LX",
    "wof:placetype":"postalcode"
},
  "geometry": {"coordinates":[-1.229327,50.593086],"type":"Point"}
}