{
  "type": "Feature",
  "properties": {
    "iso:country": "GB",
    "wof:name": "PO38 1LX",
    "wof:placetype": "postalcode"
  },
  "geometry": {"coordinates":[-1.229327,50.593086],"type":"Point"}
}
