{
  "type": "Feature",
  "properties": {
    "iso:country":"GB",
    "wof:name":"PO38 1LX",
    "wof:placetype":"postalcode"
},
  "geometry": {"coordinates":[-1.22932683220857,50.59308554774582],"type":"Point"}
}