{
  "type": "Feature",
  "properties": {
    "date:inception_lower":"1980-01-01",
    "date:inception_upper":"1980-01-31",
    "iso:country":"GB",
    "wof:name":"LE3 6SA",
    "wof:placetype":"postalcode"
},
  "geometry": {"coordinates":[-1.187852,52.632049],"type":"Point"}
}