{
  "type": "Feature",
  "properties": {
    "iso:country":"GB",
    "wof:name":"LE3 6SA",
    "wof:placetype":"postalcode"
},
  "geometry": {"coordinates":[-1.18785206796098,52.63204863933743],"type":"Point"}
}