{
  "type": "Feature",
  "properties": {
    "iso:country":"GB",
    "wof:name":"E14 5ER",
    "wof:placetype":"postalcode"
},
  "geometry": {"coordinates":[-0.01625347579679,51.50457621304803],"type":"Point"}
}