{
  "type": "Feature",
  "properties": {
    "date:inception_lower": "2001-12-01",
    "date:inception_upper": "2001-12-01",
    "iso:country": "GB",
    "wof:name": "E14 5ER",
    "wof:placetype": "postalcode"
  },
  "geometry": {"coordinates":[-0.016253,51.504576],"type":"Point"}
}
