{
  "type": "Feature",
  "properties": {
    "iso:country": "GB",
    "wof:name": "E14 5ER",
    "wof:placetype": "postalcode"
  },
  "geometry": {"coordinates":[-0.016253,51.504576],"type":"Point"}
}
