{
  "type": "Feature",
  "properties": {
    "iso:country":"GB",
    "wof:name":"G62 7HE",
    "wof:placetype":"postalcode"
},
  "geometry": {"coordinates":[-4.34988628312899,55.95237896093533],"type":"Point"}
}