{
  "type": "Feature",
  "properties": {
    "iso:country":"GB",
    "wof:name":"CO2 9PW",
    "wof:placetype":"postalcode"
},
  "geometry": {"coordinates":[0.88488444760067,51.8638300103386],"type":"Point"}
}