{
  "type": "Feature",
  "properties": {
    "iso:country": "GB",
    "wof:name": "CO2 9PW",
    "wof:placetype": "postalcode"
  },
  "geometry": {"coordinates":[0.884884,51.86383],"type":"Point"}
}
