{
  "type": "Feature",
  "properties": {
    "iso:country":"GB",
    "wof:name":"LL12 9EU",
    "wof:placetype":"postalcode"
},
  "geometry": {"coordinates":[-3.03974404974947,53.10990556557569],"type":"Point"}
}