{
  "type": "Feature",
  "properties": {
    "iso:country": "GB",
    "wof:name": "LL12 9EU",
    "wof:placetype": "postalcode"
  },
  "geometry": {"coordinates":[-3.039878,53.109904],"type":"Point"}
}
