{
  "type": "Feature",
  "properties": {
    "iso:country": "GB",
    "wof:name": "GU35 9HA",
    "wof:placetype": "postalcode"
  },
  "geometry": {"coordinates":[-0.878223,51.101809],"type":"Point"}
}
