{
  "type": "Feature",
  "properties": {
    "iso:country":"GB",
    "wof:name":"WS1 1XB",
    "wof:placetype":"postalcode"
},
  "geometry": {"coordinates":[-1.97855464426025,52.5874253307688],"type":"Point"}
}