{
  "type": "Feature",
  "properties": {
    "date:inception_lower":"2001-12-01",
    "date:inception_upper":"2001-12-31",
    "iso:country":"GB",
    "wof:name":"WR11 8XG",
    "wof:placetype":"postalcode"
},
  "geometry": {"coordinates":[-1.889179,52.159158],"type":"Point"}
}