{
  "type": "Feature",
  "properties": {
    "iso:country":"GB",
    "wof:name":"WR11 8XG",
    "wof:placetype":"postalcode"
},
  "geometry": {"coordinates":[-1.88917943481878,52.15915796565102],"type":"Point"}
}