{
  "type": "Feature",
  "properties": {
    "date:inception_lower":"2001-12-01",
    "date:inception_upper":"2001-12-31",
    "iso:country":"GB",
    "wof:name":"SR4 7LP",
    "wof:placetype":"postalcode"
},
  "geometry": {"coordinates":[-1.399605,54.897696],"type":"Point"}
}