{
  "type": "Feature",
  "properties": {
    "date:inception_lower":"1980-01-01",
    "date:inception_upper":"1980-01-31",
    "iso:country":"GB",
    "wof:name":"SY14 8DL",
    "wof:placetype":"postalcode"
},
  "geometry": {"coordinates":[-2.745214,53.029791],"type":"Point"}
}