{
  "type": "Feature",
  "properties": {
    "iso:country": "GB",
    "wof:name": "DN37 9AW",
    "wof:placetype": "postalcode"
  },
  "geometry": {"coordinates":[-0.124873,53.571201],"type":"Point"}
}
