{
  "type": "Feature",
  "properties": {
    "date:inception_lower": "2014-07-01",
    "date:inception_upper": "2014-07-01",
    "iso:country": "GB",
    "wof:name": "DG1 3FR",
    "wof:placetype": "postalcode"
  },
  "geometry": {"coordinates":[-3.591465,55.081369],"type":"Point"}
}
