{
  "type": "Feature",
  "properties": {
    "iso:country":"GB",
    "wof:name":"PE22 0TW",
    "wof:placetype":"postalcode"
},
  "geometry": {"coordinates":[0.01440415472061,53.04384047491661],"type":"Point"}
}