{
  "type": "Feature",
  "properties": {
    "iso:country":"GB",
    "wof:name":"NN17 3JP",
    "wof:placetype":"postalcode"
},
  "geometry": {"coordinates":[-0.63073382509587,52.49738560014384],"type":"Point"}
}