{
  "type": "Feature",
  "properties": {
    "iso:country":"GB",
    "wof:name":"CM23 5JL",
    "wof:placetype":"postalcode"
},
  "geometry": {"coordinates":[0.18044951872077,51.86756238726308],"type":"Point"}
}