{
  "type": "Feature",
  "properties": {
    "iso:country":"GB",
    "wof:name":"MK18 5NY",
    "wof:placetype":"postalcode"
},
  "geometry": {"coordinates":[-0.93386186982451,52.03429328431858],"type":"Point"}
}