{
  "type": "Feature",
  "properties": {
    "date:inception_lower": "1980-01-01",
    "date:inception_upper": "1980-01-01",
    "iso:country": "GB",
    "wof:name": "EX17 6AE",
    "wof:placetype": "postalcode"
  },
  "geometry": {"coordinates":[-3.811486,50.856493],"type":"Point"}
}
