{
  "type": "Feature",
  "properties": {
    "iso:country":"GB",
    "wof:name":"S61 2AG",
    "wof:placetype":"postalcode"
},
  "geometry": {"coordinates":[-1.40041751491129,53.43928126413348],"type":"Point"}
}