{
  "type": "Feature",
  "properties": {
    "iso:country":"GB",
    "wof:name":"KA20 3EU",
    "wof:placetype":"postalcode"
},
  "geometry": {"coordinates":[-4.76067904742445,55.64045530564754],"type":"Point"}
}