{
  "type": "Feature",
  "properties": {
    "iso:country": "GB",
    "wof:name": "KA20 3EU",
    "wof:placetype": "postalcode"
  },
  "geometry": {"coordinates":[-4.760679,55.640455],"type":"Point"}
}
