{
  "type": "Feature",
  "properties": {
    "iso:country": "GB",
    "wof:name": "E17 9BU",
    "wof:placetype": "postalcode"
  },
  "geometry": {"coordinates":[-0.01097,51.579197],"type":"Point"}
}
