{
  "type": "Feature",
  "properties": {
    "iso:country":"GB",
    "wof:name":"E17 9BU",
    "wof:placetype":"postalcode"
},
  "geometry": {"coordinates":[-0.01097044444774,51.57919742620889],"type":"Point"}
}