{
  "type": "Feature",
  "properties": {
    "iso:country": "GB",
    "wof:name": "LE17 6HU",
    "wof:placetype": "postalcode"
  },
  "geometry": {"coordinates":[-1.053009,52.452566],"type":"Point"}
}
