{
  "type": "Feature",
  "properties": {
    "date:inception_lower": "1980-01-01",
    "date:inception_upper": "1980-01-01",
    "iso:country": "GB",
    "wof:name": "S8 9FT",
    "wof:placetype": "postalcode"
  },
  "geometry": {"coordinates":[-1.473931,53.357067],"type":"Point"}
}
