{
  "type": "Feature",
  "properties": {
    "iso:country":"GB",
    "wof:name":"S8 9FT",
    "wof:placetype":"postalcode"
},
  "geometry": {"coordinates":[-1.47412560747072,53.35713929903726],"type":"Point"}
}