{
  "type": "Feature",
  "properties": {
    "iso:country": "GB",
    "wof:name": "S8 9FT",
    "wof:placetype": "postalcode"
  },
  "geometry": {"coordinates":[-1.473931,53.357067],"type":"Point"}
}
