{
  "type": "Feature",
  "properties": {
    "iso:country":"GB",
    "wof:name":"WN7 4QD",
    "wof:placetype":"postalcode"
},
  "geometry": {"coordinates":[-2.55313237873535,53.49436910666961],"type":"Point"}
}