{
  "type": "Feature",
  "properties": {
    "iso:country":"GB",
    "wof:name":"PE1 4PY",
    "wof:placetype":"postalcode"
},
  "geometry": {"coordinates":[-0.22783920445944,52.59897589001307],"type":"Point"}
}