{
  "type": "Feature",
  "properties": {
    "iso:country": "GB",
    "wof:name": "GU10 5LX",
    "wof:placetype": "postalcode"
  },
  "geometry": {"coordinates":[-0.897844,51.203886],"type":"Point"}
}
