{
  "type": "Feature",
  "properties": {
    "date:inception_lower":"1980-01-01",
    "date:inception_upper":"1980-01-31",
    "iso:country":"GB",
    "wof:name":"GU10 5LX",
    "wof:placetype":"postalcode"
},
  "geometry": {"coordinates":[-0.897844,51.203886],"type":"Point"}
}