{
  "type": "Feature",
  "properties": {
    "iso:country":"GB",
    "wof:name":"SK9 5JB",
    "wof:placetype":"postalcode"
},
  "geometry": {"coordinates":[-2.24043461312906,53.3205172070597],"type":"Point"}
}