{
  "type": "Feature",
  "properties": {
    "date:inception_lower": "2011-07-01",
    "date:inception_upper": "2011-07-01",
    "iso:country": "GB",
    "wof:name": "FY8 1FL",
    "wof:placetype": "postalcode"
  },
  "geometry": {"coordinates":[-3.010332,53.742769],"type":"Point"}
}
