{
  "type": "Feature",
  "properties": {
    "iso:country":"GB",
    "wof:name":"FY8 1FL",
    "wof:placetype":"postalcode"
},
  "geometry": {"coordinates":[-3.01057864287691,53.74281507147982],"type":"Point"}
}