{
  "type": "Feature",
  "properties": {
    "iso:country": "GB",
    "wof:name": "AB34 5HJ",
    "wof:placetype": "postalcode"
  },
  "geometry": {"coordinates":[-2.785324,57.074733],"type":"Point"}
}
