{
  "type": "Feature",
  "properties": {
    "iso:country":"GB",
    "wof:name":"AB34 5HJ",
    "wof:placetype":"postalcode"
},
  "geometry": {"coordinates":[-2.78532451855809,57.07473307814421],"type":"Point"}
}