{
  "type": "Feature",
  "properties": {
    "iso:country":"GB",
    "wof:name":"IP10 0NJ",
    "wof:placetype":"postalcode"
},
  "geometry": {"coordinates":[1.3221603453936,52.00566682041342],"type":"Point"}
}