{
  "type": "Feature",
  "properties": {
    "date:inception_lower": "1981-06-01",
    "date:inception_upper": "1981-06-01",
    "iso:country": "GB",
    "wof:name": "YO7 3LA",
    "wof:placetype": "postalcode"
  },
  "geometry": {"coordinates":[-1.415995,54.151234],"type":"Point"}
}
