{
  "type": "Feature",
  "properties": {
    "iso:country":"GB",
    "wof:name":"BL8 1UF",
    "wof:placetype":"postalcode"
},
  "geometry": {"coordinates":[-2.32276688883315,53.60523129541535],"type":"Point"}
}