{
  "type": "Feature",
  "properties": {
    "iso:country":"GB",
    "wof:name":"G40 3RZ",
    "wof:placetype":"postalcode"
},
  "geometry": {"coordinates":[-4.21808570759908,55.84954550221111],"type":"Point"}
}