{
  "type": "Feature",
  "properties": {
    "date:inception_lower": "2003-09-01",
    "date:inception_upper": "2003-09-01",
    "iso:country": "GB",
    "wof:name": "NG9 3SU",
    "wof:placetype": "postalcode"
  },
  "geometry": {"coordinates":[-1.233637,52.93537],"type":"Point"}
}
