{
  "type": "Feature",
  "properties": {
    "iso:country":"GB",
    "wof:name":"NG9 3SU",
    "wof:placetype":"postalcode"
},
  "geometry": {"coordinates":[-1.2336368417277,52.93536963794714],"type":"Point"}
}