{
  "type": "Feature",
  "properties": {
    "iso:country": "GB",
    "wof:name": "SE3 8QN",
    "wof:placetype": "postalcode"
  },
  "geometry": {"coordinates":[0.031913,51.466234],"type":"Point"}
}
