{
  "type": "Feature",
  "properties": {
    "iso:country":"GB",
    "wof:name":"SE3 8QN",
    "wof:placetype":"postalcode"
},
  "geometry": {"coordinates":[0.03191279035763,51.46623379049044],"type":"Point"}
}