{
  "type": "Feature",
  "properties": {
    "iso:country":"GB",
    "wof:name":"SR4 6RG",
    "wof:placetype":"postalcode"
},
  "geometry": {"coordinates":[-1.41926542401269,54.90865658762409],"type":"Point"}
}