{
  "type": "Feature",
  "properties": {
    "iso:country":"GB",
    "wof:name":"NP44 7AU",
    "wof:placetype":"postalcode"
},
  "geometry": {"coordinates":[-3.05683351131088,51.61839788367671],"type":"Point"}
}