{
  "type": "Feature",
  "properties": {
    "iso:country": "GB",
    "wof:name": "NP44 7AU",
    "wof:placetype": "postalcode"
  },
  "geometry": {"coordinates":[-3.056833,51.618398],"type":"Point"}
}
