{
  "type": "Feature",
  "properties": {
    "iso:country":"GB",
    "wof:name":"PO5 1RY",
    "wof:placetype":"postalcode"
},
  "geometry": {"coordinates":[-1.07820251342107,50.79172129434822],"type":"Point"}
}