{
  "type": "Feature",
  "properties": {
    "iso:country": "GB",
    "wof:name": "PO5 1RY",
    "wof:placetype": "postalcode"
  },
  "geometry": {"coordinates":[-1.078145,50.791791],"type":"Point"}
}
