{
  "type": "Feature",
  "properties": {
    "iso:country":"GB",
    "wof:name":"TN4 9DL",
    "wof:placetype":"postalcode"
},
  "geometry": {"coordinates":[0.273011237491,51.15371427692739],"type":"Point"}
}