{
  "type": "Feature",
  "properties": {
    "iso:country":"GB",
    "wof:name":"SN10 5RS",
    "wof:placetype":"postalcode"
},
  "geometry": {"coordinates":[-2.03684034560197,51.31587487330977],"type":"Point"}
}