{
  "type": "Feature",
  "properties": {
    "date:inception_lower": "2007-03-01",
    "date:inception_upper": "2007-03-01",
    "iso:country": "GB",
    "wof:name": "KA7 2UQ",
    "wof:placetype": "postalcode"
  },
  "geometry": {"coordinates":[-4.63917,55.452092],"type":"Point"}
}
