{
  "type": "Feature",
  "properties": {
    "iso:country": "GB",
    "wof:name": "KA7 2UQ",
    "wof:placetype": "postalcode"
  },
  "geometry": {"coordinates":[-4.63917,55.452092],"type":"Point"}
}
