{
  "type": "Feature",
  "properties": {
    "iso:country":"GB",
    "wof:name":"CW11 3PN",
    "wof:placetype":"postalcode"
},
  "geometry": {"coordinates":[-2.40070002611249,53.14722126867066],"type":"Point"}
}