{
  "type": "Feature",
  "properties": {
    "iso:country": "GB",
    "wof:name": "SA15 4DU",
    "wof:placetype": "postalcode"
  },
  "geometry": {"coordinates":[-4.193357,51.686481],"type":"Point"}
}
