{
  "type": "Feature",
  "properties": {
    "date:inception_lower":"1980-01-01",
    "date:inception_upper":"1980-01-31",
    "iso:country":"GB",
    "wof:name":"SA15 4DU",
    "wof:placetype":"postalcode"
},
  "geometry": {"coordinates":[-4.193357,51.686481],"type":"Point"}
}