{
  "type": "Feature",
  "properties": {
    "iso:country":"GB",
    "wof:name":"SA15 4DU",
    "wof:placetype":"postalcode"
},
  "geometry": {"coordinates":[-4.19335718144771,51.6864807817982],"type":"Point"}
}