{
  "type": "Feature",
  "properties": {
    "iso:country":"GB",
    "wof:name":"HX1 1RE",
    "wof:placetype":"postalcode"
},
  "geometry": {"coordinates":[-1.85640485834991,53.72204108245406],"type":"Point"}
}