{
  "type": "Feature",
  "properties": {
    "iso:country": "GB",
    "wof:name": "MK13 8PJ",
    "wof:placetype": "postalcode"
  },
  "geometry": {"coordinates":[-0.780918,52.043645],"type":"Point"}
}
