{
  "type": "Feature",
  "properties": {
    "date:inception_lower": "1992-01-01",
    "date:inception_upper": "1992-01-01",
    "iso:country": "GB",
    "wof:name": "MK13 8PJ",
    "wof:placetype": "postalcode"
  },
  "geometry": {"coordinates":[-0.780918,52.043645],"type":"Point"}
}
