{
  "type": "Feature",
  "properties": {
    "iso:country": "GB",
    "wof:name": "ME14 2PX",
    "wof:placetype": "postalcode"
  },
  "geometry": {"coordinates":[0.512217,51.285425],"type":"Point"}
}
