{
  "type": "Feature",
  "properties": {
    "iso:country":"GB",
    "wof:name":"EH49 6AP",
    "wof:placetype":"postalcode"
},
  "geometry": {"coordinates":[-3.59844924114858,55.97258919057605],"type":"Point"}
}