{
  "type": "Feature",
  "properties": {
    "iso:country":"GB",
    "wof:name":"B95 5AP",
    "wof:placetype":"postalcode"
},
  "geometry": {"coordinates":[-1.78097672254904,52.29027525889015],"type":"Point"}
}