{
  "type": "Feature",
  "properties": {
    "iso:country": "GB",
    "wof:name": "B95 5AP",
    "wof:placetype": "postalcode"
  },
  "geometry": {"coordinates":[-1.780977,52.290275],"type":"Point"}
}
