{
  "type": "Feature",
  "properties": {
    "iso:country":"GB",
    "wof:name":"PA14 6YA",
    "wof:placetype":"postalcode"
},
  "geometry": {"coordinates":[-4.58468711414494,55.92363155788723],"type":"Point"}
}