{
  "type": "Feature",
  "properties": {
    "iso:country":"GB",
    "wof:name":"G82 4HQ",
    "wof:placetype":"postalcode"
},
  "geometry": {"coordinates":[-4.58871608205037,55.95738740569105],"type":"Point"}
}