{
  "type": "Feature",
  "properties": {
    "date:inception_lower":"2013-11-01",
    "date:inception_upper":"2013-11-30",
    "iso:country":"GB",
    "wof:name":"PE2 8FL",
    "wof:placetype":"postalcode"
},
  "geometry": {"coordinates":[-0.216782,52.544352],"type":"Point"}
}