{
  "type": "Feature",
  "properties": {
    "iso:country":"GB",
    "wof:name":"S43 3ST",
    "wof:placetype":"postalcode"
},
  "geometry": {"coordinates":[-1.37288426671968,53.25595739981164],"type":"Point"}
}