{
  "type": "Feature",
  "properties": {
    "date:inception_lower": "2019-07-01",
    "date:inception_upper": "2019-07-01",
    "iso:country": "GB",
    "wof:name": "SG12 8FL",
    "wof:placetype": "postalcode"
  },
  "geometry": {"coordinates":[0.057272,51.807444],"type":"Point"}
}
