{
  "type": "Feature",
  "properties": {
    "iso:country":"GB",
    "wof:name":"PO31 7BH",
    "wof:placetype":"postalcode"
},
  "geometry": {"coordinates":[-1.2968948886995,50.76021365995699],"type":"Point"}
}