{
  "type": "Feature",
  "properties": {
    "date:inception_lower":"1984-02-01",
    "date:inception_upper":"1984-02-29",
    "iso:country":"GB",
    "wof:name":"DN7 4BW",
    "wof:placetype":"postalcode"
},
  "geometry": {"coordinates":[-1.01839,53.571819],"type":"Point"}
}