{
  "type": "Feature",
  "properties": {
    "iso:country":"GB",
    "wof:name":"DN7 4BW",
    "wof:placetype":"postalcode"
},
  "geometry": {"coordinates":[-1.01839046106413,53.57181917943011],"type":"Point"}
}