{
  "type": "Feature",
  "properties": {
    "date:inception_lower":"1997-12-01",
    "date:inception_upper":"1997-12-31",
    "iso:country":"GB",
    "wof:name":"BS30 8AL",
    "wof:placetype":"postalcode"
},
  "geometry": {"coordinates":[-2.48809,51.441889],"type":"Point"}
}