{
  "type": "Feature",
  "properties": {
    "iso:country":"GB",
    "wof:name":"BS30 8AL",
    "wof:placetype":"postalcode"
},
  "geometry": {"coordinates":[-2.48811813710908,51.44187061900605],"type":"Point"}
}