{
  "type": "Feature",
  "properties": {
    "iso:country":"GB",
    "wof:name":"BA1 4AU",
    "wof:placetype":"postalcode"
},
  "geometry": {"coordinates":[-2.38718928595705,51.39455596989526],"type":"Point"}
}