{
  "type": "Feature",
  "properties": {
    "iso:country":"GB",
    "wof:name":"TW8 8AH",
    "wof:placetype":"postalcode"
},
  "geometry": {"coordinates":[-0.30803099132589,51.48344831143951],"type":"Point"}
}