{
  "type": "Feature",
  "properties": {
    "iso:country":"GB",
    "wof:name":"KA8 8AG",
    "wof:placetype":"postalcode"
},
  "geometry": {"coordinates":[-4.63300704438016,55.4680637138193],"type":"Point"}
}