{
  "type": "Feature",
  "properties": {
    "iso:country":"GB",
    "wof:name":"DH8 0JA",
    "wof:placetype":"postalcode"
},
  "geometry": {"coordinates":[-1.85936775363773,54.86719582364663],"type":"Point"}
}