{
  "type": "Feature",
  "properties": {
    "date:inception_lower": "2024-03-01",
    "date:inception_upper": "2024-03-01",
    "iso:country": "GB",
    "wof:name": "PE11 7AD",
    "wof:placetype": "postalcode"
  },
  "geometry": {"coordinates":[-0.171675,52.763646],"type":"Point"}
}
