{
  "type": "Feature",
  "properties": {
    "iso:country":"GB",
    "wof:name":"PE30 2PZ",
    "wof:placetype":"postalcode"
},
  "geometry": {"coordinates":[0.41304060879954,52.75831324861358],"type":"Point"}
}