{
  "type": "Feature",
  "properties": {
    "iso:country":"GB",
    "wof:name":"ME6 5SD",
    "wof:placetype":"postalcode"
},
  "geometry": {"coordinates":[0.43875703159615,51.33627271747955],"type":"Point"}
}