{
  "type": "Feature",
  "properties": {
    "date:inception_lower": "2006-07-01",
    "date:inception_upper": "2006-07-01",
    "iso:country": "GB",
    "wof:name": "ME6 5SD",
    "wof:placetype": "postalcode"
  },
  "geometry": {"coordinates":[0.438212,51.336014],"type":"Point"}
}
