{
  "type": "Feature",
  "properties": {
    "date:inception_lower": "1980-01-01",
    "date:inception_upper": "1980-01-01",
    "iso:country": "GB",
    "wof:name": "PE24 5YD",
    "wof:placetype": "postalcode"
  },
  "geometry": {"coordinates":[0.2913,53.255528],"type":"Point"}
}
