{
  "type": "Feature",
  "properties": {
    "iso:country": "GB",
    "wof:name": "PE24 5YD",
    "wof:placetype": "postalcode"
  },
  "geometry": {"coordinates":[0.2913,53.255528],"type":"Point"}
}
