{
  "type": "Feature",
  "properties": {
    "iso:country":"GB",
    "wof:name":"PE24 5YD",
    "wof:placetype":"postalcode"
},
  "geometry": {"coordinates":[0.29131424467297,53.2554917852034],"type":"Point"}
}