{
  "type": "Feature",
  "properties": {
    "date:inception_lower": "1980-01-01",
    "date:inception_upper": "1980-01-01",
    "iso:country": "GB",
    "wof:name": "HG3 2PU",
    "wof:placetype": "postalcode"
  },
  "geometry": {"coordinates":[-1.681252,54.030069],"type":"Point"}
}
