{
  "type": "Feature",
  "properties": {
    "iso:country":"GB",
    "wof:name":"HG3 2PU",
    "wof:placetype":"postalcode"
},
  "geometry": {"coordinates":[-1.68125158997852,54.03006874176828],"type":"Point"}
}