{
  "type": "Feature",
  "properties": {
    "iso:country":"GB",
    "wof:name":"CO5 0JB",
    "wof:placetype":"postalcode"
},
  "geometry": {"coordinates":[0.76377554916312,51.81330035682158],"type":"Point"}
}