{
  "type": "Feature",
  "properties": {
    "iso:country": "GB",
    "wof:name": "CO5 0JB",
    "wof:placetype": "postalcode"
  },
  "geometry": {"coordinates":[0.763776,51.8133],"type":"Point"}
}
