{
  "type": "Feature",
  "properties": {
    "iso:country": "GB",
    "wof:name": "N1 3BG",
    "wof:placetype": "postalcode"
  },
  "geometry": {"coordinates":[-0.089657,51.541738],"type":"Point"}
}
