{
  "type": "Feature",
  "properties": {
    "iso:country":"GB",
    "wof:name":"N1 3BG",
    "wof:placetype":"postalcode"
},
  "geometry": {"coordinates":[-0.08965685176331,51.5417381011255],"type":"Point"}
}