{
  "type": "Feature",
  "properties": {
    "iso:country":"GB",
    "wof:name":"SO53 2HH",
    "wof:placetype":"postalcode"
},
  "geometry": {"coordinates":[-1.37657612877581,50.98396943824888],"type":"Point"}
}