{
  "type": "Feature",
  "properties": {
    "iso:country": "GB",
    "wof:name": "DN22 0HE",
    "wof:placetype": "postalcode"
  },
  "geometry": {"coordinates":[-0.85067,53.321465],"type":"Point"}
}
