{
  "type": "Feature",
  "properties": {
    "iso:country": "GB",
    "wof:name": "SO32 3LB",
    "wof:placetype": "postalcode"
  },
  "geometry": {"coordinates":[-1.113837,51.004061],"type":"Point"}
}
