{
  "type": "Feature",
  "properties": {
    "iso:country":"GB",
    "wof:name":"SO32 3LB",
    "wof:placetype":"postalcode"
},
  "geometry": {"coordinates":[-1.11383715483465,51.00406117436374],"type":"Point"}
}