{
  "type": "Feature",
  "properties": {
    "iso:country": "GB",
    "wof:name": "PO3 5PA",
    "wof:placetype": "postalcode"
  },
  "geometry": {"coordinates":[-1.054365,50.824183],"type":"Point"}
}
