{
  "type": "Feature",
  "properties": {
    "iso:country":"GB",
    "wof:name":"PO3 5PA",
    "wof:placetype":"postalcode"
},
  "geometry": {"coordinates":[-1.05436479429854,50.82418332616301],"type":"Point"}
}