{
  "type": "Feature",
  "properties": {
    "iso:country":"GB",
    "wof:name":"NN15 6XT",
    "wof:placetype":"postalcode"
},
  "geometry": {"coordinates":[-0.71185337346246,52.37289542739551],"type":"Point"}
}