{
  "type": "Feature",
  "properties": {
    "iso:country":"GB",
    "wof:name":"SN16 9QE",
    "wof:placetype":"postalcode"
},
  "geometry": {"coordinates":[-1.96663309325363,51.61496991203038],"type":"Point"}
}