{
  "type": "Feature",
  "properties": {
    "date:inception_lower": "1988-03-01",
    "date:inception_upper": "1988-03-01",
    "iso:country": "GB",
    "wof:name": "SN16 9QE",
    "wof:placetype": "postalcode"
  },
  "geometry": {"coordinates":[-1.966633,51.61497],"type":"Point"}
}
