{
  "type": "Feature",
  "properties": {
    "date:inception_lower": "1980-01-01",
    "date:inception_upper": "1980-01-01",
    "iso:country": "GB",
    "wof:name": "DN21 4NP",
    "wof:placetype": "postalcode"
  },
  "geometry": {"coordinates":[-0.587634,53.476054],"type":"Point"}
}
