{
  "type": "Feature",
  "properties": {
    "iso:country":"GB",
    "wof:name":"DN21 4NP",
    "wof:placetype":"postalcode"
},
  "geometry": {"coordinates":[-0.58763420462598,53.4760537301172],"type":"Point"}
}