{
  "type": "Feature",
  "properties": {
    "date:inception_lower": "2021-12-01",
    "date:inception_upper": "2021-12-01",
    "iso:country": "GB",
    "wof:name": "LS16 8FU",
    "wof:placetype": "postalcode"
  },
  "geometry": {"coordinates":[-1.577502,53.84502],"type":"Point"}
}
