{
  "type": "Feature",
  "properties": {
    "date:inception_lower": "2020-10-01",
    "date:inception_upper": "2020-10-01",
    "iso:country": "GB",
    "wof:name": "CH4 7FA",
    "wof:placetype": "postalcode"
  },
  "geometry": {"coordinates":[-2.90409,53.167122],"type":"Point"}
}
