{
  "type": "Feature",
  "properties": {
    "iso:country":"GB",
    "wof:name":"CR4 1XT",
    "wof:placetype":"postalcode"
},
  "geometry": {"coordinates":[-0.12671529408958,51.39805872300205],"type":"Point"}
}