{
  "type": "Feature",
  "properties": {
    "iso:country": "GB",
    "wof:name": "CR4 1XT",
    "wof:placetype": "postalcode"
  },
  "geometry": {"coordinates":[-0.126715,51.398059],"type":"Point"}
}
