{
  "type": "Feature",
  "properties": {
    "date:inception_lower": "2017-01-01",
    "date:inception_upper": "2017-01-01",
    "iso:country": "GB",
    "wof:name": "WF2 9FA",
    "wof:placetype": "postalcode"
  },
  "geometry": {"coordinates":[-1.538621,53.681618],"type":"Point"}
}
