{
  "type": "Feature",
  "properties": {
    "iso:country": "GB",
    "wof:name": "NW5 4PN",
    "wof:placetype": "postalcode"
  },
  "geometry": {"coordinates":[-0.152602,51.551064],"type":"Point"}
}
