{
  "type": "Feature",
  "properties": {
    "iso:country":"GB",
    "wof:name":"NW5 4PN",
    "wof:placetype":"postalcode"
},
  "geometry": {"coordinates":[-0.15260208555918,51.5510642169462],"type":"Point"}
}