{
  "type": "Feature",
  "properties": {
    "date:inception_lower": "1980-01-01",
    "date:inception_upper": "1980-01-01",
    "iso:country": "GB",
    "wof:name": "PE10 0NG",
    "wof:placetype": "postalcode"
  },
  "geometry": {"coordinates":[-0.444279,52.794449],"type":"Point"}
}
