{
  "type": "Feature",
  "properties": {
    "date:inception_lower": "1994-12-01",
    "date:inception_upper": "1994-12-01",
    "iso:country": "GB",
    "wof:name": "HP9 1QH",
    "wof:placetype": "postalcode"
  },
  "geometry": {"coordinates":[-0.643166,51.609574],"type":"Point"}
}
