{
  "type": "Feature",
  "properties": {
    "iso:country":"GB",
    "wof:name":"HP9 1QH",
    "wof:placetype":"postalcode"
},
  "geometry": {"coordinates":[-0.64316574519478,51.60957350969255],"type":"Point"}
}