{
  "type": "Feature",
  "properties": {
    "iso:country":"GB",
    "wof:name":"CF44 6RE",
    "wof:placetype":"postalcode"
},
  "geometry": {"coordinates":[-3.42621581172422,51.70113613777147],"type":"Point"}
}