{
  "type": "Feature",
  "properties": {
    "iso:country":"GB",
    "wof:name":"ME9 0EN",
    "wof:placetype":"postalcode"
},
  "geometry": {"coordinates":[0.79309565832416,51.31944201996334],"type":"Point"}
}