{
  "type": "Feature",
  "properties": {
    "date:inception_lower": "1980-01-01",
    "date:inception_upper": "1980-01-01",
    "iso:country": "GB",
    "wof:name": "BN13 2RR",
    "wof:placetype": "postalcode"
  },
  "geometry": {"coordinates":[-0.407934,50.834637],"type":"Point"}
}
