{
  "type": "Feature",
  "properties": {
    "date:inception_lower": "1985-04-01",
    "date:inception_upper": "1985-04-01",
    "iso:country": "GB",
    "wof:name": "TQ13 0LP",
    "wof:placetype": "postalcode"
  },
  "geometry": {"coordinates":[-3.595122,50.602883],"type":"Point"}
}
