{
  "type": "Feature",
  "properties": {
    "iso:country":"GB",
    "wof:name":"B12 9DR",
    "wof:placetype":"postalcode"
},
  "geometry": {"coordinates":[-1.88582221520388,52.46009350243171],"type":"Point"}
}