{
  "type": "Feature",
  "properties": {
    "iso:country":"GB",
    "wof:name":"SG8 5HG",
    "wof:placetype":"postalcode"
},
  "geometry": {"coordinates":[-0.0278617756871,52.05491051756458],"type":"Point"}
}