{
  "type": "Feature",
  "properties": {
    "iso:country":"GB",
    "wof:name":"CT19 5PP",
    "wof:placetype":"postalcode"
},
  "geometry": {"coordinates":[1.17788286552734,51.09147268853004],"type":"Point"}
}