{
  "type": "Feature",
  "properties": {
    "iso:country":"GB",
    "wof:name":"WN8 7DH",
    "wof:placetype":"postalcode"
},
  "geometry": {"coordinates":[-2.77479161963218,53.59292857443931],"type":"Point"}
}