{
  "type": "Feature",
  "properties": {
    "iso:country":"GB",
    "wof:name":"BN2 5HG",
    "wof:placetype":"postalcode"
},
  "geometry": {"coordinates":[-0.10599476481102,50.82755418956558],"type":"Point"}
}