{
  "type": "Feature",
  "properties": {
    "iso:country": "GB",
    "wof:name": "BN2 5HG",
    "wof:placetype": "postalcode"
  },
  "geometry": {"coordinates":[-0.105995,50.827554],"type":"Point"}
}
