{
  "type": "Feature",
  "properties": {
    "date:inception_lower":"1984-10-01",
    "date:inception_upper":"1984-10-31",
    "iso:country":"GB",
    "wof:name":"DT11 7UG",
    "wof:placetype":"postalcode"
},
  "geometry": {"coordinates":[-2.158284,50.868677],"type":"Point"}
}