{
  "type": "Feature",
  "properties": {
    "date:inception_lower": "1994-05-01",
    "date:inception_upper": "1994-05-01",
    "iso:country": "GB",
    "wof:name": "M40 5LS",
    "wof:placetype": "postalcode"
  },
  "geometry": {"coordinates":[-2.194242,53.504885],"type":"Point"}
}
