{
  "type": "Feature",
  "properties": {
    "iso:country":"GB",
    "wof:name":"M40 5LS",
    "wof:placetype":"postalcode"
},
  "geometry": {"coordinates":[-2.19424188393936,53.5048847562554],"type":"Point"}
}