{
  "type": "Feature",
  "properties": {
    "iso:country":"GB",
    "wof:name":"TR11 5LW",
    "wof:placetype":"postalcode"
},
  "geometry": {"coordinates":[-5.13601928380581,50.1108063171062],"type":"Point"}
}