{
  "type": "Feature",
  "properties": {
    "iso:country": "GB",
    "wof:name": "CH7 5DS",
    "wof:placetype": "postalcode"
  },
  "geometry": {"coordinates":[-3.189402,53.170963],"type":"Point"}
}
