{
  "type": "Feature",
  "properties": {
    "iso:country":"GB",
    "wof:name":"CH7 5DS",
    "wof:placetype":"postalcode"
},
  "geometry": {"coordinates":[-3.18940212599401,53.17096295186563],"type":"Point"}
}