{
  "type": "Feature",
  "properties": {
    "date:inception_lower": "1986-04-01",
    "date:inception_upper": "1986-04-01",
    "iso:country": "GB",
    "wof:name": "NP4 0LS",
    "wof:placetype": "postalcode"
  },
  "geometry": {"coordinates":[-3.018915,51.690468],"type":"Point"}
}
