{
  "type": "Feature",
  "properties": {
    "iso:country":"GB",
    "wof:name":"NP4 0LS",
    "wof:placetype":"postalcode"
},
  "geometry": {"coordinates":[-3.0189151782833,51.69046777788075],"type":"Point"}
}