{
  "type": "Feature",
  "properties": {
    "iso:country": "GB",
    "wof:name": "NP4 0LS",
    "wof:placetype": "postalcode"
  },
  "geometry": {"coordinates":[-3.018915,51.690468],"type":"Point"}
}
