{
  "type": "Feature",
  "properties": {
    "iso:country":"GB",
    "wof:name":"M34 6FN",
    "wof:placetype":"postalcode"
},
  "geometry": {"coordinates":[-2.1091834901996,53.44838365653197],"type":"Point"}
}