{
  "type": "Feature",
  "properties": {
    "date:inception_lower": "1992-08-01",
    "date:inception_upper": "1992-08-01",
    "iso:country": "GB",
    "wof:name": "CV9 3AX",
    "wof:placetype": "postalcode"
  },
  "geometry": {"coordinates":[-1.543845,52.584653],"type":"Point"}
}
