{
  "type": "Feature",
  "properties": {
    "iso:country":"GB",
    "wof:name":"GL12 7LW",
    "wof:placetype":"postalcode"
},
  "geometry": {"coordinates":[-2.34630617201919,51.63303013192651],"type":"Point"}
}