{
  "type": "Feature",
  "properties": {
    "iso:country": "GB",
    "wof:name": "GL12 7LW",
    "wof:placetype": "postalcode"
  },
  "geometry": {"coordinates":[-2.346306,51.63303],"type":"Point"}
}
