{
  "type": "Feature",
  "properties": {
    "iso:country": "GB",
    "wof:name": "CH5 4XE",
    "wof:placetype": "postalcode"
  },
  "geometry": {"coordinates":[-3.068954,53.222014],"type":"Point"}
}
