{
  "type": "Feature",
  "properties": {
    "iso:country":"GB",
    "wof:name":"CH5 4XE",
    "wof:placetype":"postalcode"
},
  "geometry": {"coordinates":[-3.06895425974127,53.22201367129544],"type":"Point"}
}