{
  "type": "Feature",
  "properties": {
    "iso:country": "GB",
    "wof:name": "OX12 9PJ",
    "wof:placetype": "postalcode"
  },
  "geometry": {"coordinates":[-1.493658,51.587244],"type":"Point"}
}
