{
  "type": "Feature",
  "properties": {
    "date:inception_lower": "1986-07-01",
    "date:inception_upper": "1986-07-01",
    "iso:country": "GB",
    "wof:name": "OX12 9PJ",
    "wof:placetype": "postalcode"
  },
  "geometry": {"coordinates":[-1.493588,51.587001],"type":"Point"}
}
