{
  "type": "Feature",
  "properties": {
    "iso:country":"GB",
    "wof:name":"OX12 9PJ",
    "wof:placetype":"postalcode"
},
  "geometry": {"coordinates":[-1.49610691063567,51.58641674018471],"type":"Point"}
}