{
  "type": "Feature",
  "properties": {
    "iso:country": "GB",
    "wof:name": "IG7 5JQ",
    "wof:placetype": "postalcode"
  },
  "geometry": {"coordinates":[0.091131,51.60655],"type":"Point"}
}
