{
  "type": "Feature",
  "properties": {
    "iso:country":"GB",
    "wof:name":"IG7 5JQ",
    "wof:placetype":"postalcode"
},
  "geometry": {"coordinates":[0.09113064143932,51.60654961182446],"type":"Point"}
}