{
  "type": "Feature",
  "properties": {
    "date:inception_lower": "1988-03-01",
    "date:inception_upper": "1988-03-01",
    "iso:country": "GB",
    "wof:name": "IG7 5JQ",
    "wof:placetype": "postalcode"
  },
  "geometry": {"coordinates":[0.091131,51.60655],"type":"Point"}
}
