{
  "type": "Feature",
  "properties": {
    "date:inception_lower":"2016-03-01",
    "date:inception_upper":"2016-03-31",
    "iso:country":"GB",
    "wof:name":"IG11 8PJ",
    "wof:placetype":"postalcode"
},
  "geometry": {"coordinates":[0.080563,51.540587],"type":"Point"}
}