{
  "type": "Feature",
  "properties": {
    "iso:country":"GB",
    "wof:name":"IG11 8PJ",
    "wof:placetype":"postalcode"
},
  "geometry": {"coordinates":[0.08056297138159,51.54058716498186],"type":"Point"}
}