{
  "type": "Feature",
  "properties": {
    "iso:country": "GB",
    "wof:name": "NE5 4DB",
    "wof:placetype": "postalcode"
  },
  "geometry": {"coordinates":[-1.682945,55.00226],"type":"Point"}
}
