{
  "type": "Feature",
  "properties": {
    "iso:country":"GB",
    "wof:name":"NE5 4DB",
    "wof:placetype":"postalcode"
},
  "geometry": {"coordinates":[-1.68294553000079,55.00226038685677],"type":"Point"}
}