{
  "type": "Feature",
  "properties": {
    "iso:country":"GB",
    "wof:name":"PE8 6JJ",
    "wof:placetype":"postalcode"
},
  "geometry": {"coordinates":[-0.41573268903674,52.5821644636306],"type":"Point"}
}