{
  "type": "Feature",
  "properties": {
    "iso:country": "GB",
    "wof:name": "PE8 6JJ",
    "wof:placetype": "postalcode"
  },
  "geometry": {"coordinates":[-0.415615,52.582226],"type":"Point"}
}
