{
  "type": "Feature",
  "properties": {
    "date:inception_lower": "1980-01-01",
    "date:inception_upper": "1980-01-01",
    "iso:country": "GB",
    "wof:name": "PE8 6JJ",
    "wof:placetype": "postalcode"
  },
  "geometry": {"coordinates":[-0.415615,52.582226],"type":"Point"}
}
