{
  "type": "Feature",
  "properties": {
    "iso:country":"GB",
    "wof:name":"PL9 8UY",
    "wof:placetype":"postalcode"
},
  "geometry": {"coordinates":[-4.06528155389872,50.35699522854593],"type":"Point"}
}