{
  "type": "Feature",
  "properties": {
    "iso:country": "GB",
    "wof:name": "KA1 3NT",
    "wof:placetype": "postalcode"
  },
  "geometry": {"coordinates":[-4.490738,55.593987],"type":"Point"}
}
