{
  "type": "Feature",
  "properties": {
    "iso:country":"GB",
    "wof:name":"DA1 1XB",
    "wof:placetype":"postalcode"
},
  "geometry": {"coordinates":[0.2332302555168,51.4451698813278],"type":"Point"}
}