{
  "type": "Feature",
  "properties": {
    "date:inception_lower": "2008-01-01",
    "date:inception_upper": "2008-01-01",
    "iso:country": "GB",
    "wof:name": "DA9 9TX",
    "wof:placetype": "postalcode"
  },
  "geometry": {"coordinates":[0.274817,51.44392],"type":"Point"}
}
