{
  "type": "Feature",
  "properties": {
    "iso:country": "GB",
    "wof:name": "DA9 9TX",
    "wof:placetype": "postalcode"
  },
  "geometry": {"coordinates":[0.274817,51.44392],"type":"Point"}
}
