{
  "type": "Feature",
  "properties": {
    "iso:country":"GB",
    "wof:name":"DA9 9TX",
    "wof:placetype":"postalcode"
},
  "geometry": {"coordinates":[0.27481678037264,51.4439204264328],"type":"Point"}
}