{
  "type": "Feature",
  "properties": {
    "iso:country": "GB",
    "wof:name": "EN2 7RW",
    "wof:placetype": "postalcode"
  },
  "geometry": {"coordinates":[-0.113123,51.648615],"type":"Point"}
}
