{
  "type": "Feature",
  "properties": {
    "date:inception_lower":"1980-01-01",
    "date:inception_upper":"1980-01-31",
    "iso:country":"GB",
    "wof:name":"EN2 7RW",
    "wof:placetype":"postalcode"
},
  "geometry": {"coordinates":[-0.113123,51.648615],"type":"Point"}
}