{
  "type": "Feature",
  "properties": {
    "iso:country":"GB",
    "wof:name":"EN2 7RW",
    "wof:placetype":"postalcode"
},
  "geometry": {"coordinates":[-0.11312305558348,51.64861516921199],"type":"Point"}
}