{
  "type": "Feature",
  "properties": {
    "date:inception_lower": "1980-01-01",
    "date:inception_upper": "1980-01-01",
    "iso:country": "GB",
    "wof:name": "DE1 3HY",
    "wof:placetype": "postalcode"
  },
  "geometry": {"coordinates":[-1.481957,52.926391],"type":"Point"}
}
