{
  "type": "Feature",
  "properties": {
    "iso:country": "GB",
    "wof:name": "DE1 3HY",
    "wof:placetype": "postalcode"
  },
  "geometry": {"coordinates":[-1.482065,52.926374],"type":"Point"}
}
