{
  "type": "Feature",
  "properties": {
    "iso:country":"GB",
    "wof:name":"NR21 7DY",
    "wof:placetype":"postalcode"
},
  "geometry": {"coordinates":[0.82597578139841,52.82048142262658],"type":"Point"}
}