{
  "type": "Feature",
  "properties": {
    "iso:country":"GB",
    "wof:name":"B79 8HU",
    "wof:placetype":"postalcode"
},
  "geometry": {"coordinates":[-1.69825851150899,52.64361623117709],"type":"Point"}
}