{
  "type": "Feature",
  "properties": {
    "date:inception_lower":"1995-01-01",
    "date:inception_upper":"1995-01-31",
    "iso:country":"GB",
    "wof:name":"NN12 8LZ",
    "wof:placetype":"postalcode"
},
  "geometry": {"coordinates":[-1.048887,52.143784],"type":"Point"}
}