{
  "type": "Feature",
  "properties": {
    "iso:country": "GB",
    "wof:name": "NN12 8LZ",
    "wof:placetype": "postalcode"
  },
  "geometry": {"coordinates":[-1.048887,52.143784],"type":"Point"}
}
