{
  "type": "Feature",
  "properties": {
    "date:inception_lower": "2019-02-01",
    "date:inception_upper": "2019-02-01",
    "iso:country": "GB",
    "wof:name": "DN10 5EY",
    "wof:placetype": "postalcode"
  },
  "geometry": {"coordinates":[-0.974284,53.400475],"type":"Point"}
}
