{
  "type": "Feature",
  "properties": {
    "iso:country": "GB",
    "wof:name": "NG18 3GZ",
    "wof:placetype": "postalcode"
  },
  "geometry": {"coordinates":[-1.161161,53.134552],"type":"Point"}
}
