{
  "type": "Feature",
  "properties": {
    "iso:country":"GB",
    "wof:name":"NG18 3GZ",
    "wof:placetype":"postalcode"
},
  "geometry": {"coordinates":[-1.16116135722048,53.13455234831382],"type":"Point"}
}