{
  "type": "Feature",
  "properties": {
    "iso:country":"GB",
    "wof:name":"S63 9DT",
    "wof:placetype":"postalcode"
},
  "geometry": {"coordinates":[-1.30888142548543,53.53162141040842],"type":"Point"}
}