{
  "type": "Feature",
  "properties": {
    "iso:country":"GB",
    "wof:name":"KY12 9AQ",
    "wof:placetype":"postalcode"
},
  "geometry": {"coordinates":[-3.46329086471415,56.07834998985984],"type":"Point"}
}