{
  "type": "Feature",
  "properties": {
    "iso:country":"GB",
    "wof:name":"WF8 3SN",
    "wof:placetype":"postalcode"
},
  "geometry": {"coordinates":[-1.20372852703807,53.64488825364625],"type":"Point"}
}