{
  "type": "Feature",
  "properties": {
    "date:inception_lower": "1980-01-01",
    "date:inception_upper": "1980-01-01",
    "iso:country": "GB",
    "wof:name": "IG1 2QN",
    "wof:placetype": "postalcode"
  },
  "geometry": {"coordinates":[0.078964,51.549491],"type":"Point"}
}
