{
  "type": "Feature",
  "properties": {
    "iso:country": "GB",
    "wof:name": "IG1 2QN",
    "wof:placetype": "postalcode"
  },
  "geometry": {"coordinates":[0.078964,51.549491],"type":"Point"}
}
