{
  "type": "Feature",
  "properties": {
    "iso:country":"GB",
    "wof:name":"BS31 1JB",
    "wof:placetype":"postalcode"
},
  "geometry": {"coordinates":[-2.49312480196205,51.40310460523764],"type":"Point"}
}