{
  "type": "Feature",
  "properties": {
    "date:inception_lower":"1980-01-01",
    "date:inception_upper":"1980-01-31",
    "iso:country":"GB",
    "wof:name":"PE11 2EE",
    "wof:placetype":"postalcode"
},
  "geometry": {"coordinates":[-0.141079,52.787677],"type":"Point"}
}