{
  "type": "Feature",
  "properties": {
    "iso:country":"GB",
    "wof:name":"BS20 7RZ",
    "wof:placetype":"postalcode"
},
  "geometry": {"coordinates":[-2.75325515911752,51.45724487694884],"type":"Point"}
}