{
  "type": "Feature",
  "properties": {
    "date:inception_lower":"1992-01-01",
    "date:inception_upper":"1992-01-31",
    "iso:country":"GB",
    "wof:name":"RH12 1RA",
    "wof:placetype":"postalcode"
},
  "geometry": {"coordinates":[-0.325837,51.063235],"type":"Point"}
}