{
  "type": "Feature",
  "properties": {
    "iso:country":"GB",
    "wof:name":"DN14 8DT",
    "wof:placetype":"postalcode"
},
  "geometry": {"coordinates":[-0.85890422751896,53.64472360847089],"type":"Point"}
}