{
  "type": "Feature",
  "properties": {
    "iso:country":"GB",
    "wof:name":"NN9 5ES",
    "wof:placetype":"postalcode"
},
  "geometry": {"coordinates":[-0.64401373561785,52.33991367067939],"type":"Point"}
}