{
  "type": "Feature",
  "properties": {
    "iso:country": "GB",
    "wof:name": "SG18 8XT",
    "wof:placetype": "postalcode"
  },
  "geometry": {"coordinates":[-0.212819,52.056271],"type":"Point"}
}
