{
  "type": "Feature",
  "properties": {
    "date:inception_lower": "2018-05-01",
    "date:inception_upper": "2018-05-01",
    "iso:country": "GB",
    "wof:name": "SG18 8XT",
    "wof:placetype": "postalcode"
  },
  "geometry": {"coordinates":[-0.212819,52.056271],"type":"Point"}
}
