{
  "type": "Feature",
  "properties": {
    "iso:country": "GB",
    "wof:name": "EN3 4LX",
    "wof:placetype": "postalcode"
  },
  "geometry": {"coordinates":[-0.040833,51.642593],"type":"Point"}
}
