{
  "type": "Feature",
  "properties": {
    "iso:country":"GB",
    "wof:name":"B10 9TB",
    "wof:placetype":"postalcode"
},
  "geometry": {"coordinates":[-1.8425068698902,52.46887203124543],"type":"Point"}
}