{
  "type": "Feature",
  "properties": {
    "date:inception_lower": "1986-01-01",
    "date:inception_upper": "1986-01-01",
    "iso:country": "GB",
    "wof:name": "SO43 7BQ",
    "wof:placetype": "postalcode"
  },
  "geometry": {"coordinates":[-1.568831,50.873233],"type":"Point"}
}
