{
  "type": "Feature",
  "properties": {
    "date:inception_lower": "2024-09-01",
    "date:inception_upper": "2024-09-01",
    "iso:country": "GB",
    "wof:name": "L26 0AH",
    "wof:placetype": "postalcode"
  },
  "geometry": {"coordinates":[-2.817349,53.35606],"type":"Point"}
}
