{
  "type": "Feature",
  "properties": {
    "iso:country": "GB",
    "wof:name": "B66 2RT",
    "wof:placetype": "postalcode"
  },
  "geometry": {"coordinates":[-1.952942,52.494238],"type":"Point"}
}
