{
  "type": "Feature",
  "properties": {
    "iso:country": "GB",
    "wof:name": "EH54 5BF",
    "wof:placetype": "postalcode"
  },
  "geometry": {"coordinates":[-3.505058,55.912387],"type":"Point"}
}
