{
  "type": "Feature",
  "properties": {
    "iso:country":"GB",
    "wof:name":"EH54 5BF",
    "wof:placetype":"postalcode"
},
  "geometry": {"coordinates":[-3.50471443893762,55.91250340290276],"type":"Point"}
}