{
  "type": "Feature",
  "properties": {
    "iso:country": "GB",
    "wof:name": "NE38 9DN",
    "wof:placetype": "postalcode"
  },
  "geometry": {"coordinates":[-1.537305,54.875841],"type":"Point"}
}
