{
  "type": "Feature",
  "properties": {
    "iso:country":"GB",
    "wof:name":"NE38 9DN",
    "wof:placetype":"postalcode"
},
  "geometry": {"coordinates":[-1.53730546923557,54.87584144015693],"type":"Point"}
}