{
  "type": "Feature",
  "properties": {
    "iso:country": "GB",
    "wof:name": "DN14 8AB",
    "wof:placetype": "postalcode"
  },
  "geometry": {"coordinates":[-0.86228,53.689582],"type":"Point"}
}
