{
  "type": "Feature",
  "properties": {
    "iso:country": "GB",
    "wof:name": "PR7 1EN",
    "wof:placetype": "postalcode"
  },
  "geometry": {"coordinates":[-2.630505,53.657818],"type":"Point"}
}
