{
  "type": "Feature",
  "properties": {
    "iso:country":"GB",
    "wof:name":"SO30 3FR",
    "wof:placetype":"postalcode"
},
  "geometry": {"coordinates":[-1.33317051256271,50.9310791718251],"type":"Point"}
}