{
  "type": "Feature",
  "properties": {
    "iso:country": "GB",
    "wof:name": "SO30 3FR",
    "wof:placetype": "postalcode"
  },
  "geometry": {"coordinates":[-1.33316,50.93107],"type":"Point"}
}
