{
  "type": "Feature",
  "properties": {
    "iso:country":"GB",
    "wof:name":"LE8 0SF",
    "wof:placetype":"postalcode"
},
  "geometry": {"coordinates":[-0.99159634955701,52.54035194121634],"type":"Point"}
}