{
  "type": "Feature",
  "properties": {
    "iso:country": "GB",
    "wof:name": "BA1 8DR",
    "wof:placetype": "postalcode"
  },
  "geometry": {"coordinates":[-2.361696,51.404277],"type":"Point"}
}
