{
  "type": "Feature",
  "properties": {
    "iso:country":"GB",
    "wof:name":"BA1 8DR",
    "wof:placetype":"postalcode"
},
  "geometry": {"coordinates":[-2.36169629212379,51.40427653432202],"type":"Point"}
}