{
  "type": "Feature",
  "properties": {
    "iso:country": "GB",
    "wof:name": "PE33 0PX",
    "wof:placetype": "postalcode"
  },
  "geometry": {"coordinates":[0.406743,52.707252],"type":"Point"}
}
