{
  "type": "Feature",
  "properties": {
    "iso:country":"GB",
    "wof:name":"S45 9HJ",
    "wof:placetype":"postalcode"
},
  "geometry": {"coordinates":[-1.40814367864935,53.16324543928582],"type":"Point"}
}