{
  "type": "Feature",
  "properties": {
    "iso:country": "GB",
    "wof:name": "PO1 4HL",
    "wof:placetype": "postalcode"
  },
  "geometry": {"coordinates":[-1.081497,50.803913],"type":"Point"}
}
