{
  "type": "Feature",
  "properties": {
    "date:inception_lower": "1980-01-01",
    "date:inception_upper": "1980-01-01",
    "iso:country": "GB",
    "wof:name": "CO15 4AQ",
    "wof:placetype": "postalcode"
  },
  "geometry": {"coordinates":[1.16246,51.80307],"type":"Point"}
}
