{
  "type": "Feature",
  "properties": {
    "iso:country": "GB",
    "wof:name": "S66 2HZ",
    "wof:placetype": "postalcode"
  },
  "geometry": {"coordinates":[-1.286508,53.425604],"type":"Point"}
}
