{
  "type": "Feature",
  "properties": {
    "iso:country":"GB",
    "wof:name":"S66 2HZ",
    "wof:placetype":"postalcode"
},
  "geometry": {"coordinates":[-1.28650783311111,53.42560387139234],"type":"Point"}
}