{
  "type": "Feature",
  "properties": {
    "iso:country": "GB",
    "wof:name": "SW6 3QB",
    "wof:placetype": "postalcode"
  },
  "geometry": {"coordinates":[-0.202682,51.471243],"type":"Point"}
}
