{
  "type": "Feature",
  "properties": {
    "date:inception_lower": "1998-12-01",
    "date:inception_upper": "1998-12-01",
    "iso:country": "GB",
    "wof:name": "IV36 3YD",
    "wof:placetype": "postalcode"
  },
  "geometry": {"coordinates":[-3.601979,57.655783],"type":"Point"}
}
