{
  "type": "Feature",
  "properties": {
    "iso:country":"GB",
    "wof:name":"DL9 4EF",
    "wof:placetype":"postalcode"
},
  "geometry": {"coordinates":[-1.71047564098194,54.3718249753471],"type":"Point"}
}