{
  "type": "Feature",
  "properties": {
    "iso:country":"GB",
    "wof:name":"LS18 4LR",
    "wof:placetype":"postalcode"
},
  "geometry": {"coordinates":[-1.63334483472148,53.83024110704545],"type":"Point"}
}