{
  "type": "Feature",
  "properties": {
    "iso:country":"GB",
    "wof:name":"BN22 0RJ",
    "wof:placetype":"postalcode"
},
  "geometry": {"coordinates":[0.25521132003584,50.80896150694712],"type":"Point"}
}