{
  "type": "Feature",
  "properties": {
    "iso:country":"GB",
    "wof:name":"EC3A 3BA",
    "wof:placetype":"postalcode"
},
  "geometry": {"coordinates":[-0.07944805040643,51.5136135521095],"type":"Point"}
}