{
  "type": "Feature",
  "properties": {
    "date:inception_lower":"2004-09-01",
    "date:inception_upper":"2004-09-30",
    "iso:country":"GB",
    "wof:name":"TN23 3QZ",
    "wof:placetype":"postalcode"
},
  "geometry": {"coordinates":[0.84713,51.155092],"type":"Point"}
}