{
  "type": "Feature",
  "properties": {
    "date:inception_lower":"1999-12-01",
    "date:inception_upper":"1999-12-31",
    "iso:country":"GB",
    "wof:name":"IP6 0DW",
    "wof:placetype":"postalcode"
},
  "geometry": {"coordinates":[1.115771,52.103112],"type":"Point"}
}