{
  "type": "Feature",
  "properties": {
    "iso:country": "GB",
    "wof:name": "IP6 0DW",
    "wof:placetype": "postalcode"
  },
  "geometry": {"coordinates":[1.115771,52.103112],"type":"Point"}
}
