{
  "type": "Feature",
  "properties": {
    "iso:country":"GB",
    "wof:name":"IP27 0DN",
    "wof:placetype":"postalcode"
},
  "geometry": {"coordinates":[0.6358162269528,52.44736550195567],"type":"Point"}
}