{
  "type": "Feature",
  "properties": {
    "iso:country":"GB",
    "wof:name":"WR13 6QL",
    "wof:placetype":"postalcode"
},
  "geometry": {"coordinates":[-2.35994472361208,52.08208728544904],"type":"Point"}
}