{
  "type": "Feature",
  "properties": {
    "date:inception_lower":"2000-10-01",
    "date:inception_upper":"2000-10-31",
    "iso:country":"GB",
    "wof:name":"WD3 8NB",
    "wof:placetype":"postalcode"
},
  "geometry": {"coordinates":[-0.495671,51.644104],"type":"Point"}
}