{
  "type": "Feature",
  "properties": {
    "iso:country": "GB",
    "wof:name": "NG13 8DS",
    "wof:placetype": "postalcode"
  },
  "geometry": {"coordinates":[-0.94784,52.952224],"type":"Point"}
}
