{
  "type": "Feature",
  "properties": {
    "iso:country":"GB",
    "wof:name":"NG13 8DS",
    "wof:placetype":"postalcode"
},
  "geometry": {"coordinates":[-0.94783989430134,52.95222354143842],"type":"Point"}
}