{
  "type": "Feature",
  "properties": {
    "iso:country": "GB",
    "wof:name": "PE1 3RS",
    "wof:placetype": "postalcode"
  },
  "geometry": {"coordinates":[-0.253211,52.595145],"type":"Point"}
}
