{
  "type": "Feature",
  "properties": {
    "date:inception_lower":"1987-10-01",
    "date:inception_upper":"1987-10-31",
    "iso:country":"GB",
    "wof:name":"PE1 3RS",
    "wof:placetype":"postalcode"
},
  "geometry": {"coordinates":[-0.253211,52.595145],"type":"Point"}
}