{
  "type": "Feature",
  "properties": {
    "iso:country":"GB",
    "wof:name":"PE1 3RS",
    "wof:placetype":"postalcode"
},
  "geometry": {"coordinates":[-0.25321153878914,52.59514510666168],"type":"Point"}
}