{
  "type": "Feature",
  "properties": {
    "iso:country": "GB",
    "wof:name": "CV23 8DY",
    "wof:placetype": "postalcode"
  },
  "geometry": {"coordinates":[-1.348855,52.304058],"type":"Point"}
}
