{
  "type": "Feature",
  "properties": {
    "iso:country":"GB",
    "wof:name":"CV23 8DY",
    "wof:placetype":"postalcode"
},
  "geometry": {"coordinates":[-1.34885487397386,52.30405788745749],"type":"Point"}
}