{
  "type": "Feature",
  "properties": {
    "iso:country": "GB",
    "wof:name": "PO15 7LG",
    "wof:placetype": "postalcode"
  },
  "geometry": {"coordinates":[-1.251121,50.882283],"type":"Point"}
}
