{
  "type": "Feature",
  "properties": {
    "date:inception_lower": "2022-09-01",
    "date:inception_upper": "2022-09-01",
    "iso:country": "GB",
    "wof:name": "TA1 9QF",
    "wof:placetype": "postalcode"
  },
  "geometry": {"coordinates":[-3.109655,51.023437],"type":"Point"}
}
