{
  "type": "Feature",
  "properties": {
    "date:inception_lower":"1980-01-01",
    "date:inception_upper":"1980-01-31",
    "iso:country":"GB",
    "wof:name":"TW11 0QA",
    "wof:placetype":"postalcode"
},
  "geometry": {"coordinates":[-0.349589,51.428962],"type":"Point"}
}