{
  "type": "Feature",
  "properties": {
    "iso:country": "GB",
    "wof:name": "TW11 0QA",
    "wof:placetype": "postalcode"
  },
  "geometry": {"coordinates":[-0.349589,51.428962],"type":"Point"}
}
