{
  "type": "Feature",
  "properties": {
    "date:inception_lower": "1980-01-01",
    "date:inception_upper": "1980-01-01",
    "iso:country": "GB",
    "wof:name": "GL7 1BS",
    "wof:placetype": "postalcode"
  },
  "geometry": {"coordinates":[-1.955241,51.714903],"type":"Point"}
}
