{
  "type": "Feature",
  "properties": {
    "iso:country":"GB",
    "wof:name":"GL7 1BS",
    "wof:placetype":"postalcode"
},
  "geometry": {"coordinates":[-1.95524126165391,51.71490344717282],"type":"Point"}
}