{
  "type": "Feature",
  "properties": {
    "iso:country":"GB",
    "wof:name":"AB54 6BT",
    "wof:placetype":"postalcode"
},
  "geometry": {"coordinates":[-2.64965056632927,57.49981531748359],"type":"Point"}
}