{
  "type": "Feature",
  "properties": {
    "date:inception_lower":"1990-08-01",
    "date:inception_upper":"1990-08-31",
    "iso:country":"GB",
    "wof:name":"AB54 6BT",
    "wof:placetype":"postalcode"
},
  "geometry": {"coordinates":[-2.649651,57.499815],"type":"Point"}
}