{
  "type": "Feature",
  "properties": {
    "iso:country": "GB",
    "wof:name": "AB54 6BT",
    "wof:placetype": "postalcode"
  },
  "geometry": {"coordinates":[-2.649651,57.499815],"type":"Point"}
}
