{
  "type": "Feature",
  "properties": {
    "iso:country": "GB",
    "wof:name": "WV16 5JN",
    "wof:placetype": "postalcode"
  },
  "geometry": {"coordinates":[-2.414978,52.51523],"type":"Point"}
}
