{
  "type": "Feature",
  "properties": {
    "iso:country":"GB",
    "wof:name":"CO16 7HE",
    "wof:placetype":"postalcode"
},
  "geometry": {"coordinates":[1.13989008594026,51.80190963165602],"type":"Point"}
}