{
  "type": "Feature",
  "properties": {
    "iso:country": "GB",
    "wof:name": "CO16 7HE",
    "wof:placetype": "postalcode"
  },
  "geometry": {"coordinates":[1.13989,51.80191],"type":"Point"}
}
