{
  "type": "Feature",
  "properties": {
    "date:inception_lower":"1980-01-01",
    "date:inception_upper":"1980-01-31",
    "iso:country":"GB",
    "wof:name":"NE61 3SE",
    "wof:placetype":"postalcode"
},
  "geometry": {"coordinates":[-1.756968,55.188478],"type":"Point"}
}