{
  "type": "Feature",
  "properties": {
    "date:inception_lower": "1980-01-01",
    "date:inception_upper": "1980-01-01",
    "iso:country": "GB",
    "wof:name": "NE61 3SE",
    "wof:placetype": "postalcode"
  },
  "geometry": {"coordinates":[-1.757405,55.188609],"type":"Point"}
}
