{
  "type": "Feature",
  "properties": {
    "iso:country":"GB",
    "wof:name":"NE61 3SE",
    "wof:placetype":"postalcode"
},
  "geometry": {"coordinates":[-1.75696840107618,55.18847756686117],"type":"Point"}
}