{
  "type": "Feature",
  "properties": {
    "date:inception_lower": "1998-06-01",
    "date:inception_upper": "1998-06-01",
    "iso:country": "GB",
    "wof:name": "GL52 2JL",
    "wof:placetype": "postalcode"
  },
  "geometry": {"coordinates":[-2.069253,51.901661],"type":"Point"}
}
