{
  "type": "Feature",
  "properties": {
    "iso:country": "GB",
    "wof:name": "GL52 2JL",
    "wof:placetype": "postalcode"
  },
  "geometry": {"coordinates":[-2.069253,51.901661],"type":"Point"}
}
