{
  "type": "Feature",
  "properties": {
    "iso:country":"GB",
    "wof:name":"CF46 5DB",
    "wof:placetype":"postalcode"
},
  "geometry": {"coordinates":[-3.30528421905507,51.65794340356253],"type":"Point"}
}