{
  "type": "Feature",
  "properties": {
    "date:inception_lower":"1980-01-01",
    "date:inception_upper":"1980-01-31",
    "iso:country":"GB",
    "wof:name":"CF46 5DB",
    "wof:placetype":"postalcode"
},
  "geometry": {"coordinates":[-3.305284,51.657943],"type":"Point"}
}