{
  "type": "Feature",
  "properties": {
    "iso:country": "GB",
    "wof:name": "MK44 3SY",
    "wof:placetype": "postalcode"
  },
  "geometry": {"coordinates":[-0.41769,52.114001],"type":"Point"}
}
