{
  "type": "Feature",
  "properties": {
    "iso:country":"GB",
    "wof:name":"MK44 3SY",
    "wof:placetype":"postalcode"
},
  "geometry": {"coordinates":[-0.41768987747987,52.11400090684762],"type":"Point"}
}