{
  "type": "Feature",
  "properties": {
    "iso:country":"GB",
    "wof:name":"SN7 7LA",
    "wof:placetype":"postalcode"
},
  "geometry": {"coordinates":[-1.59252973632248,51.64862424493877],"type":"Point"}
}