{
  "type": "Feature",
  "properties": {
    "iso:country":"GB",
    "wof:name":"G77 6LH",
    "wof:placetype":"postalcode"
},
  "geometry": {"coordinates":[-4.33418806172127,55.78245171477925],"type":"Point"}
}