{
  "type": "Feature",
  "properties": {
    "iso:country": "GB",
    "wof:name": "LL11 5AR",
    "wof:placetype": "postalcode"
  },
  "geometry": {"coordinates":[-3.060925,53.080071],"type":"Point"}
}
