{
  "type": "Feature",
  "properties": {
    "iso:country":"GB",
    "wof:name":"SL2 1HD",
    "wof:placetype":"postalcode"
},
  "geometry": {"coordinates":[-0.61779646654856,51.5304271903487],"type":"Point"}
}