{
  "type": "Feature",
  "properties": {
    "iso:country":"GB",
    "wof:name":"SL6 2NX",
    "wof:placetype":"postalcode"
},
  "geometry": {"coordinates":[-0.69263662505904,51.48197295537012],"type":"Point"}
}