{
  "type": "Feature",
  "properties": {
    "iso:country": "GB",
    "wof:name": "SL6 2NX",
    "wof:placetype": "postalcode"
  },
  "geometry": {"coordinates":[-0.692637,51.481973],"type":"Point"}
}
