{
  "type": "Feature",
  "properties": {
    "date:inception_lower": "2009-07-01",
    "date:inception_upper": "2009-07-01",
    "iso:country": "GB",
    "wof:name": "DT10 2FD",
    "wof:placetype": "postalcode"
  },
  "geometry": {"coordinates":[-2.375884,50.959326],"type":"Point"}
}
