{
  "type": "Feature",
  "properties": {
    "date:inception_lower": "1980-01-01",
    "date:inception_upper": "1980-01-01",
    "iso:country": "GB",
    "wof:name": "DE13 8AL",
    "wof:placetype": "postalcode"
  },
  "geometry": {"coordinates":[-1.735633,52.758107],"type":"Point"}
}
