{
  "type": "Feature",
  "properties": {
    "iso:country":"GB",
    "wof:name":"DE13 8AL",
    "wof:placetype":"postalcode"
},
  "geometry": {"coordinates":[-1.73556521093774,52.75808053080586],"type":"Point"}
}