{
  "type": "Feature",
  "properties": {
    "iso:country":"GB",
    "wof:name":"S20 5PJ",
    "wof:placetype":"postalcode"
},
  "geometry": {"coordinates":[-1.37631884108564,53.33104145892327],"type":"Point"}
}