{
  "type": "Feature",
  "properties": {
    "iso:country":"GB",
    "wof:name":"EC2A 2BB",
    "wof:placetype":"postalcode"
},
  "geometry": {"coordinates":[-0.08499752694441,51.52184256464985],"type":"Point"}
}