{
  "type": "Feature",
  "properties": {
    "iso:country":"GB",
    "wof:name":"TS12 3BF",
    "wof:placetype":"postalcode"
},
  "geometry": {"coordinates":[-0.98242917841299,54.54420948764884],"type":"Point"}
}