{
  "type": "Feature",
  "properties": {
    "iso:country": "GB",
    "wof:name": "TS12 3BF",
    "wof:placetype": "postalcode"
  },
  "geometry": {"coordinates":[-0.982429,54.544209],"type":"Point"}
}
