{
  "type": "Feature",
  "properties": {
    "date:inception_lower": "2021-05-01",
    "date:inception_upper": "2021-05-01",
    "iso:country": "GB",
    "wof:name": "BD4 0BW",
    "wof:placetype": "postalcode"
  },
  "geometry": {"coordinates":[-1.706943,53.784898],"type":"Point"}
}
