{
  "type": "Feature",
  "properties": {
    "date:inception_lower":"1980-01-01",
    "date:inception_upper":"1980-01-31",
    "iso:country":"GB",
    "wof:name":"TS25 5PB",
    "wof:placetype":"postalcode"
},
  "geometry": {"coordinates":[-1.227163,54.674939],"type":"Point"}
}