{
  "type": "Feature",
  "properties": {
    "iso:country":"GB",
    "wof:name":"L6 5LG",
    "wof:placetype":"postalcode"
},
  "geometry": {"coordinates":[-2.95387661217019,53.42248407661239],"type":"Point"}
}