{
  "type": "Feature",
  "properties": {
    "date:inception_lower":"1993-01-01",
    "date:inception_upper":"1993-01-31",
    "iso:country":"GB",
    "wof:name":"L6 5LG",
    "wof:placetype":"postalcode"
},
  "geometry": {"coordinates":[-2.953877,53.422484],"type":"Point"}
}