{
  "type": "Feature",
  "properties": {
    "iso:country": "GB",
    "wof:name": "EX23 0BE",
    "wof:placetype": "postalcode"
  },
  "geometry": {"coordinates":[-4.597514,50.732534],"type":"Point"}
}
