{
  "type": "Feature",
  "properties": {
    "iso:country":"GB",
    "wof:name":"EX23 0BE",
    "wof:placetype":"postalcode"
},
  "geometry": {"coordinates":[-4.59751377321059,50.73253432097986],"type":"Point"}
}