{
  "type": "Feature",
  "properties": {
    "date:inception_lower":"1980-01-01",
    "date:inception_upper":"1980-01-31",
    "iso:country":"GB",
    "wof:name":"EX23 0BE",
    "wof:placetype":"postalcode"
},
  "geometry": {"coordinates":[-4.597514,50.732534],"type":"Point"}
}