{
  "type": "Feature",
  "properties": {
    "iso:country": "GB",
    "wof:name": "CO6 1QJ",
    "wof:placetype": "postalcode"
  },
  "geometry": {"coordinates":[0.687099,51.876547],"type":"Point"}
}
