{
  "type": "Feature",
  "properties": {
    "date:inception_lower":"1980-01-01",
    "date:inception_upper":"1980-01-31",
    "iso:country":"GB",
    "wof:name":"CO6 1QJ",
    "wof:placetype":"postalcode"
},
  "geometry": {"coordinates":[0.687099,51.876547],"type":"Point"}
}