{
  "type": "Feature",
  "properties": {
    "iso:country":"GB",
    "wof:name":"TS8 9HE",
    "wof:placetype":"postalcode"
},
  "geometry": {"coordinates":[-1.23786854915136,54.52709808768546],"type":"Point"}
}