{
  "type": "Feature",
  "properties": {
    "iso:country": "GB",
    "wof:name": "HP10 0SZ",
    "wof:placetype": "postalcode"
  },
  "geometry": {"coordinates":[-0.6823,51.598204],"type":"Point"}
}
