{
  "type": "Feature",
  "properties": {
    "iso:country":"GB",
    "wof:name":"HP10 0SZ",
    "wof:placetype":"postalcode"
},
  "geometry": {"coordinates":[-0.68229973257206,51.59820395791909],"type":"Point"}
}