{
  "type": "Feature",
  "properties": {
    "iso:country":"GB",
    "wof:name":"TN22 5DY",
    "wof:placetype":"postalcode"
},
  "geometry": {"coordinates":[0.10189412632729,50.96560748005915],"type":"Point"}
}