{
  "type": "Feature",
  "properties": {
    "iso:country":"GB",
    "wof:name":"DE4 3EE",
    "wof:placetype":"postalcode"
},
  "geometry": {"coordinates":[-1.54143187856034,53.14020972005493],"type":"Point"}
}