{
  "type": "Feature",
  "properties": {
    "iso:country":"GB",
    "wof:name":"WF1 4RZ",
    "wof:placetype":"postalcode"
},
  "geometry": {"coordinates":[-1.47606037043198,53.69129449194106],"type":"Point"}
}