{
  "type": "Feature",
  "properties": {
    "iso:country":"GB",
    "wof:name":"PR7 4RS",
    "wof:placetype":"postalcode"
},
  "geometry": {"coordinates":[-2.61179298122857,53.612227651937],"type":"Point"}
}