{
  "type": "Feature",
  "properties": {
    "date:inception_lower":"1982-03-01",
    "date:inception_upper":"1982-03-31",
    "iso:country":"GB",
    "wof:name":"PR7 4RS",
    "wof:placetype":"postalcode"
},
  "geometry": {"coordinates":[-2.611793,53.612228],"type":"Point"}
}