{
  "type": "Feature",
  "properties": {
    "iso:country":"GB",
    "wof:name":"S60 5UR",
    "wof:placetype":"postalcode"
},
  "geometry": {"coordinates":[-1.36722654862294,53.39143411641217],"type":"Point"}
}