{
  "type": "Feature",
  "properties": {
    "iso:country": "GB",
    "wof:name": "S60 5UR",
    "wof:placetype": "postalcode"
  },
  "geometry": {"coordinates":[-1.367227,53.391434],"type":"Point"}
}
