{
  "type": "Feature",
  "properties": {
    "iso:country":"GB",
    "wof:name":"CV33 9NY",
    "wof:placetype":"postalcode"
},
  "geometry": {"coordinates":[-1.45168803405219,52.24733807029588],"type":"Point"}
}