{
  "type": "Feature",
  "properties": {
    "iso:country":"GB",
    "wof:name":"BS5 9BN",
    "wof:placetype":"postalcode"
},
  "geometry": {"coordinates":[-2.55643910676288,51.46254359106796],"type":"Point"}
}