{
  "type": "Feature",
  "properties": {
    "date:inception_lower": "2024-01-01",
    "date:inception_upper": "2024-01-01",
    "iso:country": "GB",
    "wof:name": "PE25 2FH",
    "wof:placetype": "postalcode"
  },
  "geometry": {"coordinates":[0.334783,53.147638],"type":"Point"}
}
