{
  "type": "Feature",
  "properties": {
    "iso:country":"GB",
    "wof:name":"HG5 8HU",
    "wof:placetype":"postalcode"
},
  "geometry": {"coordinates":[-1.45161925148618,54.00075908589941],"type":"Point"}
}