{
  "type": "Feature",
  "properties": {
    "iso:country": "GB",
    "wof:name": "HG5 8HU",
    "wof:placetype": "postalcode"
  },
  "geometry": {"coordinates":[-1.451619,54.000759],"type":"Point"}
}
