{
  "type": "Feature",
  "properties": {
    "iso:country":"GB",
    "wof:name":"CV34 4LT",
    "wof:placetype":"postalcode"
},
  "geometry": {"coordinates":[-1.57675831227434,52.28596249157579],"type":"Point"}
}