{
  "type": "Feature",
  "properties": {
    "iso:country":"GB",
    "wof:name":"BN5 9DZ",
    "wof:placetype":"postalcode"
},
  "geometry": {"coordinates":[-0.27793463665236,50.92791238237502],"type":"Point"}
}