{
  "type": "Feature",
  "properties": {
    "iso:country": "GB",
    "wof:name": "SW19 3SW",
    "wof:placetype": "postalcode"
  },
  "geometry": {"coordinates":[-0.206382,51.418477],"type":"Point"}
}
