{
  "type": "Feature",
  "properties": {
    "iso:country":"GB",
    "wof:name":"LA8 9EX",
    "wof:placetype":"postalcode"
},
  "geometry": {"coordinates":[-2.61442703123418,54.36129586685772],"type":"Point"}
}