{
  "type": "Feature",
  "properties": {
    "iso:country": "GB",
    "wof:name": "PR4 6FD",
    "wof:placetype": "postalcode"
  },
  "geometry": {"coordinates":[-2.830611,53.678877],"type":"Point"}
}
