{
  "type": "Feature",
  "properties": {
    "date:inception_lower": "2005-05-01",
    "date:inception_upper": "2005-05-01",
    "iso:country": "GB",
    "wof:name": "TQ1 1TH",
    "wof:placetype": "postalcode"
  },
  "geometry": {"coordinates":[-3.51316,50.468426],"type":"Point"}
}
