{
  "type": "Feature",
  "properties": {
    "iso:country":"GB",
    "wof:name":"TQ1 1TH",
    "wof:placetype":"postalcode"
},
  "geometry": {"coordinates":[-3.51315998295705,50.46842595866629],"type":"Point"}
}