{
  "type": "Feature",
  "properties": {
    "iso:country":"GB",
    "wof:name":"WF15 7AZ",
    "wof:placetype":"postalcode"
},
  "geometry": {"coordinates":[-1.6798240622798,53.70222250077988],"type":"Point"}
}