{
  "type": "Feature",
  "properties": {
    "iso:country": "GB",
    "wof:name": "WF15 7AZ",
    "wof:placetype": "postalcode"
  },
  "geometry": {"coordinates":[-1.679824,53.702222],"type":"Point"}
}
