{
  "type": "Feature",
  "properties": {
    "iso:country":"GB",
    "wof:name":"CB9 0DY",
    "wof:placetype":"postalcode"
},
  "geometry": {"coordinates":[0.43424148175492,52.09005324721672],"type":"Point"}
}