{
  "type": "Feature",
  "properties": {
    "iso:country":"GB",
    "wof:name":"SW11 2RE",
    "wof:placetype":"postalcode"
},
  "geometry": {"coordinates":[-0.17718546196742,51.4624771915736],"type":"Point"}
}