{
  "type": "Feature",
  "properties": {
    "date:inception_lower":"2015-12-01",
    "date:inception_upper":"2015-12-31",
    "iso:country":"GB",
    "wof:name":"FK8 2HD",
    "wof:placetype":"postalcode"
},
  "geometry": {"coordinates":[-3.938393,56.109707],"type":"Point"}
}