{
  "type": "Feature",
  "properties": {
    "iso:country": "GB",
    "wof:name": "FK8 2HD",
    "wof:placetype": "postalcode"
  },
  "geometry": {"coordinates":[-3.938393,56.109707],"type":"Point"}
}
