{
  "type": "Feature",
  "properties": {
    "iso:country":"GB",
    "wof:name":"FK8 2HD",
    "wof:placetype":"postalcode"
},
  "geometry": {"coordinates":[-3.93839269263615,56.10970696407907],"type":"Point"}
}