{
  "type": "Feature",
  "properties": {
    "iso:country": "GB",
    "wof:name": "S3 8DW",
    "wof:placetype": "postalcode"
  },
  "geometry": {"coordinates":[-1.476183,53.389103],"type":"Point"}
}
