{
  "type": "Feature",
  "properties": {
    "iso:country":"GB",
    "wof:name":"AL7 2BS",
    "wof:placetype":"postalcode"
},
  "geometry": {"coordinates":[-0.17231096941144,51.79845284756559],"type":"Point"}
}