{
  "type": "Feature",
  "properties": {
    "date:inception_lower": "1980-01-01",
    "date:inception_upper": "1980-01-01",
    "iso:country": "GB",
    "wof:name": "AL7 2BS",
    "wof:placetype": "postalcode"
  },
  "geometry": {"coordinates":[-0.172311,51.798453],"type":"Point"}
}
