{
  "type": "Feature",
  "properties": {
    "iso:country": "GB",
    "wof:name": "TS1 2DA",
    "wof:placetype": "postalcode"
  },
  "geometry": {"coordinates":[-1.232139,54.57552],"type":"Point"}
}
