{
  "type": "Feature",
  "properties": {
    "iso:country":"GB",
    "wof:name":"WN3 5EG",
    "wof:placetype":"postalcode"
},
  "geometry": {"coordinates":[-2.64179036582903,53.53304393394512],"type":"Point"}
}