{
  "type": "Feature",
  "properties": {
    "iso:country": "GB",
    "wof:name": "SY10 9NW",
    "wof:placetype": "postalcode"
  },
  "geometry": {"coordinates":[-3.058661,52.842648],"type":"Point"}
}
