{
  "type": "Feature",
  "properties": {
    "iso:country":"GB",
    "wof:name":"SY10 9NW",
    "wof:placetype":"postalcode"
},
  "geometry": {"coordinates":[-3.05866101280096,52.84264815082879],"type":"Point"}
}