{
  "type": "Feature",
  "properties": {
    "iso:country":"GB",
    "wof:name":"SO18 4TS",
    "wof:placetype":"postalcode"
},
  "geometry": {"coordinates":[-1.36922503506716,50.91769179299285],"type":"Point"}
}