{
  "type": "Feature",
  "properties": {
    "date:inception_lower": "1983-03-01",
    "date:inception_upper": "1983-03-01",
    "iso:country": "GB",
    "wof:name": "BS28 4AQ",
    "wof:placetype": "postalcode"
  },
  "geometry": {"coordinates":[-2.818168,51.225124],"type":"Point"}
}
