{
  "type": "Feature",
  "properties": {
    "iso:country":"GB",
    "wof:name":"BS28 4AQ",
    "wof:placetype":"postalcode"
},
  "geometry": {"coordinates":[-2.81816812919401,51.22512419392838],"type":"Point"}
}