{
  "type": "Feature",
  "properties": {
    "iso:country": "GB",
    "wof:name": "DT10 2HR",
    "wof:placetype": "postalcode"
  },
  "geometry": {"coordinates":[-2.33415,50.913556],"type":"Point"}
}
