{
  "type": "Feature",
  "properties": {
    "iso:country":"GB",
    "wof:name":"DT10 2HR",
    "wof:placetype":"postalcode"
},
  "geometry": {"coordinates":[-2.33415029730463,50.9135557396114],"type":"Point"}
}