{
  "type": "Feature",
  "properties": {
    "iso:country":"GB",
    "wof:name":"CV1 1NF",
    "wof:placetype":"postalcode"
},
  "geometry": {"coordinates":[-1.51119260759845,52.40778799557273],"type":"Point"}
}