{
  "type": "Feature",
  "properties": {
    "iso:country":"GB",
    "wof:name":"SY13 2HD",
    "wof:placetype":"postalcode"
},
  "geometry": {"coordinates":[-2.65206297858779,52.92283416793369],"type":"Point"}
}