{
  "type": "Feature",
  "properties": {
    "date:inception_lower":"1980-01-01",
    "date:inception_upper":"1980-01-31",
    "iso:country":"GB",
    "wof:name":"SY13 2HD",
    "wof:placetype":"postalcode"
},
  "geometry": {"coordinates":[-2.651433,52.922592],"type":"Point"}
}