{
  "type": "Feature",
  "properties": {
    "iso:country":"GB",
    "wof:name":"HA2 9AP",
    "wof:placetype":"postalcode"
},
  "geometry": {"coordinates":[-0.37820834654082,51.56108966206001],"type":"Point"}
}