{
  "type": "Feature",
  "properties": {
    "iso:country":"GB",
    "wof:name":"BR4 0LT",
    "wof:placetype":"postalcode"
},
  "geometry": {"coordinates":[-0.01999154707379,51.37668157537136],"type":"Point"}
}