{
  "type": "Feature",
  "properties": {
    "iso:country":"GB",
    "wof:name":"WS9 8HB",
    "wof:placetype":"postalcode"
},
  "geometry": {"coordinates":[-1.91621153597967,52.61665948679615],"type":"Point"}
}