{
  "type": "Feature",
  "properties": {
    "date:inception_lower": "1997-06-01",
    "date:inception_upper": "1997-06-01",
    "iso:country": "GB",
    "wof:name": "LL57 1SD",
    "wof:placetype": "postalcode"
  },
  "geometry": {"coordinates":[-4.112875,53.22724],"type":"Point"}
}
