{
  "type": "Feature",
  "properties": {
    "iso:country": "GB",
    "wof:name": "LL57 1SD",
    "wof:placetype": "postalcode"
  },
  "geometry": {"coordinates":[-4.112875,53.22724],"type":"Point"}
}
