{
  "type": "Feature",
  "properties": {
    "iso:country":"GB",
    "wof:name":"LL57 1SD",
    "wof:placetype":"postalcode"
},
  "geometry": {"coordinates":[-4.11287461862103,53.22724043767843],"type":"Point"}
}