{
  "type": "Feature",
  "properties": {
    "iso:country":"GB",
    "wof:name":"BS22 9HD",
    "wof:placetype":"postalcode"
},
  "geometry": {"coordinates":[-2.93160847981052,51.36009172119127],"type":"Point"}
}