{
  "type": "Feature",
  "properties": {
    "iso:country": "GB",
    "wof:name": "PH1 5UX",
    "wof:placetype": "postalcode"
  },
  "geometry": {"coordinates":[-3.431061,56.395957],"type":"Point"}
}
