{
  "type": "Feature",
  "properties": {
    "date:inception_lower": "1992-10-01",
    "date:inception_upper": "1992-10-01",
    "iso:country": "GB",
    "wof:name": "PH1 5UX",
    "wof:placetype": "postalcode"
  },
  "geometry": {"coordinates":[-3.431061,56.395957],"type":"Point"}
}
