{
  "type": "Feature",
  "properties": {
    "iso:country":"GB",
    "wof:name":"SL8 5XE",
    "wof:placetype":"postalcode"
},
  "geometry": {"coordinates":[-0.70518437078855,51.57534054007267],"type":"Point"}
}