{
  "type": "Feature",
  "properties": {
    "date:inception_lower": "1998-06-01",
    "date:inception_upper": "1998-06-01",
    "iso:country": "GB",
    "wof:name": "SL8 5XE",
    "wof:placetype": "postalcode"
  },
  "geometry": {"coordinates":[-0.704933,51.575908],"type":"Point"}
}
