{
  "type": "Feature",
  "properties": {
    "iso:country": "GB",
    "wof:name": "SL8 5XE",
    "wof:placetype": "postalcode"
  },
  "geometry": {"coordinates":[-0.704933,51.575908],"type":"Point"}
}
