{
  "type": "Feature",
  "properties": {
    "iso:country":"GB",
    "wof:name":"ST6 6US",
    "wof:placetype":"postalcode"
},
  "geometry": {"coordinates":[-2.18822140813432,53.0811745133534],"type":"Point"}
}