{
  "type": "Feature",
  "properties": {
    "iso:country":"GB",
    "wof:name":"YO18 8RE",
    "wof:placetype":"postalcode"
},
  "geometry": {"coordinates":[-0.89800628642112,54.36230887640808],"type":"Point"}
}