{
  "type": "Feature",
  "properties": {
    "iso:country": "GB",
    "wof:name": "WC1H 9PD",
    "wof:placetype": "postalcode"
  },
  "geometry": {"coordinates":[-0.124603,51.527608],"type":"Point"}
}
