{
  "type": "Feature",
  "properties": {
    "date:inception_lower": "1980-01-01",
    "date:inception_upper": "1980-01-01",
    "iso:country": "GB",
    "wof:name": "TS3 7AS",
    "wof:placetype": "postalcode"
  },
  "geometry": {"coordinates":[-1.20571,54.562309],"type":"Point"}
}
