{
  "type": "Feature",
  "properties": {
    "iso:country":"GB",
    "wof:name":"TS3 7AS",
    "wof:placetype":"postalcode"
},
  "geometry": {"coordinates":[-1.20571041478196,54.56230947049833],"type":"Point"}
}