{
  "type": "Feature",
  "properties": {
    "date:inception_lower":"2015-09-01",
    "date:inception_upper":"2015-09-30",
    "iso:country":"GB",
    "wof:name":"YO42 9AW",
    "wof:placetype":"postalcode"
},
  "geometry": {"coordinates":[-0.777241,53.932002],"type":"Point"}
}