{
  "type": "Feature",
  "properties": {
    "date:inception_lower":"2000-12-01",
    "date:inception_upper":"2000-12-31",
    "iso:country":"GB",
    "wof:name":"SY7 0DD",
    "wof:placetype":"postalcode"
},
  "geometry": {"coordinates":[-2.946651,52.358426],"type":"Point"}
}