{
  "type": "Feature",
  "properties": {
    "iso:country":"GB",
    "wof:name":"SY7 0DD",
    "wof:placetype":"postalcode"
},
  "geometry": {"coordinates":[-2.94665135327018,52.35842598012225],"type":"Point"}
}