{
  "type": "Feature",
  "properties": {
    "iso:country":"GB",
    "wof:name":"CF10 5GT",
    "wof:placetype":"postalcode"
},
  "geometry": {"coordinates":[-3.17375633865768,51.46305903098961],"type":"Point"}
}