{
  "type": "Feature",
  "properties": {
    "iso:country": "GB",
    "wof:name": "HP22 0AD",
    "wof:placetype": "postalcode"
  },
  "geometry": {"coordinates":[-0.730951,51.803919],"type":"Point"}
}
