{
  "type": "Feature",
  "properties": {
    "iso:country":"GB",
    "wof:name":"NE3 1YQ",
    "wof:placetype":"postalcode"
},
  "geometry": {"coordinates":[-1.60836886638337,55.00290604708786],"type":"Point"}
}