{
  "type": "Feature",
  "properties": {
    "iso:country":"GB",
    "wof:name":"DY13 9RQ",
    "wof:placetype":"postalcode"
},
  "geometry": {"coordinates":[-2.25961803905022,52.32526287557728],"type":"Point"}
}