{
  "type": "Feature",
  "properties": {
    "iso:country":"GB",
    "wof:name":"TQ5 8PN",
    "wof:placetype":"postalcode"
},
  "geometry": {"coordinates":[-3.53074625599982,50.39466323927464],"type":"Point"}
}