{
  "type": "Feature",
  "properties": {
    "date:inception_lower": "1991-09-01",
    "date:inception_upper": "1991-09-01",
    "iso:country": "GB",
    "wof:name": "DN16 3SR",
    "wof:placetype": "postalcode"
  },
  "geometry": {"coordinates":[-0.655979,53.553843],"type":"Point"}
}
