{
  "type": "Feature",
  "properties": {
    "iso:country":"GB",
    "wof:name":"DN16 3SR",
    "wof:placetype":"postalcode"
},
  "geometry": {"coordinates":[-0.65597905968419,53.55384253755172],"type":"Point"}
}