{
  "type": "Feature",
  "properties": {
    "iso:country": "GB",
    "wof:name": "TA8 1PS",
    "wof:placetype": "postalcode"
  },
  "geometry": {"coordinates":[-2.995043,51.235138],"type":"Point"}
}
