{
  "type": "Feature",
  "properties": {
    "date:inception_lower": "1983-08-01",
    "date:inception_upper": "1983-08-01",
    "iso:country": "GB",
    "wof:name": "G75 8EE",
    "wof:placetype": "postalcode"
  },
  "geometry": {"coordinates":[-4.220539,55.745462],"type":"Point"}
}
