{
  "type": "Feature",
  "properties": {
    "iso:country":"GB",
    "wof:name":"G75 8EE",
    "wof:placetype":"postalcode"
},
  "geometry": {"coordinates":[-4.22053904401154,55.74546242837702],"type":"Point"}
}