{
  "type": "Feature",
  "properties": {
    "iso:country": "GB",
    "wof:name": "SK8 7QX",
    "wof:placetype": "postalcode"
  },
  "geometry": {"coordinates":[-2.187985,53.358481],"type":"Point"}
}
