{
  "type": "Feature",
  "properties": {
    "iso:country":"GB",
    "wof:name":"SK8 7QX",
    "wof:placetype":"postalcode"
},
  "geometry": {"coordinates":[-2.18798528002706,53.35848072234654],"type":"Point"}
}