{
  "type": "Feature",
  "properties": {
    "iso:country":"GB",
    "wof:name":"B64 7LF",
    "wof:placetype":"postalcode"
},
  "geometry": {"coordinates":[-2.06601624748401,52.46554175290268],"type":"Point"}
}