{
  "type": "Feature",
  "properties": {
    "date:inception_lower": "2017-09-01",
    "date:inception_upper": "2017-09-01",
    "iso:country": "GB",
    "wof:name": "YO41 1FW",
    "wof:placetype": "postalcode"
  },
  "geometry": {"coordinates":[-0.917371,53.986997],"type":"Point"}
}
