{
  "type": "Feature",
  "properties": {
    "iso:country": "GB",
    "wof:name": "W2 1RX",
    "wof:placetype": "postalcode"
  },
  "geometry": {"coordinates":[-0.172892,51.515889],"type":"Point"}
}
