{
  "type": "Feature",
  "properties": {
    "iso:country":"GB",
    "wof:name":"W2 1RX",
    "wof:placetype":"postalcode"
},
  "geometry": {"coordinates":[-0.1728920516538,51.51588877799539],"type":"Point"}
}