{
  "type": "Feature",
  "properties": {
    "iso:country": "GB",
    "wof:name": "NP16 7NT",
    "wof:placetype": "postalcode"
  },
  "geometry": {"coordinates":[-2.662558,51.7226],"type":"Point"}
}
