{
  "type": "Feature",
  "properties": {
    "iso:country":"GB",
    "wof:name":"RH11 8GJ",
    "wof:placetype":"postalcode"
},
  "geometry": {"coordinates":[-0.229054464009,51.09931829076011],"type":"Point"}
}