{
  "type": "Feature",
  "properties": {
    "date:inception_lower":"1990-07-01",
    "date:inception_upper":"1990-07-31",
    "iso:country":"GB",
    "wof:name":"RH11 8GJ",
    "wof:placetype":"postalcode"
},
  "geometry": {"coordinates":[-0.229054,51.099318],"type":"Point"}
}