{
  "type": "Feature",
  "properties": {
    "date:inception_lower": "1998-06-01",
    "date:inception_upper": "1998-06-01",
    "iso:country": "GB",
    "wof:name": "GL15 5RG",
    "wof:placetype": "postalcode"
  },
  "geometry": {"coordinates":[-2.528875,51.727306],"type":"Point"}
}
