{
  "type": "Feature",
  "properties": {
    "iso:country": "GB",
    "wof:name": "SL6 6HU",
    "wof:placetype": "postalcode"
  },
  "geometry": {"coordinates":[-0.740127,51.528666],"type":"Point"}
}
