{
  "type": "Feature",
  "properties": {
    "iso:country":"GB",
    "wof:name":"SL6 6HU",
    "wof:placetype":"postalcode"
},
  "geometry": {"coordinates":[-0.74012682169987,51.52866631935938],"type":"Point"}
}