{
  "type": "Feature",
  "properties": {
    "date:inception_lower": "2000-06-01",
    "date:inception_upper": "2000-06-01",
    "iso:country": "GB",
    "wof:name": "CA8 7EH",
    "wof:placetype": "postalcode"
  },
  "geometry": {"coordinates":[-2.564102,54.989484],"type":"Point"}
}
