{
  "type": "Feature",
  "properties": {
    "iso:country":"GB",
    "wof:name":"CA8 7EH",
    "wof:placetype":"postalcode"
},
  "geometry": {"coordinates":[-2.56410155320908,54.98948405976727],"type":"Point"}
}