{
  "type": "Feature",
  "properties": {
    "iso:country": "GB",
    "wof:name": "NE1 3HD",
    "wof:placetype": "postalcode"
  },
  "geometry": {"coordinates":[-1.60546,54.969486],"type":"Point"}
}
