{
  "type": "Feature",
  "properties": {
    "iso:country":"GB",
    "wof:name":"NE1 3HD",
    "wof:placetype":"postalcode"
},
  "geometry": {"coordinates":[-1.60546042750379,54.96948579025113],"type":"Point"}
}