{
  "type": "Feature",
  "properties": {
    "iso:country":"GB",
    "wof:name":"G74 3JY",
    "wof:placetype":"postalcode"
},
  "geometry": {"coordinates":[-4.15617778831367,55.77593497111509],"type":"Point"}
}