{
  "type": "Feature",
  "properties": {
    "date:inception_lower": "1998-12-01",
    "date:inception_upper": "1998-12-01",
    "iso:country": "GB",
    "wof:name": "EC1V 1NH",
    "wof:placetype": "postalcode"
  },
  "geometry": {"coordinates":[-0.10519,51.531981],"type":"Point"}
}
