{
  "type": "Feature",
  "properties": {
    "iso:country":"GB",
    "wof:name":"WA16 6SG",
    "wof:placetype":"postalcode"
},
  "geometry": {"coordinates":[-2.37921906801473,53.3408035977538],"type":"Point"}
}