{
  "type": "Feature",
  "properties": {
    "iso:country": "GB",
    "wof:name": "WA16 6SG",
    "wof:placetype": "postalcode"
  },
  "geometry": {"coordinates":[-2.379219,53.340804],"type":"Point"}
}
