{
  "type": "Feature",
  "properties": {
    "iso:country":"GB",
    "wof:name":"TQ2 7NE",
    "wof:placetype":"postalcode"
},
  "geometry": {"coordinates":[-3.56603541308736,50.47922919210397],"type":"Point"}
}