{
  "type": "Feature",
  "properties": {
    "iso:country": "GB",
    "wof:name": "BH23 3EP",
    "wof:placetype": "postalcode"
  },
  "geometry": {"coordinates":[-1.748037,50.741593],"type":"Point"}
}
