{
  "type": "Feature",
  "properties": {
    "iso:country":"GB",
    "wof:name":"BH23 3EP",
    "wof:placetype":"postalcode"
},
  "geometry": {"coordinates":[-1.74803701020019,50.74159253098811],"type":"Point"}
}