{
  "type": "Feature",
  "properties": {
    "iso:country":"GB",
    "wof:name":"SG6 3AR",
    "wof:placetype":"postalcode"
},
  "geometry": {"coordinates":[-0.22850102210524,51.97974404096001],"type":"Point"}
}