{
  "type": "Feature",
  "properties": {
    "date:inception_lower":"1983-07-01",
    "date:inception_upper":"1983-07-31",
    "iso:country":"GB",
    "wof:name":"PE30 3RT",
    "wof:placetype":"postalcode"
},
  "geometry": {"coordinates":[0.436773,52.787563],"type":"Point"}
}