{
  "type": "Feature",
  "properties": {
    "iso:country":"GB",
    "wof:name":"PE30 3RT",
    "wof:placetype":"postalcode"
},
  "geometry": {"coordinates":[0.43677272144223,52.78756342318787],"type":"Point"}
}