{
  "type": "Feature",
  "properties": {
    "iso:country":"GB",
    "wof:name":"SO51 9BL",
    "wof:placetype":"postalcode"
},
  "geometry": {"coordinates":[-1.42888142390276,50.9949196433661],"type":"Point"}
}