{
  "type": "Feature",
  "properties": {
    "iso:country": "GB",
    "wof:name": "SO51 9BL",
    "wof:placetype": "postalcode"
  },
  "geometry": {"coordinates":[-1.428881,50.99492],"type":"Point"}
}
