{
  "type": "Feature",
  "properties": {
    "date:inception_lower": "2007-08-01",
    "date:inception_upper": "2007-08-01",
    "iso:country": "GB",
    "wof:name": "CH1 5ES",
    "wof:placetype": "postalcode"
  },
  "geometry": {"coordinates":[-2.932195,53.207036],"type":"Point"}
}
