{
  "type": "Feature",
  "properties": {
    "iso:country":"GB",
    "wof:name":"CH1 5ES",
    "wof:placetype":"postalcode"
},
  "geometry": {"coordinates":[-2.93219439591648,53.20702657612404],"type":"Point"}
}