{
  "type": "Feature",
  "properties": {
    "iso:country": "GB",
    "wof:name": "ME19 4RU",
    "wof:placetype": "postalcode"
  },
  "geometry": {"coordinates":[0.402136,51.269615],"type":"Point"}
}
