{
  "type": "Feature",
  "properties": {
    "iso:country": "GB",
    "wof:name": "IV12 5JG",
    "wof:placetype": "postalcode"
  },
  "geometry": {"coordinates":[-3.72897,57.489045],"type":"Point"}
}
