{
  "type": "Feature",
  "properties": {
    "iso:country":"GB",
    "wof:name":"ME10 3SQ",
    "wof:placetype":"postalcode"
},
  "geometry": {"coordinates":[0.76187587840259,51.35380242138968],"type":"Point"}
}