{
  "type": "Feature",
  "properties": {
    "iso:country":"GB",
    "wof:name":"DN37 0DE",
    "wof:placetype":"postalcode"
},
  "geometry": {"coordinates":[-0.11145739608529,53.51401238400978],"type":"Point"}
}