{
  "type": "Feature",
  "properties": {
    "date:inception_lower":"1980-01-01",
    "date:inception_upper":"1980-01-31",
    "iso:country":"GB",
    "wof:name":"DN37 0DE",
    "wof:placetype":"postalcode"
},
  "geometry": {"coordinates":[-0.111457,53.514012],"type":"Point"}
}