{
  "type": "Feature",
  "properties": {
    "iso:country": "GB",
    "wof:name": "B20 3QP",
    "wof:placetype": "postalcode"
  },
  "geometry": {"coordinates":[-1.91077,52.51009],"type":"Point"}
}
