{
  "type": "Feature",
  "properties": {
    "date:inception_lower": "1980-01-01",
    "date:inception_upper": "1980-01-01",
    "iso:country": "GB",
    "wof:name": "SW1H 0AB",
    "wof:placetype": "postalcode"
  },
  "geometry": {"coordinates":[-0.135123,51.499126],"type":"Point"}
}
