{
  "type": "Feature",
  "properties": {
    "iso:country":"GB",
    "wof:name":"NR3 4LB",
    "wof:placetype":"postalcode"
},
  "geometry": {"coordinates":[1.29713744619266,52.64245034286073],"type":"Point"}
}