{
  "type": "Feature",
  "properties": {
    "date:inception_lower": "1980-01-01",
    "date:inception_upper": "1980-01-01",
    "iso:country": "GB",
    "wof:name": "WV4 4XD",
    "wof:placetype": "postalcode"
  },
  "geometry": {"coordinates":[-2.206367,52.560322],"type":"Point"}
}
