{
  "type": "Feature",
  "properties": {
    "iso:country":"GB",
    "wof:name":"TD15 1RL",
    "wof:placetype":"postalcode"
},
  "geometry": {"coordinates":[-2.00847228070063,55.78162281148697],"type":"Point"}
}