{
  "type": "Feature",
  "properties": {
    "iso:country": "GB",
    "wof:name": "TD15 1RL",
    "wof:placetype": "postalcode"
  },
  "geometry": {"coordinates":[-2.008472,55.781623],"type":"Point"}
}
