{
  "type": "Feature",
  "properties": {
    "iso:country":"GB",
    "wof:name":"HA6 2YZ",
    "wof:placetype":"postalcode"
},
  "geometry": {"coordinates":[-0.4258400786325,51.60677073531703],"type":"Point"}
}