{
  "type": "Feature",
  "properties": {
    "iso:country":"GB",
    "wof:name":"W8 7HL",
    "wof:placetype":"postalcode"
},
  "geometry": {"coordinates":[-0.19632421472932,51.50319441034655],"type":"Point"}
}