{
  "type": "Feature",
  "properties": {
    "date:inception_lower": "1980-01-01",
    "date:inception_upper": "1980-01-01",
    "iso:country": "GB",
    "wof:name": "LA14 5TF",
    "wof:placetype": "postalcode"
  },
  "geometry": {"coordinates":[-3.231898,54.117277],"type":"Point"}
}
