{
  "type": "Feature",
  "properties": {
    "iso:country":"GB",
    "wof:name":"LA14 5TF",
    "wof:placetype":"postalcode"
},
  "geometry": {"coordinates":[-3.23189850222559,54.11727675276711],"type":"Point"}
}