{
  "type": "Feature",
  "properties": {
    "iso:country":"GB",
    "wof:name":"HA1 1RW",
    "wof:placetype":"postalcode"
},
  "geometry": {"coordinates":[-0.34011985913872,51.58451231164199],"type":"Point"}
}