{
  "type": "Feature",
  "properties": {
    "date:inception_lower": "1980-01-01",
    "date:inception_upper": "1980-01-01",
    "iso:country": "GB",
    "wof:name": "LU2 7TR",
    "wof:placetype": "postalcode"
  },
  "geometry": {"coordinates":[-0.40659,51.897003],"type":"Point"}
}
