{
  "type": "Feature",
  "properties": {
    "iso:country":"GB",
    "wof:name":"GL5 3HB",
    "wof:placetype":"postalcode"
},
  "geometry": {"coordinates":[-2.24116186736202,51.74105283079959],"type":"Point"}
}