{
  "type": "Feature",
  "properties": {
    "date:inception_lower": "1983-01-01",
    "date:inception_upper": "1983-01-01",
    "iso:country": "GB",
    "wof:name": "GL5 3HB",
    "wof:placetype": "postalcode"
  },
  "geometry": {"coordinates":[-2.241162,51.741053],"type":"Point"}
}
