{
  "type": "Feature",
  "properties": {
    "iso:country":"GB",
    "wof:name":"RM12 6RG",
    "wof:placetype":"postalcode"
},
  "geometry": {"coordinates":[0.21256942068396,51.54760498721808],"type":"Point"}
}