{
  "type": "Feature",
  "properties": {
    "date:inception_lower":"1980-01-01",
    "date:inception_upper":"1980-01-31",
    "iso:country":"GB",
    "wof:name":"NE6 5NB",
    "wof:placetype":"postalcode"
},
  "geometry": {"coordinates":[-1.574056,54.987928],"type":"Point"}
}