{
  "type": "Feature",
  "properties": {
    "iso:country":"GB",
    "wof:name":"NE6 5NB",
    "wof:placetype":"postalcode"
},
  "geometry": {"coordinates":[-1.57405560903699,54.98792759260764],"type":"Point"}
}