{
  "type": "Feature",
  "properties": {
    "iso:country":"GB",
    "wof:name":"GU2 4AS",
    "wof:placetype":"postalcode"
},
  "geometry": {"coordinates":[-0.5780442777741,51.23334260241066],"type":"Point"}
}