{
  "type": "Feature",
  "properties": {
    "iso:country":"GB",
    "wof:name":"S62 6NJ",
    "wof:placetype":"postalcode"
},
  "geometry": {"coordinates":[-1.34403268403377,53.46131289013137],"type":"Point"}
}