{
  "type": "Feature",
  "properties": {
    "iso:country": "GB",
    "wof:name": "S62 6NJ",
    "wof:placetype": "postalcode"
  },
  "geometry": {"coordinates":[-1.344033,53.461313],"type":"Point"}
}
