{
  "type": "Feature",
  "properties": {
    "iso:country":"GB",
    "wof:name":"NE6 2NS",
    "wof:placetype":"postalcode"
},
  "geometry": {"coordinates":[-1.57343015933257,54.97616238074795],"type":"Point"}
}