{
  "type": "Feature",
  "properties": {
    "date:inception_lower":"1980-01-01",
    "date:inception_upper":"1980-01-31",
    "iso:country":"GB",
    "wof:name":"AL10 0SJ",
    "wof:placetype":"postalcode"
},
  "geometry": {"coordinates":[-0.238785,51.760271],"type":"Point"}
}