{
  "type": "Feature",
  "properties": {
    "iso:country":"GB",
    "wof:name":"AL10 0SJ",
    "wof:placetype":"postalcode"
},
  "geometry": {"coordinates":[-0.23878510587984,51.76027117257198],"type":"Point"}
}