{
  "type": "Feature",
  "properties": {
    "iso:country": "GB",
    "wof:name": "DN18 5LD",
    "wof:placetype": "postalcode"
  },
  "geometry": {"coordinates":[-0.447799,53.68767],"type":"Point"}
}
