{
  "type": "Feature",
  "properties": {
    "date:inception_lower":"2006-07-01",
    "date:inception_upper":"2006-07-31",
    "iso:country":"GB",
    "wof:name":"DN18 5LD",
    "wof:placetype":"postalcode"
},
  "geometry": {"coordinates":[-0.447799,53.68767],"type":"Point"}
}