{
  "type": "Feature",
  "properties": {
    "iso:country":"GB",
    "wof:name":"DN18 5LD",
    "wof:placetype":"postalcode"
},
  "geometry": {"coordinates":[-0.44779867247038,53.68767022373015],"type":"Point"}
}