{
  "type": "Feature",
  "properties": {
    "iso:country":"GB",
    "wof:name":"PE12 0SY",
    "wof:placetype":"postalcode"
},
  "geometry": {"coordinates":[-0.05672799829902,52.74003133766912],"type":"Point"}
}