{
  "type": "Feature",
  "properties": {
    "iso:country": "GB",
    "wof:name": "PE12 0SY",
    "wof:placetype": "postalcode"
  },
  "geometry": {"coordinates":[-0.056728,52.740031],"type":"Point"}
}
