{
  "type": "Feature",
  "properties": {
    "date:inception_lower":"1980-01-01",
    "date:inception_upper":"1980-01-31",
    "iso:country":"GB",
    "wof:name":"PE12 0SY",
    "wof:placetype":"postalcode"
},
  "geometry": {"coordinates":[-0.056728,52.740031],"type":"Point"}
}