{
  "type": "Feature",
  "properties": {
    "date:inception_lower":"2011-02-01",
    "date:inception_upper":"2011-02-28",
    "iso:country":"GB",
    "wof:name":"LN6 9LL",
    "wof:placetype":"postalcode"
},
  "geometry": {"coordinates":[-0.605379,53.179224],"type":"Point"}
}