{
  "type": "Feature",
  "properties": {
    "iso:country":"GB",
    "wof:name":"LN6 9LL",
    "wof:placetype":"postalcode"
},
  "geometry": {"coordinates":[-0.60537885311135,53.17922447069913],"type":"Point"}
}