{
  "type": "Feature",
  "properties": {
    "date:inception_lower":"2008-10-01",
    "date:inception_upper":"2008-10-31",
    "iso:country":"GB",
    "wof:name":"BS5 9ER",
    "wof:placetype":"postalcode"
},
  "geometry": {"coordinates":[-2.557491,51.459059],"type":"Point"}
}