{
  "type": "Feature",
  "properties": {
    "iso:country":"GB",
    "wof:name":"BS5 9ER",
    "wof:placetype":"postalcode"
},
  "geometry": {"coordinates":[-2.55749061085292,51.45905883765117],"type":"Point"}
}