{
  "type": "Feature",
  "properties": {
    "iso:country":"GB",
    "wof:name":"B15 1NX",
    "wof:placetype":"postalcode"
},
  "geometry": {"coordinates":[-1.91198058476115,52.47216237542131],"type":"Point"}
}