{
  "type": "Feature",
  "properties": {
    "iso:country": "GB",
    "wof:name": "B15 1NX",
    "wof:placetype": "postalcode"
  },
  "geometry": {"coordinates":[-1.911981,52.472162],"type":"Point"}
}
