{
  "type": "Feature",
  "properties": {
    "date:inception_lower":"2010-03-01",
    "date:inception_upper":"2010-03-31",
    "iso:country":"GB",
    "wof:name":"B15 1NX",
    "wof:placetype":"postalcode"
},
  "geometry": {"coordinates":[-1.911981,52.472162],"type":"Point"}
}