{
  "type": "Feature",
  "properties": {
    "iso:country":"GB",
    "wof:name":"WN2 3JP",
    "wof:placetype":"postalcode"
},
  "geometry": {"coordinates":[-2.58060344588533,53.53020184283779],"type":"Point"}
}