{
  "type": "Feature",
  "properties": {
    "date:inception_lower": "1990-02-01",
    "date:inception_upper": "1990-02-01",
    "iso:country": "GB",
    "wof:name": "WN2 3JP",
    "wof:placetype": "postalcode"
  },
  "geometry": {"coordinates":[-2.580603,53.530202],"type":"Point"}
}
