{
  "type": "Feature",
  "properties": {
    "iso:country":"GB",
    "wof:name":"SN10 3HD",
    "wof:placetype":"postalcode"
},
  "geometry": {"coordinates":[-1.97136136495824,51.35075620163445],"type":"Point"}
}