{
  "type": "Feature",
  "properties": {
    "iso:country":"GB",
    "wof:name":"SO21 2JB",
    "wof:placetype":"postalcode"
},
  "geometry": {"coordinates":[-1.39164698766793,51.02441545036714],"type":"Point"}
}