{
  "type": "Feature",
  "properties": {
    "date:inception_lower": "1980-01-01",
    "date:inception_upper": "1980-01-01",
    "iso:country": "GB",
    "wof:name": "IG10 1NN",
    "wof:placetype": "postalcode"
  },
  "geometry": {"coordinates":[0.065279,51.650442],"type":"Point"}
}
