{
  "type": "Feature",
  "properties": {
    "iso:country":"GB",
    "wof:name":"IV51 9DB",
    "wof:placetype":"postalcode"
},
  "geometry": {"coordinates":[-6.19212568127095,57.41242287688872],"type":"Point"}
}