{
  "type": "Feature",
  "properties": {
    "date:inception_lower":"1980-01-01",
    "date:inception_upper":"1980-01-31",
    "iso:country":"GB",
    "wof:name":"IV51 9DB",
    "wof:placetype":"postalcode"
},
  "geometry": {"coordinates":[-6.192144,57.412378],"type":"Point"}
}