{
  "type": "Feature",
  "properties": {
    "iso:country":"GB",
    "wof:name":"N1 6FS",
    "wof:placetype":"postalcode"
},
  "geometry": {"coordinates":[-0.08772514565666,51.5276153212026],"type":"Point"}
}