{
  "type": "Feature",
  "properties": {
    "date:inception_lower": "1980-01-01",
    "date:inception_upper": "1980-01-01",
    "iso:country": "GB",
    "wof:name": "PE31 8PF",
    "wof:placetype": "postalcode"
  },
  "geometry": {"coordinates":[0.652097,52.920764],"type":"Point"}
}
