{
  "type": "Feature",
  "properties": {
    "iso:country":"GB",
    "wof:name":"PE31 8PF",
    "wof:placetype":"postalcode"
},
  "geometry": {"coordinates":[0.65209665396622,52.9207641243766],"type":"Point"}
}