{
  "type": "Feature",
  "properties": {
    "date:inception_lower":"1992-08-01",
    "date:inception_upper":"1992-08-31",
    "iso:country":"GB",
    "wof:name":"LE18 3TA",
    "wof:placetype":"postalcode"
},
  "geometry": {"coordinates":[-1.095496,52.571542],"type":"Point"}
}