{
  "type": "Feature",
  "properties": {
    "iso:country": "GB",
    "wof:name": "LE18 3TA",
    "wof:placetype": "postalcode"
  },
  "geometry": {"coordinates":[-1.095496,52.571542],"type":"Point"}
}
