{
  "type": "Feature",
  "properties": {
    "iso:country":"GB",
    "wof:name":"TA3 7DA",
    "wof:placetype":"postalcode"
},
  "geometry": {"coordinates":[-3.08258667777456,50.95133271757712],"type":"Point"}
}