{
  "type": "Feature",
  "properties": {
    "iso:country": "GB",
    "wof:name": "S45 0BJ",
    "wof:placetype": "postalcode"
  },
  "geometry": {"coordinates":[-1.469237,53.132036],"type":"Point"}
}
