{
  "type": "Feature",
  "properties": {
    "iso:country":"GB",
    "wof:name":"PE19 8EA",
    "wof:placetype":"postalcode"
},
  "geometry": {"coordinates":[-0.28759236928792,52.22175272617051],"type":"Point"}
}