{
  "type": "Feature",
  "properties": {
    "iso:country": "GB",
    "wof:name": "PE19 8EA",
    "wof:placetype": "postalcode"
  },
  "geometry": {"coordinates":[-0.287592,52.221753],"type":"Point"}
}
