{
  "type": "Feature",
  "properties": {
    "iso:country":"GB",
    "wof:name":"WA10 2UN",
    "wof:placetype":"postalcode"
},
  "geometry": {"coordinates":[-2.74117768050656,53.46784078351411],"type":"Point"}
}