{
  "type": "Feature",
  "properties": {
    "date:inception_lower": "2016-04-01",
    "date:inception_upper": "2016-04-01",
    "iso:country": "GB",
    "wof:name": "WA10 2UN",
    "wof:placetype": "postalcode"
  },
  "geometry": {"coordinates":[-2.741178,53.467841],"type":"Point"}
}
