{
  "type": "Feature",
  "properties": {
    "iso:country":"GB",
    "wof:name":"DL6 2PG",
    "wof:placetype":"postalcode"
},
  "geometry": {"coordinates":[-1.43689650410101,54.35850206920065],"type":"Point"}
}