{
  "type": "Feature",
  "properties": {
    "iso:country": "GB",
    "wof:name": "DL6 2PG",
    "wof:placetype": "postalcode"
  },
  "geometry": {"coordinates":[-1.436906,54.358514],"type":"Point"}
}
