{
  "type": "Feature",
  "properties": {
    "iso:country": "GB",
    "wof:name": "CF83 8FL",
    "wof:placetype": "postalcode"
  },
  "geometry": {"coordinates":[-3.184629,51.592037],"type":"Point"}
}
