{
  "type": "Feature",
  "properties": {
    "iso:country":"GB",
    "wof:name":"CF83 8FL",
    "wof:placetype":"postalcode"
},
  "geometry": {"coordinates":[-3.18462858646908,51.59203671712652],"type":"Point"}
}