{
  "type": "Feature",
  "properties": {
    "iso:country": "GB",
    "wof:name": "DL11 6BL",
    "wof:placetype": "postalcode"
  },
  "geometry": {"coordinates":[-1.776839,54.397491],"type":"Point"}
}
