{
  "type": "Feature",
  "properties": {
    "iso:country":"GB",
    "wof:name":"DL11 6BL",
    "wof:placetype":"postalcode"
},
  "geometry": {"coordinates":[-1.77666437344096,54.39738091677157],"type":"Point"}
}