{
  "type": "Feature",
  "properties": {
    "date:inception_lower": "2021-02-01",
    "date:inception_upper": "2021-02-01",
    "iso:country": "GB",
    "wof:name": "WA5 1AU",
    "wof:placetype": "postalcode"
  },
  "geometry": {"coordinates":[-2.605081,53.392148],"type":"Point"}
}
