{
  "type": "Feature",
  "properties": {
    "iso:country":"GB",
    "wof:name":"UB3 1PE",
    "wof:placetype":"postalcode"
},
  "geometry": {"coordinates":[-0.43737336335079,51.49747251507206],"type":"Point"}
}