{
  "type": "Feature",
  "properties": {
    "iso:country":"GB",
    "wof:name":"BS3 5QU",
    "wof:placetype":"postalcode"
},
  "geometry": {"coordinates":[-2.59938587983131,51.42799269162997],"type":"Point"}
}