{
  "type": "Feature",
  "properties": {
    "date:inception_lower":"1980-01-01",
    "date:inception_upper":"1980-01-31",
    "iso:country":"GB",
    "wof:name":"SS4 1QA",
    "wof:placetype":"postalcode"
},
  "geometry": {"coordinates":[0.703121,51.586987],"type":"Point"}
}