{
  "type": "Feature",
  "properties": {
    "iso:country": "GB",
    "wof:name": "LL52 0PT",
    "wof:placetype": "postalcode"
  },
  "geometry": {"coordinates":[-4.19841,52.933192],"type":"Point"}
}
