{
  "type": "Feature",
  "properties": {
    "iso:country":"GB",
    "wof:name":"LL52 0PT",
    "wof:placetype":"postalcode"
},
  "geometry": {"coordinates":[-4.19840985901848,52.93319225536707],"type":"Point"}
}