{
  "type": "Feature",
  "properties": {
    "date:inception_lower":"1980-01-01",
    "date:inception_upper":"1980-01-31",
    "iso:country":"GB",
    "wof:name":"LL52 0PT",
    "wof:placetype":"postalcode"
},
  "geometry": {"coordinates":[-4.19841,52.933192],"type":"Point"}
}