{
  "type": "Feature",
  "properties": {
    "date:inception_lower": "1980-01-01",
    "date:inception_upper": "1980-01-01",
    "iso:country": "GB",
    "wof:name": "TR19 7TN",
    "wof:placetype": "postalcode"
  },
  "geometry": {"coordinates":[-5.654322,50.153266],"type":"Point"}
}
