{
  "type": "Feature",
  "properties": {
    "iso:country":"GB",
    "wof:name":"TR19 7TN",
    "wof:placetype":"postalcode"
},
  "geometry": {"coordinates":[-5.65432250808183,50.15326576542051],"type":"Point"}
}