{
  "type": "Feature",
  "properties": {
    "iso:country":"GB",
    "wof:name":"HX7 8QP",
    "wof:placetype":"postalcode"
},
  "geometry": {"coordinates":[-2.00633367605652,53.76159310324507],"type":"Point"}
}