{
  "type": "Feature",
  "properties": {
    "iso:country": "GB",
    "wof:name": "HX7 8QP",
    "wof:placetype": "postalcode"
  },
  "geometry": {"coordinates":[-2.006334,53.761593],"type":"Point"}
}
