{
  "type": "Feature",
  "properties": {
    "iso:country":"GB",
    "wof:name":"SE4 2PU",
    "wof:placetype":"postalcode"
},
  "geometry": {"coordinates":[-0.04092821011607,51.46243771533982],"type":"Point"}
}