{
  "type": "Feature",
  "properties": {
    "iso:country": "GB",
    "wof:name": "SE4 2PU",
    "wof:placetype": "postalcode"
  },
  "geometry": {"coordinates":[-0.040928,51.462438],"type":"Point"}
}
