{
  "type": "Feature",
  "properties": {
    "iso:country":"GB",
    "wof:name":"SP2 7GA",
    "wof:placetype":"postalcode"
},
  "geometry": {"coordinates":[-1.80251314027087,51.07190702098501],"type":"Point"}
}