{
  "type": "Feature",
  "properties": {
    "iso:country": "GB",
    "wof:name": "SO41 8NQ",
    "wof:placetype": "postalcode"
  },
  "geometry": {"coordinates":[-1.550308,50.750252],"type":"Point"}
}
