{
  "type": "Feature",
  "properties": {
    "iso:country":"GB",
    "wof:name":"KT22 8ED",
    "wof:placetype":"postalcode"
},
  "geometry": {"coordinates":[-0.32613460698477,51.29518077961035],"type":"Point"}
}