{
  "type": "Feature",
  "properties": {
    "iso:country": "GB",
    "wof:name": "DA1 1DN",
    "wof:placetype": "postalcode"
  },
  "geometry": {"coordinates":[0.218711,51.444897],"type":"Point"}
}
