{
  "type": "Feature",
  "properties": {
    "iso:country":"GB",
    "wof:name":"DA1 1DN",
    "wof:placetype":"postalcode"
},
  "geometry": {"coordinates":[0.2187105895887,51.44489706936726],"type":"Point"}
}