{
  "type": "Feature",
  "properties": {
    "iso:country":"GB",
    "wof:name":"SR8 5HU",
    "wof:placetype":"postalcode"
},
  "geometry": {"coordinates":[-1.33588728685383,54.76230529513896],"type":"Point"}
}