{
  "type": "Feature",
  "properties": {
    "iso:country": "GB",
    "wof:name": "SR8 5HU",
    "wof:placetype": "postalcode"
  },
  "geometry": {"coordinates":[-1.335887,54.762305],"type":"Point"}
}
