{
  "type": "Feature",
  "properties": {
    "iso:country":"GB",
    "wof:name":"EN8 9DN",
    "wof:placetype":"postalcode"
},
  "geometry": {"coordinates":[-0.03842002042706,51.70583255867481],"type":"Point"}
}