{
  "type": "Feature",
  "properties": {
    "iso:country": "GB",
    "wof:name": "EN8 9DN",
    "wof:placetype": "postalcode"
  },
  "geometry": {"coordinates":[-0.03842,51.705833],"type":"Point"}
}
