{
  "type": "Feature",
  "properties": {
    "date:inception_lower": "1985-04-01",
    "date:inception_upper": "1985-04-01",
    "iso:country": "GB",
    "wof:name": "PR5 5YZ",
    "wof:placetype": "postalcode"
  },
  "geometry": {"coordinates":[-2.677556,53.724201],"type":"Point"}
}
