{
  "type": "Feature",
  "properties": {
    "iso:country":"GB",
    "wof:name":"PR5 5YZ",
    "wof:placetype":"postalcode"
},
  "geometry": {"coordinates":[-2.67755577540388,53.72420053852938],"type":"Point"}
}