{
  "type": "Feature",
  "properties": {
    "iso:country": "GB",
    "wof:name": "W1B 3AP",
    "wof:placetype": "postalcode"
  },
  "geometry": {"coordinates":[-0.14198,51.516241],"type":"Point"}
}
