{
  "type": "Feature",
  "properties": {
    "iso:country":"GB",
    "wof:name":"W1B 3AP",
    "wof:placetype":"postalcode"
},
  "geometry": {"coordinates":[-0.14214803575091,51.51627810727252],"type":"Point"}
}