{
  "type": "Feature",
  "properties": {
    "iso:country":"GB",
    "wof:name":"B91 3LA",
    "wof:placetype":"postalcode"
},
  "geometry": {"coordinates":[-1.78280737958873,52.39865527415312],"type":"Point"}
}