{
  "type": "Feature",
  "properties": {
    "iso:country": "GB",
    "wof:name": "B91 3LA",
    "wof:placetype": "postalcode"
  },
  "geometry": {"coordinates":[-1.782807,52.398655],"type":"Point"}
}
