{
  "type": "Feature",
  "properties": {
    "iso:country":"GB",
    "wof:name":"BN26 5JD",
    "wof:placetype":"postalcode"
},
  "geometry": {"coordinates":[0.23735184208777,50.82019709432036],"type":"Point"}
}