{
  "type": "Feature",
  "properties": {
    "iso:country":"GB",
    "wof:name":"WS11 1GU",
    "wof:placetype":"postalcode"
},
  "geometry": {"coordinates":[-2.0392069461165,52.6894449369551],"type":"Point"}
}