{
  "type": "Feature",
  "properties": {
    "date:inception_lower": "2004-01-01",
    "date:inception_upper": "2004-01-01",
    "iso:country": "GB",
    "wof:name": "WS11 1GU",
    "wof:placetype": "postalcode"
  },
  "geometry": {"coordinates":[-2.039186,52.689461],"type":"Point"}
}
