{
  "type": "Feature",
  "properties": {
    "iso:country":"GB",
    "wof:name":"BB3 1NG",
    "wof:placetype":"postalcode"
},
  "geometry": {"coordinates":[-2.47417394603084,53.69895983904517],"type":"Point"}
}