{
  "type": "Feature",
  "properties": {
    "date:inception_lower": "1980-01-01",
    "date:inception_upper": "1980-01-01",
    "iso:country": "GB",
    "wof:name": "BB3 1NG",
    "wof:placetype": "postalcode"
  },
  "geometry": {"coordinates":[-2.474174,53.69896],"type":"Point"}
}
