{
  "type": "Feature",
  "properties": {
    "iso:country":"GB",
    "wof:name":"BN10 8LS",
    "wof:placetype":"postalcode"
},
  "geometry": {"coordinates":[0.00118119360179,50.78925079125445],"type":"Point"}
}