{
  "type": "Feature",
  "properties": {
    "iso:country":"GB",
    "wof:name":"TN16 3PL",
    "wof:placetype":"postalcode"
},
  "geometry": {"coordinates":[0.02181390149319,51.30468954643429],"type":"Point"}
}