{
  "type": "Feature",
  "properties": {
    "iso:country": "GB",
    "wof:name": "LE3 2HE",
    "wof:placetype": "postalcode"
  },
  "geometry": {"coordinates":[-1.171799,52.608168],"type":"Point"}
}
