{
  "type": "Feature",
  "properties": {
    "iso:country":"GB",
    "wof:name":"LE3 2HE",
    "wof:placetype":"postalcode"
},
  "geometry": {"coordinates":[-1.17179856194477,52.60816801304991],"type":"Point"}
}