{
  "type": "Feature",
  "properties": {
    "iso:country": "GB",
    "wof:name": "TN15 6AY",
    "wof:placetype": "postalcode"
  },
  "geometry": {"coordinates":[0.270472,51.347562],"type":"Point"}
}
