{
  "type": "Feature",
  "properties": {
    "iso:country": "GB",
    "wof:name": "LS29 9PQ",
    "wof:placetype": "postalcode"
  },
  "geometry": {"coordinates":[-1.838265,53.923581],"type":"Point"}
}
