{
  "type": "Feature",
  "properties": {
    "iso:country":"GB",
    "wof:name":"LS29 9PQ",
    "wof:placetype":"postalcode"
},
  "geometry": {"coordinates":[-1.83826485707879,53.92358129436264],"type":"Point"}
}