{
  "type": "Feature",
  "properties": {
    "date:inception_lower":"1980-01-01",
    "date:inception_upper":"1980-01-31",
    "iso:country":"GB",
    "wof:name":"ST6 8RG",
    "wof:placetype":"postalcode"
},
  "geometry": {"coordinates":[-2.148054,53.078409],"type":"Point"}
}