{
  "type": "Feature",
  "properties": {
    "iso:country": "GB",
    "wof:name": "ST6 8RG",
    "wof:placetype": "postalcode"
  },
  "geometry": {"coordinates":[-2.148054,53.078409],"type":"Point"}
}
