{
  "type": "Feature",
  "properties": {
    "iso:country":"GB",
    "wof:name":"PO31 7SY",
    "wof:placetype":"postalcode"
},
  "geometry": {"coordinates":[-1.29920873358872,50.76097397852323],"type":"Point"}
}