{
  "type": "Feature",
  "properties": {
    "iso:country":"GB",
    "wof:name":"TS29 6AY",
    "wof:placetype":"postalcode"
},
  "geometry": {"coordinates":[-1.40013813137991,54.71883869808195],"type":"Point"}
}