{
  "type": "Feature",
  "properties": {
    "iso:country": "GB",
    "wof:name": "TS29 6AY",
    "wof:placetype": "postalcode"
  },
  "geometry": {"coordinates":[-1.400138,54.718839],"type":"Point"}
}
