{
  "type": "Feature",
  "properties": {
    "date:inception_lower":"1980-01-01",
    "date:inception_upper":"1980-01-31",
    "iso:country":"GB",
    "wof:name":"TS29 6AY",
    "wof:placetype":"postalcode"
},
  "geometry": {"coordinates":[-1.400138,54.718839],"type":"Point"}
}