{
  "type": "Feature",
  "properties": {
    "date:inception_lower": "1980-01-01",
    "date:inception_upper": "1980-01-01",
    "iso:country": "GB",
    "wof:name": "BH16 5QB",
    "wof:placetype": "postalcode"
  },
  "geometry": {"coordinates":[-2.03526,50.742137],"type":"Point"}
}
