{
  "type": "Feature",
  "properties": {
    "iso:country":"GB",
    "wof:name":"PA75 6QP",
    "wof:placetype":"postalcode"
},
  "geometry": {"coordinates":[-6.07385752948559,56.62190517040897],"type":"Point"}
}