{
  "type": "Feature",
  "properties": {
    "iso:country": "GB",
    "wof:name": "PA75 6QP",
    "wof:placetype": "postalcode"
  },
  "geometry": {"coordinates":[-6.073818,56.622066],"type":"Point"}
}
