{
  "type": "Feature",
  "properties": {
    "iso:country": "GB",
    "wof:name": "W8 5PU",
    "wof:placetype": "postalcode"
  },
  "geometry": {"coordinates":[-0.187466,51.497653],"type":"Point"}
}
