{
  "type": "Feature",
  "properties": {
    "iso:country":"GB",
    "wof:name":"W8 5PU",
    "wof:placetype":"postalcode"
},
  "geometry": {"coordinates":[-0.18746654021375,51.49765337808626],"type":"Point"}
}