{
  "type": "Feature",
  "properties": {
    "iso:country":"GB",
    "wof:name":"DT11 7HU",
    "wof:placetype":"postalcode"
},
  "geometry": {"coordinates":[-2.15803648172532,50.8627065109274],"type":"Point"}
}