{
  "type": "Feature",
  "properties": {
    "iso:country":"GB",
    "wof:name":"SE12 8SR",
    "wof:placetype":"postalcode"
},
  "geometry": {"coordinates":[0.01263242109089,51.45538837169514],"type":"Point"}
}