{
  "type": "Feature",
  "properties": {
    "iso:country":"GB",
    "wof:name":"DL7 8HU",
    "wof:placetype":"postalcode"
},
  "geometry": {"coordinates":[-1.45000821782555,54.32728680257672],"type":"Point"}
}