{
  "type": "Feature",
  "properties": {
    "iso:country": "GB",
    "wof:name": "CV2 5FD",
    "wof:placetype": "postalcode"
  },
  "geometry": {"coordinates":[-1.461688,52.413363],"type":"Point"}
}
