{
  "type": "Feature",
  "properties": {
    "iso:country": "GB",
    "wof:name": "PA16 0PP",
    "wof:placetype": "postalcode"
  },
  "geometry": {"coordinates":[-4.824263,55.945954],"type":"Point"}
}
