{
  "type": "Feature",
  "properties": {
    "iso:country": "GB",
    "wof:name": "NE65 7ND",
    "wof:placetype": "postalcode"
  },
  "geometry": {"coordinates":[-1.955651,55.314063],"type":"Point"}
}
