{
  "type": "Feature",
  "properties": {
    "iso:country":"GB",
    "wof:name":"NE65 7ND",
    "wof:placetype":"postalcode"
},
  "geometry": {"coordinates":[-1.95565124271171,55.31406285778558],"type":"Point"}
}