{
  "type": "Feature",
  "properties": {
    "date:inception_lower":"1980-01-01",
    "date:inception_upper":"1980-01-31",
    "iso:country":"GB",
    "wof:name":"NE65 7ND",
    "wof:placetype":"postalcode"
},
  "geometry": {"coordinates":[-1.955651,55.314063],"type":"Point"}
}