{
  "type": "Feature",
  "properties": {
    "iso:country":"GB",
    "wof:name":"SA12 6JX",
    "wof:placetype":"postalcode"
},
  "geometry": {"coordinates":[-3.8128063320453,51.59403059761033],"type":"Point"}
}