{
  "type": "Feature",
  "properties": {
    "iso:country":"GB",
    "wof:name":"DE5 3JR",
    "wof:placetype":"postalcode"
},
  "geometry": {"coordinates":[-1.38894429663782,53.04582218295626],"type":"Point"}
}