{
  "type": "Feature",
  "properties": {
    "iso:country": "GB",
    "wof:name": "SO16 0BP",
    "wof:placetype": "postalcode"
  },
  "geometry": {"coordinates":[-1.466033,50.9392],"type":"Point"}
}
