{
  "type": "Feature",
  "properties": {
    "iso:country":"GB",
    "wof:name":"L35 0NJ",
    "wof:placetype":"postalcode"
},
  "geometry": {"coordinates":[-2.76843612331601,53.41404178223585],"type":"Point"}
}