{
  "type": "Feature",
  "properties": {
    "iso:country":"GB",
    "wof:name":"LL14 4AJ",
    "wof:placetype":"postalcode"
},
  "geometry": {"coordinates":[-3.02599617943117,53.03063898569761],"type":"Point"}
}