{
  "type": "Feature",
  "properties": {
    "iso:country":"GB",
    "wof:name":"M22 8EN",
    "wof:placetype":"postalcode"
},
  "geometry": {"coordinates":[-2.26312731790029,53.39278295795526],"type":"Point"}
}