{
  "type": "Feature",
  "properties": {
    "iso:country":"GB",
    "wof:name":"WA1 1LT",
    "wof:placetype":"postalcode"
},
  "geometry": {"coordinates":[-2.60219168305449,53.38763451580136],"type":"Point"}
}