{
  "type": "Feature",
  "properties": {
    "date:inception_lower": "1980-01-01",
    "date:inception_upper": "1980-01-01",
    "iso:country": "GB",
    "wof:name": "WA1 1LT",
    "wof:placetype": "postalcode"
  },
  "geometry": {"coordinates":[-2.602192,53.387635],"type":"Point"}
}
