{
  "type": "Feature",
  "properties": {
    "date:inception_lower": "1980-01-01",
    "date:inception_upper": "1980-01-01",
    "iso:country": "GB",
    "wof:name": "DT6 5JW",
    "wof:placetype": "postalcode"
  },
  "geometry": {"coordinates":[-2.79503,50.774277],"type":"Point"}
}
