{
  "type": "Feature",
  "properties": {
    "iso:country":"GB",
    "wof:name":"SO15 8QE",
    "wof:placetype":"postalcode"
},
  "geometry": {"coordinates":[-1.43634840368901,50.91835868244162],"type":"Point"}
}