{
  "type": "Feature",
  "properties": {
    "iso:country": "GB",
    "wof:name": "SN10 2GY",
    "wof:placetype": "postalcode"
  },
  "geometry": {"coordinates":[-1.998278,51.367589],"type":"Point"}
}
