{
  "type": "Feature",
  "properties": {
    "iso:country": "GB",
    "wof:name": "HU17 0PX",
    "wof:placetype": "postalcode"
  },
  "geometry": {"coordinates":[-0.412487,53.840794],"type":"Point"}
}
