{
  "type": "Feature",
  "properties": {
    "iso:country":"GB",
    "wof:name":"B43 5NU",
    "wof:placetype":"postalcode"
},
  "geometry": {"coordinates":[-1.93199319981491,52.53526680793356],"type":"Point"}
}