{
  "type": "Feature",
  "properties": {
    "iso:country": "GB",
    "wof:name": "BD19 4DP",
    "wof:placetype": "postalcode"
  },
  "geometry": {"coordinates":[-1.715108,53.737302],"type":"Point"}
}
