{
  "type": "Feature",
  "properties": {
    "date:inception_lower": "1980-01-01",
    "date:inception_upper": "1980-01-01",
    "iso:country": "GB",
    "wof:name": "SS8 0AA",
    "wof:placetype": "postalcode"
  },
  "geometry": {"coordinates":[0.592051,51.51841],"type":"Point"}
}
