{
  "type": "Feature",
  "properties": {
    "iso:country":"GB",
    "wof:name":"SS8 0AA",
    "wof:placetype":"postalcode"
},
  "geometry": {"coordinates":[0.59205108084561,51.51840975115693],"type":"Point"}
}