{
  "type": "Feature",
  "properties": {
    "iso:country":"GB",
    "wof:name":"LE4 0AR",
    "wof:placetype":"postalcode"
},
  "geometry": {"coordinates":[-1.1460465819333,52.6467590619788],"type":"Point"}
}