{
  "type": "Feature",
  "properties": {
    "iso:country":"GB",
    "wof:name":"B15 2AU",
    "wof:placetype":"postalcode"
},
  "geometry": {"coordinates":[-1.90280909390798,52.472164206907],"type":"Point"}
}