{
  "type": "Feature",
  "properties": {
    "date:inception_lower":"1980-01-01",
    "date:inception_upper":"1980-01-31",
    "iso:country":"GB",
    "wof:name":"B15 2AU",
    "wof:placetype":"postalcode"
},
  "geometry": {"coordinates":[-1.902809,52.472164],"type":"Point"}
}