{
  "type": "Feature",
  "properties": {
    "iso:country":"GB",
    "wof:name":"SK12 1HF",
    "wof:placetype":"postalcode"
},
  "geometry": {"coordinates":[-2.13260815667997,53.35060926170375],"type":"Point"}
}