{
  "type": "Feature",
  "properties": {
    "iso:country": "GB",
    "wof:name": "DT3 6AA",
    "wof:placetype": "postalcode"
  },
  "geometry": {"coordinates":[-2.435567,50.644907],"type":"Point"}
}
