{
  "type": "Feature",
  "properties": {
    "iso:country": "GB",
    "wof:name": "SK14 8QL",
    "wof:placetype": "postalcode"
  },
  "geometry": {"coordinates":[-1.98859,53.462186],"type":"Point"}
}
