{
  "type": "Feature",
  "properties": {
    "iso:country": "GB",
    "wof:name": "LL55 2HW",
    "wof:placetype": "postalcode"
  },
  "geometry": {"coordinates":[-4.269713,53.135229],"type":"Point"}
}
