{
  "type": "Feature",
  "properties": {
    "iso:country":"GB",
    "wof:name":"LL55 2HW",
    "wof:placetype":"postalcode"
},
  "geometry": {"coordinates":[-4.26971260407971,53.1352288305769],"type":"Point"}
}