{
  "type": "Feature",
  "properties": {
    "iso:country":"GB",
    "wof:name":"WV6 7XS",
    "wof:placetype":"postalcode"
},
  "geometry": {"coordinates":[-2.20911494900933,52.59526105444527],"type":"Point"}
}