{
  "type": "Feature",
  "properties": {
    "date:inception_lower": "2023-04-01",
    "date:inception_upper": "2023-04-01",
    "iso:country": "GB",
    "wof:name": "EX7 7BE",
    "wof:placetype": "postalcode"
  },
  "geometry": {"coordinates":[-3.470748,50.580153],"type":"Point"}
}
