{
  "type": "Feature",
  "properties": {
    "iso:country":"GB",
    "wof:name":"WA3 2NF",
    "wof:placetype":"postalcode"
},
  "geometry": {"coordinates":[-2.56380588699072,53.47404103243473],"type":"Point"}
}