{
  "type": "Feature",
  "properties": {
    "iso:country":"GB",
    "wof:name":"FY3 7EQ",
    "wof:placetype":"postalcode"
},
  "geometry": {"coordinates":[-3.02103295928569,53.82685791050278],"type":"Point"}
}