{
  "type": "Feature",
  "properties": {
    "date:inception_lower": "2023-05-01",
    "date:inception_upper": "2023-05-01",
    "iso:country": "GB",
    "wof:name": "TS1 9HT",
    "wof:placetype": "postalcode"
  },
  "geometry": {"coordinates":[-1.244956,54.575865],"type":"Point"}
}
