{
  "type": "Feature",
  "properties": {
    "iso:country": "GB",
    "wof:name": "AL10 9FY",
    "wof:placetype": "postalcode"
  },
  "geometry": {"coordinates":[-0.240343,51.773504],"type":"Point"}
}
