{
  "type": "Feature",
  "properties": {
    "date:inception_lower": "2002-08-01",
    "date:inception_upper": "2002-08-01",
    "iso:country": "GB",
    "wof:name": "AL10 9FY",
    "wof:placetype": "postalcode"
  },
  "geometry": {"coordinates":[-0.240343,51.773504],"type":"Point"}
}
