{
  "type": "Feature",
  "properties": {
    "iso:country":"GB",
    "wof:name":"SY11 4JY",
    "wof:placetype":"postalcode"
},
  "geometry": {"coordinates":[-2.97017431764314,52.82075920573236],"type":"Point"}
}