{
  "type": "Feature",
  "properties": {
    "iso:country": "GB",
    "wof:name": "SY11 4JY",
    "wof:placetype": "postalcode"
  },
  "geometry": {"coordinates":[-2.970174,52.820759],"type":"Point"}
}
