{
  "type": "Feature",
  "properties": {
    "iso:country":"GB",
    "wof:name":"PE14 7RF",
    "wof:placetype":"postalcode"
},
  "geometry": {"coordinates":[0.24313484189986,52.69547213529488],"type":"Point"}
}