{
  "type": "Feature",
  "properties": {
    "iso:country":"GB",
    "wof:name":"EX6 8DD",
    "wof:placetype":"postalcode"
},
  "geometry": {"coordinates":[-3.49484863764023,50.67920919885301],"type":"Point"}
}