{
  "type": "Feature",
  "properties": {
    "date:inception_lower": "1980-01-01",
    "date:inception_upper": "1980-01-01",
    "iso:country": "GB",
    "wof:name": "EX6 8DD",
    "wof:placetype": "postalcode"
  },
  "geometry": {"coordinates":[-3.494862,50.679198],"type":"Point"}
}
