{
  "type": "Feature",
  "properties": {
    "iso:country": "GB",
    "wof:name": "EX6 8DD",
    "wof:placetype": "postalcode"
  },
  "geometry": {"coordinates":[-3.494817,50.679108],"type":"Point"}
}
