{
  "type": "Feature",
  "properties": {
    "date:inception_lower":"1980-01-01",
    "date:inception_upper":"1980-01-31",
    "iso:country":"GB",
    "wof:name":"PL16 0HE",
    "wof:placetype":"postalcode"
},
  "geometry": {"coordinates":[-4.228386,50.62277],"type":"Point"}
}