{
  "type": "Feature",
  "properties": {
    "date:inception_lower": "2007-09-01",
    "date:inception_upper": "2007-09-01",
    "iso:country": "GB",
    "wof:name": "CV22 7XG",
    "wof:placetype": "postalcode"
  },
  "geometry": {"coordinates":[-1.290584,52.3602],"type":"Point"}
}
