{
  "type": "Feature",
  "properties": {
    "date:inception_lower":"1980-01-01",
    "date:inception_upper":"1980-01-31",
    "iso:country":"GB",
    "wof:name":"LL17 0LU",
    "wof:placetype":"postalcode"
},
  "geometry": {"coordinates":[-3.449785,53.258071],"type":"Point"}
}