{
  "type": "Feature",
  "properties": {
    "date:inception_lower": "1980-01-01",
    "date:inception_upper": "1980-01-01",
    "iso:country": "GB",
    "wof:name": "LL17 0LU",
    "wof:placetype": "postalcode"
  },
  "geometry": {"coordinates":[-3.449894,53.258178],"type":"Point"}
}
