{
  "type": "Feature",
  "properties": {
    "iso:country":"GB",
    "wof:name":"LL17 0LU",
    "wof:placetype":"postalcode"
},
  "geometry": {"coordinates":[-3.44978356154818,53.25805497914097],"type":"Point"}
}