{
  "type": "Feature",
  "properties": {
    "iso:country":"GB",
    "wof:name":"NG9 6DB",
    "wof:placetype":"postalcode"
},
  "geometry": {"coordinates":[-1.22111054889484,52.91290435453612],"type":"Point"}
}