{
  "type": "Feature",
  "properties": {
    "iso:country": "GB",
    "wof:name": "NG9 6DB",
    "wof:placetype": "postalcode"
  },
  "geometry": {"coordinates":[-1.221111,52.912904],"type":"Point"}
}
