{
  "type": "Feature",
  "properties": {
    "iso:country":"GB",
    "wof:name":"RG27 9JJ",
    "wof:placetype":"postalcode"
},
  "geometry": {"coordinates":[-0.97731047453137,51.27531469319282],"type":"Point"}
}