{
  "type": "Feature",
  "properties": {
    "iso:country": "GB",
    "wof:name": "BS10 5DY",
    "wof:placetype": "postalcode"
  },
  "geometry": {"coordinates":[-2.600979,51.495528],"type":"Point"}
}
