{
  "type": "Feature",
  "properties": {
    "iso:country":"GB",
    "wof:name":"CO3 9AS",
    "wof:placetype":"postalcode"
},
  "geometry": {"coordinates":[0.84983254135045,51.88840977205361],"type":"Point"}
}