{
  "type": "Feature",
  "properties": {
    "iso:country": "GB",
    "wof:name": "CO3 9AS",
    "wof:placetype": "postalcode"
  },
  "geometry": {"coordinates":[0.849833,51.88841],"type":"Point"}
}
