{
  "type": "Feature",
  "properties": {
    "iso:country":"GB",
    "wof:name":"PO36 0HW",
    "wof:placetype":"postalcode"
},
  "geometry": {"coordinates":[-1.15253365970871,50.67457747276996],"type":"Point"}
}