{
  "type": "Feature",
  "properties": {
    "iso:country": "GB",
    "wof:name": "PO36 0HW",
    "wof:placetype": "postalcode"
  },
  "geometry": {"coordinates":[-1.152534,50.674577],"type":"Point"}
}
