{
  "type": "Feature",
  "properties": {
    "iso:country":"GB",
    "wof:name":"G41 2PT",
    "wof:placetype":"postalcode"
},
  "geometry": {"coordinates":[-4.2710937054123,55.83776612742553],"type":"Point"}
}