{
  "type": "Feature",
  "properties": {
    "iso:country":"GB",
    "wof:name":"HR4 7JZ",
    "wof:placetype":"postalcode"
},
  "geometry": {"coordinates":[-2.88797555650982,52.08339091703976],"type":"Point"}
}