{
  "type": "Feature",
  "properties": {
    "iso:country": "GB",
    "wof:name": "HR4 7JZ",
    "wof:placetype": "postalcode"
  },
  "geometry": {"coordinates":[-2.887976,52.083391],"type":"Point"}
}
