{
  "type": "Feature",
  "properties": {
    "date:inception_lower": "1980-01-01",
    "date:inception_upper": "1980-01-01",
    "iso:country": "GB",
    "wof:name": "HR4 7JZ",
    "wof:placetype": "postalcode"
  },
  "geometry": {"coordinates":[-2.887976,52.083391],"type":"Point"}
}
