{
  "type": "Feature",
  "properties": {
    "date:inception_lower": "1980-01-01",
    "date:inception_upper": "1980-01-01",
    "iso:country": "GB",
    "wof:name": "PE25 2PG",
    "wof:placetype": "postalcode"
  },
  "geometry": {"coordinates":[0.320836,53.153009],"type":"Point"}
}
