{
  "type": "Feature",
  "properties": {
    "iso:country":"GB",
    "wof:name":"PE25 2PG",
    "wof:placetype":"postalcode"
},
  "geometry": {"coordinates":[0.32085104265791,53.15300803667398],"type":"Point"}
}