{
  "type": "Feature",
  "properties": {
    "date:inception_lower": "1982-03-01",
    "date:inception_upper": "1982-03-01",
    "iso:country": "GB",
    "wof:name": "BA14 9TJ",
    "wof:placetype": "postalcode"
  },
  "geometry": {"coordinates":[-2.228916,51.320305],"type":"Point"}
}
