{
  "type": "Feature",
  "properties": {
    "iso:country":"GB",
    "wof:name":"CV32 7LT",
    "wof:placetype":"postalcode"
},
  "geometry": {"coordinates":[-1.50127113545783,52.3124232018502],"type":"Point"}
}