{
  "type": "Feature",
  "properties": {
    "iso:country":"GB",
    "wof:name":"DD9 7TJ",
    "wof:placetype":"postalcode"
},
  "geometry": {"coordinates":[-2.65635990949393,56.80949935290017],"type":"Point"}
}