{
  "type": "Feature",
  "properties": {
    "date:inception_lower": "1980-01-01",
    "date:inception_upper": "1980-01-01",
    "iso:country": "GB",
    "wof:name": "DD9 7TJ",
    "wof:placetype": "postalcode"
  },
  "geometry": {"coordinates":[-2.65636,56.809517],"type":"Point"}
}
