{
  "type": "Feature",
  "properties": {
    "iso:country": "GB",
    "wof:name": "HP17 8FL",
    "wof:placetype": "postalcode"
  },
  "geometry": {"coordinates":[-0.918655,51.771293],"type":"Point"}
}
