{
  "type": "Feature",
  "properties": {
    "iso:country": "GB",
    "wof:name": "PE12 9PB",
    "wof:placetype": "postalcode"
  },
  "geometry": {"coordinates":[0.13689,52.836587],"type":"Point"}
}
