{
  "type": "Feature",
  "properties": {
    "date:inception_lower":"1980-01-01",
    "date:inception_upper":"1980-01-31",
    "iso:country":"GB",
    "wof:name":"PE12 9PB",
    "wof:placetype":"postalcode"
},
  "geometry": {"coordinates":[0.13689,52.836587],"type":"Point"}
}