{
  "type": "Feature",
  "properties": {
    "iso:country":"GB",
    "wof:name":"PE12 9PB",
    "wof:placetype":"postalcode"
},
  "geometry": {"coordinates":[0.13683101161121,52.83653011843909],"type":"Point"}
}