{
  "type": "Feature",
  "properties": {
    "iso:country":"GB",
    "wof:name":"LE18 3YD",
    "wof:placetype":"postalcode"
},
  "geometry": {"coordinates":[-1.09362941383251,52.58120997033225],"type":"Point"}
}