{
  "type": "Feature",
  "properties": {
    "iso:country":"GB",
    "wof:name":"SS16 6DQ",
    "wof:placetype":"postalcode"
},
  "geometry": {"coordinates":[0.41324186413737,51.56710215980812],"type":"Point"}
}