{
  "type": "Feature",
  "properties": {
    "iso:country":"GB",
    "wof:name":"IP20 0HS",
    "wof:placetype":"postalcode"
},
  "geometry": {"coordinates":[1.34512032417066,52.41507935147835],"type":"Point"}
}