{
  "type": "Feature",
  "properties": {
    "iso:country": "GB",
    "wof:name": "IP20 0HS",
    "wof:placetype": "postalcode"
  },
  "geometry": {"coordinates":[1.345428,52.414715],"type":"Point"}
}
