{
  "type": "Feature",
  "properties": {
    "iso:country": "GB",
    "wof:name": "EX17 5DR",
    "wof:placetype": "postalcode"
  },
  "geometry": {"coordinates":[-3.844427,50.75793],"type":"Point"}
}
