{
  "type": "Feature",
  "properties": {
    "date:inception_lower":"2010-11-01",
    "date:inception_upper":"2010-11-30",
    "iso:country":"GB",
    "wof:name":"EX17 5DR",
    "wof:placetype":"postalcode"
},
  "geometry": {"coordinates":[-3.844427,50.75793],"type":"Point"}
}