{
  "type": "Feature",
  "properties": {
    "iso:country":"GB",
    "wof:name":"CO4 9GF",
    "wof:placetype":"postalcode"
},
  "geometry": {"coordinates":[0.92189871224423,51.91647308406332],"type":"Point"}
}