{
  "type": "Feature",
  "properties": {
    "iso:country":"GB",
    "wof:name":"EH3 9BF",
    "wof:placetype":"postalcode"
},
  "geometry": {"coordinates":[-3.19386527465881,55.94303688396534],"type":"Point"}
}