{
  "type": "Feature",
  "properties": {
    "iso:country": "GB",
    "wof:name": "WV11 1SE",
    "wof:placetype": "postalcode"
  },
  "geometry": {"coordinates":[-2.090054,52.602523],"type":"Point"}
}
