{
  "type": "Feature",
  "properties": {
    "date:inception_lower": "1980-01-01",
    "date:inception_upper": "1980-01-01",
    "iso:country": "GB",
    "wof:name": "WV11 1SE",
    "wof:placetype": "postalcode"
  },
  "geometry": {"coordinates":[-2.090054,52.602523],"type":"Point"}
}
