{
  "type": "Feature",
  "properties": {
    "iso:country":"GB",
    "wof:name":"WV11 1SE",
    "wof:placetype":"postalcode"
},
  "geometry": {"coordinates":[-2.09005377313382,52.6025225957987],"type":"Point"}
}