{
  "type": "Feature",
  "properties": {
    "date:inception_lower": "1980-01-01",
    "date:inception_upper": "1980-01-01",
    "iso:country": "GB",
    "wof:name": "RM17 6LB",
    "wof:placetype": "postalcode"
  },
  "geometry": {"coordinates":[0.335264,51.47419],"type":"Point"}
}
