{
  "type": "Feature",
  "properties": {
    "iso:country":"GB",
    "wof:name":"NR30 2QH",
    "wof:placetype":"postalcode"
},
  "geometry": {"coordinates":[1.72540332103157,52.605323867634],"type":"Point"}
}