{
  "type": "Feature",
  "properties": {
    "iso:country": "GB",
    "wof:name": "BS5 7TG",
    "wof:placetype": "postalcode"
  },
  "geometry": {"coordinates":[-2.538075,51.467681],"type":"Point"}
}
