{
  "type": "Feature",
  "properties": {
    "iso:country":"GB",
    "wof:name":"TW13 4BA",
    "wof:placetype":"postalcode"
},
  "geometry": {"coordinates":[-0.41533296244965,51.4458938577131],"type":"Point"}
}