{
  "type": "Feature",
  "properties": {
    "iso:country":"GB",
    "wof:name":"S75 3NJ",
    "wof:placetype":"postalcode"
},
  "geometry": {"coordinates":[-1.5190264749259,53.53658778022419],"type":"Point"}
}