{
  "type": "Feature",
  "properties": {
    "iso:country":"GB",
    "wof:name":"DN5 8BT",
    "wof:placetype":"postalcode"
},
  "geometry": {"coordinates":[-1.16416109193378,53.52361465491672],"type":"Point"}
}