{
  "type": "Feature",
  "properties": {
    "date:inception_lower": "1980-01-01",
    "date:inception_upper": "1980-01-01",
    "iso:country": "GB",
    "wof:name": "SN11 0AY",
    "wof:placetype": "postalcode"
  },
  "geometry": {"coordinates":[-1.993996,51.430425],"type":"Point"}
}
