{
  "type": "Feature",
  "properties": {
    "iso:country": "GB",
    "wof:name": "W1F 9UJ",
    "wof:placetype": "postalcode"
  },
  "geometry": {"coordinates":[-0.135341,51.511431],"type":"Point"}
}
