{
  "type": "Feature",
  "properties": {
    "iso:country":"GB",
    "wof:name":"W1F 9UJ",
    "wof:placetype":"postalcode"
},
  "geometry": {"coordinates":[-0.13534126478347,51.51143103921479],"type":"Point"}
}