{
  "type": "Feature",
  "properties": {
    "iso:country":"GB",
    "wof:name":"TN39 4AQ",
    "wof:placetype":"postalcode"
},
  "geometry": {"coordinates":[0.46859331946181,50.84965579527046],"type":"Point"}
}