{
  "type": "Feature",
  "properties": {
    "date:inception_lower": "1980-01-01",
    "date:inception_upper": "1980-01-01",
    "iso:country": "GB",
    "wof:name": "TN39 4AQ",
    "wof:placetype": "postalcode"
  },
  "geometry": {"coordinates":[0.468593,50.849656],"type":"Point"}
}
