{
  "type": "Feature",
  "properties": {
    "iso:country": "GB",
    "wof:name": "RG17 0EE",
    "wof:placetype": "postalcode"
  },
  "geometry": {"coordinates":[-1.510684,51.412834],"type":"Point"}
}
