{
  "type": "Feature",
  "properties": {
    "iso:country":"GB",
    "wof:name":"RG17 0EE",
    "wof:placetype":"postalcode"
},
  "geometry": {"coordinates":[-1.51068425222255,51.41283380554736],"type":"Point"}
}