{
  "type": "Feature",
  "properties": {
    "iso:country": "GB",
    "wof:name": "M24 2FU",
    "wof:placetype": "postalcode"
  },
  "geometry": {"coordinates":[-2.181154,53.54698],"type":"Point"}
}
