{
  "type": "Feature",
  "properties": {
    "iso:country":"GB",
    "wof:name":"SA1 6HH",
    "wof:placetype":"postalcode"
},
  "geometry": {"coordinates":[-3.95014180551436,51.62479478968086],"type":"Point"}
}