{
  "type": "Feature",
  "properties": {
    "date:inception_lower": "2021-10-01",
    "date:inception_upper": "2021-10-01",
    "iso:country": "GB",
    "wof:name": "OX49 5BP",
    "wof:placetype": "postalcode"
  },
  "geometry": {"coordinates":[-1.015074,51.645449],"type":"Point"}
}
