{
  "type": "Feature",
  "properties": {
    "iso:country": "GB",
    "wof:name": "W1H 7RL",
    "wof:placetype": "postalcode"
  },
  "geometry": {"coordinates":[-0.158194,51.515461],"type":"Point"}
}
