{
  "type": "Feature",
  "properties": {
    "iso:country":"GB",
    "wof:name":"W1H 7RL",
    "wof:placetype":"postalcode"
},
  "geometry": {"coordinates":[-0.15819381045305,51.51546106204043],"type":"Point"}
}