{
  "type": "Feature",
  "properties": {
    "iso:country":"GB",
    "wof:name":"TS12 1DT",
    "wof:placetype":"postalcode"
},
  "geometry": {"coordinates":[-0.97201284721906,54.58469000924665],"type":"Point"}
}