{
  "type": "Feature",
  "properties": {
    "date:inception_lower": "1980-01-01",
    "date:inception_upper": "1980-01-01",
    "iso:country": "GB",
    "wof:name": "L4 2UQ",
    "wof:placetype": "postalcode"
  },
  "geometry": {"coordinates":[-2.948318,53.430349],"type":"Point"}
}
