{
  "type": "Feature",
  "properties": {
    "date:inception_lower": "1993-08-01",
    "date:inception_upper": "1993-08-01",
    "iso:country": "GB",
    "wof:name": "SY23 3TH",
    "wof:placetype": "postalcode"
  },
  "geometry": {"coordinates":[-4.065157,52.41966],"type":"Point"}
}
