{
  "type": "Feature",
  "properties": {
    "iso:country": "GB",
    "wof:name": "SY23 3TH",
    "wof:placetype": "postalcode"
  },
  "geometry": {"coordinates":[-4.065157,52.41966],"type":"Point"}
}
