{
  "type": "Feature",
  "properties": {
    "iso:country":"GB",
    "wof:name":"TN12 5DB",
    "wof:placetype":"postalcode"
},
  "geometry": {"coordinates":[0.38151639651384,51.21407820435706],"type":"Point"}
}