{
  "type": "Feature",
  "properties": {
    "iso:country": "GB",
    "wof:name": "TN12 5DB",
    "wof:placetype": "postalcode"
  },
  "geometry": {"coordinates":[0.381516,51.214078],"type":"Point"}
}
