{
  "type": "Feature",
  "properties": {
    "date:inception_lower": "2001-12-01",
    "date:inception_upper": "2001-12-01",
    "iso:country": "GB",
    "wof:name": "B79 7RU",
    "wof:placetype": "postalcode"
  },
  "geometry": {"coordinates":[-1.708294,52.634616],"type":"Point"}
}
