{
  "type": "Feature",
  "properties": {
    "iso:country":"GB",
    "wof:name":"B79 7RU",
    "wof:placetype":"postalcode"
},
  "geometry": {"coordinates":[-1.70829418392524,52.63461563393307],"type":"Point"}
}