{
  "type": "Feature",
  "properties": {
    "iso:country":"GB",
    "wof:name":"S35 0DY",
    "wof:placetype":"postalcode"
},
  "geometry": {"coordinates":[-1.5535186308248,53.45183412336256],"type":"Point"}
}