{
  "type": "Feature",
  "properties": {
    "date:inception_lower": "1997-06-01",
    "date:inception_upper": "1997-06-01",
    "iso:country": "GB",
    "wof:name": "S35 0DY",
    "wof:placetype": "postalcode"
  },
  "geometry": {"coordinates":[-1.553519,53.451834],"type":"Point"}
}
