{
  "type": "Feature",
  "properties": {
    "iso:country": "GB",
    "wof:name": "B70 0JU",
    "wof:placetype": "postalcode"
  },
  "geometry": {"coordinates":[-2.014845,52.530961],"type":"Point"}
}
