{
  "type": "Feature",
  "properties": {
    "iso:country":"GB",
    "wof:name":"B70 0JU",
    "wof:placetype":"postalcode"
},
  "geometry": {"coordinates":[-2.01484501662492,52.53096109611275],"type":"Point"}
}