{
  "type": "Feature",
  "properties": {
    "iso:country": "GB",
    "wof:name": "CH64 6TG",
    "wof:placetype": "postalcode"
  },
  "geometry": {"coordinates":[-3.081348,53.294786],"type":"Point"}
}
