{
  "type": "Feature",
  "properties": {
    "iso:country": "GB",
    "wof:name": "PR8 5DE",
    "wof:placetype": "postalcode"
  },
  "geometry": {"coordinates":[-3.004784,53.638417],"type":"Point"}
}
