{
  "type": "Feature",
  "properties": {
    "iso:country":"GB",
    "wof:name":"GU52 8AD",
    "wof:placetype":"postalcode"
},
  "geometry": {"coordinates":[-0.82502521326579,51.26031644109846],"type":"Point"}
}