{
  "type": "Feature",
  "properties": {
    "iso:country": "GB",
    "wof:name": "GU52 8AD",
    "wof:placetype": "postalcode"
  },
  "geometry": {"coordinates":[-0.820519,51.25929],"type":"Point"}
}
