{
  "type": "Feature",
  "properties": {
    "date:inception_lower":"2009-05-01",
    "date:inception_upper":"2009-05-31",
    "iso:country":"GB",
    "wof:name":"GU52 8AD",
    "wof:placetype":"postalcode"
},
  "geometry": {"coordinates":[-0.825022,51.260315],"type":"Point"}
}