{
  "type": "Feature",
  "properties": {
    "iso:country": "GB",
    "wof:name": "WD3 4NF",
    "wof:placetype": "postalcode"
  },
  "geometry": {"coordinates":[-0.463558,51.677611],"type":"Point"}
}
