{
  "type": "Feature",
  "properties": {
    "iso:country":"GB",
    "wof:name":"WD3 4NF",
    "wof:placetype":"postalcode"
},
  "geometry": {"coordinates":[-0.46357972191111,51.67760602100794],"type":"Point"}
}