{
  "type": "Feature",
  "properties": {
    "iso:country":"GB",
    "wof:name":"SW3 2RA",
    "wof:placetype":"postalcode"
},
  "geometry": {"coordinates":[-0.1604758363901,51.49279981303295],"type":"Point"}
}