{
  "type": "Feature",
  "properties": {
    "iso:country":"GB",
    "wof:name":"SY23 5BU",
    "wof:placetype":"postalcode"
},
  "geometry": {"coordinates":[-4.15181824891125,52.30322622657472],"type":"Point"}
}