{
  "type": "Feature",
  "properties": {
    "iso:country": "GB",
    "wof:name": "SY23 5BU",
    "wof:placetype": "postalcode"
  },
  "geometry": {"coordinates":[-4.151818,52.303226],"type":"Point"}
}
