{
  "type": "Feature",
  "properties": {
    "date:inception_lower":"1988-03-01",
    "date:inception_upper":"1988-03-31",
    "iso:country":"GB",
    "wof:name":"TQ1 2SB",
    "wof:placetype":"postalcode"
},
  "geometry": {"coordinates":[-3.507775,50.461706],"type":"Point"}
}