{
  "type": "Feature",
  "properties": {
    "date:inception_lower":"1980-01-01",
    "date:inception_upper":"1980-01-31",
    "iso:country":"GB",
    "wof:name":"LL65 2TT",
    "wof:placetype":"postalcode"
},
  "geometry": {"coordinates":[-4.611746,53.287093],"type":"Point"}
}