{
  "type": "Feature",
  "properties": {
    "iso:country":"GB",
    "wof:name":"LL65 2TT",
    "wof:placetype":"postalcode"
},
  "geometry": {"coordinates":[-4.6117459139307,53.28709283874711],"type":"Point"}
}