{
  "type": "Feature",
  "properties": {
    "iso:country":"GB",
    "wof:name":"SE1 9JH",
    "wof:placetype":"postalcode"
},
  "geometry": {"coordinates":[-0.10188286453994,51.50818756937831],"type":"Point"}
}