{
  "type": "Feature",
  "properties": {
    "date:inception_lower": "2018-08-01",
    "date:inception_upper": "2018-08-01",
    "iso:country": "GB",
    "wof:name": "GL20 6FJ",
    "wof:placetype": "postalcode"
  },
  "geometry": {"coordinates":[-2.142581,52.028491],"type":"Point"}
}
