{
  "type": "Feature",
  "properties": {
    "iso:country":"GB",
    "wof:name":"LS25 1ES",
    "wof:placetype":"postalcode"
},
  "geometry": {"coordinates":[-1.39416242441417,53.7936884103754],"type":"Point"}
}