{
  "type": "Feature",
  "properties": {
    "iso:country":"GB",
    "wof:name":"PR3 0BP",
    "wof:placetype":"postalcode"
},
  "geometry": {"coordinates":[-2.77592328403463,53.95964126709625],"type":"Point"}
}