{
  "type": "Feature",
  "properties": {
    "date:inception_lower": "1980-01-01",
    "date:inception_upper": "1980-01-01",
    "iso:country": "GB",
    "wof:name": "PR3 0BP",
    "wof:placetype": "postalcode"
  },
  "geometry": {"coordinates":[-2.775923,53.959641],"type":"Point"}
}
