{
  "type": "Feature",
  "properties": {
    "iso:country":"GB",
    "wof:name":"ME13 0PG",
    "wof:placetype":"postalcode"
},
  "geometry": {"coordinates":[0.8477639091524,51.2602919579711],"type":"Point"}
}