{
  "type": "Feature",
  "properties": {
    "iso:country":"GB",
    "wof:name":"NG17 7LD",
    "wof:placetype":"postalcode"
},
  "geometry": {"coordinates":[-1.24290902625645,53.10983135205981],"type":"Point"}
}