{
  "type": "Feature",
  "properties": {
    "iso:country":"GB",
    "wof:name":"CB7 4UR",
    "wof:placetype":"postalcode"
},
  "geometry": {"coordinates":[0.34019869908482,52.4270696313578],"type":"Point"}
}