{
  "type": "Feature",
  "properties": {
    "date:inception_lower": "1980-01-01",
    "date:inception_upper": "1980-01-01",
    "iso:country": "GB",
    "wof:name": "CB7 4UR",
    "wof:placetype": "postalcode"
  },
  "geometry": {"coordinates":[0.340199,52.42707],"type":"Point"}
}
