{
  "type": "Feature",
  "properties": {
    "iso:country": "GB",
    "wof:name": "CO2 8AS",
    "wof:placetype": "postalcode"
  },
  "geometry": {"coordinates":[0.917542,51.873286],"type":"Point"}
}
