{
  "type": "Feature",
  "properties": {
    "date:inception_lower": "2012-08-01",
    "date:inception_upper": "2012-08-01",
    "iso:country": "GB",
    "wof:name": "WA1 9TE",
    "wof:placetype": "postalcode"
  },
  "geometry": {"coordinates":[-2.599635,53.389724],"type":"Point"}
}
