{
  "type": "Feature",
  "properties": {
    "iso:country":"GB",
    "wof:name":"SK4 2DD",
    "wof:placetype":"postalcode"
},
  "geometry": {"coordinates":[-2.19236297355042,53.40963682437094],"type":"Point"}
}