{
  "type": "Feature",
  "properties": {
    "iso:country":"GB",
    "wof:name":"PE7 3QE",
    "wof:placetype":"postalcode"
},
  "geometry": {"coordinates":[-0.2498190522673,52.45748817966754],"type":"Point"}
}