{
  "type": "Feature",
  "properties": {
    "date:inception_lower": "1980-01-01",
    "date:inception_upper": "1980-01-01",
    "iso:country": "GB",
    "wof:name": "PE7 3QE",
    "wof:placetype": "postalcode"
  },
  "geometry": {"coordinates":[-0.247158,52.452135],"type":"Point"}
}
