{
  "type": "Feature",
  "properties": {
    "iso:country":"GB",
    "wof:name":"LU4 0NZ",
    "wof:placetype":"postalcode"
},
  "geometry": {"coordinates":[-0.47746957747871,51.89493798389186],"type":"Point"}
}