{
  "type": "Feature",
  "properties": {
    "date:inception_lower": "2014-06-01",
    "date:inception_upper": "2014-06-01",
    "iso:country": "GB",
    "wof:name": "LU4 0NZ",
    "wof:placetype": "postalcode"
  },
  "geometry": {"coordinates":[-0.47743,51.894937],"type":"Point"}
}
