{
  "type": "Feature",
  "properties": {
    "iso:country":"GB",
    "wof:name":"SN10 3FJ",
    "wof:placetype":"postalcode"
},
  "geometry": {"coordinates":[-1.98062133489528,51.35503812317847],"type":"Point"}
}