{
  "type": "Feature",
  "properties": {
    "date:inception_lower": "2007-10-01",
    "date:inception_upper": "2007-10-01",
    "iso:country": "GB",
    "wof:name": "SN10 3FJ",
    "wof:placetype": "postalcode"
  },
  "geometry": {"coordinates":[-1.980621,51.355038],"type":"Point"}
}
