{
  "type": "Feature",
  "properties": {
    "date:inception_lower": "2011-12-01",
    "date:inception_upper": "2011-12-01",
    "iso:country": "GB",
    "wof:name": "SE15 9EA",
    "wof:placetype": "postalcode"
  },
  "geometry": {"coordinates":[-0.070925,51.471766],"type":"Point"}
}
