{
  "type": "Feature",
  "properties": {
    "date:inception_lower": "1980-01-01",
    "date:inception_upper": "1980-01-01",
    "iso:country": "GB",
    "wof:name": "ML7 4AT",
    "wof:placetype": "postalcode"
  },
  "geometry": {"coordinates":[-3.809337,55.818745],"type":"Point"}
}
