{
  "type": "Feature",
  "properties": {
    "iso:country":"GB",
    "wof:name":"ML7 4AT",
    "wof:placetype":"postalcode"
},
  "geometry": {"coordinates":[-3.80933726012591,55.81874497073085],"type":"Point"}
}