{
  "type": "Feature",
  "properties": {
    "iso:country":"GB",
    "wof:name":"EH20 9DP",
    "wof:placetype":"postalcode"
},
  "geometry": {"coordinates":[-3.15086400660406,55.87947848961311],"type":"Point"}
}