{
  "type": "Feature",
  "properties": {
    "iso:country": "GB",
    "wof:name": "EH20 9DP",
    "wof:placetype": "postalcode"
  },
  "geometry": {"coordinates":[-3.150864,55.879478],"type":"Point"}
}
