{
  "type": "Feature",
  "properties": {
    "date:inception_lower": "1980-01-01",
    "date:inception_upper": "1980-01-01",
    "iso:country": "GB",
    "wof:name": "SL6 9PU",
    "wof:placetype": "postalcode"
  },
  "geometry": {"coordinates":[-0.751513,51.555107],"type":"Point"}
}
