{
  "type": "Feature",
  "properties": {
    "iso:country":"GB",
    "wof:name":"HA0 4GJ",
    "wof:placetype":"postalcode"
},
  "geometry": {"coordinates":[-0.29638961369455,51.53919412970426],"type":"Point"}
}