{
  "type": "Feature",
  "properties": {
    "iso:country":"GB",
    "wof:name":"BA21 3ND",
    "wof:placetype":"postalcode"
},
  "geometry": {"coordinates":[-2.65321346782254,50.95172784547055],"type":"Point"}
}