{
  "type": "Feature",
  "properties": {
    "iso:country":"GB",
    "wof:name":"CV7 7NQ",
    "wof:placetype":"postalcode"
},
  "geometry": {"coordinates":[-1.64411167499148,52.43698583824798],"type":"Point"}
}