{
  "type": "Feature",
  "properties": {
    "iso:country": "GB",
    "wof:name": "GL2 2HS",
    "wof:placetype": "postalcode"
  },
  "geometry": {"coordinates":[-2.263911,51.815411],"type":"Point"}
}
