{
  "type": "Feature",
  "properties": {
    "date:inception_lower": "2005-12-01",
    "date:inception_upper": "2005-12-01",
    "iso:country": "GB",
    "wof:name": "LL14 3LJ",
    "wof:placetype": "postalcode"
  },
  "geometry": {"coordinates":[-3.067645,52.984174],"type":"Point"}
}
