{
  "type": "Feature",
  "properties": {
    "iso:country":"GB",
    "wof:name":"LL14 3LJ",
    "wof:placetype":"postalcode"
},
  "geometry": {"coordinates":[-3.06764502906666,52.9841737605279],"type":"Point"}
}