{
  "type": "Feature",
  "properties": {
    "iso:country": "GB",
    "wof:name": "LL14 3LJ",
    "wof:placetype": "postalcode"
  },
  "geometry": {"coordinates":[-3.067645,52.984174],"type":"Point"}
}
