{
  "type": "Feature",
  "properties": {
    "date:inception_lower": "2015-11-01",
    "date:inception_upper": "2015-11-01",
    "iso:country": "GB",
    "wof:name": "DE11 0FG",
    "wof:placetype": "postalcode"
  },
  "geometry": {"coordinates":[-1.56212,52.786055],"type":"Point"}
}
