{
  "type": "Feature",
  "properties": {
    "date:inception_lower": "2001-06-01",
    "date:inception_upper": "2001-06-01",
    "iso:country": "GB",
    "wof:name": "WF9 1QA",
    "wof:placetype": "postalcode"
  },
  "geometry": {"coordinates":[-1.299854,53.627961],"type":"Point"}
}
