{
  "type": "Feature",
  "properties": {
    "iso:country":"GB",
    "wof:name":"KT9 1BP",
    "wof:placetype":"postalcode"
},
  "geometry": {"coordinates":[-0.30303294983979,51.36735547083615],"type":"Point"}
}