{
  "type": "Feature",
  "properties": {
    "iso:country":"GB",
    "wof:name":"BD4 0PT",
    "wof:placetype":"postalcode"
},
  "geometry": {"coordinates":[-1.70709889798733,53.76849845796468],"type":"Point"}
}