{
  "type": "Feature",
  "properties": {
    "iso:country":"GB",
    "wof:name":"DN2 5AZ",
    "wof:placetype":"postalcode"
},
  "geometry": {"coordinates":[-1.1050494714871,53.53494413556593],"type":"Point"}
}