{
  "type": "Feature",
  "properties": {
    "iso:country":"GB",
    "wof:name":"HX2 8UH",
    "wof:placetype":"postalcode"
},
  "geometry": {"coordinates":[-1.90396995973129,53.75742054652169],"type":"Point"}
}