{
  "type": "Feature",
  "properties": {
    "date:inception_lower": "1980-01-01",
    "date:inception_upper": "1980-01-01",
    "iso:country": "GB",
    "wof:name": "HX2 8UH",
    "wof:placetype": "postalcode"
  },
  "geometry": {"coordinates":[-1.903972,53.757435],"type":"Point"}
}
