{
  "type": "Feature",
  "properties": {
    "iso:country": "GB",
    "wof:name": "CV32 4QU",
    "wof:placetype": "postalcode"
  },
  "geometry": {"coordinates":[-1.532312,52.291279],"type":"Point"}
}
