{
  "type": "Feature",
  "properties": {
    "iso:country": "GB",
    "wof:name": "OX1 4XB",
    "wof:placetype": "postalcode"
  },
  "geometry": {"coordinates":[-1.24774,51.733563],"type":"Point"}
}
