{
  "type": "Feature",
  "properties": {
    "iso:country":"GB",
    "wof:name":"OX1 4XB",
    "wof:placetype":"postalcode"
},
  "geometry": {"coordinates":[-1.24773991549724,51.73356323530696],"type":"Point"}
}