{
  "type": "Feature",
  "properties": {
    "iso:country":"GB",
    "wof:name":"YO62 6DA",
    "wof:placetype":"postalcode"
},
  "geometry": {"coordinates":[-0.93147341511369,54.26997375835921],"type":"Point"}
}