{
  "type": "Feature",
  "properties": {
    "iso:country":"GB",
    "wof:name":"EH3 6NN",
    "wof:placetype":"postalcode"
},
  "geometry": {"coordinates":[-3.19409488252538,55.95725866933174],"type":"Point"}
}