{
  "type": "Feature",
  "properties": {
    "date:inception_lower":"2010-04-01",
    "date:inception_upper":"2010-04-30",
    "iso:country":"GB",
    "wof:name":"E1 0ES",
    "wof:placetype":"postalcode"
},
  "geometry": {"coordinates":[-0.048441,51.51544],"type":"Point"}
}