{
  "type": "Feature",
  "properties": {
    "date:inception_lower": "2005-07-01",
    "date:inception_upper": "2005-07-01",
    "iso:country": "GB",
    "wof:name": "SR7 7PT",
    "wof:placetype": "postalcode"
  },
  "geometry": {"coordinates":[-1.328345,54.82739],"type":"Point"}
}
