{
  "type": "Feature",
  "properties": {
    "iso:country":"GB",
    "wof:name":"SR7 7PT",
    "wof:placetype":"postalcode"
},
  "geometry": {"coordinates":[-1.32834458982175,54.82739015191364],"type":"Point"}
}