{
  "type": "Feature",
  "properties": {
    "iso:country":"GB",
    "wof:name":"CF3 3PF",
    "wof:placetype":"postalcode"
},
  "geometry": {"coordinates":[-3.11967902775884,51.51147872153016],"type":"Point"}
}