{
  "type": "Feature",
  "properties": {
    "date:inception_lower": "1980-01-01",
    "date:inception_upper": "1980-01-01",
    "iso:country": "GB",
    "wof:name": "IP22 1DF",
    "wof:placetype": "postalcode"
  },
  "geometry": {"coordinates":[1.006817,52.341166],"type":"Point"}
}
