{
  "type": "Feature",
  "properties": {
    "iso:country":"GB",
    "wof:name":"DG9 9BD",
    "wof:placetype":"postalcode"
},
  "geometry": {"coordinates":[-4.99266265275621,54.85547271220774],"type":"Point"}
}