{
  "type": "Feature",
  "properties": {
    "iso:country":"GB",
    "wof:name":"S5 8WE",
    "wof:placetype":"postalcode"
},
  "geometry": {"coordinates":[-1.47726241569508,53.41022229136848],"type":"Point"}
}