{
  "type": "Feature",
  "properties": {
    "date:inception_lower":"1988-03-01",
    "date:inception_upper":"1988-03-31",
    "iso:country":"GB",
    "wof:name":"SN5 6JN",
    "wof:placetype":"postalcode"
},
  "geometry": {"coordinates":[-1.843342,51.558998],"type":"Point"}
}