{
  "type": "Feature",
  "properties": {
    "iso:country":"GB",
    "wof:name":"SN5 6JN",
    "wof:placetype":"postalcode"
},
  "geometry": {"coordinates":[-1.84334177367061,51.55899824997324],"type":"Point"}
}