{
  "type": "Feature",
  "properties": {
    "iso:country":"GB",
    "wof:name":"IG6 2QY",
    "wof:placetype":"postalcode"
},
  "geometry": {"coordinates":[0.08023482172742,51.60261561095746],"type":"Point"}
}