{
  "type": "Feature",
  "properties": {
    "iso:country":"GB",
    "wof:name":"ML6 0HL",
    "wof:placetype":"postalcode"
},
  "geometry": {"coordinates":[-3.99266066592438,55.87084755775196],"type":"Point"}
}