{
  "type": "Feature",
  "properties": {
    "iso:country":"GB",
    "wof:name":"NR29 4PJ",
    "wof:placetype":"postalcode"
},
  "geometry": {"coordinates":[1.63996700842662,52.70282123866584],"type":"Point"}
}