{
  "type": "Feature",
  "properties": {
    "date:inception_lower":"2008-07-01",
    "date:inception_upper":"2008-07-31",
    "iso:country":"GB",
    "wof:name":"NR29 4PJ",
    "wof:placetype":"postalcode"
},
  "geometry": {"coordinates":[1.639967,52.702821],"type":"Point"}
}