{
  "type": "Feature",
  "properties": {
    "iso:country": "GB",
    "wof:name": "NR29 4PJ",
    "wof:placetype": "postalcode"
  },
  "geometry": {"coordinates":[1.639967,52.702821],"type":"Point"}
}
