{
  "type": "Feature",
  "properties": {
    "iso:country":"GB",
    "wof:name":"CR5 3QG",
    "wof:placetype":"postalcode"
},
  "geometry": {"coordinates":[-0.15841799022452,51.30518994344487],"type":"Point"}
}