{
  "type": "Feature",
  "properties": {
    "iso:country": "GB",
    "wof:name": "ST5 3QD",
    "wof:placetype": "postalcode"
  },
  "geometry": {"coordinates":[-2.23165,52.995324],"type":"Point"}
}
