{
  "type": "Feature",
  "properties": {
    "iso:country": "GB",
    "wof:name": "B32 2RD",
    "wof:placetype": "postalcode"
  },
  "geometry": {"coordinates":[-1.984932,52.45309],"type":"Point"}
}
