{
  "type": "Feature",
  "properties": {
    "date:inception_lower": "2003-10-01",
    "date:inception_upper": "2003-10-01",
    "iso:country": "GB",
    "wof:name": "SE22 9EJ",
    "wof:placetype": "postalcode"
  },
  "geometry": {"coordinates":[-0.070055,51.457228],"type":"Point"}
}
