{
  "type": "Feature",
  "properties": {
    "iso:country":"GB",
    "wof:name":"SE22 9EJ",
    "wof:placetype":"postalcode"
},
  "geometry": {"coordinates":[-0.07005548906377,51.45722847550326],"type":"Point"}
}