{
  "type": "Feature",
  "properties": {
    "iso:country": "GB",
    "wof:name": "M32 0UD",
    "wof:placetype": "postalcode"
  },
  "geometry": {"coordinates":[-2.29588,53.453622],"type":"Point"}
}
