{
  "type": "Feature",
  "properties": {
    "iso:country":"GB",
    "wof:name":"M32 0UD",
    "wof:placetype":"postalcode"
},
  "geometry": {"coordinates":[-2.29587988568992,53.45362166550259],"type":"Point"}
}