{
  "type": "Feature",
  "properties": {
    "date:inception_lower": "1980-01-01",
    "date:inception_upper": "1980-01-01",
    "iso:country": "GB",
    "wof:name": "SR5 5NL",
    "wof:placetype": "postalcode"
  },
  "geometry": {"coordinates":[-1.428229,54.925522],"type":"Point"}
}
