{
  "type": "Feature",
  "properties": {
    "iso:country":"GB",
    "wof:name":"BS4 1TA",
    "wof:placetype":"postalcode"
},
  "geometry": {"coordinates":[-2.59715480305851,51.42125132501737],"type":"Point"}
}