{
  "type": "Feature",
  "properties": {
    "iso:country":"GB",
    "wof:name":"MK14 6FT",
    "wof:placetype":"postalcode"
},
  "geometry": {"coordinates":[-0.7753258977159,52.06846509475645],"type":"Point"}
}