{
  "type": "Feature",
  "properties": {
    "iso:country": "GB",
    "wof:name": "RG24 9ZE",
    "wof:placetype": "postalcode"
  },
  "geometry": {"coordinates":[-1.091147,51.289508],"type":"Point"}
}
