{
  "type": "Feature",
  "properties": {
    "date:inception_lower": "2016-01-01",
    "date:inception_upper": "2016-01-01",
    "iso:country": "GB",
    "wof:name": "RG24 9ZE",
    "wof:placetype": "postalcode"
  },
  "geometry": {"coordinates":[-1.0909,51.289416],"type":"Point"}
}
