{
  "type": "Feature",
  "properties": {
    "date:inception_lower":"2016-01-01",
    "date:inception_upper":"2016-01-31",
    "iso:country":"GB",
    "wof:name":"RG24 9ZE",
    "wof:placetype":"postalcode"
},
  "geometry": {"coordinates":[-1.091147,51.289508],"type":"Point"}
}