{
  "type": "Feature",
  "properties": {
    "date:inception_lower": "1980-01-01",
    "date:inception_upper": "1980-01-01",
    "iso:country": "GB",
    "wof:name": "SN15 5NH",
    "wof:placetype": "postalcode"
  },
  "geometry": {"coordinates":[-2.105875,51.49161],"type":"Point"}
}
