{
  "type": "Feature",
  "properties": {
    "iso:country": "GB",
    "wof:name": "SN15 5NH",
    "wof:placetype": "postalcode"
  },
  "geometry": {"coordinates":[-2.105875,51.49161],"type":"Point"}
}
