{
  "type": "Feature",
  "properties": {
    "date:inception_lower":"2018-10-01",
    "date:inception_upper":"2018-10-31",
    "iso:country":"GB",
    "wof:name":"W2 7WU",
    "wof:placetype":"postalcode"
},
  "geometry": {"coordinates":[-0.276962,51.500496],"type":"Point"}
}