{
  "type": "Feature",
  "properties": {
    "iso:country":"GB",
    "wof:name":"DY2 8SH",
    "wof:placetype":"postalcode"
},
  "geometry": {"coordinates":[-2.07921606882962,52.50452304441884],"type":"Point"}
}