{
  "type": "Feature",
  "properties": {
    "iso:country":"GB",
    "wof:name":"BN24 6LB",
    "wof:placetype":"postalcode"
},
  "geometry": {"coordinates":[0.35177719699381,50.81429441754982],"type":"Point"}
}