{
  "type": "Feature",
  "properties": {
    "iso:country": "GB",
    "wof:name": "BN24 6LB",
    "wof:placetype": "postalcode"
  },
  "geometry": {"coordinates":[0.351777,50.814294],"type":"Point"}
}
