{
  "type": "Feature",
  "properties": {
    "iso:country":"GB",
    "wof:name":"HA4 8PJ",
    "wof:placetype":"postalcode"
},
  "geometry": {"coordinates":[-0.40763820251642,51.57473813222485],"type":"Point"}
}