{
  "type": "Feature",
  "properties": {
    "iso:country":"GB",
    "wof:name":"KA7 2XD",
    "wof:placetype":"postalcode"
},
  "geometry": {"coordinates":[-4.64062171587602,55.45132408193469],"type":"Point"}
}