{
  "type": "Feature",
  "properties": {
    "iso:country":"GB",
    "wof:name":"SL4 1JQ",
    "wof:placetype":"postalcode"
},
  "geometry": {"coordinates":[-0.60959466602448,51.47735810920112],"type":"Point"}
}