{
  "type": "Feature",
  "properties": {
    "iso:country":"GB",
    "wof:name":"SA65 9QA",
    "wof:placetype":"postalcode"
},
  "geometry": {"coordinates":[-5.02203049781779,51.98207516143651],"type":"Point"}
}