{
  "type": "Feature",
  "properties": {
    "date:inception_lower": "1980-01-01",
    "date:inception_upper": "1980-01-01",
    "iso:country": "GB",
    "wof:name": "SA65 9QA",
    "wof:placetype": "postalcode"
  },
  "geometry": {"coordinates":[-5.02203,51.982075],"type":"Point"}
}
