{
  "type": "Feature",
  "properties": {
    "iso:country":"GB",
    "wof:name":"DL8 1EX",
    "wof:placetype":"postalcode"
},
  "geometry": {"coordinates":[-1.60028557119805,54.28544001517508],"type":"Point"}
}