{
  "type": "Feature",
  "properties": {
    "iso:country":"GB",
    "wof:name":"LE2 4FE",
    "wof:placetype":"postalcode"
},
  "geometry": {"coordinates":[-1.07660658359198,52.60890281284643],"type":"Point"}
}