{
  "type": "Feature",
  "properties": {
    "iso:country": "GB",
    "wof:name": "NG9 3JN",
    "wof:placetype": "postalcode"
  },
  "geometry": {"coordinates":[-1.254841,52.935244],"type":"Point"}
}
