{
  "type": "Feature",
  "properties": {
    "iso:country":"GB",
    "wof:name":"BA14 0JF",
    "wof:placetype":"postalcode"
},
  "geometry": {"coordinates":[-2.21645335618054,51.30662554148751],"type":"Point"}
}