{
  "type": "Feature",
  "properties": {
    "iso:country":"GB",
    "wof:name":"CF44 6PB",
    "wof:placetype":"postalcode"
},
  "geometry": {"coordinates":[-3.44317525192522,51.68520227107126],"type":"Point"}
}