{
  "type": "Feature",
  "properties": {
    "date:inception_lower": "2014-05-01",
    "date:inception_upper": "2014-05-01",
    "iso:country": "GB",
    "wof:name": "SE7 7FS",
    "wof:placetype": "postalcode"
  },
  "geometry": {"coordinates":[0.02084,51.484788],"type":"Point"}
}
