{
  "type": "Feature",
  "properties": {
    "iso:country":"GB",
    "wof:name":"SE7 7FS",
    "wof:placetype":"postalcode"
},
  "geometry": {"coordinates":[0.02084035570622,51.48478837178738],"type":"Point"}
}