{
  "type": "Feature",
  "properties": {
    "iso:country":"GB",
    "wof:name":"BB3 2DP",
    "wof:placetype":"postalcode"
},
  "geometry": {"coordinates":[-2.45716235444278,53.69315671025098],"type":"Point"}
}