{
  "type": "Feature",
  "properties": {
    "iso:country": "GB",
    "wof:name": "BB3 2DP",
    "wof:placetype": "postalcode"
  },
  "geometry": {"coordinates":[-2.457377,53.693612],"type":"Point"}
}
