{
  "type": "Feature",
  "properties": {
    "iso:country": "GB",
    "wof:name": "E5 0EE",
    "wof:placetype": "postalcode"
  },
  "geometry": {"coordinates":[-0.03754,51.550752],"type":"Point"}
}
