{
  "type": "Feature",
  "properties": {
    "iso:country":"GB",
    "wof:name":"E5 0EE",
    "wof:placetype":"postalcode"
},
  "geometry": {"coordinates":[-0.03754024151684,51.55075169387854],"type":"Point"}
}