{
  "type": "Feature",
  "properties": {
    "iso:country":"GB",
    "wof:name":"ML12 6HT",
    "wof:placetype":"postalcode"
},
  "geometry": {"coordinates":[-3.65442475024158,55.56891869851121],"type":"Point"}
}