{
  "type": "Feature",
  "properties": {
    "iso:country":"GB",
    "wof:name":"HX2 9XN",
    "wof:placetype":"postalcode"
},
  "geometry": {"coordinates":[-1.8831790545832,53.76719907041363],"type":"Point"}
}