{
  "type": "Feature",
  "properties": {
    "iso:country": "GB",
    "wof:name": "HX2 9XN",
    "wof:placetype": "postalcode"
  },
  "geometry": {"coordinates":[-1.883179,53.767199],"type":"Point"}
}
