{
  "type": "Feature",
  "properties": {
    "date:inception_lower":"1981-09-01",
    "date:inception_upper":"1981-09-30",
    "iso:country":"GB",
    "wof:name":"HX2 9XN",
    "wof:placetype":"postalcode"
},
  "geometry": {"coordinates":[-1.883179,53.767199],"type":"Point"}
}