{
  "type": "Feature",
  "properties": {
    "date:inception_lower":"1980-01-01",
    "date:inception_upper":"1980-01-31",
    "iso:country":"GB",
    "wof:name":"GL15 4SB",
    "wof:placetype":"postalcode"
},
  "geometry": {"coordinates":[-2.517679,51.759859],"type":"Point"}
}