{
  "type": "Feature",
  "properties": {
    "iso:country":"GB",
    "wof:name":"GL15 4SB",
    "wof:placetype":"postalcode"
},
  "geometry": {"coordinates":[-2.51767904768299,51.75985919812779],"type":"Point"}
}