{
  "type": "Feature",
  "properties": {
    "iso:country":"GB",
    "wof:name":"WA8 3XD",
    "wof:placetype":"postalcode"
},
  "geometry": {"coordinates":[-2.71240121755603,53.40461854696608],"type":"Point"}
}