{
  "type": "Feature",
  "properties": {
    "date:inception_lower": "1996-06-01",
    "date:inception_upper": "1996-06-01",
    "iso:country": "GB",
    "wof:name": "AB16 6QD",
    "wof:placetype": "postalcode"
  },
  "geometry": {"coordinates":[-2.170742,57.156426],"type":"Point"}
}
