{
  "type": "Feature",
  "properties": {
    "iso:country": "GB",
    "wof:name": "EX4 4SQ",
    "wof:placetype": "postalcode"
  },
  "geometry": {"coordinates":[-3.528442,50.739892],"type":"Point"}
}
