{
  "type": "Feature",
  "properties": {
    "iso:country":"GB",
    "wof:name":"SW1W 9QG",
    "wof:placetype":"postalcode"
},
  "geometry": {"coordinates":[-0.1512012854747,51.49273489576964],"type":"Point"}
}