{
  "type": "Feature",
  "properties": {
    "iso:country":"GB",
    "wof:name":"WF2 6DL",
    "wof:placetype":"postalcode"
},
  "geometry": {"coordinates":[-1.49397387781304,53.64337417565538],"type":"Point"}
}