{
  "type": "Feature",
  "properties": {
    "iso:country":"GB",
    "wof:name":"AL1 1JG",
    "wof:placetype":"postalcode"
},
  "geometry": {"coordinates":[-0.32655060440285,51.74309298782934],"type":"Point"}
}