{
  "type": "Feature",
  "properties": {
    "iso:country":"GB",
    "wof:name":"IG3 9RZ",
    "wof:placetype":"postalcode"
},
  "geometry": {"coordinates":[0.11407503108519,51.5629285269615],"type":"Point"}
}