{
  "type": "Feature",
  "properties": {
    "iso:country": "GB",
    "wof:name": "TR15 3FP",
    "wof:placetype": "postalcode"
  },
  "geometry": {"coordinates":[-5.275059,50.223743],"type":"Point"}
}
