{
  "type": "Feature",
  "properties": {
    "iso:country":"GB",
    "wof:name":"CF24 3LB",
    "wof:placetype":"postalcode"
},
  "geometry": {"coordinates":[-3.16936719248369,51.4918230802767],"type":"Point"}
}