{
  "type": "Feature",
  "properties": {
    "iso:country":"GB",
    "wof:name":"L33 8XR",
    "wof:placetype":"postalcode"
},
  "geometry": {"coordinates":[-2.87664585072083,53.48592564017144],"type":"Point"}
}