{
  "type": "Feature",
  "properties": {
    "iso:country": "GB",
    "wof:name": "PE23 4NH",
    "wof:placetype": "postalcode"
  },
  "geometry": {"coordinates":[0.046182,53.226022],"type":"Point"}
}
