{
  "type": "Feature",
  "properties": {
    "iso:country":"GB",
    "wof:name":"PE23 4NH",
    "wof:placetype":"postalcode"
},
  "geometry": {"coordinates":[0.04618177856306,53.22602220265758],"type":"Point"}
}