{
  "type": "Feature",
  "properties": {
    "date:inception_lower": "1999-06-01",
    "date:inception_upper": "1999-06-01",
    "iso:country": "GB",
    "wof:name": "CH41 9BG",
    "wof:placetype": "postalcode"
  },
  "geometry": {"coordinates":[-3.01434,53.380735],"type":"Point"}
}
