{
  "type": "Feature",
  "properties": {
    "date:inception_lower": "1980-01-01",
    "date:inception_upper": "1980-01-01",
    "iso:country": "GB",
    "wof:name": "DH9 8TW",
    "wof:placetype": "postalcode"
  },
  "geometry": {"coordinates":[-1.743561,54.863915],"type":"Point"}
}
