{
  "type": "Feature",
  "properties": {
    "iso:country":"GB",
    "wof:name":"DH9 8TW",
    "wof:placetype":"postalcode"
},
  "geometry": {"coordinates":[-1.74356062854224,54.86391547674457],"type":"Point"}
}