{
  "type": "Feature",
  "properties": {
    "iso:country": "GB",
    "wof:name": "RG27 8RN",
    "wof:placetype": "postalcode"
  },
  "geometry": {"coordinates":[-0.907814,51.302887],"type":"Point"}
}
