{
  "type": "Feature",
  "properties": {
    "date:inception_lower": "1980-01-01",
    "date:inception_upper": "1980-01-01",
    "iso:country": "GB",
    "wof:name": "HU15 1NT",
    "wof:placetype": "postalcode"
  },
  "geometry": {"coordinates":[-0.544179,53.732416],"type":"Point"}
}
