{
  "type": "Feature",
  "properties": {
    "iso:country": "GB",
    "wof:name": "E1 7QL",
    "wof:placetype": "postalcode"
  },
  "geometry": {"coordinates":[-0.068748,51.51547],"type":"Point"}
}
