{
  "type": "Feature",
  "properties": {
    "iso:country":"GB",
    "wof:name":"TN24 9LF",
    "wof:placetype":"postalcode"
},
  "geometry": {"coordinates":[0.87455761050404,51.17115040398973],"type":"Point"}
}