{
  "type": "Feature",
  "properties": {
    "date:inception_lower": "2004-01-01",
    "date:inception_upper": "2004-01-01",
    "iso:country": "GB",
    "wof:name": "TN24 9LF",
    "wof:placetype": "postalcode"
  },
  "geometry": {"coordinates":[0.874607,51.171222],"type":"Point"}
}
