{
  "type": "Feature",
  "properties": {
    "iso:country":"GB",
    "wof:name":"DY11 7AE",
    "wof:placetype":"postalcode"
},
  "geometry": {"coordinates":[-2.255886064046,52.37517551061834],"type":"Point"}
}