{
  "type": "Feature",
  "properties": {
    "date:inception_lower": "2021-05-01",
    "date:inception_upper": "2021-05-01",
    "iso:country": "GB",
    "wof:name": "NR4 7WS",
    "wof:placetype": "postalcode"
  },
  "geometry": {"coordinates":[1.228248,52.606583],"type":"Point"}
}
