{
  "type": "Feature",
  "properties": {
    "iso:country":"GB",
    "wof:name":"CF14 6AW",
    "wof:placetype":"postalcode"
},
  "geometry": {"coordinates":[-3.20738958617439,51.51997800451376],"type":"Point"}
}