{
  "type": "Feature",
  "properties": {
    "iso:country":"GB",
    "wof:name":"TN12 8HB",
    "wof:placetype":"postalcode"
},
  "geometry": {"coordinates":[0.44278717791733,51.15612747156574],"type":"Point"}
}