{
  "type": "Feature",
  "properties": {
    "date:inception_lower":"1983-07-01",
    "date:inception_upper":"1983-07-31",
    "iso:country":"GB",
    "wof:name":"TN12 8HB",
    "wof:placetype":"postalcode"
},
  "geometry": {"coordinates":[0.442787,51.156127],"type":"Point"}
}