{
  "type": "Feature",
  "properties": {
    "iso:country":"GB",
    "wof:name":"PH7 4LE",
    "wof:placetype":"postalcode"
},
  "geometry": {"coordinates":[-3.85488801491884,56.37589160599624],"type":"Point"}
}