{
  "type": "Feature",
  "properties": {
    "date:inception_lower": "1987-10-01",
    "date:inception_upper": "1987-10-01",
    "iso:country": "GB",
    "wof:name": "SO22 4HG",
    "wof:placetype": "postalcode"
  },
  "geometry": {"coordinates":[-1.344902,51.043038],"type":"Point"}
}
