{
  "type": "Feature",
  "properties": {
    "iso:country": "GB",
    "wof:name": "NE63 0DA",
    "wof:placetype": "postalcode"
  },
  "geometry": {"coordinates":[-1.562011,55.168317],"type":"Point"}
}
