{
  "type": "Feature",
  "properties": {
    "iso:country":"GB",
    "wof:name":"NE63 0DA",
    "wof:placetype":"postalcode"
},
  "geometry": {"coordinates":[-1.56201057779096,55.16831732031142],"type":"Point"}
}