{
  "type": "Feature",
  "properties": {
    "iso:country": "GB",
    "wof:name": "PR9 7TP",
    "wof:placetype": "postalcode"
  },
  "geometry": {"coordinates":[-2.968514,53.643696],"type":"Point"}
}
