{
  "type": "Feature",
  "properties": {
    "date:inception_lower":"1980-01-01",
    "date:inception_upper":"1980-01-31",
    "iso:country":"GB",
    "wof:name":"SW1V 3AY",
    "wof:placetype":"postalcode"
},
  "geometry": {"coordinates":[-0.138619,51.487572],"type":"Point"}
}