{
  "type": "Feature",
  "properties": {
    "iso:country":"GB",
    "wof:name":"DG2 7JY",
    "wof:placetype":"postalcode"
},
  "geometry": {"coordinates":[-3.62101827027177,55.06062275164889],"type":"Point"}
}