{
  "type": "Feature",
  "properties": {
    "iso:country": "GB",
    "wof:name": "DG2 7JY",
    "wof:placetype": "postalcode"
  },
  "geometry": {"coordinates":[-3.621018,55.060623],"type":"Point"}
}
