{
  "type": "Feature",
  "properties": {
    "iso:country":"GB",
    "wof:name":"KA26 0TX",
    "wof:placetype":"postalcode"
},
  "geometry": {"coordinates":[-4.78867392583819,55.22868700909526],"type":"Point"}
}