{
  "type": "Feature",
  "properties": {
    "iso:country":"GB",
    "wof:name":"CF46 6LA",
    "wof:placetype":"postalcode"
},
  "geometry": {"coordinates":[-3.29196752825529,51.6533070846705],"type":"Point"}
}