{
  "type": "Feature",
  "properties": {
    "iso:country": "GB",
    "wof:name": "CF46 6LA",
    "wof:placetype": "postalcode"
  },
  "geometry": {"coordinates":[-3.291967,51.653307],"type":"Point"}
}
