{
  "type": "Feature",
  "properties": {
    "iso:country":"GB",
    "wof:name":"BL4 7LH",
    "wof:placetype":"postalcode"
},
  "geometry": {"coordinates":[-2.40090044404638,53.55430060239419],"type":"Point"}
}