{
  "type": "Feature",
  "properties": {
    "iso:country":"GB",
    "wof:name":"TF8 7DP",
    "wof:placetype":"postalcode"
},
  "geometry": {"coordinates":[-2.49690621384684,52.63225890872252],"type":"Point"}
}