{
  "type": "Feature",
  "properties": {
    "date:inception_lower":"1980-01-01",
    "date:inception_upper":"1980-01-31",
    "iso:country":"GB",
    "wof:name":"BA12 7AJ",
    "wof:placetype":"postalcode"
},
  "geometry": {"coordinates":[-2.150488,51.160719],"type":"Point"}
}