{
  "type": "Feature",
  "properties": {
    "iso:country": "GB",
    "wof:name": "BA12 7AJ",
    "wof:placetype": "postalcode"
  },
  "geometry": {"coordinates":[-2.148831,51.163071],"type":"Point"}
}
