{
  "type": "Feature",
  "properties": {
    "iso:country":"GB",
    "wof:name":"BA12 7AJ",
    "wof:placetype":"postalcode"
},
  "geometry": {"coordinates":[-2.1504883995015,51.16071885089936],"type":"Point"}
}