{
  "type": "Feature",
  "properties": {
    "iso:country":"GB",
    "wof:name":"HX5 0RS",
    "wof:placetype":"postalcode"
},
  "geometry": {"coordinates":[-1.8372794683747,53.68677431250187],"type":"Point"}
}