{
  "type": "Feature",
  "properties": {
    "iso:country":"GB",
    "wof:name":"W7 3BB",
    "wof:placetype":"postalcode"
},
  "geometry": {"coordinates":[-0.33549946397788,51.51104317036759],"type":"Point"}
}