{
  "type": "Feature",
  "properties": {
    "iso:country":"GB",
    "wof:name":"SW6 1PX",
    "wof:placetype":"postalcode"
},
  "geometry": {"coordinates":[-0.19664673584226,51.48224691063744],"type":"Point"}
}