{
  "type": "Feature",
  "properties": {
    "date:inception_lower": "1980-01-01",
    "date:inception_upper": "1980-01-01",
    "iso:country": "GB",
    "wof:name": "NG7 1PW",
    "wof:placetype": "postalcode"
  },
  "geometry": {"coordinates":[-1.172395,52.954943],"type":"Point"}
}
