{
  "type": "Feature",
  "properties": {
    "iso:country":"GB",
    "wof:name":"HR4 0JA",
    "wof:placetype":"postalcode"
},
  "geometry": {"coordinates":[-2.73668120866201,52.05753348390506],"type":"Point"}
}