{
  "type": "Feature",
  "properties": {
    "date:inception_lower": "2020-07-01",
    "date:inception_upper": "2020-07-01",
    "iso:country": "GB",
    "wof:name": "B24 9DW",
    "wof:placetype": "postalcode"
  },
  "geometry": {"coordinates":[-1.831305,52.528672],"type":"Point"}
}
