{
  "type": "Feature",
  "properties": {
    "iso:country":"GB",
    "wof:name":"DN16 2AY",
    "wof:placetype":"postalcode"
},
  "geometry": {"coordinates":[-0.65171955022424,53.57101760405581],"type":"Point"}
}