{
  "type": "Feature",
  "properties": {
    "iso:country":"GB",
    "wof:name":"S42 7BW",
    "wof:placetype":"postalcode"
},
  "geometry": {"coordinates":[-1.50452763177331,53.22812700147615],"type":"Point"}
}