{
  "type": "Feature",
  "properties": {
    "iso:country": "GB",
    "wof:name": "S42 7BW",
    "wof:placetype": "postalcode"
  },
  "geometry": {"coordinates":[-1.504528,53.228127],"type":"Point"}
}
