{
  "type": "Feature",
  "properties": {
    "iso:country":"GB",
    "wof:name":"BH21 7JL",
    "wof:placetype":"postalcode"
},
  "geometry": {"coordinates":[-1.92043287758233,50.86430664441048],"type":"Point"}
}