{
  "type": "Feature",
  "properties": {
    "date:inception_lower": "1980-01-01",
    "date:inception_upper": "1980-01-01",
    "iso:country": "GB",
    "wof:name": "PO22 9JE",
    "wof:placetype": "postalcode"
  },
  "geometry": {"coordinates":[-0.676143,50.797834],"type":"Point"}
}
