{
  "type": "Feature",
  "properties": {
    "iso:country":"GB",
    "wof:name":"PO22 9JE",
    "wof:placetype":"postalcode"
},
  "geometry": {"coordinates":[-0.67614350730893,50.79783421254918],"type":"Point"}
}