{
  "type": "Feature",
  "properties": {
    "iso:country":"GB",
    "wof:name":"S11 9AR",
    "wof:placetype":"postalcode"
},
  "geometry": {"coordinates":[-1.49576695451108,53.36430675810292],"type":"Point"}
}