{
  "type": "Feature",
  "properties": {
    "iso:country": "GB",
    "wof:name": "RH77 1AD",
    "wof:placetype": "postalcode"
  },
  "geometry": {"coordinates":[-0.169779,51.138775],"type":"Point"}
}
