{
  "type": "Feature",
  "properties": {
    "date:inception_lower": "1980-01-01",
    "date:inception_upper": "1980-01-01",
    "iso:country": "GB",
    "wof:name": "TR4 9ER",
    "wof:placetype": "postalcode"
  },
  "geometry": {"coordinates":[-5.105331,50.286745],"type":"Point"}
}
