{
  "type": "Feature",
  "properties": {
    "iso:country": "GB",
    "wof:name": "S17 3RE",
    "wof:placetype": "postalcode"
  },
  "geometry": {"coordinates":[-1.529759,53.330135],"type":"Point"}
}
