{
  "type": "Feature",
  "properties": {
    "iso:country":"GB",
    "wof:name":"S17 3RE",
    "wof:placetype":"postalcode"
},
  "geometry": {"coordinates":[-1.52975905056066,53.33013547676718],"type":"Point"}
}