{
  "type": "Feature",
  "properties": {
    "iso:country":"GB",
    "wof:name":"AB30 1XZ",
    "wof:placetype":"postalcode"
},
  "geometry": {"coordinates":[-2.57502626410899,56.85001273005459],"type":"Point"}
}