{
  "type": "Feature",
  "properties": {
    "iso:country":"GB",
    "wof:name":"GU6 8QX",
    "wof:placetype":"postalcode"
},
  "geometry": {"coordinates":[-0.49061529485079,51.16667379400849],"type":"Point"}
}