{
  "type": "Feature",
  "properties": {
    "iso:country": "GB",
    "wof:name": "TF1 5TF",
    "wof:placetype": "postalcode"
  },
  "geometry": {"coordinates":[-2.467053,52.706483],"type":"Point"}
}
