{
  "type": "Feature",
  "properties": {
    "iso:country":"GB",
    "wof:name":"TF1 5TF",
    "wof:placetype":"postalcode"
},
  "geometry": {"coordinates":[-2.46705344039893,52.70648289686982],"type":"Point"}
}