{
  "type": "Feature",
  "properties": {
    "date:inception_lower": "2012-06-01",
    "date:inception_upper": "2012-06-01",
    "iso:country": "GB",
    "wof:name": "TF1 5TF",
    "wof:placetype": "postalcode"
  },
  "geometry": {"coordinates":[-2.467053,52.706483],"type":"Point"}
}
