{
  "type": "Feature",
  "properties": {
    "iso:country": "GB",
    "wof:name": "DE45 1HQ",
    "wof:placetype": "postalcode"
  },
  "geometry": {"coordinates":[-1.688049,53.196091],"type":"Point"}
}
