{
  "type": "Feature",
  "properties": {
    "date:inception_lower": "2018-04-01",
    "date:inception_upper": "2018-04-01",
    "iso:country": "GB",
    "wof:name": "DE45 1HQ",
    "wof:placetype": "postalcode"
  },
  "geometry": {"coordinates":[-1.688049,53.196091],"type":"Point"}
}
