{
  "type": "Feature",
  "properties": {
    "iso:country":"GB",
    "wof:name":"CH3 5NB",
    "wof:placetype":"postalcode"
},
  "geometry": {"coordinates":[-2.85737831696945,53.19288229003462],"type":"Point"}
}