{
  "type": "Feature",
  "properties": {
    "iso:country": "GB",
    "wof:name": "DY6 7FT",
    "wof:placetype": "postalcode"
  },
  "geometry": {"coordinates":[-2.1484,52.502313],"type":"Point"}
}
