{
  "type": "Feature",
  "properties": {
    "iso:country":"GB",
    "wof:name":"BA2 4HN",
    "wof:placetype":"postalcode"
},
  "geometry": {"coordinates":[-2.35142965318213,51.37963465345307],"type":"Point"}
}