{
  "type": "Feature",
  "properties": {
    "iso:country": "GB",
    "wof:name": "CB7 4AJ",
    "wof:placetype": "postalcode"
  },
  "geometry": {"coordinates":[0.267878,52.396522],"type":"Point"}
}
