{
  "type": "Feature",
  "properties": {
    "iso:country":"GB",
    "wof:name":"CB7 4AJ",
    "wof:placetype":"postalcode"
},
  "geometry": {"coordinates":[0.26787800982511,52.39652219385669],"type":"Point"}
}