{
  "type": "Feature",
  "properties": {
    "date:inception_lower":"1980-01-01",
    "date:inception_upper":"1980-01-31",
    "iso:country":"GB",
    "wof:name":"LA14 2SU",
    "wof:placetype":"postalcode"
},
  "geometry": {"coordinates":[-3.227085,54.102451],"type":"Point"}
}