{
  "type": "Feature",
  "properties": {
    "iso:country":"GB",
    "wof:name":"YO11 1XE",
    "wof:placetype":"postalcode"
},
  "geometry": {"coordinates":[-0.40264385298593,54.28501697980325],"type":"Point"}
}