{
  "type": "Feature",
  "properties": {
    "date:inception_lower":"2014-04-01",
    "date:inception_upper":"2014-04-30",
    "iso:country":"GB",
    "wof:name":"BD20 6FJ",
    "wof:placetype":"postalcode"
},
  "geometry": {"coordinates":[-1.954373,53.898907],"type":"Point"}
}