{
  "type": "Feature",
  "properties": {
    "iso:country": "GB",
    "wof:name": "BD20 6FJ",
    "wof:placetype": "postalcode"
  },
  "geometry": {"coordinates":[-1.954373,53.898907],"type":"Point"}
}
