{
  "type": "Feature",
  "properties": {
    "iso:country":"GB",
    "wof:name":"HG5 9BL",
    "wof:placetype":"postalcode"
},
  "geometry": {"coordinates":[-1.47209248065064,54.01401776000904],"type":"Point"}
}