{
  "type": "Feature",
  "properties": {
    "iso:country": "GB",
    "wof:name": "HG5 9BL",
    "wof:placetype": "postalcode"
  },
  "geometry": {"coordinates":[-1.472092,54.014018],"type":"Point"}
}
