{
  "type": "Feature",
  "properties": {
    "iso:country":"GB",
    "wof:name":"DT3 5LY",
    "wof:placetype":"postalcode"
},
  "geometry": {"coordinates":[-2.46931240317924,50.66022668733859],"type":"Point"}
}