{
  "type": "Feature",
  "properties": {
    "iso:country":"GB",
    "wof:name":"NN29 7QU",
    "wof:placetype":"postalcode"
},
  "geometry": {"coordinates":[-0.66872103439504,52.25323513912145],"type":"Point"}
}