{
  "type": "Feature",
  "properties": {
    "iso:country":"GB",
    "wof:name":"LL57 2SG",
    "wof:placetype":"postalcode"
},
  "geometry": {"coordinates":[-4.12220788511275,53.23510310437495],"type":"Point"}
}