{
  "type": "Feature",
  "properties": {
    "iso:country": "GB",
    "wof:name": "GU51 3PX",
    "wof:placetype": "postalcode"
  },
  "geometry": {"coordinates":[-0.827626,51.279666],"type":"Point"}
}
