{
  "type": "Feature",
  "properties": {
    "date:inception_lower":"2015-04-01",
    "date:inception_upper":"2015-04-30",
    "iso:country":"GB",
    "wof:name":"GU51 3PX",
    "wof:placetype":"postalcode"
},
  "geometry": {"coordinates":[-0.827626,51.279666],"type":"Point"}
}