{
  "type": "Feature",
  "properties": {
    "iso:country":"GB",
    "wof:name":"DG12 6HU",
    "wof:placetype":"postalcode"
},
  "geometry": {"coordinates":[-3.25325307832175,54.98340000238321],"type":"Point"}
}