{
  "type": "Feature",
  "properties": {
    "iso:country": "GB",
    "wof:name": "GL52 6RJ",
    "wof:placetype": "postalcode"
  },
  "geometry": {"coordinates":[-2.059358,51.893341],"type":"Point"}
}
