{
  "type": "Feature",
  "properties": {
    "iso:country":"GB",
    "wof:name":"CF42 6TL",
    "wof:placetype":"postalcode"
},
  "geometry": {"coordinates":[-3.512665065378,51.66423079331165],"type":"Point"}
}