{
  "type": "Feature",
  "properties": {
    "date:inception_lower":"1980-01-01",
    "date:inception_upper":"1980-01-31",
    "iso:country":"GB",
    "wof:name":"CF42 6TL",
    "wof:placetype":"postalcode"
},
  "geometry": {"coordinates":[-3.512665,51.664231],"type":"Point"}
}