{
  "type": "Feature",
  "properties": {
    "iso:country": "GB",
    "wof:name": "WS9 0DP",
    "wof:placetype": "postalcode"
  },
  "geometry": {"coordinates":[-1.932587,52.600201],"type":"Point"}
}
