{
  "type": "Feature",
  "properties": {
    "date:inception_lower":"1980-01-01",
    "date:inception_upper":"1980-01-31",
    "iso:country":"GB",
    "wof:name":"WS9 0DP",
    "wof:placetype":"postalcode"
},
  "geometry": {"coordinates":[-1.932587,52.600201],"type":"Point"}
}