{
  "type": "Feature",
  "properties": {
    "date:inception_lower": "1981-06-01",
    "date:inception_upper": "1981-06-01",
    "iso:country": "GB",
    "wof:name": "LA1 5JP",
    "wof:placetype": "postalcode"
  },
  "geometry": {"coordinates":[-2.819208,54.055965],"type":"Point"}
}
