{
  "type": "Feature",
  "properties": {
    "date:inception_lower": "1980-01-01",
    "date:inception_upper": "1980-01-01",
    "iso:country": "GB",
    "wof:name": "NE27 0SG",
    "wof:placetype": "postalcode"
  },
  "geometry": {"coordinates":[-1.518554,55.035581],"type":"Point"}
}
