{
  "type": "Feature",
  "properties": {
    "iso:country": "GB",
    "wof:name": "CA16 6AS",
    "wof:placetype": "postalcode"
  },
  "geometry": {"coordinates":[-2.564311,54.602673],"type":"Point"}
}
