{
  "type": "Feature",
  "properties": {
    "iso:country":"GB",
    "wof:name":"LS16 5HW",
    "wof:placetype":"postalcode"
},
  "geometry": {"coordinates":[-1.59246188598245,53.83151141384941],"type":"Point"}
}