{
  "type": "Feature",
  "properties": {
    "iso:country":"GB",
    "wof:name":"TR14 0NS",
    "wof:placetype":"postalcode"
},
  "geometry": {"coordinates":[-5.32084877526083,50.15713824500217],"type":"Point"}
}