{
  "type": "Feature",
  "properties": {
    "date:inception_lower": "1980-01-01",
    "date:inception_upper": "1980-01-01",
    "iso:country": "GB",
    "wof:name": "TR14 0NS",
    "wof:placetype": "postalcode"
  },
  "geometry": {"coordinates":[-5.3209,50.157128],"type":"Point"}
}
