{
  "type": "Feature",
  "properties": {
    "iso:country": "GB",
    "wof:name": "TR14 0NS",
    "wof:placetype": "postalcode"
  },
  "geometry": {"coordinates":[-5.3209,50.157128],"type":"Point"}
}
