{
  "type": "Feature",
  "properties": {
    "iso:country": "GB",
    "wof:name": "CH64 3SR",
    "wof:placetype": "postalcode"
  },
  "geometry": {"coordinates":[-3.066911,53.295833],"type":"Point"}
}
