{
  "type": "Feature",
  "properties": {
    "iso:country":"GB",
    "wof:name":"IV10 8TF",
    "wof:placetype":"postalcode"
},
  "geometry": {"coordinates":[-4.12868588832713,57.58256673942114],"type":"Point"}
}