{
  "type": "Feature",
  "properties": {
    "iso:country":"GB",
    "wof:name":"PO7 6LA",
    "wof:placetype":"postalcode"
},
  "geometry": {"coordinates":[-1.07052320941913,50.90344877472493],"type":"Point"}
}