{
  "type": "Feature",
  "properties": {
    "iso:country":"GB",
    "wof:name":"TN5 6LU",
    "wof:placetype":"postalcode"
},
  "geometry": {"coordinates":[0.34064795064631,51.04758573405572],"type":"Point"}
}