{
  "type": "Feature",
  "properties": {
    "date:inception_lower": "2020-06-01",
    "date:inception_upper": "2020-06-01",
    "iso:country": "GB",
    "wof:name": "DT9 5FZ",
    "wof:placetype": "postalcode"
  },
  "geometry": {"coordinates":[-2.503768,50.916645],"type":"Point"}
}
