{
  "type": "Feature",
  "properties": {
    "date:inception_lower": "1980-01-01",
    "date:inception_upper": "1980-01-01",
    "iso:country": "GB",
    "wof:name": "WS7 9BU",
    "wof:placetype": "postalcode"
  },
  "geometry": {"coordinates":[-1.909776,52.679556],"type":"Point"}
}
