{
  "type": "Feature",
  "properties": {
    "iso:country": "GB",
    "wof:name": "WS7 9BU",
    "wof:placetype": "postalcode"
  },
  "geometry": {"coordinates":[-1.909776,52.679556],"type":"Point"}
}
