{
  "type": "Feature",
  "properties": {
    "iso:country": "GB",
    "wof:name": "CT16 2NU",
    "wof:placetype": "postalcode"
  },
  "geometry": {"coordinates":[1.301492,51.13652],"type":"Point"}
}
