{
  "type": "Feature",
  "properties": {
    "date:inception_lower": "1980-01-01",
    "date:inception_upper": "1980-01-01",
    "iso:country": "GB",
    "wof:name": "YO22 4LJ",
    "wof:placetype": "postalcode"
  },
  "geometry": {"coordinates":[-0.568782,54.454172],"type":"Point"}
}
