{
  "type": "Feature",
  "properties": {
    "iso:country":"GB",
    "wof:name":"TA14 6QP",
    "wof:placetype":"postalcode"
},
  "geometry": {"coordinates":[-2.7505664648281,50.95384929206145],"type":"Point"}
}