{
  "type": "Feature",
  "properties": {
    "date:inception_lower": "1980-01-01",
    "date:inception_upper": "1980-01-01",
    "iso:country": "GB",
    "wof:name": "TA14 6QP",
    "wof:placetype": "postalcode"
  },
  "geometry": {"coordinates":[-2.750566,50.953849],"type":"Point"}
}
