{
  "type": "Feature",
  "properties": {
    "iso:country": "GB",
    "wof:name": "TA14 6QP",
    "wof:placetype": "postalcode"
  },
  "geometry": {"coordinates":[-2.750566,50.953849],"type":"Point"}
}
