{
  "type": "Feature",
  "properties": {
    "iso:country":"GB",
    "wof:name":"SP3 4AS",
    "wof:placetype":"postalcode"
},
  "geometry": {"coordinates":[-1.92438383482607,51.08388272372301],"type":"Point"}
}