{
  "type": "Feature",
  "properties": {
    "date:inception_lower": "1980-01-01",
    "date:inception_upper": "1980-01-01",
    "iso:country": "GB",
    "wof:name": "SP3 4AS",
    "wof:placetype": "postalcode"
  },
  "geometry": {"coordinates":[-1.924384,51.083883],"type":"Point"}
}
