{
  "type": "Feature",
  "properties": {
    "iso:country":"GB",
    "wof:name":"PE28 5QU",
    "wof:placetype":"postalcode"
},
  "geometry": {"coordinates":[-0.33153967206103,52.40555933975219],"type":"Point"}
}