{
  "type": "Feature",
  "properties": {
    "iso:country": "GB",
    "wof:name": "ST7 3TN",
    "wof:placetype": "postalcode"
  },
  "geometry": {"coordinates":[-2.292109,53.114314],"type":"Point"}
}
