{
  "type": "Feature",
  "properties": {
    "iso:country": "GB",
    "wof:name": "WF10 5SE",
    "wof:placetype": "postalcode"
  },
  "geometry": {"coordinates":[-1.356303,53.716238],"type":"Point"}
}
