{
  "type": "Feature",
  "properties": {
    "iso:country":"GB",
    "wof:name":"WF10 5SE",
    "wof:placetype":"postalcode"
},
  "geometry": {"coordinates":[-1.35630297344069,53.71623776330623],"type":"Point"}
}