{
  "type": "Feature",
  "properties": {
    "iso:country":"GB",
    "wof:name":"HG3 2ST",
    "wof:placetype":"postalcode"
},
  "geometry": {"coordinates":[-1.56342586680926,54.00240328158088],"type":"Point"}
}