{
  "type": "Feature",
  "properties": {
    "iso:country":"GB",
    "wof:name":"B73 6DT",
    "wof:placetype":"postalcode"
},
  "geometry": {"coordinates":[-1.82758375056845,52.56227444210919],"type":"Point"}
}