{
  "type": "Feature",
  "properties": {
    "iso:country":"GB",
    "wof:name":"WV14 0TP",
    "wof:placetype":"postalcode"
},
  "geometry": {"coordinates":[-2.06787000135799,52.56024939279503],"type":"Point"}
}