{
  "type": "Feature",
  "properties": {
    "date:inception_lower":"1982-03-01",
    "date:inception_upper":"1982-03-31",
    "iso:country":"GB",
    "wof:name":"WV14 0TP",
    "wof:placetype":"postalcode"
},
  "geometry": {"coordinates":[-2.06787,52.560249],"type":"Point"}
}