{
  "type": "Feature",
  "properties": {
    "iso:country":"GB",
    "wof:name":"CM16 6SB",
    "wof:placetype":"postalcode"
},
  "geometry": {"coordinates":[0.11744544825117,51.70427735937775],"type":"Point"}
}