{
  "type": "Feature",
  "properties": {
    "iso:country": "GB",
    "wof:name": "CM16 6SB",
    "wof:placetype": "postalcode"
  },
  "geometry": {"coordinates":[0.117445,51.704277],"type":"Point"}
}
