{
  "type": "Feature",
  "properties": {
    "iso:country":"GB",
    "wof:name":"S65 2TG",
    "wof:placetype":"postalcode"
},
  "geometry": {"coordinates":[-1.33614504302407,53.43009666473191],"type":"Point"}
}