{
  "type": "Feature",
  "properties": {
    "iso:country": "GB",
    "wof:name": "S65 2TG",
    "wof:placetype": "postalcode"
  },
  "geometry": {"coordinates":[-1.336145,53.430097],"type":"Point"}
}
