{
  "type": "Feature",
  "properties": {
    "iso:country":"GB",
    "wof:name":"CR0 5NX",
    "wof:placetype":"postalcode"
},
  "geometry": {"coordinates":[-0.08724310841242,51.37314962331369],"type":"Point"}
}