{
  "type": "Feature",
  "properties": {
    "iso:country": "GB",
    "wof:name": "YO14 9RX",
    "wof:placetype": "postalcode"
  },
  "geometry": {"coordinates":[-0.268746,54.160358],"type":"Point"}
}
