{
  "type": "Feature",
  "properties": {
    "iso:country":"GB",
    "wof:name":"YO14 9RX",
    "wof:placetype":"postalcode"
},
  "geometry": {"coordinates":[-0.26874595412423,54.16035763429766],"type":"Point"}
}