{
  "type": "Feature",
  "properties": {
    "iso:country": "GB",
    "wof:name": "M28 3UF",
    "wof:placetype": "postalcode"
  },
  "geometry": {"coordinates":[-2.382262,53.526397],"type":"Point"}
}
