{
  "type": "Feature",
  "properties": {
    "date:inception_lower":"2016-04-01",
    "date:inception_upper":"2016-04-30",
    "iso:country":"GB",
    "wof:name":"TR15 9BP",
    "wof:placetype":"postalcode"
},
  "geometry": {"coordinates":[-5.226712,50.233733],"type":"Point"}
}