{
  "type": "Feature",
  "properties": {
    "date:inception_lower": "1980-01-01",
    "date:inception_upper": "1980-01-01",
    "iso:country": "GB",
    "wof:name": "PE22 8LF",
    "wof:placetype": "postalcode"
  },
  "geometry": {"coordinates":[0.096688,53.121078],"type":"Point"}
}
