{
  "type": "Feature",
  "properties": {
    "iso:country":"GB",
    "wof:name":"PE22 8LF",
    "wof:placetype":"postalcode"
},
  "geometry": {"coordinates":[0.09669854901579,53.12106894038099],"type":"Point"}
}