{
  "type": "Feature",
  "properties": {
    "iso:country":"GB",
    "wof:name":"KA1 2BZ",
    "wof:placetype":"postalcode"
},
  "geometry": {"coordinates":[-4.50286546856331,55.60769843506697],"type":"Point"}
}