{
  "type": "Feature",
  "properties": {
    "date:inception_lower": "1980-01-01",
    "date:inception_upper": "1980-01-01",
    "iso:country": "GB",
    "wof:name": "KA1 2BZ",
    "wof:placetype": "postalcode"
  },
  "geometry": {"coordinates":[-4.502845,55.607698],"type":"Point"}
}
