{
  "type": "Feature",
  "properties": {
    "date:inception_lower":"1980-01-01",
    "date:inception_upper":"1980-01-31",
    "iso:country":"GB",
    "wof:name":"PE30 3QJ",
    "wof:placetype":"postalcode"
},
  "geometry": {"coordinates":[0.413065,52.798685],"type":"Point"}
}