{
  "type": "Feature",
  "properties": {
    "iso:country":"GB",
    "wof:name":"PE30 3QJ",
    "wof:placetype":"postalcode"
},
  "geometry": {"coordinates":[0.4130650861481,52.79868519605217],"type":"Point"}
}