{
  "type": "Feature",
  "properties": {
    "iso:country":"GB",
    "wof:name":"DY8 4EE",
    "wof:placetype":"postalcode"
},
  "geometry": {"coordinates":[-2.14863537218063,52.46984473622424],"type":"Point"}
}