{
  "type": "Feature",
  "properties": {
    "iso:country":"GB",
    "wof:name":"SO20 8JS",
    "wof:placetype":"postalcode"
},
  "geometry": {"coordinates":[-1.60079622553549,51.1463689308102],"type":"Point"}
}