{
  "type": "Feature",
  "properties": {
    "iso:country": "GB",
    "wof:name": "NE23 6DL",
    "wof:placetype": "postalcode"
  },
  "geometry": {"coordinates":[-1.584489,55.082346],"type":"Point"}
}
