{
  "type": "Feature",
  "properties": {
    "iso:country": "GB",
    "wof:name": "RG24 9BQ",
    "wof:placetype": "postalcode"
  },
  "geometry": {"coordinates":[-1.086342,51.283032],"type":"Point"}
}
