{
  "type": "Feature",
  "properties": {
    "date:inception_lower": "2005-10-01",
    "date:inception_upper": "2005-10-01",
    "iso:country": "GB",
    "wof:name": "L6 1EA",
    "wof:placetype": "postalcode"
  },
  "geometry": {"coordinates":[-2.967614,53.412477],"type":"Point"}
}
