{
  "type": "Feature",
  "properties": {
    "iso:country":"GB",
    "wof:name":"CW5 7QQ",
    "wof:placetype":"postalcode"
},
  "geometry": {"coordinates":[-2.51113533108353,53.0543722222998],"type":"Point"}
}