{
  "type": "Feature",
  "properties": {
    "iso:country":"GB",
    "wof:name":"SS7 4SA",
    "wof:placetype":"postalcode"
},
  "geometry": {"coordinates":[0.55478113987663,51.5774960469216],"type":"Point"}
}