{
  "type": "Feature",
  "properties": {
    "date:inception_lower": "2018-01-01",
    "date:inception_upper": "2018-01-01",
    "iso:country": "GB",
    "wof:name": "PE1 5WJ",
    "wof:placetype": "postalcode"
  },
  "geometry": {"coordinates":[-0.208581,52.584608],"type":"Point"}
}
