{
  "type": "Feature",
  "properties": {
    "iso:country":"GB",
    "wof:name":"MK3 7DB",
    "wof:placetype":"postalcode"
},
  "geometry": {"coordinates":[-0.75643148034891,51.99810030393169],"type":"Point"}
}