{
  "type": "Feature",
  "properties": {
    "date:inception_lower": "1980-01-01",
    "date:inception_upper": "1980-01-01",
    "iso:country": "GB",
    "wof:name": "CW6 9TS",
    "wof:placetype": "postalcode"
  },
  "geometry": {"coordinates":[-2.684046,53.122835],"type":"Point"}
}
