{
  "type": "Feature",
  "properties": {
    "iso:country":"GB",
    "wof:name":"CW6 9TS",
    "wof:placetype":"postalcode"
},
  "geometry": {"coordinates":[-2.68338478894746,53.12255328945147],"type":"Point"}
}