{
  "type": "Feature",
  "properties": {
    "date:inception_lower": "1980-01-01",
    "date:inception_upper": "1980-01-01",
    "iso:country": "GB",
    "wof:name": "NR9 5ER",
    "wof:placetype": "postalcode"
  },
  "geometry": {"coordinates":[1.154816,52.655331],"type":"Point"}
}
