{
  "type": "Feature",
  "properties": {
    "iso:country":"GB",
    "wof:name":"NR9 5ER",
    "wof:placetype":"postalcode"
},
  "geometry": {"coordinates":[1.15481557402603,52.65533083042416],"type":"Point"}
}