{
  "type": "Feature",
  "properties": {
    "iso:country":"GB",
    "wof:name":"TN5 6QU",
    "wof:placetype":"postalcode"
},
  "geometry": {"coordinates":[0.34950020120151,51.08688147092667],"type":"Point"}
}