{
  "type": "Feature",
  "properties": {
    "iso:country":"GB",
    "wof:name":"G53 7QW",
    "wof:placetype":"postalcode"
},
  "geometry": {"coordinates":[-4.34451431502894,55.81044067938151],"type":"Point"}
}