{
  "type": "Feature",
  "properties": {
    "iso:country": "GB",
    "wof:name": "GL54 2RZ",
    "wof:placetype": "postalcode"
  },
  "geometry": {"coordinates":[-1.754955,51.890602],"type":"Point"}
}
