{
  "type": "Feature",
  "properties": {
    "iso:country":"GB",
    "wof:name":"CR5 3DG",
    "wof:placetype":"postalcode"
},
  "geometry": {"coordinates":[-0.14772249775785,51.31819565991809],"type":"Point"}
}