{
  "type": "Feature",
  "properties": {
    "date:inception_lower": "1990-07-01",
    "date:inception_upper": "1990-07-01",
    "iso:country": "GB",
    "wof:name": "CR5 3DG",
    "wof:placetype": "postalcode"
  },
  "geometry": {"coordinates":[-0.147722,51.318196],"type":"Point"}
}
