{
  "type": "Feature",
  "properties": {
    "date:inception_lower": "1980-01-01",
    "date:inception_upper": "1980-01-01",
    "iso:country": "GB",
    "wof:name": "B36 8DT",
    "wof:placetype": "postalcode"
  },
  "geometry": {"coordinates":[-1.817436,52.49417],"type":"Point"}
}
