{
  "type": "Feature",
  "properties": {
    "iso:country":"GB",
    "wof:name":"TA4 4HN",
    "wof:placetype":"postalcode"
},
  "geometry": {"coordinates":[-3.33884862420212,51.14835765298731],"type":"Point"}
}