{
  "type": "Feature",
  "properties": {
    "iso:country":"GB",
    "wof:name":"S62 7TD",
    "wof:placetype":"postalcode"
},
  "geometry": {"coordinates":[-1.41436290686853,53.47939463871526],"type":"Point"}
}