{
  "type": "Feature",
  "properties": {
    "iso:country": "GB",
    "wof:name": "S62 7TD",
    "wof:placetype": "postalcode"
  },
  "geometry": {"coordinates":[-1.414363,53.479395],"type":"Point"}
}
