{
  "type": "Feature",
  "properties": {
    "iso:country": "GB",
    "wof:name": "GL51 3DR",
    "wof:placetype": "postalcode"
  },
  "geometry": {"coordinates":[-2.096358,51.880945],"type":"Point"}
}
