{
  "type": "Feature",
  "properties": {
    "iso:country": "GB",
    "wof:name": "SP6 3DP",
    "wof:placetype": "postalcode"
  },
  "geometry": {"coordinates":[-1.852967,50.909482],"type":"Point"}
}
