{
  "type": "Feature",
  "properties": {
    "iso:country":"GB",
    "wof:name":"SL6 3PF",
    "wof:placetype":"postalcode"
},
  "geometry": {"coordinates":[-0.76102130214047,51.50986194001549],"type":"Point"}
}