{
  "type": "Feature",
  "properties": {
    "iso:country":"GB",
    "wof:name":"E11 3AF",
    "wof:placetype":"postalcode"
},
  "geometry": {"coordinates":[0.01340487149287,51.56836828285908],"type":"Point"}
}