{
  "type": "Feature",
  "properties": {
    "iso:country": "GB",
    "wof:name": "G64 1DL",
    "wof:placetype": "postalcode"
  },
  "geometry": {"coordinates":[-4.20467,55.907651],"type":"Point"}
}
