{
  "type": "Feature",
  "properties": {
    "iso:country":"GB",
    "wof:name":"G64 1DL",
    "wof:placetype":"postalcode"
},
  "geometry": {"coordinates":[-4.20485725534446,55.90761676076816],"type":"Point"}
}