{
  "type": "Feature",
  "properties": {
    "iso:country": "GB",
    "wof:name": "CF62 7DW",
    "wof:placetype": "postalcode"
  },
  "geometry": {"coordinates":[-3.28421,51.399406],"type":"Point"}
}
