{
  "type": "Feature",
  "properties": {
    "iso:country":"GB",
    "wof:name":"CF62 7DW",
    "wof:placetype":"postalcode"
},
  "geometry": {"coordinates":[-3.28420976757783,51.39940610357138],"type":"Point"}
}