{
  "type": "Feature",
  "properties": {
    "iso:country":"GB",
    "wof:name":"BR3 5AL",
    "wof:placetype":"postalcode"
},
  "geometry": {"coordinates":[-0.02385157837594,51.41516400986183],"type":"Point"}
}