{
  "type": "Feature",
  "properties": {
    "iso:country":"GB",
    "wof:name":"HD6 2PT",
    "wof:placetype":"postalcode"
},
  "geometry": {"coordinates":[-1.79755663926191,53.71646452087446],"type":"Point"}
}