{
  "type": "Feature",
  "properties": {
    "iso:country": "GB",
    "wof:name": "GU2 7TD",
    "wof:placetype": "postalcode"
  },
  "geometry": {"coordinates":[-0.590106,51.237526],"type":"Point"}
}
