{
  "type": "Feature",
  "properties": {
    "iso:country":"GB",
    "wof:name":"GU2 7TD",
    "wof:placetype":"postalcode"
},
  "geometry": {"coordinates":[-0.59010586207436,51.23752612370254],"type":"Point"}
}