{
  "type": "Feature",
  "properties": {
    "iso:country": "GB",
    "wof:name": "CH45 3JQ",
    "wof:placetype": "postalcode"
  },
  "geometry": {"coordinates":[-3.060483,53.429297],"type":"Point"}
}
