{
  "type": "Feature",
  "properties": {
    "date:inception_lower": "1980-01-01",
    "date:inception_upper": "1980-01-01",
    "iso:country": "GB",
    "wof:name": "OX15 4NJ",
    "wof:placetype": "postalcode"
  },
  "geometry": {"coordinates":[-1.370068,52.021851],"type":"Point"}
}
