{
  "type": "Feature",
  "properties": {
    "iso:country": "GB",
    "wof:name": "OX15 4NJ",
    "wof:placetype": "postalcode"
  },
  "geometry": {"coordinates":[-1.370068,52.021851],"type":"Point"}
}
