{
  "type": "Feature",
  "properties": {
    "iso:country":"GB",
    "wof:name":"MK42 7AA",
    "wof:placetype":"postalcode"
},
  "geometry": {"coordinates":[-0.50170953787275,52.11661799828819],"type":"Point"}
}