{
  "type": "Feature",
  "properties": {
    "iso:country":"GB",
    "wof:name":"E13 8HT",
    "wof:placetype":"postalcode"
},
  "geometry": {"coordinates":[0.02041833577419,51.52052369425112],"type":"Point"}
}