{
  "type": "Feature",
  "properties": {
    "iso:country":"GB",
    "wof:name":"EX1 2RS",
    "wof:placetype":"postalcode"
},
  "geometry": {"coordinates":[-3.5023447583092,50.72112054210618],"type":"Point"}
}