{
  "type": "Feature",
  "properties": {
    "date:inception_lower":"2001-12-01",
    "date:inception_upper":"2001-12-31",
    "iso:country":"GB",
    "wof:name":"BS24 7TN",
    "wof:placetype":"postalcode"
},
  "geometry": {"coordinates":[-2.895792,51.358105],"type":"Point"}
}