{
  "type": "Feature",
  "properties": {
    "iso:country": "GB",
    "wof:name": "BS24 7TN",
    "wof:placetype": "postalcode"
  },
  "geometry": {"coordinates":[-2.895792,51.358105],"type":"Point"}
}
