{
  "type": "Feature",
  "properties": {
    "iso:country":"GB",
    "wof:name":"BS24 7TN",
    "wof:placetype":"postalcode"
},
  "geometry": {"coordinates":[-2.89531837044963,51.35809979582292],"type":"Point"}
}