{
  "type": "Feature",
  "properties": {
    "iso:country":"GB",
    "wof:name":"LE18 4UP",
    "wof:placetype":"postalcode"
},
  "geometry": {"coordinates":[-1.14012917974737,52.58745411668315],"type":"Point"}
}