{
  "type": "Feature",
  "properties": {
    "iso:country": "GB",
    "wof:name": "LE18 4UP",
    "wof:placetype": "postalcode"
  },
  "geometry": {"coordinates":[-1.140129,52.587454],"type":"Point"}
}
