{
  "type": "Feature",
  "properties": {
    "iso:country":"GB",
    "wof:name":"SR8 2EJ",
    "wof:placetype":"postalcode"
},
  "geometry": {"coordinates":[-1.35532553866337,54.76642716694644],"type":"Point"}
}