{
  "type": "Feature",
  "properties": {
    "iso:country":"GB",
    "wof:name":"WA3 4AD",
    "wof:placetype":"postalcode"
},
  "geometry": {"coordinates":[-2.53129228661931,53.44864454061845],"type":"Point"}
}