{
  "type": "Feature",
  "properties": {
    "date:inception_lower":"1980-01-01",
    "date:inception_upper":"1980-01-31",
    "iso:country":"GB",
    "wof:name":"WA3 4AD",
    "wof:placetype":"postalcode"
},
  "geometry": {"coordinates":[-2.531292,53.448645],"type":"Point"}
}