{
  "type": "Feature",
  "properties": {
    "iso:country": "GB",
    "wof:name": "RG4 8XR",
    "wof:placetype": "postalcode"
  },
  "geometry": {"coordinates":[-0.959948,51.485907],"type":"Point"}
}
