{
  "type": "Feature",
  "properties": {
    "iso:country":"GB",
    "wof:name":"UB1 2LS",
    "wof:placetype":"postalcode"
},
  "geometry": {"coordinates":[-0.36886936409795,51.51524374442744],"type":"Point"}
}