{
  "type": "Feature",
  "properties": {
    "iso:country": "GB",
    "wof:name": "UB1 2LS",
    "wof:placetype": "postalcode"
  },
  "geometry": {"coordinates":[-0.368869,51.515244],"type":"Point"}
}
