{
  "type": "Feature",
  "properties": {
    "iso:country":"GB",
    "wof:name":"HR3 6AT",
    "wof:placetype":"postalcode"
},
  "geometry": {"coordinates":[-2.98557934247758,52.06886793599713],"type":"Point"}
}