{
  "type": "Feature",
  "properties": {
    "iso:country": "GB",
    "wof:name": "EH13 9NP",
    "wof:placetype": "postalcode"
  },
  "geometry": {"coordinates":[-3.224614,55.903684],"type":"Point"}
}
