{
  "type": "Feature",
  "properties": {
    "iso:country":"GB",
    "wof:name":"DA2 7LG",
    "wof:placetype":"postalcode"
},
  "geometry": {"coordinates":[0.25961049222598,51.42128213621638],"type":"Point"}
}