{
  "type": "Feature",
  "properties": {
    "date:inception_lower": "2017-11-01",
    "date:inception_upper": "2017-11-01",
    "iso:country": "GB",
    "wof:name": "DN6 0BU",
    "wof:placetype": "postalcode"
  },
  "geometry": {"coordinates":[-1.153636,53.613616],"type":"Point"}
}
