{
  "type": "Feature",
  "properties": {
    "iso:country": "GB",
    "wof:name": "TQ5 9RU",
    "wof:placetype": "postalcode"
  },
  "geometry": {"coordinates":[-3.514388,50.393915],"type":"Point"}
}
