{
  "type": "Feature",
  "properties": {
    "date:inception_lower": "1980-01-01",
    "date:inception_upper": "1980-01-01",
    "iso:country": "GB",
    "wof:name": "TQ5 9RU",
    "wof:placetype": "postalcode"
  },
  "geometry": {"coordinates":[-3.51447,50.393808],"type":"Point"}
}
