{
  "type": "Feature",
  "properties": {
    "date:inception_lower":"1980-01-01",
    "date:inception_upper":"1980-01-31",
    "iso:country":"GB",
    "wof:name":"TQ5 9RU",
    "wof:placetype":"postalcode"
},
  "geometry": {"coordinates":[-3.514388,50.393915],"type":"Point"}
}