{
  "type": "Feature",
  "properties": {
    "iso:country":"GB",
    "wof:name":"TQ5 9RU",
    "wof:placetype":"postalcode"
},
  "geometry": {"coordinates":[-3.51438780339938,50.39391508811372],"type":"Point"}
}