{
  "type": "Feature",
  "properties": {
    "date:inception_lower": "1986-04-01",
    "date:inception_upper": "1986-04-01",
    "iso:country": "GB",
    "wof:name": "ME13 9LR",
    "wof:placetype": "postalcode"
  },
  "geometry": {"coordinates":[0.983347,51.291946],"type":"Point"}
}
