{
  "type": "Feature",
  "properties": {
    "iso:country":"GB",
    "wof:name":"TA8 2QR",
    "wof:placetype":"postalcode"
},
  "geometry": {"coordinates":[-3.01164865319439,51.26930035605454],"type":"Point"}
}