{
  "type": "Feature",
  "properties": {
    "date:inception_lower": "2002-06-01",
    "date:inception_upper": "2002-06-01",
    "iso:country": "GB",
    "wof:name": "KT13 8EF",
    "wof:placetype": "postalcode"
  },
  "geometry": {"coordinates":[-0.468166,51.361789],"type":"Point"}
}
