{
  "type": "Feature",
  "properties": {
    "iso:country":"GB",
    "wof:name":"GL11 4NZ",
    "wof:placetype":"postalcode"
},
  "geometry": {"coordinates":[-2.34310430717929,51.67586492184039],"type":"Point"}
}