{
  "type": "Feature",
  "properties": {
    "date:inception_lower": "2015-05-01",
    "date:inception_upper": "2015-05-01",
    "iso:country": "GB",
    "wof:name": "BA21 3FJ",
    "wof:placetype": "postalcode"
  },
  "geometry": {"coordinates":[-2.670834,50.955316],"type":"Point"}
}
