{
  "type": "Feature",
  "properties": {
    "iso:country": "GB",
    "wof:name": "BA21 3FJ",
    "wof:placetype": "postalcode"
  },
  "geometry": {"coordinates":[-2.670877,50.955316],"type":"Point"}
}
