{
  "type": "Feature",
  "properties": {
    "iso:country":"GB",
    "wof:name":"SL1 8BH",
    "wof:placetype":"postalcode"
},
  "geometry": {"coordinates":[-0.65936088816121,51.53627767849091],"type":"Point"}
}