{
  "type": "Feature",
  "properties": {
    "iso:country":"GB",
    "wof:name":"PO21 4NR",
    "wof:placetype":"postalcode"
},
  "geometry": {"coordinates":[-0.74496535983616,50.77024889220432],"type":"Point"}
}