{
  "type": "Feature",
  "properties": {
    "iso:country": "GB",
    "wof:name": "PO21 4NR",
    "wof:placetype": "postalcode"
  },
  "geometry": {"coordinates":[-0.744965,50.770249],"type":"Point"}
}
