{
  "type": "Feature",
  "properties": {
    "iso:country":"GB",
    "wof:name":"DE22 3DN",
    "wof:placetype":"postalcode"
},
  "geometry": {"coordinates":[-1.50464901423294,52.92479792814932],"type":"Point"}
}