{
  "type": "Feature",
  "properties": {
    "iso:country":"GB",
    "wof:name":"ME19 6BE",
    "wof:placetype":"postalcode"
},
  "geometry": {"coordinates":[0.45054319227416,51.27835098310126],"type":"Point"}
}