{
  "type": "Feature",
  "properties": {
    "iso:country": "GB",
    "wof:name": "PE15 0WN",
    "wof:placetype": "postalcode"
  },
  "geometry": {"coordinates":[0.053266,52.498768],"type":"Point"}
}
