{
  "type": "Feature",
  "properties": {
    "iso:country": "GB",
    "wof:name": "DA13 0QR",
    "wof:placetype": "postalcode"
  },
  "geometry": {"coordinates":[0.347889,51.343598],"type":"Point"}
}
