{
  "type": "Feature",
  "properties": {
    "iso:country":"GB",
    "wof:name":"DA13 0QR",
    "wof:placetype":"postalcode"
},
  "geometry": {"coordinates":[0.347889373687,51.34359800322766],"type":"Point"}
}