{
  "type": "Feature",
  "properties": {
    "iso:country":"GB",
    "wof:name":"IV32 7LQ",
    "wof:placetype":"postalcode"
},
  "geometry": {"coordinates":[-3.12103922660782,57.65001943296986],"type":"Point"}
}