{
  "type": "Feature",
  "properties": {
    "iso:country":"GB",
    "wof:name":"S10 1LJ",
    "wof:placetype":"postalcode"
},
  "geometry": {"coordinates":[-1.50054049297821,53.38660079558203],"type":"Point"}
}