{
  "type": "Feature",
  "properties": {
    "iso:country": "GB",
    "wof:name": "HP3 9BF",
    "wof:placetype": "postalcode"
  },
  "geometry": {"coordinates":[-0.458381,51.730813],"type":"Point"}
}
