{
  "type": "Feature",
  "properties": {
    "iso:country":"GB",
    "wof:name":"HP3 9BF",
    "wof:placetype":"postalcode"
},
  "geometry": {"coordinates":[-0.45840257891025,51.73080620937616],"type":"Point"}
}