{
  "type": "Feature",
  "properties": {
    "iso:country": "GB",
    "wof:name": "SR4 0NQ",
    "wof:placetype": "postalcode"
  },
  "geometry": {"coordinates":[-1.458382,54.902744],"type":"Point"}
}
