{
  "type": "Feature",
  "properties": {
    "iso:country":"GB",
    "wof:name":"SR4 0NQ",
    "wof:placetype":"postalcode"
},
  "geometry": {"coordinates":[-1.45824011961636,54.90302227448505],"type":"Point"}
}