{
  "type": "Feature",
  "properties": {
    "iso:country":"GB",
    "wof:name":"DE55 2AQ",
    "wof:placetype":"postalcode"
},
  "geometry": {"coordinates":[-1.34677793153749,53.10091785572313],"type":"Point"}
}