{
  "type": "Feature",
  "properties": {
    "iso:country":"GB",
    "wof:name":"HU15 1PB",
    "wof:placetype":"postalcode"
},
  "geometry": {"coordinates":[-0.54678346267496,53.73365901221372],"type":"Point"}
}