{
  "type": "Feature",
  "properties": {
    "date:inception_lower":"1999-12-01",
    "date:inception_upper":"1999-12-31",
    "iso:country":"GB",
    "wof:name":"GL2 5HD",
    "wof:placetype":"postalcode"
},
  "geometry": {"coordinates":[-2.260041,51.860881],"type":"Point"}
}