{
  "type": "Feature",
  "properties": {
    "date:inception_lower": "1984-02-01",
    "date:inception_upper": "1984-02-01",
    "iso:country": "GB",
    "wof:name": "CV4 7EY",
    "wof:placetype": "postalcode"
  },
  "geometry": {"coordinates":[-1.55453,52.385735],"type":"Point"}
}
