{
  "type": "Feature",
  "properties": {
    "iso:country":"GB",
    "wof:name":"CV4 7EY",
    "wof:placetype":"postalcode"
},
  "geometry": {"coordinates":[-1.55453018386758,52.38573546328192],"type":"Point"}
}