{
  "type": "Feature",
  "properties": {
    "iso:country": "GB",
    "wof:name": "GL15 5HS",
    "wof:placetype": "postalcode"
  },
  "geometry": {"coordinates":[-2.53678,51.725971],"type":"Point"}
}
