{
  "type": "Feature",
  "properties": {
    "iso:country":"GB",
    "wof:name":"GL15 5HS",
    "wof:placetype":"postalcode"
},
  "geometry": {"coordinates":[-2.53677914202386,51.72597563967938],"type":"Point"}
}