{
  "type": "Feature",
  "properties": {
    "iso:country": "GB",
    "wof:name": "NG4 2JN",
    "wof:placetype": "postalcode"
  },
  "geometry": {"coordinates":[-1.071641,52.956646],"type":"Point"}
}
