{
  "type": "Feature",
  "properties": {
    "iso:country":"GB",
    "wof:name":"EH47 9BU",
    "wof:placetype":"postalcode"
},
  "geometry": {"coordinates":[-3.71405095968005,55.8250167496821],"type":"Point"}
}