{
  "type": "Feature",
  "properties": {
    "iso:country":"GB",
    "wof:name":"CB5 8NN",
    "wof:placetype":"postalcode"
},
  "geometry": {"coordinates":[0.16151137935317,52.21125154036921],"type":"Point"}
}