{
  "type": "Feature",
  "properties": {
    "date:inception_lower": "1980-01-01",
    "date:inception_upper": "1980-01-01",
    "iso:country": "GB",
    "wof:name": "WF2 0QG",
    "wof:placetype": "postalcode"
  },
  "geometry": {"coordinates":[-1.519109,53.706592],"type":"Point"}
}
