{
  "type": "Feature",
  "properties": {
    "iso:country":"GB",
    "wof:name":"EX39 3BB",
    "wof:placetype":"postalcode"
},
  "geometry": {"coordinates":[-4.22515634180643,51.01290453273872],"type":"Point"}
}