{
  "type": "Feature",
  "properties": {
    "date:inception_lower": "1980-01-01",
    "date:inception_upper": "1980-01-01",
    "iso:country": "GB",
    "wof:name": "LL29 7DA",
    "wof:placetype": "postalcode"
  },
  "geometry": {"coordinates":[-3.733058,53.296002],"type":"Point"}
}
