{
  "type": "Feature",
  "properties": {
    "date:inception_lower": "2001-12-01",
    "date:inception_upper": "2001-12-01",
    "iso:country": "GB",
    "wof:name": "EX8 5SY",
    "wof:placetype": "postalcode"
  },
  "geometry": {"coordinates":[-3.401401,50.642606],"type":"Point"}
}
