{
  "type": "Feature",
  "properties": {
    "iso:country":"GB",
    "wof:name":"EX8 5SY",
    "wof:placetype":"postalcode"
},
  "geometry": {"coordinates":[-3.40140045308421,50.64256279617201],"type":"Point"}
}