{
  "type": "Feature",
  "properties": {
    "iso:country": "GB",
    "wof:name": "EX8 5SY",
    "wof:placetype": "postalcode"
  },
  "geometry": {"coordinates":[-3.4014,50.642563],"type":"Point"}
}
