{
  "type": "Feature",
  "properties": {
    "iso:country":"GB",
    "wof:name":"B14 5UR",
    "wof:placetype":"postalcode"
},
  "geometry": {"coordinates":[-1.90033747447735,52.40608548105223],"type":"Point"}
}