{
  "type": "Feature",
  "properties": {
    "date:inception_lower":"1980-01-01",
    "date:inception_upper":"1980-01-31",
    "iso:country":"GB",
    "wof:name":"IP3 8DX",
    "wof:placetype":"postalcode"
},
  "geometry": {"coordinates":[1.175342,52.049221],"type":"Point"}
}