{
  "type": "Feature",
  "properties": {
    "date:inception_lower": "1980-01-01",
    "date:inception_upper": "1980-01-01",
    "iso:country": "GB",
    "wof:name": "TW18 1QJ",
    "wof:placetype": "postalcode"
  },
  "geometry": {"coordinates":[-0.478457,51.422253],"type":"Point"}
}
