{
  "type": "Feature",
  "properties": {
    "iso:country":"GB",
    "wof:name":"TW18 1QJ",
    "wof:placetype":"postalcode"
},
  "geometry": {"coordinates":[-0.47845731439093,51.42225312484894],"type":"Point"}
}