{
  "type": "Feature",
  "properties": {
    "date:inception_lower": "1980-01-01",
    "date:inception_upper": "1980-01-01",
    "iso:country": "GB",
    "wof:name": "CO1 2DT",
    "wof:placetype": "postalcode"
  },
  "geometry": {"coordinates":[0.914876,51.883722],"type":"Point"}
}
