{
  "type": "Feature",
  "properties": {
    "iso:country": "GB",
    "wof:name": "G83 8QH",
    "wof:placetype": "postalcode"
  },
  "geometry": {"coordinates":[-4.575425,56.000881],"type":"Point"}
}
