{
  "type": "Feature",
  "properties": {
    "iso:country":"GB",
    "wof:name":"LE2 2DD",
    "wof:placetype":"postalcode"
},
  "geometry": {"coordinates":[-1.09585649626143,52.61499369074751],"type":"Point"}
}