{
  "type": "Feature",
  "properties": {
    "iso:country":"GB",
    "wof:name":"TN30 6NS",
    "wof:placetype":"postalcode"
},
  "geometry": {"coordinates":[0.69881473674208,51.07809451738368],"type":"Point"}
}