{
  "type": "Feature",
  "properties": {
    "iso:country":"GB",
    "wof:name":"MK40 4PZ",
    "wof:placetype":"postalcode"
},
  "geometry": {"coordinates":[-0.50711557091633,52.14103485630358],"type":"Point"}
}