{
  "type": "Feature",
  "properties": {
    "iso:country": "GB",
    "wof:name": "MK40 4PZ",
    "wof:placetype": "postalcode"
  },
  "geometry": {"coordinates":[-0.507116,52.141035],"type":"Point"}
}
