{
  "type": "Feature",
  "properties": {
    "date:inception_lower": "1994-12-01",
    "date:inception_upper": "1994-12-01",
    "iso:country": "GB",
    "wof:name": "MK40 4PZ",
    "wof:placetype": "postalcode"
  },
  "geometry": {"coordinates":[-0.50708,52.141065],"type":"Point"}
}
