{
  "type": "Feature",
  "properties": {
    "iso:country":"GB",
    "wof:name":"G32 8YL",
    "wof:placetype":"postalcode"
},
  "geometry": {"coordinates":[-4.17469919014161,55.83559908347603],"type":"Point"}
}