{
  "type": "Feature",
  "properties": {
    "iso:country":"GB",
    "wof:name":"PO11 0AH",
    "wof:placetype":"postalcode"
},
  "geometry": {"coordinates":[-0.99097266909955,50.78595457769612],"type":"Point"}
}