{
  "type": "Feature",
  "properties": {
    "iso:country":"GB",
    "wof:name":"SE18 2BL",
    "wof:placetype":"postalcode"
},
  "geometry": {"coordinates":[0.09874926147601,51.47915709121974],"type":"Point"}
}