{
  "type": "Feature",
  "properties": {
    "iso:country":"GB",
    "wof:name":"S5 6QT",
    "wof:placetype":"postalcode"
},
  "geometry": {"coordinates":[-1.45084295442375,53.41980254225877],"type":"Point"}
}