{
  "type": "Feature",
  "properties": {
    "date:inception_lower": "1980-01-01",
    "date:inception_upper": "1980-01-01",
    "iso:country": "GB",
    "wof:name": "S5 6QT",
    "wof:placetype": "postalcode"
  },
  "geometry": {"coordinates":[-1.450843,53.419803],"type":"Point"}
}
