{
  "type": "Feature",
  "properties": {
    "date:inception_lower":"2002-06-01",
    "date:inception_upper":"2002-06-30",
    "iso:country":"GB",
    "wof:name":"SP10 2BD",
    "wof:placetype":"postalcode"
},
  "geometry": {"coordinates":[-1.471786,51.20561],"type":"Point"}
}