{
  "type": "Feature",
  "properties": {
    "iso:country":"GB",
    "wof:name":"CR0 2GZ",
    "wof:placetype":"postalcode"
},
  "geometry": {"coordinates":[-0.09929694958682,51.38357954395552],"type":"Point"}
}