{
  "type": "Feature",
  "properties": {
    "date:inception_lower":"2005-05-01",
    "date:inception_upper":"2005-05-31",
    "iso:country":"GB",
    "wof:name":"CR0 2GZ",
    "wof:placetype":"postalcode"
},
  "geometry": {"coordinates":[-0.099297,51.38358],"type":"Point"}
}