{
  "type": "Feature",
  "properties": {
    "iso:country": "GB",
    "wof:name": "CR0 2GZ",
    "wof:placetype": "postalcode"
  },
  "geometry": {"coordinates":[-0.099297,51.38358],"type":"Point"}
}
