{
  "type": "Feature",
  "properties": {
    "date:inception_lower":"2015-10-01",
    "date:inception_upper":"2015-10-31",
    "iso:country":"GB",
    "wof:name":"GL2 4BA",
    "wof:placetype":"postalcode"
},
  "geometry": {"coordinates":[-2.294862,51.818568],"type":"Point"}
}