{
  "type": "Feature",
  "properties": {
    "iso:country":"GB",
    "wof:name":"WA4 6SB",
    "wof:placetype":"postalcode"
},
  "geometry": {"coordinates":[-2.59258672562486,53.36402425310487],"type":"Point"}
}