{
  "type": "Feature",
  "properties": {
    "iso:country": "GB",
    "wof:name": "WA4 6SB",
    "wof:placetype": "postalcode"
  },
  "geometry": {"coordinates":[-2.592587,53.364024],"type":"Point"}
}
