{
  "type": "Feature",
  "properties": {
    "date:inception_lower": "1990-02-01",
    "date:inception_upper": "1990-02-01",
    "iso:country": "GB",
    "wof:name": "RH9 8NP",
    "wof:placetype": "postalcode"
  },
  "geometry": {"coordinates":[-0.060501,51.230631],"type":"Point"}
}
