{
  "type": "Feature",
  "properties": {
    "iso:country":"GB",
    "wof:name":"RH9 8NP",
    "wof:placetype":"postalcode"
},
  "geometry": {"coordinates":[-0.06050094866338,51.23063128078184],"type":"Point"}
}