{
  "type": "Feature",
  "properties": {
    "iso:country": "GB",
    "wof:name": "AL7 4QQ",
    "wof:placetype": "postalcode"
  },
  "geometry": {"coordinates":[-0.186764,51.786041],"type":"Point"}
}
