{
  "type": "Feature",
  "properties": {
    "iso:country":"GB",
    "wof:name":"AL7 4QQ",
    "wof:placetype":"postalcode"
},
  "geometry": {"coordinates":[-0.18678980888624,51.78603418954409],"type":"Point"}
}