{
  "type": "Feature",
  "properties": {
    "date:inception_lower": "1980-01-01",
    "date:inception_upper": "1980-01-01",
    "iso:country": "GB",
    "wof:name": "AL7 4QQ",
    "wof:placetype": "postalcode"
  },
  "geometry": {"coordinates":[-0.186765,51.786032],"type":"Point"}
}
