{
  "type": "Feature",
  "properties": {
    "iso:country": "GB",
    "wof:name": "BA12 6BB",
    "wof:placetype": "postalcode"
  },
  "geometry": {"coordinates":[-2.250762,51.084321],"type":"Point"}
}
