{
  "type": "Feature",
  "properties": {
    "iso:country": "GB",
    "wof:name": "WS1 3EG",
    "wof:placetype": "postalcode"
  },
  "geometry": {"coordinates":[-1.977793,52.576422],"type":"Point"}
}
