{
  "type": "Feature",
  "properties": {
    "iso:country":"GB",
    "wof:name":"WS1 3EG",
    "wof:placetype":"postalcode"
},
  "geometry": {"coordinates":[-1.97779261575546,52.576421674206],"type":"Point"}
}