{
  "type": "Feature",
  "properties": {
    "iso:country":"GB",
    "wof:name":"LS10 1GE",
    "wof:placetype":"postalcode"
},
  "geometry": {"coordinates":[-1.52412851502674,53.78238305430487],"type":"Point"}
}