{
  "type": "Feature",
  "properties": {
    "date:inception_lower":"2011-05-01",
    "date:inception_upper":"2011-05-31",
    "iso:country":"GB",
    "wof:name":"LS10 1GE",
    "wof:placetype":"postalcode"
},
  "geometry": {"coordinates":[-1.524128,53.782383],"type":"Point"}
}