{
  "type": "Feature",
  "properties": {
    "iso:country":"GB",
    "wof:name":"E9 5LB",
    "wof:placetype":"postalcode"
},
  "geometry": {"coordinates":[-0.02796120981973,51.54511457990247],"type":"Point"}
}