{
  "type": "Feature",
  "properties": {
    "iso:country":"GB",
    "wof:name":"NR19 1EN",
    "wof:placetype":"postalcode"
},
  "geometry": {"coordinates":[0.93838319792163,52.66960420208863],"type":"Point"}
}