{
  "type": "Feature",
  "properties": {
    "iso:country":"GB",
    "wof:name":"NG17 2BL",
    "wof:placetype":"postalcode"
},
  "geometry": {"coordinates":[-1.26485853206436,53.12883717800771],"type":"Point"}
}