{
  "type": "Feature",
  "properties": {
    "date:inception_lower": "1980-01-01",
    "date:inception_upper": "1980-01-01",
    "iso:country": "GB",
    "wof:name": "NG17 2BL",
    "wof:placetype": "postalcode"
  },
  "geometry": {"coordinates":[-1.264858,53.128837],"type":"Point"}
}
