{
  "type": "Feature",
  "properties": {
    "date:inception_lower": "1980-01-01",
    "date:inception_upper": "1980-01-01",
    "iso:country": "GB",
    "wof:name": "NG19 7HZ",
    "wof:placetype": "postalcode"
  },
  "geometry": {"coordinates":[-1.21943,53.158257],"type":"Point"}
}
