{
  "type": "Feature",
  "properties": {
    "iso:country":"GB",
    "wof:name":"WS13 8HB",
    "wof:placetype":"postalcode"
},
  "geometry": {"coordinates":[-1.83485628704751,52.70771166494104],"type":"Point"}
}