{
  "type": "Feature",
  "properties": {
    "date:inception_lower": "2019-07-01",
    "date:inception_upper": "2019-07-01",
    "iso:country": "GB",
    "wof:name": "G41 1AW",
    "wof:placetype": "postalcode"
  },
  "geometry": {"coordinates":[-4.267787,55.844859],"type":"Point"}
}
