{
  "type": "Feature",
  "properties": {
    "date:inception_lower":"1980-01-01",
    "date:inception_upper":"1980-01-31",
    "iso:country":"GB",
    "wof:name":"TN25 5DB",
    "wof:placetype":"postalcode"
},
  "geometry": {"coordinates":[0.955433,51.179576],"type":"Point"}
}