{
  "type": "Feature",
  "properties": {
    "iso:country": "GB",
    "wof:name": "HA8 9QT",
    "wof:placetype": "postalcode"
  },
  "geometry": {"coordinates":[-0.269112,51.621874],"type":"Point"}
}
