{
  "type": "Feature",
  "properties": {
    "iso:country":"GB",
    "wof:name":"HA8 9QT",
    "wof:placetype":"postalcode"
},
  "geometry": {"coordinates":[-0.26911196017528,51.62187444572069],"type":"Point"}
}