{
  "type": "Feature",
  "properties": {
    "iso:country": "GB",
    "wof:name": "SN25 4GQ",
    "wof:placetype": "postalcode"
  },
  "geometry": {"coordinates":[-1.798682,51.604795],"type":"Point"}
}
