{
  "type": "Feature",
  "properties": {
    "iso:country":"GB",
    "wof:name":"SP4 0HW",
    "wof:placetype":"postalcode"
},
  "geometry": {"coordinates":[-1.70497417205718,51.16816877221167],"type":"Point"}
}