{
  "type": "Feature",
  "properties": {
    "iso:country": "GB",
    "wof:name": "SP4 0HW",
    "wof:placetype": "postalcode"
  },
  "geometry": {"coordinates":[-1.704962,51.168164],"type":"Point"}
}
