{
  "type": "Feature",
  "properties": {
    "iso:country":"GB",
    "wof:name":"SM3 8JH",
    "wof:placetype":"postalcode"
},
  "geometry": {"coordinates":[-0.23220142639961,51.36754906882722],"type":"Point"}
}