{
  "type": "Feature",
  "properties": {
    "date:inception_lower": "2013-05-01",
    "date:inception_upper": "2013-05-01",
    "iso:country": "GB",
    "wof:name": "MK3 5GL",
    "wof:placetype": "postalcode"
  },
  "geometry": {"coordinates":[-0.741806,51.972131],"type":"Point"}
}
