{
  "type": "Feature",
  "properties": {
    "iso:country":"GB",
    "wof:name":"MK3 5GL",
    "wof:placetype":"postalcode"
},
  "geometry": {"coordinates":[-0.74180641567292,51.97213116583716],"type":"Point"}
}