{
  "type": "Feature",
  "properties": {
    "iso:country": "GB",
    "wof:name": "EC3A 8EP",
    "wof:placetype": "postalcode"
  },
  "geometry": {"coordinates":[-0.080463,51.514484],"type":"Point"}
}
