{
  "type": "Feature",
  "properties": {
    "date:inception_lower":"2007-11-01",
    "date:inception_upper":"2007-11-30",
    "iso:country":"GB",
    "wof:name":"PE6 7AJ",
    "wof:placetype":"postalcode"
},
  "geometry": {"coordinates":[-0.222627,52.636174],"type":"Point"}
}