{
  "type": "Feature",
  "properties": {
    "iso:country": "GB",
    "wof:name": "PE6 7AJ",
    "wof:placetype": "postalcode"
  },
  "geometry": {"coordinates":[-0.222627,52.636174],"type":"Point"}
}
