{
  "type": "Feature",
  "properties": {
    "iso:country":"GB",
    "wof:name":"PE6 7AJ",
    "wof:placetype":"postalcode"
},
  "geometry": {"coordinates":[-0.22262688882313,52.63617397115505],"type":"Point"}
}