{
  "type": "Feature",
  "properties": {
    "iso:country": "GB",
    "wof:name": "SP11 0HB",
    "wof:placetype": "postalcode"
  },
  "geometry": {"coordinates":[-1.5078,51.306368],"type":"Point"}
}
