{
  "type": "Feature",
  "properties": {
    "iso:country":"GB",
    "wof:name":"SP11 0HB",
    "wof:placetype":"postalcode"
},
  "geometry": {"coordinates":[-1.50779993604027,51.30636837028506],"type":"Point"}
}