{
  "type": "Feature",
  "properties": {
    "iso:country":"GB",
    "wof:name":"ST15 0RN",
    "wof:placetype":"postalcode"
},
  "geometry": {"coordinates":[-2.20415235229676,52.89233905540445],"type":"Point"}
}