{
  "type": "Feature",
  "properties": {
    "iso:country":"GB",
    "wof:name":"IP13 0HW",
    "wof:placetype":"postalcode"
},
  "geometry": {"coordinates":[1.36149216233967,52.14249641777294],"type":"Point"}
}