{
  "type": "Feature",
  "properties": {
    "iso:country":"GB",
    "wof:name":"LS7 2DQ",
    "wof:placetype":"postalcode"
},
  "geometry": {"coordinates":[-1.5446990995899,53.81542201885614],"type":"Point"}
}