{
  "type": "Feature",
  "properties": {
    "iso:country": "GB",
    "wof:name": "LS7 2DQ",
    "wof:placetype": "postalcode"
  },
  "geometry": {"coordinates":[-1.544699,53.815422],"type":"Point"}
}
