{
  "type": "Feature",
  "properties": {
    "iso:country":"GB",
    "wof:name":"PE30 2BL",
    "wof:placetype":"postalcode"
},
  "geometry": {"coordinates":[0.40645239951983,52.7603263902833],"type":"Point"}
}