{
  "type": "Feature",
  "properties": {
    "iso:country": "GB",
    "wof:name": "PE30 2BL",
    "wof:placetype": "postalcode"
  },
  "geometry": {"coordinates":[0.406452,52.760326],"type":"Point"}
}
