{
  "type": "Feature",
  "properties": {
    "iso:country":"GB",
    "wof:name":"SE26 6NP",
    "wof:placetype":"postalcode"
},
  "geometry": {"coordinates":[-0.0665669320631,51.42634404816272],"type":"Point"}
}