{
  "type": "Feature",
  "properties": {
    "iso:country":"GB",
    "wof:name":"SO40 3RZ",
    "wof:placetype":"postalcode"
},
  "geometry": {"coordinates":[-1.49945176117131,50.92261176046593],"type":"Point"}
}