{
  "type": "Feature",
  "properties": {
    "date:inception_lower": "2024-10-01",
    "date:inception_upper": "2024-10-01",
    "iso:country": "GB",
    "wof:name": "B75 7EU",
    "wof:placetype": "postalcode"
  },
  "geometry": {"coordinates":[-1.77375,52.564636],"type":"Point"}
}
