{
  "type": "Feature",
  "properties": {
    "iso:country":"GB",
    "wof:name":"TR14 0JS",
    "wof:placetype":"postalcode"
},
  "geometry": {"coordinates":[-5.3101821836785,50.1729885534275],"type":"Point"}
}