{
  "type": "Feature",
  "properties": {
    "iso:country": "GB",
    "wof:name": "TR14 0JS",
    "wof:placetype": "postalcode"
  },
  "geometry": {"coordinates":[-5.310218,50.17297],"type":"Point"}
}
