{
  "type": "Feature",
  "properties": {
    "iso:country": "GB",
    "wof:name": "DL4 1DT",
    "wof:placetype": "postalcode"
  },
  "geometry": {"coordinates":[-1.645009,54.634033],"type":"Point"}
}
