{
  "type": "Feature",
  "properties": {
    "iso:country":"GB",
    "wof:name":"DL4 1DT",
    "wof:placetype":"postalcode"
},
  "geometry": {"coordinates":[-1.64500921430763,54.63403342032768],"type":"Point"}
}