{
  "type": "Feature",
  "properties": {
    "date:inception_lower":"1980-01-01",
    "date:inception_upper":"1980-01-31",
    "iso:country":"GB",
    "wof:name":"DL4 1DT",
    "wof:placetype":"postalcode"
},
  "geometry": {"coordinates":[-1.645009,54.634033],"type":"Point"}
}