{
  "type": "Feature",
  "properties": {
    "iso:country":"GB",
    "wof:name":"EN2 7EF",
    "wof:placetype":"postalcode"
},
  "geometry": {"coordinates":[-0.10348718924197,51.65436790827685],"type":"Point"}
}