{
  "type": "Feature",
  "properties": {
    "date:inception_lower": "1980-01-01",
    "date:inception_upper": "1980-01-01",
    "iso:country": "GB",
    "wof:name": "PR5 6RA",
    "wof:placetype": "postalcode"
  },
  "geometry": {"coordinates":[-2.658568,53.731129],"type":"Point"}
}
