{
  "type": "Feature",
  "properties": {
    "iso:country":"GB",
    "wof:name":"PR5 6RA",
    "wof:placetype":"postalcode"
},
  "geometry": {"coordinates":[-2.6585681495648,53.73112851026927],"type":"Point"}
}