{
  "type": "Feature",
  "properties": {
    "iso:country":"GB",
    "wof:name":"SO22 5LT",
    "wof:placetype":"postalcode"
},
  "geometry": {"coordinates":[-1.34541903574696,51.07316470600549],"type":"Point"}
}