{
  "type": "Feature",
  "properties": {
    "iso:country": "GB",
    "wof:name": "SO22 5LT",
    "wof:placetype": "postalcode"
  },
  "geometry": {"coordinates":[-1.345419,51.073165],"type":"Point"}
}
