{
  "type": "Feature",
  "properties": {
    "iso:country": "GB",
    "wof:name": "LS28 9LU",
    "wof:placetype": "postalcode"
  },
  "geometry": {"coordinates":[-1.652274,53.791883],"type":"Point"}
}
