{
  "type": "Feature",
  "properties": {
    "iso:country": "GB",
    "wof:name": "PE14 0SP",
    "wof:placetype": "postalcode"
  },
  "geometry": {"coordinates":[0.150262,52.658899],"type":"Point"}
}
