{
  "type": "Feature",
  "properties": {
    "date:inception_lower": "1980-01-01",
    "date:inception_upper": "1980-01-01",
    "iso:country": "GB",
    "wof:name": "MK40 1QX",
    "wof:placetype": "postalcode"
  },
  "geometry": {"coordinates":[-0.472322,52.135279],"type":"Point"}
}
