{
  "type": "Feature",
  "properties": {
    "iso:country":"GB",
    "wof:name":"BB2 6DZ",
    "wof:placetype":"postalcode"
},
  "geometry": {"coordinates":[-2.49907222636593,53.75633795339897],"type":"Point"}
}