{
  "type": "Feature",
  "properties": {
    "date:inception_lower":"2000-12-01",
    "date:inception_upper":"2000-12-31",
    "iso:country":"GB",
    "wof:name":"BB2 6DZ",
    "wof:placetype":"postalcode"
},
  "geometry": {"coordinates":[-2.49904,53.756362],"type":"Point"}
}