{
  "type": "Feature",
  "properties": {
    "date:inception_lower": "2000-12-01",
    "date:inception_upper": "2000-12-01",
    "iso:country": "GB",
    "wof:name": "BB2 6DZ",
    "wof:placetype": "postalcode"
  },
  "geometry": {"coordinates":[-2.499116,53.756353],"type":"Point"}
}
