{
  "type": "Feature",
  "properties": {
    "iso:country":"GB",
    "wof:name":"WV4 4PJ",
    "wof:placetype":"postalcode"
},
  "geometry": {"coordinates":[-2.17259478487868,52.56971699775366],"type":"Point"}
}