{
  "type": "Feature",
  "properties": {
    "iso:country":"GB",
    "wof:name":"M14 6JP",
    "wof:placetype":"postalcode"
},
  "geometry": {"coordinates":[-2.22544104123575,53.44337578984991],"type":"Point"}
}