{
  "type": "Feature",
  "properties": {
    "iso:country": "GB",
    "wof:name": "KT17 9NW",
    "wof:placetype": "postalcode"
  },
  "geometry": {"coordinates":[-0.262416,51.335321],"type":"Point"}
}
