{
  "type": "Feature",
  "properties": {
    "iso:country": "GB",
    "wof:name": "WD3 7BZ",
    "wof:placetype": "postalcode"
  },
  "geometry": {"coordinates":[-0.475129,51.64101],"type":"Point"}
}
