{
  "type": "Feature",
  "properties": {
    "iso:country":"GB",
    "wof:name":"WD3 7BZ",
    "wof:placetype":"postalcode"
},
  "geometry": {"coordinates":[-0.47528887230091,51.64117934524153],"type":"Point"}
}