{
  "type": "Feature",
  "properties": {
    "iso:country": "GB",
    "wof:name": "TF4 3FT",
    "wof:placetype": "postalcode"
  },
  "geometry": {"coordinates":[-2.487722,52.656926],"type":"Point"}
}
