{
  "type": "Feature",
  "properties": {
    "iso:country":"GB",
    "wof:name":"SG2 0QW",
    "wof:placetype":"postalcode"
},
  "geometry": {"coordinates":[-0.16812366752166,51.90490699001973],"type":"Point"}
}