{
  "type": "Feature",
  "properties": {
    "iso:country": "GB",
    "wof:name": "SG2 0QW",
    "wof:placetype": "postalcode"
  },
  "geometry": {"coordinates":[-0.168124,51.904907],"type":"Point"}
}
