{
  "type": "Feature",
  "properties": {
    "iso:country":"GB",
    "wof:name":"TR27 5ET",
    "wof:placetype":"postalcode"
},
  "geometry": {"coordinates":[-5.36545008667738,50.165532990259],"type":"Point"}
}