{
  "type": "Feature",
  "properties": {
    "date:inception_lower":"1980-01-01",
    "date:inception_upper":"1980-01-31",
    "iso:country":"GB",
    "wof:name":"TN12 6RA",
    "wof:placetype":"postalcode"
},
  "geometry": {"coordinates":[0.357973,51.183195],"type":"Point"}
}