{
  "type": "Feature",
  "properties": {
    "iso:country":"GB",
    "wof:name":"TN12 6RA",
    "wof:placetype":"postalcode"
},
  "geometry": {"coordinates":[0.35797268597534,51.18319460999383],"type":"Point"}
}