{
  "type": "Feature",
  "properties": {
    "iso:country":"GB",
    "wof:name":"LS28 9HX",
    "wof:placetype":"postalcode"
},
  "geometry": {"coordinates":[-1.6594173909052,53.79268521359035],"type":"Point"}
}