{
  "type": "Feature",
  "properties": {
    "iso:country": "GB",
    "wof:name": "LS28 9HX",
    "wof:placetype": "postalcode"
  },
  "geometry": {"coordinates":[-1.659417,53.792685],"type":"Point"}
}
