{
  "type": "Feature",
  "properties": {
    "iso:country":"GB",
    "wof:name":"PO20 1PQ",
    "wof:placetype":"postalcode"
},
  "geometry": {"coordinates":[-0.78015366132203,50.80989447156297],"type":"Point"}
}