{
  "type": "Feature",
  "properties": {
    "date:inception_lower": "1980-01-01",
    "date:inception_upper": "1980-01-01",
    "iso:country": "GB",
    "wof:name": "NG16 6JH",
    "wof:placetype": "postalcode"
  },
  "geometry": {"coordinates":[-1.295675,53.077641],"type":"Point"}
}
