{
  "type": "Feature",
  "properties": {
    "iso:country":"GB",
    "wof:name":"NG16 6JH",
    "wof:placetype":"postalcode"
},
  "geometry": {"coordinates":[-1.29567517893254,53.07764114056788],"type":"Point"}
}