{
  "type": "Feature",
  "properties": {
    "date:inception_lower": "2014-03-01",
    "date:inception_upper": "2014-03-01",
    "iso:country": "GB",
    "wof:name": "IP22 4QB",
    "wof:placetype": "postalcode"
  },
  "geometry": {"coordinates":[1.113387,52.379361],"type":"Point"}
}
