{
  "type": "Feature",
  "properties": {
    "iso:country":"GB",
    "wof:name":"YO24 1JX",
    "wof:placetype":"postalcode"
},
  "geometry": {"coordinates":[-1.10233709056448,53.9333338205803],"type":"Point"}
}