{
  "type": "Feature",
  "properties": {
    "iso:country":"GB",
    "wof:name":"SM6 9BZ",
    "wof:placetype":"postalcode"
},
  "geometry": {"coordinates":[-0.13618761920387,51.35457718684837],"type":"Point"}
}