{
  "type": "Feature",
  "properties": {
    "iso:country": "GB",
    "wof:name": "LL59 5RU",
    "wof:placetype": "postalcode"
  },
  "geometry": {"coordinates":[-4.200469,53.239096],"type":"Point"}
}
