{
  "type": "Feature",
  "properties": {
    "iso:country":"GB",
    "wof:name":"LL59 5RU",
    "wof:placetype":"postalcode"
},
  "geometry": {"coordinates":[-4.20046916422479,53.23909568900827],"type":"Point"}
}