{
  "type": "Feature",
  "properties": {
    "iso:country": "GB",
    "wof:name": "CR2 6AZ",
    "wof:placetype": "postalcode"
  },
  "geometry": {"coordinates":[-0.103052,51.361221],"type":"Point"}
}
