{
  "type": "Feature",
  "properties": {
    "iso:country":"GB",
    "wof:name":"CR2 6AZ",
    "wof:placetype":"postalcode"
},
  "geometry": {"coordinates":[-0.10305245310563,51.3612214981726],"type":"Point"}
}