{
  "type": "Feature",
  "properties": {
    "iso:country":"GB",
    "wof:name":"LE12 8WB",
    "wof:placetype":"postalcode"
},
  "geometry": {"coordinates":[-1.16707700241847,52.74951914451333],"type":"Point"}
}