{
  "type": "Feature",
  "properties": {
    "iso:country": "GB",
    "wof:name": "LE12 8WB",
    "wof:placetype": "postalcode"
  },
  "geometry": {"coordinates":[-1.167077,52.749519],"type":"Point"}
}
