{
  "type": "Feature",
  "properties": {
    "date:inception_lower":"2014-06-01",
    "date:inception_upper":"2014-06-30",
    "iso:country":"GB",
    "wof:name":"LE12 8WB",
    "wof:placetype":"postalcode"
},
  "geometry": {"coordinates":[-1.167077,52.749519],"type":"Point"}
}