{
  "type": "Feature",
  "properties": {
    "date:inception_lower": "2006-10-01",
    "date:inception_upper": "2006-10-01",
    "iso:country": "GB",
    "wof:name": "FY4 5PR",
    "wof:placetype": "postalcode"
  },
  "geometry": {"coordinates":[-2.989209,53.78857],"type":"Point"}
}
