{
  "type": "Feature",
  "properties": {
    "iso:country":"GB",
    "wof:name":"FY4 5PR",
    "wof:placetype":"postalcode"
},
  "geometry": {"coordinates":[-2.9892129534868,53.78855560368383],"type":"Point"}
}