{
  "type": "Feature",
  "properties": {
    "date:inception_lower":"1983-01-01",
    "date:inception_upper":"1983-01-31",
    "iso:country":"GB",
    "wof:name":"MK40 3XD",
    "wof:placetype":"postalcode"
},
  "geometry": {"coordinates":[-0.4637,52.136165],"type":"Point"}
}