{
  "type": "Feature",
  "properties": {
    "iso:country": "GB",
    "wof:name": "PL15 7JN",
    "wof:placetype": "postalcode"
  },
  "geometry": {"coordinates":[-4.434247,50.613494],"type":"Point"}
}
