{
  "type": "Feature",
  "properties": {
    "date:inception_lower":"1980-01-01",
    "date:inception_upper":"1980-01-31",
    "iso:country":"GB",
    "wof:name":"PL15 7JN",
    "wof:placetype":"postalcode"
},
  "geometry": {"coordinates":[-4.434247,50.613494],"type":"Point"}
}