{
  "type": "Feature",
  "properties": {
    "iso:country":"GB",
    "wof:name":"PL15 7JN",
    "wof:placetype":"postalcode"
},
  "geometry": {"coordinates":[-4.43424656503348,50.61349362418274],"type":"Point"}
}