{
  "type": "Feature",
  "properties": {
    "iso:country":"GB",
    "wof:name":"CM1 2AR",
    "wof:placetype":"postalcode"
},
  "geometry": {"coordinates":[0.46381471990239,51.74397102047426],"type":"Point"}
}