{
  "type": "Feature",
  "properties": {
    "iso:country": "GB",
    "wof:name": "SK9 1RA",
    "wof:placetype": "postalcode"
  },
  "geometry": {"coordinates":[-2.234671,53.315171],"type":"Point"}
}
