{
  "type": "Feature",
  "properties": {
    "date:inception_lower":"1994-12-01",
    "date:inception_upper":"1994-12-31",
    "iso:country":"GB",
    "wof:name":"SK9 1RA",
    "wof:placetype":"postalcode"
},
  "geometry": {"coordinates":[-2.234671,53.315171],"type":"Point"}
}