{
  "type": "Feature",
  "properties": {
    "iso:country":"GB",
    "wof:name":"SK9 1RA",
    "wof:placetype":"postalcode"
},
  "geometry": {"coordinates":[-2.23694234732116,53.31609277064305],"type":"Point"}
}