{
  "type": "Feature",
  "properties": {
    "iso:country":"GB",
    "wof:name":"DN1 2RZ",
    "wof:placetype":"postalcode"
},
  "geometry": {"coordinates":[-1.12644772378351,53.52964620502185],"type":"Point"}
}