{
  "type": "Feature",
  "properties": {
    "iso:country":"GB",
    "wof:name":"TQ12 1AQ",
    "wof:placetype":"postalcode"
},
  "geometry": {"coordinates":[-3.60863699623582,50.52883274764486],"type":"Point"}
}