{
  "type": "Feature",
  "properties": {
    "iso:country":"GB",
    "wof:name":"ME14 5QN",
    "wof:placetype":"postalcode"
},
  "geometry": {"coordinates":[0.53937727233574,51.28172743614],"type":"Point"}
}