{
  "type": "Feature",
  "properties": {
    "date:inception_lower": "1980-01-01",
    "date:inception_upper": "1980-01-01",
    "iso:country": "GB",
    "wof:name": "MK41 7AP",
    "wof:placetype": "postalcode"
  },
  "geometry": {"coordinates":[-0.461044,52.159814],"type":"Point"}
}
