{
  "type": "Feature",
  "properties": {
    "iso:country":"GB",
    "wof:name":"MK41 7AP",
    "wof:placetype":"postalcode"
},
  "geometry": {"coordinates":[-0.46109274253519,52.15984646267227],"type":"Point"}
}