{
  "type": "Feature",
  "properties": {
    "date:inception_lower": "2017-08-01",
    "date:inception_upper": "2017-08-01",
    "iso:country": "GB",
    "wof:name": "DE5 9TS",
    "wof:placetype": "postalcode"
  },
  "geometry": {"coordinates":[-1.387331,53.043675],"type":"Point"}
}
