{
  "type": "Feature",
  "properties": {
    "iso:country": "GB",
    "wof:name": "DE5 9TS",
    "wof:placetype": "postalcode"
  },
  "geometry": {"coordinates":[-1.387331,53.043675],"type":"Point"}
}
