{
  "type": "Feature",
  "properties": {
    "iso:country":"GB",
    "wof:name":"EN9 1LT",
    "wof:placetype":"postalcode"
},
  "geometry": {"coordinates":[0.01006008355647,51.68773852649749],"type":"Point"}
}