{
  "type": "Feature",
  "properties": {
    "iso:country": "GB",
    "wof:name": "EN9 1LT",
    "wof:placetype": "postalcode"
  },
  "geometry": {"coordinates":[0.01006,51.687739],"type":"Point"}
}
