{
  "type": "Feature",
  "properties": {
    "iso:country": "GB",
    "wof:name": "DH1 2NU",
    "wof:placetype": "postalcode"
  },
  "geometry": {"coordinates":[-1.546875,54.760284],"type":"Point"}
}
