{
  "type": "Feature",
  "properties": {
    "iso:country":"GB",
    "wof:name":"DH1 2NU",
    "wof:placetype":"postalcode"
},
  "geometry": {"coordinates":[-1.54687535433077,54.76028389607364],"type":"Point"}
}