{
  "type": "Feature",
  "properties": {
    "iso:country":"GB",
    "wof:name":"WN2 4QF",
    "wof:placetype":"postalcode"
},
  "geometry": {"coordinates":[-2.55892983824068,53.5271502021586],"type":"Point"}
}