{
  "type": "Feature",
  "properties": {
    "iso:country": "GB",
    "wof:name": "WN2 4QF",
    "wof:placetype": "postalcode"
  },
  "geometry": {"coordinates":[-2.55893,53.52715],"type":"Point"}
}
