{
  "type": "Feature",
  "properties": {
    "iso:country": "GB",
    "wof:name": "ML2 7PP",
    "wof:placetype": "postalcode"
  },
  "geometry": {"coordinates":[-3.93338,55.77727],"type":"Point"}
}
