{
  "type": "Feature",
  "properties": {
    "date:inception_lower": "1980-01-01",
    "date:inception_upper": "1980-01-01",
    "iso:country": "GB",
    "wof:name": "DH2 2NW",
    "wof:placetype": "postalcode"
  },
  "geometry": {"coordinates":[-1.610728,54.857209],"type":"Point"}
}
