{
  "type": "Feature",
  "properties": {
    "iso:country": "GB",
    "wof:name": "DH2 2NW",
    "wof:placetype": "postalcode"
  },
  "geometry": {"coordinates":[-1.610728,54.857209],"type":"Point"}
}
