{
  "type": "Feature",
  "properties": {
    "iso:country":"GB",
    "wof:name":"DH2 2NW",
    "wof:placetype":"postalcode"
},
  "geometry": {"coordinates":[-1.61071551890432,54.85720025573747],"type":"Point"}
}