{
  "type": "Feature",
  "properties": {
    "iso:country":"GB",
    "wof:name":"DN12 3EA",
    "wof:placetype":"postalcode"
},
  "geometry": {"coordinates":[-1.22489779352994,53.48592983627621],"type":"Point"}
}