{
  "type": "Feature",
  "properties": {
    "iso:country":"GB",
    "wof:name":"SK6 5JW",
    "wof:placetype":"postalcode"
},
  "geometry": {"coordinates":[-2.05009232540463,53.41604656474679],"type":"Point"}
}