{
  "type": "Feature",
  "properties": {
    "iso:country": "GB",
    "wof:name": "RG25 2HN",
    "wof:placetype": "postalcode"
  },
  "geometry": {"coordinates":[-1.124485,51.205938],"type":"Point"}
}
