{
  "type": "Feature",
  "properties": {
    "iso:country":"GB",
    "wof:name":"RG25 2HN",
    "wof:placetype":"postalcode"
},
  "geometry": {"coordinates":[-1.12448464257103,51.20593751599394],"type":"Point"}
}