{
  "type": "Feature",
  "properties": {
    "iso:country":"GB",
    "wof:name":"SA10 6EB",
    "wof:placetype":"postalcode"
},
  "geometry": {"coordinates":[-3.85805082895326,51.65688977748297],"type":"Point"}
}