{
  "type": "Feature",
  "properties": {
    "iso:country": "GB",
    "wof:name": "SA10 6EB",
    "wof:placetype": "postalcode"
  },
  "geometry": {"coordinates":[-3.858051,51.65689],"type":"Point"}
}
