{
  "type": "Feature",
  "properties": {
    "date:inception_lower": "1980-01-01",
    "date:inception_upper": "1980-01-01",
    "iso:country": "GB",
    "wof:name": "SA10 6EB",
    "wof:placetype": "postalcode"
  },
  "geometry": {"coordinates":[-3.85788,51.656925],"type":"Point"}
}
