{
  "type": "Feature",
  "properties": {
    "iso:country": "GB",
    "wof:name": "CA18 1RG",
    "wof:placetype": "postalcode"
  },
  "geometry": {"coordinates":[-3.389038,54.360222],"type":"Point"}
}
