{
  "type": "Feature",
  "properties": {
    "iso:country":"GB",
    "wof:name":"CA18 1RG",
    "wof:placetype":"postalcode"
},
  "geometry": {"coordinates":[-3.3890384253849,54.36022219879273],"type":"Point"}
}