{
  "type": "Feature",
  "properties": {
    "date:inception_lower": "1980-01-01",
    "date:inception_upper": "1980-01-01",
    "iso:country": "GB",
    "wof:name": "CA18 1RG",
    "wof:placetype": "postalcode"
  },
  "geometry": {"coordinates":[-3.389038,54.360222],"type":"Point"}
}
