{
  "type": "Feature",
  "properties": {
    "iso:country": "GB",
    "wof:name": "SE19 3HN",
    "wof:placetype": "postalcode"
  },
  "geometry": {"coordinates":[-0.105632,51.418079],"type":"Point"}
}
