{
  "type": "Feature",
  "properties": {
    "iso:country":"GB",
    "wof:name":"KA12 9PA",
    "wof:placetype":"postalcode"
},
  "geometry": {"coordinates":[-4.65923688293123,55.6308592203065],"type":"Point"}
}