{
  "type": "Feature",
  "properties": {
    "date:inception_lower":"1980-01-01",
    "date:inception_upper":"1980-01-31",
    "iso:country":"GB",
    "wof:name":"LS9 0DG",
    "wof:placetype":"postalcode"
},
  "geometry": {"coordinates":[-1.519569,53.788288],"type":"Point"}
}