{
  "type": "Feature",
  "properties": {
    "iso:country":"GB",
    "wof:name":"DA1 2HZ",
    "wof:placetype":"postalcode"
},
  "geometry": {"coordinates":[0.20910226020058,51.4482800849432],"type":"Point"}
}