{
  "type": "Feature",
  "properties": {
    "iso:country":"GB",
    "wof:name":"NW2 6JR",
    "wof:placetype":"postalcode"
},
  "geometry": {"coordinates":[-0.22311294358031,51.56347463579282],"type":"Point"}
}