{
  "type": "Feature",
  "properties": {
    "iso:country":"GB",
    "wof:name":"WA12 9DJ",
    "wof:placetype":"postalcode"
},
  "geometry": {"coordinates":[-2.64296371728882,53.45412688296593],"type":"Point"}
}