{
  "type": "Feature",
  "properties": {
    "iso:country": "GB",
    "wof:name": "PR6 9NZ",
    "wof:placetype": "postalcode"
  },
  "geometry": {"coordinates":[-2.594321,53.61999],"type":"Point"}
}
