{
  "type": "Feature",
  "properties": {
    "iso:country":"GB",
    "wof:name":"PR6 9NZ",
    "wof:placetype":"postalcode"
},
  "geometry": {"coordinates":[-2.59426173457949,53.61993816140411],"type":"Point"}
}