{
  "type": "Feature",
  "properties": {
    "iso:country":"GB",
    "wof:name":"UB8 3QH",
    "wof:placetype":"postalcode"
},
  "geometry": {"coordinates":[-0.45690252833867,51.52281925381159],"type":"Point"}
}