{
  "type": "Feature",
  "properties": {
    "iso:country":"GB",
    "wof:name":"TQ7 2EF",
    "wof:placetype":"postalcode"
},
  "geometry": {"coordinates":[-3.66819387304365,50.26355615304259],"type":"Point"}
}