{
  "type": "Feature",
  "properties": {
    "date:inception_lower":"1980-01-01",
    "date:inception_upper":"1980-01-31",
    "iso:country":"GB",
    "wof:name":"PO9 1RU",
    "wof:placetype":"postalcode"
},
  "geometry": {"coordinates":[-0.982429,50.842976],"type":"Point"}
}