{
  "type": "Feature",
  "properties": {
    "iso:country":"GB",
    "wof:name":"PO9 1RU",
    "wof:placetype":"postalcode"
},
  "geometry": {"coordinates":[-0.98242882344847,50.84297571904602],"type":"Point"}
}