{
  "type": "Feature",
  "properties": {
    "iso:country":"GB",
    "wof:name":"NR11 8AA",
    "wof:placetype":"postalcode"
},
  "geometry": {"coordinates":[1.24501923208358,52.90998626785422],"type":"Point"}
}