{
  "type": "Feature",
  "properties": {
    "iso:country":"GB",
    "wof:name":"TF9 1HN",
    "wof:placetype":"postalcode"
},
  "geometry": {"coordinates":[-2.47130363061971,52.90826325359099],"type":"Point"}
}