{
  "type": "Feature",
  "properties": {
    "iso:country": "GB",
    "wof:name": "TF9 1HN",
    "wof:placetype": "postalcode"
  },
  "geometry": {"coordinates":[-2.471168,52.908207],"type":"Point"}
}
