{
  "type": "Feature",
  "properties": {
    "date:inception_lower": "1980-01-01",
    "date:inception_upper": "1980-01-01",
    "iso:country": "GB",
    "wof:name": "CM2 9JW",
    "wof:placetype": "postalcode"
  },
  "geometry": {"coordinates":[0.479638,51.716533],"type":"Point"}
}
