{
  "type": "Feature",
  "properties": {
    "iso:country":"GB",
    "wof:name":"CM2 9JW",
    "wof:placetype":"postalcode"
},
  "geometry": {"coordinates":[0.4796383182996,51.7165329988154],"type":"Point"}
}