{
  "type": "Feature",
  "properties": {
    "iso:country":"GB",
    "wof:name":"CM23 3DT",
    "wof:placetype":"postalcode"
},
  "geometry": {"coordinates":[0.16877058218156,51.85789563160502],"type":"Point"}
}