{
  "type": "Feature",
  "properties": {
    "iso:country": "GB",
    "wof:name": "CM23 3DT",
    "wof:placetype": "postalcode"
  },
  "geometry": {"coordinates":[0.168797,51.857903],"type":"Point"}
}
