{
  "type": "Feature",
  "properties": {
    "iso:country":"GB",
    "wof:name":"HD9 6GJ",
    "wof:placetype":"postalcode"
},
  "geometry": {"coordinates":[-1.80191164993706,53.60201630038429],"type":"Point"}
}