{
  "type": "Feature",
  "properties": {
    "date:inception_lower":"2001-06-01",
    "date:inception_upper":"2001-06-30",
    "iso:country":"GB",
    "wof:name":"HD9 6GJ",
    "wof:placetype":"postalcode"
},
  "geometry": {"coordinates":[-1.801912,53.602016],"type":"Point"}
}