{
  "type": "Feature",
  "properties": {
    "iso:country": "GB",
    "wof:name": "HD9 6GJ",
    "wof:placetype": "postalcode"
  },
  "geometry": {"coordinates":[-1.801912,53.602016],"type":"Point"}
}
