{
  "type": "Feature",
  "properties": {
    "date:inception_lower": "1980-01-01",
    "date:inception_upper": "1980-01-01",
    "iso:country": "GB",
    "wof:name": "BD7 3AA",
    "wof:placetype": "postalcode"
  },
  "geometry": {"coordinates":[-1.773794,53.787751],"type":"Point"}
}
