{
  "type": "Feature",
  "properties": {
    "iso:country":"GB",
    "wof:name":"BD7 3AA",
    "wof:placetype":"postalcode"
},
  "geometry": {"coordinates":[-1.77379422978369,53.78775119762078],"type":"Point"}
}