{
  "type": "Feature",
  "properties": {
    "iso:country": "GB",
    "wof:name": "AB33 8EZ",
    "wof:placetype": "postalcode"
  },
  "geometry": {"coordinates":[-2.713459,57.23515],"type":"Point"}
}
