{
  "type": "Feature",
  "properties": {
    "iso:country":"GB",
    "wof:name":"BA22 7BR",
    "wof:placetype":"postalcode"
},
  "geometry": {"coordinates":[-2.57099981567725,51.0631420915999],"type":"Point"}
}