{
  "type": "Feature",
  "properties": {
    "iso:country": "GB",
    "wof:name": "BA22 7BR",
    "wof:placetype": "postalcode"
  },
  "geometry": {"coordinates":[-2.571,51.063142],"type":"Point"}
}
