{
  "type": "Feature",
  "properties": {
    "date:inception_lower": "2007-07-01",
    "date:inception_upper": "2007-07-01",
    "iso:country": "GB",
    "wof:name": "BA22 7BR",
    "wof:placetype": "postalcode"
  },
  "geometry": {"coordinates":[-2.571,51.063142],"type":"Point"}
}
