{
  "type": "Feature",
  "properties": {
    "iso:country": "GB",
    "wof:name": "HP17 8FQ",
    "wof:placetype": "postalcode"
  },
  "geometry": {"coordinates":[-0.920299,51.769815],"type":"Point"}
}
