{
  "type": "Feature",
  "properties": {
    "date:inception_lower":"2018-06-01",
    "date:inception_upper":"2018-06-30",
    "iso:country":"GB",
    "wof:name":"RG27 9FL",
    "wof:placetype":"postalcode"
},
  "geometry": {"coordinates":[-0.9599,51.290061],"type":"Point"}
}