{
  "type": "Feature",
  "properties": {
    "iso:country":"GB",
    "wof:name":"AB42 2YH",
    "wof:placetype":"postalcode"
},
  "geometry": {"coordinates":[-1.79847043584439,57.49787910991193],"type":"Point"}
}