{
  "type": "Feature",
  "properties": {
    "iso:country":"GB",
    "wof:name":"BS8 3UU",
    "wof:placetype":"postalcode"
},
  "geometry": {"coordinates":[-2.69157679531266,51.43885037874519],"type":"Point"}
}