{
  "type": "Feature",
  "properties": {
    "iso:country":"GB",
    "wof:name":"ST18 9DT",
    "wof:placetype":"postalcode"
},
  "geometry": {"coordinates":[-2.17797096129068,52.76011059211627],"type":"Point"}
}