{
  "type": "Feature",
  "properties": {
    "iso:country":"GB",
    "wof:name":"TF10 7PT",
    "wof:placetype":"postalcode"
},
  "geometry": {"coordinates":[-2.38490597692539,52.76800649398503],"type":"Point"}
}