{
  "type": "Feature",
  "properties": {
    "iso:country":"GB",
    "wof:name":"WA11 9BL",
    "wof:placetype":"postalcode"
},
  "geometry": {"coordinates":[-2.7093714069324,53.46115757690824],"type":"Point"}
}