{
  "type": "Feature",
  "properties": {
    "iso:country": "GB",
    "wof:name": "TN6 1LB",
    "wof:placetype": "postalcode"
  },
  "geometry": {"coordinates":[0.161985,51.04905],"type":"Point"}
}
