{
  "type": "Feature",
  "properties": {
    "date:inception_lower": "1980-01-01",
    "date:inception_upper": "1980-01-01",
    "iso:country": "GB",
    "wof:name": "TN6 1LB",
    "wof:placetype": "postalcode"
  },
  "geometry": {"coordinates":[0.161955,51.04903],"type":"Point"}
}
