{
  "type": "Feature",
  "properties": {
    "date:inception_lower":"2016-02-01",
    "date:inception_upper":"2016-02-29",
    "iso:country":"GB",
    "wof:name":"OL10 2QT",
    "wof:placetype":"postalcode"
},
  "geometry": {"coordinates":[-2.213005,53.581917],"type":"Point"}
}