{
  "type": "Feature",
  "properties": {
    "iso:country": "GB",
    "wof:name": "OL10 2QT",
    "wof:placetype": "postalcode"
  },
  "geometry": {"coordinates":[-2.213005,53.581917],"type":"Point"}
}
