{
  "type": "Feature",
  "properties": {
    "iso:country":"GB",
    "wof:name":"OL10 2QT",
    "wof:placetype":"postalcode"
},
  "geometry": {"coordinates":[-2.21764237640273,53.57857592152808],"type":"Point"}
}