{
  "type": "Feature",
  "properties": {
    "iso:country": "GB",
    "wof:name": "NG22 8BQ",
    "wof:placetype": "postalcode"
  },
  "geometry": {"coordinates":[-1.015656,53.094955],"type":"Point"}
}
