{
  "type": "Feature",
  "properties": {
    "iso:country":"GB",
    "wof:name":"NG22 8BQ",
    "wof:placetype":"postalcode"
},
  "geometry": {"coordinates":[-1.01565593412916,53.09495526439058],"type":"Point"}
}