{
  "type": "Feature",
  "properties": {
    "iso:country":"GB",
    "wof:name":"TW2 6HS",
    "wof:placetype":"postalcode"
},
  "geometry": {"coordinates":[-0.3614546785075,51.4479228618795],"type":"Point"}
}