{
  "type": "Feature",
  "properties": {
    "iso:country":"GB",
    "wof:name":"CM2 9NS",
    "wof:placetype":"postalcode"
},
  "geometry": {"coordinates":[0.47361085195347,51.71406109875647],"type":"Point"}
}