{
  "type": "Feature",
  "properties": {
    "date:inception_lower": "1981-06-01",
    "date:inception_upper": "1981-06-01",
    "iso:country": "GB",
    "wof:name": "EX1 1DP",
    "wof:placetype": "postalcode"
  },
  "geometry": {"coordinates":[-3.532642,50.72051],"type":"Point"}
}
