{
  "type": "Feature",
  "properties": {
    "iso:country": "GB",
    "wof:name": "IP28 7AB",
    "wof:placetype": "postalcode"
  },
  "geometry": {"coordinates":[0.511034,52.346536],"type":"Point"}
}
