{
  "type": "Feature",
  "properties": {
    "date:inception_lower": "1997-12-01",
    "date:inception_upper": "1997-12-01",
    "iso:country": "GB",
    "wof:name": "BS34 5DW",
    "wof:placetype": "postalcode"
  },
  "geometry": {"coordinates":[-2.586308,51.528765],"type":"Point"}
}
