{
  "type": "Feature",
  "properties": {
    "iso:country": "GB",
    "wof:name": "BS34 5DW",
    "wof:placetype": "postalcode"
  },
  "geometry": {"coordinates":[-2.586308,51.528765],"type":"Point"}
}
