{
  "type": "Feature",
  "properties": {
    "iso:country":"GB",
    "wof:name":"SE1 2DL",
    "wof:placetype":"postalcode"
},
  "geometry": {"coordinates":[-0.0716294895051,51.49910610044033],"type":"Point"}
}