{
  "type": "Feature",
  "properties": {
    "iso:country": "GB",
    "wof:name": "CW12 1GQ",
    "wof:placetype": "postalcode"
  },
  "geometry": {"coordinates":[-2.204798,53.176781],"type":"Point"}
}
