{
  "type": "Feature",
  "properties": {
    "iso:country": "GB",
    "wof:name": "IP9 2TE",
    "wof:placetype": "postalcode"
  },
  "geometry": {"coordinates":[1.116487,51.969215],"type":"Point"}
}
