{
  "type": "Feature",
  "properties": {
    "date:inception_lower": "1980-01-01",
    "date:inception_upper": "1980-01-01",
    "iso:country": "GB",
    "wof:name": "IP9 2TE",
    "wof:placetype": "postalcode"
  },
  "geometry": {"coordinates":[1.116487,51.969215],"type":"Point"}
}
