{
  "type": "Feature",
  "properties": {
    "date:inception_lower": "2020-04-01",
    "date:inception_upper": "2020-04-01",
    "iso:country": "GB",
    "wof:name": "HP14 4DQ",
    "wof:placetype": "postalcode"
  },
  "geometry": {"coordinates":[-0.786164,51.671702],"type":"Point"}
}
