{
  "type": "Feature",
  "properties": {
    "iso:country":"GB",
    "wof:name":"SG4 7JD",
    "wof:placetype":"postalcode"
},
  "geometry": {"coordinates":[-0.24179205738387,51.93258355396885],"type":"Point"}
}