{
  "type": "Feature",
  "properties": {
    "date:inception_lower": "1980-01-01",
    "date:inception_upper": "1980-01-01",
    "iso:country": "GB",
    "wof:name": "DA8 3NN",
    "wof:placetype": "postalcode"
  },
  "geometry": {"coordinates":[0.165517,51.46975],"type":"Point"}
}
