{
  "type": "Feature",
  "properties": {
    "iso:country":"GB",
    "wof:name":"DA8 3NN",
    "wof:placetype":"postalcode"
},
  "geometry": {"coordinates":[0.16551694168155,51.469750284609],"type":"Point"}
}