{
  "type": "Feature",
  "properties": {
    "iso:country": "GB",
    "wof:name": "DA8 3NN",
    "wof:placetype": "postalcode"
  },
  "geometry": {"coordinates":[0.165517,51.46975],"type":"Point"}
}
