{
  "type": "Feature",
  "properties": {
    "date:inception_lower":"1985-04-01",
    "date:inception_upper":"1985-04-30",
    "iso:country":"GB",
    "wof:name":"HR9 7BW",
    "wof:placetype":"postalcode"
},
  "geometry": {"coordinates":[-2.574292,51.916445],"type":"Point"}
}