{
  "type": "Feature",
  "properties": {
    "iso:country":"GB",
    "wof:name":"HR9 7BW",
    "wof:placetype":"postalcode"
},
  "geometry": {"coordinates":[-2.5742916372277,51.91644497983339],"type":"Point"}
}