{
  "type": "Feature",
  "properties": {
    "iso:country":"GB",
    "wof:name":"WA15 7DQ",
    "wof:placetype":"postalcode"
},
  "geometry": {"coordinates":[-2.30615490235807,53.39570945152151],"type":"Point"}
}