{
  "type": "Feature",
  "properties": {
    "iso:country": "GB",
    "wof:name": "PE31 7RX",
    "wof:placetype": "postalcode"
  },
  "geometry": {"coordinates":[0.504074,52.877563],"type":"Point"}
}
