{
  "type": "Feature",
  "properties": {
    "date:inception_lower": "2005-03-01",
    "date:inception_upper": "2005-03-01",
    "iso:country": "GB",
    "wof:name": "PE31 7RX",
    "wof:placetype": "postalcode"
  },
  "geometry": {"coordinates":[0.504074,52.877563],"type":"Point"}
}
