{
  "type": "Feature",
  "properties": {
    "iso:country":"GB",
    "wof:name":"PE31 7RX",
    "wof:placetype":"postalcode"
},
  "geometry": {"coordinates":[0.5040742135082,52.87756259360165],"type":"Point"}
}