{
  "type": "Feature",
  "properties": {
    "iso:country":"GB",
    "wof:name":"LL30 2YJ",
    "wof:placetype":"postalcode"
},
  "geometry": {"coordinates":[-3.83847215464937,53.31707963635152],"type":"Point"}
}