{
  "type": "Feature",
  "properties": {
    "iso:country":"GB",
    "wof:name":"TA2 7BE",
    "wof:placetype":"postalcode"
},
  "geometry": {"coordinates":[-3.1019441630653,51.03717474148461],"type":"Point"}
}