{
  "type": "Feature",
  "properties": {
    "iso:country":"GB",
    "wof:name":"PA5 8HQ",
    "wof:placetype":"postalcode"
},
  "geometry": {"coordinates":[-4.50203161827912,55.83581845503377],"type":"Point"}
}