{
  "type": "Feature",
  "properties": {
    "iso:country":"GB",
    "wof:name":"B16 9DB",
    "wof:placetype":"postalcode"
},
  "geometry": {"coordinates":[-1.93371985372113,52.47508026331076],"type":"Point"}
}