{
  "type": "Feature",
  "properties": {
    "date:inception_lower": "1980-01-01",
    "date:inception_upper": "1980-01-01",
    "iso:country": "GB",
    "wof:name": "N14 6EF",
    "wof:placetype": "postalcode"
  },
  "geometry": {"coordinates":[-0.125186,51.626013],"type":"Point"}
}
