{
  "type": "Feature",
  "properties": {
    "iso:country":"GB",
    "wof:name":"NW1 5QH",
    "wof:placetype":"postalcode"
},
  "geometry": {"coordinates":[-0.16333004598302,51.52070328275307],"type":"Point"}
}