{
  "type": "Feature",
  "properties": {
    "iso:country":"GB",
    "wof:name":"WA2 9LW",
    "wof:placetype":"postalcode"
},
  "geometry": {"coordinates":[-2.57649892036706,53.41122187243558],"type":"Point"}
}