{
  "type": "Feature",
  "properties": {
    "iso:country": "GB",
    "wof:name": "NE1 5BW",
    "wof:placetype": "postalcode"
  },
  "geometry": {"coordinates":[-1.619685,54.970115],"type":"Point"}
}
