{
  "type": "Feature",
  "properties": {
    "iso:country":"GB",
    "wof:name":"NN16 8BH",
    "wof:placetype":"postalcode"
},
  "geometry": {"coordinates":[-0.73018364190767,52.40113563607071],"type":"Point"}
}