{
  "type": "Feature",
  "properties": {
    "iso:country": "GB",
    "wof:name": "WR5 2AN",
    "wof:placetype": "postalcode"
  },
  "geometry": {"coordinates":[-2.214806,52.183372],"type":"Point"}
}
