{
  "type": "Feature",
  "properties": {
    "date:inception_lower": "1980-01-01",
    "date:inception_upper": "1980-01-01",
    "iso:country": "GB",
    "wof:name": "SA38 9LW",
    "wof:placetype": "postalcode"
  },
  "geometry": {"coordinates":[-4.473385,52.025793],"type":"Point"}
}
