{
  "type": "Feature",
  "properties": {
    "iso:country":"GB",
    "wof:name":"SA38 9LW",
    "wof:placetype":"postalcode"
},
  "geometry": {"coordinates":[-4.47338484930937,52.02579288710164],"type":"Point"}
}