{
  "type": "Feature",
  "properties": {
    "iso:country": "GB",
    "wof:name": "TS10 4QP",
    "wof:placetype": "postalcode"
  },
  "geometry": {"coordinates":[-1.081401,54.59408],"type":"Point"}
}
