{
  "type": "Feature",
  "properties": {
    "iso:country":"GB",
    "wof:name":"TS10 4QP",
    "wof:placetype":"postalcode"
},
  "geometry": {"coordinates":[-1.081400761186,54.59408024150171],"type":"Point"}
}