{
  "type": "Feature",
  "properties": {
    "date:inception_lower": "1980-01-01",
    "date:inception_upper": "1980-01-01",
    "iso:country": "GB",
    "wof:name": "DN14 7YP",
    "wof:placetype": "postalcode"
  },
  "geometry": {"coordinates":[-0.733094,53.70807],"type":"Point"}
}
