{
  "type": "Feature",
  "properties": {
    "iso:country":"GB",
    "wof:name":"DN14 7YP",
    "wof:placetype":"postalcode"
},
  "geometry": {"coordinates":[-0.73309434091189,53.70807000546193],"type":"Point"}
}