{
  "type": "Feature",
  "properties": {
    "iso:country":"GB",
    "wof:name":"BD19 5AJ",
    "wof:placetype":"postalcode"
},
  "geometry": {"coordinates":[-1.71298629225384,53.72381502642529],"type":"Point"}
}