{
  "type": "Feature",
  "properties": {
    "iso:country":"GB",
    "wof:name":"SK3 0JH",
    "wof:placetype":"postalcode"
},
  "geometry": {"coordinates":[-2.18658327880413,53.40205966056988],"type":"Point"}
}