{
  "type": "Feature",
  "properties": {
    "date:inception_lower": "1995-07-01",
    "date:inception_upper": "1995-07-01",
    "iso:country": "GB",
    "wof:name": "CF72 8ES",
    "wof:placetype": "postalcode"
  },
  "geometry": {"coordinates":[-3.454948,51.528923],"type":"Point"}
}
