{
  "type": "Feature",
  "properties": {
    "iso:country":"GB",
    "wof:name":"CF72 8ES",
    "wof:placetype":"postalcode"
},
  "geometry": {"coordinates":[-3.37663730138017,51.54075526520844],"type":"Point"}
}