{
  "type": "Feature",
  "properties": {
    "iso:country":"GB",
    "wof:name":"PH21 1JP",
    "wof:placetype":"postalcode"
},
  "geometry": {"coordinates":[-4.0471130717711,57.08382078609588],"type":"Point"}
}