{
  "type": "Feature",
  "properties": {
    "iso:country": "GB",
    "wof:name": "N9 9UE",
    "wof:placetype": "postalcode"
  },
  "geometry": {"coordinates":[-0.079709,51.625215],"type":"Point"}
}
