{
  "type": "Feature",
  "properties": {
    "date:inception_lower": "2002-12-01",
    "date:inception_upper": "2002-12-01",
    "iso:country": "GB",
    "wof:name": "KA9 2PU",
    "wof:placetype": "postalcode"
  },
  "geometry": {"coordinates":[-4.598738,55.517372],"type":"Point"}
}
