{
  "type": "Feature",
  "properties": {
    "iso:country":"GB",
    "wof:name":"KA9 2PU",
    "wof:placetype":"postalcode"
},
  "geometry": {"coordinates":[-4.59873792690033,55.51737163246801],"type":"Point"}
}