{
  "type": "Feature",
  "properties": {
    "iso:country": "GB",
    "wof:name": "RG20 7JW",
    "wof:placetype": "postalcode"
  },
  "geometry": {"coordinates":[-1.343211,51.493219],"type":"Point"}
}
