{
  "type": "Feature",
  "properties": {
    "iso:country":"GB",
    "wof:name":"RG20 7JW",
    "wof:placetype":"postalcode"
},
  "geometry": {"coordinates":[-1.34321145250068,51.49321916762957],"type":"Point"}
}