{
  "type": "Feature",
  "properties": {
    "iso:country":"GB",
    "wof:name":"LE4 4LB",
    "wof:placetype":"postalcode"
},
  "geometry": {"coordinates":[-1.1229399954566,52.68467177482243],"type":"Point"}
}