{
  "type": "Feature",
  "properties": {
    "iso:country":"GB",
    "wof:name":"KA5 6EN",
    "wof:placetype":"postalcode"
},
  "geometry": {"coordinates":[-4.33797250040566,55.5073675471403],"type":"Point"}
}