{
  "type": "Feature",
  "properties": {
    "date:inception_lower": "2002-07-01",
    "date:inception_upper": "2002-07-01",
    "iso:country": "GB",
    "wof:name": "KA5 6EN",
    "wof:placetype": "postalcode"
  },
  "geometry": {"coordinates":[-4.337972,55.507368],"type":"Point"}
}
