{
  "type": "Feature",
  "properties": {
    "date:inception_lower": "2023-09-01",
    "date:inception_upper": "2023-09-01",
    "iso:country": "GB",
    "wof:name": "HP22 7EL",
    "wof:placetype": "postalcode"
  },
  "geometry": {"coordinates":[-0.76866,51.82313],"type":"Point"}
}
