{
  "type": "Feature",
  "properties": {
    "date:inception_lower": "1980-01-01",
    "date:inception_upper": "1980-01-01",
    "iso:country": "GB",
    "wof:name": "CM1 3RE",
    "wof:placetype": "postalcode"
  },
  "geometry": {"coordinates":[0.390679,51.712061],"type":"Point"}
}
