{
  "type": "Feature",
  "properties": {
    "date:inception_lower":"1980-01-01",
    "date:inception_upper":"1980-01-31",
    "iso:country":"GB",
    "wof:name":"CM1 3RE",
    "wof:placetype":"postalcode"
},
  "geometry": {"coordinates":[0.3915,51.711931],"type":"Point"}
}