{
  "type": "Feature",
  "properties": {
    "iso:country":"GB",
    "wof:name":"NP25 3HQ",
    "wof:placetype":"postalcode"
},
  "geometry": {"coordinates":[-2.71280534058837,51.82081369111005],"type":"Point"}
}