{
  "type": "Feature",
  "properties": {
    "iso:country":"GB",
    "wof:name":"SW11 2JN",
    "wof:placetype":"postalcode"
},
  "geometry": {"coordinates":[-0.16328566323639,51.46661265339814],"type":"Point"}
}