{
  "type": "Feature",
  "properties": {
    "iso:country": "GB",
    "wof:name": "B38 8BJ",
    "wof:placetype": "postalcode"
  },
  "geometry": {"coordinates":[-1.934734,52.406073],"type":"Point"}
}
