{
  "type": "Feature",
  "properties": {
    "date:inception_lower": "2014-12-01",
    "date:inception_upper": "2014-12-01",
    "iso:country": "GB",
    "wof:name": "PR4 4ZR",
    "wof:placetype": "postalcode"
  },
  "geometry": {"coordinates":[-2.748494,53.721351],"type":"Point"}
}
