{
  "type": "Feature",
  "properties": {
    "iso:country":"GB",
    "wof:name":"PR4 4ZR",
    "wof:placetype":"postalcode"
},
  "geometry": {"coordinates":[-2.74849370363501,53.7213514393847],"type":"Point"}
}