{
  "type": "Feature",
  "properties": {
    "iso:country": "GB",
    "wof:name": "GU31 5LE",
    "wof:placetype": "postalcode"
  },
  "geometry": {"coordinates":[-0.879795,50.968636],"type":"Point"}
}
