{
  "type": "Feature",
  "properties": {
    "iso:country":"GB",
    "wof:name":"HR2 7PT",
    "wof:placetype":"postalcode"
},
  "geometry": {"coordinates":[-2.72441929459223,52.03705656218624],"type":"Point"}
}