{
  "type": "Feature",
  "properties": {
    "date:inception_lower": "1980-01-01",
    "date:inception_upper": "1980-01-01",
    "iso:country": "GB",
    "wof:name": "HR2 7PT",
    "wof:placetype": "postalcode"
  },
  "geometry": {"coordinates":[-2.724419,52.037057],"type":"Point"}
}
