{
  "type": "Feature",
  "properties": {
    "iso:country":"GB",
    "wof:name":"HA3 6JA",
    "wof:placetype":"postalcode"
},
  "geometry": {"coordinates":[-0.34612330849549,51.60561175947468],"type":"Point"}
}