{
  "type": "Feature",
  "properties": {
    "iso:country":"GB",
    "wof:name":"SE19 2TD",
    "wof:placetype":"postalcode"
},
  "geometry": {"coordinates":[-0.08032573007459,51.41725377440193],"type":"Point"}
}