{
  "type": "Feature",
  "properties": {
    "date:inception_lower": "1992-08-01",
    "date:inception_upper": "1992-08-01",
    "iso:country": "GB",
    "wof:name": "BA2 8SB",
    "wof:placetype": "postalcode"
  },
  "geometry": {"coordinates":[-2.432927,51.311065],"type":"Point"}
}
