{
  "type": "Feature",
  "properties": {
    "date:inception_lower": "1998-12-01",
    "date:inception_upper": "1998-12-01",
    "iso:country": "GB",
    "wof:name": "G66 8BE",
    "wof:placetype": "postalcode"
  },
  "geometry": {"coordinates":[-4.164039,55.95866],"type":"Point"}
}
