{
  "type": "Feature",
  "properties": {
    "date:inception_lower": "1980-01-01",
    "date:inception_upper": "1980-01-01",
    "iso:country": "GB",
    "wof:name": "RG27 8SP",
    "wof:placetype": "postalcode"
  },
  "geometry": {"coordinates":[-0.881144,51.280559],"type":"Point"}
}
