{
  "type": "Feature",
  "properties": {
    "iso:country":"GB",
    "wof:name":"RG27 8SP",
    "wof:placetype":"postalcode"
},
  "geometry": {"coordinates":[-0.88114412046676,51.28055904215046],"type":"Point"}
}