{
  "type": "Feature",
  "properties": {
    "iso:country": "GB",
    "wof:name": "RG27 8SP",
    "wof:placetype": "postalcode"
  },
  "geometry": {"coordinates":[-0.881144,51.280559],"type":"Point"}
}
