{
  "type": "Feature",
  "properties": {
    "iso:country":"GB",
    "wof:name":"SP2 7LP",
    "wof:placetype":"postalcode"
},
  "geometry": {"coordinates":[-1.80955157463591,51.07492205581072],"type":"Point"}
}