{
  "type": "Feature",
  "properties": {
    "iso:country":"GB",
    "wof:name":"ML6 7UF",
    "wof:placetype":"postalcode"
},
  "geometry": {"coordinates":[-3.95798473744844,55.90689306308796],"type":"Point"}
}