{
  "type": "Feature",
  "properties": {
    "iso:country":"GB",
    "wof:name":"WA7 1QA",
    "wof:placetype":"postalcode"
},
  "geometry": {"coordinates":[-2.66231551283368,53.34574288809048],"type":"Point"}
}