{
  "type": "Feature",
  "properties": {
    "iso:country": "GB",
    "wof:name": "WA7 1QA",
    "wof:placetype": "postalcode"
  },
  "geometry": {"coordinates":[-2.662315,53.345743],"type":"Point"}
}
