{
  "type": "Feature",
  "properties": {
    "iso:country":"GB",
    "wof:name":"AB24 4NU",
    "wof:placetype":"postalcode"
},
  "geometry": {"coordinates":[-2.12712035172049,57.16181368314789],"type":"Point"}
}