{
  "type": "Feature",
  "properties": {
    "iso:country":"GB",
    "wof:name":"CF31 2QG",
    "wof:placetype":"postalcode"
},
  "geometry": {"coordinates":[-3.54283100569965,51.50543390991365],"type":"Point"}
}