{
  "type": "Feature",
  "properties": {
    "date:inception_lower":"1993-08-01",
    "date:inception_upper":"1993-08-31",
    "iso:country":"GB",
    "wof:name":"CF31 2QG",
    "wof:placetype":"postalcode"
},
  "geometry": {"coordinates":[-3.542816,51.505417],"type":"Point"}
}