{
  "type": "Feature",
  "properties": {
    "iso:country":"GB",
    "wof:name":"PA5 0AU",
    "wof:placetype":"postalcode"
},
  "geometry": {"coordinates":[-4.50608007306014,55.8304779696897],"type":"Point"}
}