{
  "type": "Feature",
  "properties": {
    "date:inception_lower": "1980-01-01",
    "date:inception_upper": "1980-01-01",
    "iso:country": "GB",
    "wof:name": "CO12 4PB",
    "wof:placetype": "postalcode"
  },
  "geometry": {"coordinates":[1.253834,51.942539],"type":"Point"}
}
