{
  "type": "Feature",
  "properties": {
    "iso:country":"GB",
    "wof:name":"CO12 4PB",
    "wof:placetype":"postalcode"
},
  "geometry": {"coordinates":[1.25383429176738,51.94253851900849],"type":"Point"}
}