{
  "type": "Feature",
  "properties": {
    "iso:country": "GB",
    "wof:name": "SO32 2NX",
    "wof:placetype": "postalcode"
  },
  "geometry": {"coordinates":[-1.148955,50.926078],"type":"Point"}
}
