{
  "type": "Feature",
  "properties": {
    "iso:country":"GB",
    "wof:name":"TN12 7DD",
    "wof:placetype":"postalcode"
},
  "geometry": {"coordinates":[0.42435364192975,51.16296861670971],"type":"Point"}
}