{
  "type": "Feature",
  "properties": {
    "date:inception_lower":"1980-01-01",
    "date:inception_upper":"1980-01-31",
    "iso:country":"GB",
    "wof:name":"TN12 7DD",
    "wof:placetype":"postalcode"
},
  "geometry": {"coordinates":[0.424354,51.162969],"type":"Point"}
}