{
  "type": "Feature",
  "properties": {
    "iso:country":"GB",
    "wof:name":"CV8 2JJ",
    "wof:placetype":"postalcode"
},
  "geometry": {"coordinates":[-1.56343499305643,52.3483694472643],"type":"Point"}
}