{
  "type": "Feature",
  "properties": {
    "date:inception_lower": "1980-01-01",
    "date:inception_upper": "1980-01-01",
    "iso:country": "GB",
    "wof:name": "SG8 5PL",
    "wof:placetype": "postalcode"
  },
  "geometry": {"coordinates":[-0.061067,52.087401],"type":"Point"}
}
