{
  "type": "Feature",
  "properties": {
    "iso:country":"GB",
    "wof:name":"SG8 5PL",
    "wof:placetype":"postalcode"
},
  "geometry": {"coordinates":[-0.06106724687285,52.08740062545208],"type":"Point"}
}