{
  "type": "Feature",
  "properties": {
    "iso:country":"GB",
    "wof:name":"CM15 0LG",
    "wof:placetype":"postalcode"
},
  "geometry": {"coordinates":[0.28017579141913,51.68165360100009],"type":"Point"}
}