{
  "type": "Feature",
  "properties": {
    "iso:country":"GB",
    "wof:name":"IV17 0QS",
    "wof:placetype":"postalcode"
},
  "geometry": {"coordinates":[-4.26179520970412,57.69999981831356],"type":"Point"}
}