{
  "type": "Feature",
  "properties": {
    "iso:country":"GB",
    "wof:name":"HU12 9PJ",
    "wof:placetype":"postalcode"
},
  "geometry": {"coordinates":[-0.1694272817052,53.71824062034158],"type":"Point"}
}