{
  "type": "Feature",
  "properties": {
    "iso:country":"GB",
    "wof:name":"CH49 1RE",
    "wof:placetype":"postalcode"
},
  "geometry": {"coordinates":[-3.11967412963187,53.3730068946134],"type":"Point"}
}