{
  "type": "Feature",
  "properties": {
    "iso:country":"GB",
    "wof:name":"CV9 2SF",
    "wof:placetype":"postalcode"
},
  "geometry": {"coordinates":[-1.6304593990691,52.58132277931336],"type":"Point"}
}