{
  "type": "Feature",
  "properties": {
    "date:inception_lower":"2009-04-01",
    "date:inception_upper":"2009-04-30",
    "iso:country":"GB",
    "wof:name":"CV9 2SF",
    "wof:placetype":"postalcode"
},
  "geometry": {"coordinates":[-1.630459,52.581323],"type":"Point"}
}