{
  "type": "Feature",
  "properties": {
    "iso:country": "GB",
    "wof:name": "B26 3JB",
    "wof:placetype": "postalcode"
  },
  "geometry": {"coordinates":[-1.784292,52.452904],"type":"Point"}
}
