{
  "type": "Feature",
  "properties": {
    "iso:country":"GB",
    "wof:name":"B26 3JB",
    "wof:placetype":"postalcode"
},
  "geometry": {"coordinates":[-1.78429202378953,52.45290399289657],"type":"Point"}
}