{
  "type": "Feature",
  "properties": {
    "date:inception_lower": "1980-01-01",
    "date:inception_upper": "1980-01-01",
    "iso:country": "GB",
    "wof:name": "PR3 0XS",
    "wof:placetype": "postalcode"
  },
  "geometry": {"coordinates":[-2.916947,53.856296],"type":"Point"}
}
