{
  "type": "Feature",
  "properties": {
    "iso:country":"GB",
    "wof:name":"PR3 0XS",
    "wof:placetype":"postalcode"
},
  "geometry": {"coordinates":[-2.91674865597903,53.85604930404491],"type":"Point"}
}