{
  "type": "Feature",
  "properties": {
    "iso:country":"GB",
    "wof:name":"NG2 1QB",
    "wof:placetype":"postalcode"
},
  "geometry": {"coordinates":[-1.15632538455653,52.94314340797056],"type":"Point"}
}