{
  "type": "Feature",
  "properties": {
    "date:inception_lower": "1996-06-01",
    "date:inception_upper": "1996-06-01",
    "iso:country": "GB",
    "wof:name": "PL7 2WZ",
    "wof:placetype": "postalcode"
  },
  "geometry": {"coordinates":[-4.033248,50.392674],"type":"Point"}
}
