{
  "type": "Feature",
  "properties": {
    "iso:country":"GB",
    "wof:name":"PL7 2WZ",
    "wof:placetype":"postalcode"
},
  "geometry": {"coordinates":[-4.03324781319446,50.39267354966773],"type":"Point"}
}