{
  "type": "Feature",
  "properties": {
    "date:inception_lower": "1990-07-01",
    "date:inception_upper": "1990-07-01",
    "iso:country": "GB",
    "wof:name": "BN45 7AR",
    "wof:placetype": "postalcode"
  },
  "geometry": {"coordinates":[-0.207762,50.893194],"type":"Point"}
}
