{
  "type": "Feature",
  "properties": {
    "date:inception_lower": "1980-01-01",
    "date:inception_upper": "1980-01-01",
    "iso:country": "GB",
    "wof:name": "ZE2 9TQ",
    "wof:placetype": "postalcode"
  },
  "geometry": {"coordinates":[-1.180909,60.460141],"type":"Point"}
}
