{
  "type": "Feature",
  "properties": {
    "iso:country":"GB",
    "wof:name":"HD5 0PS",
    "wof:placetype":"postalcode"
},
  "geometry": {"coordinates":[-1.72741864120002,53.67381174494146],"type":"Point"}
}