{
  "type": "Feature",
  "properties": {
    "iso:country":"GB",
    "wof:name":"WA8 8UA",
    "wof:placetype":"postalcode"
},
  "geometry": {"coordinates":[-2.76924909543151,53.35904300349993],"type":"Point"}
}