{
  "type": "Feature",
  "properties": {
    "iso:country":"GB",
    "wof:name":"ME19 6LU",
    "wof:placetype":"postalcode"
},
  "geometry": {"coordinates":[0.40854231210801,51.29451186685048],"type":"Point"}
}