{
  "type": "Feature",
  "properties": {
    "iso:country": "GB",
    "wof:name": "ME19 6LU",
    "wof:placetype": "postalcode"
  },
  "geometry": {"coordinates":[0.408542,51.294512],"type":"Point"}
}
