{
  "type": "Feature",
  "properties": {
    "iso:country": "GB",
    "wof:name": "IP3 8XL",
    "wof:placetype": "postalcode"
  },
  "geometry": {"coordinates":[1.194558,52.049877],"type":"Point"}
}
