{
  "type": "Feature",
  "properties": {
    "iso:country":"GB",
    "wof:name":"BB3 3PQ",
    "wof:placetype":"postalcode"
},
  "geometry": {"coordinates":[-2.44828780975142,53.71166996985633],"type":"Point"}
}