{
  "type": "Feature",
  "properties": {
    "iso:country": "GB",
    "wof:name": "BB3 3PQ",
    "wof:placetype": "postalcode"
  },
  "geometry": {"coordinates":[-2.448288,53.71167],"type":"Point"}
}
