{
  "type": "Feature",
  "properties": {
    "iso:country": "GB",
    "wof:name": "ME12 2FE",
    "wof:placetype": "postalcode"
  },
  "geometry": {"coordinates":[0.796809,51.4332],"type":"Point"}
}
