{
  "type": "Feature",
  "properties": {
    "iso:country":"GB",
    "wof:name":"CB23 3FA",
    "wof:placetype":"postalcode"
},
  "geometry": {"coordinates":[-0.12118618775976,52.24890181939057],"type":"Point"}
}