{
  "type": "Feature",
  "properties": {
    "iso:country": "GB",
    "wof:name": "CB23 3FA",
    "wof:placetype": "postalcode"
  },
  "geometry": {"coordinates":[-0.121186,52.248902],"type":"Point"}
}
