{
  "type": "Feature",
  "properties": {
    "iso:country":"GB",
    "wof:name":"RG8 8RS",
    "wof:placetype":"postalcode"
},
  "geometry": {"coordinates":[-1.18456437468637,51.48908573335295],"type":"Point"}
}