{
  "type": "Feature",
  "properties": {
    "date:inception_lower": "1980-01-01",
    "date:inception_upper": "1980-01-01",
    "iso:country": "GB",
    "wof:name": "RG8 8RS",
    "wof:placetype": "postalcode"
  },
  "geometry": {"coordinates":[-1.184544,51.489087],"type":"Point"}
}
