{
  "type": "Feature",
  "properties": {
    "date:inception_lower": "1980-01-01",
    "date:inception_upper": "1980-01-01",
    "iso:country": "GB",
    "wof:name": "AL7 1PG",
    "wof:placetype": "postalcode"
  },
  "geometry": {"coordinates":[-0.1827,51.8106],"type":"Point"}
}
