{
  "type": "Feature",
  "properties": {
    "iso:country":"GB",
    "wof:name":"AL7 1PG",
    "wof:placetype":"postalcode"
},
  "geometry": {"coordinates":[-0.18269959474196,51.81060029293447],"type":"Point"}
}