{
  "type": "Feature",
  "properties": {
    "iso:country": "GB",
    "wof:name": "NE47 8LA",
    "wof:placetype": "postalcode"
  },
  "geometry": {"coordinates":[-2.324555,54.92024],"type":"Point"}
}
