{
  "type": "Feature",
  "properties": {
    "date:inception_lower":"1998-06-01",
    "date:inception_upper":"1998-06-30",
    "iso:country":"GB",
    "wof:name":"N22 7AH",
    "wof:placetype":"postalcode"
},
  "geometry": {"coordinates":[-0.129235,51.601681],"type":"Point"}
}