{
  "type": "Feature",
  "properties": {
    "iso:country":"GB",
    "wof:name":"N22 7AH",
    "wof:placetype":"postalcode"
},
  "geometry": {"coordinates":[-0.12923499879976,51.60168104473956],"type":"Point"}
}