{
  "type": "Feature",
  "properties": {
    "iso:country":"GB",
    "wof:name":"NE61 6PA",
    "wof:placetype":"postalcode"
},
  "geometry": {"coordinates":[-1.65186549266366,55.14681577245632],"type":"Point"}
}