{
  "type": "Feature",
  "properties": {
    "iso:country": "GB",
    "wof:name": "NE61 6PA",
    "wof:placetype": "postalcode"
  },
  "geometry": {"coordinates":[-1.651865,55.146816],"type":"Point"}
}
