{
  "type": "Feature",
  "properties": {
    "iso:country": "GB",
    "wof:name": "UB3 5EX",
    "wof:placetype": "postalcode"
  },
  "geometry": {"coordinates":[-0.433707,51.490527],"type":"Point"}
}
