{
  "type": "Feature",
  "properties": {
    "date:inception_lower":"1980-01-01",
    "date:inception_upper":"1980-01-31",
    "iso:country":"GB",
    "wof:name":"UB3 5EX",
    "wof:placetype":"postalcode"
},
  "geometry": {"coordinates":[-0.433707,51.490527],"type":"Point"}
}