{
  "type": "Feature",
  "properties": {
    "iso:country":"GB",
    "wof:name":"UB3 5EX",
    "wof:placetype":"postalcode"
},
  "geometry": {"coordinates":[-0.43370726079186,51.49052657807292],"type":"Point"}
}