{
  "type": "Feature",
  "properties": {
    "date:inception_lower": "2024-06-01",
    "date:inception_upper": "2024-06-01",
    "iso:country": "GB",
    "wof:name": "HU17 8WZ",
    "wof:placetype": "postalcode"
  },
  "geometry": {"coordinates":[-0.432029,53.825672],"type":"Point"}
}
