{
  "type": "Feature",
  "properties": {
    "date:inception_lower": "1980-01-01",
    "date:inception_upper": "1980-01-01",
    "iso:country": "GB",
    "wof:name": "BN27 4HE",
    "wof:placetype": "postalcode"
  },
  "geometry": {"coordinates":[0.273461,50.89972],"type":"Point"}
}
