{
  "type": "Feature",
  "properties": {
    "iso:country":"GB",
    "wof:name":"BN27 4HE",
    "wof:placetype":"postalcode"
},
  "geometry": {"coordinates":[0.27468321460344,50.90028511552639],"type":"Point"}
}