{
  "type": "Feature",
  "properties": {
    "iso:country": "GB",
    "wof:name": "CH3 9QA",
    "wof:placetype": "postalcode"
  },
  "geometry": {"coordinates":[-2.771536,53.119306],"type":"Point"}
}
