{
  "type": "Feature",
  "properties": {
    "date:inception_lower": "1980-01-01",
    "date:inception_upper": "1980-01-01",
    "iso:country": "GB",
    "wof:name": "CH3 9QA",
    "wof:placetype": "postalcode"
  },
  "geometry": {"coordinates":[-2.771641,53.119333],"type":"Point"}
}
