{
  "type": "Feature",
  "properties": {
    "iso:country":"GB",
    "wof:name":"CH3 9QA",
    "wof:placetype":"postalcode"
},
  "geometry": {"coordinates":[-2.7716403462318,53.11931705711746],"type":"Point"}
}