{
  "type": "Feature",
  "properties": {
    "iso:country":"GB",
    "wof:name":"KA10 7BS",
    "wof:placetype":"postalcode"
},
  "geometry": {"coordinates":[-4.64103477201431,55.5513608712373],"type":"Point"}
}