{
  "type": "Feature",
  "properties": {
    "date:inception_lower":"2000-12-01",
    "date:inception_upper":"2000-12-31",
    "iso:country":"GB",
    "wof:name":"CA3 8NS",
    "wof:placetype":"postalcode"
},
  "geometry": {"coordinates":[-2.934177,54.896179],"type":"Point"}
}