{
  "type": "Feature",
  "properties": {
    "iso:country":"GB",
    "wof:name":"CA3 8NS",
    "wof:placetype":"postalcode"
},
  "geometry": {"coordinates":[-2.93417705884481,54.89617855131987],"type":"Point"}
}