{
  "type": "Feature",
  "properties": {
    "iso:country": "GB",
    "wof:name": "CA3 8NS",
    "wof:placetype": "postalcode"
  },
  "geometry": {"coordinates":[-2.934177,54.896179],"type":"Point"}
}
