{
  "type": "Feature",
  "properties": {
    "date:inception_lower": "2000-12-01",
    "date:inception_upper": "2000-12-01",
    "iso:country": "GB",
    "wof:name": "CA3 8NS",
    "wof:placetype": "postalcode"
  },
  "geometry": {"coordinates":[-2.935038,54.896169],"type":"Point"}
}
