{
  "type": "Feature",
  "properties": {
    "date:inception_lower": "2002-06-01",
    "date:inception_upper": "2002-06-01",
    "iso:country": "GB",
    "wof:name": "BB1 2QP",
    "wof:placetype": "postalcode"
  },
  "geometry": {"coordinates":[-2.442553,53.734186],"type":"Point"}
}
