{
  "type": "Feature",
  "properties": {
    "iso:country":"GB",
    "wof:name":"S40 1QP",
    "wof:placetype":"postalcode"
},
  "geometry": {"coordinates":[-1.42633216848074,53.23386199346761],"type":"Point"}
}