{
  "type": "Feature",
  "properties": {
    "iso:country": "GB",
    "wof:name": "S40 1QP",
    "wof:placetype": "postalcode"
  },
  "geometry": {"coordinates":[-1.425924,53.234014],"type":"Point"}
}
