{
  "type": "Feature",
  "properties": {
    "iso:country":"GB",
    "wof:name":"BA11 4PL",
    "wof:placetype":"postalcode"
},
  "geometry": {"coordinates":[-2.407194561077,51.18692057438065],"type":"Point"}
}