{
  "type": "Feature",
  "properties": {
    "iso:country":"GB",
    "wof:name":"EX32 7DQ",
    "wof:placetype":"postalcode"
},
  "geometry": {"coordinates":[-4.04747045949574,51.08139273918948],"type":"Point"}
}