{
  "type": "Feature",
  "properties": {
    "iso:country": "GB",
    "wof:name": "NN5 6NS",
    "wof:placetype": "postalcode"
  },
  "geometry": {"coordinates":[-0.95579,52.259108],"type":"Point"}
}
