{
  "type": "Feature",
  "properties": {
    "date:inception_lower": "1980-01-01",
    "date:inception_upper": "1980-01-01",
    "iso:country": "GB",
    "wof:name": "NN5 6NS",
    "wof:placetype": "postalcode"
  },
  "geometry": {"coordinates":[-0.95579,52.259108],"type":"Point"}
}
