{
  "type": "Feature",
  "properties": {
    "iso:country": "GB",
    "wof:name": "GL12 8EP",
    "wof:placetype": "postalcode"
  },
  "geometry": {"coordinates":[-2.383562,51.630893],"type":"Point"}
}
