{
  "type": "Feature",
  "properties": {
    "iso:country":"GB",
    "wof:name":"GL12 8EP",
    "wof:placetype":"postalcode"
},
  "geometry": {"coordinates":[-2.38107152040762,51.62645762923585],"type":"Point"}
}