{
  "type": "Feature",
  "properties": {
    "date:inception_lower": "1980-01-01",
    "date:inception_upper": "1980-01-01",
    "iso:country": "GB",
    "wof:name": "GL12 8EP",
    "wof:placetype": "postalcode"
  },
  "geometry": {"coordinates":[-2.383562,51.630893],"type":"Point"}
}
