{
  "type": "Feature",
  "properties": {
    "iso:country":"GB",
    "wof:name":"NW6 1EE",
    "wof:placetype":"postalcode"
},
  "geometry": {"coordinates":[-0.19858497222815,51.55400035840857],"type":"Point"}
}