{
  "type": "Feature",
  "properties": {
    "date:inception_lower": "1980-01-01",
    "date:inception_upper": "1980-01-01",
    "iso:country": "GB",
    "wof:name": "NW6 1EE",
    "wof:placetype": "postalcode"
  },
  "geometry": {"coordinates":[-0.198585,51.554],"type":"Point"}
}
