{
  "type": "Feature",
  "properties": {
    "date:inception_lower":"2001-06-01",
    "date:inception_upper":"2001-06-30",
    "iso:country":"GB",
    "wof:name":"GL50 1WG",
    "wof:placetype":"postalcode"
},
  "geometry": {"coordinates":[-2.078651,51.898517],"type":"Point"}
}