{
  "type": "Feature",
  "properties": {
    "iso:country":"GB",
    "wof:name":"TS23 1BH",
    "wof:placetype":"postalcode"
},
  "geometry": {"coordinates":[-1.2868765756454,54.59736091518065],"type":"Point"}
}