{
  "type": "Feature",
  "properties": {
    "iso:country": "GB",
    "wof:name": "TS23 1BH",
    "wof:placetype": "postalcode"
  },
  "geometry": {"coordinates":[-1.286877,54.597361],"type":"Point"}
}
