{
  "type": "Feature",
  "properties": {
    "iso:country":"GB",
    "wof:name":"SN1 5ND",
    "wof:placetype":"postalcode"
},
  "geometry": {"coordinates":[-1.78776583556969,51.55838952795123],"type":"Point"}
}