{
  "type": "Feature",
  "properties": {
    "iso:country":"GB",
    "wof:name":"BA7 7HY",
    "wof:placetype":"postalcode"
},
  "geometry": {"coordinates":[-2.51024276721305,51.09220723000254],"type":"Point"}
}