{
  "type": "Feature",
  "properties": {
    "date:inception_lower":"2002-05-01",
    "date:inception_upper":"2002-05-31",
    "iso:country":"GB",
    "wof:name":"SS1 1HN",
    "wof:placetype":"postalcode"
},
  "geometry": {"coordinates":[0.705499,51.535156],"type":"Point"}
}