{
  "type": "Feature",
  "properties": {
    "iso:country":"GB",
    "wof:name":"KA12 9AF",
    "wof:placetype":"postalcode"
},
  "geometry": {"coordinates":[-4.66899389085071,55.62877753216947],"type":"Point"}
}