{
  "type": "Feature",
  "properties": {
    "iso:country": "GB",
    "wof:name": "DL1 5LQ",
    "wof:placetype": "postalcode"
  },
  "geometry": {"coordinates":[-1.548112,54.521842],"type":"Point"}
}
