{
  "type": "Feature",
  "properties": {
    "iso:country":"GB",
    "wof:name":"DL1 5LQ",
    "wof:placetype":"postalcode"
},
  "geometry": {"coordinates":[-1.54811177951724,54.52184224054635],"type":"Point"}
}