{
  "type": "Feature",
  "properties": {
    "iso:country":"GB",
    "wof:name":"PL12 5EN",
    "wof:placetype":"postalcode"
},
  "geometry": {"coordinates":[-4.29218946401,50.42389770335883],"type":"Point"}
}