{
  "type": "Feature",
  "properties": {
    "iso:country":"GB",
    "wof:name":"G51 2AS",
    "wof:placetype":"postalcode"
},
  "geometry": {"coordinates":[-4.30392244994817,55.86029846762674],"type":"Point"}
}