{
  "type": "Feature",
  "properties": {
    "iso:country":"GB",
    "wof:name":"HP22 4PR",
    "wof:placetype":"postalcode"
},
  "geometry": {"coordinates":[-0.74065012835123,51.86060821718652],"type":"Point"}
}