{
  "type": "Feature",
  "properties": {
    "iso:country": "GB",
    "wof:name": "HP22 4PR",
    "wof:placetype": "postalcode"
  },
  "geometry": {"coordinates":[-0.74065,51.860608],"type":"Point"}
}
