{
  "type": "Feature",
  "properties": {
    "date:inception_lower":"1993-08-01",
    "date:inception_upper":"1993-08-31",
    "iso:country":"GB",
    "wof:name":"HP22 4PR",
    "wof:placetype":"postalcode"
},
  "geometry": {"coordinates":[-0.74065,51.860608],"type":"Point"}
}