{
  "type": "Feature",
  "properties": {
    "iso:country":"GB",
    "wof:name":"W7 3UA",
    "wof:placetype":"postalcode"
},
  "geometry": {"coordinates":[-0.34152373292313,51.50785530805913],"type":"Point"}
}