{
  "type": "Feature",
  "properties": {
    "iso:country": "GB",
    "wof:name": "W7 3UA",
    "wof:placetype": "postalcode"
  },
  "geometry": {"coordinates":[-0.341524,51.507855],"type":"Point"}
}
