{
  "type": "Feature",
  "properties": {
    "iso:country": "GB",
    "wof:name": "NE46 3JL",
    "wof:placetype": "postalcode"
  },
  "geometry": {"coordinates":[-2.115255,54.971885],"type":"Point"}
}
