{
  "type": "Feature",
  "properties": {
    "date:inception_lower": "1991-09-01",
    "date:inception_upper": "1991-09-01",
    "iso:country": "GB",
    "wof:name": "SK16 5QS",
    "wof:placetype": "postalcode"
  },
  "geometry": {"coordinates":[-2.067829,53.471686],"type":"Point"}
}
