{
  "type": "Feature",
  "properties": {
    "iso:country":"GB",
    "wof:name":"SK16 5QS",
    "wof:placetype":"postalcode"
},
  "geometry": {"coordinates":[-2.06782950340491,53.47168552499019],"type":"Point"}
}