{
  "type": "Feature",
  "properties": {
    "iso:country": "GB",
    "wof:name": "DN12 3HD",
    "wof:placetype": "postalcode"
  },
  "geometry": {"coordinates":[-1.229153,53.481463],"type":"Point"}
}
