{
  "type": "Feature",
  "properties": {
    "iso:country":"GB",
    "wof:name":"HP1 2AA",
    "wof:placetype":"postalcode"
},
  "geometry": {"coordinates":[-0.49311596541261,51.75290873385068],"type":"Point"}
}