{
  "type": "Feature",
  "properties": {
    "iso:country":"GB",
    "wof:name":"SK14 5DQ",
    "wof:placetype":"postalcode"
},
  "geometry": {"coordinates":[-2.08335845121036,53.43941602941054],"type":"Point"}
}