{
  "type": "Feature",
  "properties": {
    "iso:country": "GB",
    "wof:name": "SA31 2BH",
    "wof:placetype": "postalcode"
  },
  "geometry": {"coordinates":[-4.285368,51.869787],"type":"Point"}
}
