{
  "type": "Feature",
  "properties": {
    "iso:country":"GB",
    "wof:name":"SA31 2BH",
    "wof:placetype":"postalcode"
},
  "geometry": {"coordinates":[-4.28547741305109,51.87009039621236],"type":"Point"}
}