{
  "type": "Feature",
  "properties": {
    "date:inception_lower":"2013-07-01",
    "date:inception_upper":"2013-07-31",
    "iso:country":"GB",
    "wof:name":"SA31 2BH",
    "wof:placetype":"postalcode"
},
  "geometry": {"coordinates":[-4.285368,51.869787],"type":"Point"}
}