{
  "type": "Feature",
  "properties": {
    "iso:country":"GB",
    "wof:name":"NR31 0HY",
    "wof:placetype":"postalcode"
},
  "geometry": {"coordinates":[1.7218858996818,52.60670284304383],"type":"Point"}
}