{
  "type": "Feature",
  "properties": {
    "date:inception_lower": "2006-04-01",
    "date:inception_upper": "2006-04-01",
    "iso:country": "GB",
    "wof:name": "NR31 0HY",
    "wof:placetype": "postalcode"
  },
  "geometry": {"coordinates":[1.721886,52.606703],"type":"Point"}
}
