{
  "type": "Feature",
  "properties": {
    "iso:country": "GB",
    "wof:name": "FK7 8PG",
    "wof:placetype": "postalcode"
  },
  "geometry": {"coordinates":[-3.904403,56.090682],"type":"Point"}
}
