{
  "type": "Feature",
  "properties": {
    "iso:country":"GB",
    "wof:name":"KA1 4QX",
    "wof:placetype":"postalcode"
},
  "geometry": {"coordinates":[-4.49601423429237,55.58258986004814],"type":"Point"}
}