{
  "type": "Feature",
  "properties": {
    "date:inception_lower": "1980-01-01",
    "date:inception_upper": "1980-01-01",
    "iso:country": "GB",
    "wof:name": "KA1 4QX",
    "wof:placetype": "postalcode"
  },
  "geometry": {"coordinates":[-4.496014,55.58259],"type":"Point"}
}
