{
  "type": "Feature",
  "properties": {
    "date:inception_lower": "1983-07-01",
    "date:inception_upper": "1983-07-01",
    "iso:country": "GB",
    "wof:name": "CH7 6AJ",
    "wof:placetype": "postalcode"
  },
  "geometry": {"coordinates":[-3.129368,53.188681],"type":"Point"}
}
