{
  "type": "Feature",
  "properties": {
    "iso:country":"GB",
    "wof:name":"CH7 6AJ",
    "wof:placetype":"postalcode"
},
  "geometry": {"coordinates":[-3.12936770277583,53.18868119392965],"type":"Point"}
}