{
  "type": "Feature",
  "properties": {
    "date:inception_lower": "1980-01-01",
    "date:inception_upper": "1980-01-01",
    "iso:country": "GB",
    "wof:name": "GU32 1HG",
    "wof:placetype": "postalcode"
  },
  "geometry": {"coordinates":[-1.042491,50.96796],"type":"Point"}
}
