{
  "type": "Feature",
  "properties": {
    "iso:country":"GB",
    "wof:name":"L13 6QU",
    "wof:placetype":"postalcode"
},
  "geometry": {"coordinates":[-2.92108290385382,53.41884039476325],"type":"Point"}
}