{
  "type": "Feature",
  "properties": {
    "date:inception_lower": "1981-06-01",
    "date:inception_upper": "1981-06-01",
    "iso:country": "GB",
    "wof:name": "L13 6QU",
    "wof:placetype": "postalcode"
  },
  "geometry": {"coordinates":[-2.921083,53.41884],"type":"Point"}
}
