{
  "type": "Feature",
  "properties": {
    "iso:country": "GB",
    "wof:name": "WR2 6SG",
    "wof:placetype": "postalcode"
  },
  "geometry": {"coordinates":[-2.274777,52.21427],"type":"Point"}
}
