{
  "type": "Feature",
  "properties": {
    "iso:country":"GB",
    "wof:name":"SE2 9DH",
    "wof:placetype":"postalcode"
},
  "geometry": {"coordinates":[0.10508310144564,51.49504180359358],"type":"Point"}
}