{
  "type": "Feature",
  "properties": {
    "iso:country":"GB",
    "wof:name":"ST15 8WF",
    "wof:placetype":"postalcode"
},
  "geometry": {"coordinates":[-2.10116635337151,52.94449266678501],"type":"Point"}
}