{
  "type": "Feature",
  "properties": {
    "date:inception_lower": "2008-04-01",
    "date:inception_upper": "2008-04-01",
    "iso:country": "GB",
    "wof:name": "ST15 8WF",
    "wof:placetype": "postalcode"
  },
  "geometry": {"coordinates":[-2.101166,52.944493],"type":"Point"}
}
