{
  "type": "Feature",
  "properties": {
    "iso:country":"GB",
    "wof:name":"CO9 3DQ",
    "wof:placetype":"postalcode"
},
  "geometry": {"coordinates":[0.60054233653103,51.99069006550937],"type":"Point"}
}