{
  "type": "Feature",
  "properties": {
    "iso:country": "GB",
    "wof:name": "CO9 3DQ",
    "wof:placetype": "postalcode"
  },
  "geometry": {"coordinates":[0.600542,51.99069],"type":"Point"}
}
