{
  "type": "Feature",
  "properties": {
    "iso:country": "GB",
    "wof:name": "L39 7JE",
    "wof:placetype": "postalcode"
  },
  "geometry": {"coordinates":[-2.969335,53.564077],"type":"Point"}
}
