{
  "type": "Feature",
  "properties": {
    "date:inception_lower": "1980-01-01",
    "date:inception_upper": "1980-01-01",
    "iso:country": "GB",
    "wof:name": "L39 7JE",
    "wof:placetype": "postalcode"
  },
  "geometry": {"coordinates":[-2.969335,53.564077],"type":"Point"}
}
