{
  "type": "Feature",
  "properties": {
    "iso:country":"GB",
    "wof:name":"L39 7JE",
    "wof:placetype":"postalcode"
},
  "geometry": {"coordinates":[-2.96933548791623,53.56407685007716],"type":"Point"}
}