{
  "type": "Feature",
  "properties": {
    "iso:country":"GB",
    "wof:name":"PR2 3NE",
    "wof:placetype":"postalcode"
},
  "geometry": {"coordinates":[-2.7268383653863,53.79514336316949],"type":"Point"}
}