{
  "type": "Feature",
  "properties": {
    "date:inception_lower": "1990-07-01",
    "date:inception_upper": "1990-07-01",
    "iso:country": "GB",
    "wof:name": "OX9 3UH",
    "wof:placetype": "postalcode"
  },
  "geometry": {"coordinates":[-0.968461,51.741034],"type":"Point"}
}
