{
  "type": "Feature",
  "properties": {
    "iso:country":"GB",
    "wof:name":"OX9 3UH",
    "wof:placetype":"postalcode"
},
  "geometry": {"coordinates":[-0.96812163304179,51.74101718298807],"type":"Point"}
}