{
  "type": "Feature",
  "properties": {
    "iso:country":"GB",
    "wof:name":"L20 9NN",
    "wof:placetype":"postalcode"
},
  "geometry": {"coordinates":[-2.97647992498176,53.44418030516751],"type":"Point"}
}