{
  "type": "Feature",
  "properties": {
    "iso:country": "GB",
    "wof:name": "EC1R 5BU",
    "wof:placetype": "postalcode"
  },
  "geometry": {"coordinates":[-0.108359,51.521961],"type":"Point"}
}
