{
  "type": "Feature",
  "properties": {
    "iso:country": "GB",
    "wof:name": "DD8 5LZ",
    "wof:placetype": "postalcode"
  },
  "geometry": {"coordinates":[-3.037631,56.648195],"type":"Point"}
}
