{
  "type": "Feature",
  "properties": {
    "iso:country":"GB",
    "wof:name":"CR7 7DX",
    "wof:placetype":"postalcode"
},
  "geometry": {"coordinates":[-0.10802222916336,51.39886449347377],"type":"Point"}
}