{
  "type": "Feature",
  "properties": {
    "date:inception_lower": "1980-01-01",
    "date:inception_upper": "1980-01-01",
    "iso:country": "GB",
    "wof:name": "IP24 1PD",
    "wof:placetype": "postalcode"
  },
  "geometry": {"coordinates":[0.873357,52.504285],"type":"Point"}
}
