{
  "type": "Feature",
  "properties": {
    "iso:country":"GB",
    "wof:name":"IP24 1PD",
    "wof:placetype":"postalcode"
},
  "geometry": {"coordinates":[0.87335696210289,52.5042851608009],"type":"Point"}
}