{
  "type": "Feature",
  "properties": {
    "iso:country":"GB",
    "wof:name":"DN22 7UG",
    "wof:placetype":"postalcode"
},
  "geometry": {"coordinates":[-0.94812897971347,53.30640807831402],"type":"Point"}
}