{
  "type": "Feature",
  "properties": {
    "iso:country": "GB",
    "wof:name": "CF37 1AE",
    "wof:placetype": "postalcode"
  },
  "geometry": {"coordinates":[-3.329244,51.592953],"type":"Point"}
}
