{
  "type": "Feature",
  "properties": {
    "iso:country":"GB",
    "wof:name":"RH14 9AA",
    "wof:placetype":"postalcode"
},
  "geometry": {"coordinates":[-0.44016535321397,51.02966334986333],"type":"Point"}
}