{
  "type": "Feature",
  "properties": {
    "iso:country":"GB",
    "wof:name":"CT20 2SN",
    "wof:placetype":"postalcode"
},
  "geometry": {"coordinates":[1.17194485221302,51.07922097422977],"type":"Point"}
}