{
  "type": "Feature",
  "properties": {
    "iso:country":"GB",
    "wof:name":"B70 0DT",
    "wof:placetype":"postalcode"
},
  "geometry": {"coordinates":[-2.02333718778386,52.53334202530821],"type":"Point"}
}