{
  "type": "Feature",
  "properties": {
    "date:inception_lower":"1980-01-01",
    "date:inception_upper":"1980-01-31",
    "iso:country":"GB",
    "wof:name":"B70 0DT",
    "wof:placetype":"postalcode"
},
  "geometry": {"coordinates":[-2.023337,52.533342],"type":"Point"}
}