{
  "type": "Feature",
  "properties": {
    "date:inception_lower": "2021-01-01",
    "date:inception_upper": "2021-01-01",
    "iso:country": "GB",
    "wof:name": "CO7 7GL",
    "wof:placetype": "postalcode"
  },
  "geometry": {"coordinates":[0.992845,51.879338],"type":"Point"}
}
