{
  "type": "Feature",
  "properties": {
    "iso:country":"GB",
    "wof:name":"PE19 8PP",
    "wof:placetype":"postalcode"
},
  "geometry": {"coordinates":[-0.28889824782779,52.22434319262505],"type":"Point"}
}