{
  "type": "Feature",
  "properties": {
    "date:inception_lower":"1980-01-01",
    "date:inception_upper":"1980-01-31",
    "iso:country":"GB",
    "wof:name":"SS9 5QH",
    "wof:placetype":"postalcode"
},
  "geometry": {"coordinates":[0.657154,51.572164],"type":"Point"}
}