{
  "type": "Feature",
  "properties": {
    "iso:country":"GB",
    "wof:name":"SS9 5QH",
    "wof:placetype":"postalcode"
},
  "geometry": {"coordinates":[0.65715373149835,51.57216399687342],"type":"Point"}
}