{
  "type": "Feature",
  "properties": {
    "iso:country":"GB",
    "wof:name":"S6 2BX",
    "wof:placetype":"postalcode"
},
  "geometry": {"coordinates":[-1.49855386298434,53.40341026212048],"type":"Point"}
}