{
  "type": "Feature",
  "properties": {
    "iso:country": "GB",
    "wof:name": "S6 2BX",
    "wof:placetype": "postalcode"
  },
  "geometry": {"coordinates":[-1.498554,53.40341],"type":"Point"}
}
