{
  "type": "Feature",
  "properties": {
    "iso:country":"GB",
    "wof:name":"NE3 4QJ",
    "wof:placetype":"postalcode"
},
  "geometry": {"coordinates":[-1.64088799502419,55.0009843989162],"type":"Point"}
}