{
  "type": "Feature",
  "properties": {
    "date:inception_lower":"2015-12-01",
    "date:inception_upper":"2015-12-31",
    "iso:country":"GB",
    "wof:name":"FK5 4ZL",
    "wof:placetype":"postalcode"
},
  "geometry": {"coordinates":[-3.814694,56.037194],"type":"Point"}
}