{
  "type": "Feature",
  "properties": {
    "iso:country":"GB",
    "wof:name":"FK5 4ZL",
    "wof:placetype":"postalcode"
},
  "geometry": {"coordinates":[-3.81539207935786,56.03720645157303],"type":"Point"}
}