{
  "type": "Feature",
  "properties": {
    "date:inception_lower": "2020-02-01",
    "date:inception_upper": "2020-02-01",
    "iso:country": "GB",
    "wof:name": "CV47 2RU",
    "wof:placetype": "postalcode"
  },
  "geometry": {"coordinates":[-1.429131,52.227126],"type":"Point"}
}
