{
  "type": "Feature",
  "properties": {
    "iso:country":"GB",
    "wof:name":"NE33 4AE",
    "wof:placetype":"postalcode"
},
  "geometry": {"coordinates":[-1.43131303630048,54.98784760795994],"type":"Point"}
}