{
  "type": "Feature",
  "properties": {
    "iso:country":"GB",
    "wof:name":"PE37 8DF",
    "wof:placetype":"postalcode"
},
  "geometry": {"coordinates":[0.71366807417252,52.64928346372887],"type":"Point"}
}