{
  "type": "Feature",
  "properties": {
    "iso:country":"GB",
    "wof:name":"NP11 5DY",
    "wof:placetype":"postalcode"
},
  "geometry": {"coordinates":[-3.12802590189519,51.68347308028738],"type":"Point"}
}