{
  "type": "Feature",
  "properties": {
    "iso:country": "GB",
    "wof:name": "NP11 5DY",
    "wof:placetype": "postalcode"
  },
  "geometry": {"coordinates":[-3.128026,51.683473],"type":"Point"}
}
