{
  "type": "Feature",
  "properties": {
    "date:inception_lower":"1999-06-01",
    "date:inception_upper":"1999-06-30",
    "iso:country":"GB",
    "wof:name":"NP11 5DY",
    "wof:placetype":"postalcode"
},
  "geometry": {"coordinates":[-3.128026,51.683473],"type":"Point"}
}