{
  "type": "Feature",
  "properties": {
    "date:inception_lower": "1980-01-01",
    "date:inception_upper": "1980-01-01",
    "iso:country": "GB",
    "wof:name": "B17 9UD",
    "wof:placetype": "postalcode"
  },
  "geometry": {"coordinates":[-1.966903,52.456844],"type":"Point"}
}
