{
  "type": "Feature",
  "properties": {
    "iso:country":"GB",
    "wof:name":"B17 9UD",
    "wof:placetype":"postalcode"
},
  "geometry": {"coordinates":[-1.96690312202624,52.45684446687533],"type":"Point"}
}