{
  "type": "Feature",
  "properties": {
    "iso:country":"GB",
    "wof:name":"NR9 4LT",
    "wof:placetype":"postalcode"
},
  "geometry": {"coordinates":[0.99058969214074,52.58038231975686],"type":"Point"}
}