{
  "type": "Feature",
  "properties": {
    "date:inception_lower": "1980-01-01",
    "date:inception_upper": "1980-01-01",
    "iso:country": "GB",
    "wof:name": "NR9 4LT",
    "wof:placetype": "postalcode"
  },
  "geometry": {"coordinates":[0.99059,52.580382],"type":"Point"}
}
