{
  "type": "Feature",
  "properties": {
    "iso:country":"GB",
    "wof:name":"SN10 3HR",
    "wof:placetype":"postalcode"
},
  "geometry": {"coordinates":[-1.97503292622711,51.33227008019399],"type":"Point"}
}