{
  "type": "Feature",
  "properties": {
    "iso:country": "GB",
    "wof:name": "ST19 5EQ",
    "wof:placetype": "postalcode"
  },
  "geometry": {"coordinates":[-2.103606,52.726245],"type":"Point"}
}
