{
  "type": "Feature",
  "properties": {
    "iso:country": "GB",
    "wof:name": "GU22 9DA",
    "wof:placetype": "postalcode"
  },
  "geometry": {"coordinates":[-0.545317,51.298639],"type":"Point"}
}
