{
  "type": "Feature",
  "properties": {
    "date:inception_lower":"2011-12-01",
    "date:inception_upper":"2011-12-31",
    "iso:country":"GB",
    "wof:name":"GU22 9DA",
    "wof:placetype":"postalcode"
},
  "geometry": {"coordinates":[-0.545317,51.298639],"type":"Point"}
}