{
  "type": "Feature",
  "properties": {
    "date:inception_lower":"2003-10-01",
    "date:inception_upper":"2003-10-31",
    "iso:country":"GB",
    "wof:name":"WA7 4RF",
    "wof:placetype":"postalcode"
},
  "geometry": {"coordinates":[-2.734887,53.321596],"type":"Point"}
}