{
  "type": "Feature",
  "properties": {
    "iso:country": "GB",
    "wof:name": "WA7 4RF",
    "wof:placetype": "postalcode"
  },
  "geometry": {"coordinates":[-2.734887,53.321596],"type":"Point"}
}
