{
  "type": "Feature",
  "properties": {
    "iso:country":"GB",
    "wof:name":"WA7 4RF",
    "wof:placetype":"postalcode"
},
  "geometry": {"coordinates":[-2.7348871087725,53.32159627641271],"type":"Point"}
}