{
  "type": "Feature",
  "properties": {
    "iso:country": "GB",
    "wof:name": "SO15 5FH",
    "wof:placetype": "postalcode"
  },
  "geometry": {"coordinates":[-1.421125,50.920811],"type":"Point"}
}
