{
  "type": "Feature",
  "properties": {
    "iso:country":"GB",
    "wof:name":"RG41 5LQ",
    "wof:placetype":"postalcode"
},
  "geometry": {"coordinates":[-0.88564127689862,51.43350285740043],"type":"Point"}
}