{
  "type": "Feature",
  "properties": {
    "date:inception_lower":"2012-08-01",
    "date:inception_upper":"2012-08-31",
    "iso:country":"GB",
    "wof:name":"LE1 5AE",
    "wof:placetype":"postalcode"
},
  "geometry": {"coordinates":[-1.133698,52.635117],"type":"Point"}
}