{
  "type": "Feature",
  "properties": {
    "date:inception_lower":"2017-02-01",
    "date:inception_upper":"2017-02-28",
    "iso:country":"GB",
    "wof:name":"FK2 0XW",
    "wof:placetype":"postalcode"
},
  "geometry": {"coordinates":[-3.747178,55.980675],"type":"Point"}
}