{
  "type": "Feature",
  "properties": {
    "iso:country": "GB",
    "wof:name": "SL8 5NF",
    "wof:placetype": "postalcode"
  },
  "geometry": {"coordinates":[-0.706569,51.582477],"type":"Point"}
}
