{
  "type": "Feature",
  "properties": {
    "iso:country":"GB",
    "wof:name":"SL8 5NF",
    "wof:placetype":"postalcode"
},
  "geometry": {"coordinates":[-0.70656919165557,51.58247736221791],"type":"Point"}
}