{
  "type": "Feature",
  "properties": {
    "iso:country": "GB",
    "wof:name": "BA5 2LT",
    "wof:placetype": "postalcode"
  },
  "geometry": {"coordinates":[-2.657174,51.21382],"type":"Point"}
}
