{
  "type": "Feature",
  "properties": {
    "iso:country":"GB",
    "wof:name":"BA5 2LT",
    "wof:placetype":"postalcode"
},
  "geometry": {"coordinates":[-2.65717430082781,51.21382021574526],"type":"Point"}
}