{
  "type": "Feature",
  "properties": {
    "date:inception_lower": "2018-03-01",
    "date:inception_upper": "2018-03-01",
    "iso:country": "GB",
    "wof:name": "NN6 0FN",
    "wof:placetype": "postalcode"
  },
  "geometry": {"coordinates":[-0.753649,52.273426],"type":"Point"}
}
