{
  "type": "Feature",
  "properties": {
    "iso:country": "GB",
    "wof:name": "BN3 5NL",
    "wof:placetype": "postalcode"
  },
  "geometry": {"coordinates":[-0.19618,50.833381],"type":"Point"}
}
