{
  "type": "Feature",
  "properties": {
    "date:inception_lower": "2018-04-01",
    "date:inception_upper": "2018-04-01",
    "iso:country": "GB",
    "wof:name": "EX39 3FQ",
    "wof:placetype": "postalcode"
  },
  "geometry": {"coordinates":[-4.209543,51.03631],"type":"Point"}
}
