{
  "type": "Feature",
  "properties": {
    "iso:country":"GB",
    "wof:name":"TA16 5PW",
    "wof:placetype":"postalcode"
},
  "geometry": {"coordinates":[-2.78633202803089,50.9151888843474],"type":"Point"}
}