{
  "type": "Feature",
  "properties": {
    "iso:country":"GB",
    "wof:name":"CB6 2PA",
    "wof:placetype":"postalcode"
},
  "geometry": {"coordinates":[0.09746674002403,52.3846264689039],"type":"Point"}
}