{
  "type": "Feature",
  "properties": {
    "date:inception_lower":"1980-01-01",
    "date:inception_upper":"1980-01-31",
    "iso:country":"GB",
    "wof:name":"CB6 2PA",
    "wof:placetype":"postalcode"
},
  "geometry": {"coordinates":[0.097467,52.384626],"type":"Point"}
}