{
  "type": "Feature",
  "properties": {
    "iso:country": "GB",
    "wof:name": "DN15 6EN",
    "wof:placetype": "postalcode"
  },
  "geometry": {"coordinates":[-0.651041,53.591397],"type":"Point"}
}
