{
  "type": "Feature",
  "properties": {
    "iso:country":"GB",
    "wof:name":"TA9 4NJ",
    "wof:placetype":"postalcode"
},
  "geometry": {"coordinates":[-2.88077711105935,51.21835714489567],"type":"Point"}
}