{
  "type": "Feature",
  "properties": {
    "date:inception_lower":"1980-01-01",
    "date:inception_upper":"1980-01-31",
    "iso:country":"GB",
    "wof:name":"TA9 4NJ",
    "wof:placetype":"postalcode"
},
  "geometry": {"coordinates":[-2.880777,51.218357],"type":"Point"}
}