{
  "type": "Feature",
  "properties": {
    "date:inception_lower": "1980-01-01",
    "date:inception_upper": "1980-01-01",
    "iso:country": "GB",
    "wof:name": "NG32 1ND",
    "wof:placetype": "postalcode"
  },
  "geometry": {"coordinates":[-0.759183,52.892114],"type":"Point"}
}
