{
  "type": "Feature",
  "properties": {
    "iso:country":"GB",
    "wof:name":"NG32 1ND",
    "wof:placetype":"postalcode"
},
  "geometry": {"coordinates":[-0.75918307817817,52.8921137719505],"type":"Point"}
}