{
  "type": "Feature",
  "properties": {
    "iso:country":"GB",
    "wof:name":"PR3 2GL",
    "wof:placetype":"postalcode"
},
  "geometry": {"coordinates":[-2.57983631289124,53.88501590967057],"type":"Point"}
}