{
  "type": "Feature",
  "properties": {
    "iso:country": "GB",
    "wof:name": "PR3 2GL",
    "wof:placetype": "postalcode"
  },
  "geometry": {"coordinates":[-2.579836,53.885016],"type":"Point"}
}
