{
  "type": "Feature",
  "properties": {
    "date:inception_lower":"2015-09-01",
    "date:inception_upper":"2015-09-30",
    "iso:country":"GB",
    "wof:name":"WA8 2ED",
    "wof:placetype":"postalcode"
},
  "geometry": {"coordinates":[-2.731682,53.363288],"type":"Point"}
}