{
  "type": "Feature",
  "properties": {
    "date:inception_lower":"2005-09-01",
    "date:inception_upper":"2005-09-30",
    "iso:country":"GB",
    "wof:name":"LS12 5DE",
    "wof:placetype":"postalcode"
},
  "geometry": {"coordinates":[-1.604169,53.781099],"type":"Point"}
}