{
  "type": "Feature",
  "properties": {
    "iso:country": "GB",
    "wof:name": "LS12 5DE",
    "wof:placetype": "postalcode"
  },
  "geometry": {"coordinates":[-1.604169,53.781099],"type":"Point"}
}
