{
  "type": "Feature",
  "properties": {
    "iso:country":"GB",
    "wof:name":"NN6 0QE",
    "wof:placetype":"postalcode"
},
  "geometry": {"coordinates":[-0.78650170815346,52.26464599456853],"type":"Point"}
}