{
  "type": "Feature",
  "properties": {
    "date:inception_lower": "1985-04-01",
    "date:inception_upper": "1985-04-01",
    "iso:country": "GB",
    "wof:name": "S81 8DN",
    "wof:placetype": "postalcode"
  },
  "geometry": {"coordinates":[-1.058235,53.374754],"type":"Point"}
}
