{
  "type": "Feature",
  "properties": {
    "iso:country":"GB",
    "wof:name":"S81 8DN",
    "wof:placetype":"postalcode"
},
  "geometry": {"coordinates":[-1.05823540556723,53.37475439142182],"type":"Point"}
}