{
  "type": "Feature",
  "properties": {
    "iso:country": "GB",
    "wof:name": "WR3 7RX",
    "wof:placetype": "postalcode"
  },
  "geometry": {"coordinates":[-2.202139,52.234992],"type":"Point"}
}
