{
  "type": "Feature",
  "properties": {
    "iso:country":"GB",
    "wof:name":"WR3 7RX",
    "wof:placetype":"postalcode"
},
  "geometry": {"coordinates":[-2.2022029812594,52.23504090795644],"type":"Point"}
}