{
  "type": "Feature",
  "properties": {
    "iso:country":"GB",
    "wof:name":"NG7 2EW",
    "wof:placetype":"postalcode"
},
  "geometry": {"coordinates":[-1.17531092557079,52.94799611665526],"type":"Point"}
}