{
  "type": "Feature",
  "properties": {
    "iso:country":"GB",
    "wof:name":"DY9 0HP",
    "wof:placetype":"postalcode"
},
  "geometry": {"coordinates":[-2.14408710432929,52.41146015870194],"type":"Point"}
}