{
  "type": "Feature",
  "properties": {
    "iso:country":"GB",
    "wof:name":"CT14 6NQ",
    "wof:placetype":"postalcode"
},
  "geometry": {"coordinates":[1.40374420970748,51.22980866548437],"type":"Point"}
}