{
  "type": "Feature",
  "properties": {
    "date:inception_lower": "2002-06-01",
    "date:inception_upper": "2002-06-01",
    "iso:country": "GB",
    "wof:name": "CT14 6NQ",
    "wof:placetype": "postalcode"
  },
  "geometry": {"coordinates":[1.403774,51.229835],"type":"Point"}
}
