{
  "type": "Feature",
  "properties": {
    "date:inception_lower": "1980-01-01",
    "date:inception_upper": "1980-01-01",
    "iso:country": "GB",
    "wof:name": "ML5 3JG",
    "wof:placetype": "postalcode"
  },
  "geometry": {"coordinates":[-4.016532,55.86637],"type":"Point"}
}
