{
  "type": "Feature",
  "properties": {
    "iso:country":"GB",
    "wof:name":"ML5 3JG",
    "wof:placetype":"postalcode"
},
  "geometry": {"coordinates":[-4.01653209318793,55.86636958479825],"type":"Point"}
}