{
  "type": "Feature",
  "properties": {
    "date:inception_lower": "1992-01-01",
    "date:inception_upper": "1992-01-01",
    "iso:country": "GB",
    "wof:name": "CV11 4XZ",
    "wof:placetype": "postalcode"
  },
  "geometry": {"coordinates":[-1.451558,52.505815],"type":"Point"}
}
