{
  "type": "Feature",
  "properties": {
    "iso:country":"GB",
    "wof:name":"CV6 2AP",
    "wof:placetype":"postalcode"
},
  "geometry": {"coordinates":[-1.53231576983397,52.4287394780869],"type":"Point"}
}