{
  "type": "Feature",
  "properties": {
    "iso:country":"GB",
    "wof:name":"CM18 6RT",
    "wof:placetype":"postalcode"
},
  "geometry": {"coordinates":[0.09473961413608,51.75882832550667],"type":"Point"}
}