{
  "type": "Feature",
  "properties": {
    "iso:country": "GB",
    "wof:name": "GU1 1TY",
    "wof:placetype": "postalcode"
  },
  "geometry": {"coordinates":[-0.553784,51.24693],"type":"Point"}
}
