{
  "type": "Feature",
  "properties": {
    "iso:country":"GB",
    "wof:name":"GU1 1TY",
    "wof:placetype":"postalcode"
},
  "geometry": {"coordinates":[-0.5537836687726,51.2469297483963],"type":"Point"}
}