{
  "type": "Feature",
  "properties": {
    "iso:country":"GB",
    "wof:name":"CM9 8DU",
    "wof:placetype":"postalcode"
},
  "geometry": {"coordinates":[0.70913243378653,51.78186374740123],"type":"Point"}
}