{
  "type": "Feature",
  "properties": {
    "date:inception_lower": "1980-01-01",
    "date:inception_upper": "1980-01-01",
    "iso:country": "GB",
    "wof:name": "CM9 8DU",
    "wof:placetype": "postalcode"
  },
  "geometry": {"coordinates":[0.709132,51.781864],"type":"Point"}
}
