{
  "type": "Feature",
  "properties": {
    "date:inception_lower":"2004-07-01",
    "date:inception_upper":"2004-07-31",
    "iso:country":"GB",
    "wof:name":"BH25 6QD",
    "wof:placetype":"postalcode"
},
  "geometry": {"coordinates":[-1.661856,50.746455],"type":"Point"}
}