{
  "type": "Feature",
  "properties": {
    "iso:country":"GB",
    "wof:name":"SG4 0NG",
    "wof:placetype":"postalcode"
},
  "geometry": {"coordinates":[-0.24660875454682,51.95118747931645],"type":"Point"}
}