{
  "type": "Feature",
  "properties": {
    "iso:country": "GB",
    "wof:name": "SG4 0NG",
    "wof:placetype": "postalcode"
  },
  "geometry": {"coordinates":[-0.246609,51.951187],"type":"Point"}
}
