{
  "type": "Feature",
  "properties": {
    "iso:country":"GB",
    "wof:name":"LS8 1HD",
    "wof:placetype":"postalcode"
},
  "geometry": {"coordinates":[-1.51790240294856,53.83833566277],"type":"Point"}
}