{
  "type": "Feature",
  "properties": {
    "iso:country":"GB",
    "wof:name":"SW1V 2TQ",
    "wof:placetype":"postalcode"
},
  "geometry": {"coordinates":[-0.13393115511671,51.49021321608299],"type":"Point"}
}