{
  "type": "Feature",
  "properties": {
    "date:inception_lower": "1980-01-01",
    "date:inception_upper": "1980-01-01",
    "iso:country": "GB",
    "wof:name": "SW1V 2TQ",
    "wof:placetype": "postalcode"
  },
  "geometry": {"coordinates":[-0.133931,51.490213],"type":"Point"}
}
