{
  "type": "Feature",
  "properties": {
    "iso:country": "GB",
    "wof:name": "SW1V 2TQ",
    "wof:placetype": "postalcode"
  },
  "geometry": {"coordinates":[-0.133931,51.490213],"type":"Point"}
}
