{
  "type": "Feature",
  "properties": {
    "iso:country":"GB",
    "wof:name":"L39 4XD",
    "wof:placetype":"postalcode"
},
  "geometry": {"coordinates":[-2.87120099308973,53.56140740330874],"type":"Point"}
}