{
  "type": "Feature",
  "properties": {
    "iso:country":"GB",
    "wof:name":"CO10 9EN",
    "wof:placetype":"postalcode"
},
  "geometry": {"coordinates":[0.72102917349404,52.07693540265402],"type":"Point"}
}