{
  "type": "Feature",
  "properties": {
    "iso:country": "GB",
    "wof:name": "CO10 9EN",
    "wof:placetype": "postalcode"
  },
  "geometry": {"coordinates":[0.721029,52.076935],"type":"Point"}
}
