{
  "type": "Feature",
  "properties": {
    "iso:country": "GB",
    "wof:name": "NN7 3HS",
    "wof:placetype": "postalcode"
  },
  "geometry": {"coordinates":[-0.95581,52.203974],"type":"Point"}
}
