{
  "type": "Feature",
  "properties": {
    "iso:country":"GB",
    "wof:name":"NN7 3HS",
    "wof:placetype":"postalcode"
},
  "geometry": {"coordinates":[-0.95608835792539,52.20395229159899],"type":"Point"}
}