{
  "type": "Feature",
  "properties": {
    "iso:country":"GB",
    "wof:name":"IP11 0UJ",
    "wof:placetype":"postalcode"
},
  "geometry": {"coordinates":[1.31478482029029,51.99244625952256],"type":"Point"}
}