{
  "type": "Feature",
  "properties": {
    "date:inception_lower": "1980-01-01",
    "date:inception_upper": "1980-01-01",
    "iso:country": "GB",
    "wof:name": "TN37 6RH",
    "wof:placetype": "postalcode"
  },
  "geometry": {"coordinates":[0.558195,50.862791],"type":"Point"}
}
