{
  "type": "Feature",
  "properties": {
    "iso:country":"GB",
    "wof:name":"TN37 6RH",
    "wof:placetype":"postalcode"
},
  "geometry": {"coordinates":[0.5581954001311,50.86279054171739],"type":"Point"}
}