{
  "type": "Feature",
  "properties": {
    "iso:country":"GB",
    "wof:name":"GU21 4PL",
    "wof:placetype":"postalcode"
},
  "geometry": {"coordinates":[-0.57515232273391,51.31904107929202],"type":"Point"}
}