{
  "type": "Feature",
  "properties": {
    "iso:country":"GB",
    "wof:name":"S1 4TA",
    "wof:placetype":"postalcode"
},
  "geometry": {"coordinates":[-1.46991332279634,53.37210487261203],"type":"Point"}
}