{
  "type": "Feature",
  "properties": {
    "date:inception_lower":"2011-06-01",
    "date:inception_upper":"2011-06-30",
    "iso:country":"GB",
    "wof:name":"ML5 1DF",
    "wof:placetype":"postalcode"
},
  "geometry": {"coordinates":[-4.027841,55.85797],"type":"Point"}
}