{
  "type": "Feature",
  "properties": {
    "iso:country":"GB",
    "wof:name":"BA2 4SL",
    "wof:placetype":"postalcode"
},
  "geometry": {"coordinates":[-2.36307832586612,51.3718572646909],"type":"Point"}
}