{
  "type": "Feature",
  "properties": {
    "iso:country": "GB",
    "wof:name": "PE15 8ER",
    "wof:placetype": "postalcode"
  },
  "geometry": {"coordinates":[0.075772,52.557844],"type":"Point"}
}
