{
  "type": "Feature",
  "properties": {
    "iso:country": "GB",
    "wof:name": "MK6 2BU",
    "wof:placetype": "postalcode"
  },
  "geometry": {"coordinates":[-0.742403,52.036074],"type":"Point"}
}
