{
  "type": "Feature",
  "properties": {
    "iso:country":"GB",
    "wof:name":"MK6 2BU",
    "wof:placetype":"postalcode"
},
  "geometry": {"coordinates":[-0.74240320852931,52.03607403031604],"type":"Point"}
}