{
  "type": "Feature",
  "properties": {
    "iso:country": "GB",
    "wof:name": "LL14 6DJ",
    "wof:placetype": "postalcode"
  },
  "geometry": {"coordinates":[-3.038895,52.985966],"type":"Point"}
}
