{
  "type": "Feature",
  "properties": {
    "iso:country":"GB",
    "wof:name":"LL14 6DJ",
    "wof:placetype":"postalcode"
},
  "geometry": {"coordinates":[-3.03889478008261,52.98596575395911],"type":"Point"}
}