{
  "type": "Feature",
  "properties": {
    "date:inception_lower": "1986-06-01",
    "date:inception_upper": "1986-06-01",
    "iso:country": "GB",
    "wof:name": "G32 0BJ",
    "wof:placetype": "postalcode"
  },
  "geometry": {"coordinates":[-4.146954,55.850862],"type":"Point"}
}
