{
  "type": "Feature",
  "properties": {
    "date:inception_lower":"1995-07-01",
    "date:inception_upper":"1995-07-31",
    "iso:country":"GB",
    "wof:name":"CF72 8PU",
    "wof:placetype":"postalcode"
},
  "geometry": {"coordinates":[-3.372699,51.518672],"type":"Point"}
}