{
  "type": "Feature",
  "properties": {
    "iso:country": "GB",
    "wof:name": "CF72 8PU",
    "wof:placetype": "postalcode"
  },
  "geometry": {"coordinates":[-3.372699,51.518672],"type":"Point"}
}
