{
  "type": "Feature",
  "properties": {
    "iso:country":"GB",
    "wof:name":"CF72 8PU",
    "wof:placetype":"postalcode"
},
  "geometry": {"coordinates":[-3.37269945017636,51.51867210658698],"type":"Point"}
}