{
  "type": "Feature",
  "properties": {
    "iso:country":"GB",
    "wof:name":"W5 4QR",
    "wof:placetype":"postalcode"
},
  "geometry": {"coordinates":[-0.30632107348393,51.50083282717234],"type":"Point"}
}