{
  "type": "Feature",
  "properties": {
    "date:inception_lower": "2017-08-01",
    "date:inception_upper": "2017-08-01",
    "iso:country": "GB",
    "wof:name": "GL12 8EJ",
    "wof:placetype": "postalcode"
  },
  "geometry": {"coordinates":[-2.393362,51.629647],"type":"Point"}
}
