{
  "type": "Feature",
  "properties": {
    "iso:country":"GB",
    "wof:name":"HP6 6SP",
    "wof:placetype":"postalcode"
},
  "geometry": {"coordinates":[-0.54984377089171,51.67070887717672],"type":"Point"}
}