{
  "type": "Feature",
  "properties": {
    "iso:country":"GB",
    "wof:name":"GL20 8FE",
    "wof:placetype":"postalcode"
},
  "geometry": {"coordinates":[-2.00582392162713,51.99953705737755],"type":"Point"}
}