{
  "type": "Feature",
  "properties": {
    "date:inception_lower":"2015-09-01",
    "date:inception_upper":"2015-09-30",
    "iso:country":"GB",
    "wof:name":"GL20 8FE",
    "wof:placetype":"postalcode"
},
  "geometry": {"coordinates":[-2.006194,51.999151],"type":"Point"}
}