{
  "type": "Feature",
  "properties": {
    "iso:country":"GB",
    "wof:name":"UB10 9AY",
    "wof:placetype":"postalcode"
},
  "geometry": {"coordinates":[-0.44288121154169,51.54594165952231],"type":"Point"}
}