{
  "type": "Feature",
  "properties": {
    "iso:country":"GB",
    "wof:name":"BL4 0PH",
    "wof:placetype":"postalcode"
},
  "geometry": {"coordinates":[-2.43902584525185,53.54814442567525],"type":"Point"}
}