{
  "type": "Feature",
  "properties": {
    "iso:country":"GB",
    "wof:name":"AL8 6HL",
    "wof:placetype":"postalcode"
},
  "geometry": {"coordinates":[-0.21120895594149,51.79841265955173],"type":"Point"}
}