{
  "type": "Feature",
  "properties": {
    "iso:country": "GB",
    "wof:name": "AL8 6HL",
    "wof:placetype": "postalcode"
  },
  "geometry": {"coordinates":[-0.211209,51.798413],"type":"Point"}
}
