{
  "type": "Feature",
  "properties": {
    "date:inception_lower": "1980-01-01",
    "date:inception_upper": "1980-01-01",
    "iso:country": "GB",
    "wof:name": "PE37 7QW",
    "wof:placetype": "postalcode"
  },
  "geometry": {"coordinates":[0.690526,52.649236],"type":"Point"}
}
