{
  "type": "Feature",
  "properties": {
    "date:inception_lower": "1986-07-01",
    "date:inception_upper": "1986-07-01",
    "iso:country": "GB",
    "wof:name": "N20 8QJ",
    "wof:placetype": "postalcode"
  },
  "geometry": {"coordinates":[-0.183659,51.632178],"type":"Point"}
}
