{
  "type": "Feature",
  "properties": {
    "iso:country":"GB",
    "wof:name":"N20 8QJ",
    "wof:placetype":"postalcode"
},
  "geometry": {"coordinates":[-0.18375351792971,51.6322479192617],"type":"Point"}
}