{
  "type": "Feature",
  "properties": {
    "iso:country":"GB",
    "wof:name":"CV47 7SS",
    "wof:placetype":"postalcode"
},
  "geometry": {"coordinates":[-1.32081449546496,52.2186166311624],"type":"Point"}
}