{
  "type": "Feature",
  "properties": {
    "date:inception_lower":"1980-01-01",
    "date:inception_upper":"1980-01-31",
    "iso:country":"GB",
    "wof:name":"TD12 4TA",
    "wof:placetype":"postalcode"
},
  "geometry": {"coordinates":[-2.136005,55.637092],"type":"Point"}
}