{
  "type": "Feature",
  "properties": {
    "iso:country":"GB",
    "wof:name":"TD12 4TA",
    "wof:placetype":"postalcode"
},
  "geometry": {"coordinates":[-2.13599594496437,55.63709394799673],"type":"Point"}
}