{
  "type": "Feature",
  "properties": {
    "iso:country": "GB",
    "wof:name": "TD12 4TA",
    "wof:placetype": "postalcode"
  },
  "geometry": {"coordinates":[-2.136005,55.637092],"type":"Point"}
}
