{
  "type": "Feature",
  "properties": {
    "iso:country": "GB",
    "wof:name": "CM0 8EA",
    "wof:placetype": "postalcode"
  },
  "geometry": {"coordinates":[0.817936,51.629083],"type":"Point"}
}
