{
  "type": "Feature",
  "properties": {
    "date:inception_lower": "1980-01-01",
    "date:inception_upper": "1980-01-01",
    "iso:country": "GB",
    "wof:name": "CM0 8EA",
    "wof:placetype": "postalcode"
  },
  "geometry": {"coordinates":[0.817936,51.629083],"type":"Point"}
}
