{
  "type": "Feature",
  "properties": {
    "iso:country":"GB",
    "wof:name":"SY5 0LD",
    "wof:placetype":"postalcode"
},
  "geometry": {"coordinates":[-2.97023744975357,52.5961267951745],"type":"Point"}
}