{
  "type": "Feature",
  "properties": {
    "iso:country": "GB",
    "wof:name": "SY5 0LD",
    "wof:placetype": "postalcode"
  },
  "geometry": {"coordinates":[-2.970237,52.596127],"type":"Point"}
}
