{
  "type": "Feature",
  "properties": {
    "iso:country":"GB",
    "wof:name":"LE18 4ZL",
    "wof:placetype":"postalcode"
},
  "geometry": {"coordinates":[-1.12209760206658,52.57755864008998],"type":"Point"}
}