{
  "type": "Feature",
  "properties": {
    "date:inception_lower": "1999-06-01",
    "date:inception_upper": "1999-06-01",
    "iso:country": "GB",
    "wof:name": "B61 0JH",
    "wof:placetype": "postalcode"
  },
  "geometry": {"coordinates":[-2.053065,52.362392],"type":"Point"}
}
