{
  "type": "Feature",
  "properties": {
    "iso:country":"GB",
    "wof:name":"HA7 4AF",
    "wof:placetype":"postalcode"
},
  "geometry": {"coordinates":[-0.31411337076696,51.61793429166421],"type":"Point"}
}