{
  "type": "Feature",
  "properties": {
    "date:inception_lower": "1980-01-01",
    "date:inception_upper": "1980-01-01",
    "iso:country": "GB",
    "wof:name": "HA7 4AF",
    "wof:placetype": "postalcode"
  },
  "geometry": {"coordinates":[-0.314113,51.617934],"type":"Point"}
}
