{
  "type": "Feature",
  "properties": {
    "iso:country":"GB",
    "wof:name":"ML1 2HB",
    "wof:placetype":"postalcode"
},
  "geometry": {"coordinates":[-3.96805274963416,55.77458062002998],"type":"Point"}
}