{
  "type": "Feature",
  "properties": {
    "date:inception_lower": "2010-03-01",
    "date:inception_upper": "2010-03-01",
    "iso:country": "GB",
    "wof:name": "HG4 3HG",
    "wof:placetype": "postalcode"
  },
  "geometry": {"coordinates":[-1.561619,54.188763],"type":"Point"}
}
