{
  "type": "Feature",
  "properties": {
    "iso:country": "GB",
    "wof:name": "HG4 3HG",
    "wof:placetype": "postalcode"
  },
  "geometry": {"coordinates":[-1.561619,54.188763],"type":"Point"}
}
