{
  "type": "Feature",
  "properties": {
    "iso:country":"GB",
    "wof:name":"BB10 3HN",
    "wof:placetype":"postalcode"
},
  "geometry": {"coordinates":[-2.22906016189267,53.80427367680258],"type":"Point"}
}