{
  "type": "Feature",
  "properties": {
    "date:inception_lower":"1980-01-01",
    "date:inception_upper":"1980-01-31",
    "iso:country":"GB",
    "wof:name":"BB10 3HN",
    "wof:placetype":"postalcode"
},
  "geometry": {"coordinates":[-2.22906,53.804274],"type":"Point"}
}