{
  "type": "Feature",
  "properties": {
    "iso:country":"GB",
    "wof:name":"W12 7EY",
    "wof:placetype":"postalcode"
},
  "geometry": {"coordinates":[-0.22885858338601,51.50841125838666],"type":"Point"}
}