{
  "type": "Feature",
  "properties": {
    "iso:country": "GB",
    "wof:name": "W12 7EY",
    "wof:placetype": "postalcode"
  },
  "geometry": {"coordinates":[-0.228859,51.508411],"type":"Point"}
}
