{
  "type": "Feature",
  "properties": {
    "iso:country":"GB",
    "wof:name":"BN21 4UH",
    "wof:placetype":"postalcode"
},
  "geometry": {"coordinates":[0.27859204085033,50.76669400540238],"type":"Point"}
}