{
  "type": "Feature",
  "properties": {
    "date:inception_lower": "1983-11-01",
    "date:inception_upper": "1983-11-01",
    "iso:country": "GB",
    "wof:name": "EH22 1DH",
    "wof:placetype": "postalcode"
  },
  "geometry": {"coordinates":[-3.069131,55.895104],"type":"Point"}
}
