{
  "type": "Feature",
  "properties": {
    "iso:country": "GB",
    "wof:name": "HG5 0SH",
    "wof:placetype": "postalcode"
  },
  "geometry": {"coordinates":[-1.45254,54.006147],"type":"Point"}
}
