{
  "type": "Feature",
  "properties": {
    "date:inception_lower":"1986-04-01",
    "date:inception_upper":"1986-04-30",
    "iso:country":"GB",
    "wof:name":"HG5 0SH",
    "wof:placetype":"postalcode"
},
  "geometry": {"coordinates":[-1.45254,54.006147],"type":"Point"}
}