{
  "type": "Feature",
  "properties": {
    "iso:country":"GB",
    "wof:name":"CO10 2QG",
    "wof:placetype":"postalcode"
},
  "geometry": {"coordinates":[0.74310697658102,52.04401219989132],"type":"Point"}
}