{
  "type": "Feature",
  "properties": {
    "iso:country":"GB",
    "wof:name":"S64 0QB",
    "wof:placetype":"postalcode"
},
  "geometry": {"coordinates":[-1.27343781039188,53.50104792030249],"type":"Point"}
}