{
  "type": "Feature",
  "properties": {
    "iso:country":"GB",
    "wof:name":"NE61 3SD",
    "wof:placetype":"postalcode"
},
  "geometry": {"coordinates":[-1.74571851429615,55.19410678828064],"type":"Point"}
}