{
  "type": "Feature",
  "properties": {
    "iso:country": "GB",
    "wof:name": "NE61 3SD",
    "wof:placetype": "postalcode"
  },
  "geometry": {"coordinates":[-1.745718,55.194107],"type":"Point"}
}
