{
  "type": "Feature",
  "properties": {
    "iso:country": "GB",
    "wof:name": "EX22 7TW",
    "wof:placetype": "postalcode"
  },
  "geometry": {"coordinates":[-4.406444,50.898162],"type":"Point"}
}
