{
  "type": "Feature",
  "properties": {
    "iso:country":"GB",
    "wof:name":"KT6 7LP",
    "wof:placetype":"postalcode"
},
  "geometry": {"coordinates":[-0.29893950020944,51.37392360568876],"type":"Point"}
}