{
  "type": "Feature",
  "properties": {
    "iso:country": "GB",
    "wof:name": "NR10 3HR",
    "wof:placetype": "postalcode"
  },
  "geometry": {"coordinates":[1.284284,52.690474],"type":"Point"}
}
