{
  "type": "Feature",
  "properties": {
    "date:inception_lower":"1980-01-01",
    "date:inception_upper":"1980-01-31",
    "iso:country":"GB",
    "wof:name":"NR10 3HR",
    "wof:placetype":"postalcode"
},
  "geometry": {"coordinates":[1.284284,52.690474],"type":"Point"}
}