{
  "type": "Feature",
  "properties": {
    "iso:country":"GB",
    "wof:name":"SY14 8HA",
    "wof:placetype":"postalcode"
},
  "geometry": {"coordinates":[-2.67557295164426,53.05319224106628],"type":"Point"}
}