{
  "type": "Feature",
  "properties": {
    "iso:country": "GB",
    "wof:name": "SY14 8HA",
    "wof:placetype": "postalcode"
  },
  "geometry": {"coordinates":[-2.675411,53.053353],"type":"Point"}
}
