{
  "type": "Feature",
  "properties": {
    "iso:country":"GB",
    "wof:name":"WA7 2TP",
    "wof:placetype":"postalcode"
},
  "geometry": {"coordinates":[-2.68784704250988,53.32122965188812],"type":"Point"}
}