{
  "type": "Feature",
  "properties": {
    "iso:country":"GB",
    "wof:name":"CT10 1DF",
    "wof:placetype":"postalcode"
},
  "geometry": {"coordinates":[1.43856084077281,51.36527565889607],"type":"Point"}
}