{
  "type": "Feature",
  "properties": {
    "iso:country":"GB",
    "wof:name":"TF7 4JG",
    "wof:placetype":"postalcode"
},
  "geometry": {"coordinates":[-2.43299049367698,52.6309815962235],"type":"Point"}
}