{
  "type": "Feature",
  "properties": {
    "iso:country":"GB",
    "wof:name":"RM3 0FQ",
    "wof:placetype":"postalcode"
},
  "geometry": {"coordinates":[0.22545330155932,51.59051815949543],"type":"Point"}
}