{
  "type": "Feature",
  "properties": {
    "iso:country": "GB",
    "wof:name": "RM3 0FQ",
    "wof:placetype": "postalcode"
  },
  "geometry": {"coordinates":[0.225453,51.590584],"type":"Point"}
}
