{
  "type": "Feature",
  "properties": {
    "iso:country":"GB",
    "wof:name":"PR4 4XP",
    "wof:placetype":"postalcode"
},
  "geometry": {"coordinates":[-2.74239017829927,53.71726379366075],"type":"Point"}
}