{
  "type": "Feature",
  "properties": {
    "iso:country":"GB",
    "wof:name":"MK4 4JN",
    "wof:placetype":"postalcode"
},
  "geometry": {"coordinates":[-0.80904189050751,52.00864208304549],"type":"Point"}
}