{
  "type": "Feature",
  "properties": {
    "iso:country": "GB",
    "wof:name": "MK4 4JN",
    "wof:placetype": "postalcode"
  },
  "geometry": {"coordinates":[-0.809042,52.008642],"type":"Point"}
}
