{
  "type": "Feature",
  "properties": {
    "date:inception_lower": "1996-12-01",
    "date:inception_upper": "1996-12-01",
    "iso:country": "GB",
    "wof:name": "DY1 2GQ",
    "wof:placetype": "postalcode"
  },
  "geometry": {"coordinates":[-2.116923,52.5205],"type":"Point"}
}
