{
  "type": "Feature",
  "properties": {
    "iso:country": "GB",
    "wof:name": "DY1 2GQ",
    "wof:placetype": "postalcode"
  },
  "geometry": {"coordinates":[-2.116923,52.5205],"type":"Point"}
}
