{
  "type": "Feature",
  "properties": {
    "iso:country":"GB",
    "wof:name":"BD22 8ER",
    "wof:placetype":"postalcode"
},
  "geometry": {"coordinates":[-1.95532219176713,53.83279664093911],"type":"Point"}
}