{
  "type": "Feature",
  "properties": {
    "date:inception_lower": "1992-08-01",
    "date:inception_upper": "1992-08-01",
    "iso:country": "GB",
    "wof:name": "HU18 1TW",
    "wof:placetype": "postalcode"
  },
  "geometry": {"coordinates":[-0.165112,53.901054],"type":"Point"}
}
