{
  "type": "Feature",
  "properties": {
    "iso:country":"GB",
    "wof:name":"HU18 1TW",
    "wof:placetype":"postalcode"
},
  "geometry": {"coordinates":[-0.16511220046261,53.90105352852193],"type":"Point"}
}