{
  "type": "Feature",
  "properties": {
    "iso:country":"GB",
    "wof:name":"B16 9DQ",
    "wof:placetype":"postalcode"
},
  "geometry": {"coordinates":[-1.93648759649043,52.4751357151006],"type":"Point"}
}