{
  "type": "Feature",
  "properties": {
    "iso:country": "GB",
    "wof:name": "RG42 6JG",
    "wof:placetype": "postalcode"
  },
  "geometry": {"coordinates":[-0.723742,51.447868],"type":"Point"}
}
