{
  "type": "Feature",
  "properties": {
    "iso:country":"GB",
    "wof:name":"RG42 6JG",
    "wof:placetype":"postalcode"
},
  "geometry": {"coordinates":[-0.72375901145986,51.44786732990013],"type":"Point"}
}