{
  "type": "Feature",
  "properties": {
    "iso:country":"GB",
    "wof:name":"TF13 6LP",
    "wof:placetype":"postalcode"
},
  "geometry": {"coordinates":[-2.6704129810037,52.5007073928576],"type":"Point"}
}