{
  "type": "Feature",
  "properties": {
    "iso:country":"GB",
    "wof:name":"PR1 9TQ",
    "wof:placetype":"postalcode"
},
  "geometry": {"coordinates":[-2.70013521739477,53.72953555511751],"type":"Point"}
}