{
  "type": "Feature",
  "properties": {
    "iso:country":"GB",
    "wof:name":"NG10 5HH",
    "wof:placetype":"postalcode"
},
  "geometry": {"coordinates":[-1.30163649440468,52.92027275489601],"type":"Point"}
}