{
  "type": "Feature",
  "properties": {
    "iso:country": "GB",
    "wof:name": "NG10 5HH",
    "wof:placetype": "postalcode"
  },
  "geometry": {"coordinates":[-1.301636,52.920273],"type":"Point"}
}
