{
  "type": "Feature",
  "properties": {
    "date:inception_lower": "2024-05-01",
    "date:inception_upper": "2024-05-01",
    "iso:country": "GB",
    "wof:name": "GU7 2FZ",
    "wof:placetype": "postalcode"
  },
  "geometry": {"coordinates":[-0.618667,51.189106],"type":"Point"}
}
