{
  "type": "Feature",
  "properties": {
    "iso:country":"GB",
    "wof:name":"G82 1QR",
    "wof:placetype":"postalcode"
},
  "geometry": {"coordinates":[-4.56665998855534,55.94441179870545],"type":"Point"}
}