{
  "type": "Feature",
  "properties": {
    "date:inception_lower":"1980-01-01",
    "date:inception_upper":"1980-01-31",
    "iso:country":"GB",
    "wof:name":"BA5 2UX",
    "wof:placetype":"postalcode"
},
  "geometry": {"coordinates":[-2.640581,51.211781],"type":"Point"}
}