{
  "type": "Feature",
  "properties": {
    "iso:country":"GB",
    "wof:name":"BA5 2UX",
    "wof:placetype":"postalcode"
},
  "geometry": {"coordinates":[-2.64058137876637,51.21178114489368],"type":"Point"}
}