{
  "type": "Feature",
  "properties": {
    "iso:country":"GB",
    "wof:name":"LA12 8NU",
    "wof:placetype":"postalcode"
},
  "geometry": {"coordinates":[-2.97004236419983,54.26334210774714],"type":"Point"}
}