{
  "type": "Feature",
  "properties": {
    "iso:country":"GB",
    "wof:name":"WF14 0LR",
    "wof:placetype":"postalcode"
},
  "geometry": {"coordinates":[-1.70465832555736,53.68812092318748],"type":"Point"}
}