{
  "type": "Feature",
  "properties": {
    "iso:country": "GB",
    "wof:name": "WF14 0LR",
    "wof:placetype": "postalcode"
  },
  "geometry": {"coordinates":[-1.704658,53.688121],"type":"Point"}
}
