{
  "type": "Feature",
  "properties": {
    "iso:country": "GB",
    "wof:name": "WR11 7QW",
    "wof:placetype": "postalcode"
  },
  "geometry": {"coordinates":[-1.988426,52.024144],"type":"Point"}
}
