{
  "type": "Feature",
  "properties": {
    "iso:country":"GB",
    "wof:name":"WR11 7QW",
    "wof:placetype":"postalcode"
},
  "geometry": {"coordinates":[-1.98842597797813,52.02414415103296],"type":"Point"}
}