{
  "type": "Feature",
  "properties": {
    "iso:country": "GB",
    "wof:name": "LE4 2AX",
    "wof:placetype": "postalcode"
  },
  "geometry": {"coordinates":[-1.149324,52.680901],"type":"Point"}
}
