{
  "type": "Feature",
  "properties": {
    "iso:country":"GB",
    "wof:name":"DL16 6AR",
    "wof:placetype":"postalcode"
},
  "geometry": {"coordinates":[-1.60537968873624,54.69984644021525],"type":"Point"}
}