{
  "type": "Feature",
  "properties": {
    "date:inception_lower": "1980-01-01",
    "date:inception_upper": "1980-01-01",
    "iso:country": "GB",
    "wof:name": "DL16 6AR",
    "wof:placetype": "postalcode"
  },
  "geometry": {"coordinates":[-1.60538,54.699846],"type":"Point"}
}
