{
  "type": "Feature",
  "properties": {
    "iso:country":"GB",
    "wof:name":"GU20 6AD",
    "wof:placetype":"postalcode"
},
  "geometry": {"coordinates":[-0.66331297574429,51.37162385038629],"type":"Point"}
}