{
  "type": "Feature",
  "properties": {
    "iso:country": "GB",
    "wof:name": "PR9 0BW",
    "wof:placetype": "postalcode"
  },
  "geometry": {"coordinates":[-2.999724,53.652246],"type":"Point"}
}
