{
  "type": "Feature",
  "properties": {
    "iso:country": "GB",
    "wof:name": "SO22 5QU",
    "wof:placetype": "postalcode"
  },
  "geometry": {"coordinates":[-1.343636,51.057904],"type":"Point"}
}
