{
  "type": "Feature",
  "properties": {
    "iso:country":"GB",
    "wof:name":"SO22 5QU",
    "wof:placetype":"postalcode"
},
  "geometry": {"coordinates":[-1.34363653290794,51.05790384469855],"type":"Point"}
}