{
  "type": "Feature",
  "properties": {
    "iso:country": "GB",
    "wof:name": "CA7 8ES",
    "wof:placetype": "postalcode"
  },
  "geometry": {"coordinates":[-3.057149,54.751119],"type":"Point"}
}
