{
  "type": "Feature",
  "properties": {
    "iso:country":"GB",
    "wof:name":"CA7 8ES",
    "wof:placetype":"postalcode"
},
  "geometry": {"coordinates":[-3.05714928554941,54.75111905894786],"type":"Point"}
}