{
  "type": "Feature",
  "properties": {
    "date:inception_lower":"1994-05-01",
    "date:inception_upper":"1994-05-31",
    "iso:country":"GB",
    "wof:name":"CA7 8ES",
    "wof:placetype":"postalcode"
},
  "geometry": {"coordinates":[-3.057149,54.751119],"type":"Point"}
}