{
  "type": "Feature",
  "properties": {
    "iso:country": "GB",
    "wof:name": "LL11 3LD",
    "wof:placetype": "postalcode"
  },
  "geometry": {"coordinates":[-3.058559,53.056037],"type":"Point"}
}
