{
  "type": "Feature",
  "properties": {
    "date:inception_lower": "1980-01-01",
    "date:inception_upper": "1980-01-01",
    "iso:country": "GB",
    "wof:name": "DA1 4BX",
    "wof:placetype": "postalcode"
  },
  "geometry": {"coordinates":[0.168787,51.45156],"type":"Point"}
}
