{
  "type": "Feature",
  "properties": {
    "iso:country":"GB",
    "wof:name":"DA1 4BX",
    "wof:placetype":"postalcode"
},
  "geometry": {"coordinates":[0.16878681394811,51.45156002880825],"type":"Point"}
}