{
  "type": "Feature",
  "properties": {
    "iso:country":"GB",
    "wof:name":"SE6 2TA",
    "wof:placetype":"postalcode"
},
  "geometry": {"coordinates":[-0.0166662292958,51.43131954703217],"type":"Point"}
}