{
  "type": "Feature",
  "properties": {
    "iso:country":"GB",
    "wof:name":"MK42 7HF",
    "wof:placetype":"postalcode"
},
  "geometry": {"coordinates":[-0.50294177562525,52.10904501587907],"type":"Point"}
}