{
  "type": "Feature",
  "properties": {
    "date:inception_lower": "1980-01-01",
    "date:inception_upper": "1980-01-01",
    "iso:country": "GB",
    "wof:name": "S66 8HT",
    "wof:placetype": "postalcode"
  },
  "geometry": {"coordinates":[-1.21445,53.427345],"type":"Point"}
}
