{
  "type": "Feature",
  "properties": {
    "iso:country":"GB",
    "wof:name":"S66 8HT",
    "wof:placetype":"postalcode"
},
  "geometry": {"coordinates":[-1.21445047156946,53.42734510814394],"type":"Point"}
}