{
  "type": "Feature",
  "properties": {
    "iso:country": "GB",
    "wof:name": "EH17 8TL",
    "wof:placetype": "postalcode"
  },
  "geometry": {"coordinates":[-3.127005,55.906737],"type":"Point"}
}
