{
  "type": "Feature",
  "properties": {
    "iso:country": "GB",
    "wof:name": "MK1 1ET",
    "wof:placetype": "postalcode"
  },
  "geometry": {"coordinates":[-0.731384,52.009523],"type":"Point"}
}
