{
  "type": "Feature",
  "properties": {
    "date:inception_lower": "2010-02-01",
    "date:inception_upper": "2010-02-01",
    "iso:country": "GB",
    "wof:name": "MK1 1ET",
    "wof:placetype": "postalcode"
  },
  "geometry": {"coordinates":[-0.731925,52.010464],"type":"Point"}
}
