{
  "type": "Feature",
  "properties": {
    "iso:country": "GB",
    "wof:name": "SW11 4EA",
    "wof:placetype": "postalcode"
  },
  "geometry": {"coordinates":[-0.154865,51.475122],"type":"Point"}
}
