{
  "type": "Feature",
  "properties": {
    "iso:country":"GB",
    "wof:name":"BN1 8NJ",
    "wof:placetype":"postalcode"
},
  "geometry": {"coordinates":[-0.14426775973934,50.86001498511658],"type":"Point"}
}