{
  "type": "Feature",
  "properties": {
    "iso:country":"GB",
    "wof:name":"BS32 0ER",
    "wof:placetype":"postalcode"
},
  "geometry": {"coordinates":[-2.54491931553982,51.53946650605326],"type":"Point"}
}