{
  "type": "Feature",
  "properties": {
    "iso:country":"GB",
    "wof:name":"SO32 2AP",
    "wof:placetype":"postalcode"
},
  "geometry": {"coordinates":[-1.2776465832984,50.95581105119393],"type":"Point"}
}