{
  "type": "Feature",
  "properties": {
    "date:inception_lower": "1994-12-01",
    "date:inception_upper": "1994-12-01",
    "iso:country": "GB",
    "wof:name": "SO32 2AP",
    "wof:placetype": "postalcode"
  },
  "geometry": {"coordinates":[-1.276186,50.95557],"type":"Point"}
}
