{
  "type": "Feature",
  "properties": {
    "iso:country":"GB",
    "wof:name":"BA2 8HZ",
    "wof:placetype":"postalcode"
},
  "geometry": {"coordinates":[-2.42814393624802,51.31202205494786],"type":"Point"}
}