{
  "type": "Feature",
  "properties": {
    "iso:country": "GB",
    "wof:name": "KA3 1PW",
    "wof:placetype": "postalcode"
  },
  "geometry": {"coordinates":[-4.506115,55.624036],"type":"Point"}
}
