{
  "type": "Feature",
  "properties": {
    "iso:country":"GB",
    "wof:name":"NG22 0PP",
    "wof:placetype":"postalcode"
},
  "geometry": {"coordinates":[-0.93240033729867,53.25165908625083],"type":"Point"}
}