{
  "type": "Feature",
  "properties": {
    "iso:country": "GB",
    "wof:name": "NG22 0PP",
    "wof:placetype": "postalcode"
  },
  "geometry": {"coordinates":[-0.9324,53.251659],"type":"Point"}
}
