{
  "type": "Feature",
  "properties": {
    "date:inception_lower":"1980-01-01",
    "date:inception_upper":"1980-01-31",
    "iso:country":"GB",
    "wof:name":"NG22 0PP",
    "wof:placetype":"postalcode"
},
  "geometry": {"coordinates":[-0.9324,53.251659],"type":"Point"}
}