{
  "type": "Feature",
  "properties": {
    "date:inception_lower": "2022-11-01",
    "date:inception_upper": "2022-11-01",
    "iso:country": "GB",
    "wof:name": "ML5 2TW",
    "wof:placetype": "postalcode"
  },
  "geometry": {"coordinates":[-4.057726,55.890289],"type":"Point"}
}
