{
  "type": "Feature",
  "properties": {
    "iso:country":"GB",
    "wof:name":"LS6 3NG",
    "wof:placetype":"postalcode"
},
  "geometry": {"coordinates":[-1.59101282193624,53.81804248650275],"type":"Point"}
}