{
  "type": "Feature",
  "properties": {
    "iso:country": "GB",
    "wof:name": "NN7 4NT",
    "wof:placetype": "postalcode"
  },
  "geometry": {"coordinates":[-1.051878,52.235554],"type":"Point"}
}
