{
  "type": "Feature",
  "properties": {
    "iso:country":"GB",
    "wof:name":"B42 2HB",
    "wof:placetype":"postalcode"
},
  "geometry": {"coordinates":[-1.89773774862673,52.52618044576619],"type":"Point"}
}