{
  "type": "Feature",
  "properties": {
    "iso:country":"GB",
    "wof:name":"CM11 2SN",
    "wof:placetype":"postalcode"
},
  "geometry": {"coordinates":[0.42658152644392,51.61217948115501],"type":"Point"}
}