{
  "type": "Feature",
  "properties": {
    "iso:country": "GB",
    "wof:name": "TF2 6JP",
    "wof:placetype": "postalcode"
  },
  "geometry": {"coordinates":[-2.4521,52.699004],"type":"Point"}
}
