{
  "type": "Feature",
  "properties": {
    "iso:country":"GB",
    "wof:name":"BB7 2PL",
    "wof:placetype":"postalcode"
},
  "geometry": {"coordinates":[-2.40884007396563,53.86507518523032],"type":"Point"}
}