{
  "type": "Feature",
  "properties": {
    "iso:country":"GB",
    "wof:name":"E14 7GP",
    "wof:placetype":"postalcode"
},
  "geometry": {"coordinates":[-0.02865913924603,51.51227627826466],"type":"Point"}
}