{
  "type": "Feature",
  "properties": {
    "iso:country":"GB",
    "wof:name":"ST3 3NF",
    "wof:placetype":"postalcode"
},
  "geometry": {"coordinates":[-2.15614091131547,52.96594429259941],"type":"Point"}
}