{
  "type": "Feature",
  "properties": {
    "iso:country": "GB",
    "wof:name": "GL18 1NW",
    "wof:placetype": "postalcode"
  },
  "geometry": {"coordinates":[-2.450365,51.925724],"type":"Point"}
}
