{
  "type": "Feature",
  "properties": {
    "iso:country":"GB",
    "wof:name":"M20 2YQ",
    "wof:placetype":"postalcode"
},
  "geometry": {"coordinates":[-2.25686326552277,53.42129937404679],"type":"Point"}
}