{
  "type": "Feature",
  "properties": {
    "iso:country":"GB",
    "wof:name":"CF38 1AZ",
    "wof:placetype":"postalcode"
},
  "geometry": {"coordinates":[-3.32018476603195,51.56172598448549],"type":"Point"}
}