{
  "type": "Feature",
  "properties": {
    "date:inception_lower":"2002-08-01",
    "date:inception_upper":"2002-08-31",
    "iso:country":"GB",
    "wof:name":"CF38 1AZ",
    "wof:placetype":"postalcode"
},
  "geometry": {"coordinates":[-3.320185,51.561726],"type":"Point"}
}