{
  "type": "Feature",
  "properties": {
    "iso:country":"GB",
    "wof:name":"OX16 9NJ",
    "wof:placetype":"postalcode"
},
  "geometry": {"coordinates":[-1.35390913339691,52.05403118765264],"type":"Point"}
}