{
  "type": "Feature",
  "properties": {
    "iso:country":"GB",
    "wof:name":"RG30 2UD",
    "wof:placetype":"postalcode"
},
  "geometry": {"coordinates":[-0.99437889643808,51.45532898653087],"type":"Point"}
}