{
  "type": "Feature",
  "properties": {
    "iso:country": "GB",
    "wof:name": "RG30 2UD",
    "wof:placetype": "postalcode"
  },
  "geometry": {"coordinates":[-0.994379,51.455329],"type":"Point"}
}
