{
  "type": "Feature",
  "properties": {
    "iso:country":"GB",
    "wof:name":"TA24 8AB",
    "wof:placetype":"postalcode"
},
  "geometry": {"coordinates":[-3.48219329157333,51.20499045362621],"type":"Point"}
}