{
  "type": "Feature",
  "properties": {
    "iso:country":"GB",
    "wof:name":"LN1 1BA",
    "wof:placetype":"postalcode"
},
  "geometry": {"coordinates":[-0.54483175078426,53.23105391621832],"type":"Point"}
}