{
  "type": "Feature",
  "properties": {
    "iso:country": "GB",
    "wof:name": "DN22 0EQ",
    "wof:placetype": "postalcode"
  },
  "geometry": {"coordinates":[-0.827553,53.306588],"type":"Point"}
}
