{
  "type": "Feature",
  "properties": {
    "date:inception_lower": "1980-01-01",
    "date:inception_upper": "1980-01-01",
    "iso:country": "GB",
    "wof:name": "DN22 0EQ",
    "wof:placetype": "postalcode"
  },
  "geometry": {"coordinates":[-0.827553,53.306588],"type":"Point"}
}
