{
  "type": "Feature",
  "properties": {
    "date:inception_lower": "1993-08-01",
    "date:inception_upper": "1993-08-01",
    "iso:country": "GB",
    "wof:name": "NN3 8UX",
    "wof:placetype": "postalcode"
  },
  "geometry": {"coordinates":[-0.843486,52.272069],"type":"Point"}
}
