{
  "type": "Feature",
  "properties": {
    "iso:country":"GB",
    "wof:name":"NN3 8UX",
    "wof:placetype":"postalcode"
},
  "geometry": {"coordinates":[-0.84348633341198,52.27206876668998],"type":"Point"}
}