{
  "type": "Feature",
  "properties": {
    "iso:country":"GB",
    "wof:name":"M5 5JN",
    "wof:placetype":"postalcode"
},
  "geometry": {"coordinates":[-2.30691853143126,53.48708490146061],"type":"Point"}
}