{
  "type": "Feature",
  "properties": {
    "date:inception_lower":"2002-06-01",
    "date:inception_upper":"2002-06-30",
    "iso:country":"GB",
    "wof:name":"M5 5JN",
    "wof:placetype":"postalcode"
},
  "geometry": {"coordinates":[-2.306918,53.487085],"type":"Point"}
}