{
  "type": "Feature",
  "properties": {
    "date:inception_lower":"1981-06-01",
    "date:inception_upper":"1981-06-30",
    "iso:country":"GB",
    "wof:name":"BR6 7UD",
    "wof:placetype":"postalcode"
},
  "geometry": {"coordinates":[0.069219,51.362774],"type":"Point"}
}