{
  "type": "Feature",
  "properties": {
    "iso:country":"GB",
    "wof:name":"BR6 7UD",
    "wof:placetype":"postalcode"
},
  "geometry": {"coordinates":[0.0692187514177,51.36277449712073],"type":"Point"}
}