{
  "type": "Feature",
  "properties": {
    "iso:country":"GB",
    "wof:name":"YO15 3LG",
    "wof:placetype":"postalcode"
},
  "geometry": {"coordinates":[-0.19946436089004,54.07683284821152],"type":"Point"}
}