{
  "type": "Feature",
  "properties": {
    "iso:country": "GB",
    "wof:name": "YO15 3LG",
    "wof:placetype": "postalcode"
  },
  "geometry": {"coordinates":[-0.199464,54.076833],"type":"Point"}
}
