{
  "type": "Feature",
  "properties": {
    "iso:country":"GB",
    "wof:name":"AL2 2AH",
    "wof:placetype":"postalcode"
},
  "geometry": {"coordinates":[-0.3544437717681,51.71450573414028],"type":"Point"}
}