{
  "type": "Feature",
  "properties": {
    "date:inception_lower": "1980-01-01",
    "date:inception_upper": "1980-01-01",
    "iso:country": "GB",
    "wof:name": "AL2 2AH",
    "wof:placetype": "postalcode"
  },
  "geometry": {"coordinates":[-0.354444,51.714506],"type":"Point"}
}
