{
  "type": "Feature",
  "properties": {
    "iso:country": "GB",
    "wof:name": "RH6 8DF",
    "wof:placetype": "postalcode"
  },
  "geometry": {"coordinates":[-0.171182,51.180711],"type":"Point"}
}
