{
  "type": "Feature",
  "properties": {
    "iso:country":"GB",
    "wof:name":"E6 3NF",
    "wof:placetype":"postalcode"
},
  "geometry": {"coordinates":[0.0507089504132,51.52641878643223],"type":"Point"}
}