{
  "type": "Feature",
  "properties": {
    "iso:country":"GB",
    "wof:name":"DL8 2BN",
    "wof:placetype":"postalcode"
},
  "geometry": {"coordinates":[-1.59103139486506,54.28770975714792],"type":"Point"}
}