{
  "type": "Feature",
  "properties": {
    "iso:country": "GB",
    "wof:name": "DL8 2BN",
    "wof:placetype": "postalcode"
  },
  "geometry": {"coordinates":[-1.590963,54.287631],"type":"Point"}
}
