{
  "type": "Feature",
  "properties": {
    "iso:country": "GB",
    "wof:name": "WR11 8SL",
    "wof:placetype": "postalcode"
  },
  "geometry": {"coordinates":[-1.919913,52.16366],"type":"Point"}
}
