{
  "type": "Feature",
  "properties": {
    "iso:country": "GB",
    "wof:name": "DD4 0RX",
    "wof:placetype": "postalcode"
  },
  "geometry": {"coordinates":[-2.928939,56.492494],"type":"Point"}
}
