{
  "type": "Feature",
  "properties": {
    "iso:country": "GB",
    "wof:name": "MK17 0EL",
    "wof:placetype": "postalcode"
  },
  "geometry": {"coordinates":[-0.860087,51.99745],"type":"Point"}
}
