{
  "type": "Feature",
  "properties": {
    "iso:country":"GB",
    "wof:name":"MK17 0EL",
    "wof:placetype":"postalcode"
},
  "geometry": {"coordinates":[-0.86008680912791,51.99744956176801],"type":"Point"}
}