{
  "type": "Feature",
  "properties": {
    "date:inception_lower": "1980-01-01",
    "date:inception_upper": "1980-01-01",
    "iso:country": "GB",
    "wof:name": "MK17 0EL",
    "wof:placetype": "postalcode"
  },
  "geometry": {"coordinates":[-0.860087,51.99745],"type":"Point"}
}
