{
  "type": "Feature",
  "properties": {
    "iso:country": "GB",
    "wof:name": "LA2 6EX",
    "wof:placetype": "postalcode"
  },
  "geometry": {"coordinates":[-2.804297,54.093051],"type":"Point"}
}
