{
  "type": "Feature",
  "properties": {
    "iso:country":"GB",
    "wof:name":"LA2 6EX",
    "wof:placetype":"postalcode"
},
  "geometry": {"coordinates":[-2.80429712593676,54.09305053459678],"type":"Point"}
}