{
  "type": "Feature",
  "properties": {
    "iso:country":"GB",
    "wof:name":"HP3 9BN",
    "wof:placetype":"postalcode"
},
  "geometry": {"coordinates":[-0.46222333829211,51.74665494372977],"type":"Point"}
}