{
  "type": "Feature",
  "properties": {
    "date:inception_lower": "1980-01-01",
    "date:inception_upper": "1980-01-01",
    "iso:country": "GB",
    "wof:name": "M29 7BZ",
    "wof:placetype": "postalcode"
  },
  "geometry": {"coordinates":[-2.46021,53.501702],"type":"Point"}
}
