{
  "type": "Feature",
  "properties": {
    "iso:country": "GB",
    "wof:name": "M29 7BZ",
    "wof:placetype": "postalcode"
  },
  "geometry": {"coordinates":[-2.46021,53.501702],"type":"Point"}
}
