{
  "type": "Feature",
  "properties": {
    "iso:country":"GB",
    "wof:name":"M29 7BZ",
    "wof:placetype":"postalcode"
},
  "geometry": {"coordinates":[-2.46020960749844,53.50170230514171],"type":"Point"}
}