{
  "type": "Feature",
  "properties": {
    "iso:country":"GB",
    "wof:name":"LL65 4BH",
    "wof:placetype":"postalcode"
},
  "geometry": {"coordinates":[-4.4973484141376,53.37772957891841],"type":"Point"}
}