{
  "type": "Feature",
  "properties": {
    "iso:country": "GB",
    "wof:name": "G15 7JP",
    "wof:placetype": "postalcode"
  },
  "geometry": {"coordinates":[-4.362268,55.917126],"type":"Point"}
}
