{
  "type": "Feature",
  "properties": {
    "date:inception_lower": "1980-01-01",
    "date:inception_upper": "1980-01-01",
    "iso:country": "GB",
    "wof:name": "G15 7JP",
    "wof:placetype": "postalcode"
  },
  "geometry": {"coordinates":[-4.362268,55.917126],"type":"Point"}
}
