{
  "type": "Feature",
  "properties": {
    "iso:country":"GB",
    "wof:name":"WV10 9HE",
    "wof:placetype":"postalcode"
},
  "geometry": {"coordinates":[-2.1210466175663,52.61883829998418],"type":"Point"}
}