{
  "type": "Feature",
  "properties": {
    "iso:country": "GB",
    "wof:name": "GL17 9JN",
    "wof:placetype": "postalcode"
  },
  "geometry": {"coordinates":[-2.51674,51.844953],"type":"Point"}
}
