{
  "type": "Feature",
  "properties": {
    "iso:country":"GB",
    "wof:name":"N1 4NZ",
    "wof:placetype":"postalcode"
},
  "geometry": {"coordinates":[-0.08141183044762,51.54781738777449],"type":"Point"}
}