{
  "type": "Feature",
  "properties": {
    "iso:country":"GB",
    "wof:name":"GL2 0ST",
    "wof:placetype":"postalcode"
},
  "geometry": {"coordinates":[-2.22041657857797,51.86456718934994],"type":"Point"}
}