{
  "type": "Feature",
  "properties": {
    "iso:country":"GB",
    "wof:name":"M34 7PD",
    "wof:placetype":"postalcode"
},
  "geometry": {"coordinates":[-2.10212939391718,53.43900592161197],"type":"Point"}
}