{
  "type": "Feature",
  "properties": {
    "iso:country": "GB",
    "wof:name": "M34 7PD",
    "wof:placetype": "postalcode"
  },
  "geometry": {"coordinates":[-2.102129,53.439006],"type":"Point"}
}
