{
  "type": "Feature",
  "properties": {
    "date:inception_lower":"1985-04-01",
    "date:inception_upper":"1985-04-30",
    "iso:country":"GB",
    "wof:name":"B65 9SH",
    "wof:placetype":"postalcode"
},
  "geometry": {"coordinates":[-2.038357,52.497693],"type":"Point"}
}