{
  "type": "Feature",
  "properties": {
    "iso:country": "GB",
    "wof:name": "CA14 1QF",
    "wof:placetype": "postalcode"
  },
  "geometry": {"coordinates":[-3.521828,54.666951],"type":"Point"}
}
