{
  "type": "Feature",
  "properties": {
    "date:inception_lower": "2014-04-01",
    "date:inception_upper": "2014-04-01",
    "iso:country": "GB",
    "wof:name": "CA14 1QF",
    "wof:placetype": "postalcode"
  },
  "geometry": {"coordinates":[-3.521845,54.666967],"type":"Point"}
}
