{
  "type": "Feature",
  "properties": {
    "iso:country":"GB",
    "wof:name":"CA14 1QF",
    "wof:placetype":"postalcode"
},
  "geometry": {"coordinates":[-3.52182846641347,54.66695090841876],"type":"Point"}
}