{
  "type": "Feature",
  "properties": {
    "iso:country":"GB",
    "wof:name":"L16 1JD",
    "wof:placetype":"postalcode"
},
  "geometry": {"coordinates":[-2.89342267102359,53.4035807591066],"type":"Point"}
}