{
  "type": "Feature",
  "properties": {
    "iso:country": "GB",
    "wof:name": "CR0 2WU",
    "wof:placetype": "postalcode"
  },
  "geometry": {"coordinates":[-0.093778,51.379524],"type":"Point"}
}
