{
  "type": "Feature",
  "properties": {
    "iso:country":"GB",
    "wof:name":"PH1 3PD",
    "wof:placetype":"postalcode"
},
  "geometry": {"coordinates":[-3.57953187701451,56.41780452614898],"type":"Point"}
}