{
  "type": "Feature",
  "properties": {
    "iso:country": "GB",
    "wof:name": "LS14 5HR",
    "wof:placetype": "postalcode"
  },
  "geometry": {"coordinates":[-1.446704,53.816637],"type":"Point"}
}
