{
  "type": "Feature",
  "properties": {
    "iso:country":"GB",
    "wof:name":"LS14 5HR",
    "wof:placetype":"postalcode"
},
  "geometry": {"coordinates":[-1.44670367396106,53.81663709118001],"type":"Point"}
}