{
  "type": "Feature",
  "properties": {
    "date:inception_lower":"2010-03-01",
    "date:inception_upper":"2010-03-31",
    "iso:country":"GB",
    "wof:name":"SO32 1PQ",
    "wof:placetype":"postalcode"
},
  "geometry": {"coordinates":[-1.200526,50.953115],"type":"Point"}
}