{
  "type": "Feature",
  "properties": {
    "iso:country": "GB",
    "wof:name": "DE73 6RY",
    "wof:placetype": "postalcode"
  },
  "geometry": {"coordinates":[-1.437297,52.873052],"type":"Point"}
}
