{
  "type": "Feature",
  "properties": {
    "iso:country":"GB",
    "wof:name":"SO52 9FF",
    "wof:placetype":"postalcode"
},
  "geometry": {"coordinates":[-1.4428151602072,50.97366603471633],"type":"Point"}
}