{
  "type": "Feature",
  "properties": {
    "iso:country":"GB",
    "wof:name":"WV10 0UG",
    "wof:placetype":"postalcode"
},
  "geometry": {"coordinates":[-2.10480913217486,52.59842906729117],"type":"Point"}
}