{
  "type": "Feature",
  "properties": {
    "iso:country":"GB",
    "wof:name":"LS22 6HD",
    "wof:placetype":"postalcode"
},
  "geometry": {"coordinates":[-1.39851336924649,53.92879110118665],"type":"Point"}
}