{
  "type": "Feature",
  "properties": {
    "iso:country": "GB",
    "wof:name": "SL6 7SQ",
    "wof:placetype": "postalcode"
  },
  "geometry": {"coordinates":[-0.729066,51.533475],"type":"Point"}
}
