{
  "type": "Feature",
  "properties": {
    "date:inception_lower":"1980-01-01",
    "date:inception_upper":"1980-01-31",
    "iso:country":"GB",
    "wof:name":"SL6 7SQ",
    "wof:placetype":"postalcode"
},
  "geometry": {"coordinates":[-0.729066,51.533475],"type":"Point"}
}