{
  "type": "Feature",
  "properties": {
    "iso:country":"GB",
    "wof:name":"SL6 7SQ",
    "wof:placetype":"postalcode"
},
  "geometry": {"coordinates":[-0.72906562876304,51.53347459634769],"type":"Point"}
}