{
  "type": "Feature",
  "properties": {
    "iso:country": "GB",
    "wof:name": "GU21 5JP",
    "wof:placetype": "postalcode"
  },
  "geometry": {"coordinates":[-0.545463,51.324422],"type":"Point"}
}
