{
  "type": "Feature",
  "properties": {
    "date:inception_lower": "1980-01-01",
    "date:inception_upper": "1980-01-01",
    "iso:country": "GB",
    "wof:name": "GU21 5JP",
    "wof:placetype": "postalcode"
  },
  "geometry": {"coordinates":[-0.545463,51.324422],"type":"Point"}
}
