{
  "type": "Feature",
  "properties": {
    "iso:country":"GB",
    "wof:name":"TA12 6LW",
    "wof:placetype":"postalcode"
},
  "geometry": {"coordinates":[-2.77809457406475,50.95945123838777],"type":"Point"}
}