{
  "type": "Feature",
  "properties": {
    "iso:country": "GB",
    "wof:name": "B92 8EE",
    "wof:placetype": "postalcode"
  },
  "geometry": {"coordinates":[-1.79203,52.44391],"type":"Point"}
}
