{
  "type": "Feature",
  "properties": {
    "iso:country": "GB",
    "wof:name": "PL15 7TS",
    "wof:placetype": "postalcode"
  },
  "geometry": {"coordinates":[-4.565383,50.562053],"type":"Point"}
}
