{
  "type": "Feature",
  "properties": {
    "iso:country":"GB",
    "wof:name":"PL15 7TS",
    "wof:placetype":"postalcode"
},
  "geometry": {"coordinates":[-4.56549745280913,50.5619695223872],"type":"Point"}
}