{
  "type": "Feature",
  "properties": {
    "iso:country": "GB",
    "wof:name": "TN34 3NL",
    "wof:placetype": "postalcode"
  },
  "geometry": {"coordinates":[0.596293,50.866545],"type":"Point"}
}
