{
  "type": "Feature",
  "properties": {
    "date:inception_lower": "1980-01-01",
    "date:inception_upper": "1980-01-01",
    "iso:country": "GB",
    "wof:name": "PH6 2ND",
    "wof:placetype": "postalcode"
  },
  "geometry": {"coordinates":[-4.111867,56.391729],"type":"Point"}
}
