{
  "type": "Feature",
  "properties": {
    "iso:country":"GB",
    "wof:name":"PH6 2ND",
    "wof:placetype":"postalcode"
},
  "geometry": {"coordinates":[-4.11186740297017,56.39172902901188],"type":"Point"}
}