{
  "type": "Feature",
  "properties": {
    "iso:country":"GB",
    "wof:name":"TQ13 0HH",
    "wof:placetype":"postalcode"
},
  "geometry": {"coordinates":[-3.63340279282937,50.58325002865337],"type":"Point"}
}