{
  "type": "Feature",
  "properties": {
    "date:inception_lower": "1980-01-01",
    "date:inception_upper": "1980-01-01",
    "iso:country": "GB",
    "wof:name": "TQ13 0HH",
    "wof:placetype": "postalcode"
  },
  "geometry": {"coordinates":[-3.633403,50.58325],"type":"Point"}
}
