{
  "type": "Feature",
  "properties": {
    "iso:country":"GB",
    "wof:name":"SG5 1NZ",
    "wof:placetype":"postalcode"
},
  "geometry": {"coordinates":[-0.28183722885987,51.95465616156332],"type":"Point"}
}