{
  "type": "Feature",
  "properties": {
    "iso:country": "GB",
    "wof:name": "SG5 1NZ",
    "wof:placetype": "postalcode"
  },
  "geometry": {"coordinates":[-0.281812,51.954673],"type":"Point"}
}
