{
  "type": "Feature",
  "properties": {
    "iso:country": "GB",
    "wof:name": "LL29 0EZ",
    "wof:placetype": "postalcode"
  },
  "geometry": {"coordinates":[-3.729603,53.297769],"type":"Point"}
}
