{
  "type": "Feature",
  "properties": {
    "iso:country":"GB",
    "wof:name":"B12 9RA",
    "wof:placetype":"postalcode"
},
  "geometry": {"coordinates":[-1.88817171623478,52.4563648934649],"type":"Point"}
}