{
  "type": "Feature",
  "properties": {
    "iso:country":"GB",
    "wof:name":"HU4 7SB",
    "wof:placetype":"postalcode"
},
  "geometry": {"coordinates":[-0.41431859001268,53.7452114151652],"type":"Point"}
}