{
  "type": "Feature",
  "properties": {
    "iso:country": "GB",
    "wof:name": "HU4 7SB",
    "wof:placetype": "postalcode"
  },
  "geometry": {"coordinates":[-0.414319,53.745211],"type":"Point"}
}
