{
  "type": "Feature",
  "properties": {
    "iso:country":"GB",
    "wof:name":"SE13 6QE",
    "wof:placetype":"postalcode"
},
  "geometry": {"coordinates":[-0.00709587736039,51.45255098561805],"type":"Point"}
}