{
  "type": "Feature",
  "properties": {
    "iso:country":"GB",
    "wof:name":"WD19 7DH",
    "wof:placetype":"postalcode"
},
  "geometry": {"coordinates":[-0.3952986818963,51.6288374383162],"type":"Point"}
}