{
  "type": "Feature",
  "properties": {
    "iso:country":"GB",
    "wof:name":"HU3 5EB",
    "wof:placetype":"postalcode"
},
  "geometry": {"coordinates":[-0.38588855386626,53.73918674569762],"type":"Point"}
}