{
  "type": "Feature",
  "properties": {
    "iso:country":"GB",
    "wof:name":"ME8 0DS",
    "wof:placetype":"postalcode"
},
  "geometry": {"coordinates":[0.59767896078499,51.36106787419725],"type":"Point"}
}