{
  "type": "Feature",
  "properties": {
    "iso:country":"GB",
    "wof:name":"B11 3NB",
    "wof:placetype":"postalcode"
},
  "geometry": {"coordinates":[-1.85915706246336,52.45456293971348],"type":"Point"}
}