{
  "type": "Feature",
  "properties": {
    "date:inception_lower": "1980-01-01",
    "date:inception_upper": "1980-01-01",
    "iso:country": "GB",
    "wof:name": "B11 3NB",
    "wof:placetype": "postalcode"
  },
  "geometry": {"coordinates":[-1.859157,52.454563],"type":"Point"}
}
