{
  "type": "Feature",
  "properties": {
    "iso:country":"GB",
    "wof:name":"TR9 6RD",
    "wof:placetype":"postalcode"
},
  "geometry": {"coordinates":[-4.95229615125153,50.42972521038355],"type":"Point"}
}