{
  "type": "Feature",
  "properties": {
    "iso:country": "GB",
    "wof:name": "TR9 6RD",
    "wof:placetype": "postalcode"
  },
  "geometry": {"coordinates":[-4.953204,50.429568],"type":"Point"}
}
