{
  "type": "Feature",
  "properties": {
    "date:inception_lower": "1995-12-01",
    "date:inception_upper": "1995-12-01",
    "iso:country": "GB",
    "wof:name": "TR9 6RD",
    "wof:placetype": "postalcode"
  },
  "geometry": {"coordinates":[-4.953204,50.429568],"type":"Point"}
}
