{
  "type": "Feature",
  "properties": {
    "date:inception_lower":"1992-08-01",
    "date:inception_upper":"1992-08-31",
    "iso:country":"GB",
    "wof:name":"LE18 1JS",
    "wof:placetype":"postalcode"
},
  "geometry": {"coordinates":[-1.107003,52.594869],"type":"Point"}
}