{
  "type": "Feature",
  "properties": {
    "iso:country":"GB",
    "wof:name":"LS8 1SB",
    "wof:placetype":"postalcode"
},
  "geometry": {"coordinates":[-1.50901695026262,53.82755000150179],"type":"Point"}
}