{
  "type": "Feature",
  "properties": {
    "date:inception_lower": "1980-01-01",
    "date:inception_upper": "1980-01-01",
    "iso:country": "GB",
    "wof:name": "LS8 1SB",
    "wof:placetype": "postalcode"
  },
  "geometry": {"coordinates":[-1.509017,53.82755],"type":"Point"}
}
