{
  "type": "Feature",
  "properties": {
    "iso:country":"GB",
    "wof:name":"M34 7QR",
    "wof:placetype":"postalcode"
},
  "geometry": {"coordinates":[-2.09712019582469,53.44059208601097],"type":"Point"}
}