{
  "type": "Feature",
  "properties": {
    "iso:country":"GB",
    "wof:name":"NE9 7BW",
    "wof:placetype":"postalcode"
},
  "geometry": {"coordinates":[-1.57254037101799,54.92162131288899],"type":"Point"}
}