{
  "type": "Feature",
  "properties": {
    "date:inception_lower":"1987-10-01",
    "date:inception_upper":"1987-10-31",
    "iso:country":"GB",
    "wof:name":"PE6 8SL",
    "wof:placetype":"postalcode"
},
  "geometry": {"coordinates":[-0.306037,52.680102],"type":"Point"}
}