{
  "type": "Feature",
  "properties": {
    "iso:country": "GB",
    "wof:name": "MK17 0LR",
    "wof:placetype": "postalcode"
  },
  "geometry": {"coordinates":[-0.828693,51.989042],"type":"Point"}
}
