{
  "type": "Feature",
  "properties": {
    "iso:country":"GB",
    "wof:name":"MK17 0LR",
    "wof:placetype":"postalcode"
},
  "geometry": {"coordinates":[-0.8286118534142,51.98899481593713],"type":"Point"}
}