{
  "type": "Feature",
  "properties": {
    "iso:country": "GB",
    "wof:name": "N1 1DE",
    "wof:placetype": "postalcode"
  },
  "geometry": {"coordinates":[-0.113256,51.54158],"type":"Point"}
}
