{
  "type": "Feature",
  "properties": {
    "date:inception_lower":"1993-08-01",
    "date:inception_upper":"1993-08-31",
    "iso:country":"GB",
    "wof:name":"NE5 2JN",
    "wof:placetype":"postalcode"
},
  "geometry": {"coordinates":[-1.683113,54.98294],"type":"Point"}
}