{
  "type": "Feature",
  "properties": {
    "iso:country": "GB",
    "wof:name": "TS7 0AA",
    "wof:placetype": "postalcode"
  },
  "geometry": {"coordinates":[-1.173712,54.525679],"type":"Point"}
}
