{
  "type": "Feature",
  "properties": {
    "iso:country":"GB",
    "wof:name":"TS7 0AA",
    "wof:placetype":"postalcode"
},
  "geometry": {"coordinates":[-1.17371160063296,54.52567937473103],"type":"Point"}
}