{
  "type": "Feature",
  "properties": {
    "iso:country": "GB",
    "wof:name": "MK1 1EY",
    "wof:placetype": "postalcode"
  },
  "geometry": {"coordinates":[-0.727424,52.003735],"type":"Point"}
}
