{
  "type": "Feature",
  "properties": {
    "date:inception_lower": "2017-07-01",
    "date:inception_upper": "2017-07-01",
    "iso:country": "GB",
    "wof:name": "MK1 1EY",
    "wof:placetype": "postalcode"
  },
  "geometry": {"coordinates":[-0.727635,52.003503],"type":"Point"}
}
