{
  "type": "Feature",
  "properties": {
    "iso:country":"GB",
    "wof:name":"LA9 5JQ",
    "wof:placetype":"postalcode"
},
  "geometry": {"coordinates":[-2.75486990395241,54.31608331375732],"type":"Point"}
}