{
  "type": "Feature",
  "properties": {
    "iso:country": "GB",
    "wof:name": "LA9 5JQ",
    "wof:placetype": "postalcode"
  },
  "geometry": {"coordinates":[-2.75487,54.316083],"type":"Point"}
}
