{
  "type": "Feature",
  "properties": {
    "iso:country":"GB",
    "wof:name":"SE8 4RH",
    "wof:placetype":"postalcode"
},
  "geometry": {"coordinates":[-0.02483373328845,51.47742827499466],"type":"Point"}
}