{
  "type": "Feature",
  "properties": {
    "iso:country":"GB",
    "wof:name":"G41 3SD",
    "wof:placetype":"postalcode"
},
  "geometry": {"coordinates":[-4.2902943915294,55.8294020905927],"type":"Point"}
}