{
  "type": "Feature",
  "properties": {
    "iso:country": "GB",
    "wof:name": "CM16 9SH",
    "wof:placetype": "postalcode"
  },
  "geometry": {"coordinates":[0.114367,51.701275],"type":"Point"}
}
