{
  "type": "Feature",
  "properties": {
    "date:inception_lower": "1999-06-01",
    "date:inception_upper": "1999-06-01",
    "iso:country": "GB",
    "wof:name": "NP15 1SN",
    "wof:placetype": "postalcode"
  },
  "geometry": {"coordinates":[-2.898644,51.708761],"type":"Point"}
}
