{
  "type": "Feature",
  "properties": {
    "date:inception_lower": "1980-01-01",
    "date:inception_upper": "1980-01-01",
    "iso:country": "GB",
    "wof:name": "NE49 0DD",
    "wof:placetype": "postalcode"
  },
  "geometry": {"coordinates":[-2.456774,54.97092],"type":"Point"}
}
