{
  "type": "Feature",
  "properties": {
    "iso:country":"GB",
    "wof:name":"CR8 5BS",
    "wof:placetype":"postalcode"
},
  "geometry": {"coordinates":[-0.08654269965578,51.31790441033983],"type":"Point"}
}