{
  "type": "Feature",
  "properties": {
    "date:inception_lower":"1990-07-01",
    "date:inception_upper":"1990-07-31",
    "iso:country":"GB",
    "wof:name":"CR8 5BS",
    "wof:placetype":"postalcode"
},
  "geometry": {"coordinates":[-0.086543,51.317904],"type":"Point"}
}