{
  "type": "Feature",
  "properties": {
    "date:inception_lower": "1980-01-01",
    "date:inception_upper": "1980-01-01",
    "iso:country": "GB",
    "wof:name": "DL7 8TP",
    "wof:placetype": "postalcode"
  },
  "geometry": {"coordinates":[-1.435836,54.336643],"type":"Point"}
}
