{
  "type": "Feature",
  "properties": {
    "iso:country": "GB",
    "wof:name": "DL7 8TP",
    "wof:placetype": "postalcode"
  },
  "geometry": {"coordinates":[-1.435855,54.336347],"type":"Point"}
}
