{
  "type": "Feature",
  "properties": {
    "iso:country":"GB",
    "wof:name":"DL7 8TP",
    "wof:placetype":"postalcode"
},
  "geometry": {"coordinates":[-1.43582646770213,54.33663105318456],"type":"Point"}
}