{
  "type": "Feature",
  "properties": {
    "iso:country":"GB",
    "wof:name":"IP4 3HJ",
    "wof:placetype":"postalcode"
},
  "geometry": {"coordinates":[1.19066280729048,52.070752445378],"type":"Point"}
}