{
  "type": "Feature",
  "properties": {
    "iso:country": "GB",
    "wof:name": "TF2 7JZ",
    "wof:placetype": "postalcode"
  },
  "geometry": {"coordinates":[-2.441684,52.709463],"type":"Point"}
}
