{
  "type": "Feature",
  "properties": {
    "iso:country":"GB",
    "wof:name":"TF2 7JZ",
    "wof:placetype":"postalcode"
},
  "geometry": {"coordinates":[-2.44168601886201,52.70944787016481],"type":"Point"}
}