{
  "type": "Feature",
  "properties": {
    "iso:country": "GB",
    "wof:name": "PO12 2NG",
    "wof:placetype": "postalcode"
  },
  "geometry": {"coordinates":[-1.160932,50.78847],"type":"Point"}
}
