{
  "type": "Feature",
  "properties": {
    "date:inception_lower":"1998-06-01",
    "date:inception_upper":"1998-06-30",
    "iso:country":"GB",
    "wof:name":"YO16 7JD",
    "wof:placetype":"postalcode"
},
  "geometry": {"coordinates":[-0.189785,54.091313],"type":"Point"}
}