{
  "type": "Feature",
  "properties": {
    "iso:country": "GB",
    "wof:name": "YO16 7JD",
    "wof:placetype": "postalcode"
  },
  "geometry": {"coordinates":[-0.189785,54.091313],"type":"Point"}
}
