{
  "type": "Feature",
  "properties": {
    "iso:country":"GB",
    "wof:name":"YO16 7JD",
    "wof:placetype":"postalcode"
},
  "geometry": {"coordinates":[-0.18969299717544,54.09132015607452],"type":"Point"}
}