{
  "type": "Feature",
  "properties": {
    "date:inception_lower": "1980-01-01",
    "date:inception_upper": "1980-01-01",
    "iso:country": "GB",
    "wof:name": "CM13 2JN",
    "wof:placetype": "postalcode"
  },
  "geometry": {"coordinates":[0.32787,51.622947],"type":"Point"}
}
