{
  "type": "Feature",
  "properties": {
    "date:inception_lower": "2008-02-01",
    "date:inception_upper": "2008-02-01",
    "iso:country": "GB",
    "wof:name": "OL10 1FH",
    "wof:placetype": "postalcode"
  },
  "geometry": {"coordinates":[-2.21842,53.591634],"type":"Point"}
}
