{
  "type": "Feature",
  "properties": {
    "iso:country":"GB",
    "wof:name":"RG27 9JF",
    "wof:placetype":"postalcode"
},
  "geometry": {"coordinates":[-0.96087220765811,51.27761584319828],"type":"Point"}
}