{
  "type": "Feature",
  "properties": {
    "date:inception_lower": "1980-01-01",
    "date:inception_upper": "1980-01-01",
    "iso:country": "GB",
    "wof:name": "SK10 3HH",
    "wof:placetype": "postalcode"
  },
  "geometry": {"coordinates":[-2.159306,53.267763],"type":"Point"}
}
