{
  "type": "Feature",
  "properties": {
    "iso:country":"GB",
    "wof:name":"NN2 8AR",
    "wof:placetype":"postalcode"
},
  "geometry": {"coordinates":[-0.90778688909203,52.2682665038985],"type":"Point"}
}