{
  "type": "Feature",
  "properties": {
    "iso:country":"GB",
    "wof:name":"NW2 3XA",
    "wof:placetype":"postalcode"
},
  "geometry": {"coordinates":[-0.21409504261866,51.55354505066445],"type":"Point"}
}