{
  "type": "Feature",
  "properties": {
    "iso:country":"GB",
    "wof:name":"WC1X 8PA",
    "wof:placetype":"postalcode"
},
  "geometry": {"coordinates":[-0.11572844650165,51.5211802288463],"type":"Point"}
}