{
  "type": "Feature",
  "properties": {
    "iso:country":"GB",
    "wof:name":"LE7 2PX",
    "wof:placetype":"postalcode"
},
  "geometry": {"coordinates":[-1.07333756222317,52.69098302547447],"type":"Point"}
}