{
  "type": "Feature",
  "properties": {
    "iso:country":"GB",
    "wof:name":"EX7 0LR",
    "wof:placetype":"postalcode"
},
  "geometry": {"coordinates":[-3.46387972771726,50.5927623817228],"type":"Point"}
}