{
  "type": "Feature",
  "properties": {
    "date:inception_lower": "1980-01-01",
    "date:inception_upper": "1980-01-01",
    "iso:country": "GB",
    "wof:name": "NE13 7DY",
    "wof:placetype": "postalcode"
  },
  "geometry": {"coordinates":[-1.637528,55.047649],"type":"Point"}
}
