{
  "type": "Feature",
  "properties": {
    "iso:country": "GB",
    "wof:name": "NE13 7DY",
    "wof:placetype": "postalcode"
  },
  "geometry": {"coordinates":[-1.637528,55.047649],"type":"Point"}
}
