{
  "type": "Feature",
  "properties": {
    "iso:country":"GB",
    "wof:name":"NE13 7DY",
    "wof:placetype":"postalcode"
},
  "geometry": {"coordinates":[-1.63752853191557,55.04764866102128],"type":"Point"}
}