{
  "type": "Feature",
  "properties": {
    "iso:country":"GB",
    "wof:name":"LS7 4EE",
    "wof:placetype":"postalcode"
},
  "geometry": {"coordinates":[-1.53141854725156,53.81596411460067],"type":"Point"}
}