{
  "type": "Feature",
  "properties": {
    "iso:country": "GB",
    "wof:name": "M14 7ED",
    "wof:placetype": "postalcode"
  },
  "geometry": {"coordinates":[-2.235838,53.442286],"type":"Point"}
}
