{
  "type": "Feature",
  "properties": {
    "iso:country":"GB",
    "wof:name":"M14 7ED",
    "wof:placetype":"postalcode"
},
  "geometry": {"coordinates":[-2.23583807452837,53.44228606198794],"type":"Point"}
}