{
  "type": "Feature",
  "properties": {
    "iso:country":"GB",
    "wof:name":"BH22 0LL",
    "wof:placetype":"postalcode"
},
  "geometry": {"coordinates":[-1.89092450957505,50.83184700636222],"type":"Point"}
}