{
  "type": "Feature",
  "properties": {
    "iso:country":"GB",
    "wof:name":"PO12 2TA",
    "wof:placetype":"postalcode"
},
  "geometry": {"coordinates":[-1.16682465007461,50.79138953609412],"type":"Point"}
}