{
  "type": "Feature",
  "properties": {
    "iso:country": "GB",
    "wof:name": "S43 1AB",
    "wof:placetype": "postalcode"
  },
  "geometry": {"coordinates":[-1.401355,53.254459],"type":"Point"}
}
