{
  "type": "Feature",
  "properties": {
    "iso:country":"GB",
    "wof:name":"IV21 2BS",
    "wof:placetype":"postalcode"
},
  "geometry": {"coordinates":[-5.69329250957988,57.72789120724099],"type":"Point"}
}