{
  "type": "Feature",
  "properties": {
    "iso:country":"GB",
    "wof:name":"LE18 4PX",
    "wof:placetype":"postalcode"
},
  "geometry": {"coordinates":[-1.13330755151938,52.57783897263874],"type":"Point"}
}