{
  "type": "Feature",
  "properties": {
    "iso:country":"GB",
    "wof:name":"SR3 3XE",
    "wof:placetype":"postalcode"
},
  "geometry": {"coordinates":[-1.43899975324623,54.8645897391683],"type":"Point"}
}