{
  "type": "Feature",
  "properties": {
    "date:inception_lower": "1994-05-01",
    "date:inception_upper": "1994-05-01",
    "iso:country": "GB",
    "wof:name": "SR3 3XE",
    "wof:placetype": "postalcode"
  },
  "geometry": {"coordinates":[-1.439,54.86459],"type":"Point"}
}
