{
  "type": "Feature",
  "properties": {
    "iso:country":"GB",
    "wof:name":"ML4 1PA",
    "wof:placetype":"postalcode"
},
  "geometry": {"coordinates":[-4.01905469774721,55.8179603442968],"type":"Point"}
}