{
  "type": "Feature",
  "properties": {
    "iso:country":"GB",
    "wof:name":"HD2 1JP",
    "wof:placetype":"postalcode"
},
  "geometry": {"coordinates":[-1.76041577619898,53.67146440805421],"type":"Point"}
}