{
  "type": "Feature",
  "properties": {
    "iso:country":"GB",
    "wof:name":"ME2 4PA",
    "wof:placetype":"postalcode"
},
  "geometry": {"coordinates":[0.50061580817254,51.40598096955665],"type":"Point"}
}