{
  "type": "Feature",
  "properties": {
    "iso:country":"GB",
    "wof:name":"NE23 6XG",
    "wof:placetype":"postalcode"
},
  "geometry": {"coordinates":[-1.55390169832061,55.07900240555745],"type":"Point"}
}