{
  "type": "Feature",
  "properties": {
    "date:inception_lower":"1980-01-01",
    "date:inception_upper":"1980-01-31",
    "iso:country":"GB",
    "wof:name":"NE23 6XG",
    "wof:placetype":"postalcode"
},
  "geometry": {"coordinates":[-1.553902,55.079002],"type":"Point"}
}