{
  "type": "Feature",
  "properties": {
    "iso:country":"GB",
    "wof:name":"WN6 7TD",
    "wof:placetype":"postalcode"
},
  "geometry": {"coordinates":[-2.66046144825165,53.55683369371111],"type":"Point"}
}