{
  "type": "Feature",
  "properties": {
    "iso:country": "GB",
    "wof:name": "AB51 7NE",
    "wof:placetype": "postalcode"
  },
  "geometry": {"coordinates":[-2.525041,57.160702],"type":"Point"}
}
