{
  "type": "Feature",
  "properties": {
    "iso:country":"GB",
    "wof:name":"AB51 7NE",
    "wof:placetype":"postalcode"
},
  "geometry": {"coordinates":[-2.52479507471876,57.16004339502154],"type":"Point"}
}