{
  "type": "Feature",
  "properties": {
    "iso:country": "GB",
    "wof:name": "NW10 7BZ",
    "wof:placetype": "postalcode"
  },
  "geometry": {"coordinates":[-0.264463,51.531622],"type":"Point"}
}
