{
  "type": "Feature",
  "properties": {
    "iso:country":"GB",
    "wof:name":"NE11 9PU",
    "wof:placetype":"postalcode"
},
  "geometry": {"coordinates":[-1.6434911249645,54.94182653972887],"type":"Point"}
}