{
  "type": "Feature",
  "properties": {
    "iso:country": "GB",
    "wof:name": "NE11 9PU",
    "wof:placetype": "postalcode"
  },
  "geometry": {"coordinates":[-1.643491,54.941827],"type":"Point"}
}
