{
  "type": "Feature",
  "properties": {
    "iso:country":"GB",
    "wof:name":"M16 8QJ",
    "wof:placetype":"postalcode"
},
  "geometry": {"coordinates":[-2.25216749945014,53.44653120772735],"type":"Point"}
}