{
  "type": "Feature",
  "properties": {
    "iso:country": "GB",
    "wof:name": "HA3 7JU",
    "wof:placetype": "postalcode"
  },
  "geometry": {"coordinates":[-0.329096,51.599751],"type":"Point"}
}
