{
  "type": "Feature",
  "properties": {
    "iso:country":"GB",
    "wof:name":"HA3 7JU",
    "wof:placetype":"postalcode"
},
  "geometry": {"coordinates":[-0.32909599151619,51.59975051747413],"type":"Point"}
}