{
  "type": "Feature",
  "properties": {
    "iso:country":"GB",
    "wof:name":"MK45 3WY",
    "wof:placetype":"postalcode"
},
  "geometry": {"coordinates":[-0.44485709669233,52.07319991454752],"type":"Point"}
}