{
  "type": "Feature",
  "properties": {
    "iso:country": "GB",
    "wof:name": "RG1 5RA",
    "wof:placetype": "postalcode"
  },
  "geometry": {"coordinates":[-0.944682,51.450288],"type":"Point"}
}
