{
  "type": "Feature",
  "properties": {
    "iso:country": "GB",
    "wof:name": "RH17 6FP",
    "wof:placetype": "postalcode"
  },
  "geometry": {"coordinates":[-0.200438,51.058337],"type":"Point"}
}
