{
  "type": "Feature",
  "properties": {
    "date:inception_lower": "2021-04-01",
    "date:inception_upper": "2021-04-01",
    "iso:country": "GB",
    "wof:name": "SO31 8NW",
    "wof:placetype": "postalcode"
  },
  "geometry": {"coordinates":[-1.323349,50.895205],"type":"Point"}
}
