{
  "type": "Feature",
  "properties": {
    "iso:country":"GB",
    "wof:name":"EH47 0QL",
    "wof:placetype":"postalcode"
},
  "geometry": {"coordinates":[-3.69587918422697,55.86488056103842],"type":"Point"}
}