{
  "type": "Feature",
  "properties": {
    "iso:country":"GB",
    "wof:name":"SY20 8HQ",
    "wof:placetype":"postalcode"
},
  "geometry": {"coordinates":[-3.83407416039393,52.59680228384029],"type":"Point"}
}