{
  "type": "Feature",
  "properties": {
    "iso:country":"GB",
    "wof:name":"IP19 8SW",
    "wof:placetype":"postalcode"
},
  "geometry": {"coordinates":[1.50341647580042,52.3423124617656],"type":"Point"}
}