{
  "type": "Feature",
  "properties": {
    "date:inception_lower": "1997-12-01",
    "date:inception_upper": "1997-12-01",
    "iso:country": "GB",
    "wof:name": "IP19 8SW",
    "wof:placetype": "postalcode"
  },
  "geometry": {"coordinates":[1.503319,52.342383],"type":"Point"}
}
