{
  "type": "Feature",
  "properties": {
    "date:inception_lower": "1980-01-01",
    "date:inception_upper": "1980-01-01",
    "iso:country": "GB",
    "wof:name": "L10 4YT",
    "wof:placetype": "postalcode"
  },
  "geometry": {"coordinates":[-2.910057,53.469011],"type":"Point"}
}
