{
  "type": "Feature",
  "properties": {
    "iso:country":"GB",
    "wof:name":"NW11 7AX",
    "wof:placetype":"postalcode"
},
  "geometry": {"coordinates":[-0.18673841666784,51.57948212879062],"type":"Point"}
}