{
  "type": "Feature",
  "properties": {
    "iso:country": "GB",
    "wof:name": "PO38 2HB",
    "wof:placetype": "postalcode"
  },
  "geometry": {"coordinates":[-1.316459,50.597559],"type":"Point"}
}
