{
  "type": "Feature",
  "properties": {
    "iso:country":"GB",
    "wof:name":"KY2 5AZ",
    "wof:placetype":"postalcode"
},
  "geometry": {"coordinates":[-3.16151395944385,56.12171380319549],"type":"Point"}
}