{
  "type": "Feature",
  "properties": {
    "date:inception_lower": "1980-01-01",
    "date:inception_upper": "1980-01-01",
    "iso:country": "GB",
    "wof:name": "SA18 2BL",
    "wof:placetype": "postalcode"
  },
  "geometry": {"coordinates":[-3.905149,51.805856],"type":"Point"}
}
