{
  "type": "Feature",
  "properties": {
    "iso:country":"GB",
    "wof:name":"SG7 5RN",
    "wof:placetype":"postalcode"
},
  "geometry": {"coordinates":[-0.12801429478594,52.03628573271801],"type":"Point"}
}