{
  "type": "Feature",
  "properties": {
    "iso:country":"GB",
    "wof:name":"G14 9PP",
    "wof:placetype":"postalcode"
},
  "geometry": {"coordinates":[-4.33518640328534,55.8808927644447],"type":"Point"}
}