{
  "type": "Feature",
  "properties": {
    "date:inception_lower":"1995-12-01",
    "date:inception_upper":"1995-12-31",
    "iso:country":"GB",
    "wof:name":"EN7 5RG",
    "wof:placetype":"postalcode"
},
  "geometry": {"coordinates":[-0.068255,51.707748],"type":"Point"}
}