{
  "type": "Feature",
  "properties": {
    "iso:country":"GB",
    "wof:name":"EN7 5RG",
    "wof:placetype":"postalcode"
},
  "geometry": {"coordinates":[-0.06825488050936,51.70774774878947],"type":"Point"}
}