{
  "type": "Feature",
  "properties": {
    "iso:country": "GB",
    "wof:name": "IP7 5JQ",
    "wof:placetype": "postalcode"
  },
  "geometry": {"coordinates":[0.959235,52.039544],"type":"Point"}
}
