{
  "type": "Feature",
  "properties": {
    "iso:country":"GB",
    "wof:name":"EX6 7RA",
    "wof:placetype":"postalcode"
},
  "geometry": {"coordinates":[-3.59139627352812,50.66834356107163],"type":"Point"}
}