{
  "type": "Feature",
  "properties": {
    "iso:country": "GB",
    "wof:name": "EX6 7RA",
    "wof:placetype": "postalcode"
  },
  "geometry": {"coordinates":[-3.591411,50.668332],"type":"Point"}
}
