{
  "type": "Feature",
  "properties": {
    "date:inception_lower": "1980-01-01",
    "date:inception_upper": "1980-01-01",
    "iso:country": "GB",
    "wof:name": "EX6 7RA",
    "wof:placetype": "postalcode"
  },
  "geometry": {"coordinates":[-3.592209,50.668492],"type":"Point"}
}
