{
  "type": "Feature",
  "properties": {
    "iso:country": "GB",
    "wof:name": "HR7 4SY",
    "wof:placetype": "postalcode"
  },
  "geometry": {"coordinates":[-2.54845,52.193338],"type":"Point"}
}
