{
  "type": "Feature",
  "properties": {
    "date:inception_lower":"1995-07-01",
    "date:inception_upper":"1995-07-31",
    "iso:country":"GB",
    "wof:name":"RG42 3UD",
    "wof:placetype":"postalcode"
},
  "geometry": {"coordinates":[-0.728739,51.42242],"type":"Point"}
}