{
  "type": "Feature",
  "properties": {
    "iso:country":"GB",
    "wof:name":"DN6 8ER",
    "wof:placetype":"postalcode"
},
  "geometry": {"coordinates":[-1.19920766702398,53.58724189632128],"type":"Point"}
}