{
  "type": "Feature",
  "properties": {
    "iso:country":"GB",
    "wof:name":"AB24 5HJ",
    "wof:placetype":"postalcode"
},
  "geometry": {"coordinates":[-2.08720085668234,57.15088859027333],"type":"Point"}
}