{
  "type": "Feature",
  "properties": {
    "iso:country":"GB",
    "wof:name":"HA8 7BU",
    "wof:placetype":"postalcode"
},
  "geometry": {"coordinates":[-0.28110501539992,51.61186248217129],"type":"Point"}
}