{
  "type": "Feature",
  "properties": {
    "iso:country":"GB",
    "wof:name":"BS10 7FG",
    "wof:placetype":"postalcode"
},
  "geometry": {"coordinates":[-2.62117801540652,51.50224001900796],"type":"Point"}
}