{
  "type": "Feature",
  "properties": {
    "iso:country":"GB",
    "wof:name":"N16 0XH",
    "wof:placetype":"postalcode"
},
  "geometry": {"coordinates":[-0.07712666358343,51.5700846455576],"type":"Point"}
}