{
  "type": "Feature",
  "properties": {
    "iso:country":"GB",
    "wof:name":"SY8 1XS",
    "wof:placetype":"postalcode"
},
  "geometry": {"coordinates":[-2.7007203095987,52.37310470153765],"type":"Point"}
}