{
  "type": "Feature",
  "properties": {
    "date:inception_lower": "2000-12-01",
    "date:inception_upper": "2000-12-01",
    "iso:country": "GB",
    "wof:name": "SY8 1XS",
    "wof:placetype": "postalcode"
  },
  "geometry": {"coordinates":[-2.70072,52.373105],"type":"Point"}
}
