{
  "type": "Feature",
  "properties": {
    "iso:country": "GB",
    "wof:name": "SY8 1XS",
    "wof:placetype": "postalcode"
  },
  "geometry": {"coordinates":[-2.70072,52.373105],"type":"Point"}
}
