{
  "type": "Feature",
  "properties": {
    "date:inception_lower": "1993-08-01",
    "date:inception_upper": "1993-08-01",
    "iso:country": "GB",
    "wof:name": "WN3 4PF",
    "wof:placetype": "postalcode"
  },
  "geometry": {"coordinates":[-2.607763,53.528431],"type":"Point"}
}
