{
  "type": "Feature",
  "properties": {
    "iso:country":"GB",
    "wof:name":"WN3 4PF",
    "wof:placetype":"postalcode"
},
  "geometry": {"coordinates":[-2.60776319330939,53.52843091704031],"type":"Point"}
}