{
  "type": "Feature",
  "properties": {
    "iso:country":"GB",
    "wof:name":"RG20 0EX",
    "wof:placetype":"postalcode"
},
  "geometry": {"coordinates":[-1.34677468626864,51.39901528016701],"type":"Point"}
}