{
  "type": "Feature",
  "properties": {
    "iso:country":"GB",
    "wof:name":"SK12 1UG",
    "wof:placetype":"postalcode"
},
  "geometry": {"coordinates":[-2.12699299293627,53.35168502865675],"type":"Point"}
}