{
  "type": "Feature",
  "properties": {
    "date:inception_lower":"1984-02-01",
    "date:inception_upper":"1984-02-29",
    "iso:country":"GB",
    "wof:name":"SK12 1UG",
    "wof:placetype":"postalcode"
},
  "geometry": {"coordinates":[-2.126993,53.351685],"type":"Point"}
}