{
  "type": "Feature",
  "properties": {
    "date:inception_lower": "2009-09-01",
    "date:inception_upper": "2009-09-01",
    "iso:country": "GB",
    "wof:name": "FK10 3FG",
    "wof:placetype": "postalcode"
  },
  "geometry": {"coordinates":[-3.782805,56.125863],"type":"Point"}
}
