{
  "type": "Feature",
  "properties": {
    "date:inception_lower": "1980-01-01",
    "date:inception_upper": "1980-01-01",
    "iso:country": "GB",
    "wof:name": "S72 8QF",
    "wof:placetype": "postalcode"
  },
  "geometry": {"coordinates":[-1.402634,53.591351],"type":"Point"}
}
