{
  "type": "Feature",
  "properties": {
    "iso:country":"GB",
    "wof:name":"S72 8QF",
    "wof:placetype":"postalcode"
},
  "geometry": {"coordinates":[-1.40263401302859,53.59135123587605],"type":"Point"}
}