{
  "type": "Feature",
  "properties": {
    "iso:country": "GB",
    "wof:name": "S72 8QF",
    "wof:placetype": "postalcode"
  },
  "geometry": {"coordinates":[-1.402634,53.591351],"type":"Point"}
}
