{
  "type": "Feature",
  "properties": {
    "date:inception_lower":"2001-12-01",
    "date:inception_upper":"2001-12-31",
    "iso:country":"GB",
    "wof:name":"DT5 2AJ",
    "wof:placetype":"postalcode"
},
  "geometry": {"coordinates":[-2.438644,50.547105],"type":"Point"}
}