{
  "type": "Feature",
  "properties": {
    "iso:country": "GB",
    "wof:name": "DL10 5DJ",
    "wof:placetype": "postalcode"
  },
  "geometry": {"coordinates":[-1.719485,54.411803],"type":"Point"}
}
