{
  "type": "Feature",
  "properties": {
    "iso:country":"GB",
    "wof:name":"SN11 8BL",
    "wof:placetype":"postalcode"
},
  "geometry": {"coordinates":[-1.99888647836911,51.44132327397543],"type":"Point"}
}