{
  "type": "Feature",
  "properties": {
    "iso:country":"GB",
    "wof:name":"S44 6SE",
    "wof:placetype":"postalcode"
},
  "geometry": {"coordinates":[-1.30036929361452,53.23640756578621],"type":"Point"}
}