{
  "type": "Feature",
  "properties": {
    "date:inception_lower": "1980-01-01",
    "date:inception_upper": "1980-01-01",
    "iso:country": "GB",
    "wof:name": "S44 6SE",
    "wof:placetype": "postalcode"
  },
  "geometry": {"coordinates":[-1.300368,53.236417],"type":"Point"}
}
