{
  "type": "Feature",
  "properties": {
    "iso:country": "GB",
    "wof:name": "HA0 1LF",
    "wof:placetype": "postalcode"
  },
  "geometry": {"coordinates":[-0.302232,51.538739],"type":"Point"}
}
