{
  "type": "Feature",
  "properties": {
    "iso:country":"GB",
    "wof:name":"HA0 1LF",
    "wof:placetype":"postalcode"
},
  "geometry": {"coordinates":[-0.30223220186677,51.53873928588984],"type":"Point"}
}