{
  "type": "Feature",
  "properties": {
    "iso:country":"GB",
    "wof:name":"HA8 8AA",
    "wof:placetype":"postalcode"
},
  "geometry": {"coordinates":[-0.28813076459151,51.61860138999376],"type":"Point"}
}