{
  "type": "Feature",
  "properties": {
    "iso:country": "GB",
    "wof:name": "NR3 2QT",
    "wof:placetype": "postalcode"
  },
  "geometry": {"coordinates":[1.275418,52.651741],"type":"Point"}
}
