{
  "type": "Feature",
  "properties": {
    "iso:country":"GB",
    "wof:name":"BD12 8HQ",
    "wof:placetype":"postalcode"
},
  "geometry": {"coordinates":[-1.77251929686699,53.7399774213522],"type":"Point"}
}