{
  "type": "Feature",
  "properties": {
    "iso:country":"GB",
    "wof:name":"NR9 5NH",
    "wof:placetype":"postalcode"
},
  "geometry": {"coordinates":[1.15506253368963,52.7246082483562],"type":"Point"}
}