{
  "type": "Feature",
  "properties": {
    "iso:country": "GB",
    "wof:name": "NR9 5NH",
    "wof:placetype": "postalcode"
  },
  "geometry": {"coordinates":[1.155063,52.724608],"type":"Point"}
}
