{
  "type": "Feature",
  "properties": {
    "iso:country": "GB",
    "wof:name": "BA22 9BB",
    "wof:placetype": "postalcode"
  },
  "geometry": {"coordinates":[-2.687385,50.921182],"type":"Point"}
}
