{
  "type": "Feature",
  "properties": {
    "date:inception_lower": "1980-01-01",
    "date:inception_upper": "1980-01-01",
    "iso:country": "GB",
    "wof:name": "BA22 9BB",
    "wof:placetype": "postalcode"
  },
  "geometry": {"coordinates":[-2.687134,50.921374],"type":"Point"}
}
