{
  "type": "Feature",
  "properties": {
    "iso:country":"GB",
    "wof:name":"SP4 8AB",
    "wof:placetype":"postalcode"
},
  "geometry": {"coordinates":[-1.77538434605317,51.20086690894821],"type":"Point"}
}