{
  "type": "Feature",
  "properties": {
    "date:inception_lower": "2023-05-01",
    "date:inception_upper": "2023-05-01",
    "iso:country": "GB",
    "wof:name": "BS10 7GA",
    "wof:placetype": "postalcode"
  },
  "geometry": {"coordinates":[-2.617041,51.51475],"type":"Point"}
}
