{
  "type": "Feature",
  "properties": {
    "iso:country":"GB",
    "wof:name":"EH16 5LZ",
    "wof:placetype":"postalcode"
},
  "geometry": {"coordinates":[-3.17147334695871,55.93056437781784],"type":"Point"}
}