{
  "type": "Feature",
  "properties": {
    "iso:country": "GB",
    "wof:name": "PO33 1UL",
    "wof:placetype": "postalcode"
  },
  "geometry": {"coordinates":[-1.113422,50.697596],"type":"Point"}
}
