{
  "type": "Feature",
  "properties": {
    "iso:country":"GB",
    "wof:name":"DN22 0HL",
    "wof:placetype":"postalcode"
},
  "geometry": {"coordinates":[-0.83296426781546,53.29250052866709],"type":"Point"}
}