{
  "type": "Feature",
  "properties": {
    "iso:country":"GB",
    "wof:name":"CH8 7NP",
    "wof:placetype":"postalcode"
},
  "geometry": {"coordinates":[-3.23713157702236,53.27818784400781],"type":"Point"}
}