{
  "type": "Feature",
  "properties": {
    "iso:country": "GB",
    "wof:name": "CV9 3EU",
    "wof:placetype": "postalcode"
  },
  "geometry": {"coordinates":[-1.566607,52.654921],"type":"Point"}
}
