{
  "type": "Feature",
  "properties": {
    "iso:country":"GB",
    "wof:name":"DL13 1HH",
    "wof:placetype":"postalcode"
},
  "geometry": {"coordinates":[-2.21070396500012,54.74262220110273],"type":"Point"}
}