{
  "type": "Feature",
  "properties": {
    "iso:country":"GB",
    "wof:name":"DN5 7LN",
    "wof:placetype":"postalcode"
},
  "geometry": {"coordinates":[-1.18281709967555,53.51278641839811],"type":"Point"}
}