{
  "type": "Feature",
  "properties": {
    "iso:country": "GB",
    "wof:name": "DN5 7LN",
    "wof:placetype": "postalcode"
  },
  "geometry": {"coordinates":[-1.182817,53.512786],"type":"Point"}
}
