{
  "type": "Feature",
  "properties": {
    "iso:country":"GB",
    "wof:name":"NW9 6DQ",
    "wof:placetype":"postalcode"
},
  "geometry": {"coordinates":[-0.25021918524839,51.59174908880756],"type":"Point"}
}