{
  "type": "Feature",
  "properties": {
    "iso:country":"GB",
    "wof:name":"EX1 2TG",
    "wof:placetype":"postalcode"
},
  "geometry": {"coordinates":[-3.50279326430802,50.72318321432483],"type":"Point"}
}