{
  "type": "Feature",
  "properties": {
    "date:inception_lower": "2009-09-01",
    "date:inception_upper": "2009-09-01",
    "iso:country": "GB",
    "wof:name": "SY3 8DP",
    "wof:placetype": "postalcode"
  },
  "geometry": {"coordinates":[-2.794768,52.707462],"type":"Point"}
}
