{
  "type": "Feature",
  "properties": {
    "iso:country":"GB",
    "wof:name":"SY3 8DP",
    "wof:placetype":"postalcode"
},
  "geometry": {"coordinates":[-2.794768138388,52.70746228641144],"type":"Point"}
}