{
  "type": "Feature",
  "properties": {
    "date:inception_lower":"1984-10-01",
    "date:inception_upper":"1984-10-31",
    "iso:country":"GB",
    "wof:name":"PR7 6QJ",
    "wof:placetype":"postalcode"
},
  "geometry": {"coordinates":[-2.673102,53.667375],"type":"Point"}
}