{
  "type": "Feature",
  "properties": {
    "iso:country":"GB",
    "wof:name":"PR7 6QJ",
    "wof:placetype":"postalcode"
},
  "geometry": {"coordinates":[-2.67310186422836,53.66737468729175],"type":"Point"}
}