{
  "type": "Feature",
  "properties": {
    "date:inception_lower":"2009-10-01",
    "date:inception_upper":"2009-10-31",
    "iso:country":"GB",
    "wof:name":"SY8 1FE",
    "wof:placetype":"postalcode"
},
  "geometry": {"coordinates":[-2.720183,52.367692],"type":"Point"}
}