{
  "type": "Feature",
  "properties": {
    "iso:country": "GB",
    "wof:name": "SY8 1FE",
    "wof:placetype": "postalcode"
  },
  "geometry": {"coordinates":[-2.720183,52.367692],"type":"Point"}
}
