{
  "type": "Feature",
  "properties": {
    "iso:country":"GB",
    "wof:name":"SY8 1FE",
    "wof:placetype":"postalcode"
},
  "geometry": {"coordinates":[-2.72018305335451,52.36769237747058],"type":"Point"}
}