{
  "type": "Feature",
  "properties": {
    "date:inception_lower":"2012-02-01",
    "date:inception_upper":"2012-02-29",
    "iso:country":"GB",
    "wof:name":"FK7 8AA",
    "wof:placetype":"postalcode"
},
  "geometry": {"coordinates":[-3.896914,56.057026],"type":"Point"}
}