{
  "type": "Feature",
  "properties": {
    "iso:country":"GB",
    "wof:name":"FK7 8AA",
    "wof:placetype":"postalcode"
},
  "geometry": {"coordinates":[-3.89691383936331,56.05702586168815],"type":"Point"}
}