{
  "type": "Feature",
  "properties": {
    "iso:country": "GB",
    "wof:name": "FK7 8AA",
    "wof:placetype": "postalcode"
  },
  "geometry": {"coordinates":[-3.896914,56.057026],"type":"Point"}
}
