{
  "type": "Feature",
  "properties": {
    "iso:country": "GB",
    "wof:name": "MK44 3QQ",
    "wof:placetype": "postalcode"
  },
  "geometry": {"coordinates":[-0.372248,52.138235],"type":"Point"}
}
