{
  "type": "Feature",
  "properties": {
    "iso:country":"GB",
    "wof:name":"MK44 3QQ",
    "wof:placetype":"postalcode"
},
  "geometry": {"coordinates":[-0.37224835302331,52.13823452956467],"type":"Point"}
}