{
  "type": "Feature",
  "properties": {
    "iso:country":"GB",
    "wof:name":"RG17 8YB",
    "wof:placetype":"postalcode"
},
  "geometry": {"coordinates":[-1.52954161367438,51.51023594144166],"type":"Point"}
}