{
  "type": "Feature",
  "properties": {
    "date:inception_lower": "1995-07-01",
    "date:inception_upper": "1995-07-01",
    "iso:country": "GB",
    "wof:name": "RG17 8YB",
    "wof:placetype": "postalcode"
  },
  "geometry": {"coordinates":[-1.529542,51.510236],"type":"Point"}
}
