{
  "type": "Feature",
  "properties": {
    "iso:country":"GB",
    "wof:name":"BL9 6PR",
    "wof:placetype":"postalcode"
},
  "geometry": {"coordinates":[-2.2908988796309,53.61028358594034],"type":"Point"}
}