{
  "type": "Feature",
  "properties": {
    "iso:country":"GB",
    "wof:name":"BL8 2PW",
    "wof:placetype":"postalcode"
},
  "geometry": {"coordinates":[-2.31881638534682,53.59038423579374],"type":"Point"}
}