{
  "type": "Feature",
  "properties": {
    "iso:country": "GB",
    "wof:name": "SS7 3AN",
    "wof:placetype": "postalcode"
  },
  "geometry": {"coordinates":[0.576628,51.564886],"type":"Point"}
}
