{
  "type": "Feature",
  "properties": {
    "iso:country":"GB",
    "wof:name":"SS7 3AN",
    "wof:placetype":"postalcode"
},
  "geometry": {"coordinates":[0.57662798687141,51.56488610545821],"type":"Point"}
}