{
  "type": "Feature",
  "properties": {
    "iso:country": "GB",
    "wof:name": "PO10 7RN",
    "wof:placetype": "postalcode"
  },
  "geometry": {"coordinates":[-0.931518,50.860039],"type":"Point"}
}
