{
  "type": "Feature",
  "properties": {
    "iso:country":"GB",
    "wof:name":"BL9 6EQ",
    "wof:placetype":"postalcode"
},
  "geometry": {"coordinates":[-2.28542514672123,53.60322300300957],"type":"Point"}
}