{
  "type": "Feature",
  "properties": {
    "date:inception_lower": "2022-08-01",
    "date:inception_upper": "2022-08-01",
    "iso:country": "GB",
    "wof:name": "KA10 7GR",
    "wof:placetype": "postalcode"
  },
  "geometry": {"coordinates":[-4.635275,55.556814],"type":"Point"}
}
