{
  "type": "Feature",
  "properties": {
    "date:inception_lower": "1980-01-01",
    "date:inception_upper": "1980-01-01",
    "iso:country": "GB",
    "wof:name": "RH12 3PZ",
    "wof:placetype": "postalcode"
  },
  "geometry": {"coordinates":[-0.400317,51.100228],"type":"Point"}
}
