{
  "type": "Feature",
  "properties": {
    "iso:country":"GB",
    "wof:name":"RH12 3PZ",
    "wof:placetype":"postalcode"
},
  "geometry": {"coordinates":[-0.39924198472249,51.1019072061427],"type":"Point"}
}