{
  "type": "Feature",
  "properties": {
    "date:inception_lower": "2020-11-01",
    "date:inception_upper": "2020-11-01",
    "iso:country": "GB",
    "wof:name": "G3 7AF",
    "wof:placetype": "postalcode"
  },
  "geometry": {"coordinates":[-4.272156,55.864416],"type":"Point"}
}
