{
  "type": "Feature",
  "properties": {
    "iso:country": "GB",
    "wof:name": "GL12 8NF",
    "wof:placetype": "postalcode"
  },
  "geometry": {"coordinates":[-2.411734,51.606519],"type":"Point"}
}
