{
  "type": "Feature",
  "properties": {
    "iso:country":"GB",
    "wof:name":"W2 4TT",
    "wof:placetype":"postalcode"
},
  "geometry": {"coordinates":[-0.19440990836382,51.51371310129484],"type":"Point"}
}