{
  "type": "Feature",
  "properties": {
    "iso:country": "GB",
    "wof:name": "LS9 6DH",
    "wof:placetype": "postalcode"
  },
  "geometry": {"coordinates":[-1.511256,53.80748],"type":"Point"}
}
