{
  "type": "Feature",
  "properties": {
    "iso:country":"GB",
    "wof:name":"LS9 6DH",
    "wof:placetype":"postalcode"
},
  "geometry": {"coordinates":[-1.51125583199392,53.8074798922648],"type":"Point"}
}