{
  "type": "Feature",
  "properties": {
    "iso:country": "GB",
    "wof:name": "FK2 0SX",
    "wof:placetype": "postalcode"
  },
  "geometry": {"coordinates":[-3.714796,55.981108],"type":"Point"}
}
