{
  "type": "Feature",
  "properties": {
    "iso:country":"GB",
    "wof:name":"HP23 6HX",
    "wof:placetype":"postalcode"
},
  "geometry": {"coordinates":[-0.63677647889742,51.77160287985821],"type":"Point"}
}