{
  "type": "Feature",
  "properties": {
    "iso:country": "GB",
    "wof:name": "KT2 6DU",
    "wof:placetype": "postalcode"
  },
  "geometry": {"coordinates":[-0.297685,51.415091],"type":"Point"}
}
