{
  "type": "Feature",
  "properties": {
    "iso:country":"GB",
    "wof:name":"KT2 6DU",
    "wof:placetype":"postalcode"
},
  "geometry": {"coordinates":[-0.29768510316824,51.41509104363438],"type":"Point"}
}