{
  "type": "Feature",
  "properties": {
    "date:inception_lower":"1980-01-01",
    "date:inception_upper":"1980-01-31",
    "iso:country":"GB",
    "wof:name":"ME13 9DY",
    "wof:placetype":"postalcode"
},
  "geometry": {"coordinates":[0.946805,51.327473],"type":"Point"}
}