{
  "type": "Feature",
  "properties": {
    "iso:country":"GB",
    "wof:name":"WA3 3EB",
    "wof:placetype":"postalcode"
},
  "geometry": {"coordinates":[-2.58790499509175,53.47900340105068],"type":"Point"}
}