{
  "type": "Feature",
  "properties": {
    "date:inception_lower":"1980-01-01",
    "date:inception_upper":"1980-01-31",
    "iso:country":"GB",
    "wof:name":"WA3 3EB",
    "wof:placetype":"postalcode"
},
  "geometry": {"coordinates":[-2.587905,53.479003],"type":"Point"}
}