{
  "type": "Feature",
  "properties": {
    "iso:country": "GB",
    "wof:name": "KT21 2HL",
    "wof:placetype": "postalcode"
  },
  "geometry": {"coordinates":[-0.320055,51.313583],"type":"Point"}
}
