{
  "type": "Feature",
  "properties": {
    "date:inception_lower": "1998-06-01",
    "date:inception_upper": "1998-06-01",
    "iso:country": "GB",
    "wof:name": "YO25 3BG",
    "wof:placetype": "postalcode"
  },
  "geometry": {"coordinates":[-0.446432,54.0591],"type":"Point"}
}
