{
  "type": "Feature",
  "properties": {
    "iso:country":"GB",
    "wof:name":"YO25 3BG",
    "wof:placetype":"postalcode"
},
  "geometry": {"coordinates":[-0.44655715474261,54.05951367712243],"type":"Point"}
}