{
  "type": "Feature",
  "properties": {
    "iso:country":"GB",
    "wof:name":"ST20 0RB",
    "wof:placetype":"postalcode"
},
  "geometry": {"coordinates":[-2.34194710480509,52.85588462913285],"type":"Point"}
}