{
  "type": "Feature",
  "properties": {
    "iso:country": "GB",
    "wof:name": "ST20 0RB",
    "wof:placetype": "postalcode"
  },
  "geometry": {"coordinates":[-2.341947,52.855885],"type":"Point"}
}
