{
  "type": "Feature",
  "properties": {
    "iso:country":"GB",
    "wof:name":"SA43 1NH",
    "wof:placetype":"postalcode"
},
  "geometry": {"coordinates":[-4.64739608943646,52.09152405801911],"type":"Point"}
}