{
  "type": "Feature",
  "properties": {
    "iso:country":"GB",
    "wof:name":"LA5 8LB",
    "wof:placetype":"postalcode"
},
  "geometry": {"coordinates":[-2.79563099705823,54.10519671930331],"type":"Point"}
}