{
  "type": "Feature",
  "properties": {
    "iso:country":"GB",
    "wof:name":"YO8 4PF",
    "wof:placetype":"postalcode"
},
  "geometry": {"coordinates":[-1.06795676489497,53.7842809590348],"type":"Point"}
}