{
  "type": "Feature",
  "properties": {
    "date:inception_lower":"1984-10-01",
    "date:inception_upper":"1984-10-31",
    "iso:country":"GB",
    "wof:name":"RH17 5PU",
    "wof:placetype":"postalcode"
},
  "geometry": {"coordinates":[-0.202702,50.992825],"type":"Point"}
}