{
  "type": "Feature",
  "properties": {
    "iso:country":"GB",
    "wof:name":"RH17 5PU",
    "wof:placetype":"postalcode"
},
  "geometry": {"coordinates":[-0.20270162371037,50.99282465765236],"type":"Point"}
}