{
  "type": "Feature",
  "properties": {
    "iso:country":"GB",
    "wof:name":"CV6 7HX",
    "wof:placetype":"postalcode"
},
  "geometry": {"coordinates":[-1.48007364562504,52.42643573602627],"type":"Point"}
}