{
  "type": "Feature",
  "properties": {
    "iso:country":"GB",
    "wof:name":"BD17 5BD",
    "wof:placetype":"postalcode"
},
  "geometry": {"coordinates":[-1.7936784583899,53.8463973942862],"type":"Point"}
}