{
  "type": "Feature",
  "properties": {
    "date:inception_lower":"1980-01-01",
    "date:inception_upper":"1980-01-31",
    "iso:country":"GB",
    "wof:name":"BD17 5BD",
    "wof:placetype":"postalcode"
},
  "geometry": {"coordinates":[-1.793678,53.846397],"type":"Point"}
}