{
  "type": "Feature",
  "properties": {
    "iso:country": "GB",
    "wof:name": "BD17 5BD",
    "wof:placetype": "postalcode"
  },
  "geometry": {"coordinates":[-1.793678,53.846397],"type":"Point"}
}
