{
  "type": "Feature",
  "properties": {
    "date:inception_lower": "1990-02-01",
    "date:inception_upper": "1990-02-01",
    "iso:country": "GB",
    "wof:name": "NE4 7HX",
    "wof:placetype": "postalcode"
  },
  "geometry": {"coordinates":[-1.635781,54.962003],"type":"Point"}
}
