{
  "type": "Feature",
  "properties": {
    "iso:country":"GB",
    "wof:name":"SO15 4GZ",
    "wof:placetype":"postalcode"
},
  "geometry": {"coordinates":[-1.44142238832713,50.91993874752994],"type":"Point"}
}