{
  "type": "Feature",
  "properties": {
    "iso:country":"GB",
    "wof:name":"SP7 0LG",
    "wof:placetype":"postalcode"
},
  "geometry": {"coordinates":[-2.24176809985478,50.95568815116319],"type":"Point"}
}