{
  "type": "Feature",
  "properties": {
    "date:inception_lower": "1980-01-01",
    "date:inception_upper": "1980-01-01",
    "iso:country": "GB",
    "wof:name": "SP7 0LG",
    "wof:placetype": "postalcode"
  },
  "geometry": {"coordinates":[-2.239965,50.957564],"type":"Point"}
}
