{
  "type": "Feature",
  "properties": {
    "date:inception_lower":"2012-10-01",
    "date:inception_upper":"2012-10-31",
    "iso:country":"GB",
    "wof:name":"W5 2BF",
    "wof:placetype":"postalcode"
},
  "geometry": {"coordinates":[-0.307653,51.513667],"type":"Point"}
}