{
  "type": "Feature",
  "properties": {
    "iso:country":"GB",
    "wof:name":"CB21 4PP",
    "wof:placetype":"postalcode"
},
  "geometry": {"coordinates":[0.31346531167572,52.08265760299512],"type":"Point"}
}