{
  "type": "Feature",
  "properties": {
    "iso:country": "GB",
    "wof:name": "CB21 4PP",
    "wof:placetype": "postalcode"
  },
  "geometry": {"coordinates":[0.313465,52.082658],"type":"Point"}
}
