{
  "type": "Feature",
  "properties": {
    "date:inception_lower": "2000-10-01",
    "date:inception_upper": "2000-10-01",
    "iso:country": "GB",
    "wof:name": "OX27 0HA",
    "wof:placetype": "postalcode"
  },
  "geometry": {"coordinates":[-1.066013,51.900351],"type":"Point"}
}
