{
  "type": "Feature",
  "properties": {
    "iso:country":"GB",
    "wof:name":"HR1 4AT",
    "wof:placetype":"postalcode"
},
  "geometry": {"coordinates":[-2.65697166966575,52.06633038296474],"type":"Point"}
}