{
  "type": "Feature",
  "properties": {
    "iso:country": "GB",
    "wof:name": "LN4 3LH",
    "wof:placetype": "postalcode"
  },
  "geometry": {"coordinates":[-0.436269,53.096162],"type":"Point"}
}
