{
  "type": "Feature",
  "properties": {
    "iso:country":"GB",
    "wof:name":"LE9 2AE",
    "wof:placetype":"postalcode"
},
  "geometry": {"coordinates":[-1.23435391620514,52.6352349433403],"type":"Point"}
}