{
  "type": "Feature",
  "properties": {
    "iso:country": "GB",
    "wof:name": "SL2 5NL",
    "wof:placetype": "postalcode"
  },
  "geometry": {"coordinates":[-0.572093,51.5107],"type":"Point"}
}
