{
  "type": "Feature",
  "properties": {
    "iso:country":"GB",
    "wof:name":"SL2 5NL",
    "wof:placetype":"postalcode"
},
  "geometry": {"coordinates":[-0.5720925730121,51.51069980179136],"type":"Point"}
}