{
  "type": "Feature",
  "properties": {
    "date:inception_lower": "1980-01-01",
    "date:inception_upper": "1980-01-01",
    "iso:country": "GB",
    "wof:name": "HX2 0LA",
    "wof:placetype": "postalcode"
  },
  "geometry": {"coordinates":[-1.903452,53.725189],"type":"Point"}
}
