{
  "type": "Feature",
  "properties": {
    "iso:country":"GB",
    "wof:name":"IP33 3SL",
    "wof:placetype":"postalcode"
},
  "geometry": {"coordinates":[0.6683084662956,52.2491493861784],"type":"Point"}
}