{
  "type": "Feature",
  "properties": {
    "iso:country":"GB",
    "wof:name":"RM9 5RR",
    "wof:placetype":"postalcode"
},
  "geometry": {"coordinates":[0.1420071280926,51.54172044493613],"type":"Point"}
}