{
  "type": "Feature",
  "properties": {
    "iso:country":"GB",
    "wof:name":"S61 3DU",
    "wof:placetype":"postalcode"
},
  "geometry": {"coordinates":[-1.3866539036823,53.44376866274672],"type":"Point"}
}