{
  "type": "Feature",
  "properties": {
    "iso:country":"GB",
    "wof:name":"LL11 2RE",
    "wof:placetype":"postalcode"
},
  "geometry": {"coordinates":[-2.99518308854567,53.06081780610058],"type":"Point"}
}