{
  "type": "Feature",
  "properties": {
    "date:inception_lower":"1980-01-01",
    "date:inception_upper":"1980-01-31",
    "iso:country":"GB",
    "wof:name":"LL11 2RE",
    "wof:placetype":"postalcode"
},
  "geometry": {"coordinates":[-2.995183,53.060818],"type":"Point"}
}