{
  "type": "Feature",
  "properties": {
    "date:inception_lower": "1980-01-01",
    "date:inception_upper": "1980-01-01",
    "iso:country": "GB",
    "wof:name": "B32 3HG",
    "wof:placetype": "postalcode"
  },
  "geometry": {"coordinates":[-1.989674,52.437484],"type":"Point"}
}
