{
  "type": "Feature",
  "properties": {
    "iso:country":"GB",
    "wof:name":"B32 3HG",
    "wof:placetype":"postalcode"
},
  "geometry": {"coordinates":[-1.9896737652766,52.43748411800433],"type":"Point"}
}