{
  "type": "Feature",
  "properties": {
    "iso:country":"GB",
    "wof:name":"G61 4QU",
    "wof:placetype":"postalcode"
},
  "geometry": {"coordinates":[-4.34797754295214,55.93143836588678],"type":"Point"}
}