{
  "type": "Feature",
  "properties": {
    "iso:country":"GB",
    "wof:name":"WF11 8LZ",
    "wof:placetype":"postalcode"
},
  "geometry": {"coordinates":[-1.26716521360407,53.71244520490193],"type":"Point"}
}