{
  "type": "Feature",
  "properties": {
    "date:inception_lower": "1985-09-01",
    "date:inception_upper": "1985-09-01",
    "iso:country": "GB",
    "wof:name": "G20 6XZ",
    "wof:placetype": "postalcode"
  },
  "geometry": {"coordinates":[-4.272681,55.878369],"type":"Point"}
}
