{
  "type": "Feature",
  "properties": {
    "iso:country":"GB",
    "wof:name":"G20 6XZ",
    "wof:placetype":"postalcode"
},
  "geometry": {"coordinates":[-4.27268139741044,55.87836928320644],"type":"Point"}
}