{
  "type": "Feature",
  "properties": {
    "iso:country":"GB",
    "wof:name":"BS14 9PJ",
    "wof:placetype":"postalcode"
},
  "geometry": {"coordinates":[-2.5622274635538,51.4099777080373],"type":"Point"}
}