{
  "type": "Feature",
  "properties": {
    "iso:country": "GB",
    "wof:name": "AL1 4TN",
    "wof:placetype": "postalcode"
  },
  "geometry": {"coordinates":[-0.307924,51.756629],"type":"Point"}
}
