{
  "type": "Feature",
  "properties": {
    "iso:country": "GB",
    "wof:name": "OX16 9UX",
    "wof:placetype": "postalcode"
  },
  "geometry": {"coordinates":[-1.366204,52.035417],"type":"Point"}
}
