{
  "type": "Feature",
  "properties": {
    "date:inception_lower":"1995-07-01",
    "date:inception_upper":"1995-07-31",
    "iso:country":"GB",
    "wof:name":"OX16 9UX",
    "wof:placetype":"postalcode"
},
  "geometry": {"coordinates":[-1.366204,52.035417],"type":"Point"}
}