{
  "type": "Feature",
  "properties": {
    "iso:country":"GB",
    "wof:name":"OX16 9UX",
    "wof:placetype":"postalcode"
},
  "geometry": {"coordinates":[-1.36627801919016,52.0353435986892],"type":"Point"}
}