{
  "type": "Feature",
  "properties": {
    "iso:country":"GB",
    "wof:name":"B27 7NN",
    "wof:placetype":"postalcode"
},
  "geometry": {"coordinates":[-1.82545328190646,52.44091618599786],"type":"Point"}
}