{
  "type": "Feature",
  "properties": {
    "iso:country":"GB",
    "wof:name":"WF12 0HP",
    "wof:placetype":"postalcode"
},
  "geometry": {"coordinates":[-1.61375110361637,53.65918113271179],"type":"Point"}
}