{
  "type": "Feature",
  "properties": {
    "iso:country": "GB",
    "wof:name": "PR4 6HN",
    "wof:placetype": "postalcode"
  },
  "geometry": {"coordinates":[-2.829219,53.670359],"type":"Point"}
}
