{
  "type": "Feature",
  "properties": {
    "iso:country":"GB",
    "wof:name":"E11 1DF",
    "wof:placetype":"postalcode"
},
  "geometry": {"coordinates":[0.0005591043171,51.56993689826037],"type":"Point"}
}