{
  "type": "Feature",
  "properties": {
    "iso:country": "GB",
    "wof:name": "NE36 0LR",
    "wof:placetype": "postalcode"
  },
  "geometry": {"coordinates":[-1.420332,54.945156],"type":"Point"}
}
