{
  "type": "Feature",
  "properties": {
    "iso:country": "GB",
    "wof:name": "SS13 2DF",
    "wof:placetype": "postalcode"
  },
  "geometry": {"coordinates":[0.51797,51.5662],"type":"Point"}
}
