{
  "type": "Feature",
  "properties": {
    "iso:country": "GB",
    "wof:name": "SE12 0RN",
    "wof:placetype": "postalcode"
  },
  "geometry": {"coordinates":[0.005971,51.446923],"type":"Point"}
}
