{
  "type": "Feature",
  "properties": {
    "iso:country":"GB",
    "wof:name":"CF34 0LU",
    "wof:placetype":"postalcode"
},
  "geometry": {"coordinates":[-3.64115998610482,51.60402935431062],"type":"Point"}
}