{
  "type": "Feature",
  "properties": {
    "iso:country":"GB",
    "wof:name":"ME13 8LS",
    "wof:placetype":"postalcode"
},
  "geometry": {"coordinates":[0.89353788106514,51.30799873882283],"type":"Point"}
}