{
  "type": "Feature",
  "properties": {
    "date:inception_lower": "1980-01-01",
    "date:inception_upper": "1980-01-01",
    "iso:country": "GB",
    "wof:name": "EH42 1NR",
    "wof:placetype": "postalcode"
  },
  "geometry": {"coordinates":[-2.536955,55.998919],"type":"Point"}
}
