{
  "type": "Feature",
  "properties": {
    "iso:country":"GB",
    "wof:name":"EH42 1NR",
    "wof:placetype":"postalcode"
},
  "geometry": {"coordinates":[-2.53695537623917,55.99891939485295],"type":"Point"}
}