{
  "type": "Feature",
  "properties": {
    "iso:country": "GB",
    "wof:name": "LS15 4NN",
    "wof:placetype": "postalcode"
  },
  "geometry": {"coordinates":[-1.384384,53.845653],"type":"Point"}
}
