{
  "type": "Feature",
  "properties": {
    "date:inception_lower":"1998-06-01",
    "date:inception_upper":"1998-06-30",
    "iso:country":"GB",
    "wof:name":"DA2 6RD",
    "wof:placetype":"postalcode"
},
  "geometry": {"coordinates":[0.238525,51.447209],"type":"Point"}
}