{
  "type": "Feature",
  "properties": {
    "iso:country": "GB",
    "wof:name": "L4 5UY",
    "wof:placetype": "postalcode"
  },
  "geometry": {"coordinates":[-2.966552,53.442571],"type":"Point"}
}
