{
  "type": "Feature",
  "properties": {
    "iso:country":"GB",
    "wof:name":"LL15 2RE",
    "wof:placetype":"postalcode"
},
  "geometry": {"coordinates":[-3.34472681964132,53.04182742316838],"type":"Point"}
}