{
  "type": "Feature",
  "properties": {
    "date:inception_lower":"1980-01-01",
    "date:inception_upper":"1980-01-31",
    "iso:country":"GB",
    "wof:name":"LN4 1BE",
    "wof:placetype":"postalcode"
},
  "geometry": {"coordinates":[-0.476067,53.222544],"type":"Point"}
}