{
  "type": "Feature",
  "properties": {
    "iso:country": "GB",
    "wof:name": "LN4 1BE",
    "wof:placetype": "postalcode"
  },
  "geometry": {"coordinates":[-0.476067,53.222544],"type":"Point"}
}
