{
  "type": "Feature",
  "properties": {
    "iso:country":"GB",
    "wof:name":"BN24 5LP",
    "wof:placetype":"postalcode"
},
  "geometry": {"coordinates":[0.3273569882383,50.81739255086464],"type":"Point"}
}