{
  "type": "Feature",
  "properties": {
    "iso:country":"GB",
    "wof:name":"AB25 2DN",
    "wof:placetype":"postalcode"
},
  "geometry": {"coordinates":[-2.12686981281296,57.14661468791866],"type":"Point"}
}