{
  "type": "Feature",
  "properties": {
    "date:inception_lower":"1996-06-01",
    "date:inception_upper":"1996-06-30",
    "iso:country":"GB",
    "wof:name":"AB25 2DN",
    "wof:placetype":"postalcode"
},
  "geometry": {"coordinates":[-2.12687,57.146615],"type":"Point"}
}