{
  "type": "Feature",
  "properties": {
    "iso:country": "GB",
    "wof:name": "AB25 2DN",
    "wof:placetype": "postalcode"
  },
  "geometry": {"coordinates":[-2.12687,57.146615],"type":"Point"}
}
