{
  "type": "Feature",
  "properties": {
    "iso:country": "GB",
    "wof:name": "SL4 1JF",
    "wof:placetype": "postalcode"
  },
  "geometry": {"coordinates":[-0.606689,51.476732],"type":"Point"}
}
