{
  "type": "Feature",
  "properties": {
    "iso:country":"GB",
    "wof:name":"SL4 1JF",
    "wof:placetype":"postalcode"
},
  "geometry": {"coordinates":[-0.60670499856956,51.47673033661579],"type":"Point"}
}