{
  "type": "Feature",
  "properties": {
    "iso:country":"GB",
    "wof:name":"PA3 3RQ",
    "wof:placetype":"postalcode"
},
  "geometry": {"coordinates":[-4.49973876053576,55.85060552164325],"type":"Point"}
}