{
  "type": "Feature",
  "properties": {
    "iso:country":"GB",
    "wof:name":"BD20 5LN",
    "wof:placetype":"postalcode"
},
  "geometry": {"coordinates":[-1.86468760899549,53.87063075321753],"type":"Point"}
}