{
  "type": "Feature",
  "properties": {
    "iso:country":"GB",
    "wof:name":"TF1 5HR",
    "wof:placetype":"postalcode"
},
  "geometry": {"coordinates":[-2.48402788818954,52.69163570129285],"type":"Point"}
}