{
  "type": "Feature",
  "properties": {
    "iso:country":"GB",
    "wof:name":"GL7 5DH",
    "wof:placetype":"postalcode"
},
  "geometry": {"coordinates":[-1.80579458126816,51.73161919179866],"type":"Point"}
}