{
  "type": "Feature",
  "properties": {
    "date:inception_lower": "1983-03-01",
    "date:inception_upper": "1983-03-01",
    "iso:country": "GB",
    "wof:name": "ST7 2EG",
    "wof:placetype": "postalcode"
  },
  "geometry": {"coordinates":[-2.296393,53.098573],"type":"Point"}
}
