{
  "type": "Feature",
  "properties": {
    "iso:country":"GB",
    "wof:name":"ST7 2EG",
    "wof:placetype":"postalcode"
},
  "geometry": {"coordinates":[-2.29639305568766,53.09857260733288],"type":"Point"}
}