{
  "type": "Feature",
  "properties": {
    "iso:country": "GB",
    "wof:name": "ST7 2EG",
    "wof:placetype": "postalcode"
  },
  "geometry": {"coordinates":[-2.296393,53.098573],"type":"Point"}
}
