{
  "type": "Feature",
  "properties": {
    "iso:country":"GB",
    "wof:name":"LE18 2RP",
    "wof:placetype":"postalcode"
},
  "geometry": {"coordinates":[-1.11341031929015,52.57512954246097],"type":"Point"}
}