{
  "type": "Feature",
  "properties": {
    "date:inception_lower": "1980-01-01",
    "date:inception_upper": "1980-01-01",
    "iso:country": "GB",
    "wof:name": "LL22 8EB",
    "wof:placetype": "postalcode"
  },
  "geometry": {"coordinates":[-3.631605,53.277873],"type":"Point"}
}
