{
  "type": "Feature",
  "properties": {
    "iso:country":"GB",
    "wof:name":"LL22 8EB",
    "wof:placetype":"postalcode"
},
  "geometry": {"coordinates":[-3.63160492780767,53.27787342847056],"type":"Point"}
}