{
  "type": "Feature",
  "properties": {
    "iso:country":"GB",
    "wof:name":"RG17 7HR",
    "wof:placetype":"postalcode"
},
  "geometry": {"coordinates":[-1.47292296657902,51.49056460144165],"type":"Point"}
}