{
  "type": "Feature",
  "properties": {
    "iso:country": "GB",
    "wof:name": "S26 2FG",
    "wof:placetype": "postalcode"
  },
  "geometry": {"coordinates":[-1.303652,53.360896],"type":"Point"}
}
