{
  "type": "Feature",
  "properties": {
    "date:inception_lower":"1997-06-01",
    "date:inception_upper":"1997-06-30",
    "iso:country":"GB",
    "wof:name":"S26 2FG",
    "wof:placetype":"postalcode"
},
  "geometry": {"coordinates":[-1.303652,53.360896],"type":"Point"}
}