{
  "type": "Feature",
  "properties": {
    "iso:country": "GB",
    "wof:name": "S35 7HG",
    "wof:placetype": "postalcode"
  },
  "geometry": {"coordinates":[-1.509224,53.480019],"type":"Point"}
}
