{
  "type": "Feature",
  "properties": {
    "iso:country":"GB",
    "wof:name":"S35 7HG",
    "wof:placetype":"postalcode"
},
  "geometry": {"coordinates":[-1.50922386958904,53.48001936762499],"type":"Point"}
}