{
  "type": "Feature",
  "properties": {
    "date:inception_lower": "1992-01-01",
    "date:inception_upper": "1992-01-01",
    "iso:country": "GB",
    "wof:name": "OX4 3AB",
    "wof:placetype": "postalcode"
  },
  "geometry": {"coordinates":[-1.23416,51.741981],"type":"Point"}
}
