{
  "type": "Feature",
  "properties": {
    "iso:country":"GB",
    "wof:name":"S12 9DS",
    "wof:placetype":"postalcode"
},
  "geometry": {"coordinates":[-1.42508482808653,53.3604638191204],"type":"Point"}
}