{
  "type": "Feature",
  "properties": {
    "iso:country":"GB",
    "wof:name":"PE2 9QY",
    "wof:placetype":"postalcode"
},
  "geometry": {"coordinates":[-0.25636915728383,52.56357966612097],"type":"Point"}
}