{
  "type": "Feature",
  "properties": {
    "date:inception_lower": "1980-01-01",
    "date:inception_upper": "1980-01-01",
    "iso:country": "GB",
    "wof:name": "CA1 2TU",
    "wof:placetype": "postalcode"
  },
  "geometry": {"coordinates":[-2.90597,54.890632],"type":"Point"}
}
