{
  "type": "Feature",
  "properties": {
    "date:inception_lower": "2020-06-01",
    "date:inception_upper": "2020-06-01",
    "iso:country": "GB",
    "wof:name": "RM12 6EU",
    "wof:placetype": "postalcode"
  },
  "geometry": {"coordinates":[0.218074,51.545749],"type":"Point"}
}
