{
  "type": "Feature",
  "properties": {
    "iso:country":"GB",
    "wof:name":"M16 9WE",
    "wof:placetype":"postalcode"
},
  "geometry": {"coordinates":[-2.26375647675694,53.45797549265941],"type":"Point"}
}