{
  "type": "Feature",
  "properties": {
    "iso:country":"GB",
    "wof:name":"GL6 7RG",
    "wof:placetype":"postalcode"
},
  "geometry": {"coordinates":[-2.15930508015596,51.79022072921443],"type":"Point"}
}