{
  "type": "Feature",
  "properties": {
    "date:inception_lower": "1980-01-01",
    "date:inception_upper": "1980-01-01",
    "iso:country": "GB",
    "wof:name": "GL6 7RG",
    "wof:placetype": "postalcode"
  },
  "geometry": {"coordinates":[-2.159305,51.790221],"type":"Point"}
}
