{
  "type": "Feature",
  "properties": {
    "iso:country": "GB",
    "wof:name": "OX26 1FD",
    "wof:placetype": "postalcode"
  },
  "geometry": {"coordinates":[-1.180349,51.899575],"type":"Point"}
}
