{
  "type": "Feature",
  "properties": {
    "date:inception_lower": "1980-01-01",
    "date:inception_upper": "1980-01-01",
    "iso:country": "GB",
    "wof:name": "B62 8NH",
    "wof:placetype": "postalcode"
  },
  "geometry": {"coordinates":[-2.039959,52.467502],"type":"Point"}
}
