{
  "type": "Feature",
  "properties": {
    "date:inception_lower": "2019-08-01",
    "date:inception_upper": "2019-08-01",
    "iso:country": "GB",
    "wof:name": "RG6 6EF",
    "wof:placetype": "postalcode"
  },
  "geometry": {"coordinates":[-0.943079,51.440348],"type":"Point"}
}
