{
  "type": "Feature",
  "properties": {
    "iso:country":"GB",
    "wof:name":"G32 7QD",
    "wof:placetype":"postalcode"
},
  "geometry": {"coordinates":[-4.17496024132695,55.84742175448758],"type":"Point"}
}