{
  "type": "Feature",
  "properties": {
    "iso:country": "GB",
    "wof:name": "G32 7QD",
    "wof:placetype": "postalcode"
  },
  "geometry": {"coordinates":[-4.17496,55.847422],"type":"Point"}
}
