{
  "type": "Feature",
  "properties": {
    "date:inception_lower": "2002-06-01",
    "date:inception_upper": "2002-06-01",
    "iso:country": "GB",
    "wof:name": "RH13 9ER",
    "wof:placetype": "postalcode"
  },
  "geometry": {"coordinates":[-0.351442,51.015747],"type":"Point"}
}
