{
  "type": "Feature",
  "properties": {
    "iso:country": "GB",
    "wof:name": "CH63 0NT",
    "wof:placetype": "postalcode"
  },
  "geometry": {"coordinates":[-2.984903,53.310957],"type":"Point"}
}
