{
  "type": "Feature",
  "properties": {
    "iso:country": "GB",
    "wof:name": "S6 6EL",
    "wof:placetype": "postalcode"
  },
  "geometry": {"coordinates":[-1.550413,53.389351],"type":"Point"}
}
