{
  "type": "Feature",
  "properties": {
    "date:inception_lower":"1980-01-01",
    "date:inception_upper":"1980-01-31",
    "iso:country":"GB",
    "wof:name":"S6 6EL",
    "wof:placetype":"postalcode"
},
  "geometry": {"coordinates":[-1.550413,53.389351],"type":"Point"}
}