{
  "type": "Feature",
  "properties": {
    "iso:country":"GB",
    "wof:name":"TR16 6HH",
    "wof:placetype":"postalcode"
},
  "geometry": {"coordinates":[-5.20039944363184,50.21581291726093],"type":"Point"}
}