{
  "type": "Feature",
  "properties": {
    "iso:country": "GB",
    "wof:name": "WF6 2RG",
    "wof:placetype": "postalcode"
  },
  "geometry": {"coordinates":[-1.406462,53.698709],"type":"Point"}
}
