{
  "type": "Feature",
  "properties": {
    "iso:country":"GB",
    "wof:name":"B45 0DD",
    "wof:placetype":"postalcode"
},
  "geometry": {"coordinates":[-2.01184756395329,52.40550632725649],"type":"Point"}
}