{
  "type": "Feature",
  "properties": {
    "date:inception_lower":"1980-01-01",
    "date:inception_upper":"1980-01-31",
    "iso:country":"GB",
    "wof:name":"B45 0DD",
    "wof:placetype":"postalcode"
},
  "geometry": {"coordinates":[-2.011848,52.405506],"type":"Point"}
}