{
  "type": "Feature",
  "properties": {
    "iso:country": "GB",
    "wof:name": "NR14 6LF",
    "wof:placetype": "postalcode"
  },
  "geometry": {"coordinates":[1.4762,52.53036],"type":"Point"}
}
