{
  "type": "Feature",
  "properties": {
    "iso:country":"GB",
    "wof:name":"NR14 6LF",
    "wof:placetype":"postalcode"
},
  "geometry": {"coordinates":[1.47619961835239,52.53035995722433],"type":"Point"}
}