{
  "type": "Feature",
  "properties": {
    "iso:country":"GB",
    "wof:name":"PH18 5TP",
    "wof:placetype":"postalcode"
},
  "geometry": {"coordinates":[-3.83982726059261,56.7750163449174],"type":"Point"}
}