{
  "type": "Feature",
  "properties": {
    "date:inception_lower":"1980-01-01",
    "date:inception_upper":"1980-01-31",
    "iso:country":"GB",
    "wof:name":"PH18 5TP",
    "wof:placetype":"postalcode"
},
  "geometry": {"coordinates":[-3.839827,56.775016],"type":"Point"}
}