{
  "type": "Feature",
  "properties": {
    "iso:country":"GB",
    "wof:name":"SN3 1DH",
    "wof:placetype":"postalcode"
},
  "geometry": {"coordinates":[-1.77074167516536,51.55613667028082],"type":"Point"}
}