{
  "type": "Feature",
  "properties": {
    "date:inception_lower":"1980-01-01",
    "date:inception_upper":"1980-01-31",
    "iso:country":"GB",
    "wof:name":"PO14 1JX",
    "wof:placetype":"postalcode"
},
  "geometry": {"coordinates":[-1.198088,50.843982],"type":"Point"}
}