{
  "type": "Feature",
  "properties": {
    "iso:country": "GB",
    "wof:name": "CO10 0TG",
    "wof:placetype": "postalcode"
  },
  "geometry": {"coordinates":[0.793014,52.086282],"type":"Point"}
}
