{
  "type": "Feature",
  "properties": {
    "iso:country":"GB",
    "wof:name":"CO10 0TG",
    "wof:placetype":"postalcode"
},
  "geometry": {"coordinates":[0.79304227363529,52.08745370992565],"type":"Point"}
}