{
  "type": "Feature",
  "properties": {
    "date:inception_lower": "1983-07-01",
    "date:inception_upper": "1983-07-01",
    "iso:country": "GB",
    "wof:name": "CO10 0TG",
    "wof:placetype": "postalcode"
  },
  "geometry": {"coordinates":[0.792688,52.086434],"type":"Point"}
}
