{
  "type": "Feature",
  "properties": {
    "iso:country": "GB",
    "wof:name": "BS24 8DP",
    "wof:placetype": "postalcode"
  },
  "geometry": {"coordinates":[-2.917499,51.334357],"type":"Point"}
}
