{
  "type": "Feature",
  "properties": {
    "date:inception_lower":"1980-01-01",
    "date:inception_upper":"1980-01-31",
    "iso:country":"GB",
    "wof:name":"BS24 8DP",
    "wof:placetype":"postalcode"
},
  "geometry": {"coordinates":[-2.917492,51.334342],"type":"Point"}
}