{
  "type": "Feature",
  "properties": {
    "iso:country":"GB",
    "wof:name":"BS24 8DP",
    "wof:placetype":"postalcode"
},
  "geometry": {"coordinates":[-2.9174925397398,51.33434229523126],"type":"Point"}
}