{
  "type": "Feature",
  "properties": {
    "iso:country":"GB",
    "wof:name":"HU5 5XJ",
    "wof:placetype":"postalcode"
},
  "geometry": {"coordinates":[-0.40326898088059,53.75586958356581],"type":"Point"}
}