{
  "type": "Feature",
  "properties": {
    "iso:country": "GB",
    "wof:name": "NE31 2PZ",
    "wof:placetype": "postalcode"
  },
  "geometry": {"coordinates":[-1.512812,54.965897],"type":"Point"}
}
