{
  "type": "Feature",
  "properties": {
    "iso:country": "GB",
    "wof:name": "ME14 1JR",
    "wof:placetype": "postalcode"
  },
  "geometry": {"coordinates":[0.527217,51.276513],"type":"Point"}
}
