{
  "type": "Feature",
  "properties": {
    "iso:country": "GB",
    "wof:name": "TW7 4BJ",
    "wof:placetype": "postalcode"
  },
  "geometry": {"coordinates":[-0.352953,51.476229],"type":"Point"}
}
