{
  "type": "Feature",
  "properties": {
    "iso:country":"GB",
    "wof:name":"TW7 4BJ",
    "wof:placetype":"postalcode"
},
  "geometry": {"coordinates":[-0.35295263574538,51.47622854407935],"type":"Point"}
}