{
  "type": "Feature",
  "properties": {
    "date:inception_lower": "1980-01-01",
    "date:inception_upper": "1980-01-01",
    "iso:country": "GB",
    "wof:name": "SA33 4NG",
    "wof:placetype": "postalcode"
  },
  "geometry": {"coordinates":[-4.468665,51.795307],"type":"Point"}
}
