{
  "type": "Feature",
  "properties": {
    "iso:country":"GB",
    "wof:name":"SA33 4NG",
    "wof:placetype":"postalcode"
},
  "geometry": {"coordinates":[-4.46866506518055,51.79530700694469],"type":"Point"}
}