{
  "type": "Feature",
  "properties": {
    "date:inception_lower":"1980-01-01",
    "date:inception_upper":"1980-01-31",
    "iso:country":"GB",
    "wof:name":"BS16 3BA",
    "wof:placetype":"postalcode"
},
  "geometry": {"coordinates":[-2.536321,51.477698],"type":"Point"}
}