{
  "type": "Feature",
  "properties": {
    "date:inception_lower":"1995-07-01",
    "date:inception_upper":"1995-07-31",
    "iso:country":"GB",
    "wof:name":"OL5 9AS",
    "wof:placetype":"postalcode"
},
  "geometry": {"coordinates":[-2.036233,53.521503],"type":"Point"}
}