{
  "type": "Feature",
  "properties": {
    "iso:country":"GB",
    "wof:name":"OL5 9AS",
    "wof:placetype":"postalcode"
},
  "geometry": {"coordinates":[-2.03635615897055,53.52140522716002],"type":"Point"}
}