{
  "type": "Feature",
  "properties": {
    "iso:country":"GB",
    "wof:name":"EX1 2BS",
    "wof:placetype":"postalcode"
},
  "geometry": {"coordinates":[-3.51957248247752,50.72551975983239],"type":"Point"}
}