{
  "type": "Feature",
  "properties": {
    "date:inception_lower": "1980-01-01",
    "date:inception_upper": "1980-01-01",
    "iso:country": "GB",
    "wof:name": "EX1 2BS",
    "wof:placetype": "postalcode"
  },
  "geometry": {"coordinates":[-3.519572,50.72552],"type":"Point"}
}
