{
  "type": "Feature",
  "properties": {
    "date:inception_lower": "1980-01-01",
    "date:inception_upper": "1980-01-01",
    "iso:country": "GB",
    "wof:name": "B12 0QR",
    "wof:placetype": "postalcode"
  },
  "geometry": {"coordinates":[-1.886796,52.470721],"type":"Point"}
}
