{
  "type": "Feature",
  "properties": {
    "iso:country":"GB",
    "wof:name":"B12 0QR",
    "wof:placetype":"postalcode"
},
  "geometry": {"coordinates":[-1.88679580852055,52.47072059778834],"type":"Point"}
}