{
  "type": "Feature",
  "properties": {
    "date:inception_lower": "2007-05-01",
    "date:inception_upper": "2007-05-01",
    "iso:country": "GB",
    "wof:name": "PL1 2AS",
    "wof:placetype": "postalcode"
  },
  "geometry": {"coordinates":[-4.138949,50.368831],"type":"Point"}
}
