{
  "type": "Feature",
  "properties": {
    "iso:country":"GB",
    "wof:name":"PL1 2AS",
    "wof:placetype":"postalcode"
},
  "geometry": {"coordinates":[-4.13894928173436,50.36883077663092],"type":"Point"}
}