{
  "type": "Feature",
  "properties": {
    "iso:country":"GB",
    "wof:name":"S80 4XR",
    "wof:placetype":"postalcode"
},
  "geometry": {"coordinates":[-1.18817024968204,53.28040790333696],"type":"Point"}
}