{
  "type": "Feature",
  "properties": {
    "iso:country": "GB",
    "wof:name": "S80 4XR",
    "wof:placetype": "postalcode"
  },
  "geometry": {"coordinates":[-1.187768,53.28022],"type":"Point"}
}
