{
  "type": "Feature",
  "properties": {
    "iso:country": "GB",
    "wof:name": "CW1 6FX",
    "wof:placetype": "postalcode"
  },
  "geometry": {"coordinates":[-2.429259,53.087406],"type":"Point"}
}
