{
  "type": "Feature",
  "properties": {
    "iso:country": "GB",
    "wof:name": "HP23 6JY",
    "wof:placetype": "postalcode"
  },
  "geometry": {"coordinates":[-0.689595,51.783452],"type":"Point"}
}
