{
  "type": "Feature",
  "properties": {
    "date:inception_lower":"1980-01-01",
    "date:inception_upper":"1980-01-31",
    "iso:country":"GB",
    "wof:name":"HP23 6JY",
    "wof:placetype":"postalcode"
},
  "geometry": {"coordinates":[-0.689595,51.783452],"type":"Point"}
}