{
  "type": "Feature",
  "properties": {
    "iso:country":"GB",
    "wof:name":"HP23 6JY",
    "wof:placetype":"postalcode"
},
  "geometry": {"coordinates":[-0.68959503800846,51.78345192476086],"type":"Point"}
}