{
  "type": "Feature",
  "properties": {
    "iso:country":"GB",
    "wof:name":"TR26 2DP",
    "wof:placetype":"postalcode"
},
  "geometry": {"coordinates":[-5.4830983044013,50.2074926728403],"type":"Point"}
}