{
  "type": "Feature",
  "properties": {
    "date:inception_lower":"1993-01-01",
    "date:inception_upper":"1993-01-31",
    "iso:country":"GB",
    "wof:name":"TR26 2DP",
    "wof:placetype":"postalcode"
},
  "geometry": {"coordinates":[-5.483098,50.207493],"type":"Point"}
}