{
  "type": "Feature",
  "properties": {
    "iso:country": "GB",
    "wof:name": "DN40 2SE",
    "wof:placetype": "postalcode"
  },
  "geometry": {"coordinates":[-0.208846,53.622955],"type":"Point"}
}
