{
  "type": "Feature",
  "properties": {
    "date:inception_lower": "1997-06-01",
    "date:inception_upper": "1997-06-01",
    "iso:country": "GB",
    "wof:name": "DN40 2SE",
    "wof:placetype": "postalcode"
  },
  "geometry": {"coordinates":[-0.208846,53.622955],"type":"Point"}
}
