{
  "type": "Feature",
  "properties": {
    "iso:country":"GB",
    "wof:name":"NG17 4GW",
    "wof:placetype":"postalcode"
},
  "geometry": {"coordinates":[-1.24836665821821,53.13010959574237],"type":"Point"}
}