{
  "type": "Feature",
  "properties": {
    "iso:country": "GB",
    "wof:name": "NG17 4GW",
    "wof:placetype": "postalcode"
  },
  "geometry": {"coordinates":[-1.248367,53.13011],"type":"Point"}
}
