{
  "type": "Feature",
  "properties": {
    "date:inception_lower":"1980-01-01",
    "date:inception_upper":"1980-01-31",
    "iso:country":"GB",
    "wof:name":"NG17 4GW",
    "wof:placetype":"postalcode"
},
  "geometry": {"coordinates":[-1.248367,53.13011],"type":"Point"}
}