{
  "type": "Feature",
  "properties": {
    "date:inception_lower":"1983-01-01",
    "date:inception_upper":"1983-01-31",
    "iso:country":"GB",
    "wof:name":"PE32 2HZ",
    "wof:placetype":"postalcode"
},
  "geometry": {"coordinates":[0.663004,52.778644],"type":"Point"}
}