{
  "type": "Feature",
  "properties": {
    "iso:country": "GB",
    "wof:name": "PE32 2HZ",
    "wof:placetype": "postalcode"
  },
  "geometry": {"coordinates":[0.663004,52.778644],"type":"Point"}
}
