{
  "type": "Feature",
  "properties": {
    "iso:country":"GB",
    "wof:name":"SS6 9LA",
    "wof:placetype":"postalcode"
},
  "geometry": {"coordinates":[0.60599417029152,51.59593026356369],"type":"Point"}
}