{
  "type": "Feature",
  "properties": {
    "date:inception_lower":"1980-01-01",
    "date:inception_upper":"1980-01-31",
    "iso:country":"GB",
    "wof:name":"B68 0EL",
    "wof:placetype":"postalcode"
},
  "geometry": {"coordinates":[-1.997674,52.468869],"type":"Point"}
}