{
  "type": "Feature",
  "properties": {
    "iso:country":"GB",
    "wof:name":"B68 0EL",
    "wof:placetype":"postalcode"
},
  "geometry": {"coordinates":[-1.99767449872344,52.46886861410879],"type":"Point"}
}