{
  "type": "Feature",
  "properties": {
    "iso:country":"GB",
    "wof:name":"WR2 5PP",
    "wof:placetype":"postalcode"
},
  "geometry": {"coordinates":[-2.24862282574487,52.19606875385173],"type":"Point"}
}