{
  "type": "Feature",
  "properties": {
    "iso:country":"GB",
    "wof:name":"HX2 6TG",
    "wof:placetype":"postalcode"
},
  "geometry": {"coordinates":[-1.94028100488225,53.74604723736332],"type":"Point"}
}