{
  "type": "Feature",
  "properties": {
    "iso:country":"GB",
    "wof:name":"LS25 4DR",
    "wof:placetype":"postalcode"
},
  "geometry": {"coordinates":[-1.32431347892986,53.78539678921585],"type":"Point"}
}