{
  "type": "Feature",
  "properties": {
    "date:inception_lower":"2004-06-01",
    "date:inception_upper":"2004-06-30",
    "iso:country":"GB",
    "wof:name":"LS25 4DR",
    "wof:placetype":"postalcode"
},
  "geometry": {"coordinates":[-1.324313,53.785397],"type":"Point"}
}