{
  "type": "Feature",
  "properties": {
    "iso:country": "GB",
    "wof:name": "LS25 4DR",
    "wof:placetype": "postalcode"
  },
  "geometry": {"coordinates":[-1.324313,53.785397],"type":"Point"}
}
