{
  "type": "Feature",
  "properties": {
    "date:inception_lower":"1980-01-01",
    "date:inception_upper":"1980-01-31",
    "iso:country":"GB",
    "wof:name":"CW2 6NU",
    "wof:placetype":"postalcode"
},
  "geometry": {"coordinates":[-2.448212,53.086537],"type":"Point"}
}