{
  "type": "Feature",
  "properties": {
    "iso:country":"GB",
    "wof:name":"CW2 6NU",
    "wof:placetype":"postalcode"
},
  "geometry": {"coordinates":[-2.44821161688763,53.08653745866652],"type":"Point"}
}