{
  "type": "Feature",
  "properties": {
    "iso:country": "GB",
    "wof:name": "CW2 6NU",
    "wof:placetype": "postalcode"
  },
  "geometry": {"coordinates":[-2.448212,53.086537],"type":"Point"}
}
