{
  "type": "Feature",
  "properties": {
    "iso:country":"GB",
    "wof:name":"B32 4HF",
    "wof:placetype":"postalcode"
},
  "geometry": {"coordinates":[-2.00561886365721,52.43404121993968],"type":"Point"}
}