{
  "type": "Feature",
  "properties": {
    "iso:country": "GB",
    "wof:name": "SO15 4LA",
    "wof:placetype": "postalcode"
  },
  "geometry": {"coordinates":[-1.446501,50.918731],"type":"Point"}
}
