{
  "type": "Feature",
  "properties": {
    "iso:country": "GB",
    "wof:name": "TS10 4AD",
    "wof:placetype": "postalcode"
  },
  "geometry": {"coordinates":[-1.080061,54.605466],"type":"Point"}
}
