{
  "type": "Feature",
  "properties": {
    "iso:country":"GB",
    "wof:name":"HU7 4ZP",
    "wof:placetype":"postalcode"
},
  "geometry": {"coordinates":[-0.30743613761576,53.79279459664679],"type":"Point"}
}