{
  "type": "Feature",
  "properties": {
    "date:inception_lower": "2006-09-01",
    "date:inception_upper": "2006-09-01",
    "iso:country": "GB",
    "wof:name": "HU7 4ZP",
    "wof:placetype": "postalcode"
  },
  "geometry": {"coordinates":[-0.307436,53.792795],"type":"Point"}
}
