{
  "type": "Feature",
  "properties": {
    "iso:country":"GB",
    "wof:name":"HU5 2UP",
    "wof:placetype":"postalcode"
},
  "geometry": {"coordinates":[-0.35393232060334,53.75648766000604],"type":"Point"}
}