{
  "type": "Feature",
  "properties": {
    "date:inception_lower": "2023-01-01",
    "date:inception_upper": "2023-01-01",
    "iso:country": "GB",
    "wof:name": "CH66 4AW",
    "wof:placetype": "postalcode"
  },
  "geometry": {"coordinates":[-2.950049,53.277727],"type":"Point"}
}
