{
  "type": "Feature",
  "properties": {
    "date:inception_lower": "2013-07-01",
    "date:inception_upper": "2013-07-01",
    "iso:country": "GB",
    "wof:name": "DN1 9PX",
    "wof:placetype": "postalcode"
  },
  "geometry": {"coordinates":[-1.125573,53.512914],"type":"Point"}
}
