{
  "type": "Feature",
  "properties": {
    "iso:country": "GB",
    "wof:name": "RM15 5DJ",
    "wof:placetype": "postalcode"
  },
  "geometry": {"coordinates":[0.284559,51.511053],"type":"Point"}
}
