{
  "type": "Feature",
  "properties": {
    "date:inception_lower": "1980-01-01",
    "date:inception_upper": "1980-01-01",
    "iso:country": "GB",
    "wof:name": "RM15 5DJ",
    "wof:placetype": "postalcode"
  },
  "geometry": {"coordinates":[0.284559,51.511053],"type":"Point"}
}
