{
  "type": "Feature",
  "properties": {
    "iso:country":"GB",
    "wof:name":"RM15 5DJ",
    "wof:placetype":"postalcode"
},
  "geometry": {"coordinates":[0.28455901043291,51.51105324235183],"type":"Point"}
}