{
  "type": "Feature",
  "properties": {
    "iso:country":"GB",
    "wof:name":"TW7 7HB",
    "wof:placetype":"postalcode"
},
  "geometry": {"coordinates":[-0.32536517052853,51.46513689748611],"type":"Point"}
}