{
  "type": "Feature",
  "properties": {
    "iso:country":"GB",
    "wof:name":"IG8 9PB",
    "wof:placetype":"postalcode"
},
  "geometry": {"coordinates":[0.00584457568497,51.6037846635554],"type":"Point"}
}