{
  "type": "Feature",
  "properties": {
    "iso:country": "GB",
    "wof:name": "OL12 0RB",
    "wof:placetype": "postalcode"
  },
  "geometry": {"coordinates":[-2.156112,53.623497],"type":"Point"}
}
