{
  "type": "Feature",
  "properties": {
    "iso:country":"GB",
    "wof:name":"OL12 0RB",
    "wof:placetype":"postalcode"
},
  "geometry": {"coordinates":[-2.1561121082957,53.62349662757626],"type":"Point"}
}