{
  "type": "Feature",
  "properties": {
    "iso:country":"GB",
    "wof:name":"BH23 3EB",
    "wof:placetype":"postalcode"
},
  "geometry": {"coordinates":[-1.74826790496107,50.74081966073123],"type":"Point"}
}