{
  "type": "Feature",
  "properties": {
    "iso:country":"GB",
    "wof:name":"CW10 9JF",
    "wof:placetype":"postalcode"
},
  "geometry": {"coordinates":[-2.48723904398552,53.20530891897582],"type":"Point"}
}