{
  "type": "Feature",
  "properties": {
    "iso:country": "GB",
    "wof:name": "CW10 9JF",
    "wof:placetype": "postalcode"
  },
  "geometry": {"coordinates":[-2.487239,53.205309],"type":"Point"}
}
