{
  "type": "Feature",
  "properties": {
    "iso:country":"GB",
    "wof:name":"S6 2BP",
    "wof:placetype":"postalcode"
},
  "geometry": {"coordinates":[-1.5002238716606,53.40337231612681],"type":"Point"}
}