{
  "type": "Feature",
  "properties": {
    "iso:country": "GB",
    "wof:name": "S6 2BP",
    "wof:placetype": "postalcode"
  },
  "geometry": {"coordinates":[-1.500224,53.403372],"type":"Point"}
}
