{
  "type": "Feature",
  "properties": {
    "iso:country":"GB",
    "wof:name":"NE24 4EQ",
    "wof:placetype":"postalcode"
},
  "geometry": {"coordinates":[-1.54135144028557,55.12181054959667],"type":"Point"}
}