{
  "type": "Feature",
  "properties": {
    "date:inception_lower": "1980-01-01",
    "date:inception_upper": "1980-01-01",
    "iso:country": "GB",
    "wof:name": "NE24 4EQ",
    "wof:placetype": "postalcode"
  },
  "geometry": {"coordinates":[-1.541351,55.121811],"type":"Point"}
}
