{
  "type": "Feature",
  "properties": {
    "iso:country": "GB",
    "wof:name": "KY13 8FA",
    "wof:placetype": "postalcode"
  },
  "geometry": {"coordinates":[-3.42124,56.203059],"type":"Point"}
}
