{
  "type": "Feature",
  "properties": {
    "date:inception_lower": "2018-04-01",
    "date:inception_upper": "2018-04-01",
    "iso:country": "GB",
    "wof:name": "KY13 8FA",
    "wof:placetype": "postalcode"
  },
  "geometry": {"coordinates":[-3.42124,56.203059],"type":"Point"}
}
