{
  "type": "Feature",
  "properties": {
    "iso:country":"GB",
    "wof:name":"LE11 1EF",
    "wof:placetype":"postalcode"
},
  "geometry": {"coordinates":[-1.20048385681653,52.76983208146606],"type":"Point"}
}