{
  "type": "Feature",
  "properties": {
    "iso:country": "GB",
    "wof:name": "IG5 0NQ",
    "wof:placetype": "postalcode"
  },
  "geometry": {"coordinates":[0.058663,51.596926],"type":"Point"}
}
