{
  "type": "Feature",
  "properties": {
    "iso:country":"GB",
    "wof:name":"IG5 0NQ",
    "wof:placetype":"postalcode"
},
  "geometry": {"coordinates":[0.05866292977552,51.59692595849026],"type":"Point"}
}