{
  "type": "Feature",
  "properties": {
    "date:inception_lower": "1980-01-01",
    "date:inception_upper": "1980-01-01",
    "iso:country": "GB",
    "wof:name": "IG5 0NQ",
    "wof:placetype": "postalcode"
  },
  "geometry": {"coordinates":[0.058663,51.596926],"type":"Point"}
}
