{
  "type": "Feature",
  "properties": {
    "iso:country": "GB",
    "wof:name": "TF11 9LG",
    "wof:placetype": "postalcode"
  },
  "geometry": {"coordinates":[-2.409334,52.641889],"type":"Point"}
}
