{
  "type": "Feature",
  "properties": {
    "date:inception_lower": "2021-05-01",
    "date:inception_upper": "2021-05-01",
    "iso:country": "GB",
    "wof:name": "CM9 6FD",
    "wof:placetype": "postalcode"
  },
  "geometry": {"coordinates":[0.661861,51.716292],"type":"Point"}
}
