{
  "type": "Feature",
  "properties": {
    "iso:country":"GB",
    "wof:name":"NW9 6DF",
    "wof:placetype":"postalcode"
},
  "geometry": {"coordinates":[-0.24981726203046,51.59168914250367],"type":"Point"}
}