{
  "type": "Feature",
  "properties": {
    "iso:country": "GB",
    "wof:name": "CM21 9NF",
    "wof:placetype": "postalcode"
  },
  "geometry": {"coordinates":[0.152681,51.81045],"type":"Point"}
}
