{
  "type": "Feature",
  "properties": {
    "iso:country":"GB",
    "wof:name":"CM21 9NF",
    "wof:placetype":"postalcode"
},
  "geometry": {"coordinates":[0.15268087087234,51.8104503426146],"type":"Point"}
}