{
  "type": "Feature",
  "properties": {
    "iso:country":"GB",
    "wof:name":"BS39 7RD",
    "wof:placetype":"postalcode"
},
  "geometry": {"coordinates":[-2.50317984551667,51.30279465321833],"type":"Point"}
}