{
  "type": "Feature",
  "properties": {
    "iso:country":"GB",
    "wof:name":"BS31 2DF",
    "wof:placetype":"postalcode"
},
  "geometry": {"coordinates":[-2.48697231248158,51.42207579327856],"type":"Point"}
}