{
  "type": "Feature",
  "properties": {
    "iso:country": "GB",
    "wof:name": "TN12 0EW",
    "wof:placetype": "postalcode"
  },
  "geometry": {"coordinates":[0.55138,51.153502],"type":"Point"}
}
