{
  "type": "Feature",
  "properties": {
    "iso:country":"GB",
    "wof:name":"TN12 0EW",
    "wof:placetype":"postalcode"
},
  "geometry": {"coordinates":[0.55129243063481,51.15350429446915],"type":"Point"}
}