{
  "type": "Feature",
  "properties": {
    "date:inception_lower": "1991-01-01",
    "date:inception_upper": "1991-01-01",
    "iso:country": "GB",
    "wof:name": "TN12 0EW",
    "wof:placetype": "postalcode"
  },
  "geometry": {"coordinates":[0.55138,51.153502],"type":"Point"}
}
