{
  "type": "Feature",
  "properties": {
    "date:inception_lower": "2020-04-01",
    "date:inception_upper": "2020-04-01",
    "iso:country": "GB",
    "wof:name": "TR27 6FL",
    "wof:placetype": "postalcode"
  },
  "geometry": {"coordinates":[-5.425095,50.164922],"type":"Point"}
}
