{
  "type": "Feature",
  "properties": {
    "iso:country":"GB",
    "wof:name":"SS15 4JF",
    "wof:placetype":"postalcode"
},
  "geometry": {"coordinates":[0.43122474509122,51.58743314389325],"type":"Point"}
}