{
  "type": "Feature",
  "properties": {
    "iso:country":"GB",
    "wof:name":"SN5 7UZ",
    "wof:placetype":"postalcode"
},
  "geometry": {"coordinates":[-1.81383985838471,51.55978243388494],"type":"Point"}
}