{
  "type": "Feature",
  "properties": {
    "date:inception_lower":"1988-03-01",
    "date:inception_upper":"1988-03-31",
    "iso:country":"GB",
    "wof:name":"SN5 7UZ",
    "wof:placetype":"postalcode"
},
  "geometry": {"coordinates":[-1.81384,51.559782],"type":"Point"}
}