{
  "type": "Feature",
  "properties": {
    "iso:country":"GB",
    "wof:name":"M16 7QQ",
    "wof:placetype":"postalcode"
},
  "geometry": {"coordinates":[-2.26505085819817,53.45784678663696],"type":"Point"}
}