{
  "type": "Feature",
  "properties": {
    "iso:country": "GB",
    "wof:name": "IG3 9BG",
    "wof:placetype": "postalcode"
  },
  "geometry": {"coordinates":[0.096427,51.55347],"type":"Point"}
}
