{
  "type": "Feature",
  "properties": {
    "iso:country":"GB",
    "wof:name":"IG3 9BG",
    "wof:placetype":"postalcode"
},
  "geometry": {"coordinates":[0.09642710845235,51.55347009961486],"type":"Point"}
}