{
  "type": "Feature",
  "properties": {
    "iso:country":"GB",
    "wof:name":"KA15 2EE",
    "wof:placetype":"postalcode"
},
  "geometry": {"coordinates":[-4.63112654747008,55.75818674755084],"type":"Point"}
}