{
  "type": "Feature",
  "properties": {
    "date:inception_lower": "1980-01-01",
    "date:inception_upper": "1980-01-01",
    "iso:country": "GB",
    "wof:name": "KA15 2EE",
    "wof:placetype": "postalcode"
  },
  "geometry": {"coordinates":[-4.631126,55.758187],"type":"Point"}
}
