{
  "type": "Feature",
  "properties": {
    "iso:country": "GB",
    "wof:name": "KA15 2EE",
    "wof:placetype": "postalcode"
  },
  "geometry": {"coordinates":[-4.631126,55.758187],"type":"Point"}
}
