{
  "type": "Feature",
  "properties": {
    "date:inception_lower": "1992-01-01",
    "date:inception_upper": "1992-01-01",
    "iso:country": "GB",
    "wof:name": "LL13 0UX",
    "wof:placetype": "postalcode"
  },
  "geometry": {"coordinates":[-2.93088,53.018387],"type":"Point"}
}
