{
  "type": "Feature",
  "properties": {
    "iso:country":"GB",
    "wof:name":"LL13 0UX",
    "wof:placetype":"postalcode"
},
  "geometry": {"coordinates":[-2.93087995924046,53.01838690745402],"type":"Point"}
}