{
  "type": "Feature",
  "properties": {
    "iso:country": "GB",
    "wof:name": "SG19 3LJ",
    "wof:placetype": "postalcode"
  },
  "geometry": {"coordinates":[-0.193148,52.147783],"type":"Point"}
}
