{
  "type": "Feature",
  "properties": {
    "iso:country": "GB",
    "wof:name": "BA2 0PE",
    "wof:placetype": "postalcode"
  },
  "geometry": {"coordinates":[-2.453064,51.320632],"type":"Point"}
}
