{
  "type": "Feature",
  "properties": {
    "iso:country":"GB",
    "wof:name":"BA2 0PE",
    "wof:placetype":"postalcode"
},
  "geometry": {"coordinates":[-2.45306397187586,51.32063232101077],"type":"Point"}
}