{
  "type": "Feature",
  "properties": {
    "iso:country": "GB",
    "wof:name": "CT21 5XL",
    "wof:placetype": "postalcode"
  },
  "geometry": {"coordinates":[1.10876,51.073931],"type":"Point"}
}
