{
  "type": "Feature",
  "properties": {
    "iso:country":"GB",
    "wof:name":"CT21 5XL",
    "wof:placetype":"postalcode"
},
  "geometry": {"coordinates":[1.10875977611205,51.07393070745624],"type":"Point"}
}