{
  "type": "Feature",
  "properties": {
    "iso:country":"GB",
    "wof:name":"WS6 7JH",
    "wof:placetype":"postalcode"
},
  "geometry": {"coordinates":[-2.03366523671622,52.65927734951249],"type":"Point"}
}