{
  "type": "Feature",
  "properties": {
    "iso:country": "GB",
    "wof:name": "WS6 7JH",
    "wof:placetype": "postalcode"
  },
  "geometry": {"coordinates":[-2.033665,52.659277],"type":"Point"}
}
