{
  "type": "Feature",
  "properties": {
    "iso:country":"GB",
    "wof:name":"BS23 4UL",
    "wof:placetype":"postalcode"
},
  "geometry": {"coordinates":[-2.98232288767504,51.32450066680039],"type":"Point"}
}