{
  "type": "Feature",
  "properties": {
    "iso:country":"GB",
    "wof:name":"OX13 5PT",
    "wof:placetype":"postalcode"
},
  "geometry": {"coordinates":[-1.34641410421127,51.72426282844387],"type":"Point"}
}