{
  "type": "Feature",
  "properties": {
    "iso:country": "GB",
    "wof:name": "LL38 2QZ",
    "wof:placetype": "postalcode"
  },
  "geometry": {"coordinates":[-4.050744,52.696323],"type":"Point"}
}
