{
  "type": "Feature",
  "properties": {
    "iso:country":"GB",
    "wof:name":"LL38 2QZ",
    "wof:placetype":"postalcode"
},
  "geometry": {"coordinates":[-4.05074369096514,52.696322613841],"type":"Point"}
}