{
  "type": "Feature",
  "properties": {
    "date:inception_lower": "1987-04-01",
    "date:inception_upper": "1987-04-01",
    "iso:country": "GB",
    "wof:name": "LL38 2QZ",
    "wof:placetype": "postalcode"
  },
  "geometry": {"coordinates":[-4.050744,52.696323],"type":"Point"}
}
