{
  "type": "Feature",
  "properties": {
    "iso:country":"GB",
    "wof:name":"LS4 2JQ",
    "wof:placetype":"postalcode"
},
  "geometry": {"coordinates":[-1.58418957328315,53.80916586158711],"type":"Point"}
}