{
  "type": "Feature",
  "properties": {
    "iso:country":"GB",
    "wof:name":"SK17 9BU",
    "wof:placetype":"postalcode"
},
  "geometry": {"coordinates":[-1.9245243877483,53.2532399096822],"type":"Point"}
}