{
  "type": "Feature",
  "properties": {
    "iso:country": "GB",
    "wof:name": "SK17 9BU",
    "wof:placetype": "postalcode"
  },
  "geometry": {"coordinates":[-1.924524,53.25324],"type":"Point"}
}
