{
  "type": "Feature",
  "properties": {
    "date:inception_lower": "1980-01-01",
    "date:inception_upper": "1980-01-01",
    "iso:country": "GB",
    "wof:name": "SK17 9BU",
    "wof:placetype": "postalcode"
  },
  "geometry": {"coordinates":[-1.924524,53.25324],"type":"Point"}
}
