{
  "type": "Feature",
  "properties": {
    "date:inception_lower": "1980-01-01",
    "date:inception_upper": "1980-01-01",
    "iso:country": "GB",
    "wof:name": "CV6 6FW",
    "wof:placetype": "postalcode"
  },
  "geometry": {"coordinates":[-1.502361,52.441509],"type":"Point"}
}
