{
  "type": "Feature",
  "properties": {
    "iso:country":"GB",
    "wof:name":"CV6 6FW",
    "wof:placetype":"postalcode"
},
  "geometry": {"coordinates":[-1.50236063890049,52.44150910619942],"type":"Point"}
}