{
  "type": "Feature",
  "properties": {
    "iso:country": "GB",
    "wof:name": "CV6 6FW",
    "wof:placetype": "postalcode"
  },
  "geometry": {"coordinates":[-1.502361,52.441509],"type":"Point"}
}
