{
  "type": "Feature",
  "properties": {
    "iso:country":"GB",
    "wof:name":"SR4 7RR",
    "wof:placetype":"postalcode"
},
  "geometry": {"coordinates":[-1.41596705690333,54.89838724298281],"type":"Point"}
}