{
  "type": "Feature",
  "properties": {
    "date:inception_lower": "1980-01-01",
    "date:inception_upper": "1980-01-01",
    "iso:country": "GB",
    "wof:name": "CW2 8NP",
    "wof:placetype": "postalcode"
  },
  "geometry": {"coordinates":[-2.461858,53.090746],"type":"Point"}
}
