{
  "type": "Feature",
  "properties": {
    "iso:country":"GB",
    "wof:name":"CW2 8NP",
    "wof:placetype":"postalcode"
},
  "geometry": {"coordinates":[-2.46185827935273,53.09074609423664],"type":"Point"}
}