{
  "type": "Feature",
  "properties": {
    "iso:country":"GB",
    "wof:name":"PL19 8PZ",
    "wof:placetype":"postalcode"
},
  "geometry": {"coordinates":[-4.20967409596277,50.58162664791138],"type":"Point"}
}