{
  "type": "Feature",
  "properties": {
    "iso:country": "GB",
    "wof:name": "PL19 8PZ",
    "wof:placetype": "postalcode"
  },
  "geometry": {"coordinates":[-4.210163,50.581797],"type":"Point"}
}
