{
  "type": "Feature",
  "properties": {
    "iso:country":"GB",
    "wof:name":"G65 0PG",
    "wof:placetype":"postalcode"
},
  "geometry": {"coordinates":[-4.0493596408404,55.97673484977561],"type":"Point"}
}