{
  "type": "Feature",
  "properties": {
    "iso:country": "GB",
    "wof:name": "G65 0PG",
    "wof:placetype": "postalcode"
  },
  "geometry": {"coordinates":[-4.04936,55.976735],"type":"Point"}
}
