{
  "type": "Feature",
  "properties": {
    "date:inception_lower": "1980-01-01",
    "date:inception_upper": "1980-01-01",
    "iso:country": "GB",
    "wof:name": "G65 0PG",
    "wof:placetype": "postalcode"
  },
  "geometry": {"coordinates":[-4.04936,55.976735],"type":"Point"}
}
