{
  "type": "Feature",
  "properties": {
    "iso:country":"GB",
    "wof:name":"WR8 0BP",
    "wof:placetype":"postalcode"
},
  "geometry": {"coordinates":[-2.2342647873646,52.07531973381595],"type":"Point"}
}