{
  "type": "Feature",
  "properties": {
    "iso:country": "GB",
    "wof:name": "WR8 0BP",
    "wof:placetype": "postalcode"
  },
  "geometry": {"coordinates":[-2.234483,52.075202],"type":"Point"}
}
