{
  "type": "Feature",
  "properties": {
    "iso:country":"GB",
    "wof:name":"FK10 1LT",
    "wof:placetype":"postalcode"
},
  "geometry": {"coordinates":[-3.80409123508782,56.11557954677418],"type":"Point"}
}