{
  "type": "Feature",
  "properties": {
    "iso:country": "GB",
    "wof:name": "FK10 1LT",
    "wof:placetype": "postalcode"
  },
  "geometry": {"coordinates":[-3.804091,56.11558],"type":"Point"}
}
