{
  "type": "Feature",
  "properties": {
    "iso:country":"GB",
    "wof:name":"HD5 8PP",
    "wof:placetype":"postalcode"
},
  "geometry": {"coordinates":[-1.74814135632123,53.64332418392524],"type":"Point"}
}