{
  "type": "Feature",
  "properties": {
    "iso:country": "GB",
    "wof:name": "HD5 8PP",
    "wof:placetype": "postalcode"
  },
  "geometry": {"coordinates":[-1.748141,53.643324],"type":"Point"}
}
