{
  "type": "Feature",
  "properties": {
    "iso:country":"GB",
    "wof:name":"WF7 6GE",
    "wof:placetype":"postalcode"
},
  "geometry": {"coordinates":[-1.4000374433963,53.67759043480287],"type":"Point"}
}