{
  "type": "Feature",
  "properties": {
    "date:inception_lower": "2005-10-01",
    "date:inception_upper": "2005-10-01",
    "iso:country": "GB",
    "wof:name": "WF7 6GE",
    "wof:placetype": "postalcode"
  },
  "geometry": {"coordinates":[-1.400037,53.67759],"type":"Point"}
}
