{
  "type": "Feature",
  "properties": {
    "iso:country":"GB",
    "wof:name":"TS4 2NH",
    "wof:placetype":"postalcode"
},
  "geometry": {"coordinates":[-1.22240914315438,54.56410746540126],"type":"Point"}
}