{
  "type": "Feature",
  "properties": {
    "iso:country": "GB",
    "wof:name": "DL14 0TG",
    "wof:placetype": "postalcode"
  },
  "geometry": {"coordinates":[-1.751959,54.650017],"type":"Point"}
}
