{
  "type": "Feature",
  "properties": {
    "iso:country":"GB",
    "wof:name":"DL14 0TG",
    "wof:placetype":"postalcode"
},
  "geometry": {"coordinates":[-1.7519590752012,54.65001720107218],"type":"Point"}
}