{
  "type": "Feature",
  "properties": {
    "date:inception_lower":"1996-06-01",
    "date:inception_upper":"1996-06-30",
    "iso:country":"GB",
    "wof:name":"DL14 0TG",
    "wof:placetype":"postalcode"
},
  "geometry": {"coordinates":[-1.751959,54.650017],"type":"Point"}
}