{
  "type": "Feature",
  "properties": {
    "iso:country":"GB",
    "wof:name":"NR16 1DR",
    "wof:placetype":"postalcode"
},
  "geometry": {"coordinates":[1.14443245781848,52.52339603311906],"type":"Point"}
}