{
  "type": "Feature",
  "properties": {
    "iso:country": "GB",
    "wof:name": "NR16 1DR",
    "wof:placetype": "postalcode"
  },
  "geometry": {"coordinates":[1.144433,52.523396],"type":"Point"}
}
