{
  "type": "Feature",
  "properties": {
    "date:inception_lower":"1980-01-01",
    "date:inception_upper":"1980-01-31",
    "iso:country":"GB",
    "wof:name":"B93 9PS",
    "wof:placetype":"postalcode"
},
  "geometry": {"coordinates":[-1.746834,52.392659],"type":"Point"}
}