{
  "type": "Feature",
  "properties": {
    "iso:country":"GB",
    "wof:name":"LA3 3EG",
    "wof:placetype":"postalcode"
},
  "geometry": {"coordinates":[-2.8775610373369,54.05370178510395],"type":"Point"}
}