{
  "type": "Feature",
  "properties": {
    "iso:country": "GB",
    "wof:name": "LA3 3EG",
    "wof:placetype": "postalcode"
  },
  "geometry": {"coordinates":[-2.877558,54.053713],"type":"Point"}
}
