{
  "type": "Feature",
  "properties": {
    "date:inception_lower":"1980-01-01",
    "date:inception_upper":"1980-01-31",
    "iso:country":"GB",
    "wof:name":"LA3 3EG",
    "wof:placetype":"postalcode"
},
  "geometry": {"coordinates":[-2.877558,54.053713],"type":"Point"}
}