{
  "type": "Feature",
  "properties": {
    "date:inception_lower": "1980-01-01",
    "date:inception_upper": "1980-01-01",
    "iso:country": "GB",
    "wof:name": "LA3 3EG",
    "wof:placetype": "postalcode"
  },
  "geometry": {"coordinates":[-2.876416,54.054584],"type":"Point"}
}
