{
  "type": "Feature",
  "properties": {
    "iso:country": "GB",
    "wof:name": "LA3 3EG",
    "wof:placetype": "postalcode"
  },
  "geometry": {"coordinates":[-2.876416,54.054584],"type":"Point"}
}
