{
  "type": "Feature",
  "properties": {
    "iso:country": "GB",
    "wof:name": "LE16 7SZ",
    "wof:placetype": "postalcode"
  },
  "geometry": {"coordinates":[-0.932435,52.534636],"type":"Point"}
}
