{
  "type": "Feature",
  "properties": {
    "date:inception_lower":"1980-01-01",
    "date:inception_upper":"1980-01-31",
    "iso:country":"GB",
    "wof:name":"LE16 7SZ",
    "wof:placetype":"postalcode"
},
  "geometry": {"coordinates":[-0.932435,52.534636],"type":"Point"}
}