{
  "type": "Feature",
  "properties": {
    "iso:country":"GB",
    "wof:name":"LE16 7SZ",
    "wof:placetype":"postalcode"
},
  "geometry": {"coordinates":[-0.93203963190419,52.5349659891056],"type":"Point"}
}