{
  "type": "Feature",
  "properties": {
    "date:inception_lower": "1980-01-01",
    "date:inception_upper": "1980-01-01",
    "iso:country": "GB",
    "wof:name": "GL54 4LJ",
    "wof:placetype": "postalcode"
  },
  "geometry": {"coordinates":[-1.974785,51.865967],"type":"Point"}
}
