{
  "type": "Feature",
  "properties": {
    "iso:country": "GB",
    "wof:name": "GL54 4LJ",
    "wof:placetype": "postalcode"
  },
  "geometry": {"coordinates":[-1.974785,51.865967],"type":"Point"}
}
