{
  "type": "Feature",
  "properties": {
    "iso:country":"GB",
    "wof:name":"GL54 4LJ",
    "wof:placetype":"postalcode"
},
  "geometry": {"coordinates":[-1.97478524383802,51.86596728693908],"type":"Point"}
}