{
  "type": "Feature",
  "properties": {
    "iso:country":"GB",
    "wof:name":"WN7 4DP",
    "wof:placetype":"postalcode"
},
  "geometry": {"coordinates":[-2.52443584403387,53.49583780757524],"type":"Point"}
}