{
  "type": "Feature",
  "properties": {
    "iso:country": "GB",
    "wof:name": "WN7 4DP",
    "wof:placetype": "postalcode"
  },
  "geometry": {"coordinates":[-2.524436,53.495838],"type":"Point"}
}
