{
  "type": "Feature",
  "properties": {
    "date:inception_lower":"1980-01-01",
    "date:inception_upper":"1980-01-31",
    "iso:country":"GB",
    "wof:name":"WN7 4DP",
    "wof:placetype":"postalcode"
},
  "geometry": {"coordinates":[-2.524436,53.495838],"type":"Point"}
}