{
  "type": "Feature",
  "properties": {
    "iso:country":"GB",
    "wof:name":"DG5 4HD",
    "wof:placetype":"postalcode"
},
  "geometry": {"coordinates":[-3.82120042387876,54.93242245086972],"type":"Point"}
}