{
  "type": "Feature",
  "properties": {
    "iso:country":"GB",
    "wof:name":"W1T 1SP",
    "wof:placetype":"postalcode"
},
  "geometry": {"coordinates":[-0.13606825091571,51.51904126485503],"type":"Point"}
}