{
  "type": "Feature",
  "properties": {
    "iso:country":"GB",
    "wof:name":"HP2 5RD",
    "wof:placetype":"postalcode"
},
  "geometry": {"coordinates":[-0.45642265758027,51.76596528703447],"type":"Point"}
}