{
  "type": "Feature",
  "properties": {
    "iso:country": "GB",
    "wof:name": "SG6 2JP",
    "wof:placetype": "postalcode"
  },
  "geometry": {"coordinates":[-0.210285,51.973957],"type":"Point"}
}
