{
  "type": "Feature",
  "properties": {
    "iso:country":"GB",
    "wof:name":"SG6 2JP",
    "wof:placetype":"postalcode"
},
  "geometry": {"coordinates":[-0.21025566539222,51.9739022380428],"type":"Point"}
}