{
  "type": "Feature",
  "properties": {
    "iso:country":"GB",
    "wof:name":"SA72 6JH",
    "wof:placetype":"postalcode"
},
  "geometry": {"coordinates":[-4.94612606028926,51.69396073465602],"type":"Point"}
}