{
  "type": "Feature",
  "properties": {
    "iso:country":"GB",
    "wof:name":"OL10 4SJ",
    "wof:placetype":"postalcode"
},
  "geometry": {"coordinates":[-2.23619481470606,53.59856661287957],"type":"Point"}
}