{
  "type": "Feature",
  "properties": {
    "iso:country":"GB",
    "wof:name":"CR4 3HL",
    "wof:placetype":"postalcode"
},
  "geometry": {"coordinates":[-0.16488280319277,51.41171097462824],"type":"Point"}
}