{
  "type": "Feature",
  "properties": {
    "date:inception_lower": "1980-01-01",
    "date:inception_upper": "1980-01-01",
    "iso:country": "GB",
    "wof:name": "BA12 0HS",
    "wof:placetype": "postalcode"
  },
  "geometry": {"coordinates":[-2.098341,51.197102],"type":"Point"}
}
