{
  "type": "Feature",
  "properties": {
    "iso:country":"GB",
    "wof:name":"G81 1BX",
    "wof:placetype":"postalcode"
},
  "geometry": {"coordinates":[-4.38774582433014,55.89915370530677],"type":"Point"}
}