{
  "type": "Feature",
  "properties": {
    "iso:country":"GB",
    "wof:name":"GL50 1QB",
    "wof:placetype":"postalcode"
},
  "geometry": {"coordinates":[-2.07694903608791,51.8976284491911],"type":"Point"}
}