{
  "type": "Feature",
  "properties": {
    "date:inception_lower": "1980-01-01",
    "date:inception_upper": "1980-01-01",
    "iso:country": "GB",
    "wof:name": "PE15 8SF",
    "wof:placetype": "postalcode"
  },
  "geometry": {"coordinates":[0.09855,52.560625],"type":"Point"}
}
