{
  "type": "Feature",
  "properties": {
    "iso:country": "GB",
    "wof:name": "SE2 9RB",
    "wof:placetype": "postalcode"
  },
  "geometry": {"coordinates":[0.11865,51.495256],"type":"Point"}
}
