{
  "type": "Feature",
  "properties": {
    "iso:country":"GB",
    "wof:name":"SE2 9RB",
    "wof:placetype":"postalcode"
},
  "geometry": {"coordinates":[0.11864982184321,51.4952560942079],"type":"Point"}
}