{
  "type": "Feature",
  "properties": {
    "iso:country":"GB",
    "wof:name":"PE21 9RG",
    "wof:placetype":"postalcode"
},
  "geometry": {"coordinates":[0.01231649162209,52.97785729262475],"type":"Point"}
}