{
  "type": "Feature",
  "properties": {
    "iso:country":"GB",
    "wof:name":"DT4 0EU",
    "wof:placetype":"postalcode"
},
  "geometry": {"coordinates":[-2.46373361667753,50.61523978480538],"type":"Point"}
}