{
  "type": "Feature",
  "properties": {
    "iso:country": "GB",
    "wof:name": "DE21 7HR",
    "wof:placetype": "postalcode"
  },
  "geometry": {"coordinates":[-1.395946,52.912897],"type":"Point"}
}
