{
  "type": "Feature",
  "properties": {
    "iso:country":"GB",
    "wof:name":"CM8 3DG",
    "wof:placetype":"postalcode"
},
  "geometry": {"coordinates":[0.65035418838703,51.79946405832725],"type":"Point"}
}