{
  "type": "Feature",
  "properties": {
    "date:inception_lower": "2023-02-01",
    "date:inception_upper": "2023-02-01",
    "iso:country": "GB",
    "wof:name": "PO36 6EG",
    "wof:placetype": "postalcode"
  },
  "geometry": {"coordinates":[-1.157062,50.653483],"type":"Point"}
}
