{
  "type": "Feature",
  "properties": {
    "iso:country":"GB",
    "wof:name":"SL9 0BY",
    "wof:placetype":"postalcode"
},
  "geometry": {"coordinates":[-0.55257246494168,51.61229517117467],"type":"Point"}
}