{
  "type": "Feature",
  "properties": {
    "iso:country": "GB",
    "wof:name": "NE65 9UA",
    "wof:placetype": "postalcode"
  },
  "geometry": {"coordinates":[-1.613744,55.307081],"type":"Point"}
}
