{
  "type": "Feature",
  "properties": {
    "iso:country":"GB",
    "wof:name":"NE65 9UA",
    "wof:placetype":"postalcode"
},
  "geometry": {"coordinates":[-1.61374432700525,55.30708116545591],"type":"Point"}
}