{
  "type": "Feature",
  "properties": {
    "iso:country":"GB",
    "wof:name":"PO31 8NG",
    "wof:placetype":"postalcode"
},
  "geometry": {"coordinates":[-1.3531934623173,50.73568340693422],"type":"Point"}
}