{
  "type": "Feature",
  "properties": {
    "iso:country":"GB",
    "wof:name":"CO2 7ED",
    "wof:placetype":"postalcode"
},
  "geometry": {"coordinates":[0.90515802886382,51.88447482080125],"type":"Point"}
}