{
  "type": "Feature",
  "properties": {
    "iso:country": "GB",
    "wof:name": "G68 0HS",
    "wof:placetype": "postalcode"
  },
  "geometry": {"coordinates":[-3.992513,55.968078],"type":"Point"}
}
