{
  "type": "Feature",
  "properties": {
    "date:inception_lower": "1980-01-01",
    "date:inception_upper": "1980-01-01",
    "iso:country": "GB",
    "wof:name": "PE9 2NG",
    "wof:placetype": "postalcode"
  },
  "geometry": {"coordinates":[-0.465291,52.650309],"type":"Point"}
}
