{
  "type": "Feature",
  "properties": {
    "iso:country":"GB",
    "wof:name":"PE9 2NG",
    "wof:placetype":"postalcode"
},
  "geometry": {"coordinates":[-0.46529098749681,52.65030947393304],"type":"Point"}
}