{
  "type": "Feature",
  "properties": {
    "iso:country": "GB",
    "wof:name": "FK8 1BJ",
    "wof:placetype": "postalcode"
  },
  "geometry": {"coordinates":[-3.939316,56.119229],"type":"Point"}
}
