{
  "type": "Feature",
  "properties": {
    "iso:country":"GB",
    "wof:name":"NR31 0HS",
    "wof:placetype":"postalcode"
},
  "geometry": {"coordinates":[1.71928208945694,52.60648790692684],"type":"Point"}
}