{
  "type": "Feature",
  "properties": {
    "iso:country":"GB",
    "wof:name":"SW17 7AT",
    "wof:placetype":"postalcode"
},
  "geometry": {"coordinates":[-0.15709274051422,51.43807196830966],"type":"Point"}
}