{
  "type": "Feature",
  "properties": {
    "date:inception_lower": "2005-04-01",
    "date:inception_upper": "2005-04-01",
    "iso:country": "GB",
    "wof:name": "SW17 7AT",
    "wof:placetype": "postalcode"
  },
  "geometry": {"coordinates":[-0.157093,51.438072],"type":"Point"}
}
