{
  "type": "Feature",
  "properties": {
    "iso:country":"GB",
    "wof:name":"BN7 3AA",
    "wof:placetype":"postalcode"
},
  "geometry": {"coordinates":[-0.04612816839775,50.89996291485952],"type":"Point"}
}