{
  "type": "Feature",
  "properties": {
    "iso:country":"GB",
    "wof:name":"SO40 2RX",
    "wof:placetype":"postalcode"
},
  "geometry": {"coordinates":[-1.51554215038907,50.9432272372909],"type":"Point"}
}