{
  "type": "Feature",
  "properties": {
    "iso:country": "GB",
    "wof:name": "HP16 0NQ",
    "wof:placetype": "postalcode"
  },
  "geometry": {"coordinates":[-0.742611,51.698386],"type":"Point"}
}
