{
  "type": "Feature",
  "properties": {
    "iso:country":"GB",
    "wof:name":"BR3 1SU",
    "wof:placetype":"postalcode"
},
  "geometry": {"coordinates":[-0.02349677849606,51.42205548376351],"type":"Point"}
}