{
  "type": "Feature",
  "properties": {
    "iso:country":"GB",
    "wof:name":"CR6 9RA",
    "wof:placetype":"postalcode"
},
  "geometry": {"coordinates":[-0.06362365820564,51.31792334847901],"type":"Point"}
}