{
  "type": "Feature",
  "properties": {
    "iso:country": "GB",
    "wof:name": "YO19 6RT",
    "wof:placetype": "postalcode"
  },
  "geometry": {"coordinates":[-1.055917,53.836535],"type":"Point"}
}
