{
  "type": "Feature",
  "properties": {
    "date:inception_lower": "1998-06-01",
    "date:inception_upper": "1998-06-01",
    "iso:country": "GB",
    "wof:name": "YO19 6RT",
    "wof:placetype": "postalcode"
  },
  "geometry": {"coordinates":[-1.055917,53.836535],"type":"Point"}
}
