{
  "type": "Feature",
  "properties": {
    "iso:country":"GB",
    "wof:name":"HA8 6BY",
    "wof:placetype":"postalcode"
},
  "geometry": {"coordinates":[-0.28189116342854,51.60366409559342],"type":"Point"}
}