{
  "type": "Feature",
  "properties": {
    "iso:country": "GB",
    "wof:name": "HA8 6BY",
    "wof:placetype": "postalcode"
  },
  "geometry": {"coordinates":[-0.281891,51.603664],"type":"Point"}
}
