{
  "type": "Feature",
  "properties": {
    "iso:country":"GB",
    "wof:name":"CM3 1NA",
    "wof:placetype":"postalcode"
},
  "geometry": {"coordinates":[0.4982585623506,51.82100631021041],"type":"Point"}
}