{
  "type": "Feature",
  "properties": {
    "iso:country": "GB",
    "wof:name": "CM3 1NA",
    "wof:placetype": "postalcode"
  },
  "geometry": {"coordinates":[0.498259,51.821006],"type":"Point"}
}
