{
  "type": "Feature",
  "properties": {
    "iso:country":"GB",
    "wof:name":"SP11 9FF",
    "wof:placetype":"postalcode"
},
  "geometry": {"coordinates":[-1.62284600259513,51.25618901100858],"type":"Point"}
}