{
  "type": "Feature",
  "properties": {
    "iso:country":"GB",
    "wof:name":"CH8 8SQ",
    "wof:placetype":"postalcode"
},
  "geometry": {"coordinates":[-3.25155476197901,53.28212745387231],"type":"Point"}
}