{
  "type": "Feature",
  "properties": {
    "date:inception_lower": "1980-01-01",
    "date:inception_upper": "1980-01-01",
    "iso:country": "GB",
    "wof:name": "CH8 8SQ",
    "wof:placetype": "postalcode"
  },
  "geometry": {"coordinates":[-3.251555,53.282127],"type":"Point"}
}
