{
  "type": "Feature",
  "properties": {
    "iso:country":"GB",
    "wof:name":"TS7 8SJ",
    "wof:placetype":"postalcode"
},
  "geometry": {"coordinates":[-1.20864339351432,54.53382157542556],"type":"Point"}
}