{
  "type": "Feature",
  "properties": {
    "date:inception_lower":"1980-01-01",
    "date:inception_upper":"1980-01-31",
    "iso:country":"GB",
    "wof:name":"FY5 1NH",
    "wof:placetype":"postalcode"
},
  "geometry": {"coordinates":[-3.040051,53.869614],"type":"Point"}
}