{
  "type": "Feature",
  "properties": {
    "iso:country": "GB",
    "wof:name": "OL11 2LF",
    "wof:placetype": "postalcode"
  },
  "geometry": {"coordinates":[-2.153869,53.601361],"type":"Point"}
}
