{
  "type": "Feature",
  "properties": {
    "iso:country":"GB",
    "wof:name":"BB9 6BD",
    "wof:placetype":"postalcode"
},
  "geometry": {"coordinates":[-2.20507066372162,53.86357448930697],"type":"Point"}
}