{
  "type": "Feature",
  "properties": {
    "date:inception_lower": "1980-01-01",
    "date:inception_upper": "1980-01-01",
    "iso:country": "GB",
    "wof:name": "DY9 7PS",
    "wof:placetype": "postalcode"
  },
  "geometry": {"coordinates":[-2.131535,52.456623],"type":"Point"}
}
