{
  "type": "Feature",
  "properties": {
    "iso:country":"GB",
    "wof:name":"DY9 7PS",
    "wof:placetype":"postalcode"
},
  "geometry": {"coordinates":[-2.1315345650371,52.45662276880819],"type":"Point"}
}