{
  "type": "Feature",
  "properties": {
    "iso:country":"GB",
    "wof:name":"EX6 7SR",
    "wof:placetype":"postalcode"
},
  "geometry": {"coordinates":[-3.59867918406296,50.70692450785162],"type":"Point"}
}