{
  "type": "Feature",
  "properties": {
    "iso:country":"GB",
    "wof:name":"CM0 8PY",
    "wof:placetype":"postalcode"
},
  "geometry": {"coordinates":[0.81600218097516,51.63753002452714],"type":"Point"}
}