{
  "type": "Feature",
  "properties": {
    "iso:country": "GB",
    "wof:name": "CM0 8PY",
    "wof:placetype": "postalcode"
  },
  "geometry": {"coordinates":[0.816002,51.63753],"type":"Point"}
}
