{
  "type": "Feature",
  "properties": {
    "iso:country":"GB",
    "wof:name":"AB21 7NB",
    "wof:placetype":"postalcode"
},
  "geometry": {"coordinates":[-2.17669562140981,57.20886027924422],"type":"Point"}
}