{
  "type": "Feature",
  "properties": {
    "iso:country":"GB",
    "wof:name":"OX5 1QT",
    "wof:placetype":"postalcode"
},
  "geometry": {"coordinates":[-1.31259885680949,51.83371746438193],"type":"Point"}
}