{
  "type": "Feature",
  "properties": {
    "iso:country":"GB",
    "wof:name":"WA8 9EU",
    "wof:placetype":"postalcode"
},
  "geometry": {"coordinates":[-2.73832719107885,53.38603400890707],"type":"Point"}
}