{
  "type": "Feature",
  "properties": {
    "iso:country":"GB",
    "wof:name":"N3 1YP",
    "wof:placetype":"postalcode"
},
  "geometry": {"coordinates":[-0.18705223182083,51.60785781679316],"type":"Point"}
}