{
  "type": "Feature",
  "properties": {
    "date:inception_lower": "1980-01-01",
    "date:inception_upper": "1980-01-01",
    "iso:country": "GB",
    "wof:name": "N3 1YP",
    "wof:placetype": "postalcode"
  },
  "geometry": {"coordinates":[-0.18704,51.607879],"type":"Point"}
}
