{
  "type": "Feature",
  "properties": {
    "iso:country":"GB",
    "wof:name":"DT8 3PR",
    "wof:placetype":"postalcode"
},
  "geometry": {"coordinates":[-2.75187354714621,50.81065208283707],"type":"Point"}
}