{
  "type": "Feature",
  "properties": {
    "iso:country": "GB",
    "wof:name": "DT8 3PR",
    "wof:placetype": "postalcode"
  },
  "geometry": {"coordinates":[-2.751874,50.810652],"type":"Point"}
}
