{
  "type": "Feature",
  "properties": {
    "date:inception_lower": "1980-01-01",
    "date:inception_upper": "1980-01-01",
    "iso:country": "GB",
    "wof:name": "G64 4DG",
    "wof:placetype": "postalcode"
  },
  "geometry": {"coordinates":[-4.216554,55.942673],"type":"Point"}
}
