{
  "type": "Feature",
  "properties": {
    "iso:country": "GB",
    "wof:name": "G64 4DG",
    "wof:placetype": "postalcode"
  },
  "geometry": {"coordinates":[-4.216554,55.942673],"type":"Point"}
}
