{
  "type": "Feature",
  "properties": {
    "iso:country":"GB",
    "wof:name":"TQ9 6RN",
    "wof:placetype":"postalcode"
},
  "geometry": {"coordinates":[-3.61005647482765,50.40796433078749],"type":"Point"}
}