{
  "type": "Feature",
  "properties": {
    "date:inception_lower": "1980-01-01",
    "date:inception_upper": "1980-01-01",
    "iso:country": "GB",
    "wof:name": "PE32 1ED",
    "wof:placetype": "postalcode"
  },
  "geometry": {"coordinates":[0.46785,52.727117],"type":"Point"}
}
