{
  "type": "Feature",
  "properties": {
    "date:inception_lower": "1990-02-01",
    "date:inception_upper": "1990-02-01",
    "iso:country": "GB",
    "wof:name": "HR4 9YL",
    "wof:placetype": "postalcode"
  },
  "geometry": {"coordinates":[-2.720335,52.060512],"type":"Point"}
}
