{
  "type": "Feature",
  "properties": {
    "iso:country":"GB",
    "wof:name":"TF2 9DX",
    "wof:placetype":"postalcode"
},
  "geometry": {"coordinates":[-2.43963255666219,52.69070300921459],"type":"Point"}
}