{
  "type": "Feature",
  "properties": {
    "iso:country": "GB",
    "wof:name": "TA1 2AY",
    "wof:placetype": "postalcode"
  },
  "geometry": {"coordinates":[-3.084724,51.020475],"type":"Point"}
}
