{
  "type": "Feature",
  "properties": {
    "iso:country":"GB",
    "wof:name":"TA1 2AY",
    "wof:placetype":"postalcode"
},
  "geometry": {"coordinates":[-3.08472416665087,51.02047490159202],"type":"Point"}
}