{
  "type": "Feature",
  "properties": {
    "iso:country": "GB",
    "wof:name": "L5 2AT",
    "wof:placetype": "postalcode"
  },
  "geometry": {"coordinates":[-2.988041,53.42271],"type":"Point"}
}
