{
  "type": "Feature",
  "properties": {
    "iso:country":"GB",
    "wof:name":"IG1 2HA",
    "wof:placetype":"postalcode"
},
  "geometry": {"coordinates":[0.07251882475586,51.5514398957399],"type":"Point"}
}