{
  "type": "Feature",
  "properties": {
    "date:inception_lower":"1985-04-01",
    "date:inception_upper":"1985-04-30",
    "iso:country":"GB",
    "wof:name":"GL51 0QJ",
    "wof:placetype":"postalcode"
},
  "geometry": {"coordinates":[-2.120095,51.913146],"type":"Point"}
}