{
  "type": "Feature",
  "properties": {
    "iso:country":"GB",
    "wof:name":"GL51 0QJ",
    "wof:placetype":"postalcode"
},
  "geometry": {"coordinates":[-2.12009531203741,51.91314639424319],"type":"Point"}
}