{
  "type": "Feature",
  "properties": {
    "iso:country": "GB",
    "wof:name": "GL51 0QJ",
    "wof:placetype": "postalcode"
  },
  "geometry": {"coordinates":[-2.120095,51.913146],"type":"Point"}
}
