{
  "type": "Feature",
  "properties": {
    "iso:country":"GB",
    "wof:name":"BA3 4PS",
    "wof:placetype":"postalcode"
},
  "geometry": {"coordinates":[-2.58557960968962,51.29192690657211],"type":"Point"}
}