{
  "type": "Feature",
  "properties": {
    "date:inception_lower": "1980-01-01",
    "date:inception_upper": "1980-01-01",
    "iso:country": "GB",
    "wof:name": "WR13 6BH",
    "wof:placetype": "postalcode"
  },
  "geometry": {"coordinates":[-2.290164,52.035241],"type":"Point"}
}
