{
  "type": "Feature",
  "properties": {
    "iso:country":"GB",
    "wof:name":"ML5 2QH",
    "wof:placetype":"postalcode"
},
  "geometry": {"coordinates":[-4.04084872729316,55.90672447215286],"type":"Point"}
}