{
  "type": "Feature",
  "properties": {
    "iso:country":"GB",
    "wof:name":"LE14 2NJ",
    "wof:placetype":"postalcode"
},
  "geometry": {"coordinates":[-0.97154631416834,52.75258819614492],"type":"Point"}
}