{
  "type": "Feature",
  "properties": {
    "iso:country": "GB",
    "wof:name": "NN4 9QQ",
    "wof:placetype": "postalcode"
  },
  "geometry": {"coordinates":[-0.937865,52.22071],"type":"Point"}
}
