{
  "type": "Feature",
  "properties": {
    "iso:country":"GB",
    "wof:name":"WA9 3DH",
    "wof:placetype":"postalcode"
},
  "geometry": {"coordinates":[-2.71343079590061,53.44186166698204],"type":"Point"}
}