{
  "type": "Feature",
  "properties": {
    "date:inception_lower": "2014-11-01",
    "date:inception_upper": "2014-11-01",
    "iso:country": "GB",
    "wof:name": "SA18 9AR",
    "wof:placetype": "postalcode"
  },
  "geometry": {"coordinates":[-3.984377,51.791641],"type":"Point"}
}
