{
  "type": "Feature",
  "properties": {
    "iso:country":"GB",
    "wof:name":"PH33 6ST",
    "wof:placetype":"postalcode"
},
  "geometry": {"coordinates":[-5.0709424671235,56.80293262338212],"type":"Point"}
}