{
  "type": "Feature",
  "properties": {
    "iso:country": "GB",
    "wof:name": "PH33 6ST",
    "wof:placetype": "postalcode"
  },
  "geometry": {"coordinates":[-5.070942,56.802933],"type":"Point"}
}
