{
  "type": "Feature",
  "properties": {
    "iso:country": "GB",
    "wof:name": "AB56 1RR",
    "wof:placetype": "postalcode"
  },
  "geometry": {"coordinates":[-2.981987,57.672986],"type":"Point"}
}
