{
  "type": "Feature",
  "properties": {
    "date:inception_lower": "2017-05-01",
    "date:inception_upper": "2017-05-01",
    "iso:country": "GB",
    "wof:name": "RH12 4FA",
    "wof:placetype": "postalcode"
  },
  "geometry": {"coordinates":[-0.279674,51.1224],"type":"Point"}
}
