{
  "type": "Feature",
  "properties": {
    "iso:country":"GB",
    "wof:name":"DN14 0GB",
    "wof:placetype":"postalcode"
},
  "geometry": {"coordinates":[-1.14681365891074,53.70440424907157],"type":"Point"}
}