{
  "type": "Feature",
  "properties": {
    "date:inception_lower":"2003-10-01",
    "date:inception_upper":"2003-10-31",
    "iso:country":"GB",
    "wof:name":"DN14 0GB",
    "wof:placetype":"postalcode"
},
  "geometry": {"coordinates":[-1.146814,53.704404],"type":"Point"}
}