{
  "type": "Feature",
  "properties": {
    "date:inception_lower": "1996-06-01",
    "date:inception_upper": "1996-06-01",
    "iso:country": "GB",
    "wof:name": "AB25 1SD",
    "wof:placetype": "postalcode"
  },
  "geometry": {"coordinates":[-2.112678,57.148021],"type":"Point"}
}
