{
  "type": "Feature",
  "properties": {
    "date:inception_lower": "2016-06-01",
    "date:inception_upper": "2016-06-01",
    "iso:country": "GB",
    "wof:name": "OX25 5AA",
    "wof:placetype": "postalcode"
  },
  "geometry": {"coordinates":[-1.261086,51.927074],"type":"Point"}
}
