{
  "type": "Feature",
  "properties": {
    "date:inception_lower": "1980-01-01",
    "date:inception_upper": "1980-01-01",
    "iso:country": "GB",
    "wof:name": "SG18 8AH",
    "wof:placetype": "postalcode"
  },
  "geometry": {"coordinates":[-0.26302,52.086333],"type":"Point"}
}
