{
  "type": "Feature",
  "properties": {
    "iso:country":"GB",
    "wof:name":"FY4 4DE",
    "wof:placetype":"postalcode"
},
  "geometry": {"coordinates":[-3.02359815388227,53.80307980060414],"type":"Point"}
}