{
  "type": "Feature",
  "properties": {
    "iso:country":"GB",
    "wof:name":"SA14 8EX",
    "wof:placetype":"postalcode"
},
  "geometry": {"coordinates":[-4.14548865100903,51.70738281591905],"type":"Point"}
}