{
  "type": "Feature",
  "properties": {
    "iso:country":"GB",
    "wof:name":"HP4 3HZ",
    "wof:placetype":"postalcode"
},
  "geometry": {"coordinates":[-0.57499736467303,51.76034999859119],"type":"Point"}
}