{
  "type": "Feature",
  "properties": {
    "iso:country":"GB",
    "wof:name":"EX23 8DR",
    "wof:placetype":"postalcode"
},
  "geometry": {"coordinates":[-4.53534420349755,50.82935152550137],"type":"Point"}
}