{
  "type": "Feature",
  "properties": {
    "iso:country":"GB",
    "wof:name":"AL5 4NL",
    "wof:placetype":"postalcode"
},
  "geometry": {"coordinates":[-0.34051819902316,51.82199722733144],"type":"Point"}
}