{
  "type": "Feature",
  "properties": {
    "date:inception_lower": "2020-02-01",
    "date:inception_upper": "2020-02-01",
    "iso:country": "GB",
    "wof:name": "BH19 3BP",
    "wof:placetype": "postalcode"
  },
  "geometry": {"coordinates":[-2.033979,50.599141],"type":"Point"}
}
