{
  "type": "Feature",
  "properties": {
    "date:inception_lower": "1985-02-01",
    "date:inception_upper": "1985-02-01",
    "iso:country": "GB",
    "wof:name": "KY6 3NR",
    "wof:placetype": "postalcode"
  },
  "geometry": {"coordinates":[-3.191801,56.215239],"type":"Point"}
}
