{
  "type": "Feature",
  "properties": {
    "iso:country":"GB",
    "wof:name":"DG1 1QH",
    "wof:placetype":"postalcode"
},
  "geometry": {"coordinates":[-3.58077361731031,55.10698681785703],"type":"Point"}
}