{
  "type": "Feature",
  "properties": {
    "date:inception_lower": "1980-01-01",
    "date:inception_upper": "1980-01-01",
    "iso:country": "GB",
    "wof:name": "SY12 0JD",
    "wof:placetype": "postalcode"
  },
  "geometry": {"coordinates":[-2.850311,52.860897],"type":"Point"}
}
