{
  "type": "Feature",
  "properties": {
    "date:inception_lower":"1980-01-01",
    "date:inception_upper":"1980-01-31",
    "iso:country":"GB",
    "wof:name":"SY12 0JD",
    "wof:placetype":"postalcode"
},
  "geometry": {"coordinates":[-2.851124,52.86073],"type":"Point"}
}