{
  "type": "Feature",
  "properties": {
    "iso:country": "GB",
    "wof:name": "SY12 0JD",
    "wof:placetype": "postalcode"
  },
  "geometry": {"coordinates":[-2.851124,52.86073],"type":"Point"}
}
