{
  "type": "Feature",
  "properties": {
    "iso:country":"GB",
    "wof:name":"SY12 0JD",
    "wof:placetype":"postalcode"
},
  "geometry": {"coordinates":[-2.85031276054684,52.86088260791414],"type":"Point"}
}