{
  "type": "Feature",
  "properties": {
    "iso:country": "GB",
    "wof:name": "E2 9NX",
    "wof:placetype": "postalcode"
  },
  "geometry": {"coordinates":[-0.053986,51.531098],"type":"Point"}
}
