{
  "type": "Feature",
  "properties": {
    "date:inception_lower": "1980-01-01",
    "date:inception_upper": "1980-01-01",
    "iso:country": "GB",
    "wof:name": "SW13 0PW",
    "wof:placetype": "postalcode"
  },
  "geometry": {"coordinates":[-0.254337,51.468417],"type":"Point"}
}
