{
  "type": "Feature",
  "properties": {
    "iso:country":"GB",
    "wof:name":"SW13 0PW",
    "wof:placetype":"postalcode"
},
  "geometry": {"coordinates":[-0.25430896416114,51.46838989401576],"type":"Point"}
}