{
  "type": "Feature",
  "properties": {
    "iso:country":"GB",
    "wof:name":"NE63 9UH",
    "wof:placetype":"postalcode"
},
  "geometry": {"coordinates":[-1.572792763166,55.18323633110968],"type":"Point"}
}