{
  "type": "Feature",
  "properties": {
    "date:inception_lower": "1990-02-01",
    "date:inception_upper": "1990-02-01",
    "iso:country": "GB",
    "wof:name": "CV4 7HW",
    "wof:placetype": "postalcode"
  },
  "geometry": {"coordinates":[-1.547777,52.375128],"type":"Point"}
}
