{
  "type": "Feature",
  "properties": {
    "iso:country":"GB",
    "wof:name":"CV4 7HW",
    "wof:placetype":"postalcode"
},
  "geometry": {"coordinates":[-1.54777694549112,52.37512839283259],"type":"Point"}
}