{
  "type": "Feature",
  "properties": {
    "iso:country":"GB",
    "wof:name":"PL25 5RR",
    "wof:placetype":"postalcode"
},
  "geometry": {"coordinates":[-4.79510272723919,50.34996463817099],"type":"Point"}
}