{
  "type": "Feature",
  "properties": {
    "iso:country":"GB",
    "wof:name":"LA9 6BE",
    "wof:placetype":"postalcode"
},
  "geometry": {"coordinates":[-2.72404402943499,54.32808175377355],"type":"Point"}
}