{
  "type": "Feature",
  "properties": {
    "date:inception_lower":"1980-01-01",
    "date:inception_upper":"1980-01-31",
    "iso:country":"GB",
    "wof:name":"BL4 0QW",
    "wof:placetype":"postalcode"
},
  "geometry": {"coordinates":[-2.432635,53.544563],"type":"Point"}
}