{
  "type": "Feature",
  "properties": {
    "iso:country": "GB",
    "wof:name": "CW12 4SN",
    "wof:placetype": "postalcode"
  },
  "geometry": {"coordinates":[-2.266187,53.172138],"type":"Point"}
}
