{
  "type": "Feature",
  "properties": {
    "iso:country":"GB",
    "wof:name":"CW12 4SN",
    "wof:placetype":"postalcode"
},
  "geometry": {"coordinates":[-2.26618733034964,53.17213799734895],"type":"Point"}
}