{
  "type": "Feature",
  "properties": {
    "iso:country":"GB",
    "wof:name":"HG5 9XB",
    "wof:placetype":"postalcode"
},
  "geometry": {"coordinates":[-1.4875486333854,54.03411824001324],"type":"Point"}
}