{
  "type": "Feature",
  "properties": {
    "iso:country":"GB",
    "wof:name":"SM6 9QX",
    "wof:placetype":"postalcode"
},
  "geometry": {"coordinates":[-0.13782124685822,51.35820925184552],"type":"Point"}
}