{
  "type": "Feature",
  "properties": {
    "iso:country":"GB",
    "wof:name":"DE45 1GZ",
    "wof:placetype":"postalcode"
},
  "geometry": {"coordinates":[-1.68575387169005,53.21946564025138],"type":"Point"}
}