{
  "type": "Feature",
  "properties": {
    "date:inception_lower": "2013-12-01",
    "date:inception_upper": "2013-12-01",
    "iso:country": "GB",
    "wof:name": "DE45 1GZ",
    "wof:placetype": "postalcode"
  },
  "geometry": {"coordinates":[-1.685754,53.219466],"type":"Point"}
}
