{
  "type": "Feature",
  "properties": {
    "iso:country":"GB",
    "wof:name":"E12 5RR",
    "wof:placetype":"postalcode"
},
  "geometry": {"coordinates":[0.06273148945194,51.55382459882362],"type":"Point"}
}