{
  "type": "Feature",
  "properties": {
    "iso:country":"GB",
    "wof:name":"BS4 1QZ",
    "wof:placetype":"postalcode"
},
  "geometry": {"coordinates":[-2.59838522832952,51.42516542493604],"type":"Point"}
}