{
  "type": "Feature",
  "properties": {
    "iso:country":"GB",
    "wof:name":"SA9 2HA",
    "wof:placetype":"postalcode"
},
  "geometry": {"coordinates":[-3.78279282429183,51.76124166948771],"type":"Point"}
}