{
  "type": "Feature",
  "properties": {
    "iso:country": "GB",
    "wof:name": "EH3 6QW",
    "wof:placetype": "postalcode"
  },
  "geometry": {"coordinates":[-3.19732,55.957955],"type":"Point"}
}
