{
  "type": "Feature",
  "properties": {
    "iso:country": "GB",
    "wof:name": "CM3 4EE",
    "wof:placetype": "postalcode"
  },
  "geometry": {"coordinates":[0.575993,51.712768],"type":"Point"}
}
