{
  "type": "Feature",
  "properties": {
    "iso:country": "GB",
    "wof:name": "GL7 6EQ",
    "wof:placetype": "postalcode"
  },
  "geometry": {"coordinates":[-2.024123,51.658571],"type":"Point"}
}
