{
  "type": "Feature",
  "properties": {
    "iso:country":"GB",
    "wof:name":"EX32 8EZ",
    "wof:placetype":"postalcode"
},
  "geometry": {"coordinates":[-4.03899405387774,51.07500282249193],"type":"Point"}
}