{
  "type": "Feature",
  "properties": {
    "iso:country": "GB",
    "wof:name": "EX32 8EZ",
    "wof:placetype": "postalcode"
  },
  "geometry": {"coordinates":[-4.038994,51.075003],"type":"Point"}
}
