{
  "type": "Feature",
  "properties": {
    "date:inception_lower": "2013-01-01",
    "date:inception_upper": "2013-01-01",
    "iso:country": "GB",
    "wof:name": "EX32 8EZ",
    "wof:placetype": "postalcode"
  },
  "geometry": {"coordinates":[-4.038994,51.075003],"type":"Point"}
}
