{
  "type": "Feature",
  "properties": {
    "date:inception_lower": "2006-11-01",
    "date:inception_upper": "2006-11-01",
    "iso:country": "GB",
    "wof:name": "NG31 7EW",
    "wof:placetype": "postalcode"
  },
  "geometry": {"coordinates":[-0.645774,52.9024],"type":"Point"}
}
