{
  "type": "Feature",
  "properties": {
    "iso:country":"GB",
    "wof:name":"NG31 7EW",
    "wof:placetype":"postalcode"
},
  "geometry": {"coordinates":[-0.6457741380525,52.90240025224913],"type":"Point"}
}