{
  "type": "Feature",
  "properties": {
    "date:inception_lower": "2022-08-01",
    "date:inception_upper": "2022-08-01",
    "iso:country": "GB",
    "wof:name": "WS3 1FG",
    "wof:placetype": "postalcode"
  },
  "geometry": {"coordinates":[-1.971745,52.61049],"type":"Point"}
}
