{
  "type": "Feature",
  "properties": {
    "iso:country":"GB",
    "wof:name":"TQ9 5HQ",
    "wof:placetype":"postalcode"
},
  "geometry": {"coordinates":[-3.68520564777814,50.4312640300228],"type":"Point"}
}