{
  "type": "Feature",
  "properties": {
    "iso:country": "GB",
    "wof:name": "WN2 1EJ",
    "wof:placetype": "postalcode"
  },
  "geometry": {"coordinates":[-2.602178,53.558975],"type":"Point"}
}
