{
  "type": "Feature",
  "properties": {
    "iso:country": "GB",
    "wof:name": "OX2 6AD",
    "wof:placetype": "postalcode"
  },
  "geometry": {"coordinates":[-1.265637,51.759517],"type":"Point"}
}
