{
  "type": "Feature",
  "properties": {
    "iso:country":"GB",
    "wof:name":"NG8 5SB",
    "wof:placetype":"postalcode"
},
  "geometry": {"coordinates":[-1.21209777512934,52.9744139076051],"type":"Point"}
}