{
  "type": "Feature",
  "properties": {
    "iso:country": "GB",
    "wof:name": "GL3 3RS",
    "wof:placetype": "postalcode"
  },
  "geometry": {"coordinates":[-2.195293,51.857841],"type":"Point"}
}
