{
  "type": "Feature",
  "properties": {
    "date:inception_lower": "1980-01-01",
    "date:inception_upper": "1980-01-01",
    "iso:country": "GB",
    "wof:name": "FK15 9PD",
    "wof:placetype": "postalcode"
  },
  "geometry": {"coordinates":[-4.010305,56.186596],"type":"Point"}
}
