{
  "type": "Feature",
  "properties": {
    "iso:country":"GB",
    "wof:name":"FK15 9PD",
    "wof:placetype":"postalcode"
},
  "geometry": {"coordinates":[-4.01030525747888,56.18659620595974],"type":"Point"}
}