{
  "type": "Feature",
  "properties": {
    "iso:country": "GB",
    "wof:name": "NW10 1PW",
    "wof:placetype": "postalcode"
  },
  "geometry": {"coordinates":[-0.250169,51.55773],"type":"Point"}
}
