{
  "type": "Feature",
  "properties": {
    "iso:country":"GB",
    "wof:name":"B69 1DX",
    "wof:placetype":"postalcode"
},
  "geometry": {"coordinates":[-2.03123666132053,52.48904689791614],"type":"Point"}
}