{
  "type": "Feature",
  "properties": {
    "iso:country":"GB",
    "wof:name":"SW6 5LQ",
    "wof:placetype":"postalcode"
},
  "geometry": {"coordinates":[-0.20839324358741,51.47393806942704],"type":"Point"}
}