{
  "type": "Feature",
  "properties": {
    "iso:country":"GB",
    "wof:name":"SO30 2SX",
    "wof:placetype":"postalcode"
},
  "geometry": {"coordinates":[-1.29042683605687,50.90842704036356],"type":"Point"}
}