{
  "type": "Feature",
  "properties": {
    "iso:country":"GB",
    "wof:name":"WN4 0XH",
    "wof:placetype":"postalcode"
},
  "geometry": {"coordinates":[-2.68073484975553,53.49570569936309],"type":"Point"}
}