{
  "type": "Feature",
  "properties": {
    "iso:country":"GB",
    "wof:name":"BH11 8DN",
    "wof:placetype":"postalcode"
},
  "geometry": {"coordinates":[-1.90956740650569,50.75865449651312],"type":"Point"}
}