{
  "type": "Feature",
  "properties": {
    "iso:country":"GB",
    "wof:name":"SA10 6UY",
    "wof:placetype":"postalcode"
},
  "geometry": {"coordinates":[-3.83751910892206,51.66041419624464],"type":"Point"}
}