{
  "type": "Feature",
  "properties": {
    "iso:country":"GB",
    "wof:name":"SK16 4JL",
    "wof:placetype":"postalcode"
},
  "geometry": {"coordinates":[-2.0933417834837,53.48175329970893],"type":"Point"}
}