{
  "type": "Feature",
  "properties": {
    "iso:country": "GB",
    "wof:name": "SK16 4JL",
    "wof:placetype": "postalcode"
  },
  "geometry": {"coordinates":[-2.093342,53.481753],"type":"Point"}
}
