{
  "type": "Feature",
  "properties": {
    "iso:country":"GB",
    "wof:name":"S13 9DE",
    "wof:placetype":"postalcode"
},
  "geometry": {"coordinates":[-1.38923163087625,53.37525209398169],"type":"Point"}
}