{
  "type": "Feature",
  "properties": {
    "iso:country": "GB",
    "wof:name": "S13 9DE",
    "wof:placetype": "postalcode"
  },
  "geometry": {"coordinates":[-1.389216,53.375252],"type":"Point"}
}
