{
  "type": "Feature",
  "properties": {
    "date:inception_lower": "1980-01-01",
    "date:inception_upper": "1980-01-01",
    "iso:country": "GB",
    "wof:name": "GL11 5AS",
    "wof:placetype": "postalcode"
  },
  "geometry": {"coordinates":[-2.314092,51.704862],"type":"Point"}
}
