{
  "type": "Feature",
  "properties": {
    "iso:country": "GB",
    "wof:name": "GL11 5AS",
    "wof:placetype": "postalcode"
  },
  "geometry": {"coordinates":[-2.314092,51.704862],"type":"Point"}
}
