{
  "type": "Feature",
  "properties": {
    "iso:country": "GB",
    "wof:name": "SE18 5QX",
    "wof:placetype": "postalcode"
  },
  "geometry": {"coordinates":[0.048231,51.493693],"type":"Point"}
}
