{
  "type": "Feature",
  "properties": {
    "iso:country": "GB",
    "wof:name": "NN12 6HJ",
    "wof:placetype": "postalcode"
  },
  "geometry": {"coordinates":[-1.000307,52.129694],"type":"Point"}
}
