{
  "type": "Feature",
  "properties": {
    "date:inception_lower": "1993-08-01",
    "date:inception_upper": "1993-08-01",
    "iso:country": "GB",
    "wof:name": "NN12 6HJ",
    "wof:placetype": "postalcode"
  },
  "geometry": {"coordinates":[-1.000307,52.129694],"type":"Point"}
}
