{
  "type": "Feature",
  "properties": {
    "iso:country":"GB",
    "wof:name":"SE7 7JJ",
    "wof:placetype":"postalcode"
},
  "geometry": {"coordinates":[0.02459281419814,51.48040712029617],"type":"Point"}
}