{
  "type": "Feature",
  "properties": {
    "date:inception_lower":"1980-01-01",
    "date:inception_upper":"1980-01-31",
    "iso:country":"GB",
    "wof:name":"LE4 4DB",
    "wof:placetype":"postalcode"
},
  "geometry": {"coordinates":[-1.123396,52.676692],"type":"Point"}
}