{
  "type": "Feature",
  "properties": {
    "iso:country":"GB",
    "wof:name":"LE4 4DB",
    "wof:placetype":"postalcode"
},
  "geometry": {"coordinates":[-1.12339559284875,52.67669208720037],"type":"Point"}
}