{
  "type": "Feature",
  "properties": {
    "date:inception_lower":"1995-12-01",
    "date:inception_upper":"1995-12-31",
    "iso:country":"GB",
    "wof:name":"SO32 2NU",
    "wof:placetype":"postalcode"
},
  "geometry": {"coordinates":[-1.288872,50.948866],"type":"Point"}
}