{
  "type": "Feature",
  "properties": {
    "iso:country": "GB",
    "wof:name": "SO32 2NU",
    "wof:placetype": "postalcode"
  },
  "geometry": {"coordinates":[-1.288872,50.948866],"type":"Point"}
}
