{
  "type": "Feature",
  "properties": {
    "iso:country":"GB",
    "wof:name":"BS5 7UH",
    "wof:placetype":"postalcode"
},
  "geometry": {"coordinates":[-2.54107476381789,51.46938620682353],"type":"Point"}
}