{
  "type": "Feature",
  "properties": {
    "iso:country": "GB",
    "wof:name": "BS5 7UH",
    "wof:placetype": "postalcode"
  },
  "geometry": {"coordinates":[-2.541075,51.469386],"type":"Point"}
}
