{
  "type": "Feature",
  "properties": {
    "iso:country":"GB",
    "wof:name":"TS14 8AX",
    "wof:placetype":"postalcode"
},
  "geometry": {"coordinates":[-1.0664217925161,54.53030936069975],"type":"Point"}
}