{
  "type": "Feature",
  "properties": {
    "iso:country": "GB",
    "wof:name": "PH2 6UB",
    "wof:placetype": "postalcode"
  },
  "geometry": {"coordinates":[-3.402175,56.415776],"type":"Point"}
}
