{
  "type": "Feature",
  "properties": {
    "iso:country":"GB",
    "wof:name":"PH2 6UB",
    "wof:placetype":"postalcode"
},
  "geometry": {"coordinates":[-3.40217525070629,56.41577621267079],"type":"Point"}
}