{
  "type": "Feature",
  "properties": {
    "date:inception_lower": "1980-01-01",
    "date:inception_upper": "1980-01-01",
    "iso:country": "GB",
    "wof:name": "GU3 3LF",
    "wof:placetype": "postalcode"
  },
  "geometry": {"coordinates":[-0.59713,51.264009],"type":"Point"}
}
