{
  "type": "Feature",
  "properties": {
    "iso:country":"GB",
    "wof:name":"W1D 1AW",
    "wof:placetype":"postalcode"
},
  "geometry": {"coordinates":[-0.13116222469201,51.51670607955324],"type":"Point"}
}