{
  "type": "Feature",
  "properties": {
    "iso:country":"GB",
    "wof:name":"LS15 7LE",
    "wof:placetype":"postalcode"
},
  "geometry": {"coordinates":[-1.45405507752257,53.80727823858599],"type":"Point"}
}