{
  "type": "Feature",
  "properties": {
    "iso:country": "GB",
    "wof:name": "LS15 7LE",
    "wof:placetype": "postalcode"
  },
  "geometry": {"coordinates":[-1.454055,53.807278],"type":"Point"}
}
