{
  "type": "Feature",
  "properties": {
    "iso:country":"GB",
    "wof:name":"WD25 7HD",
    "wof:placetype":"postalcode"
},
  "geometry": {"coordinates":[-0.40278979310285,51.69525569572328],"type":"Point"}
}