{
  "type": "Feature",
  "properties": {
    "iso:country":"GB",
    "wof:name":"GU21 4TB",
    "wof:placetype":"postalcode"
},
  "geometry": {"coordinates":[-0.57349328108081,51.32487490251128],"type":"Point"}
}