{
  "type": "Feature",
  "properties": {
    "iso:country": "GB",
    "wof:name": "GU21 4TB",
    "wof:placetype": "postalcode"
  },
  "geometry": {"coordinates":[-0.573493,51.324875],"type":"Point"}
}
