{
  "type": "Feature",
  "properties": {
    "date:inception_lower": "2002-06-01",
    "date:inception_upper": "2002-06-01",
    "iso:country": "GB",
    "wof:name": "HX1 5PF",
    "wof:placetype": "postalcode"
  },
  "geometry": {"coordinates":[-1.879737,53.72476],"type":"Point"}
}
