{
  "type": "Feature",
  "properties": {
    "date:inception_lower": "2021-04-01",
    "date:inception_upper": "2021-04-01",
    "iso:country": "GB",
    "wof:name": "NW10 1DT",
    "wof:placetype": "postalcode"
  },
  "geometry": {"coordinates":[-0.244702,51.553722],"type":"Point"}
}
