{
  "type": "Feature",
  "properties": {
    "date:inception_lower":"2002-06-01",
    "date:inception_upper":"2002-06-30",
    "iso:country":"GB",
    "wof:name":"ST17 0FT",
    "wof:placetype":"postalcode"
},
  "geometry": {"coordinates":[-2.073533,52.796611],"type":"Point"}
}