{
  "type": "Feature",
  "properties": {
    "iso:country":"GB",
    "wof:name":"RG10 0RY",
    "wof:placetype":"postalcode"
},
  "geometry": {"coordinates":[-0.84972481567154,51.45335192615619],"type":"Point"}
}