{
  "type": "Feature",
  "properties": {
    "date:inception_lower":"1980-01-01",
    "date:inception_upper":"1980-01-31",
    "iso:country":"GB",
    "wof:name":"RG10 0RY",
    "wof:placetype":"postalcode"
},
  "geometry": {"coordinates":[-0.849835,51.4534],"type":"Point"}
}