{
  "type": "Feature",
  "properties": {
    "iso:country":"GB",
    "wof:name":"NE3 4SX",
    "wof:placetype":"postalcode"
},
  "geometry": {"coordinates":[-1.64754814503809,55.00091399681589],"type":"Point"}
}