{
  "type": "Feature",
  "properties": {
    "iso:country": "GB",
    "wof:name": "NE3 4SX",
    "wof:placetype": "postalcode"
  },
  "geometry": {"coordinates":[-1.647548,55.000914],"type":"Point"}
}
