{
  "type": "Feature",
  "properties": {
    "iso:country":"GB",
    "wof:name":"DG7 3LZ",
    "wof:placetype":"postalcode"
},
  "geometry": {"coordinates":[-3.86508109862328,54.9760039974928],"type":"Point"}
}