{
  "type": "Feature",
  "properties": {
    "date:inception_lower":"1980-01-01",
    "date:inception_upper":"1980-01-31",
    "iso:country":"GB",
    "wof:name":"MK41 8LT",
    "wof:placetype":"postalcode"
},
  "geometry": {"coordinates":[-0.440274,52.158188],"type":"Point"}
}