{
  "type": "Feature",
  "properties": {
    "iso:country":"GB",
    "wof:name":"HD9 6BH",
    "wof:placetype":"postalcode"
},
  "geometry": {"coordinates":[-1.79364371807635,53.60552574776985],"type":"Point"}
}