{
  "type": "Feature",
  "properties": {
    "iso:country":"GB",
    "wof:name":"LS7 2RW",
    "wof:placetype":"postalcode"
},
  "geometry": {"coordinates":[-1.55448746585103,53.82907557113786],"type":"Point"}
}