{
  "type": "Feature",
  "properties": {
    "iso:country": "GB",
    "wof:name": "N13 5LU",
    "wof:placetype": "postalcode"
  },
  "geometry": {"coordinates":[-0.090601,51.620078],"type":"Point"}
}
