{
  "type": "Feature",
  "properties": {
    "iso:country":"GB",
    "wof:name":"N13 5LU",
    "wof:placetype":"postalcode"
},
  "geometry": {"coordinates":[-0.09060124617195,51.62007790383433],"type":"Point"}
}