{
  "type": "Feature",
  "properties": {
    "iso:country":"GB",
    "wof:name":"WA4 4BE",
    "wof:placetype":"postalcode"
},
  "geometry": {"coordinates":[-2.6329798245796,53.32953353342362],"type":"Point"}
}