{
  "type": "Feature",
  "properties": {
    "date:inception_lower": "1980-01-01",
    "date:inception_upper": "1980-01-01",
    "iso:country": "GB",
    "wof:name": "RH17 6QT",
    "wof:placetype": "postalcode"
  },
  "geometry": {"coordinates":[-0.121265,51.058755],"type":"Point"}
}
