{
  "type": "Feature",
  "properties": {
    "date:inception_lower":"1987-04-01",
    "date:inception_upper":"1987-04-30",
    "iso:country":"GB",
    "wof:name":"PL9 9UW",
    "wof:placetype":"postalcode"
},
  "geometry": {"coordinates":[-4.081525,50.348125],"type":"Point"}
}