{
  "type": "Feature",
  "properties": {
    "iso:country":"GB",
    "wof:name":"EN8 8QP",
    "wof:placetype":"postalcode"
},
  "geometry": {"coordinates":[-0.04237224678385,51.70212169614516],"type":"Point"}
}