{
  "type": "Feature",
  "properties": {
    "iso:country": "GB",
    "wof:name": "EN8 8QP",
    "wof:placetype": "postalcode"
  },
  "geometry": {"coordinates":[-0.042372,51.702122],"type":"Point"}
}
