{
  "type": "Feature",
  "properties": {
    "date:inception_lower":"2014-02-01",
    "date:inception_upper":"2014-02-28",
    "iso:country":"GB",
    "wof:name":"RM7 0BF",
    "wof:placetype":"postalcode"
},
  "geometry": {"coordinates":[0.175378,51.570126],"type":"Point"}
}