{
  "type": "Feature",
  "properties": {
    "iso:country":"GB",
    "wof:name":"FK2 7TL",
    "wof:placetype":"postalcode"
},
  "geometry": {"coordinates":[-3.77659771381657,56.01875643689083],"type":"Point"}
}