{
  "type": "Feature",
  "properties": {
    "iso:country":"GB",
    "wof:name":"TR8 4AA",
    "wof:placetype":"postalcode"
},
  "geometry": {"coordinates":[-5.04129562194444,50.44484611173668],"type":"Point"}
}