{
  "type": "Feature",
  "properties": {
    "iso:country": "GB",
    "wof:name": "PL19 9LA",
    "wof:placetype": "postalcode"
  },
  "geometry": {"coordinates":[-4.08945,50.538921],"type":"Point"}
}
