{
  "type": "Feature",
  "properties": {
    "iso:country":"GB",
    "wof:name":"SG5 4HT",
    "wof:placetype":"postalcode"
},
  "geometry": {"coordinates":[-0.23684418880596,52.01275199429058],"type":"Point"}
}