{
  "type": "Feature",
  "properties": {
    "iso:country":"GB",
    "wof:name":"NE37 1LS",
    "wof:placetype":"postalcode"
},
  "geometry": {"coordinates":[-1.55002207799301,54.90524778491802],"type":"Point"}
}