{
  "type": "Feature",
  "properties": {
    "date:inception_lower":"1980-01-01",
    "date:inception_upper":"1980-01-31",
    "iso:country":"GB",
    "wof:name":"NE37 1LS",
    "wof:placetype":"postalcode"
},
  "geometry": {"coordinates":[-1.550022,54.905248],"type":"Point"}
}