{
  "type": "Feature",
  "properties": {
    "iso:country":"GB",
    "wof:name":"SW3 3QA",
    "wof:placetype":"postalcode"
},
  "geometry": {"coordinates":[-0.16984544999207,51.49121085932863],"type":"Point"}
}