{
  "type": "Feature",
  "properties": {
    "iso:country": "GB",
    "wof:name": "SO19 1DF",
    "wof:placetype": "postalcode"
  },
  "geometry": {"coordinates":[-1.338766,50.90372],"type":"Point"}
}
