{
  "type": "Feature",
  "properties": {
    "iso:country":"GB",
    "wof:name":"LL57 2GB",
    "wof:placetype":"postalcode"
},
  "geometry": {"coordinates":[-4.14341607053839,53.22530128971626],"type":"Point"}
}