{
  "type": "Feature",
  "properties": {
    "iso:country": "GB",
    "wof:name": "HP23 6ES",
    "wof:placetype": "postalcode"
  },
  "geometry": {"coordinates":[-0.644417,51.782148],"type":"Point"}
}
