{
  "type": "Feature",
  "properties": {
    "iso:country":"GB",
    "wof:name":"HP23 6ES",
    "wof:placetype":"postalcode"
},
  "geometry": {"coordinates":[-0.64441742037466,51.7821484890426],"type":"Point"}
}