{
  "type": "Feature",
  "properties": {
    "date:inception_lower": "2000-06-01",
    "date:inception_upper": "2000-06-01",
    "iso:country": "GB",
    "wof:name": "SG6 3XU",
    "wof:placetype": "postalcode"
  },
  "geometry": {"coordinates":[-0.229137,51.979124],"type":"Point"}
}
