{
  "type": "Feature",
  "properties": {
    "iso:country":"GB",
    "wof:name":"SG6 3XU",
    "wof:placetype":"postalcode"
},
  "geometry": {"coordinates":[-0.22913703735438,51.97912418410248],"type":"Point"}
}