{
  "type": "Feature",
  "properties": {
    "iso:country": "GB",
    "wof:name": "CH65 6RE",
    "wof:placetype": "postalcode"
  },
  "geometry": {"coordinates":[-2.908259,53.270971],"type":"Point"}
}
