{
  "type": "Feature",
  "properties": {
    "iso:country":"GB",
    "wof:name":"NW4 1DP",
    "wof:placetype":"postalcode"
},
  "geometry": {"coordinates":[-0.22100288943029,51.58943948534937],"type":"Point"}
}