{
  "type": "Feature",
  "properties": {
    "iso:country": "GB",
    "wof:name": "WV6 7JW",
    "wof:placetype": "postalcode"
  },
  "geometry": {"coordinates":[-2.341902,52.587122],"type":"Point"}
}
