{
  "type": "Feature",
  "properties": {
    "iso:country":"GB",
    "wof:name":"WV6 7JW",
    "wof:placetype":"postalcode"
},
  "geometry": {"coordinates":[-2.34190155722274,52.58712175009364],"type":"Point"}
}