{
  "type": "Feature",
  "properties": {
    "date:inception_lower": "1980-01-01",
    "date:inception_upper": "1980-01-01",
    "iso:country": "GB",
    "wof:name": "WV6 7JW",
    "wof:placetype": "postalcode"
  },
  "geometry": {"coordinates":[-2.341902,52.587122],"type":"Point"}
}
