{
  "type": "Feature",
  "properties": {
    "iso:country":"GB",
    "wof:name":"CT15 4JN",
    "wof:placetype":"postalcode"
},
  "geometry": {"coordinates":[1.21275031979577,51.21639504648856],"type":"Point"}
}