{
  "type": "Feature",
  "properties": {
    "date:inception_lower": "2024-09-01",
    "date:inception_upper": "2024-09-01",
    "iso:country": "GB",
    "wof:name": "WF13 9GB",
    "wof:placetype": "postalcode"
  },
  "geometry": {"coordinates":[-1.634178,53.687744],"type":"Point"}
}
