{
  "type": "Feature",
  "properties": {
    "iso:country":"GB",
    "wof:name":"WN4 9HU",
    "wof:placetype":"postalcode"
},
  "geometry": {"coordinates":[-2.62429964412179,53.48554220886873],"type":"Point"}
}