{
  "type": "Feature",
  "properties": {
    "iso:country":"GB",
    "wof:name":"SA61 1TU",
    "wof:placetype":"postalcode"
},
  "geometry": {"coordinates":[-4.961595680449,51.80085945324082],"type":"Point"}
}