{
  "type": "Feature",
  "properties": {
    "iso:country":"GB",
    "wof:name":"M23 2FT",
    "wof:placetype":"postalcode"
},
  "geometry": {"coordinates":[-2.28347152687884,53.3880802518747],"type":"Point"}
}