{
  "type": "Feature",
  "properties": {
    "date:inception_lower": "1999-06-01",
    "date:inception_upper": "1999-06-01",
    "iso:country": "GB",
    "wof:name": "NP11 5DP",
    "wof:placetype": "postalcode"
  },
  "geometry": {"coordinates":[-3.131359,51.673856],"type":"Point"}
}
