{
  "type": "Feature",
  "properties": {
    "date:inception_lower": "2004-05-01",
    "date:inception_upper": "2004-05-01",
    "iso:country": "GB",
    "wof:name": "LN4 4GW",
    "wof:placetype": "postalcode"
  },
  "geometry": {"coordinates":[-0.291958,53.08161],"type":"Point"}
}
