{
  "type": "Feature",
  "properties": {
    "date:inception_lower":"1980-01-01",
    "date:inception_upper":"1980-01-31",
    "iso:country":"GB",
    "wof:name":"CT17 0EA",
    "wof:placetype":"postalcode"
},
  "geometry": {"coordinates":[1.299853,51.128587],"type":"Point"}
}