{
  "type": "Feature",
  "properties": {
    "iso:country":"GB",
    "wof:name":"S35 1RL",
    "wof:placetype":"postalcode"
},
  "geometry": {"coordinates":[-1.48076787417941,53.46085243701014],"type":"Point"}
}