{
  "type": "Feature",
  "properties": {
    "iso:country": "GB",
    "wof:name": "BB12 6HR",
    "wof:placetype": "postalcode"
  },
  "geometry": {"coordinates":[-2.283223,53.78869],"type":"Point"}
}
