{
  "type": "Feature",
  "properties": {
    "iso:country":"GB",
    "wof:name":"BB12 6HR",
    "wof:placetype":"postalcode"
},
  "geometry": {"coordinates":[-2.2832229992536,53.78868955947673],"type":"Point"}
}