{
  "type": "Feature",
  "properties": {
    "date:inception_lower": "1980-01-01",
    "date:inception_upper": "1980-01-01",
    "iso:country": "GB",
    "wof:name": "KT20 7EF",
    "wof:placetype": "postalcode"
  },
  "geometry": {"coordinates":[-0.213216,51.263971],"type":"Point"}
}
