{
  "type": "Feature",
  "properties": {
    "iso:country":"GB",
    "wof:name":"KT20 7EF",
    "wof:placetype":"postalcode"
},
  "geometry": {"coordinates":[-0.21321571294795,51.26397088586656],"type":"Point"}
}