{
  "type": "Feature",
  "properties": {
    "iso:country":"GB",
    "wof:name":"FY6 0DP",
    "wof:placetype":"postalcode"
},
  "geometry": {"coordinates":[-2.98284447167247,53.92958891582135],"type":"Point"}
}