{
  "type": "Feature",
  "properties": {
    "iso:country":"GB",
    "wof:name":"NN3 3LJ",
    "wof:placetype":"postalcode"
},
  "geometry": {"coordinates":[-0.85379418517713,52.24062071995224],"type":"Point"}
}