{
  "type": "Feature",
  "properties": {
    "date:inception_lower": "1980-01-01",
    "date:inception_upper": "1980-01-01",
    "iso:country": "GB",
    "wof:name": "NN3 3LJ",
    "wof:placetype": "postalcode"
  },
  "geometry": {"coordinates":[-0.853794,52.240621],"type":"Point"}
}
