{
  "type": "Feature",
  "properties": {
    "iso:country":"GB",
    "wof:name":"TS12 3AD",
    "wof:placetype":"postalcode"
},
  "geometry": {"coordinates":[-0.98329484167378,54.54358765359293],"type":"Point"}
}