{
  "type": "Feature",
  "properties": {
    "iso:country": "GB",
    "wof:name": "SY22 6AX",
    "wof:placetype": "postalcode"
  },
  "geometry": {"coordinates":[-3.144278,52.777414],"type":"Point"}
}
