{
  "type": "Feature",
  "properties": {
    "iso:country":"GB",
    "wof:name":"SY22 6AX",
    "wof:placetype":"postalcode"
},
  "geometry": {"coordinates":[-3.14427758235749,52.77741374312474],"type":"Point"}
}