{
  "type": "Feature",
  "properties": {
    "date:inception_lower":"1998-06-01",
    "date:inception_upper":"1998-06-30",
    "iso:country":"GB",
    "wof:name":"YO25 4UZ",
    "wof:placetype":"postalcode"
},
  "geometry": {"coordinates":[-0.323618,54.092228],"type":"Point"}
}