{
  "type": "Feature",
  "properties": {
    "iso:country":"GB",
    "wof:name":"YO25 4UZ",
    "wof:placetype":"postalcode"
},
  "geometry": {"coordinates":[-0.32360518378219,54.09220880403382],"type":"Point"}
}