{
  "type": "Feature",
  "properties": {
    "iso:country":"GB",
    "wof:name":"WN5 9QD",
    "wof:placetype":"postalcode"
},
  "geometry": {"coordinates":[-2.66470012489373,53.54026235853247],"type":"Point"}
}