{
  "type": "Feature",
  "properties": {
    "date:inception_lower":"2003-10-01",
    "date:inception_upper":"2003-10-31",
    "iso:country":"GB",
    "wof:name":"WA7 1NN",
    "wof:placetype":"postalcode"
},
  "geometry": {"coordinates":[-2.665585,53.348313],"type":"Point"}
}