{
  "type": "Feature",
  "properties": {
    "iso:country":"GB",
    "wof:name":"WA7 1NN",
    "wof:placetype":"postalcode"
},
  "geometry": {"coordinates":[-2.66558506615021,53.34831346836019],"type":"Point"}
}