{
  "type": "Feature",
  "properties": {
    "iso:country": "GB",
    "wof:name": "BL2 3FS",
    "wof:placetype": "postalcode"
  },
  "geometry": {"coordinates":[-2.411329,53.607018],"type":"Point"}
}
