{
  "type": "Feature",
  "properties": {
    "iso:country":"GB",
    "wof:name":"SN4 7PL",
    "wof:placetype":"postalcode"
},
  "geometry": {"coordinates":[-1.94322053718551,51.51121857973863],"type":"Point"}
}