{
  "type": "Feature",
  "properties": {
    "iso:country": "GB",
    "wof:name": "SN4 7PL",
    "wof:placetype": "postalcode"
  },
  "geometry": {"coordinates":[-1.94322,51.511219],"type":"Point"}
}
