{
  "type": "Feature",
  "properties": {
    "iso:country": "GB",
    "wof:name": "NN3 2RB",
    "wof:placetype": "postalcode"
  },
  "geometry": {"coordinates":[-0.865679,52.259859],"type":"Point"}
}
