{
  "type": "Feature",
  "properties": {
    "iso:country":"GB",
    "wof:name":"NN3 2RB",
    "wof:placetype":"postalcode"
},
  "geometry": {"coordinates":[-0.86567910147385,52.2598588256806],"type":"Point"}
}