{
  "type": "Feature",
  "properties": {
    "iso:country":"GB",
    "wof:name":"PA19 1YX",
    "wof:placetype":"postalcode"
},
  "geometry": {"coordinates":[-4.81666870412689,55.94990371203253],"type":"Point"}
}