{
  "type": "Feature",
  "properties": {
    "date:inception_lower": "1980-01-01",
    "date:inception_upper": "1980-01-01",
    "iso:country": "GB",
    "wof:name": "PA19 1YX",
    "wof:placetype": "postalcode"
  },
  "geometry": {"coordinates":[-4.816619,55.949925],"type":"Point"}
}
