{
  "type": "Feature",
  "properties": {
    "iso:country":"GB",
    "wof:name":"CO3 3GT",
    "wof:placetype":"postalcode"
},
  "geometry": {"coordinates":[0.89066540680623,51.89235061509174],"type":"Point"}
}