{
  "type": "Feature",
  "properties": {
    "date:inception_lower": "1999-12-01",
    "date:inception_upper": "1999-12-01",
    "iso:country": "GB",
    "wof:name": "CO3 3GT",
    "wof:placetype": "postalcode"
  },
  "geometry": {"coordinates":[0.890543,51.892707],"type":"Point"}
}
