{
  "type": "Feature",
  "properties": {
    "iso:country":"GB",
    "wof:name":"MK5 6DY",
    "wof:placetype":"postalcode"
},
  "geometry": {"coordinates":[-0.7947884718261,52.02778314850058],"type":"Point"}
}