{
  "type": "Feature",
  "properties": {
    "iso:country":"GB",
    "wof:name":"TA2 6PQ",
    "wof:placetype":"postalcode"
},
  "geometry": {"coordinates":[-3.15777155192558,51.04244403290699],"type":"Point"}
}