{
  "type": "Feature",
  "properties": {
    "iso:country":"GB",
    "wof:name":"IP2 9UW",
    "wof:placetype":"postalcode"
},
  "geometry": {"coordinates":[1.12612552430485,52.0375421293131],"type":"Point"}
}