{
  "type": "Feature",
  "properties": {
    "date:inception_lower": "1987-04-01",
    "date:inception_upper": "1987-04-01",
    "iso:country": "GB",
    "wof:name": "EX9 6RG",
    "wof:placetype": "postalcode"
  },
  "geometry": {"coordinates":[-3.327031,50.634351],"type":"Point"}
}
