{
  "type": "Feature",
  "properties": {
    "iso:country":"GB",
    "wof:name":"EX9 6RG",
    "wof:placetype":"postalcode"
},
  "geometry": {"coordinates":[-3.32703060606509,50.63435053095168],"type":"Point"}
}