{
  "type": "Feature",
  "properties": {
    "iso:country": "GB",
    "wof:name": "EX9 6RG",
    "wof:placetype": "postalcode"
  },
  "geometry": {"coordinates":[-3.327031,50.634351],"type":"Point"}
}
