{
  "type": "Feature",
  "properties": {
    "iso:country":"GB",
    "wof:name":"CB24 3DX",
    "wof:placetype":"postalcode"
},
  "geometry": {"coordinates":[0.03434404143356,52.2702505824798],"type":"Point"}
}