{
  "type": "Feature",
  "properties": {
    "date:inception_lower":"1980-01-01",
    "date:inception_upper":"1980-01-31",
    "iso:country":"GB",
    "wof:name":"KA30 9NL",
    "wof:placetype":"postalcode"
},
  "geometry": {"coordinates":[-4.853959,55.792807],"type":"Point"}
}