{
  "type": "Feature",
  "properties": {
    "iso:country": "GB",
    "wof:name": "ML1 5QH",
    "wof:placetype": "postalcode"
  },
  "geometry": {"coordinates":[-3.910833,55.802983],"type":"Point"}
}
