{
  "type": "Feature",
  "properties": {
    "iso:country": "GB",
    "wof:name": "WD25 9PH",
    "wof:placetype": "postalcode"
  },
  "geometry": {"coordinates":[-0.39086,51.68566],"type":"Point"}
}
