{
  "type": "Feature",
  "properties": {
    "iso:country":"GB",
    "wof:name":"WD25 9PH",
    "wof:placetype":"postalcode"
},
  "geometry": {"coordinates":[-0.3908600644349,51.68566030217598],"type":"Point"}
}