{
  "type": "Feature",
  "properties": {
    "date:inception_lower":"1987-09-01",
    "date:inception_upper":"1987-09-30",
    "iso:country":"GB",
    "wof:name":"G77 6RH",
    "wof:placetype":"postalcode"
},
  "geometry": {"coordinates":[-4.344832,55.781233],"type":"Point"}
}