{
  "type": "Feature",
  "properties": {
    "iso:country":"GB",
    "wof:name":"G77 6RH",
    "wof:placetype":"postalcode"
},
  "geometry": {"coordinates":[-4.34483249500387,55.78123342549429],"type":"Point"}
}