{
  "type": "Feature",
  "properties": {
    "iso:country": "GB",
    "wof:name": "IV52 8TR",
    "wof:placetype": "postalcode"
  },
  "geometry": {"coordinates":[-5.663795,57.335138],"type":"Point"}
}
