{
  "type": "Feature",
  "properties": {
    "iso:country":"GB",
    "wof:name":"DL3 7PT",
    "wof:placetype":"postalcode"
},
  "geometry": {"coordinates":[-1.56068743248505,54.52904215484384],"type":"Point"}
}