{
  "type": "Feature",
  "properties": {
    "iso:country": "GB",
    "wof:name": "YO30 5XZ",
    "wof:placetype": "postalcode"
  },
  "geometry": {"coordinates":[-1.12289,53.984348],"type":"Point"}
}
