{
  "type": "Feature",
  "properties": {
    "iso:country":"GB",
    "wof:name":"YO30 5XZ",
    "wof:placetype":"postalcode"
},
  "geometry": {"coordinates":[-1.12270062128987,53.98420372716615],"type":"Point"}
}