{
  "type": "Feature",
  "properties": {
    "iso:country":"GB",
    "wof:name":"LN5 9QR",
    "wof:placetype":"postalcode"
},
  "geometry": {"coordinates":[-0.55229021361806,53.17425814084667],"type":"Point"}
}