{
  "type": "Feature",
  "properties": {
    "iso:country":"GB",
    "wof:name":"RH19 4PD",
    "wof:placetype":"postalcode"
},
  "geometry": {"coordinates":[-0.04525975473251,51.07635267439706],"type":"Point"}
}