{
  "type": "Feature",
  "properties": {
    "iso:country": "GB",
    "wof:name": "RH19 4PD",
    "wof:placetype": "postalcode"
  },
  "geometry": {"coordinates":[-0.04526,51.076353],"type":"Point"}
}
