{
  "type": "Feature",
  "properties": {
    "date:inception_lower":"1992-08-01",
    "date:inception_upper":"1992-08-31",
    "iso:country":"GB",
    "wof:name":"DE55 6AA",
    "wof:placetype":"postalcode"
},
  "geometry": {"coordinates":[-1.409036,53.120993],"type":"Point"}
}