{
  "type": "Feature",
  "properties": {
    "iso:country":"GB",
    "wof:name":"DA13 0XF",
    "wof:placetype":"postalcode"
},
  "geometry": {"coordinates":[0.39643458112496,51.35203069064774],"type":"Point"}
}