{
  "type": "Feature",
  "properties": {
    "iso:country":"GB",
    "wof:name":"NR29 3RG",
    "wof:placetype":"postalcode"
},
  "geometry": {"coordinates":[1.68365816165385,52.67413565901981],"type":"Point"}
}