{
  "type": "Feature",
  "properties": {
    "iso:country":"GB",
    "wof:name":"OL4 2EL",
    "wof:placetype":"postalcode"
},
  "geometry": {"coordinates":[-2.07910358358381,53.54721702939961],"type":"Point"}
}