{
  "type": "Feature",
  "properties": {
    "iso:country": "GB",
    "wof:name": "OL4 2EL",
    "wof:placetype": "postalcode"
  },
  "geometry": {"coordinates":[-2.079104,53.547217],"type":"Point"}
}
