{
  "type": "Feature",
  "properties": {
    "date:inception_lower": "2007-11-01",
    "date:inception_upper": "2007-11-01",
    "iso:country": "GB",
    "wof:name": "ME3 9LZ",
    "wof:placetype": "postalcode"
  },
  "geometry": {"coordinates":[0.561906,51.428418],"type":"Point"}
}
