{
  "type": "Feature",
  "properties": {
    "iso:country":"GB",
    "wof:name":"ME3 9LZ",
    "wof:placetype":"postalcode"
},
  "geometry": {"coordinates":[0.56190563410663,51.42841768429739],"type":"Point"}
}