{
  "type": "Feature",
  "properties": {
    "iso:country":"GB",
    "wof:name":"CF24 4SY",
    "wof:placetype":"postalcode"
},
  "geometry": {"coordinates":[-3.17136279754797,51.4966228154205],"type":"Point"}
}