{
  "type": "Feature",
  "properties": {
    "iso:country":"GB",
    "wof:name":"CO15 6EU",
    "wof:placetype":"postalcode"
},
  "geometry": {"coordinates":[1.16308588721169,51.79526129839993],"type":"Point"}
}