{
  "type": "Feature",
  "properties": {
    "iso:country":"GB",
    "wof:name":"HA1 4TF",
    "wof:placetype":"postalcode"
},
  "geometry": {"coordinates":[-0.34409890040229,51.58861500006613],"type":"Point"}
}