{
  "type": "Feature",
  "properties": {
    "date:inception_lower": "1985-10-01",
    "date:inception_upper": "1985-10-01",
    "iso:country": "GB",
    "wof:name": "NE23 6YA",
    "wof:placetype": "postalcode"
  },
  "geometry": {"coordinates":[-1.580592,55.074341],"type":"Point"}
}
