{
  "type": "Feature",
  "properties": {
    "iso:country": "GB",
    "wof:name": "PL30 3BY",
    "wof:placetype": "postalcode"
  },
  "geometry": {"coordinates":[-4.747684,50.526931],"type":"Point"}
}
