{
  "type": "Feature",
  "properties": {
    "iso:country": "GB",
    "wof:name": "DY5 2NT",
    "wof:placetype": "postalcode"
  },
  "geometry": {"coordinates":[-2.118847,52.468904],"type":"Point"}
}
