{
  "type": "Feature",
  "properties": {
    "iso:country":"GB",
    "wof:name":"DY5 2NT",
    "wof:placetype":"postalcode"
},
  "geometry": {"coordinates":[-2.11883812965674,52.4689165589548],"type":"Point"}
}