{
  "type": "Feature",
  "properties": {
    "date:inception_lower":"1996-12-01",
    "date:inception_upper":"1996-12-31",
    "iso:country":"GB",
    "wof:name":"CO2 9QW",
    "wof:placetype":"postalcode"
},
  "geometry": {"coordinates":[0.880463,51.861933],"type":"Point"}
}