{
  "type": "Feature",
  "properties": {
    "iso:country": "GB",
    "wof:name": "CO2 9QW",
    "wof:placetype": "postalcode"
  },
  "geometry": {"coordinates":[0.880463,51.861933],"type":"Point"}
}
