{
  "type": "Feature",
  "properties": {
    "date:inception_lower": "2022-04-01",
    "date:inception_upper": "2022-04-01",
    "iso:country": "GB",
    "wof:name": "HP1 1BN",
    "wof:placetype": "postalcode"
  },
  "geometry": {"coordinates":[-0.474701,51.753164],"type":"Point"}
}
