{
  "type": "Feature",
  "properties": {
    "date:inception_lower": "1980-01-01",
    "date:inception_upper": "1980-01-01",
    "iso:country": "GB",
    "wof:name": "IP14 4NP",
    "wof:placetype": "postalcode"
  },
  "geometry": {"coordinates":[0.988326,52.225658],"type":"Point"}
}
