{
  "type": "Feature",
  "properties": {
    "iso:country":"GB",
    "wof:name":"LS20 9EZ",
    "wof:placetype":"postalcode"
},
  "geometry": {"coordinates":[-1.70893715271053,53.87782339111325],"type":"Point"}
}