{
  "type": "Feature",
  "properties": {
    "iso:country": "GB",
    "wof:name": "LS20 9EZ",
    "wof:placetype": "postalcode"
  },
  "geometry": {"coordinates":[-1.708937,53.877823],"type":"Point"}
}
