{
  "type": "Feature",
  "properties": {
    "iso:country":"GB",
    "wof:name":"PR4 0JE",
    "wof:placetype":"postalcode"
},
  "geometry": {"coordinates":[-2.75364515941491,53.78904562618497],"type":"Point"}
}