{
  "type": "Feature",
  "properties": {
    "iso:country":"GB",
    "wof:name":"HA1 4DJ",
    "wof:placetype":"postalcode"
},
  "geometry": {"coordinates":[-0.34695517753793,51.57753192990968],"type":"Point"}
}