{
  "type": "Feature",
  "properties": {
    "iso:country":"GB",
    "wof:name":"DT10 1DQ",
    "wof:placetype":"postalcode"
},
  "geometry": {"coordinates":[-2.30791536683188,50.92354653591011],"type":"Point"}
}