{
  "type": "Feature",
  "properties": {
    "iso:country": "GB",
    "wof:name": "DT10 1DQ",
    "wof:placetype": "postalcode"
  },
  "geometry": {"coordinates":[-2.307915,50.923547],"type":"Point"}
}
