{
  "type": "Feature",
  "properties": {
    "iso:country":"GB",
    "wof:name":"NP26 5PE",
    "wof:placetype":"postalcode"
},
  "geometry": {"coordinates":[-2.80109708431782,51.61075611738903],"type":"Point"}
}