{
  "type": "Feature",
  "properties": {
    "iso:country": "GB",
    "wof:name": "LS24 9UH",
    "wof:placetype": "postalcode"
  },
  "geometry": {"coordinates":[-1.213303,53.852788],"type":"Point"}
}
