{
  "type": "Feature",
  "properties": {
    "iso:country": "GB",
    "wof:name": "S45 9DZ",
    "wof:placetype": "postalcode"
  },
  "geometry": {"coordinates":[-1.416049,53.16599],"type":"Point"}
}
