{
  "type": "Feature",
  "properties": {
    "iso:country":"GB",
    "wof:name":"S45 9DZ",
    "wof:placetype":"postalcode"
},
  "geometry": {"coordinates":[-1.41604865081226,53.16599014022012],"type":"Point"}
}