{
  "type": "Feature",
  "properties": {
    "iso:country":"GB",
    "wof:name":"CA3 0AD",
    "wof:placetype":"postalcode"
},
  "geometry": {"coordinates":[-2.94106582152102,54.91408980217963],"type":"Point"}
}