{
  "type": "Feature",
  "properties": {
    "iso:country":"GB",
    "wof:name":"DE12 6EN",
    "wof:placetype":"postalcode"
},
  "geometry": {"coordinates":[-1.52416366463321,52.74141088982021],"type":"Point"}
}