{
  "type": "Feature",
  "properties": {
    "iso:country":"GB",
    "wof:name":"AL1 2DT",
    "wof:placetype":"postalcode"
},
  "geometry": {"coordinates":[-0.34682670615833,51.74355979418537],"type":"Point"}
}