{
  "type": "Feature",
  "properties": {
    "iso:country": "GB",
    "wof:name": "AL1 2DT",
    "wof:placetype": "postalcode"
  },
  "geometry": {"coordinates":[-0.346777,51.743511],"type":"Point"}
}
