{
  "type": "Feature",
  "properties": {
    "iso:country": "GB",
    "wof:name": "CV34 6RG",
    "wof:placetype": "postalcode"
  },
  "geometry": {"coordinates":[-1.606057,52.265197],"type":"Point"}
}
