{
  "type": "Feature",
  "properties": {
    "date:inception_lower": "2012-10-01",
    "date:inception_upper": "2012-10-01",
    "iso:country": "GB",
    "wof:name": "CV34 6RG",
    "wof:placetype": "postalcode"
  },
  "geometry": {"coordinates":[-1.605811,52.265148],"type":"Point"}
}
