{
  "type": "Feature",
  "properties": {
    "iso:country": "GB",
    "wof:name": "CW11 1FH",
    "wof:placetype": "postalcode"
  },
  "geometry": {"coordinates":[-2.374206,53.145465],"type":"Point"}
}
