{
  "type": "Feature",
  "properties": {
    "iso:country":"GB",
    "wof:name":"WA4 6DB",
    "wof:placetype":"postalcode"
},
  "geometry": {"coordinates":[-2.59563463779466,53.37352815583669],"type":"Point"}
}