{
  "type": "Feature",
  "properties": {
    "iso:country":"GB",
    "wof:name":"CM9 8JA",
    "wof:placetype":"postalcode"
},
  "geometry": {"coordinates":[0.7082227368394,51.74900484817795],"type":"Point"}
}