{
  "type": "Feature",
  "properties": {
    "date:inception_lower": "2019-09-01",
    "date:inception_upper": "2019-09-01",
    "iso:country": "GB",
    "wof:name": "M41 9GB",
    "wof:placetype": "postalcode"
  },
  "geometry": {"coordinates":[-2.329434,53.446305],"type":"Point"}
}
