{
  "type": "Feature",
  "properties": {
    "iso:country":"GB",
    "wof:name":"TS7 0LB",
    "wof:placetype":"postalcode"
},
  "geometry": {"coordinates":[-1.16146567071232,54.5328927024529],"type":"Point"}
}