{
  "type": "Feature",
  "properties": {
    "date:inception_lower":"1980-01-01",
    "date:inception_upper":"1980-01-31",
    "iso:country":"GB",
    "wof:name":"TS7 0LB",
    "wof:placetype":"postalcode"
},
  "geometry": {"coordinates":[-1.161466,54.532893],"type":"Point"}
}