{
  "type": "Feature",
  "properties": {
    "iso:country": "GB",
    "wof:name": "EX31 4QH",
    "wof:placetype": "postalcode"
  },
  "geometry": {"coordinates":[-3.90517,51.188299],"type":"Point"}
}
