{
  "type": "Feature",
  "properties": {
    "date:inception_lower": "1991-09-01",
    "date:inception_upper": "1991-09-01",
    "iso:country": "GB",
    "wof:name": "EX31 4QH",
    "wof:placetype": "postalcode"
  },
  "geometry": {"coordinates":[-3.905137,51.188201],"type":"Point"}
}
