{
  "type": "Feature",
  "properties": {
    "iso:country":"GB",
    "wof:name":"EX31 4QH",
    "wof:placetype":"postalcode"
},
  "geometry": {"coordinates":[-3.90515086446258,51.1882993713353],"type":"Point"}
}