{
  "type": "Feature",
  "properties": {
    "date:inception_lower": "1988-03-01",
    "date:inception_upper": "1988-03-01",
    "iso:country": "GB",
    "wof:name": "MK41 8RL",
    "wof:placetype": "postalcode"
  },
  "geometry": {"coordinates":[-0.42902,52.148967],"type":"Point"}
}
