{
  "type": "Feature",
  "properties": {
    "iso:country": "GB",
    "wof:name": "MK41 8RL",
    "wof:placetype": "postalcode"
  },
  "geometry": {"coordinates":[-0.42902,52.148967],"type":"Point"}
}
