{
  "type": "Feature",
  "properties": {
    "iso:country":"GB",
    "wof:name":"BD23 6HX",
    "wof:placetype":"postalcode"
},
  "geometry": {"coordinates":[-1.87272845879927,53.98238445015504],"type":"Point"}
}