{
  "type": "Feature",
  "properties": {
    "date:inception_lower": "1980-01-01",
    "date:inception_upper": "1980-01-01",
    "iso:country": "GB",
    "wof:name": "BD23 6HX",
    "wof:placetype": "postalcode"
  },
  "geometry": {"coordinates":[-1.872595,53.982462],"type":"Point"}
}
