{
  "type": "Feature",
  "properties": {
    "iso:country": "GB",
    "wof:name": "TN15 8EB",
    "wof:placetype": "postalcode"
  },
  "geometry": {"coordinates":[0.311123,51.294947],"type":"Point"}
}
