{
  "type": "Feature",
  "properties": {
    "iso:country":"GB",
    "wof:name":"RG19 8AA",
    "wof:placetype":"postalcode"
},
  "geometry": {"coordinates":[-1.25782941585073,51.3613767579839],"type":"Point"}
}