{
  "type": "Feature",
  "properties": {
    "iso:country":"GB",
    "wof:name":"SL9 9AG",
    "wof:placetype":"postalcode"
},
  "geometry": {"coordinates":[-0.55574478833891,51.60471805935524],"type":"Point"}
}