{
  "type": "Feature",
  "properties": {
    "date:inception_lower": "1980-01-01",
    "date:inception_upper": "1980-01-01",
    "iso:country": "GB",
    "wof:name": "SL9 9AG",
    "wof:placetype": "postalcode"
  },
  "geometry": {"coordinates":[-0.555745,51.604718],"type":"Point"}
}
