{
  "type": "Feature",
  "properties": {
    "date:inception_lower":"2005-01-01",
    "date:inception_upper":"2005-01-31",
    "iso:country":"GB",
    "wof:name":"S63 5AB",
    "wof:placetype":"postalcode"
},
  "geometry": {"coordinates":[-1.314261,53.498386],"type":"Point"}
}