{
  "type": "Feature",
  "properties": {
    "iso:country":"GB",
    "wof:name":"PA8 6HF",
    "wof:placetype":"postalcode"
},
  "geometry": {"coordinates":[-4.47531684879799,55.90270839689062],"type":"Point"}
}