{
  "type": "Feature",
  "properties": {
    "iso:country":"GB",
    "wof:name":"OX7 6RN",
    "wof:placetype":"postalcode"
},
  "geometry": {"coordinates":[-1.62808150406132,51.88724890100337],"type":"Point"}
}