{
  "type": "Feature",
  "properties": {
    "iso:country": "GB",
    "wof:name": "NE4 7UL",
    "wof:placetype": "postalcode"
  },
  "geometry": {"coordinates":[-1.656038,54.969666],"type":"Point"}
}
