{
  "type": "Feature",
  "properties": {
    "iso:country":"GB",
    "wof:name":"NE4 7UL",
    "wof:placetype":"postalcode"
},
  "geometry": {"coordinates":[-1.65603800156914,54.96966618994534],"type":"Point"}
}