{
  "type": "Feature",
  "properties": {
    "iso:country":"GB",
    "wof:name":"NG3 2FT",
    "wof:placetype":"postalcode"
},
  "geometry": {"coordinates":[-1.12842014365583,52.95883556848123],"type":"Point"}
}