{
  "type": "Feature",
  "properties": {
    "iso:country":"GB",
    "wof:name":"HR6 0AP",
    "wof:placetype":"postalcode"
},
  "geometry": {"coordinates":[-2.75208336572633,52.259554775791],"type":"Point"}
}