{
  "type": "Feature",
  "properties": {
    "date:inception_lower": "1980-01-01",
    "date:inception_upper": "1980-01-01",
    "iso:country": "GB",
    "wof:name": "WF9 1AW",
    "wof:placetype": "postalcode"
  },
  "geometry": {"coordinates":[-1.308541,53.633045],"type":"Point"}
}
