{
  "type": "Feature",
  "properties": {
    "iso:country":"GB",
    "wof:name":"DH8 0BX",
    "wof:placetype":"postalcode"
},
  "geometry": {"coordinates":[-1.84266694106079,54.8667260580125],"type":"Point"}
}