{
  "type": "Feature",
  "properties": {
    "iso:country":"GB",
    "wof:name":"CH7 6SE",
    "wof:placetype":"postalcode"
},
  "geometry": {"coordinates":[-3.1109267561929,53.17528068548981],"type":"Point"}
}