{
  "type": "Feature",
  "properties": {
    "iso:country":"GB",
    "wof:name":"S42 6DA",
    "wof:placetype":"postalcode"
},
  "geometry": {"coordinates":[-1.40055618203812,53.18180583709834],"type":"Point"}
}