{
  "type": "Feature",
  "properties": {
    "iso:country":"GB",
    "wof:name":"DN4 9AH",
    "wof:placetype":"postalcode"
},
  "geometry": {"coordinates":[-1.15998350067379,53.49917215941475],"type":"Point"}
}