{
  "type": "Feature",
  "properties": {
    "iso:country": "GB",
    "wof:name": "DN4 9AH",
    "wof:placetype": "postalcode"
  },
  "geometry": {"coordinates":[-1.159983,53.499172],"type":"Point"}
}
