{
  "type": "Feature",
  "properties": {
    "iso:country": "GB",
    "wof:name": "IP17 1QZ",
    "wof:placetype": "postalcode"
  },
  "geometry": {"coordinates":[1.484126,52.17405],"type":"Point"}
}
