{
  "type": "Feature",
  "properties": {
    "iso:country": "GB",
    "wof:name": "TS18 2SR",
    "wof:placetype": "postalcode"
  },
  "geometry": {"coordinates":[-1.293106,54.565637],"type":"Point"}
}
