{
  "type": "Feature",
  "properties": {
    "date:inception_lower": "2012-07-01",
    "date:inception_upper": "2012-07-01",
    "iso:country": "GB",
    "wof:name": "TS18 2SR",
    "wof:placetype": "postalcode"
  },
  "geometry": {"coordinates":[-1.293106,54.565637],"type":"Point"}
}
