{
  "type": "Feature",
  "properties": {
    "iso:country":"GB",
    "wof:name":"TS18 2SR",
    "wof:placetype":"postalcode"
},
  "geometry": {"coordinates":[-1.29310616529241,54.56563737366579],"type":"Point"}
}