{
  "type": "Feature",
  "properties": {
    "iso:country":"GB",
    "wof:name":"LS20 8HX",
    "wof:placetype":"postalcode"
},
  "geometry": {"coordinates":[-1.72484143217012,53.86948416867251],"type":"Point"}
}