{
  "type": "Feature",
  "properties": {
    "iso:country": "GB",
    "wof:name": "CH3 7HU",
    "wof:placetype": "postalcode"
  },
  "geometry": {"coordinates":[-2.799148,53.211874],"type":"Point"}
}
