{
  "type": "Feature",
  "properties": {
    "date:inception_lower":"2018-07-01",
    "date:inception_upper":"2018-07-31",
    "iso:country":"GB",
    "wof:name":"CH3 7HU",
    "wof:placetype":"postalcode"
},
  "geometry": {"coordinates":[-2.799148,53.211874],"type":"Point"}
}