{
  "type": "Feature",
  "properties": {
    "iso:country":"GB",
    "wof:name":"ST1 2AN",
    "wof:placetype":"postalcode"
},
  "geometry": {"coordinates":[-2.16487263009869,53.02634876604312],"type":"Point"}
}