{
  "type": "Feature",
  "properties": {
    "date:inception_lower":"1980-01-01",
    "date:inception_upper":"1980-01-31",
    "iso:country":"GB",
    "wof:name":"ST1 2AN",
    "wof:placetype":"postalcode"
},
  "geometry": {"coordinates":[-2.164873,53.026349],"type":"Point"}
}