{
  "type": "Feature",
  "properties": {
    "iso:country":"GB",
    "wof:name":"BS13 9PE",
    "wof:placetype":"postalcode"
},
  "geometry": {"coordinates":[-2.60622890777117,51.41142175301679],"type":"Point"}
}