{
  "type": "Feature",
  "properties": {
    "iso:country": "GB",
    "wof:name": "SY3 9BU",
    "wof:placetype": "postalcode"
  },
  "geometry": {"coordinates":[-2.785984,52.699673],"type":"Point"}
}
