{
  "type": "Feature",
  "properties": {
    "iso:country":"GB",
    "wof:name":"SY3 9BU",
    "wof:placetype":"postalcode"
},
  "geometry": {"coordinates":[-2.78598439294854,52.69967272822775],"type":"Point"}
}