{
  "type": "Feature",
  "properties": {
    "iso:country":"GB",
    "wof:name":"S75 5JL",
    "wof:placetype":"postalcode"
},
  "geometry": {"coordinates":[-1.54177603709499,53.5816460292666],"type":"Point"}
}