{
  "type": "Feature",
  "properties": {
    "iso:country":"GB",
    "wof:name":"NE9 6RL",
    "wof:placetype":"postalcode"
},
  "geometry": {"coordinates":[-1.58216083720488,54.93575431275989],"type":"Point"}
}