{
  "type": "Feature",
  "properties": {
    "date:inception_lower": "1996-12-01",
    "date:inception_upper": "1996-12-01",
    "iso:country": "GB",
    "wof:name": "NE9 6RL",
    "wof:placetype": "postalcode"
  },
  "geometry": {"coordinates":[-1.58213,54.935709],"type":"Point"}
}
