{
  "type": "Feature",
  "properties": {
    "iso:country":"GB",
    "wof:name":"WV16 6PH",
    "wof:placetype":"postalcode"
},
  "geometry": {"coordinates":[-2.43443775415695,52.46523811435639],"type":"Point"}
}