{
  "type": "Feature",
  "properties": {
    "iso:country": "GB",
    "wof:name": "L37 1QN",
    "wof:placetype": "postalcode"
  },
  "geometry": {"coordinates":[-3.079036,53.565122],"type":"Point"}
}
