{
  "type": "Feature",
  "properties": {
    "iso:country": "GB",
    "wof:name": "DE1 2LF",
    "wof:placetype": "postalcode"
  },
  "geometry": {"coordinates":[-1.473116,52.927143],"type":"Point"}
}
