{
  "type": "Feature",
  "properties": {
    "iso:country":"GB",
    "wof:name":"TN35 5NW",
    "wof:placetype":"postalcode"
},
  "geometry": {"coordinates":[0.60311363852746,50.86422531493128],"type":"Point"}
}