{
  "type": "Feature",
  "properties": {
    "iso:country": "GB",
    "wof:name": "TN35 5NW",
    "wof:placetype": "postalcode"
  },
  "geometry": {"coordinates":[0.603114,50.864225],"type":"Point"}
}
