{
  "type": "Feature",
  "properties": {
    "date:inception_lower":"1980-01-01",
    "date:inception_upper":"1980-01-31",
    "iso:country":"GB",
    "wof:name":"HX7 6NH",
    "wof:placetype":"postalcode"
},
  "geometry": {"coordinates":[-2.033587,53.737357],"type":"Point"}
}