{
  "type": "Feature",
  "properties": {
    "iso:country":"GB",
    "wof:name":"HX7 6NH",
    "wof:placetype":"postalcode"
},
  "geometry": {"coordinates":[-2.03358741572378,53.73735678045643],"type":"Point"}
}