{
  "type": "Feature",
  "properties": {
    "iso:country":"GB",
    "wof:name":"CR0 8QD",
    "wof:placetype":"postalcode"
},
  "geometry": {"coordinates":[-0.03969517560889,51.37122155763906],"type":"Point"}
}