{
  "type": "Feature",
  "properties": {
    "iso:country":"GB",
    "wof:name":"YO41 4EJ",
    "wof:placetype":"postalcode"
},
  "geometry": {"coordinates":[-0.93573744849049,53.92124152299532],"type":"Point"}
}