{
  "type": "Feature",
  "properties": {
    "date:inception_lower": "2008-09-01",
    "date:inception_upper": "2008-09-01",
    "iso:country": "GB",
    "wof:name": "YO41 4EJ",
    "wof:placetype": "postalcode"
  },
  "geometry": {"coordinates":[-0.935762,53.921181],"type":"Point"}
}
