{
  "type": "Feature",
  "properties": {
    "iso:country": "GB",
    "wof:name": "YO41 4EJ",
    "wof:placetype": "postalcode"
  },
  "geometry": {"coordinates":[-0.935762,53.921181],"type":"Point"}
}
