{
  "type": "Feature",
  "properties": {
    "iso:country":"GB",
    "wof:name":"SE3 8ED",
    "wof:placetype":"postalcode"
},
  "geometry": {"coordinates":[0.02585743365257,51.47449502256678],"type":"Point"}
}