{
  "type": "Feature",
  "properties": {
    "iso:country":"GB",
    "wof:name":"ST3 4ES",
    "wof:placetype":"postalcode"
},
  "geometry": {"coordinates":[-2.13619315179469,52.97637837477669],"type":"Point"}
}