{
  "type": "Feature",
  "properties": {
    "iso:country": "GB",
    "wof:name": "LD1 6LA",
    "wof:placetype": "postalcode"
  },
  "geometry": {"coordinates":[-3.440924,52.213199],"type":"Point"}
}
