{
  "type": "Feature",
  "properties": {
    "date:inception_lower": "1980-01-01",
    "date:inception_upper": "1980-01-01",
    "iso:country": "GB",
    "wof:name": "EX14 9BU",
    "wof:placetype": "postalcode"
  },
  "geometry": {"coordinates":[-3.089995,50.830986],"type":"Point"}
}
