{
  "type": "Feature",
  "properties": {
    "iso:country":"GB",
    "wof:name":"LE9 1RD",
    "wof:placetype":"postalcode"
},
  "geometry": {"coordinates":[-1.20932487980132,52.54075636123049],"type":"Point"}
}