{
  "type": "Feature",
  "properties": {
    "date:inception_lower": "1980-01-01",
    "date:inception_upper": "1980-01-01",
    "iso:country": "GB",
    "wof:name": "NW1 5BA",
    "wof:placetype": "postalcode"
  },
  "geometry": {"coordinates":[-0.167926,51.518959],"type":"Point"}
}
