{
  "type": "Feature",
  "properties": {
    "iso:country":"GB",
    "wof:name":"NW1 5BA",
    "wof:placetype":"postalcode"
},
  "geometry": {"coordinates":[-0.16792616356139,51.5189586818496],"type":"Point"}
}