{
  "type": "Feature",
  "properties": {
    "iso:country":"GB",
    "wof:name":"YO31 7QY",
    "wof:placetype":"postalcode"
},
  "geometry": {"coordinates":[-1.07632652500989,53.96484662686266],"type":"Point"}
}