{
  "type": "Feature",
  "properties": {
    "date:inception_lower": "1998-06-01",
    "date:inception_upper": "1998-06-01",
    "iso:country": "GB",
    "wof:name": "YO31 7QY",
    "wof:placetype": "postalcode"
  },
  "geometry": {"coordinates":[-1.076336,53.964847],"type":"Point"}
}
