{
  "type": "Feature",
  "properties": {
    "iso:country":"GB",
    "wof:name":"RH12 4NX",
    "wof:placetype":"postalcode"
},
  "geometry": {"coordinates":[-0.28780991967765,51.07582266549835],"type":"Point"}
}