{
  "type": "Feature",
  "properties": {
    "iso:country":"GB",
    "wof:name":"BS24 9DF",
    "wof:placetype":"postalcode"
},
  "geometry": {"coordinates":[-2.95828689837622,51.32326112500783],"type":"Point"}
}