{
  "type": "Feature",
  "properties": {
    "iso:country":"GB",
    "wof:name":"SE20 8FJ",
    "wof:placetype":"postalcode"
},
  "geometry": {"coordinates":[-0.07109290507945,51.4128036522086],"type":"Point"}
}