{
  "type": "Feature",
  "properties": {
    "date:inception_lower": "1980-01-01",
    "date:inception_upper": "1980-01-01",
    "iso:country": "GB",
    "wof:name": "S42 6HG",
    "wof:placetype": "postalcode"
  },
  "geometry": {"coordinates":[-1.43069,53.179627],"type":"Point"}
}
