{
  "type": "Feature",
  "properties": {
    "iso:country": "GB",
    "wof:name": "S42 6HG",
    "wof:placetype": "postalcode"
  },
  "geometry": {"coordinates":[-1.43069,53.179627],"type":"Point"}
}
