{
  "type": "Feature",
  "properties": {
    "date:inception_lower": "1980-01-01",
    "date:inception_upper": "1980-01-01",
    "iso:country": "GB",
    "wof:name": "LL20 7ES",
    "wof:placetype": "postalcode"
  },
  "geometry": {"coordinates":[-3.188298,52.931937],"type":"Point"}
}
