{
  "type": "Feature",
  "properties": {
    "iso:country": "GB",
    "wof:name": "LL20 7ES",
    "wof:placetype": "postalcode"
  },
  "geometry": {"coordinates":[-3.188298,52.931937],"type":"Point"}
}
