{
  "type": "Feature",
  "properties": {
    "iso:country":"GB",
    "wof:name":"NG6 8QX",
    "wof:placetype":"postalcode"
},
  "geometry": {"coordinates":[-1.19741547950418,52.98962472965099],"type":"Point"}
}