{
  "type": "Feature",
  "properties": {
    "date:inception_lower": "1980-01-01",
    "date:inception_upper": "1980-01-01",
    "iso:country": "GB",
    "wof:name": "SY23 1HG",
    "wof:placetype": "postalcode"
  },
  "geometry": {"coordinates":[-4.067132,52.411569],"type":"Point"}
}
