{
  "type": "Feature",
  "properties": {
    "iso:country":"GB",
    "wof:name":"CV33 9NL",
    "wof:placetype":"postalcode"
},
  "geometry": {"coordinates":[-1.46368656825318,52.22646344372065],"type":"Point"}
}