{
  "type": "Feature",
  "properties": {
    "iso:country": "GB",
    "wof:name": "BS21 7YU",
    "wof:placetype": "postalcode"
  },
  "geometry": {"coordinates":[-2.869997,51.426735],"type":"Point"}
}
