{
  "type": "Feature",
  "properties": {
    "iso:country":"GB",
    "wof:name":"BS21 7YU",
    "wof:placetype":"postalcode"
},
  "geometry": {"coordinates":[-2.86997800252428,51.42672779859498],"type":"Point"}
}