{
  "type": "Feature",
  "properties": {
    "iso:country":"GB",
    "wof:name":"NN1 4SN",
    "wof:placetype":"postalcode"
},
  "geometry": {"coordinates":[-0.87284872130966,52.25388570497239],"type":"Point"}
}