{
  "type": "Feature",
  "properties": {
    "iso:country":"GB",
    "wof:name":"WF9 3ER",
    "wof:placetype":"postalcode"
},
  "geometry": {"coordinates":[-1.33683811841157,53.58852400334283],"type":"Point"}
}