{
  "type": "Feature",
  "properties": {
    "iso:country":"GB",
    "wof:name":"BA11 2QH",
    "wof:placetype":"postalcode"
},
  "geometry": {"coordinates":[-2.34615216525044,51.25141853518025],"type":"Point"}
}