{
  "type": "Feature",
  "properties": {
    "iso:country":"GB",
    "wof:name":"SE1 2UF",
    "wof:placetype":"postalcode"
},
  "geometry": {"coordinates":[-0.07755974772754,51.50266561538526],"type":"Point"}
}