{
  "type": "Feature",
  "properties": {
    "iso:country":"GB",
    "wof:name":"LN4 3YB",
    "wof:placetype":"postalcode"
},
  "geometry": {"coordinates":[-0.43507681527036,53.09527408821584],"type":"Point"}
}