{
  "type": "Feature",
  "properties": {
    "date:inception_lower":"1995-01-01",
    "date:inception_upper":"1995-01-31",
    "iso:country":"GB",
    "wof:name":"LN4 3YB",
    "wof:placetype":"postalcode"
},
  "geometry": {"coordinates":[-0.435077,53.095274],"type":"Point"}
}