{
  "type": "Feature",
  "properties": {
    "iso:country":"GB",
    "wof:name":"RG18 0TX",
    "wof:placetype":"postalcode"
},
  "geometry": {"coordinates":[-1.23315562851626,51.48162661747801],"type":"Point"}
}