{
  "type": "Feature",
  "properties": {
    "iso:country": "GB",
    "wof:name": "TN38 9ET",
    "wof:placetype": "postalcode"
  },
  "geometry": {"coordinates":[0.550618,50.873417],"type":"Point"}
}
