{
  "type": "Feature",
  "properties": {
    "iso:country":"GB",
    "wof:name":"TN38 9ET",
    "wof:placetype":"postalcode"
},
  "geometry": {"coordinates":[0.55061796418384,50.87341677463854],"type":"Point"}
}