{
  "type": "Feature",
  "properties": {
    "date:inception_lower": "1980-01-01",
    "date:inception_upper": "1980-01-01",
    "iso:country": "GB",
    "wof:name": "NN15 6HY",
    "wof:placetype": "postalcode"
  },
  "geometry": {"coordinates":[-0.724086,52.384221],"type":"Point"}
}
