{
  "type": "Feature",
  "properties": {
    "iso:country":"GB",
    "wof:name":"AL8 7PD",
    "wof:placetype":"postalcode"
},
  "geometry": {"coordinates":[-0.20629442183276,51.80750066332898],"type":"Point"}
}