{
  "type": "Feature",
  "properties": {
    "date:inception_lower": "1980-01-01",
    "date:inception_upper": "1980-01-01",
    "iso:country": "GB",
    "wof:name": "AL8 7PD",
    "wof:placetype": "postalcode"
  },
  "geometry": {"coordinates":[-0.206256,51.807507],"type":"Point"}
}
