{
  "type": "Feature",
  "properties": {
    "iso:country": "GB",
    "wof:name": "G84 7RD",
    "wof:placetype": "postalcode"
  },
  "geometry": {"coordinates":[-4.720317,56.003179],"type":"Point"}
}
