{
  "type": "Feature",
  "properties": {
    "iso:country":"GB",
    "wof:name":"G84 7RD",
    "wof:placetype":"postalcode"
},
  "geometry": {"coordinates":[-4.72031706669471,56.00317857220164],"type":"Point"}
}