{
  "type": "Feature",
  "properties": {
    "iso:country":"GB",
    "wof:name":"SP2 8NL",
    "wof:placetype":"postalcode"
},
  "geometry": {"coordinates":[-1.81813265706602,51.0596850274538],"type":"Point"}
}