{
  "type": "Feature",
  "properties": {
    "iso:country": "GB",
    "wof:name": "SP2 8NL",
    "wof:placetype": "postalcode"
  },
  "geometry": {"coordinates":[-1.818133,51.059685],"type":"Point"}
}
