{
  "type": "Feature",
  "properties": {
    "date:inception_lower": "1983-07-01",
    "date:inception_upper": "1983-07-01",
    "iso:country": "GB",
    "wof:name": "WA14 3JN",
    "wof:placetype": "postalcode"
  },
  "geometry": {"coordinates":[-2.37309,53.37853],"type":"Point"}
}
