{
  "type": "Feature",
  "properties": {
    "iso:country":"GB",
    "wof:name":"WA14 3JN",
    "wof:placetype":"postalcode"
},
  "geometry": {"coordinates":[-2.37309049456078,53.37853041075282],"type":"Point"}
}