{
  "type": "Feature",
  "properties": {
    "iso:country":"GB",
    "wof:name":"BS7 9QJ",
    "wof:placetype":"postalcode"
},
  "geometry": {"coordinates":[-2.58388099321569,51.48555449690476],"type":"Point"}
}