{
  "type": "Feature",
  "properties": {
    "iso:country":"GB",
    "wof:name":"BS3 5JZ",
    "wof:placetype":"postalcode"
},
  "geometry": {"coordinates":[-2.59588881933539,51.43337856005444],"type":"Point"}
}