{
  "type": "Feature",
  "properties": {
    "iso:country": "GB",
    "wof:name": "BS3 5JZ",
    "wof:placetype": "postalcode"
  },
  "geometry": {"coordinates":[-2.595889,51.433379],"type":"Point"}
}
