{
  "type": "Feature",
  "properties": {
    "iso:country":"GB",
    "wof:name":"B29 4PL",
    "wof:placetype":"postalcode"
},
  "geometry": {"coordinates":[-1.95492326076677,52.42856693609234],"type":"Point"}
}