{
  "type": "Feature",
  "properties": {
    "iso:country":"GB",
    "wof:name":"HU12 9PP",
    "wof:placetype":"postalcode"
},
  "geometry": {"coordinates":[-0.16877931895188,53.71920157824354],"type":"Point"}
}