{
  "type": "Feature",
  "properties": {
    "date:inception_lower": "1980-01-01",
    "date:inception_upper": "1980-01-01",
    "iso:country": "GB",
    "wof:name": "NG17 7JT",
    "wof:placetype": "postalcode"
  },
  "geometry": {"coordinates":[-1.243169,53.107756],"type":"Point"}
}
