{
  "type": "Feature",
  "properties": {
    "iso:country": "GB",
    "wof:name": "EX15 2BU",
    "wof:placetype": "postalcode"
  },
  "geometry": {"coordinates":[-3.347368,50.851688],"type":"Point"}
}
