{
  "type": "Feature",
  "properties": {
    "iso:country":"GB",
    "wof:name":"EX15 2BU",
    "wof:placetype":"postalcode"
},
  "geometry": {"coordinates":[-3.34736770403361,50.85167883916655],"type":"Point"}
}