{
  "type": "Feature",
  "properties": {
    "date:inception_lower": "1980-01-01",
    "date:inception_upper": "1980-01-01",
    "iso:country": "GB",
    "wof:name": "PR4 5JT",
    "wof:placetype": "postalcode"
  },
  "geometry": {"coordinates":[-2.795717,53.707113],"type":"Point"}
}
