{
  "type": "Feature",
  "properties": {
    "iso:country":"GB",
    "wof:name":"PR4 5JT",
    "wof:placetype":"postalcode"
},
  "geometry": {"coordinates":[-2.79519492768459,53.70742419046613],"type":"Point"}
}