{
  "type": "Feature",
  "properties": {
    "date:inception_lower": "1980-01-01",
    "date:inception_upper": "1980-01-01",
    "iso:country": "GB",
    "wof:name": "SN15 2DP",
    "wof:placetype": "postalcode"
  },
  "geometry": {"coordinates":[-2.030013,51.385329],"type":"Point"}
}
