{
  "type": "Feature",
  "properties": {
    "iso:country":"GB",
    "wof:name":"SN15 2DP",
    "wof:placetype":"postalcode"
},
  "geometry": {"coordinates":[-2.03001319700891,51.38532868743497],"type":"Point"}
}