{
  "type": "Feature",
  "properties": {
    "iso:country": "GB",
    "wof:name": "LN13 9DP",
    "wof:placetype": "postalcode"
  },
  "geometry": {"coordinates":[0.179251,53.262646],"type":"Point"}
}
