{
  "type": "Feature",
  "properties": {
    "iso:country":"GB",
    "wof:name":"TW4 7RW",
    "wof:placetype":"postalcode"
},
  "geometry": {"coordinates":[-0.38640709210492,51.47531783508636],"type":"Point"}
}