{
  "type": "Feature",
  "properties": {
    "iso:country": "GB",
    "wof:name": "LL23 7GA",
    "wof:placetype": "postalcode"
  },
  "geometry": {"coordinates":[-3.593522,52.908909],"type":"Point"}
}
