{
  "type": "Feature",
  "properties": {
    "iso:country":"GB",
    "wof:name":"LL23 7GA",
    "wof:placetype":"postalcode"
},
  "geometry": {"coordinates":[-3.59352199293665,52.90890901266378],"type":"Point"}
}