{
  "type": "Feature",
  "properties": {
    "date:inception_lower":"1993-01-01",
    "date:inception_upper":"1993-01-31",
    "iso:country":"GB",
    "wof:name":"LL23 7GA",
    "wof:placetype":"postalcode"
},
  "geometry": {"coordinates":[-3.593522,52.908909],"type":"Point"}
}