{
  "type": "Feature",
  "properties": {
    "date:inception_lower": "1980-01-01",
    "date:inception_upper": "1980-01-01",
    "iso:country": "GB",
    "wof:name": "G22 5QJ",
    "wof:placetype": "postalcode"
  },
  "geometry": {"coordinates":[-4.255064,55.883586],"type":"Point"}
}
