{
  "type": "Feature",
  "properties": {
    "iso:country": "GB",
    "wof:name": "TW20 0NE",
    "wof:placetype": "postalcode"
  },
  "geometry": {"coordinates":[-0.578203,51.42685],"type":"Point"}
}
