{
  "type": "Feature",
  "properties": {
    "iso:country":"GB",
    "wof:name":"TW20 0NE",
    "wof:placetype":"postalcode"
},
  "geometry": {"coordinates":[-0.57820284384847,51.42685047950904],"type":"Point"}
}