{
  "type": "Feature",
  "properties": {
    "iso:country":"GB",
    "wof:name":"NG2 5FP",
    "wof:placetype":"postalcode"
},
  "geometry": {"coordinates":[-1.13446308902068,52.93800604123378],"type":"Point"}
}