{
  "type": "Feature",
  "properties": {
    "iso:country":"GB",
    "wof:name":"KA20 3AP",
    "wof:placetype":"postalcode"
},
  "geometry": {"coordinates":[-4.74771603388978,55.64098920218946],"type":"Point"}
}