{
  "type": "Feature",
  "properties": {
    "iso:country": "GB",
    "wof:name": "KA20 3AP",
    "wof:placetype": "postalcode"
  },
  "geometry": {"coordinates":[-4.747716,55.640989],"type":"Point"}
}
