{
  "type": "Feature",
  "properties": {
    "iso:country":"GB",
    "wof:name":"PL32 9SU",
    "wof:placetype":"postalcode"
},
  "geometry": {"coordinates":[-4.62744621514453,50.69683842183882],"type":"Point"}
}