{
  "type": "Feature",
  "properties": {
    "iso:country": "GB",
    "wof:name": "N17 9XL",
    "wof:placetype": "postalcode"
  },
  "geometry": {"coordinates":[-0.060618,51.598922],"type":"Point"}
}
