{
  "type": "Feature",
  "properties": {
    "iso:country":"GB",
    "wof:name":"N17 9XL",
    "wof:placetype":"postalcode"
},
  "geometry": {"coordinates":[-0.06061758549518,51.59892167674589],"type":"Point"}
}