{
  "type": "Feature",
  "properties": {
    "date:inception_lower":"1980-01-01",
    "date:inception_upper":"1980-01-31",
    "iso:country":"GB",
    "wof:name":"HG1 5JP",
    "wof:placetype":"postalcode"
},
  "geometry": {"coordinates":[-1.542158,53.995538],"type":"Point"}
}