{
  "type": "Feature",
  "properties": {
    "iso:country": "GB",
    "wof:name": "HG1 5JP",
    "wof:placetype": "postalcode"
  },
  "geometry": {"coordinates":[-1.542158,53.995538],"type":"Point"}
}
