{
  "type": "Feature",
  "properties": {
    "iso:country":"GB",
    "wof:name":"DE7 8JY",
    "wof:placetype":"postalcode"
},
  "geometry": {"coordinates":[-1.31289587922528,52.98508012453447],"type":"Point"}
}