{
  "type": "Feature",
  "properties": {
    "date:inception_lower": "1980-01-01",
    "date:inception_upper": "1980-01-01",
    "iso:country": "GB",
    "wof:name": "CF36 3LN",
    "wof:placetype": "postalcode"
  },
  "geometry": {"coordinates":[-3.710752,51.482647],"type":"Point"}
}
