{
  "type": "Feature",
  "properties": {
    "iso:country":"GB",
    "wof:name":"NE28 8JR",
    "wof:placetype":"postalcode"
},
  "geometry": {"coordinates":[-1.53491565960752,54.99134290475298],"type":"Point"}
}