{
  "type": "Feature",
  "properties": {
    "date:inception_lower": "1980-01-01",
    "date:inception_upper": "1980-01-01",
    "iso:country": "GB",
    "wof:name": "AL3 8LT",
    "wof:placetype": "postalcode"
  },
  "geometry": {"coordinates":[-0.446754,51.829931],"type":"Point"}
}
