{
  "type": "Feature",
  "properties": {
    "iso:country":"GB",
    "wof:name":"KT23 4BD",
    "wof:placetype":"postalcode"
},
  "geometry": {"coordinates":[-0.36837446309382,51.28104713530216],"type":"Point"}
}