{
  "type": "Feature",
  "properties": {
    "iso:country": "GB",
    "wof:name": "CT20 1AX",
    "wof:placetype": "postalcode"
  },
  "geometry": {"coordinates":[1.188278,51.084362],"type":"Point"}
}
