{
  "type": "Feature",
  "properties": {
    "iso:country": "GB",
    "wof:name": "CT20 1AX",
    "wof:placetype": "postalcode"
  },
  "geometry": {"coordinates":[1.188295,51.084358],"type":"Point"}
}
