{
  "type": "Feature",
  "properties": {
    "date:inception_lower": "2022-11-01",
    "date:inception_upper": "2022-11-01",
    "iso:country": "GB",
    "wof:name": "ME15 0BZ",
    "wof:placetype": "postalcode"
  },
  "geometry": {"coordinates":[0.476719,51.216849],"type":"Point"}
}
