{
  "type": "Feature",
  "properties": {
    "iso:country":"GB",
    "wof:name":"EH42 1YD",
    "wof:placetype":"postalcode"
},
  "geometry": {"coordinates":[-2.50533630651706,55.99511772846888],"type":"Point"}
}