{
  "type": "Feature",
  "properties": {
    "iso:country":"GB",
    "wof:name":"CM9 6DS",
    "wof:placetype":"postalcode"
},
  "geometry": {"coordinates":[0.68242600333797,51.72249067519668],"type":"Point"}
}