{
  "type": "Feature",
  "properties": {
    "iso:country":"GB",
    "wof:name":"YO61 1EG",
    "wof:placetype":"postalcode"
},
  "geometry": {"coordinates":[-1.07553577154149,54.08386830260033],"type":"Point"}
}