{
  "type": "Feature",
  "properties": {
    "date:inception_lower": "1998-06-01",
    "date:inception_upper": "1998-06-01",
    "iso:country": "GB",
    "wof:name": "YO61 1EG",
    "wof:placetype": "postalcode"
  },
  "geometry": {"coordinates":[-1.070641,54.081735],"type":"Point"}
}
