{
  "type": "Feature",
  "properties": {
    "iso:country":"GB",
    "wof:name":"DY9 0NH",
    "wof:placetype":"postalcode"
},
  "geometry": {"coordinates":[-2.1441028437506,52.4207828346757],"type":"Point"}
}