{
  "type": "Feature",
  "properties": {
    "iso:country": "GB",
    "wof:name": "LA12 9SY",
    "wof:placetype": "postalcode"
  },
  "geometry": {"coordinates":[-3.080513,54.194877],"type":"Point"}
}
