{
  "type": "Feature",
  "properties": {
    "date:inception_lower": "2005-02-01",
    "date:inception_upper": "2005-02-01",
    "iso:country": "GB",
    "wof:name": "LA12 9SY",
    "wof:placetype": "postalcode"
  },
  "geometry": {"coordinates":[-3.080513,54.194877],"type":"Point"}
}
