{
  "type": "Feature",
  "properties": {
    "date:inception_lower":"2013-11-01",
    "date:inception_upper":"2013-11-30",
    "iso:country":"GB",
    "wof:name":"NG1 5NT",
    "wof:placetype":"postalcode"
},
  "geometry": {"coordinates":[-1.15629,52.955666],"type":"Point"}
}