{
  "type": "Feature",
  "properties": {
    "iso:country":"GB",
    "wof:name":"NG1 5NT",
    "wof:placetype":"postalcode"
},
  "geometry": {"coordinates":[-1.15629016237082,52.95566554163684],"type":"Point"}
}