{
  "type": "Feature",
  "properties": {
    "date:inception_lower": "1980-01-01",
    "date:inception_upper": "1980-01-01",
    "iso:country": "GB",
    "wof:name": "E13 8BB",
    "wof:placetype": "postalcode"
  },
  "geometry": {"coordinates":[0.0216,51.527671],"type":"Point"}
}
