{
  "type": "Feature",
  "properties": {
    "iso:country":"GB",
    "wof:name":"E13 8BB",
    "wof:placetype":"postalcode"
},
  "geometry": {"coordinates":[0.02159974061798,51.52767050755961],"type":"Point"}
}