{
  "type": "Feature",
  "properties": {
    "iso:country":"GB",
    "wof:name":"SL4 3EL",
    "wof:placetype":"postalcode"
},
  "geometry": {"coordinates":[-0.61255292408884,51.47525302684677],"type":"Point"}
}