{
  "type": "Feature",
  "properties": {
    "iso:country":"GB",
    "wof:name":"OX1 5LR",
    "wof:placetype":"postalcode"
},
  "geometry": {"coordinates":[-1.24739912412057,51.71745764385474],"type":"Point"}
}