{
  "type": "Feature",
  "properties": {
    "date:inception_lower": "1980-01-01",
    "date:inception_upper": "1980-01-01",
    "iso:country": "GB",
    "wof:name": "OX1 5LR",
    "wof:placetype": "postalcode"
  },
  "geometry": {"coordinates":[-1.247399,51.717458],"type":"Point"}
}
