{
  "type": "Feature",
  "properties": {
    "iso:country":"GB",
    "wof:name":"OL15 8RL",
    "wof:placetype":"postalcode"
},
  "geometry": {"coordinates":[-2.11146065823811,53.64459701265984],"type":"Point"}
}