{
  "type": "Feature",
  "properties": {
    "iso:country":"GB",
    "wof:name":"DE7 8FW",
    "wof:placetype":"postalcode"
},
  "geometry": {"coordinates":[-1.30807526986121,52.97540658085271],"type":"Point"}
}