{
  "type": "Feature",
  "properties": {
    "iso:country": "GB",
    "wof:name": "DE7 8FW",
    "wof:placetype": "postalcode"
  },
  "geometry": {"coordinates":[-1.308075,52.975407],"type":"Point"}
}
