{
  "type": "Feature",
  "properties": {
    "iso:country":"GB",
    "wof:name":"E14 9RP",
    "wof:placetype":"postalcode"
},
  "geometry": {"coordinates":[-0.01747311239527,51.49639552294033],"type":"Point"}
}