{
  "type": "Feature",
  "properties": {
    "date:inception_lower": "1992-08-01",
    "date:inception_upper": "1992-08-01",
    "iso:country": "GB",
    "wof:name": "E14 9RP",
    "wof:placetype": "postalcode"
  },
  "geometry": {"coordinates":[-0.017619,51.49639],"type":"Point"}
}
