{
  "type": "Feature",
  "properties": {
    "date:inception_lower": "1980-01-01",
    "date:inception_upper": "1980-01-01",
    "iso:country": "GB",
    "wof:name": "DT2 9PD",
    "wof:placetype": "postalcode"
  },
  "geometry": {"coordinates":[-2.523588,50.795282],"type":"Point"}
}
