{
  "type": "Feature",
  "properties": {
    "iso:country":"GB",
    "wof:name":"DT2 9PD",
    "wof:placetype":"postalcode"
},
  "geometry": {"coordinates":[-2.52358771249488,50.79529104880034],"type":"Point"}
}