{
  "type": "Feature",
  "properties": {
    "iso:country":"GB",
    "wof:name":"RH6 7HU",
    "wof:placetype":"postalcode"
},
  "geometry": {"coordinates":[-0.16824732452361,51.17602688951564],"type":"Point"}
}