{
  "type": "Feature",
  "properties": {
    "iso:country":"GB",
    "wof:name":"RG10 8DA",
    "wof:placetype":"postalcode"
},
  "geometry": {"coordinates":[-0.86979821215937,51.50244499430983],"type":"Point"}
}