{
  "type": "Feature",
  "properties": {
    "iso:country":"GB",
    "wof:name":"NW10 8NY",
    "wof:placetype":"postalcode"
},
  "geometry": {"coordinates":[-0.25871101287552,51.53766078275142],"type":"Point"}
}