{
  "type": "Feature",
  "properties": {
    "iso:country": "GB",
    "wof:name": "NW10 8NY",
    "wof:placetype": "postalcode"
  },
  "geometry": {"coordinates":[-0.258711,51.537661],"type":"Point"}
}
