{
  "type": "Feature",
  "properties": {
    "date:inception_lower": "1980-01-01",
    "date:inception_upper": "1980-01-01",
    "iso:country": "GB",
    "wof:name": "WF12 7PP",
    "wof:placetype": "postalcode"
  },
  "geometry": {"coordinates":[-1.621212,53.701653],"type":"Point"}
}
