{
  "type": "Feature",
  "properties": {
    "iso:country":"GB",
    "wof:name":"BH17 9ES",
    "wof:placetype":"postalcode"
},
  "geometry": {"coordinates":[-1.9693430058023,50.75263335936553],"type":"Point"}
}