{
  "type": "Feature",
  "properties": {
    "iso:country":"GB",
    "wof:name":"IV2 5GY",
    "wof:placetype":"postalcode"
},
  "geometry": {"coordinates":[-4.15542598232739,57.47208098322284],"type":"Point"}
}