{
  "type": "Feature",
  "properties": {
    "iso:country": "GB",
    "wof:name": "DD1 2NL",
    "wof:placetype": "postalcode"
  },
  "geometry": {"coordinates":[-2.965121,56.467403],"type":"Point"}
}
