{
  "type": "Feature",
  "properties": {
    "iso:country":"GB",
    "wof:name":"N15 4DP",
    "wof:placetype":"postalcode"
},
  "geometry": {"coordinates":[-0.06637185270231,51.58480849234001],"type":"Point"}
}