{
  "type": "Feature",
  "properties": {
    "date:inception_lower":"2002-07-01",
    "date:inception_upper":"2002-07-31",
    "iso:country":"GB",
    "wof:name":"GL52 2LY",
    "wof:placetype":"postalcode"
},
  "geometry": {"coordinates":[-2.072783,51.900751],"type":"Point"}
}