{
  "type": "Feature",
  "properties": {
    "iso:country":"GB",
    "wof:name":"HP13 5JN",
    "wof:placetype":"postalcode"
},
  "geometry": {"coordinates":[-0.78230823085678,51.64259706144457],"type":"Point"}
}