{
  "type": "Feature",
  "properties": {
    "iso:country": "GB",
    "wof:name": "HP13 5JN",
    "wof:placetype": "postalcode"
  },
  "geometry": {"coordinates":[-0.782308,51.642597],"type":"Point"}
}
