{
  "type": "Feature",
  "properties": {
    "date:inception_lower":"1980-01-01",
    "date:inception_upper":"1980-01-31",
    "iso:country":"GB",
    "wof:name":"DH7 8AL",
    "wof:placetype":"postalcode"
},
  "geometry": {"coordinates":[-1.636347,54.748902],"type":"Point"}
}