{
  "type": "Feature",
  "properties": {
    "iso:country":"GB",
    "wof:name":"DH7 8AL",
    "wof:placetype":"postalcode"
},
  "geometry": {"coordinates":[-1.63634694977975,54.74890236459867],"type":"Point"}
}