{
  "type": "Feature",
  "properties": {
    "iso:country": "GB",
    "wof:name": "DH7 8AL",
    "wof:placetype": "postalcode"
  },
  "geometry": {"coordinates":[-1.636347,54.748902],"type":"Point"}
}
