{
  "type": "Feature",
  "properties": {
    "iso:country": "GB",
    "wof:name": "PE28 2SJ",
    "wof:placetype": "postalcode"
  },
  "geometry": {"coordinates":[-0.073497,52.403047],"type":"Point"}
}
