{
  "type": "Feature",
  "properties": {
    "iso:country":"GB",
    "wof:name":"PE28 2SJ",
    "wof:placetype":"postalcode"
},
  "geometry": {"coordinates":[-0.07349694760677,52.40304723400668],"type":"Point"}
}