{
  "type": "Feature",
  "properties": {
    "iso:country":"GB",
    "wof:name":"B72 1YF",
    "wof:placetype":"postalcode"
},
  "geometry": {"coordinates":[-1.81709833625945,52.53668257187046],"type":"Point"}
}