{
  "type": "Feature",
  "properties": {
    "date:inception_lower": "1981-06-01",
    "date:inception_upper": "1981-06-01",
    "iso:country": "GB",
    "wof:name": "B72 1YF",
    "wof:placetype": "postalcode"
  },
  "geometry": {"coordinates":[-1.817098,52.536683],"type":"Point"}
}
