{
  "type": "Feature",
  "properties": {
    "iso:country": "GB",
    "wof:name": "B72 1YF",
    "wof:placetype": "postalcode"
  },
  "geometry": {"coordinates":[-1.817098,52.536683],"type":"Point"}
}
