{
  "type": "Feature",
  "properties": {
    "iso:country":"GB",
    "wof:name":"GU5 0UE",
    "wof:placetype":"postalcode"
},
  "geometry": {"coordinates":[-0.52529726710753,51.18201687551201],"type":"Point"}
}