{
  "type": "Feature",
  "properties": {
    "iso:country": "GB",
    "wof:name": "PR9 7LN",
    "wof:placetype": "postalcode"
  },
  "geometry": {"coordinates":[-2.965483,53.661408],"type":"Point"}
}
