{
  "type": "Feature",
  "properties": {
    "iso:country":"GB",
    "wof:name":"AB21 9HJ",
    "wof:placetype":"postalcode"
},
  "geometry": {"coordinates":[-2.18135412035529,57.18665674865893],"type":"Point"}
}