{
  "type": "Feature",
  "properties": {
    "iso:country":"GB",
    "wof:name":"DE55 5JJ",
    "wof:placetype":"postalcode"
},
  "geometry": {"coordinates":[-1.35613851842305,53.12119442851553],"type":"Point"}
}