{
  "type": "Feature",
  "properties": {
    "iso:country": "GB",
    "wof:name": "LS14 6GY",
    "wof:placetype": "postalcode"
  },
  "geometry": {"coordinates":[-1.474117,53.803762],"type":"Point"}
}
