{
  "type": "Feature",
  "properties": {
    "iso:country":"GB",
    "wof:name":"M41 7FZ",
    "wof:placetype":"postalcode"
},
  "geometry": {"coordinates":[-2.34342374431117,53.45963352391875],"type":"Point"}
}