{
  "type": "Feature",
  "properties": {
    "date:inception_lower": "2000-06-01",
    "date:inception_upper": "2000-06-01",
    "iso:country": "GB",
    "wof:name": "M41 7FZ",
    "wof:placetype": "postalcode"
  },
  "geometry": {"coordinates":[-2.343424,53.459634],"type":"Point"}
}
