{
  "type": "Feature",
  "properties": {
    "iso:country": "GB",
    "wof:name": "M29 8SP",
    "wof:placetype": "postalcode"
  },
  "geometry": {"coordinates":[-2.436339,53.510141],"type":"Point"}
}
