{
  "type": "Feature",
  "properties": {
    "iso:country":"GB",
    "wof:name":"ST8 6SA",
    "wof:placetype":"postalcode"
},
  "geometry": {"coordinates":[-2.18500150913009,53.10659156991369],"type":"Point"}
}