{
  "type": "Feature",
  "properties": {
    "date:inception_lower": "1980-01-01",
    "date:inception_upper": "1980-01-01",
    "iso:country": "GB",
    "wof:name": "ST8 6SA",
    "wof:placetype": "postalcode"
  },
  "geometry": {"coordinates":[-2.185001,53.106592],"type":"Point"}
}
