{
  "type": "Feature",
  "properties": {
    "iso:country":"GB",
    "wof:name":"KA4 8AA",
    "wof:placetype":"postalcode"
},
  "geometry": {"coordinates":[-4.38146407131747,55.60094942633453],"type":"Point"}
}