{
  "type": "Feature",
  "properties": {
    "date:inception_lower":"1980-01-01",
    "date:inception_upper":"1980-01-31",
    "iso:country":"GB",
    "wof:name":"KA4 8AA",
    "wof:placetype":"postalcode"
},
  "geometry": {"coordinates":[-4.381665,55.601133],"type":"Point"}
}