{
  "type": "Feature",
  "properties": {
    "iso:country":"GB",
    "wof:name":"PL1 1HX",
    "wof:placetype":"postalcode"
},
  "geometry": {"coordinates":[-4.14291938556632,50.37204960288631],"type":"Point"}
}