{
  "type": "Feature",
  "properties": {
    "iso:country":"GB",
    "wof:name":"DN5 0LH",
    "wof:placetype":"postalcode"
},
  "geometry": {"coordinates":[-1.15165344588352,53.56755287633551],"type":"Point"}
}