{
  "type": "Feature",
  "properties": {
    "iso:country":"GB",
    "wof:name":"SW16 5AP",
    "wof:placetype":"postalcode"
},
  "geometry": {"coordinates":[-0.14230021275401,51.41753312194247],"type":"Point"}
}