{
  "type": "Feature",
  "properties": {
    "iso:country": "GB",
    "wof:name": "SW16 5AP",
    "wof:placetype": "postalcode"
  },
  "geometry": {"coordinates":[-0.1423,51.417533],"type":"Point"}
}
