{
  "type": "Feature",
  "properties": {
    "iso:country": "GB",
    "wof:name": "KT13 9DS",
    "wof:placetype": "postalcode"
  },
  "geometry": {"coordinates":[-0.446995,51.368111],"type":"Point"}
}
