{
  "type": "Feature",
  "properties": {
    "iso:country":"GB",
    "wof:name":"NE62 5QX",
    "wof:placetype":"postalcode"
},
  "geometry": {"coordinates":[-1.59946090396542,55.15946001901012],"type":"Point"}
}