{
  "type": "Feature",
  "properties": {
    "iso:country":"GB",
    "wof:name":"NE63 9UZ",
    "wof:placetype":"postalcode"
},
  "geometry": {"coordinates":[-1.57114158845339,55.18344620305101],"type":"Point"}
}