{
  "type": "Feature",
  "properties": {
    "iso:country": "GB",
    "wof:name": "NE63 9UZ",
    "wof:placetype": "postalcode"
  },
  "geometry": {"coordinates":[-1.571142,55.183446],"type":"Point"}
}
