{
  "type": "Feature",
  "properties": {
    "iso:country": "GB",
    "wof:name": "PE28 9BT",
    "wof:placetype": "postalcode"
  },
  "geometry": {"coordinates":[-0.10904,52.314532],"type":"Point"}
}
