{
  "type": "Feature",
  "properties": {
    "iso:country":"GB",
    "wof:name":"PE28 9BT",
    "wof:placetype":"postalcode"
},
  "geometry": {"coordinates":[-0.10911464882483,52.31433793490727],"type":"Point"}
}