{
  "type": "Feature",
  "properties": {
    "iso:country":"GB",
    "wof:name":"HA8 9PQ",
    "wof:placetype":"postalcode"
},
  "geometry": {"coordinates":[-0.26356620251669,51.61539908072376],"type":"Point"}
}