{
  "type": "Feature",
  "properties": {
    "iso:country":"GB",
    "wof:name":"HP5 2LW",
    "wof:placetype":"postalcode"
},
  "geometry": {"coordinates":[-0.61841605319001,51.72355276231091],"type":"Point"}
}