{
  "type": "Feature",
  "properties": {
    "iso:country": "GB",
    "wof:name": "HP5 2LW",
    "wof:placetype": "postalcode"
  },
  "geometry": {"coordinates":[-0.618416,51.723553],"type":"Point"}
}
