{
  "type": "Feature",
  "properties": {
    "iso:country":"GB",
    "wof:name":"NE34 6JX",
    "wof:placetype":"postalcode"
},
  "geometry": {"coordinates":[-1.40184902941472,54.98191916361925],"type":"Point"}
}