{
  "type": "Feature",
  "properties": {
    "date:inception_lower":"1980-01-01",
    "date:inception_upper":"1980-01-31",
    "iso:country":"GB",
    "wof:name":"DT7 3EQ",
    "wof:placetype":"postalcode"
},
  "geometry": {"coordinates":[-2.944355,50.723587],"type":"Point"}
}