{
  "type": "Feature",
  "properties": {
    "iso:country":"GB",
    "wof:name":"DT7 3EQ",
    "wof:placetype":"postalcode"
},
  "geometry": {"coordinates":[-2.94435514667825,50.72358658451366],"type":"Point"}
}