{
  "type": "Feature",
  "properties": {
    "date:inception_lower": "2022-10-01",
    "date:inception_upper": "2022-10-01",
    "iso:country": "GB",
    "wof:name": "PH11 8FH",
    "wof:placetype": "postalcode"
  },
  "geometry": {"coordinates":[-3.213676,56.625677],"type":"Point"}
}
