{
  "type": "Feature",
  "properties": {
    "iso:country": "GB",
    "wof:name": "CF32 9HH",
    "wof:placetype": "postalcode"
  },
  "geometry": {"coordinates":[-3.586161,51.550689],"type":"Point"}
}
