{
  "type": "Feature",
  "properties": {
    "iso:country":"GB",
    "wof:name":"HA1 4EG",
    "wof:placetype":"postalcode"
},
  "geometry": {"coordinates":[-0.35082197004829,51.57875531465643],"type":"Point"}
}