{
  "type": "Feature",
  "properties": {
    "iso:country": "GB",
    "wof:name": "HA1 4EG",
    "wof:placetype": "postalcode"
  },
  "geometry": {"coordinates":[-0.350822,51.578755],"type":"Point"}
}
