{
  "type": "Feature",
  "properties": {
    "iso:country":"GB",
    "wof:name":"PA11 3LJ",
    "wof:placetype":"postalcode"
},
  "geometry": {"coordinates":[-4.57279395741677,55.85624449138736],"type":"Point"}
}