{
  "type": "Feature",
  "properties": {
    "date:inception_lower":"1980-01-01",
    "date:inception_upper":"1980-01-31",
    "iso:country":"GB",
    "wof:name":"L31 2NF",
    "wof:placetype":"postalcode"
},
  "geometry": {"coordinates":[-2.940326,53.52234],"type":"Point"}
}