{
  "type": "Feature",
  "properties": {
    "iso:country": "GB",
    "wof:name": "L31 2NF",
    "wof:placetype": "postalcode"
  },
  "geometry": {"coordinates":[-2.940326,53.52234],"type":"Point"}
}
