{
  "type": "Feature",
  "properties": {
    "iso:country":"GB",
    "wof:name":"L31 2NF",
    "wof:placetype":"postalcode"
},
  "geometry": {"coordinates":[-2.94032652201236,53.52234026324886],"type":"Point"}
}