{
  "type": "Feature",
  "properties": {
    "iso:country":"GB",
    "wof:name":"KA26 0JQ",
    "wof:placetype":"postalcode"
},
  "geometry": {"coordinates":[-4.97008243867936,55.15221235370663],"type":"Point"}
}