{
  "type": "Feature",
  "properties": {
    "date:inception_lower": "1997-12-01",
    "date:inception_upper": "1997-12-01",
    "iso:country": "GB",
    "wof:name": "BH8 0PX",
    "wof:placetype": "postalcode"
  },
  "geometry": {"coordinates":[-1.846283,50.761979],"type":"Point"}
}
