{
  "type": "Feature",
  "properties": {
    "iso:country": "GB",
    "wof:name": "LA13 0UB",
    "wof:placetype": "postalcode"
  },
  "geometry": {"coordinates":[-3.180886,54.119271],"type":"Point"}
}
