{
  "type": "Feature",
  "properties": {
    "date:inception_lower":"1990-07-01",
    "date:inception_upper":"1990-07-31",
    "iso:country":"GB",
    "wof:name":"LA13 0UB",
    "wof:placetype":"postalcode"
},
  "geometry": {"coordinates":[-3.180886,54.119271],"type":"Point"}
}