{
  "type": "Feature",
  "properties": {
    "iso:country":"GB",
    "wof:name":"TQ9 7TH",
    "wof:placetype":"postalcode"
},
  "geometry": {"coordinates":[-3.70949997128871,50.39388162476239],"type":"Point"}
}