{
  "type": "Feature",
  "properties": {
    "iso:country": "GB",
    "wof:name": "CO10 1AR",
    "wof:placetype": "postalcode"
  },
  "geometry": {"coordinates":[0.718305,52.050573],"type":"Point"}
}
