{
  "type": "Feature",
  "properties": {
    "date:inception_lower": "2019-12-01",
    "date:inception_upper": "2019-12-01",
    "iso:country": "GB",
    "wof:name": "CO10 1AR",
    "wof:placetype": "postalcode"
  },
  "geometry": {"coordinates":[0.718305,52.050573],"type":"Point"}
}
