{
  "type": "Feature",
  "properties": {
    "iso:country":"GB",
    "wof:name":"SE15 6TW",
    "wof:placetype":"postalcode"
},
  "geometry": {"coordinates":[-0.06555840139992,51.48290032125479],"type":"Point"}
}