{
  "type": "Feature",
  "properties": {
    "iso:country":"GB",
    "wof:name":"PR5 6ZE",
    "wof:placetype":"postalcode"
},
  "geometry": {"coordinates":[-2.65060997778782,53.73405721765817],"type":"Point"}
}