{
  "type": "Feature",
  "properties": {
    "iso:country": "GB",
    "wof:name": "PR5 6ZE",
    "wof:placetype": "postalcode"
  },
  "geometry": {"coordinates":[-2.65061,53.734057],"type":"Point"}
}
