{
  "type": "Feature",
  "properties": {
    "iso:country":"GB",
    "wof:name":"SS12 0PJ",
    "wof:placetype":"postalcode"
},
  "geometry": {"coordinates":[0.51153343938358,51.6033323318297],"type":"Point"}
}