{
  "type": "Feature",
  "properties": {
    "iso:country": "GB",
    "wof:name": "ST10 2QD",
    "wof:placetype": "postalcode"
  },
  "geometry": {"coordinates":[-1.969666,53.043863],"type":"Point"}
}
