{
  "type": "Feature",
  "properties": {
    "date:inception_lower":"1991-09-01",
    "date:inception_upper":"1991-09-30",
    "iso:country":"GB",
    "wof:name":"ST10 2QD",
    "wof:placetype":"postalcode"
},
  "geometry": {"coordinates":[-1.969666,53.043863],"type":"Point"}
}