{
  "type": "Feature",
  "properties": {
    "iso:country":"GB",
    "wof:name":"HA8 9AG",
    "wof:placetype":"postalcode"
},
  "geometry": {"coordinates":[-0.27272833004771,51.60957240198965],"type":"Point"}
}