{
  "type": "Feature",
  "properties": {
    "iso:country": "GB",
    "wof:name": "HA8 9AG",
    "wof:placetype": "postalcode"
  },
  "geometry": {"coordinates":[-0.272734,51.609557],"type":"Point"}
}
