{
  "type": "Feature",
  "properties": {
    "iso:country":"GB",
    "wof:name":"BS4 5AF",
    "wof:placetype":"postalcode"
},
  "geometry": {"coordinates":[-2.54966351998414,51.4329481207908],"type":"Point"}
}