{
  "type": "Feature",
  "properties": {
    "iso:country":"GB",
    "wof:name":"NR35 2AB",
    "wof:placetype":"postalcode"
},
  "geometry": {"coordinates":[1.40915666954885,52.45213897798445],"type":"Point"}
}