{
  "type": "Feature",
  "properties": {
    "iso:country": "GB",
    "wof:name": "S63 0PP",
    "wof:placetype": "postalcode"
  },
  "geometry": {"coordinates":[-1.315055,53.552007],"type":"Point"}
}
