{
  "type": "Feature",
  "properties": {
    "iso:country":"GB",
    "wof:name":"PE7 3LB",
    "wof:placetype":"postalcode"
},
  "geometry": {"coordinates":[-0.26084504303143,52.51232519821654],"type":"Point"}
}