{
  "type": "Feature",
  "properties": {
    "iso:country":"GB",
    "wof:name":"WF3 1LX",
    "wof:placetype":"postalcode"
},
  "geometry": {"coordinates":[-1.5854022045865,53.72464622273949],"type":"Point"}
}