{
  "type": "Feature",
  "properties": {
    "date:inception_lower": "1980-01-01",
    "date:inception_upper": "1980-01-01",
    "iso:country": "GB",
    "wof:name": "SW1W 9TR",
    "wof:placetype": "postalcode"
  },
  "geometry": {"coordinates":[-0.147829,51.493232],"type":"Point"}
}
