{
  "type": "Feature",
  "properties": {
    "iso:country":"GB",
    "wof:name":"MK42 9AY",
    "wof:placetype":"postalcode"
},
  "geometry": {"coordinates":[-0.47581347934178,52.12863113994518],"type":"Point"}
}