{
  "type": "Feature",
  "properties": {
    "iso:country": "GB",
    "wof:name": "MK42 9AY",
    "wof:placetype": "postalcode"
  },
  "geometry": {"coordinates":[-0.476201,52.128411],"type":"Point"}
}
