{
  "type": "Feature",
  "properties": {
    "date:inception_lower":"2015-11-01",
    "date:inception_upper":"2015-11-30",
    "iso:country":"GB",
    "wof:name":"MK42 9AY",
    "wof:placetype":"postalcode"
},
  "geometry": {"coordinates":[-0.476201,52.128411],"type":"Point"}
}