{
  "type": "Feature",
  "properties": {
    "iso:country":"GB",
    "wof:name":"PO17 5AH",
    "wof:placetype":"postalcode"
},
  "geometry": {"coordinates":[-1.18446622865735,50.9010357553473],"type":"Point"}
}