{
  "type": "Feature",
  "properties": {
    "iso:country": "GB",
    "wof:name": "TA7 8FQ",
    "wof:placetype": "postalcode"
  },
  "geometry": {"coordinates":[-2.97859,51.167452],"type":"Point"}
}
