{
  "type": "Feature",
  "properties": {
    "iso:country": "GB",
    "wof:name": "SG1 6BZ",
    "wof:placetype": "postalcode"
  },
  "geometry": {"coordinates":[-0.166991,51.929635],"type":"Point"}
}
