{
  "type": "Feature",
  "properties": {
    "iso:country":"GB",
    "wof:name":"SG1 6BZ",
    "wof:placetype":"postalcode"
},
  "geometry": {"coordinates":[-0.16705862228226,51.92963616201651],"type":"Point"}
}