{
  "type": "Feature",
  "properties": {
    "iso:country":"GB",
    "wof:name":"DL3 0PD",
    "wof:placetype":"postalcode"
},
  "geometry": {"coordinates":[-1.55225185384805,54.53882497897512],"type":"Point"}
}