{
  "type": "Feature",
  "properties": {
    "iso:country":"GB",
    "wof:name":"LS27 7AA",
    "wof:placetype":"postalcode"
},
  "geometry": {"coordinates":[-1.62911435727534,53.75867450983286],"type":"Point"}
}