{
  "type": "Feature",
  "properties": {
    "iso:country":"GB",
    "wof:name":"CO5 8BY",
    "wof:placetype":"postalcode"
},
  "geometry": {"coordinates":[0.93162073040274,51.77720637826179],"type":"Point"}
}