{
  "type": "Feature",
  "properties": {
    "iso:country":"GB",
    "wof:name":"WF9 5LB",
    "wof:placetype":"postalcode"
},
  "geometry": {"coordinates":[-1.37459263005002,53.62520214691394],"type":"Point"}
}