{
  "type": "Feature",
  "properties": {
    "date:inception_lower":"1980-01-01",
    "date:inception_upper":"1980-01-31",
    "iso:country":"GB",
    "wof:name":"SR6 0BA",
    "wof:placetype":"postalcode"
},
  "geometry": {"coordinates":[-1.377835,54.916009],"type":"Point"}
}