{
  "type": "Feature",
  "properties": {
    "iso:country": "GB",
    "wof:name": "SR6 0BA",
    "wof:placetype": "postalcode"
  },
  "geometry": {"coordinates":[-1.377835,54.916009],"type":"Point"}
}
