{
  "type": "Feature",
  "properties": {
    "iso:country": "GB",
    "wof:name": "B12 0HU",
    "wof:placetype": "postalcode"
  },
  "geometry": {"coordinates":[-1.880183,52.466336],"type":"Point"}
}
