{
  "type": "Feature",
  "properties": {
    "date:inception_lower":"1987-04-01",
    "date:inception_upper":"1987-04-30",
    "iso:country":"GB",
    "wof:name":"B12 0HU",
    "wof:placetype":"postalcode"
},
  "geometry": {"coordinates":[-1.880183,52.466336],"type":"Point"}
}