{
  "type": "Feature",
  "properties": {
    "iso:country":"GB",
    "wof:name":"YO60 6QT",
    "wof:placetype":"postalcode"
},
  "geometry": {"coordinates":[-1.00677284232192,54.08979175976137],"type":"Point"}
}