{
  "type": "Feature",
  "properties": {
    "date:inception_lower": "1995-07-01",
    "date:inception_upper": "1995-07-01",
    "iso:country": "GB",
    "wof:name": "FY3 7PR",
    "wof:placetype": "postalcode"
  },
  "geometry": {"coordinates":[-3.010838,53.835663],"type":"Point"}
}
