{
  "type": "Feature",
  "properties": {
    "iso:country":"GB",
    "wof:name":"CR0 5QP",
    "wof:placetype":"postalcode"
},
  "geometry": {"coordinates":[-0.07908636951065,51.37235969125354],"type":"Point"}
}