{
  "type": "Feature",
  "properties": {
    "iso:country":"GB",
    "wof:name":"LN5 0QN",
    "wof:placetype":"postalcode"
},
  "geometry": {"coordinates":[-0.58629708342486,53.0791236509609],"type":"Point"}
}