{
  "type": "Feature",
  "properties": {
    "date:inception_lower": "1980-01-01",
    "date:inception_upper": "1980-01-01",
    "iso:country": "GB",
    "wof:name": "LN5 0QN",
    "wof:placetype": "postalcode"
  },
  "geometry": {"coordinates":[-0.570549,53.076234],"type":"Point"}
}
