{
  "type": "Feature",
  "properties": {
    "date:inception_lower": "1980-01-01",
    "date:inception_upper": "1980-01-01",
    "iso:country": "GB",
    "wof:name": "LA10 5HE",
    "wof:placetype": "postalcode"
  },
  "geometry": {"coordinates":[-2.537596,54.325264],"type":"Point"}
}
