{
  "type": "Feature",
  "properties": {
    "iso:country":"GB",
    "wof:name":"LA10 5HE",
    "wof:placetype":"postalcode"
},
  "geometry": {"coordinates":[-2.53759623825639,54.32526423863835],"type":"Point"}
}