{
  "type": "Feature",
  "properties": {
    "iso:country":"GB",
    "wof:name":"ME8 9BX",
    "wof:placetype":"postalcode"
},
  "geometry": {"coordinates":[0.60264981411005,51.35828636385278],"type":"Point"}
}