{
  "type": "Feature",
  "properties": {
    "iso:country": "GB",
    "wof:name": "EX34 8EU",
    "wof:placetype": "postalcode"
  },
  "geometry": {"coordinates":[-4.123656,51.198475],"type":"Point"}
}
