{
  "type": "Feature",
  "properties": {
    "date:inception_lower": "2008-07-01",
    "date:inception_upper": "2008-07-01",
    "iso:country": "GB",
    "wof:name": "YO23 7BX",
    "wof:placetype": "postalcode"
  },
  "geometry": {"coordinates":[-1.159807,53.873314],"type":"Point"}
}
