{
  "type": "Feature",
  "properties": {
    "date:inception_lower":"1995-07-01",
    "date:inception_upper":"1995-07-31",
    "iso:country":"GB",
    "wof:name":"RG20 9PQ",
    "wof:placetype":"postalcode"
},
  "geometry": {"coordinates":[-1.37485,51.340875],"type":"Point"}
}