{
  "type": "Feature",
  "properties": {
    "iso:country":"GB",
    "wof:name":"NN16 8NY",
    "wof:placetype":"postalcode"
},
  "geometry": {"coordinates":[-0.71656488591377,52.40596041704867],"type":"Point"}
}