{
  "type": "Feature",
  "properties": {
    "date:inception_lower": "1980-01-01",
    "date:inception_upper": "1980-01-01",
    "iso:country": "GB",
    "wof:name": "NN16 8NY",
    "wof:placetype": "postalcode"
  },
  "geometry": {"coordinates":[-0.716565,52.40596],"type":"Point"}
}
