{
  "type": "Feature",
  "properties": {
    "iso:country":"GB",
    "wof:name":"SE6 3SD",
    "wof:placetype":"postalcode"
},
  "geometry": {"coordinates":[-0.02516572235047,51.4330547852483],"type":"Point"}
}