{
  "type": "Feature",
  "properties": {
    "iso:country":"GB",
    "wof:name":"LE7 9UG",
    "wof:placetype":"postalcode"
},
  "geometry": {"coordinates":[-1.04510530846426,52.63952500586371],"type":"Point"}
}