{
  "type": "Feature",
  "properties": {
    "iso:country":"GB",
    "wof:name":"NG21 0QT",
    "wof:placetype":"postalcode"
},
  "geometry": {"coordinates":[-1.12868376645786,53.09522482223572],"type":"Point"}
}