{
  "type": "Feature",
  "properties": {
    "date:inception_lower":"2005-01-01",
    "date:inception_upper":"2005-01-31",
    "iso:country":"GB",
    "wof:name":"NG21 0QT",
    "wof:placetype":"postalcode"
},
  "geometry": {"coordinates":[-1.128684,53.095225],"type":"Point"}
}