{
  "type": "Feature",
  "properties": {
    "date:inception_lower":"1980-01-01",
    "date:inception_upper":"1980-01-31",
    "iso:country":"GB",
    "wof:name":"W8 5RU",
    "wof:placetype":"postalcode"
},
  "geometry": {"coordinates":[-0.184327,51.49908],"type":"Point"}
}