{
  "type": "Feature",
  "properties": {
    "iso:country":"GB",
    "wof:name":"W8 5RU",
    "wof:placetype":"postalcode"
},
  "geometry": {"coordinates":[-0.18432675880838,51.49907957615338],"type":"Point"}
}