{
  "type": "Feature",
  "properties": {
    "iso:country":"GB",
    "wof:name":"DE45 1SE",
    "wof:placetype":"postalcode"
},
  "geometry": {"coordinates":[-1.6155836575278,53.24850090965258],"type":"Point"}
}