{
  "type": "Feature",
  "properties": {
    "date:inception_lower": "1992-08-01",
    "date:inception_upper": "1992-08-01",
    "iso:country": "GB",
    "wof:name": "DE45 1SE",
    "wof:placetype": "postalcode"
  },
  "geometry": {"coordinates":[-1.615584,53.248501],"type":"Point"}
}
