{
  "type": "Feature",
  "properties": {
    "date:inception_lower": "1990-07-01",
    "date:inception_upper": "1990-07-01",
    "iso:country": "GB",
    "wof:name": "WV1 1LY",
    "wof:placetype": "postalcode"
  },
  "geometry": {"coordinates":[-2.12807,52.588182],"type":"Point"}
}
