{
  "type": "Feature",
  "properties": {
    "iso:country":"GB",
    "wof:name":"WV1 1LY",
    "wof:placetype":"postalcode"
},
  "geometry": {"coordinates":[-2.12805976520556,52.58752851335312],"type":"Point"}
}