{
  "type": "Feature",
  "properties": {
    "date:inception_lower": "1991-01-01",
    "date:inception_upper": "1991-01-01",
    "iso:country": "GB",
    "wof:name": "AL4 0PJ",
    "wof:placetype": "postalcode"
  },
  "geometry": {"coordinates":[-0.244433,51.748405],"type":"Point"}
}
