{
  "type": "Feature",
  "properties": {
    "date:inception_lower": "1980-01-01",
    "date:inception_upper": "1980-01-01",
    "iso:country": "GB",
    "wof:name": "CO16 9RG",
    "wof:placetype": "postalcode"
  },
  "geometry": {"coordinates":[1.14335,51.822432],"type":"Point"}
}
