{
  "type": "Feature",
  "properties": {
    "iso:country":"GB",
    "wof:name":"OX14 1EP",
    "wof:placetype":"postalcode"
},
  "geometry": {"coordinates":[-1.28380787999642,51.6732499872428],"type":"Point"}
}