{
  "type": "Feature",
  "properties": {
    "iso:country":"GB",
    "wof:name":"CT5 3BS",
    "wof:placetype":"postalcode"
},
  "geometry": {"coordinates":[1.0541579711279,51.35094932117001],"type":"Point"}
}