{
  "type": "Feature",
  "properties": {
    "iso:country":"GB",
    "wof:name":"IP21 4NH",
    "wof:placetype":"postalcode"
},
  "geometry": {"coordinates":[1.17450394453762,52.38707786442763],"type":"Point"}
}