{
  "type": "Feature",
  "properties": {
    "date:inception_lower": "2006-01-01",
    "date:inception_upper": "2006-01-01",
    "iso:country": "GB",
    "wof:name": "NG6 8PB",
    "wof:placetype": "postalcode"
  },
  "geometry": {"coordinates":[-1.193722,52.991191],"type":"Point"}
}
