{
  "type": "Feature",
  "properties": {
    "iso:country":"GB",
    "wof:name":"NG6 8PB",
    "wof:placetype":"postalcode"
},
  "geometry": {"coordinates":[-1.19372160673793,52.99119087429839],"type":"Point"}
}