{
  "type": "Feature",
  "properties": {
    "iso:country": "GB",
    "wof:name": "NG6 8PB",
    "wof:placetype": "postalcode"
  },
  "geometry": {"coordinates":[-1.193722,52.991191],"type":"Point"}
}
