{
  "type": "Feature",
  "properties": {
    "iso:country":"GB",
    "wof:name":"TW8 0LJ",
    "wof:placetype":"postalcode"
},
  "geometry": {"coordinates":[-0.30150234378124,51.48860547656143],"type":"Point"}
}