{
  "type": "Feature",
  "properties": {
    "iso:country":"GB",
    "wof:name":"TN23 5TX",
    "wof:placetype":"postalcode"
},
  "geometry": {"coordinates":[0.84959968159863,51.13206927538071],"type":"Point"}
}