{
  "type": "Feature",
  "properties": {
    "date:inception_lower":"2010-11-01",
    "date:inception_upper":"2010-11-30",
    "iso:country":"GB",
    "wof:name":"TN23 5TX",
    "wof:placetype":"postalcode"
},
  "geometry": {"coordinates":[0.8496,51.132069],"type":"Point"}
}