{
  "type": "Feature",
  "properties": {
    "iso:country": "GB",
    "wof:name": "TN23 5TX",
    "wof:placetype": "postalcode"
  },
  "geometry": {"coordinates":[0.8496,51.132069],"type":"Point"}
}
