{
  "type": "Feature",
  "properties": {
    "date:inception_lower": "2015-09-01",
    "date:inception_upper": "2015-09-01",
    "iso:country": "GB",
    "wof:name": "OX12 7FA",
    "wof:placetype": "postalcode"
  },
  "geometry": {"coordinates":[-1.422652,51.609206],"type":"Point"}
}
