{
  "type": "Feature",
  "properties": {
    "iso:country":"GB",
    "wof:name":"N7 9AX",
    "wof:placetype":"postalcode"
},
  "geometry": {"coordinates":[-0.12510666561799,51.54202224901627],"type":"Point"}
}