{
  "type": "Feature",
  "properties": {
    "date:inception_lower": "1994-05-01",
    "date:inception_upper": "1994-05-01",
    "iso:country": "GB",
    "wof:name": "ME12 1RQ",
    "wof:placetype": "postalcode"
  },
  "geometry": {"coordinates":[0.752946,51.441964],"type":"Point"}
}
