{
  "type": "Feature",
  "properties": {
    "iso:country":"GB",
    "wof:name":"TQ5 8JL",
    "wof:placetype":"postalcode"
},
  "geometry": {"coordinates":[-3.51303814285928,50.39571342123543],"type":"Point"}
}