{
  "type": "Feature",
  "properties": {
    "iso:country":"GB",
    "wof:name":"G77 6UT",
    "wof:placetype":"postalcode"
},
  "geometry": {"coordinates":[-4.33773354327739,55.78146756063894],"type":"Point"}
}