{
  "type": "Feature",
  "properties": {
    "date:inception_lower": "1980-10-01",
    "date:inception_upper": "1980-10-01",
    "iso:country": "GB",
    "wof:name": "G77 6UT",
    "wof:placetype": "postalcode"
  },
  "geometry": {"coordinates":[-4.337779,55.781431],"type":"Point"}
}
