{
  "type": "Feature",
  "properties": {
    "date:inception_lower": "2019-05-01",
    "date:inception_upper": "2019-05-01",
    "iso:country": "GB",
    "wof:name": "TF1 1AP",
    "wof:placetype": "postalcode"
  },
  "geometry": {"coordinates":[-2.517768,52.702431],"type":"Point"}
}
