{
  "type": "Feature",
  "properties": {
    "iso:country":"GB",
    "wof:name":"IG10 2PU",
    "wof:placetype":"postalcode"
},
  "geometry": {"coordinates":[0.07331462373439,51.6561002123419],"type":"Point"}
}