{
  "type": "Feature",
  "properties": {
    "iso:country":"GB",
    "wof:name":"HG4 3BY",
    "wof:placetype":"postalcode"
},
  "geometry": {"coordinates":[-1.64958365262002,54.18142081162029],"type":"Point"}
}