{
  "type": "Feature",
  "properties": {
    "date:inception_lower": "1980-01-01",
    "date:inception_upper": "1980-01-01",
    "iso:country": "GB",
    "wof:name": "HG4 3BY",
    "wof:placetype": "postalcode"
  },
  "geometry": {"coordinates":[-1.649584,54.181421],"type":"Point"}
}
