{
  "type": "Feature",
  "properties": {
    "iso:country":"GB",
    "wof:name":"SW2 1NZ",
    "wof:placetype":"postalcode"
},
  "geometry": {"coordinates":[-0.11773668579375,51.45531494004496],"type":"Point"}
}