{
  "type": "Feature",
  "properties": {
    "iso:country": "GB",
    "wof:name": "SW2 1NZ",
    "wof:placetype": "postalcode"
  },
  "geometry": {"coordinates":[-0.117737,51.455315],"type":"Point"}
}
