{
  "type": "Feature",
  "properties": {
    "iso:country":"GB",
    "wof:name":"PE33 0JT",
    "wof:placetype":"postalcode"
},
  "geometry": {"coordinates":[0.38588061877806,52.67489866404361],"type":"Point"}
}