{
  "type": "Feature",
  "properties": {
    "date:inception_lower":"1993-08-01",
    "date:inception_upper":"1993-08-31",
    "iso:country":"GB",
    "wof:name":"PE33 0JT",
    "wof:placetype":"postalcode"
},
  "geometry": {"coordinates":[0.385881,52.674899],"type":"Point"}
}