{
  "type": "Feature",
  "properties": {
    "iso:country":"GB",
    "wof:name":"NN6 8QF",
    "wof:placetype":"postalcode"
},
  "geometry": {"coordinates":[-1.00943879521962,52.3500418892397],"type":"Point"}
}