{
  "type": "Feature",
  "properties": {
    "iso:country": "GB",
    "wof:name": "NN6 8QF",
    "wof:placetype": "postalcode"
  },
  "geometry": {"coordinates":[-1.009439,52.350042],"type":"Point"}
}
