{
  "type": "Feature",
  "properties": {
    "date:inception_lower": "2024-02-01",
    "date:inception_upper": "2024-02-01",
    "iso:country": "GB",
    "wof:name": "TN12 6GY",
    "wof:placetype": "postalcode"
  },
  "geometry": {"coordinates":[0.397153,51.171596],"type":"Point"}
}
