{
  "type": "Feature",
  "properties": {
    "iso:country": "GB",
    "wof:name": "IP11 0TS",
    "wof:placetype": "postalcode"
  },
  "geometry": {"coordinates":[1.319814,51.977922],"type":"Point"}
}
