{
  "type": "Feature",
  "properties": {
    "iso:country":"GB",
    "wof:name":"SO32 3QU",
    "wof:placetype":"postalcode"
},
  "geometry": {"coordinates":[-1.12961378427018,50.95608794378152],"type":"Point"}
}