{
  "type": "Feature",
  "properties": {
    "date:inception_lower": "1994-12-01",
    "date:inception_upper": "1994-12-01",
    "iso:country": "GB",
    "wof:name": "SO32 3QU",
    "wof:placetype": "postalcode"
  },
  "geometry": {"coordinates":[-1.129614,50.956088],"type":"Point"}
}
