{
  "type": "Feature",
  "properties": {
    "iso:country": "GB",
    "wof:name": "NR21 9LY",
    "wof:placetype": "postalcode"
  },
  "geometry": {"coordinates":[0.755601,52.889389],"type":"Point"}
}
