{
  "type": "Feature",
  "properties": {
    "iso:country": "GB",
    "wof:name": "RG20 5RW",
    "wof:placetype": "postalcode"
  },
  "geometry": {"coordinates":[-1.240727,51.327242],"type":"Point"}
}
