{
  "type": "Feature",
  "properties": {
    "iso:country":"GB",
    "wof:name":"AB11 6NP",
    "wof:placetype":"postalcode"
},
  "geometry": {"coordinates":[-2.10689848014715,57.14389351262923],"type":"Point"}
}