{
  "type": "Feature",
  "properties": {
    "iso:country":"GB",
    "wof:name":"IP11 2NN",
    "wof:placetype":"postalcode"
},
  "geometry": {"coordinates":[1.3367802630257,51.96222399301843],"type":"Point"}
}