{
  "type": "Feature",
  "properties": {
    "iso:country":"GB",
    "wof:name":"M32 9AT",
    "wof:placetype":"postalcode"
},
  "geometry": {"coordinates":[-2.3145160805822,53.44255409164351],"type":"Point"}
}