{
  "type": "Feature",
  "properties": {
    "date:inception_lower": "2011-03-01",
    "date:inception_upper": "2011-03-01",
    "iso:country": "GB",
    "wof:name": "WS1 9NL",
    "wof:placetype": "postalcode"
  },
  "geometry": {"coordinates":[-1.981286,52.585996],"type":"Point"}
}
