{
  "type": "Feature",
  "properties": {
    "date:inception_lower": "2008-09-01",
    "date:inception_upper": "2008-09-01",
    "iso:country": "GB",
    "wof:name": "SY8 2BL",
    "wof:placetype": "postalcode"
  },
  "geometry": {"coordinates":[-2.714883,52.375106],"type":"Point"}
}
