{
  "type": "Feature",
  "properties": {
    "iso:country":"GB",
    "wof:name":"SY8 2BL",
    "wof:placetype":"postalcode"
},
  "geometry": {"coordinates":[-2.71488326465804,52.37510560310941],"type":"Point"}
}