{
  "type": "Feature",
  "properties": {
    "iso:country": "GB",
    "wof:name": "NE10 0PQ",
    "wof:placetype": "postalcode"
  },
  "geometry": {"coordinates":[-1.560883,54.950498],"type":"Point"}
}
