{
  "type": "Feature",
  "properties": {
    "iso:country":"GB",
    "wof:name":"CB6 1RS",
    "wof:placetype":"postalcode"
},
  "geometry": {"coordinates":[0.27935146101495,52.44770794329386],"type":"Point"}
}