{
  "type": "Feature",
  "properties": {
    "iso:country":"GB",
    "wof:name":"AL10 9EL",
    "wof:placetype":"postalcode"
},
  "geometry": {"coordinates":[-0.24027037223579,51.74703912350903],"type":"Point"}
}