{
  "type": "Feature",
  "properties": {
    "iso:country": "GB",
    "wof:name": "AL10 9EL",
    "wof:placetype": "postalcode"
  },
  "geometry": {"coordinates":[-0.24027,51.747039],"type":"Point"}
}
