{
  "type": "Feature",
  "properties": {
    "date:inception_lower": "1980-01-01",
    "date:inception_upper": "1980-01-01",
    "iso:country": "GB",
    "wof:name": "B45 9YF",
    "wof:placetype": "postalcode"
  },
  "geometry": {"coordinates":[-2.015005,52.396426],"type":"Point"}
}
