{
  "type": "Feature",
  "properties": {
    "iso:country":"GB",
    "wof:name":"B45 9YF",
    "wof:placetype":"postalcode"
},
  "geometry": {"coordinates":[-2.01500477543415,52.39642598203532],"type":"Point"}
}