{
  "type": "Feature",
  "properties": {
    "iso:country":"GB",
    "wof:name":"HG5 0EH",
    "wof:placetype":"postalcode"
},
  "geometry": {"coordinates":[-1.47102034194445,54.01071454556382],"type":"Point"}
}