{
  "type": "Feature",
  "properties": {
    "date:inception_lower":"1985-04-01",
    "date:inception_upper":"1985-04-30",
    "iso:country":"GB",
    "wof:name":"HG5 0EH",
    "wof:placetype":"postalcode"
},
  "geometry": {"coordinates":[-1.47102,54.010715],"type":"Point"}
}