{
  "type": "Feature",
  "properties": {
    "iso:country": "GB",
    "wof:name": "LL59 5RX",
    "wof:placetype": "postalcode"
  },
  "geometry": {"coordinates":[-4.200636,53.23885],"type":"Point"}
}
