{
  "type": "Feature",
  "properties": {
    "date:inception_lower":"2006-02-01",
    "date:inception_upper":"2006-02-28",
    "iso:country":"GB",
    "wof:name":"LL59 5RX",
    "wof:placetype":"postalcode"
},
  "geometry": {"coordinates":[-4.200636,53.23885],"type":"Point"}
}