{
  "type": "Feature",
  "properties": {
    "iso:country":"GB",
    "wof:name":"IP14 6BE",
    "wof:placetype":"postalcode"
},
  "geometry": {"coordinates":[1.16732201423444,52.20657832203489],"type":"Point"}
}