{
  "type": "Feature",
  "properties": {
    "iso:country": "GB",
    "wof:name": "E7 8AX",
    "wof:placetype": "postalcode"
  },
  "geometry": {"coordinates":[0.041924,51.548532],"type":"Point"}
}
