{
  "type": "Feature",
  "properties": {
    "iso:country": "GB",
    "wof:name": "NN3 7BZ",
    "wof:placetype": "postalcode"
  },
  "geometry": {"coordinates":[-0.859174,52.280984],"type":"Point"}
}
