{
  "type": "Feature",
  "properties": {
    "iso:country":"GB",
    "wof:name":"DG9 8TS",
    "wof:placetype":"postalcode"
},
  "geometry": {"coordinates":[-5.10653178536387,54.89292531512862],"type":"Point"}
}