{
  "type": "Feature",
  "properties": {
    "date:inception_lower":"1980-01-01",
    "date:inception_upper":"1980-01-31",
    "iso:country":"GB",
    "wof:name":"GU22 0JX",
    "wof:placetype":"postalcode"
},
  "geometry": {"coordinates":[-0.586053,51.306152],"type":"Point"}
}