{
  "type": "Feature",
  "properties": {
    "iso:country": "GB",
    "wof:name": "AL9 7TH",
    "wof:placetype": "postalcode"
  },
  "geometry": {"coordinates":[-0.224519,51.723513],"type":"Point"}
}
