{
  "type": "Feature",
  "properties": {
    "iso:country": "GB",
    "wof:name": "TQ6 9DJ",
    "wof:placetype": "postalcode"
  },
  "geometry": {"coordinates":[-3.579555,50.35103],"type":"Point"}
}
