{
  "type": "Feature",
  "properties": {
    "date:inception_lower": "2010-02-01",
    "date:inception_upper": "2010-02-01",
    "iso:country": "GB",
    "wof:name": "NP10 8ZS",
    "wof:placetype": "postalcode"
  },
  "geometry": {"coordinates":[-2.997047,51.591272],"type":"Point"}
}
