{
  "type": "Feature",
  "properties": {
    "date:inception_lower":"2004-03-01",
    "date:inception_upper":"2004-03-31",
    "iso:country":"GB",
    "wof:name":"IV36 2HE",
    "wof:placetype":"postalcode"
},
  "geometry": {"coordinates":[-3.628333,57.597222],"type":"Point"}
}