{
  "type": "Feature",
  "properties": {
    "iso:country":"GB",
    "wof:name":"HP6 5EZ",
    "wof:placetype":"postalcode"
},
  "geometry": {"coordinates":[-0.60848652261332,51.675824197483],"type":"Point"}
}