{
  "type": "Feature",
  "properties": {
    "iso:country": "GB",
    "wof:name": "HP6 5EZ",
    "wof:placetype": "postalcode"
  },
  "geometry": {"coordinates":[-0.608486,51.675824],"type":"Point"}
}
