{
  "type": "Feature",
  "properties": {
    "iso:country":"GB",
    "wof:name":"DH7 7EN",
    "wof:placetype":"postalcode"
},
  "geometry": {"coordinates":[-1.65074750073339,54.76886787798881],"type":"Point"}
}