{
  "type": "Feature",
  "properties": {
    "iso:country": "GB",
    "wof:name": "DH7 7EN",
    "wof:placetype": "postalcode"
  },
  "geometry": {"coordinates":[-1.650747,54.768868],"type":"Point"}
}
