{
  "type": "Feature",
  "properties": {
    "iso:country":"GB",
    "wof:name":"WA10 4HL",
    "wof:placetype":"postalcode"
},
  "geometry": {"coordinates":[-2.7577595101104,53.4532559606869],"type":"Point"}
}