{
  "type": "Feature",
  "properties": {
    "iso:country":"GB",
    "wof:name":"PR7 6AR",
    "wof:placetype":"postalcode"
},
  "geometry": {"coordinates":[-2.67955629881329,53.66686183910503],"type":"Point"}
}