{
  "type": "Feature",
  "properties": {
    "iso:country":"GB",
    "wof:name":"M14 5YJ",
    "wof:placetype":"postalcode"
},
  "geometry": {"coordinates":[-2.20943086123482,53.45731915873588],"type":"Point"}
}