{
  "type": "Feature",
  "properties": {
    "date:inception_lower": "1980-01-01",
    "date:inception_upper": "1980-01-01",
    "iso:country": "GB",
    "wof:name": "LL16 4DY",
    "wof:placetype": "postalcode"
  },
  "geometry": {"coordinates":[-3.352793,53.231517],"type":"Point"}
}
