{
  "type": "Feature",
  "properties": {
    "iso:country":"GB",
    "wof:name":"LL16 4DY",
    "wof:placetype":"postalcode"
},
  "geometry": {"coordinates":[-3.35279258868646,53.23151659965237],"type":"Point"}
}