{
  "type": "Feature",
  "properties": {
    "date:inception_lower": "1980-01-01",
    "date:inception_upper": "1980-01-01",
    "iso:country": "GB",
    "wof:name": "HU9 5JH",
    "wof:placetype": "postalcode"
  },
  "geometry": {"coordinates":[-0.250116,53.753588],"type":"Point"}
}
