{
  "type": "Feature",
  "properties": {
    "iso:country":"GB",
    "wof:name":"HU9 5JH",
    "wof:placetype":"postalcode"
},
  "geometry": {"coordinates":[-0.25011620810894,53.75358769112684],"type":"Point"}
}