{
  "type": "Feature",
  "properties": {
    "iso:country": "GB",
    "wof:name": "HU9 4JH",
    "wof:placetype": "postalcode"
  },
  "geometry": {"coordinates":[-0.262282,53.767887],"type":"Point"}
}
