{
  "type": "Feature",
  "properties": {
    "iso:country":"GB",
    "wof:name":"W12 8HX",
    "wof:placetype":"postalcode"
},
  "geometry": {"coordinates":[-0.22938968739702,51.50288894027822],"type":"Point"}
}