{
  "type": "Feature",
  "properties": {
    "iso:country":"GB",
    "wof:name":"CO9 2PQ",
    "wof:placetype":"postalcode"
},
  "geometry": {"coordinates":[0.63525293726185,51.94575338877962],"type":"Point"}
}