{
  "type": "Feature",
  "properties": {
    "iso:country":"GB",
    "wof:name":"BA2 5DL",
    "wof:placetype":"postalcode"
},
  "geometry": {"coordinates":[-2.34177596786045,51.36253404378922],"type":"Point"}
}