{
  "type": "Feature",
  "properties": {
    "iso:country": "GB",
    "wof:name": "GL5 3PB",
    "wof:placetype": "postalcode"
  },
  "geometry": {"coordinates":[-2.232381,51.732543],"type":"Point"}
}
