{
  "type": "Feature",
  "properties": {
    "iso:country":"GB",
    "wof:name":"TW16 7QU",
    "wof:placetype":"postalcode"
},
  "geometry": {"coordinates":[-0.41866466066914,51.42484285385901],"type":"Point"}
}