{
  "type": "Feature",
  "properties": {
    "iso:country": "GB",
    "wof:name": "W13 0HE",
    "wof:placetype": "postalcode"
  },
  "geometry": {"coordinates":[-0.325588,51.520939],"type":"Point"}
}
