{
  "type": "Feature",
  "properties": {
    "iso:country":"GB",
    "wof:name":"PE33 9FG",
    "wof:placetype":"postalcode"
},
  "geometry": {"coordinates":[0.47000899526873,52.58492789776208],"type":"Point"}
}