{
  "type": "Feature",
  "properties": {
    "date:inception_lower": "2010-06-01",
    "date:inception_upper": "2010-06-01",
    "iso:country": "GB",
    "wof:name": "PE33 9FG",
    "wof:placetype": "postalcode"
  },
  "geometry": {"coordinates":[0.470009,52.584928],"type":"Point"}
}
