{
  "type": "Feature",
  "properties": {
    "iso:country":"GB",
    "wof:name":"PR25 5UR",
    "wof:placetype":"postalcode"
},
  "geometry": {"coordinates":[-2.66157848302767,53.69502404957282],"type":"Point"}
}