{
  "type": "Feature",
  "properties": {
    "iso:country":"GB",
    "wof:name":"M24 4RE",
    "wof:placetype":"postalcode"
},
  "geometry": {"coordinates":[-2.23213793742625,53.54214588301424],"type":"Point"}
}