{
  "type": "Feature",
  "properties": {
    "date:inception_lower": "1980-01-01",
    "date:inception_upper": "1980-01-01",
    "iso:country": "GB",
    "wof:name": "FY8 5JA",
    "wof:placetype": "postalcode"
  },
  "geometry": {"coordinates":[-2.962158,53.737866],"type":"Point"}
}
