{
  "type": "Feature",
  "properties": {
    "iso:country":"GB",
    "wof:name":"CW12 3AN",
    "wof:placetype":"postalcode"
},
  "geometry": {"coordinates":[-2.20567356406844,53.15951167593881],"type":"Point"}
}