{
  "type": "Feature",
  "properties": {
    "iso:country": "GB",
    "wof:name": "YO32 5YF",
    "wof:placetype": "postalcode"
  },
  "geometry": {"coordinates":[-1.028898,54.042317],"type":"Point"}
}
