{
  "type": "Feature",
  "properties": {
    "iso:country":"GB",
    "wof:name":"CV5 7EJ",
    "wof:placetype":"postalcode"
},
  "geometry": {"coordinates":[-1.59067919042626,52.41701690374423],"type":"Point"}
}