{
  "type": "Feature",
  "properties": {
    "iso:country":"GB",
    "wof:name":"G12 0QL",
    "wof:placetype":"postalcode"
},
  "geometry": {"coordinates":[-4.30053696197523,55.88682116500764],"type":"Point"}
}