{
  "type": "Feature",
  "properties": {
    "iso:country": "GB",
    "wof:name": "NG32 3SD",
    "wof:placetype": "postalcode"
  },
  "geometry": {"coordinates":[-0.554854,52.991319],"type":"Point"}
}
