{
  "type": "Feature",
  "properties": {
    "date:inception_lower":"1980-01-01",
    "date:inception_upper":"1980-01-31",
    "iso:country":"GB",
    "wof:name":"NG32 3SD",
    "wof:placetype":"postalcode"
},
  "geometry": {"coordinates":[-0.554854,52.991319],"type":"Point"}
}