{
  "type": "Feature",
  "properties": {
    "iso:country":"GB",
    "wof:name":"TF2 9LT",
    "wof:placetype":"postalcode"
},
  "geometry": {"coordinates":[-2.43199409749642,52.69476748137345],"type":"Point"}
}