{
  "type": "Feature",
  "properties": {
    "iso:country": "GB",
    "wof:name": "TF2 9LT",
    "wof:placetype": "postalcode"
  },
  "geometry": {"coordinates":[-2.431994,52.694767],"type":"Point"}
}
