{
  "type": "Feature",
  "properties": {
    "date:inception_lower": "1987-04-01",
    "date:inception_upper": "1987-04-01",
    "iso:country": "GB",
    "wof:name": "PH1 1QZ",
    "wof:placetype": "postalcode"
  },
  "geometry": {"coordinates":[-3.482621,56.399422],"type":"Point"}
}
