{
  "type": "Feature",
  "properties": {
    "iso:country": "GB",
    "wof:name": "G33 2LE",
    "wof:placetype": "postalcode"
  },
  "geometry": {"coordinates":[-4.185902,55.864465],"type":"Point"}
}
