{
  "type": "Feature",
  "properties": {
    "iso:country":"GB",
    "wof:name":"CO10 8EE",
    "wof:placetype":"postalcode"
},
  "geometry": {"coordinates":[0.53669344269772,52.11111132080131],"type":"Point"}
}