{
  "type": "Feature",
  "properties": {
    "iso:country":"GB",
    "wof:name":"PR6 9LQ",
    "wof:placetype":"postalcode"
},
  "geometry": {"coordinates":[-2.59863202786761,53.61788500251112],"type":"Point"}
}