{
  "type": "Feature",
  "properties": {
    "iso:country":"GB",
    "wof:name":"EX4 6EP",
    "wof:placetype":"postalcode"
},
  "geometry": {"coordinates":[-3.51717097433457,50.73670270845996],"type":"Point"}
}