{
  "type": "Feature",
  "properties": {
    "iso:country": "GB",
    "wof:name": "CV33 9DD",
    "wof:placetype": "postalcode"
  },
  "geometry": {"coordinates":[-1.478359,52.322724],"type":"Point"}
}
