{
  "type": "Feature",
  "properties": {
    "date:inception_lower": "2017-07-01",
    "date:inception_upper": "2017-07-01",
    "iso:country": "GB",
    "wof:name": "CV33 9DD",
    "wof:placetype": "postalcode"
  },
  "geometry": {"coordinates":[-1.478359,52.322724],"type":"Point"}
}
