{
  "type": "Feature",
  "properties": {
    "iso:country": "GB",
    "wof:name": "WR1 2HB",
    "wof:placetype": "postalcode"
  },
  "geometry": {"coordinates":[-2.220781,52.190832],"type":"Point"}
}
