{
  "type": "Feature",
  "properties": {
    "iso:country": "GB",
    "wof:name": "GL7 4AQ",
    "wof:placetype": "postalcode"
  },
  "geometry": {"coordinates":[-1.779921,51.707325],"type":"Point"}
}
