{
  "type": "Feature",
  "properties": {
    "iso:country":"GB",
    "wof:name":"BB10 3NP",
    "wof:placetype":"postalcode"
},
  "geometry": {"coordinates":[-2.18789829208092,53.78779845532628],"type":"Point"}
}