{
  "type": "Feature",
  "properties": {
    "iso:country": "GB",
    "wof:name": "BB10 3NP",
    "wof:placetype": "postalcode"
  },
  "geometry": {"coordinates":[-2.187898,53.787798],"type":"Point"}
}
