{
  "type": "Feature",
  "properties": {
    "iso:country": "GB",
    "wof:name": "ML5 4QL",
    "wof:placetype": "postalcode"
  },
  "geometry": {"coordinates":[-4.009126,55.85315],"type":"Point"}
}
