{
  "type": "Feature",
  "properties": {
    "iso:country": "GB",
    "wof:name": "BH20 7HU",
    "wof:placetype": "postalcode"
  },
  "geometry": {"coordinates":[-2.227627,50.754618],"type":"Point"}
}
