{
  "type": "Feature",
  "properties": {
    "iso:country":"GB",
    "wof:name":"SG19 3DE",
    "wof:placetype":"postalcode"
},
  "geometry": {"coordinates":[-0.19511551280353,52.15948414903045],"type":"Point"}
}