{
  "type": "Feature",
  "properties": {
    "date:inception_lower": "1994-12-01",
    "date:inception_upper": "1994-12-01",
    "iso:country": "GB",
    "wof:name": "SG19 3DE",
    "wof:placetype": "postalcode"
  },
  "geometry": {"coordinates":[-0.195115,52.159484],"type":"Point"}
}
