{
  "type": "Feature",
  "properties": {
    "iso:country":"GB",
    "wof:name":"YO7 2PY",
    "wof:placetype":"postalcode"
},
  "geometry": {"coordinates":[-1.24112196823828,54.24192372448707],"type":"Point"}
}