{
  "type": "Feature",
  "properties": {
    "iso:country":"GB",
    "wof:name":"LE5 1EL",
    "wof:placetype":"postalcode"
},
  "geometry": {"coordinates":[-1.05678718232123,52.65568371819251],"type":"Point"}
}