{
  "type": "Feature",
  "properties": {
    "iso:country": "GB",
    "wof:name": "LE5 1EL",
    "wof:placetype": "postalcode"
  },
  "geometry": {"coordinates":[-1.05684,52.655613],"type":"Point"}
}
