{
  "type": "Feature",
  "properties": {
    "date:inception_lower": "2008-11-01",
    "date:inception_upper": "2008-11-01",
    "iso:country": "GB",
    "wof:name": "RM1 2EF",
    "wof:placetype": "postalcode"
  },
  "geometry": {"coordinates":[0.186317,51.574033],"type":"Point"}
}
