{
  "type": "Feature",
  "properties": {
    "iso:country": "GB",
    "wof:name": "RM1 2EF",
    "wof:placetype": "postalcode"
  },
  "geometry": {"coordinates":[0.186317,51.574033],"type":"Point"}
}
