{
  "type": "Feature",
  "properties": {
    "iso:country": "GB",
    "wof:name": "B69 3EL",
    "wof:placetype": "postalcode"
  },
  "geometry": {"coordinates":[-2.026585,52.515973],"type":"Point"}
}
