{
  "type": "Feature",
  "properties": {
    "date:inception_lower": "2006-10-01",
    "date:inception_upper": "2006-10-01",
    "iso:country": "GB",
    "wof:name": "B69 3EL",
    "wof:placetype": "postalcode"
  },
  "geometry": {"coordinates":[-2.026585,52.515973],"type":"Point"}
}
