{
  "type": "Feature",
  "properties": {
    "iso:country":"GB",
    "wof:name":"TD13 5XX",
    "wof:placetype":"postalcode"
},
  "geometry": {"coordinates":[-2.36339644804089,55.93232007766582],"type":"Point"}
}