{
  "type": "Feature",
  "properties": {
    "date:inception_lower":"1980-01-01",
    "date:inception_upper":"1980-01-31",
    "iso:country":"GB",
    "wof:name":"TD13 5XX",
    "wof:placetype":"postalcode"
},
  "geometry": {"coordinates":[-2.3635,55.932271],"type":"Point"}
}