{
  "type": "Feature",
  "properties": {
    "iso:country": "GB",
    "wof:name": "LS6 2RD",
    "wof:placetype": "postalcode"
  },
  "geometry": {"coordinates":[-1.556039,53.813038],"type":"Point"}
}
