{
  "type": "Feature",
  "properties": {
    "iso:country": "GB",
    "wof:name": "EH6 5QW",
    "wof:placetype": "postalcode"
  },
  "geometry": {"coordinates":[-3.187225,55.969288],"type":"Point"}
}
