{
  "type": "Feature",
  "properties": {
    "iso:country": "GB",
    "wof:name": "RM20 3AN",
    "wof:placetype": "postalcode"
  },
  "geometry": {"coordinates":[0.279409,51.47457],"type":"Point"}
}
