{
  "type": "Feature",
  "properties": {
    "iso:country":"GB",
    "wof:name":"E14 3DB",
    "wof:placetype":"postalcode"
},
  "geometry": {"coordinates":[-0.00791673607744,51.48956099306869],"type":"Point"}
}