{
  "type": "Feature",
  "properties": {
    "date:inception_lower": "2022-09-01",
    "date:inception_upper": "2022-09-01",
    "iso:country": "GB",
    "wof:name": "DD7 7DQ",
    "wof:placetype": "postalcode"
  },
  "geometry": {"coordinates":[-2.745431,56.504754],"type":"Point"}
}
