{
  "type": "Feature",
  "properties": {
    "date:inception_lower": "1980-01-01",
    "date:inception_upper": "1980-01-01",
    "iso:country": "GB",
    "wof:name": "TR4 8DF",
    "wof:placetype": "postalcode"
  },
  "geometry": {"coordinates":[-5.213555,50.278728],"type":"Point"}
}
