{
  "type": "Feature",
  "properties": {
    "iso:country": "GB",
    "wof:name": "LS28 5GG",
    "wof:placetype": "postalcode"
  },
  "geometry": {"coordinates":[-1.673478,53.818265],"type":"Point"}
}
