{
  "type": "Feature",
  "properties": {
    "iso:country":"GB",
    "wof:name":"NR15 2SN",
    "wof:placetype":"postalcode"
},
  "geometry": {"coordinates":[1.27307728133835,52.46369435923585],"type":"Point"}
}