{
  "type": "Feature",
  "properties": {
    "date:inception_lower": "1980-01-01",
    "date:inception_upper": "1980-01-01",
    "iso:country": "GB",
    "wof:name": "NR15 2SN",
    "wof:placetype": "postalcode"
  },
  "geometry": {"coordinates":[1.272792,52.463491],"type":"Point"}
}
