{
  "type": "Feature",
  "properties": {
    "iso:country":"GB",
    "wof:name":"ST6 1LF",
    "wof:placetype":"postalcode"
},
  "geometry": {"coordinates":[-2.17568008195074,53.05152077683455],"type":"Point"}
}