{
  "type": "Feature",
  "properties": {
    "iso:country": "GB",
    "wof:name": "ST6 1LF",
    "wof:placetype": "postalcode"
  },
  "geometry": {"coordinates":[-2.17568,53.051521],"type":"Point"}
}
