{
  "type": "Feature",
  "properties": {
    "iso:country": "GB",
    "wof:name": "CF37 5HW",
    "wof:placetype": "postalcode"
  },
  "geometry": {"coordinates":[-3.31062,51.591821],"type":"Point"}
}
