{
  "type": "Feature",
  "properties": {
    "iso:country":"GB",
    "wof:name":"CF37 5HW",
    "wof:placetype":"postalcode"
},
  "geometry": {"coordinates":[-3.31062002259828,51.59182114492651],"type":"Point"}
}