{
  "type": "Feature",
  "properties": {
    "date:inception_lower":"2009-07-01",
    "date:inception_upper":"2009-07-31",
    "iso:country":"GB",
    "wof:name":"CF37 5HW",
    "wof:placetype":"postalcode"
},
  "geometry": {"coordinates":[-3.31062,51.591821],"type":"Point"}
}