{
  "type": "Feature",
  "properties": {
    "iso:country":"GB",
    "wof:name":"DH3 4LN",
    "wof:placetype":"postalcode"
},
  "geometry": {"coordinates":[-1.54718795864477,54.84087639782123],"type":"Point"}
}