{
  "type": "Feature",
  "properties": {
    "date:inception_lower": "1980-01-01",
    "date:inception_upper": "1980-01-01",
    "iso:country": "GB",
    "wof:name": "DH3 4LN",
    "wof:placetype": "postalcode"
  },
  "geometry": {"coordinates":[-1.547188,54.840876],"type":"Point"}
}
