{
  "type": "Feature",
  "properties": {
    "iso:country": "GB",
    "wof:name": "DH3 4LN",
    "wof:placetype": "postalcode"
  },
  "geometry": {"coordinates":[-1.547188,54.840876],"type":"Point"}
}
