{
  "type": "Feature",
  "properties": {
    "date:inception_lower":"1989-07-01",
    "date:inception_upper":"1989-07-31",
    "iso:country":"GB",
    "wof:name":"EH55 8BT",
    "wof:placetype":"postalcode"
},
  "geometry": {"coordinates":[-3.559775,55.851692],"type":"Point"}
}