{
  "type": "Feature",
  "properties": {
    "date:inception_lower": "1980-01-01",
    "date:inception_upper": "1980-01-01",
    "iso:country": "GB",
    "wof:name": "SY23 4RP",
    "wof:placetype": "postalcode"
  },
  "geometry": {"coordinates":[-3.909706,52.351202],"type":"Point"}
}
