{
  "type": "Feature",
  "properties": {
    "iso:country": "GB",
    "wof:name": "SY23 4RP",
    "wof:placetype": "postalcode"
  },
  "geometry": {"coordinates":[-3.909706,52.351202],"type":"Point"}
}
