{
  "type": "Feature",
  "properties": {
    "iso:country":"GB",
    "wof:name":"SY23 4RP",
    "wof:placetype":"postalcode"
},
  "geometry": {"coordinates":[-3.90969530491804,52.35118838474428],"type":"Point"}
}