{
  "type": "Feature",
  "properties": {
    "iso:country":"GB",
    "wof:name":"LL29 8NA",
    "wof:placetype":"postalcode"
},
  "geometry": {"coordinates":[-3.72877464207042,53.2962816149299],"type":"Point"}
}