{
  "type": "Feature",
  "properties": {
    "iso:country": "GB",
    "wof:name": "LL29 8NA",
    "wof:placetype": "postalcode"
  },
  "geometry": {"coordinates":[-3.728775,53.296282],"type":"Point"}
}
