{
  "type": "Feature",
  "properties": {
    "date:inception_lower":"1980-01-01",
    "date:inception_upper":"1980-01-31",
    "iso:country":"GB",
    "wof:name":"LL29 8NA",
    "wof:placetype":"postalcode"
},
  "geometry": {"coordinates":[-3.728775,53.296282],"type":"Point"}
}