{
  "type": "Feature",
  "properties": {
    "iso:country":"GB",
    "wof:name":"CF72 8QW",
    "wof:placetype":"postalcode"
},
  "geometry": {"coordinates":[-3.38046339061905,51.52328379700464],"type":"Point"}
}