{
  "type": "Feature",
  "properties": {
    "date:inception_lower":"1995-12-01",
    "date:inception_upper":"1995-12-31",
    "iso:country":"GB",
    "wof:name":"CF72 8QW",
    "wof:placetype":"postalcode"
},
  "geometry": {"coordinates":[-3.380463,51.523284],"type":"Point"}
}