{
  "type": "Feature",
  "properties": {
    "date:inception_lower": "1998-06-01",
    "date:inception_upper": "1998-06-01",
    "iso:country": "GB",
    "wof:name": "LA23 3FS",
    "wof:placetype": "postalcode"
  },
  "geometry": {"coordinates":[-2.917485,54.358473],"type":"Point"}
}
