{
  "type": "Feature",
  "properties": {
    "date:inception_lower": "2010-04-01",
    "date:inception_upper": "2010-04-01",
    "iso:country": "GB",
    "wof:name": "NR3 2FE",
    "wof:placetype": "postalcode"
  },
  "geometry": {"coordinates":[1.272926,52.644705],"type":"Point"}
}
