{
  "type": "Feature",
  "properties": {
    "iso:country":"GB",
    "wof:name":"NR3 2FE",
    "wof:placetype":"postalcode"
},
  "geometry": {"coordinates":[1.27292546959705,52.64470509170199],"type":"Point"}
}