{
  "type": "Feature",
  "properties": {
    "date:inception_lower":"2011-05-01",
    "date:inception_upper":"2011-05-31",
    "iso:country":"GB",
    "wof:name":"E3 3GT",
    "wof:placetype":"postalcode"
},
  "geometry": {"coordinates":[-0.008441,51.523816],"type":"Point"}
}