{
  "type": "Feature",
  "properties": {
    "iso:country":"GB",
    "wof:name":"CM12 0AG",
    "wof:placetype":"postalcode"
},
  "geometry": {"coordinates":[0.41724550544973,51.63111378782613],"type":"Point"}
}