{
  "type": "Feature",
  "properties": {
    "date:inception_lower": "1980-01-01",
    "date:inception_upper": "1980-01-01",
    "iso:country": "GB",
    "wof:name": "CM12 0AG",
    "wof:placetype": "postalcode"
  },
  "geometry": {"coordinates":[0.417246,51.631114],"type":"Point"}
}
