{
  "type": "Feature",
  "properties": {
    "date:inception_lower": "2008-11-01",
    "date:inception_upper": "2008-11-01",
    "iso:country": "GB",
    "wof:name": "SE4 2FG",
    "wof:placetype": "postalcode"
  },
  "geometry": {"coordinates":[-0.044744,51.457034],"type":"Point"}
}
