{
  "type": "Feature",
  "properties": {
    "iso:country":"GB",
    "wof:name":"SE4 2FG",
    "wof:placetype":"postalcode"
},
  "geometry": {"coordinates":[-0.04474383066315,51.45703385811075],"type":"Point"}
}