{
  "type": "Feature",
  "properties": {
    "iso:country": "GB",
    "wof:name": "BD18 2JS",
    "wof:placetype": "postalcode"
  },
  "geometry": {"coordinates":[-1.766577,53.83283],"type":"Point"}
}
