{
  "type": "Feature",
  "properties": {
    "iso:country":"GB",
    "wof:name":"BD18 2JS",
    "wof:placetype":"postalcode"
},
  "geometry": {"coordinates":[-1.76657745659648,53.83282997316557],"type":"Point"}
}