{
  "type": "Feature",
  "properties": {
    "iso:country":"GB",
    "wof:name":"PE19 7AD",
    "wof:placetype":"postalcode"
},
  "geometry": {"coordinates":[-0.27700540705192,52.22634607386112],"type":"Point"}
}