{
  "type": "Feature",
  "properties": {
    "iso:country":"GB",
    "wof:name":"BD14 6PT",
    "wof:placetype":"postalcode"
},
  "geometry": {"coordinates":[-1.83524756072123,53.77683196085887],"type":"Point"}
}