{
  "type": "Feature",
  "properties": {
    "iso:country":"GB",
    "wof:name":"PE19 6DN",
    "wof:placetype":"postalcode"
},
  "geometry": {"coordinates":[-0.23884083258458,52.23210368464681],"type":"Point"}
}