{
  "type": "Feature",
  "properties": {
    "iso:country": "GB",
    "wof:name": "PE19 6DN",
    "wof:placetype": "postalcode"
  },
  "geometry": {"coordinates":[-0.238841,52.232104],"type":"Point"}
}
