{
  "type": "Feature",
  "properties": {
    "iso:country":"GB",
    "wof:name":"AL2 1EY",
    "wof:placetype":"postalcode"
},
  "geometry": {"coordinates":[-0.29852084126565,51.72578551509672],"type":"Point"}
}