{
  "type": "Feature",
  "properties": {
    "date:inception_lower": "1980-01-01",
    "date:inception_upper": "1980-01-01",
    "iso:country": "GB",
    "wof:name": "N22 6JH",
    "wof:placetype": "postalcode"
  },
  "geometry": {"coordinates":[-0.099425,51.596283],"type":"Point"}
}
