{
  "type": "Feature",
  "properties": {
    "iso:country":"GB",
    "wof:name":"N22 6JH",
    "wof:placetype":"postalcode"
},
  "geometry": {"coordinates":[-0.09942499648314,51.59628326314967],"type":"Point"}
}