{
  "type": "Feature",
  "properties": {
    "iso:country":"GB",
    "wof:name":"DD8 2BR",
    "wof:placetype":"postalcode"
},
  "geometry": {"coordinates":[-2.87454668612783,56.64197405428791],"type":"Point"}
}