{
  "type": "Feature",
  "properties": {
    "iso:country":"GB",
    "wof:name":"NG34 9AT",
    "wof:placetype":"postalcode"
},
  "geometry": {"coordinates":[-0.40136451152677,53.04460777114293],"type":"Point"}
}