{
  "type": "Feature",
  "properties": {
    "iso:country": "GB",
    "wof:name": "NG34 9AT",
    "wof:placetype": "postalcode"
  },
  "geometry": {"coordinates":[-0.401364,53.044608],"type":"Point"}
}
