{
  "type": "Feature",
  "properties": {
    "iso:country":"GB",
    "wof:name":"DE1 2BJ",
    "wof:placetype":"postalcode"
},
  "geometry": {"coordinates":[-1.47224388678278,52.91933677761903],"type":"Point"}
}