{
  "type": "Feature",
  "properties": {
    "iso:country":"GB",
    "wof:name":"EH5 1EJ",
    "wof:placetype":"postalcode"
},
  "geometry": {"coordinates":[-3.22799193824971,55.97865242097486],"type":"Point"}
}