{
  "type": "Feature",
  "properties": {
    "iso:country": "GB",
    "wof:name": "EH5 1EJ",
    "wof:placetype": "postalcode"
  },
  "geometry": {"coordinates":[-3.227992,55.978652],"type":"Point"}
}
