{
  "type": "Feature",
  "properties": {
    "iso:country":"GB",
    "wof:name":"DE24 9SE",
    "wof:placetype":"postalcode"
},
  "geometry": {"coordinates":[-1.48542381935652,52.8776836627119],"type":"Point"}
}