{
  "type": "Feature",
  "properties": {
    "date:inception_lower": "2010-01-01",
    "date:inception_upper": "2010-01-01",
    "iso:country": "GB",
    "wof:name": "DE24 9SE",
    "wof:placetype": "postalcode"
  },
  "geometry": {"coordinates":[-1.48545,52.877693],"type":"Point"}
}
