{
  "type": "Feature",
  "properties": {
    "iso:country": "GB",
    "wof:name": "DE24 9SE",
    "wof:placetype": "postalcode"
  },
  "geometry": {"coordinates":[-1.48545,52.877693],"type":"Point"}
}
