{
  "type": "Feature",
  "properties": {
    "iso:country":"GB",
    "wof:name":"NW6 1RR",
    "wof:placetype":"postalcode"
},
  "geometry": {"coordinates":[-0.19283552117901,51.55166384623138],"type":"Point"}
}