{
  "type": "Feature",
  "properties": {
    "iso:country": "GB",
    "wof:name": "HD9 4JD",
    "wof:placetype": "postalcode"
  },
  "geometry": {"coordinates":[-1.854219,53.586865],"type":"Point"}
}
