{
  "type": "Feature",
  "properties": {
    "iso:country": "GB",
    "wof:name": "NG24 2LT",
    "wof:placetype": "postalcode"
  },
  "geometry": {"coordinates":[-0.782937,53.077072],"type":"Point"}
}
