{
  "type": "Feature",
  "properties": {
    "iso:country":"GB",
    "wof:name":"NG24 2LT",
    "wof:placetype":"postalcode"
},
  "geometry": {"coordinates":[-0.78293716388384,53.07707176449631],"type":"Point"}
}