{
  "type": "Feature",
  "properties": {
    "iso:country": "GB",
    "wof:name": "RG8 0DH",
    "wof:placetype": "postalcode"
  },
  "geometry": {"coordinates":[-1.126893,51.529142],"type":"Point"}
}
