{
  "type": "Feature",
  "properties": {
    "date:inception_lower": "2019-03-01",
    "date:inception_upper": "2019-03-01",
    "iso:country": "GB",
    "wof:name": "TN4 8FL",
    "wof:placetype": "postalcode"
  },
  "geometry": {"coordinates":[0.26056,51.137163],"type":"Point"}
}
