{
  "type": "Feature",
  "properties": {
    "iso:country":"GB",
    "wof:name":"UB2 5AA",
    "wof:placetype":"postalcode"
},
  "geometry": {"coordinates":[-0.38318369345029,51.5021333815361],"type":"Point"}
}