{
  "type": "Feature",
  "properties": {
    "date:inception_lower": "1998-12-01",
    "date:inception_upper": "1998-12-01",
    "iso:country": "GB",
    "wof:name": "DA8 1AU",
    "wof:placetype": "postalcode"
  },
  "geometry": {"coordinates":[0.170199,51.48648],"type":"Point"}
}
