{
  "type": "Feature",
  "properties": {
    "iso:country":"GB",
    "wof:name":"RM5 3YL",
    "wof:placetype":"postalcode"
},
  "geometry": {"coordinates":[0.173567084096,51.60444931975179],"type":"Point"}
}