{
  "type": "Feature",
  "properties": {
    "date:inception_lower":"1980-01-01",
    "date:inception_upper":"1980-01-31",
    "iso:country":"GB",
    "wof:name":"M6 7HN",
    "wof:placetype":"postalcode"
},
  "geometry": {"coordinates":[-2.297326,53.49465],"type":"Point"}
}