{
  "type": "Feature",
  "properties": {
    "iso:country": "GB",
    "wof:name": "KT22 0AH",
    "wof:placetype": "postalcode"
  },
  "geometry": {"coordinates":[-0.332143,51.297191],"type":"Point"}
}
