{
  "type": "Feature",
  "properties": {
    "date:inception_lower": "1986-07-01",
    "date:inception_upper": "1986-07-01",
    "iso:country": "GB",
    "wof:name": "KT22 0AH",
    "wof:placetype": "postalcode"
  },
  "geometry": {"coordinates":[-0.332143,51.297191],"type":"Point"}
}
