{
  "type": "Feature",
  "properties": {
    "date:inception_lower": "2014-10-01",
    "date:inception_upper": "2014-10-01",
    "iso:country": "GB",
    "wof:name": "NE34 0RH",
    "wof:placetype": "postalcode"
  },
  "geometry": {"coordinates":[-1.433315,54.971052],"type":"Point"}
}
