{
  "type": "Feature",
  "properties": {
    "iso:country": "GB",
    "wof:name": "NE34 0RH",
    "wof:placetype": "postalcode"
  },
  "geometry": {"coordinates":[-1.433315,54.971052],"type":"Point"}
}
