{
  "type": "Feature",
  "properties": {
    "iso:country": "GB",
    "wof:name": "M33 4BB",
    "wof:placetype": "postalcode"
  },
  "geometry": {"coordinates":[-2.334199,53.412722],"type":"Point"}
}
