{
  "type": "Feature",
  "properties": {
    "iso:country":"GB",
    "wof:name":"M33 4BB",
    "wof:placetype":"postalcode"
},
  "geometry": {"coordinates":[-2.33419939203457,53.41272151064899],"type":"Point"}
}