{
  "type": "Feature",
  "properties": {
    "date:inception_lower": "1992-01-01",
    "date:inception_upper": "1992-01-01",
    "iso:country": "GB",
    "wof:name": "RH9 8LJ",
    "wof:placetype": "postalcode"
  },
  "geometry": {"coordinates":[-0.068788,51.219158],"type":"Point"}
}
