{
  "type": "Feature",
  "properties": {
    "iso:country":"GB",
    "wof:name":"BH21 5AN",
    "wof:placetype":"postalcode"
},
  "geometry": {"coordinates":[-2.01864612197227,50.8596559763192],"type":"Point"}
}