{
  "type": "Feature",
  "properties": {
    "date:inception_lower":"1980-01-01",
    "date:inception_upper":"1980-01-31",
    "iso:country":"GB",
    "wof:name":"KA25 7HP",
    "wof:placetype":"postalcode"
},
  "geometry": {"coordinates":[-4.685878,55.761145],"type":"Point"}
}