{
  "type": "Feature",
  "properties": {
    "iso:country":"GB",
    "wof:name":"KA25 7HP",
    "wof:placetype":"postalcode"
},
  "geometry": {"coordinates":[-4.68587801927751,55.76114531186762],"type":"Point"}
}