{
  "type": "Feature",
  "properties": {
    "iso:country":"GB",
    "wof:name":"B61 7BD",
    "wof:placetype":"postalcode"
},
  "geometry": {"coordinates":[-2.07217733742935,52.32708179917616],"type":"Point"}
}