{
  "type": "Feature",
  "properties": {
    "date:inception_lower": "1980-01-01",
    "date:inception_upper": "1980-01-01",
    "iso:country": "GB",
    "wof:name": "B61 7BD",
    "wof:placetype": "postalcode"
  },
  "geometry": {"coordinates":[-2.072177,52.327082],"type":"Point"}
}
