{
  "type": "Feature",
  "properties": {
    "iso:country":"GB",
    "wof:name":"PL14 4RG",
    "wof:placetype":"postalcode"
},
  "geometry": {"coordinates":[-4.47748509389088,50.42193222727396],"type":"Point"}
}