{
  "type": "Feature",
  "properties": {
    "iso:country":"GB",
    "wof:name":"BD21 5NH",
    "wof:placetype":"postalcode"
},
  "geometry": {"coordinates":[-1.90624720011558,53.85882432084772],"type":"Point"}
}