{
  "type": "Feature",
  "properties": {
    "iso:country":"GB",
    "wof:name":"SA8 4AF",
    "wof:placetype":"postalcode"
},
  "geometry": {"coordinates":[-3.8539336597839,51.71892053141259],"type":"Point"}
}