{
  "type": "Feature",
  "properties": {
    "iso:country":"GB",
    "wof:name":"E3 2HA",
    "wof:placetype":"postalcode"
},
  "geometry": {"coordinates":[-0.02693143690492,51.53291228425449],"type":"Point"}
}