{
  "type": "Feature",
  "properties": {
    "iso:country": "GB",
    "wof:name": "WN4 9TA",
    "wof:placetype": "postalcode"
  },
  "geometry": {"coordinates":[-2.643943,53.49795],"type":"Point"}
}
