{
  "type": "Feature",
  "properties": {
    "iso:country":"GB",
    "wof:name":"TS6 9TE",
    "wof:placetype":"postalcode"
},
  "geometry": {"coordinates":[-1.14114115313315,54.55732104259041],"type":"Point"}
}