{
  "type": "Feature",
  "properties": {
    "date:inception_lower": "1990-02-01",
    "date:inception_upper": "1990-02-01",
    "iso:country": "GB",
    "wof:name": "TS6 9TE",
    "wof:placetype": "postalcode"
  },
  "geometry": {"coordinates":[-1.141141,54.557321],"type":"Point"}
}
