{
  "type": "Feature",
  "properties": {
    "iso:country":"GB",
    "wof:name":"DN35 8NS",
    "wof:placetype":"postalcode"
},
  "geometry": {"coordinates":[-0.02841184326433,53.55495100837257],"type":"Point"}
}