{
  "type": "Feature",
  "properties": {
    "iso:country": "GB",
    "wof:name": "SL1 1XU",
    "wof:placetype": "postalcode"
  },
  "geometry": {"coordinates":[-0.594174,51.510094],"type":"Point"}
}
