{
  "type": "Feature",
  "properties": {
    "iso:country":"GB",
    "wof:name":"SL1 1XU",
    "wof:placetype":"postalcode"
},
  "geometry": {"coordinates":[-0.59417371141104,51.51009427080879],"type":"Point"}
}