{
  "type": "Feature",
  "properties": {
    "iso:country": "GB",
    "wof:name": "PE12 0PQ",
    "wof:placetype": "postalcode"
  },
  "geometry": {"coordinates":[-0.022331,52.684691],"type":"Point"}
}
