{
  "type": "Feature",
  "properties": {
    "iso:country":"GB",
    "wof:name":"OL6 7EY",
    "wof:placetype":"postalcode"
},
  "geometry": {"coordinates":[-2.10447881133849,53.48839549851306],"type":"Point"}
}