{
  "type": "Feature",
  "properties": {
    "iso:country":"GB",
    "wof:name":"SG7 5AZ",
    "wof:placetype":"postalcode"
},
  "geometry": {"coordinates":[-0.19546308288602,51.9887647021203],"type":"Point"}
}