{
  "type": "Feature",
  "properties": {
    "iso:country":"GB",
    "wof:name":"BH25 7RD",
    "wof:placetype":"postalcode"
},
  "geometry": {"coordinates":[-1.68375126072777,50.74166987267265],"type":"Point"}
}