{
  "type": "Feature",
  "properties": {
    "iso:country": "GB",
    "wof:name": "CM6 4AE",
    "wof:placetype": "postalcode"
  },
  "geometry": {"coordinates":[0.365194,51.862939],"type":"Point"}
}
