{
  "type": "Feature",
  "properties": {
    "iso:country":"GB",
    "wof:name":"DA8 1SA",
    "wof:placetype":"postalcode"
},
  "geometry": {"coordinates":[0.17881734109086,51.48144648127707],"type":"Point"}
}