{
  "type": "Feature",
  "properties": {
    "iso:country":"GB",
    "wof:name":"PO10 7EW",
    "wof:placetype":"postalcode"
},
  "geometry": {"coordinates":[-0.93701227681877,50.85397379384776],"type":"Point"}
}