{
  "type": "Feature",
  "properties": {
    "iso:country":"GB",
    "wof:name":"CW11 1YN",
    "wof:placetype":"postalcode"
},
  "geometry": {"coordinates":[-2.35213960515284,53.15107831839399],"type":"Point"}
}