{
  "type": "Feature",
  "properties": {
    "iso:country":"GB",
    "wof:name":"TR8 5QG",
    "wof:placetype":"postalcode"
},
  "geometry": {"coordinates":[-5.09979295906088,50.35894902942276],"type":"Point"}
}