{
  "type": "Feature",
  "properties": {
    "iso:country":"GB",
    "wof:name":"B93 8SW",
    "wof:placetype":"postalcode"
},
  "geometry": {"coordinates":[-1.76229438885362,52.37598772573801],"type":"Point"}
}