{
  "type": "Feature",
  "properties": {
    "iso:country":"GB",
    "wof:name":"PO20 7NL",
    "wof:placetype":"postalcode"
},
  "geometry": {"coordinates":[-0.79833977656105,50.77430920477796],"type":"Point"}
}