{
  "type": "Feature",
  "properties": {
    "iso:country": "GB",
    "wof:name": "RH12 5HF",
    "wof:placetype": "postalcode"
  },
  "geometry": {"coordinates":[-0.324179,51.087807],"type":"Point"}
}
