{
  "type": "Feature",
  "properties": {
    "iso:country":"GB",
    "wof:name":"RH12 5HF",
    "wof:placetype":"postalcode"
},
  "geometry": {"coordinates":[-0.32417881828687,51.08780669991266],"type":"Point"}
}