{
  "type": "Feature",
  "properties": {
    "iso:country":"GB",
    "wof:name":"NE16 5QE",
    "wof:placetype":"postalcode"
},
  "geometry": {"coordinates":[-1.67788292340784,54.92574710366905],"type":"Point"}
}