{
  "type": "Feature",
  "properties": {
    "date:inception_lower":"1985-10-01",
    "date:inception_upper":"1985-10-31",
    "iso:country":"GB",
    "wof:name":"NE16 5QE",
    "wof:placetype":"postalcode"
},
  "geometry": {"coordinates":[-1.677883,54.925747],"type":"Point"}
}