{
  "type": "Feature",
  "properties": {
    "iso:country": "GB",
    "wof:name": "OX15 4SW",
    "wof:placetype": "postalcode"
  },
  "geometry": {"coordinates":[-1.322537,52.03387],"type":"Point"}
}
