{
  "type": "Feature",
  "properties": {
    "iso:country":"GB",
    "wof:name":"LE2 9FP",
    "wof:placetype":"postalcode"
},
  "geometry": {"coordinates":[-1.14797387601163,52.58786140904767],"type":"Point"}
}