{
  "type": "Feature",
  "properties": {
    "date:inception_lower": "1980-01-01",
    "date:inception_upper": "1980-01-01",
    "iso:country": "GB",
    "wof:name": "DG2 7JP",
    "wof:placetype": "postalcode"
  },
  "geometry": {"coordinates":[-3.613437,55.061326],"type":"Point"}
}
