{
  "type": "Feature",
  "properties": {
    "iso:country":"GB",
    "wof:name":"DG2 7JP",
    "wof:placetype":"postalcode"
},
  "geometry": {"coordinates":[-3.61343677335706,55.0613256319394],"type":"Point"}
}