{
  "type": "Feature",
  "properties": {
    "date:inception_lower": "1980-01-01",
    "date:inception_upper": "1980-01-01",
    "iso:country": "GB",
    "wof:name": "HG3 3LT",
    "wof:placetype": "postalcode"
  },
  "geometry": {"coordinates":[-1.539865,54.051889],"type":"Point"}
}
