{
  "type": "Feature",
  "properties": {
    "iso:country":"GB",
    "wof:name":"HG3 3LT",
    "wof:placetype":"postalcode"
},
  "geometry": {"coordinates":[-1.53975076388567,54.05197205763139],"type":"Point"}
}