{
  "type": "Feature",
  "properties": {
    "iso:country": "GB",
    "wof:name": "NW8 0JD",
    "wof:placetype": "postalcode"
  },
  "geometry": {"coordinates":[-0.181485,51.53898],"type":"Point"}
}
