{
  "type": "Feature",
  "properties": {
    "iso:country":"GB",
    "wof:name":"TN23 4QX",
    "wof:placetype":"postalcode"
},
  "geometry": {"coordinates":[0.85539433107079,51.14234335313581],"type":"Point"}
}