{
  "type": "Feature",
  "properties": {
    "iso:country":"GB",
    "wof:name":"WR3 8EL",
    "wof:placetype":"postalcode"
},
  "geometry": {"coordinates":[-2.20931532593438,52.20617839744754],"type":"Point"}
}