{
  "type": "Feature",
  "properties": {
    "iso:country":"GB",
    "wof:name":"IP18 6YA",
    "wof:placetype":"postalcode"
},
  "geometry": {"coordinates":[1.66390593982034,52.334389801313],"type":"Point"}
}