{
  "type": "Feature",
  "properties": {
    "date:inception_lower": "1991-09-01",
    "date:inception_upper": "1991-09-01",
    "iso:country": "GB",
    "wof:name": "DN21 2BT",
    "wof:placetype": "postalcode"
  },
  "geometry": {"coordinates":[-0.775389,53.39933],"type":"Point"}
}
