{
  "type": "Feature",
  "properties": {
    "date:inception_lower": "1980-01-01",
    "date:inception_upper": "1980-01-01",
    "iso:country": "GB",
    "wof:name": "PR4 5EQ",
    "wof:placetype": "postalcode"
  },
  "geometry": {"coordinates":[-2.779166,53.726234],"type":"Point"}
}
