{
  "type": "Feature",
  "properties": {
    "iso:country":"GB",
    "wof:name":"PR4 5EQ",
    "wof:placetype":"postalcode"
},
  "geometry": {"coordinates":[-2.77916590741385,53.72623424961865],"type":"Point"}
}