{
  "type": "Feature",
  "properties": {
    "iso:country":"GB",
    "wof:name":"NE31 1RD",
    "wof:placetype":"postalcode"
},
  "geometry": {"coordinates":[-1.51988882226961,54.97885653358323],"type":"Point"}
}