{
  "type": "Feature",
  "properties": {
    "iso:country":"GB",
    "wof:name":"SE17 3LE",
    "wof:placetype":"postalcode"
},
  "geometry": {"coordinates":[-0.10092539284986,51.48997110397443],"type":"Point"}
}