{
  "type": "Feature",
  "properties": {
    "iso:country": "GB",
    "wof:name": "BH23 2SU",
    "wof:placetype": "postalcode"
  },
  "geometry": {"coordinates":[-1.806253,50.759716],"type":"Point"}
}
