{
  "type": "Feature",
  "properties": {
    "iso:country":"GB",
    "wof:name":"BH23 2SU",
    "wof:placetype":"postalcode"
},
  "geometry": {"coordinates":[-1.80625264077014,50.75971589276824],"type":"Point"}
}