{
  "type": "Feature",
  "properties": {
    "date:inception_lower":"1980-01-01",
    "date:inception_upper":"1980-01-31",
    "iso:country":"GB",
    "wof:name":"HU12 8AP",
    "wof:placetype":"postalcode"
},
  "geometry": {"coordinates":[-0.232824,53.718177],"type":"Point"}
}