{
  "type": "Feature",
  "properties": {
    "iso:country":"GB",
    "wof:name":"CB24 8PT",
    "wof:placetype":"postalcode"
},
  "geometry": {"coordinates":[0.13914754385512,52.3035559989282],"type":"Point"}
}