{
  "type": "Feature",
  "properties": {
    "iso:country": "GB",
    "wof:name": "CB24 8PT",
    "wof:placetype": "postalcode"
  },
  "geometry": {"coordinates":[0.138699,52.30375],"type":"Point"}
}
