{
  "type": "Feature",
  "properties": {
    "date:inception_lower": "1986-04-01",
    "date:inception_upper": "1986-04-01",
    "iso:country": "GB",
    "wof:name": "SM1 4BW",
    "wof:placetype": "postalcode"
  },
  "geometry": {"coordinates":[-0.194117,51.369108],"type":"Point"}
}
