{
  "type": "Feature",
  "properties": {
    "iso:country":"GB",
    "wof:name":"SM1 4BW",
    "wof:placetype":"postalcode"
},
  "geometry": {"coordinates":[-0.19428427685024,51.36913800811089],"type":"Point"}
}