{
  "type": "Feature",
  "properties": {
    "iso:country":"GB",
    "wof:name":"RH13 9DZ",
    "wof:placetype":"postalcode"
},
  "geometry": {"coordinates":[-0.35267873721441,51.02429904534674],"type":"Point"}
}