{
  "type": "Feature",
  "properties": {
    "iso:country": "GB",
    "wof:name": "BS48 4PJ",
    "wof:placetype": "postalcode"
  },
  "geometry": {"coordinates":[-2.751736,51.423491],"type":"Point"}
}
