{
  "type": "Feature",
  "properties": {
    "iso:country":"GB",
    "wof:name":"BN14 7AU",
    "wof:placetype":"postalcode"
},
  "geometry": {"coordinates":[-0.37943288376843,50.82393841205338],"type":"Point"}
}