{
  "type": "Feature",
  "properties": {
    "iso:country": "GB",
    "wof:name": "SY5 8BG",
    "wof:placetype": "postalcode"
  },
  "geometry": {"coordinates":[-2.793672,52.676446],"type":"Point"}
}
