{
  "type": "Feature",
  "properties": {
    "date:inception_lower":"1995-01-01",
    "date:inception_upper":"1995-01-31",
    "iso:country":"GB",
    "wof:name":"LE8 5LZ",
    "wof:placetype":"postalcode"
},
  "geometry": {"coordinates":[-1.149772,52.553191],"type":"Point"}
}