{
  "type": "Feature",
  "properties": {
    "iso:country":"GB",
    "wof:name":"LE8 5LZ",
    "wof:placetype":"postalcode"
},
  "geometry": {"coordinates":[-1.14981109225148,52.55316392186245],"type":"Point"}
}