{
  "type": "Feature",
  "properties": {
    "date:inception_lower": "2023-08-01",
    "date:inception_upper": "2023-08-01",
    "iso:country": "GB",
    "wof:name": "CF10 5EU",
    "wof:placetype": "postalcode"
  },
  "geometry": {"coordinates":[-3.167101,51.465347],"type":"Point"}
}
