{
  "type": "Feature",
  "properties": {
    "iso:country":"GB",
    "wof:name":"BH21 1RG",
    "wof:placetype":"postalcode"
},
  "geometry": {"coordinates":[-1.97720486184133,50.79374026661733],"type":"Point"}
}