{
  "type": "Feature",
  "properties": {
    "iso:country":"GB",
    "wof:name":"CA8 1EU",
    "wof:placetype":"postalcode"
},
  "geometry": {"coordinates":[-2.72335258996111,54.94238779212355],"type":"Point"}
}