{
  "type": "Feature",
  "properties": {
    "date:inception_lower": "2013-03-01",
    "date:inception_upper": "2013-03-01",
    "iso:country": "GB",
    "wof:name": "PE30 4WN",
    "wof:placetype": "postalcode"
  },
  "geometry": {"coordinates":[0.428098,52.765226],"type":"Point"}
}
