{
  "type": "Feature",
  "properties": {
    "iso:country":"GB",
    "wof:name":"PE30 4WN",
    "wof:placetype":"postalcode"
},
  "geometry": {"coordinates":[0.42809833329968,52.76522618724615],"type":"Point"}
}