{
  "type": "Feature",
  "properties": {
    "iso:country":"GB",
    "wof:name":"TR2 5LZ",
    "wof:placetype":"postalcode"
},
  "geometry": {"coordinates":[-4.97428061815885,50.22598305399424],"type":"Point"}
}