{
  "type": "Feature",
  "properties": {
    "iso:country":"GB",
    "wof:name":"E8 4LL",
    "wof:placetype":"postalcode"
},
  "geometry": {"coordinates":[-0.06581339964533,51.54050210505821],"type":"Point"}
}