{
  "type": "Feature",
  "properties": {
    "iso:country": "GB",
    "wof:name": "CW11 4AD",
    "wof:placetype": "postalcode"
  },
  "geometry": {"coordinates":[-2.34925,53.150681],"type":"Point"}
}
