{
  "type": "Feature",
  "properties": {
    "iso:country": "GB",
    "wof:name": "E5 8QX",
    "wof:placetype": "postalcode"
  },
  "geometry": {"coordinates":[-0.060674,51.557926],"type":"Point"}
}
