{
  "type": "Feature",
  "properties": {
    "iso:country":"GB",
    "wof:name":"DE5 3NW",
    "wof:placetype":"postalcode"
},
  "geometry": {"coordinates":[-1.38043335974145,53.04850192258817],"type":"Point"}
}