{
  "type": "Feature",
  "properties": {
    "date:inception_lower": "1980-01-01",
    "date:inception_upper": "1980-01-01",
    "iso:country": "GB",
    "wof:name": "SM2 6SL",
    "wof:placetype": "postalcode"
  },
  "geometry": {"coordinates":[-0.202344,51.354838],"type":"Point"}
}
