{
  "type": "Feature",
  "properties": {
    "iso:country": "GB",
    "wof:name": "HP17 8FU",
    "wof:placetype": "postalcode"
  },
  "geometry": {"coordinates":[-0.918608,51.770231],"type":"Point"}
}
