{
  "type": "Feature",
  "properties": {
    "date:inception_lower": "2019-05-01",
    "date:inception_upper": "2019-05-01",
    "iso:country": "GB",
    "wof:name": "HP17 8FU",
    "wof:placetype": "postalcode"
  },
  "geometry": {"coordinates":[-0.918689,51.769891],"type":"Point"}
}
