{
  "type": "Feature",
  "properties": {
    "date:inception_lower":"2000-06-01",
    "date:inception_upper":"2000-06-30",
    "iso:country":"GB",
    "wof:name":"NG22 8TQ",
    "wof:placetype":"postalcode"
},
  "geometry": {"coordinates":[-1.026701,53.128981],"type":"Point"}
}