{
  "type": "Feature",
  "properties": {
    "iso:country":"GB",
    "wof:name":"DH6 5EU",
    "wof:placetype":"postalcode"
},
  "geometry": {"coordinates":[-1.52368567895897,54.73812394054319],"type":"Point"}
}