{
  "type": "Feature",
  "properties": {
    "iso:country":"GB",
    "wof:name":"BH21 1SH",
    "wof:placetype":"postalcode"
},
  "geometry": {"coordinates":[-1.97003086255349,50.78568132392567],"type":"Point"}
}