{
  "type": "Feature",
  "properties": {
    "date:inception_lower": "2018-01-01",
    "date:inception_upper": "2018-01-01",
    "iso:country": "GB",
    "wof:name": "OL1 9QG",
    "wof:placetype": "postalcode"
  },
  "geometry": {"coordinates":[-2.099824,53.54151],"type":"Point"}
}
