{
  "type": "Feature",
  "properties": {
    "date:inception_lower": "1980-01-01",
    "date:inception_upper": "1980-01-01",
    "iso:country": "GB",
    "wof:name": "BL8 2BE",
    "wof:placetype": "postalcode"
  },
  "geometry": {"coordinates":[-2.320512,53.587079],"type":"Point"}
}
