{
  "type": "Feature",
  "properties": {
    "iso:country":"GB",
    "wof:name":"BL8 2BE",
    "wof:placetype":"postalcode"
},
  "geometry": {"coordinates":[-2.32051312971651,53.58701807032409],"type":"Point"}
}