{
  "type": "Feature",
  "properties": {
    "iso:country":"GB",
    "wof:name":"SO22 4AQ",
    "wof:placetype":"postalcode"
},
  "geometry": {"coordinates":[-1.33164383907677,51.05342969680326],"type":"Point"}
}