{
  "type": "Feature",
  "properties": {
    "iso:country": "GB",
    "wof:name": "SO22 4AQ",
    "wof:placetype": "postalcode"
  },
  "geometry": {"coordinates":[-1.331644,51.05343],"type":"Point"}
}
