{
  "type": "Feature",
  "properties": {
    "iso:country": "GB",
    "wof:name": "PO20 8FR",
    "wof:placetype": "postalcode"
  },
  "geometry": {"coordinates":[-0.852751,50.765755],"type":"Point"}
}
