{
  "type": "Feature",
  "properties": {
    "iso:country": "GB",
    "wof:name": "WA8 9WE",
    "wof:placetype": "postalcode"
  },
  "geometry": {"coordinates":[-2.745099,53.37863],"type":"Point"}
}
