{
  "type": "Feature",
  "properties": {
    "iso:country":"GB",
    "wof:name":"SM5 3LW",
    "wof:placetype":"postalcode"
},
  "geometry": {"coordinates":[-0.17059312130247,51.35509258596376],"type":"Point"}
}