{
  "type": "Feature",
  "properties": {
    "iso:country": "GB",
    "wof:name": "SM5 3LW",
    "wof:placetype": "postalcode"
  },
  "geometry": {"coordinates":[-0.170593,51.355093],"type":"Point"}
}
