{
  "type": "Feature",
  "properties": {
    "iso:country":"GB",
    "wof:name":"ME3 8HG",
    "wof:placetype":"postalcode"
},
  "geometry": {"coordinates":[0.50249576517722,51.43118555160731],"type":"Point"}
}