{
  "type": "Feature",
  "properties": {
    "date:inception_lower": "1981-06-01",
    "date:inception_upper": "1981-06-01",
    "iso:country": "GB",
    "wof:name": "ME3 8HG",
    "wof:placetype": "postalcode"
  },
  "geometry": {"coordinates":[0.502496,51.431186],"type":"Point"}
}
