{
  "type": "Feature",
  "properties": {
    "iso:country":"GB",
    "wof:name":"WS12 4PX",
    "wof:placetype":"postalcode"
},
  "geometry": {"coordinates":[-2.04027569303571,52.72521423864255],"type":"Point"}
}