{
  "type": "Feature",
  "properties": {
    "date:inception_lower": "1985-10-01",
    "date:inception_upper": "1985-10-01",
    "iso:country": "GB",
    "wof:name": "CR3 6AX",
    "wof:placetype": "postalcode"
  },
  "geometry": {"coordinates":[-0.089629,51.277109],"type":"Point"}
}
