{
  "type": "Feature",
  "properties": {
    "iso:country":"GB",
    "wof:name":"CR3 6AX",
    "wof:placetype":"postalcode"
},
  "geometry": {"coordinates":[-0.08962905756214,51.27710922193716],"type":"Point"}
}