{
  "type": "Feature",
  "properties": {
    "iso:country": "GB",
    "wof:name": "NG23 6TJ",
    "wof:placetype": "postalcode"
  },
  "geometry": {"coordinates":[-0.841404,53.207259],"type":"Point"}
}
