{
  "type": "Feature",
  "properties": {
    "iso:country":"GB",
    "wof:name":"NG23 6TJ",
    "wof:placetype":"postalcode"
},
  "geometry": {"coordinates":[-0.84050855668854,53.20775101435794],"type":"Point"}
}