{
  "type": "Feature",
  "properties": {
    "date:inception_lower":"1980-01-01",
    "date:inception_upper":"1980-01-31",
    "iso:country":"GB",
    "wof:name":"BA14 6AF",
    "wof:placetype":"postalcode"
},
  "geometry": {"coordinates":[-2.188848,51.295182],"type":"Point"}
}