{
  "type": "Feature",
  "properties": {
    "date:inception_lower":"2002-11-01",
    "date:inception_upper":"2002-11-30",
    "iso:country":"GB",
    "wof:name":"PO14 4FB",
    "wof:placetype":"postalcode"
},
  "geometry": {"coordinates":[-1.259789,50.859164],"type":"Point"}
}