{
  "type": "Feature",
  "properties": {
    "iso:country":"GB",
    "wof:name":"PO14 4FB",
    "wof:placetype":"postalcode"
},
  "geometry": {"coordinates":[-1.25978892620907,50.85916443821932],"type":"Point"}
}