{
  "type": "Feature",
  "properties": {
    "iso:country":"GB",
    "wof:name":"AB33 8ST",
    "wof:placetype":"postalcode"
},
  "geometry": {"coordinates":[-2.95447053543287,57.21813945613326],"type":"Point"}
}