{
  "type": "Feature",
  "properties": {
    "date:inception_lower": "1990-08-01",
    "date:inception_upper": "1990-08-01",
    "iso:country": "GB",
    "wof:name": "AB33 8ST",
    "wof:placetype": "postalcode"
  },
  "geometry": {"coordinates":[-2.95447,57.218139],"type":"Point"}
}
