{
  "type": "Feature",
  "properties": {
    "iso:country": "GB",
    "wof:name": "LA18 5HT",
    "wof:placetype": "postalcode"
  },
  "geometry": {"coordinates":[-3.23761,54.277923],"type":"Point"}
}
