{
  "type": "Feature",
  "properties": {
    "date:inception_lower": "1980-01-01",
    "date:inception_upper": "1980-01-01",
    "iso:country": "GB",
    "wof:name": "LA18 5HT",
    "wof:placetype": "postalcode"
  },
  "geometry": {"coordinates":[-3.23761,54.277923],"type":"Point"}
}
