{
  "type": "Feature",
  "properties": {
    "iso:country":"GB",
    "wof:name":"LA18 5HT",
    "wof:placetype":"postalcode"
},
  "geometry": {"coordinates":[-3.23763918264209,54.27791454767232],"type":"Point"}
}