{
  "type": "Feature",
  "properties": {
    "iso:country":"GB",
    "wof:name":"B76 1GE",
    "wof:placetype":"postalcode"
},
  "geometry": {"coordinates":[-1.79913738273821,52.54077086505978],"type":"Point"}
}