{
  "type": "Feature",
  "properties": {
    "iso:country": "GB",
    "wof:name": "ME13 8GP",
    "wof:placetype": "postalcode"
  },
  "geometry": {"coordinates":[0.908606,51.31048],"type":"Point"}
}
