{
  "type": "Feature",
  "properties": {
    "iso:country": "GB",
    "wof:name": "RH6 9NH",
    "wof:placetype": "postalcode"
  },
  "geometry": {"coordinates":[-0.118478,51.174535],"type":"Point"}
}
