{
  "type": "Feature",
  "properties": {
    "iso:country":"GB",
    "wof:name":"M31 4BW",
    "wof:placetype":"postalcode"
},
  "geometry": {"coordinates":[-2.42008273470878,53.42139377152284],"type":"Point"}
}