{
  "type": "Feature",
  "properties": {
    "date:inception_lower": "2021-03-01",
    "date:inception_upper": "2021-03-01",
    "iso:country": "GB",
    "wof:name": "SA6 6FJ",
    "wof:placetype": "postalcode"
  },
  "geometry": {"coordinates":[-3.931394,51.678175],"type":"Point"}
}
