{
  "type": "Feature",
  "properties": {
    "iso:country":"GB",
    "wof:name":"BL5 3AX",
    "wof:placetype":"postalcode"
},
  "geometry": {"coordinates":[-2.52191943128268,53.54987857981688],"type":"Point"}
}