{
  "type": "Feature",
  "properties": {
    "iso:country": "GB",
    "wof:name": "DD5 3QH",
    "wof:placetype": "postalcode"
  },
  "geometry": {"coordinates":[-2.836126,56.551067],"type":"Point"}
}
