{
  "type": "Feature",
  "properties": {
    "iso:country":"GB",
    "wof:name":"DD5 3QH",
    "wof:placetype":"postalcode"
},
  "geometry": {"coordinates":[-2.83612584580384,56.55106663322009],"type":"Point"}
}