{
  "type": "Feature",
  "properties": {
    "iso:country":"GB",
    "wof:name":"SA31 1TN",
    "wof:placetype":"postalcode"
},
  "geometry": {"coordinates":[-4.30676582667644,51.85574512003522],"type":"Point"}
}