{
  "type": "Feature",
  "properties": {
    "iso:country":"GB",
    "wof:name":"IV12 5RZ",
    "wof:placetype":"postalcode"
},
  "geometry": {"coordinates":[-3.84520017462954,57.5586718020642],"type":"Point"}
}