{
  "type": "Feature",
  "properties": {
    "iso:country": "GB",
    "wof:name": "IV12 5RZ",
    "wof:placetype": "postalcode"
  },
  "geometry": {"coordinates":[-3.845198,57.558953],"type":"Point"}
}
