{
  "type": "Feature",
  "properties": {
    "date:inception_lower": "1980-01-01",
    "date:inception_upper": "1980-01-01",
    "iso:country": "GB",
    "wof:name": "IV12 5RZ",
    "wof:placetype": "postalcode"
  },
  "geometry": {"coordinates":[-3.845198,57.558953],"type":"Point"}
}
