{
  "type": "Feature",
  "properties": {
    "iso:country":"GB",
    "wof:name":"LS14 5DT",
    "wof:placetype":"postalcode"
},
  "geometry": {"coordinates":[-1.44730319736077,53.82533129467785],"type":"Point"}
}