{
  "type": "Feature",
  "properties": {
    "date:inception_lower":"1980-01-01",
    "date:inception_upper":"1980-01-31",
    "iso:country":"GB",
    "wof:name":"LS14 5DT",
    "wof:placetype":"postalcode"
},
  "geometry": {"coordinates":[-1.447324,53.825285],"type":"Point"}
}