{
  "type": "Feature",
  "properties": {
    "iso:country": "GB",
    "wof:name": "LE17 4TN",
    "wof:placetype": "postalcode"
  },
  "geometry": {"coordinates":[-1.214716,52.45838],"type":"Point"}
}
