{
  "type": "Feature",
  "properties": {
    "iso:country":"GB",
    "wof:name":"LE17 4TN",
    "wof:placetype":"postalcode"
},
  "geometry": {"coordinates":[-1.21471565828231,52.4583795700369],"type":"Point"}
}