{
  "type": "Feature",
  "properties": {
    "iso:country":"GB",
    "wof:name":"SK9 2PR",
    "wof:placetype":"postalcode"
},
  "geometry": {"coordinates":[-2.21060167004503,53.3378858616303],"type":"Point"}
}