{
  "type": "Feature",
  "properties": {
    "date:inception_lower": "2021-04-01",
    "date:inception_upper": "2021-04-01",
    "iso:country": "GB",
    "wof:name": "IP31 3FP",
    "wof:placetype": "postalcode"
  },
  "geometry": {"coordinates":[0.815424,52.254885],"type":"Point"}
}
