{
  "type": "Feature",
  "properties": {
    "iso:country":"GB",
    "wof:name":"KW1 4JE",
    "wof:placetype":"postalcode"
},
  "geometry": {"coordinates":[-3.07962591936795,58.4454857867651],"type":"Point"}
}