{
  "type": "Feature",
  "properties": {
    "iso:country":"GB",
    "wof:name":"GU15 3BH",
    "wof:placetype":"postalcode"
},
  "geometry": {"coordinates":[-0.76335012944078,51.33366035836639],"type":"Point"}
}