{
  "type": "Feature",
  "properties": {
    "iso:country":"GB",
    "wof:name":"NR5 8YJ",
    "wof:placetype":"postalcode"
},
  "geometry": {"coordinates":[1.23813944588186,52.64096708746528],"type":"Point"}
}