{
  "type": "Feature",
  "properties": {
    "iso:country":"GB",
    "wof:name":"CA13 0YX",
    "wof:placetype":"postalcode"
},
  "geometry": {"coordinates":[-3.43932262237135,54.67090739430819],"type":"Point"}
}