{
  "type": "Feature",
  "properties": {
    "date:inception_lower": "1995-01-01",
    "date:inception_upper": "1995-01-01",
    "iso:country": "GB",
    "wof:name": "CA13 0YX",
    "wof:placetype": "postalcode"
  },
  "geometry": {"coordinates":[-3.440191,54.671335],"type":"Point"}
}
