{
  "type": "Feature",
  "properties": {
    "iso:country":"GB",
    "wof:name":"MK46 5AN",
    "wof:placetype":"postalcode"
},
  "geometry": {"coordinates":[-0.75750687622207,52.15167952536534],"type":"Point"}
}