{
  "type": "Feature",
  "properties": {
    "date:inception_lower": "1980-01-01",
    "date:inception_upper": "1980-01-01",
    "iso:country": "GB",
    "wof:name": "MK46 5AN",
    "wof:placetype": "postalcode"
  },
  "geometry": {"coordinates":[-0.757507,52.15168],"type":"Point"}
}
