{
  "type": "Feature",
  "properties": {
    "iso:country":"GB",
    "wof:name":"TS24 0RY",
    "wof:placetype":"postalcode"
},
  "geometry": {"coordinates":[-1.19096058058916,54.69485095281876],"type":"Point"}
}