{
  "type": "Feature",
  "properties": {
    "iso:country": "GB",
    "wof:name": "TS24 0RY",
    "wof:placetype": "postalcode"
  },
  "geometry": {"coordinates":[-1.190961,54.694851],"type":"Point"}
}
