{
  "type": "Feature",
  "properties": {
    "iso:country":"GB",
    "wof:name":"CM1 7BW",
    "wof:placetype":"postalcode"
},
  "geometry": {"coordinates":[0.46971387565092,51.77296652821828],"type":"Point"}
}