{
  "type": "Feature",
  "properties": {
    "iso:country": "GB",
    "wof:name": "CM1 7BW",
    "wof:placetype": "postalcode"
  },
  "geometry": {"coordinates":[0.469714,51.772967],"type":"Point"}
}
