{
  "type": "Feature",
  "properties": {
    "iso:country":"GB",
    "wof:name":"WS2 9UW",
    "wof:placetype":"postalcode"
},
  "geometry": {"coordinates":[-2.00808799637388,52.57923722265789],"type":"Point"}
}