{
  "type": "Feature",
  "properties": {
    "iso:country":"GB",
    "wof:name":"FY3 0BA",
    "wof:placetype":"postalcode"
},
  "geometry": {"coordinates":[-2.9979801774798,53.82344763758935],"type":"Point"}
}