{
  "type": "Feature",
  "properties": {
    "iso:country":"GB",
    "wof:name":"EH16 5LL",
    "wof:placetype":"postalcode"
},
  "geometry": {"coordinates":[-3.15504203851096,55.93186970469048],"type":"Point"}
}