{
  "type": "Feature",
  "properties": {
    "date:inception_lower": "1980-01-01",
    "date:inception_upper": "1980-01-01",
    "iso:country": "GB",
    "wof:name": "TS7 8PL",
    "wof:placetype": "postalcode"
  },
  "geometry": {"coordinates":[-1.187958,54.526405],"type":"Point"}
}
