{
  "type": "Feature",
  "properties": {
    "iso:country":"GB",
    "wof:name":"M25 9RB",
    "wof:placetype":"postalcode"
},
  "geometry": {"coordinates":[-2.28548942769903,53.52314570513347],"type":"Point"}
}