{
  "type": "Feature",
  "properties": {
    "iso:country":"GB",
    "wof:name":"FK7 7QR",
    "wof:placetype":"postalcode"
},
  "geometry": {"coordinates":[-3.92634697282804,56.10648963949556],"type":"Point"}
}