{
  "type": "Feature",
  "properties": {
    "date:inception_lower":"1980-01-01",
    "date:inception_upper":"1980-01-31",
    "iso:country":"GB",
    "wof:name":"FK7 7QR",
    "wof:placetype":"postalcode"
},
  "geometry": {"coordinates":[-3.926347,56.10649],"type":"Point"}
}