{
  "type": "Feature",
  "properties": {
    "iso:country":"GB",
    "wof:name":"DH7 7PS",
    "wof:placetype":"postalcode"
},
  "geometry": {"coordinates":[-1.64825566355986,54.77840439802198],"type":"Point"}
}