{
  "type": "Feature",
  "properties": {
    "iso:country": "GB",
    "wof:name": "DN16 3HG",
    "wof:placetype": "postalcode"
  },
  "geometry": {"coordinates":[-0.645192,53.561694],"type":"Point"}
}
