{
  "type": "Feature",
  "properties": {
    "iso:country":"GB",
    "wof:name":"AB24 4PW",
    "wof:placetype":"postalcode"
},
  "geometry": {"coordinates":[-2.1395666648004,57.16980428061066],"type":"Point"}
}