{
  "type": "Feature",
  "properties": {
    "date:inception_lower": "1980-01-01",
    "date:inception_upper": "1980-01-01",
    "iso:country": "GB",
    "wof:name": "GL50 4BY",
    "wof:placetype": "postalcode"
  },
  "geometry": {"coordinates":[-2.080582,51.90943],"type":"Point"}
}
