{
  "type": "Feature",
  "properties": {
    "iso:country":"GB",
    "wof:name":"N13 5EW",
    "wof:placetype":"postalcode"
},
  "geometry": {"coordinates":[-0.09072845996249,51.61739123951011],"type":"Point"}
}