{
  "type": "Feature",
  "properties": {
    "date:inception_lower":"2010-06-01",
    "date:inception_upper":"2010-06-30",
    "iso:country":"GB",
    "wof:name":"IP14 5TU",
    "wof:placetype":"postalcode"
},
  "geometry": {"coordinates":[1.011575,52.190289],"type":"Point"}
}