{
  "type": "Feature",
  "properties": {
    "date:inception_lower": "2010-06-01",
    "date:inception_upper": "2010-06-01",
    "iso:country": "GB",
    "wof:name": "IP14 5TU",
    "wof:placetype": "postalcode"
  },
  "geometry": {"coordinates":[1.011592,52.190305],"type":"Point"}
}
