{
  "type": "Feature",
  "properties": {
    "iso:country": "GB",
    "wof:name": "PO10 8RH",
    "wof:placetype": "postalcode"
  },
  "geometry": {"coordinates":[-0.907296,50.868304],"type":"Point"}
}
