{
  "type": "Feature",
  "properties": {
    "iso:country":"GB",
    "wof:name":"PO10 8RH",
    "wof:placetype":"postalcode"
},
  "geometry": {"coordinates":[-0.9077294272952,50.86808291677769],"type":"Point"}
}