{
  "type": "Feature",
  "properties": {
    "date:inception_lower": "1980-01-01",
    "date:inception_upper": "1980-01-01",
    "iso:country": "GB",
    "wof:name": "PO10 8RH",
    "wof:placetype": "postalcode"
  },
  "geometry": {"coordinates":[-0.907714,50.868074],"type":"Point"}
}
