{
  "type": "Feature",
  "properties": {
    "iso:country": "GB",
    "wof:name": "TA21 8HP",
    "wof:placetype": "postalcode"
  },
  "geometry": {"coordinates":[-3.229283,50.980617],"type":"Point"}
}
