{
  "type": "Feature",
  "properties": {
    "iso:country":"GB",
    "wof:name":"TA21 8HP",
    "wof:placetype":"postalcode"
},
  "geometry": {"coordinates":[-3.22928348947805,50.98061744512623],"type":"Point"}
}