{
  "type": "Feature",
  "properties": {
    "iso:country":"GB",
    "wof:name":"PE12 6TT",
    "wof:placetype":"postalcode"
},
  "geometry": {"coordinates":[-0.02486859924497,52.80049951016333],"type":"Point"}
}