{
  "type": "Feature",
  "properties": {
    "iso:country":"GB",
    "wof:name":"WR15 8JG",
    "wof:placetype":"postalcode"
},
  "geometry": {"coordinates":[-2.48532543550652,52.32090971900299],"type":"Point"}
}