{
  "type": "Feature",
  "properties": {
    "iso:country":"GB",
    "wof:name":"PE31 6DF",
    "wof:placetype":"postalcode"
},
  "geometry": {"coordinates":[0.55038464656001,52.79952582289873],"type":"Point"}
}