{
  "type": "Feature",
  "properties": {
    "date:inception_lower": "1987-04-01",
    "date:inception_upper": "1987-04-01",
    "iso:country": "GB",
    "wof:name": "PE31 6DF",
    "wof:placetype": "postalcode"
  },
  "geometry": {"coordinates":[0.550385,52.799526],"type":"Point"}
}
