{
  "type": "Feature",
  "properties": {
    "iso:country": "GB",
    "wof:name": "PE31 6DF",
    "wof:placetype": "postalcode"
  },
  "geometry": {"coordinates":[0.550385,52.799526],"type":"Point"}
}
