{
  "type": "Feature",
  "properties": {
    "iso:country": "GB",
    "wof:name": "PE29 2HW",
    "wof:placetype": "postalcode"
  },
  "geometry": {"coordinates":[-0.175677,52.316482],"type":"Point"}
}
