{
  "type": "Feature",
  "properties": {
    "date:inception_lower": "2000-06-01",
    "date:inception_upper": "2000-06-01",
    "iso:country": "GB",
    "wof:name": "PE29 2HW",
    "wof:placetype": "postalcode"
  },
  "geometry": {"coordinates":[-0.175677,52.316482],"type":"Point"}
}
