{
  "type": "Feature",
  "properties": {
    "iso:country":"GB",
    "wof:name":"IP28 6EU",
    "wof:placetype":"postalcode"
},
  "geometry": {"coordinates":[0.66881059911136,52.3023928980432],"type":"Point"}
}