{
  "type": "Feature",
  "properties": {
    "date:inception_lower":"1980-01-01",
    "date:inception_upper":"1980-01-31",
    "iso:country":"GB",
    "wof:name":"IP28 6EU",
    "wof:placetype":"postalcode"
},
  "geometry": {"coordinates":[0.668811,52.302393],"type":"Point"}
}