{
  "type": "Feature",
  "properties": {
    "iso:country": "GB",
    "wof:name": "LE9 7FJ",
    "wof:placetype": "postalcode"
  },
  "geometry": {"coordinates":[-1.318589,52.572766],"type":"Point"}
}
