{
  "type": "Feature",
  "properties": {
    "iso:country":"GB",
    "wof:name":"LE9 7FJ",
    "wof:placetype":"postalcode"
},
  "geometry": {"coordinates":[-1.31858912375161,52.57276565698969],"type":"Point"}
}