{
  "type": "Feature",
  "properties": {
    "iso:country":"GB",
    "wof:name":"TW15 1NH",
    "wof:placetype":"postalcode"
},
  "geometry": {"coordinates":[-0.4415301875615,51.42751406751698],"type":"Point"}
}