{
  "type": "Feature",
  "properties": {
    "date:inception_lower":"2006-10-01",
    "date:inception_upper":"2006-10-31",
    "iso:country":"GB",
    "wof:name":"EX23 8FG",
    "wof:placetype":"postalcode"
},
  "geometry": {"coordinates":[-4.531217,50.829972],"type":"Point"}
}