{
  "type": "Feature",
  "properties": {
    "iso:country":"GB",
    "wof:name":"RH13 8BF",
    "wof:placetype":"postalcode"
},
  "geometry": {"coordinates":[-0.25958848987355,50.97984565546383],"type":"Point"}
}