{
  "type": "Feature",
  "properties": {
    "iso:country": "GB",
    "wof:name": "RH13 8BF",
    "wof:placetype": "postalcode"
  },
  "geometry": {"coordinates":[-0.259588,50.979846],"type":"Point"}
}
