{
  "type": "Feature",
  "properties": {
    "iso:country":"GB",
    "wof:name":"RG7 5XB",
    "wof:placetype":"postalcode"
},
  "geometry": {"coordinates":[-1.19888380662654,51.39843969148478],"type":"Point"}
}