{
  "type": "Feature",
  "properties": {
    "date:inception_lower":"1996-06-01",
    "date:inception_upper":"1996-06-30",
    "iso:country":"GB",
    "wof:name":"NE61 6TQ",
    "wof:placetype":"postalcode"
},
  "geometry": {"coordinates":[-1.650453,55.182738],"type":"Point"}
}