{
  "type": "Feature",
  "properties": {
    "iso:country": "GB",
    "wof:name": "NE61 6TQ",
    "wof:placetype": "postalcode"
  },
  "geometry": {"coordinates":[-1.650453,55.182738],"type":"Point"}
}
