{
  "type": "Feature",
  "properties": {
    "iso:country": "GB",
    "wof:name": "SW17 7BG",
    "wof:placetype": "postalcode"
  },
  "geometry": {"coordinates":[-0.156327,51.437799],"type":"Point"}
}
