{
  "type": "Feature",
  "properties": {
    "iso:country":"GB",
    "wof:name":"CR0 7QG",
    "wof:placetype":"postalcode"
},
  "geometry": {"coordinates":[-0.04269085874419,51.38385258441359],"type":"Point"}
}