{
  "type": "Feature",
  "properties": {
    "iso:country": "GB",
    "wof:name": "AB42 3JW",
    "wof:placetype": "postalcode"
  },
  "geometry": {"coordinates":[-1.822527,57.502572],"type":"Point"}
}
