{
  "type": "Feature",
  "properties": {
    "date:inception_lower":"1997-12-01",
    "date:inception_upper":"1997-12-31",
    "iso:country":"GB",
    "wof:name":"MK43 0PB",
    "wof:placetype":"postalcode"
},
  "geometry": {"coordinates":[-0.559615,52.039232],"type":"Point"}
}