{
  "type": "Feature",
  "properties": {
    "date:inception_lower": "1980-01-01",
    "date:inception_upper": "1980-01-01",
    "iso:country": "GB",
    "wof:name": "SY5 0LT",
    "wof:placetype": "postalcode"
  },
  "geometry": {"coordinates":[-2.930408,52.610867],"type":"Point"}
}
