{
  "type": "Feature",
  "properties": {
    "iso:country":"GB",
    "wof:name":"KY1 4PL",
    "wof:placetype":"postalcode"
},
  "geometry": {"coordinates":[-3.06045615493192,56.16514912497004],"type":"Point"}
}