{
  "type": "Feature",
  "properties": {
    "iso:country":"GB",
    "wof:name":"KA7 2PQ",
    "wof:placetype":"postalcode"
},
  "geometry": {"coordinates":[-4.61888933866007,55.44677560675125],"type":"Point"}
}