{
  "type": "Feature",
  "properties": {
    "date:inception_lower": "1980-01-01",
    "date:inception_upper": "1980-01-01",
    "iso:country": "GB",
    "wof:name": "KA7 2PQ",
    "wof:placetype": "postalcode"
  },
  "geometry": {"coordinates":[-4.618889,55.446776],"type":"Point"}
}
