{
  "type": "Feature",
  "properties": {
    "date:inception_lower": "1980-01-01",
    "date:inception_upper": "1980-01-01",
    "iso:country": "GB",
    "wof:name": "CV35 8BX",
    "wof:placetype": "postalcode"
  },
  "geometry": {"coordinates":[-1.600288,52.24833],"type":"Point"}
}
