{
  "type": "Feature",
  "properties": {
    "iso:country": "GB",
    "wof:name": "CV35 8BX",
    "wof:placetype": "postalcode"
  },
  "geometry": {"coordinates":[-1.600288,52.24833],"type":"Point"}
}
