{
  "type": "Feature",
  "properties": {
    "iso:country": "GB",
    "wof:name": "MK42 7FY",
    "wof:placetype": "postalcode"
  },
  "geometry": {"coordinates":[-0.507061,52.104629],"type":"Point"}
}
