{
  "type": "Feature",
  "properties": {
    "date:inception_lower": "2013-05-01",
    "date:inception_upper": "2013-05-01",
    "iso:country": "GB",
    "wof:name": "MK42 7FY",
    "wof:placetype": "postalcode"
  },
  "geometry": {"coordinates":[-0.508587,52.105082],"type":"Point"}
}
