{
  "type": "Feature",
  "properties": {
    "date:inception_lower": "1980-01-01",
    "date:inception_upper": "1980-01-01",
    "iso:country": "GB",
    "wof:name": "SA43 2LT",
    "wof:placetype": "postalcode"
  },
  "geometry": {"coordinates":[-4.589795,52.07454],"type":"Point"}
}
