{
  "type": "Feature",
  "properties": {
    "iso:country":"GB",
    "wof:name":"SA43 2LT",
    "wof:placetype":"postalcode"
},
  "geometry": {"coordinates":[-4.58979480171844,52.07454007170418],"type":"Point"}
}