{
  "type": "Feature",
  "properties": {
    "iso:country": "GB",
    "wof:name": "SA43 2LT",
    "wof:placetype": "postalcode"
  },
  "geometry": {"coordinates":[-4.589795,52.07454],"type":"Point"}
}
