{
  "type": "Feature",
  "properties": {
    "iso:country":"GB",
    "wof:name":"NE5 3SG",
    "wof:placetype":"postalcode"
},
  "geometry": {"coordinates":[-1.67277344779296,54.99970835542638],"type":"Point"}
}