{
  "type": "Feature",
  "properties": {
    "iso:country":"GB",
    "wof:name":"OL11 4NW",
    "wof:placetype":"postalcode"
},
  "geometry": {"coordinates":[-2.17387261414248,53.60404850978608],"type":"Point"}
}