{
  "type": "Feature",
  "properties": {
    "iso:country": "GB",
    "wof:name": "AL4 9PS",
    "wof:placetype": "postalcode"
  },
  "geometry": {"coordinates":[-0.310894,51.769449],"type":"Point"}
}
