{
  "type": "Feature",
  "properties": {
    "iso:country": "GB",
    "wof:name": "CV13 0LW",
    "wof:placetype": "postalcode"
  },
  "geometry": {"coordinates":[-1.397585,52.622656],"type":"Point"}
}
