{
  "type": "Feature",
  "properties": {
    "date:inception_lower": "2020-05-01",
    "date:inception_upper": "2020-05-01",
    "iso:country": "GB",
    "wof:name": "SA1 8FD",
    "wof:placetype": "postalcode"
  },
  "geometry": {"coordinates":[-3.925972,51.62099],"type":"Point"}
}
