{
  "type": "Feature",
  "properties": {
    "date:inception_lower":"1999-06-01",
    "date:inception_upper":"1999-06-30",
    "iso:country":"GB",
    "wof:name":"B79 7YJ",
    "wof:placetype":"postalcode"
},
  "geometry": {"coordinates":[-1.715285,52.636583],"type":"Point"}
}