{
  "type": "Feature",
  "properties": {
    "iso:country":"GB",
    "wof:name":"B79 7YJ",
    "wof:placetype":"postalcode"
},
  "geometry": {"coordinates":[-1.71528524530801,52.63658339862243],"type":"Point"}
}