{
  "type": "Feature",
  "properties": {
    "iso:country": "GB",
    "wof:name": "HA0 2EY",
    "wof:placetype": "postalcode"
  },
  "geometry": {"coordinates":[-0.310217,51.551446],"type":"Point"}
}
