{
  "type": "Feature",
  "properties": {
    "iso:country":"GB",
    "wof:name":"HA0 2EY",
    "wof:placetype":"postalcode"
},
  "geometry": {"coordinates":[-0.310257548158,51.55137239492299],"type":"Point"}
}