{
  "type": "Feature",
  "properties": {
    "date:inception_lower": "2017-10-01",
    "date:inception_upper": "2017-10-01",
    "iso:country": "GB",
    "wof:name": "TS14 7FB",
    "wof:placetype": "postalcode"
  },
  "geometry": {"coordinates":[-1.052361,54.53095],"type":"Point"}
}
