{
  "type": "Feature",
  "properties": {
    "iso:country":"GB",
    "wof:name":"SE21 8PQ",
    "wof:placetype":"postalcode"
},
  "geometry": {"coordinates":[-0.08250256884522,51.43121909788491],"type":"Point"}
}