{
  "type": "Feature",
  "properties": {
    "iso:country":"GB",
    "wof:name":"DE21 6UJ",
    "wof:placetype":"postalcode"
},
  "geometry": {"coordinates":[-1.42293410692694,52.92987694300152],"type":"Point"}
}