{
  "type": "Feature",
  "properties": {
    "iso:country":"GB",
    "wof:name":"B69 1QU",
    "wof:placetype":"postalcode"
},
  "geometry": {"coordinates":[-2.0444610288774,52.5029860260509],"type":"Point"}
}