{
  "type": "Feature",
  "properties": {
    "date:inception_lower": "1980-01-01",
    "date:inception_upper": "1980-01-01",
    "iso:country": "GB",
    "wof:name": "BN6 8DQ",
    "wof:placetype": "postalcode"
  },
  "geometry": {"coordinates":[-0.133698,50.92825],"type":"Point"}
}
