{
  "type": "Feature",
  "properties": {
    "iso:country":"GB",
    "wof:name":"BN6 8DQ",
    "wof:placetype":"postalcode"
},
  "geometry": {"coordinates":[-0.13369845641425,50.92825001121467],"type":"Point"}
}