{
  "type": "Feature",
  "properties": {
    "date:inception_lower":"1980-01-01",
    "date:inception_upper":"1980-01-31",
    "iso:country":"GB",
    "wof:name":"PR5 5LA",
    "wof:placetype":"postalcode"
},
  "geometry": {"coordinates":[-2.693801,53.724117],"type":"Point"}
}