{
  "type": "Feature",
  "properties": {
    "iso:country":"GB",
    "wof:name":"LL31 9DZ",
    "wof:placetype":"postalcode"
},
  "geometry": {"coordinates":[-3.82765705969983,53.29375499511024],"type":"Point"}
}