{
  "type": "Feature",
  "properties": {
    "date:inception_lower":"2008-07-01",
    "date:inception_upper":"2008-07-31",
    "iso:country":"GB",
    "wof:name":"HP12 4BQ",
    "wof:placetype":"postalcode"
},
  "geometry": {"coordinates":[-0.775127,51.615718],"type":"Point"}
}