{
  "type": "Feature",
  "properties": {
    "iso:country": "GB",
    "wof:name": "HP12 4BQ",
    "wof:placetype": "postalcode"
  },
  "geometry": {"coordinates":[-0.775127,51.615718],"type":"Point"}
}
