{
  "type": "Feature",
  "properties": {
    "iso:country":"GB",
    "wof:name":"HP12 4BQ",
    "wof:placetype":"postalcode"
},
  "geometry": {"coordinates":[-0.77512699379684,51.61571802840717],"type":"Point"}
}