{
  "type": "Feature",
  "properties": {
    "iso:country": "GB",
    "wof:name": "NE65 0BW",
    "wof:placetype": "postalcode"
  },
  "geometry": {"coordinates":[-1.580049,55.3339],"type":"Point"}
}
