{
  "type": "Feature",
  "properties": {
    "iso:country":"GB",
    "wof:name":"NE65 0BW",
    "wof:placetype":"postalcode"
},
  "geometry": {"coordinates":[-1.58004921742012,55.33390038540111],"type":"Point"}
}