{
  "type": "Feature",
  "properties": {
    "date:inception_lower": "1980-01-01",
    "date:inception_upper": "1980-01-01",
    "iso:country": "GB",
    "wof:name": "CO4 5NE",
    "wof:placetype": "postalcode"
  },
  "geometry": {"coordinates":[0.933529,51.931314],"type":"Point"}
}
