{
  "type": "Feature",
  "properties": {
    "iso:country":"GB",
    "wof:name":"CO4 5NE",
    "wof:placetype":"postalcode"
},
  "geometry": {"coordinates":[0.93431060411254,51.93105754741617],"type":"Point"}
}