{
  "type": "Feature",
  "properties": {
    "date:inception_lower": "2016-10-01",
    "date:inception_upper": "2016-10-01",
    "iso:country": "GB",
    "wof:name": "EC1Y 8AF",
    "wof:placetype": "postalcode"
  },
  "geometry": {"coordinates":[-0.088321,51.525145],"type":"Point"}
}
