{
  "type": "Feature",
  "properties": {
    "iso:country":"GB",
    "wof:name":"TN34 2HL",
    "wof:placetype":"postalcode"
},
  "geometry": {"coordinates":[0.57520198697297,50.87249894738427],"type":"Point"}
}