{
  "type": "Feature",
  "properties": {
    "iso:country":"GB",
    "wof:name":"NN3 8TB",
    "wof:placetype":"postalcode"
},
  "geometry": {"coordinates":[-0.82295941577734,52.26132879748546],"type":"Point"}
}