{
  "type": "Feature",
  "properties": {
    "iso:country":"GB",
    "wof:name":"DA16 1DA",
    "wof:placetype":"postalcode"
},
  "geometry": {"coordinates":[0.12006224597178,51.4722897657365],"type":"Point"}
}