{
  "type": "Feature",
  "properties": {
    "iso:country": "GB",
    "wof:name": "DA16 1DA",
    "wof:placetype": "postalcode"
  },
  "geometry": {"coordinates":[0.120062,51.47229],"type":"Point"}
}
