{
  "type": "Feature",
  "properties": {
    "iso:country":"GB",
    "wof:name":"ZE2 9HJ",
    "wof:placetype":"postalcode"
},
  "geometry": {"coordinates":[-1.24777226254398,60.00105744186234],"type":"Point"}
}