{
  "type": "Feature",
  "properties": {
    "iso:country": "GB",
    "wof:name": "CT9 1QU",
    "wof:placetype": "postalcode"
  },
  "geometry": {"coordinates":[1.385729,51.387557],"type":"Point"}
}
