{
  "type": "Feature",
  "properties": {
    "iso:country":"GB",
    "wof:name":"CT9 1QU",
    "wof:placetype":"postalcode"
},
  "geometry": {"coordinates":[1.38573336333534,51.38758545443378],"type":"Point"}
}