{
  "type": "Feature",
  "properties": {
    "iso:country":"GB",
    "wof:name":"CF33 6BH",
    "wof:placetype":"postalcode"
},
  "geometry": {"coordinates":[-3.69092111307021,51.52780596758721],"type":"Point"}
}