{
  "type": "Feature",
  "properties": {
    "iso:country": "GB",
    "wof:name": "E14 0TB",
    "wof:placetype": "postalcode"
  },
  "geometry": {"coordinates":[-0.003732,51.512837],"type":"Point"}
}
