{
  "type": "Feature",
  "properties": {
    "iso:country": "GB",
    "wof:name": "RH16 4NS",
    "wof:placetype": "postalcode"
  },
  "geometry": {"coordinates":[-0.100309,50.995404],"type":"Point"}
}
