{
  "type": "Feature",
  "properties": {
    "iso:country":"GB",
    "wof:name":"RH16 4NS",
    "wof:placetype":"postalcode"
},
  "geometry": {"coordinates":[-0.10030903833572,50.99540417016558],"type":"Point"}
}