{
  "type": "Feature",
  "properties": {
    "iso:country":"GB",
    "wof:name":"OX18 4SJ",
    "wof:placetype":"postalcode"
},
  "geometry": {"coordinates":[-1.63642683497787,51.80725531689766],"type":"Point"}
}