{
  "type": "Feature",
  "properties": {
    "iso:country":"GB",
    "wof:name":"N6 5BQ",
    "wof:placetype":"postalcode"
},
  "geometry": {"coordinates":[-0.14244623778056,51.57057032731571],"type":"Point"}
}