{
  "type": "Feature",
  "properties": {
    "date:inception_lower":"2010-08-01",
    "date:inception_upper":"2010-08-31",
    "iso:country":"GB",
    "wof:name":"N6 5BQ",
    "wof:placetype":"postalcode"
},
  "geometry": {"coordinates":[-0.142446,51.57057],"type":"Point"}
}