{
  "type": "Feature",
  "properties": {
    "date:inception_lower": "2000-12-01",
    "date:inception_upper": "2000-12-01",
    "iso:country": "GB",
    "wof:name": "L7 7JF",
    "wof:placetype": "postalcode"
  },
  "geometry": {"coordinates":[-2.968448,53.402807],"type":"Point"}
}
