{
  "type": "Feature",
  "properties": {
    "iso:country": "GB",
    "wof:name": "L7 7JF",
    "wof:placetype": "postalcode"
  },
  "geometry": {"coordinates":[-2.968448,53.402807],"type":"Point"}
}
