{
  "type": "Feature",
  "properties": {
    "iso:country":"GB",
    "wof:name":"NR25 6EQ",
    "wof:placetype":"postalcode"
},
  "geometry": {"coordinates":[1.10236719247526,52.90840455689428],"type":"Point"}
}