{
  "type": "Feature",
  "properties": {
    "date:inception_lower": "1980-01-01",
    "date:inception_upper": "1980-01-01",
    "iso:country": "GB",
    "wof:name": "NR25 6EQ",
    "wof:placetype": "postalcode"
  },
  "geometry": {"coordinates":[1.102384,52.908423],"type":"Point"}
}
