{
  "type": "Feature",
  "properties": {
    "iso:country":"GB",
    "wof:name":"NE26 4DW",
    "wof:placetype":"postalcode"
},
  "geometry": {"coordinates":[-1.4740945142474,55.08163158687426],"type":"Point"}
}