{
  "type": "Feature",
  "properties": {
    "date:inception_lower": "1981-09-01",
    "date:inception_upper": "1981-09-01",
    "iso:country": "GB",
    "wof:name": "N12 8AZ",
    "wof:placetype": "postalcode"
  },
  "geometry": {"coordinates":[-0.180803,51.620489],"type":"Point"}
}
