{
  "type": "Feature",
  "properties": {
    "iso:country": "GB",
    "wof:name": "N12 8AZ",
    "wof:placetype": "postalcode"
  },
  "geometry": {"coordinates":[-0.181145,51.620527],"type":"Point"}
}
