{
  "type": "Feature",
  "properties": {
    "iso:country":"GB",
    "wof:name":"B29 6AW",
    "wof:placetype":"postalcode"
},
  "geometry": {"coordinates":[-1.9346161601757,52.44634875579453],"type":"Point"}
}