{
  "type": "Feature",
  "properties": {
    "iso:country": "GB",
    "wof:name": "DE22 2SD",
    "wof:placetype": "postalcode"
  },
  "geometry": {"coordinates":[-1.488818,52.951708],"type":"Point"}
}
