{
  "type": "Feature",
  "properties": {
    "iso:country":"GB",
    "wof:name":"YO22 4SA",
    "wof:placetype":"postalcode"
},
  "geometry": {"coordinates":[-0.53321620313132,54.43160808030658],"type":"Point"}
}