{
  "type": "Feature",
  "properties": {
    "iso:country":"GB",
    "wof:name":"B64 5LG",
    "wof:placetype":"postalcode"
},
  "geometry": {"coordinates":[-2.07664389234196,52.47417468755425],"type":"Point"}
}