{
  "type": "Feature",
  "properties": {
    "date:inception_lower": "1999-12-01",
    "date:inception_upper": "1999-12-01",
    "iso:country": "GB",
    "wof:name": "B64 5LG",
    "wof:placetype": "postalcode"
  },
  "geometry": {"coordinates":[-2.076644,52.474175],"type":"Point"}
}
