{
  "type": "Feature",
  "properties": {
    "iso:country": "GB",
    "wof:name": "NP10 8SQ",
    "wof:placetype": "postalcode"
  },
  "geometry": {"coordinates":[-3.023177,51.534174],"type":"Point"}
}
