{
  "type": "Feature",
  "properties": {
    "iso:country":"GB",
    "wof:name":"NP10 8SQ",
    "wof:placetype":"postalcode"
},
  "geometry": {"coordinates":[-3.02317728823004,51.53417439601526],"type":"Point"}
}