{
  "type": "Feature",
  "properties": {
    "iso:country":"GB",
    "wof:name":"TW14 0DW",
    "wof:placetype":"postalcode"
},
  "geometry": {"coordinates":[-0.39561545325474,51.45254078257508],"type":"Point"}
}