{
  "type": "Feature",
  "properties": {
    "date:inception_lower": "1980-01-01",
    "date:inception_upper": "1980-01-01",
    "iso:country": "GB",
    "wof:name": "TW14 0DW",
    "wof:placetype": "postalcode"
  },
  "geometry": {"coordinates":[-0.395615,51.452541],"type":"Point"}
}
