{
  "type": "Feature",
  "properties": {
    "date:inception_lower":"2002-06-01",
    "date:inception_upper":"2002-06-30",
    "iso:country":"GB",
    "wof:name":"CO4 0QG",
    "wof:placetype":"postalcode"
},
  "geometry": {"coordinates":[0.926355,51.900462],"type":"Point"}
}