{
  "type": "Feature",
  "properties": {
    "iso:country":"GB",
    "wof:name":"CO4 0QG",
    "wof:placetype":"postalcode"
},
  "geometry": {"coordinates":[0.92635458907389,51.90046156876907],"type":"Point"}
}