{
  "type": "Feature",
  "properties": {
    "iso:country": "GB",
    "wof:name": "OL4 3SA",
    "wof:placetype": "postalcode"
  },
  "geometry": {"coordinates":[-2.050104,53.552788],"type":"Point"}
}
