{
  "type": "Feature",
  "properties": {
    "date:inception_lower": "1980-01-01",
    "date:inception_upper": "1980-01-01",
    "iso:country": "GB",
    "wof:name": "OL4 3SA",
    "wof:placetype": "postalcode"
  },
  "geometry": {"coordinates":[-2.050104,53.552788],"type":"Point"}
}
