{
  "type": "Feature",
  "properties": {
    "iso:country":"GB",
    "wof:name":"OL4 3SA",
    "wof:placetype":"postalcode"
},
  "geometry": {"coordinates":[-2.05010357812566,53.55278754578684],"type":"Point"}
}