{
  "type": "Feature",
  "properties": {
    "date:inception_lower": "1980-01-01",
    "date:inception_upper": "1980-01-01",
    "iso:country": "GB",
    "wof:name": "TW14 0BB",
    "wof:placetype": "postalcode"
  },
  "geometry": {"coordinates":[-0.40436,51.455187],"type":"Point"}
}
