{
  "type": "Feature",
  "properties": {
    "iso:country":"GB",
    "wof:name":"CR5 1AT",
    "wof:placetype":"postalcode"
},
  "geometry": {"coordinates":[-0.14501575993643,51.30702874761077],"type":"Point"}
}