{
  "type": "Feature",
  "properties": {
    "iso:country":"GB",
    "wof:name":"SL4 5TA",
    "wof:placetype":"postalcode"
},
  "geometry": {"coordinates":[-0.6522034746454,51.48324175571922],"type":"Point"}
}