{
  "type": "Feature",
  "properties": {
    "iso:country":"GB",
    "wof:name":"TR13 0NG",
    "wof:placetype":"postalcode"
},
  "geometry": {"coordinates":[-5.23696857430415,50.10652162023606],"type":"Point"}
}