{
  "type": "Feature",
  "properties": {
    "iso:country":"GB",
    "wof:name":"DT4 9TA",
    "wof:placetype":"postalcode"
},
  "geometry": {"coordinates":[-2.48704300114431,50.60995572047744],"type":"Point"}
}