{
  "type": "Feature",
  "properties": {
    "date:inception_lower": "1980-01-01",
    "date:inception_upper": "1980-01-01",
    "iso:country": "GB",
    "wof:name": "DT4 9TA",
    "wof:placetype": "postalcode"
  },
  "geometry": {"coordinates":[-2.487055,50.609963],"type":"Point"}
}
