{
  "type": "Feature",
  "properties": {
    "iso:country":"GB",
    "wof:name":"TN35 4LH",
    "wof:placetype":"postalcode"
},
  "geometry": {"coordinates":[0.6154954367718,50.88432952021314],"type":"Point"}
}