{
  "type": "Feature",
  "properties": {
    "iso:country":"GB",
    "wof:name":"PR4 6BD",
    "wof:placetype":"postalcode"
},
  "geometry": {"coordinates":[-2.82853679211729,53.68802594621219],"type":"Point"}
}