{
  "type": "Feature",
  "properties": {
    "date:inception_lower": "2006-01-01",
    "date:inception_upper": "2006-01-01",
    "iso:country": "GB",
    "wof:name": "BA11 2AT",
    "wof:placetype": "postalcode"
  },
  "geometry": {"coordinates":[-2.311422,51.234683],"type":"Point"}
}
