{
  "type": "Feature",
  "properties": {
    "iso:country":"GB",
    "wof:name":"BA11 2AT",
    "wof:placetype":"postalcode"
},
  "geometry": {"coordinates":[-2.31142163816244,51.23468334019191],"type":"Point"}
}