{
  "type": "Feature",
  "properties": {
    "iso:country": "GB",
    "wof:name": "DE3 0XX",
    "wof:placetype": "postalcode"
  },
  "geometry": {"coordinates":[-1.55054,52.901563],"type":"Point"}
}
