{
  "type": "Feature",
  "properties": {
    "iso:country":"GB",
    "wof:name":"DE3 0XX",
    "wof:placetype":"postalcode"
},
  "geometry": {"coordinates":[-1.55053989698246,52.90156295593031],"type":"Point"}
}