{
  "type": "Feature",
  "properties": {
    "iso:country": "GB",
    "wof:name": "PO8 0QT",
    "wof:placetype": "postalcode"
  },
  "geometry": {"coordinates":[-1.012919,50.943407],"type":"Point"}
}
