{
  "type": "Feature",
  "properties": {
    "iso:country":"GB",
    "wof:name":"UB1 2GU",
    "wof:placetype":"postalcode"
},
  "geometry": {"coordinates":[-0.37041051557086,51.53101957879328],"type":"Point"}
}