{
  "type": "Feature",
  "properties": {
    "date:inception_lower": "2007-09-01",
    "date:inception_upper": "2007-09-01",
    "iso:country": "GB",
    "wof:name": "UB1 2GU",
    "wof:placetype": "postalcode"
  },
  "geometry": {"coordinates":[-0.37041,51.53102],"type":"Point"}
}
