{
  "type": "Feature",
  "properties": {
    "date:inception_lower": "2018-11-01",
    "date:inception_upper": "2018-11-01",
    "iso:country": "GB",
    "wof:name": "SE14 6BF",
    "wof:placetype": "postalcode"
  },
  "geometry": {"coordinates":[-0.036293,51.482271],"type":"Point"}
}
