{
  "type": "Feature",
  "properties": {
    "iso:country":"GB",
    "wof:name":"PH26 3JX",
    "wof:placetype":"postalcode"
},
  "geometry": {"coordinates":[-3.61627612381113,57.32625610615164],"type":"Point"}
}