{
  "type": "Feature",
  "properties": {
    "date:inception_lower": "1980-01-01",
    "date:inception_upper": "1980-01-01",
    "iso:country": "GB",
    "wof:name": "PH26 3JX",
    "wof:placetype": "postalcode"
  },
  "geometry": {"coordinates":[-3.615543,57.326215],"type":"Point"}
}
