{
  "type": "Feature",
  "properties": {
    "iso:country":"GB",
    "wof:name":"BH6 4BA",
    "wof:placetype":"postalcode"
},
  "geometry": {"coordinates":[-1.79169102441022,50.72158896566061],"type":"Point"}
}