{
  "type": "Feature",
  "properties": {
    "iso:country":"GB",
    "wof:name":"WF12 0JE",
    "wof:placetype":"postalcode"
},
  "geometry": {"coordinates":[-1.60962164077307,53.66065080816081],"type":"Point"}
}