{
  "type": "Feature",
  "properties": {
    "date:inception_lower":"1980-01-01",
    "date:inception_upper":"1980-01-31",
    "iso:country":"GB",
    "wof:name":"WF12 0JE",
    "wof:placetype":"postalcode"
},
  "geometry": {"coordinates":[-1.609622,53.660651],"type":"Point"}
}