{
  "type": "Feature",
  "properties": {
    "iso:country": "GB",
    "wof:name": "LA11 6AA",
    "wof:placetype": "postalcode"
  },
  "geometry": {"coordinates":[-2.910463,54.193237],"type":"Point"}
}
