{
  "type": "Feature",
  "properties": {
    "date:inception_lower": "2005-10-01",
    "date:inception_upper": "2005-10-01",
    "iso:country": "GB",
    "wof:name": "LA11 6AA",
    "wof:placetype": "postalcode"
  },
  "geometry": {"coordinates":[-2.910463,54.193237],"type":"Point"}
}
