{
  "type": "Feature",
  "properties": {
    "iso:country":"GB",
    "wof:name":"SO53 1YF",
    "wof:placetype":"postalcode"
},
  "geometry": {"coordinates":[-1.39160477360926,50.99276223432398],"type":"Point"}
}