{
  "type": "Feature",
  "properties": {
    "iso:country":"GB",
    "wof:name":"NG31 9HZ",
    "wof:placetype":"postalcode"
},
  "geometry": {"coordinates":[-0.62695336833338,52.91973270858232],"type":"Point"}
}