{
  "type": "Feature",
  "properties": {
    "date:inception_lower": "2022-07-01",
    "date:inception_upper": "2022-07-01",
    "iso:country": "GB",
    "wof:name": "MK18 1ZQ",
    "wof:placetype": "postalcode"
  },
  "geometry": {"coordinates":[-1.000327,51.994687],"type":"Point"}
}
