{
  "type": "Feature",
  "properties": {
    "iso:country":"GB",
    "wof:name":"NG24 1XX",
    "wof:placetype":"postalcode"
},
  "geometry": {"coordinates":[-0.81077362551385,53.07505181850671],"type":"Point"}
}