{
  "type": "Feature",
  "properties": {
    "iso:country": "GB",
    "wof:name": "NG24 1XX",
    "wof:placetype": "postalcode"
  },
  "geometry": {"coordinates":[-0.810774,53.075052],"type":"Point"}
}
