{
  "type": "Feature",
  "properties": {
    "iso:country":"GB",
    "wof:name":"B6 7LA",
    "wof:placetype":"postalcode"
},
  "geometry": {"coordinates":[-1.87341441367214,52.50670282686041],"type":"Point"}
}