{
  "type": "Feature",
  "properties": {
    "date:inception_lower":"1980-01-01",
    "date:inception_upper":"1980-01-31",
    "iso:country":"GB",
    "wof:name":"B6 7LA",
    "wof:placetype":"postalcode"
},
  "geometry": {"coordinates":[-1.873414,52.506703],"type":"Point"}
}