{
  "type": "Feature",
  "properties": {
    "date:inception_lower": "1997-12-01",
    "date:inception_upper": "1997-12-01",
    "iso:country": "GB",
    "wof:name": "WS6 7QX",
    "wof:placetype": "postalcode"
  },
  "geometry": {"coordinates":[-2.023405,52.659388],"type":"Point"}
}
