{
  "type": "Feature",
  "properties": {
    "date:inception_lower":"1980-01-01",
    "date:inception_upper":"1980-01-31",
    "iso:country":"GB",
    "wof:name":"PL33 9EY",
    "wof:placetype":"postalcode"
},
  "geometry": {"coordinates":[-4.715946,50.600543],"type":"Point"}
}