{
  "type": "Feature",
  "properties": {
    "date:inception_lower": "1980-01-01",
    "date:inception_upper": "1980-01-01",
    "iso:country": "GB",
    "wof:name": "CO5 0QG",
    "wof:placetype": "postalcode"
  },
  "geometry": {"coordinates":[0.719204,51.806354],"type":"Point"}
}
