{
  "type": "Feature",
  "properties": {
    "iso:country": "GB",
    "wof:name": "CO5 0QG",
    "wof:placetype": "postalcode"
  },
  "geometry": {"coordinates":[0.719204,51.806354],"type":"Point"}
}
