{
  "type": "Feature",
  "properties": {
    "iso:country":"GB",
    "wof:name":"CO5 0QG",
    "wof:placetype":"postalcode"
},
  "geometry": {"coordinates":[0.71920410947592,51.8063539136294],"type":"Point"}
}