{
  "type": "Feature",
  "properties": {
    "iso:country":"GB",
    "wof:name":"SY1 3XT",
    "wof:placetype":"postalcode"
},
  "geometry": {"coordinates":[-2.74920498409576,52.72784225581078],"type":"Point"}
}