{
  "type": "Feature",
  "properties": {
    "iso:country": "GB",
    "wof:name": "SY1 3XT",
    "wof:placetype": "postalcode"
  },
  "geometry": {"coordinates":[-2.749205,52.727842],"type":"Point"}
}
