{
  "type": "Feature",
  "properties": {
    "iso:country":"GB",
    "wof:name":"BB7 2QA",
    "wof:placetype":"postalcode"
},
  "geometry": {"coordinates":[-2.40294986465948,53.86609277687074],"type":"Point"}
}