{
  "type": "Feature",
  "properties": {
    "date:inception_lower":"1980-01-01",
    "date:inception_upper":"1980-01-31",
    "iso:country":"GB",
    "wof:name":"BB7 2QA",
    "wof:placetype":"postalcode"
},
  "geometry": {"coordinates":[-2.40295,53.866093],"type":"Point"}
}