{
  "type": "Feature",
  "properties": {
    "date:inception_lower": "1997-06-01",
    "date:inception_upper": "1997-06-01",
    "iso:country": "GB",
    "wof:name": "KT22 8BB",
    "wof:placetype": "postalcode"
  },
  "geometry": {"coordinates":[-0.326007,51.293156],"type":"Point"}
}
