{
  "type": "Feature",
  "properties": {
    "iso:country":"GB",
    "wof:name":"KT22 8BB",
    "wof:placetype":"postalcode"
},
  "geometry": {"coordinates":[-0.32600745597724,51.29315562363296],"type":"Point"}
}