{
  "type": "Feature",
  "properties": {
    "iso:country":"GB",
    "wof:name":"RH6 7PA",
    "wof:placetype":"postalcode"
},
  "geometry": {"coordinates":[-0.16265810963703,51.16367283782674],"type":"Point"}
}