{
  "type": "Feature",
  "properties": {
    "iso:country":"GB",
    "wof:name":"BS24 7GW",
    "wof:placetype":"postalcode"
},
  "geometry": {"coordinates":[-2.8971306991998,51.33471586981306],"type":"Point"}
}