{
  "type": "Feature",
  "properties": {
    "date:inception_lower":"2013-07-01",
    "date:inception_upper":"2013-07-31",
    "iso:country":"GB",
    "wof:name":"BS24 7GW",
    "wof:placetype":"postalcode"
},
  "geometry": {"coordinates":[-2.896894,51.334796],"type":"Point"}
}