{
  "type": "Feature",
  "properties": {
    "iso:country":"GB",
    "wof:name":"KY2 6XF",
    "wof:placetype":"postalcode"
},
  "geometry": {"coordinates":[-3.18326847010651,56.14132866124425],"type":"Point"}
}