{
  "type": "Feature",
  "properties": {
    "date:inception_lower": "2016-11-01",
    "date:inception_upper": "2016-11-01",
    "iso:country": "GB",
    "wof:name": "PR4 2ER",
    "wof:placetype": "postalcode"
  },
  "geometry": {"coordinates":[-2.900874,53.784593],"type":"Point"}
}
