{
  "type": "Feature",
  "properties": {
    "iso:country": "GB",
    "wof:name": "PR4 2ER",
    "wof:placetype": "postalcode"
  },
  "geometry": {"coordinates":[-2.900874,53.784593],"type":"Point"}
}
