{
  "type": "Feature",
  "properties": {
    "iso:country":"GB",
    "wof:name":"LS17 8EZ",
    "wof:placetype":"postalcode"
},
  "geometry": {"coordinates":[-1.48818315715054,53.85661105021428],"type":"Point"}
}