{
  "type": "Feature",
  "properties": {
    "iso:country":"GB",
    "wof:name":"B75 7HP",
    "wof:placetype":"postalcode"
},
  "geometry": {"coordinates":[-1.77935536948376,52.55742987975868],"type":"Point"}
}