{
  "type": "Feature",
  "properties": {
    "iso:country":"GB",
    "wof:name":"PO2 7LA",
    "wof:placetype":"postalcode"
},
  "geometry": {"coordinates":[-1.06805926373299,50.81307951284142],"type":"Point"}
}