{
  "type": "Feature",
  "properties": {
    "iso:country":"GB",
    "wof:name":"B61 8RY",
    "wof:placetype":"postalcode"
},
  "geometry": {"coordinates":[-2.06625903262558,52.34333053680898],"type":"Point"}
}