{
  "type": "Feature",
  "properties": {
    "iso:country": "GB",
    "wof:name": "EX32 9BW",
    "wof:placetype": "postalcode"
  },
  "geometry": {"coordinates":[-4.044032,51.07076],"type":"Point"}
}
