{
  "type": "Feature",
  "properties": {
    "date:inception_lower": "1980-01-01",
    "date:inception_upper": "1980-01-01",
    "iso:country": "GB",
    "wof:name": "EX32 9BW",
    "wof:placetype": "postalcode"
  },
  "geometry": {"coordinates":[-4.044032,51.07076],"type":"Point"}
}
