{
  "type": "Feature",
  "properties": {
    "iso:country":"GB",
    "wof:name":"LS8 1HR",
    "wof:placetype":"postalcode"
},
  "geometry": {"coordinates":[-1.52075426356922,53.83611805951499],"type":"Point"}
}