{
  "type": "Feature",
  "properties": {
    "iso:country": "GB",
    "wof:name": "LS8 1HR",
    "wof:placetype": "postalcode"
  },
  "geometry": {"coordinates":[-1.520754,53.836118],"type":"Point"}
}
