{
  "type": "Feature",
  "properties": {
    "date:inception_lower": "1980-01-01",
    "date:inception_upper": "1980-01-01",
    "iso:country": "GB",
    "wof:name": "LA14 2EB",
    "wof:placetype": "postalcode"
  },
  "geometry": {"coordinates":[-3.218864,54.110534],"type":"Point"}
}
