{
  "type": "Feature",
  "properties": {
    "iso:country":"GB",
    "wof:name":"RG5 3BX",
    "wof:placetype":"postalcode"
},
  "geometry": {"coordinates":[-0.91501097838969,51.45501719538434],"type":"Point"}
}