{
  "type": "Feature",
  "properties": {
    "date:inception_lower": "2001-12-01",
    "date:inception_upper": "2001-12-01",
    "iso:country": "GB",
    "wof:name": "RG5 3BX",
    "wof:placetype": "postalcode"
  },
  "geometry": {"coordinates":[-0.915011,51.455017],"type":"Point"}
}
