{
  "type": "Feature",
  "properties": {
    "iso:country": "GB",
    "wof:name": "RG5 3BX",
    "wof:placetype": "postalcode"
  },
  "geometry": {"coordinates":[-0.915011,51.455017],"type":"Point"}
}
