{
  "type": "Feature",
  "properties": {
    "iso:country":"GB",
    "wof:name":"DN4 8TS",
    "wof:placetype":"postalcode"
},
  "geometry": {"coordinates":[-1.13839690737846,53.49687924648466],"type":"Point"}
}