{
  "type": "Feature",
  "properties": {
    "date:inception_lower":"2004-05-01",
    "date:inception_upper":"2004-05-31",
    "iso:country":"GB",
    "wof:name":"DN4 8TS",
    "wof:placetype":"postalcode"
},
  "geometry": {"coordinates":[-1.138397,53.496879],"type":"Point"}
}