{
  "type": "Feature",
  "properties": {
    "iso:country":"GB",
    "wof:name":"NG23 7SL",
    "wof:placetype":"postalcode"
},
  "geometry": {"coordinates":[-0.75119765207295,53.14884845378293],"type":"Point"}
}