{
  "type": "Feature",
  "properties": {
    "date:inception_lower":"1980-01-01",
    "date:inception_upper":"1980-01-31",
    "iso:country":"GB",
    "wof:name":"LU1 3RZ",
    "wof:placetype":"postalcode"
},
  "geometry": {"coordinates":[-0.417095,51.872274],"type":"Point"}
}