{
  "type": "Feature",
  "properties": {
    "iso:country":"GB",
    "wof:name":"LU1 3RZ",
    "wof:placetype":"postalcode"
},
  "geometry": {"coordinates":[-0.41709492429521,51.87227360816872],"type":"Point"}
}