{
  "type": "Feature",
  "properties": {
    "date:inception_lower": "1999-12-01",
    "date:inception_upper": "1999-12-01",
    "iso:country": "GB",
    "wof:name": "SW11 3YR",
    "wof:placetype": "postalcode"
  },
  "geometry": {"coordinates":[-0.180288,51.468083],"type":"Point"}
}
