{
  "type": "Feature",
  "properties": {
    "iso:country":"GB",
    "wof:name":"SW11 3YR",
    "wof:placetype":"postalcode"
},
  "geometry": {"coordinates":[-0.18028794407973,51.46808276859213],"type":"Point"}
}