{
  "type": "Feature",
  "properties": {
    "iso:country":"GB",
    "wof:name":"S75 3DN",
    "wof:placetype":"postalcode"
},
  "geometry": {"coordinates":[-1.48320548198421,53.49702390952844],"type":"Point"}
}