{
  "type": "Feature",
  "properties": {
    "date:inception_lower": "1999-12-01",
    "date:inception_upper": "1999-12-01",
    "iso:country": "GB",
    "wof:name": "S75 3DN",
    "wof:placetype": "postalcode"
  },
  "geometry": {"coordinates":[-1.483205,53.497024],"type":"Point"}
}
