{
  "type": "Feature",
  "properties": {
    "iso:country":"GB",
    "wof:name":"LE9 8AR",
    "wof:placetype":"postalcode"
},
  "geometry": {"coordinates":[-1.33855633339946,52.5705953751444],"type":"Point"}
}