{
  "type": "Feature",
  "properties": {
    "iso:country": "GB",
    "wof:name": "LE9 8AR",
    "wof:placetype": "postalcode"
  },
  "geometry": {"coordinates":[-1.338556,52.570595],"type":"Point"}
}
