{
  "type": "Feature",
  "properties": {
    "iso:country": "GB",
    "wof:name": "NP20 3PX",
    "wof:placetype": "postalcode"
  },
  "geometry": {"coordinates":[-3.031382,51.577559],"type":"Point"}
}
