{
  "type": "Feature",
  "properties": {
    "date:inception_lower": "1980-01-01",
    "date:inception_upper": "1980-01-01",
    "iso:country": "GB",
    "wof:name": "BB5 5LR",
    "wof:placetype": "postalcode"
  },
  "geometry": {"coordinates":[-2.379004,53.76907],"type":"Point"}
}
