{
  "type": "Feature",
  "properties": {
    "iso:country":"GB",
    "wof:name":"BB5 5LR",
    "wof:placetype":"postalcode"
},
  "geometry": {"coordinates":[-2.37904957698644,53.76901955859643],"type":"Point"}
}