{
  "type": "Feature",
  "properties": {
    "iso:country": "GB",
    "wof:name": "CT3 3HE",
    "wof:placetype": "postalcode"
  },
  "geometry": {"coordinates":[1.202413,51.227374],"type":"Point"}
}
