{
  "type": "Feature",
  "properties": {
    "iso:country":"GB",
    "wof:name":"CT3 3HE",
    "wof:placetype":"postalcode"
},
  "geometry": {"coordinates":[1.20241295139533,51.22737359232679],"type":"Point"}
}