{
  "type": "Feature",
  "properties": {
    "date:inception_lower": "1980-01-01",
    "date:inception_upper": "1980-01-01",
    "iso:country": "GB",
    "wof:name": "TW10 5EF",
    "wof:placetype": "postalcode"
  },
  "geometry": {"coordinates":[-0.28051,51.465027],"type":"Point"}
}
