{
  "type": "Feature",
  "properties": {
    "iso:country":"GB",
    "wof:name":"RM9 5DR",
    "wof:placetype":"postalcode"
},
  "geometry": {"coordinates":[0.13990024980589,51.54753228376487],"type":"Point"}
}