{
  "type": "Feature",
  "properties": {
    "iso:country": "GB",
    "wof:name": "RM9 5DR",
    "wof:placetype": "postalcode"
  },
  "geometry": {"coordinates":[0.1399,51.547532],"type":"Point"}
}
