{
  "type": "Feature",
  "properties": {
    "date:inception_lower": "2020-12-01",
    "date:inception_upper": "2020-12-01",
    "iso:country": "GB",
    "wof:name": "HX2 7AF",
    "wof:placetype": "postalcode"
  },
  "geometry": {"coordinates":[-1.900927,53.717032],"type":"Point"}
}
