{
  "type": "Feature",
  "properties": {
    "iso:country": "GB",
    "wof:name": "MK13 0BJ",
    "wof:placetype": "postalcode"
  },
  "geometry": {"coordinates":[-0.792922,52.06461],"type":"Point"}
}
