{
  "type": "Feature",
  "properties": {
    "iso:country":"GB",
    "wof:name":"KY16 9XF",
    "wof:placetype":"postalcode"
},
  "geometry": {"coordinates":[-2.80207249189756,56.33975412507987],"type":"Point"}
}