{
  "type": "Feature",
  "properties": {
    "date:inception_lower":"1980-01-01",
    "date:inception_upper":"1980-01-31",
    "iso:country":"GB",
    "wof:name":"SK9 2PP",
    "wof:placetype":"postalcode"
},
  "geometry": {"coordinates":[-2.211518,53.338037],"type":"Point"}
}