{
  "type": "Feature",
  "properties": {
    "iso:country": "GB",
    "wof:name": "SK9 2PP",
    "wof:placetype": "postalcode"
  },
  "geometry": {"coordinates":[-2.211518,53.338037],"type":"Point"}
}
