{
  "type": "Feature",
  "properties": {
    "iso:country":"GB",
    "wof:name":"SK9 2PP",
    "wof:placetype":"postalcode"
},
  "geometry": {"coordinates":[-2.21151851210432,53.33803704542246],"type":"Point"}
}