{
  "type": "Feature",
  "properties": {
    "iso:country":"GB",
    "wof:name":"NE61 4NJ",
    "wof:placetype":"postalcode"
},
  "geometry": {"coordinates":[-1.84352115270188,55.20525198055873],"type":"Point"}
}