{
  "type": "Feature",
  "properties": {
    "iso:country": "GB",
    "wof:name": "NE61 4NJ",
    "wof:placetype": "postalcode"
  },
  "geometry": {"coordinates":[-1.843521,55.205252],"type":"Point"}
}
