{
  "type": "Feature",
  "properties": {
    "iso:country": "GB",
    "wof:name": "OL10 1AX",
    "wof:placetype": "postalcode"
  },
  "geometry": {"coordinates":[-2.217755,53.588679],"type":"Point"}
}
