{
  "type": "Feature",
  "properties": {
    "iso:country": "GB",
    "wof:name": "NN3 3PJ",
    "wof:placetype": "postalcode"
  },
  "geometry": {"coordinates":[-0.837171,52.251283],"type":"Point"}
}
