{
  "type": "Feature",
  "properties": {
    "iso:country":"GB",
    "wof:name":"NN3 3PJ",
    "wof:placetype":"postalcode"
},
  "geometry": {"coordinates":[-0.83717114979097,52.25128306539149],"type":"Point"}
}