{
  "type": "Feature",
  "properties": {
    "iso:country":"GB",
    "wof:name":"RG24 9JX",
    "wof:placetype":"postalcode"
},
  "geometry": {"coordinates":[-1.11483926189722,51.28791775470661],"type":"Point"}
}