{
  "type": "Feature",
  "properties": {
    "date:inception_lower":"1988-03-01",
    "date:inception_upper":"1988-03-31",
    "iso:country":"GB",
    "wof:name":"NE4 7ST",
    "wof:placetype":"postalcode"
},
  "geometry": {"coordinates":[-1.639365,54.963337],"type":"Point"}
}