{
  "type": "Feature",
  "properties": {
    "iso:country": "GB",
    "wof:name": "NE4 7ST",
    "wof:placetype": "postalcode"
  },
  "geometry": {"coordinates":[-1.639365,54.963337],"type":"Point"}
}
