{
  "type": "Feature",
  "properties": {
    "iso:country":"GB",
    "wof:name":"LE19 1TP",
    "wof:placetype":"postalcode"
},
  "geometry": {"coordinates":[-1.19108332769753,52.61145672326609],"type":"Point"}
}