{
  "type": "Feature",
  "properties": {
    "date:inception_lower":"1980-01-01",
    "date:inception_upper":"1980-01-31",
    "iso:country":"GB",
    "wof:name":"BL8 1AP",
    "wof:placetype":"postalcode"
},
  "geometry": {"coordinates":[-2.308873,53.598275],"type":"Point"}
}