{
  "type": "Feature",
  "properties": {
    "iso:country": "GB",
    "wof:name": "BL8 1AP",
    "wof:placetype": "postalcode"
  },
  "geometry": {"coordinates":[-2.308873,53.598275],"type":"Point"}
}
