{
  "type": "Feature",
  "properties": {
    "iso:country":"GB",
    "wof:name":"NE40 3PD",
    "wof:placetype":"postalcode"
},
  "geometry": {"coordinates":[-1.75071621364976,54.97687019359986],"type":"Point"}
}