{
  "type": "Feature",
  "properties": {
    "date:inception_lower": "1980-01-01",
    "date:inception_upper": "1980-01-01",
    "iso:country": "GB",
    "wof:name": "NE40 3PD",
    "wof:placetype": "postalcode"
  },
  "geometry": {"coordinates":[-1.750729,54.976877],"type":"Point"}
}
