{
  "type": "Feature",
  "properties": {
    "iso:country":"GB",
    "wof:name":"B73 6XD",
    "wof:placetype":"postalcode"
},
  "geometry": {"coordinates":[-1.87923993944371,52.56375867048686],"type":"Point"}
}