{
  "type": "Feature",
  "properties": {
    "iso:country": "GB",
    "wof:name": "B73 6XD",
    "wof:placetype": "postalcode"
  },
  "geometry": {"coordinates":[-1.87924,52.563759],"type":"Point"}
}
