{
  "type": "Feature",
  "properties": {
    "iso:country":"GB",
    "wof:name":"M1 4HR",
    "wof:placetype":"postalcode"
},
  "geometry": {"coordinates":[-2.24155351149535,53.47845329687889],"type":"Point"}
}