{
  "type": "Feature",
  "properties": {
    "date:inception_lower": "1980-01-01",
    "date:inception_upper": "1980-01-01",
    "iso:country": "GB",
    "wof:name": "M1 4HR",
    "wof:placetype": "postalcode"
  },
  "geometry": {"coordinates":[-2.241553,53.478453],"type":"Point"}
}
