{
  "type": "Feature",
  "properties": {
    "iso:country":"GB",
    "wof:name":"PO22 9LN",
    "wof:placetype":"postalcode"
},
  "geometry": {"coordinates":[-0.66926696484341,50.79513900672746],"type":"Point"}
}