{
  "type": "Feature",
  "properties": {
    "iso:country":"GB",
    "wof:name":"BR5 1QN",
    "wof:placetype":"postalcode"
},
  "geometry": {"coordinates":[0.08636418494281,51.39012373080224],"type":"Point"}
}