{
  "type": "Feature",
  "properties": {
    "date:inception_lower": "1984-02-01",
    "date:inception_upper": "1984-02-01",
    "iso:country": "GB",
    "wof:name": "ST5 4JW",
    "wof:placetype": "postalcode"
  },
  "geometry": {"coordinates":[-2.225051,52.984082],"type":"Point"}
}
