{
  "type": "Feature",
  "properties": {
    "date:inception_lower": "1994-12-01",
    "date:inception_upper": "1994-12-01",
    "iso:country": "GB",
    "wof:name": "FY4 4UU",
    "wof:placetype": "postalcode"
  },
  "geometry": {"coordinates":[-2.993435,53.802138],"type":"Point"}
}
