{
  "type": "Feature",
  "properties": {
    "date:inception_lower": "1980-01-01",
    "date:inception_upper": "1980-01-01",
    "iso:country": "GB",
    "wof:name": "HU15 2AH",
    "wof:placetype": "postalcode"
  },
  "geometry": {"coordinates":[-0.607236,53.795917],"type":"Point"}
}
