{
  "type": "Feature",
  "properties": {
    "iso:country": "GB",
    "wof:name": "HU15 2AH",
    "wof:placetype": "postalcode"
  },
  "geometry": {"coordinates":[-0.607236,53.795917],"type":"Point"}
}
