{
  "type": "Feature",
  "properties": {
    "date:inception_lower": "1980-01-01",
    "date:inception_upper": "1980-01-01",
    "iso:country": "GB",
    "wof:name": "YO7 3BQ",
    "wof:placetype": "postalcode"
  },
  "geometry": {"coordinates":[-1.302636,54.179257],"type":"Point"}
}
