{
  "type": "Feature",
  "properties": {
    "iso:country": "GB",
    "wof:name": "SO19 8FD",
    "wof:placetype": "postalcode"
  },
  "geometry": {"coordinates":[-1.353977,50.899012],"type":"Point"}
}
