{
  "type": "Feature",
  "properties": {
    "date:inception_lower": "1991-09-01",
    "date:inception_upper": "1991-09-01",
    "iso:country": "GB",
    "wof:name": "BN23 7NX",
    "wof:placetype": "postalcode"
  },
  "geometry": {"coordinates":[0.308577,50.803348],"type":"Point"}
}
