{
  "type": "Feature",
  "properties": {
    "date:inception_lower": "2021-09-01",
    "date:inception_upper": "2021-09-01",
    "iso:country": "GB",
    "wof:name": "CB3 1AP",
    "wof:placetype": "postalcode"
  },
  "geometry": {"coordinates":[0.090119,52.222092],"type":"Point"}
}
