{
  "type": "Feature",
  "properties": {
    "iso:country":"GB",
    "wof:name":"CM15 8JZ",
    "wof:placetype":"postalcode"
},
  "geometry": {"coordinates":[0.32088361621878,51.62957846991792],"type":"Point"}
}