{
  "type": "Feature",
  "properties": {
    "date:inception_lower": "1980-01-01",
    "date:inception_upper": "1980-01-01",
    "iso:country": "GB",
    "wof:name": "CM15 8JZ",
    "wof:placetype": "postalcode"
  },
  "geometry": {"coordinates":[0.320884,51.629578],"type":"Point"}
}
