{
  "type": "Feature",
  "properties": {
    "iso:country": "GB",
    "wof:name": "CM15 8JZ",
    "wof:placetype": "postalcode"
  },
  "geometry": {"coordinates":[0.320884,51.629578],"type":"Point"}
}
