{
  "type": "Feature",
  "properties": {
    "date:inception_lower": "1980-01-01",
    "date:inception_upper": "1980-01-01",
    "iso:country": "GB",
    "wof:name": "SY3 8BA",
    "wof:placetype": "postalcode"
  },
  "geometry": {"coordinates":[-2.784908,52.703282],"type":"Point"}
}
