{
  "type": "Feature",
  "properties": {
    "iso:country":"GB",
    "wof:name":"SY3 8BA",
    "wof:placetype":"postalcode"
},
  "geometry": {"coordinates":[-2.78487982832787,52.70326699555838],"type":"Point"}
}