{
  "type": "Feature",
  "properties": {
    "iso:country":"GB",
    "wof:name":"KA27 8HJ",
    "wof:placetype":"postalcode"
},
  "geometry": {"coordinates":[-5.27960012151976,55.69958508312745],"type":"Point"}
}