{
  "type": "Feature",
  "properties": {
    "iso:country": "GB",
    "wof:name": "KA27 8HJ",
    "wof:placetype": "postalcode"
  },
  "geometry": {"coordinates":[-5.2796,55.699585],"type":"Point"}
}
