{
  "type": "Feature",
  "properties": {
    "date:inception_lower": "1980-01-01",
    "date:inception_upper": "1980-01-01",
    "iso:country": "GB",
    "wof:name": "KA27 8HJ",
    "wof:placetype": "postalcode"
  },
  "geometry": {"coordinates":[-5.279568,55.699581],"type":"Point"}
}
