{
  "type": "Feature",
  "properties": {
    "iso:country": "GB",
    "wof:name": "PE32 1DN",
    "wof:placetype": "postalcode"
  },
  "geometry": {"coordinates":[0.554549,52.770338],"type":"Point"}
}
