{
  "type": "Feature",
  "properties": {
    "iso:country":"GB",
    "wof:name":"PE32 1DN",
    "wof:placetype":"postalcode"
},
  "geometry": {"coordinates":[0.55454878765701,52.77033847113935],"type":"Point"}
}