{
  "type": "Feature",
  "properties": {
    "iso:country":"GB",
    "wof:name":"NG17 7FJ",
    "wof:placetype":"postalcode"
},
  "geometry": {"coordinates":[-1.24299168615469,53.09235681713395],"type":"Point"}
}