{
  "type": "Feature",
  "properties": {
    "iso:country":"GB",
    "wof:name":"B44 8DL",
    "wof:placetype":"postalcode"
},
  "geometry": {"coordinates":[-1.88865324144185,52.53398447960343],"type":"Point"}
}