{
  "type": "Feature",
  "properties": {
    "iso:country":"GB",
    "wof:name":"BN21 3TH",
    "wof:placetype":"postalcode"
},
  "geometry": {"coordinates":[0.28739334685055,50.77006531100228],"type":"Point"}
}