{
  "type": "Feature",
  "properties": {
    "date:inception_lower": "1980-01-01",
    "date:inception_upper": "1980-01-01",
    "iso:country": "GB",
    "wof:name": "NE46 3BD",
    "wof:placetype": "postalcode"
  },
  "geometry": {"coordinates":[-2.115168,54.974392],"type":"Point"}
}
