{
  "type": "Feature",
  "properties": {
    "iso:country":"GB",
    "wof:name":"G75 0JS",
    "wof:placetype":"postalcode"
},
  "geometry": {"coordinates":[-4.17891834799801,55.75740620950491],"type":"Point"}
}