{
  "type": "Feature",
  "properties": {
    "iso:country":"GB",
    "wof:name":"KW17 2NL",
    "wof:placetype":"postalcode"
},
  "geometry": {"coordinates":[-3.16598054181767,59.13286783826158],"type":"Point"}
}