{
  "type": "Feature",
  "properties": {
    "iso:country": "GB",
    "wof:name": "CT8 8QB",
    "wof:placetype": "postalcode"
  },
  "geometry": {"coordinates":[1.325576,51.381736],"type":"Point"}
}
