{
  "type": "Feature",
  "properties": {
    "iso:country":"GB",
    "wof:name":"NG1 6AA",
    "wof:placetype":"postalcode"
},
  "geometry": {"coordinates":[-1.1531568069538,52.95070802776151],"type":"Point"}
}