{
  "type": "Feature",
  "properties": {
    "iso:country": "GB",
    "wof:name": "PO20 7QR",
    "wof:placetype": "postalcode"
  },
  "geometry": {"coordinates":[-0.803247,50.783576],"type":"Point"}
}
