{
  "type": "Feature",
  "properties": {
    "iso:country":"GB",
    "wof:name":"PO20 7QR",
    "wof:placetype":"postalcode"
},
  "geometry": {"coordinates":[-0.80326554367233,50.78358662873852],"type":"Point"}
}