{
  "type": "Feature",
  "properties": {
    "iso:country": "GB",
    "wof:name": "NP10 8WN",
    "wof:placetype": "postalcode"
  },
  "geometry": {"coordinates":[-3.017777,51.564173],"type":"Point"}
}
