{
  "type": "Feature",
  "properties": {
    "iso:country":"GB",
    "wof:name":"LS24 8BJ",
    "wof:placetype":"postalcode"
},
  "geometry": {"coordinates":[-1.30862133665506,53.91726127182368],"type":"Point"}
}