{
  "type": "Feature",
  "properties": {
    "iso:country":"GB",
    "wof:name":"HG3 3QQ",
    "wof:placetype":"postalcode"
},
  "geometry": {"coordinates":[-1.50133634242901,54.09019627500413],"type":"Point"}
}