{
  "type": "Feature",
  "properties": {
    "iso:country": "GB",
    "wof:name": "HG3 3QQ",
    "wof:placetype": "postalcode"
  },
  "geometry": {"coordinates":[-1.501336,54.090196],"type":"Point"}
}
