{
  "type": "Feature",
  "properties": {
    "date:inception_lower": "1980-01-01",
    "date:inception_upper": "1980-01-01",
    "iso:country": "GB",
    "wof:name": "SG6 3DG",
    "wof:placetype": "postalcode"
  },
  "geometry": {"coordinates":[-0.228559,51.979008],"type":"Point"}
}
