{
  "type": "Feature",
  "properties": {
    "iso:country": "GB",
    "wof:name": "SG6 3DG",
    "wof:placetype": "postalcode"
  },
  "geometry": {"coordinates":[-0.228559,51.979008],"type":"Point"}
}
