{
  "type": "Feature",
  "properties": {
    "iso:country":"GB",
    "wof:name":"SG6 3DG",
    "wof:placetype":"postalcode"
},
  "geometry": {"coordinates":[-0.22855919678341,51.97900759191097],"type":"Point"}
}