{
  "type": "Feature",
  "properties": {
    "iso:country":"GB",
    "wof:name":"PE1 1XA",
    "wof:placetype":"postalcode"
},
  "geometry": {"coordinates":[-0.24473753071281,52.57221889111101],"type":"Point"}
}