{
  "type": "Feature",
  "properties": {
    "iso:country": "GB",
    "wof:name": "B80 7PL",
    "wof:placetype": "postalcode"
  },
  "geometry": {"coordinates":[-1.898135,52.264183],"type":"Point"}
}
