{
  "type": "Feature",
  "properties": {
    "iso:country":"GB",
    "wof:name":"B80 7PL",
    "wof:placetype":"postalcode"
},
  "geometry": {"coordinates":[-1.89813485181193,52.26418255778864],"type":"Point"}
}