{
  "type": "Feature",
  "properties": {
    "iso:country":"GB",
    "wof:name":"HP16 0DR",
    "wof:placetype":"postalcode"
},
  "geometry": {"coordinates":[-0.697679249351,51.67882503717087],"type":"Point"}
}