{
  "type": "Feature",
  "properties": {
    "iso:country":"GB",
    "wof:name":"KY12 8PJ",
    "wof:placetype":"postalcode"
},
  "geometry": {"coordinates":[-3.49994565061528,56.06397308710819],"type":"Point"}
}