{
  "type": "Feature",
  "properties": {
    "iso:country": "GB",
    "wof:name": "EX17 6BQ",
    "wof:placetype": "postalcode"
  },
  "geometry": {"coordinates":[-3.849694,50.832475],"type":"Point"}
}
