{
  "type": "Feature",
  "properties": {
    "iso:country":"GB",
    "wof:name":"EX17 6BQ",
    "wof:placetype":"postalcode"
},
  "geometry": {"coordinates":[-3.84969392786012,50.83247463132155],"type":"Point"}
}