{
  "type": "Feature",
  "properties": {
    "date:inception_lower": "1999-06-01",
    "date:inception_upper": "1999-06-01",
    "iso:country": "GB",
    "wof:name": "CH63 0NP",
    "wof:placetype": "postalcode"
  },
  "geometry": {"coordinates":[-2.987063,53.312189],"type":"Point"}
}
