{
  "type": "Feature",
  "properties": {
    "date:inception_lower": "1980-01-01",
    "date:inception_upper": "1980-01-01",
    "iso:country": "GB",
    "wof:name": "NW8 7PE",
    "wof:placetype": "postalcode"
  },
  "geometry": {"coordinates":[-0.169549,51.532151],"type":"Point"}
}
