{
  "type": "Feature",
  "properties": {
    "date:inception_lower":"1980-01-01",
    "date:inception_upper":"1980-01-31",
    "iso:country":"GB",
    "wof:name":"TA20 4LR",
    "wof:placetype":"postalcode"
},
  "geometry": {"coordinates":[-2.911478,50.836888],"type":"Point"}
}