{
  "type": "Feature",
  "properties": {
    "iso:country":"GB",
    "wof:name":"TA20 4LR",
    "wof:placetype":"postalcode"
},
  "geometry": {"coordinates":[-2.91146467162233,50.83693293645857],"type":"Point"}
}