{
  "type": "Feature",
  "properties": {
    "iso:country": "GB",
    "wof:name": "IP6 9HU",
    "wof:placetype": "postalcode"
  },
  "geometry": {"coordinates":[1.182248,52.102412],"type":"Point"}
}
