{
  "type": "Feature",
  "properties": {
    "iso:country":"GB",
    "wof:name":"PO8 9SU",
    "wof:placetype":"postalcode"
},
  "geometry": {"coordinates":[-1.01670642737048,50.9163710999547],"type":"Point"}
}