{
  "type": "Feature",
  "properties": {
    "date:inception_lower": "1980-01-01",
    "date:inception_upper": "1980-01-01",
    "iso:country": "GB",
    "wof:name": "PO8 9SU",
    "wof:placetype": "postalcode"
  },
  "geometry": {"coordinates":[-1.017003,50.916383],"type":"Point"}
}
