{
  "type": "Feature",
  "properties": {
    "date:inception_lower": "1980-01-01",
    "date:inception_upper": "1980-01-01",
    "iso:country": "GB",
    "wof:name": "SG13 7JP",
    "wof:placetype": "postalcode"
  },
  "geometry": {"coordinates":[-0.056661,51.798873],"type":"Point"}
}
