{
  "type": "Feature",
  "properties": {
    "iso:country":"GB",
    "wof:name":"SG13 7JP",
    "wof:placetype":"postalcode"
},
  "geometry": {"coordinates":[-0.05666122890605,51.79887310432628],"type":"Point"}
}