{
  "type": "Feature",
  "properties": {
    "iso:country":"GB",
    "wof:name":"ST2 7JR",
    "wof:placetype":"postalcode"
},
  "geometry": {"coordinates":[-2.13683262928013,53.05604844704545],"type":"Point"}
}