{
  "type": "Feature",
  "properties": {
    "iso:country":"GB",
    "wof:name":"SS11 7LP",
    "wof:placetype":"postalcode"
},
  "geometry": {"coordinates":[0.51484239453893,51.6276601813625],"type":"Point"}
}