{
  "type": "Feature",
  "properties": {
    "date:inception_lower": "2008-10-01",
    "date:inception_upper": "2008-10-01",
    "iso:country": "GB",
    "wof:name": "IP3 9QN",
    "wof:placetype": "postalcode"
  },
  "geometry": {"coordinates":[1.199262,52.036099],"type":"Point"}
}
