{
  "type": "Feature",
  "properties": {
    "iso:country":"GB",
    "wof:name":"IP3 9QN",
    "wof:placetype":"postalcode"
},
  "geometry": {"coordinates":[1.1992617224496,52.03609901217684],"type":"Point"}
}