{
  "type": "Feature",
  "properties": {
    "date:inception_lower":"1980-01-01",
    "date:inception_upper":"1980-01-31",
    "iso:country":"GB",
    "wof:name":"BS5 7DF",
    "wof:placetype":"postalcode"
},
  "geometry": {"coordinates":[-2.543704,51.46406],"type":"Point"}
}