{
  "type": "Feature",
  "properties": {
    "iso:country": "GB",
    "wof:name": "BS5 7DF",
    "wof:placetype": "postalcode"
  },
  "geometry": {"coordinates":[-2.543704,51.46406],"type":"Point"}
}
