{
  "type": "Feature",
  "properties": {
    "iso:country":"GB",
    "wof:name":"BS5 7DF",
    "wof:placetype":"postalcode"
},
  "geometry": {"coordinates":[-2.54370360289328,51.46406000306887],"type":"Point"}
}