{
  "type": "Feature",
  "properties": {
    "iso:country":"GB",
    "wof:name":"ME7 2LF",
    "wof:placetype":"postalcode"
},
  "geometry": {"coordinates":[0.56445387899985,51.37551550884699],"type":"Point"}
}