{
  "type": "Feature",
  "properties": {
    "date:inception_lower": "1980-01-01",
    "date:inception_upper": "1980-01-01",
    "iso:country": "GB",
    "wof:name": "ME7 2LF",
    "wof:placetype": "postalcode"
  },
  "geometry": {"coordinates":[0.564454,51.375516],"type":"Point"}
}
