{
  "type": "Feature",
  "properties": {
    "iso:country": "GB",
    "wof:name": "BR2 9NS",
    "wof:placetype": "postalcode"
  },
  "geometry": {"coordinates":[0.033777,51.396084],"type":"Point"}
}
