{
  "type": "Feature",
  "properties": {
    "iso:country":"GB",
    "wof:name":"BR2 9NS",
    "wof:placetype":"postalcode"
},
  "geometry": {"coordinates":[0.03377653909118,51.39608440471633],"type":"Point"}
}