{
  "type": "Feature",
  "properties": {
    "iso:country": "GB",
    "wof:name": "HX5 9JT",
    "wof:placetype": "postalcode"
  },
  "geometry": {"coordinates":[-1.82331,53.678],"type":"Point"}
}
