{
  "type": "Feature",
  "properties": {
    "iso:country":"GB",
    "wof:name":"LD3 8LU",
    "wof:placetype":"postalcode"
},
  "geometry": {"coordinates":[-3.39363087385364,51.93677445490562],"type":"Point"}
}