{
  "type": "Feature",
  "properties": {
    "iso:country":"GB",
    "wof:name":"S70 4RS",
    "wof:placetype":"postalcode"
},
  "geometry": {"coordinates":[-1.45704246006256,53.53197213518188],"type":"Point"}
}