{
  "type": "Feature",
  "properties": {
    "iso:country":"GB",
    "wof:name":"DT2 7SP",
    "wof:placetype":"postalcode"
},
  "geometry": {"coordinates":[-2.37725379770045,50.75556941143464],"type":"Point"}
}