{
  "type": "Feature",
  "properties": {
    "iso:country": "GB",
    "wof:name": "DT2 7SP",
    "wof:placetype": "postalcode"
  },
  "geometry": {"coordinates":[-2.377254,50.755569],"type":"Point"}
}
