{
  "type": "Feature",
  "properties": {
    "iso:country":"GB",
    "wof:name":"GU33 7AT",
    "wof:placetype":"postalcode"
},
  "geometry": {"coordinates":[-0.88377055698486,51.05407604239893],"type":"Point"}
}