{
  "type": "Feature",
  "properties": {
    "iso:country": "GB",
    "wof:name": "TW10 6NS",
    "wof:placetype": "postalcode"
  },
  "geometry": {"coordinates":[-0.294742,51.455532],"type":"Point"}
}
