{
  "type": "Feature",
  "properties": {
    "iso:country":"GB",
    "wof:name":"TW10 6NS",
    "wof:placetype":"postalcode"
},
  "geometry": {"coordinates":[-0.29474176252556,51.45553225272835],"type":"Point"}
}