{
  "type": "Feature",
  "properties": {
    "iso:country":"GB",
    "wof:name":"PE24 5TR",
    "wof:placetype":"postalcode"
},
  "geometry": {"coordinates":[0.33517797656885,53.21687855106035],"type":"Point"}
}