{
  "type": "Feature",
  "properties": {
    "date:inception_lower": "1980-01-01",
    "date:inception_upper": "1980-01-01",
    "iso:country": "GB",
    "wof:name": "PE24 5TR",
    "wof:placetype": "postalcode"
  },
  "geometry": {"coordinates":[0.335179,53.216906],"type":"Point"}
}
