{
  "type": "Feature",
  "properties": {
    "date:inception_lower": "2000-06-01",
    "date:inception_upper": "2000-06-01",
    "iso:country": "GB",
    "wof:name": "SW7 2BX",
    "wof:placetype": "postalcode"
  },
  "geometry": {"coordinates":[-0.17461,51.499603],"type":"Point"}
}
