{
  "type": "Feature",
  "properties": {
    "date:inception_lower":"1998-06-01",
    "date:inception_upper":"1998-06-30",
    "iso:country":"GB",
    "wof:name":"YO26 9RE",
    "wof:placetype":"postalcode"
},
  "geometry": {"coordinates":[-1.318798,54.051526],"type":"Point"}
}