{
  "type": "Feature",
  "properties": {
    "iso:country":"GB",
    "wof:name":"YO26 9RE",
    "wof:placetype":"postalcode"
},
  "geometry": {"coordinates":[-1.31879781338232,54.05152627006161],"type":"Point"}
}