{
  "type": "Feature",
  "properties": {
    "iso:country": "GB",
    "wof:name": "YO26 9RE",
    "wof:placetype": "postalcode"
  },
  "geometry": {"coordinates":[-1.318798,54.051526],"type":"Point"}
}
