{
  "type": "Feature",
  "properties": {
    "iso:country":"GB",
    "wof:name":"SO21 3DB",
    "wof:placetype":"postalcode"
},
  "geometry": {"coordinates":[-1.26780133215947,51.14994765474569],"type":"Point"}
}