{
  "type": "Feature",
  "properties": {
    "iso:country": "GB",
    "wof:name": "DL2 2HT",
    "wof:placetype": "postalcode"
  },
  "geometry": {"coordinates":[-1.589431,54.548143],"type":"Point"}
}
