{
  "type": "Feature",
  "properties": {
    "iso:country": "GB",
    "wof:name": "PL31 1EN",
    "wof:placetype": "postalcode"
  },
  "geometry": {"coordinates":[-4.707029,50.460836],"type":"Point"}
}
