{
  "type": "Feature",
  "properties": {
    "date:inception_lower":"1980-01-01",
    "date:inception_upper":"1980-01-31",
    "iso:country":"GB",
    "wof:name":"PL31 1EN",
    "wof:placetype":"postalcode"
},
  "geometry": {"coordinates":[-4.707029,50.460836],"type":"Point"}
}