{
  "type": "Feature",
  "properties": {
    "iso:country": "GB",
    "wof:name": "GL10 3GJ",
    "wof:placetype": "postalcode"
  },
  "geometry": {"coordinates":[-2.281395,51.727481],"type":"Point"}
}
