{
  "type": "Feature",
  "properties": {
    "date:inception_lower": "2015-08-01",
    "date:inception_upper": "2015-08-01",
    "iso:country": "GB",
    "wof:name": "S45 9PA",
    "wof:placetype": "postalcode"
  },
  "geometry": {"coordinates":[-1.414217,53.165406],"type":"Point"}
}
