{
  "type": "Feature",
  "properties": {
    "iso:country":"GB",
    "wof:name":"S45 9PA",
    "wof:placetype":"postalcode"
},
  "geometry": {"coordinates":[-1.41419813830224,53.16567543068154],"type":"Point"}
}