{
  "type": "Feature",
  "properties": {
    "iso:country":"GB",
    "wof:name":"LA6 2PF",
    "wof:placetype":"postalcode"
},
  "geometry": {"coordinates":[-2.65908412355186,54.19187194898584],"type":"Point"}
}