{
  "type": "Feature",
  "properties": {
    "date:inception_lower": "1980-01-01",
    "date:inception_upper": "1980-01-01",
    "iso:country": "GB",
    "wof:name": "LA6 2PF",
    "wof:placetype": "postalcode"
  },
  "geometry": {"coordinates":[-2.659054,54.191901],"type":"Point"}
}
