{
  "type": "Feature",
  "properties": {
    "iso:country":"GB",
    "wof:name":"PR1 0AS",
    "wof:placetype":"postalcode"
},
  "geometry": {"coordinates":[-2.72832618793261,53.75396833621639],"type":"Point"}
}