{
  "type": "Feature",
  "properties": {
    "iso:country": "GB",
    "wof:name": "PE19 2BX",
    "wof:placetype": "postalcode"
  },
  "geometry": {"coordinates":[-0.263394,52.224928],"type":"Point"}
}
