{
  "type": "Feature",
  "properties": {
    "iso:country":"GB",
    "wof:name":"S12 4YH",
    "wof:placetype":"postalcode"
},
  "geometry": {"coordinates":[-1.40390655978356,53.34585210885805],"type":"Point"}
}