{
  "type": "Feature",
  "properties": {
    "iso:country":"GB",
    "wof:name":"L1 7AY",
    "wof:placetype":"postalcode"
},
  "geometry": {"coordinates":[-2.97232385799113,53.39535953704404],"type":"Point"}
}