{
  "type": "Feature",
  "properties": {
    "iso:country":"GB",
    "wof:name":"WF7 7ET",
    "wof:placetype":"postalcode"
},
  "geometry": {"coordinates":[-1.33068419007106,53.66438776092419],"type":"Point"}
}