{
  "type": "Feature",
  "properties": {
    "iso:country":"GB",
    "wof:name":"B61 0JQ",
    "wof:placetype":"postalcode"
},
  "geometry": {"coordinates":[-2.04418888787797,52.3645037171468],"type":"Point"}
}