{
  "type": "Feature",
  "properties": {
    "iso:country":"GB",
    "wof:name":"NR8 6RE",
    "wof:placetype":"postalcode"
},
  "geometry": {"coordinates":[1.20127693715092,52.6841756025074],"type":"Point"}
}