{
  "type": "Feature",
  "properties": {
    "iso:country": "GB",
    "wof:name": "HG1 4AA",
    "wof:placetype": "postalcode"
  },
  "geometry": {"coordinates":[-1.52877,53.997761],"type":"Point"}
}
