{
  "type": "Feature",
  "properties": {
    "iso:country":"GB",
    "wof:name":"NP23 4BL",
    "wof:placetype":"postalcode"
},
  "geometry": {"coordinates":[-3.17640121652829,51.79291998978301],"type":"Point"}
}