{
  "type": "Feature",
  "properties": {
    "date:inception_lower": "1999-06-01",
    "date:inception_upper": "1999-06-01",
    "iso:country": "GB",
    "wof:name": "NP23 4BL",
    "wof:placetype": "postalcode"
  },
  "geometry": {"coordinates":[-3.176401,51.79292],"type":"Point"}
}
