{
  "type": "Feature",
  "properties": {
    "iso:country":"GB",
    "wof:name":"OL5 0QX",
    "wof:placetype":"postalcode"
},
  "geometry": {"coordinates":[-2.04588646885867,53.51959526522502],"type":"Point"}
}