{
  "type": "Feature",
  "properties": {
    "date:inception_lower":"2012-02-01",
    "date:inception_upper":"2012-02-29",
    "iso:country":"GB",
    "wof:name":"YO21 1AD",
    "wof:placetype":"postalcode"
},
  "geometry": {"coordinates":[-0.62682,54.485233],"type":"Point"}
}