{
  "type": "Feature",
  "properties": {
    "iso:country":"GB",
    "wof:name":"PO8 0SE",
    "wof:placetype":"postalcode"
},
  "geometry": {"coordinates":[-1.03932726516461,50.94459829958756],"type":"Point"}
}