{
  "type": "Feature",
  "properties": {
    "iso:country": "GB",
    "wof:name": "PO8 0SE",
    "wof:placetype": "postalcode"
  },
  "geometry": {"coordinates":[-1.039312,50.944591],"type":"Point"}
}
