{
  "type": "Feature",
  "properties": {
    "date:inception_lower":"1980-07-01",
    "date:inception_upper":"1980-07-31",
    "iso:country":"GB",
    "wof:name":"EH48 1TT",
    "wof:placetype":"postalcode"
},
  "geometry": {"coordinates":[-3.643228,55.901666],"type":"Point"}
}