{
  "type": "Feature",
  "properties": {
    "iso:country": "GB",
    "wof:name": "BS24 8EU",
    "wof:placetype": "postalcode"
  },
  "geometry": {"coordinates":[-2.952717,51.332565],"type":"Point"}
}
