{
  "type": "Feature",
  "properties": {
    "iso:country":"GB",
    "wof:name":"LD7 1DW",
    "wof:placetype":"postalcode"
},
  "geometry": {"coordinates":[-3.04934216121462,52.34310169457792],"type":"Point"}
}