{
  "type": "Feature",
  "properties": {
    "iso:country":"GB",
    "wof:name":"DG1 1QE",
    "wof:placetype":"postalcode"
},
  "geometry": {"coordinates":[-3.57945836242181,55.10623098470461],"type":"Point"}
}