{
  "type": "Feature",
  "properties": {
    "iso:country":"GB",
    "wof:name":"SG8 5QH",
    "wof:placetype":"postalcode"
},
  "geometry": {"coordinates":[-0.01753738667289,52.13025994384476],"type":"Point"}
}