{
  "type": "Feature",
  "properties": {
    "iso:country":"GB",
    "wof:name":"ME17 1PG",
    "wof:placetype":"postalcode"
},
  "geometry": {"coordinates":[0.6331754497408,51.2530416064364],"type":"Point"}
}