{
  "type": "Feature",
  "properties": {
    "date:inception_lower": "2021-03-01",
    "date:inception_upper": "2021-03-01",
    "iso:country": "GB",
    "wof:name": "B29 6WQ",
    "wof:placetype": "postalcode"
  },
  "geometry": {"coordinates":[-1.933757,52.436231],"type":"Point"}
}
