{
  "type": "Feature",
  "properties": {
    "date:inception_lower": "1980-01-01",
    "date:inception_upper": "1980-01-01",
    "iso:country": "GB",
    "wof:name": "PA2 7EX",
    "wof:placetype": "postalcode"
  },
  "geometry": {"coordinates":[-4.405275,55.837327],"type":"Point"}
}
