{
  "type": "Feature",
  "properties": {
    "iso:country": "GB",
    "wof:name": "CA3 0FT",
    "wof:placetype": "postalcode"
  },
  "geometry": {"coordinates":[-2.943673,54.926046],"type":"Point"}
}
