{
  "type": "Feature",
  "properties": {
    "iso:country": "GB",
    "wof:name": "OX29 8LH",
    "wof:placetype": "postalcode"
  },
  "geometry": {"coordinates":[-1.368497,51.825705],"type":"Point"}
}
