{
  "type": "Feature",
  "properties": {
    "date:inception_lower":"1980-01-01",
    "date:inception_upper":"1980-01-31",
    "iso:country":"GB",
    "wof:name":"IP33 3RQ",
    "wof:placetype":"postalcode"
},
  "geometry": {"coordinates":[0.703175,52.247653],"type":"Point"}
}