{
  "type": "Feature",
  "properties": {
    "iso:country":"GB",
    "wof:name":"YO62 6TQ",
    "wof:placetype":"postalcode"
},
  "geometry": {"coordinates":[-0.8803701457892,54.30565894080046],"type":"Point"}
}