{
  "type": "Feature",
  "properties": {
    "date:inception_lower": "2024-09-01",
    "date:inception_upper": "2024-09-01",
    "iso:country": "GB",
    "wof:name": "DH9 8FN",
    "wof:placetype": "postalcode"
  },
  "geometry": {"coordinates":[-1.74813,54.867384],"type":"Point"}
}
