{
  "type": "Feature",
  "properties": {
    "iso:country":"GB",
    "wof:name":"LE10 0BP",
    "wof:placetype":"postalcode"
},
  "geometry": {"coordinates":[-1.37422073562793,52.54242575542239],"type":"Point"}
}