{
  "type": "Feature",
  "properties": {
    "date:inception_lower":"2009-10-01",
    "date:inception_upper":"2009-10-31",
    "iso:country":"GB",
    "wof:name":"LE10 0BP",
    "wof:placetype":"postalcode"
},
  "geometry": {"coordinates":[-1.374221,52.542426],"type":"Point"}
}