{
  "type": "Feature",
  "properties": {
    "iso:country":"GB",
    "wof:name":"SN10 1RY",
    "wof:placetype":"postalcode"
},
  "geometry": {"coordinates":[-2.04563940425945,51.33373833263572],"type":"Point"}
}