{
  "type": "Feature",
  "properties": {
    "date:inception_lower": "2007-10-01",
    "date:inception_upper": "2007-10-01",
    "iso:country": "GB",
    "wof:name": "NG24 3RU",
    "wof:placetype": "postalcode"
  },
  "geometry": {"coordinates":[-0.77023,53.048884],"type":"Point"}
}
