{
  "type": "Feature",
  "properties": {
    "iso:country":"GB",
    "wof:name":"NG24 3RU",
    "wof:placetype":"postalcode"
},
  "geometry": {"coordinates":[-0.77023034738482,53.04888447879625],"type":"Point"}
}