{
  "type": "Feature",
  "properties": {
    "iso:country":"GB",
    "wof:name":"SS12 0DJ",
    "wof:placetype":"postalcode"
},
  "geometry": {"coordinates":[0.51076460580997,51.61295359349825],"type":"Point"}
}