{
  "type": "Feature",
  "properties": {
    "date:inception_lower": "1991-01-01",
    "date:inception_upper": "1991-01-01",
    "iso:country": "GB",
    "wof:name": "TR13 9DU",
    "wof:placetype": "postalcode"
  },
  "geometry": {"coordinates":[-5.315139,50.085142],"type":"Point"}
}
