{
  "type": "Feature",
  "properties": {
    "iso:country": "GB",
    "wof:name": "CW10 0EQ",
    "wof:placetype": "postalcode"
  },
  "geometry": {"coordinates":[-2.436893,53.180677],"type":"Point"}
}
