{
  "type": "Feature",
  "properties": {
    "date:inception_lower":"1980-01-01",
    "date:inception_upper":"1980-01-31",
    "iso:country":"GB",
    "wof:name":"CF47 9BW",
    "wof:placetype":"postalcode"
},
  "geometry": {"coordinates":[-3.384829,51.767451],"type":"Point"}
}