{
  "type": "Feature",
  "properties": {
    "iso:country":"GB",
    "wof:name":"CF47 9BW",
    "wof:placetype":"postalcode"
},
  "geometry": {"coordinates":[-3.38482904478359,51.76745074048038],"type":"Point"}
}