{
  "type": "Feature",
  "properties": {
    "iso:country":"GB",
    "wof:name":"SL5 7QE",
    "wof:placetype":"postalcode"
},
  "geometry": {"coordinates":[-0.64102553657616,51.41447603543788],"type":"Point"}
}