{
  "type": "Feature",
  "properties": {
    "iso:country": "GB",
    "wof:name": "CH43 4UA",
    "wof:placetype": "postalcode"
  },
  "geometry": {"coordinates":[-3.03958,53.385606],"type":"Point"}
}
