{
  "type": "Feature",
  "properties": {
    "iso:country":"GB",
    "wof:name":"CH43 4UA",
    "wof:placetype":"postalcode"
},
  "geometry": {"coordinates":[-3.03958017025492,53.38560597684069],"type":"Point"}
}