{
  "type": "Feature",
  "properties": {
    "iso:country": "GB",
    "wof:name": "PR4 3WG",
    "wof:placetype": "postalcode"
  },
  "geometry": {"coordinates":[-2.926015,53.799235],"type":"Point"}
}
