{
  "type": "Feature",
  "properties": {
    "date:inception_lower":"1980-01-01",
    "date:inception_upper":"1980-01-31",
    "iso:country":"GB",
    "wof:name":"SK8 4JQ",
    "wof:placetype":"postalcode"
},
  "geometry": {"coordinates":[-2.241854,53.385655],"type":"Point"}
}