{
  "type": "Feature",
  "properties": {
    "iso:country":"GB",
    "wof:name":"SK8 4JQ",
    "wof:placetype":"postalcode"
},
  "geometry": {"coordinates":[-2.24185427389953,53.38565508846466],"type":"Point"}
}