{
  "type": "Feature",
  "properties": {
    "date:inception_lower": "1980-01-01",
    "date:inception_upper": "1980-01-01",
    "iso:country": "GB",
    "wof:name": "N1 8TW",
    "wof:placetype": "postalcode"
  },
  "geometry": {"coordinates":[-0.093283,51.53847],"type":"Point"}
}
