{
  "type": "Feature",
  "properties": {
    "iso:country":"GB",
    "wof:name":"ML9 3FB",
    "wof:placetype":"postalcode"
},
  "geometry": {"coordinates":[-3.93599423123788,55.72998454858477],"type":"Point"}
}