{
  "type": "Feature",
  "properties": {
    "date:inception_lower": "2000-12-01",
    "date:inception_upper": "2000-12-01",
    "iso:country": "GB",
    "wof:name": "ML9 3FB",
    "wof:placetype": "postalcode"
  },
  "geometry": {"coordinates":[-3.935994,55.729985],"type":"Point"}
}
