{
  "type": "Feature",
  "properties": {
    "iso:country": "GB",
    "wof:name": "CF64 5TZ",
    "wof:placetype": "postalcode"
  },
  "geometry": {"coordinates":[-3.211827,51.409088],"type":"Point"}
}
