{
  "type": "Feature",
  "properties": {
    "iso:country":"GB",
    "wof:name":"CF64 5TZ",
    "wof:placetype":"postalcode"
},
  "geometry": {"coordinates":[-3.21182741179854,51.4090882556441],"type":"Point"}
}