{
  "type": "Feature",
  "properties": {
    "iso:country": "GB",
    "wof:name": "LU3 4BX",
    "wof:placetype": "postalcode"
  },
  "geometry": {"coordinates":[-0.448514,51.924628],"type":"Point"}
}
