{
  "type": "Feature",
  "properties": {
    "iso:country":"GB",
    "wof:name":"WS11 1JG",
    "wof:placetype":"postalcode"
},
  "geometry": {"coordinates":[-2.04504208081795,52.69535802979112],"type":"Point"}
}