{
  "type": "Feature",
  "properties": {
    "date:inception_lower": "1986-04-01",
    "date:inception_upper": "1986-04-01",
    "iso:country": "GB",
    "wof:name": "IP32 7EU",
    "wof:placetype": "postalcode"
  },
  "geometry": {"coordinates":[0.744872,52.242168],"type":"Point"}
}
