{
  "type": "Feature",
  "properties": {
    "iso:country":"GB",
    "wof:name":"HA2 8NW",
    "wof:placetype":"postalcode"
},
  "geometry": {"coordinates":[-0.36126955453711,51.56073743748277],"type":"Point"}
}