{
  "type": "Feature",
  "properties": {
    "iso:country": "GB",
    "wof:name": "HA2 8NW",
    "wof:placetype": "postalcode"
  },
  "geometry": {"coordinates":[-0.36127,51.560737],"type":"Point"}
}
