{
  "type": "Feature",
  "properties": {
    "iso:country": "GB",
    "wof:name": "HA6 1RF",
    "wof:placetype": "postalcode"
  },
  "geometry": {"coordinates":[-0.409509,51.604635],"type":"Point"}
}
