{
  "type": "Feature",
  "properties": {
    "iso:country":"GB",
    "wof:name":"HA6 1RF",
    "wof:placetype":"postalcode"
},
  "geometry": {"coordinates":[-0.40950952490075,51.6046353032406],"type":"Point"}
}