{
  "type": "Feature",
  "properties": {
    "iso:country":"GB",
    "wof:name":"EX6 6NL",
    "wof:placetype":"postalcode"
},
  "geometry": {"coordinates":[-3.79193925030781,50.71043551922168],"type":"Point"}
}