{
  "type": "Feature",
  "properties": {
    "date:inception_lower": "1980-01-01",
    "date:inception_upper": "1980-01-01",
    "iso:country": "GB",
    "wof:name": "RG1 6JB",
    "wof:placetype": "postalcode"
  },
  "geometry": {"coordinates":[-0.989133,51.446526],"type":"Point"}
}
