{
  "type": "Feature",
  "properties": {
    "iso:country":"GB",
    "wof:name":"EH26 8JZ",
    "wof:placetype":"postalcode"
},
  "geometry": {"coordinates":[-3.20904622833924,55.83617606363923],"type":"Point"}
}