{
  "type": "Feature",
  "properties": {
    "iso:country":"GB",
    "wof:name":"DA5 1AD",
    "wof:placetype":"postalcode"
},
  "geometry": {"coordinates":[0.14717370325773,51.4415530990799],"type":"Point"}
}