{
  "type": "Feature",
  "properties": {
    "iso:country":"GB",
    "wof:name":"S3 9QX",
    "wof:placetype":"postalcode"
},
  "geometry": {"coordinates":[-1.47630544930709,53.39626770050196],"type":"Point"}
}