{
  "type": "Feature",
  "properties": {
    "iso:country":"GB",
    "wof:name":"IP8 3NU",
    "wof:placetype":"postalcode"
},
  "geometry": {"coordinates":[1.02760070166159,52.05674622817376],"type":"Point"}
}