{
  "type": "Feature",
  "properties": {
    "iso:country": "GB",
    "wof:name": "IP8 3NU",
    "wof:placetype": "postalcode"
  },
  "geometry": {"coordinates":[1.027601,52.056746],"type":"Point"}
}
