{
  "type": "Feature",
  "properties": {
    "iso:country": "GB",
    "wof:name": "DD7 7NS",
    "wof:placetype": "postalcode"
  },
  "geometry": {"coordinates":[-2.738895,56.496439],"type":"Point"}
}
