{
  "type": "Feature",
  "properties": {
    "date:inception_lower": "1984-02-01",
    "date:inception_upper": "1984-02-01",
    "iso:country": "GB",
    "wof:name": "DD7 7NS",
    "wof:placetype": "postalcode"
  },
  "geometry": {"coordinates":[-2.738895,56.496439],"type":"Point"}
}
