{
  "type": "Feature",
  "properties": {
    "iso:country":"GB",
    "wof:name":"DD7 7NS",
    "wof:placetype":"postalcode"
},
  "geometry": {"coordinates":[-2.73889547503705,56.49643887645154],"type":"Point"}
}