{
  "type": "Feature",
  "properties": {
    "iso:country": "GB",
    "wof:name": "LE16 7LN",
    "wof:placetype": "postalcode"
  },
  "geometry": {"coordinates":[-0.920494,52.487518],"type":"Point"}
}
