{
  "type": "Feature",
  "properties": {
    "date:inception_lower": "1980-01-01",
    "date:inception_upper": "1980-01-01",
    "iso:country": "GB",
    "wof:name": "LN6 9PU",
    "wof:placetype": "postalcode"
  },
  "geometry": {"coordinates":[-0.657555,53.157718],"type":"Point"}
}
