{
  "type": "Feature",
  "properties": {
    "iso:country":"GB",
    "wof:name":"KY9 1HU",
    "wof:placetype":"postalcode"
},
  "geometry": {"coordinates":[-2.86325323557712,56.25601046005033],"type":"Point"}
}