{
  "type": "Feature",
  "properties": {
    "iso:country": "GB",
    "wof:name": "KY9 1HU",
    "wof:placetype": "postalcode"
  },
  "geometry": {"coordinates":[-2.863879,56.255756],"type":"Point"}
}
