{
  "type": "Feature",
  "properties": {
    "iso:country":"GB",
    "wof:name":"NG4 1LH",
    "wof:placetype":"postalcode"
},
  "geometry": {"coordinates":[-1.10528162540158,52.97204009906386],"type":"Point"}
}