{
  "type": "Feature",
  "properties": {
    "iso:country":"GB",
    "wof:name":"EX12 3ED",
    "wof:placetype":"postalcode"
},
  "geometry": {"coordinates":[-3.09011333973751,50.69820428162557],"type":"Point"}
}