{
  "type": "Feature",
  "properties": {
    "iso:country": "GB",
    "wof:name": "EX12 3ED",
    "wof:placetype": "postalcode"
  },
  "geometry": {"coordinates":[-3.090113,50.698204],"type":"Point"}
}
