{
  "type": "Feature",
  "properties": {
    "iso:country":"GB",
    "wof:name":"DL17 8RN",
    "wof:placetype":"postalcode"
},
  "geometry": {"coordinates":[-1.57342360828118,54.68424519912072],"type":"Point"}
}