{
  "type": "Feature",
  "properties": {
    "date:inception_lower": "2023-02-01",
    "date:inception_upper": "2023-02-01",
    "iso:country": "GB",
    "wof:name": "S35 0ES",
    "wof:placetype": "postalcode"
  },
  "geometry": {"coordinates":[-1.545319,53.442814],"type":"Point"}
}
