{
  "type": "Feature",
  "properties": {
    "iso:country":"GB",
    "wof:name":"B30 2QG",
    "wof:placetype":"postalcode"
},
  "geometry": {"coordinates":[-1.91324961310469,52.42556809805795],"type":"Point"}
}