{
  "type": "Feature",
  "properties": {
    "iso:country":"GB",
    "wof:name":"S81 0EL",
    "wof:placetype":"postalcode"
},
  "geometry": {"coordinates":[-1.10025978917092,53.30997139901617],"type":"Point"}
}