{
  "type": "Feature",
  "properties": {
    "iso:country": "GB",
    "wof:name": "S81 0EL",
    "wof:placetype": "postalcode"
  },
  "geometry": {"coordinates":[-1.10026,53.309971],"type":"Point"}
}
