{
  "type": "Feature",
  "properties": {
    "iso:country":"GB",
    "wof:name":"SP5 2EE",
    "wof:placetype":"postalcode"
},
  "geometry": {"coordinates":[-1.63665043173283,50.980337276326],"type":"Point"}
}