{
  "type": "Feature",
  "properties": {
    "iso:country":"GB",
    "wof:name":"LL57 3LZ",
    "wof:placetype":"postalcode"
},
  "geometry": {"coordinates":[-4.02048764854954,53.12328607376539],"type":"Point"}
}