{
  "type": "Feature",
  "properties": {
    "date:inception_lower": "1980-01-01",
    "date:inception_upper": "1980-01-01",
    "iso:country": "GB",
    "wof:name": "LL57 3LZ",
    "wof:placetype": "postalcode"
  },
  "geometry": {"coordinates":[-4.020488,53.123286],"type":"Point"}
}
