{
  "type": "Feature",
  "properties": {
    "iso:country":"GB",
    "wof:name":"G72 8TU",
    "wof:placetype":"postalcode"
},
  "geometry": {"coordinates":[-4.15614881960892,55.80975476874973],"type":"Point"}
}