{
  "type": "Feature",
  "properties": {
    "iso:country": "GB",
    "wof:name": "TN24 0GT",
    "wof:placetype": "postalcode"
  },
  "geometry": {"coordinates":[0.882537,51.130029],"type":"Point"}
}
