{
  "type": "Feature",
  "properties": {
    "iso:country":"GB",
    "wof:name":"DE5 3PR",
    "wof:placetype":"postalcode"
},
  "geometry": {"coordinates":[-1.409750323534,53.04271802646035],"type":"Point"}
}