{
  "type": "Feature",
  "properties": {
    "iso:country": "GB",
    "wof:name": "PL5 4BT",
    "wof:placetype": "postalcode"
  },
  "geometry": {"coordinates":[-4.146491,50.415328],"type":"Point"}
}
