{
  "type": "Feature",
  "properties": {
    "iso:country": "GB",
    "wof:name": "NE33 2JZ",
    "wof:placetype": "postalcode"
  },
  "geometry": {"coordinates":[-1.417168,55.003075],"type":"Point"}
}
