{
  "type": "Feature",
  "properties": {
    "iso:country":"GB",
    "wof:name":"NE4 9SH",
    "wof:placetype":"postalcode"
},
  "geometry": {"coordinates":[-1.66448386065277,54.98337580917907],"type":"Point"}
}