{
  "type": "Feature",
  "properties": {
    "iso:country": "GB",
    "wof:name": "LE5 6PX",
    "wof:placetype": "postalcode"
  },
  "geometry": {"coordinates":[-1.060182,52.629019],"type":"Point"}
}
