{
  "type": "Feature",
  "properties": {
    "iso:country": "GB",
    "wof:name": "EH53 0HP",
    "wof:placetype": "postalcode"
  },
  "geometry": {"coordinates":[-3.486029,55.899265],"type":"Point"}
}
