{
  "type": "Feature",
  "properties": {
    "iso:country":"GB",
    "wof:name":"EH53 0HP",
    "wof:placetype":"postalcode"
},
  "geometry": {"coordinates":[-3.48668454997644,55.89999833157094],"type":"Point"}
}