{
  "type": "Feature",
  "properties": {
    "iso:country":"GB",
    "wof:name":"SR3 4LL",
    "wof:placetype":"postalcode"
},
  "geometry": {"coordinates":[-1.43002729753079,54.88104718763838],"type":"Point"}
}