{
  "type": "Feature",
  "properties": {
    "iso:country":"GB",
    "wof:name":"KA6 6NR",
    "wof:placetype":"postalcode"
},
  "geometry": {"coordinates":[-4.5183280130241,55.44876182924349],"type":"Point"}
}