{
  "type": "Feature",
  "properties": {
    "iso:country": "GB",
    "wof:name": "KA6 6NR",
    "wof:placetype": "postalcode"
  },
  "geometry": {"coordinates":[-4.518328,55.448762],"type":"Point"}
}
