{
  "type": "Feature",
  "properties": {
    "iso:country":"GB",
    "wof:name":"RM7 7EB",
    "wof:placetype":"postalcode"
},
  "geometry": {"coordinates":[0.17248147613872,51.58140291439485],"type":"Point"}
}