{
  "type": "Feature",
  "properties": {
    "date:inception_lower":"1980-01-01",
    "date:inception_upper":"1980-01-31",
    "iso:country":"GB",
    "wof:name":"LL53 7YW",
    "wof:placetype":"postalcode"
},
  "geometry": {"coordinates":[-4.488276,52.884214],"type":"Point"}
}