{
  "type": "Feature",
  "properties": {
    "iso:country": "GB",
    "wof:name": "LL53 7YW",
    "wof:placetype": "postalcode"
  },
  "geometry": {"coordinates":[-4.488276,52.884214],"type":"Point"}
}
