{
  "type": "Feature",
  "properties": {
    "iso:country": "GB",
    "wof:name": "PO19 1AX",
    "wof:placetype": "postalcode"
  },
  "geometry": {"coordinates":[-0.780586,50.837993],"type":"Point"}
}
