{
  "type": "Feature",
  "properties": {
    "iso:country":"GB",
    "wof:name":"PO19 1AX",
    "wof:placetype":"postalcode"
},
  "geometry": {"coordinates":[-0.78058590972783,50.83799286789208],"type":"Point"}
}