{
  "type": "Feature",
  "properties": {
    "iso:country":"GB",
    "wof:name":"IP14 1NS",
    "wof:placetype":"postalcode"
},
  "geometry": {"coordinates":[0.98792756983928,52.19595373619683],"type":"Point"}
}