{
  "type": "Feature",
  "properties": {
    "iso:country":"GB",
    "wof:name":"LL41 4DN",
    "wof:placetype":"postalcode"
},
  "geometry": {"coordinates":[-3.92604403674921,52.98942837723396],"type":"Point"}
}