{
  "type": "Feature",
  "properties": {
    "iso:country": "GB",
    "wof:name": "BS22 7XL",
    "wof:placetype": "postalcode"
  },
  "geometry": {"coordinates":[-2.898577,51.361699],"type":"Point"}
}
