{
  "type": "Feature",
  "properties": {
    "date:inception_lower": "1980-01-01",
    "date:inception_upper": "1980-01-01",
    "iso:country": "GB",
    "wof:name": "ST1 3HZ",
    "wof:placetype": "postalcode"
  },
  "geometry": {"coordinates":[-2.167919,53.016007],"type":"Point"}
}
