{
  "type": "Feature",
  "properties": {
    "iso:country":"GB",
    "wof:name":"LE3 0HB",
    "wof:placetype":"postalcode"
},
  "geometry": {"coordinates":[-1.15373109911104,52.62614622030986],"type":"Point"}
}