{
  "type": "Feature",
  "properties": {
    "iso:country":"GB",
    "wof:name":"AB11 5AF",
    "wof:placetype":"postalcode"
},
  "geometry": {"coordinates":[-2.09292500200943,57.14649177740427],"type":"Point"}
}