{
  "type": "Feature",
  "properties": {
    "iso:country":"GB",
    "wof:name":"GU3 3JW",
    "wof:placetype":"postalcode"
},
  "geometry": {"coordinates":[-0.61086542197381,51.2602643737374],"type":"Point"}
}