{
  "type": "Feature",
  "properties": {
    "iso:country": "GB",
    "wof:name": "GU3 3JW",
    "wof:placetype": "postalcode"
  },
  "geometry": {"coordinates":[-0.611052,51.260084],"type":"Point"}
}
