{
  "type": "Feature",
  "properties": {
    "iso:country":"GB",
    "wof:name":"W14 0JD",
    "wof:placetype":"postalcode"
},
  "geometry": {"coordinates":[-0.21816976549948,51.49649624983083],"type":"Point"}
}