{
  "type": "Feature",
  "properties": {
    "date:inception_lower": "1980-01-01",
    "date:inception_upper": "1980-01-01",
    "iso:country": "GB",
    "wof:name": "W14 0JD",
    "wof:placetype": "postalcode"
  },
  "geometry": {"coordinates":[-0.21817,51.496496],"type":"Point"}
}
