{
  "type": "Feature",
  "properties": {
    "date:inception_lower": "2000-06-01",
    "date:inception_upper": "2000-06-01",
    "iso:country": "GB",
    "wof:name": "OX16 2NN",
    "wof:placetype": "postalcode"
  },
  "geometry": {"coordinates":[-1.349583,52.068725],"type":"Point"}
}
