{
  "type": "Feature",
  "properties": {
    "iso:country":"GB",
    "wof:name":"DH6 3LE",
    "wof:placetype":"postalcode"
},
  "geometry": {"coordinates":[-1.41775655561952,54.74169687345717],"type":"Point"}
}