{
  "type": "Feature",
  "properties": {
    "date:inception_lower":"1980-01-01",
    "date:inception_upper":"1980-01-31",
    "iso:country":"GB",
    "wof:name":"DH6 3LE",
    "wof:placetype":"postalcode"
},
  "geometry": {"coordinates":[-1.417757,54.741697],"type":"Point"}
}