{
  "type": "Feature",
  "properties": {
    "date:inception_lower": "1984-10-01",
    "date:inception_upper": "1984-10-01",
    "iso:country": "GB",
    "wof:name": "HR4 0BA",
    "wof:placetype": "postalcode"
  },
  "geometry": {"coordinates":[-2.717725,52.056814],"type":"Point"}
}
