{
  "type": "Feature",
  "properties": {
    "iso:country":"GB",
    "wof:name":"HR4 0BA",
    "wof:placetype":"postalcode"
},
  "geometry": {"coordinates":[-2.71773808881183,52.05680528129174],"type":"Point"}
}