{
  "type": "Feature",
  "properties": {
    "iso:country":"GB",
    "wof:name":"NG3 6NE",
    "wof:placetype":"postalcode"
},
  "geometry": {"coordinates":[-1.11473013830169,52.96730143165438],"type":"Point"}
}