{
  "type": "Feature",
  "properties": {
    "iso:country":"GB",
    "wof:name":"KT1 9ZX",
    "wof:placetype":"postalcode"
},
  "geometry": {"coordinates":[-0.30593893866376,51.40771990863136],"type":"Point"}
}