{
  "type": "Feature",
  "properties": {
    "iso:country":"GB",
    "wof:name":"NE12 6LS",
    "wof:placetype":"postalcode"
},
  "geometry": {"coordinates":[-1.55829913893307,55.03382701491138],"type":"Point"}
}