{
  "type": "Feature",
  "properties": {
    "iso:country":"GB",
    "wof:name":"CH60 0BB",
    "wof:placetype":"postalcode"
},
  "geometry": {"coordinates":[-3.09272791672422,53.32443685404893],"type":"Point"}
}