{
  "type": "Feature",
  "properties": {
    "iso:country": "GB",
    "wof:name": "SE13 5NZ",
    "wof:placetype": "postalcode"
  },
  "geometry": {"coordinates":[-0.004046,51.460107],"type":"Point"}
}
