{
  "type": "Feature",
  "properties": {
    "iso:country":"GB",
    "wof:name":"SE13 5NZ",
    "wof:placetype":"postalcode"
},
  "geometry": {"coordinates":[-0.00404597795964,51.46010695783104],"type":"Point"}
}