{
  "type": "Feature",
  "properties": {
    "iso:country":"GB",
    "wof:name":"BL3 4RX",
    "wof:placetype":"postalcode"
},
  "geometry": {"coordinates":[-2.48068819254542,53.57009563356657],"type":"Point"}
}