{
  "type": "Feature",
  "properties": {
    "iso:country":"GB",
    "wof:name":"DN6 0EW",
    "wof:placetype":"postalcode"
},
  "geometry": {"coordinates":[-1.15062472359299,53.61663208719486],"type":"Point"}
}