{
  "type": "Feature",
  "properties": {
    "date:inception_lower": "1980-01-01",
    "date:inception_upper": "1980-01-01",
    "iso:country": "GB",
    "wof:name": "DN6 0EW",
    "wof:placetype": "postalcode"
  },
  "geometry": {"coordinates":[-1.150625,53.616632],"type":"Point"}
}
