{
  "type": "Feature",
  "properties": {
    "iso:country": "GB",
    "wof:name": "RG4 9ET",
    "wof:placetype": "postalcode"
  },
  "geometry": {"coordinates":[-1.001189,51.492155],"type":"Point"}
}
