{
  "type": "Feature",
  "properties": {
    "iso:country": "GB",
    "wof:name": "SN2 7JJ",
    "wof:placetype": "postalcode"
  },
  "geometry": {"coordinates":[-1.76213,51.581089],"type":"Point"}
}
