{
  "type": "Feature",
  "properties": {
    "iso:country": "GB",
    "wof:name": "PL12 6QA",
    "wof:placetype": "postalcode"
  },
  "geometry": {"coordinates":[-4.255608,50.454256],"type":"Point"}
}
