{
  "type": "Feature",
  "properties": {
    "date:inception_lower":"1986-04-01",
    "date:inception_upper":"1986-04-30",
    "iso:country":"GB",
    "wof:name":"IP24 3ET",
    "wof:placetype":"postalcode"
},
  "geometry": {"coordinates":[0.74683,52.406223],"type":"Point"}
}