{
  "type": "Feature",
  "properties": {
    "iso:country": "GB",
    "wof:name": "IP24 3ET",
    "wof:placetype": "postalcode"
  },
  "geometry": {"coordinates":[0.74683,52.406223],"type":"Point"}
}
