{
  "type": "Feature",
  "properties": {
    "iso:country":"GB",
    "wof:name":"BR2 0RW",
    "wof:placetype":"postalcode"
},
  "geometry": {"coordinates":[-0.00091284639853,51.3980303209698],"type":"Point"}
}