{
  "type": "Feature",
  "properties": {
    "iso:country":"GB",
    "wof:name":"BS20 6LZ",
    "wof:placetype":"postalcode"
},
  "geometry": {"coordinates":[-2.77970254266255,51.4830129729387],"type":"Point"}
}