{
  "type": "Feature",
  "properties": {
    "iso:country": "GB",
    "wof:name": "LE15 8QP",
    "wof:placetype": "postalcode"
  },
  "geometry": {"coordinates":[-0.765804,52.651815],"type":"Point"}
}
