{
  "type": "Feature",
  "properties": {
    "iso:country":"GB",
    "wof:name":"LE15 8QP",
    "wof:placetype":"postalcode"
},
  "geometry": {"coordinates":[-0.76580391375475,52.6518152753874],"type":"Point"}
}