{
  "type": "Feature",
  "properties": {
    "date:inception_lower": "1981-09-01",
    "date:inception_upper": "1981-09-01",
    "iso:country": "GB",
    "wof:name": "BB9 8AJ",
    "wof:placetype": "postalcode"
  },
  "geometry": {"coordinates":[-2.20222,53.840094],"type":"Point"}
}
