{
  "type": "Feature",
  "properties": {
    "iso:country":"GB",
    "wof:name":"BB9 8AJ",
    "wof:placetype":"postalcode"
},
  "geometry": {"coordinates":[-2.20222030715863,53.84009397307647],"type":"Point"}
}