{
  "type": "Feature",
  "properties": {
    "iso:country":"GB",
    "wof:name":"LD3 0EL",
    "wof:placetype":"postalcode"
},
  "geometry": {"coordinates":[-3.20068318343027,51.97696994605565],"type":"Point"}
}