{
  "type": "Feature",
  "properties": {
    "iso:country":"GB",
    "wof:name":"SA18 3PR",
    "wof:placetype":"postalcode"
},
  "geometry": {"coordinates":[-4.00749886091581,51.77613247557389],"type":"Point"}
}