{
  "type": "Feature",
  "properties": {
    "date:inception_lower": "2005-10-01",
    "date:inception_upper": "2005-10-01",
    "iso:country": "GB",
    "wof:name": "SA18 3PR",
    "wof:placetype": "postalcode"
  },
  "geometry": {"coordinates":[-4.007499,51.776132],"type":"Point"}
}
