{
  "type": "Feature",
  "properties": {
    "iso:country": "GB",
    "wof:name": "SP11 8DB",
    "wof:placetype": "postalcode"
  },
  "geometry": {"coordinates":[-1.538787,51.208905],"type":"Point"}
}
