{
  "type": "Feature",
  "properties": {
    "iso:country":"GB",
    "wof:name":"N14 4DA",
    "wof:placetype":"postalcode"
},
  "geometry": {"coordinates":[-0.13540639756071,51.63819832424136],"type":"Point"}
}