{
  "type": "Feature",
  "properties": {
    "iso:country":"GB",
    "wof:name":"PO16 9NE",
    "wof:placetype":"postalcode"
},
  "geometry": {"coordinates":[-1.12723699377232,50.84038032716504],"type":"Point"}
}