{
  "type": "Feature",
  "properties": {
    "iso:country":"GB",
    "wof:name":"GU3 2HZ",
    "wof:placetype":"postalcode"
},
  "geometry": {"coordinates":[-0.69522821335819,51.25401410548838],"type":"Point"}
}