{
  "type": "Feature",
  "properties": {
    "iso:country": "GB",
    "wof:name": "NW7 4NN",
    "wof:placetype": "postalcode"
  },
  "geometry": {"coordinates":[-0.245941,51.621477],"type":"Point"}
}
