{
  "type": "Feature",
  "properties": {
    "iso:country":"GB",
    "wof:name":"NW7 4NN",
    "wof:placetype":"postalcode"
},
  "geometry": {"coordinates":[-0.24594109027563,51.62147658493576],"type":"Point"}
}