{
  "type": "Feature",
  "properties": {
    "iso:country":"GB",
    "wof:name":"PO18 9BH",
    "wof:placetype":"postalcode"
},
  "geometry": {"coordinates":[-0.82035460116254,50.86997549602071],"type":"Point"}
}