{
  "type": "Feature",
  "properties": {
    "iso:country": "GB",
    "wof:name": "FY4 3PG",
    "wof:placetype": "postalcode"
  },
  "geometry": {"coordinates":[-3.031141,53.787456],"type":"Point"}
}
