{
  "type": "Feature",
  "properties": {
    "iso:country":"GB",
    "wof:name":"S61 2BN",
    "wof:placetype":"postalcode"
},
  "geometry": {"coordinates":[-1.4042993527989,53.44050515311424],"type":"Point"}
}