{
  "type": "Feature",
  "properties": {
    "iso:country": "GB",
    "wof:name": "RG7 3EL",
    "wof:placetype": "postalcode"
  },
  "geometry": {"coordinates":[-1.062839,51.395822],"type":"Point"}
}
