{
  "type": "Feature",
  "properties": {
    "iso:country": "GB",
    "wof:name": "BN22 0TN",
    "wof:placetype": "postalcode"
  },
  "geometry": {"coordinates":[0.267482,50.80294],"type":"Point"}
}
