{
  "type": "Feature",
  "properties": {
    "iso:country":"GB",
    "wof:name":"UB10 8FW",
    "wof:placetype":"postalcode"
},
  "geometry": {"coordinates":[-0.43717252685076,51.56902049955436],"type":"Point"}
}