{
  "type": "Feature",
  "properties": {
    "date:inception_lower": "1980-01-01",
    "date:inception_upper": "1980-01-01",
    "iso:country": "GB",
    "wof:name": "PL5 2EE",
    "wof:placetype": "postalcode"
  },
  "geometry": {"coordinates":[-4.180023,50.408309],"type":"Point"}
}
