{
  "type": "Feature",
  "properties": {
    "iso:country": "GB",
    "wof:name": "PL5 2EE",
    "wof:placetype": "postalcode"
  },
  "geometry": {"coordinates":[-4.180023,50.408309],"type":"Point"}
}
