{
  "type": "Feature",
  "properties": {
    "iso:country":"GB",
    "wof:name":"PL5 2EE",
    "wof:placetype":"postalcode"
},
  "geometry": {"coordinates":[-4.18002272603189,50.40830870566313],"type":"Point"}
}