{
  "type": "Feature",
  "properties": {
    "iso:country":"GB",
    "wof:name":"BD22 6NW",
    "wof:placetype":"postalcode"
},
  "geometry": {"coordinates":[-1.92911348257385,53.85895679710094],"type":"Point"}
}