{
  "type": "Feature",
  "properties": {
    "iso:country":"GB",
    "wof:name":"WS11 7JY",
    "wof:placetype":"postalcode"
},
  "geometry": {"coordinates":[-2.01290166096689,52.68695165670213],"type":"Point"}
}