{
  "type": "Feature",
  "properties": {
    "date:inception_lower": "2007-11-01",
    "date:inception_upper": "2007-11-01",
    "iso:country": "GB",
    "wof:name": "WS11 7JY",
    "wof:placetype": "postalcode"
  },
  "geometry": {"coordinates":[-2.012902,52.686952],"type":"Point"}
}
