{
  "type": "Feature",
  "properties": {
    "iso:country":"GB",
    "wof:name":"CH6 5JD",
    "wof:placetype":"postalcode"
},
  "geometry": {"coordinates":[-3.12932462526071,53.24567393635645],"type":"Point"}
}