{
  "type": "Feature",
  "properties": {
    "iso:country":"GB",
    "wof:name":"N13 5QH",
    "wof:placetype":"postalcode"
},
  "geometry": {"coordinates":[-0.08999675152386,51.62380891493269],"type":"Point"}
}