{
  "type": "Feature",
  "properties": {
    "date:inception_lower": "1980-01-01",
    "date:inception_upper": "1980-01-01",
    "iso:country": "GB",
    "wof:name": "N13 5QH",
    "wof:placetype": "postalcode"
  },
  "geometry": {"coordinates":[-0.089997,51.623809],"type":"Point"}
}
