{
  "type": "Feature",
  "properties": {
    "date:inception_lower": "1980-01-01",
    "date:inception_upper": "1980-01-01",
    "iso:country": "GB",
    "wof:name": "B96 6BG",
    "wof:placetype": "postalcode"
  },
  "geometry": {"coordinates":[-1.939904,52.251189],"type":"Point"}
}
