{
  "type": "Feature",
  "properties": {
    "iso:country": "GB",
    "wof:name": "SA42 0YH",
    "wof:placetype": "postalcode"
  },
  "geometry": {"coordinates":[-4.897989,52.002299],"type":"Point"}
}
