{
  "type": "Feature",
  "properties": {
    "iso:country":"GB",
    "wof:name":"SA42 0YH",
    "wof:placetype":"postalcode"
},
  "geometry": {"coordinates":[-4.89791653698964,52.00227593564699],"type":"Point"}
}