{
  "type": "Feature",
  "properties": {
    "iso:country":"GB",
    "wof:name":"BD18 2ED",
    "wof:placetype":"postalcode"
},
  "geometry": {"coordinates":[-1.76489293445074,53.82702947316412],"type":"Point"}
}