{
  "type": "Feature",
  "properties": {
    "iso:country":"GB",
    "wof:name":"SO30 3NA",
    "wof:placetype":"postalcode"
},
  "geometry": {"coordinates":[-1.34550281308853,50.93143667330975],"type":"Point"}
}