{
  "type": "Feature",
  "properties": {
    "date:inception_lower": "1995-01-01",
    "date:inception_upper": "1995-01-01",
    "iso:country": "GB",
    "wof:name": "SO30 3NA",
    "wof:placetype": "postalcode"
  },
  "geometry": {"coordinates":[-1.345478,50.931437],"type":"Point"}
}
