{
  "type": "Feature",
  "properties": {
    "iso:country":"GB",
    "wof:name":"DN11 9BX",
    "wof:placetype":"postalcode"
},
  "geometry": {"coordinates":[-1.14626896261245,53.46518754026061],"type":"Point"}
}