{
  "type": "Feature",
  "properties": {
    "iso:country":"GB",
    "wof:name":"GL12 7PF",
    "wof:placetype":"postalcode"
},
  "geometry": {"coordinates":[-2.37906048275764,51.65034502357991],"type":"Point"}
}