{
  "type": "Feature",
  "properties": {
    "iso:country": "GB",
    "wof:name": "GL12 7PF",
    "wof:placetype": "postalcode"
  },
  "geometry": {"coordinates":[-2.38323,51.649686],"type":"Point"}
}
