{
  "type": "Feature",
  "properties": {
    "iso:country":"GB",
    "wof:name":"BN5 9AY",
    "wof:placetype":"postalcode"
},
  "geometry": {"coordinates":[-0.24170046026505,50.96953240230941],"type":"Point"}
}