{
  "type": "Feature",
  "properties": {
    "iso:country":"GB",
    "wof:name":"BD5 9DD",
    "wof:placetype":"postalcode"
},
  "geometry": {"coordinates":[-1.76877180974134,53.77641674841907],"type":"Point"}
}