{
  "type": "Feature",
  "properties": {
    "iso:country":"GB",
    "wof:name":"PL6 5QG",
    "wof:placetype":"postalcode"
},
  "geometry": {"coordinates":[-4.10566791491144,50.40386864277882],"type":"Point"}
}