{
  "type": "Feature",
  "properties": {
    "iso:country": "GB",
    "wof:name": "PL6 5QG",
    "wof:placetype": "postalcode"
  },
  "geometry": {"coordinates":[-4.105668,50.403869],"type":"Point"}
}
