{
  "type": "Feature",
  "properties": {
    "date:inception_lower": "1986-07-01",
    "date:inception_upper": "1986-07-01",
    "iso:country": "GB",
    "wof:name": "SW17 9NY",
    "wof:placetype": "postalcode"
  },
  "geometry": {"coordinates":[-0.157655,51.425536],"type":"Point"}
}
