{
  "type": "Feature",
  "properties": {
    "iso:country":"GB",
    "wof:name":"SW17 9NY",
    "wof:placetype":"postalcode"
},
  "geometry": {"coordinates":[-0.15765465722164,51.42553612470001],"type":"Point"}
}