{
  "type": "Feature",
  "properties": {
    "iso:country": "GB",
    "wof:name": "HA7 4PR",
    "wof:placetype": "postalcode"
  },
  "geometry": {"coordinates":[-0.297224,51.62457],"type":"Point"}
}
