{
  "type": "Feature",
  "properties": {
    "iso:country":"GB",
    "wof:name":"LE9 9LX",
    "wof:placetype":"postalcode"
},
  "geometry": {"coordinates":[-1.34250877462181,52.62694828374819],"type":"Point"}
}