{
  "type": "Feature",
  "properties": {
    "iso:country":"GB",
    "wof:name":"N13 4JP",
    "wof:placetype":"postalcode"
},
  "geometry": {"coordinates":[-0.11484462875126,51.61582066254079],"type":"Point"}
}