{
  "type": "Feature",
  "properties": {
    "date:inception_lower": "1980-01-01",
    "date:inception_upper": "1980-01-01",
    "iso:country": "GB",
    "wof:name": "N6 5QB",
    "wof:placetype": "postalcode"
  },
  "geometry": {"coordinates":[-0.136341,51.573765],"type":"Point"}
}
