{
  "type": "Feature",
  "properties": {
    "iso:country":"GB",
    "wof:name":"DT1 3AB",
    "wof:placetype":"postalcode"
},
  "geometry": {"coordinates":[-2.46361665025029,50.71249755611777],"type":"Point"}
}