{
  "type": "Feature",
  "properties": {
    "date:inception_lower": "2008-06-01",
    "date:inception_upper": "2008-06-01",
    "iso:country": "GB",
    "wof:name": "DT1 3AB",
    "wof:placetype": "postalcode"
  },
  "geometry": {"coordinates":[-2.463615,50.71247],"type":"Point"}
}
