{
  "type": "Feature",
  "properties": {
    "iso:country": "GB",
    "wof:name": "DT1 3AB",
    "wof:placetype": "postalcode"
  },
  "geometry": {"coordinates":[-2.463615,50.712551],"type":"Point"}
}
