{
  "type": "Feature",
  "properties": {
    "iso:country": "GB",
    "wof:name": "WS12 1TB",
    "wof:placetype": "postalcode"
  },
  "geometry": {"coordinates":[-1.99411,52.71402],"type":"Point"}
}
