{
  "type": "Feature",
  "properties": {
    "iso:country":"GB",
    "wof:name":"W2 3JL",
    "wof:placetype":"postalcode"
},
  "geometry": {"coordinates":[-0.18664613423957,51.51142614675039],"type":"Point"}
}