{
  "type": "Feature",
  "properties": {
    "iso:country": "GB",
    "wof:name": "W2 3JL",
    "wof:placetype": "postalcode"
  },
  "geometry": {"coordinates":[-0.186646,51.511426],"type":"Point"}
}
