{
  "type": "Feature",
  "properties": {
    "iso:country":"GB",
    "wof:name":"CV31 1UN",
    "wof:placetype":"postalcode"
},
  "geometry": {"coordinates":[-1.494391645158,52.27247689522159],"type":"Point"}
}