{
  "type": "Feature",
  "properties": {
    "iso:country":"GB",
    "wof:name":"NR21 8EX",
    "wof:placetype":"postalcode"
},
  "geometry": {"coordinates":[0.85706621353575,52.835068763772],"type":"Point"}
}