{
  "type": "Feature",
  "properties": {
    "iso:country":"GB",
    "wof:name":"M7 4WU",
    "wof:placetype":"postalcode"
},
  "geometry": {"coordinates":[-2.26595192063986,53.51280020169369],"type":"Point"}
}