{
  "type": "Feature",
  "properties": {
    "iso:country": "GB",
    "wof:name": "M7 4WU",
    "wof:placetype": "postalcode"
  },
  "geometry": {"coordinates":[-2.265952,53.5128],"type":"Point"}
}
