{
  "type": "Feature",
  "properties": {
    "iso:country":"GB",
    "wof:name":"SS12 9HF",
    "wof:placetype":"postalcode"
},
  "geometry": {"coordinates":[0.52423411114184,51.60162086573236],"type":"Point"}
}