{
  "type": "Feature",
  "properties": {
    "iso:country":"GB",
    "wof:name":"E3 3QF",
    "wof:placetype":"postalcode"
},
  "geometry": {"coordinates":[-0.01935251352074,51.5211660780765],"type":"Point"}
}