{
  "type": "Feature",
  "properties": {
    "date:inception_lower": "2012-09-01",
    "date:inception_upper": "2012-09-01",
    "iso:country": "GB",
    "wof:name": "E3 3QF",
    "wof:placetype": "postalcode"
  },
  "geometry": {"coordinates":[-0.019352,51.521166],"type":"Point"}
}
