{
  "type": "Feature",
  "properties": {
    "iso:country":"GB",
    "wof:name":"B30 1LT",
    "wof:placetype":"postalcode"
},
  "geometry": {"coordinates":[-1.94198544669013,52.42527097107878],"type":"Point"}
}