{
  "type": "Feature",
  "properties": {
    "iso:country":"GB",
    "wof:name":"CF39 9HU",
    "wof:placetype":"postalcode"
},
  "geometry": {"coordinates":[-3.40374792249765,51.60682159914219],"type":"Point"}
}