{
  "type": "Feature",
  "properties": {
    "iso:country":"GB",
    "wof:name":"NG19 8HY",
    "wof:placetype":"postalcode"
},
  "geometry": {"coordinates":[-1.20149876666119,53.17031885642426],"type":"Point"}
}