{
  "type": "Feature",
  "properties": {
    "iso:country":"GB",
    "wof:name":"WA11 9LP",
    "wof:placetype":"postalcode"
},
  "geometry": {"coordinates":[-2.72596989659031,53.46912966893804],"type":"Point"}
}