{
  "type": "Feature",
  "properties": {
    "iso:country": "GB",
    "wof:name": "L4 2PA",
    "wof:placetype": "postalcode"
  },
  "geometry": {"coordinates":[-2.946804,53.432678],"type":"Point"}
}
