{
  "type": "Feature",
  "properties": {
    "date:inception_lower": "2004-01-01",
    "date:inception_upper": "2004-01-01",
    "iso:country": "GB",
    "wof:name": "L4 2PA",
    "wof:placetype": "postalcode"
  },
  "geometry": {"coordinates":[-2.946532,53.432618],"type":"Point"}
}
