{
  "type": "Feature",
  "properties": {
    "iso:country":"GB",
    "wof:name":"L4 2PA",
    "wof:placetype":"postalcode"
},
  "geometry": {"coordinates":[-2.94653211547526,53.43260107107],"type":"Point"}
}