{
  "type": "Feature",
  "properties": {
    "date:inception_lower": "1980-01-01",
    "date:inception_upper": "1980-01-01",
    "iso:country": "GB",
    "wof:name": "B38 8RH",
    "wof:placetype": "postalcode"
  },
  "geometry": {"coordinates":[-1.933959,52.403187],"type":"Point"}
}
