{
  "type": "Feature",
  "properties": {
    "date:inception_lower": "1980-01-01",
    "date:inception_upper": "1980-01-01",
    "iso:country": "GB",
    "wof:name": "OX11 9PS",
    "wof:placetype": "postalcode"
  },
  "geometry": {"coordinates":[-1.231943,51.570087],"type":"Point"}
}
