{
  "type": "Feature",
  "properties": {
    "iso:country": "GB",
    "wof:name": "PR2 3RY",
    "wof:placetype": "postalcode"
  },
  "geometry": {"coordinates":[-2.725949,53.777082],"type":"Point"}
}
