{
  "type": "Feature",
  "properties": {
    "iso:country":"GB",
    "wof:name":"S70 5HJ",
    "wof:placetype":"postalcode"
},
  "geometry": {"coordinates":[-1.47586924295884,53.53452792274852],"type":"Point"}
}