{
  "type": "Feature",
  "properties": {
    "iso:country": "GB",
    "wof:name": "S70 5HJ",
    "wof:placetype": "postalcode"
  },
  "geometry": {"coordinates":[-1.475869,53.534528],"type":"Point"}
}
