{
  "type": "Feature",
  "properties": {
    "iso:country":"GB",
    "wof:name":"MK45 1QJ",
    "wof:placetype":"postalcode"
},
  "geometry": {"coordinates":[-0.49868265987173,52.00142723968513],"type":"Point"}
}