{
  "type": "Feature",
  "properties": {
    "iso:country": "GB",
    "wof:name": "MK45 1QJ",
    "wof:placetype": "postalcode"
  },
  "geometry": {"coordinates":[-0.498683,52.001427],"type":"Point"}
}
