{
  "type": "Feature",
  "properties": {
    "iso:country":"GB",
    "wof:name":"EN2 6JA",
    "wof:placetype":"postalcode"
},
  "geometry": {"coordinates":[-0.0816922346875,51.65182872292074],"type":"Point"}
}