{
  "type": "Feature",
  "properties": {
    "iso:country":"GB",
    "wof:name":"NW9 6RU",
    "wof:placetype":"postalcode"
},
  "geometry": {"coordinates":[-0.25064267289997,51.58861709700418],"type":"Point"}
}