{
  "type": "Feature",
  "properties": {
    "iso:country": "GB",
    "wof:name": "SG6 4EA",
    "wof:placetype": "postalcode"
  },
  "geometry": {"coordinates":[-0.245035,51.984029],"type":"Point"}
}
