{
  "type": "Feature",
  "properties": {
    "iso:country":"GB",
    "wof:name":"SG6 4EA",
    "wof:placetype":"postalcode"
},
  "geometry": {"coordinates":[-0.24503523459357,51.98402890064473],"type":"Point"}
}