{
  "type": "Feature",
  "properties": {
    "iso:country": "GB",
    "wof:name": "LN1 2SR",
    "wof:placetype": "postalcode"
  },
  "geometry": {"coordinates":[-0.622992,53.286147],"type":"Point"}
}
