{
  "type": "Feature",
  "properties": {
    "iso:country":"GB",
    "wof:name":"RH10 4HU",
    "wof:placetype":"postalcode"
},
  "geometry": {"coordinates":[-0.08231211213353,51.12624888320128],"type":"Point"}
}