{
  "type": "Feature",
  "properties": {
    "iso:country": "GB",
    "wof:name": "SK6 6NA",
    "wof:placetype": "postalcode"
  },
  "geometry": {"coordinates":[-2.067784,53.39638],"type":"Point"}
}
