{
  "type": "Feature",
  "properties": {
    "iso:country":"GB",
    "wof:name":"SK6 6NA",
    "wof:placetype":"postalcode"
},
  "geometry": {"coordinates":[-2.06778443396197,53.39637983785899],"type":"Point"}
}