{
  "type": "Feature",
  "properties": {
    "iso:country": "GB",
    "wof:name": "BH23 2NE",
    "wof:placetype": "postalcode"
  },
  "geometry": {"coordinates":[-1.787832,50.748074],"type":"Point"}
}
