{
  "type": "Feature",
  "properties": {
    "iso:country":"GB",
    "wof:name":"BH23 2NE",
    "wof:placetype":"postalcode"
},
  "geometry": {"coordinates":[-1.78783168579978,50.7480743933661],"type":"Point"}
}