{
  "type": "Feature",
  "properties": {
    "iso:country":"GB",
    "wof:name":"TR20 9HZ",
    "wof:placetype":"postalcode"
},
  "geometry": {"coordinates":[-5.43494435234248,50.12666473321692],"type":"Point"}
}