{
  "type": "Feature",
  "properties": {
    "date:inception_lower": "2017-08-01",
    "date:inception_upper": "2017-08-01",
    "iso:country": "GB",
    "wof:name": "CH62 4SW",
    "wof:placetype": "postalcode"
  },
  "geometry": {"coordinates":[-2.987856,53.352407],"type":"Point"}
}
