{
  "type": "Feature",
  "properties": {
    "date:inception_lower":"1980-01-01",
    "date:inception_upper":"1980-01-31",
    "iso:country":"GB",
    "wof:name":"RH5 5EX",
    "wof:placetype":"postalcode"
},
  "geometry": {"coordinates":[-0.326511,51.149756],"type":"Point"}
}