{
  "type": "Feature",
  "properties": {
    "iso:country":"GB",
    "wof:name":"G66 1DL",
    "wof:placetype":"postalcode"
},
  "geometry": {"coordinates":[-4.16064115179739,55.93908298618605],"type":"Point"}
}