{
  "type": "Feature",
  "properties": {
    "iso:country":"GB",
    "wof:name":"BA3 3EG",
    "wof:placetype":"postalcode"
},
  "geometry": {"coordinates":[-2.44899668957489,51.29648697308457],"type":"Point"}
}