{
  "type": "Feature",
  "properties": {
    "iso:country": "GB",
    "wof:name": "BA3 3EG",
    "wof:placetype": "postalcode"
  },
  "geometry": {"coordinates":[-2.448997,51.296487],"type":"Point"}
}
