{
  "type": "Feature",
  "properties": {
    "iso:country":"GB",
    "wof:name":"AB16 5QU",
    "wof:placetype":"postalcode"
},
  "geometry": {"coordinates":[-2.1618696805666,57.16119869199679],"type":"Point"}
}