{
  "type": "Feature",
  "properties": {
    "date:inception_lower": "2022-06-01",
    "date:inception_upper": "2022-06-01",
    "iso:country": "GB",
    "wof:name": "LN4 3FL",
    "wof:placetype": "postalcode"
  },
  "geometry": {"coordinates":[-0.408914,53.144071],"type":"Point"}
}
