{
  "type": "Feature",
  "properties": {
    "iso:country":"GB",
    "wof:name":"DE3 9LZ",
    "wof:placetype":"postalcode"
},
  "geometry": {"coordinates":[-1.53300233764612,52.91353213777656],"type":"Point"}
}