{
  "type": "Feature",
  "properties": {
    "iso:country": "GB",
    "wof:name": "DE3 9LZ",
    "wof:placetype": "postalcode"
  },
  "geometry": {"coordinates":[-1.533002,52.913532],"type":"Point"}
}
