{
  "type": "Feature",
  "properties": {
    "date:inception_lower": "1980-01-01",
    "date:inception_upper": "1980-01-01",
    "iso:country": "GB",
    "wof:name": "B68 9RZ",
    "wof:placetype": "postalcode"
  },
  "geometry": {"coordinates":[-1.998498,52.493447],"type":"Point"}
}
