{
  "type": "Feature",
  "properties": {
    "iso:country": "GB",
    "wof:name": "B68 9RZ",
    "wof:placetype": "postalcode"
  },
  "geometry": {"coordinates":[-1.998498,52.493447],"type":"Point"}
}
