{
  "type": "Feature",
  "properties": {
    "iso:country":"GB",
    "wof:name":"B68 9RZ",
    "wof:placetype":"postalcode"
},
  "geometry": {"coordinates":[-1.99849815063993,52.49344716544329],"type":"Point"}
}