{
  "type": "Feature",
  "properties": {
    "iso:country": "GB",
    "wof:name": "PE23 4DS",
    "wof:placetype": "postalcode"
  },
  "geometry": {"coordinates":[0.052909,53.183426],"type":"Point"}
}
