{
  "type": "Feature",
  "properties": {
    "iso:country":"GB",
    "wof:name":"PE23 4DS",
    "wof:placetype":"postalcode"
},
  "geometry": {"coordinates":[0.05290875427119,53.18342648377375],"type":"Point"}
}