{
  "type": "Feature",
  "properties": {
    "iso:country":"GB",
    "wof:name":"CF32 9UD",
    "wof:placetype":"postalcode"
},
  "geometry": {"coordinates":[-3.58214607005765,51.54015045289633],"type":"Point"}
}