{
  "type": "Feature",
  "properties": {
    "iso:country": "GB",
    "wof:name": "CF32 9UD",
    "wof:placetype": "postalcode"
  },
  "geometry": {"coordinates":[-3.582162,51.540143],"type":"Point"}
}
