{
  "type": "Feature",
  "properties": {
    "date:inception_lower": "2021-05-01",
    "date:inception_upper": "2021-05-01",
    "iso:country": "GB",
    "wof:name": "G33 6PF",
    "wof:placetype": "postalcode"
  },
  "geometry": {"coordinates":[-4.174885,55.89062],"type":"Point"}
}
